
main <./moonscript/transform/accumulator.lua:0,0> (74 instructions, 296 bytes at 0x7fc9f0c068d0)
0+ params, 15 slots, 0 upvalues, 12 locals, 29 constants, 7 functions
	1	[1]	GETGLOBAL	0 -1	; require
	2	[1]	LOADK    	1 -2	; "moonscript.types"
	3	[1]	CALL     	0 2 2
	4	[2]	LOADNIL  	1 3
	5	[3]	GETTABLE 	4 0 -3	; "build"
	6	[3]	GETTABLE 	5 0 -4	; "ntype"
	7	[3]	GETTABLE 	3 0 -5	; "NOOP"
	8	[3]	MOVE     	2 5
	9	[3]	MOVE     	1 4
	10	[4]	LOADNIL  	4 4
	11	[5]	GETGLOBAL	5 -1	; require
	12	[5]	LOADK    	6 -6	; "moonscript.transform.names"
	13	[5]	CALL     	5 2 2
	14	[5]	GETTABLE 	4 5 -7	; "NameProxy"
	15	[6]	LOADNIL  	5 5
	16	[7]	GETGLOBAL	6 -8	; table
	17	[7]	GETTABLE 	5 6 -9	; "insert"
	18	[8]	LOADNIL  	6 6
	19	[18]	CLOSURE  	6 0	; 0x7fc9f0c070f0
	20	[18]	MOVE     	0 2
	21	[18]	MOVE     	0 6
	22	[19]	LOADNIL  	7 7
	23	[20]	GETGLOBAL	8 -1	; require
	24	[20]	LOADK    	9 -10	; "moonscript.transform.statements"
	25	[20]	CALL     	8 2 2
	26	[20]	GETTABLE 	7 8 -11	; "transform_last_stm"
	27	[21]	LOADNIL  	8 9
	28	[24]	NEWTABLE 	10 0 4
	29	[25]	NEWTABLE 	11 0 3
	30	[26]	SETTABLE 	11 -13 -14	; "for" 4
	31	[27]	SETTABLE 	11 -15 -16	; "while" 3
	32	[28]	SETTABLE 	11 -17 -14	; "foreach" 4
	33	[29]	SETTABLE 	10 -12 11	; "body_idx" -
	34	[34]	CLOSURE  	11 1	; 0x7fc9f0c07070
	35	[34]	MOVE     	0 2
	36	[34]	SETTABLE 	10 -18 11	; "convert" -
	37	[45]	CLOSURE  	11 2	; 0x7fc9f0c07840
	38	[45]	MOVE     	0 1
	39	[45]	MOVE     	0 3
	40	[45]	SETTABLE 	10 -19 11	; "wrap" -
	41	[81]	CLOSURE  	11 3	; 0x7fc9f0c08160
	42	[81]	MOVE     	0 6
	43	[81]	MOVE     	0 0
	44	[81]	MOVE     	0 7
	45	[81]	MOVE     	0 1
	46	[81]	MOVE     	0 4
	47	[81]	MOVE     	0 5
	48	[81]	SETTABLE 	10 -20 11	; "mutate_body" -
	49	[83]	SETTABLE 	10 -21 10	; "__index" -
	50	[84]	GETGLOBAL	11 -22	; setmetatable
	51	[84]	NEWTABLE 	12 0 3
	52	[89]	CLOSURE  	13 4	; 0x7fc9f0c08460
	53	[89]	MOVE     	0 4
	54	[89]	SETTABLE 	12 -23 13	; "__init" -
	55	[90]	SETTABLE 	12 -24 10	; "__base" -
	56	[91]	SETTABLE 	12 -25 -26	; "__name" "Accumulator"
	57	[92]	NEWTABLE 	13 0 2
	58	[93]	SETTABLE 	13 -21 10	; "__index" -
	59	[98]	CLOSURE  	14 5	; 0x7fc9f0c08c20
	60	[98]	MOVE     	0 10
	61	[98]	SETTABLE 	13 -27 14	; "__call" -
	62	[84]	CALL     	11 3 2
	63	[99]	MOVE     	9 11
	64	[100]	SETTABLE 	10 -28 9	; "__class" -
	65	[101]	MOVE     	8 9
	66	[101]	CLOSE    	9
	67	[103]	LOADNIL  	9 9
	68	[106]	CLOSURE  	9 6	; 0x7fc9f0c067c0
	69	[106]	MOVE     	0 8
	70	[107]	NEWTABLE 	10 0 2
	71	[108]	SETTABLE 	10 -26 8	; "Accumulator" -
	72	[109]	SETTABLE 	10 -29 9	; "default_accumulator" -
	73	[110]	RETURN   	10 2
	74	[110]	RETURN   	0 1

function <./moonscript/transform/accumulator.lua:9,18> (18 instructions, 72 bytes at 0x7fc9f0c070f0)
1 param, 3 slots, 2 upvalues, 1 local, 3 constants, 0 functions
	1	[10]	LEN      	1 0
	2	[10]	EQ       	1 1 -1	; - 1
	3	[10]	JMP      	2	; to 6
	4	[11]	LOADBOOL 	1 0 0
	5	[11]	RETURN   	1 2
	6	[13]	GETUPVAL 	1 0	; ntype
	7	[13]	MOVE     	2 0
	8	[13]	CALL     	1 2 2
	9	[13]	EQ       	0 -2 1	; "group" -
	10	[13]	JMP      	5	; to 16
	11	[14]	GETUPVAL 	1 1	; is_singular
	12	[14]	GETTABLE 	2 0 -3	; 2
	13	[14]	TAILCALL 	1 2 0
	14	[14]	RETURN   	1 0
	15	[14]	JMP      	2	; to 18
	16	[16]	GETTABLE 	1 0 -1	; 1
	17	[16]	RETURN   	1 2
	18	[18]	RETURN   	0 1

function <./moonscript/transform/accumulator.lua:30,34> (14 instructions, 56 bytes at 0x7fc9f0c07070)
2 params, 6 slots, 1 upvalue, 3 locals, 3 constants, 0 functions
	1	[31]	GETTABLE 	2 0 -1	; "body_idx"
	2	[31]	GETUPVAL 	3 0	; ntype
	3	[31]	MOVE     	4 1
	4	[31]	CALL     	3 2 2
	5	[31]	GETTABLE 	2 2 3
	6	[32]	SELF     	3 0 -2	; "mutate_body"
	7	[32]	GETTABLE 	5 1 2
	8	[32]	CALL     	3 3 2
	9	[32]	SETTABLE 	1 2 3
	10	[33]	SELF     	3 0 -3	; "wrap"
	11	[33]	MOVE     	5 1
	12	[33]	TAILCALL 	3 3 0
	13	[33]	RETURN   	3 0
	14	[34]	RETURN   	0 1

function <./moonscript/transform/accumulator.lua:35,45> (29 instructions, 116 bytes at 0x7fc9f0c07840)
3 params, 9 slots, 2 upvalues, 3 locals, 7 constants, 0 functions
	1	[36]	EQ       	0 2 -1	; - nil
	2	[36]	JMP      	1	; to 4
	3	[37]	LOADK    	2 -2	; "block_exp"
	4	[39]	GETUPVAL 	3 0	; build
	5	[39]	GETTABLE 	3 3 2
	6	[39]	NEWTABLE 	4 4 0
	7	[40]	GETUPVAL 	5 0	; build
	8	[40]	GETTABLE 	5 5 -3	; "assign_one"
	9	[40]	GETTABLE 	6 0 -4	; "accum_name"
	10	[40]	GETUPVAL 	7 0	; build
	11	[40]	GETTABLE 	7 7 -5	; "table"
	12	[40]	CALL     	7 1 0
	13	[40]	CALL     	5 0 2
	14	[41]	GETUPVAL 	6 0	; build
	15	[41]	GETTABLE 	6 6 -3	; "assign_one"
	16	[41]	GETTABLE 	7 0 -6	; "len_name"
	17	[41]	LOADK    	8 -7	; 1
	18	[41]	CALL     	6 3 2
	19	[42]	MOVE     	7 1
	20	[43]	EQ       	0 2 -2	; - "block_exp"
	21	[43]	JMP      	3	; to 25
	22	[43]	GETTABLE 	8 0 -4	; "accum_name"
	23	[43]	TEST     	8 0 1
	24	[43]	JMP      	1	; to 26
	25	[43]	GETUPVAL 	8 1	; NOOP
	26	[44]	SETLIST  	4 4 1	; 1
	27	[39]	TAILCALL 	3 2 0
	28	[44]	RETURN   	3 0
	29	[45]	RETURN   	0 1

function <./moonscript/transform/accumulator.lua:46,81> (51 instructions, 204 bytes at 0x7fc9f0c08160)
2 params, 11 slots, 6 upvalues, 5 locals, 10 constants, 1 function
	1	[47]	GETUPVAL 	2 0	; is_singular
	2	[47]	MOVE     	3 1
	3	[47]	CALL     	2 2 2
	4	[48]	LOADNIL  	3 3
	5	[49]	TEST     	2 0 0
	6	[49]	JMP      	10	; to 17
	7	[49]	GETUPVAL 	4 1	; types
	8	[49]	GETTABLE 	4 4 -1	; "is_value"
	9	[49]	MOVE     	5 2
	10	[49]	CALL     	4 2 2
	11	[49]	TEST     	4 0 0
	12	[49]	JMP      	4	; to 17
	13	[50]	NEWTABLE 	4 0 0
	14	[50]	MOVE     	1 4
	15	[51]	MOVE     	3 2
	16	[51]	JMP      	9	; to 26
	17	[53]	GETUPVAL 	4 2	; transform_last_stm
	18	[53]	MOVE     	5 1
	19	[67]	CLOSURE  	6 0	; 0x7fc9f0c07e60
	20	[67]	GETUPVAL 	0 1	; types
	21	[67]	GETUPVAL 	0 3	; build
	22	[67]	MOVE     	0 0
	23	[53]	CALL     	4 3 2
	24	[67]	MOVE     	1 4
	25	[68]	GETTABLE 	3 0 -2	; "value_name"
	26	[70]	NEWTABLE 	4 2 0
	27	[71]	GETUPVAL 	5 3	; build
	28	[71]	GETTABLE 	5 5 -3	; "assign_one"
	29	[71]	GETUPVAL 	6 4	; NameProxy
	30	[71]	GETTABLE 	6 6 -4	; "index"
	31	[71]	GETTABLE 	7 0 -5	; "accum_name"
	32	[71]	GETTABLE 	8 0 -6	; "len_name"
	33	[71]	CALL     	6 3 2
	34	[71]	MOVE     	7 3
	35	[71]	CALL     	5 3 2
	36	[71]	NEWTABLE 	6 4 0
	37	[73]	LOADK    	7 -7	; "update"
	38	[74]	GETTABLE 	8 0 -6	; "len_name"
	39	[75]	LOADK    	9 -8	; "+="
	40	[77]	LOADK    	10 -9	; 1
	41	[77]	SETLIST  	6 4 1	; 1
	42	[78]	SETLIST  	4 2 1	; 1
	43	[79]	GETUPVAL 	5 5	; insert
	44	[79]	MOVE     	6 1
	45	[79]	GETUPVAL 	7 3	; build
	46	[79]	GETTABLE 	7 7 -10	; "group"
	47	[79]	MOVE     	8 4
	48	[79]	CALL     	7 2 0
	49	[79]	CALL     	5 0 1
	50	[80]	RETURN   	1 2
	51	[81]	RETURN   	0 1

function <./moonscript/transform/accumulator.lua:53,67> (29 instructions, 116 bytes at 0x7fc9f0c07e60)
1 param, 7 slots, 3 upvalues, 1 local, 5 constants, 0 functions
	1	[54]	GETUPVAL 	1 0	; types
	2	[54]	GETTABLE 	1 1 -1	; "is_value"
	3	[54]	MOVE     	2 0
	4	[54]	CALL     	1 2 2
	5	[54]	TEST     	1 0 0
	6	[54]	JMP      	8	; to 15
	7	[55]	GETUPVAL 	1 1	; build
	8	[55]	GETTABLE 	1 1 -2	; "assign_one"
	9	[55]	GETUPVAL 	2 2	; self
	10	[55]	GETTABLE 	2 2 -3	; "value_name"
	11	[55]	MOVE     	3 0
	12	[55]	TAILCALL 	1 3 0
	13	[55]	RETURN   	1 0
	14	[55]	JMP      	14	; to 29
	15	[57]	GETUPVAL 	1 1	; build
	16	[57]	GETTABLE 	1 1 -4	; "group"
	17	[57]	NEWTABLE 	2 2 0
	18	[57]	NEWTABLE 	3 2 0
	19	[59]	LOADK    	4 -5	; "declare"
	20	[59]	NEWTABLE 	5 1 0
	21	[61]	GETUPVAL 	6 2	; self
	22	[62]	GETTABLE 	6 6 -3	; "value_name"
	23	[62]	SETLIST  	5 1 1	; 1
	24	[63]	SETLIST  	3 2 1	; 1
	25	[65]	MOVE     	4 0
	26	[65]	SETLIST  	2 2 1	; 1
	27	[57]	TAILCALL 	1 2 0
	28	[65]	RETURN   	1 0
	29	[67]	RETURN   	0 1

function <./moonscript/transform/accumulator.lua:85,89> (13 instructions, 52 bytes at 0x7fc9f0c08460)
2 params, 4 slots, 1 upvalue, 2 locals, 6 constants, 0 functions
	1	[86]	GETUPVAL 	2 0	; NameProxy
	2	[86]	LOADK    	3 -2	; "accum"
	3	[86]	CALL     	2 2 2
	4	[86]	SETTABLE 	0 -1 2	; "accum_name" -
	5	[87]	GETUPVAL 	2 0	; NameProxy
	6	[87]	LOADK    	3 -4	; "value"
	7	[87]	CALL     	2 2 2
	8	[87]	SETTABLE 	0 -3 2	; "value_name" -
	9	[88]	GETUPVAL 	2 0	; NameProxy
	10	[88]	LOADK    	3 -6	; "len"
	11	[88]	CALL     	2 2 2
	12	[88]	SETTABLE 	0 -5 2	; "len_name" -
	13	[89]	RETURN   	0 1

function <./moonscript/transform/accumulator.lua:94,98> (10 instructions, 40 bytes at 0x7fc9f0c08c20)
1+ param, 6 slots, 1 upvalue, 3 locals, 2 constants, 0 functions
	1	[95]	GETGLOBAL	2 -1	; setmetatable
	2	[95]	NEWTABLE 	3 0 0
	3	[95]	GETUPVAL 	4 0	; _base_0
	4	[95]	CALL     	2 3 2
	5	[96]	GETTABLE 	3 0 -2	; "__init"
	6	[96]	MOVE     	4 2
	7	[96]	VARARG   	5 0
	8	[96]	CALL     	3 0 1
	9	[97]	RETURN   	2 2
	10	[98]	RETURN   	0 1

function <./moonscript/transform/accumulator.lua:104,106> (7 instructions, 28 bytes at 0x7fc9f0c067c0)
2 params, 5 slots, 1 upvalue, 2 locals, 1 constant, 0 functions
	1	[105]	GETUPVAL 	2 0	; Accumulator
	2	[105]	CALL     	2 1 2
	3	[105]	SELF     	2 2 -1	; "convert"
	4	[105]	MOVE     	4 1
	5	[105]	TAILCALL 	2 3 0
	6	[105]	RETURN   	2 0
	7	[106]	RETURN   	0 1
