
main <./moonscript/cmd/args.lua:0,0> (15 instructions, 60 bytes at 0x7fdbf6c068c0)
0+ params, 4 slots, 0 upvalues, 3 locals, 5 constants, 2 functions
	1	[2]	GETGLOBAL	1 -1	; require
	2	[2]	LOADK    	2 -2	; "moonscript.util"
	3	[2]	CALL     	1 2 2
	4	[2]	GETTABLE 	0 1 -3	; "unpack"
	5	[3]	LOADNIL  	1 1
	6	[23]	CLOSURE  	1 0	; 0x7fdbf6c06a80
	7	[23]	MOVE     	0 0
	8	[24]	LOADNIL  	2 2
	9	[65]	CLOSURE  	2 1	; 0x7fdbf6c072b0
	10	[65]	MOVE     	0 1
	11	[66]	NEWTABLE 	3 0 2
	12	[67]	SETTABLE 	3 -4 2	; "parse_arguments" -
	13	[68]	SETTABLE 	3 -5 1	; "parse_spec" -
	14	[69]	RETURN   	3 2
	15	[69]	RETURN   	0 1

function <./moonscript/cmd/args.lua:4,23> (42 instructions, 168 bytes at 0x7fdbf6c06a80)
1 param, 12 slots, 1 upvalue, 8 locals, 12 constants, 0 functions
	1	[6]	GETGLOBAL	3 -1	; type
	2	[6]	MOVE     	4 0
	3	[6]	CALL     	3 2 2
	4	[6]	EQ       	0 3 -2	; - "table"
	5	[6]	JMP      	6	; to 12
	6	[7]	GETUPVAL 	3 0	; unpack
	7	[7]	MOVE     	4 0
	8	[7]	CALL     	3 2 2
	9	[7]	MOVE     	2 0
	10	[7]	MOVE     	1 3
	11	[7]	JMP      	4	; to 16
	12	[9]	MOVE     	3 0
	13	[9]	NEWTABLE 	4 0 0
	14	[9]	MOVE     	2 4
	15	[9]	MOVE     	1 3
	16	[11]	GETGLOBAL	3 -3	; assert
	17	[11]	LOADK    	4 -4	; "no flags for arguments"
	18	[11]	CALL     	3 2 1
	19	[12]	NEWTABLE 	3 0 0
	20	[13]	SELF     	4 1 -5	; "gmatch"
	21	[13]	LOADK    	6 -6	; "%w:?"
	22	[13]	CALL     	4 3 4
	23	[13]	JMP      	15	; to 39
	24	[14]	SELF     	8 7 -7	; "match"
	25	[14]	LOADK    	10 -8	; ":$"
	26	[14]	CALL     	8 3 2
	27	[14]	TEST     	8 0 0
	28	[14]	JMP      	8	; to 37
	29	[15]	SELF     	8 7 -9	; "sub"
	30	[15]	LOADK    	10 -10	; 1
	31	[15]	LOADK    	11 -10	; 1
	32	[15]	CALL     	8 4 2
	33	[15]	NEWTABLE 	9 0 1
	34	[16]	SETTABLE 	9 -11 -12	; "value" true
	35	[17]	SETTABLE 	3 8 9
	36	[17]	JMP      	2	; to 39
	37	[19]	NEWTABLE 	8 0 0
	38	[19]	SETTABLE 	3 7 8
	39	[13]	TFORLOOP 	4 1
	40	[20]	JMP      	-17	; to 24
	41	[22]	RETURN   	3 2
	42	[23]	RETURN   	0 1

function <./moonscript/cmd/args.lua:25,65> (52 instructions, 208 bytes at 0x7fdbf6c072b0)
2 params, 20 slots, 1 upvalue, 18 locals, 8 constants, 0 functions
	1	[26]	GETUPVAL 	2 0	; parse_spec
	2	[26]	MOVE     	3 0
	3	[26]	CALL     	2 2 2
	4	[26]	MOVE     	0 2
	5	[27]	NEWTABLE 	2 0 0
	6	[28]	NEWTABLE 	3 0 0
	7	[29]	LOADNIL  	4 4
	8	[30]	LOADK    	5 -1	; 1
	9	[30]	LEN      	6 1
	10	[30]	LOADK    	7 -1	; 1
	11	[30]	FORPREP  	5 36	; to 48
	12	[31]	LOADBOOL 	9 0 0
	13	[33]	GETTABLE 	10 1 8
	14	[34]	NEWTABLE 	11 0 0
	15	[35]	TEST     	4 0 0
	16	[35]	JMP      	3	; to 20
	17	[36]	SETTABLE 	2 4 10
	18	[37]	LOADBOOL 	9 1 0
	19	[38]	JMP      	25	; to 45
	20	[41]	SELF     	12 10 -2	; "match"
	21	[41]	LOADK    	14 -3	; "-(%w+)"
	22	[41]	CALL     	12 3 2
	23	[42]	TEST     	12 0 0
	24	[42]	JMP      	14	; to 39
	25	[44]	GETTABLE 	13 0 12
	26	[45]	TEST     	13 0 0
	27	[45]	JMP      	2	; to 30
	28	[46]	SETTABLE 	2 13 -4	; - true
	29	[46]	JMP      	7	; to 37
	30	[48]	SELF     	14 12 -5	; "gmatch"
	31	[48]	LOADK    	16 -6	; "."
	32	[48]	CALL     	14 3 4
	33	[48]	JMP      	1	; to 35
	34	[49]	SETTABLE 	2 17 -4	; - true
	35	[48]	TFORLOOP 	14 1
	36	[49]	JMP      	-3	; to 34
	37	[53]	LOADBOOL 	9 1 0
	38	[54]	JMP      	6	; to 45
	39	[57]	GETGLOBAL	12 -7	; table
	40	[57]	GETTABLE 	12 12 -8	; "insert"
	41	[57]	MOVE     	13 3
	42	[57]	MOVE     	14 10
	43	[57]	CALL     	12 3 1
	44	[58]	LOADBOOL 	9 1 0
	45	[60]	TEST     	9 0 1
	46	[60]	JMP      	1	; to 48
	47	[61]	JMP      	1	; to 49
	48	[30]	FORLOOP  	5 -37	; to 12
	49	[64]	MOVE     	5 2
	50	[64]	MOVE     	6 3
	51	[64]	RETURN   	5 3
	52	[65]	RETURN   	0 1
