
main <./moonscript/base.lua:0,0> (74 instructions, 296 bytes at 0x7fdeb0c068a0)
0+ params, 22 slots, 0 upvalues, 22 locals, 26 constants, 8 functions
	1	[1]	GETGLOBAL	0 -1	; require
	2	[1]	LOADK    	1 -2	; "moonscript.compile"
	3	[1]	CALL     	0 2 2
	4	[2]	GETGLOBAL	1 -1	; require
	5	[2]	LOADK    	2 -3	; "moonscript.parse"
	6	[2]	CALL     	1 2 2
	7	[3]	LOADNIL  	2 4
	8	[5]	GETGLOBAL	5 -4	; table
	9	[6]	GETTABLE 	6 5 -5	; "concat"
	10	[6]	GETTABLE 	7 5 -6	; "insert"
	11	[6]	GETTABLE 	4 5 -7	; "remove"
	12	[6]	MOVE     	3 7
	13	[6]	MOVE     	2 6
	14	[8]	LOADNIL  	5 8
	15	[10]	GETGLOBAL	9 -1	; require
	16	[10]	LOADK    	10 -8	; "moonscript.util"
	17	[10]	CALL     	9 2 2
	18	[11]	GETTABLE 	10 9 -9	; "split"
	19	[11]	GETTABLE 	11 9 -10	; "dump"
	20	[11]	GETTABLE 	12 9 -11	; "get_options"
	21	[11]	GETTABLE 	8 9 -12	; "unpack"
	22	[11]	MOVE     	7 12
	23	[11]	MOVE     	6 11
	24	[11]	MOVE     	5 10
	25	[13]	NEWTABLE 	9 0 2
	26	[14]	GETGLOBAL	10 -13	; loadstring
	27	[14]	SETTABLE 	9 -13 10	; "loadstring" -
	28	[15]	GETGLOBAL	10 -14	; load
	29	[15]	SETTABLE 	9 -14 10	; "load" -
	30	[17]	LOADNIL  	10 19
	31	[18]	LOADK    	10 -15	; "/"
	32	[19]	GETGLOBAL	20 -1	; require
	33	[19]	LOADK    	21 -16	; "moonscript.line_tables"
	34	[19]	CALL     	20 2 2
	35	[19]	MOVE     	11 20
	36	[47]	CLOSURE  	12 0	; 0x7fdeb0c06cf0
	37	[47]	MOVE     	0 5
	38	[47]	MOVE     	0 2
	39	[65]	CLOSURE  	13 1	; 0x7fdeb0c07680
	40	[65]	MOVE     	0 1
	41	[65]	MOVE     	0 0
	42	[86]	CLOSURE  	14 2	; 0x7fdeb0c07f10
	43	[86]	MOVE     	0 10
	44	[86]	MOVE     	0 15
	45	[101]	CLOSURE  	15 3	; 0x7fdeb0c08340
	46	[101]	MOVE     	0 7
	47	[101]	MOVE     	0 13
	48	[101]	MOVE     	0 11
	49	[101]	MOVE     	0 9
	50	[101]	MOVE     	0 8
	51	[110]	CLOSURE  	16 4	; 0x7fdeb0c08b80
	52	[110]	MOVE     	0 15
	53	[114]	CLOSURE  	17 5	; 0x7fdeb0c08fc0
	54	[114]	MOVE     	0 16
	55	[131]	CLOSURE  	18 6	; 0x7fdeb0c090c0
	56	[131]	MOVE     	0 12
	57	[131]	MOVE     	0 14
	58	[131]	MOVE     	0 3
	59	[141]	CLOSURE  	19 7	; 0x7fdeb0c09620
	60	[141]	MOVE     	0 14
	61	[141]	MOVE     	0 4
	62	[142]	NEWTABLE 	20 0 10
	63	[143]	SETTABLE 	20 -17 -18	; "_NAME" "moonscript"
	64	[144]	SETTABLE 	20 -19 18	; "insert_loader" -
	65	[145]	SETTABLE 	20 -20 19	; "remove_loader" -
	66	[146]	SETTABLE 	20 -21 13	; "to_lua" -
	67	[147]	SETTABLE 	20 -22 14	; "moon_loader" -
	68	[148]	SETTABLE 	20 -23 10	; "dirsep" -
	69	[149]	SETTABLE 	20 -24 17	; "dofile" -
	70	[150]	SETTABLE 	20 -25 16	; "loadfile" -
	71	[151]	SETTABLE 	20 -13 15	; "loadstring" -
	72	[152]	SETTABLE 	20 -26 12	; "create_moonpath" -
	73	[153]	RETURN   	20 2
	74	[153]	RETURN   	0 1

function <./moonscript/base.lua:20,47> (36 instructions, 144 bytes at 0x7fdeb0c06cf0)
1 param, 14 slots, 2 upvalues, 13 locals, 5 constants, 0 functions
	1	[23]	NEWTABLE 	2 0 0
	2	[24]	LOADK    	3 -1	; 1
	3	[25]	GETUPVAL 	4 0	; split
	4	[25]	MOVE     	5 0
	5	[25]	LOADK    	6 -2	; ";"
	6	[25]	CALL     	4 3 2
	7	[26]	LOADK    	5 -1	; 1
	8	[26]	LEN      	6 4
	9	[26]	LOADK    	7 -1	; 1
	10	[26]	FORPREP  	5 18	; to 29
	11	[27]	LOADBOOL 	9 0 0
	12	[29]	GETTABLE 	10 4 8
	13	[30]	SELF     	11 10 -3	; "match"
	14	[30]	LOADK    	13 -4	; "^(.-)%.lua$"
	15	[30]	CALL     	11 3 2
	16	[31]	TEST     	11 0 1
	17	[31]	JMP      	2	; to 20
	18	[32]	LOADBOOL 	9 1 0
	19	[33]	JMP      	6	; to 26
	20	[35]	MOVE     	12 11
	21	[35]	LOADK    	13 -5	; ".moon"
	22	[35]	CONCAT   	12 12 13
	23	[36]	SETTABLE 	2 3 12
	24	[37]	ADD      	3 3 -1	; - 1
	25	[38]	LOADBOOL 	9 1 0
	26	[40]	TEST     	9 0 1
	27	[40]	JMP      	1	; to 29
	28	[41]	JMP      	1	; to 30
	29	[26]	FORLOOP  	5 -19	; to 11
	30	[44]	MOVE     	1 2
	31	[46]	GETUPVAL 	2 1	; concat
	32	[46]	MOVE     	3 1
	33	[46]	LOADK    	4 -2	; ";"
	34	[46]	TAILCALL 	2 3 0
	35	[46]	RETURN   	2 0
	36	[47]	RETURN   	0 1

function <./moonscript/base.lua:48,65> (46 instructions, 184 bytes at 0x7fdeb0c07680)
2 params, 12 slots, 2 upvalues, 8 locals, 7 constants, 0 functions
	1	[49]	EQ       	0 1 -1	; - nil
	2	[49]	JMP      	2	; to 5
	3	[50]	NEWTABLE 	2 0 0
	4	[50]	MOVE     	1 2
	5	[52]	GETGLOBAL	2 -3	; type
	6	[52]	MOVE     	3 0
	7	[52]	CALL     	2 2 2
	8	[52]	EQ       	1 -2 2	; "string" -
	9	[52]	JMP      	9	; to 19
	10	[53]	GETGLOBAL	2 -3	; type
	11	[53]	MOVE     	3 0
	12	[53]	CALL     	2 2 2
	13	[54]	LOADNIL  	3 3
	14	[54]	LOADK    	4 -4	; "expecting string (got "
	15	[54]	MOVE     	5 2
	16	[54]	LOADK    	6 -5	; ")"
	17	[54]	CONCAT   	4 4 6
	18	[54]	RETURN   	3 3
	19	[56]	GETUPVAL 	2 0	; parse
	20	[56]	GETTABLE 	2 2 -2	; "string"
	21	[56]	MOVE     	3 0
	22	[56]	CALL     	2 2 3
	23	[57]	TEST     	2 0 1
	24	[57]	JMP      	3	; to 28
	25	[58]	LOADNIL  	4 4
	26	[58]	MOVE     	5 3
	27	[58]	RETURN   	4 3
	28	[60]	GETUPVAL 	4 1	; compile
	29	[60]	GETTABLE 	4 4 -6	; "tree"
	30	[60]	MOVE     	5 2
	31	[60]	MOVE     	6 1
	32	[60]	CALL     	4 3 4
	33	[61]	TEST     	4 0 1
	34	[61]	JMP      	8	; to 43
	35	[62]	LOADNIL  	7 7
	36	[62]	GETUPVAL 	8 1	; compile
	37	[62]	GETTABLE 	8 8 -7	; "format_error"
	38	[62]	MOVE     	9 5
	39	[62]	MOVE     	10 6
	40	[62]	MOVE     	11 0
	41	[62]	CALL     	8 4 0
	42	[62]	RETURN   	7 0
	43	[64]	MOVE     	7 4
	44	[64]	MOVE     	8 5
	45	[64]	RETURN   	7 3
	46	[65]	RETURN   	0 1

function <./moonscript/base.lua:66,86> (54 instructions, 216 bytes at 0x7fdeb0c07f10)
1 param, 12 slots, 2 upvalues, 11 locals, 17 constants, 0 functions
	1	[67]	SELF     	1 0 -1	; "gsub"
	2	[67]	LOADK    	3 -2	; "%."
	3	[67]	GETUPVAL 	4 0	; dirsep
	4	[67]	CALL     	1 4 2
	5	[68]	LOADNIL  	2 3
	6	[69]	GETGLOBAL	4 -3	; package
	7	[69]	GETTABLE 	4 4 -4	; "moonpath"
	8	[69]	SELF     	4 4 -5	; "gmatch"
	9	[69]	LOADK    	6 -6	; "[^;]+"
	10	[69]	CALL     	4 3 4
	11	[69]	JMP      	13	; to 25
	12	[70]	SELF     	8 7 -1	; "gsub"
	13	[70]	LOADK    	10 -7	; "?"
	14	[70]	MOVE     	11 1
	15	[70]	CALL     	8 4 2
	16	[70]	MOVE     	3 8
	17	[71]	GETGLOBAL	8 -8	; io
	18	[71]	GETTABLE 	8 8 -9	; "open"
	19	[71]	MOVE     	9 3
	20	[71]	CALL     	8 2 2
	21	[71]	MOVE     	2 8
	22	[72]	TEST     	2 0 0
	23	[72]	JMP      	1	; to 25
	24	[73]	JMP      	2	; to 27
	25	[69]	TFORLOOP 	4 1
	26	[74]	JMP      	-15	; to 12
	27	[76]	TEST     	2 0 0
	28	[76]	JMP      	22	; to 51
	29	[77]	SELF     	4 2 -10	; "read"
	30	[77]	LOADK    	6 -11	; "*a"
	31	[77]	CALL     	4 3 2
	32	[78]	SELF     	5 2 -12	; "close"
	33	[78]	CALL     	5 2 1
	34	[79]	GETUPVAL 	5 1	; loadstring
	35	[79]	MOVE     	6 4
	36	[79]	LOADK    	7 -13	; "@"
	37	[79]	GETGLOBAL	8 -14	; tostring
	38	[79]	MOVE     	9 3
	39	[79]	CALL     	8 2 2
	40	[79]	CONCAT   	7 7 8
	41	[79]	CALL     	5 3 3
	42	[80]	TEST     	5 0 1
	43	[80]	JMP      	6	; to 50
	44	[81]	GETGLOBAL	7 -15	; error
	45	[81]	MOVE     	8 3
	46	[81]	LOADK    	9 -16	; ": "
	47	[81]	MOVE     	10 6
	48	[81]	CONCAT   	8 8 10
	49	[81]	CALL     	7 2 1
	50	[83]	RETURN   	5 2
	51	[85]	LOADNIL  	4 4
	52	[85]	LOADK    	5 -17	; "Could not find moon file"
	53	[85]	RETURN   	4 3
	54	[86]	RETURN   	0 1

function <./moonscript/base.lua:87,101> (36 instructions, 144 bytes at 0x7fdeb0c08340)
0+ params, 15 slots, 5 upvalues, 8 locals, 3 constants, 0 functions
	1	[88]	GETUPVAL 	1 0	; get_options
	2	[88]	VARARG   	2 0
	3	[88]	CALL     	1 0 6
	4	[89]	TEST     	3 0 1
	5	[89]	JMP      	1	; to 7
	6	[89]	LOADK    	3 -1	; "=(moonscript.loadstring)"
	7	[90]	GETUPVAL 	6 1	; to_lua
	8	[90]	MOVE     	7 2
	9	[90]	MOVE     	8 1
	10	[90]	CALL     	6 3 3
	11	[91]	TEST     	6 0 1
	12	[91]	JMP      	3	; to 16
	13	[92]	LOADNIL  	8 8
	14	[92]	MOVE     	9 7
	15	[92]	RETURN   	8 3
	16	[94]	TEST     	3 0 0
	17	[94]	JMP      	2	; to 20
	18	[95]	GETUPVAL 	8 2	; line_tables
	19	[95]	SETTABLE 	8 3 7
	20	[97]	GETUPVAL 	8 3	; lua
	21	[97]	GETTABLE 	8 8 -2	; "loadstring"
	22	[97]	TEST     	8 0 1
	23	[97]	JMP      	2	; to 26
	24	[97]	GETUPVAL 	8 3	; lua
	25	[97]	GETTABLE 	8 8 -3	; "load"
	26	[97]	MOVE     	9 6
	27	[97]	MOVE     	10 3
	28	[97]	GETUPVAL 	11 4	; unpack
	29	[97]	NEWTABLE 	12 2 0
	30	[98]	MOVE     	13 4
	31	[100]	MOVE     	14 5
	32	[100]	SETLIST  	12 2 1	; 1
	33	[97]	CALL     	11 2 0
	34	[97]	TAILCALL 	8 0 0
	35	[100]	RETURN   	8 0
	36	[101]	RETURN   	0 1

function <./moonscript/base.lua:102,110> (27 instructions, 108 bytes at 0x7fdeb0c08b80)
1+ param, 10 slots, 1 upvalue, 5 locals, 8 constants, 0 functions
	1	[103]	GETGLOBAL	2 -1	; io
	2	[103]	GETTABLE 	2 2 -2	; "open"
	3	[103]	MOVE     	3 0
	4	[103]	CALL     	2 2 3
	5	[104]	TEST     	2 0 1
	6	[104]	JMP      	3	; to 10
	7	[105]	LOADNIL  	4 4
	8	[105]	MOVE     	5 3
	9	[105]	RETURN   	4 3
	10	[107]	GETGLOBAL	4 -3	; assert
	11	[107]	SELF     	5 2 -4	; "read"
	12	[107]	LOADK    	7 -5	; "*a"
	13	[107]	CALL     	5 3 0
	14	[107]	CALL     	4 0 2
	15	[108]	SELF     	5 2 -6	; "close"
	16	[108]	CALL     	5 2 1
	17	[109]	GETUPVAL 	5 0	; loadstring
	18	[109]	MOVE     	6 4
	19	[109]	LOADK    	7 -7	; "@"
	20	[109]	GETGLOBAL	8 -8	; tostring
	21	[109]	MOVE     	9 0
	22	[109]	CALL     	8 2 2
	23	[109]	CONCAT   	7 7 8
	24	[109]	VARARG   	8 0
	25	[109]	TAILCALL 	5 0 0
	26	[109]	RETURN   	5 0
	27	[110]	RETURN   	0 1

function <./moonscript/base.lua:111,114> (9 instructions, 36 bytes at 0x7fdeb0c08fc0)
0+ params, 4 slots, 1 upvalue, 2 locals, 1 constant, 0 functions
	1	[112]	GETGLOBAL	1 -1	; assert
	2	[112]	GETUPVAL 	2 0	; loadfile
	3	[112]	VARARG   	3 0
	4	[112]	CALL     	2 0 0
	5	[112]	CALL     	1 0 2
	6	[113]	MOVE     	2 1
	7	[113]	TAILCALL 	2 1 0
	8	[113]	RETURN   	2 0
	9	[114]	RETURN   	0 1

function <./moonscript/base.lua:115,131> (38 instructions, 152 bytes at 0x7fdeb0c090c0)
1 param, 8 slots, 3 upvalues, 7 locals, 8 constants, 0 functions
	1	[116]	EQ       	0 0 -1	; - nil
	2	[116]	JMP      	1	; to 4
	3	[117]	LOADK    	0 -2	; 2
	4	[119]	GETGLOBAL	1 -3	; package
	5	[119]	GETTABLE 	1 1 -4	; "moonpath"
	6	[119]	TEST     	1 0 1
	7	[119]	JMP      	6	; to 14
	8	[120]	GETGLOBAL	1 -3	; package
	9	[120]	GETUPVAL 	2 0	; create_moonpath
	10	[120]	GETGLOBAL	3 -3	; package
	11	[120]	GETTABLE 	3 3 -5	; "path"
	12	[120]	CALL     	2 2 2
	13	[120]	SETTABLE 	1 -4 2	; "moonpath" -
	14	[122]	GETGLOBAL	1 -3	; package
	15	[122]	GETTABLE 	1 1 -6	; "loaders"
	16	[122]	TEST     	1 0 1
	17	[122]	JMP      	2	; to 20
	18	[122]	GETGLOBAL	1 -3	; package
	19	[122]	GETTABLE 	1 1 -7	; "searchers"
	20	[123]	LOADK    	2 -8	; 1
	21	[123]	LEN      	3 1
	22	[123]	LOADK    	4 -8	; 1
	23	[123]	FORPREP  	2 6	; to 30
	24	[124]	GETTABLE 	6 1 5
	25	[125]	GETUPVAL 	7 1	; moon_loader
	26	[125]	EQ       	0 6 7
	27	[125]	JMP      	2	; to 30
	28	[126]	LOADBOOL 	7 0 0
	29	[126]	RETURN   	7 2
	30	[123]	FORLOOP  	2 -7	; to 24
	31	[129]	GETUPVAL 	2 2	; insert
	32	[129]	MOVE     	3 1
	33	[129]	MOVE     	4 0
	34	[129]	GETUPVAL 	5 1	; moon_loader
	35	[129]	CALL     	2 4 1
	36	[130]	LOADBOOL 	2 1 0
	37	[130]	RETURN   	2 2
	38	[131]	RETURN   	0 1

function <./moonscript/base.lua:132,141> (24 instructions, 96 bytes at 0x7fdeb0c09620)
0 params, 9 slots, 2 upvalues, 6 locals, 4 constants, 0 functions
	1	[133]	GETGLOBAL	0 -1	; package
	2	[133]	GETTABLE 	0 0 -2	; "loaders"
	3	[133]	TEST     	0 0 1
	4	[133]	JMP      	2	; to 7
	5	[133]	GETGLOBAL	0 -1	; package
	6	[133]	GETTABLE 	0 0 -3	; "searchers"
	7	[134]	GETGLOBAL	1 -4	; ipairs
	8	[134]	MOVE     	2 0
	9	[134]	CALL     	1 2 4
	10	[134]	JMP      	9	; to 20
	11	[135]	GETUPVAL 	6 0	; moon_loader
	12	[135]	EQ       	0 5 6
	13	[135]	JMP      	6	; to 20
	14	[136]	GETUPVAL 	6 1	; remove
	15	[136]	MOVE     	7 0
	16	[136]	MOVE     	8 4
	17	[136]	CALL     	6 3 1
	18	[137]	LOADBOOL 	6 1 0
	19	[137]	RETURN   	6 2
	20	[134]	TFORLOOP 	1 2
	21	[138]	JMP      	-11	; to 11
	22	[140]	LOADBOOL 	1 0 0
	23	[140]	RETURN   	1 2
	24	[141]	RETURN   	0 1
