
main <./moonscript/transform/class.lua:0,0> (51 instructions, 204 bytes at 0x7fdec4c068d0)
0+ params, 12 slots, 0 upvalues, 13 locals, 15 constants, 3 functions
	1	[3]	GETGLOBAL	2 -1	; require
	2	[3]	LOADK    	3 -2	; "moonscript.transform.names"
	3	[3]	CALL     	2 2 2
	4	[4]	GETTABLE 	3 2 -3	; "NameProxy"
	5	[4]	GETTABLE 	1 2 -4	; "LocalName"
	6	[4]	MOVE     	0 3
	7	[6]	LOADNIL  	2 2
	8	[7]	GETGLOBAL	3 -1	; require
	9	[7]	LOADK    	4 -5	; "moonscript.transform.statements"
	10	[7]	CALL     	3 2 2
	11	[7]	GETTABLE 	2 3 -6	; "Run"
	12	[8]	LOADK    	3 -7	; "new"
	13	[9]	LOADNIL  	4 4
	14	[10]	GETGLOBAL	5 -8	; table
	15	[10]	GETTABLE 	4 5 -9	; "insert"
	16	[11]	LOADNIL  	5 7
	17	[13]	GETGLOBAL	8 -1	; require
	18	[13]	LOADK    	9 -10	; "moonscript.types"
	19	[13]	CALL     	8 2 2
	20	[14]	GETTABLE 	9 8 -11	; "build"
	21	[14]	GETTABLE 	10 8 -12	; "ntype"
	22	[14]	GETTABLE 	7 8 -13	; "NOOP"
	23	[14]	MOVE     	6 10
	24	[14]	MOVE     	5 9
	25	[16]	LOADNIL  	8 8
	26	[17]	GETGLOBAL	9 -1	; require
	27	[17]	LOADK    	10 -14	; "moonscript.util"
	28	[17]	CALL     	9 2 2
	29	[17]	GETTABLE 	8 9 -15	; "unpack"
	30	[18]	LOADNIL  	9 9
	31	[91]	CLOSURE  	9 0	; 0x7fdec4c06e80
	32	[91]	MOVE     	0 8
	33	[91]	MOVE     	0 4
	34	[91]	MOVE     	0 6
	35	[92]	LOADNIL  	10 10
	36	[107]	CLOSURE  	10 1	; 0x7fdec4c06b40
	37	[107]	MOVE     	0 2
	38	[486]	CLOSURE  	11 2	; 0x7fdec4c086d0
	39	[486]	MOVE     	0 8
	40	[486]	MOVE     	0 0
	41	[486]	MOVE     	0 9
	42	[486]	MOVE     	0 4
	43	[486]	MOVE     	0 6
	44	[486]	MOVE     	0 10
	45	[486]	MOVE     	0 5
	46	[486]	MOVE     	0 3
	47	[486]	MOVE     	0 1
	48	[486]	MOVE     	0 2
	49	[486]	MOVE     	0 7
	50	[486]	RETURN   	11 2
	51	[486]	RETURN   	0 1

function <./moonscript/transform/class.lua:19,91> (110 instructions, 440 bytes at 0x7fdec4c06e80)
4 params, 17 slots, 3 upvalues, 16 locals, 17 constants, 0 functions
	1	[20]	EQ       	0 1 -1	; - nil
	2	[20]	JMP      	1	; to 4
	3	[21]	LOADBOOL 	1 1 0
	4	[23]	NEWTABLE 	4 3 0
	5	[24]	LOADK    	5 -2	; "chain"
	6	[25]	MOVE     	6 0
	7	[25]	NEWTABLE 	7 2 0
	8	[27]	LOADK    	8 -3	; "dot"
	9	[29]	LOADK    	9 -4	; "__parent"
	10	[29]	SETLIST  	7 2 1	; 1
	11	[30]	SETLIST  	4 3 1	; 1
	12	[31]	TEST     	3 0 1
	13	[31]	JMP      	1	; to 15
	14	[32]	RETURN   	4 2
	15	[34]	NEWTABLE 	5 0 0
	16	[35]	GETUPVAL 	6 0	; unpack
	17	[35]	MOVE     	7 3
	18	[35]	LOADK    	8 -5	; 3
	19	[35]	CALL     	6 3 0
	20	[36]	SETLIST  	5 0 1	; 1
	21	[37]	GETTABLE 	6 5 -6	; 1
	22	[38]	EQ       	0 6 -1	; - nil
	23	[38]	JMP      	1	; to 25
	24	[39]	RETURN   	4 2
	25	[41]	MOVE     	7 4
	26	[42]	GETTABLE 	8 6 -6	; 1
	27	[43]	EQ       	0 -7 8	; "call" -
	28	[43]	JMP      	47	; to 76
	29	[44]	TEST     	1 0 0
	30	[44]	JMP      	7	; to 38
	31	[45]	GETUPVAL 	9 1	; insert
	32	[45]	MOVE     	10 7
	33	[45]	NEWTABLE 	11 2 0
	34	[46]	LOADK    	12 -3	; "dot"
	35	[48]	LOADK    	13 -8	; "__base"
	36	[48]	SETLIST  	11 2 1	; 1
	37	[45]	CALL     	9 3 1
	38	[50]	SELF     	9 2 -9	; "get"
	39	[50]	LOADK    	11 -10	; "current_method"
	40	[50]	CALL     	9 3 2
	41	[51]	GETGLOBAL	10 -11	; assert
	42	[51]	MOVE     	11 9
	43	[51]	LOADK    	12 -12	; "missing calling name"
	44	[51]	CALL     	10 3 1
	45	[52]	NEWTABLE 	10 2 0
	46	[53]	LOADK    	11 -7	; "call"
	47	[53]	NEWTABLE 	12 1 0
	48	[55]	LOADK    	13 -13	; "self"
	49	[56]	GETUPVAL 	14 0	; unpack
	50	[56]	GETTABLE 	15 6 -14	; 2
	51	[56]	CALL     	14 2 0
	52	[57]	SETLIST  	12 0 1	; 1
	53	[58]	SETLIST  	10 2 1	; 1
	54	[58]	SETTABLE 	5 -6 10	; 1 -
	55	[59]	GETUPVAL 	10 2	; ntype
	56	[59]	MOVE     	11 9
	57	[59]	CALL     	10 2 2
	58	[59]	EQ       	0 10 -15	; - "key_literal"
	59	[59]	JMP      	8	; to 68
	60	[60]	GETUPVAL 	10 1	; insert
	61	[60]	MOVE     	11 7
	62	[60]	NEWTABLE 	12 2 0
	63	[61]	LOADK    	13 -3	; "dot"
	64	[63]	GETTABLE 	14 9 -14	; 2
	65	[63]	SETLIST  	12 2 1	; 1
	66	[60]	CALL     	10 3 1
	67	[63]	JMP      	31	; to 99
	68	[65]	GETUPVAL 	10 1	; insert
	69	[65]	MOVE     	11 7
	70	[65]	NEWTABLE 	12 2 0
	71	[66]	LOADK    	13 -16	; "index"
	72	[68]	MOVE     	14 9
	73	[68]	SETLIST  	12 2 1	; 1
	74	[65]	CALL     	10 3 1
	75	[69]	JMP      	23	; to 99
	76	[70]	EQ       	0 -17 8	; "colon" -
	77	[70]	JMP      	21	; to 99
	78	[71]	GETTABLE 	9 5 -14	; 2
	79	[72]	TEST     	9 0 0
	80	[72]	JMP      	18	; to 99
	81	[72]	GETTABLE 	10 9 -6	; 1
	82	[72]	EQ       	0 10 -7	; - "call"
	83	[72]	JMP      	15	; to 99
	84	[73]	NEWTABLE 	10 2 0
	85	[74]	LOADK    	11 -3	; "dot"
	86	[76]	GETTABLE 	12 6 -14	; 2
	87	[76]	SETLIST  	10 2 1	; 1
	88	[76]	SETTABLE 	5 -6 10	; 1 -
	89	[77]	NEWTABLE 	10 2 0
	90	[78]	LOADK    	11 -7	; "call"
	91	[78]	NEWTABLE 	12 1 0
	92	[80]	LOADK    	13 -13	; "self"
	93	[81]	GETUPVAL 	14 0	; unpack
	94	[81]	GETTABLE 	15 9 -14	; 2
	95	[81]	CALL     	14 2 0
	96	[82]	SETLIST  	12 0 1	; 1
	97	[83]	SETLIST  	10 2 1	; 1
	98	[83]	SETTABLE 	5 -14 10	; 2 -
	99	[86]	LOADK    	9 -6	; 1
	100	[86]	LEN      	10 5
	101	[86]	LOADK    	11 -6	; 1
	102	[86]	FORPREP  	9 5	; to 108
	103	[87]	GETTABLE 	13 5 12
	104	[88]	GETUPVAL 	14 1	; insert
	105	[88]	MOVE     	15 7
	106	[88]	MOVE     	16 13
	107	[88]	CALL     	14 3 1
	108	[86]	FORLOOP  	9 -6	; to 103
	109	[90]	RETURN   	7 2
	110	[91]	RETURN   	0 1

function <./moonscript/transform/class.lua:93,107> (16 instructions, 64 bytes at 0x7fdec4c06b40)
3 params, 10 slots, 1 upvalue, 4 locals, 1 constant, 2 functions
	1	[95]	NEWTABLE 	4 3 0
	2	[96]	LOADK    	5 -1	; "scoped"
	3	[97]	GETUPVAL 	6 0	; Run
	4	[101]	CLOSURE  	7 0	; 0x7fdec4c07de0
	5	[101]	MOVE     	0 3
	6	[101]	MOVE     	0 2
	7	[101]	MOVE     	0 1
	8	[97]	CALL     	6 2 2
	9	[102]	MOVE     	7 0
	10	[103]	GETUPVAL 	8 0	; Run
	11	[105]	CLOSURE  	9 1	; 0x7fdec4c082e0
	12	[105]	MOVE     	0 3
	13	[103]	CALL     	8 2 0
	14	[106]	SETLIST  	4 0 1	; 1
	15	[106]	RETURN   	4 2
	16	[107]	RETURN   	0 1

function <./moonscript/transform/class.lua:97,101> (14 instructions, 56 bytes at 0x7fdec4c07de0)
1 param, 5 slots, 3 upvalues, 1 local, 4 constants, 0 functions
	1	[98]	SELF     	1 0 -1	; "get"
	2	[98]	LOADK    	3 -2	; "current_method"
	3	[98]	CALL     	1 3 2
	4	[98]	SETUPVAL 	1 0	; prev_method
	5	[99]	SELF     	1 0 -3	; "set"
	6	[99]	LOADK    	3 -2	; "current_method"
	7	[99]	GETUPVAL 	4 1	; key
	8	[99]	CALL     	1 4 1
	9	[100]	SELF     	1 0 -3	; "set"
	10	[100]	LOADK    	3 -4	; "super"
	11	[100]	GETUPVAL 	4 2	; t
	12	[100]	TAILCALL 	1 4 0
	13	[100]	RETURN   	1 0
	14	[101]	RETURN   	0 1

function <./moonscript/transform/class.lua:103,105> (6 instructions, 24 bytes at 0x7fdec4c082e0)
1 param, 5 slots, 1 upvalue, 1 local, 2 constants, 0 functions
	1	[104]	SELF     	1 0 -1	; "set"
	2	[104]	LOADK    	3 -2	; "current_method"
	3	[104]	GETUPVAL 	4 0	; prev_method
	4	[104]	TAILCALL 	1 4 0
	5	[104]	RETURN   	1 0
	6	[105]	RETURN   	0 1

function <./moonscript/transform/class.lua:108,486> (603 instructions, 2412 bytes at 0x7fdec4c086d0)
4 params, 44 slots, 11 upvalues, 52 locals, 57 constants, 7 functions
	1	[109]	GETUPVAL 	4 0	; unpack
	2	[109]	MOVE     	5 1
	3	[109]	LOADK    	6 -1	; 2
	4	[109]	CALL     	4 3 4
	5	[110]	EQ       	0 5 -2	; - ""
	6	[110]	JMP      	1	; to 8
	7	[111]	LOADNIL  	5 5
	8	[113]	GETUPVAL 	7 1	; NameProxy
	9	[113]	LOADK    	8 -3	; "parent"
	10	[113]	CALL     	7 2 2
	11	[114]	GETUPVAL 	8 1	; NameProxy
	12	[114]	LOADK    	9 -4	; "base"
	13	[114]	CALL     	8 2 2
	14	[115]	GETUPVAL 	9 1	; NameProxy
	15	[115]	LOADK    	10 -5	; "self"
	16	[115]	CALL     	9 2 2
	17	[116]	GETUPVAL 	10 1	; NameProxy
	18	[116]	LOADK    	11 -6	; "class"
	19	[116]	CALL     	10 2 2
	20	[117]	LOADNIL  	11 11
	21	[120]	CLOSURE  	11 0	; 0x7fdec4c08a50
	22	[120]	GETUPVAL 	0 2	; transform_super
	23	[120]	MOVE     	0 10
	24	[121]	LOADNIL  	12 12
	25	[124]	CLOSURE  	12 1	; 0x7fdec4c08c30
	26	[124]	GETUPVAL 	0 2	; transform_super
	27	[124]	MOVE     	0 10
	28	[125]	NEWTABLE 	13 0 0
	29	[126]	NEWTABLE 	14 0 0
	30	[127]	LOADK    	15 -7	; 1
	31	[127]	LEN      	16 6
	32	[127]	LOADK    	17 -7	; 1
	33	[127]	FORPREP  	15 48	; to 82
	34	[128]	GETTABLE 	19 6 18
	35	[129]	GETTABLE 	20 19 -7	; 1
	36	[130]	EQ       	0 -8 20	; "stm" -
	37	[130]	JMP      	5	; to 43
	38	[131]	GETUPVAL 	21 3	; insert
	39	[131]	MOVE     	22 13
	40	[131]	GETTABLE 	23 19 -1	; 2
	41	[131]	CALL     	21 3 1
	42	[131]	JMP      	39	; to 82
	43	[132]	EQ       	0 -9 20	; "props" -
	44	[132]	JMP      	37	; to 82
	45	[133]	LOADK    	21 -1	; 2
	46	[133]	LEN      	22 19
	47	[133]	LOADK    	23 -7	; 1
	48	[133]	FORPREP  	21 32	; to 81
	49	[134]	GETTABLE 	25 19 24
	50	[135]	GETUPVAL 	26 4	; ntype
	51	[135]	GETTABLE 	27 25 -7	; 1
	52	[135]	CALL     	26 2 2
	53	[135]	EQ       	0 26 -5	; - "self"
	54	[135]	JMP      	22	; to 77
	55	[136]	LOADNIL  	26 27
	56	[137]	GETTABLE 	28 25 -7	; 1
	57	[137]	GETTABLE 	27 25 -1	; 2
	58	[137]	MOVE     	26 28
	59	[138]	GETUPVAL 	28 5	; super_scope
	60	[138]	MOVE     	29 27
	61	[138]	MOVE     	30 12
	62	[138]	NEWTABLE 	31 2 0
	63	[139]	LOADK    	32 -10	; "key_literal"
	64	[141]	GETTABLE 	33 26 -1	; 2
	65	[141]	SETLIST  	31 2 1	; 1
	66	[138]	CALL     	28 4 2
	67	[141]	MOVE     	27 28
	68	[142]	GETUPVAL 	28 3	; insert
	69	[142]	MOVE     	29 13
	70	[142]	GETUPVAL 	30 6	; build
	71	[142]	GETTABLE 	30 30 -11	; "assign_one"
	72	[142]	MOVE     	31 26
	73	[142]	MOVE     	32 27
	74	[142]	CALL     	30 3 0
	75	[142]	CALL     	28 0 1
	76	[142]	JMP      	4	; to 81
	77	[144]	GETUPVAL 	26 3	; insert
	78	[144]	MOVE     	27 14
	79	[144]	MOVE     	28 25
	80	[144]	CALL     	26 3 1
	81	[133]	FORLOOP  	21 -33	; to 49
	82	[127]	FORLOOP  	15 -49	; to 34
	83	[149]	LOADNIL  	15 15
	84	[151]	NEWTABLE 	16 0 0
	85	[152]	LOADK    	17 -7	; 1
	86	[153]	LOADK    	18 -7	; 1
	87	[153]	LEN      	19 14
	88	[153]	LOADK    	20 -7	; 1
	89	[153]	FORPREP  	18 34	; to 124
	90	[154]	LOADBOOL 	22 0 0
	91	[156]	GETTABLE 	23 14 21
	92	[157]	GETTABLE 	24 23 -7	; 1
	93	[158]	LOADNIL  	25 25
	94	[159]	GETTABLE 	26 24 -7	; 1
	95	[159]	EQ       	0 26 -10	; - "key_literal"
	96	[159]	JMP      	8	; to 105
	97	[159]	GETTABLE 	26 24 -1	; 2
	98	[159]	GETUPVAL 	27 7	; CONSTRUCTOR_NAME
	99	[159]	EQ       	0 26 27
	100	[159]	JMP      	4	; to 105
	101	[160]	GETTABLE 	15 23 -1	; 2
	102	[161]	LOADBOOL 	22 1 0
	103	[162]	JMP      	17	; to 121
	104	[162]	JMP      	13	; to 118
	105	[164]	LOADNIL  	26 26
	106	[165]	GETTABLE 	27 23 -7	; 1
	107	[165]	GETTABLE 	26 23 -1	; 2
	108	[165]	MOVE     	24 27
	109	[166]	NEWTABLE 	27 1 0
	110	[167]	MOVE     	28 24
	111	[168]	GETUPVAL 	29 5	; super_scope
	112	[168]	MOVE     	30 26
	113	[168]	MOVE     	31 11
	114	[168]	MOVE     	32 24
	115	[168]	CALL     	29 4 0
	116	[169]	SETLIST  	27 0 1	; 1
	117	[169]	MOVE     	25 27
	118	[171]	SETTABLE 	16 17 25
	119	[172]	ADD      	17 17 -7	; - 1
	120	[173]	LOADBOOL 	22 1 0
	121	[175]	TEST     	22 0 1
	122	[175]	JMP      	1	; to 124
	123	[176]	JMP      	1	; to 125
	124	[153]	FORLOOP  	18 -35	; to 90
	125	[179]	MOVE     	14 16
	126	[181]	TEST     	15 0 1
	127	[181]	JMP      	34	; to 162
	128	[182]	TEST     	5 0 0
	129	[182]	JMP      	28	; to 158
	130	[183]	GETUPVAL 	16 6	; build
	131	[183]	GETTABLE 	16 16 -12	; "fndef"
	132	[183]	NEWTABLE 	17 0 3
	133	[184]	NEWTABLE 	18 1 0
	134	[184]	NEWTABLE 	19 1 0
	135	[187]	LOADK    	20 -14	; "..."
	136	[187]	SETLIST  	19 1 1	; 1
	137	[188]	SETLIST  	18 1 1	; 1
	138	[188]	SETTABLE 	17 -13 18	; "args" -
	139	[189]	SETTABLE 	17 -15 -16	; "arrow" "fat"
	140	[190]	NEWTABLE 	18 0 0
	141	[191]	GETUPVAL 	19 6	; build
	142	[191]	GETTABLE 	19 19 -18	; "chain"
	143	[191]	NEWTABLE 	20 1 1
	144	[192]	SETTABLE 	20 -4 -19	; "base" "super"
	145	[192]	NEWTABLE 	21 2 0
	146	[194]	LOADK    	22 -20	; "call"
	147	[194]	NEWTABLE 	23 1 0
	148	[197]	LOADK    	24 -14	; "..."
	149	[197]	SETLIST  	23 1 1	; 1
	150	[198]	SETLIST  	21 2 1	; 1
	151	[199]	SETLIST  	20 1 1	; 1
	152	[191]	CALL     	19 2 0
	153	[200]	SETLIST  	18 0 1	; 1
	154	[200]	SETTABLE 	17 -17 18	; "body" -
	155	[183]	CALL     	16 2 2
	156	[201]	MOVE     	15 16
	157	[201]	JMP      	4	; to 162
	158	[203]	GETUPVAL 	16 6	; build
	159	[203]	GETTABLE 	16 16 -12	; "fndef"
	160	[203]	CALL     	16 1 2
	161	[203]	MOVE     	15 16
	162	[206]	TESTSET  	16 4 1
	163	[206]	JMP      	4	; to 168
	164	[206]	TESTSET  	16 3 0
	165	[206]	JMP      	2	; to 168
	166	[206]	GETTABLE 	16 3 -1	; 2
	167	[206]	GETTABLE 	16 16 -7	; 1
	168	[207]	GETUPVAL 	17 4	; ntype
	169	[207]	MOVE     	18 16
	170	[207]	CALL     	17 2 2
	171	[208]	EQ       	0 -18 17	; "chain" -
	172	[208]	JMP      	20	; to 193
	173	[209]	LEN      	18 16
	174	[209]	GETTABLE 	18 16 18
	175	[210]	GETUPVAL 	19 4	; ntype
	176	[210]	MOVE     	20 18
	177	[210]	CALL     	19 2 2
	178	[211]	EQ       	0 -21 19	; "dot" -
	179	[211]	JMP      	7	; to 187
	180	[212]	NEWTABLE 	20 3 0
	181	[213]	LOADK    	21 -22	; "string"
	182	[214]	LOADK    	22 -23	; "\""
	183	[216]	GETTABLE 	23 18 -1	; 2
	184	[216]	SETLIST  	20 3 1	; 1
	185	[216]	MOVE     	16 20
	186	[216]	JMP      	39	; to 226
	187	[217]	EQ       	0 -24 19	; "index" -
	188	[217]	JMP      	2	; to 191
	189	[218]	GETTABLE 	16 18 -1	; 2
	190	[218]	JMP      	35	; to 226
	191	[220]	LOADK    	16 -25	; "nil"
	192	[221]	JMP      	33	; to 226
	193	[222]	EQ       	0 -25 17	; "nil" -
	194	[222]	JMP      	2	; to 197
	195	[223]	LOADK    	16 -25	; "nil"
	196	[223]	JMP      	29	; to 226
	197	[225]	GETGLOBAL	18 -26	; type
	198	[225]	MOVE     	19 16
	199	[225]	CALL     	18 2 2
	200	[226]	LOADNIL  	19 19
	201	[227]	EQ       	0 18 -22	; - "string"
	202	[227]	JMP      	2	; to 205
	203	[228]	MOVE     	19 16
	204	[228]	JMP      	15	; to 220
	205	[229]	EQ       	0 18 -27	; - "table"
	206	[229]	JMP      	5	; to 212
	207	[229]	GETTABLE 	20 16 -7	; 1
	208	[229]	EQ       	0 20 -28	; - "ref"
	209	[229]	JMP      	2	; to 212
	210	[230]	GETTABLE 	19 16 -1	; 2
	211	[230]	JMP      	8	; to 220
	212	[232]	GETGLOBAL	20 -29	; error
	213	[232]	LOADK    	21 -30	; "don't know how to extract name from "
	214	[232]	GETGLOBAL	22 -31	; tostring
	215	[232]	MOVE     	23 18
	216	[232]	CALL     	22 2 2
	217	[232]	CONCAT   	21 21 22
	218	[232]	CALL     	20 2 2
	219	[232]	MOVE     	19 20
	220	[234]	NEWTABLE 	20 3 0
	221	[235]	LOADK    	21 -22	; "string"
	222	[236]	LOADK    	22 -23	; "\""
	223	[238]	MOVE     	23 19
	224	[238]	SETLIST  	20 3 1	; 1
	225	[238]	MOVE     	16 20
	226	[240]	GETUPVAL 	18 6	; build
	227	[240]	GETTABLE 	18 18 -27	; "table"
	228	[240]	NEWTABLE 	19 4 0
	229	[240]	NEWTABLE 	20 1 0
	230	[242]	LOADK    	21 -32	; "__init"
	231	[243]	GETUPVAL 	22 5	; super_scope
	232	[243]	MOVE     	23 15
	233	[243]	MOVE     	24 12
	234	[243]	NEWTABLE 	25 2 0
	235	[244]	LOADK    	26 -10	; "key_literal"
	236	[246]	LOADK    	27 -32	; "__init"
	237	[246]	SETLIST  	25 2 1	; 1
	238	[243]	CALL     	22 4 0
	239	[247]	SETLIST  	20 0 1	; 1
	240	[247]	NEWTABLE 	21 2 0
	241	[249]	LOADK    	22 -33	; "__base"
	242	[251]	MOVE     	23 8
	243	[251]	SETLIST  	21 2 1	; 1
	244	[251]	NEWTABLE 	22 2 0
	245	[253]	LOADK    	23 -34	; "__name"
	246	[255]	MOVE     	24 16
	247	[255]	SETLIST  	22 2 1	; 1
	248	[256]	TEST     	5 0 0
	249	[256]	JMP      	6	; to 256
	250	[256]	NEWTABLE 	23 2 0
	251	[257]	LOADK    	24 -35	; "__parent"
	252	[259]	MOVE     	25 7
	253	[259]	SETLIST  	23 2 1	; 1
	254	[259]	TEST     	23 0 1
	255	[259]	JMP      	1	; to 257
	256	[260]	LOADNIL  	23 23
	257	[260]	SETLIST  	19 4 1	; 1
	258	[240]	CALL     	18 2 2
	259	[261]	LOADNIL  	19 19
	260	[262]	TEST     	5 0 0
	261	[262]	JMP      	117	; to 379
	262	[263]	GETUPVAL 	20 6	; build
	263	[263]	GETTABLE 	20 20 -36	; "if"
	264	[263]	NEWTABLE 	21 0 2
	265	[264]	NEWTABLE 	22 4 0
	266	[265]	LOADK    	23 -38	; "exp"
	267	[265]	NEWTABLE 	24 2 0
	268	[267]	LOADK    	25 -28	; "ref"
	269	[269]	LOADK    	26 -39	; "val"
	270	[269]	SETLIST  	24 2 1	; 1
	271	[270]	LOADK    	25 -40	; "=="
	272	[272]	LOADK    	26 -25	; "nil"
	273	[272]	SETLIST  	22 4 1	; 1
	274	[272]	SETTABLE 	21 -37 22	; "cond" -
	275	[273]	NEWTABLE 	22 1 0
	276	[274]	GETUPVAL 	23 6	; build
	277	[274]	GETTABLE 	23 23 -11	; "assign_one"
	278	[274]	GETUPVAL 	24 8	; LocalName
	279	[274]	LOADK    	25 -3	; "parent"
	280	[274]	CALL     	24 2 2
	281	[274]	GETUPVAL 	25 6	; build
	282	[274]	GETTABLE 	25 25 -18	; "chain"
	283	[274]	NEWTABLE 	26 1 1
	284	[275]	SETTABLE 	26 -4 -42	; "base" "rawget"
	285	[275]	NEWTABLE 	27 2 0
	286	[277]	LOADK    	28 -20	; "call"
	287	[277]	NEWTABLE 	29 2 0
	288	[278]	NEWTABLE 	30 2 0
	289	[280]	LOADK    	31 -28	; "ref"
	290	[282]	LOADK    	32 -43	; "cls"
	291	[282]	SETLIST  	30 2 1	; 1
	292	[282]	NEWTABLE 	31 3 0
	293	[284]	LOADK    	32 -22	; "string"
	294	[285]	LOADK    	33 -23	; "\""
	295	[287]	LOADK    	34 -35	; "__parent"
	296	[287]	SETLIST  	31 3 1	; 1
	297	[288]	SETLIST  	29 2 1	; 1
	298	[289]	SETLIST  	27 2 1	; 1
	299	[290]	SETLIST  	26 1 1	; 1
	300	[274]	CALL     	25 2 0
	301	[274]	CALL     	23 0 2
	302	[291]	GETUPVAL 	24 6	; build
	303	[291]	GETTABLE 	24 24 -36	; "if"
	304	[291]	NEWTABLE 	25 0 2
	305	[292]	GETUPVAL 	26 8	; LocalName
	306	[292]	LOADK    	27 -3	; "parent"
	307	[292]	CALL     	26 2 2
	308	[292]	SETTABLE 	25 -37 26	; "cond" -
	309	[293]	NEWTABLE 	26 0 0
	310	[294]	GETUPVAL 	27 6	; build
	311	[294]	GETTABLE 	27 27 -18	; "chain"
	312	[294]	NEWTABLE 	28 1 1
	313	[295]	GETUPVAL 	29 8	; LocalName
	314	[295]	LOADK    	30 -3	; "parent"
	315	[295]	CALL     	29 2 2
	316	[295]	SETTABLE 	28 -4 29	; "base" -
	317	[295]	NEWTABLE 	29 2 0
	318	[297]	LOADK    	30 -24	; "index"
	319	[299]	LOADK    	31 -44	; "name"
	320	[299]	SETLIST  	29 2 1	; 1
	321	[300]	SETLIST  	28 1 1	; 1
	322	[294]	CALL     	27 2 0
	323	[301]	SETLIST  	26 0 1	; 1
	324	[301]	SETTABLE 	25 -41 26	; "then" -
	325	[291]	CALL     	24 2 0
	326	[303]	SETLIST  	22 0 1	; 1
	327	[303]	SETTABLE 	21 -41 22	; "then" -
	328	[263]	CALL     	20 2 2
	329	[305]	GETUPVAL 	21 3	; insert
	330	[305]	MOVE     	22 20
	331	[305]	NEWTABLE 	23 2 0
	332	[306]	LOADK    	24 -45	; "else"
	333	[306]	NEWTABLE 	25 1 0
	334	[309]	LOADK    	26 -39	; "val"
	335	[309]	SETLIST  	25 1 1	; 1
	336	[310]	SETLIST  	23 2 1	; 1
	337	[305]	CALL     	21 3 1
	338	[311]	GETUPVAL 	21 6	; build
	339	[311]	GETTABLE 	21 21 -12	; "fndef"
	340	[311]	NEWTABLE 	22 0 2
	341	[312]	NEWTABLE 	23 2 0
	342	[312]	NEWTABLE 	24 1 0
	343	[315]	LOADK    	25 -43	; "cls"
	344	[315]	SETLIST  	24 1 1	; 1
	345	[315]	NEWTABLE 	25 1 0
	346	[318]	LOADK    	26 -44	; "name"
	347	[318]	SETLIST  	25 1 1	; 1
	348	[319]	SETLIST  	23 2 1	; 1
	349	[319]	SETTABLE 	22 -13 23	; "args" -
	350	[320]	NEWTABLE 	23 2 0
	351	[321]	GETUPVAL 	24 6	; build
	352	[321]	GETTABLE 	24 24 -11	; "assign_one"
	353	[321]	GETUPVAL 	25 8	; LocalName
	354	[321]	LOADK    	26 -39	; "val"
	355	[321]	CALL     	25 2 2
	356	[321]	GETUPVAL 	26 6	; build
	357	[321]	GETTABLE 	26 26 -18	; "chain"
	358	[321]	NEWTABLE 	27 1 1
	359	[322]	SETTABLE 	27 -4 -42	; "base" "rawget"
	360	[322]	NEWTABLE 	28 2 0
	361	[324]	LOADK    	29 -20	; "call"
	362	[324]	NEWTABLE 	30 2 0
	363	[326]	MOVE     	31 8
	364	[326]	NEWTABLE 	32 2 0
	365	[328]	LOADK    	33 -28	; "ref"
	366	[330]	LOADK    	34 -44	; "name"
	367	[330]	SETLIST  	32 2 1	; 1
	368	[331]	SETLIST  	30 2 1	; 1
	369	[332]	SETLIST  	28 2 1	; 1
	370	[333]	SETLIST  	27 1 1	; 1
	371	[321]	CALL     	26 2 0
	372	[321]	CALL     	24 0 2
	373	[335]	MOVE     	25 20
	374	[335]	SETLIST  	23 2 1	; 1
	375	[335]	SETTABLE 	22 -17 23	; "body" -
	376	[311]	CALL     	21 2 2
	377	[336]	MOVE     	19 21
	378	[336]	JMP      	1	; to 380
	379	[338]	MOVE     	19 8
	380	[340]	GETUPVAL 	20 6	; build
	381	[340]	GETTABLE 	20 20 -27	; "table"
	382	[340]	NEWTABLE 	21 2 0
	383	[340]	NEWTABLE 	22 2 0
	384	[342]	LOADK    	23 -46	; "__index"
	385	[344]	MOVE     	24 19
	386	[344]	SETLIST  	22 2 1	; 1
	387	[344]	NEWTABLE 	23 1 0
	388	[346]	LOADK    	24 -47	; "__call"
	389	[347]	GETUPVAL 	25 6	; build
	390	[347]	GETTABLE 	25 25 -12	; "fndef"
	391	[347]	NEWTABLE 	26 0 2
	392	[348]	NEWTABLE 	27 2 0
	393	[348]	NEWTABLE 	28 1 0
	394	[351]	LOADK    	29 -43	; "cls"
	395	[351]	SETLIST  	28 1 1	; 1
	396	[351]	NEWTABLE 	29 1 0
	397	[354]	LOADK    	30 -14	; "..."
	398	[354]	SETLIST  	29 1 1	; 1
	399	[355]	SETLIST  	27 2 1	; 1
	400	[355]	SETTABLE 	26 -13 27	; "args" -
	401	[356]	NEWTABLE 	27 3 0
	402	[357]	GETUPVAL 	28 6	; build
	403	[357]	GETTABLE 	28 28 -11	; "assign_one"
	404	[357]	MOVE     	29 9
	405	[357]	GETUPVAL 	30 6	; build
	406	[357]	GETTABLE 	30 30 -18	; "chain"
	407	[357]	NEWTABLE 	31 1 1
	408	[358]	SETTABLE 	31 -4 -48	; "base" "setmetatable"
	409	[358]	NEWTABLE 	32 2 0
	410	[360]	LOADK    	33 -20	; "call"
	411	[360]	NEWTABLE 	34 2 0
	412	[362]	LOADK    	35 -49	; "{}"
	413	[364]	MOVE     	36 8
	414	[364]	SETLIST  	34 2 1	; 1
	415	[365]	SETLIST  	32 2 1	; 1
	416	[366]	SETLIST  	31 1 1	; 1
	417	[357]	CALL     	30 2 0
	418	[357]	CALL     	28 0 2
	419	[367]	GETUPVAL 	29 6	; build
	420	[367]	GETTABLE 	29 29 -18	; "chain"
	421	[367]	NEWTABLE 	30 1 1
	422	[368]	SETTABLE 	30 -4 -50	; "base" "cls.__init"
	423	[368]	NEWTABLE 	31 2 0
	424	[370]	LOADK    	32 -20	; "call"
	425	[370]	NEWTABLE 	33 2 0
	426	[372]	MOVE     	34 9
	427	[374]	LOADK    	35 -14	; "..."
	428	[374]	SETLIST  	33 2 1	; 1
	429	[375]	SETLIST  	31 2 1	; 1
	430	[376]	SETLIST  	30 1 1	; 1
	431	[367]	CALL     	29 2 2
	432	[378]	MOVE     	30 9
	433	[378]	SETLIST  	27 3 1	; 1
	434	[378]	SETTABLE 	26 -17 27	; "body" -
	435	[347]	CALL     	25 2 0
	436	[380]	SETLIST  	23 0 1	; 1
	437	[381]	SETLIST  	21 2 1	; 1
	438	[340]	CALL     	20 2 2
	439	[382]	GETUPVAL 	21 6	; build
	440	[382]	GETTABLE 	21 21 -18	; "chain"
	441	[382]	NEWTABLE 	22 1 1
	442	[383]	SETTABLE 	22 -4 -48	; "base" "setmetatable"
	443	[383]	NEWTABLE 	23 2 0
	444	[385]	LOADK    	24 -20	; "call"
	445	[385]	NEWTABLE 	25 2 0
	446	[387]	MOVE     	26 18
	447	[389]	MOVE     	27 20
	448	[389]	SETLIST  	25 2 1	; 1
	449	[390]	SETLIST  	23 2 1	; 1
	450	[391]	SETLIST  	22 1 1	; 1
	451	[382]	CALL     	21 2 2
	452	[391]	MOVE     	18 21
	453	[392]	LOADNIL  	21 21
	454	[394]	NEWTABLE 	22 12 0
	455	[395]	GETUPVAL 	23 9	; Run
	456	[399]	CLOSURE  	24 2	; 0x7fdec4c09530
	457	[399]	MOVE     	0 4
	458	[395]	CALL     	23 2 2
	459	[399]	NEWTABLE 	24 2 0
	460	[401]	LOADK    	25 -51	; "declare"
	461	[401]	NEWTABLE 	26 1 0
	462	[404]	MOVE     	27 10
	463	[404]	SETLIST  	26 1 1	; 1
	464	[405]	SETLIST  	24 2 1	; 1
	465	[405]	NEWTABLE 	25 2 0
	466	[407]	LOADK    	26 -52	; "declare_glob"
	467	[409]	LOADK    	27 -53	; "*"
	468	[409]	SETLIST  	25 2 1	; 1
	469	[410]	TEST     	5 0 0
	470	[410]	JMP      	7	; to 478
	471	[410]	GETUPVAL 	26 6	; build
	472	[410]	GETTABLE 	26 26 -11	; "assign_one"
	473	[410]	MOVE     	27 7
	474	[410]	MOVE     	28 5
	475	[410]	CALL     	26 3 2
	476	[410]	TEST     	26 0 1
	477	[410]	JMP      	1	; to 479
	478	[410]	GETUPVAL 	26 10	; NOOP
	479	[411]	GETUPVAL 	27 6	; build
	480	[411]	GETTABLE 	27 27 -11	; "assign_one"
	481	[411]	MOVE     	28 8
	482	[411]	NEWTABLE 	29 2 0
	483	[412]	LOADK    	30 -27	; "table"
	484	[414]	MOVE     	31 14
	485	[414]	SETLIST  	29 2 1	; 1
	486	[411]	CALL     	27 3 2
	487	[415]	GETUPVAL 	28 6	; build
	488	[415]	GETTABLE 	28 28 -11	; "assign_one"
	489	[415]	SELF     	29 8 -18	; "chain"
	490	[415]	LOADK    	31 -46	; "__index"
	491	[415]	CALL     	29 3 2
	492	[415]	MOVE     	30 8
	493	[415]	CALL     	28 3 2
	494	[416]	TEST     	5 0 0
	495	[416]	JMP      	24	; to 520
	496	[416]	GETUPVAL 	29 6	; build
	497	[416]	GETTABLE 	29 29 -18	; "chain"
	498	[416]	NEWTABLE 	30 1 1
	499	[417]	SETTABLE 	30 -4 -48	; "base" "setmetatable"
	500	[417]	NEWTABLE 	31 2 0
	501	[419]	LOADK    	32 -20	; "call"
	502	[419]	NEWTABLE 	33 1 0
	503	[421]	MOVE     	34 8
	504	[422]	GETUPVAL 	35 6	; build
	505	[422]	GETTABLE 	35 35 -18	; "chain"
	506	[422]	NEWTABLE 	36 1 1
	507	[423]	SETTABLE 	36 -4 7	; "base" -
	508	[423]	NEWTABLE 	37 2 0
	509	[425]	LOADK    	38 -21	; "dot"
	510	[427]	LOADK    	39 -33	; "__base"
	511	[427]	SETLIST  	37 2 1	; 1
	512	[428]	SETLIST  	36 1 1	; 1
	513	[422]	CALL     	35 2 0
	514	[429]	SETLIST  	33 0 1	; 1
	515	[430]	SETLIST  	31 2 1	; 1
	516	[431]	SETLIST  	30 1 1	; 1
	517	[416]	CALL     	29 2 2
	518	[431]	TEST     	29 0 1
	519	[431]	JMP      	1	; to 521
	520	[431]	GETUPVAL 	29 10	; NOOP
	521	[432]	GETUPVAL 	30 6	; build
	522	[432]	GETTABLE 	30 30 -11	; "assign_one"
	523	[432]	MOVE     	31 10
	524	[432]	MOVE     	32 18
	525	[432]	CALL     	30 3 2
	526	[433]	GETUPVAL 	31 6	; build
	527	[433]	GETTABLE 	31 31 -11	; "assign_one"
	528	[433]	SELF     	32 8 -18	; "chain"
	529	[433]	LOADK    	34 -54	; "__class"
	530	[433]	CALL     	32 3 2
	531	[433]	MOVE     	33 10
	532	[433]	CALL     	31 3 2
	533	[434]	GETUPVAL 	32 6	; build
	534	[434]	GETTABLE 	32 32 -55	; "group"
	535	[441]	CLOSURE  	33 3	; 0x7fdec4c09670
	536	[441]	MOVE     	0 13
	537	[441]	GETUPVAL 	0 6	; build
	538	[441]	GETUPVAL 	0 8	; LocalName
	539	[441]	MOVE     	0 10
	540	[441]	CALL     	33 1 0
	541	[434]	CALL     	32 0 2
	542	[442]	TEST     	5 0 0
	543	[442]	JMP      	26	; to 570
	544	[442]	GETUPVAL 	33 6	; build
	545	[442]	GETTABLE 	33 33 -36	; "if"
	546	[442]	NEWTABLE 	34 0 2
	547	[443]	NEWTABLE 	35 1 0
	548	[444]	LOADK    	36 -38	; "exp"
	549	[445]	SELF     	37 7 -18	; "chain"
	550	[445]	LOADK    	39 -56	; "__inherited"
	551	[445]	CALL     	37 3 0
	552	[446]	SETLIST  	35 0 1	; 1
	553	[446]	SETTABLE 	34 -37 35	; "cond" -
	554	[447]	NEWTABLE 	35 0 0
	555	[448]	SELF     	36 7 -18	; "chain"
	556	[448]	LOADK    	38 -56	; "__inherited"
	557	[448]	NEWTABLE 	39 2 0
	558	[449]	LOADK    	40 -20	; "call"
	559	[449]	NEWTABLE 	41 2 0
	560	[451]	MOVE     	42 7
	561	[453]	MOVE     	43 10
	562	[453]	SETLIST  	41 2 1	; 1
	563	[454]	SETLIST  	39 2 1	; 1
	564	[448]	CALL     	36 4 0
	565	[455]	SETLIST  	35 0 1	; 1
	566	[455]	SETTABLE 	34 -41 35	; "then" -
	567	[442]	CALL     	33 2 2
	568	[456]	TEST     	33 0 1
	569	[456]	JMP      	1	; to 571
	570	[456]	GETUPVAL 	33 10	; NOOP
	571	[457]	GETUPVAL 	34 6	; build
	572	[457]	GETTABLE 	34 34 -55	; "group"
	573	[463]	CLOSURE  	35 4	; 0x7fdec4c09b30
	574	[463]	MOVE     	0 4
	575	[463]	GETUPVAL 	0 6	; build
	576	[463]	MOVE     	0 10
	577	[463]	CALL     	35 1 0
	578	[457]	CALL     	34 0 2
	579	[468]	CLOSURE  	35 5	; 0x7fdec4c08df0
	580	[468]	MOVE     	0 2
	581	[468]	MOVE     	0 10
	582	[468]	CALL     	35 1 0
	583	[469]	SETLIST  	22 0 1	; 1
	584	[470]	GETUPVAL 	23 6	; build
	585	[470]	GETTABLE 	23 23 -55	; "group"
	586	[470]	NEWTABLE 	24 1 0
	587	[471]	GETUPVAL 	25 6	; build
	588	[471]	GETTABLE 	25 25 -55	; "group"
	589	[481]	CLOSURE  	26 6	; 0x7fdec4c08e70
	590	[481]	GETUPVAL 	0 4	; ntype
	591	[481]	MOVE     	0 4
	592	[481]	GETUPVAL 	0 6	; build
	593	[481]	CALL     	26 1 0
	594	[471]	CALL     	25 0 2
	595	[482]	GETUPVAL 	26 6	; build
	596	[482]	GETTABLE 	26 26 -57	; "do"
	597	[482]	MOVE     	27 22
	598	[482]	CALL     	26 2 0
	599	[483]	SETLIST  	24 0 1	; 1
	600	[470]	CALL     	23 2 2
	601	[483]	MOVE     	21 23
	602	[485]	RETURN   	21 2
	603	[486]	RETURN   	0 1

function <./moonscript/transform/class.lua:118,120> (7 instructions, 28 bytes at 0x7fdec4c08a50)
0+ params, 5 slots, 2 upvalues, 1 local, 0 constants, 0 functions
	1	[119]	GETUPVAL 	1 0	; transform_super
	2	[119]	GETUPVAL 	2 1	; cls_name
	3	[119]	LOADBOOL 	3 1 0
	4	[119]	VARARG   	4 0
	5	[119]	TAILCALL 	1 0 0
	6	[119]	RETURN   	1 0
	7	[120]	RETURN   	0 1

function <./moonscript/transform/class.lua:122,124> (7 instructions, 28 bytes at 0x7fdec4c08c30)
0+ params, 5 slots, 2 upvalues, 1 local, 0 constants, 0 functions
	1	[123]	GETUPVAL 	1 0	; transform_super
	2	[123]	GETUPVAL 	2 1	; cls_name
	3	[123]	LOADBOOL 	3 0 0
	4	[123]	VARARG   	4 0
	5	[123]	TAILCALL 	1 0 0
	6	[123]	RETURN   	1 0
	7	[124]	RETURN   	0 1

function <./moonscript/transform/class.lua:395,399> (8 instructions, 32 bytes at 0x7fdec4c09530)
1 param, 4 slots, 1 upvalue, 1 local, 1 constant, 0 functions
	1	[396]	GETUPVAL 	1 0	; name
	2	[396]	TEST     	1 0 0
	3	[396]	JMP      	4	; to 8
	4	[397]	SELF     	1 0 -1	; "put_name"
	5	[397]	GETUPVAL 	3 0	; name
	6	[397]	TAILCALL 	1 3 0
	7	[397]	RETURN   	1 0
	8	[399]	RETURN   	0 1

function <./moonscript/transform/class.lua:434,441> (19 instructions, 76 bytes at 0x7fdec4c09670)
0 params, 4 slots, 4 upvalues, 0 locals, 4 constants, 0 functions
	1	[435]	GETUPVAL 	0 0	; statements
	2	[435]	LEN      	0 0
	3	[435]	LT       	0 -1 0	; 0 -
	4	[435]	JMP      	14	; to 19
	5	[436]	NEWTABLE 	0 1 0
	6	[437]	GETUPVAL 	1 1	; build
	7	[437]	GETTABLE 	1 1 -2	; "assign_one"
	8	[437]	GETUPVAL 	2 2	; LocalName
	9	[437]	LOADK    	3 -3	; "self"
	10	[437]	CALL     	2 2 2
	11	[437]	GETUPVAL 	3 3	; cls_name
	12	[437]	CALL     	1 3 2
	13	[438]	GETUPVAL 	2 1	; build
	14	[438]	GETTABLE 	2 2 -4	; "group"
	15	[438]	GETUPVAL 	3 0	; statements
	16	[438]	CALL     	2 2 0
	17	[439]	SETLIST  	0 0 1	; 1
	18	[439]	RETURN   	0 2
	19	[441]	RETURN   	0 1

function <./moonscript/transform/class.lua:457,463> (12 instructions, 48 bytes at 0x7fdec4c09b30)
0 params, 4 slots, 3 upvalues, 0 locals, 1 constant, 0 functions
	1	[458]	GETUPVAL 	0 0	; name
	2	[458]	TEST     	0 0 0
	3	[458]	JMP      	8	; to 12
	4	[459]	NEWTABLE 	0 0 0
	5	[460]	GETUPVAL 	1 1	; build
	6	[460]	GETTABLE 	1 1 -1	; "assign_one"
	7	[460]	GETUPVAL 	2 0	; name
	8	[460]	GETUPVAL 	3 2	; cls_name
	9	[460]	CALL     	1 3 0
	10	[461]	SETLIST  	0 0 1	; 1
	11	[461]	RETURN   	0 2
	12	[463]	RETURN   	0 1

function <./moonscript/transform/class.lua:464,468> (8 instructions, 32 bytes at 0x7fdec4c08df0)
0 params, 2 slots, 2 upvalues, 0 locals, 0 constants, 0 functions
	1	[465]	GETUPVAL 	0 0	; ret
	2	[465]	TEST     	0 0 0
	3	[465]	JMP      	4	; to 8
	4	[466]	GETUPVAL 	0 0	; ret
	5	[466]	GETUPVAL 	1 1	; cls_name
	6	[466]	TAILCALL 	0 2 0
	7	[466]	RETURN   	0 0
	8	[468]	RETURN   	0 1

function <./moonscript/transform/class.lua:471,481> (17 instructions, 68 bytes at 0x7fdec4c08e70)
0 params, 5 slots, 3 upvalues, 0 locals, 3 constants, 0 functions
	1	[472]	GETUPVAL 	0 0	; ntype
	2	[472]	GETUPVAL 	1 1	; name
	3	[472]	CALL     	0 2 2
	4	[472]	EQ       	0 0 -1	; - "value"
	5	[472]	JMP      	11	; to 17
	6	[473]	NEWTABLE 	0 0 0
	7	[474]	GETUPVAL 	1 2	; build
	8	[474]	GETTABLE 	1 1 -2	; "declare"
	9	[474]	NEWTABLE 	2 0 1
	10	[475]	NEWTABLE 	3 1 0
	11	[477]	GETUPVAL 	4 1	; name
	12	[477]	SETLIST  	3 1 1	; 1
	13	[477]	SETTABLE 	2 -3 3	; "names" -
	14	[474]	CALL     	1 2 0
	15	[479]	SETLIST  	0 0 1	; 1
	16	[479]	RETURN   	0 2
	17	[481]	RETURN   	0 1
