
main <./moonscript/transform/comprehension.lua:0,0> (14 instructions, 56 bytes at 0x7f95444068f0)
0+ params, 4 slots, 0 upvalues, 3 locals, 5 constants, 2 functions
	1	[2]	GETGLOBAL	1 -1	; require
	2	[2]	LOADK    	2 -2	; "moonscript.types"
	3	[2]	CALL     	1 2 2
	4	[2]	GETTABLE 	0 1 -3	; "is_value"
	5	[3]	LOADNIL  	1 1
	6	[46]	CLOSURE  	1 0	; 0x7f9544406ac0
	7	[47]	LOADNIL  	2 2
	8	[50]	CLOSURE  	2 1	; 0x7f9544407130
	9	[50]	MOVE     	0 0
	10	[51]	NEWTABLE 	3 0 2
	11	[52]	SETTABLE 	3 -4 1	; "construct_comprehension" -
	12	[53]	SETTABLE 	3 -5 2	; "comprehension_has_value" -
	13	[54]	RETURN   	3 2
	14	[54]	RETURN   	0 1

function <./moonscript/transform/comprehension.lua:4,46> (69 instructions, 276 bytes at 0x7f9544406ac0)
2 params, 18 slots, 0 upvalues, 18 locals, 10 constants, 0 functions
	1	[5]	MOVE     	2 0
	2	[6]	LEN      	3 1
	3	[6]	LOADK    	4 -1	; 1
	4	[6]	LOADK    	5 -2	; -1
	5	[6]	FORPREP  	3 60	; to 66
	6	[7]	GETTABLE 	7 1 6
	7	[8]	GETTABLE 	8 7 -1	; 1
	8	[9]	MOVE     	9 8
	9	[10]	EQ       	0 -3 9	; "for" -
	10	[10]	JMP      	14	; to 25
	11	[11]	LOADNIL  	10 12
	12	[12]	GETTABLE 	13 7 -1	; 1
	13	[12]	GETTABLE 	14 7 -4	; 2
	14	[12]	GETTABLE 	12 7 -5	; 3
	15	[12]	MOVE     	11 14
	16	[12]	MOVE     	10 13
	17	[13]	NEWTABLE 	13 4 0
	18	[14]	LOADK    	14 -3	; "for"
	19	[15]	MOVE     	15 11
	20	[16]	MOVE     	16 12
	21	[18]	MOVE     	17 2
	22	[18]	SETLIST  	13 4 1	; 1
	23	[18]	MOVE     	2 13
	24	[18]	JMP      	37	; to 62
	25	[19]	EQ       	0 -6 9	; "foreach" -
	26	[19]	JMP      	16	; to 43
	27	[20]	LOADNIL  	10 12
	28	[21]	GETTABLE 	13 7 -1	; 1
	29	[21]	GETTABLE 	14 7 -4	; 2
	30	[21]	GETTABLE 	12 7 -5	; 3
	31	[21]	MOVE     	11 14
	32	[21]	MOVE     	10 13
	33	[22]	NEWTABLE 	13 4 0
	34	[23]	LOADK    	14 -6	; "foreach"
	35	[24]	MOVE     	15 11
	36	[24]	NEWTABLE 	16 1 0
	37	[27]	MOVE     	17 12
	38	[27]	SETLIST  	16 1 1	; 1
	39	[29]	MOVE     	17 2
	40	[29]	SETLIST  	13 4 1	; 1
	41	[29]	MOVE     	2 13
	42	[29]	JMP      	19	; to 62
	43	[30]	EQ       	0 -7 9	; "when" -
	44	[30]	JMP      	11	; to 56
	45	[31]	LOADNIL  	10 11
	46	[32]	GETTABLE 	12 7 -1	; 1
	47	[32]	GETTABLE 	11 7 -4	; 2
	48	[32]	MOVE     	10 12
	49	[33]	NEWTABLE 	12 3 0
	50	[34]	LOADK    	13 -8	; "if"
	51	[35]	MOVE     	14 11
	52	[37]	MOVE     	15 2
	53	[37]	SETLIST  	12 3 1	; 1
	54	[37]	MOVE     	2 12
	55	[37]	JMP      	6	; to 62
	56	[39]	GETGLOBAL	10 -9	; error
	57	[39]	LOADK    	11 -10	; "Unknown comprehension clause: "
	58	[39]	MOVE     	12 8
	59	[39]	CONCAT   	11 11 12
	60	[39]	CALL     	10 2 2
	61	[39]	MOVE     	2 10
	62	[41]	NEWTABLE 	10 1 0
	63	[43]	MOVE     	11 2
	64	[43]	SETLIST  	10 1 1	; 1
	65	[43]	MOVE     	2 10
	66	[6]	FORLOOP  	3 -61	; to 6
	67	[45]	GETTABLE 	3 2 -1	; 1
	68	[45]	RETURN   	3 2
	69	[46]	RETURN   	0 1

function <./moonscript/transform/comprehension.lua:48,50> (5 instructions, 20 bytes at 0x7f9544407130)
1 param, 3 slots, 1 upvalue, 1 local, 1 constant, 0 functions
	1	[49]	GETUPVAL 	1 0	; is_value
	2	[49]	GETTABLE 	2 0 -1	; 2
	3	[49]	TAILCALL 	1 2 0
	4	[49]	RETURN   	1 0
	5	[50]	RETURN   	0 1
