-- BYTECODE -- comprehension.lua:4-46
0001    MOV      2   0
0002    LEN      3   1
0003    KSHORT   4   1
0004    KSHORT   5  -1
0005    FORI     3 => 0060
0006 => TGETV    7   1   6
0007    TGETB    8   7   1
0008    MOV      9   8
0009    ISNES    9   0      ; "for"
0010    JMP     10 => 0023
0011    KNIL    10  12
0012    TGETB   13   7   1
0013    TGETB   14   7   2
0014    TGETB   12   7   3
0015    MOV     11  14
0016    MOV     10  13
0017    TDUP    13   1
0018    TSETB   11  13   2
0019    TSETB   12  13   3
0020    TSETB    2  13   4
0021    MOV      2  13
0022    JMP     10 => 0056
0023 => ISNES    9   2      ; "foreach"
0024    JMP     10 => 0039
0025    KNIL    10  12
0026    TGETB   13   7   1
0027    TGETB   14   7   2
0028    TGETB   12   7   3
0029    MOV     11  14
0030    MOV     10  13
0031    TDUP    13   3
0032    TSETB   11  13   2
0033    TNEW    14   3
0034    TSETB   12  14   1
0035    TSETB   14  13   3
0036    TSETB    2  13   4
0037    MOV      2  13
0038    JMP     10 => 0056
0039 => ISNES    9   4      ; "when"
0040    JMP     10 => 0050
0041    KNIL    10  11
0042    TGETB   12   7   1
0043    TGETB   11   7   2
0044    MOV     10  12
0045    TDUP    12   5
0046    TSETB   11  12   2
0047    TSETB    2  12   3
0048    MOV      2  12
0049    JMP     10 => 0056
0050 => GGET    10   6      ; "error"
0051    KSTR    11   7      ; "Unknown comprehension clause: "
0052    MOV     12   8
0053    CAT     11  11  12
0054    CALL    10   2   2
0055    MOV      2  10
0056 => TNEW    10   3
0057    TSETB    2  10   1
0058    MOV      2  10
0059    FORL     3 => 0006
0060 => TGETB    3   2   1
0061    RET1     3   2

-- BYTECODE -- comprehension.lua:48-50
0001    UGET     1   0      ; is_value
0002    TGETB    2   0   2
0003    CALLT    1   2

-- BYTECODE -- comprehension.lua:0-55
0001    KPRI     0   0
0002    GGET     1   0      ; "require"
0003    KSTR     2   1      ; "moonscript.types"
0004    CALL     1   2   2
0005    TGETS    0   1   2  ; "is_value"
0006    KPRI     1   0
0007    FNEW     1   3      ; comprehension.lua:4
0008    KPRI     2   0
0009    FNEW     2   4      ; comprehension.lua:48
0010    TDUP     3   5
0011    TSETS    1   3   6  ; "construct_comprehension"
0012    TSETS    2   3   7  ; "comprehension_has_value"
0013    UCLO     0 => 0014
0014 => RET1     3   2

