
main <./moonscript/data.lua:0,0> (69 instructions, 276 bytes at 0x7fd03dc068a0)
0+ params, 28 slots, 0 upvalues, 9 locals, 39 constants, 7 functions
	1	[3]	GETGLOBAL	3 -1	; table
	2	[4]	GETTABLE 	4 3 -2	; "concat"
	3	[4]	GETTABLE 	5 3 -3	; "remove"
	4	[4]	GETTABLE 	2 3 -4	; "insert"
	5	[4]	MOVE     	1 5
	6	[4]	MOVE     	0 4
	7	[6]	LOADNIL  	3 3
	8	[14]	CLOSURE  	3 0	; 0x7fd03dc06b20
	9	[15]	LOADNIL  	4 5
	10	[18]	NEWTABLE 	6 0 4
	11	[21]	CLOSURE  	7 1	; 0x7fd03dd045b0
	12	[21]	MOVE     	0 0
	13	[21]	SETTABLE 	6 -5 7	; "__tostring" -
	14	[24]	CLOSURE  	7 2	; 0x7fd03dd049b0
	15	[24]	MOVE     	0 1
	16	[24]	SETTABLE 	6 -6 7	; "pop" -
	17	[32]	CLOSURE  	7 3	; 0x7fd03dd04b90
	18	[32]	MOVE     	0 2
	19	[32]	SETTABLE 	6 -7 7	; "push" -
	20	[35]	CLOSURE  	7 4	; 0x7fd03dd051c0
	21	[35]	SETTABLE 	6 -8 7	; "top" -
	22	[37]	SETTABLE 	6 -9 6	; "__index" -
	23	[38]	GETGLOBAL	7 -10	; setmetatable
	24	[38]	NEWTABLE 	8 0 3
	25	[42]	CLOSURE  	9 5	; 0x7fd03dd04530
	26	[42]	SETTABLE 	8 -11 9	; "__init" -
	27	[43]	SETTABLE 	8 -12 6	; "__base" -
	28	[44]	SETTABLE 	8 -13 -14	; "__name" "Stack"
	29	[45]	NEWTABLE 	9 0 2
	30	[46]	SETTABLE 	9 -9 6	; "__index" -
	31	[51]	CLOSURE  	10 6	; 0x7fd03dd05420
	32	[51]	MOVE     	0 6
	33	[51]	SETTABLE 	9 -15 10	; "__call" -
	34	[38]	CALL     	7 3 2
	35	[52]	MOVE     	5 7
	36	[53]	SETTABLE 	6 -16 5	; "__class" -
	37	[54]	MOVE     	4 5
	38	[54]	CLOSE    	5
	39	[56]	MOVE     	5 3
	40	[56]	NEWTABLE 	6 19 0
	41	[57]	LOADK    	7 -17	; "and"
	42	[58]	LOADK    	8 -18	; "break"
	43	[59]	LOADK    	9 -19	; "do"
	44	[60]	LOADK    	10 -20	; "else"
	45	[61]	LOADK    	11 -21	; "elseif"
	46	[62]	LOADK    	12 -22	; "end"
	47	[63]	LOADK    	13 -23	; "false"
	48	[64]	LOADK    	14 -24	; "for"
	49	[65]	LOADK    	15 -25	; "function"
	50	[66]	LOADK    	16 -26	; "if"
	51	[67]	LOADK    	17 -27	; "in"
	52	[68]	LOADK    	18 -28	; "local"
	53	[69]	LOADK    	19 -29	; "nil"
	54	[70]	LOADK    	20 -30	; "not"
	55	[71]	LOADK    	21 -31	; "or"
	56	[72]	LOADK    	22 -32	; "repeat"
	57	[73]	LOADK    	23 -33	; "return"
	58	[74]	LOADK    	24 -34	; "then"
	59	[75]	LOADK    	25 -35	; "true"
	60	[76]	LOADK    	26 -36	; "until"
	61	[78]	LOADK    	27 -37	; "while"
	62	[78]	SETLIST  	6 21 1	; 1
	63	[56]	CALL     	5 2 2
	64	[79]	NEWTABLE 	6 0 3
	65	[80]	SETTABLE 	6 -38 3	; "Set" -
	66	[81]	SETTABLE 	6 -14 4	; "Stack" -
	67	[82]	SETTABLE 	6 -39 5	; "lua_keywords" -
	68	[83]	RETURN   	6 2
	69	[83]	RETURN   	0 1

function <./moonscript/data.lua:7,14> (10 instructions, 40 bytes at 0x7fd03dc06b20)
1 param, 7 slots, 0 upvalues, 7 locals, 2 constants, 0 functions
	1	[8]	NEWTABLE 	1 0 0
	2	[9]	LOADK    	2 -1	; 1
	3	[9]	LEN      	3 0
	4	[9]	LOADK    	4 -1	; 1
	5	[9]	FORPREP  	2 2	; to 8
	6	[10]	GETTABLE 	6 0 5
	7	[11]	SETTABLE 	1 6 -2	; - true
	8	[9]	FORLOOP  	2 -3	; to 6
	9	[13]	RETURN   	1 2
	10	[14]	RETURN   	0 1

function <./moonscript/data.lua:19,21> (9 instructions, 36 bytes at 0x7fd03dd045b0)
1 param, 5 slots, 1 upvalue, 1 local, 3 constants, 0 functions
	1	[20]	LOADK    	1 -1	; "<Stack {"
	2	[20]	GETUPVAL 	2 0	; concat
	3	[20]	MOVE     	3 0
	4	[20]	LOADK    	4 -2	; ", "
	5	[20]	CALL     	2 3 2
	6	[20]	LOADK    	3 -3	; "}>"
	7	[20]	CONCAT   	1 1 3
	8	[20]	RETURN   	1 2
	9	[21]	RETURN   	0 1

function <./moonscript/data.lua:22,24> (5 instructions, 20 bytes at 0x7fd03dd049b0)
1 param, 3 slots, 1 upvalue, 1 local, 0 constants, 0 functions
	1	[23]	GETUPVAL 	1 0	; remove
	2	[23]	MOVE     	2 0
	3	[23]	TAILCALL 	1 2 0
	4	[23]	RETURN   	1 0
	5	[24]	RETURN   	0 1

function <./moonscript/data.lua:25,32> (14 instructions, 56 bytes at 0x7fd03dd04b90)
2+ params, 6 slots, 1 upvalue, 3 locals, 1 constant, 0 functions
	1	[26]	GETUPVAL 	3 0	; insert
	2	[26]	MOVE     	4 0
	3	[26]	MOVE     	5 1
	4	[26]	CALL     	3 3 1
	5	[27]	VARARG   	3 2
	6	[27]	TEST     	3 0 0
	7	[27]	JMP      	5	; to 13
	8	[28]	SELF     	3 0 -1	; "push"
	9	[28]	VARARG   	5 0
	10	[28]	TAILCALL 	3 0 0
	11	[28]	RETURN   	3 0
	12	[28]	JMP      	1	; to 14
	13	[30]	RETURN   	1 2
	14	[32]	RETURN   	0 1

function <./moonscript/data.lua:33,35> (4 instructions, 16 bytes at 0x7fd03dd051c0)
1 param, 2 slots, 0 upvalues, 1 local, 0 constants, 0 functions
	1	[34]	LEN      	1 0
	2	[34]	GETTABLE 	1 0 1
	3	[34]	RETURN   	1 2
	4	[35]	RETURN   	0 1

function <./moonscript/data.lua:39,42> (6 instructions, 24 bytes at 0x7fd03dd04530)
1+ param, 5 slots, 0 upvalues, 2 locals, 1 constant, 0 functions
	1	[40]	SELF     	2 0 -1	; "push"
	2	[40]	VARARG   	4 0
	3	[40]	CALL     	2 0 1
	4	[41]	LOADNIL  	2 2
	5	[41]	RETURN   	2 2
	6	[42]	RETURN   	0 1

function <./moonscript/data.lua:47,51> (10 instructions, 40 bytes at 0x7fd03dd05420)
1+ param, 6 slots, 1 upvalue, 3 locals, 2 constants, 0 functions
	1	[48]	GETGLOBAL	2 -1	; setmetatable
	2	[48]	NEWTABLE 	3 0 0
	3	[48]	GETUPVAL 	4 0	; _base_0
	4	[48]	CALL     	2 3 2
	5	[49]	GETTABLE 	3 0 -2	; "__init"
	6	[49]	MOVE     	4 2
	7	[49]	VARARG   	5 0
	8	[49]	CALL     	3 0 1
	9	[50]	RETURN   	2 2
	10	[51]	RETURN   	0 1
