
main <./moonscript/dump.lua:0,0> (13 instructions, 52 bytes at 0x7f8ab34068a0)
0+ params, 4 slots, 0 upvalues, 3 locals, 2 constants, 3 functions
	1	[25]	CLOSURE  	0 0	; 0x7f8ab3406af0
	2	[25]	MOVE     	0 0
	3	[26]	LOADNIL  	1 1
	4	[29]	CLOSURE  	1 1	; 0x7f8ab3406d00
	5	[29]	MOVE     	0 0
	6	[30]	LOADNIL  	2 2
	7	[37]	CLOSURE  	2 2	; 0x7f8ab3407520
	8	[37]	MOVE     	0 0
	9	[38]	NEWTABLE 	3 0 2
	10	[39]	SETTABLE 	3 -1 1	; "value" -
	11	[40]	SETTABLE 	3 -2 2	; "tree" -
	12	[41]	RETURN   	3 2
	13	[41]	RETURN   	0 1

function <./moonscript/dump.lua:2,25> (58 instructions, 232 bytes at 0x7f8ab3406af0)
2 params, 13 slots, 1 upvalue, 11 locals, 15 constants, 0 functions
	1	[3]	EQ       	0 1 -1	; - nil
	2	[3]	JMP      	1	; to 4
	3	[4]	LOADK    	1 -2	; 1
	4	[6]	GETGLOBAL	2 -3	; type
	5	[6]	MOVE     	3 0
	6	[6]	CALL     	2 2 2
	7	[6]	EQ       	0 2 -4	; - "string"
	8	[6]	JMP      	5	; to 14
	9	[7]	LOADK    	2 -5	; "\""
	10	[7]	MOVE     	3 0
	11	[7]	LOADK    	4 -5	; "\""
	12	[7]	CONCAT   	2 2 4
	13	[7]	RETURN   	2 2
	14	[9]	GETGLOBAL	2 -3	; type
	15	[9]	MOVE     	3 0
	16	[9]	CALL     	2 2 2
	17	[9]	EQ       	1 2 -6	; - "table"
	18	[9]	JMP      	4	; to 23
	19	[10]	GETGLOBAL	2 -7	; tostring
	20	[10]	MOVE     	3 0
	21	[10]	TAILCALL 	2 2 0
	22	[10]	RETURN   	2 0
	23	[12]	LOADNIL  	2 2
	24	[14]	NEWTABLE 	3 0 0
	25	[15]	LOADK    	4 -2	; 1
	26	[16]	LOADK    	5 -2	; 1
	27	[16]	LEN      	6 0
	28	[16]	LOADK    	7 -2	; 1
	29	[16]	FORPREP  	5 7	; to 37
	30	[17]	GETTABLE 	9 0 8
	31	[18]	GETUPVAL 	10 0	; flat_value
	32	[18]	MOVE     	11 9
	33	[18]	ADD      	12 1 -2	; - 1
	34	[18]	CALL     	10 3 2
	35	[18]	SETTABLE 	3 4 10
	36	[19]	ADD      	4 4 -2	; - 1
	37	[16]	FORLOOP  	5 -8	; to 30
	38	[21]	MOVE     	2 3
	39	[23]	GETTABLE 	3 0 -8	; -1
	40	[24]	LOADK    	4 -9	; "{"
	41	[24]	TEST     	3 0 0
	42	[24]	JMP      	6	; to 49
	43	[24]	LOADK    	5 -10	; "["
	44	[24]	MOVE     	6 3
	45	[24]	LOADK    	7 -11	; "] "
	46	[24]	CONCAT   	5 5 7
	47	[24]	TEST     	5 0 1
	48	[24]	JMP      	1	; to 50
	49	[24]	LOADK    	5 -12	; ""
	50	[24]	GETGLOBAL	6 -6	; table
	51	[24]	GETTABLE 	6 6 -13	; "concat"
	52	[24]	MOVE     	7 2
	53	[24]	LOADK    	8 -14	; ", "
	54	[24]	CALL     	6 3 2
	55	[24]	LOADK    	7 -15	; "}"
	56	[24]	CONCAT   	4 4 7
	57	[24]	RETURN   	4 2
	58	[25]	RETURN   	0 1

function <./moonscript/dump.lua:27,29> (5 instructions, 20 bytes at 0x7f8ab3406d00)
1 param, 3 slots, 1 upvalue, 1 local, 0 constants, 0 functions
	1	[28]	GETUPVAL 	1 0	; flat_value
	2	[28]	MOVE     	2 0
	3	[28]	TAILCALL 	1 2 0
	4	[28]	RETURN   	1 0
	5	[29]	RETURN   	0 1

function <./moonscript/dump.lua:31,37> (13 instructions, 52 bytes at 0x7f8ab3407520)
1 param, 10 slots, 1 upvalue, 7 locals, 2 constants, 0 functions
	1	[32]	MOVE     	1 0
	2	[33]	LOADK    	2 -1	; 1
	3	[33]	LEN      	3 1
	4	[33]	LOADK    	4 -1	; 1
	5	[33]	FORPREP  	2 6	; to 12
	6	[34]	GETTABLE 	6 1 5
	7	[35]	GETGLOBAL	7 -2	; print
	8	[35]	GETUPVAL 	8 0	; flat_value
	9	[35]	MOVE     	9 6
	10	[35]	CALL     	8 2 0
	11	[35]	CALL     	7 0 1
	12	[33]	FORLOOP  	2 -7	; to 6
	13	[37]	RETURN   	0 1
