-- BYTECODE -- env.lua:20-32
0001    TNEW     0   0
0002    KSHORT   1   1
0003    TNEW     2   3
0004    VARG     3   0   0
0005    TSETM    3   0      ; 1
0006    KSHORT   3   1
0007    LEN      4   2
0008    KSHORT   5   1
0009    FORI     3 => 0017
0010 => TGETV    7   2   6
0011    GGET     8   0      ; "tostring"
0012    MOV      9   7
0013    CALL     8   2   2
0014    TSETV    8   0   1
0015    ADDVN    1   1   1  ; 1
0016    FORL     3 => 0010
0017 => RET1     0   2

-- BYTECODE -- env.lua:19-34
0001    GGET     0   0      ; "table"
0002    TGETS    0   0   1  ; "concat"
0003    FNEW     1   2      ; env.lua:20
0004    VARG     2   0   0
0005    CALLM    1   2   0
0006    KSTR     2   3      ; ", "
0007    CALL     0   2   3
0008    GGET     1   4      ; "io"
0009    TGETS    1   1   5  ; "stderr"
0010    MOV      2   1
0011    TGETS    1   1   6  ; "write"
0012    GGET     3   7      ; "tostring"
0013    UGET     4   0      ; indent_char
0014    MOV      5   4
0015    TGETS    4   4   8  ; "rep"
0016    UGET     6   1      ; indent
0017    CALL     4   0   3
0018    CALLM    3   2   0
0019    GGET     4   7      ; "tostring"
0020    MOV      5   0
0021    CALL     4   2   2
0022    KSTR     5   9      ; "\n"
0023    CAT      3   3   5
0024    UCLO     0 => 0025
0025 => CALLT    1   3

-- BYTECODE -- env.lua:37-42
0001    MOV      3   0
0002    TGETS    2   0   0  ; "sub"
0003    MOV      4   1
0004    KSHORT   5  -1
0005    CALL     2   2   4
0006    MOV      3   2
0007    TGETS    2   2   1  ; "match"
0008    KSTR     4   2      ; "^([^\n]*)"
0009    CALL     2   2   3
0010    UGET     3   0      ; iprint
0011    KSTR     4   3      ; "* "
0012    GGET     5   4      ; "tostring"
0013    UGET     6   1      ; name
0014    CALL     5   2   2
0015    KSTR     6   5      ; " ("
0016    GGET     7   4      ; "tostring"
0017    MOV      8   2
0018    CALL     7   2   2
0019    KSTR     8   6      ; ")"
0020    CAT      4   4   8
0021    CALL     3   1   2
0022    UGET     3   2      ; indent
0023    ADDVN    3   3   0  ; 1
0024    USETV    2   3      ; indent
0025    KPRI     3   2
0026    RET1     3   2

-- BYTECODE -- env.lua:42-46
0001    UGET     2   0      ; iprint
0002    UGET     3   1      ; name
0003    KPRI     4   2
0004    CALL     2   1   3
0005    UGET     2   2      ; indent
0006    SUBVN    2   2   0  ; 1
0007    USETV    2   2      ; indent
0008    KPRI     2   2
0009    VARG     3   0   2
0010    RETM     2   1

-- BYTECODE -- env.lua:46-50
0001    UGET     0   0      ; iprint
0002    UGET     1   1      ; name
0003    KPRI     2   1
0004    CALL     0   1   3
0005    UGET     0   2      ; indent
0006    SUBVN    0   0   0  ; 1
0007    USETV    2   0      ; indent
0008    KPRI     0   1
0009    RET1     0   2

-- BYTECODE -- env.lua:35-52
0001    UGET     1   0      ; V
0002    MOV      2   0
0003    CALL     1   2   2
0004    UGET     2   1      ; Cmt
0005    KSTR     3   0      ; ""
0006    FNEW     4   1      ; env.lua:37
0007    CALL     2   2   3
0008    UGET     3   1      ; Cmt
0009    MOV      4   1
0010    FNEW     5   2      ; env.lua:42
0011    CALL     3   2   3
0012    MULVV    2   2   3
0013    UGET     3   1      ; Cmt
0014    KSTR     4   0      ; ""
0015    FNEW     5   3      ; env.lua:46
0016    CALL     3   2   3
0017    ADDVV    1   2   3
0018    UCLO     0 => 0019
0019 => RET1     1   2

-- BYTECODE -- env.lua:55-65
0001    UGET     2   0      ; env
0002    TGETV    2   2   1
0003    ISEQP    2   0
0004    JMP      3 => 0006
0005    RET1     2   2
0006 => MOV      4   1
0007    TGETS    3   1   0  ; "match"
0008    KSTR     5   1      ; "^[A-Z][A-Za-z0-9]*$"
0009    CALL     3   2   3
0010    ISF          3
0011    JMP      4 => 0016
0012    UGET     3   1      ; wrap_name
0013    MOV      4   1
0014    CALL     3   2   2
0015    RET1     3   2
0016 => GGET     3   2      ; "error"
0017    KSTR     4   3      ; "unknown variable referenced: "
0018    GGET     5   4      ; "tostring"
0019    MOV      6   1
0020    CALL     5   2   2
0021    CAT      4   4   5
0022    CALLT    3   2

-- BYTECODE -- env.lua:7-67
0001    KNIL     2   3
0002    GGET     4   0      ; "require"
0003    KSTR     5   1      ; "lpeg"
0004    CALL     4   2   2
0005    TGETS    5   4   2  ; "V"
0006    TGETS    3   4   3  ; "Cmt"
0007    MOV      2   5
0008    UGET     4   0      ; getfenv
0009    MOV      5   1
0010    CALL     4   2   2
0011    MOV      5   2
0012    ISF          0
0013    JMP      6 => 0020
0014    KSHORT   6   0
0015    KSTR     7   4      ; "  "
0016    KPRI     8   0
0017    FNEW     8   5      ; env.lua:19
0018    FNEW     5   6      ; env.lua:35
0019    UCLO     6 => 0020
0020 => UGET     6   1      ; setfenv
0021    MOV      7   1
0022    GGET     8   7      ; "setmetatable"
0023    TNEW     9   0
0024    TDUP    10   9
0025    FNEW    11   8      ; env.lua:55
0026    TSETS   11  10  10  ; "__index"
0027    CALL     8   0   3
0028    UCLO     0 => 0029
0029 => CALLMT   6   1

-- BYTECODE -- env.lua:0-71
0001    KNIL     0   1
0002    GGET     2   0      ; "require"
0003    KSTR     3   1      ; "moonscript.util"
0004    CALL     2   2   2
0005    TGETS    3   2   2  ; "getfenv"
0006    TGETS    1   2   3  ; "setfenv"
0007    MOV      0   3
0008    KPRI     2   0
0009    FNEW     2   4      ; env.lua:7
0010    TDUP     3   5
0011    TSETS    2   3   6  ; "wrap_env"
0012    UCLO     0 => 0013
0013 => RET1     3   2

