
main <./moonscript/errors.lua:0,0> (39 instructions, 156 bytes at 0x7fde8ac068b0)
0+ params, 12 slots, 0 upvalues, 12 locals, 12 constants, 5 functions
	1	[1]	GETGLOBAL	0 -1	; require
	2	[1]	LOADK    	1 -2	; "moonscript.util"
	3	[1]	CALL     	0 2 2
	4	[2]	GETGLOBAL	1 -1	; require
	5	[2]	LOADK    	2 -3	; "lpeg"
	6	[2]	CALL     	1 2 2
	7	[3]	LOADNIL  	2 3
	8	[5]	GETGLOBAL	4 -4	; table
	9	[6]	GETTABLE 	5 4 -5	; "concat"
	10	[6]	GETTABLE 	3 4 -6	; "insert"
	11	[6]	MOVE     	2 5
	12	[8]	LOADNIL  	4 5
	13	[9]	GETTABLE 	6 0 -7	; "split"
	14	[9]	GETTABLE 	5 0 -8	; "pos_to_line"
	15	[9]	MOVE     	4 6
	16	[10]	LOADNIL  	6 6
	17	[16]	CLOSURE  	6 0	; 0x7fde8ac06f60
	18	[17]	LOADNIL  	7 7
	19	[27]	CLOSURE  	7 1	; 0x7fde8ac06ba0
	20	[27]	MOVE     	0 5
	21	[28]	LOADNIL  	8 8
	22	[36]	CLOSURE  	8 2	; 0x7fde8ac066e0
	23	[36]	MOVE     	0 7
	24	[37]	LOADNIL  	9 9
	25	[64]	CLOSURE  	9 3	; 0x7fde8ac07770
	26	[64]	MOVE     	0 4
	27	[64]	MOVE     	0 2
	28	[65]	LOADNIL  	10 10
	29	[111]	CLOSURE  	10 4	; 0x7fde8ac079f0
	30	[111]	MOVE     	0 1
	31	[111]	MOVE     	0 2
	32	[111]	MOVE     	0 8
	33	[112]	NEWTABLE 	11 0 4
	34	[113]	SETTABLE 	11 -9 10	; "rewrite_traceback" -
	35	[114]	SETTABLE 	11 -10 9	; "truncate_traceback" -
	36	[115]	SETTABLE 	11 -11 6	; "user_error" -
	37	[116]	SETTABLE 	11 -12 8	; "reverse_line_number" -
	38	[117]	RETURN   	11 2
	39	[117]	RETURN   	0 1

function <./moonscript/errors.lua:11,16> (8 instructions, 32 bytes at 0x7fde8ac06f60)
0+ params, 5 slots, 0 upvalues, 1 local, 2 constants, 0 functions
	1	[12]	GETGLOBAL	1 -1	; error
	2	[12]	NEWTABLE 	2 1 0
	3	[13]	LOADK    	3 -2	; "user-error"
	4	[13]	VARARG   	4 0
	5	[15]	SETLIST  	2 0 1	; 1
	6	[12]	TAILCALL 	1 2 0
	7	[15]	RETURN   	1 0
	8	[16]	RETURN   	0 1

function <./moonscript/errors.lua:18,27> (21 instructions, 84 bytes at 0x7fde8ac06ba0)
3 params, 7 slots, 1 upvalue, 4 locals, 6 constants, 0 functions
	1	[19]	GETTABLE 	3 2 0
	2	[19]	TEST     	3 0 1
	3	[19]	JMP      	12	; to 16
	4	[21]	GETGLOBAL	3 -1	; assert
	5	[21]	GETGLOBAL	4 -2	; io
	6	[21]	GETTABLE 	4 4 -3	; "open"
	7	[21]	MOVE     	5 0
	8	[21]	CALL     	4 2 0
	9	[21]	CALL     	3 0 2
	10	[22]	SELF     	4 3 -4	; "read"
	11	[22]	LOADK    	6 -5	; "*a"
	12	[22]	CALL     	4 3 2
	13	[22]	SETTABLE 	2 0 4
	14	[23]	SELF     	4 3 -6	; "close"
	15	[23]	CALL     	4 2 1
	16	[26]	GETUPVAL 	3 0	; pos_to_line
	17	[26]	GETTABLE 	4 2 0
	18	[26]	MOVE     	5 1
	19	[26]	TAILCALL 	3 3 0
	20	[26]	RETURN   	3 0
	21	[27]	RETURN   	0 1

function <./moonscript/errors.lua:29,36> (17 instructions, 68 bytes at 0x7fde8ac066e0)
4 params, 12 slots, 1 upvalue, 8 locals, 3 constants, 0 functions
	1	[30]	MOVE     	4 2
	2	[30]	LOADK    	5 -1	; 0
	3	[30]	LOADK    	6 -2	; -1
	4	[30]	FORPREP  	4 9	; to 14
	5	[31]	GETTABLE 	8 1 7
	6	[31]	TEST     	8 0 0
	7	[31]	JMP      	6	; to 14
	8	[32]	GETUPVAL 	8 0	; lookup_line
	9	[32]	MOVE     	9 0
	10	[32]	GETTABLE 	10 1 7
	11	[32]	MOVE     	11 3
	12	[32]	TAILCALL 	8 4 0
	13	[32]	RETURN   	8 0
	14	[30]	FORLOOP  	4 -10	; to 5
	15	[35]	LOADK    	4 -3	; "unknown"
	16	[35]	RETURN   	4 2
	17	[36]	RETURN   	0 1

function <./moonscript/errors.lua:38,64> (56 instructions, 224 bytes at 0x7fde8ac07770)
2 params, 11 slots, 2 upvalues, 12 locals, 10 constants, 0 functions
	1	[39]	EQ       	0 1 -1	; - nil
	2	[39]	JMP      	1	; to 4
	3	[40]	LOADK    	1 -2	; "moonscript_chunk"
	4	[42]	GETUPVAL 	2 0	; split
	5	[42]	MOVE     	3 0
	6	[42]	LOADK    	4 -3	; "\n"
	7	[42]	CALL     	2 3 2
	8	[42]	MOVE     	0 2
	9	[43]	LEN      	2 0
	10	[44]	LT       	0 -4 2	; 1 -
	11	[44]	JMP      	9	; to 21
	12	[45]	GETTABLE 	3 0 2
	13	[45]	SELF     	3 3 -5	; "match"
	14	[45]	MOVE     	5 1
	15	[45]	CALL     	3 3 2
	16	[45]	TEST     	3 0 0
	17	[45]	JMP      	1	; to 19
	18	[46]	JMP      	2	; to 21
	19	[48]	SUB      	2 2 -4	; - 1
	20	[48]	JMP      	-11	; to 10
	21	[51]	NEWTABLE 	3 0 0
	22	[52]	LOADK    	4 -4	; 1
	23	[53]	MOVE     	5 2
	24	[54]	LOADK    	6 -4	; 1
	25	[54]	LT       	0 5 -6	; - 0
	26	[54]	JMP      	4	; to 31
	27	[54]	LEN      	7 0
	28	[54]	ADD      	7 7 5
	29	[54]	TEST     	7 0 1
	30	[54]	JMP      	1	; to 32
	31	[54]	MOVE     	7 5
	32	[54]	LOADK    	8 -4	; 1
	33	[54]	FORPREP  	6 3	; to 37
	34	[55]	GETTABLE 	10 0 9
	35	[56]	SETTABLE 	3 4 10
	36	[57]	ADD      	4 4 -4	; - 1
	37	[54]	FORLOOP  	6 -4	; to 34
	38	[59]	MOVE     	0 3
	39	[61]	LOADK    	3 -7	; "function '"
	40	[61]	MOVE     	4 1
	41	[61]	LOADK    	5 -8	; "'"
	42	[61]	CONCAT   	3 3 5
	43	[62]	LEN      	4 0
	44	[62]	LEN      	5 0
	45	[62]	GETTABLE 	5 0 5
	46	[62]	SELF     	5 5 -9	; "gsub"
	47	[62]	MOVE     	7 3
	48	[62]	LOADK    	8 -10	; "main chunk"
	49	[62]	CALL     	5 4 2
	50	[62]	SETTABLE 	0 4 5
	51	[63]	GETUPVAL 	4 1	; concat
	52	[63]	MOVE     	5 0
	53	[63]	LOADK    	6 -3	; "\n"
	54	[63]	TAILCALL 	4 3 0
	55	[63]	RETURN   	4 0
	56	[64]	RETURN   	0 1

function <./moonscript/errors.lua:66,111> (91 instructions, 364 bytes at 0x7fde8ac079f0)
2 params, 23 slots, 3 upvalues, 20 locals, 19 constants, 1 function
	1	[67]	GETGLOBAL	2 -1	; require
	2	[67]	LOADK    	3 -2	; "moonscript.line_tables"
	3	[67]	CALL     	2 2 2
	4	[68]	LOADNIL  	3 6
	5	[69]	GETUPVAL 	7 0	; lpeg
	6	[69]	GETTABLE 	7 7 -3	; "V"
	7	[69]	GETUPVAL 	8 0	; lpeg
	8	[69]	GETTABLE 	8 8 -4	; "S"
	9	[69]	GETUPVAL 	9 0	; lpeg
	10	[69]	GETTABLE 	9 9 -5	; "Ct"
	11	[69]	GETUPVAL 	10 0	; lpeg
	12	[69]	GETTABLE 	6 10 -6	; "C"
	13	[69]	MOVE     	5 9
	14	[69]	MOVE     	4 8
	15	[69]	MOVE     	3 7
	16	[70]	LOADK    	7 -7	; "stack traceback:"
	17	[71]	MOVE     	8 3
	18	[71]	LOADK    	9 -8	; "Header"
	19	[71]	CALL     	8 2 2
	20	[71]	MOVE     	9 3
	21	[71]	LOADK    	10 -9	; "Line"
	22	[71]	CALL     	9 2 2
	23	[72]	GETUPVAL 	10 0	; lpeg
	24	[72]	GETTABLE 	10 10 -4	; "S"
	25	[72]	LOADK    	11 -10	; "\n"
	26	[72]	CALL     	10 2 2
	27	[73]	GETUPVAL 	11 0	; lpeg
	28	[73]	GETTABLE 	11 11 -11	; "P"
	29	[73]	NEWTABLE 	12 1 2
	30	[74]	MOVE     	13 8
	31	[75]	MUL      	14 7 10
	32	[75]	MOVE     	15 5
	33	[75]	POW      	16 9 -12	; - 1
	34	[75]	CALL     	15 2 2
	35	[75]	MUL      	14 14 15
	36	[75]	SETTABLE 	12 -8 14	; "Header" -
	37	[76]	MOVE     	14 6
	38	[76]	SUB      	15 -12 10	; 1 -
	39	[76]	POW      	15 15 -14	; - 0
	40	[76]	CALL     	14 2 2
	41	[76]	MUL      	14 -13 14	; "\t" -
	42	[76]	ADD      	15 10 -15	; - -1
	43	[76]	MUL      	14 14 15
	44	[76]	SETTABLE 	12 -9 14	; "Line" -
	45	[77]	SETLIST  	12 1 1	; 1
	46	[73]	CALL     	11 2 2
	47	[78]	NEWTABLE 	12 0 0
	48	[79]	LOADNIL  	13 13
	49	[97]	CLOSURE  	13 0	; 0x7fde8ac086a0
	50	[97]	MOVE     	0 2
	51	[97]	GETUPVAL 	0 1	; concat
	52	[97]	GETUPVAL 	0 2	; reverse_line_number
	53	[97]	MOVE     	0 12
	54	[98]	MOVE     	14 13
	55	[98]	MOVE     	15 1
	56	[98]	CALL     	14 2 2
	57	[98]	MOVE     	1 14
	58	[99]	SELF     	14 11 -16	; "match"
	59	[99]	MOVE     	16 0
	60	[99]	CALL     	14 3 2
	61	[100]	TEST     	14 0 1
	62	[100]	JMP      	2	; to 65
	63	[101]	LOADNIL  	15 15
	64	[101]	RETURN   	15 2
	65	[103]	GETGLOBAL	15 -17	; ipairs
	66	[103]	MOVE     	16 14
	67	[103]	CALL     	15 2 4
	68	[103]	JMP      	4	; to 73
	69	[104]	MOVE     	20 13
	70	[104]	MOVE     	21 19
	71	[104]	CALL     	20 2 2
	72	[104]	SETTABLE 	14 18 20
	73	[103]	TFORLOOP 	15 2
	74	[104]	JMP      	-6	; to 69
	75	[106]	GETUPVAL 	15 1	; concat
	76	[106]	NEWTABLE 	16 3 0
	77	[107]	LOADK    	17 -18	; "moon: "
	78	[107]	MOVE     	18 1
	79	[107]	CONCAT   	17 17 18
	80	[108]	MOVE     	18 7
	81	[109]	LOADK    	19 -13	; "\t"
	82	[109]	GETUPVAL 	20 1	; concat
	83	[109]	MOVE     	21 14
	84	[109]	LOADK    	22 -19	; "\n\t"
	85	[109]	CALL     	20 3 2
	86	[109]	CONCAT   	19 19 20
	87	[110]	SETLIST  	16 3 1	; 1
	88	[110]	LOADK    	17 -10	; "\n"
	89	[106]	TAILCALL 	15 3 0
	90	[110]	RETURN   	15 0
	91	[111]	RETURN   	0 1

function <./moonscript/errors.lua:80,97> (35 instructions, 140 bytes at 0x7fde8ac086a0)
1 param, 15 slots, 4 upvalues, 5 locals, 8 constants, 0 functions
	1	[81]	SELF     	1 0 -1	; "match"
	2	[81]	LOADK    	3 -2	; "^(.-):(%d+): (.*)$"
	3	[81]	CALL     	1 3 4
	4	[82]	GETUPVAL 	4 0	; line_tables
	5	[82]	LOADK    	5 -3	; "@"
	6	[82]	GETGLOBAL	6 -4	; tostring
	7	[82]	MOVE     	7 1
	8	[82]	CALL     	6 2 2
	9	[82]	CONCAT   	5 5 6
	10	[82]	GETTABLE 	4 4 5
	11	[83]	TEST     	1 0 0
	12	[83]	JMP      	21	; to 34
	13	[83]	TEST     	4 0 0
	14	[83]	JMP      	19	; to 34
	15	[84]	GETUPVAL 	5 1	; concat
	16	[84]	NEWTABLE 	6 8 0
	17	[85]	MOVE     	7 1
	18	[86]	LOADK    	8 -5	; ":"
	19	[87]	GETUPVAL 	9 2	; reverse_line_number
	20	[87]	MOVE     	10 1
	21	[87]	MOVE     	11 4
	22	[87]	MOVE     	12 2
	23	[87]	GETUPVAL 	13 3	; cache
	24	[87]	CALL     	9 5 2
	25	[88]	LOADK    	10 -6	; ": "
	26	[89]	LOADK    	11 -7	; "("
	27	[90]	MOVE     	12 2
	28	[91]	LOADK    	13 -8	; ") "
	29	[93]	MOVE     	14 3
	30	[93]	SETLIST  	6 8 1	; 1
	31	[84]	TAILCALL 	5 2 0
	32	[93]	RETURN   	5 0
	33	[93]	JMP      	1	; to 35
	34	[95]	RETURN   	0 2
	35	[97]	RETURN   	0 1
