
main <./moon/init.lua:0,0> (60 instructions, 240 bytes at 0x7fec21c068a0)
0+ params, 21 slots, 0 upvalues, 18 locals, 21 constants, 13 functions
	1	[1]	NEWTABLE 	0 0 2
	2	[2]	GETGLOBAL	1 -1	; debug
	3	[2]	SETTABLE 	0 -1 1	; "debug" -
	4	[3]	GETGLOBAL	1 -2	; type
	5	[3]	SETTABLE 	0 -2 1	; "type" -
	6	[5]	LOADNIL  	1 3
	7	[7]	GETGLOBAL	4 -3	; require
	8	[7]	LOADK    	5 -4	; "moonscript.util"
	9	[7]	CALL     	4 2 2
	10	[8]	GETTABLE 	5 4 -5	; "getfenv"
	11	[8]	GETTABLE 	6 4 -6	; "setfenv"
	12	[8]	GETTABLE 	3 4 -7	; "dump"
	13	[8]	MOVE     	2 6
	14	[8]	MOVE     	1 5
	15	[10]	LOADNIL  	4 16
	16	[13]	CLOSURE  	4 0	; 0x7fec21c06b80
	17	[13]	MOVE     	0 3
	18	[16]	CLOSURE  	5 1	; 0x7fec21c06700
	19	[16]	MOVE     	0 0
	20	[26]	CLOSURE  	6 2	; 0x7fec21c074d0
	21	[26]	MOVE     	0 0
	22	[27]	GETGLOBAL	17 -8	; setmetatable
	23	[27]	NEWTABLE 	18 0 1
	24	[48]	CLOSURE  	19 3	; 0x7fec21c06c00
	25	[48]	MOVE     	0 0
	26	[48]	SETTABLE 	18 -9 19	; "upvalue" -
	27	[49]	NEWTABLE 	19 0 1
	28	[50]	GETTABLE 	20 0 -1	; "debug"
	29	[50]	SETTABLE 	19 -10 20	; "__index" -
	30	[27]	CALL     	17 3 2
	31	[51]	MOVE     	7 17
	32	[66]	CLOSURE  	8 4	; 0x7fec21c07e70
	33	[66]	MOVE     	0 1
	34	[66]	MOVE     	0 2
	35	[83]	CLOSURE  	9 5	; 0x7fec21c06fd0
	36	[83]	MOVE     	0 0
	37	[96]	CLOSURE  	10 6	; 0x7fec21c09650
	38	[112]	CLOSURE  	11 7	; 0x7fec21c09d40
	39	[119]	CLOSURE  	12 8	; 0x7fec21c06640
	40	[127]	CLOSURE  	13 9	; 0x7fec21c07440
	41	[135]	CLOSURE  	14 10	; 0x7fec21c094f0
	42	[147]	CLOSURE  	15 11	; 0x7fec21c0a570
	43	[159]	CLOSURE  	16 12	; 0x7fec21c0a920
	44	[160]	NEWTABLE 	17 0 14
	45	[161]	SETTABLE 	17 -7 3	; "dump" -
	46	[162]	SETTABLE 	17 -11 4	; "p" -
	47	[163]	SETTABLE 	17 -12 5	; "is_object" -
	48	[164]	SETTABLE 	17 -2 6	; "type" -
	49	[165]	SETTABLE 	17 -1 7	; "debug" -
	50	[166]	SETTABLE 	17 -13 8	; "run_with_scope" -
	51	[167]	SETTABLE 	17 -14 9	; "bind_methods" -
	52	[168]	SETTABLE 	17 -15 10	; "defaultbl" -
	53	[169]	SETTABLE 	17 -16 11	; "extend" -
	54	[170]	SETTABLE 	17 -17 12	; "copy" -
	55	[171]	SETTABLE 	17 -18 13	; "mixin" -
	56	[172]	SETTABLE 	17 -19 14	; "mixin_object" -
	57	[173]	SETTABLE 	17 -20 15	; "mixin_table" -
	58	[174]	SETTABLE 	17 -21 16	; "fold" -
	59	[175]	RETURN   	17 2
	60	[175]	RETURN   	0 1

function <./moon/init.lua:11,13> (7 instructions, 28 bytes at 0x7fec21c06b80)
0+ params, 4 slots, 1 upvalue, 1 local, 1 constant, 0 functions
	1	[12]	GETGLOBAL	1 -1	; print
	2	[12]	GETUPVAL 	2 0	; dump
	3	[12]	VARARG   	3 0
	4	[12]	CALL     	2 0 0
	5	[12]	TAILCALL 	1 0 0
	6	[12]	RETURN   	1 0
	7	[13]	RETURN   	0 1

function <./moon/init.lua:14,16> (12 instructions, 48 bytes at 0x7fec21c06700)
1 param, 3 slots, 1 upvalue, 1 local, 3 constants, 0 functions
	1	[15]	GETUPVAL 	1 0	; lua
	2	[15]	GETTABLE 	1 1 -1	; "type"
	3	[15]	MOVE     	2 0
	4	[15]	CALL     	1 2 2
	5	[15]	EQ       	0 1 -2	; - "table"
	6	[15]	JMP      	2	; to 9
	7	[15]	GETTABLE 	1 0 -3	; "__class"
	8	[15]	JMP      	2	; to 11
	9	[15]	LOADBOOL 	1 0 1
	10	[15]	LOADBOOL 	1 1 0
	11	[15]	RETURN   	1 2
	12	[16]	RETURN   	0 1

function <./moon/init.lua:17,26> (12 instructions, 48 bytes at 0x7fec21c074d0)
1 param, 3 slots, 1 upvalue, 3 locals, 3 constants, 0 functions
	1	[18]	GETUPVAL 	1 0	; lua
	2	[18]	GETTABLE 	1 1 -1	; "type"
	3	[18]	MOVE     	2 0
	4	[18]	CALL     	1 2 2
	5	[19]	EQ       	0 1 -2	; - "table"
	6	[19]	JMP      	4	; to 11
	7	[20]	GETTABLE 	2 0 -3	; "__class"
	8	[21]	TEST     	2 0 0
	9	[21]	JMP      	1	; to 11
	10	[22]	RETURN   	2 2
	11	[25]	RETURN   	1 2
	12	[26]	RETURN   	0 1

function <./moon/init.lua:28,48> (43 instructions, 172 bytes at 0x7fec21c06c00)
3 params, 9 slots, 1 upvalue, 8 locals, 8 constants, 0 functions
	1	[29]	NEWTABLE 	3 0 0
	2	[30]	LOADK    	4 -1	; 1
	3	[32]	GETUPVAL 	5 0	; lua
	4	[32]	GETTABLE 	5 5 -2	; "debug"
	5	[32]	GETTABLE 	5 5 -3	; "getupvalue"
	6	[32]	MOVE     	6 0
	7	[32]	MOVE     	7 4
	8	[32]	CALL     	5 3 2
	9	[33]	EQ       	0 5 -4	; - nil
	10	[33]	JMP      	1	; to 12
	11	[34]	JMP      	3	; to 15
	12	[36]	SETTABLE 	3 5 4
	13	[37]	ADD      	4 4 -1	; - 1
	14	[37]	JMP      	-12	; to 3
	15	[39]	GETTABLE 	5 3 1
	16	[39]	TEST     	5 0 1
	17	[39]	JMP      	7	; to 25
	18	[40]	GETGLOBAL	5 -5	; error
	19	[40]	LOADK    	6 -6	; "Failed to find upvalue: "
	20	[40]	GETGLOBAL	7 -7	; tostring
	21	[40]	MOVE     	8 1
	22	[40]	CALL     	7 2 2
	23	[40]	CONCAT   	6 6 7
	24	[40]	CALL     	5 2 1
	25	[42]	TEST     	2 0 1
	26	[42]	JMP      	8	; to 35
	27	[43]	GETUPVAL 	5 0	; lua
	28	[43]	GETTABLE 	5 5 -2	; "debug"
	29	[43]	GETTABLE 	5 5 -3	; "getupvalue"
	30	[43]	MOVE     	6 0
	31	[43]	GETTABLE 	7 3 1
	32	[43]	CALL     	5 3 3
	33	[44]	RETURN   	6 2
	34	[44]	JMP      	8	; to 43
	35	[46]	GETUPVAL 	5 0	; lua
	36	[46]	GETTABLE 	5 5 -2	; "debug"
	37	[46]	GETTABLE 	5 5 -8	; "setupvalue"
	38	[46]	MOVE     	6 0
	39	[46]	GETTABLE 	7 3 1
	40	[46]	MOVE     	8 2
	41	[46]	TAILCALL 	5 4 0
	42	[46]	RETURN   	5 0
	43	[48]	RETURN   	0 1

function <./moon/init.lua:52,66> (20 instructions, 80 bytes at 0x7fec21c07e70)
2+ params, 8 slots, 2 upvalues, 5 locals, 2 constants, 1 function
	1	[53]	GETUPVAL 	3 0	; getfenv
	2	[53]	MOVE     	4 0
	3	[53]	CALL     	3 2 2
	4	[54]	GETGLOBAL	4 -1	; setmetatable
	5	[54]	NEWTABLE 	5 0 0
	6	[54]	NEWTABLE 	6 0 1
	7	[62]	CLOSURE  	7 0	; 0x7fec21c081f0
	8	[62]	MOVE     	0 1
	9	[62]	MOVE     	0 3
	10	[62]	SETTABLE 	6 -2 7	; "__index" -
	11	[54]	CALL     	4 3 2
	12	[64]	GETUPVAL 	5 1	; setfenv
	13	[64]	MOVE     	6 0
	14	[64]	MOVE     	7 4
	15	[64]	CALL     	5 3 1
	16	[65]	MOVE     	5 0
	17	[65]	VARARG   	6 0
	18	[65]	TAILCALL 	5 0 0
	19	[65]	RETURN   	5 0
	20	[66]	RETURN   	0 1

function <./moon/init.lua:55,62> (10 instructions, 40 bytes at 0x7fec21c081f0)
2 params, 4 slots, 2 upvalues, 3 locals, 1 constant, 0 functions
	1	[56]	GETUPVAL 	2 0	; scope
	2	[56]	GETTABLE 	2 2 1
	3	[57]	EQ       	1 2 -1	; - nil
	4	[57]	JMP      	2	; to 7
	5	[58]	RETURN   	2 2
	6	[58]	JMP      	3	; to 10
	7	[60]	GETUPVAL 	3 1	; old_env
	8	[60]	GETTABLE 	3 3 1
	9	[60]	RETURN   	3 2
	10	[62]	RETURN   	0 1

function <./moon/init.lua:67,83> (10 instructions, 40 bytes at 0x7fec21c06fd0)
1 param, 5 slots, 1 upvalue, 1 local, 2 constants, 1 function
	1	[68]	GETGLOBAL	1 -1	; setmetatable
	2	[68]	NEWTABLE 	2 0 0
	3	[68]	NEWTABLE 	3 0 1
	4	[81]	CLOSURE  	4 0	; 0x7fec21c06f20
	5	[81]	MOVE     	0 0
	6	[81]	GETUPVAL 	0 0	; lua
	7	[81]	SETTABLE 	3 -2 4	; "__index" -
	8	[68]	TAILCALL 	1 3 0
	9	[82]	RETURN   	1 0
	10	[83]	RETURN   	0 1

function <./moon/init.lua:69,81> (19 instructions, 76 bytes at 0x7fec21c06f20)
2 params, 5 slots, 2 upvalues, 4 locals, 2 constants, 1 function
	1	[70]	GETUPVAL 	2 0	; obj
	2	[70]	GETTABLE 	2 2 1
	3	[71]	TEST     	2 0 0
	4	[71]	JMP      	13	; to 18
	5	[71]	GETUPVAL 	3 1	; lua
	6	[71]	GETTABLE 	3 3 -1	; "type"
	7	[71]	MOVE     	4 2
	8	[71]	CALL     	3 2 2
	9	[71]	EQ       	0 3 -2	; - "function"
	10	[71]	JMP      	7	; to 18
	11	[72]	LOADNIL  	3 3
	12	[75]	CLOSURE  	3 0	; 0x7fec21c08fd0
	13	[75]	MOVE     	0 2
	14	[75]	GETUPVAL 	0 0	; obj
	15	[76]	SETTABLE 	0 1 3
	16	[77]	RETURN   	3 2
	17	[77]	JMP      	1	; to 19
	18	[79]	RETURN   	2 2
	19	[81]	RETURN   	0 1

function <./moon/init.lua:73,75> (6 instructions, 24 bytes at 0x7fec21c08fd0)
0+ params, 4 slots, 2 upvalues, 1 local, 0 constants, 0 functions
	1	[74]	GETUPVAL 	1 0	; val
	2	[74]	GETUPVAL 	2 1	; obj
	3	[74]	VARARG   	3 0
	4	[74]	TAILCALL 	1 0 0
	5	[74]	RETURN   	1 0
	6	[75]	RETURN   	0 1

function <./moon/init.lua:84,96> (14 instructions, 56 bytes at 0x7fec21c09650)
2 params, 6 slots, 0 upvalues, 2 locals, 2 constants, 1 function
	1	[85]	TEST     	1 0 1
	2	[85]	JMP      	3	; to 6
	3	[86]	MOVE     	1 0
	4	[87]	NEWTABLE 	2 0 0
	5	[87]	MOVE     	0 2
	6	[89]	GETGLOBAL	2 -1	; setmetatable
	7	[89]	MOVE     	3 0
	8	[89]	NEWTABLE 	4 0 1
	9	[94]	CLOSURE  	5 0	; 0x7fec21c09750
	10	[94]	MOVE     	0 1
	11	[94]	SETTABLE 	4 -2 5	; "__index" -
	12	[89]	TAILCALL 	2 3 0
	13	[95]	RETURN   	2 0
	14	[96]	RETURN   	0 1

function <./moon/init.lua:90,94> (11 instructions, 44 bytes at 0x7fec21c09750)
2 params, 7 slots, 1 upvalue, 3 locals, 1 constant, 0 functions
	1	[91]	GETUPVAL 	2 0	; fn
	2	[91]	MOVE     	3 0
	3	[91]	MOVE     	4 1
	4	[91]	CALL     	2 3 2
	5	[92]	GETGLOBAL	3 -1	; rawset
	6	[92]	MOVE     	4 0
	7	[92]	MOVE     	5 1
	8	[92]	MOVE     	6 2
	9	[92]	CALL     	3 4 1
	10	[93]	RETURN   	2 2
	11	[94]	RETURN   	0 1

function <./moon/init.lua:97,112> (24 instructions, 96 bytes at 0x7fec21c09d40)
0+ params, 11 slots, 0 upvalues, 8 locals, 4 constants, 0 functions
	1	[98]	NEWTABLE 	1 0 0
	2	[98]	VARARG   	2 0
	3	[100]	SETLIST  	1 0 1	; 1
	4	[101]	LEN      	2 1
	5	[101]	LT       	0 2 -1	; - 2
	6	[101]	JMP      	1	; to 8
	7	[102]	RETURN   	0 1
	8	[104]	LOADK    	2 -2	; 1
	9	[104]	LEN      	3 1
	10	[104]	SUB      	3 3 -2	; - 1
	11	[104]	LOADK    	4 -2	; 1
	12	[104]	FORPREP  	2 8	; to 21
	13	[105]	GETTABLE 	6 1 5
	14	[106]	ADD      	7 5 -2	; - 1
	15	[106]	GETTABLE 	7 1 7
	16	[107]	GETGLOBAL	8 -3	; setmetatable
	17	[107]	MOVE     	9 6
	18	[107]	NEWTABLE 	10 0 1
	19	[108]	SETTABLE 	10 -4 7	; "__index" -
	20	[107]	CALL     	8 3 1
	21	[104]	FORLOOP  	2 -9	; to 13
	22	[111]	GETTABLE 	2 1 -2	; 1
	23	[111]	RETURN   	2 2
	24	[112]	RETURN   	0 1

function <./moon/init.lua:113,119> (10 instructions, 40 bytes at 0x7fec21c06640)
1 param, 8 slots, 0 upvalues, 7 locals, 1 constant, 0 functions
	1	[114]	NEWTABLE 	1 0 0
	2	[115]	GETGLOBAL	2 -1	; pairs
	3	[115]	MOVE     	3 0
	4	[115]	CALL     	2 2 4
	5	[115]	JMP      	1	; to 7
	6	[116]	SETTABLE 	1 5 6
	7	[115]	TFORLOOP 	2 2
	8	[116]	JMP      	-3	; to 6
	9	[118]	RETURN   	1 2
	10	[119]	RETURN   	0 1

function <./moon/init.lua:120,127> (18 instructions, 72 bytes at 0x7fec21c07440)
2+ params, 11 slots, 0 upvalues, 8 locals, 5 constants, 0 functions
	1	[121]	GETGLOBAL	3 -1	; pairs
	2	[121]	GETTABLE 	4 1 -2	; "__base"
	3	[121]	CALL     	3 2 4
	4	[121]	JMP      	6	; to 11
	5	[122]	SELF     	8 6 -3	; "match"
	6	[122]	LOADK    	10 -4	; "^__"
	7	[122]	CALL     	8 3 2
	8	[122]	TEST     	8 0 1
	9	[122]	JMP      	1	; to 11
	10	[123]	SETTABLE 	0 6 7
	11	[121]	TFORLOOP 	3 2
	12	[124]	JMP      	-8	; to 5
	13	[126]	GETTABLE 	3 1 -5	; "__init"
	14	[126]	MOVE     	4 0
	15	[126]	VARARG   	5 0
	16	[126]	TAILCALL 	3 0 0
	17	[126]	RETURN   	3 0
	18	[127]	RETURN   	0 1

function <./moon/init.lua:128,135> (12 instructions, 48 bytes at 0x7fec21c094f0)
3 params, 9 slots, 0 upvalues, 8 locals, 1 constant, 1 function
	1	[129]	LOADK    	3 -1	; 1
	2	[129]	LEN      	4 2
	3	[129]	LOADK    	5 -1	; 1
	4	[129]	FORPREP  	3 6	; to 11
	5	[130]	GETTABLE 	7 2 6
	6	[133]	CLOSURE  	8 0	; 0x7fec21c0a190
	7	[133]	MOVE     	0 1
	8	[133]	MOVE     	0 7
	9	[133]	SETTABLE 	0 7 8
	10	[133]	CLOSE    	7
	11	[129]	FORLOOP  	3 -7	; to 5
	12	[135]	RETURN   	0 1

function <./moon/init.lua:131,133> (8 instructions, 32 bytes at 0x7fec21c0a190)
1+ param, 5 slots, 2 upvalues, 2 locals, 0 constants, 0 functions
	1	[132]	GETUPVAL 	2 0	; object
	2	[132]	GETUPVAL 	3 1	; name
	3	[132]	GETTABLE 	2 2 3
	4	[132]	GETUPVAL 	3 0	; object
	5	[132]	VARARG   	4 0
	6	[132]	TAILCALL 	2 0 0
	7	[132]	RETURN   	2 0
	8	[133]	RETURN   	0 1

function <./moon/init.lua:136,147> (19 instructions, 76 bytes at 0x7fec21c0a570)
3 params, 9 slots, 0 upvalues, 13 locals, 2 constants, 0 functions
	1	[137]	TEST     	2 0 0
	2	[137]	JMP      	9	; to 12
	3	[138]	LOADK    	3 -1	; 1
	4	[138]	LEN      	4 2
	5	[138]	LOADK    	5 -1	; 1
	6	[138]	FORPREP  	3 3	; to 10
	7	[139]	GETTABLE 	7 2 6
	8	[140]	GETTABLE 	8 1 7
	9	[140]	SETTABLE 	0 7 8
	10	[138]	FORLOOP  	3 -4	; to 7
	11	[141]	JMP      	7	; to 19
	12	[143]	GETGLOBAL	3 -2	; pairs
	13	[143]	MOVE     	4 1
	14	[143]	CALL     	3 2 4
	15	[143]	JMP      	1	; to 17
	16	[144]	SETTABLE 	0 6 7
	17	[143]	TFORLOOP 	3 2
	18	[144]	JMP      	-3	; to 16
	19	[147]	RETURN   	0 1

function <./moon/init.lua:148,159> (22 instructions, 88 bytes at 0x7fec21c0a920)
2 params, 11 slots, 0 upvalues, 8 locals, 3 constants, 0 functions
	1	[149]	LEN      	2 0
	2	[150]	LT       	0 -1 2	; 1 -
	3	[150]	JMP      	16	; to 20
	4	[151]	MOVE     	3 1
	5	[151]	GETTABLE 	4 0 -1	; 1
	6	[151]	GETTABLE 	5 0 -2	; 2
	7	[151]	CALL     	3 3 2
	8	[152]	LOADK    	4 -3	; 3
	9	[152]	MOVE     	5 2
	10	[152]	LOADK    	6 -1	; 1
	11	[152]	FORPREP  	4 5	; to 17
	12	[153]	MOVE     	8 1
	13	[153]	MOVE     	9 3
	14	[153]	GETTABLE 	10 0 7
	15	[153]	CALL     	8 3 2
	16	[153]	MOVE     	3 8
	17	[152]	FORLOOP  	4 -6	; to 12
	18	[155]	RETURN   	3 2
	19	[155]	JMP      	2	; to 22
	20	[157]	GETTABLE 	3 0 -1	; 1
	21	[157]	RETURN   	3 2
	22	[159]	RETURN   	0 1
