
main <./moonscript/cmd/lint.lua:0,0> (134 instructions, 536 bytes at 0x7ffc5fc068c0)
0+ params, 48 slots, 0 upvalues, 14 locals, 64 constants, 11 functions
	1	[2]	GETGLOBAL	1 -1	; table
	2	[2]	GETTABLE 	0 1 -2	; "insert"
	3	[3]	LOADNIL  	1 1
	4	[4]	GETGLOBAL	2 -3	; require
	5	[4]	LOADK    	3 -4	; "moonscript.data"
	6	[4]	CALL     	2 2 2
	7	[4]	GETTABLE 	1 2 -5	; "Set"
	8	[5]	LOADNIL  	2 2
	9	[6]	GETGLOBAL	3 -3	; require
	10	[6]	LOADK    	4 -6	; "moonscript.compile"
	11	[6]	CALL     	3 2 2
	12	[6]	GETTABLE 	2 3 -7	; "Block"
	13	[7]	LOADNIL  	3 3
	14	[8]	GETGLOBAL	4 -3	; require
	15	[8]	LOADK    	5 -8	; "moonscript.util"
	16	[8]	CALL     	4 2 2
	17	[8]	GETTABLE 	4 4 -9	; "moon"
	18	[8]	GETTABLE 	3 4 -10	; "type"
	19	[9]	MOVE     	4 1
	20	[9]	NEWTABLE 	5 27 0
	21	[10]	LOADK    	6 -11	; "_G"
	22	[11]	LOADK    	7 -12	; "_VERSION"
	23	[12]	LOADK    	8 -13	; "assert"
	24	[13]	LOADK    	9 -14	; "bit32"
	25	[14]	LOADK    	10 -15	; "collectgarbage"
	26	[15]	LOADK    	11 -16	; "coroutine"
	27	[16]	LOADK    	12 -17	; "debug"
	28	[17]	LOADK    	13 -18	; "dofile"
	29	[18]	LOADK    	14 -19	; "error"
	30	[19]	LOADK    	15 -20	; "getfenv"
	31	[20]	LOADK    	16 -21	; "getmetatable"
	32	[21]	LOADK    	17 -22	; "io"
	33	[22]	LOADK    	18 -23	; "ipairs"
	34	[23]	LOADK    	19 -24	; "load"
	35	[24]	LOADK    	20 -25	; "loadfile"
	36	[25]	LOADK    	21 -26	; "loadstring"
	37	[26]	LOADK    	22 -27	; "math"
	38	[27]	LOADK    	23 -28	; "module"
	39	[28]	LOADK    	24 -29	; "next"
	40	[29]	LOADK    	25 -30	; "os"
	41	[30]	LOADK    	26 -31	; "package"
	42	[31]	LOADK    	27 -32	; "pairs"
	43	[32]	LOADK    	28 -33	; "pcall"
	44	[33]	LOADK    	29 -34	; "print"
	45	[34]	LOADK    	30 -35	; "rawequal"
	46	[35]	LOADK    	31 -36	; "rawget"
	47	[36]	LOADK    	32 -37	; "rawlen"
	48	[37]	LOADK    	33 -38	; "rawset"
	49	[38]	LOADK    	34 -3	; "require"
	50	[39]	LOADK    	35 -39	; "select"
	51	[40]	LOADK    	36 -40	; "setfenv"
	52	[41]	LOADK    	37 -41	; "setmetatable"
	53	[42]	LOADK    	38 -42	; "string"
	54	[43]	LOADK    	39 -1	; "table"
	55	[44]	LOADK    	40 -43	; "tonumber"
	56	[45]	LOADK    	41 -44	; "tostring"
	57	[46]	LOADK    	42 -10	; "type"
	58	[47]	LOADK    	43 -45	; "unpack"
	59	[48]	LOADK    	44 -46	; "xpcall"
	60	[49]	LOADK    	45 -47	; "nil"
	61	[50]	LOADK    	46 -48	; "true"
	62	[52]	LOADK    	47 -49	; "false"
	63	[52]	SETLIST  	5 42 1	; 1
	64	[9]	CALL     	4 2 2
	65	[53]	LOADNIL  	5 6
	66	[56]	MOVE     	7 2
	67	[57]	NEWTABLE 	8 0 4
	68	[66]	CLOSURE  	9 0	; 0x7ffc5fc07080
	69	[66]	SETTABLE 	8 -50 9	; "lint_mark_used" -
	70	[121]	CLOSURE  	9 1	; 0x7ffc5fc07ae0
	71	[121]	MOVE     	0 0
	72	[121]	SETTABLE 	8 -51 9	; "lint_check_unused" -
	73	[125]	CLOSURE  	9 2	; 0x7ffc5fc082f0
	74	[125]	MOVE     	0 6
	75	[125]	SETTABLE 	8 -52 9	; "render" -
	76	[138]	CLOSURE  	9 3	; 0x7ffc5fc07860
	77	[138]	MOVE     	0 6
	78	[138]	SETTABLE 	8 -53 9	; "block" -
	79	[140]	SETTABLE 	8 -54 8	; "__index" -
	80	[141]	GETGLOBAL	9 -41	; setmetatable
	81	[141]	MOVE     	10 8
	82	[141]	GETTABLE 	11 7 -55	; "__base"
	83	[141]	CALL     	9 3 1
	84	[142]	GETGLOBAL	9 -41	; setmetatable
	85	[142]	NEWTABLE 	10 0 4
	86	[202]	CLOSURE  	11 4	; 0x7ffc5fc09240
	87	[202]	MOVE     	0 4
	88	[202]	MOVE     	0 6
	89	[202]	MOVE     	0 0
	90	[202]	SETTABLE 	10 -56 11	; "__init" -
	91	[203]	SETTABLE 	10 -55 8	; "__base" -
	92	[204]	SETTABLE 	10 -57 -58	; "__name" "LinterBlock"
	93	[205]	SETTABLE 	10 -59 7	; "__parent" -
	94	[206]	NEWTABLE 	11 0 2
	95	[217]	CLOSURE  	12 5	; 0x7ffc5fc0a130
	96	[217]	MOVE     	0 8
	97	[217]	SETTABLE 	11 -54 12	; "__index" -
	98	[222]	CLOSURE  	12 6	; 0x7ffc5fc0a5d0
	99	[222]	MOVE     	0 8
	100	[222]	SETTABLE 	11 -60 12	; "__call" -
	101	[142]	CALL     	9 3 2
	102	[223]	MOVE     	6 9
	103	[224]	SETTABLE 	8 -61 6	; "__class" -
	104	[225]	GETTABLE 	9 7 -62	; "__inherited"
	105	[225]	TEST     	9 0 0
	106	[225]	JMP      	4	; to 111
	107	[226]	GETTABLE 	9 7 -62	; "__inherited"
	108	[226]	MOVE     	10 7
	109	[226]	MOVE     	11 6
	110	[226]	CALL     	9 3 1
	111	[228]	MOVE     	5 6
	112	[228]	CLOSE    	6
	113	[230]	LOADNIL  	6 6
	114	[269]	CLOSURE  	6 7	; 0x7ffc5fc0aba0
	115	[270]	LOADNIL  	7 8
	116	[295]	CLOSURE  	7 8	; 0x7ffc5fc0b050
	117	[295]	MOVE     	0 8
	118	[295]	MOVE     	0 4
	119	[295]	MOVE     	0 0
	120	[295]	MOVE     	0 1
	121	[295]	CLOSE    	8
	122	[297]	LOADNIL  	8 8
	123	[311]	CLOSURE  	8 9	; 0x7ffc5fc0b6f0
	124	[311]	MOVE     	0 5
	125	[311]	MOVE     	0 6
	126	[312]	LOADNIL  	9 9
	127	[319]	CLOSURE  	9 10	; 0x7ffc5fc0c430
	128	[319]	MOVE     	0 8
	129	[319]	MOVE     	0 7
	130	[320]	NEWTABLE 	10 0 2
	131	[321]	SETTABLE 	10 -63 8	; "lint_code" -
	132	[322]	SETTABLE 	10 -64 9	; "lint_file" -
	133	[323]	RETURN   	10 2
	134	[323]	RETURN   	0 1

function <./moonscript/cmd/lint.lua:58,66> (19 instructions, 76 bytes at 0x7ffc5fc07080)
2 params, 5 slots, 0 upvalues, 2 locals, 4 constants, 0 functions
	1	[59]	GETTABLE 	2 0 -1	; "lint_unused_names"
	2	[59]	TEST     	2 0 0
	3	[59]	JMP      	7	; to 11
	4	[59]	GETTABLE 	2 0 -1	; "lint_unused_names"
	5	[59]	GETTABLE 	2 2 1
	6	[59]	TEST     	2 0 0
	7	[59]	JMP      	3	; to 11
	8	[60]	GETTABLE 	2 0 -1	; "lint_unused_names"
	9	[60]	SETTABLE 	2 1 -2	; - false
	10	[61]	RETURN   	0 1
	11	[63]	GETTABLE 	2 0 -3	; "parent"
	12	[63]	TEST     	2 0 0
	13	[63]	JMP      	5	; to 19
	14	[64]	GETTABLE 	2 0 -3	; "parent"
	15	[64]	SELF     	2 2 -4	; "lint_mark_used"
	16	[64]	MOVE     	4 1
	17	[64]	TAILCALL 	2 3 0
	18	[64]	RETURN   	2 0
	19	[66]	RETURN   	0 1

function <./moonscript/cmd/lint.lua:67,121> (86 instructions, 344 bytes at 0x7ffc5fc07ae0)
1 param, 18 slots, 1 upvalue, 23 locals, 13 constants, 2 functions
	1	[68]	GETTABLE 	1 0 -1	; "lint_unused_names"
	2	[68]	TEST     	1 0 0
	3	[68]	JMP      	5	; to 9
	4	[68]	GETGLOBAL	1 -2	; next
	5	[68]	GETTABLE 	2 0 -1	; "lint_unused_names"
	6	[68]	CALL     	1 2 2
	7	[68]	TEST     	1 0 1
	8	[68]	JMP      	1	; to 10
	9	[69]	RETURN   	0 1
	10	[71]	NEWTABLE 	1 0 0
	11	[72]	GETGLOBAL	2 -3	; pairs
	12	[72]	GETTABLE 	3 0 -1	; "lint_unused_names"
	13	[72]	CALL     	2 2 4
	14	[72]	JMP      	18	; to 33
	15	[73]	LOADBOOL 	7 0 0
	16	[75]	TEST     	6 0 1
	17	[75]	JMP      	2	; to 20
	18	[76]	LOADBOOL 	7 1 0
	19	[77]	JMP      	10	; to 30
	20	[79]	GETTABLE 	8 1 6
	21	[79]	TEST     	8 0 1
	22	[79]	JMP      	1	; to 24
	23	[79]	NEWTABLE 	8 0 0
	24	[79]	SETTABLE 	1 6 8
	25	[80]	GETUPVAL 	8 0	; insert
	26	[80]	GETTABLE 	9 1 6
	27	[80]	MOVE     	10 5
	28	[80]	CALL     	8 3 1
	29	[81]	LOADBOOL 	7 1 0
	30	[83]	TEST     	7 0 1
	31	[83]	JMP      	1	; to 33
	32	[84]	JMP      	2	; to 35
	33	[72]	TFORLOOP 	2 2
	34	[85]	JMP      	-20	; to 15
	35	[87]	LOADNIL  	2 2
	36	[89]	NEWTABLE 	3 0 0
	37	[90]	LOADK    	4 -4	; 1
	38	[91]	GETGLOBAL	5 -3	; pairs
	39	[91]	MOVE     	6 1
	40	[91]	CALL     	5 2 4
	41	[91]	JMP      	6	; to 48
	42	[92]	NEWTABLE 	10 2 0
	43	[93]	MOVE     	11 8
	44	[95]	MOVE     	12 9
	45	[95]	SETLIST  	10 2 1	; 1
	46	[95]	SETTABLE 	3 4 10
	47	[96]	ADD      	4 4 -4	; - 1
	48	[91]	TFORLOOP 	5 2
	49	[96]	JMP      	-8	; to 42
	50	[98]	MOVE     	2 3
	51	[100]	GETGLOBAL	3 -5	; table
	52	[100]	GETTABLE 	3 3 -6	; "sort"
	53	[100]	MOVE     	4 2
	54	[102]	CLOSURE  	5 0	; 0x7ffc5fc07f90
	55	[100]	CALL     	3 3 1
	56	[103]	LOADK    	3 -4	; 1
	57	[103]	LEN      	4 2
	58	[103]	LOADK    	5 -4	; 1
	59	[103]	FORPREP  	3 25	; to 85
	60	[104]	GETTABLE 	7 2 6
	61	[105]	LOADNIL  	8 9
	62	[106]	GETTABLE 	10 7 -4	; 1
	63	[106]	GETTABLE 	9 7 -7	; 2
	64	[106]	MOVE     	8 10
	65	[107]	GETUPVAL 	10 0	; insert
	66	[107]	SELF     	11 0 -8	; "get_root_block"
	67	[107]	CALL     	11 2 2
	68	[107]	GETTABLE 	11 11 -9	; "lint_errors"
	69	[107]	NEWTABLE 	12 2 0
	70	[108]	LOADK    	13 -10	; "assigned but unused "
	71	[108]	GETGLOBAL	14 -11	; tostring
	72	[108]	GETGLOBAL	15 -5	; table
	73	[108]	GETTABLE 	15 15 -12	; "concat"
	74	[117]	CLOSURE  	16 1	; 0x7ffc5fc07ce0
	75	[117]	MOVE     	0 9
	76	[117]	CALL     	16 1 2
	77	[117]	LOADK    	17 -13	; ", "
	78	[108]	CALL     	15 3 0
	79	[108]	CALL     	14 0 2
	80	[117]	CONCAT   	13 13 14
	81	[119]	MOVE     	14 8
	82	[119]	SETLIST  	12 2 1	; 1
	83	[107]	CALL     	10 3 1
	84	[119]	CLOSE    	7
	85	[103]	FORLOOP  	3 -26	; to 60
	86	[121]	RETURN   	0 1

function <./moonscript/cmd/lint.lua:100,102> (8 instructions, 32 bytes at 0x7ffc5fc07f90)
2 params, 4 slots, 0 upvalues, 2 locals, 1 constant, 0 functions
	1	[101]	GETTABLE 	2 0 -1	; 1
	2	[101]	GETTABLE 	3 1 -1	; 1
	3	[101]	LT       	1 2 3
	4	[101]	JMP      	1	; to 6
	5	[101]	LOADBOOL 	2 0 1
	6	[101]	LOADBOOL 	2 1 0
	7	[101]	RETURN   	2 2
	8	[102]	RETURN   	0 1

function <./moonscript/cmd/lint.lua:108,117> (20 instructions, 80 bytes at 0x7ffc5fc07ce0)
0 params, 10 slots, 1 upvalue, 7 locals, 3 constants, 0 functions
	1	[109]	NEWTABLE 	0 0 0
	2	[110]	LOADK    	1 -1	; 1
	3	[111]	LOADK    	2 -1	; 1
	4	[111]	GETUPVAL 	3 0	; names
	5	[111]	LEN      	3 3
	6	[111]	LOADK    	4 -1	; 1
	7	[111]	FORPREP  	2 10	; to 18
	8	[112]	GETUPVAL 	6 0	; names
	9	[112]	GETTABLE 	6 6 5
	10	[113]	LOADK    	7 -2	; "`"
	11	[113]	GETGLOBAL	8 -3	; tostring
	12	[113]	MOVE     	9 6
	13	[113]	CALL     	8 2 2
	14	[113]	LOADK    	9 -2	; "`"
	15	[113]	CONCAT   	7 7 9
	16	[113]	SETTABLE 	0 1 7
	17	[114]	ADD      	1 1 -1	; - 1
	18	[111]	FORLOOP  	2 -11	; to 8
	19	[116]	RETURN   	0 2
	20	[117]	RETURN   	0 1

function <./moonscript/cmd/lint.lua:122,125> (11 instructions, 44 bytes at 0x7ffc5fc082f0)
1+ param, 5 slots, 1 upvalue, 2 locals, 4 constants, 0 functions
	1	[123]	SELF     	2 0 -1	; "lint_check_unused"
	2	[123]	CALL     	2 2 1
	3	[124]	GETUPVAL 	2 0	; _class_0
	4	[124]	GETTABLE 	2 2 -2	; "__parent"
	5	[124]	GETTABLE 	2 2 -3	; "__base"
	6	[124]	GETTABLE 	2 2 -4	; "render"
	7	[124]	MOVE     	3 0
	8	[124]	VARARG   	4 0
	9	[124]	TAILCALL 	2 0 0
	10	[124]	RETURN   	2 0
	11	[125]	RETURN   	0 1

function <./moonscript/cmd/lint.lua:126,138> (23 instructions, 92 bytes at 0x7ffc5fc07860)
1+ param, 5 slots, 1 upvalue, 3 locals, 9 constants, 0 functions
	1	[128]	GETUPVAL 	2 0	; _class_0
	2	[128]	GETTABLE 	2 2 -1	; "__parent"
	3	[128]	GETTABLE 	2 2 -2	; "__base"
	4	[128]	GETTABLE 	2 2 -3	; "block"
	5	[128]	MOVE     	3 0
	6	[128]	VARARG   	4 0
	7	[128]	CALL     	2 0 2
	8	[129]	GETTABLE 	3 0 -3	; "block"
	9	[129]	SETTABLE 	2 -3 3	; "block" -
	10	[130]	GETTABLE 	3 0 -4	; "render"
	11	[130]	SETTABLE 	2 -4 3	; "render" -
	12	[131]	GETTABLE 	3 0 -5	; "get_root_block"
	13	[131]	SETTABLE 	2 -5 3	; "get_root_block" -
	14	[132]	GETTABLE 	3 0 -6	; "lint_check_unused"
	15	[132]	SETTABLE 	2 -6 3	; "lint_check_unused" -
	16	[133]	GETTABLE 	3 0 -7	; "lint_mark_used"
	17	[133]	SETTABLE 	2 -7 3	; "lint_mark_used" -
	18	[134]	GETTABLE 	3 0 -8	; "value_compilers"
	19	[134]	SETTABLE 	2 -8 3	; "value_compilers" -
	20	[135]	GETTABLE 	3 0 -9	; "statement_compilers"
	21	[135]	SETTABLE 	2 -9 3	; "statement_compilers" -
	22	[136]	RETURN   	2 2
	23	[138]	RETURN   	0 1

function <./moonscript/cmd/lint.lua:143,202> (38 instructions, 152 bytes at 0x7ffc5fc09240)
2+ params, 8 slots, 3 upvalues, 5 locals, 11 constants, 3 functions
	1	[144]	EQ       	0 1 -1	; - nil
	2	[144]	JMP      	1	; to 4
	3	[145]	GETUPVAL 	1 0	; default_whitelist
	4	[147]	GETUPVAL 	3 1	; _class_0
	5	[147]	GETTABLE 	3 3 -2	; "__parent"
	6	[147]	GETTABLE 	3 3 -3	; "__init"
	7	[147]	MOVE     	4 0
	8	[147]	VARARG   	5 0
	9	[147]	CALL     	3 0 1
	10	[150]	CLOSURE  	3 0	; 0x7ffc5fc09490
	11	[150]	MOVE     	0 0
	12	[150]	SETTABLE 	0 -4 3	; "get_root_block" -
	13	[151]	NEWTABLE 	3 0 0
	14	[151]	SETTABLE 	0 -5 3	; "lint_errors" -
	15	[152]	GETTABLE 	3 0 -6	; "value_compilers"
	16	[153]	GETGLOBAL	4 -7	; setmetatable
	17	[153]	NEWTABLE 	5 0 1
	18	[164]	CLOSURE  	6 1	; 0x7ffc5fc09360
	19	[164]	MOVE     	0 1
	20	[164]	GETUPVAL 	0 2	; insert
	21	[164]	MOVE     	0 0
	22	[164]	MOVE     	0 3
	23	[164]	SETTABLE 	5 -8 6	; "ref" -
	24	[165]	NEWTABLE 	6 0 1
	25	[166]	SETTABLE 	6 -9 3	; "__index" -
	26	[153]	CALL     	4 3 2
	27	[167]	SETTABLE 	0 -6 4	; "value_compilers" -
	28	[168]	GETTABLE 	4 0 -10	; "statement_compilers"
	29	[169]	GETGLOBAL	5 -7	; setmetatable
	30	[169]	NEWTABLE 	6 0 1
	31	[198]	CLOSURE  	7 2	; 0x7ffc5fc09c70
	32	[198]	MOVE     	0 4
	33	[198]	SETTABLE 	6 -11 7	; "assign" -
	34	[199]	NEWTABLE 	7 0 1
	35	[200]	SETTABLE 	7 -9 4	; "__index" -
	36	[169]	CALL     	5 3 2
	37	[201]	SETTABLE 	0 -10 5	; "statement_compilers" -
	38	[202]	RETURN   	0 1

function <./moonscript/cmd/lint.lua:148,150> (3 instructions, 12 bytes at 0x7ffc5fc09490)
0 params, 2 slots, 1 upvalue, 0 locals, 0 constants, 0 functions
	1	[149]	GETUPVAL 	0 0	; self
	2	[149]	RETURN   	0 2
	3	[150]	RETURN   	0 1

function <./moonscript/cmd/lint.lua:154,164> (38 instructions, 152 bytes at 0x7ffc5fc09360)
2 params, 9 slots, 4 upvalues, 3 locals, 11 constants, 0 functions
	1	[155]	GETTABLE 	2 1 -1	; 2
	2	[156]	SELF     	3 0 -2	; "has_name"
	3	[156]	MOVE     	5 2
	4	[156]	CALL     	3 3 2
	5	[156]	TEST     	3 0 1
	6	[156]	JMP      	22	; to 29
	7	[156]	GETUPVAL 	3 0	; whitelist_globals
	8	[156]	GETTABLE 	3 3 2
	9	[156]	TEST     	3 0 1
	10	[156]	JMP      	18	; to 29
	11	[156]	SELF     	3 2 -3	; "match"
	12	[156]	LOADK    	5 -4	; "%."
	13	[156]	CALL     	3 3 2
	14	[156]	TEST     	3 0 1
	15	[156]	JMP      	13	; to 29
	16	[157]	GETUPVAL 	3 1	; insert
	17	[157]	GETUPVAL 	4 2	; self
	18	[157]	GETTABLE 	4 4 -5	; "lint_errors"
	19	[157]	NEWTABLE 	5 2 0
	20	[158]	LOADK    	6 -6	; "accessing global `"
	21	[158]	GETGLOBAL	7 -7	; tostring
	22	[158]	MOVE     	8 2
	23	[158]	CALL     	7 2 2
	24	[158]	LOADK    	8 -8	; "`"
	25	[158]	CONCAT   	6 6 8
	26	[160]	GETTABLE 	7 1 -9	; -1
	27	[160]	SETLIST  	5 2 1	; 1
	28	[157]	CALL     	3 3 1
	29	[162]	SELF     	3 0 -10	; "lint_mark_used"
	30	[162]	MOVE     	5 2
	31	[162]	CALL     	3 3 1
	32	[163]	GETUPVAL 	3 3	; vc
	33	[163]	GETTABLE 	3 3 -11	; "ref"
	34	[163]	MOVE     	4 0
	35	[163]	MOVE     	5 1
	36	[163]	TAILCALL 	3 3 0
	37	[163]	RETURN   	3 0
	38	[164]	RETURN   	0 1

function <./moonscript/cmd/lint.lua:170,198> (60 instructions, 240 bytes at 0x7ffc5fc09c70)
2 params, 15 slots, 1 upvalue, 11 locals, 12 constants, 0 functions
	1	[171]	GETTABLE 	2 1 -1	; 2
	2	[172]	LOADK    	3 -2	; 1
	3	[172]	LEN      	4 2
	4	[172]	LOADK    	5 -2	; 1
	5	[172]	FORPREP  	3 47	; to 53
	6	[173]	LOADBOOL 	7 0 0
	7	[175]	GETTABLE 	8 2 6
	8	[176]	GETGLOBAL	9 -3	; type
	9	[176]	MOVE     	10 8
	10	[176]	CALL     	9 2 2
	11	[176]	EQ       	0 9 -4	; - "table"
	12	[176]	JMP      	5	; to 18
	13	[176]	GETTABLE 	9 8 -2	; 1
	14	[176]	EQ       	0 9 -5	; - "temp_name"
	15	[176]	JMP      	2	; to 18
	16	[177]	LOADBOOL 	7 1 0
	17	[178]	JMP      	32	; to 50
	18	[180]	SELF     	9 0 -6	; "extract_assign_name"
	19	[180]	MOVE     	11 8
	20	[180]	CALL     	9 3 3
	21	[181]	TEST     	10 0 1
	22	[181]	JMP      	11	; to 34
	23	[181]	TEST     	9 0 0
	24	[181]	JMP      	7	; to 32
	25	[181]	SELF     	11 0 -7	; "has_name"
	26	[181]	MOVE     	13 9
	27	[181]	LOADBOOL 	14 1 0
	28	[181]	CALL     	11 4 2
	29	[181]	NOT      	11 11
	30	[181]	TEST     	11 0 1
	31	[181]	JMP      	2	; to 34
	32	[182]	LOADBOOL 	7 1 0
	33	[183]	JMP      	16	; to 50
	34	[185]	EQ       	0 9 -8	; - "_"
	35	[185]	JMP      	2	; to 38
	36	[186]	LOADBOOL 	7 1 0
	37	[187]	JMP      	12	; to 50
	38	[189]	GETTABLE 	11 0 -9	; "lint_unused_names"
	39	[189]	TEST     	11 0 1
	40	[189]	JMP      	1	; to 42
	41	[189]	NEWTABLE 	11 0 0
	42	[189]	SETTABLE 	0 -9 11	; "lint_unused_names" -
	43	[190]	GETTABLE 	11 0 -9	; "lint_unused_names"
	44	[190]	GETTABLE 	12 1 -10	; -1
	45	[190]	TEST     	12 0 1
	46	[190]	JMP      	1	; to 48
	47	[190]	LOADK    	12 -11	; 0
	48	[190]	SETTABLE 	11 9 12
	49	[191]	LOADBOOL 	7 1 0
	50	[193]	TEST     	7 0 1
	51	[193]	JMP      	1	; to 53
	52	[194]	JMP      	1	; to 54
	53	[172]	FORLOOP  	3 -48	; to 6
	54	[197]	GETUPVAL 	3 0	; sc
	55	[197]	GETTABLE 	3 3 -12	; "assign"
	56	[197]	MOVE     	4 0
	57	[197]	MOVE     	5 1
	58	[197]	TAILCALL 	3 3 0
	59	[197]	RETURN   	3 0
	60	[198]	RETURN   	0 1

function <./moonscript/cmd/lint.lua:207,217> (17 instructions, 68 bytes at 0x7ffc5fc0a130)
2 params, 6 slots, 1 upvalue, 4 locals, 3 constants, 0 functions
	1	[208]	GETGLOBAL	2 -1	; rawget
	2	[208]	GETUPVAL 	3 0	; _base_0
	3	[208]	MOVE     	4 1
	4	[208]	CALL     	2 3 2
	5	[209]	EQ       	0 2 -2	; - nil
	6	[209]	JMP      	9	; to 16
	7	[210]	GETGLOBAL	3 -1	; rawget
	8	[210]	MOVE     	4 0
	9	[210]	LOADK    	5 -3	; "__parent"
	10	[210]	CALL     	3 3 2
	11	[211]	TEST     	3 0 0
	12	[211]	JMP      	4	; to 17
	13	[212]	GETTABLE 	4 3 1
	14	[212]	RETURN   	4 2
	15	[213]	JMP      	1	; to 17
	16	[215]	RETURN   	2 2
	17	[217]	RETURN   	0 1

function <./moonscript/cmd/lint.lua:218,222> (10 instructions, 40 bytes at 0x7ffc5fc0a5d0)
1+ param, 6 slots, 1 upvalue, 3 locals, 2 constants, 0 functions
	1	[219]	GETGLOBAL	2 -1	; setmetatable
	2	[219]	NEWTABLE 	3 0 0
	3	[219]	GETUPVAL 	4 0	; _base_0
	4	[219]	CALL     	2 3 2
	5	[220]	GETTABLE 	3 0 -2	; "__init"
	6	[220]	MOVE     	4 2
	7	[220]	VARARG   	5 0
	8	[220]	CALL     	3 0 1
	9	[221]	RETURN   	2 2
	10	[222]	RETURN   	0 1

function <./moonscript/cmd/lint.lua:231,269> (84 instructions, 336 bytes at 0x7ffc5fc0aba0)
3 params, 24 slots, 0 upvalues, 19 locals, 20 constants, 0 functions
	1	[232]	GETGLOBAL	3 -1	; next
	2	[232]	MOVE     	4 0
	3	[232]	CALL     	3 2 2
	4	[232]	TEST     	3 0 1
	5	[232]	JMP      	1	; to 7
	6	[233]	RETURN   	0 1
	7	[235]	LOADNIL  	3 4
	8	[237]	GETGLOBAL	5 -2	; require
	9	[237]	LOADK    	6 -3	; "moonscript.util"
	10	[237]	CALL     	5 2 2
	11	[238]	GETTABLE 	6 5 -4	; "pos_to_line"
	12	[238]	GETTABLE 	4 5 -5	; "get_line"
	13	[238]	MOVE     	3 6
	14	[240]	LOADNIL  	5 5
	15	[242]	NEWTABLE 	6 0 0
	16	[243]	LOADK    	7 -6	; 1
	17	[244]	LOADK    	8 -6	; 1
	18	[244]	LEN      	9 0
	19	[244]	LOADK    	10 -6	; 1
	20	[244]	FORPREP  	8 47	; to 68
	21	[245]	GETTABLE 	12 0 11
	22	[246]	LOADNIL  	13 14
	23	[247]	GETTABLE 	15 12 -6	; 1
	24	[247]	GETTABLE 	14 12 -7	; 2
	25	[247]	MOVE     	13 15
	26	[248]	TEST     	14 0 0
	27	[248]	JMP      	38	; to 66
	28	[249]	MOVE     	15 3
	29	[249]	MOVE     	16 1
	30	[249]	MOVE     	17 14
	31	[249]	CALL     	15 3 2
	32	[250]	LOADK    	16 -8	; "line "
	33	[250]	GETGLOBAL	17 -9	; tostring
	34	[250]	MOVE     	18 15
	35	[250]	CALL     	17 2 2
	36	[250]	LOADK    	18 -10	; ": "
	37	[250]	GETGLOBAL	19 -9	; tostring
	38	[250]	MOVE     	20 13
	39	[250]	CALL     	19 2 2
	40	[250]	CONCAT   	13 16 19
	41	[251]	LOADK    	16 -11	; "> "
	42	[251]	MOVE     	17 4
	43	[251]	MOVE     	18 1
	44	[251]	MOVE     	19 15
	45	[251]	CALL     	17 3 2
	46	[251]	CONCAT   	16 16 17
	47	[252]	GETGLOBAL	17 -12	; math
	48	[252]	GETTABLE 	17 17 -13	; "max"
	49	[252]	LEN      	18 13
	50	[252]	LEN      	19 16
	51	[252]	CALL     	17 3 2
	52	[253]	GETGLOBAL	18 -14	; table
	53	[253]	GETTABLE 	18 18 -15	; "concat"
	54	[253]	NEWTABLE 	19 3 0
	55	[254]	MOVE     	20 13
	56	[255]	LOADK    	21 -16	; "="
	57	[255]	SELF     	21 21 -17	; "rep"
	58	[255]	MOVE     	23 17
	59	[255]	CALL     	21 3 2
	60	[257]	MOVE     	22 16
	61	[257]	SETLIST  	19 3 1	; 1
	62	[257]	LOADK    	20 -18	; "\n"
	63	[253]	CALL     	18 3 2
	64	[257]	SETTABLE 	6 7 18
	65	[257]	JMP      	1	; to 67
	66	[259]	SETTABLE 	6 7 13
	67	[261]	ADD      	7 7 -6	; - 1
	68	[244]	FORLOOP  	8 -48	; to 21
	69	[263]	MOVE     	5 6
	70	[265]	TEST     	2 0 0
	71	[265]	JMP      	6	; to 78
	72	[266]	GETGLOBAL	6 -14	; table
	73	[266]	GETTABLE 	6 6 -19	; "insert"
	74	[266]	MOVE     	7 5
	75	[266]	LOADK    	8 -6	; 1
	76	[266]	MOVE     	9 2
	77	[266]	CALL     	6 4 1
	78	[268]	GETGLOBAL	6 -14	; table
	79	[268]	GETTABLE 	6 6 -15	; "concat"
	80	[268]	MOVE     	7 5
	81	[268]	LOADK    	8 -20	; "\n\n"
	82	[268]	TAILCALL 	6 3 0
	83	[268]	RETURN   	6 0
	84	[269]	RETURN   	0 1

function <./moonscript/cmd/lint.lua:273,295> (48 instructions, 192 bytes at 0x7ffc5fc0b050)
1 param, 15 slots, 4 upvalues, 12 locals, 7 constants, 1 function
	1	[274]	GETUPVAL 	1 0	; lint_config
	2	[274]	TEST     	1 0 1
	3	[274]	JMP      	6	; to 10
	4	[275]	NEWTABLE 	1 0 0
	5	[275]	SETUPVAL 	1 0	; lint_config
	6	[276]	GETGLOBAL	1 -1	; pcall
	7	[278]	CLOSURE  	2 0	; 0x7ffc5fc0b2f0
	8	[278]	GETUPVAL 	0 0	; lint_config
	9	[276]	CALL     	1 2 1
	10	[280]	GETUPVAL 	1 0	; lint_config
	11	[280]	GETTABLE 	1 1 -2	; "whitelist_globals"
	12	[280]	TEST     	1 0 1
	13	[280]	JMP      	2	; to 16
	14	[281]	GETUPVAL 	1 1	; default_whitelist
	15	[281]	RETURN   	1 2
	16	[283]	NEWTABLE 	1 0 0
	17	[284]	GETGLOBAL	2 -3	; pairs
	18	[284]	GETUPVAL 	3 0	; lint_config
	19	[284]	GETTABLE 	3 3 -2	; "whitelist_globals"
	20	[284]	CALL     	2 2 4
	21	[284]	JMP      	15	; to 37
	22	[285]	SELF     	7 0 -4	; "match"
	23	[285]	MOVE     	9 5
	24	[285]	CALL     	7 3 2
	25	[285]	TEST     	7 0 0
	26	[285]	JMP      	10	; to 37
	27	[286]	LOADK    	7 -5	; 1
	28	[286]	LEN      	8 6
	29	[286]	LOADK    	9 -5	; 1
	30	[286]	FORPREP  	7 5	; to 36
	31	[287]	GETTABLE 	11 6 10
	32	[288]	GETUPVAL 	12 2	; insert
	33	[288]	MOVE     	13 1
	34	[288]	MOVE     	14 11
	35	[288]	CALL     	12 3 1
	36	[286]	FORLOOP  	7 -6	; to 31
	37	[284]	TFORLOOP 	2 2
	38	[290]	JMP      	-17	; to 22
	39	[292]	GETGLOBAL	2 -6	; setmetatable
	40	[292]	GETUPVAL 	3 3	; Set
	41	[292]	MOVE     	4 1
	42	[292]	CALL     	3 2 2
	43	[292]	NEWTABLE 	4 0 1
	44	[293]	GETUPVAL 	5 1	; default_whitelist
	45	[293]	SETTABLE 	4 -7 5	; "__index" -
	46	[292]	TAILCALL 	2 3 0
	47	[294]	RETURN   	2 0
	48	[295]	RETURN   	0 1

function <./moonscript/cmd/lint.lua:276,278> (5 instructions, 20 bytes at 0x7ffc5fc0b2f0)
0 params, 2 slots, 1 upvalue, 0 locals, 2 constants, 0 functions
	1	[277]	GETGLOBAL	0 -1	; require
	2	[277]	LOADK    	1 -2	; "lint_config"
	3	[277]	CALL     	0 2 2
	4	[277]	SETUPVAL 	0 0	; lint_config
	5	[278]	RETURN   	0 1

function <./moonscript/cmd/lint.lua:298,311> (29 instructions, 116 bytes at 0x7ffc5fc0b6f0)
3 params, 11 slots, 2 upvalues, 7 locals, 8 constants, 0 functions
	1	[299]	EQ       	0 1 -1	; - nil
	2	[299]	JMP      	1	; to 4
	3	[300]	LOADK    	1 -2	; "string input"
	4	[302]	GETGLOBAL	3 -3	; require
	5	[302]	LOADK    	4 -4	; "moonscript.parse"
	6	[302]	CALL     	3 2 2
	7	[303]	GETTABLE 	4 3 -5	; "string"
	8	[303]	MOVE     	5 0
	9	[303]	CALL     	4 2 3
	10	[304]	TEST     	4 0 1
	11	[304]	JMP      	3	; to 15
	12	[305]	LOADNIL  	6 6
	13	[305]	MOVE     	7 5
	14	[305]	RETURN   	6 3
	15	[307]	GETUPVAL 	6 0	; LinterBlock
	16	[307]	MOVE     	7 2
	17	[307]	CALL     	6 2 2
	18	[308]	SELF     	7 6 -6	; "stms"
	19	[308]	MOVE     	9 4
	20	[308]	CALL     	7 3 1
	21	[309]	SELF     	7 6 -7	; "lint_check_unused"
	22	[309]	CALL     	7 2 1
	23	[310]	GETUPVAL 	7 1	; format_lint
	24	[310]	GETTABLE 	8 6 -8	; "lint_errors"
	25	[310]	MOVE     	9 0
	26	[310]	MOVE     	10 1
	27	[310]	TAILCALL 	7 4 0
	28	[310]	RETURN   	7 0
	29	[311]	RETURN   	0 1

function <./moonscript/cmd/lint.lua:313,319> (20 instructions, 80 bytes at 0x7ffc5fc0c430)
1 param, 8 slots, 2 upvalues, 3 locals, 4 constants, 0 functions
	1	[314]	GETGLOBAL	1 -1	; io
	2	[314]	GETTABLE 	1 1 -2	; "open"
	3	[314]	MOVE     	2 0
	4	[314]	CALL     	1 2 3
	5	[315]	TEST     	1 0 1
	6	[315]	JMP      	3	; to 10
	7	[316]	LOADNIL  	3 3
	8	[316]	MOVE     	4 2
	9	[316]	RETURN   	3 3
	10	[318]	GETUPVAL 	3 0	; lint_code
	11	[318]	SELF     	4 1 -3	; "read"
	12	[318]	LOADK    	6 -4	; "*a"
	13	[318]	CALL     	4 3 2
	14	[318]	MOVE     	5 0
	15	[318]	GETUPVAL 	6 1	; whitelist_for_file
	16	[318]	MOVE     	7 0
	17	[318]	CALL     	6 2 0
	18	[318]	TAILCALL 	3 0 0
	19	[318]	RETURN   	3 0
	20	[319]	RETURN   	0 1
