-- BYTECODE -- literals.lua:9-11
0001    LEN      1   0
0002    RET1     1   2

-- BYTECODE -- literals.lua:0-40
0001    KPRI     0   0
0002    GGET     1   0      ; "require"
0003    KSTR     2   1      ; "moonscript.util"
0004    CALL     1   2   2
0005    TGETS    0   1   2  ; "safe_module"
0006    KNIL     1   4
0007    GGET     5   0      ; "require"
0008    KSTR     6   3      ; "lpeg"
0009    CALL     5   2   2
0010    TGETS    6   5   4  ; "S"
0011    TGETS    7   5   5  ; "P"
0012    TGETS    8   5   6  ; "R"
0013    TGETS    4   5   7  ; "C"
0014    MOV      3   8
0015    MOV      2   7
0016    MOV      1   6
0017    GGET     5   0      ; "require"
0018    KSTR     6   3      ; "lpeg"
0019    CALL     5   2   2
0020    TGETS    6   5   8  ; "luversion"
0021    ISF          6
0022    JMP      7 => 0026
0023    TGETS    6   5   9  ; "L"
0024    IST          6
0025    JMP      7 => 0027
0026 => FNEW     6  10      ; literals.lua:9
0027 => MOV      7   1
0028    KSTR     8  11      ; " \t\r\n"
0029    CALL     7   2   2
0030    KSHORT   8   0
0031    POW      7   7   8
0032    MOV      8   1
0033    KSTR     9  12      ; " \t"
0034    CALL     8   2   2
0035    KSHORT   9   0
0036    POW      8   8   9
0037    MOV      9   2
0038    KSTR    10  13      ; "\r"
0039    CALL     9   2   2
0040    KSHORT  10  -1
0041    POW      9   9  10
0042    MOV     10   2
0043    KSTR    11  14      ; "\n"
0044    CALL    10   2   2
0045    MULVV    9   9  10
0046    ADDVN   10   9   0  ; -1
0047    MOV     11   2
0048    KSTR    12  15      ; "--"
0049    CALL    11   2   2
0050    MOV     12   1
0051    KSTR    13  16      ; "\r\n"
0052    CALL    12   2   2
0053    SUBNV   12  12   1  ; 1
0054    KSHORT  13   0
0055    POW     12  12  13
0056    MULVV   11  11  12
0057    MOV     12   6
0058    MOV     13  10
0059    CALL    12   2   2
0060    MULVV   11  11  12
0061    KSHORT  12  -1
0062    POW     12  11  12
0063    MULVV   12   8  12
0064    MOV     13   1
0065    KSTR    14  12      ; " \t"
0066    CALL    13   2   2
0067    KSHORT  14   1
0068    POW     13  13  14
0069    KSHORT  14  -1
0070    POW     14  11  14
0071    MULVV   13  13  14
0072    MULVV   14  12   9
0073    MOV     15  14
0074    MOV     16   3
0075    KSTR    17  17      ; "az"
0076    KSTR    18  18      ; "AZ"
0077    KSTR    19  19      ; "09"
0078    KSTR    20  20      ; "__"
0079    CALL    16   2   5
0080    MOV     17   4
0081    MOV     18   3
0082    KSTR    19  17      ; "az"
0083    KSTR    20  18      ; "AZ"
0084    KSTR    21  20      ; "__"
0085    CALL    18   2   4
0086    KSHORT  19   0
0087    POW     19  16  19
0088    MULVV   18  18  19
0089    CALL    17   2   2
0090    MOV     18   2
0091    KSTR    19  21      ; "0x"
0092    CALL    18   2   2
0093    MOV     19   3
0094    KSTR    20  19      ; "09"
0095    KSTR    21  22      ; "af"
0096    KSTR    22  23      ; "AF"
0097    CALL    19   2   4
0098    KSHORT  20   1
0099    POW     19  19  20
0100    MULVV   18  18  19
0101    MOV     19   1
0102    KSTR    20  24      ; "uU"
0103    CALL    19   2   2
0104    KSHORT  20  -1
0105    POW     19  19  20
0106    MOV     20   1
0107    KSTR    21  25      ; "lL"
0108    CALL    20   2   2
0109    KSHORT  21   2
0110    POW     20  20  21
0111    MULVV   19  19  20
0112    KSHORT  20  -1
0113    POW     19  19  20
0114    MULVV   18  18  19
0115    MOV     19   3
0116    KSTR    20  19      ; "09"
0117    CALL    19   2   2
0118    KSHORT  20   1
0119    POW     19  19  20
0120    MOV     20   1
0121    KSTR    21  24      ; "uU"
0122    CALL    20   2   2
0123    KSHORT  21  -1
0124    POW     20  20  21
0125    MOV     21   1
0126    KSTR    22  25      ; "lL"
0127    CALL    21   2   2
0128    KSHORT  22   2
0129    POW     21  21  22
0130    MULVV   20  20  21
0131    MULVV   19  19  20
0132    ADDVV   18  18  19
0133    MOV     19   3
0134    KSTR    20  19      ; "09"
0135    CALL    19   2   2
0136    KSHORT  20   1
0137    POW     19  19  20
0138    MOV     20   2
0139    KSTR    21  26      ; "."
0140    CALL    20   2   2
0141    MOV     21   3
0142    KSTR    22  19      ; "09"
0143    CALL    21   2   2
0144    KSHORT  22   1
0145    POW     21  21  22
0146    MULVV   20  20  21
0147    KSHORT  21  -1
0148    POW     20  20  21
0149    MULVV   19  19  20
0150    MOV     20   2
0151    KSTR    21  26      ; "."
0152    CALL    20   2   2
0153    MOV     21   3
0154    KSTR    22  19      ; "09"
0155    CALL    21   2   2
0156    KSHORT  22   1
0157    POW     21  21  22
0158    MULVV   20  20  21
0159    ADDVV   19  19  20
0160    MOV     20   1
0161    KSTR    21  27      ; "eE"
0162    CALL    20   2   2
0163    MOV     21   2
0164    KSTR    22  28      ; "-"
0165    CALL    21   2   2
0166    KSHORT  22  -1
0167    POW     21  21  22
0168    MULVV   20  20  21
0169    MOV     21   3
0170    KSTR    22  19      ; "09"
0171    CALL    21   2   2
0172    KSHORT  22   1
0173    POW     21  21  22
0174    MULVV   20  20  21
0175    KSHORT  21  -1
0176    POW     20  20  21
0177    MULVV   19  19  20
0178    ADDVV   18  18  19
0179    MOV     19   2
0180    KSTR    20  29      ; "#!"
0181    CALL    19   2   2
0182    MOV     20   2
0183    SUBNV   21  10   1  ; 1
0184    CALL    20   2   2
0185    KSHORT  21   0
0186    POW     20  20  21
0187    MULVV   19  19  20
0188    MOV     20   0
0189    KSTR    21  30      ; "moonscript.parse.literals"
0190    TDUP    22  31
0191    TSETS    6  22   9  ; "L"
0192    TSETS    7  22  32  ; "White"
0193    TSETS    9  22  33  ; "Break"
0194    TSETS   10  22  34  ; "Stop"
0195    TSETS   11  22  35  ; "Comment"
0196    TSETS   12  22  36  ; "Space"
0197    TSETS   13  22  37  ; "SomeSpace"
0198    TSETS   14  22  38  ; "SpaceBreak"
0199    TSETS   15  22  39  ; "EmptyLine"
0200    TSETS   16  22  40  ; "AlphaNum"
0201    TSETS   17  22  41  ; "Name"
0202    TSETS   18  22  42  ; "Num"
0203    TSETS   19  22  43  ; "Shebang"
0204    UCLO     0 => 0205
0205 => CALLT   20   3

