
main <./moonscript/parse/literals.lua:0,0> (182 instructions, 728 bytes at 0x7fc26d4068c0)
0+ params, 23 slots, 0 upvalues, 21 locals, 46 constants, 1 function
	1	[2]	GETGLOBAL	1 -1	; require
	2	[2]	LOADK    	2 -2	; "moonscript.util"
	3	[2]	CALL     	1 2 2
	4	[2]	GETTABLE 	0 1 -3	; "safe_module"
	5	[3]	LOADNIL  	1 4
	6	[5]	GETGLOBAL	5 -1	; require
	7	[5]	LOADK    	6 -4	; "lpeg"
	8	[5]	CALL     	5 2 2
	9	[6]	GETTABLE 	6 5 -5	; "S"
	10	[6]	GETTABLE 	7 5 -6	; "P"
	11	[6]	GETTABLE 	8 5 -7	; "R"
	12	[6]	GETTABLE 	4 5 -8	; "C"
	13	[6]	MOVE     	3 8
	14	[6]	MOVE     	2 7
	15	[6]	MOVE     	1 6
	16	[8]	GETGLOBAL	5 -1	; require
	17	[8]	LOADK    	6 -4	; "lpeg"
	18	[8]	CALL     	5 2 2
	19	[9]	GETTABLE 	6 5 -9	; "luversion"
	20	[9]	TEST     	6 0 0
	21	[9]	JMP      	3	; to 25
	22	[9]	GETTABLE 	6 5 -10	; "L"
	23	[9]	TEST     	6 0 1
	24	[9]	JMP      	1	; to 26
	25	[11]	CLOSURE  	6 0	; 0x7fc26d406ab0
	26	[12]	MOVE     	7 1
	27	[12]	LOADK    	8 -11	; " \t\r\n"
	28	[12]	CALL     	7 2 2
	29	[12]	POW      	7 7 -12	; - 0
	30	[13]	MOVE     	8 1
	31	[13]	LOADK    	9 -13	; " \t"
	32	[13]	CALL     	8 2 2
	33	[13]	POW      	8 8 -12	; - 0
	34	[14]	MOVE     	9 2
	35	[14]	LOADK    	10 -14	; "\r"
	36	[14]	CALL     	9 2 2
	37	[14]	POW      	9 9 -15	; - -1
	38	[14]	MOVE     	10 2
	39	[14]	LOADK    	11 -16	; "\n"
	40	[14]	CALL     	10 2 2
	41	[14]	MUL      	9 9 10
	42	[15]	ADD      	10 9 -15	; - -1
	43	[16]	MOVE     	11 2
	44	[16]	LOADK    	12 -17	; "--"
	45	[16]	CALL     	11 2 2
	46	[16]	MOVE     	12 1
	47	[16]	LOADK    	13 -18	; "\r\n"
	48	[16]	CALL     	12 2 2
	49	[16]	SUB      	12 -19 12	; 1 -
	50	[16]	POW      	12 12 -12	; - 0
	51	[16]	MUL      	11 11 12
	52	[16]	MOVE     	12 6
	53	[16]	MOVE     	13 10
	54	[16]	CALL     	12 2 2
	55	[16]	MUL      	11 11 12
	56	[17]	POW      	12 11 -15	; - -1
	57	[17]	MUL      	12 8 12
	58	[18]	MOVE     	13 1
	59	[18]	LOADK    	14 -13	; " \t"
	60	[18]	CALL     	13 2 2
	61	[18]	POW      	13 13 -19	; - 1
	62	[18]	POW      	14 11 -15	; - -1
	63	[18]	MUL      	13 13 14
	64	[19]	MUL      	14 12 9
	65	[20]	MOVE     	15 14
	66	[21]	MOVE     	16 3
	67	[21]	LOADK    	17 -20	; "az"
	68	[21]	LOADK    	18 -21	; "AZ"
	69	[21]	LOADK    	19 -22	; "09"
	70	[21]	LOADK    	20 -23	; "__"
	71	[21]	CALL     	16 5 2
	72	[22]	MOVE     	17 4
	73	[22]	MOVE     	18 3
	74	[22]	LOADK    	19 -20	; "az"
	75	[22]	LOADK    	20 -21	; "AZ"
	76	[22]	LOADK    	21 -23	; "__"
	77	[22]	CALL     	18 4 2
	78	[22]	POW      	19 16 -12	; - 0
	79	[22]	MUL      	18 18 19
	80	[22]	CALL     	17 2 2
	81	[23]	MOVE     	18 2
	82	[23]	LOADK    	19 -24	; "0x"
	83	[23]	CALL     	18 2 2
	84	[23]	MOVE     	19 3
	85	[23]	LOADK    	20 -22	; "09"
	86	[23]	LOADK    	21 -25	; "af"
	87	[23]	LOADK    	22 -26	; "AF"
	88	[23]	CALL     	19 4 2
	89	[23]	POW      	19 19 -19	; - 1
	90	[23]	MUL      	18 18 19
	91	[23]	MOVE     	19 1
	92	[23]	LOADK    	20 -27	; "uU"
	93	[23]	CALL     	19 2 2
	94	[23]	POW      	19 19 -15	; - -1
	95	[23]	MOVE     	20 1
	96	[23]	LOADK    	21 -28	; "lL"
	97	[23]	CALL     	20 2 2
	98	[23]	POW      	20 20 -29	; - 2
	99	[23]	MUL      	19 19 20
	100	[23]	POW      	19 19 -15	; - -1
	101	[23]	MUL      	18 18 19
	102	[23]	MOVE     	19 3
	103	[23]	LOADK    	20 -22	; "09"
	104	[23]	CALL     	19 2 2
	105	[23]	POW      	19 19 -19	; - 1
	106	[23]	MOVE     	20 1
	107	[23]	LOADK    	21 -27	; "uU"
	108	[23]	CALL     	20 2 2
	109	[23]	POW      	20 20 -15	; - -1
	110	[23]	MOVE     	21 1
	111	[23]	LOADK    	22 -28	; "lL"
	112	[23]	CALL     	21 2 2
	113	[23]	POW      	21 21 -29	; - 2
	114	[23]	MUL      	20 20 21
	115	[23]	MUL      	19 19 20
	116	[23]	ADD      	18 18 19
	117	[23]	MOVE     	19 3
	118	[23]	LOADK    	20 -22	; "09"
	119	[23]	CALL     	19 2 2
	120	[23]	POW      	19 19 -19	; - 1
	121	[23]	MOVE     	20 2
	122	[23]	LOADK    	21 -30	; "."
	123	[23]	CALL     	20 2 2
	124	[23]	MOVE     	21 3
	125	[23]	LOADK    	22 -22	; "09"
	126	[23]	CALL     	21 2 2
	127	[23]	POW      	21 21 -19	; - 1
	128	[23]	MUL      	20 20 21
	129	[23]	POW      	20 20 -15	; - -1
	130	[23]	MUL      	19 19 20
	131	[23]	MOVE     	20 2
	132	[23]	LOADK    	21 -30	; "."
	133	[23]	CALL     	20 2 2
	134	[23]	MOVE     	21 3
	135	[23]	LOADK    	22 -22	; "09"
	136	[23]	CALL     	21 2 2
	137	[23]	POW      	21 21 -19	; - 1
	138	[23]	MUL      	20 20 21
	139	[23]	ADD      	19 19 20
	140	[23]	MOVE     	20 1
	141	[23]	LOADK    	21 -31	; "eE"
	142	[23]	CALL     	20 2 2
	143	[23]	MOVE     	21 2
	144	[23]	LOADK    	22 -32	; "-"
	145	[23]	CALL     	21 2 2
	146	[23]	POW      	21 21 -15	; - -1
	147	[23]	MUL      	20 20 21
	148	[23]	MOVE     	21 3
	149	[23]	LOADK    	22 -22	; "09"
	150	[23]	CALL     	21 2 2
	151	[23]	POW      	21 21 -19	; - 1
	152	[23]	MUL      	20 20 21
	153	[23]	POW      	20 20 -15	; - -1
	154	[23]	MUL      	19 19 20
	155	[23]	ADD      	18 18 19
	156	[24]	MOVE     	19 2
	157	[24]	LOADK    	20 -33	; "#!"
	158	[24]	CALL     	19 2 2
	159	[24]	MOVE     	20 2
	160	[24]	SUB      	21 -19 10	; 1 -
	161	[24]	CALL     	20 2 2
	162	[24]	POW      	20 20 -12	; - 0
	163	[24]	MUL      	19 19 20
	164	[25]	MOVE     	20 0
	165	[25]	LOADK    	21 -34	; "moonscript.parse.literals"
	166	[25]	NEWTABLE 	22 0 13
	167	[26]	SETTABLE 	22 -10 6	; "L" -
	168	[27]	SETTABLE 	22 -35 7	; "White" -
	169	[28]	SETTABLE 	22 -36 9	; "Break" -
	170	[29]	SETTABLE 	22 -37 10	; "Stop" -
	171	[30]	SETTABLE 	22 -38 11	; "Comment" -
	172	[31]	SETTABLE 	22 -39 12	; "Space" -
	173	[32]	SETTABLE 	22 -40 13	; "SomeSpace" -
	174	[33]	SETTABLE 	22 -41 14	; "SpaceBreak" -
	175	[34]	SETTABLE 	22 -42 15	; "EmptyLine" -
	176	[35]	SETTABLE 	22 -43 16	; "AlphaNum" -
	177	[36]	SETTABLE 	22 -44 17	; "Name" -
	178	[37]	SETTABLE 	22 -45 18	; "Num" -
	179	[38]	SETTABLE 	22 -46 19	; "Shebang" -
	180	[25]	TAILCALL 	20 3 0
	181	[39]	RETURN   	20 0
	182	[39]	RETURN   	0 1

function <./moonscript/parse/literals.lua:9,11> (3 instructions, 12 bytes at 0x7fc26d406ab0)
1 param, 2 slots, 0 upvalues, 1 local, 0 constants, 0 functions
	1	[10]	LEN      	1 0
	2	[10]	RETURN   	1 2
	3	[11]	RETURN   	0 1
