
main <./moonscript/cmd/moonc.lua:0,0> (69 instructions, 276 bytes at 0x7fd606c068c0)
0+ params, 20 slots, 0 upvalues, 17 locals, 21 constants, 12 functions
	1	[1]	GETGLOBAL	0 -1	; require
	2	[1]	LOADK    	1 -2	; "lfs"
	3	[1]	CALL     	0 2 2
	4	[2]	LOADNIL  	1 1
	5	[3]	GETGLOBAL	2 -1	; require
	6	[3]	LOADK    	3 -3	; "moonscript.util"
	7	[3]	CALL     	2 2 2
	8	[3]	GETTABLE 	1 2 -4	; "split"
	9	[4]	LOADNIL  	2 15
	10	[5]	GETGLOBAL	16 -5	; package
	11	[5]	GETTABLE 	16 16 -6	; "config"
	12	[5]	SELF     	16 16 -7	; "sub"
	13	[5]	LOADK    	18 -8	; 1
	14	[5]	LOADK    	19 -8	; 1
	15	[5]	CALL     	16 4 2
	16	[5]	MOVE     	2 16
	17	[6]	EQ       	0 2 -9	; - "\\"
	18	[6]	JMP      	2	; to 21
	19	[7]	LOADK    	3 -10	; "\\/"
	20	[7]	JMP      	1	; to 22
	21	[9]	MOVE     	3 2
	22	[20]	CLOSURE  	4 0	; 0x7fd606c06640
	23	[20]	MOVE     	0 1
	24	[20]	MOVE     	0 2
	25	[20]	MOVE     	0 0
	26	[23]	CLOSURE  	5 1	; 0x7fd606c077a0
	27	[23]	MOVE     	0 3
	28	[23]	MOVE     	0 2
	29	[26]	CLOSURE  	6 2	; 0x7fd606c073b0
	30	[26]	MOVE     	0 3
	31	[29]	CLOSURE  	7 3	; 0x7fd606c07b20
	32	[29]	MOVE     	0 3
	33	[36]	CLOSURE  	8 4	; 0x7fd606c07f80
	34	[39]	CLOSURE  	9 5	; 0x7fd606c065c0
	35	[41]	LOADNIL  	16 16
	36	[56]	CLOSURE  	10 6	; 0x7fd606c08920
	37	[56]	MOVE     	0 16
	38	[56]	CLOSE    	16
	39	[108]	CLOSURE  	11 7	; 0x7fd606c08fe0
	40	[108]	MOVE     	0 10
	41	[108]	MOVE     	0 9
	42	[119]	CLOSURE  	12 8	; 0x7fd606c08ef0
	43	[119]	MOVE     	0 4
	44	[119]	MOVE     	0 6
	45	[142]	CLOSURE  	13 9	; 0x7fd606c097b0
	46	[142]	MOVE     	0 11
	47	[142]	MOVE     	0 12
	48	[150]	CLOSURE  	14 10	; 0x7fd606c09aa0
	49	[150]	MOVE     	0 2
	50	[178]	CLOSURE  	15 11	; 0x7fd606c09f80
	51	[178]	MOVE     	0 8
	52	[178]	MOVE     	0 5
	53	[178]	MOVE     	0 3
	54	[178]	MOVE     	0 14
	55	[178]	MOVE     	0 7
	56	[179]	NEWTABLE 	16 0 11
	57	[180]	SETTABLE 	16 -11 2	; "dirsep" -
	58	[181]	SETTABLE 	16 -12 4	; "mkdir" -
	59	[182]	SETTABLE 	16 -13 5	; "normalize_dir" -
	60	[183]	SETTABLE 	16 -14 6	; "parse_dir" -
	61	[184]	SETTABLE 	16 -15 7	; "parse_file" -
	62	[185]	SETTABLE 	16 -16 8	; "convert_path" -
	63	[186]	SETTABLE 	16 -17 10	; "gettime" -
	64	[187]	SETTABLE 	16 -18 9	; "format_time" -
	65	[188]	SETTABLE 	16 -19 15	; "path_to_target" -
	66	[189]	SETTABLE 	16 -20 11	; "compile_file_text" -
	67	[190]	SETTABLE 	16 -21 13	; "compile_and_write" -
	68	[191]	RETURN   	16 2
	69	[191]	RETURN   	0 1

function <./moonscript/cmd/moonc.lua:11,20> (37 instructions, 148 bytes at 0x7fd606c06640)
1 param, 12 slots, 3 upvalues, 8 locals, 5 constants, 0 functions
	1	[12]	GETUPVAL 	1 0	; split
	2	[12]	MOVE     	2 0
	3	[12]	GETUPVAL 	3 1	; dirsep
	4	[12]	CALL     	1 3 2
	5	[13]	LOADNIL  	2 2
	6	[14]	LOADK    	3 -1	; 1
	7	[14]	LEN      	4 1
	8	[14]	LOADK    	5 -1	; 1
	9	[14]	FORPREP  	3 20	; to 30
	10	[15]	GETTABLE 	7 1 6
	11	[16]	TEST     	2 0 0
	12	[16]	JMP      	12	; to 25
	13	[16]	GETGLOBAL	8 -2	; tostring
	14	[16]	MOVE     	9 2
	15	[16]	CALL     	8 2 2
	16	[16]	GETGLOBAL	9 -2	; tostring
	17	[16]	GETUPVAL 	10 1	; dirsep
	18	[16]	CALL     	9 2 2
	19	[16]	GETGLOBAL	10 -2	; tostring
	20	[16]	MOVE     	11 7
	21	[16]	CALL     	10 2 2
	22	[16]	CONCAT   	8 8 10
	23	[16]	TESTSET  	2 8 1
	24	[16]	JMP      	1	; to 26
	25	[16]	MOVE     	2 7
	26	[17]	GETUPVAL 	8 2	; lfs
	27	[17]	GETTABLE 	8 8 -3	; "mkdir"
	28	[17]	MOVE     	9 2
	29	[17]	CALL     	8 2 1
	30	[14]	FORLOOP  	3 -21	; to 10
	31	[19]	GETUPVAL 	3 2	; lfs
	32	[19]	GETTABLE 	3 3 -4	; "attributes"
	33	[19]	MOVE     	4 0
	34	[19]	LOADK    	5 -5	; "mode"
	35	[19]	TAILCALL 	3 3 0
	36	[19]	RETURN   	3 0
	37	[20]	RETURN   	0 1

function <./moonscript/cmd/moonc.lua:21,23> (12 instructions, 48 bytes at 0x7fd606c077a0)
1 param, 6 slots, 2 upvalues, 1 local, 4 constants, 0 functions
	1	[22]	SELF     	1 0 -1	; "match"
	2	[22]	LOADK    	3 -2	; "^(.-)["
	3	[22]	GETGLOBAL	4 -3	; tostring
	4	[22]	GETUPVAL 	5 0	; dirsep_chars
	5	[22]	CALL     	4 2 2
	6	[22]	LOADK    	5 -4	; "]*$"
	7	[22]	CONCAT   	3 3 5
	8	[22]	CALL     	1 3 2
	9	[22]	GETUPVAL 	2 1	; dirsep
	10	[22]	CONCAT   	1 1 2
	11	[22]	RETURN   	1 2
	12	[23]	RETURN   	0 1

function <./moonscript/cmd/moonc.lua:24,26> (10 instructions, 40 bytes at 0x7fd606c073b0)
1 param, 6 slots, 1 upvalue, 1 local, 4 constants, 0 functions
	1	[25]	SELF     	1 0 -1	; "match"
	2	[25]	LOADK    	3 -2	; "^(.-)[^"
	3	[25]	GETGLOBAL	4 -3	; tostring
	4	[25]	GETUPVAL 	5 0	; dirsep_chars
	5	[25]	CALL     	4 2 2
	6	[25]	LOADK    	5 -4	; "]*$"
	7	[25]	CONCAT   	3 3 5
	8	[25]	CALL     	1 3 2
	9	[25]	RETURN   	1 2
	10	[26]	RETURN   	0 1

function <./moonscript/cmd/moonc.lua:27,29> (10 instructions, 40 bytes at 0x7fd606c07b20)
1 param, 6 slots, 1 upvalue, 1 local, 4 constants, 0 functions
	1	[28]	SELF     	1 0 -1	; "match"
	2	[28]	LOADK    	3 -2	; "^.-([^"
	3	[28]	GETGLOBAL	4 -3	; tostring
	4	[28]	GETUPVAL 	5 0	; dirsep_chars
	5	[28]	CALL     	4 2 2
	6	[28]	LOADK    	5 -4	; "]*)$"
	7	[28]	CONCAT   	3 3 5
	8	[28]	CALL     	1 3 2
	9	[28]	RETURN   	1 2
	10	[29]	RETURN   	0 1

function <./moonscript/cmd/moonc.lua:30,36> (11 instructions, 44 bytes at 0x7fd606c07f80)
1 param, 5 slots, 0 upvalues, 2 locals, 3 constants, 0 functions
	1	[31]	SELF     	1 0 -1	; "gsub"
	2	[31]	LOADK    	3 -2	; "%.moon$"
	3	[31]	LOADK    	4 -3	; ".lua"
	4	[31]	CALL     	1 4 2
	5	[32]	EQ       	0 1 0
	6	[32]	JMP      	3	; to 10
	7	[33]	MOVE     	2 0
	8	[33]	LOADK    	3 -3	; ".lua"
	9	[33]	CONCAT   	1 2 3
	10	[35]	RETURN   	1 2
	11	[36]	RETURN   	0 1

function <./moonscript/cmd/moonc.lua:37,39> (6 instructions, 24 bytes at 0x7fd606c065c0)
1 param, 4 slots, 0 upvalues, 1 local, 3 constants, 0 functions
	1	[38]	LOADK    	1 -1	; "%.3fms"
	2	[38]	SELF     	1 1 -2	; "format"
	3	[38]	MUL      	3 0 -3	; - 1000
	4	[38]	TAILCALL 	1 3 0
	5	[38]	RETURN   	1 0
	6	[39]	RETURN   	0 1

function <./moonscript/cmd/moonc.lua:42,56> (24 instructions, 96 bytes at 0x7fd606c08920)
0 params, 2 slots, 1 upvalue, 0 locals, 4 constants, 1 function
	1	[43]	GETUPVAL 	0 0	; socket
	2	[43]	EQ       	0 0 -1	; - nil
	3	[43]	JMP      	9	; to 13
	4	[44]	GETGLOBAL	0 -2	; pcall
	5	[46]	CLOSURE  	1 0	; 0x7fd606c06c30
	6	[46]	GETUPVAL 	0 0	; socket
	7	[44]	CALL     	0 2 1
	8	[47]	GETUPVAL 	0 0	; socket
	9	[47]	TEST     	0 0 1
	10	[47]	JMP      	2	; to 13
	11	[48]	LOADBOOL 	0 0 0
	12	[48]	SETUPVAL 	0 0	; socket
	13	[51]	GETUPVAL 	0 0	; socket
	14	[51]	TEST     	0 0 0
	15	[51]	JMP      	5	; to 21
	16	[52]	GETUPVAL 	0 0	; socket
	17	[52]	GETTABLE 	0 0 -3	; "gettime"
	18	[52]	TAILCALL 	0 1 0
	19	[52]	RETURN   	0 0
	20	[52]	JMP      	3	; to 24
	21	[54]	LOADNIL  	0 0
	22	[54]	LOADK    	1 -4	; "LuaSocket needed for benchmark"
	23	[54]	RETURN   	0 3
	24	[56]	RETURN   	0 1

function <./moonscript/cmd/moonc.lua:44,46> (5 instructions, 20 bytes at 0x7fd606c06c30)
0 params, 2 slots, 1 upvalue, 0 locals, 2 constants, 0 functions
	1	[45]	GETGLOBAL	0 -1	; require
	2	[45]	LOADK    	1 -2	; "socket"
	3	[45]	CALL     	0 2 2
	4	[45]	SETUPVAL 	0 0	; socket
	5	[46]	RETURN   	0 1

function <./moonscript/cmd/moonc.lua:58,108> (120 instructions, 480 bytes at 0x7fd606c08fe0)
2 params, 19 slots, 2 upvalues, 13 locals, 27 constants, 0 functions
	1	[59]	EQ       	0 1 -1	; - nil
	2	[59]	JMP      	2	; to 5
	3	[60]	NEWTABLE 	2 0 0
	4	[60]	MOVE     	1 2
	5	[62]	GETGLOBAL	2 -2	; require
	6	[62]	LOADK    	3 -3	; "moonscript.parse"
	7	[62]	CALL     	2 2 2
	8	[63]	GETGLOBAL	3 -2	; require
	9	[63]	LOADK    	4 -4	; "moonscript.compile"
	10	[63]	CALL     	3 2 2
	11	[64]	LOADNIL  	4 4
	12	[65]	GETTABLE 	5 1 -5	; "benchmark"
	13	[65]	TEST     	5 0 0
	14	[65]	JMP      	5	; to 20
	15	[66]	GETGLOBAL	5 -6	; assert
	16	[66]	GETUPVAL 	6 0	; gettime
	17	[66]	CALL     	6 1 0
	18	[66]	CALL     	5 0 2
	19	[66]	MOVE     	4 5
	20	[68]	GETTABLE 	5 2 -7	; "string"
	21	[68]	MOVE     	6 0
	22	[68]	CALL     	5 2 3
	23	[69]	TEST     	5 0 1
	24	[69]	JMP      	3	; to 28
	25	[70]	LOADNIL  	7 7
	26	[70]	MOVE     	8 6
	27	[70]	RETURN   	7 3
	28	[72]	TEST     	4 0 0
	29	[72]	JMP      	3	; to 33
	30	[73]	GETUPVAL 	7 0	; gettime
	31	[73]	CALL     	7 1 2
	32	[73]	SUB      	4 7 4
	33	[75]	GETTABLE 	7 1 -8	; "show_parse_tree"
	34	[75]	TEST     	7 0 0
	35	[75]	JMP      	8	; to 44
	36	[76]	GETGLOBAL	7 -2	; require
	37	[76]	LOADK    	8 -9	; "moonscript.dump"
	38	[76]	CALL     	7 2 2
	39	[77]	GETTABLE 	8 7 -10	; "tree"
	40	[77]	MOVE     	9 5
	41	[77]	CALL     	8 2 1
	42	[78]	LOADBOOL 	8 1 0
	43	[78]	RETURN   	8 2
	44	[80]	LOADNIL  	7 7
	45	[81]	GETTABLE 	8 1 -5	; "benchmark"
	46	[81]	TEST     	8 0 0
	47	[81]	JMP      	3	; to 51
	48	[82]	GETUPVAL 	8 0	; gettime
	49	[82]	CALL     	8 1 2
	50	[82]	MOVE     	7 8
	51	[84]	GETTABLE 	8 3 -10	; "tree"
	52	[84]	MOVE     	9 5
	53	[84]	CALL     	8 2 4
	54	[85]	TEST     	8 0 1
	55	[85]	JMP      	7	; to 63
	56	[86]	LOADNIL  	11 11
	57	[86]	GETTABLE 	12 3 -11	; "format_error"
	58	[86]	MOVE     	13 9
	59	[86]	MOVE     	14 10
	60	[86]	MOVE     	15 0
	61	[86]	CALL     	12 4 0
	62	[86]	RETURN   	11 0
	63	[88]	TEST     	7 0 0
	64	[88]	JMP      	3	; to 68
	65	[89]	GETUPVAL 	11 0	; gettime
	66	[89]	CALL     	11 1 2
	67	[89]	SUB      	7 11 7
	68	[91]	GETTABLE 	11 1 -12	; "show_posmap"
	69	[91]	TEST     	11 0 0
	70	[91]	JMP      	20	; to 91
	71	[92]	LOADNIL  	11 11
	72	[93]	GETGLOBAL	12 -2	; require
	73	[93]	LOADK    	13 -13	; "moonscript.util"
	74	[93]	CALL     	12 2 2
	75	[93]	GETTABLE 	11 12 -14	; "debug_posmap"
	76	[94]	GETGLOBAL	12 -15	; print
	77	[94]	LOADK    	13 -16	; "Pos"
	78	[94]	LOADK    	14 -17	; "Lua"
	79	[94]	LOADK    	15 -18	; ">>"
	80	[94]	LOADK    	16 -19	; "Moon"
	81	[94]	CALL     	12 5 1
	82	[95]	GETGLOBAL	12 -15	; print
	83	[95]	MOVE     	13 11
	84	[95]	MOVE     	14 9
	85	[95]	MOVE     	15 0
	86	[95]	MOVE     	16 8
	87	[95]	CALL     	13 4 0
	88	[95]	CALL     	12 0 1
	89	[96]	LOADBOOL 	12 1 0
	90	[96]	RETURN   	12 2
	91	[98]	GETTABLE 	11 1 -5	; "benchmark"
	92	[98]	TEST     	11 0 0
	93	[98]	JMP      	25	; to 119
	94	[99]	GETGLOBAL	11 -15	; print
	95	[99]	GETGLOBAL	12 -20	; table
	96	[99]	GETTABLE 	12 12 -21	; "concat"
	97	[99]	NEWTABLE 	13 4 0
	98	[100]	GETTABLE 	14 1 -22	; "fname"
	99	[100]	TEST     	14 0 1
	100	[100]	JMP      	1	; to 102
	101	[100]	LOADK    	14 -23	; "stdin"
	102	[101]	LOADK    	15 -24	; "Parse time  \t"
	103	[101]	GETUPVAL 	16 1	; format_time
	104	[101]	MOVE     	17 4
	105	[101]	CALL     	16 2 2
	106	[101]	CONCAT   	15 15 16
	107	[102]	LOADK    	16 -25	; "Compile time\t"
	108	[102]	GETUPVAL 	17 1	; format_time
	109	[102]	MOVE     	18 7
	110	[102]	CALL     	17 2 2
	111	[102]	CONCAT   	16 16 17
	112	[104]	LOADK    	17 -26	; ""
	113	[104]	SETLIST  	13 4 1	; 1
	114	[104]	LOADK    	14 -27	; "\n"
	115	[99]	CALL     	12 3 0
	116	[99]	CALL     	11 0 1
	117	[105]	LOADBOOL 	11 1 0
	118	[105]	RETURN   	11 2
	119	[107]	RETURN   	8 2
	120	[108]	RETURN   	0 1

function <./moonscript/cmd/moonc.lua:109,119> (30 instructions, 120 bytes at 0x7fd606c08ef0)
2 params, 8 slots, 2 upvalues, 4 locals, 8 constants, 0 functions
	1	[110]	GETUPVAL 	2 0	; mkdir
	2	[110]	GETUPVAL 	3 1	; parse_dir
	3	[110]	MOVE     	4 0
	4	[110]	CALL     	3 2 0
	5	[110]	CALL     	2 0 1
	6	[111]	GETGLOBAL	2 -1	; io
	7	[111]	GETTABLE 	2 2 -2	; "open"
	8	[111]	MOVE     	3 0
	9	[111]	LOADK    	4 -3	; "w"
	10	[111]	CALL     	2 3 3
	11	[112]	TEST     	2 0 1
	12	[112]	JMP      	3	; to 16
	13	[113]	LOADNIL  	4 4
	14	[113]	MOVE     	5 3
	15	[113]	RETURN   	4 3
	16	[115]	GETGLOBAL	4 -4	; assert
	17	[115]	SELF     	5 2 -5	; "write"
	18	[115]	MOVE     	7 1
	19	[115]	CALL     	5 3 0
	20	[115]	CALL     	4 0 1
	21	[116]	GETGLOBAL	4 -4	; assert
	22	[116]	SELF     	5 2 -5	; "write"
	23	[116]	LOADK    	7 -6	; "\n"
	24	[116]	CALL     	5 3 0
	25	[116]	CALL     	4 0 1
	26	[117]	SELF     	4 2 -7	; "close"
	27	[117]	CALL     	4 2 1
	28	[118]	LOADK    	4 -8	; "build"
	29	[118]	RETURN   	4 2
	30	[119]	RETURN   	0 1

function <./moonscript/cmd/moonc.lua:120,142> (47 instructions, 188 bytes at 0x7fd606c097b0)
3 params, 10 slots, 2 upvalues, 7 locals, 10 constants, 0 functions
	1	[121]	EQ       	0 2 -1	; - nil
	2	[121]	JMP      	2	; to 5
	3	[122]	NEWTABLE 	3 0 0
	4	[122]	MOVE     	2 3
	5	[124]	GETGLOBAL	3 -2	; io
	6	[124]	GETTABLE 	3 3 -3	; "open"
	7	[124]	MOVE     	4 0
	8	[124]	CALL     	3 2 2
	9	[125]	TEST     	3 0 1
	10	[125]	JMP      	3	; to 14
	11	[126]	LOADNIL  	4 4
	12	[126]	LOADK    	5 -4	; "Can't find file"
	13	[126]	RETURN   	4 3
	14	[128]	GETGLOBAL	4 -5	; assert
	15	[128]	SELF     	5 3 -6	; "read"
	16	[128]	LOADK    	7 -7	; "*a"
	17	[128]	CALL     	5 3 0
	18	[128]	CALL     	4 0 2
	19	[129]	SELF     	5 3 -8	; "close"
	20	[129]	CALL     	5 2 1
	21	[130]	GETUPVAL 	5 0	; compile_file_text
	22	[130]	MOVE     	6 4
	23	[130]	MOVE     	7 2
	24	[130]	CALL     	5 3 3
	25	[131]	TEST     	5 0 1
	26	[131]	JMP      	3	; to 30
	27	[132]	LOADNIL  	7 7
	28	[132]	MOVE     	8 6
	29	[132]	RETURN   	7 3
	30	[134]	EQ       	0 5 -9	; - true
	31	[134]	JMP      	2	; to 34
	32	[135]	LOADBOOL 	7 1 0
	33	[135]	RETURN   	7 2
	34	[137]	GETTABLE 	7 2 -10	; "print"
	35	[137]	TEST     	7 0 0
	36	[137]	JMP      	5	; to 42
	37	[138]	GETGLOBAL	7 -10	; print
	38	[138]	MOVE     	8 5
	39	[138]	CALL     	7 2 1
	40	[139]	LOADBOOL 	7 1 0
	41	[139]	RETURN   	7 2
	42	[141]	GETUPVAL 	7 1	; write_file
	43	[141]	MOVE     	8 1
	44	[141]	MOVE     	9 5
	45	[141]	TAILCALL 	7 3 0
	46	[141]	RETURN   	7 0
	47	[142]	RETURN   	0 1

function <./moonscript/cmd/moonc.lua:143,150> (28 instructions, 112 bytes at 0x7fd606c09aa0)
1 param, 6 slots, 1 upvalue, 2 locals, 6 constants, 0 functions
	1	[144]	SELF     	1 0 -1	; "sub"
	2	[144]	LOADK    	3 -2	; 1
	3	[144]	LOADK    	4 -2	; 1
	4	[144]	CALL     	1 4 2
	5	[145]	GETUPVAL 	2 0	; dirsep
	6	[145]	EQ       	0 2 -3	; - "\\"
	7	[145]	JMP      	14	; to 22
	8	[146]	EQ       	1 1 -4	; - "/"
	9	[146]	JMP      	9	; to 19
	10	[146]	EQ       	1 1 -3	; - "\\"
	11	[146]	JMP      	7	; to 19
	12	[146]	SELF     	2 0 -1	; "sub"
	13	[146]	LOADK    	4 -5	; 2
	14	[146]	LOADK    	5 -2	; 1
	15	[146]	CALL     	2 4 2
	16	[146]	EQ       	1 2 -6	; - ":"
	17	[146]	JMP      	1	; to 19
	18	[146]	LOADBOOL 	2 0 1
	19	[146]	LOADBOOL 	2 1 0
	20	[146]	RETURN   	2 2
	21	[146]	JMP      	6	; to 28
	22	[148]	GETUPVAL 	2 0	; dirsep
	23	[148]	EQ       	1 1 2
	24	[148]	JMP      	1	; to 26
	25	[148]	LOADBOOL 	2 0 1
	26	[148]	LOADBOOL 	2 1 0
	27	[148]	RETURN   	2 2
	28	[150]	RETURN   	0 1

function <./moonscript/cmd/moonc.lua:151,178> (60 instructions, 240 bytes at 0x7fd606c09f80)
3 params, 11 slots, 5 upvalues, 7 locals, 9 constants, 0 functions
	1	[152]	EQ       	0 1 -1	; - nil
	2	[152]	JMP      	1	; to 4
	3	[153]	LOADNIL  	1 1
	4	[155]	EQ       	0 2 -1	; - nil
	5	[155]	JMP      	1	; to 7
	6	[156]	LOADNIL  	2 2
	7	[158]	GETUPVAL 	3 0	; convert_path
	8	[158]	MOVE     	4 0
	9	[158]	CALL     	3 2 2
	10	[159]	TEST     	1 0 0
	11	[159]	JMP      	4	; to 16
	12	[160]	GETUPVAL 	4 1	; normalize_dir
	13	[160]	MOVE     	5 1
	14	[160]	CALL     	4 2 2
	15	[160]	MOVE     	1 4
	16	[162]	TEST     	2 0 0
	17	[162]	JMP      	27	; to 45
	18	[162]	TEST     	1 0 0
	19	[162]	JMP      	25	; to 45
	20	[163]	SELF     	4 2 -2	; "match"
	21	[163]	LOADK    	6 -3	; "^(.-)[^"
	22	[163]	GETGLOBAL	7 -4	; tostring
	23	[163]	GETUPVAL 	8 2	; dirsep_chars
	24	[163]	CALL     	7 2 2
	25	[163]	LOADK    	8 -5	; "]*["
	26	[163]	GETGLOBAL	9 -4	; tostring
	27	[163]	GETUPVAL 	10 2	; dirsep_chars
	28	[163]	CALL     	9 2 2
	29	[163]	LOADK    	10 -6	; "]?$"
	30	[163]	CONCAT   	6 6 10
	31	[163]	CALL     	4 3 2
	32	[164]	TEST     	4 0 0
	33	[164]	JMP      	11	; to 45
	34	[165]	SELF     	5 3 -7	; "find"
	35	[165]	MOVE     	7 4
	36	[165]	LOADK    	8 -8	; 1
	37	[165]	LOADBOOL 	9 1 0
	38	[165]	CALL     	5 5 3
	39	[166]	EQ       	0 5 -8	; - 1
	40	[166]	JMP      	4	; to 45
	41	[167]	SELF     	7 3 -9	; "sub"
	42	[167]	ADD      	9 6 -8	; - 1
	43	[167]	CALL     	7 3 2
	44	[167]	MOVE     	3 7
	45	[171]	TEST     	1 0 0
	46	[171]	JMP      	12	; to 59
	47	[172]	GETUPVAL 	4 3	; is_abs_path
	48	[172]	MOVE     	5 3
	49	[172]	CALL     	4 2 2
	50	[172]	TEST     	4 0 0
	51	[172]	JMP      	4	; to 56
	52	[173]	GETUPVAL 	4 4	; parse_file
	53	[173]	MOVE     	5 3
	54	[173]	CALL     	4 2 2
	55	[173]	MOVE     	3 4
	56	[175]	MOVE     	4 1
	57	[175]	MOVE     	5 3
	58	[175]	CONCAT   	3 4 5
	59	[177]	RETURN   	3 2
	60	[178]	RETURN   	0 1
