
main <./moonscript/transform/names.lua:0,0> (69 instructions, 276 bytes at 0x7f88efc068d0)
0+ params, 10 slots, 0 upvalues, 9 locals, 19 constants, 10 functions
	1	[2]	GETGLOBAL	1 -1	; require
	2	[2]	LOADK    	2 -2	; "moonscript.types"
	3	[2]	CALL     	1 2 2
	4	[2]	GETTABLE 	0 1 -3	; "build"
	5	[3]	LOADNIL  	1 1
	6	[4]	GETGLOBAL	2 -1	; require
	7	[4]	LOADK    	3 -4	; "moonscript.util"
	8	[4]	CALL     	2 2 2
	9	[4]	GETTABLE 	1 2 -5	; "unpack"
	10	[5]	LOADNIL  	2 3
	11	[8]	NEWTABLE 	4 0 1
	12	[11]	CLOSURE  	5 0	; 0x7f88efc06c70
	13	[11]	SETTABLE 	4 -6 5	; "get_name" -
	14	[13]	SETTABLE 	4 -7 4	; "__index" -
	15	[14]	GETGLOBAL	5 -8	; setmetatable
	16	[14]	NEWTABLE 	6 0 3
	17	[18]	CLOSURE  	7 1	; 0x7f88efc06a90
	18	[18]	SETTABLE 	6 -9 7	; "__init" -
	19	[19]	SETTABLE 	6 -10 4	; "__base" -
	20	[20]	SETTABLE 	6 -11 -12	; "__name" "LocalName"
	21	[21]	NEWTABLE 	7 0 2
	22	[22]	SETTABLE 	7 -7 4	; "__index" -
	23	[27]	CLOSURE  	8 2	; 0x7f88efc06da0
	24	[27]	MOVE     	0 4
	25	[27]	SETTABLE 	7 -13 8	; "__call" -
	26	[14]	CALL     	5 3 2
	27	[28]	MOVE     	3 5
	28	[29]	SETTABLE 	4 -14 3	; "__class" -
	29	[30]	MOVE     	2 3
	30	[30]	CLOSE    	3
	31	[32]	LOADNIL  	3 4
	32	[35]	NEWTABLE 	5 0 4
	33	[44]	CLOSURE  	6 3	; 0x7f88efc06f70
	34	[44]	SETTABLE 	5 -6 6	; "get_name" -
	35	[61]	CLOSURE  	6 4	; 0x7f88efc07530
	36	[61]	MOVE     	0 0
	37	[61]	SETTABLE 	5 -15 6	; "chain" -
	38	[76]	CLOSURE  	6 5	; 0x7f88efc08050
	39	[76]	MOVE     	0 0
	40	[76]	SETTABLE 	5 -16 6	; "index" -
	41	[83]	CLOSURE  	6 6	; 0x7f88efc08370
	42	[83]	SETTABLE 	5 -17 6	; "__tostring" -
	43	[85]	SETTABLE 	5 -7 5	; "__index" -
	44	[86]	GETGLOBAL	6 -8	; setmetatable
	45	[86]	NEWTABLE 	7 0 3
	46	[90]	CLOSURE  	8 7	; 0x7f88efc07200
	47	[90]	SETTABLE 	7 -9 8	; "__init" -
	48	[91]	SETTABLE 	7 -10 5	; "__base" -
	49	[92]	SETTABLE 	7 -11 -18	; "__name" "NameProxy"
	50	[93]	NEWTABLE 	8 0 2
	51	[94]	SETTABLE 	8 -7 5	; "__index" -
	52	[99]	CLOSURE  	9 8	; 0x7f88efc089c0
	53	[99]	MOVE     	0 5
	54	[99]	SETTABLE 	8 -13 9	; "__call" -
	55	[86]	CALL     	6 3 2
	56	[100]	MOVE     	4 6
	57	[101]	SETTABLE 	5 -14 4	; "__class" -
	58	[102]	MOVE     	3 4
	59	[102]	CLOSE    	4
	60	[104]	LOADNIL  	4 4
	61	[113]	CLOSURE  	4 9	; 0x7f88efc06bc0
	62	[113]	MOVE     	0 2
	63	[113]	MOVE     	0 3
	64	[114]	NEWTABLE 	5 0 3
	65	[115]	SETTABLE 	5 -18 3	; "NameProxy" -
	66	[116]	SETTABLE 	5 -12 2	; "LocalName" -
	67	[117]	SETTABLE 	5 -19 4	; "is_name_proxy" -
	68	[118]	RETURN   	5 2
	69	[118]	RETURN   	0 1

function <./moonscript/transform/names.lua:9,11> (3 instructions, 12 bytes at 0x7f88efc06c70)
1 param, 2 slots, 0 upvalues, 1 local, 1 constant, 0 functions
	1	[10]	GETTABLE 	1 0 -1	; "name"
	2	[10]	RETURN   	1 2
	3	[11]	RETURN   	0 1

function <./moonscript/transform/names.lua:15,18> (3 instructions, 12 bytes at 0x7f88efc06a90)
2 params, 2 slots, 0 upvalues, 2 locals, 3 constants, 0 functions
	1	[16]	SETTABLE 	0 -1 1	; "name" -
	2	[17]	SETTABLE 	0 -2 -3	; 1 "temp_name"
	3	[18]	RETURN   	0 1

function <./moonscript/transform/names.lua:23,27> (10 instructions, 40 bytes at 0x7f88efc06da0)
1+ param, 6 slots, 1 upvalue, 3 locals, 2 constants, 0 functions
	1	[24]	GETGLOBAL	2 -1	; setmetatable
	2	[24]	NEWTABLE 	3 0 0
	3	[24]	GETUPVAL 	4 0	; _base_0
	4	[24]	CALL     	2 3 2
	5	[25]	GETTABLE 	3 0 -2	; "__init"
	6	[25]	MOVE     	4 2
	7	[25]	VARARG   	5 0
	8	[25]	CALL     	3 0 1
	9	[26]	RETURN   	2 2
	10	[27]	RETURN   	0 1

function <./moonscript/transform/names.lua:36,44> (14 instructions, 56 bytes at 0x7f88efc06f70)
3 params, 7 slots, 0 upvalues, 3 locals, 4 constants, 0 functions
	1	[37]	EQ       	0 2 -1	; - nil
	2	[37]	JMP      	1	; to 4
	3	[38]	LOADBOOL 	2 1 0
	4	[40]	GETTABLE 	3 0 -2	; "name"
	5	[40]	TEST     	3 0 1
	6	[40]	JMP      	5	; to 12
	7	[41]	SELF     	3 1 -3	; "free_name"
	8	[41]	GETTABLE 	5 0 -4	; "prefix"
	9	[41]	MOVE     	6 2
	10	[41]	CALL     	3 4 2
	11	[41]	SETTABLE 	0 -2 3	; "name" -
	12	[43]	GETTABLE 	3 0 -2	; "name"
	13	[43]	RETURN   	3 2
	14	[44]	RETURN   	0 1

function <./moonscript/transform/names.lua:45,61> (28 instructions, 112 bytes at 0x7f88efc07530)
1+ param, 11 slots, 1 upvalue, 8 locals, 6 constants, 0 functions
	1	[46]	NEWTABLE 	2 0 1
	2	[47]	SETTABLE 	2 -1 0	; "base" -
	3	[47]	VARARG   	3 0
	4	[49]	SETLIST  	2 0 1	; 1
	5	[50]	GETGLOBAL	3 -2	; ipairs
	6	[50]	MOVE     	4 2
	7	[50]	CALL     	3 2 4
	8	[50]	JMP      	12	; to 21
	9	[51]	GETGLOBAL	8 -3	; type
	10	[51]	MOVE     	9 7
	11	[51]	CALL     	8 2 2
	12	[51]	EQ       	0 8 -4	; - "string"
	13	[51]	JMP      	6	; to 20
	14	[52]	NEWTABLE 	8 2 0
	15	[53]	LOADK    	9 -5	; "dot"
	16	[55]	MOVE     	10 7
	17	[55]	SETLIST  	8 2 1	; 1
	18	[55]	SETTABLE 	2 6 8
	19	[55]	JMP      	1	; to 21
	20	[57]	SETTABLE 	2 6 7
	21	[50]	TFORLOOP 	3 2
	22	[58]	JMP      	-14	; to 9
	23	[60]	GETUPVAL 	3 0	; build
	24	[60]	GETTABLE 	3 3 -6	; "chain"
	25	[60]	MOVE     	4 2
	26	[60]	TAILCALL 	3 2 0
	27	[60]	RETURN   	3 0
	28	[61]	RETURN   	0 1

function <./moonscript/transform/names.lua:62,76> (22 instructions, 88 bytes at 0x7f88efc08050)
2 params, 7 slots, 1 upvalue, 2 locals, 6 constants, 0 functions
	1	[63]	GETGLOBAL	2 -1	; type
	2	[63]	MOVE     	3 1
	3	[63]	CALL     	2 2 2
	4	[63]	EQ       	0 2 -2	; - "string"
	5	[63]	JMP      	5	; to 11
	6	[64]	NEWTABLE 	2 2 0
	7	[65]	LOADK    	3 -3	; "ref"
	8	[67]	MOVE     	4 1
	9	[67]	SETLIST  	2 2 1	; 1
	10	[67]	MOVE     	1 2
	11	[69]	GETUPVAL 	2 0	; build
	12	[69]	GETTABLE 	2 2 -4	; "chain"
	13	[69]	NEWTABLE 	3 1 1
	14	[70]	SETTABLE 	3 -5 0	; "base" -
	15	[70]	NEWTABLE 	4 2 0
	16	[72]	LOADK    	5 -6	; "index"
	17	[74]	MOVE     	6 1
	18	[74]	SETLIST  	4 2 1	; 1
	19	[75]	SETLIST  	3 1 1	; 1
	20	[69]	TAILCALL 	2 2 0
	21	[75]	RETURN   	2 0
	22	[76]	RETURN   	0 1

function <./moonscript/transform/names.lua:77,83> (15 instructions, 60 bytes at 0x7f88efc08370)
1 param, 4 slots, 0 upvalues, 1 local, 5 constants, 0 functions
	1	[78]	GETTABLE 	1 0 -1	; "name"
	2	[78]	TEST     	1 0 0
	3	[78]	JMP      	6	; to 10
	4	[79]	LOADK    	1 -2	; "name<%s>"
	5	[79]	SELF     	1 1 -3	; "format"
	6	[79]	GETTABLE 	3 0 -1	; "name"
	7	[79]	TAILCALL 	1 3 0
	8	[79]	RETURN   	1 0
	9	[79]	JMP      	5	; to 15
	10	[81]	LOADK    	1 -4	; "name<prefix(%s)>"
	11	[81]	SELF     	1 1 -3	; "format"
	12	[81]	GETTABLE 	3 0 -5	; "prefix"
	13	[81]	TAILCALL 	1 3 0
	14	[81]	RETURN   	1 0
	15	[83]	RETURN   	0 1

function <./moonscript/transform/names.lua:87,90> (3 instructions, 12 bytes at 0x7f88efc07200)
2 params, 2 slots, 0 upvalues, 2 locals, 3 constants, 0 functions
	1	[88]	SETTABLE 	0 -1 1	; "prefix" -
	2	[89]	SETTABLE 	0 -2 -3	; 1 "temp_name"
	3	[90]	RETURN   	0 1

function <./moonscript/transform/names.lua:95,99> (10 instructions, 40 bytes at 0x7f88efc089c0)
1+ param, 6 slots, 1 upvalue, 3 locals, 2 constants, 0 functions
	1	[96]	GETGLOBAL	2 -1	; setmetatable
	2	[96]	NEWTABLE 	3 0 0
	3	[96]	GETUPVAL 	4 0	; _base_0
	4	[96]	CALL     	2 3 2
	5	[97]	GETTABLE 	3 0 -2	; "__init"
	6	[97]	MOVE     	4 2
	7	[97]	VARARG   	5 0
	8	[97]	CALL     	3 0 1
	9	[98]	RETURN   	2 2
	10	[99]	RETURN   	0 1

function <./moonscript/transform/names.lua:105,113> (17 instructions, 68 bytes at 0x7f88efc06bc0)
1 param, 3 slots, 2 upvalues, 2 locals, 3 constants, 0 functions
	1	[106]	GETGLOBAL	1 -1	; type
	2	[106]	MOVE     	2 0
	3	[106]	CALL     	1 2 2
	4	[106]	EQ       	1 1 -2	; - "table"
	5	[106]	JMP      	2	; to 8
	6	[107]	LOADBOOL 	1 0 0
	7	[107]	RETURN   	1 2
	8	[109]	GETTABLE 	1 0 -3	; "__class"
	9	[110]	GETUPVAL 	2 0	; LocalName
	10	[110]	EQ       	1 2 1
	11	[110]	JMP      	3	; to 15
	12	[110]	GETUPVAL 	2 1	; NameProxy
	13	[110]	EQ       	0 2 1
	14	[110]	JMP      	2	; to 17
	15	[111]	LOADBOOL 	2 1 0
	16	[111]	RETURN   	2 2
	17	[113]	RETURN   	0 1
