
main <./moonscript/parse.lua:0,0> (190 instructions, 760 bytes at 0x7f9c3ec068a0)
0+ params, 73 slots, 0 upvalues, 58 locals, 61 constants, 4 functions
	1	[1]	LOADBOOL 	0 0 0
	2	[2]	GETGLOBAL	1 -1	; require
	3	[2]	LOADK    	2 -2	; "lpeg"
	4	[2]	CALL     	1 2 2
	5	[3]	GETTABLE 	2 1 -3	; "setmaxstack"
	6	[3]	LOADK    	3 -4	; 10000
	7	[3]	CALL     	2 2 1
	8	[4]	LOADK    	2 -5	; "Failed to parse:%s\n [%d] >>    %s"
	9	[5]	LOADNIL  	3 3
	10	[6]	GETGLOBAL	4 -1	; require
	11	[6]	LOADK    	5 -6	; "moonscript.data"
	12	[6]	CALL     	4 2 2
	13	[6]	GETTABLE 	3 4 -7	; "Stack"
	14	[7]	LOADNIL  	4 6
	15	[9]	GETGLOBAL	7 -1	; require
	16	[9]	LOADK    	8 -8	; "moonscript.util"
	17	[9]	CALL     	7 2 2
	18	[10]	GETTABLE 	8 7 -9	; "trim"
	19	[10]	GETTABLE 	9 7 -10	; "pos_to_line"
	20	[10]	GETTABLE 	6 7 -11	; "get_line"
	21	[10]	MOVE     	5 9
	22	[10]	MOVE     	4 8
	23	[12]	LOADNIL  	7 7
	24	[13]	GETGLOBAL	8 -1	; require
	25	[13]	LOADK    	9 -8	; "moonscript.util"
	26	[13]	CALL     	8 2 2
	27	[13]	GETTABLE 	7 8 -12	; "unpack"
	28	[14]	LOADNIL  	8 8
	29	[15]	GETGLOBAL	9 -1	; require
	30	[15]	LOADK    	10 -13	; "moonscript.parse.env"
	31	[15]	CALL     	9 2 2
	32	[15]	GETTABLE 	8 9 -14	; "wrap_env"
	33	[16]	LOADNIL  	9 18
	34	[17]	GETTABLE 	19 1 -15	; "R"
	35	[17]	GETTABLE 	20 1 -16	; "S"
	36	[17]	GETTABLE 	21 1 -17	; "V"
	37	[17]	GETTABLE 	22 1 -18	; "P"
	38	[17]	GETTABLE 	23 1 -19	; "C"
	39	[17]	GETTABLE 	24 1 -20	; "Ct"
	40	[17]	GETTABLE 	25 1 -21	; "Cmt"
	41	[17]	GETTABLE 	26 1 -22	; "Cg"
	42	[17]	GETTABLE 	27 1 -23	; "Cb"
	43	[17]	GETTABLE 	18 1 -24	; "Cc"
	44	[17]	MOVE     	17 27
	45	[17]	MOVE     	16 26
	46	[17]	MOVE     	15 25
	47	[17]	MOVE     	14 24
	48	[17]	MOVE     	13 23
	49	[17]	MOVE     	12 22
	50	[17]	MOVE     	11 21
	51	[17]	MOVE     	10 20
	52	[17]	MOVE     	9 19
	53	[18]	LOADNIL  	19 31
	54	[20]	GETGLOBAL	32 -1	; require
	55	[20]	LOADK    	33 -25	; "moonscript.parse.literals"
	56	[20]	CALL     	32 2 2
	57	[21]	GETTABLE 	33 32 -26	; "White"
	58	[21]	GETTABLE 	34 32 -27	; "Break"
	59	[21]	GETTABLE 	35 32 -28	; "Stop"
	60	[21]	GETTABLE 	36 32 -29	; "Comment"
	61	[21]	GETTABLE 	37 32 -30	; "Space"
	62	[21]	GETTABLE 	38 32 -31	; "SomeSpace"
	63	[21]	GETTABLE 	39 32 -32	; "SpaceBreak"
	64	[21]	GETTABLE 	40 32 -33	; "EmptyLine"
	65	[21]	GETTABLE 	41 32 -34	; "AlphaNum"
	66	[21]	GETTABLE 	42 32 -35	; "Num"
	67	[21]	GETTABLE 	43 32 -36	; "Shebang"
	68	[21]	GETTABLE 	44 32 -37	; "L"
	69	[21]	GETTABLE 	31 32 -38	; "Name"
	70	[21]	MOVE     	30 44
	71	[21]	MOVE     	29 43
	72	[21]	MOVE     	28 42
	73	[21]	MOVE     	27 41
	74	[21]	MOVE     	26 40
	75	[21]	MOVE     	25 39
	76	[21]	MOVE     	24 38
	77	[21]	MOVE     	23 37
	78	[21]	MOVE     	22 36
	79	[21]	MOVE     	21 35
	80	[21]	MOVE     	20 34
	81	[21]	MOVE     	19 33
	82	[23]	MUL      	32 23 31
	83	[29]	CLOSURE  	33 0	; 0x7f9c3ec06d20
	84	[29]	DIV      	33 28 33
	85	[29]	MUL      	28 23 33
	86	[30]	LOADNIL  	33 52
	87	[32]	GETGLOBAL	53 -1	; require
	88	[32]	LOADK    	54 -39	; "moonscript.parse.util"
	89	[32]	CALL     	53 2 2
	90	[33]	GETTABLE 	54 53 -40	; "Indent"
	91	[33]	GETTABLE 	55 53 -41	; "Cut"
	92	[33]	GETTABLE 	56 53 -42	; "ensure"
	93	[33]	GETTABLE 	57 53 -43	; "extract_line"
	94	[33]	GETTABLE 	58 53 -44	; "mark"
	95	[33]	GETTABLE 	59 53 -45	; "pos"
	96	[33]	GETTABLE 	60 53 -46	; "flatten_or_mark"
	97	[33]	GETTABLE 	61 53 -47	; "is_assignable"
	98	[33]	GETTABLE 	62 53 -48	; "check_assignable"
	99	[33]	GETTABLE 	63 53 -49	; "format_assign"
	100	[33]	GETTABLE 	64 53 -50	; "format_single_assign"
	101	[33]	GETTABLE 	65 53 -51	; "sym"
	102	[33]	GETTABLE 	66 53 -52	; "symx"
	103	[33]	GETTABLE 	67 53 -53	; "simple_string"
	104	[33]	GETTABLE 	68 53 -54	; "wrap_func_arg"
	105	[33]	GETTABLE 	69 53 -55	; "join_chain"
	106	[33]	GETTABLE 	70 53 -56	; "wrap_decorator"
	107	[33]	GETTABLE 	71 53 -57	; "check_lua_string"
	108	[33]	GETTABLE 	72 53 -58	; "self_assign"
	109	[33]	GETTABLE 	52 53 -59	; "got"
	110	[33]	MOVE     	51 72
	111	[33]	MOVE     	50 71
	112	[33]	MOVE     	49 70
	113	[33]	MOVE     	48 69
	114	[33]	MOVE     	47 68
	115	[33]	MOVE     	46 67
	116	[33]	MOVE     	45 66
	117	[33]	MOVE     	44 65
	118	[33]	MOVE     	43 64
	119	[33]	MOVE     	42 63
	120	[33]	MOVE     	41 62
	121	[33]	MOVE     	40 61
	122	[33]	MOVE     	39 60
	123	[33]	MOVE     	38 59
	124	[33]	MOVE     	37 58
	125	[33]	MOVE     	36 57
	126	[33]	MOVE     	35 56
	127	[33]	MOVE     	34 55
	128	[33]	MOVE     	33 54
	129	[35]	MOVE     	53 8
	130	[35]	MOVE     	54 0
	131	[204]	CLOSURE  	55 1	; 0x7f9c3ec07020
	132	[204]	MOVE     	0 3
	133	[204]	MOVE     	0 15
	134	[204]	MOVE     	0 23
	135	[204]	MOVE     	0 27
	136	[204]	MOVE     	0 13
	137	[204]	MOVE     	0 32
	138	[204]	MOVE     	0 4
	139	[204]	MOVE     	0 31
	140	[204]	MOVE     	0 37
	141	[204]	MOVE     	0 18
	142	[204]	MOVE     	0 12
	143	[204]	MOVE     	0 29
	144	[204]	MOVE     	0 14
	145	[204]	MOVE     	0 20
	146	[204]	MOVE     	0 33
	147	[204]	MOVE     	0 30
	148	[204]	MOVE     	0 21
	149	[204]	MOVE     	0 38
	150	[204]	MOVE     	0 42
	151	[204]	MOVE     	0 49
	152	[204]	MOVE     	0 26
	153	[204]	MOVE     	0 25
	154	[204]	MOVE     	0 44
	155	[204]	MOVE     	0 35
	156	[204]	MOVE     	0 43
	157	[204]	MOVE     	0 10
	158	[204]	MOVE     	0 41
	159	[204]	MOVE     	0 39
	160	[204]	MOVE     	0 24
	161	[204]	MOVE     	0 28
	162	[204]	MOVE     	0 48
	163	[204]	MOVE     	0 46
	164	[204]	MOVE     	0 16
	165	[204]	MOVE     	0 17
	166	[204]	MOVE     	0 50
	167	[204]	MOVE     	0 45
	168	[204]	MOVE     	0 19
	169	[204]	MOVE     	0 47
	170	[204]	MOVE     	0 34
	171	[204]	MOVE     	0 1
	172	[204]	MOVE     	0 51
	173	[35]	CALL     	53 3 2
	174	[205]	LOADNIL  	54 54
	175	[238]	CLOSURE  	54 2	; 0x7f9c3ec09b10
	176	[238]	MOVE     	0 53
	177	[238]	MOVE     	0 19
	178	[238]	MOVE     	0 7
	179	[238]	MOVE     	0 5
	180	[238]	MOVE     	0 6
	181	[238]	MOVE     	0 2
	182	[238]	MOVE     	0 4
	183	[239]	NEWTABLE 	55 0 3
	184	[240]	SETTABLE 	55 -43 36	; "extract_line" -
	185	[241]	SETTABLE 	55 -60 53	; "build_grammar" -
	186	[244]	CLOSURE  	56 3	; 0x7f9c3ec0b4c0
	187	[244]	MOVE     	0 54
	188	[244]	SETTABLE 	55 -61 56	; "string" -
	189	[245]	RETURN   	55 2
	190	[245]	RETURN   	0 1

function <./moonscript/parse.lua:24,29> (6 instructions, 24 bytes at 0x7f9c3ec06d20)
1 param, 4 slots, 0 upvalues, 1 local, 1 constant, 0 functions
	1	[25]	NEWTABLE 	1 2 0
	2	[26]	LOADK    	2 -1	; "number"
	3	[28]	MOVE     	3 0
	4	[28]	SETLIST  	1 2 1	; 1
	5	[28]	RETURN   	1 2
	6	[29]	RETURN   	0 1

function <./moonscript/parse.lua:35,204> (1831 instructions, 7324 bytes at 0x7f9c3ec07020)
1 param, 30 slots, 41 upvalues, 21 locals, 205 constants, 10 functions
	1	[36]	GETUPVAL 	1 0	; Stack
	2	[36]	LOADK    	2 -1	; 0
	3	[36]	CALL     	1 2 2
	4	[37]	GETUPVAL 	2 0	; Stack
	5	[37]	LOADK    	3 -1	; 0
	6	[37]	CALL     	2 2 2
	7	[38]	NEWTABLE 	3 0 1
	8	[39]	SETTABLE 	3 -2 -1	; "last_pos" 0
	9	[41]	LOADNIL  	4 4
	10	[45]	CLOSURE  	4 0	; 0x7f9c3ec072d0
	11	[45]	MOVE     	0 3
	12	[45]	MOVE     	0 1
	13	[46]	LOADNIL  	5 5
	14	[53]	CLOSURE  	5 1	; 0x7f9c3ec07ad0
	15	[53]	MOVE     	0 1
	16	[54]	LOADNIL  	6 6
	17	[58]	CLOSURE  	6 2	; 0x7f9c3ec07f90
	18	[58]	MOVE     	0 1
	19	[59]	LOADNIL  	7 7
	20	[63]	CLOSURE  	7 3	; 0x7f9c3ec084d0
	21	[63]	MOVE     	0 1
	22	[64]	LOADNIL  	8 8
	23	[71]	CLOSURE  	8 4	; 0x7f9c3ec07210
	24	[71]	MOVE     	0 2
	25	[72]	LOADNIL  	9 9
	26	[76]	CLOSURE  	9 5	; 0x7f9c3ec08d10
	27	[76]	MOVE     	0 2
	28	[77]	LOADNIL  	10 10
	29	[81]	CLOSURE  	10 6	; 0x7f9c3ec090f0
	30	[81]	MOVE     	0 2
	31	[82]	GETUPVAL 	11 1	; Cmt
	32	[82]	LOADK    	12 -3	; ""
	33	[82]	MOVE     	13 9
	34	[82]	CALL     	11 3 2
	35	[83]	GETUPVAL 	12 1	; Cmt
	36	[83]	LOADK    	13 -3	; ""
	37	[83]	MOVE     	14 10
	38	[83]	CALL     	12 3 2
	39	[84]	NEWTABLE 	13 0 0
	40	[85]	LOADNIL  	14 14
	41	[89]	CLOSURE  	14 7	; 0x7f9c3ec08450
	42	[89]	MOVE     	0 13
	43	[89]	GETUPVAL 	0 2	; Space
	44	[89]	GETUPVAL 	0 3	; AlphaNum
	45	[90]	LOADNIL  	15 15
	46	[98]	CLOSURE  	15 8	; 0x7f9c3ec097f0
	47	[98]	GETUPVAL 	0 2	; Space
	48	[98]	GETUPVAL 	0 4	; C
	49	[98]	MOVE     	0 13
	50	[98]	GETUPVAL 	0 3	; AlphaNum
	51	[99]	GETUPVAL 	16 1	; Cmt
	52	[99]	GETUPVAL 	17 5	; SpaceName
	53	[104]	CLOSURE  	18 9	; 0x7f9c3ec09c30
	54	[104]	MOVE     	0 13
	55	[99]	CALL     	16 3 2
	56	[104]	GETUPVAL 	17 6	; trim
	57	[104]	DIV      	16 16 17
	58	[105]	GETUPVAL 	17 2	; Space
	59	[105]	MUL      	17 17 -4	; - "@"
	60	[105]	GETUPVAL 	18 7	; _Name
	61	[105]	GETUPVAL 	19 8	; mark
	62	[105]	LOADK    	20 -5	; "self_class"
	63	[105]	CALL     	19 2 2
	64	[105]	DIV      	18 18 19
	65	[105]	GETUPVAL 	19 9	; Cc
	66	[105]	LOADK    	20 -6	; "self.__class"
	67	[105]	CALL     	19 2 2
	68	[105]	ADD      	18 18 19
	69	[105]	MUL      	18 -4 18	; "@" -
	70	[105]	GETUPVAL 	19 7	; _Name
	71	[105]	GETUPVAL 	20 8	; mark
	72	[105]	LOADK    	21 -7	; "self"
	73	[105]	CALL     	20 2 2
	74	[105]	DIV      	19 19 20
	75	[105]	ADD      	18 18 19
	76	[105]	GETUPVAL 	19 9	; Cc
	77	[105]	LOADK    	20 -7	; "self"
	78	[105]	CALL     	19 2 2
	79	[105]	ADD      	18 18 19
	80	[105]	MUL      	17 17 18
	81	[106]	GETUPVAL 	18 2	; Space
	82	[106]	GETUPVAL 	19 7	; _Name
	83	[106]	MUL      	18 18 19
	84	[106]	GETUPVAL 	19 8	; mark
	85	[106]	LOADK    	20 -8	; "key_literal"
	86	[106]	CALL     	19 2 2
	87	[106]	DIV      	18 18 19
	88	[106]	ADD      	18 17 18
	89	[107]	GETUPVAL 	19 2	; Space
	90	[107]	GETUPVAL 	20 10	; P
	91	[107]	LOADK    	21 -9	; "..."
	92	[107]	CALL     	20 2 2
	93	[107]	MUL      	19 19 20
	94	[107]	GETUPVAL 	20 6	; trim
	95	[107]	DIV      	19 19 20
	96	[108]	GETUPVAL 	20 10	; P
	97	[108]	NEWTABLE 	21 1 36
	98	[109]	TESTSET  	22 0 1
	99	[109]	JMP      	1	; to 101
	100	[109]	GETGLOBAL	22 -10	; File
	101	[110]	GETUPVAL 	23 11	; Shebang
	102	[110]	POW      	23 23 -11	; - -1
	103	[110]	GETGLOBAL	24 -12	; Block
	104	[110]	GETUPVAL 	25 12	; Ct
	105	[110]	LOADK    	26 -3	; ""
	106	[110]	CALL     	25 2 2
	107	[110]	ADD      	24 24 25
	108	[110]	MUL      	23 23 24
	109	[110]	SETTABLE 	21 -10 23	; "File" -
	110	[111]	GETUPVAL 	23 12	; Ct
	111	[111]	GETGLOBAL	24 -13	; Line
	112	[111]	GETUPVAL 	25 13	; Break
	113	[111]	POW      	25 25 -14	; - 1
	114	[111]	GETGLOBAL	26 -13	; Line
	115	[111]	MUL      	25 25 26
	116	[111]	POW      	25 25 -1	; - 0
	117	[111]	MUL      	24 24 25
	118	[111]	CALL     	23 2 2
	119	[111]	SETTABLE 	21 -12 23	; "Block" -
	120	[112]	GETUPVAL 	23 1	; Cmt
	121	[112]	GETUPVAL 	24 14	; Indent
	122	[112]	MOVE     	25 4
	123	[112]	CALL     	23 3 2
	124	[112]	SETTABLE 	21 -15 23	; "CheckIndent" -
	125	[113]	GETGLOBAL	23 -15	; CheckIndent
	126	[113]	GETGLOBAL	24 -16	; Statement
	127	[113]	MUL      	23 23 24
	128	[113]	GETUPVAL 	24 2	; Space
	129	[113]	GETUPVAL 	25 15	; L
	130	[113]	GETUPVAL 	26 16	; Stop
	131	[113]	CALL     	25 2 2
	132	[113]	MUL      	24 24 25
	133	[113]	ADD      	23 23 24
	134	[113]	SETTABLE 	21 -13 23	; "Line" -
	135	[114]	GETUPVAL 	23 17	; pos
	136	[114]	GETGLOBAL	24 -17	; Import
	137	[114]	GETGLOBAL	25 -18	; While
	138	[114]	ADD      	24 24 25
	139	[114]	GETGLOBAL	25 -19	; With
	140	[114]	ADD      	24 24 25
	141	[114]	GETGLOBAL	25 -20	; For
	142	[114]	ADD      	24 24 25
	143	[114]	GETGLOBAL	25 -21	; ForEach
	144	[114]	ADD      	24 24 25
	145	[114]	GETGLOBAL	25 -22	; Switch
	146	[114]	ADD      	24 24 25
	147	[114]	GETGLOBAL	25 -23	; Return
	148	[114]	ADD      	24 24 25
	149	[114]	GETGLOBAL	25 -24	; Local
	150	[114]	ADD      	24 24 25
	151	[114]	GETGLOBAL	25 -25	; Export
	152	[114]	ADD      	24 24 25
	153	[114]	GETGLOBAL	25 -26	; BreakLoop
	154	[114]	ADD      	24 24 25
	155	[114]	GETUPVAL 	25 12	; Ct
	156	[114]	GETGLOBAL	26 -27	; ExpList
	157	[114]	CALL     	25 2 2
	158	[114]	GETGLOBAL	26 -28	; Update
	159	[114]	GETGLOBAL	27 -29	; Assign
	160	[114]	ADD      	26 26 27
	161	[114]	POW      	26 26 -11	; - -1
	162	[114]	MUL      	25 25 26
	163	[114]	GETUPVAL 	26 18	; format_assign
	164	[114]	DIV      	25 25 26
	165	[114]	ADD      	24 24 25
	166	[114]	CALL     	23 2 2
	167	[114]	GETUPVAL 	24 2	; Space
	168	[114]	MUL      	23 23 24
	169	[114]	MOVE     	24 14
	170	[114]	LOADK    	25 -30	; "if"
	171	[114]	CALL     	24 2 2
	172	[114]	GETGLOBAL	25 -31	; Exp
	173	[114]	MUL      	24 24 25
	174	[114]	MOVE     	25 14
	175	[114]	LOADK    	26 -32	; "else"
	176	[114]	CALL     	25 2 2
	177	[114]	GETGLOBAL	26 -31	; Exp
	178	[114]	MUL      	25 25 26
	179	[114]	POW      	25 25 -11	; - -1
	180	[114]	MUL      	24 24 25
	181	[114]	GETUPVAL 	25 2	; Space
	182	[114]	MUL      	24 24 25
	183	[114]	GETUPVAL 	25 8	; mark
	184	[114]	LOADK    	26 -30	; "if"
	185	[114]	CALL     	25 2 2
	186	[114]	DIV      	24 24 25
	187	[114]	MOVE     	25 14
	188	[114]	LOADK    	26 -33	; "unless"
	189	[114]	CALL     	25 2 2
	190	[114]	GETGLOBAL	26 -31	; Exp
	191	[114]	MUL      	25 25 26
	192	[114]	GETUPVAL 	26 8	; mark
	193	[114]	LOADK    	27 -33	; "unless"
	194	[114]	CALL     	26 2 2
	195	[114]	DIV      	25 25 26
	196	[114]	ADD      	24 24 25
	197	[114]	GETGLOBAL	25 -34	; CompInner
	198	[114]	GETUPVAL 	26 8	; mark
	199	[114]	LOADK    	27 -35	; "comprehension"
	200	[114]	CALL     	26 2 2
	201	[114]	DIV      	25 25 26
	202	[114]	ADD      	24 24 25
	203	[114]	GETUPVAL 	25 2	; Space
	204	[114]	MUL      	24 24 25
	205	[114]	POW      	24 24 -11	; - -1
	206	[114]	MUL      	23 23 24
	207	[114]	GETUPVAL 	24 19	; wrap_decorator
	208	[114]	DIV      	23 23 24
	209	[114]	SETTABLE 	21 -16 23	; "Statement" -
	210	[115]	GETUPVAL 	23 2	; Space
	211	[115]	POW      	23 23 -11	; - -1
	212	[115]	GETUPVAL 	24 13	; Break
	213	[115]	MUL      	23 23 24
	214	[115]	GETUPVAL 	24 20	; EmptyLine
	215	[115]	POW      	24 24 -1	; - 0
	216	[115]	MUL      	23 23 24
	217	[115]	GETGLOBAL	24 -37	; InBlock
	218	[115]	MUL      	23 23 24
	219	[115]	GETUPVAL 	24 12	; Ct
	220	[115]	GETGLOBAL	25 -16	; Statement
	221	[115]	CALL     	24 2 2
	222	[115]	ADD      	23 23 24
	223	[115]	SETTABLE 	21 -36 23	; "Body" -
	224	[116]	GETUPVAL 	23 15	; L
	225	[116]	GETUPVAL 	24 1	; Cmt
	226	[116]	GETUPVAL 	25 14	; Indent
	227	[116]	MOVE     	26 5
	228	[116]	CALL     	24 3 0
	229	[116]	CALL     	23 0 2
	230	[116]	SETTABLE 	21 -38 23	; "Advance" -
	231	[117]	GETUPVAL 	23 1	; Cmt
	232	[117]	GETUPVAL 	24 14	; Indent
	233	[117]	MOVE     	25 6
	234	[117]	CALL     	23 3 2
	235	[117]	SETTABLE 	21 -39 23	; "PushIndent" -
	236	[118]	GETUPVAL 	23 1	; Cmt
	237	[118]	GETUPVAL 	24 9	; Cc
	238	[118]	LOADK    	25 -11	; -1
	239	[118]	CALL     	24 2 2
	240	[118]	MOVE     	25 6
	241	[118]	CALL     	23 3 2
	242	[118]	SETTABLE 	21 -40 23	; "PreventIndent" -
	243	[119]	GETUPVAL 	23 1	; Cmt
	244	[119]	LOADK    	24 -3	; ""
	245	[119]	MOVE     	25 7
	246	[119]	CALL     	23 3 2
	247	[119]	SETTABLE 	21 -41 23	; "PopIndent" -
	248	[120]	GETGLOBAL	23 -38	; Advance
	249	[120]	GETGLOBAL	24 -12	; Block
	250	[120]	MUL      	23 23 24
	251	[120]	GETGLOBAL	24 -41	; PopIndent
	252	[120]	MUL      	23 23 24
	253	[120]	SETTABLE 	21 -37 23	; "InBlock" -
	254	[121]	MOVE     	23 14
	255	[121]	LOADK    	24 -42	; "local"
	256	[121]	CALL     	23 2 2
	257	[121]	MOVE     	24 15
	258	[121]	LOADK    	25 -43	; "*"
	259	[121]	CALL     	24 2 2
	260	[121]	MOVE     	25 15
	261	[121]	LOADK    	26 -44	; "^"
	262	[121]	CALL     	25 2 2
	263	[121]	ADD      	24 24 25
	264	[121]	GETUPVAL 	25 8	; mark
	265	[121]	LOADK    	26 -45	; "declare_glob"
	266	[121]	CALL     	25 2 2
	267	[121]	DIV      	24 24 25
	268	[121]	GETUPVAL 	25 12	; Ct
	269	[121]	GETGLOBAL	26 -46	; NameList
	270	[121]	CALL     	25 2 2
	271	[121]	GETUPVAL 	26 8	; mark
	272	[121]	LOADK    	27 -47	; "declare_with_shadows"
	273	[121]	CALL     	26 2 2
	274	[121]	DIV      	25 25 26
	275	[121]	ADD      	24 24 25
	276	[121]	MUL      	23 23 24
	277	[121]	SETTABLE 	21 -24 23	; "Local" -
	278	[122]	MOVE     	23 14
	279	[122]	LOADK    	24 -48	; "import"
	280	[122]	CALL     	23 2 2
	281	[122]	GETUPVAL 	24 12	; Ct
	282	[122]	GETGLOBAL	25 -49	; ImportNameList
	283	[122]	CALL     	24 2 2
	284	[122]	MUL      	23 23 24
	285	[122]	GETUPVAL 	24 21	; SpaceBreak
	286	[122]	POW      	24 24 -1	; - 0
	287	[122]	MUL      	23 23 24
	288	[122]	MOVE     	24 14
	289	[122]	LOADK    	25 -50	; "from"
	290	[122]	CALL     	24 2 2
	291	[122]	MUL      	23 23 24
	292	[122]	GETGLOBAL	24 -31	; Exp
	293	[122]	MUL      	23 23 24
	294	[122]	GETUPVAL 	24 8	; mark
	295	[122]	LOADK    	25 -48	; "import"
	296	[122]	CALL     	24 2 2
	297	[122]	DIV      	23 23 24
	298	[122]	SETTABLE 	21 -17 23	; "Import" -
	299	[123]	GETUPVAL 	23 22	; sym
	300	[123]	LOADK    	24 -52	; "\\"
	301	[123]	CALL     	23 2 2
	302	[123]	GETUPVAL 	24 12	; Ct
	303	[123]	GETUPVAL 	25 9	; Cc
	304	[123]	LOADK    	26 -53	; "colon"
	305	[123]	CALL     	25 2 2
	306	[123]	MUL      	25 25 16
	307	[123]	CALL     	24 2 2
	308	[123]	MUL      	23 23 24
	309	[123]	ADD      	23 23 16
	310	[123]	SETTABLE 	21 -51 23	; "ImportName" -
	311	[124]	GETUPVAL 	23 21	; SpaceBreak
	312	[124]	POW      	23 23 -1	; - 0
	313	[124]	GETGLOBAL	24 -51	; ImportName
	314	[124]	MUL      	23 23 24
	315	[124]	GETUPVAL 	24 21	; SpaceBreak
	316	[124]	POW      	24 24 -14	; - 1
	317	[124]	GETUPVAL 	25 22	; sym
	318	[124]	LOADK    	26 -54	; ","
	319	[124]	CALL     	25 2 2
	320	[124]	GETUPVAL 	26 21	; SpaceBreak
	321	[124]	POW      	26 26 -1	; - 0
	322	[124]	MUL      	25 25 26
	323	[124]	ADD      	24 24 25
	324	[124]	GETGLOBAL	25 -51	; ImportName
	325	[124]	MUL      	24 24 25
	326	[124]	POW      	24 24 -1	; - 0
	327	[124]	MUL      	23 23 24
	328	[124]	SETTABLE 	21 -49 23	; "ImportNameList" -
	329	[125]	GETUPVAL 	23 12	; Ct
	330	[125]	MOVE     	24 14
	331	[125]	LOADK    	25 -55	; "break"
	332	[125]	CALL     	24 2 2
	333	[125]	GETUPVAL 	25 6	; trim
	334	[125]	DIV      	24 24 25
	335	[125]	CALL     	23 2 2
	336	[125]	GETUPVAL 	24 12	; Ct
	337	[125]	MOVE     	25 14
	338	[125]	LOADK    	26 -56	; "continue"
	339	[125]	CALL     	25 2 2
	340	[125]	GETUPVAL 	26 6	; trim
	341	[125]	DIV      	25 25 26
	342	[125]	CALL     	24 2 2
	343	[125]	ADD      	23 23 24
	344	[125]	SETTABLE 	21 -26 23	; "BreakLoop" -
	345	[126]	MOVE     	23 14
	346	[126]	LOADK    	24 -57	; "return"
	347	[126]	CALL     	23 2 2
	348	[126]	GETGLOBAL	24 -58	; ExpListLow
	349	[126]	GETUPVAL 	25 8	; mark
	350	[126]	LOADK    	26 -59	; "explist"
	351	[126]	CALL     	25 2 2
	352	[126]	DIV      	24 24 25
	353	[126]	GETUPVAL 	25 4	; C
	354	[126]	LOADK    	26 -3	; ""
	355	[126]	CALL     	25 2 2
	356	[126]	ADD      	24 24 25
	357	[126]	MUL      	23 23 24
	358	[126]	GETUPVAL 	24 8	; mark
	359	[126]	LOADK    	25 -57	; "return"
	360	[126]	CALL     	24 2 2
	361	[126]	DIV      	23 23 24
	362	[126]	SETTABLE 	21 -23 23	; "Return" -
	363	[127]	GETUPVAL 	23 12	; Ct
	364	[127]	GETGLOBAL	24 -27	; ExpList
	365	[127]	CALL     	23 2 2
	366	[127]	GETGLOBAL	24 -29	; Assign
	367	[127]	POW      	24 24 -11	; - -1
	368	[127]	MUL      	23 23 24
	369	[127]	GETUPVAL 	24 18	; format_assign
	370	[127]	DIV      	23 23 24
	371	[127]	SETTABLE 	21 -60 23	; "WithExp" -
	372	[128]	MOVE     	23 14
	373	[128]	LOADK    	24 -61	; "with"
	374	[128]	CALL     	23 2 2
	375	[128]	MUL      	23 23 11
	376	[128]	GETUPVAL 	24 23	; ensure
	377	[128]	GETGLOBAL	25 -60	; WithExp
	378	[128]	MOVE     	26 12
	379	[128]	CALL     	24 3 2
	380	[128]	MUL      	23 23 24
	381	[128]	MOVE     	24 14
	382	[128]	LOADK    	25 -62	; "do"
	383	[128]	CALL     	24 2 2
	384	[128]	POW      	24 24 -11	; - -1
	385	[128]	MUL      	23 23 24
	386	[128]	GETGLOBAL	24 -36	; Body
	387	[128]	MUL      	23 23 24
	388	[128]	GETUPVAL 	24 8	; mark
	389	[128]	LOADK    	25 -61	; "with"
	390	[128]	CALL     	24 2 2
	391	[128]	DIV      	23 23 24
	392	[128]	SETTABLE 	21 -19 23	; "With" -
	393	[129]	MOVE     	23 14
	394	[129]	LOADK    	24 -63	; "switch"
	395	[129]	CALL     	23 2 2
	396	[129]	MUL      	23 23 11
	397	[129]	GETUPVAL 	24 23	; ensure
	398	[129]	GETGLOBAL	25 -31	; Exp
	399	[129]	MOVE     	26 12
	400	[129]	CALL     	24 3 2
	401	[129]	MUL      	23 23 24
	402	[129]	MOVE     	24 14
	403	[129]	LOADK    	25 -62	; "do"
	404	[129]	CALL     	24 2 2
	405	[129]	POW      	24 24 -11	; - -1
	406	[129]	MUL      	23 23 24
	407	[129]	GETUPVAL 	24 2	; Space
	408	[129]	POW      	24 24 -11	; - -1
	409	[129]	MUL      	23 23 24
	410	[129]	GETUPVAL 	24 13	; Break
	411	[129]	MUL      	23 23 24
	412	[129]	GETGLOBAL	24 -64	; SwitchBlock
	413	[129]	MUL      	23 23 24
	414	[129]	GETUPVAL 	24 8	; mark
	415	[129]	LOADK    	25 -63	; "switch"
	416	[129]	CALL     	24 2 2
	417	[129]	DIV      	23 23 24
	418	[129]	SETTABLE 	21 -22 23	; "Switch" -
	419	[130]	GETUPVAL 	23 20	; EmptyLine
	420	[130]	POW      	23 23 -1	; - 0
	421	[130]	GETGLOBAL	24 -38	; Advance
	422	[130]	MUL      	23 23 24
	423	[130]	GETUPVAL 	24 12	; Ct
	424	[130]	GETGLOBAL	25 -65	; SwitchCase
	425	[130]	GETUPVAL 	26 13	; Break
	426	[130]	POW      	26 26 -14	; - 1
	427	[130]	GETGLOBAL	27 -65	; SwitchCase
	428	[130]	MUL      	26 26 27
	429	[130]	POW      	26 26 -1	; - 0
	430	[130]	MUL      	25 25 26
	431	[130]	GETUPVAL 	26 13	; Break
	432	[130]	POW      	26 26 -14	; - 1
	433	[130]	GETGLOBAL	27 -66	; SwitchElse
	434	[130]	MUL      	26 26 27
	435	[130]	POW      	26 26 -11	; - -1
	436	[130]	MUL      	25 25 26
	437	[130]	CALL     	24 2 2
	438	[130]	MUL      	23 23 24
	439	[130]	GETGLOBAL	24 -41	; PopIndent
	440	[130]	MUL      	23 23 24
	441	[130]	SETTABLE 	21 -64 23	; "SwitchBlock" -
	442	[131]	MOVE     	23 14
	443	[131]	LOADK    	24 -67	; "when"
	444	[131]	CALL     	23 2 2
	445	[131]	GETUPVAL 	24 12	; Ct
	446	[131]	GETGLOBAL	25 -27	; ExpList
	447	[131]	CALL     	24 2 2
	448	[131]	MUL      	23 23 24
	449	[131]	MOVE     	24 14
	450	[131]	LOADK    	25 -68	; "then"
	451	[131]	CALL     	24 2 2
	452	[131]	POW      	24 24 -11	; - -1
	453	[131]	MUL      	23 23 24
	454	[131]	GETGLOBAL	24 -36	; Body
	455	[131]	MUL      	23 23 24
	456	[131]	GETUPVAL 	24 8	; mark
	457	[131]	LOADK    	25 -69	; "case"
	458	[131]	CALL     	24 2 2
	459	[131]	DIV      	23 23 24
	460	[131]	SETTABLE 	21 -65 23	; "SwitchCase" -
	461	[132]	MOVE     	23 14
	462	[132]	LOADK    	24 -32	; "else"
	463	[132]	CALL     	23 2 2
	464	[132]	GETGLOBAL	24 -36	; Body
	465	[132]	MUL      	23 23 24
	466	[132]	GETUPVAL 	24 8	; mark
	467	[132]	LOADK    	25 -32	; "else"
	468	[132]	CALL     	24 2 2
	469	[132]	DIV      	23 23 24
	470	[132]	SETTABLE 	21 -66 23	; "SwitchElse" -
	471	[133]	GETGLOBAL	23 -31	; Exp
	472	[133]	GETGLOBAL	24 -29	; Assign
	473	[133]	POW      	24 24 -11	; - -1
	474	[133]	MUL      	23 23 24
	475	[133]	GETUPVAL 	24 24	; format_single_assign
	476	[133]	DIV      	23 23 24
	477	[133]	SETTABLE 	21 -70 23	; "IfCond" -
	478	[134]	GETUPVAL 	23 13	; Break
	479	[134]	GETUPVAL 	24 20	; EmptyLine
	480	[134]	POW      	24 24 -1	; - 0
	481	[134]	MUL      	23 23 24
	482	[134]	GETGLOBAL	24 -15	; CheckIndent
	483	[134]	MUL      	23 23 24
	484	[134]	POW      	23 23 -11	; - -1
	485	[134]	MOVE     	24 14
	486	[134]	LOADK    	25 -32	; "else"
	487	[134]	CALL     	24 2 2
	488	[134]	MUL      	23 23 24
	489	[134]	GETGLOBAL	24 -36	; Body
	490	[134]	MUL      	23 23 24
	491	[134]	GETUPVAL 	24 8	; mark
	492	[134]	LOADK    	25 -32	; "else"
	493	[134]	CALL     	24 2 2
	494	[134]	DIV      	23 23 24
	495	[134]	SETTABLE 	21 -71 23	; "IfElse" -
	496	[135]	GETUPVAL 	23 13	; Break
	497	[135]	GETUPVAL 	24 20	; EmptyLine
	498	[135]	POW      	24 24 -1	; - 0
	499	[135]	MUL      	23 23 24
	500	[135]	GETGLOBAL	24 -15	; CheckIndent
	501	[135]	MUL      	23 23 24
	502	[135]	POW      	23 23 -11	; - -1
	503	[135]	MOVE     	24 14
	504	[135]	LOADK    	25 -73	; "elseif"
	505	[135]	CALL     	24 2 2
	506	[135]	MUL      	23 23 24
	507	[135]	GETUPVAL 	24 17	; pos
	508	[135]	GETGLOBAL	25 -70	; IfCond
	509	[135]	CALL     	24 2 2
	510	[135]	MUL      	23 23 24
	511	[135]	MOVE     	24 14
	512	[135]	LOADK    	25 -68	; "then"
	513	[135]	CALL     	24 2 2
	514	[135]	POW      	24 24 -11	; - -1
	515	[135]	MUL      	23 23 24
	516	[135]	GETGLOBAL	24 -36	; Body
	517	[135]	MUL      	23 23 24
	518	[135]	GETUPVAL 	24 8	; mark
	519	[135]	LOADK    	25 -73	; "elseif"
	520	[135]	CALL     	24 2 2
	521	[135]	DIV      	23 23 24
	522	[135]	SETTABLE 	21 -72 23	; "IfElseIf" -
	523	[136]	MOVE     	23 14
	524	[136]	LOADK    	24 -30	; "if"
	525	[136]	CALL     	23 2 2
	526	[136]	GETGLOBAL	24 -70	; IfCond
	527	[136]	MUL      	23 23 24
	528	[136]	MOVE     	24 14
	529	[136]	LOADK    	25 -68	; "then"
	530	[136]	CALL     	24 2 2
	531	[136]	POW      	24 24 -11	; - -1
	532	[136]	MUL      	23 23 24
	533	[136]	GETGLOBAL	24 -36	; Body
	534	[136]	MUL      	23 23 24
	535	[136]	GETGLOBAL	24 -72	; IfElseIf
	536	[136]	POW      	24 24 -1	; - 0
	537	[136]	MUL      	23 23 24
	538	[136]	GETGLOBAL	24 -71	; IfElse
	539	[136]	POW      	24 24 -11	; - -1
	540	[136]	MUL      	23 23 24
	541	[136]	GETUPVAL 	24 8	; mark
	542	[136]	LOADK    	25 -30	; "if"
	543	[136]	CALL     	24 2 2
	544	[136]	DIV      	23 23 24
	545	[136]	SETTABLE 	21 -74 23	; "If" -
	546	[137]	MOVE     	23 14
	547	[137]	LOADK    	24 -33	; "unless"
	548	[137]	CALL     	23 2 2
	549	[137]	GETGLOBAL	24 -70	; IfCond
	550	[137]	MUL      	23 23 24
	551	[137]	MOVE     	24 14
	552	[137]	LOADK    	25 -68	; "then"
	553	[137]	CALL     	24 2 2
	554	[137]	POW      	24 24 -11	; - -1
	555	[137]	MUL      	23 23 24
	556	[137]	GETGLOBAL	24 -36	; Body
	557	[137]	MUL      	23 23 24
	558	[137]	GETGLOBAL	24 -72	; IfElseIf
	559	[137]	POW      	24 24 -1	; - 0
	560	[137]	MUL      	23 23 24
	561	[137]	GETGLOBAL	24 -71	; IfElse
	562	[137]	POW      	24 24 -11	; - -1
	563	[137]	MUL      	23 23 24
	564	[137]	GETUPVAL 	24 8	; mark
	565	[137]	LOADK    	25 -33	; "unless"
	566	[137]	CALL     	24 2 2
	567	[137]	DIV      	23 23 24
	568	[137]	SETTABLE 	21 -75 23	; "Unless" -
	569	[138]	MOVE     	23 14
	570	[138]	LOADK    	24 -76	; "while"
	571	[138]	CALL     	23 2 2
	572	[138]	MUL      	23 23 11
	573	[138]	GETUPVAL 	24 23	; ensure
	574	[138]	GETGLOBAL	25 -31	; Exp
	575	[138]	MOVE     	26 12
	576	[138]	CALL     	24 3 2
	577	[138]	MUL      	23 23 24
	578	[138]	MOVE     	24 14
	579	[138]	LOADK    	25 -62	; "do"
	580	[138]	CALL     	24 2 2
	581	[138]	POW      	24 24 -11	; - -1
	582	[138]	MUL      	23 23 24
	583	[138]	GETGLOBAL	24 -36	; Body
	584	[138]	MUL      	23 23 24
	585	[138]	GETUPVAL 	24 8	; mark
	586	[138]	LOADK    	25 -76	; "while"
	587	[138]	CALL     	24 2 2
	588	[138]	DIV      	23 23 24
	589	[138]	SETTABLE 	21 -18 23	; "While" -
	590	[139]	MOVE     	23 14
	591	[139]	LOADK    	24 -77	; "for"
	592	[139]	CALL     	23 2 2
	593	[139]	MUL      	23 23 11
	594	[139]	GETUPVAL 	24 23	; ensure
	595	[139]	GETUPVAL 	25 22	; sym
	596	[139]	LOADK    	26 -78	; "="
	597	[139]	CALL     	25 2 2
	598	[139]	MUL      	25 16 25
	599	[139]	GETUPVAL 	26 12	; Ct
	600	[139]	GETGLOBAL	27 -31	; Exp
	601	[139]	GETUPVAL 	28 22	; sym
	602	[139]	LOADK    	29 -54	; ","
	603	[139]	CALL     	28 2 2
	604	[139]	MUL      	27 27 28
	605	[139]	GETGLOBAL	28 -31	; Exp
	606	[139]	MUL      	27 27 28
	607	[139]	GETUPVAL 	28 22	; sym
	608	[139]	LOADK    	29 -54	; ","
	609	[139]	CALL     	28 2 2
	610	[139]	GETGLOBAL	29 -31	; Exp
	611	[139]	MUL      	28 28 29
	612	[139]	POW      	28 28 -11	; - -1
	613	[139]	MUL      	27 27 28
	614	[139]	CALL     	26 2 2
	615	[139]	MUL      	25 25 26
	616	[139]	MOVE     	26 12
	617	[139]	CALL     	24 3 2
	618	[139]	MUL      	23 23 24
	619	[139]	MOVE     	24 14
	620	[139]	LOADK    	25 -62	; "do"
	621	[139]	CALL     	24 2 2
	622	[139]	POW      	24 24 -11	; - -1
	623	[139]	MUL      	23 23 24
	624	[139]	GETGLOBAL	24 -36	; Body
	625	[139]	MUL      	23 23 24
	626	[139]	GETUPVAL 	24 8	; mark
	627	[139]	LOADK    	25 -77	; "for"
	628	[139]	CALL     	24 2 2
	629	[139]	DIV      	23 23 24
	630	[139]	SETTABLE 	21 -20 23	; "For" -
	631	[140]	MOVE     	23 14
	632	[140]	LOADK    	24 -77	; "for"
	633	[140]	CALL     	23 2 2
	634	[140]	GETUPVAL 	24 12	; Ct
	635	[140]	GETGLOBAL	25 -79	; AssignableNameList
	636	[140]	CALL     	24 2 2
	637	[140]	MUL      	23 23 24
	638	[140]	MOVE     	24 14
	639	[140]	LOADK    	25 -80	; "in"
	640	[140]	CALL     	24 2 2
	641	[140]	MUL      	23 23 24
	642	[140]	MUL      	23 23 11
	643	[140]	GETUPVAL 	24 23	; ensure
	644	[140]	GETUPVAL 	25 12	; Ct
	645	[140]	GETUPVAL 	26 22	; sym
	646	[140]	LOADK    	27 -43	; "*"
	647	[140]	CALL     	26 2 2
	648	[140]	GETGLOBAL	27 -31	; Exp
	649	[140]	MUL      	26 26 27
	650	[140]	GETUPVAL 	27 8	; mark
	651	[140]	LOADK    	28 -81	; "unpack"
	652	[140]	CALL     	27 2 2
	653	[140]	DIV      	26 26 27
	654	[140]	GETGLOBAL	27 -27	; ExpList
	655	[140]	ADD      	26 26 27
	656	[140]	CALL     	25 2 2
	657	[140]	MOVE     	26 12
	658	[140]	CALL     	24 3 2
	659	[140]	MUL      	23 23 24
	660	[140]	MOVE     	24 14
	661	[140]	LOADK    	25 -62	; "do"
	662	[140]	CALL     	24 2 2
	663	[140]	POW      	24 24 -11	; - -1
	664	[140]	MUL      	23 23 24
	665	[140]	GETGLOBAL	24 -36	; Body
	666	[140]	MUL      	23 23 24
	667	[140]	GETUPVAL 	24 8	; mark
	668	[140]	LOADK    	25 -82	; "foreach"
	669	[140]	CALL     	24 2 2
	670	[140]	DIV      	23 23 24
	671	[140]	SETTABLE 	21 -21 23	; "ForEach" -
	672	[141]	MOVE     	23 14
	673	[141]	LOADK    	24 -62	; "do"
	674	[141]	CALL     	23 2 2
	675	[141]	GETGLOBAL	24 -36	; Body
	676	[141]	MUL      	23 23 24
	677	[141]	GETUPVAL 	24 8	; mark
	678	[141]	LOADK    	25 -62	; "do"
	679	[141]	CALL     	24 2 2
	680	[141]	DIV      	23 23 24
	681	[141]	SETTABLE 	21 -83 23	; "Do" -
	682	[142]	GETUPVAL 	23 22	; sym
	683	[142]	LOADK    	24 -85	; "["
	684	[142]	CALL     	23 2 2
	685	[142]	GETGLOBAL	24 -31	; Exp
	686	[142]	MUL      	23 23 24
	687	[142]	GETGLOBAL	24 -34	; CompInner
	688	[142]	MUL      	23 23 24
	689	[142]	GETUPVAL 	24 22	; sym
	690	[142]	LOADK    	25 -86	; "]"
	691	[142]	CALL     	24 2 2
	692	[142]	MUL      	23 23 24
	693	[142]	GETUPVAL 	24 8	; mark
	694	[142]	LOADK    	25 -35	; "comprehension"
	695	[142]	CALL     	24 2 2
	696	[142]	DIV      	23 23 24
	697	[142]	SETTABLE 	21 -84 23	; "Comprehension" -
	698	[143]	GETUPVAL 	23 22	; sym
	699	[143]	LOADK    	24 -88	; "{"
	700	[143]	CALL     	23 2 2
	701	[143]	GETUPVAL 	24 12	; Ct
	702	[143]	GETGLOBAL	25 -31	; Exp
	703	[143]	GETUPVAL 	26 22	; sym
	704	[143]	LOADK    	27 -54	; ","
	705	[143]	CALL     	26 2 2
	706	[143]	GETGLOBAL	27 -31	; Exp
	707	[143]	MUL      	26 26 27
	708	[143]	POW      	26 26 -11	; - -1
	709	[143]	MUL      	25 25 26
	710	[143]	CALL     	24 2 2
	711	[143]	MUL      	23 23 24
	712	[143]	GETGLOBAL	24 -34	; CompInner
	713	[143]	MUL      	23 23 24
	714	[143]	GETUPVAL 	24 22	; sym
	715	[143]	LOADK    	25 -89	; "}"
	716	[143]	CALL     	24 2 2
	717	[143]	MUL      	23 23 24
	718	[143]	GETUPVAL 	24 8	; mark
	719	[143]	LOADK    	25 -90	; "tblcomprehension"
	720	[143]	CALL     	24 2 2
	721	[143]	DIV      	23 23 24
	722	[143]	SETTABLE 	21 -87 23	; "TblComprehension" -
	723	[144]	GETUPVAL 	23 12	; Ct
	724	[144]	GETGLOBAL	24 -91	; CompForEach
	725	[144]	GETGLOBAL	25 -92	; CompFor
	726	[144]	ADD      	24 24 25
	727	[144]	GETGLOBAL	25 -93	; CompClause
	728	[144]	POW      	25 25 -1	; - 0
	729	[144]	MUL      	24 24 25
	730	[144]	CALL     	23 2 2
	731	[144]	SETTABLE 	21 -34 23	; "CompInner" -
	732	[145]	MOVE     	23 14
	733	[145]	LOADK    	24 -77	; "for"
	734	[145]	CALL     	23 2 2
	735	[145]	GETUPVAL 	24 12	; Ct
	736	[145]	GETGLOBAL	25 -79	; AssignableNameList
	737	[145]	CALL     	24 2 2
	738	[145]	MUL      	23 23 24
	739	[145]	MOVE     	24 14
	740	[145]	LOADK    	25 -80	; "in"
	741	[145]	CALL     	24 2 2
	742	[145]	MUL      	23 23 24
	743	[145]	GETUPVAL 	24 22	; sym
	744	[145]	LOADK    	25 -43	; "*"
	745	[145]	CALL     	24 2 2
	746	[145]	GETGLOBAL	25 -31	; Exp
	747	[145]	MUL      	24 24 25
	748	[145]	GETUPVAL 	25 8	; mark
	749	[145]	LOADK    	26 -81	; "unpack"
	750	[145]	CALL     	25 2 2
	751	[145]	DIV      	24 24 25
	752	[145]	GETGLOBAL	25 -31	; Exp
	753	[145]	ADD      	24 24 25
	754	[145]	MUL      	23 23 24
	755	[145]	GETUPVAL 	24 8	; mark
	756	[145]	LOADK    	25 -82	; "foreach"
	757	[145]	CALL     	24 2 2
	758	[145]	DIV      	23 23 24
	759	[145]	SETTABLE 	21 -91 23	; "CompForEach" -
	760	[146]	MOVE     	23 14
	761	[146]	MUL      	24 -77 16	; "for" -
	762	[146]	GETUPVAL 	25 22	; sym
	763	[146]	LOADK    	26 -78	; "="
	764	[146]	CALL     	25 2 2
	765	[146]	MUL      	24 24 25
	766	[146]	GETUPVAL 	25 12	; Ct
	767	[146]	GETGLOBAL	26 -31	; Exp
	768	[146]	GETUPVAL 	27 22	; sym
	769	[146]	LOADK    	28 -54	; ","
	770	[146]	CALL     	27 2 2
	771	[146]	MUL      	26 26 27
	772	[146]	GETGLOBAL	27 -31	; Exp
	773	[146]	MUL      	26 26 27
	774	[146]	GETUPVAL 	27 22	; sym
	775	[146]	LOADK    	28 -54	; ","
	776	[146]	CALL     	27 2 2
	777	[146]	GETGLOBAL	28 -31	; Exp
	778	[146]	MUL      	27 27 28
	779	[146]	POW      	27 27 -11	; - -1
	780	[146]	MUL      	26 26 27
	781	[146]	CALL     	25 2 2
	782	[146]	MUL      	24 24 25
	783	[146]	GETUPVAL 	25 8	; mark
	784	[146]	LOADK    	26 -77	; "for"
	785	[146]	CALL     	25 2 2
	786	[146]	DIV      	24 24 25
	787	[146]	CALL     	23 2 2
	788	[146]	SETTABLE 	21 -92 23	; "CompFor" -
	789	[147]	GETGLOBAL	23 -92	; CompFor
	790	[147]	GETGLOBAL	24 -91	; CompForEach
	791	[147]	ADD      	23 23 24
	792	[147]	MOVE     	24 14
	793	[147]	LOADK    	25 -67	; "when"
	794	[147]	CALL     	24 2 2
	795	[147]	GETGLOBAL	25 -31	; Exp
	796	[147]	MUL      	24 24 25
	797	[147]	GETUPVAL 	25 8	; mark
	798	[147]	LOADK    	26 -67	; "when"
	799	[147]	CALL     	25 2 2
	800	[147]	DIV      	24 24 25
	801	[147]	ADD      	23 23 24
	802	[147]	SETTABLE 	21 -93 23	; "CompClause" -
	803	[148]	GETUPVAL 	23 22	; sym
	804	[148]	LOADK    	24 -78	; "="
	805	[148]	CALL     	23 2 2
	806	[148]	GETUPVAL 	24 12	; Ct
	807	[148]	GETGLOBAL	25 -19	; With
	808	[148]	GETGLOBAL	26 -74	; If
	809	[148]	ADD      	25 25 26
	810	[148]	GETGLOBAL	26 -22	; Switch
	811	[148]	ADD      	25 25 26
	812	[148]	CALL     	24 2 2
	813	[148]	GETUPVAL 	25 12	; Ct
	814	[148]	GETGLOBAL	26 -94	; TableBlock
	815	[148]	GETGLOBAL	27 -58	; ExpListLow
	816	[148]	ADD      	26 26 27
	817	[148]	CALL     	25 2 2
	818	[148]	ADD      	24 24 25
	819	[148]	MUL      	23 23 24
	820	[148]	GETUPVAL 	24 8	; mark
	821	[148]	LOADK    	25 -95	; "assign"
	822	[148]	CALL     	24 2 2
	823	[148]	DIV      	23 23 24
	824	[148]	SETTABLE 	21 -29 23	; "Assign" -
	825	[149]	GETUPVAL 	23 22	; sym
	826	[149]	LOADK    	24 -96	; "..="
	827	[149]	CALL     	23 2 2
	828	[149]	GETUPVAL 	24 22	; sym
	829	[149]	LOADK    	25 -97	; "+="
	830	[149]	CALL     	24 2 2
	831	[149]	ADD      	23 23 24
	832	[149]	GETUPVAL 	24 22	; sym
	833	[149]	LOADK    	25 -98	; "-="
	834	[149]	CALL     	24 2 2
	835	[149]	ADD      	23 23 24
	836	[149]	GETUPVAL 	24 22	; sym
	837	[149]	LOADK    	25 -99	; "*="
	838	[149]	CALL     	24 2 2
	839	[149]	ADD      	23 23 24
	840	[149]	GETUPVAL 	24 22	; sym
	841	[149]	LOADK    	25 -100	; "/="
	842	[149]	CALL     	24 2 2
	843	[149]	ADD      	23 23 24
	844	[149]	GETUPVAL 	24 22	; sym
	845	[149]	LOADK    	25 -101	; "%="
	846	[149]	CALL     	24 2 2
	847	[149]	ADD      	23 23 24
	848	[149]	GETUPVAL 	24 22	; sym
	849	[149]	LOADK    	25 -102	; "or="
	850	[149]	CALL     	24 2 2
	851	[149]	ADD      	23 23 24
	852	[149]	GETUPVAL 	24 22	; sym
	853	[149]	LOADK    	25 -103	; "and="
	854	[149]	CALL     	24 2 2
	855	[149]	ADD      	23 23 24
	856	[149]	GETUPVAL 	24 22	; sym
	857	[149]	LOADK    	25 -104	; "&="
	858	[149]	CALL     	24 2 2
	859	[149]	ADD      	23 23 24
	860	[149]	GETUPVAL 	24 22	; sym
	861	[149]	LOADK    	25 -105	; "|="
	862	[149]	CALL     	24 2 2
	863	[149]	ADD      	23 23 24
	864	[149]	GETUPVAL 	24 22	; sym
	865	[149]	LOADK    	25 -106	; ">>="
	866	[149]	CALL     	24 2 2
	867	[149]	ADD      	23 23 24
	868	[149]	GETUPVAL 	24 22	; sym
	869	[149]	LOADK    	25 -107	; "<<="
	870	[149]	CALL     	24 2 2
	871	[149]	ADD      	23 23 24
	872	[149]	GETUPVAL 	24 6	; trim
	873	[149]	DIV      	23 23 24
	874	[149]	GETGLOBAL	24 -31	; Exp
	875	[149]	MUL      	23 23 24
	876	[149]	GETUPVAL 	24 8	; mark
	877	[149]	LOADK    	25 -108	; "update"
	878	[149]	CALL     	24 2 2
	879	[149]	DIV      	23 23 24
	880	[149]	SETTABLE 	21 -28 23	; "Update" -
	881	[150]	GETUPVAL 	23 2	; Space
	882	[150]	GETUPVAL 	24 4	; C
	883	[150]	GETUPVAL 	25 25	; S
	884	[150]	LOADK    	26 -110	; "+-*/%^><|&"
	885	[150]	CALL     	25 2 0
	886	[150]	CALL     	24 0 2
	887	[150]	MUL      	23 23 24
	888	[150]	SETTABLE 	21 -109 23	; "CharOperators" -
	889	[151]	MOVE     	23 15
	890	[151]	LOADK    	24 -112	; "or"
	891	[151]	CALL     	23 2 2
	892	[151]	MOVE     	24 15
	893	[151]	LOADK    	25 -113	; "and"
	894	[151]	CALL     	24 2 2
	895	[151]	ADD      	23 23 24
	896	[151]	MOVE     	24 15
	897	[151]	LOADK    	25 -114	; "<="
	898	[151]	CALL     	24 2 2
	899	[151]	ADD      	23 23 24
	900	[151]	MOVE     	24 15
	901	[151]	LOADK    	25 -115	; ">="
	902	[151]	CALL     	24 2 2
	903	[151]	ADD      	23 23 24
	904	[151]	MOVE     	24 15
	905	[151]	LOADK    	25 -116	; "~="
	906	[151]	CALL     	24 2 2
	907	[151]	ADD      	23 23 24
	908	[151]	MOVE     	24 15
	909	[151]	LOADK    	25 -117	; "!="
	910	[151]	CALL     	24 2 2
	911	[151]	ADD      	23 23 24
	912	[151]	MOVE     	24 15
	913	[151]	LOADK    	25 -118	; "=="
	914	[151]	CALL     	24 2 2
	915	[151]	ADD      	23 23 24
	916	[151]	MOVE     	24 15
	917	[151]	LOADK    	25 -119	; ".."
	918	[151]	CALL     	24 2 2
	919	[151]	ADD      	23 23 24
	920	[151]	MOVE     	24 15
	921	[151]	LOADK    	25 -120	; "<<"
	922	[151]	CALL     	24 2 2
	923	[151]	ADD      	23 23 24
	924	[151]	MOVE     	24 15
	925	[151]	LOADK    	25 -121	; ">>"
	926	[151]	CALL     	24 2 2
	927	[151]	ADD      	23 23 24
	928	[151]	MOVE     	24 15
	929	[151]	LOADK    	25 -122	; "//"
	930	[151]	CALL     	24 2 2
	931	[151]	ADD      	23 23 24
	932	[151]	SETTABLE 	21 -111 23	; "WordOperators" -
	933	[152]	GETGLOBAL	23 -111	; WordOperators
	934	[152]	GETGLOBAL	24 -109	; CharOperators
	935	[152]	ADD      	23 23 24
	936	[152]	GETUPVAL 	24 21	; SpaceBreak
	937	[152]	POW      	24 24 -1	; - 0
	938	[152]	MUL      	23 23 24
	939	[152]	SETTABLE 	21 -123 23	; "BinaryOperator" -
	940	[153]	GETUPVAL 	23 1	; Cmt
	941	[153]	GETGLOBAL	24 -125	; Chain
	942	[153]	GETUPVAL 	25 26	; check_assignable
	943	[153]	CALL     	23 3 2
	944	[153]	ADD      	23 23 16
	945	[153]	ADD      	23 23 17
	946	[153]	SETTABLE 	21 -124 23	; "Assignable" -
	947	[154]	GETUPVAL 	23 12	; Ct
	948	[154]	GETGLOBAL	24 -126	; Value
	949	[154]	GETGLOBAL	25 -123	; BinaryOperator
	950	[154]	GETGLOBAL	26 -126	; Value
	951	[154]	MUL      	25 25 26
	952	[154]	POW      	25 25 -1	; - 0
	953	[154]	MUL      	24 24 25
	954	[154]	CALL     	23 2 2
	955	[154]	GETUPVAL 	24 27	; flatten_or_mark
	956	[154]	LOADK    	25 -127	; "exp"
	957	[154]	CALL     	24 2 2
	958	[154]	DIV      	23 23 24
	959	[154]	SETTABLE 	21 -31 23	; "Exp" -
	960	[155]	GETGLOBAL	23 -74	; If
	961	[155]	GETGLOBAL	24 -75	; Unless
	962	[155]	ADD      	23 23 24
	963	[155]	GETGLOBAL	24 -22	; Switch
	964	[155]	ADD      	23 23 24
	965	[155]	GETGLOBAL	24 -19	; With
	966	[155]	ADD      	23 23 24
	967	[155]	GETGLOBAL	24 -129	; ClassDecl
	968	[155]	ADD      	23 23 24
	969	[155]	GETGLOBAL	24 -21	; ForEach
	970	[155]	ADD      	23 23 24
	971	[155]	GETGLOBAL	24 -20	; For
	972	[155]	ADD      	23 23 24
	973	[155]	GETGLOBAL	24 -18	; While
	974	[155]	ADD      	23 23 24
	975	[155]	GETUPVAL 	24 1	; Cmt
	976	[155]	GETGLOBAL	25 -83	; Do
	977	[155]	MOVE     	26 8
	978	[155]	CALL     	24 3 2
	979	[155]	ADD      	23 23 24
	980	[155]	GETUPVAL 	24 22	; sym
	981	[155]	LOADK    	25 -130	; "-"
	982	[155]	CALL     	24 2 2
	983	[155]	GETUPVAL 	25 28	; SomeSpace
	984	[155]	UNM      	25 25
	985	[155]	MUL      	24 24 25
	986	[155]	GETGLOBAL	25 -31	; Exp
	987	[155]	MUL      	24 24 25
	988	[155]	GETUPVAL 	25 8	; mark
	989	[155]	LOADK    	26 -131	; "minus"
	990	[155]	CALL     	25 2 2
	991	[155]	DIV      	24 24 25
	992	[155]	ADD      	23 23 24
	993	[155]	GETUPVAL 	24 22	; sym
	994	[155]	LOADK    	25 -132	; "#"
	995	[155]	CALL     	24 2 2
	996	[155]	GETGLOBAL	25 -31	; Exp
	997	[155]	MUL      	24 24 25
	998	[155]	GETUPVAL 	25 8	; mark
	999	[155]	LOADK    	26 -133	; "length"
	1000	[155]	CALL     	25 2 2
	1001	[155]	DIV      	24 24 25
	1002	[155]	ADD      	23 23 24
	1003	[155]	GETUPVAL 	24 22	; sym
	1004	[155]	LOADK    	25 -134	; "~"
	1005	[155]	CALL     	24 2 2
	1006	[155]	GETGLOBAL	25 -31	; Exp
	1007	[155]	MUL      	24 24 25
	1008	[155]	GETUPVAL 	25 8	; mark
	1009	[155]	LOADK    	26 -135	; "bitnot"
	1010	[155]	CALL     	25 2 2
	1011	[155]	DIV      	24 24 25
	1012	[155]	ADD      	23 23 24
	1013	[155]	MOVE     	24 14
	1014	[155]	LOADK    	25 -136	; "not"
	1015	[155]	CALL     	24 2 2
	1016	[155]	GETGLOBAL	25 -31	; Exp
	1017	[155]	MUL      	24 24 25
	1018	[155]	GETUPVAL 	25 8	; mark
	1019	[155]	LOADK    	26 -136	; "not"
	1020	[155]	CALL     	25 2 2
	1021	[155]	DIV      	24 24 25
	1022	[155]	ADD      	23 23 24
	1023	[155]	GETGLOBAL	24 -87	; TblComprehension
	1024	[155]	ADD      	23 23 24
	1025	[155]	GETGLOBAL	24 -137	; TableLit
	1026	[155]	ADD      	23 23 24
	1027	[155]	GETGLOBAL	24 -84	; Comprehension
	1028	[155]	ADD      	23 23 24
	1029	[155]	GETGLOBAL	24 -138	; FunLit
	1030	[155]	ADD      	23 23 24
	1031	[155]	GETUPVAL 	24 29	; Num
	1032	[155]	ADD      	23 23 24
	1033	[155]	SETTABLE 	21 -128 23	; "SimpleValue" -
	1034	[156]	GETGLOBAL	23 -125	; Chain
	1035	[156]	GETGLOBAL	24 -140	; Callable
	1036	[156]	ADD      	23 23 24
	1037	[156]	GETUPVAL 	24 12	; Ct
	1038	[156]	GETGLOBAL	25 -141	; InvokeArgs
	1039	[156]	POW      	25 25 -11	; - -1
	1040	[156]	CALL     	24 2 2
	1041	[156]	MUL      	23 23 24
	1042	[156]	GETUPVAL 	24 30	; join_chain
	1043	[156]	DIV      	23 23 24
	1044	[156]	SETTABLE 	21 -139 23	; "ChainValue" -
	1045	[157]	GETUPVAL 	23 17	; pos
	1046	[157]	GETGLOBAL	24 -128	; SimpleValue
	1047	[157]	GETUPVAL 	25 12	; Ct
	1048	[157]	GETGLOBAL	26 -142	; KeyValueList
	1049	[157]	CALL     	25 2 2
	1050	[157]	GETUPVAL 	26 8	; mark
	1051	[157]	LOADK    	27 -143	; "table"
	1052	[157]	CALL     	26 2 2
	1053	[157]	DIV      	25 25 26
	1054	[157]	ADD      	24 24 25
	1055	[157]	GETGLOBAL	25 -139	; ChainValue
	1056	[157]	ADD      	24 24 25
	1057	[157]	GETGLOBAL	25 -144	; String
	1058	[157]	ADD      	24 24 25
	1059	[157]	CALL     	23 2 2
	1060	[157]	SETTABLE 	21 -126 23	; "Value" -
	1061	[158]	GETGLOBAL	23 -31	; Exp
	1062	[158]	SETTABLE 	21 -145 23	; "SliceValue" -
	1063	[159]	GETUPVAL 	23 2	; Space
	1064	[159]	GETGLOBAL	24 -146	; DoubleString
	1065	[159]	MUL      	23 23 24
	1066	[159]	GETUPVAL 	24 2	; Space
	1067	[159]	GETGLOBAL	25 -147	; SingleString
	1068	[159]	MUL      	24 24 25
	1069	[159]	ADD      	23 23 24
	1070	[159]	GETGLOBAL	24 -148	; LuaString
	1071	[159]	ADD      	23 23 24
	1072	[159]	SETTABLE 	21 -144 23	; "String" -
	1073	[160]	GETUPVAL 	23 31	; simple_string
	1074	[160]	LOADK    	24 -149	; "'"
	1075	[160]	CALL     	23 2 2
	1076	[160]	SETTABLE 	21 -147 23	; "SingleString" -
	1077	[161]	GETUPVAL 	23 31	; simple_string
	1078	[161]	LOADK    	24 -150	; "\""
	1079	[161]	LOADBOOL 	25 1 0
	1080	[161]	CALL     	23 3 2
	1081	[161]	SETTABLE 	21 -146 23	; "DoubleString" -
	1082	[162]	GETUPVAL 	23 32	; Cg
	1083	[162]	GETGLOBAL	24 -151	; LuaStringOpen
	1084	[162]	LOADK    	25 -152	; "string_open"
	1085	[162]	CALL     	23 3 2
	1086	[162]	GETUPVAL 	24 33	; Cb
	1087	[162]	LOADK    	25 -152	; "string_open"
	1088	[162]	CALL     	24 2 2
	1089	[162]	MUL      	23 23 24
	1090	[162]	GETUPVAL 	24 13	; Break
	1091	[162]	POW      	24 24 -11	; - -1
	1092	[162]	MUL      	23 23 24
	1093	[162]	GETUPVAL 	24 4	; C
	1094	[162]	GETUPVAL 	25 1	; Cmt
	1095	[162]	GETUPVAL 	26 4	; C
	1096	[162]	GETGLOBAL	27 -153	; LuaStringClose
	1097	[162]	CALL     	26 2 2
	1098	[162]	GETUPVAL 	27 33	; Cb
	1099	[162]	LOADK    	28 -152	; "string_open"
	1100	[162]	CALL     	27 2 2
	1101	[162]	MUL      	26 26 27
	1102	[162]	GETUPVAL 	27 34	; check_lua_string
	1103	[162]	CALL     	25 3 2
	1104	[162]	SUB      	25 -14 25	; 1 -
	1105	[162]	POW      	25 25 -1	; - 0
	1106	[162]	CALL     	24 2 2
	1107	[162]	MUL      	23 23 24
	1108	[162]	GETGLOBAL	24 -153	; LuaStringClose
	1109	[162]	MUL      	23 23 24
	1110	[162]	GETUPVAL 	24 8	; mark
	1111	[162]	LOADK    	25 -154	; "string"
	1112	[162]	CALL     	24 2 2
	1113	[162]	DIV      	23 23 24
	1114	[162]	SETTABLE 	21 -148 23	; "LuaString" -
	1115	[163]	GETUPVAL 	23 22	; sym
	1116	[163]	LOADK    	24 -85	; "["
	1117	[163]	CALL     	23 2 2
	1118	[163]	GETUPVAL 	24 10	; P
	1119	[163]	LOADK    	25 -78	; "="
	1120	[163]	CALL     	24 2 2
	1121	[163]	POW      	24 24 -1	; - 0
	1122	[163]	MUL      	23 23 24
	1123	[163]	MUL      	23 23 -85	; - "["
	1124	[163]	GETUPVAL 	24 6	; trim
	1125	[163]	DIV      	23 23 24
	1126	[163]	SETTABLE 	21 -151 23	; "LuaStringOpen" -
	1127	[164]	GETUPVAL 	23 10	; P
	1128	[164]	LOADK    	24 -78	; "="
	1129	[164]	CALL     	23 2 2
	1130	[164]	POW      	23 23 -1	; - 0
	1131	[164]	MUL      	23 -86 23	; "]" -
	1132	[164]	MUL      	23 23 -86	; - "]"
	1133	[164]	SETTABLE 	21 -153 23	; "LuaStringClose" -
	1134	[165]	GETUPVAL 	23 17	; pos
	1135	[165]	GETUPVAL 	24 8	; mark
	1136	[165]	LOADK    	25 -155	; "ref"
	1137	[165]	CALL     	24 2 2
	1138	[165]	DIV      	24 16 24
	1139	[165]	CALL     	23 2 2
	1140	[165]	ADD      	23 23 17
	1141	[165]	ADD      	23 23 19
	1142	[165]	GETGLOBAL	24 -156	; Parens
	1143	[165]	GETUPVAL 	25 8	; mark
	1144	[165]	LOADK    	26 -157	; "parens"
	1145	[165]	CALL     	25 2 2
	1146	[165]	DIV      	24 24 25
	1147	[165]	ADD      	23 23 24
	1148	[165]	SETTABLE 	21 -140 23	; "Callable" -
	1149	[166]	GETUPVAL 	23 22	; sym
	1150	[166]	LOADK    	24 -158	; "("
	1151	[166]	CALL     	23 2 2
	1152	[166]	GETUPVAL 	24 21	; SpaceBreak
	1153	[166]	POW      	24 24 -1	; - 0
	1154	[166]	MUL      	23 23 24
	1155	[166]	GETGLOBAL	24 -31	; Exp
	1156	[166]	MUL      	23 23 24
	1157	[166]	GETUPVAL 	24 21	; SpaceBreak
	1158	[166]	POW      	24 24 -1	; - 0
	1159	[166]	MUL      	23 23 24
	1160	[166]	GETUPVAL 	24 22	; sym
	1161	[166]	LOADK    	25 -159	; ")"
	1162	[166]	CALL     	24 2 2
	1163	[166]	MUL      	23 23 24
	1164	[166]	SETTABLE 	21 -156 23	; "Parens" -
	1165	[167]	GETUPVAL 	23 35	; symx
	1166	[167]	LOADK    	24 -158	; "("
	1167	[167]	CALL     	23 2 2
	1168	[167]	GETUPVAL 	24 21	; SpaceBreak
	1169	[167]	POW      	24 24 -1	; - 0
	1170	[167]	MUL      	23 23 24
	1171	[167]	GETUPVAL 	24 12	; Ct
	1172	[167]	GETGLOBAL	25 -161	; FnArgsExpList
	1173	[167]	POW      	25 25 -11	; - -1
	1174	[167]	CALL     	24 2 2
	1175	[167]	MUL      	23 23 24
	1176	[167]	GETUPVAL 	24 21	; SpaceBreak
	1177	[167]	POW      	24 24 -1	; - 0
	1178	[167]	MUL      	23 23 24
	1179	[167]	GETUPVAL 	24 22	; sym
	1180	[167]	LOADK    	25 -159	; ")"
	1181	[167]	CALL     	24 2 2
	1182	[167]	MUL      	23 23 24
	1183	[167]	GETUPVAL 	24 22	; sym
	1184	[167]	LOADK    	25 -162	; "!"
	1185	[167]	CALL     	24 2 2
	1186	[167]	GETUPVAL 	25 10	; P
	1187	[167]	LOADK    	26 -78	; "="
	1188	[167]	CALL     	25 2 2
	1189	[167]	UNM      	25 25
	1190	[167]	MUL      	24 24 25
	1191	[167]	GETUPVAL 	25 12	; Ct
	1192	[167]	LOADK    	26 -3	; ""
	1193	[167]	CALL     	25 2 2
	1194	[167]	MUL      	24 24 25
	1195	[167]	ADD      	23 23 24
	1196	[167]	SETTABLE 	21 -160 23	; "FnArgs" -
	1197	[168]	GETGLOBAL	23 -31	; Exp
	1198	[168]	GETUPVAL 	24 13	; Break
	1199	[168]	GETUPVAL 	25 22	; sym
	1200	[168]	LOADK    	26 -54	; ","
	1201	[168]	CALL     	25 2 2
	1202	[168]	ADD      	24 24 25
	1203	[168]	GETUPVAL 	25 36	; White
	1204	[168]	MUL      	24 24 25
	1205	[168]	GETGLOBAL	25 -31	; Exp
	1206	[168]	MUL      	24 24 25
	1207	[168]	POW      	24 24 -1	; - 0
	1208	[168]	MUL      	23 23 24
	1209	[168]	SETTABLE 	21 -161 23	; "FnArgsExpList" -
	1210	[169]	GETGLOBAL	23 -140	; Callable
	1211	[169]	GETGLOBAL	24 -144	; String
	1212	[169]	ADD      	23 23 24
	1213	[169]	GETUPVAL 	24 25	; S
	1214	[169]	LOADK    	25 -163	; ".\\"
	1215	[169]	CALL     	24 2 2
	1216	[169]	UNM      	24 24
	1217	[169]	ADD      	23 23 24
	1218	[169]	GETGLOBAL	24 -164	; ChainItems
	1219	[169]	MUL      	23 23 24
	1220	[169]	GETUPVAL 	24 8	; mark
	1221	[169]	LOADK    	25 -165	; "chain"
	1222	[169]	CALL     	24 2 2
	1223	[169]	DIV      	23 23 24
	1224	[169]	GETUPVAL 	24 2	; Space
	1225	[169]	GETGLOBAL	25 -166	; DotChainItem
	1226	[169]	GETGLOBAL	26 -164	; ChainItems
	1227	[169]	POW      	26 26 -11	; - -1
	1228	[169]	MUL      	25 25 26
	1229	[169]	GETGLOBAL	26 -167	; ColonChain
	1230	[169]	ADD      	25 25 26
	1231	[169]	MUL      	24 24 25
	1232	[169]	GETUPVAL 	25 8	; mark
	1233	[169]	LOADK    	26 -165	; "chain"
	1234	[169]	CALL     	25 2 2
	1235	[169]	DIV      	24 24 25
	1236	[169]	ADD      	23 23 24
	1237	[169]	SETTABLE 	21 -125 23	; "Chain" -
	1238	[170]	GETGLOBAL	23 -168	; ChainItem
	1239	[170]	POW      	23 23 -14	; - 1
	1240	[170]	GETGLOBAL	24 -167	; ColonChain
	1241	[170]	POW      	24 24 -11	; - -1
	1242	[170]	MUL      	23 23 24
	1243	[170]	GETGLOBAL	24 -167	; ColonChain
	1244	[170]	ADD      	23 23 24
	1245	[170]	SETTABLE 	21 -164 23	; "ChainItems" -
	1246	[171]	GETGLOBAL	23 -169	; Invoke
	1247	[171]	GETGLOBAL	24 -166	; DotChainItem
	1248	[171]	ADD      	23 23 24
	1249	[171]	GETGLOBAL	24 -170	; Slice
	1250	[171]	ADD      	23 23 24
	1251	[171]	GETUPVAL 	24 35	; symx
	1252	[171]	LOADK    	25 -85	; "["
	1253	[171]	CALL     	24 2 2
	1254	[171]	GETGLOBAL	25 -31	; Exp
	1255	[171]	MUL      	24 24 25
	1256	[171]	GETUPVAL 	25 8	; mark
	1257	[171]	LOADK    	26 -171	; "index"
	1258	[171]	CALL     	25 2 2
	1259	[171]	DIV      	24 24 25
	1260	[171]	GETUPVAL 	25 22	; sym
	1261	[171]	LOADK    	26 -86	; "]"
	1262	[171]	CALL     	25 2 2
	1263	[171]	MUL      	24 24 25
	1264	[171]	ADD      	23 23 24
	1265	[171]	SETTABLE 	21 -168 23	; "ChainItem" -
	1266	[172]	GETUPVAL 	23 35	; symx
	1267	[172]	LOADK    	24 -172	; "."
	1268	[172]	CALL     	23 2 2
	1269	[172]	GETUPVAL 	24 7	; _Name
	1270	[172]	MUL      	23 23 24
	1271	[172]	GETUPVAL 	24 8	; mark
	1272	[172]	LOADK    	25 -173	; "dot"
	1273	[172]	CALL     	24 2 2
	1274	[172]	DIV      	23 23 24
	1275	[172]	SETTABLE 	21 -166 23	; "DotChainItem" -
	1276	[173]	GETUPVAL 	23 35	; symx
	1277	[173]	LOADK    	24 -52	; "\\"
	1278	[173]	CALL     	23 2 2
	1279	[173]	GETUPVAL 	24 7	; _Name
	1280	[173]	MUL      	23 23 24
	1281	[173]	GETUPVAL 	24 8	; mark
	1282	[173]	LOADK    	25 -53	; "colon"
	1283	[173]	CALL     	24 2 2
	1284	[173]	DIV      	23 23 24
	1285	[173]	SETTABLE 	21 -174 23	; "ColonChainItem" -
	1286	[174]	GETGLOBAL	23 -174	; ColonChainItem
	1287	[174]	GETGLOBAL	24 -169	; Invoke
	1288	[174]	GETGLOBAL	25 -164	; ChainItems
	1289	[174]	POW      	25 25 -11	; - -1
	1290	[174]	MUL      	24 24 25
	1291	[174]	POW      	24 24 -11	; - -1
	1292	[174]	MUL      	23 23 24
	1293	[174]	SETTABLE 	21 -167 23	; "ColonChain" -
	1294	[175]	GETUPVAL 	23 35	; symx
	1295	[175]	LOADK    	24 -85	; "["
	1296	[175]	CALL     	23 2 2
	1297	[175]	GETGLOBAL	24 -145	; SliceValue
	1298	[175]	GETUPVAL 	25 9	; Cc
	1299	[175]	LOADK    	26 -14	; 1
	1300	[175]	CALL     	25 2 2
	1301	[175]	ADD      	24 24 25
	1302	[175]	MUL      	23 23 24
	1303	[175]	GETUPVAL 	24 22	; sym
	1304	[175]	LOADK    	25 -54	; ","
	1305	[175]	CALL     	24 2 2
	1306	[175]	MUL      	23 23 24
	1307	[175]	GETGLOBAL	24 -145	; SliceValue
	1308	[175]	GETUPVAL 	25 9	; Cc
	1309	[175]	LOADK    	26 -3	; ""
	1310	[175]	CALL     	25 2 2
	1311	[175]	ADD      	24 24 25
	1312	[175]	MUL      	23 23 24
	1313	[175]	GETUPVAL 	24 22	; sym
	1314	[175]	LOADK    	25 -54	; ","
	1315	[175]	CALL     	24 2 2
	1316	[175]	GETGLOBAL	25 -145	; SliceValue
	1317	[175]	MUL      	24 24 25
	1318	[175]	POW      	24 24 -11	; - -1
	1319	[175]	MUL      	23 23 24
	1320	[175]	GETUPVAL 	24 22	; sym
	1321	[175]	LOADK    	25 -86	; "]"
	1322	[175]	CALL     	24 2 2
	1323	[175]	MUL      	23 23 24
	1324	[175]	GETUPVAL 	24 8	; mark
	1325	[175]	LOADK    	25 -175	; "slice"
	1326	[175]	CALL     	24 2 2
	1327	[175]	DIV      	23 23 24
	1328	[175]	SETTABLE 	21 -170 23	; "Slice" -
	1329	[176]	GETGLOBAL	23 -160	; FnArgs
	1330	[176]	GETUPVAL 	24 8	; mark
	1331	[176]	LOADK    	25 -176	; "call"
	1332	[176]	CALL     	24 2 2
	1333	[176]	DIV      	23 23 24
	1334	[176]	GETGLOBAL	24 -147	; SingleString
	1335	[176]	GETUPVAL 	25 37	; wrap_func_arg
	1336	[176]	DIV      	24 24 25
	1337	[176]	ADD      	23 23 24
	1338	[176]	GETGLOBAL	24 -146	; DoubleString
	1339	[176]	GETUPVAL 	25 37	; wrap_func_arg
	1340	[176]	DIV      	24 24 25
	1341	[176]	ADD      	23 23 24
	1342	[176]	GETUPVAL 	24 15	; L
	1343	[176]	GETUPVAL 	25 10	; P
	1344	[176]	LOADK    	26 -85	; "["
	1345	[176]	CALL     	25 2 0
	1346	[176]	CALL     	24 0 2
	1347	[176]	GETGLOBAL	25 -148	; LuaString
	1348	[176]	MUL      	24 24 25
	1349	[176]	GETUPVAL 	25 37	; wrap_func_arg
	1350	[176]	DIV      	24 24 25
	1351	[176]	ADD      	23 23 24
	1352	[176]	SETTABLE 	21 -169 23	; "Invoke" -
	1353	[177]	GETGLOBAL	23 -178	; KeyValue
	1354	[177]	GETUPVAL 	24 12	; Ct
	1355	[177]	GETGLOBAL	25 -31	; Exp
	1356	[177]	CALL     	24 2 2
	1357	[177]	ADD      	23 23 24
	1358	[177]	SETTABLE 	21 -177 23	; "TableValue" -
	1359	[178]	GETUPVAL 	23 22	; sym
	1360	[178]	LOADK    	24 -88	; "{"
	1361	[178]	CALL     	23 2 2
	1362	[178]	GETUPVAL 	24 12	; Ct
	1363	[178]	GETGLOBAL	25 -179	; TableValueList
	1364	[178]	POW      	25 25 -11	; - -1
	1365	[178]	GETUPVAL 	26 22	; sym
	1366	[178]	LOADK    	27 -54	; ","
	1367	[178]	CALL     	26 2 2
	1368	[178]	POW      	26 26 -11	; - -1
	1369	[178]	MUL      	25 25 26
	1370	[178]	GETUPVAL 	26 21	; SpaceBreak
	1371	[178]	GETGLOBAL	27 -180	; TableLitLine
	1372	[178]	MUL      	26 26 27
	1373	[178]	GETUPVAL 	27 22	; sym
	1374	[178]	LOADK    	28 -54	; ","
	1375	[178]	CALL     	27 2 2
	1376	[178]	POW      	27 27 -11	; - -1
	1377	[178]	GETUPVAL 	28 21	; SpaceBreak
	1378	[178]	MUL      	27 27 28
	1379	[178]	GETGLOBAL	28 -180	; TableLitLine
	1380	[178]	MUL      	27 27 28
	1381	[178]	POW      	27 27 -1	; - 0
	1382	[178]	MUL      	26 26 27
	1383	[178]	GETUPVAL 	27 22	; sym
	1384	[178]	LOADK    	28 -54	; ","
	1385	[178]	CALL     	27 2 2
	1386	[178]	POW      	27 27 -11	; - -1
	1387	[178]	MUL      	26 26 27
	1388	[178]	POW      	26 26 -11	; - -1
	1389	[178]	MUL      	25 25 26
	1390	[178]	CALL     	24 2 2
	1391	[178]	MUL      	23 23 24
	1392	[178]	GETUPVAL 	24 36	; White
	1393	[178]	MUL      	23 23 24
	1394	[178]	GETUPVAL 	24 22	; sym
	1395	[178]	LOADK    	25 -89	; "}"
	1396	[178]	CALL     	24 2 2
	1397	[178]	MUL      	23 23 24
	1398	[178]	GETUPVAL 	24 8	; mark
	1399	[178]	LOADK    	25 -143	; "table"
	1400	[178]	CALL     	24 2 2
	1401	[178]	DIV      	23 23 24
	1402	[178]	SETTABLE 	21 -137 23	; "TableLit" -
	1403	[179]	GETGLOBAL	23 -177	; TableValue
	1404	[179]	GETUPVAL 	24 22	; sym
	1405	[179]	LOADK    	25 -54	; ","
	1406	[179]	CALL     	24 2 2
	1407	[179]	GETGLOBAL	25 -177	; TableValue
	1408	[179]	MUL      	24 24 25
	1409	[179]	POW      	24 24 -1	; - 0
	1410	[179]	MUL      	23 23 24
	1411	[179]	SETTABLE 	21 -179 23	; "TableValueList" -
	1412	[180]	GETGLOBAL	23 -39	; PushIndent
	1413	[180]	GETGLOBAL	24 -179	; TableValueList
	1414	[180]	GETGLOBAL	25 -41	; PopIndent
	1415	[180]	MUL      	24 24 25
	1416	[180]	GETGLOBAL	25 -41	; PopIndent
	1417	[180]	GETUPVAL 	26 38	; Cut
	1418	[180]	MUL      	25 25 26
	1419	[180]	ADD      	24 24 25
	1420	[180]	MUL      	23 23 24
	1421	[180]	GETUPVAL 	24 2	; Space
	1422	[180]	ADD      	23 23 24
	1423	[180]	SETTABLE 	21 -180 23	; "TableLitLine" -
	1424	[181]	GETUPVAL 	23 12	; Ct
	1425	[181]	GETGLOBAL	24 -182	; KeyValueLine
	1426	[181]	GETUPVAL 	25 21	; SpaceBreak
	1427	[181]	POW      	25 25 -14	; - 1
	1428	[181]	GETGLOBAL	26 -182	; KeyValueLine
	1429	[181]	MUL      	25 25 26
	1430	[181]	POW      	25 25 -1	; - 0
	1431	[181]	MUL      	24 24 25
	1432	[181]	CALL     	23 2 2
	1433	[181]	SETTABLE 	21 -181 23	; "TableBlockInner" -
	1434	[182]	GETUPVAL 	23 21	; SpaceBreak
	1435	[182]	POW      	23 23 -14	; - 1
	1436	[182]	GETGLOBAL	24 -38	; Advance
	1437	[182]	MUL      	23 23 24
	1438	[182]	GETUPVAL 	24 23	; ensure
	1439	[182]	GETGLOBAL	25 -181	; TableBlockInner
	1440	[182]	GETGLOBAL	26 -41	; PopIndent
	1441	[182]	CALL     	24 3 2
	1442	[182]	MUL      	23 23 24
	1443	[182]	GETUPVAL 	24 8	; mark
	1444	[182]	LOADK    	25 -143	; "table"
	1445	[182]	CALL     	24 2 2
	1446	[182]	DIV      	23 23 24
	1447	[182]	SETTABLE 	21 -94 23	; "TableBlock" -
	1448	[183]	MOVE     	23 14
	1449	[183]	LOADK    	24 -183	; "class"
	1450	[183]	CALL     	23 2 2
	1451	[183]	GETUPVAL 	24 10	; P
	1452	[183]	LOADK    	25 -184	; ":"
	1453	[183]	CALL     	24 2 2
	1454	[183]	UNM      	24 24
	1455	[183]	MUL      	23 23 24
	1456	[183]	GETGLOBAL	24 -124	; Assignable
	1457	[183]	GETUPVAL 	25 9	; Cc
	1458	[183]	LOADNIL  	26 26
	1459	[183]	CALL     	25 2 2
	1460	[183]	ADD      	24 24 25
	1461	[183]	MUL      	23 23 24
	1462	[183]	MOVE     	24 14
	1463	[183]	LOADK    	25 -185	; "extends"
	1464	[183]	CALL     	24 2 2
	1465	[183]	GETGLOBAL	25 -40	; PreventIndent
	1466	[183]	MUL      	24 24 25
	1467	[183]	GETUPVAL 	25 23	; ensure
	1468	[183]	GETGLOBAL	26 -31	; Exp
	1469	[183]	GETGLOBAL	27 -41	; PopIndent
	1470	[183]	CALL     	25 3 2
	1471	[183]	MUL      	24 24 25
	1472	[183]	GETUPVAL 	25 4	; C
	1473	[183]	LOADK    	26 -3	; ""
	1474	[183]	CALL     	25 2 2
	1475	[183]	ADD      	24 24 25
	1476	[183]	POW      	24 24 -11	; - -1
	1477	[183]	MUL      	23 23 24
	1478	[183]	GETGLOBAL	24 -186	; ClassBlock
	1479	[183]	GETUPVAL 	25 12	; Ct
	1480	[183]	LOADK    	26 -3	; ""
	1481	[183]	CALL     	25 2 2
	1482	[183]	ADD      	24 24 25
	1483	[183]	MUL      	23 23 24
	1484	[183]	GETUPVAL 	24 8	; mark
	1485	[183]	LOADK    	25 -183	; "class"
	1486	[183]	CALL     	24 2 2
	1487	[183]	DIV      	23 23 24
	1488	[183]	SETTABLE 	21 -129 23	; "ClassDecl" -
	1489	[184]	GETUPVAL 	23 21	; SpaceBreak
	1490	[184]	POW      	23 23 -14	; - 1
	1491	[184]	GETGLOBAL	24 -38	; Advance
	1492	[184]	MUL      	23 23 24
	1493	[184]	GETUPVAL 	24 12	; Ct
	1494	[184]	GETGLOBAL	25 -187	; ClassLine
	1495	[184]	GETUPVAL 	26 21	; SpaceBreak
	1496	[184]	POW      	26 26 -14	; - 1
	1497	[184]	GETGLOBAL	27 -187	; ClassLine
	1498	[184]	MUL      	26 26 27
	1499	[184]	POW      	26 26 -1	; - 0
	1500	[184]	MUL      	25 25 26
	1501	[184]	CALL     	24 2 2
	1502	[184]	MUL      	23 23 24
	1503	[184]	GETGLOBAL	24 -41	; PopIndent
	1504	[184]	MUL      	23 23 24
	1505	[184]	SETTABLE 	21 -186 23	; "ClassBlock" -
	1506	[185]	GETGLOBAL	23 -15	; CheckIndent
	1507	[185]	GETGLOBAL	24 -142	; KeyValueList
	1508	[185]	GETUPVAL 	25 8	; mark
	1509	[185]	LOADK    	26 -188	; "props"
	1510	[185]	CALL     	25 2 2
	1511	[185]	DIV      	24 24 25
	1512	[185]	GETGLOBAL	25 -16	; Statement
	1513	[185]	GETUPVAL 	26 8	; mark
	1514	[185]	LOADK    	27 -189	; "stm"
	1515	[185]	CALL     	26 2 2
	1516	[185]	DIV      	25 25 26
	1517	[185]	ADD      	24 24 25
	1518	[185]	GETGLOBAL	25 -31	; Exp
	1519	[185]	GETUPVAL 	26 8	; mark
	1520	[185]	LOADK    	27 -189	; "stm"
	1521	[185]	CALL     	26 2 2
	1522	[185]	DIV      	25 25 26
	1523	[185]	ADD      	24 24 25
	1524	[185]	GETUPVAL 	25 22	; sym
	1525	[185]	LOADK    	26 -54	; ","
	1526	[185]	CALL     	25 2 2
	1527	[185]	POW      	25 25 -11	; - -1
	1528	[185]	MUL      	24 24 25
	1529	[185]	MUL      	23 23 24
	1530	[185]	SETTABLE 	21 -187 23	; "ClassLine" -
	1531	[186]	MOVE     	23 14
	1532	[186]	LOADK    	24 -190	; "export"
	1533	[186]	CALL     	23 2 2
	1534	[186]	GETUPVAL 	24 9	; Cc
	1535	[186]	LOADK    	25 -183	; "class"
	1536	[186]	CALL     	24 2 2
	1537	[186]	GETGLOBAL	25 -129	; ClassDecl
	1538	[186]	MUL      	24 24 25
	1539	[186]	MOVE     	25 15
	1540	[186]	LOADK    	26 -43	; "*"
	1541	[186]	CALL     	25 2 2
	1542	[186]	ADD      	24 24 25
	1543	[186]	MOVE     	25 15
	1544	[186]	LOADK    	26 -44	; "^"
	1545	[186]	CALL     	25 2 2
	1546	[186]	ADD      	24 24 25
	1547	[186]	GETUPVAL 	25 12	; Ct
	1548	[186]	GETGLOBAL	26 -46	; NameList
	1549	[186]	CALL     	25 2 2
	1550	[186]	GETUPVAL 	26 22	; sym
	1551	[186]	LOADK    	27 -78	; "="
	1552	[186]	CALL     	26 2 2
	1553	[186]	GETUPVAL 	27 12	; Ct
	1554	[186]	GETGLOBAL	28 -58	; ExpListLow
	1555	[186]	CALL     	27 2 2
	1556	[186]	MUL      	26 26 27
	1557	[186]	POW      	26 26 -11	; - -1
	1558	[186]	MUL      	25 25 26
	1559	[186]	ADD      	24 24 25
	1560	[186]	MUL      	23 23 24
	1561	[186]	GETUPVAL 	24 8	; mark
	1562	[186]	LOADK    	25 -190	; "export"
	1563	[186]	CALL     	24 2 2
	1564	[186]	DIV      	23 23 24
	1565	[186]	SETTABLE 	21 -25 23	; "Export" -
	1566	[187]	GETUPVAL 	23 22	; sym
	1567	[187]	LOADK    	24 -184	; ":"
	1568	[187]	CALL     	23 2 2
	1569	[187]	GETUPVAL 	24 28	; SomeSpace
	1570	[187]	UNM      	24 24
	1571	[187]	MUL      	23 23 24
	1572	[187]	MUL      	23 23 16
	1573	[187]	GETUPVAL 	24 39	; lpeg
	1574	[187]	GETTABLE 	24 24 -191	; "Cp"
	1575	[187]	CALL     	24 1 2
	1576	[187]	MUL      	23 23 24
	1577	[187]	GETUPVAL 	24 40	; self_assign
	1578	[187]	DIV      	23 23 24
	1579	[187]	GETUPVAL 	24 12	; Ct
	1580	[187]	GETUPVAL 	25 22	; sym
	1581	[187]	LOADK    	26 -85	; "["
	1582	[187]	CALL     	25 2 2
	1583	[187]	GETGLOBAL	26 -31	; Exp
	1584	[187]	MUL      	25 25 26
	1585	[187]	GETUPVAL 	26 22	; sym
	1586	[187]	LOADK    	27 -86	; "]"
	1587	[187]	CALL     	26 2 2
	1588	[187]	MUL      	25 25 26
	1589	[187]	ADD      	25 18 25
	1590	[187]	GETUPVAL 	26 2	; Space
	1591	[187]	GETGLOBAL	27 -146	; DoubleString
	1592	[187]	MUL      	26 26 27
	1593	[187]	ADD      	25 25 26
	1594	[187]	GETUPVAL 	26 2	; Space
	1595	[187]	GETGLOBAL	27 -147	; SingleString
	1596	[187]	MUL      	26 26 27
	1597	[187]	ADD      	25 25 26
	1598	[187]	GETUPVAL 	26 35	; symx
	1599	[187]	LOADK    	27 -184	; ":"
	1600	[187]	CALL     	26 2 2
	1601	[187]	MUL      	25 25 26
	1602	[187]	GETGLOBAL	26 -31	; Exp
	1603	[187]	GETGLOBAL	27 -94	; TableBlock
	1604	[187]	ADD      	26 26 27
	1605	[187]	GETUPVAL 	27 21	; SpaceBreak
	1606	[187]	POW      	27 27 -14	; - 1
	1607	[187]	GETGLOBAL	28 -31	; Exp
	1608	[187]	MUL      	27 27 28
	1609	[187]	ADD      	26 26 27
	1610	[187]	MUL      	25 25 26
	1611	[187]	CALL     	24 2 2
	1612	[187]	ADD      	23 23 24
	1613	[187]	SETTABLE 	21 -178 23	; "KeyValue" -
	1614	[188]	GETGLOBAL	23 -178	; KeyValue
	1615	[188]	GETUPVAL 	24 22	; sym
	1616	[188]	LOADK    	25 -54	; ","
	1617	[188]	CALL     	24 2 2
	1618	[188]	GETGLOBAL	25 -178	; KeyValue
	1619	[188]	MUL      	24 24 25
	1620	[188]	POW      	24 24 -1	; - 0
	1621	[188]	MUL      	23 23 24
	1622	[188]	SETTABLE 	21 -142 23	; "KeyValueList" -
	1623	[189]	GETGLOBAL	23 -15	; CheckIndent
	1624	[189]	GETGLOBAL	24 -142	; KeyValueList
	1625	[189]	MUL      	23 23 24
	1626	[189]	GETUPVAL 	24 22	; sym
	1627	[189]	LOADK    	25 -54	; ","
	1628	[189]	CALL     	24 2 2
	1629	[189]	POW      	24 24 -11	; - -1
	1630	[189]	MUL      	23 23 24
	1631	[189]	SETTABLE 	21 -182 23	; "KeyValueLine" -
	1632	[190]	GETUPVAL 	23 22	; sym
	1633	[190]	LOADK    	24 -158	; "("
	1634	[190]	CALL     	23 2 2
	1635	[190]	GETUPVAL 	24 36	; White
	1636	[190]	MUL      	23 23 24
	1637	[190]	GETUPVAL 	24 12	; Ct
	1638	[190]	GETGLOBAL	25 -193	; FnArgDefList
	1639	[190]	POW      	25 25 -11	; - -1
	1640	[190]	CALL     	24 2 2
	1641	[190]	MUL      	23 23 24
	1642	[190]	MOVE     	24 14
	1643	[190]	LOADK    	25 -194	; "using"
	1644	[190]	CALL     	24 2 2
	1645	[190]	GETUPVAL 	25 12	; Ct
	1646	[190]	GETGLOBAL	26 -46	; NameList
	1647	[190]	GETUPVAL 	27 2	; Space
	1648	[190]	MUL      	27 27 -195	; - "nil"
	1649	[190]	ADD      	26 26 27
	1650	[190]	CALL     	25 2 2
	1651	[190]	MUL      	24 24 25
	1652	[190]	GETUPVAL 	25 12	; Ct
	1653	[190]	LOADK    	26 -3	; ""
	1654	[190]	CALL     	25 2 2
	1655	[190]	ADD      	24 24 25
	1656	[190]	MUL      	23 23 24
	1657	[190]	GETUPVAL 	24 36	; White
	1658	[190]	MUL      	23 23 24
	1659	[190]	GETUPVAL 	24 22	; sym
	1660	[190]	LOADK    	25 -159	; ")"
	1661	[190]	CALL     	24 2 2
	1662	[190]	MUL      	23 23 24
	1663	[190]	GETUPVAL 	24 12	; Ct
	1664	[190]	LOADK    	25 -3	; ""
	1665	[190]	CALL     	24 2 2
	1666	[190]	GETUPVAL 	25 12	; Ct
	1667	[190]	LOADK    	26 -3	; ""
	1668	[190]	CALL     	25 2 2
	1669	[190]	MUL      	24 24 25
	1670	[190]	ADD      	23 23 24
	1671	[190]	SETTABLE 	21 -192 23	; "FnArgsDef" -
	1672	[191]	GETGLOBAL	23 -196	; FnArgDef
	1673	[191]	GETUPVAL 	24 22	; sym
	1674	[191]	LOADK    	25 -54	; ","
	1675	[191]	CALL     	24 2 2
	1676	[191]	GETUPVAL 	25 13	; Break
	1677	[191]	ADD      	24 24 25
	1678	[191]	GETUPVAL 	25 36	; White
	1679	[191]	MUL      	24 24 25
	1680	[191]	GETGLOBAL	25 -196	; FnArgDef
	1681	[191]	MUL      	24 24 25
	1682	[191]	POW      	24 24 -1	; - 0
	1683	[191]	MUL      	23 23 24
	1684	[191]	GETUPVAL 	24 22	; sym
	1685	[191]	LOADK    	25 -54	; ","
	1686	[191]	CALL     	24 2 2
	1687	[191]	GETUPVAL 	25 13	; Break
	1688	[191]	ADD      	24 24 25
	1689	[191]	GETUPVAL 	25 36	; White
	1690	[191]	MUL      	24 24 25
	1691	[191]	GETUPVAL 	25 12	; Ct
	1692	[191]	MOVE     	26 19
	1693	[191]	CALL     	25 2 2
	1694	[191]	MUL      	24 24 25
	1695	[191]	POW      	24 24 -1	; - 0
	1696	[191]	MUL      	23 23 24
	1697	[191]	GETUPVAL 	24 12	; Ct
	1698	[191]	MOVE     	25 19
	1699	[191]	CALL     	24 2 2
	1700	[191]	ADD      	23 23 24
	1701	[191]	SETTABLE 	21 -193 23	; "FnArgDefList" -
	1702	[192]	GETUPVAL 	23 12	; Ct
	1703	[192]	ADD      	24 16 17
	1704	[192]	GETUPVAL 	25 22	; sym
	1705	[192]	LOADK    	26 -78	; "="
	1706	[192]	CALL     	25 2 2
	1707	[192]	GETGLOBAL	26 -31	; Exp
	1708	[192]	MUL      	25 25 26
	1709	[192]	POW      	25 25 -11	; - -1
	1710	[192]	MUL      	24 24 25
	1711	[192]	CALL     	23 2 2
	1712	[192]	SETTABLE 	21 -196 23	; "FnArgDef" -
	1713	[193]	GETGLOBAL	23 -192	; FnArgsDef
	1714	[193]	GETUPVAL 	24 22	; sym
	1715	[193]	LOADK    	25 -197	; "->"
	1716	[193]	CALL     	24 2 2
	1717	[193]	GETUPVAL 	25 9	; Cc
	1718	[193]	LOADK    	26 -198	; "slim"
	1719	[193]	CALL     	25 2 2
	1720	[193]	MUL      	24 24 25
	1721	[193]	GETUPVAL 	25 22	; sym
	1722	[193]	LOADK    	26 -199	; "=>"
	1723	[193]	CALL     	25 2 2
	1724	[193]	GETUPVAL 	26 9	; Cc
	1725	[193]	LOADK    	27 -200	; "fat"
	1726	[193]	CALL     	26 2 2
	1727	[193]	MUL      	25 25 26
	1728	[193]	ADD      	24 24 25
	1729	[193]	MUL      	23 23 24
	1730	[193]	GETGLOBAL	24 -36	; Body
	1731	[193]	GETUPVAL 	25 12	; Ct
	1732	[193]	LOADK    	26 -3	; ""
	1733	[193]	CALL     	25 2 2
	1734	[193]	ADD      	24 24 25
	1735	[193]	MUL      	23 23 24
	1736	[193]	GETUPVAL 	24 8	; mark
	1737	[193]	LOADK    	25 -201	; "fndef"
	1738	[193]	CALL     	24 2 2
	1739	[193]	DIV      	23 23 24
	1740	[193]	SETTABLE 	21 -138 23	; "FunLit" -
	1741	[194]	GETUPVAL 	23 22	; sym
	1742	[194]	LOADK    	24 -54	; ","
	1743	[194]	CALL     	23 2 2
	1744	[194]	MUL      	23 23 16
	1745	[194]	POW      	23 23 -1	; - 0
	1746	[194]	MUL      	23 16 23
	1747	[194]	SETTABLE 	21 -46 23	; "NameList" -
	1748	[195]	GETGLOBAL	23 -137	; TableLit
	1749	[195]	ADD      	23 16 23
	1750	[195]	SETTABLE 	21 -202 23	; "NameOrDestructure" -
	1751	[196]	GETGLOBAL	23 -202	; NameOrDestructure
	1752	[196]	GETUPVAL 	24 22	; sym
	1753	[196]	LOADK    	25 -54	; ","
	1754	[196]	CALL     	24 2 2
	1755	[196]	GETGLOBAL	25 -202	; NameOrDestructure
	1756	[196]	MUL      	24 24 25
	1757	[196]	POW      	24 24 -1	; - 0
	1758	[196]	MUL      	23 23 24
	1759	[196]	SETTABLE 	21 -79 23	; "AssignableNameList" -
	1760	[197]	GETGLOBAL	23 -31	; Exp
	1761	[197]	GETUPVAL 	24 22	; sym
	1762	[197]	LOADK    	25 -54	; ","
	1763	[197]	CALL     	24 2 2
	1764	[197]	GETGLOBAL	25 -31	; Exp
	1765	[197]	MUL      	24 24 25
	1766	[197]	POW      	24 24 -1	; - 0
	1767	[197]	MUL      	23 23 24
	1768	[197]	SETTABLE 	21 -27 23	; "ExpList" -
	1769	[198]	GETGLOBAL	23 -31	; Exp
	1770	[198]	GETUPVAL 	24 22	; sym
	1771	[198]	LOADK    	25 -54	; ","
	1772	[198]	CALL     	24 2 2
	1773	[198]	GETUPVAL 	25 22	; sym
	1774	[198]	LOADK    	26 -203	; ";"
	1775	[198]	CALL     	25 2 2
	1776	[198]	ADD      	24 24 25
	1777	[198]	GETGLOBAL	25 -31	; Exp
	1778	[198]	MUL      	24 24 25
	1779	[198]	POW      	24 24 -1	; - 0
	1780	[198]	MUL      	23 23 24
	1781	[198]	SETTABLE 	21 -58 23	; "ExpListLow" -
	1782	[199]	GETUPVAL 	23 10	; P
	1783	[199]	LOADK    	24 -130	; "-"
	1784	[199]	CALL     	23 2 2
	1785	[199]	UNM      	23 23
	1786	[199]	GETGLOBAL	24 -27	; ExpList
	1787	[199]	GETUPVAL 	25 22	; sym
	1788	[199]	LOADK    	26 -54	; ","
	1789	[199]	CALL     	25 2 2
	1790	[199]	GETGLOBAL	26 -94	; TableBlock
	1791	[199]	GETUPVAL 	27 21	; SpaceBreak
	1792	[199]	GETGLOBAL	28 -38	; Advance
	1793	[199]	MUL      	27 27 28
	1794	[199]	GETGLOBAL	28 -204	; ArgBlock
	1795	[199]	MUL      	27 27 28
	1796	[199]	GETGLOBAL	28 -94	; TableBlock
	1797	[199]	POW      	28 28 -11	; - -1
	1798	[199]	MUL      	27 27 28
	1799	[199]	ADD      	26 26 27
	1800	[199]	MUL      	25 25 26
	1801	[199]	GETGLOBAL	26 -94	; TableBlock
	1802	[199]	ADD      	25 25 26
	1803	[199]	POW      	25 25 -11	; - -1
	1804	[199]	MUL      	24 24 25
	1805	[199]	GETGLOBAL	25 -94	; TableBlock
	1806	[199]	ADD      	24 24 25
	1807	[199]	MUL      	23 23 24
	1808	[199]	SETTABLE 	21 -141 23	; "InvokeArgs" -
	1809	[200]	GETGLOBAL	23 -205	; ArgLine
	1810	[200]	GETUPVAL 	24 22	; sym
	1811	[200]	LOADK    	25 -54	; ","
	1812	[200]	CALL     	24 2 2
	1813	[200]	GETUPVAL 	25 21	; SpaceBreak
	1814	[200]	MUL      	24 24 25
	1815	[200]	GETGLOBAL	25 -205	; ArgLine
	1816	[200]	MUL      	24 24 25
	1817	[200]	POW      	24 24 -1	; - 0
	1818	[200]	MUL      	23 23 24
	1819	[200]	GETGLOBAL	24 -41	; PopIndent
	1820	[200]	MUL      	23 23 24
	1821	[200]	SETTABLE 	21 -204 23	; "ArgBlock" -
	1822	[201]	GETGLOBAL	23 -15	; CheckIndent
	1823	[201]	GETGLOBAL	24 -27	; ExpList
	1824	[201]	MUL      	23 23 24
	1825	[201]	SETTABLE 	21 -205 23	; "ArgLine" -
	1826	[202]	SETLIST  	21 1 1	; 1
	1827	[108]	CALL     	20 2 2
	1828	[203]	MOVE     	21 20
	1829	[203]	MOVE     	22 3
	1830	[203]	RETURN   	21 3
	1831	[204]	RETURN   	0 1

function <./moonscript/parse.lua:42,45> (11 instructions, 44 bytes at 0x7f9c3ec072d0)
3 params, 5 slots, 2 upvalues, 3 locals, 2 constants, 0 functions
	1	[43]	GETUPVAL 	3 0	; state
	2	[43]	SETTABLE 	3 -1 1	; "last_pos" -
	3	[44]	GETUPVAL 	3 1	; _indent
	4	[44]	SELF     	3 3 -2	; "top"
	5	[44]	CALL     	3 2 2
	6	[44]	EQ       	1 3 2
	7	[44]	JMP      	1	; to 9
	8	[44]	LOADBOOL 	3 0 1
	9	[44]	LOADBOOL 	3 1 0
	10	[44]	RETURN   	3 2
	11	[45]	RETURN   	0 1

function <./moonscript/parse.lua:47,53> (14 instructions, 56 bytes at 0x7f9c3ec07ad0)
3 params, 7 slots, 1 upvalue, 4 locals, 3 constants, 0 functions
	1	[48]	GETUPVAL 	3 0	; _indent
	2	[48]	SELF     	3 3 -1	; "top"
	3	[48]	CALL     	3 2 2
	4	[49]	EQ       	1 3 -2	; - -1
	5	[49]	JMP      	8	; to 14
	6	[49]	LT       	0 3 2
	7	[49]	JMP      	6	; to 14
	8	[50]	GETUPVAL 	4 0	; _indent
	9	[50]	SELF     	4 4 -3	; "push"
	10	[50]	MOVE     	6 2
	11	[50]	CALL     	4 3 1
	12	[51]	LOADBOOL 	4 1 0
	13	[51]	RETURN   	4 2
	14	[53]	RETURN   	0 1

function <./moonscript/parse.lua:55,58> (7 instructions, 28 bytes at 0x7f9c3ec07f90)
3 params, 6 slots, 1 upvalue, 3 locals, 1 constant, 0 functions
	1	[56]	GETUPVAL 	3 0	; _indent
	2	[56]	SELF     	3 3 -1	; "push"
	3	[56]	MOVE     	5 2
	4	[56]	CALL     	3 3 1
	5	[57]	LOADBOOL 	3 1 0
	6	[57]	RETURN   	3 2
	7	[58]	RETURN   	0 1

function <./moonscript/parse.lua:60,63> (9 instructions, 36 bytes at 0x7f9c3ec084d0)
0 params, 3 slots, 1 upvalue, 0 locals, 3 constants, 0 functions
	1	[61]	GETGLOBAL	0 -1	; assert
	2	[61]	GETUPVAL 	1 0	; _indent
	3	[61]	SELF     	1 1 -2	; "pop"
	4	[61]	CALL     	1 2 2
	5	[61]	LOADK    	2 -3	; "unexpected outdent"
	6	[61]	CALL     	0 3 1
	7	[62]	LOADBOOL 	0 1 0
	8	[62]	RETURN   	0 2
	9	[63]	RETURN   	0 1

function <./moonscript/parse.lua:65,71> (13 instructions, 52 bytes at 0x7f9c3ec07210)
3 params, 6 slots, 1 upvalue, 4 locals, 2 constants, 0 functions
	1	[66]	GETUPVAL 	3 0	; _do_stack
	2	[66]	SELF     	3 3 -1	; "top"
	3	[66]	CALL     	3 2 2
	4	[67]	EQ       	1 3 -2	; - nil
	5	[67]	JMP      	2	; to 8
	6	[67]	TEST     	3 0 0
	7	[67]	JMP      	3	; to 11
	8	[68]	LOADBOOL 	4 1 0
	9	[68]	MOVE     	5 2
	10	[68]	RETURN   	4 3
	11	[70]	LOADBOOL 	4 0 0
	12	[70]	RETURN   	4 2
	13	[71]	RETURN   	0 1

function <./moonscript/parse.lua:73,76> (7 instructions, 28 bytes at 0x7f9c3ec08d10)
0 params, 3 slots, 1 upvalue, 0 locals, 1 constant, 0 functions
	1	[74]	GETUPVAL 	0 0	; _do_stack
	2	[74]	SELF     	0 0 -1	; "push"
	3	[74]	LOADBOOL 	2 0 0
	4	[74]	CALL     	0 3 1
	5	[75]	LOADBOOL 	0 1 0
	6	[75]	RETURN   	0 2
	7	[76]	RETURN   	0 1

function <./moonscript/parse.lua:78,81> (13 instructions, 52 bytes at 0x7f9c3ec090f0)
0 params, 3 slots, 1 upvalue, 0 locals, 4 constants, 0 functions
	1	[79]	GETGLOBAL	0 -1	; assert
	2	[79]	GETUPVAL 	1 0	; _do_stack
	3	[79]	SELF     	1 1 -2	; "pop"
	4	[79]	CALL     	1 2 2
	5	[79]	EQ       	0 1 -3	; - nil
	6	[79]	JMP      	1	; to 8
	7	[79]	LOADBOOL 	1 0 1
	8	[79]	LOADBOOL 	1 1 0
	9	[79]	LOADK    	2 -4	; "unexpected do pop"
	10	[79]	CALL     	0 3 1
	11	[80]	LOADBOOL 	0 1 0
	12	[80]	RETURN   	0 2
	13	[81]	RETURN   	0 1

function <./moonscript/parse.lua:86,89> (9 instructions, 36 bytes at 0x7f9c3ec08450)
1 param, 3 slots, 3 upvalues, 1 local, 1 constant, 0 functions
	1	[87]	GETUPVAL 	1 0	; keywords
	2	[87]	SETTABLE 	1 0 -1	; - true
	3	[88]	GETUPVAL 	1 1	; Space
	4	[88]	MUL      	1 1 0
	5	[88]	GETUPVAL 	2 2	; AlphaNum
	6	[88]	UNM      	2 2
	7	[88]	MUL      	1 1 2
	8	[88]	RETURN   	1 2
	9	[89]	RETURN   	0 1

function <./moonscript/parse.lua:91,98> (17 instructions, 68 bytes at 0x7f9c3ec097f0)
1 param, 5 slots, 4 upvalues, 2 locals, 3 constants, 0 functions
	1	[92]	GETUPVAL 	1 0	; Space
	2	[92]	GETUPVAL 	2 1	; C
	3	[92]	MOVE     	3 0
	4	[92]	CALL     	2 2 2
	5	[92]	MUL      	1 1 2
	6	[93]	SELF     	2 0 -1	; "match"
	7	[93]	LOADK    	4 -2	; "^%w*$"
	8	[93]	CALL     	2 3 2
	9	[93]	TEST     	2 0 0
	10	[93]	JMP      	5	; to 16
	11	[94]	GETUPVAL 	2 2	; keywords
	12	[94]	SETTABLE 	2 0 -3	; - true
	13	[95]	GETUPVAL 	2 3	; AlphaNum
	14	[95]	UNM      	2 2
	15	[95]	MUL      	1 1 2
	16	[97]	RETURN   	1 2
	17	[98]	RETURN   	0 1

function <./moonscript/parse.lua:99,104> (9 instructions, 36 bytes at 0x7f9c3ec09c30)
3 params, 4 slots, 1 upvalue, 3 locals, 0 constants, 0 functions
	1	[100]	GETUPVAL 	3 0	; keywords
	2	[100]	GETTABLE 	3 3 2
	3	[100]	TEST     	3 0 0
	4	[100]	JMP      	2	; to 7
	5	[101]	LOADBOOL 	3 0 0
	6	[101]	RETURN   	3 2
	7	[103]	LOADBOOL 	3 1 0
	8	[103]	RETURN   	3 2
	9	[104]	RETURN   	0 1

function <./moonscript/parse.lua:206,238> (19 instructions, 76 bytes at 0x7f9c3ec09b10)
0 params, 5 slots, 7 upvalues, 3 locals, 2 constants, 1 function
	1	[207]	GETUPVAL 	0 0	; build_grammar
	2	[207]	CALL     	0 1 3
	3	[208]	GETUPVAL 	2 1	; White
	4	[208]	MUL      	2 2 0
	5	[208]	GETUPVAL 	3 1	; White
	6	[208]	MUL      	2 2 3
	7	[208]	MUL      	2 2 -1	; - -1
	8	[209]	NEWTABLE 	3 0 1
	9	[236]	CLOSURE  	4 0	; 0x7f9c3ec0aad0
	10	[236]	MOVE     	0 2
	11	[236]	MOVE     	0 1
	12	[236]	GETUPVAL 	0 2	; unpack
	13	[236]	GETUPVAL 	0 3	; pos_to_line
	14	[236]	GETUPVAL 	0 4	; get_line
	15	[236]	GETUPVAL 	0 5	; err_msg
	16	[236]	GETUPVAL 	0 6	; trim
	17	[236]	SETTABLE 	3 -2 4	; "match" -
	18	[237]	RETURN   	3 2
	19	[238]	RETURN   	0 1

function <./moonscript/parse.lua:210,236> (59 instructions, 236 bytes at 0x7f9c3ec0aad0)
2 params, 16 slots, 7 upvalues, 10 locals, 8 constants, 2 functions
	1	[212]	GETGLOBAL	3 -1	; xpcall
	2	[214]	CLOSURE  	4 0	; 0x7f9c3ec0a580
	3	[214]	MOVE     	0 2
	4	[214]	GETUPVAL 	0 0	; file_grammar
	5	[214]	MOVE     	0 1
	6	[216]	CLOSURE  	5 1	; 0x7f9c3ec0b0c0
	7	[212]	CALL     	3 3 3
	8	[217]	GETGLOBAL	5 -2	; type
	9	[217]	MOVE     	6 4
	10	[217]	CALL     	5 2 2
	11	[217]	EQ       	0 5 -3	; - "string"
	12	[217]	JMP      	3	; to 16
	13	[218]	LOADNIL  	5 5
	14	[218]	MOVE     	6 4
	15	[218]	RETURN   	5 3
	16	[220]	TEST     	2 0 1
	17	[220]	JMP      	40	; to 58
	18	[221]	LOADNIL  	5 5
	19	[222]	GETUPVAL 	6 1	; state
	20	[222]	GETTABLE 	6 6 -4	; "last_pos"
	21	[223]	TEST     	4 0 0
	22	[223]	JMP      	12	; to 35
	23	[224]	LOADNIL  	7 7
	24	[225]	GETUPVAL 	8 2	; unpack
	25	[225]	MOVE     	9 4
	26	[225]	CALL     	8 2 3
	27	[225]	MOVE     	5 9
	28	[225]	MOVE     	7 8
	29	[226]	TEST     	5 0 0
	30	[226]	JMP      	3	; to 34
	31	[227]	LOADK    	8 -5	; " "
	32	[227]	MOVE     	9 5
	33	[227]	CONCAT   	5 8 9
	34	[229]	GETTABLE 	6 7 -6	; -1
	35	[231]	GETUPVAL 	7 3	; pos_to_line
	36	[231]	MOVE     	8 1
	37	[231]	MOVE     	9 6
	38	[231]	CALL     	7 3 2
	39	[232]	GETUPVAL 	8 4	; get_line
	40	[232]	MOVE     	9 1
	41	[232]	MOVE     	10 7
	42	[232]	CALL     	8 3 2
	43	[232]	TEST     	8 0 1
	44	[232]	JMP      	1	; to 46
	45	[232]	LOADK    	8 -7	; ""
	46	[233]	LOADNIL  	9 9
	47	[233]	GETUPVAL 	10 5	; err_msg
	48	[233]	SELF     	10 10 -8	; "format"
	49	[233]	TESTSET  	12 5 1
	50	[233]	JMP      	1	; to 52
	51	[233]	LOADK    	12 -7	; ""
	52	[233]	MOVE     	13 7
	53	[233]	GETUPVAL 	14 6	; trim
	54	[233]	MOVE     	15 8
	55	[233]	CALL     	14 2 0
	56	[233]	CALL     	10 0 0
	57	[233]	RETURN   	9 0
	58	[235]	RETURN   	2 2
	59	[236]	RETURN   	0 1

function <./moonscript/parse.lua:212,214> (6 instructions, 24 bytes at 0x7f9c3ec0a580)
0 params, 3 slots, 3 upvalues, 0 locals, 1 constant, 0 functions
	1	[213]	GETUPVAL 	0 1	; file_grammar
	2	[213]	SELF     	0 0 -1	; "match"
	3	[213]	GETUPVAL 	2 2	; str
	4	[213]	CALL     	0 3 2
	5	[213]	SETUPVAL 	0 0	; tree
	6	[214]	RETURN   	0 1

function <./moonscript/parse.lua:214,216> (7 instructions, 28 bytes at 0x7f9c3ec0b0c0)
1 param, 4 slots, 0 upvalues, 1 local, 3 constants, 0 functions
	1	[215]	GETGLOBAL	1 -1	; debug
	2	[215]	GETTABLE 	1 1 -2	; "traceback"
	3	[215]	MOVE     	2 0
	4	[215]	LOADK    	3 -3	; 2
	5	[215]	TAILCALL 	1 3 0
	6	[215]	RETURN   	1 0
	7	[216]	RETURN   	0 1

function <./moonscript/parse.lua:242,244> (7 instructions, 28 bytes at 0x7f9c3ec0b4c0)
1 param, 4 slots, 1 upvalue, 1 local, 1 constant, 0 functions
	1	[243]	GETUPVAL 	1 0	; file_parser
	2	[243]	CALL     	1 1 2
	3	[243]	SELF     	1 1 -1	; "match"
	4	[243]	MOVE     	3 0
	5	[243]	TAILCALL 	1 3 0
	6	[243]	RETURN   	1 0
	7	[244]	RETURN   	0 1
