
main <./moonscript/transform/statements.lua:0,0> (64 instructions, 256 bytes at 0x7ff631c068d0)
0+ params, 13 slots, 0 upvalues, 13 locals, 21 constants, 7 functions
	1	[1]	GETGLOBAL	0 -1	; require
	2	[1]	LOADK    	1 -2	; "moonscript.types"
	3	[1]	CALL     	0 2 2
	4	[2]	LOADNIL  	1 4
	5	[3]	GETTABLE 	5 0 -3	; "ntype"
	6	[3]	GETTABLE 	6 0 -4	; "mtype"
	7	[3]	GETTABLE 	7 0 -5	; "is_value"
	8	[3]	GETTABLE 	4 0 -6	; "NOOP"
	9	[3]	MOVE     	3 7
	10	[3]	MOVE     	2 6
	11	[3]	MOVE     	1 5
	12	[4]	LOADNIL  	5 5
	13	[5]	GETGLOBAL	6 -1	; require
	14	[5]	LOADK    	7 -7	; "moonscript.transform.comprehension"
	15	[5]	CALL     	6 2 2
	16	[5]	GETTABLE 	5 6 -8	; "comprehension_has_value"
	17	[6]	LOADNIL  	6 7
	18	[9]	NEWTABLE 	8 0 1
	19	[12]	CLOSURE  	9 0	; 0x7ff631c06ab0
	20	[12]	SETTABLE 	8 -9 9	; "call" -
	21	[14]	SETTABLE 	8 -10 8	; "__index" -
	22	[15]	GETGLOBAL	9 -11	; setmetatable
	23	[15]	NEWTABLE 	10 0 3
	24	[19]	CLOSURE  	11 1	; 0x7ff631c07330
	25	[19]	SETTABLE 	10 -12 11	; "__init" -
	26	[20]	SETTABLE 	10 -13 8	; "__base" -
	27	[21]	SETTABLE 	10 -14 -15	; "__name" "Run"
	28	[22]	NEWTABLE 	11 0 2
	29	[23]	SETTABLE 	11 -10 8	; "__index" -
	30	[28]	CLOSURE  	12 2	; 0x7ff631c07520
	31	[28]	MOVE     	0 8
	32	[28]	SETTABLE 	11 -16 12	; "__call" -
	33	[15]	CALL     	9 3 2
	34	[29]	MOVE     	7 9
	35	[30]	SETTABLE 	8 -17 7	; "__class" -
	36	[31]	MOVE     	6 7
	37	[31]	CLOSE    	7
	38	[33]	LOADNIL  	7 7
	39	[47]	CLOSURE  	7 3	; 0x7ff631c07050
	40	[47]	MOVE     	0 2
	41	[47]	MOVE     	0 6
	42	[47]	MOVE     	0 1
	43	[47]	MOVE     	0 7
	44	[48]	LOADNIL  	8 8
	45	[71]	CLOSURE  	8 4	; 0x7ff631c071d0
	46	[71]	MOVE     	0 7
	47	[72]	LOADNIL  	9 9
	48	[76]	CLOSURE  	9 5	; 0x7ff631c087e0
	49	[76]	MOVE     	0 1
	50	[77]	LOADNIL  	10 10
	51	[108]	CLOSURE  	10 6	; 0x7ff631c08b90
	52	[108]	MOVE     	0 1
	53	[108]	MOVE     	0 0
	54	[108]	MOVE     	0 3
	55	[108]	MOVE     	0 4
	56	[108]	MOVE     	0 5
	57	[109]	NEWTABLE 	11 0 5
	58	[110]	SETTABLE 	11 -15 6	; "Run" -
	59	[111]	SETTABLE 	11 -18 7	; "last_stm" -
	60	[112]	SETTABLE 	11 -19 8	; "transform_last_stm" -
	61	[113]	SETTABLE 	11 -20 9	; "chain_is_stub" -
	62	[114]	SETTABLE 	11 -21 10	; "implicitly_return" -
	63	[115]	RETURN   	11 2
	64	[115]	RETURN   	0 1

function <./moonscript/transform/statements.lua:10,12> (5 instructions, 20 bytes at 0x7ff631c06ab0)
2 params, 4 slots, 0 upvalues, 2 locals, 1 constant, 0 functions
	1	[11]	GETTABLE 	2 0 -1	; "fn"
	2	[11]	MOVE     	3 1
	3	[11]	TAILCALL 	2 2 0
	4	[11]	RETURN   	2 0
	5	[12]	RETURN   	0 1

function <./moonscript/transform/statements.lua:16,19> (3 instructions, 12 bytes at 0x7ff631c07330)
2 params, 2 slots, 0 upvalues, 2 locals, 3 constants, 0 functions
	1	[17]	SETTABLE 	0 -1 1	; "fn" -
	2	[18]	SETTABLE 	0 -2 -3	; 1 "run"
	3	[19]	RETURN   	0 1

function <./moonscript/transform/statements.lua:24,28> (10 instructions, 40 bytes at 0x7ff631c07520)
1+ param, 6 slots, 1 upvalue, 3 locals, 2 constants, 0 functions
	1	[25]	GETGLOBAL	2 -1	; setmetatable
	2	[25]	NEWTABLE 	3 0 0
	3	[25]	GETUPVAL 	4 0	; _base_0
	4	[25]	CALL     	2 3 2
	5	[26]	GETTABLE 	3 0 -2	; "__init"
	6	[26]	MOVE     	4 2
	7	[26]	VARARG   	5 0
	8	[26]	CALL     	3 0 1
	9	[27]	RETURN   	2 2
	10	[28]	RETURN   	0 1

function <./moonscript/transform/statements.lua:34,47> (31 instructions, 124 bytes at 0x7ff631c07050)
1 param, 9 slots, 4 upvalues, 7 locals, 5 constants, 0 functions
	1	[35]	LOADK    	1 -1	; 0
	2	[36]	LEN      	2 0
	3	[36]	LOADK    	3 -2	; 1
	4	[36]	LOADK    	4 -3	; -1
	5	[36]	FORPREP  	2 20	; to 26
	6	[37]	GETTABLE 	6 0 5
	7	[38]	TEST     	6 0 0
	8	[38]	JMP      	17	; to 26
	9	[38]	GETUPVAL 	7 0	; mtype
	10	[38]	MOVE     	8 6
	11	[38]	CALL     	7 2 2
	12	[38]	GETUPVAL 	8 1	; Run
	13	[38]	EQ       	1 7 8
	14	[38]	JMP      	11	; to 26
	15	[39]	GETUPVAL 	7 2	; ntype
	16	[39]	MOVE     	8 6
	17	[39]	CALL     	7 2 2
	18	[39]	EQ       	0 7 -4	; - "group"
	19	[39]	JMP      	4	; to 24
	20	[40]	GETUPVAL 	7 3	; last_stm
	21	[40]	GETTABLE 	8 6 -5	; 2
	22	[40]	TAILCALL 	7 2 0
	23	[40]	RETURN   	7 0
	24	[42]	MOVE     	1 5
	25	[43]	JMP      	1	; to 27
	26	[36]	FORLOOP  	2 -21	; to 6
	27	[46]	GETTABLE 	2 0 1
	28	[46]	MOVE     	3 1
	29	[46]	MOVE     	4 0
	30	[46]	RETURN   	2 4
	31	[47]	RETURN   	0 1

function <./moonscript/transform/statements.lua:49,71> (15 instructions, 60 bytes at 0x7ff631c071d0)
2 params, 7 slots, 1 upvalue, 5 locals, 2 constants, 1 function
	1	[50]	GETUPVAL 	2 0	; last_stm
	2	[50]	MOVE     	3 0
	3	[50]	CALL     	2 2 4
	4	[51]	EQ       	1 4 0
	5	[51]	JMP      	3	; to 9
	6	[52]	GETGLOBAL	5 -1	; error
	7	[52]	LOADK    	6 -2	; "cannot transform last node in group"
	8	[52]	CALL     	5 2 1
	9	[70]	CLOSURE  	5 0	; 0x7ff631c08090
	10	[70]	MOVE     	0 0
	11	[70]	MOVE     	0 3
	12	[70]	MOVE     	0 1
	13	[70]	TAILCALL 	5 1 0
	14	[70]	RETURN   	5 0
	15	[71]	RETURN   	0 1

function <./moonscript/transform/statements.lua:54,70> (22 instructions, 88 bytes at 0x7ff631c08090)
0 params, 11 slots, 3 upvalues, 7 locals, 3 constants, 0 functions
	1	[55]	NEWTABLE 	0 0 0
	2	[56]	LOADK    	1 -1	; 1
	3	[57]	GETGLOBAL	2 -2	; ipairs
	4	[57]	GETUPVAL 	3 0	; stms
	5	[57]	CALL     	2 2 4
	6	[57]	JMP      	12	; to 19
	7	[58]	GETUPVAL 	7 1	; last_idx
	8	[58]	EQ       	0 5 7
	9	[58]	JMP      	7	; to 17
	10	[59]	NEWTABLE 	7 3 0
	11	[60]	LOADK    	8 -3	; "transform"
	12	[61]	MOVE     	9 6
	13	[63]	GETUPVAL 	10 2	; fn
	14	[63]	SETLIST  	7 3 1	; 1
	15	[63]	SETTABLE 	0 1 7
	16	[63]	JMP      	1	; to 18
	17	[65]	SETTABLE 	0 1 6
	18	[67]	ADD      	1 1 -1	; - 1
	19	[57]	TFORLOOP 	2 2
	20	[67]	JMP      	-14	; to 7
	21	[69]	RETURN   	0 2
	22	[70]	RETURN   	0 1

function <./moonscript/transform/statements.lua:73,76> (13 instructions, 52 bytes at 0x7ff631c087e0)
1 param, 4 slots, 1 upvalue, 2 locals, 1 constant, 0 functions
	1	[74]	LEN      	1 0
	2	[74]	GETTABLE 	1 0 1
	3	[75]	TESTSET  	2 1 0
	4	[75]	JMP      	7	; to 12
	5	[75]	GETUPVAL 	2 0	; ntype
	6	[75]	MOVE     	3 1
	7	[75]	CALL     	2 2 2
	8	[75]	EQ       	1 2 -1	; - "colon"
	9	[75]	JMP      	1	; to 11
	10	[75]	LOADBOOL 	2 0 1
	11	[75]	LOADBOOL 	2 1 0
	12	[75]	RETURN   	2 2
	13	[76]	RETURN   	0 1

function <./moonscript/transform/statements.lua:78,108> (13 instructions, 52 bytes at 0x7ff631c08b90)
1 param, 3 slots, 5 upvalues, 3 locals, 0 constants, 1 function
	1	[79]	LOADBOOL 	1 1 0
	2	[80]	LOADNIL  	2 2
	3	[106]	CLOSURE  	2 0	; 0x7ff631c08eb0
	4	[106]	GETUPVAL 	0 0	; ntype
	5	[106]	MOVE     	0 0
	6	[106]	GETUPVAL 	0 1	; types
	7	[106]	MOVE     	0 1
	8	[106]	MOVE     	0 2
	9	[106]	GETUPVAL 	0 2	; is_value
	10	[106]	GETUPVAL 	0 3	; NOOP
	11	[106]	GETUPVAL 	0 4	; comprehension_has_value
	12	[107]	RETURN   	2 2
	13	[108]	RETURN   	0 1

function <./moonscript/transform/statements.lua:81,106> (68 instructions, 272 bytes at 0x7ff631c08eb0)
1 param, 5 slots, 8 upvalues, 2 locals, 9 constants, 0 functions
	1	[82]	GETUPVAL 	1 0	; ntype
	2	[82]	MOVE     	2 0
	3	[82]	CALL     	1 2 2
	4	[83]	EQ       	0 1 -1	; - "decorated"
	5	[83]	JMP      	10	; to 16
	6	[84]	GETUPVAL 	2 1	; scope
	7	[84]	GETTABLE 	2 2 -2	; "transform"
	8	[84]	GETTABLE 	2 2 -3	; "statement"
	9	[84]	MOVE     	3 0
	10	[84]	CALL     	2 2 2
	11	[84]	MOVE     	0 2
	12	[85]	GETUPVAL 	2 0	; ntype
	13	[85]	MOVE     	3 0
	14	[85]	CALL     	2 2 2
	15	[85]	MOVE     	1 2
	16	[87]	GETUPVAL 	2 2	; types
	17	[87]	GETTABLE 	2 2 -4	; "cascading"
	18	[87]	GETTABLE 	2 2 1
	19	[87]	TEST     	2 0 0
	20	[87]	JMP      	10	; to 31
	21	[88]	LOADBOOL 	2 0 0
	22	[88]	SETUPVAL 	2 3	; is_top
	23	[89]	GETUPVAL 	2 1	; scope
	24	[89]	GETTABLE 	2 2 -2	; "transform"
	25	[89]	GETTABLE 	2 2 -3	; "statement"
	26	[89]	MOVE     	3 0
	27	[89]	GETUPVAL 	4 4	; fn
	28	[89]	TAILCALL 	2 3 0
	29	[89]	RETURN   	2 0
	30	[89]	JMP      	37	; to 68
	31	[90]	GETUPVAL 	2 2	; types
	32	[90]	GETTABLE 	2 2 -5	; "manual_return"
	33	[90]	GETTABLE 	2 2 1
	34	[90]	TEST     	2 0 1
	35	[90]	JMP      	5	; to 41
	36	[90]	GETUPVAL 	2 5	; is_value
	37	[90]	MOVE     	3 0
	38	[90]	CALL     	2 2 2
	39	[90]	TEST     	2 0 1
	40	[90]	JMP      	13	; to 54
	41	[91]	GETUPVAL 	2 3	; is_top
	42	[91]	TEST     	2 0 0
	43	[91]	JMP      	8	; to 52
	44	[91]	EQ       	0 1 -6	; - "return"
	45	[91]	JMP      	6	; to 52
	46	[91]	GETTABLE 	2 0 -7	; 2
	47	[91]	EQ       	0 2 -8	; - ""
	48	[91]	JMP      	3	; to 52
	49	[92]	GETUPVAL 	2 6	; NOOP
	50	[92]	RETURN   	2 2
	51	[92]	JMP      	16	; to 68
	52	[94]	RETURN   	0 2
	53	[95]	JMP      	14	; to 68
	54	[97]	EQ       	0 1 -9	; - "comprehension"
	55	[97]	JMP      	7	; to 63
	56	[97]	GETUPVAL 	2 7	; comprehension_has_value
	57	[97]	MOVE     	3 0
	58	[97]	CALL     	2 2 2
	59	[97]	TEST     	2 0 1
	60	[97]	JMP      	2	; to 63
	61	[98]	RETURN   	0 2
	62	[98]	JMP      	5	; to 68
	63	[100]	NEWTABLE 	2 2 0
	64	[101]	LOADK    	3 -6	; "return"
	65	[103]	MOVE     	4 0
	66	[103]	SETLIST  	2 2 1	; 1
	67	[103]	RETURN   	2 2
	68	[106]	RETURN   	0 1
