
main <./moonscript/transform/transformer.lua:0,0> (40 instructions, 160 bytes at 0x7fd7174068d0)
0+ params, 8 slots, 0 upvalues, 4 locals, 15 constants, 7 functions
	1	[2]	GETGLOBAL	1 -1	; require
	2	[2]	LOADK    	2 -2	; "moonscript.types"
	3	[2]	CALL     	1 2 2
	4	[2]	GETTABLE 	0 1 -3	; "ntype"
	5	[3]	LOADNIL  	1 2
	6	[6]	NEWTABLE 	3 0 5
	7	[18]	CLOSURE  	4 0	; 0x7fd717406bd0
	8	[18]	MOVE     	0 0
	9	[18]	SETTABLE 	3 -4 4	; "transform_once" -
	10	[38]	CLOSURE  	4 1	; 0x7fd7174072d0
	11	[38]	MOVE     	0 0
	12	[38]	SETTABLE 	3 -5 4	; "transform" -
	13	[43]	CLOSURE  	4 2	; 0x7fd717407660
	14	[43]	SETTABLE 	3 -6 4	; "bind" -
	15	[46]	CLOSURE  	4 3	; 0x7fd7174078f0
	16	[46]	SETTABLE 	3 -7 4	; "__call" -
	17	[49]	CLOSURE  	4 4	; 0x7fd717407b60
	18	[49]	MOVE     	0 0
	19	[49]	SETTABLE 	3 -8 4	; "can_transform" -
	20	[51]	SETTABLE 	3 -9 3	; "__index" -
	21	[52]	GETGLOBAL	4 -10	; setmetatable
	22	[52]	NEWTABLE 	5 0 3
	23	[58]	CLOSURE  	6 5	; 0x7fd717407250
	24	[58]	SETTABLE 	5 -11 6	; "__init" -
	25	[59]	SETTABLE 	5 -12 3	; "__base" -
	26	[60]	SETTABLE 	5 -13 -14	; "__name" "Transformer"
	27	[61]	NEWTABLE 	6 0 2
	28	[62]	SETTABLE 	6 -9 3	; "__index" -
	29	[67]	CLOSURE  	7 6	; 0x7fd7174065c0
	30	[67]	MOVE     	0 3
	31	[67]	SETTABLE 	6 -7 7	; "__call" -
	32	[52]	CALL     	4 3 2
	33	[68]	MOVE     	2 4
	34	[69]	SETTABLE 	3 -15 2	; "__class" -
	35	[70]	MOVE     	1 2
	36	[70]	CLOSE    	2
	37	[72]	NEWTABLE 	2 0 1
	38	[73]	SETTABLE 	2 -14 1	; "Transformer" -
	39	[74]	RETURN   	2 2
	40	[74]	RETURN   	0 1

function <./moonscript/transform/transformer.lua:7,18> (26 instructions, 104 bytes at 0x7fd717406bd0)
3+ params, 9 slots, 1 upvalue, 5 locals, 3 constants, 0 functions
	1	[8]	GETTABLE 	4 0 -1	; "seen_nodes"
	2	[8]	GETTABLE 	4 4 2
	3	[8]	TEST     	4 0 0
	4	[8]	JMP      	1	; to 6
	5	[9]	RETURN   	2 2
	6	[11]	GETTABLE 	4 0 -1	; "seen_nodes"
	7	[11]	SETTABLE 	4 2 -2	; - true
	8	[12]	GETTABLE 	4 0 -3	; "transformers"
	9	[12]	GETUPVAL 	5 0	; ntype
	10	[12]	MOVE     	6 2
	11	[12]	CALL     	5 2 2
	12	[12]	GETTABLE 	4 4 5
	13	[13]	TEST     	4 0 0
	14	[13]	JMP      	10	; to 25
	15	[14]	MOVE     	5 4
	16	[14]	MOVE     	6 1
	17	[14]	MOVE     	7 2
	18	[14]	VARARG   	8 0
	19	[14]	CALL     	5 0 2
	20	[14]	TEST     	5 0 1
	21	[14]	JMP      	1	; to 23
	22	[14]	MOVE     	5 2
	23	[14]	RETURN   	5 2
	24	[14]	JMP      	1	; to 26
	25	[16]	RETURN   	2 2
	26	[18]	RETURN   	0 1

function <./moonscript/transform/transformer.lua:19,38> (32 instructions, 128 bytes at 0x7fd7174072d0)
3+ params, 10 slots, 1 upvalue, 6 locals, 3 constants, 0 functions
	1	[20]	GETTABLE 	4 0 -1	; "seen_nodes"
	2	[20]	GETTABLE 	4 4 2
	3	[20]	TEST     	4 0 0
	4	[20]	JMP      	1	; to 6
	5	[21]	RETURN   	2 2
	6	[23]	GETTABLE 	4 0 -1	; "seen_nodes"
	7	[23]	SETTABLE 	4 2 -2	; - true
	8	[25]	GETTABLE 	4 0 -3	; "transformers"
	9	[25]	GETUPVAL 	5 0	; ntype
	10	[25]	MOVE     	6 2
	11	[25]	CALL     	5 2 2
	12	[25]	GETTABLE 	4 4 5
	13	[26]	LOADNIL  	5 5
	14	[27]	TEST     	4 0 0
	15	[27]	JMP      	9	; to 25
	16	[28]	MOVE     	6 4
	17	[28]	MOVE     	7 1
	18	[28]	MOVE     	8 2
	19	[28]	VARARG   	9 0
	20	[28]	CALL     	6 0 2
	21	[28]	TESTSET  	5 6 1
	22	[28]	JMP      	1	; to 24
	23	[28]	MOVE     	5 2
	24	[28]	JMP      	1	; to 26
	25	[30]	MOVE     	5 2
	26	[32]	EQ       	0 5 2
	27	[32]	JMP      	1	; to 29
	28	[33]	RETURN   	2 2
	29	[35]	MOVE     	2 5
	30	[35]	JMP      	-23	; to 8
	31	[37]	RETURN   	2 2
	32	[38]	RETURN   	0 1

function <./moonscript/transform/transformer.lua:39,43> (5 instructions, 20 bytes at 0x7fd717407660)
2 params, 3 slots, 0 upvalues, 2 locals, 0 constants, 1 function
	1	[42]	CLOSURE  	2 0	; 0x7fd7174077d0
	2	[42]	MOVE     	0 0
	3	[42]	MOVE     	0 1
	4	[42]	RETURN   	2 2
	5	[43]	RETURN   	0 1

function <./moonscript/transform/transformer.lua:40,42> (7 instructions, 28 bytes at 0x7fd7174077d0)
0+ params, 5 slots, 2 upvalues, 1 local, 1 constant, 0 functions
	1	[41]	GETUPVAL 	1 0	; self
	2	[41]	SELF     	1 1 -1	; "transform"
	3	[41]	GETUPVAL 	3 1	; scope
	4	[41]	VARARG   	4 0
	5	[41]	TAILCALL 	1 0 0
	6	[41]	RETURN   	1 0
	7	[42]	RETURN   	0 1

function <./moonscript/transform/transformer.lua:44,46> (5 instructions, 20 bytes at 0x7fd7174078f0)
1+ param, 5 slots, 0 upvalues, 2 locals, 1 constant, 0 functions
	1	[45]	SELF     	2 0 -1	; "transform"
	2	[45]	VARARG   	4 0
	3	[45]	TAILCALL 	2 0 0
	4	[45]	RETURN   	2 0
	5	[46]	RETURN   	0 1

function <./moonscript/transform/transformer.lua:47,49> (11 instructions, 44 bytes at 0x7fd717407b60)
2 params, 5 slots, 1 upvalue, 2 locals, 2 constants, 0 functions
	1	[48]	GETTABLE 	2 0 -1	; "transformers"
	2	[48]	GETUPVAL 	3 0	; ntype
	3	[48]	MOVE     	4 1
	4	[48]	CALL     	3 2 2
	5	[48]	GETTABLE 	2 2 3
	6	[48]	EQ       	0 2 -2	; - nil
	7	[48]	JMP      	1	; to 9
	8	[48]	LOADBOOL 	2 0 1
	9	[48]	LOADBOOL 	2 1 0
	10	[48]	RETURN   	2 2
	11	[49]	RETURN   	0 1

function <./moonscript/transform/transformer.lua:53,58> (8 instructions, 32 bytes at 0x7fd717407250)
2 params, 5 slots, 0 upvalues, 2 locals, 5 constants, 0 functions
	1	[54]	SETTABLE 	0 -1 1	; "transformers" -
	2	[55]	GETGLOBAL	2 -3	; setmetatable
	3	[55]	NEWTABLE 	3 0 0
	4	[55]	NEWTABLE 	4 0 1
	5	[56]	SETTABLE 	4 -4 -5	; "__mode" "k"
	6	[55]	CALL     	2 3 2
	7	[57]	SETTABLE 	0 -2 2	; "seen_nodes" -
	8	[58]	RETURN   	0 1

function <./moonscript/transform/transformer.lua:63,67> (10 instructions, 40 bytes at 0x7fd7174065c0)
1+ param, 6 slots, 1 upvalue, 3 locals, 2 constants, 0 functions
	1	[64]	GETGLOBAL	2 -1	; setmetatable
	2	[64]	NEWTABLE 	3 0 0
	3	[64]	GETUPVAL 	4 0	; _base_0
	4	[64]	CALL     	2 3 2
	5	[65]	GETTABLE 	3 0 -2	; "__init"
	6	[65]	MOVE     	4 2
	7	[65]	VARARG   	5 0
	8	[65]	CALL     	3 0 1
	9	[66]	RETURN   	2 2
	10	[67]	RETURN   	0 1
