
main <./moonscript/util.lua:0,0> (73 instructions, 292 bytes at 0x7fd6e54068a0)
0+ params, 16 slots, 0 upvalues, 15 locals, 18 constants, 14 functions
	1	[2]	GETGLOBAL	1 -1	; table
	2	[2]	GETTABLE 	0 1 -2	; "concat"
	3	[3]	GETGLOBAL	1 -3	; unpack
	4	[3]	TEST     	1 0 1
	5	[3]	JMP      	2	; to 8
	6	[3]	GETGLOBAL	1 -1	; table
	7	[3]	GETTABLE 	1 1 -3	; "unpack"
	8	[4]	GETGLOBAL	2 -4	; type
	9	[5]	NEWTABLE 	3 0 3
	10	[8]	CLOSURE  	4 0	; 0x7fd6e5406b60
	11	[8]	MOVE     	0 2
	12	[8]	SETTABLE 	3 -5 4	; "is_object" -
	13	[21]	CLOSURE  	4 1	; 0x7fd6e54071f0
	14	[21]	MOVE     	0 2
	15	[21]	SETTABLE 	3 -6 4	; "is_a" -
	16	[31]	CLOSURE  	4 2	; 0x7fd6e54074e0
	17	[31]	MOVE     	0 2
	18	[31]	SETTABLE 	3 -4 4	; "type" -
	19	[33]	LOADNIL  	4 4
	20	[40]	CLOSURE  	4 3	; 0x7fd6e5407850
	21	[41]	LOADNIL  	5 5
	22	[44]	CLOSURE  	5 4	; 0x7fd6e5407db0
	23	[45]	LOADNIL  	6 6
	24	[53]	CLOSURE  	6 5	; 0x7fd6e5406640
	25	[54]	LOADNIL  	7 7
	26	[62]	CLOSURE  	7 6	; 0x7fd6e5408330
	27	[62]	MOVE     	0 6
	28	[62]	MOVE     	0 5
	29	[62]	MOVE     	0 7
	30	[63]	LOADNIL  	8 8
	31	[76]	CLOSURE  	8 7	; 0x7fd6e54077d0
	32	[77]	LOADNIL  	9 9
	33	[111]	CLOSURE  	9 8	; 0x7fd6e5408f60
	34	[111]	MOVE     	0 2
	35	[111]	MOVE     	0 0
	36	[112]	LOADNIL  	10 10
	37	[147]	CLOSURE  	10 9	; 0x7fd6e5407750
	38	[147]	MOVE     	0 1
	39	[147]	MOVE     	0 4
	40	[147]	MOVE     	0 6
	41	[147]	MOVE     	0 7
	42	[147]	MOVE     	0 5
	43	[147]	MOVE     	0 0
	44	[148]	GETGLOBAL	11 -7	; setfenv
	45	[148]	TEST     	11 0 1
	46	[148]	JMP      	1	; to 48
	47	[164]	CLOSURE  	11 10	; 0x7fd6e5406ed0
	48	[165]	GETGLOBAL	12 -8	; getfenv
	49	[165]	TEST     	12 0 1
	50	[165]	JMP      	1	; to 52
	51	[178]	CLOSURE  	12 11	; 0x7fd6e540a040
	52	[179]	LOADNIL  	13 13
	53	[190]	CLOSURE  	13 12	; 0x7fd6e540a330
	54	[190]	MOVE     	0 2
	55	[190]	MOVE     	0 1
	56	[191]	LOADNIL  	14 14
	57	[198]	CLOSURE  	14 13	; 0x7fd6e540a6a0
	58	[199]	NEWTABLE 	15 0 13
	59	[200]	SETTABLE 	15 -9 3	; "moon" -
	60	[201]	SETTABLE 	15 -10 4	; "pos_to_line" -
	61	[202]	SETTABLE 	15 -11 7	; "get_closest_line" -
	62	[203]	SETTABLE 	15 -12 6	; "get_line" -
	63	[204]	SETTABLE 	15 -13 5	; "trim" -
	64	[205]	SETTABLE 	15 -14 8	; "split" -
	65	[206]	SETTABLE 	15 -15 9	; "dump" -
	66	[207]	SETTABLE 	15 -16 10	; "debug_posmap" -
	67	[208]	SETTABLE 	15 -8 12	; "getfenv" -
	68	[209]	SETTABLE 	15 -7 11	; "setfenv" -
	69	[210]	SETTABLE 	15 -17 13	; "get_options" -
	70	[211]	SETTABLE 	15 -3 1	; "unpack" -
	71	[212]	SETTABLE 	15 -18 14	; "safe_module" -
	72	[213]	RETURN   	15 2
	73	[213]	RETURN   	0 1

function <./moonscript/util.lua:6,8> (11 instructions, 44 bytes at 0x7fd6e5406b60)
1 param, 3 slots, 1 upvalue, 1 local, 2 constants, 0 functions
	1	[7]	GETUPVAL 	1 0	; type
	2	[7]	MOVE     	2 0
	3	[7]	CALL     	1 2 2
	4	[7]	EQ       	0 1 -1	; - "table"
	5	[7]	JMP      	2	; to 8
	6	[7]	GETTABLE 	1 0 -2	; "__class"
	7	[7]	JMP      	2	; to 10
	8	[7]	LOADBOOL 	1 0 1
	9	[7]	LOADBOOL 	1 1 0
	10	[7]	RETURN   	1 2
	11	[8]	RETURN   	0 1

function <./moonscript/util.lua:9,21> (19 instructions, 76 bytes at 0x7fd6e54071f0)
2 params, 4 slots, 1 upvalue, 3 locals, 3 constants, 0 functions
	1	[10]	GETUPVAL 	2 0	; type
	2	[10]	MOVE     	3 0
	3	[10]	CALL     	2 2 2
	4	[10]	EQ       	1 2 -1	; - "table"
	5	[10]	JMP      	2	; to 8
	6	[11]	LOADBOOL 	2 0 0
	7	[11]	RETURN   	2 2
	8	[13]	GETTABLE 	2 0 -2	; "__class"
	9	[14]	TEST     	2 0 0
	10	[14]	JMP      	6	; to 17
	11	[15]	EQ       	0 2 1
	12	[15]	JMP      	2	; to 15
	13	[16]	LOADBOOL 	3 1 0
	14	[16]	RETURN   	3 2
	15	[18]	GETTABLE 	2 2 -3	; "__parent"
	16	[18]	JMP      	-8	; to 9
	17	[20]	LOADBOOL 	3 0 0
	18	[20]	RETURN   	3 2
	19	[21]	RETURN   	0 1

function <./moonscript/util.lua:22,31> (11 instructions, 44 bytes at 0x7fd6e54074e0)
1 param, 3 slots, 1 upvalue, 3 locals, 2 constants, 0 functions
	1	[23]	GETUPVAL 	1 0	; type
	2	[23]	MOVE     	2 0
	3	[23]	CALL     	1 2 2
	4	[24]	EQ       	0 1 -1	; - "table"
	5	[24]	JMP      	4	; to 10
	6	[25]	GETTABLE 	2 0 -2	; "__class"
	7	[26]	TEST     	2 0 0
	8	[26]	JMP      	1	; to 10
	9	[27]	RETURN   	2 2
	10	[30]	RETURN   	1 2
	11	[31]	RETURN   	0 1

function <./moonscript/util.lua:34,40> (14 instructions, 56 bytes at 0x7fd6e5407850)
2 params, 9 slots, 0 upvalues, 7 locals, 4 constants, 0 functions
	1	[35]	LOADK    	2 -1	; 1
	2	[36]	SELF     	3 0 -2	; "sub"
	3	[36]	LOADK    	5 -1	; 1
	4	[36]	MOVE     	6 1
	5	[36]	CALL     	3 4 2
	6	[36]	SELF     	3 3 -3	; "gmatch"
	7	[36]	LOADK    	5 -4	; "\n"
	8	[36]	CALL     	3 3 4
	9	[36]	JMP      	1	; to 11
	10	[37]	ADD      	2 2 -1	; - 1
	11	[36]	TFORLOOP 	3 1
	12	[37]	JMP      	-3	; to 10
	13	[39]	RETURN   	2 2
	14	[40]	RETURN   	0 1

function <./moonscript/util.lua:42,44> (5 instructions, 20 bytes at 0x7fd6e5407db0)
1 param, 4 slots, 0 upvalues, 1 local, 2 constants, 0 functions
	1	[43]	SELF     	1 0 -1	; "match"
	2	[43]	LOADK    	3 -2	; "^%s*(.-)%s*$"
	3	[43]	TAILCALL 	1 3 0
	4	[43]	RETURN   	1 0
	5	[44]	RETURN   	0 1

function <./moonscript/util.lua:46,53> (11 instructions, 44 bytes at 0x7fd6e5406640)
2 params, 8 slots, 0 upvalues, 6 locals, 3 constants, 0 functions
	1	[47]	SELF     	2 0 -1	; "gmatch"
	2	[47]	LOADK    	4 -2	; "([^\n]*)\n?"
	3	[47]	CALL     	2 3 4
	4	[47]	JMP      	4	; to 9
	5	[48]	EQ       	0 1 -3	; - 1
	6	[48]	JMP      	1	; to 8
	7	[49]	RETURN   	5 2
	8	[51]	SUB      	1 1 -3	; - 1
	9	[47]	TFORLOOP 	2 1
	10	[51]	JMP      	-6	; to 5
	11	[53]	RETURN   	0 1

function <./moonscript/util.lua:55,62> (23 instructions, 92 bytes at 0x7fd6e5408330)
2 params, 6 slots, 3 upvalues, 3 locals, 2 constants, 0 functions
	1	[56]	GETUPVAL 	2 0	; get_line
	2	[56]	MOVE     	3 0
	3	[56]	MOVE     	4 1
	4	[56]	CALL     	2 3 2
	5	[57]	TEST     	2 0 0
	6	[57]	JMP      	5	; to 12
	7	[57]	GETUPVAL 	3 1	; trim
	8	[57]	MOVE     	4 2
	9	[57]	CALL     	3 2 2
	10	[57]	EQ       	0 3 -1	; - ""
	11	[57]	JMP      	8	; to 20
	12	[57]	LT       	0 -2 1	; 1 -
	13	[57]	JMP      	6	; to 20
	14	[58]	GETUPVAL 	3 2	; get_closest_line
	15	[58]	MOVE     	4 0
	16	[58]	SUB      	5 1 -2	; - 1
	17	[58]	TAILCALL 	3 3 0
	18	[58]	RETURN   	3 0
	19	[58]	JMP      	3	; to 23
	20	[60]	MOVE     	3 2
	21	[60]	MOVE     	4 1
	22	[60]	RETURN   	3 3
	23	[62]	RETURN   	0 1

function <./moonscript/util.lua:64,76> (21 instructions, 84 bytes at 0x7fd6e54077d0)
2 params, 10 slots, 0 upvalues, 8 locals, 4 constants, 0 functions
	1	[65]	EQ       	0 0 -1	; - ""
	2	[65]	JMP      	2	; to 5
	3	[66]	NEWTABLE 	2 0 0
	4	[66]	RETURN   	2 2
	5	[68]	MOVE     	2 0
	6	[68]	MOVE     	3 1
	7	[68]	CONCAT   	0 2 3
	8	[69]	NEWTABLE 	2 0 0
	9	[70]	LOADK    	3 -2	; 1
	10	[71]	SELF     	4 0 -3	; "gmatch"
	11	[71]	LOADK    	6 -4	; "(.-)"
	12	[71]	MOVE     	7 1
	13	[71]	CONCAT   	6 6 7
	14	[71]	CALL     	4 3 4
	15	[71]	JMP      	2	; to 18
	16	[72]	SETTABLE 	2 3 7
	17	[73]	ADD      	3 3 -2	; - 1
	18	[71]	TFORLOOP 	4 1
	19	[73]	JMP      	-4	; to 16
	20	[75]	RETURN   	2 2
	21	[76]	RETURN   	0 1

function <./moonscript/util.lua:78,111> (12 instructions, 48 bytes at 0x7fd6e5408f60)
1 param, 5 slots, 2 upvalues, 3 locals, 0 constants, 1 function
	1	[79]	NEWTABLE 	1 0 0
	2	[80]	LOADNIL  	2 2
	3	[109]	CLOSURE  	2 0	; 0x7fd6e5409270
	4	[109]	GETUPVAL 	0 0	; type
	5	[109]	MOVE     	0 1
	6	[109]	MOVE     	0 2
	7	[109]	GETUPVAL 	0 1	; concat
	8	[110]	MOVE     	3 2
	9	[110]	MOVE     	4 0
	10	[110]	TAILCALL 	3 2 0
	11	[110]	RETURN   	3 0
	12	[111]	RETURN   	0 1

function <./moonscript/util.lua:81,109> (78 instructions, 312 bytes at 0x7fd6e5409270)
2 params, 18 slots, 4 upvalues, 11 locals, 21 constants, 0 functions
	1	[82]	EQ       	0 1 -1	; - nil
	2	[82]	JMP      	1	; to 4
	3	[83]	LOADK    	1 -2	; 0
	4	[85]	GETUPVAL 	2 0	; type
	5	[85]	MOVE     	3 0
	6	[85]	CALL     	2 2 2
	7	[86]	EQ       	0 2 -3	; - "string"
	8	[86]	JMP      	6	; to 15
	9	[87]	LOADK    	3 -4	; "\""
	10	[87]	MOVE     	4 0
	11	[87]	LOADK    	5 -5	; "\"\n"
	12	[87]	CONCAT   	3 3 5
	13	[87]	RETURN   	3 2
	14	[87]	JMP      	63	; to 78
	15	[88]	EQ       	0 2 -6	; - "table"
	16	[88]	JMP      	55	; to 72
	17	[89]	GETUPVAL 	3 1	; seen
	18	[89]	GETTABLE 	3 3 0
	19	[89]	TEST     	3 0 0
	20	[89]	JMP      	7	; to 28
	21	[90]	LOADK    	3 -7	; "recursion("
	22	[90]	GETGLOBAL	4 -8	; tostring
	23	[90]	MOVE     	5 0
	24	[90]	CALL     	4 2 2
	25	[90]	LOADK    	5 -9	; ")...\n"
	26	[90]	CONCAT   	3 3 5
	27	[90]	RETURN   	3 2
	28	[92]	GETUPVAL 	3 1	; seen
	29	[92]	SETTABLE 	3 0 -10	; - true
	30	[93]	ADD      	1 1 -11	; - 1
	31	[94]	LOADNIL  	3 3
	32	[96]	NEWTABLE 	4 0 0
	33	[97]	LOADK    	5 -11	; 1
	34	[98]	GETGLOBAL	6 -12	; pairs
	35	[98]	MOVE     	7 0
	36	[98]	CALL     	6 2 4
	37	[98]	JMP      	16	; to 54
	38	[99]	LOADK    	11 -13	; " "
	39	[99]	SELF     	11 11 -14	; "rep"
	40	[99]	MUL      	13 1 -15	; - 4
	41	[99]	CALL     	11 3 2
	42	[99]	LOADK    	12 -16	; "["
	43	[99]	GETGLOBAL	13 -8	; tostring
	44	[99]	MOVE     	14 9
	45	[99]	CALL     	13 2 2
	46	[99]	LOADK    	14 -17	; "] = "
	47	[99]	GETUPVAL 	15 2	; _dump
	48	[99]	MOVE     	16 10
	49	[99]	MOVE     	17 1
	50	[99]	CALL     	15 3 2
	51	[99]	CONCAT   	11 11 15
	52	[99]	SETTABLE 	4 5 11
	53	[100]	ADD      	5 5 -11	; - 1
	54	[98]	TFORLOOP 	6 2
	55	[100]	JMP      	-18	; to 38
	56	[102]	MOVE     	3 4
	57	[104]	GETUPVAL 	4 1	; seen
	58	[104]	SETTABLE 	4 0 -18	; - false
	59	[105]	LOADK    	4 -19	; "{\n"
	60	[105]	GETUPVAL 	5 3	; concat
	61	[105]	MOVE     	6 3
	62	[105]	CALL     	5 2 2
	63	[105]	LOADK    	6 -13	; " "
	64	[105]	SELF     	6 6 -14	; "rep"
	65	[105]	SUB      	8 1 -11	; - 1
	66	[105]	MUL      	8 8 -15	; - 4
	67	[105]	CALL     	6 3 2
	68	[105]	LOADK    	7 -20	; "}\n"
	69	[105]	CONCAT   	4 4 7
	70	[105]	RETURN   	4 2
	71	[105]	JMP      	6	; to 78
	72	[107]	GETGLOBAL	3 -8	; tostring
	73	[107]	MOVE     	4 0
	74	[107]	CALL     	3 2 2
	75	[107]	LOADK    	4 -21	; "\n"
	76	[107]	CONCAT   	3 3 4
	77	[107]	RETURN   	3 2
	78	[109]	RETURN   	0 1

function <./moonscript/util.lua:113,147> (78 instructions, 312 bytes at 0x7fd6e5407750)
3 params, 28 slots, 6 upvalues, 25 locals, 10 constants, 1 function
	1	[116]	NEWTABLE 	4 0 0
	2	[117]	LOADK    	5 -1	; 1
	3	[118]	GETGLOBAL	6 -2	; pairs
	4	[118]	MOVE     	7 0
	5	[118]	CALL     	6 2 4
	6	[118]	JMP      	6	; to 13
	7	[119]	NEWTABLE 	11 2 0
	8	[120]	MOVE     	12 9
	9	[122]	MOVE     	13 10
	10	[122]	SETLIST  	11 2 1	; 1
	11	[122]	SETTABLE 	4 5 11
	12	[123]	ADD      	5 5 -1	; - 1
	13	[118]	TFORLOOP 	6 2
	14	[123]	JMP      	-8	; to 7
	15	[125]	MOVE     	3 4
	16	[127]	GETGLOBAL	4 -3	; table
	17	[127]	GETTABLE 	4 4 -4	; "sort"
	18	[127]	MOVE     	5 3
	19	[129]	CLOSURE  	6 0	; 0x7fd6e5406f50
	20	[127]	CALL     	4 3 1
	21	[130]	LOADNIL  	4 4
	22	[132]	NEWTABLE 	5 0 0
	23	[133]	LOADK    	6 -1	; 1
	24	[134]	LOADK    	7 -1	; 1
	25	[134]	LEN      	8 3
	26	[134]	LOADK    	9 -1	; 1
	27	[134]	FORPREP  	7 43	; to 71
	28	[135]	GETTABLE 	11 3 10
	29	[136]	GETUPVAL 	12 0	; unpack
	30	[136]	MOVE     	13 11
	31	[136]	CALL     	12 2 3
	32	[137]	GETUPVAL 	14 1	; pos_to_line
	33	[137]	MOVE     	15 1
	34	[137]	MOVE     	16 13
	35	[137]	CALL     	14 3 2
	36	[138]	GETUPVAL 	15 2	; get_line
	37	[138]	MOVE     	16 2
	38	[138]	MOVE     	17 12
	39	[138]	CALL     	15 3 2
	40	[139]	GETUPVAL 	16 3	; get_closest_line
	41	[139]	MOVE     	17 1
	42	[139]	MOVE     	18 14
	43	[139]	CALL     	16 3 2
	44	[140]	GETGLOBAL	17 -5	; tostring
	45	[140]	MOVE     	18 13
	46	[140]	CALL     	17 2 2
	47	[140]	LOADK    	18 -6	; "\t "
	48	[140]	GETGLOBAL	19 -5	; tostring
	49	[140]	MOVE     	20 12
	50	[140]	CALL     	19 2 2
	51	[140]	LOADK    	20 -7	; ":[ "
	52	[140]	GETGLOBAL	21 -5	; tostring
	53	[140]	GETUPVAL 	22 4	; trim
	54	[140]	MOVE     	23 15
	55	[140]	CALL     	22 2 0
	56	[140]	CALL     	21 0 2
	57	[140]	LOADK    	22 -8	; " ] >> "
	58	[140]	GETGLOBAL	23 -5	; tostring
	59	[140]	MOVE     	24 14
	60	[140]	CALL     	23 2 2
	61	[140]	LOADK    	24 -7	; ":[ "
	62	[140]	GETGLOBAL	25 -5	; tostring
	63	[140]	GETUPVAL 	26 4	; trim
	64	[140]	MOVE     	27 16
	65	[140]	CALL     	26 2 0
	66	[140]	CALL     	25 0 2
	67	[140]	LOADK    	26 -9	; " ]"
	68	[140]	CONCAT   	17 17 26
	69	[141]	SETTABLE 	5 6 17
	70	[142]	ADD      	6 6 -1	; - 1
	71	[134]	FORLOOP  	7 -44	; to 28
	72	[144]	MOVE     	4 5
	73	[146]	GETUPVAL 	5 5	; concat
	74	[146]	MOVE     	6 4
	75	[146]	LOADK    	7 -10	; "\n"
	76	[146]	TAILCALL 	5 3 0
	77	[146]	RETURN   	5 0
	78	[147]	RETURN   	0 1

function <./moonscript/util.lua:127,129> (8 instructions, 32 bytes at 0x7fd6e5406f50)
2 params, 4 slots, 0 upvalues, 2 locals, 1 constant, 0 functions
	1	[128]	GETTABLE 	2 0 -1	; 1
	2	[128]	GETTABLE 	3 1 -1	; 1
	3	[128]	LT       	1 2 3
	4	[128]	JMP      	1	; to 6
	5	[128]	LOADBOOL 	2 0 1
	6	[128]	LOADBOOL 	2 1 0
	7	[128]	RETURN   	2 2
	8	[129]	RETURN   	0 1

function <./moonscript/util.lua:148,164> (26 instructions, 104 bytes at 0x7fd6e5406ed0)
2 params, 9 slots, 0 upvalues, 4 locals, 5 constants, 1 function
	1	[150]	LOADK    	3 -1	; 1
	2	[152]	GETGLOBAL	4 -2	; debug
	3	[152]	GETTABLE 	4 4 -3	; "getupvalue"
	4	[152]	MOVE     	5 0
	5	[152]	MOVE     	6 3
	6	[152]	CALL     	4 3 2
	7	[152]	MOVE     	2 4
	8	[153]	TEST     	2 0 0
	9	[153]	JMP      	5	; to 15
	10	[153]	EQ       	0 2 -4	; - "_ENV"
	11	[153]	JMP      	1	; to 13
	12	[154]	JMP      	2	; to 15
	13	[156]	ADD      	3 3 -1	; - 1
	14	[156]	JMP      	-13	; to 2
	15	[158]	TEST     	2 0 0
	16	[158]	JMP      	8	; to 25
	17	[159]	GETGLOBAL	4 -2	; debug
	18	[159]	GETTABLE 	4 4 -5	; "upvaluejoin"
	19	[159]	MOVE     	5 0
	20	[159]	MOVE     	6 3
	21	[161]	CLOSURE  	7 0	; 0x7fd6e5409f20
	22	[161]	MOVE     	0 1
	23	[161]	LOADK    	8 -1	; 1
	24	[159]	CALL     	4 5 1
	25	[163]	RETURN   	0 2
	26	[164]	RETURN   	0 1

function <./moonscript/util.lua:159,161> (3 instructions, 12 bytes at 0x7fd6e5409f20)
0 params, 2 slots, 1 upvalue, 0 locals, 0 constants, 0 functions
	1	[160]	GETUPVAL 	0 0	; env
	2	[160]	RETURN   	0 2
	3	[161]	RETURN   	0 1

function <./moonscript/util.lua:165,178> (17 instructions, 68 bytes at 0x7fd6e540a040)
1 param, 5 slots, 0 upvalues, 4 locals, 4 constants, 0 functions
	1	[166]	LOADK    	1 -1	; 1
	2	[168]	GETGLOBAL	2 -2	; debug
	3	[168]	GETTABLE 	2 2 -3	; "getupvalue"
	4	[168]	MOVE     	3 0
	5	[168]	MOVE     	4 1
	6	[168]	CALL     	2 3 3
	7	[169]	TEST     	2 0 1
	8	[169]	JMP      	1	; to 10
	9	[170]	JMP      	5	; to 15
	10	[172]	EQ       	0 2 -4	; - "_ENV"
	11	[172]	JMP      	1	; to 13
	12	[173]	RETURN   	3 2
	13	[175]	ADD      	1 1 -1	; - 1
	14	[175]	JMP      	-13	; to 2
	15	[177]	LOADNIL  	2 2
	16	[177]	RETURN   	2 2
	17	[178]	RETURN   	0 1

function <./moonscript/util.lua:180,190> (27 instructions, 108 bytes at 0x7fd6e540a330)
0+ params, 8 slots, 2 upvalues, 3 locals, 4 constants, 0 functions
	1	[181]	GETGLOBAL	1 -1	; select
	2	[181]	LOADK    	2 -2	; "#"
	3	[181]	VARARG   	3 0
	4	[181]	CALL     	1 0 2
	5	[182]	GETGLOBAL	2 -1	; select
	6	[182]	MOVE     	3 1
	7	[182]	VARARG   	4 0
	8	[182]	CALL     	2 0 2
	9	[183]	GETUPVAL 	3 0	; type
	10	[183]	MOVE     	4 2
	11	[183]	CALL     	3 2 2
	12	[183]	EQ       	0 3 -3	; - "table"
	13	[183]	JMP      	10	; to 24
	14	[184]	MOVE     	3 2
	15	[184]	GETUPVAL 	4 1	; unpack
	16	[184]	NEWTABLE 	5 0 0
	17	[184]	VARARG   	6 0
	18	[186]	SETLIST  	5 0 1	; 1
	19	[186]	LOADNIL  	6 6
	20	[186]	SUB      	7 1 -4	; - 1
	21	[184]	CALL     	4 4 0
	22	[186]	RETURN   	3 0
	23	[186]	JMP      	3	; to 27
	24	[188]	NEWTABLE 	3 0 0
	25	[188]	VARARG   	4 0
	26	[188]	RETURN   	3 0
	27	[190]	RETURN   	0 1

function <./moonscript/util.lua:192,198> (9 instructions, 36 bytes at 0x7fd6e540a6a0)
2 params, 6 slots, 0 upvalues, 2 locals, 2 constants, 1 function
	1	[193]	GETGLOBAL	2 -1	; setmetatable
	2	[193]	MOVE     	3 1
	3	[193]	NEWTABLE 	4 0 1
	4	[196]	CLOSURE  	5 0	; 0x7fd6e540ac10
	5	[196]	MOVE     	0 0
	6	[196]	SETTABLE 	4 -2 5	; "__index" -
	7	[193]	TAILCALL 	2 3 0
	8	[197]	RETURN   	2 0
	9	[198]	RETURN   	0 1

function <./moonscript/util.lua:194,196> (13 instructions, 52 bytes at 0x7fd6e540ac10)
2 params, 8 slots, 1 upvalue, 2 locals, 4 constants, 0 functions
	1	[195]	GETGLOBAL	2 -1	; error
	2	[195]	LOADK    	3 -2	; "Attempted to import non-existent `"
	3	[195]	GETGLOBAL	4 -3	; tostring
	4	[195]	MOVE     	5 1
	5	[195]	CALL     	4 2 2
	6	[195]	LOADK    	5 -4	; "` from "
	7	[195]	GETGLOBAL	6 -3	; tostring
	8	[195]	GETUPVAL 	7 0	; name
	9	[195]	CALL     	6 2 2
	10	[195]	CONCAT   	3 3 6
	11	[195]	TAILCALL 	2 2 0
	12	[195]	RETURN   	2 0
	13	[196]	RETURN   	0 1
