
main <./moonscript/transform/value.lua:0,0> (116 instructions, 464 bytes at 0x7fef9a4068d0)
0+ params, 18 slots, 0 upvalues, 18 locals, 41 constants, 13 functions
	1	[2]	GETGLOBAL	1 -1	; require
	2	[2]	LOADK    	2 -2	; "moonscript.transform.transformer"
	3	[2]	CALL     	1 2 2
	4	[2]	GETTABLE 	0 1 -3	; "Transformer"
	5	[3]	LOADNIL  	1 3
	6	[5]	GETGLOBAL	4 -1	; require
	7	[5]	LOADK    	5 -4	; "moonscript.types"
	8	[5]	CALL     	4 2 2
	9	[6]	GETTABLE 	5 4 -5	; "build"
	10	[6]	GETTABLE 	6 4 -6	; "ntype"
	11	[6]	GETTABLE 	3 4 -7	; "smart_node"
	12	[6]	MOVE     	2 6
	13	[6]	MOVE     	1 5
	14	[8]	LOADNIL  	4 4
	15	[9]	GETGLOBAL	5 -1	; require
	16	[9]	LOADK    	6 -8	; "moonscript.transform.names"
	17	[9]	CALL     	5 2 2
	18	[9]	GETTABLE 	4 5 -9	; "NameProxy"
	19	[10]	LOADNIL  	5 6
	20	[12]	GETGLOBAL	7 -1	; require
	21	[12]	LOADK    	8 -10	; "moonscript.transform.accumulator"
	22	[12]	CALL     	7 2 2
	23	[13]	GETTABLE 	8 7 -11	; "Accumulator"
	24	[13]	GETTABLE 	6 7 -12	; "default_accumulator"
	25	[13]	MOVE     	5 8
	26	[15]	LOADNIL  	7 7
	27	[16]	GETGLOBAL	8 -1	; require
	28	[16]	LOADK    	9 -13	; "moonscript.data"
	29	[16]	CALL     	8 2 2
	30	[16]	GETTABLE 	7 8 -14	; "lua_keywords"
	31	[17]	LOADNIL  	8 11
	32	[19]	GETGLOBAL	12 -1	; require
	33	[19]	LOADK    	13 -15	; "moonscript.transform.statements"
	34	[19]	CALL     	12 2 2
	35	[20]	GETTABLE 	13 12 -16	; "Run"
	36	[20]	GETTABLE 	14 12 -17	; "transform_last_stm"
	37	[20]	GETTABLE 	15 12 -18	; "implicitly_return"
	38	[20]	GETTABLE 	11 12 -19	; "chain_is_stub"
	39	[20]	MOVE     	10 15
	40	[20]	MOVE     	9 14
	41	[20]	MOVE     	8 13
	42	[22]	LOADNIL  	12 12
	43	[23]	GETGLOBAL	13 -1	; require
	44	[23]	LOADK    	14 -20	; "moonscript.transform.comprehension"
	45	[23]	CALL     	13 2 2
	46	[23]	GETTABLE 	12 13 -21	; "construct_comprehension"
	47	[24]	LOADNIL  	13 13
	48	[25]	GETGLOBAL	14 -22	; table
	49	[25]	GETTABLE 	13 14 -23	; "insert"
	50	[26]	LOADNIL  	14 14
	51	[27]	GETGLOBAL	15 -1	; require
	52	[27]	LOADK    	16 -24	; "moonscript.util"
	53	[27]	CALL     	15 2 2
	54	[27]	GETTABLE 	14 15 -25	; "unpack"
	55	[28]	MOVE     	15 0
	56	[28]	NEWTABLE 	16 0 16
	57	[29]	SETTABLE 	16 -26 6	; "for" -
	58	[30]	SETTABLE 	16 -27 6	; "while" -
	59	[31]	SETTABLE 	16 -28 6	; "foreach" -
	60	[34]	CLOSURE  	17 0	; 0x7fef9a407070
	61	[34]	MOVE     	0 1
	62	[34]	SETTABLE 	16 -29 17	; "do" -
	63	[37]	CLOSURE  	17 1	; 0x7fef9a407150
	64	[37]	SETTABLE 	16 -30 17	; "decorated" -
	65	[42]	CLOSURE  	17 2	; 0x7fef9a407790
	66	[42]	MOVE     	0 1
	67	[42]	SETTABLE 	16 -31 17	; "class" -
	68	[81]	CLOSURE  	17 3	; 0x7fef9a407ae0
	69	[81]	MOVE     	0 1
	70	[81]	MOVE     	0 13
	71	[81]	SETTABLE 	16 -32 17	; "string" -
	72	[90]	CLOSURE  	17 4	; 0x7fef9a408170
	73	[90]	MOVE     	0 5
	74	[90]	SETTABLE 	16 -33 17	; "comprehension" -
	75	[134]	CLOSURE  	17 5	; 0x7fef9a408aa0
	76	[134]	MOVE     	0 14
	77	[134]	MOVE     	0 4
	78	[134]	MOVE     	0 1
	79	[134]	MOVE     	0 12
	80	[134]	SETTABLE 	16 -34 17	; "tblcomprehension" -
	81	[145]	CLOSURE  	17 6	; 0x7fef9a407990
	82	[145]	MOVE     	0 3
	83	[145]	MOVE     	0 9
	84	[145]	MOVE     	0 10
	85	[145]	MOVE     	0 8
	86	[145]	MOVE     	0 14
	87	[145]	SETTABLE 	16 -35 17	; "fndef" -
	88	[150]	CLOSURE  	17 7	; 0x7fef9a409690
	89	[150]	MOVE     	0 1
	90	[150]	SETTABLE 	16 -36 17	; "if" -
	91	[155]	CLOSURE  	17 8	; 0x7fef9a409ce0
	92	[155]	MOVE     	0 1
	93	[155]	SETTABLE 	16 -37 17	; "unless" -
	94	[160]	CLOSURE  	17 9	; 0x7fef9a40a160
	95	[160]	MOVE     	0 1
	96	[160]	SETTABLE 	16 -38 17	; "with" -
	97	[165]	CLOSURE  	17 10	; 0x7fef9a40a280
	98	[165]	MOVE     	0 1
	99	[165]	SETTABLE 	16 -39 17	; "switch" -
	100	[235]	CLOSURE  	17 11	; 0x7fef9a40a530
	101	[235]	MOVE     	0 2
	102	[235]	MOVE     	0 7
	103	[235]	MOVE     	0 11
	104	[235]	MOVE     	0 4
	105	[235]	MOVE     	0 1
	106	[235]	SETTABLE 	16 -40 17	; "chain" -
	107	[264]	CLOSURE  	17 12	; 0x7fef9a40a820
	108	[264]	MOVE     	0 14
	109	[264]	MOVE     	0 3
	110	[264]	MOVE     	0 1
	111	[264]	MOVE     	0 8
	112	[264]	MOVE     	0 13
	113	[264]	SETTABLE 	16 -41 17	; "block_exp" -
	114	[28]	TAILCALL 	15 2 0
	115	[265]	RETURN   	15 0
	116	[265]	RETURN   	0 1

function <./moonscript/transform/value.lua:32,34> (6 instructions, 24 bytes at 0x7fef9a407070)
2 params, 4 slots, 1 upvalue, 2 locals, 2 constants, 0 functions
	1	[33]	GETUPVAL 	2 0	; build
	2	[33]	GETTABLE 	2 2 -1	; "block_exp"
	3	[33]	GETTABLE 	3 1 -2	; 2
	4	[33]	TAILCALL 	2 2 0
	5	[33]	RETURN   	2 0
	6	[34]	RETURN   	0 1

function <./moonscript/transform/value.lua:35,37> (6 instructions, 24 bytes at 0x7fef9a407150)
2 params, 4 slots, 0 upvalues, 2 locals, 2 constants, 0 functions
	1	[36]	GETTABLE 	2 0 -1	; "transform"
	2	[36]	GETTABLE 	2 2 -2	; "statement"
	3	[36]	MOVE     	3 1
	4	[36]	TAILCALL 	2 2 0
	5	[36]	RETURN   	2 0
	6	[37]	RETURN   	0 1

function <./moonscript/transform/value.lua:38,42> (8 instructions, 32 bytes at 0x7fef9a407790)
2 params, 5 slots, 1 upvalue, 2 locals, 1 constant, 0 functions
	1	[39]	GETUPVAL 	2 0	; build
	2	[39]	GETTABLE 	2 2 -1	; "block_exp"
	3	[39]	NEWTABLE 	3 1 0
	4	[41]	MOVE     	4 1
	5	[41]	SETLIST  	3 1 1	; 1
	6	[39]	TAILCALL 	2 2 0
	7	[41]	RETURN   	2 0
	8	[42]	RETURN   	0 1

function <./moonscript/transform/value.lua:43,81> (42 instructions, 168 bytes at 0x7fef9a407ae0)
2 params, 13 slots, 2 upvalues, 9 locals, 8 constants, 1 function
	1	[44]	GETTABLE 	2 1 -1	; 2
	2	[45]	LOADNIL  	3 3
	3	[64]	CLOSURE  	3 0	; 0x7fef9a4081f0
	4	[64]	MOVE     	0 2
	5	[64]	GETUPVAL 	0 0	; build
	6	[65]	LEN      	4 1
	7	[65]	LE       	0 4 -2	; - 3
	8	[65]	JMP      	11	; to 20
	9	[66]	GETGLOBAL	4 -3	; type
	10	[66]	GETTABLE 	5 1 -2	; 3
	11	[66]	CALL     	4 2 2
	12	[66]	EQ       	0 4 -4	; - "string"
	13	[66]	JMP      	2	; to 16
	14	[67]	RETURN   	1 2
	15	[67]	JMP      	4	; to 20
	16	[69]	MOVE     	4 3
	17	[69]	GETTABLE 	5 1 -2	; 3
	18	[69]	TAILCALL 	4 2 0
	19	[69]	RETURN   	4 0
	20	[72]	NEWTABLE 	4 1 0
	21	[73]	LOADK    	5 -5	; "exp"
	22	[74]	MOVE     	6 3
	23	[74]	GETTABLE 	7 1 -2	; 3
	24	[74]	CALL     	6 2 0
	25	[75]	SETLIST  	4 0 1	; 1
	26	[76]	LOADK    	5 -6	; 4
	27	[76]	LEN      	6 1
	28	[76]	LOADK    	7 -7	; 1
	29	[76]	FORPREP  	5 10	; to 40
	30	[77]	GETUPVAL 	9 1	; insert
	31	[77]	MOVE     	10 4
	32	[77]	LOADK    	11 -8	; ".."
	33	[77]	CALL     	9 3 1
	34	[78]	GETUPVAL 	9 1	; insert
	35	[78]	MOVE     	10 4
	36	[78]	MOVE     	11 3
	37	[78]	GETTABLE 	12 1 8
	38	[78]	CALL     	11 2 0
	39	[78]	CALL     	9 0 1
	40	[76]	FORLOOP  	5 -11	; to 30
	41	[80]	RETURN   	4 2
	42	[81]	RETURN   	0 1

function <./moonscript/transform/value.lua:46,64> (30 instructions, 120 bytes at 0x7fef9a4081f0)
1 param, 7 slots, 2 upvalues, 1 local, 9 constants, 0 functions
	1	[47]	GETGLOBAL	1 -1	; type
	2	[47]	MOVE     	2 0
	3	[47]	CALL     	1 2 2
	4	[47]	EQ       	1 1 -2	; - "string"
	5	[47]	JMP      	2	; to 8
	6	[47]	EQ       	0 0 -3	; - nil
	7	[47]	JMP      	9	; to 17
	8	[48]	NEWTABLE 	1 3 0
	9	[49]	LOADK    	2 -2	; "string"
	10	[50]	GETUPVAL 	3 0	; delim
	11	[51]	TESTSET  	4 0 1
	12	[51]	JMP      	1	; to 14
	13	[52]	LOADK    	4 -4	; ""
	14	[52]	SETLIST  	1 3 1	; 1
	15	[52]	RETURN   	1 2
	16	[52]	JMP      	13	; to 30
	17	[54]	GETUPVAL 	1 1	; build
	18	[54]	GETTABLE 	1 1 -5	; "chain"
	19	[54]	NEWTABLE 	2 1 1
	20	[55]	SETTABLE 	2 -6 -7	; "base" "tostring"
	21	[55]	NEWTABLE 	3 2 0
	22	[57]	LOADK    	4 -8	; "call"
	23	[57]	NEWTABLE 	5 1 0
	24	[60]	GETTABLE 	6 0 -9	; 2
	25	[60]	SETLIST  	5 1 1	; 1
	26	[61]	SETLIST  	3 2 1	; 1
	27	[62]	SETLIST  	2 1 1	; 1
	28	[54]	TAILCALL 	1 2 0
	29	[62]	RETURN   	1 0
	30	[64]	RETURN   	0 1

function <./moonscript/transform/value.lua:82,90> (14 instructions, 56 bytes at 0x7fef9a408170)
2 params, 6 slots, 1 upvalue, 3 locals, 3 constants, 1 function
	1	[83]	GETUPVAL 	2 0	; Accumulator
	2	[83]	CALL     	2 1 2
	3	[84]	GETTABLE 	3 0 -1	; "transform"
	4	[84]	GETTABLE 	3 3 -2	; "statement"
	5	[84]	MOVE     	4 1
	6	[88]	CLOSURE  	5 0	; 0x7fef9a4073e0
	7	[88]	MOVE     	0 2
	8	[84]	CALL     	3 3 2
	9	[88]	MOVE     	1 3
	10	[89]	SELF     	3 2 -3	; "wrap"
	11	[89]	MOVE     	5 1
	12	[89]	TAILCALL 	3 3 0
	13	[89]	RETURN   	3 0
	14	[90]	RETURN   	0 1

function <./moonscript/transform/value.lua:84,88> (8 instructions, 32 bytes at 0x7fef9a4073e0)
1 param, 5 slots, 1 upvalue, 1 local, 1 constant, 0 functions
	1	[85]	GETUPVAL 	1 0	; a
	2	[85]	SELF     	1 1 -1	; "mutate_body"
	3	[85]	NEWTABLE 	3 1 0
	4	[87]	MOVE     	4 0
	5	[87]	SETLIST  	3 1 1	; 1
	6	[85]	TAILCALL 	1 3 0
	7	[87]	RETURN   	1 0
	8	[88]	RETURN   	0 1

function <./moonscript/transform/value.lua:91,134> (88 instructions, 352 bytes at 0x7fef9a408aa0)
2 params, 17 slots, 4 upvalues, 12 locals, 13 constants, 0 functions
	1	[92]	GETUPVAL 	2 0	; unpack
	2	[92]	MOVE     	3 1
	3	[92]	LOADK    	4 -1	; 2
	4	[92]	CALL     	2 3 3
	5	[93]	GETUPVAL 	4 0	; unpack
	6	[93]	MOVE     	5 2
	7	[93]	CALL     	4 2 3
	8	[94]	GETUPVAL 	6 1	; NameProxy
	9	[94]	LOADK    	7 -2	; "tbl"
	10	[94]	CALL     	6 2 2
	11	[95]	LOADNIL  	7 7
	12	[96]	TEST     	5 0 0
	13	[96]	JMP      	19	; to 33
	14	[97]	GETUPVAL 	8 2	; build
	15	[97]	GETTABLE 	8 8 -3	; "chain"
	16	[97]	NEWTABLE 	9 1 1
	17	[98]	SETTABLE 	9 -4 6	; "base" -
	18	[98]	NEWTABLE 	10 2 0
	19	[100]	LOADK    	11 -5	; "index"
	20	[102]	MOVE     	12 4
	21	[102]	SETLIST  	10 2 1	; 1
	22	[103]	SETLIST  	9 1 1	; 1
	23	[97]	CALL     	8 2 2
	24	[104]	NEWTABLE 	9 0 0
	25	[105]	GETUPVAL 	10 2	; build
	26	[105]	GETTABLE 	10 10 -6	; "assign_one"
	27	[105]	MOVE     	11 8
	28	[105]	MOVE     	12 5
	29	[105]	CALL     	10 3 0
	30	[106]	SETLIST  	9 0 1	; 1
	31	[106]	MOVE     	7 9
	32	[106]	JMP      	37	; to 70
	33	[108]	GETUPVAL 	8 1	; NameProxy
	34	[108]	LOADK    	9 -7	; "key"
	35	[108]	CALL     	8 2 2
	36	[108]	GETUPVAL 	9 1	; NameProxy
	37	[108]	LOADK    	10 -8	; "val"
	38	[108]	CALL     	9 2 2
	39	[109]	GETUPVAL 	10 2	; build
	40	[109]	GETTABLE 	10 10 -3	; "chain"
	41	[109]	NEWTABLE 	11 1 1
	42	[110]	SETTABLE 	11 -4 6	; "base" -
	43	[110]	NEWTABLE 	12 2 0
	44	[112]	LOADK    	13 -5	; "index"
	45	[114]	MOVE     	14 8
	46	[114]	SETLIST  	12 2 1	; 1
	47	[115]	SETLIST  	11 1 1	; 1
	48	[109]	CALL     	10 2 2
	49	[116]	NEWTABLE 	11 1 0
	50	[117]	GETUPVAL 	12 2	; build
	51	[117]	GETTABLE 	12 12 -9	; "assign"
	52	[117]	NEWTABLE 	13 0 2
	53	[118]	NEWTABLE 	14 2 0
	54	[119]	MOVE     	15 8
	55	[121]	MOVE     	16 9
	56	[121]	SETLIST  	14 2 1	; 1
	57	[121]	SETTABLE 	13 -10 14	; "names" -
	58	[122]	NEWTABLE 	14 1 0
	59	[124]	MOVE     	15 4
	60	[124]	SETLIST  	14 1 1	; 1
	61	[124]	SETTABLE 	13 -11 14	; "values" -
	62	[117]	CALL     	12 2 2
	63	[126]	GETUPVAL 	13 2	; build
	64	[126]	GETTABLE 	13 13 -6	; "assign_one"
	65	[126]	MOVE     	14 10
	66	[126]	MOVE     	15 9
	67	[126]	CALL     	13 3 0
	68	[127]	SETLIST  	11 0 1	; 1
	69	[127]	MOVE     	7 11
	70	[129]	GETUPVAL 	8 2	; build
	71	[129]	GETTABLE 	8 8 -12	; "block_exp"
	72	[129]	NEWTABLE 	9 3 0
	73	[130]	GETUPVAL 	10 2	; build
	74	[130]	GETTABLE 	10 10 -6	; "assign_one"
	75	[130]	MOVE     	11 6
	76	[130]	GETUPVAL 	12 2	; build
	77	[130]	GETTABLE 	12 12 -13	; "table"
	78	[130]	CALL     	12 1 0
	79	[130]	CALL     	10 0 2
	80	[131]	GETUPVAL 	11 3	; construct_comprehension
	81	[131]	MOVE     	12 7
	82	[131]	MOVE     	13 3
	83	[131]	CALL     	11 3 2
	84	[133]	MOVE     	12 6
	85	[133]	SETLIST  	9 3 1	; 1
	86	[129]	TAILCALL 	8 2 0
	87	[133]	RETURN   	8 0
	88	[134]	RETURN   	0 1

function <./moonscript/transform/value.lua:135,145> (21 instructions, 84 bytes at 0x7fef9a407990)
2 params, 6 slots, 5 upvalues, 2 locals, 1 constant, 1 function
	1	[136]	GETUPVAL 	2 0	; smart_node
	2	[136]	MOVE     	3 1
	3	[136]	CALL     	2 2 1
	4	[137]	GETUPVAL 	2 1	; transform_last_stm
	5	[137]	GETTABLE 	3 1 -1	; "body"
	6	[137]	GETUPVAL 	4 2	; implicitly_return
	7	[137]	MOVE     	5 0
	8	[137]	CALL     	4 2 0
	9	[137]	CALL     	2 0 2
	10	[137]	SETTABLE 	1 -1 2	; "body" -
	11	[138]	NEWTABLE 	2 1 0
	12	[139]	GETUPVAL 	3 3	; Run
	13	[141]	CLOSURE  	4 0	; 0x7fef9a407600
	14	[139]	CALL     	3 2 2
	15	[142]	GETUPVAL 	4 4	; unpack
	16	[142]	GETTABLE 	5 1 -1	; "body"
	17	[142]	CALL     	4 2 0
	18	[143]	SETLIST  	2 0 1	; 1
	19	[143]	SETTABLE 	1 -1 2	; "body" -
	20	[144]	RETURN   	1 2
	21	[145]	RETURN   	0 1

function <./moonscript/transform/value.lua:139,141> (6 instructions, 24 bytes at 0x7fef9a407600)
1 param, 5 slots, 0 upvalues, 1 local, 2 constants, 1 function
	1	[140]	SELF     	1 0 -1	; "listen"
	2	[140]	LOADK    	3 -2	; "varargs"
	3	[140]	CLOSURE  	4 0	; 0x7fef9a4099c0
	4	[140]	TAILCALL 	1 4 0
	5	[140]	RETURN   	1 0
	6	[141]	RETURN   	0 1

function <./moonscript/transform/value.lua:140,140> (1 instruction, 4 bytes at 0x7fef9a4099c0)
0 params, 2 slots, 0 upvalues, 0 locals, 0 constants, 0 functions
	1	[140]	RETURN   	0 1

function <./moonscript/transform/value.lua:146,150> (8 instructions, 32 bytes at 0x7fef9a409690)
2 params, 5 slots, 1 upvalue, 2 locals, 1 constant, 0 functions
	1	[147]	GETUPVAL 	2 0	; build
	2	[147]	GETTABLE 	2 2 -1	; "block_exp"
	3	[147]	NEWTABLE 	3 1 0
	4	[149]	MOVE     	4 1
	5	[149]	SETLIST  	3 1 1	; 1
	6	[147]	TAILCALL 	2 2 0
	7	[149]	RETURN   	2 0
	8	[150]	RETURN   	0 1

function <./moonscript/transform/value.lua:151,155> (8 instructions, 32 bytes at 0x7fef9a409ce0)
2 params, 5 slots, 1 upvalue, 2 locals, 1 constant, 0 functions
	1	[152]	GETUPVAL 	2 0	; build
	2	[152]	GETTABLE 	2 2 -1	; "block_exp"
	3	[152]	NEWTABLE 	3 1 0
	4	[154]	MOVE     	4 1
	5	[154]	SETLIST  	3 1 1	; 1
	6	[152]	TAILCALL 	2 2 0
	7	[154]	RETURN   	2 0
	8	[155]	RETURN   	0 1

function <./moonscript/transform/value.lua:156,160> (8 instructions, 32 bytes at 0x7fef9a40a160)
2 params, 5 slots, 1 upvalue, 2 locals, 1 constant, 0 functions
	1	[157]	GETUPVAL 	2 0	; build
	2	[157]	GETTABLE 	2 2 -1	; "block_exp"
	3	[157]	NEWTABLE 	3 1 0
	4	[159]	MOVE     	4 1
	5	[159]	SETLIST  	3 1 1	; 1
	6	[157]	TAILCALL 	2 2 0
	7	[159]	RETURN   	2 0
	8	[160]	RETURN   	0 1

function <./moonscript/transform/value.lua:161,165> (8 instructions, 32 bytes at 0x7fef9a40a280)
2 params, 5 slots, 1 upvalue, 2 locals, 1 constant, 0 functions
	1	[162]	GETUPVAL 	2 0	; build
	2	[162]	GETTABLE 	2 2 -1	; "block_exp"
	3	[162]	NEWTABLE 	3 1 0
	4	[164]	MOVE     	4 1
	5	[164]	SETLIST  	3 1 1	; 1
	6	[162]	TAILCALL 	2 2 0
	7	[164]	RETURN   	2 0
	8	[165]	RETURN   	0 1

function <./moonscript/transform/value.lua:166,235> (132 instructions, 528 bytes at 0x7fef9a40a530)
2 params, 20 slots, 5 upvalues, 11 locals, 24 constants, 0 functions
	1	[167]	LOADK    	2 -1	; 2
	2	[167]	LEN      	3 1
	3	[167]	LOADK    	4 -2	; 1
	4	[167]	FORPREP  	2 20	; to 25
	5	[168]	GETTABLE 	6 1 5
	6	[169]	GETUPVAL 	7 0	; ntype
	7	[169]	MOVE     	8 6
	8	[169]	CALL     	7 2 2
	9	[169]	EQ       	0 7 -3	; - "dot"
	10	[169]	JMP      	14	; to 25
	11	[169]	GETUPVAL 	7 1	; lua_keywords
	12	[169]	GETTABLE 	8 6 -1	; 2
	13	[169]	GETTABLE 	7 7 8
	14	[169]	TEST     	7 0 0
	15	[169]	JMP      	9	; to 25
	16	[170]	NEWTABLE 	7 2 0
	17	[171]	LOADK    	8 -4	; "index"
	18	[171]	NEWTABLE 	9 3 0
	19	[173]	LOADK    	10 -5	; "string"
	20	[174]	LOADK    	11 -6	; "\""
	21	[176]	GETTABLE 	12 6 -1	; 2
	22	[176]	SETLIST  	9 3 1	; 1
	23	[177]	SETLIST  	7 2 1	; 1
	24	[177]	SETTABLE 	1 5 7
	25	[167]	FORLOOP  	2 -21	; to 5
	26	[180]	GETUPVAL 	2 0	; ntype
	27	[180]	GETTABLE 	3 1 -1	; 2
	28	[180]	CALL     	2 2 2
	29	[180]	EQ       	0 2 -5	; - "string"
	30	[180]	JMP      	5	; to 36
	31	[181]	NEWTABLE 	2 2 0
	32	[182]	LOADK    	3 -7	; "parens"
	33	[184]	GETTABLE 	4 1 -1	; 2
	34	[184]	SETLIST  	2 2 1	; 1
	35	[184]	SETTABLE 	1 -1 2	; 2 -
	36	[186]	GETUPVAL 	2 2	; chain_is_stub
	37	[186]	MOVE     	3 1
	38	[186]	CALL     	2 2 2
	39	[186]	TEST     	2 0 0
	40	[186]	JMP      	91	; to 132
	41	[187]	GETUPVAL 	2 3	; NameProxy
	42	[187]	LOADK    	3 -8	; "base"
	43	[187]	CALL     	2 2 2
	44	[188]	GETUPVAL 	3 3	; NameProxy
	45	[188]	LOADK    	4 -9	; "fn"
	46	[188]	CALL     	3 2 2
	47	[189]	GETGLOBAL	4 -10	; table
	48	[189]	GETTABLE 	4 4 -11	; "remove"
	49	[189]	MOVE     	5 1
	50	[189]	CALL     	4 2 2
	51	[190]	GETUPVAL 	5 0	; ntype
	52	[190]	GETTABLE 	6 1 -1	; 2
	53	[190]	CALL     	5 2 2
	54	[190]	EQ       	0 5 -12	; - "ref"
	55	[190]	JMP      	4	; to 60
	56	[190]	GETTABLE 	5 1 -1	; 2
	57	[190]	GETTABLE 	5 5 -1	; 2
	58	[190]	EQ       	1 5 -13	; - "super"
	59	[190]	JMP      	1	; to 61
	60	[190]	LOADBOOL 	5 0 1
	61	[190]	LOADBOOL 	5 1 0
	62	[191]	GETUPVAL 	6 4	; build
	63	[191]	GETTABLE 	6 6 -14	; "block_exp"
	64	[191]	NEWTABLE 	7 2 0
	65	[192]	GETUPVAL 	8 4	; build
	66	[192]	GETTABLE 	8 8 -15	; "assign"
	67	[192]	NEWTABLE 	9 0 2
	68	[193]	NEWTABLE 	10 1 0
	69	[195]	MOVE     	11 2
	70	[195]	SETLIST  	10 1 1	; 1
	71	[195]	SETTABLE 	9 -16 10	; "names" -
	72	[196]	NEWTABLE 	10 1 0
	73	[198]	MOVE     	11 1
	74	[198]	SETLIST  	10 1 1	; 1
	75	[198]	SETTABLE 	9 -17 10	; "values" -
	76	[192]	CALL     	8 2 2
	77	[200]	GETUPVAL 	9 4	; build
	78	[200]	GETTABLE 	9 9 -15	; "assign"
	79	[200]	NEWTABLE 	10 0 2
	80	[201]	NEWTABLE 	11 1 0
	81	[203]	MOVE     	12 3
	82	[203]	SETLIST  	11 1 1	; 1
	83	[203]	SETTABLE 	10 -16 11	; "names" -
	84	[204]	NEWTABLE 	11 0 0
	85	[205]	GETUPVAL 	12 4	; build
	86	[205]	GETTABLE 	12 12 -18	; "chain"
	87	[205]	NEWTABLE 	13 1 1
	88	[206]	SETTABLE 	13 -8 2	; "base" -
	89	[206]	NEWTABLE 	14 2 0
	90	[208]	LOADK    	15 -3	; "dot"
	91	[210]	GETTABLE 	16 4 -1	; 2
	92	[210]	SETLIST  	14 2 1	; 1
	93	[211]	SETLIST  	13 1 1	; 1
	94	[205]	CALL     	12 2 0
	95	[212]	SETLIST  	11 0 1	; 1
	96	[212]	SETTABLE 	10 -17 11	; "values" -
	97	[200]	CALL     	9 2 2
	98	[214]	GETUPVAL 	10 4	; build
	99	[214]	GETTABLE 	10 10 -19	; "fndef"
	100	[214]	NEWTABLE 	11 0 2
	101	[215]	NEWTABLE 	12 1 0
	102	[215]	NEWTABLE 	13 1 0
	103	[218]	LOADK    	14 -21	; "..."
	104	[218]	SETLIST  	13 1 1	; 1
	105	[219]	SETLIST  	12 1 1	; 1
	106	[219]	SETTABLE 	11 -20 12	; "args" -
	107	[220]	NEWTABLE 	12 0 0
	108	[221]	GETUPVAL 	13 4	; build
	109	[221]	GETTABLE 	13 13 -18	; "chain"
	110	[221]	NEWTABLE 	14 1 1
	111	[222]	SETTABLE 	14 -8 3	; "base" -
	112	[222]	NEWTABLE 	15 2 0
	113	[224]	LOADK    	16 -23	; "call"
	114	[224]	NEWTABLE 	17 2 0
	115	[226]	TEST     	5 0 0
	116	[226]	JMP      	3	; to 120
	117	[226]	LOADK    	18 -24	; "self"
	118	[226]	TEST     	18 0 1
	119	[226]	JMP      	1	; to 121
	120	[226]	MOVE     	18 2
	121	[228]	LOADK    	19 -21	; "..."
	122	[228]	SETLIST  	17 2 1	; 1
	123	[229]	SETLIST  	15 2 1	; 1
	124	[230]	SETLIST  	14 1 1	; 1
	125	[221]	CALL     	13 2 0
	126	[231]	SETLIST  	12 0 1	; 1
	127	[231]	SETTABLE 	11 -22 12	; "body" -
	128	[214]	CALL     	10 2 0
	129	[233]	SETLIST  	7 0 1	; 1
	130	[191]	TAILCALL 	6 2 0
	131	[233]	RETURN   	6 0
	132	[235]	RETURN   	0 1

function <./moonscript/transform/value.lua:236,264> (41 instructions, 164 bytes at 0x7fef9a40a820)
2 params, 12 slots, 5 upvalues, 5 locals, 7 constants, 1 function
	1	[237]	GETUPVAL 	2 0	; unpack
	2	[237]	MOVE     	3 1
	3	[237]	LOADK    	4 -1	; 2
	4	[237]	CALL     	2 3 2
	5	[238]	LOADNIL  	3 3
	6	[239]	NEWTABLE 	4 0 0
	7	[240]	GETUPVAL 	5 1	; smart_node
	8	[240]	GETUPVAL 	6 2	; build
	9	[240]	GETTABLE 	6 6 -2	; "fndef"
	10	[240]	NEWTABLE 	7 0 1
	11	[241]	NEWTABLE 	8 1 0
	12	[242]	GETUPVAL 	9 3	; Run
	13	[250]	CLOSURE  	10 0	; 0x7fef9a40ae20
	14	[250]	GETUPVAL 	0 4	; insert
	15	[250]	MOVE     	0 4
	16	[250]	MOVE     	0 3
	17	[242]	CALL     	9 2 2
	18	[251]	GETUPVAL 	10 0	; unpack
	19	[251]	MOVE     	11 2
	20	[251]	CALL     	10 2 0
	21	[252]	SETLIST  	8 0 1	; 1
	22	[252]	SETTABLE 	7 -3 8	; "body" -
	23	[240]	CALL     	6 2 0
	24	[240]	CALL     	5 0 2
	25	[253]	MOVE     	3 5
	26	[254]	GETUPVAL 	5 2	; build
	27	[254]	GETTABLE 	5 5 -4	; "chain"
	28	[254]	NEWTABLE 	6 1 1
	29	[255]	NEWTABLE 	7 2 0
	30	[256]	LOADK    	8 -6	; "parens"
	31	[258]	MOVE     	9 3
	32	[258]	SETLIST  	7 2 1	; 1
	33	[258]	SETTABLE 	6 -5 7	; "base" -
	34	[258]	NEWTABLE 	7 2 0
	35	[260]	LOADK    	8 -7	; "call"
	36	[262]	MOVE     	9 4
	37	[262]	SETLIST  	7 2 1	; 1
	38	[263]	SETLIST  	6 1 1	; 1
	39	[254]	TAILCALL 	5 2 0
	40	[263]	RETURN   	5 0
	41	[264]	RETURN   	0 1

function <./moonscript/transform/value.lua:242,250> (10 instructions, 40 bytes at 0x7fef9a40ae20)
1 param, 5 slots, 3 upvalues, 1 local, 2 constants, 1 function
	1	[243]	SELF     	1 0 -1	; "listen"
	2	[243]	LOADK    	3 -2	; "varargs"
	3	[249]	CLOSURE  	4 0	; 0x7fef9a40b4f0
	4	[249]	GETUPVAL 	0 0	; insert
	5	[249]	GETUPVAL 	0 1	; arg_list
	6	[249]	GETUPVAL 	0 2	; fn
	7	[249]	MOVE     	0 0
	8	[243]	TAILCALL 	1 4 0
	9	[249]	RETURN   	1 0
	10	[250]	RETURN   	0 1

function <./moonscript/transform/value.lua:243,249> (17 instructions, 68 bytes at 0x7fef9a40b4f0)
0 params, 4 slots, 4 upvalues, 0 locals, 4 constants, 0 functions
	1	[244]	GETUPVAL 	0 0	; insert
	2	[244]	GETUPVAL 	1 1	; arg_list
	3	[244]	LOADK    	2 -1	; "..."
	4	[244]	CALL     	0 3 1
	5	[245]	GETUPVAL 	0 0	; insert
	6	[245]	GETUPVAL 	1 2	; fn
	7	[245]	GETTABLE 	1 1 -2	; "args"
	8	[245]	NEWTABLE 	2 1 0
	9	[247]	LOADK    	3 -1	; "..."
	10	[247]	SETLIST  	2 1 1	; 1
	11	[245]	CALL     	0 3 1
	12	[248]	GETUPVAL 	0 3	; self
	13	[248]	SELF     	0 0 -3	; "unlisten"
	14	[248]	LOADK    	2 -4	; "varargs"
	15	[248]	TAILCALL 	0 3 0
	16	[248]	RETURN   	0 0
	17	[249]	RETURN   	0 1
