-- BYTECODE -- version.lua:4-6
0001    GGET     0   0      ; "print"
0002    KSTR     1   1      ; "MoonScript version "
0003    GGET     2   2      ; "tostring"
0004    UGET     3   0      ; version
0005    CALL     2   2   2
0006    CAT      1   1   2
0007    CALLT    0   2

-- BYTECODE -- version.lua:0-8
0001    KSTR     0   0      ; "0.5.0"
0002    TDUP     1   1
0003    TSETS    0   1   2  ; "version"
0004    FNEW     2   3      ; version.lua:4
0005    TSETS    2   1   4  ; "print_version"
0006    UCLO     0 => 0007
0007 => RET1     1   2

