
main <./LuaMidi/Chunk.lua:0,0> (6 instructions, 24 bytes at 0x7f99f9c068a0)
0+ params, 2 slots, 0 upvalues, 1 local, 1 constant, 1 function
	1	[1]	NEWTABLE 	0 0 0
	2	[10]	CLOSURE  	1 0	; 0x7f99f9c06b40
	3	[10]	MOVE     	0 0
	4	[3]	SETTABLE 	0 -1 1	; "new" -
	5	[12]	RETURN   	0 2
	6	[12]	RETURN   	0 1

function <./LuaMidi/Chunk.lua:3,10> (21 instructions, 84 bytes at 0x7f99f9c06b40)
1 param, 7 slots, 1 upvalue, 2 locals, 6 constants, 0 functions
	1	[4]	NEWTABLE 	1 0 3
	2	[5]	GETTABLE 	2 0 -1	; "type"
	3	[5]	SETTABLE 	1 -1 2	; "type" -
	4	[6]	GETTABLE 	2 0 -2	; "data"
	5	[6]	SETTABLE 	1 -2 2	; "data" -
	6	[7]	NEWTABLE 	2 4 0
	7	[7]	LOADK    	3 -4	; 0
	8	[7]	LOADK    	4 -4	; 0
	9	[7]	LOADK    	5 -4	; 0
	10	[7]	GETTABLE 	6 0 -2	; "data"
	11	[7]	LEN      	6 6
	12	[7]	SETLIST  	2 4 1	; 1
	13	[7]	SETTABLE 	1 -3 2	; "size" -
	14	[9]	GETGLOBAL	2 -5	; setmetatable
	15	[9]	MOVE     	3 1
	16	[9]	NEWTABLE 	4 0 1
	17	[9]	GETUPVAL 	5 0	; Chunk
	18	[9]	SETTABLE 	4 -6 5	; "__index" -
	19	[9]	TAILCALL 	2 3 0
	20	[9]	RETURN   	2 0
	21	[10]	RETURN   	0 1
