-- BYTECODE -- Chunk.lua:3-10
0001    TDUP     1   1
0002    TGETS    2   0   0  ; "type"
0003    TSETS    2   1   0  ; "type"
0004    TGETS    2   0   2  ; "data"
0005    TSETS    2   1   2  ; "data"
0006    TDUP     2   3
0007    TGETS    3   0   2  ; "data"
0008    LEN      3   3
0009    TSETB    3   2   4
0010    TSETS    2   1   4  ; "size"
0011    GGET     2   5      ; "setmetatable"
0012    MOV      3   1
0013    TDUP     4   6
0014    UGET     5   0      ; Chunk
0015    TSETS    5   4   7  ; "__index"
0016    CALLT    2   3

-- BYTECODE -- Chunk.lua:0-12
0001    TNEW     0   0
0002    FNEW     1   1      ; Chunk.lua:3
0003    TSETS    1   0   0  ; "new"
0004    UCLO     0 => 0005
0005 => RET1     0   2

