-- BYTECODE -- Constants.lua:0-54
0001    TDUP     0   1
0002    TDUP     1   0
0003    TSETS    1   0   2  ; "HEADER_CHUNK_TYPE"
0004    TDUP     1   3
0005    TSETS    1   0   4  ; "HEADER_CHUNK_LENGTH"
0006    TDUP     1   5
0007    TSETS    1   0   6  ; "HEADER_CHUNK_FORMAT0"
0008    TDUP     1   7
0009    TSETS    1   0   8  ; "HEADER_CHUNK_FORMAT1"
0010    TDUP     1   9
0011    TSETS    1   0  10  ; "HEADER_CHUNK_DIVISION"
0012    TDUP     1  11
0013    TSETS    1   0  12  ; "TRACK_CHUNK_TYPE"
0014    TDUP     1  13
0015    TSETS    1   0  14  ; "META_END_OF_TRACK_ID"
0016    TNEW     1   0
0017    TSETS    1   0  15  ; "NOTES"
0018    TNEW     1  13
0019    TDUP     2  16
0020    TSETB    2   1   1
0021    TDUP     2  17
0022    TSETB    2   1   2
0023    TDUP     2  18
0024    TSETB    2   1   3
0025    TDUP     2  19
0026    TSETB    2   1   4
0027    TDUP     2  20
0028    TSETB    2   1   5
0029    TDUP     2  21
0030    TSETB    2   1   6
0031    TDUP     2  22
0032    TSETB    2   1   7
0033    TDUP     2  23
0034    TSETB    2   1   8
0035    TDUP     2  24
0036    TSETB    2   1   9
0037    TDUP     2  25
0038    TSETB    2   1  10
0039    TDUP     2  26
0040    TSETB    2   1  11
0041    TDUP     2  27
0042    TSETB    2   1  12
0043    KSHORT   2   0
0044    KSHORT   3  -1
0045    KSHORT   4   9
0046    KSHORT   5   1
0047    FORI     3 => 0067
0048 => GGET     7  28      ; "ipairs"
0049    MOV      8   1
0050    CALL     7   4   2
0051    JMP     10 => 0064
0052 => GGET    12  28      ; "ipairs"
0053    MOV     13  11
0054    CALL    12   4   2
0055    JMP     15 => 0061
0056 => TGETS   17   0  15  ; "NOTES"
0057    MOV     18  16
0058    MOV     19   6
0059    CAT     18  18  19
0060    TSETV    2  17  18
0061 => ITERC   15   3   3
0062    ITERL   15 => 0056
0063    ADDVN    2   2   0  ; 1
0064 => ITERC   10   3   3
0065    ITERL   10 => 0052
0066    FORL     3 => 0048
0067 => RET1     0   2

