
main <./LuaMidi/Constants.lua:0,0> (130 instructions, 520 bytes at 0x7f8068c068b0)
0+ params, 20 slots, 0 upvalues, 17 locals, 66 constants, 0 functions
	1	[1]	NEWTABLE 	0 0 19
	2	[2]	NEWTABLE 	1 4 0
	3	[2]	LOADK    	2 -2	; 77
	4	[2]	LOADK    	3 -3	; 84
	5	[2]	LOADK    	4 -4	; 104
	6	[2]	LOADK    	5 -5	; 100
	7	[2]	SETLIST  	1 4 1	; 1
	8	[2]	SETTABLE 	0 -1 1	; "HEADER_CHUNK_TYPE" -
	9	[3]	NEWTABLE 	1 4 0
	10	[3]	LOADK    	2 -7	; 0
	11	[3]	LOADK    	3 -7	; 0
	12	[3]	LOADK    	4 -7	; 0
	13	[3]	LOADK    	5 -8	; 6
	14	[3]	SETLIST  	1 4 1	; 1
	15	[3]	SETTABLE 	0 -6 1	; "HEADER_CHUNK_LENGTH" -
	16	[4]	NEWTABLE 	1 2 0
	17	[4]	LOADK    	2 -7	; 0
	18	[4]	LOADK    	3 -7	; 0
	19	[4]	SETLIST  	1 2 1	; 1
	20	[4]	SETTABLE 	0 -9 1	; "HEADER_CHUNK_FORMAT0" -
	21	[5]	NEWTABLE 	1 2 0
	22	[5]	LOADK    	2 -7	; 0
	23	[5]	LOADK    	3 -11	; 1
	24	[5]	SETLIST  	1 2 1	; 1
	25	[5]	SETTABLE 	0 -10 1	; "HEADER_CHUNK_FORMAT1" -
	26	[6]	NEWTABLE 	1 2 0
	27	[6]	LOADK    	2 -7	; 0
	28	[6]	LOADK    	3 -13	; 128
	29	[6]	SETLIST  	1 2 1	; 1
	30	[6]	SETTABLE 	0 -12 1	; "HEADER_CHUNK_DIVISION" -
	31	[7]	NEWTABLE 	1 4 0
	32	[7]	LOADK    	2 -2	; 77
	33	[7]	LOADK    	3 -3	; 84
	34	[7]	LOADK    	4 -15	; 114
	35	[7]	LOADK    	5 -16	; 107
	36	[7]	SETLIST  	1 4 1	; 1
	37	[7]	SETTABLE 	0 -14 1	; "TRACK_CHUNK_TYPE" -
	38	[8]	SETTABLE 	0 -17 -18	; "META_EVENT_ID" 255
	39	[9]	SETTABLE 	0 -19 -11	; "META_TEXT_ID" 1
	40	[10]	SETTABLE 	0 -20 -21	; "META_COPYRIGHT_ID" 2
	41	[11]	SETTABLE 	0 -22 -23	; "META_TRACK_NAME_ID" 3
	42	[12]	SETTABLE 	0 -24 -25	; "META_INSTRUMENT_NAME_ID" 4
	43	[13]	SETTABLE 	0 -26 -27	; "META_LYRIC_ID" 5
	44	[14]	SETTABLE 	0 -28 -8	; "META_MARKER_ID" 6
	45	[15]	SETTABLE 	0 -29 -30	; "META_CUE_POINT" 7
	46	[16]	SETTABLE 	0 -31 -32	; "META_TEMPO_ID" 81
	47	[17]	SETTABLE 	0 -33 -3	; "META_SMTPE_OFFSET" 84
	48	[18]	SETTABLE 	0 -34 -35	; "META_TIME_SIGNATURE_ID" 88
	49	[19]	SETTABLE 	0 -36 -37	; "META_KEY_SIGNATURE_ID" 89
	50	[20]	NEWTABLE 	1 2 0
	51	[20]	LOADK    	2 -39	; 47
	52	[20]	LOADK    	3 -7	; 0
	53	[20]	SETLIST  	1 2 1	; 1
	54	[20]	SETTABLE 	0 -38 1	; "META_END_OF_TRACK_ID" -
	55	[23]	SETTABLE 	0 -40 -41	; "PROGRAM_CHANGE_STATUS" 192
	56	[24]	NEWTABLE 	1 0 0
	57	[24]	SETTABLE 	0 -42 1	; "NOTES" -
	58	[27]	NEWTABLE 	1 12 0
	59	[27]	NEWTABLE 	2 2 0
	60	[28]	LOADK    	3 -43	; "C"
	61	[28]	LOADK    	4 -44	; "B#"
	62	[28]	SETLIST  	2 2 1	; 1
	63	[28]	NEWTABLE 	3 2 0
	64	[29]	LOADK    	4 -45	; "C#"
	65	[29]	LOADK    	5 -46	; "Db"
	66	[29]	SETLIST  	3 2 1	; 1
	67	[29]	NEWTABLE 	4 1 0
	68	[30]	LOADK    	5 -47	; "D"
	69	[30]	SETLIST  	4 1 1	; 1
	70	[30]	NEWTABLE 	5 2 0
	71	[31]	LOADK    	6 -48	; "D#"
	72	[31]	LOADK    	7 -49	; "Eb"
	73	[31]	SETLIST  	5 2 1	; 1
	74	[31]	NEWTABLE 	6 2 0
	75	[32]	LOADK    	7 -50	; "E"
	76	[32]	LOADK    	8 -51	; "Fb"
	77	[32]	SETLIST  	6 2 1	; 1
	78	[32]	NEWTABLE 	7 2 0
	79	[33]	LOADK    	8 -52	; "F"
	80	[33]	LOADK    	9 -53	; "E#"
	81	[33]	SETLIST  	7 2 1	; 1
	82	[33]	NEWTABLE 	8 2 0
	83	[34]	LOADK    	9 -54	; "F#"
	84	[34]	LOADK    	10 -55	; "Gb"
	85	[34]	SETLIST  	8 2 1	; 1
	86	[34]	NEWTABLE 	9 1 0
	87	[35]	LOADK    	10 -56	; "G"
	88	[35]	SETLIST  	9 1 1	; 1
	89	[35]	NEWTABLE 	10 2 0
	90	[36]	LOADK    	11 -57	; "G#"
	91	[36]	LOADK    	12 -58	; "Ab"
	92	[36]	SETLIST  	10 2 1	; 1
	93	[36]	NEWTABLE 	11 1 0
	94	[37]	LOADK    	12 -59	; "A"
	95	[37]	SETLIST  	11 1 1	; 1
	96	[37]	NEWTABLE 	12 2 0
	97	[38]	LOADK    	13 -60	; "A#"
	98	[38]	LOADK    	14 -61	; "Bb"
	99	[38]	SETLIST  	12 2 1	; 1
	100	[38]	NEWTABLE 	13 2 0
	101	[39]	LOADK    	14 -62	; "B"
	102	[39]	LOADK    	15 -63	; "Cb"
	103	[39]	SETLIST  	13 2 1	; 1
	104	[40]	SETLIST  	1 12 1	; 1
	105	[42]	LOADK    	2 -7	; 0
	106	[43]	LOADK    	3 -64	; -1
	107	[43]	LOADK    	4 -65	; 9
	108	[43]	LOADK    	5 -11	; 1
	109	[43]	FORPREP  	3 18	; to 128
	110	[45]	GETGLOBAL	7 -66	; ipairs
	111	[45]	MOVE     	8 1
	112	[45]	CALL     	7 2 4
	113	[45]	JMP      	12	; to 126
	114	[46]	GETGLOBAL	12 -66	; ipairs
	115	[46]	MOVE     	13 11
	116	[46]	CALL     	12 2 4
	117	[46]	JMP      	5	; to 123
	118	[47]	GETTABLE 	17 0 -42	; "NOTES"
	119	[47]	MOVE     	18 16
	120	[47]	MOVE     	19 6
	121	[47]	CONCAT   	18 18 19
	122	[47]	SETTABLE 	17 18 2
	123	[46]	TFORLOOP 	12 2
	124	[47]	JMP      	-7	; to 118
	125	[49]	ADD      	2 2 -11	; - 1
	126	[45]	TFORLOOP 	7 2
	127	[49]	JMP      	-14	; to 114
	128	[43]	FORLOOP  	3 -19	; to 110
	129	[53]	RETURN   	0 2
	130	[53]	RETURN   	0 1
