
main <./LuaMidi/MetaEvent.lua:0,0> (14 instructions, 56 bytes at 0x7fb7aac068b0)
0+ params, 4 slots, 0 upvalues, 3 locals, 4 constants, 1 function
	1	[1]	GETGLOBAL	0 -1	; require
	2	[1]	LOADK    	1 -2	; "LuaMidi.Constants"
	3	[1]	CALL     	0 2 2
	4	[2]	GETGLOBAL	1 -1	; require
	5	[2]	LOADK    	2 -3	; "LuaMidi.Util"
	6	[2]	CALL     	1 2 2
	7	[4]	NEWTABLE 	2 0 0
	8	[15]	CLOSURE  	3 0	; 0x7fb7aac06bb0
	9	[15]	MOVE     	0 1
	10	[15]	MOVE     	0 0
	11	[15]	MOVE     	0 2
	12	[6]	SETTABLE 	2 -4 3	; "new" -
	13	[17]	RETURN   	2 2
	14	[17]	RETURN   	0 1

function <./LuaMidi/MetaEvent.lua:6,15> (30 instructions, 120 bytes at 0x7fb7aac06bb0)
1 param, 7 slots, 3 upvalues, 3 locals, 9 constants, 0 functions
	1	[7]	GETUPVAL 	1 0	; Util
	2	[7]	GETTABLE 	1 1 -1	; "num_to_var_length"
	3	[7]	LOADK    	2 -2	; 0
	4	[7]	CALL     	1 2 2
	5	[8]	GETUPVAL 	2 0	; Util
	6	[8]	GETTABLE 	2 2 -3	; "table_concat"
	7	[8]	MOVE     	3 1
	8	[8]	NEWTABLE 	4 1 0
	9	[8]	GETUPVAL 	5 1	; Constants
	10	[8]	GETTABLE 	5 5 -4	; "META_EVENT_ID"
	11	[8]	SETLIST  	4 1 1	; 1
	12	[8]	CALL     	2 3 2
	13	[8]	MOVE     	1 2
	14	[9]	GETUPVAL 	2 0	; Util
	15	[9]	GETTABLE 	2 2 -3	; "table_concat"
	16	[9]	MOVE     	3 1
	17	[9]	GETTABLE 	4 0 -5	; "data"
	18	[9]	CALL     	2 3 2
	19	[9]	MOVE     	1 2
	20	[10]	NEWTABLE 	2 0 2
	21	[11]	SETTABLE 	2 -6 -7	; "type" "meta"
	22	[12]	SETTABLE 	2 -5 1	; "data" -
	23	[14]	GETGLOBAL	3 -8	; setmetatable
	24	[14]	MOVE     	4 2
	25	[14]	NEWTABLE 	5 0 1
	26	[14]	GETUPVAL 	6 2	; MetaEvent
	27	[14]	SETTABLE 	5 -9 6	; "__index" -
	28	[14]	TAILCALL 	3 3 0
	29	[14]	RETURN   	3 0
	30	[15]	RETURN   	0 1
