-- BYTECODE -- NoteEvent.lua:19-25
0001    IST          0
0002    JMP      1 => 0004
0003    KSHORT   0  50
0004 => KSHORT   1 100
0005    ISGE     1   0
0006    JMP      1 => 0008
0007    KSHORT   0 100
0008 => UGET     1   0      ; Util
0009    TGETS    1   1   0  ; "round"
0010    DIVVN    2   0   0  ; 100
0011    MULVN    2   2   1  ; 127
0012    CALLT    1   2

-- BYTECODE -- NoteEvent.lua:27-33
0001    GGET     2   0      ; "tostring"
0002    MOV      3   0
0003    CALL     2   2   2
0004    MOV      3   2
0005    TGETS    2   2   1  ; "lower"
0006    CALL     2   2   2
0007    MOV      3   2
0008    TGETS    2   2   2  ; "sub"
0009    KSHORT   4   1
0010    KSHORT   5   1
0011    CALL     2   2   4
0012    ISNES    2   3      ; "t"
0013    JMP      2 => 0021
0014    GGET     2   4      ; "string"
0015    TGETS    2   2   5  ; "match"
0016    GGET     3   0      ; "tostring"
0017    MOV      4   0
0018    CALL     3   2   2
0019    KSTR     4   6      ; "%d+"
0020    CALLT    2   3
0021 => UGET     2   0      ; Util
0022    TGETS    2   2   7  ; "number_from_bytes"
0023    UGET     3   1      ; Constants
0024    TGETS    3   3   8  ; "HEADER_CHUNK_DIVISION"
0025    CALL     2   2   2
0026    UGET     3   0      ; Util
0027    TGETS    3   3   9  ; "round"
0028    UGET     4   2      ; self
0029    TGETS    4   4  10  ; "get_duration_multiplier"
0030    MOV      5   0
0031    MOV      6   1
0032    CALL     4   2   3
0033    MULVV    4   2   4
0034    CALLT    3   2

-- BYTECODE -- NoteEvent.lua:34-62
0001    GGET     2   0      ; "tostring"
0002    MOV      3   0
0003    CALL     2   2   2
0004    MOV      0   2
0005    ISNES    0   1      ; "0"
0006    JMP      2 => 0010
0007    KSHORT   2   0
0008    RET1     2   2
0009    JMP      2 => 0061
0010 => ISNES    0   2      ; "1"
0011    JMP      2 => 0015
0012    KSHORT   2   4
0013    RET1     2   2
0014    JMP      2 => 0061
0015 => ISNES    0   3      ; "2"
0016    JMP      2 => 0020
0017    KSHORT   2   2
0018    RET1     2   2
0019    JMP      2 => 0061
0020 => ISNES    0   4      ; "d2"
0021    JMP      2 => 0025
0022    KSHORT   2   3
0023    RET1     2   2
0024    JMP      2 => 0061
0025 => ISNES    0   5      ; "4"
0026    JMP      2 => 0030
0027    KSHORT   2   1
0028    RET1     2   2
0029    JMP      2 => 0061
0030 => ISNES    0   6      ; "d4"
0031    JMP      2 => 0035
0032    KNUM     2   0      ; 1.5
0033    RET1     2   2
0034    JMP      2 => 0061
0035 => ISNES    0   7      ; "8"
0036    JMP      2 => 0040
0037    KNUM     2   1      ; 0.5
0038    RET1     2   2
0039    JMP      2 => 0061
0040 => ISNES    0   8      ; "8t"
0041    JMP      2 => 0045
0042    KNUM     2   2      ; 0.33
0043    RET1     2   2
0044    JMP      2 => 0061
0045 => ISNES    0   9      ; "d8"
0046    JMP      2 => 0050
0047    KNUM     2   3      ; 0.75
0048    RET1     2   2
0049    JMP      2 => 0061
0050 => ISNES    0  10      ; "16"
0051    JMP      2 => 0055
0052    KNUM     2   4      ; 0.25
0053    RET1     2   2
0054    JMP      2 => 0061
0055 => ISNES    1  11      ; "note"
0056    JMP      2 => 0059
0057    KSHORT   2   1
0058    RET1     2   2
0059 => KSHORT   2   0
0060    RET1     2   2
0061 => RET0     0   1

-- BYTECODE -- NoteEvent.lua:63-65
0001    UGET     0   0      ; self
0002    TGETS    0   0   0  ; "channel"
0003    ADDNV    0   0   0  ; 144
0004    SUBVN    0   0   1  ; 1
0005    RET1     0   2

-- BYTECODE -- NoteEvent.lua:66-68
0001    UGET     0   0      ; self
0002    TGETS    0   0   0  ; "channel"
0003    ADDNV    0   0   0  ; 128
0004    SUBVN    0   0   1  ; 1
0005    RET1     0   2

-- BYTECODE -- NoteEvent.lua:69-143
0001    UGET     0   0      ; self
0002    TNEW     1   0
0003    TSETS    1   0   0  ; "data"
0004    UGET     0   0      ; self
0005    TGETS    0   0   1  ; "get_tick_duration"
0006    UGET     1   0      ; self
0007    TGETS    1   1   2  ; "duration"
0008    KSTR     2   3      ; "note"
0009    CALL     0   2   3
0010    UGET     1   0      ; self
0011    TGETS    1   1   1  ; "get_tick_duration"
0012    UGET     2   0      ; self
0013    TGETS    2   2   4  ; "wait"
0014    KSTR     3   5      ; "rest"
0015    CALL     1   2   3
0016    KNIL     2   3
0017    GGET     4   6      ; "type"
0018    UGET     5   0      ; self
0019    TGETS    5   5   7  ; "pitch"
0020    CALL     4   2   2
0021    ISNES    4   8      ; "table"
0022    JMP      4 => 0261
0023    UGET     4   0      ; self
0024    TGETS    4   4   9  ; "sequential"
0025    IST          4
0026    JMP      4 => 0152
0027    KSHORT   4   1
0028    UGET     5   0      ; self
0029    TGETS    5   5  10  ; "repetition"
0030    KSHORT   6   1
0031    FORI     4 => 0151
0032 => GGET     8  11      ; "ipairs"
0033    UGET     9   0      ; self
0034    TGETS    9   9   7  ; "pitch"
0035    CALL     8   4   2
0036    JMP     11 => 0089
0037 => TNEW    13   0
0038    KPRI    14   0
0039    ISNEN   11   0      ; 1
0040    JMP     15 => 0065
0041    UGET    15   1      ; Util
0042    TGETS   15  15  12  ; "num_to_var_length"
0043    MOV     16   1
0044    CALL    15   2   2
0045    MOV     14  15
0046    LEN     15  14
0047    ADDVN   15  15   0  ; 1
0048    UGET    16   0      ; self
0049    TGETS   16  16  13  ; "get_note_on_status"
0050    CALL    16   2   1
0051    TSETV   16  14  15
0052    LEN     15  14
0053    ADDVN   15  15   0  ; 1
0054    UGET    16   1      ; Util
0055    TGETS   16  16  14  ; "get_pitch"
0056    MOV     17  12
0057    CALL    16   2   2
0058    TSETV   16  14  15
0059    LEN     15  14
0060    ADDVN   15  15   0  ; 1
0061    UGET    16   0      ; self
0062    TGETS   16  16  15  ; "velocity"
0063    TSETV   16  14  15
0064    JMP     15 => 0075
0065 => TDUP    15  16
0066    UGET    16   1      ; Util
0067    TGETS   16  16  14  ; "get_pitch"
0068    MOV     17  12
0069    CALL    16   2   2
0070    TSETB   16  15   2
0071    UGET    16   0      ; self
0072    TGETS   16  16  15  ; "velocity"
0073    TSETB   16  15   3
0074    MOV     14  15
0075 => TSETS   14  13   0  ; "data"
0076    UGET    15   2      ; NoteOnEvent
0077    TGETS   15  15  17  ; "new"
0078    MOV     16  13
0079    CALL    15   2   2
0080    MOV      2  15
0081    UGET    15   0      ; self
0082    UGET    16   1      ; Util
0083    TGETS   16  16  18  ; "table_concat"
0084    UGET    17   0      ; self
0085    TGETS   17  17   0  ; "data"
0086    TGETS   18   2   0  ; "data"
0087    CALL    16   2   3
0088    TSETS   16  15   0  ; "data"
0089 => ITERC   11   3   3
0090    ITERL   11 => 0037
0091    GGET     8  11      ; "ipairs"
0092    UGET     9   0      ; self
0093    TGETS    9   9   7  ; "pitch"
0094    CALL     8   4   2
0095    JMP     11 => 0148
0096 => TNEW    13   0
0097    KPRI    14   0
0098    ISNEN   11   0      ; 1
0099    JMP     15 => 0124
0100    UGET    15   1      ; Util
0101    TGETS   15  15  12  ; "num_to_var_length"
0102    MOV     16   0
0103    CALL    15   2   2
0104    MOV     14  15
0105    LEN     15  14
0106    ADDVN   15  15   0  ; 1
0107    UGET    16   0      ; self
0108    TGETS   16  16  19  ; "get_note_off_status"
0109    CALL    16   2   1
0110    TSETV   16  14  15
0111    LEN     15  14
0112    ADDVN   15  15   0  ; 1
0113    UGET    16   1      ; Util
0114    TGETS   16  16  14  ; "get_pitch"
0115    MOV     17  12
0116    CALL    16   2   2
0117    TSETV   16  14  15
0118    LEN     15  14
0119    ADDVN   15  15   0  ; 1
0120    UGET    16   0      ; self
0121    TGETS   16  16  15  ; "velocity"
0122    TSETV   16  14  15
0123    JMP     15 => 0134
0124 => TDUP    15  20
0125    UGET    16   1      ; Util
0126    TGETS   16  16  14  ; "get_pitch"
0127    MOV     17  12
0128    CALL    16   2   2
0129    TSETB   16  15   2
0130    UGET    16   0      ; self
0131    TGETS   16  16  15  ; "velocity"
0132    TSETB   16  15   3
0133    MOV     14  15
0134 => TSETS   14  13   0  ; "data"
0135    UGET    15   3      ; NoteOffEvent
0136    TGETS   15  15  17  ; "new"
0137    MOV     16  13
0138    CALL    15   2   2
0139    MOV      3  15
0140    UGET    15   0      ; self
0141    UGET    16   1      ; Util
0142    TGETS   16  16  18  ; "table_concat"
0143    UGET    17   0      ; self
0144    TGETS   17  17   0  ; "data"
0145    TGETS   18   3   0  ; "data"
0146    CALL    16   2   3
0147    TSETS   16  15   0  ; "data"
0148 => ITERC   11   3   3
0149    ITERL   11 => 0096
0150    FORL     4 => 0032
0151 => JMP      4 => 0264
0152 => KSHORT   4   1
0153    UGET     5   0      ; self
0154    TGETS    5   5  10  ; "repetition"
0155    KSHORT   6   1
0156    FORI     4 => 0260
0157 => GGET     8  11      ; "ipairs"
0158    UGET     9   0      ; self
0159    TGETS    9   9   7  ; "pitch"
0160    CALL     8   4   2
0161    JMP     11 => 0257
0162 => TNEW    13   0
0163    KSHORT  14   1
0164    ISGE    14  11
0165    JMP     14 => 0167
0166    KSHORT   1   0
0167 => UGET    14   0      ; self
0168    TGETS   14  14   2  ; "duration"
0169    ISNES   14  21      ; "8t"
0170    JMP     14 => 0183
0171    UGET    14   0      ; self
0172    TGETS   14  14   7  ; "pitch"
0173    LEN     14  14
0174    ISNEV   11  14
0175    JMP     14 => 0183
0176    UGET    14   1      ; Util
0177    TGETS   14  14  22  ; "number_from_bytes"
0178    UGET    15   4      ; Constants
0179    TGETS   15  15  23  ; "HEADER_CHUNK_DIVISION"
0180    CALL    14   2   2
0181    MULVN   15   0   1  ; 2
0182    SUBVV    0  14  15
0183 => TNEW    14   0
0184    TNEW    15   0
0185    UGET    16   1      ; Util
0186    TGETS   16  16  12  ; "num_to_var_length"
0187    MOV     17   1
0188    CALL    16   2   2
0189    LEN     17  16
0190    ADDVN   17  17   0  ; 1
0191    UGET    18   0      ; self
0192    TGETS   18  18  13  ; "get_note_on_status"
0193    CALL    18   2   1
0194    TSETV   18  16  17
0195    LEN     17  16
0196    ADDVN   17  17   0  ; 1
0197    UGET    18   1      ; Util
0198    TGETS   18  18  14  ; "get_pitch"
0199    MOV     19  12
0200    CALL    18   2   2
0201    TSETV   18  16  17
0202    LEN     17  16
0203    ADDVN   17  17   0  ; 1
0204    UGET    18   0      ; self
0205    TGETS   18  18  15  ; "velocity"
0206    TSETV   18  16  17
0207    TSETS   16  14   0  ; "data"
0208    UGET    17   2      ; NoteOnEvent
0209    TGETS   17  17  17  ; "new"
0210    MOV     18  14
0211    CALL    17   2   2
0212    MOV      2  17
0213    UGET    17   1      ; Util
0214    TGETS   17  17  12  ; "num_to_var_length"
0215    MOV     18   0
0216    CALL    17   2   2
0217    LEN     18  17
0218    ADDVN   18  18   0  ; 1
0219    UGET    19   0      ; self
0220    TGETS   19  19  19  ; "get_note_off_status"
0221    CALL    19   2   1
0222    TSETV   19  17  18
0223    LEN     18  17
0224    ADDVN   18  18   0  ; 1
0225    UGET    19   1      ; Util
0226    TGETS   19  19  14  ; "get_pitch"
0227    MOV     20  12
0228    CALL    19   2   2
0229    TSETV   19  17  18
0230    LEN     18  17
0231    ADDVN   18  18   0  ; 1
0232    UGET    19   0      ; self
0233    TGETS   19  19  15  ; "velocity"
0234    TSETV   19  17  18
0235    TSETS   17  15   0  ; "data"
0236    UGET    18   3      ; NoteOffEvent
0237    TGETS   18  18  17  ; "new"
0238    MOV     19  15
0239    CALL    18   2   2
0240    MOV      3  18
0241    UGET    18   0      ; self
0242    UGET    19   1      ; Util
0243    TGETS   19  19  18  ; "table_concat"
0244    UGET    20   0      ; self
0245    TGETS   20  20   0  ; "data"
0246    MOV     21  16
0247    CALL    19   2   3
0248    TSETS   19  18   0  ; "data"
0249    UGET    18   0      ; self
0250    UGET    19   1      ; Util
0251    TGETS   19  19  18  ; "table_concat"
0252    UGET    20   0      ; self
0253    TGETS   20  20   0  ; "data"
0254    MOV     21  17
0255    CALL    19   2   3
0256    TSETS   19  18   0  ; "data"
0257 => ITERC   11   3   3
0258    ITERL   11 => 0162
0259    FORL     4 => 0157
0260 => JMP      4 => 0264
0261 => GGET     4  24      ; "print"
0262    KSTR     5  25      ; "Pitch must be an array."
0263    CALL     4   1   2
0264 => RET0     0   1

-- BYTECODE -- NoteEvent.lua:8-146
0001    TDUP     1   0
0002    TGETS    2   0   1  ; "pitch"
0003    TSETS    2   1   1  ; "pitch"
0004    TGETS    2   0   2  ; "wait"
0005    IST          2
0006    JMP      3 => 0008
0007    KSHORT   2   0
0008 => TSETS    2   1   2  ; "wait"
0009    TGETS    2   0   3  ; "duration"
0010    TSETS    2   1   3  ; "duration"
0011    TGETS    2   0   4  ; "sequential"
0012    IST          2
0013    JMP      3 => 0015
0014    KPRI     2   1
0015 => TSETS    2   1   4  ; "sequential"
0016    TGETS    2   0   5  ; "velocity"
0017    IST          2
0018    JMP      3 => 0020
0019    KSHORT   2  50
0020 => TSETS    2   1   5  ; "velocity"
0021    TGETS    2   0   6  ; "channel"
0022    IST          2
0023    JMP      3 => 0025
0024    KSHORT   2   1
0025 => TSETS    2   1   6  ; "channel"
0026    TGETS    2   0   7  ; "repetition"
0027    IST          2
0028    JMP      3 => 0030
0029    KSHORT   2   1
0030 => TSETS    2   1   7  ; "repetition"
0031    FNEW     2   9      ; NoteEvent.lua:19
0032    TSETS    2   1   8  ; "convert_velocity"
0033    TGETS    2   1   8  ; "convert_velocity"
0034    TGETS    3   1   5  ; "velocity"
0035    CALL     2   2   2
0036    TSETS    2   1   5  ; "velocity"
0037    FNEW     2  11      ; NoteEvent.lua:27
0038    TSETS    2   1  10  ; "get_tick_duration"
0039    FNEW     2  13      ; NoteEvent.lua:34
0040    TSETS    2   1  12  ; "get_duration_multiplier"
0041    FNEW     2  15      ; NoteEvent.lua:63
0042    TSETS    2   1  14  ; "get_note_on_status"
0043    FNEW     2  17      ; NoteEvent.lua:66
0044    TSETS    2   1  16  ; "get_note_off_status"
0045    FNEW     2  19      ; NoteEvent.lua:69
0046    TSETS    2   1  18  ; "build_data"
0047    TGETS    2   1  18  ; "build_data"
0048    CALL     2   1   1
0049    GGET     2  20      ; "setmetatable"
0050    MOV      3   1
0051    TDUP     4  21
0052    UGET     5   4      ; NoteEvent
0053    TSETS    5   4  22  ; "__index"
0054    UCLO     0 => 0055
0055 => CALLT    2   3

-- BYTECODE -- NoteEvent.lua:0-149
0001    GGET     0   0      ; "require"
0002    KSTR     1   1      ; "LuaMidi.Constants"
0003    CALL     0   2   2
0004    GGET     1   0      ; "require"
0005    KSTR     2   2      ; "LuaMidi.Util"
0006    CALL     1   2   2
0007    GGET     2   0      ; "require"
0008    KSTR     3   3      ; "LuaMidi.NoteOnEvent"
0009    CALL     2   2   2
0010    GGET     3   0      ; "require"
0011    KSTR     4   4      ; "LuaMidi.NoteOffEvent"
0012    CALL     3   2   2
0013    TNEW     4   0
0014    FNEW     5   6      ; NoteEvent.lua:8
0015    TSETS    5   4   5  ; "new"
0016    UCLO     0 => 0017
0017 => RET1     4   2

