
main <./LuaMidi/Writer.lua:0,0> (33 instructions, 132 bytes at 0x7f9eff4068a0)
0+ params, 6 slots, 0 upvalues, 5 locals, 11 constants, 6 functions
	1	[1]	GETGLOBAL	0 -1	; require
	2	[1]	LOADK    	1 -2	; "LuaMidi.Util"
	3	[1]	CALL     	0 2 2
	4	[2]	GETGLOBAL	1 -1	; require
	5	[2]	LOADK    	2 -3	; "LuaMidi.Constants"
	6	[2]	CALL     	1 2 2
	7	[3]	GETGLOBAL	2 -1	; require
	8	[3]	LOADK    	3 -4	; "LuaMidi.Chunk"
	9	[3]	CALL     	2 2 2
	10	[4]	GETGLOBAL	3 -1	; require
	11	[4]	LOADK    	4 -5	; "LuaMidi.MetaEvent"
	12	[4]	CALL     	3 2 2
	13	[6]	NEWTABLE 	4 0 0
	14	[27]	CLOSURE  	5 0	; 0x7f9eff406fd0
	15	[27]	MOVE     	0 1
	16	[27]	MOVE     	0 0
	17	[27]	MOVE     	0 2
	18	[27]	MOVE     	0 3
	19	[27]	MOVE     	0 4
	20	[8]	SETTABLE 	4 -6 5	; "new" -
	21	[37]	CLOSURE  	5 1	; 0x7f9eff407740
	22	[37]	MOVE     	0 0
	23	[29]	SETTABLE 	4 -7 5	; "build_file" -
	24	[41]	CLOSURE  	5 2	; 0x7f9eff407ba0
	25	[39]	SETTABLE 	4 -8 5	; "base64" -
	26	[45]	CLOSURE  	5 3	; 0x7f9eff406bd0
	27	[43]	SETTABLE 	4 -9 5	; "data_URI" -
	28	[50]	CLOSURE  	5 4	; 0x7f9eff406d50
	29	[47]	SETTABLE 	4 -10 5	; "stdout" -
	30	[64]	CLOSURE  	5 5	; 0x7f9eff406e20
	31	[52]	SETTABLE 	4 -11 5	; "save_MIDI" -
	32	[66]	RETURN   	4 2
	33	[66]	RETURN   	0 1

function <./LuaMidi/Writer.lua:8,27> (64 instructions, 256 bytes at 0x7f9eff406fd0)
1 param, 14 slots, 5 upvalues, 9 locals, 16 constants, 0 functions
	1	[9]	NEWTABLE 	1 0 1
	2	[10]	NEWTABLE 	2 0 0
	3	[10]	SETTABLE 	1 -1 2	; "data" -
	4	[12]	GETUPVAL 	2 0	; Constants
	5	[12]	GETTABLE 	2 2 -2	; "HEADER_CHUNK_FORMAT0"
	6	[13]	LEN      	3 0
	7	[13]	LT       	0 -3 3	; 1 -
	8	[13]	JMP      	2	; to 11
	9	[14]	GETUPVAL 	3 0	; Constants
	10	[14]	GETTABLE 	2 3 -4	; "HEADER_CHUNK_FORMAT1"
	11	[16]	GETUPVAL 	3 1	; Util
	12	[16]	GETTABLE 	3 3 -5	; "table_concat"
	13	[16]	MOVE     	4 2
	14	[16]	GETUPVAL 	5 1	; Util
	15	[16]	GETTABLE 	5 5 -6	; "number_to_bytes"
	16	[16]	LEN      	6 0
	17	[16]	LOADK    	7 -7	; 2
	18	[16]	CALL     	5 3 0
	19	[16]	CALL     	3 0 2
	20	[17]	GETUPVAL 	4 1	; Util
	21	[17]	GETTABLE 	4 4 -5	; "table_concat"
	22	[17]	MOVE     	5 3
	23	[17]	GETUPVAL 	6 0	; Constants
	24	[17]	GETTABLE 	6 6 -8	; "HEADER_CHUNK_DIVISION"
	25	[17]	CALL     	4 3 2
	26	[17]	MOVE     	3 4
	27	[18]	GETTABLE 	4 1 -1	; "data"
	28	[18]	GETUPVAL 	5 2	; Chunk
	29	[18]	GETTABLE 	5 5 -9	; "new"
	30	[18]	NEWTABLE 	6 0 2
	31	[19]	GETUPVAL 	7 0	; Constants
	32	[19]	GETTABLE 	7 7 -11	; "HEADER_CHUNK_TYPE"
	33	[19]	SETTABLE 	6 -10 7	; "type" -
	34	[20]	SETTABLE 	6 -1 3	; "data" -
	35	[18]	CALL     	5 2 2
	36	[21]	SETTABLE 	4 -3 5	; 1 -
	37	[22]	GETGLOBAL	4 -12	; ipairs
	38	[22]	MOVE     	5 0
	39	[22]	CALL     	4 2 4
	40	[22]	JMP      	14	; to 55
	41	[23]	SELF     	9 8 -13	; "add_event"
	42	[23]	GETUPVAL 	11 3	; MetaEvent
	43	[23]	GETTABLE 	11 11 -9	; "new"
	44	[23]	NEWTABLE 	12 0 1
	45	[23]	GETUPVAL 	13 0	; Constants
	46	[23]	GETTABLE 	13 13 -14	; "META_END_OF_TRACK_ID"
	47	[23]	SETTABLE 	12 -1 13	; "data" -
	48	[23]	CALL     	11 2 0
	49	[23]	CALL     	9 0 1
	50	[24]	GETTABLE 	9 1 -1	; "data"
	51	[24]	GETTABLE 	10 1 -1	; "data"
	52	[24]	LEN      	10 10
	53	[24]	ADD      	10 10 -3	; - 1
	54	[24]	SETTABLE 	9 10 8
	55	[22]	TFORLOOP 	4 2
	56	[24]	JMP      	-16	; to 41
	57	[26]	GETGLOBAL	4 -15	; setmetatable
	58	[26]	MOVE     	5 1
	59	[26]	NEWTABLE 	6 0 1
	60	[26]	GETUPVAL 	7 4	; Writer
	61	[26]	SETTABLE 	6 -16 7	; "__index" -
	62	[26]	TAILCALL 	4 3 0
	63	[26]	RETURN   	4 0
	64	[27]	RETURN   	0 1

function <./LuaMidi/Writer.lua:29,37> (27 instructions, 108 bytes at 0x7f9eff407740)
1 param, 10 slots, 1 upvalue, 7 locals, 5 constants, 0 functions
	1	[30]	NEWTABLE 	1 0 0
	2	[31]	GETGLOBAL	2 -1	; ipairs
	3	[31]	GETTABLE 	3 0 -2	; "data"
	4	[31]	CALL     	2 2 4
	5	[31]	JMP      	18	; to 24
	6	[32]	GETUPVAL 	7 0	; Util
	7	[32]	GETTABLE 	7 7 -3	; "table_concat"
	8	[32]	MOVE     	8 1
	9	[32]	GETTABLE 	9 6 -4	; "type"
	10	[32]	CALL     	7 3 2
	11	[32]	MOVE     	1 7
	12	[33]	GETUPVAL 	7 0	; Util
	13	[33]	GETTABLE 	7 7 -3	; "table_concat"
	14	[33]	MOVE     	8 1
	15	[33]	GETTABLE 	9 6 -5	; "size"
	16	[33]	CALL     	7 3 2
	17	[33]	MOVE     	1 7
	18	[34]	GETUPVAL 	7 0	; Util
	19	[34]	GETTABLE 	7 7 -3	; "table_concat"
	20	[34]	MOVE     	8 1
	21	[34]	GETTABLE 	9 6 -2	; "data"
	22	[34]	CALL     	7 3 2
	23	[34]	MOVE     	1 7
	24	[31]	TFORLOOP 	2 2
	25	[34]	JMP      	-20	; to 6
	26	[36]	RETURN   	1 2
	27	[37]	RETURN   	0 1

function <./LuaMidi/Writer.lua:39,41> (1 instruction, 4 bytes at 0x7f9eff407ba0)
1 param, 2 slots, 0 upvalues, 1 local, 0 constants, 0 functions
	1	[41]	RETURN   	0 1

function <./LuaMidi/Writer.lua:43,45> (1 instruction, 4 bytes at 0x7f9eff406bd0)
1 param, 2 slots, 0 upvalues, 1 local, 0 constants, 0 functions
	1	[45]	RETURN   	0 1

function <./LuaMidi/Writer.lua:47,50> (8 instructions, 32 bytes at 0x7f9eff406d50)
1 param, 5 slots, 0 upvalues, 2 locals, 3 constants, 0 functions
	1	[48]	GETGLOBAL	1 -1	; require
	2	[48]	LOADK    	2 -2	; "mm"
	3	[48]	CALL     	1 2 2
	4	[49]	MOVE     	2 1
	5	[49]	SELF     	3 0 -3	; "build_file"
	6	[49]	CALL     	3 2 0
	7	[49]	CALL     	2 0 1
	8	[50]	RETURN   	0 1

function <./LuaMidi/Writer.lua:52,64> (55 instructions, 220 bytes at 0x7f9eff406e20)
3 params, 8 slots, 0 upvalues, 5 locals, 21 constants, 0 functions
	1	[53]	SELF     	3 1 -1	; "sub"
	2	[53]	LEN      	5 1
	3	[53]	SUB      	5 5 -2	; - 3
	4	[53]	CALL     	3 3 2
	5	[53]	EQ       	1 3 -3	; - ".mid"
	6	[53]	JMP      	3	; to 10
	7	[53]	MOVE     	3 1
	8	[53]	LOADK    	4 -3	; ".mid"
	9	[53]	CONCAT   	1 3 4
	10	[54]	GETGLOBAL	3 -4	; type
	11	[54]	MOVE     	4 2
	12	[54]	CALL     	3 2 2
	13	[54]	EQ       	0 3 -5	; - "string"
	14	[54]	JMP      	22	; to 37
	15	[54]	LEN      	3 2
	16	[54]	EQ       	1 3 -6	; - 0
	17	[54]	JMP      	19	; to 37
	18	[55]	GETGLOBAL	3 -7	; os
	19	[55]	GETTABLE 	3 3 -8	; "rename"
	20	[55]	MOVE     	4 2
	21	[55]	MOVE     	5 2
	22	[55]	CALL     	3 3 2
	23	[55]	TEST     	3 0 1
	24	[55]	JMP      	8	; to 33
	25	[56]	GETGLOBAL	3 -7	; os
	26	[56]	GETTABLE 	3 3 -9	; "execute"
	27	[56]	LOADK    	4 -10	; "mkdir "
	28	[56]	LOADK    	5 -11	; "'"
	29	[56]	MOVE     	6 2
	30	[56]	LOADK    	7 -11	; "'"
	31	[56]	CONCAT   	4 4 7
	32	[56]	CALL     	3 2 1
	33	[58]	MOVE     	3 2
	34	[58]	LOADK    	4 -12	; "/"
	35	[58]	MOVE     	5 1
	36	[58]	CONCAT   	1 3 5
	37	[60]	GETGLOBAL	3 -13	; io
	38	[60]	GETTABLE 	3 3 -14	; "open"
	39	[60]	MOVE     	4 1
	40	[60]	LOADK    	5 -15	; "wb"
	41	[60]	CALL     	3 3 2
	42	[61]	GETGLOBAL	4 -5	; string
	43	[61]	GETTABLE 	4 4 -16	; "char"
	44	[61]	GETGLOBAL	5 -17	; table
	45	[61]	GETTABLE 	5 5 -18	; "unpack"
	46	[61]	SELF     	6 0 -19	; "build_file"
	47	[61]	CALL     	6 2 0
	48	[61]	CALL     	5 0 0
	49	[61]	CALL     	4 0 2
	50	[62]	SELF     	5 3 -20	; "write"
	51	[62]	MOVE     	7 4
	52	[62]	CALL     	5 3 1
	53	[63]	SELF     	5 3 -21	; "close"
	54	[63]	CALL     	5 2 1
	55	[64]	RETURN   	0 1
