-- BYTECODE -- Writer.lua:8-27
0001    TDUP     1   0
0002    TNEW     2   0
0003    TSETS    2   1   1  ; "data"
0004    UGET     2   0      ; Constants
0005    TGETS    2   2   2  ; "HEADER_CHUNK_FORMAT0"
0006    LEN      3   0
0007    KSHORT   4   1
0008    ISGE     4   3
0009    JMP      3 => 0012
0010    UGET     3   0      ; Constants
0011    TGETS    2   3   3  ; "HEADER_CHUNK_FORMAT1"
0012 => UGET     3   1      ; Util
0013    TGETS    3   3   4  ; "table_concat"
0014    MOV      4   2
0015    UGET     5   1      ; Util
0016    TGETS    5   5   5  ; "number_to_bytes"
0017    LEN      6   0
0018    KSHORT   7   2
0019    CALL     5   0   3
0020    CALLM    3   2   1
0021    UGET     4   1      ; Util
0022    TGETS    4   4   4  ; "table_concat"
0023    MOV      5   3
0024    UGET     6   0      ; Constants
0025    TGETS    6   6   6  ; "HEADER_CHUNK_DIVISION"
0026    CALL     4   2   3
0027    MOV      3   4
0028    TGETS    4   1   1  ; "data"
0029    UGET     5   2      ; Chunk
0030    TGETS    5   5   7  ; "new"
0031    TDUP     6   9
0032    UGET     7   0      ; Constants
0033    TGETS    7   7   8  ; "HEADER_CHUNK_TYPE"
0034    TSETS    7   6  10  ; "type"
0035    TSETS    3   6   1  ; "data"
0036    CALL     5   2   2
0037    TSETB    5   4   1
0038    GGET     4  11      ; "ipairs"
0039    MOV      5   0
0040    CALL     4   4   2
0041    JMP      7 => 0057
0042 => MOV     10   8
0043    TGETS    9   8  12  ; "add_event"
0044    UGET    11   3      ; MetaEvent
0045    TGETS   11  11   7  ; "new"
0046    TDUP    12  14
0047    UGET    13   0      ; Constants
0048    TGETS   13  13  13  ; "META_END_OF_TRACK_ID"
0049    TSETS   13  12   1  ; "data"
0050    CALL    11   0   2
0051    CALLM    9   1   1
0052    TGETS    9   1   1  ; "data"
0053    TGETS   10   1   1  ; "data"
0054    LEN     10  10
0055    ADDVN   10  10   0  ; 1
0056    TSETV    8   9  10
0057 => ITERC    7   3   3
0058    ITERL    7 => 0042
0059    GGET     4  15      ; "setmetatable"
0060    MOV      5   1
0061    TDUP     6  16
0062    UGET     7   4      ; Writer
0063    TSETS    7   6  17  ; "__index"
0064    CALLT    4   3

-- BYTECODE -- Writer.lua:29-37
0001    TNEW     1   0
0002    GGET     2   0      ; "ipairs"
0003    TGETS    3   0   1  ; "data"
0004    CALL     2   4   2
0005    JMP      5 => 0024
0006 => UGET     7   0      ; Util
0007    TGETS    7   7   2  ; "table_concat"
0008    MOV      8   1
0009    TGETS    9   6   3  ; "type"
0010    CALL     7   2   3
0011    MOV      1   7
0012    UGET     7   0      ; Util
0013    TGETS    7   7   2  ; "table_concat"
0014    MOV      8   1
0015    TGETS    9   6   4  ; "size"
0016    CALL     7   2   3
0017    MOV      1   7
0018    UGET     7   0      ; Util
0019    TGETS    7   7   2  ; "table_concat"
0020    MOV      8   1
0021    TGETS    9   6   1  ; "data"
0022    CALL     7   2   3
0023    MOV      1   7
0024 => ITERC    5   3   3
0025    ITERL    5 => 0006
0026    RET1     1   2

-- BYTECODE -- Writer.lua:39-41
0001    RET0     0   1

-- BYTECODE -- Writer.lua:43-45
0001    RET0     0   1

-- BYTECODE -- Writer.lua:47-50
0001    GGET     1   0      ; "require"
0002    KSTR     2   1      ; "mm"
0003    CALL     1   2   2
0004    MOV      2   1
0005    MOV      4   0
0006    TGETS    3   0   2  ; "build_file"
0007    CALL     3   0   2
0008    CALLM    2   1   0
0009    RET0     0   1

-- BYTECODE -- Writer.lua:52-64
0001    MOV      4   1
0002    TGETS    3   1   0  ; "sub"
0003    LEN      5   1
0004    SUBVN    5   5   0  ; 3
0005    CALL     3   2   3
0006    ISEQS    3   1      ; ".mid"
0007    JMP      3 => 0011
0008    MOV      3   1
0009    KSTR     4   1      ; ".mid"
0010    CAT      1   3   4
0011 => GGET     3   2      ; "type"
0012    MOV      4   2
0013    CALL     3   2   2
0014    ISNES    3   3      ; "string"
0015    JMP      3 => 0038
0016    LEN      3   2
0017    ISEQN    3   1      ; 0
0018    JMP      3 => 0038
0019    GGET     3   4      ; "os"
0020    TGETS    3   3   5  ; "rename"
0021    MOV      4   2
0022    MOV      5   2
0023    CALL     3   2   3
0024    IST          3
0025    JMP      3 => 0034
0026    GGET     3   4      ; "os"
0027    TGETS    3   3   6  ; "execute"
0028    KSTR     4   7      ; "mkdir "
0029    KSTR     5   8      ; "'"
0030    MOV      6   2
0031    KSTR     7   8      ; "'"
0032    CAT      4   4   7
0033    CALL     3   1   2
0034 => MOV      3   2
0035    KSTR     4   9      ; "/"
0036    MOV      5   1
0037    CAT      1   3   5
0038 => GGET     3  10      ; "io"
0039    TGETS    3   3  11  ; "open"
0040    MOV      4   1
0041    KSTR     5  12      ; "wb"
0042    CALL     3   2   3
0043    GGET     4   3      ; "string"
0044    TGETS    4   4  13  ; "char"
0045    GGET     5  14      ; "table"
0046    TGETS    5   5  15  ; "unpack"
0047    MOV      7   0
0048    TGETS    6   0  16  ; "build_file"
0049    CALL     6   0   2
0050    CALLM    5   0   0
0051    CALLM    4   2   0
0052    MOV      6   3
0053    TGETS    5   3  17  ; "write"
0054    MOV      7   4
0055    CALL     5   1   3
0056    MOV      6   3
0057    TGETS    5   3  18  ; "close"
0058    CALL     5   1   2
0059    RET0     0   1

-- BYTECODE -- Writer.lua:0-67
0001    GGET     0   0      ; "require"
0002    KSTR     1   1      ; "LuaMidi.Util"
0003    CALL     0   2   2
0004    GGET     1   0      ; "require"
0005    KSTR     2   2      ; "LuaMidi.Constants"
0006    CALL     1   2   2
0007    GGET     2   0      ; "require"
0008    KSTR     3   3      ; "LuaMidi.Chunk"
0009    CALL     2   2   2
0010    GGET     3   0      ; "require"
0011    KSTR     4   4      ; "LuaMidi.MetaEvent"
0012    CALL     3   2   2
0013    TNEW     4   0
0014    FNEW     5   6      ; Writer.lua:8
0015    TSETS    5   4   5  ; "new"
0016    FNEW     5   8      ; Writer.lua:29
0017    TSETS    5   4   7  ; "build_file"
0018    FNEW     5  10      ; Writer.lua:39
0019    TSETS    5   4   9  ; "base64"
0020    FNEW     5  12      ; Writer.lua:43
0021    TSETS    5   4  11  ; "data_URI"
0022    FNEW     5  14      ; Writer.lua:47
0023    TSETS    5   4  13  ; "stdout"
0024    FNEW     5  16      ; Writer.lua:52
0025    TSETS    5   4  15  ; "save_MIDI"
0026    UCLO     0 => 0027
0027 => RET1     4   2

