
main <./tictactoe.lua:0,0> (104 instructions, 416 bytes at 0x7fed614068a0)
0+ params, 6 slots, 0 upvalues, 2 locals, 33 constants, 5 functions
	1	[10]	LOADK    	0 -2	; 0
	2	[10]	SETGLOBAL	0 -1	; games
	3	[11]	NEWTABLE 	0 0 0
	4	[11]	SETGLOBAL	0 -3	; board
	5	[12]	LOADBOOL 	0 0 0
	6	[12]	SETGLOBAL	0 -4	; gameOver
	7	[21]	CLOSURE  	0 0	; 0x7fed61406c70
	8	[14]	SETGLOBAL	0 -5	; initBoard
	9	[32]	CLOSURE  	0 1	; 0x7fed61407080
	10	[24]	SETGLOBAL	0 -6	; printBoard
	11	[53]	CLOSURE  	0 2	; 0x7fed614076a0
	12	[34]	SETGLOBAL	0 -7	; playUser
	13	[66]	CLOSURE  	0 3	; 0x7fed614065c0
	14	[55]	SETGLOBAL	0 -8	; playTurn
	15	[97]	CLOSURE  	0 4	; 0x7fed61406a60
	16	[68]	SETGLOBAL	0 -9	; checkGameOver
	17	[101]	GETGLOBAL	0 -10	; print
	18	[101]	LOADK    	1 -11	; "Play a game of tic tac toe? [yes or no]: "
	19	[101]	CALL     	0 2 1
	20	[102]	GETGLOBAL	0 -13	; io
	21	[102]	GETTABLE 	0 0 -14	; "read"
	22	[102]	CALL     	0 1 2
	23	[102]	SETGLOBAL	0 -12	; ans
	24	[103]	GETGLOBAL	0 -12	; ans
	25	[103]	EQ       	0 0 -15	; - "no"
	26	[103]	JMP      	5	; to 32
	27	[104]	GETGLOBAL	0 -10	; print
	28	[104]	LOADK    	1 -16	; "Thanks for playing!"
	29	[104]	CALL     	0 2 1
	30	[105]	RETURN   	0 1
	31	[105]	JMP      	-15	; to 17
	32	[106]	GETGLOBAL	0 -12	; ans
	33	[106]	EQ       	0 0 -17	; - "yes"
	34	[106]	JMP      	65	; to 100
	35	[107]	GETGLOBAL	0 -5	; initBoard
	36	[107]	CALL     	0 1 1
	37	[108]	GETGLOBAL	0 -18	; math
	38	[108]	GETTABLE 	0 0 -19	; "randomseed"
	39	[108]	GETGLOBAL	1 -20	; tonumber
	40	[108]	GETGLOBAL	2 -21	; tostring
	41	[108]	GETGLOBAL	3 -22	; os
	42	[108]	GETTABLE 	3 3 -23	; "time"
	43	[108]	CALL     	3 1 0
	44	[108]	CALL     	2 0 2
	45	[108]	SELF     	2 2 -24	; "reverse"
	46	[108]	CALL     	2 2 2
	47	[108]	SELF     	2 2 -25	; "sub"
	48	[108]	LOADK    	4 -26	; 1
	49	[108]	LOADK    	5 -27	; 6
	50	[108]	CALL     	2 4 0
	51	[108]	CALL     	1 0 0
	52	[108]	CALL     	0 0 1
	53	[109]	GETGLOBAL	0 -1	; games
	54	[109]	ADD      	0 0 -26	; - 1
	55	[109]	SETGLOBAL	0 -1	; games
	56	[110]	GETGLOBAL	0 -10	; print
	57	[110]	LOADK    	1 -28	; "Starting game...\n"
	58	[110]	CALL     	0 2 1
	59	[111]	GETGLOBAL	0 -6	; printBoard
	60	[111]	CALL     	0 1 1
	61	[112]	LOADK    	0 -2	; 0
	62	[114]	GETGLOBAL	1 -18	; math
	63	[114]	GETTABLE 	1 1 -29	; "random"
	64	[114]	LOADK    	2 -2	; 0
	65	[114]	LOADK    	3 -26	; 1
	66	[114]	CALL     	1 3 2
	67	[115]	EQ       	0 1 -26	; - 1
	68	[115]	JMP      	3	; to 72
	69	[116]	GETGLOBAL	2 -7	; playUser
	70	[116]	CALL     	2 1 1
	71	[117]	ADD      	0 0 -26	; - 1
	72	[120]	GETGLOBAL	2 -4	; gameOver
	73	[120]	TEST     	2 0 1
	74	[120]	JMP      	22	; to 97
	75	[120]	LT       	0 0 -30	; - 9
	76	[120]	JMP      	20	; to 97
	77	[121]	SUB      	2 0 1
	78	[121]	MOD      	2 2 -31
	79	[121]	EQ       	0 2 -2	; - 0
	80	[121]	JMP      	3	; to 84
	81	[121]	GETGLOBAL	2 -8	; playTurn
	82	[121]	CALL     	2 1 1
	83	[121]	JMP      	2	; to 86
	84	[121]	GETGLOBAL	2 -7	; playUser
	85	[121]	CALL     	2 1 1
	86	[122]	GETGLOBAL	2 -6	; printBoard
	87	[122]	CALL     	2 1 1
	88	[123]	GETGLOBAL	2 -9	; checkGameOver
	89	[123]	CALL     	2 1 1
	90	[124]	ADD      	0 0 -26	; - 1
	91	[125]	EQ       	0 0 -30	; - 9
	92	[125]	JMP      	-21	; to 72
	93	[125]	GETGLOBAL	2 -10	; print
	94	[125]	LOADK    	3 -32	; "Game over."
	95	[125]	CALL     	2 2 1
	96	[125]	JMP      	-25	; to 72
	97	[127]	LOADBOOL 	2 0 0
	98	[127]	SETGLOBAL	2 -4	; gameOver
	99	[127]	JMP      	-83	; to 17
	100	[129]	GETGLOBAL	0 -10	; print
	101	[129]	LOADK    	1 -33	; "Choice not valid. Say [yes or no]:"
	102	[129]	CALL     	0 2 1
	103	[130]	JMP      	-87	; to 17
	104	[131]	RETURN   	0 1

function <./tictactoe.lua:14,21> (21 instructions, 84 bytes at 0x7fed61406c70)
0 params, 12 slots, 0 upvalues, 8 locals, 4 constants, 0 functions
	1	[15]	LOADK    	0 -1	; 1
	2	[15]	LOADK    	1 -2	; 3
	3	[15]	LOADK    	2 -1	; 1
	4	[15]	FORPREP  	0 15	; to 20
	5	[16]	GETGLOBAL	4 -3	; board
	6	[16]	NEWTABLE 	5 0 0
	7	[16]	SETTABLE 	4 3 5
	8	[17]	LOADK    	4 -1	; 1
	9	[17]	LOADK    	5 -2	; 3
	10	[17]	LOADK    	6 -1	; 1
	11	[17]	FORPREP  	4 7	; to 19
	12	[18]	GETGLOBAL	8 -3	; board
	13	[18]	GETTABLE 	8 8 3
	14	[18]	MOVE     	9 3
	15	[18]	LOADK    	10 -4	; ","
	16	[18]	MOVE     	11 7
	17	[18]	CONCAT   	9 9 11
	18	[18]	SETTABLE 	8 7 9
	19	[17]	FORLOOP  	4 -8	; to 12
	20	[15]	FORLOOP  	0 -16	; to 5
	21	[21]	RETURN   	0 1

function <./tictactoe.lua:24,32> (27 instructions, 108 bytes at 0x7fed61407080)
0 params, 11 slots, 0 upvalues, 8 locals, 8 constants, 0 functions
	1	[25]	GETGLOBAL	0 -1	; io
	2	[25]	GETTABLE 	0 0 -2	; "write"
	3	[25]	LOADK    	1 -3	; "\n"
	4	[25]	CALL     	0 2 1
	5	[26]	LOADK    	0 -4	; 1
	6	[26]	LOADK    	1 -5	; 3
	7	[26]	LOADK    	2 -4	; 1
	8	[26]	FORPREP  	0 17	; to 26
	9	[27]	LOADK    	4 -4	; 1
	10	[27]	LOADK    	5 -5	; 3
	11	[27]	LOADK    	6 -4	; 1
	12	[27]	FORPREP  	4 8	; to 21
	13	[28]	GETGLOBAL	8 -1	; io
	14	[28]	GETTABLE 	8 8 -2	; "write"
	15	[28]	GETGLOBAL	9 -6	; board
	16	[28]	GETTABLE 	9 9 3
	17	[28]	GETTABLE 	9 9 7
	18	[28]	LOADK    	10 -7	; "\t"
	19	[28]	CONCAT   	9 9 10
	20	[28]	CALL     	8 2 1
	21	[27]	FORLOOP  	4 -9	; to 13
	22	[30]	GETGLOBAL	4 -1	; io
	23	[30]	GETTABLE 	4 4 -2	; "write"
	24	[30]	LOADK    	5 -8	; "\n\n"
	25	[30]	CALL     	4 2 1
	26	[26]	FORLOOP  	0 -18	; to 9
	27	[32]	RETURN   	0 1

function <./tictactoe.lua:34,53> (55 instructions, 220 bytes at 0x7fed614076a0)
0 params, 4 slots, 0 upvalues, 2 locals, 14 constants, 0 functions
	1	[35]	GETGLOBAL	0 -1	; print
	2	[35]	LOADK    	1 -2	; "Your turn...\n"
	3	[35]	CALL     	0 2 1
	4	[37]	GETGLOBAL	0 -1	; print
	5	[37]	LOADK    	1 -3	; "Select a row? [i]: "
	6	[37]	CALL     	0 2 1
	7	[38]	GETGLOBAL	0 -4	; tonumber
	8	[38]	GETGLOBAL	1 -5	; io
	9	[38]	GETTABLE 	1 1 -6	; "read"
	10	[38]	CALL     	1 1 0
	11	[38]	CALL     	0 0 2
	12	[39]	GETGLOBAL	1 -1	; print
	13	[39]	LOADK    	2 -7	; "Select a column? [j]: "
	14	[39]	CALL     	1 2 1
	15	[40]	GETGLOBAL	1 -4	; tonumber
	16	[40]	GETGLOBAL	2 -5	; io
	17	[40]	GETTABLE 	2 2 -6	; "read"
	18	[40]	CALL     	2 1 0
	19	[40]	CALL     	1 0 2
	20	[41]	TEST     	0 0 0
	21	[41]	JMP      	29	; to 51
	22	[41]	TEST     	1 0 0
	23	[41]	JMP      	27	; to 51
	24	[41]	LE       	0 -8 0	; 1 -
	25	[41]	JMP      	25	; to 51
	26	[41]	LE       	0 0 -9	; - 3
	27	[41]	JMP      	23	; to 51
	28	[41]	LE       	0 -8 1	; 1 -
	29	[41]	JMP      	21	; to 51
	30	[41]	LE       	0 1 -9	; - 3
	31	[41]	JMP      	19	; to 51
	32	[42]	GETGLOBAL	2 -11	; board
	33	[42]	GETTABLE 	2 2 0
	34	[42]	GETTABLE 	2 2 1
	35	[42]	SETGLOBAL	2 -10	; x
	36	[43]	GETGLOBAL	2 -10	; x
	37	[43]	EQ       	1 2 -12	; - " x "
	38	[43]	JMP      	8	; to 47
	39	[43]	GETGLOBAL	2 -10	; x
	40	[43]	EQ       	1 2 -13	; - " o "
	41	[43]	JMP      	5	; to 47
	42	[44]	GETGLOBAL	2 -11	; board
	43	[44]	GETTABLE 	2 2 0
	44	[44]	SETTABLE 	2 1 -12	; - " x "
	45	[45]	RETURN   	0 1
	46	[45]	JMP      	-43	; to 4
	47	[47]	GETGLOBAL	2 -1	; print
	48	[47]	LOADK    	3 -14	; "Choice is not valid."
	49	[47]	CALL     	2 2 1
	50	[48]	JMP      	-47	; to 4
	51	[50]	GETGLOBAL	2 -1	; print
	52	[50]	LOADK    	3 -14	; "Choice is not valid."
	53	[50]	CALL     	2 2 1
	54	[51]	JMP      	-51	; to 4
	55	[53]	RETURN   	0 1

function <./tictactoe.lua:55,66> (29 instructions, 116 bytes at 0x7fed614065c0)
0 params, 4 slots, 0 upvalues, 2 locals, 10 constants, 0 functions
	1	[56]	GETGLOBAL	0 -1	; print
	2	[56]	LOADK    	1 -2	; "My turn..."
	3	[56]	CALL     	0 2 1
	4	[58]	GETGLOBAL	0 -3	; math
	5	[58]	GETTABLE 	0 0 -4	; "random"
	6	[58]	LOADK    	1 -5	; 1
	7	[58]	LOADK    	2 -6	; 3
	8	[58]	CALL     	0 3 2
	9	[59]	GETGLOBAL	1 -3	; math
	10	[59]	GETTABLE 	1 1 -4	; "random"
	11	[59]	LOADK    	2 -5	; 1
	12	[59]	LOADK    	3 -6	; 3
	13	[59]	CALL     	1 3 2
	14	[60]	GETGLOBAL	2 -8	; board
	15	[60]	GETTABLE 	2 2 0
	16	[60]	GETTABLE 	2 2 1
	17	[60]	SETGLOBAL	2 -7	; x
	18	[61]	GETGLOBAL	2 -7	; x
	19	[61]	EQ       	1 2 -9	; - " o "
	20	[61]	JMP      	-17	; to 4
	21	[61]	GETGLOBAL	2 -7	; x
	22	[61]	EQ       	1 2 -10	; - " x "
	23	[61]	JMP      	-20	; to 4
	24	[62]	GETGLOBAL	2 -8	; board
	25	[62]	GETTABLE 	2 2 0
	26	[62]	SETTABLE 	2 1 -9	; - " o "
	27	[63]	RETURN   	0 1
	28	[64]	JMP      	-25	; to 4
	29	[66]	RETURN   	0 1

function <./tictactoe.lua:68,97> (84 instructions, 336 bytes at 0x7fed61406a60)
0 params, 9 slots, 0 upvalues, 8 locals, 10 constants, 0 functions
	1	[71]	LOADK    	4 -1	; 1
	2	[71]	LOADK    	5 -2	; 3
	3	[71]	LOADK    	6 -1	; 1
	4	[71]	FORPREP  	4 32	; to 37
	5	[73]	GETGLOBAL	8 -3	; board
	6	[73]	GETTABLE 	8 8 7
	7	[73]	GETTABLE 	1 8 -1	; 1
	8	[74]	GETGLOBAL	8 -3	; board
	9	[74]	GETTABLE 	8 8 7
	10	[74]	GETTABLE 	2 8 -4	; 2
	11	[75]	GETGLOBAL	8 -3	; board
	12	[75]	GETTABLE 	8 8 7
	13	[75]	GETTABLE 	3 8 -2	; 3
	14	[76]	EQ       	0 1 2
	15	[76]	JMP      	5	; to 21
	16	[76]	EQ       	0 2 3
	17	[76]	JMP      	3	; to 21
	18	[76]	EQ       	0 1 3
	19	[76]	JMP      	1	; to 21
	20	[76]	MOVE     	0 1
	21	[78]	GETGLOBAL	8 -3	; board
	22	[78]	GETTABLE 	8 8 -1	; 1
	23	[78]	GETTABLE 	1 8 7
	24	[79]	GETGLOBAL	8 -3	; board
	25	[79]	GETTABLE 	8 8 -4	; 2
	26	[79]	GETTABLE 	2 8 7
	27	[80]	GETGLOBAL	8 -3	; board
	28	[80]	GETTABLE 	8 8 -2	; 3
	29	[80]	GETTABLE 	3 8 7
	30	[81]	EQ       	0 1 2
	31	[81]	JMP      	5	; to 37
	32	[81]	EQ       	0 2 3
	33	[81]	JMP      	3	; to 37
	34	[81]	EQ       	0 1 3
	35	[81]	JMP      	1	; to 37
	36	[81]	MOVE     	0 1
	37	[71]	FORLOOP  	4 -33	; to 5
	38	[84]	GETGLOBAL	4 -3	; board
	39	[84]	GETTABLE 	4 4 -1	; 1
	40	[84]	GETTABLE 	1 4 -1	; 1
	41	[85]	GETGLOBAL	4 -3	; board
	42	[85]	GETTABLE 	4 4 -4	; 2
	43	[85]	GETTABLE 	2 4 -4	; 2
	44	[86]	GETGLOBAL	4 -3	; board
	45	[86]	GETTABLE 	4 4 -2	; 3
	46	[86]	GETTABLE 	3 4 -2	; 3
	47	[87]	EQ       	0 1 2
	48	[87]	JMP      	5	; to 54
	49	[87]	EQ       	0 2 3
	50	[87]	JMP      	3	; to 54
	51	[87]	EQ       	0 1 3
	52	[87]	JMP      	1	; to 54
	53	[87]	MOVE     	0 1
	54	[88]	GETGLOBAL	4 -3	; board
	55	[88]	GETTABLE 	4 4 -1	; 1
	56	[88]	GETTABLE 	1 4 -2	; 3
	57	[89]	GETGLOBAL	4 -3	; board
	58	[89]	GETTABLE 	4 4 -4	; 2
	59	[89]	GETTABLE 	2 4 -4	; 2
	60	[90]	GETGLOBAL	4 -3	; board
	61	[90]	GETTABLE 	4 4 -2	; 3
	62	[90]	GETTABLE 	3 4 -1	; 1
	63	[91]	EQ       	0 1 2
	64	[91]	JMP      	5	; to 70
	65	[91]	EQ       	0 2 3
	66	[91]	JMP      	3	; to 70
	67	[91]	EQ       	0 1 3
	68	[91]	JMP      	1	; to 70
	69	[91]	MOVE     	0 1
	70	[92]	TEST     	0 0 0
	71	[92]	JMP      	12	; to 84
	72	[93]	LOADBOOL 	4 1 0
	73	[93]	SETGLOBAL	4 -5	; gameOver
	74	[94]	EQ       	0 0 -6	; - " x "
	75	[94]	JMP      	3	; to 79
	76	[94]	GETGLOBAL	4 -7	; print
	77	[94]	LOADK    	5 -8	; "You've won! Well played."
	78	[94]	CALL     	4 2 1
	79	[95]	EQ       	0 0 -9	; - " o "
	80	[95]	JMP      	3	; to 84
	81	[95]	GETGLOBAL	4 -7	; print
	82	[95]	LOADK    	5 -10	; "I've won! Better luck next time."
	83	[95]	CALL     	4 2 1
	84	[97]	RETURN   	0 1
