-- BYTECODE -- tictactoe.lua:14-21
0001    KSHORT   0   1
0002    KSHORT   1   3
0003    KSHORT   2   1
0004    FORI     0 => 0021
0005 => GGET     4   0      ; "board"
0006    TNEW     5   0
0007    TSETV    5   4   3
0008    KSHORT   4   1
0009    KSHORT   5   3
0010    KSHORT   6   1
0011    FORI     4 => 0020
0012 => GGET     8   0      ; "board"
0013    TGETV    8   8   3
0014    MOV      9   3
0015    KSTR    10   1      ; ","
0016    MOV     11   7
0017    CAT      9   9  11
0018    TSETV    9   8   7
0019    FORL     4 => 0012
0020 => FORL     0 => 0005
0021 => RET0     0   1

-- BYTECODE -- tictactoe.lua:24-32
0001    GGET     0   0      ; "io"
0002    TGETS    0   0   1  ; "write"
0003    KSTR     1   2      ; "\n"
0004    CALL     0   1   2
0005    KSHORT   0   1
0006    KSHORT   1   3
0007    KSHORT   2   1
0008    FORI     0 => 0027
0009 => KSHORT   4   1
0010    KSHORT   5   3
0011    KSHORT   6   1
0012    FORI     4 => 0022
0013 => GGET     8   0      ; "io"
0014    TGETS    8   8   1  ; "write"
0015    GGET     9   3      ; "board"
0016    TGETV    9   9   3
0017    TGETV    9   9   7
0018    KSTR    10   4      ; "\t"
0019    CAT      9   9  10
0020    CALL     8   1   2
0021    FORL     4 => 0013
0022 => GGET     4   0      ; "io"
0023    TGETS    4   4   1  ; "write"
0024    KSTR     5   5      ; "\n\n"
0025    CALL     4   1   2
0026    FORL     0 => 0009
0027 => RET0     0   1

-- BYTECODE -- tictactoe.lua:34-53
0001    GGET     0   0      ; "print"
0002    KSTR     1   1      ; "Your turn...\n"
0003    CALL     0   1   2
0004 => LOOP     0 => 0061
0005    GGET     0   0      ; "print"
0006    KSTR     1   2      ; "Select a row? [i]: "
0007    CALL     0   1   2
0008    GGET     0   3      ; "tonumber"
0009    GGET     1   4      ; "io"
0010    TGETS    1   1   5  ; "read"
0011    CALL     1   0   1
0012    CALLM    0   2   0
0013    GGET     1   0      ; "print"
0014    KSTR     2   6      ; "Select a column? [j]: "
0015    CALL     1   1   2
0016    GGET     1   3      ; "tonumber"
0017    GGET     2   4      ; "io"
0018    TGETS    2   2   5  ; "read"
0019    CALL     2   0   1
0020    CALLM    1   2   0
0021    ISF          0
0022    JMP      2 => 0057
0023    ISF          1
0024    JMP      2 => 0057
0025    KSHORT   2   1
0026    ISGT     2   0
0027    JMP      2 => 0057
0028    KSHORT   2   3
0029    ISGT     0   2
0030    JMP      2 => 0057
0031    KSHORT   2   1
0032    ISGT     2   1
0033    JMP      2 => 0057
0034    KSHORT   2   3
0035    ISGT     1   2
0036    JMP      2 => 0057
0037    GGET     2   7      ; "board"
0038    TGETV    2   2   0
0039    TGETV    2   2   1
0040    GSET     2   8      ; "x"
0041    GGET     2   8      ; "x"
0042    ISEQS    2   9      ; " x "
0043    JMP      2 => 0053
0044    GGET     2   8      ; "x"
0045    ISEQS    2  10      ; " o "
0046    JMP      2 => 0053
0047    GGET     2   7      ; "board"
0048    TGETV    2   2   0
0049    KSTR     3   9      ; " x "
0050    TSETV    3   2   1
0051    RET0     0   1
0052    JMP      2 => 0004
0053 => GGET     2   0      ; "print"
0054    KSTR     3  11      ; "Choice is not valid."
0055    CALL     2   1   2
0056    JMP      2 => 0004
0057 => GGET     2   0      ; "print"
0058    KSTR     3  11      ; "Choice is not valid."
0059    CALL     2   1   2
0060    JMP      0 => 0004
0061 => RET0     0   1

-- BYTECODE -- tictactoe.lua:55-66
0001    GGET     0   0      ; "print"
0002    KSTR     1   1      ; "My turn..."
0003    CALL     0   1   2
0004 => LOOP     0 => 0031
0005    GGET     0   2      ; "math"
0006    TGETS    0   0   3  ; "random"
0007    KSHORT   1   1
0008    KSHORT   2   3
0009    CALL     0   2   3
0010    GGET     1   2      ; "math"
0011    TGETS    1   1   3  ; "random"
0012    KSHORT   2   1
0013    KSHORT   3   3
0014    CALL     1   2   3
0015    GGET     2   4      ; "board"
0016    TGETV    2   2   0
0017    TGETV    2   2   1
0018    GSET     2   5      ; "x"
0019    GGET     2   5      ; "x"
0020    ISEQS    2   6      ; " o "
0021    JMP      2 => 0004
0022    GGET     2   5      ; "x"
0023    ISEQS    2   7      ; " x "
0024    JMP      2 => 0004
0025    GGET     2   4      ; "board"
0026    TGETV    2   2   0
0027    KSTR     3   6      ; " o "
0028    TSETV    3   2   1
0029    RET0     0   1
0030    JMP      0 => 0004
0031 => RET0     0   1

-- BYTECODE -- tictactoe.lua:68-97
0001    KNIL     0   3
0002    KSHORT   4   1
0003    KSHORT   5   3
0004    KSHORT   6   1
0005    FORI     4 => 0039
0006 => GGET     8   0      ; "board"
0007    TGETV    8   8   7
0008    TGETB    1   8   1
0009    GGET     8   0      ; "board"
0010    TGETV    8   8   7
0011    TGETB    2   8   2
0012    GGET     8   0      ; "board"
0013    TGETV    8   8   7
0014    TGETB    3   8   3
0015    ISNEV    1   2
0016    JMP      8 => 0022
0017    ISNEV    2   3
0018    JMP      8 => 0022
0019    ISNEV    1   3
0020    JMP      8 => 0022
0021    MOV      0   1
0022 => GGET     8   0      ; "board"
0023    TGETB    8   8   1
0024    TGETV    1   8   7
0025    GGET     8   0      ; "board"
0026    TGETB    8   8   2
0027    TGETV    2   8   7
0028    GGET     8   0      ; "board"
0029    TGETB    8   8   3
0030    TGETV    3   8   7
0031    ISNEV    1   2
0032    JMP      8 => 0038
0033    ISNEV    2   3
0034    JMP      8 => 0038
0035    ISNEV    1   3
0036    JMP      8 => 0038
0037    MOV      0   1
0038 => FORL     4 => 0006
0039 => GGET     4   0      ; "board"
0040    TGETB    4   4   1
0041    TGETB    1   4   1
0042    GGET     4   0      ; "board"
0043    TGETB    4   4   2
0044    TGETB    2   4   2
0045    GGET     4   0      ; "board"
0046    TGETB    4   4   3
0047    TGETB    3   4   3
0048    ISNEV    1   2
0049    JMP      4 => 0055
0050    ISNEV    2   3
0051    JMP      4 => 0055
0052    ISNEV    1   3
0053    JMP      4 => 0055
0054    MOV      0   1
0055 => GGET     4   0      ; "board"
0056    TGETB    4   4   1
0057    TGETB    1   4   3
0058    GGET     4   0      ; "board"
0059    TGETB    4   4   2
0060    TGETB    2   4   2
0061    GGET     4   0      ; "board"
0062    TGETB    4   4   3
0063    TGETB    3   4   1
0064    ISNEV    1   2
0065    JMP      4 => 0071
0066    ISNEV    2   3
0067    JMP      4 => 0071
0068    ISNEV    1   3
0069    JMP      4 => 0071
0070    MOV      0   1
0071 => ISF          0
0072    JMP      4 => 0085
0073    KPRI     4   2
0074    GSET     4   1      ; "gameOver"
0075    ISNES    0   2      ; " x "
0076    JMP      4 => 0080
0077    GGET     4   3      ; "print"
0078    KSTR     5   4      ; "You've won! Well played."
0079    CALL     4   1   2
0080 => ISNES    0   5      ; " o "
0081    JMP      4 => 0085
0082    GGET     4   3      ; "print"
0083    KSTR     5   6      ; "I've won! Better luck next time."
0084    CALL     4   1   2
0085 => RET0     0   1

-- BYTECODE -- tictactoe.lua:0-132
0001    KSHORT   0   0
0002    GSET     0   0      ; "games"
0003    TNEW     0   0
0004    GSET     0   1      ; "board"
0005    KPRI     0   1
0006    GSET     0   2      ; "gameOver"
0007    FNEW     0   3      ; tictactoe.lua:14
0008    GSET     0   4      ; "initBoard"
0009    FNEW     0   5      ; tictactoe.lua:24
0010    GSET     0   6      ; "printBoard"
0011    FNEW     0   7      ; tictactoe.lua:34
0012    GSET     0   8      ; "playUser"
0013    FNEW     0   9      ; tictactoe.lua:55
0014    GSET     0  10      ; "playTurn"
0015    FNEW     0  11      ; tictactoe.lua:68
0016    GSET     0  12      ; "checkGameOver"
0017 => LOOP     0 => 0110
0018    GGET     0  13      ; "print"
0019    KSTR     1  14      ; "Play a game of tic tac toe? [yes or no]:"~
0020    CALL     0   1   2
0021    GGET     0  15      ; "io"
0022    TGETS    0   0  16  ; "read"
0023    CALL     0   2   1
0024    GSET     0  17      ; "ans"
0025    GGET     0  17      ; "ans"
0026    ISNES    0  18      ; "no"
0027    JMP      0 => 0034
0028    GGET     0  13      ; "print"
0029    KSTR     1  19      ; "Thanks for playing!"
0030    CALL     0   1   2
0031    UCLO     0 => 0032
0032 => RET0     0   1
0033    JMP      0 => 0017
0034 => GGET     0  17      ; "ans"
0035    ISNES    0  20      ; "yes"
0036    JMP      0 => 0106
0037    GGET     0   4      ; "initBoard"
0038    CALL     0   1   1
0039    GGET     0  21      ; "math"
0040    TGETS    0   0  22  ; "randomseed"
0041    GGET     1  23      ; "tonumber"
0042    GGET     2  24      ; "tostring"
0043    GGET     3  25      ; "os"
0044    TGETS    3   3  26  ; "time"
0045    CALL     3   0   1
0046    CALLM    2   2   0
0047    MOV      3   2
0048    TGETS    2   2  27  ; "reverse"
0049    CALL     2   2   2
0050    MOV      3   2
0051    TGETS    2   2  28  ; "sub"
0052    KSHORT   4   1
0053    KSHORT   5   6
0054    CALL     2   0   4
0055    CALLM    1   0   0
0056    CALLM    0   1   0
0057    GGET     0   0      ; "games"
0058    ADDVN    0   0   0  ; 1
0059    GSET     0   0      ; "games"
0060    GGET     0  13      ; "print"
0061    KSTR     1  29      ; "Starting game...\n"
0062    CALL     0   1   2
0063    GGET     0   6      ; "printBoard"
0064    CALL     0   1   1
0065    KSHORT   0   0
0066    GGET     1  21      ; "math"
0067    TGETS    1   1  30  ; "random"
0068    KSHORT   2   0
0069    KSHORT   3   1
0070    CALL     1   2   3
0071    ISNEN    1   0      ; 1
0072    JMP      2 => 0076
0073    GGET     2   8      ; "playUser"
0074    CALL     2   1   1
0075    ADDVN    0   0   0  ; 1
0076 => GGET     2   2      ; "gameOver"
0077    IST          2
0078    JMP      2 => 0103
0079    KSHORT   2   9
0080    ISGE     0   2
0081    JMP      2 => 0103
0082    LOOP     2 => 0103
0083    SUBVV    2   0   1
0084    MODVN    2   2   1  ; 2
0085    ISNEN    2   2      ; 0
0086    JMP      2 => 0090
0087    GGET     2  10      ; "playTurn"
0088    CALL     2   1   1
0089    JMP      2 => 0092
0090 => GGET     2   8      ; "playUser"
0091    CALL     2   1   1
0092 => GGET     2   6      ; "printBoard"
0093    CALL     2   1   1
0094    GGET     2  12      ; "checkGameOver"
0095    CALL     2   1   1
0096    ADDVN    0   0   0  ; 1
0097    ISNEN    0   3      ; 9
0098    JMP      2 => 0076
0099    GGET     2  13      ; "print"
0100    KSTR     3  31      ; "Game over."
0101    CALL     2   1   2
0102    JMP      2 => 0076
0103 => KPRI     2   1
0104    GSET     2   2      ; "gameOver"
0105    JMP      0 => 0017
0106 => GGET     0  13      ; "print"
0107    KSTR     1  32      ; "Choice not valid. Say [yes or no]:"
0108    CALL     0   1   2
0109    JMP      0 => 0017
0110 => RET0     0   1

