
main <./upload/api.lua:0,0> (75 instructions, 300 bytes at 0x7fb47bc068a0)
0+ params, 15 slots, 0 upvalues, 14 locals, 16 constants, 11 functions
	1	[2]	NEWTABLE 	0 0 0
	2	[4]	GETGLOBAL	1 -1	; require
	3	[4]	LOADK    	2 -2	; "luarocks.core.cfg"
	4	[4]	CALL     	1 2 2
	5	[5]	GETGLOBAL	2 -1	; require
	6	[5]	LOADK    	3 -3	; "luarocks.fs"
	7	[5]	CALL     	2 2 2
	8	[6]	GETGLOBAL	3 -1	; require
	9	[6]	LOADK    	4 -4	; "luarocks.dir"
	10	[6]	CALL     	3 2 2
	11	[7]	GETGLOBAL	4 -1	; require
	12	[7]	LOADK    	5 -5	; "luarocks.util"
	13	[7]	CALL     	4 2 2
	14	[8]	GETGLOBAL	5 -1	; require
	15	[8]	LOADK    	6 -6	; "luarocks.persist"
	16	[8]	CALL     	5 2 2
	17	[9]	GETGLOBAL	6 -1	; require
	18	[9]	LOADK    	7 -7	; "luarocks.upload.multipart"
	19	[9]	CALL     	6 2 2
	20	[11]	NEWTABLE 	7 0 0
	21	[18]	CLOSURE  	8 0	; 0x7fb47bc06c10
	22	[18]	MOVE     	0 1
	23	[25]	CLOSURE  	9 1	; 0x7fb47bc06640
	24	[25]	MOVE     	0 8
	25	[25]	MOVE     	0 5
	26	[20]	SETTABLE 	7 -8 9	; "load_config" -
	27	[45]	CLOSURE  	9 2	; 0x7fb47bc06f50
	28	[45]	MOVE     	0 4
	29	[45]	MOVE     	0 8
	30	[45]	MOVE     	0 2
	31	[45]	MOVE     	0 3
	32	[45]	MOVE     	0 5
	33	[27]	SETTABLE 	7 -9 9	; "save_config" -
	34	[68]	CLOSURE  	9 3	; 0x7fb47bc07050
	35	[68]	MOVE     	0 1
	36	[68]	MOVE     	0 4
	37	[47]	SETTABLE 	7 -10 9	; "check_version" -
	38	[83]	CLOSURE  	9 4	; 0x7fb47bc084e0
	39	[70]	SETTABLE 	7 -11 9	; "method" -
	40	[89]	CLOSURE  	9 5	; 0x7fb47bc08a50
	41	[89]	MOVE     	0 1
	42	[85]	SETTABLE 	7 -12 9	; "raw_method" -
	43	[109]	CLOSURE  	9 6	; 0x7fb47bc072d0
	44	[109]	MOVE     	0 6
	45	[114]	CLOSURE  	10 7	; 0x7fb47bc076a0
	46	[116]	GETGLOBAL	11 -13	; pcall
	47	[116]	GETGLOBAL	12 -1	; require
	48	[116]	LOADK    	13 -14	; "ltn12"
	49	[116]	CALL     	11 3 3
	50	[117]	TEST     	11 0 1
	51	[117]	JMP      	8	; to 60
	52	[178]	CLOSURE  	13 8	; 0x7fb47bc094a0
	53	[178]	MOVE     	0 1
	54	[178]	MOVE     	0 4
	55	[178]	MOVE     	0 2
	56	[178]	MOVE     	0 9
	57	[178]	MOVE     	0 10
	58	[119]	SETTABLE 	7 -15 13	; "request" -
	59	[178]	JMP      	10	; to 70
	60	[182]	LOADBOOL 	13 0 0
	61	[244]	CLOSURE  	14 9	; 0x7fb47bc0a1e0
	62	[244]	MOVE     	0 4
	63	[244]	MOVE     	0 13
	64	[244]	MOVE     	0 9
	65	[244]	MOVE     	0 6
	66	[244]	MOVE     	0 10
	67	[244]	MOVE     	0 12
	68	[184]	SETTABLE 	7 -15 14	; "request" -
	69	[244]	CLOSE    	13
	70	[265]	CLOSURE  	13 10	; 0x7fb47bc09740
	71	[265]	MOVE     	0 7
	72	[265]	MOVE     	0 1
	73	[248]	SETTABLE 	0 -16 13	; "new" -
	74	[267]	RETURN   	0 2
	75	[267]	RETURN   	0 1

function <./upload/api.lua:13,18> (18 instructions, 72 bytes at 0x7fb47bc06c10)
0 params, 4 slots, 1 upvalue, 0 locals, 6 constants, 0 functions
	1	[14]	GETUPVAL 	0 0	; cfg
	2	[14]	GETTABLE 	0 0 -1	; "config_files"
	3	[14]	GETTABLE 	0 0 -2	; "user"
	4	[14]	GETTABLE 	0 0 -3	; "file"
	5	[14]	TEST     	0 0 1
	6	[14]	JMP      	2	; to 9
	7	[15]	LOADNIL  	0 0
	8	[15]	RETURN   	0 2
	9	[17]	GETUPVAL 	0 0	; cfg
	10	[17]	GETTABLE 	0 0 -1	; "config_files"
	11	[17]	GETTABLE 	0 0 -2	; "user"
	12	[17]	GETTABLE 	0 0 -3	; "file"
	13	[17]	SELF     	0 0 -4	; "gsub"
	14	[17]	LOADK    	2 -5	; "/[^/]+$"
	15	[17]	LOADK    	3 -6	; "/upload_config.lua"
	16	[17]	CALL     	0 4 2
	17	[17]	RETURN   	0 2
	18	[18]	RETURN   	0 1

function <./upload/api.lua:20,25> (12 instructions, 48 bytes at 0x7fb47bc06640)
1 param, 4 slots, 2 upvalues, 4 locals, 1 constant, 0 functions
	1	[21]	GETUPVAL 	1 0	; upload_config_file
	2	[21]	CALL     	1 1 2
	3	[22]	TEST     	1 0 1
	4	[22]	JMP      	2	; to 7
	5	[22]	LOADNIL  	2 2
	6	[22]	RETURN   	2 2
	7	[23]	GETUPVAL 	2 1	; persist
	8	[23]	GETTABLE 	2 2 -1	; "load_into_table"
	9	[23]	MOVE     	3 1
	10	[23]	CALL     	2 2 3
	11	[24]	RETURN   	2 2
	12	[25]	RETURN   	0 1

function <./upload/api.lua:27,45> (51 instructions, 204 bytes at 0x7fb47bc06f50)
1 param, 10 slots, 5 upvalues, 6 locals, 14 constants, 0 functions
	1	[29]	SELF     	1 0 -1	; "raw_method"
	2	[29]	LOADK    	3 -2	; "status"
	3	[29]	CALL     	1 3 3
	4	[30]	TEST     	1 0 1
	5	[30]	JMP      	3	; to 9
	6	[31]	LOADNIL  	3 3
	7	[31]	MOVE     	4 2
	8	[31]	RETURN   	3 3
	9	[33]	GETTABLE 	3 1 -3	; "errors"
	10	[33]	TEST     	3 0 0
	11	[33]	JMP      	10	; to 22
	12	[34]	GETUPVAL 	3 0	; util
	13	[34]	GETTABLE 	3 3 -4	; "printerr"
	14	[34]	LOADK    	4 -5	; "Server says: "
	15	[34]	GETGLOBAL	5 -6	; tostring
	16	[34]	GETTABLE 	6 1 -3	; "errors"
	17	[34]	GETTABLE 	6 6 -7	; 1
	18	[34]	CALL     	5 2 2
	19	[34]	CONCAT   	4 4 5
	20	[34]	CALL     	3 2 1
	21	[35]	RETURN   	0 1
	22	[37]	GETUPVAL 	3 1	; upload_config_file
	23	[37]	CALL     	3 1 2
	24	[38]	TEST     	3 0 1
	25	[38]	JMP      	2	; to 28
	26	[38]	LOADNIL  	4 4
	27	[38]	RETURN   	4 2
	28	[39]	GETUPVAL 	4 2	; fs
	29	[39]	GETTABLE 	4 4 -8	; "make_dir"
	30	[39]	GETUPVAL 	5 3	; dir
	31	[39]	GETTABLE 	5 5 -9	; "dir_name"
	32	[39]	MOVE     	6 3
	33	[39]	CALL     	5 2 0
	34	[39]	CALL     	4 0 3
	35	[40]	TEST     	4 0 1
	36	[40]	JMP      	3	; to 40
	37	[41]	LOADNIL  	6 6
	38	[41]	MOVE     	7 5
	39	[41]	RETURN   	6 3
	40	[43]	GETUPVAL 	6 4	; persist
	41	[43]	GETTABLE 	6 6 -10	; "save_from_table"
	42	[43]	MOVE     	7 3
	43	[43]	GETTABLE 	8 0 -11	; "config"
	44	[43]	CALL     	6 3 1
	45	[44]	GETUPVAL 	6 2	; fs
	46	[44]	GETTABLE 	6 6 -12	; "set_permissions"
	47	[44]	MOVE     	7 3
	48	[44]	LOADK    	8 -13	; "read"
	49	[44]	LOADK    	9 -14	; "user"
	50	[44]	CALL     	6 4 1
	51	[45]	RETURN   	0 1

function <./upload/api.lua:47,68> (45 instructions, 180 bytes at 0x7fb47bc07050)
1 param, 6 slots, 2 upvalues, 4 locals, 15 constants, 0 functions
	1	[48]	GETTABLE 	1 0 -1	; "_server_tool_version"
	2	[48]	TEST     	1 0 1
	3	[48]	JMP      	39	; to 43
	4	[49]	GETUPVAL 	1 0	; cfg
	5	[49]	GETTABLE 	1 1 -2	; "upload"
	6	[49]	GETTABLE 	1 1 -3	; "tool_version"
	7	[50]	SELF     	2 0 -4	; "request"
	8	[50]	GETGLOBAL	4 -5	; tostring
	9	[50]	GETTABLE 	5 0 -6	; "config"
	10	[50]	GETTABLE 	5 5 -7	; "server"
	11	[50]	CALL     	4 2 2
	12	[50]	LOADK    	5 -8	; "/api/tool_version"
	13	[50]	CONCAT   	4 4 5
	14	[50]	NEWTABLE 	5 0 1
	15	[51]	SETTABLE 	5 -9 1	; "current" -
	16	[50]	CALL     	2 4 3
	17	[53]	TEST     	2 0 1
	18	[53]	JMP      	3	; to 22
	19	[54]	LOADNIL  	4 4
	20	[54]	MOVE     	5 3
	21	[54]	RETURN   	4 3
	22	[56]	GETTABLE 	4 2 -10	; "version"
	23	[56]	TEST     	4 0 1
	24	[56]	JMP      	3	; to 28
	25	[57]	LOADNIL  	4 4
	26	[57]	LOADK    	5 -11	; "failed to fetch tool version"
	27	[57]	RETURN   	4 3
	28	[59]	GETTABLE 	4 2 -10	; "version"
	29	[59]	SETTABLE 	0 -1 4	; "_server_tool_version" -
	30	[60]	GETTABLE 	4 2 -12	; "force_update"
	31	[60]	TEST     	4 0 0
	32	[60]	JMP      	3	; to 36
	33	[61]	LOADNIL  	4 4
	34	[61]	LOADK    	5 -13	; "Your upload client is too out of date to continue, please upgrade LuaRocks."
	35	[61]	RETURN   	4 3
	36	[63]	GETTABLE 	4 2 -10	; "version"
	37	[63]	EQ       	1 4 1
	38	[63]	JMP      	4	; to 43
	39	[64]	GETUPVAL 	4 1	; util
	40	[64]	GETTABLE 	4 4 -14	; "warning"
	41	[64]	LOADK    	5 -15	; "your LuaRocks is out of date, consider upgrading."
	42	[64]	CALL     	4 2 1
	43	[67]	LOADBOOL 	1 1 0
	44	[67]	RETURN   	1 2
	45	[68]	RETURN   	0 1

function <./upload/api.lua:70,83> (33 instructions, 132 bytes at 0x7fb47bc084e0)
1+ param, 8 slots, 0 upvalues, 5 locals, 9 constants, 0 functions
	1	[71]	SELF     	2 0 -1	; "raw_method"
	2	[71]	VARARG   	4 0
	3	[71]	CALL     	2 0 3
	4	[72]	TEST     	2 0 1
	5	[72]	JMP      	3	; to 9
	6	[73]	LOADNIL  	4 4
	7	[73]	MOVE     	5 3
	8	[73]	RETURN   	4 3
	9	[75]	GETTABLE 	4 2 -2	; "errors"
	10	[75]	TEST     	4 0 0
	11	[75]	JMP      	20	; to 32
	12	[76]	GETTABLE 	4 2 -2	; "errors"
	13	[76]	GETTABLE 	4 4 -3	; 1
	14	[76]	EQ       	0 4 -4	; - "Invalid key"
	15	[76]	JMP      	6	; to 22
	16	[77]	LOADNIL  	4 4
	17	[77]	GETTABLE 	5 2 -2	; "errors"
	18	[77]	GETTABLE 	5 5 -3	; 1
	19	[77]	LOADK    	6 -5	; " (use the --api-key flag to change)"
	20	[77]	CONCAT   	5 5 6
	21	[77]	RETURN   	4 3
	22	[79]	GETGLOBAL	4 -6	; table
	23	[79]	GETTABLE 	4 4 -7	; "concat"
	24	[79]	GETTABLE 	5 2 -2	; "errors"
	25	[79]	LOADK    	6 -8	; ", "
	26	[79]	CALL     	4 3 2
	27	[80]	LOADNIL  	5 5
	28	[80]	LOADK    	6 -9	; "API Failed: "
	29	[80]	MOVE     	7 4
	30	[80]	CONCAT   	6 6 7
	31	[80]	RETURN   	5 3
	32	[82]	RETURN   	2 2
	33	[83]	RETURN   	0 1

function <./upload/api.lua:85,89> (28 instructions, 112 bytes at 0x7fb47bc08a50)
2+ params, 11 slots, 1 upvalue, 4 locals, 10 constants, 0 functions
	1	[86]	SELF     	3 0 -1	; "check_version"
	2	[86]	CALL     	3 2 1
	3	[87]	GETGLOBAL	3 -2	; tostring
	4	[87]	GETTABLE 	4 0 -3	; "config"
	5	[87]	GETTABLE 	4 4 -4	; "server"
	6	[87]	CALL     	3 2 2
	7	[87]	LOADK    	4 -5	; "/api/"
	8	[87]	GETGLOBAL	5 -2	; tostring
	9	[87]	GETUPVAL 	6 0	; cfg
	10	[87]	GETTABLE 	6 6 -6	; "upload"
	11	[87]	GETTABLE 	6 6 -7	; "api_version"
	12	[87]	CALL     	5 2 2
	13	[87]	LOADK    	6 -8	; "/"
	14	[87]	GETGLOBAL	7 -2	; tostring
	15	[87]	GETTABLE 	8 0 -3	; "config"
	16	[87]	GETTABLE 	8 8 -9	; "key"
	17	[87]	CALL     	7 2 2
	18	[87]	LOADK    	8 -8	; "/"
	19	[87]	GETGLOBAL	9 -2	; tostring
	20	[87]	MOVE     	10 1
	21	[87]	CALL     	9 2 2
	22	[87]	CONCAT   	3 3 9
	23	[88]	SELF     	4 0 -10	; "request"
	24	[88]	MOVE     	6 3
	25	[88]	VARARG   	7 0
	26	[88]	TAILCALL 	4 0 0
	27	[88]	RETURN   	4 0
	28	[89]	RETURN   	0 1

function <./upload/api.lua:91,109> (48 instructions, 192 bytes at 0x7fb47bc072d0)
2 params, 12 slots, 1 upvalue, 9 locals, 14 constants, 0 functions
	1	[92]	EQ       	0 1 -1	; - nil
	2	[92]	JMP      	1	; to 4
	3	[93]	LOADK    	1 -2	; "&"
	4	[95]	LOADK    	2 -3	; 0
	5	[96]	NEWTABLE 	3 0 0
	6	[97]	GETGLOBAL	4 -4	; pairs
	7	[97]	MOVE     	5 0
	8	[97]	CALL     	4 2 4
	9	[97]	JMP      	30	; to 40
	10	[98]	GETGLOBAL	9 -5	; type
	11	[98]	MOVE     	10 7
	12	[98]	CALL     	9 2 2
	13	[98]	EQ       	0 9 -6	; - "number"
	14	[98]	JMP      	8	; to 23
	15	[98]	GETGLOBAL	9 -5	; type
	16	[98]	MOVE     	10 8
	17	[98]	CALL     	9 2 2
	18	[98]	EQ       	0 9 -7	; - "table"
	19	[98]	JMP      	3	; to 23
	20	[99]	GETTABLE 	9 8 -8	; 1
	21	[99]	GETTABLE 	8 8 -9	; 2
	22	[99]	MOVE     	7 9
	23	[101]	ADD      	9 2 -8	; - 1
	24	[101]	GETUPVAL 	10 0	; multipart
	25	[101]	GETTABLE 	10 10 -10	; "url_escape"
	26	[101]	MOVE     	11 7
	27	[101]	CALL     	10 2 2
	28	[101]	SETTABLE 	3 9 10
	29	[102]	ADD      	9 2 -9	; - 2
	30	[102]	SETTABLE 	3 9 -11	; - "="
	31	[103]	ADD      	9 2 -12	; - 3
	32	[103]	GETUPVAL 	10 0	; multipart
	33	[103]	GETTABLE 	10 10 -10	; "url_escape"
	34	[103]	MOVE     	11 8
	35	[103]	CALL     	10 2 2
	36	[103]	SETTABLE 	3 9 10
	37	[104]	ADD      	9 2 -13	; - 4
	38	[104]	SETTABLE 	3 9 1
	39	[105]	ADD      	2 2 -13	; - 4
	40	[97]	TFORLOOP 	4 2
	41	[105]	JMP      	-32	; to 10
	42	[107]	SETTABLE 	3 2 -1	; - nil
	43	[108]	GETGLOBAL	4 -7	; table
	44	[108]	GETTABLE 	4 4 -14	; "concat"
	45	[108]	MOVE     	5 3
	46	[108]	TAILCALL 	4 2 0
	47	[108]	RETURN   	4 0
	48	[109]	RETURN   	0 1

function <./upload/api.lua:111,114> (13 instructions, 52 bytes at 0x7fb47bc076a0)
1 param, 5 slots, 0 upvalues, 1 local, 4 constants, 0 functions
	1	[112]	GETGLOBAL	1 -1	; tostring
	2	[112]	MOVE     	2 0
	3	[112]	CALL     	1 2 2
	4	[112]	MOVE     	0 1
	5	[113]	SELF     	1 0 -2	; "gsub"
	6	[113]	LOADK    	3 -3	; ".*/api/[^/]+/[^/]+"
	7	[113]	LOADK    	4 -4	; ""
	8	[113]	CALL     	1 4 2
	9	[113]	TEST     	1 0 1
	10	[113]	JMP      	1	; to 12
	11	[113]	LOADK    	1 -4	; ""
	12	[113]	RETURN   	1 2
	13	[114]	RETURN   	0 1

function <./upload/api.lua:119,178> (190 instructions, 760 bytes at 0x7fb47bc094a0)
4 params, 23 slots, 5 upvalues, 23 locals, 54 constants, 0 functions
	1	[120]	GETUPVAL 	4 0	; cfg
	2	[120]	GETTABLE 	4 4 -1	; "variables"
	3	[121]	GETUPVAL 	5 1	; util
	4	[121]	GETTABLE 	5 5 -2	; "require_json"
	5	[121]	CALL     	5 1 3
	6	[122]	TEST     	5 0 1
	7	[122]	JMP      	5	; to 13
	8	[122]	LOADNIL  	7 7
	9	[122]	LOADK    	8 -3	; "A JSON library is required for this command. "
	10	[122]	MOVE     	9 6
	11	[122]	CONCAT   	8 8 9
	12	[122]	RETURN   	7 3
	13	[124]	GETUPVAL 	7 2	; fs
	14	[124]	GETTABLE 	7 7 -4	; "which_tool"
	15	[124]	LOADK    	8 -5	; "downloader"
	16	[124]	CALL     	7 2 2
	17	[124]	EQ       	0 7 -6	; - "wget"
	18	[124]	JMP      	10	; to 29
	19	[125]	GETUPVAL 	7 2	; fs
	20	[125]	GETTABLE 	7 7 -7	; "is_tool_available"
	21	[125]	GETTABLE 	8 4 -8	; "CURL"
	22	[125]	LOADK    	9 -9	; "curl"
	23	[125]	CALL     	7 3 3
	24	[126]	TEST     	7 0 1
	25	[126]	JMP      	3	; to 29
	26	[127]	LOADNIL  	9 9
	27	[127]	MOVE     	10 8
	28	[127]	RETURN   	9 3
	29	[131]	GETTABLE 	7 0 -10	; "config"
	30	[131]	GETTABLE 	7 7 -11	; "key"
	31	[131]	TEST     	7 0 1
	32	[131]	JMP      	3	; to 36
	33	[132]	LOADNIL  	7 7
	34	[132]	LOADK    	8 -12	; "Must have API key before performing any actions."
	35	[132]	RETURN   	7 3
	36	[134]	TEST     	2 0 0
	37	[134]	JMP      	11	; to 49
	38	[134]	GETGLOBAL	7 -13	; next
	39	[134]	MOVE     	8 2
	40	[134]	CALL     	7 2 2
	41	[134]	TEST     	7 0 0
	42	[134]	JMP      	6	; to 49
	43	[135]	MOVE     	7 1
	44	[135]	LOADK    	8 -14	; "?"
	45	[135]	GETUPVAL 	9 3	; encode_query_string
	46	[135]	MOVE     	10 2
	47	[135]	CALL     	9 2 2
	48	[135]	CONCAT   	1 7 9
	49	[137]	LOADK    	7 -15	; "GET"
	50	[138]	LOADNIL  	8 8
	51	[139]	GETUPVAL 	9 2	; fs
	52	[139]	GETTABLE 	9 9 -16	; "tmpname"
	53	[139]	CALL     	9 1 2
	54	[140]	TEST     	3 0 0
	55	[140]	JMP      	69	; to 125
	56	[141]	LOADK    	7 -17	; "POST"
	57	[142]	GETTABLE 	10 4 -8	; "CURL"
	58	[142]	LOADK    	11 -18	; " -f -k -L --silent --user-agent \""
	59	[142]	GETUPVAL 	12 0	; cfg
	60	[142]	GETTABLE 	12 12 -19	; "user_agent"
	61	[142]	LOADK    	13 -20	; " via curl\" "
	62	[142]	CONCAT   	10 10 13
	63	[143]	GETGLOBAL	11 -21	; pairs
	64	[143]	MOVE     	12 3
	65	[143]	CALL     	11 2 4
	66	[143]	JMP      	16	; to 83
	67	[144]	MOVE     	16 15
	68	[145]	GETGLOBAL	17 -22	; type
	69	[145]	MOVE     	18 15
	70	[145]	CALL     	17 2 2
	71	[145]	EQ       	0 17 -23	; - "table"
	72	[145]	JMP      	3	; to 76
	73	[146]	LOADK    	17 -24	; "@"
	74	[146]	GETTABLE 	18 15 -25	; "fname"
	75	[146]	CONCAT   	16 17 18
	76	[148]	MOVE     	17 10
	77	[148]	LOADK    	18 -26	; "--form \""
	78	[148]	MOVE     	19 14
	79	[148]	LOADK    	20 -27	; "="
	80	[148]	MOVE     	21 16
	81	[148]	LOADK    	22 -28	; "\" "
	82	[148]	CONCAT   	10 17 22
	83	[143]	TFORLOOP 	11 2
	84	[148]	JMP      	-18	; to 67
	85	[150]	GETUPVAL 	11 0	; cfg
	86	[150]	GETTABLE 	11 11 -29	; "connection_timeout"
	87	[150]	TEST     	11 0 0
	88	[150]	JMP      	12	; to 101
	89	[150]	GETUPVAL 	11 0	; cfg
	90	[150]	GETTABLE 	11 11 -29	; "connection_timeout"
	91	[150]	LT       	0 -30 11	; 0 -
	92	[150]	JMP      	8	; to 101
	93	[151]	MOVE     	11 10
	94	[151]	LOADK    	12 -31	; "--connect-timeout "
	95	[151]	GETGLOBAL	13 -32	; tonumber
	96	[151]	GETUPVAL 	14 0	; cfg
	97	[151]	GETTABLE 	14 14 -29	; "connection_timeout"
	98	[151]	CALL     	13 2 2
	99	[151]	LOADK    	14 -33	; " "
	100	[151]	CONCAT   	10 11 14
	101	[153]	GETUPVAL 	11 2	; fs
	102	[153]	GETTABLE 	11 11 -34	; "execute_string"
	103	[153]	MOVE     	12 10
	104	[153]	GETUPVAL 	13 2	; fs
	105	[153]	GETTABLE 	13 13 -35	; "Q"
	106	[153]	MOVE     	14 1
	107	[153]	CALL     	13 2 2
	108	[153]	LOADK    	14 -36	; " -o "
	109	[153]	GETUPVAL 	15 2	; fs
	110	[153]	GETTABLE 	15 15 -35	; "Q"
	111	[153]	MOVE     	16 9
	112	[153]	CALL     	15 2 2
	113	[153]	CONCAT   	12 12 15
	114	[153]	CALL     	11 2 2
	115	[154]	TEST     	11 0 1
	116	[154]	JMP      	26	; to 143
	117	[155]	LOADNIL  	12 12
	118	[155]	LOADK    	13 -37	; "API failure: "
	119	[155]	GETUPVAL 	14 4	; redact_api_url
	120	[155]	MOVE     	15 1
	121	[155]	CALL     	14 2 2
	122	[155]	CONCAT   	13 13 14
	123	[155]	RETURN   	12 3
	124	[156]	JMP      	18	; to 143
	125	[158]	GETUPVAL 	10 2	; fs
	126	[158]	GETTABLE 	10 10 -38	; "download"
	127	[158]	MOVE     	11 1
	128	[158]	MOVE     	12 9
	129	[158]	CALL     	10 3 3
	130	[159]	TEST     	10 0 1
	131	[159]	JMP      	11	; to 143
	132	[160]	LOADNIL  	12 12
	133	[160]	LOADK    	13 -37	; "API failure: "
	134	[160]	GETGLOBAL	14 -39	; tostring
	135	[160]	MOVE     	15 11
	136	[160]	CALL     	14 2 2
	137	[160]	LOADK    	15 -40	; " - "
	138	[160]	GETUPVAL 	16 4	; redact_api_url
	139	[160]	MOVE     	17 1
	140	[160]	CALL     	16 2 2
	141	[160]	CONCAT   	13 13 16
	142	[160]	RETURN   	12 3
	143	[164]	GETGLOBAL	10 -41	; io
	144	[164]	GETTABLE 	10 10 -42	; "open"
	145	[164]	MOVE     	11 9
	146	[164]	CALL     	10 2 2
	147	[165]	TEST     	10 0 1
	148	[165]	JMP      	11	; to 160
	149	[166]	GETGLOBAL	11 -43	; os
	150	[166]	GETTABLE 	11 11 -44	; "remove"
	151	[166]	MOVE     	12 9
	152	[166]	CALL     	11 2 1
	153	[167]	LOADNIL  	11 11
	154	[167]	LOADK    	12 -45	; "API failure reading temporary file - "
	155	[167]	GETUPVAL 	13 4	; redact_api_url
	156	[167]	MOVE     	14 1
	157	[167]	CALL     	13 2 2
	158	[167]	CONCAT   	12 12 13
	159	[167]	RETURN   	11 3
	160	[169]	SELF     	11 10 -46	; "read"
	161	[169]	LOADK    	13 -47	; "*a"
	162	[169]	CALL     	11 3 2
	163	[169]	MOVE     	8 11
	164	[170]	SELF     	11 10 -48	; "close"
	165	[170]	CALL     	11 2 1
	166	[171]	GETGLOBAL	11 -43	; os
	167	[171]	GETTABLE 	11 11 -44	; "remove"
	168	[171]	MOVE     	12 9
	169	[171]	CALL     	11 2 1
	170	[173]	GETTABLE 	11 0 -49	; "debug"
	171	[173]	TEST     	11 0 0
	172	[173]	JMP      	13	; to 186
	173	[174]	GETUPVAL 	11 1	; util
	174	[174]	GETTABLE 	11 11 -50	; "printout"
	175	[174]	LOADK    	12 -51	; "["
	176	[174]	GETGLOBAL	13 -39	; tostring
	177	[174]	MOVE     	14 7
	178	[174]	CALL     	13 2 2
	179	[174]	LOADK    	14 -52	; " via curl] "
	180	[174]	GETUPVAL 	15 4	; redact_api_url
	181	[174]	MOVE     	16 1
	182	[174]	CALL     	15 2 2
	183	[174]	LOADK    	16 -53	; " ... "
	184	[174]	CONCAT   	12 12 16
	185	[174]	CALL     	11 2 1
	186	[177]	GETTABLE 	11 6 -54	; "decode"
	187	[177]	MOVE     	12 8
	188	[177]	TAILCALL 	11 2 0
	189	[177]	RETURN   	11 0
	190	[178]	RETURN   	0 1

function <./upload/api.lua:184,244> (181 instructions, 724 bytes at 0x7fb47bc0a1e0)
4 params, 25 slots, 6 upvalues, 20 locals, 47 constants, 0 functions
	1	[185]	GETUPVAL 	4 0	; util
	2	[185]	GETTABLE 	4 4 -1	; "require_json"
	3	[185]	CALL     	4 1 3
	4	[186]	TEST     	4 0 1
	5	[186]	JMP      	5	; to 11
	6	[186]	LOADNIL  	6 6
	7	[186]	LOADK    	7 -2	; "A JSON library is required for this command. "
	8	[186]	MOVE     	8 5
	9	[186]	CONCAT   	7 7 8
	10	[186]	RETURN   	6 3
	11	[187]	GETGLOBAL	6 -3	; tostring
	12	[187]	GETTABLE 	7 0 -4	; "config"
	13	[187]	GETTABLE 	7 7 -5	; "server"
	14	[187]	CALL     	6 2 2
	15	[188]	LOADNIL  	7 8
	16	[189]	LOADK    	9 -6	; "luasocket"
	17	[190]	SELF     	10 6 -7	; "match"
	18	[190]	LOADK    	12 -8	; "^https://"
	19	[190]	CALL     	10 3 2
	20	[190]	TEST     	10 0 0
	21	[190]	JMP      	32	; to 54
	22	[191]	GETGLOBAL	10 -9	; pcall
	23	[191]	GETGLOBAL	11 -10	; require
	24	[191]	LOADK    	12 -11	; "ssl.https"
	25	[191]	CALL     	10 3 3
	26	[191]	MOVE     	8 11
	27	[191]	MOVE     	7 10
	28	[192]	TEST     	7 0 0
	29	[192]	JMP      	2	; to 32
	30	[193]	LOADK    	9 -12	; "luasec"
	31	[193]	JMP      	28	; to 60
	32	[195]	GETUPVAL 	10 1	; warned_luasec
	33	[195]	TEST     	10 0 1
	34	[195]	JMP      	6	; to 41
	35	[196]	GETUPVAL 	10 0	; util
	36	[196]	GETTABLE 	10 10 -13	; "printerr"
	37	[196]	LOADK    	11 -14	; "LuaSec is not available; using plain HTTP. Install 'luasec' to enable HTTPS."
	38	[196]	CALL     	10 2 1
	39	[197]	LOADBOOL 	10 1 0
	40	[197]	SETUPVAL 	10 1	; warned_luasec
	41	[199]	GETGLOBAL	10 -9	; pcall
	42	[199]	GETGLOBAL	11 -10	; require
	43	[199]	LOADK    	12 -15	; "socket.http"
	44	[199]	CALL     	10 3 3
	45	[199]	MOVE     	8 11
	46	[199]	MOVE     	7 10
	47	[200]	SELF     	10 1 -16	; "gsub"
	48	[200]	LOADK    	12 -17	; "^https"
	49	[200]	LOADK    	13 -18	; "http"
	50	[200]	CALL     	10 4 2
	51	[200]	MOVE     	1 10
	52	[201]	LOADK    	9 -6	; "luasocket"
	53	[202]	JMP      	6	; to 60
	54	[204]	GETGLOBAL	10 -9	; pcall
	55	[204]	GETGLOBAL	11 -10	; require
	56	[204]	LOADK    	12 -15	; "socket.http"
	57	[204]	CALL     	10 3 3
	58	[204]	MOVE     	8 11
	59	[204]	MOVE     	7 10
	60	[206]	TEST     	7 0 1
	61	[206]	JMP      	3	; to 65
	62	[207]	LOADNIL  	10 10
	63	[207]	LOADK    	11 -19	; "Failed loading socket library!"
	64	[207]	RETURN   	10 3
	65	[210]	GETTABLE 	10 0 -4	; "config"
	66	[210]	GETTABLE 	10 10 -20	; "key"
	67	[210]	TEST     	10 0 1
	68	[210]	JMP      	3	; to 72
	69	[211]	LOADNIL  	10 10
	70	[211]	LOADK    	11 -21	; "Must have API key before performing any actions."
	71	[211]	RETURN   	10 3
	72	[213]	LOADNIL  	10 10
	73	[214]	NEWTABLE 	11 0 0
	74	[215]	TEST     	2 0 0
	75	[215]	JMP      	11	; to 87
	76	[215]	GETGLOBAL	12 -22	; next
	77	[215]	MOVE     	13 2
	78	[215]	CALL     	12 2 2
	79	[215]	TEST     	12 0 0
	80	[215]	JMP      	6	; to 87
	81	[216]	MOVE     	12 1
	82	[216]	LOADK    	13 -23	; "?"
	83	[216]	GETUPVAL 	14 2	; encode_query_string
	84	[216]	MOVE     	15 2
	85	[216]	CALL     	14 2 2
	86	[216]	CONCAT   	1 12 14
	87	[218]	TEST     	3 0 0
	88	[218]	JMP      	15	; to 104
	89	[219]	LOADNIL  	12 12
	90	[220]	GETUPVAL 	13 3	; multipart
	91	[220]	GETTABLE 	13 13 -24	; "encode"
	92	[220]	MOVE     	14 3
	93	[220]	CALL     	13 2 3
	94	[220]	MOVE     	12 14
	95	[220]	MOVE     	10 13
	96	[221]	LEN      	13 10
	97	[221]	SETTABLE 	11 -25 13	; "Content-length" -
	98	[222]	LOADK    	13 -27	; "multipart/form-data; boundary="
	99	[222]	GETGLOBAL	14 -3	; tostring
	100	[222]	MOVE     	15 12
	101	[222]	CALL     	14 2 2
	102	[222]	CONCAT   	13 13 14
	103	[222]	SETTABLE 	11 -26 13	; "Content-type" -
	104	[224]	TEST     	3 0 0
	105	[224]	JMP      	3	; to 109
	106	[224]	LOADK    	12 -28	; "POST"
	107	[224]	TEST     	12 0 1
	108	[224]	JMP      	1	; to 110
	109	[224]	LOADK    	12 -29	; "GET"
	110	[225]	GETTABLE 	13 0 -30	; "debug"
	111	[225]	TEST     	13 0 0
	112	[225]	JMP      	15	; to 128
	113	[226]	GETUPVAL 	13 0	; util
	114	[226]	GETTABLE 	13 13 -31	; "printout"
	115	[226]	LOADK    	14 -32	; "["
	116	[226]	GETGLOBAL	15 -3	; tostring
	117	[226]	MOVE     	16 12
	118	[226]	CALL     	15 2 2
	119	[226]	LOADK    	16 -33	; " via "
	120	[226]	MOVE     	17 9
	121	[226]	LOADK    	18 -34	; "] "
	122	[226]	GETUPVAL 	19 4	; redact_api_url
	123	[226]	MOVE     	20 1
	124	[226]	CALL     	19 2 2
	125	[226]	LOADK    	20 -35	; " ... "
	126	[226]	CONCAT   	14 14 20
	127	[226]	CALL     	13 2 1
	128	[228]	NEWTABLE 	13 0 0
	129	[229]	GETTABLE 	14 8 -36	; "request"
	130	[229]	NEWTABLE 	15 0 5
	131	[230]	SETTABLE 	15 -37 1	; "url" -
	132	[231]	SETTABLE 	15 -38 11	; "headers" -
	133	[232]	SETTABLE 	15 -39 12	; "method" -
	134	[233]	GETUPVAL 	16 5	; ltn12
	135	[233]	GETTABLE 	16 16 -40	; "sink"
	136	[233]	GETTABLE 	16 16 -41	; "table"
	137	[233]	MOVE     	17 13
	138	[233]	CALL     	16 2 2
	139	[233]	SETTABLE 	15 -40 16	; "sink" -
	140	[234]	TESTSET  	16 10 0
	141	[234]	JMP      	5	; to 147
	142	[234]	GETUPVAL 	16 5	; ltn12
	143	[234]	GETTABLE 	16 16 -42	; "source"
	144	[234]	GETTABLE 	16 16 -43	; "string"
	145	[234]	MOVE     	17 10
	146	[234]	CALL     	16 2 2
	147	[234]	SETTABLE 	15 -42 16	; "source" -
	148	[229]	CALL     	14 2 3
	149	[236]	GETTABLE 	16 0 -30	; "debug"
	150	[236]	TEST     	16 0 0
	151	[236]	JMP      	6	; to 158
	152	[237]	GETUPVAL 	16 0	; util
	153	[237]	GETTABLE 	16 16 -31	; "printout"
	154	[237]	GETGLOBAL	17 -3	; tostring
	155	[237]	MOVE     	18 15
	156	[237]	CALL     	17 2 0
	157	[237]	CALL     	16 0 1
	158	[239]	GETGLOBAL	16 -9	; pcall
	159	[239]	GETTABLE 	17 5 -44	; "decode"
	160	[239]	GETGLOBAL	18 -41	; table
	161	[239]	GETTABLE 	18 18 -45	; "concat"
	162	[239]	MOVE     	19 13
	163	[239]	CALL     	18 2 0
	164	[239]	CALL     	16 0 4
	165	[240]	TEST     	16 0 0
	166	[240]	JMP      	3	; to 170
	167	[240]	TEST     	17 0 0
	168	[240]	JMP      	1	; to 170
	169	[241]	RETURN   	17 2
	170	[243]	LOADNIL  	19 19
	171	[243]	LOADK    	20 -46	; "API returned "
	172	[243]	GETGLOBAL	21 -3	; tostring
	173	[243]	MOVE     	22 15
	174	[243]	CALL     	21 2 2
	175	[243]	LOADK    	22 -47	; " - "
	176	[243]	GETUPVAL 	23 4	; redact_api_url
	177	[243]	MOVE     	24 1
	178	[243]	CALL     	23 2 2
	179	[243]	CONCAT   	20 20 23
	180	[243]	RETURN   	19 3
	181	[244]	RETURN   	0 1

function <./upload/api.lua:248,265> (66 instructions, 264 bytes at 0x7fb47bc09740)
1 param, 8 slots, 2 upvalues, 2 locals, 16 constants, 0 functions
	1	[249]	NEWTABLE 	1 0 0
	2	[250]	GETGLOBAL	2 -1	; setmetatable
	3	[250]	MOVE     	3 1
	4	[250]	NEWTABLE 	4 0 1
	5	[250]	GETUPVAL 	5 0	; Api
	6	[250]	SETTABLE 	4 -2 5	; "__index" -
	7	[250]	CALL     	2 3 1
	8	[251]	SELF     	2 1 -4	; "load_config"
	9	[251]	CALL     	2 2 2
	10	[251]	TEST     	2 0 1
	11	[251]	JMP      	1	; to 13
	12	[251]	NEWTABLE 	2 0 0
	13	[251]	SETTABLE 	1 -3 2	; "config" -
	14	[252]	GETTABLE 	2 1 -3	; "config"
	15	[252]	GETTABLE 	3 0 -5	; "server"
	16	[252]	TEST     	3 0 1
	17	[252]	JMP      	7	; to 25
	18	[252]	GETTABLE 	3 1 -3	; "config"
	19	[252]	GETTABLE 	3 3 -5	; "server"
	20	[252]	TEST     	3 0 1
	21	[252]	JMP      	3	; to 25
	22	[252]	GETUPVAL 	3 1	; cfg
	23	[252]	GETTABLE 	3 3 -6	; "upload"
	24	[252]	GETTABLE 	3 3 -5	; "server"
	25	[252]	SETTABLE 	2 -5 3	; "server" -
	26	[253]	GETTABLE 	2 1 -3	; "config"
	27	[253]	GETTABLE 	3 1 -3	; "config"
	28	[253]	GETTABLE 	3 3 -7	; "version"
	29	[253]	TEST     	3 0 1
	30	[253]	JMP      	3	; to 34
	31	[253]	GETUPVAL 	3 1	; cfg
	32	[253]	GETTABLE 	3 3 -6	; "upload"
	33	[253]	GETTABLE 	3 3 -7	; "version"
	34	[253]	SETTABLE 	2 -7 3	; "version" -
	35	[254]	GETTABLE 	2 1 -3	; "config"
	36	[254]	GETTABLE 	3 0 -9	; "temp_key"
	37	[254]	TEST     	3 0 1
	38	[254]	JMP      	5	; to 44
	39	[254]	GETTABLE 	3 0 -10	; "api_key"
	40	[254]	TEST     	3 0 1
	41	[254]	JMP      	2	; to 44
	42	[254]	GETTABLE 	3 1 -3	; "config"
	43	[254]	GETTABLE 	3 3 -8	; "key"
	44	[254]	SETTABLE 	2 -8 3	; "key" -
	45	[255]	GETTABLE 	2 0 -11	; "debug"
	46	[255]	SETTABLE 	1 -11 2	; "debug" -
	47	[256]	GETTABLE 	2 1 -3	; "config"
	48	[256]	GETTABLE 	2 2 -8	; "key"
	49	[256]	TEST     	2 0 1
	50	[256]	JMP      	9	; to 60
	51	[257]	LOADNIL  	2 2
	52	[257]	LOADK    	3 -12	; "You need an API key to upload rocks.\n"
	53	[258]	LOADK    	4 -13	; "Navigate to "
	54	[258]	GETTABLE 	5 1 -3	; "config"
	55	[258]	GETTABLE 	5 5 -5	; "server"
	56	[258]	LOADK    	6 -14	; "/settings to get a key\n"
	57	[259]	LOADK    	7 -15	; "and then pass it through the --api-key=<key> flag."
	58	[259]	CONCAT   	3 3 7
	59	[259]	RETURN   	2 3
	60	[261]	GETTABLE 	2 0 -10	; "api_key"
	61	[261]	TEST     	2 0 0
	62	[261]	JMP      	2	; to 65
	63	[262]	SELF     	2 1 -16	; "save_config"
	64	[262]	CALL     	2 2 1
	65	[264]	RETURN   	1 2
	66	[265]	RETURN   	0 1
