
main <./build.lua:0,0> (112 instructions, 448 bytes at 0x7fd56c4068a0)
0+ params, 20 slots, 0 upvalues, 22 locals, 29 constants, 12 functions
	1	[2]	NEWTABLE 	0 0 0
	2	[4]	GETGLOBAL	1 -1	; require
	3	[4]	LOADK    	2 -2	; "luarocks.path"
	4	[4]	CALL     	1 2 2
	5	[5]	GETGLOBAL	2 -1	; require
	6	[5]	LOADK    	3 -3	; "luarocks.util"
	7	[5]	CALL     	2 2 2
	8	[6]	GETGLOBAL	3 -1	; require
	9	[6]	LOADK    	4 -4	; "luarocks.fun"
	10	[6]	CALL     	3 2 2
	11	[7]	GETGLOBAL	4 -1	; require
	12	[7]	LOADK    	5 -5	; "luarocks.fetch"
	13	[7]	CALL     	4 2 2
	14	[8]	GETGLOBAL	5 -1	; require
	15	[8]	LOADK    	6 -6	; "luarocks.fs"
	16	[8]	CALL     	5 2 2
	17	[9]	GETGLOBAL	6 -1	; require
	18	[9]	LOADK    	7 -7	; "luarocks.dir"
	19	[9]	CALL     	6 2 2
	20	[10]	GETGLOBAL	7 -1	; require
	21	[10]	LOADK    	8 -8	; "luarocks.deps"
	22	[10]	CALL     	7 2 2
	23	[11]	GETGLOBAL	8 -1	; require
	24	[11]	LOADK    	9 -9	; "luarocks.core.cfg"
	25	[11]	CALL     	8 2 2
	26	[12]	GETGLOBAL	9 -1	; require
	27	[12]	LOADK    	10 -10	; "luarocks.repos"
	28	[12]	CALL     	9 2 2
	29	[13]	GETGLOBAL	10 -1	; require
	30	[13]	LOADK    	11 -11	; "luarocks.manif.writer"
	31	[13]	CALL     	10 2 2
	32	[14]	GETGLOBAL	11 -1	; require
	33	[14]	LOADK    	12 -12	; "luarocks.deplocks"
	34	[14]	CALL     	11 2 2
	35	[16]	GETTABLE 	12 2 -14	; "opts_table"
	36	[16]	LOADK    	13 -15	; "build.opts"
	37	[16]	NEWTABLE 	14 0 9
	38	[17]	SETTABLE 	14 -16 -17	; "need_to_fetch" "boolean"
	39	[18]	SETTABLE 	14 -18 -17	; "minimal_mode" "boolean"
	40	[19]	SETTABLE 	14 -19 -20	; "deps_mode" "string"
	41	[20]	SETTABLE 	14 -21 -17	; "build_only_deps" "boolean"
	42	[21]	SETTABLE 	14 -22 -23	; "namespace" "string?"
	43	[22]	SETTABLE 	14 -24 -23	; "branch" "string?"
	44	[23]	SETTABLE 	14 -25 -17	; "verify" "boolean"
	45	[24]	SETTABLE 	14 -26 -17	; "check_lua_versions" "boolean"
	46	[25]	SETTABLE 	14 -27 -17	; "pin" "boolean"
	47	[16]	CALL     	12 3 2
	48	[26]	SETTABLE 	0 -13 12	; "opts" -
	49	[38]	CLOSURE  	12 0	; 0x7fd56c406fd0
	50	[38]	MOVE     	0 6
	51	[38]	MOVE     	0 5
	52	[79]	CLOSURE  	13 1	; 0x7fd56c4078b0
	53	[79]	MOVE     	0 5
	54	[79]	MOVE     	0 12
	55	[79]	MOVE     	0 2
	56	[46]	SETTABLE 	0 -28 13	; "apply_patches" -
	57	[79]	CLOSE    	12
	58	[105]	CLOSURE  	12 2	; 0x7fd56c407a90
	59	[105]	MOVE     	0 8
	60	[105]	MOVE     	0 2
	61	[144]	CLOSURE  	13 3	; 0x7fd56c409470
	62	[144]	MOVE     	0 7
	63	[144]	MOVE     	0 8
	64	[171]	CLOSURE  	14 4	; 0x7fd56c409900
	65	[171]	MOVE     	0 4
	66	[171]	MOVE     	0 5
	67	[189]	CLOSURE  	15 5	; 0x7fd56c406cd0
	68	[189]	MOVE     	0 1
	69	[189]	MOVE     	0 5
	70	[214]	CLOSURE  	16 6	; 0x7fd56c406600
	71	[214]	MOVE     	0 2
	72	[214]	MOVE     	0 8
	73	[214]	MOVE     	0 3
	74	[216]	LOADNIL  	17 17
	75	[270]	CLOSURE  	18 7	; 0x7fd56c40b650
	76	[270]	MOVE     	0 6
	77	[270]	MOVE     	0 1
	78	[270]	MOVE     	0 5
	79	[288]	CLOSURE  	19 8	; 0x7fd56c40b700
	80	[288]	MOVE     	0 6
	81	[288]	MOVE     	0 1
	82	[288]	MOVE     	0 5
	83	[325]	CLOSURE  	17 9	; 0x7fd56c40c040
	84	[325]	MOVE     	0 18
	85	[325]	MOVE     	0 5
	86	[325]	MOVE     	0 6
	87	[325]	MOVE     	0 1
	88	[325]	MOVE     	0 19
	89	[325]	CLOSE    	18
	90	[345]	CLOSURE  	18 10	; 0x7fd56c40c630
	91	[345]	MOVE     	0 5
	92	[345]	MOVE     	0 1
	93	[345]	MOVE     	0 11
	94	[345]	MOVE     	0 6
	95	[345]	MOVE     	0 10
	96	[441]	CLOSURE  	19 11	; 0x7fd56c40c860
	97	[441]	MOVE     	0 14
	98	[441]	MOVE     	0 11
	99	[441]	MOVE     	0 13
	100	[441]	MOVE     	0 9
	101	[441]	MOVE     	0 15
	102	[441]	MOVE     	0 2
	103	[441]	MOVE     	0 5
	104	[441]	MOVE     	0 1
	105	[441]	MOVE     	0 0
	106	[441]	MOVE     	0 12
	107	[441]	MOVE     	0 16
	108	[441]	MOVE     	0 17
	109	[441]	MOVE     	0 18
	110	[351]	SETTABLE 	0 -29 19	; "build_rockspec" -
	111	[443]	RETURN   	0 2
	112	[443]	RETURN   	0 1

function <./build.lua:32,38> (23 instructions, 92 bytes at 0x7fd56c406fd0)
1 param, 10 slots, 2 upvalues, 7 locals, 8 constants, 0 functions
	1	[33]	GETGLOBAL	1 -1	; pairs
	2	[33]	MOVE     	2 0
	3	[33]	CALL     	1 2 4
	4	[33]	JMP      	16	; to 21
	5	[34]	GETGLOBAL	6 -2	; io
	6	[34]	GETTABLE 	6 6 -3	; "open"
	7	[34]	GETUPVAL 	7 0	; dir
	8	[34]	GETTABLE 	7 7 -4	; "path"
	9	[34]	GETUPVAL 	8 1	; fs
	10	[34]	GETTABLE 	8 8 -5	; "current_dir"
	11	[34]	CALL     	8 1 2
	12	[34]	MOVE     	9 4
	13	[34]	CALL     	7 3 2
	14	[34]	LOADK    	8 -6	; "w+"
	15	[34]	CALL     	6 3 2
	16	[35]	SELF     	7 6 -7	; "write"
	17	[35]	MOVE     	9 5
	18	[35]	CALL     	7 3 1
	19	[36]	SELF     	7 6 -8	; "close"
	20	[36]	CALL     	7 2 1
	21	[33]	TFORLOOP 	1 2
	22	[36]	JMP      	-18	; to 5
	23	[38]	RETURN   	0 1

function <./build.lua:46,79> (97 instructions, 388 bytes at 0x7fd56c4078b0)
1 param, 13 slots, 3 upvalues, 10 locals, 22 constants, 0 functions
	1	[47]	GETGLOBAL	1 -1	; assert
	2	[47]	SELF     	2 0 -2	; "type"
	3	[47]	CALL     	2 2 2
	4	[47]	EQ       	1 2 -3	; - "rockspec"
	5	[47]	JMP      	1	; to 7
	6	[47]	LOADBOOL 	2 0 1
	7	[47]	LOADBOOL 	2 1 0
	8	[47]	CALL     	1 2 1
	9	[49]	GETTABLE 	1 0 -4	; "build"
	10	[49]	GETTABLE 	1 1 -5	; "extra_files"
	11	[49]	TEST     	1 0 1
	12	[49]	JMP      	6	; to 19
	13	[49]	GETTABLE 	1 0 -4	; "build"
	14	[49]	GETTABLE 	1 1 -6	; "patches"
	15	[49]	TEST     	1 0 1
	16	[49]	JMP      	2	; to 19
	17	[50]	LOADBOOL 	1 1 0
	18	[50]	RETURN   	1 2
	19	[53]	GETGLOBAL	1 -7	; io
	20	[53]	GETTABLE 	1 1 -8	; "open"
	21	[53]	GETUPVAL 	2 0	; fs
	22	[53]	GETTABLE 	2 2 -9	; "absolute_name"
	23	[53]	LOADK    	3 -10	; ".luarocks.patches.applied"
	24	[53]	CALL     	2 2 2
	25	[53]	LOADK    	3 -11	; "r"
	26	[53]	CALL     	1 3 2
	27	[54]	TEST     	1 0 0
	28	[54]	JMP      	4	; to 33
	29	[55]	SELF     	2 1 -12	; "close"
	30	[55]	CALL     	2 2 1
	31	[56]	LOADBOOL 	2 1 0
	32	[56]	RETURN   	2 2
	33	[59]	GETTABLE 	2 0 -4	; "build"
	34	[59]	GETTABLE 	2 2 -5	; "extra_files"
	35	[59]	TEST     	2 0 0
	36	[59]	JMP      	4	; to 41
	37	[60]	GETUPVAL 	2 1	; extract_from_rockspec
	38	[60]	GETTABLE 	3 0 -4	; "build"
	39	[60]	GETTABLE 	3 3 -5	; "extra_files"
	40	[60]	CALL     	2 2 1
	41	[62]	GETTABLE 	2 0 -4	; "build"
	42	[62]	GETTABLE 	2 2 -6	; "patches"
	43	[62]	TEST     	2 0 0
	44	[62]	JMP      	37	; to 82
	45	[63]	GETUPVAL 	2 1	; extract_from_rockspec
	46	[63]	GETTABLE 	3 0 -4	; "build"
	47	[63]	GETTABLE 	3 3 -6	; "patches"
	48	[63]	CALL     	2 2 1
	49	[64]	GETUPVAL 	2 2	; util
	50	[64]	GETTABLE 	2 2 -13	; "sortedpairs"
	51	[64]	GETTABLE 	3 0 -4	; "build"
	52	[64]	GETTABLE 	3 3 -6	; "patches"
	53	[64]	CALL     	2 2 4
	54	[64]	JMP      	25	; to 80
	55	[65]	GETUPVAL 	7 2	; util
	56	[65]	GETTABLE 	7 7 -14	; "printout"
	57	[65]	LOADK    	8 -15	; "Applying patch "
	58	[65]	MOVE     	9 5
	59	[65]	LOADK    	10 -16	; "..."
	60	[65]	CONCAT   	8 8 10
	61	[65]	CALL     	7 2 1
	62	[66]	SELF     	7 0 -17	; "format_is_at_least"
	63	[66]	LOADK    	9 -18	; "3.0"
	64	[66]	CALL     	7 3 2
	65	[67]	GETUPVAL 	8 0	; fs
	66	[67]	GETTABLE 	8 8 -19	; "apply_patch"
	67	[67]	GETGLOBAL	9 -20	; tostring
	68	[67]	MOVE     	10 5
	69	[67]	CALL     	9 2 2
	70	[67]	MOVE     	10 6
	71	[67]	MOVE     	11 7
	72	[67]	CALL     	8 4 3
	73	[68]	TEST     	8 0 1
	74	[68]	JMP      	5	; to 80
	75	[69]	LOADNIL  	10 10
	76	[69]	LOADK    	11 -21	; "Failed applying patch "
	77	[69]	MOVE     	12 5
	78	[69]	CONCAT   	11 11 12
	79	[69]	RETURN   	10 3
	80	[64]	TFORLOOP 	2 2
	81	[70]	JMP      	-27	; to 55
	82	[74]	GETGLOBAL	2 -7	; io
	83	[74]	GETTABLE 	2 2 -8	; "open"
	84	[74]	GETUPVAL 	3 0	; fs
	85	[74]	GETTABLE 	3 3 -9	; "absolute_name"
	86	[74]	LOADK    	4 -10	; ".luarocks.patches.applied"
	87	[74]	CALL     	3 2 2
	88	[74]	LOADK    	4 -22	; "w"
	89	[74]	CALL     	2 3 2
	90	[74]	MOVE     	1 2
	91	[75]	TEST     	1 0 0
	92	[75]	JMP      	2	; to 95
	93	[76]	SELF     	2 1 -12	; "close"
	94	[76]	CALL     	2 2 1
	95	[78]	LOADBOOL 	2 1 0
	96	[78]	RETURN   	2 2
	97	[79]	RETURN   	0 1

function <./build.lua:82,105> (47 instructions, 188 bytes at 0x7fd56c407a90)
1 param, 12 slots, 2 upvalues, 7 locals, 12 constants, 2 functions
	1	[83]	GETTABLE 	1 0 -1	; "build"
	2	[83]	GETTABLE 	1 1 -2	; "macosx_deployment_target"
	3	[86]	CLOSURE  	2 0	; 0x7fd56c408830
	4	[93]	CLOSURE  	3 1	; 0x7fd56c407d80
	5	[93]	MOVE     	0 0
	6	[93]	MOVE     	0 1
	7	[94]	GETUPVAL 	4 0	; cfg
	8	[94]	GETTABLE 	4 4 -3	; "is_platform"
	9	[94]	LOADK    	5 -4	; "macosx"
	10	[94]	CALL     	4 2 2
	11	[94]	TEST     	4 0 0
	12	[94]	JMP      	32	; to 45
	13	[94]	SELF     	4 0 -5	; "format_is_at_least"
	14	[94]	LOADK    	6 -6	; "3.0"
	15	[94]	CALL     	4 3 2
	16	[94]	TEST     	4 0 0
	17	[94]	JMP      	27	; to 45
	18	[94]	TEST     	1 0 0
	19	[94]	JMP      	25	; to 45
	20	[95]	GETUPVAL 	4 1	; util
	21	[95]	GETTABLE 	4 4 -7	; "popen_read"
	22	[95]	LOADK    	5 -8	; "sw_vers -productVersion"
	23	[95]	CALL     	4 2 2
	24	[96]	MOVE     	5 2
	25	[96]	MOVE     	6 4
	26	[96]	CALL     	5 2 2
	27	[97]	MOVE     	6 2
	28	[97]	MOVE     	7 1
	29	[97]	CALL     	6 2 2
	30	[98]	LT       	0 5 6
	31	[98]	JMP      	7	; to 39
	32	[99]	LOADNIL  	7 7
	33	[99]	LOADK    	8 -9	; "This rock requires Mac OSX 10.%d, and you are running 10.%d."
	34	[99]	SELF     	8 8 -10	; "format"
	35	[99]	MOVE     	10 6
	36	[99]	MOVE     	11 5
	37	[99]	CALL     	8 4 0
	38	[99]	RETURN   	7 0
	39	[101]	MOVE     	7 3
	40	[101]	LOADK    	8 -11	; "CC"
	41	[101]	CALL     	7 2 1
	42	[102]	MOVE     	7 3
	43	[102]	LOADK    	8 -12	; "LD"
	44	[102]	CALL     	7 2 1
	45	[104]	LOADBOOL 	4 1 0
	46	[104]	RETURN   	4 2
	47	[105]	RETURN   	0 1

function <./build.lua:84,86> (9 instructions, 36 bytes at 0x7fd56c408830)
1 param, 5 slots, 0 upvalues, 1 local, 3 constants, 0 functions
	1	[85]	GETGLOBAL	1 -1	; tonumber
	2	[85]	TESTSET  	2 0 0
	3	[85]	JMP      	3	; to 7
	4	[85]	SELF     	2 0 -2	; "match"
	5	[85]	LOADK    	4 -3	; "^[^.]+%.([^.]+)"
	6	[85]	CALL     	2 3 2
	7	[85]	TAILCALL 	1 2 0
	8	[85]	RETURN   	1 0
	9	[86]	RETURN   	0 1

function <./build.lua:87,93> (32 instructions, 128 bytes at 0x7fd56c407d80)
1 param, 7 slots, 2 upvalues, 1 local, 8 constants, 0 functions
	1	[88]	GETUPVAL 	1 0	; rockspec
	2	[88]	GETTABLE 	1 1 -1	; "variables"
	3	[88]	GETTABLE 	1 1 0
	4	[88]	SELF     	1 1 -2	; "match"
	5	[88]	LOADK    	3 -3	; "MACOSX_DEPLOYMENT_TARGET"
	6	[88]	CALL     	1 3 2
	7	[88]	TEST     	1 0 0
	8	[88]	JMP      	13	; to 22
	9	[89]	GETUPVAL 	1 0	; rockspec
	10	[89]	GETTABLE 	1 1 -1	; "variables"
	11	[89]	GETUPVAL 	2 0	; rockspec
	12	[89]	GETTABLE 	2 2 -1	; "variables"
	13	[89]	GETTABLE 	2 2 0
	14	[89]	SELF     	2 2 -4	; "gsub"
	15	[89]	LOADK    	4 -5	; "MACOSX_DEPLOYMENT_TARGET=[^ ]*"
	16	[89]	LOADK    	5 -6	; "MACOSX_DEPLOYMENT_TARGET="
	17	[89]	GETUPVAL 	6 1	; target
	18	[89]	CONCAT   	5 5 6
	19	[89]	CALL     	2 4 2
	20	[89]	SETTABLE 	1 0 2
	21	[89]	JMP      	10	; to 32
	22	[91]	GETUPVAL 	1 0	; rockspec
	23	[91]	GETTABLE 	1 1 -1	; "variables"
	24	[91]	LOADK    	2 -7	; "env MACOSX_DEPLOYMENT_TARGET="
	25	[91]	GETUPVAL 	3 1	; target
	26	[91]	LOADK    	4 -8	; " "
	27	[91]	GETUPVAL 	5 0	; rockspec
	28	[91]	GETTABLE 	5 5 -1	; "variables"
	29	[91]	GETTABLE 	5 5 0
	30	[91]	CONCAT   	2 2 5
	31	[91]	SETTABLE 	1 0 2
	32	[93]	RETURN   	0 1

function <./build.lua:107,144> (80 instructions, 320 bytes at 0x7fd56c409470)
2 params, 11 slots, 2 upvalues, 17 locals, 14 constants, 0 functions
	1	[108]	GETTABLE 	2 1 -1	; "build_only_deps"
	2	[108]	TEST     	2 0 1
	3	[108]	JMP      	11	; to 15
	4	[109]	GETUPVAL 	2 0	; deps
	5	[109]	GETTABLE 	2 2 -2	; "check_external_deps"
	6	[109]	MOVE     	3 0
	7	[109]	LOADK    	4 -3	; "build"
	8	[109]	CALL     	2 3 4
	9	[110]	TEST     	3 0 0
	10	[110]	JMP      	4	; to 15
	11	[111]	LOADNIL  	5 5
	12	[111]	MOVE     	6 3
	13	[111]	MOVE     	7 4
	14	[111]	RETURN   	5 4
	15	[115]	GETUPVAL 	2 0	; deps
	16	[115]	GETTABLE 	2 2 -4	; "check_lua_incdir"
	17	[115]	GETTABLE 	3 0 -5	; "variables"
	18	[115]	CALL     	2 2 4
	19	[116]	TEST     	2 0 1
	20	[116]	JMP      	4	; to 25
	21	[117]	LOADNIL  	5 5
	22	[117]	MOVE     	6 3
	23	[117]	MOVE     	7 4
	24	[117]	RETURN   	5 4
	25	[120]	GETUPVAL 	5 1	; cfg
	26	[120]	GETTABLE 	5 5 -6	; "link_lua_explicitly"
	27	[120]	TEST     	5 0 0
	28	[120]	JMP      	10	; to 39
	29	[121]	GETUPVAL 	5 0	; deps
	30	[121]	GETTABLE 	5 5 -7	; "check_lua_libdir"
	31	[121]	GETTABLE 	6 0 -5	; "variables"
	32	[121]	CALL     	5 2 4
	33	[122]	TEST     	5 0 1
	34	[122]	JMP      	4	; to 39
	35	[123]	LOADNIL  	8 8
	36	[123]	MOVE     	9 6
	37	[123]	MOVE     	10 7
	38	[123]	RETURN   	8 4
	39	[127]	GETTABLE 	5 1 -8	; "deps_mode"
	40	[127]	EQ       	0 5 -9	; - "none"
	41	[127]	JMP      	2	; to 44
	42	[128]	LOADBOOL 	5 1 0
	43	[128]	RETURN   	5 2
	44	[131]	GETTABLE 	5 1 -1	; "build_only_deps"
	45	[131]	TEST     	5 0 1
	46	[131]	JMP      	18	; to 65
	47	[132]	GETGLOBAL	5 -10	; next
	48	[132]	GETTABLE 	6 0 -11	; "build_dependencies"
	49	[132]	CALL     	5 2 2
	50	[132]	TEST     	5 0 0
	51	[132]	JMP      	13	; to 65
	52	[133]	GETUPVAL 	5 0	; deps
	53	[133]	GETTABLE 	5 5 -12	; "fulfill_dependencies"
	54	[133]	MOVE     	6 0
	55	[133]	LOADK    	7 -11	; "build_dependencies"
	56	[133]	GETTABLE 	8 1 -8	; "deps_mode"
	57	[133]	GETTABLE 	9 1 -13	; "verify"
	58	[133]	CALL     	5 5 4
	59	[134]	TEST     	6 0 0
	60	[134]	JMP      	4	; to 65
	61	[135]	LOADNIL  	8 8
	62	[135]	MOVE     	9 6
	63	[135]	MOVE     	10 7
	64	[135]	RETURN   	8 4
	65	[139]	GETUPVAL 	5 0	; deps
	66	[139]	GETTABLE 	5 5 -12	; "fulfill_dependencies"
	67	[139]	MOVE     	6 0
	68	[139]	LOADK    	7 -14	; "dependencies"
	69	[139]	GETTABLE 	8 1 -8	; "deps_mode"
	70	[139]	GETTABLE 	9 1 -13	; "verify"
	71	[139]	CALL     	5 5 4
	72	[140]	TEST     	6 0 0
	73	[140]	JMP      	4	; to 78
	74	[141]	LOADNIL  	8 8
	75	[141]	MOVE     	9 6
	76	[141]	MOVE     	10 7
	77	[141]	RETURN   	8 4
	78	[143]	LOADBOOL 	8 1 0
	79	[143]	RETURN   	8 2
	80	[144]	RETURN   	0 1

function <./build.lua:146,171> (63 instructions, 252 bytes at 0x7fd56c409900)
2 params, 8 slots, 2 upvalues, 8 locals, 10 constants, 0 functions
	1	[147]	GETTABLE 	2 1 -1	; "minimal_mode"
	2	[147]	TEST     	2 0 1
	3	[147]	JMP      	3	; to 7
	4	[147]	GETTABLE 	2 1 -2	; "build_only_deps"
	5	[147]	TEST     	2 0 0
	6	[147]	JMP      	2	; to 9
	7	[148]	LOADBOOL 	2 1 0
	8	[148]	RETURN   	2 2
	9	[150]	GETTABLE 	2 1 -3	; "need_to_fetch"
	10	[150]	TEST     	2 0 0
	11	[150]	JMP      	30	; to 42
	12	[151]	GETTABLE 	2 1 -4	; "branch"
	13	[151]	TEST     	2 0 0
	14	[151]	JMP      	3	; to 18
	15	[152]	GETTABLE 	2 0 -5	; "source"
	16	[152]	GETTABLE 	3 1 -4	; "branch"
	17	[152]	SETTABLE 	2 -4 3	; "branch" -
	18	[154]	GETUPVAL 	2 0	; fetch
	19	[154]	GETTABLE 	2 2 -6	; "fetch_sources"
	20	[154]	MOVE     	3 0
	21	[154]	LOADBOOL 	4 1 0
	22	[154]	CALL     	2 3 4
	23	[155]	TEST     	2 0 1
	24	[155]	JMP      	4	; to 29
	25	[156]	LOADNIL  	5 5
	26	[156]	MOVE     	6 3
	27	[156]	MOVE     	7 4
	28	[156]	RETURN   	5 4
	29	[158]	LOADNIL  	5 5
	30	[159]	GETUPVAL 	6 1	; fs
	31	[159]	GETTABLE 	6 6 -7	; "change_dir"
	32	[159]	MOVE     	7 3
	33	[159]	CALL     	6 2 3
	34	[159]	MOVE     	5 7
	35	[159]	MOVE     	2 6
	36	[160]	TEST     	2 0 1
	37	[160]	JMP      	18	; to 56
	38	[161]	LOADNIL  	6 6
	39	[161]	MOVE     	7 5
	40	[161]	RETURN   	6 3
	41	[162]	JMP      	14	; to 56
	42	[163]	GETTABLE 	2 0 -5	; "source"
	43	[163]	GETTABLE 	2 2 -8	; "file"
	44	[163]	TEST     	2 0 0
	45	[163]	JMP      	10	; to 56
	46	[164]	GETUPVAL 	2 1	; fs
	47	[164]	GETTABLE 	2 2 -9	; "unpack_archive"
	48	[164]	GETTABLE 	3 0 -5	; "source"
	49	[164]	GETTABLE 	3 3 -8	; "file"
	50	[164]	CALL     	2 2 3
	51	[165]	TEST     	2 0 1
	52	[165]	JMP      	3	; to 56
	53	[166]	LOADNIL  	4 4
	54	[166]	MOVE     	5 3
	55	[166]	RETURN   	4 3
	56	[169]	GETUPVAL 	2 1	; fs
	57	[169]	GETTABLE 	2 2 -7	; "change_dir"
	58	[169]	GETTABLE 	3 0 -5	; "source"
	59	[169]	GETTABLE 	3 3 -10	; "dir"
	60	[169]	CALL     	2 2 1
	61	[170]	LOADBOOL 	2 1 0
	62	[170]	RETURN   	2 2
	63	[171]	RETURN   	0 1

function <./build.lua:173,189> (58 instructions, 232 bytes at 0x7fd56c406cd0)
2 params, 12 slots, 2 upvalues, 10 locals, 17 constants, 0 functions
	1	[174]	NEWTABLE 	2 0 4
	2	[175]	NEWTABLE 	3 0 3
	3	[175]	GETUPVAL 	4 0	; path
	4	[175]	GETTABLE 	4 4 -3	; "lua_dir"
	5	[175]	MOVE     	5 0
	6	[175]	MOVE     	6 1
	7	[175]	CALL     	4 3 2
	8	[175]	SETTABLE 	3 -2 4	; "name" -
	9	[175]	SETTABLE 	3 -4 -5	; "is_module_path" true
	10	[175]	SETTABLE 	3 -6 -7	; "perms" "read"
	11	[175]	SETTABLE 	2 -1 3	; "lua" -
	12	[176]	NEWTABLE 	3 0 3
	13	[176]	GETUPVAL 	4 0	; path
	14	[176]	GETTABLE 	4 4 -9	; "lib_dir"
	15	[176]	MOVE     	5 0
	16	[176]	MOVE     	6 1
	17	[176]	CALL     	4 3 2
	18	[176]	SETTABLE 	3 -2 4	; "name" -
	19	[176]	SETTABLE 	3 -4 -5	; "is_module_path" true
	20	[176]	SETTABLE 	3 -6 -10	; "perms" "exec"
	21	[176]	SETTABLE 	2 -8 3	; "lib" -
	22	[177]	NEWTABLE 	3 0 3
	23	[177]	GETUPVAL 	4 0	; path
	24	[177]	GETTABLE 	4 4 -12	; "bin_dir"
	25	[177]	MOVE     	5 0
	26	[177]	MOVE     	6 1
	27	[177]	CALL     	4 3 2
	28	[177]	SETTABLE 	3 -2 4	; "name" -
	29	[177]	SETTABLE 	3 -4 -13	; "is_module_path" false
	30	[177]	SETTABLE 	3 -6 -10	; "perms" "exec"
	31	[177]	SETTABLE 	2 -11 3	; "bin" -
	32	[178]	NEWTABLE 	3 0 3
	33	[178]	GETUPVAL 	4 0	; path
	34	[178]	GETTABLE 	4 4 -15	; "conf_dir"
	35	[178]	MOVE     	5 0
	36	[178]	MOVE     	6 1
	37	[178]	CALL     	4 3 2
	38	[178]	SETTABLE 	3 -2 4	; "name" -
	39	[178]	SETTABLE 	3 -4 -13	; "is_module_path" false
	40	[178]	SETTABLE 	3 -6 -7	; "perms" "read"
	41	[178]	SETTABLE 	2 -14 3	; "conf" -
	42	[181]	GETGLOBAL	3 -16	; pairs
	43	[181]	MOVE     	4 2
	44	[181]	CALL     	3 2 4
	45	[181]	JMP      	9	; to 55
	46	[182]	GETUPVAL 	8 1	; fs
	47	[182]	GETTABLE 	8 8 -17	; "make_dir"
	48	[182]	GETTABLE 	9 7 -2	; "name"
	49	[182]	CALL     	8 2 3
	50	[183]	TEST     	8 0 1
	51	[183]	JMP      	3	; to 55
	52	[184]	LOADNIL  	10 10
	53	[184]	MOVE     	11 9
	54	[184]	RETURN   	10 3
	55	[181]	TFORLOOP 	3 2
	56	[185]	JMP      	-11	; to 46
	57	[188]	RETURN   	2 2
	58	[189]	RETURN   	0 1

function <./build.lua:191,214> (66 instructions, 264 bytes at 0x7fd56c406600)
1 param, 9 slots, 3 upvalues, 6 locals, 19 constants, 0 functions
	1	[192]	GETTABLE 	1 0 -1	; "build"
	2	[192]	GETTABLE 	1 1 -2	; "type"
	3	[193]	EQ       	0 1 -3	; - "none"
	4	[193]	JMP      	2	; to 7
	5	[194]	LOADBOOL 	2 1 0
	6	[194]	RETURN   	2 2
	7	[197]	EQ       	0 1 -4	; - "module"
	8	[197]	JMP      	7	; to 16
	9	[198]	GETUPVAL 	2 0	; util
	10	[198]	GETTABLE 	2 2 -5	; "printout"
	11	[198]	LOADK    	3 -6	; "Do not use 'module' as a build type. Use 'builtin' instead."
	12	[198]	CALL     	2 2 1
	13	[199]	LOADK    	1 -7	; "builtin"
	14	[200]	GETTABLE 	2 0 -1	; "build"
	15	[200]	SETTABLE 	2 -2 1	; "type" -
	16	[202]	GETUPVAL 	2 1	; cfg
	17	[202]	GETTABLE 	2 2 -8	; "accepted_build_types"
	18	[202]	TEST     	2 0 0
	19	[202]	JMP      	14	; to 34
	20	[202]	GETUPVAL 	2 2	; fun
	21	[202]	GETTABLE 	2 2 -9	; "contains"
	22	[202]	GETUPVAL 	3 1	; cfg
	23	[202]	GETTABLE 	3 3 -8	; "accepted_build_types"
	24	[202]	MOVE     	4 1
	25	[202]	CALL     	2 3 2
	26	[202]	TEST     	2 0 1
	27	[202]	JMP      	6	; to 34
	28	[203]	LOADNIL  	2 2
	29	[203]	LOADK    	3 -10	; "This rockspec uses the '"
	30	[203]	MOVE     	4 1
	31	[203]	LOADK    	5 -11	; "' build type, which is blocked by the 'accepted_build_types' setting in your LuaRocks configuration."
	32	[203]	CONCAT   	3 3 5
	33	[203]	RETURN   	2 3
	34	[205]	GETGLOBAL	2 -12	; pcall
	35	[205]	GETGLOBAL	3 -13	; require
	36	[205]	LOADK    	4 -14	; "luarocks.build."
	37	[205]	MOVE     	5 1
	38	[205]	CONCAT   	4 4 5
	39	[205]	CALL     	2 3 3
	40	[206]	TEST     	2 0 0
	41	[206]	JMP      	5	; to 47
	42	[206]	GETGLOBAL	4 -2	; type
	43	[206]	MOVE     	5 3
	44	[206]	CALL     	4 2 2
	45	[206]	EQ       	1 4 -15	; - "table"
	46	[206]	JMP      	7	; to 54
	47	[207]	LOADNIL  	4 4
	48	[207]	LOADK    	5 -16	; "Failed initializing build back-end for build type '"
	49	[207]	MOVE     	6 1
	50	[207]	LOADK    	7 -17	; "': "
	51	[207]	MOVE     	8 3
	52	[207]	CONCAT   	5 5 8
	53	[207]	RETURN   	4 3
	54	[209]	GETTABLE 	4 3 -18	; "run"
	55	[209]	MOVE     	5 0
	56	[209]	CALL     	4 2 3
	57	[210]	TEST     	4 0 1
	58	[210]	JMP      	5	; to 64
	59	[211]	LOADNIL  	6 6
	60	[211]	LOADK    	7 -19	; "Build error: "
	61	[211]	MOVE     	8 5
	62	[211]	CONCAT   	7 7 8
	63	[211]	RETURN   	6 3
	64	[213]	LOADBOOL 	6 1 0
	65	[213]	RETURN   	6 2
	66	[214]	RETURN   	0 1

function <./build.lua:235,270> (129 instructions, 516 bytes at 0x7fd56c40b650)
4 params, 17 slots, 3 upvalues, 20 locals, 16 constants, 0 functions
	1	[236]	GETGLOBAL	4 -1	; assert
	2	[236]	GETGLOBAL	5 -2	; type
	3	[236]	MOVE     	6 0
	4	[236]	CALL     	5 2 2
	5	[236]	EQ       	1 5 -3	; - "table"
	6	[236]	JMP      	3	; to 10
	7	[236]	NOT      	5 0
	8	[236]	JMP      	2	; to 11
	9	[236]	LOADBOOL 	5 0 1
	10	[236]	LOADBOOL 	5 1 0
	11	[236]	CALL     	4 2 1
	12	[237]	GETGLOBAL	4 -1	; assert
	13	[237]	GETGLOBAL	5 -2	; type
	14	[237]	MOVE     	6 1
	15	[237]	CALL     	5 2 2
	16	[237]	EQ       	1 5 -4	; - "string"
	17	[237]	JMP      	1	; to 19
	18	[237]	LOADBOOL 	5 0 1
	19	[237]	LOADBOOL 	5 1 0
	20	[237]	CALL     	4 2 1
	21	[238]	TEST     	0 0 1
	22	[238]	JMP      	2	; to 25
	23	[239]	LOADBOOL 	4 1 0
	24	[239]	RETURN   	4 2
	25	[241]	GETGLOBAL	4 -5	; pairs
	26	[241]	MOVE     	5 0
	27	[241]	CALL     	4 2 4
	28	[241]	JMP      	96	; to 125
	29	[242]	MOVE     	9 1
	30	[243]	GETUPVAL 	10 0	; dir
	31	[243]	GETTABLE 	10 10 -6	; "base_name"
	32	[243]	MOVE     	11 8
	33	[243]	CALL     	10 2 2
	34	[244]	GETGLOBAL	11 -2	; type
	35	[244]	MOVE     	12 7
	36	[244]	CALL     	11 2 2
	37	[244]	EQ       	0 11 -4	; - "string"
	38	[244]	JMP      	57	; to 96
	39	[245]	MOVE     	11 7
	40	[246]	TEST     	2 0 0
	41	[246]	JMP      	30	; to 72
	42	[247]	GETUPVAL 	12 0	; dir
	43	[247]	GETTABLE 	12 12 -7	; "path"
	44	[247]	MOVE     	13 1
	45	[247]	GETUPVAL 	14 1	; path
	46	[247]	GETTABLE 	14 14 -8	; "module_to_path"
	47	[247]	MOVE     	15 11
	48	[247]	CALL     	14 2 0
	49	[247]	CALL     	12 0 2
	50	[247]	MOVE     	9 12
	51	[248]	GETUPVAL 	12 2	; fs
	52	[248]	GETTABLE 	12 12 -9	; "make_dir"
	53	[248]	MOVE     	13 9
	54	[248]	CALL     	12 2 3
	55	[249]	TEST     	12 0 1
	56	[249]	JMP      	3	; to 60
	57	[249]	LOADNIL  	14 14
	58	[249]	MOVE     	15 13
	59	[249]	RETURN   	14 3
	60	[250]	SELF     	14 10 -10	; "match"
	61	[250]	LOADK    	16 -11	; "%.lua$"
	62	[250]	CALL     	14 3 2
	63	[250]	TEST     	14 0 0
	64	[250]	JMP      	40	; to 105
	65	[251]	SELF     	14 11 -10	; "match"
	66	[251]	LOADK    	16 -12	; "([^.]+)$"
	67	[251]	CALL     	14 3 2
	68	[252]	MOVE     	15 14
	69	[252]	LOADK    	16 -13	; ".lua"
	70	[252]	CONCAT   	10 15 16
	71	[253]	JMP      	33	; to 105
	72	[255]	GETUPVAL 	12 0	; dir
	73	[255]	GETTABLE 	12 12 -7	; "path"
	74	[255]	MOVE     	13 1
	75	[255]	GETUPVAL 	14 0	; dir
	76	[255]	GETTABLE 	14 14 -14	; "dir_name"
	77	[255]	MOVE     	15 11
	78	[255]	CALL     	14 2 0
	79	[255]	CALL     	12 0 2
	80	[255]	MOVE     	9 12
	81	[256]	GETUPVAL 	12 2	; fs
	82	[256]	GETTABLE 	12 12 -9	; "make_dir"
	83	[256]	MOVE     	13 9
	84	[256]	CALL     	12 2 3
	85	[257]	TEST     	12 0 1
	86	[257]	JMP      	3	; to 90
	87	[257]	LOADNIL  	14 14
	88	[257]	MOVE     	15 13
	89	[257]	RETURN   	14 3
	90	[258]	GETUPVAL 	14 0	; dir
	91	[258]	GETTABLE 	14 14 -6	; "base_name"
	92	[258]	MOVE     	15 11
	93	[258]	CALL     	14 2 2
	94	[258]	MOVE     	10 14
	95	[259]	JMP      	9	; to 105
	96	[261]	GETUPVAL 	11 2	; fs
	97	[261]	GETTABLE 	11 11 -9	; "make_dir"
	98	[261]	MOVE     	12 9
	99	[261]	CALL     	11 2 3
	100	[262]	TEST     	11 0 1
	101	[262]	JMP      	3	; to 105
	102	[262]	LOADNIL  	13 13
	103	[262]	MOVE     	14 12
	104	[262]	RETURN   	13 3
	105	[264]	GETUPVAL 	11 2	; fs
	106	[264]	GETTABLE 	11 11 -15	; "copy"
	107	[264]	GETUPVAL 	12 0	; dir
	108	[264]	GETTABLE 	12 12 -7	; "path"
	109	[264]	MOVE     	13 8
	110	[264]	CALL     	12 2 2
	111	[264]	GETUPVAL 	13 0	; dir
	112	[264]	GETTABLE 	13 13 -7	; "path"
	113	[264]	MOVE     	14 9
	114	[264]	MOVE     	15 10
	115	[264]	CALL     	13 3 2
	116	[264]	MOVE     	14 3
	117	[264]	CALL     	11 4 2
	118	[265]	TEST     	11 0 1
	119	[265]	JMP      	5	; to 125
	120	[266]	LOADNIL  	12 12
	121	[266]	LOADK    	13 -16	; "Failed copying "
	122	[266]	MOVE     	14 8
	123	[266]	CONCAT   	13 13 14
	124	[266]	RETURN   	12 3
	125	[241]	TFORLOOP 	4 2
	126	[267]	JMP      	-98	; to 29
	127	[269]	LOADBOOL 	4 1 0
	128	[269]	RETURN   	4 2
	129	[270]	RETURN   	0 1

function <./build.lua:272,288> (52 instructions, 208 bytes at 0x7fd56c40b700)
2 params, 18 slots, 3 upvalues, 14 locals, 15 constants, 0 functions
	1	[273]	NEWTABLE 	2 4 0
	2	[273]	LOADK    	3 -1	; "readme"
	3	[273]	LOADK    	4 -2	; "license"
	4	[273]	LOADK    	5 -3	; "copying"
	5	[273]	LOADK    	6 -4	; ".*%.md"
	6	[273]	SETLIST  	2 4 1	; 1
	7	[274]	GETUPVAL 	3 0	; dir
	8	[274]	GETTABLE 	3 3 -5	; "path"
	9	[274]	GETUPVAL 	4 1	; path
	10	[274]	GETTABLE 	4 4 -6	; "install_dir"
	11	[274]	MOVE     	5 0
	12	[274]	MOVE     	6 1
	13	[274]	CALL     	4 3 2
	14	[274]	LOADK    	5 -7	; "doc"
	15	[274]	CALL     	3 3 2
	16	[275]	LOADBOOL 	4 0 0
	17	[276]	GETUPVAL 	5 2	; fs
	18	[276]	GETTABLE 	5 5 -8	; "dir"
	19	[276]	CALL     	5 1 4
	20	[276]	JMP      	29	; to 50
	21	[277]	GETGLOBAL	9 -9	; ipairs
	22	[277]	MOVE     	10 2
	23	[277]	CALL     	9 2 4
	24	[277]	JMP      	23	; to 48
	25	[278]	SELF     	14 8 -10	; "lower"
	26	[278]	CALL     	14 2 2
	27	[278]	SELF     	14 14 -11	; "match"
	28	[278]	LOADK    	16 -12	; "^"
	29	[278]	MOVE     	17 13
	30	[278]	CONCAT   	16 16 17
	31	[278]	CALL     	14 3 2
	32	[278]	TEST     	14 0 0
	33	[278]	JMP      	14	; to 48
	34	[279]	TEST     	4 0 1
	35	[279]	JMP      	5	; to 41
	36	[280]	GETUPVAL 	14 2	; fs
	37	[280]	GETTABLE 	14 14 -13	; "make_dir"
	38	[280]	MOVE     	15 3
	39	[280]	CALL     	14 2 1
	40	[281]	LOADBOOL 	4 1 0
	41	[283]	GETUPVAL 	14 2	; fs
	42	[283]	GETTABLE 	14 14 -14	; "copy"
	43	[283]	MOVE     	15 8
	44	[283]	MOVE     	16 3
	45	[283]	LOADK    	17 -15	; "read"
	46	[283]	CALL     	14 4 1
	47	[284]	JMP      	2	; to 50
	48	[277]	TFORLOOP 	9 2
	49	[285]	JMP      	-25	; to 25
	50	[276]	TFORLOOP 	5 1
	51	[286]	JMP      	-31	; to 21
	52	[288]	RETURN   	0 1

function <./build.lua:290,325> (85 instructions, 340 bytes at 0x7fd56c40c040)
2 params, 16 slots, 5 upvalues, 20 locals, 16 constants, 0 functions
	1	[291]	GETTABLE 	2 0 -1	; "name"
	2	[291]	GETTABLE 	3 0 -2	; "version"
	3	[293]	GETTABLE 	4 0 -3	; "build"
	4	[293]	GETTABLE 	4 4 -4	; "install"
	5	[293]	TEST     	4 0 0
	6	[293]	JMP      	19	; to 26
	7	[294]	GETGLOBAL	4 -5	; pairs
	8	[294]	MOVE     	5 1
	9	[294]	CALL     	4 2 4
	10	[294]	JMP      	13	; to 24
	11	[295]	GETUPVAL 	9 0	; install_to
	12	[295]	GETTABLE 	10 0 -3	; "build"
	13	[295]	GETTABLE 	10 10 -4	; "install"
	14	[295]	GETTABLE 	10 10 7
	15	[295]	GETTABLE 	11 8 -1	; "name"
	16	[295]	GETTABLE 	12 8 -6	; "is_module_path"
	17	[295]	GETTABLE 	13 8 -7	; "perms"
	18	[295]	CALL     	9 5 3
	19	[296]	TEST     	9 0 1
	20	[296]	JMP      	3	; to 24
	21	[296]	LOADNIL  	11 11
	22	[296]	MOVE     	12 10
	23	[296]	RETURN   	11 3
	24	[294]	TFORLOOP 	4 2
	25	[296]	JMP      	-15	; to 11
	26	[300]	GETTABLE 	4 0 -3	; "build"
	27	[300]	GETTABLE 	4 4 -8	; "copy_directories"
	28	[301]	LOADBOOL 	5 0 0
	29	[302]	TEST     	4 0 1
	30	[302]	JMP      	5	; to 36
	31	[303]	NEWTABLE 	6 1 0
	32	[303]	LOADK    	7 -9	; "doc"
	33	[303]	SETLIST  	6 1 1	; 1
	34	[303]	MOVE     	4 6
	35	[304]	LOADBOOL 	5 1 0
	36	[307]	LOADBOOL 	6 0 0
	37	[308]	GETGLOBAL	7 -5	; pairs
	38	[308]	MOVE     	8 4
	39	[308]	CALL     	7 2 4
	40	[308]	JMP      	34	; to 75
	41	[309]	GETUPVAL 	12 1	; fs
	42	[309]	GETTABLE 	12 12 -10	; "is_dir"
	43	[309]	MOVE     	13 11
	44	[309]	CALL     	12 2 2
	45	[309]	TEST     	12 0 0
	46	[309]	JMP      	20	; to 67
	47	[310]	GETUPVAL 	12 2	; dir
	48	[310]	GETTABLE 	12 12 -11	; "path"
	49	[310]	GETUPVAL 	13 3	; path
	50	[310]	GETTABLE 	13 13 -12	; "install_dir"
	51	[310]	MOVE     	14 2
	52	[310]	MOVE     	15 3
	53	[310]	CALL     	13 3 2
	54	[310]	MOVE     	14 11
	55	[310]	CALL     	12 3 2
	56	[311]	GETUPVAL 	13 1	; fs
	57	[311]	GETTABLE 	13 13 -13	; "make_dir"
	58	[311]	MOVE     	14 12
	59	[311]	CALL     	13 2 1
	60	[312]	GETUPVAL 	13 1	; fs
	61	[312]	GETTABLE 	13 13 -14	; "copy_contents"
	62	[312]	MOVE     	14 11
	63	[312]	MOVE     	15 12
	64	[312]	CALL     	13 3 1
	65	[313]	LOADBOOL 	6 1 0
	66	[313]	JMP      	8	; to 75
	67	[315]	TEST     	5 0 1
	68	[315]	JMP      	6	; to 75
	69	[316]	LOADNIL  	12 12
	70	[316]	LOADK    	13 -15	; "Directory '"
	71	[316]	MOVE     	14 11
	72	[316]	LOADK    	15 -16	; "' not found"
	73	[316]	CONCAT   	13 13 15
	74	[316]	RETURN   	12 3
	75	[308]	TFORLOOP 	7 2
	76	[318]	JMP      	-36	; to 41
	77	[320]	TEST     	6 0 1
	78	[320]	JMP      	4	; to 83
	79	[321]	GETUPVAL 	7 4	; install_default_docs
	80	[321]	MOVE     	8 2
	81	[321]	MOVE     	9 3
	82	[321]	CALL     	7 3 1
	83	[324]	LOADBOOL 	7 1 0
	84	[324]	RETURN   	7 2
	85	[325]	RETURN   	0 1

function <./build.lua:328,345> (58 instructions, 232 bytes at 0x7fd56c40c630)
2 params, 11 slots, 5 upvalues, 7 locals, 13 constants, 0 functions
	1	[329]	GETTABLE 	2 0 -1	; "name"
	2	[329]	GETTABLE 	3 0 -2	; "version"
	3	[331]	GETUPVAL 	4 0	; fs
	4	[331]	GETTABLE 	4 4 -3	; "copy"
	5	[331]	GETTABLE 	5 0 -4	; "local_abs_filename"
	6	[331]	GETUPVAL 	6 1	; path
	7	[331]	GETTABLE 	6 6 -5	; "rockspec_file"
	8	[331]	MOVE     	7 2
	9	[331]	MOVE     	8 3
	10	[331]	CALL     	6 3 2
	11	[331]	LOADK    	7 -6	; "read"
	12	[331]	CALL     	4 4 1
	13	[333]	GETUPVAL 	4 2	; deplocks
	14	[333]	GETTABLE 	4 4 -7	; "get_abs_filename"
	15	[333]	GETTABLE 	5 0 -1	; "name"
	16	[333]	CALL     	4 2 2
	17	[334]	TEST     	4 0 0
	18	[334]	JMP      	14	; to 33
	19	[335]	GETUPVAL 	5 0	; fs
	20	[335]	GETTABLE 	5 5 -3	; "copy"
	21	[335]	MOVE     	6 4
	22	[335]	GETUPVAL 	7 3	; dir
	23	[335]	GETTABLE 	7 7 -8	; "path"
	24	[335]	GETUPVAL 	8 1	; path
	25	[335]	GETTABLE 	8 8 -9	; "install_dir"
	26	[335]	MOVE     	9 2
	27	[335]	MOVE     	10 3
	28	[335]	CALL     	8 3 2
	29	[335]	LOADK    	9 -10	; "luarocks.lock"
	30	[335]	CALL     	7 3 2
	31	[335]	LOADK    	8 -6	; "read"
	32	[335]	CALL     	5 4 1
	33	[338]	GETUPVAL 	5 4	; writer
	34	[338]	GETTABLE 	5 5 -11	; "make_rock_manifest"
	35	[338]	MOVE     	6 2
	36	[338]	MOVE     	7 3
	37	[338]	CALL     	5 3 3
	38	[339]	TEST     	5 0 1
	39	[339]	JMP      	3	; to 43
	40	[339]	LOADNIL  	7 7
	41	[339]	MOVE     	8 6
	42	[339]	RETURN   	7 3
	43	[341]	GETUPVAL 	7 4	; writer
	44	[341]	GETTABLE 	7 7 -12	; "make_namespace_file"
	45	[341]	MOVE     	8 2
	46	[341]	MOVE     	9 3
	47	[341]	GETTABLE 	10 1 -13	; "namespace"
	48	[341]	CALL     	7 4 3
	49	[341]	MOVE     	6 8
	50	[341]	MOVE     	5 7
	51	[342]	TEST     	5 0 1
	52	[342]	JMP      	3	; to 56
	53	[342]	LOADNIL  	7 7
	54	[342]	MOVE     	8 6
	55	[342]	RETURN   	7 3
	56	[344]	LOADBOOL 	7 1 0
	57	[344]	RETURN   	7 2
	58	[345]	RETURN   	0 1

function <./build.lua:351,441> (244 instructions, 976 bytes at 0x7fd56c40c860)
2 params, 16 slots, 13 upvalues, 14 locals, 32 constants, 2 functions
	1	[352]	GETGLOBAL	2 -1	; assert
	2	[352]	SELF     	3 0 -2	; "type"
	3	[352]	CALL     	3 2 2
	4	[352]	EQ       	1 3 -3	; - "rockspec"
	5	[352]	JMP      	1	; to 7
	6	[352]	LOADBOOL 	3 0 1
	7	[352]	LOADBOOL 	3 1 0
	8	[352]	CALL     	2 2 1
	9	[353]	GETGLOBAL	2 -1	; assert
	10	[353]	SELF     	3 1 -2	; "type"
	11	[353]	CALL     	3 2 2
	12	[353]	EQ       	1 3 -4	; - "build.opts"
	13	[353]	JMP      	1	; to 15
	14	[353]	LOADBOOL 	3 0 1
	15	[353]	LOADBOOL 	3 1 0
	16	[353]	CALL     	2 2 1
	17	[355]	GETTABLE 	2 0 -5	; "build"
	18	[355]	TEST     	2 0 1
	19	[355]	JMP      	12	; to 32
	20	[356]	SELF     	2 0 -6	; "format_is_at_least"
	21	[356]	LOADK    	4 -7	; "3.0"
	22	[356]	CALL     	2 3 2
	23	[356]	TEST     	2 0 0
	24	[356]	JMP      	4	; to 29
	25	[357]	NEWTABLE 	2 0 1
	26	[358]	SETTABLE 	2 -2 -8	; "type" "builtin"
	27	[359]	SETTABLE 	0 -5 2	; "build" -
	28	[359]	JMP      	3	; to 32
	29	[361]	LOADNIL  	2 2
	30	[361]	LOADK    	3 -9	; "Rockspec error: build table not specified"
	31	[361]	RETURN   	2 3
	32	[365]	GETTABLE 	2 0 -5	; "build"
	33	[365]	GETTABLE 	2 2 -2	; "type"
	34	[365]	TEST     	2 0 1
	35	[365]	JMP      	11	; to 47
	36	[366]	SELF     	2 0 -6	; "format_is_at_least"
	37	[366]	LOADK    	4 -7	; "3.0"
	38	[366]	CALL     	2 3 2
	39	[366]	TEST     	2 0 0
	40	[366]	JMP      	3	; to 44
	41	[367]	GETTABLE 	2 0 -5	; "build"
	42	[367]	SETTABLE 	2 -2 -8	; "type" "builtin"
	43	[367]	JMP      	3	; to 47
	44	[369]	LOADNIL  	2 2
	45	[369]	LOADK    	3 -10	; "Rockspec error: build type not specified"
	46	[369]	RETURN   	2 3
	47	[373]	GETUPVAL 	2 0	; fetch_and_change_to_source_dir
	48	[373]	MOVE     	3 0
	49	[373]	MOVE     	4 1
	50	[373]	CALL     	2 3 3
	51	[374]	TEST     	2 0 1
	52	[374]	JMP      	3	; to 56
	53	[374]	LOADNIL  	4 4
	54	[374]	MOVE     	5 3
	55	[374]	RETURN   	4 3
	56	[376]	GETTABLE 	4 1 -11	; "pin"
	57	[376]	TEST     	4 0 0
	58	[376]	JMP      	5	; to 64
	59	[377]	GETUPVAL 	4 1	; deplocks
	60	[377]	GETTABLE 	4 4 -12	; "init"
	61	[377]	GETTABLE 	5 0 -13	; "name"
	62	[377]	LOADK    	6 -14	; "."
	63	[377]	CALL     	4 3 1
	64	[380]	GETUPVAL 	4 2	; process_dependencies
	65	[380]	MOVE     	5 0
	66	[380]	MOVE     	6 1
	67	[380]	CALL     	4 3 3
	68	[380]	MOVE     	3 5
	69	[380]	MOVE     	2 4
	70	[381]	TEST     	2 0 1
	71	[381]	JMP      	3	; to 75
	72	[381]	LOADNIL  	4 4
	73	[381]	MOVE     	5 3
	74	[381]	RETURN   	4 3
	75	[383]	GETTABLE 	4 0 -13	; "name"
	76	[383]	GETTABLE 	5 0 -15	; "version"
	77	[384]	GETTABLE 	6 1 -16	; "build_only_deps"
	78	[384]	TEST     	6 0 0
	79	[384]	JMP      	3	; to 83
	80	[385]	MOVE     	6 4
	81	[385]	MOVE     	7 5
	82	[385]	RETURN   	6 3
	83	[388]	GETUPVAL 	6 3	; repos
	84	[388]	GETTABLE 	6 6 -17	; "is_installed"
	85	[388]	MOVE     	7 4
	86	[388]	MOVE     	8 5
	87	[388]	CALL     	6 3 2
	88	[388]	TEST     	6 0 0
	89	[388]	JMP      	6	; to 96
	90	[389]	GETUPVAL 	6 3	; repos
	91	[389]	GETTABLE 	6 6 -18	; "delete_version"
	92	[389]	MOVE     	7 4
	93	[389]	MOVE     	8 5
	94	[389]	GETTABLE 	9 1 -19	; "deps_mode"
	95	[389]	CALL     	6 4 1
	96	[391]	GETUPVAL 	6 4	; prepare_install_dirs
	97	[391]	MOVE     	7 4
	98	[391]	MOVE     	8 5
	99	[391]	CALL     	6 3 3
	100	[392]	TEST     	6 0 1
	101	[392]	JMP      	3	; to 105
	102	[392]	LOADNIL  	8 8
	103	[392]	MOVE     	9 7
	104	[392]	RETURN   	8 3
	105	[394]	GETUPVAL 	8 5	; util
	106	[394]	GETTABLE 	8 8 -20	; "schedule_function"
	107	[397]	CLOSURE  	9 0	; 0x7fd56c40d6b0
	108	[397]	GETUPVAL 	0 6	; fs
	109	[397]	GETUPVAL 	0 7	; path
	110	[397]	MOVE     	0 4
	111	[397]	MOVE     	0 5
	112	[394]	CALL     	8 2 2
	113	[399]	GETUPVAL 	9 8	; build
	114	[399]	GETTABLE 	9 9 -21	; "apply_patches"
	115	[399]	MOVE     	10 0
	116	[399]	CALL     	9 2 3
	117	[399]	MOVE     	7 10
	118	[399]	MOVE     	2 9
	119	[400]	TEST     	2 0 1
	120	[400]	JMP      	3	; to 124
	121	[400]	LOADNIL  	9 9
	122	[400]	MOVE     	10 7
	123	[400]	RETURN   	9 3
	124	[402]	GETUPVAL 	9 9	; check_macosx_deployment_target
	125	[402]	MOVE     	10 0
	126	[402]	CALL     	9 2 3
	127	[402]	MOVE     	7 10
	128	[402]	MOVE     	2 9
	129	[403]	TEST     	2 0 1
	130	[403]	JMP      	3	; to 134
	131	[403]	LOADNIL  	9 9
	132	[403]	MOVE     	10 7
	133	[403]	RETURN   	9 3
	134	[405]	GETUPVAL 	9 10	; run_build_driver
	135	[405]	MOVE     	10 0
	136	[405]	CALL     	9 2 3
	137	[405]	MOVE     	7 10
	138	[405]	MOVE     	2 9
	139	[406]	TEST     	2 0 1
	140	[406]	JMP      	3	; to 144
	141	[406]	LOADNIL  	9 9
	142	[406]	MOVE     	10 7
	143	[406]	RETURN   	9 3
	144	[408]	GETUPVAL 	9 11	; install_files
	145	[408]	MOVE     	10 0
	146	[408]	MOVE     	11 6
	147	[408]	CALL     	9 3 3
	148	[408]	MOVE     	7 10
	149	[408]	MOVE     	2 9
	150	[409]	TEST     	2 0 1
	151	[409]	JMP      	3	; to 155
	152	[409]	LOADNIL  	9 9
	153	[409]	MOVE     	10 7
	154	[409]	RETURN   	9 3
	155	[411]	GETGLOBAL	9 -22	; pairs
	156	[411]	MOVE     	10 6
	157	[411]	CALL     	9 2 4
	158	[411]	JMP      	4	; to 163
	159	[412]	GETUPVAL 	14 6	; fs
	160	[412]	GETTABLE 	14 14 -23	; "remove_dir_if_empty"
	161	[412]	GETTABLE 	15 13 -13	; "name"
	162	[412]	CALL     	14 2 1
	163	[411]	TFORLOOP 	9 2
	164	[412]	JMP      	-6	; to 159
	165	[415]	GETUPVAL 	9 6	; fs
	166	[415]	GETTABLE 	9 9 -24	; "pop_dir"
	167	[415]	CALL     	9 1 1
	168	[416]	GETTABLE 	9 1 -25	; "need_to_fetch"
	169	[416]	TEST     	9 0 0
	170	[416]	JMP      	3	; to 174
	171	[417]	GETUPVAL 	9 6	; fs
	172	[417]	GETTABLE 	9 9 -24	; "pop_dir"
	173	[417]	CALL     	9 1 1
	174	[420]	GETTABLE 	9 1 -11	; "pin"
	175	[420]	TEST     	9 0 0
	176	[420]	JMP      	3	; to 180
	177	[421]	GETUPVAL 	9 1	; deplocks
	178	[421]	GETTABLE 	9 9 -26	; "write_file"
	179	[421]	CALL     	9 1 1
	180	[424]	GETUPVAL 	9 12	; write_rock_dir_files
	181	[424]	MOVE     	10 0
	182	[424]	MOVE     	11 1
	183	[424]	CALL     	9 3 3
	184	[424]	MOVE     	7 10
	185	[424]	MOVE     	2 9
	186	[425]	TEST     	2 0 1
	187	[425]	JMP      	3	; to 191
	188	[425]	LOADNIL  	9 9
	189	[425]	MOVE     	10 7
	190	[425]	RETURN   	9 3
	191	[427]	GETUPVAL 	9 3	; repos
	192	[427]	GETTABLE 	9 9 -27	; "deploy_files"
	193	[427]	MOVE     	10 4
	194	[427]	MOVE     	11 5
	195	[427]	GETUPVAL 	12 3	; repos
	196	[427]	GETTABLE 	12 12 -28	; "should_wrap_bin_scripts"
	197	[427]	MOVE     	13 0
	198	[427]	CALL     	12 2 2
	199	[427]	GETTABLE 	13 1 -19	; "deps_mode"
	200	[427]	CALL     	9 5 3
	201	[427]	MOVE     	7 10
	202	[427]	MOVE     	2 9
	203	[428]	TEST     	2 0 1
	204	[428]	JMP      	3	; to 208
	205	[428]	LOADNIL  	9 9
	206	[428]	MOVE     	10 7
	207	[428]	RETURN   	9 3
	208	[430]	GETUPVAL 	9 5	; util
	209	[430]	GETTABLE 	9 9 -29	; "remove_scheduled_function"
	210	[430]	MOVE     	10 8
	211	[430]	CALL     	9 2 1
	212	[431]	GETUPVAL 	9 5	; util
	213	[431]	GETTABLE 	9 9 -20	; "schedule_function"
	214	[433]	CLOSURE  	10 1	; 0x7fd56c40e050
	215	[433]	GETUPVAL 	0 3	; repos
	216	[433]	MOVE     	0 4
	217	[433]	MOVE     	0 5
	218	[433]	MOVE     	0 1
	219	[431]	CALL     	9 2 2
	220	[433]	MOVE     	8 9
	221	[435]	GETUPVAL 	9 3	; repos
	222	[435]	GETTABLE 	9 9 -30	; "run_hook"
	223	[435]	MOVE     	10 0
	224	[435]	LOADK    	11 -31	; "post_install"
	225	[435]	CALL     	9 3 3
	226	[435]	MOVE     	7 10
	227	[435]	MOVE     	2 9
	228	[436]	TEST     	2 0 1
	229	[436]	JMP      	3	; to 233
	230	[436]	LOADNIL  	9 9
	231	[436]	MOVE     	10 7
	232	[436]	RETURN   	9 3
	233	[438]	GETUPVAL 	9 5	; util
	234	[438]	GETTABLE 	9 9 -32	; "announce_install"
	235	[438]	MOVE     	10 0
	236	[438]	CALL     	9 2 1
	237	[439]	GETUPVAL 	9 5	; util
	238	[439]	GETTABLE 	9 9 -29	; "remove_scheduled_function"
	239	[439]	MOVE     	10 8
	240	[439]	CALL     	9 2 1
	241	[440]	MOVE     	9 4
	242	[440]	MOVE     	10 5
	243	[440]	RETURN   	9 3
	244	[441]	RETURN   	0 1

function <./build.lua:394,397> (16 instructions, 64 bytes at 0x7fd56c40d6b0)
0 params, 4 slots, 4 upvalues, 0 locals, 4 constants, 0 functions
	1	[395]	GETUPVAL 	0 0	; fs
	2	[395]	GETTABLE 	0 0 -1	; "delete"
	3	[395]	GETUPVAL 	1 1	; path
	4	[395]	GETTABLE 	1 1 -2	; "install_dir"
	5	[395]	GETUPVAL 	2 2	; name
	6	[395]	GETUPVAL 	3 3	; version
	7	[395]	CALL     	1 3 0
	8	[395]	CALL     	0 0 1
	9	[396]	GETUPVAL 	0 0	; fs
	10	[396]	GETTABLE 	0 0 -3	; "remove_dir_if_empty"
	11	[396]	GETUPVAL 	1 1	; path
	12	[396]	GETTABLE 	1 1 -4	; "versions_dir"
	13	[396]	GETUPVAL 	2 2	; name
	14	[396]	CALL     	1 2 0
	15	[396]	CALL     	0 0 1
	16	[397]	RETURN   	0 1

function <./build.lua:431,433> (8 instructions, 32 bytes at 0x7fd56c40e050)
0 params, 4 slots, 4 upvalues, 0 locals, 2 constants, 0 functions
	1	[432]	GETUPVAL 	0 0	; repos
	2	[432]	GETTABLE 	0 0 -1	; "delete_version"
	3	[432]	GETUPVAL 	1 1	; name
	4	[432]	GETUPVAL 	2 2	; version
	5	[432]	GETUPVAL 	3 3	; opts
	6	[432]	GETTABLE 	3 3 -2	; "deps_mode"
	7	[432]	CALL     	0 4 1
	8	[433]	RETURN   	0 1
