
main <./build/builtin.lua:0,0> (56 instructions, 224 bytes at 0x7fd65bc068a0)
0+ params, 11 slots, 0 upvalues, 11 locals, 17 constants, 6 functions
	1	[3]	NEWTABLE 	0 0 0
	2	[5]	GETGLOBAL	1 -1	; unpack
	3	[5]	TEST     	1 0 1
	4	[5]	JMP      	2	; to 7
	5	[5]	GETGLOBAL	1 -2	; table
	6	[5]	GETTABLE 	1 1 -1	; "unpack"
	7	[7]	GETGLOBAL	2 -3	; require
	8	[7]	LOADK    	3 -4	; "luarocks.fs"
	9	[7]	CALL     	2 2 2
	10	[8]	GETGLOBAL	3 -3	; require
	11	[8]	LOADK    	4 -5	; "luarocks.path"
	12	[8]	CALL     	3 2 2
	13	[9]	GETGLOBAL	4 -3	; require
	14	[9]	LOADK    	5 -6	; "luarocks.util"
	15	[9]	CALL     	4 2 2
	16	[10]	GETGLOBAL	5 -3	; require
	17	[10]	LOADK    	6 -7	; "luarocks.core.cfg"
	18	[10]	CALL     	5 2 2
	19	[11]	GETGLOBAL	6 -3	; require
	20	[11]	LOADK    	7 -8	; "luarocks.dir"
	21	[11]	CALL     	6 2 2
	22	[43]	CLOSURE  	7 0	; 0x7fd65bc06b20
	23	[13]	SETTABLE 	0 -9 7	; "autodetect_external_dependencies" -
	24	[60]	CLOSURE  	7 1	; 0x7fd65bc07110
	25	[69]	CLOSURE  	8 2	; 0x7fd65bc06ba0
	26	[69]	MOVE     	0 6
	27	[69]	MOVE     	0 2
	28	[71]	NEWTABLE 	9 0 5
	29	[72]	SETTABLE 	9 -10 -11	; "spec" true
	30	[73]	SETTABLE 	9 -12 -11	; ".luarocks" true
	31	[74]	SETTABLE 	9 -13 -11	; "lua_modules" true
	32	[75]	SETTABLE 	9 -14 -11	; "test.lua" true
	33	[76]	SETTABLE 	9 -15 -11	; "tests.lua" true
	34	[137]	CLOSURE  	10 3	; 0x7fd65bc07020
	35	[137]	MOVE     	0 2
	36	[137]	MOVE     	0 9
	37	[137]	MOVE     	0 3
	38	[137]	MOVE     	0 8
	39	[137]	MOVE     	0 6
	40	[79]	SETTABLE 	0 -16 10	; "autodetect_modules" -
	41	[137]	CLOSE    	8
	42	[146]	CLOSURE  	8 4	; 0x7fd65bc087e0
	43	[146]	MOVE     	0 2
	44	[363]	CLOSURE  	9 5	; 0x7fd65bc06d20
	45	[363]	MOVE     	0 4
	46	[363]	MOVE     	0 5
	47	[363]	MOVE     	0 8
	48	[363]	MOVE     	0 1
	49	[363]	MOVE     	0 6
	50	[363]	MOVE     	0 2
	51	[363]	MOVE     	0 3
	52	[363]	MOVE     	0 7
	53	[363]	MOVE     	0 0
	54	[152]	SETTABLE 	0 -17 9	; "run" -
	55	[365]	RETURN   	0 2
	56	[365]	RETURN   	0 1

function <./build/builtin.lua:13,43> (86 instructions, 344 bytes at 0x7fd65bc06b20)
1 param, 22 slots, 0 upvalues, 17 locals, 20 constants, 0 functions
	1	[14]	TEST     	0 0 0
	2	[14]	JMP      	3	; to 6
	3	[14]	GETTABLE 	1 0 -1	; "modules"
	4	[14]	TEST     	1 0 1
	5	[14]	JMP      	2	; to 8
	6	[15]	LOADNIL  	1 1
	7	[15]	RETURN   	1 2
	8	[17]	NEWTABLE 	1 0 0
	9	[18]	LOADBOOL 	2 0 0
	10	[19]	GETGLOBAL	3 -2	; pairs
	11	[19]	GETTABLE 	4 0 -1	; "modules"
	12	[19]	CALL     	3 2 4
	13	[19]	JMP      	64	; to 78
	14	[20]	GETGLOBAL	8 -3	; type
	15	[20]	MOVE     	9 7
	16	[20]	CALL     	8 2 2
	17	[20]	EQ       	0 8 -4	; - "table"
	18	[20]	JMP      	59	; to 78
	19	[20]	GETTABLE 	8 7 -5	; "libraries"
	20	[20]	TEST     	8 0 0
	21	[20]	JMP      	56	; to 78
	22	[21]	GETTABLE 	8 7 -5	; "libraries"
	23	[22]	GETGLOBAL	9 -3	; type
	24	[22]	MOVE     	10 8
	25	[22]	CALL     	9 2 2
	26	[22]	EQ       	0 9 -6	; - "string"
	27	[22]	JMP      	4	; to 32
	28	[23]	NEWTABLE 	9 1 0
	29	[23]	MOVE     	10 8
	30	[23]	SETLIST  	9 1 1	; 1
	31	[23]	MOVE     	8 9
	32	[25]	NEWTABLE 	9 0 0
	33	[26]	NEWTABLE 	10 0 0
	34	[27]	GETGLOBAL	11 -7	; ipairs
	35	[27]	MOVE     	12 8
	36	[27]	CALL     	11 2 4
	37	[27]	JMP      	30	; to 68
	38	[28]	SELF     	16 15 -8	; "upper"
	39	[28]	CALL     	16 2 2
	40	[28]	SELF     	16 16 -9	; "gsub"
	41	[28]	LOADK    	18 -10	; "%+"
	42	[28]	LOADK    	19 -11	; "P"
	43	[28]	CALL     	16 4 2
	44	[28]	SELF     	16 16 -9	; "gsub"
	45	[28]	LOADK    	18 -12	; "[^%w]"
	46	[28]	LOADK    	19 -13	; "_"
	47	[28]	CALL     	16 4 2
	48	[29]	LOADBOOL 	2 1 0
	49	[30]	NEWTABLE 	17 0 1
	50	[30]	SETTABLE 	17 -14 15	; "library" -
	51	[30]	SETTABLE 	1 16 17
	52	[31]	GETGLOBAL	17 -4	; table
	53	[31]	GETTABLE 	17 17 -15	; "insert"
	54	[31]	MOVE     	18 9
	55	[31]	LOADK    	19 -16	; "$("
	56	[31]	MOVE     	20 16
	57	[31]	LOADK    	21 -17	; "_INCDIR)"
	58	[31]	CONCAT   	19 19 21
	59	[31]	CALL     	17 3 1
	60	[32]	GETGLOBAL	17 -4	; table
	61	[32]	GETTABLE 	17 17 -15	; "insert"
	62	[32]	MOVE     	18 10
	63	[32]	LOADK    	19 -16	; "$("
	64	[32]	MOVE     	20 16
	65	[32]	LOADK    	21 -18	; "_LIBDIR)"
	66	[32]	CONCAT   	19 19 21
	67	[32]	CALL     	17 3 1
	68	[27]	TFORLOOP 	11 2
	69	[32]	JMP      	-32	; to 38
	70	[34]	GETTABLE 	11 7 -19	; "incdirs"
	71	[34]	TEST     	11 0 1
	72	[34]	JMP      	1	; to 74
	73	[35]	SETTABLE 	7 -19 9	; "incdirs" -
	74	[37]	GETTABLE 	11 7 -20	; "libdirs"
	75	[37]	TEST     	11 0 1
	76	[37]	JMP      	1	; to 78
	77	[38]	SETTABLE 	7 -20 10	; "libdirs" -
	78	[19]	TFORLOOP 	3 2
	79	[40]	JMP      	-66	; to 14
	80	[42]	TEST     	2 0 0
	81	[42]	JMP      	2	; to 84
	82	[42]	TESTSET  	3 1 1
	83	[42]	JMP      	1	; to 85
	84	[42]	LOADNIL  	3 3
	85	[42]	RETURN   	3 2
	86	[43]	RETURN   	0 1

function <./build/builtin.lua:45,60> (42 instructions, 168 bytes at 0x7fd65bc07110)
2 params, 14 slots, 0 upvalues, 10 locals, 6 constants, 0 functions
	1	[46]	TEST     	0 0 1
	2	[46]	JMP      	2	; to 5
	3	[47]	LOADNIL  	2 4
	4	[47]	RETURN   	2 4
	5	[49]	NEWTABLE 	2 0 0
	6	[50]	NEWTABLE 	3 0 0
	7	[51]	NEWTABLE 	4 0 0
	8	[52]	GETGLOBAL	5 -1	; pairs
	9	[52]	MOVE     	6 0
	10	[52]	CALL     	5 2 4
	11	[52]	JMP      	24	; to 36
	12	[53]	GETTABLE 	10 9 -2	; "library"
	13	[53]	TEST     	10 0 0
	14	[53]	JMP      	21	; to 36
	15	[54]	GETGLOBAL	10 -3	; table
	16	[54]	GETTABLE 	10 10 -4	; "insert"
	17	[54]	MOVE     	11 2
	18	[54]	GETTABLE 	12 9 -2	; "library"
	19	[54]	CALL     	10 3 1
	20	[55]	GETGLOBAL	10 -3	; table
	21	[55]	GETTABLE 	10 10 -4	; "insert"
	22	[55]	MOVE     	11 3
	23	[55]	MOVE     	12 8
	24	[55]	LOADK    	13 -5	; "_INCDIR"
	25	[55]	CONCAT   	12 12 13
	26	[55]	GETTABLE 	12 1 12
	27	[55]	CALL     	10 3 1
	28	[56]	GETGLOBAL	10 -3	; table
	29	[56]	GETTABLE 	10 10 -4	; "insert"
	30	[56]	MOVE     	11 4
	31	[56]	MOVE     	12 8
	32	[56]	LOADK    	13 -6	; "_LIBDIR"
	33	[56]	CONCAT   	12 12 13
	34	[56]	GETTABLE 	12 1 12
	35	[56]	CALL     	10 3 1
	36	[52]	TFORLOOP 	5 2
	37	[57]	JMP      	-26	; to 12
	38	[59]	MOVE     	5 2
	39	[59]	MOVE     	6 3
	40	[59]	MOVE     	7 4
	41	[59]	RETURN   	5 4
	42	[60]	RETURN   	0 1

function <./build/builtin.lua:63,69> (25 instructions, 100 bytes at 0x7fd65bc06ba0)
1 param, 6 slots, 2 upvalues, 3 locals, 10 constants, 0 functions
	1	[64]	GETGLOBAL	1 -1	; io
	2	[64]	GETTABLE 	1 1 -2	; "open"
	3	[64]	GETUPVAL 	2 0	; dir
	4	[64]	GETTABLE 	2 2 -3	; "path"
	5	[64]	GETUPVAL 	3 1	; fs
	6	[64]	GETTABLE 	3 3 -4	; "current_dir"
	7	[64]	CALL     	3 1 2
	8	[64]	MOVE     	4 0
	9	[64]	CALL     	2 3 2
	10	[64]	LOADK    	3 -5	; "r"
	11	[64]	CALL     	1 3 2
	12	[65]	TEST     	1 0 1
	13	[65]	JMP      	2	; to 16
	14	[65]	LOADNIL  	2 2
	15	[65]	RETURN   	2 2
	16	[66]	SELF     	2 1 -6	; "read"
	17	[66]	LOADK    	4 -7	; "*a"
	18	[66]	CALL     	2 3 2
	19	[67]	SELF     	3 1 -8	; "close"
	20	[67]	CALL     	3 2 1
	21	[68]	SELF     	3 2 -9	; "match"
	22	[68]	LOADK    	5 -10	; "int%s+luaopen_([a-zA-Z0-9_]+)"
	23	[68]	CALL     	3 3 2
	24	[68]	RETURN   	3 2
	25	[69]	RETURN   	0 1

function <./build/builtin.lua:79,137> (158 instructions, 632 bytes at 0x7fd65bc07020)
3 params, 20 slots, 5 upvalues, 32 locals, 32 constants, 0 functions
	1	[80]	NEWTABLE 	3 0 0
	2	[81]	LOADNIL  	4 5
	3	[84]	LOADK    	6 -1	; ""
	4	[85]	GETGLOBAL	7 -2	; ipairs
	5	[85]	NEWTABLE 	8 3 0
	6	[85]	LOADK    	9 -3	; "src"
	7	[85]	LOADK    	10 -4	; "lua"
	8	[85]	LOADK    	11 -5	; "lib"
	9	[85]	SETLIST  	8 3 1	; 1
	10	[85]	CALL     	7 2 4
	11	[85]	JMP      	14	; to 26
	12	[86]	GETUPVAL 	12 0	; fs
	13	[86]	GETTABLE 	12 12 -6	; "is_dir"
	14	[86]	MOVE     	13 11
	15	[86]	CALL     	12 2 2
	16	[86]	TEST     	12 0 0
	17	[86]	JMP      	8	; to 26
	18	[87]	GETUPVAL 	12 0	; fs
	19	[87]	GETTABLE 	12 12 -7	; "change_dir"
	20	[87]	MOVE     	13 11
	21	[87]	CALL     	12 2 1
	22	[88]	MOVE     	12 11
	23	[88]	LOADK    	13 -8	; "/"
	24	[88]	CONCAT   	6 12 13
	25	[89]	JMP      	2	; to 28
	26	[85]	TFORLOOP 	7 2
	27	[90]	JMP      	-16	; to 12
	28	[93]	GETGLOBAL	7 -2	; ipairs
	29	[93]	GETUPVAL 	8 0	; fs
	30	[93]	GETTABLE 	8 8 -9	; "find"
	31	[93]	CALL     	8 1 0
	32	[93]	CALL     	7 0 4
	33	[93]	JMP      	47	; to 81
	34	[94]	SELF     	12 11 -10	; "match"
	35	[94]	LOADK    	14 -11	; "^([^\\/]*)"
	36	[94]	CALL     	12 3 2
	37	[95]	GETUPVAL 	13 1	; skiplist
	38	[95]	GETTABLE 	13 13 12
	39	[95]	TEST     	13 0 1
	40	[95]	JMP      	40	; to 81
	41	[96]	SELF     	13 11 -10	; "match"
	42	[96]	LOADK    	15 -12	; "(.*)%.lua$"
	43	[96]	CALL     	13 3 2
	44	[97]	TEST     	13 0 0
	45	[97]	JMP      	9	; to 55
	46	[98]	GETUPVAL 	14 2	; path
	47	[98]	GETTABLE 	14 14 -13	; "path_to_module"
	48	[98]	MOVE     	15 11
	49	[98]	CALL     	14 2 2
	50	[98]	MOVE     	15 6
	51	[98]	MOVE     	16 11
	52	[98]	CONCAT   	15 15 16
	53	[98]	SETTABLE 	3 14 15
	54	[98]	JMP      	26	; to 81
	55	[100]	SELF     	14 11 -10	; "match"
	56	[100]	LOADK    	16 -14	; "(.*)%.c$"
	57	[100]	CALL     	14 3 2
	58	[101]	TEST     	14 0 0
	59	[101]	JMP      	21	; to 81
	60	[102]	GETUPVAL 	15 3	; get_cmod_name
	61	[102]	MOVE     	16 11
	62	[102]	CALL     	15 2 2
	63	[102]	TEST     	15 0 1
	64	[102]	JMP      	7	; to 72
	65	[102]	GETUPVAL 	15 2	; path
	66	[102]	GETTABLE 	15 15 -13	; "path_to_module"
	67	[102]	SELF     	16 11 -15	; "gsub"
	68	[102]	LOADK    	18 -16	; "%.c$"
	69	[102]	LOADK    	19 -17	; ".lua"
	70	[102]	CALL     	16 4 0
	71	[102]	CALL     	15 0 2
	72	[103]	NEWTABLE 	16 0 4
	73	[104]	MOVE     	17 6
	74	[104]	MOVE     	18 11
	75	[104]	CONCAT   	17 17 18
	76	[104]	SETTABLE 	16 -18 17	; "sources" -
	77	[105]	SETTABLE 	16 -19 0	; "libraries" -
	78	[106]	SETTABLE 	16 -20 1	; "incdirs" -
	79	[107]	SETTABLE 	16 -21 2	; "libdirs" -
	80	[108]	SETTABLE 	3 15 16
	81	[93]	TFORLOOP 	7 2
	82	[111]	JMP      	-49	; to 34
	83	[114]	EQ       	1 6 -1	; - ""
	84	[114]	JMP      	3	; to 88
	85	[115]	GETUPVAL 	7 0	; fs
	86	[115]	GETTABLE 	7 7 -22	; "pop_dir"
	87	[115]	CALL     	7 1 1
	88	[118]	GETUPVAL 	7 0	; fs
	89	[118]	GETTABLE 	7 7 -6	; "is_dir"
	90	[118]	LOADK    	8 -23	; "src/bin"
	91	[118]	CALL     	7 2 2
	92	[118]	TEST     	7 0 0
	93	[118]	JMP      	3	; to 97
	94	[119]	LOADK    	7 -23	; "src/bin"
	95	[119]	TEST     	7 0 1
	96	[119]	JMP      	7	; to 104
	97	[119]	GETUPVAL 	7 0	; fs
	98	[119]	GETTABLE 	7 7 -6	; "is_dir"
	99	[119]	LOADK    	8 -24	; "bin"
	100	[119]	CALL     	7 2 2
	101	[119]	TEST     	7 0 0
	102	[119]	JMP      	1	; to 104
	103	[119]	LOADK    	7 -24	; "bin"
	104	[120]	TEST     	7 0 0
	105	[120]	JMP      	22	; to 128
	106	[121]	NEWTABLE 	8 0 1
	107	[121]	NEWTABLE 	9 0 0
	108	[121]	SETTABLE 	8 -24 9	; "bin" -
	109	[121]	MOVE     	4 8
	110	[122]	GETGLOBAL	8 -2	; ipairs
	111	[122]	GETUPVAL 	9 0	; fs
	112	[122]	GETTABLE 	9 9 -25	; "list_dir"
	113	[122]	MOVE     	10 7
	114	[122]	CALL     	9 2 0
	115	[122]	CALL     	8 0 4
	116	[122]	JMP      	9	; to 126
	117	[123]	GETGLOBAL	13 -26	; table
	118	[123]	GETTABLE 	13 13 -27	; "insert"
	119	[123]	GETTABLE 	14 4 -24	; "bin"
	120	[123]	GETUPVAL 	15 4	; dir
	121	[123]	GETTABLE 	15 15 -28	; "path"
	122	[123]	MOVE     	16 7
	123	[123]	MOVE     	17 12
	124	[123]	CALL     	15 3 0
	125	[123]	CALL     	13 0 1
	126	[122]	TFORLOOP 	8 2
	127	[123]	JMP      	-11	; to 117
	128	[127]	GETGLOBAL	8 -2	; ipairs
	129	[127]	NEWTABLE 	9 4 0
	130	[127]	LOADK    	10 -29	; "doc"
	131	[127]	LOADK    	11 -30	; "docs"
	132	[127]	LOADK    	12 -31	; "samples"
	133	[127]	LOADK    	13 -32	; "tests"
	134	[127]	SETLIST  	9 4 1	; 1
	135	[127]	CALL     	8 2 4
	136	[127]	JMP      	15	; to 152
	137	[128]	GETUPVAL 	13 0	; fs
	138	[128]	GETTABLE 	13 13 -6	; "is_dir"
	139	[128]	MOVE     	14 12
	140	[128]	CALL     	13 2 2
	141	[128]	TEST     	13 0 0
	142	[128]	JMP      	9	; to 152
	143	[129]	TEST     	5 0 1
	144	[129]	JMP      	2	; to 147
	145	[130]	NEWTABLE 	13 0 0
	146	[130]	MOVE     	5 13
	147	[132]	GETGLOBAL	13 -26	; table
	148	[132]	GETTABLE 	13 13 -27	; "insert"
	149	[132]	MOVE     	14 5
	150	[132]	MOVE     	15 12
	151	[132]	CALL     	13 3 1
	152	[127]	TFORLOOP 	8 2
	153	[133]	JMP      	-17	; to 137
	154	[136]	MOVE     	8 3
	155	[136]	MOVE     	9 4
	156	[136]	MOVE     	10 5
	157	[136]	RETURN   	8 4
	158	[137]	RETURN   	0 1

function <./build/builtin.lua:143,146> (19 instructions, 76 bytes at 0x7fd65bc087e0)
0+ params, 6 slots, 1 upvalue, 1 local, 8 constants, 0 functions
	1	[144]	GETGLOBAL	1 -1	; io
	2	[144]	GETTABLE 	1 1 -2	; "stdout"
	3	[144]	SELF     	1 1 -3	; "write"
	4	[144]	GETGLOBAL	3 -4	; table
	5	[144]	GETTABLE 	3 3 -5	; "concat"
	6	[144]	NEWTABLE 	4 0 0
	7	[144]	VARARG   	5 0
	8	[144]	SETLIST  	4 0 1	; 1
	9	[144]	LOADK    	5 -6	; " "
	10	[144]	CALL     	3 3 2
	11	[144]	LOADK    	4 -7	; "\n"
	12	[144]	CONCAT   	3 3 4
	13	[144]	CALL     	1 3 1
	14	[145]	GETUPVAL 	1 0	; fs
	15	[145]	GETTABLE 	1 1 -8	; "execute"
	16	[145]	VARARG   	2 0
	17	[145]	TAILCALL 	1 0 0
	18	[145]	RETURN   	1 0
	19	[146]	RETURN   	0 1

function <./build/builtin.lua:152,363> (374 instructions, 1496 bytes at 0x7fd65bc06d20)
1 param, 33 slots, 9 upvalues, 50 locals, 72 constants, 8 functions
	1	[153]	GETGLOBAL	1 -1	; assert
	2	[153]	SELF     	2 0 -2	; "type"
	3	[153]	CALL     	2 2 2
	4	[153]	EQ       	1 2 -3	; - "rockspec"
	5	[153]	JMP      	1	; to 7
	6	[153]	LOADBOOL 	2 0 1
	7	[153]	LOADBOOL 	2 1 0
	8	[153]	CALL     	1 2 1
	9	[154]	LOADNIL  	1 3
	10	[156]	GETTABLE 	4 0 -4	; "build"
	11	[157]	GETTABLE 	5 0 -5	; "variables"
	12	[158]	LOADBOOL 	6 0 0
	13	[170]	CLOSURE  	7 0	; 0x7fd65bc099d0
	14	[170]	GETUPVAL 	0 0	; util
	15	[170]	MOVE     	0 5
	16	[172]	GETUPVAL 	8 1	; cfg
	17	[172]	GETTABLE 	8 8 -6	; "is_platform"
	18	[172]	LOADK    	9 -7	; "mingw32"
	19	[172]	CALL     	8 2 2
	20	[172]	TEST     	8 0 0
	21	[172]	JMP      	12	; to 34
	22	[178]	CLOSURE  	1 1	; 0x7fd65bc0a130
	23	[178]	MOVE     	0 7
	24	[178]	GETUPVAL 	0 2	; execute
	25	[178]	MOVE     	0 5
	26	[178]	GETUPVAL 	0 3	; unpack
	27	[187]	CLOSURE  	2 2	; 0x7fd65bc09b10
	28	[187]	GETUPVAL 	0 3	; unpack
	29	[187]	MOVE     	0 7
	30	[187]	GETUPVAL 	0 4	; dir
	31	[187]	MOVE     	0 5
	32	[187]	GETUPVAL 	0 2	; execute
	33	[187]	JMP      	34	; to 68
	34	[197]	GETUPVAL 	8 1	; cfg
	35	[197]	GETTABLE 	8 8 -6	; "is_platform"
	36	[197]	LOADK    	9 -8	; "win32"
	37	[197]	CALL     	8 2 2
	38	[197]	TEST     	8 0 0
	39	[197]	JMP      	13	; to 53
	40	[203]	CLOSURE  	1 3	; 0x7fd65bc0a0b0
	41	[203]	MOVE     	0 7
	42	[203]	GETUPVAL 	0 2	; execute
	43	[203]	MOVE     	0 5
	44	[203]	GETUPVAL 	0 3	; unpack
	45	[228]	CLOSURE  	2 4	; 0x7fd65bc09420
	46	[228]	GETUPVAL 	0 3	; unpack
	47	[228]	MOVE     	0 7
	48	[228]	GETUPVAL 	0 4	; dir
	49	[228]	GETUPVAL 	0 5	; fs
	50	[228]	GETUPVAL 	0 2	; execute
	51	[228]	MOVE     	0 5
	52	[228]	JMP      	15	; to 68
	53	[241]	CLOSURE  	1 5	; 0x7fd65bc0b230
	54	[241]	MOVE     	0 7
	55	[241]	GETUPVAL 	0 2	; execute
	56	[241]	MOVE     	0 5
	57	[241]	GETUPVAL 	0 3	; unpack
	58	[254]	CLOSURE  	2 6	; 0x7fd65bc0b3e0
	59	[254]	GETUPVAL 	0 3	; unpack
	60	[254]	MOVE     	0 7
	61	[254]	GETUPVAL 	0 1	; cfg
	62	[254]	MOVE     	0 5
	63	[254]	GETUPVAL 	0 2	; execute
	64	[261]	CLOSURE  	3 7	; 0x7fd65bc0bc30
	65	[261]	GETUPVAL 	0 2	; execute
	66	[261]	MOVE     	0 5
	67	[261]	GETUPVAL 	0 3	; unpack
	68	[264]	LOADNIL  	8 9
	69	[265]	NEWTABLE 	10 0 0
	70	[266]	NEWTABLE 	11 0 0
	71	[267]	GETUPVAL 	12 6	; path
	72	[267]	GETTABLE 	12 12 -9	; "lua_dir"
	73	[267]	GETTABLE 	13 0 -10	; "name"
	74	[267]	GETTABLE 	14 0 -11	; "version"
	75	[267]	CALL     	12 3 2
	76	[268]	GETUPVAL 	13 6	; path
	77	[268]	GETTABLE 	13 13 -12	; "lib_dir"
	78	[268]	GETTABLE 	14 0 -10	; "name"
	79	[268]	GETTABLE 	15 0 -11	; "version"
	80	[268]	CALL     	13 3 2
	81	[270]	GETTABLE 	14 4 -13	; "modules"
	82	[270]	TEST     	14 0 1
	83	[270]	JMP      	33	; to 117
	84	[271]	SELF     	14 0 -14	; "format_is_at_least"
	85	[271]	LOADK    	16 -15	; "3.0"
	86	[271]	CALL     	14 3 2
	87	[271]	TEST     	14 0 0
	88	[271]	JMP      	25	; to 114
	89	[272]	GETUPVAL 	14 7	; autoextract_libs
	90	[272]	GETTABLE 	15 0 -16	; "external_dependencies"
	91	[272]	GETTABLE 	16 0 -5	; "variables"
	92	[272]	CALL     	14 3 4
	93	[273]	LOADNIL  	17 18
	94	[274]	GETUPVAL 	19 8	; builtin
	95	[274]	GETTABLE 	19 19 -17	; "autodetect_modules"
	96	[274]	MOVE     	20 14
	97	[274]	MOVE     	21 15
	98	[274]	MOVE     	22 16
	99	[274]	CALL     	19 4 4
	100	[274]	MOVE     	18 21
	101	[274]	MOVE     	17 20
	102	[274]	SETTABLE 	4 -13 19	; "modules" -
	103	[275]	GETTABLE 	19 4 -18	; "install"
	104	[275]	TEST     	19 0 1
	105	[275]	JMP      	1	; to 107
	106	[275]	MOVE     	19 17
	107	[275]	SETTABLE 	4 -18 19	; "install" -
	108	[276]	GETTABLE 	19 4 -19	; "copy_directories"
	109	[276]	TEST     	19 0 1
	110	[276]	JMP      	1	; to 112
	111	[276]	MOVE     	19 18
	112	[276]	SETTABLE 	4 -19 19	; "copy_directories" -
	113	[276]	JMP      	3	; to 117
	114	[278]	LOADNIL  	14 14
	115	[278]	LOADK    	15 -20	; "Missing build.modules table"
	116	[278]	RETURN   	14 3
	117	[281]	GETGLOBAL	14 -21	; pairs
	118	[281]	GETTABLE 	15 4 -13	; "modules"
	119	[281]	CALL     	14 2 4
	120	[281]	JMP      	184	; to 305
	121	[282]	GETUPVAL 	19 6	; path
	122	[282]	GETTABLE 	19 19 -22	; "module_to_path"
	123	[282]	MOVE     	20 17
	124	[282]	CALL     	19 2 2
	125	[283]	GETGLOBAL	20 -2	; type
	126	[283]	MOVE     	21 18
	127	[283]	CALL     	20 2 2
	128	[283]	EQ       	0 20 -23	; - "string"
	129	[283]	JMP      	42	; to 172
	130	[284]	SELF     	20 18 -24	; "match"
	131	[284]	LOADK    	22 -25	; "%.([^.]+)$"
	132	[284]	CALL     	20 3 2
	133	[285]	EQ       	0 20 -26	; - "lua"
	134	[285]	JMP      	33	; to 168
	135	[286]	GETUPVAL 	21 4	; dir
	136	[286]	GETTABLE 	21 21 -27	; "base_name"
	137	[286]	MOVE     	22 18
	138	[286]	CALL     	21 2 2
	139	[287]	EQ       	0 21 -28	; - "init.lua"
	140	[287]	JMP      	13	; to 154
	141	[287]	SELF     	22 17 -24	; "match"
	142	[287]	LOADK    	24 -29	; "%.init$"
	143	[287]	CALL     	22 3 2
	144	[287]	TEST     	22 0 1
	145	[287]	JMP      	8	; to 154
	146	[288]	GETUPVAL 	22 6	; path
	147	[288]	GETTABLE 	22 22 -22	; "module_to_path"
	148	[288]	MOVE     	23 17
	149	[288]	LOADK    	24 -30	; ".init"
	150	[288]	CONCAT   	23 23 24
	151	[288]	CALL     	22 2 2
	152	[288]	MOVE     	19 22
	153	[288]	JMP      	6	; to 160
	154	[290]	SELF     	22 17 -24	; "match"
	155	[290]	LOADK    	24 -31	; "([^.]+)$"
	156	[290]	CALL     	22 3 2
	157	[291]	MOVE     	23 22
	158	[291]	LOADK    	24 -32	; ".lua"
	159	[291]	CONCAT   	21 23 24
	160	[293]	GETUPVAL 	22 4	; dir
	161	[293]	GETTABLE 	22 22 -33	; "path"
	162	[293]	MOVE     	23 12
	163	[293]	MOVE     	24 19
	164	[293]	MOVE     	25 21
	165	[293]	CALL     	22 4 2
	166	[294]	SETTABLE 	10 18 22
	167	[294]	JMP      	4	; to 172
	168	[296]	NEWTABLE 	21 1 0
	169	[296]	MOVE     	22 18
	170	[296]	SETLIST  	21 1 1	; 1
	171	[296]	MOVE     	18 21
	172	[299]	GETGLOBAL	20 -2	; type
	173	[299]	MOVE     	21 18
	174	[299]	CALL     	20 2 2
	175	[299]	EQ       	0 20 -34	; - "table"
	176	[299]	JMP      	128	; to 305
	177	[300]	TEST     	6 0 1
	178	[300]	JMP      	22	; to 201
	179	[301]	GETTABLE 	20 5 -35	; "LUA_INCDIR"
	180	[301]	LOADK    	21 -36	; "lua.h"
	181	[302]	GETUPVAL 	22 5	; fs
	182	[302]	GETTABLE 	22 22 -37	; "exists"
	183	[302]	GETUPVAL 	23 4	; dir
	184	[302]	GETTABLE 	23 23 -33	; "path"
	185	[302]	MOVE     	24 20
	186	[302]	MOVE     	25 21
	187	[302]	CALL     	23 3 0
	188	[302]	CALL     	22 0 2
	189	[302]	TEST     	22 0 1
	190	[302]	JMP      	9	; to 200
	191	[303]	LOADNIL  	22 22
	192	[303]	LOADK    	23 -38	; "Lua header file "
	193	[303]	MOVE     	24 21
	194	[303]	LOADK    	25 -39	; " not found (looked in "
	195	[303]	MOVE     	26 20
	196	[303]	LOADK    	27 -40	; "). \n"
	197	[304]	LOADK    	28 -41	; "You need to install the Lua development package for your system."
	198	[304]	CONCAT   	23 23 28
	199	[304]	RETURN   	22 3
	200	[306]	LOADBOOL 	6 1 0
	201	[308]	NEWTABLE 	20 0 0
	202	[309]	GETTABLE 	21 18 -42	; "sources"
	203	[310]	GETTABLE 	22 18 -43	; 1
	204	[310]	TEST     	22 0 0
	205	[310]	JMP      	1	; to 207
	206	[310]	MOVE     	21 18
	207	[311]	GETGLOBAL	22 -2	; type
	208	[311]	MOVE     	23 21
	209	[311]	CALL     	22 2 2
	210	[311]	EQ       	0 22 -23	; - "string"
	211	[311]	JMP      	4	; to 216
	212	[311]	NEWTABLE 	22 1 0
	213	[311]	MOVE     	23 21
	214	[311]	SETLIST  	22 1 1	; 1
	215	[311]	MOVE     	21 22
	216	[312]	GETGLOBAL	22 -44	; ipairs
	217	[312]	MOVE     	23 21
	218	[312]	CALL     	22 2 4
	219	[312]	JMP      	33	; to 253
	220	[313]	SELF     	27 26 -45	; "gsub"
	221	[313]	LOADK    	29 -46	; "%.[^.]*$"
	222	[313]	LOADK    	30 -47	; "."
	223	[313]	GETUPVAL 	31 1	; cfg
	224	[313]	GETTABLE 	31 31 -48	; "obj_extension"
	225	[313]	CONCAT   	30 30 31
	226	[313]	CALL     	27 4 2
	227	[314]	TEST     	27 0 1
	228	[314]	JMP      	5	; to 234
	229	[315]	MOVE     	28 26
	230	[315]	LOADK    	29 -47	; "."
	231	[315]	GETUPVAL 	30 1	; cfg
	232	[315]	GETTABLE 	30 30 -48	; "obj_extension"
	233	[315]	CONCAT   	27 28 30
	234	[317]	MOVE     	28 1
	235	[317]	MOVE     	29 27
	236	[317]	MOVE     	30 26
	237	[317]	GETTABLE 	31 18 -49	; "defines"
	238	[317]	GETTABLE 	32 18 -50	; "incdirs"
	239	[317]	CALL     	28 5 2
	240	[317]	MOVE     	8 28
	241	[318]	TEST     	8 0 1
	242	[318]	JMP      	5	; to 248
	243	[319]	LOADNIL  	28 28
	244	[319]	LOADK    	29 -51	; "Failed compiling object "
	245	[319]	MOVE     	30 27
	246	[319]	CONCAT   	29 29 30
	247	[319]	RETURN   	28 3
	248	[321]	GETGLOBAL	28 -34	; table
	249	[321]	GETTABLE 	28 28 -52	; "insert"
	250	[321]	MOVE     	29 20
	251	[321]	MOVE     	30 27
	252	[321]	CALL     	28 3 1
	253	[312]	TFORLOOP 	22 2
	254	[321]	JMP      	-35	; to 220
	255	[323]	SELF     	22 17 -24	; "match"
	256	[323]	LOADK    	24 -53	; "([^.]*)$"
	257	[323]	CALL     	22 3 2
	258	[323]	LOADK    	23 -47	; "."
	259	[323]	GETUPVAL 	24 0	; util
	260	[323]	GETTABLE 	24 24 -54	; "matchquote"
	261	[323]	GETUPVAL 	25 1	; cfg
	262	[323]	GETTABLE 	25 25 -55	; "lib_extension"
	263	[323]	CALL     	24 2 2
	264	[323]	CONCAT   	22 22 24
	265	[324]	EQ       	1 19 -56	; - ""
	266	[324]	JMP      	17	; to 284
	267	[325]	GETUPVAL 	23 4	; dir
	268	[325]	GETTABLE 	23 23 -33	; "path"
	269	[325]	MOVE     	24 19
	270	[325]	MOVE     	25 22
	271	[325]	CALL     	23 3 2
	272	[325]	MOVE     	22 23
	273	[326]	GETUPVAL 	23 5	; fs
	274	[326]	GETTABLE 	23 23 -57	; "make_dir"
	275	[326]	MOVE     	24 19
	276	[326]	CALL     	23 2 3
	277	[326]	MOVE     	9 24
	278	[326]	MOVE     	8 23
	279	[327]	TEST     	8 0 1
	280	[327]	JMP      	3	; to 284
	281	[327]	LOADNIL  	23 23
	282	[327]	MOVE     	24 9
	283	[327]	RETURN   	23 3
	284	[329]	GETUPVAL 	23 4	; dir
	285	[329]	GETTABLE 	23 23 -33	; "path"
	286	[329]	MOVE     	24 13
	287	[329]	MOVE     	25 22
	288	[329]	CALL     	23 3 2
	289	[329]	SETTABLE 	11 22 23
	290	[330]	MOVE     	23 2
	291	[330]	MOVE     	24 22
	292	[330]	MOVE     	25 20
	293	[330]	GETTABLE 	26 18 -58	; "libraries"
	294	[330]	GETTABLE 	27 18 -59	; "libdirs"
	295	[330]	MOVE     	28 17
	296	[330]	CALL     	23 6 2
	297	[330]	MOVE     	8 23
	298	[331]	TEST     	8 0 1
	299	[331]	JMP      	5	; to 305
	300	[332]	LOADNIL  	23 23
	301	[332]	LOADK    	24 -60	; "Failed compiling module "
	302	[332]	MOVE     	25 22
	303	[332]	CONCAT   	24 24 25
	304	[332]	RETURN   	23 3
	305	[281]	TFORLOOP 	14 2
	306	[345]	JMP      	-186	; to 121
	307	[347]	GETGLOBAL	14 -44	; ipairs
	308	[347]	NEWTABLE 	15 2 0
	309	[347]	NEWTABLE 	16 0 2
	310	[347]	SETTABLE 	16 -61 10	; "tbl" -
	311	[347]	SETTABLE 	16 -62 -63	; "perms" "read"
	312	[347]	NEWTABLE 	17 0 2
	313	[347]	SETTABLE 	17 -61 11	; "tbl" -
	314	[347]	SETTABLE 	17 -62 -64	; "perms" "exec"
	315	[347]	SETLIST  	15 2 1	; 1
	316	[347]	CALL     	14 2 4
	317	[347]	JMP      	32	; to 350
	318	[348]	GETGLOBAL	19 -21	; pairs
	319	[348]	GETTABLE 	20 18 -61	; "tbl"
	320	[348]	CALL     	19 2 4
	321	[348]	JMP      	26	; to 348
	322	[349]	GETUPVAL 	24 5	; fs
	323	[349]	GETTABLE 	24 24 -57	; "make_dir"
	324	[349]	GETUPVAL 	25 4	; dir
	325	[349]	GETTABLE 	25 25 -65	; "dir_name"
	326	[349]	MOVE     	26 23
	327	[349]	CALL     	25 2 0
	328	[349]	CALL     	24 0 1
	329	[350]	GETUPVAL 	24 5	; fs
	330	[350]	GETTABLE 	24 24 -66	; "copy"
	331	[350]	MOVE     	25 22
	332	[350]	MOVE     	26 23
	333	[350]	GETTABLE 	27 18 -62	; "perms"
	334	[350]	CALL     	24 4 3
	335	[350]	MOVE     	9 25
	336	[350]	MOVE     	8 24
	337	[351]	TEST     	8 0 1
	338	[351]	JMP      	9	; to 348
	339	[352]	LOADNIL  	24 24
	340	[352]	LOADK    	25 -67	; "Failed installing "
	341	[352]	MOVE     	26 22
	342	[352]	LOADK    	27 -68	; " in "
	343	[352]	MOVE     	28 23
	344	[352]	LOADK    	29 -69	; ": "
	345	[352]	MOVE     	30 9
	346	[352]	CONCAT   	25 25 30
	347	[352]	RETURN   	24 3
	348	[348]	TFORLOOP 	19 2
	349	[353]	JMP      	-28	; to 322
	350	[347]	TFORLOOP 	14 2
	351	[354]	JMP      	-34	; to 318
	352	[356]	GETUPVAL 	14 5	; fs
	353	[356]	GETTABLE 	14 14 -70	; "is_dir"
	354	[356]	LOADK    	15 -26	; "lua"
	355	[356]	CALL     	14 2 2
	356	[356]	TEST     	14 0 0
	357	[356]	JMP      	14	; to 372
	358	[357]	GETUPVAL 	14 5	; fs
	359	[357]	GETTABLE 	14 14 -71	; "copy_contents"
	360	[357]	LOADK    	15 -26	; "lua"
	361	[357]	MOVE     	16 12
	362	[357]	CALL     	14 3 3
	363	[357]	MOVE     	9 15
	364	[357]	MOVE     	8 14
	365	[358]	TEST     	8 0 1
	366	[358]	JMP      	5	; to 372
	367	[359]	LOADNIL  	14 14
	368	[359]	LOADK    	15 -72	; "Failed copying contents of 'lua' directory: "
	369	[359]	MOVE     	16 9
	370	[359]	CONCAT   	15 15 16
	371	[359]	RETURN   	14 3
	372	[362]	LOADBOOL 	14 1 0
	373	[362]	RETURN   	14 2
	374	[363]	RETURN   	0 1

function <./build/builtin.lua:160,170> (32 instructions, 128 bytes at 0x7fd65bc099d0)
3 params, 13 slots, 2 upvalues, 8 locals, 7 constants, 0 functions
	1	[161]	TEST     	2 0 0
	2	[161]	JMP      	29	; to 32
	3	[162]	GETGLOBAL	3 -1	; type
	4	[162]	MOVE     	4 2
	5	[162]	CALL     	3 2 2
	6	[162]	EQ       	1 3 -2	; - "table"
	7	[162]	JMP      	6	; to 14
	8	[163]	NEWTABLE 	3 0 0
	9	[163]	GETGLOBAL	4 -3	; tostring
	10	[163]	MOVE     	5 2
	11	[163]	CALL     	4 2 0
	12	[163]	SETLIST  	3 0 1	; 1
	13	[163]	MOVE     	2 3
	14	[165]	GETUPVAL 	3 0	; util
	15	[165]	GETTABLE 	3 3 -4	; "variable_substitutions"
	16	[165]	MOVE     	4 2
	17	[165]	GETUPVAL 	5 1	; variables
	18	[165]	CALL     	3 3 1
	19	[166]	GETGLOBAL	3 -5	; ipairs
	20	[166]	MOVE     	4 2
	21	[166]	CALL     	3 2 4
	22	[166]	JMP      	7	; to 30
	23	[167]	GETGLOBAL	8 -2	; table
	24	[167]	GETTABLE 	8 8 -6	; "insert"
	25	[167]	MOVE     	9 0
	26	[167]	SELF     	10 1 -7	; "format"
	27	[167]	MOVE     	12 7
	28	[167]	CALL     	10 3 0
	29	[167]	CALL     	8 0 1
	30	[166]	TFORLOOP 	3 2
	31	[167]	JMP      	-9	; to 23
	32	[170]	RETURN   	0 1

function <./build/builtin.lua:173,178> (32 instructions, 128 bytes at 0x7fd65bc0a130)
4 params, 14 slots, 4 upvalues, 5 locals, 9 constants, 0 functions
	1	[174]	NEWTABLE 	4 0 0
	2	[175]	GETUPVAL 	5 0	; add_flags
	3	[175]	MOVE     	6 4
	4	[175]	LOADK    	7 -1	; "-D%s"
	5	[175]	MOVE     	8 2
	6	[175]	CALL     	5 4 1
	7	[176]	GETUPVAL 	5 0	; add_flags
	8	[176]	MOVE     	6 4
	9	[176]	LOADK    	7 -2	; "-I%s"
	10	[176]	MOVE     	8 3
	11	[176]	CALL     	5 4 1
	12	[177]	GETUPVAL 	5 1	; execute
	13	[177]	GETUPVAL 	6 2	; variables
	14	[177]	GETTABLE 	6 6 -3	; "CC"
	15	[177]	LOADK    	7 -4	; " "
	16	[177]	GETUPVAL 	8 2	; variables
	17	[177]	GETTABLE 	8 8 -5	; "CFLAGS"
	18	[177]	CONCAT   	6 6 8
	19	[177]	LOADK    	7 -6	; "-c"
	20	[177]	LOADK    	8 -7	; "-o"
	21	[177]	MOVE     	9 0
	22	[177]	LOADK    	10 -8	; "-I"
	23	[177]	GETUPVAL 	11 2	; variables
	24	[177]	GETTABLE 	11 11 -9	; "LUA_INCDIR"
	25	[177]	CONCAT   	10 10 11
	26	[177]	MOVE     	11 1
	27	[177]	GETUPVAL 	12 3	; unpack
	28	[177]	MOVE     	13 4
	29	[177]	CALL     	12 2 0
	30	[177]	TAILCALL 	5 0 0
	31	[177]	RETURN   	5 0
	32	[178]	RETURN   	0 1

function <./build/builtin.lua:179,187> (50 instructions, 200 bytes at 0x7fd65bc09b10)
4 params, 11 slots, 5 upvalues, 6 locals, 13 constants, 0 functions
	1	[180]	NEWTABLE 	4 0 0
	2	[180]	GETUPVAL 	5 0	; unpack
	3	[180]	MOVE     	6 1
	4	[180]	CALL     	5 2 0
	5	[180]	SETLIST  	4 0 1	; 1
	6	[181]	GETUPVAL 	5 1	; add_flags
	7	[181]	MOVE     	6 4
	8	[181]	LOADK    	7 -1	; "-L%s"
	9	[181]	MOVE     	8 3
	10	[181]	CALL     	5 4 1
	11	[182]	GETUPVAL 	5 1	; add_flags
	12	[182]	MOVE     	6 4
	13	[182]	LOADK    	7 -2	; "-l%s"
	14	[182]	MOVE     	8 2
	15	[182]	CALL     	5 4 1
	16	[183]	LEN      	5 4
	17	[183]	ADD      	5 5 -3	; - 1
	18	[183]	GETUPVAL 	6 2	; dir
	19	[183]	GETTABLE 	6 6 -4	; "path"
	20	[183]	GETUPVAL 	7 3	; variables
	21	[183]	GETTABLE 	7 7 -5	; "LUA_LIBDIR"
	22	[183]	GETUPVAL 	8 3	; variables
	23	[183]	GETTABLE 	8 8 -6	; "LUALIB"
	24	[183]	CALL     	6 3 2
	25	[183]	SETTABLE 	4 5 6
	26	[184]	LEN      	5 4
	27	[184]	ADD      	5 5 -3	; - 1
	28	[184]	LOADK    	6 -7	; "-l"
	29	[184]	GETUPVAL 	7 3	; variables
	30	[184]	GETTABLE 	7 7 -8	; "MSVCRT"
	31	[184]	TEST     	7 0 1
	32	[184]	JMP      	1	; to 34
	33	[184]	LOADK    	7 -9	; "m"
	34	[184]	CONCAT   	6 6 7
	35	[184]	SETTABLE 	4 5 6
	36	[185]	GETUPVAL 	5 4	; execute
	37	[185]	GETUPVAL 	6 3	; variables
	38	[185]	GETTABLE 	6 6 -10	; "LD"
	39	[185]	LOADK    	7 -11	; " "
	40	[185]	GETUPVAL 	8 3	; variables
	41	[185]	GETTABLE 	8 8 -12	; "LIBFLAG"
	42	[185]	CONCAT   	6 6 8
	43	[185]	LOADK    	7 -13	; "-o"
	44	[185]	MOVE     	8 0
	45	[185]	GETUPVAL 	9 0	; unpack
	46	[185]	MOVE     	10 4
	47	[185]	CALL     	9 2 0
	48	[185]	CALL     	5 0 2
	49	[186]	RETURN   	5 2
	50	[187]	RETURN   	0 1

function <./build/builtin.lua:198,203> (33 instructions, 132 bytes at 0x7fd65bc0a0b0)
4 params, 13 slots, 4 upvalues, 5 locals, 9 constants, 0 functions
	1	[199]	NEWTABLE 	4 0 0
	2	[200]	GETUPVAL 	5 0	; add_flags
	3	[200]	MOVE     	6 4
	4	[200]	LOADK    	7 -1	; "-D%s"
	5	[200]	MOVE     	8 2
	6	[200]	CALL     	5 4 1
	7	[201]	GETUPVAL 	5 0	; add_flags
	8	[201]	MOVE     	6 4
	9	[201]	LOADK    	7 -2	; "-I%s"
	10	[201]	MOVE     	8 3
	11	[201]	CALL     	5 4 1
	12	[202]	GETUPVAL 	5 1	; execute
	13	[202]	GETUPVAL 	6 2	; variables
	14	[202]	GETTABLE 	6 6 -3	; "CC"
	15	[202]	LOADK    	7 -4	; " "
	16	[202]	GETUPVAL 	8 2	; variables
	17	[202]	GETTABLE 	8 8 -5	; "CFLAGS"
	18	[202]	CONCAT   	6 6 8
	19	[202]	LOADK    	7 -6	; "-c"
	20	[202]	LOADK    	8 -7	; "-Fo"
	21	[202]	MOVE     	9 0
	22	[202]	CONCAT   	8 8 9
	23	[202]	LOADK    	9 -8	; "-I"
	24	[202]	GETUPVAL 	10 2	; variables
	25	[202]	GETTABLE 	10 10 -9	; "LUA_INCDIR"
	26	[202]	CONCAT   	9 9 10
	27	[202]	MOVE     	10 1
	28	[202]	GETUPVAL 	11 3	; unpack
	29	[202]	MOVE     	12 4
	30	[202]	CALL     	11 2 0
	31	[202]	TAILCALL 	5 0 0
	32	[202]	RETURN   	5 0
	33	[203]	RETURN   	0 1

function <./build/builtin.lua:204,228> (120 instructions, 480 bytes at 0x7fd65bc09420)
5 params, 21 slots, 6 upvalues, 13 locals, 37 constants, 0 functions
	1	[205]	NEWTABLE 	5 0 0
	2	[205]	GETUPVAL 	6 0	; unpack
	3	[205]	MOVE     	7 1
	4	[205]	CALL     	6 2 0
	5	[205]	SETLIST  	5 0 1	; 1
	6	[206]	GETUPVAL 	6 1	; add_flags
	7	[206]	MOVE     	7 5
	8	[206]	LOADK    	8 -1	; "-libpath:%s"
	9	[206]	MOVE     	9 3
	10	[206]	CALL     	6 4 1
	11	[207]	GETUPVAL 	6 1	; add_flags
	12	[207]	MOVE     	7 5
	13	[207]	LOADK    	8 -2	; "%s.lib"
	14	[207]	MOVE     	9 2
	15	[207]	CALL     	6 4 1
	16	[208]	GETUPVAL 	6 2	; dir
	17	[208]	GETTABLE 	6 6 -3	; "base_name"
	18	[208]	MOVE     	7 0
	19	[208]	CALL     	6 2 2
	20	[208]	SELF     	6 6 -4	; "gsub"
	21	[208]	LOADK    	8 -5	; ".[^.]*$"
	22	[208]	LOADK    	9 -6	; ""
	23	[208]	CALL     	6 4 2
	24	[209]	MOVE     	7 6
	25	[209]	LOADK    	8 -7	; ".def"
	26	[209]	CONCAT   	7 7 8
	27	[210]	GETGLOBAL	8 -8	; io
	28	[210]	GETTABLE 	8 8 -9	; "open"
	29	[210]	GETUPVAL 	9 2	; dir
	30	[210]	GETTABLE 	9 9 -10	; "path"
	31	[210]	GETUPVAL 	10 3	; fs
	32	[210]	GETTABLE 	10 10 -11	; "current_dir"
	33	[210]	CALL     	10 1 2
	34	[210]	MOVE     	11 7
	35	[210]	CALL     	9 3 2
	36	[210]	LOADK    	10 -12	; "w+"
	37	[210]	CALL     	8 3 2
	38	[211]	SELF     	9 4 -4	; "gsub"
	39	[211]	LOADK    	11 -13	; "%."
	40	[211]	LOADK    	12 -14	; "_"
	41	[211]	CALL     	9 4 2
	42	[212]	SELF     	10 9 -15	; "match"
	43	[212]	LOADK    	12 -16	; "^[^%-]+%-(.+)$"
	44	[212]	CALL     	10 3 2
	45	[212]	TESTSET  	9 10 1
	46	[212]	JMP      	0	; to 47
	47	[213]	SELF     	10 8 -17	; "write"
	48	[213]	LOADK    	12 -18	; "EXPORTS\n"
	49	[213]	CALL     	10 3 1
	50	[214]	SELF     	10 8 -17	; "write"
	51	[214]	LOADK    	12 -19	; "luaopen_"
	52	[214]	MOVE     	13 9
	53	[214]	LOADK    	14 -20	; "\n"
	54	[214]	CONCAT   	12 12 14
	55	[214]	CALL     	10 3 1
	56	[215]	SELF     	10 8 -21	; "close"
	57	[215]	CALL     	10 2 1
	58	[216]	GETUPVAL 	10 4	; execute
	59	[216]	GETUPVAL 	11 5	; variables
	60	[216]	GETTABLE 	11 11 -22	; "LD"
	61	[216]	LOADK    	12 -23	; "-dll"
	62	[216]	LOADK    	13 -24	; "-def:"
	63	[216]	MOVE     	14 7
	64	[216]	CONCAT   	13 13 14
	65	[216]	LOADK    	14 -25	; "-out:"
	66	[216]	MOVE     	15 0
	67	[216]	CONCAT   	14 14 15
	68	[216]	GETUPVAL 	15 2	; dir
	69	[216]	GETTABLE 	15 15 -10	; "path"
	70	[216]	GETUPVAL 	16 5	; variables
	71	[216]	GETTABLE 	16 16 -26	; "LUA_LIBDIR"
	72	[216]	GETUPVAL 	17 5	; variables
	73	[216]	GETTABLE 	17 17 -27	; "LUALIB"
	74	[216]	CALL     	15 3 2
	75	[216]	GETUPVAL 	16 0	; unpack
	76	[216]	MOVE     	17 5
	77	[216]	CALL     	16 2 0
	78	[216]	CALL     	10 0 2
	79	[217]	LOADK    	11 -6	; ""
	80	[218]	SELF     	12 4 -28	; "find"
	81	[218]	LOADK    	14 -13	; "%."
	82	[218]	CALL     	12 3 2
	83	[218]	EQ       	1 12 -29	; - nil
	84	[218]	JMP      	10	; to 95
	85	[219]	SELF     	12 4 -4	; "gsub"
	86	[219]	LOADK    	14 -30	; "%.%w+$"
	87	[219]	LOADK    	15 -31	; "\\"
	88	[219]	CALL     	12 4 2
	89	[219]	MOVE     	11 12
	90	[220]	SELF     	12 11 -4	; "gsub"
	91	[220]	LOADK    	14 -13	; "%."
	92	[220]	LOADK    	15 -31	; "\\"
	93	[220]	CALL     	12 4 2
	94	[220]	MOVE     	11 12
	95	[222]	MOVE     	12 11
	96	[222]	MOVE     	13 6
	97	[222]	LOADK    	14 -32	; ".dll.manifest"
	98	[222]	CONCAT   	12 12 14
	99	[224]	TEST     	10 0 0
	100	[224]	JMP      	18	; to 119
	101	[224]	GETUPVAL 	13 3	; fs
	102	[224]	GETTABLE 	13 13 -33	; "exists"
	103	[224]	MOVE     	14 12
	104	[224]	CALL     	13 2 2
	105	[224]	TEST     	13 0 0
	106	[224]	JMP      	12	; to 119
	107	[225]	GETUPVAL 	13 4	; execute
	108	[225]	GETUPVAL 	14 5	; variables
	109	[225]	GETTABLE 	14 14 -34	; "MT"
	110	[225]	LOADK    	15 -35	; "-manifest"
	111	[225]	MOVE     	16 12
	112	[225]	LOADK    	17 -36	; "-outputresource:"
	113	[225]	MOVE     	18 11
	114	[225]	MOVE     	19 6
	115	[225]	LOADK    	20 -37	; ".dll;2"
	116	[225]	CONCAT   	17 17 20
	117	[225]	CALL     	13 5 2
	118	[225]	MOVE     	10 13
	119	[227]	RETURN   	10 2
	120	[228]	RETURN   	0 1

function <./build/builtin.lua:236,241> (32 instructions, 128 bytes at 0x7fd65bc0b230)
4 params, 14 slots, 4 upvalues, 5 locals, 9 constants, 0 functions
	1	[237]	NEWTABLE 	4 0 0
	2	[238]	GETUPVAL 	5 0	; add_flags
	3	[238]	MOVE     	6 4
	4	[238]	LOADK    	7 -1	; "-D%s"
	5	[238]	MOVE     	8 2
	6	[238]	CALL     	5 4 1
	7	[239]	GETUPVAL 	5 0	; add_flags
	8	[239]	MOVE     	6 4
	9	[239]	LOADK    	7 -2	; "-I%s"
	10	[239]	MOVE     	8 3
	11	[239]	CALL     	5 4 1
	12	[240]	GETUPVAL 	5 1	; execute
	13	[240]	GETUPVAL 	6 2	; variables
	14	[240]	GETTABLE 	6 6 -3	; "CC"
	15	[240]	LOADK    	7 -4	; " "
	16	[240]	GETUPVAL 	8 2	; variables
	17	[240]	GETTABLE 	8 8 -5	; "CFLAGS"
	18	[240]	CONCAT   	6 6 8
	19	[240]	LOADK    	7 -6	; "-I"
	20	[240]	GETUPVAL 	8 2	; variables
	21	[240]	GETTABLE 	8 8 -7	; "LUA_INCDIR"
	22	[240]	CONCAT   	7 7 8
	23	[240]	LOADK    	8 -8	; "-c"
	24	[240]	MOVE     	9 1
	25	[240]	LOADK    	10 -9	; "-o"
	26	[240]	MOVE     	11 0
	27	[240]	GETUPVAL 	12 3	; unpack
	28	[240]	MOVE     	13 4
	29	[240]	CALL     	12 2 0
	30	[240]	TAILCALL 	5 0 0
	31	[240]	RETURN   	5 0
	32	[241]	RETURN   	0 1

function <./build/builtin.lua:242,254> (53 instructions, 212 bytes at 0x7fd65bc0b3e0)
4 params, 11 slots, 5 upvalues, 5 locals, 13 constants, 0 functions
	1	[243]	NEWTABLE 	4 0 0
	2	[243]	GETUPVAL 	5 0	; unpack
	3	[243]	MOVE     	6 1
	4	[243]	CALL     	5 2 0
	5	[243]	SETLIST  	4 0 1	; 1
	6	[244]	GETUPVAL 	5 1	; add_flags
	7	[244]	MOVE     	6 4
	8	[244]	LOADK    	7 -1	; "-L%s"
	9	[244]	MOVE     	8 3
	10	[244]	CALL     	5 4 1
	11	[245]	GETUPVAL 	5 2	; cfg
	12	[245]	GETTABLE 	5 5 -2	; "gcc_rpath"
	13	[245]	TEST     	5 0 0
	14	[245]	JMP      	5	; to 20
	15	[246]	GETUPVAL 	5 1	; add_flags
	16	[246]	MOVE     	6 4
	17	[246]	LOADK    	7 -3	; "-Wl,-rpath,%s"
	18	[246]	MOVE     	8 3
	19	[246]	CALL     	5 4 1
	20	[248]	GETUPVAL 	5 1	; add_flags
	21	[248]	MOVE     	6 4
	22	[248]	LOADK    	7 -4	; "-l%s"
	23	[248]	MOVE     	8 2
	24	[248]	CALL     	5 4 1
	25	[249]	GETUPVAL 	5 2	; cfg
	26	[249]	GETTABLE 	5 5 -5	; "link_lua_explicitly"
	27	[249]	TEST     	5 0 0
	28	[249]	JMP      	10	; to 39
	29	[250]	LEN      	5 4
	30	[250]	ADD      	5 5 -6	; - 1
	31	[250]	LOADK    	6 -7	; "-L"
	32	[250]	GETUPVAL 	7 3	; variables
	33	[250]	GETTABLE 	7 7 -8	; "LUA_LIBDIR"
	34	[250]	CONCAT   	6 6 7
	35	[250]	SETTABLE 	4 5 6
	36	[251]	LEN      	5 4
	37	[251]	ADD      	5 5 -6	; - 1
	38	[251]	SETTABLE 	4 5 -9	; - "-llua"
	39	[253]	GETUPVAL 	5 4	; execute
	40	[253]	GETUPVAL 	6 3	; variables
	41	[253]	GETTABLE 	6 6 -10	; "LD"
	42	[253]	LOADK    	7 -11	; " "
	43	[253]	GETUPVAL 	8 3	; variables
	44	[253]	GETTABLE 	8 8 -12	; "LIBFLAG"
	45	[253]	CONCAT   	6 6 8
	46	[253]	LOADK    	7 -13	; "-o"
	47	[253]	MOVE     	8 0
	48	[253]	GETUPVAL 	9 0	; unpack
	49	[253]	MOVE     	10 4
	50	[253]	CALL     	9 2 0
	51	[253]	TAILCALL 	5 0 0
	52	[253]	RETURN   	5 0
	53	[254]	RETURN   	0 1

function <./build/builtin.lua:255,261> (19 instructions, 76 bytes at 0x7fd65bc0bc30)
5 params, 11 slots, 3 upvalues, 6 locals, 3 constants, 0 functions
	1	[256]	GETUPVAL 	5 0	; execute
	2	[256]	GETUPVAL 	6 1	; variables
	3	[256]	GETTABLE 	6 6 -1	; "AR"
	4	[256]	LOADK    	7 -2	; "rc"
	5	[256]	MOVE     	8 0
	6	[256]	GETUPVAL 	9 2	; unpack
	7	[256]	MOVE     	10 1
	8	[256]	CALL     	9 2 0
	9	[256]	CALL     	5 0 2
	10	[257]	TEST     	5 0 0
	11	[257]	JMP      	6	; to 18
	12	[258]	GETUPVAL 	6 0	; execute
	13	[258]	GETUPVAL 	7 1	; variables
	14	[258]	GETTABLE 	7 7 -3	; "RANLIB"
	15	[258]	MOVE     	8 0
	16	[258]	CALL     	6 3 2
	17	[258]	MOVE     	5 6
	18	[260]	RETURN   	5 2
	19	[261]	RETURN   	0 1
