
main <./test/busted.lua:0,0> (34 instructions, 136 bytes at 0x7ff7adc068a0)
0+ params, 8 slots, 0 upvalues, 7 locals, 10 constants, 2 functions
	1	[2]	NEWTABLE 	0 0 0
	2	[4]	GETGLOBAL	1 -1	; require
	3	[4]	LOADK    	2 -2	; "luarocks.fs"
	4	[4]	CALL     	1 2 2
	5	[5]	GETGLOBAL	2 -1	; require
	6	[5]	LOADK    	3 -3	; "luarocks.deps"
	7	[5]	CALL     	2 2 2
	8	[6]	GETGLOBAL	3 -1	; require
	9	[6]	LOADK    	4 -4	; "luarocks.path"
	10	[6]	CALL     	3 2 2
	11	[7]	GETGLOBAL	4 -1	; require
	12	[7]	LOADK    	5 -5	; "luarocks.dir"
	13	[7]	CALL     	4 2 2
	14	[8]	GETGLOBAL	5 -1	; require
	15	[8]	LOADK    	6 -6	; "luarocks.queries"
	16	[8]	CALL     	5 2 2
	17	[10]	GETGLOBAL	6 -7	; table
	18	[10]	GETTABLE 	6 6 -8	; "unpack"
	19	[10]	TEST     	6 0 1
	20	[10]	JMP      	1	; to 22
	21	[10]	GETGLOBAL	6 -8	; unpack
	22	[17]	CLOSURE  	7 0	; 0x7ff7adc06f50
	23	[17]	MOVE     	0 1
	24	[12]	SETTABLE 	0 -9 7	; "detect_type" -
	25	[57]	CLOSURE  	7 1	; 0x7ff7adc070d0
	26	[57]	MOVE     	0 2
	27	[57]	MOVE     	0 5
	28	[57]	MOVE     	0 4
	29	[57]	MOVE     	0 3
	30	[57]	MOVE     	0 1
	31	[57]	MOVE     	0 6
	32	[19]	SETTABLE 	0 -10 7	; "run_tests" -
	33	[60]	RETURN   	0 2
	34	[60]	RETURN   	0 1

function <./test/busted.lua:12,17> (11 instructions, 44 bytes at 0x7ff7adc06f50)
0 params, 2 slots, 1 upvalue, 0 locals, 2 constants, 0 functions
	1	[13]	GETUPVAL 	0 0	; fs
	2	[13]	GETTABLE 	0 0 -1	; "exists"
	3	[13]	LOADK    	1 -2	; ".busted"
	4	[13]	CALL     	0 2 2
	5	[13]	TEST     	0 0 0
	6	[13]	JMP      	2	; to 9
	7	[14]	LOADBOOL 	0 1 0
	8	[14]	RETURN   	0 2
	9	[16]	LOADBOOL 	0 0 0
	10	[16]	RETURN   	0 2
	11	[17]	RETURN   	0 1

function <./test/busted.lua:19,57> (97 instructions, 388 bytes at 0x7ff7adc070d0)
2 params, 14 slots, 6 upvalues, 12 locals, 18 constants, 0 functions
	1	[20]	TEST     	0 0 1
	2	[20]	JMP      	2	; to 5
	3	[21]	NEWTABLE 	2 0 0
	4	[21]	MOVE     	0 2
	5	[24]	GETUPVAL 	2 0	; deps
	6	[24]	GETTABLE 	2 2 -1	; "fulfill_dependency"
	7	[24]	GETUPVAL 	3 1	; queries
	8	[24]	GETTABLE 	3 3 -2	; "new"
	9	[24]	LOADK    	4 -3	; "busted"
	10	[24]	CALL     	3 2 2
	11	[24]	LOADNIL  	4 6
	12	[24]	LOADK    	7 -4	; "test_dependencies"
	13	[24]	CALL     	2 6 4
	14	[25]	TEST     	2 0 1
	15	[25]	JMP      	3	; to 19
	16	[26]	LOADNIL  	5 5
	17	[26]	MOVE     	6 3
	18	[26]	RETURN   	5 3
	19	[29]	LOADNIL  	5 5
	20	[30]	GETTABLE 	6 0 -5	; "busted_executable"
	21	[30]	TEST     	6 0 0
	22	[30]	JMP      	2	; to 25
	23	[31]	GETTABLE 	5 0 -5	; "busted_executable"
	24	[31]	JMP      	34	; to 59
	25	[33]	GETUPVAL 	6 2	; dir
	26	[33]	GETTABLE 	6 6 -6	; "path"
	27	[33]	GETUPVAL 	7 3	; path
	28	[33]	GETTABLE 	7 7 -7	; "root_dir"
	29	[33]	MOVE     	8 4
	30	[33]	CALL     	7 2 2
	31	[33]	LOADK    	8 -8	; "bin"
	32	[33]	LOADK    	9 -3	; "busted"
	33	[33]	CALL     	6 4 2
	34	[33]	MOVE     	5 6
	35	[36]	GETUPVAL 	6 2	; dir
	36	[36]	GETTABLE 	6 6 -6	; "path"
	37	[36]	GETUPVAL 	7 3	; path
	38	[36]	GETTABLE 	7 7 -7	; "root_dir"
	39	[36]	MOVE     	8 4
	40	[36]	CALL     	7 2 2
	41	[36]	LOADK    	8 -8	; "bin"
	42	[36]	LOADK    	9 -9	; "busted.bat"
	43	[36]	CALL     	6 4 2
	44	[38]	GETUPVAL 	7 4	; fs
	45	[38]	GETTABLE 	7 7 -10	; "exists"
	46	[38]	MOVE     	8 5
	47	[38]	CALL     	7 2 2
	48	[38]	TEST     	7 0 1
	49	[38]	JMP      	9	; to 59
	50	[38]	GETUPVAL 	7 4	; fs
	51	[38]	GETTABLE 	7 7 -10	; "exists"
	52	[38]	MOVE     	8 6
	53	[38]	CALL     	7 2 2
	54	[38]	TEST     	7 0 1
	55	[38]	JMP      	3	; to 59
	56	[39]	LOADNIL  	7 7
	57	[39]	LOADK    	8 -11	; "'busted' executable failed to be installed"
	58	[39]	RETURN   	7 3
	59	[43]	GETGLOBAL	6 -12	; type
	60	[43]	GETTABLE 	7 0 -13	; "flags"
	61	[43]	CALL     	6 2 2
	62	[43]	EQ       	0 6 -14	; - "table"
	63	[43]	JMP      	13	; to 77
	64	[45]	LOADK    	6 -15	; 1
	65	[45]	GETTABLE 	7 0 -13	; "flags"
	66	[45]	LEN      	7 7
	67	[45]	LOADK    	8 -15	; 1
	68	[45]	FORPREP  	6 7	; to 76
	69	[46]	GETGLOBAL	10 -14	; table
	70	[46]	GETTABLE 	10 10 -16	; "insert"
	71	[46]	MOVE     	11 1
	72	[46]	MOVE     	12 9
	73	[46]	GETTABLE 	13 0 -13	; "flags"
	74	[46]	GETTABLE 	13 13 9
	75	[46]	CALL     	10 4 1
	76	[45]	FORLOOP  	6 -8	; to 69
	77	[50]	LOADNIL  	6 6
	78	[51]	GETUPVAL 	7 4	; fs
	79	[51]	GETTABLE 	7 7 -17	; "execute"
	80	[51]	MOVE     	8 5
	81	[51]	GETUPVAL 	9 5	; unpack
	82	[51]	MOVE     	10 1
	83	[51]	CALL     	9 2 0
	84	[51]	CALL     	7 0 3
	85	[51]	MOVE     	6 8
	86	[51]	MOVE     	2 7
	87	[52]	TEST     	2 0 0
	88	[52]	JMP      	3	; to 92
	89	[53]	LOADBOOL 	7 1 0
	90	[53]	RETURN   	7 2
	91	[53]	JMP      	5	; to 97
	92	[55]	LOADNIL  	7 7
	93	[55]	TESTSET  	8 6 1
	94	[55]	JMP      	1	; to 96
	95	[55]	LOADK    	8 -18	; "test suite failed."
	96	[55]	RETURN   	7 3
	97	[57]	RETURN   	0 1
