
main <./build/cmake.lua:0,0> (17 instructions, 68 bytes at 0x7fc288c068a0)
0+ params, 5 slots, 0 upvalues, 4 locals, 5 constants, 1 function
	1	[3]	NEWTABLE 	0 0 0
	2	[5]	GETGLOBAL	1 -1	; require
	3	[5]	LOADK    	2 -2	; "luarocks.fs"
	4	[5]	CALL     	1 2 2
	5	[6]	GETGLOBAL	2 -1	; require
	6	[6]	LOADK    	3 -3	; "luarocks.util"
	7	[6]	CALL     	2 2 2
	8	[7]	GETGLOBAL	3 -1	; require
	9	[7]	LOADK    	4 -4	; "luarocks.core.cfg"
	10	[7]	CALL     	3 2 2
	11	[76]	CLOSURE  	4 0	; 0x7fc288c06f50
	12	[76]	MOVE     	0 2
	13	[76]	MOVE     	0 1
	14	[76]	MOVE     	0 3
	15	[13]	SETTABLE 	0 -5 4	; "run" -
	16	[78]	RETURN   	0 2
	17	[78]	RETURN   	0 1

function <./build/cmake.lua:13,76> (175 instructions, 700 bytes at 0x7fc288c06f50)
1 param, 17 slots, 3 upvalues, 14 locals, 49 constants, 0 functions
	1	[14]	GETGLOBAL	1 -1	; assert
	2	[14]	SELF     	2 0 -2	; "type"
	3	[14]	CALL     	2 2 2
	4	[14]	EQ       	1 2 -3	; - "rockspec"
	5	[14]	JMP      	1	; to 7
	6	[14]	LOADBOOL 	2 0 1
	7	[14]	LOADBOOL 	2 1 0
	8	[14]	CALL     	1 2 1
	9	[15]	GETTABLE 	1 0 -4	; "build"
	10	[16]	GETTABLE 	2 1 -5	; "variables"
	11	[16]	TEST     	2 0 1
	12	[16]	JMP      	1	; to 14
	13	[16]	NEWTABLE 	2 0 0
	14	[19]	GETGLOBAL	3 -7	; os
	15	[19]	GETTABLE 	3 3 -8	; "getenv"
	16	[19]	LOADK    	4 -6	; "CMAKE_MODULE_PATH"
	17	[19]	CALL     	3 2 2
	18	[19]	SETTABLE 	2 -6 3	; "CMAKE_MODULE_PATH" -
	19	[20]	GETGLOBAL	3 -7	; os
	20	[20]	GETTABLE 	3 3 -8	; "getenv"
	21	[20]	LOADK    	4 -9	; "CMAKE_LIBRARY_PATH"
	22	[20]	CALL     	3 2 2
	23	[20]	SETTABLE 	2 -9 3	; "CMAKE_LIBRARY_PATH" -
	24	[21]	GETGLOBAL	3 -7	; os
	25	[21]	GETTABLE 	3 3 -8	; "getenv"
	26	[21]	LOADK    	4 -10	; "CMAKE_INCLUDE_PATH"
	27	[21]	CALL     	3 2 2
	28	[21]	SETTABLE 	2 -10 3	; "CMAKE_INCLUDE_PATH" -
	29	[23]	GETUPVAL 	3 0	; util
	30	[23]	GETTABLE 	3 3 -11	; "variable_substitutions"
	31	[23]	MOVE     	4 2
	32	[23]	GETTABLE 	5 0 -5	; "variables"
	33	[23]	CALL     	3 3 1
	34	[25]	GETUPVAL 	3 1	; fs
	35	[25]	GETTABLE 	3 3 -12	; "is_tool_available"
	36	[25]	GETTABLE 	4 0 -5	; "variables"
	37	[25]	GETTABLE 	4 4 -13	; "CMAKE"
	38	[25]	LOADK    	5 -14	; "CMake"
	39	[25]	CALL     	3 3 3
	40	[26]	TEST     	3 0 1
	41	[26]	JMP      	3	; to 45
	42	[27]	LOADNIL  	5 5
	43	[27]	MOVE     	6 4
	44	[27]	RETURN   	5 3
	45	[31]	GETGLOBAL	5 -2	; type
	46	[31]	GETTABLE 	6 1 -15	; "cmake"
	47	[31]	CALL     	5 2 2
	48	[31]	EQ       	0 5 -16	; - "string"
	49	[31]	JMP      	16	; to 66
	50	[32]	GETGLOBAL	5 -1	; assert
	51	[32]	GETGLOBAL	6 -17	; io
	52	[32]	GETTABLE 	6 6 -18	; "open"
	53	[32]	GETUPVAL 	7 1	; fs
	54	[32]	GETTABLE 	7 7 -19	; "current_dir"
	55	[32]	CALL     	7 1 2
	56	[32]	LOADK    	8 -20	; "/CMakeLists.txt"
	57	[32]	CONCAT   	7 7 8
	58	[32]	LOADK    	8 -21	; "w"
	59	[32]	CALL     	6 3 0
	60	[32]	CALL     	5 0 2
	61	[33]	SELF     	6 5 -22	; "write"
	62	[33]	GETTABLE 	8 1 -15	; "cmake"
	63	[33]	CALL     	6 3 1
	64	[34]	SELF     	6 5 -23	; "close"
	65	[34]	CALL     	6 2 1
	66	[38]	LOADK    	5 -24	; ""
	67	[41]	GETUPVAL 	6 2	; cfg
	68	[41]	GETTABLE 	6 6 -25	; "cmake_generator"
	69	[41]	TEST     	6 0 0
	70	[41]	JMP      	7	; to 78
	71	[42]	MOVE     	6 5
	72	[42]	LOADK    	7 -26	; " -G\""
	73	[42]	GETUPVAL 	8 2	; cfg
	74	[42]	GETTABLE 	8 8 -25	; "cmake_generator"
	75	[42]	LOADK    	9 -27	; "\""
	76	[42]	CONCAT   	5 6 9
	77	[42]	JMP      	16	; to 94
	78	[43]	GETUPVAL 	6 2	; cfg
	79	[43]	GETTABLE 	6 6 -28	; "is_platform"
	80	[43]	LOADK    	7 -29	; "windows"
	81	[43]	CALL     	6 2 2
	82	[43]	TEST     	6 0 0
	83	[43]	JMP      	10	; to 94
	84	[43]	GETUPVAL 	6 2	; cfg
	85	[43]	GETTABLE 	6 6 -30	; "target_cpu"
	86	[43]	SELF     	6 6 -31	; "match"
	87	[43]	LOADK    	8 -32	; "x86_64$"
	88	[43]	CALL     	6 3 2
	89	[43]	TEST     	6 0 0
	90	[43]	JMP      	3	; to 94
	91	[44]	MOVE     	6 5
	92	[44]	LOADK    	7 -33	; " -DCMAKE_GENERATOR_PLATFORM=x64"
	93	[44]	CONCAT   	5 6 7
	94	[47]	GETGLOBAL	6 -34	; pairs
	95	[47]	MOVE     	7 2
	96	[47]	CALL     	6 2 4
	97	[47]	JMP      	9	; to 107
	98	[48]	MOVE     	11 5
	99	[48]	LOADK    	12 -35	; " -D"
	100	[48]	MOVE     	13 9
	101	[48]	LOADK    	14 -36	; "=\""
	102	[48]	GETGLOBAL	15 -37	; tostring
	103	[48]	MOVE     	16 10
	104	[48]	CALL     	15 2 2
	105	[48]	LOADK    	16 -27	; "\""
	106	[48]	CONCAT   	5 11 16
	107	[47]	TFORLOOP 	6 2
	108	[48]	JMP      	-11	; to 98
	109	[51]	GETUPVAL 	6 1	; fs
	110	[51]	GETTABLE 	6 6 -38	; "execute_string"
	111	[51]	GETTABLE 	7 0 -5	; "variables"
	112	[51]	GETTABLE 	7 7 -13	; "CMAKE"
	113	[51]	LOADK    	8 -39	; " -H. -Bbuild.luarocks "
	114	[51]	MOVE     	9 5
	115	[51]	CONCAT   	7 7 9
	116	[51]	CALL     	6 2 2
	117	[51]	TEST     	6 0 1
	118	[51]	JMP      	3	; to 122
	119	[52]	LOADNIL  	6 6
	120	[52]	LOADK    	7 -40	; "Failed cmake."
	121	[52]	RETURN   	6 3
	122	[55]	LOADNIL  	6 7
	123	[56]	SELF     	8 0 -41	; "format_is_at_least"
	124	[56]	LOADK    	10 -42	; "3.0"
	125	[56]	CALL     	8 3 2
	126	[56]	TEST     	8 0 0
	127	[56]	JMP      	15	; to 143
	128	[57]	GETTABLE 	8 1 -43	; "build_pass"
	129	[57]	EQ       	0 8 -44	; - nil
	130	[57]	JMP      	3	; to 134
	131	[57]	LOADBOOL 	8 1 0
	132	[57]	TESTSET  	6 8 1
	133	[57]	JMP      	1	; to 135
	134	[57]	GETTABLE 	6 1 -43	; "build_pass"
	135	[58]	GETTABLE 	8 1 -45	; "install_pass"
	136	[58]	EQ       	0 8 -44	; - nil
	137	[58]	JMP      	3	; to 141
	138	[58]	LOADBOOL 	8 1 0
	139	[58]	TESTSET  	7 8 1
	140	[58]	JMP      	1	; to 142
	141	[58]	GETTABLE 	7 1 -45	; "install_pass"
	142	[58]	JMP      	2	; to 145
	143	[60]	LOADBOOL 	6 1 0
	144	[61]	LOADBOOL 	7 1 0
	145	[64]	TEST     	6 0 0
	146	[64]	JMP      	12	; to 159
	147	[65]	GETUPVAL 	8 1	; fs
	148	[65]	GETTABLE 	8 8 -38	; "execute_string"
	149	[65]	GETTABLE 	9 0 -5	; "variables"
	150	[65]	GETTABLE 	9 9 -13	; "CMAKE"
	151	[65]	LOADK    	10 -46	; " --build build.luarocks --config Release"
	152	[65]	CONCAT   	9 9 10
	153	[65]	CALL     	8 2 2
	154	[65]	TEST     	8 0 1
	155	[65]	JMP      	3	; to 159
	156	[66]	LOADNIL  	8 8
	157	[66]	LOADK    	9 -47	; "Failed building."
	158	[66]	RETURN   	8 3
	159	[69]	TEST     	7 0 0
	160	[69]	JMP      	12	; to 173
	161	[70]	GETUPVAL 	8 1	; fs
	162	[70]	GETTABLE 	8 8 -38	; "execute_string"
	163	[70]	GETTABLE 	9 0 -5	; "variables"
	164	[70]	GETTABLE 	9 9 -13	; "CMAKE"
	165	[70]	LOADK    	10 -48	; " --build build.luarocks --target install --config Release"
	166	[70]	CONCAT   	9 9 10
	167	[70]	CALL     	8 2 2
	168	[70]	TEST     	8 0 1
	169	[70]	JMP      	3	; to 173
	170	[71]	LOADNIL  	8 8
	171	[71]	LOADK    	9 -49	; "Failed installing."
	172	[71]	RETURN   	8 3
	173	[75]	LOADBOOL 	8 1 0
	174	[75]	RETURN   	8 2
	175	[76]	RETURN   	0 1
