-- BYTECODE -- dir.lua:15-20
0001    GGET     1   0      ; "assert"
0002    GGET     2   1      ; "type"
0003    MOV      3   0
0004    CALL     2   2   2
0005    ISEQS    2   2      ; "string"
0006    JMP      2 => 0009
0007    KPRI     2   1
0008    JMP      3 => 0010
0009 => KPRI     2   2
0010 => CALL     1   1   2
0011    MOV      2   0
0012    TGETS    1   0   3  ; "gsub"
0013    KSTR     3   4      ; "[/\]*$"
0014    KSTR     4   5      ; ""
0015    CALL     1   2   4
0016    MOV      2   1
0017    TGETS    1   1   6  ; "match"
0018    KSTR     3   7      ; ".*[/\]([^/\]*)"
0019    CALL     1   2   3
0020    ISTC     2   1
0021    JMP      2 => 0023
0022    MOV      2   0
0023 => RET1     2   2

-- BYTECODE -- dir.lua:27-30
0001    GGET     1   0      ; "assert"
0002    GGET     2   1      ; "type"
0003    MOV      3   0
0004    CALL     2   2   2
0005    ISEQS    2   2      ; "string"
0006    JMP      2 => 0009
0007    KPRI     2   1
0008    JMP      3 => 0010
0009 => KPRI     2   2
0010 => CALL     1   1   2
0011    MOV      2   0
0012    TGETS    1   0   3  ; "gsub"
0013    KSTR     3   4      ; "/*$"
0014    KSTR     4   5      ; ""
0015    CALL     1   2   4
0016    MOV      2   1
0017    TGETS    1   1   6  ; "match"
0018    KSTR     3   7      ; "(.*)[/]+[^/]*"
0019    CALL     1   2   3
0020    IST          1
0021    JMP      2 => 0023
0022    KSTR     1   5      ; ""
0023 => RET1     1   2

-- BYTECODE -- dir.lua:34-36
0001    ISEQS    0   0      ; "http"
0002    JMP      1 => 0011
0003    ISEQS    0   1      ; "https"
0004    JMP      1 => 0011
0005    ISEQS    0   2      ; "ftp"
0006    JMP      1 => 0011
0007    ISEQS    0   3      ; "file"
0008    JMP      1 => 0011
0009    KPRI     1   1
0010    JMP      2 => 0012
0011 => KPRI     1   2
0012 => RET1     1   2

-- BYTECODE -- dir.lua:38-46
0001    TNEW     1   0
0002    GGET     2   0      ; "ipairs"
0003    TDUP     3   1
0004    CALL     2   4   2
0005    JMP      5 => 0008
0006 => KSTR     7   2      ; ""
0007    TSETV    7   1   6
0008 => ITERC    5   3   3
0009    ITERL    5 => 0006
0010    UGET     2   0      ; dir
0011    TGETS    2   2   3  ; "base_name"
0012    MOV      3   0
0013    CALL     2   2   2
0014    MOV      4   2
0015    TGETS    3   2   4  ; "gsub"
0016    KSTR     5   5      ; "%.([^.]*)$"
0017    MOV      6   1
0018    CALL     3   2   4
0019    MOV      4   3
0020    TGETS    3   3   4  ; "gsub"
0021    KSTR     5   6      ; "%.tar"
0022    KSTR     6   2      ; ""
0023    CALL     3   2   4
0024    RET1     3   2

-- BYTECODE -- dir.lua:0-49
0001    TNEW     0   0
0002    GGET     1   0      ; "require"
0003    KSTR     2   1      ; "luarocks.core.dir"
0004    CALL     1   2   2
0005    TGETS    2   1   2  ; "path"
0006    TSETS    2   0   2  ; "path"
0007    TGETS    2   1   3  ; "split_url"
0008    TSETS    2   0   3  ; "split_url"
0009    TGETS    2   1   4  ; "normalize"
0010    TSETS    2   0   4  ; "normalize"
0011    FNEW     2   6      ; dir.lua:15
0012    TSETS    2   0   5  ; "base_name"
0013    FNEW     2   8      ; dir.lua:27
0014    TSETS    2   0   7  ; "dir_name"
0015    FNEW     2  10      ; dir.lua:34
0016    TSETS    2   0   9  ; "is_basic_protocol"
0017    FNEW     2  12      ; dir.lua:38
0018    TSETS    2   0  11  ; "deduce_base_dir"
0019    UCLO     0 => 0020
0020 => RET1     0   2

