
main <./dir.lua:0,0> (21 instructions, 84 bytes at 0x7fac194068a0)
0+ params, 3 slots, 0 upvalues, 2 locals, 9 constants, 4 functions
	1	[3]	NEWTABLE 	0 0 0
	2	[5]	GETGLOBAL	1 -1	; require
	3	[5]	LOADK    	2 -2	; "luarocks.core.dir"
	4	[5]	CALL     	1 2 2
	5	[7]	GETTABLE 	2 1 -3	; "path"
	6	[7]	SETTABLE 	0 -3 2	; "path" -
	7	[8]	GETTABLE 	2 1 -4	; "split_url"
	8	[8]	SETTABLE 	0 -4 2	; "split_url" -
	9	[9]	GETTABLE 	2 1 -5	; "normalize"
	10	[9]	SETTABLE 	0 -5 2	; "normalize" -
	11	[20]	CLOSURE  	2 0	; 0x7fac19406bd0
	12	[15]	SETTABLE 	0 -6 2	; "base_name" -
	13	[30]	CLOSURE  	2 1	; 0x7fac19407210
	14	[27]	SETTABLE 	0 -7 2	; "dir_name" -
	15	[36]	CLOSURE  	2 2	; 0x7fac19407630
	16	[34]	SETTABLE 	0 -8 2	; "is_basic_protocol" -
	17	[46]	CLOSURE  	2 3	; 0x7fac19406cd0
	18	[46]	MOVE     	0 0
	19	[38]	SETTABLE 	0 -9 2	; "deduce_base_dir" -
	20	[48]	RETURN   	0 2
	21	[48]	RETURN   	0 1

function <./dir.lua:15,20> (21 instructions, 84 bytes at 0x7fac19406bd0)
1 param, 5 slots, 0 upvalues, 2 locals, 8 constants, 0 functions
	1	[16]	GETGLOBAL	1 -1	; assert
	2	[16]	GETGLOBAL	2 -2	; type
	3	[16]	MOVE     	3 0
	4	[16]	CALL     	2 2 2
	5	[16]	EQ       	1 2 -3	; - "string"
	6	[16]	JMP      	1	; to 8
	7	[16]	LOADBOOL 	2 0 1
	8	[16]	LOADBOOL 	2 1 0
	9	[16]	CALL     	1 2 1
	10	[18]	SELF     	1 0 -4	; "gsub"
	11	[18]	LOADK    	3 -5	; "[/\\]*$"
	12	[18]	LOADK    	4 -6	; ""
	13	[18]	CALL     	1 4 2
	14	[18]	SELF     	1 1 -7	; "match"
	15	[18]	LOADK    	3 -8	; ".*[/\\]([^/\\]*)"
	16	[18]	CALL     	1 3 2
	17	[19]	TESTSET  	2 1 1
	18	[19]	JMP      	1	; to 20
	19	[19]	MOVE     	2 0
	20	[19]	RETURN   	2 2
	21	[20]	RETURN   	0 1

function <./dir.lua:27,30> (21 instructions, 84 bytes at 0x7fac19407210)
1 param, 5 slots, 0 upvalues, 1 local, 8 constants, 0 functions
	1	[28]	GETGLOBAL	1 -1	; assert
	2	[28]	GETGLOBAL	2 -2	; type
	3	[28]	MOVE     	3 0
	4	[28]	CALL     	2 2 2
	5	[28]	EQ       	1 2 -3	; - "string"
	6	[28]	JMP      	1	; to 8
	7	[28]	LOADBOOL 	2 0 1
	8	[28]	LOADBOOL 	2 1 0
	9	[28]	CALL     	1 2 1
	10	[29]	SELF     	1 0 -4	; "gsub"
	11	[29]	LOADK    	3 -5	; "/*$"
	12	[29]	LOADK    	4 -6	; ""
	13	[29]	CALL     	1 4 2
	14	[29]	SELF     	1 1 -7	; "match"
	15	[29]	LOADK    	3 -8	; "(.*)[/]+[^/]*"
	16	[29]	CALL     	1 3 2
	17	[29]	TEST     	1 0 1
	18	[29]	JMP      	1	; to 20
	19	[29]	LOADK    	1 -6	; ""
	20	[29]	RETURN   	1 2
	21	[30]	RETURN   	0 1

function <./dir.lua:34,36> (12 instructions, 48 bytes at 0x7fac19407630)
1 param, 2 slots, 0 upvalues, 1 local, 4 constants, 0 functions
	1	[35]	EQ       	1 0 -1	; - "http"
	2	[35]	JMP      	7	; to 10
	3	[35]	EQ       	1 0 -2	; - "https"
	4	[35]	JMP      	5	; to 10
	5	[35]	EQ       	1 0 -3	; - "ftp"
	6	[35]	JMP      	3	; to 10
	7	[35]	EQ       	1 0 -4	; - "file"
	8	[35]	JMP      	1	; to 10
	9	[35]	LOADBOOL 	1 0 1
	10	[35]	LOADBOOL 	1 1 0
	11	[35]	RETURN   	1 2
	12	[36]	RETURN   	0 1

function <./dir.lua:38,46> (29 instructions, 116 bytes at 0x7fac19406cd0)
1 param, 10 slots, 1 upvalue, 8 locals, 12 constants, 0 functions
	1	[40]	NEWTABLE 	1 0 0
	2	[41]	GETGLOBAL	2 -1	; ipairs
	3	[41]	NEWTABLE 	3 6 0
	4	[41]	LOADK    	4 -2	; "zip"
	5	[41]	LOADK    	5 -3	; "git"
	6	[41]	LOADK    	6 -4	; "tgz"
	7	[41]	LOADK    	7 -5	; "tar"
	8	[41]	LOADK    	8 -6	; "gz"
	9	[41]	LOADK    	9 -7	; "bz2"
	10	[41]	SETLIST  	3 6 1	; 1
	11	[41]	CALL     	2 2 4
	12	[41]	JMP      	1	; to 14
	13	[42]	SETTABLE 	1 6 -8	; - ""
	14	[41]	TFORLOOP 	2 2
	15	[42]	JMP      	-3	; to 13
	16	[44]	GETUPVAL 	2 0	; dir
	17	[44]	GETTABLE 	2 2 -9	; "base_name"
	18	[44]	MOVE     	3 0
	19	[44]	CALL     	2 2 2
	20	[45]	SELF     	3 2 -10	; "gsub"
	21	[45]	LOADK    	5 -11	; "%.([^.]*)$"
	22	[45]	MOVE     	6 1
	23	[45]	CALL     	3 4 2
	24	[45]	SELF     	3 3 -10	; "gsub"
	25	[45]	LOADK    	5 -12	; "%.tar"
	26	[45]	LOADK    	6 -8	; ""
	27	[45]	CALL     	3 4 2
	28	[45]	RETURN   	3 2
	29	[46]	RETURN   	0 1
