
main <./download.lua:0,0> (35 instructions, 140 bytes at 0x7f88c8c068a0)
0+ params, 10 slots, 0 upvalues, 9 locals, 9 constants, 2 functions
	1	[1]	NEWTABLE 	0 0 0
	2	[3]	GETGLOBAL	1 -1	; require
	3	[3]	LOADK    	2 -2	; "luarocks.path"
	4	[3]	CALL     	1 2 2
	5	[4]	GETGLOBAL	2 -1	; require
	6	[4]	LOADK    	3 -3	; "luarocks.fetch"
	7	[4]	CALL     	2 2 2
	8	[5]	GETGLOBAL	3 -1	; require
	9	[5]	LOADK    	4 -4	; "luarocks.search"
	10	[5]	CALL     	3 2 2
	11	[6]	GETGLOBAL	4 -1	; require
	12	[6]	LOADK    	5 -5	; "luarocks.queries"
	13	[6]	CALL     	4 2 2
	14	[7]	GETGLOBAL	5 -1	; require
	15	[7]	LOADK    	6 -6	; "luarocks.fs"
	16	[7]	CALL     	5 2 2
	17	[8]	GETGLOBAL	6 -1	; require
	18	[8]	LOADK    	7 -7	; "luarocks.dir"
	19	[8]	CALL     	6 2 2
	20	[9]	GETGLOBAL	7 -1	; require
	21	[9]	LOADK    	8 -8	; "luarocks.util"
	22	[9]	CALL     	7 2 2
	23	[23]	CLOSURE  	8 0	; 0x7f88c8c06c20
	24	[23]	MOVE     	0 6
	25	[23]	MOVE     	0 5
	26	[23]	MOVE     	0 2
	27	[64]	CLOSURE  	9 1	; 0x7f88c8c06f60
	28	[64]	MOVE     	0 4
	29	[64]	MOVE     	0 3
	30	[64]	MOVE     	0 1
	31	[64]	MOVE     	0 8
	32	[64]	MOVE     	0 7
	33	[25]	SETTABLE 	0 -9 9	; "download" -
	34	[66]	RETURN   	0 2
	35	[66]	RETURN   	0 1

function <./download.lua:11,23> (28 instructions, 112 bytes at 0x7f88c8c06c20)
1 param, 7 slots, 3 upvalues, 5 locals, 6 constants, 0 functions
	1	[12]	GETUPVAL 	1 0	; dir
	2	[12]	GETTABLE 	1 1 -1	; "split_url"
	3	[12]	MOVE     	2 0
	4	[12]	CALL     	1 2 3
	5	[13]	EQ       	0 1 -2	; - "file"
	6	[13]	JMP      	16	; to 23
	7	[14]	GETUPVAL 	3 1	; fs
	8	[14]	GETTABLE 	3 3 -3	; "copy"
	9	[14]	MOVE     	4 2
	10	[14]	GETUPVAL 	5 1	; fs
	11	[14]	GETTABLE 	5 5 -4	; "current_dir"
	12	[14]	CALL     	5 1 2
	13	[14]	LOADK    	6 -5	; "read"
	14	[14]	CALL     	3 4 3
	15	[15]	TEST     	3 0 0
	16	[15]	JMP      	2	; to 19
	17	[16]	RETURN   	2 2
	18	[16]	JMP      	9	; to 28
	19	[18]	LOADNIL  	5 5
	20	[18]	MOVE     	6 4
	21	[18]	RETURN   	5 3
	22	[19]	JMP      	5	; to 28
	23	[21]	GETUPVAL 	3 2	; fetch
	24	[21]	GETTABLE 	3 3 -6	; "fetch_url"
	25	[21]	MOVE     	4 0
	26	[21]	TAILCALL 	3 2 0
	27	[21]	RETURN   	3 0
	28	[23]	RETURN   	0 1

function <./download.lua:25,64> (103 instructions, 412 bytes at 0x7f88c8c06f60)
6 params, 34 slots, 5 upvalues, 33 locals, 15 constants, 0 functions
	1	[26]	TESTSET  	6 4 0
	2	[26]	JMP      	4	; to 7
	3	[26]	EQ       	1 1 -1	; - ""
	4	[26]	JMP      	1	; to 6
	5	[26]	LOADBOOL 	6 0 1
	6	[26]	LOADBOOL 	6 1 0
	7	[27]	GETUPVAL 	7 0	; queries
	8	[27]	GETTABLE 	7 7 -2	; "new"
	9	[27]	MOVE     	8 1
	10	[27]	MOVE     	9 2
	11	[27]	MOVE     	10 3
	12	[27]	MOVE     	11 6
	13	[27]	MOVE     	12 0
	14	[27]	CALL     	7 6 2
	15	[28]	LOADNIL  	8 8
	16	[30]	TEST     	4 0 0
	17	[30]	JMP      	52	; to 70
	18	[31]	GETUPVAL 	9 1	; search
	19	[31]	GETTABLE 	9 9 -3	; "search_repos"
	20	[31]	MOVE     	10 7
	21	[31]	CALL     	9 2 2
	22	[32]	LOADBOOL 	10 0 0
	23	[33]	LOADBOOL 	11 1 0
	24	[34]	LOADK    	12 -1	; ""
	25	[35]	GETGLOBAL	13 -4	; pairs
	26	[35]	MOVE     	14 9
	27	[35]	CALL     	13 2 4
	28	[35]	JMP      	33	; to 62
	29	[36]	GETGLOBAL	18 -4	; pairs
	30	[36]	MOVE     	19 17
	31	[36]	CALL     	18 2 4
	32	[36]	JMP      	27	; to 60
	33	[37]	GETGLOBAL	23 -5	; ipairs
	34	[37]	MOVE     	24 22
	35	[37]	CALL     	23 2 4
	36	[37]	JMP      	21	; to 58
	37	[39]	GETTABLE 	28 27 -6	; "arch"
	38	[39]	EQ       	1 28 -7	; - "installed"
	39	[39]	JMP      	18	; to 58
	40	[40]	LOADBOOL 	10 1 0
	41	[41]	GETUPVAL 	28 2	; path
	42	[41]	GETTABLE 	28 28 -8	; "make_url"
	43	[41]	GETTABLE 	29 27 -9	; "repo"
	44	[41]	MOVE     	30 16
	45	[41]	MOVE     	31 21
	46	[41]	GETTABLE 	32 27 -6	; "arch"
	47	[41]	CALL     	28 5 2
	48	[42]	GETUPVAL 	29 3	; get_file
	49	[42]	MOVE     	30 28
	50	[42]	CALL     	29 2 3
	51	[43]	TEST     	29 0 1
	52	[43]	JMP      	5	; to 58
	53	[44]	LOADBOOL 	11 0 0
	54	[45]	MOVE     	31 12
	55	[45]	LOADK    	32 -10	; "\n"
	56	[45]	MOVE     	33 30
	57	[45]	CONCAT   	12 31 33
	58	[37]	TFORLOOP 	23 2
	59	[47]	JMP      	-23	; to 37
	60	[36]	TFORLOOP 	18 2
	61	[48]	JMP      	-29	; to 33
	62	[35]	TFORLOOP 	13 2
	63	[49]	JMP      	-35	; to 29
	64	[52]	TEST     	10 0 0
	65	[52]	JMP      	18	; to 84
	66	[53]	MOVE     	13 11
	67	[53]	MOVE     	14 12
	68	[53]	RETURN   	13 3
	69	[54]	JMP      	14	; to 84
	70	[56]	LOADNIL  	9 9
	71	[57]	GETUPVAL 	10 1	; search
	72	[57]	GETTABLE 	10 10 -11	; "find_rock_checking_lua_versions"
	73	[57]	MOVE     	11 7
	74	[57]	MOVE     	12 5
	75	[57]	CALL     	10 3 3
	76	[57]	MOVE     	8 11
	77	[57]	MOVE     	9 10
	78	[58]	TEST     	9 0 0
	79	[58]	JMP      	4	; to 84
	80	[59]	GETUPVAL 	10 3	; get_file
	81	[59]	MOVE     	11 9
	82	[59]	TAILCALL 	10 2 0
	83	[59]	RETURN   	10 0
	84	[62]	GETUPVAL 	9 4	; util
	85	[62]	GETTABLE 	9 9 -12	; "format_rock_name"
	86	[62]	MOVE     	10 1
	87	[62]	MOVE     	11 2
	88	[62]	MOVE     	12 3
	89	[62]	CALL     	9 4 2
	90	[63]	LOADNIL  	10 10
	91	[63]	LOADK    	11 -13	; "Could not find a result named "
	92	[63]	MOVE     	12 9
	93	[63]	TEST     	8 0 0
	94	[63]	JMP      	5	; to 100
	95	[63]	LOADK    	13 -14	; ": "
	96	[63]	MOVE     	14 8
	97	[63]	CONCAT   	13 13 14
	98	[63]	TEST     	13 0 1
	99	[63]	JMP      	1	; to 101
	100	[63]	LOADK    	13 -15	; "."
	101	[63]	CONCAT   	11 11 13
	102	[63]	RETURN   	10 3
	103	[64]	RETURN   	0 1
