-- BYTECODE -- download.lua:11-23
0001    UGET     1   0      ; dir
0002    TGETS    1   1   0  ; "split_url"
0003    MOV      2   0
0004    CALL     1   3   2
0005    ISNES    1   1      ; "file"
0006    JMP      3 => 0023
0007    UGET     3   1      ; fs
0008    TGETS    3   3   2  ; "copy"
0009    MOV      4   2
0010    UGET     5   1      ; fs
0011    TGETS    5   5   3  ; "current_dir"
0012    CALL     5   2   1
0013    KSTR     6   4      ; "read"
0014    CALL     3   3   4
0015    ISF          3
0016    JMP      5 => 0019
0017    RET1     2   2
0018    JMP      5 => 0027
0019 => KPRI     5   0
0020    MOV      6   4
0021    RET      5   3
0022    JMP      3 => 0027
0023 => UGET     3   2      ; fetch
0024    TGETS    3   3   5  ; "fetch_url"
0025    MOV      4   0
0026    CALLT    3   2
0027 => RET0     0   1

-- BYTECODE -- download.lua:25-64
0001    ISFC     6   4
0002    JMP      6 => 0008
0003    ISEQS    1   0      ; ""
0004    JMP      6 => 0007
0005    KPRI     6   1
0006    JMP      7 => 0008
0007 => KPRI     6   2
0008 => UGET     7   0      ; queries
0009    TGETS    7   7   1  ; "new"
0010    MOV      8   1
0011    MOV      9   2
0012    MOV     10   3
0013    MOV     11   6
0014    MOV     12   0
0015    CALL     7   2   6
0016    KPRI     8   0
0017    ISF          4
0018    JMP      9 => 0071
0019    UGET     9   1      ; search
0020    TGETS    9   9   2  ; "search_repos"
0021    MOV     10   7
0022    CALL     9   2   2
0023    KPRI    10   1
0024    KPRI    11   2
0025    KSTR    12   0      ; ""
0026    GGET    13   3      ; "pairs"
0027    MOV     14   9
0028    CALL    13   4   2
0029    ISNEXT  16 => 0063
0030 => GGET    18   3      ; "pairs"
0031    MOV     19  17
0032    CALL    18   4   2
0033    ISNEXT  21 => 0061
0034 => GGET    23   4      ; "ipairs"
0035    MOV     24  22
0036    CALL    23   4   2
0037    JMP     26 => 0059
0038 => TGETS   28  27   5  ; "arch"
0039    ISEQS   28   6      ; "installed"
0040    JMP     28 => 0059
0041    KPRI    10   2
0042    UGET    28   2      ; path
0043    TGETS   28  28   7  ; "make_url"
0044    TGETS   29  27   8  ; "repo"
0045    MOV     30  16
0046    MOV     31  21
0047    TGETS   32  27   5  ; "arch"
0048    CALL    28   2   5
0049    UGET    29   3      ; get_file
0050    MOV     30  28
0051    CALL    29   3   2
0052    IST         29
0053    JMP     31 => 0059
0054    KPRI    11   1
0055    MOV     31  12
0056    KSTR    32   9      ; "\n"
0057    MOV     33  30
0058    CAT     12  31  33
0059 => ITERC   26   3   3
0060    ITERL   26 => 0038
0061 => ITERN   21   3   3
0062    ITERL   21 => 0034
0063 => ITERN   16   3   3
0064    ITERL   16 => 0030
0065    ISF         10
0066    JMP     13 => 0084
0067    MOV     13  11
0068    MOV     14  12
0069    RET     13   3
0070    JMP      9 => 0084
0071 => KPRI     9   0
0072    UGET    10   1      ; search
0073    TGETS   10  10  10  ; "find_rock_checking_lua_versions"
0074    MOV     11   7
0075    MOV     12   5
0076    CALL    10   3   3
0077    MOV      8  11
0078    MOV      9  10
0079    ISF          9
0080    JMP     10 => 0084
0081    UGET    10   3      ; get_file
0082    MOV     11   9
0083    CALLT   10   2
0084 => UGET     9   4      ; util
0085    TGETS    9   9  11  ; "format_rock_name"
0086    MOV     10   1
0087    MOV     11   2
0088    MOV     12   3
0089    CALL     9   2   4
0090    KPRI    10   0
0091    KSTR    11  12      ; "Could not find a result named "
0092    MOV     12   9
0093    ISF          8
0094    JMP     13 => 0100
0095    KSTR    13  13      ; ": "
0096    MOV     14   8
0097    CAT     13  13  14
0098    IST         13
0099    JMP     14 => 0101
0100 => KSTR    13  14      ; "."
0101 => CAT     11  11  13
0102    RET     10   3

-- BYTECODE -- download.lua:0-67
0001    TNEW     0   0
0002    GGET     1   0      ; "require"
0003    KSTR     2   1      ; "luarocks.path"
0004    CALL     1   2   2
0005    GGET     2   0      ; "require"
0006    KSTR     3   2      ; "luarocks.fetch"
0007    CALL     2   2   2
0008    GGET     3   0      ; "require"
0009    KSTR     4   3      ; "luarocks.search"
0010    CALL     3   2   2
0011    GGET     4   0      ; "require"
0012    KSTR     5   4      ; "luarocks.queries"
0013    CALL     4   2   2
0014    GGET     5   0      ; "require"
0015    KSTR     6   5      ; "luarocks.fs"
0016    CALL     5   2   2
0017    GGET     6   0      ; "require"
0018    KSTR     7   6      ; "luarocks.dir"
0019    CALL     6   2   2
0020    GGET     7   0      ; "require"
0021    KSTR     8   7      ; "luarocks.util"
0022    CALL     7   2   2
0023    FNEW     8   8      ; download.lua:11
0024    FNEW     9  10      ; download.lua:25
0025    TSETS    9   0   9  ; "download"
0026    UCLO     0 => 0027
0027 => RET1     0   2

