
main <./fetch.lua:0,0> (77 instructions, 308 bytes at 0x7fb5b6c068a0)
0+ params, 10 slots, 0 upvalues, 9 locals, 17 constants, 10 functions
	1	[3]	NEWTABLE 	0 0 0
	2	[5]	GETGLOBAL	1 -1	; require
	3	[5]	LOADK    	2 -2	; "luarocks.fs"
	4	[5]	CALL     	1 2 2
	5	[6]	GETGLOBAL	2 -1	; require
	6	[6]	LOADK    	3 -3	; "luarocks.dir"
	7	[6]	CALL     	2 2 2
	8	[7]	GETGLOBAL	3 -1	; require
	9	[7]	LOADK    	4 -4	; "luarocks.rockspecs"
	10	[7]	CALL     	3 2 2
	11	[8]	GETGLOBAL	4 -1	; require
	12	[8]	LOADK    	5 -5	; "luarocks.signing"
	13	[8]	CALL     	4 2 2
	14	[9]	GETGLOBAL	5 -1	; require
	15	[9]	LOADK    	6 -6	; "luarocks.persist"
	16	[9]	CALL     	5 2 2
	17	[10]	GETGLOBAL	6 -1	; require
	18	[10]	LOADK    	7 -7	; "luarocks.util"
	19	[10]	CALL     	6 2 2
	20	[11]	GETGLOBAL	7 -1	; require
	21	[11]	LOADK    	8 -8	; "luarocks.core.cfg"
	22	[11]	CALL     	7 2 2
	23	[38]	CLOSURE  	8 0	; 0x7fb5b6c06f80
	24	[38]	MOVE     	0 2
	25	[38]	MOVE     	0 7
	26	[38]	MOVE     	0 1
	27	[38]	MOVE     	0 0
	28	[13]	SETTABLE 	0 -9 8	; "fetch_caching" -
	29	[77]	CLOSURE  	8 1	; 0x7fb5b6c07210
	30	[77]	MOVE     	0 2
	31	[77]	MOVE     	0 1
	32	[61]	SETTABLE 	0 -10 8	; "fetch_url" -
	33	[133]	CLOSURE  	8 2	; 0x7fb5b6c07cc0
	34	[133]	MOVE     	0 2
	35	[133]	MOVE     	0 1
	36	[133]	MOVE     	0 6
	37	[133]	MOVE     	0 0
	38	[90]	SETTABLE 	0 -11 8	; "fetch_url_at_temp_dir" -
	39	[171]	CLOSURE  	8 3	; 0x7fb5b6c07080
	40	[171]	MOVE     	0 1
	41	[171]	MOVE     	0 2
	42	[171]	MOVE     	0 6
	43	[147]	SETTABLE 	0 -12 8	; "find_base_dir" -
	44	[186]	CLOSURE  	8 4	; 0x7fb5b6c06c10
	45	[186]	MOVE     	0 4
	46	[186]	MOVE     	0 0
	47	[186]	MOVE     	0 1
	48	[249]	CLOSURE  	9 5	; 0x7fb5b6c09610
	49	[249]	MOVE     	0 2
	50	[249]	MOVE     	0 0
	51	[249]	MOVE     	0 8
	52	[249]	MOVE     	0 1
	53	[249]	MOVE     	0 6
	54	[197]	SETTABLE 	0 -13 9	; "fetch_and_unpack_rock" -
	55	[285]	CLOSURE  	9 6	; 0x7fb5b6c0a090
	56	[285]	MOVE     	0 1
	57	[285]	MOVE     	0 2
	58	[285]	MOVE     	0 5
	59	[285]	MOVE     	0 3
	60	[258]	SETTABLE 	0 -14 9	; "load_local_rockspec" -
	61	[333]	CLOSURE  	9 7	; 0x7fb5b6c0a300
	62	[333]	MOVE     	0 2
	63	[333]	MOVE     	0 1
	64	[333]	MOVE     	0 0
	65	[333]	MOVE     	0 8
	66	[297]	SETTABLE 	0 -15 9	; "load_rockspec" -
	67	[403]	CLOSURE  	9 8	; 0x7fb5b6c0ae90
	68	[403]	MOVE     	0 1
	69	[403]	MOVE     	0 0
	70	[344]	SETTABLE 	0 -16 9	; "get_sources" -
	71	[440]	CLOSURE  	9 9	; 0x7fb5b6c088e0
	72	[440]	MOVE     	0 2
	73	[440]	MOVE     	0 0
	74	[440]	MOVE     	0 7
	75	[414]	SETTABLE 	0 -17 9	; "fetch_sources" -
	76	[442]	RETURN   	0 2
	77	[442]	RETURN   	0 1

function <./fetch.lua:13,38> (100 instructions, 400 bytes at 0x7fb5b6c06f80)
1 param, 16 slots, 4 upvalues, 11 locals, 19 constants, 0 functions
	1	[14]	SELF     	1 0 -1	; "match"
	2	[14]	LOADK    	3 -2	; "^(.*)/([^/]+)$"
	3	[14]	CALL     	1 3 3
	4	[15]	SELF     	3 1 -3	; "gsub"
	5	[15]	LOADK    	5 -4	; "[/:]"
	6	[15]	LOADK    	6 -5	; "_"
	7	[15]	CALL     	3 4 2
	8	[16]	GETUPVAL 	4 0	; dir
	9	[16]	GETTABLE 	4 4 -6	; "path"
	10	[16]	GETUPVAL 	5 1	; cfg
	11	[16]	GETTABLE 	5 5 -7	; "local_cache"
	12	[16]	MOVE     	6 3
	13	[16]	CALL     	4 3 2
	14	[17]	GETUPVAL 	5 2	; fs
	15	[17]	GETTABLE 	5 5 -8	; "make_dir"
	16	[17]	MOVE     	6 4
	17	[17]	CALL     	5 2 2
	18	[18]	TEST     	5 0 1
	19	[18]	JMP      	25	; to 45
	20	[19]	GETUPVAL 	6 1	; cfg
	21	[19]	GETUPVAL 	7 2	; fs
	22	[19]	GETTABLE 	7 7 -9	; "make_temp_dir"
	23	[19]	LOADK    	8 -7	; "local_cache"
	24	[19]	CALL     	7 2 2
	25	[19]	SETTABLE 	6 -7 7	; "local_cache" -
	26	[20]	GETUPVAL 	6 0	; dir
	27	[20]	GETTABLE 	6 6 -6	; "path"
	28	[20]	GETUPVAL 	7 1	; cfg
	29	[20]	GETTABLE 	7 7 -7	; "local_cache"
	30	[20]	MOVE     	8 3
	31	[20]	CALL     	6 3 2
	32	[20]	MOVE     	4 6
	33	[21]	GETUPVAL 	6 2	; fs
	34	[21]	GETTABLE 	6 6 -8	; "make_dir"
	35	[21]	MOVE     	7 4
	36	[21]	CALL     	6 2 2
	37	[21]	MOVE     	5 6
	38	[22]	TEST     	5 0 1
	39	[22]	JMP      	5	; to 45
	40	[23]	LOADNIL  	6 6
	41	[23]	LOADK    	7 -10	; "Failed creating temporary cache directory "
	42	[23]	MOVE     	8 4
	43	[23]	CONCAT   	7 7 8
	44	[23]	RETURN   	6 3
	45	[27]	GETUPVAL 	6 0	; dir
	46	[27]	GETTABLE 	6 6 -6	; "path"
	47	[27]	MOVE     	7 4
	48	[27]	MOVE     	8 2
	49	[27]	CALL     	6 3 2
	50	[28]	GETUPVAL 	7 1	; cfg
	51	[28]	GETTABLE 	7 7 -11	; "aggressive_cache"
	52	[28]	TEST     	7 0 0
	53	[28]	JMP      	20	; to 74
	54	[28]	SELF     	7 3 -1	; "match"
	55	[28]	LOADK    	9 -12	; "^manifest"
	56	[28]	CALL     	7 3 2
	57	[28]	TEST     	7 0 1
	58	[28]	JMP      	15	; to 74
	59	[28]	GETUPVAL 	7 2	; fs
	60	[28]	GETTABLE 	7 7 -13	; "exists"
	61	[28]	MOVE     	8 6
	62	[28]	CALL     	7 2 2
	63	[28]	TEST     	7 0 0
	64	[28]	JMP      	9	; to 74
	65	[29]	GETGLOBAL	7 -14	; print
	66	[29]	LOADK    	8 -15	; "FAST TRACK!"
	67	[29]	GETUPVAL 	9 1	; cfg
	68	[29]	GETTABLE 	9 9 -11	; "aggressive_cache"
	69	[29]	CALL     	7 3 1
	70	[30]	MOVE     	7 6
	71	[30]	LOADNIL  	8 9
	72	[30]	LOADBOOL 	10 1 0
	73	[30]	RETURN   	7 5
	74	[33]	GETUPVAL 	7 3	; fetch
	75	[33]	GETTABLE 	7 7 -16	; "fetch_url"
	76	[33]	MOVE     	8 0
	77	[33]	MOVE     	9 6
	78	[33]	LOADBOOL 	10 1 0
	79	[33]	CALL     	7 4 5
	80	[34]	TEST     	7 0 1
	81	[34]	JMP      	14	; to 96
	82	[35]	LOADNIL  	11 11
	83	[35]	LOADK    	12 -17	; "Failed downloading "
	84	[35]	MOVE     	13 1
	85	[35]	TEST     	8 0 0
	86	[35]	JMP      	5	; to 92
	87	[35]	LOADK    	14 -18	; " - "
	88	[35]	MOVE     	15 8
	89	[35]	CONCAT   	14 14 15
	90	[35]	TEST     	14 0 1
	91	[35]	JMP      	1	; to 93
	92	[35]	LOADK    	14 -19	; ""
	93	[35]	CONCAT   	12 12 14
	94	[35]	MOVE     	13 9
	95	[35]	RETURN   	11 4
	96	[37]	MOVE     	11 7
	97	[37]	LOADNIL  	12 13
	98	[37]	MOVE     	14 10
	99	[37]	RETURN   	11 5
	100	[38]	RETURN   	0 1

function <./fetch.lua:61,77> (71 instructions, 284 bytes at 0x7fb5b6c07210)
3 params, 13 slots, 2 upvalues, 8 locals, 13 constants, 0 functions
	1	[62]	GETGLOBAL	3 -1	; assert
	2	[62]	GETGLOBAL	4 -2	; type
	3	[62]	MOVE     	5 0
	4	[62]	CALL     	4 2 2
	5	[62]	EQ       	1 4 -3	; - "string"
	6	[62]	JMP      	1	; to 8
	7	[62]	LOADBOOL 	4 0 1
	8	[62]	LOADBOOL 	4 1 0
	9	[62]	CALL     	3 2 1
	10	[63]	GETGLOBAL	3 -1	; assert
	11	[63]	GETGLOBAL	4 -2	; type
	12	[63]	MOVE     	5 1
	13	[63]	CALL     	4 2 2
	14	[63]	EQ       	1 4 -3	; - "string"
	15	[63]	JMP      	3	; to 19
	16	[63]	NOT      	4 1
	17	[63]	JMP      	2	; to 20
	18	[63]	LOADBOOL 	4 0 1
	19	[63]	LOADBOOL 	4 1 0
	20	[63]	CALL     	3 2 1
	21	[65]	GETUPVAL 	3 0	; dir
	22	[65]	GETTABLE 	3 3 -4	; "split_url"
	23	[65]	MOVE     	4 0
	24	[65]	CALL     	3 2 3
	25	[66]	EQ       	0 3 -5	; - "file"
	26	[66]	JMP      	6	; to 33
	27	[67]	GETUPVAL 	5 1	; fs
	28	[67]	GETTABLE 	5 5 -6	; "absolute_name"
	29	[67]	MOVE     	6 4
	30	[67]	TAILCALL 	5 2 0
	31	[67]	RETURN   	5 0
	32	[67]	JMP      	38	; to 71
	33	[68]	GETUPVAL 	5 0	; dir
	34	[68]	GETTABLE 	5 5 -7	; "is_basic_protocol"
	35	[68]	MOVE     	6 3
	36	[68]	CALL     	5 2 2
	37	[68]	TEST     	5 0 0
	38	[68]	JMP      	27	; to 66
	39	[69]	GETUPVAL 	5 1	; fs
	40	[69]	GETTABLE 	5 5 -8	; "download"
	41	[69]	MOVE     	6 0
	42	[69]	MOVE     	7 1
	43	[69]	MOVE     	8 2
	44	[69]	CALL     	5 4 4
	45	[70]	TEST     	5 0 1
	46	[70]	JMP      	14	; to 61
	47	[71]	LOADNIL  	8 8
	48	[71]	LOADK    	9 -9	; "Failed downloading "
	49	[71]	MOVE     	10 0
	50	[71]	TEST     	1 0 0
	51	[71]	JMP      	5	; to 57
	52	[71]	LOADK    	11 -10	; " - "
	53	[71]	MOVE     	12 1
	54	[71]	CONCAT   	11 11 12
	55	[71]	TEST     	11 0 1
	56	[71]	JMP      	1	; to 58
	57	[71]	LOADK    	11 -11	; ""
	58	[71]	CONCAT   	9 9 11
	59	[71]	LOADK    	10 -12	; "network"
	60	[71]	RETURN   	8 4
	61	[73]	MOVE     	8 6
	62	[73]	LOADNIL  	9 10
	63	[73]	MOVE     	11 7
	64	[73]	RETURN   	8 5
	65	[73]	JMP      	5	; to 71
	66	[75]	LOADNIL  	5 5
	67	[75]	LOADK    	6 -13	; "Unsupported protocol "
	68	[75]	MOVE     	7 3
	69	[75]	CONCAT   	6 6 7
	70	[75]	RETURN   	5 3
	71	[77]	RETURN   	0 1

function <./fetch.lua:90,133> (141 instructions, 564 bytes at 0x7fb5b6c07cc0)
4 params, 17 slots, 4 upvalues, 14 locals, 22 constants, 0 functions
	1	[91]	GETGLOBAL	4 -1	; assert
	2	[91]	GETGLOBAL	5 -2	; type
	3	[91]	MOVE     	6 0
	4	[91]	CALL     	5 2 2
	5	[91]	EQ       	1 5 -3	; - "string"
	6	[91]	JMP      	1	; to 8
	7	[91]	LOADBOOL 	5 0 1
	8	[91]	LOADBOOL 	5 1 0
	9	[91]	CALL     	4 2 1
	10	[92]	GETGLOBAL	4 -1	; assert
	11	[92]	GETGLOBAL	5 -2	; type
	12	[92]	MOVE     	6 1
	13	[92]	CALL     	5 2 2
	14	[92]	EQ       	1 5 -3	; - "string"
	15	[92]	JMP      	1	; to 17
	16	[92]	LOADBOOL 	5 0 1
	17	[92]	LOADBOOL 	5 1 0
	18	[92]	CALL     	4 2 1
	19	[93]	GETGLOBAL	4 -1	; assert
	20	[93]	GETGLOBAL	5 -2	; type
	21	[93]	MOVE     	6 2
	22	[93]	CALL     	5 2 2
	23	[93]	EQ       	1 5 -3	; - "string"
	24	[93]	JMP      	3	; to 28
	25	[93]	NOT      	5 2
	26	[93]	JMP      	2	; to 29
	27	[93]	LOADBOOL 	5 0 1
	28	[93]	LOADBOOL 	5 1 0
	29	[93]	CALL     	4 2 1
	30	[94]	TEST     	2 0 1
	31	[94]	JMP      	5	; to 37
	32	[94]	GETUPVAL 	4 0	; dir
	33	[94]	GETTABLE 	4 4 -4	; "base_name"
	34	[94]	MOVE     	5 0
	35	[94]	CALL     	4 2 2
	36	[94]	MOVE     	2 4
	37	[96]	GETUPVAL 	4 0	; dir
	38	[96]	GETTABLE 	4 4 -5	; "split_url"
	39	[96]	MOVE     	5 0
	40	[96]	CALL     	4 2 3
	41	[97]	EQ       	0 4 -6	; - "file"
	42	[97]	JMP      	22	; to 65
	43	[98]	GETUPVAL 	6 1	; fs
	44	[98]	GETTABLE 	6 6 -7	; "exists"
	45	[98]	MOVE     	7 5
	46	[98]	CALL     	6 2 2
	47	[98]	TEST     	6 0 0
	48	[98]	JMP      	10	; to 59
	49	[99]	MOVE     	6 5
	50	[99]	GETUPVAL 	7 0	; dir
	51	[99]	GETTABLE 	7 7 -8	; "dir_name"
	52	[99]	GETUPVAL 	8 1	; fs
	53	[99]	GETTABLE 	8 8 -9	; "absolute_name"
	54	[99]	MOVE     	9 5
	55	[99]	CALL     	8 2 0
	56	[99]	CALL     	7 0 0
	57	[99]	RETURN   	6 0
	58	[99]	JMP      	82	; to 141
	59	[101]	LOADNIL  	6 6
	60	[101]	LOADK    	7 -10	; "File not found: "
	61	[101]	MOVE     	8 5
	62	[101]	CONCAT   	7 7 8
	63	[101]	RETURN   	6 3
	64	[102]	JMP      	76	; to 141
	65	[104]	GETUPVAL 	6 1	; fs
	66	[104]	GETTABLE 	6 6 -11	; "make_temp_dir"
	67	[104]	MOVE     	7 1
	68	[104]	CALL     	6 2 3
	69	[105]	TEST     	6 0 1
	70	[105]	JMP      	7	; to 78
	71	[106]	LOADNIL  	8 8
	72	[106]	LOADK    	9 -12	; "Failed creating temporary directory "
	73	[106]	MOVE     	10 1
	74	[106]	LOADK    	11 -13	; ": "
	75	[106]	MOVE     	12 7
	76	[106]	CONCAT   	9 9 12
	77	[106]	RETURN   	8 3
	78	[108]	GETUPVAL 	8 2	; util
	79	[108]	GETTABLE 	8 8 -14	; "schedule_function"
	80	[108]	GETUPVAL 	9 1	; fs
	81	[108]	GETTABLE 	9 9 -15	; "delete"
	82	[108]	MOVE     	10 6
	83	[108]	CALL     	8 3 1
	84	[109]	GETUPVAL 	8 1	; fs
	85	[109]	GETTABLE 	8 8 -16	; "change_dir"
	86	[109]	MOVE     	9 6
	87	[109]	CALL     	8 2 3
	88	[110]	TEST     	8 0 1
	89	[110]	JMP      	3	; to 93
	90	[110]	LOADNIL  	10 10
	91	[110]	MOVE     	11 9
	92	[110]	RETURN   	10 3
	93	[112]	LOADNIL  	10 12
	94	[114]	TEST     	3 0 0
	95	[114]	JMP      	22	; to 118
	96	[115]	LOADNIL  	13 13
	97	[116]	GETUPVAL 	14 3	; fetch
	98	[116]	GETTABLE 	14 14 -17	; "fetch_caching"
	99	[116]	MOVE     	15 0
	100	[116]	CALL     	14 2 4
	101	[116]	MOVE     	12 16
	102	[116]	MOVE     	11 15
	103	[116]	MOVE     	13 14
	104	[118]	TEST     	13 0 0
	105	[118]	JMP      	21	; to 127
	106	[119]	GETUPVAL 	14 0	; dir
	107	[119]	GETTABLE 	14 14 -18	; "path"
	108	[119]	MOVE     	15 6
	109	[119]	MOVE     	16 2
	110	[119]	CALL     	14 3 2
	111	[119]	MOVE     	10 14
	112	[120]	GETUPVAL 	14 1	; fs
	113	[120]	GETTABLE 	14 14 -19	; "copy"
	114	[120]	MOVE     	15 13
	115	[120]	MOVE     	16 10
	116	[120]	CALL     	14 3 1
	117	[121]	JMP      	9	; to 127
	118	[123]	GETUPVAL 	13 3	; fetch
	119	[123]	GETTABLE 	13 13 -20	; "fetch_url"
	120	[123]	MOVE     	14 0
	121	[123]	MOVE     	15 2
	122	[123]	MOVE     	16 3
	123	[123]	CALL     	13 4 4
	124	[123]	MOVE     	12 15
	125	[123]	MOVE     	11 14
	126	[123]	MOVE     	10 13
	127	[126]	GETUPVAL 	13 1	; fs
	128	[126]	GETTABLE 	13 13 -21	; "pop_dir"
	129	[126]	CALL     	13 1 1
	130	[127]	TEST     	10 0 1
	131	[127]	JMP      	6	; to 138
	132	[128]	LOADNIL  	13 13
	133	[128]	LOADK    	14 -22	; "Error fetching file: "
	134	[128]	MOVE     	15 11
	135	[128]	CONCAT   	14 14 15
	136	[128]	MOVE     	15 12
	137	[128]	RETURN   	13 4
	138	[131]	MOVE     	13 10
	139	[131]	MOVE     	14 6
	140	[131]	RETURN   	13 3
	141	[133]	RETURN   	0 1

function <./fetch.lua:147,171> (71 instructions, 284 bytes at 0x7fb5b6c07080)
4 params, 17 slots, 3 upvalues, 14 locals, 14 constants, 0 functions
	1	[148]	GETUPVAL 	4 0	; fs
	2	[148]	GETTABLE 	4 4 -1	; "change_dir"
	3	[148]	MOVE     	5 1
	4	[148]	CALL     	4 2 3
	5	[149]	TEST     	4 0 1
	6	[149]	JMP      	3	; to 10
	7	[149]	LOADNIL  	6 6
	8	[149]	MOVE     	7 5
	9	[149]	RETURN   	6 3
	10	[150]	GETUPVAL 	6 0	; fs
	11	[150]	GETTABLE 	6 6 -2	; "unpack_archive"
	12	[150]	MOVE     	7 0
	13	[150]	CALL     	6 2 1
	14	[151]	TESTSET  	6 3 1
	15	[151]	JMP      	4	; to 20
	16	[151]	GETUPVAL 	6 1	; dir
	17	[151]	GETTABLE 	6 6 -3	; "deduce_base_dir"
	18	[151]	MOVE     	7 2
	19	[151]	CALL     	6 2 2
	20	[152]	LOADNIL  	7 7
	21	[153]	GETUPVAL 	8 0	; fs
	22	[153]	GETTABLE 	8 8 -4	; "exists"
	23	[153]	MOVE     	9 6
	24	[153]	CALL     	8 2 2
	25	[153]	TEST     	8 0 0
	26	[153]	JMP      	2	; to 29
	27	[154]	MOVE     	7 6
	28	[154]	JMP      	36	; to 65
	29	[156]	GETUPVAL 	8 2	; util
	30	[156]	GETTABLE 	8 8 -5	; "printerr"
	31	[156]	LOADK    	9 -6	; "Directory "
	32	[156]	MOVE     	10 6
	33	[156]	LOADK    	11 -7	; " not found"
	34	[156]	CONCAT   	9 9 11
	35	[156]	CALL     	8 2 1
	36	[157]	GETUPVAL 	8 0	; fs
	37	[157]	GETTABLE 	8 8 -8	; "list_dir"
	38	[157]	CALL     	8 1 2
	39	[158]	TEST     	8 0 0
	40	[158]	JMP      	24	; to 65
	41	[159]	GETGLOBAL	9 -9	; table
	42	[159]	GETTABLE 	9 9 -10	; "sort"
	43	[159]	MOVE     	10 8
	44	[159]	CALL     	9 2 1
	45	[160]	GETGLOBAL	9 -11	; ipairs
	46	[160]	MOVE     	10 8
	47	[160]	CALL     	9 2 4
	48	[160]	JMP      	14	; to 63
	49	[161]	GETUPVAL 	14 0	; fs
	50	[161]	GETTABLE 	14 14 -12	; "is_dir"
	51	[161]	MOVE     	15 13
	52	[161]	CALL     	14 2 2
	53	[161]	TEST     	14 0 0
	54	[161]	JMP      	8	; to 63
	55	[162]	GETUPVAL 	14 2	; util
	56	[162]	GETTABLE 	14 14 -5	; "printerr"
	57	[162]	LOADK    	15 -13	; "Found "
	58	[162]	MOVE     	16 13
	59	[162]	CONCAT   	15 15 16
	60	[162]	CALL     	14 2 1
	61	[163]	MOVE     	7 13
	62	[164]	JMP      	2	; to 65
	63	[160]	TFORLOOP 	9 2
	64	[165]	JMP      	-16	; to 49
	65	[169]	GETUPVAL 	8 0	; fs
	66	[169]	GETTABLE 	8 8 -14	; "pop_dir"
	67	[169]	CALL     	8 1 1
	68	[170]	MOVE     	8 6
	69	[170]	MOVE     	9 7
	70	[170]	RETURN   	8 3
	71	[171]	RETURN   	0 1

function <./fetch.lua:173,186> (35 instructions, 140 bytes at 0x7fb5b6c06c10)
3 params, 12 slots, 3 upvalues, 9 locals, 6 constants, 0 functions
	1	[174]	GETUPVAL 	3 0	; signing
	2	[174]	GETTABLE 	3 3 -1	; "signature_url"
	3	[174]	MOVE     	4 0
	4	[174]	CALL     	3 2 2
	5	[175]	GETUPVAL 	4 1	; fetch
	6	[175]	GETTABLE 	4 4 -2	; "fetch_url_at_temp_dir"
	7	[175]	MOVE     	5 3
	8	[175]	MOVE     	6 2
	9	[175]	CALL     	4 3 4
	10	[176]	TEST     	4 0 1
	11	[176]	JMP      	6	; to 18
	12	[177]	LOADNIL  	7 7
	13	[177]	LOADK    	8 -3	; "Could not fetch signature file for verification: "
	14	[177]	MOVE     	9 5
	15	[177]	CONCAT   	8 8 9
	16	[177]	MOVE     	9 6
	17	[177]	RETURN   	7 4
	18	[180]	GETUPVAL 	7 0	; signing
	19	[180]	GETTABLE 	7 7 -4	; "verify_signature"
	20	[180]	MOVE     	8 1
	21	[180]	MOVE     	9 4
	22	[180]	CALL     	7 3 3
	23	[181]	TEST     	7 0 1
	24	[181]	JMP      	5	; to 30
	25	[182]	LOADNIL  	9 9
	26	[182]	LOADK    	10 -5	; "Failed signature verification: "
	27	[182]	MOVE     	11 8
	28	[182]	CONCAT   	10 10 11
	29	[182]	RETURN   	9 3
	30	[185]	GETUPVAL 	9 2	; fs
	31	[185]	GETTABLE 	9 9 -6	; "absolute_name"
	32	[185]	MOVE     	10 4
	33	[185]	TAILCALL 	9 2 0
	34	[185]	RETURN   	9 0
	35	[186]	RETURN   	0 1

function <./fetch.lua:197,249> (145 instructions, 580 bytes at 0x7fb5b6c09610)
3 params, 17 slots, 5 upvalues, 14 locals, 23 constants, 0 functions
	1	[198]	GETGLOBAL	3 -1	; assert
	2	[198]	GETGLOBAL	4 -2	; type
	3	[198]	MOVE     	5 0
	4	[198]	CALL     	4 2 2
	5	[198]	EQ       	1 4 -3	; - "string"
	6	[198]	JMP      	1	; to 8
	7	[198]	LOADBOOL 	4 0 1
	8	[198]	LOADBOOL 	4 1 0
	9	[198]	CALL     	3 2 1
	10	[199]	GETGLOBAL	3 -1	; assert
	11	[199]	GETGLOBAL	4 -2	; type
	12	[199]	MOVE     	5 1
	13	[199]	CALL     	4 2 2
	14	[199]	EQ       	1 4 -3	; - "string"
	15	[199]	JMP      	3	; to 19
	16	[199]	NOT      	4 1
	17	[199]	JMP      	2	; to 20
	18	[199]	LOADBOOL 	4 0 1
	19	[199]	LOADBOOL 	4 1 0
	20	[199]	CALL     	3 2 1
	21	[201]	GETUPVAL 	3 0	; dir
	22	[201]	GETTABLE 	3 3 -4	; "base_name"
	23	[201]	MOVE     	4 0
	24	[201]	CALL     	3 2 2
	25	[201]	SELF     	3 3 -5	; "match"
	26	[201]	LOADK    	5 -6	; "(.*)%.[^.]*%.rock"
	27	[201]	CALL     	3 3 2
	28	[202]	LOADK    	4 -7	; "luarocks-rock-"
	29	[202]	MOVE     	5 3
	30	[202]	CONCAT   	4 4 5
	31	[204]	GETUPVAL 	5 1	; fetch
	32	[204]	GETTABLE 	5 5 -8	; "fetch_url_at_temp_dir"
	33	[204]	MOVE     	6 0
	34	[204]	MOVE     	7 4
	35	[204]	LOADNIL  	8 8
	36	[204]	LOADBOOL 	9 1 0
	37	[204]	CALL     	5 5 4
	38	[205]	TEST     	5 0 1
	39	[205]	JMP      	6	; to 46
	40	[206]	LOADNIL  	8 8
	41	[206]	LOADK    	9 -9	; "Could not fetch rock file: "
	42	[206]	MOVE     	10 6
	43	[206]	CONCAT   	9 9 10
	44	[206]	MOVE     	10 7
	45	[206]	RETURN   	8 4
	46	[209]	LOADNIL  	8 8
	47	[210]	TEST     	2 0 0
	48	[210]	JMP      	12	; to 61
	49	[211]	GETUPVAL 	9 2	; fetch_and_verify_signature_for
	50	[211]	MOVE     	10 0
	51	[211]	MOVE     	11 5
	52	[211]	MOVE     	12 4
	53	[211]	CALL     	9 4 3
	54	[211]	MOVE     	6 10
	55	[211]	MOVE     	8 9
	56	[212]	TEST     	6 0 0
	57	[212]	JMP      	3	; to 61
	58	[213]	LOADNIL  	9 9
	59	[213]	MOVE     	10 6
	60	[213]	RETURN   	9 3
	61	[217]	GETUPVAL 	9 3	; fs
	62	[217]	GETTABLE 	9 9 -10	; "absolute_name"
	63	[217]	MOVE     	10 5
	64	[217]	CALL     	9 2 2
	65	[217]	MOVE     	5 9
	66	[219]	LOADNIL  	9 9
	67	[220]	TEST     	1 0 0
	68	[220]	JMP      	13	; to 82
	69	[221]	MOVE     	9 1
	70	[222]	GETUPVAL 	10 3	; fs
	71	[222]	GETTABLE 	10 10 -11	; "make_dir"
	72	[222]	MOVE     	11 9
	73	[222]	CALL     	10 2 3
	74	[223]	TEST     	10 0 1
	75	[223]	JMP      	19	; to 95
	76	[224]	LOADNIL  	12 12
	77	[224]	LOADK    	13 -12	; "Failed unpacking rock file: "
	78	[224]	MOVE     	14 11
	79	[224]	CONCAT   	13 13 14
	80	[224]	RETURN   	12 3
	81	[225]	JMP      	13	; to 95
	82	[227]	GETUPVAL 	10 3	; fs
	83	[227]	GETTABLE 	10 10 -13	; "make_temp_dir"
	84	[227]	MOVE     	11 3
	85	[227]	CALL     	10 2 3
	86	[227]	MOVE     	6 11
	87	[227]	MOVE     	9 10
	88	[228]	TEST     	9 0 1
	89	[228]	JMP      	5	; to 95
	90	[229]	LOADNIL  	10 10
	91	[229]	LOADK    	11 -14	; "Failed creating temporary dir: "
	92	[229]	MOVE     	12 6
	93	[229]	CONCAT   	11 11 12
	94	[229]	RETURN   	10 3
	95	[232]	TEST     	1 0 1
	96	[232]	JMP      	6	; to 103
	97	[233]	GETUPVAL 	10 4	; util
	98	[233]	GETTABLE 	10 10 -15	; "schedule_function"
	99	[233]	GETUPVAL 	11 3	; fs
	100	[233]	GETTABLE 	11 11 -16	; "delete"
	101	[233]	MOVE     	12 9
	102	[233]	CALL     	10 3 1
	103	[235]	GETUPVAL 	10 3	; fs
	104	[235]	GETTABLE 	10 10 -17	; "change_dir"
	105	[235]	MOVE     	11 9
	106	[235]	CALL     	10 2 3
	107	[236]	TEST     	10 0 1
	108	[236]	JMP      	3	; to 112
	109	[236]	LOADNIL  	12 12
	110	[236]	MOVE     	13 11
	111	[236]	RETURN   	12 3
	112	[237]	GETUPVAL 	12 3	; fs
	113	[237]	GETTABLE 	12 12 -18	; "unzip"
	114	[237]	MOVE     	13 5
	115	[237]	CALL     	12 2 3
	116	[237]	MOVE     	11 13
	117	[237]	MOVE     	10 12
	118	[238]	TEST     	10 0 1
	119	[238]	JMP      	7	; to 127
	120	[239]	LOADNIL  	12 12
	121	[239]	LOADK    	13 -12	; "Failed unpacking rock file: "
	122	[239]	MOVE     	14 5
	123	[239]	LOADK    	15 -19	; ": "
	124	[239]	MOVE     	16 11
	125	[239]	CONCAT   	13 13 16
	126	[239]	RETURN   	12 3
	127	[241]	TEST     	8 0 0
	128	[241]	JMP      	12	; to 141
	129	[242]	GETUPVAL 	12 3	; fs
	130	[242]	GETTABLE 	12 12 -20	; "copy"
	131	[242]	MOVE     	13 8
	132	[242]	LOADK    	14 -21	; "."
	133	[242]	CALL     	12 3 3
	134	[242]	MOVE     	11 13
	135	[242]	MOVE     	10 12
	136	[243]	TEST     	10 0 1
	137	[243]	JMP      	3	; to 141
	138	[244]	LOADNIL  	12 12
	139	[244]	LOADK    	13 -22	; "Failed copying signature file"
	140	[244]	RETURN   	12 3
	141	[247]	GETUPVAL 	12 3	; fs
	142	[247]	GETTABLE 	12 12 -23	; "pop_dir"
	143	[247]	CALL     	12 1 1
	144	[248]	RETURN   	9 2
	145	[249]	RETURN   	0 1

function <./fetch.lua:258,285> (79 instructions, 316 bytes at 0x7fb5b6c0a090)
2 params, 15 slots, 4 upvalues, 9 locals, 23 constants, 0 functions
	1	[259]	GETGLOBAL	2 -1	; assert
	2	[259]	GETGLOBAL	3 -2	; type
	3	[259]	MOVE     	4 0
	4	[259]	CALL     	3 2 2
	5	[259]	EQ       	1 3 -3	; - "string"
	6	[259]	JMP      	1	; to 8
	7	[259]	LOADBOOL 	3 0 1
	8	[259]	LOADBOOL 	3 1 0
	9	[259]	CALL     	2 2 1
	10	[260]	GETUPVAL 	2 0	; fs
	11	[260]	GETTABLE 	2 2 -4	; "absolute_name"
	12	[260]	MOVE     	3 0
	13	[260]	CALL     	2 2 2
	14	[262]	GETUPVAL 	3 1	; dir
	15	[262]	GETTABLE 	3 3 -5	; "base_name"
	16	[262]	MOVE     	4 2
	17	[262]	CALL     	3 2 2
	18	[263]	EQ       	1 3 -6	; - "rockspec"
	19	[263]	JMP      	8	; to 28
	20	[264]	SELF     	4 3 -7	; "match"
	21	[264]	LOADK    	6 -8	; "(.*)%-[^-]*%-[0-9]*"
	22	[264]	CALL     	4 3 2
	23	[264]	TEST     	4 0 1
	24	[264]	JMP      	3	; to 28
	25	[265]	LOADNIL  	4 4
	26	[265]	LOADK    	5 -9	; "Expected filename in format 'name-version-revision.rockspec'."
	27	[265]	RETURN   	4 3
	28	[269]	GETUPVAL 	4 2	; persist
	29	[269]	GETTABLE 	4 4 -10	; "load_into_table"
	30	[269]	MOVE     	5 2
	31	[269]	CALL     	4 2 3
	32	[270]	TEST     	4 0 1
	33	[270]	JMP      	8	; to 42
	34	[271]	LOADNIL  	6 6
	35	[271]	LOADK    	7 -11	; "Could not load rockspec file "
	36	[271]	MOVE     	8 2
	37	[271]	LOADK    	9 -12	; " ("
	38	[271]	MOVE     	10 5
	39	[271]	LOADK    	11 -13	; ")"
	40	[271]	CONCAT   	7 7 11
	41	[271]	RETURN   	6 3
	42	[274]	GETUPVAL 	6 3	; rockspecs
	43	[274]	GETTABLE 	6 6 -14	; "from_persisted_table"
	44	[274]	MOVE     	7 2
	45	[274]	MOVE     	8 4
	46	[274]	MOVE     	9 5
	47	[274]	MOVE     	10 1
	48	[274]	CALL     	6 5 3
	49	[275]	TEST     	6 0 1
	50	[275]	JMP      	6	; to 57
	51	[276]	LOADNIL  	8 8
	52	[276]	MOVE     	9 2
	53	[276]	LOADK    	10 -15	; ": "
	54	[276]	MOVE     	11 7
	55	[276]	CONCAT   	9 9 11
	56	[276]	RETURN   	8 3
	57	[279]	GETTABLE 	8 6 -16	; "package"
	58	[279]	SELF     	8 8 -17	; "lower"
	59	[279]	CALL     	8 2 2
	60	[279]	LOADK    	9 -18	; "-"
	61	[279]	GETTABLE 	10 6 -19	; "version"
	62	[279]	CONCAT   	8 8 10
	63	[280]	EQ       	1 3 -6	; - "rockspec"
	64	[280]	JMP      	13	; to 78
	65	[280]	MOVE     	9 8
	66	[280]	LOADK    	10 -20	; ".rockspec"
	67	[280]	CONCAT   	9 9 10
	68	[280]	EQ       	1 3 9
	69	[280]	JMP      	8	; to 78
	70	[281]	LOADNIL  	9 9
	71	[281]	LOADK    	10 -21	; "Inconsistency between rockspec filename ("
	72	[281]	MOVE     	11 3
	73	[281]	LOADK    	12 -22	; ") and its contents ("
	74	[281]	MOVE     	13 8
	75	[281]	LOADK    	14 -23	; ".rockspec)."
	76	[281]	CONCAT   	10 10 14
	77	[281]	RETURN   	9 3
	78	[284]	RETURN   	6 2
	79	[285]	RETURN   	0 1

function <./fetch.lua:297,333> (89 instructions, 356 bytes at 0x7fb5b6c0a300)
3 params, 14 slots, 4 upvalues, 13 locals, 15 constants, 0 functions
	1	[298]	GETGLOBAL	3 -1	; assert
	2	[298]	GETGLOBAL	4 -2	; type
	3	[298]	MOVE     	5 0
	4	[298]	CALL     	4 2 2
	5	[298]	EQ       	1 4 -3	; - "string"
	6	[298]	JMP      	1	; to 8
	7	[298]	LOADBOOL 	4 0 1
	8	[298]	LOADBOOL 	4 1 0
	9	[298]	CALL     	3 2 1
	10	[300]	LOADNIL  	3 3
	11	[301]	GETUPVAL 	4 0	; dir
	12	[301]	GETTABLE 	4 4 -4	; "base_name"
	13	[301]	MOVE     	5 0
	14	[301]	CALL     	4 2 2
	15	[302]	EQ       	0 4 -5	; - "rockspec"
	16	[302]	JMP      	2	; to 19
	17	[303]	LOADK    	3 -5	; "rockspec"
	18	[303]	JMP      	12	; to 31
	19	[305]	SELF     	5 4 -6	; "match"
	20	[305]	LOADK    	7 -7	; "(.*)%.rockspec"
	21	[305]	CALL     	5 3 2
	22	[305]	MOVE     	3 5
	23	[306]	TEST     	3 0 1
	24	[306]	JMP      	6	; to 31
	25	[307]	LOADNIL  	5 5
	26	[307]	LOADK    	6 -8	; "Filename '"
	27	[307]	MOVE     	7 0
	28	[307]	LOADK    	8 -9	; "' does not look like a rockspec."
	29	[307]	CONCAT   	6 6 8
	30	[307]	RETURN   	5 3
	31	[311]	LOADK    	5 -10	; "luarocks-rockspec-"
	32	[311]	MOVE     	6 3
	33	[311]	CONCAT   	5 5 6
	34	[312]	LOADNIL  	6 8
	35	[313]	TEST     	1 0 0
	36	[313]	JMP      	19	; to 56
	37	[314]	GETUPVAL 	9 1	; fs
	38	[314]	GETTABLE 	9 9 -11	; "change_dir"
	39	[314]	MOVE     	10 1
	40	[314]	CALL     	9 2 3
	41	[315]	TEST     	9 0 1
	42	[315]	JMP      	3	; to 46
	43	[315]	LOADNIL  	11 11
	44	[315]	MOVE     	12 10
	45	[315]	RETURN   	11 3
	46	[316]	GETUPVAL 	11 2	; fetch
	47	[316]	GETTABLE 	11 11 -12	; "fetch_url"
	48	[316]	MOVE     	12 0
	49	[316]	CALL     	11 2 3
	50	[316]	MOVE     	10 12
	51	[316]	MOVE     	6 11
	52	[317]	GETUPVAL 	11 1	; fs
	53	[317]	GETTABLE 	11 11 -13	; "pop_dir"
	54	[317]	CALL     	11 1 1
	55	[317]	JMP      	10	; to 66
	56	[319]	GETUPVAL 	9 2	; fetch
	57	[319]	GETTABLE 	9 9 -14	; "fetch_url_at_temp_dir"
	58	[319]	MOVE     	10 0
	59	[319]	MOVE     	11 5
	60	[319]	LOADNIL  	12 12
	61	[319]	LOADBOOL 	13 1 0
	62	[319]	CALL     	9 5 4
	63	[319]	MOVE     	8 11
	64	[319]	MOVE     	7 10
	65	[319]	MOVE     	6 9
	66	[321]	TEST     	6 0 1
	67	[321]	JMP      	4	; to 72
	68	[322]	LOADNIL  	9 9
	69	[322]	MOVE     	10 7
	70	[322]	MOVE     	11 8
	71	[322]	RETURN   	9 4
	72	[325]	TEST     	2 0 0
	73	[325]	JMP      	10	; to 84
	74	[326]	GETUPVAL 	9 3	; fetch_and_verify_signature_for
	75	[326]	MOVE     	10 0
	76	[326]	MOVE     	11 6
	77	[326]	MOVE     	12 5
	78	[326]	CALL     	9 4 3
	79	[327]	TEST     	10 0 0
	80	[327]	JMP      	3	; to 84
	81	[328]	LOADNIL  	11 11
	82	[328]	MOVE     	12 10
	83	[328]	RETURN   	11 3
	84	[332]	GETUPVAL 	9 2	; fetch
	85	[332]	GETTABLE 	9 9 -15	; "load_local_rockspec"
	86	[332]	MOVE     	10 6
	87	[332]	TAILCALL 	9 2 0
	88	[332]	RETURN   	9 0
	89	[333]	RETURN   	0 1

function <./fetch.lua:344,403> (183 instructions, 732 bytes at 0x7fb5b6c0ae90)
3 params, 21 slots, 2 upvalues, 19 locals, 33 constants, 0 functions
	1	[345]	GETGLOBAL	3 -1	; assert
	2	[345]	SELF     	4 0 -2	; "type"
	3	[345]	CALL     	4 2 2
	4	[345]	EQ       	1 4 -3	; - "rockspec"
	5	[345]	JMP      	1	; to 7
	6	[345]	LOADBOOL 	4 0 1
	7	[345]	LOADBOOL 	4 1 0
	8	[345]	CALL     	3 2 1
	9	[346]	GETGLOBAL	3 -1	; assert
	10	[346]	GETGLOBAL	4 -2	; type
	11	[346]	MOVE     	5 1
	12	[346]	CALL     	4 2 2
	13	[346]	EQ       	1 4 -4	; - "boolean"
	14	[346]	JMP      	1	; to 16
	15	[346]	LOADBOOL 	4 0 1
	16	[346]	LOADBOOL 	4 1 0
	17	[346]	CALL     	3 2 1
	18	[347]	GETGLOBAL	3 -1	; assert
	19	[347]	GETGLOBAL	4 -2	; type
	20	[347]	MOVE     	5 2
	21	[347]	CALL     	4 2 2
	22	[347]	EQ       	1 4 -5	; - "string"
	23	[347]	JMP      	3	; to 27
	24	[347]	NOT      	4 2
	25	[347]	JMP      	2	; to 28
	26	[347]	LOADBOOL 	4 0 1
	27	[347]	LOADBOOL 	4 1 0
	28	[347]	CALL     	3 2 1
	29	[349]	GETTABLE 	3 0 -6	; "source"
	30	[349]	GETTABLE 	3 3 -7	; "url"
	31	[350]	GETTABLE 	4 0 -8	; "name"
	32	[350]	LOADK    	5 -9	; "-"
	33	[350]	GETTABLE 	6 0 -10	; "version"
	34	[350]	CONCAT   	4 4 6
	35	[351]	GETTABLE 	5 0 -6	; "source"
	36	[351]	GETTABLE 	5 5 -11	; "file"
	37	[352]	LOADNIL  	6 10
	38	[354]	TEST     	2 0 0
	39	[354]	JMP      	25	; to 65
	40	[355]	GETUPVAL 	11 0	; fs
	41	[355]	GETTABLE 	11 11 -12	; "change_dir"
	42	[355]	MOVE     	12 2
	43	[355]	CALL     	11 2 3
	44	[355]	MOVE     	9 12
	45	[355]	MOVE     	8 11
	46	[356]	TEST     	8 0 1
	47	[356]	JMP      	4	; to 52
	48	[356]	LOADNIL  	11 11
	49	[356]	MOVE     	12 9
	50	[356]	LOADK    	13 -13	; "dest_dir"
	51	[356]	RETURN   	11 4
	52	[357]	GETUPVAL 	11 1	; fetch
	53	[357]	GETTABLE 	11 11 -14	; "fetch_url"
	54	[357]	MOVE     	12 3
	55	[357]	MOVE     	13 5
	56	[357]	CALL     	11 3 4
	57	[357]	MOVE     	10 13
	58	[357]	MOVE     	9 12
	59	[357]	MOVE     	6 11
	60	[358]	GETUPVAL 	11 0	; fs
	61	[358]	GETTABLE 	11 11 -15	; "pop_dir"
	62	[358]	CALL     	11 1 1
	63	[359]	MOVE     	7 2
	64	[359]	JMP      	11	; to 76
	65	[361]	GETUPVAL 	11 1	; fetch
	66	[361]	GETTABLE 	11 11 -16	; "fetch_url_at_temp_dir"
	67	[361]	MOVE     	12 3
	68	[361]	LOADK    	13 -17	; "luarocks-source-"
	69	[361]	MOVE     	14 4
	70	[361]	CONCAT   	13 13 14
	71	[361]	MOVE     	14 5
	72	[361]	CALL     	11 4 4
	73	[361]	MOVE     	10 13
	74	[361]	MOVE     	7 12
	75	[361]	MOVE     	6 11
	76	[363]	TEST     	6 0 1
	77	[363]	JMP      	6	; to 84
	78	[364]	LOADNIL  	11 11
	79	[364]	TESTSET  	12 9 1
	80	[364]	JMP      	1	; to 82
	81	[364]	MOVE     	12 7
	82	[364]	MOVE     	13 10
	83	[364]	RETURN   	11 4
	84	[366]	GETTABLE 	11 0 -6	; "source"
	85	[366]	GETTABLE 	11 11 -18	; "md5"
	86	[366]	TEST     	11 0 0
	87	[366]	JMP      	15	; to 103
	88	[367]	GETUPVAL 	11 0	; fs
	89	[367]	GETTABLE 	11 11 -19	; "check_md5"
	90	[367]	MOVE     	12 6
	91	[367]	GETTABLE 	13 0 -6	; "source"
	92	[367]	GETTABLE 	13 13 -18	; "md5"
	93	[367]	CALL     	11 3 2
	94	[367]	TEST     	11 0 1
	95	[367]	JMP      	7	; to 103
	96	[368]	LOADNIL  	11 11
	97	[368]	LOADK    	12 -20	; "MD5 check for "
	98	[368]	MOVE     	13 5
	99	[368]	LOADK    	14 -21	; " has failed."
	100	[368]	CONCAT   	12 12 14
	101	[368]	LOADK    	13 -18	; "md5"
	102	[368]	RETURN   	11 4
	103	[371]	TEST     	1 0 0
	104	[371]	JMP      	75	; to 180
	105	[372]	GETUPVAL 	11 0	; fs
	106	[372]	GETTABLE 	11 11 -12	; "change_dir"
	107	[372]	MOVE     	12 7
	108	[372]	CALL     	11 2 3
	109	[373]	TEST     	11 0 1
	110	[373]	JMP      	3	; to 114
	111	[373]	LOADNIL  	13 13
	112	[373]	MOVE     	14 12
	113	[373]	RETURN   	13 3
	114	[374]	GETUPVAL 	13 0	; fs
	115	[374]	GETTABLE 	13 13 -22	; "unpack_archive"
	116	[374]	GETTABLE 	14 0 -6	; "source"
	117	[374]	GETTABLE 	14 14 -11	; "file"
	118	[374]	CALL     	13 2 3
	119	[374]	MOVE     	12 14
	120	[374]	MOVE     	11 13
	121	[375]	TEST     	11 0 1
	122	[375]	JMP      	3	; to 126
	123	[375]	LOADNIL  	13 13
	124	[375]	MOVE     	14 12
	125	[375]	RETURN   	13 3
	126	[376]	GETUPVAL 	13 0	; fs
	127	[376]	GETTABLE 	13 13 -23	; "exists"
	128	[376]	GETTABLE 	14 0 -6	; "source"
	129	[376]	GETTABLE 	14 14 -24	; "dir"
	130	[376]	CALL     	13 2 2
	131	[376]	TEST     	13 0 1
	132	[376]	JMP      	44	; to 177
	133	[383]	LOADK    	13 -25	; 0
	134	[383]	LOADNIL  	14 14
	135	[385]	GETTABLE 	15 0 -6	; "source"
	136	[385]	GETTABLE 	15 15 -26	; "dir_set"
	137	[385]	TEST     	15 0 1
	138	[385]	JMP      	19	; to 158
	139	[385]	SELF     	15 0 -27	; "format_is_at_least"
	140	[385]	LOADK    	17 -28	; "3.0"
	141	[385]	CALL     	15 3 2
	142	[385]	TEST     	15 0 0
	143	[385]	JMP      	14	; to 158
	144	[386]	GETUPVAL 	15 0	; fs
	145	[386]	GETTABLE 	15 15 -24	; "dir"
	146	[386]	CALL     	15 1 4
	147	[386]	JMP      	8	; to 156
	148	[387]	ADD      	13 13 -29	; - 1
	149	[388]	GETUPVAL 	19 0	; fs
	150	[388]	GETTABLE 	19 19 -30	; "is_dir"
	151	[388]	MOVE     	20 18
	152	[388]	CALL     	19 2 2
	153	[388]	TEST     	19 0 0
	154	[388]	JMP      	1	; to 156
	155	[389]	MOVE     	14 18
	156	[386]	TFORLOOP 	15 1
	157	[390]	JMP      	-10	; to 148
	158	[394]	EQ       	0 13 -29	; - 1
	159	[394]	JMP      	5	; to 165
	160	[394]	TEST     	14 0 0
	161	[394]	JMP      	3	; to 165
	162	[395]	GETTABLE 	15 0 -6	; "source"
	163	[395]	SETTABLE 	15 -24 14	; "dir" -
	164	[395]	JMP      	12	; to 177
	165	[397]	LOADNIL  	15 15
	166	[397]	LOADK    	16 -31	; "Directory "
	167	[397]	GETTABLE 	17 0 -6	; "source"
	168	[397]	GETTABLE 	17 17 -24	; "dir"
	169	[397]	LOADK    	18 -32	; " not found inside archive "
	170	[397]	GETTABLE 	19 0 -6	; "source"
	171	[397]	GETTABLE 	19 19 -11	; "file"
	172	[397]	CONCAT   	16 16 19
	173	[397]	LOADK    	17 -33	; "source.dir"
	174	[397]	MOVE     	18 6
	175	[397]	MOVE     	19 7
	176	[397]	RETURN   	15 6
	177	[400]	GETUPVAL 	13 0	; fs
	178	[400]	GETTABLE 	13 13 -15	; "pop_dir"
	179	[400]	CALL     	13 1 1
	180	[402]	MOVE     	11 6
	181	[402]	MOVE     	12 7
	182	[402]	RETURN   	11 3
	183	[403]	RETURN   	0 1

function <./fetch.lua:414,440> (109 instructions, 436 bytes at 0x7fb5b6c088e0)
3 params, 13 slots, 3 upvalues, 6 locals, 25 constants, 0 functions
	1	[415]	GETGLOBAL	3 -1	; assert
	2	[415]	SELF     	4 0 -2	; "type"
	3	[415]	CALL     	4 2 2
	4	[415]	EQ       	1 4 -3	; - "rockspec"
	5	[415]	JMP      	1	; to 7
	6	[415]	LOADBOOL 	4 0 1
	7	[415]	LOADBOOL 	4 1 0
	8	[415]	CALL     	3 2 1
	9	[416]	GETGLOBAL	3 -1	; assert
	10	[416]	GETGLOBAL	4 -2	; type
	11	[416]	MOVE     	5 1
	12	[416]	CALL     	4 2 2
	13	[416]	EQ       	1 4 -4	; - "boolean"
	14	[416]	JMP      	1	; to 16
	15	[416]	LOADBOOL 	4 0 1
	16	[416]	LOADBOOL 	4 1 0
	17	[416]	CALL     	3 2 1
	18	[417]	GETGLOBAL	3 -1	; assert
	19	[417]	GETGLOBAL	4 -2	; type
	20	[417]	MOVE     	5 2
	21	[417]	CALL     	4 2 2
	22	[417]	EQ       	1 4 -5	; - "string"
	23	[417]	JMP      	3	; to 27
	24	[417]	NOT      	4 2
	25	[417]	JMP      	2	; to 28
	26	[417]	LOADBOOL 	4 0 1
	27	[417]	LOADBOOL 	4 1 0
	28	[417]	CALL     	3 2 1
	29	[419]	GETTABLE 	3 0 -6	; "source"
	30	[419]	GETTABLE 	3 3 -7	; "protocol"
	31	[420]	LOADNIL  	4 5
	32	[421]	GETUPVAL 	6 0	; dir
	33	[421]	GETTABLE 	6 6 -8	; "is_basic_protocol"
	34	[421]	MOVE     	7 3
	35	[421]	CALL     	6 2 2
	36	[421]	TEST     	6 0 0
	37	[421]	JMP      	2	; to 40
	38	[422]	GETUPVAL 	5 1	; fetch
	39	[422]	JMP      	18	; to 58
	40	[424]	GETGLOBAL	6 -9	; pcall
	41	[424]	GETGLOBAL	7 -10	; require
	42	[424]	LOADK    	8 -11	; "luarocks.fetch."
	43	[424]	SELF     	9 3 -12	; "gsub"
	44	[424]	LOADK    	11 -13	; "[+-]"
	45	[424]	LOADK    	12 -14	; "_"
	46	[424]	CALL     	9 4 2
	47	[424]	CONCAT   	8 8 9
	48	[424]	CALL     	6 3 3
	49	[424]	MOVE     	5 7
	50	[424]	MOVE     	4 6
	51	[425]	TEST     	4 0 1
	52	[425]	JMP      	5	; to 58
	53	[426]	LOADNIL  	6 6
	54	[426]	LOADK    	7 -15	; "Unknown protocol "
	55	[426]	MOVE     	8 3
	56	[426]	CONCAT   	7 7 8
	57	[426]	RETURN   	6 3
	58	[430]	GETUPVAL 	6 2	; cfg
	59	[431]	GETTABLE 	6 6 -16	; "only_sources_from"
	60	[431]	TEST     	6 0 0
	61	[431]	JMP      	41	; to 103
	62	[431]	GETTABLE 	6 0 -6	; "source"
	63	[431]	GETTABLE 	6 6 -17	; "pathname"
	64	[432]	TEST     	6 0 0
	65	[432]	JMP      	37	; to 103
	66	[432]	GETTABLE 	6 0 -6	; "source"
	67	[432]	GETTABLE 	6 6 -17	; "pathname"
	68	[432]	LEN      	6 6
	69	[432]	LT       	0 -18 6	; 0 -
	70	[432]	JMP      	32	; to 103
	71	[433]	GETUPVAL 	6 2	; cfg
	72	[433]	GETTABLE 	6 6 -16	; "only_sources_from"
	73	[433]	LEN      	6 6
	74	[433]	EQ       	0 6 -18	; - 0
	75	[433]	JMP      	8	; to 84
	76	[434]	LOADNIL  	6 6
	77	[434]	LOADK    	7 -19	; "Can't download "
	78	[434]	GETTABLE 	8 0 -6	; "source"
	79	[434]	GETTABLE 	8 8 -20	; "url"
	80	[434]	LOADK    	9 -21	; " -- download from remote servers disabled"
	81	[434]	CONCAT   	7 7 9
	82	[434]	RETURN   	6 3
	83	[434]	JMP      	19	; to 103
	84	[435]	GETTABLE 	6 0 -6	; "source"
	85	[435]	GETTABLE 	6 6 -17	; "pathname"
	86	[435]	SELF     	6 6 -22	; "find"
	87	[435]	GETUPVAL 	8 2	; cfg
	88	[435]	GETTABLE 	8 8 -16	; "only_sources_from"
	89	[435]	LOADK    	9 -23	; 1
	90	[435]	LOADBOOL 	10 1 0
	91	[435]	CALL     	6 5 2
	92	[435]	EQ       	1 6 -23	; - 1
	93	[435]	JMP      	9	; to 103
	94	[436]	LOADNIL  	6 6
	95	[436]	LOADK    	7 -19	; "Can't download "
	96	[436]	GETTABLE 	8 0 -6	; "source"
	97	[436]	GETTABLE 	8 8 -20	; "url"
	98	[436]	LOADK    	9 -24	; " -- only downloading from "
	99	[436]	GETUPVAL 	10 2	; cfg
	100	[436]	GETTABLE 	10 10 -16	; "only_sources_from"
	101	[436]	CONCAT   	7 7 10
	102	[436]	RETURN   	6 3
	103	[439]	GETTABLE 	6 5 -25	; "get_sources"
	104	[439]	MOVE     	7 0
	105	[439]	MOVE     	8 1
	106	[439]	MOVE     	9 2
	107	[439]	TAILCALL 	6 4 0
	108	[439]	RETURN   	6 0
	109	[440]	RETURN   	0 1
