-- BYTECODE -- freebsd.lua:6-9
0001    UGET     0   0      ; fs
0002    TGETS    0   0   0  ; "set_tool_available"
0003    KSTR     1   1      ; "zip"
0004    KPRI     2   2
0005    CALL     0   1   3
0006    UGET     0   0      ; fs
0007    TGETS    0   0   0  ; "set_tool_available"
0008    KSTR     1   2      ; "unzip"
0009    KPRI     2   2
0010    CALL     0   1   3
0011    RET0     0   1

-- BYTECODE -- freebsd.lua:0-12
0001    TNEW     0   0
0002    GGET     1   0      ; "require"
0003    KSTR     2   1      ; "luarocks.fs"
0004    CALL     1   2   2
0005    FNEW     2   3      ; freebsd.lua:6
0006    TSETS    2   0   2  ; "init"
0007    UCLO     0 => 0008
0008 => RET1     0   2

