-- BYTECODE -- index.lua:98-124
0001    TGETS    1   0   0  ; "external_dependencies"
0002    ISF          1
0003    JMP      2 => 0067
0004    TNEW     1   0
0005    TNEW     2   0
0006    KPRI     3   0
0007    UGET     4   0      ; util
0008    TGETS    4   4   1  ; "sortedpairs"
0009    TGETS    5   0   0  ; "external_dependencies"
0010    CALL     4   4   2
0011    JMP      7 => 0025
0012 => ISEQS    7   2      ; "platforms"
0013    JMP      9 => 0024
0014    GGET     9   3      ; "table"
0015    TGETS    9   9   4  ; "insert"
0016    MOV     10   1
0017    MOV     12   7
0018    TGETS   11   7   5  ; "lower"
0019    CALL    11   0   2
0020    CALLM    9   1   1
0021    KPRI     9   2
0022    TSETV    9   2   7
0023    JMP      9 => 0025
0024 => MOV      3   8
0025 => ITERC    7   3   3
0026    ITERL    7 => 0012
0027    ISF          3
0028    JMP      4 => 0057
0029    UGET     4   0      ; util
0030    TGETS    4   4   1  ; "sortedpairs"
0031    MOV      5   3
0032    CALL     4   4   2
0033    JMP      7 => 0055
0034 => UGET     9   0      ; util
0035    TGETS    9   9   1  ; "sortedpairs"
0036    MOV     10   8
0037    CALL     9   4   2
0038    JMP     12 => 0053
0039 => TGETV   14   2  12
0040    IST         14
0041    JMP     14 => 0053
0042    GGET    14   3      ; "table"
0043    TGETS   14  14   4  ; "insert"
0044    MOV     15   1
0045    MOV     17  12
0046    TGETS   16  12   5  ; "lower"
0047    CALL    16   2   2
0048    KSTR    17   6      ; " (on "
0049    MOV     18   7
0050    KSTR    19   7      ; ")"
0051    CAT     16  16  19
0052    CALL    14   1   3
0053 => ITERC   12   3   3
0054    ITERL   12 => 0039
0055 => ITERC    7   3   3
0056    ITERL    7 => 0034
0057 => KSTR     4   8      ; "<p><b>External dependencies:</b> "
0058    GGET     5   3      ; "table"
0059    TGETS    5   5   9  ; "concat"
0060    MOV      6   1
0061    KSTR     7  10      ; ",&nbsp;"
0062    CALL     5   2   3
0063    KSTR     6  11      ; "</p>"
0064    CAT      4   4   6
0065    RET1     4   2
0066    JMP      1 => 0069
0067 => KSTR     1  12      ; ""
0068    RET1     1   2
0069 => RET0     0   1

-- BYTECODE -- index.lua:140-140
0001    TGETS    2   0   0  ; "arch"
0002    TGETS    3   1   0  ; "arch"
0003    ISLT     2   3
0004    JMP      2 => 0007
0005    KPRI     2   1
0006    JMP      3 => 0008
0007 => KPRI     2   2
0008 => RET1     2   2

-- BYTECODE -- index.lua:126-183
0001    UGET     1   0      ; fs
0002    TGETS    1   1   0  ; "is_dir"
0003    MOV      2   0
0004    CALL     1   2   2
0005    IST          1
0006    JMP      1 => 0012
0007    KPRI     1   0
0008    KSTR     2   1      ; "Cannot access repository at "
0009    MOV      3   0
0010    CAT      2   2   3
0011    UCLO     0 => 0239
0012 => UGET     1   1      ; manif
0013    TGETS    1   1   2  ; "load_manifest"
0014    MOV      2   0
0015    CALL     1   2   2
0016    GGET     2   3      ; "io"
0017    TGETS    2   2   4  ; "open"
0018    UGET     3   2      ; dir
0019    TGETS    3   3   5  ; "path"
0020    MOV      4   0
0021    KSTR     5   6      ; "index.html"
0022    CALL     3   2   3
0023    KSTR     4   7      ; "w"
0024    CALL     2   2   3
0025    MOV      4   2
0026    TGETS    3   2   8  ; "write"
0027    UGET     5   3      ; index_header
0028    CALL     3   1   3
0029    UGET     3   4      ; util
0030    TGETS    3   3   9  ; "sortedpairs"
0031    TGETS    4   1  10  ; "repository"
0032    CALL     3   4   2
0033    JMP      6 => 0210
0034 => KPRI     8   0
0035    UGET     9   5      ; index_package_begin
0036    UGET    10   4      ; util
0037    TGETS   10  10   9  ; "sortedpairs"
0038    MOV     11   7
0039    UGET    12   6      ; vers
0040    TGETS   12  12  11  ; "compare_versions"
0041    CALL    10   4   3
0042    JMP     13 => 0100
0043 => TNEW    15   0
0044    MOV     16   9
0045    MOV     17  13
0046    KSTR    18  12      ; ":&nbsp;"
0047    CAT      9  16  18
0048    GGET    16  13      ; "table"
0049    TGETS   16  16  14  ; "sort"
0050    MOV     17  14
0051    FNEW    18  15      ; index.lua:140
0052    CALL    16   1   3
0053    GGET    16  16      ; "ipairs"
0054    MOV     17  14
0055    CALL    16   4   2
0056    JMP     19 => 0090
0057 => KPRI    21   0
0058    TGETS   22  20  17  ; "arch"
0059    ISNES   22  18      ; "rockspec"
0060    JMP     22 => 0072
0061    KSTR    22  19      ; "%s-%s.rockspec"
0062    MOV     23  22
0063    TGETS   22  22  20  ; "format"
0064    MOV     24   6
0065    MOV     25  13
0066    CALL    22   2   4
0067    MOV     21  22
0068    IST          8
0069    JMP     22 => 0080
0070    MOV      8  21
0071    JMP     22 => 0080
0072 => KSTR    22  21      ; "%s-%s.%s.rock"
0073    MOV     23  22
0074    TGETS   22  22  20  ; "format"
0075    MOV     24   6
0076    MOV     25  13
0077    TGETS   26  20  17  ; "arch"
0078    CALL    22   2   5
0079    MOV     21  22
0080 => GGET    22  13      ; "table"
0081    TGETS   22  22  22  ; "insert"
0082    MOV     23  15
0083    KSTR    24  23      ; "<a href=""
0084    MOV     25  21
0085    KSTR    26  24      ; "">"
0086    TGETS   27  20  17  ; "arch"
0087    KSTR    28  25      ; "</a>"
0088    CAT     24  24  28
0089    CALL    22   1   3
0090 => ITERC   19   3   3
0091    ITERL   19 => 0057
0092    MOV     16   9
0093    GGET    17  13      ; "table"
0094    TGETS   17  17  26  ; "concat"
0095    MOV     18  15
0096    KSTR    19  27      ; ",&nbsp;"
0097    CALL    17   2   3
0098    KSTR    18  28      ; "<br/>"
0099    CAT      9  16  18
0100 => ITERC   13   3   3
0101    ITERL   13 => 0043
0102    MOV     10   9
0103    UGET    11   7      ; index_package_end
0104    CAT      9  10  11
0105    ISF          8
0106    JMP     10 => 0188
0107    UGET    10   8      ; persist
0108    TGETS   10  10  29  ; "load_into_table"
0109    UGET    11   2      ; dir
0110    TGETS   11  11   5  ; "path"
0111    MOV     12   0
0112    MOV     13   8
0113    CALL    11   0   3
0114    CALLM   10   2   0
0115    TGETS   11  10  30  ; "description"
0116    IST         11
0117    JMP     12 => 0119
0118    TNEW    11   0
0119 => TDUP    12  31
0120    TSETS    6  12  32  ; "anchor"
0121    TGETS   13  10  33  ; "package"
0122    TSETS   13  12  33  ; "package"
0123    TGETS   13  10  34  ; "source"
0124    TGETS   13  13  35  ; "url"
0125    TSETS   13  12  36  ; "original"
0126    TGETS   13  11  37  ; "summary"
0127    IST         13
0128    JMP     14 => 0130
0129    KSTR    13  38      ; ""
0130 => TSETS   13  12  37  ; "summary"
0131    TGETS   13  11  39  ; "detailed"
0132    IST         13
0133    JMP     14 => 0135
0134    KSTR    13  38      ; ""
0135 => TSETS   13  12  39  ; "detailed"
0136    TGETS   13  11  40  ; "license"
0137    IST         13
0138    JMP     14 => 0140
0139    KSTR    13  41      ; "N/A"
0140 => TSETS   13  12  40  ; "license"
0141    TGETS   13  11  42  ; "homepage"
0142    ISF         13
0143    JMP     14 => 0152
0144    KSTR    13  43      ; "| <a href=""
0145    TGETS   14  11  42  ; "homepage"
0146    KSTR    15  44      ; """
0147    UGET    16   9      ; ext_url_target
0148    KSTR    17  45      ; ">project homepage</a>"
0149    CAT     13  13  17
0150    IST         13
0151    JMP     14 => 0153
0152 => KSTR    13  38      ; ""
0153 => TSETS   13  12  42  ; "homepage"
0154    UGET    13  10      ; index
0155    TGETS   13  13  46  ; "format_external_dependencies"
0156    MOV     14  10
0157    CALL    13   2   2
0158    TSETS   13  12  47  ; "externaldependencies"
0159    TGETS   13  12  39  ; "detailed"
0160    MOV     14  13
0161    TGETS   13  13  48  ; "gsub"
0162    KSTR    15  49      ; "\n\n"
0163    KSTR    16  50      ; "</p><p>"
0164    CALL    13   2   4
0165    MOV     14  13
0166    TGETS   13  13  48  ; "gsub"
0167    KSTR    15  51      ; "%s+"
0168    KSTR    16  52      ; " "
0169    CALL    13   2   4
0170    TSETS   13  12  39  ; "detailed"
0171    TGETS   13  12  39  ; "detailed"
0172    MOV     14  13
0173    TGETS   13  13  48  ; "gsub"
0174    KSTR    15  53      ; "(https?://[a-zA-Z0-9%.%%-_%+%[%]=%?&/$@;"~
0175    KSTR    16  54      ; "<a href="%1""
0176    UGET    17   9      ; ext_url_target
0177    KSTR    18  55      ; ">%1</a>"
0178    CAT     16  16  18
0179    CALL    13   2   4
0180    TSETS   13  12  39  ; "detailed"
0181    MOV     14   9
0182    TGETS   13   9  48  ; "gsub"
0183    KSTR    15  56      ; "$(%w+)"
0184    MOV     16  12
0185    CALL    13   2   4
0186    MOV      9  13
0187    JMP     10 => 0206
0188 => MOV     11   9
0189    TGETS   10   9  48  ; "gsub"
0190    KSTR    12  57      ; "$anchor"
0191    MOV     13   6
0192    CALL    10   2   4
0193    MOV      9  10
0194    MOV     11   9
0195    TGETS   10   9  48  ; "gsub"
0196    KSTR    12  58      ; "$package"
0197    MOV     13   6
0198    CALL    10   2   4
0199    MOV      9  10
0200    MOV     11   9
0201    TGETS   10   9  48  ; "gsub"
0202    KSTR    12  56      ; "$(%w+)"
0203    KSTR    13  38      ; ""
0204    CALL    10   2   4
0205    MOV      9  10
0206 => MOV     11   2
0207    TGETS   10   2   8  ; "write"
0208    MOV     12   9
0209    CALL    10   1   3
0210 => ITERC    6   3   3
0211    ITERL    6 => 0034
0212    MOV      4   2
0213    TGETS    3   2   8  ; "write"
0214    UGET     5  11      ; index_footer_begin
0215    CALL     3   1   3
0216    UGET     3   4      ; util
0217    TGETS    3   3  59  ; "lua_versions"
0218    CALL     3   4   1
0219    JMP      6 => 0229
0220 => MOV      8   2
0221    TGETS    7   2   8  ; "write"
0222    UGET     9  12      ; index_manifest_ver
0223    MOV     10   9
0224    TGETS    9   9  48  ; "gsub"
0225    KSTR    11  60      ; "$VER"
0226    MOV     12   6
0227    CALL     9   2   4
0228    CALL     7   1   3
0229 => ITERC    6   2   3
0230    ITERL    6 => 0220
0231    MOV      4   2
0232    TGETS    3   2   8  ; "write"
0233    UGET     5  13      ; index_footer_end
0234    CALL     3   1   3
0235    MOV      4   2
0236    TGETS    3   2  61  ; "close"
0237    CALL     3   1   2
0238    RET0     0   1
0239 => RET      1   3

-- BYTECODE -- index.lua:0-186
0001    TNEW     0   0
0002    GGET     1   0      ; "require"
0003    KSTR     2   1      ; "luarocks.util"
0004    CALL     1   2   2
0005    GGET     2   0      ; "require"
0006    KSTR     3   2      ; "luarocks.fs"
0007    CALL     2   2   2
0008    GGET     3   0      ; "require"
0009    KSTR     4   3      ; "luarocks.core.vers"
0010    CALL     3   2   2
0011    GGET     4   0      ; "require"
0012    KSTR     5   4      ; "luarocks.persist"
0013    CALL     4   2   2
0014    GGET     5   0      ; "require"
0015    KSTR     6   5      ; "luarocks.dir"
0016    CALL     5   2   2
0017    GGET     6   0      ; "require"
0018    KSTR     7   6      ; "luarocks.manif"
0019    CALL     6   2   2
0020    KSTR     7   7      ; " target="_blank""
0021    KSTR     8   8      ; "<!DOCTYPE html PUBLIC "-//W3C//DTD HTML "~
0022    KSTR     9   9      ; "<td class="package">\n<p><a name="$ancho"~
0023    KSTR    10  10      ; "</td></tr>\n<tr><td colspan="2" class="s"~
0024    KSTR    11  11      ; "</table>\n<p class="manifest">\n<a href="~
0025    KSTR    12  12      ; "&bull; <a href="manifest-$VER">Lua $VER "~
0026    KSTR    13  13      ; "</p>\n</body>\n</html>\n"
0027    FNEW    14  15      ; index.lua:98
0028    TSETS   14   0  14  ; "format_external_dependencies"
0029    FNEW    14  17      ; index.lua:126
0030    TSETS   14   0  16  ; "make_index"
0031    UCLO     0 => 0032
0032 => RET1     0   2

