-- BYTECODE -- init.lua:13-23
0001    MOV      2   0
0002    TGETS    1   0   0  ; "command"
0003    KSTR     3   1      ; "init"
0004    KSTR     4   2      ; "Initialize a directory for a Lua project"~
0005    UGET     5   0      ; util
0006    TGETS    5   5   3  ; "see_also"
0007    CALL     5   0   1
0008    CALLM    1   2   3
0009    MOV      3   1
0010    TGETS    2   1   4  ; "argument"
0011    KSTR     4   5      ; "name"
0012    KSTR     5   6      ; "The project name."
0013    CALL     2   2   4
0014    MOV      3   2
0015    TGETS    2   2   7  ; "args"
0016    KSTR     4   8      ; "?"
0017    CALL     2   1   3
0018    MOV      3   1
0019    TGETS    2   1   4  ; "argument"
0020    KSTR     4   9      ; "version"
0021    KSTR     5  10      ; "An optional project version."
0022    CALL     2   2   4
0023    MOV      3   2
0024    TGETS    2   2   7  ; "args"
0025    KSTR     4   8      ; "?"
0026    CALL     2   1   3
0027    MOV      3   1
0028    TGETS    2   1  11  ; "flag"
0029    KSTR     4  12      ; "--reset"
0030    KSTR     5  13      ; "Delete .luarocks/config-5.x.lua and ./lu"~
0031    CALL     2   1   4
0032    MOV      3   1
0033    TGETS    2   1  14  ; "group"
0034    KSTR     4  15      ; "Options for specifying rockspec data"
0035    UGET     5   1      ; write_rockspec
0036    TGETS    5   5  16  ; "cmd_options"
0037    MOV      6   1
0038    CALL     5   0   2
0039    CALLM    2   1   2
0040    RET0     0   1

-- BYTECODE -- init.lua:25-42
0001    KSTR     1   0      ; ""
0002    GGET     2   1      ; "io"
0003    TGETS    2   2   2  ; "open"
0004    KSTR     3   3      ; ".gitignore"
0005    KSTR     4   4      ; "r"
0006    CALL     2   2   3
0007    ISF          2
0008    JMP      3 => 0021
0009    MOV      4   2
0010    TGETS    3   2   5  ; "read"
0011    KSTR     5   6      ; "*a"
0012    CALL     3   2   3
0013    MOV      1   3
0014    MOV      4   2
0015    TGETS    3   2   7  ; "close"
0016    CALL     3   1   2
0017    KSTR     3   8      ; "\n"
0018    MOV      4   1
0019    KSTR     5   8      ; "\n"
0020    CAT      1   3   5
0021 => GGET     3   1      ; "io"
0022    TGETS    3   3   2  ; "open"
0023    KSTR     4   3      ; ".gitignore"
0024    ISF          1
0025    JMP      5 => 0028
0026    KSTR     5   9      ; "a"
0027    JMP      6 => 0029
0028 => KSTR     5  10      ; "w"
0029 => CALL     3   2   3
0030    MOV      2   3
0031    GGET     3  11      ; "ipairs"
0032    MOV      4   0
0033    CALL     3   4   2
0034    JMP      6 => 0055
0035 => KSTR     8  12      ; "/"
0036    MOV      9   7
0037    CAT      7   8   9
0038    MOV      9   1
0039    TGETS    8   1  13  ; "find"
0040    KSTR    10   8      ; "\n"
0041    MOV     11   7
0042    KSTR    12   8      ; "\n"
0043    CAT     10  10  12
0044    KSHORT  11   1
0045    KPRI    12   2
0046    CALL     8   2   5
0047    IST          8
0048    JMP      8 => 0055
0049    MOV      9   2
0050    TGETS    8   2  14  ; "write"
0051    MOV     10   7
0052    KSTR    11   8      ; "\n"
0053    CAT     10  10  11
0054    CALL     8   1   3
0055 => ITERC    6   3   3
0056    ITERL    6 => 0035
0057    MOV      4   2
0058    TGETS    3   2   7  ; "close"
0059    CALL     3   1   2
0060    RET0     0   1

-- BYTECODE -- init.lua:46-174
0001    UGET     1   0      ; fs
0002    TGETS    1   1   0  ; "current_dir"
0003    CALL     1   2   1
0004    TGETS    2   0   1  ; "name"
0005    IST          2
0006    JMP      2 => 0018
0007    UGET     2   1      ; dir
0008    TGETS    2   2   2  ; "base_name"
0009    MOV      3   1
0010    CALL     2   2   2
0011    TSETS    2   0   1  ; "name"
0012    TGETS    2   0   1  ; "name"
0013    ISNES    2   3      ; "/"
0014    JMP      2 => 0018
0015    KPRI     2   0
0016    KSTR     3   4      ; "When running from the root directory, pl"~
0017    RET      2   3
0018 => UGET     2   2      ; util
0019    TGETS    2   2   5  ; "title"
0020    KSTR     3   6      ; "Initializing project '"
0021    TGETS    4   0   1  ; "name"
0022    KSTR     5   7      ; "' for Lua "
0023    UGET     6   3      ; cfg
0024    TGETS    6   6   8  ; "lua_version"
0025    KSTR     7   9      ; " ..."
0026    CAT      3   3   7
0027    CALL     2   1   2
0028    UGET     2   2      ; util
0029    TGETS    2   2  10  ; "printout"
0030    KSTR     3  11      ; "Checking your Lua installation ..."
0031    CALL     2   1   2
0032    UGET     2   3      ; cfg
0033    TGETS    2   2  12  ; "lua_found"
0034    IST          2
0035    JMP      2 => 0039
0036    KPRI     2   0
0037    KSTR     3  13      ; "Lua installation is not found."
0038    RET      2   3
0039 => UGET     2   4      ; deps
0040    TGETS    2   2  14  ; "check_lua_incdir"
0041    UGET     3   3      ; cfg
0042    TGETS    3   3  15  ; "variables"
0043    CALL     2   3   2
0044    IST          2
0045    JMP      4 => 0049
0046    KPRI     4   0
0047    MOV      5   3
0048    RET      4   3
0049 => KPRI     4   1
0050    UGET     5   0      ; fs
0051    TGETS    5   5  16  ; "dir"
0052    CALL     5   4   1
0053    JMP      8 => 0062
0054 => MOV     10   8
0055    TGETS    9   8  17  ; "match"
0056    KSTR    11  18      ; "%.rockspec$"
0057    CALL     9   2   3
0058    ISF          9
0059    JMP     10 => 0062
0060    KPRI     4   2
0061    JMP      5 => 0064
0062 => ITERC    8   2   3
0063    ITERL    8 => 0054
0064 => IST          4
0065    JMP      5 => 0082
0066    TGETS    5   0  19  ; "version"
0067    IST          5
0068    JMP      6 => 0070
0069    KSTR     5  20      ; "dev"
0070 => TSETS    5   0  19  ; "version"
0071    TSETS    1   0  21  ; "location"
0072    UGET     5   5      ; write_rockspec
0073    TGETS    5   5  22  ; "command"
0074    MOV      6   0
0075    CALL     5   3   2
0076    IST          5
0077    JMP      7 => 0082
0078    UGET     7   2      ; util
0079    TGETS    7   7  23  ; "printerr"
0080    MOV      8   6
0081    CALL     7   1   2
0082 => UGET     5   3      ; cfg
0083    TGETS    5   5  24  ; "wrapper_suffix"
0084    KSTR     6  25      ; "luarocks"
0085    MOV      7   5
0086    CAT      6   6   7
0087    KSTR     7  26      ; "lua"
0088    MOV      8   5
0089    CAT      7   7   8
0090    UGET     8   2      ; util
0091    TGETS    8   8  10  ; "printout"
0092    KSTR     9  27      ; "Adding entries to .gitignore ..."
0093    CALL     8   1   2
0094    UGET     8   6      ; write_gitignore
0095    TDUP     9  28
0096    TSETB    6   9   1
0097    TSETB    7   9   2
0098    CALL     8   1   2
0099    UGET     8   2      ; util
0100    TGETS    8   8  10  ; "printout"
0101    KSTR     9  29      ; "Preparing ./.luarocks/ ..."
0102    CALL     8   1   2
0103    UGET     8   0      ; fs
0104    TGETS    8   8  30  ; "make_dir"
0105    KSTR     9  31      ; ".luarocks"
0106    CALL     8   1   2
0107    KSTR     8  32      ; ".luarocks/config-"
0108    UGET     9   3      ; cfg
0109    TGETS    9   9   8  ; "lua_version"
0110    KSTR    10  33      ; ".lua"
0111    CAT      8   8  10
0112    TGETS    9   0  34  ; "reset"
0113    ISF          9
0114    JMP     10 => 0123
0115    UGET     9   0      ; fs
0116    TGETS    9   9  35  ; "delete"
0117    MOV     10   7
0118    CALL     9   1   2
0119    UGET     9   0      ; fs
0120    TGETS    9   9  35  ; "delete"
0121    MOV     10   8
0122    CALL     9   1   2
0123 => UGET     9   7      ; persist
0124    TGETS    9   9  36  ; "load_config_file_if_basic"
0125    MOV     10   8
0126    UGET    11   3      ; cfg
0127    CALL     9   3   3
0128    ISF          9
0129    JMP     11 => 0189
0130    TDUP    11  37
0131    GGET    12  38      ; "ipairs"
0132    MOV     13  11
0133    CALL    12   4   2
0134    JMP     15 => 0142
0135 => UGET    17   3      ; cfg
0136    TGETV   17  17  16
0137    ISF         17
0138    JMP     18 => 0142
0139    UGET    17   3      ; cfg
0140    TGETV   17  17  16
0141    TSETV   17   9  16
0142 => ITERC   15   3   3
0143    ITERL   15 => 0135
0144    TDUP    12  39
0145    GGET    13  38      ; "ipairs"
0146    MOV     14  12
0147    CALL    13   4   2
0148    JMP     16 => 0164
0149 => UGET    18   3      ; cfg
0150    TGETS   18  18  15  ; "variables"
0151    TGETV   18  18  17
0152    ISF         18
0153    JMP     19 => 0164
0154    TGETS   18   9  15  ; "variables"
0155    IST         18
0156    JMP     19 => 0158
0157    TNEW    18   0
0158 => TSETS   18   9  15  ; "variables"
0159    TGETS   18   9  15  ; "variables"
0160    UGET    19   3      ; cfg
0161    TGETS   19  19  15  ; "variables"
0162    TGETV   19  19  17
0163    TSETV   19  18  17
0164 => ITERC   16   3   3
0165    ITERL   16 => 0149
0166    UGET    13   7      ; persist
0167    TGETS   13  13  40  ; "save_from_table"
0168    MOV     14   8
0169    MOV     15   9
0170    CALL    13   3   3
0171    ISF         13
0172    JMP     15 => 0180
0173    UGET    15   2      ; util
0174    TGETS   15  15  10  ; "printout"
0175    KSTR    16  41      ; "Wrote "
0176    MOV     17   8
0177    CAT     16  16  17
0178    CALL    15   1   2
0179    JMP     15 => 0195
0180 => UGET    15   2      ; util
0181    TGETS   15  15  10  ; "printout"
0182    KSTR    16  42      ; "Failed writing "
0183    MOV     17   8
0184    KSTR    18  43      ; ": "
0185    MOV     19  14
0186    CAT     16  16  19
0187    CALL    15   1   2
0188    JMP     11 => 0195
0189 => UGET    11   2      ; util
0190    TGETS   11  11  10  ; "printout"
0191    KSTR    12  44      ; "Will not attempt to overwrite "
0192    MOV     13   8
0193    CAT     12  12  13
0194    CALL    11   1   2
0195 => UGET    11   7      ; persist
0196    TGETS   11  11  45  ; "save_default_lua_version"
0197    KSTR    12  31      ; ".luarocks"
0198    UGET    13   3      ; cfg
0199    TGETS   13  13   8  ; "lua_version"
0200    CALL    11   3   3
0201    MOV     10  12
0202    MOV      2  11
0203    IST          2
0204    JMP     11 => 0211
0205    UGET    11   2      ; util
0206    TGETS   11  11  10  ; "printout"
0207    KSTR    12  46      ; "Failed setting default Lua version: "
0208    MOV     13  10
0209    CAT     12  12  13
0210    CALL    11   1   2
0211 => UGET    11   2      ; util
0212    TGETS   11  11  10  ; "printout"
0213    KSTR    12  47      ; "Preparing ./lua_modules/ ..."
0214    CALL    11   1   2
0215    UGET    11   0      ; fs
0216    TGETS   11  11  30  ; "make_dir"
0217    KSTR    12  48      ; "lua_modules/lib/luarocks/rocks-"
0218    UGET    13   3      ; cfg
0219    TGETS   13  13   8  ; "lua_version"
0220    CAT     12  12  13
0221    CALL    11   1   2
0222    UGET    11   1      ; dir
0223    TGETS   11  11  49  ; "path"
0224    MOV     12   1
0225    KSTR    13  50      ; "lua_modules"
0226    CALL    11   2   3
0227    UGET    12   1      ; dir
0228    TGETS   12  12  49  ; "path"
0229    KSTR    13  51      ; "."
0230    MOV     14   6
0231    CALL    12   2   3
0232    MOV      6  12
0233    UGET    12   0      ; fs
0234    TGETS   12  12  52  ; "exists"
0235    MOV     13   6
0236    CALL    12   2   2
0237    IST         12
0238    JMP     12 => 0257
0239    UGET    12   2      ; util
0240    TGETS   12  12  10  ; "printout"
0241    KSTR    13  53      ; "Preparing "
0242    MOV     14   6
0243    KSTR    15   9      ; " ..."
0244    CAT     13  13  15
0245    CALL    12   1   2
0246    UGET    12   0      ; fs
0247    TGETS   12  12  54  ; "wrap_script"
0248    GGET    13  55      ; "arg"
0249    TGETB   13  13   0
0250    KSTR    14  25      ; "luarocks"
0251    KSTR    15  56      ; "none"
0252    KNIL    16  17
0253    KSTR    18  57      ; "--project-tree"
0254    MOV     19  11
0255    CALL    12   1   8
0256    JMP     12 => 0263
0257 => UGET    12   2      ; util
0258    TGETS   12  12  10  ; "printout"
0259    MOV     13   6
0260    KSTR    14  58      ; " already exists. Not overwriting it!"
0261    CAT     13  13  14
0262    CALL    12   1   2
0263 => UGET    12   1      ; dir
0264    TGETS   12  12  49  ; "path"
0265    KSTR    13  51      ; "."
0266    MOV     14   7
0267    CALL    12   2   3
0268    MOV      7  12
0269    KPRI    12   2
0270    UGET    13   0      ; fs
0271    TGETS   13  13  52  ; "exists"
0272    MOV     14   7
0273    CALL    13   2   2
0274    ISF         13
0275    JMP     14 => 0289
0276    UGET    13   2      ; util
0277    TGETS   13  13  59  ; "lua_is_wrapper"
0278    MOV     14   7
0279    CALL    13   2   2
0280    IST         13
0281    JMP     13 => 0289
0282    UGET    13   2      ; util
0283    TGETS   13  13  10  ; "printout"
0284    MOV     14   7
0285    KSTR    15  60      ; " already exists and does not look like a"~
0286    CAT     14  14  15
0287    CALL    13   1   2
0288    KPRI    12   1
0289 => ISF         12
0290    JMP     13 => 0337
0291    UGET    13   1      ; dir
0292    TGETS   13  13  49  ; "path"
0293    UGET    14   3      ; cfg
0294    TGETS   14  14  15  ; "variables"
0295    TGETS   14  14  61  ; "LUA_BINDIR"
0296    UGET    15   3      ; cfg
0297    TGETS   15  15  62  ; "lua_interpreter"
0298    CALL    13   2   3
0299    UGET    14   2      ; util
0300    TGETS   14  14  63  ; "check_lua_version"
0301    MOV     15  13
0302    UGET    16   3      ; cfg
0303    TGETS   16  16   8  ; "lua_version"
0304    CALL    14   2   3
0305    ISF         14
0306    JMP     15 => 0328
0307    UGET    14   2      ; util
0308    TGETS   14  14  10  ; "printout"
0309    KSTR    15  53      ; "Preparing "
0310    MOV     16   7
0311    KSTR    17  64      ; " for version "
0312    UGET    18   3      ; cfg
0313    TGETS   18  18   8  ; "lua_version"
0314    KSTR    19  65      ; "..."
0315    CAT     15  15  19
0316    CALL    14   1   2
0317    UGET    14   8      ; path
0318    TGETS   14  14  66  ; "use_tree"
0319    MOV     15  11
0320    CALL    14   1   2
0321    UGET    14   0      ; fs
0322    TGETS   14  14  54  ; "wrap_script"
0323    KPRI    15   0
0324    KSTR    16  26      ; "lua"
0325    KSTR    17  67      ; "all"
0326    CALL    14   1   4
0327    JMP     14 => 0337
0328 => UGET    14   2      ; util
0329    TGETS   14  14  68  ; "warning"
0330    KSTR    15  69      ; "No Lua interpreter detected for version "
0331    UGET    16   3      ; cfg
0332    TGETS   16  16   8  ; "lua_version"
0333    KSTR    17  70      ; ". Not creating "
0334    MOV     18   7
0335    CAT     15  15  18
0336    CALL    14   1   2
0337 => KPRI    13   2
0338    RET1    13   2

-- BYTECODE -- init.lua:0-177
0001    TNEW     0   0
0002    GGET     1   0      ; "require"
0003    KSTR     2   1      ; "luarocks.core.cfg"
0004    CALL     1   2   2
0005    GGET     2   0      ; "require"
0006    KSTR     3   2      ; "luarocks.fs"
0007    CALL     2   2   2
0008    GGET     3   0      ; "require"
0009    KSTR     4   3      ; "luarocks.path"
0010    CALL     3   2   2
0011    GGET     4   0      ; "require"
0012    KSTR     5   4      ; "luarocks.deps"
0013    CALL     4   2   2
0014    GGET     5   0      ; "require"
0015    KSTR     6   5      ; "luarocks.dir"
0016    CALL     5   2   2
0017    GGET     6   0      ; "require"
0018    KSTR     7   6      ; "luarocks.util"
0019    CALL     6   2   2
0020    GGET     7   0      ; "require"
0021    KSTR     8   7      ; "luarocks.persist"
0022    CALL     7   2   2
0023    GGET     8   0      ; "require"
0024    KSTR     9   8      ; "luarocks.cmd.write_rockspec"
0025    CALL     8   2   2
0026    FNEW     9  10      ; init.lua:13
0027    TSETS    9   0   9  ; "add_to_parser"
0028    FNEW     9  11      ; init.lua:25
0029    FNEW    10  13      ; init.lua:46
0030    TSETS   10   0  12  ; "command"
0031    UCLO     0 => 0032
0032 => RET1     0   2

