-- BYTECODE -- lint.lua:10-17
0001    MOV      2   0
0002    TGETS    1   0   0  ; "command"
0003    KSTR     3   1      ; "lint"
0004    KSTR     4   2      ; "Check syntax of a rockspec.\n\n"
0005    KSTR     5   3      ; "Returns success if the text of the rocks"~
0006    CAT      4   4   5
0007    UGET     5   0      ; util
0008    TGETS    5   5   4  ; "see_also"
0009    CALL     5   0   1
0010    CALLM    1   2   3
0011    MOV      2   1
0012    TGETS    1   1   5  ; "summary"
0013    KSTR     3   6      ; "Check syntax of a rockspec."
0014    CALL     1   2   3
0015    MOV      3   1
0016    TGETS    2   1   7  ; "argument"
0017    KSTR     4   8      ; "rockspec"
0018    KSTR     5   9      ; "The rockspec to check."
0019    CALL     2   1   4
0020    RET0     0   1

-- BYTECODE -- lint.lua:19-48
0001    TGETS    1   0   0  ; "rockspec"
0002    MOV      3   1
0003    TGETS    2   1   1  ; "match"
0004    KSTR     4   2      ; ".rockspec$"
0005    CALL     2   2   3
0006    IST          2
0007    JMP      2 => 0023
0008    KPRI     2   0
0009    UGET     3   0      ; download
0010    TGETS    3   3   3  ; "download"
0011    KSTR     4   0      ; "rockspec"
0012    MOV      6   1
0013    TGETS    5   1   4  ; "lower"
0014    CALL     5   0   2
0015    CALLM    3   3   1
0016    MOV      2   4
0017    MOV      1   3
0018    IST          1
0019    JMP      3 => 0023
0020    KPRI     3   0
0021    MOV      4   2
0022    RET      3   3
0023 => UGET     2   1      ; fetch
0024    TGETS    2   2   5  ; "load_local_rockspec"
0025    MOV      3   1
0026    CALL     2   3   2
0027    IST          2
0028    JMP      4 => 0034
0029    KPRI     4   0
0030    KSTR     5   6      ; "Failed loading rockspec: "
0031    MOV      6   3
0032    CAT      5   5   6
0033    RET      4   3
0034 => KPRI     4   2
0035    TGETS    5   2   7  ; "description"
0036    TGETS    5   5   8  ; "license"
0037    IST          5
0038    JMP      5 => 0044
0039    UGET     5   2      ; util
0040    TGETS    5   5   9  ; "printerr"
0041    KSTR     6  10      ; "Rockspec has no license field."
0042    CALL     5   1   2
0043    KPRI     4   1
0044 => MOV      5   4
0045    ISTC     6   4
0046    JMP      6 => 0050
0047    MOV      6   1
0048    KSTR     7  11      ; " failed consistency checks."
0049    CAT      6   6   7
0050 => RET      5   3

-- BYTECODE -- lint.lua:0-51
0001    TNEW     0   0
0002    GGET     1   0      ; "require"
0003    KSTR     2   1      ; "luarocks.util"
0004    CALL     1   2   2
0005    GGET     2   0      ; "require"
0006    KSTR     3   2      ; "luarocks.download"
0007    CALL     2   2   2
0008    GGET     3   0      ; "require"
0009    KSTR     4   3      ; "luarocks.fetch"
0010    CALL     3   2   2
0011    FNEW     4   5      ; lint.lua:10
0012    TSETS    4   0   4  ; "add_to_parser"
0013    FNEW     4   7      ; lint.lua:19
0014    TSETS    4   0   6  ; "command"
0015    UCLO     0 => 0016
0016 => RET1     0   2

