
main <./loader.lua:0,0> (128 instructions, 512 bytes at 0x7fb32d4068a0)
0+ params, 32 slots, 0 upvalues, 30 locals, 37 constants, 8 functions
	1	[8]	GETGLOBAL	0 -1	; package
	2	[8]	GETTABLE 	0 0 -2	; "loaders"
	3	[8]	TEST     	0 0 1
	4	[8]	JMP      	2	; to 7
	5	[8]	GETGLOBAL	0 -1	; package
	6	[8]	GETTABLE 	0 0 -3	; "searchers"
	7	[10]	GETGLOBAL	1 -4	; require
	8	[10]	GETGLOBAL	2 -5	; ipairs
	9	[10]	GETGLOBAL	3 -6	; table
	10	[10]	GETGLOBAL	4 -7	; type
	11	[10]	GETGLOBAL	5 -8	; next
	12	[10]	GETGLOBAL	6 -9	; tostring
	13	[10]	GETGLOBAL	7 -10	; error
	14	[11]	GETGLOBAL	8 -11	; unpack
	15	[11]	TEST     	8 0 1
	16	[11]	JMP      	1	; to 18
	17	[11]	GETTABLE 	8 3 -11	; "unpack"
	18	[13]	NEWTABLE 	9 0 0
	19	[15]	GETGLOBAL	10 -1	; package
	20	[15]	GETTABLE 	10 10 -12	; "loaded"
	21	[15]	GETTABLE 	10 10 -13	; "luarocks.core.cfg"
	22	[15]	NOT      	10 10
	23	[18]	MOVE     	11 1
	24	[18]	LOADK    	12 -13	; "luarocks.core.cfg"
	25	[18]	CALL     	11 2 2
	26	[19]	GETTABLE 	12 11 -14	; "init"
	27	[19]	CALL     	12 1 3
	28	[20]	TEST     	12 0 0
	29	[20]	JMP      	2	; to 32
	30	[21]	GETTABLE 	14 11 -15	; "init_package_paths"
	31	[21]	CALL     	14 1 1
	32	[24]	MOVE     	14 1
	33	[24]	LOADK    	15 -16	; "luarocks.core.path"
	34	[24]	CALL     	14 2 2
	35	[25]	MOVE     	15 1
	36	[25]	LOADK    	16 -17	; "luarocks.core.manif"
	37	[25]	CALL     	15 2 2
	38	[26]	MOVE     	16 1
	39	[26]	LOADK    	17 -18	; "luarocks.core.vers"
	40	[26]	CALL     	16 2 2
	41	[27]	LOADNIL  	17 17
	42	[31]	LOADBOOL 	18 0 0
	43	[32]	GETGLOBAL	19 -19	; luarocks
	44	[32]	TEST     	19 0 0
	45	[32]	JMP      	3	; to 49
	46	[36]	GETGLOBAL	19 -19	; luarocks
	47	[36]	SETTABLE 	19 -20 9	; "loader" -
	48	[36]	JMP      	15	; to 64
	49	[43]	GETGLOBAL	19 -21	; debug
	50	[43]	GETTABLE 	19 19 -22	; "getinfo"
	51	[43]	LOADK    	20 -23	; 2
	52	[43]	LOADK    	21 -24	; "nS"
	53	[43]	CALL     	19 3 2
	54	[44]	GETTABLE 	20 19 -25	; "what"
	55	[44]	EQ       	0 20 -26	; - "C"
	56	[44]	JMP      	7	; to 64
	57	[44]	GETTABLE 	20 19 -27	; "name"
	58	[44]	TEST     	20 0 1
	59	[44]	JMP      	4	; to 64
	60	[45]	NEWTABLE 	20 0 1
	61	[45]	SETTABLE 	20 -20 9	; "loader" -
	62	[45]	SETGLOBAL	20 -19	; luarocks
	63	[46]	LOADBOOL 	18 1 0
	64	[52]	NEWTABLE 	19 0 0
	65	[52]	SETTABLE 	9 -28 19	; "context" -
	66	[75]	CLOSURE  	19 0	; 0x7fb32d407080
	67	[75]	MOVE     	0 18
	68	[75]	MOVE     	0 15
	69	[75]	MOVE     	0 9
	70	[58]	SETTABLE 	9 -29 19	; "add_context" -
	71	[83]	CLOSURE  	19 1	; 0x7fb32d407900
	72	[108]	CLOSURE  	20 2	; 0x7fb32d407a10
	73	[108]	MOVE     	0 2
	74	[108]	MOVE     	0 0
	75	[108]	MOVE     	0 9
	76	[108]	MOVE     	0 4
	77	[108]	MOVE     	0 8
	78	[124]	CLOSURE  	21 3	; 0x7fb32d408070
	79	[124]	MOVE     	0 2
	80	[124]	MOVE     	0 4
	81	[124]	MOVE     	0 7
	82	[124]	MOVE     	0 6
	83	[124]	MOVE     	0 9
	84	[124]	MOVE     	0 16
	85	[124]	MOVE     	0 3
	86	[167]	CLOSURE  	22 4	; 0x7fb32d408470
	87	[167]	MOVE     	0 15
	88	[167]	MOVE     	0 2
	89	[167]	MOVE     	0 21
	90	[167]	MOVE     	0 5
	91	[167]	MOVE     	0 3
	92	[167]	MOVE     	0 19
	93	[184]	CLOSURE  	23 5	; 0x7fb32d4091b0
	94	[184]	MOVE     	0 22
	95	[184]	MOVE     	0 14
	96	[193]	CLOSURE  	24 6	; 0x7fb32d409340
	97	[193]	MOVE     	0 22
	98	[193]	MOVE     	0 14
	99	[190]	SETTABLE 	9 -30 24	; "which" -
	100	[212]	CLOSURE  	24 7	; 0x7fb32d409bd0
	101	[212]	MOVE     	0 23
	102	[212]	MOVE     	0 9
	103	[212]	MOVE     	0 20
	104	[204]	SETTABLE 	9 -31 24	; "luarocks_loader" -
	105	[214]	GETTABLE 	24 3 -32	; "insert"
	106	[214]	MOVE     	25 0
	107	[214]	LOADK    	26 -33	; 1
	108	[214]	GETTABLE 	27 9 -31	; "luarocks_loader"
	109	[214]	CALL     	24 4 1
	110	[216]	TEST     	10 0 0
	111	[216]	JMP      	15	; to 127
	112	[217]	GETGLOBAL	24 -34	; pairs
	113	[217]	GETGLOBAL	25 -1	; package
	114	[217]	GETTABLE 	25 25 -12	; "loaded"
	115	[217]	CALL     	24 2 4
	116	[217]	JMP      	8	; to 125
	117	[218]	SELF     	29 27 -35	; "match"
	118	[218]	LOADK    	31 -36	; "^luarocks%."
	119	[218]	CALL     	29 3 2
	120	[218]	TEST     	29 0 0
	121	[218]	JMP      	3	; to 125
	122	[219]	GETGLOBAL	29 -1	; package
	123	[219]	GETTABLE 	29 29 -12	; "loaded"
	124	[219]	SETTABLE 	29 27 -37	; - nil
	125	[217]	TFORLOOP 	24 2
	126	[220]	JMP      	-10	; to 117
	127	[224]	RETURN   	9 2
	128	[224]	RETURN   	0 1

function <./loader.lua:58,75> (24 instructions, 96 bytes at 0x7fb32d407080)
2 params, 8 slots, 3 upvalues, 3 locals, 4 constants, 0 functions
	1	[62]	GETUPVAL 	2 0	; temporary_global
	2	[62]	TEST     	2 0 0
	3	[62]	JMP      	4	; to 8
	4	[65]	LOADNIL  	2 2
	5	[65]	SETGLOBAL	2 -1	; luarocks
	6	[66]	LOADBOOL 	2 0 0
	7	[66]	SETUPVAL 	2 0	; temporary_global
	8	[69]	GETUPVAL 	2 1	; manif
	9	[69]	GETTABLE 	2 2 -2	; "load_rocks_tree_manifests"
	10	[69]	CALL     	2 1 2
	11	[70]	TEST     	2 0 1
	12	[70]	JMP      	2	; to 15
	13	[71]	LOADNIL  	3 3
	14	[71]	RETURN   	3 2
	15	[74]	GETUPVAL 	3 1	; manif
	16	[74]	GETTABLE 	3 3 -3	; "scan_dependencies"
	17	[74]	MOVE     	4 0
	18	[74]	MOVE     	5 1
	19	[74]	MOVE     	6 2
	20	[74]	GETUPVAL 	7 2	; loader
	21	[74]	GETTABLE 	7 7 -4	; "context"
	22	[74]	TAILCALL 	3 5 0
	23	[74]	RETURN   	3 0
	24	[75]	RETURN   	0 1

function <./loader.lua:81,83> (8 instructions, 32 bytes at 0x7fb32d407900)
2 params, 4 slots, 0 upvalues, 2 locals, 1 constant, 0 functions
	1	[82]	GETTABLE 	2 0 -1	; "version"
	2	[82]	GETTABLE 	3 1 -1	; "version"
	3	[82]	LT       	1 3 2
	4	[82]	JMP      	1	; to 6
	5	[82]	LOADBOOL 	2 0 1
	6	[82]	LOADBOOL 	2 1 0
	7	[82]	RETURN   	2 2
	8	[83]	RETURN   	0 1

function <./loader.lua:98,108> (33 instructions, 132 bytes at 0x7fb32d407a10)
4 params, 12 slots, 5 upvalues, 10 locals, 6 constants, 0 functions
	1	[99]	GETUPVAL 	4 0	; ipairs
	2	[99]	GETUPVAL 	5 1	; loaders
	3	[99]	CALL     	4 2 4
	4	[99]	JMP      	18	; to 23
	5	[100]	GETUPVAL 	9 2	; loader
	6	[100]	GETTABLE 	9 9 -1	; "luarocks_loader"
	7	[100]	EQ       	1 8 9
	8	[100]	JMP      	14	; to 23
	9	[101]	NEWTABLE 	9 0 0
	10	[101]	MOVE     	10 8
	11	[101]	MOVE     	11 3
	12	[101]	CALL     	10 2 0
	13	[101]	SETLIST  	9 0 1	; 1
	14	[102]	GETUPVAL 	10 3	; type
	15	[102]	GETTABLE 	11 9 -2	; 1
	16	[102]	CALL     	10 2 2
	17	[102]	EQ       	0 10 -3	; - "function"
	18	[102]	JMP      	4	; to 23
	19	[103]	GETUPVAL 	10 4	; unpack
	20	[103]	MOVE     	11 9
	21	[103]	TAILCALL 	10 2 0
	22	[103]	RETURN   	10 0
	23	[99]	TFORLOOP 	4 2
	24	[105]	JMP      	-20	; to 5
	25	[107]	LOADK    	4 -4	; "Failed loading module "
	26	[107]	MOVE     	5 0
	27	[107]	LOADK    	6 -5	; " in LuaRocks rock "
	28	[107]	MOVE     	7 1
	29	[107]	LOADK    	8 -6	; " "
	30	[107]	MOVE     	9 2
	31	[107]	CONCAT   	4 4 9
	32	[107]	RETURN   	4 2
	33	[108]	RETURN   	0 1

function <./loader.lua:110,124> (69 instructions, 276 bytes at 0x7fb32d408070)
5 params, 21 slots, 7 upvalues, 13 locals, 18 constants, 0 functions
	1	[111]	GETUPVAL 	5 0	; ipairs
	2	[111]	MOVE     	6 1
	3	[111]	CALL     	5 2 4
	4	[111]	JMP      	62	; to 67
	5	[112]	SELF     	10 9 -1	; "match"
	6	[112]	LOADK    	12 -2	; "^([^/]*)/(.*)$"
	7	[112]	CALL     	10 3 3
	8	[113]	GETTABLE 	12 2 -3	; "manifest"
	9	[113]	GETTABLE 	12 12 -4	; "repository"
	10	[113]	GETTABLE 	12 12 10
	11	[113]	GETTABLE 	12 12 11
	12	[113]	GETTABLE 	12 12 -5	; 1
	13	[113]	GETTABLE 	12 12 -6	; "modules"
	14	[113]	GETTABLE 	12 12 3
	15	[114]	GETUPVAL 	13 1	; type
	16	[114]	MOVE     	14 12
	17	[114]	CALL     	13 2 2
	18	[114]	EQ       	1 13 -7	; - "string"
	19	[114]	JMP      	16	; to 36
	20	[115]	GETUPVAL 	13 2	; error
	21	[115]	LOADK    	14 -8	; "Invalid data in manifest file for module "
	22	[115]	GETUPVAL 	15 3	; tostring
	23	[115]	MOVE     	16 3
	24	[115]	CALL     	15 2 2
	25	[115]	LOADK    	16 -9	; " (invalid data for "
	26	[115]	GETUPVAL 	17 3	; tostring
	27	[115]	MOVE     	18 10
	28	[115]	CALL     	17 2 2
	29	[115]	LOADK    	18 -10	; " "
	30	[115]	GETUPVAL 	19 3	; tostring
	31	[115]	MOVE     	20 11
	32	[115]	CALL     	19 2 2
	33	[115]	LOADK    	20 -11	; ")"
	34	[115]	CONCAT   	14 14 20
	35	[115]	CALL     	13 2 1
	36	[117]	MOVE     	13 4
	37	[117]	MOVE     	14 12
	38	[117]	MOVE     	15 10
	39	[117]	MOVE     	16 11
	40	[117]	GETTABLE 	17 2 -12	; "tree"
	41	[117]	MOVE     	18 8
	42	[117]	CALL     	13 6 2
	43	[117]	MOVE     	12 13
	44	[118]	GETUPVAL 	13 4	; loader
	45	[118]	GETTABLE 	13 13 -13	; "context"
	46	[118]	GETTABLE 	13 13 10
	47	[118]	EQ       	0 13 11
	48	[118]	JMP      	4	; to 53
	49	[119]	MOVE     	13 10
	50	[119]	MOVE     	14 11
	51	[119]	MOVE     	15 12
	52	[119]	RETURN   	13 4
	53	[121]	GETUPVAL 	13 5	; vers
	54	[121]	GETTABLE 	13 13 -14	; "parse_version"
	55	[121]	MOVE     	14 11
	56	[121]	CALL     	13 2 2
	57	[121]	MOVE     	11 13
	58	[122]	GETUPVAL 	13 6	; table
	59	[122]	GETTABLE 	13 13 -15	; "insert"
	60	[122]	MOVE     	14 0
	61	[122]	NEWTABLE 	15 0 4
	62	[122]	SETTABLE 	15 -16 10	; "name" -
	63	[122]	SETTABLE 	15 -17 11	; "version" -
	64	[122]	SETTABLE 	15 -18 12	; "module_name" -
	65	[122]	SETTABLE 	15 -12 2	; "tree" -
	66	[122]	CALL     	13 3 1
	67	[111]	TFORLOOP 	5 2
	68	[122]	JMP      	-64	; to 5
	69	[124]	RETURN   	0 1

function <./loader.lua:138,167> (63 instructions, 252 bytes at 0x7fb32d408470)
2 params, 17 slots, 6 upvalues, 12 locals, 11 constants, 0 functions
	1	[142]	GETUPVAL 	2 0	; manif
	2	[142]	GETTABLE 	2 2 -1	; "load_rocks_tree_manifests"
	3	[142]	CALL     	2 1 2
	4	[143]	TEST     	2 0 1
	5	[143]	JMP      	2	; to 8
	6	[144]	LOADNIL  	3 3
	7	[144]	RETURN   	3 2
	8	[147]	NEWTABLE 	3 0 0
	9	[148]	LOADNIL  	4 4
	10	[149]	GETUPVAL 	5 1	; ipairs
	11	[149]	MOVE     	6 2
	12	[149]	CALL     	5 2 4
	13	[149]	JMP      	30	; to 44
	14	[150]	GETTABLE 	10 9 -2	; "manifest"
	15	[150]	GETTABLE 	10 10 -3	; "modules"
	16	[150]	GETTABLE 	10 10 0
	17	[151]	TEST     	10 0 0
	18	[151]	JMP      	8	; to 27
	19	[152]	GETUPVAL 	11 2	; add_providers
	20	[152]	MOVE     	12 3
	21	[152]	MOVE     	13 10
	22	[152]	MOVE     	14 9
	23	[152]	MOVE     	15 0
	24	[152]	MOVE     	16 1
	25	[152]	CALL     	11 6 1
	26	[152]	JMP      	17	; to 44
	27	[154]	TEST     	4 0 1
	28	[154]	JMP      	3	; to 32
	29	[154]	MOVE     	11 0
	30	[154]	LOADK    	12 -4	; ".init"
	31	[154]	CONCAT   	4 11 12
	32	[155]	GETTABLE 	11 9 -2	; "manifest"
	33	[155]	GETTABLE 	11 11 -3	; "modules"
	34	[155]	GETTABLE 	10 11 4
	35	[156]	TEST     	10 0 0
	36	[156]	JMP      	7	; to 44
	37	[157]	GETUPVAL 	11 2	; add_providers
	38	[157]	MOVE     	12 3
	39	[157]	MOVE     	13 10
	40	[157]	MOVE     	14 9
	41	[157]	MOVE     	15 4
	42	[157]	MOVE     	16 1
	43	[157]	CALL     	11 6 1
	44	[149]	TFORLOOP 	5 2
	45	[159]	JMP      	-32	; to 14
	46	[162]	GETUPVAL 	5 3	; next
	47	[162]	MOVE     	6 3
	48	[162]	CALL     	5 2 2
	49	[162]	TEST     	5 0 0
	50	[162]	JMP      	12	; to 63
	51	[163]	GETUPVAL 	5 4	; table
	52	[163]	GETTABLE 	5 5 -5	; "sort"
	53	[163]	MOVE     	6 3
	54	[163]	GETUPVAL 	7 5	; sort_versions
	55	[163]	CALL     	5 3 1
	56	[164]	GETTABLE 	5 3 -6	; 1
	57	[165]	GETTABLE 	6 5 -7	; "name"
	58	[165]	GETTABLE 	7 5 -8	; "version"
	59	[165]	GETTABLE 	7 7 -9	; "string"
	60	[165]	GETTABLE 	8 5 -10	; "module_name"
	61	[165]	GETTABLE 	9 5 -11	; "tree"
	62	[165]	RETURN   	6 5
	63	[167]	RETURN   	0 1

function <./loader.lua:176,184> (7 instructions, 28 bytes at 0x7fb32d4091b0)
1 param, 4 slots, 2 upvalues, 1 local, 0 constants, 1 function
	1	[178]	GETUPVAL 	1 0	; select_module
	2	[178]	MOVE     	2 0
	3	[183]	CLOSURE  	3 0	; 0x7fb32d4093d0
	4	[183]	GETUPVAL 	0 1	; path
	5	[178]	TAILCALL 	1 3 0
	6	[183]	RETURN   	1 0
	7	[184]	RETURN   	0 1

function <./loader.lua:178,183> (16 instructions, 64 bytes at 0x7fb32d4093d0)
5 params, 10 slots, 1 upvalue, 5 locals, 4 constants, 0 functions
	1	[179]	LT       	0 -1 4	; 1 -
	2	[179]	JMP      	8	; to 11
	3	[180]	GETUPVAL 	5 0	; path
	4	[180]	GETTABLE 	5 5 -2	; "versioned_name"
	5	[180]	MOVE     	6 0
	6	[180]	LOADK    	7 -3	; ""
	7	[180]	MOVE     	8 1
	8	[180]	MOVE     	9 2
	9	[180]	CALL     	5 5 2
	10	[180]	MOVE     	0 5
	11	[182]	GETUPVAL 	5 0	; path
	12	[182]	GETTABLE 	5 5 -4	; "path_to_module"
	13	[182]	MOVE     	6 0
	14	[182]	TAILCALL 	5 2 0
	15	[182]	RETURN   	5 0
	16	[183]	RETURN   	0 1

function <./loader.lua:190,193> (10 instructions, 40 bytes at 0x7fb32d409340)
1 param, 7 slots, 2 upvalues, 4 locals, 1 constant, 0 functions
	1	[191]	GETUPVAL 	1 0	; select_module
	2	[191]	MOVE     	2 0
	3	[191]	GETUPVAL 	3 1	; path
	4	[191]	GETTABLE 	3 3 -1	; "which_i"
	5	[191]	CALL     	1 3 4
	6	[192]	MOVE     	4 3
	7	[192]	MOVE     	5 1
	8	[192]	MOVE     	6 2
	9	[192]	RETURN   	4 4
	10	[193]	RETURN   	0 1

function <./loader.lua:204,212> (23 instructions, 92 bytes at 0x7fb32d409bd0)
1 param, 9 slots, 3 upvalues, 4 locals, 2 constants, 0 functions
	1	[205]	GETUPVAL 	1 0	; pick_module
	2	[205]	MOVE     	2 0
	3	[205]	CALL     	1 2 4
	4	[206]	TEST     	1 0 1
	5	[206]	JMP      	5	; to 11
	6	[207]	LOADK    	4 -1	; "No LuaRocks module found for "
	7	[207]	MOVE     	5 0
	8	[207]	CONCAT   	4 4 5
	9	[207]	RETURN   	4 2
	10	[207]	JMP      	12	; to 23
	11	[209]	GETUPVAL 	4 1	; loader
	12	[209]	GETTABLE 	4 4 -2	; "add_context"
	13	[209]	MOVE     	5 1
	14	[209]	MOVE     	6 2
	15	[209]	CALL     	4 3 1
	16	[210]	GETUPVAL 	4 2	; call_other_loaders
	17	[210]	MOVE     	5 0
	18	[210]	MOVE     	6 1
	19	[210]	MOVE     	7 2
	20	[210]	MOVE     	8 3
	21	[210]	TAILCALL 	4 5 0
	22	[210]	RETURN   	4 0
	23	[212]	RETURN   	0 1
