
main <./build/make.lua:0,0> (25 instructions, 100 bytes at 0x7fc432c068a0)
0+ params, 7 slots, 0 upvalues, 6 locals, 7 constants, 2 functions
	1	[3]	NEWTABLE 	0 0 0
	2	[5]	GETGLOBAL	1 -1	; unpack
	3	[5]	TEST     	1 0 1
	4	[5]	JMP      	2	; to 7
	5	[5]	GETGLOBAL	1 -2	; table
	6	[5]	GETTABLE 	1 1 -1	; "unpack"
	7	[7]	GETGLOBAL	2 -3	; require
	8	[7]	LOADK    	3 -4	; "luarocks.fs"
	9	[7]	CALL     	2 2 2
	10	[8]	GETGLOBAL	3 -3	; require
	11	[8]	LOADK    	4 -5	; "luarocks.util"
	12	[8]	CALL     	3 2 2
	13	[9]	GETGLOBAL	4 -3	; require
	14	[9]	LOADK    	5 -6	; "luarocks.core.cfg"
	15	[9]	CALL     	4 2 2
	16	[35]	CLOSURE  	5 0	; 0x7fc432c06fa0
	17	[35]	MOVE     	0 2
	18	[35]	MOVE     	0 1
	19	[94]	CLOSURE  	6 1	; 0x7fc432c07610
	20	[94]	MOVE     	0 4
	21	[94]	MOVE     	0 3
	22	[94]	MOVE     	0 5
	23	[41]	SETTABLE 	0 -7 6	; "run" -
	24	[96]	RETURN   	0 2
	25	[96]	RETURN   	0 1

function <./build/make.lua:21,35> (59 instructions, 236 bytes at 0x7fc432c06fa0)
4 params, 15 slots, 2 upvalues, 10 locals, 10 constants, 0 functions
	1	[22]	GETGLOBAL	4 -1	; assert
	2	[22]	GETGLOBAL	5 -2	; type
	3	[22]	MOVE     	6 1
	4	[22]	CALL     	5 2 2
	5	[22]	EQ       	1 5 -3	; - "boolean"
	6	[22]	JMP      	1	; to 8
	7	[22]	LOADBOOL 	5 0 1
	8	[22]	LOADBOOL 	5 1 0
	9	[22]	CALL     	4 2 1
	10	[23]	GETGLOBAL	4 -1	; assert
	11	[23]	GETGLOBAL	5 -2	; type
	12	[23]	MOVE     	6 2
	13	[23]	CALL     	5 2 2
	14	[23]	EQ       	1 5 -4	; - "string"
	15	[23]	JMP      	1	; to 17
	16	[23]	LOADBOOL 	5 0 1
	17	[23]	LOADBOOL 	5 1 0
	18	[23]	CALL     	4 2 1
	19	[24]	GETGLOBAL	4 -1	; assert
	20	[24]	GETGLOBAL	5 -2	; type
	21	[24]	MOVE     	6 3
	22	[24]	CALL     	5 2 2
	23	[24]	EQ       	1 5 -5	; - "table"
	24	[24]	JMP      	1	; to 26
	25	[24]	LOADBOOL 	5 0 1
	26	[24]	LOADBOOL 	5 1 0
	27	[24]	CALL     	4 2 1
	28	[26]	NEWTABLE 	4 0 0
	29	[27]	GETGLOBAL	5 -6	; pairs
	30	[27]	MOVE     	6 3
	31	[27]	CALL     	5 2 4
	32	[27]	JMP      	8	; to 41
	33	[28]	GETGLOBAL	10 -5	; table
	34	[28]	GETTABLE 	10 10 -7	; "insert"
	35	[28]	MOVE     	11 4
	36	[28]	MOVE     	12 8
	37	[28]	LOADK    	13 -8	; "="
	38	[28]	MOVE     	14 9
	39	[28]	CONCAT   	12 12 14
	40	[28]	CALL     	10 3 1
	41	[27]	TFORLOOP 	5 2
	42	[28]	JMP      	-10	; to 33
	43	[30]	TEST     	1 0 0
	44	[30]	JMP      	12	; to 57
	45	[31]	GETUPVAL 	5 0	; fs
	46	[31]	GETTABLE 	5 5 -9	; "execute"
	47	[31]	MOVE     	6 0
	48	[31]	LOADK    	7 -10	; " "
	49	[31]	MOVE     	8 2
	50	[31]	CONCAT   	6 6 8
	51	[31]	GETUPVAL 	7 1	; unpack
	52	[31]	MOVE     	8 4
	53	[31]	CALL     	7 2 0
	54	[31]	TAILCALL 	5 0 0
	55	[31]	RETURN   	5 0
	56	[31]	JMP      	2	; to 59
	57	[33]	LOADBOOL 	5 1 0
	58	[33]	RETURN   	5 2
	59	[35]	RETURN   	0 1

function <./build/make.lua:41,94> (143 instructions, 572 bytes at 0x7fc432c07610)
1 param, 11 slots, 3 upvalues, 16 locals, 28 constants, 0 functions
	1	[42]	GETGLOBAL	1 -1	; assert
	2	[42]	SELF     	2 0 -2	; "type"
	3	[42]	CALL     	2 2 2
	4	[42]	EQ       	1 2 -3	; - "rockspec"
	5	[42]	JMP      	1	; to 7
	6	[42]	LOADBOOL 	2 0 1
	7	[42]	LOADBOOL 	2 1 0
	8	[42]	CALL     	1 2 1
	9	[44]	GETTABLE 	1 0 -4	; "build"
	10	[46]	GETTABLE 	2 1 -5	; "build_pass"
	11	[46]	EQ       	0 2 -6	; - nil
	12	[46]	JMP      	1	; to 14
	13	[46]	SETTABLE 	1 -5 -7	; "build_pass" true
	14	[47]	GETTABLE 	2 1 -8	; "install_pass"
	15	[47]	EQ       	0 2 -6	; - nil
	16	[47]	JMP      	1	; to 18
	17	[47]	SETTABLE 	1 -8 -7	; "install_pass" true
	18	[48]	GETTABLE 	2 1 -9	; "build_variables"
	19	[48]	TEST     	2 0 1
	20	[48]	JMP      	1	; to 22
	21	[48]	NEWTABLE 	2 0 0
	22	[48]	SETTABLE 	1 -9 2	; "build_variables" -
	23	[49]	GETTABLE 	2 1 -10	; "install_variables"
	24	[49]	TEST     	2 0 1
	25	[49]	JMP      	1	; to 27
	26	[49]	NEWTABLE 	2 0 0
	27	[49]	SETTABLE 	1 -10 2	; "install_variables" -
	28	[50]	GETTABLE 	2 1 -11	; "build_target"
	29	[50]	TEST     	2 0 1
	30	[50]	JMP      	1	; to 32
	31	[50]	LOADK    	2 -12	; ""
	32	[50]	SETTABLE 	1 -11 2	; "build_target" -
	33	[51]	GETTABLE 	2 1 -13	; "install_target"
	34	[51]	TEST     	2 0 1
	35	[51]	JMP      	1	; to 37
	36	[51]	LOADK    	2 -14	; "install"
	37	[51]	SETTABLE 	1 -13 2	; "install_target" -
	38	[52]	GETTABLE 	2 1 -15	; "makefile"
	39	[52]	TEST     	2 0 1
	40	[52]	JMP      	2	; to 43
	41	[52]	GETUPVAL 	2 0	; cfg
	42	[52]	GETTABLE 	2 2 -15	; "makefile"
	43	[53]	TEST     	2 0 0
	44	[53]	JMP      	12	; to 57
	45	[55]	LOADK    	3 -16	; "-f "
	46	[55]	MOVE     	4 2
	47	[55]	LOADK    	5 -17	; " "
	48	[55]	GETTABLE 	6 1 -11	; "build_target"
	49	[55]	CONCAT   	3 3 6
	50	[55]	SETTABLE 	1 -11 3	; "build_target" -
	51	[56]	LOADK    	3 -16	; "-f "
	52	[56]	MOVE     	4 2
	53	[56]	LOADK    	5 -17	; " "
	54	[56]	GETTABLE 	6 1 -13	; "install_target"
	55	[56]	CONCAT   	3 3 6
	56	[56]	SETTABLE 	1 -13 3	; "install_target" -
	57	[59]	GETTABLE 	3 1 -18	; "variables"
	58	[59]	TEST     	3 0 0
	59	[59]	JMP      	10	; to 70
	60	[60]	GETGLOBAL	3 -19	; pairs
	61	[60]	GETTABLE 	4 1 -18	; "variables"
	62	[60]	CALL     	3 2 4
	63	[60]	JMP      	4	; to 68
	64	[61]	GETTABLE 	8 1 -9	; "build_variables"
	65	[61]	SETTABLE 	8 6 7
	66	[62]	GETTABLE 	8 1 -10	; "install_variables"
	67	[62]	SETTABLE 	8 6 7
	68	[60]	TFORLOOP 	3 2
	69	[62]	JMP      	-6	; to 64
	70	[66]	GETUPVAL 	3 1	; util
	71	[66]	GETTABLE 	3 3 -20	; "warn_if_not_used"
	72	[66]	GETTABLE 	4 1 -9	; "build_variables"
	73	[66]	NEWTABLE 	5 0 1
	74	[66]	SETTABLE 	5 -21 -7	; "CFLAGS" true
	75	[66]	LOADK    	6 -22	; "variable %s was not passed in build_variables"
	76	[66]	CALL     	3 4 1
	77	[68]	GETUPVAL 	3 1	; util
	78	[68]	GETTABLE 	3 3 -23	; "variable_substitutions"
	79	[68]	GETTABLE 	4 1 -9	; "build_variables"
	80	[68]	GETTABLE 	5 0 -18	; "variables"
	81	[68]	CALL     	3 3 1
	82	[69]	GETUPVAL 	3 1	; util
	83	[69]	GETTABLE 	3 3 -23	; "variable_substitutions"
	84	[69]	GETTABLE 	4 1 -10	; "install_variables"
	85	[69]	GETTABLE 	5 0 -18	; "variables"
	86	[69]	CALL     	3 3 1
	87	[71]	NEWTABLE 	3 1 0
	88	[71]	LOADK    	4 -24	; "CC"
	89	[71]	SETLIST  	3 1 1	; 1
	90	[73]	GETGLOBAL	4 -19	; pairs
	91	[73]	MOVE     	5 3
	92	[73]	CALL     	4 2 4
	93	[73]	JMP      	16	; to 110
	94	[74]	GETTABLE 	9 1 -9	; "build_variables"
	95	[74]	GETTABLE 	9 9 8
	96	[74]	TEST     	9 0 1
	97	[74]	JMP      	4	; to 102
	98	[75]	GETTABLE 	9 1 -9	; "build_variables"
	99	[75]	GETTABLE 	10 0 -18	; "variables"
	100	[75]	GETTABLE 	10 10 8
	101	[75]	SETTABLE 	9 8 10
	102	[77]	GETTABLE 	9 1 -10	; "install_variables"
	103	[77]	GETTABLE 	9 9 8
	104	[77]	TEST     	9 0 1
	105	[77]	JMP      	4	; to 110
	106	[78]	GETTABLE 	9 1 -10	; "install_variables"
	107	[78]	GETTABLE 	10 0 -18	; "variables"
	108	[78]	GETTABLE 	10 10 8
	109	[78]	SETTABLE 	9 8 10
	110	[73]	TFORLOOP 	4 2
	111	[79]	JMP      	-18	; to 94
	112	[83]	GETUPVAL 	4 0	; cfg
	113	[83]	GETTABLE 	4 4 -25	; "make"
	114	[83]	TEST     	4 0 1
	115	[83]	JMP      	2	; to 118
	116	[83]	GETTABLE 	4 0 -18	; "variables"
	117	[83]	GETTABLE 	4 4 -26	; "MAKE"
	118	[85]	GETUPVAL 	5 2	; make_pass
	119	[85]	MOVE     	6 4
	120	[85]	GETTABLE 	7 1 -5	; "build_pass"
	121	[85]	GETTABLE 	8 1 -11	; "build_target"
	122	[85]	GETTABLE 	9 1 -9	; "build_variables"
	123	[85]	CALL     	5 5 2
	124	[86]	TEST     	5 0 1
	125	[86]	JMP      	3	; to 129
	126	[87]	LOADNIL  	6 6
	127	[87]	LOADK    	7 -27	; "Failed building."
	128	[87]	RETURN   	6 3
	129	[89]	GETUPVAL 	6 2	; make_pass
	130	[89]	MOVE     	7 4
	131	[89]	GETTABLE 	8 1 -8	; "install_pass"
	132	[89]	GETTABLE 	9 1 -13	; "install_target"
	133	[89]	GETTABLE 	10 1 -10	; "install_variables"
	134	[89]	CALL     	6 5 2
	135	[89]	MOVE     	5 6
	136	[90]	TEST     	5 0 1
	137	[90]	JMP      	3	; to 141
	138	[91]	LOADNIL  	6 6
	139	[91]	LOADK    	7 -28	; "Failed installing."
	140	[91]	RETURN   	6 3
	141	[93]	LOADBOOL 	6 1 0
	142	[93]	RETURN   	6 2
	143	[94]	RETURN   	0 1
