-- BYTECODE -- make.lua:21-35
0001    GGET     4   0      ; "assert"
0002    GGET     5   1      ; "type"
0003    MOV      6   1
0004    CALL     5   2   2
0005    ISEQS    5   2      ; "boolean"
0006    JMP      5 => 0009
0007    KPRI     5   1
0008    JMP      6 => 0010
0009 => KPRI     5   2
0010 => CALL     4   1   2
0011    GGET     4   0      ; "assert"
0012    GGET     5   1      ; "type"
0013    MOV      6   2
0014    CALL     5   2   2
0015    ISEQS    5   3      ; "string"
0016    JMP      5 => 0019
0017    KPRI     5   1
0018    JMP      6 => 0020
0019 => KPRI     5   2
0020 => CALL     4   1   2
0021    GGET     4   0      ; "assert"
0022    GGET     5   1      ; "type"
0023    MOV      6   3
0024    CALL     5   2   2
0025    ISEQS    5   4      ; "table"
0026    JMP      5 => 0029
0027    KPRI     5   1
0028    JMP      6 => 0030
0029 => KPRI     5   2
0030 => CALL     4   1   2
0031    TNEW     4   0
0032    GGET     5   5      ; "pairs"
0033    MOV      6   3
0034    CALL     5   4   2
0035    ISNEXT   8 => 0044
0036 => GGET    10   4      ; "table"
0037    TGETS   10  10   6  ; "insert"
0038    MOV     11   4
0039    MOV     12   8
0040    KSTR    13   7      ; "="
0041    MOV     14   9
0042    CAT     12  12  14
0043    CALL    10   1   3
0044 => ITERN    8   3   3
0045    ITERL    8 => 0036
0046    ISF          1
0047    JMP      5 => 0059
0048    UGET     5   0      ; fs
0049    TGETS    5   5   8  ; "execute"
0050    MOV      6   0
0051    KSTR     7   9      ; " "
0052    MOV      8   2
0053    CAT      6   6   8
0054    UGET     7   1      ; unpack
0055    MOV      8   4
0056    CALL     7   0   2
0057    CALLMT   5   1
0058    JMP      5 => 0061
0059 => KPRI     5   2
0060    RET1     5   2
0061 => RET0     0   1

-- BYTECODE -- make.lua:41-94
0001    GGET     1   0      ; "assert"
0002    MOV      3   0
0003    TGETS    2   0   1  ; "type"
0004    CALL     2   2   2
0005    ISEQS    2   2      ; "rockspec"
0006    JMP      2 => 0009
0007    KPRI     2   1
0008    JMP      3 => 0010
0009 => KPRI     2   2
0010 => CALL     1   1   2
0011    TGETS    1   0   3  ; "build"
0012    TGETS    2   1   4  ; "build_pass"
0013    ISNEP    2   0
0014    JMP      2 => 0017
0015    KPRI     2   2
0016    TSETS    2   1   4  ; "build_pass"
0017 => TGETS    2   1   5  ; "install_pass"
0018    ISNEP    2   0
0019    JMP      2 => 0022
0020    KPRI     2   2
0021    TSETS    2   1   5  ; "install_pass"
0022 => TGETS    2   1   6  ; "build_variables"
0023    IST          2
0024    JMP      3 => 0026
0025    TNEW     2   0
0026 => TSETS    2   1   6  ; "build_variables"
0027    TGETS    2   1   7  ; "install_variables"
0028    IST          2
0029    JMP      3 => 0031
0030    TNEW     2   0
0031 => TSETS    2   1   7  ; "install_variables"
0032    TGETS    2   1   8  ; "build_target"
0033    IST          2
0034    JMP      3 => 0036
0035    KSTR     2   9      ; ""
0036 => TSETS    2   1   8  ; "build_target"
0037    TGETS    2   1  10  ; "install_target"
0038    IST          2
0039    JMP      3 => 0041
0040    KSTR     2  11      ; "install"
0041 => TSETS    2   1  10  ; "install_target"
0042    TGETS    2   1  12  ; "makefile"
0043    IST          2
0044    JMP      3 => 0047
0045    UGET     2   0      ; cfg
0046    TGETS    2   2  12  ; "makefile"
0047 => ISF          2
0048    JMP      3 => 0061
0049    KSTR     3  13      ; "-f "
0050    MOV      4   2
0051    KSTR     5  14      ; " "
0052    TGETS    6   1   8  ; "build_target"
0053    CAT      3   3   6
0054    TSETS    3   1   8  ; "build_target"
0055    KSTR     3  13      ; "-f "
0056    MOV      4   2
0057    KSTR     5  14      ; " "
0058    TGETS    6   1  10  ; "install_target"
0059    CAT      3   3   6
0060    TSETS    3   1  10  ; "install_target"
0061 => TGETS    3   1  15  ; "variables"
0062    ISF          3
0063    JMP      4 => 0074
0064    GGET     3  16      ; "pairs"
0065    TGETS    4   1  15  ; "variables"
0066    CALL     3   4   2
0067    ISNEXT   6 => 0072
0068 => TGETS    8   1   6  ; "build_variables"
0069    TSETV    7   8   6
0070    TGETS    8   1   7  ; "install_variables"
0071    TSETV    7   8   6
0072 => ITERN    6   3   3
0073    ITERL    6 => 0068
0074 => UGET     3   1      ; util
0075    TGETS    3   3  17  ; "warn_if_not_used"
0076    TGETS    4   1   6  ; "build_variables"
0077    TDUP     5  18
0078    KSTR     6  19      ; "variable %s was not passed in build_vari"~
0079    CALL     3   1   4
0080    UGET     3   1      ; util
0081    TGETS    3   3  20  ; "variable_substitutions"
0082    TGETS    4   1   6  ; "build_variables"
0083    TGETS    5   0  15  ; "variables"
0084    CALL     3   1   3
0085    UGET     3   1      ; util
0086    TGETS    3   3  20  ; "variable_substitutions"
0087    TGETS    4   1   7  ; "install_variables"
0088    TGETS    5   0  15  ; "variables"
0089    CALL     3   1   3
0090    TDUP     3  21
0091    GGET     4  16      ; "pairs"
0092    MOV      5   3
0093    CALL     4   4   2
0094    ISNEXT   7 => 0111
0095 => TGETS    9   1   6  ; "build_variables"
0096    TGETV    9   9   8
0097    IST          9
0098    JMP      9 => 0103
0099    TGETS    9   1   6  ; "build_variables"
0100    TGETS   10   0  15  ; "variables"
0101    TGETV   10  10   8
0102    TSETV   10   9   8
0103 => TGETS    9   1   7  ; "install_variables"
0104    TGETV    9   9   8
0105    IST          9
0106    JMP      9 => 0111
0107    TGETS    9   1   7  ; "install_variables"
0108    TGETS   10   0  15  ; "variables"
0109    TGETV   10  10   8
0110    TSETV   10   9   8
0111 => ITERN    7   3   3
0112    ITERL    7 => 0095
0113    UGET     4   0      ; cfg
0114    TGETS    4   4  22  ; "make"
0115    IST          4
0116    JMP      5 => 0119
0117    TGETS    4   0  15  ; "variables"
0118    TGETS    4   4  23  ; "MAKE"
0119 => UGET     5   2      ; make_pass
0120    MOV      6   4
0121    TGETS    7   1   4  ; "build_pass"
0122    TGETS    8   1   8  ; "build_target"
0123    TGETS    9   1   6  ; "build_variables"
0124    CALL     5   2   5
0125    IST          5
0126    JMP      6 => 0130
0127    KPRI     6   0
0128    KSTR     7  24      ; "Failed building."
0129    RET      6   3
0130 => UGET     6   2      ; make_pass
0131    MOV      7   4
0132    TGETS    8   1   5  ; "install_pass"
0133    TGETS    9   1  10  ; "install_target"
0134    TGETS   10   1   7  ; "install_variables"
0135    CALL     6   2   5
0136    MOV      5   6
0137    IST          5
0138    JMP      6 => 0142
0139    KPRI     6   0
0140    KSTR     7  25      ; "Failed installing."
0141    RET      6   3
0142 => KPRI     6   2
0143    RET1     6   2

-- BYTECODE -- make.lua:0-97
0001    TNEW     0   0
0002    GGET     1   0      ; "unpack"
0003    IST          1
0004    JMP      2 => 0007
0005    GGET     1   1      ; "table"
0006    TGETS    1   1   0  ; "unpack"
0007 => GGET     2   2      ; "require"
0008    KSTR     3   3      ; "luarocks.fs"
0009    CALL     2   2   2
0010    GGET     3   2      ; "require"
0011    KSTR     4   4      ; "luarocks.util"
0012    CALL     3   2   2
0013    GGET     4   2      ; "require"
0014    KSTR     5   5      ; "luarocks.core.cfg"
0015    CALL     4   2   2
0016    FNEW     5   6      ; make.lua:21
0017    FNEW     6   8      ; make.lua:41
0018    TSETS    6   0   7  ; "run"
0019    UCLO     0 => 0020
0020 => RET1     0   2

