
main <./type/manifest.lua:0,0> (91 instructions, 364 bytes at 0x7ff4105040a0)
0+ params, 13 slots, 0 upvalues, 3 locals, 23 constants, 1 function
	1	[1]	NEWTABLE 	0 0 0
	2	[3]	GETGLOBAL	1 -1	; require
	3	[3]	LOADK    	2 -2	; "luarocks.type_check"
	4	[3]	CALL     	1 2 2
	5	[5]	GETTABLE 	2 1 -3	; "declare_schemas"
	6	[5]	NEWTABLE 	3 0 1
	7	[6]	NEWTABLE 	4 0 4
	8	[7]	NEWTABLE 	5 0 2
	9	[8]	SETTABLE 	5 -6 -7	; "_mandatory" true
	10	[10]	NEWTABLE 	6 0 1
	11	[12]	NEWTABLE 	7 0 1
	12	[14]	NEWTABLE 	8 0 4
	13	[15]	NEWTABLE 	9 0 2
	14	[15]	SETTABLE 	9 -10 -11	; "_type" "string"
	15	[15]	SETTABLE 	9 -6 -7	; "_mandatory" true
	16	[15]	SETTABLE 	8 -9 9	; "arch" -
	17	[16]	NEWTABLE 	9 0 1
	18	[16]	NEWTABLE 	10 0 1
	19	[16]	SETTABLE 	10 -10 -11	; "_type" "string"
	20	[16]	SETTABLE 	9 -8 10	; "_any" -
	21	[16]	SETTABLE 	8 -12 9	; "modules" -
	22	[17]	NEWTABLE 	9 0 1
	23	[17]	NEWTABLE 	10 0 1
	24	[17]	SETTABLE 	10 -10 -11	; "_type" "string"
	25	[17]	SETTABLE 	9 -8 10	; "_any" -
	26	[17]	SETTABLE 	8 -13 9	; "commands" -
	27	[18]	NEWTABLE 	9 0 1
	28	[18]	NEWTABLE 	10 0 1
	29	[18]	SETTABLE 	10 -10 -11	; "_type" "string"
	30	[18]	SETTABLE 	9 -8 10	; "_any" -
	31	[18]	SETTABLE 	8 -14 9	; "dependencies" -
	32	[20]	SETTABLE 	7 -8 8	; "_any" -
	33	[21]	SETTABLE 	6 -8 7	; "_any" -
	34	[22]	SETTABLE 	5 -8 6	; "_any" -
	35	[23]	SETTABLE 	4 -5 5	; "repository" -
	36	[24]	NEWTABLE 	5 0 2
	37	[25]	SETTABLE 	5 -6 -7	; "_mandatory" true
	38	[27]	NEWTABLE 	6 0 1
	39	[29]	NEWTABLE 	7 0 1
	40	[29]	SETTABLE 	7 -10 -11	; "_type" "string"
	41	[29]	SETTABLE 	6 -8 7	; "_any" -
	42	[30]	SETTABLE 	5 -8 6	; "_any" -
	43	[31]	SETTABLE 	4 -12 5	; "modules" -
	44	[32]	NEWTABLE 	5 0 2
	45	[33]	SETTABLE 	5 -6 -7	; "_mandatory" true
	46	[35]	NEWTABLE 	6 0 1
	47	[37]	NEWTABLE 	7 0 1
	48	[37]	SETTABLE 	7 -10 -11	; "_type" "string"
	49	[37]	SETTABLE 	6 -8 7	; "_any" -
	50	[38]	SETTABLE 	5 -8 6	; "_any" -
	51	[39]	SETTABLE 	4 -13 5	; "commands" -
	52	[40]	NEWTABLE 	5 0 1
	53	[42]	NEWTABLE 	6 0 1
	54	[44]	NEWTABLE 	7 0 1
	55	[46]	NEWTABLE 	8 0 3
	56	[47]	NEWTABLE 	9 0 1
	57	[47]	SETTABLE 	9 -10 -11	; "_type" "string"
	58	[47]	SETTABLE 	8 -15 9	; "name" -
	59	[48]	NEWTABLE 	9 0 1
	60	[48]	SETTABLE 	9 -10 -11	; "_type" "string"
	61	[48]	SETTABLE 	8 -16 9	; "namespace" -
	62	[49]	NEWTABLE 	9 0 1
	63	[50]	NEWTABLE 	10 0 3
	64	[51]	NEWTABLE 	11 0 1
	65	[51]	SETTABLE 	11 -10 -19	; "_type" "boolean"
	66	[51]	SETTABLE 	10 -18 11	; "no_upgrade" -
	67	[52]	NEWTABLE 	11 0 1
	68	[52]	SETTABLE 	11 -10 -11	; "_type" "string"
	69	[52]	SETTABLE 	10 -20 11	; "op" -
	70	[53]	NEWTABLE 	11 0 2
	71	[54]	NEWTABLE 	12 0 1
	72	[54]	SETTABLE 	12 -10 -11	; "_type" "string"
	73	[54]	SETTABLE 	11 -11 12	; "string" -
	74	[55]	NEWTABLE 	12 0 1
	75	[55]	SETTABLE 	12 -10 -22	; "_type" "number"
	76	[55]	SETTABLE 	11 -8 12	; "_any" -
	77	[56]	SETTABLE 	10 -21 11	; "version" -
	78	[57]	SETTABLE 	9 -8 10	; "_any" -
	79	[58]	SETTABLE 	8 -17 9	; "constraints" -
	80	[59]	SETTABLE 	7 -8 8	; "_any" -
	81	[60]	SETTABLE 	6 -8 7	; "_any" -
	82	[61]	SETTABLE 	5 -8 6	; "_any" -
	83	[62]	SETTABLE 	4 -14 5	; "dependencies" -
	84	[63]	SETTABLE 	3 -4 4	; "3.0" -
	85	[5]	CALL     	2 2 2
	86	[78]	CLOSURE  	3 0	; 0x7ff410504510
	87	[78]	MOVE     	0 2
	88	[78]	MOVE     	0 1
	89	[72]	SETTABLE 	0 -23 3	; "check" -
	90	[80]	RETURN   	0 2
	91	[80]	RETURN   	0 1

function <./type/manifest.lua:72,78> (30 instructions, 120 bytes at 0x7ff410504510)
2 params, 10 slots, 2 upvalues, 5 locals, 7 constants, 0 functions
	1	[73]	GETGLOBAL	2 -1	; assert
	2	[73]	GETGLOBAL	3 -2	; type
	3	[73]	MOVE     	4 0
	4	[73]	CALL     	3 2 2
	5	[73]	EQ       	1 3 -3	; - "table"
	6	[73]	JMP      	1	; to 8
	7	[73]	LOADBOOL 	3 0 1
	8	[73]	LOADBOOL 	3 1 0
	9	[73]	CALL     	2 2 1
	10	[74]	GETUPVAL 	2 0	; manifest_formats
	11	[74]	GETTABLE 	2 2 -4	; "3.0"
	12	[75]	GETUPVAL 	3 1	; type_check
	13	[75]	GETTABLE 	3 3 -5	; "check_undeclared_globals"
	14	[75]	MOVE     	4 1
	15	[75]	MOVE     	5 2
	16	[75]	CALL     	3 3 3
	17	[76]	TEST     	3 0 1
	18	[76]	JMP      	3	; to 22
	19	[76]	LOADNIL  	5 5
	20	[76]	MOVE     	6 4
	21	[76]	RETURN   	5 3
	22	[77]	GETUPVAL 	5 1	; type_check
	23	[77]	GETTABLE 	5 5 -6	; "type_check_table"
	24	[77]	LOADK    	6 -4	; "3.0"
	25	[77]	MOVE     	7 0
	26	[77]	MOVE     	8 2
	27	[77]	LOADK    	9 -7	; ""
	28	[77]	TAILCALL 	5 5 0
	29	[77]	RETURN   	5 0
	30	[78]	RETURN   	0 1
