-- BYTECODE -- manifest.lua:72-78
0001    GGET     2   0      ; "assert"
0002    GGET     3   1      ; "type"
0003    MOV      4   0
0004    CALL     3   2   2
0005    ISEQS    3   2      ; "table"
0006    JMP      3 => 0009
0007    KPRI     3   1
0008    JMP      4 => 0010
0009 => KPRI     3   2
0010 => CALL     2   1   2
0011    UGET     2   0      ; manifest_formats
0012    TGETS    2   2   3  ; "3.0"
0013    UGET     3   1      ; type_check
0014    TGETS    3   3   4  ; "check_undeclared_globals"
0015    MOV      4   1
0016    MOV      5   2
0017    CALL     3   3   3
0018    IST          3
0019    JMP      5 => 0023
0020    KPRI     5   0
0021    MOV      6   4
0022    RET      5   3
0023 => UGET     5   1      ; type_check
0024    TGETS    5   5   5  ; "type_check_table"
0025    KSTR     6   3      ; "3.0"
0026    MOV      7   0
0027    MOV      8   2
0028    KSTR     9   6      ; ""
0029    CALLT    5   5

-- BYTECODE -- manifest.lua:0-81
0001    TNEW     0   0
0002    GGET     1   0      ; "require"
0003    KSTR     2   1      ; "luarocks.type_check"
0004    CALL     1   2   2
0005    TGETS    2   1   2  ; "declare_schemas"
0006    TDUP     3  47
0007    TDUP     4  19
0008    TDUP     5   3
0009    TDUP     6  18
0010    TDUP     7  17
0011    TDUP     8   5
0012    TDUP     9   4
0013    TSETS    9   8   6  ; "arch"
0014    TDUP     9   8
0015    TDUP    10   7
0016    TSETS   10   9   9  ; "_any"
0017    TSETS    9   8  10  ; "modules"
0018    TDUP     9  12
0019    TDUP    10  11
0020    TSETS   10   9   9  ; "_any"
0021    TSETS    9   8  13  ; "commands"
0022    TDUP     9  15
0023    TDUP    10  14
0024    TSETS   10   9   9  ; "_any"
0025    TSETS    9   8  16  ; "dependencies"
0026    TSETS    8   7   9  ; "_any"
0027    TSETS    7   6   9  ; "_any"
0028    TSETS    6   5   9  ; "_any"
0029    TSETS    5   4  20  ; "repository"
0030    TDUP     5  21
0031    TDUP     6  23
0032    TDUP     7  22
0033    TSETS    7   6   9  ; "_any"
0034    TSETS    6   5   9  ; "_any"
0035    TSETS    5   4  10  ; "modules"
0036    TDUP     5  24
0037    TDUP     6  26
0038    TDUP     7  25
0039    TSETS    7   6   9  ; "_any"
0040    TSETS    6   5   9  ; "_any"
0041    TSETS    5   4  13  ; "commands"
0042    TDUP     5  46
0043    TDUP     6  45
0044    TDUP     7  44
0045    TDUP     8  28
0046    TDUP     9  27
0047    TSETS    9   8  29  ; "name"
0048    TDUP     9  30
0049    TSETS    9   8  31  ; "namespace"
0050    TDUP     9  42
0051    TDUP    10  33
0052    TDUP    11  32
0053    TSETS   11  10  34  ; "no_upgrade"
0054    TDUP    11  35
0055    TSETS   11  10  36  ; "op"
0056    TDUP    11  38
0057    TDUP    12  37
0058    TSETS   12  11  39  ; "string"
0059    TDUP    12  40
0060    TSETS   12  11   9  ; "_any"
0061    TSETS   11  10  41  ; "version"
0062    TSETS   10   9   9  ; "_any"
0063    TSETS    9   8  43  ; "constraints"
0064    TSETS    8   7   9  ; "_any"
0065    TSETS    7   6   9  ; "_any"
0066    TSETS    6   5   9  ; "_any"
0067    TSETS    5   4  16  ; "dependencies"
0068    TSETS    4   3  48  ; "3.0"
0069    CALL     2   2   2
0070    FNEW     3  50      ; manifest.lua:72
0071    TSETS    3   0  49  ; "check"
0072    UCLO     0 => 0073
0073 => RET1     0   2

