
main <./pack.lua:0,0> (74 instructions, 296 bytes at 0x7fb6744068a0)
0+ params, 15 slots, 0 upvalues, 14 locals, 18 constants, 5 functions
	1	[3]	NEWTABLE 	0 0 0
	2	[5]	GETGLOBAL	1 -1	; unpack
	3	[5]	TEST     	1 0 1
	4	[5]	JMP      	2	; to 7
	5	[5]	GETGLOBAL	1 -2	; table
	6	[5]	GETTABLE 	1 1 -1	; "unpack"
	7	[7]	GETGLOBAL	2 -3	; require
	8	[7]	LOADK    	3 -4	; "luarocks.queries"
	9	[7]	CALL     	2 2 2
	10	[8]	GETGLOBAL	3 -3	; require
	11	[8]	LOADK    	4 -5	; "luarocks.path"
	12	[8]	CALL     	3 2 2
	13	[9]	GETGLOBAL	4 -3	; require
	14	[9]	LOADK    	5 -6	; "luarocks.repos"
	15	[9]	CALL     	4 2 2
	16	[10]	GETGLOBAL	5 -3	; require
	17	[10]	LOADK    	6 -7	; "luarocks.fetch"
	18	[10]	CALL     	5 2 2
	19	[11]	GETGLOBAL	6 -3	; require
	20	[11]	LOADK    	7 -8	; "luarocks.fs"
	21	[11]	CALL     	6 2 2
	22	[12]	GETGLOBAL	7 -3	; require
	23	[12]	LOADK    	8 -9	; "luarocks.core.cfg"
	24	[12]	CALL     	7 2 2
	25	[13]	GETGLOBAL	8 -3	; require
	26	[13]	LOADK    	9 -10	; "luarocks.util"
	27	[13]	CALL     	8 2 2
	28	[14]	GETGLOBAL	9 -3	; require
	29	[14]	LOADK    	10 -11	; "luarocks.dir"
	30	[14]	CALL     	9 2 2
	31	[15]	GETGLOBAL	10 -3	; require
	32	[15]	LOADK    	11 -12	; "luarocks.manif"
	33	[15]	CALL     	10 2 2
	34	[16]	GETGLOBAL	11 -3	; require
	35	[16]	LOADK    	12 -13	; "luarocks.search"
	36	[16]	CALL     	11 2 2
	37	[17]	GETGLOBAL	12 -3	; require
	38	[17]	LOADK    	13 -14	; "luarocks.signing"
	39	[17]	CALL     	12 2 2
	40	[54]	CLOSURE  	13 0	; 0x7fb674406fa0
	41	[54]	MOVE     	0 5
	42	[54]	MOVE     	0 6
	43	[54]	MOVE     	0 9
	44	[26]	SETTABLE 	0 -15 13	; "pack_source_rock" -
	45	[75]	CLOSURE  	13 1	; 0x7fb674407120
	46	[75]	MOVE     	0 6
	47	[75]	MOVE     	0 9
	48	[75]	MOVE     	0 13
	49	[75]	MOVE     	0 3
	50	[127]	CLOSURE  	14 2	; 0x7fb6744081d0
	51	[127]	MOVE     	0 11
	52	[127]	MOVE     	0 3
	53	[127]	MOVE     	0 6
	54	[127]	MOVE     	0 10
	55	[127]	MOVE     	0 7
	56	[127]	MOVE     	0 13
	57	[127]	MOVE     	0 9
	58	[127]	MOVE     	0 4
	59	[127]	MOVE     	0 1
	60	[82]	SETTABLE 	0 -16 14	; "pack_installed_rock" -
	61	[146]	CLOSURE  	14 3	; 0x7fb674406d20
	62	[146]	MOVE     	0 12
	63	[146]	MOVE     	0 8
	64	[129]	SETTABLE 	0 -17 14	; "report_and_sign_local_file" -
	65	[175]	CLOSURE  	14 4	; 0x7fb674409190
	66	[175]	MOVE     	0 6
	67	[175]	MOVE     	0 9
	68	[175]	MOVE     	0 8
	69	[175]	MOVE     	0 3
	70	[175]	MOVE     	0 2
	71	[175]	MOVE     	0 0
	72	[148]	SETTABLE 	0 -18 14	; "pack_binary_rock" -
	73	[177]	RETURN   	0 2
	74	[177]	RETURN   	0 1

function <./pack.lua:26,54> (88 instructions, 352 bytes at 0x7fb674406fa0)
1 param, 14 slots, 3 upvalues, 9 locals, 21 constants, 0 functions
	1	[27]	GETGLOBAL	1 -1	; assert
	2	[27]	GETGLOBAL	2 -2	; type
	3	[27]	MOVE     	3 0
	4	[27]	CALL     	2 2 2
	5	[27]	EQ       	1 2 -3	; - "string"
	6	[27]	JMP      	1	; to 8
	7	[27]	LOADBOOL 	2 0 1
	8	[27]	LOADBOOL 	2 1 0
	9	[27]	CALL     	1 2 1
	10	[29]	GETUPVAL 	1 0	; fetch
	11	[29]	GETTABLE 	1 1 -4	; "load_rockspec"
	12	[29]	MOVE     	2 0
	13	[29]	CALL     	1 2 3
	14	[30]	TEST     	2 0 0
	15	[30]	JMP      	5	; to 21
	16	[31]	LOADNIL  	3 3
	17	[31]	LOADK    	4 -5	; "Error loading rockspec: "
	18	[31]	MOVE     	5 2
	19	[31]	CONCAT   	4 4 5
	20	[31]	RETURN   	3 3
	21	[33]	GETTABLE 	0 1 -6	; "local_abs_filename"
	22	[35]	GETTABLE 	3 1 -7	; "name"
	23	[35]	LOADK    	4 -8	; "-"
	24	[35]	GETTABLE 	5 1 -9	; "version"
	25	[35]	CONCAT   	3 3 5
	26	[36]	GETUPVAL 	4 1	; fs
	27	[36]	GETTABLE 	4 4 -10	; "absolute_name"
	28	[36]	MOVE     	5 3
	29	[36]	LOADK    	6 -11	; ".src.rock"
	30	[36]	CONCAT   	5 5 6
	31	[36]	CALL     	4 2 2
	32	[38]	GETUPVAL 	5 0	; fetch
	33	[38]	GETTABLE 	5 5 -12	; "fetch_sources"
	34	[38]	MOVE     	6 1
	35	[38]	LOADBOOL 	7 0 0
	36	[38]	CALL     	5 3 3
	37	[39]	TEST     	5 0 1
	38	[39]	JMP      	3	; to 42
	39	[40]	LOADNIL  	7 7
	40	[40]	MOVE     	8 6
	41	[40]	RETURN   	7 3
	42	[42]	GETUPVAL 	7 1	; fs
	43	[42]	GETTABLE 	7 7 -13	; "change_dir"
	44	[42]	MOVE     	8 6
	45	[42]	CALL     	7 2 3
	46	[43]	TEST     	7 0 1
	47	[43]	JMP      	3	; to 51
	48	[43]	LOADNIL  	9 9
	49	[43]	MOVE     	10 8
	50	[43]	RETURN   	9 3
	51	[45]	GETUPVAL 	9 1	; fs
	52	[45]	GETTABLE 	9 9 -14	; "delete"
	53	[45]	MOVE     	10 4
	54	[45]	CALL     	9 2 1
	55	[46]	GETUPVAL 	9 1	; fs
	56	[46]	GETTABLE 	9 9 -15	; "copy"
	57	[46]	MOVE     	10 0
	58	[46]	MOVE     	11 6
	59	[46]	LOADK    	12 -16	; "read"
	60	[46]	CALL     	9 4 1
	61	[47]	GETUPVAL 	9 1	; fs
	62	[47]	GETTABLE 	9 9 -17	; "zip"
	63	[47]	MOVE     	10 4
	64	[47]	GETUPVAL 	11 2	; dir
	65	[47]	GETTABLE 	11 11 -18	; "base_name"
	66	[47]	MOVE     	12 0
	67	[47]	CALL     	11 2 2
	68	[47]	GETUPVAL 	12 2	; dir
	69	[47]	GETTABLE 	12 12 -18	; "base_name"
	70	[47]	MOVE     	13 5
	71	[47]	CALL     	12 2 0
	72	[47]	CALL     	9 0 3
	73	[47]	MOVE     	8 10
	74	[47]	MOVE     	7 9
	75	[48]	TEST     	7 0 1
	76	[48]	JMP      	7	; to 84
	77	[49]	LOADNIL  	9 9
	78	[49]	LOADK    	10 -19	; "Failed packing "
	79	[49]	MOVE     	11 4
	80	[49]	LOADK    	12 -20	; " - "
	81	[49]	MOVE     	13 8
	82	[49]	CONCAT   	10 10 13
	83	[49]	RETURN   	9 3
	84	[51]	GETUPVAL 	9 1	; fs
	85	[51]	GETTABLE 	9 9 -21	; "pop_dir"
	86	[51]	CALL     	9 1 1
	87	[53]	RETURN   	4 2
	88	[54]	RETURN   	0 1

function <./pack.lua:56,75> (72 instructions, 288 bytes at 0x7fb674407120)
6 params, 21 slots, 4 upvalues, 18 locals, 8 constants, 0 functions
	1	[57]	GETUPVAL 	6 0	; fs
	2	[57]	GETTABLE 	6 6 -1	; "make_dir"
	3	[57]	MOVE     	7 4
	4	[57]	CALL     	6 2 3
	5	[58]	TEST     	6 0 1
	6	[58]	JMP      	3	; to 10
	7	[58]	LOADNIL  	8 8
	8	[58]	MOVE     	9 7
	9	[58]	RETURN   	8 3
	10	[59]	GETGLOBAL	8 -2	; pairs
	11	[59]	MOVE     	9 2
	12	[59]	CALL     	8 2 4
	13	[59]	JMP      	54	; to 68
	14	[60]	GETUPVAL 	13 1	; dir
	15	[60]	GETTABLE 	13 13 -3	; "path"
	16	[60]	MOVE     	14 3
	17	[60]	MOVE     	15 11
	18	[60]	CALL     	13 3 2
	19	[61]	GETUPVAL 	14 1	; dir
	20	[61]	GETTABLE 	14 14 -3	; "path"
	21	[61]	MOVE     	15 4
	22	[61]	MOVE     	16 11
	23	[61]	CALL     	14 3 2
	24	[62]	GETGLOBAL	15 -4	; type
	25	[62]	MOVE     	16 12
	26	[62]	CALL     	15 2 2
	27	[62]	EQ       	0 15 -5	; - "table"
	28	[62]	JMP      	13	; to 42
	29	[63]	GETUPVAL 	15 2	; copy_back_files
	30	[63]	MOVE     	16 0
	31	[63]	MOVE     	17 1
	32	[63]	MOVE     	18 12
	33	[63]	MOVE     	19 13
	34	[63]	MOVE     	20 14
	35	[63]	CALL     	15 6 3
	36	[64]	TEST     	15 0 1
	37	[64]	JMP      	30	; to 68
	38	[64]	LOADNIL  	17 17
	39	[64]	MOVE     	18 16
	40	[64]	RETURN   	17 3
	41	[64]	JMP      	26	; to 68
	42	[66]	GETUPVAL 	15 3	; path
	43	[66]	GETTABLE 	15 15 -6	; "versioned_name"
	44	[66]	MOVE     	16 13
	45	[66]	MOVE     	17 3
	46	[66]	MOVE     	18 0
	47	[66]	MOVE     	19 1
	48	[66]	CALL     	15 5 2
	49	[67]	GETUPVAL 	16 0	; fs
	50	[67]	GETTABLE 	16 16 -7	; "exists"
	51	[67]	MOVE     	17 15
	52	[67]	CALL     	16 2 2
	53	[67]	TEST     	16 0 0
	54	[67]	JMP      	7	; to 62
	55	[68]	GETUPVAL 	16 0	; fs
	56	[68]	GETTABLE 	16 16 -8	; "copy"
	57	[68]	MOVE     	17 15
	58	[68]	MOVE     	18 14
	59	[68]	MOVE     	19 5
	60	[68]	CALL     	16 4 1
	61	[68]	JMP      	6	; to 68
	62	[70]	GETUPVAL 	16 0	; fs
	63	[70]	GETTABLE 	16 16 -8	; "copy"
	64	[70]	MOVE     	17 13
	65	[70]	MOVE     	18 14
	66	[70]	MOVE     	19 5
	67	[70]	CALL     	16 4 1
	68	[59]	TFORLOOP 	8 2
	69	[72]	JMP      	-56	; to 14
	70	[74]	LOADBOOL 	8 1 0
	71	[74]	RETURN   	8 2
	72	[75]	RETURN   	0 1

function <./pack.lua:82,127> (179 instructions, 716 bytes at 0x7fb6744081d0)
2 params, 23 slots, 9 upvalues, 20 locals, 36 constants, 0 functions
	1	[84]	GETUPVAL 	2 0	; search
	2	[84]	GETTABLE 	2 2 -1	; "pick_installed_rock"
	3	[84]	MOVE     	3 0
	4	[84]	MOVE     	4 1
	5	[84]	CALL     	2 3 5
	6	[85]	TEST     	2 0 1
	7	[85]	JMP      	3	; to 11
	8	[86]	LOADNIL  	6 6
	9	[86]	MOVE     	7 3
	10	[86]	RETURN   	6 3
	11	[89]	GETUPVAL 	6 1	; path
	12	[89]	GETTABLE 	6 6 -2	; "root_from_rocks_dir"
	13	[89]	MOVE     	7 5
	14	[89]	CALL     	6 2 2
	15	[90]	GETUPVAL 	7 1	; path
	16	[90]	GETTABLE 	7 7 -3	; "install_dir"
	17	[90]	MOVE     	8 2
	18	[90]	MOVE     	9 3
	19	[90]	MOVE     	10 6
	20	[90]	CALL     	7 4 2
	21	[91]	GETUPVAL 	8 2	; fs
	22	[91]	GETTABLE 	8 8 -4	; "exists"
	23	[91]	MOVE     	9 7
	24	[91]	CALL     	8 2 2
	25	[91]	TEST     	8 0 1
	26	[91]	JMP      	8	; to 35
	27	[92]	LOADNIL  	8 8
	28	[92]	LOADK    	9 -5	; "'"
	29	[92]	MOVE     	10 2
	30	[92]	LOADK    	11 -6	; " "
	31	[92]	MOVE     	12 3
	32	[92]	LOADK    	13 -7	; "' does not seem to be an installed rock."
	33	[92]	CONCAT   	9 9 13
	34	[92]	RETURN   	8 3
	35	[95]	GETUPVAL 	8 3	; manif
	36	[95]	GETTABLE 	8 8 -8	; "load_rock_manifest"
	37	[95]	MOVE     	9 2
	38	[95]	MOVE     	10 3
	39	[95]	MOVE     	11 6
	40	[95]	CALL     	8 4 3
	41	[96]	TEST     	8 0 1
	42	[96]	JMP      	3	; to 46
	43	[96]	LOADNIL  	10 10
	44	[96]	MOVE     	11 9
	45	[96]	RETURN   	10 3
	46	[98]	MOVE     	10 2
	47	[98]	LOADK    	11 -9	; "-"
	48	[98]	MOVE     	12 3
	49	[98]	CONCAT   	10 10 12
	50	[99]	GETUPVAL 	11 2	; fs
	51	[99]	GETTABLE 	11 11 -10	; "absolute_name"
	52	[99]	MOVE     	12 10
	53	[99]	LOADK    	13 -11	; "."
	54	[99]	GETUPVAL 	14 4	; cfg
	55	[99]	GETTABLE 	14 14 -12	; "arch"
	56	[99]	LOADK    	15 -13	; ".rock"
	57	[99]	CONCAT   	12 12 15
	58	[99]	CALL     	11 2 2
	59	[101]	GETUPVAL 	12 2	; fs
	60	[101]	GETTABLE 	12 12 -14	; "make_temp_dir"
	61	[101]	LOADK    	13 -15	; "pack"
	62	[101]	CALL     	12 2 2
	63	[102]	GETUPVAL 	13 2	; fs
	64	[102]	GETTABLE 	13 13 -16	; "copy_contents"
	65	[102]	MOVE     	14 7
	66	[102]	MOVE     	15 12
	67	[102]	CALL     	13 3 1
	68	[104]	LOADBOOL 	13 0 0
	69	[105]	GETTABLE 	14 8 -17	; "lib"
	70	[105]	TEST     	14 0 0
	71	[105]	JMP      	23	; to 95
	72	[106]	GETUPVAL 	14 5	; copy_back_files
	73	[106]	MOVE     	15 2
	74	[106]	MOVE     	16 3
	75	[106]	GETTABLE 	17 8 -17	; "lib"
	76	[106]	GETUPVAL 	18 1	; path
	77	[106]	GETTABLE 	18 18 -18	; "deploy_lib_dir"
	78	[106]	MOVE     	19 4
	79	[106]	CALL     	18 2 2
	80	[106]	GETUPVAL 	19 6	; dir
	81	[106]	GETTABLE 	19 19 -19	; "path"
	82	[106]	MOVE     	20 12
	83	[106]	LOADK    	21 -17	; "lib"
	84	[106]	CALL     	19 3 2
	85	[106]	LOADK    	20 -20	; "exec"
	86	[106]	CALL     	14 7 3
	87	[107]	TEST     	14 0 1
	88	[107]	JMP      	5	; to 94
	89	[107]	LOADNIL  	16 16
	90	[107]	LOADK    	17 -21	; "Failed copying back files: "
	91	[107]	MOVE     	18 15
	92	[107]	CONCAT   	17 17 18
	93	[107]	RETURN   	16 3
	94	[108]	LOADBOOL 	13 1 0
	95	[110]	GETTABLE 	14 8 -22	; "lua"
	96	[110]	TEST     	14 0 0
	97	[110]	JMP      	22	; to 120
	98	[111]	GETUPVAL 	14 5	; copy_back_files
	99	[111]	MOVE     	15 2
	100	[111]	MOVE     	16 3
	101	[111]	GETTABLE 	17 8 -22	; "lua"
	102	[111]	GETUPVAL 	18 1	; path
	103	[111]	GETTABLE 	18 18 -23	; "deploy_lua_dir"
	104	[111]	MOVE     	19 4
	105	[111]	CALL     	18 2 2
	106	[111]	GETUPVAL 	19 6	; dir
	107	[111]	GETTABLE 	19 19 -19	; "path"
	108	[111]	MOVE     	20 12
	109	[111]	LOADK    	21 -22	; "lua"
	110	[111]	CALL     	19 3 2
	111	[111]	LOADK    	20 -24	; "read"
	112	[111]	CALL     	14 7 3
	113	[112]	TEST     	14 0 1
	114	[112]	JMP      	5	; to 120
	115	[112]	LOADNIL  	16 16
	116	[112]	LOADK    	17 -21	; "Failed copying back files: "
	117	[112]	MOVE     	18 15
	118	[112]	CONCAT   	17 17 18
	119	[112]	RETURN   	16 3
	120	[115]	GETUPVAL 	14 2	; fs
	121	[115]	GETTABLE 	14 14 -25	; "change_dir"
	122	[115]	MOVE     	15 12
	123	[115]	CALL     	14 2 3
	124	[116]	TEST     	14 0 1
	125	[116]	JMP      	3	; to 129
	126	[116]	LOADNIL  	16 16
	127	[116]	MOVE     	17 15
	128	[116]	RETURN   	16 3
	129	[117]	TEST     	13 0 1
	130	[117]	JMP      	20	; to 151
	131	[117]	GETUPVAL 	16 7	; repos
	132	[117]	GETTABLE 	16 16 -26	; "has_binaries"
	133	[117]	MOVE     	17 2
	134	[117]	MOVE     	18 3
	135	[117]	CALL     	16 3 2
	136	[117]	TEST     	16 0 1
	137	[117]	JMP      	13	; to 151
	138	[118]	SELF     	16 11 -27	; "gsub"
	139	[118]	LOADK    	18 -28	; "%."
	140	[118]	GETUPVAL 	19 4	; cfg
	141	[118]	GETTABLE 	19 19 -12	; "arch"
	142	[118]	SELF     	19 19 -27	; "gsub"
	143	[118]	LOADK    	21 -29	; "%-"
	144	[118]	LOADK    	22 -30	; "%%-"
	145	[118]	CALL     	19 4 2
	146	[118]	LOADK    	20 -28	; "%."
	147	[118]	CONCAT   	18 18 20
	148	[118]	LOADK    	19 -31	; ".all."
	149	[118]	CALL     	16 4 2
	150	[118]	MOVE     	11 16
	151	[120]	GETUPVAL 	16 2	; fs
	152	[120]	GETTABLE 	16 16 -32	; "delete"
	153	[120]	MOVE     	17 11
	154	[120]	CALL     	16 2 1
	155	[121]	GETUPVAL 	16 2	; fs
	156	[121]	GETTABLE 	16 16 -33	; "zip"
	157	[121]	MOVE     	17 11
	158	[121]	GETUPVAL 	18 8	; unpack
	159	[121]	GETUPVAL 	19 2	; fs
	160	[121]	GETTABLE 	19 19 -34	; "list_dir"
	161	[121]	CALL     	19 1 0
	162	[121]	CALL     	18 0 0
	163	[121]	CALL     	16 0 2
	164	[121]	TEST     	16 0 1
	165	[121]	JMP      	5	; to 171
	166	[122]	LOADNIL  	16 16
	167	[122]	LOADK    	17 -35	; "Failed packing "
	168	[122]	MOVE     	18 11
	169	[122]	CONCAT   	17 17 18
	170	[122]	RETURN   	16 3
	171	[124]	GETUPVAL 	16 2	; fs
	172	[124]	GETTABLE 	16 16 -36	; "pop_dir"
	173	[124]	CALL     	16 1 1
	174	[125]	GETUPVAL 	16 2	; fs
	175	[125]	GETTABLE 	16 16 -32	; "delete"
	176	[125]	MOVE     	17 12
	177	[125]	CALL     	16 2 1
	178	[126]	RETURN   	11 2
	179	[127]	RETURN   	0 1

function <./pack.lua:129,146> (39 instructions, 156 bytes at 0x7fb674406d20)
3 params, 7 slots, 2 upvalues, 4 locals, 4 constants, 0 functions
	1	[130]	TEST     	1 0 0
	2	[130]	JMP      	3	; to 6
	3	[131]	LOADNIL  	3 3
	4	[131]	MOVE     	4 1
	5	[131]	RETURN   	3 3
	6	[133]	LOADNIL  	3 3
	7	[134]	TEST     	2 0 0
	8	[134]	JMP      	9	; to 18
	9	[135]	GETUPVAL 	4 0	; signing
	10	[135]	GETTABLE 	4 4 -1	; "sign_file"
	11	[135]	MOVE     	5 0
	12	[135]	CALL     	4 2 3
	13	[135]	MOVE     	1 5
	14	[135]	MOVE     	3 4
	15	[136]	GETUPVAL 	4 1	; util
	16	[136]	GETTABLE 	4 4 -2	; "printout"
	17	[136]	CALL     	4 1 1
	18	[138]	GETUPVAL 	4 1	; util
	19	[138]	GETTABLE 	4 4 -2	; "printout"
	20	[138]	LOADK    	5 -3	; "Packed: "
	21	[138]	MOVE     	6 0
	22	[138]	CONCAT   	5 5 6
	23	[138]	CALL     	4 2 1
	24	[139]	TEST     	3 0 0
	25	[139]	JMP      	6	; to 32
	26	[140]	GETUPVAL 	4 1	; util
	27	[140]	GETTABLE 	4 4 -2	; "printout"
	28	[140]	LOADK    	5 -4	; "Signature stored in: "
	29	[140]	MOVE     	6 3
	30	[140]	CONCAT   	5 5 6
	31	[140]	CALL     	4 2 1
	32	[142]	TEST     	1 0 0
	33	[142]	JMP      	3	; to 37
	34	[143]	LOADNIL  	4 4
	35	[143]	MOVE     	5 1
	36	[143]	RETURN   	4 3
	37	[145]	LOADBOOL 	4 1 0
	38	[145]	RETURN   	4 2
	39	[146]	RETURN   	0 1

function <./pack.lua:148,175> (61 instructions, 244 bytes at 0x7fb674409190)
5 params, 18 slots, 6 upvalues, 14 locals, 11 constants, 0 functions
	1	[157]	GETUPVAL 	5 0	; fs
	2	[157]	GETTABLE 	5 5 -1	; "make_temp_dir"
	3	[157]	LOADK    	6 -2	; "luarocks-build-pack-"
	4	[157]	GETUPVAL 	7 1	; dir
	5	[157]	GETTABLE 	7 7 -3	; "base_name"
	6	[157]	MOVE     	8 0
	7	[157]	CALL     	7 2 2
	8	[157]	CONCAT   	6 6 7
	9	[157]	CALL     	5 2 3
	10	[158]	TEST     	5 0 1
	11	[158]	JMP      	5	; to 17
	12	[159]	LOADNIL  	7 7
	13	[159]	LOADK    	8 -4	; "Failed creating temporary directory: "
	14	[159]	MOVE     	9 6
	15	[159]	CONCAT   	8 8 9
	16	[159]	RETURN   	7 3
	17	[161]	GETUPVAL 	7 2	; util
	18	[161]	GETTABLE 	7 7 -5	; "schedule_function"
	19	[161]	GETUPVAL 	8 0	; fs
	20	[161]	GETTABLE 	8 8 -6	; "delete"
	21	[161]	MOVE     	9 5
	22	[161]	CALL     	7 3 1
	23	[163]	GETUPVAL 	7 3	; path
	24	[163]	GETTABLE 	7 7 -7	; "use_tree"
	25	[163]	MOVE     	8 5
	26	[163]	CALL     	7 2 1
	27	[164]	MOVE     	7 4
	28	[164]	CALL     	7 1 3
	29	[165]	TEST     	7 0 1
	30	[165]	JMP      	3	; to 34
	31	[166]	LOADNIL  	9 9
	32	[166]	MOVE     	10 8
	33	[166]	RETURN   	9 3
	34	[168]	GETUPVAL 	9 3	; path
	35	[168]	GETTABLE 	9 9 -8	; "parse_name"
	36	[168]	MOVE     	10 0
	37	[168]	CALL     	9 2 3
	38	[169]	TEST     	9 0 1
	39	[169]	JMP      	3	; to 43
	40	[170]	MOVE     	11 0
	41	[170]	MOVE     	10 2
	42	[170]	MOVE     	9 11
	43	[172]	GETUPVAL 	11 4	; queries
	44	[172]	GETTABLE 	11 11 -9	; "new"
	45	[172]	MOVE     	12 9
	46	[172]	MOVE     	13 1
	47	[172]	MOVE     	14 10
	48	[172]	CALL     	11 4 2
	49	[173]	GETUPVAL 	12 5	; pack
	50	[173]	GETTABLE 	12 12 -10	; "pack_installed_rock"
	51	[173]	MOVE     	13 11
	52	[173]	MOVE     	14 5
	53	[173]	CALL     	12 3 3
	54	[174]	GETUPVAL 	14 5	; pack
	55	[174]	GETTABLE 	14 14 -11	; "report_and_sign_local_file"
	56	[174]	MOVE     	15 12
	57	[174]	MOVE     	16 13
	58	[174]	MOVE     	17 3
	59	[174]	TAILCALL 	14 4 0
	60	[174]	RETURN   	14 0
	61	[175]	RETURN   	0 1
