
main <./persist.lua:0,0> (81 instructions, 324 bytes at 0x7fb52a4068a0)
0+ params, 11 slots, 0 upvalues, 11 locals, 36 constants, 11 functions
	1	[4]	NEWTABLE 	0 0 0
	2	[6]	GETGLOBAL	1 -1	; require
	3	[6]	LOADK    	2 -2	; "luarocks.core.persist"
	4	[6]	CALL     	1 2 2
	5	[7]	GETGLOBAL	2 -1	; require
	6	[7]	LOADK    	3 -3	; "luarocks.util"
	7	[7]	CALL     	2 2 2
	8	[8]	GETGLOBAL	3 -1	; require
	9	[8]	LOADK    	4 -4	; "luarocks.dir"
	10	[8]	CALL     	3 2 2
	11	[9]	GETGLOBAL	4 -1	; require
	12	[9]	LOADK    	5 -5	; "luarocks.fs"
	13	[9]	CALL     	4 2 2
	14	[11]	GETTABLE 	5 1 -6	; "run_file"
	15	[11]	SETTABLE 	0 -6 5	; "run_file" -
	16	[12]	GETTABLE 	5 1 -7	; "load_into_table"
	17	[12]	SETTABLE 	0 -7 5	; "load_into_table" -
	18	[14]	LOADNIL  	5 5
	19	[45]	CLOSURE  	6 0	; 0x7fb52a4070d0
	20	[45]	MOVE     	0 5
	21	[24]	SETTABLE 	0 -8 6	; "write_value" -
	22	[47]	LOADNIL  	6 6
	23	[49]	NEWTABLE 	7 0 19
	24	[50]	SETTABLE 	7 -9 -10	; "and" true
	25	[51]	SETTABLE 	7 -11 -10	; "break" true
	26	[52]	SETTABLE 	7 -12 -10	; "do" true
	27	[53]	SETTABLE 	7 -13 -10	; "else" true
	28	[54]	SETTABLE 	7 -14 -10	; "elseif" true
	29	[55]	SETTABLE 	7 -15 -10	; "end" true
	30	[56]	SETTABLE 	7 -16 -10	; "false" true
	31	[57]	SETTABLE 	7 -17 -10	; "for" true
	32	[58]	SETTABLE 	7 -18 -10	; "function" true
	33	[59]	SETTABLE 	7 -19 -10	; "goto" true
	34	[60]	SETTABLE 	7 -20 -10	; "if" true
	35	[61]	SETTABLE 	7 -21 -10	; "in" true
	36	[62]	SETTABLE 	7 -22 -10	; "local" true
	37	[63]	SETTABLE 	7 -23 -10	; "nil" true
	38	[64]	SETTABLE 	7 -24 -10	; "not" true
	39	[65]	SETTABLE 	7 -25 -10	; "or" true
	40	[66]	SETTABLE 	7 -26 -10	; "repeat" true
	41	[67]	SETTABLE 	7 -27 -10	; "return" true
	42	[68]	SETTABLE 	7 -28 -10	; "then" true
	43	[69]	SETTABLE 	7 -29 -10	; "true" true
	44	[70]	SETTABLE 	7 -30 -10	; "until" true
	45	[71]	SETTABLE 	7 -31 -10	; "while" true
	46	[77]	CLOSURE  	6 1	; 0x7fb52a407050
	47	[73]	MOVE     	0 7
	48	[77]	CLOSE    	7
	49	[90]	CLOSURE  	7 2	; 0x7fb52a406c10
	50	[90]	MOVE     	0 6
	51	[90]	MOVE     	0 0
	52	[131]	CLOSURE  	5 3	; 0x7fb52a4083f0
	53	[131]	MOVE     	0 2
	54	[131]	MOVE     	0 7
	55	[131]	MOVE     	0 0
	56	[148]	CLOSURE  	8 4	; 0x7fb52a4087f0
	57	[148]	MOVE     	0 2
	58	[148]	MOVE     	0 6
	59	[148]	MOVE     	0 0
	60	[162]	CLOSURE  	9 5	; 0x7fb52a4094e0
	61	[162]	MOVE     	0 2
	62	[162]	MOVE     	0 7
	63	[162]	MOVE     	0 0
	64	[179]	CLOSURE  	10 6	; 0x7fb52a409700
	65	[179]	MOVE     	0 8
	66	[171]	SETTABLE 	0 -32 10	; "save_from_table_to_string" -
	67	[201]	CLOSURE  	10 7	; 0x7fb52a407670
	68	[201]	MOVE     	0 8
	69	[190]	SETTABLE 	0 -33 10	; "save_from_table" -
	70	[219]	CLOSURE  	10 8	; 0x7fb52a40a230
	71	[219]	MOVE     	0 9
	72	[211]	SETTABLE 	0 -34 10	; "save_as_module" -
	73	[241]	CLOSURE  	10 9	; 0x7fb52a40a4f0
	74	[241]	MOVE     	0 0
	75	[221]	SETTABLE 	0 -35 10	; "load_config_file_if_basic" -
	76	[255]	CLOSURE  	10 10	; 0x7fb52a40a570
	77	[255]	MOVE     	0 4
	78	[255]	MOVE     	0 3
	79	[243]	SETTABLE 	0 -36 10	; "save_default_lua_version" -
	80	[257]	RETURN   	0 2
	81	[257]	RETURN   	0 1

function <./persist.lua:24,45> (74 instructions, 296 bytes at 0x7fb52a4070d0)
4 params, 14 slots, 1 upvalue, 9 locals, 19 constants, 0 functions
	1	[25]	GETGLOBAL	4 -1	; type
	2	[25]	MOVE     	5 1
	3	[25]	CALL     	4 2 2
	4	[25]	EQ       	0 4 -2	; - "table"
	5	[25]	JMP      	10	; to 16
	6	[26]	TEST     	2 0 1
	7	[26]	JMP      	1	; to 9
	8	[26]	LOADK    	2 -3	; 0
	9	[27]	GETUPVAL 	4 0	; write_table
	10	[27]	MOVE     	5 0
	11	[27]	MOVE     	6 1
	12	[27]	ADD      	7 2 -4	; - 1
	13	[27]	MOVE     	8 3
	14	[27]	CALL     	4 5 1
	15	[27]	JMP      	58	; to 74
	16	[28]	GETGLOBAL	4 -1	; type
	17	[28]	MOVE     	5 1
	18	[28]	CALL     	4 2 2
	19	[28]	EQ       	0 4 -5	; - "string"
	20	[28]	JMP      	48	; to 69
	21	[29]	SELF     	4 1 -6	; "match"
	22	[29]	LOADK    	6 -7	; "[\r\n]"
	23	[29]	CALL     	4 3 2
	24	[29]	TEST     	4 0 0
	25	[29]	JMP      	36	; to 62
	26	[30]	LOADK    	4 -8	; "[["
	27	[30]	LOADK    	5 -9	; "]]"
	28	[31]	LOADK    	6 -3	; 0
	29	[32]	MOVE     	7 1
	30	[32]	LOADK    	8 -10	; "]"
	31	[32]	CONCAT   	7 7 8
	32	[33]	SELF     	8 7 -11	; "find"
	33	[33]	MOVE     	10 5
	34	[33]	LOADK    	11 -4	; 1
	35	[33]	LOADBOOL 	12 1 0
	36	[33]	CALL     	8 5 2
	37	[33]	TEST     	8 0 0
	38	[33]	JMP      	15	; to 54
	39	[34]	ADD      	6 6 -4	; - 1
	40	[35]	LOADK    	8 -12	; "="
	41	[35]	SELF     	8 8 -13	; "rep"
	42	[35]	MOVE     	10 6
	43	[35]	CALL     	8 3 2
	44	[36]	LOADK    	9 -14	; "["
	45	[36]	MOVE     	10 8
	46	[36]	LOADK    	11 -14	; "["
	47	[36]	CONCAT   	9 9 11
	48	[36]	LOADK    	10 -10	; "]"
	49	[36]	MOVE     	11 8
	50	[36]	LOADK    	12 -10	; "]"
	51	[36]	CONCAT   	5 10 12
	52	[36]	MOVE     	4 9
	53	[36]	JMP      	-22	; to 32
	54	[38]	SELF     	8 0 -15	; "write"
	55	[38]	MOVE     	10 4
	56	[38]	LOADK    	11 -16	; "\n"
	57	[38]	MOVE     	12 1
	58	[38]	MOVE     	13 5
	59	[38]	CONCAT   	10 10 13
	60	[38]	CALL     	8 3 1
	61	[38]	JMP      	12	; to 74
	62	[40]	SELF     	4 0 -15	; "write"
	63	[40]	LOADK    	6 -17	; "%q"
	64	[40]	SELF     	6 6 -18	; "format"
	65	[40]	MOVE     	8 1
	66	[40]	CALL     	6 3 0
	67	[40]	CALL     	4 0 1
	68	[41]	JMP      	5	; to 74
	69	[43]	SELF     	4 0 -15	; "write"
	70	[43]	GETGLOBAL	6 -19	; tostring
	71	[43]	MOVE     	7 1
	72	[43]	CALL     	6 2 0
	73	[43]	CALL     	4 0 1
	74	[45]	RETURN   	0 1

function <./persist.lua:73,77> (18 instructions, 72 bytes at 0x7fb52a407050)
1 param, 4 slots, 1 upvalue, 1 local, 4 constants, 0 functions
	1	[74]	GETGLOBAL	1 -1	; type
	2	[74]	MOVE     	2 0
	3	[74]	CALL     	1 2 2
	4	[74]	EQ       	0 1 -2	; - "string"
	5	[74]	JMP      	9	; to 15
	6	[75]	SELF     	1 0 -3	; "match"
	7	[75]	LOADK    	3 -4	; "^[a-zA-Z_][a-zA-Z0-9_]*$"
	8	[75]	CALL     	1 3 2
	9	[76]	TEST     	1 0 0
	10	[76]	JMP      	6	; to 17
	11	[76]	GETUPVAL 	1 0	; keywords
	12	[76]	GETTABLE 	1 1 0
	13	[76]	NOT      	1 1
	14	[76]	JMP      	2	; to 17
	15	[76]	LOADBOOL 	1 0 1
	16	[76]	LOADBOOL 	1 1 0
	17	[76]	RETURN   	1 2
	18	[77]	RETURN   	0 1

function <./persist.lua:80,90> (25 instructions, 100 bytes at 0x7fb52a406c10)
3 params, 7 slots, 2 upvalues, 3 locals, 5 constants, 0 functions
	1	[81]	GETUPVAL 	3 0	; is_valid_plain_key
	2	[81]	MOVE     	4 1
	3	[81]	CALL     	3 2 2
	4	[81]	TEST     	3 0 0
	5	[81]	JMP      	4	; to 10
	6	[82]	SELF     	3 0 -1	; "write"
	7	[82]	MOVE     	5 1
	8	[82]	CALL     	3 3 1
	9	[82]	JMP      	12	; to 22
	10	[84]	SELF     	3 0 -1	; "write"
	11	[84]	LOADK    	5 -2	; "["
	12	[84]	CALL     	3 3 1
	13	[85]	GETUPVAL 	3 1	; persist
	14	[85]	GETTABLE 	3 3 -3	; "write_value"
	15	[85]	MOVE     	4 0
	16	[85]	MOVE     	5 1
	17	[85]	MOVE     	6 2
	18	[85]	CALL     	3 4 1
	19	[86]	SELF     	3 0 -1	; "write"
	20	[86]	LOADK    	5 -4	; "]"
	21	[86]	CALL     	3 3 1
	22	[89]	SELF     	3 0 -1	; "write"
	23	[89]	LOADK    	5 -5	; " = "
	24	[89]	CALL     	3 3 1
	25	[90]	RETURN   	0 1

function <./persist.lua:99,131> (71 instructions, 284 bytes at 0x7fb52a4083f0)
4 params, 21 slots, 3 upvalues, 22 locals, 12 constants, 0 functions
	1	[100]	SELF     	4 0 -1	; "write"
	2	[100]	LOADK    	6 -2	; "{"
	3	[100]	CALL     	4 3 1
	4	[101]	LOADK    	4 -3	; "\n"
	5	[102]	LOADK    	5 -4	; "   "
	6	[103]	LOADBOOL 	6 1 0
	7	[104]	LOADK    	7 -5	; 1
	8	[105]	GETUPVAL 	8 0	; util
	9	[105]	GETTABLE 	8 8 -6	; "sortedpairs"
	10	[105]	MOVE     	9 1
	11	[105]	MOVE     	10 3
	12	[105]	CALL     	8 3 4
	13	[105]	JMP      	39	; to 53
	14	[106]	SELF     	14 0 -1	; "write"
	15	[106]	MOVE     	16 4
	16	[106]	CALL     	14 3 1
	17	[107]	TEST     	6 0 0
	18	[107]	JMP      	8	; to 27
	19	[108]	LOADK    	14 -5	; 1
	20	[108]	MOVE     	15 2
	21	[108]	LOADK    	16 -5	; 1
	22	[108]	FORPREP  	14 3	; to 26
	23	[108]	SELF     	18 0 -1	; "write"
	24	[108]	MOVE     	20 5
	25	[108]	CALL     	18 3 1
	26	[108]	FORLOOP  	14 -4	; to 23
	27	[111]	EQ       	0 11 7
	28	[111]	JMP      	2	; to 31
	29	[112]	ADD      	7 7 -5	; - 1
	30	[112]	JMP      	5	; to 36
	31	[114]	GETUPVAL 	14 1	; write_table_key_assignment
	32	[114]	MOVE     	15 0
	33	[114]	MOVE     	16 11
	34	[114]	MOVE     	17 2
	35	[114]	CALL     	14 4 1
	36	[117]	GETUPVAL 	14 2	; persist
	37	[117]	GETTABLE 	14 14 -7	; "write_value"
	38	[117]	MOVE     	15 0
	39	[117]	MOVE     	16 12
	40	[117]	MOVE     	17 2
	41	[117]	MOVE     	18 13
	42	[117]	CALL     	14 5 1
	43	[118]	GETGLOBAL	14 -8	; type
	44	[118]	MOVE     	15 12
	45	[118]	CALL     	14 2 2
	46	[118]	EQ       	0 14 -9	; - "number"
	47	[118]	JMP      	3	; to 51
	48	[119]	LOADK    	4 -10	; ", "
	49	[120]	LOADBOOL 	6 0 0
	50	[120]	JMP      	2	; to 53
	51	[122]	LOADK    	4 -11	; ",\n"
	52	[123]	LOADBOOL 	6 1 0
	53	[105]	TFORLOOP 	8 3
	54	[124]	JMP      	-41	; to 14
	55	[126]	EQ       	1 4 -3	; - "\n"
	56	[126]	JMP      	11	; to 68
	57	[127]	SELF     	8 0 -1	; "write"
	58	[127]	LOADK    	10 -3	; "\n"
	59	[127]	CALL     	8 3 1
	60	[128]	LOADK    	8 -5	; 1
	61	[128]	SUB      	9 2 -5	; - 1
	62	[128]	LOADK    	10 -5	; 1
	63	[128]	FORPREP  	8 3	; to 67
	64	[128]	SELF     	12 0 -1	; "write"
	65	[128]	MOVE     	14 5
	66	[128]	CALL     	12 3 1
	67	[128]	FORLOOP  	8 -4	; to 64
	68	[130]	SELF     	8 0 -1	; "write"
	69	[130]	LOADK    	10 -12	; "}"
	70	[130]	CALL     	8 3 1
	71	[131]	RETURN   	0 1

function <./persist.lua:138,148> (39 instructions, 156 bytes at 0x7fb52a4087f0)
3 params, 14 slots, 3 upvalues, 9 locals, 9 constants, 0 functions
	1	[139]	GETUPVAL 	3 0	; util
	2	[139]	GETTABLE 	3 3 -1	; "sortedpairs"
	3	[139]	MOVE     	4 1
	4	[139]	MOVE     	5 2
	5	[139]	CALL     	3 3 4
	6	[139]	JMP      	28	; to 35
	7	[140]	GETUPVAL 	9 1	; is_valid_plain_key
	8	[140]	MOVE     	10 6
	9	[140]	CALL     	9 2 2
	10	[140]	TEST     	9 0 1
	11	[140]	JMP      	8	; to 20
	12	[141]	LOADNIL  	9 9
	13	[141]	LOADK    	10 -2	; "cannot store '"
	14	[141]	GETGLOBAL	11 -3	; tostring
	15	[141]	MOVE     	12 6
	16	[141]	CALL     	11 2 2
	17	[141]	LOADK    	12 -4	; "' as a plain key."
	18	[141]	CONCAT   	10 10 12
	19	[141]	RETURN   	9 3
	20	[143]	SELF     	9 0 -5	; "write"
	21	[143]	MOVE     	11 6
	22	[143]	LOADK    	12 -6	; " = "
	23	[143]	CONCAT   	11 11 12
	24	[143]	CALL     	9 3 1
	25	[144]	GETUPVAL 	9 2	; persist
	26	[144]	GETTABLE 	9 9 -7	; "write_value"
	27	[144]	MOVE     	10 0
	28	[144]	MOVE     	11 7
	29	[144]	LOADK    	12 -8	; 0
	30	[144]	MOVE     	13 8
	31	[144]	CALL     	9 5 1
	32	[145]	SELF     	9 0 -5	; "write"
	33	[145]	LOADK    	11 -9	; "\n"
	34	[145]	CALL     	9 3 1
	35	[139]	TFORLOOP 	3 3
	36	[145]	JMP      	-30	; to 7
	37	[147]	LOADBOOL 	3 1 0
	38	[147]	RETURN   	3 2
	39	[148]	RETURN   	0 1

function <./persist.lua:153,162> (32 instructions, 128 bytes at 0x7fb52a4094e0)
2 params, 13 slots, 3 upvalues, 8 locals, 8 constants, 0 functions
	1	[154]	SELF     	2 0 -1	; "write"
	2	[154]	LOADK    	4 -2	; "return {\n"
	3	[154]	CALL     	2 3 1
	4	[155]	GETUPVAL 	2 0	; util
	5	[155]	GETTABLE 	2 2 -3	; "sortedpairs"
	6	[155]	MOVE     	3 1
	7	[155]	CALL     	2 2 4
	8	[155]	JMP      	18	; to 27
	9	[156]	SELF     	8 0 -1	; "write"
	10	[156]	LOADK    	10 -4	; "   "
	11	[156]	CALL     	8 3 1
	12	[157]	GETUPVAL 	8 1	; write_table_key_assignment
	13	[157]	MOVE     	9 0
	14	[157]	MOVE     	10 5
	15	[157]	LOADK    	11 -5	; 1
	16	[157]	CALL     	8 4 1
	17	[158]	GETUPVAL 	8 2	; persist
	18	[158]	GETTABLE 	8 8 -6	; "write_value"
	19	[158]	MOVE     	9 0
	20	[158]	MOVE     	10 6
	21	[158]	LOADK    	11 -5	; 1
	22	[158]	MOVE     	12 7
	23	[158]	CALL     	8 5 1
	24	[159]	SELF     	8 0 -1	; "write"
	25	[159]	LOADK    	10 -7	; ",\n"
	26	[159]	CALL     	8 3 1
	27	[155]	TFORLOOP 	2 3
	28	[159]	JMP      	-20	; to 9
	29	[161]	SELF     	2 0 -1	; "write"
	30	[161]	LOADK    	4 -8	; "}\n"
	31	[161]	CALL     	2 3 1
	32	[162]	RETURN   	0 1

function <./persist.lua:171,179> (21 instructions, 84 bytes at 0x7fb52a409700)
2 params, 7 slots, 1 upvalue, 5 locals, 4 constants, 1 function
	1	[172]	NEWTABLE 	2 0 1
	2	[172]	NEWTABLE 	3 0 0
	3	[172]	SETTABLE 	2 -1 3	; "buffer" -
	4	[173]	CLOSURE  	3 0	; 0x7fb52a4098b0
	5	[173]	SETTABLE 	2 -2 3	; "write" -
	6	[174]	GETUPVAL 	3 0	; write_table_as_assignments
	7	[174]	MOVE     	4 2
	8	[174]	MOVE     	5 0
	9	[174]	MOVE     	6 1
	10	[174]	CALL     	3 4 3
	11	[175]	TEST     	3 0 1
	12	[175]	JMP      	3	; to 16
	13	[176]	LOADNIL  	5 5
	14	[176]	MOVE     	6 4
	15	[176]	RETURN   	5 3
	16	[178]	GETGLOBAL	5 -3	; table
	17	[178]	GETTABLE 	5 5 -4	; "concat"
	18	[178]	GETTABLE 	6 2 -1	; "buffer"
	19	[178]	TAILCALL 	5 2 0
	20	[178]	RETURN   	5 0
	21	[179]	RETURN   	0 1

function <./persist.lua:173,173> (6 instructions, 24 bytes at 0x7fb52a4098b0)
2 params, 5 slots, 0 upvalues, 2 locals, 3 constants, 0 functions
	1	[173]	GETGLOBAL	2 -1	; table
	2	[173]	GETTABLE 	2 2 -2	; "insert"
	3	[173]	GETTABLE 	3 0 -3	; "buffer"
	4	[173]	MOVE     	4 1
	5	[173]	CALL     	2 3 1
	6	[173]	RETURN   	0 1

function <./persist.lua:190,201> (27 instructions, 108 bytes at 0x7fb52a407670)
3 params, 8 slots, 1 upvalue, 6 locals, 5 constants, 0 functions
	1	[191]	GETGLOBAL	3 -1	; io
	2	[191]	GETTABLE 	3 3 -2	; "open"
	3	[191]	MOVE     	4 0
	4	[191]	LOADK    	5 -3	; "w"
	5	[191]	CALL     	3 3 2
	6	[192]	TEST     	3 0 1
	7	[192]	JMP      	5	; to 13
	8	[193]	LOADNIL  	4 4
	9	[193]	LOADK    	5 -4	; "Cannot create file at "
	10	[193]	MOVE     	6 0
	11	[193]	CONCAT   	5 5 6
	12	[193]	RETURN   	4 3
	13	[195]	GETUPVAL 	4 0	; write_table_as_assignments
	14	[195]	MOVE     	5 3
	15	[195]	MOVE     	6 1
	16	[195]	MOVE     	7 2
	17	[195]	CALL     	4 4 3
	18	[196]	SELF     	6 3 -5	; "close"
	19	[196]	CALL     	6 2 1
	20	[197]	TEST     	4 0 1
	21	[197]	JMP      	3	; to 25
	22	[198]	LOADNIL  	6 6
	23	[198]	MOVE     	7 5
	24	[198]	RETURN   	6 3
	25	[200]	LOADBOOL 	6 1 0
	26	[200]	RETURN   	6 2
	27	[201]	RETURN   	0 1

function <./persist.lua:211,219> (21 instructions, 84 bytes at 0x7fb52a40a230)
2 params, 6 slots, 1 upvalue, 3 locals, 5 constants, 0 functions
	1	[212]	GETGLOBAL	2 -1	; io
	2	[212]	GETTABLE 	2 2 -2	; "open"
	3	[212]	MOVE     	3 0
	4	[212]	LOADK    	4 -3	; "w"
	5	[212]	CALL     	2 3 2
	6	[213]	TEST     	2 0 1
	7	[213]	JMP      	5	; to 13
	8	[214]	LOADNIL  	3 3
	9	[214]	LOADK    	4 -4	; "Cannot create file at "
	10	[214]	MOVE     	5 0
	11	[214]	CONCAT   	4 4 5
	12	[214]	RETURN   	3 3
	13	[216]	GETUPVAL 	3 0	; write_table_as_table
	14	[216]	MOVE     	4 2
	15	[216]	MOVE     	5 1
	16	[216]	CALL     	3 3 1
	17	[217]	SELF     	3 2 -5	; "close"
	18	[217]	CALL     	3 2 1
	19	[218]	LOADBOOL 	3 1 0
	20	[218]	RETURN   	3 2
	21	[219]	RETURN   	0 1

function <./persist.lua:221,241> (27 instructions, 108 bytes at 0x7fb52a40a4f0)
2 params, 9 slots, 1 upvalue, 7 locals, 7 constants, 0 functions
	1	[222]	NEWTABLE 	2 0 1
	2	[223]	GETTABLE 	3 1 -1	; "home"
	3	[223]	SETTABLE 	2 -1 3	; "home" -
	4	[225]	GETUPVAL 	3 0	; persist
	5	[225]	GETTABLE 	3 3 -2	; "load_into_table"
	6	[225]	MOVE     	4 0
	7	[225]	MOVE     	5 2
	8	[225]	CALL     	3 3 4
	9	[226]	EQ       	1 5 -3	; - "load"
	10	[226]	JMP      	2	; to 13
	11	[226]	EQ       	0 5 -4	; - "run"
	12	[226]	JMP      	5	; to 18
	13	[228]	LOADNIL  	6 6
	14	[228]	LOADK    	7 -5	; "Could not read existing config file "
	15	[228]	MOVE     	8 0
	16	[228]	CONCAT   	7 7 8
	17	[228]	RETURN   	6 3
	18	[231]	LOADNIL  	6 6
	19	[232]	EQ       	0 5 -6	; - "open"
	20	[232]	JMP      	3	; to 24
	21	[234]	NEWTABLE 	7 0 0
	22	[234]	MOVE     	6 7
	23	[234]	JMP      	2	; to 26
	24	[236]	MOVE     	6 3
	25	[237]	SETTABLE 	6 -1 -7	; "home" nil
	26	[240]	RETURN   	6 2
	27	[241]	RETURN   	0 1

function <./persist.lua:243,255> (34 instructions, 136 bytes at 0x7fb52a40a570)
2 params, 11 slots, 2 upvalues, 6 locals, 10 constants, 0 functions
	1	[244]	GETUPVAL 	2 0	; fs
	2	[244]	GETTABLE 	2 2 -1	; "make_dir"
	3	[244]	MOVE     	3 0
	4	[244]	CALL     	2 2 3
	5	[245]	TEST     	2 0 1
	6	[245]	JMP      	3	; to 10
	7	[246]	LOADNIL  	4 4
	8	[246]	MOVE     	5 3
	9	[246]	RETURN   	4 3
	10	[248]	GETGLOBAL	4 -2	; io
	11	[248]	GETTABLE 	4 4 -3	; "open"
	12	[248]	GETUPVAL 	5 1	; dir
	13	[248]	GETTABLE 	5 5 -4	; "path"
	14	[248]	MOVE     	6 0
	15	[248]	LOADK    	7 -5	; "default-lua-version.lua"
	16	[248]	CALL     	5 3 2
	17	[248]	LOADK    	6 -6	; "w"
	18	[248]	CALL     	4 3 3
	19	[249]	TEST     	4 0 1
	20	[249]	JMP      	3	; to 24
	21	[250]	LOADNIL  	6 6
	22	[250]	MOVE     	7 5
	23	[250]	RETURN   	6 3
	24	[252]	SELF     	6 4 -7	; "write"
	25	[252]	LOADK    	8 -8	; "return \""
	26	[252]	MOVE     	9 1
	27	[252]	LOADK    	10 -9	; "\"\n"
	28	[252]	CONCAT   	8 8 10
	29	[252]	CALL     	6 3 1
	30	[253]	SELF     	6 4 -10	; "close"
	31	[253]	CALL     	6 2 1
	32	[254]	LOADBOOL 	6 1 0
	33	[254]	RETURN   	6 2
	34	[255]	RETURN   	0 1
