
main <./cmd/purge.lua:0,0> (52 instructions, 208 bytes at 0x7fdb52c068a0)
0+ params, 13 slots, 0 upvalues, 12 locals, 14 constants, 2 functions
	1	[4]	NEWTABLE 	0 0 0
	2	[6]	GETGLOBAL	1 -1	; require
	3	[6]	LOADK    	2 -2	; "luarocks.util"
	4	[6]	CALL     	1 2 2
	5	[7]	GETGLOBAL	2 -1	; require
	6	[7]	LOADK    	3 -3	; "luarocks.fs"
	7	[7]	CALL     	2 2 2
	8	[8]	GETGLOBAL	3 -1	; require
	9	[8]	LOADK    	4 -4	; "luarocks.path"
	10	[8]	CALL     	3 2 2
	11	[9]	GETGLOBAL	4 -1	; require
	12	[9]	LOADK    	5 -5	; "luarocks.search"
	13	[9]	CALL     	4 2 2
	14	[10]	GETGLOBAL	5 -1	; require
	15	[10]	LOADK    	6 -6	; "luarocks.core.vers"
	16	[10]	CALL     	5 2 2
	17	[11]	GETGLOBAL	6 -1	; require
	18	[11]	LOADK    	7 -7	; "luarocks.repos"
	19	[11]	CALL     	6 2 2
	20	[12]	GETGLOBAL	7 -1	; require
	21	[12]	LOADK    	8 -8	; "luarocks.manif.writer"
	22	[12]	CALL     	7 2 2
	23	[13]	GETGLOBAL	8 -1	; require
	24	[13]	LOADK    	9 -9	; "luarocks.core.cfg"
	25	[13]	CALL     	8 2 2
	26	[14]	GETGLOBAL	9 -1	; require
	27	[14]	LOADK    	10 -10	; "luarocks.remove"
	28	[14]	CALL     	9 2 2
	29	[15]	GETGLOBAL	10 -1	; require
	30	[15]	LOADK    	11 -11	; "luarocks.queries"
	31	[15]	CALL     	10 2 2
	32	[16]	GETGLOBAL	11 -1	; require
	33	[16]	LOADK    	12 -12	; "luarocks.cmd"
	34	[16]	CALL     	11 2 2
	35	[35]	CLOSURE  	12 0	; 0x7fdb52c06fd0
	36	[35]	MOVE     	0 1
	37	[18]	SETTABLE 	0 -13 12	; "add_to_parser" -
	38	[78]	CLOSURE  	12 1	; 0x7fdb52c07600
	39	[78]	MOVE     	0 1
	40	[78]	MOVE     	0 2
	41	[78]	MOVE     	0 11
	42	[78]	MOVE     	0 4
	43	[78]	MOVE     	0 3
	44	[78]	MOVE     	0 10
	45	[78]	MOVE     	0 5
	46	[78]	MOVE     	0 9
	47	[78]	MOVE     	0 6
	48	[78]	MOVE     	0 7
	49	[78]	MOVE     	0 8
	50	[37]	SETTABLE 	0 -14 12	; "command" -
	51	[80]	RETURN   	0 2
	52	[80]	RETURN   	0 1

function <./cmd/purge.lua:18,35> (31 instructions, 124 bytes at 0x7fdb52c06fd0)
1 param, 9 slots, 1 upvalue, 2 locals, 18 constants, 0 functions
	1	[19]	SELF     	1 0 -1	; "command"
	2	[19]	LOADK    	3 -2	; "purge"
	3	[23]	LOADK    	4 -3	; "This command removes rocks en masse from a given tree.\nBy default, it removes all rocks from a tree.\n\nThe --tree option is mandatory: luarocks purge does not assume a default tree."
	4	[24]	GETUPVAL 	5 0	; util
	5	[24]	GETTABLE 	5 5 -4	; "see_also"
	6	[24]	CALL     	5 1 0
	7	[19]	CALL     	1 0 2
	8	[25]	SELF     	1 1 -5	; "summary"
	9	[25]	LOADK    	3 -6	; "Remove all installed rocks from a tree."
	10	[25]	CALL     	1 3 2
	11	[27]	SELF     	2 1 -7	; "flag"
	12	[27]	LOADK    	4 -8	; "--old-versions"
	13	[27]	LOADK    	5 -9	; "Keep the highest-numbered version of each "
	14	[28]	LOADK    	6 -10	; "rock and remove the other ones. By default it only removes old "
	15	[29]	LOADK    	7 -11	; "versions if they are not needed as dependencies. This can be "
	16	[30]	LOADK    	8 -12	; "overridden with the flag --force."
	17	[30]	CONCAT   	5 5 8
	18	[27]	CALL     	2 4 1
	19	[31]	SELF     	2 1 -7	; "flag"
	20	[31]	LOADK    	4 -13	; "--force"
	21	[31]	LOADK    	5 -14	; "If --old-versions is specified, force removal of "
	22	[32]	LOADK    	6 -15	; "previously installed versions if it would break dependencies."
	23	[32]	CONCAT   	5 5 6
	24	[31]	CALL     	2 4 1
	25	[33]	SELF     	2 1 -7	; "flag"
	26	[33]	LOADK    	4 -16	; "--force-fast"
	27	[33]	LOADK    	5 -17	; "Like --force, but performs a forced removal "
	28	[34]	LOADK    	6 -18	; "without reporting dependency issues."
	29	[34]	CONCAT   	5 5 6
	30	[33]	CALL     	2 4 1
	31	[35]	RETURN   	0 1

function <./cmd/purge.lua:37,78> (128 instructions, 512 bytes at 0x7fdb52c07600)
1 param, 22 slots, 11 upvalues, 20 locals, 30 constants, 1 function
	1	[38]	GETTABLE 	1 0 -1	; "tree"
	2	[40]	GETGLOBAL	2 -2	; type
	3	[40]	MOVE     	3 1
	4	[40]	CALL     	2 2 2
	5	[40]	EQ       	1 2 -3	; - "string"
	6	[40]	JMP      	8	; to 15
	7	[41]	LOADNIL  	2 2
	8	[41]	LOADK    	3 -4	; "The --tree argument is mandatory. "
	9	[41]	GETUPVAL 	4 0	; util
	10	[41]	GETTABLE 	4 4 -5	; "see_help"
	11	[41]	LOADK    	5 -6	; "purge"
	12	[41]	CALL     	4 2 2
	13	[41]	CONCAT   	3 3 4
	14	[41]	RETURN   	2 3
	15	[44]	NEWTABLE 	2 0 0
	16	[45]	GETUPVAL 	3 1	; fs
	17	[45]	GETTABLE 	3 3 -7	; "is_dir"
	18	[45]	MOVE     	4 1
	19	[45]	CALL     	3 2 2
	20	[45]	TEST     	3 0 1
	21	[45]	JMP      	5	; to 27
	22	[46]	LOADNIL  	3 3
	23	[46]	LOADK    	4 -8	; "Directory not found: "
	24	[46]	MOVE     	5 1
	25	[46]	CONCAT   	4 4 5
	26	[46]	RETURN   	3 3
	27	[49]	GETUPVAL 	3 1	; fs
	28	[49]	GETTABLE 	3 3 -9	; "check_command_permissions"
	29	[49]	MOVE     	4 0
	30	[49]	CALL     	3 2 3
	31	[50]	TEST     	3 0 1
	32	[50]	JMP      	6	; to 39
	33	[50]	LOADNIL  	5 5
	34	[50]	MOVE     	6 4
	35	[50]	GETUPVAL 	7 2	; cmd
	36	[50]	GETTABLE 	7 7 -10	; "errorcodes"
	37	[50]	GETTABLE 	7 7 -11	; "PERMISSIONDENIED"
	38	[50]	RETURN   	5 4
	39	[52]	GETUPVAL 	5 3	; search
	40	[52]	GETTABLE 	5 5 -12	; "local_manifest_search"
	41	[52]	MOVE     	6 2
	42	[52]	GETUPVAL 	7 4	; path
	43	[52]	GETTABLE 	7 7 -13	; "rocks_dir"
	44	[52]	MOVE     	8 1
	45	[52]	CALL     	7 2 2
	46	[52]	GETUPVAL 	8 5	; queries
	47	[52]	GETTABLE 	8 8 -14	; "all"
	48	[52]	CALL     	8 1 0
	49	[52]	CALL     	5 0 1
	50	[54]	CLOSURE  	5 0	; 0x7fdb52c07d20
	51	[54]	GETUPVAL 	0 6	; vers
	52	[55]	GETTABLE 	6 0 -15	; "old_versions"
	53	[55]	TEST     	6 0 0
	54	[55]	JMP      	2	; to 57
	55	[56]	GETUPVAL 	6 6	; vers
	56	[56]	GETTABLE 	5 6 -16	; "compare_versions"
	57	[59]	GETUPVAL 	6 0	; util
	58	[59]	GETTABLE 	6 6 -17	; "sortedpairs"
	59	[59]	MOVE     	7 2
	60	[59]	CALL     	6 2 4
	61	[59]	JMP      	57	; to 119
	62	[60]	GETUPVAL 	11 0	; util
	63	[60]	GETTABLE 	11 11 -17	; "sortedpairs"
	64	[60]	MOVE     	12 10
	65	[60]	MOVE     	13 5
	66	[60]	CALL     	11 3 4
	67	[60]	JMP      	49	; to 117
	68	[61]	GETTABLE 	16 0 -15	; "old_versions"
	69	[61]	TEST     	16 0 0
	70	[61]	JMP      	24	; to 95
	71	[62]	GETUPVAL 	16 0	; util
	72	[62]	GETTABLE 	16 16 -18	; "printout"
	73	[62]	LOADK    	17 -19	; "Keeping "
	74	[62]	MOVE     	18 9
	75	[62]	LOADK    	19 -20	; " "
	76	[62]	MOVE     	20 14
	77	[62]	LOADK    	21 -21	; "..."
	78	[62]	CONCAT   	17 17 21
	79	[62]	CALL     	16 2 1
	80	[63]	GETUPVAL 	16 7	; remove
	81	[63]	GETTABLE 	16 16 -22	; "remove_other_versions"
	82	[63]	MOVE     	17 9
	83	[63]	MOVE     	18 14
	84	[63]	GETTABLE 	19 0 -23	; "force"
	85	[63]	GETTABLE 	20 0 -24	; "force_fast"
	86	[63]	CALL     	16 5 3
	87	[64]	TEST     	16 0 1
	88	[64]	JMP      	30	; to 119
	89	[65]	GETUPVAL 	18 0	; util
	90	[65]	GETTABLE 	18 18 -25	; "printerr"
	91	[65]	MOVE     	19 17
	92	[65]	CALL     	18 2 1
	93	[67]	JMP      	25	; to 119
	94	[67]	JMP      	22	; to 117
	95	[69]	GETUPVAL 	16 0	; util
	96	[69]	GETTABLE 	16 16 -18	; "printout"
	97	[69]	LOADK    	17 -26	; "Removing "
	98	[69]	MOVE     	18 9
	99	[69]	LOADK    	19 -20	; " "
	100	[69]	MOVE     	20 14
	101	[69]	LOADK    	21 -21	; "..."
	102	[69]	CONCAT   	17 17 21
	103	[69]	CALL     	16 2 1
	104	[70]	GETUPVAL 	16 8	; repos
	105	[70]	GETTABLE 	16 16 -27	; "delete_version"
	106	[70]	MOVE     	17 9
	107	[70]	MOVE     	18 14
	108	[70]	LOADK    	19 -28	; "none"
	109	[70]	LOADBOOL 	20 1 0
	110	[70]	CALL     	16 5 3
	111	[71]	TEST     	16 0 1
	112	[71]	JMP      	4	; to 117
	113	[72]	GETUPVAL 	18 0	; util
	114	[72]	GETTABLE 	18 18 -25	; "printerr"
	115	[72]	MOVE     	19 17
	116	[72]	CALL     	18 2 1
	117	[60]	TFORLOOP 	11 2
	118	[74]	JMP      	-51	; to 68
	119	[59]	TFORLOOP 	6 2
	120	[75]	JMP      	-59	; to 62
	121	[77]	GETUPVAL 	6 9	; writer
	122	[77]	GETTABLE 	6 6 -29	; "make_manifest"
	123	[77]	GETUPVAL 	7 10	; cfg
	124	[77]	GETTABLE 	7 7 -13	; "rocks_dir"
	125	[77]	LOADK    	8 -30	; "one"
	126	[77]	TAILCALL 	6 3 0
	127	[77]	RETURN   	6 0
	128	[78]	RETURN   	0 1

function <./cmd/purge.lua:54,54> (7 instructions, 28 bytes at 0x7fdb52c07d20)
2 params, 5 slots, 1 upvalue, 2 locals, 1 constant, 0 functions
	1	[54]	GETUPVAL 	2 0	; vers
	2	[54]	GETTABLE 	2 2 -1	; "compare_versions"
	3	[54]	MOVE     	3 1
	4	[54]	MOVE     	4 0
	5	[54]	TAILCALL 	2 3 0
	6	[54]	RETURN   	2 0
	7	[54]	RETURN   	0 1
