
main <./queries.lua:0,0> (65 instructions, 260 bytes at 0x7f8e82c068a0)
0+ params, 9 slots, 0 upvalues, 9 locals, 28 constants, 9 functions
	1	[2]	NEWTABLE 	0 0 0
	2	[4]	GETGLOBAL	1 -1	; require
	3	[4]	LOADK    	2 -2	; "luarocks.core.vers"
	4	[4]	CALL     	1 2 2
	5	[5]	GETGLOBAL	2 -1	; require
	6	[5]	LOADK    	3 -3	; "luarocks.util"
	7	[5]	CALL     	2 2 2
	8	[6]	GETGLOBAL	3 -1	; require
	9	[6]	LOADK    	4 -4	; "luarocks.core.cfg"
	10	[6]	CALL     	3 2 2
	11	[8]	NEWTABLE 	4 0 0
	12	[10]	SETTABLE 	4 -5 4	; "__index" -
	13	[14]	CLOSURE  	5 0	; 0x7f8e82c06fd0
	14	[12]	SETTABLE 	4 -6 5	; "type" -
	15	[17]	NEWTABLE 	5 0 4
	16	[18]	SETTABLE 	5 -8 -9	; "src" true
	17	[19]	SETTABLE 	5 -10 -9	; "all" true
	18	[20]	SETTABLE 	5 -11 -9	; "rockspec" true
	19	[21]	SETTABLE 	5 -12 -9	; "installed" true
	20	[23]	SETTABLE 	4 -7 5	; "arch" -
	21	[26]	SETTABLE 	4 -13 -14	; "substring" false
	22	[40]	CLOSURE  	5 1	; 0x7f8e82c06ea0
	23	[74]	CLOSURE  	6 2	; 0x7f8e82c07400
	24	[74]	MOVE     	0 5
	25	[74]	MOVE     	0 1
	26	[74]	MOVE     	0 4
	27	[74]	MOVE     	0 3
	28	[51]	SETTABLE 	0 -15 6	; "new" -
	29	[82]	CLOSURE  	6 3	; 0x7f8e82c075e0
	30	[82]	MOVE     	0 0
	31	[78]	SETTABLE 	0 -10 6	; "all" -
	32	[85]	LOADNIL  	6 7
	33	[89]	NEWTABLE 	8 0 10
	34	[90]	SETTABLE 	8 -16 -16	; "==" "=="
	35	[91]	SETTABLE 	8 -17 -17	; "~=" "~="
	36	[92]	SETTABLE 	8 -18 -18	; ">" ">"
	37	[93]	SETTABLE 	8 -19 -19	; "<" "<"
	38	[94]	SETTABLE 	8 -20 -20	; ">=" ">="
	39	[95]	SETTABLE 	8 -21 -21	; "<=" "<="
	40	[96]	SETTABLE 	8 -22 -22	; "~>" "~>"
	41	[98]	SETTABLE 	8 -23 -16	; "" "=="
	42	[99]	SETTABLE 	8 -24 -16	; "=" "=="
	43	[100]	SETTABLE 	8 -25 -17	; "!=" "~="
	44	[124]	CLOSURE  	7 4	; 0x7f8e82c06dc0
	45	[124]	MOVE     	0 8
	46	[124]	MOVE     	0 1
	47	[124]	CLOSE    	8
	48	[148]	CLOSURE  	6 5	; 0x7f8e82c08300
	49	[148]	MOVE     	0 7
	50	[148]	CLOSE    	7
	51	[178]	CLOSURE  	7 6	; 0x7f8e82c06d00
	52	[178]	MOVE     	0 6
	53	[178]	MOVE     	0 2
	54	[178]	MOVE     	0 4
	55	[178]	MOVE     	0 3
	56	[155]	SETTABLE 	0 -26 7	; "from_dep_string" -
	57	[178]	CLOSE    	6
	58	[184]	CLOSURE  	6 7	; 0x7f8e82c08fe0
	59	[184]	MOVE     	0 4
	60	[184]	MOVE     	0 3
	61	[181]	SETTABLE 	0 -27 6	; "from_persisted_table" -
	62	[213]	CLOSURE  	6 8	; 0x7f8e82c09580
	63	[190]	SETTABLE 	4 -28 6	; "__tostring" -
	64	[215]	RETURN   	0 2
	65	[215]	RETURN   	0 1

function <./queries.lua:12,14> (3 instructions, 12 bytes at 0x7f8e82c06fd0)
0 params, 2 slots, 0 upvalues, 0 locals, 1 constant, 0 functions
	1	[13]	LOADK    	0 -1	; "query"
	2	[13]	RETURN   	0 2
	3	[14]	RETURN   	0 1

function <./queries.lua:30,40> (22 instructions, 88 bytes at 0x7f8e82c06ea0)
1 param, 8 slots, 0 upvalues, 6 locals, 6 constants, 0 functions
	1	[31]	GETGLOBAL	1 -1	; type
	2	[31]	MOVE     	2 0
	3	[31]	CALL     	1 2 2
	4	[31]	EQ       	0 1 -2	; - "table"
	5	[31]	JMP      	2	; to 8
	6	[32]	RETURN   	0 2
	7	[32]	JMP      	14	; to 22
	8	[33]	GETGLOBAL	1 -1	; type
	9	[33]	MOVE     	2 0
	10	[33]	CALL     	1 2 2
	11	[33]	EQ       	0 1 -3	; - "string"
	12	[33]	JMP      	9	; to 22
	13	[34]	NEWTABLE 	1 0 0
	14	[35]	SELF     	2 0 -4	; "gmatch"
	15	[35]	LOADK    	4 -5	; "[%w_-]+"
	16	[35]	CALL     	2 3 4
	17	[35]	JMP      	1	; to 19
	18	[36]	SETTABLE 	1 5 -6	; - true
	19	[35]	TFORLOOP 	2 1
	20	[36]	JMP      	-3	; to 18
	21	[38]	RETURN   	1 2
	22	[40]	RETURN   	0 1

function <./queries.lua:51,74> (101 instructions, 404 bytes at 0x7f8e82c07400)
6 params, 12 slots, 4 upvalues, 7 locals, 17 constants, 0 functions
	1	[52]	GETGLOBAL	6 -1	; assert
	2	[52]	GETGLOBAL	7 -2	; type
	3	[52]	MOVE     	8 0
	4	[52]	CALL     	7 2 2
	5	[52]	EQ       	1 7 -3	; - "string"
	6	[52]	JMP      	1	; to 8
	7	[52]	LOADBOOL 	7 0 1
	8	[52]	LOADBOOL 	7 1 0
	9	[52]	CALL     	6 2 1
	10	[53]	GETGLOBAL	6 -1	; assert
	11	[53]	GETGLOBAL	7 -2	; type
	12	[53]	MOVE     	8 1
	13	[53]	CALL     	7 2 2
	14	[53]	EQ       	1 7 -3	; - "string"
	15	[53]	JMP      	3	; to 19
	16	[53]	NOT      	7 1
	17	[53]	JMP      	2	; to 20
	18	[53]	LOADBOOL 	7 0 1
	19	[53]	LOADBOOL 	7 1 0
	20	[53]	CALL     	6 2 1
	21	[54]	GETGLOBAL	6 -1	; assert
	22	[54]	GETGLOBAL	7 -2	; type
	23	[54]	MOVE     	8 2
	24	[54]	CALL     	7 2 2
	25	[54]	EQ       	1 7 -3	; - "string"
	26	[54]	JMP      	3	; to 30
	27	[54]	NOT      	7 2
	28	[54]	JMP      	2	; to 31
	29	[54]	LOADBOOL 	7 0 1
	30	[54]	LOADBOOL 	7 1 0
	31	[54]	CALL     	6 2 1
	32	[55]	GETGLOBAL	6 -1	; assert
	33	[55]	GETGLOBAL	7 -2	; type
	34	[55]	MOVE     	8 3
	35	[55]	CALL     	7 2 2
	36	[55]	EQ       	1 7 -4	; - "boolean"
	37	[55]	JMP      	3	; to 41
	38	[55]	NOT      	7 3
	39	[55]	JMP      	2	; to 42
	40	[55]	LOADBOOL 	7 0 1
	41	[55]	LOADBOOL 	7 1 0
	42	[55]	CALL     	6 2 1
	43	[56]	GETGLOBAL	6 -1	; assert
	44	[56]	GETGLOBAL	7 -2	; type
	45	[56]	MOVE     	8 4
	46	[56]	CALL     	7 2 2
	47	[56]	EQ       	1 7 -3	; - "string"
	48	[56]	JMP      	3	; to 52
	49	[56]	NOT      	7 4
	50	[56]	JMP      	2	; to 53
	51	[56]	LOADBOOL 	7 0 1
	52	[56]	LOADBOOL 	7 1 0
	53	[56]	CALL     	6 2 1
	54	[57]	GETGLOBAL	6 -1	; assert
	55	[57]	GETGLOBAL	7 -2	; type
	56	[57]	MOVE     	8 5
	57	[57]	CALL     	7 2 2
	58	[57]	EQ       	1 7 -3	; - "string"
	59	[57]	JMP      	3	; to 63
	60	[57]	NOT      	7 5
	61	[57]	JMP      	2	; to 64
	62	[57]	LOADBOOL 	7 0 1
	63	[57]	LOADBOOL 	7 1 0
	64	[57]	CALL     	6 2 1
	65	[59]	TEST     	5 0 1
	66	[59]	JMP      	1	; to 68
	67	[59]	LOADK    	5 -5	; "=="
	68	[61]	NEWTABLE 	6 0 5
	69	[62]	SETTABLE 	6 -6 0	; "name" -
	70	[63]	SETTABLE 	6 -7 1	; "namespace" -
	71	[64]	NEWTABLE 	7 0 0
	72	[64]	SETTABLE 	6 -8 7	; "constraints" -
	73	[65]	SETTABLE 	6 -9 3	; "substring" -
	74	[66]	GETUPVAL 	7 0	; arch_to_table
	75	[66]	MOVE     	8 4
	76	[66]	CALL     	7 2 2
	77	[66]	SETTABLE 	6 -10 7	; "arch" -
	78	[68]	TEST     	2 0 0
	79	[68]	JMP      	11	; to 91
	80	[69]	GETGLOBAL	7 -11	; table
	81	[69]	GETTABLE 	7 7 -12	; "insert"
	82	[69]	GETTABLE 	8 6 -8	; "constraints"
	83	[69]	NEWTABLE 	9 0 2
	84	[69]	SETTABLE 	9 -13 5	; "op" -
	85	[69]	GETUPVAL 	10 1	; vers
	86	[69]	GETTABLE 	10 10 -15	; "parse_version"
	87	[69]	MOVE     	11 2
	88	[69]	CALL     	10 2 2
	89	[69]	SETTABLE 	9 -14 10	; "version" -
	90	[69]	CALL     	7 3 1
	91	[72]	GETUPVAL 	7 2	; query_mt
	92	[72]	GETTABLE 	7 7 -10	; "arch"
	93	[72]	GETUPVAL 	8 3	; cfg
	94	[72]	GETTABLE 	8 8 -10	; "arch"
	95	[72]	SETTABLE 	7 8 -16	; - true
	96	[73]	GETGLOBAL	7 -17	; setmetatable
	97	[73]	MOVE     	8 6
	98	[73]	GETUPVAL 	9 2	; query_mt
	99	[73]	TAILCALL 	7 3 0
	100	[73]	RETURN   	7 0
	101	[74]	RETURN   	0 1

function <./queries.lua:78,82> (20 instructions, 80 bytes at 0x7f8e82c075e0)
1 param, 7 slots, 1 upvalue, 1 local, 5 constants, 0 functions
	1	[79]	GETGLOBAL	1 -1	; assert
	2	[79]	GETGLOBAL	2 -2	; type
	3	[79]	MOVE     	3 0
	4	[79]	CALL     	2 2 2
	5	[79]	EQ       	1 2 -3	; - "string"
	6	[79]	JMP      	3	; to 10
	7	[79]	NOT      	2 0
	8	[79]	JMP      	2	; to 11
	9	[79]	LOADBOOL 	2 0 1
	10	[79]	LOADBOOL 	2 1 0
	11	[79]	CALL     	1 2 1
	12	[81]	GETUPVAL 	1 0	; queries
	13	[81]	GETTABLE 	1 1 -4	; "new"
	14	[81]	LOADK    	2 -5	; ""
	15	[81]	LOADNIL  	3 4
	16	[81]	LOADBOOL 	5 1 0
	17	[81]	MOVE     	6 0
	18	[81]	TAILCALL 	1 6 0
	19	[81]	RETURN   	1 0
	20	[82]	RETURN   	0 1

function <./queries.lua:111,124> (52 instructions, 208 bytes at 0x7f8e82c06dc0)
1 param, 12 slots, 2 upvalues, 6 locals, 15 constants, 0 functions
	1	[112]	GETGLOBAL	1 -1	; assert
	2	[112]	GETGLOBAL	2 -2	; type
	3	[112]	MOVE     	3 0
	4	[112]	CALL     	2 2 2
	5	[112]	EQ       	1 2 -3	; - "string"
	6	[112]	JMP      	1	; to 8
	7	[112]	LOADBOOL 	2 0 1
	8	[112]	LOADBOOL 	2 1 0
	9	[112]	CALL     	1 2 1
	10	[114]	SELF     	1 0 -4	; "match"
	11	[114]	LOADK    	3 -5	; "^(@?)([<>=~!]*)%s*([%w%.%_%-]+)[%s,]*(.*)"
	12	[114]	CALL     	1 3 5
	13	[115]	GETUPVAL 	5 0	; operators
	14	[115]	GETTABLE 	5 5 2
	15	[116]	GETUPVAL 	6 1	; vers
	16	[116]	GETTABLE 	6 6 -6	; "parse_version"
	17	[116]	MOVE     	7 3
	18	[116]	CALL     	6 2 2
	19	[116]	MOVE     	3 6
	20	[117]	TEST     	5 0 1
	21	[117]	JMP      	10	; to 32
	22	[118]	LOADNIL  	6 6
	23	[118]	LOADK    	7 -7	; "Encountered bad constraint operator: '"
	24	[118]	GETGLOBAL	8 -8	; tostring
	25	[118]	MOVE     	9 2
	26	[118]	CALL     	8 2 2
	27	[118]	LOADK    	9 -9	; "' in '"
	28	[118]	MOVE     	10 0
	29	[118]	LOADK    	11 -10	; "'"
	30	[118]	CONCAT   	7 7 11
	31	[118]	RETURN   	6 3
	32	[120]	TEST     	3 0 1
	33	[120]	JMP      	6	; to 40
	34	[121]	LOADNIL  	6 6
	35	[121]	LOADK    	7 -11	; "Could not parse version from constraint: '"
	36	[121]	MOVE     	8 0
	37	[121]	LOADK    	9 -10	; "'"
	38	[121]	CONCAT   	7 7 9
	39	[121]	RETURN   	6 3
	40	[123]	NEWTABLE 	6 0 3
	41	[123]	SETTABLE 	6 -12 5	; "op" -
	42	[123]	SETTABLE 	6 -13 3	; "version" -
	43	[123]	EQ       	0 1 -15	; - "@"
	44	[123]	JMP      	3	; to 48
	45	[123]	LOADBOOL 	7 1 0
	46	[123]	TEST     	7 0 1
	47	[123]	JMP      	1	; to 49
	48	[123]	LOADNIL  	7 7
	49	[123]	SETTABLE 	6 -14 7	; "no_upgrade" -
	50	[123]	MOVE     	7 4
	51	[123]	RETURN   	6 3
	52	[124]	RETURN   	0 1

function <./queries.lua:135,148> (40 instructions, 160 bytes at 0x7f8e82c08300)
1 param, 9 slots, 1 upvalue, 4 locals, 9 constants, 0 functions
	1	[136]	GETGLOBAL	1 -1	; assert
	2	[136]	GETGLOBAL	2 -2	; type
	3	[136]	MOVE     	3 0
	4	[136]	CALL     	2 2 2
	5	[136]	EQ       	1 2 -3	; - "string"
	6	[136]	JMP      	1	; to 8
	7	[136]	LOADBOOL 	2 0 1
	8	[136]	LOADBOOL 	2 1 0
	9	[136]	CALL     	1 2 1
	10	[138]	NEWTABLE 	1 0 0
	11	[138]	MOVE     	2 0
	12	[138]	LOADNIL  	3 3
	13	[139]	LEN      	4 0
	14	[139]	LT       	0 -4 4	; 0 -
	15	[139]	JMP      	23	; to 39
	16	[140]	GETUPVAL 	4 0	; parse_constraint
	17	[140]	MOVE     	5 0
	18	[140]	CALL     	4 2 3
	19	[140]	MOVE     	0 5
	20	[140]	MOVE     	3 4
	21	[141]	TEST     	3 0 0
	22	[141]	JMP      	6	; to 29
	23	[142]	GETGLOBAL	4 -5	; table
	24	[142]	GETTABLE 	4 4 -6	; "insert"
	25	[142]	MOVE     	5 1
	26	[142]	MOVE     	6 3
	27	[142]	CALL     	4 3 1
	28	[142]	JMP      	-16	; to 13
	29	[144]	LOADNIL  	4 4
	30	[144]	LOADK    	5 -7	; "Failed to parse constraint '"
	31	[144]	GETGLOBAL	6 -8	; tostring
	32	[144]	MOVE     	7 2
	33	[144]	CALL     	6 2 2
	34	[144]	LOADK    	7 -9	; "' with error: "
	35	[144]	MOVE     	8 0
	36	[144]	CONCAT   	5 5 8
	37	[144]	RETURN   	4 3
	38	[145]	JMP      	-26	; to 13
	39	[147]	RETURN   	1 2
	40	[148]	RETURN   	0 1

function <./queries.lua:155,178> (47 instructions, 188 bytes at 0x7f8e82c06d00)
1 param, 11 slots, 4 upvalues, 8 locals, 14 constants, 0 functions
	1	[156]	GETGLOBAL	1 -1	; assert
	2	[156]	GETGLOBAL	2 -2	; type
	3	[156]	MOVE     	3 0
	4	[156]	CALL     	2 2 2
	5	[156]	EQ       	1 2 -3	; - "string"
	6	[156]	JMP      	1	; to 8
	7	[156]	LOADBOOL 	2 0 1
	8	[156]	LOADBOOL 	2 1 0
	9	[156]	CALL     	1 2 1
	10	[158]	SELF     	1 0 -4	; "match"
	11	[158]	LOADK    	3 -5	; "^%s*([a-zA-Z0-9%.%-%_]*/?[a-zA-Z0-9][a-zA-Z0-9%.%-%_]*)%s*([^/]*)"
	12	[158]	CALL     	1 3 3
	13	[159]	TEST     	1 0 1
	14	[159]	JMP      	6	; to 21
	15	[160]	LOADNIL  	3 3
	16	[160]	LOADK    	4 -6	; "failed to extract dependency name from '"
	17	[160]	MOVE     	5 0
	18	[160]	LOADK    	6 -7	; "'"
	19	[160]	CONCAT   	4 4 6
	20	[160]	RETURN   	3 3
	21	[163]	GETUPVAL 	3 0	; parse_constraints
	22	[163]	MOVE     	4 2
	23	[163]	CALL     	3 2 3
	24	[164]	TEST     	3 0 1
	25	[164]	JMP      	3	; to 29
	26	[165]	LOADNIL  	5 5
	27	[165]	MOVE     	6 4
	28	[165]	RETURN   	5 3
	29	[168]	GETUPVAL 	5 1	; util
	30	[168]	GETTABLE 	5 5 -8	; "split_namespace"
	31	[168]	MOVE     	6 1
	32	[168]	CALL     	5 2 3
	33	[170]	NEWTABLE 	7 0 3
	34	[171]	SETTABLE 	7 -9 5	; "name" -
	35	[172]	SETTABLE 	7 -10 6	; "namespace" -
	36	[173]	SETTABLE 	7 -11 3	; "constraints" -
	37	[176]	GETUPVAL 	8 2	; query_mt
	38	[176]	GETTABLE 	8 8 -12	; "arch"
	39	[176]	GETUPVAL 	9 3	; cfg
	40	[176]	GETTABLE 	9 9 -12	; "arch"
	41	[176]	SETTABLE 	8 9 -13	; - true
	42	[177]	GETGLOBAL	8 -14	; setmetatable
	43	[177]	MOVE     	9 7
	44	[177]	GETUPVAL 	10 2	; query_mt
	45	[177]	TAILCALL 	8 3 0
	46	[177]	RETURN   	8 0
	47	[178]	RETURN   	0 1

function <./queries.lua:181,184> (11 instructions, 44 bytes at 0x7f8e82c08fe0)
1 param, 4 slots, 2 upvalues, 1 local, 3 constants, 0 functions
	1	[182]	GETUPVAL 	1 0	; query_mt
	2	[182]	GETTABLE 	1 1 -1	; "arch"
	3	[182]	GETUPVAL 	2 1	; cfg
	4	[182]	GETTABLE 	2 2 -1	; "arch"
	5	[182]	SETTABLE 	1 2 -2	; - true
	6	[183]	GETGLOBAL	1 -3	; setmetatable
	7	[183]	MOVE     	2 0
	8	[183]	GETUPVAL 	3 0	; query_mt
	9	[183]	TAILCALL 	1 3 0
	10	[183]	RETURN   	1 0
	11	[184]	RETURN   	0 1

function <./queries.lua:190,213> (69 instructions, 276 bytes at 0x7f8e82c09580)
1 param, 14 slots, 0 upvalues, 9 locals, 15 constants, 0 functions
	1	[191]	NEWTABLE 	1 0 0
	2	[192]	GETTABLE 	2 0 -1	; "namespace"
	3	[192]	TEST     	2 0 0
	4	[192]	JMP      	10	; to 15
	5	[193]	GETGLOBAL	2 -2	; table
	6	[193]	GETTABLE 	2 2 -3	; "insert"
	7	[193]	MOVE     	3 1
	8	[193]	GETTABLE 	4 0 -1	; "namespace"
	9	[193]	CALL     	2 3 1
	10	[194]	GETGLOBAL	2 -2	; table
	11	[194]	GETTABLE 	2 2 -3	; "insert"
	12	[194]	MOVE     	3 1
	13	[194]	LOADK    	4 -4	; "/"
	14	[194]	CALL     	2 3 1
	15	[196]	GETGLOBAL	2 -2	; table
	16	[196]	GETTABLE 	2 2 -3	; "insert"
	17	[196]	MOVE     	3 1
	18	[196]	GETTABLE 	4 0 -5	; "name"
	19	[196]	CALL     	2 3 1
	20	[198]	GETTABLE 	2 0 -6	; "constraints"
	21	[198]	LEN      	2 2
	22	[198]	LT       	0 -7 2	; 0 -
	23	[198]	JMP      	40	; to 64
	24	[199]	NEWTABLE 	2 0 0
	25	[200]	GETGLOBAL	3 -8	; ipairs
	26	[200]	GETTABLE 	4 0 -6	; "constraints"
	27	[200]	CALL     	3 2 4
	28	[200]	JMP      	19	; to 48
	29	[201]	GETTABLE 	8 7 -9	; "version"
	30	[201]	GETTABLE 	8 8 -10	; "string"
	31	[202]	GETTABLE 	9 7 -11	; "op"
	32	[202]	EQ       	0 9 -12	; - "=="
	33	[202]	JMP      	6	; to 40
	34	[203]	GETGLOBAL	9 -2	; table
	35	[203]	GETTABLE 	9 9 -3	; "insert"
	36	[203]	MOVE     	10 2
	37	[203]	MOVE     	11 8
	38	[203]	CALL     	9 3 1
	39	[203]	JMP      	8	; to 48
	40	[205]	GETGLOBAL	9 -2	; table
	41	[205]	GETTABLE 	9 9 -3	; "insert"
	42	[205]	MOVE     	10 2
	43	[205]	GETTABLE 	11 7 -11	; "op"
	44	[205]	LOADK    	12 -13	; " "
	45	[205]	MOVE     	13 8
	46	[205]	CONCAT   	11 11 13
	47	[205]	CALL     	9 3 1
	48	[200]	TFORLOOP 	3 2
	49	[206]	JMP      	-21	; to 29
	50	[208]	GETGLOBAL	3 -2	; table
	51	[208]	GETTABLE 	3 3 -3	; "insert"
	52	[208]	MOVE     	4 1
	53	[208]	LOADK    	5 -13	; " "
	54	[208]	CALL     	3 3 1
	55	[209]	GETGLOBAL	3 -2	; table
	56	[209]	GETTABLE 	3 3 -3	; "insert"
	57	[209]	MOVE     	4 1
	58	[209]	GETGLOBAL	5 -2	; table
	59	[209]	GETTABLE 	5 5 -14	; "concat"
	60	[209]	MOVE     	6 2
	61	[209]	LOADK    	7 -15	; ", "
	62	[209]	CALL     	5 3 0
	63	[209]	CALL     	3 0 1
	64	[212]	GETGLOBAL	2 -2	; table
	65	[212]	GETTABLE 	2 2 -14	; "concat"
	66	[212]	MOVE     	3 1
	67	[212]	TAILCALL 	2 2 0
	68	[212]	RETURN   	2 0
	69	[213]	RETURN   	0 1
