
main <./remove.lua:0,0> (48 instructions, 192 bytes at 0x7f92854068a0)
0+ params, 12 slots, 0 upvalues, 11 locals, 11 constants, 4 functions
	1	[1]	NEWTABLE 	0 0 0
	2	[3]	GETGLOBAL	1 -1	; require
	3	[3]	LOADK    	2 -2	; "luarocks.search"
	4	[3]	CALL     	1 2 2
	5	[4]	GETGLOBAL	2 -1	; require
	6	[4]	LOADK    	3 -3	; "luarocks.deps"
	7	[4]	CALL     	2 2 2
	8	[5]	GETGLOBAL	3 -1	; require
	9	[5]	LOADK    	4 -4	; "luarocks.fetch"
	10	[5]	CALL     	3 2 2
	11	[6]	GETGLOBAL	4 -1	; require
	12	[6]	LOADK    	5 -5	; "luarocks.repos"
	13	[6]	CALL     	4 2 2
	14	[7]	GETGLOBAL	5 -1	; require
	15	[7]	LOADK    	6 -6	; "luarocks.path"
	16	[7]	CALL     	5 2 2
	17	[8]	GETGLOBAL	6 -1	; require
	18	[8]	LOADK    	7 -7	; "luarocks.util"
	19	[8]	CALL     	6 2 2
	20	[9]	GETGLOBAL	7 -1	; require
	21	[9]	LOADK    	8 -8	; "luarocks.core.cfg"
	22	[9]	CALL     	7 2 2
	23	[10]	GETGLOBAL	8 -1	; require
	24	[10]	LOADK    	9 -9	; "luarocks.queries"
	25	[10]	CALL     	8 2 2
	26	[41]	CLOSURE  	9 0	; 0x7f9285406f50
	27	[41]	MOVE     	0 8
	28	[41]	MOVE     	0 1
	29	[41]	MOVE     	0 7
	30	[41]	MOVE     	0 3
	31	[41]	MOVE     	0 5
	32	[41]	MOVE     	0 2
	33	[59]	CLOSURE  	10 1	; 0x7f92854073c0
	34	[59]	MOVE     	0 6
	35	[59]	MOVE     	0 4
	36	[104]	CLOSURE  	11 2	; 0x7f9285407050
	37	[104]	MOVE     	0 6
	38	[104]	MOVE     	0 9
	39	[104]	MOVE     	0 10
	40	[61]	SETTABLE 	0 -10 11	; "remove_search_results" -
	41	[114]	CLOSURE  	11 3	; 0x7f9285408560
	42	[114]	MOVE     	0 8
	43	[114]	MOVE     	0 1
	44	[114]	MOVE     	0 7
	45	[114]	MOVE     	0 0
	46	[106]	SETTABLE 	0 -11 11	; "remove_other_versions" -
	47	[116]	RETURN   	0 2
	48	[116]	RETURN   	0 1

function <./remove.lua:18,41> (65 instructions, 260 bytes at 0x7f9285406f50)
3 params, 24 slots, 6 upvalues, 26 locals, 15 constants, 0 functions
	1	[19]	NEWTABLE 	3 0 0
	2	[20]	NEWTABLE 	4 0 0
	3	[21]	NEWTABLE 	5 0 0
	4	[21]	SETTABLE 	4 0 5
	5	[22]	GETGLOBAL	5 -1	; pairs
	6	[22]	MOVE     	6 1
	7	[22]	CALL     	5 2 4
	8	[22]	JMP      	2	; to 11
	9	[23]	GETTABLE 	10 4 0
	10	[23]	SETTABLE 	10 8 -2	; - true
	11	[22]	TFORLOOP 	5 2
	12	[23]	JMP      	-4	; to 9
	13	[25]	NEWTABLE 	5 0 0
	14	[26]	GETUPVAL 	6 0	; queries
	15	[26]	GETTABLE 	6 6 -3	; "all"
	16	[26]	CALL     	6 1 2
	17	[27]	GETUPVAL 	7 1	; search
	18	[27]	GETTABLE 	7 7 -4	; "local_manifest_search"
	19	[27]	MOVE     	8 5
	20	[27]	GETUPVAL 	9 2	; cfg
	21	[27]	GETTABLE 	9 9 -5	; "rocks_dir"
	22	[27]	MOVE     	10 6
	23	[27]	CALL     	7 4 1
	24	[28]	SETTABLE 	5 0 -6	; - nil
	25	[29]	GETGLOBAL	7 -1	; pairs
	26	[29]	MOVE     	8 5
	27	[29]	CALL     	7 2 4
	28	[29]	JMP      	33	; to 62
	29	[30]	GETGLOBAL	12 -1	; pairs
	30	[30]	MOVE     	13 11
	31	[30]	CALL     	12 2 4
	32	[30]	JMP      	27	; to 60
	33	[31]	GETUPVAL 	17 3	; fetch
	34	[31]	GETTABLE 	17 17 -7	; "load_rockspec"
	35	[31]	GETUPVAL 	18 4	; path
	36	[31]	GETTABLE 	18 18 -8	; "rockspec_file"
	37	[31]	MOVE     	19 10
	38	[31]	MOVE     	20 15
	39	[31]	CALL     	18 3 0
	40	[31]	CALL     	17 0 3
	41	[32]	TEST     	17 0 0
	42	[32]	JMP      	17	; to 60
	43	[33]	GETUPVAL 	19 5	; deps
	44	[33]	GETTABLE 	19 19 -9	; "match_deps"
	45	[33]	GETTABLE 	20 17 -10	; "dependencies"
	46	[33]	GETTABLE 	21 17 -11	; "rocks_provided"
	47	[33]	MOVE     	22 4
	48	[33]	MOVE     	23 2
	49	[33]	CALL     	19 5 3
	50	[34]	GETTABLE 	21 20 0
	51	[34]	TEST     	21 0 0
	52	[34]	JMP      	7	; to 60
	53	[35]	GETGLOBAL	21 -12	; table
	54	[35]	GETTABLE 	21 21 -13	; "insert"
	55	[35]	MOVE     	22 3
	56	[35]	NEWTABLE 	23 0 2
	57	[35]	SETTABLE 	23 -14 10	; "name" -
	58	[35]	SETTABLE 	23 -15 15	; "version" -
	59	[35]	CALL     	21 3 1
	60	[30]	TFORLOOP 	12 2
	61	[37]	JMP      	-29	; to 33
	62	[29]	TFORLOOP 	7 2
	63	[38]	JMP      	-35	; to 29
	64	[40]	RETURN   	3 2
	65	[41]	RETURN   	0 1

function <./remove.lua:50,59> (29 instructions, 116 bytes at 0x7f92854073c0)
3 params, 14 slots, 2 upvalues, 10 locals, 6 constants, 0 functions
	1	[52]	GETGLOBAL	3 -1	; pairs
	2	[52]	MOVE     	4 1
	3	[52]	CALL     	3 2 4
	4	[52]	JMP      	20	; to 25
	5	[53]	GETUPVAL 	8 0	; util
	6	[53]	GETTABLE 	8 8 -2	; "printout"
	7	[53]	LOADK    	9 -3	; "Removing "
	8	[53]	MOVE     	10 0
	9	[53]	LOADK    	11 -4	; " "
	10	[53]	MOVE     	12 6
	11	[53]	LOADK    	13 -5	; "..."
	12	[53]	CONCAT   	9 9 13
	13	[53]	CALL     	8 2 1
	14	[54]	GETUPVAL 	8 1	; repos
	15	[54]	GETTABLE 	8 8 -6	; "delete_version"
	16	[54]	MOVE     	9 0
	17	[54]	MOVE     	10 6
	18	[54]	MOVE     	11 2
	19	[54]	CALL     	8 4 3
	20	[55]	TEST     	8 0 1
	21	[55]	JMP      	3	; to 25
	22	[55]	LOADNIL  	10 10
	23	[55]	MOVE     	11 9
	24	[55]	RETURN   	10 3
	25	[52]	TFORLOOP 	3 2
	26	[55]	JMP      	-22	; to 5
	27	[58]	LOADBOOL 	3 1 0
	28	[58]	RETURN   	3 2
	29	[59]	RETURN   	0 1

function <./remove.lua:61,104> (134 instructions, 536 bytes at 0x7f9285407050)
5 params, 18 slots, 3 upvalues, 21 locals, 23 constants, 0 functions
	1	[62]	GETTABLE 	5 0 1
	2	[64]	GETGLOBAL	6 -1	; next
	3	[64]	MOVE     	7 5
	4	[64]	CALL     	6 2 2
	5	[65]	GETGLOBAL	7 -1	; next
	6	[65]	MOVE     	8 5
	7	[65]	MOVE     	9 6
	8	[65]	CALL     	7 3 2
	9	[67]	NEWTABLE 	8 0 0
	10	[68]	TEST     	4 0 1
	11	[68]	JMP      	28	; to 40
	12	[69]	GETUPVAL 	9 0	; util
	13	[69]	GETTABLE 	9 9 -2	; "printout"
	14	[69]	LOADK    	10 -3	; "Checking stability of dependencies in the absence of"
	15	[69]	CALL     	9 2 1
	16	[70]	GETUPVAL 	9 0	; util
	17	[70]	GETTABLE 	9 9 -2	; "printout"
	18	[70]	MOVE     	10 1
	19	[70]	LOADK    	11 -4	; " "
	20	[70]	GETGLOBAL	12 -5	; table
	21	[70]	GETTABLE 	12 12 -6	; "concat"
	22	[70]	GETUPVAL 	13 0	; util
	23	[70]	GETTABLE 	13 13 -7	; "keys"
	24	[70]	MOVE     	14 5
	25	[70]	CALL     	13 2 2
	26	[70]	LOADK    	14 -8	; ", "
	27	[70]	CALL     	12 3 2
	28	[70]	LOADK    	13 -9	; "..."
	29	[70]	CONCAT   	10 10 13
	30	[70]	CALL     	9 2 1
	31	[71]	GETUPVAL 	9 0	; util
	32	[71]	GETTABLE 	9 9 -2	; "printout"
	33	[71]	CALL     	9 1 1
	34	[72]	GETUPVAL 	9 1	; check_dependents
	35	[72]	MOVE     	10 1
	36	[72]	MOVE     	11 5
	37	[72]	MOVE     	12 2
	38	[72]	CALL     	9 4 2
	39	[72]	MOVE     	8 9
	40	[75]	LEN      	9 8
	41	[75]	LT       	0 -10 9	; 0 -
	42	[75]	JMP      	75	; to 118
	43	[76]	TEST     	3 0 1
	44	[76]	JMP      	2	; to 47
	45	[76]	TEST     	4 0 0
	46	[76]	JMP      	21	; to 68
	47	[77]	GETUPVAL 	9 0	; util
	48	[77]	GETTABLE 	9 9 -11	; "printerr"
	49	[77]	LOADK    	10 -12	; "The following packages may be broken by this forced removal:"
	50	[77]	CALL     	9 2 1
	51	[78]	GETGLOBAL	9 -13	; ipairs
	52	[78]	MOVE     	10 8
	53	[78]	CALL     	9 2 4
	54	[78]	JMP      	7	; to 62
	55	[79]	GETUPVAL 	14 0	; util
	56	[79]	GETTABLE 	14 14 -11	; "printerr"
	57	[79]	GETTABLE 	15 13 -14	; "name"
	58	[79]	LOADK    	16 -4	; " "
	59	[79]	GETTABLE 	17 13 -15	; "version"
	60	[79]	CONCAT   	15 15 17
	61	[79]	CALL     	14 2 1
	62	[78]	TFORLOOP 	9 2
	63	[79]	JMP      	-9	; to 55
	64	[81]	GETUPVAL 	9 0	; util
	65	[81]	GETTABLE 	9 9 -11	; "printerr"
	66	[81]	CALL     	9 1 1
	67	[81]	JMP      	50	; to 118
	68	[83]	TEST     	7 0 1
	69	[83]	JMP      	14	; to 84
	70	[84]	GETUPVAL 	9 0	; util
	71	[84]	GETTABLE 	9 9 -11	; "printerr"
	72	[84]	LOADK    	10 -16	; "Will not remove "
	73	[84]	MOVE     	11 1
	74	[84]	LOADK    	12 -4	; " "
	75	[84]	MOVE     	13 6
	76	[84]	LOADK    	14 -17	; "."
	77	[84]	CONCAT   	10 10 14
	78	[84]	CALL     	9 2 1
	79	[85]	GETUPVAL 	9 0	; util
	80	[85]	GETTABLE 	9 9 -11	; "printerr"
	81	[85]	LOADK    	10 -18	; "Removing it would break dependencies for: "
	82	[85]	CALL     	9 2 1
	83	[85]	JMP      	11	; to 95
	84	[87]	GETUPVAL 	9 0	; util
	85	[87]	GETTABLE 	9 9 -11	; "printerr"
	86	[87]	LOADK    	10 -19	; "Will not remove installed versions of "
	87	[87]	MOVE     	11 1
	88	[87]	LOADK    	12 -17	; "."
	89	[87]	CONCAT   	10 10 12
	90	[87]	CALL     	9 2 1
	91	[88]	GETUPVAL 	9 0	; util
	92	[88]	GETTABLE 	9 9 -11	; "printerr"
	93	[88]	LOADK    	10 -20	; "Removing them would break dependencies for: "
	94	[88]	CALL     	9 2 1
	95	[90]	GETGLOBAL	9 -13	; ipairs
	96	[90]	MOVE     	10 8
	97	[90]	CALL     	9 2 4
	98	[90]	JMP      	7	; to 106
	99	[91]	GETUPVAL 	14 0	; util
	100	[91]	GETTABLE 	14 14 -11	; "printerr"
	101	[91]	GETTABLE 	15 13 -14	; "name"
	102	[91]	LOADK    	16 -4	; " "
	103	[91]	GETTABLE 	17 13 -15	; "version"
	104	[91]	CONCAT   	15 15 17
	105	[91]	CALL     	14 2 1
	106	[90]	TFORLOOP 	9 2
	107	[91]	JMP      	-9	; to 99
	108	[93]	GETUPVAL 	9 0	; util
	109	[93]	GETTABLE 	9 9 -11	; "printerr"
	110	[93]	CALL     	9 1 1
	111	[94]	GETUPVAL 	9 0	; util
	112	[94]	GETTABLE 	9 9 -11	; "printerr"
	113	[94]	LOADK    	10 -21	; "Use --force to force removal (warning: this may break modules)."
	114	[94]	CALL     	9 2 1
	115	[95]	LOADNIL  	9 9
	116	[95]	LOADK    	10 -22	; "Failed removing."
	117	[95]	RETURN   	9 3
	118	[99]	GETUPVAL 	9 2	; delete_versions
	119	[99]	MOVE     	10 1
	120	[99]	MOVE     	11 5
	121	[99]	MOVE     	12 2
	122	[99]	CALL     	9 4 3
	123	[100]	TEST     	9 0 1
	124	[100]	JMP      	3	; to 128
	125	[100]	LOADNIL  	11 11
	126	[100]	MOVE     	12 10
	127	[100]	RETURN   	11 3
	128	[102]	GETUPVAL 	11 0	; util
	129	[102]	GETTABLE 	11 11 -2	; "printout"
	130	[102]	LOADK    	12 -23	; "Removal successful."
	131	[102]	CALL     	11 2 1
	132	[103]	LOADBOOL 	11 1 0
	133	[103]	RETURN   	11 2
	134	[104]	RETURN   	0 1

function <./remove.lua:106,114> (33 instructions, 132 bytes at 0x7f9285408560)
4 params, 12 slots, 4 upvalues, 6 locals, 6 constants, 0 functions
	1	[107]	NEWTABLE 	4 0 0
	2	[108]	GETUPVAL 	5 0	; queries
	3	[108]	GETTABLE 	5 5 -1	; "new"
	4	[108]	MOVE     	6 0
	5	[108]	LOADNIL  	7 7
	6	[108]	MOVE     	8 1
	7	[108]	LOADBOOL 	9 0 0
	8	[108]	LOADNIL  	10 10
	9	[108]	LOADK    	11 -2	; "~="
	10	[108]	CALL     	5 7 2
	11	[109]	GETUPVAL 	6 1	; search
	12	[109]	GETTABLE 	6 6 -3	; "local_manifest_search"
	13	[109]	MOVE     	7 4
	14	[109]	GETUPVAL 	8 2	; cfg
	15	[109]	GETTABLE 	8 8 -4	; "rocks_dir"
	16	[109]	MOVE     	9 5
	17	[109]	CALL     	6 4 1
	18	[110]	GETTABLE 	6 4 0
	19	[110]	TEST     	6 0 0
	20	[110]	JMP      	10	; to 31
	21	[111]	GETUPVAL 	6 3	; remove
	22	[111]	GETTABLE 	6 6 -5	; "remove_search_results"
	23	[111]	MOVE     	7 4
	24	[111]	MOVE     	8 0
	25	[111]	GETUPVAL 	9 2	; cfg
	26	[111]	GETTABLE 	9 9 -6	; "deps_mode"
	27	[111]	MOVE     	10 2
	28	[111]	MOVE     	11 3
	29	[111]	TAILCALL 	6 6 0
	30	[111]	RETURN   	6 0
	31	[113]	LOADBOOL 	6 1 0
	32	[113]	RETURN   	6 2
	33	[114]	RETURN   	0 1
