
main <./repos.lua:0,0> (127 instructions, 508 bytes at 0x7ff7bdc068a0)
0+ params, 25 slots, 0 upvalues, 24 locals, 19 constants, 23 functions
	1	[3]	NEWTABLE 	0 0 0
	2	[5]	GETGLOBAL	1 -1	; require
	3	[5]	LOADK    	2 -2	; "luarocks.fs"
	4	[5]	CALL     	1 2 2
	5	[6]	GETGLOBAL	2 -1	; require
	6	[6]	LOADK    	3 -3	; "luarocks.path"
	7	[6]	CALL     	2 2 2
	8	[7]	GETGLOBAL	3 -1	; require
	9	[7]	LOADK    	4 -4	; "luarocks.core.cfg"
	10	[7]	CALL     	3 2 2
	11	[8]	GETGLOBAL	4 -1	; require
	12	[8]	LOADK    	5 -5	; "luarocks.util"
	13	[8]	CALL     	4 2 2
	14	[9]	GETGLOBAL	5 -1	; require
	15	[9]	LOADK    	6 -6	; "luarocks.dir"
	16	[9]	CALL     	5 2 2
	17	[10]	GETGLOBAL	6 -1	; require
	18	[10]	LOADK    	7 -7	; "luarocks.manif"
	19	[10]	CALL     	6 2 2
	20	[11]	GETGLOBAL	7 -1	; require
	21	[11]	LOADK    	8 -8	; "luarocks.core.vers"
	22	[11]	CALL     	7 2 2
	23	[12]	NEWTABLE 	8 0 0
	24	[14]	GETGLOBAL	9 -9	; unpack
	25	[14]	TEST     	9 0 1
	26	[14]	JMP      	2	; to 29
	27	[14]	GETGLOBAL	9 -10	; table
	28	[14]	GETTABLE 	9 9 -9	; "unpack"
	29	[26]	CLOSURE  	10 0	; 0x7ff7bdc06f50
	30	[26]	MOVE     	0 2
	31	[54]	CLOSURE  	11 1	; 0x7ff7bdc07250
	32	[54]	MOVE     	0 1
	33	[54]	MOVE     	0 2
	34	[67]	CLOSURE  	12 2	; 0x7ff7bdc07050
	35	[67]	MOVE     	0 1
	36	[67]	MOVE     	0 2
	37	[62]	SETTABLE 	0 -11 12	; "is_installed" -
	38	[93]	CLOSURE  	12 3	; 0x7ff7bdc074d0
	39	[69]	SETTABLE 	0 -12 12	; "recurse_rock_manifest_entry" -
	40	[103]	CLOSURE  	12 4	; 0x7ff7bdc08670
	41	[103]	MOVE     	0 0
	42	[103]	MOVE     	0 10
	43	[124]	CLOSURE  	13 5	; 0x7ff7bdc08cf0
	44	[124]	MOVE     	0 6
	45	[124]	MOVE     	0 12
	46	[114]	SETTABLE 	0 -13 13	; "package_modules" -
	47	[144]	CLOSURE  	13 6	; 0x7ff7bdc09350
	48	[144]	MOVE     	0 6
	49	[144]	MOVE     	0 12
	50	[135]	SETTABLE 	0 -14 13	; "package_commands" -
	51	[166]	CLOSURE  	13 7	; 0x7ff7bdc096b0
	52	[166]	MOVE     	0 6
	53	[166]	MOVE     	0 1
	54	[166]	MOVE     	0 5
	55	[166]	MOVE     	0 3
	56	[152]	SETTABLE 	0 -15 13	; "has_binaries" -
	57	[193]	CLOSURE  	13 8	; 0x7ff7bdc09930
	58	[193]	MOVE     	0 3
	59	[193]	MOVE     	0 4
	60	[193]	MOVE     	0 1
	61	[168]	SETTABLE 	0 -16 13	; "run_hook" -
	62	[205]	CLOSURE  	13 9	; 0x7ff7bdc09de0
	63	[205]	MOVE     	0 3
	64	[195]	SETTABLE 	0 -17 13	; "should_wrap_bin_scripts" -
	65	[220]	CLOSURE  	13 10	; 0x7ff7bdc06e20
	66	[220]	MOVE     	0 1
	67	[228]	CLOSURE  	14 11	; 0x7ff7bdc08350
	68	[228]	MOVE     	0 13
	69	[247]	CLOSURE  	15 12	; 0x7ff7bdc07780
	70	[247]	MOVE     	0 3
	71	[247]	MOVE     	0 2
	72	[247]	MOVE     	0 5
	73	[261]	CLOSURE  	16 13	; 0x7ff7bdc091c0
	74	[261]	MOVE     	0 10
	75	[261]	MOVE     	0 6
	76	[261]	MOVE     	0 7
	77	[281]	CLOSURE  	17 14	; 0x7ff7bdc06d10
	78	[281]	MOVE     	0 1
	79	[281]	MOVE     	0 4
	80	[329]	CLOSURE  	18 15	; 0x7ff7bdc0bd40
	81	[329]	MOVE     	0 1
	82	[329]	MOVE     	0 5
	83	[329]	MOVE     	0 17
	84	[338]	CLOSURE  	19 16	; 0x7ff7bdc0d420
	85	[338]	MOVE     	0 1
	86	[338]	MOVE     	0 5
	87	[356]	CLOSURE  	20 17	; 0x7ff7bdc0a1d0
	88	[356]	MOVE     	0 14
	89	[356]	MOVE     	0 1
	90	[356]	MOVE     	0 5
	91	[360]	CLOSURE  	21 18	; 0x7ff7bdc0dc30
	92	[360]	MOVE     	0 20
	93	[388]	CLOSURE  	22 19	; 0x7ff7bdc0db50
	94	[388]	MOVE     	0 1
	95	[388]	MOVE     	0 14
	96	[388]	MOVE     	0 5
	97	[394]	CLOSURE  	23 20	; 0x7ff7bdc0eaa0
	98	[509]	CLOSURE  	24 21	; 0x7ff7bdc0ed90
	99	[509]	MOVE     	0 6
	100	[509]	MOVE     	0 3
	101	[509]	MOVE     	0 1
	102	[509]	MOVE     	0 2
	103	[509]	MOVE     	0 0
	104	[509]	MOVE     	0 5
	105	[509]	MOVE     	0 15
	106	[509]	MOVE     	0 16
	107	[509]	MOVE     	0 20
	108	[509]	MOVE     	0 23
	109	[509]	MOVE     	0 21
	110	[509]	MOVE     	0 18
	111	[509]	MOVE     	0 19
	112	[403]	SETTABLE 	0 -18 24	; "deploy_files" -
	113	[614]	CLOSURE  	24 22	; 0x7ff7bdc0f220
	114	[614]	MOVE     	0 6
	115	[614]	MOVE     	0 3
	116	[614]	MOVE     	0 0
	117	[614]	MOVE     	0 15
	118	[614]	MOVE     	0 16
	119	[614]	MOVE     	0 22
	120	[614]	MOVE     	0 20
	121	[614]	MOVE     	0 1
	122	[614]	MOVE     	0 2
	123	[614]	MOVE     	0 11
	124	[614]	MOVE     	0 5
	125	[521]	SETTABLE 	0 -19 24	; "delete_version" -
	126	[616]	RETURN   	0 2
	127	[616]	RETURN   	0 1

function <./repos.lua:20,26> (36 instructions, 144 bytes at 0x7ff7bdc06f50)
2 params, 6 slots, 1 upvalue, 4 locals, 7 constants, 0 functions
	1	[21]	GETGLOBAL	2 -1	; assert
	2	[21]	GETGLOBAL	3 -2	; type
	3	[21]	MOVE     	4 0
	4	[21]	CALL     	3 2 2
	5	[21]	EQ       	1 3 -3	; - "string"
	6	[21]	JMP      	1	; to 8
	7	[21]	LOADBOOL 	3 0 1
	8	[21]	LOADBOOL 	3 1 0
	9	[21]	CALL     	2 2 1
	10	[22]	GETGLOBAL	2 -1	; assert
	11	[22]	GETGLOBAL	3 -2	; type
	12	[22]	MOVE     	4 1
	13	[22]	CALL     	3 2 2
	14	[22]	EQ       	1 3 -3	; - "string"
	15	[22]	JMP      	1	; to 17
	16	[22]	LOADBOOL 	3 0 1
	17	[22]	LOADBOOL 	3 1 0
	18	[22]	CALL     	2 2 1
	19	[23]	EQ       	0 0 -4	; - "bin"
	20	[23]	JMP      	3	; to 24
	21	[23]	LOADK    	2 -5	; "command"
	22	[23]	TEST     	2 0 1
	23	[23]	JMP      	1	; to 25
	24	[23]	LOADK    	2 -6	; "module"
	25	[24]	EQ       	0 2 -5	; - "command"
	26	[24]	JMP      	2	; to 29
	27	[24]	TESTSET  	3 1 1
	28	[24]	JMP      	4	; to 33
	29	[24]	GETUPVAL 	3 0	; path
	30	[24]	GETTABLE 	3 3 -7	; "path_to_module"
	31	[24]	MOVE     	4 1
	32	[24]	CALL     	3 2 2
	33	[25]	MOVE     	4 2
	34	[25]	MOVE     	5 3
	35	[25]	RETURN   	4 3
	36	[26]	RETURN   	0 1

function <./repos.lua:49,54> (31 instructions, 124 bytes at 0x7ff7bdc07250)
1 param, 5 slots, 2 upvalues, 2 locals, 8 constants, 0 functions
	1	[50]	GETGLOBAL	1 -1	; assert
	2	[50]	GETGLOBAL	2 -2	; type
	3	[50]	MOVE     	3 0
	4	[50]	CALL     	2 2 2
	5	[50]	EQ       	0 2 -3	; - "string"
	6	[50]	JMP      	5	; to 12
	7	[50]	SELF     	2 0 -4	; "match"
	8	[50]	LOADK    	4 -5	; "/"
	9	[50]	CALL     	2 3 2
	10	[50]	NOT      	2 2
	11	[50]	JMP      	2	; to 14
	12	[50]	LOADBOOL 	2 0 1
	13	[50]	LOADBOOL 	2 1 0
	14	[50]	CALL     	1 2 1
	15	[52]	GETUPVAL 	1 0	; fs
	16	[52]	GETTABLE 	1 1 -6	; "list_dir"
	17	[52]	GETUPVAL 	2 1	; path
	18	[52]	GETTABLE 	2 2 -7	; "versions_dir"
	19	[52]	MOVE     	3 0
	20	[52]	CALL     	2 2 0
	21	[52]	CALL     	1 0 2
	22	[53]	TEST     	1 0 0
	23	[53]	JMP      	5	; to 29
	24	[53]	LEN      	2 1
	25	[53]	LT       	0 -8 2	; 0 -
	26	[53]	JMP      	2	; to 29
	27	[53]	TESTSET  	2 1 1
	28	[53]	JMP      	1	; to 30
	29	[53]	LOADNIL  	2 2
	30	[53]	RETURN   	2 2
	31	[54]	RETURN   	0 1

function <./repos.lua:62,67> (33 instructions, 132 bytes at 0x7ff7bdc07050)
2 params, 6 slots, 2 upvalues, 2 locals, 7 constants, 0 functions
	1	[63]	GETGLOBAL	2 -1	; assert
	2	[63]	GETGLOBAL	3 -2	; type
	3	[63]	MOVE     	4 0
	4	[63]	CALL     	3 2 2
	5	[63]	EQ       	0 3 -3	; - "string"
	6	[63]	JMP      	5	; to 12
	7	[63]	SELF     	3 0 -4	; "match"
	8	[63]	LOADK    	5 -5	; "/"
	9	[63]	CALL     	3 3 2
	10	[63]	NOT      	3 3
	11	[63]	JMP      	2	; to 14
	12	[63]	LOADBOOL 	3 0 1
	13	[63]	LOADBOOL 	3 1 0
	14	[63]	CALL     	2 2 1
	15	[64]	GETGLOBAL	2 -1	; assert
	16	[64]	GETGLOBAL	3 -2	; type
	17	[64]	MOVE     	4 1
	18	[64]	CALL     	3 2 2
	19	[64]	EQ       	1 3 -3	; - "string"
	20	[64]	JMP      	1	; to 22
	21	[64]	LOADBOOL 	3 0 1
	22	[64]	LOADBOOL 	3 1 0
	23	[64]	CALL     	2 2 1
	24	[66]	GETUPVAL 	2 0	; fs
	25	[66]	GETTABLE 	2 2 -6	; "is_dir"
	26	[66]	GETUPVAL 	3 1	; path
	27	[66]	GETTABLE 	3 3 -7	; "install_dir"
	28	[66]	MOVE     	4 0
	29	[66]	MOVE     	5 1
	30	[66]	CALL     	3 3 0
	31	[66]	TAILCALL 	2 0 0
	32	[66]	RETURN   	2 0
	33	[67]	RETURN   	0 1

function <./repos.lua:69,93> (21 instructions, 84 bytes at 0x7ff7bdc074d0)
2 params, 5 slots, 0 upvalues, 3 locals, 4 constants, 1 function
	1	[70]	GETGLOBAL	2 -1	; assert
	2	[70]	GETGLOBAL	3 -2	; type
	3	[70]	MOVE     	4 1
	4	[70]	CALL     	3 2 2
	5	[70]	EQ       	1 3 -3	; - "function"
	6	[70]	JMP      	1	; to 8
	7	[70]	LOADBOOL 	3 0 1
	8	[70]	LOADBOOL 	3 1 0
	9	[70]	CALL     	2 2 1
	10	[72]	EQ       	0 0 -4	; - nil
	11	[72]	JMP      	2	; to 14
	12	[73]	LOADBOOL 	2 1 0
	13	[73]	RETURN   	2 2
	14	[91]	CLOSURE  	2 0	; 0x7ff7bdc08130
	15	[91]	MOVE     	0 2
	16	[91]	MOVE     	0 1
	17	[92]	MOVE     	3 2
	18	[92]	MOVE     	4 0
	19	[92]	TAILCALL 	3 2 0
	20	[92]	RETURN   	3 0
	21	[93]	RETURN   	0 1

function <./repos.lua:76,91> (42 instructions, 168 bytes at 0x7ff7bdc08130)
2 params, 13 slots, 2 upvalues, 10 locals, 5 constants, 0 functions
	1	[78]	GETGLOBAL	2 -1	; pairs
	2	[78]	MOVE     	3 0
	3	[78]	CALL     	2 2 4
	4	[78]	JMP      	33	; to 38
	5	[79]	TEST     	1 0 0
	6	[79]	JMP      	5	; to 12
	7	[79]	MOVE     	7 1
	8	[79]	LOADK    	8 -2	; "/"
	9	[79]	CONCAT   	7 7 8
	10	[79]	TEST     	7 0 1
	11	[79]	JMP      	1	; to 13
	12	[79]	LOADK    	7 -3	; ""
	13	[79]	MOVE     	8 5
	14	[79]	CONCAT   	7 7 8
	15	[80]	LOADNIL  	8 9
	16	[82]	GETGLOBAL	10 -4	; type
	17	[82]	MOVE     	11 6
	18	[82]	CALL     	10 2 2
	19	[82]	EQ       	0 10 -5	; - "table"
	20	[82]	JMP      	7	; to 28
	21	[83]	GETUPVAL 	10 0	; do_recurse_rock_manifest_entry
	22	[83]	MOVE     	11 6
	23	[83]	MOVE     	12 7
	24	[83]	CALL     	10 3 3
	25	[83]	MOVE     	9 11
	26	[83]	MOVE     	8 10
	27	[83]	JMP      	5	; to 33
	28	[85]	GETUPVAL 	10 1	; action
	29	[85]	MOVE     	11 7
	30	[85]	CALL     	10 2 3
	31	[85]	MOVE     	9 11
	32	[85]	MOVE     	8 10
	33	[88]	TEST     	9 0 0
	34	[88]	JMP      	3	; to 38
	35	[88]	LOADNIL  	10 10
	36	[88]	MOVE     	11 9
	37	[88]	RETURN   	10 3
	38	[78]	TFORLOOP 	2 2
	39	[88]	JMP      	-35	; to 5
	40	[90]	LOADBOOL 	2 1 0
	41	[90]	RETURN   	2 2
	42	[91]	RETURN   	0 1

function <./repos.lua:95,103> (12 instructions, 48 bytes at 0x7ff7bdc08670)
3 params, 6 slots, 2 upvalues, 3 locals, 1 constant, 1 function
	1	[96]	GETTABLE 	3 1 2
	2	[96]	TEST     	3 0 0
	3	[96]	JMP      	8	; to 12
	4	[97]	GETUPVAL 	3 0	; repos
	5	[97]	GETTABLE 	3 3 -1	; "recurse_rock_manifest_entry"
	6	[97]	GETTABLE 	4 1 2
	7	[101]	CLOSURE  	5 0	; 0x7ff7bdc08c20
	8	[101]	GETUPVAL 	0 1	; get_provided_item
	9	[101]	MOVE     	0 2
	10	[101]	MOVE     	0 0
	11	[97]	CALL     	3 3 1
	12	[103]	RETURN   	0 1

function <./repos.lua:97,101> (9 instructions, 36 bytes at 0x7ff7bdc08c20)
1 param, 4 slots, 3 upvalues, 3 locals, 0 constants, 0 functions
	1	[98]	GETUPVAL 	1 0	; get_provided_item
	2	[98]	GETUPVAL 	2 1	; deploy_type
	3	[98]	MOVE     	3 0
	4	[98]	CALL     	1 3 3
	5	[99]	GETUPVAL 	3 2	; result
	6	[99]	SETTABLE 	3 2 0
	7	[100]	LOADBOOL 	3 1 0
	8	[100]	RETURN   	3 2
	9	[101]	RETURN   	0 1

function <./repos.lua:114,124> (44 instructions, 176 bytes at 0x7ff7bdc08cf0)
2 params, 8 slots, 2 upvalues, 4 locals, 8 constants, 0 functions
	1	[115]	GETGLOBAL	2 -1	; assert
	2	[115]	GETGLOBAL	3 -2	; type
	3	[115]	MOVE     	4 0
	4	[115]	CALL     	3 2 2
	5	[115]	EQ       	0 3 -3	; - "string"
	6	[115]	JMP      	5	; to 12
	7	[115]	SELF     	3 0 -4	; "match"
	8	[115]	LOADK    	5 -5	; "/"
	9	[115]	CALL     	3 3 2
	10	[115]	NOT      	3 3
	11	[115]	JMP      	2	; to 14
	12	[115]	LOADBOOL 	3 0 1
	13	[115]	LOADBOOL 	3 1 0
	14	[115]	CALL     	2 2 1
	15	[116]	GETGLOBAL	2 -1	; assert
	16	[116]	GETGLOBAL	3 -2	; type
	17	[116]	MOVE     	4 1
	18	[116]	CALL     	3 2 2
	19	[116]	EQ       	1 3 -3	; - "string"
	20	[116]	JMP      	1	; to 22
	21	[116]	LOADBOOL 	3 0 1
	22	[116]	LOADBOOL 	3 1 0
	23	[116]	CALL     	2 2 1
	24	[118]	NEWTABLE 	2 0 0
	25	[119]	GETUPVAL 	3 0	; manif
	26	[119]	GETTABLE 	3 3 -6	; "load_rock_manifest"
	27	[119]	MOVE     	4 0
	28	[119]	MOVE     	5 1
	29	[119]	CALL     	3 3 2
	30	[120]	TEST     	3 0 1
	31	[120]	JMP      	1	; to 33
	32	[120]	RETURN   	2 2
	33	[121]	GETUPVAL 	4 1	; store_package_data
	34	[121]	MOVE     	5 2
	35	[121]	MOVE     	6 3
	36	[121]	LOADK    	7 -7	; "lib"
	37	[121]	CALL     	4 4 1
	38	[122]	GETUPVAL 	4 1	; store_package_data
	39	[122]	MOVE     	5 2
	40	[122]	MOVE     	6 3
	41	[122]	LOADK    	7 -8	; "lua"
	42	[122]	CALL     	4 4 1
	43	[123]	RETURN   	2 2
	44	[124]	RETURN   	0 1

function <./repos.lua:135,144> (39 instructions, 156 bytes at 0x7ff7bdc09350)
2 params, 8 slots, 2 upvalues, 4 locals, 7 constants, 0 functions
	1	[136]	GETGLOBAL	2 -1	; assert
	2	[136]	GETGLOBAL	3 -2	; type
	3	[136]	MOVE     	4 0
	4	[136]	CALL     	3 2 2
	5	[136]	EQ       	0 3 -3	; - "string"
	6	[136]	JMP      	5	; to 12
	7	[136]	SELF     	3 0 -4	; "match"
	8	[136]	LOADK    	5 -5	; "/"
	9	[136]	CALL     	3 3 2
	10	[136]	NOT      	3 3
	11	[136]	JMP      	2	; to 14
	12	[136]	LOADBOOL 	3 0 1
	13	[136]	LOADBOOL 	3 1 0
	14	[136]	CALL     	2 2 1
	15	[137]	GETGLOBAL	2 -1	; assert
	16	[137]	GETGLOBAL	3 -2	; type
	17	[137]	MOVE     	4 1
	18	[137]	CALL     	3 2 2
	19	[137]	EQ       	1 3 -3	; - "string"
	20	[137]	JMP      	1	; to 22
	21	[137]	LOADBOOL 	3 0 1
	22	[137]	LOADBOOL 	3 1 0
	23	[137]	CALL     	2 2 1
	24	[139]	NEWTABLE 	2 0 0
	25	[140]	GETUPVAL 	3 0	; manif
	26	[140]	GETTABLE 	3 3 -6	; "load_rock_manifest"
	27	[140]	MOVE     	4 0
	28	[140]	MOVE     	5 1
	29	[140]	CALL     	3 3 2
	30	[141]	TEST     	3 0 1
	31	[141]	JMP      	1	; to 33
	32	[141]	RETURN   	2 2
	33	[142]	GETUPVAL 	4 1	; store_package_data
	34	[142]	MOVE     	5 2
	35	[142]	MOVE     	6 3
	36	[142]	LOADK    	7 -7	; "bin"
	37	[142]	CALL     	4 4 1
	38	[143]	RETURN   	2 2
	39	[144]	RETURN   	0 1

function <./repos.lua:152,166> (55 instructions, 220 bytes at 0x7ff7bdc096b0)
2 params, 12 slots, 4 upvalues, 8 locals, 11 constants, 0 functions
	1	[153]	GETGLOBAL	2 -1	; assert
	2	[153]	GETGLOBAL	3 -2	; type
	3	[153]	MOVE     	4 0
	4	[153]	CALL     	3 2 2
	5	[153]	EQ       	0 3 -3	; - "string"
	6	[153]	JMP      	5	; to 12
	7	[153]	SELF     	3 0 -4	; "match"
	8	[153]	LOADK    	5 -5	; "/"
	9	[153]	CALL     	3 3 2
	10	[153]	NOT      	3 3
	11	[153]	JMP      	2	; to 14
	12	[153]	LOADBOOL 	3 0 1
	13	[153]	LOADBOOL 	3 1 0
	14	[153]	CALL     	2 2 1
	15	[154]	GETGLOBAL	2 -1	; assert
	16	[154]	GETGLOBAL	3 -2	; type
	17	[154]	MOVE     	4 1
	18	[154]	CALL     	3 2 2
	19	[154]	EQ       	1 3 -3	; - "string"
	20	[154]	JMP      	1	; to 22
	21	[154]	LOADBOOL 	3 0 1
	22	[154]	LOADBOOL 	3 1 0
	23	[154]	CALL     	2 2 1
	24	[156]	GETUPVAL 	2 0	; manif
	25	[156]	GETTABLE 	2 2 -6	; "load_rock_manifest"
	26	[156]	MOVE     	3 0
	27	[156]	MOVE     	4 1
	28	[156]	CALL     	2 3 2
	29	[157]	TEST     	2 0 0
	30	[157]	JMP      	22	; to 53
	31	[157]	GETTABLE 	3 2 -7	; "bin"
	32	[157]	TEST     	3 0 0
	33	[157]	JMP      	19	; to 53
	34	[158]	GETGLOBAL	3 -8	; pairs
	35	[158]	GETTABLE 	4 2 -7	; "bin"
	36	[158]	CALL     	3 2 4
	37	[158]	JMP      	13	; to 51
	38	[160]	GETUPVAL 	8 1	; fs
	39	[160]	GETTABLE 	8 8 -9	; "is_actual_binary"
	40	[160]	GETUPVAL 	9 2	; dir
	41	[160]	GETTABLE 	9 9 -10	; "path"
	42	[160]	GETUPVAL 	10 3	; cfg
	43	[160]	GETTABLE 	10 10 -11	; "deploy_bin_dir"
	44	[160]	MOVE     	11 6
	45	[160]	CALL     	9 3 0
	46	[160]	CALL     	8 0 2
	47	[160]	TEST     	8 0 0
	48	[160]	JMP      	2	; to 51
	49	[161]	LOADBOOL 	8 1 0
	50	[161]	RETURN   	8 2
	51	[158]	TFORLOOP 	3 2
	52	[162]	JMP      	-15	; to 38
	53	[165]	LOADBOOL 	3 0 0
	54	[165]	RETURN   	3 2
	55	[166]	RETURN   	0 1

function <./repos.lua:168,193> (60 instructions, 240 bytes at 0x7ff7bdc09930)
2 params, 8 slots, 3 upvalues, 4 locals, 16 constants, 0 functions
	1	[169]	GETGLOBAL	2 -1	; assert
	2	[169]	SELF     	3 0 -2	; "type"
	3	[169]	CALL     	3 2 2
	4	[169]	EQ       	1 3 -3	; - "rockspec"
	5	[169]	JMP      	1	; to 7
	6	[169]	LOADBOOL 	3 0 1
	7	[169]	LOADBOOL 	3 1 0
	8	[169]	CALL     	2 2 1
	9	[170]	GETGLOBAL	2 -1	; assert
	10	[170]	GETGLOBAL	3 -2	; type
	11	[170]	MOVE     	4 1
	12	[170]	CALL     	3 2 2
	13	[170]	EQ       	1 3 -4	; - "string"
	14	[170]	JMP      	1	; to 16
	15	[170]	LOADBOOL 	3 0 1
	16	[170]	LOADBOOL 	3 1 0
	17	[170]	CALL     	2 2 1
	18	[172]	GETTABLE 	2 0 -5	; "hooks"
	19	[173]	TEST     	2 0 1
	20	[173]	JMP      	2	; to 23
	21	[174]	LOADBOOL 	3 1 0
	22	[174]	RETURN   	3 2
	23	[177]	GETUPVAL 	3 0	; cfg
	24	[177]	GETTABLE 	3 3 -6	; "hooks_enabled"
	25	[177]	EQ       	0 3 -7	; - false
	26	[177]	JMP      	3	; to 30
	27	[178]	LOADNIL  	3 3
	28	[178]	LOADK    	4 -8	; "This rockspec contains hooks, which are blocked by the 'hooks_enabled' setting in your LuaRocks configuration."
	29	[178]	RETURN   	3 3
	30	[181]	GETTABLE 	3 2 -9	; "substituted_variables"
	31	[181]	TEST     	3 0 1
	32	[181]	JMP      	6	; to 39
	33	[182]	GETUPVAL 	3 1	; util
	34	[182]	GETTABLE 	3 3 -10	; "variable_substitutions"
	35	[182]	MOVE     	4 2
	36	[182]	GETTABLE 	5 0 -11	; "variables"
	37	[182]	CALL     	3 3 1
	38	[183]	SETTABLE 	2 -9 -12	; "substituted_variables" true
	39	[185]	GETTABLE 	3 2 1
	40	[186]	TEST     	3 0 0
	41	[186]	JMP      	16	; to 58
	42	[187]	GETUPVAL 	4 1	; util
	43	[187]	GETTABLE 	4 4 -13	; "printout"
	44	[187]	MOVE     	5 3
	45	[187]	CALL     	4 2 1
	46	[188]	GETUPVAL 	4 2	; fs
	47	[188]	GETTABLE 	4 4 -14	; "execute"
	48	[188]	MOVE     	5 3
	49	[188]	CALL     	4 2 2
	50	[188]	TEST     	4 0 1
	51	[188]	JMP      	6	; to 58
	52	[189]	LOADNIL  	4 4
	53	[189]	LOADK    	5 -15	; "Failed running "
	54	[189]	MOVE     	6 1
	55	[189]	LOADK    	7 -16	; " hook."
	56	[189]	CONCAT   	5 5 7
	57	[189]	RETURN   	4 3
	58	[192]	LOADBOOL 	4 1 0
	59	[192]	RETURN   	4 2
	60	[193]	RETURN   	0 1

function <./repos.lua:195,205> (27 instructions, 108 bytes at 0x7ff7bdc09de0)
1 param, 4 slots, 1 upvalue, 1 local, 7 constants, 0 functions
	1	[196]	GETGLOBAL	1 -1	; assert
	2	[196]	SELF     	2 0 -2	; "type"
	3	[196]	CALL     	2 2 2
	4	[196]	EQ       	1 2 -3	; - "rockspec"
	5	[196]	JMP      	1	; to 7
	6	[196]	LOADBOOL 	2 0 1
	7	[196]	LOADBOOL 	2 1 0
	8	[196]	CALL     	1 2 1
	9	[198]	GETUPVAL 	1 0	; cfg
	10	[198]	GETTABLE 	1 1 -4	; "wrap_bin_scripts"
	11	[198]	EQ       	1 1 -5	; - nil
	12	[198]	JMP      	3	; to 16
	13	[199]	GETUPVAL 	1 0	; cfg
	14	[199]	GETTABLE 	1 1 -4	; "wrap_bin_scripts"
	15	[199]	RETURN   	1 2
	16	[201]	GETTABLE 	1 0 -6	; "deploy"
	17	[201]	TEST     	1 0 0
	18	[201]	JMP      	6	; to 25
	19	[201]	GETTABLE 	1 0 -6	; "deploy"
	20	[201]	GETTABLE 	1 1 -4	; "wrap_bin_scripts"
	21	[201]	EQ       	0 1 -7	; - false
	22	[201]	JMP      	2	; to 25
	23	[202]	LOADBOOL 	1 0 0
	24	[202]	RETURN   	1 2
	25	[204]	LOADBOOL 	1 1 0
	26	[204]	RETURN   	1 2
	27	[205]	RETURN   	0 1

function <./repos.lua:207,220> (38 instructions, 152 bytes at 0x7ff7bdc06e20)
2 params, 10 slots, 1 upvalue, 8 locals, 9 constants, 0 functions
	1	[208]	NEWTABLE 	2 1 0
	2	[208]	MOVE     	3 0
	3	[208]	SETLIST  	2 1 1	; 1
	4	[209]	TEST     	1 0 0
	5	[209]	JMP      	10	; to 16
	6	[209]	EQ       	1 1 -1	; - ""
	7	[209]	JMP      	8	; to 16
	8	[210]	GETGLOBAL	3 -2	; table
	9	[210]	GETTABLE 	3 3 -3	; "insert"
	10	[210]	MOVE     	4 2
	11	[210]	LOADK    	5 -4	; 1
	12	[210]	MOVE     	6 0
	13	[210]	MOVE     	7 1
	14	[210]	CONCAT   	6 6 7
	15	[210]	CALL     	3 4 1
	16	[213]	GETGLOBAL	3 -5	; ipairs
	17	[213]	MOVE     	4 2
	18	[213]	CALL     	3 2 4
	19	[213]	JMP      	7	; to 27
	20	[214]	GETUPVAL 	8 0	; fs
	21	[214]	GETTABLE 	8 8 -6	; "exists"
	22	[214]	MOVE     	9 7
	23	[214]	CALL     	8 2 2
	24	[214]	TEST     	8 0 0
	25	[214]	JMP      	1	; to 27
	26	[215]	RETURN   	7 2
	27	[213]	TFORLOOP 	3 2
	28	[216]	JMP      	-9	; to 20
	29	[219]	LOADNIL  	3 3
	30	[219]	GETGLOBAL	4 -2	; table
	31	[219]	GETTABLE 	4 4 -7	; "concat"
	32	[219]	MOVE     	5 2
	33	[219]	LOADK    	6 -8	; ", "
	34	[219]	CALL     	4 3 2
	35	[219]	LOADK    	5 -9	; " not found"
	36	[219]	CONCAT   	4 4 5
	37	[219]	RETURN   	3 3
	38	[220]	RETURN   	0 1

function <./repos.lua:222,228> (14 instructions, 56 bytes at 0x7ff7bdc08350)
2 params, 7 slots, 1 upvalue, 4 locals, 3 constants, 0 functions
	1	[223]	GETUPVAL 	2 0	; find_suffixed
	2	[223]	MOVE     	3 0
	3	[223]	MOVE     	4 1
	4	[223]	CALL     	2 3 3
	5	[224]	TEST     	2 0 1
	6	[224]	JMP      	2	; to 9
	7	[225]	LOADK    	4 -1	; ""
	8	[225]	RETURN   	4 2
	9	[227]	SELF     	4 2 -2	; "sub"
	10	[227]	LEN      	6 0
	11	[227]	ADD      	6 6 -3	; - 1
	12	[227]	TAILCALL 	4 3 0
	13	[227]	RETURN   	4 0
	14	[228]	RETURN   	0 1

function <./repos.lua:236,247> (65 instructions, 260 bytes at 0x7ff7bdc07780)
5 params, 12 slots, 3 upvalues, 8 locals, 10 constants, 0 functions
	1	[237]	GETGLOBAL	5 -1	; assert
	2	[237]	GETGLOBAL	6 -2	; type
	3	[237]	MOVE     	7 0
	4	[237]	CALL     	6 2 2
	5	[237]	EQ       	1 6 -3	; - "string"
	6	[237]	JMP      	1	; to 8
	7	[237]	LOADBOOL 	6 0 1
	8	[237]	LOADBOOL 	6 1 0
	9	[237]	CALL     	5 2 1
	10	[238]	GETGLOBAL	5 -1	; assert
	11	[238]	GETGLOBAL	6 -2	; type
	12	[238]	MOVE     	7 1
	13	[238]	CALL     	6 2 2
	14	[238]	EQ       	1 6 -3	; - "string"
	15	[238]	JMP      	1	; to 17
	16	[238]	LOADBOOL 	6 0 1
	17	[238]	LOADBOOL 	6 1 0
	18	[238]	CALL     	5 2 1
	19	[239]	GETGLOBAL	5 -1	; assert
	20	[239]	GETGLOBAL	6 -2	; type
	21	[239]	MOVE     	7 2
	22	[239]	CALL     	6 2 2
	23	[239]	EQ       	1 6 -3	; - "string"
	24	[239]	JMP      	1	; to 26
	25	[239]	LOADBOOL 	6 0 1
	26	[239]	LOADBOOL 	6 1 0
	27	[239]	CALL     	5 2 1
	28	[240]	GETGLOBAL	5 -1	; assert
	29	[240]	GETGLOBAL	6 -2	; type
	30	[240]	MOVE     	7 3
	31	[240]	CALL     	6 2 2
	32	[240]	EQ       	1 6 -3	; - "string"
	33	[240]	JMP      	1	; to 35
	34	[240]	LOADBOOL 	6 0 1
	35	[240]	LOADBOOL 	6 1 0
	36	[240]	CALL     	5 2 1
	37	[242]	TEST     	4 0 1
	38	[242]	JMP      	2	; to 41
	39	[242]	GETUPVAL 	5 0	; cfg
	40	[242]	GETTABLE 	4 5 -4	; "root_dir"
	41	[243]	GETUPVAL 	5 1	; path
	42	[243]	LOADK    	6 -5	; "deploy_"
	43	[243]	MOVE     	7 2
	44	[243]	LOADK    	8 -6	; "_dir"
	45	[243]	CONCAT   	6 6 8
	46	[243]	GETTABLE 	5 5 6
	47	[243]	MOVE     	6 4
	48	[243]	CALL     	5 2 2
	49	[244]	GETUPVAL 	6 2	; dir
	50	[244]	GETTABLE 	6 6 -7	; "path"
	51	[244]	MOVE     	7 5
	52	[244]	MOVE     	8 3
	53	[244]	CALL     	6 3 2
	54	[245]	GETUPVAL 	7 1	; path
	55	[245]	GETTABLE 	7 7 -8	; "versioned_name"
	56	[245]	MOVE     	8 6
	57	[245]	MOVE     	9 5
	58	[245]	MOVE     	10 0
	59	[245]	MOVE     	11 1
	60	[245]	CALL     	7 5 2
	61	[246]	NEWTABLE 	8 0 2
	62	[246]	SETTABLE 	8 -9 6	; "nv" -
	63	[246]	SETTABLE 	8 -10 7	; "v" -
	64	[246]	RETURN   	8 2
	65	[247]	RETURN   	0 1

function <./repos.lua:249,261> (36 instructions, 144 bytes at 0x7ff7bdc091c0)
4 params, 12 slots, 3 upvalues, 8 locals, 4 constants, 0 functions
	1	[250]	GETUPVAL 	4 0	; get_provided_item
	2	[250]	MOVE     	5 2
	3	[250]	MOVE     	6 3
	4	[250]	CALL     	4 3 3
	5	[251]	GETUPVAL 	6 1	; manif
	6	[251]	GETTABLE 	6 6 -1	; "get_current_provider"
	7	[251]	MOVE     	7 4
	8	[251]	MOVE     	8 5
	9	[251]	CALL     	6 3 3
	10	[253]	TEST     	6 0 0
	11	[253]	JMP      	13	; to 25
	12	[253]	LT       	1 0 6
	13	[253]	JMP      	11	; to 25
	14	[254]	EQ       	0 0 6
	15	[254]	JMP      	15	; to 31
	16	[254]	EQ       	1 1 7
	17	[254]	JMP      	7	; to 25
	18	[255]	GETUPVAL 	8 2	; vers
	19	[255]	GETTABLE 	8 8 -2	; "compare_versions"
	20	[255]	MOVE     	9 1
	21	[255]	MOVE     	10 7
	22	[255]	CALL     	8 3 2
	23	[255]	TEST     	8 0 0
	24	[255]	JMP      	6	; to 31
	25	[256]	LOADK    	8 -3	; "nv"
	26	[256]	MOVE     	9 6
	27	[256]	MOVE     	10 7
	28	[256]	MOVE     	11 5
	29	[256]	RETURN   	8 5
	30	[256]	JMP      	5	; to 36
	31	[259]	LOADK    	8 -4	; "v"
	32	[259]	MOVE     	9 6
	33	[259]	MOVE     	10 7
	34	[259]	MOVE     	11 5
	35	[259]	RETURN   	8 5
	36	[261]	RETURN   	0 1

function <./repos.lua:263,281> (42 instructions, 168 bytes at 0x7ff7bdc06d10)
2 params, 7 slots, 2 upvalues, 5 locals, 7 constants, 0 functions
	1	[264]	TEST     	0 0 1
	2	[264]	JMP      	5	; to 8
	3	[265]	GETUPVAL 	2 0	; fs
	4	[265]	GETTABLE 	2 2 -1	; "delete"
	5	[265]	MOVE     	3 1
	6	[265]	CALL     	2 2 1
	7	[266]	RETURN   	0 1
	8	[268]	GETUPVAL 	2 0	; fs
	9	[268]	GETTABLE 	2 2 -2	; "exists"
	10	[268]	MOVE     	3 1
	11	[268]	CALL     	2 2 2
	12	[268]	TEST     	2 0 0
	13	[268]	JMP      	28	; to 42
	14	[269]	MOVE     	2 1
	15	[271]	MOVE     	3 2
	16	[271]	LOADK    	4 -3	; "~"
	17	[271]	CONCAT   	2 3 4
	18	[272]	GETUPVAL 	3 0	; fs
	19	[272]	GETTABLE 	3 3 -2	; "exists"
	20	[272]	MOVE     	4 2
	21	[272]	CALL     	3 2 2
	22	[272]	TEST     	3 0 1
	23	[272]	JMP      	-9	; to 15
	24	[274]	GETUPVAL 	3 1	; util
	25	[274]	GETTABLE 	3 3 -4	; "warning"
	26	[274]	MOVE     	4 1
	27	[274]	LOADK    	5 -5	; " is not tracked by this installation of LuaRocks. Moving it to "
	28	[274]	MOVE     	6 2
	29	[274]	CONCAT   	4 4 6
	30	[274]	CALL     	3 2 1
	31	[275]	GETGLOBAL	3 -6	; os
	32	[275]	GETTABLE 	3 3 -7	; "rename"
	33	[275]	MOVE     	4 1
	34	[275]	MOVE     	5 2
	35	[275]	CALL     	3 3 3
	36	[276]	TEST     	3 0 1
	37	[276]	JMP      	3	; to 41
	38	[277]	LOADNIL  	5 5
	39	[277]	MOVE     	6 4
	40	[277]	RETURN   	5 3
	41	[279]	RETURN   	2 2
	42	[281]	RETURN   	0 1

function <./repos.lua:283,329> (17 instructions, 68 bytes at 0x7ff7bdc0bd40)
0 params, 7 slots, 3 upvalues, 5 locals, 0 constants, 3 functions
	1	[284]	NEWTABLE 	0 0 0
	2	[285]	NEWTABLE 	1 0 0
	3	[297]	CLOSURE  	2 0	; 0x7ff7bdc0c380
	4	[297]	MOVE     	0 0
	5	[297]	GETUPVAL 	0 0	; fs
	6	[320]	CLOSURE  	3 1	; 0x7ff7bdc0c490
	7	[320]	MOVE     	0 2
	8	[320]	GETUPVAL 	0 1	; dir
	9	[320]	GETUPVAL 	0 2	; backup_existing
	10	[320]	MOVE     	0 1
	11	[326]	CLOSURE  	4 2	; 0x7ff7bdc0cb20
	12	[326]	MOVE     	0 1
	13	[326]	GETUPVAL 	0 0	; fs
	14	[328]	MOVE     	5 3
	15	[328]	MOVE     	6 4
	16	[328]	RETURN   	5 3
	17	[329]	RETURN   	0 1

function <./repos.lua:287,297> (20 instructions, 80 bytes at 0x7ff7bdc0c380)
1 param, 5 slots, 2 upvalues, 3 locals, 2 constants, 0 functions
	1	[288]	GETUPVAL 	1 0	; mkdirs
	2	[288]	GETTABLE 	1 1 0
	3	[288]	TEST     	1 0 0
	4	[288]	JMP      	2	; to 7
	5	[289]	LOADBOOL 	1 1 0
	6	[289]	RETURN   	1 2
	7	[291]	GETUPVAL 	1 1	; fs
	8	[291]	GETTABLE 	1 1 -1	; "make_dir"
	9	[291]	MOVE     	2 0
	10	[291]	CALL     	1 2 3
	11	[292]	TEST     	1 0 1
	12	[292]	JMP      	3	; to 16
	13	[293]	LOADNIL  	3 3
	14	[293]	MOVE     	4 2
	15	[293]	RETURN   	3 3
	16	[295]	GETUPVAL 	3 0	; mkdirs
	17	[295]	SETTABLE 	3 0 -2	; - true
	18	[296]	LOADBOOL 	3 1 0
	19	[296]	RETURN   	3 2
	20	[297]	RETURN   	0 1

function <./repos.lua:299,320> (47 instructions, 188 bytes at 0x7ff7bdc0c490)
1 param, 9 slots, 4 upvalues, 5 locals, 8 constants, 0 functions
	1	[300]	GETUPVAL 	1 0	; memoize_mkdir
	2	[300]	GETUPVAL 	2 1	; dir
	3	[300]	GETTABLE 	2 2 -1	; "dir_name"
	4	[300]	GETTABLE 	3 0 -2	; "dst"
	5	[300]	CALL     	2 2 0
	6	[300]	CALL     	1 0 3
	7	[301]	TEST     	1 0 1
	8	[301]	JMP      	3	; to 12
	9	[302]	LOADNIL  	3 3
	10	[302]	MOVE     	4 2
	11	[302]	RETURN   	3 3
	12	[305]	GETUPVAL 	3 2	; backup_existing
	13	[305]	GETTABLE 	4 0 -3	; "backup"
	14	[305]	GETTABLE 	5 0 -4	; "realdst"
	15	[305]	TEST     	5 0 1
	16	[305]	JMP      	1	; to 18
	17	[305]	GETTABLE 	5 0 -2	; "dst"
	18	[305]	CALL     	3 3 3
	19	[306]	TEST     	4 0 0
	20	[306]	JMP      	3	; to 24
	21	[307]	LOADNIL  	5 5
	22	[307]	MOVE     	6 4
	23	[307]	RETURN   	5 3
	24	[309]	TEST     	3 0 0
	25	[309]	JMP      	1	; to 27
	26	[310]	SETTABLE 	0 -5 3	; "backup_file" -
	27	[313]	GETTABLE 	5 0 -6	; "fn"
	28	[313]	GETTABLE 	6 0 -7	; "src"
	29	[313]	GETTABLE 	7 0 -2	; "dst"
	30	[313]	GETTABLE 	8 0 -3	; "backup"
	31	[313]	CALL     	5 4 3
	32	[313]	MOVE     	4 6
	33	[313]	MOVE     	1 5
	34	[314]	TEST     	1 0 1
	35	[314]	JMP      	3	; to 39
	36	[315]	LOADNIL  	5 5
	37	[315]	MOVE     	6 4
	38	[315]	RETURN   	5 3
	39	[318]	GETUPVAL 	5 3	; rmdirs
	40	[318]	GETUPVAL 	6 1	; dir
	41	[318]	GETTABLE 	6 6 -1	; "dir_name"
	42	[318]	GETTABLE 	7 0 -7	; "src"
	43	[318]	CALL     	6 2 2
	44	[318]	SETTABLE 	5 6 -8	; - true
	45	[319]	LOADBOOL 	5 1 0
	46	[319]	RETURN   	5 2
	47	[320]	RETURN   	0 1

function <./repos.lua:322,326> (11 instructions, 44 bytes at 0x7ff7bdc0cb20)
0 params, 7 slots, 2 upvalues, 5 locals, 2 constants, 0 functions
	1	[323]	GETGLOBAL	0 -1	; pairs
	2	[323]	GETUPVAL 	1 0	; rmdirs
	3	[323]	CALL     	0 2 4
	4	[323]	JMP      	4	; to 9
	5	[324]	GETUPVAL 	5 1	; fs
	6	[324]	GETTABLE 	5 5 -2	; "remove_dir_tree_if_empty"
	7	[324]	MOVE     	6 3
	8	[324]	CALL     	5 2 1
	9	[323]	TFORLOOP 	0 2
	10	[324]	JMP      	-6	; to 5
	11	[326]	RETURN   	0 1

function <./repos.lua:331,338> (22 instructions, 88 bytes at 0x7ff7bdc0d420)
1 param, 4 slots, 2 upvalues, 1 local, 7 constants, 0 functions
	1	[332]	GETUPVAL 	1 0	; fs
	2	[332]	GETTABLE 	1 1 -1	; "delete"
	3	[332]	GETTABLE 	2 0 -2	; "dst"
	4	[332]	CALL     	1 2 1
	5	[333]	GETTABLE 	1 0 -3	; "backup_file"
	6	[333]	TEST     	1 0 0
	7	[333]	JMP      	5	; to 13
	8	[334]	GETGLOBAL	1 -4	; os
	9	[334]	GETTABLE 	1 1 -5	; "rename"
	10	[334]	GETTABLE 	2 0 -3	; "backup_file"
	11	[334]	GETTABLE 	3 0 -2	; "dst"
	12	[334]	CALL     	1 3 1
	13	[336]	GETUPVAL 	1 0	; fs
	14	[336]	GETTABLE 	1 1 -6	; "remove_dir_tree_if_empty"
	15	[336]	GETUPVAL 	2 1	; dir
	16	[336]	GETTABLE 	2 2 -7	; "dir_name"
	17	[336]	GETTABLE 	3 0 -2	; "dst"
	18	[336]	CALL     	2 2 0
	19	[336]	CALL     	1 0 1
	20	[337]	LOADBOOL 	1 1 0
	21	[337]	RETURN   	1 2
	22	[338]	RETURN   	0 1

function <./repos.lua:340,356> (51 instructions, 204 bytes at 0x7ff7bdc0a1d0)
1 param, 6 slots, 3 upvalues, 4 locals, 10 constants, 0 functions
	1	[341]	GETTABLE 	1 0 -1	; "suffix"
	2	[341]	TEST     	1 0 0
	3	[341]	JMP      	12	; to 16
	4	[342]	GETUPVAL 	1 0	; check_suffix
	5	[342]	GETTABLE 	2 0 -2	; "src"
	6	[342]	GETTABLE 	3 0 -1	; "suffix"
	7	[342]	CALL     	1 3 2
	8	[343]	GETTABLE 	2 0 -2	; "src"
	9	[343]	MOVE     	3 1
	10	[343]	CONCAT   	2 2 3
	11	[343]	SETTABLE 	0 -2 2	; "src" -
	12	[344]	GETTABLE 	2 0 -3	; "dst"
	13	[344]	MOVE     	3 1
	14	[344]	CONCAT   	2 2 3
	15	[344]	SETTABLE 	0 -3 2	; "dst" -
	16	[347]	GETUPVAL 	1 1	; fs
	17	[347]	GETTABLE 	1 1 -4	; "exists"
	18	[347]	GETTABLE 	2 0 -2	; "src"
	19	[347]	CALL     	1 2 2
	20	[347]	TEST     	1 0 0
	21	[347]	JMP      	27	; to 49
	22	[348]	GETUPVAL 	1 1	; fs
	23	[348]	GETTABLE 	1 1 -5	; "make_dir"
	24	[348]	GETUPVAL 	2 2	; dir
	25	[348]	GETTABLE 	2 2 -6	; "dir_name"
	26	[348]	GETTABLE 	3 0 -3	; "dst"
	27	[348]	CALL     	2 2 0
	28	[348]	CALL     	1 0 1
	29	[349]	GETUPVAL 	1 1	; fs
	30	[349]	GETTABLE 	1 1 -7	; "delete"
	31	[349]	GETTABLE 	2 0 -3	; "dst"
	32	[349]	CALL     	1 2 1
	33	[350]	GETGLOBAL	1 -8	; os
	34	[350]	GETTABLE 	1 1 -9	; "rename"
	35	[350]	GETTABLE 	2 0 -2	; "src"
	36	[350]	GETTABLE 	3 0 -3	; "dst"
	37	[350]	CALL     	1 3 3
	38	[351]	GETUPVAL 	3 1	; fs
	39	[351]	GETTABLE 	3 3 -10	; "remove_dir_tree_if_empty"
	40	[351]	GETUPVAL 	4 2	; dir
	41	[351]	GETTABLE 	4 4 -6	; "dir_name"
	42	[351]	GETTABLE 	5 0 -2	; "src"
	43	[351]	CALL     	4 2 0
	44	[351]	CALL     	3 0 1
	45	[352]	MOVE     	3 1
	46	[352]	MOVE     	4 2
	47	[352]	RETURN   	3 3
	48	[352]	JMP      	2	; to 51
	49	[354]	LOADBOOL 	1 1 0
	50	[354]	RETURN   	1 2
	51	[356]	RETURN   	0 1

function <./repos.lua:358,360> (9 instructions, 36 bytes at 0x7ff7bdc0dc30)
1 param, 4 slots, 1 upvalue, 1 local, 2 constants, 0 functions
	1	[359]	GETUPVAL 	1 0	; op_rename
	2	[359]	NEWTABLE 	2 0 2
	3	[359]	GETTABLE 	3 0 -2	; "dst"
	4	[359]	SETTABLE 	2 -1 3	; "src" -
	5	[359]	GETTABLE 	3 0 -1	; "src"
	6	[359]	SETTABLE 	2 -2 3	; "dst" -
	7	[359]	TAILCALL 	1 2 0
	8	[359]	RETURN   	1 0
	9	[360]	RETURN   	0 1

function <./repos.lua:362,388> (15 instructions, 60 bytes at 0x7ff7bdc0db50)
0 params, 6 slots, 3 upvalues, 4 locals, 0 constants, 2 functions
	1	[363]	NEWTABLE 	0 0 0
	2	[364]	NEWTABLE 	1 0 0
	3	[374]	CLOSURE  	2 0	; 0x7ff7bdc0e450
	4	[374]	MOVE     	0 0
	5	[374]	MOVE     	0 1
	6	[374]	GETUPVAL 	0 0	; fs
	7	[385]	CLOSURE  	3 1	; 0x7ff7bdc0e790
	8	[385]	GETUPVAL 	0 1	; check_suffix
	9	[385]	MOVE     	0 0
	10	[385]	MOVE     	0 1
	11	[385]	GETUPVAL 	0 2	; dir
	12	[387]	MOVE     	4 3
	13	[387]	MOVE     	5 2
	14	[387]	RETURN   	4 3
	15	[388]	RETURN   	0 1

function <./repos.lua:366,374> (21 instructions, 84 bytes at 0x7ff7bdc0e450)
0 params, 7 slots, 3 upvalues, 10 locals, 5 constants, 0 functions
	1	[367]	GETGLOBAL	0 -1	; ipairs
	2	[367]	GETUPVAL 	1 0	; deletes
	3	[367]	CALL     	0 2 4
	4	[367]	JMP      	4	; to 9
	5	[368]	GETGLOBAL	5 -2	; os
	6	[368]	GETTABLE 	5 5 -3	; "remove"
	7	[368]	MOVE     	6 4
	8	[368]	CALL     	5 2 1
	9	[367]	TFORLOOP 	0 2
	10	[368]	JMP      	-6	; to 5
	11	[371]	GETGLOBAL	0 -4	; pairs
	12	[371]	GETUPVAL 	1 1	; rmdirs
	13	[371]	CALL     	0 2 4
	14	[371]	JMP      	4	; to 19
	15	[372]	GETUPVAL 	5 2	; fs
	16	[372]	GETTABLE 	5 5 -5	; "remove_dir_tree_if_empty"
	17	[372]	MOVE     	6 3
	18	[372]	CALL     	5 2 1
	19	[371]	TFORLOOP 	0 2
	20	[372]	JMP      	-6	; to 15
	21	[374]	RETURN   	0 1

function <./repos.lua:376,385> (23 instructions, 92 bytes at 0x7ff7bdc0e790)
1 param, 4 slots, 4 upvalues, 2 locals, 6 constants, 0 functions
	1	[377]	GETTABLE 	1 0 -1	; "suffix"
	2	[377]	TEST     	1 0 0
	3	[377]	JMP      	8	; to 12
	4	[378]	GETUPVAL 	1 0	; check_suffix
	5	[378]	GETTABLE 	2 0 -2	; "name"
	6	[378]	GETTABLE 	3 0 -1	; "suffix"
	7	[378]	CALL     	1 3 2
	8	[379]	GETTABLE 	2 0 -2	; "name"
	9	[379]	MOVE     	3 1
	10	[379]	CONCAT   	2 2 3
	11	[379]	SETTABLE 	0 -2 2	; "name" -
	12	[382]	GETGLOBAL	1 -3	; table
	13	[382]	GETTABLE 	1 1 -4	; "insert"
	14	[382]	GETUPVAL 	2 1	; deletes
	15	[382]	GETTABLE 	3 0 -2	; "name"
	16	[382]	CALL     	1 3 1
	17	[384]	GETUPVAL 	1 2	; rmdirs
	18	[384]	GETUPVAL 	2 3	; dir
	19	[384]	GETTABLE 	2 2 -5	; "dir_name"
	20	[384]	GETTABLE 	3 0 -2	; "name"
	21	[384]	CALL     	2 2 2
	22	[384]	SETTABLE 	1 2 -6	; - true
	23	[385]	RETURN   	0 1

function <./repos.lua:390,394> (9 instructions, 36 bytes at 0x7ff7bdc0eaa0)
3 params, 9 slots, 0 upvalues, 7 locals, 1 constant, 0 functions
	1	[391]	LOADK    	3 -1	; 1
	2	[391]	MOVE     	4 2
	3	[391]	LOADK    	5 -1	; 1
	4	[391]	FORPREP  	3 3	; to 8
	5	[392]	MOVE     	7 1
	6	[392]	GETTABLE 	8 0 6
	7	[392]	CALL     	7 2 1
	8	[391]	FORLOOP  	3 -4	; to 5
	9	[394]	RETURN   	0 1

function <./repos.lua:403,509> (190 instructions, 760 bytes at 0x7ff7bdc0ed90)
4 params, 25 slots, 13 upvalues, 32 locals, 20 constants, 6 functions
	1	[404]	GETGLOBAL	4 -1	; assert
	2	[404]	GETGLOBAL	5 -2	; type
	3	[404]	MOVE     	6 0
	4	[404]	CALL     	5 2 2
	5	[404]	EQ       	0 5 -3	; - "string"
	6	[404]	JMP      	5	; to 12
	7	[404]	SELF     	5 0 -4	; "match"
	8	[404]	LOADK    	7 -5	; "/"
	9	[404]	CALL     	5 3 2
	10	[404]	NOT      	5 5
	11	[404]	JMP      	2	; to 14
	12	[404]	LOADBOOL 	5 0 1
	13	[404]	LOADBOOL 	5 1 0
	14	[404]	CALL     	4 2 1
	15	[405]	GETGLOBAL	4 -1	; assert
	16	[405]	GETGLOBAL	5 -2	; type
	17	[405]	MOVE     	6 1
	18	[405]	CALL     	5 2 2
	19	[405]	EQ       	1 5 -3	; - "string"
	20	[405]	JMP      	1	; to 22
	21	[405]	LOADBOOL 	5 0 1
	22	[405]	LOADBOOL 	5 1 0
	23	[405]	CALL     	4 2 1
	24	[406]	GETGLOBAL	4 -1	; assert
	25	[406]	GETGLOBAL	5 -2	; type
	26	[406]	MOVE     	6 2
	27	[406]	CALL     	5 2 2
	28	[406]	EQ       	1 5 -6	; - "boolean"
	29	[406]	JMP      	1	; to 31
	30	[406]	LOADBOOL 	5 0 1
	31	[406]	LOADBOOL 	5 1 0
	32	[406]	CALL     	4 2 1
	33	[408]	GETUPVAL 	4 0	; manif
	34	[408]	GETTABLE 	4 4 -7	; "load_rock_manifest"
	35	[408]	MOVE     	5 0
	36	[408]	MOVE     	6 1
	37	[408]	CALL     	4 3 3
	38	[409]	TEST     	4 0 1
	39	[409]	JMP      	3	; to 43
	40	[409]	LOADNIL  	6 6
	41	[409]	MOVE     	7 5
	42	[409]	RETURN   	6 3
	43	[411]	GETUPVAL 	6 1	; cfg
	44	[411]	GETTABLE 	6 6 -8	; "root_dir"
	45	[412]	NEWTABLE 	7 0 0
	46	[413]	NEWTABLE 	8 0 0
	47	[421]	CLOSURE  	9 0	; 0x7ff7bdc0ee80
	48	[421]	MOVE     	0 2
	49	[421]	GETUPVAL 	0 2	; fs
	50	[421]	MOVE     	0 3
	51	[421]	MOVE     	0 0
	52	[421]	MOVE     	0 1
	53	[425]	CLOSURE  	10 1	; 0x7ff7bdc0c2c0
	54	[425]	GETUPVAL 	0 2	; fs
	55	[429]	CLOSURE  	11 2	; 0x7ff7bdc0e070
	56	[429]	GETUPVAL 	0 2	; fs
	57	[431]	GETTABLE 	12 4 -9	; "bin"
	58	[431]	TEST     	12 0 0
	59	[431]	JMP      	24	; to 84
	60	[432]	GETUPVAL 	12 3	; path
	61	[432]	GETTABLE 	12 12 -10	; "bin_dir"
	62	[432]	MOVE     	13 0
	63	[432]	MOVE     	14 1
	64	[432]	CALL     	12 3 2
	65	[433]	GETUPVAL 	13 4	; repos
	66	[433]	GETTABLE 	13 13 -11	; "recurse_rock_manifest_entry"
	67	[433]	GETTABLE 	14 4 -9	; "bin"
	68	[448]	CLOSURE  	15 3	; 0x7ff7bdc0d3a0
	69	[448]	GETUPVAL 	0 5	; dir
	70	[448]	MOVE     	0 12
	71	[448]	GETUPVAL 	0 6	; get_deploy_paths
	72	[448]	MOVE     	0 0
	73	[448]	MOVE     	0 1
	74	[448]	MOVE     	0 6
	75	[448]	GETUPVAL 	0 7	; check_spot_if_available
	76	[448]	MOVE     	0 7
	77	[448]	GETUPVAL 	0 1	; cfg
	78	[448]	MOVE     	0 2
	79	[448]	GETUPVAL 	0 2	; fs
	80	[448]	MOVE     	0 8
	81	[448]	MOVE     	0 9
	82	[433]	CALL     	13 3 1
	83	[448]	CLOSE    	12
	84	[451]	GETTABLE 	12 4 -12	; "lua"
	85	[451]	TEST     	12 0 0
	86	[451]	JMP      	22	; to 109
	87	[452]	GETUPVAL 	12 3	; path
	88	[452]	GETTABLE 	12 12 -13	; "lua_dir"
	89	[452]	MOVE     	13 0
	90	[452]	MOVE     	14 1
	91	[452]	CALL     	12 3 2
	92	[453]	GETUPVAL 	13 4	; repos
	93	[453]	GETTABLE 	13 13 -11	; "recurse_rock_manifest_entry"
	94	[453]	GETTABLE 	14 4 -12	; "lua"
	95	[467]	CLOSURE  	15 4	; 0x7ff7bdc0d950
	96	[467]	GETUPVAL 	0 5	; dir
	97	[467]	MOVE     	0 12
	98	[467]	GETUPVAL 	0 6	; get_deploy_paths
	99	[467]	MOVE     	0 0
	100	[467]	MOVE     	0 1
	101	[467]	MOVE     	0 6
	102	[467]	GETUPVAL 	0 7	; check_spot_if_available
	103	[467]	MOVE     	0 7
	104	[467]	GETUPVAL 	0 1	; cfg
	105	[467]	MOVE     	0 8
	106	[467]	MOVE     	0 10
	107	[453]	CALL     	13 3 1
	108	[467]	CLOSE    	12
	109	[470]	GETTABLE 	12 4 -14	; "lib"
	110	[470]	TEST     	12 0 0
	111	[470]	JMP      	21	; to 133
	112	[471]	GETUPVAL 	12 3	; path
	113	[471]	GETTABLE 	12 12 -15	; "lib_dir"
	114	[471]	MOVE     	13 0
	115	[471]	MOVE     	14 1
	116	[471]	CALL     	12 3 2
	117	[472]	GETUPVAL 	13 4	; repos
	118	[472]	GETTABLE 	13 13 -11	; "recurse_rock_manifest_entry"
	119	[472]	GETTABLE 	14 4 -14	; "lib"
	120	[486]	CLOSURE  	15 5	; 0x7ff7bdc0e0f0
	121	[486]	GETUPVAL 	0 5	; dir
	122	[486]	MOVE     	0 12
	123	[486]	GETUPVAL 	0 6	; get_deploy_paths
	124	[486]	MOVE     	0 0
	125	[486]	MOVE     	0 1
	126	[486]	MOVE     	0 6
	127	[486]	GETUPVAL 	0 7	; check_spot_if_available
	128	[486]	MOVE     	0 7
	129	[486]	MOVE     	0 8
	130	[486]	MOVE     	0 11
	131	[472]	CALL     	13 3 1
	132	[486]	CLOSE    	12
	133	[489]	GETGLOBAL	12 -16	; ipairs
	134	[489]	MOVE     	13 7
	135	[489]	CALL     	12 2 4
	136	[489]	JMP      	13	; to 150
	137	[490]	GETUPVAL 	17 8	; op_rename
	138	[490]	MOVE     	18 16
	139	[490]	CALL     	17 2 3
	140	[491]	TEST     	17 0 1
	141	[491]	JMP      	8	; to 150
	142	[492]	GETUPVAL 	19 9	; rollback_ops
	143	[492]	MOVE     	20 7
	144	[492]	GETUPVAL 	21 10	; rollback_rename
	145	[492]	SUB      	22 15 -17	; - 1
	146	[492]	CALL     	19 4 1
	147	[493]	LOADNIL  	19 19
	148	[493]	MOVE     	20 18
	149	[493]	RETURN   	19 3
	150	[489]	TFORLOOP 	12 2
	151	[494]	JMP      	-15	; to 137
	152	[496]	GETUPVAL 	12 11	; prepare_op_install
	153	[496]	CALL     	12 1 3
	154	[497]	GETGLOBAL	14 -16	; ipairs
	155	[497]	MOVE     	15 8
	156	[497]	CALL     	14 2 4
	157	[497]	JMP      	18	; to 176
	158	[498]	MOVE     	19 12
	159	[498]	MOVE     	20 18
	160	[498]	CALL     	19 2 3
	161	[499]	TEST     	19 0 1
	162	[499]	JMP      	13	; to 176
	163	[500]	GETUPVAL 	21 9	; rollback_ops
	164	[500]	MOVE     	22 8
	165	[500]	GETUPVAL 	23 12	; rollback_install
	166	[500]	SUB      	24 17 -17	; - 1
	167	[500]	CALL     	21 4 1
	168	[501]	GETUPVAL 	21 9	; rollback_ops
	169	[501]	MOVE     	22 7
	170	[501]	GETUPVAL 	23 10	; rollback_rename
	171	[501]	LEN      	24 7
	172	[501]	CALL     	21 4 1
	173	[502]	LOADNIL  	21 21
	174	[502]	MOVE     	22 20
	175	[502]	RETURN   	21 3
	176	[497]	TFORLOOP 	14 2
	177	[503]	JMP      	-20	; to 158
	178	[505]	MOVE     	14 13
	179	[505]	CALL     	14 1 1
	180	[507]	GETGLOBAL	14 -18	; require
	181	[507]	LOADK    	15 -19	; "luarocks.manif.writer"
	182	[507]	CALL     	14 2 2
	183	[508]	GETTABLE 	15 14 -20	; "add_to_manifest"
	184	[508]	MOVE     	16 0
	185	[508]	MOVE     	17 1
	186	[508]	LOADNIL  	18 18
	187	[508]	MOVE     	19 3
	188	[508]	TAILCALL 	15 5 0
	189	[508]	RETURN   	15 0
	190	[509]	RETURN   	0 1

function <./repos.lua:415,421> (26 instructions, 104 bytes at 0x7ff7bdc0ee80)
2 params, 8 slots, 5 upvalues, 2 locals, 3 constants, 0 functions
	1	[416]	GETUPVAL 	2 0	; wrap_bin_scripts
	2	[416]	TEST     	2 0 0
	3	[416]	JMP      	16	; to 20
	4	[416]	GETUPVAL 	2 1	; fs
	5	[416]	GETTABLE 	2 2 -1	; "is_lua"
	6	[416]	MOVE     	3 0
	7	[416]	CALL     	2 2 2
	8	[416]	TEST     	2 0 0
	9	[416]	JMP      	10	; to 20
	10	[417]	GETUPVAL 	2 1	; fs
	11	[417]	GETTABLE 	2 2 -2	; "wrap_script"
	12	[417]	MOVE     	3 0
	13	[417]	MOVE     	4 1
	14	[417]	GETUPVAL 	5 2	; deps_mode
	15	[417]	GETUPVAL 	6 3	; name
	16	[417]	GETUPVAL 	7 4	; version
	17	[417]	TAILCALL 	2 6 0
	18	[417]	RETURN   	2 0
	19	[417]	JMP      	6	; to 26
	20	[419]	GETUPVAL 	2 1	; fs
	21	[419]	GETTABLE 	2 2 -3	; "copy_binary"
	22	[419]	MOVE     	3 0
	23	[419]	MOVE     	4 1
	24	[419]	TAILCALL 	2 3 0
	25	[419]	RETURN   	2 0
	26	[421]	RETURN   	0 1

function <./repos.lua:423,425> (8 instructions, 32 bytes at 0x7ff7bdc0c2c0)
2 params, 6 slots, 1 upvalue, 2 locals, 2 constants, 0 functions
	1	[424]	GETUPVAL 	2 0	; fs
	2	[424]	GETTABLE 	2 2 -1	; "move"
	3	[424]	MOVE     	3 0
	4	[424]	MOVE     	4 1
	5	[424]	LOADK    	5 -2	; "read"
	6	[424]	TAILCALL 	2 4 0
	7	[424]	RETURN   	2 0
	8	[425]	RETURN   	0 1

function <./repos.lua:427,429> (8 instructions, 32 bytes at 0x7ff7bdc0e070)
2 params, 6 slots, 1 upvalue, 2 locals, 2 constants, 0 functions
	1	[428]	GETUPVAL 	2 0	; fs
	2	[428]	GETTABLE 	2 2 -1	; "move"
	3	[428]	MOVE     	3 0
	4	[428]	MOVE     	4 1
	5	[428]	LOADK    	5 -2	; "exec"
	6	[428]	TAILCALL 	2 4 0
	7	[428]	RETURN   	2 0
	8	[429]	RETURN   	0 1

function <./repos.lua:433,448> (86 instructions, 344 bytes at 0x7ff7bdc0d3a0)
1 param, 13 slots, 13 upvalues, 10 locals, 15 constants, 0 functions
	1	[434]	GETUPVAL 	1 0	; dir
	2	[434]	GETTABLE 	1 1 -1	; "path"
	3	[434]	GETUPVAL 	2 1	; source_dir
	4	[434]	MOVE     	3 0
	5	[434]	CALL     	1 3 2
	6	[435]	GETUPVAL 	2 2	; get_deploy_paths
	7	[435]	GETUPVAL 	3 3	; name
	8	[435]	GETUPVAL 	4 4	; version
	9	[435]	LOADK    	5 -2	; "bin"
	10	[435]	MOVE     	6 0
	11	[435]	GETUPVAL 	7 5	; repo
	12	[435]	CALL     	2 6 2
	13	[436]	GETUPVAL 	3 6	; check_spot_if_available
	14	[436]	GETUPVAL 	4 3	; name
	15	[436]	GETUPVAL 	5 4	; version
	16	[436]	LOADK    	6 -2	; "bin"
	17	[436]	MOVE     	7 0
	18	[436]	CALL     	3 5 4
	19	[438]	EQ       	0 3 -3	; - "nv"
	20	[438]	JMP      	21	; to 42
	21	[438]	TEST     	4 0 0
	22	[438]	JMP      	19	; to 42
	23	[439]	GETUPVAL 	6 2	; get_deploy_paths
	24	[439]	MOVE     	7 4
	25	[439]	MOVE     	8 5
	26	[439]	LOADK    	9 -2	; "bin"
	27	[439]	MOVE     	10 0
	28	[439]	GETUPVAL 	11 5	; repo
	29	[439]	CALL     	6 6 2
	30	[440]	GETGLOBAL	7 -4	; table
	31	[440]	GETTABLE 	7 7 -5	; "insert"
	32	[440]	GETUPVAL 	8 7	; renames
	33	[440]	NEWTABLE 	9 0 3
	34	[440]	GETTABLE 	10 6 -3	; "nv"
	35	[440]	SETTABLE 	9 -6 10	; "src" -
	36	[440]	GETTABLE 	10 6 -8	; "v"
	37	[440]	SETTABLE 	9 -7 10	; "dst" -
	38	[440]	GETUPVAL 	10 8	; cfg
	39	[440]	GETTABLE 	10 10 -10	; "wrapper_suffix"
	40	[440]	SETTABLE 	9 -9 10	; "suffix" -
	41	[440]	CALL     	7 3 1
	42	[442]	EQ       	0 3 -3	; - "nv"
	43	[442]	JMP      	3	; to 47
	44	[442]	GETTABLE 	6 2 -3	; "nv"
	45	[442]	TEST     	6 0 1
	46	[442]	JMP      	1	; to 48
	47	[442]	GETTABLE 	6 2 -8	; "v"
	48	[443]	GETUPVAL 	7 3	; name
	49	[443]	EQ       	0 7 4
	50	[443]	JMP      	4	; to 55
	51	[443]	GETUPVAL 	7 4	; version
	52	[443]	EQ       	0 7 5
	53	[443]	JMP      	1	; to 55
	54	[443]	LOADBOOL 	7 0 1
	55	[443]	LOADBOOL 	7 1 0
	56	[444]	GETUPVAL 	8 9	; wrap_bin_scripts
	57	[444]	TEST     	8 0 0
	58	[444]	JMP      	15	; to 74
	59	[444]	GETUPVAL 	8 10	; fs
	60	[444]	GETTABLE 	8 8 -11	; "is_lua"
	61	[444]	MOVE     	9 1
	62	[444]	CALL     	8 2 2
	63	[445]	TEST     	8 0 0
	64	[445]	JMP      	9	; to 74
	65	[445]	MOVE     	8 6
	66	[445]	GETUPVAL 	9 8	; cfg
	67	[445]	GETTABLE 	9 9 -10	; "wrapper_suffix"
	68	[445]	TEST     	9 0 1
	69	[445]	JMP      	1	; to 71
	70	[445]	LOADK    	9 -12	; ""
	71	[445]	CONCAT   	8 8 9
	72	[446]	TEST     	8 0 1
	73	[446]	JMP      	1	; to 75
	74	[446]	MOVE     	8 6
	75	[447]	GETGLOBAL	9 -4	; table
	76	[447]	GETTABLE 	9 9 -5	; "insert"
	77	[447]	GETUPVAL 	10 11	; installs
	78	[447]	NEWTABLE 	11 0 5
	79	[447]	GETUPVAL 	12 12	; install_binary
	80	[447]	SETTABLE 	11 -13 12	; "fn" -
	81	[447]	SETTABLE 	11 -6 1	; "src" -
	82	[447]	SETTABLE 	11 -7 6	; "dst" -
	83	[447]	SETTABLE 	11 -14 7	; "backup" -
	84	[447]	SETTABLE 	11 -15 8	; "realdst" -
	85	[447]	CALL     	9 3 1
	86	[448]	RETURN   	0 1

function <./repos.lua:453,467> (86 instructions, 344 bytes at 0x7ff7bdc0d950)
1 param, 16 slots, 11 upvalues, 9 locals, 15 constants, 0 functions
	1	[454]	GETUPVAL 	1 0	; dir
	2	[454]	GETTABLE 	1 1 -1	; "path"
	3	[454]	GETUPVAL 	2 1	; source_dir
	4	[454]	MOVE     	3 0
	5	[454]	CALL     	1 3 2
	6	[455]	GETUPVAL 	2 2	; get_deploy_paths
	7	[455]	GETUPVAL 	3 3	; name
	8	[455]	GETUPVAL 	4 4	; version
	9	[455]	LOADK    	5 -2	; "lua"
	10	[455]	MOVE     	6 0
	11	[455]	GETUPVAL 	7 5	; repo
	12	[455]	CALL     	2 6 2
	13	[456]	GETUPVAL 	3 6	; check_spot_if_available
	14	[456]	GETUPVAL 	4 3	; name
	15	[456]	GETUPVAL 	5 4	; version
	16	[456]	LOADK    	6 -2	; "lua"
	17	[456]	MOVE     	7 0
	18	[456]	CALL     	3 5 4
	19	[458]	EQ       	0 3 -3	; - "nv"
	20	[458]	JMP      	41	; to 62
	21	[458]	TEST     	4 0 0
	22	[458]	JMP      	39	; to 62
	23	[459]	GETUPVAL 	6 2	; get_deploy_paths
	24	[459]	MOVE     	7 4
	25	[459]	MOVE     	8 5
	26	[459]	LOADK    	9 -2	; "lua"
	27	[459]	MOVE     	10 0
	28	[459]	GETUPVAL 	11 5	; repo
	29	[459]	CALL     	6 6 2
	30	[460]	GETGLOBAL	7 -4	; table
	31	[460]	GETTABLE 	7 7 -5	; "insert"
	32	[460]	GETUPVAL 	8 7	; renames
	33	[460]	NEWTABLE 	9 0 2
	34	[460]	GETTABLE 	10 6 -3	; "nv"
	35	[460]	SETTABLE 	9 -6 10	; "src" -
	36	[460]	GETTABLE 	10 6 -8	; "v"
	37	[460]	SETTABLE 	9 -7 10	; "dst" -
	38	[460]	CALL     	7 3 1
	39	[461]	GETUPVAL 	7 2	; get_deploy_paths
	40	[461]	MOVE     	8 4
	41	[461]	MOVE     	9 5
	42	[461]	LOADK    	10 -9	; "lib"
	43	[461]	SELF     	11 0 -10	; "gsub"
	44	[461]	LOADK    	13 -11	; "%.lua$"
	45	[461]	LOADK    	14 -12	; "."
	46	[461]	GETUPVAL 	15 8	; cfg
	47	[461]	GETTABLE 	15 15 -13	; "lib_extension"
	48	[461]	CONCAT   	14 14 15
	49	[461]	CALL     	11 4 2
	50	[461]	GETUPVAL 	12 5	; repo
	51	[461]	CALL     	7 6 2
	52	[461]	MOVE     	6 7
	53	[462]	GETGLOBAL	7 -4	; table
	54	[462]	GETTABLE 	7 7 -5	; "insert"
	55	[462]	GETUPVAL 	8 7	; renames
	56	[462]	NEWTABLE 	9 0 2
	57	[462]	GETTABLE 	10 6 -3	; "nv"
	58	[462]	SETTABLE 	9 -6 10	; "src" -
	59	[462]	GETTABLE 	10 6 -8	; "v"
	60	[462]	SETTABLE 	9 -7 10	; "dst" -
	61	[462]	CALL     	7 3 1
	62	[464]	EQ       	0 3 -3	; - "nv"
	63	[464]	JMP      	3	; to 67
	64	[464]	GETTABLE 	6 2 -3	; "nv"
	65	[464]	TEST     	6 0 1
	66	[464]	JMP      	1	; to 68
	67	[464]	GETTABLE 	6 2 -8	; "v"
	68	[465]	GETUPVAL 	7 3	; name
	69	[465]	EQ       	0 7 4
	70	[465]	JMP      	4	; to 75
	71	[465]	GETUPVAL 	7 4	; version
	72	[465]	EQ       	0 7 5
	73	[465]	JMP      	1	; to 75
	74	[465]	LOADBOOL 	7 0 1
	75	[465]	LOADBOOL 	7 1 0
	76	[466]	GETGLOBAL	8 -4	; table
	77	[466]	GETTABLE 	8 8 -5	; "insert"
	78	[466]	GETUPVAL 	9 9	; installs
	79	[466]	NEWTABLE 	10 0 4
	80	[466]	GETUPVAL 	11 10	; move_lua
	81	[466]	SETTABLE 	10 -14 11	; "fn" -
	82	[466]	SETTABLE 	10 -6 1	; "src" -
	83	[466]	SETTABLE 	10 -7 6	; "dst" -
	84	[466]	SETTABLE 	10 -15 7	; "backup" -
	85	[466]	CALL     	8 3 1
	86	[467]	RETURN   	0 1

function <./repos.lua:472,486> (83 instructions, 332 bytes at 0x7ff7bdc0e0f0)
1 param, 14 slots, 10 upvalues, 9 locals, 14 constants, 0 functions
	1	[473]	GETUPVAL 	1 0	; dir
	2	[473]	GETTABLE 	1 1 -1	; "path"
	3	[473]	GETUPVAL 	2 1	; source_dir
	4	[473]	MOVE     	3 0
	5	[473]	CALL     	1 3 2
	6	[474]	GETUPVAL 	2 2	; get_deploy_paths
	7	[474]	GETUPVAL 	3 3	; name
	8	[474]	GETUPVAL 	4 4	; version
	9	[474]	LOADK    	5 -2	; "lib"
	10	[474]	MOVE     	6 0
	11	[474]	GETUPVAL 	7 5	; repo
	12	[474]	CALL     	2 6 2
	13	[475]	GETUPVAL 	3 6	; check_spot_if_available
	14	[475]	GETUPVAL 	4 3	; name
	15	[475]	GETUPVAL 	5 4	; version
	16	[475]	LOADK    	6 -2	; "lib"
	17	[475]	MOVE     	7 0
	18	[475]	CALL     	3 5 4
	19	[477]	EQ       	0 3 -3	; - "nv"
	20	[477]	JMP      	38	; to 59
	21	[477]	TEST     	4 0 0
	22	[477]	JMP      	36	; to 59
	23	[478]	GETUPVAL 	6 2	; get_deploy_paths
	24	[478]	MOVE     	7 4
	25	[478]	MOVE     	8 5
	26	[478]	LOADK    	9 -4	; "lua"
	27	[478]	SELF     	10 0 -5	; "gsub"
	28	[478]	LOADK    	12 -6	; "%.[^.]+$"
	29	[478]	LOADK    	13 -7	; ".lua"
	30	[478]	CALL     	10 4 2
	31	[478]	GETUPVAL 	11 5	; repo
	32	[478]	CALL     	6 6 2
	33	[479]	GETGLOBAL	7 -8	; table
	34	[479]	GETTABLE 	7 7 -9	; "insert"
	35	[479]	GETUPVAL 	8 7	; renames
	36	[479]	NEWTABLE 	9 0 2
	37	[479]	GETTABLE 	10 6 -3	; "nv"
	38	[479]	SETTABLE 	9 -10 10	; "src" -
	39	[479]	GETTABLE 	10 6 -12	; "v"
	40	[479]	SETTABLE 	9 -11 10	; "dst" -
	41	[479]	CALL     	7 3 1
	42	[480]	GETUPVAL 	7 2	; get_deploy_paths
	43	[480]	MOVE     	8 4
	44	[480]	MOVE     	9 5
	45	[480]	LOADK    	10 -2	; "lib"
	46	[480]	MOVE     	11 0
	47	[480]	GETUPVAL 	12 5	; repo
	48	[480]	CALL     	7 6 2
	49	[480]	MOVE     	6 7
	50	[481]	GETGLOBAL	7 -8	; table
	51	[481]	GETTABLE 	7 7 -9	; "insert"
	52	[481]	GETUPVAL 	8 7	; renames
	53	[481]	NEWTABLE 	9 0 2
	54	[481]	GETTABLE 	10 6 -3	; "nv"
	55	[481]	SETTABLE 	9 -10 10	; "src" -
	56	[481]	GETTABLE 	10 6 -12	; "v"
	57	[481]	SETTABLE 	9 -11 10	; "dst" -
	58	[481]	CALL     	7 3 1
	59	[483]	EQ       	0 3 -3	; - "nv"
	60	[483]	JMP      	3	; to 64
	61	[483]	GETTABLE 	6 2 -3	; "nv"
	62	[483]	TEST     	6 0 1
	63	[483]	JMP      	1	; to 65
	64	[483]	GETTABLE 	6 2 -12	; "v"
	65	[484]	GETUPVAL 	7 3	; name
	66	[484]	EQ       	0 7 4
	67	[484]	JMP      	4	; to 72
	68	[484]	GETUPVAL 	7 4	; version
	69	[484]	EQ       	0 7 5
	70	[484]	JMP      	1	; to 72
	71	[484]	LOADBOOL 	7 0 1
	72	[484]	LOADBOOL 	7 1 0
	73	[485]	GETGLOBAL	8 -8	; table
	74	[485]	GETTABLE 	8 8 -9	; "insert"
	75	[485]	GETUPVAL 	9 8	; installs
	76	[485]	NEWTABLE 	10 0 4
	77	[485]	GETUPVAL 	11 9	; move_lib
	78	[485]	SETTABLE 	10 -13 11	; "fn" -
	79	[485]	SETTABLE 	10 -10 1	; "src" -
	80	[485]	SETTABLE 	10 -11 6	; "dst" -
	81	[485]	SETTABLE 	10 -14 7	; "backup" -
	82	[485]	CALL     	8 3 1
	83	[486]	RETURN   	0 1

function <./repos.lua:521,614> (156 instructions, 624 bytes at 0x7ff7bdc0f220)
4 params, 18 slots, 11 upvalues, 22 locals, 19 constants, 3 functions
	1	[522]	GETGLOBAL	4 -1	; assert
	2	[522]	GETGLOBAL	5 -2	; type
	3	[522]	MOVE     	6 0
	4	[522]	CALL     	5 2 2
	5	[522]	EQ       	0 5 -3	; - "string"
	6	[522]	JMP      	5	; to 12
	7	[522]	SELF     	5 0 -4	; "match"
	8	[522]	LOADK    	7 -5	; "/"
	9	[522]	CALL     	5 3 2
	10	[522]	NOT      	5 5
	11	[522]	JMP      	2	; to 14
	12	[522]	LOADBOOL 	5 0 1
	13	[522]	LOADBOOL 	5 1 0
	14	[522]	CALL     	4 2 1
	15	[523]	GETGLOBAL	4 -1	; assert
	16	[523]	GETGLOBAL	5 -2	; type
	17	[523]	MOVE     	6 1
	18	[523]	CALL     	5 2 2
	19	[523]	EQ       	1 5 -3	; - "string"
	20	[523]	JMP      	1	; to 22
	21	[523]	LOADBOOL 	5 0 1
	22	[523]	LOADBOOL 	5 1 0
	23	[523]	CALL     	4 2 1
	24	[524]	GETGLOBAL	4 -1	; assert
	25	[524]	GETGLOBAL	5 -2	; type
	26	[524]	MOVE     	6 2
	27	[524]	CALL     	5 2 2
	28	[524]	EQ       	1 5 -3	; - "string"
	29	[524]	JMP      	1	; to 31
	30	[524]	LOADBOOL 	5 0 1
	31	[524]	LOADBOOL 	5 1 0
	32	[524]	CALL     	4 2 1
	33	[526]	GETUPVAL 	4 0	; manif
	34	[526]	GETTABLE 	4 4 -6	; "load_rock_manifest"
	35	[526]	MOVE     	5 0
	36	[526]	MOVE     	6 1
	37	[526]	CALL     	4 3 3
	38	[527]	TEST     	4 0 1
	39	[527]	JMP      	3	; to 43
	40	[527]	LOADNIL  	6 6
	41	[527]	MOVE     	7 5
	42	[527]	RETURN   	6 3
	43	[529]	GETUPVAL 	6 1	; cfg
	44	[529]	GETTABLE 	6 6 -7	; "root_dir"
	45	[530]	NEWTABLE 	7 0 0
	46	[531]	NEWTABLE 	8 0 0
	47	[533]	GETTABLE 	9 4 -8	; "bin"
	48	[533]	TEST     	9 0 0
	49	[533]	JMP      	14	; to 64
	50	[534]	GETUPVAL 	9 2	; repos
	51	[534]	GETTABLE 	9 9 -9	; "recurse_rock_manifest_entry"
	52	[534]	GETTABLE 	10 4 -8	; "bin"
	53	[548]	CLOSURE  	11 0	; 0x7ff7bdc102f0
	54	[548]	GETUPVAL 	0 3	; get_deploy_paths
	55	[548]	MOVE     	0 0
	56	[548]	MOVE     	0 1
	57	[548]	MOVE     	0 6
	58	[548]	GETUPVAL 	0 4	; check_spot_if_available
	59	[548]	MOVE     	0 8
	60	[548]	GETUPVAL 	0 1	; cfg
	61	[548]	GETUPVAL 	0 0	; manif
	62	[548]	MOVE     	0 7
	63	[534]	CALL     	9 3 1
	64	[551]	GETTABLE 	9 4 -10	; "lua"
	65	[551]	TEST     	9 0 0
	66	[551]	JMP      	13	; to 80
	67	[552]	GETUPVAL 	9 2	; repos
	68	[552]	GETTABLE 	9 9 -9	; "recurse_rock_manifest_entry"
	69	[552]	GETTABLE 	10 4 -10	; "lua"
	70	[568]	CLOSURE  	11 1	; 0x7ff7bdc11070
	71	[568]	GETUPVAL 	0 3	; get_deploy_paths
	72	[568]	MOVE     	0 0
	73	[568]	MOVE     	0 1
	74	[568]	MOVE     	0 6
	75	[568]	GETUPVAL 	0 4	; check_spot_if_available
	76	[568]	MOVE     	0 8
	77	[568]	GETUPVAL 	0 0	; manif
	78	[568]	MOVE     	0 7
	79	[552]	CALL     	9 3 1
	80	[571]	GETTABLE 	9 4 -11	; "lib"
	81	[571]	TEST     	9 0 0
	82	[571]	JMP      	13	; to 96
	83	[572]	GETUPVAL 	9 2	; repos
	84	[572]	GETTABLE 	9 9 -9	; "recurse_rock_manifest_entry"
	85	[572]	GETTABLE 	10 4 -11	; "lib"
	86	[588]	CLOSURE  	11 2	; 0x7ff7bdc10de0
	87	[588]	GETUPVAL 	0 3	; get_deploy_paths
	88	[588]	MOVE     	0 0
	89	[588]	MOVE     	0 1
	90	[588]	MOVE     	0 6
	91	[588]	GETUPVAL 	0 4	; check_spot_if_available
	92	[588]	MOVE     	0 8
	93	[588]	GETUPVAL 	0 0	; manif
	94	[588]	MOVE     	0 7
	95	[572]	CALL     	9 3 1
	96	[591]	GETUPVAL 	9 5	; prepare_op_delete
	97	[591]	CALL     	9 1 3
	98	[592]	GETGLOBAL	11 -12	; ipairs
	99	[592]	MOVE     	12 8
	100	[592]	CALL     	11 2 4
	101	[592]	JMP      	3	; to 105
	102	[593]	MOVE     	16 9
	103	[593]	MOVE     	17 15
	104	[593]	CALL     	16 2 1
	105	[592]	TFORLOOP 	11 2
	106	[593]	JMP      	-5	; to 102
	107	[595]	MOVE     	11 10
	108	[595]	CALL     	11 1 1
	109	[597]	TEST     	3 0 1
	110	[597]	JMP      	9	; to 120
	111	[598]	GETGLOBAL	11 -12	; ipairs
	112	[598]	MOVE     	12 7
	113	[598]	CALL     	11 2 4
	114	[598]	JMP      	3	; to 118
	115	[599]	GETUPVAL 	16 6	; op_rename
	116	[599]	MOVE     	17 15
	117	[599]	CALL     	16 2 1
	118	[598]	TFORLOOP 	11 2
	119	[599]	JMP      	-5	; to 115
	120	[603]	GETUPVAL 	11 7	; fs
	121	[603]	GETTABLE 	11 11 -13	; "delete"
	122	[603]	GETUPVAL 	12 8	; path
	123	[603]	GETTABLE 	12 12 -14	; "install_dir"
	124	[603]	MOVE     	13 0
	125	[603]	MOVE     	14 1
	126	[603]	CALL     	12 3 0
	127	[603]	CALL     	11 0 1
	128	[604]	GETUPVAL 	11 9	; get_installed_versions
	129	[604]	MOVE     	12 0
	130	[604]	CALL     	11 2 2
	131	[604]	TEST     	11 0 1
	132	[604]	JMP      	9	; to 142
	133	[605]	GETUPVAL 	11 7	; fs
	134	[605]	GETTABLE 	11 11 -13	; "delete"
	135	[605]	GETUPVAL 	12 10	; dir
	136	[605]	GETTABLE 	12 12 -15	; "path"
	137	[605]	GETUPVAL 	13 1	; cfg
	138	[605]	GETTABLE 	13 13 -16	; "rocks_dir"
	139	[605]	MOVE     	14 0
	140	[605]	CALL     	12 3 0
	141	[605]	CALL     	11 0 1
	142	[608]	TEST     	3 0 0
	143	[608]	JMP      	2	; to 146
	144	[609]	LOADBOOL 	11 1 0
	145	[609]	RETURN   	11 2
	146	[612]	GETGLOBAL	11 -17	; require
	147	[612]	LOADK    	12 -18	; "luarocks.manif.writer"
	148	[612]	CALL     	11 2 2
	149	[613]	GETTABLE 	12 11 -19	; "remove_from_manifest"
	150	[613]	MOVE     	13 0
	151	[613]	MOVE     	14 1
	152	[613]	LOADNIL  	15 15
	153	[613]	MOVE     	16 2
	154	[613]	TAILCALL 	12 5 0
	155	[613]	RETURN   	12 0
	156	[614]	RETURN   	0 1

function <./repos.lua:534,548> (63 instructions, 252 bytes at 0x7ff7bdc102f0)
1 param, 14 slots, 9 upvalues, 9 locals, 13 constants, 0 functions
	1	[535]	GETUPVAL 	1 0	; get_deploy_paths
	2	[535]	GETUPVAL 	2 1	; name
	3	[535]	GETUPVAL 	3 2	; version
	4	[535]	LOADK    	4 -1	; "bin"
	5	[535]	MOVE     	5 0
	6	[535]	GETUPVAL 	6 3	; repo
	7	[535]	CALL     	1 6 2
	8	[536]	GETUPVAL 	2 4	; check_spot_if_available
	9	[536]	GETUPVAL 	3 1	; name
	10	[536]	GETUPVAL 	4 2	; version
	11	[536]	LOADK    	5 -1	; "bin"
	12	[536]	MOVE     	6 0
	13	[536]	CALL     	2 5 5
	14	[537]	EQ       	0 2 -2	; - "v"
	15	[537]	JMP      	11	; to 27
	16	[538]	GETGLOBAL	6 -3	; table
	17	[538]	GETTABLE 	6 6 -4	; "insert"
	18	[538]	GETUPVAL 	7 5	; deletes
	19	[538]	NEWTABLE 	8 0 2
	20	[538]	GETTABLE 	9 1 -2	; "v"
	21	[538]	SETTABLE 	8 -5 9	; "name" -
	22	[538]	GETUPVAL 	9 6	; cfg
	23	[538]	GETTABLE 	9 9 -7	; "wrapper_suffix"
	24	[538]	SETTABLE 	8 -6 9	; "suffix" -
	25	[538]	CALL     	6 3 1
	26	[538]	JMP      	36	; to 63
	27	[540]	GETGLOBAL	6 -3	; table
	28	[540]	GETTABLE 	6 6 -4	; "insert"
	29	[540]	GETUPVAL 	7 5	; deletes
	30	[540]	NEWTABLE 	8 0 2
	31	[540]	GETTABLE 	9 1 -8	; "nv"
	32	[540]	SETTABLE 	8 -5 9	; "name" -
	33	[540]	GETUPVAL 	9 6	; cfg
	34	[540]	GETTABLE 	9 9 -7	; "wrapper_suffix"
	35	[540]	SETTABLE 	8 -6 9	; "suffix" -
	36	[540]	CALL     	6 3 1
	37	[542]	GETUPVAL 	6 7	; manif
	38	[542]	GETTABLE 	6 6 -9	; "get_next_provider"
	39	[542]	LOADK    	7 -10	; "command"
	40	[542]	MOVE     	8 5
	41	[542]	CALL     	6 3 3
	42	[543]	TEST     	6 0 0
	43	[543]	JMP      	19	; to 63
	44	[544]	GETUPVAL 	8 0	; get_deploy_paths
	45	[544]	MOVE     	9 6
	46	[544]	MOVE     	10 7
	47	[544]	LOADK    	11 -11	; "lua"
	48	[544]	MOVE     	12 0
	49	[544]	GETUPVAL 	13 3	; repo
	50	[544]	CALL     	8 6 2
	51	[545]	GETGLOBAL	9 -3	; table
	52	[545]	GETTABLE 	9 9 -4	; "insert"
	53	[545]	GETUPVAL 	10 8	; renames
	54	[545]	NEWTABLE 	11 0 3
	55	[545]	GETTABLE 	12 8 -2	; "v"
	56	[545]	SETTABLE 	11 -12 12	; "src" -
	57	[545]	GETTABLE 	12 8 -8	; "nv"
	58	[545]	SETTABLE 	11 -13 12	; "dst" -
	59	[545]	GETUPVAL 	12 6	; cfg
	60	[545]	GETTABLE 	12 12 -7	; "wrapper_suffix"
	61	[545]	SETTABLE 	11 -6 12	; "suffix" -
	62	[545]	CALL     	9 3 1
	63	[548]	RETURN   	0 1

function <./repos.lua:552,568> (73 instructions, 292 bytes at 0x7ff7bdc11070)
1 param, 17 slots, 8 upvalues, 10 locals, 14 constants, 0 functions
	1	[553]	GETUPVAL 	1 0	; get_deploy_paths
	2	[553]	GETUPVAL 	2 1	; name
	3	[553]	GETUPVAL 	3 2	; version
	4	[553]	LOADK    	4 -1	; "lua"
	5	[553]	MOVE     	5 0
	6	[553]	GETUPVAL 	6 3	; repo
	7	[553]	CALL     	1 6 2
	8	[554]	GETUPVAL 	2 4	; check_spot_if_available
	9	[554]	GETUPVAL 	3 1	; name
	10	[554]	GETUPVAL 	4 2	; version
	11	[554]	LOADK    	5 -1	; "lua"
	12	[554]	MOVE     	6 0
	13	[554]	CALL     	2 5 5
	14	[555]	EQ       	0 2 -2	; - "v"
	15	[555]	JMP      	8	; to 24
	16	[556]	GETGLOBAL	6 -3	; table
	17	[556]	GETTABLE 	6 6 -4	; "insert"
	18	[556]	GETUPVAL 	7 5	; deletes
	19	[556]	NEWTABLE 	8 0 1
	20	[556]	GETTABLE 	9 1 -2	; "v"
	21	[556]	SETTABLE 	8 -5 9	; "name" -
	22	[556]	CALL     	6 3 1
	23	[556]	JMP      	49	; to 73
	24	[558]	GETGLOBAL	6 -3	; table
	25	[558]	GETTABLE 	6 6 -4	; "insert"
	26	[558]	GETUPVAL 	7 5	; deletes
	27	[558]	NEWTABLE 	8 0 1
	28	[558]	GETTABLE 	9 1 -6	; "nv"
	29	[558]	SETTABLE 	8 -5 9	; "name" -
	30	[558]	CALL     	6 3 1
	31	[560]	GETUPVAL 	6 6	; manif
	32	[560]	GETTABLE 	6 6 -7	; "get_next_provider"
	33	[560]	LOADK    	7 -8	; "module"
	34	[560]	MOVE     	8 5
	35	[560]	CALL     	6 3 3
	36	[561]	TEST     	6 0 0
	37	[561]	JMP      	35	; to 73
	38	[562]	GETUPVAL 	8 0	; get_deploy_paths
	39	[562]	MOVE     	9 6
	40	[562]	MOVE     	10 7
	41	[562]	LOADK    	11 -1	; "lua"
	42	[562]	MOVE     	12 0
	43	[562]	GETUPVAL 	13 3	; repo
	44	[562]	CALL     	8 6 2
	45	[563]	GETGLOBAL	9 -3	; table
	46	[563]	GETTABLE 	9 9 -4	; "insert"
	47	[563]	GETUPVAL 	10 7	; renames
	48	[563]	NEWTABLE 	11 0 2
	49	[563]	GETTABLE 	12 8 -2	; "v"
	50	[563]	SETTABLE 	11 -9 12	; "src" -
	51	[563]	GETTABLE 	12 8 -6	; "nv"
	52	[563]	SETTABLE 	11 -10 12	; "dst" -
	53	[563]	CALL     	9 3 1
	54	[564]	GETUPVAL 	9 0	; get_deploy_paths
	55	[564]	MOVE     	10 6
	56	[564]	MOVE     	11 7
	57	[564]	LOADK    	12 -11	; "lib"
	58	[564]	SELF     	13 0 -12	; "gsub"
	59	[564]	LOADK    	15 -13	; "%.[^.]+$"
	60	[564]	LOADK    	16 -14	; ".lua"
	61	[564]	CALL     	13 4 2
	62	[564]	GETUPVAL 	14 3	; repo
	63	[564]	CALL     	9 6 2
	64	[565]	GETGLOBAL	10 -3	; table
	65	[565]	GETTABLE 	10 10 -4	; "insert"
	66	[565]	GETUPVAL 	11 7	; renames
	67	[565]	NEWTABLE 	12 0 2
	68	[565]	GETTABLE 	13 9 -2	; "v"
	69	[565]	SETTABLE 	12 -9 13	; "src" -
	70	[565]	GETTABLE 	13 9 -6	; "nv"
	71	[565]	SETTABLE 	12 -10 13	; "dst" -
	72	[565]	CALL     	10 3 1
	73	[568]	RETURN   	0 1

function <./repos.lua:572,588> (73 instructions, 292 bytes at 0x7ff7bdc10de0)
1 param, 16 slots, 8 upvalues, 10 locals, 14 constants, 0 functions
	1	[573]	GETUPVAL 	1 0	; get_deploy_paths
	2	[573]	GETUPVAL 	2 1	; name
	3	[573]	GETUPVAL 	3 2	; version
	4	[573]	LOADK    	4 -1	; "lib"
	5	[573]	MOVE     	5 0
	6	[573]	GETUPVAL 	6 3	; repo
	7	[573]	CALL     	1 6 2
	8	[574]	GETUPVAL 	2 4	; check_spot_if_available
	9	[574]	GETUPVAL 	3 1	; name
	10	[574]	GETUPVAL 	4 2	; version
	11	[574]	LOADK    	5 -1	; "lib"
	12	[574]	MOVE     	6 0
	13	[574]	CALL     	2 5 5
	14	[575]	EQ       	0 2 -2	; - "v"
	15	[575]	JMP      	8	; to 24
	16	[576]	GETGLOBAL	6 -3	; table
	17	[576]	GETTABLE 	6 6 -4	; "insert"
	18	[576]	GETUPVAL 	7 5	; deletes
	19	[576]	NEWTABLE 	8 0 1
	20	[576]	GETTABLE 	9 1 -2	; "v"
	21	[576]	SETTABLE 	8 -5 9	; "name" -
	22	[576]	CALL     	6 3 1
	23	[576]	JMP      	49	; to 73
	24	[578]	GETGLOBAL	6 -3	; table
	25	[578]	GETTABLE 	6 6 -4	; "insert"
	26	[578]	GETUPVAL 	7 5	; deletes
	27	[578]	NEWTABLE 	8 0 1
	28	[578]	GETTABLE 	9 1 -6	; "nv"
	29	[578]	SETTABLE 	8 -5 9	; "name" -
	30	[578]	CALL     	6 3 1
	31	[580]	GETUPVAL 	6 6	; manif
	32	[580]	GETTABLE 	6 6 -7	; "get_next_provider"
	33	[580]	LOADK    	7 -8	; "module"
	34	[580]	MOVE     	8 5
	35	[580]	CALL     	6 3 3
	36	[581]	TEST     	6 0 0
	37	[581]	JMP      	35	; to 73
	38	[582]	GETUPVAL 	8 0	; get_deploy_paths
	39	[582]	MOVE     	9 6
	40	[582]	MOVE     	10 7
	41	[582]	LOADK    	11 -9	; "lua"
	42	[582]	SELF     	12 0 -10	; "gsub"
	43	[582]	LOADK    	14 -11	; "%.[^.]+$"
	44	[582]	LOADK    	15 -12	; ".lua"
	45	[582]	CALL     	12 4 2
	46	[582]	GETUPVAL 	13 3	; repo
	47	[582]	CALL     	8 6 2
	48	[583]	GETGLOBAL	9 -3	; table
	49	[583]	GETTABLE 	9 9 -4	; "insert"
	50	[583]	GETUPVAL 	10 7	; renames
	51	[583]	NEWTABLE 	11 0 2
	52	[583]	GETTABLE 	12 8 -2	; "v"
	53	[583]	SETTABLE 	11 -13 12	; "src" -
	54	[583]	GETTABLE 	12 8 -6	; "nv"
	55	[583]	SETTABLE 	11 -14 12	; "dst" -
	56	[583]	CALL     	9 3 1
	57	[584]	GETUPVAL 	9 0	; get_deploy_paths
	58	[584]	MOVE     	10 6
	59	[584]	MOVE     	11 7
	60	[584]	LOADK    	12 -1	; "lib"
	61	[584]	MOVE     	13 0
	62	[584]	GETUPVAL 	14 3	; repo
	63	[584]	CALL     	9 6 2
	64	[585]	GETGLOBAL	10 -3	; table
	65	[585]	GETTABLE 	10 10 -4	; "insert"
	66	[585]	GETUPVAL 	11 7	; renames
	67	[585]	NEWTABLE 	12 0 2
	68	[585]	GETTABLE 	13 9 -2	; "v"
	69	[585]	SETTABLE 	12 -13 13	; "src" -
	70	[585]	GETTABLE 	13 9 -6	; "nv"
	71	[585]	SETTABLE 	12 -14 13	; "dst" -
	72	[585]	CALL     	10 3 1
	73	[588]	RETURN   	0 1
