-- BYTECODE -- results.lua:10-12
0001    KSTR     0   0      ; "result"
0002    RET1     0   2

-- BYTECODE -- results.lua:14-34
0001    GGET     5   0      ; "assert"
0002    GGET     6   1      ; "type"
0003    MOV      7   0
0004    CALL     6   2   2
0005    ISNES    6   2      ; "string"
0006    JMP      6 => 0013
0007    MOV      7   0
0008    TGETS    6   0   3  ; "match"
0009    KSTR     8   4      ; "/"
0010    CALL     6   2   3
0011    NOT      6   6
0012    JMP      7 => 0016
0013 => KPRI     6   1
0014    JMP      7 => 0016
0015    KPRI     6   2
0016 => CALL     5   1   2
0017    GGET     5   0      ; "assert"
0018    GGET     6   1      ; "type"
0019    MOV      7   1
0020    CALL     6   2   2
0021    ISEQS    6   2      ; "string"
0022    JMP      6 => 0025
0023    KPRI     6   1
0024    JMP      7 => 0026
0025 => KPRI     6   2
0026 => CALL     5   1   2
0027    GGET     5   0      ; "assert"
0028    GGET     6   1      ; "type"
0029    MOV      7   2
0030    CALL     6   2   2
0031    ISEQS    6   2      ; "string"
0032    JMP      6 => 0035
0033    KPRI     6   1
0034    JMP      7 => 0036
0035 => KPRI     6   2
0036 => CALL     5   1   2
0037    GGET     5   0      ; "assert"
0038    GGET     6   1      ; "type"
0039    MOV      7   3
0040    CALL     6   2   2
0041    ISEQS    6   2      ; "string"
0042    JMP      6 => 0047
0043    NOT      6   3
0044    JMP      7 => 0048
0045    KPRI     6   1
0046    JMP      7 => 0048
0047 => KPRI     6   2
0048 => CALL     5   1   2
0049    GGET     5   0      ; "assert"
0050    GGET     6   1      ; "type"
0051    MOV      7   4
0052    CALL     6   2   2
0053    ISEQS    6   2      ; "string"
0054    JMP      6 => 0059
0055    NOT      6   4
0056    JMP      7 => 0060
0057    KPRI     6   1
0058    JMP      7 => 0060
0059 => KPRI     6   2
0060 => CALL     5   1   2
0061    IST          4
0062    JMP      5 => 0069
0063    UGET     5   0      ; util
0064    TGETS    5   5   5  ; "split_namespace"
0065    MOV      6   0
0066    CALL     5   3   2
0067    MOV      4   6
0068    MOV      0   5
0069 => TDUP     5   6
0070    TSETS    0   5   7  ; "name"
0071    TSETS    1   5   8  ; "version"
0072    TSETS    4   5   9  ; "namespace"
0073    TSETS    3   5  10  ; "arch"
0074    TSETS    2   5  11  ; "repo"
0075    GGET     6  12      ; "setmetatable"
0076    MOV      7   5
0077    UGET     8   1      ; result_mt
0078    CALLT    6   3

-- BYTECODE -- results.lua:43-49
0001    TGETS    2   0   0  ; "substring"
0002    ISF          2
0003    JMP      3 => 0017
0004    MOV      3   1
0005    TGETS    2   1   1  ; "find"
0006    TGETS    4   0   2  ; "name"
0007    KSHORT   5   0
0008    KPRI     6   2
0009    CALL     2   2   5
0010    ISF          2
0011    JMP      3 => 0014
0012    KPRI     2   2
0013    JMP      3 => 0015
0014 => KPRI     2   1
0015 => RET1     2   2
0016    JMP      2 => 0024
0017 => TGETS    2   0   2  ; "name"
0018    ISEQV    1   2
0019    JMP      2 => 0022
0020    KPRI     2   1
0021    JMP      3 => 0023
0022 => KPRI     2   2
0023 => RET1     2   2
0024 => RET0     0   1

-- BYTECODE -- results.lua:54-60
0001    GGET     2   0      ; "assert"
0002    MOV      4   1
0003    TGETS    3   1   1  ; "type"
0004    CALL     3   2   2
0005    ISEQS    3   2      ; "query"
0006    JMP      3 => 0009
0007    KPRI     3   1
0008    JMP      4 => 0010
0009 => KPRI     3   2
0010 => CALL     2   1   2
0011    UGET     2   0      ; match_name
0012    MOV      3   1
0013    TGETS    4   0   3  ; "name"
0014    CALL     2   2   3
0015    ISF          2
0016    JMP      3 => 0045
0017    TGETS    2   1   4  ; "arch"
0018    TGETS    3   0   4  ; "arch"
0019    TGETV    2   2   3
0020    IST          2
0021    JMP      3 => 0026
0022    TGETS    2   1   4  ; "arch"
0023    TGETS    2   2   5  ; "any"
0024    ISF          2
0025    JMP      3 => 0045
0026 => TGETS    2   1   6  ; "namespace"
0027    ISF          2
0028    JMP      2 => 0033
0029    TGETS    2   1   6  ; "namespace"
0030    TGETS    3   0   6  ; "namespace"
0031    ISNEV    2   3
0032    JMP      2 => 0042
0033 => UGET     2   1      ; vers
0034    TGETS    2   2   7  ; "match_constraints"
0035    UGET     3   1      ; vers
0036    TGETS    3   3   8  ; "parse_version"
0037    TGETS    4   0   9  ; "version"
0038    CALL     3   2   2
0039    TGETS    4   1  10  ; "constraints"
0040    CALL     2   2   3
0041    JMP      3 => 0045
0042 => KPRI     2   1
0043    JMP      3 => 0045
0044    KPRI     2   2
0045 => RET1     2   2

-- BYTECODE -- results.lua:0-63
0001    TNEW     0   0
0002    GGET     1   0      ; "require"
0003    KSTR     2   1      ; "luarocks.core.vers"
0004    CALL     1   2   2
0005    GGET     2   0      ; "require"
0006    KSTR     3   2      ; "luarocks.util"
0007    CALL     2   2   2
0008    TNEW     3   0
0009    TSETS    3   3   3  ; "__index"
0010    FNEW     4   5      ; results.lua:10
0011    TSETS    4   3   4  ; "type"
0012    FNEW     4   7      ; results.lua:14
0013    TSETS    4   0   6  ; "new"
0014    FNEW     4   8      ; results.lua:43
0015    FNEW     5  10      ; results.lua:54
0016    TSETS    5   3   9  ; "satisfies"
0017    UCLO     0 => 0018
0018 => RET1     0   2

