
main <./results.lua:0,0> (22 instructions, 88 bytes at 0x7fa6a9c068a0)
0+ params, 6 slots, 0 upvalues, 5 locals, 7 constants, 4 functions
	1	[1]	NEWTABLE 	0 0 0
	2	[3]	GETGLOBAL	1 -1	; require
	3	[3]	LOADK    	2 -2	; "luarocks.core.vers"
	4	[3]	CALL     	1 2 2
	5	[4]	GETGLOBAL	2 -1	; require
	6	[4]	LOADK    	3 -3	; "luarocks.util"
	7	[4]	CALL     	2 2 2
	8	[6]	NEWTABLE 	3 0 0
	9	[8]	SETTABLE 	3 -4 3	; "__index" -
	10	[12]	CLOSURE  	4 0	; 0x7fa6a9c06f50
	11	[10]	SETTABLE 	3 -5 4	; "type" -
	12	[34]	CLOSURE  	4 1	; 0x7fa6a9c070c0
	13	[34]	MOVE     	0 2
	14	[34]	MOVE     	0 3
	15	[14]	SETTABLE 	0 -6 4	; "new" -
	16	[49]	CLOSURE  	4 2	; 0x7fa6a9c076e0
	17	[60]	CLOSURE  	5 3	; 0x7fa6a9c07d60
	18	[60]	MOVE     	0 4
	19	[60]	MOVE     	0 1
	20	[54]	SETTABLE 	3 -7 5	; "satisfies" -
	21	[62]	RETURN   	0 2
	22	[62]	RETURN   	0 1

function <./results.lua:10,12> (3 instructions, 12 bytes at 0x7fa6a9c06f50)
0 params, 2 slots, 0 upvalues, 0 locals, 1 constant, 0 functions
	1	[11]	LOADK    	0 -1	; "result"
	2	[11]	RETURN   	0 2
	3	[12]	RETURN   	0 1

function <./results.lua:14,34> (74 instructions, 296 bytes at 0x7fa6a9c070c0)
5 params, 9 slots, 2 upvalues, 6 locals, 12 constants, 0 functions
	1	[15]	GETGLOBAL	5 -1	; assert
	2	[15]	GETGLOBAL	6 -2	; type
	3	[15]	MOVE     	7 0
	4	[15]	CALL     	6 2 2
	5	[15]	EQ       	0 6 -3	; - "string"
	6	[15]	JMP      	5	; to 12
	7	[15]	SELF     	6 0 -4	; "match"
	8	[15]	LOADK    	8 -5	; "/"
	9	[15]	CALL     	6 3 2
	10	[15]	NOT      	6 6
	11	[15]	JMP      	2	; to 14
	12	[15]	LOADBOOL 	6 0 1
	13	[15]	LOADBOOL 	6 1 0
	14	[15]	CALL     	5 2 1
	15	[16]	GETGLOBAL	5 -1	; assert
	16	[16]	GETGLOBAL	6 -2	; type
	17	[16]	MOVE     	7 1
	18	[16]	CALL     	6 2 2
	19	[16]	EQ       	1 6 -3	; - "string"
	20	[16]	JMP      	1	; to 22
	21	[16]	LOADBOOL 	6 0 1
	22	[16]	LOADBOOL 	6 1 0
	23	[16]	CALL     	5 2 1
	24	[17]	GETGLOBAL	5 -1	; assert
	25	[17]	GETGLOBAL	6 -2	; type
	26	[17]	MOVE     	7 2
	27	[17]	CALL     	6 2 2
	28	[17]	EQ       	1 6 -3	; - "string"
	29	[17]	JMP      	1	; to 31
	30	[17]	LOADBOOL 	6 0 1
	31	[17]	LOADBOOL 	6 1 0
	32	[17]	CALL     	5 2 1
	33	[18]	GETGLOBAL	5 -1	; assert
	34	[18]	GETGLOBAL	6 -2	; type
	35	[18]	MOVE     	7 3
	36	[18]	CALL     	6 2 2
	37	[18]	EQ       	1 6 -3	; - "string"
	38	[18]	JMP      	3	; to 42
	39	[18]	NOT      	6 3
	40	[18]	JMP      	2	; to 43
	41	[18]	LOADBOOL 	6 0 1
	42	[18]	LOADBOOL 	6 1 0
	43	[18]	CALL     	5 2 1
	44	[19]	GETGLOBAL	5 -1	; assert
	45	[19]	GETGLOBAL	6 -2	; type
	46	[19]	MOVE     	7 4
	47	[19]	CALL     	6 2 2
	48	[19]	EQ       	1 6 -3	; - "string"
	49	[19]	JMP      	3	; to 53
	50	[19]	NOT      	6 4
	51	[19]	JMP      	2	; to 54
	52	[19]	LOADBOOL 	6 0 1
	53	[19]	LOADBOOL 	6 1 0
	54	[19]	CALL     	5 2 1
	55	[21]	TEST     	4 0 1
	56	[21]	JMP      	6	; to 63
	57	[22]	GETUPVAL 	5 0	; util
	58	[22]	GETTABLE 	5 5 -6	; "split_namespace"
	59	[22]	MOVE     	6 0
	60	[22]	CALL     	5 2 3
	61	[22]	MOVE     	4 6
	62	[22]	MOVE     	0 5
	63	[25]	NEWTABLE 	5 0 5
	64	[26]	SETTABLE 	5 -7 0	; "name" -
	65	[27]	SETTABLE 	5 -8 1	; "version" -
	66	[28]	SETTABLE 	5 -9 4	; "namespace" -
	67	[29]	SETTABLE 	5 -10 3	; "arch" -
	68	[30]	SETTABLE 	5 -11 2	; "repo" -
	69	[33]	GETGLOBAL	6 -12	; setmetatable
	70	[33]	MOVE     	7 5
	71	[33]	GETUPVAL 	8 1	; result_mt
	72	[33]	TAILCALL 	6 3 0
	73	[33]	RETURN   	6 0
	74	[34]	RETURN   	0 1

function <./results.lua:43,49> (23 instructions, 92 bytes at 0x7fa6a9c076e0)
2 params, 7 slots, 0 upvalues, 2 locals, 4 constants, 0 functions
	1	[44]	GETTABLE 	2 0 -1	; "substring"
	2	[44]	TEST     	2 0 0
	3	[44]	JMP      	13	; to 17
	4	[45]	SELF     	2 1 -2	; "find"
	5	[45]	GETTABLE 	4 0 -3	; "name"
	6	[45]	LOADK    	5 -4	; 0
	7	[45]	LOADBOOL 	6 1 0
	8	[45]	CALL     	2 5 2
	9	[45]	TEST     	2 0 0
	10	[45]	JMP      	3	; to 14
	11	[45]	LOADBOOL 	2 1 0
	12	[45]	TEST     	2 0 1
	13	[45]	JMP      	1	; to 15
	14	[45]	LOADBOOL 	2 0 0
	15	[45]	RETURN   	2 2
	16	[45]	JMP      	6	; to 23
	17	[47]	GETTABLE 	2 0 -3	; "name"
	18	[47]	EQ       	1 1 2
	19	[47]	JMP      	1	; to 21
	20	[47]	LOADBOOL 	2 0 1
	21	[47]	LOADBOOL 	2 1 0
	22	[47]	RETURN   	2 2
	23	[49]	RETURN   	0 1

function <./results.lua:54,60> (43 instructions, 172 bytes at 0x7fa6a9c07d60)
2 params, 5 slots, 2 upvalues, 2 locals, 11 constants, 0 functions
	1	[55]	GETGLOBAL	2 -1	; assert
	2	[55]	SELF     	3 1 -2	; "type"
	3	[55]	CALL     	3 2 2
	4	[55]	EQ       	1 3 -3	; - "query"
	5	[55]	JMP      	1	; to 7
	6	[55]	LOADBOOL 	3 0 1
	7	[55]	LOADBOOL 	3 1 0
	8	[55]	CALL     	2 2 1
	9	[56]	GETUPVAL 	2 0	; match_name
	10	[56]	MOVE     	3 1
	11	[56]	GETTABLE 	4 0 -4	; "name"
	12	[56]	CALL     	2 3 2
	13	[57]	TEST     	2 0 0
	14	[57]	JMP      	27	; to 42
	15	[57]	GETTABLE 	2 1 -5	; "arch"
	16	[57]	GETTABLE 	3 0 -5	; "arch"
	17	[57]	GETTABLE 	2 2 3
	18	[57]	TEST     	2 0 1
	19	[57]	JMP      	4	; to 24
	20	[57]	GETTABLE 	2 1 -5	; "arch"
	21	[57]	GETTABLE 	2 2 -6	; "any"
	22	[58]	TEST     	2 0 0
	23	[58]	JMP      	18	; to 42
	24	[58]	GETTABLE 	2 1 -7	; "namespace"
	25	[58]	TEST     	2 0 0
	26	[58]	JMP      	4	; to 31
	27	[58]	GETTABLE 	2 1 -7	; "namespace"
	28	[58]	GETTABLE 	3 0 -7	; "namespace"
	29	[58]	EQ       	0 2 3
	30	[58]	JMP      	9	; to 40
	31	[59]	GETUPVAL 	2 1	; vers
	32	[59]	GETTABLE 	2 2 -8	; "match_constraints"
	33	[59]	GETUPVAL 	3 1	; vers
	34	[59]	GETTABLE 	3 3 -9	; "parse_version"
	35	[59]	GETTABLE 	4 0 -10	; "version"
	36	[59]	CALL     	3 2 2
	37	[59]	GETTABLE 	4 1 -11	; "constraints"
	38	[59]	CALL     	2 3 2
	39	[59]	JMP      	2	; to 42
	40	[59]	LOADBOOL 	2 0 1
	41	[59]	LOADBOOL 	2 1 0
	42	[59]	RETURN   	2 2
	43	[60]	RETURN   	0 1
