
main <./type/rockspec.lua:0,0> (243 instructions, 972 bytes at 0x7f8e65c068a0)
0+ params, 21 slots, 0 upvalues, 5 locals, 67 constants, 2 functions
	1	[1]	NEWTABLE 	0 0 0
	2	[3]	GETGLOBAL	1 -1	; require
	3	[3]	LOADK    	2 -2	; "luarocks.type_check"
	4	[3]	CALL     	1 2 2
	5	[5]	SETTABLE 	0 -3 -4	; "rockspec_format" "3.0"
	6	[20]	GETTABLE 	2 1 -5	; "declare_schemas"
	7	[20]	NEWTABLE 	3 0 3
	8	[21]	NEWTABLE 	4 0 10
	9	[22]	NEWTABLE 	5 0 1
	10	[22]	SETTABLE 	5 -7 -8	; "_type" "string"
	11	[22]	SETTABLE 	4 -3 5	; "rockspec_format" -
	12	[23]	NEWTABLE 	5 0 2
	13	[23]	SETTABLE 	5 -7 -8	; "_type" "string"
	14	[23]	SETTABLE 	5 -10 -11	; "_mandatory" true
	15	[23]	SETTABLE 	4 -9 5	; "package" -
	16	[24]	NEWTABLE 	5 0 3
	17	[24]	SETTABLE 	5 -7 -8	; "_type" "string"
	18	[24]	SETTABLE 	5 -13 -14	; "_pattern" "[%w.]+-[%d]+"
	19	[24]	SETTABLE 	5 -10 -11	; "_mandatory" true
	20	[24]	SETTABLE 	4 -12 5	; "version" -
	21	[25]	NEWTABLE 	5 0 5
	22	[26]	NEWTABLE 	6 0 1
	23	[26]	SETTABLE 	6 -7 -8	; "_type" "string"
	24	[26]	SETTABLE 	5 -16 6	; "summary" -
	25	[27]	NEWTABLE 	6 0 1
	26	[27]	SETTABLE 	6 -7 -8	; "_type" "string"
	27	[27]	SETTABLE 	5 -17 6	; "detailed" -
	28	[28]	NEWTABLE 	6 0 1
	29	[28]	SETTABLE 	6 -7 -8	; "_type" "string"
	30	[28]	SETTABLE 	5 -18 6	; "homepage" -
	31	[29]	NEWTABLE 	6 0 1
	32	[29]	SETTABLE 	6 -7 -8	; "_type" "string"
	33	[29]	SETTABLE 	5 -19 6	; "license" -
	34	[30]	NEWTABLE 	6 0 1
	35	[30]	SETTABLE 	6 -7 -8	; "_type" "string"
	36	[30]	SETTABLE 	5 -20 6	; "maintainer" -
	37	[31]	SETTABLE 	4 -15 5	; "description" -
	38	[32]	NEWTABLE 	5 0 2
	39	[33]	GETTABLE 	6 1 -23	; "MAGIC_PLATFORMS"
	40	[33]	SETTABLE 	5 -22 6	; "platforms" -
	41	[34]	NEWTABLE 	6 0 3
	42	[35]	SETTABLE 	6 -7 -8	; "_type" "string"
	43	[36]	SETTABLE 	6 -25 -26	; "_name" "a valid dependency string"
	44	[37]	SETTABLE 	6 -13 -27	; "_pattern" "%s*([a-zA-Z0-9][a-zA-Z0-9%.%-%_]*)%s*([^/]*)"
	45	[38]	SETTABLE 	5 -24 6	; "_any" -
	46	[39]	SETTABLE 	4 -21 5	; "dependencies" -
	47	[40]	NEWTABLE 	5 0 1
	48	[41]	NEWTABLE 	6 0 1
	49	[41]	SETTABLE 	6 -7 -8	; "_type" "string"
	50	[41]	SETTABLE 	5 -24 6	; "_any" -
	51	[42]	SETTABLE 	4 -28 5	; "supported_platforms" -
	52	[43]	NEWTABLE 	5 0 2
	53	[44]	GETTABLE 	6 1 -23	; "MAGIC_PLATFORMS"
	54	[44]	SETTABLE 	5 -22 6	; "platforms" -
	55	[45]	NEWTABLE 	6 0 3
	56	[46]	NEWTABLE 	7 0 1
	57	[46]	SETTABLE 	7 -7 -8	; "_type" "string"
	58	[46]	SETTABLE 	6 -30 7	; "program" -
	59	[47]	NEWTABLE 	7 0 1
	60	[47]	SETTABLE 	7 -7 -8	; "_type" "string"
	61	[47]	SETTABLE 	6 -31 7	; "header" -
	62	[48]	NEWTABLE 	7 0 1
	63	[48]	SETTABLE 	7 -7 -8	; "_type" "string"
	64	[48]	SETTABLE 	6 -32 7	; "library" -
	65	[49]	SETTABLE 	5 -24 6	; "_any" -
	66	[50]	SETTABLE 	4 -29 5	; "external_dependencies" -
	67	[51]	NEWTABLE 	5 0 11
	68	[52]	SETTABLE 	5 -10 -11	; "_mandatory" true
	69	[53]	GETTABLE 	6 1 -23	; "MAGIC_PLATFORMS"
	70	[53]	SETTABLE 	5 -22 6	; "platforms" -
	71	[54]	NEWTABLE 	6 0 2
	72	[54]	SETTABLE 	6 -7 -8	; "_type" "string"
	73	[54]	SETTABLE 	6 -10 -11	; "_mandatory" true
	74	[54]	SETTABLE 	5 -34 6	; "url" -
	75	[55]	NEWTABLE 	6 0 1
	76	[55]	SETTABLE 	6 -7 -8	; "_type" "string"
	77	[55]	SETTABLE 	5 -35 6	; "md5" -
	78	[56]	NEWTABLE 	6 0 1
	79	[56]	SETTABLE 	6 -7 -8	; "_type" "string"
	80	[56]	SETTABLE 	5 -36 6	; "file" -
	81	[57]	NEWTABLE 	6 0 1
	82	[57]	SETTABLE 	6 -7 -8	; "_type" "string"
	83	[57]	SETTABLE 	5 -37 6	; "dir" -
	84	[58]	NEWTABLE 	6 0 1
	85	[58]	SETTABLE 	6 -7 -8	; "_type" "string"
	86	[58]	SETTABLE 	5 -38 6	; "tag" -
	87	[59]	NEWTABLE 	6 0 1
	88	[59]	SETTABLE 	6 -7 -8	; "_type" "string"
	89	[59]	SETTABLE 	5 -39 6	; "branch" -
	90	[60]	NEWTABLE 	6 0 1
	91	[60]	SETTABLE 	6 -7 -8	; "_type" "string"
	92	[60]	SETTABLE 	5 -40 6	; "module" -
	93	[61]	NEWTABLE 	6 0 1
	94	[61]	SETTABLE 	6 -7 -8	; "_type" "string"
	95	[61]	SETTABLE 	5 -41 6	; "cvs_tag" -
	96	[62]	NEWTABLE 	6 0 1
	97	[62]	SETTABLE 	6 -7 -8	; "_type" "string"
	98	[62]	SETTABLE 	5 -42 6	; "cvs_module" -
	99	[63]	SETTABLE 	4 -33 5	; "source" -
	100	[64]	NEWTABLE 	5 0 6
	101	[65]	GETTABLE 	6 1 -23	; "MAGIC_PLATFORMS"
	102	[65]	SETTABLE 	5 -22 6	; "platforms" -
	103	[66]	NEWTABLE 	6 0 1
	104	[66]	SETTABLE 	6 -7 -8	; "_type" "string"
	105	[66]	SETTABLE 	5 -44 6	; "type" -
	106	[67]	NEWTABLE 	6 0 4
	107	[68]	NEWTABLE 	7 0 1
	108	[69]	SETTABLE 	7 -47 -11	; "_more" true
	109	[70]	SETTABLE 	6 -46 7	; "lua" -
	110	[71]	NEWTABLE 	7 0 1
	111	[72]	SETTABLE 	7 -47 -11	; "_more" true
	112	[73]	SETTABLE 	6 -48 7	; "lib" -
	113	[74]	NEWTABLE 	7 0 1
	114	[75]	SETTABLE 	7 -47 -11	; "_more" true
	115	[76]	SETTABLE 	6 -49 7	; "conf" -
	116	[77]	NEWTABLE 	7 0 1
	117	[78]	SETTABLE 	7 -47 -11	; "_more" true
	118	[79]	SETTABLE 	6 -50 7	; "bin" -
	119	[80]	SETTABLE 	5 -45 6	; "install" -
	120	[81]	NEWTABLE 	6 0 1
	121	[82]	NEWTABLE 	7 0 1
	122	[82]	SETTABLE 	7 -7 -8	; "_type" "string"
	123	[82]	SETTABLE 	6 -24 7	; "_any" -
	124	[83]	SETTABLE 	5 -51 6	; "copy_directories" -
	125	[84]	SETTABLE 	5 -47 -11	; "_more" true
	126	[85]	SETTABLE 	5 -10 -11	; "_mandatory" true
	127	[86]	SETTABLE 	4 -43 5	; "build" -
	128	[87]	NEWTABLE 	5 0 2
	129	[88]	GETTABLE 	6 1 -23	; "MAGIC_PLATFORMS"
	130	[88]	SETTABLE 	5 -22 6	; "platforms" -
	131	[89]	NEWTABLE 	6 0 1
	132	[89]	SETTABLE 	6 -7 -8	; "_type" "string"
	133	[89]	SETTABLE 	5 -53 6	; "post_install" -
	134	[90]	SETTABLE 	4 -52 5	; "hooks" -
	135	[91]	SETTABLE 	3 -6 4	; "1.0" -
	136	[93]	NEWTABLE 	4 0 1
	137	[94]	NEWTABLE 	5 0 1
	138	[95]	NEWTABLE 	6 0 1
	139	[95]	SETTABLE 	6 -7 -57	; "_type" "boolean"
	140	[95]	SETTABLE 	5 -56 6	; "wrap_bin_scripts" -
	141	[96]	SETTABLE 	4 -55 5	; "deploy" -
	142	[97]	SETTABLE 	3 -54 4	; "1.1" -
	143	[99]	NEWTABLE 	4 0 6
	144	[100]	NEWTABLE 	5 0 2
	145	[101]	NEWTABLE 	6 0 1
	146	[102]	NEWTABLE 	7 0 1
	147	[102]	SETTABLE 	7 -7 -8	; "_type" "string"
	148	[102]	SETTABLE 	6 -24 7	; "_any" -
	149	[103]	SETTABLE 	5 -58 6	; "labels" -
	150	[104]	NEWTABLE 	6 0 1
	151	[104]	SETTABLE 	6 -7 -8	; "_type" "string"
	152	[104]	SETTABLE 	5 -59 6	; "issues_url" -
	153	[105]	SETTABLE 	4 -15 5	; "description" -
	154	[106]	NEWTABLE 	5 0 1
	155	[107]	NEWTABLE 	6 0 1
	156	[108]	SETTABLE 	6 -13 -60	; "_pattern" "%s*([a-zA-Z0-9%.%-%_]*/?[a-zA-Z0-9][a-zA-Z0-9%.%-%_]*)%s*([^/]*)"
	157	[109]	SETTABLE 	5 -24 6	; "_any" -
	158	[110]	SETTABLE 	4 -21 5	; "dependencies" -
	159	[111]	NEWTABLE 	5 0 2
	160	[112]	GETTABLE 	6 1 -23	; "MAGIC_PLATFORMS"
	161	[112]	SETTABLE 	5 -22 6	; "platforms" -
	162	[113]	NEWTABLE 	6 0 3
	163	[114]	SETTABLE 	6 -7 -8	; "_type" "string"
	164	[115]	SETTABLE 	6 -25 -26	; "_name" "a valid dependency string"
	165	[116]	SETTABLE 	6 -13 -60	; "_pattern" "%s*([a-zA-Z0-9%.%-%_]*/?[a-zA-Z0-9][a-zA-Z0-9%.%-%_]*)%s*([^/]*)"
	166	[117]	SETTABLE 	5 -24 6	; "_any" -
	167	[118]	SETTABLE 	4 -61 5	; "build_dependencies" -
	168	[119]	NEWTABLE 	5 0 2
	169	[120]	GETTABLE 	6 1 -23	; "MAGIC_PLATFORMS"
	170	[120]	SETTABLE 	5 -22 6	; "platforms" -
	171	[121]	NEWTABLE 	6 0 3
	172	[122]	SETTABLE 	6 -7 -8	; "_type" "string"
	173	[123]	SETTABLE 	6 -25 -26	; "_name" "a valid dependency string"
	174	[124]	SETTABLE 	6 -13 -60	; "_pattern" "%s*([a-zA-Z0-9%.%-%_]*/?[a-zA-Z0-9][a-zA-Z0-9%.%-%_]*)%s*([^/]*)"
	175	[125]	SETTABLE 	5 -24 6	; "_any" -
	176	[126]	SETTABLE 	4 -62 5	; "test_dependencies" -
	177	[127]	NEWTABLE 	5 0 1
	178	[128]	SETTABLE 	5 -10 -63	; "_mandatory" false
	179	[129]	SETTABLE 	4 -43 5	; "build" -
	180	[130]	NEWTABLE 	5 0 3
	181	[131]	GETTABLE 	6 1 -23	; "MAGIC_PLATFORMS"
	182	[131]	SETTABLE 	5 -22 6	; "platforms" -
	183	[132]	NEWTABLE 	6 0 1
	184	[132]	SETTABLE 	6 -7 -8	; "_type" "string"
	185	[132]	SETTABLE 	5 -44 6	; "type" -
	186	[133]	SETTABLE 	5 -47 -11	; "_more" true
	187	[134]	SETTABLE 	4 -64 5	; "test" -
	188	[135]	SETTABLE 	3 -4 4	; "3.0" -
	189	[20]	CALL     	2 2 3
	190	[138]	NEWTABLE 	4 13 0
	191	[138]	LOADK    	5 -3	; "rockspec_format"
	192	[138]	LOADK    	6 -9	; "package"
	193	[138]	LOADK    	7 -12	; "version"
	194	[138]	NEWTABLE 	8 2 0
	195	[139]	LOADK    	9 -33	; "source"
	196	[139]	NEWTABLE 	10 4 0
	197	[139]	LOADK    	11 -34	; "url"
	198	[139]	LOADK    	12 -38	; "tag"
	199	[139]	LOADK    	13 -39	; "branch"
	200	[139]	LOADK    	14 -35	; "md5"
	201	[139]	SETLIST  	10 4 1	; 1
	202	[139]	SETLIST  	8 2 1	; 1
	203	[139]	NEWTABLE 	9 2 0
	204	[140]	LOADK    	10 -15	; "description"
	205	[140]	NEWTABLE 	11 4 0
	206	[140]	LOADK    	12 -16	; "summary"
	207	[140]	LOADK    	13 -17	; "detailed"
	208	[140]	LOADK    	14 -18	; "homepage"
	209	[140]	LOADK    	15 -19	; "license"
	210	[140]	SETLIST  	11 4 1	; 1
	211	[140]	SETLIST  	9 2 1	; 1
	212	[141]	LOADK    	10 -28	; "supported_platforms"
	213	[141]	LOADK    	11 -21	; "dependencies"
	214	[141]	LOADK    	12 -61	; "build_dependencies"
	215	[141]	LOADK    	13 -29	; "external_dependencies"
	216	[141]	NEWTABLE 	14 2 0
	217	[142]	LOADK    	15 -43	; "build"
	218	[142]	NEWTABLE 	16 4 0
	219	[142]	LOADK    	17 -44	; "type"
	220	[142]	LOADK    	18 -66	; "modules"
	221	[142]	LOADK    	19 -51	; "copy_directories"
	222	[142]	LOADK    	20 -22	; "platforms"
	223	[142]	SETLIST  	16 4 1	; 1
	224	[142]	SETLIST  	14 2 1	; 1
	225	[143]	LOADK    	15 -62	; "test_dependencies"
	226	[143]	NEWTABLE 	16 2 0
	227	[143]	LOADK    	17 -64	; "test"
	228	[143]	NEWTABLE 	18 1 0
	229	[143]	LOADK    	19 -44	; "type"
	230	[143]	SETLIST  	18 1 1	; 1
	231	[143]	SETLIST  	16 2 1	; 1
	232	[144]	LOADK    	17 -52	; "hooks"
	233	[144]	SETLIST  	4 13 1	; 1
	234	[144]	SETTABLE 	0 -65 4	; "order" -
	235	[160]	CLOSURE  	4 0	; 0x7f8e65c073c0
	236	[160]	MOVE     	0 2
	237	[160]	MOVE     	0 1
	238	[197]	CLOSURE  	5 1	; 0x7f8e65c07720
	239	[197]	MOVE     	0 4
	240	[197]	MOVE     	0 3
	241	[168]	SETTABLE 	0 -67 5	; "check" -
	242	[199]	RETURN   	0 2
	243	[199]	RETURN   	0 1

function <./type/rockspec.lua:146,160> (34 instructions, 136 bytes at 0x7f8e65c073c0)
3 params, 11 slots, 2 upvalues, 6 locals, 4 constants, 0 functions
	1	[147]	GETUPVAL 	3 0	; rockspec_formats
	2	[147]	GETTABLE 	3 3 2
	3	[148]	TEST     	3 0 1
	4	[148]	JMP      	5	; to 10
	5	[149]	LOADNIL  	4 4
	6	[149]	LOADK    	5 -1	; "unknown rockspec format "
	7	[149]	MOVE     	6 2
	8	[149]	CONCAT   	5 5 6
	9	[149]	RETURN   	4 3
	10	[151]	GETUPVAL 	4 1	; type_check
	11	[151]	GETTABLE 	4 4 -2	; "check_undeclared_globals"
	12	[151]	MOVE     	5 1
	13	[151]	MOVE     	6 3
	14	[151]	CALL     	4 3 3
	15	[152]	TEST     	4 0 0
	16	[152]	JMP      	9	; to 26
	17	[153]	GETUPVAL 	6 1	; type_check
	18	[153]	GETTABLE 	6 6 -3	; "type_check_table"
	19	[153]	MOVE     	7 2
	20	[153]	MOVE     	8 0
	21	[153]	MOVE     	9 3
	22	[153]	LOADK    	10 -4	; ""
	23	[153]	CALL     	6 5 3
	24	[153]	MOVE     	5 7
	25	[153]	MOVE     	4 6
	26	[155]	TEST     	4 0 0
	27	[155]	JMP      	3	; to 31
	28	[156]	LOADBOOL 	6 1 0
	29	[156]	RETURN   	6 2
	30	[156]	JMP      	3	; to 34
	31	[158]	LOADNIL  	6 6
	32	[158]	MOVE     	7 5
	33	[158]	RETURN   	6 3
	34	[160]	RETURN   	0 1

function <./type/rockspec.lua:168,197> (61 instructions, 244 bytes at 0x7f8e65c07720)
2 params, 22 slots, 2 upvalues, 13 locals, 12 constants, 0 functions
	1	[169]	GETGLOBAL	2 -1	; assert
	2	[169]	GETGLOBAL	3 -2	; type
	3	[169]	MOVE     	4 0
	4	[169]	CALL     	3 2 2
	5	[169]	EQ       	1 3 -3	; - "table"
	6	[169]	JMP      	1	; to 8
	7	[169]	LOADBOOL 	3 0 1
	8	[169]	LOADBOOL 	3 1 0
	9	[169]	CALL     	2 2 1
	10	[171]	GETTABLE 	2 0 -4	; "rockspec_format"
	11	[171]	TEST     	2 0 1
	12	[171]	JMP      	1	; to 14
	13	[171]	LOADK    	2 -5	; "1.0"
	14	[172]	GETUPVAL 	3 0	; check_rockspec_using_version
	15	[172]	MOVE     	4 0
	16	[172]	MOVE     	5 1
	17	[172]	MOVE     	6 2
	18	[172]	CALL     	3 4 3
	19	[173]	TEST     	3 0 0
	20	[173]	JMP      	2	; to 23
	21	[174]	LOADBOOL 	5 1 0
	22	[174]	RETURN   	5 2
	23	[180]	LOADBOOL 	5 0 0
	24	[181]	GETGLOBAL	6 -6	; ipairs
	25	[181]	GETUPVAL 	7 1	; versions
	26	[181]	CALL     	6 2 4
	27	[181]	JMP      	24	; to 52
	28	[182]	TEST     	5 0 1
	29	[182]	JMP      	4	; to 34
	30	[183]	EQ       	0 10 2
	31	[183]	JMP      	20	; to 52
	32	[184]	LOADBOOL 	5 1 0
	33	[185]	JMP      	18	; to 52
	34	[187]	GETUPVAL 	11 0	; check_rockspec_using_version
	35	[187]	MOVE     	12 0
	36	[187]	MOVE     	13 1
	37	[187]	MOVE     	14 10
	38	[187]	CALL     	11 4 3
	39	[188]	TEST     	11 0 0
	40	[188]	JMP      	11	; to 52
	41	[189]	LOADNIL  	13 13
	42	[189]	MOVE     	14 4
	43	[189]	LOADK    	15 -7	; " (using rockspec format "
	44	[189]	MOVE     	16 2
	45	[189]	LOADK    	17 -8	; " -- "
	46	[190]	LOADK    	18 -9	; "adding 'rockspec_format = \""
	47	[190]	MOVE     	19 10
	48	[190]	LOADK    	20 -10	; "\"' to the rockspec "
	49	[191]	LOADK    	21 -11	; "will fix this)"
	50	[191]	CONCAT   	14 14 21
	51	[191]	RETURN   	13 3
	52	[181]	TFORLOOP 	6 2
	53	[193]	JMP      	-26	; to 28
	54	[196]	LOADNIL  	6 6
	55	[196]	MOVE     	7 4
	56	[196]	LOADK    	8 -7	; " (using rockspec format "
	57	[196]	MOVE     	9 2
	58	[196]	LOADK    	10 -12	; ")"
	59	[196]	CONCAT   	7 7 10
	60	[196]	RETURN   	6 3
	61	[197]	RETURN   	0 1
