
main <./rockspecs.lua:0,0> (46 instructions, 184 bytes at 0x7ffa32c068a0)
0+ params, 13 slots, 0 upvalues, 12 locals, 11 constants, 5 functions
	1	[1]	NEWTABLE 	0 0 0
	2	[3]	GETGLOBAL	1 -1	; require
	3	[3]	LOADK    	2 -2	; "luarocks.core.cfg"
	4	[3]	CALL     	1 2 2
	5	[4]	GETGLOBAL	2 -1	; require
	6	[4]	LOADK    	3 -3	; "luarocks.dir"
	7	[4]	CALL     	2 2 2
	8	[5]	GETGLOBAL	3 -1	; require
	9	[5]	LOADK    	4 -4	; "luarocks.path"
	10	[5]	CALL     	3 2 2
	11	[6]	GETGLOBAL	4 -1	; require
	12	[6]	LOADK    	5 -5	; "luarocks.queries"
	13	[6]	CALL     	4 2 2
	14	[7]	GETGLOBAL	5 -1	; require
	15	[7]	LOADK    	6 -6	; "luarocks.type.rockspec"
	16	[7]	CALL     	5 2 2
	17	[8]	GETGLOBAL	6 -1	; require
	18	[8]	LOADK    	7 -7	; "luarocks.util"
	19	[8]	CALL     	6 2 2
	20	[9]	GETGLOBAL	7 -1	; require
	21	[9]	LOADK    	8 -8	; "luarocks.core.vers"
	22	[9]	CALL     	7 2 2
	23	[11]	NEWTABLE 	8 0 0
	24	[13]	SETTABLE 	8 -9 8	; "__index" -
	25	[17]	CLOSURE  	9 0	; 0x7ffa32c06f60
	26	[15]	SETTABLE 	8 -10 9	; "type" -
	27	[46]	CLOSURE  	9 1	; 0x7ffa32c071f0
	28	[46]	MOVE     	0 1
	29	[46]	MOVE     	0 6
	30	[61]	CLOSURE  	10 2	; 0x7ffa32c06610
	31	[61]	MOVE     	0 4
	32	[80]	CLOSURE  	11 3	; 0x7ffa32c07a20
	33	[80]	MOVE     	0 1
	34	[80]	MOVE     	0 3
	35	[159]	CLOSURE  	12 4	; 0x7ffa32c07060
	36	[159]	MOVE     	0 7
	37	[159]	MOVE     	0 5
	38	[159]	MOVE     	0 9
	39	[159]	MOVE     	0 2
	40	[159]	MOVE     	0 6
	41	[159]	MOVE     	0 10
	42	[159]	MOVE     	0 11
	43	[159]	MOVE     	0 8
	44	[82]	SETTABLE 	0 -11 12	; "from_persisted_table" -
	45	[161]	RETURN   	0 2
	46	[161]	RETURN   	0 1

function <./rockspecs.lua:15,17> (3 instructions, 12 bytes at 0x7ffa32c06f60)
0 params, 2 slots, 0 upvalues, 0 locals, 1 constant, 0 functions
	1	[16]	LOADK    	0 -1	; "rockspec"
	2	[16]	RETURN   	0 2
	3	[17]	RETURN   	0 1

function <./rockspecs.lua:32,46> (34 instructions, 136 bytes at 0x7ffa32c071f0)
1 param, 9 slots, 2 upvalues, 6 locals, 7 constants, 0 functions
	1	[33]	GETGLOBAL	1 -1	; assert
	2	[33]	GETGLOBAL	2 -2	; type
	3	[33]	MOVE     	3 0
	4	[33]	CALL     	2 2 2
	5	[33]	EQ       	1 2 -3	; - "table"
	6	[33]	JMP      	3	; to 10
	7	[33]	NOT      	2 0
	8	[33]	JMP      	2	; to 11
	9	[33]	LOADBOOL 	2 0 1
	10	[33]	LOADBOOL 	2 1 0
	11	[33]	CALL     	1 2 1
	12	[35]	TEST     	0 0 1
	13	[35]	JMP      	1	; to 15
	14	[35]	RETURN   	0 1
	15	[37]	GETTABLE 	1 0 -4	; "platforms"
	16	[37]	TEST     	1 0 0
	17	[37]	JMP      	15	; to 33
	18	[38]	GETUPVAL 	1 0	; cfg
	19	[38]	GETTABLE 	1 1 -5	; "each_platform"
	20	[38]	CALL     	1 1 4
	21	[38]	JMP      	9	; to 31
	22	[39]	GETTABLE 	5 0 -4	; "platforms"
	23	[39]	GETTABLE 	5 5 4
	24	[40]	TEST     	5 0 0
	25	[40]	JMP      	5	; to 31
	26	[41]	GETUPVAL 	6 1	; util
	27	[41]	GETTABLE 	6 6 -6	; "deep_merge"
	28	[41]	MOVE     	7 0
	29	[41]	MOVE     	8 5
	30	[41]	CALL     	6 3 1
	31	[38]	TFORLOOP 	1 1
	32	[42]	JMP      	-11	; to 22
	33	[45]	SETTABLE 	0 -4 -7	; "platforms" nil
	34	[46]	RETURN   	0 1

function <./rockspecs.lua:48,61> (34 instructions, 136 bytes at 0x7ffa32c06610)
2 params, 14 slots, 1 upvalue, 8 locals, 5 constants, 0 functions
	1	[49]	GETTABLE 	2 0 1
	2	[49]	TEST     	2 0 0
	3	[49]	JMP      	26	; to 30
	4	[50]	LOADK    	2 -1	; 1
	5	[50]	GETTABLE 	3 0 1
	6	[50]	LEN      	3 3
	7	[50]	LOADK    	4 -1	; 1
	8	[50]	FORPREP  	2 19	; to 28
	9	[51]	GETUPVAL 	6 0	; queries
	10	[51]	GETTABLE 	6 6 -2	; "from_dep_string"
	11	[51]	GETTABLE 	7 0 1
	12	[51]	GETTABLE 	7 7 5
	13	[51]	CALL     	6 2 3
	14	[52]	TEST     	6 0 1
	15	[52]	JMP      	10	; to 26
	16	[53]	LOADNIL  	8 8
	17	[53]	LOADK    	9 -3	; "Parse error processing dependency '"
	18	[53]	GETTABLE 	10 0 1
	19	[53]	GETTABLE 	10 10 5
	20	[53]	LOADK    	11 -4	; "': "
	21	[53]	GETGLOBAL	12 -5	; tostring
	22	[53]	MOVE     	13 7
	23	[53]	CALL     	12 2 2
	24	[53]	CONCAT   	9 9 12
	25	[53]	RETURN   	8 3
	26	[55]	GETTABLE 	8 0 1
	27	[55]	SETTABLE 	8 5 6
	28	[50]	FORLOOP  	2 -20	; to 9
	29	[56]	JMP      	2	; to 32
	30	[58]	NEWTABLE 	2 0 0
	31	[58]	SETTABLE 	0 1 2
	32	[60]	LOADBOOL 	2 1 0
	33	[60]	RETURN   	2 2
	34	[61]	RETURN   	0 1

function <./rockspecs.lua:67,80> (49 instructions, 196 bytes at 0x7ffa32c07a20)
1 param, 8 slots, 2 upvalues, 9 locals, 16 constants, 0 functions
	1	[68]	NEWTABLE 	1 0 0
	2	[69]	GETGLOBAL	2 -1	; pairs
	3	[69]	GETUPVAL 	3 0	; cfg
	4	[69]	GETTABLE 	3 3 -2	; "variables"
	5	[69]	CALL     	2 2 4
	6	[69]	JMP      	1	; to 8
	7	[70]	SETTABLE 	1 5 6
	8	[69]	TFORLOOP 	2 2
	9	[70]	JMP      	-3	; to 7
	10	[72]	GETTABLE 	2 0 -3	; "name"
	11	[72]	GETTABLE 	3 0 -4	; "version"
	12	[73]	GETUPVAL 	4 1	; path
	13	[73]	GETTABLE 	4 4 -6	; "install_dir"
	14	[73]	MOVE     	5 2
	15	[73]	MOVE     	6 3
	16	[73]	CALL     	4 3 2
	17	[73]	SETTABLE 	1 -5 4	; "PREFIX" -
	18	[74]	GETUPVAL 	4 1	; path
	19	[74]	GETTABLE 	4 4 -8	; "lua_dir"
	20	[74]	MOVE     	5 2
	21	[74]	MOVE     	6 3
	22	[74]	CALL     	4 3 2
	23	[74]	SETTABLE 	1 -7 4	; "LUADIR" -
	24	[75]	GETUPVAL 	4 1	; path
	25	[75]	GETTABLE 	4 4 -10	; "lib_dir"
	26	[75]	MOVE     	5 2
	27	[75]	MOVE     	6 3
	28	[75]	CALL     	4 3 2
	29	[75]	SETTABLE 	1 -9 4	; "LIBDIR" -
	30	[76]	GETUPVAL 	4 1	; path
	31	[76]	GETTABLE 	4 4 -12	; "conf_dir"
	32	[76]	MOVE     	5 2
	33	[76]	MOVE     	6 3
	34	[76]	CALL     	4 3 2
	35	[76]	SETTABLE 	1 -11 4	; "CONFDIR" -
	36	[77]	GETUPVAL 	4 1	; path
	37	[77]	GETTABLE 	4 4 -14	; "bin_dir"
	38	[77]	MOVE     	5 2
	39	[77]	MOVE     	6 3
	40	[77]	CALL     	4 3 2
	41	[77]	SETTABLE 	1 -13 4	; "BINDIR" -
	42	[78]	GETUPVAL 	4 1	; path
	43	[78]	GETTABLE 	4 4 -16	; "doc_dir"
	44	[78]	MOVE     	5 2
	45	[78]	MOVE     	6 3
	46	[78]	CALL     	4 3 2
	47	[78]	SETTABLE 	1 -15 4	; "DOCDIR" -
	48	[79]	SETTABLE 	0 -2 1	; "variables" -
	49	[80]	RETURN   	0 1

function <./rockspecs.lua:82,159> (248 instructions, 992 bytes at 0x7ffa32c07060)
4 params, 17 slots, 8 upvalues, 18 locals, 49 constants, 1 function
	1	[83]	GETGLOBAL	4 -1	; assert
	2	[83]	GETGLOBAL	5 -2	; type
	3	[83]	MOVE     	6 1
	4	[83]	CALL     	5 2 2
	5	[83]	EQ       	1 5 -3	; - "table"
	6	[83]	JMP      	1	; to 8
	7	[83]	LOADBOOL 	5 0 1
	8	[83]	LOADBOOL 	5 1 0
	9	[83]	CALL     	4 2 1
	10	[84]	GETGLOBAL	4 -1	; assert
	11	[84]	GETGLOBAL	5 -2	; type
	12	[84]	MOVE     	6 2
	13	[84]	CALL     	5 2 2
	14	[84]	EQ       	1 5 -3	; - "table"
	15	[84]	JMP      	3	; to 19
	16	[84]	EQ       	1 2 -4	; - nil
	17	[84]	JMP      	1	; to 19
	18	[84]	LOADBOOL 	5 0 1
	19	[84]	LOADBOOL 	5 1 0
	20	[84]	CALL     	4 2 1
	21	[85]	GETGLOBAL	4 -1	; assert
	22	[85]	GETGLOBAL	5 -2	; type
	23	[85]	MOVE     	6 0
	24	[85]	CALL     	5 2 2
	25	[85]	EQ       	1 5 -5	; - "string"
	26	[85]	JMP      	1	; to 28
	27	[85]	LOADBOOL 	5 0 1
	28	[85]	LOADBOOL 	5 1 0
	29	[85]	CALL     	4 2 1
	30	[86]	GETGLOBAL	4 -1	; assert
	31	[86]	GETGLOBAL	5 -2	; type
	32	[86]	MOVE     	6 3
	33	[86]	CALL     	5 2 2
	34	[86]	EQ       	1 5 -6	; - "boolean"
	35	[86]	JMP      	3	; to 39
	36	[86]	EQ       	1 3 -4	; - nil
	37	[86]	JMP      	1	; to 39
	38	[86]	LOADBOOL 	5 0 1
	39	[86]	LOADBOOL 	5 1 0
	40	[86]	CALL     	4 2 1
	41	[88]	GETTABLE 	4 1 -7	; "rockspec_format"
	42	[88]	TEST     	4 0 0
	43	[88]	JMP      	14	; to 58
	44	[89]	GETUPVAL 	4 0	; vers
	45	[89]	GETTABLE 	4 4 -8	; "compare_versions"
	46	[89]	GETTABLE 	5 1 -7	; "rockspec_format"
	47	[89]	GETUPVAL 	6 1	; type_rockspec
	48	[89]	GETTABLE 	6 6 -7	; "rockspec_format"
	49	[89]	CALL     	4 3 2
	50	[89]	TEST     	4 0 0
	51	[89]	JMP      	6	; to 58
	52	[90]	LOADNIL  	4 4
	53	[90]	LOADK    	5 -9	; "Rockspec format "
	54	[90]	GETTABLE 	6 1 -7	; "rockspec_format"
	55	[90]	LOADK    	7 -10	; " is not supported, please upgrade LuaRocks."
	56	[90]	CONCAT   	5 5 7
	57	[90]	RETURN   	4 3
	58	[94]	TEST     	3 0 1
	59	[94]	JMP      	12	; to 72
	60	[95]	GETUPVAL 	4 1	; type_rockspec
	61	[95]	GETTABLE 	4 4 -11	; "check"
	62	[95]	MOVE     	5 1
	63	[95]	TESTSET  	6 2 1
	64	[95]	JMP      	1	; to 66
	65	[95]	NEWTABLE 	6 0 0
	66	[95]	CALL     	4 3 3
	67	[96]	TEST     	4 0 1
	68	[96]	JMP      	3	; to 72
	69	[97]	LOADNIL  	6 6
	70	[97]	MOVE     	7 5
	71	[97]	RETURN   	6 3
	72	[106]	GETUPVAL 	4 0	; vers
	73	[106]	GETTABLE 	4 4 -12	; "parse_version"
	74	[106]	GETTABLE 	5 1 -7	; "rockspec_format"
	75	[106]	TEST     	5 0 1
	76	[106]	JMP      	1	; to 78
	77	[106]	LOADK    	5 -13	; "1.0"
	78	[106]	CALL     	4 2 2
	79	[109]	CLOSURE  	5 0	; 0x7ffa32c08750
	80	[109]	MOVE     	0 4
	81	[109]	GETUPVAL 	0 0	; vers
	82	[109]	SETTABLE 	1 -14 5	; "format_is_at_least" -
	83	[109]	CLOSE    	4
	84	[112]	GETUPVAL 	4 2	; platform_overrides
	85	[112]	GETTABLE 	5 1 -15	; "build"
	86	[112]	CALL     	4 2 1
	87	[113]	GETUPVAL 	4 2	; platform_overrides
	88	[113]	GETTABLE 	5 1 -16	; "dependencies"
	89	[113]	CALL     	4 2 1
	90	[114]	GETUPVAL 	4 2	; platform_overrides
	91	[114]	GETTABLE 	5 1 -17	; "build_dependencies"
	92	[114]	CALL     	4 2 1
	93	[115]	GETUPVAL 	4 2	; platform_overrides
	94	[115]	GETTABLE 	5 1 -18	; "test_dependencies"
	95	[115]	CALL     	4 2 1
	96	[116]	GETUPVAL 	4 2	; platform_overrides
	97	[116]	GETTABLE 	5 1 -19	; "external_dependencies"
	98	[116]	CALL     	4 2 1
	99	[117]	GETUPVAL 	4 2	; platform_overrides
	100	[117]	GETTABLE 	5 1 -20	; "source"
	101	[117]	CALL     	4 2 1
	102	[118]	GETUPVAL 	4 2	; platform_overrides
	103	[118]	GETTABLE 	5 1 -21	; "hooks"
	104	[118]	CALL     	4 2 1
	105	[119]	GETUPVAL 	4 2	; platform_overrides
	106	[119]	GETTABLE 	5 1 -22	; "test"
	107	[119]	CALL     	4 2 1
	108	[121]	GETTABLE 	4 1 -24	; "package"
	109	[121]	SELF     	4 4 -25	; "lower"
	110	[121]	CALL     	4 2 2
	111	[121]	SETTABLE 	1 -23 4	; "name" -
	112	[123]	GETUPVAL 	4 3	; dir
	113	[123]	GETTABLE 	4 4 -26	; "split_url"
	114	[123]	GETTABLE 	5 1 -20	; "source"
	115	[123]	GETTABLE 	5 5 -27	; "url"
	116	[123]	CALL     	4 2 3
	117	[124]	GETUPVAL 	6 3	; dir
	118	[124]	GETTABLE 	6 6 -28	; "is_basic_protocol"
	119	[124]	MOVE     	7 4
	120	[124]	CALL     	6 2 2
	121	[124]	TEST     	6 0 0
	122	[124]	JMP      	11	; to 134
	123	[125]	GETTABLE 	6 1 -20	; "source"
	124	[125]	GETTABLE 	7 1 -20	; "source"
	125	[125]	GETTABLE 	7 7 -29	; "file"
	126	[125]	TEST     	7 0 1
	127	[125]	JMP      	5	; to 133
	128	[125]	GETUPVAL 	7 3	; dir
	129	[125]	GETTABLE 	7 7 -30	; "base_name"
	130	[125]	GETTABLE 	8 1 -20	; "source"
	131	[125]	GETTABLE 	8 8 -27	; "url"
	132	[125]	CALL     	7 2 2
	133	[125]	SETTABLE 	6 -29 7	; "file" -
	134	[127]	GETTABLE 	6 1 -20	; "source"
	135	[127]	GETTABLE 	7 1 -20	; "source"
	136	[127]	MOVE     	8 4
	137	[127]	SETTABLE 	7 -32 5	; "pathname" -
	138	[127]	SETTABLE 	6 -31 8	; "protocol" -
	139	[130]	GETTABLE 	6 1 -20	; "source"
	140	[130]	GETTABLE 	6 6 -33	; "cvs_module"
	141	[130]	TEST     	6 0 0
	142	[130]	JMP      	4	; to 147
	143	[130]	GETTABLE 	6 1 -20	; "source"
	144	[130]	GETTABLE 	7 1 -20	; "source"
	145	[130]	GETTABLE 	7 7 -33	; "cvs_module"
	146	[130]	SETTABLE 	6 -34 7	; "module" -
	147	[131]	GETTABLE 	6 1 -20	; "source"
	148	[131]	GETTABLE 	6 6 -35	; "cvs_tag"
	149	[131]	TEST     	6 0 0
	150	[131]	JMP      	4	; to 155
	151	[131]	GETTABLE 	6 1 -20	; "source"
	152	[131]	GETTABLE 	7 1 -20	; "source"
	153	[131]	GETTABLE 	7 7 -35	; "cvs_tag"
	154	[131]	SETTABLE 	6 -36 7	; "tag" -
	155	[133]	SETTABLE 	1 -37 0	; "local_abs_filename" -
	156	[134]	GETTABLE 	6 1 -20	; "source"
	157	[134]	GETTABLE 	6 6 -29	; "file"
	158	[134]	TEST     	6 0 1
	159	[134]	JMP      	2	; to 162
	160	[134]	GETTABLE 	6 1 -20	; "source"
	161	[134]	GETTABLE 	6 6 -27	; "url"
	162	[135]	GETUPVAL 	7 3	; dir
	163	[135]	GETTABLE 	7 7 -38	; "deduce_base_dir"
	164	[135]	MOVE     	8 6
	165	[135]	CALL     	7 2 2
	166	[136]	GETTABLE 	8 1 -20	; "source"
	167	[136]	GETTABLE 	9 1 -20	; "source"
	168	[136]	GETTABLE 	9 9 -40	; "dir"
	169	[136]	EQ       	0 9 -4	; - nil
	170	[136]	JMP      	1	; to 172
	171	[136]	LOADBOOL 	9 0 1
	172	[136]	LOADBOOL 	9 1 0
	173	[136]	SETTABLE 	8 -39 9	; "dir_set" -
	174	[137]	GETTABLE 	8 1 -20	; "source"
	175	[137]	GETTABLE 	9 1 -20	; "source"
	176	[138]	GETTABLE 	9 9 -40	; "dir"
	177	[138]	TEST     	9 0 1
	178	[138]	JMP      	34	; to 213
	179	[138]	GETTABLE 	9 1 -20	; "source"
	180	[138]	GETTABLE 	9 9 -34	; "module"
	181	[139]	TEST     	9 0 1
	182	[139]	JMP      	30	; to 213
	183	[139]	SELF     	9 6 -41	; "match"
	184	[139]	LOADK    	11 -42	; "%.lua$"
	185	[139]	CALL     	9 3 2
	186	[139]	TEST     	9 0 1
	187	[139]	JMP      	5	; to 193
	188	[139]	SELF     	9 6 -41	; "match"
	189	[139]	LOADK    	11 -43	; "%.c$"
	190	[139]	CALL     	9 3 2
	191	[140]	TEST     	9 0 0
	192	[140]	JMP      	19	; to 212
	193	[140]	SELF     	9 1 -14	; "format_is_at_least"
	194	[140]	LOADK    	11 -44	; "3.0"
	195	[140]	CALL     	9 3 2
	196	[141]	TEST     	9 0 0
	197	[141]	JMP      	11	; to 209
	198	[141]	GETUPVAL 	9 3	; dir
	199	[141]	GETTABLE 	9 9 -28	; "is_basic_protocol"
	200	[141]	MOVE     	10 4
	201	[141]	CALL     	9 2 2
	202	[141]	TEST     	9 0 0
	203	[141]	JMP      	3	; to 207
	204	[141]	LOADK    	9 -45	; "."
	205	[141]	TEST     	9 0 1
	206	[141]	JMP      	6	; to 213
	207	[142]	TESTSET  	9 7 1
	208	[142]	JMP      	4	; to 213
	209	[143]	LOADK    	9 -45	; "."
	210	[143]	TEST     	9 0 1
	211	[143]	JMP      	1	; to 213
	212	[143]	MOVE     	9 7
	213	[143]	SETTABLE 	8 -40 9	; "dir" -
	214	[145]	GETUPVAL 	8 4	; util
	215	[145]	GETTABLE 	8 8 -47	; "get_rocks_provided"
	216	[145]	MOVE     	9 1
	217	[145]	CALL     	8 2 2
	218	[145]	SETTABLE 	1 -46 8	; "rocks_provided" -
	219	[147]	GETGLOBAL	8 -48	; ipairs
	220	[147]	NEWTABLE 	9 3 0
	221	[147]	LOADK    	10 -16	; "dependencies"
	222	[147]	LOADK    	11 -17	; "build_dependencies"
	223	[147]	LOADK    	12 -18	; "test_dependencies"
	224	[147]	SETLIST  	9 3 1	; 1
	225	[147]	CALL     	8 2 4
	226	[147]	JMP      	9	; to 236
	227	[148]	GETUPVAL 	13 5	; convert_dependencies
	228	[148]	MOVE     	14 1
	229	[148]	MOVE     	15 12
	230	[148]	CALL     	13 3 3
	231	[149]	TEST     	13 0 1
	232	[149]	JMP      	3	; to 236
	233	[150]	LOADNIL  	15 15
	234	[150]	MOVE     	16 14
	235	[150]	RETURN   	15 3
	236	[147]	TFORLOOP 	8 2
	237	[151]	JMP      	-11	; to 227
	238	[154]	TEST     	3 0 1
	239	[154]	JMP      	3	; to 243
	240	[155]	GETUPVAL 	8 6	; configure_paths
	241	[155]	MOVE     	9 1
	242	[155]	CALL     	8 2 1
	243	[158]	GETGLOBAL	8 -49	; setmetatable
	244	[158]	MOVE     	9 1
	245	[158]	GETUPVAL 	10 7	; rockspec_mt
	246	[158]	TAILCALL 	8 3 0
	247	[158]	RETURN   	8 0
	248	[159]	RETURN   	0 1

function <./rockspecs.lua:107,109> (11 instructions, 44 bytes at 0x7ffa32c08750)
2 params, 5 slots, 2 upvalues, 2 locals, 1 constant, 0 functions
	1	[108]	GETUPVAL 	2 0	; parsed_format
	2	[108]	GETUPVAL 	3 1	; vers
	3	[108]	GETTABLE 	3 3 -1	; "parse_version"
	4	[108]	MOVE     	4 1
	5	[108]	CALL     	3 2 2
	6	[108]	LE       	1 3 2
	7	[108]	JMP      	1	; to 9
	8	[108]	LOADBOOL 	2 0 1
	9	[108]	LOADBOOL 	2 1 0
	10	[108]	RETURN   	2 2
	11	[109]	RETURN   	0 1
