-- BYTECODE -- rockspecs.lua:15-17
0001    KSTR     0   0      ; "rockspec"
0002    RET1     0   2

-- BYTECODE -- rockspecs.lua:32-46
0001    GGET     1   0      ; "assert"
0002    GGET     2   1      ; "type"
0003    MOV      3   0
0004    CALL     2   2   2
0005    ISEQS    2   2      ; "table"
0006    JMP      2 => 0011
0007    NOT      2   0
0008    JMP      3 => 0012
0009    KPRI     2   1
0010    JMP      3 => 0012
0011 => KPRI     2   2
0012 => CALL     1   1   2
0013    IST          0
0014    JMP      1 => 0016
0015    RET0     0   1
0016 => TGETS    1   0   3  ; "platforms"
0017    ISF          1
0018    JMP      2 => 0034
0019    UGET     1   0      ; cfg
0020    TGETS    1   1   4  ; "each_platform"
0021    CALL     1   4   1
0022    JMP      4 => 0032
0023 => TGETS    5   0   3  ; "platforms"
0024    TGETV    5   5   4
0025    ISF          5
0026    JMP      6 => 0032
0027    UGET     6   1      ; util
0028    TGETS    6   6   5  ; "deep_merge"
0029    MOV      7   0
0030    MOV      8   5
0031    CALL     6   1   3
0032 => ITERC    4   2   3
0033    ITERL    4 => 0023
0034 => KPRI     1   0
0035    TSETS    1   0   3  ; "platforms"
0036    RET0     0   1

-- BYTECODE -- rockspecs.lua:48-61
0001    TGETV    2   0   1
0002    ISF          2
0003    JMP      3 => 0030
0004    KSHORT   2   1
0005    TGETV    3   0   1
0006    LEN      3   3
0007    KSHORT   4   1
0008    FORI     2 => 0029
0009 => UGET     6   0      ; queries
0010    TGETS    6   6   0  ; "from_dep_string"
0011    TGETV    7   0   1
0012    TGETV    7   7   5
0013    CALL     6   3   2
0014    IST          6
0015    JMP      8 => 0026
0016    KPRI     8   0
0017    KSTR     9   1      ; "Parse error processing dependency '"
0018    TGETV   10   0   1
0019    TGETV   10  10   5
0020    KSTR    11   2      ; "': "
0021    GGET    12   3      ; "tostring"
0022    MOV     13   7
0023    CALL    12   2   2
0024    CAT      9   9  12
0025    RET      8   3
0026 => TGETV    8   0   1
0027    TSETV    6   8   5
0028    FORL     2 => 0009
0029 => JMP      2 => 0032
0030 => TNEW     2   0
0031    TSETV    2   0   1
0032 => KPRI     2   2
0033    RET1     2   2

-- BYTECODE -- rockspecs.lua:67-80
0001    TNEW     1   0
0002    GGET     2   0      ; "pairs"
0003    UGET     3   0      ; cfg
0004    TGETS    3   3   1  ; "variables"
0005    CALL     2   4   2
0006    ISNEXT   5 => 0008
0007 => TSETV    6   1   5
0008 => ITERN    5   3   3
0009    ITERL    5 => 0007
0010    TGETS    2   0   2  ; "name"
0011    TGETS    3   0   3  ; "version"
0012    UGET     4   1      ; path
0013    TGETS    4   4   5  ; "install_dir"
0014    MOV      5   2
0015    MOV      6   3
0016    CALL     4   2   3
0017    TSETS    4   1   4  ; "PREFIX"
0018    UGET     4   1      ; path
0019    TGETS    4   4   7  ; "lua_dir"
0020    MOV      5   2
0021    MOV      6   3
0022    CALL     4   2   3
0023    TSETS    4   1   6  ; "LUADIR"
0024    UGET     4   1      ; path
0025    TGETS    4   4   9  ; "lib_dir"
0026    MOV      5   2
0027    MOV      6   3
0028    CALL     4   2   3
0029    TSETS    4   1   8  ; "LIBDIR"
0030    UGET     4   1      ; path
0031    TGETS    4   4  11  ; "conf_dir"
0032    MOV      5   2
0033    MOV      6   3
0034    CALL     4   2   3
0035    TSETS    4   1  10  ; "CONFDIR"
0036    UGET     4   1      ; path
0037    TGETS    4   4  13  ; "bin_dir"
0038    MOV      5   2
0039    MOV      6   3
0040    CALL     4   2   3
0041    TSETS    4   1  12  ; "BINDIR"
0042    UGET     4   1      ; path
0043    TGETS    4   4  15  ; "doc_dir"
0044    MOV      5   2
0045    MOV      6   3
0046    CALL     4   2   3
0047    TSETS    4   1  14  ; "DOCDIR"
0048    TSETS    1   0   1  ; "variables"
0049    RET0     0   1

-- BYTECODE -- rockspecs.lua:107-109
0001    UGET     2   0      ; parsed_format
0002    UGET     3   1      ; vers
0003    TGETS    3   3   0  ; "parse_version"
0004    MOV      4   1
0005    CALL     3   2   2
0006    ISLE     3   2
0007    JMP      2 => 0010
0008    KPRI     2   1
0009    JMP      3 => 0011
0010 => KPRI     2   2
0011 => RET1     2   2

-- BYTECODE -- rockspecs.lua:82-159
0001    GGET     4   0      ; "assert"
0002    GGET     5   1      ; "type"
0003    MOV      6   1
0004    CALL     5   2   2
0005    ISEQS    5   2      ; "table"
0006    JMP      5 => 0009
0007    KPRI     5   1
0008    JMP      6 => 0010
0009 => KPRI     5   2
0010 => CALL     4   1   2
0011    GGET     4   0      ; "assert"
0012    GGET     5   1      ; "type"
0013    MOV      6   2
0014    CALL     5   2   2
0015    ISEQS    5   2      ; "table"
0016    JMP      5 => 0021
0017    ISEQP    2   0
0018    JMP      5 => 0021
0019    KPRI     5   1
0020    JMP      6 => 0022
0021 => KPRI     5   2
0022 => CALL     4   1   2
0023    GGET     4   0      ; "assert"
0024    GGET     5   1      ; "type"
0025    MOV      6   0
0026    CALL     5   2   2
0027    ISEQS    5   3      ; "string"
0028    JMP      5 => 0031
0029    KPRI     5   1
0030    JMP      6 => 0032
0031 => KPRI     5   2
0032 => CALL     4   1   2
0033    GGET     4   0      ; "assert"
0034    GGET     5   1      ; "type"
0035    MOV      6   3
0036    CALL     5   2   2
0037    ISEQS    5   4      ; "boolean"
0038    JMP      5 => 0043
0039    ISEQP    3   0
0040    JMP      5 => 0043
0041    KPRI     5   1
0042    JMP      6 => 0044
0043 => KPRI     5   2
0044 => CALL     4   1   2
0045    TGETS    4   1   5  ; "rockspec_format"
0046    ISF          4
0047    JMP      5 => 0062
0048    UGET     4   0      ; vers
0049    TGETS    4   4   6  ; "compare_versions"
0050    TGETS    5   1   5  ; "rockspec_format"
0051    UGET     6   1      ; type_rockspec
0052    TGETS    6   6   5  ; "rockspec_format"
0053    CALL     4   2   3
0054    ISF          4
0055    JMP      5 => 0062
0056    KPRI     4   0
0057    KSTR     5   7      ; "Rockspec format "
0058    TGETS    6   1   5  ; "rockspec_format"
0059    KSTR     7   8      ; " is not supported, please upgrade LuaRoc"~
0060    CAT      5   5   7
0061    UCLO     0 => 0250
0062 => IST          3
0063    JMP      4 => 0076
0064    UGET     4   1      ; type_rockspec
0065    TGETS    4   4   9  ; "check"
0066    MOV      5   1
0067    ISTC     6   2
0068    JMP      6 => 0070
0069    TNEW     6   0
0070 => CALL     4   3   3
0071    IST          4
0072    JMP      6 => 0076
0073    KPRI     6   0
0074    MOV      7   5
0075    UCLO     0 => 0251
0076 => UGET     4   0      ; vers
0077    TGETS    4   4  10  ; "parse_version"
0078    TGETS    5   1   5  ; "rockspec_format"
0079    IST          5
0080    JMP      6 => 0082
0081    KSTR     5  11      ; "1.0"
0082 => CALL     4   2   2
0083    FNEW     5  13      ; rockspecs.lua:107
0084    TSETS    5   1  12  ; "format_is_at_least"
0085    UCLO     4 => 0086
0086 => UGET     4   2      ; platform_overrides
0087    TGETS    5   1  14  ; "build"
0088    CALL     4   1   2
0089    UGET     4   2      ; platform_overrides
0090    TGETS    5   1  15  ; "dependencies"
0091    CALL     4   1   2
0092    UGET     4   2      ; platform_overrides
0093    TGETS    5   1  16  ; "build_dependencies"
0094    CALL     4   1   2
0095    UGET     4   2      ; platform_overrides
0096    TGETS    5   1  17  ; "test_dependencies"
0097    CALL     4   1   2
0098    UGET     4   2      ; platform_overrides
0099    TGETS    5   1  18  ; "external_dependencies"
0100    CALL     4   1   2
0101    UGET     4   2      ; platform_overrides
0102    TGETS    5   1  19  ; "source"
0103    CALL     4   1   2
0104    UGET     4   2      ; platform_overrides
0105    TGETS    5   1  20  ; "hooks"
0106    CALL     4   1   2
0107    UGET     4   2      ; platform_overrides
0108    TGETS    5   1  21  ; "test"
0109    CALL     4   1   2
0110    TGETS    4   1  23  ; "package"
0111    MOV      5   4
0112    TGETS    4   4  24  ; "lower"
0113    CALL     4   2   2
0114    TSETS    4   1  22  ; "name"
0115    UGET     4   3      ; dir
0116    TGETS    4   4  25  ; "split_url"
0117    TGETS    5   1  19  ; "source"
0118    TGETS    5   5  26  ; "url"
0119    CALL     4   3   2
0120    UGET     6   3      ; dir
0121    TGETS    6   6  27  ; "is_basic_protocol"
0122    MOV      7   4
0123    CALL     6   2   2
0124    ISF          6
0125    JMP      7 => 0137
0126    TGETS    6   1  19  ; "source"
0127    TGETS    7   1  19  ; "source"
0128    TGETS    7   7  28  ; "file"
0129    IST          7
0130    JMP      8 => 0136
0131    UGET     7   3      ; dir
0132    TGETS    7   7  29  ; "base_name"
0133    TGETS    8   1  19  ; "source"
0134    TGETS    8   8  26  ; "url"
0135    CALL     7   2   2
0136 => TSETS    7   6  28  ; "file"
0137 => TGETS    6   1  19  ; "source"
0138    TGETS    7   1  19  ; "source"
0139    MOV      8   4
0140    TSETS    5   7  31  ; "pathname"
0141    TSETS    8   6  30  ; "protocol"
0142    TGETS    6   1  19  ; "source"
0143    TGETS    6   6  32  ; "cvs_module"
0144    ISF          6
0145    JMP      7 => 0150
0146    TGETS    6   1  19  ; "source"
0147    TGETS    7   1  19  ; "source"
0148    TGETS    7   7  32  ; "cvs_module"
0149    TSETS    7   6  33  ; "module"
0150 => TGETS    6   1  19  ; "source"
0151    TGETS    6   6  34  ; "cvs_tag"
0152    ISF          6
0153    JMP      7 => 0158
0154    TGETS    6   1  19  ; "source"
0155    TGETS    7   1  19  ; "source"
0156    TGETS    7   7  34  ; "cvs_tag"
0157    TSETS    7   6  35  ; "tag"
0158 => TSETS    0   1  36  ; "local_abs_filename"
0159    TGETS    6   1  19  ; "source"
0160    TGETS    6   6  28  ; "file"
0161    IST          6
0162    JMP      7 => 0165
0163    TGETS    6   1  19  ; "source"
0164    TGETS    6   6  26  ; "url"
0165 => UGET     7   3      ; dir
0166    TGETS    7   7  37  ; "deduce_base_dir"
0167    MOV      8   6
0168    CALL     7   2   2
0169    TGETS    8   1  19  ; "source"
0170    TGETS    9   1  19  ; "source"
0171    TGETS    9   9  39  ; "dir"
0172    ISNEP    9   0
0173    JMP      9 => 0176
0174    KPRI     9   1
0175    JMP     10 => 0177
0176 => KPRI     9   2
0177 => TSETS    9   8  38  ; "dir_set"
0178    TGETS    8   1  19  ; "source"
0179    TGETS    9   1  19  ; "source"
0180    TGETS    9   9  39  ; "dir"
0181    IST          9
0182    JMP     10 => 0218
0183    TGETS    9   1  19  ; "source"
0184    TGETS    9   9  33  ; "module"
0185    IST          9
0186    JMP     10 => 0218
0187    MOV     10   6
0188    TGETS    9   6  40  ; "match"
0189    KSTR    11  41      ; "%.lua$"
0190    CALL     9   2   3
0191    IST          9
0192    JMP     10 => 0199
0193    MOV     10   6
0194    TGETS    9   6  40  ; "match"
0195    KSTR    11  42      ; "%.c$"
0196    CALL     9   2   3
0197    ISF          9
0198    JMP     10 => 0217
0199 => MOV     10   1
0200    TGETS    9   1  12  ; "format_is_at_least"
0201    KSTR    11  43      ; "3.0"
0202    CALL     9   2   3
0203    ISF          9
0204    JMP     10 => 0215
0205    UGET     9   3      ; dir
0206    TGETS    9   9  27  ; "is_basic_protocol"
0207    MOV     10   4
0208    CALL     9   2   2
0209    ISF          9
0210    JMP     10 => 0213
0211    KSTR     9  44      ; "."
0212    JMP     10 => 0218
0213 => ISTC     9   7
0214    JMP      9 => 0218
0215 => KSTR     9  44      ; "."
0216    JMP     10 => 0218
0217 => MOV      9   7
0218 => TSETS    9   8  39  ; "dir"
0219    UGET     8   4      ; util
0220    TGETS    8   8  46  ; "get_rocks_provided"
0221    MOV      9   1
0222    CALL     8   2   2
0223    TSETS    8   1  45  ; "rocks_provided"
0224    GGET     8  47      ; "ipairs"
0225    TDUP     9  48
0226    CALL     8   4   2
0227    JMP     11 => 0238
0228 => UGET    13   5      ; convert_dependencies
0229    MOV     14   1
0230    MOV     15  12
0231    CALL    13   3   3
0232    IST         13
0233    JMP     15 => 0238
0234    KPRI    15   0
0235    MOV     16  14
0236    UCLO     0 => 0237
0237 => RET     15   3
0238 => ITERC   11   3   3
0239    ITERL   11 => 0228
0240    IST          3
0241    JMP      8 => 0245
0242    UGET     8   6      ; configure_paths
0243    MOV      9   1
0244    CALL     8   1   2
0245 => GGET     8  49      ; "setmetatable"
0246    MOV      9   1
0247    UGET    10   7      ; rockspec_mt
0248    UCLO     0 => 0249
0249 => CALLT    8   3
0250 => RET      4   3
0251 => RET      6   3

-- BYTECODE -- rockspecs.lua:0-161
0001    TNEW     0   0
0002    GGET     1   0      ; "require"
0003    KSTR     2   1      ; "luarocks.core.cfg"
0004    CALL     1   2   2
0005    GGET     2   0      ; "require"
0006    KSTR     3   2      ; "luarocks.dir"
0007    CALL     2   2   2
0008    GGET     3   0      ; "require"
0009    KSTR     4   3      ; "luarocks.path"
0010    CALL     3   2   2
0011    GGET     4   0      ; "require"
0012    KSTR     5   4      ; "luarocks.queries"
0013    CALL     4   2   2
0014    GGET     5   0      ; "require"
0015    KSTR     6   5      ; "luarocks.type.rockspec"
0016    CALL     5   2   2
0017    GGET     6   0      ; "require"
0018    KSTR     7   6      ; "luarocks.util"
0019    CALL     6   2   2
0020    GGET     7   0      ; "require"
0021    KSTR     8   7      ; "luarocks.core.vers"
0022    CALL     7   2   2
0023    TNEW     8   0
0024    TSETS    8   8   8  ; "__index"
0025    FNEW     9  10      ; rockspecs.lua:15
0026    TSETS    9   8   9  ; "type"
0027    FNEW     9  11      ; rockspecs.lua:32
0028    FNEW    10  12      ; rockspecs.lua:48
0029    FNEW    11  13      ; rockspecs.lua:67
0030    FNEW    12  15      ; rockspecs.lua:82
0031    TSETS   12   0  14  ; "from_persisted_table"
0032    UCLO     0 => 0033
0033 => RET1     0   2

