-- BYTECODE -- rockspec.lua:146-160
0001    UGET     3   0      ; rockspec_formats
0002    TGETV    3   3   2
0003    IST          3
0004    JMP      4 => 0010
0005    KPRI     4   0
0006    KSTR     5   0      ; "unknown rockspec format "
0007    MOV      6   2
0008    CAT      5   5   6
0009    RET      4   3
0010 => UGET     4   1      ; type_check
0011    TGETS    4   4   1  ; "check_undeclared_globals"
0012    MOV      5   1
0013    MOV      6   3
0014    CALL     4   3   3
0015    ISF          4
0016    JMP      6 => 0026
0017    UGET     6   1      ; type_check
0018    TGETS    6   6   2  ; "type_check_table"
0019    MOV      7   2
0020    MOV      8   0
0021    MOV      9   3
0022    KSTR    10   3      ; ""
0023    CALL     6   3   5
0024    MOV      5   7
0025    MOV      4   6
0026 => ISF          4
0027    JMP      6 => 0031
0028    KPRI     6   2
0029    RET1     6   2
0030    JMP      6 => 0034
0031 => KPRI     6   0
0032    MOV      7   5
0033    RET      6   3
0034 => RET0     0   1

-- BYTECODE -- rockspec.lua:168-197
0001    GGET     2   0      ; "assert"
0002    GGET     3   1      ; "type"
0003    MOV      4   0
0004    CALL     3   2   2
0005    ISEQS    3   2      ; "table"
0006    JMP      3 => 0009
0007    KPRI     3   1
0008    JMP      4 => 0010
0009 => KPRI     3   2
0010 => CALL     2   1   2
0011    TGETS    2   0   3  ; "rockspec_format"
0012    IST          2
0013    JMP      3 => 0015
0014    KSTR     2   4      ; "1.0"
0015 => UGET     3   0      ; check_rockspec_using_version
0016    MOV      4   0
0017    MOV      5   1
0018    MOV      6   2
0019    CALL     3   3   4
0020    ISF          3
0021    JMP      5 => 0024
0022    KPRI     5   2
0023    RET1     5   2
0024 => KPRI     5   1
0025    GGET     6   5      ; "ipairs"
0026    UGET     7   1      ; versions
0027    CALL     6   4   2
0028    JMP      9 => 0053
0029 => IST          5
0030    JMP     11 => 0035
0031    ISNEV   10   2
0032    JMP     11 => 0053
0033    KPRI     5   2
0034    JMP     11 => 0053
0035 => UGET    11   0      ; check_rockspec_using_version
0036    MOV     12   0
0037    MOV     13   1
0038    MOV     14  10
0039    CALL    11   3   4
0040    ISF         11
0041    JMP     13 => 0053
0042    KPRI    13   0
0043    MOV     14   4
0044    KSTR    15   6      ; " (using rockspec format "
0045    MOV     16   2
0046    KSTR    17   7      ; " -- "
0047    KSTR    18   8      ; "adding 'rockspec_format = ""
0048    MOV     19  10
0049    KSTR    20   9      ; ""' to the rockspec "
0050    KSTR    21  10      ; "will fix this)"
0051    CAT     14  14  21
0052    RET     13   3
0053 => ITERC    9   3   3
0054    ITERL    9 => 0029
0055    KPRI     6   0
0056    MOV      7   4
0057    KSTR     8   6      ; " (using rockspec format "
0058    MOV      9   2
0059    KSTR    10  11      ; ")"
0060    CAT      7   7  10
0061    RET      6   3

-- BYTECODE -- rockspec.lua:0-200
0001    TNEW     0   0
0002    GGET     1   0      ; "require"
0003    KSTR     2   1      ; "luarocks.type_check"
0004    CALL     1   2   2
0005    KSTR     2   3      ; "3.0"
0006    TSETS    2   0   2  ; "rockspec_format"
0007    TGETS    2   1   4  ; "declare_schemas"
0008    TDUP     3  82
0009    TDUP     4   6
0010    TDUP     5   5
0011    TSETS    5   4   2  ; "rockspec_format"
0012    TDUP     5   7
0013    TSETS    5   4   8  ; "package"
0014    TDUP     5   9
0015    TSETS    5   4  10  ; "version"
0016    TDUP     5  12
0017    TDUP     6  11
0018    TSETS    6   5  13  ; "summary"
0019    TDUP     6  14
0020    TSETS    6   5  15  ; "detailed"
0021    TDUP     6  16
0022    TSETS    6   5  17  ; "homepage"
0023    TDUP     6  18
0024    TSETS    6   5  19  ; "license"
0025    TDUP     6  20
0026    TSETS    6   5  21  ; "maintainer"
0027    TSETS    5   4  22  ; "description"
0028    TDUP     5  24
0029    TGETS    6   1  23  ; "MAGIC_PLATFORMS"
0030    TSETS    6   5  25  ; "platforms"
0031    TDUP     6  26
0032    TSETS    6   5  27  ; "_any"
0033    TSETS    5   4  28  ; "dependencies"
0034    TDUP     5  30
0035    TDUP     6  29
0036    TSETS    6   5  27  ; "_any"
0037    TSETS    5   4  31  ; "supported_platforms"
0038    TDUP     5  32
0039    TGETS    6   1  23  ; "MAGIC_PLATFORMS"
0040    TSETS    6   5  25  ; "platforms"
0041    TDUP     6  34
0042    TDUP     7  33
0043    TSETS    7   6  35  ; "program"
0044    TDUP     7  36
0045    TSETS    7   6  37  ; "header"
0046    TDUP     7  38
0047    TSETS    7   6  39  ; "library"
0048    TSETS    6   5  27  ; "_any"
0049    TSETS    5   4  40  ; "external_dependencies"
0050    TDUP     5  41
0051    TGETS    6   1  23  ; "MAGIC_PLATFORMS"
0052    TSETS    6   5  25  ; "platforms"
0053    TDUP     6  42
0054    TSETS    6   5  43  ; "url"
0055    TDUP     6  44
0056    TSETS    6   5  45  ; "md5"
0057    TDUP     6  46
0058    TSETS    6   5  47  ; "file"
0059    TDUP     6  48
0060    TSETS    6   5  49  ; "dir"
0061    TDUP     6  50
0062    TSETS    6   5  51  ; "tag"
0063    TDUP     6  52
0064    TSETS    6   5  53  ; "branch"
0065    TDUP     6  54
0066    TSETS    6   5  55  ; "module"
0067    TDUP     6  56
0068    TSETS    6   5  57  ; "cvs_tag"
0069    TDUP     6  58
0070    TSETS    6   5  59  ; "cvs_module"
0071    TSETS    5   4  60  ; "source"
0072    TDUP     5  61
0073    TGETS    6   1  23  ; "MAGIC_PLATFORMS"
0074    TSETS    6   5  25  ; "platforms"
0075    TDUP     6  62
0076    TSETS    6   5  63  ; "type"
0077    TDUP     6  65
0078    TDUP     7  64
0079    TSETS    7   6  66  ; "lua"
0080    TDUP     7  67
0081    TSETS    7   6  68  ; "lib"
0082    TDUP     7  69
0083    TSETS    7   6  70  ; "conf"
0084    TDUP     7  71
0085    TSETS    7   6  72  ; "bin"
0086    TSETS    6   5  73  ; "install"
0087    TDUP     6  75
0088    TDUP     7  74
0089    TSETS    7   6  27  ; "_any"
0090    TSETS    6   5  76  ; "copy_directories"
0091    TSETS    5   4  77  ; "build"
0092    TDUP     5  78
0093    TGETS    6   1  23  ; "MAGIC_PLATFORMS"
0094    TSETS    6   5  25  ; "platforms"
0095    TDUP     6  79
0096    TSETS    6   5  80  ; "post_install"
0097    TSETS    5   4  81  ; "hooks"
0098    TSETS    4   3  83  ; "1.0"
0099    TDUP     4  87
0100    TDUP     5  85
0101    TDUP     6  84
0102    TSETS    6   5  86  ; "wrap_bin_scripts"
0103    TSETS    5   4  88  ; "deploy"
0104    TSETS    4   3  89  ; "1.1"
0105    TDUP     4  96
0106    TDUP     5  92
0107    TDUP     6  91
0108    TDUP     7  90
0109    TSETS    7   6  27  ; "_any"
0110    TSETS    6   5  93  ; "labels"
0111    TDUP     6  94
0112    TSETS    6   5  95  ; "issues_url"
0113    TSETS    5   4  22  ; "description"
0114    TDUP     5  98
0115    TDUP     6  97
0116    TSETS    6   5  27  ; "_any"
0117    TSETS    5   4  28  ; "dependencies"
0118    TDUP     5  99
0119    TGETS    6   1  23  ; "MAGIC_PLATFORMS"
0120    TSETS    6   5  25  ; "platforms"
0121    TDUP     6 100
0122    TSETS    6   5  27  ; "_any"
0123    TSETS    5   4 101  ; "build_dependencies"
0124    TDUP     5 102
0125    TGETS    6   1  23  ; "MAGIC_PLATFORMS"
0126    TSETS    6   5  25  ; "platforms"
0127    TDUP     6 103
0128    TSETS    6   5  27  ; "_any"
0129    TSETS    5   4 104  ; "test_dependencies"
0130    TDUP     5 105
0131    TSETS    5   4  77  ; "build"
0132    TDUP     5 106
0133    TGETS    6   1  23  ; "MAGIC_PLATFORMS"
0134    TSETS    6   5  25  ; "platforms"
0135    TDUP     6 107
0136    TSETS    6   5  63  ; "type"
0137    TSETS    5   4 108  ; "test"
0138    TSETS    4   3   3  ; "3.0"
0139    CALL     2   3   2
0140    TDUP     4 110
0141    TDUP     5 111
0142    TDUP     6 112
0143    TSETB    6   5   2
0144    TSETB    5   4   4
0145    TDUP     5 113
0146    TDUP     6 114
0147    TSETB    6   5   2
0148    TSETB    5   4   5
0149    TDUP     5 115
0150    TDUP     6 116
0151    TSETB    6   5   2
0152    TSETB    5   4  10
0153    TDUP     5 117
0154    TDUP     6 118
0155    TSETB    6   5   2
0156    TSETB    5   4  12
0157    TSETS    4   0 109  ; "order"
0158    FNEW     4 119      ; rockspec.lua:146
0159    FNEW     5 121      ; rockspec.lua:168
0160    TSETS    5   0 120  ; "check"
0161    UCLO     0 => 0162
0162 => RET1     0   2

