-- BYTECODE -- search.lua:17-31
0001    GGET     2   0      ; "assert"
0002    GGET     3   1      ; "type"
0003    MOV      4   0
0004    CALL     3   2   2
0005    ISEQS    3   2      ; "table"
0006    JMP      3 => 0009
0007    KPRI     3   1
0008    JMP      4 => 0010
0009 => KPRI     3   2
0010 => CALL     2   1   2
0011    GGET     2   0      ; "assert"
0012    MOV      4   1
0013    TGETS    3   1   1  ; "type"
0014    CALL     3   2   2
0015    ISEQS    3   3      ; "result"
0016    JMP      3 => 0019
0017    KPRI     3   1
0018    JMP      4 => 0020
0019 => KPRI     3   2
0020 => CALL     2   1   2
0021    TGETS    2   1   4  ; "name"
0022    TGETS    3   1   5  ; "version"
0023    TGETV    4   0   2
0024    IST          4
0025    JMP      4 => 0028
0026    TNEW     4   0
0027    TSETV    4   0   2
0028 => TGETV    4   0   2
0029    TGETV    4   4   3
0030    IST          4
0031    JMP      4 => 0035
0032    TGETV    4   0   2
0033    TNEW     5   0
0034    TSETV    5   4   3
0035 => GGET     4   2      ; "table"
0036    TGETS    4   4   6  ; "insert"
0037    TGETV    5   0   2
0038    TGETV    5   5   3
0039    TDUP     6   8
0040    TGETS    7   1   7  ; "arch"
0041    TSETS    7   6   7  ; "arch"
0042    TGETS    7   1   9  ; "repo"
0043    TSETS    7   6   9  ; "repo"
0044    TGETS    7   1  10  ; "namespace"
0045    TSETS    7   6  10  ; "namespace"
0046    CALL     4   1   3
0047    RET0     0   1

-- BYTECODE -- search.lua:42-49
0001    GGET     3   0      ; "assert"
0002    MOV      5   1
0003    TGETS    4   1   1  ; "type"
0004    CALL     4   2   2
0005    ISEQS    4   2      ; "result"
0006    JMP      4 => 0009
0007    KPRI     4   1
0008    JMP      5 => 0010
0009 => KPRI     4   2
0010 => CALL     3   1   2
0011    GGET     3   0      ; "assert"
0012    MOV      5   2
0013    TGETS    4   2   1  ; "type"
0014    CALL     4   2   2
0015    ISEQS    4   3      ; "query"
0016    JMP      4 => 0019
0017    KPRI     4   1
0018    JMP      5 => 0020
0019 => KPRI     4   2
0020 => CALL     3   1   2
0021    MOV      4   1
0022    TGETS    3   1   4  ; "satisfies"
0023    MOV      5   2
0024    CALL     3   2   3
0025    ISF          3
0026    JMP      4 => 0032
0027    UGET     3   0      ; search
0028    TGETS    3   3   5  ; "store_result"
0029    MOV      4   0
0030    MOV      5   1
0031    CALL     3   1   3
0032 => RET0     0   1

-- BYTECODE -- search.lua:60-89
0001    GGET     3   0      ; "assert"
0002    GGET     4   1      ; "type"
0003    MOV      5   0
0004    CALL     4   2   2
0005    ISEQS    4   2      ; "string"
0006    JMP      4 => 0009
0007    KPRI     4   1
0008    JMP      5 => 0010
0009 => KPRI     4   2
0010 => CALL     3   1   2
0011    GGET     3   0      ; "assert"
0012    MOV      5   1
0013    TGETS    4   1   1  ; "type"
0014    CALL     4   2   2
0015    ISEQS    4   3      ; "query"
0016    JMP      4 => 0019
0017    KPRI     4   1
0018    JMP      5 => 0020
0019 => KPRI     4   2
0020 => CALL     3   1   2
0021    GGET     3   0      ; "assert"
0022    GGET     4   1      ; "type"
0023    MOV      5   2
0024    CALL     4   2   2
0025    ISEQS    4   4      ; "table"
0026    JMP      4 => 0031
0027    NOT      4   2
0028    JMP      5 => 0032
0029    KPRI     4   1
0030    JMP      5 => 0032
0031 => KPRI     4   2
0032 => CALL     3   1   2
0033    GGET     3   5      ; "require"
0034    KSTR     4   6      ; "luarocks.fs"
0035    CALL     3   2   2
0036    IST          2
0037    JMP      4 => 0039
0038    TNEW     2   0
0039 => TGETS    4   3   7  ; "dir"
0040    MOV      5   0
0041    CALL     4   4   2
0042    JMP      7 => 0115
0043 => UGET     8   0      ; dir
0044    TGETS    8   8   8  ; "path"
0045    MOV      9   0
0046    MOV     10   7
0047    CALL     8   2   3
0048    UGET     9   1      ; path
0049    TGETS    9   9   9  ; "parse_name"
0050    MOV     10   7
0051    CALL     9   4   2
0052    ISF          9
0053    JMP     12 => 0079
0054    MOV     13   8
0055    TGETS   12   8  10  ; "match"
0056    KSTR    14  11      ; ".rockspec$"
0057    CALL    12   2   3
0058    IST         12
0059    JMP     13 => 0066
0060    MOV     13   8
0061    TGETS   12   8  10  ; "match"
0062    KSTR    14  12      ; ".rock$"
0063    CALL    12   2   3
0064    ISF         12
0065    JMP     13 => 0079
0066 => UGET    12   2      ; results
0067    TGETS   12  12  13  ; "new"
0068    MOV     13   9
0069    MOV     14  10
0070    MOV     15   0
0071    MOV     16  11
0072    CALL    12   2   5
0073    UGET    13   3      ; store_if_match
0074    MOV     14   2
0075    MOV     15  12
0076    MOV     16   1
0077    CALL    13   1   4
0078    JMP     12 => 0115
0079 => TGETS   12   3  14  ; "is_dir"
0080    MOV     13   8
0081    CALL    12   2   2
0082    ISF         12
0083    JMP     13 => 0115
0084    TGETS   12   3   7  ; "dir"
0085    MOV     13   8
0086    CALL    12   4   2
0087    JMP     15 => 0113
0088 => MOV     17  15
0089    TGETS   16  15  10  ; "match"
0090    KSTR    18  15      ; "-%d+$"
0091    CALL    16   2   3
0092    ISF         16
0093    JMP     17 => 0113
0094    UGET    16   1      ; path
0095    TGETS   16  16  16  ; "read_namespace"
0096    MOV     17   7
0097    MOV     18  15
0098    MOV     19   0
0099    CALL    16   2   4
0100    UGET    17   2      ; results
0101    TGETS   17  17  13  ; "new"
0102    MOV     18   7
0103    MOV     19  15
0104    MOV     20   0
0105    KSTR    21  17      ; "installed"
0106    MOV     22  16
0107    CALL    17   2   6
0108    UGET    18   3      ; store_if_match
0109    MOV     19   2
0110    MOV     20  17
0111    MOV     21   1
0112    CALL    18   1   4
0113 => ITERC   15   2   3
0114    ITERL   15 => 0088
0115 => ITERC    7   2   3
0116    ITERL    7 => 0043
0117    RET1     2   2

-- BYTECODE -- search.lua:101-125
0001    GGET     5   0      ; "assert"
0002    GGET     6   1      ; "type"
0003    MOV      7   0
0004    CALL     6   2   2
0005    ISEQS    6   2      ; "table"
0006    JMP      6 => 0009
0007    KPRI     6   1
0008    JMP      7 => 0010
0009 => KPRI     6   2
0010 => CALL     5   1   2
0011    GGET     5   0      ; "assert"
0012    GGET     6   1      ; "type"
0013    MOV      7   1
0014    CALL     6   2   2
0015    ISEQS    6   3      ; "string"
0016    JMP      6 => 0019
0017    KPRI     6   1
0018    JMP      7 => 0020
0019 => KPRI     6   2
0020 => CALL     5   1   2
0021    GGET     5   0      ; "assert"
0022    MOV      7   2
0023    TGETS    6   2   1  ; "type"
0024    CALL     6   2   2
0025    ISEQS    6   4      ; "query"
0026    JMP      6 => 0029
0027    KPRI     6   1
0028    JMP      7 => 0030
0029 => KPRI     6   2
0030 => CALL     5   1   2
0031    IST          4
0032    JMP      5 => 0040
0033    TGETS    5   2   5  ; "namespace"
0034    ISF          5
0035    JMP      6 => 0040
0036    MOV      5   1
0037    KSTR     6   6      ; "/manifests/"
0038    TGETS    7   2   5  ; "namespace"
0039    CAT      1   5   7
0040 => UGET     5   0      ; manif
0041    TGETS    5   5   7  ; "load_manifest"
0042    MOV      6   1
0043    MOV      7   3
0044    NOT      8   4
0045    CALL     5   4   4
0046    IST          5
0047    JMP      8 => 0052
0048    KPRI     8   0
0049    MOV      9   6
0050    MOV     10   7
0051    RET      8   4
0052 => GGET     8   8      ; "pairs"
0053    TGETS    9   5   9  ; "repository"
0054    CALL     8   4   2
0055    ISNEXT  11 => 0092
0056 => GGET    13   8      ; "pairs"
0057    MOV     14  12
0058    CALL    13   4   2
0059    ISNEXT  16 => 0090
0060 => ISF          4
0061    JMP     18 => 0070
0062    UGET    18   1      ; path
0063    TGETS   18  18  10  ; "read_namespace"
0064    MOV     19  11
0065    MOV     20  16
0066    MOV     21   1
0067    CALL    18   2   4
0068    IST         18
0069    JMP     19 => 0071
0070 => TGETS   18   2   5  ; "namespace"
0071 => GGET    19  11      ; "ipairs"
0072    MOV     20  17
0073    CALL    19   4   2
0074    JMP     22 => 0088
0075 => UGET    24   2      ; results
0076    TGETS   24  24  12  ; "new"
0077    MOV     25  11
0078    MOV     26  16
0079    MOV     27   1
0080    TGETS   28  23  13  ; "arch"
0081    MOV     29  18
0082    CALL    24   2   6
0083    UGET    25   3      ; store_if_match
0084    MOV     26   0
0085    MOV     27  24
0086    MOV     28   2
0087    CALL    25   1   4
0088 => ITERC   22   3   3
0089    ITERL   22 => 0075
0090 => ITERN   16   3   3
0091    ITERL   16 => 0060
0092 => ITERN   11   3   3
0093    ITERL   11 => 0056
0094    KPRI     8   2
0095    RET1     8   2

-- BYTECODE -- search.lua:127-129
0001    UGET     4   0      ; manifest_search
0002    MOV      5   0
0003    MOV      6   1
0004    MOV      7   2
0005    MOV      8   3
0006    KPRI     9   1
0007    CALLT    4   6

-- BYTECODE -- search.lua:131-133
0001    UGET     4   0      ; manifest_search
0002    MOV      5   0
0003    MOV      6   1
0004    MOV      7   2
0005    MOV      8   3
0006    KPRI     9   2
0007    CALLT    4   6

-- BYTECODE -- search.lua:141-174
0001    GGET     2   0      ; "assert"
0002    MOV      4   0
0003    TGETS    3   0   1  ; "type"
0004    CALL     3   2   2
0005    ISEQS    3   2      ; "query"
0006    JMP      3 => 0009
0007    KPRI     3   1
0008    JMP      4 => 0010
0009 => KPRI     3   2
0010 => CALL     2   1   2
0011    TNEW     2   0
0012    GGET     3   3      ; "ipairs"
0013    UGET     4   0      ; cfg
0014    TGETS    4   4   4  ; "rocks_servers"
0015    CALL     3   4   2
0016    JMP      6 => 0065
0017 => UGET     8   0      ; cfg
0018    TGETS    8   8   5  ; "disabled_servers"
0019    TGETV    8   8   7
0020    IST          8
0021    JMP      8 => 0065
0022    GGET     8   1      ; "type"
0023    MOV      9   7
0024    CALL     8   2   2
0025    ISNES    8   6      ; "string"
0026    JMP      8 => 0030
0027    TNEW     8   3
0028    TSETB    7   8   1
0029    MOV      7   8
0030 => GGET     8   3      ; "ipairs"
0031    MOV      9   7
0032    CALL     8   4   2
0033    JMP     11 => 0063
0034 => UGET    13   1      ; dir
0035    TGETS   13  13   7  ; "split_url"
0036    MOV     14  12
0037    CALL    13   3   2
0038    ISNES   13   8      ; "file"
0039    JMP     15 => 0041
0040    MOV     12  14
0041 => UGET    15   2      ; remote_manifest_search
0042    MOV     16   2
0043    MOV     17  12
0044    MOV     18   0
0045    MOV     19   1
0046    CALL    15   4   5
0047    ISNES   17   9      ; "network"
0048    JMP     18 => 0053
0049    UGET    18   0      ; cfg
0050    TGETS   18  18   5  ; "disabled_servers"
0051    KPRI    19   2
0052    TSETV   19  18   7
0053 => ISF         15
0054    JMP     18 => 0057
0055    JMP      8 => 0065
0056    JMP     18 => 0063
0057 => UGET    18   3      ; util
0058    TGETS   18  18  10  ; "warning"
0059    KSTR    19  11      ; "Failed searching manifest: "
0060    MOV     20  16
0061    CAT     19  19  20
0062    CALL    18   1   2
0063 => ITERC   11   3   3
0064    ITERL   11 => 0034
0065 => ITERC    6   3   3
0066    ITERL    6 => 0017
0067    KSTR     3  12      ; "provided by VM or rocks_provided"
0068    GGET     4  13      ; "pairs"
0069    UGET     5   3      ; util
0070    TGETS    5   5  14  ; "get_rocks_provided"
0071    CALL     5   0   1
0072    CALLM    4   4   0
0073    ISNEXT   7 => 0086
0074 => UGET     9   4      ; results
0075    TGETS    9   9  15  ; "new"
0076    MOV     10   7
0077    MOV     11   8
0078    MOV     12   3
0079    KSTR    13  16      ; "installed"
0080    CALL     9   2   5
0081    UGET    10   5      ; store_if_match
0082    MOV     11   2
0083    MOV     12   9
0084    MOV     13   0
0085    CALL    10   1   4
0086 => ITERN    7   3   3
0087    ITERL    7 => 0074
0088    RET1     2   2

-- BYTECODE -- search.lua:182-204
0001    GGET     2   0      ; "assert"
0002    GGET     3   1      ; "type"
0003    MOV      4   0
0004    CALL     3   2   2
0005    ISNES    3   2      ; "string"
0006    JMP      3 => 0013
0007    MOV      4   0
0008    TGETS    3   0   3  ; "match"
0009    KSTR     5   4      ; "/"
0010    CALL     3   2   3
0011    NOT      3   3
0012    JMP      4 => 0016
0013 => KPRI     3   1
0014    JMP      4 => 0016
0015    KPRI     3   2
0016 => CALL     2   1   2
0017    GGET     2   0      ; "assert"
0018    GGET     3   1      ; "type"
0019    MOV      4   1
0020    CALL     3   2   2
0021    ISEQS    3   5      ; "table"
0022    JMP      3 => 0025
0023    KPRI     3   1
0024    JMP      4 => 0026
0025 => KPRI     3   2
0026 => CALL     2   1   2
0027    TNEW     2   0
0028    GGET     3   6      ; "pairs"
0029    MOV      4   1
0030    CALL     3   4   2
0031    ISNEXT   6 => 0040
0032 => GGET     8   5      ; "table"
0033    TGETS    8   8   7  ; "insert"
0034    MOV      9   2
0035    UGET    10   0      ; vers
0036    TGETS   10  10   8  ; "parse_version"
0037    MOV     11   6
0038    CALL    10   0   2
0039    CALLM    8   1   1
0040 => ITERN    6   3   3
0041    ITERL    6 => 0032
0042    GGET     3   5      ; "table"
0043    TGETS    3   3   9  ; "sort"
0044    MOV      4   2
0045    CALL     3   1   2
0046    LEN      3   2
0047    TGETV    3   2   3
0048    TGETS    3   3   2  ; "string"
0049    TGETV    4   1   3
0050    ISF          4
0051    JMP      5 => 0082
0052    KSHORT   5   1
0053    GGET     6  10      ; "ipairs"
0054    MOV      7   4
0055    CALL     6   4   2
0056    JMP      9 => 0071
0057 => TGETS   11  10  11  ; "arch"
0058    ISNES   11  12      ; "src"
0059    JMP     11 => 0064
0060    TGETV   11   4   5
0061    TGETS   11  11  11  ; "arch"
0062    ISEQS   11  13      ; "rockspec"
0063    JMP     11 => 0070
0064 => TGETS   11  10  11  ; "arch"
0065    ISEQS   11  12      ; "src"
0066    JMP     11 => 0071
0067    TGETS   11  10  11  ; "arch"
0068    ISEQS   11  13      ; "rockspec"
0069    JMP     11 => 0071
0070 => MOV      5   9
0071 => ITERC    9   3   3
0072    ITERL    9 => 0057
0073    UGET     6   1      ; path
0074    TGETS    6   6  14  ; "make_url"
0075    TGETV    7   4   5
0076    TGETS    7   7  15  ; "repo"
0077    MOV      8   0
0078    MOV      9   3
0079    TGETV   10   4   5
0080    TGETS   10  10  11  ; "arch"
0081    CALLT    6   5
0082 => KPRI     5   0
0083    RET1     5   2

-- BYTECODE -- search.lua:209-223
0001    GGET     1   0      ; "assert"
0002    MOV      3   0
0003    TGETS    2   0   1  ; "type"
0004    CALL     2   2   2
0005    ISEQS    2   2      ; "query"
0006    JMP      2 => 0009
0007    KPRI     2   1
0008    JMP      3 => 0010
0009 => KPRI     2   2
0010 => CALL     1   1   2
0011    TNEW     1   0
0012    UGET     2   0      ; util
0013    TGETS    2   2   3  ; "lua_versions"
0014    CALL     2   4   1
0015    JMP      5 => 0041
0016 => UGET     6   1      ; cfg
0017    TGETS    6   6   4  ; "lua_version"
0018    ISEQV    5   6
0019    JMP      6 => 0041
0020    UGET     6   0      ; util
0021    TGETS    6   6   5  ; "printout"
0022    KSTR     7   6      ; "Checking for Lua "
0023    MOV      8   5
0024    KSTR     9   7      ; "..."
0025    CAT      7   7   9
0026    CALL     6   1   2
0027    UGET     6   2      ; search
0028    TGETS    6   6   8  ; "search_repos"
0029    MOV      7   0
0030    MOV      8   5
0031    CALL     6   2   3
0032    TGETS    7   0   9  ; "name"
0033    TGETV    6   6   7
0034    ISF          6
0035    JMP      7 => 0041
0036    GGET     6  10      ; "table"
0037    TGETS    6   6  11  ; "insert"
0038    MOV      7   1
0039    MOV      8   5
0040    CALL     6   1   3
0041 => ITERC    5   2   3
0042    ITERL    5 => 0016
0043    RET1     1   2

-- BYTECODE -- search.lua:230-251
0001    GGET     1   0      ; "assert"
0002    MOV      3   0
0003    TGETS    2   0   1  ; "type"
0004    CALL     2   2   2
0005    ISEQS    2   2      ; "query"
0006    JMP      2 => 0009
0007    KPRI     2   1
0008    JMP      3 => 0010
0009 => KPRI     2   2
0010 => CALL     1   1   2
0011    UGET     1   0      ; util
0012    TGETS    1   1   3  ; "get_rocks_provided"
0013    CALL     1   2   1
0014    TGETS    2   0   4  ; "name"
0015    TGETV    2   1   2
0016    ISEQP    2   0
0017    JMP      2 => 0028
0018    KPRI     2   0
0019    KSTR     3   5      ; "Rock "
0020    TGETS    4   0   4  ; "name"
0021    KSTR     5   6      ; " "
0022    TGETS    6   0   4  ; "name"
0023    TGETV    6   1   6
0024    KSTR     7   7      ; " is already provided by VM or via 'rocks"~
0025    CAT      3   3   7
0026    KSTR     4   8      ; "provided"
0027    RET      2   4
0028 => UGET     2   1      ; search
0029    TGETS    2   2   9  ; "search_repos"
0030    MOV      3   0
0031    CALL     2   2   2
0032    GGET     3  10      ; "next"
0033    MOV      4   2
0034    CALL     3   2   2
0035    IST          3
0036    JMP      4 => 0046
0037    KPRI     4   0
0038    KSTR     5  11      ; "No results matching query were found for"~
0039    UGET     6   2      ; cfg
0040    TGETS    6   6  12  ; "lua_version"
0041    KSTR     7  13      ; "."
0042    CAT      5   5   7
0043    KSTR     6  14      ; "notfound"
0044    RET      4   4
0045    JMP      4 => 0061
0046 => GGET     4  10      ; "next"
0047    MOV      5   2
0048    MOV      6   3
0049    CALL     4   2   3
0050    ISF          4
0051    JMP      5 => 0057
0052    KPRI     4   0
0053    KSTR     5  15      ; "Several rocks matched query."
0054    KSTR     6  16      ; "manyfound"
0055    RET      4   4
0056    JMP      4 => 0061
0057 => UGET     4   3      ; pick_latest_version
0058    TGETS    5   0   4  ; "name"
0059    TGETV    6   2   3
0060    CALLT    4   3
0061 => RET0     0   1

-- BYTECODE -- search.lua:253-260
0001    UGET     4   0      ; queries
0002    TGETS    4   4   0  ; "new"
0003    MOV      5   0
0004    MOV      6   1
0005    MOV      7   2
0006    KPRI     8   1
0007    KSTR     9   1      ; "src|rockspec"
0008    CALL     4   2   6
0009    UGET     5   1      ; search
0010    TGETS    5   5   2  ; "find_rock_checking_lua_versions"
0011    MOV      6   4
0012    MOV      7   3
0013    CALL     5   3   3
0014    IST          5
0015    JMP      7 => 0025
0016    KPRI     7   0
0017    KSTR     8   3      ; "Could not find a result named "
0018    GGET     9   4      ; "tostring"
0019    MOV     10   4
0020    CALL     9   2   2
0021    KSTR    10   5      ; ": "
0022    MOV     11   6
0023    CAT      8   8  11
0024    RET      7   3
0025 => RET1     5   2

-- BYTECODE -- search.lua:262-303
0001    UGET     2   0      ; search
0002    TGETS    2   2   0  ; "find_suitable_rock"
0003    MOV      3   0
0004    CALL     2   4   2
0005    ISF          2
0006    JMP      5 => 0008
0007    RET1     2   2
0008 => ISNES    4   1      ; "notfound"
0009    JMP      5 => 0096
0010    KPRI     5   0
0011    ISF          1
0012    JMP      6 => 0091
0013    UGET     6   1      ; util
0014    TGETS    6   6   2  ; "printout"
0015    TGETS    7   0   3  ; "name"
0016    KSTR     8   4      ; " not found for Lua "
0017    UGET     9   2      ; cfg
0018    TGETS    9   9   5  ; "lua_version"
0019    KSTR    10   6      ; "."
0020    CAT      7   7  10
0021    CALL     6   1   2
0022    UGET     6   1      ; util
0023    TGETS    6   6   2  ; "printout"
0024    KSTR     7   7      ; "Checking if available for other Lua vers"~
0025    CALL     6   1   2
0026    UGET     6   3      ; supported_lua_versions
0027    MOV      7   0
0028    CALL     6   2   2
0029    LEN      7   6
0030    ISEQN    7   0      ; 0
0031    JMP      7 => 0087
0032    GGET     7   8      ; "ipairs"
0033    MOV      8   6
0034    CALL     7   4   2
0035    JMP     10 => 0040
0036 => KSTR    12   9      ; "Lua "
0037    MOV     13  11
0038    CAT     12  12  13
0039    TSETV   12   6  10
0040 => ITERC   10   3   3
0041    ITERL   10 => 0036
0042    KSTR     7  10      ; "only "
0043    GGET     8  11      ; "table"
0044    TGETS    8   8  12  ; "concat"
0045    MOV      9   6
0046    KSTR    10  13      ; " and "
0047    CALL     8   2   3
0048    KSTR     9  14      ; " but not Lua "
0049    UGET    10   2      ; cfg
0050    TGETS   10  10   5  ; "lua_version"
0051    KSTR    11   6      ; "."
0052    CAT      7   7  11
0053    TGETS    8   0  15  ; "constraints"
0054    LEN      8   8
0055    ISNEN    8   0      ; 0
0056    JMP      8 => 0062
0057    TGETS    8   0   3  ; "name"
0058    KSTR     9  16      ; " supports "
0059    MOV     10   7
0060    CAT      5   8  10
0061    JMP      8 => 0092
0062 => TGETS    8   0  15  ; "constraints"
0063    LEN      8   8
0064    ISNEN    8   1      ; 1
0065    JMP      8 => 0081
0066    TGETS    8   0  15  ; "constraints"
0067    TGETB    8   8   1
0068    TGETS    8   8  17  ; "op"
0069    ISNES    8  18      ; "=="
0070    JMP      8 => 0081
0071    TGETS    8   0   3  ; "name"
0072    KSTR     9  19      ; " "
0073    TGETS   10   0  15  ; "constraints"
0074    TGETB   10  10   1
0075    TGETS   10  10  20  ; "version"
0076    TGETS   10  10  21  ; "string"
0077    KSTR    11  16      ; " supports "
0078    MOV     12   7
0079    CAT      5   8  12
0080    JMP      8 => 0092
0081 => KSTR     8  22      ; "Matching "
0082    TGETS    9   0   3  ; "name"
0083    KSTR    10  23      ; " versions support "
0084    MOV     11   7
0085    CAT      5   8  11
0086    JMP      7 => 0092
0087 => TGETS    7   0   3  ; "name"
0088    KSTR     8  24      ; " is not available for any Lua versions."
0089    CAT      5   7   8
0090    JMP      6 => 0092
0091 => KSTR     5  25      ; "To check if it is available for other Lu"~
0092 => MOV      6   3
0093    KSTR     7  26      ; "\n"
0094    MOV      8   5
0095    CAT      3   6   8
0096 => KPRI     5   0
0097    MOV      6   3
0098    RET      5   3

-- BYTECODE -- search.lua:308-344
0001    GGET     2   0      ; "assert"
0002    GGET     3   1      ; "type"
0003    MOV      4   0
0004    CALL     3   2   2
0005    ISEQS    3   2      ; "table"
0006    JMP      3 => 0009
0007    KPRI     3   1
0008    JMP      4 => 0010
0009 => KPRI     3   2
0010 => CALL     2   1   2
0011    GGET     2   0      ; "assert"
0012    GGET     3   1      ; "type"
0013    MOV      4   1
0014    CALL     3   2   2
0015    ISEQS    3   3      ; "boolean"
0016    JMP      3 => 0021
0017    NOT      3   1
0018    JMP      4 => 0022
0019    KPRI     3   1
0020    JMP      4 => 0022
0021 => KPRI     3   2
0022 => CALL     2   1   2
0023    ISF          1
0024    JMP      2 => 0060
0025    UGET     2   0      ; util
0026    TGETS    2   2   4  ; "sortedpairs"
0027    MOV      3   0
0028    CALL     2   4   2
0029    JMP      5 => 0057
0030 => UGET     7   0      ; util
0031    TGETS    7   7   4  ; "sortedpairs"
0032    MOV      8   6
0033    UGET     9   1      ; vers
0034    TGETS    9   9   5  ; "compare_versions"
0035    CALL     7   4   3
0036    JMP     10 => 0055
0037 => GGET    12   6      ; "ipairs"
0038    MOV     13  11
0039    CALL    12   4   2
0040    JMP     15 => 0053
0041 => UGET    17   2      ; dir
0042    TGETS   17  17   7  ; "normalize"
0043    TGETS   18  16   8  ; "repo"
0044    CALL    17   2   2
0045    UGET    18   0      ; util
0046    TGETS   18  18   9  ; "printout"
0047    MOV     19   5
0048    MOV     20  10
0049    TGETS   21  16  10  ; "arch"
0050    MOV     22  17
0051    TGETS   23  16  11  ; "namespace"
0052    CALL    18   1   6
0053 => ITERC   15   3   3
0054    ITERL   15 => 0041
0055 => ITERC   10   3   3
0056    ITERL   10 => 0037
0057 => ITERC    5   3   3
0058    ITERL    5 => 0030
0059    RET0     0   1
0060 => UGET     2   0      ; util
0061    TGETS    2   2   4  ; "sortedpairs"
0062    MOV      3   0
0063    CALL     2   4   2
0064    JMP      5 => 0140
0065 => TNEW     7   0
0066    UGET     8   0      ; util
0067    TGETS    8   8   4  ; "sortedpairs"
0068    MOV      9   6
0069    UGET    10   1      ; vers
0070    TGETS   10  10   5  ; "compare_versions"
0071    CALL     8   4   3
0072    JMP     11 => 0107
0073 => GGET    13   6      ; "ipairs"
0074    MOV     14  12
0075    CALL    13   4   2
0076    JMP     16 => 0105
0077 => TGETS   18  17  11  ; "namespace"
0078    IST         18
0079    JMP     19 => 0081
0080    KSTR    18  12      ; ""
0081 => TGETV   19   7  18
0082    IST         19
0083    JMP     20 => 0085
0084    TNEW    19   0
0085 => TSETV   19   7  18
0086    UGET    20   2      ; dir
0087    TGETS   20  20   7  ; "normalize"
0088    TGETS   21  17   8  ; "repo"
0089    CALL    20   2   2
0090    TSETS   20  17   8  ; "repo"
0091    GGET    20   2      ; "table"
0092    TGETS   20  20  13  ; "insert"
0093    MOV     21  19
0094    KSTR    22  14      ; "   "
0095    MOV     23  11
0096    KSTR    24  15      ; " ("
0097    TGETS   25  17  10  ; "arch"
0098    KSTR    26  16      ; ") - "
0099    UGET    27   3      ; path
0100    TGETS   27  27  17  ; "root_dir"
0101    TGETS   28  17   8  ; "repo"
0102    CALL    27   2   2
0103    CAT     22  22  27
0104    CALL    20   1   3
0105 => ITERC   16   3   3
0106    ITERL   16 => 0077
0107 => ITERC   11   3   3
0108    ITERL   11 => 0073
0109    UGET     8   0      ; util
0110    TGETS    8   8   4  ; "sortedpairs"
0111    MOV      9   7
0112    CALL     8   4   2
0113    JMP     11 => 0138
0114 => UGET    13   0      ; util
0115    TGETS   13  13   9  ; "printout"
0116    ISNES   11  12      ; ""
0117    JMP     14 => 0120
0118    ISTC    14   5
0119    JMP     14 => 0124
0120 => MOV     14  11
0121    KSTR    15  18      ; "/"
0122    MOV     16   5
0123    CAT     14  14  16
0124 => CALL    13   1   2
0125    GGET    13   6      ; "ipairs"
0126    MOV     14  12
0127    CALL    13   4   2
0128    JMP     16 => 0133
0129 => UGET    18   0      ; util
0130    TGETS   18  18   9  ; "printout"
0131    MOV     19  17
0132    CALL    18   1   2
0133 => ITERC   16   3   3
0134    ITERL   16 => 0129
0135    UGET    13   0      ; util
0136    TGETS   13  13   9  ; "printout"
0137    CALL    13   1   1
0138 => ITERC   11   3   3
0139    ITERL   11 => 0114
0140 => ITERC    5   3   3
0141    ITERL    5 => 0065
0142    RET0     0   1

-- BYTECODE -- search.lua:346-376
0001    GGET     2   0      ; "assert"
0002    MOV      4   0
0003    TGETS    3   0   1  ; "type"
0004    CALL     3   2   2
0005    ISEQS    3   2      ; "query"
0006    JMP      3 => 0009
0007    KPRI     3   1
0008    JMP      4 => 0010
0009 => KPRI     3   2
0010 => CALL     2   1   2
0011    TNEW     2   0
0012    TNEW     3   0
0013    UGET     4   0      ; cfg
0014    TGETS    4   4   3  ; "rocks_trees"
0015    ISF          1
0016    JMP      5 => 0020
0017    TNEW     5   3
0018    TSETB    1   5   1
0019    MOV      4   5
0020 => GGET     5   4      ; "ipairs"
0021    MOV      6   4
0022    CALL     5   4   2
0023    JMP      8 => 0035
0024 => UGET    10   1      ; path
0025    TGETS   10  10   5  ; "rocks_dir"
0026    MOV     11   9
0027    CALL    10   2   2
0028    TSETV    9   3  10
0029    UGET    11   2      ; search
0030    TGETS   11  11   6  ; "local_manifest_search"
0031    MOV     12   2
0032    MOV     13  10
0033    MOV     14   0
0034    CALL    11   1   4
0035 => ITERC    8   3   3
0036    ITERL    8 => 0024
0037    GGET     5   7      ; "next"
0038    MOV      6   2
0039    CALL     5   2   2
0040    IST          5
0041    JMP      5 => 0050
0042    KPRI     5   0
0043    KSTR     6   8      ; "cannot find package "
0044    GGET     7   9      ; "tostring"
0045    MOV      8   0
0046    CALL     7   2   2
0047    KSTR     8  10      ; "\nUse 'list' to find installed rocks."
0048    CAT      6   6   8
0049    RET      5   3
0050 => KNIL     5   6
0051    UGET     7   3      ; util
0052    TGETS    7   7  11  ; "sortedpairs"
0053    MOV      8   2
0054    CALL     7   2   2
0055    CALL     7   3   1
0056    UGET     9   3      ; util
0057    TGETS    9   9  11  ; "sortedpairs"
0058    MOV     10   8
0059    UGET    11   4      ; vers
0060    TGETS   11  11  12  ; "compare_versions"
0061    CALL     9   4   3
0062    JMP     12 => 0073
0063 => IST          5
0064    JMP     14 => 0066
0065    MOV      5  12
0066 => GGET    14   4      ; "ipairs"
0067    MOV     15  13
0068    CALL    14   4   2
0069    JMP     17 => 0071
0070 => TGETS    6  18  13  ; "repo"
0071 => ITERC   17   3   3
0072    ITERL   17 => 0070
0073 => ITERC   12   3   3
0074    ITERL   12 => 0063
0075    TGETV    9   3   6
0076    TGETS   10   0  14  ; "name"
0077    MOV     11   5
0078    MOV     12   9
0079    MOV     13   6
0080    RET     10   5

-- BYTECODE -- search.lua:0-379
0001    TNEW     0   0
0002    GGET     1   0      ; "require"
0003    KSTR     2   1      ; "luarocks.dir"
0004    CALL     1   2   2
0005    GGET     2   0      ; "require"
0006    KSTR     3   2      ; "luarocks.path"
0007    CALL     2   2   2
0008    GGET     3   0      ; "require"
0009    KSTR     4   3      ; "luarocks.manif"
0010    CALL     3   2   2
0011    GGET     4   0      ; "require"
0012    KSTR     5   4      ; "luarocks.core.vers"
0013    CALL     4   2   2
0014    GGET     5   0      ; "require"
0015    KSTR     6   5      ; "luarocks.core.cfg"
0016    CALL     5   2   2
0017    GGET     6   0      ; "require"
0018    KSTR     7   6      ; "luarocks.util"
0019    CALL     6   2   2
0020    GGET     7   0      ; "require"
0021    KSTR     8   7      ; "luarocks.queries"
0022    CALL     7   2   2
0023    GGET     8   0      ; "require"
0024    KSTR     9   8      ; "luarocks.results"
0025    CALL     8   2   2
0026    FNEW     9  10      ; search.lua:17
0027    TSETS    9   0   9  ; "store_result"
0028    FNEW     9  11      ; search.lua:42
0029    FNEW    10  13      ; search.lua:60
0030    TSETS   10   0  12  ; "disk_search"
0031    FNEW    10  14      ; search.lua:101
0032    FNEW    11  15      ; search.lua:127
0033    FNEW    12  17      ; search.lua:131
0034    TSETS   12   0  16  ; "local_manifest_search"
0035    FNEW    12  19      ; search.lua:141
0036    TSETS   12   0  18  ; "search_repos"
0037    FNEW    12  20      ; search.lua:182
0038    FNEW    13  21      ; search.lua:209
0039    FNEW    14  23      ; search.lua:230
0040    TSETS   14   0  22  ; "find_suitable_rock"
0041    FNEW    14  25      ; search.lua:253
0042    TSETS   14   0  24  ; "find_src_or_rockspec"
0043    FNEW    14  27      ; search.lua:262
0044    TSETS   14   0  26  ; "find_rock_checking_lua_versions"
0045    FNEW    14  29      ; search.lua:308
0046    TSETS   14   0  28  ; "print_result_tree"
0047    FNEW    14  31      ; search.lua:346
0048    TSETS   14   0  30  ; "pick_installed_rock"
0049    UCLO     0 => 0050
0050 => RET1     0   2

