
main <./search.lua:0,0> (91 instructions, 364 bytes at 0x7fee3dc068a0)
0+ params, 15 slots, 0 upvalues, 14 locals, 18 constants, 14 functions
	1	[1]	NEWTABLE 	0 0 0
	2	[3]	GETGLOBAL	1 -1	; require
	3	[3]	LOADK    	2 -2	; "luarocks.dir"
	4	[3]	CALL     	1 2 2
	5	[4]	GETGLOBAL	2 -1	; require
	6	[4]	LOADK    	3 -3	; "luarocks.path"
	7	[4]	CALL     	2 2 2
	8	[5]	GETGLOBAL	3 -1	; require
	9	[5]	LOADK    	4 -4	; "luarocks.manif"
	10	[5]	CALL     	3 2 2
	11	[6]	GETGLOBAL	4 -1	; require
	12	[6]	LOADK    	5 -5	; "luarocks.core.vers"
	13	[6]	CALL     	4 2 2
	14	[7]	GETGLOBAL	5 -1	; require
	15	[7]	LOADK    	6 -6	; "luarocks.core.cfg"
	16	[7]	CALL     	5 2 2
	17	[8]	GETGLOBAL	6 -1	; require
	18	[8]	LOADK    	7 -7	; "luarocks.util"
	19	[8]	CALL     	6 2 2
	20	[9]	GETGLOBAL	7 -1	; require
	21	[9]	LOADK    	8 -8	; "luarocks.queries"
	22	[9]	CALL     	7 2 2
	23	[10]	GETGLOBAL	8 -1	; require
	24	[10]	LOADK    	9 -9	; "luarocks.results"
	25	[10]	CALL     	8 2 2
	26	[31]	CLOSURE  	9 0	; 0x7fee3dc06f50
	27	[17]	SETTABLE 	0 -10 9	; "store_result" -
	28	[49]	CLOSURE  	9 1	; 0x7fee3dc072c0
	29	[49]	MOVE     	0 0
	30	[89]	CLOSURE  	10 2	; 0x7fee3dc07830
	31	[89]	MOVE     	0 1
	32	[89]	MOVE     	0 2
	33	[89]	MOVE     	0 8
	34	[89]	MOVE     	0 9
	35	[60]	SETTABLE 	0 -11 10	; "disk_search" -
	36	[125]	CLOSURE  	10 3	; 0x7fee3dc07050
	37	[125]	MOVE     	0 3
	38	[125]	MOVE     	0 2
	39	[125]	MOVE     	0 8
	40	[125]	MOVE     	0 9
	41	[129]	CLOSURE  	11 4	; 0x7fee3dc07d60
	42	[129]	MOVE     	0 10
	43	[133]	CLOSURE  	12 5	; 0x7fee3dc081f0
	44	[133]	MOVE     	0 10
	45	[131]	SETTABLE 	0 -12 12	; "local_manifest_search" -
	46	[174]	CLOSURE  	12 6	; 0x7fee3dc09580
	47	[174]	MOVE     	0 5
	48	[174]	MOVE     	0 1
	49	[174]	MOVE     	0 11
	50	[174]	MOVE     	0 6
	51	[174]	MOVE     	0 8
	52	[174]	MOVE     	0 9
	53	[141]	SETTABLE 	0 -13 12	; "search_repos" -
	54	[204]	CLOSURE  	12 7	; 0x7fee3dc09970
	55	[204]	MOVE     	0 4
	56	[204]	MOVE     	0 2
	57	[223]	CLOSURE  	13 8	; 0x7fee3dc09d30
	58	[223]	MOVE     	0 6
	59	[223]	MOVE     	0 5
	60	[223]	MOVE     	0 0
	61	[251]	CLOSURE  	14 9	; 0x7fee3dc0a7d0
	62	[251]	MOVE     	0 6
	63	[251]	MOVE     	0 0
	64	[251]	MOVE     	0 5
	65	[251]	MOVE     	0 12
	66	[230]	SETTABLE 	0 -14 14	; "find_suitable_rock" -
	67	[260]	CLOSURE  	14 10	; 0x7fee3dc0b4a0
	68	[260]	MOVE     	0 7
	69	[260]	MOVE     	0 0
	70	[253]	SETTABLE 	0 -15 14	; "find_src_or_rockspec" -
	71	[303]	CLOSURE  	14 11	; 0x7fee3dc08330
	72	[303]	MOVE     	0 0
	73	[303]	MOVE     	0 6
	74	[303]	MOVE     	0 5
	75	[303]	MOVE     	0 13
	76	[262]	SETTABLE 	0 -16 14	; "find_rock_checking_lua_versions" -
	77	[344]	CLOSURE  	14 12	; 0x7fee3dc09300
	78	[344]	MOVE     	0 6
	79	[344]	MOVE     	0 4
	80	[344]	MOVE     	0 1
	81	[344]	MOVE     	0 2
	82	[308]	SETTABLE 	0 -17 14	; "print_result_tree" -
	83	[376]	CLOSURE  	14 13	; 0x7fee3dc0c110
	84	[376]	MOVE     	0 5
	85	[376]	MOVE     	0 2
	86	[376]	MOVE     	0 0
	87	[376]	MOVE     	0 6
	88	[376]	MOVE     	0 4
	89	[346]	SETTABLE 	0 -18 14	; "pick_installed_rock" -
	90	[378]	RETURN   	0 2
	91	[378]	RETURN   	0 1

function <./search.lua:17,31> (44 instructions, 176 bytes at 0x7fee3dc06f50)
2 params, 8 slots, 0 upvalues, 4 locals, 10 constants, 0 functions
	1	[18]	GETGLOBAL	2 -1	; assert
	2	[18]	GETGLOBAL	3 -2	; type
	3	[18]	MOVE     	4 0
	4	[18]	CALL     	3 2 2
	5	[18]	EQ       	1 3 -3	; - "table"
	6	[18]	JMP      	1	; to 8
	7	[18]	LOADBOOL 	3 0 1
	8	[18]	LOADBOOL 	3 1 0
	9	[18]	CALL     	2 2 1
	10	[19]	GETGLOBAL	2 -1	; assert
	11	[19]	SELF     	3 1 -2	; "type"
	12	[19]	CALL     	3 2 2
	13	[19]	EQ       	1 3 -4	; - "result"
	14	[19]	JMP      	1	; to 16
	15	[19]	LOADBOOL 	3 0 1
	16	[19]	LOADBOOL 	3 1 0
	17	[19]	CALL     	2 2 1
	18	[21]	GETTABLE 	2 1 -5	; "name"
	19	[22]	GETTABLE 	3 1 -6	; "version"
	20	[24]	GETTABLE 	4 0 2
	21	[24]	TEST     	4 0 1
	22	[24]	JMP      	2	; to 25
	23	[24]	NEWTABLE 	4 0 0
	24	[24]	SETTABLE 	0 2 4
	25	[25]	GETTABLE 	4 0 2
	26	[25]	GETTABLE 	4 4 3
	27	[25]	TEST     	4 0 1
	28	[25]	JMP      	3	; to 32
	29	[25]	GETTABLE 	4 0 2
	30	[25]	NEWTABLE 	5 0 0
	31	[25]	SETTABLE 	4 3 5
	32	[26]	GETGLOBAL	4 -3	; table
	33	[26]	GETTABLE 	4 4 -7	; "insert"
	34	[26]	GETTABLE 	5 0 2
	35	[26]	GETTABLE 	5 5 3
	36	[26]	NEWTABLE 	6 0 3
	37	[27]	GETTABLE 	7 1 -8	; "arch"
	38	[27]	SETTABLE 	6 -8 7	; "arch" -
	39	[28]	GETTABLE 	7 1 -9	; "repo"
	40	[28]	SETTABLE 	6 -9 7	; "repo" -
	41	[29]	GETTABLE 	7 1 -10	; "namespace"
	42	[29]	SETTABLE 	6 -10 7	; "namespace" -
	43	[26]	CALL     	4 3 1
	44	[31]	RETURN   	0 1

function <./search.lua:42,49> (27 instructions, 108 bytes at 0x7fee3dc072c0)
3 params, 6 slots, 1 upvalue, 3 locals, 6 constants, 0 functions
	1	[43]	GETGLOBAL	3 -1	; assert
	2	[43]	SELF     	4 1 -2	; "type"
	3	[43]	CALL     	4 2 2
	4	[43]	EQ       	1 4 -3	; - "result"
	5	[43]	JMP      	1	; to 7
	6	[43]	LOADBOOL 	4 0 1
	7	[43]	LOADBOOL 	4 1 0
	8	[43]	CALL     	3 2 1
	9	[44]	GETGLOBAL	3 -1	; assert
	10	[44]	SELF     	4 2 -2	; "type"
	11	[44]	CALL     	4 2 2
	12	[44]	EQ       	1 4 -4	; - "query"
	13	[44]	JMP      	1	; to 15
	14	[44]	LOADBOOL 	4 0 1
	15	[44]	LOADBOOL 	4 1 0
	16	[44]	CALL     	3 2 1
	17	[46]	SELF     	3 1 -5	; "satisfies"
	18	[46]	MOVE     	5 2
	19	[46]	CALL     	3 3 2
	20	[46]	TEST     	3 0 0
	21	[46]	JMP      	5	; to 27
	22	[47]	GETUPVAL 	3 0	; search
	23	[47]	GETTABLE 	3 3 -6	; "store_result"
	24	[47]	MOVE     	4 0
	25	[47]	MOVE     	5 1
	26	[47]	CALL     	3 3 1
	27	[49]	RETURN   	0 1

function <./search.lua:60,89> (112 instructions, 448 bytes at 0x7fee3dc07830)
3 params, 23 slots, 4 upvalues, 19 locals, 18 constants, 0 functions
	1	[61]	GETGLOBAL	3 -1	; assert
	2	[61]	GETGLOBAL	4 -2	; type
	3	[61]	MOVE     	5 0
	4	[61]	CALL     	4 2 2
	5	[61]	EQ       	1 4 -3	; - "string"
	6	[61]	JMP      	1	; to 8
	7	[61]	LOADBOOL 	4 0 1
	8	[61]	LOADBOOL 	4 1 0
	9	[61]	CALL     	3 2 1
	10	[62]	GETGLOBAL	3 -1	; assert
	11	[62]	SELF     	4 1 -2	; "type"
	12	[62]	CALL     	4 2 2
	13	[62]	EQ       	1 4 -4	; - "query"
	14	[62]	JMP      	1	; to 16
	15	[62]	LOADBOOL 	4 0 1
	16	[62]	LOADBOOL 	4 1 0
	17	[62]	CALL     	3 2 1
	18	[63]	GETGLOBAL	3 -1	; assert
	19	[63]	GETGLOBAL	4 -2	; type
	20	[63]	MOVE     	5 2
	21	[63]	CALL     	4 2 2
	22	[63]	EQ       	1 4 -5	; - "table"
	23	[63]	JMP      	3	; to 27
	24	[63]	NOT      	4 2
	25	[63]	JMP      	2	; to 28
	26	[63]	LOADBOOL 	4 0 1
	27	[63]	LOADBOOL 	4 1 0
	28	[63]	CALL     	3 2 1
	29	[65]	GETGLOBAL	3 -6	; require
	30	[65]	LOADK    	4 -7	; "luarocks.fs"
	31	[65]	CALL     	3 2 2
	32	[67]	TEST     	2 0 1
	33	[67]	JMP      	2	; to 36
	34	[68]	NEWTABLE 	4 0 0
	35	[68]	MOVE     	2 4
	36	[71]	GETTABLE 	4 3 -8	; "dir"
	37	[71]	MOVE     	5 0
	38	[71]	CALL     	4 2 4
	39	[71]	JMP      	69	; to 109
	40	[72]	GETUPVAL 	8 0	; dir
	41	[72]	GETTABLE 	8 8 -9	; "path"
	42	[72]	MOVE     	9 0
	43	[72]	MOVE     	10 7
	44	[72]	CALL     	8 3 2
	45	[73]	GETUPVAL 	9 1	; path
	46	[73]	GETTABLE 	9 9 -10	; "parse_name"
	47	[73]	MOVE     	10 7
	48	[73]	CALL     	9 2 4
	49	[75]	TEST     	9 0 0
	50	[75]	JMP      	23	; to 74
	51	[75]	SELF     	12 8 -11	; "match"
	52	[75]	LOADK    	14 -12	; ".rockspec$"
	53	[75]	CALL     	12 3 2
	54	[75]	TEST     	12 0 1
	55	[75]	JMP      	5	; to 61
	56	[75]	SELF     	12 8 -11	; "match"
	57	[75]	LOADK    	14 -13	; ".rock$"
	58	[75]	CALL     	12 3 2
	59	[75]	TEST     	12 0 0
	60	[75]	JMP      	13	; to 74
	61	[76]	GETUPVAL 	12 2	; results
	62	[76]	GETTABLE 	12 12 -14	; "new"
	63	[76]	MOVE     	13 9
	64	[76]	MOVE     	14 10
	65	[76]	MOVE     	15 0
	66	[76]	MOVE     	16 11
	67	[76]	CALL     	12 5 2
	68	[77]	GETUPVAL 	13 3	; store_if_match
	69	[77]	MOVE     	14 2
	70	[77]	MOVE     	15 12
	71	[77]	MOVE     	16 1
	72	[77]	CALL     	13 4 1
	73	[77]	JMP      	35	; to 109
	74	[78]	GETTABLE 	12 3 -15	; "is_dir"
	75	[78]	MOVE     	13 8
	76	[78]	CALL     	12 2 2
	77	[78]	TEST     	12 0 0
	78	[78]	JMP      	30	; to 109
	79	[79]	GETTABLE 	12 3 -8	; "dir"
	80	[79]	MOVE     	13 8
	81	[79]	CALL     	12 2 4
	82	[79]	JMP      	24	; to 107
	83	[80]	SELF     	16 15 -11	; "match"
	84	[80]	LOADK    	18 -16	; "-%d+$"
	85	[80]	CALL     	16 3 2
	86	[80]	TEST     	16 0 0
	87	[80]	JMP      	19	; to 107
	88	[81]	GETUPVAL 	16 1	; path
	89	[81]	GETTABLE 	16 16 -17	; "read_namespace"
	90	[81]	MOVE     	17 7
	91	[81]	MOVE     	18 15
	92	[81]	MOVE     	19 0
	93	[81]	CALL     	16 4 2
	94	[82]	GETUPVAL 	17 2	; results
	95	[82]	GETTABLE 	17 17 -14	; "new"
	96	[82]	MOVE     	18 7
	97	[82]	MOVE     	19 15
	98	[82]	MOVE     	20 0
	99	[82]	LOADK    	21 -18	; "installed"
	100	[82]	MOVE     	22 16
	101	[82]	CALL     	17 6 2
	102	[83]	GETUPVAL 	18 3	; store_if_match
	103	[83]	MOVE     	19 2
	104	[83]	MOVE     	20 17
	105	[83]	MOVE     	21 1
	106	[83]	CALL     	18 4 1
	107	[79]	TFORLOOP 	12 1
	108	[84]	JMP      	-26	; to 83
	109	[71]	TFORLOOP 	4 1
	110	[86]	JMP      	-71	; to 40
	111	[88]	RETURN   	2 2
	112	[89]	RETURN   	0 1

function <./search.lua:101,125> (92 instructions, 368 bytes at 0x7fee3dc07050)
5 params, 30 slots, 4 upvalues, 25 locals, 14 constants, 0 functions
	1	[102]	GETGLOBAL	5 -1	; assert
	2	[102]	GETGLOBAL	6 -2	; type
	3	[102]	MOVE     	7 0
	4	[102]	CALL     	6 2 2
	5	[102]	EQ       	1 6 -3	; - "table"
	6	[102]	JMP      	1	; to 8
	7	[102]	LOADBOOL 	6 0 1
	8	[102]	LOADBOOL 	6 1 0
	9	[102]	CALL     	5 2 1
	10	[103]	GETGLOBAL	5 -1	; assert
	11	[103]	GETGLOBAL	6 -2	; type
	12	[103]	MOVE     	7 1
	13	[103]	CALL     	6 2 2
	14	[103]	EQ       	1 6 -4	; - "string"
	15	[103]	JMP      	1	; to 17
	16	[103]	LOADBOOL 	6 0 1
	17	[103]	LOADBOOL 	6 1 0
	18	[103]	CALL     	5 2 1
	19	[104]	GETGLOBAL	5 -1	; assert
	20	[104]	SELF     	6 2 -2	; "type"
	21	[104]	CALL     	6 2 2
	22	[104]	EQ       	1 6 -5	; - "query"
	23	[104]	JMP      	1	; to 25
	24	[104]	LOADBOOL 	6 0 1
	25	[104]	LOADBOOL 	6 1 0
	26	[104]	CALL     	5 2 1
	27	[107]	TEST     	4 0 1
	28	[107]	JMP      	7	; to 36
	29	[107]	GETTABLE 	5 2 -6	; "namespace"
	30	[107]	TEST     	5 0 0
	31	[107]	JMP      	4	; to 36
	32	[108]	MOVE     	5 1
	33	[108]	LOADK    	6 -7	; "/manifests/"
	34	[108]	GETTABLE 	7 2 -6	; "namespace"
	35	[108]	CONCAT   	1 5 7
	36	[111]	GETUPVAL 	5 0	; manif
	37	[111]	GETTABLE 	5 5 -8	; "load_manifest"
	38	[111]	MOVE     	6 1
	39	[111]	MOVE     	7 3
	40	[111]	NOT      	8 4
	41	[111]	CALL     	5 4 4
	42	[112]	TEST     	5 0 1
	43	[112]	JMP      	4	; to 48
	44	[113]	LOADNIL  	8 8
	45	[113]	MOVE     	9 6
	46	[113]	MOVE     	10 7
	47	[113]	RETURN   	8 4
	48	[115]	GETGLOBAL	8 -9	; pairs
	49	[115]	GETTABLE 	9 5 -10	; "repository"
	50	[115]	CALL     	8 2 4
	51	[115]	JMP      	36	; to 88
	52	[116]	GETGLOBAL	13 -9	; pairs
	53	[116]	MOVE     	14 12
	54	[116]	CALL     	13 2 4
	55	[116]	JMP      	30	; to 86
	56	[117]	TEST     	4 0 0
	57	[117]	JMP      	8	; to 66
	58	[117]	GETUPVAL 	18 1	; path
	59	[117]	GETTABLE 	18 18 -11	; "read_namespace"
	60	[117]	MOVE     	19 11
	61	[117]	MOVE     	20 16
	62	[117]	MOVE     	21 1
	63	[117]	CALL     	18 4 2
	64	[117]	TEST     	18 0 1
	65	[117]	JMP      	1	; to 67
	66	[117]	GETTABLE 	18 2 -6	; "namespace"
	67	[118]	GETGLOBAL	19 -12	; ipairs
	68	[118]	MOVE     	20 17
	69	[118]	CALL     	19 2 4
	70	[118]	JMP      	13	; to 84
	71	[119]	GETUPVAL 	24 2	; results
	72	[119]	GETTABLE 	24 24 -13	; "new"
	73	[119]	MOVE     	25 11
	74	[119]	MOVE     	26 16
	75	[119]	MOVE     	27 1
	76	[119]	GETTABLE 	28 23 -14	; "arch"
	77	[119]	MOVE     	29 18
	78	[119]	CALL     	24 6 2
	79	[120]	GETUPVAL 	25 3	; store_if_match
	80	[120]	MOVE     	26 0
	81	[120]	MOVE     	27 24
	82	[120]	MOVE     	28 2
	83	[120]	CALL     	25 4 1
	84	[118]	TFORLOOP 	19 2
	85	[120]	JMP      	-15	; to 71
	86	[116]	TFORLOOP 	13 2
	87	[121]	JMP      	-32	; to 56
	88	[115]	TFORLOOP 	8 2
	89	[122]	JMP      	-38	; to 52
	90	[124]	LOADBOOL 	8 1 0
	91	[124]	RETURN   	8 2
	92	[125]	RETURN   	0 1

function <./search.lua:127,129> (9 instructions, 36 bytes at 0x7fee3dc07d60)
4 params, 10 slots, 1 upvalue, 4 locals, 0 constants, 0 functions
	1	[128]	GETUPVAL 	4 0	; manifest_search
	2	[128]	MOVE     	5 0
	3	[128]	MOVE     	6 1
	4	[128]	MOVE     	7 2
	5	[128]	MOVE     	8 3
	6	[128]	LOADBOOL 	9 0 0
	7	[128]	TAILCALL 	4 6 0
	8	[128]	RETURN   	4 0
	9	[129]	RETURN   	0 1

function <./search.lua:131,133> (9 instructions, 36 bytes at 0x7fee3dc081f0)
4 params, 10 slots, 1 upvalue, 4 locals, 0 constants, 0 functions
	1	[132]	GETUPVAL 	4 0	; manifest_search
	2	[132]	MOVE     	5 0
	3	[132]	MOVE     	6 1
	4	[132]	MOVE     	7 2
	5	[132]	MOVE     	8 3
	6	[132]	LOADBOOL 	9 1 0
	7	[132]	TAILCALL 	4 6 0
	8	[132]	RETURN   	4 0
	9	[133]	RETURN   	0 1

function <./search.lua:141,174> (87 instructions, 348 bytes at 0x7fee3dc09580)
2 params, 21 slots, 6 upvalues, 25 locals, 18 constants, 0 functions
	1	[142]	GETGLOBAL	2 -1	; assert
	2	[142]	SELF     	3 0 -2	; "type"
	3	[142]	CALL     	3 2 2
	4	[142]	EQ       	1 3 -3	; - "query"
	5	[142]	JMP      	1	; to 7
	6	[142]	LOADBOOL 	3 0 1
	7	[142]	LOADBOOL 	3 1 0
	8	[142]	CALL     	2 2 1
	9	[144]	NEWTABLE 	2 0 0
	10	[145]	GETGLOBAL	3 -4	; ipairs
	11	[145]	GETUPVAL 	4 0	; cfg
	12	[145]	GETTABLE 	4 4 -5	; "rocks_servers"
	13	[145]	CALL     	3 2 4
	14	[145]	JMP      	48	; to 63
	15	[146]	GETUPVAL 	8 0	; cfg
	16	[146]	GETTABLE 	8 8 -6	; "disabled_servers"
	17	[146]	GETTABLE 	8 8 7
	18	[146]	TEST     	8 0 1
	19	[146]	JMP      	43	; to 63
	20	[147]	GETGLOBAL	8 -2	; type
	21	[147]	MOVE     	9 7
	22	[147]	CALL     	8 2 2
	23	[147]	EQ       	0 8 -7	; - "string"
	24	[147]	JMP      	4	; to 29
	25	[148]	NEWTABLE 	8 1 0
	26	[148]	MOVE     	9 7
	27	[148]	SETLIST  	8 1 1	; 1
	28	[148]	MOVE     	7 8
	29	[150]	GETGLOBAL	8 -4	; ipairs
	30	[150]	MOVE     	9 7
	31	[150]	CALL     	8 2 4
	32	[150]	JMP      	28	; to 61
	33	[151]	GETUPVAL 	13 1	; dir
	34	[151]	GETTABLE 	13 13 -8	; "split_url"
	35	[151]	MOVE     	14 12
	36	[151]	CALL     	13 2 3
	37	[152]	EQ       	0 13 -9	; - "file"
	38	[152]	JMP      	1	; to 40
	39	[153]	MOVE     	12 14
	40	[155]	GETUPVAL 	15 2	; remote_manifest_search
	41	[155]	MOVE     	16 2
	42	[155]	MOVE     	17 12
	43	[155]	MOVE     	18 0
	44	[155]	MOVE     	19 1
	45	[155]	CALL     	15 5 4
	46	[156]	EQ       	0 17 -10	; - "network"
	47	[156]	JMP      	3	; to 51
	48	[157]	GETUPVAL 	18 0	; cfg
	49	[157]	GETTABLE 	18 18 -6	; "disabled_servers"
	50	[157]	SETTABLE 	18 7 -11	; - true
	51	[159]	TEST     	15 0 0
	52	[159]	JMP      	2	; to 55
	53	[160]	JMP      	9	; to 63
	54	[160]	JMP      	6	; to 61
	55	[162]	GETUPVAL 	18 3	; util
	56	[162]	GETTABLE 	18 18 -12	; "warning"
	57	[162]	LOADK    	19 -13	; "Failed searching manifest: "
	58	[162]	MOVE     	20 16
	59	[162]	CONCAT   	19 19 20
	60	[162]	CALL     	18 2 1
	61	[150]	TFORLOOP 	8 2
	62	[163]	JMP      	-30	; to 33
	63	[145]	TFORLOOP 	3 2
	64	[165]	JMP      	-50	; to 15
	65	[168]	LOADK    	3 -14	; "provided by VM or rocks_provided"
	66	[169]	GETGLOBAL	4 -15	; pairs
	67	[169]	GETUPVAL 	5 3	; util
	68	[169]	GETTABLE 	5 5 -16	; "get_rocks_provided"
	69	[169]	CALL     	5 1 0
	70	[169]	CALL     	4 0 4
	71	[169]	JMP      	12	; to 84
	72	[170]	GETUPVAL 	9 4	; results
	73	[170]	GETTABLE 	9 9 -17	; "new"
	74	[170]	MOVE     	10 7
	75	[170]	MOVE     	11 8
	76	[170]	MOVE     	12 3
	77	[170]	LOADK    	13 -18	; "installed"
	78	[170]	CALL     	9 5 2
	79	[171]	GETUPVAL 	10 5	; store_if_match
	80	[171]	MOVE     	11 2
	81	[171]	MOVE     	12 9
	82	[171]	MOVE     	13 0
	83	[171]	CALL     	10 4 1
	84	[169]	TFORLOOP 	4 2
	85	[171]	JMP      	-14	; to 72
	86	[173]	RETURN   	2 2
	87	[174]	RETURN   	0 1

function <./search.lua:182,204> (82 instructions, 328 bytes at 0x7fee3dc09970)
2 params, 12 slots, 2 upvalues, 16 locals, 17 constants, 0 functions
	1	[183]	GETGLOBAL	2 -1	; assert
	2	[183]	GETGLOBAL	3 -2	; type
	3	[183]	MOVE     	4 0
	4	[183]	CALL     	3 2 2
	5	[183]	EQ       	0 3 -3	; - "string"
	6	[183]	JMP      	5	; to 12
	7	[183]	SELF     	3 0 -4	; "match"
	8	[183]	LOADK    	5 -5	; "/"
	9	[183]	CALL     	3 3 2
	10	[183]	NOT      	3 3
	11	[183]	JMP      	2	; to 14
	12	[183]	LOADBOOL 	3 0 1
	13	[183]	LOADBOOL 	3 1 0
	14	[183]	CALL     	2 2 1
	15	[184]	GETGLOBAL	2 -1	; assert
	16	[184]	GETGLOBAL	3 -2	; type
	17	[184]	MOVE     	4 1
	18	[184]	CALL     	3 2 2
	19	[184]	EQ       	1 3 -6	; - "table"
	20	[184]	JMP      	1	; to 22
	21	[184]	LOADBOOL 	3 0 1
	22	[184]	LOADBOOL 	3 1 0
	23	[184]	CALL     	2 2 1
	24	[186]	NEWTABLE 	2 0 0
	25	[187]	GETGLOBAL	3 -7	; pairs
	26	[187]	MOVE     	4 1
	27	[187]	CALL     	3 2 4
	28	[187]	JMP      	8	; to 37
	29	[188]	GETGLOBAL	8 -6	; table
	30	[188]	GETTABLE 	8 8 -8	; "insert"
	31	[188]	MOVE     	9 2
	32	[188]	GETUPVAL 	10 0	; vers
	33	[188]	GETTABLE 	10 10 -9	; "parse_version"
	34	[188]	MOVE     	11 6
	35	[188]	CALL     	10 2 0
	36	[188]	CALL     	8 0 1
	37	[187]	TFORLOOP 	3 2
	38	[188]	JMP      	-10	; to 29
	39	[190]	GETGLOBAL	3 -6	; table
	40	[190]	GETTABLE 	3 3 -10	; "sort"
	41	[190]	MOVE     	4 2
	42	[190]	CALL     	3 2 1
	43	[191]	LEN      	3 2
	44	[191]	GETTABLE 	3 2 3
	45	[191]	GETTABLE 	3 3 -3	; "string"
	46	[192]	GETTABLE 	4 1 3
	47	[193]	TEST     	4 0 0
	48	[193]	JMP      	31	; to 80
	49	[194]	LOADK    	5 -11	; 1
	50	[195]	GETGLOBAL	6 -12	; ipairs
	51	[195]	MOVE     	7 4
	52	[195]	CALL     	6 2 4
	53	[195]	JMP      	14	; to 68
	54	[196]	GETTABLE 	11 10 -13	; "arch"
	55	[196]	EQ       	0 11 -14	; - "src"
	56	[196]	JMP      	4	; to 61
	57	[196]	GETTABLE 	11 4 5
	58	[196]	GETTABLE 	11 11 -13	; "arch"
	59	[196]	EQ       	1 11 -15	; - "rockspec"
	60	[196]	JMP      	6	; to 67
	61	[197]	GETTABLE 	11 10 -13	; "arch"
	62	[197]	EQ       	1 11 -14	; - "src"
	63	[197]	JMP      	4	; to 68
	64	[197]	GETTABLE 	11 10 -13	; "arch"
	65	[197]	EQ       	1 11 -15	; - "rockspec"
	66	[197]	JMP      	1	; to 68
	67	[198]	MOVE     	5 9
	68	[195]	TFORLOOP 	6 2
	69	[199]	JMP      	-16	; to 54
	70	[201]	GETUPVAL 	6 1	; path
	71	[201]	GETTABLE 	6 6 -16	; "make_url"
	72	[201]	GETTABLE 	7 4 5
	73	[201]	GETTABLE 	7 7 -17	; "repo"
	74	[201]	MOVE     	8 0
	75	[201]	MOVE     	9 3
	76	[201]	GETTABLE 	10 4 5
	77	[201]	GETTABLE 	10 10 -13	; "arch"
	78	[201]	TAILCALL 	6 5 0
	79	[201]	RETURN   	6 0
	80	[203]	LOADNIL  	5 5
	81	[203]	RETURN   	5 2
	82	[204]	RETURN   	0 1

function <./search.lua:209,223> (42 instructions, 168 bytes at 0x7fee3dc09d30)
1 param, 10 slots, 3 upvalues, 6 locals, 12 constants, 0 functions
	1	[210]	GETGLOBAL	1 -1	; assert
	2	[210]	SELF     	2 0 -2	; "type"
	3	[210]	CALL     	2 2 2
	4	[210]	EQ       	1 2 -3	; - "query"
	5	[210]	JMP      	1	; to 7
	6	[210]	LOADBOOL 	2 0 1
	7	[210]	LOADBOOL 	2 1 0
	8	[210]	CALL     	1 2 1
	9	[211]	NEWTABLE 	1 0 0
	10	[213]	GETUPVAL 	2 0	; util
	11	[213]	GETTABLE 	2 2 -4	; "lua_versions"
	12	[213]	CALL     	2 1 4
	13	[213]	JMP      	25	; to 39
	14	[214]	GETUPVAL 	6 1	; cfg
	15	[214]	GETTABLE 	6 6 -5	; "lua_version"
	16	[214]	EQ       	1 5 6
	17	[214]	JMP      	21	; to 39
	18	[215]	GETUPVAL 	6 0	; util
	19	[215]	GETTABLE 	6 6 -6	; "printout"
	20	[215]	LOADK    	7 -7	; "Checking for Lua "
	21	[215]	MOVE     	8 5
	22	[215]	LOADK    	9 -8	; "..."
	23	[215]	CONCAT   	7 7 9
	24	[215]	CALL     	6 2 1
	25	[216]	GETUPVAL 	6 2	; search
	26	[216]	GETTABLE 	6 6 -9	; "search_repos"
	27	[216]	MOVE     	7 0
	28	[216]	MOVE     	8 5
	29	[216]	CALL     	6 3 2
	30	[216]	GETTABLE 	7 0 -10	; "name"
	31	[216]	GETTABLE 	6 6 7
	32	[216]	TEST     	6 0 0
	33	[216]	JMP      	5	; to 39
	34	[217]	GETGLOBAL	6 -11	; table
	35	[217]	GETTABLE 	6 6 -12	; "insert"
	36	[217]	MOVE     	7 1
	37	[217]	MOVE     	8 5
	38	[217]	CALL     	6 3 1
	39	[213]	TFORLOOP 	2 1
	40	[219]	JMP      	-27	; to 14
	41	[222]	RETURN   	1 2
	42	[223]	RETURN   	0 1

function <./search.lua:230,251> (60 instructions, 240 bytes at 0x7fee3dc0a7d0)
1 param, 8 slots, 4 upvalues, 4 locals, 18 constants, 0 functions
	1	[231]	GETGLOBAL	1 -1	; assert
	2	[231]	SELF     	2 0 -2	; "type"
	3	[231]	CALL     	2 2 2
	4	[231]	EQ       	1 2 -3	; - "query"
	5	[231]	JMP      	1	; to 7
	6	[231]	LOADBOOL 	2 0 1
	7	[231]	LOADBOOL 	2 1 0
	8	[231]	CALL     	1 2 1
	9	[233]	GETUPVAL 	1 0	; util
	10	[233]	GETTABLE 	1 1 -4	; "get_rocks_provided"
	11	[233]	CALL     	1 1 2
	12	[235]	GETTABLE 	2 0 -5	; "name"
	13	[235]	GETTABLE 	2 1 2
	14	[235]	EQ       	1 2 -6	; - nil
	15	[235]	JMP      	10	; to 26
	16	[237]	LOADNIL  	2 2
	17	[237]	LOADK    	3 -7	; "Rock "
	18	[237]	GETTABLE 	4 0 -5	; "name"
	19	[237]	LOADK    	5 -8	; " "
	20	[237]	GETTABLE 	6 0 -5	; "name"
	21	[237]	GETTABLE 	6 1 6
	22	[238]	LOADK    	7 -9	; " is already provided by VM or via 'rocks_provided' in the config file."
	23	[238]	CONCAT   	3 3 7
	24	[238]	LOADK    	4 -10	; "provided"
	25	[238]	RETURN   	2 4
	26	[241]	GETUPVAL 	2 1	; search
	27	[241]	GETTABLE 	2 2 -11	; "search_repos"
	28	[241]	MOVE     	3 0
	29	[241]	CALL     	2 2 2
	30	[242]	GETGLOBAL	3 -12	; next
	31	[242]	MOVE     	4 2
	32	[242]	CALL     	3 2 2
	33	[243]	TEST     	3 0 1
	34	[243]	JMP      	9	; to 44
	35	[244]	LOADNIL  	4 4
	36	[244]	LOADK    	5 -13	; "No results matching query were found for Lua "
	37	[244]	GETUPVAL 	6 2	; cfg
	38	[244]	GETTABLE 	6 6 -14	; "lua_version"
	39	[244]	LOADK    	7 -15	; "."
	40	[244]	CONCAT   	5 5 7
	41	[244]	LOADK    	6 -16	; "notfound"
	42	[244]	RETURN   	4 4
	43	[244]	JMP      	16	; to 60
	44	[245]	GETGLOBAL	4 -12	; next
	45	[245]	MOVE     	5 2
	46	[245]	MOVE     	6 3
	47	[245]	CALL     	4 3 2
	48	[245]	TEST     	4 0 0
	49	[245]	JMP      	5	; to 55
	50	[247]	LOADNIL  	4 4
	51	[247]	LOADK    	5 -17	; "Several rocks matched query."
	52	[247]	LOADK    	6 -18	; "manyfound"
	53	[247]	RETURN   	4 4
	54	[247]	JMP      	5	; to 60
	55	[249]	GETUPVAL 	4 3	; pick_latest_version
	56	[249]	GETTABLE 	5 0 -5	; "name"
	57	[249]	GETTABLE 	6 2 3
	58	[249]	TAILCALL 	4 3 0
	59	[249]	RETURN   	4 0
	60	[251]	RETURN   	0 1

function <./search.lua:253,260> (26 instructions, 104 bytes at 0x7fee3dc0b4a0)
4 params, 12 slots, 2 upvalues, 7 locals, 6 constants, 0 functions
	1	[254]	GETUPVAL 	4 0	; queries
	2	[254]	GETTABLE 	4 4 -1	; "new"
	3	[254]	MOVE     	5 0
	4	[254]	MOVE     	6 1
	5	[254]	MOVE     	7 2
	6	[254]	LOADBOOL 	8 0 0
	7	[254]	LOADK    	9 -2	; "src|rockspec"
	8	[254]	CALL     	4 6 2
	9	[255]	GETUPVAL 	5 1	; search
	10	[255]	GETTABLE 	5 5 -3	; "find_rock_checking_lua_versions"
	11	[255]	MOVE     	6 4
	12	[255]	MOVE     	7 3
	13	[255]	CALL     	5 3 3
	14	[256]	TEST     	5 0 1
	15	[256]	JMP      	9	; to 25
	16	[257]	LOADNIL  	7 7
	17	[257]	LOADK    	8 -4	; "Could not find a result named "
	18	[257]	GETGLOBAL	9 -5	; tostring
	19	[257]	MOVE     	10 4
	20	[257]	CALL     	9 2 2
	21	[257]	LOADK    	10 -6	; ": "
	22	[257]	MOVE     	11 6
	23	[257]	CONCAT   	8 8 11
	24	[257]	RETURN   	7 3
	25	[259]	RETURN   	5 2
	26	[260]	RETURN   	0 1

function <./search.lua:262,303> (99 instructions, 396 bytes at 0x7fee3dc08330)
2 params, 14 slots, 4 upvalues, 13 locals, 29 constants, 0 functions
	1	[263]	GETUPVAL 	2 0	; search
	2	[263]	GETTABLE 	2 2 -1	; "find_suitable_rock"
	3	[263]	MOVE     	3 0
	4	[263]	CALL     	2 2 4
	5	[264]	TEST     	2 0 0
	6	[264]	JMP      	1	; to 8
	7	[265]	RETURN   	2 2
	8	[268]	EQ       	0 4 -2	; - "notfound"
	9	[268]	JMP      	86	; to 96
	10	[269]	LOADNIL  	5 5
	11	[270]	TEST     	1 0 0
	12	[270]	JMP      	78	; to 91
	13	[271]	GETUPVAL 	6 1	; util
	14	[271]	GETTABLE 	6 6 -3	; "printout"
	15	[271]	GETTABLE 	7 0 -4	; "name"
	16	[271]	LOADK    	8 -5	; " not found for Lua "
	17	[271]	GETUPVAL 	9 2	; cfg
	18	[271]	GETTABLE 	9 9 -6	; "lua_version"
	19	[271]	LOADK    	10 -7	; "."
	20	[271]	CONCAT   	7 7 10
	21	[271]	CALL     	6 2 1
	22	[272]	GETUPVAL 	6 1	; util
	23	[272]	GETTABLE 	6 6 -3	; "printout"
	24	[272]	LOADK    	7 -8	; "Checking if available for other Lua versions..."
	25	[272]	CALL     	6 2 1
	26	[275]	GETUPVAL 	6 3	; supported_lua_versions
	27	[275]	MOVE     	7 0
	28	[275]	CALL     	6 2 2
	29	[277]	LEN      	7 6
	30	[277]	EQ       	1 7 -9	; - 0
	31	[277]	JMP      	55	; to 87
	32	[279]	GETGLOBAL	7 -10	; ipairs
	33	[279]	MOVE     	8 6
	34	[279]	CALL     	7 2 4
	35	[279]	JMP      	4	; to 40
	36	[280]	LOADK    	12 -11	; "Lua "
	37	[280]	MOVE     	13 11
	38	[280]	CONCAT   	12 12 13
	39	[280]	SETTABLE 	6 10 12
	40	[279]	TFORLOOP 	7 2
	41	[280]	JMP      	-6	; to 36
	42	[283]	LOADK    	7 -12	; "only "
	43	[283]	GETGLOBAL	8 -13	; table
	44	[283]	GETTABLE 	8 8 -14	; "concat"
	45	[283]	MOVE     	9 6
	46	[283]	LOADK    	10 -15	; " and "
	47	[283]	CALL     	8 3 2
	48	[284]	LOADK    	9 -16	; " but not Lua "
	49	[284]	GETUPVAL 	10 2	; cfg
	50	[284]	GETTABLE 	10 10 -6	; "lua_version"
	51	[284]	LOADK    	11 -7	; "."
	52	[284]	CONCAT   	7 7 11
	53	[286]	GETTABLE 	8 0 -17	; "constraints"
	54	[286]	LEN      	8 8
	55	[286]	EQ       	0 8 -9	; - 0
	56	[286]	JMP      	5	; to 62
	57	[287]	GETTABLE 	8 0 -4	; "name"
	58	[287]	LOADK    	9 -18	; " supports "
	59	[287]	MOVE     	10 7
	60	[287]	CONCAT   	5 8 10
	61	[287]	JMP      	30	; to 92
	62	[288]	GETTABLE 	8 0 -17	; "constraints"
	63	[288]	LEN      	8 8
	64	[288]	EQ       	0 8 -19	; - 1
	65	[288]	JMP      	15	; to 81
	66	[288]	GETTABLE 	8 0 -17	; "constraints"
	67	[288]	GETTABLE 	8 8 -19	; 1
	68	[288]	GETTABLE 	8 8 -20	; "op"
	69	[288]	EQ       	0 8 -21	; - "=="
	70	[288]	JMP      	10	; to 81
	71	[289]	GETTABLE 	8 0 -4	; "name"
	72	[289]	LOADK    	9 -22	; " "
	73	[289]	GETTABLE 	10 0 -17	; "constraints"
	74	[289]	GETTABLE 	10 10 -19	; 1
	75	[289]	GETTABLE 	10 10 -23	; "version"
	76	[289]	GETTABLE 	10 10 -24	; "string"
	77	[289]	LOADK    	11 -18	; " supports "
	78	[289]	MOVE     	12 7
	79	[289]	CONCAT   	5 8 12
	80	[289]	JMP      	11	; to 92
	81	[291]	LOADK    	8 -25	; "Matching "
	82	[291]	GETTABLE 	9 0 -4	; "name"
	83	[291]	LOADK    	10 -26	; " versions support "
	84	[291]	MOVE     	11 7
	85	[291]	CONCAT   	5 8 11
	86	[292]	JMP      	5	; to 92
	87	[294]	GETTABLE 	7 0 -4	; "name"
	88	[294]	LOADK    	8 -27	; " is not available for any Lua versions."
	89	[294]	CONCAT   	5 7 8
	90	[295]	JMP      	1	; to 92
	91	[297]	LOADK    	5 -28	; "To check if it is available for other Lua versions, use --check-lua-versions."
	92	[299]	MOVE     	6 3
	93	[299]	LOADK    	7 -29	; "\n"
	94	[299]	MOVE     	8 5
	95	[299]	CONCAT   	3 6 8
	96	[302]	LOADNIL  	5 5
	97	[302]	MOVE     	6 3
	98	[302]	RETURN   	5 3
	99	[303]	RETURN   	0 1

function <./search.lua:308,344> (140 instructions, 560 bytes at 0x7fee3dc09300)
2 params, 29 slots, 4 upvalues, 46 locals, 19 constants, 0 functions
	1	[309]	GETGLOBAL	2 -1	; assert
	2	[309]	GETGLOBAL	3 -2	; type
	3	[309]	MOVE     	4 0
	4	[309]	CALL     	3 2 2
	5	[309]	EQ       	1 3 -3	; - "table"
	6	[309]	JMP      	1	; to 8
	7	[309]	LOADBOOL 	3 0 1
	8	[309]	LOADBOOL 	3 1 0
	9	[309]	CALL     	2 2 1
	10	[310]	GETGLOBAL	2 -1	; assert
	11	[310]	GETGLOBAL	3 -2	; type
	12	[310]	MOVE     	4 1
	13	[310]	CALL     	3 2 2
	14	[310]	EQ       	1 3 -4	; - "boolean"
	15	[310]	JMP      	3	; to 19
	16	[310]	NOT      	3 1
	17	[310]	JMP      	2	; to 20
	18	[310]	LOADBOOL 	3 0 1
	19	[310]	LOADBOOL 	3 1 0
	20	[310]	CALL     	2 2 1
	21	[312]	TEST     	1 0 0
	22	[312]	JMP      	35	; to 58
	23	[313]	GETUPVAL 	2 0	; util
	24	[313]	GETTABLE 	2 2 -5	; "sortedpairs"
	25	[313]	MOVE     	3 0
	26	[313]	CALL     	2 2 4
	27	[313]	JMP      	27	; to 55
	28	[314]	GETUPVAL 	7 0	; util
	29	[314]	GETTABLE 	7 7 -5	; "sortedpairs"
	30	[314]	MOVE     	8 6
	31	[314]	GETUPVAL 	9 1	; vers
	32	[314]	GETTABLE 	9 9 -6	; "compare_versions"
	33	[314]	CALL     	7 3 4
	34	[314]	JMP      	18	; to 53
	35	[315]	GETGLOBAL	12 -7	; ipairs
	36	[315]	MOVE     	13 11
	37	[315]	CALL     	12 2 4
	38	[315]	JMP      	12	; to 51
	39	[316]	GETUPVAL 	17 2	; dir
	40	[316]	GETTABLE 	17 17 -8	; "normalize"
	41	[316]	GETTABLE 	18 16 -9	; "repo"
	42	[316]	CALL     	17 2 2
	43	[317]	GETUPVAL 	18 0	; util
	44	[317]	GETTABLE 	18 18 -10	; "printout"
	45	[317]	MOVE     	19 5
	46	[317]	MOVE     	20 10
	47	[317]	GETTABLE 	21 16 -11	; "arch"
	48	[317]	MOVE     	22 17
	49	[317]	GETTABLE 	23 16 -12	; "namespace"
	50	[317]	CALL     	18 6 1
	51	[315]	TFORLOOP 	12 2
	52	[317]	JMP      	-14	; to 39
	53	[314]	TFORLOOP 	7 2
	54	[318]	JMP      	-20	; to 35
	55	[313]	TFORLOOP 	2 2
	56	[319]	JMP      	-29	; to 28
	57	[321]	RETURN   	0 1
	58	[324]	GETUPVAL 	2 0	; util
	59	[324]	GETTABLE 	2 2 -5	; "sortedpairs"
	60	[324]	MOVE     	3 0
	61	[324]	CALL     	2 2 4
	62	[324]	JMP      	75	; to 138
	63	[325]	NEWTABLE 	7 0 0
	64	[326]	GETUPVAL 	8 0	; util
	65	[326]	GETTABLE 	8 8 -5	; "sortedpairs"
	66	[326]	MOVE     	9 6
	67	[326]	GETUPVAL 	10 1	; vers
	68	[326]	GETTABLE 	10 10 -6	; "compare_versions"
	69	[326]	CALL     	8 3 4
	70	[326]	JMP      	34	; to 105
	71	[327]	GETGLOBAL	13 -7	; ipairs
	72	[327]	MOVE     	14 12
	73	[327]	CALL     	13 2 4
	74	[327]	JMP      	28	; to 103
	75	[328]	GETTABLE 	18 17 -12	; "namespace"
	76	[328]	TEST     	18 0 1
	77	[328]	JMP      	1	; to 79
	78	[328]	LOADK    	18 -13	; ""
	79	[329]	GETTABLE 	19 7 18
	80	[329]	TEST     	19 0 1
	81	[329]	JMP      	1	; to 83
	82	[329]	NEWTABLE 	19 0 0
	83	[330]	SETTABLE 	7 18 19
	84	[332]	GETUPVAL 	20 2	; dir
	85	[332]	GETTABLE 	20 20 -8	; "normalize"
	86	[332]	GETTABLE 	21 17 -9	; "repo"
	87	[332]	CALL     	20 2 2
	88	[332]	SETTABLE 	17 -9 20	; "repo" -
	89	[333]	GETGLOBAL	20 -3	; table
	90	[333]	GETTABLE 	20 20 -14	; "insert"
	91	[333]	MOVE     	21 19
	92	[333]	LOADK    	22 -15	; "   "
	93	[333]	MOVE     	23 11
	94	[333]	LOADK    	24 -16	; " ("
	95	[333]	GETTABLE 	25 17 -11	; "arch"
	96	[333]	LOADK    	26 -17	; ") - "
	97	[333]	GETUPVAL 	27 3	; path
	98	[333]	GETTABLE 	27 27 -18	; "root_dir"
	99	[333]	GETTABLE 	28 17 -9	; "repo"
	100	[333]	CALL     	27 2 2
	101	[333]	CONCAT   	22 22 27
	102	[333]	CALL     	20 3 1
	103	[327]	TFORLOOP 	13 2
	104	[333]	JMP      	-30	; to 75
	105	[326]	TFORLOOP 	8 2
	106	[334]	JMP      	-36	; to 71
	107	[336]	GETUPVAL 	8 0	; util
	108	[336]	GETTABLE 	8 8 -5	; "sortedpairs"
	109	[336]	MOVE     	9 7
	110	[336]	CALL     	8 2 4
	111	[336]	JMP      	24	; to 136
	112	[337]	GETUPVAL 	13 0	; util
	113	[337]	GETTABLE 	13 13 -10	; "printout"
	114	[337]	EQ       	0 11 -13	; - ""
	115	[337]	JMP      	2	; to 118
	116	[337]	TESTSET  	14 5 1
	117	[337]	JMP      	4	; to 122
	118	[337]	MOVE     	14 11
	119	[337]	LOADK    	15 -19	; "/"
	120	[337]	MOVE     	16 5
	121	[337]	CONCAT   	14 14 16
	122	[337]	CALL     	13 2 1
	123	[338]	GETGLOBAL	13 -7	; ipairs
	124	[338]	MOVE     	14 12
	125	[338]	CALL     	13 2 4
	126	[338]	JMP      	4	; to 131
	127	[339]	GETUPVAL 	18 0	; util
	128	[339]	GETTABLE 	18 18 -10	; "printout"
	129	[339]	MOVE     	19 17
	130	[339]	CALL     	18 2 1
	131	[338]	TFORLOOP 	13 2
	132	[339]	JMP      	-6	; to 127
	133	[341]	GETUPVAL 	13 0	; util
	134	[341]	GETTABLE 	13 13 -10	; "printout"
	135	[341]	CALL     	13 1 1
	136	[336]	TFORLOOP 	8 2
	137	[341]	JMP      	-26	; to 112
	138	[324]	TFORLOOP 	2 2
	139	[342]	JMP      	-77	; to 63
	140	[344]	RETURN   	0 1

function <./search.lua:346,376> (80 instructions, 320 bytes at 0x7fee3dc0c110)
2 params, 20 slots, 5 upvalues, 26 locals, 15 constants, 0 functions
	1	[347]	GETGLOBAL	2 -1	; assert
	2	[347]	SELF     	3 0 -2	; "type"
	3	[347]	CALL     	3 2 2
	4	[347]	EQ       	1 3 -3	; - "query"
	5	[347]	JMP      	1	; to 7
	6	[347]	LOADBOOL 	3 0 1
	7	[347]	LOADBOOL 	3 1 0
	8	[347]	CALL     	2 2 1
	9	[349]	NEWTABLE 	2 0 0
	10	[350]	NEWTABLE 	3 0 0
	11	[351]	GETUPVAL 	4 0	; cfg
	12	[351]	GETTABLE 	4 4 -4	; "rocks_trees"
	13	[352]	TEST     	1 0 0
	14	[352]	JMP      	4	; to 19
	15	[353]	NEWTABLE 	5 1 0
	16	[353]	MOVE     	6 1
	17	[353]	SETLIST  	5 1 1	; 1
	18	[353]	MOVE     	4 5
	19	[355]	GETGLOBAL	5 -5	; ipairs
	20	[355]	MOVE     	6 4
	21	[355]	CALL     	5 2 4
	22	[355]	JMP      	11	; to 34
	23	[356]	GETUPVAL 	10 1	; path
	24	[356]	GETTABLE 	10 10 -6	; "rocks_dir"
	25	[356]	MOVE     	11 9
	26	[356]	CALL     	10 2 2
	27	[357]	SETTABLE 	3 10 9
	28	[358]	GETUPVAL 	11 2	; search
	29	[358]	GETTABLE 	11 11 -7	; "local_manifest_search"
	30	[358]	MOVE     	12 2
	31	[358]	MOVE     	13 10
	32	[358]	MOVE     	14 0
	33	[358]	CALL     	11 4 1
	34	[355]	TFORLOOP 	5 2
	35	[358]	JMP      	-13	; to 23
	36	[360]	GETGLOBAL	5 -8	; next
	37	[360]	MOVE     	6 2
	38	[360]	CALL     	5 2 2
	39	[360]	TEST     	5 0 1
	40	[360]	JMP      	8	; to 49
	41	[361]	LOADNIL  	5 5
	42	[361]	LOADK    	6 -9	; "cannot find package "
	43	[361]	GETGLOBAL	7 -10	; tostring
	44	[361]	MOVE     	8 0
	45	[361]	CALL     	7 2 2
	46	[361]	LOADK    	8 -11	; "\nUse 'list' to find installed rocks."
	47	[361]	CONCAT   	6 6 8
	48	[361]	RETURN   	5 3
	49	[364]	LOADNIL  	5 6
	50	[366]	GETUPVAL 	7 3	; util
	51	[366]	GETTABLE 	7 7 -12	; "sortedpairs"
	52	[366]	MOVE     	8 2
	53	[366]	CALL     	7 2 2
	54	[366]	CALL     	7 1 3
	55	[369]	GETUPVAL 	9 3	; util
	56	[369]	GETTABLE 	9 9 -12	; "sortedpairs"
	57	[369]	MOVE     	10 8
	58	[369]	GETUPVAL 	11 4	; vers
	59	[369]	GETTABLE 	11 11 -13	; "compare_versions"
	60	[369]	CALL     	9 3 4
	61	[369]	JMP      	10	; to 72
	62	[370]	TEST     	5 0 1
	63	[370]	JMP      	1	; to 65
	64	[370]	MOVE     	5 12
	65	[371]	GETGLOBAL	14 -5	; ipairs
	66	[371]	MOVE     	15 13
	67	[371]	CALL     	14 2 4
	68	[371]	JMP      	1	; to 70
	69	[371]	GETTABLE 	6 18 -14	; "repo"
	70	[371]	TFORLOOP 	14 2
	71	[371]	JMP      	-3	; to 69
	72	[369]	TFORLOOP 	9 2
	73	[371]	JMP      	-12	; to 62
	74	[374]	GETTABLE 	9 3 6
	75	[375]	GETTABLE 	10 0 -15	; "name"
	76	[375]	MOVE     	11 5
	77	[375]	MOVE     	12 9
	78	[375]	MOVE     	13 6
	79	[375]	RETURN   	10 5
	80	[376]	RETURN   	0 1
