
main <./cmd/show.lua:0,0> (91 instructions, 364 bytes at 0x7fc6aac068a0)
0+ params, 25 slots, 0 upvalues, 24 locals, 15 constants, 13 functions
	1	[3]	NEWTABLE 	0 0 0
	2	[5]	GETGLOBAL	1 -1	; require
	3	[5]	LOADK    	2 -2	; "luarocks.queries"
	4	[5]	CALL     	1 2 2
	5	[6]	GETGLOBAL	2 -1	; require
	6	[6]	LOADK    	3 -3	; "luarocks.search"
	7	[6]	CALL     	2 2 2
	8	[7]	GETGLOBAL	3 -1	; require
	9	[7]	LOADK    	4 -4	; "luarocks.core.dir"
	10	[7]	CALL     	3 2 2
	11	[8]	GETGLOBAL	4 -1	; require
	12	[8]	LOADK    	5 -5	; "luarocks.fs"
	13	[8]	CALL     	4 2 2
	14	[9]	GETGLOBAL	5 -1	; require
	15	[9]	LOADK    	6 -6	; "luarocks.core.cfg"
	16	[9]	CALL     	5 2 2
	17	[10]	GETGLOBAL	6 -1	; require
	18	[10]	LOADK    	7 -7	; "luarocks.util"
	19	[10]	CALL     	6 2 2
	20	[11]	GETGLOBAL	7 -1	; require
	21	[11]	LOADK    	8 -8	; "luarocks.path"
	22	[11]	CALL     	7 2 2
	23	[12]	GETGLOBAL	8 -1	; require
	24	[12]	LOADK    	9 -9	; "luarocks.fetch"
	25	[12]	CALL     	8 2 2
	26	[13]	GETGLOBAL	9 -1	; require
	27	[13]	LOADK    	10 -10	; "luarocks.manif"
	28	[13]	CALL     	9 2 2
	29	[14]	GETGLOBAL	10 -1	; require
	30	[14]	LOADK    	11 -11	; "luarocks.repos"
	31	[14]	CALL     	10 2 2
	32	[43]	CLOSURE  	11 0	; 0x7fc6aac06f50
	33	[43]	MOVE     	0 6
	34	[16]	SETTABLE 	0 -12 11	; "add_to_parser" -
	35	[76]	LOADK    	11 -13	; "          :\n?namespace:${namespace}/${package} ${version} - ${summary}\n!namespace:${package} ${version} - ${summary}\n          :\n*detailed :${detailed}\n?detailed :\n?license  :License:      \\t${license}\n?homepage :Homepage:     \\t${homepage}\n?issues   :Issues:       \\t${issues}\n?labels   :Labels:       \\t${labels}\n?location :Installed in: \\t${location}\n?commands :\n?commands :Commands:\n*commands :\\t${name} (${file})\n?modules  :\n?modules  :Modules:\n*modules  :\\t${name} (${file})\n?bdeps    :\n?bdeps    :Has build dependency on:\n*bdeps    :\\t${name} (${label})\n?tdeps    :\n?tdeps    :Tests depend on:\n*tdeps    :\\t${name} (${label})\n?deps     :\n?deps     :Depends on:\n*deps     :\\t${name} (${label})\n?ideps    :\n?ideps    :Indirectly pulling:\n*ideps    :\\t${name} (${label})\n          :\n"
	36	[95]	LOADK    	12 -14	; "?namespace:namespace\\t${namespace}\n?package  :package\\t${package}\n?version  :version\\t${version}\n?summary  :summary\\t${summary}\n*detailed :detailed\\t${detailed}\n?license  :license\\t${license}\n?homepage :homepage\\t${homepage}\n?issues   :issues\\t${issues}\n?labels   :labels\\t${labels}\n?location :location\\t${location}\n*commands :command\\t${name}\\t${file}\n*modules  :module\\t${name}\\t${file}\n*bdeps    :build_dependency\\t${name}\\t${label}\n*tdeps    :test_dependency\\t${name}\\t${label}\n*deps     :dependency\\t${name}\\t${label}\n*ideps    :indirect_dependency\\t${name}\\t${label}\n"
	37	[101]	CLOSURE  	13 1	; 0x7fc6aac07050
	38	[101]	MOVE     	0 6
	39	[116]	CLOSURE  	14 2	; 0x7fc6aac08b20
	40	[116]	MOVE     	0 14
	41	[125]	CLOSURE  	15 3	; 0x7fc6aac089e0
	42	[125]	MOVE     	0 6
	43	[125]	MOVE     	0 14
	44	[136]	CLOSURE  	16 4	; 0x7fc6aac08fe0
	45	[136]	MOVE     	0 6
	46	[136]	MOVE     	0 2
	47	[158]	CLOSURE  	17 5	; 0x7fc6aac09900
	48	[166]	CLOSURE  	18 6	; 0x7fc6aac09e00
	49	[166]	MOVE     	0 3
	50	[166]	MOVE     	0 7
	51	[166]	MOVE     	0 4
	52	[193]	CLOSURE  	19 7	; 0x7fc6aac0a860
	53	[193]	MOVE     	0 9
	54	[193]	MOVE     	0 7
	55	[193]	MOVE     	0 10
	56	[193]	MOVE     	0 18
	57	[214]	CLOSURE  	20 8	; 0x7fc6aac0bd20
	58	[214]	MOVE     	0 9
	59	[214]	MOVE     	0 7
	60	[214]	MOVE     	0 10
	61	[214]	MOVE     	0 18
	62	[214]	MOVE     	0 5
	63	[222]	CLOSURE  	21 9	; 0x7fc6aac0b270
	64	[222]	MOVE     	0 16
	65	[236]	CLOSURE  	22 10	; 0x7fc6aac0c290
	66	[236]	MOVE     	0 6
	67	[236]	MOVE     	0 16
	68	[236]	MOVE     	0 1
	69	[259]	CLOSURE  	23 11	; 0x7fc6aac0c8c0
	70	[259]	MOVE     	0 6
	71	[259]	MOVE     	0 15
	72	[259]	MOVE     	0 7
	73	[259]	MOVE     	0 20
	74	[259]	MOVE     	0 19
	75	[259]	MOVE     	0 21
	76	[259]	MOVE     	0 22
	77	[259]	MOVE     	0 17
	78	[310]	CLOSURE  	24 12	; 0x7fc6aac0d350
	79	[310]	MOVE     	0 1
	80	[310]	MOVE     	0 2
	81	[310]	MOVE     	0 7
	82	[310]	MOVE     	0 8
	83	[310]	MOVE     	0 9
	84	[310]	MOVE     	0 6
	85	[310]	MOVE     	0 13
	86	[310]	MOVE     	0 23
	87	[310]	MOVE     	0 12
	88	[310]	MOVE     	0 11
	89	[263]	SETTABLE 	0 -15 24	; "command" -
	90	[312]	RETURN   	0 2
	91	[312]	RETURN   	0 1

function <./cmd/show.lua:16,43> (82 instructions, 328 bytes at 0x7fc6aac06f50)
1 param, 6 slots, 1 upvalue, 2 locals, 44 constants, 0 functions
	1	[17]	SELF     	1 0 -1	; "command"
	2	[17]	LOADK    	3 -2	; "show"
	3	[21]	LOADK    	4 -3	; "Show information about an installed rock.\n\nWithout any flags, show all module information.\nWith flags, return only the desired information."
	4	[21]	GETUPVAL 	5 0	; util
	5	[21]	GETTABLE 	5 5 -4	; "see_also"
	6	[21]	CALL     	5 1 0
	7	[17]	CALL     	1 0 2
	8	[22]	SELF     	1 1 -5	; "summary"
	9	[22]	LOADK    	3 -6	; "Show information about an installed rock."
	10	[22]	CALL     	1 3 2
	11	[24]	SELF     	2 1 -7	; "argument"
	12	[24]	LOADK    	4 -8	; "rock"
	13	[24]	LOADK    	5 -9	; "Name of an installed rock."
	14	[24]	CALL     	2 4 2
	15	[25]	SELF     	2 2 -10	; "action"
	16	[25]	GETUPVAL 	4 0	; util
	17	[25]	GETTABLE 	4 4 -11	; "namespaced_name_action"
	18	[25]	CALL     	2 3 1
	19	[26]	SELF     	2 1 -7	; "argument"
	20	[26]	LOADK    	4 -12	; "version"
	21	[26]	LOADK    	5 -13	; "Rock version."
	22	[26]	CALL     	2 4 2
	23	[27]	SELF     	2 2 -14	; "args"
	24	[27]	LOADK    	4 -15	; "?"
	25	[27]	CALL     	2 3 1
	26	[29]	SELF     	2 1 -16	; "flag"
	27	[29]	LOADK    	4 -17	; "--home"
	28	[29]	LOADK    	5 -18	; "Show home page of project."
	29	[29]	CALL     	2 4 1
	30	[30]	SELF     	2 1 -16	; "flag"
	31	[30]	LOADK    	4 -19	; "--modules"
	32	[30]	LOADK    	5 -20	; "Show all modules provided by the package as used by require()."
	33	[30]	CALL     	2 4 1
	34	[31]	SELF     	2 1 -16	; "flag"
	35	[31]	LOADK    	4 -21	; "--deps"
	36	[31]	LOADK    	5 -22	; "Show packages the package depends on."
	37	[31]	CALL     	2 4 1
	38	[32]	SELF     	2 1 -16	; "flag"
	39	[32]	LOADK    	4 -23	; "--build-deps"
	40	[32]	LOADK    	5 -24	; "Show build-only dependencies for the package."
	41	[32]	CALL     	2 4 1
	42	[33]	SELF     	2 1 -16	; "flag"
	43	[33]	LOADK    	4 -25	; "--test-deps"
	44	[33]	LOADK    	5 -26	; "Show dependencies for testing the package."
	45	[33]	CALL     	2 4 1
	46	[34]	SELF     	2 1 -16	; "flag"
	47	[34]	LOADK    	4 -27	; "--rockspec"
	48	[34]	LOADK    	5 -28	; "Show the full path of the rockspec file."
	49	[34]	CALL     	2 4 1
	50	[35]	SELF     	2 1 -16	; "flag"
	51	[35]	LOADK    	4 -29	; "--mversion"
	52	[35]	LOADK    	5 -30	; "Show the package version."
	53	[35]	CALL     	2 4 1
	54	[36]	SELF     	2 1 -16	; "flag"
	55	[36]	LOADK    	4 -31	; "--rock-tree"
	56	[36]	LOADK    	5 -32	; "Show local tree where rock is installed."
	57	[36]	CALL     	2 4 1
	58	[37]	SELF     	2 1 -16	; "flag"
	59	[37]	LOADK    	4 -33	; "--rock-namespace"
	60	[37]	LOADK    	5 -34	; "Show rock namespace."
	61	[37]	CALL     	2 4 1
	62	[38]	SELF     	2 1 -16	; "flag"
	63	[38]	LOADK    	4 -35	; "--rock-dir"
	64	[38]	LOADK    	5 -36	; "Show data directory of the installed rock."
	65	[38]	CALL     	2 4 1
	66	[39]	SELF     	2 1 -16	; "flag"
	67	[39]	LOADK    	4 -37	; "--rock-license"
	68	[39]	LOADK    	5 -38	; "Show rock license."
	69	[39]	CALL     	2 4 1
	70	[40]	SELF     	2 1 -16	; "flag"
	71	[40]	LOADK    	4 -39	; "--issues"
	72	[40]	LOADK    	5 -40	; "Show URL for project's issue tracker."
	73	[40]	CALL     	2 4 1
	74	[41]	SELF     	2 1 -16	; "flag"
	75	[41]	LOADK    	4 -41	; "--labels"
	76	[41]	LOADK    	5 -42	; "List the labels of the rock."
	77	[41]	CALL     	2 4 1
	78	[42]	SELF     	2 1 -16	; "flag"
	79	[42]	LOADK    	4 -43	; "--porcelain"
	80	[42]	LOADK    	5 -44	; "Produce machine-friendly output."
	81	[42]	CALL     	2 4 1
	82	[43]	RETURN   	0 1

function <./cmd/show.lua:97,101> (17 instructions, 68 bytes at 0x7fc6aac07050)
2 params, 6 slots, 1 upvalue, 3 locals, 5 constants, 0 functions
	1	[98]	GETUPVAL 	2 0	; util
	2	[98]	GETTABLE 	2 2 -1	; "keys"
	3	[98]	MOVE     	3 0
	4	[98]	CALL     	2 2 2
	5	[99]	GETGLOBAL	3 -2	; table
	6	[99]	GETTABLE 	3 3 -3	; "sort"
	7	[99]	MOVE     	4 2
	8	[99]	CALL     	3 2 1
	9	[100]	GETGLOBAL	3 -2	; table
	10	[100]	GETTABLE 	3 3 -4	; "concat"
	11	[100]	MOVE     	4 2
	12	[100]	TESTSET  	5 1 1
	13	[100]	JMP      	1	; to 15
	14	[100]	LOADK    	5 -5	; " "
	15	[100]	TAILCALL 	3 3 0
	16	[100]	RETURN   	3 0
	17	[101]	RETURN   	0 1

function <./cmd/show.lua:103,116> (42 instructions, 168 bytes at 0x7fc6aac08b20)
1 param, 9 slots, 1 upvalue, 3 locals, 10 constants, 0 functions
	1	[104]	GETGLOBAL	1 -1	; tonumber
	2	[104]	GETGLOBAL	2 -2	; os
	3	[104]	GETTABLE 	2 2 -3	; "getenv"
	4	[104]	LOADK    	3 -4	; "COLUMNS"
	5	[104]	CALL     	2 2 0
	6	[104]	CALL     	1 0 2
	7	[104]	TEST     	1 0 1
	8	[104]	JMP      	1	; to 10
	9	[104]	LOADK    	1 -5	; 80
	10	[105]	LT       	0 -5 1	; 80 -
	11	[105]	JMP      	1	; to 13
	12	[105]	LOADK    	1 -5	; 80
	13	[106]	LEN      	2 0
	14	[106]	LT       	0 1 2
	15	[106]	JMP      	25	; to 41
	16	[107]	MOVE     	2 1
	17	[108]	LT       	0 -6 2	; 0 -
	18	[108]	JMP      	8	; to 27
	19	[108]	SELF     	3 0 -7	; "sub"
	20	[108]	MOVE     	5 2
	21	[108]	MOVE     	6 2
	22	[108]	CALL     	3 4 2
	23	[108]	EQ       	1 3 -8	; - " "
	24	[108]	JMP      	2	; to 27
	25	[109]	SUB      	2 2 -9	; - 1
	26	[109]	JMP      	-10	; to 17
	27	[111]	LT       	0 -6 2	; 0 -
	28	[111]	JMP      	12	; to 41
	29	[112]	SELF     	3 0 -7	; "sub"
	30	[112]	LOADK    	5 -9	; 1
	31	[112]	SUB      	6 2 -9	; - 1
	32	[112]	CALL     	3 4 2
	33	[112]	LOADK    	4 -10	; "\n"
	34	[112]	GETUPVAL 	5 0	; word_wrap
	35	[112]	SELF     	6 0 -7	; "sub"
	36	[112]	ADD      	8 2 -9	; - 1
	37	[112]	CALL     	6 3 0
	38	[112]	CALL     	5 0 2
	39	[112]	CONCAT   	3 3 5
	40	[112]	RETURN   	3 2
	41	[115]	RETURN   	0 2
	42	[116]	RETURN   	0 1

function <./cmd/show.lua:118,125> (43 instructions, 172 bytes at 0x7fc6aac089e0)
1 param, 9 slots, 2 upvalues, 7 locals, 13 constants, 0 functions
	1	[119]	SELF     	1 0 -1	; "gsub"
	2	[119]	LOADK    	3 -2	; "^%s*"
	3	[119]	LOADK    	4 -3	; ""
	4	[119]	CALL     	1 4 2
	5	[119]	SELF     	1 1 -1	; "gsub"
	6	[119]	LOADK    	3 -4	; "%s$"
	7	[119]	LOADK    	4 -3	; ""
	8	[119]	CALL     	1 4 2
	9	[119]	SELF     	1 1 -1	; "gsub"
	10	[119]	LOADK    	3 -5	; "\n[ \t]+"
	11	[119]	LOADK    	4 -6	; "\n"
	12	[119]	CALL     	1 4 2
	13	[119]	SELF     	1 1 -1	; "gsub"
	14	[119]	LOADK    	3 -7	; "([^\n])\n([^\n])"
	15	[119]	LOADK    	4 -8	; "%1 %2"
	16	[119]	CALL     	1 4 2
	17	[119]	MOVE     	0 1
	18	[120]	GETUPVAL 	1 0	; util
	19	[120]	GETTABLE 	1 1 -9	; "split_string"
	20	[120]	MOVE     	2 0
	21	[120]	LOADK    	3 -10	; "\n\n"
	22	[120]	CALL     	1 3 2
	23	[121]	GETGLOBAL	2 -11	; ipairs
	24	[121]	MOVE     	3 1
	25	[121]	CALL     	2 2 4
	26	[121]	JMP      	4	; to 31
	27	[122]	GETUPVAL 	7 1	; word_wrap
	28	[122]	MOVE     	8 6
	29	[122]	CALL     	7 2 2
	30	[122]	SETTABLE 	1 5 7
	31	[121]	TFORLOOP 	2 2
	32	[122]	JMP      	-6	; to 27
	33	[124]	GETGLOBAL	2 -12	; table
	34	[124]	GETTABLE 	2 2 -13	; "concat"
	35	[124]	MOVE     	3 1
	36	[124]	LOADK    	4 -10	; "\n\n"
	37	[124]	CALL     	2 3 2
	38	[124]	SELF     	2 2 -1	; "gsub"
	39	[124]	LOADK    	4 -4	; "%s$"
	40	[124]	LOADK    	5 -3	; ""
	41	[124]	CALL     	2 4 2
	42	[124]	RETURN   	2 2
	43	[125]	RETURN   	0 1

function <./cmd/show.lua:127,136> (29 instructions, 116 bytes at 0x7fc6aac08fe0)
2 params, 8 slots, 2 upvalues, 5 locals, 5 constants, 0 functions
	1	[129]	GETUPVAL 	4 0	; util
	2	[129]	GETTABLE 	4 4 -1	; "get_rocks_provided"
	3	[129]	CALL     	4 1 2
	4	[130]	GETTABLE 	5 0 -2	; "name"
	5	[130]	GETTABLE 	5 4 5
	6	[130]	TEST     	5 0 0
	7	[130]	JMP      	5	; to 13
	8	[131]	LOADBOOL 	5 1 0
	9	[131]	GETTABLE 	6 0 -2	; "name"
	10	[131]	GETTABLE 	3 4 6
	11	[131]	MOVE     	2 5
	12	[131]	JMP      	7	; to 20
	13	[133]	GETUPVAL 	5 1	; search
	14	[133]	GETTABLE 	5 5 -3	; "pick_installed_rock"
	15	[133]	MOVE     	6 0
	16	[133]	MOVE     	7 1
	17	[133]	CALL     	5 3 3
	18	[133]	MOVE     	3 6
	19	[133]	MOVE     	2 5
	20	[135]	TEST     	2 0 0
	21	[135]	JMP      	5	; to 27
	22	[135]	LOADK    	5 -4	; "using "
	23	[135]	MOVE     	6 3
	24	[135]	CONCAT   	5 5 6
	25	[135]	TEST     	5 0 1
	26	[135]	JMP      	1	; to 28
	27	[135]	LOADK    	5 -5	; "missing"
	28	[135]	RETURN   	5 2
	29	[136]	RETURN   	0 1

function <./cmd/show.lua:138,158> (80 instructions, 320 bytes at 0x7fc6aac09900)
2 params, 22 slots, 0 upvalues, 16 locals, 19 constants, 0 functions
	1	[139]	NEWTABLE 	2 0 0
	2	[140]	SELF     	3 0 -1	; "gmatch"
	3	[140]	LOADK    	5 -2	; "(.)([a-z]*)%s*:([^\n]*)\n"
	4	[140]	CALL     	3 3 4
	5	[140]	JMP      	66	; to 72
	6	[141]	SELF     	9 8 -3	; "gsub"
	7	[141]	LOADK    	11 -4	; "\\t"
	8	[141]	LOADK    	12 -5	; "\t"
	9	[141]	CALL     	9 4 2
	10	[141]	MOVE     	8 9
	11	[142]	GETTABLE 	9 1 7
	12	[143]	EQ       	0 6 -6	; - " "
	13	[143]	JMP      	6	; to 20
	14	[144]	GETGLOBAL	10 -7	; table
	15	[144]	GETTABLE 	10 10 -8	; "insert"
	16	[144]	MOVE     	11 2
	17	[144]	MOVE     	12 8
	18	[144]	CALL     	10 3 1
	19	[144]	JMP      	52	; to 72
	20	[145]	EQ       	1 6 -9	; - "?"
	21	[145]	JMP      	4	; to 26
	22	[145]	EQ       	1 6 -10	; - "*"
	23	[145]	JMP      	2	; to 26
	24	[145]	EQ       	0 6 -11	; - "!"
	25	[145]	JMP      	46	; to 72
	26	[146]	EQ       	0 6 -11	; - "!"
	27	[146]	JMP      	2	; to 30
	28	[146]	EQ       	1 9 -12	; - nil
	29	[146]	JMP      	17	; to 47
	30	[147]	EQ       	1 6 -11	; - "!"
	31	[147]	JMP      	40	; to 72
	32	[147]	GETGLOBAL	10 -13	; type
	33	[147]	MOVE     	11 9
	34	[147]	CALL     	10 2 2
	35	[147]	EQ       	1 10 -14	; - "string"
	36	[147]	JMP      	10	; to 47
	37	[148]	GETGLOBAL	10 -13	; type
	38	[148]	MOVE     	11 9
	39	[148]	CALL     	10 2 2
	40	[148]	EQ       	0 10 -7	; - "table"
	41	[148]	JMP      	30	; to 72
	42	[148]	GETGLOBAL	10 -15	; next
	43	[148]	MOVE     	11 9
	44	[148]	CALL     	10 2 2
	45	[148]	TEST     	10 0 0
	46	[148]	JMP      	25	; to 72
	47	[149]	EQ       	0 6 -10	; - "*"
	48	[149]	JMP      	3	; to 52
	49	[149]	LEN      	10 9
	50	[149]	TEST     	10 0 1
	51	[149]	JMP      	1	; to 53
	52	[149]	LOADK    	10 -16	; 1
	53	[150]	LOADK    	11 -16	; 1
	54	[150]	MOVE     	12 10
	55	[150]	LOADK    	13 -16	; 1
	56	[150]	FORPREP  	11 14	; to 71
	57	[151]	EQ       	0 6 -10	; - "*"
	58	[151]	JMP      	3	; to 62
	59	[151]	GETTABLE 	15 9 14
	60	[151]	TEST     	15 0 1
	61	[151]	JMP      	1	; to 63
	62	[151]	MOVE     	15 1
	63	[152]	GETGLOBAL	16 -7	; table
	64	[152]	GETTABLE 	16 16 -8	; "insert"
	65	[152]	MOVE     	17 2
	66	[152]	SELF     	18 8 -3	; "gsub"
	67	[152]	LOADK    	20 -17	; "${([a-z]+)}"
	68	[152]	MOVE     	21 15
	69	[152]	CALL     	18 4 2
	70	[152]	CALL     	16 3 1
	71	[150]	FORLOOP  	11 -15	; to 57
	72	[140]	TFORLOOP 	3 3
	73	[155]	JMP      	-68	; to 6
	74	[157]	GETGLOBAL	3 -7	; table
	75	[157]	GETTABLE 	3 3 -18	; "concat"
	76	[157]	MOVE     	4 2
	77	[157]	LOADK    	5 -19	; "\n"
	78	[157]	TAILCALL 	3 3 0
	79	[157]	RETURN   	3 0
	80	[158]	RETURN   	0 1

function <./cmd/show.lua:160,166> (28 instructions, 112 bytes at 0x7fc6aac09e00)
5 params, 10 slots, 3 upvalues, 6 locals, 4 constants, 0 functions
	1	[161]	GETUPVAL 	5 0	; dir
	2	[161]	GETTABLE 	5 5 -1	; "path"
	3	[161]	MOVE     	6 2
	4	[161]	MOVE     	7 3
	5	[161]	CALL     	5 3 2
	6	[161]	MOVE     	3 5
	7	[162]	GETUPVAL 	5 1	; path
	8	[162]	GETTABLE 	5 5 -2	; "versioned_name"
	9	[162]	MOVE     	6 3
	10	[162]	MOVE     	7 2
	11	[162]	MOVE     	8 0
	12	[162]	MOVE     	9 1
	13	[162]	CALL     	5 5 2
	14	[163]	GETUPVAL 	6 2	; fs
	15	[163]	GETTABLE 	6 6 -3	; "exists"
	16	[163]	MOVE     	7 5
	17	[163]	CALL     	6 2 2
	18	[164]	TEST     	6 0 0
	19	[164]	JMP      	2	; to 22
	20	[165]	TESTSET  	6 5 1
	21	[165]	JMP      	1	; to 23
	22	[165]	MOVE     	6 3
	23	[165]	TESTSET  	7 4 1
	24	[165]	JMP      	1	; to 26
	25	[165]	LOADK    	7 -4	; ""
	26	[165]	CONCAT   	6 6 7
	27	[165]	RETURN   	6 2
	28	[166]	RETURN   	0 1

function <./cmd/show.lua:168,193> (44 instructions, 176 bytes at 0x7fc6aac0a860)
3 params, 10 slots, 4 upvalues, 7 locals, 8 constants, 3 functions
	1	[169]	NEWTABLE 	3 0 0
	2	[170]	GETUPVAL 	4 0	; manif
	3	[170]	GETTABLE 	4 4 -1	; "load_rock_manifest"
	4	[170]	MOVE     	5 0
	5	[170]	MOVE     	6 1
	6	[170]	MOVE     	7 2
	7	[170]	CALL     	4 4 2
	8	[172]	GETUPVAL 	5 1	; path
	9	[172]	GETTABLE 	5 5 -2	; "deploy_lua_dir"
	10	[172]	MOVE     	6 2
	11	[172]	CALL     	5 2 2
	12	[173]	GETUPVAL 	6 1	; path
	13	[173]	GETTABLE 	6 6 -3	; "deploy_lib_dir"
	14	[173]	MOVE     	7 2
	15	[173]	CALL     	6 2 2
	16	[174]	GETUPVAL 	7 2	; repos
	17	[174]	GETTABLE 	7 7 -4	; "recurse_rock_manifest_entry"
	18	[174]	GETTABLE 	8 4 -5	; "lua"
	19	[179]	CLOSURE  	9 0	; 0x7fc6aac0acb0
	20	[179]	MOVE     	0 3
	21	[179]	GETUPVAL 	0 1	; path
	22	[179]	GETUPVAL 	0 3	; adjust_path
	23	[179]	MOVE     	0 0
	24	[179]	MOVE     	0 1
	25	[179]	MOVE     	0 5
	26	[174]	CALL     	7 3 1
	27	[180]	GETUPVAL 	7 2	; repos
	28	[180]	GETTABLE 	7 7 -4	; "recurse_rock_manifest_entry"
	29	[180]	GETTABLE 	8 4 -6	; "lib"
	30	[185]	CLOSURE  	9 1	; 0x7fc6aac0b400
	31	[185]	MOVE     	0 3
	32	[185]	GETUPVAL 	0 1	; path
	33	[185]	GETUPVAL 	0 3	; adjust_path
	34	[185]	MOVE     	0 0
	35	[185]	MOVE     	0 1
	36	[185]	MOVE     	0 6
	37	[180]	CALL     	7 3 1
	38	[186]	GETGLOBAL	7 -7	; table
	39	[186]	GETTABLE 	7 7 -8	; "sort"
	40	[186]	MOVE     	8 3
	41	[191]	CLOSURE  	9 2	; 0x7fc6aac0af40
	42	[186]	CALL     	7 3 1
	43	[192]	RETURN   	3 2
	44	[193]	RETURN   	0 1

function <./cmd/show.lua:174,179> (18 instructions, 72 bytes at 0x7fc6aac0acb0)
1 param, 9 slots, 6 upvalues, 1 local, 5 constants, 0 functions
	1	[175]	GETGLOBAL	1 -1	; table
	2	[175]	GETTABLE 	1 1 -2	; "insert"
	3	[175]	GETUPVAL 	2 0	; ret
	4	[175]	NEWTABLE 	3 0 2
	5	[176]	GETUPVAL 	4 1	; path
	6	[176]	GETTABLE 	4 4 -4	; "path_to_module"
	7	[176]	MOVE     	5 0
	8	[176]	CALL     	4 2 2
	9	[176]	SETTABLE 	3 -3 4	; "name" -
	10	[177]	GETUPVAL 	4 2	; adjust_path
	11	[177]	GETUPVAL 	5 3	; name
	12	[177]	GETUPVAL 	6 4	; version
	13	[177]	GETUPVAL 	7 5	; lua_dir
	14	[177]	MOVE     	8 0
	15	[177]	CALL     	4 5 2
	16	[177]	SETTABLE 	3 -5 4	; "file" -
	17	[175]	CALL     	1 3 1
	18	[179]	RETURN   	0 1

function <./cmd/show.lua:180,185> (18 instructions, 72 bytes at 0x7fc6aac0b400)
1 param, 9 slots, 6 upvalues, 1 local, 5 constants, 0 functions
	1	[181]	GETGLOBAL	1 -1	; table
	2	[181]	GETTABLE 	1 1 -2	; "insert"
	3	[181]	GETUPVAL 	2 0	; ret
	4	[181]	NEWTABLE 	3 0 2
	5	[182]	GETUPVAL 	4 1	; path
	6	[182]	GETTABLE 	4 4 -4	; "path_to_module"
	7	[182]	MOVE     	5 0
	8	[182]	CALL     	4 2 2
	9	[182]	SETTABLE 	3 -3 4	; "name" -
	10	[183]	GETUPVAL 	4 2	; adjust_path
	11	[183]	GETUPVAL 	5 3	; name
	12	[183]	GETUPVAL 	6 4	; version
	13	[183]	GETUPVAL 	7 5	; lib_dir
	14	[183]	MOVE     	8 0
	15	[183]	CALL     	4 5 2
	16	[183]	SETTABLE 	3 -5 4	; "file" -
	17	[181]	CALL     	1 3 1
	18	[185]	RETURN   	0 1

function <./cmd/show.lua:186,191> (19 instructions, 76 bytes at 0x7fc6aac0af40)
2 params, 4 slots, 0 upvalues, 2 locals, 2 constants, 0 functions
	1	[187]	GETTABLE 	2 0 -1	; "name"
	2	[187]	GETTABLE 	3 1 -1	; "name"
	3	[187]	EQ       	0 2 3
	4	[187]	JMP      	7	; to 12
	5	[188]	GETTABLE 	2 0 -2	; "file"
	6	[188]	GETTABLE 	3 1 -2	; "file"
	7	[188]	LT       	1 2 3
	8	[188]	JMP      	1	; to 10
	9	[188]	LOADBOOL 	2 0 1
	10	[188]	LOADBOOL 	2 1 0
	11	[188]	RETURN   	2 2
	12	[190]	GETTABLE 	2 0 -1	; "name"
	13	[190]	GETTABLE 	3 1 -1	; "name"
	14	[190]	LT       	1 2 3
	15	[190]	JMP      	1	; to 17
	16	[190]	LOADBOOL 	2 0 1
	17	[190]	LOADBOOL 	2 1 0
	18	[190]	RETURN   	2 2
	19	[191]	RETURN   	0 1

function <./cmd/show.lua:195,214> (29 instructions, 116 bytes at 0x7fc6aac0bd20)
3 params, 9 slots, 5 upvalues, 6 locals, 6 constants, 2 functions
	1	[196]	NEWTABLE 	3 0 0
	2	[197]	GETUPVAL 	4 0	; manif
	3	[197]	GETTABLE 	4 4 -1	; "load_rock_manifest"
	4	[197]	MOVE     	5 0
	5	[197]	MOVE     	6 1
	6	[197]	MOVE     	7 2
	7	[197]	CALL     	4 4 2
	8	[199]	GETUPVAL 	5 1	; path
	9	[199]	GETTABLE 	5 5 -2	; "deploy_bin_dir"
	10	[199]	MOVE     	6 2
	11	[199]	CALL     	5 2 2
	12	[200]	GETUPVAL 	6 2	; repos
	13	[200]	GETTABLE 	6 6 -3	; "recurse_rock_manifest_entry"
	14	[200]	GETTABLE 	7 4 -4	; "bin"
	15	[206]	CLOSURE  	8 0	; 0x7fc6aac0bed0
	16	[206]	GETUPVAL 	0 3	; adjust_path
	17	[206]	MOVE     	0 0
	18	[206]	MOVE     	0 1
	19	[206]	MOVE     	0 5
	20	[206]	MOVE     	0 3
	21	[206]	GETUPVAL 	0 4	; cfg
	22	[200]	CALL     	6 3 1
	23	[207]	GETGLOBAL	6 -5	; table
	24	[207]	GETTABLE 	6 6 -6	; "sort"
	25	[207]	MOVE     	7 3
	26	[212]	CLOSURE  	8 1	; 0x7fc6aac0be50
	27	[207]	CALL     	6 3 1
	28	[213]	RETURN   	3 2
	29	[214]	RETURN   	0 1

function <./cmd/show.lua:200,206> (23 instructions, 92 bytes at 0x7fc6aac0bed0)
1 param, 10 slots, 6 upvalues, 1 local, 5 constants, 0 functions
	1	[201]	GETUPVAL 	1 0	; adjust_path
	2	[201]	GETUPVAL 	2 1	; name
	3	[201]	GETUPVAL 	3 2	; version
	4	[201]	GETUPVAL 	4 3	; bin_dir
	5	[201]	MOVE     	5 0
	6	[201]	CALL     	1 5 2
	7	[201]	MOVE     	0 1
	8	[202]	GETGLOBAL	1 -1	; table
	9	[202]	GETTABLE 	1 1 -2	; "insert"
	10	[202]	GETUPVAL 	2 4	; ret
	11	[202]	NEWTABLE 	3 0 2
	12	[203]	SETTABLE 	3 -3 0	; "name" -
	13	[204]	GETUPVAL 	4 0	; adjust_path
	14	[204]	GETUPVAL 	5 1	; name
	15	[204]	GETUPVAL 	6 2	; version
	16	[204]	GETUPVAL 	7 3	; bin_dir
	17	[204]	MOVE     	8 0
	18	[204]	GETUPVAL 	9 5	; cfg
	19	[204]	GETTABLE 	9 9 -5	; "wrapper_suffix"
	20	[204]	CALL     	4 6 2
	21	[204]	SETTABLE 	3 -4 4	; "file" -
	22	[202]	CALL     	1 3 1
	23	[206]	RETURN   	0 1

function <./cmd/show.lua:207,212> (19 instructions, 76 bytes at 0x7fc6aac0be50)
2 params, 4 slots, 0 upvalues, 2 locals, 2 constants, 0 functions
	1	[208]	GETTABLE 	2 0 -1	; "name"
	2	[208]	GETTABLE 	3 1 -1	; "name"
	3	[208]	EQ       	0 2 3
	4	[208]	JMP      	7	; to 12
	5	[209]	GETTABLE 	2 0 -2	; "file"
	6	[209]	GETTABLE 	3 1 -2	; "file"
	7	[209]	LT       	1 2 3
	8	[209]	JMP      	1	; to 10
	9	[209]	LOADBOOL 	2 0 1
	10	[209]	LOADBOOL 	2 1 0
	11	[209]	RETURN   	2 2
	12	[211]	GETTABLE 	2 0 -1	; "name"
	13	[211]	GETTABLE 	3 1 -1	; "name"
	14	[211]	LT       	1 2 3
	15	[211]	JMP      	1	; to 17
	16	[211]	LOADBOOL 	2 0 1
	17	[211]	LOADBOOL 	2 1 0
	18	[211]	RETURN   	2 2
	19	[212]	RETURN   	0 1

function <./cmd/show.lua:216,222> (25 instructions, 100 bytes at 0x7fc6aac0b270)
2 params, 14 slots, 1 upvalue, 8 locals, 6 constants, 0 functions
	1	[217]	NEWTABLE 	2 0 0
	2	[218]	GETGLOBAL	3 -1	; ipairs
	3	[218]	TESTSET  	4 0 1
	4	[218]	JMP      	1	; to 6
	5	[218]	NEWTABLE 	4 0 0
	6	[218]	CALL     	3 2 4
	7	[218]	JMP      	14	; to 22
	8	[219]	GETGLOBAL	8 -2	; table
	9	[219]	GETTABLE 	8 8 -3	; "insert"
	10	[219]	MOVE     	9 2
	11	[219]	NEWTABLE 	10 0 2
	12	[219]	GETGLOBAL	11 -5	; tostring
	13	[219]	MOVE     	12 7
	14	[219]	CALL     	11 2 2
	15	[219]	SETTABLE 	10 -4 11	; "name" -
	16	[219]	GETUPVAL 	11 0	; installed_rock_label
	17	[219]	MOVE     	12 7
	18	[219]	MOVE     	13 1
	19	[219]	CALL     	11 3 2
	20	[219]	SETTABLE 	10 -6 11	; "label" -
	21	[219]	CALL     	8 3 1
	22	[218]	TFORLOOP 	3 2
	23	[219]	JMP      	-16	; to 8
	24	[221]	RETURN   	2 2
	25	[222]	RETURN   	0 1

function <./cmd/show.lua:224,236> (40 instructions, 160 bytes at 0x7fc6aac0c290)
3 params, 15 slots, 3 upvalues, 14 locals, 9 constants, 0 functions
	1	[225]	NEWTABLE 	3 0 0
	2	[226]	NEWTABLE 	4 0 0
	3	[227]	GETGLOBAL	5 -1	; ipairs
	4	[227]	MOVE     	6 1
	5	[227]	CALL     	5 2 4
	6	[227]	JMP      	1	; to 8
	7	[228]	SETTABLE 	4 9 -2	; - true
	8	[227]	TFORLOOP 	5 2
	9	[228]	JMP      	-3	; to 7
	10	[230]	GETUPVAL 	5 0	; util
	11	[230]	GETTABLE 	5 5 -3	; "sortedpairs"
	12	[230]	TESTSET  	6 0 1
	13	[230]	JMP      	1	; to 15
	14	[230]	NEWTABLE 	6 0 0
	15	[230]	CALL     	5 2 4
	16	[230]	JMP      	20	; to 37
	17	[231]	GETTABLE 	9 4 8
	18	[231]	TEST     	9 0 1
	19	[231]	JMP      	17	; to 37
	20	[232]	GETGLOBAL	9 -4	; table
	21	[232]	GETTABLE 	9 9 -5	; "insert"
	22	[232]	MOVE     	10 3
	23	[232]	NEWTABLE 	11 0 2
	24	[232]	GETGLOBAL	12 -7	; tostring
	25	[232]	MOVE     	13 8
	26	[232]	CALL     	12 2 2
	27	[232]	SETTABLE 	11 -6 12	; "name" -
	28	[232]	GETUPVAL 	12 1	; installed_rock_label
	29	[232]	GETUPVAL 	13 2	; queries
	30	[232]	GETTABLE 	13 13 -9	; "new"
	31	[232]	MOVE     	14 8
	32	[232]	CALL     	13 2 2
	33	[232]	MOVE     	14 2
	34	[232]	CALL     	12 3 2
	35	[232]	SETTABLE 	11 -8 12	; "label" -
	36	[232]	CALL     	9 3 1
	37	[230]	TFORLOOP 	5 1
	38	[233]	JMP      	-22	; to 17
	39	[235]	RETURN   	3 2
	40	[236]	RETURN   	0 1

function <./cmd/show.lua:238,259> (84 instructions, 336 bytes at 0x7fc6aac0c8c0)
8 params, 14 slots, 8 upvalues, 10 locals, 29 constants, 0 functions
	1	[239]	GETTABLE 	8 4 -1	; "description"
	2	[240]	NEWTABLE 	9 0 16
	3	[241]	SETTABLE 	9 -2 1	; "namespace" -
	4	[242]	GETTABLE 	10 4 -3	; "package"
	5	[242]	SETTABLE 	9 -3 10	; "package" -
	6	[243]	GETTABLE 	10 4 -4	; "version"
	7	[243]	SETTABLE 	9 -4 10	; "version" -
	8	[244]	GETTABLE 	10 8 -5	; "summary"
	9	[244]	TEST     	10 0 1
	10	[244]	JMP      	1	; to 12
	11	[244]	LOADK    	10 -6	; ""
	12	[244]	SETTABLE 	9 -5 10	; "summary" -
	13	[245]	GETTABLE 	10 8 -7	; "detailed"
	14	[245]	TEST     	10 0 0
	15	[245]	JMP      	7	; to 23
	16	[245]	GETUPVAL 	10 0	; util
	17	[245]	GETTABLE 	10 10 -8	; "split_string"
	18	[245]	GETUPVAL 	11 1	; format_text
	19	[245]	GETTABLE 	12 8 -7	; "detailed"
	20	[245]	CALL     	11 2 2
	21	[245]	LOADK    	12 -9	; "\n"
	22	[245]	CALL     	10 3 2
	23	[245]	SETTABLE 	9 -7 10	; "detailed" -
	24	[246]	GETTABLE 	10 8 -10	; "license"
	25	[246]	SETTABLE 	9 -10 10	; "license" -
	26	[247]	GETTABLE 	10 8 -11	; "homepage"
	27	[247]	SETTABLE 	9 -11 10	; "homepage" -
	28	[248]	GETTABLE 	10 8 -13	; "issues_url"
	29	[248]	SETTABLE 	9 -12 10	; "issues" -
	30	[249]	GETTABLE 	10 8 -14	; "labels"
	31	[249]	TEST     	10 0 0
	32	[249]	JMP      	5	; to 38
	33	[249]	GETGLOBAL	10 -15	; table
	34	[249]	GETTABLE 	10 10 -16	; "concat"
	35	[249]	GETTABLE 	11 8 -14	; "labels"
	36	[249]	LOADK    	12 -17	; ", "
	37	[249]	CALL     	10 3 2
	38	[249]	SETTABLE 	9 -14 10	; "labels" -
	39	[250]	GETUPVAL 	10 2	; path
	40	[250]	GETTABLE 	10 10 -19	; "rocks_tree_to_string"
	41	[250]	MOVE     	11 5
	42	[250]	CALL     	10 2 2
	43	[250]	SETTABLE 	9 -18 10	; "location" -
	44	[251]	GETUPVAL 	10 3	; commands_to_list
	45	[251]	MOVE     	11 2
	46	[251]	MOVE     	12 3
	47	[251]	MOVE     	13 5
	48	[251]	CALL     	10 4 2
	49	[251]	SETTABLE 	9 -20 10	; "commands" -
	50	[252]	GETUPVAL 	10 4	; modules_to_list
	51	[252]	MOVE     	11 2
	52	[252]	MOVE     	12 3
	53	[252]	MOVE     	13 5
	54	[252]	CALL     	10 4 2
	55	[252]	SETTABLE 	9 -21 10	; "modules" -
	56	[253]	GETUPVAL 	10 5	; deps_to_list
	57	[253]	GETTABLE 	11 4 -23	; "build_dependencies"
	58	[253]	MOVE     	12 7
	59	[253]	CALL     	10 3 2
	60	[253]	SETTABLE 	9 -22 10	; "bdeps" -
	61	[254]	GETUPVAL 	10 5	; deps_to_list
	62	[254]	GETTABLE 	11 4 -25	; "test_dependencies"
	63	[254]	MOVE     	12 7
	64	[254]	CALL     	10 3 2
	65	[254]	SETTABLE 	9 -24 10	; "tdeps" -
	66	[255]	GETUPVAL 	10 5	; deps_to_list
	67	[255]	GETTABLE 	11 4 -27	; "dependencies"
	68	[255]	MOVE     	12 7
	69	[255]	CALL     	10 3 2
	70	[255]	SETTABLE 	9 -26 10	; "deps" -
	71	[256]	GETUPVAL 	10 6	; indirect_deps
	72	[256]	GETTABLE 	11 6 -27	; "dependencies"
	73	[256]	GETTABLE 	12 4 -27	; "dependencies"
	74	[256]	MOVE     	13 7
	75	[256]	CALL     	10 4 2
	76	[256]	SETTABLE 	9 -28 10	; "ideps" -
	77	[258]	GETUPVAL 	10 0	; util
	78	[258]	GETTABLE 	10 10 -29	; "printout"
	79	[258]	GETUPVAL 	11 7	; render
	80	[258]	MOVE     	12 0
	81	[258]	MOVE     	13 9
	82	[258]	CALL     	11 3 0
	83	[258]	CALL     	10 0 1
	84	[259]	RETURN   	0 1

function <./cmd/show.lua:263,310> (229 instructions, 916 bytes at 0x7fc6aac0d350)
1 param, 25 slots, 10 upvalues, 31 locals, 41 constants, 0 functions
	1	[264]	GETUPVAL 	1 0	; queries
	2	[264]	GETTABLE 	1 1 -1	; "new"
	3	[264]	GETTABLE 	2 0 -2	; "rock"
	4	[264]	GETTABLE 	3 0 -3	; "namespace"
	5	[264]	GETTABLE 	4 0 -4	; "version"
	6	[264]	CALL     	1 4 2
	7	[266]	GETUPVAL 	2 1	; search
	8	[266]	GETTABLE 	2 2 -5	; "pick_installed_rock"
	9	[266]	MOVE     	3 1
	10	[266]	GETTABLE 	4 0 -6	; "tree"
	11	[266]	CALL     	2 3 5
	12	[267]	TEST     	2 0 1
	13	[267]	JMP      	3	; to 17
	14	[268]	LOADNIL  	6 6
	15	[268]	MOVE     	7 3
	16	[268]	RETURN   	6 3
	17	[270]	GETUPVAL 	6 2	; path
	18	[270]	GETTABLE 	6 6 -7	; "rocks_tree_to_string"
	19	[270]	MOVE     	7 4
	20	[270]	CALL     	6 2 2
	21	[271]	GETUPVAL 	7 2	; path
	22	[271]	GETTABLE 	7 7 -8	; "install_dir"
	23	[271]	MOVE     	8 2
	24	[271]	MOVE     	9 3
	25	[271]	MOVE     	10 4
	26	[271]	CALL     	7 4 2
	27	[272]	GETUPVAL 	8 2	; path
	28	[272]	GETTABLE 	8 8 -9	; "read_namespace"
	29	[272]	MOVE     	9 2
	30	[272]	MOVE     	10 3
	31	[272]	MOVE     	11 6
	32	[272]	CALL     	8 4 2
	33	[273]	GETUPVAL 	9 2	; path
	34	[273]	GETTABLE 	9 9 -10	; "rockspec_file"
	35	[273]	MOVE     	10 2
	36	[273]	MOVE     	11 3
	37	[273]	MOVE     	12 4
	38	[273]	CALL     	9 4 2
	39	[274]	GETUPVAL 	10 3	; fetch
	40	[274]	GETTABLE 	10 10 -11	; "load_local_rockspec"
	41	[274]	MOVE     	11 9
	42	[274]	CALL     	10 2 3
	43	[275]	TEST     	10 0 1
	44	[275]	JMP      	3	; to 48
	45	[275]	LOADNIL  	12 12
	46	[275]	MOVE     	13 11
	47	[275]	RETURN   	12 3
	48	[277]	GETTABLE 	12 10 -12	; "description"
	49	[277]	TEST     	12 0 1
	50	[277]	JMP      	1	; to 52
	51	[277]	NEWTABLE 	12 0 0
	52	[278]	GETUPVAL 	13 4	; manif
	53	[278]	GETTABLE 	13 13 -13	; "load_manifest"
	54	[278]	MOVE     	14 5
	55	[278]	CALL     	13 2 3
	56	[279]	TEST     	13 0 1
	57	[279]	JMP      	3	; to 61
	58	[279]	LOADNIL  	15 15
	59	[279]	MOVE     	16 14
	60	[279]	RETURN   	15 3
	61	[280]	GETTABLE 	15 13 -14	; "repository"
	62	[280]	GETTABLE 	15 15 2
	63	[280]	GETTABLE 	15 15 3
	64	[280]	GETTABLE 	15 15 -15	; 1
	65	[282]	GETTABLE 	16 0 -16	; "rock_tree"
	66	[282]	TEST     	16 0 0
	67	[282]	JMP      	5	; to 73
	68	[282]	GETUPVAL 	16 5	; util
	69	[282]	GETTABLE 	16 16 -17	; "printout"
	70	[282]	MOVE     	17 6
	71	[282]	CALL     	16 2 1
	72	[282]	JMP      	154	; to 227
	73	[283]	GETTABLE 	16 0 -18	; "rock_namespace"
	74	[283]	TEST     	16 0 0
	75	[283]	JMP      	5	; to 81
	76	[283]	GETUPVAL 	16 5	; util
	77	[283]	GETTABLE 	16 16 -17	; "printout"
	78	[283]	MOVE     	17 8
	79	[283]	CALL     	16 2 1
	80	[283]	JMP      	146	; to 227
	81	[284]	GETTABLE 	16 0 -19	; "rock_dir"
	82	[284]	TEST     	16 0 0
	83	[284]	JMP      	5	; to 89
	84	[284]	GETUPVAL 	16 5	; util
	85	[284]	GETTABLE 	16 16 -17	; "printout"
	86	[284]	MOVE     	17 7
	87	[284]	CALL     	16 2 1
	88	[284]	JMP      	138	; to 227
	89	[285]	GETTABLE 	16 0 -20	; "home"
	90	[285]	TEST     	16 0 0
	91	[285]	JMP      	5	; to 97
	92	[285]	GETUPVAL 	16 5	; util
	93	[285]	GETTABLE 	16 16 -17	; "printout"
	94	[285]	GETTABLE 	17 12 -21	; "homepage"
	95	[285]	CALL     	16 2 1
	96	[285]	JMP      	130	; to 227
	97	[286]	GETTABLE 	16 0 -22	; "rock_license"
	98	[286]	TEST     	16 0 0
	99	[286]	JMP      	5	; to 105
	100	[286]	GETUPVAL 	16 5	; util
	101	[286]	GETTABLE 	16 16 -17	; "printout"
	102	[286]	GETTABLE 	17 12 -23	; "license"
	103	[286]	CALL     	16 2 1
	104	[286]	JMP      	122	; to 227
	105	[287]	GETTABLE 	16 0 -24	; "issues"
	106	[287]	TEST     	16 0 0
	107	[287]	JMP      	5	; to 113
	108	[287]	GETUPVAL 	16 5	; util
	109	[287]	GETTABLE 	16 16 -17	; "printout"
	110	[287]	GETTABLE 	17 12 -25	; "issues_url"
	111	[287]	CALL     	16 2 1
	112	[287]	JMP      	114	; to 227
	113	[288]	GETTABLE 	16 0 -26	; "labels"
	114	[288]	TEST     	16 0 0
	115	[288]	JMP      	12	; to 128
	116	[288]	GETUPVAL 	16 5	; util
	117	[288]	GETTABLE 	16 16 -17	; "printout"
	118	[288]	GETTABLE 	17 12 -26	; "labels"
	119	[288]	TEST     	17 0 0
	120	[288]	JMP      	5	; to 126
	121	[288]	GETGLOBAL	17 -27	; table
	122	[288]	GETTABLE 	17 17 -28	; "concat"
	123	[288]	GETTABLE 	18 12 -26	; "labels"
	124	[288]	LOADK    	19 -29	; "\n"
	125	[288]	CALL     	17 3 2
	126	[288]	CALL     	16 2 1
	127	[288]	JMP      	99	; to 227
	128	[289]	GETTABLE 	16 0 -30	; "modules"
	129	[289]	TEST     	16 0 0
	130	[289]	JMP      	8	; to 139
	131	[289]	GETUPVAL 	16 5	; util
	132	[289]	GETTABLE 	16 16 -17	; "printout"
	133	[289]	GETUPVAL 	17 6	; keys_as_string
	134	[289]	GETTABLE 	18 15 -30	; "modules"
	135	[289]	LOADK    	19 -29	; "\n"
	136	[289]	CALL     	17 3 0
	137	[289]	CALL     	16 0 1
	138	[289]	JMP      	88	; to 227
	139	[290]	GETTABLE 	16 0 -31	; "deps"
	140	[290]	TEST     	16 0 0
	141	[290]	JMP      	13	; to 155
	142	[291]	GETGLOBAL	16 -32	; ipairs
	143	[291]	GETTABLE 	17 10 -33	; "dependencies"
	144	[291]	CALL     	16 2 4
	145	[291]	JMP      	6	; to 152
	146	[292]	GETUPVAL 	21 5	; util
	147	[292]	GETTABLE 	21 21 -17	; "printout"
	148	[292]	GETGLOBAL	22 -34	; tostring
	149	[292]	MOVE     	23 20
	150	[292]	CALL     	22 2 0
	151	[292]	CALL     	21 0 1
	152	[291]	TFORLOOP 	16 2
	153	[292]	JMP      	-8	; to 146
	154	[293]	JMP      	72	; to 227
	155	[294]	GETTABLE 	16 0 -35	; "build_deps"
	156	[294]	TEST     	16 0 0
	157	[294]	JMP      	13	; to 171
	158	[295]	GETGLOBAL	16 -32	; ipairs
	159	[295]	GETTABLE 	17 10 -36	; "build_dependencies"
	160	[295]	CALL     	16 2 4
	161	[295]	JMP      	6	; to 168
	162	[296]	GETUPVAL 	21 5	; util
	163	[296]	GETTABLE 	21 21 -17	; "printout"
	164	[296]	GETGLOBAL	22 -34	; tostring
	165	[296]	MOVE     	23 20
	166	[296]	CALL     	22 2 0
	167	[296]	CALL     	21 0 1
	168	[295]	TFORLOOP 	16 2
	169	[296]	JMP      	-8	; to 162
	170	[297]	JMP      	56	; to 227
	171	[298]	GETTABLE 	16 0 -37	; "test_deps"
	172	[298]	TEST     	16 0 0
	173	[298]	JMP      	13	; to 187
	174	[299]	GETGLOBAL	16 -32	; ipairs
	175	[299]	GETTABLE 	17 10 -38	; "test_dependencies"
	176	[299]	CALL     	16 2 4
	177	[299]	JMP      	6	; to 184
	178	[300]	GETUPVAL 	21 5	; util
	179	[300]	GETTABLE 	21 21 -17	; "printout"
	180	[300]	GETGLOBAL	22 -34	; tostring
	181	[300]	MOVE     	23 20
	182	[300]	CALL     	22 2 0
	183	[300]	CALL     	21 0 1
	184	[299]	TFORLOOP 	16 2
	185	[300]	JMP      	-8	; to 178
	186	[301]	JMP      	40	; to 227
	187	[302]	GETTABLE 	16 0 -39	; "rockspec"
	188	[302]	TEST     	16 0 0
	189	[302]	JMP      	5	; to 195
	190	[302]	GETUPVAL 	16 5	; util
	191	[302]	GETTABLE 	16 16 -17	; "printout"
	192	[302]	MOVE     	17 9
	193	[302]	CALL     	16 2 1
	194	[302]	JMP      	32	; to 227
	195	[303]	GETTABLE 	16 0 -40	; "mversion"
	196	[303]	TEST     	16 0 0
	197	[303]	JMP      	5	; to 203
	198	[303]	GETUPVAL 	16 5	; util
	199	[303]	GETTABLE 	16 16 -17	; "printout"
	200	[303]	MOVE     	17 3
	201	[303]	CALL     	16 2 1
	202	[303]	JMP      	24	; to 227
	203	[304]	GETTABLE 	16 0 -41	; "porcelain"
	204	[304]	TEST     	16 0 0
	205	[304]	JMP      	11	; to 217
	206	[305]	GETUPVAL 	16 7	; show_rock
	207	[305]	GETUPVAL 	17 8	; porcelain_template
	208	[305]	MOVE     	18 8
	209	[305]	MOVE     	19 2
	210	[305]	MOVE     	20 3
	211	[305]	MOVE     	21 10
	212	[305]	MOVE     	22 4
	213	[305]	MOVE     	23 15
	214	[305]	GETTABLE 	24 0 -6	; "tree"
	215	[305]	CALL     	16 9 1
	216	[305]	JMP      	10	; to 227
	217	[307]	GETUPVAL 	16 7	; show_rock
	218	[307]	GETUPVAL 	17 9	; friendly_template
	219	[307]	MOVE     	18 8
	220	[307]	MOVE     	19 2
	221	[307]	MOVE     	20 3
	222	[307]	MOVE     	21 10
	223	[307]	MOVE     	22 4
	224	[307]	MOVE     	23 15
	225	[307]	GETTABLE 	24 0 -6	; "tree"
	226	[307]	CALL     	16 9 1
	227	[309]	LOADBOOL 	16 1 0
	228	[309]	RETURN   	16 2
	229	[310]	RETURN   	0 1
