
main <./signing.lua:0,0> (22 instructions, 88 bytes at 0x7f81904068a0)
0+ params, 5 slots, 0 upvalues, 4 locals, 6 constants, 4 functions
	1	[1]	NEWTABLE 	0 0 0
	2	[3]	GETGLOBAL	1 -1	; require
	3	[3]	LOADK    	2 -2	; "luarocks.core.cfg"
	4	[3]	CALL     	1 2 2
	5	[4]	GETGLOBAL	2 -1	; require
	6	[4]	LOADK    	3 -3	; "luarocks.fs"
	7	[4]	CALL     	2 2 2
	8	[14]	CLOSURE  	3 0	; 0x7f8190406b90
	9	[14]	MOVE     	0 1
	10	[14]	MOVE     	0 2
	11	[18]	CLOSURE  	4 1	; 0x7f8190407140
	12	[16]	SETTABLE 	0 -4 4	; "signature_url" -
	13	[32]	CLOSURE  	4 2	; 0x7f8190407270
	14	[32]	MOVE     	0 3
	15	[32]	MOVE     	0 2
	16	[20]	SETTABLE 	0 -5 4	; "sign_file" -
	17	[46]	CLOSURE  	4 3	; 0x7f8190407700
	18	[46]	MOVE     	0 3
	19	[46]	MOVE     	0 2
	20	[34]	SETTABLE 	0 -6 4	; "verify_signature" -
	21	[48]	RETURN   	0 2
	22	[48]	RETURN   	0 1

function <./signing.lua:6,14> (15 instructions, 60 bytes at 0x7f8190406b90)
0 params, 6 slots, 2 upvalues, 4 locals, 4 constants, 0 functions
	1	[7]	GETUPVAL 	0 0	; cfg
	2	[7]	GETTABLE 	0 0 -1	; "variables"
	3	[8]	GETTABLE 	1 0 -2	; "GPG"
	4	[9]	GETUPVAL 	2 1	; fs
	5	[9]	GETTABLE 	2 2 -3	; "is_tool_available"
	6	[9]	MOVE     	3 1
	7	[9]	LOADK    	4 -4	; "gpg"
	8	[9]	CALL     	2 3 3
	9	[10]	TEST     	2 0 1
	10	[10]	JMP      	3	; to 14
	11	[11]	LOADNIL  	4 4
	12	[11]	MOVE     	5 3
	13	[11]	RETURN   	4 3
	14	[13]	RETURN   	1 2
	15	[14]	RETURN   	0 1

function <./signing.lua:16,18> (5 instructions, 20 bytes at 0x7f8190407140)
1 param, 3 slots, 0 upvalues, 1 local, 1 constant, 0 functions
	1	[17]	MOVE     	1 0
	2	[17]	LOADK    	2 -1	; ".asc"
	3	[17]	CONCAT   	1 1 2
	4	[17]	RETURN   	1 2
	5	[18]	RETURN   	0 1

function <./signing.lua:20,32> (31 instructions, 124 bytes at 0x7f8190407270)
1 param, 11 slots, 2 upvalues, 4 locals, 7 constants, 0 functions
	1	[21]	GETUPVAL 	1 0	; get_gpg
	2	[21]	CALL     	1 1 3
	3	[22]	TEST     	1 0 1
	4	[22]	JMP      	3	; to 8
	5	[23]	LOADNIL  	3 3
	6	[23]	MOVE     	4 2
	7	[23]	RETURN   	3 3
	8	[26]	MOVE     	3 0
	9	[26]	LOADK    	4 -1	; ".asc"
	10	[26]	CONCAT   	3 3 4
	11	[27]	GETUPVAL 	4 1	; fs
	12	[27]	GETTABLE 	4 4 -2	; "execute"
	13	[27]	MOVE     	5 1
	14	[27]	LOADK    	6 -3	; "--armor"
	15	[27]	LOADK    	7 -4	; "--output"
	16	[27]	MOVE     	8 3
	17	[27]	LOADK    	9 -5	; "--detach-sign"
	18	[27]	MOVE     	10 0
	19	[27]	CALL     	4 7 2
	20	[27]	TEST     	4 0 0
	21	[27]	JMP      	2	; to 24
	22	[28]	RETURN   	3 2
	23	[28]	JMP      	7	; to 31
	24	[30]	LOADNIL  	4 4
	25	[30]	LOADK    	5 -6	; "failed running "
	26	[30]	MOVE     	6 1
	27	[30]	LOADK    	7 -7	; " to sign "
	28	[30]	MOVE     	8 0
	29	[30]	CONCAT   	5 5 8
	30	[30]	RETURN   	4 3
	31	[32]	RETURN   	0 1

function <./signing.lua:34,46> (23 instructions, 92 bytes at 0x7f8190407700)
2 params, 9 slots, 2 upvalues, 4 locals, 3 constants, 0 functions
	1	[35]	GETUPVAL 	2 0	; get_gpg
	2	[35]	CALL     	2 1 3
	3	[36]	TEST     	2 0 1
	4	[36]	JMP      	3	; to 8
	5	[37]	LOADNIL  	4 4
	6	[37]	MOVE     	5 3
	7	[37]	RETURN   	4 3
	8	[40]	GETUPVAL 	4 1	; fs
	9	[40]	GETTABLE 	4 4 -1	; "execute"
	10	[40]	MOVE     	5 2
	11	[40]	LOADK    	6 -2	; "--verify"
	12	[40]	MOVE     	7 1
	13	[40]	MOVE     	8 0
	14	[40]	CALL     	4 5 2
	15	[40]	TEST     	4 0 0
	16	[40]	JMP      	3	; to 20
	17	[41]	LOADBOOL 	4 1 0
	18	[41]	RETURN   	4 2
	19	[41]	JMP      	3	; to 23
	20	[43]	LOADNIL  	4 4
	21	[43]	LOADK    	5 -3	; "GPG returned a verification error"
	22	[43]	RETURN   	4 3
	23	[46]	RETURN   	0 1
