
main <./fetch/sscm.lua:0,0> (13 instructions, 52 bytes at 0x7f8e254068a0)
0+ params, 4 slots, 0 upvalues, 3 locals, 4 constants, 1 function
	1	[3]	NEWTABLE 	0 0 0
	2	[5]	GETGLOBAL	1 -1	; require
	3	[5]	LOADK    	2 -2	; "luarocks.fs"
	4	[5]	CALL     	1 2 2
	5	[6]	GETGLOBAL	2 -1	; require
	6	[6]	LOADK    	3 -3	; "luarocks.dir"
	7	[6]	CALL     	2 2 2
	8	[42]	CLOSURE  	3 0	; 0x7f8e25406b90
	9	[42]	MOVE     	0 2
	10	[42]	MOVE     	0 1
	11	[15]	SETTABLE 	0 -4 3	; "get_sources" -
	12	[44]	RETURN   	0 2
	13	[44]	RETURN   	0 1

function <./fetch/sscm.lua:15,42> (101 instructions, 404 bytes at 0x7f8e25406b90)
3 params, 19 slots, 2 upvalues, 13 locals, 32 constants, 0 functions
	1	[16]	GETGLOBAL	3 -1	; assert
	2	[16]	SELF     	4 0 -2	; "type"
	3	[16]	CALL     	4 2 2
	4	[16]	EQ       	1 4 -3	; - "rockspec"
	5	[16]	JMP      	1	; to 7
	6	[16]	LOADBOOL 	4 0 1
	7	[16]	LOADBOOL 	4 1 0
	8	[16]	CALL     	3 2 1
	9	[17]	GETGLOBAL	3 -1	; assert
	10	[17]	GETGLOBAL	4 -2	; type
	11	[17]	MOVE     	5 2
	12	[17]	CALL     	4 2 2
	13	[17]	EQ       	1 4 -4	; - "string"
	14	[17]	JMP      	3	; to 18
	15	[17]	NOT      	4 2
	16	[17]	JMP      	2	; to 19
	17	[17]	LOADBOOL 	4 0 1
	18	[17]	LOADBOOL 	4 1 0
	19	[17]	CALL     	3 2 1
	20	[19]	GETTABLE 	3 0 -5	; "variables"
	21	[19]	GETTABLE 	3 3 -6	; "SSCM"
	22	[20]	GETTABLE 	4 0 -7	; "source"
	23	[20]	GETTABLE 	4 4 -8	; "module"
	24	[20]	TEST     	4 0 1
	25	[20]	JMP      	5	; to 31
	26	[20]	GETUPVAL 	4 0	; dir
	27	[20]	GETTABLE 	4 4 -9	; "base_name"
	28	[20]	GETTABLE 	5 0 -7	; "source"
	29	[20]	GETTABLE 	5 5 -10	; "url"
	30	[20]	CALL     	4 2 2
	31	[21]	GETGLOBAL	5 -4	; string
	32	[21]	GETTABLE 	5 5 -11	; "match"
	33	[21]	GETTABLE 	6 0 -7	; "source"
	34	[21]	GETTABLE 	6 6 -12	; "pathname"
	35	[21]	LOADK    	7 -13	; "^([^/]*)/(.*)"
	36	[21]	CALL     	5 3 3
	37	[22]	TEST     	5 0 0
	38	[22]	JMP      	2	; to 41
	39	[22]	TEST     	6 0 1
	40	[22]	JMP      	3	; to 44
	41	[23]	LOADNIL  	7 7
	42	[23]	LOADK    	8 -14	; "Error retrieving branch and repository from rockspec."
	43	[23]	RETURN   	7 3
	44	[26]	LOADNIL  	7 7
	45	[27]	GETGLOBAL	8 -15	; io
	46	[27]	GETTABLE 	8 8 -16	; "popen"
	47	[27]	GETGLOBAL	9 -4	; string
	48	[27]	GETTABLE 	9 9 -17	; "format"
	49	[27]	MOVE     	10 3
	50	[27]	LOADK    	11 -18	; " property \"/\" -d -b%s -p%s"
	51	[27]	CONCAT   	10 10 11
	52	[27]	MOVE     	11 5
	53	[27]	MOVE     	12 6
	54	[27]	CALL     	9 4 0
	55	[27]	CALL     	8 0 2
	56	[28]	SELF     	9 8 -19	; "lines"
	57	[28]	CALL     	9 2 4
	58	[28]	JMP      	9	; to 68
	59	[30]	GETGLOBAL	13 -4	; string
	60	[30]	GETTABLE 	13 13 -11	; "match"
	61	[30]	MOVE     	14 12
	62	[30]	LOADK    	15 -20	; "Working directory:[%s]*(.*)%c$"
	63	[30]	CALL     	13 3 2
	64	[30]	MOVE     	7 13
	65	[31]	TEST     	7 0 0
	66	[31]	JMP      	1	; to 68
	67	[31]	JMP      	2	; to 70
	68	[28]	TFORLOOP 	9 1
	69	[31]	JMP      	-11	; to 59
	70	[33]	SELF     	9 8 -21	; "close"
	71	[33]	CALL     	9 2 1
	72	[34]	TEST     	7 0 1
	73	[34]	JMP      	3	; to 77
	74	[35]	LOADNIL  	9 9
	75	[35]	LOADK    	10 -22	; "Error retrieving working directory from SSCM."
	76	[35]	RETURN   	9 3
	77	[37]	GETUPVAL 	9 1	; fs
	78	[37]	GETTABLE 	9 9 -23	; "execute"
	79	[37]	MOVE     	10 3
	80	[37]	LOADK    	11 -24	; "get"
	81	[37]	LOADK    	12 -25	; "*"
	82	[37]	LOADK    	13 -26	; "-e"
	83	[37]	LOADK    	14 -27	; "-r"
	84	[37]	LOADK    	15 -28	; "-b"
	85	[37]	MOVE     	16 5
	86	[37]	CONCAT   	15 15 16
	87	[37]	LOADK    	16 -29	; "-p"
	88	[37]	MOVE     	17 6
	89	[37]	CONCAT   	16 16 17
	90	[37]	LOADK    	17 -30	; "-tmodify"
	91	[37]	LOADK    	18 -31	; "-wreplace"
	92	[37]	CALL     	9 10 2
	93	[37]	TEST     	9 0 1
	94	[37]	JMP      	3	; to 98
	95	[38]	LOADNIL  	9 9
	96	[38]	LOADK    	10 -32	; "Failed fetching files from SSCM."
	97	[38]	RETURN   	9 3
	98	[41]	MOVE     	9 4
	99	[41]	MOVE     	10 7
	100	[41]	RETURN   	9 3
	101	[42]	RETURN   	0 1
