-- BYTECODE -- svn.lua:18-61
0001    GGET     3   0      ; "assert"
0002    MOV      5   0
0003    TGETS    4   0   1  ; "type"
0004    CALL     4   2   2
0005    ISEQS    4   2      ; "rockspec"
0006    JMP      4 => 0009
0007    KPRI     4   1
0008    JMP      5 => 0010
0009 => KPRI     4   2
0010 => CALL     3   1   2
0011    GGET     3   0      ; "assert"
0012    GGET     4   1      ; "type"
0013    MOV      5   2
0014    CALL     4   2   2
0015    ISEQS    4   3      ; "string"
0016    JMP      4 => 0021
0017    NOT      4   2
0018    JMP      5 => 0022
0019    KPRI     4   1
0020    JMP      5 => 0022
0021 => KPRI     4   2
0022 => CALL     3   1   2
0023    TGETS    3   0   4  ; "variables"
0024    TGETS    3   3   5  ; "SVN"
0025    UGET     4   0      ; fs
0026    TGETS    4   4   6  ; "is_tool_available"
0027    MOV      5   3
0028    KSTR     6   7      ; "--version"
0029    KSTR     7   8      ; "Subversion"
0030    CALL     4   3   4
0031    IST          4
0032    JMP      6 => 0036
0033    KPRI     6   0
0034    MOV      7   5
0035    RET      6   3
0036 => TGETS    6   0   9  ; "name"
0037    KSTR     7  10      ; "-"
0038    TGETS    8   0  11  ; "version"
0039    CAT      6   6   8
0040    TGETS    7   0  12  ; "source"
0041    TGETS    7   7  13  ; "module"
0042    IST          7
0043    JMP      8 => 0049
0044    UGET     7   1      ; dir
0045    TGETS    7   7  14  ; "base_name"
0046    TGETS    8   0  12  ; "source"
0047    TGETS    8   8  15  ; "url"
0048    CALL     7   2   2
0049 => TGETS    8   0  12  ; "source"
0050    TGETS    8   8  15  ; "url"
0051    MOV      9   8
0052    TGETS    8   8  16  ; "gsub"
0053    KSTR    10  17      ; "^svn://"
0054    KSTR    11  18      ; ""
0055    CALL     8   2   4
0056    TDUP     9  19
0057    TSETB    3   9   1
0058    TSETB    8   9   3
0059    TSETB    7   9   4
0060    TGETS   10   0  12  ; "source"
0061    TGETS   10  10  20  ; "tag"
0062    ISF         10
0063    JMP     11 => 0077
0064    GGET    10  21      ; "table"
0065    TGETS   10  10  22  ; "insert"
0066    MOV     11   9
0067    KSHORT  12   5
0068    KSTR    13  23      ; "-r"
0069    CALL    10   1   4
0070    GGET    10  21      ; "table"
0071    TGETS   10  10  22  ; "insert"
0072    MOV     11   9
0073    KSHORT  12   6
0074    TGETS   13   0  12  ; "source"
0075    TGETS   13  13  20  ; "tag"
0076    CALL    10   1   4
0077 => KPRI    10   0
0078    IST          2
0079    JMP     11 => 0097
0080    UGET    11   0      ; fs
0081    TGETS   11  11  24  ; "make_temp_dir"
0082    MOV     12   6
0083    CALL    11   2   2
0084    MOV     10  11
0085    IST         10
0086    JMP     11 => 0090
0087    KPRI    11   0
0088    KSTR    12  25      ; "Failed creating temporary directory."
0089    RET     11   3
0090 => UGET    11   2      ; util
0091    TGETS   11  11  26  ; "schedule_function"
0092    UGET    12   0      ; fs
0093    TGETS   12  12  27  ; "delete"
0094    MOV     13  10
0095    CALL    11   1   3
0096    JMP     11 => 0098
0097 => MOV     10   2
0098 => UGET    11   0      ; fs
0099    TGETS   11  11  28  ; "change_dir"
0100    MOV     12  10
0101    CALL    11   3   2
0102    IST         11
0103    JMP     13 => 0107
0104    KPRI    13   0
0105    MOV     14  12
0106    RET     13   3
0107 => UGET    13   0      ; fs
0108    TGETS   13  13  29  ; "execute"
0109    UGET    14   3      ; unpack
0110    MOV     15   9
0111    CALL    14   0   2
0112    CALLM   13   2   0
0113    IST         13
0114    JMP     13 => 0118
0115    KPRI    13   0
0116    KSTR    14  30      ; "Failed fetching files from Subversion."
0117    RET     13   3
0118 => UGET    13   0      ; fs
0119    TGETS   13  13  28  ; "change_dir"
0120    MOV     14   7
0121    CALL    13   3   2
0122    MOV     12  14
0123    MOV     11  13
0124    IST         11
0125    JMP     13 => 0129
0126    KPRI    13   0
0127    MOV     14  12
0128    RET     13   3
0129 => GGET    13  31      ; "ipairs"
0130    UGET    14   0      ; fs
0131    TGETS   14  14  32  ; "find"
0132    KSTR    15  33      ; "."
0133    CALL    14   0   2
0134    CALLM   13   4   0
0135    JMP     16 => 0151
0136 => UGET    18   1      ; dir
0137    TGETS   18  18  14  ; "base_name"
0138    MOV     19  17
0139    CALL    18   2   2
0140    ISNES   18  34      ; ".svn"
0141    JMP     18 => 0151
0142    UGET    18   0      ; fs
0143    TGETS   18  18  27  ; "delete"
0144    UGET    19   1      ; dir
0145    TGETS   19  19  35  ; "path"
0146    MOV     20  10
0147    MOV     21   7
0148    MOV     22  17
0149    CALL    19   0   4
0150    CALLM   18   1   0
0151 => ITERC   16   3   3
0152    ITERL   16 => 0136
0153    UGET    13   0      ; fs
0154    TGETS   13  13  36  ; "pop_dir"
0155    CALL    13   1   1
0156    UGET    13   0      ; fs
0157    TGETS   13  13  36  ; "pop_dir"
0158    CALL    13   1   1
0159    MOV     13   7
0160    MOV     14  10
0161    RET     13   3

-- BYTECODE -- svn.lua:0-65
0001    TNEW     0   0
0002    GGET     1   0      ; "unpack"
0003    IST          1
0004    JMP      2 => 0007
0005    GGET     1   1      ; "table"
0006    TGETS    1   1   0  ; "unpack"
0007 => GGET     2   2      ; "require"
0008    KSTR     3   3      ; "luarocks.fs"
0009    CALL     2   2   2
0010    GGET     3   2      ; "require"
0011    KSTR     4   4      ; "luarocks.dir"
0012    CALL     3   2   2
0013    GGET     4   2      ; "require"
0014    KSTR     5   5      ; "luarocks.util"
0015    CALL     4   2   2
0016    FNEW     5   7      ; svn.lua:18
0017    TSETS    5   0   6  ; "get_sources"
0018    UCLO     0 => 0019
0019 => RET1     0   2

