
main <./test.lua:0,0> (39 instructions, 156 bytes at 0x7ff9394068a0)
0+ params, 14 slots, 0 upvalues, 12 locals, 10 constants, 2 functions
	1	[2]	NEWTABLE 	0 0 0
	2	[4]	GETGLOBAL	1 -1	; require
	3	[4]	LOADK    	2 -2	; "luarocks.fetch"
	4	[4]	CALL     	1 2 2
	5	[5]	GETGLOBAL	2 -1	; require
	6	[5]	LOADK    	3 -3	; "luarocks.deps"
	7	[5]	CALL     	2 2 2
	8	[7]	NEWTABLE 	3 2 0
	9	[8]	LOADK    	4 -4	; "busted"
	10	[10]	LOADK    	5 -5	; "command"
	11	[10]	SETLIST  	3 2 1	; 1
	12	[12]	NEWTABLE 	4 0 0
	13	[14]	GETGLOBAL	5 -6	; ipairs
	14	[14]	MOVE     	6 3
	15	[14]	CALL     	5 2 4
	16	[14]	JMP      	12	; to 29
	17	[15]	GETGLOBAL	10 -1	; require
	18	[15]	LOADK    	11 -7	; "luarocks.test."
	19	[15]	MOVE     	12 9
	20	[15]	CONCAT   	11 11 12
	21	[15]	CALL     	10 2 2
	22	[16]	GETGLOBAL	11 -8	; table
	23	[16]	GETTABLE 	11 11 -9	; "insert"
	24	[16]	MOVE     	12 4
	25	[16]	MOVE     	13 10
	26	[16]	CALL     	11 3 1
	27	[17]	SETTABLE 	4 9 10
	28	[18]	SETTABLE 	4 10 9
	29	[14]	TFORLOOP 	5 2
	30	[18]	JMP      	-14	; to 17
	31	[33]	CLOSURE  	5 0	; 0x7ff939406c30
	32	[33]	MOVE     	0 4
	33	[72]	CLOSURE  	6 1	; 0x7ff9394072e0
	34	[72]	MOVE     	0 1
	35	[72]	MOVE     	0 5
	36	[72]	MOVE     	0 2
	37	[36]	SETTABLE 	0 -10 6	; "run_test_suite" -
	38	[74]	RETURN   	0 2
	39	[74]	RETURN   	0 1

function <./test.lua:21,33> (30 instructions, 120 bytes at 0x7ff939406c30)
1 param, 7 slots, 1 upvalue, 6 locals, 7 constants, 0 functions
	1	[22]	GETTABLE 	1 0 -1	; "test"
	2	[22]	TEST     	1 0 0
	3	[22]	JMP      	7	; to 11
	4	[22]	GETTABLE 	1 0 -1	; "test"
	5	[22]	GETTABLE 	1 1 -2	; "type"
	6	[22]	TEST     	1 0 0
	7	[22]	JMP      	3	; to 11
	8	[23]	GETTABLE 	1 0 -1	; "test"
	9	[23]	GETTABLE 	1 1 -2	; "type"
	10	[23]	RETURN   	1 2
	11	[26]	GETGLOBAL	1 -3	; ipairs
	12	[26]	GETUPVAL 	2 0	; test_modules
	13	[26]	CALL     	1 2 4
	14	[26]	JMP      	7	; to 22
	15	[27]	GETTABLE 	6 5 -4	; "detect_type"
	16	[27]	CALL     	6 1 2
	17	[27]	TEST     	6 0 0
	18	[27]	JMP      	3	; to 22
	19	[28]	GETUPVAL 	6 0	; test_modules
	20	[28]	GETTABLE 	6 6 5
	21	[28]	RETURN   	6 2
	22	[26]	TFORLOOP 	1 2
	23	[29]	JMP      	-9	; to 15
	24	[32]	LOADNIL  	1 1
	25	[32]	LOADK    	2 -5	; "could not detect test type -- no test suite for "
	26	[32]	GETTABLE 	3 0 -6	; "package"
	27	[32]	LOADK    	4 -7	; "?"
	28	[32]	CONCAT   	2 2 4
	29	[32]	RETURN   	1 3
	30	[33]	RETURN   	0 1

function <./test.lua:36,72> (84 instructions, 336 bytes at 0x7ff9394072e0)
3 params, 10 slots, 3 upvalues, 13 locals, 15 constants, 0 functions
	1	[38]	GETGLOBAL	4 -1	; type
	2	[38]	MOVE     	5 0
	3	[38]	CALL     	4 2 2
	4	[38]	EQ       	0 4 -2	; - "string"
	5	[38]	JMP      	15	; to 21
	6	[39]	LOADNIL  	4 5
	7	[40]	GETUPVAL 	6 0	; fetch
	8	[40]	GETTABLE 	6 6 -3	; "load_rockspec"
	9	[40]	MOVE     	7 0
	10	[40]	CALL     	6 2 4
	11	[40]	MOVE     	5 8
	12	[40]	MOVE     	4 7
	13	[40]	MOVE     	3 6
	14	[41]	TEST     	4 0 0
	15	[41]	JMP      	15	; to 31
	16	[42]	LOADNIL  	6 6
	17	[42]	MOVE     	7 4
	18	[42]	MOVE     	8 5
	19	[42]	RETURN   	6 4
	20	[43]	JMP      	10	; to 31
	21	[45]	GETGLOBAL	4 -4	; assert
	22	[45]	GETGLOBAL	5 -1	; type
	23	[45]	MOVE     	6 0
	24	[45]	CALL     	5 2 2
	25	[45]	EQ       	1 5 -5	; - "table"
	26	[45]	JMP      	1	; to 28
	27	[45]	LOADBOOL 	5 0 1
	28	[45]	LOADBOOL 	5 1 0
	29	[45]	CALL     	4 2 1
	30	[46]	MOVE     	3 0
	31	[49]	TEST     	1 0 1
	32	[49]	JMP      	12	; to 45
	33	[50]	LOADNIL  	4 4
	34	[51]	GETUPVAL 	5 1	; get_test_type
	35	[51]	MOVE     	6 3
	36	[51]	MOVE     	7 1
	37	[51]	CALL     	5 3 3
	38	[51]	MOVE     	4 6
	39	[51]	MOVE     	1 5
	40	[52]	TEST     	1 0 1
	41	[52]	JMP      	3	; to 45
	42	[53]	LOADNIL  	5 5
	43	[53]	MOVE     	6 4
	44	[53]	RETURN   	5 3
	45	[56]	GETGLOBAL	4 -4	; assert
	46	[56]	MOVE     	5 1
	47	[56]	CALL     	4 2 1
	48	[58]	GETGLOBAL	4 -6	; next
	49	[58]	GETTABLE 	5 3 -7	; "test_dependencies"
	50	[58]	CALL     	4 2 2
	51	[58]	TEST     	4 0 0
	52	[58]	JMP      	12	; to 65
	53	[59]	GETUPVAL 	4 2	; deps
	54	[59]	GETTABLE 	4 4 -8	; "fulfill_dependencies"
	55	[59]	MOVE     	5 3
	56	[59]	LOADK    	6 -7	; "test_dependencies"
	57	[59]	LOADK    	7 -9	; "all"
	58	[59]	CALL     	4 4 4
	59	[60]	TEST     	5 0 0
	60	[60]	JMP      	4	; to 65
	61	[61]	LOADNIL  	7 7
	62	[61]	MOVE     	8 5
	63	[61]	MOVE     	9 6
	64	[61]	RETURN   	7 4
	65	[65]	LOADK    	4 -10	; "luarocks.test."
	66	[65]	MOVE     	5 1
	67	[65]	CONCAT   	4 4 5
	68	[66]	GETGLOBAL	5 -11	; pcall
	69	[66]	GETGLOBAL	6 -12	; require
	70	[66]	MOVE     	7 4
	71	[66]	CALL     	5 3 3
	72	[67]	TEST     	5 0 1
	73	[67]	JMP      	5	; to 79
	74	[68]	LOADNIL  	7 7
	75	[68]	LOADK    	8 -13	; "failed loading test execution module "
	76	[68]	MOVE     	9 4
	77	[68]	CONCAT   	8 8 9
	78	[68]	RETURN   	7 3
	79	[71]	GETTABLE 	7 6 -14	; "run_tests"
	80	[71]	GETTABLE 	8 3 -15	; "test"
	81	[71]	MOVE     	9 2
	82	[71]	TAILCALL 	7 3 0
	83	[71]	RETURN   	7 0
	84	[72]	RETURN   	0 1
