-- BYTECODE -- test.lua:21-33
0001    TGETS    1   0   0  ; "test"
0002    ISF          1
0003    JMP      2 => 0011
0004    TGETS    1   0   0  ; "test"
0005    TGETS    1   1   1  ; "type"
0006    ISF          1
0007    JMP      2 => 0011
0008    TGETS    1   0   0  ; "test"
0009    TGETS    1   1   1  ; "type"
0010    RET1     1   2
0011 => GGET     1   2      ; "ipairs"
0012    UGET     2   0      ; test_modules
0013    CALL     1   4   2
0014    JMP      4 => 0022
0015 => TGETS    6   5   3  ; "detect_type"
0016    CALL     6   2   1
0017    ISF          6
0018    JMP      7 => 0022
0019    UGET     6   0      ; test_modules
0020    TGETV    6   6   5
0021    RET1     6   2
0022 => ITERC    4   3   3
0023    ITERL    4 => 0015
0024    KPRI     1   0
0025    KSTR     2   4      ; "could not detect test type -- no test su"~
0026    TGETS    3   0   5  ; "package"
0027    KSTR     4   6      ; "?"
0028    CAT      2   2   4
0029    RET      1   3

-- BYTECODE -- test.lua:36-72
0001    KPRI     3   0
0002    GGET     4   0      ; "type"
0003    MOV      5   0
0004    CALL     4   2   2
0005    ISNES    4   1      ; "string"
0006    JMP      4 => 0022
0007    KNIL     4   5
0008    UGET     6   0      ; fetch
0009    TGETS    6   6   2  ; "load_rockspec"
0010    MOV      7   0
0011    CALL     6   4   2
0012    MOV      5   8
0013    MOV      4   7
0014    MOV      3   6
0015    ISF          4
0016    JMP      6 => 0033
0017    KPRI     6   0
0018    MOV      7   4
0019    MOV      8   5
0020    RET      6   4
0021    JMP      4 => 0033
0022 => GGET     4   3      ; "assert"
0023    GGET     5   0      ; "type"
0024    MOV      6   0
0025    CALL     5   2   2
0026    ISEQS    5   4      ; "table"
0027    JMP      5 => 0030
0028    KPRI     5   1
0029    JMP      6 => 0031
0030 => KPRI     5   2
0031 => CALL     4   1   2
0032    MOV      3   0
0033 => IST          1
0034    JMP      4 => 0047
0035    KPRI     4   0
0036    UGET     5   1      ; get_test_type
0037    MOV      6   3
0038    MOV      7   1
0039    CALL     5   3   3
0040    MOV      4   6
0041    MOV      1   5
0042    IST          1
0043    JMP      5 => 0047
0044    KPRI     5   0
0045    MOV      6   4
0046    RET      5   3
0047 => GGET     4   3      ; "assert"
0048    MOV      5   1
0049    CALL     4   1   2
0050    GGET     4   5      ; "next"
0051    TGETS    5   3   6  ; "test_dependencies"
0052    CALL     4   2   2
0053    ISF          4
0054    JMP      5 => 0067
0055    UGET     4   2      ; deps
0056    TGETS    4   4   7  ; "fulfill_dependencies"
0057    MOV      5   3
0058    KSTR     6   6      ; "test_dependencies"
0059    KSTR     7   8      ; "all"
0060    CALL     4   4   4
0061    ISF          5
0062    JMP      7 => 0067
0063    KPRI     7   0
0064    MOV      8   5
0065    MOV      9   6
0066    RET      7   4
0067 => KSTR     4   9      ; "luarocks.test."
0068    MOV      5   1
0069    CAT      4   4   5
0070    GGET     5  10      ; "pcall"
0071    GGET     6  11      ; "require"
0072    MOV      7   4
0073    CALL     5   3   3
0074    IST          5
0075    JMP      7 => 0081
0076    KPRI     7   0
0077    KSTR     8  12      ; "failed loading test execution module "
0078    MOV      9   4
0079    CAT      8   8   9
0080    RET      7   3
0081 => TGETS    7   6  13  ; "run_tests"
0082    TGETS    8   3  14  ; "test"
0083    MOV      9   2
0084    CALLT    7   3

-- BYTECODE -- test.lua:0-75
0001    TNEW     0   0
0002    GGET     1   0      ; "require"
0003    KSTR     2   1      ; "luarocks.fetch"
0004    CALL     1   2   2
0005    GGET     2   0      ; "require"
0006    KSTR     3   2      ; "luarocks.deps"
0007    CALL     2   2   2
0008    TDUP     3   3
0009    TNEW     4   0
0010    GGET     5   4      ; "ipairs"
0011    MOV      6   3
0012    CALL     5   4   2
0013    JMP      8 => 0026
0014 => GGET    10   0      ; "require"
0015    KSTR    11   5      ; "luarocks.test."
0016    MOV     12   9
0017    CAT     11  11  12
0018    CALL    10   2   2
0019    GGET    11   6      ; "table"
0020    TGETS   11  11   7  ; "insert"
0021    MOV     12   4
0022    MOV     13  10
0023    CALL    11   1   3
0024    TSETV   10   4   9
0025    TSETV    9   4  10
0026 => ITERC    8   3   3
0027    ITERL    8 => 0014
0028    FNEW     5   8      ; test.lua:21
0029    FNEW     6  10      ; test.lua:36
0030    TSETS    6   0   9  ; "run_test_suite"
0031    UCLO     0 => 0032
0032 => RET1     0   2

