
main <./fs/win32/tools.lua:0,0> (80 instructions, 320 bytes at 0x7f802dc068a0)
0+ params, 8 slots, 0 upvalues, 7 locals, 21 constants, 18 functions
	1	[5]	NEWTABLE 	0 0 0
	2	[7]	GETGLOBAL	1 -1	; require
	3	[7]	LOADK    	2 -2	; "luarocks.fs"
	4	[7]	CALL     	1 2 2
	5	[8]	GETGLOBAL	2 -1	; require
	6	[8]	LOADK    	3 -3	; "luarocks.dir"
	7	[8]	CALL     	2 2 2
	8	[9]	GETGLOBAL	3 -1	; require
	9	[9]	LOADK    	4 -4	; "luarocks.core.cfg"
	10	[9]	CALL     	3 2 2
	11	[11]	GETGLOBAL	4 -5	; setmetatable
	12	[11]	NEWTABLE 	5 0 0
	13	[11]	NEWTABLE 	6 0 1
	14	[11]	CLOSURE  	7 0	; 0x7f802dc06fd0
	15	[11]	MOVE     	0 3
	16	[11]	SETTABLE 	6 -6 7	; "__index" -
	17	[11]	CALL     	4 3 2
	18	[29]	CLOSURE  	5 1	; 0x7f802dc07360
	19	[29]	MOVE     	0 1
	20	[18]	SETTABLE 	0 -7 5	; "command_at" -
	21	[44]	CLOSURE  	5 2	; 0x7f802dc06640
	22	[44]	MOVE     	0 2
	23	[44]	MOVE     	0 1
	24	[44]	MOVE     	0 4
	25	[36]	SETTABLE 	0 -8 5	; "make_dir" -
	26	[53]	CLOSURE  	5 3	; 0x7f802dc06f50
	27	[53]	MOVE     	0 1
	28	[53]	MOVE     	0 4
	29	[50]	SETTABLE 	0 -9 5	; "remove_dir_if_empty" -
	30	[62]	CLOSURE  	5 4	; 0x7f802dc07bc0
	31	[62]	MOVE     	0 1
	32	[62]	MOVE     	0 4
	33	[59]	SETTABLE 	0 -10 5	; "remove_dir_tree_if_empty" -
	34	[78]	CLOSURE  	5 5	; 0x7f802dc072e0
	35	[78]	MOVE     	0 1
	36	[78]	MOVE     	0 4
	37	[69]	SETTABLE 	0 -11 5	; "copy" -
	38	[95]	CLOSURE  	5 6	; 0x7f802dc08560
	39	[95]	MOVE     	0 1
	40	[95]	MOVE     	0 4
	41	[85]	SETTABLE 	0 -12 5	; "copy_contents" -
	42	[105]	CLOSURE  	5 7	; 0x7f802dc08480
	43	[105]	MOVE     	0 1
	44	[101]	SETTABLE 	0 -13 5	; "delete" -
	45	[132]	CLOSURE  	5 8	; 0x7f802dc08320
	46	[132]	MOVE     	0 1
	47	[132]	MOVE     	0 4
	48	[112]	SETTABLE 	0 -14 5	; "find" -
	49	[145]	CLOSURE  	5 9	; 0x7f802dc08e60
	50	[145]	MOVE     	0 1
	51	[145]	MOVE     	0 4
	52	[139]	SETTABLE 	0 -15 5	; "zip" -
	53	[157]	CLOSURE  	5 10	; 0x7f802dc09bf0
	54	[157]	MOVE     	0 1
	55	[157]	MOVE     	0 4
	56	[150]	SETTABLE 	0 -16 5	; "unzip" -
	57	[184]	CLOSURE  	5 11	; 0x7f802dc0a160
	58	[184]	MOVE     	0 2
	59	[184]	MOVE     	0 1
	60	[184]	MOVE     	0 4
	61	[193]	CLOSURE  	6 12	; 0x7f802dc0a270
	62	[193]	MOVE     	0 5
	63	[191]	SETTABLE 	0 -17 6	; "gunzip" -
	64	[202]	CLOSURE  	6 13	; 0x7f802dc0a490
	65	[202]	MOVE     	0 5
	66	[200]	SETTABLE 	0 -18 6	; "bunzip2" -
	67	[216]	CLOSURE  	6 14	; 0x7f802dc0b0d0
	68	[277]	CLOSURE  	7 15	; 0x7f802dc08020
	69	[277]	MOVE     	0 1
	70	[277]	MOVE     	0 4
	71	[277]	MOVE     	0 6
	72	[224]	SETTABLE 	0 -19 7	; "set_permissions" -
	73	[281]	CLOSURE  	7 16	; 0x7f802dc0b920
	74	[281]	MOVE     	0 1
	75	[281]	MOVE     	0 3
	76	[279]	SETTABLE 	0 -20 7	; "browser" -
	77	[290]	CLOSURE  	7 17	; 0x7f802dc09150
	78	[288]	SETTABLE 	0 -21 7	; "set_time" -
	79	[292]	RETURN   	0 2
	80	[292]	RETURN   	0 1

function <./fs/win32/tools.lua:11,11> (5 instructions, 20 bytes at 0x7f802dc06fd0)
2 params, 3 slots, 1 upvalue, 2 locals, 1 constant, 0 functions
	1	[11]	GETUPVAL 	2 0	; cfg
	2	[11]	GETTABLE 	2 2 -1	; "variables"
	3	[11]	GETTABLE 	2 2 1
	4	[11]	RETURN   	2 2
	5	[11]	RETURN   	0 1

function <./fs/win32/tools.lua:18,29> (23 instructions, 92 bytes at 0x7f802dc07360)
3 params, 9 slots, 1 upvalue, 6 locals, 6 constants, 0 functions
	1	[19]	SELF     	3 0 -1	; "match"
	2	[19]	LOADK    	5 -2	; "^([A-Za-z]:)"
	3	[19]	CALL     	3 3 2
	4	[20]	LOADK    	4 -3	; " & "
	5	[21]	TEST     	2 0 0
	6	[21]	JMP      	1	; to 8
	7	[22]	LOADK    	4 -4	; " && "
	8	[24]	LOADK    	5 -5	; "cd "
	9	[24]	GETUPVAL 	6 0	; fs
	10	[24]	GETTABLE 	6 6 -6	; "Q"
	11	[24]	MOVE     	7 0
	12	[24]	CALL     	6 2 2
	13	[24]	MOVE     	7 4
	14	[24]	MOVE     	8 1
	15	[24]	CONCAT   	5 5 8
	16	[25]	TEST     	3 0 0
	17	[25]	JMP      	4	; to 22
	18	[26]	MOVE     	6 3
	19	[26]	LOADK    	7 -3	; " & "
	20	[26]	MOVE     	8 5
	21	[26]	CONCAT   	5 6 8
	22	[28]	RETURN   	5 2
	23	[29]	RETURN   	0 1

function <./fs/win32/tools.lua:36,44> (30 instructions, 120 bytes at 0x7f802dc06640)
1 param, 4 slots, 3 upvalues, 1 local, 7 constants, 0 functions
	1	[37]	GETGLOBAL	1 -1	; assert
	2	[37]	MOVE     	2 0
	3	[37]	CALL     	1 2 1
	4	[38]	GETUPVAL 	1 0	; dir
	5	[38]	GETTABLE 	1 1 -2	; "normalize"
	6	[38]	MOVE     	2 0
	7	[38]	CALL     	1 2 2
	8	[38]	MOVE     	0 1
	9	[39]	GETUPVAL 	1 1	; fs
	10	[39]	GETTABLE 	1 1 -3	; "execute_quiet"
	11	[39]	GETUPVAL 	2 2	; vars
	12	[39]	GETTABLE 	2 2 -4	; "MKDIR"
	13	[39]	LOADK    	3 -5	; " -p "
	14	[39]	CONCAT   	2 2 3
	15	[39]	MOVE     	3 0
	16	[39]	CALL     	1 3 1
	17	[40]	GETUPVAL 	1 1	; fs
	18	[40]	GETTABLE 	1 1 -6	; "is_dir"
	19	[40]	MOVE     	2 0
	20	[40]	CALL     	1 2 2
	21	[40]	TEST     	1 0 1
	22	[40]	JMP      	5	; to 28
	23	[41]	LOADBOOL 	1 0 0
	24	[41]	LOADK    	2 -7	; "failed making directory "
	25	[41]	MOVE     	3 0
	26	[41]	CONCAT   	2 2 3
	27	[41]	RETURN   	1 3
	28	[43]	LOADBOOL 	1 1 0
	29	[43]	RETURN   	1 2
	30	[44]	RETURN   	0 1

function <./fs/win32/tools.lua:50,53> (10 instructions, 40 bytes at 0x7f802dc06f50)
1 param, 4 slots, 2 upvalues, 1 local, 3 constants, 0 functions
	1	[51]	GETGLOBAL	1 -1	; assert
	2	[51]	MOVE     	2 0
	3	[51]	CALL     	1 2 1
	4	[52]	GETUPVAL 	1 0	; fs
	5	[52]	GETTABLE 	1 1 -2	; "execute_quiet"
	6	[52]	GETUPVAL 	2 1	; vars
	7	[52]	GETTABLE 	2 2 -3	; "RMDIR"
	8	[52]	MOVE     	3 0
	9	[52]	CALL     	1 3 1
	10	[53]	RETURN   	0 1

function <./fs/win32/tools.lua:59,62> (10 instructions, 40 bytes at 0x7f802dc07bc0)
1 param, 4 slots, 2 upvalues, 1 local, 3 constants, 0 functions
	1	[60]	GETGLOBAL	1 -1	; assert
	2	[60]	MOVE     	2 0
	3	[60]	CALL     	1 2 1
	4	[61]	GETUPVAL 	1 0	; fs
	5	[61]	GETTABLE 	1 1 -2	; "execute_quiet"
	6	[61]	GETUPVAL 	2 1	; vars
	7	[61]	GETTABLE 	2 2 -3	; "RMDIR"
	8	[61]	MOVE     	3 0
	9	[61]	CALL     	1 3 1
	10	[62]	RETURN   	0 1

function <./fs/win32/tools.lua:69,78> (35 instructions, 140 bytes at 0x7f802dc072e0)
2 params, 8 slots, 2 upvalues, 3 locals, 10 constants, 0 functions
	1	[70]	GETGLOBAL	2 -1	; assert
	2	[70]	TESTSET  	3 0 0
	3	[70]	JMP      	1	; to 5
	4	[70]	MOVE     	3 1
	5	[70]	CALL     	2 2 1
	6	[71]	SELF     	2 1 -2	; "match"
	7	[71]	LOADK    	4 -3	; "[/\\]$"
	8	[71]	CALL     	2 3 2
	9	[71]	TEST     	2 0 0
	10	[71]	JMP      	5	; to 16
	11	[71]	SELF     	2 1 -4	; "sub"
	12	[71]	LOADK    	4 -5	; 1
	13	[71]	LOADK    	5 -6	; -2
	14	[71]	CALL     	2 4 2
	15	[71]	MOVE     	1 2
	16	[72]	GETUPVAL 	2 0	; fs
	17	[72]	GETTABLE 	2 2 -7	; "execute"
	18	[72]	GETUPVAL 	3 1	; vars
	19	[72]	GETTABLE 	3 3 -8	; "CP"
	20	[72]	MOVE     	4 0
	21	[72]	MOVE     	5 1
	22	[72]	CALL     	2 4 2
	23	[73]	TEST     	2 0 0
	24	[73]	JMP      	3	; to 28
	25	[74]	LOADBOOL 	3 1 0
	26	[74]	RETURN   	3 2
	27	[74]	JMP      	7	; to 35
	28	[76]	LOADBOOL 	3 0 0
	29	[76]	LOADK    	4 -9	; "Failed copying "
	30	[76]	MOVE     	5 0
	31	[76]	LOADK    	6 -10	; " to "
	32	[76]	MOVE     	7 1
	33	[76]	CONCAT   	4 4 7
	34	[76]	RETURN   	3 3
	35	[78]	RETURN   	0 1

function <./fs/win32/tools.lua:85,95> (45 instructions, 180 bytes at 0x7f802dc08560)
2 params, 7 slots, 2 upvalues, 2 locals, 10 constants, 0 functions
	1	[86]	GETGLOBAL	2 -1	; assert
	2	[86]	TESTSET  	3 0 0
	3	[86]	JMP      	1	; to 5
	4	[86]	MOVE     	3 1
	5	[86]	CALL     	2 2 1
	6	[87]	GETUPVAL 	2 0	; fs
	7	[87]	GETTABLE 	2 2 -2	; "is_dir"
	8	[87]	MOVE     	3 0
	9	[87]	CALL     	2 2 2
	10	[87]	TEST     	2 0 1
	11	[87]	JMP      	5	; to 17
	12	[88]	LOADBOOL 	2 0 0
	13	[88]	MOVE     	3 0
	14	[88]	LOADK    	4 -3	; " is not a directory"
	15	[88]	CONCAT   	3 3 4
	16	[88]	RETURN   	2 3
	17	[90]	GETUPVAL 	2 0	; fs
	18	[90]	GETTABLE 	2 2 -4	; "make_dir"
	19	[90]	MOVE     	3 1
	20	[90]	CALL     	2 2 2
	21	[90]	TEST     	2 0 0
	22	[90]	JMP      	15	; to 38
	23	[90]	GETUPVAL 	2 0	; fs
	24	[90]	GETTABLE 	2 2 -5	; "execute_quiet"
	25	[90]	GETUPVAL 	3 1	; vars
	26	[90]	GETTABLE 	3 3 -6	; "CP"
	27	[90]	LOADK    	4 -7	; "-dR"
	28	[90]	MOVE     	5 0
	29	[90]	LOADK    	6 -8	; "\\*.*"
	30	[90]	CONCAT   	5 5 6
	31	[90]	MOVE     	6 1
	32	[90]	CALL     	2 5 2
	33	[90]	TEST     	2 0 0
	34	[90]	JMP      	3	; to 38
	35	[91]	LOADBOOL 	2 1 0
	36	[91]	RETURN   	2 2
	37	[91]	JMP      	7	; to 45
	38	[93]	LOADBOOL 	2 0 0
	39	[93]	LOADK    	3 -9	; "Failed copying "
	40	[93]	MOVE     	4 0
	41	[93]	LOADK    	5 -10	; " to "
	42	[93]	MOVE     	6 1
	43	[93]	CONCAT   	3 3 6
	44	[93]	RETURN   	2 3
	45	[95]	RETURN   	0 1

function <./fs/win32/tools.lua:101,105> (31 instructions, 124 bytes at 0x7f802dc08480)
1 param, 9 slots, 1 upvalue, 1 local, 10 constants, 0 functions
	1	[102]	GETGLOBAL	1 -1	; assert
	2	[102]	MOVE     	2 0
	3	[102]	CALL     	1 2 1
	4	[103]	GETGLOBAL	1 -1	; assert
	5	[103]	SELF     	2 0 -2	; "match"
	6	[103]	LOADK    	4 -3	; "^[a-zA-Z]?:?[\\/]"
	7	[103]	CALL     	2 3 0
	8	[103]	CALL     	1 0 1
	9	[104]	GETUPVAL 	1 0	; fs
	10	[104]	GETTABLE 	1 1 -4	; "execute_quiet"
	11	[104]	LOADK    	2 -5	; "if exist "
	12	[104]	GETUPVAL 	3 0	; fs
	13	[104]	GETTABLE 	3 3 -6	; "Q"
	14	[104]	MOVE     	4 0
	15	[104]	LOADK    	5 -7	; "\\*"
	16	[104]	CONCAT   	4 4 5
	17	[104]	CALL     	3 2 2
	18	[104]	LOADK    	4 -8	; " ( RMDIR /S /Q "
	19	[104]	GETUPVAL 	5 0	; fs
	20	[104]	GETTABLE 	5 5 -6	; "Q"
	21	[104]	MOVE     	6 0
	22	[104]	CALL     	5 2 2
	23	[104]	LOADK    	6 -9	; " ) else ( DEL /Q /F "
	24	[104]	GETUPVAL 	7 0	; fs
	25	[104]	GETTABLE 	7 7 -6	; "Q"
	26	[104]	MOVE     	8 0
	27	[104]	CALL     	7 2 2
	28	[104]	LOADK    	8 -10	; " )"
	29	[104]	CONCAT   	2 2 8
	30	[104]	CALL     	1 2 1
	31	[105]	RETURN   	0 1

function <./fs/win32/tools.lua:112,132> (70 instructions, 280 bytes at 0x7f802dc08320)
1 param, 14 slots, 2 upvalues, 8 locals, 24 constants, 0 functions
	1	[113]	GETGLOBAL	1 -1	; assert
	2	[113]	GETGLOBAL	2 -2	; type
	3	[113]	MOVE     	3 0
	4	[113]	CALL     	2 2 2
	5	[113]	EQ       	1 2 -3	; - "string"
	6	[113]	JMP      	3	; to 10
	7	[113]	NOT      	2 0
	8	[113]	JMP      	2	; to 11
	9	[113]	LOADBOOL 	2 0 1
	10	[113]	LOADBOOL 	2 1 0
	11	[113]	CALL     	1 2 1
	12	[114]	TEST     	0 0 1
	13	[114]	JMP      	4	; to 18
	14	[115]	GETUPVAL 	1 0	; fs
	15	[115]	GETTABLE 	1 1 -4	; "current_dir"
	16	[115]	CALL     	1 1 2
	17	[115]	MOVE     	0 1
	18	[117]	GETUPVAL 	1 0	; fs
	19	[117]	GETTABLE 	1 1 -5	; "is_dir"
	20	[117]	MOVE     	2 0
	21	[117]	CALL     	1 2 2
	22	[117]	TEST     	1 0 1
	23	[117]	JMP      	2	; to 26
	24	[118]	NEWTABLE 	1 0 0
	25	[118]	RETURN   	1 2
	26	[120]	NEWTABLE 	1 0 0
	27	[121]	GETGLOBAL	2 -6	; io
	28	[121]	GETTABLE 	2 2 -7	; "popen"
	29	[121]	GETUPVAL 	3 0	; fs
	30	[121]	GETTABLE 	3 3 -8	; "command_at"
	31	[121]	MOVE     	4 0
	32	[121]	GETUPVAL 	5 0	; fs
	33	[121]	GETTABLE 	5 5 -9	; "quiet_stderr"
	34	[121]	GETUPVAL 	6 1	; vars
	35	[121]	GETTABLE 	6 6 -10	; "FIND"
	36	[121]	CALL     	5 2 2
	37	[121]	LOADBOOL 	6 1 0
	38	[121]	CALL     	3 4 0
	39	[121]	CALL     	2 0 2
	40	[122]	SELF     	3 2 -11	; "lines"
	41	[122]	CALL     	3 2 4
	42	[122]	JMP      	22	; to 65
	43	[124]	SELF     	7 6 -12	; "sub"
	44	[124]	LOADK    	9 -13	; 1
	45	[124]	LOADK    	10 -14	; 2
	46	[124]	CALL     	7 4 2
	47	[125]	EQ       	1 7 -15	; - ".\\"
	48	[125]	JMP      	2	; to 51
	49	[125]	EQ       	0 7 -16	; - "./"
	50	[125]	JMP      	4	; to 55
	51	[125]	SELF     	8 6 -12	; "sub"
	52	[125]	LOADK    	10 -17	; 3
	53	[125]	CALL     	8 3 2
	54	[125]	MOVE     	6 8
	55	[126]	EQ       	1 6 -18	; - "."
	56	[126]	JMP      	8	; to 65
	57	[127]	GETGLOBAL	8 -19	; table
	58	[127]	GETTABLE 	8 8 -20	; "insert"
	59	[127]	MOVE     	9 1
	60	[127]	SELF     	10 6 -21	; "gsub"
	61	[127]	LOADK    	12 -22	; "\\"
	62	[127]	LOADK    	13 -23	; "/"
	63	[127]	CALL     	10 4 2
	64	[127]	CALL     	8 3 1
	65	[122]	TFORLOOP 	3 1
	66	[128]	JMP      	-24	; to 43
	67	[130]	SELF     	3 2 -24	; "close"
	68	[130]	CALL     	3 2 1
	69	[131]	RETURN   	1 2
	70	[132]	RETURN   	0 1

function <./fs/win32/tools.lua:139,145> (20 instructions, 80 bytes at 0x7f802dc08e60)
1+ param, 6 slots, 2 upvalues, 2 locals, 4 constants, 0 functions
	1	[140]	GETUPVAL 	2 0	; fs
	2	[140]	GETTABLE 	2 2 -1	; "execute_quiet"
	3	[140]	GETUPVAL 	3 1	; vars
	4	[140]	GETTABLE 	3 3 -2	; "SEVENZ"
	5	[140]	LOADK    	4 -3	; " -aoa a -tzip"
	6	[140]	CONCAT   	3 3 4
	7	[140]	MOVE     	4 0
	8	[140]	VARARG   	5 0
	9	[140]	CALL     	2 0 2
	10	[140]	TEST     	2 0 0
	11	[140]	JMP      	3	; to 15
	12	[141]	LOADBOOL 	2 1 0
	13	[141]	RETURN   	2 2
	14	[141]	JMP      	5	; to 20
	15	[143]	LOADNIL  	2 2
	16	[143]	LOADK    	3 -4	; "failed compressing "
	17	[143]	MOVE     	4 0
	18	[143]	CONCAT   	3 3 4
	19	[143]	RETURN   	2 3
	20	[145]	RETURN   	0 1

function <./fs/win32/tools.lua:150,157> (22 instructions, 88 bytes at 0x7f802dc09bf0)
1 param, 4 slots, 2 upvalues, 1 local, 5 constants, 0 functions
	1	[151]	GETGLOBAL	1 -1	; assert
	2	[151]	MOVE     	2 0
	3	[151]	CALL     	1 2 1
	4	[152]	GETUPVAL 	1 0	; fs
	5	[152]	GETTABLE 	1 1 -2	; "execute_quiet"
	6	[152]	GETUPVAL 	2 1	; vars
	7	[152]	GETTABLE 	2 2 -3	; "SEVENZ"
	8	[152]	LOADK    	3 -4	; " -aoa x"
	9	[152]	CONCAT   	2 2 3
	10	[152]	MOVE     	3 0
	11	[152]	CALL     	1 3 2
	12	[152]	TEST     	1 0 0
	13	[152]	JMP      	3	; to 17
	14	[153]	LOADBOOL 	1 1 0
	15	[153]	RETURN   	1 2
	16	[153]	JMP      	5	; to 22
	17	[155]	LOADNIL  	1 1
	18	[155]	LOADK    	2 -5	; "failed extracting "
	19	[155]	MOVE     	3 0
	20	[155]	CONCAT   	2 2 3
	21	[155]	RETURN   	1 3
	22	[157]	RETURN   	0 1

function <./fs/win32/tools.lua:159,184> (89 instructions, 356 bytes at 0x7f802dc0a160)
3 params, 11 slots, 3 upvalues, 8 locals, 19 constants, 0 functions
	1	[160]	GETGLOBAL	3 -1	; assert
	2	[160]	GETGLOBAL	4 -2	; type
	3	[160]	MOVE     	5 1
	4	[160]	CALL     	4 2 2
	5	[160]	EQ       	1 4 -3	; - "string"
	6	[160]	JMP      	1	; to 8
	7	[160]	LOADBOOL 	4 0 1
	8	[160]	LOADBOOL 	4 1 0
	9	[160]	CALL     	3 2 1
	10	[161]	GETGLOBAL	3 -1	; assert
	11	[161]	EQ       	1 2 -4	; - nil
	12	[161]	JMP      	6	; to 19
	13	[161]	GETGLOBAL	4 -2	; type
	14	[161]	MOVE     	5 2
	15	[161]	CALL     	4 2 2
	16	[161]	EQ       	1 4 -3	; - "string"
	17	[161]	JMP      	1	; to 19
	18	[161]	LOADBOOL 	4 0 1
	19	[161]	LOADBOOL 	4 1 0
	20	[161]	CALL     	3 2 1
	21	[163]	SELF     	3 1 -5	; "gsub"
	22	[163]	LOADK    	5 -6	; "%."
	23	[163]	MOVE     	6 0
	24	[163]	LOADK    	7 -7	; "$"
	25	[163]	CONCAT   	5 5 7
	26	[163]	LOADK    	6 -8	; ""
	27	[163]	CALL     	3 4 2
	28	[164]	GETUPVAL 	4 0	; dir
	29	[164]	GETTABLE 	4 4 -9	; "dir_name"
	30	[164]	MOVE     	5 3
	31	[164]	CALL     	4 2 2
	32	[166]	GETUPVAL 	5 1	; fs
	33	[166]	GETTABLE 	5 5 -10	; "absolute_name"
	34	[166]	MOVE     	6 1
	35	[166]	CALL     	5 2 2
	36	[166]	MOVE     	1 5
	37	[168]	GETUPVAL 	5 2	; vars
	38	[168]	GETTABLE 	5 5 -11	; "SEVENZ"
	39	[168]	LOADK    	6 -12	; " -aoa -t* -o"
	40	[168]	GETUPVAL 	7 1	; fs
	41	[168]	GETTABLE 	7 7 -13	; "Q"
	42	[168]	MOVE     	8 4
	43	[168]	CALL     	7 2 2
	44	[168]	LOADK    	8 -14	; " x "
	45	[168]	GETUPVAL 	9 1	; fs
	46	[168]	GETTABLE 	9 9 -13	; "Q"
	47	[168]	MOVE     	10 1
	48	[168]	CALL     	9 2 2
	49	[168]	CONCAT   	5 5 9
	50	[169]	GETUPVAL 	6 1	; fs
	51	[169]	GETTABLE 	6 6 -15	; "execute_quiet"
	52	[169]	MOVE     	7 5
	53	[169]	CALL     	6 2 3
	54	[170]	TEST     	6 0 1
	55	[170]	JMP      	5	; to 61
	56	[171]	LOADNIL  	8 8
	57	[171]	LOADK    	9 -16	; "failed extracting "
	58	[171]	MOVE     	10 1
	59	[171]	CONCAT   	9 9 10
	60	[171]	RETURN   	8 3
	61	[174]	TEST     	2 0 0
	62	[174]	JMP      	24	; to 87
	63	[175]	GETUPVAL 	8 1	; fs
	64	[175]	GETTABLE 	8 8 -10	; "absolute_name"
	65	[175]	MOVE     	9 2
	66	[175]	CALL     	8 2 2
	67	[175]	MOVE     	2 8
	68	[176]	GETUPVAL 	8 1	; fs
	69	[176]	GETTABLE 	8 8 -10	; "absolute_name"
	70	[176]	MOVE     	9 3
	71	[176]	CALL     	8 2 2
	72	[176]	MOVE     	3 8
	73	[177]	GETGLOBAL	8 -17	; os
	74	[177]	GETTABLE 	8 8 -18	; "rename"
	75	[177]	MOVE     	9 3
	76	[177]	MOVE     	10 2
	77	[177]	CALL     	8 3 3
	78	[177]	MOVE     	7 9
	79	[177]	MOVE     	6 8
	80	[178]	TEST     	6 0 1
	81	[178]	JMP      	5	; to 87
	82	[179]	LOADNIL  	8 8
	83	[179]	LOADK    	9 -19	; "failed creating new file "
	84	[179]	MOVE     	10 2
	85	[179]	CONCAT   	9 9 10
	86	[179]	RETURN   	8 3
	87	[183]	LOADBOOL 	8 1 0
	88	[183]	RETURN   	8 2
	89	[184]	RETURN   	0 1

function <./fs/win32/tools.lua:191,193> (7 instructions, 28 bytes at 0x7f802dc0a270)
2 params, 6 slots, 1 upvalue, 2 locals, 1 constant, 0 functions
	1	[192]	GETUPVAL 	2 0	; sevenz
	2	[192]	LOADK    	3 -1	; "gz"
	3	[192]	MOVE     	4 0
	4	[192]	MOVE     	5 1
	5	[192]	TAILCALL 	2 4 0
	6	[192]	RETURN   	2 0
	7	[193]	RETURN   	0 1

function <./fs/win32/tools.lua:200,202> (7 instructions, 28 bytes at 0x7f802dc0a490)
2 params, 6 slots, 1 upvalue, 2 locals, 1 constant, 0 functions
	1	[201]	GETUPVAL 	2 0	; sevenz
	2	[201]	LOADK    	3 -1	; "bz2"
	3	[201]	MOVE     	4 0
	4	[201]	MOVE     	5 1
	5	[201]	TAILCALL 	2 4 0
	6	[201]	RETURN   	2 0
	7	[202]	RETURN   	0 1

function <./fs/win32/tools.lua:206,216> (30 instructions, 120 bytes at 0x7f802dc0b0d0)
0 params, 10 slots, 0 upvalues, 6 locals, 12 constants, 0 functions
	1	[207]	NEWTABLE 	0 0 0
	2	[208]	GETGLOBAL	1 -1	; assert
	3	[208]	GETGLOBAL	2 -2	; io
	4	[208]	GETTABLE 	2 2 -3	; "popen"
	5	[208]	LOADK    	3 -4	; "wmic UserAccount get name"
	6	[208]	CALL     	2 2 0
	7	[208]	CALL     	1 0 2
	8	[209]	SELF     	2 1 -5	; "lines"
	9	[209]	CALL     	2 2 4
	10	[209]	JMP      	16	; to 27
	11	[210]	SELF     	6 5 -6	; "gsub"
	12	[210]	LOADK    	8 -7	; "%s+$"
	13	[210]	LOADK    	9 -8	; ""
	14	[210]	CALL     	6 4 2
	15	[210]	MOVE     	5 6
	16	[211]	EQ       	1 5 -8	; - ""
	17	[211]	JMP      	9	; to 27
	18	[211]	EQ       	1 5 -9	; - "Name"
	19	[211]	JMP      	7	; to 27
	20	[211]	EQ       	1 5 -10	; - "Administrator"
	21	[211]	JMP      	5	; to 27
	22	[212]	GETGLOBAL	6 -11	; table
	23	[212]	GETTABLE 	6 6 -12	; "insert"
	24	[212]	MOVE     	7 0
	25	[212]	MOVE     	8 5
	26	[212]	CALL     	6 3 1
	27	[209]	TFORLOOP 	2 1
	28	[213]	JMP      	-18	; to 11
	29	[215]	RETURN   	0 2
	30	[216]	RETURN   	0 1

function <./fs/win32/tools.lua:224,277> (151 instructions, 604 bytes at 0x7f802dc08020)
3 params, 17 slots, 3 upvalues, 14 locals, 22 constants, 0 functions
	1	[225]	GETGLOBAL	3 -1	; assert
	2	[225]	TESTSET  	4 0 0
	3	[225]	JMP      	3	; to 7
	4	[225]	TESTSET  	4 1 0
	5	[225]	JMP      	1	; to 7
	6	[225]	MOVE     	4 2
	7	[225]	CALL     	3 2 1
	8	[227]	EQ       	0 2 -2	; - "user"
	9	[227]	JMP      	80	; to 90
	10	[228]	LOADNIL  	3 3
	11	[229]	EQ       	0 1 -3	; - "read"
	12	[229]	JMP      	2	; to 15
	13	[230]	LOADK    	3 -4	; "(R,W,M)"
	14	[230]	JMP      	3	; to 18
	15	[231]	EQ       	0 1 -5	; - "exec"
	16	[231]	JMP      	1	; to 18
	17	[232]	LOADK    	3 -6	; "(F)"
	18	[235]	LOADNIL  	4 4
	19	[237]	GETUPVAL 	5 0	; fs
	20	[237]	GETTABLE 	5 5 -7	; "execute_quiet"
	21	[237]	LOADK    	6 -8	; "takeown /f "
	22	[237]	GETUPVAL 	7 0	; fs
	23	[237]	GETTABLE 	7 7 -9	; "Q"
	24	[237]	MOVE     	8 0
	25	[237]	CALL     	7 2 2
	26	[237]	CONCAT   	6 6 7
	27	[237]	CALL     	5 2 2
	28	[237]	MOVE     	4 5
	29	[238]	TEST     	4 0 1
	30	[238]	JMP      	3	; to 34
	31	[239]	LOADBOOL 	5 0 0
	32	[239]	LOADK    	6 -10	; "Could not take ownership of the given file"
	33	[239]	RETURN   	5 3
	34	[242]	GETUPVAL 	5 0	; fs
	35	[242]	GETTABLE 	5 5 -7	; "execute_quiet"
	36	[242]	GETUPVAL 	6 1	; vars
	37	[242]	GETTABLE 	6 6 -11	; "ICACLS"
	38	[242]	LOADK    	7 -12	; " "
	39	[242]	GETUPVAL 	8 0	; fs
	40	[242]	GETTABLE 	8 8 -9	; "Q"
	41	[242]	MOVE     	9 0
	42	[242]	CALL     	8 2 2
	43	[242]	LOADK    	9 -13	; " /inheritance:d /grant:r \"%USERNAME%\":"
	44	[242]	MOVE     	10 3
	45	[242]	CONCAT   	6 6 10
	46	[242]	CALL     	5 2 2
	47	[242]	MOVE     	4 5
	48	[243]	TEST     	4 0 1
	49	[243]	JMP      	7	; to 57
	50	[244]	LOADBOOL 	5 0 0
	51	[244]	LOADK    	6 -14	; "Failed setting permission "
	52	[244]	MOVE     	7 1
	53	[244]	LOADK    	8 -15	; " for "
	54	[244]	MOVE     	9 2
	55	[244]	CONCAT   	6 6 9
	56	[244]	RETURN   	5 3
	57	[247]	GETGLOBAL	5 -16	; pairs
	58	[247]	GETUPVAL 	6 2	; get_system_users
	59	[247]	CALL     	6 1 0
	60	[247]	CALL     	5 0 4
	61	[247]	JMP      	25	; to 87
	62	[248]	GETUPVAL 	10 0	; fs
	63	[248]	GETTABLE 	10 10 -7	; "execute_quiet"
	64	[248]	GETUPVAL 	11 1	; vars
	65	[248]	GETTABLE 	11 11 -11	; "ICACLS"
	66	[248]	LOADK    	12 -12	; " "
	67	[248]	GETUPVAL 	13 0	; fs
	68	[248]	GETTABLE 	13 13 -9	; "Q"
	69	[248]	MOVE     	14 0
	70	[248]	CALL     	13 2 2
	71	[248]	LOADK    	14 -17	; " /remove "
	72	[248]	GETUPVAL 	15 0	; fs
	73	[248]	GETTABLE 	15 15 -9	; "Q"
	74	[248]	MOVE     	16 9
	75	[248]	CALL     	15 2 2
	76	[248]	CONCAT   	11 11 15
	77	[248]	CALL     	10 2 2
	78	[249]	TEST     	10 0 1
	79	[249]	JMP      	7	; to 87
	80	[250]	LOADBOOL 	11 0 0
	81	[250]	LOADK    	12 -14	; "Failed setting permission "
	82	[250]	MOVE     	13 1
	83	[250]	LOADK    	14 -15	; " for "
	84	[250]	MOVE     	15 2
	85	[250]	CONCAT   	12 12 15
	86	[250]	RETURN   	11 3
	87	[247]	TFORLOOP 	5 2
	88	[251]	JMP      	-27	; to 62
	89	[252]	JMP      	59	; to 149
	90	[253]	EQ       	0 2 -18	; - "all"
	91	[253]	JMP      	57	; to 149
	92	[254]	LOADNIL  	3 4
	93	[255]	EQ       	0 1 -3	; - "read"
	94	[255]	JMP      	3	; to 98
	95	[256]	LOADK    	3 -4	; "(R,W,M)"
	96	[257]	LOADK    	4 -19	; "(R)"
	97	[257]	JMP      	4	; to 102
	98	[258]	EQ       	0 1 -5	; - "exec"
	99	[258]	JMP      	2	; to 102
	100	[259]	LOADK    	3 -6	; "(F)"
	101	[260]	LOADK    	4 -20	; "(RX)"
	102	[263]	LOADNIL  	5 5
	103	[265]	GETUPVAL 	6 0	; fs
	104	[265]	GETTABLE 	6 6 -7	; "execute_quiet"
	105	[265]	GETUPVAL 	7 1	; vars
	106	[265]	GETTABLE 	7 7 -11	; "ICACLS"
	107	[265]	LOADK    	8 -12	; " "
	108	[265]	GETUPVAL 	9 0	; fs
	109	[265]	GETTABLE 	9 9 -9	; "Q"
	110	[265]	MOVE     	10 0
	111	[265]	CALL     	9 2 2
	112	[265]	LOADK    	10 -21	; " /inheritance:d /grant:r *S-1-1-0:"
	113	[265]	MOVE     	11 4
	114	[265]	CONCAT   	7 7 11
	115	[265]	CALL     	6 2 2
	116	[265]	MOVE     	5 6
	117	[266]	TEST     	5 0 1
	118	[266]	JMP      	7	; to 126
	119	[267]	LOADBOOL 	6 0 0
	120	[267]	LOADK    	7 -14	; "Failed setting permission "
	121	[267]	MOVE     	8 1
	122	[267]	LOADK    	9 -15	; " for "
	123	[267]	MOVE     	10 2
	124	[267]	CONCAT   	7 7 10
	125	[267]	RETURN   	6 3
	126	[270]	GETUPVAL 	6 0	; fs
	127	[270]	GETTABLE 	6 6 -7	; "execute_quiet"
	128	[270]	GETUPVAL 	7 1	; vars
	129	[270]	GETTABLE 	7 7 -11	; "ICACLS"
	130	[270]	LOADK    	8 -12	; " "
	131	[270]	GETUPVAL 	9 0	; fs
	132	[270]	GETTABLE 	9 9 -9	; "Q"
	133	[270]	MOVE     	10 0
	134	[270]	CALL     	9 2 2
	135	[270]	LOADK    	10 -22	; " /inheritance:d /grant \"%USERNAME%\":"
	136	[270]	MOVE     	11 3
	137	[270]	CONCAT   	7 7 11
	138	[270]	CALL     	6 2 2
	139	[270]	MOVE     	5 6
	140	[271]	TEST     	5 0 1
	141	[271]	JMP      	7	; to 149
	142	[272]	LOADBOOL 	6 0 0
	143	[272]	LOADK    	7 -14	; "Failed setting permission "
	144	[272]	MOVE     	8 1
	145	[272]	LOADK    	9 -15	; " for "
	146	[272]	MOVE     	10 2
	147	[272]	CONCAT   	7 7 10
	148	[272]	RETURN   	6 3
	149	[276]	LOADBOOL 	3 1 0
	150	[276]	RETURN   	3 2
	151	[277]	RETURN   	0 1

function <./fs/win32/tools.lua:279,281> (13 instructions, 52 bytes at 0x7f802dc0b920)
1 param, 6 slots, 2 upvalues, 1 local, 4 constants, 0 functions
	1	[280]	GETUPVAL 	1 0	; fs
	2	[280]	GETTABLE 	1 1 -1	; "execute"
	3	[280]	GETUPVAL 	2 1	; cfg
	4	[280]	GETTABLE 	2 2 -2	; "web_browser"
	5	[280]	LOADK    	3 -3	; " \"Starting docs...\" "
	6	[280]	GETUPVAL 	4 0	; fs
	7	[280]	GETTABLE 	4 4 -4	; "Q"
	8	[280]	MOVE     	5 0
	9	[280]	CALL     	4 2 2
	10	[280]	CONCAT   	2 2 4
	11	[280]	TAILCALL 	1 2 0
	12	[280]	RETURN   	1 0
	13	[281]	RETURN   	0 1

function <./fs/win32/tools.lua:288,290> (3 instructions, 12 bytes at 0x7f802dc09150)
2 params, 3 slots, 0 upvalues, 2 locals, 0 constants, 0 functions
	1	[289]	LOADBOOL 	2 1 0
	2	[289]	RETURN   	2 2
	3	[290]	RETURN   	0 1
