
main <./type_check.lua:0,0> (44 instructions, 176 bytes at 0x7fc186c068a0)
0+ params, 9 slots, 0 upvalues, 10 locals, 10 constants, 8 functions
	1	[2]	NEWTABLE 	0 0 0
	2	[4]	GETGLOBAL	1 -1	; require
	3	[4]	LOADK    	2 -2	; "luarocks.core.cfg"
	4	[4]	CALL     	1 2 2
	5	[5]	GETGLOBAL	2 -1	; require
	6	[5]	LOADK    	3 -3	; "luarocks.fun"
	7	[5]	CALL     	2 2 2
	8	[6]	GETGLOBAL	3 -1	; require
	9	[6]	LOADK    	4 -4	; "luarocks.util"
	10	[6]	CALL     	3 2 2
	11	[7]	GETGLOBAL	4 -1	; require
	12	[7]	LOADK    	5 -5	; "luarocks.core.vers"
	13	[7]	CALL     	4 2 2
	14	[12]	SETTABLE 	0 -6 -7	; "MAGIC_PLATFORMS" 3953913772
	15	[24]	CLOSURE  	5 0	; 0x7fc186c07060
	16	[24]	MOVE     	0 5
	17	[37]	CLOSURE  	6 1	; 0x7fc186c066c0
	18	[37]	MOVE     	0 0
	19	[37]	MOVE     	0 3
	20	[37]	MOVE     	0 6
	21	[64]	CLOSURE  	7 2	; 0x7fc186c06dd0
	22	[64]	MOVE     	0 2
	23	[64]	MOVE     	0 3
	24	[64]	MOVE     	0 4
	25	[64]	MOVE     	0 5
	26	[64]	MOVE     	0 6
	27	[44]	SETTABLE 	0 -8 7	; "declare_schemas" -
	28	[64]	CLOSE    	5
	29	[79]	CLOSURE  	5 3	; 0x7fc186c07840
	30	[79]	MOVE     	0 4
	31	[131]	CLOSURE  	6 4	; 0x7fc186c06c20
	32	[131]	MOVE     	0 5
	33	[131]	MOVE     	0 0
	34	[141]	CLOSURE  	7 5	; 0x7fc186c06d50
	35	[196]	CLOSURE  	8 6	; 0x7fc186c06f60
	36	[196]	MOVE     	0 5
	37	[196]	MOVE     	0 6
	38	[196]	MOVE     	0 7
	39	[196]	MOVE     	0 1
	40	[165]	SETTABLE 	0 -9 8	; "type_check_table" -
	41	[211]	CLOSURE  	8 7	; 0x7fc186c094b0
	42	[198]	SETTABLE 	0 -10 8	; "check_undeclared_globals" -
	43	[213]	RETURN   	0 2
	44	[213]	RETURN   	0 1

function <./type_check.lua:15,24> (19 instructions, 76 bytes at 0x7fc186c07060)
2 params, 9 slots, 1 upvalue, 7 locals, 5 constants, 0 functions
	1	[16]	GETGLOBAL	2 -1	; pairs
	2	[16]	MOVE     	3 0
	3	[16]	CALL     	2 2 4
	4	[16]	JMP      	12	; to 17
	5	[17]	GETGLOBAL	7 -2	; type
	6	[17]	MOVE     	8 6
	7	[17]	CALL     	7 2 2
	8	[17]	EQ       	0 7 -3	; - "table"
	9	[17]	JMP      	7	; to 17
	10	[18]	GETTABLE 	7 6 -4	; "_version"
	11	[18]	EQ       	0 7 -5	; - nil
	12	[18]	JMP      	1	; to 14
	13	[19]	SETTABLE 	6 -4 1	; "_version" -
	14	[21]	GETUPVAL 	7 0	; fill_in_version
	15	[21]	MOVE     	8 6
	16	[21]	CALL     	7 2 1
	17	[16]	TFORLOOP 	2 2
	18	[22]	JMP      	-14	; to 5
	19	[24]	RETURN   	0 1

function <./type_check.lua:26,37> (30 instructions, 120 bytes at 0x7fc186c066c0)
1 param, 9 slots, 3 upvalues, 6 locals, 7 constants, 0 functions
	1	[27]	GETGLOBAL	1 -1	; pairs
	2	[27]	MOVE     	2 0
	3	[27]	CALL     	1 2 4
	4	[27]	JMP      	23	; to 28
	5	[28]	GETUPVAL 	6 0	; type_check
	6	[28]	GETTABLE 	6 6 -2	; "MAGIC_PLATFORMS"
	7	[28]	EQ       	0 5 6
	8	[28]	JMP      	11	; to 20
	9	[29]	NEWTABLE 	6 0 1
	10	[30]	GETUPVAL 	7 1	; util
	11	[30]	GETTABLE 	7 7 -4	; "deep_copy"
	12	[30]	MOVE     	8 0
	13	[30]	CALL     	7 2 2
	14	[30]	SETTABLE 	6 -3 7	; "_any" -
	15	[31]	SETTABLE 	0 4 6
	16	[32]	GETTABLE 	6 0 4
	17	[32]	GETTABLE 	6 6 -3	; "_any"
	18	[32]	SETTABLE 	6 4 -5	; - nil
	19	[32]	JMP      	8	; to 28
	20	[33]	GETGLOBAL	6 -6	; type
	21	[33]	MOVE     	7 5
	22	[33]	CALL     	6 2 2
	23	[33]	EQ       	0 6 -7	; - "table"
	24	[33]	JMP      	3	; to 28
	25	[34]	GETUPVAL 	6 2	; expand_magic_platforms
	26	[34]	MOVE     	7 5
	27	[34]	CALL     	6 2 1
	28	[27]	TFORLOOP 	1 2
	29	[35]	JMP      	-25	; to 5
	30	[37]	RETURN   	0 1

function <./type_check.lua:44,64> (46 instructions, 184 bytes at 0x7fc186c06dd0)
1 param, 14 slots, 5 upvalues, 11 locals, 8 constants, 0 functions
	1	[45]	NEWTABLE 	1 0 0
	2	[46]	LOADNIL  	2 2
	3	[48]	GETUPVAL 	3 0	; fun
	4	[48]	GETTABLE 	3 3 -1	; "reverse_in"
	5	[48]	GETUPVAL 	4 0	; fun
	6	[48]	GETTABLE 	4 4 -2	; "sort_in"
	7	[48]	GETUPVAL 	5 1	; util
	8	[48]	GETTABLE 	5 5 -3	; "keys"
	9	[48]	MOVE     	6 0
	10	[48]	CALL     	5 2 2
	11	[48]	GETUPVAL 	6 2	; vers
	12	[48]	GETTABLE 	6 6 -4	; "compare_versions"
	13	[48]	CALL     	4 3 0
	14	[48]	CALL     	3 0 2
	15	[50]	GETGLOBAL	4 -5	; ipairs
	16	[50]	MOVE     	5 3
	17	[50]	CALL     	4 2 4
	18	[50]	JMP      	22	; to 41
	19	[51]	GETTABLE 	9 0 8
	20	[52]	EQ       	1 2 -6	; - nil
	21	[52]	JMP      	10	; to 32
	22	[53]	GETUPVAL 	10 1	; util
	23	[53]	GETTABLE 	10 10 -7	; "deep_copy"
	24	[53]	GETTABLE 	11 1 2
	25	[53]	CALL     	10 2 2
	26	[54]	GETUPVAL 	11 1	; util
	27	[54]	GETTABLE 	11 11 -8	; "deep_merge"
	28	[54]	MOVE     	12 10
	29	[54]	MOVE     	13 9
	30	[54]	CALL     	11 3 1
	31	[55]	MOVE     	9 10
	32	[57]	GETUPVAL 	10 3	; fill_in_version
	33	[57]	MOVE     	11 9
	34	[57]	MOVE     	12 8
	35	[57]	CALL     	10 3 1
	36	[58]	GETUPVAL 	10 4	; expand_magic_platforms
	37	[58]	MOVE     	11 9
	38	[58]	CALL     	10 2 1
	39	[59]	MOVE     	2 8
	40	[60]	SETTABLE 	1 8 9
	41	[50]	TFORLOOP 	4 2
	42	[60]	JMP      	-24	; to 19
	43	[63]	MOVE     	4 1
	44	[63]	MOVE     	5 3
	45	[63]	RETURN   	4 3
	46	[64]	RETURN   	0 1

function <./type_check.lua:69,79> (29 instructions, 116 bytes at 0x7fc186c07840)
3 params, 11 slots, 1 upvalue, 4 locals, 8 constants, 0 functions
	1	[70]	GETTABLE 	3 1 -1	; "_version"
	2	[70]	TEST     	3 0 1
	3	[70]	JMP      	1	; to 5
	4	[70]	LOADK    	3 -2	; "1.0"
	5	[71]	GETUPVAL 	4 0	; vers
	6	[71]	GETTABLE 	4 4 -3	; "compare_versions"
	7	[71]	MOVE     	5 3
	8	[71]	MOVE     	6 0
	9	[71]	CALL     	4 3 2
	10	[71]	TEST     	4 0 0
	11	[71]	JMP      	15	; to 27
	12	[72]	EQ       	0 2 -4	; - ""
	13	[72]	JMP      	4	; to 18
	14	[73]	LOADNIL  	4 4
	15	[73]	LOADK    	5 -5	; "Invalid rockspec_format version number in rockspec? Please fix rockspec accordingly."
	16	[73]	RETURN   	4 3
	17	[73]	JMP      	9	; to 27
	18	[75]	LOADNIL  	4 4
	19	[75]	MOVE     	5 2
	20	[75]	LOADK    	6 -6	; " is not supported in rockspec format "
	21	[75]	MOVE     	7 0
	22	[75]	LOADK    	8 -7	; " (requires version "
	23	[75]	MOVE     	9 3
	24	[75]	LOADK    	10 -8	; "), please fix the rockspec_format field accordingly."
	25	[75]	CONCAT   	5 5 10
	26	[75]	RETURN   	4 3
	27	[78]	LOADBOOL 	4 1 0
	28	[78]	RETURN   	4 2
	29	[79]	RETURN   	0 1

function <./type_check.lua:93,131> (120 instructions, 480 bytes at 0x7fc186c06c20)
4 params, 15 slots, 2 upvalues, 10 locals, 24 constants, 0 functions
	1	[94]	GETGLOBAL	4 -1	; assert
	2	[94]	GETGLOBAL	5 -2	; type
	3	[94]	MOVE     	6 0
	4	[94]	CALL     	5 2 2
	5	[94]	EQ       	1 5 -3	; - "string"
	6	[94]	JMP      	1	; to 8
	7	[94]	LOADBOOL 	5 0 1
	8	[94]	LOADBOOL 	5 1 0
	9	[94]	CALL     	4 2 1
	10	[96]	GETTABLE 	4 2 -4	; "_version"
	11	[96]	TEST     	4 0 0
	12	[96]	JMP      	13	; to 26
	13	[96]	GETTABLE 	4 2 -4	; "_version"
	14	[96]	EQ       	1 4 -5	; - "1.0"
	15	[96]	JMP      	10	; to 26
	16	[97]	GETUPVAL 	4 0	; check_version
	17	[97]	MOVE     	5 0
	18	[97]	MOVE     	6 2
	19	[97]	MOVE     	7 3
	20	[97]	CALL     	4 4 3
	21	[98]	TEST     	4 0 1
	22	[98]	JMP      	3	; to 26
	23	[99]	LOADNIL  	6 6
	24	[99]	MOVE     	7 5
	25	[99]	RETURN   	6 3
	26	[103]	GETGLOBAL	4 -2	; type
	27	[103]	MOVE     	5 1
	28	[103]	CALL     	4 2 2
	29	[103]	TEST     	4 0 1
	30	[103]	JMP      	1	; to 32
	31	[103]	LOADK    	4 -6	; "nil"
	32	[104]	GETTABLE 	5 2 -7	; "_type"
	33	[104]	TEST     	5 0 1
	34	[104]	JMP      	1	; to 36
	35	[104]	LOADK    	5 -8	; "table"
	36	[106]	EQ       	0 5 -9	; - "number"
	37	[106]	JMP      	12	; to 50
	38	[107]	GETGLOBAL	6 -10	; tonumber
	39	[107]	MOVE     	7 1
	40	[107]	CALL     	6 2 2
	41	[107]	TEST     	6 0 1
	42	[107]	JMP      	75	; to 118
	43	[108]	LOADNIL  	6 6
	44	[108]	LOADK    	7 -11	; "Type mismatch on field "
	45	[108]	MOVE     	8 3
	46	[108]	LOADK    	9 -12	; ": expected a number"
	47	[108]	CONCAT   	7 7 9
	48	[108]	RETURN   	6 3
	49	[109]	JMP      	68	; to 118
	50	[110]	EQ       	0 5 -3	; - "string"
	51	[110]	JMP      	37	; to 89
	52	[111]	EQ       	1 4 -3	; - "string"
	53	[111]	JMP      	7	; to 61
	54	[112]	LOADNIL  	6 6
	55	[112]	LOADK    	7 -11	; "Type mismatch on field "
	56	[112]	MOVE     	8 3
	57	[112]	LOADK    	9 -13	; ": expected a string, got "
	58	[112]	MOVE     	10 4
	59	[112]	CONCAT   	7 7 10
	60	[112]	RETURN   	6 3
	61	[114]	GETTABLE 	6 2 -14	; "_pattern"
	62	[115]	TEST     	6 0 0
	63	[115]	JMP      	54	; to 118
	64	[116]	SELF     	7 1 -15	; "match"
	65	[116]	LOADK    	9 -16	; "^"
	66	[116]	MOVE     	10 6
	67	[116]	LOADK    	11 -17	; "$"
	68	[116]	CONCAT   	9 9 11
	69	[116]	CALL     	7 3 2
	70	[116]	TEST     	7 0 1
	71	[116]	JMP      	46	; to 118
	72	[117]	GETTABLE 	7 2 -18	; "_name"
	73	[117]	TEST     	7 0 1
	74	[117]	JMP      	4	; to 79
	75	[117]	LOADK    	7 -19	; "'"
	76	[117]	MOVE     	8 6
	77	[117]	LOADK    	9 -19	; "'"
	78	[117]	CONCAT   	7 7 9
	79	[118]	LOADNIL  	8 8
	80	[118]	LOADK    	9 -11	; "Type mismatch on field "
	81	[118]	MOVE     	10 3
	82	[118]	LOADK    	11 -20	; ": invalid value '"
	83	[118]	MOVE     	12 1
	84	[118]	LOADK    	13 -21	; "' does not match "
	85	[118]	MOVE     	14 7
	86	[118]	CONCAT   	9 9 14
	87	[118]	RETURN   	8 3
	88	[120]	JMP      	29	; to 118
	89	[121]	EQ       	0 5 -8	; - "table"
	90	[121]	JMP      	18	; to 109
	91	[122]	EQ       	1 4 5
	92	[122]	JMP      	7	; to 100
	93	[123]	LOADNIL  	6 6
	94	[123]	LOADK    	7 -11	; "Type mismatch on field "
	95	[123]	MOVE     	8 3
	96	[123]	LOADK    	9 -22	; ": expected a table"
	97	[123]	CONCAT   	7 7 9
	98	[123]	RETURN   	6 3
	99	[123]	JMP      	18	; to 118
	100	[125]	GETUPVAL 	6 1	; type_check
	101	[125]	GETTABLE 	6 6 -23	; "type_check_table"
	102	[125]	MOVE     	7 0
	103	[125]	MOVE     	8 1
	104	[125]	MOVE     	9 2
	105	[125]	MOVE     	10 3
	106	[125]	TAILCALL 	6 5 0
	107	[125]	RETURN   	6 0
	108	[126]	JMP      	9	; to 118
	109	[127]	EQ       	1 4 5
	110	[127]	JMP      	7	; to 118
	111	[128]	LOADNIL  	6 6
	112	[128]	LOADK    	7 -11	; "Type mismatch on field "
	113	[128]	MOVE     	8 3
	114	[128]	LOADK    	9 -24	; ": expected "
	115	[128]	MOVE     	10 5
	116	[128]	CONCAT   	7 7 10
	117	[128]	RETURN   	6 3
	118	[130]	LOADBOOL 	6 1 0
	119	[130]	RETURN   	6 2
	120	[131]	RETURN   	0 1

function <./type_check.lua:133,141> (27 instructions, 108 bytes at 0x7fc186c06d50)
2 params, 6 slots, 0 upvalues, 2 locals, 7 constants, 0 functions
	1	[134]	EQ       	0 0 -1	; - ""
	2	[134]	JMP      	5	; to 8
	3	[135]	GETGLOBAL	2 -2	; tostring
	4	[135]	MOVE     	3 1
	5	[135]	TAILCALL 	2 2 0
	6	[135]	RETURN   	2 0
	7	[135]	JMP      	19	; to 27
	8	[136]	GETGLOBAL	2 -3	; type
	9	[136]	MOVE     	3 1
	10	[136]	CALL     	2 2 2
	11	[136]	EQ       	0 2 -4	; - "string"
	12	[136]	JMP      	6	; to 19
	13	[137]	MOVE     	2 0
	14	[137]	LOADK    	3 -5	; "."
	15	[137]	MOVE     	4 1
	16	[137]	CONCAT   	2 2 4
	17	[137]	RETURN   	2 2
	18	[137]	JMP      	8	; to 27
	19	[139]	MOVE     	2 0
	20	[139]	LOADK    	3 -6	; "["
	21	[139]	GETGLOBAL	4 -2	; tostring
	22	[139]	MOVE     	5 1
	23	[139]	CALL     	4 2 2
	24	[139]	LOADK    	5 -7	; "]"
	25	[139]	CONCAT   	2 2 5
	26	[139]	RETURN   	2 2
	27	[141]	RETURN   	0 1

function <./type_check.lua:165,196> (107 instructions, 428 bytes at 0x7fc186c06f60)
4 params, 19 slots, 4 upvalues, 19 locals, 15 constants, 0 functions
	1	[166]	GETGLOBAL	4 -1	; assert
	2	[166]	GETGLOBAL	5 -2	; type
	3	[166]	MOVE     	6 0
	4	[166]	CALL     	5 2 2
	5	[166]	EQ       	1 5 -3	; - "string"
	6	[166]	JMP      	1	; to 8
	7	[166]	LOADBOOL 	5 0 1
	8	[166]	LOADBOOL 	5 1 0
	9	[166]	CALL     	4 2 1
	10	[167]	GETGLOBAL	4 -1	; assert
	11	[167]	GETGLOBAL	5 -2	; type
	12	[167]	MOVE     	6 1
	13	[167]	CALL     	5 2 2
	14	[167]	EQ       	1 5 -4	; - "table"
	15	[167]	JMP      	1	; to 17
	16	[167]	LOADBOOL 	5 0 1
	17	[167]	LOADBOOL 	5 1 0
	18	[167]	CALL     	4 2 1
	19	[168]	GETGLOBAL	4 -1	; assert
	20	[168]	GETGLOBAL	5 -2	; type
	21	[168]	MOVE     	6 2
	22	[168]	CALL     	5 2 2
	23	[168]	EQ       	1 5 -4	; - "table"
	24	[168]	JMP      	1	; to 26
	25	[168]	LOADBOOL 	5 0 1
	26	[168]	LOADBOOL 	5 1 0
	27	[168]	CALL     	4 2 1
	28	[170]	GETUPVAL 	4 0	; check_version
	29	[170]	MOVE     	5 0
	30	[170]	MOVE     	6 2
	31	[170]	MOVE     	7 3
	32	[170]	CALL     	4 4 3
	33	[171]	TEST     	4 0 1
	34	[171]	JMP      	3	; to 38
	35	[172]	LOADNIL  	6 6
	36	[172]	MOVE     	7 5
	37	[172]	RETURN   	6 3
	38	[175]	GETGLOBAL	6 -5	; pairs
	39	[175]	MOVE     	7 1
	40	[175]	CALL     	6 2 4
	41	[175]	JMP      	34	; to 76
	42	[176]	GETTABLE 	11 2 9
	43	[176]	TEST     	11 0 1
	44	[176]	JMP      	1	; to 46
	45	[176]	GETTABLE 	11 2 -6	; "_any"
	46	[177]	TEST     	11 0 0
	47	[177]	JMP      	15	; to 63
	48	[178]	GETUPVAL 	12 1	; type_check_item
	49	[178]	MOVE     	13 0
	50	[178]	MOVE     	14 10
	51	[178]	MOVE     	15 11
	52	[178]	GETUPVAL 	16 2	; mkfield
	53	[178]	MOVE     	17 3
	54	[178]	MOVE     	18 9
	55	[178]	CALL     	16 3 0
	56	[178]	CALL     	12 0 3
	57	[179]	TEST     	12 0 1
	58	[179]	JMP      	17	; to 76
	59	[179]	LOADNIL  	14 14
	60	[179]	MOVE     	15 13
	61	[179]	RETURN   	14 3
	62	[179]	JMP      	13	; to 76
	63	[180]	GETTABLE 	12 2 -7	; "_more"
	64	[180]	TEST     	12 0 0
	65	[180]	JMP      	1	; to 67
	66	[180]	JMP      	9	; to 76
	67	[183]	GETUPVAL 	12 3	; cfg
	68	[183]	GETTABLE 	12 12 -8	; "accept_unknown_fields"
	69	[183]	TEST     	12 0 1
	70	[183]	JMP      	5	; to 76
	71	[184]	LOADNIL  	12 12
	72	[184]	LOADK    	13 -9	; "Unknown field "
	73	[184]	MOVE     	14 9
	74	[184]	CONCAT   	13 13 14
	75	[184]	RETURN   	12 3
	76	[175]	TFORLOOP 	6 2
	77	[186]	JMP      	-36	; to 42
	78	[188]	GETGLOBAL	6 -5	; pairs
	79	[188]	MOVE     	7 2
	80	[188]	CALL     	6 2 4
	81	[188]	JMP      	21	; to 103
	82	[189]	SELF     	11 9 -10	; "sub"
	83	[189]	LOADK    	13 -11	; 1
	84	[189]	LOADK    	14 -11	; 1
	85	[189]	CALL     	11 4 2
	86	[189]	EQ       	1 11 -12	; - "_"
	87	[189]	JMP      	15	; to 103
	88	[189]	GETTABLE 	11 10 -13	; "_mandatory"
	89	[189]	TEST     	11 0 0
	90	[189]	JMP      	12	; to 103
	91	[190]	GETTABLE 	11 1 9
	92	[190]	TEST     	11 0 1
	93	[190]	JMP      	9	; to 103
	94	[191]	LOADNIL  	11 11
	95	[191]	LOADK    	12 -14	; "Mandatory field "
	96	[191]	GETUPVAL 	13 2	; mkfield
	97	[191]	MOVE     	14 3
	98	[191]	MOVE     	15 9
	99	[191]	CALL     	13 3 2
	100	[191]	LOADK    	14 -15	; " is missing."
	101	[191]	CONCAT   	12 12 14
	102	[191]	RETURN   	11 3
	103	[188]	TFORLOOP 	6 2
	104	[193]	JMP      	-23	; to 82
	105	[195]	LOADBOOL 	6 1 0
	106	[195]	RETURN   	6 2
	107	[196]	RETURN   	0 1

function <./type_check.lua:198,211> (45 instructions, 180 bytes at 0x7fc186c094b0)
2 params, 11 slots, 0 upvalues, 8 locals, 9 constants, 0 functions
	1	[199]	NEWTABLE 	2 0 0
	2	[200]	GETGLOBAL	3 -1	; pairs
	3	[200]	MOVE     	4 0
	4	[200]	CALL     	3 2 4
	5	[200]	JMP      	14	; to 20
	6	[201]	GETTABLE 	8 1 6
	7	[201]	TEST     	8 0 1
	8	[201]	JMP      	11	; to 20
	9	[201]	LOADK    	8 -2	; "MUST_"
	10	[201]	MOVE     	9 6
	11	[201]	CONCAT   	8 8 9
	12	[201]	GETTABLE 	8 1 8
	13	[201]	TEST     	8 0 1
	14	[201]	JMP      	5	; to 20
	15	[202]	GETGLOBAL	8 -3	; table
	16	[202]	GETTABLE 	8 8 -4	; "insert"
	17	[202]	MOVE     	9 2
	18	[202]	MOVE     	10 6
	19	[202]	CALL     	8 3 1
	20	[200]	TFORLOOP 	3 2
	21	[203]	JMP      	-16	; to 6
	22	[205]	LEN      	3 2
	23	[205]	EQ       	0 3 -5	; - 1
	24	[205]	JMP      	6	; to 31
	25	[206]	LOADNIL  	3 3
	26	[206]	LOADK    	4 -6	; "Unknown variable: "
	27	[206]	GETTABLE 	5 2 -5	; 1
	28	[206]	CONCAT   	4 4 5
	29	[206]	RETURN   	3 3
	30	[206]	JMP      	12	; to 43
	31	[207]	LEN      	3 2
	32	[207]	LT       	0 -5 3	; 1 -
	33	[207]	JMP      	9	; to 43
	34	[208]	LOADNIL  	3 3
	35	[208]	LOADK    	4 -7	; "Unknown variables: "
	36	[208]	GETGLOBAL	5 -3	; table
	37	[208]	GETTABLE 	5 5 -8	; "concat"
	38	[208]	MOVE     	6 2
	39	[208]	LOADK    	7 -9	; ", "
	40	[208]	CALL     	5 3 2
	41	[208]	CONCAT   	4 4 5
	42	[208]	RETURN   	3 3
	43	[210]	LOADBOOL 	3 1 0
	44	[210]	RETURN   	3 2
	45	[211]	RETURN   	0 1
