-- BYTECODE -- unix.lua:15-17
0001    MOV      1   0
0002    KSTR     2   0      ; " 1> /dev/null 2> /dev/null"
0003    CAT      1   1   2
0004    RET1     1   2

-- BYTECODE -- unix.lua:22-24
0001    MOV      1   0
0002    KSTR     2   0      ; " 2> /dev/null"
0003    CAT      1   1   2
0004    RET1     1   2

-- BYTECODE -- unix.lua:30-33
0001    GGET     1   0      ; "assert"
0002    GGET     2   1      ; "type"
0003    MOV      3   0
0004    CALL     2   2   2
0005    ISEQS    2   2      ; "string"
0006    JMP      2 => 0009
0007    KPRI     2   1
0008    JMP      3 => 0010
0009 => KPRI     2   2
0010 => CALL     1   1   2
0011    KSTR     1   3      ; "'"
0012    MOV      3   0
0013    TGETS    2   0   4  ; "gsub"
0014    KSTR     4   3      ; "'"
0015    KSTR     5   5      ; "'\''"
0016    CALL     2   2   4
0017    KSTR     3   3      ; "'"
0018    CAT      1   1   3
0019    RET1     1   2

-- BYTECODE -- unix.lua:41-56
0001    GGET     2   0      ; "assert"
0002    GGET     3   1      ; "type"
0003    MOV      4   0
0004    CALL     3   2   2
0005    ISEQS    3   2      ; "string"
0006    JMP      3 => 0009
0007    KPRI     3   1
0008    JMP      4 => 0010
0009 => KPRI     3   2
0010 => CALL     2   1   2
0011    GGET     2   0      ; "assert"
0012    GGET     3   1      ; "type"
0013    MOV      4   1
0014    CALL     3   2   2
0015    ISEQS    3   2      ; "string"
0016    JMP      3 => 0021
0017    NOT      3   1
0018    JMP      4 => 0022
0019    KPRI     3   1
0020    JMP      4 => 0022
0021 => KPRI     3   2
0022 => CALL     2   1   2
0023    MOV      3   0
0024    TGETS    2   0   3  ; "match"
0025    KSTR     4   4      ; "^['"](.*)['"]$"
0026    CALL     2   2   3
0027    ISF          2
0028    JMP      3 => 0030
0029    MOV      0   2
0030 => ISTC     3   1
0031    JMP      3 => 0035
0032    UGET     3   0      ; fs
0033    TGETS    3   3   5  ; "current_dir"
0034    CALL     3   2   1
0035 => MOV      4   3
0036    TGETS    3   3   6  ; "gsub"
0037    KSTR     5   7      ; "/*$"
0038    KSTR     6   8      ; ""
0039    CALL     3   2   4
0040    MOV      1   3
0041    MOV      4   0
0042    TGETS    3   0   9  ; "sub"
0043    KSHORT   5   1
0044    KSHORT   6   1
0045    CALL     3   2   4
0046    ISNES    3  10      ; "/"
0047    JMP      3 => 0050
0048    RET1     0   2
0049    JMP      3 => 0055
0050 => MOV      3   1
0051    KSTR     4  10      ; "/"
0052    MOV      5   0
0053    CAT      3   3   5
0054    RET1     3   2
0055 => RET0     0   1

-- BYTECODE -- unix.lua:62-64
0001    KSTR     1   0      ; "/"
0002    RET1     1   2

-- BYTECODE -- unix.lua:73-121
0001    GGET     5   0      ; "assert"
0002    GGET     6   1      ; "type"
0003    MOV      7   0
0004    CALL     6   2   2
0005    ISEQS    6   2      ; "string"
0006    JMP      6 => 0011
0007    NOT      6   0
0008    JMP      7 => 0012
0009    KPRI     6   1
0010    JMP      7 => 0012
0011 => KPRI     6   2
0012 => CALL     5   1   2
0013    GGET     5   0      ; "assert"
0014    GGET     6   1      ; "type"
0015    MOV      7   1
0016    CALL     6   2   2
0017    ISEQS    6   2      ; "string"
0018    JMP      6 => 0021
0019    KPRI     6   1
0020    JMP      7 => 0022
0021 => KPRI     6   2
0022 => CALL     5   1   2
0023    GGET     5   0      ; "assert"
0024    GGET     6   1      ; "type"
0025    MOV      7   2
0026    CALL     6   2   2
0027    ISEQS    6   2      ; "string"
0028    JMP      6 => 0031
0029    KPRI     6   1
0030    JMP      7 => 0032
0031 => KPRI     6   2
0032 => CALL     5   1   2
0033    GGET     5   0      ; "assert"
0034    GGET     6   1      ; "type"
0035    MOV      7   3
0036    CALL     6   2   2
0037    ISEQS    6   2      ; "string"
0038    JMP      6 => 0043
0039    NOT      6   3
0040    JMP      7 => 0044
0041    KPRI     6   1
0042    JMP      7 => 0044
0043 => KPRI     6   2
0044 => CALL     5   1   2
0045    GGET     5   0      ; "assert"
0046    GGET     6   1      ; "type"
0047    MOV      7   4
0048    CALL     6   2   2
0049    ISEQS    6   2      ; "string"
0050    JMP      6 => 0055
0051    NOT      6   4
0052    JMP      7 => 0056
0053    KPRI     6   1
0054    JMP      7 => 0056
0055 => KPRI     6   2
0056 => CALL     5   1   2
0057    GGET     5   3      ; "io"
0058    TGETS    5   5   4  ; "open"
0059    MOV      6   1
0060    KSTR     7   5      ; "w"
0061    CALL     5   2   3
0062    IST          5
0063    JMP      6 => 0070
0064    KPRI     6   0
0065    KSTR     7   6      ; "Could not open "
0066    MOV      8   1
0067    KSTR     9   7      ; " for writing."
0068    CAT      7   7   9
0069    RET      6   3
0070 => UGET     6   0      ; path
0071    TGETS    6   6   8  ; "package_paths"
0072    MOV      7   2
0073    CALL     6   3   2
0074    TNEW     8   3
0075    KSTR     9   9      ; "package.path="
0076    UGET    10   1      ; util
0077    TGETS   10  10  10  ; "LQ"
0078    MOV     11   6
0079    KSTR    12  11      ; ";"
0080    CAT     11  11  12
0081    CALL    10   2   2
0082    KSTR    11  12      ; "..package.path"
0083    CAT      9   9  11
0084    TSETB    9   8   1
0085    KSTR     9  13      ; "package.cpath="
0086    UGET    10   1      ; util
0087    TGETS   10  10  10  ; "LQ"
0088    MOV     11   7
0089    KSTR    12  11      ; ";"
0090    CAT     11  11  12
0091    CALL    10   2   2
0092    KSTR    11  14      ; "..package.cpath"
0093    CAT      9   9  11
0094    TSETB    9   8   2
0095    ISEQS    1  15      ; "luarocks"
0096    JMP      9 => 0099
0097    ISNES    1  16      ; "luarocks-admin"
0098    JMP      9 => 0117
0099 => TNEW     9   3
0100    KSTR    10   9      ; "package.path="
0101    UGET    11   1      ; util
0102    TGETS   11  11  10  ; "LQ"
0103    GGET    12  17      ; "package"
0104    TGETS   12  12  18  ; "path"
0105    CALL    11   2   2
0106    CAT     10  10  11
0107    TSETB   10   9   1
0108    KSTR    10  13      ; "package.cpath="
0109    UGET    11   1      ; util
0110    TGETS   11  11  10  ; "LQ"
0111    GGET    12  17      ; "package"
0112    TGETS   12  12  19  ; "cpath"
0113    CALL    11   2   2
0114    CAT     10  10  11
0115    TSETB   10   9   2
0116    MOV      8   9
0117 => ISF          3
0118    JMP      9 => 0144
0119    ISF          4
0120    JMP      9 => 0144
0121    KSTR     9  20      ; "local k,l,_=pcall(require,"
0122    UGET    10   1      ; util
0123    TGETS   10  10  10  ; "LQ"
0124    KSTR    11  21      ; "luarocks.loader"
0125    CALL    10   2   2
0126    KSTR    11  22      ; ") _=k "
0127    KSTR    12  23      ; "and l.add_context("
0128    UGET    13   1      ; util
0129    TGETS   13  13  10  ; "LQ"
0130    MOV     14   3
0131    CALL    13   2   2
0132    KSTR    14  24      ; ","
0133    UGET    15   1      ; util
0134    TGETS   15  15  10  ; "LQ"
0135    MOV     16   4
0136    CALL    15   2   2
0137    KSTR    16  25      ; ")"
0138    CAT      9   9  16
0139    GGET    10  26      ; "table"
0140    TGETS   10  10  27  ; "insert"
0141    MOV     11   8
0142    MOV     12   9
0143    CALL    10   1   3
0144 => TDUP     9  32
0145    UGET    10   2      ; fs
0146    TGETS   10  10  28  ; "Q"
0147    UGET    11   3      ; dir
0148    TGETS   11  11  18  ; "path"
0149    UGET    12   4      ; cfg
0150    TGETS   12  12  29  ; "variables"
0151    TGETS   12  12  30  ; "LUA_BINDIR"
0152    UGET    13   4      ; cfg
0153    TGETS   13  13  31  ; "lua_interpreter"
0154    CALL    11   0   3
0155    CALLM   10   2   0
0156    TSETB   10   9   1
0157    UGET    10   2      ; fs
0158    TGETS   10  10  28  ; "Q"
0159    GGET    11  26      ; "table"
0160    TGETS   11  11  33  ; "concat"
0161    MOV     12   8
0162    KSTR    13  11      ; ";"
0163    CALL    11   0   3
0164    CALLM   10   2   0
0165    TSETB   10   9   3
0166    ISF          0
0167    JMP     10 => 0174
0168    UGET    10   2      ; fs
0169    TGETS   10  10  28  ; "Q"
0170    MOV     11   0
0171    CALL    10   2   2
0172    IST         10
0173    JMP     11 => 0175
0174 => KSTR    10  34      ; "$([ "$*" ] || echo -i)"
0175 => TSETB   10   9   4
0176    VARG    10   0   5
0177    TSETM   10   0      ; 5
0178    MOV     11   5
0179    TGETS   10   5  35  ; "write"
0180    KSTR    12  36      ; "#!/bin/sh\n\n"
0181    CALL    10   1   3
0182    MOV     11   5
0183    TGETS   10   5  35  ; "write"
0184    KSTR    12  37      ; "LUAROCKS_SYSCONFDIR="
0185    UGET    13   2      ; fs
0186    TGETS   13  13  28  ; "Q"
0187    UGET    14   4      ; cfg
0188    TGETS   14  14  38  ; "sysconfdir"
0189    CALL    13   2   2
0190    KSTR    14  39      ; " "
0191    CAT     12  12  14
0192    CALL    10   1   3
0193    MOV     11   5
0194    TGETS   10   5  35  ; "write"
0195    KSTR    12  40      ; "exec "
0196    GGET    13  26      ; "table"
0197    TGETS   13  13  33  ; "concat"
0198    MOV     14   9
0199    KSTR    15  39      ; " "
0200    CALL    13   2   3
0201    KSTR    14  41      ; " "$@"\n"
0202    CAT     12  12  14
0203    CALL    10   1   3
0204    MOV     11   5
0205    TGETS   10   5  42  ; "close"
0206    CALL    10   1   2
0207    UGET    10   2      ; fs
0208    TGETS   10  10  43  ; "set_permissions"
0209    MOV     11   1
0210    KSTR    12  44      ; "exec"
0211    KSTR    13  45      ; "all"
0212    CALL    10   2   4
0213    ISF         10
0214    JMP     11 => 0218
0215    KPRI    10   2
0216    RET1    10   2
0217    JMP     10 => 0224
0218 => KPRI    10   0
0219    KSTR    11  46      ; "Could not make "
0220    MOV     12   1
0221    KSTR    13  47      ; " executable."
0222    CAT     11  11  13
0223    RET     10   3
0224 => RET0     0   1

-- BYTECODE -- unix.lua:128-143
0001    MOV      2   0
0002    TGETS    1   0   0  ; "match"
0003    KSTR     3   1      ; "%.lua$"
0004    CALL     1   2   3
0005    ISF          1
0006    JMP      2 => 0009
0007    KPRI     1   1
0008    RET1     1   2
0009 => GGET     1   2      ; "io"
0010    TGETS    1   1   3  ; "open"
0011    MOV      2   0
0012    CALL     1   2   2
0013    IST          1
0014    JMP      2 => 0017
0015    KPRI     2   2
0016    RET1     2   2
0017 => MOV      3   1
0018    TGETS    2   1   4  ; "read"
0019    KSHORT   4   2
0020    CALL     2   2   3
0021    MOV      4   1
0022    TGETS    3   1   5  ; "close"
0023    CALL     3   1   2
0024    IST          2
0025    JMP      3 => 0034
0026    UGET     3   0      ; util
0027    TGETS    3   3   6  ; "warning"
0028    KSTR     4   7      ; "could not read "
0029    MOV      5   0
0030    CAT      4   4   5
0031    CALL     3   1   2
0032    KPRI     3   2
0033    RET1     3   2
0034 => ISNES    2   8      ; "#!"
0035    JMP      3 => 0038
0036    KPRI     3   1
0037    JMP      4 => 0039
0038 => KPRI     3   2
0039 => RET1     3   2

-- BYTECODE -- unix.lua:145-147
0001    UGET     2   0      ; fs
0002    TGETS    2   2   0  ; "copy"
0003    MOV      3   0
0004    MOV      4   1
0005    KSTR     5   1      ; "exec"
0006    CALLT    2   4

-- BYTECODE -- unix.lua:159-161
0001    GGET     2   0      ; "os"
0002    TGETS    2   2   1  ; "rename"
0003    MOV      3   1
0004    MOV      4   0
0005    CALLT    2   3

-- BYTECODE -- unix.lua:163-165
0001    GGET     0   0      ; "os"
0002    TGETS    0   0   1  ; "tmpname"
0003    CALLT    0   1

-- BYTECODE -- unix.lua:167-169
0001    GGET     0   0      ; "os"
0002    TGETS    0   0   1  ; "getenv"
0003    KSTR     1   2      ; "USER"
0004    CALLT    0   2

-- BYTECODE -- unix.lua:171-173
0001    KSTR     2   0      ; "export %s='%s'"
0002    MOV      3   2
0003    TGETS    2   2   1  ; "format"
0004    MOV      4   0
0005    MOV      5   1
0006    CALLT    2   4

-- BYTECODE -- unix.lua:192-212
0001    UGET     1   0      ; fs
0002    TGETS    1   1   0  ; "_unix_umask"
0003    CALL     1   2   1
0004    KSTR     2   1      ; ""
0005    KSHORT   3   1
0006    KSHORT   4   3
0007    KSHORT   5   1
0008    FORI     3 => 0053
0009 => UGET     7   1      ; octal_to_rwx
0010    MOV      9   0
0011    TGETS    8   0   2  ; "sub"
0012    MOV     10   6
0013    MOV     11   6
0014    CALL     8   2   4
0015    TGETV    7   7   8
0016    UGET     8   1      ; octal_to_rwx
0017    MOV     10   1
0018    TGETS    9   1   2  ; "sub"
0019    MOV     11   6
0020    MOV     12   6
0021    CALL     9   2   4
0022    TGETV    8   8   9
0023    KSTR     9   1      ; ""
0024    KSHORT  10   1
0025    KSHORT  11   3
0026    KSHORT  12   1
0027    FORI    10 => 0048
0028 => MOV     15   7
0029    TGETS   14   7   2  ; "sub"
0030    MOV     16  13
0031    MOV     17  13
0032    CALL    14   2   4
0033    MOV     16   8
0034    TGETS   15   8   2  ; "sub"
0035    MOV     17  13
0036    MOV     18  13
0037    CALL    15   2   4
0038    ISNEV   14  15
0039    JMP     16 => 0044
0040    MOV     16   9
0041    KSTR    17   3      ; "-"
0042    CAT      9  16  17
0043    JMP     16 => 0047
0044 => MOV     16   9
0045    MOV     17  14
0046    CAT      9  16  17
0047 => FORL    10 => 0028
0048 => MOV     10   2
0049    UGET    11   2      ; rwx_to_octal
0050    TGETV   11  11   9
0051    CAT      2  10  11
0052    FORL     3 => 0009
0053 => RET1     2   2

-- BYTECODE -- unix.lua:214-219
0001    UGET     0   0      ; fs
0002    TGETS    0   0   0  ; "is_dir"
0003    KSTR     1   1      ; "/var/cache"
0004    CALL     0   2   2
0005    ISF          0
0006    JMP      1 => 0009
0007    KSTR     0   1      ; "/var/cache"
0008    RET1     0   2
0009 => UGET     0   1      ; dir
0010    TGETS    0   0   2  ; "path"
0011    UGET     1   0      ; fs
0012    TGETS    1   1   3  ; "system_temp_dir"
0013    CALL     1   2   1
0014    KSTR     2   4      ; "cache"
0015    CALLT    0   3

-- BYTECODE -- unix.lua:0-222
0001    TNEW     0   0
0002    GGET     1   0      ; "require"
0003    KSTR     2   1      ; "luarocks.fs"
0004    CALL     1   2   2
0005    GGET     2   0      ; "require"
0006    KSTR     3   2      ; "luarocks.core.cfg"
0007    CALL     2   2   2
0008    GGET     3   0      ; "require"
0009    KSTR     4   3      ; "luarocks.dir"
0010    CALL     3   2   2
0011    GGET     4   0      ; "require"
0012    KSTR     5   4      ; "luarocks.path"
0013    CALL     4   2   2
0014    GGET     5   0      ; "require"
0015    KSTR     6   5      ; "luarocks.util"
0016    CALL     5   2   2
0017    FNEW     6   7      ; unix.lua:15
0018    TSETS    6   0   6  ; "quiet"
0019    FNEW     6   9      ; unix.lua:22
0020    TSETS    6   0   8  ; "quiet_stderr"
0021    FNEW     6  11      ; unix.lua:30
0022    TSETS    6   0  10  ; "Q"
0023    FNEW     6  13      ; unix.lua:41
0024    TSETS    6   0  12  ; "absolute_name"
0025    FNEW     6  15      ; unix.lua:62
0026    TSETS    6   0  14  ; "root_of"
0027    FNEW     6  17      ; unix.lua:73
0028    TSETS    6   0  16  ; "wrap_script"
0029    FNEW     6  19      ; unix.lua:128
0030    TSETS    6   0  18  ; "is_actual_binary"
0031    FNEW     6  21      ; unix.lua:145
0032    TSETS    6   0  20  ; "copy_binary"
0033    FNEW     6  23      ; unix.lua:159
0034    TSETS    6   0  22  ; "replace_file"
0035    FNEW     6  25      ; unix.lua:163
0036    TSETS    6   0  24  ; "tmpname"
0037    FNEW     6  27      ; unix.lua:167
0038    TSETS    6   0  26  ; "current_user"
0039    FNEW     6  29      ; unix.lua:171
0040    TSETS    6   0  28  ; "export_cmd"
0041    TDUP     6  30
0042    TNEW     7   0
0043    GGET     8  31      ; "pairs"
0044    MOV      9   6
0045    CALL     8   4   2
0046    ISNEXT  11 => 0048
0047 => TSETV   11   7  12
0048 => ITERN   11   3   3
0049    ITERL   11 => 0047
0050    FNEW     8  33      ; unix.lua:192
0051    TSETS    8   0  32  ; "_unix_moderate_permissions"
0052    FNEW     8  35      ; unix.lua:214
0053    TSETS    8   0  34  ; "system_cache_dir"
0054    UCLO     0 => 0055
0055 => RET1     0   2

