
main <./cmd/unpack.lua:0,0> (42 instructions, 168 bytes at 0x7fec3bc068a0)
0+ params, 11 slots, 0 upvalues, 10 locals, 9 constants, 5 functions
	1	[4]	NEWTABLE 	0 0 0
	2	[6]	GETGLOBAL	1 -1	; require
	3	[6]	LOADK    	2 -2	; "luarocks.fetch"
	4	[6]	CALL     	1 2 2
	5	[7]	GETGLOBAL	2 -1	; require
	6	[7]	LOADK    	3 -3	; "luarocks.fs"
	7	[7]	CALL     	2 2 2
	8	[8]	GETGLOBAL	3 -1	; require
	9	[8]	LOADK    	4 -4	; "luarocks.util"
	10	[8]	CALL     	3 2 2
	11	[9]	GETGLOBAL	4 -1	; require
	12	[9]	LOADK    	5 -5	; "luarocks.build"
	13	[9]	CALL     	4 2 2
	14	[10]	GETGLOBAL	5 -1	; require
	15	[10]	LOADK    	6 -6	; "luarocks.dir"
	16	[10]	CALL     	5 2 2
	17	[11]	GETGLOBAL	6 -1	; require
	18	[11]	LOADK    	7 -7	; "luarocks.search"
	19	[11]	CALL     	6 2 2
	20	[29]	CLOSURE  	7 0	; 0x7fec3bc06cd0
	21	[29]	MOVE     	0 3
	22	[13]	SETTABLE 	0 -8 7	; "add_to_parser" -
	23	[57]	CLOSURE  	7 1	; 0x7fec3bc066c0
	24	[57]	MOVE     	0 1
	25	[57]	MOVE     	0 2
	26	[57]	MOVE     	0 4
	27	[95]	CLOSURE  	8 2	; 0x7fec3bc06c10
	28	[95]	MOVE     	0 1
	29	[95]	MOVE     	0 2
	30	[95]	MOVE     	0 4
	31	[149]	CLOSURE  	9 3	; 0x7fec3bc067b0
	32	[149]	MOVE     	0 5
	33	[149]	MOVE     	0 2
	34	[149]	MOVE     	0 3
	35	[149]	MOVE     	0 8
	36	[149]	MOVE     	0 7
	37	[166]	CLOSURE  	10 4	; 0x7fec3bc07050
	38	[166]	MOVE     	0 6
	39	[166]	MOVE     	0 9
	40	[154]	SETTABLE 	0 -9 10	; "command" -
	41	[168]	RETURN   	0 2
	42	[168]	RETURN   	0 1

function <./cmd/unpack.lua:13,29> (36 instructions, 144 bytes at 0x7fec3bc06cd0)
1 param, 7 slots, 1 upvalue, 2 locals, 21 constants, 0 functions
	1	[14]	SELF     	1 0 -1	; "command"
	2	[14]	LOADK    	3 -2	; "unpack"
	3	[17]	LOADK    	4 -3	; "Unpacks the contents of a rock in a newly created directory.\nArgument may be a rock file, or the name of a rock in a rocks server.\nIn the latter case, the rock version may be given as a second argument."
	4	[18]	GETUPVAL 	5 0	; util
	5	[18]	GETTABLE 	5 5 -4	; "see_also"
	6	[18]	CALL     	5 1 0
	7	[14]	CALL     	1 0 2
	8	[19]	SELF     	1 1 -5	; "summary"
	9	[19]	LOADK    	3 -6	; "Unpack the contents of a rock."
	10	[19]	CALL     	1 3 2
	11	[21]	SELF     	2 1 -7	; "argument"
	12	[21]	LOADK    	4 -8	; "rock"
	13	[21]	LOADK    	5 -9	; "A rock file or the name of a rock."
	14	[21]	CALL     	2 4 2
	15	[22]	SELF     	2 2 -10	; "action"
	16	[22]	GETUPVAL 	4 0	; util
	17	[22]	GETTABLE 	4 4 -11	; "namespaced_name_action"
	18	[22]	CALL     	2 3 1
	19	[23]	SELF     	2 1 -7	; "argument"
	20	[23]	LOADK    	4 -12	; "version"
	21	[23]	LOADK    	5 -13	; "Rock version."
	22	[23]	CALL     	2 4 2
	23	[24]	SELF     	2 2 -14	; "args"
	24	[24]	LOADK    	4 -15	; "?"
	25	[24]	CALL     	2 3 1
	26	[26]	SELF     	2 1 -16	; "flag"
	27	[26]	LOADK    	4 -17	; "--force"
	28	[26]	LOADK    	5 -18	; "Unpack files even if the output directory already exists."
	29	[26]	CALL     	2 4 1
	30	[27]	SELF     	2 1 -16	; "flag"
	31	[27]	LOADK    	4 -19	; "--check-lua-versions"
	32	[27]	LOADK    	5 -20	; "If the rock can't be found, check repository "
	33	[28]	LOADK    	6 -21	; "and report if it is available for another Lua version."
	34	[28]	CONCAT   	5 5 6
	35	[27]	CALL     	2 4 1
	36	[29]	RETURN   	0 1

function <./cmd/unpack.lua:37,57> (78 instructions, 312 bytes at 0x7fec3bc066c0)
2 params, 10 slots, 3 upvalues, 8 locals, 11 constants, 0 functions
	1	[38]	GETGLOBAL	2 -1	; assert
	2	[38]	GETGLOBAL	3 -2	; type
	3	[38]	MOVE     	4 0
	4	[38]	CALL     	3 2 2
	5	[38]	EQ       	1 3 -3	; - "string"
	6	[38]	JMP      	1	; to 8
	7	[38]	LOADBOOL 	3 0 1
	8	[38]	LOADBOOL 	3 1 0
	9	[38]	CALL     	2 2 1
	10	[39]	GETGLOBAL	2 -1	; assert
	11	[39]	GETGLOBAL	3 -2	; type
	12	[39]	MOVE     	4 1
	13	[39]	CALL     	3 2 2
	14	[39]	EQ       	1 3 -3	; - "string"
	15	[39]	JMP      	1	; to 17
	16	[39]	LOADBOOL 	3 0 1
	17	[39]	LOADBOOL 	3 1 0
	18	[39]	CALL     	2 2 1
	19	[41]	GETUPVAL 	2 0	; fetch
	20	[41]	GETTABLE 	2 2 -4	; "load_rockspec"
	21	[41]	MOVE     	3 0
	22	[41]	CALL     	2 2 3
	23	[42]	TEST     	2 0 1
	24	[42]	JMP      	7	; to 32
	25	[43]	LOADNIL  	4 4
	26	[43]	LOADK    	5 -5	; "Failed loading rockspec "
	27	[43]	MOVE     	6 0
	28	[43]	LOADK    	7 -6	; ": "
	29	[43]	MOVE     	8 3
	30	[43]	CONCAT   	5 5 8
	31	[43]	RETURN   	4 3
	32	[45]	GETUPVAL 	4 1	; fs
	33	[45]	GETTABLE 	4 4 -7	; "change_dir"
	34	[45]	MOVE     	5 1
	35	[45]	CALL     	4 2 3
	36	[46]	TEST     	4 0 1
	37	[46]	JMP      	3	; to 41
	38	[46]	LOADNIL  	6 6
	39	[46]	MOVE     	7 5
	40	[46]	RETURN   	6 3
	41	[47]	GETUPVAL 	6 0	; fetch
	42	[47]	GETTABLE 	6 6 -8	; "fetch_sources"
	43	[47]	MOVE     	7 2
	44	[47]	LOADBOOL 	8 1 0
	45	[47]	LOADK    	9 -9	; "."
	46	[47]	CALL     	6 4 3
	47	[48]	TEST     	6 0 1
	48	[48]	JMP      	3	; to 52
	49	[49]	LOADNIL  	8 8
	50	[49]	MOVE     	9 7
	51	[49]	RETURN   	8 3
	52	[51]	GETUPVAL 	8 1	; fs
	53	[51]	GETTABLE 	8 8 -7	; "change_dir"
	54	[51]	MOVE     	9 7
	55	[51]	CALL     	8 2 3
	56	[51]	MOVE     	5 9
	57	[51]	MOVE     	6 8
	58	[52]	TEST     	6 0 1
	59	[52]	JMP      	3	; to 63
	60	[52]	LOADNIL  	8 8
	61	[52]	MOVE     	9 5
	62	[52]	RETURN   	8 3
	63	[53]	GETUPVAL 	8 2	; build
	64	[53]	GETTABLE 	8 8 -10	; "apply_patches"
	65	[53]	MOVE     	9 2
	66	[53]	CALL     	8 2 3
	67	[53]	MOVE     	5 9
	68	[53]	MOVE     	6 8
	69	[54]	GETUPVAL 	8 1	; fs
	70	[54]	GETTABLE 	8 8 -11	; "pop_dir"
	71	[54]	CALL     	8 1 1
	72	[55]	TEST     	6 0 1
	73	[55]	JMP      	3	; to 77
	74	[55]	LOADNIL  	8 8
	75	[55]	MOVE     	9 5
	76	[55]	RETURN   	8 3
	77	[56]	RETURN   	2 2
	78	[57]	RETURN   	0 1

function <./cmd/unpack.lua:66,95> (100 instructions, 400 bytes at 0x7fec3bc06c10)
3 params, 14 slots, 3 upvalues, 11 locals, 16 constants, 0 functions
	1	[67]	GETGLOBAL	3 -1	; assert
	2	[67]	GETGLOBAL	4 -2	; type
	3	[67]	MOVE     	5 0
	4	[67]	CALL     	4 2 2
	5	[67]	EQ       	1 4 -3	; - "string"
	6	[67]	JMP      	1	; to 8
	7	[67]	LOADBOOL 	4 0 1
	8	[67]	LOADBOOL 	4 1 0
	9	[67]	CALL     	3 2 1
	10	[68]	GETGLOBAL	3 -1	; assert
	11	[68]	GETGLOBAL	4 -2	; type
	12	[68]	MOVE     	5 1
	13	[68]	CALL     	4 2 2
	14	[68]	EQ       	1 4 -3	; - "string"
	15	[68]	JMP      	1	; to 17
	16	[68]	LOADBOOL 	4 0 1
	17	[68]	LOADBOOL 	4 1 0
	18	[68]	CALL     	3 2 1
	19	[70]	GETUPVAL 	3 0	; fetch
	20	[70]	GETTABLE 	3 3 -4	; "fetch_and_unpack_rock"
	21	[70]	MOVE     	4 0
	22	[70]	MOVE     	5 1
	23	[70]	CALL     	3 3 4
	24	[71]	TEST     	3 0 1
	25	[71]	JMP      	4	; to 30
	26	[72]	LOADNIL  	6 6
	27	[72]	MOVE     	7 4
	28	[72]	MOVE     	8 5
	29	[72]	RETURN   	6 4
	30	[74]	GETUPVAL 	6 1	; fs
	31	[74]	GETTABLE 	6 6 -5	; "change_dir"
	32	[74]	MOVE     	7 1
	33	[74]	CALL     	6 2 3
	34	[74]	MOVE     	4 7
	35	[74]	MOVE     	3 6
	36	[75]	TEST     	3 0 1
	37	[75]	JMP      	3	; to 41
	38	[75]	LOADNIL  	6 6
	39	[75]	MOVE     	7 4
	40	[75]	RETURN   	6 3
	41	[76]	MOVE     	6 1
	42	[76]	LOADK    	7 -6	; ".rockspec"
	43	[76]	CONCAT   	6 6 7
	44	[77]	GETUPVAL 	7 0	; fetch
	45	[77]	GETTABLE 	7 7 -7	; "load_rockspec"
	46	[77]	MOVE     	8 6
	47	[77]	CALL     	7 2 3
	48	[78]	TEST     	7 0 1
	49	[78]	JMP      	7	; to 57
	50	[79]	LOADNIL  	9 9
	51	[79]	LOADK    	10 -8	; "Failed loading rockspec "
	52	[79]	MOVE     	11 6
	53	[79]	LOADK    	12 -9	; ": "
	54	[79]	MOVE     	13 8
	55	[79]	CONCAT   	10 10 13
	56	[79]	RETURN   	9 3
	57	[81]	EQ       	0 2 -10	; - "src"
	58	[81]	JMP      	40	; to 99
	59	[82]	GETTABLE 	9 7 -11	; "source"
	60	[82]	GETTABLE 	9 9 -12	; "file"
	61	[82]	TEST     	9 0 0
	62	[82]	JMP      	36	; to 99
	63	[83]	GETUPVAL 	9 1	; fs
	64	[83]	GETTABLE 	9 9 -13	; "unpack_archive"
	65	[83]	GETTABLE 	10 7 -11	; "source"
	66	[83]	GETTABLE 	10 10 -12	; "file"
	67	[83]	CALL     	9 2 3
	68	[84]	TEST     	9 0 1
	69	[84]	JMP      	3	; to 73
	70	[85]	LOADNIL  	11 11
	71	[85]	MOVE     	12 10
	72	[85]	RETURN   	11 3
	73	[87]	GETUPVAL 	11 1	; fs
	74	[87]	GETTABLE 	11 11 -5	; "change_dir"
	75	[87]	GETTABLE 	12 7 -11	; "source"
	76	[87]	GETTABLE 	12 12 -14	; "dir"
	77	[87]	CALL     	11 2 3
	78	[87]	MOVE     	10 12
	79	[87]	MOVE     	9 11
	80	[88]	TEST     	9 0 1
	81	[88]	JMP      	3	; to 85
	82	[88]	LOADNIL  	11 11
	83	[88]	MOVE     	12 10
	84	[88]	RETURN   	11 3
	85	[89]	GETUPVAL 	11 2	; build
	86	[89]	GETTABLE 	11 11 -15	; "apply_patches"
	87	[89]	MOVE     	12 7
	88	[89]	CALL     	11 2 3
	89	[89]	MOVE     	10 12
	90	[89]	MOVE     	9 11
	91	[90]	GETUPVAL 	11 1	; fs
	92	[90]	GETTABLE 	11 11 -16	; "pop_dir"
	93	[90]	CALL     	11 1 1
	94	[91]	TEST     	9 0 1
	95	[91]	JMP      	3	; to 99
	96	[91]	LOADNIL  	11 11
	97	[91]	MOVE     	12 10
	98	[91]	RETURN   	11 3
	99	[94]	RETURN   	7 2
	100	[95]	RETURN   	0 1

function <./cmd/unpack.lua:103,149> (136 instructions, 544 bytes at 0x7fec3bc067b0)
2 params, 14 slots, 5 upvalues, 13 locals, 30 constants, 0 functions
	1	[104]	GETGLOBAL	2 -1	; assert
	2	[104]	GETGLOBAL	3 -2	; type
	3	[104]	MOVE     	4 0
	4	[104]	CALL     	3 2 2
	5	[104]	EQ       	1 3 -3	; - "string"
	6	[104]	JMP      	1	; to 8
	7	[104]	LOADBOOL 	3 0 1
	8	[104]	LOADBOOL 	3 1 0
	9	[104]	CALL     	2 2 1
	10	[106]	GETUPVAL 	2 0	; dir
	11	[106]	GETTABLE 	2 2 -4	; "base_name"
	12	[106]	MOVE     	3 0
	13	[106]	CALL     	2 2 2
	14	[107]	SELF     	3 2 -5	; "match"
	15	[107]	LOADK    	5 -6	; "(.*)%.([^.]+)%.(rock)$"
	16	[107]	CALL     	3 3 4
	17	[108]	TEST     	5 0 1
	18	[108]	JMP      	6	; to 25
	19	[109]	SELF     	6 2 -5	; "match"
	20	[109]	LOADK    	8 -7	; "(.*)%.(rockspec)$"
	21	[109]	CALL     	6 3 3
	22	[109]	MOVE     	5 7
	23	[109]	MOVE     	3 6
	24	[110]	LOADK    	4 -8	; "rockspec"
	25	[112]	TEST     	5 0 1
	26	[112]	JMP      	5	; to 32
	27	[113]	LOADNIL  	6 6
	28	[113]	MOVE     	7 0
	29	[113]	LOADK    	8 -9	; " does not seem to be a valid filename."
	30	[113]	CONCAT   	7 7 8
	31	[113]	RETURN   	6 3
	32	[116]	GETUPVAL 	6 1	; fs
	33	[116]	GETTABLE 	6 6 -10	; "exists"
	34	[116]	MOVE     	7 3
	35	[116]	CALL     	6 2 2
	36	[117]	TEST     	6 0 0
	37	[117]	JMP      	8	; to 46
	38	[117]	TEST     	1 0 1
	39	[117]	JMP      	6	; to 46
	40	[118]	LOADNIL  	7 7
	41	[118]	LOADK    	8 -11	; "Directory "
	42	[118]	MOVE     	9 3
	43	[118]	LOADK    	10 -12	; " already exists."
	44	[118]	CONCAT   	8 8 10
	45	[118]	RETURN   	7 3
	46	[120]	TEST     	6 0 1
	47	[120]	JMP      	9	; to 57
	48	[121]	GETUPVAL 	7 1	; fs
	49	[121]	GETTABLE 	7 7 -13	; "make_dir"
	50	[121]	MOVE     	8 3
	51	[121]	CALL     	7 2 3
	52	[122]	TEST     	7 0 1
	53	[122]	JMP      	3	; to 57
	54	[122]	LOADNIL  	9 9
	55	[122]	MOVE     	10 8
	56	[122]	RETURN   	9 3
	57	[124]	GETUPVAL 	7 2	; util
	58	[124]	GETTABLE 	7 7 -14	; "schedule_function"
	59	[124]	GETUPVAL 	8 1	; fs
	60	[124]	GETTABLE 	8 8 -15	; "delete"
	61	[124]	GETUPVAL 	9 1	; fs
	62	[124]	GETTABLE 	9 9 -16	; "absolute_name"
	63	[124]	MOVE     	10 3
	64	[124]	CALL     	9 2 0
	65	[124]	CALL     	7 0 2
	66	[126]	LOADNIL  	8 9
	67	[127]	EQ       	0 5 -17	; - "rock"
	68	[127]	JMP      	8	; to 77
	69	[128]	GETUPVAL 	10 3	; unpack_rock
	70	[128]	MOVE     	11 0
	71	[128]	MOVE     	12 3
	72	[128]	MOVE     	13 4
	73	[128]	CALL     	10 4 3
	74	[128]	MOVE     	9 11
	75	[128]	MOVE     	8 10
	76	[128]	JMP      	8	; to 85
	77	[129]	EQ       	0 5 -8	; - "rockspec"
	78	[129]	JMP      	6	; to 85
	79	[130]	GETUPVAL 	10 4	; unpack_rockspec
	80	[130]	MOVE     	11 0
	81	[130]	MOVE     	12 3
	82	[130]	CALL     	10 3 3
	83	[130]	MOVE     	9 11
	84	[130]	MOVE     	8 10
	85	[132]	TEST     	8 0 1
	86	[132]	JMP      	3	; to 90
	87	[133]	LOADNIL  	10 10
	88	[133]	MOVE     	11 9
	89	[133]	RETURN   	10 3
	90	[135]	EQ       	1 4 -18	; - "src"
	91	[135]	JMP      	2	; to 94
	92	[135]	EQ       	0 4 -8	; - "rockspec"
	93	[135]	JMP      	36	; to 130
	94	[136]	GETTABLE 	10 8 -19	; "source"
	95	[136]	GETTABLE 	10 10 -20	; "dir"
	96	[136]	EQ       	1 10 -21	; - "."
	97	[136]	JMP      	12	; to 110
	98	[137]	GETUPVAL 	10 1	; fs
	99	[137]	GETTABLE 	10 10 -22	; "copy"
	100	[137]	GETTABLE 	11 8 -23	; "local_abs_filename"
	101	[137]	GETTABLE 	12 8 -19	; "source"
	102	[137]	GETTABLE 	12 12 -20	; "dir"
	103	[137]	LOADK    	13 -24	; "read"
	104	[137]	CALL     	10 4 2
	105	[138]	TEST     	10 0 1
	106	[138]	JMP      	3	; to 110
	107	[139]	LOADNIL  	11 11
	108	[139]	LOADK    	12 -25	; "Failed copying unpacked rockspec into unpacked source directory."
	109	[139]	RETURN   	11 3
	110	[142]	GETUPVAL 	10 2	; util
	111	[142]	GETTABLE 	10 10 -26	; "printout"
	112	[142]	CALL     	10 1 1
	113	[143]	GETUPVAL 	10 2	; util
	114	[143]	GETTABLE 	10 10 -26	; "printout"
	115	[143]	LOADK    	11 -27	; "Done. You may now enter directory "
	116	[143]	CALL     	10 2 1
	117	[144]	GETUPVAL 	10 2	; util
	118	[144]	GETTABLE 	10 10 -26	; "printout"
	119	[144]	GETUPVAL 	11 0	; dir
	120	[144]	GETTABLE 	11 11 -28	; "path"
	121	[144]	MOVE     	12 3
	122	[144]	GETTABLE 	13 8 -19	; "source"
	123	[144]	GETTABLE 	13 13 -20	; "dir"
	124	[144]	CALL     	11 3 0
	125	[144]	CALL     	10 0 1
	126	[145]	GETUPVAL 	10 2	; util
	127	[145]	GETTABLE 	10 10 -26	; "printout"
	128	[145]	LOADK    	11 -29	; "and type 'luarocks make' to build."
	129	[145]	CALL     	10 2 1
	130	[147]	GETUPVAL 	10 2	; util
	131	[147]	GETTABLE 	10 10 -30	; "remove_scheduled_function"
	132	[147]	MOVE     	11 7
	133	[147]	CALL     	10 2 1
	134	[148]	LOADBOOL 	10 1 0
	135	[148]	RETURN   	10 2
	136	[149]	RETURN   	0 1

function <./cmd/unpack.lua:154,166> (34 instructions, 136 bytes at 0x7fec3bc07050)
1 param, 8 slots, 2 upvalues, 3 locals, 9 constants, 0 functions
	1	[156]	GETTABLE 	3 0 -1	; "rock"
	2	[156]	SELF     	3 3 -2	; "match"
	3	[156]	LOADK    	5 -3	; ".*%.rock"
	4	[156]	CALL     	3 3 2
	5	[156]	TEST     	3 0 1
	6	[156]	JMP      	6	; to 13
	7	[156]	GETTABLE 	3 0 -1	; "rock"
	8	[156]	SELF     	3 3 -2	; "match"
	9	[156]	LOADK    	5 -4	; ".*%.rockspec"
	10	[156]	CALL     	3 3 2
	11	[156]	TEST     	3 0 0
	12	[156]	JMP      	2	; to 15
	13	[157]	GETTABLE 	1 0 -1	; "rock"
	14	[157]	JMP      	14	; to 29
	15	[159]	GETUPVAL 	3 0	; search
	16	[159]	GETTABLE 	3 3 -5	; "find_src_or_rockspec"
	17	[159]	GETTABLE 	4 0 -1	; "rock"
	18	[159]	GETTABLE 	5 0 -6	; "namespace"
	19	[159]	GETTABLE 	6 0 -7	; "version"
	20	[159]	GETTABLE 	7 0 -8	; "check_lua_versions"
	21	[159]	CALL     	3 5 3
	22	[159]	MOVE     	2 4
	23	[159]	MOVE     	1 3
	24	[160]	TEST     	1 0 1
	25	[160]	JMP      	3	; to 29
	26	[161]	LOADNIL  	3 3
	27	[161]	MOVE     	4 2
	28	[161]	RETURN   	3 3
	29	[165]	GETUPVAL 	3 1	; run_unpacker
	30	[165]	MOVE     	4 1
	31	[165]	GETTABLE 	5 0 -9	; "force"
	32	[165]	TAILCALL 	3 3 0
	33	[165]	RETURN   	3 0
	34	[166]	RETURN   	0 1
