
main <./core/vers.lua:0,0> (46 instructions, 184 bytes at 0x7fb345c068a0)
0+ params, 9 slots, 0 upvalues, 7 locals, 26 constants, 8 functions
	1	[2]	NEWTABLE 	0 0 0
	2	[4]	GETGLOBAL	1 -1	; require
	3	[4]	LOADK    	2 -2	; "luarocks.core.util"
	4	[4]	CALL     	1 2 2
	5	[5]	LOADNIL  	2 2
	6	[8]	NEWTABLE 	3 0 7
	7	[9]	SETTABLE 	3 -3 -4	; "dev" 120000000
	8	[10]	SETTABLE 	3 -5 -6	; "scm" 110000000
	9	[11]	SETTABLE 	3 -7 -8	; "cvs" 100000000
	10	[12]	SETTABLE 	3 -9 -10	; "rc" -1000
	11	[13]	SETTABLE 	3 -11 -12	; "pre" -10000
	12	[14]	SETTABLE 	3 -13 -14	; "beta" -100000
	13	[15]	SETTABLE 	3 -15 -16	; "alpha" -1000000
	14	[18]	NEWTABLE 	4 0 4
	15	[39]	CLOSURE  	5 0	; 0x7fb345c06b90
	16	[39]	SETTABLE 	4 -17 5	; "__eq" -
	17	[58]	CLOSURE  	5 1	; 0x7fb345c07510
	18	[58]	SETTABLE 	4 -18 5	; "__lt" -
	19	[64]	CLOSURE  	5 2	; 0x7fb345c06e00
	20	[64]	SETTABLE 	4 -19 5	; "__le" -
	21	[70]	CLOSURE  	5 3	; 0x7fb345c079d0
	22	[70]	SETTABLE 	4 -20 5	; "__tostring" -
	23	[73]	NEWTABLE 	5 0 0
	24	[74]	GETGLOBAL	6 -21	; setmetatable
	25	[74]	MOVE     	7 5
	26	[74]	NEWTABLE 	8 0 1
	27	[75]	SETTABLE 	8 -22 -23	; "__mode" "kv"
	28	[74]	CALL     	6 3 1
	29	[135]	CLOSURE  	6 4	; 0x7fb345c07db0
	30	[135]	MOVE     	0 5
	31	[135]	MOVE     	0 1
	32	[135]	MOVE     	0 3
	33	[135]	MOVE     	0 4
	34	[89]	SETTABLE 	0 -24 6	; "parse_version" -
	35	[146]	CLOSURE  	6 5	; 0x7fb345c06ae0
	36	[146]	MOVE     	0 0
	37	[141]	SETTABLE 	0 -25 6	; "compare_versions" -
	38	[176]	CLOSURE  	6 6	; 0x7fb345c08370
	39	[176]	MOVE     	0 0
	40	[205]	CLOSURE  	7 7	; 0x7fb345c09300
	41	[205]	MOVE     	0 4
	42	[205]	MOVE     	0 0
	43	[205]	MOVE     	0 6
	44	[183]	SETTABLE 	0 -26 7	; "match_constraints" -
	45	[207]	RETURN   	0 2
	46	[207]	RETURN   	0 1

function <./core/vers.lua:26,39> (33 instructions, 132 bytes at 0x7fb345c06b90)
2 params, 8 slots, 0 upvalues, 6 locals, 2 constants, 0 functions
	1	[27]	LEN      	2 0
	2	[27]	LEN      	3 1
	3	[27]	EQ       	1 2 3
	4	[27]	JMP      	2	; to 7
	5	[28]	LOADBOOL 	2 0 0
	6	[28]	RETURN   	2 2
	7	[30]	LOADK    	2 -1	; 1
	8	[30]	LEN      	3 0
	9	[30]	LOADK    	4 -1	; 1
	10	[30]	FORPREP  	2 6	; to 17
	11	[31]	GETTABLE 	6 0 5
	12	[31]	GETTABLE 	7 1 5
	13	[31]	EQ       	1 6 7
	14	[31]	JMP      	2	; to 17
	15	[32]	LOADBOOL 	6 0 0
	16	[32]	RETURN   	6 2
	17	[30]	FORLOOP  	2 -7	; to 11
	18	[35]	GETTABLE 	2 0 -2	; "revision"
	19	[35]	TEST     	2 0 0
	20	[35]	JMP      	10	; to 31
	21	[35]	GETTABLE 	2 1 -2	; "revision"
	22	[35]	TEST     	2 0 0
	23	[35]	JMP      	7	; to 31
	24	[36]	GETTABLE 	2 0 -2	; "revision"
	25	[36]	GETTABLE 	3 1 -2	; "revision"
	26	[36]	EQ       	1 2 3
	27	[36]	JMP      	1	; to 29
	28	[36]	LOADBOOL 	2 0 1
	29	[36]	LOADBOOL 	2 1 0
	30	[36]	RETURN   	2 2
	31	[38]	LOADBOOL 	2 1 0
	32	[38]	RETURN   	2 2
	33	[39]	RETURN   	0 1

function <./core/vers.lua:47,58> (40 instructions, 160 bytes at 0x7fb345c07510)
2 params, 9 slots, 0 upvalues, 8 locals, 5 constants, 0 functions
	1	[48]	LOADK    	2 -1	; 1
	2	[48]	GETGLOBAL	3 -2	; math
	3	[48]	GETTABLE 	3 3 -3	; "max"
	4	[48]	LEN      	4 0
	5	[48]	LEN      	5 1
	6	[48]	CALL     	3 3 2
	7	[48]	LOADK    	4 -1	; 1
	8	[48]	FORPREP  	2 15	; to 24
	9	[49]	GETTABLE 	6 0 5
	10	[49]	TEST     	6 0 1
	11	[49]	JMP      	1	; to 13
	12	[49]	LOADK    	6 -4	; 0
	13	[49]	GETTABLE 	7 1 5
	14	[49]	TEST     	7 0 1
	15	[49]	JMP      	1	; to 17
	16	[49]	LOADK    	7 -4	; 0
	17	[50]	EQ       	1 6 7
	18	[50]	JMP      	5	; to 24
	19	[51]	LT       	1 6 7
	20	[51]	JMP      	1	; to 22
	21	[51]	LOADBOOL 	8 0 1
	22	[51]	LOADBOOL 	8 1 0
	23	[51]	RETURN   	8 2
	24	[48]	FORLOOP  	2 -16	; to 9
	25	[54]	GETTABLE 	2 0 -5	; "revision"
	26	[54]	TEST     	2 0 0
	27	[54]	JMP      	10	; to 38
	28	[54]	GETTABLE 	2 1 -5	; "revision"
	29	[54]	TEST     	2 0 0
	30	[54]	JMP      	7	; to 38
	31	[55]	GETTABLE 	2 0 -5	; "revision"
	32	[55]	GETTABLE 	3 1 -5	; "revision"
	33	[55]	LT       	1 2 3
	34	[55]	JMP      	1	; to 36
	35	[55]	LOADBOOL 	2 0 1
	36	[55]	LOADBOOL 	2 1 0
	37	[55]	RETURN   	2 2
	38	[57]	LOADBOOL 	2 0 0
	39	[57]	RETURN   	2 2
	40	[58]	RETURN   	0 1

function <./core/vers.lua:62,64> (6 instructions, 24 bytes at 0x7fb345c06e00)
2 params, 3 slots, 0 upvalues, 2 locals, 0 constants, 0 functions
	1	[63]	LT       	0 1 0
	2	[63]	JMP      	1	; to 4
	3	[63]	LOADBOOL 	2 0 1
	4	[63]	LOADBOOL 	2 1 0
	5	[63]	RETURN   	2 2
	6	[64]	RETURN   	0 1

function <./core/vers.lua:68,70> (3 instructions, 12 bytes at 0x7fb345c079d0)
1 param, 2 slots, 0 upvalues, 1 local, 1 constant, 0 functions
	1	[69]	GETTABLE 	1 0 -1	; "string"
	2	[69]	RETURN   	1 2
	3	[70]	RETURN   	0 1

function <./core/vers.lua:89,135> (85 instructions, 340 bytes at 0x7fb345c07db0)
1 param, 14 slots, 4 upvalues, 10 locals, 18 constants, 1 function
	1	[90]	TEST     	0 0 1
	2	[90]	JMP      	2	; to 5
	3	[90]	LOADNIL  	1 1
	4	[90]	RETURN   	1 2
	5	[91]	GETGLOBAL	1 -1	; assert
	6	[91]	GETGLOBAL	2 -2	; type
	7	[91]	MOVE     	3 0
	8	[91]	CALL     	2 2 2
	9	[91]	EQ       	1 2 -3	; - "string"
	10	[91]	JMP      	1	; to 12
	11	[91]	LOADBOOL 	2 0 1
	12	[91]	LOADBOOL 	2 1 0
	13	[91]	CALL     	1 2 1
	14	[93]	GETUPVAL 	1 0	; version_cache
	15	[93]	GETTABLE 	1 1 0
	16	[94]	TEST     	1 0 0
	17	[94]	JMP      	1	; to 19
	18	[95]	RETURN   	1 2
	19	[98]	NEWTABLE 	2 0 0
	20	[99]	LOADK    	3 -4	; 1
	21	[104]	CLOSURE  	4 0	; 0x7fb345c08180
	22	[104]	MOVE     	0 2
	23	[104]	MOVE     	0 3
	24	[107]	SELF     	5 0 -5	; "match"
	25	[107]	LOADK    	7 -6	; "^%s*(.*)%s*$"
	26	[107]	CALL     	5 3 2
	27	[108]	SETTABLE 	2 -3 5	; "string" -
	28	[110]	SELF     	6 5 -5	; "match"
	29	[110]	LOADK    	8 -7	; "(.*)%-(%d+)$"
	30	[110]	CALL     	6 3 3
	31	[111]	TEST     	7 0 0
	32	[111]	JMP      	5	; to 38
	33	[112]	MOVE     	5 6
	34	[113]	GETGLOBAL	8 -9	; tonumber
	35	[113]	MOVE     	9 7
	36	[113]	CALL     	8 2 2
	37	[113]	SETTABLE 	2 -8 8	; "revision" -
	38	[115]	LEN      	8 5
	39	[115]	LT       	0 -10 8	; 0 -
	40	[115]	JMP      	37	; to 78
	41	[117]	SELF     	8 5 -5	; "match"
	42	[117]	LOADK    	10 -11	; "^(%d+)[%.%-%_]*(.*)"
	43	[117]	CALL     	8 3 3
	44	[118]	TEST     	8 0 0
	45	[118]	JMP      	6	; to 52
	46	[119]	MOVE     	10 4
	47	[119]	GETGLOBAL	11 -9	; tonumber
	48	[119]	MOVE     	12 8
	49	[119]	CALL     	11 2 0
	50	[119]	CALL     	10 0 1
	51	[119]	JMP      	24	; to 76
	52	[122]	SELF     	10 5 -5	; "match"
	53	[122]	LOADK    	12 -12	; "^(%a+)[%.%-%_]*(.*)"
	54	[122]	CALL     	10 3 3
	55	[122]	MOVE     	9 11
	56	[122]	MOVE     	8 10
	57	[123]	TEST     	8 0 1
	58	[123]	JMP      	9	; to 68
	59	[124]	GETUPVAL 	10 1	; util
	60	[124]	GETTABLE 	10 10 -13	; "warning"
	61	[124]	LOADK    	11 -14	; "version number '"
	62	[124]	MOVE     	12 5
	63	[124]	LOADK    	13 -15	; "' could not be parsed."
	64	[124]	CONCAT   	11 11 13
	65	[124]	CALL     	10 2 1
	66	[125]	SETTABLE 	2 3 -10	; - 0
	67	[126]	JMP      	10	; to 78
	68	[128]	GETUPVAL 	10 2	; deltas
	69	[128]	GETTABLE 	10 10 8
	70	[128]	TEST     	10 0 1
	71	[128]	JMP      	3	; to 75
	72	[128]	SELF     	10 8 -16	; "byte"
	73	[128]	CALL     	10 2 2
	74	[128]	DIV      	10 10 -17	; - 1000
	75	[128]	SETTABLE 	2 3 10
	76	[130]	MOVE     	5 9
	77	[130]	JMP      	-40	; to 38
	78	[132]	GETGLOBAL	8 -18	; setmetatable
	79	[132]	MOVE     	9 2
	80	[132]	GETUPVAL 	10 3	; version_mt
	81	[132]	CALL     	8 3 1
	82	[133]	GETUPVAL 	8 0	; version_cache
	83	[133]	SETTABLE 	8 0 2
	84	[134]	RETURN   	2 2
	85	[135]	RETURN   	0 1

function <./core/vers.lua:101,104> (20 instructions, 80 bytes at 0x7fb345c08180)
1 param, 5 slots, 2 upvalues, 1 local, 2 constants, 0 functions
	1	[102]	GETUPVAL 	1 0	; version
	2	[102]	GETUPVAL 	2 1	; i
	3	[102]	GETUPVAL 	3 0	; version
	4	[102]	GETUPVAL 	4 1	; i
	5	[102]	GETTABLE 	3 3 4
	6	[102]	TEST     	3 0 0
	7	[102]	JMP      	7	; to 15
	8	[102]	GETUPVAL 	3 0	; version
	9	[102]	GETUPVAL 	4 1	; i
	10	[102]	GETTABLE 	3 3 4
	11	[102]	DIV      	4 0 -1	; - 100000
	12	[102]	ADD      	3 3 4
	13	[102]	TEST     	3 0 1
	14	[102]	JMP      	1	; to 16
	15	[102]	MOVE     	3 0
	16	[102]	SETTABLE 	1 2 3
	17	[103]	GETUPVAL 	1 1	; i
	18	[103]	ADD      	1 1 -2	; - 1
	19	[103]	SETUPVAL 	1 1	; i
	20	[104]	RETURN   	0 1

function <./core/vers.lua:141,146> (18 instructions, 72 bytes at 0x7fb345c06ae0)
2 params, 5 slots, 1 upvalue, 2 locals, 1 constant, 0 functions
	1	[142]	EQ       	0 0 1
	2	[142]	JMP      	2	; to 5
	3	[143]	LOADBOOL 	2 0 0
	4	[143]	RETURN   	2 2
	5	[145]	GETUPVAL 	2 0	; vers
	6	[145]	GETTABLE 	2 2 -1	; "parse_version"
	7	[145]	MOVE     	3 0
	8	[145]	CALL     	2 2 2
	9	[145]	GETUPVAL 	3 0	; vers
	10	[145]	GETTABLE 	3 3 -1	; "parse_version"
	11	[145]	MOVE     	4 1
	12	[145]	CALL     	3 2 2
	13	[145]	LT       	1 3 2
	14	[145]	JMP      	1	; to 16
	15	[145]	LOADBOOL 	2 0 1
	16	[145]	LOADBOOL 	2 1 0
	17	[145]	RETURN   	2 2
	18	[146]	RETURN   	0 1

function <./core/vers.lua:160,176> (81 instructions, 324 bytes at 0x7fb345c08370)
2 params, 9 slots, 1 upvalue, 8 locals, 8 constants, 0 functions
	1	[161]	GETGLOBAL	2 -1	; assert
	2	[161]	GETGLOBAL	3 -2	; type
	3	[161]	MOVE     	4 0
	4	[161]	CALL     	3 2 2
	5	[161]	EQ       	1 3 -3	; - "string"
	6	[161]	JMP      	6	; to 13
	7	[161]	GETGLOBAL	3 -2	; type
	8	[161]	MOVE     	4 0
	9	[161]	CALL     	3 2 2
	10	[161]	EQ       	1 3 -4	; - "table"
	11	[161]	JMP      	1	; to 13
	12	[161]	LOADBOOL 	3 0 1
	13	[161]	LOADBOOL 	3 1 0
	14	[161]	CALL     	2 2 1
	15	[162]	GETGLOBAL	2 -1	; assert
	16	[162]	GETGLOBAL	3 -2	; type
	17	[162]	MOVE     	4 1
	18	[162]	CALL     	3 2 2
	19	[162]	EQ       	1 3 -3	; - "string"
	20	[162]	JMP      	6	; to 27
	21	[162]	GETGLOBAL	3 -2	; type
	22	[162]	MOVE     	4 0
	23	[162]	CALL     	3 2 2
	24	[162]	EQ       	1 3 -4	; - "table"
	25	[162]	JMP      	1	; to 27
	26	[162]	LOADBOOL 	3 0 1
	27	[162]	LOADBOOL 	3 1 0
	28	[162]	CALL     	2 2 1
	29	[164]	GETGLOBAL	2 -2	; type
	30	[164]	MOVE     	3 0
	31	[164]	CALL     	2 2 2
	32	[164]	EQ       	1 2 -4	; - "table"
	33	[164]	JMP      	5	; to 39
	34	[164]	GETUPVAL 	2 0	; vers
	35	[164]	GETTABLE 	2 2 -5	; "parse_version"
	36	[164]	MOVE     	3 0
	37	[164]	CALL     	2 2 2
	38	[164]	MOVE     	0 2
	39	[165]	GETGLOBAL	2 -2	; type
	40	[165]	MOVE     	3 1
	41	[165]	CALL     	2 2 2
	42	[165]	EQ       	1 2 -4	; - "table"
	43	[165]	JMP      	5	; to 49
	44	[165]	GETUPVAL 	2 0	; vers
	45	[165]	GETTABLE 	2 2 -5	; "parse_version"
	46	[165]	MOVE     	3 1
	47	[165]	CALL     	2 2 2
	48	[165]	MOVE     	1 2
	49	[166]	TEST     	0 0 0
	50	[166]	JMP      	2	; to 53
	51	[166]	TEST     	1 0 1
	52	[166]	JMP      	2	; to 55
	53	[166]	LOADBOOL 	2 0 0
	54	[166]	RETURN   	2 2
	55	[168]	GETGLOBAL	2 -6	; ipairs
	56	[168]	MOVE     	3 1
	57	[168]	CALL     	2 2 4
	58	[168]	JMP      	8	; to 67
	59	[169]	GETTABLE 	7 0 5
	60	[169]	TEST     	7 0 1
	61	[169]	JMP      	1	; to 63
	62	[169]	LOADK    	7 -7	; 0
	63	[170]	EQ       	1 6 7
	64	[170]	JMP      	2	; to 67
	65	[170]	LOADBOOL 	8 0 0
	66	[170]	RETURN   	8 2
	67	[168]	TFORLOOP 	2 2
	68	[170]	JMP      	-10	; to 59
	69	[172]	GETTABLE 	2 1 -8	; "revision"
	70	[172]	TEST     	2 0 0
	71	[172]	JMP      	7	; to 79
	72	[173]	GETTABLE 	2 1 -8	; "revision"
	73	[173]	GETTABLE 	3 0 -8	; "revision"
	74	[173]	EQ       	1 2 3
	75	[173]	JMP      	1	; to 77
	76	[173]	LOADBOOL 	2 0 1
	77	[173]	LOADBOOL 	2 1 0
	78	[173]	RETURN   	2 2
	79	[175]	LOADBOOL 	2 1 0
	80	[175]	RETURN   	2 2
	81	[176]	RETURN   	0 1

function <./core/vers.lua:183,205> (99 instructions, 396 bytes at 0x7fb345c09300)
2 params, 13 slots, 3 upvalues, 10 locals, 16 constants, 0 functions
	1	[184]	GETGLOBAL	2 -1	; assert
	2	[184]	GETGLOBAL	3 -2	; type
	3	[184]	MOVE     	4 0
	4	[184]	CALL     	3 2 2
	5	[184]	EQ       	1 3 -3	; - "table"
	6	[184]	JMP      	1	; to 8
	7	[184]	LOADBOOL 	3 0 1
	8	[184]	LOADBOOL 	3 1 0
	9	[184]	CALL     	2 2 1
	10	[185]	GETGLOBAL	2 -1	; assert
	11	[185]	GETGLOBAL	3 -2	; type
	12	[185]	MOVE     	4 1
	13	[185]	CALL     	3 2 2
	14	[185]	EQ       	1 3 -3	; - "table"
	15	[185]	JMP      	1	; to 17
	16	[185]	LOADBOOL 	3 0 1
	17	[185]	LOADBOOL 	3 1 0
	18	[185]	CALL     	2 2 1
	19	[186]	LOADBOOL 	2 1 0
	20	[187]	GETGLOBAL	3 -4	; setmetatable
	21	[187]	MOVE     	4 0
	22	[187]	GETUPVAL 	5 0	; version_mt
	23	[187]	CALL     	3 3 1
	24	[188]	GETGLOBAL	3 -5	; pairs
	25	[188]	MOVE     	4 1
	26	[188]	CALL     	3 2 4
	27	[188]	JMP      	68	; to 96
	28	[189]	GETGLOBAL	8 -2	; type
	29	[189]	GETTABLE 	9 7 -6	; "version"
	30	[189]	CALL     	8 2 2
	31	[189]	EQ       	0 8 -7	; - "string"
	32	[189]	JMP      	5	; to 38
	33	[190]	GETUPVAL 	8 1	; vers
	34	[190]	GETTABLE 	8 8 -8	; "parse_version"
	35	[190]	GETTABLE 	9 7 -6	; "version"
	36	[190]	CALL     	8 2 2
	37	[190]	SETTABLE 	7 -6 8	; "version" -
	38	[192]	GETTABLE 	8 7 -6	; "version"
	39	[192]	GETTABLE 	9 7 -9	; "op"
	40	[193]	GETGLOBAL	10 -4	; setmetatable
	41	[193]	MOVE     	11 8
	42	[193]	GETUPVAL 	12 0	; version_mt
	43	[193]	CALL     	10 3 1
	44	[194]	EQ       	0 9 -10	; - "=="
	45	[194]	JMP      	5	; to 51
	46	[194]	EQ       	1 0 8
	47	[194]	JMP      	1	; to 49
	48	[194]	LOADBOOL 	2 0 1
	49	[194]	LOADBOOL 	2 1 0
	50	[194]	JMP      	42	; to 93
	51	[195]	EQ       	0 9 -11	; - "~="
	52	[195]	JMP      	5	; to 58
	53	[195]	EQ       	0 0 8
	54	[195]	JMP      	1	; to 56
	55	[195]	LOADBOOL 	2 0 1
	56	[195]	LOADBOOL 	2 1 0
	57	[195]	JMP      	35	; to 93
	58	[196]	EQ       	0 9 -12	; - ">"
	59	[196]	JMP      	5	; to 65
	60	[196]	LT       	1 8 0
	61	[196]	JMP      	1	; to 63
	62	[196]	LOADBOOL 	2 0 1
	63	[196]	LOADBOOL 	2 1 0
	64	[196]	JMP      	28	; to 93
	65	[197]	EQ       	0 9 -13	; - "<"
	66	[197]	JMP      	5	; to 72
	67	[197]	LT       	1 0 8
	68	[197]	JMP      	1	; to 70
	69	[197]	LOADBOOL 	2 0 1
	70	[197]	LOADBOOL 	2 1 0
	71	[197]	JMP      	21	; to 93
	72	[198]	EQ       	0 9 -14	; - ">="
	73	[198]	JMP      	5	; to 79
	74	[198]	LE       	1 8 0
	75	[198]	JMP      	1	; to 77
	76	[198]	LOADBOOL 	2 0 1
	77	[198]	LOADBOOL 	2 1 0
	78	[198]	JMP      	14	; to 93
	79	[199]	EQ       	0 9 -15	; - "<="
	80	[199]	JMP      	5	; to 86
	81	[199]	LE       	1 0 8
	82	[199]	JMP      	1	; to 84
	83	[199]	LOADBOOL 	2 0 1
	84	[199]	LOADBOOL 	2 1 0
	85	[199]	JMP      	7	; to 93
	86	[200]	EQ       	0 9 -16	; - "~>"
	87	[200]	JMP      	5	; to 93
	88	[200]	GETUPVAL 	10 2	; partial_match
	89	[200]	MOVE     	11 0
	90	[200]	MOVE     	12 8
	91	[200]	CALL     	10 3 2
	92	[200]	MOVE     	2 10
	93	[202]	TEST     	2 0 1
	94	[202]	JMP      	1	; to 96
	95	[202]	JMP      	2	; to 98
	96	[188]	TFORLOOP 	3 2
	97	[202]	JMP      	-70	; to 28
	98	[204]	RETURN   	2 2
	99	[205]	RETURN   	0 1
