-- BYTECODE -- which.lua:11-19
0001    MOV      2   0
0002    TGETS    1   0   0  ; "command"
0003    KSTR     3   1      ; "which"
0004    KSTR     4   2      ; "Given a module name like "foo.bar", "
0005    KSTR     5   3      ; "output which file would be loaded to res"~
0006    KSTR     6   4      ; "luarocks.loader, like "/usr/local/lua/"
0007    UGET     7   0      ; cfg
0008    TGETS    7   7   5  ; "lua_version"
0009    KSTR     8   6      ; "/foo/bar.lua"."
0010    CAT      4   4   8
0011    UGET     5   1      ; util
0012    TGETS    5   5   7  ; "see_also"
0013    CALL     5   0   1
0014    CALLM    1   2   3
0015    MOV      2   1
0016    TGETS    1   1   8  ; "summary"
0017    KSTR     3   9      ; "Tell which file corresponds to a given m"~
0018    CALL     1   2   3
0019    MOV      3   1
0020    TGETS    2   1  10  ; "argument"
0021    KSTR     4  11      ; "modname"
0022    KSTR     5  12      ; "Module name."
0023    CALL     2   1   4
0024    RET0     0   1

-- BYTECODE -- which.lua:23-45
0001    UGET     1   0      ; loader
0002    TGETS    1   1   0  ; "which"
0003    TGETS    2   0   1  ; "modname"
0004    CALL     1   4   2
0005    ISF          1
0006    JMP      4 => 0026
0007    UGET     4   1      ; util
0008    TGETS    4   4   2  ; "printout"
0009    MOV      5   1
0010    CALL     4   1   2
0011    UGET     4   1      ; util
0012    TGETS    4   4   2  ; "printout"
0013    KSTR     5   3      ; "(provided by "
0014    GGET     6   4      ; "tostring"
0015    MOV      7   2
0016    CALL     6   2   2
0017    KSTR     7   5      ; " "
0018    GGET     8   4      ; "tostring"
0019    MOV      9   3
0020    CALL     8   2   2
0021    KSTR     9   6      ; ")"
0022    CAT      5   5   9
0023    CALL     4   1   2
0024    KPRI     4   2
0025    RET1     4   2
0026 => TGETS    4   0   1  ; "modname"
0027    MOV      5   4
0028    TGETS    4   4   7  ; "gsub"
0029    KSTR     6   8      ; "%."
0030    KSTR     7   9      ; "/"
0031    CALL     4   2   4
0032    GGET     5  10      ; "ipairs"
0033    TDUP     6  11
0034    CALL     5   4   2
0035    JMP      8 => 0069
0036 => GGET    10  12      ; "package"
0037    TGETV   10  10   9
0038    MOV     11  10
0039    TGETS   10  10  13  ; "gmatch"
0040    KSTR    12  14      ; "([^;]+)"
0041    CALL    10   4   3
0042    JMP     13 => 0067
0043 => MOV     15  13
0044    TGETS   14  13   7  ; "gsub"
0045    KSTR    16  15      ; "%?"
0046    MOV     17   4
0047    CALL    14   2   4
0048    UGET    15   2      ; fs
0049    TGETS   15  15  16  ; "exists"
0050    MOV     16  14
0051    CALL    15   2   2
0052    ISF         15
0053    JMP     16 => 0067
0054    UGET    15   1      ; util
0055    TGETS   15  15   2  ; "printout"
0056    MOV     16  14
0057    CALL    15   1   2
0058    UGET    15   1      ; util
0059    TGETS   15  15   2  ; "printout"
0060    KSTR    16  17      ; "(found directly via package."
0061    MOV     17   9
0062    KSTR    18  18      ; " -- not installed as a rock?)"
0063    CAT     16  16  18
0064    CALL    15   1   2
0065    KPRI    15   2
0066    RET1    15   2
0067 => ITERC   13   2   3
0068    ITERL   13 => 0043
0069 => ITERC    8   3   3
0070    ITERL    8 => 0036
0071    KPRI     5   0
0072    KSTR     6  19      ; "Module '"
0073    TGETS    7   0   1  ; "modname"
0074    KSTR     8  20      ; "' not found."
0075    CAT      6   6   8
0076    RET      5   3

-- BYTECODE -- which.lua:0-49
0001    TNEW     0   0
0002    GGET     1   0      ; "require"
0003    KSTR     2   1      ; "luarocks.loader"
0004    CALL     1   2   2
0005    GGET     2   0      ; "require"
0006    KSTR     3   2      ; "luarocks.core.cfg"
0007    CALL     2   2   2
0008    GGET     3   0      ; "require"
0009    KSTR     4   3      ; "luarocks.util"
0010    CALL     3   2   2
0011    GGET     4   0      ; "require"
0012    KSTR     5   4      ; "luarocks.fs"
0013    CALL     4   2   2
0014    FNEW     5   6      ; which.lua:11
0015    TSETS    5   0   5  ; "add_to_parser"
0016    FNEW     5   8      ; which.lua:23
0017    TSETS    5   0   7  ; "command"
0018    UCLO     0 => 0019
0019 => RET1     0   2

