
main <./cmd/which.lua:0,0> (24 instructions, 96 bytes at 0x7fe559e056c0)
0+ params, 6 slots, 0 upvalues, 5 locals, 7 constants, 2 functions
	1	[4]	NEWTABLE 	0 0 0
	2	[6]	GETGLOBAL	1 -1	; require
	3	[6]	LOADK    	2 -2	; "luarocks.loader"
	4	[6]	CALL     	1 2 2
	5	[7]	GETGLOBAL	2 -1	; require
	6	[7]	LOADK    	3 -3	; "luarocks.core.cfg"
	7	[7]	CALL     	2 2 2
	8	[8]	GETGLOBAL	3 -1	; require
	9	[8]	LOADK    	4 -4	; "luarocks.util"
	10	[8]	CALL     	3 2 2
	11	[9]	GETGLOBAL	4 -1	; require
	12	[9]	LOADK    	5 -5	; "luarocks.fs"
	13	[9]	CALL     	4 2 2
	14	[19]	CLOSURE  	5 0	; 0x7fe559e05e00
	15	[19]	MOVE     	0 2
	16	[19]	MOVE     	0 3
	17	[11]	SETTABLE 	0 -6 5	; "add_to_parser" -
	18	[45]	CLOSURE  	5 1	; 0x7fe559e06290
	19	[45]	MOVE     	0 1
	20	[45]	MOVE     	0 3
	21	[45]	MOVE     	0 4
	22	[23]	SETTABLE 	0 -7 5	; "command" -
	23	[47]	RETURN   	0 2
	24	[47]	RETURN   	0 1

function <./cmd/which.lua:11,19> (21 instructions, 84 bytes at 0x7fe559e05e00)
1 param, 9 slots, 2 upvalues, 2 locals, 13 constants, 0 functions
	1	[12]	SELF     	1 0 -1	; "command"
	2	[12]	LOADK    	3 -2	; "which"
	3	[12]	LOADK    	4 -3	; "Given a module name like \"foo.bar\", "
	4	[13]	LOADK    	5 -4	; "output which file would be loaded to resolve that module by "
	5	[14]	LOADK    	6 -5	; "luarocks.loader, like \"/usr/local/lua/"
	6	[14]	GETUPVAL 	7 0	; cfg
	7	[14]	GETTABLE 	7 7 -6	; "lua_version"
	8	[14]	LOADK    	8 -7	; "/foo/bar.lua\"."
	9	[14]	CONCAT   	4 4 8
	10	[15]	GETUPVAL 	5 1	; util
	11	[15]	GETTABLE 	5 5 -8	; "see_also"
	12	[15]	CALL     	5 1 0
	13	[12]	CALL     	1 0 2
	14	[16]	SELF     	1 1 -9	; "summary"
	15	[16]	LOADK    	3 -10	; "Tell which file corresponds to a given module name."
	16	[16]	CALL     	1 3 2
	17	[18]	SELF     	2 1 -11	; "argument"
	18	[18]	LOADK    	4 -12	; "modname"
	19	[18]	LOADK    	5 -13	; "Module name."
	20	[18]	CALL     	2 4 1
	21	[19]	RETURN   	0 1

function <./cmd/which.lua:23,45> (77 instructions, 308 bytes at 0x7fe559e06290)
1 param, 19 slots, 3 upvalues, 15 locals, 22 constants, 0 functions
	1	[24]	GETUPVAL 	1 0	; loader
	2	[24]	GETTABLE 	1 1 -1	; "which"
	3	[24]	GETTABLE 	2 0 -2	; "modname"
	4	[24]	CALL     	1 2 4
	5	[26]	TEST     	1 0 0
	6	[26]	JMP      	19	; to 26
	7	[27]	GETUPVAL 	4 1	; util
	8	[27]	GETTABLE 	4 4 -3	; "printout"
	9	[27]	MOVE     	5 1
	10	[27]	CALL     	4 2 1
	11	[28]	GETUPVAL 	4 1	; util
	12	[28]	GETTABLE 	4 4 -3	; "printout"
	13	[28]	LOADK    	5 -4	; "(provided by "
	14	[28]	GETGLOBAL	6 -5	; tostring
	15	[28]	MOVE     	7 2
	16	[28]	CALL     	6 2 2
	17	[28]	LOADK    	7 -6	; " "
	18	[28]	GETGLOBAL	8 -5	; tostring
	19	[28]	MOVE     	9 3
	20	[28]	CALL     	8 2 2
	21	[28]	LOADK    	9 -7	; ")"
	22	[28]	CONCAT   	5 5 9
	23	[28]	CALL     	4 2 1
	24	[29]	LOADBOOL 	4 1 0
	25	[29]	RETURN   	4 2
	26	[32]	GETTABLE 	4 0 -2	; "modname"
	27	[32]	SELF     	4 4 -8	; "gsub"
	28	[32]	LOADK    	6 -9	; "%."
	29	[32]	LOADK    	7 -10	; "/"
	30	[32]	CALL     	4 4 2
	31	[33]	GETGLOBAL	5 -11	; ipairs
	32	[33]	NEWTABLE 	6 2 0
	33	[33]	LOADK    	7 -12	; "path"
	34	[33]	LOADK    	8 -13	; "cpath"
	35	[33]	SETLIST  	6 2 1	; 1
	36	[33]	CALL     	5 2 4
	37	[33]	JMP      	31	; to 69
	38	[34]	GETGLOBAL	10 -14	; package
	39	[34]	GETTABLE 	10 10 9
	40	[34]	SELF     	10 10 -15	; "gmatch"
	41	[34]	LOADK    	12 -16	; "([^;]+)"
	42	[34]	CALL     	10 3 4
	43	[34]	JMP      	23	; to 67
	44	[35]	SELF     	14 13 -8	; "gsub"
	45	[35]	LOADK    	16 -17	; "%?"
	46	[35]	MOVE     	17 4
	47	[35]	CALL     	14 4 2
	48	[36]	GETUPVAL 	15 2	; fs
	49	[36]	GETTABLE 	15 15 -18	; "exists"
	50	[36]	MOVE     	16 14
	51	[36]	CALL     	15 2 2
	52	[36]	TEST     	15 0 0
	53	[36]	JMP      	13	; to 67
	54	[37]	GETUPVAL 	15 1	; util
	55	[37]	GETTABLE 	15 15 -3	; "printout"
	56	[37]	MOVE     	16 14
	57	[37]	CALL     	15 2 1
	58	[38]	GETUPVAL 	15 1	; util
	59	[38]	GETTABLE 	15 15 -3	; "printout"
	60	[38]	LOADK    	16 -19	; "(found directly via package."
	61	[38]	MOVE     	17 9
	62	[38]	LOADK    	18 -20	; " -- not installed as a rock?)"
	63	[38]	CONCAT   	16 16 18
	64	[38]	CALL     	15 2 1
	65	[39]	LOADBOOL 	15 1 0
	66	[39]	RETURN   	15 2
	67	[34]	TFORLOOP 	10 1
	68	[40]	JMP      	-25	; to 44
	69	[33]	TFORLOOP 	5 2
	70	[41]	JMP      	-33	; to 38
	71	[44]	LOADNIL  	5 5
	72	[44]	LOADK    	6 -21	; "Module '"
	73	[44]	GETTABLE 	7 0 -2	; "modname"
	74	[44]	LOADK    	8 -22	; "' not found."
	75	[44]	CONCAT   	6 6 8
	76	[44]	RETURN   	5 3
	77	[45]	RETURN   	0 1
