-- BYTECODE -- writer.lua:25-40
0001    GGET     4   0      ; "assert"
0002    GGET     5   1      ; "type"
0003    MOV      6   0
0004    CALL     5   2   2
0005    ISEQS    5   2      ; "table"
0006    JMP      5 => 0009
0007    KPRI     5   1
0008    JMP      6 => 0010
0009 => KPRI     5   2
0010 => CALL     4   1   2
0011    GGET     4   0      ; "assert"
0012    GGET     5   1      ; "type"
0013    MOV      6   3
0014    CALL     5   2   2
0015    ISEQS    5   2      ; "table"
0016    JMP      5 => 0019
0017    KPRI     5   1
0018    JMP      6 => 0020
0019 => KPRI     5   2
0020 => CALL     4   1   2
0021    GGET     4   0      ; "assert"
0022    GGET     5   1      ; "type"
0023    MOV      6   1
0024    CALL     5   2   2
0025    ISNES    5   3      ; "string"
0026    JMP      5 => 0033
0027    MOV      6   1
0028    TGETS    5   1   4  ; "match"
0029    KSTR     7   5      ; "/"
0030    CALL     5   2   3
0031    NOT      5   5
0032    JMP      6 => 0036
0033 => KPRI     5   1
0034    JMP      6 => 0036
0035    KPRI     5   2
0036 => CALL     4   1   2
0037    GGET     4   0      ; "assert"
0038    GGET     5   1      ; "type"
0039    MOV      6   2
0040    CALL     5   2   2
0041    ISEQS    5   3      ; "string"
0042    JMP      5 => 0045
0043    KPRI     5   1
0044    JMP      6 => 0046
0045 => KPRI     5   2
0046 => CALL     4   1   2
0047    MOV      4   1
0048    KSTR     5   5      ; "/"
0049    MOV      6   2
0050    CAT      4   4   6
0051    GGET     5   6      ; "pairs"
0052    MOV      6   3
0053    CALL     5   4   2
0054    ISNEXT   8 => 0065
0055 => TGETV   10   0   8
0056    IST         10
0057    JMP     10 => 0060
0058    TNEW    10   0
0059    TSETV   10   0   8
0060 => GGET    10   2      ; "table"
0061    TGETS   10  10   7  ; "insert"
0062    TGETV   11   0   8
0063    MOV     12   4
0064    CALL    10   1   3
0065 => ITERN    8   3   3
0066    ITERL    8 => 0055
0067    RET0     0   1

-- BYTECODE -- writer.lua:49-71
0001    GGET     4   0      ; "assert"
0002    GGET     5   1      ; "type"
0003    MOV      6   0
0004    CALL     5   2   2
0005    ISEQS    5   2      ; "table"
0006    JMP      5 => 0009
0007    KPRI     5   1
0008    JMP      6 => 0010
0009 => KPRI     5   2
0010 => CALL     4   1   2
0011    GGET     4   0      ; "assert"
0012    GGET     5   1      ; "type"
0013    MOV      6   3
0014    CALL     5   2   2
0015    ISEQS    5   2      ; "table"
0016    JMP      5 => 0019
0017    KPRI     5   1
0018    JMP      6 => 0020
0019 => KPRI     5   2
0020 => CALL     4   1   2
0021    GGET     4   0      ; "assert"
0022    GGET     5   1      ; "type"
0023    MOV      6   1
0024    CALL     5   2   2
0025    ISNES    5   3      ; "string"
0026    JMP      5 => 0033
0027    MOV      6   1
0028    TGETS    5   1   4  ; "match"
0029    KSTR     7   5      ; "/"
0030    CALL     5   2   3
0031    NOT      5   5
0032    JMP      6 => 0036
0033 => KPRI     5   1
0034    JMP      6 => 0036
0035    KPRI     5   2
0036 => CALL     4   1   2
0037    GGET     4   0      ; "assert"
0038    GGET     5   1      ; "type"
0039    MOV      6   2
0040    CALL     5   2   2
0041    ISEQS    5   3      ; "string"
0042    JMP      5 => 0045
0043    KPRI     5   1
0044    JMP      6 => 0046
0045 => KPRI     5   2
0046 => CALL     4   1   2
0047    MOV      4   1
0048    KSTR     5   5      ; "/"
0049    MOV      6   2
0050    CAT      4   4   6
0051    GGET     5   6      ; "pairs"
0052    MOV      6   3
0053    CALL     5   4   2
0054    ISNEXT   8 => 0075
0055 => TGETV   10   0   8
0056    GGET    11   7      ; "ipairs"
0057    MOV     12  10
0058    CALL    11   4   2
0059    JMP     14 => 0068
0060 => ISNEV   15   4
0061    JMP     16 => 0068
0062    GGET    16   2      ; "table"
0063    TGETS   16  16   8  ; "remove"
0064    MOV     17  10
0065    MOV     18  14
0066    CALL    16   1   3
0067    JMP     11 => 0070
0068 => ITERC   14   3   3
0069    ITERL   14 => 0060
0070 => LEN     11  10
0071    ISNEN   11   0      ; 0
0072    JMP     11 => 0075
0073    KPRI    11   0
0074    TSETV   11   0   8
0075 => ITERN    8   3   3
0076    ITERL    8 => 0055
0077    RET0     0   1

-- BYTECODE -- writer.lua:81-96
0001    GGET     2   0      ; "assert"
0002    GGET     3   1      ; "type"
0003    MOV      4   0
0004    CALL     3   2   2
0005    ISEQS    3   2      ; "table"
0006    JMP      3 => 0009
0007    KPRI     3   1
0008    JMP      4 => 0010
0009 => KPRI     3   2
0010 => CALL     2   1   2
0011    GGET     2   0      ; "assert"
0012    GGET     3   1      ; "type"
0013    MOV      4   1
0014    CALL     3   2   2
0015    ISEQS    3   3      ; "string"
0016    JMP      3 => 0019
0017    KPRI     3   1
0018    JMP      4 => 0020
0019 => KPRI     3   2
0020 => CALL     2   1   2
0021    GGET     2   4      ; "pairs"
0022    TGETS    3   0   5  ; "repository"
0023    CALL     2   4   2
0024    ISNEXT   5 => 0053
0025 => GGET     7   4      ; "pairs"
0026    MOV      8   6
0027    CALL     7   4   2
0028    ISNEXT  10 => 0051
0029 => GGET    12   6      ; "ipairs"
0030    MOV     13  11
0031    CALL    12   4   2
0032    JMP     15 => 0049
0033 => TGETS   17  16   7  ; "arch"
0034    ISNES   17   8      ; "installed"
0035    JMP     17 => 0049
0036    TNEW    17   0
0037    TSETS   17  16   9  ; "dependencies"
0038    UGET    17   0      ; deps
0039    TGETS   17  17  10  ; "scan_deps"
0040    TGETS   18  16   9  ; "dependencies"
0041    MOV     19   0
0042    MOV     20   5
0043    MOV     21  10
0044    MOV     22   1
0045    CALL    17   1   6
0046    TGETS   17  16   9  ; "dependencies"
0047    KPRI    18   0
0048    TSETV   18  17   5
0049 => ITERC   15   3   3
0050    ITERL   15 => 0033
0051 => ITERN   10   3   3
0052    ITERL   10 => 0029
0053 => ITERN    5   3   3
0054    ITERL    5 => 0025
0055    RET0     0   1

-- BYTECODE -- writer.lua:107-115
0001    GGET     2   0      ; "assert"
0002    GGET     3   1      ; "type"
0003    MOV      4   0
0004    CALL     3   2   2
0005    ISEQS    3   2      ; "string"
0006    JMP      3 => 0009
0007    KPRI     3   1
0008    JMP      4 => 0010
0009 => KPRI     3   2
0010 => CALL     2   1   2
0011    GGET     2   0      ; "assert"
0012    GGET     3   1      ; "type"
0013    MOV      4   1
0014    CALL     3   2   2
0015    ISEQS    3   2      ; "string"
0016    JMP      3 => 0019
0017    KPRI     3   1
0018    JMP      4 => 0020
0019 => KPRI     3   2
0020 => CALL     2   1   2
0021    MOV      3   0
0022    TGETS    2   0   3  ; "match"
0023    KSTR     4   4      ; "(.*)/(.*)$"
0024    CALL     2   3   3
0025    MOV      5   1
0026    TGETS    4   1   3  ; "match"
0027    KSTR     6   4      ; "(.*)/(.*)$"
0028    CALL     4   3   3
0029    ISNEV    2   4
0030    JMP      6 => 0038
0031    UGET     6   0      ; vers
0032    TGETS    6   6   5  ; "compare_versions"
0033    MOV      7   3
0034    MOV      8   5
0035    CALL     6   2   3
0036    IST          6
0037    JMP      7 => 0043
0038 => ISLT     2   4
0039    JMP      6 => 0042
0040    KPRI     6   1
0041    JMP      7 => 0043
0042 => KPRI     6   2
0043 => RET1     6   2

-- BYTECODE -- writer.lua:120-142
0001    GGET     1   0      ; "assert"
0002    GGET     2   1      ; "type"
0003    MOV      3   0
0004    CALL     2   2   2
0005    ISEQS    2   2      ; "table"
0006    JMP      2 => 0009
0007    KPRI     2   1
0008    JMP      3 => 0010
0009 => KPRI     2   2
0010 => CALL     1   1   2
0011    GGET     1   3      ; "next"
0012    MOV      2   0
0013    CALL     1   2   2
0014    ISF          1
0015    JMP      2 => 0049
0016    GGET     1   4      ; "pairs"
0017    MOV      2   0
0018    CALL     1   4   2
0019    ISNEXT   4 => 0047
0020 => LEN      6   5
0021    KSHORT   7   1
0022    ISGE     7   6
0023    JMP      6 => 0047
0024    GGET     6   2      ; "table"
0025    TGETS    6   6   5  ; "sort"
0026    MOV      7   5
0027    UGET     8   0      ; sort_pkgs
0028    CALL     6   1   3
0029    KPRI     6   0
0030    KSHORT   7   1
0031 => TGETV    8   5   7
0032    ISF          8
0033    JMP      9 => 0047
0034    LOOP     8 => 0047
0035    TGETV    8   5   7
0036    ISNEV    8   6
0037    JMP      9 => 0044
0038    GGET     9   2      ; "table"
0039    TGETS    9   9   6  ; "remove"
0040    MOV     10   5
0041    MOV     11   7
0042    CALL     9   1   3
0043    JMP      9 => 0031
0044 => MOV      6   8
0045    ADDVN    7   7   0  ; 1
0046    JMP      8 => 0031
0047 => ITERN    4   3   3
0048    ITERL    4 => 0020
0049 => RET0     0   1

-- BYTECODE -- writer.lua:150-192
0001    GGET     4   0      ; "assert"
0002    GGET     5   1      ; "type"
0003    MOV      6   0
0004    CALL     5   2   2
0005    ISEQS    5   2      ; "table"
0006    JMP      5 => 0009
0007    KPRI     5   1
0008    JMP      6 => 0010
0009 => KPRI     5   2
0010 => CALL     4   1   2
0011    GGET     4   0      ; "assert"
0012    GGET     5   1      ; "type"
0013    MOV      6   2
0014    CALL     5   2   2
0015    ISEQS    5   3      ; "string"
0016    JMP      5 => 0019
0017    KPRI     5   1
0018    JMP      6 => 0020
0019 => KPRI     5   2
0020 => CALL     4   1   2
0021    GGET     4   0      ; "assert"
0022    ISF          3
0023    JMP      5 => 0031
0024    GGET     5   1      ; "type"
0025    MOV      6   3
0026    CALL     5   2   2
0027    ISEQS    5   2      ; "table"
0028    JMP      5 => 0031
0029    KPRI     5   1
0030    JMP      6 => 0032
0031 => KPRI     5   2
0032 => CALL     4   1   2
0033    IST          3
0034    JMP      4 => 0036
0035    TNEW     3   0
0036 => UGET     4   0      ; vers
0037    TGETS    4   4   4  ; "parse_version"
0038    MOV      5   1
0039    CALL     4   2   2
0040    MOV      1   4
0041    GGET     4   5      ; "pairs"
0042    TGETS    5   0   6  ; "repository"
0043    CALL     4   4   2
0044    ISNEXT   7 => 0138
0045 => TNEW     9   0
0046    GGET    10   5      ; "pairs"
0047    MOV     11   8
0048    CALL    10   4   2
0049    ISNEXT  13 => 0115
0050 => GGET    15   7      ; "ipairs"
0051    MOV     16  14
0052    CALL    15   4   2
0053    JMP     18 => 0113
0054 => TGETS   20  19   8  ; "arch"
0055    ISNES   20   9      ; "rockspec"
0056    JMP     20 => 0113
0057    UGET    20   1      ; dir
0058    TGETS   20  20  10  ; "path"
0059    MOV     21   2
0060    MOV     22   7
0061    KSTR    23  11      ; "-"
0062    MOV     24  13
0063    KSTR    25  12      ; ".rockspec"
0064    CAT     22  22  25
0065    CALL    20   2   3
0066    TGETV   21   3  20
0067    KPRI    22   0
0068    IST         21
0069    JMP     23 => 0077
0070    UGET    23   2      ; fetch
0071    TGETS   23  23  13  ; "load_local_rockspec"
0072    MOV     24  20
0073    KPRI    25   2
0074    CALL    23   3   3
0075    MOV     22  24
0076    MOV     21  23
0077 => ISF         21
0078    JMP     23 => 0103
0079    TSETV   21   3  20
0080    GGET    23   7      ; "ipairs"
0081    TGETS   24  21  14  ; "dependencies"
0082    CALL    23   4   2
0083    JMP     26 => 0100
0084 => TGETS   28  27  15  ; "name"
0085    ISNES   28  16      ; "lua"
0086    JMP     28 => 0100
0087    UGET    28   0      ; vers
0088    TGETS   28  28  17  ; "match_constraints"
0089    MOV     29   1
0090    TGETS   30  27  18  ; "constraints"
0091    CALL    28   2   3
0092    IST         28
0093    JMP     28 => 0113
0094    GGET    28   2      ; "table"
0095    TGETS   28  28  19  ; "insert"
0096    MOV     29   9
0097    MOV     30  13
0098    CALL    28   1   3
0099    JMP     23 => 0113
0100 => ITERC   26   3   3
0101    ITERL   26 => 0084
0102    JMP     23 => 0113
0103 => UGET    23   3      ; util
0104    TGETS   23  23  20  ; "printerr"
0105    KSTR    24  21      ; "Error loading rockspec for "
0106    MOV     25   7
0107    KSTR    26  22      ; " "
0108    MOV     27  13
0109    KSTR    28  23      ; ": "
0110    MOV     29  22
0111    CAT     24  24  29
0112    CALL    23   1   2
0113 => ITERC   18   3   3
0114    ITERL   18 => 0054
0115 => ITERN   13   3   3
0116    ITERL   13 => 0050
0117    GGET    10  24      ; "next"
0118    MOV     11   9
0119    CALL    10   2   2
0120    ISF         10
0121    JMP     11 => 0138
0122    GGET    10   7      ; "ipairs"
0123    MOV     11   9
0124    CALL    10   4   2
0125    JMP     13 => 0128
0126 => KPRI    15   0
0127    TSETV   15   8  14
0128 => ITERC   13   3   3
0129    ITERL   13 => 0126
0130    GGET    10  24      ; "next"
0131    MOV     11   8
0132    CALL    10   2   2
0133    IST         10
0134    JMP     10 => 0138
0135    TGETS   10   0   6  ; "repository"
0136    KPRI    11   0
0137    TSETV   11  10   7
0138 => ITERN    7   3   3
0139    ITERL    7 => 0045
0140    RET0     0   1

-- BYTECODE -- writer.lua:199-228
0001    GGET     2   0      ; "assert"
0002    GGET     3   1      ; "type"
0003    MOV      4   0
0004    CALL     3   2   2
0005    ISEQS    3   2      ; "table"
0006    JMP      3 => 0009
0007    KPRI     3   1
0008    JMP      4 => 0010
0009 => KPRI     3   2
0010 => CALL     2   1   2
0011    GGET     2   0      ; "assert"
0012    GGET     3   1      ; "type"
0013    MOV      4   1
0014    CALL     3   2   2
0015    ISEQS    3   2      ; "table"
0016    JMP      3 => 0019
0017    KPRI     3   1
0018    JMP      4 => 0020
0019 => KPRI     3   2
0020 => CALL     2   1   2
0021    GGET     2   3      ; "pairs"
0022    MOV      3   0
0023    CALL     2   4   2
0024    ISNEXT   5 => 0091
0025 => TGETS    7   1   4  ; "repository"
0026    TGETV    7   7   5
0027    IST          7
0028    JMP      8 => 0030
0029    TNEW     7   0
0030 => GGET     8   3      ; "pairs"
0031    MOV      9   6
0032    CALL     8   4   2
0033    ISNEXT  11 => 0087
0034 => TNEW    13   0
0035    GGET    14   5      ; "ipairs"
0036    MOV     15  12
0037    CALL    14   4   2
0038    JMP     17 => 0084
0039 => TNEW    19   0
0040    TGETS   20  18   6  ; "arch"
0041    TSETS   20  19   6  ; "arch"
0042    TGETS   20  18   6  ; "arch"
0043    ISNES   20   7      ; "installed"
0044    JMP     20 => 0079
0045    UGET    20   0      ; manif
0046    TGETS   20  20   8  ; "load_rock_manifest"
0047    MOV     21   5
0048    MOV     22  11
0049    CALL    20   3   3
0050    IST         20
0051    JMP     22 => 0055
0052    KPRI    22   0
0053    MOV     23  21
0054    RET     22   3
0055 => UGET    22   1      ; repos
0056    TGETS   22  22  10  ; "package_modules"
0057    MOV     23   5
0058    MOV     24  11
0059    CALL    22   2   3
0060    TSETS   22  19   9  ; "modules"
0061    UGET    22   2      ; store_package_items
0062    TGETS   23   1   9  ; "modules"
0063    MOV     24   5
0064    MOV     25  11
0065    TGETS   26  19   9  ; "modules"
0066    CALL    22   1   5
0067    UGET    22   1      ; repos
0068    TGETS   22  22  12  ; "package_commands"
0069    MOV     23   5
0070    MOV     24  11
0071    CALL    22   2   3
0072    TSETS   22  19  11  ; "commands"
0073    UGET    22   2      ; store_package_items
0074    TGETS   23   1  11  ; "commands"
0075    MOV     24   5
0076    MOV     25  11
0077    TGETS   26  19  11  ; "commands"
0078    CALL    22   1   5
0079 => GGET    20   2      ; "table"
0080    TGETS   20  20  13  ; "insert"
0081    MOV     21  13
0082    MOV     22  19
0083    CALL    20   1   3
0084 => ITERC   17   3   3
0085    ITERL   17 => 0039
0086    TSETV   13   7  11
0087 => ITERN   11   3   3
0088    ITERL   11 => 0034
0089    TGETS    8   1   4  ; "repository"
0090    TSETV    7   8   5
0091 => ITERN    5   3   3
0092    ITERL    5 => 0025
0093    UGET     2   3      ; sort_package_matching_table
0094    TGETS    3   1   9  ; "modules"
0095    CALL     2   1   2
0096    UGET     2   3      ; sort_package_matching_table
0097    TGETS    3   1  11  ; "commands"
0098    CALL     2   1   2
0099    KPRI     2   2
0100    RET1     2   2

-- BYTECODE -- writer.lua:236-247
0001    GGET     3   0      ; "assert"
0002    GGET     4   1      ; "type"
0003    MOV      5   0
0004    CALL     4   2   2
0005    ISEQS    4   2      ; "string"
0006    JMP      4 => 0009
0007    KPRI     4   1
0008    JMP      5 => 0010
0009 => KPRI     4   2
0010 => CALL     3   1   2
0011    GGET     3   0      ; "assert"
0012    GGET     4   1      ; "type"
0013    MOV      5   1
0014    CALL     4   2   2
0015    ISNES    4   2      ; "string"
0016    JMP      4 => 0023
0017    MOV      5   1
0018    TGETS    4   1   3  ; "match"
0019    KSTR     6   4      ; "/"
0020    CALL     4   2   3
0021    NOT      4   4
0022    JMP      5 => 0026
0023 => KPRI     4   1
0024    JMP      5 => 0026
0025    KPRI     4   2
0026 => CALL     3   1   2
0027    GGET     3   0      ; "assert"
0028    GGET     4   1      ; "type"
0029    MOV      5   2
0030    CALL     4   2   2
0031    ISEQS    4   5      ; "table"
0032    JMP      4 => 0035
0033    KPRI     4   1
0034    JMP      5 => 0036
0035 => KPRI     4   2
0036 => CALL     3   1   2
0037    UGET     3   0      ; dir
0038    TGETS    3   3   6  ; "path"
0039    MOV      4   0
0040    MOV      5   1
0041    CALL     3   2   3
0042    UGET     4   1      ; persist
0043    TGETS    4   4   7  ; "save_from_table"
0044    MOV      5   3
0045    KSTR     6   8      ; ".tmp"
0046    CAT      5   5   6
0047    MOV      6   2
0048    CALL     4   3   3
0049    ISF          4
0050    JMP      6 => 0060
0051    UGET     6   2      ; fs
0052    TGETS    6   6   9  ; "replace_file"
0053    MOV      7   3
0054    MOV      8   3
0055    KSTR     9   8      ; ".tmp"
0056    CAT      8   8   9
0057    CALL     6   3   3
0058    MOV      5   7
0059    MOV      4   6
0060 => MOV      6   4
0061    MOV      7   5
0062    RET      6   3

-- BYTECODE -- writer.lua:249-279
0001    UGET     2   0      ; path
0002    TGETS    2   2   0  ; "install_dir"
0003    MOV      3   0
0004    MOV      4   1
0005    CALL     2   2   3
0006    TNEW     3   0
0007    GGET     4   1      ; "ipairs"
0008    UGET     5   1      ; fs
0009    TGETS    5   5   2  ; "find"
0010    MOV      6   2
0011    CALL     5   0   2
0012    CALLM    4   4   0
0013    JMP      7 => 0056
0014 => UGET     9   2      ; dir
0015    TGETS    9   9   3  ; "path"
0016    MOV     10   2
0017    MOV     11   8
0018    CALL     9   2   3
0019    MOV     10   3
0020    KNIL    11  12
0021    MOV     14   8
0022    TGETS   13   8   4  ; "gmatch"
0023    KSTR    15   5      ; "[^/]+"
0024    CALL    13   4   3
0025    JMP     16 => 0034
0026 => TGETV   17  10  16
0027    IST         17
0028    JMP     18 => 0031
0029    TNEW    17   0
0030    TSETV   17  10  16
0031 => MOV     11  10
0032    MOV     12  16
0033    MOV     10  17
0034 => ITERC   16   2   3
0035    ITERL   16 => 0026
0036    UGET    13   1      ; fs
0037    TGETS   13  13   6  ; "is_file"
0038    MOV     14   9
0039    CALL    13   2   2
0040    ISF         13
0041    JMP     14 => 0056
0042    UGET    13   1      ; fs
0043    TGETS   13  13   7  ; "get_md5"
0044    MOV     14   9
0045    CALL    13   3   2
0046    IST         13
0047    JMP     15 => 0055
0048    KPRI    15   0
0049    KSTR    16   8      ; "Failed producing checksum: "
0050    GGET    17   9      ; "tostring"
0051    MOV     18  14
0052    CALL    17   2   2
0053    CAT     16  16  17
0054    RET     15   3
0055 => TSETV   13  11  12
0056 => ITERC    7   3   3
0057    ITERL    7 => 0014
0058    TDUP     4  10
0059    TSETS    3   4  11  ; "rock_manifest"
0060    UGET     5   3      ; manif
0061    TGETS    5   5  12  ; "rock_manifest_cache"
0062    MOV      6   0
0063    KSTR     7  13      ; "/"
0064    MOV      8   1
0065    CAT      6   6   8
0066    TSETV    4   5   6
0067    UGET     5   4      ; save_table
0068    MOV      6   2
0069    KSTR     7  11      ; "rock_manifest"
0070    MOV      8   4
0071    CALL     5   1   4
0072    KPRI     5   2
0073    RET1     5   2

-- BYTECODE -- writer.lua:287-304
0001    GGET     3   0      ; "assert"
0002    GGET     4   1      ; "type"
0003    MOV      5   0
0004    CALL     4   2   2
0005    ISNES    4   2      ; "string"
0006    JMP      4 => 0013
0007    MOV      5   0
0008    TGETS    4   0   3  ; "match"
0009    KSTR     6   4      ; "/"
0010    CALL     4   2   3
0011    NOT      4   4
0012    JMP      5 => 0016
0013 => KPRI     4   1
0014    JMP      5 => 0016
0015    KPRI     4   2
0016 => CALL     3   1   2
0017    GGET     3   0      ; "assert"
0018    GGET     4   1      ; "type"
0019    MOV      5   1
0020    CALL     4   2   2
0021    ISEQS    4   2      ; "string"
0022    JMP      4 => 0025
0023    KPRI     4   1
0024    JMP      5 => 0026
0025 => KPRI     4   2
0026 => CALL     3   1   2
0027    GGET     3   0      ; "assert"
0028    GGET     4   1      ; "type"
0029    MOV      5   2
0030    CALL     4   2   2
0031    ISEQS    4   2      ; "string"
0032    JMP      4 => 0037
0033    NOT      4   2
0034    JMP      5 => 0038
0035    KPRI     4   1
0036    JMP      5 => 0038
0037 => KPRI     4   2
0038 => CALL     3   1   2
0039    IST          2
0040    JMP      3 => 0043
0041    KPRI     3   2
0042    RET1     3   2
0043 => GGET     3   5      ; "io"
0044    TGETS    3   3   6  ; "open"
0045    UGET     4   0      ; path
0046    TGETS    4   4   7  ; "rock_namespace_file"
0047    MOV      5   0
0048    MOV      6   1
0049    CALL     4   2   3
0050    KSTR     5   8      ; "w"
0051    CALL     3   3   3
0052    IST          3
0053    JMP      5 => 0057
0054    KPRI     5   0
0055    MOV      6   4
0056    RET      5   3
0057 => MOV      6   3
0058    TGETS    5   3   9  ; "write"
0059    MOV      7   2
0060    CALL     5   3   3
0061    IST          5
0062    JMP      7 => 0066
0063    KPRI     7   0
0064    MOV      8   6
0065    RET      7   3
0066 => MOV      8   3
0067    TGETS    7   3  10  ; "close"
0068    CALL     7   1   2
0069    KPRI     7   2
0070    RET1     7   2

-- BYTECODE -- writer.lua:316-354
0001    GGET     3   0      ; "assert"
0002    GGET     4   1      ; "type"
0003    MOV      5   0
0004    CALL     4   2   2
0005    ISEQS    4   2      ; "string"
0006    JMP      4 => 0009
0007    KPRI     4   1
0008    JMP      5 => 0010
0009 => KPRI     4   2
0010 => CALL     3   1   2
0011    GGET     3   0      ; "assert"
0012    GGET     4   1      ; "type"
0013    MOV      5   1
0014    CALL     4   2   2
0015    ISEQS    4   2      ; "string"
0016    JMP      4 => 0019
0017    KPRI     4   1
0018    JMP      5 => 0020
0019 => KPRI     4   2
0020 => CALL     3   1   2
0021    ISNES    1   3      ; "none"
0022    JMP      3 => 0025
0023    UGET     3   0      ; cfg
0024    TGETS    1   3   4  ; "deps_mode"
0025 => UGET     3   1      ; fs
0026    TGETS    3   3   5  ; "is_dir"
0027    MOV      4   0
0028    CALL     3   2   2
0029    IST          3
0030    JMP      3 => 0036
0031    KPRI     3   0
0032    KSTR     4   6      ; "Cannot access repository at "
0033    MOV      5   0
0034    CAT      4   4   5
0035    RET      3   3
0036 => UGET     3   2      ; queries
0037    TGETS    3   3   7  ; "all"
0038    KSTR     4   8      ; "any"
0039    CALL     3   2   2
0040    UGET     4   3      ; search
0041    TGETS    4   4   9  ; "disk_search"
0042    MOV      5   0
0043    MOV      6   3
0044    CALL     4   2   3
0045    TDUP     5  10
0046    TNEW     6   0
0047    TSETS    6   5  11  ; "repository"
0048    TNEW     6   0
0049    TSETS    6   5  12  ; "modules"
0050    TNEW     6   0
0051    TSETS    6   5  13  ; "commands"
0052    UGET     6   4      ; manif
0053    TGETS    6   6  14  ; "cache_manifest"
0054    MOV      7   0
0055    KPRI     8   0
0056    MOV      9   5
0057    CALL     6   1   4
0058    UGET     6   5      ; store_results
0059    MOV      7   4
0060    MOV      8   5
0061    CALL     6   3   3
0062    IST          6
0063    JMP      8 => 0067
0064    KPRI     8   0
0065    MOV      9   7
0066    RET      8   3
0067 => ISF          2
0068    JMP      8 => 0105
0069    TNEW     8   0
0070    UGET     9   6      ; util
0071    TGETS    9   9  15  ; "lua_versions"
0072    CALL     9   4   1
0073    JMP     12 => 0102
0074 => TDUP    13  16
0075    TNEW    14   0
0076    TSETS   14  13  11  ; "repository"
0077    TNEW    14   0
0078    TSETS   14  13  12  ; "modules"
0079    TNEW    14   0
0080    TSETS   14  13  13  ; "commands"
0081    UGET    14   5      ; store_results
0082    MOV     15   4
0083    MOV     16  13
0084    CALL    14   3   3
0085    UGET    16   7      ; filter_by_lua_version
0086    MOV     17  13
0087    MOV     18  12
0088    MOV     19   0
0089    MOV     20   8
0090    CALL    16   1   5
0091    UGET    16   0      ; cfg
0092    TGETS   16  16  17  ; "no_manifest"
0093    IST         16
0094    JMP     16 => 0102
0095    UGET    16   8      ; save_table
0096    MOV     17   0
0097    KSTR    18  18      ; "manifest-"
0098    MOV     19  12
0099    CAT     18  18  19
0100    MOV     19  13
0101    CALL    16   1   4
0102 => ITERC   12   2   3
0103    ITERL   12 => 0074
0104    JMP      8 => 0109
0105 => UGET     8   9      ; update_dependencies
0106    MOV      9   5
0107    MOV     10   1
0108    CALL     8   1   3
0109 => UGET     8   0      ; cfg
0110    TGETS    8   8  17  ; "no_manifest"
0111    ISF          8
0112    JMP      9 => 0115
0113    KPRI     8   2
0114    RET1     8   2
0115 => UGET     8   8      ; save_table
0116    MOV      9   0
0117    KSTR    10  19      ; "manifest"
0118    MOV     11   5
0119    CALLT    8   4

-- BYTECODE -- writer.lua:367-395
0001    GGET     4   0      ; "assert"
0002    GGET     5   1      ; "type"
0003    MOV      6   0
0004    CALL     5   2   2
0005    ISNES    5   2      ; "string"
0006    JMP      5 => 0013
0007    MOV      6   0
0008    TGETS    5   0   3  ; "match"
0009    KSTR     7   4      ; "/"
0010    CALL     5   2   3
0011    NOT      5   5
0012    JMP      6 => 0016
0013 => KPRI     5   1
0014    JMP      6 => 0016
0015    KPRI     5   2
0016 => CALL     4   1   2
0017    GGET     4   0      ; "assert"
0018    GGET     5   1      ; "type"
0019    MOV      6   1
0020    CALL     5   2   2
0021    ISEQS    5   2      ; "string"
0022    JMP      5 => 0025
0023    KPRI     5   1
0024    JMP      6 => 0026
0025 => KPRI     5   2
0026 => CALL     4   1   2
0027    UGET     4   0      ; path
0028    TGETS    4   4   5  ; "rocks_dir"
0029    ISTC     5   2
0030    JMP      5 => 0033
0031    UGET     5   1      ; cfg
0032    TGETS    5   5   6  ; "root_dir"
0033 => CALL     4   2   2
0034    GGET     5   0      ; "assert"
0035    GGET     6   1      ; "type"
0036    MOV      7   3
0037    CALL     6   2   2
0038    ISEQS    6   2      ; "string"
0039    JMP      6 => 0042
0040    KPRI     6   1
0041    JMP      7 => 0043
0042 => KPRI     6   2
0043 => CALL     5   1   2
0044    ISNES    3   7      ; "none"
0045    JMP      5 => 0048
0046    UGET     5   1      ; cfg
0047    TGETS    3   5   8  ; "deps_mode"
0048 => UGET     5   2      ; manif
0049    TGETS    5   5   9  ; "load_manifest"
0050    MOV      6   4
0051    CALL     5   3   2
0052    IST          5
0053    JMP      7 => 0063
0054    UGET     7   3      ; util
0055    TGETS    7   7  10  ; "printerr"
0056    KSTR     8  11      ; "No existing manifest. Attempting to rebu"~
0057    CALL     7   1   2
0058    UGET     7   4      ; writer
0059    TGETS    7   7  12  ; "make_manifest"
0060    MOV      8   4
0061    MOV      9   3
0062    CALLT    7   3
0063 => TNEW     7 2048
0064    TNEW     8 2048
0065    TNEW     9   3
0066    TDUP    10  13
0067    TSETS    4  10  14  ; "repo"
0068    TSETB   10   9   1
0069    TSETV    9   8   1
0070    TSETV    8   7   0
0071    UGET     8   5      ; store_results
0072    MOV      9   7
0073    MOV     10   5
0074    CALL     8   3   3
0075    IST          8
0076    JMP     10 => 0080
0077    KPRI    10   0
0078    MOV     11   9
0079    RET     10   3
0080 => UGET    10   6      ; update_dependencies
0081    MOV     11   5
0082    MOV     12   3
0083    CALL    10   1   3
0084    UGET    10   1      ; cfg
0085    TGETS   10  10  15  ; "no_manifest"
0086    ISF         10
0087    JMP     11 => 0090
0088    KPRI    10   2
0089    RET1    10   2
0090 => UGET    10   7      ; save_table
0091    MOV     11   4
0092    KSTR    12  16      ; "manifest"
0093    MOV     13   5
0094    CALLT   10   4

-- BYTECODE -- writer.lua:408-454
0001    GGET     4   0      ; "assert"
0002    GGET     5   1      ; "type"
0003    MOV      6   0
0004    CALL     5   2   2
0005    ISNES    5   2      ; "string"
0006    JMP      5 => 0013
0007    MOV      6   0
0008    TGETS    5   0   3  ; "match"
0009    KSTR     7   4      ; "/"
0010    CALL     5   2   3
0011    NOT      5   5
0012    JMP      6 => 0016
0013 => KPRI     5   1
0014    JMP      6 => 0016
0015    KPRI     5   2
0016 => CALL     4   1   2
0017    GGET     4   0      ; "assert"
0018    GGET     5   1      ; "type"
0019    MOV      6   1
0020    CALL     5   2   2
0021    ISEQS    5   2      ; "string"
0022    JMP      5 => 0025
0023    KPRI     5   1
0024    JMP      6 => 0026
0025 => KPRI     5   2
0026 => CALL     4   1   2
0027    UGET     4   0      ; path
0028    TGETS    4   4   5  ; "rocks_dir"
0029    ISTC     5   2
0030    JMP      5 => 0033
0031    UGET     5   1      ; cfg
0032    TGETS    5   5   6  ; "root_dir"
0033 => CALL     4   2   2
0034    GGET     5   0      ; "assert"
0035    GGET     6   1      ; "type"
0036    MOV      7   3
0037    CALL     6   2   2
0038    ISEQS    6   2      ; "string"
0039    JMP      6 => 0042
0040    KPRI     6   1
0041    JMP      7 => 0043
0042 => KPRI     6   2
0043 => CALL     5   1   2
0044    ISNES    3   7      ; "none"
0045    JMP      5 => 0048
0046    UGET     5   1      ; cfg
0047    TGETS    3   5   8  ; "deps_mode"
0048 => UGET     5   2      ; manif
0049    TGETS    5   5   9  ; "load_manifest"
0050    MOV      6   4
0051    CALL     5   3   2
0052    IST          5
0053    JMP      7 => 0063
0054    UGET     7   3      ; util
0055    TGETS    7   7  10  ; "printerr"
0056    KSTR     8  11      ; "No existing manifest. Attempting to rebu"~
0057    CALL     7   1   2
0058    UGET     7   4      ; writer
0059    TGETS    7   7  12  ; "make_manifest"
0060    MOV      8   4
0061    MOV      9   3
0062    CALLT    7   3
0063 => TGETS    7   5  13  ; "repository"
0064    TGETV    7   7   0
0065    ISEQP    7   0
0066    JMP      8 => 0070
0067    TGETV    8   7   1
0068    ISNEP    8   0
0069    JMP      8 => 0072
0070 => KPRI     8   2
0071    RET1     8   2
0072 => TGETV    8   7   1
0073    TGETB    8   8   1
0074    IST          8
0075    JMP      9 => 0081
0076    UGET     9   4      ; writer
0077    TGETS    9   9  12  ; "make_manifest"
0078    MOV     10   4
0079    MOV     11   3
0080    CALLT    9   3
0081 => UGET     9   5      ; remove_package_items
0082    TGETS   10   5  14  ; "modules"
0083    MOV     11   0
0084    MOV     12   1
0085    TGETS   13   8  14  ; "modules"
0086    CALL     9   1   5
0087    UGET     9   5      ; remove_package_items
0088    TGETS   10   5  15  ; "commands"
0089    MOV     11   0
0090    MOV     12   1
0091    TGETS   13   8  15  ; "commands"
0092    CALL     9   1   5
0093    KPRI     9   0
0094    TSETV    9   7   1
0095    TGETS    9   5  16  ; "dependencies"
0096    TGETV    9   9   0
0097    KPRI    10   0
0098    TSETV   10   9   1
0099    GGET     9  17      ; "next"
0100    MOV     10   7
0101    CALL     9   2   2
0102    IST          9
0103    JMP      9 => 0110
0104    TGETS    9   5  13  ; "repository"
0105    KPRI    10   0
0106    TSETV   10   9   0
0107    TGETS    9   5  16  ; "dependencies"
0108    KPRI    10   0
0109    TSETV   10   9   0
0110 => UGET     9   6      ; update_dependencies
0111    MOV     10   5
0112    MOV     11   3
0113    CALL     9   1   3
0114    UGET     9   1      ; cfg
0115    TGETS    9   9  18  ; "no_manifest"
0116    ISF          9
0117    JMP     10 => 0120
0118    KPRI     9   2
0119    RET1     9   2
0120 => UGET     9   7      ; save_table
0121    MOV     10   4
0122    KSTR    11  19      ; "manifest"
0123    MOV     12   5
0124    CALLT    9   4

-- BYTECODE -- writer.lua:462-483
0001    UGET     2   0      ; path
0002    TGETS    2   2   0  ; "rocks_dir"
0003    ISTC     3   0
0004    JMP      3 => 0007
0005    UGET     3   1      ; cfg
0006    TGETS    3   3   1  ; "root_dir"
0007 => CALL     2   2   2
0008    GGET     3   2      ; "assert"
0009    GGET     4   3      ; "type"
0010    MOV      5   1
0011    CALL     4   2   2
0012    ISEQS    4   4      ; "string"
0013    JMP      4 => 0016
0014    KPRI     4   1
0015    JMP      5 => 0017
0016 => KPRI     4   2
0017 => CALL     3   1   2
0018    ISNES    1   5      ; "none"
0019    JMP      3 => 0022
0020    UGET     3   1      ; cfg
0021    TGETS    1   3   6  ; "deps_mode"
0022 => UGET     3   2      ; manif
0023    TGETS    3   3   7  ; "load_manifest"
0024    MOV      4   2
0025    CALL     3   2   2
0026    IST          3
0027    JMP      4 => 0029
0028    RET0     0   1
0029 => UGET     4   3      ; util
0030    TGETS    4   4   8  ; "sortedpairs"
0031    TGETS    5   3   9  ; "repository"
0032    CALL     4   4   2
0033    JMP      7 => 0073
0034 => UGET     9   3      ; util
0035    TGETS    9   9   8  ; "sortedpairs"
0036    MOV     10   8
0037    UGET    11   4      ; vers
0038    TGETS   11  11  10  ; "compare_versions"
0039    CALL     9   4   3
0040    JMP     12 => 0071
0041 => GGET    14  11      ; "ipairs"
0042    MOV     15  13
0043    CALL    14   4   2
0044    JMP     17 => 0069
0045 => TGETS   19  18  12  ; "arch"
0046    ISNES   19  13      ; "installed"
0047    JMP     19 => 0069
0048    TGETS   19   3  14  ; "dependencies"
0049    TGETV   19  19   7
0050    ISF         19
0051    JMP     20 => 0069
0052    TGETS   19   3  14  ; "dependencies"
0053    TGETV   19  19   7
0054    TGETV   19  19  12
0055    ISF         19
0056    JMP     20 => 0069
0057    UGET    19   5      ; deps
0058    TGETS   19  19  15  ; "report_missing_dependencies"
0059    MOV     20   7
0060    MOV     21  12
0061    TGETS   22   3  14  ; "dependencies"
0062    TGETV   22  22   7
0063    TGETV   22  22  12
0064    MOV     23   1
0065    UGET    24   3      ; util
0066    TGETS   24  24  16  ; "get_rocks_provided"
0067    CALL    24   0   1
0068    CALLM   19   1   4
0069 => ITERC   17   3   3
0070    ITERL   17 => 0045
0071 => ITERC   12   3   3
0072    ITERL   12 => 0041
0073 => ITERC    7   3   3
0074    ITERL    7 => 0034
0075    RET0     0   1

-- BYTECODE -- writer.lua:0-486
0001    TNEW     0   0
0002    GGET     1   0      ; "require"
0003    KSTR     2   1      ; "luarocks.core.cfg"
0004    CALL     1   2   2
0005    GGET     2   0      ; "require"
0006    KSTR     3   2      ; "luarocks.search"
0007    CALL     2   2   2
0008    GGET     3   0      ; "require"
0009    KSTR     4   3      ; "luarocks.repos"
0010    CALL     3   2   2
0011    GGET     4   0      ; "require"
0012    KSTR     5   4      ; "luarocks.deps"
0013    CALL     4   2   2
0014    GGET     5   0      ; "require"
0015    KSTR     6   5      ; "luarocks.core.vers"
0016    CALL     5   2   2
0017    GGET     6   0      ; "require"
0018    KSTR     7   6      ; "luarocks.fs"
0019    CALL     6   2   2
0020    GGET     7   0      ; "require"
0021    KSTR     8   7      ; "luarocks.util"
0022    CALL     7   2   2
0023    GGET     8   0      ; "require"
0024    KSTR     9   8      ; "luarocks.dir"
0025    CALL     8   2   2
0026    GGET     9   0      ; "require"
0027    KSTR    10   9      ; "luarocks.fetch"
0028    CALL     9   2   2
0029    GGET    10   0      ; "require"
0030    KSTR    11  10      ; "luarocks.path"
0031    CALL    10   2   2
0032    GGET    11   0      ; "require"
0033    KSTR    12  11      ; "luarocks.persist"
0034    CALL    11   2   2
0035    GGET    12   0      ; "require"
0036    KSTR    13  12      ; "luarocks.manif"
0037    CALL    12   2   2
0038    GGET    13   0      ; "require"
0039    KSTR    14  13      ; "luarocks.queries"
0040    CALL    13   2   2
0041    FNEW    14  14      ; writer.lua:25
0042    FNEW    15  15      ; writer.lua:49
0043    FNEW    16  16      ; writer.lua:81
0044    FNEW    17  17      ; writer.lua:107
0045    FNEW    18  18      ; writer.lua:120
0046    FNEW    19  19      ; writer.lua:150
0047    FNEW    20  20      ; writer.lua:199
0048    FNEW    21  21      ; writer.lua:236
0049    FNEW    22  23      ; writer.lua:249
0050    TSETS   22   0  22  ; "make_rock_manifest"
0051    FNEW    22  25      ; writer.lua:287
0052    TSETS   22   0  24  ; "make_namespace_file"
0053    FNEW    22  27      ; writer.lua:316
0054    TSETS   22   0  26  ; "make_manifest"
0055    FNEW    22  29      ; writer.lua:367
0056    TSETS   22   0  28  ; "add_to_manifest"
0057    FNEW    22  31      ; writer.lua:408
0058    TSETS   22   0  30  ; "remove_from_manifest"
0059    FNEW    22  33      ; writer.lua:462
0060    TSETS   22   0  32  ; "check_dependencies"
0061    UCLO     0 => 0062
0062 => RET1     0   2

