
main <./cmd/write_rockspec.lua:0,0> (122 instructions, 488 bytes at 0x7fcd374068c0)
0+ params, 24 slots, 0 upvalues, 25 locals, 46 constants, 14 functions
	1	[2]	NEWTABLE 	0 0 0
	2	[4]	GETGLOBAL	1 -1	; require
	3	[4]	LOADK    	2 -2	; "luarocks.build.builtin"
	4	[4]	CALL     	1 2 2
	5	[5]	GETGLOBAL	2 -1	; require
	6	[5]	LOADK    	3 -3	; "luarocks.core.cfg"
	7	[5]	CALL     	2 2 2
	8	[6]	GETGLOBAL	3 -1	; require
	9	[6]	LOADK    	4 -4	; "luarocks.dir"
	10	[6]	CALL     	3 2 2
	11	[7]	GETGLOBAL	4 -1	; require
	12	[7]	LOADK    	5 -5	; "luarocks.fetch"
	13	[7]	CALL     	4 2 2
	14	[8]	GETGLOBAL	5 -1	; require
	15	[8]	LOADK    	6 -6	; "luarocks.fs"
	16	[8]	CALL     	5 2 2
	17	[9]	GETGLOBAL	6 -1	; require
	18	[9]	LOADK    	7 -7	; "luarocks.persist"
	19	[9]	CALL     	6 2 2
	20	[10]	GETGLOBAL	7 -1	; require
	21	[10]	LOADK    	8 -8	; "luarocks.rockspecs"
	22	[10]	CALL     	7 2 2
	23	[11]	GETGLOBAL	8 -1	; require
	24	[11]	LOADK    	9 -9	; "luarocks.type.rockspec"
	25	[11]	CALL     	8 2 2
	26	[12]	GETGLOBAL	9 -1	; require
	27	[12]	LOADK    	10 -10	; "luarocks.util"
	28	[12]	CALL     	9 2 2
	29	[14]	NEWTABLE 	10 10 0
	30	[15]	LOADK    	11 -11	; "5.1"
	31	[16]	LOADK    	12 -12	; "5.2"
	32	[17]	LOADK    	13 -13	; "5.3"
	33	[18]	LOADK    	14 -14	; "5.4"
	34	[19]	LOADK    	15 -15	; "5.1,5.2"
	35	[20]	LOADK    	16 -16	; "5.2,5.3"
	36	[21]	LOADK    	17 -17	; "5.3,5.4"
	37	[22]	LOADK    	18 -18	; "5.1,5.2,5.3"
	38	[23]	LOADK    	19 -19	; "5.2,5.3,5.4"
	39	[25]	LOADK    	20 -20	; "5.1,5.2,5.3,5.4"
	40	[25]	SETLIST  	10 10 1	; 1
	41	[49]	CLOSURE  	11 0	; 0x7fcd37407000
	42	[49]	MOVE     	0 10
	43	[27]	SETTABLE 	0 -21 11	; "cmd_options" -
	44	[74]	CLOSURE  	11 1	; 0x7fcd37407a70
	45	[74]	MOVE     	0 9
	46	[74]	MOVE     	0 0
	47	[51]	SETTABLE 	0 -22 11	; "add_to_parser" -
	48	[78]	CLOSURE  	11 2	; 0x7fcd374084b0
	49	[78]	MOVE     	0 3
	50	[78]	MOVE     	0 5
	51	[94]	CLOSURE  	12 3	; 0x7fcd37408b90
	52	[94]	MOVE     	0 4
	53	[94]	MOVE     	0 9
	54	[94]	MOVE     	0 3
	55	[94]	MOVE     	0 5
	56	[96]	NEWTABLE 	13 0 10
	57	[97]	SETTABLE 	13 -11 -23	; "5.1" "lua ~> 5.1"
	58	[98]	SETTABLE 	13 -12 -24	; "5.2" "lua ~> 5.2"
	59	[99]	SETTABLE 	13 -13 -25	; "5.3" "lua ~> 5.3"
	60	[100]	SETTABLE 	13 -14 -26	; "5.4" "lua ~> 5.4"
	61	[101]	SETTABLE 	13 -15 -27	; "5.1,5.2" "lua >= 5.1, < 5.3"
	62	[102]	SETTABLE 	13 -16 -28	; "5.2,5.3" "lua >= 5.2, < 5.4"
	63	[103]	SETTABLE 	13 -17 -29	; "5.3,5.4" "lua >= 5.3, < 5.5"
	64	[104]	SETTABLE 	13 -18 -30	; "5.1,5.2,5.3" "lua >= 5.1, < 5.4"
	65	[105]	SETTABLE 	13 -19 -31	; "5.2,5.3,5.4" "lua >= 5.2, < 5.5"
	66	[106]	SETTABLE 	13 -20 -32	; "5.1,5.2,5.3,5.4" "lua >= 5.1, < 5.5"
	67	[109]	NEWTABLE 	14 0 8
	68	[110]	SETTABLE 	14 -33 -34	; "git" true
	69	[111]	SETTABLE 	14 -35 -34	; "git+http" true
	70	[112]	SETTABLE 	14 -36 -34	; "git+https" true
	71	[113]	SETTABLE 	14 -37 -34	; "git+ssh" true
	72	[114]	SETTABLE 	14 -38 -34	; "hg" true
	73	[115]	SETTABLE 	14 -39 -34	; "hg+http" true
	74	[116]	SETTABLE 	14 -40 -34	; "hg+https" true
	75	[117]	SETTABLE 	14 -41 -34	; "hg+ssh" true
	76	[120]	LOADNIL  	15 15
	77	[139]	CLOSURE  	16 4	; 0x7fcd37409120
	78	[139]	MOVE     	0 5
	79	[139]	MOVE     	0 2
	80	[139]	MOVE     	0 9
	81	[139]	MOVE     	0 14
	82	[139]	MOVE     	0 3
	83	[144]	CLOSURE  	17 5	; 0x7fcd3740a070
	84	[144]	MOVE     	0 16
	85	[152]	CLOSURE  	15 6	; 0x7fcd3740aa10
	86	[152]	MOVE     	0 17
	87	[152]	CLOSE    	16
	88	[170]	CLOSURE  	16 7	; 0x7fcd3740aeb0
	89	[170]	MOVE     	0 3
	90	[170]	MOVE     	0 14
	91	[170]	MOVE     	0 9
	92	[190]	CLOSURE  	17 8	; 0x7fcd3740b670
	93	[190]	MOVE     	0 11
	94	[192]	NEWTABLE 	18 0 2
	95	[193]	SETTABLE 	18 -42 -43	; 78656 "MIT"
	96	[194]	SETTABLE 	18 -44 -45	; 49311 "ISC"
	97	[207]	CLOSURE  	19 9	; 0x7fcd3740baf0
	98	[207]	MOVE     	0 18
	99	[219]	CLOSURE  	20 10	; 0x7fcd3740ab50
	100	[219]	MOVE     	0 11
	101	[219]	MOVE     	0 19
	102	[235]	CLOSURE  	21 11	; 0x7fcd37408ce0
	103	[235]	MOVE     	0 1
	104	[261]	CLOSURE  	22 12	; 0x7fcd3740b100
	105	[406]	CLOSURE  	23 13	; 0x7fcd3740cb60
	106	[406]	MOVE     	0 3
	107	[406]	MOVE     	0 5
	108	[406]	MOVE     	0 9
	109	[406]	MOVE     	0 15
	110	[406]	MOVE     	0 16
	111	[406]	MOVE     	0 7
	112	[406]	MOVE     	0 13
	113	[406]	MOVE     	0 12
	114	[406]	MOVE     	0 17
	115	[406]	MOVE     	0 20
	116	[406]	MOVE     	0 21
	117	[406]	MOVE     	0 22
	118	[406]	MOVE     	0 6
	119	[406]	MOVE     	0 8
	120	[263]	SETTABLE 	0 -46 23	; "command" -
	121	[408]	RETURN   	0 2
	122	[408]	RETURN   	0 1

function <./cmd/write_rockspec.lua:27,49> (75 instructions, 300 bytes at 0x7fcd37407000)
1 param, 13 slots, 1 upvalue, 1 local, 32 constants, 0 functions
	1	[28]	SELF     	1 0 -1	; "option"
	2	[28]	LOADK    	3 -2	; "--output"
	3	[28]	LOADK    	4 -3	; "Write the rockspec with the given filename.\n"
	4	[29]	LOADK    	5 -4	; "If not given, a file is written in the current directory with a "
	5	[30]	LOADK    	6 -5	; "filename based on given name and version."
	6	[30]	CONCAT   	4 4 6
	7	[28]	CALL     	1 4 2
	8	[31]	SELF     	1 1 -6	; "argname"
	9	[31]	LOADK    	3 -7	; "<file>"
	10	[31]	CALL     	1 3 2
	11	[32]	SELF     	2 0 -1	; "option"
	12	[32]	LOADK    	4 -8	; "--license"
	13	[32]	LOADK    	5 -9	; "A license string, such as \"MIT/X11\" or \"GNU GPL v3\"."
	14	[32]	CALL     	2 4 2
	15	[33]	SELF     	2 2 -6	; "argname"
	16	[33]	LOADK    	4 -10	; "<string>"
	17	[33]	CALL     	2 3 2
	18	[34]	SELF     	3 0 -1	; "option"
	19	[34]	LOADK    	5 -11	; "--summary"
	20	[34]	LOADK    	6 -12	; "A short one-line description summary."
	21	[34]	CALL     	3 4 2
	22	[35]	SELF     	3 3 -6	; "argname"
	23	[35]	LOADK    	5 -13	; "<txt>"
	24	[35]	CALL     	3 3 2
	25	[36]	SELF     	4 0 -1	; "option"
	26	[36]	LOADK    	6 -14	; "--detailed"
	27	[36]	LOADK    	7 -15	; "A longer description string."
	28	[36]	CALL     	4 4 2
	29	[37]	SELF     	4 4 -6	; "argname"
	30	[37]	LOADK    	6 -13	; "<txt>"
	31	[37]	CALL     	4 3 2
	32	[38]	SELF     	5 0 -1	; "option"
	33	[38]	LOADK    	7 -16	; "--homepage"
	34	[38]	LOADK    	8 -17	; "Project homepage."
	35	[38]	CALL     	5 4 2
	36	[39]	SELF     	5 5 -6	; "argname"
	37	[39]	LOADK    	7 -13	; "<txt>"
	38	[39]	CALL     	5 3 2
	39	[40]	SELF     	6 0 -1	; "option"
	40	[40]	LOADK    	8 -18	; "--lua-versions"
	41	[40]	LOADK    	9 -19	; "Supported Lua versions. Accepted values are: \""
	42	[41]	GETGLOBAL	10 -20	; table
	43	[41]	GETTABLE 	10 10 -21	; "concat"
	44	[41]	GETUPVAL 	11 0	; lua_versions
	45	[41]	LOADK    	12 -22	; "\", \""
	46	[41]	CALL     	10 3 2
	47	[41]	LOADK    	11 -23	; "\"."
	48	[41]	CONCAT   	9 9 11
	49	[40]	CALL     	6 4 2
	50	[42]	SELF     	6 6 -6	; "argname"
	51	[42]	LOADK    	8 -24	; "<ver>"
	52	[42]	CALL     	6 3 2
	53	[43]	SELF     	6 6 -25	; "choices"
	54	[43]	GETUPVAL 	8 0	; lua_versions
	55	[43]	CALL     	6 3 2
	56	[44]	SELF     	7 0 -1	; "option"
	57	[44]	LOADK    	9 -26	; "--rockspec-format"
	58	[44]	LOADK    	10 -27	; "Rockspec format version, such as \"1.0\" or \"1.1\"."
	59	[44]	CALL     	7 4 2
	60	[45]	SELF     	7 7 -6	; "argname"
	61	[45]	LOADK    	9 -24	; "<ver>"
	62	[45]	CALL     	7 3 2
	63	[46]	SELF     	8 0 -1	; "option"
	64	[46]	LOADK    	10 -28	; "--tag"
	65	[46]	LOADK    	11 -29	; "Tag to use. Will attempt to extract version number from it."
	66	[46]	CALL     	8 4 2
	67	[47]	SELF     	9 0 -1	; "option"
	68	[47]	LOADK    	11 -30	; "--lib"
	69	[47]	LOADK    	12 -31	; "A comma-separated list of libraries that C files need to link to."
	70	[47]	CALL     	9 4 2
	71	[48]	SELF     	9 9 -6	; "argname"
	72	[48]	LOADK    	11 -32	; "<libs>"
	73	[48]	CALL     	9 3 0
	74	[48]	RETURN   	1 0
	75	[49]	RETURN   	0 1

function <./cmd/write_rockspec.lua:51,74> (36 instructions, 144 bytes at 0x7fcd37407a70)
1 param, 6 slots, 2 upvalues, 2 locals, 16 constants, 0 functions
	1	[52]	SELF     	1 0 -1	; "command"
	2	[52]	LOADK    	3 -2	; "write_rockspec"
	3	[63]	LOADK    	4 -3	; "This command writes an initial version of a rockspec file,\nbased on a name, a version, and a location (an URL or a local path).\nIf only two arguments are given, the first one is considered the name and the\nsecond one is the location.\nIf only one argument is given, it must be the location.\nIf no arguments are given, current directory is used as the location.\nLuaRocks will attempt to infer name and version if not given,\nusing 'dev' as a fallback default version.\n\nNote that the generated file is a _starting point_ for writing a\nrockspec, and is not guaranteed to be complete or correct. "
	4	[63]	GETUPVAL 	5 0	; util
	5	[63]	GETTABLE 	5 5 -4	; "see_also"
	6	[63]	CALL     	5 1 0
	7	[52]	CALL     	1 0 2
	8	[64]	SELF     	1 1 -5	; "summary"
	9	[64]	LOADK    	3 -6	; "Write a template for a rockspec file."
	10	[64]	CALL     	1 3 2
	11	[66]	SELF     	2 1 -7	; "argument"
	12	[66]	LOADK    	4 -8	; "name"
	13	[66]	LOADK    	5 -9	; "Name of the rock."
	14	[66]	CALL     	2 4 2
	15	[67]	SELF     	2 2 -10	; "args"
	16	[67]	LOADK    	4 -11	; "?"
	17	[67]	CALL     	2 3 1
	18	[68]	SELF     	2 1 -7	; "argument"
	19	[68]	LOADK    	4 -12	; "version"
	20	[68]	LOADK    	5 -13	; "Rock version."
	21	[68]	CALL     	2 4 2
	22	[69]	SELF     	2 2 -10	; "args"
	23	[69]	LOADK    	4 -11	; "?"
	24	[69]	CALL     	2 3 1
	25	[70]	SELF     	2 1 -7	; "argument"
	26	[70]	LOADK    	4 -14	; "location"
	27	[70]	LOADK    	5 -15	; "URL or path to the rock sources."
	28	[70]	CALL     	2 4 2
	29	[71]	SELF     	2 2 -10	; "args"
	30	[71]	LOADK    	4 -11	; "?"
	31	[71]	CALL     	2 3 1
	32	[73]	GETUPVAL 	2 1	; write_rockspec
	33	[73]	GETTABLE 	2 2 -16	; "cmd_options"
	34	[73]	MOVE     	3 1
	35	[73]	CALL     	2 2 1
	36	[74]	RETURN   	0 1

function <./cmd/write_rockspec.lua:76,78> (13 instructions, 52 bytes at 0x7fcd374084b0)
1 param, 5 slots, 2 upvalues, 1 local, 5 constants, 0 functions
	1	[77]	GETGLOBAL	1 -1	; io
	2	[77]	GETTABLE 	1 1 -2	; "open"
	3	[77]	GETUPVAL 	2 0	; dir
	4	[77]	GETTABLE 	2 2 -3	; "path"
	5	[77]	GETUPVAL 	3 1	; fs
	6	[77]	GETTABLE 	3 3 -4	; "current_dir"
	7	[77]	CALL     	3 1 2
	8	[77]	MOVE     	4 0
	9	[77]	CALL     	2 3 2
	10	[77]	LOADK    	3 -5	; "r"
	11	[77]	TAILCALL 	1 3 0
	12	[77]	RETURN   	1 0
	13	[78]	RETURN   	0 1

function <./cmd/write_rockspec.lua:80,94> (52 instructions, 208 bytes at 0x7fcd37408b90)
1 param, 11 slots, 4 upvalues, 8 locals, 13 constants, 0 functions
	1	[81]	GETUPVAL 	1 0	; fetch
	2	[81]	GETTABLE 	1 1 -1	; "fetch_sources"
	3	[81]	MOVE     	2 0
	4	[81]	LOADBOOL 	3 0 0
	5	[81]	CALL     	1 3 6
	6	[82]	EQ       	0 3 -2	; - "source.dir"
	7	[82]	JMP      	4	; to 12
	8	[83]	MOVE     	6 4
	9	[83]	MOVE     	2 5
	10	[83]	MOVE     	1 6
	11	[83]	JMP      	10	; to 22
	12	[84]	TEST     	1 0 1
	13	[84]	JMP      	8	; to 22
	14	[85]	GETUPVAL 	6 1	; util
	15	[85]	GETTABLE 	6 6 -3	; "warning"
	16	[85]	LOADK    	7 -4	; "Could not fetch sources - "
	17	[85]	MOVE     	8 2
	18	[85]	CONCAT   	7 7 8
	19	[85]	CALL     	6 2 1
	20	[86]	LOADBOOL 	6 0 0
	21	[86]	RETURN   	6 2
	22	[88]	GETUPVAL 	6 1	; util
	23	[88]	GETTABLE 	6 6 -5	; "printout"
	24	[88]	LOADK    	7 -6	; "File successfully downloaded. Making checksum and checking base dir..."
	25	[88]	CALL     	6 2 1
	26	[89]	GETUPVAL 	6 2	; dir
	27	[89]	GETTABLE 	6 6 -7	; "is_basic_protocol"
	28	[89]	GETTABLE 	7 0 -8	; "source"
	29	[89]	GETTABLE 	7 7 -9	; "protocol"
	30	[89]	CALL     	6 2 2
	31	[89]	TEST     	6 0 0
	32	[89]	JMP      	6	; to 39
	33	[90]	GETTABLE 	6 0 -8	; "source"
	34	[90]	GETUPVAL 	7 3	; fs
	35	[90]	GETTABLE 	7 7 -11	; "get_md5"
	36	[90]	MOVE     	8 1
	37	[90]	CALL     	7 2 2
	38	[90]	SETTABLE 	6 -10 7	; "md5" -
	39	[92]	GETUPVAL 	6 0	; fetch
	40	[92]	GETTABLE 	6 6 -12	; "find_base_dir"
	41	[92]	MOVE     	7 1
	42	[92]	MOVE     	8 2
	43	[92]	GETTABLE 	9 0 -8	; "source"
	44	[92]	GETTABLE 	9 9 -13	; "url"
	45	[92]	CALL     	6 4 3
	46	[93]	LOADBOOL 	8 1 0
	47	[93]	TESTSET  	9 7 1
	48	[93]	JMP      	1	; to 50
	49	[93]	MOVE     	9 6
	50	[93]	MOVE     	10 2
	51	[93]	RETURN   	8 4
	52	[94]	RETURN   	0 1

function <./cmd/write_rockspec.lua:122,139> (78 instructions, 312 bytes at 0x7fcd37409120)
3 params, 16 slots, 5 upvalues, 9 locals, 22 constants, 0 functions
	1	[123]	GETUPVAL 	3 0	; fs
	2	[123]	GETTABLE 	3 3 -1	; "Q"
	3	[123]	GETUPVAL 	4 1	; cfg
	4	[123]	GETTABLE 	4 4 -2	; "variables"
	5	[123]	SELF     	5 0 -3	; "upper"
	6	[123]	CALL     	5 2 2
	7	[123]	GETTABLE 	4 4 5
	8	[123]	CALL     	3 2 2
	9	[123]	LOADK    	4 -4	; " "
	10	[123]	MOVE     	5 1
	11	[123]	CONCAT   	3 3 5
	12	[124]	GETGLOBAL	4 -5	; io
	13	[124]	GETTABLE 	4 4 -6	; "popen"
	14	[124]	GETUPVAL 	5 0	; fs
	15	[124]	GETTABLE 	5 5 -7	; "command_at"
	16	[124]	MOVE     	6 2
	17	[124]	GETUPVAL 	7 0	; fs
	18	[124]	GETTABLE 	7 7 -8	; "quiet_stderr"
	19	[124]	MOVE     	8 3
	20	[124]	CALL     	7 2 0
	21	[124]	CALL     	5 0 0
	22	[124]	CALL     	4 0 2
	23	[125]	TEST     	4 0 1
	24	[125]	JMP      	2	; to 27
	25	[125]	LOADNIL  	5 5
	26	[125]	RETURN   	5 2
	27	[126]	SELF     	5 4 -9	; "read"
	28	[126]	LOADK    	7 -10	; "*a"
	29	[126]	CALL     	5 3 2
	30	[126]	SELF     	5 5 -11	; "match"
	31	[126]	LOADK    	7 -12	; "^([^\r\n]+)"
	32	[126]	CALL     	5 3 2
	33	[127]	SELF     	6 4 -13	; "close"
	34	[127]	CALL     	6 2 1
	35	[128]	TEST     	5 0 1
	36	[128]	JMP      	2	; to 39
	37	[128]	LOADNIL  	6 6
	38	[128]	RETURN   	6 2
	39	[129]	SELF     	6 5 -11	; "match"
	40	[129]	LOADK    	8 -14	; "^[^@:/]+@[^@:/]+:.*$"
	41	[129]	CALL     	6 3 2
	42	[129]	TEST     	6 0 0
	43	[129]	JMP      	12	; to 56
	44	[130]	SELF     	6 5 -11	; "match"
	45	[130]	LOADK    	8 -15	; "^([^@]+)@([^:]+):(.*)$"
	46	[130]	CALL     	6 3 4
	47	[131]	MOVE     	9 0
	48	[131]	LOADK    	10 -16	; "+ssh://"
	49	[131]	MOVE     	11 6
	50	[131]	LOADK    	12 -17	; "@"
	51	[131]	MOVE     	13 7
	52	[131]	LOADK    	14 -18	; "/"
	53	[131]	MOVE     	15 8
	54	[131]	CONCAT   	5 9 15
	55	[131]	JMP      	13	; to 69
	56	[132]	GETUPVAL 	6 2	; util
	57	[132]	GETTABLE 	6 6 -19	; "starts_with"
	58	[132]	MOVE     	7 5
	59	[132]	MOVE     	8 0
	60	[132]	LOADK    	9 -20	; "://"
	61	[132]	CONCAT   	8 8 9
	62	[132]	CALL     	6 3 2
	63	[132]	TEST     	6 0 1
	64	[132]	JMP      	4	; to 69
	65	[133]	MOVE     	6 0
	66	[133]	LOADK    	7 -21	; "+"
	67	[133]	MOVE     	8 5
	68	[133]	CONCAT   	5 6 8
	69	[136]	GETUPVAL 	6 3	; simple_scm_protocols
	70	[136]	GETUPVAL 	7 4	; dir
	71	[136]	GETTABLE 	7 7 -22	; "split_url"
	72	[136]	MOVE     	8 5
	73	[136]	CALL     	7 2 2
	74	[136]	GETTABLE 	6 6 7
	75	[136]	TEST     	6 0 0
	76	[136]	JMP      	1	; to 78
	77	[137]	RETURN   	5 2
	78	[139]	RETURN   	0 1

function <./cmd/write_rockspec.lua:141,144> (14 instructions, 56 bytes at 0x7fcd3740a070)
1 param, 5 slots, 1 upvalue, 1 local, 4 constants, 0 functions
	1	[142]	GETUPVAL 	1 0	; detect_url_from_command
	2	[142]	LOADK    	2 -1	; "git"
	3	[142]	LOADK    	3 -2	; "config --get remote.origin.url"
	4	[142]	MOVE     	4 0
	5	[142]	CALL     	1 4 2
	6	[142]	TEST     	1 0 1
	7	[142]	JMP      	5	; to 13
	8	[143]	GETUPVAL 	1 0	; detect_url_from_command
	9	[143]	LOADK    	2 -3	; "hg"
	10	[143]	LOADK    	3 -4	; "paths default"
	11	[143]	MOVE     	4 0
	12	[143]	CALL     	1 4 2
	13	[143]	RETURN   	1 2
	14	[144]	RETURN   	0 1

function <./cmd/write_rockspec.lua:146,152> (15 instructions, 60 bytes at 0x7fcd3740aa10)
1 param, 4 slots, 1 upvalue, 1 local, 3 constants, 0 functions
	1	[147]	SELF     	1 0 -1	; "match"
	2	[147]	LOADK    	3 -2	; "://"
	3	[147]	CALL     	1 3 2
	4	[147]	TEST     	1 0 0
	5	[147]	JMP      	2	; to 8
	6	[148]	RETURN   	0 2
	7	[148]	JMP      	7	; to 15
	8	[150]	GETUPVAL 	1 0	; detect_scm_url
	9	[150]	MOVE     	2 0
	10	[150]	CALL     	1 2 2
	11	[150]	TEST     	1 0 1
	12	[150]	JMP      	1	; to 14
	13	[150]	LOADK    	1 -3	; "*** please add URL for source tarball, zip or repository here ***"
	14	[150]	RETURN   	1 2
	15	[152]	RETURN   	0 1

function <./cmd/write_rockspec.lua:155,170> (38 instructions, 152 bytes at 0x7fcd3740aeb0)
2 params, 14 slots, 3 upvalues, 9 locals, 11 constants, 0 functions
	1	[156]	TEST     	1 0 0
	2	[156]	JMP      	1	; to 4
	3	[157]	RETURN   	1 2
	4	[159]	GETUPVAL 	2 0	; dir
	5	[159]	GETTABLE 	2 2 -1	; "split_url"
	6	[159]	MOVE     	3 0
	7	[159]	CALL     	2 2 3
	8	[161]	GETUPVAL 	4 1	; simple_scm_protocols
	9	[161]	GETTABLE 	4 4 2
	10	[161]	TEST     	4 0 0
	11	[161]	JMP      	24	; to 36
	12	[162]	GETGLOBAL	4 -2	; ipairs
	13	[162]	NEWTABLE 	5 3 0
	14	[162]	LOADK    	6 -3	; "github.com"
	15	[162]	LOADK    	7 -4	; "bitbucket.org"
	16	[162]	LOADK    	8 -5	; "gitlab.com"
	17	[162]	SETLIST  	5 3 1	; 1
	18	[162]	CALL     	4 2 4
	19	[162]	JMP      	14	; to 34
	20	[163]	GETUPVAL 	9 2	; util
	21	[163]	GETTABLE 	9 9 -6	; "starts_with"
	22	[163]	MOVE     	10 3
	23	[163]	MOVE     	11 8
	24	[163]	CALL     	9 3 2
	25	[163]	TEST     	9 0 0
	26	[163]	JMP      	7	; to 34
	27	[164]	LOADK    	9 -7	; "https://"
	28	[164]	SELF     	10 3 -8	; "gsub"
	29	[164]	LOADK    	12 -9	; "%.git$"
	30	[164]	LOADK    	13 -10	; ""
	31	[164]	CALL     	10 4 2
	32	[164]	CONCAT   	9 9 10
	33	[164]	RETURN   	9 2
	34	[162]	TFORLOOP 	4 2
	35	[165]	JMP      	-16	; to 20
	36	[169]	LOADK    	4 -11	; "*** please enter a project homepage ***"
	37	[169]	RETURN   	4 2
	38	[170]	RETURN   	0 1

function <./cmd/write_rockspec.lua:172,190> (50 instructions, 200 bytes at 0x7fcd3740b670)
0 params, 9 slots, 1 upvalue, 5 locals, 14 constants, 0 functions
	1	[173]	GETUPVAL 	0 0	; open_file
	2	[173]	LOADK    	1 -1	; "README.md"
	3	[173]	CALL     	0 2 2
	4	[173]	TEST     	0 0 1
	5	[173]	JMP      	3	; to 9
	6	[173]	GETUPVAL 	0 0	; open_file
	7	[173]	LOADK    	1 -2	; "README"
	8	[173]	CALL     	0 2 2
	9	[174]	TEST     	0 0 1
	10	[174]	JMP      	1	; to 12
	11	[174]	RETURN   	0 1
	12	[175]	SELF     	1 0 -3	; "read"
	13	[175]	LOADK    	3 -4	; "*a"
	14	[175]	CALL     	1 3 2
	15	[176]	SELF     	2 0 -5	; "close"
	16	[176]	CALL     	2 2 1
	17	[177]	SELF     	2 1 -6	; "match"
	18	[177]	LOADK    	4 -7	; "\n\n([^%[].-)\n\n"
	19	[177]	CALL     	2 3 2
	20	[178]	TEST     	2 0 1
	21	[178]	JMP      	4	; to 26
	22	[178]	SELF     	3 1 -6	; "match"
	23	[178]	LOADK    	5 -8	; "\n\n(.*)"
	24	[178]	CALL     	3 3 2
	25	[178]	MOVE     	2 3
	26	[179]	LOADNIL  	3 4
	27	[180]	TEST     	2 0 0
	28	[180]	JMP      	18	; to 47
	29	[181]	MOVE     	4 2
	30	[183]	LEN      	5 2
	31	[183]	LT       	0 5 -9	; - 80
	32	[183]	JMP      	6	; to 39
	33	[184]	SELF     	5 2 -10	; "gsub"
	34	[184]	LOADK    	7 -11	; "\n"
	35	[184]	LOADK    	8 -12	; ""
	36	[184]	CALL     	5 4 2
	37	[184]	MOVE     	3 5
	38	[184]	JMP      	8	; to 47
	39	[186]	SELF     	5 2 -10	; "gsub"
	40	[186]	LOADK    	7 -11	; "\n"
	41	[186]	LOADK    	8 -13	; " "
	42	[186]	CALL     	5 4 2
	43	[186]	SELF     	5 5 -6	; "match"
	44	[186]	LOADK    	7 -14	; "([^.]*%.) "
	45	[186]	CALL     	5 3 2
	46	[186]	MOVE     	3 5
	47	[189]	MOVE     	5 3
	48	[189]	MOVE     	6 4
	49	[189]	RETURN   	5 3
	50	[190]	RETURN   	0 1

function <./cmd/write_rockspec.lua:197,207> (26 instructions, 104 bytes at 0x7fcd3740baf0)
1 param, 12 slots, 1 upvalue, 8 locals, 10 constants, 0 functions
	1	[198]	SELF     	1 0 -1	; "gsub"
	2	[198]	LOADK    	3 -2	; "^Copyright [^\n]*\n"
	3	[198]	LOADK    	4 -3	; ""
	4	[198]	CALL     	1 4 2
	5	[199]	LOADK    	2 -4	; 0
	6	[200]	LOADK    	3 -5	; 1
	7	[200]	LEN      	4 1
	8	[200]	LOADK    	5 -5	; 1
	9	[200]	FORPREP  	3 12	; to 22
	10	[201]	GETGLOBAL	7 -6	; string
	11	[201]	GETTABLE 	7 7 -7	; "byte"
	12	[201]	SELF     	8 1 -8	; "sub"
	13	[201]	MOVE     	10 6
	14	[201]	MOVE     	11 6
	15	[201]	CALL     	8 4 0
	16	[201]	CALL     	7 0 2
	17	[202]	LT       	0 -9 7	; 32 -
	18	[202]	JMP      	3	; to 22
	19	[202]	LE       	0 7 -10	; - 128
	20	[202]	JMP      	1	; to 22
	21	[203]	ADD      	2 2 7
	22	[200]	FORLOOP  	3 -13	; to 10
	23	[206]	GETUPVAL 	3 0	; licenses
	24	[206]	GETTABLE 	3 3 2
	25	[206]	RETURN   	3 2
	26	[207]	RETURN   	0 1

function <./cmd/write_rockspec.lua:209,219> (34 instructions, 136 bytes at 0x7fcd3740ab50)
0 params, 5 slots, 2 upvalues, 3 locals, 6 constants, 0 functions
	1	[210]	GETUPVAL 	0 0	; open_file
	2	[210]	LOADK    	1 -1	; "COPYING"
	3	[210]	CALL     	0 2 2
	4	[210]	TEST     	0 0 1
	5	[210]	JMP      	8	; to 14
	6	[210]	GETUPVAL 	0 0	; open_file
	7	[210]	LOADK    	1 -2	; "LICENSE"
	8	[210]	CALL     	0 2 2
	9	[210]	TEST     	0 0 1
	10	[210]	JMP      	3	; to 14
	11	[210]	GETUPVAL 	0 0	; open_file
	12	[210]	LOADK    	1 -3	; "MIT-LICENSE.txt"
	13	[210]	CALL     	0 2 2
	14	[211]	TEST     	0 0 1
	15	[211]	JMP      	2	; to 18
	16	[211]	LOADNIL  	1 1
	17	[211]	RETURN   	1 2
	18	[212]	SELF     	1 0 -4	; "read"
	19	[212]	LOADK    	3 -5	; "*a"
	20	[212]	CALL     	1 3 2
	21	[213]	SELF     	2 0 -6	; "close"
	22	[213]	CALL     	2 2 1
	23	[214]	GETUPVAL 	2 1	; detect_license
	24	[214]	MOVE     	3 1
	25	[214]	CALL     	2 2 2
	26	[215]	TEST     	2 0 0
	27	[215]	JMP      	3	; to 31
	28	[216]	MOVE     	3 2
	29	[216]	MOVE     	4 1
	30	[216]	RETURN   	3 3
	31	[218]	LOADNIL  	3 3
	32	[218]	MOVE     	4 1
	33	[218]	RETURN   	3 3
	34	[219]	RETURN   	0 1

function <./cmd/write_rockspec.lua:221,235> (44 instructions, 176 bytes at 0x7fcd37408ce0)
2 params, 14 slots, 1 upvalue, 10 locals, 13 constants, 0 functions
	1	[222]	GETTABLE 	2 0 -1	; "build"
	2	[222]	SETTABLE 	2 -2 -3	; "type" "builtin"
	3	[224]	LOADNIL  	2 3
	4	[225]	TEST     	1 0 0
	5	[225]	JMP      	26	; to 32
	6	[226]	NEWTABLE 	4 0 0
	7	[226]	NEWTABLE 	5 0 0
	8	[226]	MOVE     	3 5
	9	[226]	MOVE     	2 4
	10	[227]	GETGLOBAL	4 -4	; ipairs
	11	[227]	MOVE     	5 1
	12	[227]	CALL     	4 2 4
	13	[227]	JMP      	16	; to 30
	14	[228]	SELF     	9 8 -5	; "upper"
	15	[228]	CALL     	9 2 2
	16	[229]	LEN      	10 2
	17	[229]	ADD      	10 10 -6	; - 1
	18	[229]	LOADK    	11 -7	; "$("
	19	[229]	MOVE     	12 9
	20	[229]	LOADK    	13 -8	; "_INCDIR)"
	21	[229]	CONCAT   	11 11 13
	22	[229]	SETTABLE 	2 10 11
	23	[230]	LEN      	10 3
	24	[230]	ADD      	10 10 -6	; - 1
	25	[230]	LOADK    	11 -7	; "$("
	26	[230]	MOVE     	12 9
	27	[230]	LOADK    	13 -9	; "_LIBDIR)"
	28	[230]	CONCAT   	11 11 13
	29	[230]	SETTABLE 	3 10 11
	30	[227]	TFORLOOP 	4 2
	31	[230]	JMP      	-18	; to 14
	32	[234]	GETTABLE 	4 0 -1	; "build"
	33	[234]	GETTABLE 	5 0 -1	; "build"
	34	[234]	GETTABLE 	6 0 -1	; "build"
	35	[234]	GETUPVAL 	7 0	; builtin
	36	[234]	GETTABLE 	7 7 -13	; "autodetect_modules"
	37	[234]	MOVE     	8 1
	38	[234]	MOVE     	9 2
	39	[234]	MOVE     	10 3
	40	[234]	CALL     	7 4 4
	41	[234]	SETTABLE 	6 -12 9	; "copy_directories" -
	42	[234]	SETTABLE 	5 -11 8	; "install" -
	43	[234]	SETTABLE 	4 -10 7	; "modules" -
	44	[235]	RETURN   	0 1

function <./cmd/write_rockspec.lua:237,261> (61 instructions, 244 bytes at 0x7fcd3740b100)
1 param, 14 slots, 0 upvalues, 16 locals, 19 constants, 0 functions
	1	[238]	GETTABLE 	1 0 -1	; "source"
	2	[238]	SETTABLE 	1 -2 -3	; "file" nil
	3	[239]	GETTABLE 	1 0 -1	; "source"
	4	[239]	SETTABLE 	1 -4 -3	; "protocol" nil
	5	[240]	GETTABLE 	1 0 -1	; "source"
	6	[240]	SETTABLE 	1 -5 -3	; "identifier" nil
	7	[241]	GETTABLE 	1 0 -1	; "source"
	8	[241]	SETTABLE 	1 -6 -3	; "dir" nil
	9	[242]	GETTABLE 	1 0 -1	; "source"
	10	[242]	SETTABLE 	1 -7 -3	; "dir_set" nil
	11	[243]	GETTABLE 	1 0 -1	; "source"
	12	[243]	SETTABLE 	1 -8 -3	; "pathname" nil
	13	[244]	SETTABLE 	0 -9 -3	; "variables" nil
	14	[245]	SETTABLE 	0 -10 -3	; "name" nil
	15	[246]	SETTABLE 	0 -11 -3	; "format_is_at_least" nil
	16	[247]	SETTABLE 	0 -12 -3	; "local_abs_filename" nil
	17	[248]	SETTABLE 	0 -13 -3	; "rocks_provided" nil
	18	[249]	GETGLOBAL	1 -14	; ipairs
	19	[249]	NEWTABLE 	2 3 0
	20	[249]	LOADK    	3 -15	; "dependencies"
	21	[249]	LOADK    	4 -16	; "build_dependencies"
	22	[249]	LOADK    	5 -17	; "test_dependencies"
	23	[249]	SETLIST  	2 3 1	; 1
	24	[249]	CALL     	1 2 4
	25	[249]	JMP      	9	; to 35
	26	[250]	GETTABLE 	6 0 5
	27	[250]	TEST     	6 0 0
	28	[250]	JMP      	6	; to 35
	29	[250]	GETGLOBAL	6 -18	; next
	30	[250]	GETTABLE 	7 0 5
	31	[250]	CALL     	6 2 2
	32	[250]	TEST     	6 0 1
	33	[250]	JMP      	1	; to 35
	34	[251]	SETTABLE 	0 5 -3	; - nil
	35	[249]	TFORLOOP 	1 2
	36	[252]	JMP      	-11	; to 26
	37	[254]	GETGLOBAL	1 -14	; ipairs
	38	[254]	NEWTABLE 	2 3 0
	39	[254]	LOADK    	3 -15	; "dependencies"
	40	[254]	LOADK    	4 -16	; "build_dependencies"
	41	[254]	LOADK    	5 -17	; "test_dependencies"
	42	[254]	SETLIST  	2 3 1	; 1
	43	[254]	CALL     	1 2 4
	44	[254]	JMP      	14	; to 59
	45	[255]	GETTABLE 	6 0 5
	46	[255]	TEST     	6 0 0
	47	[255]	JMP      	11	; to 59
	48	[256]	GETGLOBAL	6 -14	; ipairs
	49	[256]	GETTABLE 	7 0 5
	50	[256]	CALL     	6 2 4
	51	[256]	JMP      	5	; to 57
	52	[257]	GETTABLE 	11 0 5
	53	[257]	GETGLOBAL	12 -19	; tostring
	54	[257]	MOVE     	13 10
	55	[257]	CALL     	12 2 2
	56	[257]	SETTABLE 	11 9 12
	57	[256]	TFORLOOP 	6 2
	58	[257]	JMP      	-7	; to 52
	59	[254]	TFORLOOP 	1 2
	60	[259]	JMP      	-16	; to 45
	61	[261]	RETURN   	0 1

function <./cmd/write_rockspec.lua:263,406> (355 instructions, 1420 bytes at 0x7fcd3740cb60)
1 param, 20 slots, 14 upvalues, 29 locals, 71 constants, 0 functions
	1	[264]	GETTABLE 	1 0 -1	; "name"
	2	[264]	GETTABLE 	2 0 -2	; "version"
	3	[265]	GETTABLE 	3 0 -3	; "location"
	4	[267]	TEST     	1 0 1
	5	[267]	JMP      	2	; to 8
	6	[268]	LOADK    	3 -4	; "."
	7	[268]	JMP      	9	; to 17
	8	[269]	TEST     	2 0 1
	9	[269]	JMP      	3	; to 13
	10	[270]	MOVE     	3 1
	11	[271]	LOADNIL  	1 1
	12	[271]	JMP      	4	; to 17
	13	[272]	TEST     	3 0 1
	14	[272]	JMP      	2	; to 17
	15	[273]	MOVE     	3 2
	16	[274]	LOADNIL  	2 2
	17	[277]	GETTABLE 	4 0 -5	; "tag"
	18	[277]	TEST     	4 0 0
	19	[277]	JMP      	8	; to 28
	20	[278]	TEST     	2 0 1
	21	[278]	JMP      	6	; to 28
	22	[279]	GETTABLE 	4 0 -5	; "tag"
	23	[279]	SELF     	4 4 -6	; "gsub"
	24	[279]	LOADK    	6 -7	; "^v"
	25	[279]	LOADK    	7 -8	; ""
	26	[279]	CALL     	4 4 2
	27	[279]	MOVE     	2 4
	28	[283]	GETUPVAL 	4 0	; dir
	29	[283]	GETTABLE 	4 4 -9	; "split_url"
	30	[283]	MOVE     	5 3
	31	[283]	CALL     	4 2 3
	32	[284]	EQ       	0 4 -10	; - "file"
	33	[284]	JMP      	12	; to 46
	34	[285]	EQ       	0 5 -4	; - "."
	35	[285]	JMP      	51	; to 87
	36	[286]	TEST     	1 0 1
	37	[286]	JMP      	7	; to 45
	38	[286]	GETUPVAL 	6 0	; dir
	39	[286]	GETTABLE 	6 6 -11	; "base_name"
	40	[286]	GETUPVAL 	7 1	; fs
	41	[286]	GETTABLE 	7 7 -12	; "current_dir"
	42	[286]	CALL     	7 1 0
	43	[286]	CALL     	6 0 2
	44	[286]	MOVE     	1 6
	45	[287]	JMP      	41	; to 87
	46	[288]	GETUPVAL 	6 0	; dir
	47	[288]	GETTABLE 	6 6 -13	; "is_basic_protocol"
	48	[288]	MOVE     	7 4
	49	[288]	CALL     	6 2 2
	50	[288]	TEST     	6 0 0
	51	[288]	JMP      	24	; to 76
	52	[289]	GETUPVAL 	6 0	; dir
	53	[289]	GETTABLE 	6 6 -11	; "base_name"
	54	[289]	MOVE     	7 3
	55	[289]	CALL     	6 2 2
	56	[290]	SELF     	7 6 -14	; "match"
	57	[290]	LOADK    	9 -15	; "(.*)-([^-]+)"
	58	[290]	CALL     	7 3 3
	59	[291]	TEST     	7 0 0
	60	[291]	JMP      	26	; to 87
	61	[292]	TEST     	1 0 1
	62	[292]	JMP      	1	; to 64
	63	[292]	MOVE     	1 7
	64	[293]	TEST     	2 0 1
	65	[293]	JMP      	9	; to 75
	66	[293]	SELF     	9 8 -6	; "gsub"
	67	[293]	LOADK    	11 -16	; "%.[a-z]+$"
	68	[293]	LOADK    	12 -8	; ""
	69	[293]	CALL     	9 4 2
	70	[293]	SELF     	9 9 -6	; "gsub"
	71	[293]	LOADK    	11 -17	; "%.tar$"
	72	[293]	LOADK    	12 -8	; ""
	73	[293]	CALL     	9 4 2
	74	[293]	MOVE     	2 9
	75	[294]	JMP      	11	; to 87
	76	[296]	TEST     	1 0 1
	77	[296]	JMP      	9	; to 87
	78	[296]	GETUPVAL 	6 0	; dir
	79	[296]	GETTABLE 	6 6 -11	; "base_name"
	80	[296]	MOVE     	7 3
	81	[296]	CALL     	6 2 2
	82	[296]	SELF     	6 6 -6	; "gsub"
	83	[296]	LOADK    	8 -18	; "%.[^.]+$"
	84	[296]	LOADK    	9 -8	; ""
	85	[296]	CALL     	6 4 2
	86	[296]	MOVE     	1 6
	87	[299]	TEST     	1 0 1
	88	[299]	JMP      	8	; to 97
	89	[300]	LOADNIL  	6 6
	90	[300]	LOADK    	7 -19	; "Could not infer rock name. "
	91	[300]	GETUPVAL 	8 2	; util
	92	[300]	GETTABLE 	8 8 -20	; "see_help"
	93	[300]	LOADK    	9 -21	; "write_rockspec"
	94	[300]	CALL     	8 2 2
	95	[300]	CONCAT   	7 7 8
	96	[300]	RETURN   	6 3
	97	[302]	TEST     	2 0 1
	98	[302]	JMP      	1	; to 100
	99	[302]	LOADK    	2 -22	; "dev"
	100	[304]	GETTABLE 	6 0 -23	; "output"
	101	[304]	TEST     	6 0 1
	102	[304]	JMP      	12	; to 115
	103	[304]	GETUPVAL 	6 0	; dir
	104	[304]	GETTABLE 	6 6 -24	; "path"
	105	[304]	GETUPVAL 	7 1	; fs
	106	[304]	GETTABLE 	7 7 -12	; "current_dir"
	107	[304]	CALL     	7 1 2
	108	[304]	SELF     	8 1 -25	; "lower"
	109	[304]	CALL     	8 2 2
	110	[304]	LOADK    	9 -26	; "-"
	111	[304]	MOVE     	10 2
	112	[304]	LOADK    	11 -27	; "-1.rockspec"
	113	[304]	CONCAT   	8 8 11
	114	[304]	CALL     	6 3 2
	115	[306]	GETUPVAL 	7 3	; detect_url
	116	[306]	MOVE     	8 3
	117	[306]	CALL     	7 2 2
	118	[307]	GETUPVAL 	8 4	; detect_homepage
	119	[307]	MOVE     	9 7
	120	[307]	GETTABLE 	10 0 -28	; "homepage"
	121	[307]	CALL     	8 3 2
	122	[309]	GETUPVAL 	9 5	; rockspecs
	123	[309]	GETTABLE 	9 9 -29	; "from_persisted_table"
	124	[309]	MOVE     	10 6
	125	[309]	NEWTABLE 	11 0 7
	126	[310]	GETTABLE 	12 0 -30	; "rockspec_format"
	127	[310]	SETTABLE 	11 -30 12	; "rockspec_format" -
	128	[311]	SETTABLE 	11 -31 1	; "package" -
	129	[312]	MOVE     	12 2
	130	[312]	LOADK    	13 -32	; "-1"
	131	[312]	CONCAT   	12 12 13
	132	[312]	SETTABLE 	11 -2 12	; "version" -
	133	[313]	NEWTABLE 	12 0 2
	134	[314]	SETTABLE 	12 -34 7	; "url" -
	135	[315]	GETTABLE 	13 0 -5	; "tag"
	136	[315]	SETTABLE 	12 -5 13	; "tag" -
	137	[316]	SETTABLE 	11 -33 12	; "source" -
	138	[317]	NEWTABLE 	12 0 4
	139	[318]	GETTABLE 	13 0 -36	; "summary"
	140	[318]	TEST     	13 0 1
	141	[318]	JMP      	1	; to 143
	142	[318]	LOADK    	13 -37	; "*** please specify description summary ***"
	143	[318]	SETTABLE 	12 -36 13	; "summary" -
	144	[319]	GETTABLE 	13 0 -38	; "detailed"
	145	[319]	TEST     	13 0 1
	146	[319]	JMP      	1	; to 148
	147	[319]	LOADK    	13 -39	; "*** please enter a detailed description ***"
	148	[319]	SETTABLE 	12 -38 13	; "detailed" -
	149	[320]	SETTABLE 	12 -28 8	; "homepage" -
	150	[321]	GETTABLE 	13 0 -40	; "license"
	151	[321]	TEST     	13 0 1
	152	[321]	JMP      	1	; to 154
	153	[321]	LOADK    	13 -41	; "*** please specify a license ***"
	154	[321]	SETTABLE 	12 -40 13	; "license" -
	155	[322]	SETTABLE 	11 -35 12	; "description" -
	156	[323]	NEWTABLE 	12 1 0
	157	[324]	GETUPVAL 	13 6	; lua_version_dep
	158	[324]	GETTABLE 	14 0 -43	; "lua_versions"
	159	[325]	GETTABLE 	13 13 14
	160	[325]	SETLIST  	12 1 1	; 1
	161	[325]	SETTABLE 	11 -42 12	; "dependencies" -
	162	[326]	NEWTABLE 	12 0 0
	163	[326]	SETTABLE 	11 -44 12	; "build" -
	164	[309]	CALL     	9 3 3
	165	[328]	GETGLOBAL	11 -45	; assert
	166	[328]	NOT      	12 10
	167	[328]	MOVE     	13 10
	168	[328]	CALL     	11 3 1
	169	[329]	GETTABLE 	11 9 -33	; "source"
	170	[329]	SETTABLE 	11 -46 4	; "protocol" -
	171	[331]	GETGLOBAL	11 -47	; next
	172	[331]	GETTABLE 	12 9 -42	; "dependencies"
	173	[331]	CALL     	11 2 2
	174	[331]	TEST     	11 0 1
	175	[331]	JMP      	9	; to 185
	176	[332]	GETUPVAL 	11 2	; util
	177	[332]	GETTABLE 	11 11 -48	; "warning"
	178	[332]	LOADK    	12 -49	; "Please specify supported Lua versions with --lua-versions=<ver>. "
	179	[332]	GETUPVAL 	13 2	; util
	180	[332]	GETTABLE 	13 13 -20	; "see_help"
	181	[332]	LOADK    	14 -21	; "write_rockspec"
	182	[332]	CALL     	13 2 2
	183	[332]	CONCAT   	12 12 13
	184	[332]	CALL     	11 2 1
	185	[335]	MOVE     	11 3
	186	[337]	SELF     	12 3 -14	; "match"
	187	[337]	LOADK    	14 -50	; "://"
	188	[337]	CALL     	12 3 2
	189	[337]	TEST     	12 0 0
	190	[337]	JMP      	48	; to 239
	191	[338]	GETTABLE 	12 9 -33	; "source"
	192	[338]	GETUPVAL 	13 0	; dir
	193	[338]	GETTABLE 	13 13 -11	; "base_name"
	194	[338]	MOVE     	14 3
	195	[338]	CALL     	13 2 2
	196	[338]	SETTABLE 	12 -10 13	; "file" -
	197	[339]	GETUPVAL 	12 0	; dir
	198	[339]	GETTABLE 	12 12 -13	; "is_basic_protocol"
	199	[339]	GETTABLE 	13 9 -33	; "source"
	200	[339]	GETTABLE 	13 13 -46	; "protocol"
	201	[339]	CALL     	12 2 2
	202	[339]	TEST     	12 0 1
	203	[339]	JMP      	10	; to 214
	204	[340]	EQ       	1 2 -22	; - "dev"
	205	[340]	JMP      	8	; to 214
	206	[341]	GETTABLE 	12 9 -33	; "source"
	207	[341]	GETTABLE 	13 0 -5	; "tag"
	208	[341]	TEST     	13 0 1
	209	[341]	JMP      	3	; to 213
	210	[341]	LOADK    	13 -51	; "v"
	211	[341]	MOVE     	14 2
	212	[341]	CONCAT   	13 13 14
	213	[341]	SETTABLE 	12 -5 13	; "tag" -
	214	[344]	GETTABLE 	12 9 -33	; "source"
	215	[344]	SETTABLE 	12 -52 -53	; "dir" nil
	216	[345]	GETUPVAL 	12 7	; fetch_url
	217	[345]	MOVE     	13 9
	218	[345]	CALL     	12 2 4
	219	[346]	TEST     	12 0 0
	220	[346]	JMP      	8	; to 229
	221	[347]	GETUPVAL 	15 0	; dir
	222	[347]	GETTABLE 	15 15 -11	; "base_name"
	223	[347]	MOVE     	16 3
	224	[347]	CALL     	15 2 2
	225	[347]	EQ       	1 13 15
	226	[347]	JMP      	2	; to 229
	227	[348]	GETTABLE 	15 9 -33	; "source"
	228	[348]	SETTABLE 	15 -52 13	; "dir" -
	229	[351]	TEST     	13 0 0
	230	[351]	JMP      	7	; to 238
	231	[352]	GETUPVAL 	15 0	; dir
	232	[352]	GETTABLE 	15 15 -24	; "path"
	233	[352]	MOVE     	16 14
	234	[352]	MOVE     	17 13
	235	[352]	CALL     	15 3 2
	236	[352]	MOVE     	11 15
	237	[352]	JMP      	1	; to 239
	238	[354]	LOADNIL  	11 11
	239	[358]	TEST     	11 0 1
	240	[358]	JMP      	1	; to 242
	241	[359]	LOADK    	11 -4	; "."
	242	[362]	LOADNIL  	12 12
	243	[363]	GETTABLE 	13 0 -54	; "lib"
	244	[363]	TEST     	13 0 0
	245	[363]	JMP      	22	; to 268
	246	[364]	NEWTABLE 	13 0 0
	247	[364]	MOVE     	12 13
	248	[365]	NEWTABLE 	13 0 0
	249	[365]	SETTABLE 	9 -55 13	; "external_dependencies" -
	250	[366]	GETTABLE 	13 0 -54	; "lib"
	251	[366]	SELF     	13 13 -56	; "gmatch"
	252	[366]	LOADK    	15 -57	; "([^,]+)"
	253	[366]	CALL     	13 3 4
	254	[366]	JMP      	11	; to 266
	255	[367]	GETGLOBAL	17 -58	; table
	256	[367]	GETTABLE 	17 17 -59	; "insert"
	257	[367]	MOVE     	18 12
	258	[367]	MOVE     	19 16
	259	[367]	CALL     	17 3 1
	260	[368]	GETTABLE 	17 9 -55	; "external_dependencies"
	261	[368]	SELF     	18 16 -60	; "upper"
	262	[368]	CALL     	18 2 2
	263	[368]	NEWTABLE 	19 0 1
	264	[369]	SETTABLE 	19 -61 16	; "library" -
	265	[370]	SETTABLE 	17 18 19
	266	[366]	TFORLOOP 	13 1
	267	[370]	JMP      	-13	; to 255
	268	[374]	GETUPVAL 	13 1	; fs
	269	[374]	GETTABLE 	13 13 -62	; "change_dir"
	270	[374]	MOVE     	14 11
	271	[374]	CALL     	13 2 3
	272	[375]	TEST     	13 0 1
	273	[375]	JMP      	5	; to 279
	274	[375]	LOADNIL  	15 15
	275	[375]	LOADK    	16 -63	; "Failed reaching files from project - error entering directory "
	276	[375]	MOVE     	17 11
	277	[375]	CONCAT   	16 16 17
	278	[375]	RETURN   	15 3
	279	[377]	GETTABLE 	15 0 -36	; "summary"
	280	[377]	TEST     	15 0 0
	281	[377]	JMP      	3	; to 285
	282	[377]	GETTABLE 	15 0 -38	; "detailed"
	283	[377]	TEST     	15 0 1
	284	[377]	JMP      	14	; to 299
	285	[378]	GETUPVAL 	15 8	; detect_description
	286	[378]	CALL     	15 1 3
	287	[379]	GETTABLE 	17 9 -35	; "description"
	288	[379]	GETTABLE 	18 0 -36	; "summary"
	289	[379]	TEST     	18 0 1
	290	[379]	JMP      	1	; to 292
	291	[379]	MOVE     	18 15
	292	[379]	SETTABLE 	17 -36 18	; "summary" -
	293	[380]	GETTABLE 	17 9 -35	; "description"
	294	[380]	GETTABLE 	18 0 -38	; "detailed"
	295	[380]	TEST     	18 0 1
	296	[380]	JMP      	1	; to 298
	297	[380]	MOVE     	18 16
	298	[380]	SETTABLE 	17 -38 18	; "detailed" -
	299	[383]	GETTABLE 	15 0 -40	; "license"
	300	[383]	TEST     	15 0 1
	301	[383]	JMP      	24	; to 326
	302	[384]	GETUPVAL 	15 9	; check_license
	303	[384]	CALL     	15 1 3
	304	[385]	TEST     	15 0 0
	305	[385]	JMP      	3	; to 309
	306	[386]	GETTABLE 	17 9 -35	; "description"
	307	[386]	SETTABLE 	17 -40 15	; "license" -
	308	[386]	JMP      	17	; to 326
	309	[387]	TEST     	15 0 0
	310	[387]	JMP      	15	; to 326
	311	[388]	GETUPVAL 	17 2	; util
	312	[388]	GETTABLE 	17 17 -64	; "title"
	313	[388]	LOADK    	18 -65	; "Could not auto-detect type for project license:"
	314	[388]	CALL     	17 2 1
	315	[389]	GETUPVAL 	17 2	; util
	316	[389]	GETTABLE 	17 17 -66	; "printout"
	317	[389]	MOVE     	18 16
	318	[389]	CALL     	17 2 1
	319	[390]	GETUPVAL 	17 2	; util
	320	[390]	GETTABLE 	17 17 -66	; "printout"
	321	[390]	CALL     	17 1 1
	322	[391]	GETUPVAL 	17 2	; util
	323	[391]	GETTABLE 	17 17 -64	; "title"
	324	[391]	LOADK    	18 -67	; "Please fill in the source.license field manually or use --license."
	325	[391]	CALL     	17 2 1
	326	[395]	GETUPVAL 	15 10	; fill_as_builtin
	327	[395]	MOVE     	16 9
	328	[395]	MOVE     	17 12
	329	[395]	CALL     	15 3 1
	330	[397]	GETUPVAL 	15 11	; rockspec_cleanup
	331	[397]	MOVE     	16 9
	332	[397]	CALL     	15 2 1
	333	[399]	GETUPVAL 	15 12	; persist
	334	[399]	GETTABLE 	15 15 -68	; "save_from_table"
	335	[399]	MOVE     	16 6
	336	[399]	MOVE     	17 9
	337	[399]	GETUPVAL 	18 13	; type_rockspec
	338	[399]	GETTABLE 	18 18 -69	; "order"
	339	[399]	CALL     	15 4 1
	340	[401]	GETUPVAL 	15 2	; util
	341	[401]	GETTABLE 	15 15 -66	; "printout"
	342	[401]	CALL     	15 1 1
	343	[402]	GETUPVAL 	15 2	; util
	344	[402]	GETTABLE 	15 15 -66	; "printout"
	345	[402]	LOADK    	16 -70	; "Wrote template at "
	346	[402]	MOVE     	17 6
	347	[402]	LOADK    	18 -71	; " -- you should now edit and finish it."
	348	[402]	CONCAT   	16 16 18
	349	[402]	CALL     	15 2 1
	350	[403]	GETUPVAL 	15 2	; util
	351	[403]	GETTABLE 	15 15 -66	; "printout"
	352	[403]	CALL     	15 1 1
	353	[405]	LOADBOOL 	15 1 0
	354	[405]	RETURN   	15 2
	355	[406]	RETURN   	0 1
