
main <./manif/writer.lua:0,0> (114 instructions, 456 bytes at 0x7faa234068a0)
0+ params, 23 slots, 0 upvalues, 22 locals, 20 constants, 14 functions
	1	[2]	NEWTABLE 	0 0 0
	2	[4]	GETGLOBAL	1 -1	; require
	3	[4]	LOADK    	2 -2	; "luarocks.core.cfg"
	4	[4]	CALL     	1 2 2
	5	[5]	GETGLOBAL	2 -1	; require
	6	[5]	LOADK    	3 -3	; "luarocks.search"
	7	[5]	CALL     	2 2 2
	8	[6]	GETGLOBAL	3 -1	; require
	9	[6]	LOADK    	4 -4	; "luarocks.repos"
	10	[6]	CALL     	3 2 2
	11	[7]	GETGLOBAL	4 -1	; require
	12	[7]	LOADK    	5 -5	; "luarocks.deps"
	13	[7]	CALL     	4 2 2
	14	[8]	GETGLOBAL	5 -1	; require
	15	[8]	LOADK    	6 -6	; "luarocks.core.vers"
	16	[8]	CALL     	5 2 2
	17	[9]	GETGLOBAL	6 -1	; require
	18	[9]	LOADK    	7 -7	; "luarocks.fs"
	19	[9]	CALL     	6 2 2
	20	[10]	GETGLOBAL	7 -1	; require
	21	[10]	LOADK    	8 -8	; "luarocks.util"
	22	[10]	CALL     	7 2 2
	23	[11]	GETGLOBAL	8 -1	; require
	24	[11]	LOADK    	9 -9	; "luarocks.dir"
	25	[11]	CALL     	8 2 2
	26	[12]	GETGLOBAL	9 -1	; require
	27	[12]	LOADK    	10 -10	; "luarocks.fetch"
	28	[12]	CALL     	9 2 2
	29	[13]	GETGLOBAL	10 -1	; require
	30	[13]	LOADK    	11 -11	; "luarocks.path"
	31	[13]	CALL     	10 2 2
	32	[14]	GETGLOBAL	11 -1	; require
	33	[14]	LOADK    	12 -12	; "luarocks.persist"
	34	[14]	CALL     	11 2 2
	35	[15]	GETGLOBAL	12 -1	; require
	36	[15]	LOADK    	13 -13	; "luarocks.manif"
	37	[15]	CALL     	12 2 2
	38	[16]	GETGLOBAL	13 -1	; require
	39	[16]	LOADK    	14 -14	; "luarocks.queries"
	40	[16]	CALL     	13 2 2
	41	[40]	CLOSURE  	14 0	; 0x7faa23406fd0
	42	[71]	CLOSURE  	15 1	; 0x7faa23407200
	43	[96]	CLOSURE  	16 2	; 0x7faa23407680
	44	[96]	MOVE     	0 4
	45	[115]	CLOSURE  	17 3	; 0x7faa234079c0
	46	[115]	MOVE     	0 5
	47	[142]	CLOSURE  	18 4	; 0x7faa23408a20
	48	[142]	MOVE     	0 17
	49	[192]	CLOSURE  	19 5	; 0x7faa23408ee0
	50	[192]	MOVE     	0 5
	51	[192]	MOVE     	0 8
	52	[192]	MOVE     	0 9
	53	[192]	MOVE     	0 7
	54	[228]	CLOSURE  	20 6	; 0x7faa23409530
	55	[228]	MOVE     	0 12
	56	[228]	MOVE     	0 3
	57	[228]	MOVE     	0 14
	58	[228]	MOVE     	0 18
	59	[247]	CLOSURE  	21 7	; 0x7faa234097d0
	60	[247]	MOVE     	0 8
	61	[247]	MOVE     	0 11
	62	[247]	MOVE     	0 6
	63	[279]	CLOSURE  	22 8	; 0x7faa2340a570
	64	[279]	MOVE     	0 10
	65	[279]	MOVE     	0 6
	66	[279]	MOVE     	0 8
	67	[279]	MOVE     	0 12
	68	[279]	MOVE     	0 21
	69	[249]	SETTABLE 	0 -15 22	; "make_rock_manifest" -
	70	[304]	CLOSURE  	22 9	; 0x7faa23407080
	71	[304]	MOVE     	0 10
	72	[287]	SETTABLE 	0 -16 22	; "make_namespace_file" -
	73	[354]	CLOSURE  	22 10	; 0x7faa23406640
	74	[354]	MOVE     	0 1
	75	[354]	MOVE     	0 6
	76	[354]	MOVE     	0 13
	77	[354]	MOVE     	0 2
	78	[354]	MOVE     	0 12
	79	[354]	MOVE     	0 20
	80	[354]	MOVE     	0 7
	81	[354]	MOVE     	0 19
	82	[354]	MOVE     	0 21
	83	[354]	MOVE     	0 16
	84	[316]	SETTABLE 	0 -17 22	; "make_manifest" -
	85	[395]	CLOSURE  	22 11	; 0x7faa2340c2c0
	86	[395]	MOVE     	0 10
	87	[395]	MOVE     	0 1
	88	[395]	MOVE     	0 12
	89	[395]	MOVE     	0 7
	90	[395]	MOVE     	0 0
	91	[395]	MOVE     	0 20
	92	[395]	MOVE     	0 16
	93	[395]	MOVE     	0 21
	94	[367]	SETTABLE 	0 -18 22	; "add_to_manifest" -
	95	[454]	CLOSURE  	22 12	; 0x7faa2340bc00
	96	[454]	MOVE     	0 10
	97	[454]	MOVE     	0 1
	98	[454]	MOVE     	0 12
	99	[454]	MOVE     	0 7
	100	[454]	MOVE     	0 0
	101	[454]	MOVE     	0 15
	102	[454]	MOVE     	0 16
	103	[454]	MOVE     	0 21
	104	[408]	SETTABLE 	0 -19 22	; "remove_from_manifest" -
	105	[483]	CLOSURE  	22 13	; 0x7faa2340d730
	106	[483]	MOVE     	0 10
	107	[483]	MOVE     	0 1
	108	[483]	MOVE     	0 12
	109	[483]	MOVE     	0 7
	110	[483]	MOVE     	0 5
	111	[483]	MOVE     	0 4
	112	[462]	SETTABLE 	0 -20 22	; "check_dependencies" -
	113	[485]	RETURN   	0 2
	114	[485]	RETURN   	0 1

function <./manif/writer.lua:25,40> (62 instructions, 248 bytes at 0x7faa23406fd0)
4 params, 13 slots, 0 upvalues, 10 locals, 8 constants, 0 functions
	1	[26]	GETGLOBAL	4 -1	; assert
	2	[26]	GETGLOBAL	5 -2	; type
	3	[26]	MOVE     	6 0
	4	[26]	CALL     	5 2 2
	5	[26]	EQ       	1 5 -3	; - "table"
	6	[26]	JMP      	1	; to 8
	7	[26]	LOADBOOL 	5 0 1
	8	[26]	LOADBOOL 	5 1 0
	9	[26]	CALL     	4 2 1
	10	[27]	GETGLOBAL	4 -1	; assert
	11	[27]	GETGLOBAL	5 -2	; type
	12	[27]	MOVE     	6 3
	13	[27]	CALL     	5 2 2
	14	[27]	EQ       	1 5 -3	; - "table"
	15	[27]	JMP      	1	; to 17
	16	[27]	LOADBOOL 	5 0 1
	17	[27]	LOADBOOL 	5 1 0
	18	[27]	CALL     	4 2 1
	19	[28]	GETGLOBAL	4 -1	; assert
	20	[28]	GETGLOBAL	5 -2	; type
	21	[28]	MOVE     	6 1
	22	[28]	CALL     	5 2 2
	23	[28]	EQ       	0 5 -4	; - "string"
	24	[28]	JMP      	5	; to 30
	25	[28]	SELF     	5 1 -5	; "match"
	26	[28]	LOADK    	7 -6	; "/"
	27	[28]	CALL     	5 3 2
	28	[28]	NOT      	5 5
	29	[28]	JMP      	2	; to 32
	30	[28]	LOADBOOL 	5 0 1
	31	[28]	LOADBOOL 	5 1 0
	32	[28]	CALL     	4 2 1
	33	[29]	GETGLOBAL	4 -1	; assert
	34	[29]	GETGLOBAL	5 -2	; type
	35	[29]	MOVE     	6 2
	36	[29]	CALL     	5 2 2
	37	[29]	EQ       	1 5 -4	; - "string"
	38	[29]	JMP      	1	; to 40
	39	[29]	LOADBOOL 	5 0 1
	40	[29]	LOADBOOL 	5 1 0
	41	[29]	CALL     	4 2 1
	42	[31]	MOVE     	4 1
	43	[31]	LOADK    	5 -6	; "/"
	44	[31]	MOVE     	6 2
	45	[31]	CONCAT   	4 4 6
	46	[33]	GETGLOBAL	5 -7	; pairs
	47	[33]	MOVE     	6 3
	48	[33]	CALL     	5 2 4
	49	[33]	JMP      	10	; to 60
	50	[34]	GETTABLE 	10 0 8
	51	[34]	TEST     	10 0 1
	52	[34]	JMP      	2	; to 55
	53	[35]	NEWTABLE 	10 0 0
	54	[35]	SETTABLE 	0 8 10
	55	[38]	GETGLOBAL	10 -3	; table
	56	[38]	GETTABLE 	10 10 -8	; "insert"
	57	[38]	GETTABLE 	11 0 8
	58	[38]	MOVE     	12 4
	59	[38]	CALL     	10 3 1
	60	[33]	TFORLOOP 	5 2
	61	[38]	JMP      	-12	; to 50
	62	[40]	RETURN   	0 1

function <./manif/writer.lua:49,71> (71 instructions, 284 bytes at 0x7faa23407200)
4 params, 19 slots, 0 upvalues, 16 locals, 11 constants, 0 functions
	1	[50]	GETGLOBAL	4 -1	; assert
	2	[50]	GETGLOBAL	5 -2	; type
	3	[50]	MOVE     	6 0
	4	[50]	CALL     	5 2 2
	5	[50]	EQ       	1 5 -3	; - "table"
	6	[50]	JMP      	1	; to 8
	7	[50]	LOADBOOL 	5 0 1
	8	[50]	LOADBOOL 	5 1 0
	9	[50]	CALL     	4 2 1
	10	[51]	GETGLOBAL	4 -1	; assert
	11	[51]	GETGLOBAL	5 -2	; type
	12	[51]	MOVE     	6 3
	13	[51]	CALL     	5 2 2
	14	[51]	EQ       	1 5 -3	; - "table"
	15	[51]	JMP      	1	; to 17
	16	[51]	LOADBOOL 	5 0 1
	17	[51]	LOADBOOL 	5 1 0
	18	[51]	CALL     	4 2 1
	19	[52]	GETGLOBAL	4 -1	; assert
	20	[52]	GETGLOBAL	5 -2	; type
	21	[52]	MOVE     	6 1
	22	[52]	CALL     	5 2 2
	23	[52]	EQ       	0 5 -4	; - "string"
	24	[52]	JMP      	5	; to 30
	25	[52]	SELF     	5 1 -5	; "match"
	26	[52]	LOADK    	7 -6	; "/"
	27	[52]	CALL     	5 3 2
	28	[52]	NOT      	5 5
	29	[52]	JMP      	2	; to 32
	30	[52]	LOADBOOL 	5 0 1
	31	[52]	LOADBOOL 	5 1 0
	32	[52]	CALL     	4 2 1
	33	[53]	GETGLOBAL	4 -1	; assert
	34	[53]	GETGLOBAL	5 -2	; type
	35	[53]	MOVE     	6 2
	36	[53]	CALL     	5 2 2
	37	[53]	EQ       	1 5 -4	; - "string"
	38	[53]	JMP      	1	; to 40
	39	[53]	LOADBOOL 	5 0 1
	40	[53]	LOADBOOL 	5 1 0
	41	[53]	CALL     	4 2 1
	42	[55]	MOVE     	4 1
	43	[55]	LOADK    	5 -6	; "/"
	44	[55]	MOVE     	6 2
	45	[55]	CONCAT   	4 4 6
	46	[57]	GETGLOBAL	5 -7	; pairs
	47	[57]	MOVE     	6 3
	48	[57]	CALL     	5 2 4
	49	[57]	JMP      	19	; to 69
	50	[58]	GETTABLE 	10 0 8
	51	[60]	GETGLOBAL	11 -8	; ipairs
	52	[60]	MOVE     	12 10
	53	[60]	CALL     	11 2 4
	54	[60]	JMP      	8	; to 63
	55	[61]	EQ       	0 15 4
	56	[61]	JMP      	6	; to 63
	57	[62]	GETGLOBAL	16 -3	; table
	58	[62]	GETTABLE 	16 16 -9	; "remove"
	59	[62]	MOVE     	17 10
	60	[62]	MOVE     	18 14
	61	[62]	CALL     	16 3 1
	62	[63]	JMP      	2	; to 65
	63	[60]	TFORLOOP 	11 2
	64	[64]	JMP      	-10	; to 55
	65	[67]	LEN      	11 10
	66	[67]	EQ       	0 11 -10	; - 0
	67	[67]	JMP      	1	; to 69
	68	[68]	SETTABLE 	0 8 -11	; - nil
	69	[57]	TFORLOOP 	5 2
	70	[69]	JMP      	-21	; to 50
	71	[71]	RETURN   	0 1

function <./manif/writer.lua:81,96> (52 instructions, 208 bytes at 0x7faa23407680)
2 params, 23 slots, 1 upvalue, 17 locals, 12 constants, 0 functions
	1	[82]	GETGLOBAL	2 -1	; assert
	2	[82]	GETGLOBAL	3 -2	; type
	3	[82]	MOVE     	4 0
	4	[82]	CALL     	3 2 2
	5	[82]	EQ       	1 3 -3	; - "table"
	6	[82]	JMP      	1	; to 8
	7	[82]	LOADBOOL 	3 0 1
	8	[82]	LOADBOOL 	3 1 0
	9	[82]	CALL     	2 2 1
	10	[83]	GETGLOBAL	2 -1	; assert
	11	[83]	GETGLOBAL	3 -2	; type
	12	[83]	MOVE     	4 1
	13	[83]	CALL     	3 2 2
	14	[83]	EQ       	1 3 -4	; - "string"
	15	[83]	JMP      	1	; to 17
	16	[83]	LOADBOOL 	3 0 1
	17	[83]	LOADBOOL 	3 1 0
	18	[83]	CALL     	2 2 1
	19	[85]	GETGLOBAL	2 -5	; pairs
	20	[85]	GETTABLE 	3 0 -6	; "repository"
	21	[85]	CALL     	2 2 4
	22	[85]	JMP      	27	; to 50
	23	[86]	GETGLOBAL	7 -5	; pairs
	24	[86]	MOVE     	8 6
	25	[86]	CALL     	7 2 4
	26	[86]	JMP      	21	; to 48
	27	[87]	GETGLOBAL	12 -7	; ipairs
	28	[87]	MOVE     	13 11
	29	[87]	CALL     	12 2 4
	30	[87]	JMP      	15	; to 46
	31	[88]	GETTABLE 	17 16 -8	; "arch"
	32	[88]	EQ       	0 17 -9	; - "installed"
	33	[88]	JMP      	12	; to 46
	34	[89]	NEWTABLE 	17 0 0
	35	[89]	SETTABLE 	16 -10 17	; "dependencies" -
	36	[90]	GETUPVAL 	17 0	; deps
	37	[90]	GETTABLE 	17 17 -11	; "scan_deps"
	38	[90]	GETTABLE 	18 16 -10	; "dependencies"
	39	[90]	MOVE     	19 0
	40	[90]	MOVE     	20 5
	41	[90]	MOVE     	21 10
	42	[90]	MOVE     	22 1
	43	[90]	CALL     	17 6 1
	44	[91]	GETTABLE 	17 16 -10	; "dependencies"
	45	[91]	SETTABLE 	17 5 -12	; - nil
	46	[87]	TFORLOOP 	12 2
	47	[92]	JMP      	-17	; to 31
	48	[86]	TFORLOOP 	7 2
	49	[93]	JMP      	-23	; to 27
	50	[85]	TFORLOOP 	2 2
	51	[94]	JMP      	-29	; to 23
	52	[96]	RETURN   	0 1

function <./manif/writer.lua:107,115> (39 instructions, 156 bytes at 0x7faa234079c0)
2 params, 9 slots, 1 upvalue, 6 locals, 6 constants, 0 functions
	1	[108]	GETGLOBAL	2 -1	; assert
	2	[108]	GETGLOBAL	3 -2	; type
	3	[108]	MOVE     	4 0
	4	[108]	CALL     	3 2 2
	5	[108]	EQ       	1 3 -3	; - "string"
	6	[108]	JMP      	1	; to 8
	7	[108]	LOADBOOL 	3 0 1
	8	[108]	LOADBOOL 	3 1 0
	9	[108]	CALL     	2 2 1
	10	[109]	GETGLOBAL	2 -1	; assert
	11	[109]	GETGLOBAL	3 -2	; type
	12	[109]	MOVE     	4 1
	13	[109]	CALL     	3 2 2
	14	[109]	EQ       	1 3 -3	; - "string"
	15	[109]	JMP      	1	; to 17
	16	[109]	LOADBOOL 	3 0 1
	17	[109]	LOADBOOL 	3 1 0
	18	[109]	CALL     	2 2 1
	19	[111]	SELF     	2 0 -4	; "match"
	20	[111]	LOADK    	4 -5	; "(.*)/(.*)$"
	21	[111]	CALL     	2 3 3
	22	[112]	SELF     	4 1 -4	; "match"
	23	[112]	LOADK    	6 -5	; "(.*)/(.*)$"
	24	[112]	CALL     	4 3 3
	25	[114]	EQ       	0 2 4
	26	[114]	JMP      	7	; to 34
	27	[114]	GETUPVAL 	6 0	; vers
	28	[114]	GETTABLE 	6 6 -6	; "compare_versions"
	29	[114]	MOVE     	7 3
	30	[114]	MOVE     	8 5
	31	[114]	CALL     	6 3 2
	32	[114]	TEST     	6 0 1
	33	[114]	JMP      	4	; to 38
	34	[114]	LT       	1 2 4
	35	[114]	JMP      	1	; to 37
	36	[114]	LOADBOOL 	6 0 1
	37	[114]	LOADBOOL 	6 1 0
	38	[114]	RETURN   	6 2
	39	[115]	RETURN   	0 1

function <./manif/writer.lua:120,142> (46 instructions, 184 bytes at 0x7faa23408a20)
1 param, 12 slots, 1 upvalue, 9 locals, 8 constants, 0 functions
	1	[121]	GETGLOBAL	1 -1	; assert
	2	[121]	GETGLOBAL	2 -2	; type
	3	[121]	MOVE     	3 0
	4	[121]	CALL     	2 2 2
	5	[121]	EQ       	1 2 -3	; - "table"
	6	[121]	JMP      	1	; to 8
	7	[121]	LOADBOOL 	2 0 1
	8	[121]	LOADBOOL 	2 1 0
	9	[121]	CALL     	1 2 1
	10	[123]	GETGLOBAL	1 -4	; next
	11	[123]	MOVE     	2 0
	12	[123]	CALL     	1 2 2
	13	[123]	TEST     	1 0 0
	14	[123]	JMP      	31	; to 46
	15	[124]	GETGLOBAL	1 -5	; pairs
	16	[124]	MOVE     	2 0
	17	[124]	CALL     	1 2 4
	18	[124]	JMP      	25	; to 44
	19	[125]	LEN      	6 5
	20	[125]	LT       	0 -6 6	; 1 -
	21	[125]	JMP      	22	; to 44
	22	[126]	GETGLOBAL	6 -3	; table
	23	[126]	GETTABLE 	6 6 -7	; "sort"
	24	[126]	MOVE     	7 5
	25	[126]	GETUPVAL 	8 0	; sort_pkgs
	26	[126]	CALL     	6 3 1
	27	[128]	LOADNIL  	6 6
	28	[129]	LOADK    	7 -6	; 1
	29	[130]	GETTABLE 	8 5 7
	30	[130]	TEST     	8 0 0
	31	[130]	JMP      	12	; to 44
	32	[131]	GETTABLE 	8 5 7
	33	[132]	EQ       	0 8 6
	34	[132]	JMP      	6	; to 41
	35	[133]	GETGLOBAL	9 -3	; table
	36	[133]	GETTABLE 	9 9 -8	; "remove"
	37	[133]	MOVE     	10 5
	38	[133]	MOVE     	11 7
	39	[133]	CALL     	9 3 1
	40	[133]	JMP      	-12	; to 29
	41	[135]	MOVE     	6 8
	42	[136]	ADD      	7 7 -6	; - 1
	43	[137]	JMP      	-15	; to 29
	44	[124]	TFORLOOP 	1 2
	45	[139]	JMP      	-27	; to 19
	46	[142]	RETURN   	0 1

function <./manif/writer.lua:150,192> (136 instructions, 544 bytes at 0x7faa23408ee0)
4 params, 31 slots, 4 upvalues, 33 locals, 26 constants, 0 functions
	1	[151]	GETGLOBAL	4 -1	; assert
	2	[151]	GETGLOBAL	5 -2	; type
	3	[151]	MOVE     	6 0
	4	[151]	CALL     	5 2 2
	5	[151]	EQ       	1 5 -3	; - "table"
	6	[151]	JMP      	1	; to 8
	7	[151]	LOADBOOL 	5 0 1
	8	[151]	LOADBOOL 	5 1 0
	9	[151]	CALL     	4 2 1
	10	[152]	GETGLOBAL	4 -1	; assert
	11	[152]	GETGLOBAL	5 -2	; type
	12	[152]	MOVE     	6 2
	13	[152]	CALL     	5 2 2
	14	[152]	EQ       	1 5 -4	; - "string"
	15	[152]	JMP      	1	; to 17
	16	[152]	LOADBOOL 	5 0 1
	17	[152]	LOADBOOL 	5 1 0
	18	[152]	CALL     	4 2 1
	19	[153]	GETGLOBAL	4 -1	; assert
	20	[153]	TEST     	3 0 0
	21	[153]	JMP      	6	; to 28
	22	[153]	GETGLOBAL	5 -2	; type
	23	[153]	MOVE     	6 3
	24	[153]	CALL     	5 2 2
	25	[153]	EQ       	1 5 -3	; - "table"
	26	[153]	JMP      	1	; to 28
	27	[153]	LOADBOOL 	5 0 1
	28	[153]	LOADBOOL 	5 1 0
	29	[153]	CALL     	4 2 1
	30	[155]	TEST     	3 0 1
	31	[155]	JMP      	2	; to 34
	32	[155]	NEWTABLE 	4 0 0
	33	[155]	MOVE     	3 4
	34	[156]	GETUPVAL 	4 0	; vers
	35	[156]	GETTABLE 	4 4 -5	; "parse_version"
	36	[156]	MOVE     	5 1
	37	[156]	CALL     	4 2 2
	38	[156]	MOVE     	1 4
	39	[157]	GETGLOBAL	4 -6	; pairs
	40	[157]	GETTABLE 	5 0 -7	; "repository"
	41	[157]	CALL     	4 2 4
	42	[157]	JMP      	91	; to 134
	43	[158]	NEWTABLE 	9 0 0
	44	[159]	GETGLOBAL	10 -6	; pairs
	45	[159]	MOVE     	11 8
	46	[159]	CALL     	10 2 4
	47	[159]	JMP      	65	; to 113
	48	[160]	GETGLOBAL	15 -8	; ipairs
	49	[160]	MOVE     	16 14
	50	[160]	CALL     	15 2 4
	51	[160]	JMP      	59	; to 111
	52	[161]	GETTABLE 	20 19 -9	; "arch"
	53	[161]	EQ       	0 20 -10	; - "rockspec"
	54	[161]	JMP      	56	; to 111
	55	[162]	GETUPVAL 	20 1	; dir
	56	[162]	GETTABLE 	20 20 -11	; "path"
	57	[162]	MOVE     	21 2
	58	[162]	MOVE     	22 7
	59	[162]	LOADK    	23 -12	; "-"
	60	[162]	MOVE     	24 13
	61	[162]	LOADK    	25 -13	; ".rockspec"
	62	[162]	CONCAT   	22 22 25
	63	[162]	CALL     	20 3 2
	64	[163]	GETTABLE 	21 3 20
	65	[163]	LOADNIL  	22 22
	66	[164]	TEST     	21 0 1
	67	[164]	JMP      	7	; to 75
	68	[165]	GETUPVAL 	23 2	; fetch
	69	[165]	GETTABLE 	23 23 -14	; "load_local_rockspec"
	70	[165]	MOVE     	24 20
	71	[165]	LOADBOOL 	25 1 0
	72	[165]	CALL     	23 3 3
	73	[165]	MOVE     	22 24
	74	[165]	MOVE     	21 23
	75	[167]	TEST     	21 0 0
	76	[167]	JMP      	24	; to 101
	77	[168]	SETTABLE 	3 20 21
	78	[169]	GETGLOBAL	23 -8	; ipairs
	79	[169]	GETTABLE 	24 21 -15	; "dependencies"
	80	[169]	CALL     	23 2 4
	81	[169]	JMP      	16	; to 98
	82	[170]	GETTABLE 	28 27 -16	; "name"
	83	[170]	EQ       	0 28 -17	; - "lua"
	84	[170]	JMP      	13	; to 98
	85	[171]	GETUPVAL 	28 0	; vers
	86	[171]	GETTABLE 	28 28 -18	; "match_constraints"
	87	[171]	MOVE     	29 1
	88	[171]	GETTABLE 	30 27 -19	; "constraints"
	89	[171]	CALL     	28 3 2
	90	[171]	TEST     	28 0 1
	91	[171]	JMP      	19	; to 111
	92	[172]	GETGLOBAL	28 -3	; table
	93	[172]	GETTABLE 	28 28 -20	; "insert"
	94	[172]	MOVE     	29 9
	95	[172]	MOVE     	30 13
	96	[172]	CALL     	28 3 1
	97	[174]	JMP      	13	; to 111
	98	[169]	TFORLOOP 	23 2
	99	[175]	JMP      	-18	; to 82
	100	[176]	JMP      	10	; to 111
	101	[178]	GETUPVAL 	23 3	; util
	102	[178]	GETTABLE 	23 23 -21	; "printerr"
	103	[178]	LOADK    	24 -22	; "Error loading rockspec for "
	104	[178]	MOVE     	25 7
	105	[178]	LOADK    	26 -23	; " "
	106	[178]	MOVE     	27 13
	107	[178]	LOADK    	28 -24	; ": "
	108	[178]	MOVE     	29 22
	109	[178]	CONCAT   	24 24 29
	110	[178]	CALL     	23 2 1
	111	[160]	TFORLOOP 	15 2
	112	[180]	JMP      	-61	; to 52
	113	[159]	TFORLOOP 	10 2
	114	[181]	JMP      	-67	; to 48
	115	[183]	GETGLOBAL	10 -25	; next
	116	[183]	MOVE     	11 9
	117	[183]	CALL     	10 2 2
	118	[183]	TEST     	10 0 0
	119	[183]	JMP      	14	; to 134
	120	[184]	GETGLOBAL	10 -8	; ipairs
	121	[184]	MOVE     	11 9
	122	[184]	CALL     	10 2 4
	123	[184]	JMP      	1	; to 125
	124	[185]	SETTABLE 	8 14 -26	; - nil
	125	[184]	TFORLOOP 	10 2
	126	[185]	JMP      	-3	; to 124
	127	[187]	GETGLOBAL	10 -25	; next
	128	[187]	MOVE     	11 8
	129	[187]	CALL     	10 2 2
	130	[187]	TEST     	10 0 1
	131	[187]	JMP      	2	; to 134
	132	[188]	GETTABLE 	10 0 -7	; "repository"
	133	[188]	SETTABLE 	10 7 -26	; - nil
	134	[157]	TFORLOOP 	4 2
	135	[190]	JMP      	-93	; to 43
	136	[192]	RETURN   	0 1

function <./manif/writer.lua:199,228> (99 instructions, 396 bytes at 0x7faa23409530)
2 params, 27 slots, 4 upvalues, 22 locals, 14 constants, 0 functions
	1	[200]	GETGLOBAL	2 -1	; assert
	2	[200]	GETGLOBAL	3 -2	; type
	3	[200]	MOVE     	4 0
	4	[200]	CALL     	3 2 2
	5	[200]	EQ       	1 3 -3	; - "table"
	6	[200]	JMP      	1	; to 8
	7	[200]	LOADBOOL 	3 0 1
	8	[200]	LOADBOOL 	3 1 0
	9	[200]	CALL     	2 2 1
	10	[201]	GETGLOBAL	2 -1	; assert
	11	[201]	GETGLOBAL	3 -2	; type
	12	[201]	MOVE     	4 1
	13	[201]	CALL     	3 2 2
	14	[201]	EQ       	1 3 -3	; - "table"
	15	[201]	JMP      	1	; to 17
	16	[201]	LOADBOOL 	3 0 1
	17	[201]	LOADBOOL 	3 1 0
	18	[201]	CALL     	2 2 1
	19	[203]	GETGLOBAL	2 -4	; pairs
	20	[203]	MOVE     	3 0
	21	[203]	CALL     	2 2 4
	22	[203]	JMP      	66	; to 89
	23	[204]	GETTABLE 	7 1 -5	; "repository"
	24	[204]	GETTABLE 	7 7 5
	25	[204]	TEST     	7 0 1
	26	[204]	JMP      	1	; to 28
	27	[204]	NEWTABLE 	7 0 0
	28	[205]	GETGLOBAL	8 -4	; pairs
	29	[205]	MOVE     	9 6
	30	[205]	CALL     	8 2 4
	31	[205]	JMP      	53	; to 85
	32	[206]	NEWTABLE 	13 0 0
	33	[207]	GETGLOBAL	14 -6	; ipairs
	34	[207]	MOVE     	15 12
	35	[207]	CALL     	14 2 4
	36	[207]	JMP      	45	; to 82
	37	[208]	NEWTABLE 	19 0 0
	38	[209]	GETTABLE 	20 18 -7	; "arch"
	39	[209]	SETTABLE 	19 -7 20	; "arch" -
	40	[210]	GETTABLE 	20 18 -7	; "arch"
	41	[210]	EQ       	0 20 -8	; - "installed"
	42	[210]	JMP      	34	; to 77
	43	[211]	GETUPVAL 	20 0	; manif
	44	[211]	GETTABLE 	20 20 -9	; "load_rock_manifest"
	45	[211]	MOVE     	21 5
	46	[211]	MOVE     	22 11
	47	[211]	CALL     	20 3 3
	48	[212]	TEST     	20 0 1
	49	[212]	JMP      	3	; to 53
	50	[212]	LOADNIL  	22 22
	51	[212]	MOVE     	23 21
	52	[212]	RETURN   	22 3
	53	[214]	GETUPVAL 	22 1	; repos
	54	[214]	GETTABLE 	22 22 -11	; "package_modules"
	55	[214]	MOVE     	23 5
	56	[214]	MOVE     	24 11
	57	[214]	CALL     	22 3 2
	58	[214]	SETTABLE 	19 -10 22	; "modules" -
	59	[215]	GETUPVAL 	22 2	; store_package_items
	60	[215]	GETTABLE 	23 1 -10	; "modules"
	61	[215]	MOVE     	24 5
	62	[215]	MOVE     	25 11
	63	[215]	GETTABLE 	26 19 -10	; "modules"
	64	[215]	CALL     	22 5 1
	65	[216]	GETUPVAL 	22 1	; repos
	66	[216]	GETTABLE 	22 22 -13	; "package_commands"
	67	[216]	MOVE     	23 5
	68	[216]	MOVE     	24 11
	69	[216]	CALL     	22 3 2
	70	[216]	SETTABLE 	19 -12 22	; "commands" -
	71	[217]	GETUPVAL 	22 2	; store_package_items
	72	[217]	GETTABLE 	23 1 -12	; "commands"
	73	[217]	MOVE     	24 5
	74	[217]	MOVE     	25 11
	75	[217]	GETTABLE 	26 19 -12	; "commands"
	76	[217]	CALL     	22 5 1
	77	[219]	GETGLOBAL	20 -3	; table
	78	[219]	GETTABLE 	20 20 -14	; "insert"
	79	[219]	MOVE     	21 13
	80	[219]	MOVE     	22 19
	81	[219]	CALL     	20 3 1
	82	[207]	TFORLOOP 	14 2
	83	[219]	JMP      	-47	; to 37
	84	[221]	SETTABLE 	7 11 13
	85	[205]	TFORLOOP 	8 2
	86	[221]	JMP      	-55	; to 32
	87	[223]	GETTABLE 	8 1 -5	; "repository"
	88	[223]	SETTABLE 	8 5 7
	89	[203]	TFORLOOP 	2 2
	90	[223]	JMP      	-68	; to 23
	91	[225]	GETUPVAL 	2 3	; sort_package_matching_table
	92	[225]	GETTABLE 	3 1 -10	; "modules"
	93	[225]	CALL     	2 2 1
	94	[226]	GETUPVAL 	2 3	; sort_package_matching_table
	95	[226]	GETTABLE 	3 1 -12	; "commands"
	96	[226]	CALL     	2 2 1
	97	[227]	LOADBOOL 	2 1 0
	98	[227]	RETURN   	2 2
	99	[228]	RETURN   	0 1

function <./manif/writer.lua:236,247> (59 instructions, 236 bytes at 0x7faa234097d0)
3 params, 10 slots, 3 upvalues, 6 locals, 10 constants, 0 functions
	1	[237]	GETGLOBAL	3 -1	; assert
	2	[237]	GETGLOBAL	4 -2	; type
	3	[237]	MOVE     	5 0
	4	[237]	CALL     	4 2 2
	5	[237]	EQ       	1 4 -3	; - "string"
	6	[237]	JMP      	1	; to 8
	7	[237]	LOADBOOL 	4 0 1
	8	[237]	LOADBOOL 	4 1 0
	9	[237]	CALL     	3 2 1
	10	[238]	GETGLOBAL	3 -1	; assert
	11	[238]	GETGLOBAL	4 -2	; type
	12	[238]	MOVE     	5 1
	13	[238]	CALL     	4 2 2
	14	[238]	EQ       	0 4 -3	; - "string"
	15	[238]	JMP      	5	; to 21
	16	[238]	SELF     	4 1 -4	; "match"
	17	[238]	LOADK    	6 -5	; "/"
	18	[238]	CALL     	4 3 2
	19	[238]	NOT      	4 4
	20	[238]	JMP      	2	; to 23
	21	[238]	LOADBOOL 	4 0 1
	22	[238]	LOADBOOL 	4 1 0
	23	[238]	CALL     	3 2 1
	24	[239]	GETGLOBAL	3 -1	; assert
	25	[239]	GETGLOBAL	4 -2	; type
	26	[239]	MOVE     	5 2
	27	[239]	CALL     	4 2 2
	28	[239]	EQ       	1 4 -6	; - "table"
	29	[239]	JMP      	1	; to 31
	30	[239]	LOADBOOL 	4 0 1
	31	[239]	LOADBOOL 	4 1 0
	32	[239]	CALL     	3 2 1
	33	[241]	GETUPVAL 	3 0	; dir
	34	[241]	GETTABLE 	3 3 -7	; "path"
	35	[241]	MOVE     	4 0
	36	[241]	MOVE     	5 1
	37	[241]	CALL     	3 3 2
	38	[242]	GETUPVAL 	4 1	; persist
	39	[242]	GETTABLE 	4 4 -8	; "save_from_table"
	40	[242]	MOVE     	5 3
	41	[242]	LOADK    	6 -9	; ".tmp"
	42	[242]	CONCAT   	5 5 6
	43	[242]	MOVE     	6 2
	44	[242]	CALL     	4 3 3
	45	[243]	TEST     	4 0 0
	46	[243]	JMP      	9	; to 56
	47	[244]	GETUPVAL 	6 2	; fs
	48	[244]	GETTABLE 	6 6 -10	; "replace_file"
	49	[244]	MOVE     	7 3
	50	[244]	MOVE     	8 3
	51	[244]	LOADK    	9 -9	; ".tmp"
	52	[244]	CONCAT   	8 8 9
	53	[244]	CALL     	6 3 3
	54	[244]	MOVE     	5 7
	55	[244]	MOVE     	4 6
	56	[246]	MOVE     	6 4
	57	[246]	MOVE     	7 5
	58	[246]	RETURN   	6 3
	59	[247]	RETURN   	0 1

function <./manif/writer.lua:249,279> (74 instructions, 296 bytes at 0x7faa2340a570)
2 params, 19 slots, 5 upvalues, 21 locals, 13 constants, 0 functions
	1	[250]	GETUPVAL 	2 0	; path
	2	[250]	GETTABLE 	2 2 -1	; "install_dir"
	3	[250]	MOVE     	3 0
	4	[250]	MOVE     	4 1
	5	[250]	CALL     	2 3 2
	6	[251]	NEWTABLE 	3 0 0
	7	[252]	GETGLOBAL	4 -2	; ipairs
	8	[252]	GETUPVAL 	5 1	; fs
	9	[252]	GETTABLE 	5 5 -3	; "find"
	10	[252]	MOVE     	6 2
	11	[252]	CALL     	5 2 0
	12	[252]	CALL     	4 0 4
	13	[252]	JMP      	42	; to 56
	14	[253]	GETUPVAL 	9 2	; dir
	15	[253]	GETTABLE 	9 9 -4	; "path"
	16	[253]	MOVE     	10 2
	17	[253]	MOVE     	11 8
	18	[253]	CALL     	9 3 2
	19	[254]	MOVE     	10 3
	20	[255]	LOADNIL  	11 12
	21	[257]	SELF     	13 8 -5	; "gmatch"
	22	[257]	LOADK    	15 -6	; "[^/]+"
	23	[257]	CALL     	13 3 4
	24	[257]	JMP      	9	; to 34
	25	[258]	GETTABLE 	17 10 16
	26	[259]	TEST     	17 0 1
	27	[259]	JMP      	3	; to 31
	28	[260]	NEWTABLE 	18 0 0
	29	[260]	MOVE     	17 18
	30	[261]	SETTABLE 	10 16 17
	31	[263]	MOVE     	11 10
	32	[264]	MOVE     	12 16
	33	[265]	MOVE     	10 17
	34	[257]	TFORLOOP 	13 1
	35	[265]	JMP      	-11	; to 25
	36	[267]	GETUPVAL 	13 1	; fs
	37	[267]	GETTABLE 	13 13 -7	; "is_file"
	38	[267]	MOVE     	14 9
	39	[267]	CALL     	13 2 2
	40	[267]	TEST     	13 0 0
	41	[267]	JMP      	14	; to 56
	42	[268]	GETUPVAL 	13 1	; fs
	43	[268]	GETTABLE 	13 13 -8	; "get_md5"
	44	[268]	MOVE     	14 9
	45	[268]	CALL     	13 2 3
	46	[269]	TEST     	13 0 1
	47	[269]	JMP      	7	; to 55
	48	[270]	LOADNIL  	15 15
	49	[270]	LOADK    	16 -9	; "Failed producing checksum: "
	50	[270]	GETGLOBAL	17 -10	; tostring
	51	[270]	MOVE     	18 14
	52	[270]	CALL     	17 2 2
	53	[270]	CONCAT   	16 16 17
	54	[270]	RETURN   	15 3
	55	[272]	SETTABLE 	11 12 13
	56	[252]	TFORLOOP 	4 2
	57	[273]	JMP      	-44	; to 14
	58	[275]	NEWTABLE 	4 0 1
	59	[275]	SETTABLE 	4 -11 3	; "rock_manifest" -
	60	[276]	GETUPVAL 	5 3	; manif
	61	[276]	GETTABLE 	5 5 -12	; "rock_manifest_cache"
	62	[276]	MOVE     	6 0
	63	[276]	LOADK    	7 -13	; "/"
	64	[276]	MOVE     	8 1
	65	[276]	CONCAT   	6 6 8
	66	[276]	SETTABLE 	5 6 4
	67	[277]	GETUPVAL 	5 4	; save_table
	68	[277]	MOVE     	6 2
	69	[277]	LOADK    	7 -11	; "rock_manifest"
	70	[277]	MOVE     	8 4
	71	[277]	CALL     	5 4 1
	72	[278]	LOADBOOL 	5 1 0
	73	[278]	RETURN   	5 2
	74	[279]	RETURN   	0 1

function <./manif/writer.lua:287,304> (65 instructions, 260 bytes at 0x7faa23407080)
3 params, 9 slots, 1 upvalue, 7 locals, 11 constants, 0 functions
	1	[288]	GETGLOBAL	3 -1	; assert
	2	[288]	GETGLOBAL	4 -2	; type
	3	[288]	MOVE     	5 0
	4	[288]	CALL     	4 2 2
	5	[288]	EQ       	0 4 -3	; - "string"
	6	[288]	JMP      	5	; to 12
	7	[288]	SELF     	4 0 -4	; "match"
	8	[288]	LOADK    	6 -5	; "/"
	9	[288]	CALL     	4 3 2
	10	[288]	NOT      	4 4
	11	[288]	JMP      	2	; to 14
	12	[288]	LOADBOOL 	4 0 1
	13	[288]	LOADBOOL 	4 1 0
	14	[288]	CALL     	3 2 1
	15	[289]	GETGLOBAL	3 -1	; assert
	16	[289]	GETGLOBAL	4 -2	; type
	17	[289]	MOVE     	5 1
	18	[289]	CALL     	4 2 2
	19	[289]	EQ       	1 4 -3	; - "string"
	20	[289]	JMP      	1	; to 22
	21	[289]	LOADBOOL 	4 0 1
	22	[289]	LOADBOOL 	4 1 0
	23	[289]	CALL     	3 2 1
	24	[290]	GETGLOBAL	3 -1	; assert
	25	[290]	GETGLOBAL	4 -2	; type
	26	[290]	MOVE     	5 2
	27	[290]	CALL     	4 2 2
	28	[290]	EQ       	1 4 -3	; - "string"
	29	[290]	JMP      	3	; to 33
	30	[290]	NOT      	4 2
	31	[290]	JMP      	2	; to 34
	32	[290]	LOADBOOL 	4 0 1
	33	[290]	LOADBOOL 	4 1 0
	34	[290]	CALL     	3 2 1
	35	[291]	TEST     	2 0 1
	36	[291]	JMP      	2	; to 39
	37	[292]	LOADBOOL 	3 1 0
	38	[292]	RETURN   	3 2
	39	[294]	GETGLOBAL	3 -6	; io
	40	[294]	GETTABLE 	3 3 -7	; "open"
	41	[294]	GETUPVAL 	4 0	; path
	42	[294]	GETTABLE 	4 4 -8	; "rock_namespace_file"
	43	[294]	MOVE     	5 0
	44	[294]	MOVE     	6 1
	45	[294]	CALL     	4 3 2
	46	[294]	LOADK    	5 -9	; "w"
	47	[294]	CALL     	3 3 3
	48	[295]	TEST     	3 0 1
	49	[295]	JMP      	3	; to 53
	50	[296]	LOADNIL  	5 5
	51	[296]	MOVE     	6 4
	52	[296]	RETURN   	5 3
	53	[298]	SELF     	5 3 -10	; "write"
	54	[298]	MOVE     	7 2
	55	[298]	CALL     	5 3 3
	56	[299]	TEST     	5 0 1
	57	[299]	JMP      	3	; to 61
	58	[300]	LOADNIL  	7 7
	59	[300]	MOVE     	8 6
	60	[300]	RETURN   	7 3
	61	[302]	SELF     	7 3 -11	; "close"
	62	[302]	CALL     	7 2 1
	63	[303]	LOADBOOL 	7 1 0
	64	[303]	RETURN   	7 2
	65	[304]	RETURN   	0 1

function <./manif/writer.lua:316,354> (119 instructions, 476 bytes at 0x7faa23406640)
3 params, 21 slots, 10 upvalues, 16 locals, 18 constants, 0 functions
	1	[317]	GETGLOBAL	3 -1	; assert
	2	[317]	GETGLOBAL	4 -2	; type
	3	[317]	MOVE     	5 0
	4	[317]	CALL     	4 2 2
	5	[317]	EQ       	1 4 -3	; - "string"
	6	[317]	JMP      	1	; to 8
	7	[317]	LOADBOOL 	4 0 1
	8	[317]	LOADBOOL 	4 1 0
	9	[317]	CALL     	3 2 1
	10	[318]	GETGLOBAL	3 -1	; assert
	11	[318]	GETGLOBAL	4 -2	; type
	12	[318]	MOVE     	5 1
	13	[318]	CALL     	4 2 2
	14	[318]	EQ       	1 4 -3	; - "string"
	15	[318]	JMP      	1	; to 17
	16	[318]	LOADBOOL 	4 0 1
	17	[318]	LOADBOOL 	4 1 0
	18	[318]	CALL     	3 2 1
	19	[320]	EQ       	0 1 -4	; - "none"
	20	[320]	JMP      	2	; to 23
	21	[320]	GETUPVAL 	3 0	; cfg
	22	[320]	GETTABLE 	1 3 -5	; "deps_mode"
	23	[322]	GETUPVAL 	3 1	; fs
	24	[322]	GETTABLE 	3 3 -6	; "is_dir"
	25	[322]	MOVE     	4 0
	26	[322]	CALL     	3 2 2
	27	[322]	TEST     	3 0 1
	28	[322]	JMP      	5	; to 34
	29	[323]	LOADNIL  	3 3
	30	[323]	LOADK    	4 -7	; "Cannot access repository at "
	31	[323]	MOVE     	5 0
	32	[323]	CONCAT   	4 4 5
	33	[323]	RETURN   	3 3
	34	[326]	GETUPVAL 	3 2	; queries
	35	[326]	GETTABLE 	3 3 -8	; "all"
	36	[326]	LOADK    	4 -9	; "any"
	37	[326]	CALL     	3 2 2
	38	[327]	GETUPVAL 	4 3	; search
	39	[327]	GETTABLE 	4 4 -10	; "disk_search"
	40	[327]	MOVE     	5 0
	41	[327]	MOVE     	6 3
	42	[327]	CALL     	4 3 2
	43	[328]	NEWTABLE 	5 0 3
	44	[328]	NEWTABLE 	6 0 0
	45	[328]	SETTABLE 	5 -11 6	; "repository" -
	46	[328]	NEWTABLE 	6 0 0
	47	[328]	SETTABLE 	5 -12 6	; "modules" -
	48	[328]	NEWTABLE 	6 0 0
	49	[328]	SETTABLE 	5 -13 6	; "commands" -
	50	[330]	GETUPVAL 	6 4	; manif
	51	[330]	GETTABLE 	6 6 -14	; "cache_manifest"
	52	[330]	MOVE     	7 0
	53	[330]	LOADNIL  	8 8
	54	[330]	MOVE     	9 5
	55	[330]	CALL     	6 4 1
	56	[332]	GETUPVAL 	6 5	; store_results
	57	[332]	MOVE     	7 4
	58	[332]	MOVE     	8 5
	59	[332]	CALL     	6 3 3
	60	[333]	TEST     	6 0 1
	61	[333]	JMP      	3	; to 65
	62	[333]	LOADNIL  	8 8
	63	[333]	MOVE     	9 7
	64	[333]	RETURN   	8 3
	65	[335]	TEST     	2 0 0
	66	[335]	JMP      	36	; to 103
	67	[336]	NEWTABLE 	8 0 0
	68	[337]	GETUPVAL 	9 6	; util
	69	[337]	GETTABLE 	9 9 -15	; "lua_versions"
	70	[337]	CALL     	9 1 4
	71	[337]	JMP      	28	; to 100
	72	[338]	NEWTABLE 	13 0 3
	73	[338]	NEWTABLE 	14 0 0
	74	[338]	SETTABLE 	13 -11 14	; "repository" -
	75	[338]	NEWTABLE 	14 0 0
	76	[338]	SETTABLE 	13 -12 14	; "modules" -
	77	[338]	NEWTABLE 	14 0 0
	78	[338]	SETTABLE 	13 -13 14	; "commands" -
	79	[339]	GETUPVAL 	14 5	; store_results
	80	[339]	MOVE     	15 4
	81	[339]	MOVE     	16 13
	82	[339]	CALL     	14 3 3
	83	[340]	GETUPVAL 	16 7	; filter_by_lua_version
	84	[340]	MOVE     	17 13
	85	[340]	MOVE     	18 12
	86	[340]	MOVE     	19 0
	87	[340]	MOVE     	20 8
	88	[340]	CALL     	16 5 1
	89	[341]	GETUPVAL 	16 0	; cfg
	90	[341]	GETTABLE 	16 16 -16	; "no_manifest"
	91	[341]	TEST     	16 0 1
	92	[341]	JMP      	7	; to 100
	93	[342]	GETUPVAL 	16 8	; save_table
	94	[342]	MOVE     	17 0
	95	[342]	LOADK    	18 -17	; "manifest-"
	96	[342]	MOVE     	19 12
	97	[342]	CONCAT   	18 18 19
	98	[342]	MOVE     	19 13
	99	[342]	CALL     	16 4 1
	100	[337]	TFORLOOP 	9 1
	101	[343]	JMP      	-30	; to 72
	102	[344]	JMP      	4	; to 107
	103	[346]	GETUPVAL 	8 9	; update_dependencies
	104	[346]	MOVE     	9 5
	105	[346]	MOVE     	10 1
	106	[346]	CALL     	8 3 1
	107	[349]	GETUPVAL 	8 0	; cfg
	108	[349]	GETTABLE 	8 8 -16	; "no_manifest"
	109	[349]	TEST     	8 0 0
	110	[349]	JMP      	2	; to 113
	111	[351]	LOADBOOL 	8 1 0
	112	[351]	RETURN   	8 2
	113	[353]	GETUPVAL 	8 8	; save_table
	114	[353]	MOVE     	9 0
	115	[353]	LOADK    	10 -18	; "manifest"
	116	[353]	MOVE     	11 5
	117	[353]	TAILCALL 	8 4 0
	118	[353]	RETURN   	8 0
	119	[354]	RETURN   	0 1

function <./manif/writer.lua:367,395> (94 instructions, 376 bytes at 0x7faa2340c2c0)
4 params, 14 slots, 8 upvalues, 10 locals, 18 constants, 0 functions
	1	[368]	GETGLOBAL	4 -1	; assert
	2	[368]	GETGLOBAL	5 -2	; type
	3	[368]	MOVE     	6 0
	4	[368]	CALL     	5 2 2
	5	[368]	EQ       	0 5 -3	; - "string"
	6	[368]	JMP      	5	; to 12
	7	[368]	SELF     	5 0 -4	; "match"
	8	[368]	LOADK    	7 -5	; "/"
	9	[368]	CALL     	5 3 2
	10	[368]	NOT      	5 5
	11	[368]	JMP      	2	; to 14
	12	[368]	LOADBOOL 	5 0 1
	13	[368]	LOADBOOL 	5 1 0
	14	[368]	CALL     	4 2 1
	15	[369]	GETGLOBAL	4 -1	; assert
	16	[369]	GETGLOBAL	5 -2	; type
	17	[369]	MOVE     	6 1
	18	[369]	CALL     	5 2 2
	19	[369]	EQ       	1 5 -3	; - "string"
	20	[369]	JMP      	1	; to 22
	21	[369]	LOADBOOL 	5 0 1
	22	[369]	LOADBOOL 	5 1 0
	23	[369]	CALL     	4 2 1
	24	[370]	GETUPVAL 	4 0	; path
	25	[370]	GETTABLE 	4 4 -6	; "rocks_dir"
	26	[370]	TESTSET  	5 2 1
	27	[370]	JMP      	2	; to 30
	28	[370]	GETUPVAL 	5 1	; cfg
	29	[370]	GETTABLE 	5 5 -7	; "root_dir"
	30	[370]	CALL     	4 2 2
	31	[371]	GETGLOBAL	5 -1	; assert
	32	[371]	GETGLOBAL	6 -2	; type
	33	[371]	MOVE     	7 3
	34	[371]	CALL     	6 2 2
	35	[371]	EQ       	1 6 -3	; - "string"
	36	[371]	JMP      	1	; to 38
	37	[371]	LOADBOOL 	6 0 1
	38	[371]	LOADBOOL 	6 1 0
	39	[371]	CALL     	5 2 1
	40	[373]	EQ       	0 3 -8	; - "none"
	41	[373]	JMP      	2	; to 44
	42	[373]	GETUPVAL 	5 1	; cfg
	43	[373]	GETTABLE 	3 5 -9	; "deps_mode"
	44	[375]	GETUPVAL 	5 2	; manif
	45	[375]	GETTABLE 	5 5 -10	; "load_manifest"
	46	[375]	MOVE     	6 4
	47	[375]	CALL     	5 2 3
	48	[376]	TEST     	5 0 1
	49	[376]	JMP      	10	; to 60
	50	[377]	GETUPVAL 	7 3	; util
	51	[377]	GETTABLE 	7 7 -11	; "printerr"
	52	[377]	LOADK    	8 -12	; "No existing manifest. Attempting to rebuild..."
	53	[377]	CALL     	7 2 1
	54	[381]	GETUPVAL 	7 4	; writer
	55	[381]	GETTABLE 	7 7 -13	; "make_manifest"
	56	[381]	MOVE     	8 4
	57	[381]	MOVE     	9 3
	58	[381]	TAILCALL 	7 3 0
	59	[381]	RETURN   	7 0
	60	[384]	NEWTABLE 	7 0 1
	61	[384]	NEWTABLE 	8 0 1
	62	[384]	NEWTABLE 	9 1 0
	63	[384]	NEWTABLE 	10 0 2
	64	[384]	SETTABLE 	10 -14 -15	; "arch" "installed"
	65	[384]	SETTABLE 	10 -16 4	; "repo" -
	66	[384]	SETLIST  	9 1 1	; 1
	67	[384]	SETTABLE 	8 1 9
	68	[384]	SETTABLE 	7 0 8
	69	[386]	GETUPVAL 	8 5	; store_results
	70	[386]	MOVE     	9 7
	71	[386]	MOVE     	10 5
	72	[386]	CALL     	8 3 3
	73	[387]	TEST     	8 0 1
	74	[387]	JMP      	3	; to 78
	75	[387]	LOADNIL  	10 10
	76	[387]	MOVE     	11 9
	77	[387]	RETURN   	10 3
	78	[389]	GETUPVAL 	10 6	; update_dependencies
	79	[389]	MOVE     	11 5
	80	[389]	MOVE     	12 3
	81	[389]	CALL     	10 3 1
	82	[391]	GETUPVAL 	10 1	; cfg
	83	[391]	GETTABLE 	10 10 -17	; "no_manifest"
	84	[391]	TEST     	10 0 0
	85	[391]	JMP      	2	; to 88
	86	[392]	LOADBOOL 	10 1 0
	87	[392]	RETURN   	10 2
	88	[394]	GETUPVAL 	10 7	; save_table
	89	[394]	MOVE     	11 4
	90	[394]	LOADK    	12 -18	; "manifest"
	91	[394]	MOVE     	13 5
	92	[394]	TAILCALL 	10 4 0
	93	[394]	RETURN   	10 0
	94	[395]	RETURN   	0 1

function <./manif/writer.lua:408,454> (120 instructions, 480 bytes at 0x7faa2340bc00)
4 params, 14 slots, 8 upvalues, 9 locals, 22 constants, 0 functions
	1	[409]	GETGLOBAL	4 -1	; assert
	2	[409]	GETGLOBAL	5 -2	; type
	3	[409]	MOVE     	6 0
	4	[409]	CALL     	5 2 2
	5	[409]	EQ       	0 5 -3	; - "string"
	6	[409]	JMP      	5	; to 12
	7	[409]	SELF     	5 0 -4	; "match"
	8	[409]	LOADK    	7 -5	; "/"
	9	[409]	CALL     	5 3 2
	10	[409]	NOT      	5 5
	11	[409]	JMP      	2	; to 14
	12	[409]	LOADBOOL 	5 0 1
	13	[409]	LOADBOOL 	5 1 0
	14	[409]	CALL     	4 2 1
	15	[410]	GETGLOBAL	4 -1	; assert
	16	[410]	GETGLOBAL	5 -2	; type
	17	[410]	MOVE     	6 1
	18	[410]	CALL     	5 2 2
	19	[410]	EQ       	1 5 -3	; - "string"
	20	[410]	JMP      	1	; to 22
	21	[410]	LOADBOOL 	5 0 1
	22	[410]	LOADBOOL 	5 1 0
	23	[410]	CALL     	4 2 1
	24	[411]	GETUPVAL 	4 0	; path
	25	[411]	GETTABLE 	4 4 -6	; "rocks_dir"
	26	[411]	TESTSET  	5 2 1
	27	[411]	JMP      	2	; to 30
	28	[411]	GETUPVAL 	5 1	; cfg
	29	[411]	GETTABLE 	5 5 -7	; "root_dir"
	30	[411]	CALL     	4 2 2
	31	[412]	GETGLOBAL	5 -1	; assert
	32	[412]	GETGLOBAL	6 -2	; type
	33	[412]	MOVE     	7 3
	34	[412]	CALL     	6 2 2
	35	[412]	EQ       	1 6 -3	; - "string"
	36	[412]	JMP      	1	; to 38
	37	[412]	LOADBOOL 	6 0 1
	38	[412]	LOADBOOL 	6 1 0
	39	[412]	CALL     	5 2 1
	40	[414]	EQ       	0 3 -8	; - "none"
	41	[414]	JMP      	2	; to 44
	42	[414]	GETUPVAL 	5 1	; cfg
	43	[414]	GETTABLE 	3 5 -9	; "deps_mode"
	44	[416]	GETUPVAL 	5 2	; manif
	45	[416]	GETTABLE 	5 5 -10	; "load_manifest"
	46	[416]	MOVE     	6 4
	47	[416]	CALL     	5 2 3
	48	[417]	TEST     	5 0 1
	49	[417]	JMP      	10	; to 60
	50	[418]	GETUPVAL 	7 3	; util
	51	[418]	GETTABLE 	7 7 -11	; "printerr"
	52	[418]	LOADK    	8 -12	; "No existing manifest. Attempting to rebuild..."
	53	[418]	CALL     	7 2 1
	54	[421]	GETUPVAL 	7 4	; writer
	55	[421]	GETTABLE 	7 7 -13	; "make_manifest"
	56	[421]	MOVE     	8 4
	57	[421]	MOVE     	9 3
	58	[421]	TAILCALL 	7 3 0
	59	[421]	RETURN   	7 0
	60	[424]	GETTABLE 	7 5 -14	; "repository"
	61	[424]	GETTABLE 	7 7 0
	62	[425]	EQ       	1 7 -15	; - nil
	63	[425]	JMP      	3	; to 67
	64	[425]	GETTABLE 	8 7 1
	65	[425]	EQ       	0 8 -15	; - nil
	66	[425]	JMP      	2	; to 69
	67	[427]	LOADBOOL 	8 1 0
	68	[427]	RETURN   	8 2
	69	[430]	GETTABLE 	8 7 1
	70	[430]	GETTABLE 	8 8 -16	; 1
	71	[431]	TEST     	8 0 1
	72	[431]	JMP      	6	; to 79
	73	[433]	GETUPVAL 	9 4	; writer
	74	[433]	GETTABLE 	9 9 -13	; "make_manifest"
	75	[433]	MOVE     	10 4
	76	[433]	MOVE     	11 3
	77	[433]	TAILCALL 	9 3 0
	78	[433]	RETURN   	9 0
	79	[436]	GETUPVAL 	9 5	; remove_package_items
	80	[436]	GETTABLE 	10 5 -17	; "modules"
	81	[436]	MOVE     	11 0
	82	[436]	MOVE     	12 1
	83	[436]	GETTABLE 	13 8 -17	; "modules"
	84	[436]	CALL     	9 5 1
	85	[437]	GETUPVAL 	9 5	; remove_package_items
	86	[437]	GETTABLE 	10 5 -18	; "commands"
	87	[437]	MOVE     	11 0
	88	[437]	MOVE     	12 1
	89	[437]	GETTABLE 	13 8 -18	; "commands"
	90	[437]	CALL     	9 5 1
	91	[439]	SETTABLE 	7 1 -15	; - nil
	92	[440]	GETTABLE 	9 5 -19	; "dependencies"
	93	[440]	GETTABLE 	9 9 0
	94	[440]	SETTABLE 	9 1 -15	; - nil
	95	[442]	GETGLOBAL	9 -20	; next
	96	[442]	MOVE     	10 7
	97	[442]	CALL     	9 2 2
	98	[442]	TEST     	9 0 1
	99	[442]	JMP      	4	; to 104
	100	[444]	GETTABLE 	9 5 -14	; "repository"
	101	[444]	SETTABLE 	9 0 -15	; - nil
	102	[445]	GETTABLE 	9 5 -19	; "dependencies"
	103	[445]	SETTABLE 	9 0 -15	; - nil
	104	[448]	GETUPVAL 	9 6	; update_dependencies
	105	[448]	MOVE     	10 5
	106	[448]	MOVE     	11 3
	107	[448]	CALL     	9 3 1
	108	[450]	GETUPVAL 	9 1	; cfg
	109	[450]	GETTABLE 	9 9 -21	; "no_manifest"
	110	[450]	TEST     	9 0 0
	111	[450]	JMP      	2	; to 114
	112	[451]	LOADBOOL 	9 1 0
	113	[451]	RETURN   	9 2
	114	[453]	GETUPVAL 	9 7	; save_table
	115	[453]	MOVE     	10 4
	116	[453]	LOADK    	11 -22	; "manifest"
	117	[453]	MOVE     	12 5
	118	[453]	TAILCALL 	9 4 0
	119	[453]	RETURN   	9 0
	120	[454]	RETURN   	0 1

function <./manif/writer.lua:462,483> (74 instructions, 296 bytes at 0x7faa2340d730)
2 params, 25 slots, 6 upvalues, 19 locals, 17 constants, 0 functions
	1	[463]	GETUPVAL 	2 0	; path
	2	[463]	GETTABLE 	2 2 -1	; "rocks_dir"
	3	[463]	TESTSET  	3 0 1
	4	[463]	JMP      	2	; to 7
	5	[463]	GETUPVAL 	3 1	; cfg
	6	[463]	GETTABLE 	3 3 -2	; "root_dir"
	7	[463]	CALL     	2 2 2
	8	[464]	GETGLOBAL	3 -3	; assert
	9	[464]	GETGLOBAL	4 -4	; type
	10	[464]	MOVE     	5 1
	11	[464]	CALL     	4 2 2
	12	[464]	EQ       	1 4 -5	; - "string"
	13	[464]	JMP      	1	; to 15
	14	[464]	LOADBOOL 	4 0 1
	15	[464]	LOADBOOL 	4 1 0
	16	[464]	CALL     	3 2 1
	17	[465]	EQ       	0 1 -6	; - "none"
	18	[465]	JMP      	2	; to 21
	19	[465]	GETUPVAL 	3 1	; cfg
	20	[465]	GETTABLE 	1 3 -7	; "deps_mode"
	21	[467]	GETUPVAL 	3 2	; manif
	22	[467]	GETTABLE 	3 3 -8	; "load_manifest"
	23	[467]	MOVE     	4 2
	24	[467]	CALL     	3 2 2
	25	[468]	TEST     	3 0 1
	26	[468]	JMP      	1	; to 28
	27	[469]	RETURN   	0 1
	28	[472]	GETUPVAL 	4 3	; util
	29	[472]	GETTABLE 	4 4 -9	; "sortedpairs"
	30	[472]	GETTABLE 	5 3 -10	; "repository"
	31	[472]	CALL     	4 2 4
	32	[472]	JMP      	39	; to 72
	33	[473]	GETUPVAL 	9 3	; util
	34	[473]	GETTABLE 	9 9 -9	; "sortedpairs"
	35	[473]	MOVE     	10 8
	36	[473]	GETUPVAL 	11 4	; vers
	37	[473]	GETTABLE 	11 11 -11	; "compare_versions"
	38	[473]	CALL     	9 3 4
	39	[473]	JMP      	30	; to 70
	40	[474]	GETGLOBAL	14 -12	; ipairs
	41	[474]	MOVE     	15 13
	42	[474]	CALL     	14 2 4
	43	[474]	JMP      	24	; to 68
	44	[475]	GETTABLE 	19 18 -13	; "arch"
	45	[475]	EQ       	0 19 -14	; - "installed"
	46	[475]	JMP      	21	; to 68
	47	[476]	GETTABLE 	19 3 -15	; "dependencies"
	48	[476]	GETTABLE 	19 19 7
	49	[476]	TEST     	19 0 0
	50	[476]	JMP      	17	; to 68
	51	[476]	GETTABLE 	19 3 -15	; "dependencies"
	52	[476]	GETTABLE 	19 19 7
	53	[476]	GETTABLE 	19 19 12
	54	[476]	TEST     	19 0 0
	55	[476]	JMP      	12	; to 68
	56	[477]	GETUPVAL 	19 5	; deps
	57	[477]	GETTABLE 	19 19 -16	; "report_missing_dependencies"
	58	[477]	MOVE     	20 7
	59	[477]	MOVE     	21 12
	60	[477]	GETTABLE 	22 3 -15	; "dependencies"
	61	[477]	GETTABLE 	22 22 7
	62	[477]	GETTABLE 	22 22 12
	63	[477]	MOVE     	23 1
	64	[477]	GETUPVAL 	24 3	; util
	65	[477]	GETTABLE 	24 24 -17	; "get_rocks_provided"
	66	[477]	CALL     	24 1 0
	67	[477]	CALL     	19 0 1
	68	[474]	TFORLOOP 	14 2
	69	[479]	JMP      	-26	; to 44
	70	[473]	TFORLOOP 	9 2
	71	[480]	JMP      	-32	; to 40
	72	[472]	TFORLOOP 	4 2
	73	[481]	JMP      	-41	; to 33
	74	[483]	RETURN   	0 1
