LuaSocket, accessed from https://luarocks.org/modules/luasocket/luasocket
-----------------------

main <./socket.lua:0,0> (62 instructions, 248 bytes at 0x7fa7a74068a0)
0+ params, 9 slots, 0 upvalues, 7 locals, 22 constants, 8 functions
	1	[9]	GETGLOBAL	0 -1	; _G
	2	[10]	GETGLOBAL	1 -2	; require
	3	[10]	LOADK    	2 -3	; "string"
	4	[10]	CALL     	1 2 2
	5	[11]	GETGLOBAL	2 -2	; require
	6	[11]	LOADK    	3 -4	; "math"
	7	[11]	CALL     	2 2 2
	8	[12]	GETGLOBAL	3 -2	; require
	9	[12]	LOADK    	4 -5	; "socket.core"
	10	[12]	CALL     	3 2 2
	11	[14]	MOVE     	4 3
	12	[21]	CLOSURE  	5 0	; 0x7fa7a7406c00
	13	[21]	MOVE     	0 3
	14	[19]	SETTABLE 	4 -6 5	; "connect4" -
	15	[25]	CLOSURE  	5 1	; 0x7fa7a7407180
	16	[25]	MOVE     	0 3
	17	[23]	SETTABLE 	4 -7 5	; "connect6" -
	18	[54]	CLOSURE  	5 2	; 0x7fa7a7407a30
	19	[54]	MOVE     	0 3
	20	[54]	MOVE     	0 0
	21	[27]	SETTABLE 	4 -8 5	; "bind" -
	22	[56]	GETTABLE 	5 4 -10	; "newtry"
	23	[56]	CALL     	5 1 2
	24	[56]	SETTABLE 	4 -9 5	; "try" -
	25	[67]	CLOSURE  	5 3	; 0x7fa7a7406cc0
	26	[67]	MOVE     	0 0
	27	[58]	SETTABLE 	4 -11 5	; "choose" -
	28	[73]	NEWTABLE 	5 0 0
	29	[73]	NEWTABLE 	6 0 0
	30	[74]	SETTABLE 	4 -12 5	; "sourcet" -
	31	[75]	SETTABLE 	4 -13 6	; "sinkt" -
	32	[77]	SETTABLE 	4 -14 -15	; "BLOCKSIZE" 2048
	33	[91]	CLOSURE  	7 4	; 0x7fa7a74086e0
	34	[91]	MOVE     	0 0
	35	[91]	SETTABLE 	6 -16 7	; "close-when-done" -
	36	[103]	CLOSURE  	7 5	; 0x7fa7a74076e0
	37	[103]	MOVE     	0 0
	38	[103]	SETTABLE 	6 -17 7	; "keep-open" -
	39	[105]	GETTABLE 	7 6 -17	; "keep-open"
	40	[105]	SETTABLE 	6 -18 7	; "default" -
	41	[107]	GETTABLE 	7 4 -11	; "choose"
	42	[107]	MOVE     	8 6
	43	[107]	CALL     	7 2 2
	44	[107]	SETTABLE 	4 -19 7	; "sink" -
	45	[123]	CLOSURE  	7 6	; 0x7fa7a74095a0
	46	[123]	MOVE     	0 0
	47	[123]	MOVE     	0 2
	48	[123]	MOVE     	0 3
	49	[123]	MOVE     	0 1
	50	[123]	SETTABLE 	5 -20 7	; "by-length" -
	51	[142]	CLOSURE  	7 7	; 0x7fa7a740ac30
	52	[142]	MOVE     	0 0
	53	[142]	MOVE     	0 3
	54	[142]	SETTABLE 	5 -21 7	; "until-closed" -
	55	[145]	GETTABLE 	7 5 -21	; "until-closed"
	56	[145]	SETTABLE 	5 -18 7	; "default" -
	57	[147]	GETTABLE 	7 4 -11	; "choose"
	58	[147]	MOVE     	8 5
	59	[147]	CALL     	7 2 2
	60	[147]	SETTABLE 	4 -22 7	; "source" -
	61	[149]	RETURN   	4 2
	62	[149]	RETURN   	0 1

function <./socket.lua:19,21> (10 instructions, 40 bytes at 0x7fa7a7406c00)
4 params, 10 slots, 1 upvalue, 4 locals, 2 constants, 0 functions
	1	[20]	GETUPVAL 	4 0	; socket
	2	[20]	GETTABLE 	4 4 -1	; "connect"
	3	[20]	MOVE     	5 0
	4	[20]	MOVE     	6 1
	5	[20]	MOVE     	7 2
	6	[20]	MOVE     	8 3
	7	[20]	LOADK    	9 -2	; "inet"
	8	[20]	TAILCALL 	4 6 0
	9	[20]	RETURN   	4 0
	10	[21]	RETURN   	0 1

function <./socket.lua:23,25> (10 instructions, 40 bytes at 0x7fa7a7407180)
4 params, 10 slots, 1 upvalue, 4 locals, 2 constants, 0 functions
	1	[24]	GETUPVAL 	4 0	; socket
	2	[24]	GETTABLE 	4 4 -1	; "connect"
	3	[24]	MOVE     	5 0
	4	[24]	MOVE     	6 1
	5	[24]	MOVE     	7 2
	6	[24]	MOVE     	8 3
	7	[24]	LOADK    	9 -2	; "inet6"
	8	[24]	TAILCALL 	4 6 0
	9	[24]	RETURN   	4 0
	10	[25]	RETURN   	0 1

function <./socket.lua:27,54> (71 instructions, 284 bytes at 0x7fa7a7407a30)
3 params, 16 slots, 2 upvalues, 12 locals, 16 constants, 0 functions
	1	[28]	EQ       	0 0 -1	; - "*"
	2	[28]	JMP      	1	; to 4
	3	[28]	LOADK    	0 -2	; "0.0.0.0"
	4	[29]	GETUPVAL 	3 0	; socket
	5	[29]	GETTABLE 	3 3 -3	; "dns"
	6	[29]	GETTABLE 	3 3 -4	; "getaddrinfo"
	7	[29]	MOVE     	4 0
	8	[29]	CALL     	3 2 3
	9	[30]	TEST     	3 0 1
	10	[30]	JMP      	3	; to 14
	11	[30]	LOADNIL  	5 5
	12	[30]	MOVE     	6 4
	13	[30]	RETURN   	5 3
	14	[31]	LOADNIL  	5 6
	15	[32]	LOADK    	4 -5	; "no info on address"
	16	[33]	GETUPVAL 	7 1	; base
	17	[33]	GETTABLE 	7 7 -6	; "ipairs"
	18	[33]	MOVE     	8 3
	19	[33]	CALL     	7 2 4
	20	[33]	JMP      	45	; to 66
	21	[34]	GETTABLE 	12 11 -7	; "family"
	22	[34]	EQ       	0 12 -8	; - "inet"
	23	[34]	JMP      	6	; to 30
	24	[35]	GETUPVAL 	12 0	; socket
	25	[35]	GETTABLE 	12 12 -9	; "tcp"
	26	[35]	CALL     	12 1 3
	27	[35]	MOVE     	4 13
	28	[35]	MOVE     	5 12
	29	[35]	JMP      	5	; to 35
	30	[37]	GETUPVAL 	12 0	; socket
	31	[37]	GETTABLE 	12 12 -10	; "tcp6"
	32	[37]	CALL     	12 1 3
	33	[37]	MOVE     	4 13
	34	[37]	MOVE     	5 12
	35	[39]	TEST     	5 0 1
	36	[39]	JMP      	3	; to 40
	37	[39]	LOADNIL  	12 12
	38	[39]	MOVE     	13 4
	39	[39]	RETURN   	12 3
	40	[40]	SELF     	12 5 -11	; "setoption"
	41	[40]	LOADK    	14 -12	; "reuseaddr"
	42	[40]	LOADBOOL 	15 1 0
	43	[40]	CALL     	12 4 1
	44	[41]	SELF     	12 5 -13	; "bind"
	45	[41]	GETTABLE 	14 11 -14	; "addr"
	46	[41]	MOVE     	15 1
	47	[41]	CALL     	12 4 3
	48	[41]	MOVE     	4 13
	49	[41]	MOVE     	6 12
	50	[42]	TEST     	6 0 1
	51	[42]	JMP      	3	; to 55
	52	[43]	SELF     	12 5 -15	; "close"
	53	[43]	CALL     	12 2 1
	54	[43]	JMP      	11	; to 66
	55	[45]	SELF     	12 5 -16	; "listen"
	56	[45]	MOVE     	14 2
	57	[45]	CALL     	12 3 3
	58	[45]	MOVE     	4 13
	59	[45]	MOVE     	6 12
	60	[46]	TEST     	6 0 1
	61	[46]	JMP      	3	; to 65
	62	[47]	SELF     	12 5 -15	; "close"
	63	[47]	CALL     	12 2 1
	64	[47]	JMP      	1	; to 66
	65	[49]	RETURN   	5 2
	66	[33]	TFORLOOP 	7 2
	67	[51]	JMP      	-47	; to 21
	68	[53]	LOADNIL  	7 7
	69	[53]	MOVE     	8 4
	70	[53]	RETURN   	7 3
	71	[54]	RETURN   	0 1

function <./socket.lua:58,67> (5 instructions, 20 bytes at 0x7fa7a7406cc0)
1 param, 2 slots, 1 upvalue, 1 local, 0 constants, 1 function
	1	[66]	CLOSURE  	1 0	; 0x7fa7a7408560
	2	[66]	GETUPVAL 	0 0	; base
	3	[66]	MOVE     	0 0
	4	[66]	RETURN   	1 2
	5	[67]	RETURN   	0 1

function <./socket.lua:59,66> (36 instructions, 144 bytes at 0x7fa7a7408560)
3 params, 8 slots, 2 upvalues, 4 locals, 9 constants, 0 functions
	1	[60]	GETUPVAL 	3 0	; base
	2	[60]	GETTABLE 	3 3 -1	; "type"
	3	[60]	MOVE     	4 0
	4	[60]	CALL     	3 2 2
	5	[60]	EQ       	1 3 -2	; - "string"
	6	[60]	JMP      	5	; to 12
	7	[61]	LOADK    	3 -3	; "default"
	8	[61]	MOVE     	4 0
	9	[61]	MOVE     	2 1
	10	[61]	MOVE     	1 4
	11	[61]	MOVE     	0 3
	12	[63]	GETUPVAL 	3 1	; table
	13	[63]	TESTSET  	4 0 1
	14	[63]	JMP      	1	; to 16
	15	[63]	LOADK    	4 -4	; "nil"
	16	[63]	GETTABLE 	3 3 4
	17	[64]	TEST     	3 0 1
	18	[64]	JMP      	12	; to 31
	19	[64]	GETUPVAL 	4 0	; base
	20	[64]	GETTABLE 	4 4 -5	; "error"
	21	[64]	LOADK    	5 -6	; "unknown key ("
	22	[64]	GETUPVAL 	6 0	; base
	23	[64]	GETTABLE 	6 6 -7	; "tostring"
	24	[64]	MOVE     	7 0
	25	[64]	CALL     	6 2 2
	26	[64]	LOADK    	7 -8	; ")"
	27	[64]	CONCAT   	5 5 7
	28	[64]	LOADK    	6 -9	; 3
	29	[64]	CALL     	4 3 1
	30	[64]	JMP      	5	; to 36
	31	[65]	MOVE     	4 3
	32	[65]	MOVE     	5 1
	33	[65]	MOVE     	6 2
	34	[65]	TAILCALL 	4 3 0
	35	[65]	RETURN   	4 0
	36	[66]	RETURN   	0 1

function <./socket.lua:79,91> (16 instructions, 64 bytes at 0x7fa7a74086e0)
1 param, 5 slots, 1 upvalue, 1 local, 4 constants, 3 functions
	1	[80]	GETUPVAL 	1 0	; base
	2	[80]	GETTABLE 	1 1 -1	; "setmetatable"
	3	[80]	NEWTABLE 	2 0 2
	4	[81]	CLOSURE  	3 0	; 0x7fa7a7406eb0
	5	[81]	MOVE     	0 0
	6	[81]	SETTABLE 	2 -2 3	; "getfd" -
	7	[82]	CLOSURE  	3 1	; 0x7fa7a7408de0
	8	[82]	MOVE     	0 0
	9	[82]	SETTABLE 	2 -3 3	; "dirty" -
	10	[83]	NEWTABLE 	3 0 1
	11	[89]	CLOSURE  	4 2	; 0x7fa7a7407890
	12	[89]	MOVE     	0 0
	13	[89]	SETTABLE 	3 -4 4	; "__call" -
	14	[80]	TAILCALL 	1 3 0
	15	[90]	RETURN   	1 0
	16	[91]	RETURN   	0 1

function <./socket.lua:81,81> (5 instructions, 20 bytes at 0x7fa7a7406eb0)
0 params, 2 slots, 1 upvalue, 0 locals, 1 constant, 0 functions
	1	[81]	GETUPVAL 	0 0	; sock
	2	[81]	SELF     	0 0 -1	; "getfd"
	3	[81]	TAILCALL 	0 2 0
	4	[81]	RETURN   	0 0
	5	[81]	RETURN   	0 1

function <./socket.lua:82,82> (5 instructions, 20 bytes at 0x7fa7a7408de0)
0 params, 2 slots, 1 upvalue, 0 locals, 1 constant, 0 functions
	1	[82]	GETUPVAL 	0 0	; sock
	2	[82]	SELF     	0 0 -1	; "dirty"
	3	[82]	TAILCALL 	0 2 0
	4	[82]	RETURN   	0 0
	5	[82]	RETURN   	0 1

function <./socket.lua:84,89> (14 instructions, 56 bytes at 0x7fa7a7407890)
3 params, 6 slots, 1 upvalue, 3 locals, 3 constants, 0 functions
	1	[85]	TEST     	1 0 1
	2	[85]	JMP      	6	; to 9
	3	[86]	GETUPVAL 	3 0	; sock
	4	[86]	SELF     	3 3 -1	; "close"
	5	[86]	CALL     	3 2 1
	6	[87]	LOADK    	3 -2	; 1
	7	[87]	RETURN   	3 2
	8	[87]	JMP      	5	; to 14
	9	[88]	GETUPVAL 	3 0	; sock
	10	[88]	SELF     	3 3 -3	; "send"
	11	[88]	MOVE     	5 1
	12	[88]	TAILCALL 	3 3 0
	13	[88]	RETURN   	3 0
	14	[89]	RETURN   	0 1

function <./socket.lua:93,103> (16 instructions, 64 bytes at 0x7fa7a74076e0)
1 param, 5 slots, 1 upvalue, 1 local, 4 constants, 3 functions
	1	[94]	GETUPVAL 	1 0	; base
	2	[94]	GETTABLE 	1 1 -1	; "setmetatable"
	3	[94]	NEWTABLE 	2 0 2
	4	[95]	CLOSURE  	3 0	; 0x7fa7a7407460
	5	[95]	MOVE     	0 0
	6	[95]	SETTABLE 	2 -2 3	; "getfd" -
	7	[96]	CLOSURE  	3 1	; 0x7fa7a7409720
	8	[96]	MOVE     	0 0
	9	[96]	SETTABLE 	2 -3 3	; "dirty" -
	10	[97]	NEWTABLE 	3 0 1
	11	[101]	CLOSURE  	4 2	; 0x7fa7a7409980
	12	[101]	MOVE     	0 0
	13	[101]	SETTABLE 	3 -4 4	; "__call" -
	14	[94]	TAILCALL 	1 3 0
	15	[102]	RETURN   	1 0
	16	[103]	RETURN   	0 1

function <./socket.lua:95,95> (5 instructions, 20 bytes at 0x7fa7a7407460)
0 params, 2 slots, 1 upvalue, 0 locals, 1 constant, 0 functions
	1	[95]	GETUPVAL 	0 0	; sock
	2	[95]	SELF     	0 0 -1	; "getfd"
	3	[95]	TAILCALL 	0 2 0
	4	[95]	RETURN   	0 0
	5	[95]	RETURN   	0 1

function <./socket.lua:96,96> (5 instructions, 20 bytes at 0x7fa7a7409720)
0 params, 2 slots, 1 upvalue, 0 locals, 1 constant, 0 functions
	1	[96]	GETUPVAL 	0 0	; sock
	2	[96]	SELF     	0 0 -1	; "dirty"
	3	[96]	TAILCALL 	0 2 0
	4	[96]	RETURN   	0 0
	5	[96]	RETURN   	0 1

function <./socket.lua:98,101> (11 instructions, 44 bytes at 0x7fa7a7409980)
3 params, 6 slots, 1 upvalue, 3 locals, 2 constants, 0 functions
	1	[99]	TEST     	1 0 0
	2	[99]	JMP      	6	; to 9
	3	[99]	GETUPVAL 	3 0	; sock
	4	[99]	SELF     	3 3 -1	; "send"
	5	[99]	MOVE     	5 1
	6	[99]	TAILCALL 	3 3 0
	7	[99]	RETURN   	3 0
	8	[99]	JMP      	2	; to 11
	9	[100]	LOADK    	3 -2	; 1
	10	[100]	RETURN   	3 2
	11	[101]	RETURN   	0 1

function <./socket.lua:109,123> (20 instructions, 80 bytes at 0x7fa7a74095a0)
2 params, 6 slots, 4 upvalues, 2 locals, 4 constants, 3 functions
	1	[110]	GETUPVAL 	2 0	; base
	2	[110]	GETTABLE 	2 2 -1	; "setmetatable"
	3	[110]	NEWTABLE 	3 0 2
	4	[111]	CLOSURE  	4 0	; 0x7fa7a7409bc0
	5	[111]	MOVE     	0 0
	6	[111]	SETTABLE 	3 -2 4	; "getfd" -
	7	[112]	CLOSURE  	4 1	; 0x7fa7a740a3e0
	8	[112]	MOVE     	0 0
	9	[112]	SETTABLE 	3 -3 4	; "dirty" -
	10	[113]	NEWTABLE 	4 0 1
	11	[121]	CLOSURE  	5 2	; 0x7fa7a740a1b0
	12	[121]	MOVE     	0 1
	13	[121]	GETUPVAL 	0 1	; math
	14	[121]	GETUPVAL 	0 2	; socket
	15	[121]	MOVE     	0 0
	16	[121]	GETUPVAL 	0 3	; string
	17	[121]	SETTABLE 	4 -4 5	; "__call" -
	18	[110]	TAILCALL 	2 3 0
	19	[122]	RETURN   	2 0
	20	[123]	RETURN   	0 1

function <./socket.lua:111,111> (5 instructions, 20 bytes at 0x7fa7a7409bc0)
0 params, 2 slots, 1 upvalue, 0 locals, 1 constant, 0 functions
	1	[111]	GETUPVAL 	0 0	; sock
	2	[111]	SELF     	0 0 -1	; "getfd"
	3	[111]	TAILCALL 	0 2 0
	4	[111]	RETURN   	0 0
	5	[111]	RETURN   	0 1

function <./socket.lua:112,112> (5 instructions, 20 bytes at 0x7fa7a740a3e0)
0 params, 2 slots, 1 upvalue, 0 locals, 1 constant, 0 functions
	1	[112]	GETUPVAL 	0 0	; sock
	2	[112]	SELF     	0 0 -1	; "dirty"
	3	[112]	TAILCALL 	0 2 0
	4	[112]	RETURN   	0 0
	5	[112]	RETURN   	0 1

function <./socket.lua:114,121> (29 instructions, 116 bytes at 0x7fa7a740a1b0)
0 params, 6 slots, 5 upvalues, 3 locals, 5 constants, 0 functions
	1	[115]	GETUPVAL 	0 0	; length
	2	[115]	LE       	0 0 -1	; - 0
	3	[115]	JMP      	2	; to 6
	4	[115]	LOADNIL  	0 0
	5	[115]	RETURN   	0 2
	6	[116]	GETUPVAL 	0 1	; math
	7	[116]	GETTABLE 	0 0 -2	; "min"
	8	[116]	GETUPVAL 	1 2	; socket
	9	[116]	GETTABLE 	1 1 -3	; "BLOCKSIZE"
	10	[116]	GETUPVAL 	2 0	; length
	11	[116]	CALL     	0 3 2
	12	[117]	GETUPVAL 	1 3	; sock
	13	[117]	SELF     	1 1 -4	; "receive"
	14	[117]	MOVE     	3 0
	15	[117]	CALL     	1 3 3
	16	[118]	TEST     	2 0 0
	17	[118]	JMP      	3	; to 21
	18	[118]	LOADNIL  	3 3
	19	[118]	MOVE     	4 2
	20	[118]	RETURN   	3 3
	21	[119]	GETUPVAL 	3 0	; length
	22	[119]	GETUPVAL 	4 4	; string
	23	[119]	GETTABLE 	4 4 -5	; "len"
	24	[119]	MOVE     	5 1
	25	[119]	CALL     	4 2 2
	26	[119]	SUB      	3 3 4
	27	[119]	SETUPVAL 	3 0	; length
	28	[120]	RETURN   	1 2
	29	[121]	RETURN   	0 1

function <./socket.lua:125,142> (18 instructions, 72 bytes at 0x7fa7a740ac30)
1 param, 6 slots, 2 upvalues, 2 locals, 4 constants, 3 functions
	1	[127]	GETUPVAL 	2 0	; base
	2	[127]	GETTABLE 	2 2 -1	; "setmetatable"
	3	[127]	NEWTABLE 	3 0 2
	4	[128]	CLOSURE  	4 0	; 0x7fa7a740ae90
	5	[128]	MOVE     	0 0
	6	[128]	SETTABLE 	3 -2 4	; "getfd" -
	7	[129]	CLOSURE  	4 1	; 0x7fa7a740ad50
	8	[129]	MOVE     	0 0
	9	[129]	SETTABLE 	3 -3 4	; "dirty" -
	10	[130]	NEWTABLE 	4 0 1
	11	[140]	CLOSURE  	5 2	; 0x7fa7a740b3b0
	12	[140]	MOVE     	0 1
	13	[140]	MOVE     	0 0
	14	[140]	GETUPVAL 	0 1	; socket
	15	[140]	SETTABLE 	4 -4 5	; "__call" -
	16	[127]	TAILCALL 	2 3 0
	17	[141]	RETURN   	2 0
	18	[142]	RETURN   	0 1

function <./socket.lua:128,128> (5 instructions, 20 bytes at 0x7fa7a740ae90)
0 params, 2 slots, 1 upvalue, 0 locals, 1 constant, 0 functions
	1	[128]	GETUPVAL 	0 0	; sock
	2	[128]	SELF     	0 0 -1	; "getfd"
	3	[128]	TAILCALL 	0 2 0
	4	[128]	RETURN   	0 0
	5	[128]	RETURN   	0 1

function <./socket.lua:129,129> (5 instructions, 20 bytes at 0x7fa7a740ad50)
0 params, 2 slots, 1 upvalue, 0 locals, 1 constant, 0 functions
	1	[129]	GETUPVAL 	0 0	; sock
	2	[129]	SELF     	0 0 -1	; "dirty"
	3	[129]	TAILCALL 	0 2 0
	4	[129]	RETURN   	0 0
	5	[129]	RETURN   	0 1

function <./socket.lua:131,140> (27 instructions, 108 bytes at 0x7fa7a740b3b0)
0 params, 5 slots, 3 upvalues, 3 locals, 5 constants, 0 functions
	1	[132]	GETUPVAL 	0 0	; done
	2	[132]	TEST     	0 0 0
	3	[132]	JMP      	2	; to 6
	4	[132]	LOADNIL  	0 0
	5	[132]	RETURN   	0 2
	6	[133]	GETUPVAL 	0 1	; sock
	7	[133]	SELF     	0 0 -1	; "receive"
	8	[133]	GETUPVAL 	2 2	; socket
	9	[133]	GETTABLE 	2 2 -2	; "BLOCKSIZE"
	10	[133]	CALL     	0 3 4
	11	[134]	TEST     	1 0 1
	12	[134]	JMP      	2	; to 15
	13	[134]	RETURN   	0 2
	14	[134]	JMP      	12	; to 27
	15	[135]	EQ       	0 1 -3	; - "closed"
	16	[135]	JMP      	7	; to 24
	17	[136]	GETUPVAL 	3 1	; sock
	18	[136]	SELF     	3 3 -4	; "close"
	19	[136]	CALL     	3 2 1
	20	[137]	LOADK    	3 -5	; 1
	21	[137]	SETUPVAL 	3 0	; done
	22	[138]	RETURN   	2 2
	23	[138]	JMP      	3	; to 27
	24	[139]	LOADNIL  	3 3
	25	[139]	MOVE     	4 1
	26	[139]	RETURN   	3 3
	27	[140]	RETURN   	0 1
-----------------------

main <./socket/tp.lua:0,0> (64 instructions, 256 bytes at 0x7fdb344068a0)
0+ params, 9 slots, 0 upvalues, 7 locals, 20 constants, 12 functions
	1	[10]	GETGLOBAL	0 -1	; _G
	2	[11]	GETGLOBAL	1 -2	; require
	3	[11]	LOADK    	2 -3	; "string"
	4	[11]	CALL     	1 2 2
	5	[12]	GETGLOBAL	2 -2	; require
	6	[12]	LOADK    	3 -4	; "socket"
	7	[12]	CALL     	2 2 2
	8	[13]	GETGLOBAL	3 -2	; require
	9	[13]	LOADK    	4 -5	; "ltn12"
	10	[13]	CALL     	3 2 2
	11	[15]	NEWTABLE 	4 0 0
	12	[15]	SETTABLE 	2 -6 4	; "tp" -
	13	[16]	GETTABLE 	4 2 -6	; "tp"
	14	[21]	SETTABLE 	4 -7 -8	; "TIMEOUT" 60
	15	[44]	CLOSURE  	5 0	; 0x7fdb34406f80
	16	[44]	MOVE     	0 2
	17	[44]	MOVE     	0 1
	18	[47]	NEWTABLE 	6 0 1
	19	[47]	NEWTABLE 	7 0 0
	20	[47]	SETTABLE 	6 -9 7	; "__index" -
	21	[49]	GETTABLE 	7 6 -9	; "__index"
	22	[65]	CLOSURE  	8 1	; 0x7fdb34406a80
	23	[65]	MOVE     	0 5
	24	[65]	MOVE     	0 0
	25	[65]	MOVE     	0 1
	26	[49]	SETTABLE 	7 -10 8	; "check" -
	27	[67]	GETTABLE 	7 6 -9	; "__index"
	28	[74]	CLOSURE  	8 2	; 0x7fdb34407790
	29	[74]	MOVE     	0 1
	30	[67]	SETTABLE 	7 -11 8	; "command" -
	31	[76]	GETTABLE 	7 6 -9	; "__index"
	32	[79]	CLOSURE  	8 3	; 0x7fdb34407ae0
	33	[76]	SETTABLE 	7 -12 8	; "sink" -
	34	[81]	GETTABLE 	7 6 -9	; "__index"
	35	[83]	CLOSURE  	8 4	; 0x7fdb34407510
	36	[81]	SETTABLE 	7 -13 8	; "send" -
	37	[85]	GETTABLE 	7 6 -9	; "__index"
	38	[87]	CLOSURE  	8 5	; 0x7fdb34408810
	39	[85]	SETTABLE 	7 -14 8	; "receive" -
	40	[89]	GETTABLE 	7 6 -9	; "__index"
	41	[91]	CLOSURE  	8 6	; 0x7fdb34408aa0
	42	[89]	SETTABLE 	7 -15 8	; "getfd" -
	43	[93]	GETTABLE 	7 6 -9	; "__index"
	44	[95]	CLOSURE  	8 7	; 0x7fdb34408ce0
	45	[93]	SETTABLE 	7 -16 8	; "dirty" -
	46	[97]	GETTABLE 	7 6 -9	; "__index"
	47	[99]	CLOSURE  	8 8	; 0x7fdb34408f90
	48	[97]	SETTABLE 	7 -17 8	; "getcontrol" -
	49	[101]	GETTABLE 	7 6 -9	; "__index"
	50	[105]	CLOSURE  	8 9	; 0x7fdb34408e90
	51	[105]	MOVE     	0 2
	52	[105]	MOVE     	0 3
	53	[101]	SETTABLE 	7 -18 8	; "source" -
	54	[108]	GETTABLE 	7 6 -9	; "__index"
	55	[111]	CLOSURE  	8 10	; 0x7fdb344088b0
	56	[108]	SETTABLE 	7 -19 8	; "close" -
	57	[124]	CLOSURE  	7 11	; 0x7fdb34408930
	58	[124]	MOVE     	0 2
	59	[124]	MOVE     	0 4
	60	[124]	MOVE     	0 0
	61	[124]	MOVE     	0 6
	62	[114]	SETTABLE 	4 -20 7	; "connect" -
	63	[126]	RETURN   	4 2
	64	[126]	RETURN   	0 1

function <./socket/tp.lua:27,44> (58 instructions, 232 bytes at 0x7fdb34406f80)
1 param, 12 slots, 2 upvalues, 7 locals, 9 constants, 0 functions
	1	[29]	SELF     	4 0 -1	; "receive"
	2	[29]	CALL     	4 2 3
	3	[30]	MOVE     	6 4
	4	[31]	TEST     	5 0 0
	5	[31]	JMP      	3	; to 9
	6	[31]	LOADNIL  	7 7
	7	[31]	MOVE     	8 5
	8	[31]	RETURN   	7 3
	9	[32]	GETUPVAL 	7 0	; socket
	10	[32]	GETTABLE 	7 7 -2	; "skip"
	11	[32]	LOADK    	8 -3	; 2
	12	[32]	GETUPVAL 	9 1	; string
	13	[32]	GETTABLE 	9 9 -4	; "find"
	14	[32]	MOVE     	10 4
	15	[32]	LOADK    	11 -5	; "^(%d%d%d)(.?)"
	16	[32]	CALL     	9 3 0
	17	[32]	CALL     	7 0 3
	18	[32]	MOVE     	3 8
	19	[32]	MOVE     	1 7
	20	[33]	TEST     	1 0 1
	21	[33]	JMP      	3	; to 25
	22	[33]	LOADNIL  	7 7
	23	[33]	LOADK    	8 -6	; "invalid server reply"
	24	[33]	RETURN   	7 3
	25	[34]	EQ       	0 3 -7	; - "-"
	26	[34]	JMP      	28	; to 55
	27	[36]	SELF     	7 0 -1	; "receive"
	28	[36]	CALL     	7 2 3
	29	[36]	MOVE     	5 8
	30	[36]	MOVE     	4 7
	31	[37]	TEST     	5 0 0
	32	[37]	JMP      	3	; to 36
	33	[37]	LOADNIL  	7 7
	34	[37]	MOVE     	8 5
	35	[37]	RETURN   	7 3
	36	[38]	GETUPVAL 	7 0	; socket
	37	[38]	GETTABLE 	7 7 -2	; "skip"
	38	[38]	LOADK    	8 -3	; 2
	39	[38]	GETUPVAL 	9 1	; string
	40	[38]	GETTABLE 	9 9 -4	; "find"
	41	[38]	MOVE     	10 4
	42	[38]	LOADK    	11 -5	; "^(%d%d%d)(.?)"
	43	[38]	CALL     	9 3 0
	44	[38]	CALL     	7 0 3
	45	[38]	MOVE     	3 8
	46	[38]	MOVE     	2 7
	47	[39]	MOVE     	7 6
	48	[39]	LOADK    	8 -8	; "\n"
	49	[39]	MOVE     	9 4
	50	[39]	CONCAT   	6 7 9
	51	[41]	EQ       	0 1 2
	52	[41]	JMP      	-26	; to 27
	53	[41]	EQ       	0 3 -9	; - " "
	54	[41]	JMP      	-28	; to 27
	55	[43]	MOVE     	7 1
	56	[43]	MOVE     	8 6
	57	[43]	RETURN   	7 3
	58	[44]	RETURN   	0 1

function <./socket/tp.lua:49,65> (71 instructions, 284 bytes at 0x7fdb34406a80)
2 params, 12 slots, 3 upvalues, 9 locals, 7 constants, 0 functions
	1	[50]	GETUPVAL 	2 0	; get_reply
	2	[50]	GETTABLE 	3 0 -1	; "c"
	3	[50]	CALL     	2 2 3
	4	[51]	TEST     	2 0 1
	5	[51]	JMP      	3	; to 9
	6	[51]	LOADNIL  	4 4
	7	[51]	MOVE     	5 3
	8	[51]	RETURN   	4 3
	9	[52]	GETUPVAL 	4 1	; base
	10	[52]	GETTABLE 	4 4 -2	; "type"
	11	[52]	MOVE     	5 1
	12	[52]	CALL     	4 2 2
	13	[52]	EQ       	1 4 -3	; - "function"
	14	[52]	JMP      	48	; to 63
	15	[53]	GETUPVAL 	4 1	; base
	16	[53]	GETTABLE 	4 4 -2	; "type"
	17	[53]	MOVE     	5 1
	18	[53]	CALL     	4 2 2
	19	[53]	EQ       	0 4 -4	; - "table"
	20	[53]	JMP      	24	; to 45
	21	[54]	GETUPVAL 	4 1	; base
	22	[54]	GETTABLE 	4 4 -5	; "ipairs"
	23	[54]	MOVE     	5 1
	24	[54]	CALL     	4 2 4
	25	[54]	JMP      	13	; to 39
	26	[55]	GETUPVAL 	9 2	; string
	27	[55]	GETTABLE 	9 9 -6	; "find"
	28	[55]	MOVE     	10 2
	29	[55]	MOVE     	11 8
	30	[55]	CALL     	9 3 2
	31	[55]	TEST     	9 0 0
	32	[55]	JMP      	6	; to 39
	33	[56]	GETUPVAL 	9 1	; base
	34	[56]	GETTABLE 	9 9 -7	; "tonumber"
	35	[56]	MOVE     	10 2
	36	[56]	CALL     	9 2 2
	37	[56]	MOVE     	10 3
	38	[56]	RETURN   	9 3
	39	[54]	TFORLOOP 	4 2
	40	[57]	JMP      	-15	; to 26
	41	[59]	LOADNIL  	4 4
	42	[59]	MOVE     	5 3
	43	[59]	RETURN   	4 3
	44	[59]	JMP      	26	; to 71
	45	[61]	GETUPVAL 	4 2	; string
	46	[61]	GETTABLE 	4 4 -6	; "find"
	47	[61]	MOVE     	5 2
	48	[61]	MOVE     	6 1
	49	[61]	CALL     	4 3 2
	50	[61]	TEST     	4 0 0
	51	[61]	JMP      	7	; to 59
	52	[61]	GETUPVAL 	4 1	; base
	53	[61]	GETTABLE 	4 4 -7	; "tonumber"
	54	[61]	MOVE     	5 2
	55	[61]	CALL     	4 2 2
	56	[61]	MOVE     	5 3
	57	[61]	RETURN   	4 3
	58	[61]	JMP      	12	; to 71
	59	[62]	LOADNIL  	4 4
	60	[62]	MOVE     	5 3
	61	[62]	RETURN   	4 3
	62	[63]	JMP      	8	; to 71
	63	[64]	MOVE     	4 1
	64	[64]	GETUPVAL 	5 1	; base
	65	[64]	GETTABLE 	5 5 -7	; "tonumber"
	66	[64]	MOVE     	6 2
	67	[64]	CALL     	5 2 2
	68	[64]	MOVE     	6 3
	69	[64]	TAILCALL 	4 3 0
	70	[64]	RETURN   	4 0
	71	[65]	RETURN   	0 1

function <./socket/tp.lua:67,74> (25 instructions, 100 bytes at 0x7fdb34407790)
3 params, 9 slots, 1 upvalue, 3 locals, 5 constants, 0 functions
	1	[68]	GETUPVAL 	3 0	; string
	2	[68]	GETTABLE 	3 3 -1	; "upper"
	3	[68]	MOVE     	4 1
	4	[68]	CALL     	3 2 2
	5	[68]	MOVE     	1 3
	6	[69]	TEST     	2 0 0
	7	[69]	JMP      	10	; to 18
	8	[70]	GETTABLE 	3 0 -2	; "c"
	9	[70]	SELF     	3 3 -3	; "send"
	10	[70]	MOVE     	5 1
	11	[70]	LOADK    	6 -4	; " "
	12	[70]	MOVE     	7 2
	13	[70]	LOADK    	8 -5	; "\r\n"
	14	[70]	CONCAT   	5 5 8
	15	[70]	TAILCALL 	3 3 0
	16	[70]	RETURN   	3 0
	17	[70]	JMP      	7	; to 25
	18	[72]	GETTABLE 	3 0 -2	; "c"
	19	[72]	SELF     	3 3 -3	; "send"
	20	[72]	MOVE     	5 1
	21	[72]	LOADK    	6 -5	; "\r\n"
	22	[72]	CONCAT   	5 5 6
	23	[72]	TAILCALL 	3 3 0
	24	[72]	RETURN   	3 0
	25	[74]	RETURN   	0 1

function <./socket/tp.lua:76,79> (10 instructions, 40 bytes at 0x7fdb34407ae0)
3 params, 8 slots, 0 upvalues, 5 locals, 2 constants, 0 functions
	1	[77]	GETGLOBAL	3 -1	; c
	2	[77]	SELF     	3 3 -2	; "receive"
	3	[77]	MOVE     	5 2
	4	[77]	CALL     	3 3 3
	5	[78]	MOVE     	5 1
	6	[78]	MOVE     	6 3
	7	[78]	MOVE     	7 4
	8	[78]	TAILCALL 	5 3 0
	9	[78]	RETURN   	5 0
	10	[79]	RETURN   	0 1

function <./socket/tp.lua:81,83> (6 instructions, 24 bytes at 0x7fdb34407510)
2 params, 5 slots, 0 upvalues, 2 locals, 2 constants, 0 functions
	1	[82]	GETTABLE 	2 0 -1	; "c"
	2	[82]	SELF     	2 2 -2	; "send"
	3	[82]	MOVE     	4 1
	4	[82]	TAILCALL 	2 3 0
	5	[82]	RETURN   	2 0
	6	[83]	RETURN   	0 1

function <./socket/tp.lua:85,87> (6 instructions, 24 bytes at 0x7fdb34408810)
2 params, 5 slots, 0 upvalues, 2 locals, 2 constants, 0 functions
	1	[86]	GETTABLE 	2 0 -1	; "c"
	2	[86]	SELF     	2 2 -2	; "receive"
	3	[86]	MOVE     	4 1
	4	[86]	TAILCALL 	2 3 0
	5	[86]	RETURN   	2 0
	6	[87]	RETURN   	0 1

function <./socket/tp.lua:89,91> (5 instructions, 20 bytes at 0x7fdb34408aa0)
1 param, 3 slots, 0 upvalues, 1 local, 2 constants, 0 functions
	1	[90]	GETTABLE 	1 0 -1	; "c"
	2	[90]	SELF     	1 1 -2	; "getfd"
	3	[90]	TAILCALL 	1 2 0
	4	[90]	RETURN   	1 0
	5	[91]	RETURN   	0 1

function <./socket/tp.lua:93,95> (5 instructions, 20 bytes at 0x7fdb34408ce0)
1 param, 3 slots, 0 upvalues, 1 local, 2 constants, 0 functions
	1	[94]	GETTABLE 	1 0 -1	; "c"
	2	[94]	SELF     	1 1 -2	; "dirty"
	3	[94]	TAILCALL 	1 2 0
	4	[94]	RETURN   	1 0
	5	[95]	RETURN   	0 1

function <./socket/tp.lua:97,99> (3 instructions, 12 bytes at 0x7fdb34408f90)
1 param, 2 slots, 0 upvalues, 1 local, 1 constant, 0 functions
	1	[98]	GETTABLE 	1 0 -1	; "c"
	2	[98]	RETURN   	1 2
	3	[99]	RETURN   	0 1

function <./socket/tp.lua:101,105> (20 instructions, 80 bytes at 0x7fdb34408e90)
3 params, 8 slots, 2 upvalues, 6 locals, 6 constants, 0 functions
	1	[102]	GETUPVAL 	3 0	; socket
	2	[102]	GETTABLE 	3 3 -1	; "sink"
	3	[102]	LOADK    	4 -2	; "keep-open"
	4	[102]	GETTABLE 	5 0 -3	; "c"
	5	[102]	CALL     	3 3 2
	6	[103]	GETUPVAL 	4 1	; ltn12
	7	[103]	GETTABLE 	4 4 -4	; "pump"
	8	[103]	GETTABLE 	4 4 -5	; "all"
	9	[103]	MOVE     	5 1
	10	[103]	MOVE     	6 3
	11	[103]	TESTSET  	7 2 1
	12	[103]	JMP      	3	; to 16
	13	[103]	GETUPVAL 	7 1	; ltn12
	14	[103]	GETTABLE 	7 7 -4	; "pump"
	15	[103]	GETTABLE 	7 7 -6	; "step"
	16	[103]	CALL     	4 4 3
	17	[104]	MOVE     	6 4
	18	[104]	MOVE     	7 5
	19	[104]	RETURN   	6 3
	20	[105]	RETURN   	0 1

function <./socket/tp.lua:108,111> (6 instructions, 24 bytes at 0x7fdb344088b0)
1 param, 3 slots, 0 upvalues, 1 local, 3 constants, 0 functions
	1	[109]	GETTABLE 	1 0 -1	; "c"
	2	[109]	SELF     	1 1 -2	; "close"
	3	[109]	CALL     	1 2 1
	4	[110]	LOADK    	1 -3	; 1
	5	[110]	RETURN   	1 2
	6	[111]	RETURN   	0 1

function <./socket/tp.lua:114,124> (35 instructions, 140 bytes at 0x7fdb34408930)
4 params, 11 slots, 4 upvalues, 8 locals, 7 constants, 0 functions
	1	[115]	TESTSET  	4 3 1
	2	[115]	JMP      	2	; to 5
	3	[115]	GETUPVAL 	4 0	; socket
	4	[115]	GETTABLE 	4 4 -1	; "tcp"
	5	[115]	CALL     	4 1 3
	6	[116]	TEST     	4 0 1
	7	[116]	JMP      	3	; to 11
	8	[116]	LOADNIL  	6 6
	9	[116]	MOVE     	7 5
	10	[116]	RETURN   	6 3
	11	[117]	SELF     	6 4 -2	; "settimeout"
	12	[117]	TESTSET  	8 2 1
	13	[117]	JMP      	2	; to 16
	14	[117]	GETUPVAL 	8 1	; _M
	15	[117]	GETTABLE 	8 8 -3	; "TIMEOUT"
	16	[117]	CALL     	6 3 1
	17	[118]	SELF     	6 4 -4	; "connect"
	18	[118]	MOVE     	8 0
	19	[118]	MOVE     	9 1
	20	[118]	CALL     	6 4 3
	21	[119]	TEST     	6 0 1
	22	[119]	JMP      	5	; to 28
	23	[120]	SELF     	8 4 -5	; "close"
	24	[120]	CALL     	8 2 1
	25	[121]	LOADNIL  	8 8
	26	[121]	MOVE     	9 7
	27	[121]	RETURN   	8 3
	28	[123]	GETUPVAL 	8 2	; base
	29	[123]	GETTABLE 	8 8 -6	; "setmetatable"
	30	[123]	NEWTABLE 	9 0 1
	31	[123]	SETTABLE 	9 -7 4	; "c" -
	32	[123]	GETUPVAL 	10 3	; metat
	33	[123]	TAILCALL 	8 3 0
	34	[123]	RETURN   	8 0
	35	[124]	RETURN   	0 1
-----------------------

main <./socket/headers.lua:0,0> (101 instructions, 404 bytes at 0x7fca95c068a0)
0+ params, 3 slots, 0 upvalues, 2 locals, 186 constants, 0 functions
	1	[6]	GETGLOBAL	0 -1	; require
	2	[6]	LOADK    	1 -2	; "socket"
	3	[6]	CALL     	0 2 2
	4	[7]	NEWTABLE 	1 0 0
	5	[7]	SETTABLE 	0 -3 1	; "headers" -
	6	[8]	GETTABLE 	1 0 -3	; "headers"
	7	[10]	NEWTABLE 	2 0 36
	8	[11]	SETTABLE 	2 -5 -6	; "accept" "Accept"
	9	[12]	SETTABLE 	2 -7 -8	; "accept-charset" "Accept-Charset"
	10	[13]	SETTABLE 	2 -9 -10	; "accept-encoding" "Accept-Encoding"
	11	[14]	SETTABLE 	2 -11 -12	; "accept-language" "Accept-Language"
	12	[15]	SETTABLE 	2 -13 -14	; "accept-ranges" "Accept-Ranges"
	13	[16]	SETTABLE 	2 -15 -16	; "action" "Action"
	14	[17]	SETTABLE 	2 -17 -18	; "alternate-recipient" "Alternate-Recipient"
	15	[18]	SETTABLE 	2 -19 -20	; "age" "Age"
	16	[19]	SETTABLE 	2 -21 -22	; "allow" "Allow"
	17	[20]	SETTABLE 	2 -23 -24	; "arrival-date" "Arrival-Date"
	18	[21]	SETTABLE 	2 -25 -26	; "authorization" "Authorization"
	19	[22]	SETTABLE 	2 -27 -28	; "bcc" "Bcc"
	20	[23]	SETTABLE 	2 -29 -30	; "cache-control" "Cache-Control"
	21	[24]	SETTABLE 	2 -31 -32	; "cc" "Cc"
	22	[25]	SETTABLE 	2 -33 -34	; "comments" "Comments"
	23	[26]	SETTABLE 	2 -35 -36	; "connection" "Connection"
	24	[27]	SETTABLE 	2 -37 -38	; "content-description" "Content-Description"
	25	[28]	SETTABLE 	2 -39 -40	; "content-disposition" "Content-Disposition"
	26	[29]	SETTABLE 	2 -41 -42	; "content-encoding" "Content-Encoding"
	27	[30]	SETTABLE 	2 -43 -44	; "content-id" "Content-ID"
	28	[31]	SETTABLE 	2 -45 -46	; "content-language" "Content-Language"
	29	[32]	SETTABLE 	2 -47 -48	; "content-length" "Content-Length"
	30	[33]	SETTABLE 	2 -49 -50	; "content-location" "Content-Location"
	31	[34]	SETTABLE 	2 -51 -52	; "content-md5" "Content-MD5"
	32	[35]	SETTABLE 	2 -53 -54	; "content-range" "Content-Range"
	33	[36]	SETTABLE 	2 -55 -56	; "content-transfer-encoding" "Content-Transfer-Encoding"
	34	[37]	SETTABLE 	2 -57 -58	; "content-type" "Content-Type"
	35	[38]	SETTABLE 	2 -59 -60	; "cookie" "Cookie"
	36	[39]	SETTABLE 	2 -61 -62	; "date" "Date"
	37	[40]	SETTABLE 	2 -63 -64	; "diagnostic-code" "Diagnostic-Code"
	38	[41]	SETTABLE 	2 -65 -66	; "dsn-gateway" "DSN-Gateway"
	39	[42]	SETTABLE 	2 -67 -68	; "etag" "ETag"
	40	[43]	SETTABLE 	2 -69 -70	; "expect" "Expect"
	41	[44]	SETTABLE 	2 -71 -72	; "expires" "Expires"
	42	[45]	SETTABLE 	2 -73 -74	; "final-log-id" "Final-Log-ID"
	43	[46]	SETTABLE 	2 -75 -76	; "final-recipient" "Final-Recipient"
	44	[47]	SETTABLE 	2 -77 -78	; "from" "From"
	45	[48]	SETTABLE 	2 -79 -80	; "host" "Host"
	46	[49]	SETTABLE 	2 -81 -82	; "if-match" "If-Match"
	47	[50]	SETTABLE 	2 -83 -84	; "if-modified-since" "If-Modified-Since"
	48	[51]	SETTABLE 	2 -85 -86	; "if-none-match" "If-None-Match"
	49	[52]	SETTABLE 	2 -87 -88	; "if-range" "If-Range"
	50	[53]	SETTABLE 	2 -89 -90	; "if-unmodified-since" "If-Unmodified-Since"
	51	[54]	SETTABLE 	2 -91 -92	; "in-reply-to" "In-Reply-To"
	52	[55]	SETTABLE 	2 -93 -94	; "keywords" "Keywords"
	53	[56]	SETTABLE 	2 -95 -96	; "last-attempt-date" "Last-Attempt-Date"
	54	[57]	SETTABLE 	2 -97 -98	; "last-modified" "Last-Modified"
	55	[58]	SETTABLE 	2 -99 -100	; "location" "Location"
	56	[59]	SETTABLE 	2 -101 -102	; "max-forwards" "Max-Forwards"
	57	[60]	SETTABLE 	2 -103 -104	; "message-id" "Message-ID"
	58	[61]	SETTABLE 	2 -105 -106	; "mime-version" "MIME-Version"
	59	[62]	SETTABLE 	2 -107 -108	; "original-envelope-id" "Original-Envelope-ID"
	60	[63]	SETTABLE 	2 -109 -110	; "original-recipient" "Original-Recipient"
	61	[64]	SETTABLE 	2 -111 -112	; "pragma" "Pragma"
	62	[65]	SETTABLE 	2 -113 -114	; "proxy-authenticate" "Proxy-Authenticate"
	63	[66]	SETTABLE 	2 -115 -116	; "proxy-authorization" "Proxy-Authorization"
	64	[67]	SETTABLE 	2 -117 -118	; "range" "Range"
	65	[68]	SETTABLE 	2 -119 -120	; "received" "Received"
	66	[69]	SETTABLE 	2 -121 -122	; "received-from-mta" "Received-From-MTA"
	67	[70]	SETTABLE 	2 -123 -124	; "references" "References"
	68	[71]	SETTABLE 	2 -125 -126	; "referer" "Referer"
	69	[72]	SETTABLE 	2 -127 -128	; "remote-mta" "Remote-MTA"
	70	[73]	SETTABLE 	2 -129 -130	; "reply-to" "Reply-To"
	71	[74]	SETTABLE 	2 -131 -132	; "reporting-mta" "Reporting-MTA"
	72	[75]	SETTABLE 	2 -133 -134	; "resent-bcc" "Resent-Bcc"
	73	[76]	SETTABLE 	2 -135 -136	; "resent-cc" "Resent-Cc"
	74	[77]	SETTABLE 	2 -137 -138	; "resent-date" "Resent-Date"
	75	[78]	SETTABLE 	2 -139 -140	; "resent-from" "Resent-From"
	76	[79]	SETTABLE 	2 -141 -142	; "resent-message-id" "Resent-Message-ID"
	77	[80]	SETTABLE 	2 -143 -144	; "resent-reply-to" "Resent-Reply-To"
	78	[81]	SETTABLE 	2 -145 -146	; "resent-sender" "Resent-Sender"
	79	[82]	SETTABLE 	2 -147 -148	; "resent-to" "Resent-To"
	80	[83]	SETTABLE 	2 -149 -150	; "retry-after" "Retry-After"
	81	[84]	SETTABLE 	2 -151 -152	; "return-path" "Return-Path"
	82	[85]	SETTABLE 	2 -153 -154	; "sender" "Sender"
	83	[86]	SETTABLE 	2 -155 -156	; "server" "Server"
	84	[87]	SETTABLE 	2 -157 -158	; "smtp-remote-recipient" "SMTP-Remote-Recipient"
	85	[88]	SETTABLE 	2 -159 -160	; "status" "Status"
	86	[89]	SETTABLE 	2 -161 -162	; "subject" "Subject"
	87	[90]	SETTABLE 	2 -163 -164	; "te" "TE"
	88	[91]	SETTABLE 	2 -165 -166	; "to" "To"
	89	[92]	SETTABLE 	2 -167 -168	; "trailer" "Trailer"
	90	[93]	SETTABLE 	2 -169 -170	; "transfer-encoding" "Transfer-Encoding"
	91	[94]	SETTABLE 	2 -171 -172	; "upgrade" "Upgrade"
	92	[95]	SETTABLE 	2 -173 -174	; "user-agent" "User-Agent"
	93	[96]	SETTABLE 	2 -175 -176	; "vary" "Vary"
	94	[97]	SETTABLE 	2 -177 -178	; "via" "Via"
	95	[98]	SETTABLE 	2 -179 -180	; "warning" "Warning"
	96	[99]	SETTABLE 	2 -181 -182	; "will-retry-until" "Will-Retry-Until"
	97	[100]	SETTABLE 	2 -183 -184	; "www-authenticate" "WWW-Authenticate"
	98	[101]	SETTABLE 	2 -185 -186	; "x-mailer" "X-Mailer"
	99	[102]	SETTABLE 	1 -4 2	; "canonic" -
	100	[104]	RETURN   	1 2
	101	[104]	RETURN   	0 1
-----------------------

main <./socket/http.lua:0,0> (143 instructions, 572 bytes at 0x7fe9394068a0)
0+ params, 23 slots, 0 upvalues, 21 locals, 37 constants, 22 functions
	1	[10]	GETGLOBAL	0 -1	; require
	2	[10]	LOADK    	1 -2	; "socket"
	3	[10]	CALL     	0 2 2
	4	[11]	GETGLOBAL	1 -1	; require
	5	[11]	LOADK    	2 -3	; "socket.url"
	6	[11]	CALL     	1 2 2
	7	[12]	GETGLOBAL	2 -1	; require
	8	[12]	LOADK    	3 -4	; "ltn12"
	9	[12]	CALL     	2 2 2
	10	[13]	GETGLOBAL	3 -1	; require
	11	[13]	LOADK    	4 -5	; "mime"
	12	[13]	CALL     	3 2 2
	13	[14]	GETGLOBAL	4 -1	; require
	14	[14]	LOADK    	5 -6	; "string"
	15	[14]	CALL     	4 2 2
	16	[15]	GETGLOBAL	5 -1	; require
	17	[15]	LOADK    	6 -7	; "socket.headers"
	18	[15]	CALL     	5 2 2
	19	[16]	GETGLOBAL	6 -8	; _G
	20	[17]	GETGLOBAL	7 -1	; require
	21	[17]	LOADK    	8 -9	; "table"
	22	[17]	CALL     	7 2 2
	23	[18]	NEWTABLE 	8 0 0
	24	[18]	SETTABLE 	0 -10 8	; "http" -
	25	[19]	GETTABLE 	8 0 -10	; "http"
	26	[25]	LOADK    	9 -12	; 60
	27	[25]	SETGLOBAL	9 -11	; TIMEOUT
	28	[27]	SETTABLE 	8 -13 -14	; "PORT" 80
	29	[29]	GETTABLE 	9 0 -16	; "_VERSION"
	30	[29]	SETTABLE 	8 -15 9	; "USERAGENT" -
	31	[60]	CLOSURE  	9 0	; 0x7fe939406d50
	32	[60]	MOVE     	0 0
	33	[60]	MOVE     	0 4
	34	[65]	GETTABLE 	10 0 -17	; "sourcet"
	35	[89]	CLOSURE  	11 1	; 0x7fe939406c10
	36	[89]	MOVE     	0 6
	37	[89]	MOVE     	0 4
	38	[89]	MOVE     	0 9
	39	[89]	SETTABLE 	10 -18 11	; "http-chunked" -
	40	[91]	GETTABLE 	10 0 -19	; "sinkt"
	41	[102]	CLOSURE  	11 2	; 0x7fe939408430
	42	[102]	MOVE     	0 6
	43	[102]	MOVE     	0 4
	44	[102]	SETTABLE 	10 -18 11	; "http-chunked" -
	45	[107]	NEWTABLE 	10 0 1
	46	[107]	NEWTABLE 	11 0 0
	47	[107]	SETTABLE 	10 -20 11	; "__index" -
	48	[120]	CLOSURE  	11 3	; 0x7fe939408c80
	49	[120]	MOVE     	0 0
	50	[120]	MOVE     	0 6
	51	[120]	MOVE     	0 10
	52	[120]	MOVE     	0 8
	53	[109]	SETTABLE 	8 -21 11	; "open" -
	54	[122]	GETTABLE 	11 10 -20	; "__index"
	55	[125]	CLOSURE  	12 4	; 0x7fe939409720
	56	[125]	MOVE     	0 4
	57	[122]	SETTABLE 	11 -22 12	; "sendrequestline" -
	58	[127]	GETTABLE 	11 10 -20	; "__index"
	59	[135]	CLOSURE  	12 5	; 0x7fe939409a00
	60	[135]	MOVE     	0 5
	61	[135]	MOVE     	0 6
	62	[127]	SETTABLE 	11 -23 12	; "sendheaders" -
	63	[137]	GETTABLE 	11 10 -20	; "__index"
	64	[144]	CLOSURE  	12 6	; 0x7fe93940a0f0
	65	[144]	MOVE     	0 2
	66	[144]	MOVE     	0 0
	67	[137]	SETTABLE 	11 -24 12	; "sendbody" -
	68	[146]	GETTABLE 	11 10 -20	; "__index"
	69	[155]	CLOSURE  	12 7	; 0x7fe93940a450
	70	[155]	MOVE     	0 0
	71	[155]	MOVE     	0 4
	72	[155]	MOVE     	0 6
	73	[146]	SETTABLE 	11 -25 12	; "receivestatusline" -
	74	[157]	GETTABLE 	11 10 -20	; "__index"
	75	[159]	CLOSURE  	12 8	; 0x7fe93940a6b0
	76	[159]	MOVE     	0 9
	77	[157]	SETTABLE 	11 -26 12	; "receiveheaders" -
	78	[161]	GETTABLE 	11 10 -20	; "__index"
	79	[171]	CLOSURE  	12 9	; 0x7fe93940af50
	80	[171]	MOVE     	0 2
	81	[171]	MOVE     	0 6
	82	[171]	MOVE     	0 0
	83	[161]	SETTABLE 	11 -27 12	; "receivebody" -
	84	[173]	GETTABLE 	11 10 -20	; "__index"
	85	[177]	CLOSURE  	12 10	; 0x7fe93940b650
	86	[177]	MOVE     	0 2
	87	[177]	MOVE     	0 0
	88	[173]	SETTABLE 	11 -28 12	; "receive09body" -
	89	[179]	GETTABLE 	11 10 -20	; "__index"
	90	[181]	CLOSURE  	12 11	; 0x7fe93940b990
	91	[179]	SETTABLE 	11 -29 12	; "close" -
	92	[198]	CLOSURE  	11 12	; 0x7fe93940ba10
	93	[198]	MOVE     	0 0
	94	[198]	MOVE     	0 1
	95	[208]	CLOSURE  	12 13	; 0x7fe93940be60
	96	[208]	MOVE     	0 1
	97	[228]	CLOSURE  	13 14	; 0x7fe93940c670
	98	[228]	MOVE     	0 8
	99	[228]	MOVE     	0 3
	100	[228]	MOVE     	0 6
	101	[228]	MOVE     	0 4
	102	[231]	NEWTABLE 	14 0 4
	103	[232]	SETTABLE 	14 -30 -31	; "host" ""
	104	[233]	GETTABLE 	15 8 -13	; "PORT"
	105	[233]	SETTABLE 	14 -32 15	; "port" -
	106	[234]	SETTABLE 	14 -33 -34	; "path" "/"
	107	[235]	SETTABLE 	14 -35 -10	; "scheme" "http"
	108	[253]	CLOSURE  	15 15	; 0x7fe93940c760
	109	[253]	MOVE     	0 1
	110	[253]	MOVE     	0 14
	111	[253]	MOVE     	0 6
	112	[253]	MOVE     	0 0
	113	[253]	MOVE     	0 11
	114	[253]	MOVE     	0 12
	115	[253]	MOVE     	0 13
	116	[262]	CLOSURE  	16 16	; 0x7fe939409140
	117	[262]	MOVE     	0 4
	118	[269]	CLOSURE  	17 17	; 0x7fe93940aed0
	119	[272]	LOADNIL  	18 19
	120	[290]	CLOSURE  	19 18	; 0x7fe9394071d0
	121	[290]	MOVE     	0 18
	122	[274]	MOVE     	0 1
	123	[329]	CLOSURE  	18 19	; 0x7fe93940cdf0
	124	[329]	MOVE     	0 15
	125	[329]	MOVE     	0 8
	126	[329]	MOVE     	0 16
	127	[329]	MOVE     	0 19
	128	[292]	MOVE     	0 17
	129	[347]	CLOSURE  	20 20	; 0x7fe93940d5e0
	130	[347]	MOVE     	0 2
	131	[347]	MOVE     	0 4
	132	[347]	MOVE     	0 0
	133	[347]	MOVE     	0 18
	134	[347]	MOVE     	0 7
	135	[349]	GETTABLE 	21 0 -37	; "protect"
	136	[352]	CLOSURE  	22 21	; 0x7fe93940dcc0
	137	[352]	MOVE     	0 6
	138	[352]	MOVE     	0 20
	139	[352]	MOVE     	0 18
	140	[349]	CALL     	21 2 2
	141	[352]	SETTABLE 	8 -36 21	; "request" -
	142	[354]	RETURN   	8 2
	143	[354]	RETURN   	0 1

function <./socket/http.lua:34,60> (79 instructions, 316 bytes at 0x7fe939406d50)
2 params, 11 slots, 2 upvalues, 6 locals, 10 constants, 0 functions
	1	[36]	TEST     	1 0 1
	2	[36]	JMP      	2	; to 5
	3	[36]	NEWTABLE 	6 0 0
	4	[36]	MOVE     	1 6
	5	[38]	SELF     	6 0 -1	; "receive"
	6	[38]	CALL     	6 2 3
	7	[38]	MOVE     	5 7
	8	[38]	MOVE     	2 6
	9	[39]	TEST     	5 0 0
	10	[39]	JMP      	3	; to 14
	11	[39]	LOADNIL  	6 6
	12	[39]	MOVE     	7 5
	13	[39]	RETURN   	6 3
	14	[41]	EQ       	1 2 -2	; - ""
	15	[41]	JMP      	62	; to 78
	16	[43]	GETUPVAL 	6 0	; socket
	17	[43]	GETTABLE 	6 6 -3	; "skip"
	18	[43]	LOADK    	7 -4	; 2
	19	[43]	GETUPVAL 	8 1	; string
	20	[43]	GETTABLE 	8 8 -5	; "find"
	21	[43]	MOVE     	9 2
	22	[43]	LOADK    	10 -6	; "^(.-):%s*(.*)"
	23	[43]	CALL     	8 3 0
	24	[43]	CALL     	6 0 3
	25	[43]	MOVE     	4 7
	26	[43]	MOVE     	3 6
	27	[44]	TEST     	3 0 0
	28	[44]	JMP      	2	; to 31
	29	[44]	TEST     	4 0 1
	30	[44]	JMP      	3	; to 34
	31	[44]	LOADNIL  	6 6
	32	[44]	LOADK    	7 -7	; "malformed reponse headers"
	33	[44]	RETURN   	6 3
	34	[45]	GETUPVAL 	6 1	; string
	35	[45]	GETTABLE 	6 6 -8	; "lower"
	36	[45]	MOVE     	7 3
	37	[45]	CALL     	6 2 2
	38	[45]	MOVE     	3 6
	39	[47]	SELF     	6 0 -1	; "receive"
	40	[47]	CALL     	6 2 3
	41	[47]	MOVE     	5 7
	42	[47]	MOVE     	2 6
	43	[48]	TEST     	5 0 0
	44	[48]	JMP      	3	; to 48
	45	[48]	LOADNIL  	6 6
	46	[48]	MOVE     	7 5
	47	[48]	RETURN   	6 3
	48	[50]	GETUPVAL 	6 1	; string
	49	[50]	GETTABLE 	6 6 -5	; "find"
	50	[50]	MOVE     	7 2
	51	[50]	LOADK    	8 -9	; "^%s"
	52	[50]	CALL     	6 3 2
	53	[50]	TEST     	6 0 0
	54	[50]	JMP      	12	; to 67
	55	[51]	MOVE     	6 4
	56	[51]	MOVE     	7 2
	57	[51]	CONCAT   	4 6 7
	58	[52]	SELF     	6 0 -1	; "receive"
	59	[52]	CALL     	6 2 2
	60	[52]	MOVE     	2 6
	61	[53]	TEST     	5 0 0
	62	[53]	JMP      	-15	; to 48
	63	[53]	LOADNIL  	6 6
	64	[53]	MOVE     	7 5
	65	[53]	RETURN   	6 3
	66	[53]	JMP      	-19	; to 48
	67	[56]	GETTABLE 	6 1 3
	68	[56]	TEST     	6 0 0
	69	[56]	JMP      	6	; to 76
	70	[56]	GETTABLE 	6 1 3
	71	[56]	LOADK    	7 -10	; ", "
	72	[56]	MOVE     	8 4
	73	[56]	CONCAT   	6 6 8
	74	[56]	SETTABLE 	1 3 6
	75	[56]	JMP      	-62	; to 14
	76	[57]	SETTABLE 	1 3 4
	77	[57]	JMP      	-64	; to 14
	78	[59]	RETURN   	1 2
	79	[60]	RETURN   	0 1

function <./socket/http.lua:65,89> (20 instructions, 80 bytes at 0x7fe939406c10)
2 params, 6 slots, 3 upvalues, 2 locals, 4 constants, 3 functions
	1	[66]	GETUPVAL 	2 0	; base
	2	[66]	GETTABLE 	2 2 -1	; "setmetatable"
	3	[66]	NEWTABLE 	3 0 2
	4	[67]	CLOSURE  	4 0	; 0x7fe939407050
	5	[67]	MOVE     	0 0
	6	[67]	SETTABLE 	3 -2 4	; "getfd" -
	7	[68]	CLOSURE  	4 1	; 0x7fe939407d70
	8	[68]	MOVE     	0 0
	9	[68]	SETTABLE 	3 -3 4	; "dirty" -
	10	[69]	NEWTABLE 	4 0 1
	11	[87]	CLOSURE  	5 2	; 0x7fe939407bd0
	12	[87]	MOVE     	0 0
	13	[87]	GETUPVAL 	0 0	; base
	14	[87]	GETUPVAL 	0 1	; string
	15	[87]	MOVE     	0 1
	16	[87]	GETUPVAL 	0 2	; receiveheaders
	17	[87]	SETTABLE 	4 -4 5	; "__call" -
	18	[66]	TAILCALL 	2 3 0
	19	[88]	RETURN   	2 0
	20	[89]	RETURN   	0 1

function <./socket/http.lua:67,67> (5 instructions, 20 bytes at 0x7fe939407050)
0 params, 2 slots, 1 upvalue, 0 locals, 1 constant, 0 functions
	1	[67]	GETUPVAL 	0 0	; sock
	2	[67]	SELF     	0 0 -1	; "getfd"
	3	[67]	TAILCALL 	0 2 0
	4	[67]	RETURN   	0 0
	5	[67]	RETURN   	0 1

function <./socket/http.lua:68,68> (5 instructions, 20 bytes at 0x7fe939407d70)
0 params, 2 slots, 1 upvalue, 0 locals, 1 constant, 0 functions
	1	[68]	GETUPVAL 	0 0	; sock
	2	[68]	SELF     	0 0 -1	; "dirty"
	3	[68]	TAILCALL 	0 2 0
	4	[68]	RETURN   	0 0
	5	[68]	RETURN   	0 1

function <./socket/http.lua:70,87> (51 instructions, 204 bytes at 0x7fe939407bd0)
0 params, 8 slots, 5 upvalues, 6 locals, 8 constants, 0 functions
	1	[72]	GETUPVAL 	0 0	; sock
	2	[72]	SELF     	0 0 -1	; "receive"
	3	[72]	CALL     	0 2 3
	4	[73]	TEST     	1 0 0
	5	[73]	JMP      	3	; to 9
	6	[73]	LOADNIL  	2 2
	7	[73]	MOVE     	3 1
	8	[73]	RETURN   	2 3
	9	[74]	GETUPVAL 	2 1	; base
	10	[74]	GETTABLE 	2 2 -2	; "tonumber"
	11	[74]	GETUPVAL 	3 2	; string
	12	[74]	GETTABLE 	3 3 -3	; "gsub"
	13	[74]	MOVE     	4 0
	14	[74]	LOADK    	5 -4	; ";.*"
	15	[74]	LOADK    	6 -5	; ""
	16	[74]	CALL     	3 4 2
	17	[74]	LOADK    	4 -6	; 16
	18	[74]	CALL     	2 3 2
	19	[75]	TEST     	2 0 1
	20	[75]	JMP      	3	; to 24
	21	[75]	LOADNIL  	3 3
	22	[75]	LOADK    	4 -7	; "invalid chunk size"
	23	[75]	RETURN   	3 3
	24	[77]	LT       	0 -8 2	; 0 -
	25	[77]	JMP      	13	; to 39
	26	[79]	GETUPVAL 	3 0	; sock
	27	[79]	SELF     	3 3 -1	; "receive"
	28	[79]	MOVE     	5 2
	29	[79]	CALL     	3 3 4
	30	[80]	TEST     	3 0 0
	31	[80]	JMP      	3	; to 35
	32	[80]	GETUPVAL 	6 0	; sock
	33	[80]	SELF     	6 6 -1	; "receive"
	34	[80]	CALL     	6 2 1
	35	[81]	MOVE     	6 3
	36	[81]	MOVE     	7 4
	37	[81]	RETURN   	6 3
	38	[81]	JMP      	12	; to 51
	39	[84]	GETUPVAL 	3 4	; receiveheaders
	40	[84]	GETUPVAL 	4 0	; sock
	41	[84]	GETUPVAL 	5 3	; headers
	42	[84]	CALL     	3 3 3
	43	[84]	MOVE     	1 4
	44	[84]	SETUPVAL 	3 3	; headers
	45	[85]	GETUPVAL 	3 3	; headers
	46	[85]	TEST     	3 0 1
	47	[85]	JMP      	3	; to 51
	48	[85]	LOADNIL  	3 3
	49	[85]	MOVE     	4 1
	50	[85]	RETURN   	3 3
	51	[87]	RETURN   	0 1

function <./socket/http.lua:91,102> (17 instructions, 68 bytes at 0x7fe939408430)
1 param, 5 slots, 2 upvalues, 1 local, 4 constants, 3 functions
	1	[92]	GETUPVAL 	1 0	; base
	2	[92]	GETTABLE 	1 1 -1	; "setmetatable"
	3	[92]	NEWTABLE 	2 0 2
	4	[93]	CLOSURE  	3 0	; 0x7fe9394089f0
	5	[93]	MOVE     	0 0
	6	[93]	SETTABLE 	2 -2 3	; "getfd" -
	7	[94]	CLOSURE  	3 1	; 0x7fe939408b30
	8	[94]	MOVE     	0 0
	9	[94]	SETTABLE 	2 -3 3	; "dirty" -
	10	[95]	NEWTABLE 	3 0 1
	11	[100]	CLOSURE  	4 2	; 0x7fe939408db0
	12	[100]	MOVE     	0 0
	13	[100]	GETUPVAL 	0 1	; string
	14	[100]	SETTABLE 	3 -4 4	; "__call" -
	15	[92]	TAILCALL 	1 3 0
	16	[101]	RETURN   	1 0
	17	[102]	RETURN   	0 1

function <./socket/http.lua:93,93> (5 instructions, 20 bytes at 0x7fe9394089f0)
0 params, 2 slots, 1 upvalue, 0 locals, 1 constant, 0 functions
	1	[93]	GETUPVAL 	0 0	; sock
	2	[93]	SELF     	0 0 -1	; "getfd"
	3	[93]	TAILCALL 	0 2 0
	4	[93]	RETURN   	0 0
	5	[93]	RETURN   	0 1

function <./socket/http.lua:94,94> (5 instructions, 20 bytes at 0x7fe939408b30)
0 params, 2 slots, 1 upvalue, 0 locals, 1 constant, 0 functions
	1	[94]	GETUPVAL 	0 0	; sock
	2	[94]	SELF     	0 0 -1	; "dirty"
	3	[94]	TAILCALL 	0 2 0
	4	[94]	RETURN   	0 0
	5	[94]	RETURN   	0 1

function <./socket/http.lua:96,100> (24 instructions, 96 bytes at 0x7fe939408db0)
3 params, 9 slots, 2 upvalues, 4 locals, 6 constants, 0 functions
	1	[97]	TEST     	1 0 1
	2	[97]	JMP      	5	; to 8
	3	[97]	GETUPVAL 	3 0	; sock
	4	[97]	SELF     	3 3 -1	; "send"
	5	[97]	LOADK    	5 -2	; "0\r\n\r\n"
	6	[97]	TAILCALL 	3 3 0
	7	[97]	RETURN   	3 0
	8	[98]	GETUPVAL 	3 1	; string
	9	[98]	GETTABLE 	3 3 -3	; "format"
	10	[98]	LOADK    	4 -4	; "%X\r\n"
	11	[98]	GETUPVAL 	5 1	; string
	12	[98]	GETTABLE 	5 5 -5	; "len"
	13	[98]	MOVE     	6 1
	14	[98]	CALL     	5 2 0
	15	[98]	CALL     	3 0 2
	16	[99]	GETUPVAL 	4 0	; sock
	17	[99]	SELF     	4 4 -1	; "send"
	18	[99]	MOVE     	6 3
	19	[99]	MOVE     	7 1
	20	[99]	LOADK    	8 -6	; "\r\n"
	21	[99]	CONCAT   	6 6 8
	22	[99]	TAILCALL 	4 3 0
	23	[99]	RETURN   	4 0
	24	[100]	RETURN   	0 1

function <./socket/http.lua:109,120> (37 instructions, 148 bytes at 0x7fe939408c80)
3 params, 10 slots, 4 upvalues, 5 locals, 9 constants, 1 function
	1	[111]	GETUPVAL 	3 0	; socket
	2	[111]	GETTABLE 	3 3 -1	; "try"
	3	[111]	TESTSET  	4 2 1
	4	[111]	JMP      	2	; to 7
	5	[111]	GETUPVAL 	4 0	; socket
	6	[111]	GETTABLE 	4 4 -2	; "tcp"
	7	[111]	CALL     	4 1 0
	8	[111]	CALL     	3 0 2
	9	[112]	GETUPVAL 	4 1	; base
	10	[112]	GETTABLE 	4 4 -3	; "setmetatable"
	11	[112]	NEWTABLE 	5 0 1
	12	[112]	SETTABLE 	5 -4 3	; "c" -
	13	[112]	GETUPVAL 	6 2	; metat
	14	[112]	CALL     	4 3 2
	15	[114]	GETUPVAL 	5 0	; socket
	16	[114]	GETTABLE 	5 5 -5	; "newtry"
	17	[114]	CLOSURE  	6 0	; 0x7fe9394088b0
	18	[114]	MOVE     	0 4
	19	[114]	CALL     	5 2 2
	20	[114]	SETTABLE 	4 -1 5	; "try" -
	21	[116]	GETTABLE 	5 4 -1	; "try"
	22	[116]	SELF     	6 3 -6	; "settimeout"
	23	[116]	GETUPVAL 	8 3	; _M
	24	[116]	GETTABLE 	8 8 -7	; "TIMEOUT"
	25	[116]	CALL     	6 3 0
	26	[116]	CALL     	5 0 1
	27	[117]	GETTABLE 	5 4 -1	; "try"
	28	[117]	SELF     	6 3 -8	; "connect"
	29	[117]	MOVE     	8 0
	30	[117]	TESTSET  	9 1 1
	31	[117]	JMP      	2	; to 34
	32	[117]	GETUPVAL 	9 3	; _M
	33	[117]	GETTABLE 	9 9 -9	; "PORT"
	34	[117]	CALL     	6 4 0
	35	[117]	CALL     	5 0 1
	36	[119]	RETURN   	4 2
	37	[120]	RETURN   	0 1

function <./socket/http.lua:114,114> (4 instructions, 16 bytes at 0x7fe9394088b0)
0 params, 2 slots, 1 upvalue, 0 locals, 1 constant, 0 functions
	1	[114]	GETUPVAL 	0 0	; h
	2	[114]	SELF     	0 0 -1	; "close"
	3	[114]	CALL     	0 2 1
	4	[114]	RETURN   	0 1

function <./socket/http.lua:122,125> (16 instructions, 64 bytes at 0x7fe939409720)
3 params, 8 slots, 1 upvalue, 4 locals, 6 constants, 0 functions
	1	[123]	GETUPVAL 	3 0	; string
	2	[123]	GETTABLE 	3 3 -1	; "format"
	3	[123]	LOADK    	4 -2	; "%s %s HTTP/1.1\r\n"
	4	[123]	TESTSET  	5 1 1
	5	[123]	JMP      	1	; to 7
	6	[123]	LOADK    	5 -3	; "GET"
	7	[123]	MOVE     	6 2
	8	[123]	CALL     	3 4 2
	9	[124]	GETTABLE 	4 0 -4	; "try"
	10	[124]	GETTABLE 	5 0 -5	; "c"
	11	[124]	SELF     	5 5 -6	; "send"
	12	[124]	MOVE     	7 3
	13	[124]	CALL     	5 3 0
	14	[124]	TAILCALL 	4 0 0
	15	[124]	RETURN   	4 0
	16	[125]	RETURN   	0 1

function <./socket/http.lua:127,135> (28 instructions, 112 bytes at 0x7fe939409a00)
2 params, 14 slots, 2 upvalues, 9 locals, 8 constants, 0 functions
	1	[128]	GETUPVAL 	2 0	; headers
	2	[128]	GETTABLE 	2 2 -1	; "canonic"
	3	[129]	LOADK    	3 -2	; "\r\n"
	4	[130]	GETUPVAL 	4 1	; base
	5	[130]	GETTABLE 	4 4 -3	; "pairs"
	6	[130]	MOVE     	5 1
	7	[130]	CALL     	4 2 4
	8	[130]	JMP      	9	; to 18
	9	[131]	GETTABLE 	9 2 7
	10	[131]	TEST     	9 0 1
	11	[131]	JMP      	1	; to 13
	12	[131]	MOVE     	9 7
	13	[131]	LOADK    	10 -4	; ": "
	14	[131]	MOVE     	11 8
	15	[131]	LOADK    	12 -2	; "\r\n"
	16	[131]	MOVE     	13 3
	17	[131]	CONCAT   	3 9 13
	18	[130]	TFORLOOP 	4 2
	19	[131]	JMP      	-11	; to 9
	20	[133]	GETTABLE 	4 0 -5	; "try"
	21	[133]	GETTABLE 	5 0 -6	; "c"
	22	[133]	SELF     	5 5 -7	; "send"
	23	[133]	MOVE     	7 3
	24	[133]	CALL     	5 3 0
	25	[133]	CALL     	4 0 1
	26	[134]	LOADK    	4 -8	; 1
	27	[134]	RETURN   	4 2
	28	[135]	RETURN   	0 1

function <./socket/http.lua:137,144> (32 instructions, 128 bytes at 0x7fe93940a0f0)
4 params, 11 slots, 2 upvalues, 5 locals, 11 constants, 0 functions
	1	[138]	TEST     	2 0 1
	2	[138]	JMP      	5	; to 8
	3	[138]	GETUPVAL 	4 0	; ltn12
	4	[138]	GETTABLE 	4 4 -1	; "source"
	5	[138]	GETTABLE 	4 4 -2	; "empty"
	6	[138]	CALL     	4 1 2
	7	[138]	MOVE     	2 4
	8	[139]	TEST     	3 0 1
	9	[139]	JMP      	3	; to 13
	10	[139]	GETUPVAL 	4 0	; ltn12
	11	[139]	GETTABLE 	4 4 -3	; "pump"
	12	[139]	GETTABLE 	3 4 -4	; "step"
	13	[141]	LOADK    	4 -5	; "http-chunked"
	14	[142]	GETTABLE 	5 1 -6	; "content-length"
	15	[142]	TEST     	5 0 0
	16	[142]	JMP      	1	; to 18
	17	[142]	LOADK    	4 -7	; "keep-open"
	18	[143]	GETTABLE 	5 0 -8	; "try"
	19	[143]	GETUPVAL 	6 0	; ltn12
	20	[143]	GETTABLE 	6 6 -3	; "pump"
	21	[143]	GETTABLE 	6 6 -9	; "all"
	22	[143]	MOVE     	7 2
	23	[143]	GETUPVAL 	8 1	; socket
	24	[143]	GETTABLE 	8 8 -10	; "sink"
	25	[143]	MOVE     	9 4
	26	[143]	GETTABLE 	10 0 -11	; "c"
	27	[143]	CALL     	8 3 2
	28	[143]	MOVE     	9 3
	29	[143]	CALL     	6 4 0
	30	[143]	TAILCALL 	5 0 0
	31	[143]	RETURN   	5 0
	32	[144]	RETURN   	0 1

function <./socket/http.lua:146,155> (37 instructions, 148 bytes at 0x7fe93940a450)
1 param, 7 slots, 3 upvalues, 3 locals, 11 constants, 0 functions
	1	[147]	GETTABLE 	1 0 -1	; "try"
	2	[147]	GETTABLE 	2 0 -2	; "c"
	3	[147]	SELF     	2 2 -3	; "receive"
	4	[147]	LOADK    	4 -4	; 5
	5	[147]	CALL     	2 3 0
	6	[147]	CALL     	1 0 2
	7	[150]	EQ       	1 1 -5	; - "HTTP/"
	8	[150]	JMP      	3	; to 12
	9	[150]	LOADNIL  	2 2
	10	[150]	MOVE     	3 1
	11	[150]	RETURN   	2 3
	12	[152]	GETTABLE 	2 0 -1	; "try"
	13	[152]	GETTABLE 	3 0 -2	; "c"
	14	[152]	SELF     	3 3 -3	; "receive"
	15	[152]	LOADK    	5 -6	; "*l"
	16	[152]	MOVE     	6 1
	17	[152]	CALL     	3 4 0
	18	[152]	CALL     	2 0 2
	19	[152]	MOVE     	1 2
	20	[153]	GETUPVAL 	2 0	; socket
	21	[153]	GETTABLE 	2 2 -7	; "skip"
	22	[153]	LOADK    	3 -8	; 2
	23	[153]	GETUPVAL 	4 1	; string
	24	[153]	GETTABLE 	4 4 -9	; "find"
	25	[153]	MOVE     	5 1
	26	[153]	LOADK    	6 -10	; "HTTP/%d*%.%d* (%d%d%d)"
	27	[153]	CALL     	4 3 0
	28	[153]	CALL     	2 0 2
	29	[154]	GETTABLE 	3 0 -1	; "try"
	30	[154]	GETUPVAL 	4 2	; base
	31	[154]	GETTABLE 	4 4 -11	; "tonumber"
	32	[154]	MOVE     	5 2
	33	[154]	CALL     	4 2 2
	34	[154]	MOVE     	5 1
	35	[154]	TAILCALL 	3 3 0
	36	[154]	RETURN   	3 0
	37	[155]	RETURN   	0 1

function <./socket/http.lua:157,159> (7 instructions, 28 bytes at 0x7fe93940a6b0)
1 param, 4 slots, 1 upvalue, 1 local, 2 constants, 0 functions
	1	[158]	GETTABLE 	1 0 -1	; "try"
	2	[158]	GETUPVAL 	2 0	; receiveheaders
	3	[158]	GETTABLE 	3 0 -2	; "c"
	4	[158]	CALL     	2 2 0
	5	[158]	TAILCALL 	1 0 0
	6	[158]	RETURN   	1 0
	7	[159]	RETURN   	0 1

function <./socket/http.lua:161,171> (47 instructions, 188 bytes at 0x7fe93940af50)
4 params, 13 slots, 3 upvalues, 7 locals, 15 constants, 0 functions
	1	[162]	TEST     	2 0 1
	2	[162]	JMP      	5	; to 8
	3	[162]	GETUPVAL 	4 0	; ltn12
	4	[162]	GETTABLE 	4 4 -1	; "sink"
	5	[162]	GETTABLE 	4 4 -2	; "null"
	6	[162]	CALL     	4 1 2
	7	[162]	MOVE     	2 4
	8	[163]	TEST     	3 0 1
	9	[163]	JMP      	3	; to 13
	10	[163]	GETUPVAL 	4 0	; ltn12
	11	[163]	GETTABLE 	4 4 -3	; "pump"
	12	[163]	GETTABLE 	3 4 -4	; "step"
	13	[164]	GETUPVAL 	4 1	; base
	14	[164]	GETTABLE 	4 4 -5	; "tonumber"
	15	[164]	GETTABLE 	5 1 -6	; "content-length"
	16	[164]	CALL     	4 2 2
	17	[165]	GETTABLE 	5 1 -7	; "transfer-encoding"
	18	[166]	LOADK    	6 -8	; "default"
	19	[167]	TEST     	5 0 0
	20	[167]	JMP      	4	; to 25
	21	[167]	EQ       	1 5 -9	; - "identity"
	22	[167]	JMP      	2	; to 25
	23	[167]	LOADK    	6 -10	; "http-chunked"
	24	[167]	JMP      	7	; to 32
	25	[168]	GETUPVAL 	7 1	; base
	26	[168]	GETTABLE 	7 7 -5	; "tonumber"
	27	[168]	GETTABLE 	8 1 -6	; "content-length"
	28	[168]	CALL     	7 2 2
	29	[168]	TEST     	7 0 0
	30	[168]	JMP      	1	; to 32
	31	[168]	LOADK    	6 -11	; "by-length"
	32	[169]	GETTABLE 	7 0 -12	; "try"
	33	[169]	GETUPVAL 	8 0	; ltn12
	34	[169]	GETTABLE 	8 8 -3	; "pump"
	35	[169]	GETTABLE 	8 8 -13	; "all"
	36	[169]	GETUPVAL 	9 2	; socket
	37	[169]	GETTABLE 	9 9 -14	; "source"
	38	[169]	MOVE     	10 6
	39	[169]	GETTABLE 	11 0 -15	; "c"
	40	[169]	MOVE     	12 4
	41	[169]	CALL     	9 4 2
	42	[170]	MOVE     	10 2
	43	[170]	MOVE     	11 3
	44	[169]	CALL     	8 4 0
	45	[169]	TAILCALL 	7 0 0
	46	[170]	RETURN   	7 0
	47	[171]	RETURN   	0 1

function <./socket/http.lua:173,177> (23 instructions, 92 bytes at 0x7fe93940b650)
4 params, 10 slots, 2 upvalues, 5 locals, 7 constants, 0 functions
	1	[174]	GETUPVAL 	4 0	; ltn12
	2	[174]	GETTABLE 	4 4 -1	; "source"
	3	[174]	GETTABLE 	4 4 -2	; "rewind"
	4	[174]	GETUPVAL 	5 1	; socket
	5	[174]	GETTABLE 	5 5 -1	; "source"
	6	[174]	LOADK    	6 -3	; "until-closed"
	7	[174]	GETTABLE 	7 0 -4	; "c"
	8	[174]	CALL     	5 3 0
	9	[174]	CALL     	4 0 2
	10	[175]	MOVE     	5 4
	11	[175]	MOVE     	6 1
	12	[175]	CALL     	5 2 1
	13	[176]	GETTABLE 	5 0 -5	; "try"
	14	[176]	GETUPVAL 	6 0	; ltn12
	15	[176]	GETTABLE 	6 6 -6	; "pump"
	16	[176]	GETTABLE 	6 6 -7	; "all"
	17	[176]	MOVE     	7 4
	18	[176]	MOVE     	8 2
	19	[176]	MOVE     	9 3
	20	[176]	CALL     	6 4 0
	21	[176]	TAILCALL 	5 0 0
	22	[176]	RETURN   	5 0
	23	[177]	RETURN   	0 1

function <./socket/http.lua:179,181> (5 instructions, 20 bytes at 0x7fe93940b990)
1 param, 3 slots, 0 upvalues, 1 local, 2 constants, 0 functions
	1	[180]	GETTABLE 	1 0 -1	; "c"
	2	[180]	SELF     	1 1 -2	; "close"
	3	[180]	TAILCALL 	1 2 0
	4	[180]	RETURN   	1 0
	5	[181]	RETURN   	0 1

function <./socket/http.lua:186,198> (27 instructions, 108 bytes at 0x7fe93940ba10)
1 param, 6 slots, 2 upvalues, 2 locals, 9 constants, 0 functions
	1	[187]	MOVE     	1 0
	2	[189]	GETTABLE 	2 0 -1	; "proxy"
	3	[189]	TEST     	2 0 1
	4	[189]	JMP      	17	; to 22
	5	[189]	GETGLOBAL	2 -2	; PROXY
	6	[189]	TEST     	2 0 1
	7	[189]	JMP      	14	; to 22
	8	[190]	NEWTABLE 	2 0 4
	9	[191]	GETUPVAL 	3 0	; socket
	10	[191]	GETTABLE 	3 3 -4	; "try"
	11	[191]	GETTABLE 	4 0 -3	; "path"
	12	[191]	LOADK    	5 -5	; "invalid path 'nil'"
	13	[191]	CALL     	3 3 2
	14	[191]	SETTABLE 	2 -3 3	; "path" -
	15	[192]	GETTABLE 	3 0 -6	; "params"
	16	[192]	SETTABLE 	2 -6 3	; "params" -
	17	[193]	GETTABLE 	3 0 -7	; "query"
	18	[193]	SETTABLE 	2 -7 3	; "query" -
	19	[194]	GETTABLE 	3 0 -8	; "fragment"
	20	[194]	SETTABLE 	2 -8 3	; "fragment" -
	21	[195]	MOVE     	1 2
	22	[197]	GETUPVAL 	2 1	; url
	23	[197]	GETTABLE 	2 2 -9	; "build"
	24	[197]	MOVE     	3 1
	25	[197]	TAILCALL 	2 2 0
	26	[197]	RETURN   	2 0
	27	[198]	RETURN   	0 1

function <./socket/http.lua:200,208> (22 instructions, 88 bytes at 0x7fe93940be60)
1 param, 4 slots, 1 upvalue, 2 locals, 6 constants, 0 functions
	1	[201]	GETTABLE 	1 0 -1	; "proxy"
	2	[201]	TEST     	1 0 1
	3	[201]	JMP      	1	; to 5
	4	[201]	GETGLOBAL	1 -2	; PROXY
	5	[202]	TEST     	1 0 0
	6	[202]	JMP      	12	; to 19
	7	[203]	GETUPVAL 	2 0	; url
	8	[203]	GETTABLE 	2 2 -3	; "parse"
	9	[203]	MOVE     	3 1
	10	[203]	CALL     	2 2 2
	11	[203]	MOVE     	1 2
	12	[204]	GETTABLE 	2 1 -4	; "host"
	13	[204]	GETTABLE 	3 1 -5	; "port"
	14	[204]	TEST     	3 0 1
	15	[204]	JMP      	1	; to 17
	16	[204]	LOADK    	3 -6	; 3128
	17	[204]	RETURN   	2 3
	18	[204]	JMP      	3	; to 22
	19	[206]	GETTABLE 	2 0 -4	; "host"
	20	[206]	GETTABLE 	3 0 -5	; "port"
	21	[206]	RETURN   	2 3
	22	[208]	RETURN   	0 1

function <./socket/http.lua:210,228> (41 instructions, 164 bytes at 0x7fe93940c670)
1 param, 9 slots, 4 upvalues, 7 locals, 16 constants, 0 functions
	1	[212]	NEWTABLE 	1 0 4
	2	[213]	GETUPVAL 	2 0	; _M
	3	[213]	GETTABLE 	2 2 -2	; "USERAGENT"
	4	[213]	SETTABLE 	1 -1 2	; "user-agent" -
	5	[214]	GETTABLE 	2 0 -3	; "host"
	6	[214]	SETTABLE 	1 -3 2	; "host" -
	7	[215]	SETTABLE 	1 -4 -5	; "connection" "close, TE"
	8	[216]	SETTABLE 	1 -6 -7	; "te" "trailers"
	9	[219]	GETTABLE 	2 0 -8	; "user"
	10	[219]	TEST     	2 0 0
	11	[219]	JMP      	13	; to 25
	12	[219]	GETTABLE 	2 0 -9	; "password"
	13	[219]	TEST     	2 0 0
	14	[219]	JMP      	10	; to 25
	15	[221]	LOADK    	2 -11	; "Basic "
	16	[221]	GETUPVAL 	3 1	; mime
	17	[221]	GETTABLE 	3 3 -12	; "b64"
	18	[221]	GETTABLE 	4 0 -8	; "user"
	19	[221]	LOADK    	5 -13	; ":"
	20	[221]	GETTABLE 	6 0 -9	; "password"
	21	[221]	CONCAT   	4 4 6
	22	[221]	CALL     	3 2 2
	23	[221]	CONCAT   	2 2 3
	24	[221]	SETTABLE 	1 -10 2	; "authorization" -
	25	[224]	GETUPVAL 	2 2	; base
	26	[224]	GETTABLE 	2 2 -14	; "pairs"
	27	[224]	GETTABLE 	3 0 -15	; "headers"
	28	[224]	TEST     	3 0 1
	29	[224]	JMP      	1	; to 31
	30	[224]	MOVE     	3 1
	31	[224]	CALL     	2 2 4
	32	[224]	JMP      	5	; to 38
	33	[225]	GETUPVAL 	7 3	; string
	34	[225]	GETTABLE 	7 7 -16	; "lower"
	35	[225]	MOVE     	8 5
	36	[225]	CALL     	7 2 2
	37	[225]	SETTABLE 	1 7 6
	38	[224]	TFORLOOP 	2 2
	39	[225]	JMP      	-7	; to 33
	40	[227]	RETURN   	1 2
	41	[228]	RETURN   	0 1

function <./socket/http.lua:238,253> (59 instructions, 236 bytes at 0x7fe93940c760)
1 param, 8 slots, 7 upvalues, 7 locals, 13 constants, 0 functions
	1	[240]	GETTABLE 	1 0 -1	; "url"
	2	[240]	TEST     	1 0 0
	3	[240]	JMP      	7	; to 11
	4	[240]	GETUPVAL 	1 0	; url
	5	[240]	GETTABLE 	1 1 -2	; "parse"
	6	[240]	GETTABLE 	2 0 -1	; "url"
	7	[240]	GETUPVAL 	3 1	; default
	8	[240]	CALL     	1 3 2
	9	[240]	TEST     	1 0 1
	10	[240]	JMP      	1	; to 12
	11	[240]	NEWTABLE 	1 0 0
	12	[242]	GETUPVAL 	2 2	; base
	13	[242]	GETTABLE 	2 2 -3	; "pairs"
	14	[242]	MOVE     	3 0
	15	[242]	CALL     	2 2 4
	16	[242]	JMP      	1	; to 18
	17	[242]	SETTABLE 	1 5 6
	18	[242]	TFORLOOP 	2 2
	19	[242]	JMP      	-3	; to 17
	20	[243]	GETTABLE 	2 1 -4	; "port"
	21	[243]	EQ       	0 2 -5	; - ""
	22	[243]	JMP      	1	; to 24
	23	[243]	SETTABLE 	1 -4 -6	; "port" 80
	24	[244]	GETUPVAL 	2 3	; socket
	25	[244]	GETTABLE 	2 2 -7	; "try"
	26	[244]	GETTABLE 	3 1 -8	; "host"
	27	[244]	TEST     	3 0 0
	28	[244]	JMP      	5	; to 34
	29	[244]	GETTABLE 	3 1 -8	; "host"
	30	[244]	EQ       	0 3 -5	; - ""
	31	[244]	JMP      	1	; to 33
	32	[244]	LOADBOOL 	3 0 1
	33	[244]	LOADBOOL 	3 1 0
	34	[245]	LOADK    	4 -9	; "invalid host '"
	35	[245]	GETUPVAL 	5 2	; base
	36	[245]	GETTABLE 	5 5 -10	; "tostring"
	37	[245]	GETTABLE 	6 1 -8	; "host"
	38	[245]	CALL     	5 2 2
	39	[245]	LOADK    	6 -11	; "'"
	40	[245]	CONCAT   	4 4 6
	41	[244]	CALL     	2 3 1
	42	[247]	GETTABLE 	2 0 -12	; "uri"
	43	[247]	TEST     	2 0 1
	44	[247]	JMP      	3	; to 48
	45	[247]	GETUPVAL 	2 4	; adjusturi
	46	[247]	MOVE     	3 1
	47	[247]	CALL     	2 2 2
	48	[247]	SETTABLE 	1 -12 2	; "uri" -
	49	[249]	GETUPVAL 	2 5	; adjustproxy
	50	[249]	MOVE     	3 1
	51	[249]	CALL     	2 2 3
	52	[249]	SETTABLE 	1 -4 3	; "port" -
	53	[249]	SETTABLE 	1 -8 2	; "host" -
	54	[251]	GETUPVAL 	2 6	; adjustheaders
	55	[251]	MOVE     	3 1
	56	[251]	CALL     	2 2 2
	57	[251]	SETTABLE 	1 -13 2	; "headers" -
	58	[252]	RETURN   	1 2
	59	[253]	RETURN   	0 1

function <./socket/http.lua:255,262> (41 instructions, 164 bytes at 0x7fe939409140)
3 params, 7 slots, 1 upvalue, 3 locals, 15 constants, 0 functions
	1	[256]	GETTABLE 	3 2 -1	; "location"
	2	[256]	TEST     	3 0 0
	3	[256]	JMP      	36	; to 40
	4	[257]	GETUPVAL 	3 0	; string
	5	[257]	GETTABLE 	3 3 -2	; "gsub"
	6	[257]	GETTABLE 	4 2 -1	; "location"
	7	[257]	LOADK    	5 -3	; "%s"
	8	[257]	LOADK    	6 -4	; ""
	9	[257]	CALL     	3 4 2
	10	[257]	EQ       	1 3 -4	; - ""
	11	[257]	JMP      	26	; to 38
	12	[258]	GETTABLE 	3 0 -5	; "redirect"
	13	[258]	EQ       	1 3 -6	; - false
	14	[258]	JMP      	23	; to 38
	15	[259]	EQ       	1 1 -7	; - 301
	16	[259]	JMP      	6	; to 23
	17	[259]	EQ       	1 1 -8	; - 302
	18	[259]	JMP      	4	; to 23
	19	[259]	EQ       	1 1 -9	; - 303
	20	[259]	JMP      	2	; to 23
	21	[259]	EQ       	0 1 -10	; - 307
	22	[259]	JMP      	15	; to 38
	23	[260]	GETTABLE 	3 0 -11	; "method"
	24	[260]	TEST     	3 0 0
	25	[260]	JMP      	6	; to 32
	26	[260]	GETTABLE 	3 0 -11	; "method"
	27	[260]	EQ       	1 3 -12	; - "GET"
	28	[260]	JMP      	3	; to 32
	29	[260]	GETTABLE 	3 0 -11	; "method"
	30	[260]	EQ       	0 3 -13	; - "HEAD"
	31	[260]	JMP      	6	; to 38
	32	[261]	GETTABLE 	3 0 -14	; "nredirects"
	33	[261]	TEST     	3 0 0
	34	[261]	JMP      	4	; to 39
	35	[261]	GETTABLE 	3 0 -14	; "nredirects"
	36	[261]	LT       	1 3 -15	; - 5
	37	[261]	JMP      	1	; to 39
	38	[261]	LOADBOOL 	3 0 1
	39	[261]	LOADBOOL 	3 1 0
	40	[261]	RETURN   	3 2
	41	[262]	RETURN   	0 1

function <./socket/http.lua:264,269> (20 instructions, 80 bytes at 0x7fe93940aed0)
2 params, 3 slots, 0 upvalues, 2 locals, 7 constants, 0 functions
	1	[265]	GETTABLE 	2 0 -1	; "method"
	2	[265]	EQ       	0 2 -2	; - "HEAD"
	3	[265]	JMP      	2	; to 6
	4	[265]	LOADNIL  	2 2
	5	[265]	RETURN   	2 2
	6	[266]	EQ       	1 1 -3	; - 204
	7	[266]	JMP      	2	; to 10
	8	[266]	EQ       	0 1 -4	; - 304
	9	[266]	JMP      	2	; to 12
	10	[266]	LOADNIL  	2 2
	11	[266]	RETURN   	2 2
	12	[267]	LE       	0 -5 1	; 100 -
	13	[267]	JMP      	4	; to 18
	14	[267]	LT       	0 1 -6	; - 200
	15	[267]	JMP      	2	; to 18
	16	[267]	LOADNIL  	2 2
	17	[267]	RETURN   	2 2
	18	[268]	LOADK    	2 -7	; 1
	19	[268]	RETURN   	2 2
	20	[269]	RETURN   	0 1

function <./socket/http.lua:274,290> (40 instructions, 160 bytes at 0x7fe9394071d0)
2 params, 10 slots, 2 upvalues, 6 locals, 11 constants, 0 functions
	1	[275]	GETUPVAL 	2 0	; trequest
	2	[275]	NEWTABLE 	3 0 7
	3	[278]	GETUPVAL 	4 1	; url
	4	[278]	GETTABLE 	4 4 -2	; "absolute"
	5	[278]	GETTABLE 	5 0 -1	; "url"
	6	[278]	MOVE     	6 1
	7	[278]	CALL     	4 3 2
	8	[278]	SETTABLE 	3 -1 4	; "url" -
	9	[279]	GETTABLE 	4 0 -3	; "source"
	10	[279]	SETTABLE 	3 -3 4	; "source" -
	11	[280]	GETTABLE 	4 0 -4	; "sink"
	12	[280]	SETTABLE 	3 -4 4	; "sink" -
	13	[281]	GETTABLE 	4 0 -5	; "headers"
	14	[281]	SETTABLE 	3 -5 4	; "headers" -
	15	[282]	GETTABLE 	4 0 -6	; "proxy"
	16	[282]	SETTABLE 	3 -6 4	; "proxy" -
	17	[283]	GETTABLE 	4 0 -7	; "nredirects"
	18	[283]	TEST     	4 0 1
	19	[283]	JMP      	1	; to 21
	20	[283]	LOADK    	4 -8	; 0
	21	[283]	ADD      	4 4 -9	; - 1
	22	[283]	SETTABLE 	3 -7 4	; "nredirects" -
	23	[284]	GETTABLE 	4 0 -10	; "create"
	24	[284]	SETTABLE 	3 -10 4	; "create" -
	25	[275]	CALL     	2 2 5
	26	[287]	TEST     	4 0 1
	27	[287]	JMP      	2	; to 30
	28	[287]	NEWTABLE 	6 0 0
	29	[287]	MOVE     	4 6
	30	[288]	GETTABLE 	6 4 -11	; "location"
	31	[288]	TEST     	6 0 1
	32	[288]	JMP      	1	; to 34
	33	[288]	MOVE     	6 1
	34	[288]	SETTABLE 	4 -11 6	; "location" -
	35	[289]	MOVE     	6 2
	36	[289]	MOVE     	7 3
	37	[289]	MOVE     	8 4
	38	[289]	MOVE     	9 5
	39	[289]	RETURN   	6 5
	40	[290]	RETURN   	0 1

function <./socket/http.lua:292,329> (86 instructions, 344 bytes at 0x7fe93940cdf0)
1 param, 11 slots, 5 upvalues, 6 locals, 22 constants, 0 functions
	1	[295]	GETUPVAL 	1 0	; adjustrequest
	2	[295]	MOVE     	2 0
	3	[295]	CALL     	1 2 2
	4	[296]	GETUPVAL 	2 1	; _M
	5	[296]	GETTABLE 	2 2 -1	; "open"
	6	[296]	GETTABLE 	3 1 -2	; "host"
	7	[296]	GETTABLE 	4 1 -3	; "port"
	8	[296]	GETTABLE 	5 1 -4	; "create"
	9	[296]	CALL     	2 4 2
	10	[298]	SELF     	3 2 -5	; "sendrequestline"
	11	[298]	GETTABLE 	5 1 -6	; "method"
	12	[298]	GETTABLE 	6 1 -7	; "uri"
	13	[298]	CALL     	3 4 1
	14	[299]	SELF     	3 2 -8	; "sendheaders"
	15	[299]	GETTABLE 	5 1 -9	; "headers"
	16	[299]	CALL     	3 3 1
	17	[301]	GETTABLE 	3 1 -10	; "source"
	18	[301]	TEST     	3 0 0
	19	[301]	JMP      	5	; to 25
	20	[302]	SELF     	3 2 -11	; "sendbody"
	21	[302]	GETTABLE 	5 1 -9	; "headers"
	22	[302]	GETTABLE 	6 1 -10	; "source"
	23	[302]	GETTABLE 	7 1 -12	; "step"
	24	[302]	CALL     	3 5 1
	25	[304]	SELF     	3 2 -13	; "receivestatusline"
	26	[304]	CALL     	3 2 3
	27	[306]	TEST     	3 0 1
	28	[306]	JMP      	8	; to 37
	29	[307]	SELF     	5 2 -14	; "receive09body"
	30	[307]	MOVE     	7 4
	31	[307]	GETTABLE 	8 1 -15	; "sink"
	32	[307]	GETTABLE 	9 1 -12	; "step"
	33	[307]	CALL     	5 5 1
	34	[308]	LOADK    	5 -16	; 1
	35	[308]	LOADK    	6 -17	; 200
	36	[308]	RETURN   	5 3
	37	[310]	LOADNIL  	5 5
	38	[312]	EQ       	0 3 -18	; - 100
	39	[312]	JMP      	8	; to 48
	40	[313]	SELF     	6 2 -19	; "receiveheaders"
	41	[313]	CALL     	6 2 2
	42	[313]	MOVE     	5 6
	43	[314]	SELF     	6 2 -13	; "receivestatusline"
	44	[314]	CALL     	6 2 3
	45	[314]	MOVE     	4 7
	46	[314]	MOVE     	3 6
	47	[314]	JMP      	-10	; to 38
	48	[316]	SELF     	6 2 -19	; "receiveheaders"
	49	[316]	CALL     	6 2 2
	50	[316]	MOVE     	5 6
	51	[319]	GETUPVAL 	6 2	; shouldredirect
	52	[319]	MOVE     	7 1
	53	[319]	MOVE     	8 3
	54	[319]	MOVE     	9 5
	55	[319]	CALL     	6 4 2
	56	[319]	TEST     	6 0 0
	57	[319]	JMP      	10	; to 68
	58	[319]	GETTABLE 	6 1 -10	; "source"
	59	[319]	TEST     	6 0 1
	60	[319]	JMP      	7	; to 68
	61	[320]	SELF     	6 2 -20	; "close"
	62	[320]	CALL     	6 2 1
	63	[321]	GETUPVAL 	6 3	; tredirect
	64	[321]	MOVE     	7 0
	65	[321]	GETTABLE 	8 5 -21	; "location"
	66	[321]	TAILCALL 	6 3 0
	67	[321]	RETURN   	6 0
	68	[324]	GETUPVAL 	6 4	; shouldreceivebody
	69	[324]	MOVE     	7 1
	70	[324]	MOVE     	8 3
	71	[324]	CALL     	6 3 2
	72	[324]	TEST     	6 0 0
	73	[324]	JMP      	5	; to 79
	74	[325]	SELF     	6 2 -22	; "receivebody"
	75	[325]	MOVE     	8 5
	76	[325]	GETTABLE 	9 1 -15	; "sink"
	77	[325]	GETTABLE 	10 1 -12	; "step"
	78	[325]	CALL     	6 5 1
	79	[327]	SELF     	6 2 -20	; "close"
	80	[327]	CALL     	6 2 1
	81	[328]	LOADK    	6 -16	; 1
	82	[328]	MOVE     	7 3
	83	[328]	MOVE     	8 5
	84	[328]	MOVE     	9 4
	85	[328]	RETURN   	6 5
	86	[329]	RETURN   	0 1

function <./socket/http.lua:331,347> (42 instructions, 168 bytes at 0x7fe93940d5e0)
2 params, 11 slots, 5 upvalues, 7 locals, 15 constants, 0 functions
	1	[332]	NEWTABLE 	2 0 0
	2	[333]	NEWTABLE 	3 0 2
	3	[334]	SETTABLE 	3 -1 0	; "url" -
	4	[335]	GETUPVAL 	4 0	; ltn12
	5	[335]	GETTABLE 	4 4 -2	; "sink"
	6	[335]	GETTABLE 	4 4 -3	; "table"
	7	[335]	MOVE     	5 2
	8	[335]	CALL     	4 2 2
	9	[335]	SETTABLE 	3 -2 4	; "sink" -
	10	[337]	TEST     	1 0 0
	11	[337]	JMP      	15	; to 27
	12	[338]	GETUPVAL 	4 0	; ltn12
	13	[338]	GETTABLE 	4 4 -4	; "source"
	14	[338]	GETTABLE 	4 4 -5	; "string"
	15	[338]	MOVE     	5 1
	16	[338]	CALL     	4 2 2
	17	[338]	SETTABLE 	3 -4 4	; "source" -
	18	[339]	NEWTABLE 	4 0 2
	19	[340]	GETUPVAL 	5 1	; string
	20	[340]	GETTABLE 	5 5 -8	; "len"
	21	[340]	MOVE     	6 1
	22	[340]	CALL     	5 2 2
	23	[340]	SETTABLE 	4 -7 5	; "content-length" -
	24	[341]	SETTABLE 	4 -9 -10	; "content-type" "application/x-www-form-urlencoded"
	25	[342]	SETTABLE 	3 -6 4	; "headers" -
	26	[343]	SETTABLE 	3 -11 -12	; "method" "POST"
	27	[345]	GETUPVAL 	4 2	; socket
	28	[345]	GETTABLE 	4 4 -13	; "skip"
	29	[345]	LOADK    	5 -14	; 1
	30	[345]	GETUPVAL 	6 3	; trequest
	31	[345]	MOVE     	7 3
	32	[345]	CALL     	6 2 0
	33	[345]	CALL     	4 0 4
	34	[346]	GETUPVAL 	7 4	; table
	35	[346]	GETTABLE 	7 7 -15	; "concat"
	36	[346]	MOVE     	8 2
	37	[346]	CALL     	7 2 2
	38	[346]	MOVE     	8 4
	39	[346]	MOVE     	9 5
	40	[346]	MOVE     	10 6
	41	[346]	RETURN   	7 5
	42	[347]	RETURN   	0 1

function <./socket/http.lua:349,352> (17 instructions, 68 bytes at 0x7fe93940dcc0)
2 params, 5 slots, 3 upvalues, 2 locals, 2 constants, 0 functions
	1	[350]	GETUPVAL 	2 0	; base
	2	[350]	GETTABLE 	2 2 -1	; "type"
	3	[350]	MOVE     	3 0
	4	[350]	CALL     	2 2 2
	5	[350]	EQ       	0 2 -2	; - "string"
	6	[350]	JMP      	6	; to 13
	7	[350]	GETUPVAL 	2 1	; srequest
	8	[350]	MOVE     	3 0
	9	[350]	MOVE     	4 1
	10	[350]	TAILCALL 	2 3 0
	11	[350]	RETURN   	2 0
	12	[350]	JMP      	4	; to 17
	13	[351]	GETUPVAL 	2 2	; trequest
	14	[351]	MOVE     	3 0
	15	[351]	TAILCALL 	2 2 0
	16	[351]	RETURN   	2 0
	17	[352]	RETURN   	0 1
-----------------------

main <./socket/url.lua:0,0> (71 instructions, 284 bytes at 0x7faad44068a0)
0+ params, 24 slots, 0 upvalues, 9 locals, 31 constants, 10 functions
	1	[10]	GETGLOBAL	0 -1	; require
	2	[10]	LOADK    	1 -2	; "string"
	3	[10]	CALL     	0 2 2
	4	[11]	GETGLOBAL	1 -3	; _G
	5	[12]	GETGLOBAL	2 -1	; require
	6	[12]	LOADK    	3 -4	; "table"
	7	[12]	CALL     	2 2 2
	8	[13]	GETGLOBAL	3 -1	; require
	9	[13]	LOADK    	4 -5	; "socket"
	10	[13]	CALL     	3 2 2
	11	[15]	NEWTABLE 	4 0 0
	12	[15]	SETTABLE 	3 -6 4	; "url" -
	13	[16]	GETTABLE 	4 3 -6	; "url"
	14	[21]	SETTABLE 	4 -7 -8	; "_VERSION" "URL 1.0.3"
	15	[34]	CLOSURE  	5 0	; 0x7faad4406a80
	16	[34]	MOVE     	0 0
	17	[30]	SETTABLE 	4 -9 5	; "escape" -
	18	[50]	CLOSURE  	5 1	; 0x7faad4407820
	19	[50]	MOVE     	0 1
	20	[54]	MOVE     	6 5
	21	[54]	NEWTABLE 	7 16 0
	22	[55]	LOADK    	8 -10	; "-"
	23	[55]	LOADK    	9 -11	; "_"
	24	[55]	LOADK    	10 -12	; "."
	25	[55]	LOADK    	11 -13	; "!"
	26	[55]	LOADK    	12 -14	; "~"
	27	[55]	LOADK    	13 -15	; "*"
	28	[55]	LOADK    	14 -16	; "'"
	29	[55]	LOADK    	15 -17	; "("
	30	[56]	LOADK    	16 -18	; ")"
	31	[56]	LOADK    	17 -19	; ":"
	32	[56]	LOADK    	18 -20	; "@"
	33	[56]	LOADK    	19 -21	; "&"
	34	[56]	LOADK    	20 -22	; "="
	35	[56]	LOADK    	21 -23	; "+"
	36	[56]	LOADK    	22 -24	; "$"
	37	[57]	LOADK    	23 -25	; ","
	38	[57]	SETLIST  	7 16 1	; 1
	39	[54]	CALL     	6 2 2
	40	[64]	CLOSURE  	7 2	; 0x7faad44077a0
	41	[64]	MOVE     	0 0
	42	[64]	MOVE     	0 6
	43	[77]	CLOSURE  	8 3	; 0x7faad44081d0
	44	[77]	MOVE     	0 0
	45	[77]	MOVE     	0 1
	46	[73]	SETTABLE 	4 -26 8	; "unescape" -
	47	[106]	CLOSURE  	8 4	; 0x7faad4406b80
	48	[106]	MOVE     	0 0
	49	[175]	CLOSURE  	9 5	; 0x7faad4407f20
	50	[175]	MOVE     	0 1
	51	[175]	MOVE     	0 0
	52	[126]	SETTABLE 	4 -27 9	; "parse" -
	53	[211]	CLOSURE  	9 6	; 0x7faad440ad90
	54	[211]	MOVE     	0 4
	55	[211]	MOVE     	0 0
	56	[185]	SETTABLE 	4 -28 9	; "build" -
	57	[251]	CLOSURE  	9 7	; 0x7faad440b250
	58	[251]	MOVE     	0 1
	59	[251]	MOVE     	0 4
	60	[251]	MOVE     	0 8
	61	[221]	SETTABLE 	4 -29 9	; "absolute" -
	62	[271]	CLOSURE  	9 8	; 0x7faad440bae0
	63	[271]	MOVE     	0 0
	64	[271]	MOVE     	0 2
	65	[271]	MOVE     	0 4
	66	[260]	SETTABLE 	4 -30 9	; "parse_path" -
	67	[305]	CLOSURE  	9 9	; 0x7faad440ca10
	68	[305]	MOVE     	0 7
	69	[281]	SETTABLE 	4 -31 9	; "build_path" -
	70	[307]	RETURN   	4 2
	71	[307]	RETURN   	0 1

function <./socket/url.lua:30,34> (9 instructions, 36 bytes at 0x7faad4406a80)
1 param, 5 slots, 1 upvalue, 1 local, 2 constants, 1 function
	1	[31]	GETUPVAL 	1 0	; string
	2	[31]	GETTABLE 	1 1 -1	; "gsub"
	3	[31]	MOVE     	2 0
	4	[31]	LOADK    	3 -2	; "([^A-Za-z0-9_])"
	5	[33]	CLOSURE  	4 0	; 0x7faad4407380
	6	[33]	GETUPVAL 	0 0	; string
	7	[31]	CALL     	1 4 2
	8	[33]	RETURN   	1 2
	9	[34]	RETURN   	0 1

function <./socket/url.lua:31,33> (10 instructions, 40 bytes at 0x7faad4407380)
1 param, 5 slots, 1 upvalue, 1 local, 3 constants, 0 functions
	1	[32]	GETUPVAL 	1 0	; string
	2	[32]	GETTABLE 	1 1 -1	; "format"
	3	[32]	LOADK    	2 -2	; "%%%02x"
	4	[32]	GETUPVAL 	3 0	; string
	5	[32]	GETTABLE 	3 3 -3	; "byte"
	6	[32]	MOVE     	4 0
	7	[32]	CALL     	3 2 0
	8	[32]	TAILCALL 	1 0 0
	9	[32]	RETURN   	1 0
	10	[33]	RETURN   	0 1

function <./socket/url.lua:44,50> (12 instructions, 48 bytes at 0x7faad4407820)
1 param, 8 slots, 1 upvalue, 7 locals, 2 constants, 0 functions
	1	[45]	NEWTABLE 	1 0 0
	2	[46]	GETUPVAL 	2 0	; base
	3	[46]	GETTABLE 	2 2 -1	; "ipairs"
	4	[46]	MOVE     	3 0
	5	[46]	CALL     	2 2 4
	6	[46]	JMP      	2	; to 9
	7	[47]	GETTABLE 	7 0 5
	8	[47]	SETTABLE 	1 7 -2	; - 1
	9	[46]	TFORLOOP 	2 2
	10	[47]	JMP      	-4	; to 7
	11	[49]	RETURN   	1 2
	12	[50]	RETURN   	0 1

function <./socket/url.lua:59,64> (10 instructions, 40 bytes at 0x7faad44077a0)
1 param, 5 slots, 2 upvalues, 1 local, 2 constants, 1 function
	1	[60]	GETUPVAL 	1 0	; string
	2	[60]	GETTABLE 	1 1 -1	; "gsub"
	3	[60]	MOVE     	2 0
	4	[60]	LOADK    	3 -2	; "([^A-Za-z0-9_])"
	5	[63]	CLOSURE  	4 0	; 0x7faad4408030
	6	[63]	GETUPVAL 	0 1	; segment_set
	7	[63]	GETUPVAL 	0 0	; string
	8	[60]	TAILCALL 	1 4 0
	9	[63]	RETURN   	1 0
	10	[64]	RETURN   	0 1

function <./socket/url.lua:60,63> (16 instructions, 64 bytes at 0x7faad4408030)
1 param, 5 slots, 2 upvalues, 1 local, 3 constants, 0 functions
	1	[61]	GETUPVAL 	1 0	; segment_set
	2	[61]	GETTABLE 	1 1 0
	3	[61]	TEST     	1 0 0
	4	[61]	JMP      	2	; to 7
	5	[61]	RETURN   	0 2
	6	[61]	JMP      	9	; to 16
	7	[62]	GETUPVAL 	1 1	; string
	8	[62]	GETTABLE 	1 1 -1	; "format"
	9	[62]	LOADK    	2 -2	; "%%%02x"
	10	[62]	GETUPVAL 	3 1	; string
	11	[62]	GETTABLE 	3 3 -3	; "byte"
	12	[62]	MOVE     	4 0
	13	[62]	CALL     	3 2 0
	14	[62]	TAILCALL 	1 0 0
	15	[62]	RETURN   	1 0
	16	[63]	RETURN   	0 1

function <./socket/url.lua:73,77> (10 instructions, 40 bytes at 0x7faad44081d0)
1 param, 5 slots, 2 upvalues, 1 local, 2 constants, 1 function
	1	[74]	GETUPVAL 	1 0	; string
	2	[74]	GETTABLE 	1 1 -1	; "gsub"
	3	[74]	MOVE     	2 0
	4	[74]	LOADK    	3 -2	; "%%(%x%x)"
	5	[76]	CLOSURE  	4 0	; 0x7faad44087f0
	6	[76]	GETUPVAL 	0 0	; string
	7	[76]	GETUPVAL 	0 1	; base
	8	[74]	CALL     	1 4 2
	9	[76]	RETURN   	1 2
	10	[77]	RETURN   	0 1

function <./socket/url.lua:74,76> (10 instructions, 40 bytes at 0x7faad44087f0)
1 param, 5 slots, 2 upvalues, 1 local, 3 constants, 0 functions
	1	[75]	GETUPVAL 	1 0	; string
	2	[75]	GETTABLE 	1 1 -1	; "char"
	3	[75]	GETUPVAL 	2 1	; base
	4	[75]	GETTABLE 	2 2 -2	; "tonumber"
	5	[75]	MOVE     	3 0
	6	[75]	LOADK    	4 -3	; 16
	7	[75]	CALL     	2 3 0
	8	[75]	TAILCALL 	1 0 0
	9	[75]	RETURN   	1 0
	10	[76]	RETURN   	0 1

function <./socket/url.lua:87,106> (53 instructions, 212 bytes at 0x7faad4406b80)
2 params, 8 slots, 1 upvalue, 4 locals, 10 constants, 3 functions
	1	[88]	GETUPVAL 	2 0	; string
	2	[88]	GETTABLE 	2 2 -1	; "sub"
	3	[88]	MOVE     	3 1
	4	[88]	LOADK    	4 -2	; 1
	5	[88]	LOADK    	5 -2	; 1
	6	[88]	CALL     	2 4 2
	7	[88]	EQ       	0 2 -3	; - "/"
	8	[88]	JMP      	1	; to 10
	9	[88]	RETURN   	1 2
	10	[89]	GETUPVAL 	2 0	; string
	11	[89]	GETTABLE 	2 2 -4	; "gsub"
	12	[89]	MOVE     	3 0
	13	[89]	LOADK    	4 -5	; "[^/]*$"
	14	[89]	LOADK    	5 -6	; ""
	15	[89]	CALL     	2 4 2
	16	[90]	MOVE     	3 2
	17	[90]	MOVE     	4 1
	18	[90]	CONCAT   	2 3 4
	19	[91]	GETUPVAL 	3 0	; string
	20	[91]	GETTABLE 	3 3 -4	; "gsub"
	21	[91]	MOVE     	4 2
	22	[91]	LOADK    	5 -7	; "([^/]*%./)"
	23	[93]	CLOSURE  	6 0	; 0x7faad4408f40
	24	[91]	CALL     	3 4 2
	25	[93]	MOVE     	2 3
	26	[94]	GETUPVAL 	3 0	; string
	27	[94]	GETTABLE 	3 3 -4	; "gsub"
	28	[94]	MOVE     	4 2
	29	[94]	LOADK    	5 -8	; "/%.$"
	30	[94]	LOADK    	6 -3	; "/"
	31	[94]	CALL     	3 4 2
	32	[94]	MOVE     	2 3
	33	[95]	LOADNIL  	3 3
	34	[96]	EQ       	1 3 2
	35	[96]	JMP      	9	; to 45
	36	[97]	MOVE     	3 2
	37	[98]	GETUPVAL 	4 0	; string
	38	[98]	GETTABLE 	4 4 -4	; "gsub"
	39	[98]	MOVE     	5 3
	40	[98]	LOADK    	6 -9	; "([^/]*/%.%./)"
	41	[100]	CLOSURE  	7 1	; 0x7faad4408ec0
	42	[98]	CALL     	4 4 2
	43	[100]	MOVE     	2 4
	44	[100]	JMP      	-11	; to 34
	45	[102]	GETUPVAL 	4 0	; string
	46	[102]	GETTABLE 	4 4 -4	; "gsub"
	47	[102]	MOVE     	5 3
	48	[102]	LOADK    	6 -10	; "([^/]*/%.%.)$"
	49	[104]	CLOSURE  	7 2	; 0x7faad4409430
	50	[102]	CALL     	4 4 2
	51	[104]	MOVE     	2 4
	52	[105]	RETURN   	2 2
	53	[106]	RETURN   	0 1

function <./socket/url.lua:91,93> (7 instructions, 28 bytes at 0x7faad4408f40)
1 param, 2 slots, 0 upvalues, 1 local, 2 constants, 0 functions
	1	[92]	EQ       	1 0 -1	; - "./"
	2	[92]	JMP      	2	; to 5
	3	[92]	RETURN   	0 2
	4	[92]	JMP      	2	; to 7
	5	[92]	LOADK    	1 -2	; ""
	6	[92]	RETURN   	1 2
	7	[93]	RETURN   	0 1

function <./socket/url.lua:98,100> (7 instructions, 28 bytes at 0x7faad4408ec0)
1 param, 2 slots, 0 upvalues, 1 local, 2 constants, 0 functions
	1	[99]	EQ       	1 0 -1	; - "../../"
	2	[99]	JMP      	3	; to 6
	3	[99]	LOADK    	1 -2	; ""
	4	[99]	RETURN   	1 2
	5	[99]	JMP      	1	; to 7
	6	[99]	RETURN   	0 2
	7	[100]	RETURN   	0 1

function <./socket/url.lua:102,104> (7 instructions, 28 bytes at 0x7faad4409430)
1 param, 2 slots, 0 upvalues, 1 local, 2 constants, 0 functions
	1	[103]	EQ       	1 0 -1	; - "../.."
	2	[103]	JMP      	3	; to 6
	3	[103]	LOADK    	1 -2	; ""
	4	[103]	RETURN   	1 2
	5	[103]	JMP      	1	; to 7
	6	[103]	RETURN   	0 2
	7	[104]	RETURN   	0 1

function <./socket/url.lua:126,175> (107 instructions, 428 bytes at 0x7faad4407f20)
2 params, 9 slots, 2 upvalues, 10 locals, 19 constants, 8 functions
	1	[128]	NEWTABLE 	2 0 0
	2	[129]	GETUPVAL 	3 0	; base
	3	[129]	GETTABLE 	3 3 -1	; "pairs"
	4	[129]	TESTSET  	4 1 1
	5	[129]	JMP      	1	; to 7
	6	[129]	MOVE     	4 2
	7	[129]	CALL     	3 2 4
	8	[129]	JMP      	1	; to 10
	9	[129]	SETTABLE 	2 6 7
	10	[129]	TFORLOOP 	3 2
	11	[129]	JMP      	-3	; to 9
	12	[131]	TEST     	0 0 0
	13	[131]	JMP      	2	; to 16
	14	[131]	EQ       	0 0 -2	; - ""
	15	[131]	JMP      	3	; to 19
	16	[131]	LOADNIL  	3 3
	17	[131]	LOADK    	4 -3	; "invalid url"
	18	[131]	RETURN   	3 3
	19	[135]	GETUPVAL 	3 1	; string
	20	[135]	GETTABLE 	3 3 -4	; "gsub"
	21	[135]	MOVE     	4 0
	22	[135]	LOADK    	5 -5	; "#(.*)$"
	23	[138]	CLOSURE  	6 0	; 0x7faad4407a80
	24	[138]	MOVE     	0 2
	25	[135]	CALL     	3 4 2
	26	[138]	MOVE     	0 3
	27	[140]	GETUPVAL 	3 1	; string
	28	[140]	GETTABLE 	3 3 -4	; "gsub"
	29	[140]	MOVE     	4 0
	30	[140]	LOADK    	5 -6	; "^([%w][%w%+%-%.]*)%:"
	31	[141]	CLOSURE  	6 1	; 0x7faad4407b70
	32	[141]	MOVE     	0 2
	33	[140]	CALL     	3 4 2
	34	[141]	MOVE     	0 3
	35	[143]	GETUPVAL 	3 1	; string
	36	[143]	GETTABLE 	3 3 -4	; "gsub"
	37	[143]	MOVE     	4 0
	38	[143]	LOADK    	5 -7	; "^//([^/]*)"
	39	[146]	CLOSURE  	6 2	; 0x7faad4409170
	40	[146]	MOVE     	0 2
	41	[143]	CALL     	3 4 2
	42	[146]	MOVE     	0 3
	43	[148]	GETUPVAL 	3 1	; string
	44	[148]	GETTABLE 	3 3 -4	; "gsub"
	45	[148]	MOVE     	4 0
	46	[148]	LOADK    	5 -8	; "%?(.*)"
	47	[151]	CLOSURE  	6 3	; 0x7faad4409a30
	48	[151]	MOVE     	0 2
	49	[148]	CALL     	3 4 2
	50	[151]	MOVE     	0 3
	51	[153]	GETUPVAL 	3 1	; string
	52	[153]	GETTABLE 	3 3 -4	; "gsub"
	53	[153]	MOVE     	4 0
	54	[153]	LOADK    	5 -9	; "%;(.*)"
	55	[156]	CLOSURE  	6 4	; 0x7faad44091f0
	56	[156]	MOVE     	0 2
	57	[153]	CALL     	3 4 2
	58	[156]	MOVE     	0 3
	59	[158]	EQ       	1 0 -2	; - ""
	60	[158]	JMP      	1	; to 62
	61	[158]	SETTABLE 	2 -10 0	; "path" -
	62	[159]	GETTABLE 	3 2 -11	; "authority"
	63	[160]	TEST     	3 0 1
	64	[160]	JMP      	1	; to 66
	65	[160]	RETURN   	2 2
	66	[161]	GETUPVAL 	4 1	; string
	67	[161]	GETTABLE 	4 4 -4	; "gsub"
	68	[161]	MOVE     	5 3
	69	[161]	LOADK    	6 -12	; "^([^@]*)@"
	70	[162]	CLOSURE  	7 5	; 0x7faad4408460
	71	[162]	MOVE     	0 2
	72	[161]	CALL     	4 4 2
	73	[162]	MOVE     	3 4
	74	[163]	GETUPVAL 	4 1	; string
	75	[163]	GETTABLE 	4 4 -4	; "gsub"
	76	[163]	MOVE     	5 3
	77	[163]	LOADK    	6 -13	; ":([^:%]]*)$"
	78	[164]	CLOSURE  	7 6	; 0x7faad4409890
	79	[164]	MOVE     	0 2
	80	[163]	CALL     	4 4 2
	81	[164]	MOVE     	3 4
	82	[165]	EQ       	1 3 -2	; - ""
	83	[165]	JMP      	9	; to 93
	84	[167]	GETUPVAL 	4 1	; string
	85	[167]	GETTABLE 	4 4 -15	; "match"
	86	[167]	MOVE     	5 3
	87	[167]	LOADK    	6 -16	; "^%[(.+)%]$"
	88	[167]	CALL     	4 3 2
	89	[167]	TEST     	4 0 1
	90	[167]	JMP      	1	; to 92
	91	[167]	MOVE     	4 3
	92	[167]	SETTABLE 	2 -14 4	; "host" -
	93	[169]	GETTABLE 	4 2 -17	; "userinfo"
	94	[170]	TEST     	4 0 1
	95	[170]	JMP      	1	; to 97
	96	[170]	RETURN   	2 2
	97	[171]	GETUPVAL 	5 1	; string
	98	[171]	GETTABLE 	5 5 -4	; "gsub"
	99	[171]	MOVE     	6 4
	100	[171]	LOADK    	7 -18	; ":([^:]*)$"
	101	[172]	CLOSURE  	8 7	; 0x7faad4409f60
	102	[172]	MOVE     	0 2
	103	[171]	CALL     	5 4 2
	104	[172]	MOVE     	4 5
	105	[173]	SETTABLE 	2 -19 4	; "user" -
	106	[174]	RETURN   	2 2
	107	[175]	RETURN   	0 1

function <./socket/url.lua:135,138> (5 instructions, 20 bytes at 0x7faad4407a80)
1 param, 2 slots, 1 upvalue, 1 local, 2 constants, 0 functions
	1	[136]	GETUPVAL 	1 0	; parsed
	2	[136]	SETTABLE 	1 -1 0	; "fragment" -
	3	[137]	LOADK    	1 -2	; ""
	4	[137]	RETURN   	1 2
	5	[138]	RETURN   	0 1

function <./socket/url.lua:141,141> (5 instructions, 20 bytes at 0x7faad4407b70)
1 param, 2 slots, 1 upvalue, 1 local, 2 constants, 0 functions
	1	[141]	GETUPVAL 	1 0	; parsed
	2	[141]	SETTABLE 	1 -1 0	; "scheme" -
	3	[141]	LOADK    	1 -2	; ""
	4	[141]	RETURN   	1 2
	5	[141]	RETURN   	0 1

function <./socket/url.lua:143,146> (5 instructions, 20 bytes at 0x7faad4409170)
1 param, 2 slots, 1 upvalue, 1 local, 2 constants, 0 functions
	1	[144]	GETUPVAL 	1 0	; parsed
	2	[144]	SETTABLE 	1 -1 0	; "authority" -
	3	[145]	LOADK    	1 -2	; ""
	4	[145]	RETURN   	1 2
	5	[146]	RETURN   	0 1

function <./socket/url.lua:148,151> (5 instructions, 20 bytes at 0x7faad4409a30)
1 param, 2 slots, 1 upvalue, 1 local, 2 constants, 0 functions
	1	[149]	GETUPVAL 	1 0	; parsed
	2	[149]	SETTABLE 	1 -1 0	; "query" -
	3	[150]	LOADK    	1 -2	; ""
	4	[150]	RETURN   	1 2
	5	[151]	RETURN   	0 1

function <./socket/url.lua:153,156> (5 instructions, 20 bytes at 0x7faad44091f0)
1 param, 2 slots, 1 upvalue, 1 local, 2 constants, 0 functions
	1	[154]	GETUPVAL 	1 0	; parsed
	2	[154]	SETTABLE 	1 -1 0	; "params" -
	3	[155]	LOADK    	1 -2	; ""
	4	[155]	RETURN   	1 2
	5	[156]	RETURN   	0 1

function <./socket/url.lua:162,162> (5 instructions, 20 bytes at 0x7faad4408460)
1 param, 2 slots, 1 upvalue, 1 local, 2 constants, 0 functions
	1	[162]	GETUPVAL 	1 0	; parsed
	2	[162]	SETTABLE 	1 -1 0	; "userinfo" -
	3	[162]	LOADK    	1 -2	; ""
	4	[162]	RETURN   	1 2
	5	[162]	RETURN   	0 1

function <./socket/url.lua:164,164> (5 instructions, 20 bytes at 0x7faad4409890)
1 param, 2 slots, 1 upvalue, 1 local, 2 constants, 0 functions
	1	[164]	GETUPVAL 	1 0	; parsed
	2	[164]	SETTABLE 	1 -1 0	; "port" -
	3	[164]	LOADK    	1 -2	; ""
	4	[164]	RETURN   	1 2
	5	[164]	RETURN   	0 1

function <./socket/url.lua:172,172> (5 instructions, 20 bytes at 0x7faad4409f60)
1 param, 2 slots, 1 upvalue, 1 local, 2 constants, 0 functions
	1	[172]	GETUPVAL 	1 0	; parsed
	2	[172]	SETTABLE 	1 -1 0	; "password" -
	3	[172]	LOADK    	1 -2	; ""
	4	[172]	RETURN   	1 2
	5	[172]	RETURN   	0 1

function <./socket/url.lua:185,211> (88 instructions, 352 bytes at 0x7faad440ad90)
1 param, 8 slots, 2 upvalues, 5 locals, 23 constants, 0 functions
	1	[186]	GETUPVAL 	1 0	; _M
	2	[186]	GETTABLE 	1 1 -1	; "parse_path"
	3	[186]	GETTABLE 	2 0 -2	; "path"
	4	[186]	TEST     	2 0 1
	5	[186]	JMP      	1	; to 7
	6	[186]	LOADK    	2 -3	; ""
	7	[186]	CALL     	1 2 2
	8	[187]	GETUPVAL 	2 0	; _M
	9	[187]	GETTABLE 	2 2 -4	; "build_path"
	10	[187]	MOVE     	3 1
	11	[187]	CALL     	2 2 2
	12	[188]	GETTABLE 	3 0 -5	; "params"
	13	[188]	TEST     	3 0 0
	14	[188]	JMP      	4	; to 19
	15	[188]	MOVE     	3 2
	16	[188]	LOADK    	4 -6	; ";"
	17	[188]	GETTABLE 	5 0 -5	; "params"
	18	[188]	CONCAT   	2 3 5
	19	[189]	GETTABLE 	3 0 -7	; "query"
	20	[189]	TEST     	3 0 0
	21	[189]	JMP      	4	; to 26
	22	[189]	MOVE     	3 2
	23	[189]	LOADK    	4 -8	; "?"
	24	[189]	GETTABLE 	5 0 -7	; "query"
	25	[189]	CONCAT   	2 3 5
	26	[190]	GETTABLE 	3 0 -9	; "authority"
	27	[191]	GETTABLE 	4 0 -10	; "host"
	28	[191]	TEST     	4 0 0
	29	[191]	JMP      	37	; to 67
	30	[192]	GETTABLE 	3 0 -10	; "host"
	31	[193]	GETUPVAL 	4 1	; string
	32	[193]	GETTABLE 	4 4 -11	; "find"
	33	[193]	MOVE     	5 3
	34	[193]	LOADK    	6 -12	; ":"
	35	[193]	CALL     	4 3 2
	36	[193]	TEST     	4 0 0
	37	[193]	JMP      	4	; to 42
	38	[194]	LOADK    	4 -13	; "["
	39	[194]	MOVE     	5 3
	40	[194]	LOADK    	6 -14	; "]"
	41	[194]	CONCAT   	3 4 6
	42	[196]	GETTABLE 	4 0 -15	; "port"
	43	[196]	TEST     	4 0 0
	44	[196]	JMP      	4	; to 49
	45	[196]	MOVE     	4 3
	46	[196]	LOADK    	5 -12	; ":"
	47	[196]	GETTABLE 	6 0 -15	; "port"
	48	[196]	CONCAT   	3 4 6
	49	[197]	GETTABLE 	4 0 -16	; "userinfo"
	50	[198]	GETTABLE 	5 0 -17	; "user"
	51	[198]	TEST     	5 0 0
	52	[198]	JMP      	8	; to 61
	53	[199]	GETTABLE 	4 0 -17	; "user"
	54	[200]	GETTABLE 	5 0 -18	; "password"
	55	[200]	TEST     	5 0 0
	56	[200]	JMP      	4	; to 61
	57	[201]	MOVE     	5 4
	58	[201]	LOADK    	6 -12	; ":"
	59	[201]	GETTABLE 	7 0 -18	; "password"
	60	[201]	CONCAT   	4 5 7
	61	[204]	TEST     	4 0 0
	62	[204]	JMP      	4	; to 67
	63	[204]	MOVE     	5 4
	64	[204]	LOADK    	6 -19	; "@"
	65	[204]	MOVE     	7 3
	66	[204]	CONCAT   	3 5 7
	67	[206]	TEST     	3 0 0
	68	[206]	JMP      	4	; to 73
	69	[206]	LOADK    	4 -20	; "//"
	70	[206]	MOVE     	5 3
	71	[206]	MOVE     	6 2
	72	[206]	CONCAT   	2 4 6
	73	[207]	GETTABLE 	4 0 -21	; "scheme"
	74	[207]	TEST     	4 0 0
	75	[207]	JMP      	4	; to 80
	76	[207]	GETTABLE 	4 0 -21	; "scheme"
	77	[207]	LOADK    	5 -12	; ":"
	78	[207]	MOVE     	6 2
	79	[207]	CONCAT   	2 4 6
	80	[208]	GETTABLE 	4 0 -22	; "fragment"
	81	[208]	TEST     	4 0 0
	82	[208]	JMP      	4	; to 87
	83	[208]	MOVE     	4 2
	84	[208]	LOADK    	5 -23	; "#"
	85	[208]	GETTABLE 	6 0 -22	; "fragment"
	86	[208]	CONCAT   	2 4 6
	87	[210]	RETURN   	2 2
	88	[211]	RETURN   	0 1

function <./socket/url.lua:221,251> (79 instructions, 316 bytes at 0x7faad440b250)
2 params, 6 slots, 3 upvalues, 3 locals, 11 constants, 0 functions
	1	[222]	GETUPVAL 	2 0	; base
	2	[222]	GETTABLE 	2 2 -1	; "type"
	3	[222]	MOVE     	3 0
	4	[222]	CALL     	2 2 2
	5	[222]	EQ       	0 2 -2	; - "table"
	6	[222]	JMP      	7	; to 14
	7	[223]	SETGLOBAL	0 -3	; base_parsed
	8	[224]	GETUPVAL 	2 1	; _M
	9	[224]	GETTABLE 	2 2 -4	; "build"
	10	[224]	GETGLOBAL	3 -3	; base_parsed
	11	[224]	CALL     	2 2 2
	12	[224]	MOVE     	0 2
	13	[224]	JMP      	5	; to 19
	14	[226]	GETUPVAL 	2 1	; _M
	15	[226]	GETTABLE 	2 2 -5	; "parse"
	16	[226]	MOVE     	3 0
	17	[226]	CALL     	2 2 2
	18	[226]	SETGLOBAL	2 -3	; base_parsed
	19	[228]	GETUPVAL 	2 1	; _M
	20	[228]	GETTABLE 	2 2 -5	; "parse"
	21	[228]	MOVE     	3 1
	22	[228]	CALL     	2 2 2
	23	[229]	GETGLOBAL	3 -3	; base_parsed
	24	[229]	TEST     	3 0 1
	25	[229]	JMP      	2	; to 28
	26	[229]	RETURN   	1 2
	27	[229]	JMP      	51	; to 79
	28	[230]	TEST     	2 0 1
	29	[230]	JMP      	2	; to 32
	30	[230]	RETURN   	0 2
	31	[230]	JMP      	47	; to 79
	32	[231]	GETTABLE 	3 2 -6	; "scheme"
	33	[231]	TEST     	3 0 0
	34	[231]	JMP      	2	; to 37
	35	[231]	RETURN   	1 2
	36	[231]	JMP      	42	; to 79
	37	[233]	GETGLOBAL	3 -3	; base_parsed
	38	[233]	GETTABLE 	3 3 -6	; "scheme"
	39	[233]	SETTABLE 	2 -6 3	; "scheme" -
	40	[234]	GETTABLE 	3 2 -7	; "authority"
	41	[234]	TEST     	3 0 1
	42	[234]	JMP      	31	; to 74
	43	[235]	GETGLOBAL	3 -3	; base_parsed
	44	[235]	GETTABLE 	3 3 -7	; "authority"
	45	[235]	SETTABLE 	2 -7 3	; "authority" -
	46	[236]	GETTABLE 	3 2 -8	; "path"
	47	[236]	TEST     	3 0 1
	48	[236]	JMP      	16	; to 65
	49	[237]	GETGLOBAL	3 -3	; base_parsed
	50	[237]	GETTABLE 	3 3 -8	; "path"
	51	[237]	SETTABLE 	2 -8 3	; "path" -
	52	[238]	GETTABLE 	3 2 -9	; "params"
	53	[238]	TEST     	3 0 1
	54	[238]	JMP      	19	; to 74
	55	[239]	GETGLOBAL	3 -3	; base_parsed
	56	[239]	GETTABLE 	3 3 -9	; "params"
	57	[239]	SETTABLE 	2 -9 3	; "params" -
	58	[240]	GETTABLE 	3 2 -10	; "query"
	59	[240]	TEST     	3 0 1
	60	[240]	JMP      	13	; to 74
	61	[241]	GETGLOBAL	3 -3	; base_parsed
	62	[241]	GETTABLE 	3 3 -10	; "query"
	63	[241]	SETTABLE 	2 -10 3	; "query" -
	64	[243]	JMP      	9	; to 74
	65	[245]	GETUPVAL 	3 2	; absolute_path
	66	[245]	GETGLOBAL	4 -3	; base_parsed
	67	[245]	GETTABLE 	4 4 -8	; "path"
	68	[245]	TEST     	4 0 1
	69	[245]	JMP      	1	; to 71
	70	[245]	LOADK    	4 -11	; ""
	71	[246]	GETTABLE 	5 2 -8	; "path"
	72	[245]	CALL     	3 3 2
	73	[246]	SETTABLE 	2 -8 3	; "path" -
	74	[249]	GETUPVAL 	3 1	; _M
	75	[249]	GETTABLE 	3 3 -4	; "build"
	76	[249]	MOVE     	4 2
	77	[249]	TAILCALL 	3 2 0
	78	[249]	RETURN   	3 0
	79	[251]	RETURN   	0 1

function <./socket/url.lua:260,271> (42 instructions, 168 bytes at 0x7faad440bae0)
1 param, 8 slots, 3 upvalues, 6 locals, 10 constants, 1 function
	1	[261]	NEWTABLE 	1 0 0
	2	[262]	TEST     	0 0 1
	3	[262]	JMP      	1	; to 5
	4	[262]	LOADK    	0 -1	; ""
	5	[264]	GETUPVAL 	2 0	; string
	6	[264]	GETTABLE 	2 2 -2	; "gsub"
	7	[264]	MOVE     	3 0
	8	[264]	LOADK    	4 -3	; "([^/]+)"
	9	[264]	CLOSURE  	5 0	; 0x7faad440bba0
	10	[264]	GETUPVAL 	0 1	; table
	11	[264]	MOVE     	0 1
	12	[264]	CALL     	2 4 1
	13	[265]	LOADK    	2 -4	; 1
	14	[265]	LEN      	3 1
	15	[265]	LOADK    	4 -4	; 1
	16	[265]	FORPREP  	2 5	; to 22
	17	[266]	GETUPVAL 	6 2	; _M
	18	[266]	GETTABLE 	6 6 -5	; "unescape"
	19	[266]	GETTABLE 	7 1 5
	20	[266]	CALL     	6 2 2
	21	[266]	SETTABLE 	1 5 6
	22	[265]	FORLOOP  	2 -6	; to 17
	23	[268]	GETUPVAL 	2 0	; string
	24	[268]	GETTABLE 	2 2 -6	; "sub"
	25	[268]	MOVE     	3 0
	26	[268]	LOADK    	4 -4	; 1
	27	[268]	LOADK    	5 -4	; 1
	28	[268]	CALL     	2 4 2
	29	[268]	EQ       	0 2 -7	; - "/"
	30	[268]	JMP      	1	; to 32
	31	[268]	SETTABLE 	1 -8 -4	; "is_absolute" 1
	32	[269]	GETUPVAL 	2 0	; string
	33	[269]	GETTABLE 	2 2 -6	; "sub"
	34	[269]	MOVE     	3 0
	35	[269]	LOADK    	4 -9	; -1
	36	[269]	LOADK    	5 -9	; -1
	37	[269]	CALL     	2 4 2
	38	[269]	EQ       	0 2 -7	; - "/"
	39	[269]	JMP      	1	; to 41
	40	[269]	SETTABLE 	1 -10 -4	; "is_directory" 1
	41	[270]	RETURN   	1 2
	42	[271]	RETURN   	0 1

function <./socket/url.lua:264,264> (6 instructions, 24 bytes at 0x7faad440bba0)
1 param, 4 slots, 2 upvalues, 1 local, 1 constant, 0 functions
	1	[264]	GETUPVAL 	1 0	; table
	2	[264]	GETTABLE 	1 1 -1	; "insert"
	3	[264]	GETUPVAL 	2 1	; parsed
	4	[264]	MOVE     	3 0
	5	[264]	CALL     	1 3 1
	6	[264]	RETURN   	0 1

function <./socket/url.lua:281,305> (61 instructions, 244 bytes at 0x7faad440ca10)
2 params, 11 slots, 1 upvalue, 12 locals, 6 constants, 0 functions
	1	[282]	LOADK    	2 -1	; ""
	2	[283]	LEN      	3 0
	3	[284]	TEST     	1 0 0
	4	[284]	JMP      	23	; to 28
	5	[285]	LOADK    	4 -2	; 1
	6	[285]	SUB      	5 3 -2	; - 1
	7	[285]	LOADK    	6 -2	; 1
	8	[285]	FORPREP  	4 6	; to 15
	9	[286]	MOVE     	8 2
	10	[286]	GETTABLE 	9 0 7
	11	[286]	CONCAT   	2 8 9
	12	[287]	MOVE     	8 2
	13	[287]	LOADK    	9 -3	; "/"
	14	[287]	CONCAT   	2 8 9
	15	[285]	FORLOOP  	4 -7	; to 9
	16	[289]	LT       	0 -4 3	; 0 -
	17	[289]	JMP      	36	; to 54
	18	[290]	MOVE     	4 2
	19	[290]	GETTABLE 	5 0 3
	20	[290]	CONCAT   	2 4 5
	21	[291]	GETTABLE 	4 0 -5	; "is_directory"
	22	[291]	TEST     	4 0 0
	23	[291]	JMP      	30	; to 54
	24	[291]	MOVE     	4 2
	25	[291]	LOADK    	5 -3	; "/"
	26	[291]	CONCAT   	2 4 5
	27	[292]	JMP      	26	; to 54
	28	[294]	LOADK    	4 -2	; 1
	29	[294]	SUB      	5 3 -2	; - 1
	30	[294]	LOADK    	6 -2	; 1
	31	[294]	FORPREP  	4 8	; to 40
	32	[295]	MOVE     	8 2
	33	[295]	GETUPVAL 	9 0	; protect_segment
	34	[295]	GETTABLE 	10 0 7
	35	[295]	CALL     	9 2 2
	36	[295]	CONCAT   	2 8 9
	37	[296]	MOVE     	8 2
	38	[296]	LOADK    	9 -3	; "/"
	39	[296]	CONCAT   	2 8 9
	40	[294]	FORLOOP  	4 -9	; to 32
	41	[298]	LT       	0 -4 3	; 0 -
	42	[298]	JMP      	11	; to 54
	43	[299]	MOVE     	4 2
	44	[299]	GETUPVAL 	5 0	; protect_segment
	45	[299]	GETTABLE 	6 0 3
	46	[299]	CALL     	5 2 2
	47	[299]	CONCAT   	2 4 5
	48	[300]	GETTABLE 	4 0 -5	; "is_directory"
	49	[300]	TEST     	4 0 0
	50	[300]	JMP      	3	; to 54
	51	[300]	MOVE     	4 2
	52	[300]	LOADK    	5 -3	; "/"
	53	[300]	CONCAT   	2 4 5
	54	[303]	GETTABLE 	4 0 -6	; "is_absolute"
	55	[303]	TEST     	4 0 0
	56	[303]	JMP      	3	; to 60
	57	[303]	LOADK    	4 -3	; "/"
	58	[303]	MOVE     	5 2
	59	[303]	CONCAT   	2 4 5
	60	[304]	RETURN   	2 2
	61	[305]	RETURN   	0 1
-----------------------

main <./socket/ftp.lua:0,0> (145 instructions, 580 bytes at 0x7fe715c068a0)
0+ params, 19 slots, 0 upvalues, 17 locals, 38 constants, 22 functions
	1	[10]	GETGLOBAL	0 -1	; _G
	2	[11]	GETGLOBAL	1 -2	; require
	3	[11]	LOADK    	2 -3	; "table"
	4	[11]	CALL     	1 2 2
	5	[12]	GETGLOBAL	2 -2	; require
	6	[12]	LOADK    	3 -4	; "string"
	7	[12]	CALL     	2 2 2
	8	[13]	GETGLOBAL	3 -2	; require
	9	[13]	LOADK    	4 -5	; "math"
	10	[13]	CALL     	3 2 2
	11	[14]	GETGLOBAL	4 -2	; require
	12	[14]	LOADK    	5 -6	; "socket"
	13	[14]	CALL     	4 2 2
	14	[15]	GETGLOBAL	5 -2	; require
	15	[15]	LOADK    	6 -7	; "socket.url"
	16	[15]	CALL     	5 2 2
	17	[16]	GETGLOBAL	6 -2	; require
	18	[16]	LOADK    	7 -8	; "socket.tp"
	19	[16]	CALL     	6 2 2
	20	[17]	GETGLOBAL	7 -2	; require
	21	[17]	LOADK    	8 -9	; "ltn12"
	22	[17]	CALL     	7 2 2
	23	[18]	NEWTABLE 	8 0 0
	24	[18]	SETTABLE 	4 -10 8	; "ftp" -
	25	[19]	GETTABLE 	8 4 -10	; "ftp"
	26	[24]	SETTABLE 	8 -11 -12	; "TIMEOUT" 60
	27	[26]	SETTABLE 	8 -13 -14	; "PORT" 21
	28	[29]	SETTABLE 	8 -15 -10	; "USER" "ftp"
	29	[30]	SETTABLE 	8 -16 -17	; "PASSWORD" "anonymous@anonymous.org"
	30	[35]	NEWTABLE 	9 0 1
	31	[35]	NEWTABLE 	10 0 0
	32	[35]	SETTABLE 	9 -18 10	; "__index" -
	33	[43]	CLOSURE  	10 0	; 0x7fe715c06d00
	34	[43]	MOVE     	0 4
	35	[43]	MOVE     	0 6
	36	[43]	MOVE     	0 8
	37	[43]	MOVE     	0 0
	38	[43]	MOVE     	0 9
	39	[37]	SETTABLE 	8 -19 10	; "open" -
	40	[45]	GETTABLE 	10 9 -18	; "__index"
	41	[49]	CLOSURE  	11 1	; 0x7fe715c07000
	42	[49]	MOVE     	0 8
	43	[45]	SETTABLE 	10 -20 11	; "portconnect" -
	44	[51]	GETTABLE 	10 9 -18	; "__index"
	45	[55]	CLOSURE  	11 2	; 0x7fe715c07840
	46	[55]	MOVE     	0 4
	47	[55]	MOVE     	0 8
	48	[51]	SETTABLE 	10 -21 11	; "pasvconnect" -
	49	[57]	GETTABLE 	10 9 -18	; "__index"
	50	[65]	CLOSURE  	11 3	; 0x7fe715c07f60
	51	[65]	MOVE     	0 8
	52	[57]	SETTABLE 	10 -22 11	; "login" -
	53	[67]	GETTABLE 	10 9 -18	; "__index"
	54	[82]	CLOSURE  	11 4	; 0x7fe715c08800
	55	[82]	MOVE     	0 4
	56	[82]	MOVE     	0 2
	57	[67]	SETTABLE 	10 -23 11	; "pasv" -
	58	[84]	GETTABLE 	10 9 -18	; "__index"
	59	[98]	CLOSURE  	11 5	; 0x7fe715c089d0
	60	[98]	MOVE     	0 4
	61	[98]	MOVE     	0 8
	62	[98]	MOVE     	0 3
	63	[98]	MOVE     	0 2
	64	[84]	SETTABLE 	10 -24 11	; "port" -
	65	[100]	GETTABLE 	10 9 -18	; "__index"
	66	[135]	CLOSURE  	11 6	; 0x7fe715c08fd0
	67	[135]	MOVE     	0 5
	68	[135]	MOVE     	0 2
	69	[135]	MOVE     	0 7
	70	[135]	MOVE     	0 4
	71	[135]	MOVE     	0 6
	72	[100]	SETTABLE 	10 -25 11	; "send" -
	73	[137]	GETTABLE 	10 9 -18	; "__index"
	74	[158]	CLOSURE  	11 7	; 0x7fe715c0a1d0
	75	[158]	MOVE     	0 5
	76	[158]	MOVE     	0 2
	77	[158]	MOVE     	0 4
	78	[158]	MOVE     	0 7
	79	[137]	SETTABLE 	10 -26 11	; "receive" -
	80	[160]	GETTABLE 	10 9 -18	; "__index"
	81	[164]	CLOSURE  	11 8	; 0x7fe715c0a480
	82	[160]	SETTABLE 	10 -27 11	; "cwd" -
	83	[166]	GETTABLE 	10 9 -18	; "__index"
	84	[170]	CLOSURE  	11 9	; 0x7fe715c0acc0
	85	[166]	SETTABLE 	10 -28 11	; "type" -
	86	[172]	GETTABLE 	10 9 -18	; "__index"
	87	[176]	CLOSURE  	11 10	; 0x7fe715c0b080
	88	[176]	MOVE     	0 2
	89	[172]	SETTABLE 	10 -29 11	; "greet" -
	90	[178]	GETTABLE 	10 9 -18	; "__index"
	91	[182]	CLOSURE  	11 11	; 0x7fe715c0b620
	92	[178]	SETTABLE 	10 -30 11	; "quit" -
	93	[184]	GETTABLE 	10 9 -18	; "__index"
	94	[188]	CLOSURE  	11 12	; 0x7fe715c0b9d0
	95	[184]	SETTABLE 	10 -31 11	; "close" -
	96	[201]	CLOSURE  	10 13	; 0x7fe715c0be30
	97	[201]	MOVE     	0 5
	98	[201]	MOVE     	0 0
	99	[215]	CLOSURE  	11 14	; 0x7fe715c0c480
	100	[215]	MOVE     	0 10
	101	[215]	MOVE     	0 4
	102	[215]	MOVE     	0 8
	103	[217]	NEWTABLE 	12 0 2
	104	[218]	SETTABLE 	12 -32 -33	; "path" "/"
	105	[219]	SETTABLE 	12 -34 -10	; "scheme" "ftp"
	106	[233]	CLOSURE  	13 15	; 0x7fe715c0c750
	107	[233]	MOVE     	0 4
	108	[233]	MOVE     	0 5
	109	[233]	MOVE     	0 12
	110	[233]	MOVE     	0 2
	111	[239]	CLOSURE  	14 16	; 0x7fe715c06d80
	112	[239]	MOVE     	0 13
	113	[239]	MOVE     	0 7
	114	[239]	MOVE     	0 11
	115	[241]	GETTABLE 	15 4 -36	; "protect"
	116	[244]	CLOSURE  	16 17	; 0x7fe715c0ac40
	117	[244]	MOVE     	0 0
	118	[244]	MOVE     	0 14
	119	[244]	MOVE     	0 11
	120	[241]	CALL     	15 2 2
	121	[244]	SETTABLE 	8 -35 15	; "put" -
	122	[257]	CLOSURE  	15 18	; 0x7fe715c0d870
	123	[257]	MOVE     	0 10
	124	[257]	MOVE     	0 4
	125	[257]	MOVE     	0 8
	126	[265]	CLOSURE  	16 19	; 0x7fe715c0da30
	127	[265]	MOVE     	0 13
	128	[265]	MOVE     	0 7
	129	[265]	MOVE     	0 15
	130	[265]	MOVE     	0 1
	131	[267]	GETTABLE 	17 4 -36	; "protect"
	132	[278]	CLOSURE  	18 20	; 0x7fe715c0d970
	133	[278]	MOVE     	0 10
	134	[278]	MOVE     	0 4
	135	[267]	CALL     	17 2 2
	136	[278]	SETTABLE 	8 -37 17	; "command" -
	137	[280]	GETTABLE 	17 4 -36	; "protect"
	138	[283]	CLOSURE  	18 21	; 0x7fe715c09690
	139	[283]	MOVE     	0 0
	140	[283]	MOVE     	0 16
	141	[283]	MOVE     	0 15
	142	[280]	CALL     	17 2 2
	143	[283]	SETTABLE 	8 -38 17	; "get" -
	144	[285]	RETURN   	8 2
	145	[285]	RETURN   	0 1

function <./socket/ftp.lua:37,43> (28 instructions, 112 bytes at 0x7fe715c06d00)
3 params, 9 slots, 5 upvalues, 5 locals, 7 constants, 1 function
	1	[38]	GETUPVAL 	3 0	; socket
	2	[38]	GETTABLE 	3 3 -1	; "try"
	3	[38]	GETUPVAL 	4 1	; tp
	4	[38]	GETTABLE 	4 4 -2	; "connect"
	5	[38]	MOVE     	5 0
	6	[38]	TESTSET  	6 1 1
	7	[38]	JMP      	2	; to 10
	8	[38]	GETUPVAL 	6 2	; _M
	9	[38]	GETTABLE 	6 6 -3	; "PORT"
	10	[38]	GETUPVAL 	7 2	; _M
	11	[38]	GETTABLE 	7 7 -4	; "TIMEOUT"
	12	[38]	MOVE     	8 2
	13	[38]	CALL     	4 5 0
	14	[38]	CALL     	3 0 2
	15	[39]	GETUPVAL 	4 3	; base
	16	[39]	GETTABLE 	4 4 -5	; "setmetatable"
	17	[39]	NEWTABLE 	5 0 1
	18	[39]	SETTABLE 	5 -6 3	; "tp" -
	19	[39]	GETUPVAL 	6 4	; metat
	20	[39]	CALL     	4 3 2
	21	[41]	GETUPVAL 	5 0	; socket
	22	[41]	GETTABLE 	5 5 -7	; "newtry"
	23	[41]	CLOSURE  	6 0	; 0x7fe715c07280
	24	[41]	MOVE     	0 4
	25	[41]	CALL     	5 2 2
	26	[41]	SETTABLE 	4 -1 5	; "try" -
	27	[42]	RETURN   	4 2
	28	[43]	RETURN   	0 1

function <./socket/ftp.lua:41,41> (4 instructions, 16 bytes at 0x7fe715c07280)
0 params, 2 slots, 1 upvalue, 0 locals, 1 constant, 0 functions
	1	[41]	GETUPVAL 	0 0	; f
	2	[41]	SELF     	0 0 -1	; "close"
	3	[41]	CALL     	0 2 1
	4	[41]	RETURN   	0 1

function <./socket/ftp.lua:45,49> (21 instructions, 84 bytes at 0x7fe715c07000)
1 param, 5 slots, 1 upvalue, 1 local, 6 constants, 0 functions
	1	[46]	GETTABLE 	1 0 -1	; "try"
	2	[46]	GETTABLE 	2 0 -2	; "server"
	3	[46]	SELF     	2 2 -3	; "settimeout"
	4	[46]	GETUPVAL 	4 0	; _M
	5	[46]	GETTABLE 	4 4 -4	; "TIMEOUT"
	6	[46]	CALL     	2 3 0
	7	[46]	CALL     	1 0 1
	8	[47]	GETTABLE 	1 0 -1	; "try"
	9	[47]	GETTABLE 	2 0 -2	; "server"
	10	[47]	SELF     	2 2 -6	; "accept"
	11	[47]	CALL     	2 2 0
	12	[47]	CALL     	1 0 2
	13	[47]	SETTABLE 	0 -5 1	; "data" -
	14	[48]	GETTABLE 	1 0 -1	; "try"
	15	[48]	GETTABLE 	2 0 -5	; "data"
	16	[48]	SELF     	2 2 -3	; "settimeout"
	17	[48]	GETUPVAL 	4 0	; _M
	18	[48]	GETTABLE 	4 4 -4	; "TIMEOUT"
	19	[48]	CALL     	2 3 0
	20	[48]	CALL     	1 0 1
	21	[49]	RETURN   	0 1

function <./socket/ftp.lua:51,55> (23 instructions, 92 bytes at 0x7fe715c07840)
1 param, 6 slots, 2 upvalues, 1 local, 9 constants, 0 functions
	1	[52]	GETTABLE 	1 0 -2	; "try"
	2	[52]	GETUPVAL 	2 0	; socket
	3	[52]	GETTABLE 	2 2 -3	; "tcp"
	4	[52]	CALL     	2 1 0
	5	[52]	CALL     	1 0 2
	6	[52]	SETTABLE 	0 -1 1	; "data" -
	7	[53]	GETTABLE 	1 0 -2	; "try"
	8	[53]	GETTABLE 	2 0 -1	; "data"
	9	[53]	SELF     	2 2 -4	; "settimeout"
	10	[53]	GETUPVAL 	4 1	; _M
	11	[53]	GETTABLE 	4 4 -5	; "TIMEOUT"
	12	[53]	CALL     	2 3 0
	13	[53]	CALL     	1 0 1
	14	[54]	GETTABLE 	1 0 -2	; "try"
	15	[54]	GETTABLE 	2 0 -1	; "data"
	16	[54]	SELF     	2 2 -6	; "connect"
	17	[54]	GETTABLE 	4 0 -7	; "pasvt"
	18	[54]	GETTABLE 	4 4 -8	; "ip"
	19	[54]	GETTABLE 	5 0 -7	; "pasvt"
	20	[54]	GETTABLE 	5 5 -9	; "port"
	21	[54]	CALL     	2 4 0
	22	[54]	CALL     	1 0 1
	23	[55]	RETURN   	0 1

function <./socket/ftp.lua:57,65> (40 instructions, 160 bytes at 0x7fe715c07f60)
3 params, 10 slots, 1 upvalue, 5 locals, 11 constants, 0 functions
	1	[58]	GETTABLE 	3 0 -1	; "try"
	2	[58]	GETTABLE 	4 0 -2	; "tp"
	3	[58]	SELF     	4 4 -3	; "command"
	4	[58]	LOADK    	6 -4	; "user"
	5	[58]	TESTSET  	7 1 1
	6	[58]	JMP      	2	; to 9
	7	[58]	GETUPVAL 	7 0	; _M
	8	[58]	GETTABLE 	7 7 -5	; "USER"
	9	[58]	CALL     	4 4 0
	10	[58]	CALL     	3 0 1
	11	[59]	GETTABLE 	3 0 -1	; "try"
	12	[59]	GETTABLE 	4 0 -2	; "tp"
	13	[59]	SELF     	4 4 -6	; "check"
	14	[59]	NEWTABLE 	6 2 0
	15	[59]	LOADK    	7 -7	; "2.."
	16	[59]	LOADK    	8 -8	; 331
	17	[59]	SETLIST  	6 2 1	; 1
	18	[59]	CALL     	4 3 0
	19	[59]	CALL     	3 0 3
	20	[60]	EQ       	0 3 -8	; - 331
	21	[60]	JMP      	16	; to 38
	22	[61]	GETTABLE 	5 0 -1	; "try"
	23	[61]	GETTABLE 	6 0 -2	; "tp"
	24	[61]	SELF     	6 6 -3	; "command"
	25	[61]	LOADK    	8 -9	; "pass"
	26	[61]	TESTSET  	9 2 1
	27	[61]	JMP      	2	; to 30
	28	[61]	GETUPVAL 	9 0	; _M
	29	[61]	GETTABLE 	9 9 -10	; "PASSWORD"
	30	[61]	CALL     	6 4 0
	31	[61]	CALL     	5 0 1
	32	[62]	GETTABLE 	5 0 -1	; "try"
	33	[62]	GETTABLE 	6 0 -2	; "tp"
	34	[62]	SELF     	6 6 -6	; "check"
	35	[62]	LOADK    	8 -7	; "2.."
	36	[62]	CALL     	6 3 0
	37	[62]	CALL     	5 0 1
	38	[64]	LOADK    	5 -11	; 1
	39	[64]	RETURN   	5 2
	40	[65]	RETURN   	0 1

function <./socket/ftp.lua:67,82> (63 instructions, 252 bytes at 0x7fe715c08800)
1 param, 17 slots, 2 upvalues, 10 locals, 19 constants, 0 functions
	1	[68]	GETTABLE 	1 0 -1	; "try"
	2	[68]	GETTABLE 	2 0 -2	; "tp"
	3	[68]	SELF     	2 2 -3	; "command"
	4	[68]	LOADK    	4 -4	; "pasv"
	5	[68]	CALL     	2 3 0
	6	[68]	CALL     	1 0 1
	7	[69]	GETTABLE 	1 0 -1	; "try"
	8	[69]	GETTABLE 	2 0 -2	; "tp"
	9	[69]	SELF     	2 2 -5	; "check"
	10	[69]	LOADK    	4 -6	; "2.."
	11	[69]	CALL     	2 3 0
	12	[69]	CALL     	1 0 3
	13	[70]	LOADK    	3 -7	; "(%d+)%D(%d+)%D(%d+)%D(%d+)%D(%d+)%D(%d+)"
	14	[71]	GETUPVAL 	4 0	; socket
	15	[71]	GETTABLE 	4 4 -8	; "skip"
	16	[71]	LOADK    	5 -9	; 2
	17	[71]	GETUPVAL 	6 1	; string
	18	[71]	GETTABLE 	6 6 -10	; "find"
	19	[71]	MOVE     	7 2
	20	[71]	MOVE     	8 3
	21	[71]	CALL     	6 3 0
	22	[71]	CALL     	4 0 7
	23	[72]	GETTABLE 	10 0 -1	; "try"
	24	[72]	TESTSET  	11 4 0
	25	[72]	JMP      	9	; to 35
	26	[72]	TESTSET  	11 5 0
	27	[72]	JMP      	7	; to 35
	28	[72]	TESTSET  	11 6 0
	29	[72]	JMP      	5	; to 35
	30	[72]	TESTSET  	11 7 0
	31	[72]	JMP      	3	; to 35
	32	[72]	TESTSET  	11 8 0
	33	[72]	JMP      	1	; to 35
	34	[72]	MOVE     	11 9
	35	[72]	MOVE     	12 2
	36	[72]	CALL     	10 3 1
	37	[73]	NEWTABLE 	10 0 2
	38	[74]	GETUPVAL 	11 1	; string
	39	[74]	GETTABLE 	11 11 -13	; "format"
	40	[74]	LOADK    	12 -14	; "%d.%d.%d.%d"
	41	[74]	MOVE     	13 4
	42	[74]	MOVE     	14 5
	43	[74]	MOVE     	15 6
	44	[74]	MOVE     	16 7
	45	[74]	CALL     	11 6 2
	46	[74]	SETTABLE 	10 -12 11	; "ip" -
	47	[75]	MUL      	11 8 -16	; - 256
	48	[75]	ADD      	11 11 9
	49	[75]	SETTABLE 	10 -15 11	; "port" -
	50	[76]	SETTABLE 	0 -11 10	; "pasvt" -
	51	[77]	GETTABLE 	10 0 -17	; "server"
	52	[77]	TEST     	10 0 0
	53	[77]	JMP      	4	; to 58
	54	[78]	GETTABLE 	10 0 -17	; "server"
	55	[78]	SELF     	10 10 -18	; "close"
	56	[78]	CALL     	10 2 1
	57	[79]	SETTABLE 	0 -17 -19	; "server" nil
	58	[81]	GETTABLE 	10 0 -11	; "pasvt"
	59	[81]	GETTABLE 	10 10 -12	; "ip"
	60	[81]	GETTABLE 	11 0 -11	; "pasvt"
	61	[81]	GETTABLE 	11 11 -15	; "port"
	62	[81]	RETURN   	10 3
	63	[82]	RETURN   	0 1

function <./socket/ftp.lua:84,98> (69 instructions, 276 bytes at 0x7fe715c089d0)
3 params, 11 slots, 4 upvalues, 6 locals, 23 constants, 0 functions
	1	[85]	SETTABLE 	0 -1 -2	; "pasvt" nil
	2	[86]	TEST     	1 0 1
	3	[86]	JMP      	31	; to 35
	4	[87]	GETTABLE 	3 0 -3	; "try"
	5	[87]	GETTABLE 	4 0 -4	; "tp"
	6	[87]	SELF     	4 4 -5	; "getcontrol"
	7	[87]	CALL     	4 2 2
	8	[87]	SELF     	4 4 -6	; "getsockname"
	9	[87]	CALL     	4 2 0
	10	[87]	CALL     	3 0 3
	11	[87]	MOVE     	2 4
	12	[87]	MOVE     	1 3
	13	[88]	GETTABLE 	3 0 -3	; "try"
	14	[88]	GETUPVAL 	4 0	; socket
	15	[88]	GETTABLE 	4 4 -8	; "bind"
	16	[88]	MOVE     	5 1
	17	[88]	LOADK    	6 -9	; 0
	18	[88]	CALL     	4 3 0
	19	[88]	CALL     	3 0 2
	20	[88]	SETTABLE 	0 -7 3	; "server" -
	21	[89]	GETTABLE 	3 0 -3	; "try"
	22	[89]	GETTABLE 	4 0 -7	; "server"
	23	[89]	SELF     	4 4 -6	; "getsockname"
	24	[89]	CALL     	4 2 0
	25	[89]	CALL     	3 0 3
	26	[89]	MOVE     	2 4
	27	[89]	MOVE     	1 3
	28	[90]	GETTABLE 	3 0 -3	; "try"
	29	[90]	GETTABLE 	4 0 -7	; "server"
	30	[90]	SELF     	4 4 -10	; "settimeout"
	31	[90]	GETUPVAL 	6 1	; _M
	32	[90]	GETTABLE 	6 6 -11	; "TIMEOUT"
	33	[90]	CALL     	4 3 0
	34	[90]	CALL     	3 0 1
	35	[92]	GETUPVAL 	3 2	; math
	36	[92]	GETTABLE 	3 3 -12	; "mod"
	37	[92]	MOVE     	4 2
	38	[92]	LOADK    	5 -13	; 256
	39	[92]	CALL     	3 3 2
	40	[93]	SUB      	4 2 3
	41	[93]	DIV      	4 4 -13	; - 256
	42	[94]	GETUPVAL 	5 3	; string
	43	[94]	GETTABLE 	5 5 -14	; "gsub"
	44	[94]	GETUPVAL 	6 3	; string
	45	[94]	GETTABLE 	6 6 -15	; "format"
	46	[94]	LOADK    	7 -16	; "%s,%d,%d"
	47	[94]	MOVE     	8 1
	48	[94]	MOVE     	9 4
	49	[94]	MOVE     	10 3
	50	[94]	CALL     	6 5 2
	51	[94]	LOADK    	7 -17	; "%."
	52	[94]	LOADK    	8 -18	; ","
	53	[94]	CALL     	5 4 2
	54	[95]	GETTABLE 	6 0 -3	; "try"
	55	[95]	GETTABLE 	7 0 -4	; "tp"
	56	[95]	SELF     	7 7 -19	; "command"
	57	[95]	LOADK    	9 -20	; "port"
	58	[95]	MOVE     	10 5
	59	[95]	CALL     	7 4 0
	60	[95]	CALL     	6 0 1
	61	[96]	GETTABLE 	6 0 -3	; "try"
	62	[96]	GETTABLE 	7 0 -4	; "tp"
	63	[96]	SELF     	7 7 -21	; "check"
	64	[96]	LOADK    	9 -22	; "2.."
	65	[96]	CALL     	7 3 0
	66	[96]	CALL     	6 0 1
	67	[97]	LOADK    	6 -23	; 1
	68	[97]	RETURN   	6 2
	69	[98]	RETURN   	0 1

function <./socket/ftp.lua:100,135> (112 instructions, 448 bytes at 0x7fe715c08fd0)
2 params, 15 slots, 5 upvalues, 11 locals, 32 constants, 1 function
	1	[101]	GETTABLE 	2 0 -1	; "try"
	2	[101]	GETTABLE 	3 0 -2	; "pasvt"
	3	[101]	TEST     	3 0 1
	4	[101]	JMP      	1	; to 6
	5	[101]	GETTABLE 	3 0 -3	; "server"
	6	[101]	LOADK    	4 -4	; "need port or pasv first"
	7	[101]	CALL     	2 3 1
	8	[104]	GETTABLE 	2 0 -2	; "pasvt"
	9	[104]	TEST     	2 0 0
	10	[104]	JMP      	2	; to 13
	11	[104]	SELF     	2 0 -5	; "pasvconnect"
	12	[104]	CALL     	2 2 1
	13	[106]	GETTABLE 	2 1 -6	; "argument"
	14	[106]	TEST     	2 0 1
	15	[106]	JMP      	12	; to 28
	16	[107]	GETUPVAL 	2 0	; url
	17	[107]	GETTABLE 	2 2 -7	; "unescape"
	18	[107]	GETUPVAL 	3 1	; string
	19	[107]	GETTABLE 	3 3 -8	; "gsub"
	20	[107]	GETTABLE 	4 1 -9	; "path"
	21	[107]	TEST     	4 0 1
	22	[107]	JMP      	1	; to 24
	23	[107]	LOADK    	4 -10	; ""
	24	[107]	LOADK    	5 -11	; "^[/\\]"
	25	[107]	LOADK    	6 -10	; ""
	26	[107]	CALL     	3 4 0
	27	[107]	CALL     	2 0 2
	28	[108]	EQ       	0 2 -10	; - ""
	29	[108]	JMP      	1	; to 31
	30	[108]	LOADNIL  	2 2
	31	[109]	GETTABLE 	3 1 -12	; "command"
	32	[109]	TEST     	3 0 1
	33	[109]	JMP      	1	; to 35
	34	[109]	LOADK    	3 -13	; "stor"
	35	[111]	GETTABLE 	4 0 -1	; "try"
	36	[111]	GETTABLE 	5 0 -14	; "tp"
	37	[111]	SELF     	5 5 -12	; "command"
	38	[111]	MOVE     	7 3
	39	[111]	MOVE     	8 2
	40	[111]	CALL     	5 4 0
	41	[111]	CALL     	4 0 1
	42	[112]	GETTABLE 	4 0 -1	; "try"
	43	[112]	GETTABLE 	5 0 -14	; "tp"
	44	[112]	SELF     	5 5 -15	; "check"
	45	[112]	NEWTABLE 	7 2 0
	46	[112]	LOADK    	8 -16	; "2.."
	47	[112]	LOADK    	9 -17	; "1.."
	48	[112]	SETLIST  	7 2 1	; 1
	49	[112]	CALL     	5 3 0
	50	[112]	CALL     	4 0 3
	51	[115]	GETTABLE 	6 0 -2	; "pasvt"
	52	[115]	TEST     	6 0 1
	53	[115]	JMP      	2	; to 56
	54	[115]	SELF     	6 0 -18	; "portconnect"
	55	[115]	CALL     	6 2 1
	56	[117]	GETTABLE 	6 1 -19	; "step"
	57	[117]	TEST     	6 0 1
	58	[117]	JMP      	3	; to 62
	59	[117]	GETUPVAL 	6 2	; ltn12
	60	[117]	GETTABLE 	6 6 -20	; "pump"
	61	[117]	GETTABLE 	6 6 -19	; "step"
	62	[118]	NEWTABLE 	7 1 0
	63	[118]	GETTABLE 	8 0 -14	; "tp"
	64	[118]	GETTABLE 	8 8 -21	; "c"
	65	[118]	SETLIST  	7 1 1	; 1
	66	[124]	CLOSURE  	8 0	; 0x7fe715c07720
	67	[124]	GETUPVAL 	0 3	; socket
	68	[124]	MOVE     	0 7
	69	[124]	GETUPVAL 	0 4	; tp
	70	[124]	MOVE     	0 4
	71	[124]	MOVE     	0 0
	72	[124]	MOVE     	0 6
	73	[125]	GETUPVAL 	9 3	; socket
	74	[125]	GETTABLE 	9 9 -22	; "sink"
	75	[125]	LOADK    	10 -23	; "close-when-done"
	76	[125]	GETTABLE 	11 0 -24	; "data"
	77	[125]	CALL     	9 3 2
	78	[127]	GETTABLE 	10 0 -1	; "try"
	79	[127]	GETUPVAL 	11 2	; ltn12
	80	[127]	GETTABLE 	11 11 -20	; "pump"
	81	[127]	GETTABLE 	11 11 -25	; "all"
	82	[127]	GETTABLE 	12 1 -26	; "source"
	83	[127]	MOVE     	13 9
	84	[127]	MOVE     	14 8
	85	[127]	CALL     	11 4 0
	86	[127]	CALL     	10 0 1
	87	[128]	GETUPVAL 	10 1	; string
	88	[128]	GETTABLE 	10 10 -27	; "find"
	89	[128]	MOVE     	11 4
	90	[128]	LOADK    	12 -17	; "1.."
	91	[128]	CALL     	10 3 2
	92	[128]	TEST     	10 0 0
	93	[128]	JMP      	6	; to 100
	94	[128]	GETTABLE 	10 0 -1	; "try"
	95	[128]	GETTABLE 	11 0 -14	; "tp"
	96	[128]	SELF     	11 11 -15	; "check"
	97	[128]	LOADK    	13 -16	; "2.."
	98	[128]	CALL     	11 3 0
	99	[128]	CALL     	10 0 1
	100	[130]	GETTABLE 	10 0 -24	; "data"
	101	[130]	SELF     	10 10 -28	; "close"
	102	[130]	CALL     	10 2 1
	103	[132]	GETUPVAL 	10 3	; socket
	104	[132]	GETTABLE 	10 10 -29	; "skip"
	105	[132]	LOADK    	11 -30	; 1
	106	[132]	GETTABLE 	12 0 -24	; "data"
	107	[132]	SELF     	12 12 -31	; "getstats"
	108	[132]	CALL     	12 2 0
	109	[132]	CALL     	10 0 2
	110	[133]	SETTABLE 	0 -24 -32	; "data" nil
	111	[134]	RETURN   	10 2
	112	[135]	RETURN   	0 1

function <./socket/ftp.lua:119,124> (25 instructions, 100 bytes at 0x7fe715c07720)
2 params, 7 slots, 6 upvalues, 3 locals, 6 constants, 0 functions
	1	[121]	GETUPVAL 	2 0	; socket
	2	[121]	GETTABLE 	2 2 -1	; "select"
	3	[121]	GETUPVAL 	3 1	; readt
	4	[121]	LOADNIL  	4 4
	5	[121]	LOADK    	5 -2	; 0
	6	[121]	CALL     	2 4 2
	7	[122]	GETUPVAL 	3 2	; tp
	8	[122]	GETTABLE 	3 2 3
	9	[122]	TEST     	3 0 0
	10	[122]	JMP      	9	; to 20
	11	[122]	GETUPVAL 	3 4	; self
	12	[122]	GETTABLE 	3 3 -3	; "try"
	13	[122]	GETUPVAL 	4 4	; self
	14	[122]	GETTABLE 	4 4 -4	; "tp"
	15	[122]	SELF     	4 4 -5	; "check"
	16	[122]	LOADK    	6 -6	; "2.."
	17	[122]	CALL     	4 3 0
	18	[122]	CALL     	3 0 2
	19	[122]	SETUPVAL 	3 3	; code
	20	[123]	GETUPVAL 	3 5	; step
	21	[123]	MOVE     	4 0
	22	[123]	MOVE     	5 1
	23	[123]	TAILCALL 	3 3 0
	24	[123]	RETURN   	3 0
	25	[124]	RETURN   	0 1

function <./socket/ftp.lua:137,158> (104 instructions, 416 bytes at 0x7fe715c0a1d0)
2 params, 13 slots, 4 upvalues, 8 locals, 31 constants, 0 functions
	1	[138]	GETTABLE 	2 0 -1	; "try"
	2	[138]	GETTABLE 	3 0 -2	; "pasvt"
	3	[138]	TEST     	3 0 1
	4	[138]	JMP      	1	; to 6
	5	[138]	GETTABLE 	3 0 -3	; "server"
	6	[138]	LOADK    	4 -4	; "need port or pasv first"
	7	[138]	CALL     	2 3 1
	8	[139]	GETTABLE 	2 0 -2	; "pasvt"
	9	[139]	TEST     	2 0 0
	10	[139]	JMP      	2	; to 13
	11	[139]	SELF     	2 0 -5	; "pasvconnect"
	12	[139]	CALL     	2 2 1
	13	[140]	GETTABLE 	2 1 -6	; "argument"
	14	[140]	TEST     	2 0 1
	15	[140]	JMP      	12	; to 28
	16	[141]	GETUPVAL 	2 0	; url
	17	[141]	GETTABLE 	2 2 -7	; "unescape"
	18	[141]	GETUPVAL 	3 1	; string
	19	[141]	GETTABLE 	3 3 -8	; "gsub"
	20	[141]	GETTABLE 	4 1 -9	; "path"
	21	[141]	TEST     	4 0 1
	22	[141]	JMP      	1	; to 24
	23	[141]	LOADK    	4 -10	; ""
	24	[141]	LOADK    	5 -11	; "^[/\\]"
	25	[141]	LOADK    	6 -10	; ""
	26	[141]	CALL     	3 4 0
	27	[141]	CALL     	2 0 2
	28	[142]	EQ       	0 2 -10	; - ""
	29	[142]	JMP      	1	; to 31
	30	[142]	LOADNIL  	2 2
	31	[143]	GETTABLE 	3 1 -12	; "command"
	32	[143]	TEST     	3 0 1
	33	[143]	JMP      	1	; to 35
	34	[143]	LOADK    	3 -13	; "retr"
	35	[144]	GETTABLE 	4 0 -1	; "try"
	36	[144]	GETTABLE 	5 0 -14	; "tp"
	37	[144]	SELF     	5 5 -12	; "command"
	38	[144]	MOVE     	7 3
	39	[144]	MOVE     	8 2
	40	[144]	CALL     	5 4 0
	41	[144]	CALL     	4 0 1
	42	[145]	GETTABLE 	4 0 -1	; "try"
	43	[145]	GETTABLE 	5 0 -14	; "tp"
	44	[145]	SELF     	5 5 -15	; "check"
	45	[145]	NEWTABLE 	7 2 0
	46	[145]	LOADK    	8 -16	; "1.."
	47	[145]	LOADK    	9 -17	; "2.."
	48	[145]	SETLIST  	7 2 1	; 1
	49	[145]	CALL     	5 3 0
	50	[145]	CALL     	4 0 3
	51	[146]	LE       	0 -18 4	; 200 -
	52	[146]	JMP      	7	; to 60
	53	[146]	LE       	0 4 -19	; - 299
	54	[146]	JMP      	5	; to 60
	55	[147]	GETTABLE 	6 1 -20	; "sink"
	56	[147]	MOVE     	7 5
	57	[147]	CALL     	6 2 1
	58	[148]	LOADK    	6 -21	; 1
	59	[148]	RETURN   	6 2
	60	[150]	GETTABLE 	6 0 -2	; "pasvt"
	61	[150]	TEST     	6 0 1
	62	[150]	JMP      	2	; to 65
	63	[150]	SELF     	6 0 -22	; "portconnect"
	64	[150]	CALL     	6 2 1
	65	[151]	GETUPVAL 	6 2	; socket
	66	[151]	GETTABLE 	6 6 -23	; "source"
	67	[151]	LOADK    	7 -24	; "until-closed"
	68	[151]	GETTABLE 	8 0 -25	; "data"
	69	[151]	CALL     	6 3 2
	70	[152]	GETTABLE 	7 1 -26	; "step"
	71	[152]	TEST     	7 0 1
	72	[152]	JMP      	3	; to 76
	73	[152]	GETUPVAL 	7 3	; ltn12
	74	[152]	GETTABLE 	7 7 -27	; "pump"
	75	[152]	GETTABLE 	7 7 -26	; "step"
	76	[153]	GETTABLE 	8 0 -1	; "try"
	77	[153]	GETUPVAL 	9 3	; ltn12
	78	[153]	GETTABLE 	9 9 -27	; "pump"
	79	[153]	GETTABLE 	9 9 -28	; "all"
	80	[153]	MOVE     	10 6
	81	[153]	GETTABLE 	11 1 -20	; "sink"
	82	[153]	MOVE     	12 7
	83	[153]	CALL     	9 4 0
	84	[153]	CALL     	8 0 1
	85	[154]	GETUPVAL 	8 1	; string
	86	[154]	GETTABLE 	8 8 -29	; "find"
	87	[154]	MOVE     	9 4
	88	[154]	LOADK    	10 -16	; "1.."
	89	[154]	CALL     	8 3 2
	90	[154]	TEST     	8 0 0
	91	[154]	JMP      	6	; to 98
	92	[154]	GETTABLE 	8 0 -1	; "try"
	93	[154]	GETTABLE 	9 0 -14	; "tp"
	94	[154]	SELF     	9 9 -15	; "check"
	95	[154]	LOADK    	11 -17	; "2.."
	96	[154]	CALL     	9 3 0
	97	[154]	CALL     	8 0 1
	98	[155]	GETTABLE 	8 0 -25	; "data"
	99	[155]	SELF     	8 8 -30	; "close"
	100	[155]	CALL     	8 2 1
	101	[156]	SETTABLE 	0 -25 -31	; "data" nil
	102	[157]	LOADK    	8 -21	; 1
	103	[157]	RETURN   	8 2
	104	[158]	RETURN   	0 1

function <./socket/ftp.lua:160,164> (16 instructions, 64 bytes at 0x7fe715c0a480)
2 params, 7 slots, 0 upvalues, 2 locals, 7 constants, 0 functions
	1	[161]	GETTABLE 	2 0 -1	; "try"
	2	[161]	GETTABLE 	3 0 -2	; "tp"
	3	[161]	SELF     	3 3 -3	; "command"
	4	[161]	LOADK    	5 -4	; "cwd"
	5	[161]	MOVE     	6 1
	6	[161]	CALL     	3 4 0
	7	[161]	CALL     	2 0 1
	8	[162]	GETTABLE 	2 0 -1	; "try"
	9	[162]	GETTABLE 	3 0 -2	; "tp"
	10	[162]	SELF     	3 3 -5	; "check"
	11	[162]	LOADK    	5 -6	; 250
	12	[162]	CALL     	3 3 0
	13	[162]	CALL     	2 0 1
	14	[163]	LOADK    	2 -7	; 1
	15	[163]	RETURN   	2 2
	16	[164]	RETURN   	0 1

function <./socket/ftp.lua:166,170> (16 instructions, 64 bytes at 0x7fe715c0acc0)
2 params, 7 slots, 0 upvalues, 2 locals, 7 constants, 0 functions
	1	[167]	GETTABLE 	2 0 -1	; "try"
	2	[167]	GETTABLE 	3 0 -2	; "tp"
	3	[167]	SELF     	3 3 -3	; "command"
	4	[167]	LOADK    	5 -4	; "type"
	5	[167]	MOVE     	6 1
	6	[167]	CALL     	3 4 0
	7	[167]	CALL     	2 0 1
	8	[168]	GETTABLE 	2 0 -1	; "try"
	9	[168]	GETTABLE 	3 0 -2	; "tp"
	10	[168]	SELF     	3 3 -5	; "check"
	11	[168]	LOADK    	5 -6	; 200
	12	[168]	CALL     	3 3 0
	13	[168]	CALL     	2 0 1
	14	[169]	LOADK    	2 -7	; 1
	15	[169]	RETURN   	2 2
	16	[170]	RETURN   	0 1

function <./socket/ftp.lua:172,176> (25 instructions, 100 bytes at 0x7fe715c0b080)
1 param, 7 slots, 1 upvalue, 2 locals, 7 constants, 0 functions
	1	[173]	GETTABLE 	1 0 -1	; "try"
	2	[173]	GETTABLE 	2 0 -2	; "tp"
	3	[173]	SELF     	2 2 -3	; "check"
	4	[173]	NEWTABLE 	4 2 0
	5	[173]	LOADK    	5 -4	; "1.."
	6	[173]	LOADK    	6 -5	; "2.."
	7	[173]	SETLIST  	4 2 1	; 1
	8	[173]	CALL     	2 3 0
	9	[173]	CALL     	1 0 2
	10	[174]	GETUPVAL 	2 0	; string
	11	[174]	GETTABLE 	2 2 -6	; "find"
	12	[174]	MOVE     	3 1
	13	[174]	LOADK    	4 -4	; "1.."
	14	[174]	CALL     	2 3 2
	15	[174]	TEST     	2 0 0
	16	[174]	JMP      	6	; to 23
	17	[174]	GETTABLE 	2 0 -1	; "try"
	18	[174]	GETTABLE 	3 0 -2	; "tp"
	19	[174]	SELF     	3 3 -3	; "check"
	20	[174]	LOADK    	5 -5	; "2.."
	21	[174]	CALL     	3 3 0
	22	[174]	CALL     	2 0 1
	23	[175]	LOADK    	2 -7	; 1
	24	[175]	RETURN   	2 2
	25	[176]	RETURN   	0 1

function <./socket/ftp.lua:178,182> (15 instructions, 60 bytes at 0x7fe715c0b620)
1 param, 5 slots, 0 upvalues, 1 local, 7 constants, 0 functions
	1	[179]	GETTABLE 	1 0 -1	; "try"
	2	[179]	GETTABLE 	2 0 -2	; "tp"
	3	[179]	SELF     	2 2 -3	; "command"
	4	[179]	LOADK    	4 -4	; "quit"
	5	[179]	CALL     	2 3 0
	6	[179]	CALL     	1 0 1
	7	[180]	GETTABLE 	1 0 -1	; "try"
	8	[180]	GETTABLE 	2 0 -2	; "tp"
	9	[180]	SELF     	2 2 -5	; "check"
	10	[180]	LOADK    	4 -6	; "2.."
	11	[180]	CALL     	2 3 0
	12	[180]	CALL     	1 0 1
	13	[181]	LOADK    	1 -7	; 1
	14	[181]	RETURN   	1 2
	15	[182]	RETURN   	0 1

function <./socket/ftp.lua:184,188> (17 instructions, 68 bytes at 0x7fe715c0b9d0)
1 param, 3 slots, 0 upvalues, 1 local, 4 constants, 0 functions
	1	[185]	GETTABLE 	1 0 -1	; "data"
	2	[185]	TEST     	1 0 0
	3	[185]	JMP      	3	; to 7
	4	[185]	GETTABLE 	1 0 -1	; "data"
	5	[185]	SELF     	1 1 -2	; "close"
	6	[185]	CALL     	1 2 1
	7	[186]	GETTABLE 	1 0 -3	; "server"
	8	[186]	TEST     	1 0 0
	9	[186]	JMP      	3	; to 13
	10	[186]	GETTABLE 	1 0 -3	; "server"
	11	[186]	SELF     	1 1 -2	; "close"
	12	[186]	CALL     	1 2 1
	13	[187]	GETTABLE 	1 0 -4	; "tp"
	14	[187]	SELF     	1 1 -2	; "close"
	15	[187]	TAILCALL 	1 2 0
	16	[187]	RETURN   	1 0
	17	[188]	RETURN   	0 1

function <./socket/ftp.lua:193,201> (19 instructions, 76 bytes at 0x7fe715c0be30)
1 param, 8 slots, 2 upvalues, 7 locals, 3 constants, 0 functions
	1	[194]	GETTABLE 	1 0 -1	; "url"
	2	[194]	TEST     	1 0 0
	3	[194]	JMP      	14	; to 18
	4	[195]	GETUPVAL 	1 0	; url
	5	[195]	GETTABLE 	1 1 -2	; "parse"
	6	[195]	GETTABLE 	2 0 -1	; "url"
	7	[195]	CALL     	1 2 2
	8	[196]	GETUPVAL 	2 1	; base
	9	[196]	GETTABLE 	2 2 -3	; "pairs"
	10	[196]	MOVE     	3 0
	11	[196]	CALL     	2 2 4
	12	[196]	JMP      	1	; to 14
	13	[197]	SETTABLE 	1 5 6
	14	[196]	TFORLOOP 	2 2
	15	[197]	JMP      	-3	; to 13
	16	[199]	RETURN   	1 2
	17	[199]	JMP      	1	; to 19
	18	[200]	RETURN   	0 2
	19	[201]	RETURN   	0 1

function <./socket/ftp.lua:203,215> (38 instructions, 152 bytes at 0x7fe715c0c480)
1 param, 6 slots, 3 upvalues, 3 locals, 15 constants, 0 functions
	1	[204]	GETUPVAL 	1 0	; override
	2	[204]	MOVE     	2 0
	3	[204]	CALL     	1 2 2
	4	[204]	MOVE     	0 1
	5	[205]	GETUPVAL 	1 1	; socket
	6	[205]	GETTABLE 	1 1 -1	; "try"
	7	[205]	GETTABLE 	2 0 -2	; "host"
	8	[205]	LOADK    	3 -3	; "missing hostname"
	9	[205]	CALL     	1 3 1
	10	[206]	GETUPVAL 	1 2	; _M
	11	[206]	GETTABLE 	1 1 -4	; "open"
	12	[206]	GETTABLE 	2 0 -2	; "host"
	13	[206]	GETTABLE 	3 0 -5	; "port"
	14	[206]	GETTABLE 	4 0 -6	; "create"
	15	[206]	CALL     	1 4 2
	16	[207]	SELF     	2 1 -7	; "greet"
	17	[207]	CALL     	2 2 1
	18	[208]	SELF     	2 1 -8	; "login"
	19	[208]	GETTABLE 	4 0 -9	; "user"
	20	[208]	GETTABLE 	5 0 -10	; "password"
	21	[208]	CALL     	2 4 1
	22	[209]	GETTABLE 	2 0 -11	; "type"
	23	[209]	TEST     	2 0 0
	24	[209]	JMP      	3	; to 28
	25	[209]	SELF     	2 1 -11	; "type"
	26	[209]	GETTABLE 	4 0 -11	; "type"
	27	[209]	CALL     	2 3 1
	28	[210]	SELF     	2 1 -12	; "pasv"
	29	[210]	CALL     	2 2 1
	30	[211]	SELF     	2 1 -13	; "send"
	31	[211]	MOVE     	4 0
	32	[211]	CALL     	2 3 2
	33	[212]	SELF     	3 1 -14	; "quit"
	34	[212]	CALL     	3 2 1
	35	[213]	SELF     	3 1 -15	; "close"
	36	[213]	CALL     	3 2 1
	37	[214]	RETURN   	2 2
	38	[215]	RETURN   	0 1

function <./socket/ftp.lua:222,233> (56 instructions, 224 bytes at 0x7fe715c0c750)
1 param, 8 slots, 4 upvalues, 3 locals, 17 constants, 0 functions
	1	[223]	GETUPVAL 	1 0	; socket
	2	[223]	GETTABLE 	1 1 -1	; "try"
	3	[223]	GETUPVAL 	2 1	; url
	4	[223]	GETTABLE 	2 2 -2	; "parse"
	5	[223]	MOVE     	3 0
	6	[223]	GETUPVAL 	4 2	; default
	7	[223]	CALL     	2 3 0
	8	[223]	CALL     	1 0 2
	9	[224]	GETUPVAL 	2 0	; socket
	10	[224]	GETTABLE 	2 2 -1	; "try"
	11	[224]	GETTABLE 	3 1 -3	; "scheme"
	12	[224]	EQ       	1 3 -4	; - "ftp"
	13	[224]	JMP      	1	; to 15
	14	[224]	LOADBOOL 	3 0 1
	15	[224]	LOADBOOL 	3 1 0
	16	[224]	LOADK    	4 -5	; "wrong scheme '"
	17	[224]	GETTABLE 	5 1 -3	; "scheme"
	18	[224]	LOADK    	6 -6	; "'"
	19	[224]	CONCAT   	4 4 6
	20	[224]	CALL     	2 3 1
	21	[225]	GETUPVAL 	2 0	; socket
	22	[225]	GETTABLE 	2 2 -1	; "try"
	23	[225]	GETTABLE 	3 1 -7	; "host"
	24	[225]	LOADK    	4 -8	; "missing hostname"
	25	[225]	CALL     	2 3 1
	26	[226]	LOADK    	2 -9	; "^type=(.)$"
	27	[227]	GETTABLE 	3 1 -10	; "params"
	28	[227]	TEST     	3 0 0
	29	[227]	JMP      	25	; to 55
	30	[228]	GETUPVAL 	3 0	; socket
	31	[228]	GETTABLE 	3 3 -12	; "skip"
	32	[228]	LOADK    	4 -13	; 2
	33	[228]	GETUPVAL 	5 3	; string
	34	[228]	GETTABLE 	5 5 -14	; "find"
	35	[228]	GETTABLE 	6 1 -10	; "params"
	36	[228]	MOVE     	7 2
	37	[228]	CALL     	5 3 0
	38	[228]	CALL     	3 0 2
	39	[228]	SETTABLE 	1 -11 3	; "type" -
	40	[229]	GETUPVAL 	3 0	; socket
	41	[229]	GETTABLE 	3 3 -1	; "try"
	42	[229]	GETTABLE 	4 1 -11	; "type"
	43	[229]	EQ       	1 4 -15	; - "a"
	44	[229]	JMP      	4	; to 49
	45	[229]	GETTABLE 	4 1 -11	; "type"
	46	[229]	EQ       	1 4 -16	; - "i"
	47	[229]	JMP      	1	; to 49
	48	[229]	LOADBOOL 	4 0 1
	49	[229]	LOADBOOL 	4 1 0
	50	[230]	LOADK    	5 -17	; "invalid type '"
	51	[230]	GETTABLE 	6 1 -11	; "type"
	52	[230]	LOADK    	7 -6	; "'"
	53	[230]	CONCAT   	5 5 7
	54	[229]	CALL     	3 3 1
	55	[232]	RETURN   	1 2
	56	[233]	RETURN   	0 1

function <./socket/ftp.lua:235,239> (14 instructions, 56 bytes at 0x7fe715c06d80)
2 params, 5 slots, 3 upvalues, 3 locals, 2 constants, 0 functions
	1	[236]	GETUPVAL 	2 0	; parse
	2	[236]	MOVE     	3 0
	3	[236]	CALL     	2 2 2
	4	[237]	GETUPVAL 	3 1	; ltn12
	5	[237]	GETTABLE 	3 3 -1	; "source"
	6	[237]	GETTABLE 	3 3 -2	; "string"
	7	[237]	MOVE     	4 1
	8	[237]	CALL     	3 2 2
	9	[237]	SETTABLE 	2 -1 3	; "source" -
	10	[238]	GETUPVAL 	3 2	; tput
	11	[238]	MOVE     	4 2
	12	[238]	TAILCALL 	3 2 0
	13	[238]	RETURN   	3 0
	14	[239]	RETURN   	0 1

function <./socket/ftp.lua:241,244> (17 instructions, 68 bytes at 0x7fe715c0ac40)
2 params, 5 slots, 3 upvalues, 2 locals, 2 constants, 0 functions
	1	[242]	GETUPVAL 	2 0	; base
	2	[242]	GETTABLE 	2 2 -1	; "type"
	3	[242]	MOVE     	3 0
	4	[242]	CALL     	2 2 2
	5	[242]	EQ       	0 2 -2	; - "string"
	6	[242]	JMP      	6	; to 13
	7	[242]	GETUPVAL 	2 1	; sput
	8	[242]	MOVE     	3 0
	9	[242]	MOVE     	4 1
	10	[242]	TAILCALL 	2 3 0
	11	[242]	RETURN   	2 0
	12	[242]	JMP      	4	; to 17
	13	[243]	GETUPVAL 	2 2	; tput
	14	[243]	MOVE     	3 0
	15	[243]	TAILCALL 	2 2 0
	16	[243]	RETURN   	2 0
	17	[244]	RETURN   	0 1

function <./socket/ftp.lua:246,257> (38 instructions, 152 bytes at 0x7fe715c0d870)
1 param, 6 slots, 3 upvalues, 2 locals, 15 constants, 0 functions
	1	[247]	GETUPVAL 	1 0	; override
	2	[247]	MOVE     	2 0
	3	[247]	CALL     	1 2 2
	4	[247]	MOVE     	0 1
	5	[248]	GETUPVAL 	1 1	; socket
	6	[248]	GETTABLE 	1 1 -1	; "try"
	7	[248]	GETTABLE 	2 0 -2	; "host"
	8	[248]	LOADK    	3 -3	; "missing hostname"
	9	[248]	CALL     	1 3 1
	10	[249]	GETUPVAL 	1 2	; _M
	11	[249]	GETTABLE 	1 1 -4	; "open"
	12	[249]	GETTABLE 	2 0 -2	; "host"
	13	[249]	GETTABLE 	3 0 -5	; "port"
	14	[249]	GETTABLE 	4 0 -6	; "create"
	15	[249]	CALL     	1 4 2
	16	[250]	SELF     	2 1 -7	; "greet"
	17	[250]	CALL     	2 2 1
	18	[251]	SELF     	2 1 -8	; "login"
	19	[251]	GETTABLE 	4 0 -9	; "user"
	20	[251]	GETTABLE 	5 0 -10	; "password"
	21	[251]	CALL     	2 4 1
	22	[252]	GETTABLE 	2 0 -11	; "type"
	23	[252]	TEST     	2 0 0
	24	[252]	JMP      	3	; to 28
	25	[252]	SELF     	2 1 -11	; "type"
	26	[252]	GETTABLE 	4 0 -11	; "type"
	27	[252]	CALL     	2 3 1
	28	[253]	SELF     	2 1 -12	; "pasv"
	29	[253]	CALL     	2 2 1
	30	[254]	SELF     	2 1 -13	; "receive"
	31	[254]	MOVE     	4 0
	32	[254]	CALL     	2 3 1
	33	[255]	SELF     	2 1 -14	; "quit"
	34	[255]	CALL     	2 2 1
	35	[256]	SELF     	2 1 -15	; "close"
	36	[256]	TAILCALL 	2 2 0
	37	[256]	RETURN   	2 0
	38	[257]	RETURN   	0 1

function <./socket/ftp.lua:259,265> (19 instructions, 76 bytes at 0x7fe715c0da30)
1 param, 5 slots, 4 upvalues, 3 locals, 3 constants, 0 functions
	1	[260]	GETUPVAL 	1 0	; parse
	2	[260]	MOVE     	2 0
	3	[260]	CALL     	1 2 2
	4	[261]	NEWTABLE 	2 0 0
	5	[262]	GETUPVAL 	3 1	; ltn12
	6	[262]	GETTABLE 	3 3 -1	; "sink"
	7	[262]	GETTABLE 	3 3 -2	; "table"
	8	[262]	MOVE     	4 2
	9	[262]	CALL     	3 2 2
	10	[262]	SETTABLE 	1 -1 3	; "sink" -
	11	[263]	GETUPVAL 	3 2	; tget
	12	[263]	MOVE     	4 1
	13	[263]	CALL     	3 2 1
	14	[264]	GETUPVAL 	3 3	; table
	15	[264]	GETTABLE 	3 3 -3	; "concat"
	16	[264]	MOVE     	4 2
	17	[264]	TAILCALL 	3 2 0
	18	[264]	RETURN   	3 0
	19	[265]	RETURN   	0 1

function <./socket/ftp.lua:267,278> (47 instructions, 188 bytes at 0x7fe715c0d970)
1 param, 7 slots, 2 upvalues, 2 locals, 17 constants, 0 functions
	1	[268]	GETUPVAL 	1 0	; override
	2	[268]	MOVE     	2 0
	3	[268]	CALL     	1 2 2
	4	[268]	MOVE     	0 1
	5	[269]	GETUPVAL 	1 1	; socket
	6	[269]	GETTABLE 	1 1 -1	; "try"
	7	[269]	GETTABLE 	2 0 -2	; "host"
	8	[269]	LOADK    	3 -3	; "missing hostname"
	9	[269]	CALL     	1 3 1
	10	[270]	GETUPVAL 	1 1	; socket
	11	[270]	GETTABLE 	1 1 -1	; "try"
	12	[270]	GETTABLE 	2 0 -4	; "command"
	13	[270]	LOADK    	3 -5	; "missing command"
	14	[270]	CALL     	1 3 1
	15	[271]	GETGLOBAL	1 -6	; open
	16	[271]	GETTABLE 	2 0 -2	; "host"
	17	[271]	GETTABLE 	3 0 -7	; "port"
	18	[271]	GETTABLE 	4 0 -8	; "create"
	19	[271]	CALL     	1 4 2
	20	[272]	SELF     	2 1 -9	; "greet"
	21	[272]	CALL     	2 2 1
	22	[273]	SELF     	2 1 -10	; "login"
	23	[273]	GETTABLE 	4 0 -11	; "user"
	24	[273]	GETTABLE 	5 0 -12	; "password"
	25	[273]	CALL     	2 4 1
	26	[274]	GETTABLE 	2 1 -1	; "try"
	27	[274]	GETTABLE 	3 1 -13	; "tp"
	28	[274]	SELF     	3 3 -4	; "command"
	29	[274]	GETTABLE 	5 0 -4	; "command"
	30	[274]	GETTABLE 	6 0 -14	; "argument"
	31	[274]	CALL     	3 4 0
	32	[274]	CALL     	2 0 1
	33	[275]	GETTABLE 	2 0 -15	; "check"
	34	[275]	TEST     	2 0 0
	35	[275]	JMP      	6	; to 42
	36	[275]	GETTABLE 	2 1 -1	; "try"
	37	[275]	GETTABLE 	3 1 -13	; "tp"
	38	[275]	SELF     	3 3 -15	; "check"
	39	[275]	GETTABLE 	5 0 -15	; "check"
	40	[275]	CALL     	3 3 0
	41	[275]	CALL     	2 0 1
	42	[276]	SELF     	2 1 -16	; "quit"
	43	[276]	CALL     	2 2 1
	44	[277]	SELF     	2 1 -17	; "close"
	45	[277]	TAILCALL 	2 2 0
	46	[277]	RETURN   	2 0
	47	[278]	RETURN   	0 1

function <./socket/ftp.lua:280,283> (16 instructions, 64 bytes at 0x7fe715c09690)
1 param, 3 slots, 3 upvalues, 1 local, 2 constants, 0 functions
	1	[281]	GETUPVAL 	1 0	; base
	2	[281]	GETTABLE 	1 1 -1	; "type"
	3	[281]	MOVE     	2 0
	4	[281]	CALL     	1 2 2
	5	[281]	EQ       	0 1 -2	; - "string"
	6	[281]	JMP      	5	; to 12
	7	[281]	GETUPVAL 	1 1	; sget
	8	[281]	MOVE     	2 0
	9	[281]	TAILCALL 	1 2 0
	10	[281]	RETURN   	1 0
	11	[281]	JMP      	4	; to 16
	12	[282]	GETUPVAL 	1 2	; tget
	13	[282]	MOVE     	2 0
	14	[282]	TAILCALL 	1 2 0
	15	[282]	RETURN   	1 0
	16	[283]	RETURN   	0 1
-----------------------

main <./socket/smtp.lua:0,0> (141 instructions, 564 bytes at 0x7f8574c068a0)
0+ params, 23 slots, 0 upvalues, 21 locals, 38 constants, 21 functions
	1	[10]	GETGLOBAL	0 -1	; _G
	2	[11]	GETGLOBAL	1 -2	; require
	3	[11]	LOADK    	2 -3	; "coroutine"
	4	[11]	CALL     	1 2 2
	5	[12]	GETGLOBAL	2 -2	; require
	6	[12]	LOADK    	3 -4	; "string"
	7	[12]	CALL     	2 2 2
	8	[13]	GETGLOBAL	3 -2	; require
	9	[13]	LOADK    	4 -5	; "math"
	10	[13]	CALL     	3 2 2
	11	[14]	GETGLOBAL	4 -2	; require
	12	[14]	LOADK    	5 -6	; "os"
	13	[14]	CALL     	4 2 2
	14	[15]	GETGLOBAL	5 -2	; require
	15	[15]	LOADK    	6 -7	; "socket"
	16	[15]	CALL     	5 2 2
	17	[16]	GETGLOBAL	6 -2	; require
	18	[16]	LOADK    	7 -8	; "socket.tp"
	19	[16]	CALL     	6 2 2
	20	[17]	GETGLOBAL	7 -2	; require
	21	[17]	LOADK    	8 -9	; "ltn12"
	22	[17]	CALL     	7 2 2
	23	[18]	GETGLOBAL	8 -2	; require
	24	[18]	LOADK    	9 -10	; "socket.headers"
	25	[18]	CALL     	8 2 2
	26	[19]	GETGLOBAL	9 -2	; require
	27	[19]	LOADK    	10 -11	; "mime"
	28	[19]	CALL     	9 2 2
	29	[21]	NEWTABLE 	10 0 0
	30	[21]	SETTABLE 	5 -12 10	; "smtp" -
	31	[22]	GETTABLE 	10 5 -12	; "smtp"
	32	[28]	SETTABLE 	10 -13 -14	; "TIMEOUT" 60
	33	[30]	SETTABLE 	10 -15 -16	; "SERVER" "localhost"
	34	[32]	SETTABLE 	10 -17 -18	; "PORT" 25
	35	[35]	GETTABLE 	11 4 -20	; "getenv"
	36	[35]	LOADK    	12 -21	; "SERVER_NAME"
	37	[35]	CALL     	11 2 2
	38	[35]	TEST     	11 0 1
	39	[35]	JMP      	1	; to 41
	40	[35]	LOADK    	11 -16	; "localhost"
	41	[35]	SETTABLE 	10 -19 11	; "DOMAIN" -
	42	[37]	SETTABLE 	10 -22 -23	; "ZONE" "-0000"
	43	[42]	NEWTABLE 	11 0 1
	44	[42]	NEWTABLE 	12 0 0
	45	[42]	SETTABLE 	11 -24 12	; "__index" -
	46	[44]	GETTABLE 	12 11 -24	; "__index"
	47	[48]	CLOSURE  	13 0	; 0x7f8574c06c30
	48	[48]	MOVE     	0 10
	49	[48]	MOVE     	0 5
	50	[44]	SETTABLE 	12 -25 13	; "greet" -
	51	[50]	GETTABLE 	12 11 -24	; "__index"
	52	[53]	CLOSURE  	13 1	; 0x7f8574c06680
	53	[50]	SETTABLE 	12 -26 13	; "mail" -
	54	[55]	GETTABLE 	12 11 -24	; "__index"
	55	[58]	CLOSURE  	13 2	; 0x7f8574c07530
	56	[55]	SETTABLE 	12 -27 13	; "rcpt" -
	57	[60]	GETTABLE 	12 11 -24	; "__index"
	58	[66]	CLOSURE  	13 3	; 0x7f8574c07f60
	59	[60]	SETTABLE 	12 -28 13	; "data" -
	60	[68]	GETTABLE 	12 11 -24	; "__index"
	61	[71]	CLOSURE  	13 4	; 0x7f8574c084f0
	62	[68]	SETTABLE 	12 -29 13	; "quit" -
	63	[73]	GETTABLE 	12 11 -24	; "__index"
	64	[75]	CLOSURE  	13 5	; 0x7f8574c08c30
	65	[73]	SETTABLE 	12 -30 13	; "close" -
	66	[77]	GETTABLE 	12 11 -24	; "__index"
	67	[84]	CLOSURE  	13 6	; 0x7f8574c09010
	68	[84]	MOVE     	0 9
	69	[77]	SETTABLE 	12 -31 13	; "login" -
	70	[86]	GETTABLE 	12 11 -24	; "__index"
	71	[90]	CLOSURE  	13 7	; 0x7f8574c06e50
	72	[90]	MOVE     	0 9
	73	[86]	SETTABLE 	12 -32 13	; "plain" -
	74	[92]	GETTABLE 	12 11 -24	; "__index"
	75	[101]	CLOSURE  	13 8	; 0x7f8574c06ef0
	76	[101]	MOVE     	0 2
	77	[92]	SETTABLE 	12 -33 13	; "auth" -
	78	[104]	GETTABLE 	12 11 -24	; "__index"
	79	[114]	CLOSURE  	13 9	; 0x7f8574c08f90
	80	[114]	MOVE     	0 0
	81	[114]	MOVE     	0 7
	82	[114]	MOVE     	0 9
	83	[104]	SETTABLE 	12 -34 13	; "send" -
	84	[125]	CLOSURE  	12 10	; 0x7f8574c09830
	85	[125]	MOVE     	0 5
	86	[125]	MOVE     	0 6
	87	[125]	MOVE     	0 10
	88	[125]	MOVE     	0 0
	89	[125]	MOVE     	0 11
	90	[116]	SETTABLE 	10 -35 12	; "open" -
	91	[134]	CLOSURE  	12 11	; 0x7f8574c09d90
	92	[134]	MOVE     	0 0
	93	[134]	MOVE     	0 2
	94	[140]	LOADK    	13 -36	; 0
	95	[145]	CLOSURE  	14 12	; 0x7f8574c0a160
	96	[145]	MOVE     	0 13
	97	[145]	MOVE     	0 2
	98	[145]	MOVE     	0 4
	99	[145]	MOVE     	0 3
	100	[148]	LOADNIL  	15 15
	101	[158]	CLOSURE  	16 13	; 0x7f8574c0a400
	102	[158]	MOVE     	0 8
	103	[158]	MOVE     	0 0
	104	[158]	MOVE     	0 1
	105	[186]	CLOSURE  	17 14	; 0x7f8574c0ac00
	106	[186]	MOVE     	0 14
	107	[186]	MOVE     	0 12
	108	[186]	MOVE     	0 16
	109	[186]	MOVE     	0 1
	110	[186]	MOVE     	0 0
	111	[186]	MOVE     	0 15
	112	[202]	CLOSURE  	18 15	; 0x7f8574c0adf0
	113	[202]	MOVE     	0 12
	114	[202]	MOVE     	0 16
	115	[202]	MOVE     	0 1
	116	[213]	CLOSURE  	19 16	; 0x7f8574c09cf0
	117	[213]	MOVE     	0 12
	118	[213]	MOVE     	0 16
	119	[213]	MOVE     	0 1
	120	[220]	CLOSURE  	15 17	; 0x7f8574c08d90
	121	[220]	MOVE     	0 0
	122	[220]	MOVE     	0 17
	123	[220]	MOVE     	0 18
	124	[216]	MOVE     	0 19
	125	[231]	CLOSURE  	20 18	; 0x7f8574c0ba00
	126	[231]	MOVE     	0 12
	127	[231]	MOVE     	0 4
	128	[231]	MOVE     	0 10
	129	[231]	MOVE     	0 5
	130	[242]	CLOSURE  	21 19	; 0x7f8574c0c080
	131	[242]	MOVE     	0 20
	132	[242]	MOVE     	0 1
	133	[242]	MOVE     	0 15
	134	[233]	SETTABLE 	10 -37 21	; "message" -
	135	[247]	GETTABLE 	21 5 -38	; "protect"
	136	[254]	CLOSURE  	22 20	; 0x7f8574c0c760
	137	[254]	MOVE     	0 10
	138	[247]	CALL     	21 2 2
	139	[254]	SETTABLE 	10 -34 21	; "send" -
	140	[256]	RETURN   	10 2
	141	[256]	RETURN   	0 1

function <./socket/smtp.lua:44,48> (28 instructions, 112 bytes at 0x7f8574c06c30)
2 params, 8 slots, 2 upvalues, 2 locals, 9 constants, 0 functions
	1	[45]	GETTABLE 	2 0 -1	; "try"
	2	[45]	GETTABLE 	3 0 -2	; "tp"
	3	[45]	SELF     	3 3 -3	; "check"
	4	[45]	LOADK    	5 -4	; "2.."
	5	[45]	CALL     	3 3 0
	6	[45]	CALL     	2 0 1
	7	[46]	GETTABLE 	2 0 -1	; "try"
	8	[46]	GETTABLE 	3 0 -2	; "tp"
	9	[46]	SELF     	3 3 -5	; "command"
	10	[46]	LOADK    	5 -6	; "EHLO"
	11	[46]	TESTSET  	6 1 1
	12	[46]	JMP      	2	; to 15
	13	[46]	GETUPVAL 	6 0	; _M
	14	[46]	GETTABLE 	6 6 -7	; "DOMAIN"
	15	[46]	CALL     	3 4 0
	16	[46]	CALL     	2 0 1
	17	[47]	GETUPVAL 	2 1	; socket
	18	[47]	GETTABLE 	2 2 -8	; "skip"
	19	[47]	LOADK    	3 -9	; 1
	20	[47]	GETTABLE 	4 0 -1	; "try"
	21	[47]	GETTABLE 	5 0 -2	; "tp"
	22	[47]	SELF     	5 5 -3	; "check"
	23	[47]	LOADK    	7 -4	; "2.."
	24	[47]	CALL     	5 3 0
	25	[47]	CALL     	4 0 0
	26	[47]	TAILCALL 	2 0 0
	27	[47]	RETURN   	2 0
	28	[48]	RETURN   	0 1

function <./socket/smtp.lua:50,53> (17 instructions, 68 bytes at 0x7f8574c06680)
2 params, 8 slots, 0 upvalues, 2 locals, 7 constants, 0 functions
	1	[51]	GETTABLE 	2 0 -1	; "try"
	2	[51]	GETTABLE 	3 0 -2	; "tp"
	3	[51]	SELF     	3 3 -3	; "command"
	4	[51]	LOADK    	5 -4	; "MAIL"
	5	[51]	LOADK    	6 -5	; "FROM:"
	6	[51]	MOVE     	7 1
	7	[51]	CONCAT   	6 6 7
	8	[51]	CALL     	3 4 0
	9	[51]	CALL     	2 0 1
	10	[52]	GETTABLE 	2 0 -1	; "try"
	11	[52]	GETTABLE 	3 0 -2	; "tp"
	12	[52]	SELF     	3 3 -6	; "check"
	13	[52]	LOADK    	5 -7	; "2.."
	14	[52]	CALL     	3 3 0
	15	[52]	TAILCALL 	2 0 0
	16	[52]	RETURN   	2 0
	17	[53]	RETURN   	0 1

function <./socket/smtp.lua:55,58> (17 instructions, 68 bytes at 0x7f8574c07530)
2 params, 8 slots, 0 upvalues, 2 locals, 7 constants, 0 functions
	1	[56]	GETTABLE 	2 0 -1	; "try"
	2	[56]	GETTABLE 	3 0 -2	; "tp"
	3	[56]	SELF     	3 3 -3	; "command"
	4	[56]	LOADK    	5 -4	; "RCPT"
	5	[56]	LOADK    	6 -5	; "TO:"
	6	[56]	MOVE     	7 1
	7	[56]	CONCAT   	6 6 7
	8	[56]	CALL     	3 4 0
	9	[56]	CALL     	2 0 1
	10	[57]	GETTABLE 	2 0 -1	; "try"
	11	[57]	GETTABLE 	3 0 -2	; "tp"
	12	[57]	SELF     	3 3 -6	; "check"
	13	[57]	LOADK    	5 -7	; "2.."
	14	[57]	CALL     	3 3 0
	15	[57]	TAILCALL 	2 0 0
	16	[57]	RETURN   	2 0
	17	[58]	RETURN   	0 1

function <./socket/smtp.lua:60,66> (33 instructions, 132 bytes at 0x7f8574c07f60)
3 params, 8 slots, 0 upvalues, 3 locals, 10 constants, 0 functions
	1	[61]	GETTABLE 	3 0 -1	; "try"
	2	[61]	GETTABLE 	4 0 -2	; "tp"
	3	[61]	SELF     	4 4 -3	; "command"
	4	[61]	LOADK    	6 -4	; "DATA"
	5	[61]	CALL     	4 3 0
	6	[61]	CALL     	3 0 1
	7	[62]	GETTABLE 	3 0 -1	; "try"
	8	[62]	GETTABLE 	4 0 -2	; "tp"
	9	[62]	SELF     	4 4 -5	; "check"
	10	[62]	LOADK    	6 -6	; "3.."
	11	[62]	CALL     	4 3 0
	12	[62]	CALL     	3 0 1
	13	[63]	GETTABLE 	3 0 -1	; "try"
	14	[63]	GETTABLE 	4 0 -2	; "tp"
	15	[63]	SELF     	4 4 -7	; "source"
	16	[63]	MOVE     	6 1
	17	[63]	MOVE     	7 2
	18	[63]	CALL     	4 4 0
	19	[63]	CALL     	3 0 1
	20	[64]	GETTABLE 	3 0 -1	; "try"
	21	[64]	GETTABLE 	4 0 -2	; "tp"
	22	[64]	SELF     	4 4 -8	; "send"
	23	[64]	LOADK    	6 -9	; "\r\n.\r\n"
	24	[64]	CALL     	4 3 0
	25	[64]	CALL     	3 0 1
	26	[65]	GETTABLE 	3 0 -1	; "try"
	27	[65]	GETTABLE 	4 0 -2	; "tp"
	28	[65]	SELF     	4 4 -5	; "check"
	29	[65]	LOADK    	6 -10	; "2.."
	30	[65]	CALL     	4 3 0
	31	[65]	TAILCALL 	3 0 0
	32	[65]	RETURN   	3 0
	33	[66]	RETURN   	0 1

function <./socket/smtp.lua:68,71> (14 instructions, 56 bytes at 0x7f8574c084f0)
1 param, 5 slots, 0 upvalues, 1 local, 6 constants, 0 functions
	1	[69]	GETTABLE 	1 0 -1	; "try"
	2	[69]	GETTABLE 	2 0 -2	; "tp"
	3	[69]	SELF     	2 2 -3	; "command"
	4	[69]	LOADK    	4 -4	; "QUIT"
	5	[69]	CALL     	2 3 0
	6	[69]	CALL     	1 0 1
	7	[70]	GETTABLE 	1 0 -1	; "try"
	8	[70]	GETTABLE 	2 0 -2	; "tp"
	9	[70]	SELF     	2 2 -5	; "check"
	10	[70]	LOADK    	4 -6	; "2.."
	11	[70]	CALL     	2 3 0
	12	[70]	TAILCALL 	1 0 0
	13	[70]	RETURN   	1 0
	14	[71]	RETURN   	0 1

function <./socket/smtp.lua:73,75> (5 instructions, 20 bytes at 0x7f8574c08c30)
1 param, 3 slots, 0 upvalues, 1 local, 2 constants, 0 functions
	1	[74]	GETTABLE 	1 0 -1	; "tp"
	2	[74]	SELF     	1 1 -2	; "close"
	3	[74]	TAILCALL 	1 2 0
	4	[74]	RETURN   	1 0
	5	[75]	RETURN   	0 1

function <./socket/smtp.lua:77,84> (49 instructions, 196 bytes at 0x7f8574c09010)
3 params, 8 slots, 1 upvalue, 3 locals, 11 constants, 0 functions
	1	[78]	GETTABLE 	3 0 -1	; "try"
	2	[78]	GETTABLE 	4 0 -2	; "tp"
	3	[78]	SELF     	4 4 -3	; "command"
	4	[78]	LOADK    	6 -4	; "AUTH"
	5	[78]	LOADK    	7 -5	; "LOGIN"
	6	[78]	CALL     	4 4 0
	7	[78]	CALL     	3 0 1
	8	[79]	GETTABLE 	3 0 -1	; "try"
	9	[79]	GETTABLE 	4 0 -2	; "tp"
	10	[79]	SELF     	4 4 -6	; "check"
	11	[79]	LOADK    	6 -7	; "3.."
	12	[79]	CALL     	4 3 0
	13	[79]	CALL     	3 0 1
	14	[80]	GETTABLE 	3 0 -1	; "try"
	15	[80]	GETTABLE 	4 0 -2	; "tp"
	16	[80]	SELF     	4 4 -8	; "send"
	17	[80]	GETUPVAL 	6 0	; mime
	18	[80]	GETTABLE 	6 6 -9	; "b64"
	19	[80]	MOVE     	7 1
	20	[80]	CALL     	6 2 2
	21	[80]	LOADK    	7 -10	; "\r\n"
	22	[80]	CONCAT   	6 6 7
	23	[80]	CALL     	4 3 0
	24	[80]	CALL     	3 0 1
	25	[81]	GETTABLE 	3 0 -1	; "try"
	26	[81]	GETTABLE 	4 0 -2	; "tp"
	27	[81]	SELF     	4 4 -6	; "check"
	28	[81]	LOADK    	6 -7	; "3.."
	29	[81]	CALL     	4 3 0
	30	[81]	CALL     	3 0 1
	31	[82]	GETTABLE 	3 0 -1	; "try"
	32	[82]	GETTABLE 	4 0 -2	; "tp"
	33	[82]	SELF     	4 4 -8	; "send"
	34	[82]	GETUPVAL 	6 0	; mime
	35	[82]	GETTABLE 	6 6 -9	; "b64"
	36	[82]	MOVE     	7 2
	37	[82]	CALL     	6 2 2
	38	[82]	LOADK    	7 -10	; "\r\n"
	39	[82]	CONCAT   	6 6 7
	40	[82]	CALL     	4 3 0
	41	[82]	CALL     	3 0 1
	42	[83]	GETTABLE 	3 0 -1	; "try"
	43	[83]	GETTABLE 	4 0 -2	; "tp"
	44	[83]	SELF     	4 4 -6	; "check"
	45	[83]	LOADK    	6 -11	; "2.."
	46	[83]	CALL     	4 3 0
	47	[83]	TAILCALL 	3 0 0
	48	[83]	RETURN   	3 0
	49	[84]	RETURN   	0 1

function <./socket/smtp.lua:86,90> (25 instructions, 100 bytes at 0x7f8574c06e50)
3 params, 9 slots, 1 upvalue, 4 locals, 9 constants, 0 functions
	1	[87]	LOADK    	3 -1	; "PLAIN "
	2	[87]	GETUPVAL 	4 0	; mime
	3	[87]	GETTABLE 	4 4 -2	; "b64"
	4	[87]	LOADK    	5 -3	; "\000"
	5	[87]	MOVE     	6 1
	6	[87]	LOADK    	7 -3	; "\000"
	7	[87]	MOVE     	8 2
	8	[87]	CONCAT   	5 5 8
	9	[87]	CALL     	4 2 2
	10	[87]	CONCAT   	3 3 4
	11	[88]	GETTABLE 	4 0 -4	; "try"
	12	[88]	GETTABLE 	5 0 -5	; "tp"
	13	[88]	SELF     	5 5 -6	; "command"
	14	[88]	LOADK    	7 -7	; "AUTH"
	15	[88]	MOVE     	8 3
	16	[88]	CALL     	5 4 0
	17	[88]	CALL     	4 0 1
	18	[89]	GETTABLE 	4 0 -4	; "try"
	19	[89]	GETTABLE 	5 0 -5	; "tp"
	20	[89]	SELF     	5 5 -8	; "check"
	21	[89]	LOADK    	7 -9	; "2.."
	22	[89]	CALL     	5 3 0
	23	[89]	TAILCALL 	4 0 0
	24	[89]	RETURN   	4 0
	25	[90]	RETURN   	0 1

function <./socket/smtp.lua:92,101> (37 instructions, 148 bytes at 0x7f8574c06ef0)
4 params, 8 slots, 1 upvalue, 4 locals, 8 constants, 0 functions
	1	[93]	TEST     	1 0 0
	2	[93]	JMP      	2	; to 5
	3	[93]	TEST     	2 0 1
	4	[93]	JMP      	2	; to 7
	5	[93]	LOADK    	4 -1	; 1
	6	[93]	RETURN   	4 2
	7	[94]	GETUPVAL 	4 0	; string
	8	[94]	GETTABLE 	4 4 -2	; "find"
	9	[94]	MOVE     	5 3
	10	[94]	LOADK    	6 -3	; "AUTH[^\n]+LOGIN"
	11	[94]	CALL     	4 3 2
	12	[94]	TEST     	4 0 0
	13	[94]	JMP      	6	; to 20
	14	[95]	SELF     	4 0 -4	; "login"
	15	[95]	MOVE     	6 1
	16	[95]	MOVE     	7 2
	17	[95]	TAILCALL 	4 4 0
	18	[95]	RETURN   	4 0
	19	[95]	JMP      	17	; to 37
	20	[96]	GETUPVAL 	4 0	; string
	21	[96]	GETTABLE 	4 4 -2	; "find"
	22	[96]	MOVE     	5 3
	23	[96]	LOADK    	6 -5	; "AUTH[^\n]+PLAIN"
	24	[96]	CALL     	4 3 2
	25	[96]	TEST     	4 0 0
	26	[96]	JMP      	6	; to 33
	27	[97]	SELF     	4 0 -6	; "plain"
	28	[97]	MOVE     	6 1
	29	[97]	MOVE     	7 2
	30	[97]	TAILCALL 	4 4 0
	31	[97]	RETURN   	4 0
	32	[97]	JMP      	4	; to 37
	33	[99]	GETTABLE 	4 0 -7	; "try"
	34	[99]	LOADNIL  	5 5
	35	[99]	LOADK    	6 -8	; "authentication not supported"
	36	[99]	CALL     	4 3 1
	37	[101]	RETURN   	0 1

function <./socket/smtp.lua:104,114> (35 instructions, 140 bytes at 0x7f8574c08f90)
2 params, 10 slots, 3 upvalues, 7 locals, 11 constants, 0 functions
	1	[105]	SELF     	2 0 -1	; "mail"
	2	[105]	GETTABLE 	4 1 -2	; "from"
	3	[105]	CALL     	2 3 1
	4	[106]	GETUPVAL 	2 0	; base
	5	[106]	GETTABLE 	2 2 -3	; "type"
	6	[106]	GETTABLE 	3 1 -4	; "rcpt"
	7	[106]	CALL     	2 2 2
	8	[106]	EQ       	0 2 -5	; - "table"
	9	[106]	JMP      	11	; to 21
	10	[107]	GETUPVAL 	2 0	; base
	11	[107]	GETTABLE 	2 2 -6	; "ipairs"
	12	[107]	GETTABLE 	3 1 -4	; "rcpt"
	13	[107]	CALL     	2 2 4
	14	[107]	JMP      	3	; to 18
	15	[108]	SELF     	7 0 -4	; "rcpt"
	16	[108]	MOVE     	9 6
	17	[108]	CALL     	7 3 1
	18	[107]	TFORLOOP 	2 2
	19	[108]	JMP      	-5	; to 15
	20	[109]	JMP      	3	; to 24
	21	[111]	SELF     	2 0 -4	; "rcpt"
	22	[111]	GETTABLE 	4 1 -4	; "rcpt"
	23	[111]	CALL     	2 3 1
	24	[113]	SELF     	2 0 -7	; "data"
	25	[113]	GETUPVAL 	4 1	; ltn12
	26	[113]	GETTABLE 	4 4 -8	; "source"
	27	[113]	GETTABLE 	4 4 -9	; "chain"
	28	[113]	GETTABLE 	5 1 -8	; "source"
	29	[113]	GETUPVAL 	6 2	; mime
	30	[113]	GETTABLE 	6 6 -10	; "stuff"
	31	[113]	CALL     	6 1 0
	32	[113]	CALL     	4 0 2
	33	[113]	GETTABLE 	5 1 -11	; "step"
	34	[113]	CALL     	2 4 1
	35	[114]	RETURN   	0 1

function <./socket/smtp.lua:116,125> (31 instructions, 124 bytes at 0x7f8574c09830)
3 params, 9 slots, 5 upvalues, 5 locals, 8 constants, 1 function
	1	[117]	GETUPVAL 	3 0	; socket
	2	[117]	GETTABLE 	3 3 -1	; "try"
	3	[117]	GETUPVAL 	4 1	; tp
	4	[117]	GETTABLE 	4 4 -2	; "connect"
	5	[117]	TESTSET  	5 0 1
	6	[117]	JMP      	2	; to 9
	7	[117]	GETUPVAL 	5 2	; _M
	8	[117]	GETTABLE 	5 5 -3	; "SERVER"
	9	[117]	TESTSET  	6 1 1
	10	[117]	JMP      	2	; to 13
	11	[117]	GETUPVAL 	6 2	; _M
	12	[117]	GETTABLE 	6 6 -4	; "PORT"
	13	[118]	GETUPVAL 	7 2	; _M
	14	[118]	GETTABLE 	7 7 -5	; "TIMEOUT"
	15	[118]	MOVE     	8 2
	16	[117]	CALL     	4 5 0
	17	[117]	CALL     	3 0 2
	18	[119]	GETUPVAL 	4 3	; base
	19	[119]	GETTABLE 	4 4 -6	; "setmetatable"
	20	[119]	NEWTABLE 	5 0 1
	21	[119]	SETTABLE 	5 -7 3	; "tp" -
	22	[119]	GETUPVAL 	6 4	; metat
	23	[119]	CALL     	4 3 2
	24	[121]	GETUPVAL 	5 0	; socket
	25	[121]	GETTABLE 	5 5 -8	; "newtry"
	26	[123]	CLOSURE  	6 0	; 0x7f8574c09b90
	27	[123]	MOVE     	0 4
	28	[121]	CALL     	5 2 2
	29	[123]	SETTABLE 	4 -1 5	; "try" -
	30	[124]	RETURN   	4 2
	31	[125]	RETURN   	0 1

function <./socket/smtp.lua:121,123> (4 instructions, 16 bytes at 0x7f8574c09b90)
0 params, 2 slots, 1 upvalue, 0 locals, 1 constant, 0 functions
	1	[122]	GETUPVAL 	0 0	; s
	2	[122]	SELF     	0 0 -1	; "close"
	3	[122]	CALL     	0 2 1
	4	[123]	RETURN   	0 1

function <./socket/smtp.lua:128,134> (17 instructions, 68 bytes at 0x7f8574c09d90)
1 param, 9 slots, 2 upvalues, 7 locals, 2 constants, 0 functions
	1	[129]	NEWTABLE 	1 0 0
	2	[130]	GETUPVAL 	2 0	; base
	3	[130]	GETTABLE 	2 2 -1	; "pairs"
	4	[130]	TESTSET  	3 0 1
	5	[130]	JMP      	1	; to 7
	6	[130]	MOVE     	3 1
	7	[130]	CALL     	2 2 4
	8	[130]	JMP      	5	; to 14
	9	[131]	GETUPVAL 	7 1	; string
	10	[131]	GETTABLE 	7 7 -2	; "lower"
	11	[131]	MOVE     	8 5
	12	[131]	CALL     	7 2 2
	13	[131]	SETTABLE 	1 7 6
	14	[130]	TFORLOOP 	2 2
	15	[131]	JMP      	-7	; to 9
	16	[133]	RETURN   	1 2
	17	[134]	RETURN   	0 1

function <./socket/smtp.lua:141,145> (19 instructions, 76 bytes at 0x7f8574c0a160)
0 params, 6 slots, 4 upvalues, 0 locals, 8 constants, 0 functions
	1	[142]	GETUPVAL 	0 0	; seqno
	2	[142]	ADD      	0 0 -1	; - 1
	3	[142]	SETUPVAL 	0 0	; seqno
	4	[143]	GETUPVAL 	0 1	; string
	5	[143]	GETTABLE 	0 0 -2	; "format"
	6	[143]	LOADK    	1 -3	; "%s%05d==%05u"
	7	[143]	GETUPVAL 	2 2	; os
	8	[143]	GETTABLE 	2 2 -4	; "date"
	9	[143]	LOADK    	3 -5	; "%d%m%Y%H%M%S"
	10	[143]	CALL     	2 2 2
	11	[144]	GETUPVAL 	3 3	; math
	12	[144]	GETTABLE 	3 3 -6	; "random"
	13	[144]	LOADK    	4 -7	; 0
	14	[144]	LOADK    	5 -8	; 99999
	15	[144]	CALL     	3 3 2
	16	[144]	GETUPVAL 	4 0	; seqno
	17	[143]	TAILCALL 	0 5 0
	18	[144]	RETURN   	0 0
	19	[145]	RETURN   	0 1

function <./socket/smtp.lua:151,158> (24 instructions, 96 bytes at 0x7f8574c0a400)
1 param, 13 slots, 3 upvalues, 8 locals, 5 constants, 0 functions
	1	[152]	GETUPVAL 	1 0	; headers
	2	[152]	GETTABLE 	1 1 -1	; "canonic"
	3	[153]	LOADK    	2 -2	; "\r\n"
	4	[154]	GETUPVAL 	3 1	; base
	5	[154]	GETTABLE 	3 3 -3	; "pairs"
	6	[154]	MOVE     	4 0
	7	[154]	CALL     	3 2 4
	8	[154]	JMP      	9	; to 18
	9	[155]	GETTABLE 	8 1 6
	10	[155]	TEST     	8 0 1
	11	[155]	JMP      	1	; to 13
	12	[155]	MOVE     	8 6
	13	[155]	LOADK    	9 -4	; ": "
	14	[155]	MOVE     	10 7
	15	[155]	LOADK    	11 -2	; "\r\n"
	16	[155]	MOVE     	12 2
	17	[155]	CONCAT   	2 8 12
	18	[154]	TFORLOOP 	3 2
	19	[155]	JMP      	-11	; to 9
	20	[157]	GETUPVAL 	3 2	; coroutine
	21	[157]	GETTABLE 	3 3 -5	; "yield"
	22	[157]	MOVE     	4 2
	23	[157]	CALL     	3 2 1
	24	[158]	RETURN   	0 1

function <./socket/smtp.lua:161,186> (73 instructions, 292 bytes at 0x7f8574c0ac00)
1 param, 12 slots, 6 upvalues, 8 locals, 13 constants, 0 functions
	1	[163]	GETUPVAL 	1 0	; newboundary
	2	[163]	CALL     	1 1 2
	3	[164]	GETUPVAL 	2 1	; lower_headers
	4	[164]	GETTABLE 	3 0 -1	; "headers"
	5	[164]	TEST     	3 0 1
	6	[164]	JMP      	1	; to 8
	7	[164]	NEWTABLE 	3 0 0
	8	[164]	CALL     	2 2 2
	9	[165]	GETTABLE 	3 2 -2	; "content-type"
	10	[165]	TEST     	3 0 1
	11	[165]	JMP      	1	; to 13
	12	[165]	LOADK    	3 -3	; "multipart/mixed"
	13	[165]	SETTABLE 	2 -2 3	; "content-type" -
	14	[166]	GETTABLE 	3 2 -2	; "content-type"
	15	[167]	LOADK    	4 -4	; "; boundary=\""
	16	[167]	MOVE     	5 1
	17	[167]	LOADK    	6 -5	; "\""
	18	[167]	CONCAT   	3 3 6
	19	[167]	SETTABLE 	2 -2 3	; "content-type" -
	20	[168]	GETUPVAL 	3 2	; send_headers
	21	[168]	MOVE     	4 2
	22	[168]	CALL     	3 2 1
	23	[170]	GETTABLE 	3 0 -6	; "body"
	24	[170]	GETTABLE 	3 3 -7	; "preamble"
	25	[170]	TEST     	3 0 0
	26	[170]	JMP      	9	; to 36
	27	[171]	GETUPVAL 	3 3	; coroutine
	28	[171]	GETTABLE 	3 3 -8	; "yield"
	29	[171]	GETTABLE 	4 0 -6	; "body"
	30	[171]	GETTABLE 	4 4 -7	; "preamble"
	31	[171]	CALL     	3 2 1
	32	[172]	GETUPVAL 	3 3	; coroutine
	33	[172]	GETTABLE 	3 3 -8	; "yield"
	34	[172]	LOADK    	4 -9	; "\r\n"
	35	[172]	CALL     	3 2 1
	36	[175]	GETUPVAL 	3 4	; base
	37	[175]	GETTABLE 	3 3 -10	; "ipairs"
	38	[175]	GETTABLE 	4 0 -6	; "body"
	39	[175]	CALL     	3 2 4
	40	[175]	JMP      	10	; to 51
	41	[176]	GETUPVAL 	8 3	; coroutine
	42	[176]	GETTABLE 	8 8 -8	; "yield"
	43	[176]	LOADK    	9 -11	; "\r\n--"
	44	[176]	MOVE     	10 1
	45	[176]	LOADK    	11 -9	; "\r\n"
	46	[176]	CONCAT   	9 9 11
	47	[176]	CALL     	8 2 1
	48	[177]	GETUPVAL 	8 5	; send_message
	49	[177]	MOVE     	9 7
	50	[177]	CALL     	8 2 1
	51	[175]	TFORLOOP 	3 2
	52	[177]	JMP      	-12	; to 41
	53	[180]	GETUPVAL 	3 3	; coroutine
	54	[180]	GETTABLE 	3 3 -8	; "yield"
	55	[180]	LOADK    	4 -11	; "\r\n--"
	56	[180]	MOVE     	5 1
	57	[180]	LOADK    	6 -12	; "--\r\n\r\n"
	58	[180]	CONCAT   	4 4 6
	59	[180]	CALL     	3 2 1
	60	[182]	GETTABLE 	3 0 -6	; "body"
	61	[182]	GETTABLE 	3 3 -13	; "epilogue"
	62	[182]	TEST     	3 0 0
	63	[182]	JMP      	9	; to 73
	64	[183]	GETUPVAL 	3 3	; coroutine
	65	[183]	GETTABLE 	3 3 -8	; "yield"
	66	[183]	GETTABLE 	4 0 -6	; "body"
	67	[183]	GETTABLE 	4 4 -13	; "epilogue"
	68	[183]	CALL     	3 2 1
	69	[184]	GETUPVAL 	3 3	; coroutine
	70	[184]	GETTABLE 	3 3 -8	; "yield"
	71	[184]	LOADK    	4 -9	; "\r\n"
	72	[184]	CALL     	3 2 1
	73	[186]	RETURN   	0 1

function <./socket/smtp.lua:189,202> (34 instructions, 136 bytes at 0x7f8574c0adf0)
1 param, 7 slots, 3 upvalues, 4 locals, 5 constants, 0 functions
	1	[191]	GETUPVAL 	1 0	; lower_headers
	2	[191]	GETTABLE 	2 0 -1	; "headers"
	3	[191]	TEST     	2 0 1
	4	[191]	JMP      	1	; to 6
	5	[191]	NEWTABLE 	2 0 0
	6	[191]	CALL     	1 2 2
	7	[192]	GETTABLE 	2 1 -2	; "content-type"
	8	[192]	TEST     	2 0 1
	9	[192]	JMP      	1	; to 11
	10	[193]	LOADK    	2 -3	; "text/plain; charset=\"iso-8859-1\""
	11	[193]	SETTABLE 	1 -2 2	; "content-type" -
	12	[194]	GETUPVAL 	2 1	; send_headers
	13	[194]	MOVE     	3 1
	14	[194]	CALL     	2 2 1
	15	[197]	GETTABLE 	2 0 -4	; "body"
	16	[197]	CALL     	2 1 3
	17	[198]	TEST     	3 0 0
	18	[198]	JMP      	6	; to 25
	19	[198]	GETUPVAL 	4 2	; coroutine
	20	[198]	GETTABLE 	4 4 -5	; "yield"
	21	[198]	LOADNIL  	5 5
	22	[198]	MOVE     	6 3
	23	[198]	CALL     	4 3 1
	24	[198]	JMP      	-10	; to 15
	25	[199]	TEST     	2 0 0
	26	[199]	JMP      	7	; to 34
	27	[199]	GETUPVAL 	4 2	; coroutine
	28	[199]	GETTABLE 	4 4 -5	; "yield"
	29	[199]	MOVE     	5 2
	30	[199]	CALL     	4 2 1
	31	[199]	JMP      	-17	; to 15
	32	[200]	JMP      	1	; to 34
	33	[200]	JMP      	-19	; to 15
	34	[202]	RETURN   	0 1

function <./socket/smtp.lua:205,213> (19 instructions, 76 bytes at 0x7f8574c09cf0)
1 param, 4 slots, 3 upvalues, 2 locals, 5 constants, 0 functions
	1	[207]	GETUPVAL 	1 0	; lower_headers
	2	[207]	GETTABLE 	2 0 -1	; "headers"
	3	[207]	TEST     	2 0 1
	4	[207]	JMP      	1	; to 6
	5	[207]	NEWTABLE 	2 0 0
	6	[207]	CALL     	1 2 2
	7	[208]	GETTABLE 	2 1 -2	; "content-type"
	8	[208]	TEST     	2 0 1
	9	[208]	JMP      	1	; to 11
	10	[209]	LOADK    	2 -3	; "text/plain; charset=\"iso-8859-1\""
	11	[209]	SETTABLE 	1 -2 2	; "content-type" -
	12	[210]	GETUPVAL 	2 1	; send_headers
	13	[210]	MOVE     	3 1
	14	[210]	CALL     	2 2 1
	15	[212]	GETUPVAL 	2 2	; coroutine
	16	[212]	GETTABLE 	2 2 -4	; "yield"
	17	[212]	GETTABLE 	3 0 -5	; "body"
	18	[212]	CALL     	2 2 1
	19	[213]	RETURN   	0 1

function <./socket/smtp.lua:216,220> (24 instructions, 96 bytes at 0x7f8574c08d90)
1 param, 3 slots, 4 upvalues, 1 local, 4 constants, 0 functions
	1	[217]	GETUPVAL 	1 0	; base
	2	[217]	GETTABLE 	1 1 -1	; "type"
	3	[217]	GETTABLE 	2 0 -2	; "body"
	4	[217]	CALL     	1 2 2
	5	[217]	EQ       	0 1 -3	; - "table"
	6	[217]	JMP      	4	; to 11
	7	[217]	GETUPVAL 	1 1	; send_multipart
	8	[217]	MOVE     	2 0
	9	[217]	CALL     	1 2 1
	10	[217]	JMP      	13	; to 24
	11	[218]	GETUPVAL 	1 0	; base
	12	[218]	GETTABLE 	1 1 -1	; "type"
	13	[218]	GETTABLE 	2 0 -2	; "body"
	14	[218]	CALL     	1 2 2
	15	[218]	EQ       	0 1 -4	; - "function"
	16	[218]	JMP      	4	; to 21
	17	[218]	GETUPVAL 	1 2	; send_source
	18	[218]	MOVE     	2 0
	19	[218]	CALL     	1 2 1
	20	[218]	JMP      	3	; to 24
	21	[219]	GETUPVAL 	1 3	; send_string
	22	[219]	MOVE     	2 0
	23	[219]	CALL     	1 2 1
	24	[220]	RETURN   	0 1

function <./socket/smtp.lua:223,231> (26 instructions, 104 bytes at 0x7f8574c0ba00)
1 param, 4 slots, 4 upvalues, 2 locals, 9 constants, 0 functions
	1	[224]	GETUPVAL 	1 0	; lower_headers
	2	[224]	GETTABLE 	2 0 -1	; "headers"
	3	[224]	CALL     	1 2 2
	4	[225]	GETTABLE 	2 1 -2	; "date"
	5	[225]	TEST     	2 0 1
	6	[225]	JMP      	10	; to 17
	7	[226]	GETUPVAL 	2 1	; os
	8	[226]	GETTABLE 	2 2 -2	; "date"
	9	[226]	LOADK    	3 -3	; "!%a, %d %b %Y %H:%M:%S "
	10	[226]	CALL     	2 2 2
	11	[226]	GETTABLE 	3 0 -4	; "zone"
	12	[226]	TEST     	3 0 1
	13	[226]	JMP      	2	; to 16
	14	[226]	GETUPVAL 	3 2	; _M
	15	[226]	GETTABLE 	3 3 -5	; "ZONE"
	16	[226]	CONCAT   	2 2 3
	17	[226]	SETTABLE 	1 -2 2	; "date" -
	18	[227]	GETTABLE 	2 1 -6	; "x-mailer"
	19	[227]	TEST     	2 0 1
	20	[227]	JMP      	2	; to 23
	21	[227]	GETUPVAL 	2 3	; socket
	22	[227]	GETTABLE 	2 2 -7	; "_VERSION"
	23	[227]	SETTABLE 	1 -6 2	; "x-mailer" -
	24	[229]	SETTABLE 	1 -8 -9	; "mime-version" "1.0"
	25	[230]	RETURN   	1 2
	26	[231]	RETURN   	0 1

function <./socket/smtp.lua:233,242> (15 instructions, 60 bytes at 0x7f8574c0c080)
1 param, 3 slots, 3 upvalues, 2 locals, 2 constants, 2 functions
	1	[234]	GETUPVAL 	1 0	; adjust_headers
	2	[234]	MOVE     	2 0
	3	[234]	CALL     	1 2 2
	4	[234]	SETTABLE 	0 -1 1	; "headers" -
	5	[236]	GETUPVAL 	1 1	; coroutine
	6	[236]	GETTABLE 	1 1 -2	; "create"
	7	[236]	CLOSURE  	2 0	; 0x7f8574c0c380
	8	[236]	GETUPVAL 	0 2	; send_message
	9	[236]	MOVE     	0 0
	10	[236]	CALL     	1 2 2
	11	[241]	CLOSURE  	2 1	; 0x7f8574c09230
	12	[241]	GETUPVAL 	0 1	; coroutine
	13	[241]	MOVE     	0 1
	14	[241]	RETURN   	2 2
	15	[242]	RETURN   	0 1

function <./socket/smtp.lua:236,236> (4 instructions, 16 bytes at 0x7f8574c0c380)
0 params, 2 slots, 2 upvalues, 0 locals, 0 constants, 0 functions
	1	[236]	GETUPVAL 	0 0	; send_message
	2	[236]	GETUPVAL 	1 1	; mesgt
	3	[236]	CALL     	0 2 1
	4	[236]	RETURN   	0 1

function <./socket/smtp.lua:237,241> (14 instructions, 56 bytes at 0x7f8574c09230)
0 params, 5 slots, 2 upvalues, 3 locals, 1 constant, 0 functions
	1	[238]	GETUPVAL 	0 0	; coroutine
	2	[238]	GETTABLE 	0 0 -1	; "resume"
	3	[238]	GETUPVAL 	1 1	; co
	4	[238]	CALL     	0 2 4
	5	[239]	TEST     	0 0 0
	6	[239]	JMP      	4	; to 11
	7	[239]	MOVE     	3 1
	8	[239]	MOVE     	4 2
	9	[239]	RETURN   	3 3
	10	[239]	JMP      	3	; to 14
	11	[240]	LOADNIL  	3 3
	12	[240]	MOVE     	4 1
	13	[240]	RETURN   	3 3
	14	[241]	RETURN   	0 1

function <./socket/smtp.lua:247,254> (23 instructions, 92 bytes at 0x7f8574c0c760)
1 param, 8 slots, 1 upvalue, 3 locals, 12 constants, 0 functions
	1	[248]	GETUPVAL 	1 0	; _M
	2	[248]	GETTABLE 	1 1 -1	; "open"
	3	[248]	GETTABLE 	2 0 -2	; "server"
	4	[248]	GETTABLE 	3 0 -3	; "port"
	5	[248]	GETTABLE 	4 0 -4	; "create"
	6	[248]	CALL     	1 4 2
	7	[249]	SELF     	2 1 -5	; "greet"
	8	[249]	GETTABLE 	4 0 -6	; "domain"
	9	[249]	CALL     	2 3 2
	10	[250]	SELF     	3 1 -7	; "auth"
	11	[250]	GETTABLE 	5 0 -8	; "user"
	12	[250]	GETTABLE 	6 0 -9	; "password"
	13	[250]	MOVE     	7 2
	14	[250]	CALL     	3 5 1
	15	[251]	SELF     	3 1 -10	; "send"
	16	[251]	MOVE     	5 0
	17	[251]	CALL     	3 3 1
	18	[252]	SELF     	3 1 -11	; "quit"
	19	[252]	CALL     	3 2 1
	20	[253]	SELF     	3 1 -12	; "close"
	21	[253]	TAILCALL 	3 2 0
	22	[253]	RETURN   	3 0
	23	[254]	RETURN   	0 1
