
main <./socket/ftp.lua:0,0> (145 instructions, 580 bytes at 0x7fd604c068a0)
0+ params, 19 slots, 0 upvalues, 17 locals, 38 constants, 22 functions
	1	[10]	GETGLOBAL	0 -1	; _G
	2	[11]	GETGLOBAL	1 -2	; require
	3	[11]	LOADK    	2 -3	; "table"
	4	[11]	CALL     	1 2 2
	5	[12]	GETGLOBAL	2 -2	; require
	6	[12]	LOADK    	3 -4	; "string"
	7	[12]	CALL     	2 2 2
	8	[13]	GETGLOBAL	3 -2	; require
	9	[13]	LOADK    	4 -5	; "math"
	10	[13]	CALL     	3 2 2
	11	[14]	GETGLOBAL	4 -2	; require
	12	[14]	LOADK    	5 -6	; "socket"
	13	[14]	CALL     	4 2 2
	14	[15]	GETGLOBAL	5 -2	; require
	15	[15]	LOADK    	6 -7	; "socket.url"
	16	[15]	CALL     	5 2 2
	17	[16]	GETGLOBAL	6 -2	; require
	18	[16]	LOADK    	7 -8	; "socket.tp"
	19	[16]	CALL     	6 2 2
	20	[17]	GETGLOBAL	7 -2	; require
	21	[17]	LOADK    	8 -9	; "ltn12"
	22	[17]	CALL     	7 2 2
	23	[18]	NEWTABLE 	8 0 0
	24	[18]	SETTABLE 	4 -10 8	; "ftp" -
	25	[19]	GETTABLE 	8 4 -10	; "ftp"
	26	[24]	SETTABLE 	8 -11 -12	; "TIMEOUT" 60
	27	[26]	SETTABLE 	8 -13 -14	; "PORT" 21
	28	[29]	SETTABLE 	8 -15 -10	; "USER" "ftp"
	29	[30]	SETTABLE 	8 -16 -17	; "PASSWORD" "anonymous@anonymous.org"
	30	[35]	NEWTABLE 	9 0 1
	31	[35]	NEWTABLE 	10 0 0
	32	[35]	SETTABLE 	9 -18 10	; "__index" -
	33	[43]	CLOSURE  	10 0	; 0x7fd604c06d00
	34	[43]	MOVE     	0 4
	35	[43]	MOVE     	0 6
	36	[43]	MOVE     	0 8
	37	[43]	MOVE     	0 0
	38	[43]	MOVE     	0 9
	39	[37]	SETTABLE 	8 -19 10	; "open" -
	40	[45]	GETTABLE 	10 9 -18	; "__index"
	41	[49]	CLOSURE  	11 1	; 0x7fd604c07000
	42	[49]	MOVE     	0 8
	43	[45]	SETTABLE 	10 -20 11	; "portconnect" -
	44	[51]	GETTABLE 	10 9 -18	; "__index"
	45	[55]	CLOSURE  	11 2	; 0x7fd604c07840
	46	[55]	MOVE     	0 4
	47	[55]	MOVE     	0 8
	48	[51]	SETTABLE 	10 -21 11	; "pasvconnect" -
	49	[57]	GETTABLE 	10 9 -18	; "__index"
	50	[65]	CLOSURE  	11 3	; 0x7fd604c07f60
	51	[65]	MOVE     	0 8
	52	[57]	SETTABLE 	10 -22 11	; "login" -
	53	[67]	GETTABLE 	10 9 -18	; "__index"
	54	[82]	CLOSURE  	11 4	; 0x7fd604c08800
	55	[82]	MOVE     	0 4
	56	[82]	MOVE     	0 2
	57	[67]	SETTABLE 	10 -23 11	; "pasv" -
	58	[84]	GETTABLE 	10 9 -18	; "__index"
	59	[98]	CLOSURE  	11 5	; 0x7fd604c089d0
	60	[98]	MOVE     	0 4
	61	[98]	MOVE     	0 8
	62	[98]	MOVE     	0 3
	63	[98]	MOVE     	0 2
	64	[84]	SETTABLE 	10 -24 11	; "port" -
	65	[100]	GETTABLE 	10 9 -18	; "__index"
	66	[135]	CLOSURE  	11 6	; 0x7fd604c08fd0
	67	[135]	MOVE     	0 5
	68	[135]	MOVE     	0 2
	69	[135]	MOVE     	0 7
	70	[135]	MOVE     	0 4
	71	[135]	MOVE     	0 6
	72	[100]	SETTABLE 	10 -25 11	; "send" -
	73	[137]	GETTABLE 	10 9 -18	; "__index"
	74	[158]	CLOSURE  	11 7	; 0x7fd604c0a1d0
	75	[158]	MOVE     	0 5
	76	[158]	MOVE     	0 2
	77	[158]	MOVE     	0 4
	78	[158]	MOVE     	0 7
	79	[137]	SETTABLE 	10 -26 11	; "receive" -
	80	[160]	GETTABLE 	10 9 -18	; "__index"
	81	[164]	CLOSURE  	11 8	; 0x7fd604c0a480
	82	[160]	SETTABLE 	10 -27 11	; "cwd" -
	83	[166]	GETTABLE 	10 9 -18	; "__index"
	84	[170]	CLOSURE  	11 9	; 0x7fd604c0acc0
	85	[166]	SETTABLE 	10 -28 11	; "type" -
	86	[172]	GETTABLE 	10 9 -18	; "__index"
	87	[176]	CLOSURE  	11 10	; 0x7fd604c0b080
	88	[176]	MOVE     	0 2
	89	[172]	SETTABLE 	10 -29 11	; "greet" -
	90	[178]	GETTABLE 	10 9 -18	; "__index"
	91	[182]	CLOSURE  	11 11	; 0x7fd604c0b620
	92	[178]	SETTABLE 	10 -30 11	; "quit" -
	93	[184]	GETTABLE 	10 9 -18	; "__index"
	94	[188]	CLOSURE  	11 12	; 0x7fd604c0b9d0
	95	[184]	SETTABLE 	10 -31 11	; "close" -
	96	[201]	CLOSURE  	10 13	; 0x7fd604c0be30
	97	[201]	MOVE     	0 5
	98	[201]	MOVE     	0 0
	99	[215]	CLOSURE  	11 14	; 0x7fd604d04120
	100	[215]	MOVE     	0 10
	101	[215]	MOVE     	0 4
	102	[215]	MOVE     	0 8
	103	[217]	NEWTABLE 	12 0 2
	104	[218]	SETTABLE 	12 -32 -33	; "path" "/"
	105	[219]	SETTABLE 	12 -34 -10	; "scheme" "ftp"
	106	[233]	CLOSURE  	13 15	; 0x7fd604d04550
	107	[233]	MOVE     	0 4
	108	[233]	MOVE     	0 5
	109	[233]	MOVE     	0 12
	110	[233]	MOVE     	0 2
	111	[239]	CLOSURE  	14 16	; 0x7fd604d04990
	112	[239]	MOVE     	0 13
	113	[239]	MOVE     	0 7
	114	[239]	MOVE     	0 11
	115	[241]	GETTABLE 	15 4 -36	; "protect"
	116	[244]	CLOSURE  	16 17	; 0x7fd604d05010
	117	[244]	MOVE     	0 0
	118	[244]	MOVE     	0 14
	119	[244]	MOVE     	0 11
	120	[241]	CALL     	15 2 2
	121	[244]	SETTABLE 	8 -35 15	; "put" -
	122	[257]	CLOSURE  	15 18	; 0x7fd604d05860
	123	[257]	MOVE     	0 10
	124	[257]	MOVE     	0 4
	125	[257]	MOVE     	0 8
	126	[265]	CLOSURE  	16 19	; 0x7fd604d05a20
	127	[265]	MOVE     	0 13
	128	[265]	MOVE     	0 7
	129	[265]	MOVE     	0 15
	130	[265]	MOVE     	0 1
	131	[267]	GETTABLE 	17 4 -36	; "protect"
	132	[278]	CLOSURE  	18 20	; 0x7fd604d058e0
	133	[278]	MOVE     	0 10
	134	[278]	MOVE     	0 4
	135	[267]	CALL     	17 2 2
	136	[278]	SETTABLE 	8 -37 17	; "command" -
	137	[280]	GETTABLE 	17 4 -36	; "protect"
	138	[283]	CLOSURE  	18 21	; 0x7fd604d064c0
	139	[283]	MOVE     	0 0
	140	[283]	MOVE     	0 16
	141	[283]	MOVE     	0 15
	142	[280]	CALL     	17 2 2
	143	[283]	SETTABLE 	8 -38 17	; "get" -
	144	[285]	RETURN   	8 2
	145	[285]	RETURN   	0 1

function <./socket/ftp.lua:37,43> (28 instructions, 112 bytes at 0x7fd604c06d00)
3 params, 9 slots, 5 upvalues, 5 locals, 7 constants, 1 function
	1	[38]	GETUPVAL 	3 0	; socket
	2	[38]	GETTABLE 	3 3 -1	; "try"
	3	[38]	GETUPVAL 	4 1	; tp
	4	[38]	GETTABLE 	4 4 -2	; "connect"
	5	[38]	MOVE     	5 0
	6	[38]	TESTSET  	6 1 1
	7	[38]	JMP      	2	; to 10
	8	[38]	GETUPVAL 	6 2	; _M
	9	[38]	GETTABLE 	6 6 -3	; "PORT"
	10	[38]	GETUPVAL 	7 2	; _M
	11	[38]	GETTABLE 	7 7 -4	; "TIMEOUT"
	12	[38]	MOVE     	8 2
	13	[38]	CALL     	4 5 0
	14	[38]	CALL     	3 0 2
	15	[39]	GETUPVAL 	4 3	; base
	16	[39]	GETTABLE 	4 4 -5	; "setmetatable"
	17	[39]	NEWTABLE 	5 0 1
	18	[39]	SETTABLE 	5 -6 3	; "tp" -
	19	[39]	GETUPVAL 	6 4	; metat
	20	[39]	CALL     	4 3 2
	21	[41]	GETUPVAL 	5 0	; socket
	22	[41]	GETTABLE 	5 5 -7	; "newtry"
	23	[41]	CLOSURE  	6 0	; 0x7fd604c07280
	24	[41]	MOVE     	0 4
	25	[41]	CALL     	5 2 2
	26	[41]	SETTABLE 	4 -1 5	; "try" -
	27	[42]	RETURN   	4 2
	28	[43]	RETURN   	0 1

function <./socket/ftp.lua:41,41> (4 instructions, 16 bytes at 0x7fd604c07280)
0 params, 2 slots, 1 upvalue, 0 locals, 1 constant, 0 functions
	1	[41]	GETUPVAL 	0 0	; f
	2	[41]	SELF     	0 0 -1	; "close"
	3	[41]	CALL     	0 2 1
	4	[41]	RETURN   	0 1

function <./socket/ftp.lua:45,49> (21 instructions, 84 bytes at 0x7fd604c07000)
1 param, 5 slots, 1 upvalue, 1 local, 6 constants, 0 functions
	1	[46]	GETTABLE 	1 0 -1	; "try"
	2	[46]	GETTABLE 	2 0 -2	; "server"
	3	[46]	SELF     	2 2 -3	; "settimeout"
	4	[46]	GETUPVAL 	4 0	; _M
	5	[46]	GETTABLE 	4 4 -4	; "TIMEOUT"
	6	[46]	CALL     	2 3 0
	7	[46]	CALL     	1 0 1
	8	[47]	GETTABLE 	1 0 -1	; "try"
	9	[47]	GETTABLE 	2 0 -2	; "server"
	10	[47]	SELF     	2 2 -6	; "accept"
	11	[47]	CALL     	2 2 0
	12	[47]	CALL     	1 0 2
	13	[47]	SETTABLE 	0 -5 1	; "data" -
	14	[48]	GETTABLE 	1 0 -1	; "try"
	15	[48]	GETTABLE 	2 0 -5	; "data"
	16	[48]	SELF     	2 2 -3	; "settimeout"
	17	[48]	GETUPVAL 	4 0	; _M
	18	[48]	GETTABLE 	4 4 -4	; "TIMEOUT"
	19	[48]	CALL     	2 3 0
	20	[48]	CALL     	1 0 1
	21	[49]	RETURN   	0 1

function <./socket/ftp.lua:51,55> (23 instructions, 92 bytes at 0x7fd604c07840)
1 param, 6 slots, 2 upvalues, 1 local, 9 constants, 0 functions
	1	[52]	GETTABLE 	1 0 -2	; "try"
	2	[52]	GETUPVAL 	2 0	; socket
	3	[52]	GETTABLE 	2 2 -3	; "tcp"
	4	[52]	CALL     	2 1 0
	5	[52]	CALL     	1 0 2
	6	[52]	SETTABLE 	0 -1 1	; "data" -
	7	[53]	GETTABLE 	1 0 -2	; "try"
	8	[53]	GETTABLE 	2 0 -1	; "data"
	9	[53]	SELF     	2 2 -4	; "settimeout"
	10	[53]	GETUPVAL 	4 1	; _M
	11	[53]	GETTABLE 	4 4 -5	; "TIMEOUT"
	12	[53]	CALL     	2 3 0
	13	[53]	CALL     	1 0 1
	14	[54]	GETTABLE 	1 0 -2	; "try"
	15	[54]	GETTABLE 	2 0 -1	; "data"
	16	[54]	SELF     	2 2 -6	; "connect"
	17	[54]	GETTABLE 	4 0 -7	; "pasvt"
	18	[54]	GETTABLE 	4 4 -8	; "ip"
	19	[54]	GETTABLE 	5 0 -7	; "pasvt"
	20	[54]	GETTABLE 	5 5 -9	; "port"
	21	[54]	CALL     	2 4 0
	22	[54]	CALL     	1 0 1
	23	[55]	RETURN   	0 1

function <./socket/ftp.lua:57,65> (40 instructions, 160 bytes at 0x7fd604c07f60)
3 params, 10 slots, 1 upvalue, 5 locals, 11 constants, 0 functions
	1	[58]	GETTABLE 	3 0 -1	; "try"
	2	[58]	GETTABLE 	4 0 -2	; "tp"
	3	[58]	SELF     	4 4 -3	; "command"
	4	[58]	LOADK    	6 -4	; "user"
	5	[58]	TESTSET  	7 1 1
	6	[58]	JMP      	2	; to 9
	7	[58]	GETUPVAL 	7 0	; _M
	8	[58]	GETTABLE 	7 7 -5	; "USER"
	9	[58]	CALL     	4 4 0
	10	[58]	CALL     	3 0 1
	11	[59]	GETTABLE 	3 0 -1	; "try"
	12	[59]	GETTABLE 	4 0 -2	; "tp"
	13	[59]	SELF     	4 4 -6	; "check"
	14	[59]	NEWTABLE 	6 2 0
	15	[59]	LOADK    	7 -7	; "2.."
	16	[59]	LOADK    	8 -8	; 331
	17	[59]	SETLIST  	6 2 1	; 1
	18	[59]	CALL     	4 3 0
	19	[59]	CALL     	3 0 3
	20	[60]	EQ       	0 3 -8	; - 331
	21	[60]	JMP      	16	; to 38
	22	[61]	GETTABLE 	5 0 -1	; "try"
	23	[61]	GETTABLE 	6 0 -2	; "tp"
	24	[61]	SELF     	6 6 -3	; "command"
	25	[61]	LOADK    	8 -9	; "pass"
	26	[61]	TESTSET  	9 2 1
	27	[61]	JMP      	2	; to 30
	28	[61]	GETUPVAL 	9 0	; _M
	29	[61]	GETTABLE 	9 9 -10	; "PASSWORD"
	30	[61]	CALL     	6 4 0
	31	[61]	CALL     	5 0 1
	32	[62]	GETTABLE 	5 0 -1	; "try"
	33	[62]	GETTABLE 	6 0 -2	; "tp"
	34	[62]	SELF     	6 6 -6	; "check"
	35	[62]	LOADK    	8 -7	; "2.."
	36	[62]	CALL     	6 3 0
	37	[62]	CALL     	5 0 1
	38	[64]	LOADK    	5 -11	; 1
	39	[64]	RETURN   	5 2
	40	[65]	RETURN   	0 1

function <./socket/ftp.lua:67,82> (63 instructions, 252 bytes at 0x7fd604c08800)
1 param, 17 slots, 2 upvalues, 10 locals, 19 constants, 0 functions
	1	[68]	GETTABLE 	1 0 -1	; "try"
	2	[68]	GETTABLE 	2 0 -2	; "tp"
	3	[68]	SELF     	2 2 -3	; "command"
	4	[68]	LOADK    	4 -4	; "pasv"
	5	[68]	CALL     	2 3 0
	6	[68]	CALL     	1 0 1
	7	[69]	GETTABLE 	1 0 -1	; "try"
	8	[69]	GETTABLE 	2 0 -2	; "tp"
	9	[69]	SELF     	2 2 -5	; "check"
	10	[69]	LOADK    	4 -6	; "2.."
	11	[69]	CALL     	2 3 0
	12	[69]	CALL     	1 0 3
	13	[70]	LOADK    	3 -7	; "(%d+)%D(%d+)%D(%d+)%D(%d+)%D(%d+)%D(%d+)"
	14	[71]	GETUPVAL 	4 0	; socket
	15	[71]	GETTABLE 	4 4 -8	; "skip"
	16	[71]	LOADK    	5 -9	; 2
	17	[71]	GETUPVAL 	6 1	; string
	18	[71]	GETTABLE 	6 6 -10	; "find"
	19	[71]	MOVE     	7 2
	20	[71]	MOVE     	8 3
	21	[71]	CALL     	6 3 0
	22	[71]	CALL     	4 0 7
	23	[72]	GETTABLE 	10 0 -1	; "try"
	24	[72]	TESTSET  	11 4 0
	25	[72]	JMP      	9	; to 35
	26	[72]	TESTSET  	11 5 0
	27	[72]	JMP      	7	; to 35
	28	[72]	TESTSET  	11 6 0
	29	[72]	JMP      	5	; to 35
	30	[72]	TESTSET  	11 7 0
	31	[72]	JMP      	3	; to 35
	32	[72]	TESTSET  	11 8 0
	33	[72]	JMP      	1	; to 35
	34	[72]	MOVE     	11 9
	35	[72]	MOVE     	12 2
	36	[72]	CALL     	10 3 1
	37	[73]	NEWTABLE 	10 0 2
	38	[74]	GETUPVAL 	11 1	; string
	39	[74]	GETTABLE 	11 11 -13	; "format"
	40	[74]	LOADK    	12 -14	; "%d.%d.%d.%d"
	41	[74]	MOVE     	13 4
	42	[74]	MOVE     	14 5
	43	[74]	MOVE     	15 6
	44	[74]	MOVE     	16 7
	45	[74]	CALL     	11 6 2
	46	[74]	SETTABLE 	10 -12 11	; "ip" -
	47	[75]	MUL      	11 8 -16	; - 256
	48	[75]	ADD      	11 11 9
	49	[75]	SETTABLE 	10 -15 11	; "port" -
	50	[76]	SETTABLE 	0 -11 10	; "pasvt" -
	51	[77]	GETTABLE 	10 0 -17	; "server"
	52	[77]	TEST     	10 0 0
	53	[77]	JMP      	4	; to 58
	54	[78]	GETTABLE 	10 0 -17	; "server"
	55	[78]	SELF     	10 10 -18	; "close"
	56	[78]	CALL     	10 2 1
	57	[79]	SETTABLE 	0 -17 -19	; "server" nil
	58	[81]	GETTABLE 	10 0 -11	; "pasvt"
	59	[81]	GETTABLE 	10 10 -12	; "ip"
	60	[81]	GETTABLE 	11 0 -11	; "pasvt"
	61	[81]	GETTABLE 	11 11 -15	; "port"
	62	[81]	RETURN   	10 3
	63	[82]	RETURN   	0 1

function <./socket/ftp.lua:84,98> (69 instructions, 276 bytes at 0x7fd604c089d0)
3 params, 11 slots, 4 upvalues, 6 locals, 23 constants, 0 functions
	1	[85]	SETTABLE 	0 -1 -2	; "pasvt" nil
	2	[86]	TEST     	1 0 1
	3	[86]	JMP      	31	; to 35
	4	[87]	GETTABLE 	3 0 -3	; "try"
	5	[87]	GETTABLE 	4 0 -4	; "tp"
	6	[87]	SELF     	4 4 -5	; "getcontrol"
	7	[87]	CALL     	4 2 2
	8	[87]	SELF     	4 4 -6	; "getsockname"
	9	[87]	CALL     	4 2 0
	10	[87]	CALL     	3 0 3
	11	[87]	MOVE     	2 4
	12	[87]	MOVE     	1 3
	13	[88]	GETTABLE 	3 0 -3	; "try"
	14	[88]	GETUPVAL 	4 0	; socket
	15	[88]	GETTABLE 	4 4 -8	; "bind"
	16	[88]	MOVE     	5 1
	17	[88]	LOADK    	6 -9	; 0
	18	[88]	CALL     	4 3 0
	19	[88]	CALL     	3 0 2
	20	[88]	SETTABLE 	0 -7 3	; "server" -
	21	[89]	GETTABLE 	3 0 -3	; "try"
	22	[89]	GETTABLE 	4 0 -7	; "server"
	23	[89]	SELF     	4 4 -6	; "getsockname"
	24	[89]	CALL     	4 2 0
	25	[89]	CALL     	3 0 3
	26	[89]	MOVE     	2 4
	27	[89]	MOVE     	1 3
	28	[90]	GETTABLE 	3 0 -3	; "try"
	29	[90]	GETTABLE 	4 0 -7	; "server"
	30	[90]	SELF     	4 4 -10	; "settimeout"
	31	[90]	GETUPVAL 	6 1	; _M
	32	[90]	GETTABLE 	6 6 -11	; "TIMEOUT"
	33	[90]	CALL     	4 3 0
	34	[90]	CALL     	3 0 1
	35	[92]	GETUPVAL 	3 2	; math
	36	[92]	GETTABLE 	3 3 -12	; "mod"
	37	[92]	MOVE     	4 2
	38	[92]	LOADK    	5 -13	; 256
	39	[92]	CALL     	3 3 2
	40	[93]	SUB      	4 2 3
	41	[93]	DIV      	4 4 -13	; - 256
	42	[94]	GETUPVAL 	5 3	; string
	43	[94]	GETTABLE 	5 5 -14	; "gsub"
	44	[94]	GETUPVAL 	6 3	; string
	45	[94]	GETTABLE 	6 6 -15	; "format"
	46	[94]	LOADK    	7 -16	; "%s,%d,%d"
	47	[94]	MOVE     	8 1
	48	[94]	MOVE     	9 4
	49	[94]	MOVE     	10 3
	50	[94]	CALL     	6 5 2
	51	[94]	LOADK    	7 -17	; "%."
	52	[94]	LOADK    	8 -18	; ","
	53	[94]	CALL     	5 4 2
	54	[95]	GETTABLE 	6 0 -3	; "try"
	55	[95]	GETTABLE 	7 0 -4	; "tp"
	56	[95]	SELF     	7 7 -19	; "command"
	57	[95]	LOADK    	9 -20	; "port"
	58	[95]	MOVE     	10 5
	59	[95]	CALL     	7 4 0
	60	[95]	CALL     	6 0 1
	61	[96]	GETTABLE 	6 0 -3	; "try"
	62	[96]	GETTABLE 	7 0 -4	; "tp"
	63	[96]	SELF     	7 7 -21	; "check"
	64	[96]	LOADK    	9 -22	; "2.."
	65	[96]	CALL     	7 3 0
	66	[96]	CALL     	6 0 1
	67	[97]	LOADK    	6 -23	; 1
	68	[97]	RETURN   	6 2
	69	[98]	RETURN   	0 1

function <./socket/ftp.lua:100,135> (112 instructions, 448 bytes at 0x7fd604c08fd0)
2 params, 15 slots, 5 upvalues, 11 locals, 32 constants, 1 function
	1	[101]	GETTABLE 	2 0 -1	; "try"
	2	[101]	GETTABLE 	3 0 -2	; "pasvt"
	3	[101]	TEST     	3 0 1
	4	[101]	JMP      	1	; to 6
	5	[101]	GETTABLE 	3 0 -3	; "server"
	6	[101]	LOADK    	4 -4	; "need port or pasv first"
	7	[101]	CALL     	2 3 1
	8	[104]	GETTABLE 	2 0 -2	; "pasvt"
	9	[104]	TEST     	2 0 0
	10	[104]	JMP      	2	; to 13
	11	[104]	SELF     	2 0 -5	; "pasvconnect"
	12	[104]	CALL     	2 2 1
	13	[106]	GETTABLE 	2 1 -6	; "argument"
	14	[106]	TEST     	2 0 1
	15	[106]	JMP      	12	; to 28
	16	[107]	GETUPVAL 	2 0	; url
	17	[107]	GETTABLE 	2 2 -7	; "unescape"
	18	[107]	GETUPVAL 	3 1	; string
	19	[107]	GETTABLE 	3 3 -8	; "gsub"
	20	[107]	GETTABLE 	4 1 -9	; "path"
	21	[107]	TEST     	4 0 1
	22	[107]	JMP      	1	; to 24
	23	[107]	LOADK    	4 -10	; ""
	24	[107]	LOADK    	5 -11	; "^[/\\]"
	25	[107]	LOADK    	6 -10	; ""
	26	[107]	CALL     	3 4 0
	27	[107]	CALL     	2 0 2
	28	[108]	EQ       	0 2 -10	; - ""
	29	[108]	JMP      	1	; to 31
	30	[108]	LOADNIL  	2 2
	31	[109]	GETTABLE 	3 1 -12	; "command"
	32	[109]	TEST     	3 0 1
	33	[109]	JMP      	1	; to 35
	34	[109]	LOADK    	3 -13	; "stor"
	35	[111]	GETTABLE 	4 0 -1	; "try"
	36	[111]	GETTABLE 	5 0 -14	; "tp"
	37	[111]	SELF     	5 5 -12	; "command"
	38	[111]	MOVE     	7 3
	39	[111]	MOVE     	8 2
	40	[111]	CALL     	5 4 0
	41	[111]	CALL     	4 0 1
	42	[112]	GETTABLE 	4 0 -1	; "try"
	43	[112]	GETTABLE 	5 0 -14	; "tp"
	44	[112]	SELF     	5 5 -15	; "check"
	45	[112]	NEWTABLE 	7 2 0
	46	[112]	LOADK    	8 -16	; "2.."
	47	[112]	LOADK    	9 -17	; "1.."
	48	[112]	SETLIST  	7 2 1	; 1
	49	[112]	CALL     	5 3 0
	50	[112]	CALL     	4 0 3
	51	[115]	GETTABLE 	6 0 -2	; "pasvt"
	52	[115]	TEST     	6 0 1
	53	[115]	JMP      	2	; to 56
	54	[115]	SELF     	6 0 -18	; "portconnect"
	55	[115]	CALL     	6 2 1
	56	[117]	GETTABLE 	6 1 -19	; "step"
	57	[117]	TEST     	6 0 1
	58	[117]	JMP      	3	; to 62
	59	[117]	GETUPVAL 	6 2	; ltn12
	60	[117]	GETTABLE 	6 6 -20	; "pump"
	61	[117]	GETTABLE 	6 6 -19	; "step"
	62	[118]	NEWTABLE 	7 1 0
	63	[118]	GETTABLE 	8 0 -14	; "tp"
	64	[118]	GETTABLE 	8 8 -21	; "c"
	65	[118]	SETLIST  	7 1 1	; 1
	66	[124]	CLOSURE  	8 0	; 0x7fd604c07720
	67	[124]	GETUPVAL 	0 3	; socket
	68	[124]	MOVE     	0 7
	69	[124]	GETUPVAL 	0 4	; tp
	70	[124]	MOVE     	0 4
	71	[124]	MOVE     	0 0
	72	[124]	MOVE     	0 6
	73	[125]	GETUPVAL 	9 3	; socket
	74	[125]	GETTABLE 	9 9 -22	; "sink"
	75	[125]	LOADK    	10 -23	; "close-when-done"
	76	[125]	GETTABLE 	11 0 -24	; "data"
	77	[125]	CALL     	9 3 2
	78	[127]	GETTABLE 	10 0 -1	; "try"
	79	[127]	GETUPVAL 	11 2	; ltn12
	80	[127]	GETTABLE 	11 11 -20	; "pump"
	81	[127]	GETTABLE 	11 11 -25	; "all"
	82	[127]	GETTABLE 	12 1 -26	; "source"
	83	[127]	MOVE     	13 9
	84	[127]	MOVE     	14 8
	85	[127]	CALL     	11 4 0
	86	[127]	CALL     	10 0 1
	87	[128]	GETUPVAL 	10 1	; string
	88	[128]	GETTABLE 	10 10 -27	; "find"
	89	[128]	MOVE     	11 4
	90	[128]	LOADK    	12 -17	; "1.."
	91	[128]	CALL     	10 3 2
	92	[128]	TEST     	10 0 0
	93	[128]	JMP      	6	; to 100
	94	[128]	GETTABLE 	10 0 -1	; "try"
	95	[128]	GETTABLE 	11 0 -14	; "tp"
	96	[128]	SELF     	11 11 -15	; "check"
	97	[128]	LOADK    	13 -16	; "2.."
	98	[128]	CALL     	11 3 0
	99	[128]	CALL     	10 0 1
	100	[130]	GETTABLE 	10 0 -24	; "data"
	101	[130]	SELF     	10 10 -28	; "close"
	102	[130]	CALL     	10 2 1
	103	[132]	GETUPVAL 	10 3	; socket
	104	[132]	GETTABLE 	10 10 -29	; "skip"
	105	[132]	LOADK    	11 -30	; 1
	106	[132]	GETTABLE 	12 0 -24	; "data"
	107	[132]	SELF     	12 12 -31	; "getstats"
	108	[132]	CALL     	12 2 0
	109	[132]	CALL     	10 0 2
	110	[133]	SETTABLE 	0 -24 -32	; "data" nil
	111	[134]	RETURN   	10 2
	112	[135]	RETURN   	0 1

function <./socket/ftp.lua:119,124> (25 instructions, 100 bytes at 0x7fd604c07720)
2 params, 7 slots, 6 upvalues, 3 locals, 6 constants, 0 functions
	1	[121]	GETUPVAL 	2 0	; socket
	2	[121]	GETTABLE 	2 2 -1	; "select"
	3	[121]	GETUPVAL 	3 1	; readt
	4	[121]	LOADNIL  	4 4
	5	[121]	LOADK    	5 -2	; 0
	6	[121]	CALL     	2 4 2
	7	[122]	GETUPVAL 	3 2	; tp
	8	[122]	GETTABLE 	3 2 3
	9	[122]	TEST     	3 0 0
	10	[122]	JMP      	9	; to 20
	11	[122]	GETUPVAL 	3 4	; self
	12	[122]	GETTABLE 	3 3 -3	; "try"
	13	[122]	GETUPVAL 	4 4	; self
	14	[122]	GETTABLE 	4 4 -4	; "tp"
	15	[122]	SELF     	4 4 -5	; "check"
	16	[122]	LOADK    	6 -6	; "2.."
	17	[122]	CALL     	4 3 0
	18	[122]	CALL     	3 0 2
	19	[122]	SETUPVAL 	3 3	; code
	20	[123]	GETUPVAL 	3 5	; step
	21	[123]	MOVE     	4 0
	22	[123]	MOVE     	5 1
	23	[123]	TAILCALL 	3 3 0
	24	[123]	RETURN   	3 0
	25	[124]	RETURN   	0 1

function <./socket/ftp.lua:137,158> (104 instructions, 416 bytes at 0x7fd604c0a1d0)
2 params, 13 slots, 4 upvalues, 8 locals, 31 constants, 0 functions
	1	[138]	GETTABLE 	2 0 -1	; "try"
	2	[138]	GETTABLE 	3 0 -2	; "pasvt"
	3	[138]	TEST     	3 0 1
	4	[138]	JMP      	1	; to 6
	5	[138]	GETTABLE 	3 0 -3	; "server"
	6	[138]	LOADK    	4 -4	; "need port or pasv first"
	7	[138]	CALL     	2 3 1
	8	[139]	GETTABLE 	2 0 -2	; "pasvt"
	9	[139]	TEST     	2 0 0
	10	[139]	JMP      	2	; to 13
	11	[139]	SELF     	2 0 -5	; "pasvconnect"
	12	[139]	CALL     	2 2 1
	13	[140]	GETTABLE 	2 1 -6	; "argument"
	14	[140]	TEST     	2 0 1
	15	[140]	JMP      	12	; to 28
	16	[141]	GETUPVAL 	2 0	; url
	17	[141]	GETTABLE 	2 2 -7	; "unescape"
	18	[141]	GETUPVAL 	3 1	; string
	19	[141]	GETTABLE 	3 3 -8	; "gsub"
	20	[141]	GETTABLE 	4 1 -9	; "path"
	21	[141]	TEST     	4 0 1
	22	[141]	JMP      	1	; to 24
	23	[141]	LOADK    	4 -10	; ""
	24	[141]	LOADK    	5 -11	; "^[/\\]"
	25	[141]	LOADK    	6 -10	; ""
	26	[141]	CALL     	3 4 0
	27	[141]	CALL     	2 0 2
	28	[142]	EQ       	0 2 -10	; - ""
	29	[142]	JMP      	1	; to 31
	30	[142]	LOADNIL  	2 2
	31	[143]	GETTABLE 	3 1 -12	; "command"
	32	[143]	TEST     	3 0 1
	33	[143]	JMP      	1	; to 35
	34	[143]	LOADK    	3 -13	; "retr"
	35	[144]	GETTABLE 	4 0 -1	; "try"
	36	[144]	GETTABLE 	5 0 -14	; "tp"
	37	[144]	SELF     	5 5 -12	; "command"
	38	[144]	MOVE     	7 3
	39	[144]	MOVE     	8 2
	40	[144]	CALL     	5 4 0
	41	[144]	CALL     	4 0 1
	42	[145]	GETTABLE 	4 0 -1	; "try"
	43	[145]	GETTABLE 	5 0 -14	; "tp"
	44	[145]	SELF     	5 5 -15	; "check"
	45	[145]	NEWTABLE 	7 2 0
	46	[145]	LOADK    	8 -16	; "1.."
	47	[145]	LOADK    	9 -17	; "2.."
	48	[145]	SETLIST  	7 2 1	; 1
	49	[145]	CALL     	5 3 0
	50	[145]	CALL     	4 0 3
	51	[146]	LE       	0 -18 4	; 200 -
	52	[146]	JMP      	7	; to 60
	53	[146]	LE       	0 4 -19	; - 299
	54	[146]	JMP      	5	; to 60
	55	[147]	GETTABLE 	6 1 -20	; "sink"
	56	[147]	MOVE     	7 5
	57	[147]	CALL     	6 2 1
	58	[148]	LOADK    	6 -21	; 1
	59	[148]	RETURN   	6 2
	60	[150]	GETTABLE 	6 0 -2	; "pasvt"
	61	[150]	TEST     	6 0 1
	62	[150]	JMP      	2	; to 65
	63	[150]	SELF     	6 0 -22	; "portconnect"
	64	[150]	CALL     	6 2 1
	65	[151]	GETUPVAL 	6 2	; socket
	66	[151]	GETTABLE 	6 6 -23	; "source"
	67	[151]	LOADK    	7 -24	; "until-closed"
	68	[151]	GETTABLE 	8 0 -25	; "data"
	69	[151]	CALL     	6 3 2
	70	[152]	GETTABLE 	7 1 -26	; "step"
	71	[152]	TEST     	7 0 1
	72	[152]	JMP      	3	; to 76
	73	[152]	GETUPVAL 	7 3	; ltn12
	74	[152]	GETTABLE 	7 7 -27	; "pump"
	75	[152]	GETTABLE 	7 7 -26	; "step"
	76	[153]	GETTABLE 	8 0 -1	; "try"
	77	[153]	GETUPVAL 	9 3	; ltn12
	78	[153]	GETTABLE 	9 9 -27	; "pump"
	79	[153]	GETTABLE 	9 9 -28	; "all"
	80	[153]	MOVE     	10 6
	81	[153]	GETTABLE 	11 1 -20	; "sink"
	82	[153]	MOVE     	12 7
	83	[153]	CALL     	9 4 0
	84	[153]	CALL     	8 0 1
	85	[154]	GETUPVAL 	8 1	; string
	86	[154]	GETTABLE 	8 8 -29	; "find"
	87	[154]	MOVE     	9 4
	88	[154]	LOADK    	10 -16	; "1.."
	89	[154]	CALL     	8 3 2
	90	[154]	TEST     	8 0 0
	91	[154]	JMP      	6	; to 98
	92	[154]	GETTABLE 	8 0 -1	; "try"
	93	[154]	GETTABLE 	9 0 -14	; "tp"
	94	[154]	SELF     	9 9 -15	; "check"
	95	[154]	LOADK    	11 -17	; "2.."
	96	[154]	CALL     	9 3 0
	97	[154]	CALL     	8 0 1
	98	[155]	GETTABLE 	8 0 -25	; "data"
	99	[155]	SELF     	8 8 -30	; "close"
	100	[155]	CALL     	8 2 1
	101	[156]	SETTABLE 	0 -25 -31	; "data" nil
	102	[157]	LOADK    	8 -21	; 1
	103	[157]	RETURN   	8 2
	104	[158]	RETURN   	0 1

function <./socket/ftp.lua:160,164> (16 instructions, 64 bytes at 0x7fd604c0a480)
2 params, 7 slots, 0 upvalues, 2 locals, 7 constants, 0 functions
	1	[161]	GETTABLE 	2 0 -1	; "try"
	2	[161]	GETTABLE 	3 0 -2	; "tp"
	3	[161]	SELF     	3 3 -3	; "command"
	4	[161]	LOADK    	5 -4	; "cwd"
	5	[161]	MOVE     	6 1
	6	[161]	CALL     	3 4 0
	7	[161]	CALL     	2 0 1
	8	[162]	GETTABLE 	2 0 -1	; "try"
	9	[162]	GETTABLE 	3 0 -2	; "tp"
	10	[162]	SELF     	3 3 -5	; "check"
	11	[162]	LOADK    	5 -6	; 250
	12	[162]	CALL     	3 3 0
	13	[162]	CALL     	2 0 1
	14	[163]	LOADK    	2 -7	; 1
	15	[163]	RETURN   	2 2
	16	[164]	RETURN   	0 1

function <./socket/ftp.lua:166,170> (16 instructions, 64 bytes at 0x7fd604c0acc0)
2 params, 7 slots, 0 upvalues, 2 locals, 7 constants, 0 functions
	1	[167]	GETTABLE 	2 0 -1	; "try"
	2	[167]	GETTABLE 	3 0 -2	; "tp"
	3	[167]	SELF     	3 3 -3	; "command"
	4	[167]	LOADK    	5 -4	; "type"
	5	[167]	MOVE     	6 1
	6	[167]	CALL     	3 4 0
	7	[167]	CALL     	2 0 1
	8	[168]	GETTABLE 	2 0 -1	; "try"
	9	[168]	GETTABLE 	3 0 -2	; "tp"
	10	[168]	SELF     	3 3 -5	; "check"
	11	[168]	LOADK    	5 -6	; 200
	12	[168]	CALL     	3 3 0
	13	[168]	CALL     	2 0 1
	14	[169]	LOADK    	2 -7	; 1
	15	[169]	RETURN   	2 2
	16	[170]	RETURN   	0 1

function <./socket/ftp.lua:172,176> (25 instructions, 100 bytes at 0x7fd604c0b080)
1 param, 7 slots, 1 upvalue, 2 locals, 7 constants, 0 functions
	1	[173]	GETTABLE 	1 0 -1	; "try"
	2	[173]	GETTABLE 	2 0 -2	; "tp"
	3	[173]	SELF     	2 2 -3	; "check"
	4	[173]	NEWTABLE 	4 2 0
	5	[173]	LOADK    	5 -4	; "1.."
	6	[173]	LOADK    	6 -5	; "2.."
	7	[173]	SETLIST  	4 2 1	; 1
	8	[173]	CALL     	2 3 0
	9	[173]	CALL     	1 0 2
	10	[174]	GETUPVAL 	2 0	; string
	11	[174]	GETTABLE 	2 2 -6	; "find"
	12	[174]	MOVE     	3 1
	13	[174]	LOADK    	4 -4	; "1.."
	14	[174]	CALL     	2 3 2
	15	[174]	TEST     	2 0 0
	16	[174]	JMP      	6	; to 23
	17	[174]	GETTABLE 	2 0 -1	; "try"
	18	[174]	GETTABLE 	3 0 -2	; "tp"
	19	[174]	SELF     	3 3 -3	; "check"
	20	[174]	LOADK    	5 -5	; "2.."
	21	[174]	CALL     	3 3 0
	22	[174]	CALL     	2 0 1
	23	[175]	LOADK    	2 -7	; 1
	24	[175]	RETURN   	2 2
	25	[176]	RETURN   	0 1

function <./socket/ftp.lua:178,182> (15 instructions, 60 bytes at 0x7fd604c0b620)
1 param, 5 slots, 0 upvalues, 1 local, 7 constants, 0 functions
	1	[179]	GETTABLE 	1 0 -1	; "try"
	2	[179]	GETTABLE 	2 0 -2	; "tp"
	3	[179]	SELF     	2 2 -3	; "command"
	4	[179]	LOADK    	4 -4	; "quit"
	5	[179]	CALL     	2 3 0
	6	[179]	CALL     	1 0 1
	7	[180]	GETTABLE 	1 0 -1	; "try"
	8	[180]	GETTABLE 	2 0 -2	; "tp"
	9	[180]	SELF     	2 2 -5	; "check"
	10	[180]	LOADK    	4 -6	; "2.."
	11	[180]	CALL     	2 3 0
	12	[180]	CALL     	1 0 1
	13	[181]	LOADK    	1 -7	; 1
	14	[181]	RETURN   	1 2
	15	[182]	RETURN   	0 1

function <./socket/ftp.lua:184,188> (17 instructions, 68 bytes at 0x7fd604c0b9d0)
1 param, 3 slots, 0 upvalues, 1 local, 4 constants, 0 functions
	1	[185]	GETTABLE 	1 0 -1	; "data"
	2	[185]	TEST     	1 0 0
	3	[185]	JMP      	3	; to 7
	4	[185]	GETTABLE 	1 0 -1	; "data"
	5	[185]	SELF     	1 1 -2	; "close"
	6	[185]	CALL     	1 2 1
	7	[186]	GETTABLE 	1 0 -3	; "server"
	8	[186]	TEST     	1 0 0
	9	[186]	JMP      	3	; to 13
	10	[186]	GETTABLE 	1 0 -3	; "server"
	11	[186]	SELF     	1 1 -2	; "close"
	12	[186]	CALL     	1 2 1
	13	[187]	GETTABLE 	1 0 -4	; "tp"
	14	[187]	SELF     	1 1 -2	; "close"
	15	[187]	TAILCALL 	1 2 0
	16	[187]	RETURN   	1 0
	17	[188]	RETURN   	0 1

function <./socket/ftp.lua:193,201> (19 instructions, 76 bytes at 0x7fd604c0be30)
1 param, 8 slots, 2 upvalues, 7 locals, 3 constants, 0 functions
	1	[194]	GETTABLE 	1 0 -1	; "url"
	2	[194]	TEST     	1 0 0
	3	[194]	JMP      	14	; to 18
	4	[195]	GETUPVAL 	1 0	; url
	5	[195]	GETTABLE 	1 1 -2	; "parse"
	6	[195]	GETTABLE 	2 0 -1	; "url"
	7	[195]	CALL     	1 2 2
	8	[196]	GETUPVAL 	2 1	; base
	9	[196]	GETTABLE 	2 2 -3	; "pairs"
	10	[196]	MOVE     	3 0
	11	[196]	CALL     	2 2 4
	12	[196]	JMP      	1	; to 14
	13	[197]	SETTABLE 	1 5 6
	14	[196]	TFORLOOP 	2 2
	15	[197]	JMP      	-3	; to 13
	16	[199]	RETURN   	1 2
	17	[199]	JMP      	1	; to 19
	18	[200]	RETURN   	0 2
	19	[201]	RETURN   	0 1

function <./socket/ftp.lua:203,215> (38 instructions, 152 bytes at 0x7fd604d04120)
1 param, 6 slots, 3 upvalues, 3 locals, 15 constants, 0 functions
	1	[204]	GETUPVAL 	1 0	; override
	2	[204]	MOVE     	2 0
	3	[204]	CALL     	1 2 2
	4	[204]	MOVE     	0 1
	5	[205]	GETUPVAL 	1 1	; socket
	6	[205]	GETTABLE 	1 1 -1	; "try"
	7	[205]	GETTABLE 	2 0 -2	; "host"
	8	[205]	LOADK    	3 -3	; "missing hostname"
	9	[205]	CALL     	1 3 1
	10	[206]	GETUPVAL 	1 2	; _M
	11	[206]	GETTABLE 	1 1 -4	; "open"
	12	[206]	GETTABLE 	2 0 -2	; "host"
	13	[206]	GETTABLE 	3 0 -5	; "port"
	14	[206]	GETTABLE 	4 0 -6	; "create"
	15	[206]	CALL     	1 4 2
	16	[207]	SELF     	2 1 -7	; "greet"
	17	[207]	CALL     	2 2 1
	18	[208]	SELF     	2 1 -8	; "login"
	19	[208]	GETTABLE 	4 0 -9	; "user"
	20	[208]	GETTABLE 	5 0 -10	; "password"
	21	[208]	CALL     	2 4 1
	22	[209]	GETTABLE 	2 0 -11	; "type"
	23	[209]	TEST     	2 0 0
	24	[209]	JMP      	3	; to 28
	25	[209]	SELF     	2 1 -11	; "type"
	26	[209]	GETTABLE 	4 0 -11	; "type"
	27	[209]	CALL     	2 3 1
	28	[210]	SELF     	2 1 -12	; "pasv"
	29	[210]	CALL     	2 2 1
	30	[211]	SELF     	2 1 -13	; "send"
	31	[211]	MOVE     	4 0
	32	[211]	CALL     	2 3 2
	33	[212]	SELF     	3 1 -14	; "quit"
	34	[212]	CALL     	3 2 1
	35	[213]	SELF     	3 1 -15	; "close"
	36	[213]	CALL     	3 2 1
	37	[214]	RETURN   	2 2
	38	[215]	RETURN   	0 1

function <./socket/ftp.lua:222,233> (56 instructions, 224 bytes at 0x7fd604d04550)
1 param, 8 slots, 4 upvalues, 3 locals, 17 constants, 0 functions
	1	[223]	GETUPVAL 	1 0	; socket
	2	[223]	GETTABLE 	1 1 -1	; "try"
	3	[223]	GETUPVAL 	2 1	; url
	4	[223]	GETTABLE 	2 2 -2	; "parse"
	5	[223]	MOVE     	3 0
	6	[223]	GETUPVAL 	4 2	; default
	7	[223]	CALL     	2 3 0
	8	[223]	CALL     	1 0 2
	9	[224]	GETUPVAL 	2 0	; socket
	10	[224]	GETTABLE 	2 2 -1	; "try"
	11	[224]	GETTABLE 	3 1 -3	; "scheme"
	12	[224]	EQ       	1 3 -4	; - "ftp"
	13	[224]	JMP      	1	; to 15
	14	[224]	LOADBOOL 	3 0 1
	15	[224]	LOADBOOL 	3 1 0
	16	[224]	LOADK    	4 -5	; "wrong scheme '"
	17	[224]	GETTABLE 	5 1 -3	; "scheme"
	18	[224]	LOADK    	6 -6	; "'"
	19	[224]	CONCAT   	4 4 6
	20	[224]	CALL     	2 3 1
	21	[225]	GETUPVAL 	2 0	; socket
	22	[225]	GETTABLE 	2 2 -1	; "try"
	23	[225]	GETTABLE 	3 1 -7	; "host"
	24	[225]	LOADK    	4 -8	; "missing hostname"
	25	[225]	CALL     	2 3 1
	26	[226]	LOADK    	2 -9	; "^type=(.)$"
	27	[227]	GETTABLE 	3 1 -10	; "params"
	28	[227]	TEST     	3 0 0
	29	[227]	JMP      	25	; to 55
	30	[228]	GETUPVAL 	3 0	; socket
	31	[228]	GETTABLE 	3 3 -12	; "skip"
	32	[228]	LOADK    	4 -13	; 2
	33	[228]	GETUPVAL 	5 3	; string
	34	[228]	GETTABLE 	5 5 -14	; "find"
	35	[228]	GETTABLE 	6 1 -10	; "params"
	36	[228]	MOVE     	7 2
	37	[228]	CALL     	5 3 0
	38	[228]	CALL     	3 0 2
	39	[228]	SETTABLE 	1 -11 3	; "type" -
	40	[229]	GETUPVAL 	3 0	; socket
	41	[229]	GETTABLE 	3 3 -1	; "try"
	42	[229]	GETTABLE 	4 1 -11	; "type"
	43	[229]	EQ       	1 4 -15	; - "a"
	44	[229]	JMP      	4	; to 49
	45	[229]	GETTABLE 	4 1 -11	; "type"
	46	[229]	EQ       	1 4 -16	; - "i"
	47	[229]	JMP      	1	; to 49
	48	[229]	LOADBOOL 	4 0 1
	49	[229]	LOADBOOL 	4 1 0
	50	[230]	LOADK    	5 -17	; "invalid type '"
	51	[230]	GETTABLE 	6 1 -11	; "type"
	52	[230]	LOADK    	7 -6	; "'"
	53	[230]	CONCAT   	5 5 7
	54	[229]	CALL     	3 3 1
	55	[232]	RETURN   	1 2
	56	[233]	RETURN   	0 1

function <./socket/ftp.lua:235,239> (14 instructions, 56 bytes at 0x7fd604d04990)
2 params, 5 slots, 3 upvalues, 3 locals, 2 constants, 0 functions
	1	[236]	GETUPVAL 	2 0	; parse
	2	[236]	MOVE     	3 0
	3	[236]	CALL     	2 2 2
	4	[237]	GETUPVAL 	3 1	; ltn12
	5	[237]	GETTABLE 	3 3 -1	; "source"
	6	[237]	GETTABLE 	3 3 -2	; "string"
	7	[237]	MOVE     	4 1
	8	[237]	CALL     	3 2 2
	9	[237]	SETTABLE 	2 -1 3	; "source" -
	10	[238]	GETUPVAL 	3 2	; tput
	11	[238]	MOVE     	4 2
	12	[238]	TAILCALL 	3 2 0
	13	[238]	RETURN   	3 0
	14	[239]	RETURN   	0 1

function <./socket/ftp.lua:241,244> (17 instructions, 68 bytes at 0x7fd604d05010)
2 params, 5 slots, 3 upvalues, 2 locals, 2 constants, 0 functions
	1	[242]	GETUPVAL 	2 0	; base
	2	[242]	GETTABLE 	2 2 -1	; "type"
	3	[242]	MOVE     	3 0
	4	[242]	CALL     	2 2 2
	5	[242]	EQ       	0 2 -2	; - "string"
	6	[242]	JMP      	6	; to 13
	7	[242]	GETUPVAL 	2 1	; sput
	8	[242]	MOVE     	3 0
	9	[242]	MOVE     	4 1
	10	[242]	TAILCALL 	2 3 0
	11	[242]	RETURN   	2 0
	12	[242]	JMP      	4	; to 17
	13	[243]	GETUPVAL 	2 2	; tput
	14	[243]	MOVE     	3 0
	15	[243]	TAILCALL 	2 2 0
	16	[243]	RETURN   	2 0
	17	[244]	RETURN   	0 1

function <./socket/ftp.lua:246,257> (38 instructions, 152 bytes at 0x7fd604d05860)
1 param, 6 slots, 3 upvalues, 2 locals, 15 constants, 0 functions
	1	[247]	GETUPVAL 	1 0	; override
	2	[247]	MOVE     	2 0
	3	[247]	CALL     	1 2 2
	4	[247]	MOVE     	0 1
	5	[248]	GETUPVAL 	1 1	; socket
	6	[248]	GETTABLE 	1 1 -1	; "try"
	7	[248]	GETTABLE 	2 0 -2	; "host"
	8	[248]	LOADK    	3 -3	; "missing hostname"
	9	[248]	CALL     	1 3 1
	10	[249]	GETUPVAL 	1 2	; _M
	11	[249]	GETTABLE 	1 1 -4	; "open"
	12	[249]	GETTABLE 	2 0 -2	; "host"
	13	[249]	GETTABLE 	3 0 -5	; "port"
	14	[249]	GETTABLE 	4 0 -6	; "create"
	15	[249]	CALL     	1 4 2
	16	[250]	SELF     	2 1 -7	; "greet"
	17	[250]	CALL     	2 2 1
	18	[251]	SELF     	2 1 -8	; "login"
	19	[251]	GETTABLE 	4 0 -9	; "user"
	20	[251]	GETTABLE 	5 0 -10	; "password"
	21	[251]	CALL     	2 4 1
	22	[252]	GETTABLE 	2 0 -11	; "type"
	23	[252]	TEST     	2 0 0
	24	[252]	JMP      	3	; to 28
	25	[252]	SELF     	2 1 -11	; "type"
	26	[252]	GETTABLE 	4 0 -11	; "type"
	27	[252]	CALL     	2 3 1
	28	[253]	SELF     	2 1 -12	; "pasv"
	29	[253]	CALL     	2 2 1
	30	[254]	SELF     	2 1 -13	; "receive"
	31	[254]	MOVE     	4 0
	32	[254]	CALL     	2 3 1
	33	[255]	SELF     	2 1 -14	; "quit"
	34	[255]	CALL     	2 2 1
	35	[256]	SELF     	2 1 -15	; "close"
	36	[256]	TAILCALL 	2 2 0
	37	[256]	RETURN   	2 0
	38	[257]	RETURN   	0 1

function <./socket/ftp.lua:259,265> (19 instructions, 76 bytes at 0x7fd604d05a20)
1 param, 5 slots, 4 upvalues, 3 locals, 3 constants, 0 functions
	1	[260]	GETUPVAL 	1 0	; parse
	2	[260]	MOVE     	2 0
	3	[260]	CALL     	1 2 2
	4	[261]	NEWTABLE 	2 0 0
	5	[262]	GETUPVAL 	3 1	; ltn12
	6	[262]	GETTABLE 	3 3 -1	; "sink"
	7	[262]	GETTABLE 	3 3 -2	; "table"
	8	[262]	MOVE     	4 2
	9	[262]	CALL     	3 2 2
	10	[262]	SETTABLE 	1 -1 3	; "sink" -
	11	[263]	GETUPVAL 	3 2	; tget
	12	[263]	MOVE     	4 1
	13	[263]	CALL     	3 2 1
	14	[264]	GETUPVAL 	3 3	; table
	15	[264]	GETTABLE 	3 3 -3	; "concat"
	16	[264]	MOVE     	4 2
	17	[264]	TAILCALL 	3 2 0
	18	[264]	RETURN   	3 0
	19	[265]	RETURN   	0 1

function <./socket/ftp.lua:267,278> (47 instructions, 188 bytes at 0x7fd604d058e0)
1 param, 7 slots, 2 upvalues, 2 locals, 17 constants, 0 functions
	1	[268]	GETUPVAL 	1 0	; override
	2	[268]	MOVE     	2 0
	3	[268]	CALL     	1 2 2
	4	[268]	MOVE     	0 1
	5	[269]	GETUPVAL 	1 1	; socket
	6	[269]	GETTABLE 	1 1 -1	; "try"
	7	[269]	GETTABLE 	2 0 -2	; "host"
	8	[269]	LOADK    	3 -3	; "missing hostname"
	9	[269]	CALL     	1 3 1
	10	[270]	GETUPVAL 	1 1	; socket
	11	[270]	GETTABLE 	1 1 -1	; "try"
	12	[270]	GETTABLE 	2 0 -4	; "command"
	13	[270]	LOADK    	3 -5	; "missing command"
	14	[270]	CALL     	1 3 1
	15	[271]	GETGLOBAL	1 -6	; open
	16	[271]	GETTABLE 	2 0 -2	; "host"
	17	[271]	GETTABLE 	3 0 -7	; "port"
	18	[271]	GETTABLE 	4 0 -8	; "create"
	19	[271]	CALL     	1 4 2
	20	[272]	SELF     	2 1 -9	; "greet"
	21	[272]	CALL     	2 2 1
	22	[273]	SELF     	2 1 -10	; "login"
	23	[273]	GETTABLE 	4 0 -11	; "user"
	24	[273]	GETTABLE 	5 0 -12	; "password"
	25	[273]	CALL     	2 4 1
	26	[274]	GETTABLE 	2 1 -1	; "try"
	27	[274]	GETTABLE 	3 1 -13	; "tp"
	28	[274]	SELF     	3 3 -4	; "command"
	29	[274]	GETTABLE 	5 0 -4	; "command"
	30	[274]	GETTABLE 	6 0 -14	; "argument"
	31	[274]	CALL     	3 4 0
	32	[274]	CALL     	2 0 1
	33	[275]	GETTABLE 	2 0 -15	; "check"
	34	[275]	TEST     	2 0 0
	35	[275]	JMP      	6	; to 42
	36	[275]	GETTABLE 	2 1 -1	; "try"
	37	[275]	GETTABLE 	3 1 -13	; "tp"
	38	[275]	SELF     	3 3 -15	; "check"
	39	[275]	GETTABLE 	5 0 -15	; "check"
	40	[275]	CALL     	3 3 0
	41	[275]	CALL     	2 0 1
	42	[276]	SELF     	2 1 -16	; "quit"
	43	[276]	CALL     	2 2 1
	44	[277]	SELF     	2 1 -17	; "close"
	45	[277]	TAILCALL 	2 2 0
	46	[277]	RETURN   	2 0
	47	[278]	RETURN   	0 1

function <./socket/ftp.lua:280,283> (16 instructions, 64 bytes at 0x7fd604d064c0)
1 param, 3 slots, 3 upvalues, 1 local, 2 constants, 0 functions
	1	[281]	GETUPVAL 	1 0	; base
	2	[281]	GETTABLE 	1 1 -1	; "type"
	3	[281]	MOVE     	2 0
	4	[281]	CALL     	1 2 2
	5	[281]	EQ       	0 1 -2	; - "string"
	6	[281]	JMP      	5	; to 12
	7	[281]	GETUPVAL 	1 1	; sget
	8	[281]	MOVE     	2 0
	9	[281]	TAILCALL 	1 2 0
	10	[281]	RETURN   	1 0
	11	[281]	JMP      	4	; to 16
	12	[282]	GETUPVAL 	1 2	; tget
	13	[282]	MOVE     	2 0
	14	[282]	TAILCALL 	1 2 0
	15	[282]	RETURN   	1 0
	16	[283]	RETURN   	0 1
