
main <./socket/http.lua:0,0> (143 instructions, 572 bytes at 0x7fc2f1c068a0)
0+ params, 23 slots, 0 upvalues, 21 locals, 37 constants, 22 functions
	1	[10]	GETGLOBAL	0 -1	; require
	2	[10]	LOADK    	1 -2	; "socket"
	3	[10]	CALL     	0 2 2
	4	[11]	GETGLOBAL	1 -1	; require
	5	[11]	LOADK    	2 -3	; "socket.url"
	6	[11]	CALL     	1 2 2
	7	[12]	GETGLOBAL	2 -1	; require
	8	[12]	LOADK    	3 -4	; "ltn12"
	9	[12]	CALL     	2 2 2
	10	[13]	GETGLOBAL	3 -1	; require
	11	[13]	LOADK    	4 -5	; "mime"
	12	[13]	CALL     	3 2 2
	13	[14]	GETGLOBAL	4 -1	; require
	14	[14]	LOADK    	5 -6	; "string"
	15	[14]	CALL     	4 2 2
	16	[15]	GETGLOBAL	5 -1	; require
	17	[15]	LOADK    	6 -7	; "socket.headers"
	18	[15]	CALL     	5 2 2
	19	[16]	GETGLOBAL	6 -8	; _G
	20	[17]	GETGLOBAL	7 -1	; require
	21	[17]	LOADK    	8 -9	; "table"
	22	[17]	CALL     	7 2 2
	23	[18]	NEWTABLE 	8 0 0
	24	[18]	SETTABLE 	0 -10 8	; "http" -
	25	[19]	GETTABLE 	8 0 -10	; "http"
	26	[25]	LOADK    	9 -12	; 60
	27	[25]	SETGLOBAL	9 -11	; TIMEOUT
	28	[27]	SETTABLE 	8 -13 -14	; "PORT" 80
	29	[29]	GETTABLE 	9 0 -16	; "_VERSION"
	30	[29]	SETTABLE 	8 -15 9	; "USERAGENT" -
	31	[60]	CLOSURE  	9 0	; 0x7fc2f1c06d50
	32	[60]	MOVE     	0 0
	33	[60]	MOVE     	0 4
	34	[65]	GETTABLE 	10 0 -17	; "sourcet"
	35	[89]	CLOSURE  	11 1	; 0x7fc2f1c06c10
	36	[89]	MOVE     	0 6
	37	[89]	MOVE     	0 4
	38	[89]	MOVE     	0 9
	39	[89]	SETTABLE 	10 -18 11	; "http-chunked" -
	40	[91]	GETTABLE 	10 0 -19	; "sinkt"
	41	[102]	CLOSURE  	11 2	; 0x7fc2f1c08430
	42	[102]	MOVE     	0 6
	43	[102]	MOVE     	0 4
	44	[102]	SETTABLE 	10 -18 11	; "http-chunked" -
	45	[107]	NEWTABLE 	10 0 1
	46	[107]	NEWTABLE 	11 0 0
	47	[107]	SETTABLE 	10 -20 11	; "__index" -
	48	[120]	CLOSURE  	11 3	; 0x7fc2f1c08c80
	49	[120]	MOVE     	0 0
	50	[120]	MOVE     	0 6
	51	[120]	MOVE     	0 10
	52	[120]	MOVE     	0 8
	53	[109]	SETTABLE 	8 -21 11	; "open" -
	54	[122]	GETTABLE 	11 10 -20	; "__index"
	55	[125]	CLOSURE  	12 4	; 0x7fc2f1c09720
	56	[125]	MOVE     	0 4
	57	[122]	SETTABLE 	11 -22 12	; "sendrequestline" -
	58	[127]	GETTABLE 	11 10 -20	; "__index"
	59	[135]	CLOSURE  	12 5	; 0x7fc2f1c09a00
	60	[135]	MOVE     	0 5
	61	[135]	MOVE     	0 6
	62	[127]	SETTABLE 	11 -23 12	; "sendheaders" -
	63	[137]	GETTABLE 	11 10 -20	; "__index"
	64	[144]	CLOSURE  	12 6	; 0x7fc2f1c0a0f0
	65	[144]	MOVE     	0 2
	66	[144]	MOVE     	0 0
	67	[137]	SETTABLE 	11 -24 12	; "sendbody" -
	68	[146]	GETTABLE 	11 10 -20	; "__index"
	69	[155]	CLOSURE  	12 7	; 0x7fc2f1c0a450
	70	[155]	MOVE     	0 0
	71	[155]	MOVE     	0 4
	72	[155]	MOVE     	0 6
	73	[146]	SETTABLE 	11 -25 12	; "receivestatusline" -
	74	[157]	GETTABLE 	11 10 -20	; "__index"
	75	[159]	CLOSURE  	12 8	; 0x7fc2f1c0a6b0
	76	[159]	MOVE     	0 9
	77	[157]	SETTABLE 	11 -26 12	; "receiveheaders" -
	78	[161]	GETTABLE 	11 10 -20	; "__index"
	79	[171]	CLOSURE  	12 9	; 0x7fc2f1c0af50
	80	[171]	MOVE     	0 2
	81	[171]	MOVE     	0 6
	82	[171]	MOVE     	0 0
	83	[161]	SETTABLE 	11 -27 12	; "receivebody" -
	84	[173]	GETTABLE 	11 10 -20	; "__index"
	85	[177]	CLOSURE  	12 10	; 0x7fc2f1c0b650
	86	[177]	MOVE     	0 2
	87	[177]	MOVE     	0 0
	88	[173]	SETTABLE 	11 -28 12	; "receive09body" -
	89	[179]	GETTABLE 	11 10 -20	; "__index"
	90	[181]	CLOSURE  	12 11	; 0x7fc2f1c0b990
	91	[179]	SETTABLE 	11 -29 12	; "close" -
	92	[198]	CLOSURE  	11 12	; 0x7fc2f1c0ba10
	93	[198]	MOVE     	0 0
	94	[198]	MOVE     	0 1
	95	[208]	CLOSURE  	12 13	; 0x7fc2f1c0be60
	96	[208]	MOVE     	0 1
	97	[228]	CLOSURE  	13 14	; 0x7fc2f1c0c670
	98	[228]	MOVE     	0 8
	99	[228]	MOVE     	0 3
	100	[228]	MOVE     	0 6
	101	[228]	MOVE     	0 4
	102	[231]	NEWTABLE 	14 0 4
	103	[232]	SETTABLE 	14 -30 -31	; "host" ""
	104	[233]	GETTABLE 	15 8 -13	; "PORT"
	105	[233]	SETTABLE 	14 -32 15	; "port" -
	106	[234]	SETTABLE 	14 -33 -34	; "path" "/"
	107	[235]	SETTABLE 	14 -35 -10	; "scheme" "http"
	108	[253]	CLOSURE  	15 15	; 0x7fc2f1c0c760
	109	[253]	MOVE     	0 1
	110	[253]	MOVE     	0 14
	111	[253]	MOVE     	0 6
	112	[253]	MOVE     	0 0
	113	[253]	MOVE     	0 11
	114	[253]	MOVE     	0 12
	115	[253]	MOVE     	0 13
	116	[262]	CLOSURE  	16 16	; 0x7fc2f1c09140
	117	[262]	MOVE     	0 4
	118	[269]	CLOSURE  	17 17	; 0x7fc2f1c0aed0
	119	[272]	LOADNIL  	18 19
	120	[290]	CLOSURE  	19 18	; 0x7fc2f1c071d0
	121	[290]	MOVE     	0 18
	122	[274]	MOVE     	0 1
	123	[329]	CLOSURE  	18 19	; 0x7fc2f1c0cdf0
	124	[329]	MOVE     	0 15
	125	[329]	MOVE     	0 8
	126	[329]	MOVE     	0 16
	127	[329]	MOVE     	0 19
	128	[292]	MOVE     	0 17
	129	[347]	CLOSURE  	20 20	; 0x7fc2f1c0d5e0
	130	[347]	MOVE     	0 2
	131	[347]	MOVE     	0 4
	132	[347]	MOVE     	0 0
	133	[347]	MOVE     	0 18
	134	[347]	MOVE     	0 7
	135	[349]	GETTABLE 	21 0 -37	; "protect"
	136	[352]	CLOSURE  	22 21	; 0x7fc2f1c0dcc0
	137	[352]	MOVE     	0 6
	138	[352]	MOVE     	0 20
	139	[352]	MOVE     	0 18
	140	[349]	CALL     	21 2 2
	141	[352]	SETTABLE 	8 -36 21	; "request" -
	142	[354]	RETURN   	8 2
	143	[354]	RETURN   	0 1

function <./socket/http.lua:34,60> (79 instructions, 316 bytes at 0x7fc2f1c06d50)
2 params, 11 slots, 2 upvalues, 6 locals, 10 constants, 0 functions
	1	[36]	TEST     	1 0 1
	2	[36]	JMP      	2	; to 5
	3	[36]	NEWTABLE 	6 0 0
	4	[36]	MOVE     	1 6
	5	[38]	SELF     	6 0 -1	; "receive"
	6	[38]	CALL     	6 2 3
	7	[38]	MOVE     	5 7
	8	[38]	MOVE     	2 6
	9	[39]	TEST     	5 0 0
	10	[39]	JMP      	3	; to 14
	11	[39]	LOADNIL  	6 6
	12	[39]	MOVE     	7 5
	13	[39]	RETURN   	6 3
	14	[41]	EQ       	1 2 -2	; - ""
	15	[41]	JMP      	62	; to 78
	16	[43]	GETUPVAL 	6 0	; socket
	17	[43]	GETTABLE 	6 6 -3	; "skip"
	18	[43]	LOADK    	7 -4	; 2
	19	[43]	GETUPVAL 	8 1	; string
	20	[43]	GETTABLE 	8 8 -5	; "find"
	21	[43]	MOVE     	9 2
	22	[43]	LOADK    	10 -6	; "^(.-):%s*(.*)"
	23	[43]	CALL     	8 3 0
	24	[43]	CALL     	6 0 3
	25	[43]	MOVE     	4 7
	26	[43]	MOVE     	3 6
	27	[44]	TEST     	3 0 0
	28	[44]	JMP      	2	; to 31
	29	[44]	TEST     	4 0 1
	30	[44]	JMP      	3	; to 34
	31	[44]	LOADNIL  	6 6
	32	[44]	LOADK    	7 -7	; "malformed reponse headers"
	33	[44]	RETURN   	6 3
	34	[45]	GETUPVAL 	6 1	; string
	35	[45]	GETTABLE 	6 6 -8	; "lower"
	36	[45]	MOVE     	7 3
	37	[45]	CALL     	6 2 2
	38	[45]	MOVE     	3 6
	39	[47]	SELF     	6 0 -1	; "receive"
	40	[47]	CALL     	6 2 3
	41	[47]	MOVE     	5 7
	42	[47]	MOVE     	2 6
	43	[48]	TEST     	5 0 0
	44	[48]	JMP      	3	; to 48
	45	[48]	LOADNIL  	6 6
	46	[48]	MOVE     	7 5
	47	[48]	RETURN   	6 3
	48	[50]	GETUPVAL 	6 1	; string
	49	[50]	GETTABLE 	6 6 -5	; "find"
	50	[50]	MOVE     	7 2
	51	[50]	LOADK    	8 -9	; "^%s"
	52	[50]	CALL     	6 3 2
	53	[50]	TEST     	6 0 0
	54	[50]	JMP      	12	; to 67
	55	[51]	MOVE     	6 4
	56	[51]	MOVE     	7 2
	57	[51]	CONCAT   	4 6 7
	58	[52]	SELF     	6 0 -1	; "receive"
	59	[52]	CALL     	6 2 2
	60	[52]	MOVE     	2 6
	61	[53]	TEST     	5 0 0
	62	[53]	JMP      	-15	; to 48
	63	[53]	LOADNIL  	6 6
	64	[53]	MOVE     	7 5
	65	[53]	RETURN   	6 3
	66	[53]	JMP      	-19	; to 48
	67	[56]	GETTABLE 	6 1 3
	68	[56]	TEST     	6 0 0
	69	[56]	JMP      	6	; to 76
	70	[56]	GETTABLE 	6 1 3
	71	[56]	LOADK    	7 -10	; ", "
	72	[56]	MOVE     	8 4
	73	[56]	CONCAT   	6 6 8
	74	[56]	SETTABLE 	1 3 6
	75	[56]	JMP      	-62	; to 14
	76	[57]	SETTABLE 	1 3 4
	77	[57]	JMP      	-64	; to 14
	78	[59]	RETURN   	1 2
	79	[60]	RETURN   	0 1

function <./socket/http.lua:65,89> (20 instructions, 80 bytes at 0x7fc2f1c06c10)
2 params, 6 slots, 3 upvalues, 2 locals, 4 constants, 3 functions
	1	[66]	GETUPVAL 	2 0	; base
	2	[66]	GETTABLE 	2 2 -1	; "setmetatable"
	3	[66]	NEWTABLE 	3 0 2
	4	[67]	CLOSURE  	4 0	; 0x7fc2f1c07050
	5	[67]	MOVE     	0 0
	6	[67]	SETTABLE 	3 -2 4	; "getfd" -
	7	[68]	CLOSURE  	4 1	; 0x7fc2f1c07d70
	8	[68]	MOVE     	0 0
	9	[68]	SETTABLE 	3 -3 4	; "dirty" -
	10	[69]	NEWTABLE 	4 0 1
	11	[87]	CLOSURE  	5 2	; 0x7fc2f1c07bd0
	12	[87]	MOVE     	0 0
	13	[87]	GETUPVAL 	0 0	; base
	14	[87]	GETUPVAL 	0 1	; string
	15	[87]	MOVE     	0 1
	16	[87]	GETUPVAL 	0 2	; receiveheaders
	17	[87]	SETTABLE 	4 -4 5	; "__call" -
	18	[66]	TAILCALL 	2 3 0
	19	[88]	RETURN   	2 0
	20	[89]	RETURN   	0 1

function <./socket/http.lua:67,67> (5 instructions, 20 bytes at 0x7fc2f1c07050)
0 params, 2 slots, 1 upvalue, 0 locals, 1 constant, 0 functions
	1	[67]	GETUPVAL 	0 0	; sock
	2	[67]	SELF     	0 0 -1	; "getfd"
	3	[67]	TAILCALL 	0 2 0
	4	[67]	RETURN   	0 0
	5	[67]	RETURN   	0 1

function <./socket/http.lua:68,68> (5 instructions, 20 bytes at 0x7fc2f1c07d70)
0 params, 2 slots, 1 upvalue, 0 locals, 1 constant, 0 functions
	1	[68]	GETUPVAL 	0 0	; sock
	2	[68]	SELF     	0 0 -1	; "dirty"
	3	[68]	TAILCALL 	0 2 0
	4	[68]	RETURN   	0 0
	5	[68]	RETURN   	0 1

function <./socket/http.lua:70,87> (51 instructions, 204 bytes at 0x7fc2f1c07bd0)
0 params, 8 slots, 5 upvalues, 6 locals, 8 constants, 0 functions
	1	[72]	GETUPVAL 	0 0	; sock
	2	[72]	SELF     	0 0 -1	; "receive"
	3	[72]	CALL     	0 2 3
	4	[73]	TEST     	1 0 0
	5	[73]	JMP      	3	; to 9
	6	[73]	LOADNIL  	2 2
	7	[73]	MOVE     	3 1
	8	[73]	RETURN   	2 3
	9	[74]	GETUPVAL 	2 1	; base
	10	[74]	GETTABLE 	2 2 -2	; "tonumber"
	11	[74]	GETUPVAL 	3 2	; string
	12	[74]	GETTABLE 	3 3 -3	; "gsub"
	13	[74]	MOVE     	4 0
	14	[74]	LOADK    	5 -4	; ";.*"
	15	[74]	LOADK    	6 -5	; ""
	16	[74]	CALL     	3 4 2
	17	[74]	LOADK    	4 -6	; 16
	18	[74]	CALL     	2 3 2
	19	[75]	TEST     	2 0 1
	20	[75]	JMP      	3	; to 24
	21	[75]	LOADNIL  	3 3
	22	[75]	LOADK    	4 -7	; "invalid chunk size"
	23	[75]	RETURN   	3 3
	24	[77]	LT       	0 -8 2	; 0 -
	25	[77]	JMP      	13	; to 39
	26	[79]	GETUPVAL 	3 0	; sock
	27	[79]	SELF     	3 3 -1	; "receive"
	28	[79]	MOVE     	5 2
	29	[79]	CALL     	3 3 4
	30	[80]	TEST     	3 0 0
	31	[80]	JMP      	3	; to 35
	32	[80]	GETUPVAL 	6 0	; sock
	33	[80]	SELF     	6 6 -1	; "receive"
	34	[80]	CALL     	6 2 1
	35	[81]	MOVE     	6 3
	36	[81]	MOVE     	7 4
	37	[81]	RETURN   	6 3
	38	[81]	JMP      	12	; to 51
	39	[84]	GETUPVAL 	3 4	; receiveheaders
	40	[84]	GETUPVAL 	4 0	; sock
	41	[84]	GETUPVAL 	5 3	; headers
	42	[84]	CALL     	3 3 3
	43	[84]	MOVE     	1 4
	44	[84]	SETUPVAL 	3 3	; headers
	45	[85]	GETUPVAL 	3 3	; headers
	46	[85]	TEST     	3 0 1
	47	[85]	JMP      	3	; to 51
	48	[85]	LOADNIL  	3 3
	49	[85]	MOVE     	4 1
	50	[85]	RETURN   	3 3
	51	[87]	RETURN   	0 1

function <./socket/http.lua:91,102> (17 instructions, 68 bytes at 0x7fc2f1c08430)
1 param, 5 slots, 2 upvalues, 1 local, 4 constants, 3 functions
	1	[92]	GETUPVAL 	1 0	; base
	2	[92]	GETTABLE 	1 1 -1	; "setmetatable"
	3	[92]	NEWTABLE 	2 0 2
	4	[93]	CLOSURE  	3 0	; 0x7fc2f1c089f0
	5	[93]	MOVE     	0 0
	6	[93]	SETTABLE 	2 -2 3	; "getfd" -
	7	[94]	CLOSURE  	3 1	; 0x7fc2f1c08b30
	8	[94]	MOVE     	0 0
	9	[94]	SETTABLE 	2 -3 3	; "dirty" -
	10	[95]	NEWTABLE 	3 0 1
	11	[100]	CLOSURE  	4 2	; 0x7fc2f1c08db0
	12	[100]	MOVE     	0 0
	13	[100]	GETUPVAL 	0 1	; string
	14	[100]	SETTABLE 	3 -4 4	; "__call" -
	15	[92]	TAILCALL 	1 3 0
	16	[101]	RETURN   	1 0
	17	[102]	RETURN   	0 1

function <./socket/http.lua:93,93> (5 instructions, 20 bytes at 0x7fc2f1c089f0)
0 params, 2 slots, 1 upvalue, 0 locals, 1 constant, 0 functions
	1	[93]	GETUPVAL 	0 0	; sock
	2	[93]	SELF     	0 0 -1	; "getfd"
	3	[93]	TAILCALL 	0 2 0
	4	[93]	RETURN   	0 0
	5	[93]	RETURN   	0 1

function <./socket/http.lua:94,94> (5 instructions, 20 bytes at 0x7fc2f1c08b30)
0 params, 2 slots, 1 upvalue, 0 locals, 1 constant, 0 functions
	1	[94]	GETUPVAL 	0 0	; sock
	2	[94]	SELF     	0 0 -1	; "dirty"
	3	[94]	TAILCALL 	0 2 0
	4	[94]	RETURN   	0 0
	5	[94]	RETURN   	0 1

function <./socket/http.lua:96,100> (24 instructions, 96 bytes at 0x7fc2f1c08db0)
3 params, 9 slots, 2 upvalues, 4 locals, 6 constants, 0 functions
	1	[97]	TEST     	1 0 1
	2	[97]	JMP      	5	; to 8
	3	[97]	GETUPVAL 	3 0	; sock
	4	[97]	SELF     	3 3 -1	; "send"
	5	[97]	LOADK    	5 -2	; "0\r\n\r\n"
	6	[97]	TAILCALL 	3 3 0
	7	[97]	RETURN   	3 0
	8	[98]	GETUPVAL 	3 1	; string
	9	[98]	GETTABLE 	3 3 -3	; "format"
	10	[98]	LOADK    	4 -4	; "%X\r\n"
	11	[98]	GETUPVAL 	5 1	; string
	12	[98]	GETTABLE 	5 5 -5	; "len"
	13	[98]	MOVE     	6 1
	14	[98]	CALL     	5 2 0
	15	[98]	CALL     	3 0 2
	16	[99]	GETUPVAL 	4 0	; sock
	17	[99]	SELF     	4 4 -1	; "send"
	18	[99]	MOVE     	6 3
	19	[99]	MOVE     	7 1
	20	[99]	LOADK    	8 -6	; "\r\n"
	21	[99]	CONCAT   	6 6 8
	22	[99]	TAILCALL 	4 3 0
	23	[99]	RETURN   	4 0
	24	[100]	RETURN   	0 1

function <./socket/http.lua:109,120> (37 instructions, 148 bytes at 0x7fc2f1c08c80)
3 params, 10 slots, 4 upvalues, 5 locals, 9 constants, 1 function
	1	[111]	GETUPVAL 	3 0	; socket
	2	[111]	GETTABLE 	3 3 -1	; "try"
	3	[111]	TESTSET  	4 2 1
	4	[111]	JMP      	2	; to 7
	5	[111]	GETUPVAL 	4 0	; socket
	6	[111]	GETTABLE 	4 4 -2	; "tcp"
	7	[111]	CALL     	4 1 0
	8	[111]	CALL     	3 0 2
	9	[112]	GETUPVAL 	4 1	; base
	10	[112]	GETTABLE 	4 4 -3	; "setmetatable"
	11	[112]	NEWTABLE 	5 0 1
	12	[112]	SETTABLE 	5 -4 3	; "c" -
	13	[112]	GETUPVAL 	6 2	; metat
	14	[112]	CALL     	4 3 2
	15	[114]	GETUPVAL 	5 0	; socket
	16	[114]	GETTABLE 	5 5 -5	; "newtry"
	17	[114]	CLOSURE  	6 0	; 0x7fc2f1c088b0
	18	[114]	MOVE     	0 4
	19	[114]	CALL     	5 2 2
	20	[114]	SETTABLE 	4 -1 5	; "try" -
	21	[116]	GETTABLE 	5 4 -1	; "try"
	22	[116]	SELF     	6 3 -6	; "settimeout"
	23	[116]	GETUPVAL 	8 3	; _M
	24	[116]	GETTABLE 	8 8 -7	; "TIMEOUT"
	25	[116]	CALL     	6 3 0
	26	[116]	CALL     	5 0 1
	27	[117]	GETTABLE 	5 4 -1	; "try"
	28	[117]	SELF     	6 3 -8	; "connect"
	29	[117]	MOVE     	8 0
	30	[117]	TESTSET  	9 1 1
	31	[117]	JMP      	2	; to 34
	32	[117]	GETUPVAL 	9 3	; _M
	33	[117]	GETTABLE 	9 9 -9	; "PORT"
	34	[117]	CALL     	6 4 0
	35	[117]	CALL     	5 0 1
	36	[119]	RETURN   	4 2
	37	[120]	RETURN   	0 1

function <./socket/http.lua:114,114> (4 instructions, 16 bytes at 0x7fc2f1c088b0)
0 params, 2 slots, 1 upvalue, 0 locals, 1 constant, 0 functions
	1	[114]	GETUPVAL 	0 0	; h
	2	[114]	SELF     	0 0 -1	; "close"
	3	[114]	CALL     	0 2 1
	4	[114]	RETURN   	0 1

function <./socket/http.lua:122,125> (16 instructions, 64 bytes at 0x7fc2f1c09720)
3 params, 8 slots, 1 upvalue, 4 locals, 6 constants, 0 functions
	1	[123]	GETUPVAL 	3 0	; string
	2	[123]	GETTABLE 	3 3 -1	; "format"
	3	[123]	LOADK    	4 -2	; "%s %s HTTP/1.1\r\n"
	4	[123]	TESTSET  	5 1 1
	5	[123]	JMP      	1	; to 7
	6	[123]	LOADK    	5 -3	; "GET"
	7	[123]	MOVE     	6 2
	8	[123]	CALL     	3 4 2
	9	[124]	GETTABLE 	4 0 -4	; "try"
	10	[124]	GETTABLE 	5 0 -5	; "c"
	11	[124]	SELF     	5 5 -6	; "send"
	12	[124]	MOVE     	7 3
	13	[124]	CALL     	5 3 0
	14	[124]	TAILCALL 	4 0 0
	15	[124]	RETURN   	4 0
	16	[125]	RETURN   	0 1

function <./socket/http.lua:127,135> (28 instructions, 112 bytes at 0x7fc2f1c09a00)
2 params, 14 slots, 2 upvalues, 9 locals, 8 constants, 0 functions
	1	[128]	GETUPVAL 	2 0	; headers
	2	[128]	GETTABLE 	2 2 -1	; "canonic"
	3	[129]	LOADK    	3 -2	; "\r\n"
	4	[130]	GETUPVAL 	4 1	; base
	5	[130]	GETTABLE 	4 4 -3	; "pairs"
	6	[130]	MOVE     	5 1
	7	[130]	CALL     	4 2 4
	8	[130]	JMP      	9	; to 18
	9	[131]	GETTABLE 	9 2 7
	10	[131]	TEST     	9 0 1
	11	[131]	JMP      	1	; to 13
	12	[131]	MOVE     	9 7
	13	[131]	LOADK    	10 -4	; ": "
	14	[131]	MOVE     	11 8
	15	[131]	LOADK    	12 -2	; "\r\n"
	16	[131]	MOVE     	13 3
	17	[131]	CONCAT   	3 9 13
	18	[130]	TFORLOOP 	4 2
	19	[131]	JMP      	-11	; to 9
	20	[133]	GETTABLE 	4 0 -5	; "try"
	21	[133]	GETTABLE 	5 0 -6	; "c"
	22	[133]	SELF     	5 5 -7	; "send"
	23	[133]	MOVE     	7 3
	24	[133]	CALL     	5 3 0
	25	[133]	CALL     	4 0 1
	26	[134]	LOADK    	4 -8	; 1
	27	[134]	RETURN   	4 2
	28	[135]	RETURN   	0 1

function <./socket/http.lua:137,144> (32 instructions, 128 bytes at 0x7fc2f1c0a0f0)
4 params, 11 slots, 2 upvalues, 5 locals, 11 constants, 0 functions
	1	[138]	TEST     	2 0 1
	2	[138]	JMP      	5	; to 8
	3	[138]	GETUPVAL 	4 0	; ltn12
	4	[138]	GETTABLE 	4 4 -1	; "source"
	5	[138]	GETTABLE 	4 4 -2	; "empty"
	6	[138]	CALL     	4 1 2
	7	[138]	MOVE     	2 4
	8	[139]	TEST     	3 0 1
	9	[139]	JMP      	3	; to 13
	10	[139]	GETUPVAL 	4 0	; ltn12
	11	[139]	GETTABLE 	4 4 -3	; "pump"
	12	[139]	GETTABLE 	3 4 -4	; "step"
	13	[141]	LOADK    	4 -5	; "http-chunked"
	14	[142]	GETTABLE 	5 1 -6	; "content-length"
	15	[142]	TEST     	5 0 0
	16	[142]	JMP      	1	; to 18
	17	[142]	LOADK    	4 -7	; "keep-open"
	18	[143]	GETTABLE 	5 0 -8	; "try"
	19	[143]	GETUPVAL 	6 0	; ltn12
	20	[143]	GETTABLE 	6 6 -3	; "pump"
	21	[143]	GETTABLE 	6 6 -9	; "all"
	22	[143]	MOVE     	7 2
	23	[143]	GETUPVAL 	8 1	; socket
	24	[143]	GETTABLE 	8 8 -10	; "sink"
	25	[143]	MOVE     	9 4
	26	[143]	GETTABLE 	10 0 -11	; "c"
	27	[143]	CALL     	8 3 2
	28	[143]	MOVE     	9 3
	29	[143]	CALL     	6 4 0
	30	[143]	TAILCALL 	5 0 0
	31	[143]	RETURN   	5 0
	32	[144]	RETURN   	0 1

function <./socket/http.lua:146,155> (37 instructions, 148 bytes at 0x7fc2f1c0a450)
1 param, 7 slots, 3 upvalues, 3 locals, 11 constants, 0 functions
	1	[147]	GETTABLE 	1 0 -1	; "try"
	2	[147]	GETTABLE 	2 0 -2	; "c"
	3	[147]	SELF     	2 2 -3	; "receive"
	4	[147]	LOADK    	4 -4	; 5
	5	[147]	CALL     	2 3 0
	6	[147]	CALL     	1 0 2
	7	[150]	EQ       	1 1 -5	; - "HTTP/"
	8	[150]	JMP      	3	; to 12
	9	[150]	LOADNIL  	2 2
	10	[150]	MOVE     	3 1
	11	[150]	RETURN   	2 3
	12	[152]	GETTABLE 	2 0 -1	; "try"
	13	[152]	GETTABLE 	3 0 -2	; "c"
	14	[152]	SELF     	3 3 -3	; "receive"
	15	[152]	LOADK    	5 -6	; "*l"
	16	[152]	MOVE     	6 1
	17	[152]	CALL     	3 4 0
	18	[152]	CALL     	2 0 2
	19	[152]	MOVE     	1 2
	20	[153]	GETUPVAL 	2 0	; socket
	21	[153]	GETTABLE 	2 2 -7	; "skip"
	22	[153]	LOADK    	3 -8	; 2
	23	[153]	GETUPVAL 	4 1	; string
	24	[153]	GETTABLE 	4 4 -9	; "find"
	25	[153]	MOVE     	5 1
	26	[153]	LOADK    	6 -10	; "HTTP/%d*%.%d* (%d%d%d)"
	27	[153]	CALL     	4 3 0
	28	[153]	CALL     	2 0 2
	29	[154]	GETTABLE 	3 0 -1	; "try"
	30	[154]	GETUPVAL 	4 2	; base
	31	[154]	GETTABLE 	4 4 -11	; "tonumber"
	32	[154]	MOVE     	5 2
	33	[154]	CALL     	4 2 2
	34	[154]	MOVE     	5 1
	35	[154]	TAILCALL 	3 3 0
	36	[154]	RETURN   	3 0
	37	[155]	RETURN   	0 1

function <./socket/http.lua:157,159> (7 instructions, 28 bytes at 0x7fc2f1c0a6b0)
1 param, 4 slots, 1 upvalue, 1 local, 2 constants, 0 functions
	1	[158]	GETTABLE 	1 0 -1	; "try"
	2	[158]	GETUPVAL 	2 0	; receiveheaders
	3	[158]	GETTABLE 	3 0 -2	; "c"
	4	[158]	CALL     	2 2 0
	5	[158]	TAILCALL 	1 0 0
	6	[158]	RETURN   	1 0
	7	[159]	RETURN   	0 1

function <./socket/http.lua:161,171> (47 instructions, 188 bytes at 0x7fc2f1c0af50)
4 params, 13 slots, 3 upvalues, 7 locals, 15 constants, 0 functions
	1	[162]	TEST     	2 0 1
	2	[162]	JMP      	5	; to 8
	3	[162]	GETUPVAL 	4 0	; ltn12
	4	[162]	GETTABLE 	4 4 -1	; "sink"
	5	[162]	GETTABLE 	4 4 -2	; "null"
	6	[162]	CALL     	4 1 2
	7	[162]	MOVE     	2 4
	8	[163]	TEST     	3 0 1
	9	[163]	JMP      	3	; to 13
	10	[163]	GETUPVAL 	4 0	; ltn12
	11	[163]	GETTABLE 	4 4 -3	; "pump"
	12	[163]	GETTABLE 	3 4 -4	; "step"
	13	[164]	GETUPVAL 	4 1	; base
	14	[164]	GETTABLE 	4 4 -5	; "tonumber"
	15	[164]	GETTABLE 	5 1 -6	; "content-length"
	16	[164]	CALL     	4 2 2
	17	[165]	GETTABLE 	5 1 -7	; "transfer-encoding"
	18	[166]	LOADK    	6 -8	; "default"
	19	[167]	TEST     	5 0 0
	20	[167]	JMP      	4	; to 25
	21	[167]	EQ       	1 5 -9	; - "identity"
	22	[167]	JMP      	2	; to 25
	23	[167]	LOADK    	6 -10	; "http-chunked"
	24	[167]	JMP      	7	; to 32
	25	[168]	GETUPVAL 	7 1	; base
	26	[168]	GETTABLE 	7 7 -5	; "tonumber"
	27	[168]	GETTABLE 	8 1 -6	; "content-length"
	28	[168]	CALL     	7 2 2
	29	[168]	TEST     	7 0 0
	30	[168]	JMP      	1	; to 32
	31	[168]	LOADK    	6 -11	; "by-length"
	32	[169]	GETTABLE 	7 0 -12	; "try"
	33	[169]	GETUPVAL 	8 0	; ltn12
	34	[169]	GETTABLE 	8 8 -3	; "pump"
	35	[169]	GETTABLE 	8 8 -13	; "all"
	36	[169]	GETUPVAL 	9 2	; socket
	37	[169]	GETTABLE 	9 9 -14	; "source"
	38	[169]	MOVE     	10 6
	39	[169]	GETTABLE 	11 0 -15	; "c"
	40	[169]	MOVE     	12 4
	41	[169]	CALL     	9 4 2
	42	[170]	MOVE     	10 2
	43	[170]	MOVE     	11 3
	44	[169]	CALL     	8 4 0
	45	[169]	TAILCALL 	7 0 0
	46	[170]	RETURN   	7 0
	47	[171]	RETURN   	0 1

function <./socket/http.lua:173,177> (23 instructions, 92 bytes at 0x7fc2f1c0b650)
4 params, 10 slots, 2 upvalues, 5 locals, 7 constants, 0 functions
	1	[174]	GETUPVAL 	4 0	; ltn12
	2	[174]	GETTABLE 	4 4 -1	; "source"
	3	[174]	GETTABLE 	4 4 -2	; "rewind"
	4	[174]	GETUPVAL 	5 1	; socket
	5	[174]	GETTABLE 	5 5 -1	; "source"
	6	[174]	LOADK    	6 -3	; "until-closed"
	7	[174]	GETTABLE 	7 0 -4	; "c"
	8	[174]	CALL     	5 3 0
	9	[174]	CALL     	4 0 2
	10	[175]	MOVE     	5 4
	11	[175]	MOVE     	6 1
	12	[175]	CALL     	5 2 1
	13	[176]	GETTABLE 	5 0 -5	; "try"
	14	[176]	GETUPVAL 	6 0	; ltn12
	15	[176]	GETTABLE 	6 6 -6	; "pump"
	16	[176]	GETTABLE 	6 6 -7	; "all"
	17	[176]	MOVE     	7 4
	18	[176]	MOVE     	8 2
	19	[176]	MOVE     	9 3
	20	[176]	CALL     	6 4 0
	21	[176]	TAILCALL 	5 0 0
	22	[176]	RETURN   	5 0
	23	[177]	RETURN   	0 1

function <./socket/http.lua:179,181> (5 instructions, 20 bytes at 0x7fc2f1c0b990)
1 param, 3 slots, 0 upvalues, 1 local, 2 constants, 0 functions
	1	[180]	GETTABLE 	1 0 -1	; "c"
	2	[180]	SELF     	1 1 -2	; "close"
	3	[180]	TAILCALL 	1 2 0
	4	[180]	RETURN   	1 0
	5	[181]	RETURN   	0 1

function <./socket/http.lua:186,198> (27 instructions, 108 bytes at 0x7fc2f1c0ba10)
1 param, 6 slots, 2 upvalues, 2 locals, 9 constants, 0 functions
	1	[187]	MOVE     	1 0
	2	[189]	GETTABLE 	2 0 -1	; "proxy"
	3	[189]	TEST     	2 0 1
	4	[189]	JMP      	17	; to 22
	5	[189]	GETGLOBAL	2 -2	; PROXY
	6	[189]	TEST     	2 0 1
	7	[189]	JMP      	14	; to 22
	8	[190]	NEWTABLE 	2 0 4
	9	[191]	GETUPVAL 	3 0	; socket
	10	[191]	GETTABLE 	3 3 -4	; "try"
	11	[191]	GETTABLE 	4 0 -3	; "path"
	12	[191]	LOADK    	5 -5	; "invalid path 'nil'"
	13	[191]	CALL     	3 3 2
	14	[191]	SETTABLE 	2 -3 3	; "path" -
	15	[192]	GETTABLE 	3 0 -6	; "params"
	16	[192]	SETTABLE 	2 -6 3	; "params" -
	17	[193]	GETTABLE 	3 0 -7	; "query"
	18	[193]	SETTABLE 	2 -7 3	; "query" -
	19	[194]	GETTABLE 	3 0 -8	; "fragment"
	20	[194]	SETTABLE 	2 -8 3	; "fragment" -
	21	[195]	MOVE     	1 2
	22	[197]	GETUPVAL 	2 1	; url
	23	[197]	GETTABLE 	2 2 -9	; "build"
	24	[197]	MOVE     	3 1
	25	[197]	TAILCALL 	2 2 0
	26	[197]	RETURN   	2 0
	27	[198]	RETURN   	0 1

function <./socket/http.lua:200,208> (22 instructions, 88 bytes at 0x7fc2f1c0be60)
1 param, 4 slots, 1 upvalue, 2 locals, 6 constants, 0 functions
	1	[201]	GETTABLE 	1 0 -1	; "proxy"
	2	[201]	TEST     	1 0 1
	3	[201]	JMP      	1	; to 5
	4	[201]	GETGLOBAL	1 -2	; PROXY
	5	[202]	TEST     	1 0 0
	6	[202]	JMP      	12	; to 19
	7	[203]	GETUPVAL 	2 0	; url
	8	[203]	GETTABLE 	2 2 -3	; "parse"
	9	[203]	MOVE     	3 1
	10	[203]	CALL     	2 2 2
	11	[203]	MOVE     	1 2
	12	[204]	GETTABLE 	2 1 -4	; "host"
	13	[204]	GETTABLE 	3 1 -5	; "port"
	14	[204]	TEST     	3 0 1
	15	[204]	JMP      	1	; to 17
	16	[204]	LOADK    	3 -6	; 3128
	17	[204]	RETURN   	2 3
	18	[204]	JMP      	3	; to 22
	19	[206]	GETTABLE 	2 0 -4	; "host"
	20	[206]	GETTABLE 	3 0 -5	; "port"
	21	[206]	RETURN   	2 3
	22	[208]	RETURN   	0 1

function <./socket/http.lua:210,228> (41 instructions, 164 bytes at 0x7fc2f1c0c670)
1 param, 9 slots, 4 upvalues, 7 locals, 16 constants, 0 functions
	1	[212]	NEWTABLE 	1 0 4
	2	[213]	GETUPVAL 	2 0	; _M
	3	[213]	GETTABLE 	2 2 -2	; "USERAGENT"
	4	[213]	SETTABLE 	1 -1 2	; "user-agent" -
	5	[214]	GETTABLE 	2 0 -3	; "host"
	6	[214]	SETTABLE 	1 -3 2	; "host" -
	7	[215]	SETTABLE 	1 -4 -5	; "connection" "close, TE"
	8	[216]	SETTABLE 	1 -6 -7	; "te" "trailers"
	9	[219]	GETTABLE 	2 0 -8	; "user"
	10	[219]	TEST     	2 0 0
	11	[219]	JMP      	13	; to 25
	12	[219]	GETTABLE 	2 0 -9	; "password"
	13	[219]	TEST     	2 0 0
	14	[219]	JMP      	10	; to 25
	15	[221]	LOADK    	2 -11	; "Basic "
	16	[221]	GETUPVAL 	3 1	; mime
	17	[221]	GETTABLE 	3 3 -12	; "b64"
	18	[221]	GETTABLE 	4 0 -8	; "user"
	19	[221]	LOADK    	5 -13	; ":"
	20	[221]	GETTABLE 	6 0 -9	; "password"
	21	[221]	CONCAT   	4 4 6
	22	[221]	CALL     	3 2 2
	23	[221]	CONCAT   	2 2 3
	24	[221]	SETTABLE 	1 -10 2	; "authorization" -
	25	[224]	GETUPVAL 	2 2	; base
	26	[224]	GETTABLE 	2 2 -14	; "pairs"
	27	[224]	GETTABLE 	3 0 -15	; "headers"
	28	[224]	TEST     	3 0 1
	29	[224]	JMP      	1	; to 31
	30	[224]	MOVE     	3 1
	31	[224]	CALL     	2 2 4
	32	[224]	JMP      	5	; to 38
	33	[225]	GETUPVAL 	7 3	; string
	34	[225]	GETTABLE 	7 7 -16	; "lower"
	35	[225]	MOVE     	8 5
	36	[225]	CALL     	7 2 2
	37	[225]	SETTABLE 	1 7 6
	38	[224]	TFORLOOP 	2 2
	39	[225]	JMP      	-7	; to 33
	40	[227]	RETURN   	1 2
	41	[228]	RETURN   	0 1

function <./socket/http.lua:238,253> (59 instructions, 236 bytes at 0x7fc2f1c0c760)
1 param, 8 slots, 7 upvalues, 7 locals, 13 constants, 0 functions
	1	[240]	GETTABLE 	1 0 -1	; "url"
	2	[240]	TEST     	1 0 0
	3	[240]	JMP      	7	; to 11
	4	[240]	GETUPVAL 	1 0	; url
	5	[240]	GETTABLE 	1 1 -2	; "parse"
	6	[240]	GETTABLE 	2 0 -1	; "url"
	7	[240]	GETUPVAL 	3 1	; default
	8	[240]	CALL     	1 3 2
	9	[240]	TEST     	1 0 1
	10	[240]	JMP      	1	; to 12
	11	[240]	NEWTABLE 	1 0 0
	12	[242]	GETUPVAL 	2 2	; base
	13	[242]	GETTABLE 	2 2 -3	; "pairs"
	14	[242]	MOVE     	3 0
	15	[242]	CALL     	2 2 4
	16	[242]	JMP      	1	; to 18
	17	[242]	SETTABLE 	1 5 6
	18	[242]	TFORLOOP 	2 2
	19	[242]	JMP      	-3	; to 17
	20	[243]	GETTABLE 	2 1 -4	; "port"
	21	[243]	EQ       	0 2 -5	; - ""
	22	[243]	JMP      	1	; to 24
	23	[243]	SETTABLE 	1 -4 -6	; "port" 80
	24	[244]	GETUPVAL 	2 3	; socket
	25	[244]	GETTABLE 	2 2 -7	; "try"
	26	[244]	GETTABLE 	3 1 -8	; "host"
	27	[244]	TEST     	3 0 0
	28	[244]	JMP      	5	; to 34
	29	[244]	GETTABLE 	3 1 -8	; "host"
	30	[244]	EQ       	0 3 -5	; - ""
	31	[244]	JMP      	1	; to 33
	32	[244]	LOADBOOL 	3 0 1
	33	[244]	LOADBOOL 	3 1 0
	34	[245]	LOADK    	4 -9	; "invalid host '"
	35	[245]	GETUPVAL 	5 2	; base
	36	[245]	GETTABLE 	5 5 -10	; "tostring"
	37	[245]	GETTABLE 	6 1 -8	; "host"
	38	[245]	CALL     	5 2 2
	39	[245]	LOADK    	6 -11	; "'"
	40	[245]	CONCAT   	4 4 6
	41	[244]	CALL     	2 3 1
	42	[247]	GETTABLE 	2 0 -12	; "uri"
	43	[247]	TEST     	2 0 1
	44	[247]	JMP      	3	; to 48
	45	[247]	GETUPVAL 	2 4	; adjusturi
	46	[247]	MOVE     	3 1
	47	[247]	CALL     	2 2 2
	48	[247]	SETTABLE 	1 -12 2	; "uri" -
	49	[249]	GETUPVAL 	2 5	; adjustproxy
	50	[249]	MOVE     	3 1
	51	[249]	CALL     	2 2 3
	52	[249]	SETTABLE 	1 -4 3	; "port" -
	53	[249]	SETTABLE 	1 -8 2	; "host" -
	54	[251]	GETUPVAL 	2 6	; adjustheaders
	55	[251]	MOVE     	3 1
	56	[251]	CALL     	2 2 2
	57	[251]	SETTABLE 	1 -13 2	; "headers" -
	58	[252]	RETURN   	1 2
	59	[253]	RETURN   	0 1

function <./socket/http.lua:255,262> (41 instructions, 164 bytes at 0x7fc2f1c09140)
3 params, 7 slots, 1 upvalue, 3 locals, 15 constants, 0 functions
	1	[256]	GETTABLE 	3 2 -1	; "location"
	2	[256]	TEST     	3 0 0
	3	[256]	JMP      	36	; to 40
	4	[257]	GETUPVAL 	3 0	; string
	5	[257]	GETTABLE 	3 3 -2	; "gsub"
	6	[257]	GETTABLE 	4 2 -1	; "location"
	7	[257]	LOADK    	5 -3	; "%s"
	8	[257]	LOADK    	6 -4	; ""
	9	[257]	CALL     	3 4 2
	10	[257]	EQ       	1 3 -4	; - ""
	11	[257]	JMP      	26	; to 38
	12	[258]	GETTABLE 	3 0 -5	; "redirect"
	13	[258]	EQ       	1 3 -6	; - false
	14	[258]	JMP      	23	; to 38
	15	[259]	EQ       	1 1 -7	; - 301
	16	[259]	JMP      	6	; to 23
	17	[259]	EQ       	1 1 -8	; - 302
	18	[259]	JMP      	4	; to 23
	19	[259]	EQ       	1 1 -9	; - 303
	20	[259]	JMP      	2	; to 23
	21	[259]	EQ       	0 1 -10	; - 307
	22	[259]	JMP      	15	; to 38
	23	[260]	GETTABLE 	3 0 -11	; "method"
	24	[260]	TEST     	3 0 0
	25	[260]	JMP      	6	; to 32
	26	[260]	GETTABLE 	3 0 -11	; "method"
	27	[260]	EQ       	1 3 -12	; - "GET"
	28	[260]	JMP      	3	; to 32
	29	[260]	GETTABLE 	3 0 -11	; "method"
	30	[260]	EQ       	0 3 -13	; - "HEAD"
	31	[260]	JMP      	6	; to 38
	32	[261]	GETTABLE 	3 0 -14	; "nredirects"
	33	[261]	TEST     	3 0 0
	34	[261]	JMP      	4	; to 39
	35	[261]	GETTABLE 	3 0 -14	; "nredirects"
	36	[261]	LT       	1 3 -15	; - 5
	37	[261]	JMP      	1	; to 39
	38	[261]	LOADBOOL 	3 0 1
	39	[261]	LOADBOOL 	3 1 0
	40	[261]	RETURN   	3 2
	41	[262]	RETURN   	0 1

function <./socket/http.lua:264,269> (20 instructions, 80 bytes at 0x7fc2f1c0aed0)
2 params, 3 slots, 0 upvalues, 2 locals, 7 constants, 0 functions
	1	[265]	GETTABLE 	2 0 -1	; "method"
	2	[265]	EQ       	0 2 -2	; - "HEAD"
	3	[265]	JMP      	2	; to 6
	4	[265]	LOADNIL  	2 2
	5	[265]	RETURN   	2 2
	6	[266]	EQ       	1 1 -3	; - 204
	7	[266]	JMP      	2	; to 10
	8	[266]	EQ       	0 1 -4	; - 304
	9	[266]	JMP      	2	; to 12
	10	[266]	LOADNIL  	2 2
	11	[266]	RETURN   	2 2
	12	[267]	LE       	0 -5 1	; 100 -
	13	[267]	JMP      	4	; to 18
	14	[267]	LT       	0 1 -6	; - 200
	15	[267]	JMP      	2	; to 18
	16	[267]	LOADNIL  	2 2
	17	[267]	RETURN   	2 2
	18	[268]	LOADK    	2 -7	; 1
	19	[268]	RETURN   	2 2
	20	[269]	RETURN   	0 1

function <./socket/http.lua:274,290> (40 instructions, 160 bytes at 0x7fc2f1c071d0)
2 params, 10 slots, 2 upvalues, 6 locals, 11 constants, 0 functions
	1	[275]	GETUPVAL 	2 0	; trequest
	2	[275]	NEWTABLE 	3 0 7
	3	[278]	GETUPVAL 	4 1	; url
	4	[278]	GETTABLE 	4 4 -2	; "absolute"
	5	[278]	GETTABLE 	5 0 -1	; "url"
	6	[278]	MOVE     	6 1
	7	[278]	CALL     	4 3 2
	8	[278]	SETTABLE 	3 -1 4	; "url" -
	9	[279]	GETTABLE 	4 0 -3	; "source"
	10	[279]	SETTABLE 	3 -3 4	; "source" -
	11	[280]	GETTABLE 	4 0 -4	; "sink"
	12	[280]	SETTABLE 	3 -4 4	; "sink" -
	13	[281]	GETTABLE 	4 0 -5	; "headers"
	14	[281]	SETTABLE 	3 -5 4	; "headers" -
	15	[282]	GETTABLE 	4 0 -6	; "proxy"
	16	[282]	SETTABLE 	3 -6 4	; "proxy" -
	17	[283]	GETTABLE 	4 0 -7	; "nredirects"
	18	[283]	TEST     	4 0 1
	19	[283]	JMP      	1	; to 21
	20	[283]	LOADK    	4 -8	; 0
	21	[283]	ADD      	4 4 -9	; - 1
	22	[283]	SETTABLE 	3 -7 4	; "nredirects" -
	23	[284]	GETTABLE 	4 0 -10	; "create"
	24	[284]	SETTABLE 	3 -10 4	; "create" -
	25	[275]	CALL     	2 2 5
	26	[287]	TEST     	4 0 1
	27	[287]	JMP      	2	; to 30
	28	[287]	NEWTABLE 	6 0 0
	29	[287]	MOVE     	4 6
	30	[288]	GETTABLE 	6 4 -11	; "location"
	31	[288]	TEST     	6 0 1
	32	[288]	JMP      	1	; to 34
	33	[288]	MOVE     	6 1
	34	[288]	SETTABLE 	4 -11 6	; "location" -
	35	[289]	MOVE     	6 2
	36	[289]	MOVE     	7 3
	37	[289]	MOVE     	8 4
	38	[289]	MOVE     	9 5
	39	[289]	RETURN   	6 5
	40	[290]	RETURN   	0 1

function <./socket/http.lua:292,329> (86 instructions, 344 bytes at 0x7fc2f1c0cdf0)
1 param, 11 slots, 5 upvalues, 6 locals, 22 constants, 0 functions
	1	[295]	GETUPVAL 	1 0	; adjustrequest
	2	[295]	MOVE     	2 0
	3	[295]	CALL     	1 2 2
	4	[296]	GETUPVAL 	2 1	; _M
	5	[296]	GETTABLE 	2 2 -1	; "open"
	6	[296]	GETTABLE 	3 1 -2	; "host"
	7	[296]	GETTABLE 	4 1 -3	; "port"
	8	[296]	GETTABLE 	5 1 -4	; "create"
	9	[296]	CALL     	2 4 2
	10	[298]	SELF     	3 2 -5	; "sendrequestline"
	11	[298]	GETTABLE 	5 1 -6	; "method"
	12	[298]	GETTABLE 	6 1 -7	; "uri"
	13	[298]	CALL     	3 4 1
	14	[299]	SELF     	3 2 -8	; "sendheaders"
	15	[299]	GETTABLE 	5 1 -9	; "headers"
	16	[299]	CALL     	3 3 1
	17	[301]	GETTABLE 	3 1 -10	; "source"
	18	[301]	TEST     	3 0 0
	19	[301]	JMP      	5	; to 25
	20	[302]	SELF     	3 2 -11	; "sendbody"
	21	[302]	GETTABLE 	5 1 -9	; "headers"
	22	[302]	GETTABLE 	6 1 -10	; "source"
	23	[302]	GETTABLE 	7 1 -12	; "step"
	24	[302]	CALL     	3 5 1
	25	[304]	SELF     	3 2 -13	; "receivestatusline"
	26	[304]	CALL     	3 2 3
	27	[306]	TEST     	3 0 1
	28	[306]	JMP      	8	; to 37
	29	[307]	SELF     	5 2 -14	; "receive09body"
	30	[307]	MOVE     	7 4
	31	[307]	GETTABLE 	8 1 -15	; "sink"
	32	[307]	GETTABLE 	9 1 -12	; "step"
	33	[307]	CALL     	5 5 1
	34	[308]	LOADK    	5 -16	; 1
	35	[308]	LOADK    	6 -17	; 200
	36	[308]	RETURN   	5 3
	37	[310]	LOADNIL  	5 5
	38	[312]	EQ       	0 3 -18	; - 100
	39	[312]	JMP      	8	; to 48
	40	[313]	SELF     	6 2 -19	; "receiveheaders"
	41	[313]	CALL     	6 2 2
	42	[313]	MOVE     	5 6
	43	[314]	SELF     	6 2 -13	; "receivestatusline"
	44	[314]	CALL     	6 2 3
	45	[314]	MOVE     	4 7
	46	[314]	MOVE     	3 6
	47	[314]	JMP      	-10	; to 38
	48	[316]	SELF     	6 2 -19	; "receiveheaders"
	49	[316]	CALL     	6 2 2
	50	[316]	MOVE     	5 6
	51	[319]	GETUPVAL 	6 2	; shouldredirect
	52	[319]	MOVE     	7 1
	53	[319]	MOVE     	8 3
	54	[319]	MOVE     	9 5
	55	[319]	CALL     	6 4 2
	56	[319]	TEST     	6 0 0
	57	[319]	JMP      	10	; to 68
	58	[319]	GETTABLE 	6 1 -10	; "source"
	59	[319]	TEST     	6 0 1
	60	[319]	JMP      	7	; to 68
	61	[320]	SELF     	6 2 -20	; "close"
	62	[320]	CALL     	6 2 1
	63	[321]	GETUPVAL 	6 3	; tredirect
	64	[321]	MOVE     	7 0
	65	[321]	GETTABLE 	8 5 -21	; "location"
	66	[321]	TAILCALL 	6 3 0
	67	[321]	RETURN   	6 0
	68	[324]	GETUPVAL 	6 4	; shouldreceivebody
	69	[324]	MOVE     	7 1
	70	[324]	MOVE     	8 3
	71	[324]	CALL     	6 3 2
	72	[324]	TEST     	6 0 0
	73	[324]	JMP      	5	; to 79
	74	[325]	SELF     	6 2 -22	; "receivebody"
	75	[325]	MOVE     	8 5
	76	[325]	GETTABLE 	9 1 -15	; "sink"
	77	[325]	GETTABLE 	10 1 -12	; "step"
	78	[325]	CALL     	6 5 1
	79	[327]	SELF     	6 2 -20	; "close"
	80	[327]	CALL     	6 2 1
	81	[328]	LOADK    	6 -16	; 1
	82	[328]	MOVE     	7 3
	83	[328]	MOVE     	8 5
	84	[328]	MOVE     	9 4
	85	[328]	RETURN   	6 5
	86	[329]	RETURN   	0 1

function <./socket/http.lua:331,347> (42 instructions, 168 bytes at 0x7fc2f1c0d5e0)
2 params, 11 slots, 5 upvalues, 7 locals, 15 constants, 0 functions
	1	[332]	NEWTABLE 	2 0 0
	2	[333]	NEWTABLE 	3 0 2
	3	[334]	SETTABLE 	3 -1 0	; "url" -
	4	[335]	GETUPVAL 	4 0	; ltn12
	5	[335]	GETTABLE 	4 4 -2	; "sink"
	6	[335]	GETTABLE 	4 4 -3	; "table"
	7	[335]	MOVE     	5 2
	8	[335]	CALL     	4 2 2
	9	[335]	SETTABLE 	3 -2 4	; "sink" -
	10	[337]	TEST     	1 0 0
	11	[337]	JMP      	15	; to 27
	12	[338]	GETUPVAL 	4 0	; ltn12
	13	[338]	GETTABLE 	4 4 -4	; "source"
	14	[338]	GETTABLE 	4 4 -5	; "string"
	15	[338]	MOVE     	5 1
	16	[338]	CALL     	4 2 2
	17	[338]	SETTABLE 	3 -4 4	; "source" -
	18	[339]	NEWTABLE 	4 0 2
	19	[340]	GETUPVAL 	5 1	; string
	20	[340]	GETTABLE 	5 5 -8	; "len"
	21	[340]	MOVE     	6 1
	22	[340]	CALL     	5 2 2
	23	[340]	SETTABLE 	4 -7 5	; "content-length" -
	24	[341]	SETTABLE 	4 -9 -10	; "content-type" "application/x-www-form-urlencoded"
	25	[342]	SETTABLE 	3 -6 4	; "headers" -
	26	[343]	SETTABLE 	3 -11 -12	; "method" "POST"
	27	[345]	GETUPVAL 	4 2	; socket
	28	[345]	GETTABLE 	4 4 -13	; "skip"
	29	[345]	LOADK    	5 -14	; 1
	30	[345]	GETUPVAL 	6 3	; trequest
	31	[345]	MOVE     	7 3
	32	[345]	CALL     	6 2 0
	33	[345]	CALL     	4 0 4
	34	[346]	GETUPVAL 	7 4	; table
	35	[346]	GETTABLE 	7 7 -15	; "concat"
	36	[346]	MOVE     	8 2
	37	[346]	CALL     	7 2 2
	38	[346]	MOVE     	8 4
	39	[346]	MOVE     	9 5
	40	[346]	MOVE     	10 6
	41	[346]	RETURN   	7 5
	42	[347]	RETURN   	0 1

function <./socket/http.lua:349,352> (17 instructions, 68 bytes at 0x7fc2f1c0dcc0)
2 params, 5 slots, 3 upvalues, 2 locals, 2 constants, 0 functions
	1	[350]	GETUPVAL 	2 0	; base
	2	[350]	GETTABLE 	2 2 -1	; "type"
	3	[350]	MOVE     	3 0
	4	[350]	CALL     	2 2 2
	5	[350]	EQ       	0 2 -2	; - "string"
	6	[350]	JMP      	6	; to 13
	7	[350]	GETUPVAL 	2 1	; srequest
	8	[350]	MOVE     	3 0
	9	[350]	MOVE     	4 1
	10	[350]	TAILCALL 	2 3 0
	11	[350]	RETURN   	2 0
	12	[350]	JMP      	4	; to 17
	13	[351]	GETUPVAL 	2 2	; trequest
	14	[351]	MOVE     	3 0
	15	[351]	TAILCALL 	2 2 0
	16	[351]	RETURN   	2 0
	17	[352]	RETURN   	0 1
