
main <./socket/smtp.lua:0,0> (141 instructions, 564 bytes at 0x7fce674068a0)
0+ params, 23 slots, 0 upvalues, 21 locals, 38 constants, 21 functions
	1	[10]	GETGLOBAL	0 -1	; _G
	2	[11]	GETGLOBAL	1 -2	; require
	3	[11]	LOADK    	2 -3	; "coroutine"
	4	[11]	CALL     	1 2 2
	5	[12]	GETGLOBAL	2 -2	; require
	6	[12]	LOADK    	3 -4	; "string"
	7	[12]	CALL     	2 2 2
	8	[13]	GETGLOBAL	3 -2	; require
	9	[13]	LOADK    	4 -5	; "math"
	10	[13]	CALL     	3 2 2
	11	[14]	GETGLOBAL	4 -2	; require
	12	[14]	LOADK    	5 -6	; "os"
	13	[14]	CALL     	4 2 2
	14	[15]	GETGLOBAL	5 -2	; require
	15	[15]	LOADK    	6 -7	; "socket"
	16	[15]	CALL     	5 2 2
	17	[16]	GETGLOBAL	6 -2	; require
	18	[16]	LOADK    	7 -8	; "socket.tp"
	19	[16]	CALL     	6 2 2
	20	[17]	GETGLOBAL	7 -2	; require
	21	[17]	LOADK    	8 -9	; "ltn12"
	22	[17]	CALL     	7 2 2
	23	[18]	GETGLOBAL	8 -2	; require
	24	[18]	LOADK    	9 -10	; "socket.headers"
	25	[18]	CALL     	8 2 2
	26	[19]	GETGLOBAL	9 -2	; require
	27	[19]	LOADK    	10 -11	; "mime"
	28	[19]	CALL     	9 2 2
	29	[21]	NEWTABLE 	10 0 0
	30	[21]	SETTABLE 	5 -12 10	; "smtp" -
	31	[22]	GETTABLE 	10 5 -12	; "smtp"
	32	[28]	SETTABLE 	10 -13 -14	; "TIMEOUT" 60
	33	[30]	SETTABLE 	10 -15 -16	; "SERVER" "localhost"
	34	[32]	SETTABLE 	10 -17 -18	; "PORT" 25
	35	[35]	GETTABLE 	11 4 -20	; "getenv"
	36	[35]	LOADK    	12 -21	; "SERVER_NAME"
	37	[35]	CALL     	11 2 2
	38	[35]	TEST     	11 0 1
	39	[35]	JMP      	1	; to 41
	40	[35]	LOADK    	11 -16	; "localhost"
	41	[35]	SETTABLE 	10 -19 11	; "DOMAIN" -
	42	[37]	SETTABLE 	10 -22 -23	; "ZONE" "-0000"
	43	[42]	NEWTABLE 	11 0 1
	44	[42]	NEWTABLE 	12 0 0
	45	[42]	SETTABLE 	11 -24 12	; "__index" -
	46	[44]	GETTABLE 	12 11 -24	; "__index"
	47	[48]	CLOSURE  	13 0	; 0x7fce67406c30
	48	[48]	MOVE     	0 10
	49	[48]	MOVE     	0 5
	50	[44]	SETTABLE 	12 -25 13	; "greet" -
	51	[50]	GETTABLE 	12 11 -24	; "__index"
	52	[53]	CLOSURE  	13 1	; 0x7fce67406680
	53	[50]	SETTABLE 	12 -26 13	; "mail" -
	54	[55]	GETTABLE 	12 11 -24	; "__index"
	55	[58]	CLOSURE  	13 2	; 0x7fce67407530
	56	[55]	SETTABLE 	12 -27 13	; "rcpt" -
	57	[60]	GETTABLE 	12 11 -24	; "__index"
	58	[66]	CLOSURE  	13 3	; 0x7fce67407f60
	59	[60]	SETTABLE 	12 -28 13	; "data" -
	60	[68]	GETTABLE 	12 11 -24	; "__index"
	61	[71]	CLOSURE  	13 4	; 0x7fce674084f0
	62	[68]	SETTABLE 	12 -29 13	; "quit" -
	63	[73]	GETTABLE 	12 11 -24	; "__index"
	64	[75]	CLOSURE  	13 5	; 0x7fce67408c30
	65	[73]	SETTABLE 	12 -30 13	; "close" -
	66	[77]	GETTABLE 	12 11 -24	; "__index"
	67	[84]	CLOSURE  	13 6	; 0x7fce67409010
	68	[84]	MOVE     	0 9
	69	[77]	SETTABLE 	12 -31 13	; "login" -
	70	[86]	GETTABLE 	12 11 -24	; "__index"
	71	[90]	CLOSURE  	13 7	; 0x7fce67406e50
	72	[90]	MOVE     	0 9
	73	[86]	SETTABLE 	12 -32 13	; "plain" -
	74	[92]	GETTABLE 	12 11 -24	; "__index"
	75	[101]	CLOSURE  	13 8	; 0x7fce67406ef0
	76	[101]	MOVE     	0 2
	77	[92]	SETTABLE 	12 -33 13	; "auth" -
	78	[104]	GETTABLE 	12 11 -24	; "__index"
	79	[114]	CLOSURE  	13 9	; 0x7fce67408f90
	80	[114]	MOVE     	0 0
	81	[114]	MOVE     	0 7
	82	[114]	MOVE     	0 9
	83	[104]	SETTABLE 	12 -34 13	; "send" -
	84	[125]	CLOSURE  	12 10	; 0x7fce67409830
	85	[125]	MOVE     	0 5
	86	[125]	MOVE     	0 6
	87	[125]	MOVE     	0 10
	88	[125]	MOVE     	0 0
	89	[125]	MOVE     	0 11
	90	[116]	SETTABLE 	10 -35 12	; "open" -
	91	[134]	CLOSURE  	12 11	; 0x7fce67409d90
	92	[134]	MOVE     	0 0
	93	[134]	MOVE     	0 2
	94	[140]	LOADK    	13 -36	; 0
	95	[145]	CLOSURE  	14 12	; 0x7fce6740a160
	96	[145]	MOVE     	0 13
	97	[145]	MOVE     	0 2
	98	[145]	MOVE     	0 4
	99	[145]	MOVE     	0 3
	100	[148]	LOADNIL  	15 15
	101	[158]	CLOSURE  	16 13	; 0x7fce6740a400
	102	[158]	MOVE     	0 8
	103	[158]	MOVE     	0 0
	104	[158]	MOVE     	0 1
	105	[186]	CLOSURE  	17 14	; 0x7fce6740ac00
	106	[186]	MOVE     	0 14
	107	[186]	MOVE     	0 12
	108	[186]	MOVE     	0 16
	109	[186]	MOVE     	0 1
	110	[186]	MOVE     	0 0
	111	[186]	MOVE     	0 15
	112	[202]	CLOSURE  	18 15	; 0x7fce6740adf0
	113	[202]	MOVE     	0 12
	114	[202]	MOVE     	0 16
	115	[202]	MOVE     	0 1
	116	[213]	CLOSURE  	19 16	; 0x7fce67409cf0
	117	[213]	MOVE     	0 12
	118	[213]	MOVE     	0 16
	119	[213]	MOVE     	0 1
	120	[220]	CLOSURE  	15 17	; 0x7fce67408d90
	121	[220]	MOVE     	0 0
	122	[220]	MOVE     	0 17
	123	[220]	MOVE     	0 18
	124	[216]	MOVE     	0 19
	125	[231]	CLOSURE  	20 18	; 0x7fce6740ba00
	126	[231]	MOVE     	0 12
	127	[231]	MOVE     	0 4
	128	[231]	MOVE     	0 10
	129	[231]	MOVE     	0 5
	130	[242]	CLOSURE  	21 19	; 0x7fce6740c080
	131	[242]	MOVE     	0 20
	132	[242]	MOVE     	0 1
	133	[242]	MOVE     	0 15
	134	[233]	SETTABLE 	10 -37 21	; "message" -
	135	[247]	GETTABLE 	21 5 -38	; "protect"
	136	[254]	CLOSURE  	22 20	; 0x7fce6740c760
	137	[254]	MOVE     	0 10
	138	[247]	CALL     	21 2 2
	139	[254]	SETTABLE 	10 -34 21	; "send" -
	140	[256]	RETURN   	10 2
	141	[256]	RETURN   	0 1

function <./socket/smtp.lua:44,48> (28 instructions, 112 bytes at 0x7fce67406c30)
2 params, 8 slots, 2 upvalues, 2 locals, 9 constants, 0 functions
	1	[45]	GETTABLE 	2 0 -1	; "try"
	2	[45]	GETTABLE 	3 0 -2	; "tp"
	3	[45]	SELF     	3 3 -3	; "check"
	4	[45]	LOADK    	5 -4	; "2.."
	5	[45]	CALL     	3 3 0
	6	[45]	CALL     	2 0 1
	7	[46]	GETTABLE 	2 0 -1	; "try"
	8	[46]	GETTABLE 	3 0 -2	; "tp"
	9	[46]	SELF     	3 3 -5	; "command"
	10	[46]	LOADK    	5 -6	; "EHLO"
	11	[46]	TESTSET  	6 1 1
	12	[46]	JMP      	2	; to 15
	13	[46]	GETUPVAL 	6 0	; _M
	14	[46]	GETTABLE 	6 6 -7	; "DOMAIN"
	15	[46]	CALL     	3 4 0
	16	[46]	CALL     	2 0 1
	17	[47]	GETUPVAL 	2 1	; socket
	18	[47]	GETTABLE 	2 2 -8	; "skip"
	19	[47]	LOADK    	3 -9	; 1
	20	[47]	GETTABLE 	4 0 -1	; "try"
	21	[47]	GETTABLE 	5 0 -2	; "tp"
	22	[47]	SELF     	5 5 -3	; "check"
	23	[47]	LOADK    	7 -4	; "2.."
	24	[47]	CALL     	5 3 0
	25	[47]	CALL     	4 0 0
	26	[47]	TAILCALL 	2 0 0
	27	[47]	RETURN   	2 0
	28	[48]	RETURN   	0 1

function <./socket/smtp.lua:50,53> (17 instructions, 68 bytes at 0x7fce67406680)
2 params, 8 slots, 0 upvalues, 2 locals, 7 constants, 0 functions
	1	[51]	GETTABLE 	2 0 -1	; "try"
	2	[51]	GETTABLE 	3 0 -2	; "tp"
	3	[51]	SELF     	3 3 -3	; "command"
	4	[51]	LOADK    	5 -4	; "MAIL"
	5	[51]	LOADK    	6 -5	; "FROM:"
	6	[51]	MOVE     	7 1
	7	[51]	CONCAT   	6 6 7
	8	[51]	CALL     	3 4 0
	9	[51]	CALL     	2 0 1
	10	[52]	GETTABLE 	2 0 -1	; "try"
	11	[52]	GETTABLE 	3 0 -2	; "tp"
	12	[52]	SELF     	3 3 -6	; "check"
	13	[52]	LOADK    	5 -7	; "2.."
	14	[52]	CALL     	3 3 0
	15	[52]	TAILCALL 	2 0 0
	16	[52]	RETURN   	2 0
	17	[53]	RETURN   	0 1

function <./socket/smtp.lua:55,58> (17 instructions, 68 bytes at 0x7fce67407530)
2 params, 8 slots, 0 upvalues, 2 locals, 7 constants, 0 functions
	1	[56]	GETTABLE 	2 0 -1	; "try"
	2	[56]	GETTABLE 	3 0 -2	; "tp"
	3	[56]	SELF     	3 3 -3	; "command"
	4	[56]	LOADK    	5 -4	; "RCPT"
	5	[56]	LOADK    	6 -5	; "TO:"
	6	[56]	MOVE     	7 1
	7	[56]	CONCAT   	6 6 7
	8	[56]	CALL     	3 4 0
	9	[56]	CALL     	2 0 1
	10	[57]	GETTABLE 	2 0 -1	; "try"
	11	[57]	GETTABLE 	3 0 -2	; "tp"
	12	[57]	SELF     	3 3 -6	; "check"
	13	[57]	LOADK    	5 -7	; "2.."
	14	[57]	CALL     	3 3 0
	15	[57]	TAILCALL 	2 0 0
	16	[57]	RETURN   	2 0
	17	[58]	RETURN   	0 1

function <./socket/smtp.lua:60,66> (33 instructions, 132 bytes at 0x7fce67407f60)
3 params, 8 slots, 0 upvalues, 3 locals, 10 constants, 0 functions
	1	[61]	GETTABLE 	3 0 -1	; "try"
	2	[61]	GETTABLE 	4 0 -2	; "tp"
	3	[61]	SELF     	4 4 -3	; "command"
	4	[61]	LOADK    	6 -4	; "DATA"
	5	[61]	CALL     	4 3 0
	6	[61]	CALL     	3 0 1
	7	[62]	GETTABLE 	3 0 -1	; "try"
	8	[62]	GETTABLE 	4 0 -2	; "tp"
	9	[62]	SELF     	4 4 -5	; "check"
	10	[62]	LOADK    	6 -6	; "3.."
	11	[62]	CALL     	4 3 0
	12	[62]	CALL     	3 0 1
	13	[63]	GETTABLE 	3 0 -1	; "try"
	14	[63]	GETTABLE 	4 0 -2	; "tp"
	15	[63]	SELF     	4 4 -7	; "source"
	16	[63]	MOVE     	6 1
	17	[63]	MOVE     	7 2
	18	[63]	CALL     	4 4 0
	19	[63]	CALL     	3 0 1
	20	[64]	GETTABLE 	3 0 -1	; "try"
	21	[64]	GETTABLE 	4 0 -2	; "tp"
	22	[64]	SELF     	4 4 -8	; "send"
	23	[64]	LOADK    	6 -9	; "\r\n.\r\n"
	24	[64]	CALL     	4 3 0
	25	[64]	CALL     	3 0 1
	26	[65]	GETTABLE 	3 0 -1	; "try"
	27	[65]	GETTABLE 	4 0 -2	; "tp"
	28	[65]	SELF     	4 4 -5	; "check"
	29	[65]	LOADK    	6 -10	; "2.."
	30	[65]	CALL     	4 3 0
	31	[65]	TAILCALL 	3 0 0
	32	[65]	RETURN   	3 0
	33	[66]	RETURN   	0 1

function <./socket/smtp.lua:68,71> (14 instructions, 56 bytes at 0x7fce674084f0)
1 param, 5 slots, 0 upvalues, 1 local, 6 constants, 0 functions
	1	[69]	GETTABLE 	1 0 -1	; "try"
	2	[69]	GETTABLE 	2 0 -2	; "tp"
	3	[69]	SELF     	2 2 -3	; "command"
	4	[69]	LOADK    	4 -4	; "QUIT"
	5	[69]	CALL     	2 3 0
	6	[69]	CALL     	1 0 1
	7	[70]	GETTABLE 	1 0 -1	; "try"
	8	[70]	GETTABLE 	2 0 -2	; "tp"
	9	[70]	SELF     	2 2 -5	; "check"
	10	[70]	LOADK    	4 -6	; "2.."
	11	[70]	CALL     	2 3 0
	12	[70]	TAILCALL 	1 0 0
	13	[70]	RETURN   	1 0
	14	[71]	RETURN   	0 1

function <./socket/smtp.lua:73,75> (5 instructions, 20 bytes at 0x7fce67408c30)
1 param, 3 slots, 0 upvalues, 1 local, 2 constants, 0 functions
	1	[74]	GETTABLE 	1 0 -1	; "tp"
	2	[74]	SELF     	1 1 -2	; "close"
	3	[74]	TAILCALL 	1 2 0
	4	[74]	RETURN   	1 0
	5	[75]	RETURN   	0 1

function <./socket/smtp.lua:77,84> (49 instructions, 196 bytes at 0x7fce67409010)
3 params, 8 slots, 1 upvalue, 3 locals, 11 constants, 0 functions
	1	[78]	GETTABLE 	3 0 -1	; "try"
	2	[78]	GETTABLE 	4 0 -2	; "tp"
	3	[78]	SELF     	4 4 -3	; "command"
	4	[78]	LOADK    	6 -4	; "AUTH"
	5	[78]	LOADK    	7 -5	; "LOGIN"
	6	[78]	CALL     	4 4 0
	7	[78]	CALL     	3 0 1
	8	[79]	GETTABLE 	3 0 -1	; "try"
	9	[79]	GETTABLE 	4 0 -2	; "tp"
	10	[79]	SELF     	4 4 -6	; "check"
	11	[79]	LOADK    	6 -7	; "3.."
	12	[79]	CALL     	4 3 0
	13	[79]	CALL     	3 0 1
	14	[80]	GETTABLE 	3 0 -1	; "try"
	15	[80]	GETTABLE 	4 0 -2	; "tp"
	16	[80]	SELF     	4 4 -8	; "send"
	17	[80]	GETUPVAL 	6 0	; mime
	18	[80]	GETTABLE 	6 6 -9	; "b64"
	19	[80]	MOVE     	7 1
	20	[80]	CALL     	6 2 2
	21	[80]	LOADK    	7 -10	; "\r\n"
	22	[80]	CONCAT   	6 6 7
	23	[80]	CALL     	4 3 0
	24	[80]	CALL     	3 0 1
	25	[81]	GETTABLE 	3 0 -1	; "try"
	26	[81]	GETTABLE 	4 0 -2	; "tp"
	27	[81]	SELF     	4 4 -6	; "check"
	28	[81]	LOADK    	6 -7	; "3.."
	29	[81]	CALL     	4 3 0
	30	[81]	CALL     	3 0 1
	31	[82]	GETTABLE 	3 0 -1	; "try"
	32	[82]	GETTABLE 	4 0 -2	; "tp"
	33	[82]	SELF     	4 4 -8	; "send"
	34	[82]	GETUPVAL 	6 0	; mime
	35	[82]	GETTABLE 	6 6 -9	; "b64"
	36	[82]	MOVE     	7 2
	37	[82]	CALL     	6 2 2
	38	[82]	LOADK    	7 -10	; "\r\n"
	39	[82]	CONCAT   	6 6 7
	40	[82]	CALL     	4 3 0
	41	[82]	CALL     	3 0 1
	42	[83]	GETTABLE 	3 0 -1	; "try"
	43	[83]	GETTABLE 	4 0 -2	; "tp"
	44	[83]	SELF     	4 4 -6	; "check"
	45	[83]	LOADK    	6 -11	; "2.."
	46	[83]	CALL     	4 3 0
	47	[83]	TAILCALL 	3 0 0
	48	[83]	RETURN   	3 0
	49	[84]	RETURN   	0 1

function <./socket/smtp.lua:86,90> (25 instructions, 100 bytes at 0x7fce67406e50)
3 params, 9 slots, 1 upvalue, 4 locals, 9 constants, 0 functions
	1	[87]	LOADK    	3 -1	; "PLAIN "
	2	[87]	GETUPVAL 	4 0	; mime
	3	[87]	GETTABLE 	4 4 -2	; "b64"
	4	[87]	LOADK    	5 -3	; "\000"
	5	[87]	MOVE     	6 1
	6	[87]	LOADK    	7 -3	; "\000"
	7	[87]	MOVE     	8 2
	8	[87]	CONCAT   	5 5 8
	9	[87]	CALL     	4 2 2
	10	[87]	CONCAT   	3 3 4
	11	[88]	GETTABLE 	4 0 -4	; "try"
	12	[88]	GETTABLE 	5 0 -5	; "tp"
	13	[88]	SELF     	5 5 -6	; "command"
	14	[88]	LOADK    	7 -7	; "AUTH"
	15	[88]	MOVE     	8 3
	16	[88]	CALL     	5 4 0
	17	[88]	CALL     	4 0 1
	18	[89]	GETTABLE 	4 0 -4	; "try"
	19	[89]	GETTABLE 	5 0 -5	; "tp"
	20	[89]	SELF     	5 5 -8	; "check"
	21	[89]	LOADK    	7 -9	; "2.."
	22	[89]	CALL     	5 3 0
	23	[89]	TAILCALL 	4 0 0
	24	[89]	RETURN   	4 0
	25	[90]	RETURN   	0 1

function <./socket/smtp.lua:92,101> (37 instructions, 148 bytes at 0x7fce67406ef0)
4 params, 8 slots, 1 upvalue, 4 locals, 8 constants, 0 functions
	1	[93]	TEST     	1 0 0
	2	[93]	JMP      	2	; to 5
	3	[93]	TEST     	2 0 1
	4	[93]	JMP      	2	; to 7
	5	[93]	LOADK    	4 -1	; 1
	6	[93]	RETURN   	4 2
	7	[94]	GETUPVAL 	4 0	; string
	8	[94]	GETTABLE 	4 4 -2	; "find"
	9	[94]	MOVE     	5 3
	10	[94]	LOADK    	6 -3	; "AUTH[^\n]+LOGIN"
	11	[94]	CALL     	4 3 2
	12	[94]	TEST     	4 0 0
	13	[94]	JMP      	6	; to 20
	14	[95]	SELF     	4 0 -4	; "login"
	15	[95]	MOVE     	6 1
	16	[95]	MOVE     	7 2
	17	[95]	TAILCALL 	4 4 0
	18	[95]	RETURN   	4 0
	19	[95]	JMP      	17	; to 37
	20	[96]	GETUPVAL 	4 0	; string
	21	[96]	GETTABLE 	4 4 -2	; "find"
	22	[96]	MOVE     	5 3
	23	[96]	LOADK    	6 -5	; "AUTH[^\n]+PLAIN"
	24	[96]	CALL     	4 3 2
	25	[96]	TEST     	4 0 0
	26	[96]	JMP      	6	; to 33
	27	[97]	SELF     	4 0 -6	; "plain"
	28	[97]	MOVE     	6 1
	29	[97]	MOVE     	7 2
	30	[97]	TAILCALL 	4 4 0
	31	[97]	RETURN   	4 0
	32	[97]	JMP      	4	; to 37
	33	[99]	GETTABLE 	4 0 -7	; "try"
	34	[99]	LOADNIL  	5 5
	35	[99]	LOADK    	6 -8	; "authentication not supported"
	36	[99]	CALL     	4 3 1
	37	[101]	RETURN   	0 1

function <./socket/smtp.lua:104,114> (35 instructions, 140 bytes at 0x7fce67408f90)
2 params, 10 slots, 3 upvalues, 7 locals, 11 constants, 0 functions
	1	[105]	SELF     	2 0 -1	; "mail"
	2	[105]	GETTABLE 	4 1 -2	; "from"
	3	[105]	CALL     	2 3 1
	4	[106]	GETUPVAL 	2 0	; base
	5	[106]	GETTABLE 	2 2 -3	; "type"
	6	[106]	GETTABLE 	3 1 -4	; "rcpt"
	7	[106]	CALL     	2 2 2
	8	[106]	EQ       	0 2 -5	; - "table"
	9	[106]	JMP      	11	; to 21
	10	[107]	GETUPVAL 	2 0	; base
	11	[107]	GETTABLE 	2 2 -6	; "ipairs"
	12	[107]	GETTABLE 	3 1 -4	; "rcpt"
	13	[107]	CALL     	2 2 4
	14	[107]	JMP      	3	; to 18
	15	[108]	SELF     	7 0 -4	; "rcpt"
	16	[108]	MOVE     	9 6
	17	[108]	CALL     	7 3 1
	18	[107]	TFORLOOP 	2 2
	19	[108]	JMP      	-5	; to 15
	20	[109]	JMP      	3	; to 24
	21	[111]	SELF     	2 0 -4	; "rcpt"
	22	[111]	GETTABLE 	4 1 -4	; "rcpt"
	23	[111]	CALL     	2 3 1
	24	[113]	SELF     	2 0 -7	; "data"
	25	[113]	GETUPVAL 	4 1	; ltn12
	26	[113]	GETTABLE 	4 4 -8	; "source"
	27	[113]	GETTABLE 	4 4 -9	; "chain"
	28	[113]	GETTABLE 	5 1 -8	; "source"
	29	[113]	GETUPVAL 	6 2	; mime
	30	[113]	GETTABLE 	6 6 -10	; "stuff"
	31	[113]	CALL     	6 1 0
	32	[113]	CALL     	4 0 2
	33	[113]	GETTABLE 	5 1 -11	; "step"
	34	[113]	CALL     	2 4 1
	35	[114]	RETURN   	0 1

function <./socket/smtp.lua:116,125> (31 instructions, 124 bytes at 0x7fce67409830)
3 params, 9 slots, 5 upvalues, 5 locals, 8 constants, 1 function
	1	[117]	GETUPVAL 	3 0	; socket
	2	[117]	GETTABLE 	3 3 -1	; "try"
	3	[117]	GETUPVAL 	4 1	; tp
	4	[117]	GETTABLE 	4 4 -2	; "connect"
	5	[117]	TESTSET  	5 0 1
	6	[117]	JMP      	2	; to 9
	7	[117]	GETUPVAL 	5 2	; _M
	8	[117]	GETTABLE 	5 5 -3	; "SERVER"
	9	[117]	TESTSET  	6 1 1
	10	[117]	JMP      	2	; to 13
	11	[117]	GETUPVAL 	6 2	; _M
	12	[117]	GETTABLE 	6 6 -4	; "PORT"
	13	[118]	GETUPVAL 	7 2	; _M
	14	[118]	GETTABLE 	7 7 -5	; "TIMEOUT"
	15	[118]	MOVE     	8 2
	16	[117]	CALL     	4 5 0
	17	[117]	CALL     	3 0 2
	18	[119]	GETUPVAL 	4 3	; base
	19	[119]	GETTABLE 	4 4 -6	; "setmetatable"
	20	[119]	NEWTABLE 	5 0 1
	21	[119]	SETTABLE 	5 -7 3	; "tp" -
	22	[119]	GETUPVAL 	6 4	; metat
	23	[119]	CALL     	4 3 2
	24	[121]	GETUPVAL 	5 0	; socket
	25	[121]	GETTABLE 	5 5 -8	; "newtry"
	26	[123]	CLOSURE  	6 0	; 0x7fce67409b90
	27	[123]	MOVE     	0 4
	28	[121]	CALL     	5 2 2
	29	[123]	SETTABLE 	4 -1 5	; "try" -
	30	[124]	RETURN   	4 2
	31	[125]	RETURN   	0 1

function <./socket/smtp.lua:121,123> (4 instructions, 16 bytes at 0x7fce67409b90)
0 params, 2 slots, 1 upvalue, 0 locals, 1 constant, 0 functions
	1	[122]	GETUPVAL 	0 0	; s
	2	[122]	SELF     	0 0 -1	; "close"
	3	[122]	CALL     	0 2 1
	4	[123]	RETURN   	0 1

function <./socket/smtp.lua:128,134> (17 instructions, 68 bytes at 0x7fce67409d90)
1 param, 9 slots, 2 upvalues, 7 locals, 2 constants, 0 functions
	1	[129]	NEWTABLE 	1 0 0
	2	[130]	GETUPVAL 	2 0	; base
	3	[130]	GETTABLE 	2 2 -1	; "pairs"
	4	[130]	TESTSET  	3 0 1
	5	[130]	JMP      	1	; to 7
	6	[130]	MOVE     	3 1
	7	[130]	CALL     	2 2 4
	8	[130]	JMP      	5	; to 14
	9	[131]	GETUPVAL 	7 1	; string
	10	[131]	GETTABLE 	7 7 -2	; "lower"
	11	[131]	MOVE     	8 5
	12	[131]	CALL     	7 2 2
	13	[131]	SETTABLE 	1 7 6
	14	[130]	TFORLOOP 	2 2
	15	[131]	JMP      	-7	; to 9
	16	[133]	RETURN   	1 2
	17	[134]	RETURN   	0 1

function <./socket/smtp.lua:141,145> (19 instructions, 76 bytes at 0x7fce6740a160)
0 params, 6 slots, 4 upvalues, 0 locals, 8 constants, 0 functions
	1	[142]	GETUPVAL 	0 0	; seqno
	2	[142]	ADD      	0 0 -1	; - 1
	3	[142]	SETUPVAL 	0 0	; seqno
	4	[143]	GETUPVAL 	0 1	; string
	5	[143]	GETTABLE 	0 0 -2	; "format"
	6	[143]	LOADK    	1 -3	; "%s%05d==%05u"
	7	[143]	GETUPVAL 	2 2	; os
	8	[143]	GETTABLE 	2 2 -4	; "date"
	9	[143]	LOADK    	3 -5	; "%d%m%Y%H%M%S"
	10	[143]	CALL     	2 2 2
	11	[144]	GETUPVAL 	3 3	; math
	12	[144]	GETTABLE 	3 3 -6	; "random"
	13	[144]	LOADK    	4 -7	; 0
	14	[144]	LOADK    	5 -8	; 99999
	15	[144]	CALL     	3 3 2
	16	[144]	GETUPVAL 	4 0	; seqno
	17	[143]	TAILCALL 	0 5 0
	18	[144]	RETURN   	0 0
	19	[145]	RETURN   	0 1

function <./socket/smtp.lua:151,158> (24 instructions, 96 bytes at 0x7fce6740a400)
1 param, 13 slots, 3 upvalues, 8 locals, 5 constants, 0 functions
	1	[152]	GETUPVAL 	1 0	; headers
	2	[152]	GETTABLE 	1 1 -1	; "canonic"
	3	[153]	LOADK    	2 -2	; "\r\n"
	4	[154]	GETUPVAL 	3 1	; base
	5	[154]	GETTABLE 	3 3 -3	; "pairs"
	6	[154]	MOVE     	4 0
	7	[154]	CALL     	3 2 4
	8	[154]	JMP      	9	; to 18
	9	[155]	GETTABLE 	8 1 6
	10	[155]	TEST     	8 0 1
	11	[155]	JMP      	1	; to 13
	12	[155]	MOVE     	8 6
	13	[155]	LOADK    	9 -4	; ": "
	14	[155]	MOVE     	10 7
	15	[155]	LOADK    	11 -2	; "\r\n"
	16	[155]	MOVE     	12 2
	17	[155]	CONCAT   	2 8 12
	18	[154]	TFORLOOP 	3 2
	19	[155]	JMP      	-11	; to 9
	20	[157]	GETUPVAL 	3 2	; coroutine
	21	[157]	GETTABLE 	3 3 -5	; "yield"
	22	[157]	MOVE     	4 2
	23	[157]	CALL     	3 2 1
	24	[158]	RETURN   	0 1

function <./socket/smtp.lua:161,186> (73 instructions, 292 bytes at 0x7fce6740ac00)
1 param, 12 slots, 6 upvalues, 8 locals, 13 constants, 0 functions
	1	[163]	GETUPVAL 	1 0	; newboundary
	2	[163]	CALL     	1 1 2
	3	[164]	GETUPVAL 	2 1	; lower_headers
	4	[164]	GETTABLE 	3 0 -1	; "headers"
	5	[164]	TEST     	3 0 1
	6	[164]	JMP      	1	; to 8
	7	[164]	NEWTABLE 	3 0 0
	8	[164]	CALL     	2 2 2
	9	[165]	GETTABLE 	3 2 -2	; "content-type"
	10	[165]	TEST     	3 0 1
	11	[165]	JMP      	1	; to 13
	12	[165]	LOADK    	3 -3	; "multipart/mixed"
	13	[165]	SETTABLE 	2 -2 3	; "content-type" -
	14	[166]	GETTABLE 	3 2 -2	; "content-type"
	15	[167]	LOADK    	4 -4	; "; boundary=\""
	16	[167]	MOVE     	5 1
	17	[167]	LOADK    	6 -5	; "\""
	18	[167]	CONCAT   	3 3 6
	19	[167]	SETTABLE 	2 -2 3	; "content-type" -
	20	[168]	GETUPVAL 	3 2	; send_headers
	21	[168]	MOVE     	4 2
	22	[168]	CALL     	3 2 1
	23	[170]	GETTABLE 	3 0 -6	; "body"
	24	[170]	GETTABLE 	3 3 -7	; "preamble"
	25	[170]	TEST     	3 0 0
	26	[170]	JMP      	9	; to 36
	27	[171]	GETUPVAL 	3 3	; coroutine
	28	[171]	GETTABLE 	3 3 -8	; "yield"
	29	[171]	GETTABLE 	4 0 -6	; "body"
	30	[171]	GETTABLE 	4 4 -7	; "preamble"
	31	[171]	CALL     	3 2 1
	32	[172]	GETUPVAL 	3 3	; coroutine
	33	[172]	GETTABLE 	3 3 -8	; "yield"
	34	[172]	LOADK    	4 -9	; "\r\n"
	35	[172]	CALL     	3 2 1
	36	[175]	GETUPVAL 	3 4	; base
	37	[175]	GETTABLE 	3 3 -10	; "ipairs"
	38	[175]	GETTABLE 	4 0 -6	; "body"
	39	[175]	CALL     	3 2 4
	40	[175]	JMP      	10	; to 51
	41	[176]	GETUPVAL 	8 3	; coroutine
	42	[176]	GETTABLE 	8 8 -8	; "yield"
	43	[176]	LOADK    	9 -11	; "\r\n--"
	44	[176]	MOVE     	10 1
	45	[176]	LOADK    	11 -9	; "\r\n"
	46	[176]	CONCAT   	9 9 11
	47	[176]	CALL     	8 2 1
	48	[177]	GETUPVAL 	8 5	; send_message
	49	[177]	MOVE     	9 7
	50	[177]	CALL     	8 2 1
	51	[175]	TFORLOOP 	3 2
	52	[177]	JMP      	-12	; to 41
	53	[180]	GETUPVAL 	3 3	; coroutine
	54	[180]	GETTABLE 	3 3 -8	; "yield"
	55	[180]	LOADK    	4 -11	; "\r\n--"
	56	[180]	MOVE     	5 1
	57	[180]	LOADK    	6 -12	; "--\r\n\r\n"
	58	[180]	CONCAT   	4 4 6
	59	[180]	CALL     	3 2 1
	60	[182]	GETTABLE 	3 0 -6	; "body"
	61	[182]	GETTABLE 	3 3 -13	; "epilogue"
	62	[182]	TEST     	3 0 0
	63	[182]	JMP      	9	; to 73
	64	[183]	GETUPVAL 	3 3	; coroutine
	65	[183]	GETTABLE 	3 3 -8	; "yield"
	66	[183]	GETTABLE 	4 0 -6	; "body"
	67	[183]	GETTABLE 	4 4 -13	; "epilogue"
	68	[183]	CALL     	3 2 1
	69	[184]	GETUPVAL 	3 3	; coroutine
	70	[184]	GETTABLE 	3 3 -8	; "yield"
	71	[184]	LOADK    	4 -9	; "\r\n"
	72	[184]	CALL     	3 2 1
	73	[186]	RETURN   	0 1

function <./socket/smtp.lua:189,202> (34 instructions, 136 bytes at 0x7fce6740adf0)
1 param, 7 slots, 3 upvalues, 4 locals, 5 constants, 0 functions
	1	[191]	GETUPVAL 	1 0	; lower_headers
	2	[191]	GETTABLE 	2 0 -1	; "headers"
	3	[191]	TEST     	2 0 1
	4	[191]	JMP      	1	; to 6
	5	[191]	NEWTABLE 	2 0 0
	6	[191]	CALL     	1 2 2
	7	[192]	GETTABLE 	2 1 -2	; "content-type"
	8	[192]	TEST     	2 0 1
	9	[192]	JMP      	1	; to 11
	10	[193]	LOADK    	2 -3	; "text/plain; charset=\"iso-8859-1\""
	11	[193]	SETTABLE 	1 -2 2	; "content-type" -
	12	[194]	GETUPVAL 	2 1	; send_headers
	13	[194]	MOVE     	3 1
	14	[194]	CALL     	2 2 1
	15	[197]	GETTABLE 	2 0 -4	; "body"
	16	[197]	CALL     	2 1 3
	17	[198]	TEST     	3 0 0
	18	[198]	JMP      	6	; to 25
	19	[198]	GETUPVAL 	4 2	; coroutine
	20	[198]	GETTABLE 	4 4 -5	; "yield"
	21	[198]	LOADNIL  	5 5
	22	[198]	MOVE     	6 3
	23	[198]	CALL     	4 3 1
	24	[198]	JMP      	-10	; to 15
	25	[199]	TEST     	2 0 0
	26	[199]	JMP      	7	; to 34
	27	[199]	GETUPVAL 	4 2	; coroutine
	28	[199]	GETTABLE 	4 4 -5	; "yield"
	29	[199]	MOVE     	5 2
	30	[199]	CALL     	4 2 1
	31	[199]	JMP      	-17	; to 15
	32	[200]	JMP      	1	; to 34
	33	[200]	JMP      	-19	; to 15
	34	[202]	RETURN   	0 1

function <./socket/smtp.lua:205,213> (19 instructions, 76 bytes at 0x7fce67409cf0)
1 param, 4 slots, 3 upvalues, 2 locals, 5 constants, 0 functions
	1	[207]	GETUPVAL 	1 0	; lower_headers
	2	[207]	GETTABLE 	2 0 -1	; "headers"
	3	[207]	TEST     	2 0 1
	4	[207]	JMP      	1	; to 6
	5	[207]	NEWTABLE 	2 0 0
	6	[207]	CALL     	1 2 2
	7	[208]	GETTABLE 	2 1 -2	; "content-type"
	8	[208]	TEST     	2 0 1
	9	[208]	JMP      	1	; to 11
	10	[209]	LOADK    	2 -3	; "text/plain; charset=\"iso-8859-1\""
	11	[209]	SETTABLE 	1 -2 2	; "content-type" -
	12	[210]	GETUPVAL 	2 1	; send_headers
	13	[210]	MOVE     	3 1
	14	[210]	CALL     	2 2 1
	15	[212]	GETUPVAL 	2 2	; coroutine
	16	[212]	GETTABLE 	2 2 -4	; "yield"
	17	[212]	GETTABLE 	3 0 -5	; "body"
	18	[212]	CALL     	2 2 1
	19	[213]	RETURN   	0 1

function <./socket/smtp.lua:216,220> (24 instructions, 96 bytes at 0x7fce67408d90)
1 param, 3 slots, 4 upvalues, 1 local, 4 constants, 0 functions
	1	[217]	GETUPVAL 	1 0	; base
	2	[217]	GETTABLE 	1 1 -1	; "type"
	3	[217]	GETTABLE 	2 0 -2	; "body"
	4	[217]	CALL     	1 2 2
	5	[217]	EQ       	0 1 -3	; - "table"
	6	[217]	JMP      	4	; to 11
	7	[217]	GETUPVAL 	1 1	; send_multipart
	8	[217]	MOVE     	2 0
	9	[217]	CALL     	1 2 1
	10	[217]	JMP      	13	; to 24
	11	[218]	GETUPVAL 	1 0	; base
	12	[218]	GETTABLE 	1 1 -1	; "type"
	13	[218]	GETTABLE 	2 0 -2	; "body"
	14	[218]	CALL     	1 2 2
	15	[218]	EQ       	0 1 -4	; - "function"
	16	[218]	JMP      	4	; to 21
	17	[218]	GETUPVAL 	1 2	; send_source
	18	[218]	MOVE     	2 0
	19	[218]	CALL     	1 2 1
	20	[218]	JMP      	3	; to 24
	21	[219]	GETUPVAL 	1 3	; send_string
	22	[219]	MOVE     	2 0
	23	[219]	CALL     	1 2 1
	24	[220]	RETURN   	0 1

function <./socket/smtp.lua:223,231> (26 instructions, 104 bytes at 0x7fce6740ba00)
1 param, 4 slots, 4 upvalues, 2 locals, 9 constants, 0 functions
	1	[224]	GETUPVAL 	1 0	; lower_headers
	2	[224]	GETTABLE 	2 0 -1	; "headers"
	3	[224]	CALL     	1 2 2
	4	[225]	GETTABLE 	2 1 -2	; "date"
	5	[225]	TEST     	2 0 1
	6	[225]	JMP      	10	; to 17
	7	[226]	GETUPVAL 	2 1	; os
	8	[226]	GETTABLE 	2 2 -2	; "date"
	9	[226]	LOADK    	3 -3	; "!%a, %d %b %Y %H:%M:%S "
	10	[226]	CALL     	2 2 2
	11	[226]	GETTABLE 	3 0 -4	; "zone"
	12	[226]	TEST     	3 0 1
	13	[226]	JMP      	2	; to 16
	14	[226]	GETUPVAL 	3 2	; _M
	15	[226]	GETTABLE 	3 3 -5	; "ZONE"
	16	[226]	CONCAT   	2 2 3
	17	[226]	SETTABLE 	1 -2 2	; "date" -
	18	[227]	GETTABLE 	2 1 -6	; "x-mailer"
	19	[227]	TEST     	2 0 1
	20	[227]	JMP      	2	; to 23
	21	[227]	GETUPVAL 	2 3	; socket
	22	[227]	GETTABLE 	2 2 -7	; "_VERSION"
	23	[227]	SETTABLE 	1 -6 2	; "x-mailer" -
	24	[229]	SETTABLE 	1 -8 -9	; "mime-version" "1.0"
	25	[230]	RETURN   	1 2
	26	[231]	RETURN   	0 1

function <./socket/smtp.lua:233,242> (15 instructions, 60 bytes at 0x7fce6740c080)
1 param, 3 slots, 3 upvalues, 2 locals, 2 constants, 2 functions
	1	[234]	GETUPVAL 	1 0	; adjust_headers
	2	[234]	MOVE     	2 0
	3	[234]	CALL     	1 2 2
	4	[234]	SETTABLE 	0 -1 1	; "headers" -
	5	[236]	GETUPVAL 	1 1	; coroutine
	6	[236]	GETTABLE 	1 1 -2	; "create"
	7	[236]	CLOSURE  	2 0	; 0x7fce6740c380
	8	[236]	GETUPVAL 	0 2	; send_message
	9	[236]	MOVE     	0 0
	10	[236]	CALL     	1 2 2
	11	[241]	CLOSURE  	2 1	; 0x7fce67409230
	12	[241]	GETUPVAL 	0 1	; coroutine
	13	[241]	MOVE     	0 1
	14	[241]	RETURN   	2 2
	15	[242]	RETURN   	0 1

function <./socket/smtp.lua:236,236> (4 instructions, 16 bytes at 0x7fce6740c380)
0 params, 2 slots, 2 upvalues, 0 locals, 0 constants, 0 functions
	1	[236]	GETUPVAL 	0 0	; send_message
	2	[236]	GETUPVAL 	1 1	; mesgt
	3	[236]	CALL     	0 2 1
	4	[236]	RETURN   	0 1

function <./socket/smtp.lua:237,241> (14 instructions, 56 bytes at 0x7fce67409230)
0 params, 5 slots, 2 upvalues, 3 locals, 1 constant, 0 functions
	1	[238]	GETUPVAL 	0 0	; coroutine
	2	[238]	GETTABLE 	0 0 -1	; "resume"
	3	[238]	GETUPVAL 	1 1	; co
	4	[238]	CALL     	0 2 4
	5	[239]	TEST     	0 0 0
	6	[239]	JMP      	4	; to 11
	7	[239]	MOVE     	3 1
	8	[239]	MOVE     	4 2
	9	[239]	RETURN   	3 3
	10	[239]	JMP      	3	; to 14
	11	[240]	LOADNIL  	3 3
	12	[240]	MOVE     	4 1
	13	[240]	RETURN   	3 3
	14	[241]	RETURN   	0 1

function <./socket/smtp.lua:247,254> (23 instructions, 92 bytes at 0x7fce6740c760)
1 param, 8 slots, 1 upvalue, 3 locals, 12 constants, 0 functions
	1	[248]	GETUPVAL 	1 0	; _M
	2	[248]	GETTABLE 	1 1 -1	; "open"
	3	[248]	GETTABLE 	2 0 -2	; "server"
	4	[248]	GETTABLE 	3 0 -3	; "port"
	5	[248]	GETTABLE 	4 0 -4	; "create"
	6	[248]	CALL     	1 4 2
	7	[249]	SELF     	2 1 -5	; "greet"
	8	[249]	GETTABLE 	4 0 -6	; "domain"
	9	[249]	CALL     	2 3 2
	10	[250]	SELF     	3 1 -7	; "auth"
	11	[250]	GETTABLE 	5 0 -8	; "user"
	12	[250]	GETTABLE 	6 0 -9	; "password"
	13	[250]	MOVE     	7 2
	14	[250]	CALL     	3 5 1
	15	[251]	SELF     	3 1 -10	; "send"
	16	[251]	MOVE     	5 0
	17	[251]	CALL     	3 3 1
	18	[252]	SELF     	3 1 -11	; "quit"
	19	[252]	CALL     	3 2 1
	20	[253]	SELF     	3 1 -12	; "close"
	21	[253]	TAILCALL 	3 2 0
	22	[253]	RETURN   	3 0
	23	[254]	RETURN   	0 1
