-- BYTECODE -- smtp.lua:44-48
0001    TGETS    2   0   0  ; "try"
0002    TGETS    3   0   1  ; "tp"
0003    MOV      4   3
0004    TGETS    3   3   2  ; "check"
0005    KSTR     5   3      ; "2.."
0006    CALL     3   0   3
0007    CALLM    2   1   0
0008    TGETS    2   0   0  ; "try"
0009    TGETS    3   0   1  ; "tp"
0010    MOV      4   3
0011    TGETS    3   3   4  ; "command"
0012    KSTR     5   5      ; "EHLO"
0013    ISTC     6   1
0014    JMP      6 => 0017
0015    UGET     6   0      ; _M
0016    TGETS    6   6   6  ; "DOMAIN"
0017 => CALL     3   0   4
0018    CALLM    2   1   0
0019    UGET     2   1      ; socket
0020    TGETS    2   2   7  ; "skip"
0021    KSHORT   3   1
0022    TGETS    4   0   0  ; "try"
0023    TGETS    5   0   1  ; "tp"
0024    MOV      6   5
0025    TGETS    5   5   2  ; "check"
0026    KSTR     7   3      ; "2.."
0027    CALL     5   0   3
0028    CALLM    4   0   0
0029    CALLMT   2   1

-- BYTECODE -- smtp.lua:50-53
0001    TGETS    2   0   0  ; "try"
0002    TGETS    3   0   1  ; "tp"
0003    MOV      4   3
0004    TGETS    3   3   2  ; "command"
0005    KSTR     5   3      ; "MAIL"
0006    KSTR     6   4      ; "FROM:"
0007    MOV      7   1
0008    CAT      6   6   7
0009    CALL     3   0   4
0010    CALLM    2   1   0
0011    TGETS    2   0   0  ; "try"
0012    TGETS    3   0   1  ; "tp"
0013    MOV      4   3
0014    TGETS    3   3   5  ; "check"
0015    KSTR     5   6      ; "2.."
0016    CALL     3   0   3
0017    CALLMT   2   0

-- BYTECODE -- smtp.lua:55-58
0001    TGETS    2   0   0  ; "try"
0002    TGETS    3   0   1  ; "tp"
0003    MOV      4   3
0004    TGETS    3   3   2  ; "command"
0005    KSTR     5   3      ; "RCPT"
0006    KSTR     6   4      ; "TO:"
0007    MOV      7   1
0008    CAT      6   6   7
0009    CALL     3   0   4
0010    CALLM    2   1   0
0011    TGETS    2   0   0  ; "try"
0012    TGETS    3   0   1  ; "tp"
0013    MOV      4   3
0014    TGETS    3   3   5  ; "check"
0015    KSTR     5   6      ; "2.."
0016    CALL     3   0   3
0017    CALLMT   2   0

-- BYTECODE -- smtp.lua:60-66
0001    TGETS    3   0   0  ; "try"
0002    TGETS    4   0   1  ; "tp"
0003    MOV      5   4
0004    TGETS    4   4   2  ; "command"
0005    KSTR     6   3      ; "DATA"
0006    CALL     4   0   3
0007    CALLM    3   1   0
0008    TGETS    3   0   0  ; "try"
0009    TGETS    4   0   1  ; "tp"
0010    MOV      5   4
0011    TGETS    4   4   4  ; "check"
0012    KSTR     6   5      ; "3.."
0013    CALL     4   0   3
0014    CALLM    3   1   0
0015    TGETS    3   0   0  ; "try"
0016    TGETS    4   0   1  ; "tp"
0017    MOV      5   4
0018    TGETS    4   4   6  ; "source"
0019    MOV      6   1
0020    MOV      7   2
0021    CALL     4   0   4
0022    CALLM    3   1   0
0023    TGETS    3   0   0  ; "try"
0024    TGETS    4   0   1  ; "tp"
0025    MOV      5   4
0026    TGETS    4   4   7  ; "send"
0027    KSTR     6   8      ; "\r\n.\r\n"
0028    CALL     4   0   3
0029    CALLM    3   1   0
0030    TGETS    3   0   0  ; "try"
0031    TGETS    4   0   1  ; "tp"
0032    MOV      5   4
0033    TGETS    4   4   4  ; "check"
0034    KSTR     6   9      ; "2.."
0035    CALL     4   0   3
0036    CALLMT   3   0

-- BYTECODE -- smtp.lua:68-71
0001    TGETS    1   0   0  ; "try"
0002    TGETS    2   0   1  ; "tp"
0003    MOV      3   2
0004    TGETS    2   2   2  ; "command"
0005    KSTR     4   3      ; "QUIT"
0006    CALL     2   0   3
0007    CALLM    1   1   0
0008    TGETS    1   0   0  ; "try"
0009    TGETS    2   0   1  ; "tp"
0010    MOV      3   2
0011    TGETS    2   2   4  ; "check"
0012    KSTR     4   5      ; "2.."
0013    CALL     2   0   3
0014    CALLMT   1   0

-- BYTECODE -- smtp.lua:73-75
0001    TGETS    1   0   0  ; "tp"
0002    MOV      2   1
0003    TGETS    1   1   1  ; "close"
0004    CALLT    1   2

-- BYTECODE -- smtp.lua:77-84
0001    TGETS    3   0   0  ; "try"
0002    TGETS    4   0   1  ; "tp"
0003    MOV      5   4
0004    TGETS    4   4   2  ; "command"
0005    KSTR     6   3      ; "AUTH"
0006    KSTR     7   4      ; "LOGIN"
0007    CALL     4   0   4
0008    CALLM    3   1   0
0009    TGETS    3   0   0  ; "try"
0010    TGETS    4   0   1  ; "tp"
0011    MOV      5   4
0012    TGETS    4   4   5  ; "check"
0013    KSTR     6   6      ; "3.."
0014    CALL     4   0   3
0015    CALLM    3   1   0
0016    TGETS    3   0   0  ; "try"
0017    TGETS    4   0   1  ; "tp"
0018    MOV      5   4
0019    TGETS    4   4   7  ; "send"
0020    UGET     6   0      ; mime
0021    TGETS    6   6   8  ; "b64"
0022    MOV      7   1
0023    CALL     6   2   2
0024    KSTR     7   9      ; "\r\n"
0025    CAT      6   6   7
0026    CALL     4   0   3
0027    CALLM    3   1   0
0028    TGETS    3   0   0  ; "try"
0029    TGETS    4   0   1  ; "tp"
0030    MOV      5   4
0031    TGETS    4   4   5  ; "check"
0032    KSTR     6   6      ; "3.."
0033    CALL     4   0   3
0034    CALLM    3   1   0
0035    TGETS    3   0   0  ; "try"
0036    TGETS    4   0   1  ; "tp"
0037    MOV      5   4
0038    TGETS    4   4   7  ; "send"
0039    UGET     6   0      ; mime
0040    TGETS    6   6   8  ; "b64"
0041    MOV      7   2
0042    CALL     6   2   2
0043    KSTR     7   9      ; "\r\n"
0044    CAT      6   6   7
0045    CALL     4   0   3
0046    CALLM    3   1   0
0047    TGETS    3   0   0  ; "try"
0048    TGETS    4   0   1  ; "tp"
0049    MOV      5   4
0050    TGETS    4   4   5  ; "check"
0051    KSTR     6  10      ; "2.."
0052    CALL     4   0   3
0053    CALLMT   3   0

-- BYTECODE -- smtp.lua:86-90
0001    KSTR     3   0      ; "PLAIN "
0002    UGET     4   0      ; mime
0003    TGETS    4   4   1  ; "b64"
0004    KSTR     5   2      ; "\000"
0005    MOV      6   1
0006    KSTR     7   2      ; "\000"
0007    MOV      8   2
0008    CAT      5   5   8
0009    CALL     4   2   2
0010    CAT      3   3   4
0011    TGETS    4   0   3  ; "try"
0012    TGETS    5   0   4  ; "tp"
0013    MOV      6   5
0014    TGETS    5   5   5  ; "command"
0015    KSTR     7   6      ; "AUTH"
0016    MOV      8   3
0017    CALL     5   0   4
0018    CALLM    4   1   0
0019    TGETS    4   0   3  ; "try"
0020    TGETS    5   0   4  ; "tp"
0021    MOV      6   5
0022    TGETS    5   5   7  ; "check"
0023    KSTR     7   8      ; "2.."
0024    CALL     5   0   3
0025    CALLMT   4   0

-- BYTECODE -- smtp.lua:92-101
0001    ISF          1
0002    JMP      4 => 0005
0003    IST          2
0004    JMP      4 => 0007
0005 => KSHORT   4   1
0006    RET1     4   2
0007 => UGET     4   0      ; string
0008    TGETS    4   4   0  ; "find"
0009    MOV      5   3
0010    KSTR     6   1      ; "AUTH[^\n]+LOGIN"
0011    CALL     4   2   3
0012    ISF          4
0013    JMP      5 => 0020
0014    MOV      5   0
0015    TGETS    4   0   2  ; "login"
0016    MOV      6   1
0017    MOV      7   2
0018    CALLT    4   4
0019    JMP      4 => 0037
0020 => UGET     4   0      ; string
0021    TGETS    4   4   0  ; "find"
0022    MOV      5   3
0023    KSTR     6   3      ; "AUTH[^\n]+PLAIN"
0024    CALL     4   2   3
0025    ISF          4
0026    JMP      5 => 0033
0027    MOV      5   0
0028    TGETS    4   0   4  ; "plain"
0029    MOV      6   1
0030    MOV      7   2
0031    CALLT    4   4
0032    JMP      4 => 0037
0033 => TGETS    4   0   5  ; "try"
0034    KPRI     5   0
0035    KSTR     6   6      ; "authentication not supported"
0036    CALL     4   1   3
0037 => RET0     0   1

-- BYTECODE -- smtp.lua:104-114
0001    MOV      3   0
0002    TGETS    2   0   0  ; "mail"
0003    TGETS    4   1   1  ; "from"
0004    CALL     2   1   3
0005    UGET     2   0      ; base
0006    TGETS    2   2   2  ; "type"
0007    TGETS    3   1   3  ; "rcpt"
0008    CALL     2   2   2
0009    ISNES    2   4      ; "table"
0010    JMP      2 => 0023
0011    UGET     2   0      ; base
0012    TGETS    2   2   5  ; "ipairs"
0013    TGETS    3   1   3  ; "rcpt"
0014    CALL     2   4   2
0015    JMP      5 => 0020
0016 => MOV      8   0
0017    TGETS    7   0   3  ; "rcpt"
0018    MOV      9   6
0019    CALL     7   1   3
0020 => ITERC    5   3   3
0021    ITERL    5 => 0016
0022    JMP      2 => 0027
0023 => MOV      3   0
0024    TGETS    2   0   3  ; "rcpt"
0025    TGETS    4   1   3  ; "rcpt"
0026    CALL     2   1   3
0027 => MOV      3   0
0028    TGETS    2   0   6  ; "data"
0029    UGET     4   1      ; ltn12
0030    TGETS    4   4   7  ; "source"
0031    TGETS    4   4   8  ; "chain"
0032    TGETS    5   1   7  ; "source"
0033    UGET     6   2      ; mime
0034    TGETS    6   6   9  ; "stuff"
0035    CALL     6   0   1
0036    CALLM    4   2   1
0037    TGETS    5   1  10  ; "step"
0038    CALL     2   1   4
0039    RET0     0   1

-- BYTECODE -- smtp.lua:121-123
0001    UGET     0   0      ; s
0002    MOV      1   0
0003    TGETS    0   0   0  ; "close"
0004    CALL     0   1   2
0005    RET0     0   1

-- BYTECODE -- smtp.lua:116-125
0001    UGET     3   0      ; socket
0002    TGETS    3   3   0  ; "try"
0003    UGET     4   1      ; tp
0004    TGETS    4   4   1  ; "connect"
0005    ISTC     5   0
0006    JMP      5 => 0009
0007    UGET     5   2      ; _M
0008    TGETS    5   5   2  ; "SERVER"
0009 => ISTC     6   1
0010    JMP      6 => 0013
0011    UGET     6   2      ; _M
0012    TGETS    6   6   3  ; "PORT"
0013 => UGET     7   2      ; _M
0014    TGETS    7   7   4  ; "TIMEOUT"
0015    MOV      8   2
0016    CALL     4   0   5
0017    CALLM    3   2   0
0018    UGET     4   3      ; base
0019    TGETS    4   4   5  ; "setmetatable"
0020    TDUP     5   6
0021    TSETS    3   5   7  ; "tp"
0022    UGET     6   4      ; metat
0023    CALL     4   2   3
0024    UGET     5   0      ; socket
0025    TGETS    5   5   8  ; "newtry"
0026    FNEW     6   9      ; smtp.lua:121
0027    CALL     5   2   2
0028    TSETS    5   4   0  ; "try"
0029    UCLO     0 => 0030
0030 => RET1     4   2

-- BYTECODE -- smtp.lua:128-134
0001    TNEW     1   0
0002    UGET     2   0      ; base
0003    TGETS    2   2   0  ; "pairs"
0004    ISTC     3   0
0005    JMP      3 => 0007
0006    MOV      3   1
0007 => CALL     2   4   2
0008    JMP      5 => 0014
0009 => UGET     7   1      ; string
0010    TGETS    7   7   1  ; "lower"
0011    MOV      8   5
0012    CALL     7   2   2
0013    TSETV    6   1   7
0014 => ITERC    5   3   3
0015    ITERL    5 => 0009
0016    RET1     1   2

-- BYTECODE -- smtp.lua:141-145
0001    UGET     0   0      ; seqno
0002    ADDVN    0   0   0  ; 1
0003    USETV    0   0      ; seqno
0004    UGET     0   1      ; string
0005    TGETS    0   0   0  ; "format"
0006    KSTR     1   1      ; "%s%05d==%05u"
0007    UGET     2   2      ; os
0008    TGETS    2   2   2  ; "date"
0009    KSTR     3   3      ; "%d%m%Y%H%M%S"
0010    CALL     2   2   2
0011    UGET     3   3      ; math
0012    TGETS    3   3   4  ; "random"
0013    KSHORT   4   0
0014    KNUM     5   1      ; 99999
0015    CALL     3   2   3
0016    UGET     4   0      ; seqno
0017    CALLT    0   5

-- BYTECODE -- smtp.lua:151-158
0001    UGET     1   0      ; headers
0002    TGETS    1   1   0  ; "canonic"
0003    KSTR     2   1      ; "\r\n"
0004    UGET     3   1      ; base
0005    TGETS    3   3   2  ; "pairs"
0006    MOV      4   0
0007    CALL     3   4   2
0008    JMP      6 => 0018
0009 => TGETV    8   1   6
0010    IST          8
0011    JMP      9 => 0013
0012    MOV      8   6
0013 => KSTR     9   3      ; ": "
0014    MOV     10   7
0015    KSTR    11   1      ; "\r\n"
0016    MOV     12   2
0017    CAT      2   8  12
0018 => ITERC    6   3   3
0019    ITERL    6 => 0009
0020    UGET     3   2      ; coroutine
0021    TGETS    3   3   4  ; "yield"
0022    MOV      4   2
0023    CALL     3   1   2
0024    RET0     0   1

-- BYTECODE -- smtp.lua:161-186
0001    UGET     1   0      ; newboundary
0002    CALL     1   2   1
0003    UGET     2   1      ; lower_headers
0004    TGETS    3   0   0  ; "headers"
0005    IST          3
0006    JMP      4 => 0008
0007    TNEW     3   0
0008 => CALL     2   2   2
0009    TGETS    3   2   1  ; "content-type"
0010    IST          3
0011    JMP      4 => 0013
0012    KSTR     3   2      ; "multipart/mixed"
0013 => TSETS    3   2   1  ; "content-type"
0014    TGETS    3   2   1  ; "content-type"
0015    KSTR     4   3      ; "; boundary=""
0016    MOV      5   1
0017    KSTR     6   4      ; """
0018    CAT      3   3   6
0019    TSETS    3   2   1  ; "content-type"
0020    UGET     3   2      ; send_headers
0021    MOV      4   2
0022    CALL     3   1   2
0023    TGETS    3   0   5  ; "body"
0024    TGETS    3   3   6  ; "preamble"
0025    ISF          3
0026    JMP      4 => 0036
0027    UGET     3   3      ; coroutine
0028    TGETS    3   3   7  ; "yield"
0029    TGETS    4   0   5  ; "body"
0030    TGETS    4   4   6  ; "preamble"
0031    CALL     3   1   2
0032    UGET     3   3      ; coroutine
0033    TGETS    3   3   7  ; "yield"
0034    KSTR     4   8      ; "\r\n"
0035    CALL     3   1   2
0036 => UGET     3   4      ; base
0037    TGETS    3   3   9  ; "ipairs"
0038    TGETS    4   0   5  ; "body"
0039    CALL     3   4   2
0040    JMP      6 => 0051
0041 => UGET     8   3      ; coroutine
0042    TGETS    8   8   7  ; "yield"
0043    KSTR     9  10      ; "\r\n--"
0044    MOV     10   1
0045    KSTR    11   8      ; "\r\n"
0046    CAT      9   9  11
0047    CALL     8   1   2
0048    UGET     8   5      ; send_message
0049    MOV      9   7
0050    CALL     8   1   2
0051 => ITERC    6   3   3
0052    ITERL    6 => 0041
0053    UGET     3   3      ; coroutine
0054    TGETS    3   3   7  ; "yield"
0055    KSTR     4  10      ; "\r\n--"
0056    MOV      5   1
0057    KSTR     6  11      ; "--\r\n\r\n"
0058    CAT      4   4   6
0059    CALL     3   1   2
0060    TGETS    3   0   5  ; "body"
0061    TGETS    3   3  12  ; "epilogue"
0062    ISF          3
0063    JMP      4 => 0073
0064    UGET     3   3      ; coroutine
0065    TGETS    3   3   7  ; "yield"
0066    TGETS    4   0   5  ; "body"
0067    TGETS    4   4  12  ; "epilogue"
0068    CALL     3   1   2
0069    UGET     3   3      ; coroutine
0070    TGETS    3   3   7  ; "yield"
0071    KSTR     4   8      ; "\r\n"
0072    CALL     3   1   2
0073 => RET0     0   1

-- BYTECODE -- smtp.lua:189-202
0001    UGET     1   0      ; lower_headers
0002    TGETS    2   0   0  ; "headers"
0003    IST          2
0004    JMP      3 => 0006
0005    TNEW     2   0
0006 => CALL     1   2   2
0007    TGETS    2   1   1  ; "content-type"
0008    IST          2
0009    JMP      3 => 0011
0010    KSTR     2   2      ; "text/plain; charset="iso-8859-1""
0011 => TSETS    2   1   1  ; "content-type"
0012    UGET     2   1      ; send_headers
0013    MOV      3   1
0014    CALL     2   1   2
0015 => LOOP     2 => 0035
0016    TGETS    2   0   3  ; "body"
0017    CALL     2   3   1
0018    ISF          3
0019    JMP      4 => 0026
0020    UGET     4   2      ; coroutine
0021    TGETS    4   4   4  ; "yield"
0022    KPRI     5   0
0023    MOV      6   3
0024    CALL     4   1   3
0025    JMP      4 => 0015
0026 => ISF          2
0027    JMP      4 => 0035
0028    UGET     4   2      ; coroutine
0029    TGETS    4   4   4  ; "yield"
0030    MOV      5   2
0031    CALL     4   1   2
0032    JMP      4 => 0015
0033    JMP      2 => 0035
0034    JMP      2 => 0015
0035 => RET0     0   1

-- BYTECODE -- smtp.lua:205-213
0001    UGET     1   0      ; lower_headers
0002    TGETS    2   0   0  ; "headers"
0003    IST          2
0004    JMP      3 => 0006
0005    TNEW     2   0
0006 => CALL     1   2   2
0007    TGETS    2   1   1  ; "content-type"
0008    IST          2
0009    JMP      3 => 0011
0010    KSTR     2   2      ; "text/plain; charset="iso-8859-1""
0011 => TSETS    2   1   1  ; "content-type"
0012    UGET     2   1      ; send_headers
0013    MOV      3   1
0014    CALL     2   1   2
0015    UGET     2   2      ; coroutine
0016    TGETS    2   2   3  ; "yield"
0017    TGETS    3   0   4  ; "body"
0018    CALL     2   1   2
0019    RET0     0   1

-- BYTECODE -- smtp.lua:216-220
0001    UGET     1   0      ; base
0002    TGETS    1   1   0  ; "type"
0003    TGETS    2   0   1  ; "body"
0004    CALL     1   2   2
0005    ISNES    1   2      ; "table"
0006    JMP      1 => 0011
0007    UGET     1   1      ; send_multipart
0008    MOV      2   0
0009    CALL     1   1   2
0010    JMP      1 => 0024
0011 => UGET     1   0      ; base
0012    TGETS    1   1   0  ; "type"
0013    TGETS    2   0   1  ; "body"
0014    CALL     1   2   2
0015    ISNES    1   3      ; "function"
0016    JMP      1 => 0021
0017    UGET     1   2      ; send_source
0018    MOV      2   0
0019    CALL     1   1   2
0020    JMP      1 => 0024
0021 => UGET     1   3      ; send_string
0022    MOV      2   0
0023    CALL     1   1   2
0024 => RET0     0   1

-- BYTECODE -- smtp.lua:223-231
0001    UGET     1   0      ; lower_headers
0002    TGETS    2   0   0  ; "headers"
0003    CALL     1   2   2
0004    TGETS    2   1   1  ; "date"
0005    IST          2
0006    JMP      3 => 0017
0007    UGET     2   1      ; os
0008    TGETS    2   2   1  ; "date"
0009    KSTR     3   2      ; "!%a, %d %b %Y %H:%M:%S "
0010    CALL     2   2   2
0011    TGETS    3   0   3  ; "zone"
0012    IST          3
0013    JMP      4 => 0016
0014    UGET     3   2      ; _M
0015    TGETS    3   3   4  ; "ZONE"
0016 => CAT      2   2   3
0017 => TSETS    2   1   1  ; "date"
0018    TGETS    2   1   5  ; "x-mailer"
0019    IST          2
0020    JMP      3 => 0023
0021    UGET     2   3      ; socket
0022    TGETS    2   2   6  ; "_VERSION"
0023 => TSETS    2   1   5  ; "x-mailer"
0024    KSTR     2   8      ; "1.0"
0025    TSETS    2   1   7  ; "mime-version"
0026    RET1     1   2

-- BYTECODE -- smtp.lua:236-236
0001    UGET     0   0      ; send_message
0002    UGET     1   1      ; mesgt
0003    CALL     0   1   2
0004    RET0     0   1

-- BYTECODE -- smtp.lua:237-241
0001    UGET     0   0      ; coroutine
0002    TGETS    0   0   0  ; "resume"
0003    UGET     1   1      ; co
0004    CALL     0   4   2
0005    ISF          0
0006    JMP      3 => 0011
0007    MOV      3   1
0008    MOV      4   2
0009    RET      3   3
0010    JMP      3 => 0014
0011 => KPRI     3   0
0012    MOV      4   1
0013    RET      3   3
0014 => RET0     0   1

-- BYTECODE -- smtp.lua:233-242
0001    UGET     1   0      ; adjust_headers
0002    MOV      2   0
0003    CALL     1   2   2
0004    TSETS    1   0   0  ; "headers"
0005    UGET     1   1      ; coroutine
0006    TGETS    1   1   1  ; "create"
0007    FNEW     2   2      ; smtp.lua:236
0008    CALL     1   2   2
0009    FNEW     2   3      ; smtp.lua:237
0010    UCLO     0 => 0011
0011 => RET1     2   2

-- BYTECODE -- smtp.lua:247-254
0001    UGET     1   0      ; _M
0002    TGETS    1   1   0  ; "open"
0003    TGETS    2   0   1  ; "server"
0004    TGETS    3   0   2  ; "port"
0005    TGETS    4   0   3  ; "create"
0006    CALL     1   2   4
0007    MOV      3   1
0008    TGETS    2   1   4  ; "greet"
0009    TGETS    4   0   5  ; "domain"
0010    CALL     2   2   3
0011    MOV      4   1
0012    TGETS    3   1   6  ; "auth"
0013    TGETS    5   0   7  ; "user"
0014    TGETS    6   0   8  ; "password"
0015    MOV      7   2
0016    CALL     3   1   5
0017    MOV      4   1
0018    TGETS    3   1   9  ; "send"
0019    MOV      5   0
0020    CALL     3   1   3
0021    MOV      4   1
0022    TGETS    3   1  10  ; "quit"
0023    CALL     3   1   2
0024    MOV      4   1
0025    TGETS    3   1  11  ; "close"
0026    CALLT    3   2

-- BYTECODE -- smtp.lua:0-256
0001    GGET     0   0      ; "_G"
0002    GGET     1   1      ; "require"
0003    KSTR     2   2      ; "coroutine"
0004    CALL     1   2   2
0005    GGET     2   1      ; "require"
0006    KSTR     3   3      ; "string"
0007    CALL     2   2   2
0008    GGET     3   1      ; "require"
0009    KSTR     4   4      ; "math"
0010    CALL     3   2   2
0011    GGET     4   1      ; "require"
0012    KSTR     5   5      ; "os"
0013    CALL     4   2   2
0014    GGET     5   1      ; "require"
0015    KSTR     6   6      ; "socket"
0016    CALL     5   2   2
0017    GGET     6   1      ; "require"
0018    KSTR     7   7      ; "socket.tp"
0019    CALL     6   2   2
0020    GGET     7   1      ; "require"
0021    KSTR     8   8      ; "ltn12"
0022    CALL     7   2   2
0023    GGET     8   1      ; "require"
0024    KSTR     9   9      ; "socket.headers"
0025    CALL     8   2   2
0026    GGET     9   1      ; "require"
0027    KSTR    10  10      ; "mime"
0028    CALL     9   2   2
0029    TNEW    10   0
0030    TSETS   10   5  11  ; "smtp"
0031    TGETS   10   5  11  ; "smtp"
0032    KSHORT  11  60
0033    TSETS   11  10  12  ; "TIMEOUT"
0034    KSTR    11  14      ; "localhost"
0035    TSETS   11  10  13  ; "SERVER"
0036    KSHORT  11  25
0037    TSETS   11  10  15  ; "PORT"
0038    TGETS   11   4  17  ; "getenv"
0039    KSTR    12  18      ; "SERVER_NAME"
0040    CALL    11   2   2
0041    IST         11
0042    JMP     12 => 0044
0043    KSTR    11  14      ; "localhost"
0044 => TSETS   11  10  16  ; "DOMAIN"
0045    KSTR    11  20      ; "-0000"
0046    TSETS   11  10  19  ; "ZONE"
0047    TDUP    11  21
0048    TNEW    12   0
0049    TSETS   12  11  22  ; "__index"
0050    TGETS   12  11  22  ; "__index"
0051    FNEW    13  24      ; smtp.lua:44
0052    TSETS   13  12  23  ; "greet"
0053    TGETS   12  11  22  ; "__index"
0054    FNEW    13  26      ; smtp.lua:50
0055    TSETS   13  12  25  ; "mail"
0056    TGETS   12  11  22  ; "__index"
0057    FNEW    13  28      ; smtp.lua:55
0058    TSETS   13  12  27  ; "rcpt"
0059    TGETS   12  11  22  ; "__index"
0060    FNEW    13  30      ; smtp.lua:60
0061    TSETS   13  12  29  ; "data"
0062    TGETS   12  11  22  ; "__index"
0063    FNEW    13  32      ; smtp.lua:68
0064    TSETS   13  12  31  ; "quit"
0065    TGETS   12  11  22  ; "__index"
0066    FNEW    13  34      ; smtp.lua:73
0067    TSETS   13  12  33  ; "close"
0068    TGETS   12  11  22  ; "__index"
0069    FNEW    13  36      ; smtp.lua:77
0070    TSETS   13  12  35  ; "login"
0071    TGETS   12  11  22  ; "__index"
0072    FNEW    13  38      ; smtp.lua:86
0073    TSETS   13  12  37  ; "plain"
0074    TGETS   12  11  22  ; "__index"
0075    FNEW    13  40      ; smtp.lua:92
0076    TSETS   13  12  39  ; "auth"
0077    TGETS   12  11  22  ; "__index"
0078    FNEW    13  42      ; smtp.lua:104
0079    TSETS   13  12  41  ; "send"
0080    FNEW    12  44      ; smtp.lua:116
0081    TSETS   12  10  43  ; "open"
0082    FNEW    12  45      ; smtp.lua:128
0083    KSHORT  13   0
0084    FNEW    14  46      ; smtp.lua:141
0085    KPRI    15   0
0086    FNEW    16  47      ; smtp.lua:151
0087    FNEW    17  48      ; smtp.lua:161
0088    FNEW    18  49      ; smtp.lua:189
0089    FNEW    19  50      ; smtp.lua:205
0090    FNEW    15  51      ; smtp.lua:216
0091    FNEW    20  52      ; smtp.lua:223
0092    FNEW    21  54      ; smtp.lua:233
0093    TSETS   21  10  53  ; "message"
0094    TGETS   21   5  55  ; "protect"
0095    FNEW    22  56      ; smtp.lua:247
0096    CALL    21   2   2
0097    TSETS   21  10  41  ; "send"
0098    UCLO     0 => 0099
0099 => RET1    10   2

