
main <./socket/tp.lua:0,0> (64 instructions, 256 bytes at 0x7fe2d5c068a0)
0+ params, 9 slots, 0 upvalues, 7 locals, 20 constants, 12 functions
	1	[10]	GETGLOBAL	0 -1	; _G
	2	[11]	GETGLOBAL	1 -2	; require
	3	[11]	LOADK    	2 -3	; "string"
	4	[11]	CALL     	1 2 2
	5	[12]	GETGLOBAL	2 -2	; require
	6	[12]	LOADK    	3 -4	; "socket"
	7	[12]	CALL     	2 2 2
	8	[13]	GETGLOBAL	3 -2	; require
	9	[13]	LOADK    	4 -5	; "ltn12"
	10	[13]	CALL     	3 2 2
	11	[15]	NEWTABLE 	4 0 0
	12	[15]	SETTABLE 	2 -6 4	; "tp" -
	13	[16]	GETTABLE 	4 2 -6	; "tp"
	14	[21]	SETTABLE 	4 -7 -8	; "TIMEOUT" 60
	15	[44]	CLOSURE  	5 0	; 0x7fe2d5c06f80
	16	[44]	MOVE     	0 2
	17	[44]	MOVE     	0 1
	18	[47]	NEWTABLE 	6 0 1
	19	[47]	NEWTABLE 	7 0 0
	20	[47]	SETTABLE 	6 -9 7	; "__index" -
	21	[49]	GETTABLE 	7 6 -9	; "__index"
	22	[65]	CLOSURE  	8 1	; 0x7fe2d5c06a80
	23	[65]	MOVE     	0 5
	24	[65]	MOVE     	0 0
	25	[65]	MOVE     	0 1
	26	[49]	SETTABLE 	7 -10 8	; "check" -
	27	[67]	GETTABLE 	7 6 -9	; "__index"
	28	[74]	CLOSURE  	8 2	; 0x7fe2d5c07790
	29	[74]	MOVE     	0 1
	30	[67]	SETTABLE 	7 -11 8	; "command" -
	31	[76]	GETTABLE 	7 6 -9	; "__index"
	32	[79]	CLOSURE  	8 3	; 0x7fe2d5c07ae0
	33	[76]	SETTABLE 	7 -12 8	; "sink" -
	34	[81]	GETTABLE 	7 6 -9	; "__index"
	35	[83]	CLOSURE  	8 4	; 0x7fe2d5c07510
	36	[81]	SETTABLE 	7 -13 8	; "send" -
	37	[85]	GETTABLE 	7 6 -9	; "__index"
	38	[87]	CLOSURE  	8 5	; 0x7fe2d5c08810
	39	[85]	SETTABLE 	7 -14 8	; "receive" -
	40	[89]	GETTABLE 	7 6 -9	; "__index"
	41	[91]	CLOSURE  	8 6	; 0x7fe2d5c08aa0
	42	[89]	SETTABLE 	7 -15 8	; "getfd" -
	43	[93]	GETTABLE 	7 6 -9	; "__index"
	44	[95]	CLOSURE  	8 7	; 0x7fe2d5c08ce0
	45	[93]	SETTABLE 	7 -16 8	; "dirty" -
	46	[97]	GETTABLE 	7 6 -9	; "__index"
	47	[99]	CLOSURE  	8 8	; 0x7fe2d5c08f90
	48	[97]	SETTABLE 	7 -17 8	; "getcontrol" -
	49	[101]	GETTABLE 	7 6 -9	; "__index"
	50	[105]	CLOSURE  	8 9	; 0x7fe2d5c08e90
	51	[105]	MOVE     	0 2
	52	[105]	MOVE     	0 3
	53	[101]	SETTABLE 	7 -18 8	; "source" -
	54	[108]	GETTABLE 	7 6 -9	; "__index"
	55	[111]	CLOSURE  	8 10	; 0x7fe2d5c088b0
	56	[108]	SETTABLE 	7 -19 8	; "close" -
	57	[124]	CLOSURE  	7 11	; 0x7fe2d5c08930
	58	[124]	MOVE     	0 2
	59	[124]	MOVE     	0 4
	60	[124]	MOVE     	0 0
	61	[124]	MOVE     	0 6
	62	[114]	SETTABLE 	4 -20 7	; "connect" -
	63	[126]	RETURN   	4 2
	64	[126]	RETURN   	0 1

function <./socket/tp.lua:27,44> (58 instructions, 232 bytes at 0x7fe2d5c06f80)
1 param, 12 slots, 2 upvalues, 7 locals, 9 constants, 0 functions
	1	[29]	SELF     	4 0 -1	; "receive"
	2	[29]	CALL     	4 2 3
	3	[30]	MOVE     	6 4
	4	[31]	TEST     	5 0 0
	5	[31]	JMP      	3	; to 9
	6	[31]	LOADNIL  	7 7
	7	[31]	MOVE     	8 5
	8	[31]	RETURN   	7 3
	9	[32]	GETUPVAL 	7 0	; socket
	10	[32]	GETTABLE 	7 7 -2	; "skip"
	11	[32]	LOADK    	8 -3	; 2
	12	[32]	GETUPVAL 	9 1	; string
	13	[32]	GETTABLE 	9 9 -4	; "find"
	14	[32]	MOVE     	10 4
	15	[32]	LOADK    	11 -5	; "^(%d%d%d)(.?)"
	16	[32]	CALL     	9 3 0
	17	[32]	CALL     	7 0 3
	18	[32]	MOVE     	3 8
	19	[32]	MOVE     	1 7
	20	[33]	TEST     	1 0 1
	21	[33]	JMP      	3	; to 25
	22	[33]	LOADNIL  	7 7
	23	[33]	LOADK    	8 -6	; "invalid server reply"
	24	[33]	RETURN   	7 3
	25	[34]	EQ       	0 3 -7	; - "-"
	26	[34]	JMP      	28	; to 55
	27	[36]	SELF     	7 0 -1	; "receive"
	28	[36]	CALL     	7 2 3
	29	[36]	MOVE     	5 8
	30	[36]	MOVE     	4 7
	31	[37]	TEST     	5 0 0
	32	[37]	JMP      	3	; to 36
	33	[37]	LOADNIL  	7 7
	34	[37]	MOVE     	8 5
	35	[37]	RETURN   	7 3
	36	[38]	GETUPVAL 	7 0	; socket
	37	[38]	GETTABLE 	7 7 -2	; "skip"
	38	[38]	LOADK    	8 -3	; 2
	39	[38]	GETUPVAL 	9 1	; string
	40	[38]	GETTABLE 	9 9 -4	; "find"
	41	[38]	MOVE     	10 4
	42	[38]	LOADK    	11 -5	; "^(%d%d%d)(.?)"
	43	[38]	CALL     	9 3 0
	44	[38]	CALL     	7 0 3
	45	[38]	MOVE     	3 8
	46	[38]	MOVE     	2 7
	47	[39]	MOVE     	7 6
	48	[39]	LOADK    	8 -8	; "\n"
	49	[39]	MOVE     	9 4
	50	[39]	CONCAT   	6 7 9
	51	[41]	EQ       	0 1 2
	52	[41]	JMP      	-26	; to 27
	53	[41]	EQ       	0 3 -9	; - " "
	54	[41]	JMP      	-28	; to 27
	55	[43]	MOVE     	7 1
	56	[43]	MOVE     	8 6
	57	[43]	RETURN   	7 3
	58	[44]	RETURN   	0 1

function <./socket/tp.lua:49,65> (71 instructions, 284 bytes at 0x7fe2d5c06a80)
2 params, 12 slots, 3 upvalues, 9 locals, 7 constants, 0 functions
	1	[50]	GETUPVAL 	2 0	; get_reply
	2	[50]	GETTABLE 	3 0 -1	; "c"
	3	[50]	CALL     	2 2 3
	4	[51]	TEST     	2 0 1
	5	[51]	JMP      	3	; to 9
	6	[51]	LOADNIL  	4 4
	7	[51]	MOVE     	5 3
	8	[51]	RETURN   	4 3
	9	[52]	GETUPVAL 	4 1	; base
	10	[52]	GETTABLE 	4 4 -2	; "type"
	11	[52]	MOVE     	5 1
	12	[52]	CALL     	4 2 2
	13	[52]	EQ       	1 4 -3	; - "function"
	14	[52]	JMP      	48	; to 63
	15	[53]	GETUPVAL 	4 1	; base
	16	[53]	GETTABLE 	4 4 -2	; "type"
	17	[53]	MOVE     	5 1
	18	[53]	CALL     	4 2 2
	19	[53]	EQ       	0 4 -4	; - "table"
	20	[53]	JMP      	24	; to 45
	21	[54]	GETUPVAL 	4 1	; base
	22	[54]	GETTABLE 	4 4 -5	; "ipairs"
	23	[54]	MOVE     	5 1
	24	[54]	CALL     	4 2 4
	25	[54]	JMP      	13	; to 39
	26	[55]	GETUPVAL 	9 2	; string
	27	[55]	GETTABLE 	9 9 -6	; "find"
	28	[55]	MOVE     	10 2
	29	[55]	MOVE     	11 8
	30	[55]	CALL     	9 3 2
	31	[55]	TEST     	9 0 0
	32	[55]	JMP      	6	; to 39
	33	[56]	GETUPVAL 	9 1	; base
	34	[56]	GETTABLE 	9 9 -7	; "tonumber"
	35	[56]	MOVE     	10 2
	36	[56]	CALL     	9 2 2
	37	[56]	MOVE     	10 3
	38	[56]	RETURN   	9 3
	39	[54]	TFORLOOP 	4 2
	40	[57]	JMP      	-15	; to 26
	41	[59]	LOADNIL  	4 4
	42	[59]	MOVE     	5 3
	43	[59]	RETURN   	4 3
	44	[59]	JMP      	26	; to 71
	45	[61]	GETUPVAL 	4 2	; string
	46	[61]	GETTABLE 	4 4 -6	; "find"
	47	[61]	MOVE     	5 2
	48	[61]	MOVE     	6 1
	49	[61]	CALL     	4 3 2
	50	[61]	TEST     	4 0 0
	51	[61]	JMP      	7	; to 59
	52	[61]	GETUPVAL 	4 1	; base
	53	[61]	GETTABLE 	4 4 -7	; "tonumber"
	54	[61]	MOVE     	5 2
	55	[61]	CALL     	4 2 2
	56	[61]	MOVE     	5 3
	57	[61]	RETURN   	4 3
	58	[61]	JMP      	12	; to 71
	59	[62]	LOADNIL  	4 4
	60	[62]	MOVE     	5 3
	61	[62]	RETURN   	4 3
	62	[63]	JMP      	8	; to 71
	63	[64]	MOVE     	4 1
	64	[64]	GETUPVAL 	5 1	; base
	65	[64]	GETTABLE 	5 5 -7	; "tonumber"
	66	[64]	MOVE     	6 2
	67	[64]	CALL     	5 2 2
	68	[64]	MOVE     	6 3
	69	[64]	TAILCALL 	4 3 0
	70	[64]	RETURN   	4 0
	71	[65]	RETURN   	0 1

function <./socket/tp.lua:67,74> (25 instructions, 100 bytes at 0x7fe2d5c07790)
3 params, 9 slots, 1 upvalue, 3 locals, 5 constants, 0 functions
	1	[68]	GETUPVAL 	3 0	; string
	2	[68]	GETTABLE 	3 3 -1	; "upper"
	3	[68]	MOVE     	4 1
	4	[68]	CALL     	3 2 2
	5	[68]	MOVE     	1 3
	6	[69]	TEST     	2 0 0
	7	[69]	JMP      	10	; to 18
	8	[70]	GETTABLE 	3 0 -2	; "c"
	9	[70]	SELF     	3 3 -3	; "send"
	10	[70]	MOVE     	5 1
	11	[70]	LOADK    	6 -4	; " "
	12	[70]	MOVE     	7 2
	13	[70]	LOADK    	8 -5	; "\r\n"
	14	[70]	CONCAT   	5 5 8
	15	[70]	TAILCALL 	3 3 0
	16	[70]	RETURN   	3 0
	17	[70]	JMP      	7	; to 25
	18	[72]	GETTABLE 	3 0 -2	; "c"
	19	[72]	SELF     	3 3 -3	; "send"
	20	[72]	MOVE     	5 1
	21	[72]	LOADK    	6 -5	; "\r\n"
	22	[72]	CONCAT   	5 5 6
	23	[72]	TAILCALL 	3 3 0
	24	[72]	RETURN   	3 0
	25	[74]	RETURN   	0 1

function <./socket/tp.lua:76,79> (10 instructions, 40 bytes at 0x7fe2d5c07ae0)
3 params, 8 slots, 0 upvalues, 5 locals, 2 constants, 0 functions
	1	[77]	GETGLOBAL	3 -1	; c
	2	[77]	SELF     	3 3 -2	; "receive"
	3	[77]	MOVE     	5 2
	4	[77]	CALL     	3 3 3
	5	[78]	MOVE     	5 1
	6	[78]	MOVE     	6 3
	7	[78]	MOVE     	7 4
	8	[78]	TAILCALL 	5 3 0
	9	[78]	RETURN   	5 0
	10	[79]	RETURN   	0 1

function <./socket/tp.lua:81,83> (6 instructions, 24 bytes at 0x7fe2d5c07510)
2 params, 5 slots, 0 upvalues, 2 locals, 2 constants, 0 functions
	1	[82]	GETTABLE 	2 0 -1	; "c"
	2	[82]	SELF     	2 2 -2	; "send"
	3	[82]	MOVE     	4 1
	4	[82]	TAILCALL 	2 3 0
	5	[82]	RETURN   	2 0
	6	[83]	RETURN   	0 1

function <./socket/tp.lua:85,87> (6 instructions, 24 bytes at 0x7fe2d5c08810)
2 params, 5 slots, 0 upvalues, 2 locals, 2 constants, 0 functions
	1	[86]	GETTABLE 	2 0 -1	; "c"
	2	[86]	SELF     	2 2 -2	; "receive"
	3	[86]	MOVE     	4 1
	4	[86]	TAILCALL 	2 3 0
	5	[86]	RETURN   	2 0
	6	[87]	RETURN   	0 1

function <./socket/tp.lua:89,91> (5 instructions, 20 bytes at 0x7fe2d5c08aa0)
1 param, 3 slots, 0 upvalues, 1 local, 2 constants, 0 functions
	1	[90]	GETTABLE 	1 0 -1	; "c"
	2	[90]	SELF     	1 1 -2	; "getfd"
	3	[90]	TAILCALL 	1 2 0
	4	[90]	RETURN   	1 0
	5	[91]	RETURN   	0 1

function <./socket/tp.lua:93,95> (5 instructions, 20 bytes at 0x7fe2d5c08ce0)
1 param, 3 slots, 0 upvalues, 1 local, 2 constants, 0 functions
	1	[94]	GETTABLE 	1 0 -1	; "c"
	2	[94]	SELF     	1 1 -2	; "dirty"
	3	[94]	TAILCALL 	1 2 0
	4	[94]	RETURN   	1 0
	5	[95]	RETURN   	0 1

function <./socket/tp.lua:97,99> (3 instructions, 12 bytes at 0x7fe2d5c08f90)
1 param, 2 slots, 0 upvalues, 1 local, 1 constant, 0 functions
	1	[98]	GETTABLE 	1 0 -1	; "c"
	2	[98]	RETURN   	1 2
	3	[99]	RETURN   	0 1

function <./socket/tp.lua:101,105> (20 instructions, 80 bytes at 0x7fe2d5c08e90)
3 params, 8 slots, 2 upvalues, 6 locals, 6 constants, 0 functions
	1	[102]	GETUPVAL 	3 0	; socket
	2	[102]	GETTABLE 	3 3 -1	; "sink"
	3	[102]	LOADK    	4 -2	; "keep-open"
	4	[102]	GETTABLE 	5 0 -3	; "c"
	5	[102]	CALL     	3 3 2
	6	[103]	GETUPVAL 	4 1	; ltn12
	7	[103]	GETTABLE 	4 4 -4	; "pump"
	8	[103]	GETTABLE 	4 4 -5	; "all"
	9	[103]	MOVE     	5 1
	10	[103]	MOVE     	6 3
	11	[103]	TESTSET  	7 2 1
	12	[103]	JMP      	3	; to 16
	13	[103]	GETUPVAL 	7 1	; ltn12
	14	[103]	GETTABLE 	7 7 -4	; "pump"
	15	[103]	GETTABLE 	7 7 -6	; "step"
	16	[103]	CALL     	4 4 3
	17	[104]	MOVE     	6 4
	18	[104]	MOVE     	7 5
	19	[104]	RETURN   	6 3
	20	[105]	RETURN   	0 1

function <./socket/tp.lua:108,111> (6 instructions, 24 bytes at 0x7fe2d5c088b0)
1 param, 3 slots, 0 upvalues, 1 local, 3 constants, 0 functions
	1	[109]	GETTABLE 	1 0 -1	; "c"
	2	[109]	SELF     	1 1 -2	; "close"
	3	[109]	CALL     	1 2 1
	4	[110]	LOADK    	1 -3	; 1
	5	[110]	RETURN   	1 2
	6	[111]	RETURN   	0 1

function <./socket/tp.lua:114,124> (35 instructions, 140 bytes at 0x7fe2d5c08930)
4 params, 11 slots, 4 upvalues, 8 locals, 7 constants, 0 functions
	1	[115]	TESTSET  	4 3 1
	2	[115]	JMP      	2	; to 5
	3	[115]	GETUPVAL 	4 0	; socket
	4	[115]	GETTABLE 	4 4 -1	; "tcp"
	5	[115]	CALL     	4 1 3
	6	[116]	TEST     	4 0 1
	7	[116]	JMP      	3	; to 11
	8	[116]	LOADNIL  	6 6
	9	[116]	MOVE     	7 5
	10	[116]	RETURN   	6 3
	11	[117]	SELF     	6 4 -2	; "settimeout"
	12	[117]	TESTSET  	8 2 1
	13	[117]	JMP      	2	; to 16
	14	[117]	GETUPVAL 	8 1	; _M
	15	[117]	GETTABLE 	8 8 -3	; "TIMEOUT"
	16	[117]	CALL     	6 3 1
	17	[118]	SELF     	6 4 -4	; "connect"
	18	[118]	MOVE     	8 0
	19	[118]	MOVE     	9 1
	20	[118]	CALL     	6 4 3
	21	[119]	TEST     	6 0 1
	22	[119]	JMP      	5	; to 28
	23	[120]	SELF     	8 4 -5	; "close"
	24	[120]	CALL     	8 2 1
	25	[121]	LOADNIL  	8 8
	26	[121]	MOVE     	9 7
	27	[121]	RETURN   	8 3
	28	[123]	GETUPVAL 	8 2	; base
	29	[123]	GETTABLE 	8 8 -6	; "setmetatable"
	30	[123]	NEWTABLE 	9 0 1
	31	[123]	SETTABLE 	9 -7 4	; "c" -
	32	[123]	GETUPVAL 	10 3	; metat
	33	[123]	TAILCALL 	8 3 0
	34	[123]	RETURN   	8 0
	35	[124]	RETURN   	0 1
