
main <./plugins/statistics.koplugin/_meta.lua:0,0> (15 instructions, 60 bytes at 0x7fda404068e0)
0+ params, 4 slots, 0 upvalues, 1 local, 8 constants, 0 functions
	1	[1]	GETGLOBAL	0 -1	; require
	2	[1]	LOADK    	1 -2	; "gettext"
	3	[1]	CALL     	0 2 2
	4	[2]	NEWTABLE 	1 0 3
	5	[3]	SETTABLE 	1 -3 -4	; "name" "statistics"
	6	[4]	MOVE     	2 0
	7	[4]	LOADK    	3 -6	; "Reader statistics"
	8	[4]	CALL     	2 2 2
	9	[4]	SETTABLE 	1 -5 2	; "fullname" -
	10	[5]	MOVE     	2 0
	11	[5]	LOADK    	3 -8	; "Keeps and displays your reading statistics."
	12	[5]	CALL     	2 2 2
	13	[5]	SETTABLE 	1 -7 2	; "description" -
	14	[6]	RETURN   	1 2
	15	[6]	RETURN   	0 1
