
main <./frontend/ui/widget/container/alphacontainer.lua:0,0> (21 instructions, 84 bytes at 0x7fcfe7406900)
0+ params, 5 slots, 0 upvalues, 3 locals, 13 constants, 2 functions
	1	[20]	GETGLOBAL	0 -1	; require
	2	[20]	LOADK    	1 -2	; "ffi/blitbuffer"
	3	[20]	CALL     	0 2 2
	4	[21]	GETGLOBAL	1 -1	; require
	5	[21]	LOADK    	2 -3	; "ui/widget/container/widgetcontainer"
	6	[21]	CALL     	1 2 2
	7	[23]	SELF     	2 1 -4	; "new"
	8	[23]	NEWTABLE 	4 0 5
	9	[24]	SETTABLE 	4 -5 -6	; "alpha" 1
	10	[26]	SETTABLE 	4 -7 -8	; "private_bb" nil
	11	[28]	SETTABLE 	4 -9 -8	; "background_bb" nil
	12	[29]	SETTABLE 	4 -10 -8	; "background_bb_x" nil
	13	[30]	SETTABLE 	4 -11 -8	; "background_bb_y" nil
	14	[23]	CALL     	2 3 2
	15	[73]	CLOSURE  	3 0	; 0x7fcfe7406c10
	16	[73]	MOVE     	0 0
	17	[33]	SETTABLE 	2 -12 3	; "paintTo" -
	18	[84]	CLOSURE  	3 1	; 0x7fcfe7406df0
	19	[75]	SETTABLE 	2 -13 3	; "onCloseWidget" -
	20	[87]	RETURN   	2 2
	21	[87]	RETURN   	0 1

function <./frontend/ui/widget/container/alphacontainer.lua:33,73> (88 instructions, 352 bytes at 0x7fcfe7406c10)
4 params, 16 slots, 1 upvalue, 6 locals, 18 constants, 0 functions
	1	[34]	GETTABLE 	4 0 -1	; 1
	2	[34]	SELF     	4 4 -2	; "getSize"
	3	[34]	CALL     	4 2 2
	4	[35]	GETTABLE 	5 0 -3	; "private_bb"
	5	[37]	GETTABLE 	6 0 -4	; "background_bb"
	6	[37]	TEST     	6 0 0
	7	[37]	JMP      	5	; to 13
	8	[40]	SELF     	6 1 -5	; "blitFrom"
	9	[40]	GETTABLE 	8 0 -4	; "background_bb"
	10	[40]	GETTABLE 	9 0 -6	; "background_bb_x"
	11	[40]	GETTABLE 	10 0 -7	; "background_bb_y"
	12	[40]	CALL     	6 5 1
	13	[44]	TEST     	5 0 0
	14	[44]	JMP      	10	; to 25
	15	[44]	SELF     	6 5 -8	; "getWidth"
	16	[44]	CALL     	6 2 2
	17	[44]	GETTABLE 	7 4 -9	; "w"
	18	[44]	EQ       	0 6 7
	19	[44]	JMP      	5	; to 25
	20	[45]	SELF     	6 5 -10	; "getHeight"
	21	[45]	CALL     	6 2 2
	22	[45]	GETTABLE 	7 4 -11	; "h"
	23	[45]	EQ       	1 6 7
	24	[45]	JMP      	50	; to 75
	25	[47]	TEST     	5 0 0
	26	[47]	JMP      	2	; to 29
	27	[48]	SELF     	6 5 -12	; "free"
	28	[48]	CALL     	6 2 1
	29	[51]	GETUPVAL 	6 0	; BlitBuffer
	30	[51]	GETTABLE 	6 6 -13	; "new"
	31	[51]	GETTABLE 	7 4 -9	; "w"
	32	[51]	GETTABLE 	8 4 -11	; "h"
	33	[51]	SELF     	9 1 -14	; "getType"
	34	[51]	CALL     	9 2 0
	35	[51]	CALL     	6 0 2
	36	[51]	MOVE     	5 6
	37	[52]	SETTABLE 	0 -3 5	; "private_bb" -
	38	[55]	GETTABLE 	6 0 -4	; "background_bb"
	39	[56]	TEST     	6 0 0
	40	[56]	JMP      	12	; to 53
	41	[56]	GETTABLE 	6 0 -4	; "background_bb"
	42	[56]	SELF     	6 6 -8	; "getWidth"
	43	[56]	CALL     	6 2 2
	44	[56]	GETTABLE 	7 4 -9	; "w"
	45	[56]	EQ       	0 6 7
	46	[56]	JMP      	6	; to 53
	47	[57]	GETTABLE 	6 0 -4	; "background_bb"
	48	[57]	SELF     	6 6 -10	; "getHeight"
	49	[57]	CALL     	6 2 2
	50	[57]	GETTABLE 	7 4 -11	; "h"
	51	[57]	EQ       	1 6 7
	52	[57]	JMP      	14	; to 67
	53	[59]	GETTABLE 	6 0 -4	; "background_bb"
	54	[59]	TEST     	6 0 0
	55	[59]	JMP      	3	; to 59
	56	[60]	GETTABLE 	6 0 -4	; "background_bb"
	57	[60]	SELF     	6 6 -12	; "free"
	58	[60]	CALL     	6 2 1
	59	[62]	GETUPVAL 	6 0	; BlitBuffer
	60	[62]	GETTABLE 	6 6 -13	; "new"
	61	[62]	GETTABLE 	7 4 -9	; "w"
	62	[62]	GETTABLE 	8 4 -11	; "h"
	63	[62]	SELF     	9 1 -14	; "getType"
	64	[62]	CALL     	9 2 0
	65	[62]	CALL     	6 0 2
	66	[62]	SETTABLE 	0 -4 6	; "background_bb" -
	67	[64]	GETTABLE 	6 0 -4	; "background_bb"
	68	[64]	SELF     	6 6 -5	; "blitFrom"
	69	[64]	MOVE     	8 1
	70	[64]	LOADK    	9 -15	; 0
	71	[64]	LOADK    	10 -15	; 0
	72	[64]	MOVE     	11 2
	73	[64]	MOVE     	12 3
	74	[64]	CALL     	6 7 1
	75	[69]	GETTABLE 	6 0 -1	; 1
	76	[69]	SELF     	6 6 -16	; "paintTo"
	77	[69]	MOVE     	8 5
	78	[69]	LOADK    	9 -15	; 0
	79	[69]	LOADK    	10 -15	; 0
	80	[69]	CALL     	6 5 1
	81	[72]	SELF     	6 1 -17	; "addblitFrom"
	82	[72]	MOVE     	8 5
	83	[72]	MOVE     	9 2
	84	[72]	MOVE     	10 3
	85	[72]	LOADNIL  	11 14
	86	[72]	GETTABLE 	15 0 -18	; "alpha"
	87	[72]	CALL     	6 10 1
	88	[73]	RETURN   	0 1

function <./frontend/ui/widget/container/alphacontainer.lua:75,84> (15 instructions, 60 bytes at 0x7fcfe7406df0)
1 param, 3 slots, 0 upvalues, 1 local, 4 constants, 0 functions
	1	[76]	GETTABLE 	1 0 -1	; "private_bb"
	2	[76]	TEST     	1 0 0
	3	[76]	JMP      	4	; to 8
	4	[77]	GETTABLE 	1 0 -1	; "private_bb"
	5	[77]	SELF     	1 1 -2	; "free"
	6	[77]	CALL     	1 2 1
	7	[78]	SETTABLE 	0 -1 -3	; "private_bb" nil
	8	[80]	GETTABLE 	1 0 -4	; "background_bb"
	9	[80]	TEST     	1 0 0
	10	[80]	JMP      	4	; to 15
	11	[81]	GETTABLE 	1 0 -4	; "background_bb"
	12	[81]	SELF     	1 1 -2	; "free"
	13	[81]	CALL     	1 2 1
	14	[82]	SETTABLE 	0 -4 -3	; "background_bb" nil
	15	[84]	RETURN   	0 1
