-- BYTECODE -- alphacontainer.lua:33-73
0001    TGETB    4   0   1
0002    MOV      5   4
0003    TGETS    4   4   0  ; "getSize"
0004    CALL     4   2   2
0005    TGETS    5   0   1  ; "private_bb"
0006    TGETS    6   0   2  ; "background_bb"
0007    ISF          6
0008    JMP      7 => 0015
0009    MOV      7   1
0010    TGETS    6   1   3  ; "blitFrom"
0011    TGETS    8   0   2  ; "background_bb"
0012    TGETS    9   0   4  ; "background_bb_x"
0013    TGETS   10   0   5  ; "background_bb_y"
0014    CALL     6   1   5
0015 => ISF          5
0016    JMP      6 => 0029
0017    MOV      7   5
0018    TGETS    6   5   6  ; "getWidth"
0019    CALL     6   2   2
0020    TGETS    7   4   7  ; "w"
0021    ISNEV    6   7
0022    JMP      6 => 0029
0023    MOV      7   5
0024    TGETS    6   5   8  ; "getHeight"
0025    CALL     6   2   2
0026    TGETS    7   4   9  ; "h"
0027    ISEQV    6   7
0028    JMP      6 => 0086
0029 => ISF          5
0030    JMP      6 => 0034
0031    MOV      7   5
0032    TGETS    6   5  10  ; "free"
0033    CALL     6   1   2
0034 => UGET     6   0      ; BlitBuffer
0035    TGETS    6   6  11  ; "new"
0036    TGETS    7   4   7  ; "w"
0037    TGETS    8   4   9  ; "h"
0038    MOV     10   1
0039    TGETS    9   1  12  ; "getType"
0040    CALL     9   0   2
0041    CALLM    6   2   2
0042    MOV      5   6
0043    TSETS    5   0   1  ; "private_bb"
0044    TGETS    6   0   2  ; "background_bb"
0045    ISF          6
0046    JMP      6 => 0061
0047    TGETS    6   0   2  ; "background_bb"
0048    MOV      7   6
0049    TGETS    6   6   6  ; "getWidth"
0050    CALL     6   2   2
0051    TGETS    7   4   7  ; "w"
0052    ISNEV    6   7
0053    JMP      6 => 0061
0054    TGETS    6   0   2  ; "background_bb"
0055    MOV      7   6
0056    TGETS    6   6   8  ; "getHeight"
0057    CALL     6   2   2
0058    TGETS    7   4   9  ; "h"
0059    ISEQV    6   7
0060    JMP      6 => 0077
0061 => TGETS    6   0   2  ; "background_bb"
0062    ISF          6
0063    JMP      7 => 0068
0064    TGETS    6   0   2  ; "background_bb"
0065    MOV      7   6
0066    TGETS    6   6  10  ; "free"
0067    CALL     6   1   2
0068 => UGET     6   0      ; BlitBuffer
0069    TGETS    6   6  11  ; "new"
0070    TGETS    7   4   7  ; "w"
0071    TGETS    8   4   9  ; "h"
0072    MOV     10   1
0073    TGETS    9   1  12  ; "getType"
0074    CALL     9   0   2
0075    CALLM    6   2   2
0076    TSETS    6   0   2  ; "background_bb"
0077 => TGETS    6   0   2  ; "background_bb"
0078    MOV      7   6
0079    TGETS    6   6   3  ; "blitFrom"
0080    MOV      8   1
0081    KSHORT   9   0
0082    KSHORT  10   0
0083    MOV     11   2
0084    MOV     12   3
0085    CALL     6   1   7
0086 => TGETB    6   0   1
0087    MOV      7   6
0088    TGETS    6   6  13  ; "paintTo"
0089    MOV      8   5
0090    KSHORT   9   0
0091    KSHORT  10   0
0092    CALL     6   1   5
0093    MOV      7   1
0094    TGETS    6   1  14  ; "addblitFrom"
0095    MOV      8   5
0096    MOV      9   2
0097    MOV     10   3
0098    KNIL    11  14
0099    TGETS   15   0  15  ; "alpha"
0100    CALL     6   1  10
0101    RET0     0   1

-- BYTECODE -- alphacontainer.lua:75-84
0001    TGETS    1   0   0  ; "private_bb"
0002    ISF          1
0003    JMP      2 => 0010
0004    TGETS    1   0   0  ; "private_bb"
0005    MOV      2   1
0006    TGETS    1   1   1  ; "free"
0007    CALL     1   1   2
0008    KPRI     1   0
0009    TSETS    1   0   0  ; "private_bb"
0010 => TGETS    1   0   2  ; "background_bb"
0011    ISF          1
0012    JMP      2 => 0019
0013    TGETS    1   0   2  ; "background_bb"
0014    MOV      2   1
0015    TGETS    1   1   1  ; "free"
0016    CALL     1   1   2
0017    KPRI     1   0
0018    TSETS    1   0   2  ; "background_bb"
0019 => RET0     0   1

-- BYTECODE -- alphacontainer.lua:0-88
0001    GGET     0   0      ; "require"
0002    KSTR     1   1      ; "ffi/blitbuffer"
0003    CALL     0   2   2
0004    GGET     1   0      ; "require"
0005    KSTR     2   2      ; "ui/widget/container/widgetcontainer"
0006    CALL     1   2   2
0007    MOV      3   1
0008    TGETS    2   1   3  ; "new"
0009    TDUP     4   4
0010    CALL     2   2   3
0011    FNEW     3   6      ; alphacontainer.lua:33
0012    TSETS    3   2   5  ; "paintTo"
0013    FNEW     3   8      ; alphacontainer.lua:75
0014    TSETS    3   2   7  ; "onCloseWidget"
0015    UCLO     0 => 0016
0016 => RET1     2   2

