
main <./frontend/ui/data/keyboardlayouts/ar_AA_keyboard.lua:0,0> (335 instructions, 1340 bytes at 0x7ff301506790)
0+ params, 67 slots, 0 upvalues, 48 locals, 147 constants, 0 functions
	1	[1]	GETGLOBAL	0 -1	; require
	2	[1]	LOADK    	1 -2	; "ui/data/keyboardlayouts/keypopup/en_popup"
	3	[1]	CALL     	0 2 2
	4	[2]	GETGLOBAL	1 -1	; require
	5	[2]	LOADK    	2 -3	; "ui/data/keyboardlayouts/keypopup/ar_AA_popup"
	6	[2]	CALL     	1 2 2
	7	[3]	GETTABLE 	2 0 -4	; "com"
	8	[4]	GETTABLE 	3 0 -5	; "prd"
	9	[5]	GETTABLE 	4 0 -6	; "_at"
	10	[6]	GETTABLE 	5 0 -7	; "_eq"
	11	[7]	GETTABLE 	6 1 -8	; "alef"
	12	[8]	GETTABLE 	7 1 -9	; "ba"
	13	[9]	GETTABLE 	8 1 -10	; "jeem"
	14	[10]	GETTABLE 	9 1 -11	; "daal"
	15	[11]	GETTABLE 	10 1 -12	; "h_aa"
	16	[12]	GETTABLE 	11 1 -13	; "waw"
	17	[13]	GETTABLE 	12 1 -14	; "zay"
	18	[14]	GETTABLE 	13 1 -15	; "ha"
	19	[15]	GETTABLE 	14 1 -16	; "tah"
	20	[16]	GETTABLE 	15 1 -17	; "yaa"
	21	[17]	GETTABLE 	16 1 -18	; "kaf"
	22	[18]	GETTABLE 	17 1 -19	; "lam"
	23	[19]	GETTABLE 	18 1 -20	; "meem"
	24	[20]	GETTABLE 	19 1 -21	; "nun"
	25	[21]	GETTABLE 	20 1 -22	; "seen"
	26	[22]	GETTABLE 	21 1 -23	; "ayin"
	27	[23]	GETTABLE 	22 1 -24	; "fah"
	28	[24]	GETTABLE 	23 1 -25	; "saad"
	29	[25]	GETTABLE 	24 1 -26	; "qaf"
	30	[26]	GETTABLE 	25 1 -27	; "raa"
	31	[27]	GETTABLE 	26 1 -28	; "sheen"
	32	[28]	GETTABLE 	27 1 -29	; "taa"
	33	[29]	GETTABLE 	28 1 -30	; "thaa"
	34	[30]	GETTABLE 	29 1 -31	; "thaal"
	35	[31]	GETTABLE 	30 1 -32	; "dhad"
	36	[32]	GETTABLE 	31 1 -33	; "ghayn"
	37	[33]	GETTABLE 	32 1 -34	; "khaa"
	38	[34]	GETTABLE 	33 1 -35	; "hamza"
	39	[35]	GETTABLE 	34 1 -36	; "wawhamza"
	40	[36]	GETTABLE 	35 1 -37	; "laa"
	41	[37]	GETTABLE 	36 1 -38	; "alefmaqsoura"
	42	[38]	GETTABLE 	37 1 -39	; "taamarbouta"
	43	[39]	GETTABLE 	38 1 -40	; "diacritics"
	44	[40]	GETTABLE 	39 1 -41	; "diacritic_fat_ha"
	45	[41]	GETTABLE 	40 1 -42	; "diacritic_damma"
	46	[42]	GETTABLE 	41 1 -43	; "diacritic_kasra"
	47	[43]	GETTABLE 	42 1 -44	; "diacritic_sukoon"
	48	[44]	GETTABLE 	43 1 -45	; "diacritic_shadda"
	49	[45]	GETTABLE 	44 1 -46	; "diacritic_tanween_fath"
	50	[46]	GETTABLE 	45 1 -47	; "diacritic_tanween_damm"
	51	[47]	GETTABLE 	46 1 -48	; "diacritic_tanween_kasr"
	52	[48]	GETTABLE 	47 1 -49	; "arabic_comma"
	53	[51]	NEWTABLE 	48 0 7
	54	[52]	SETTABLE 	48 -50 -51	; "min_layer" 1
	55	[53]	SETTABLE 	48 -52 -53	; "max_layer" 4
	56	[54]	NEWTABLE 	49 0 1
	57	[54]	SETTABLE 	49 -55 -56	; "\216\168\216\175\217\145\217\132" true
	58	[54]	SETTABLE 	48 -54 49	; "shiftmode_keys" -
	59	[55]	NEWTABLE 	49 0 2
	60	[55]	SETTABLE 	49 -58 -56	; "\216\177\217\133\216\178" true
	61	[55]	SETTABLE 	49 -59 -56	; "\216\173\216\177\217\129" true
	62	[55]	SETTABLE 	48 -57 49	; "symbolmode_keys" -
	63	[56]	NEWTABLE 	49 0 1
	64	[56]	SETTABLE 	49 -61 -56	; "\240\159\140\144" true
	65	[56]	SETTABLE 	48 -60 49	; "utf8mode_keys" -
	66	[57]	NEWTABLE 	49 0 1
	67	[57]	SETTABLE 	49 -63 -64	; "\195\132\195\169\195\159" false
	68	[57]	SETTABLE 	48 -62 49	; "umlautmode_keys" -
	69	[58]	NEWTABLE 	49 4 0
	70	[58]	NEWTABLE 	50 12 0
	71	[60]	NEWTABLE 	51 4 0
	72	[61]	MOVE     	52 39
	73	[61]	MOVE     	53 30
	74	[61]	LOADK    	54 -66	; "\226\128\158"
	75	[61]	LOADK    	55 -67	; "0"
	76	[61]	SETLIST  	51 4 1	; 1
	77	[61]	NEWTABLE 	52 4 0
	78	[62]	MOVE     	53 44
	79	[62]	MOVE     	54 23
	80	[62]	LOADK    	55 -68	; "!"
	81	[62]	LOADK    	56 -69	; "1"
	82	[62]	SETLIST  	52 4 1	; 1
	83	[62]	NEWTABLE 	53 4 0
	84	[63]	MOVE     	54 40
	85	[63]	MOVE     	55 28
	86	[63]	MOVE     	56 4
	87	[63]	LOADK    	57 -70	; "2"
	88	[63]	SETLIST  	53 4 1	; 1
	89	[63]	NEWTABLE 	54 4 0
	90	[64]	MOVE     	55 45
	91	[64]	MOVE     	56 24
	92	[64]	LOADK    	57 -71	; "#"
	93	[64]	LOADK    	58 -72	; "3"
	94	[64]	SETLIST  	54 4 1	; 1
	95	[64]	NEWTABLE 	55 4 0
	96	[65]	LOADK    	56 -73	; "\239\187\185"
	97	[65]	MOVE     	57 22
	98	[65]	LOADK    	58 -74	; "+"
	99	[65]	MOVE     	59 5
	100	[65]	SETLIST  	55 4 1	; 1
	101	[65]	NEWTABLE 	56 4 0
	102	[66]	LOADK    	57 -75	; "\216\165"
	103	[66]	MOVE     	58 31
	104	[66]	LOADK    	59 -76	; "\226\130\172"
	105	[66]	LOADK    	60 -77	; "("
	106	[66]	SETLIST  	56 4 1	; 1
	107	[66]	NEWTABLE 	57 4 0
	108	[67]	LOADK    	58 -78	; "`"
	109	[67]	MOVE     	59 21
	110	[67]	LOADK    	60 -79	; "\226\128\176"
	111	[67]	LOADK    	61 -80	; ")"
	112	[67]	SETLIST  	57 4 1	; 1
	113	[67]	NEWTABLE 	58 4 0
	114	[68]	LOADK    	59 -81	; "\195\183"
	115	[68]	MOVE     	60 10
	116	[68]	LOADK    	61 -82	; "|"
	117	[68]	LOADK    	62 -83	; "\217\128"
	118	[68]	SETLIST  	58 4 1	; 1
	119	[68]	NEWTABLE 	59 4 0
	120	[69]	LOADK    	60 -84	; "\195\151"
	121	[69]	MOVE     	61 32
	122	[69]	LOADK    	62 -85	; "?"
	123	[69]	LOADK    	63 -86	; "\217\145"
	124	[69]	SETLIST  	59 4 1	; 1
	125	[69]	NEWTABLE 	60 4 0
	126	[70]	LOADK    	61 -87	; "\216\155"
	127	[70]	MOVE     	62 13
	128	[70]	LOADK    	63 -88	; "~"
	129	[70]	LOADK    	64 -89	; "\217\140"
	130	[70]	SETLIST  	60 4 1	; 1
	131	[70]	NEWTABLE 	61 4 0
	132	[71]	LOADK    	62 -90	; "<"
	133	[71]	MOVE     	63 8
	134	[71]	LOADK    	64 -90	; "<"
	135	[71]	LOADK    	65 -91	; "\217\139"
	136	[71]	SETLIST  	61 4 1	; 1
	137	[71]	NEWTABLE 	62 4 0
	138	[72]	LOADK    	63 -92	; ">"
	139	[72]	MOVE     	64 9
	140	[72]	LOADK    	65 -92	; ">"
	141	[72]	LOADK    	66 -88	; "~"
	142	[72]	SETLIST  	62 4 1	; 1
	143	[73]	SETLIST  	50 12 1	; 1
	144	[73]	NEWTABLE 	51 11 0
	145	[75]	NEWTABLE 	52 4 0
	146	[76]	MOVE     	53 41
	147	[76]	MOVE     	54 26
	148	[76]	LOADK    	55 -93	; "\226\128\166"
	149	[76]	LOADK    	56 -94	; "4"
	150	[76]	SETLIST  	52 4 1	; 1
	151	[76]	NEWTABLE 	53 4 0
	152	[77]	MOVE     	54 46
	153	[77]	MOVE     	55 20
	154	[77]	LOADK    	56 -95	; "$"
	155	[77]	LOADK    	57 -96	; "5"
	156	[77]	SETLIST  	53 4 1	; 1
	157	[77]	NEWTABLE 	54 4 0
	158	[78]	LOADK    	55 -97	; "]"
	159	[78]	MOVE     	56 15
	160	[78]	LOADK    	57 -98	; "%"
	161	[78]	LOADK    	58 -99	; "6"
	162	[78]	SETLIST  	54 4 1	; 1
	163	[78]	NEWTABLE 	55 4 0
	164	[79]	LOADK    	56 -100	; "["
	165	[79]	MOVE     	57 7
	166	[79]	LOADK    	58 -101	; "^"
	167	[79]	LOADK    	59 -102	; ";"
	168	[79]	SETLIST  	55 4 1	; 1
	169	[79]	NEWTABLE 	56 4 0
	170	[80]	LOADK    	57 -103	; "\239\187\183"
	171	[80]	MOVE     	58 17
	172	[80]	LOADK    	59 -104	; ":"
	173	[80]	LOADK    	60 -105	; "'"
	174	[80]	SETLIST  	56 4 1	; 1
	175	[80]	NEWTABLE 	57 4 0
	176	[81]	LOADK    	58 -106	; "\216\163"
	177	[81]	MOVE     	59 6
	178	[81]	LOADK    	60 -107	; "\""
	179	[81]	LOADK    	61 -108	; "\\"
	180	[81]	SETLIST  	57 4 1	; 1
	181	[81]	NEWTABLE 	58 4 0
	182	[82]	LOADK    	59 -83	; "\217\128"
	183	[82]	MOVE     	60 27
	184	[82]	LOADK    	61 -109	; "}"
	185	[82]	LOADK    	62 -86	; "\217\145"
	186	[82]	SETLIST  	58 4 1	; 1
	187	[82]	NEWTABLE 	59 4 0
	188	[83]	LOADK    	60 -110	; "\216\140"
	189	[83]	MOVE     	61 19
	190	[83]	LOADK    	62 -111	; "{"
	191	[83]	LOADK    	63 -105	; "'"
	192	[83]	SETLIST  	59 4 1	; 1
	193	[83]	NEWTABLE 	60 4 0
	194	[84]	LOADK    	61 -112	; "/"
	195	[84]	MOVE     	62 18
	196	[84]	LOADK    	63 -113	; "_"
	197	[84]	LOADK    	64 -114	; "\217\144"
	198	[84]	SETLIST  	60 4 1	; 1
	199	[84]	NEWTABLE 	61 4 0
	200	[85]	LOADK    	62 -104	; ":"
	201	[85]	MOVE     	63 16
	202	[85]	LOADK    	64 -81	; "\195\183"
	203	[85]	LOADK    	65 -115	; "\217\143"
	204	[85]	SETLIST  	61 4 1	; 1
	205	[85]	NEWTABLE 	62 4 0
	206	[86]	LOADK    	63 -107	; "\""
	207	[86]	MOVE     	64 14
	208	[86]	LOADK    	65 -84	; "\195\151"
	209	[86]	LOADK    	66 -116	; "\217\142"
	210	[86]	SETLIST  	62 4 1	; 1
	211	[87]	SETLIST  	51 11 1	; 1
	212	[87]	NEWTABLE 	52 11 0
	213	[89]	NEWTABLE 	53 4 0
	214	[90]	MOVE     	54 43
	215	[90]	MOVE     	55 29
	216	[90]	LOADK    	56 -117	; "&"
	217	[90]	LOADK    	57 -118	; "7"
	218	[90]	SETLIST  	53 4 1	; 1
	219	[90]	NEWTABLE 	54 4 0
	220	[91]	MOVE     	55 42
	221	[91]	MOVE     	56 33
	222	[91]	LOADK    	57 -119	; "*"
	223	[91]	LOADK    	58 -120	; "8"
	224	[91]	SETLIST  	54 4 1	; 1
	225	[91]	NEWTABLE 	55 4 0
	226	[92]	LOADK    	56 -109	; "}"
	227	[92]	MOVE     	57 34
	228	[92]	LOADK    	58 -121	; "\194\163"
	229	[92]	LOADK    	59 -122	; "9"
	230	[92]	SETLIST  	55 4 1	; 1
	231	[92]	NEWTABLE 	56 4 0
	232	[93]	LOADK    	57 -111	; "{"
	233	[93]	MOVE     	58 25
	234	[93]	LOADK    	59 -113	; "_"
	235	[93]	MOVE     	60 2
	236	[93]	SETLIST  	56 4 1	; 1
	237	[93]	NEWTABLE 	57 4 0
	238	[94]	LOADK    	58 -123	; "\239\187\181"
	239	[94]	MOVE     	59 35
	240	[94]	LOADK    	60 -112	; "/"
	241	[94]	MOVE     	61 3
	242	[94]	SETLIST  	57 4 1	; 1
	243	[94]	NEWTABLE 	58 4 0
	244	[95]	LOADK    	59 -124	; "\216\162"
	245	[95]	MOVE     	60 36
	246	[95]	LOADK    	61 -125	; "\226\128\152"
	247	[95]	LOADK    	62 -100	; "["
	248	[95]	SETLIST  	58 4 1	; 1
	249	[95]	NEWTABLE 	59 4 0
	250	[96]	LOADK    	60 -105	; "'"
	251	[96]	MOVE     	61 37
	252	[96]	LOADK    	62 -105	; "'"
	253	[96]	LOADK    	63 -97	; "]"
	254	[96]	SETLIST  	59 4 1	; 1
	255	[96]	NEWTABLE 	60 4 0
	256	[97]	MOVE     	61 47
	257	[97]	MOVE     	62 11
	258	[97]	LOADK    	63 -71	; "#"
	259	[97]	LOADK    	64 -126	; "\226\134\145"
	260	[97]	SETLIST  	60 4 1	; 1
	261	[97]	NEWTABLE 	61 4 0
	262	[98]	LOADK    	62 -127	; "."
	263	[98]	MOVE     	63 12
	264	[98]	LOADK    	64 -128	; "@"
	265	[98]	LOADK    	65 -129	; "\226\134\147"
	266	[98]	SETLIST  	61 4 1	; 1
	267	[98]	NEWTABLE 	62 4 0
	268	[99]	LOADK    	63 -130	; "\216\159"
	269	[99]	MOVE     	64 28
	270	[99]	LOADK    	65 -68	; "!"
	271	[99]	MOVE     	66 4
	272	[99]	SETLIST  	62 4 1	; 1
	273	[99]	NEWTABLE 	63 0 3
	274	[100]	SETTABLE 	63 -131 -132	; "label" "\238\157\173"
	275	[101]	SETTABLE 	63 -133 -134	; "width" 1.5
	276	[102]	SETTABLE 	63 -135 -64	; "bold" false
	277	[104]	SETLIST  	52 11 1	; 1
	278	[104]	NEWTABLE 	53 8 0
	279	[106]	NEWTABLE 	54 4 1
	280	[107]	LOADK    	55 -55	; "\216\168\216\175\217\145\217\132"
	281	[107]	LOADK    	56 -55	; "\216\168\216\175\217\145\217\132"
	282	[107]	LOADK    	57 -55	; "\216\168\216\175\217\145\217\132"
	283	[107]	LOADK    	58 -55	; "\216\168\216\175\217\145\217\132"
	284	[108]	SETTABLE 	54 -133 -136	; "width" 1.4
	285	[108]	SETLIST  	54 4 1	; 1
	286	[108]	NEWTABLE 	55 0 1
	287	[109]	SETTABLE 	55 -131 -61	; "label" "\240\159\140\144"
	288	[109]	NEWTABLE 	56 4 1
	289	[110]	LOADK    	57 -58	; "\216\177\217\133\216\178"
	290	[110]	LOADK    	58 -58	; "\216\177\217\133\216\178"
	291	[110]	LOADK    	59 -59	; "\216\173\216\177\217\129"
	292	[110]	LOADK    	60 -59	; "\216\173\216\177\217\129"
	293	[111]	SETTABLE 	56 -133 -137	; "width" 1.2
	294	[111]	SETLIST  	56 4 1	; 1
	295	[111]	NEWTABLE 	57 4 2
	296	[112]	SETTABLE 	57 -131 -138	; "label" "\217\133\216\179\216\167\217\129\216\169"
	297	[113]	LOADK    	58 -139	; " "
	298	[113]	LOADK    	59 -139	; " "
	299	[113]	LOADK    	60 -139	; " "
	300	[113]	LOADK    	61 -139	; " "
	301	[114]	SETTABLE 	57 -133 -140	; "width" 3
	302	[114]	SETLIST  	57 4 1	; 1
	303	[114]	NEWTABLE 	58 4 0
	304	[115]	MOVE     	59 2
	305	[115]	MOVE     	60 47
	306	[115]	LOADK    	61 -141	; "\226\128\156"
	307	[115]	LOADK    	62 -142	; "\226\134\144"
	308	[115]	SETLIST  	58 4 1	; 1
	309	[115]	NEWTABLE 	59 4 0
	310	[116]	MOVE     	60 3
	311	[116]	MOVE     	61 3
	312	[116]	LOADK    	62 -143	; "\226\128\157"
	313	[116]	LOADK    	63 -144	; "\226\134\146"
	314	[116]	SETLIST  	59 4 1	; 1
	315	[116]	NEWTABLE 	60 4 2
	316	[117]	SETTABLE 	60 -131 -145	; "label" "\216\173\216\177\217\131\216\167\216\170"
	317	[117]	MOVE     	61 38
	318	[117]	MOVE     	62 38
	319	[117]	MOVE     	63 38
	320	[117]	MOVE     	64 38
	321	[118]	SETTABLE 	60 -133 -134	; "width" 1.5
	322	[118]	SETLIST  	60 4 1	; 1
	323	[118]	NEWTABLE 	61 4 2
	324	[119]	SETTABLE 	61 -131 -146	; "label" "\226\174\160"
	325	[120]	LOADK    	62 -147	; "\n"
	326	[120]	LOADK    	63 -147	; "\n"
	327	[120]	LOADK    	64 -147	; "\n"
	328	[120]	LOADK    	65 -147	; "\n"
	329	[121]	SETTABLE 	61 -133 -134	; "width" 1.5
	330	[122]	SETLIST  	61 4 1	; 1
	331	[123]	SETLIST  	53 8 1	; 1
	332	[124]	SETLIST  	49 4 1	; 1
	333	[124]	SETTABLE 	48 -65 49	; "keys" -
	334	[125]	RETURN   	48 2
	335	[125]	RETURN   	0 1
