-- BYTECODE -- ar_AA_keyboard.lua:0-126
0001    GGET     0   0      ; "require"
0002    KSTR     1   1      ; "ui/data/keyboardlayouts/keypopup/en_popu"~
0003    CALL     0   2   2
0004    GGET     1   0      ; "require"
0005    KSTR     2   2      ; "ui/data/keyboardlayouts/keypopup/ar_AA_p"~
0006    CALL     1   2   2
0007    TGETS    2   0   3  ; "com"
0008    TGETS    3   0   4  ; "prd"
0009    TGETS    4   0   5  ; "_at"
0010    TGETS    5   0   6  ; "_eq"
0011    TGETS    6   1   7  ; "alef"
0012    TGETS    7   1   8  ; "ba"
0013    TGETS    8   1   9  ; "jeem"
0014    TGETS    9   1  10  ; "daal"
0015    TGETS   10   1  11  ; "h_aa"
0016    TGETS   11   1  12  ; "waw"
0017    TGETS   12   1  13  ; "zay"
0018    TGETS   13   1  14  ; "ha"
0019    TGETS   14   1  15  ; "tah"
0020    TGETS   15   1  16  ; "yaa"
0021    TGETS   16   1  17  ; "kaf"
0022    TGETS   17   1  18  ; "lam"
0023    TGETS   18   1  19  ; "meem"
0024    TGETS   19   1  20  ; "nun"
0025    TGETS   20   1  21  ; "seen"
0026    TGETS   21   1  22  ; "ayin"
0027    TGETS   22   1  23  ; "fah"
0028    TGETS   23   1  24  ; "saad"
0029    TGETS   24   1  25  ; "qaf"
0030    TGETS   25   1  26  ; "raa"
0031    TGETS   26   1  27  ; "sheen"
0032    TGETS   27   1  28  ; "taa"
0033    TGETS   28   1  29  ; "thaa"
0034    TGETS   29   1  30  ; "thaal"
0035    TGETS   30   1  31  ; "dhad"
0036    TGETS   31   1  32  ; "ghayn"
0037    TGETS   32   1  33  ; "khaa"
0038    TGETS   33   1  34  ; "hamza"
0039    TGETS   34   1  35  ; "wawhamza"
0040    TGETS   35   1  36  ; "laa"
0041    TGETS   36   1  37  ; "alefmaqsoura"
0042    TGETS   37   1  38  ; "taamarbouta"
0043    TGETS   38   1  39  ; "diacritics"
0044    TGETS   39   1  40  ; "diacritic_fat_ha"
0045    TGETS   40   1  41  ; "diacritic_damma"
0046    TGETS   41   1  42  ; "diacritic_kasra"
0047    TGETS   42   1  43  ; "diacritic_sukoon"
0048    TGETS   43   1  44  ; "diacritic_shadda"
0049    TGETS   44   1  45  ; "diacritic_tanween_fath"
0050    TGETS   45   1  46  ; "diacritic_tanween_damm"
0051    TGETS   46   1  47  ; "diacritic_tanween_kasr"
0052    TGETS   47   1  48  ; "arabic_comma"
0053    TDUP    48  49
0054    TDUP    49  50
0055    TSETS   49  48  51  ; "shiftmode_keys"
0056    TDUP    49  52
0057    TSETS   49  48  53  ; "symbolmode_keys"
0058    TDUP    49  54
0059    TSETS   49  48  55  ; "utf8mode_keys"
0060    TDUP    49  56
0061    TSETS   49  48  57  ; "umlautmode_keys"
0062    TNEW    49   5
0063    TNEW    50  13
0064    TDUP    51  58
0065    TSETB   39  51   1
0066    TSETB   30  51   2
0067    TSETB   51  50   1
0068    TDUP    51  59
0069    TSETB   44  51   1
0070    TSETB   23  51   2
0071    TSETB   51  50   2
0072    TDUP    51  60
0073    TSETB   40  51   1
0074    TSETB   28  51   2
0075    TSETB    4  51   3
0076    TSETB   51  50   3
0077    TDUP    51  61
0078    TSETB   45  51   1
0079    TSETB   24  51   2
0080    TSETB   51  50   4
0081    TDUP    51  62
0082    TSETB   22  51   2
0083    TSETB    5  51   4
0084    TSETB   51  50   5
0085    TDUP    51  63
0086    TSETB   31  51   2
0087    TSETB   51  50   6
0088    TDUP    51  64
0089    TSETB   21  51   2
0090    TSETB   51  50   7
0091    TDUP    51  65
0092    TSETB   10  51   2
0093    TSETB   51  50   8
0094    TDUP    51  66
0095    TSETB   32  51   2
0096    TSETB   51  50   9
0097    TDUP    51  67
0098    TSETB   13  51   2
0099    TSETB   51  50  10
0100    TDUP    51  68
0101    TSETB    8  51   2
0102    TSETB   51  50  11
0103    TDUP    51  69
0104    TSETB    9  51   2
0105    TSETB   51  50  12
0106    TSETB   50  49   1
0107    TNEW    50  12
0108    TDUP    51  70
0109    TSETB   41  51   1
0110    TSETB   26  51   2
0111    TSETB   51  50   1
0112    TDUP    51  71
0113    TSETB   46  51   1
0114    TSETB   20  51   2
0115    TSETB   51  50   2
0116    TDUP    51  72
0117    TSETB   15  51   2
0118    TSETB   51  50   3
0119    TDUP    51  73
0120    TSETB    7  51   2
0121    TSETB   51  50   4
0122    TDUP    51  74
0123    TSETB   17  51   2
0124    TSETB   51  50   5
0125    TDUP    51  75
0126    TSETB    6  51   2
0127    TSETB   51  50   6
0128    TDUP    51  76
0129    TSETB   27  51   2
0130    TSETB   51  50   7
0131    TDUP    51  77
0132    TSETB   19  51   2
0133    TSETB   51  50   8
0134    TDUP    51  78
0135    TSETB   18  51   2
0136    TSETB   51  50   9
0137    TDUP    51  79
0138    TSETB   16  51   2
0139    TSETB   51  50  10
0140    TDUP    51  80
0141    TSETB   14  51   2
0142    TSETB   51  50  11
0143    TSETB   50  49   2
0144    TNEW    50  12
0145    TDUP    51  81
0146    TSETB   43  51   1
0147    TSETB   29  51   2
0148    TSETB   51  50   1
0149    TDUP    51  82
0150    TSETB   42  51   1
0151    TSETB   33  51   2
0152    TSETB   51  50   2
0153    TDUP    51  83
0154    TSETB   34  51   2
0155    TSETB   51  50   3
0156    TDUP    51  84
0157    TSETB   25  51   2
0158    TSETB    2  51   4
0159    TSETB   51  50   4
0160    TDUP    51  85
0161    TSETB   35  51   2
0162    TSETB    3  51   4
0163    TSETB   51  50   5
0164    TDUP    51  86
0165    TSETB   36  51   2
0166    TSETB   51  50   6
0167    TDUP    51  87
0168    TSETB   37  51   2
0169    TSETB   51  50   7
0170    TDUP    51  88
0171    TSETB   47  51   1
0172    TSETB   11  51   2
0173    TSETB   51  50   8
0174    TDUP    51  89
0175    TSETB   12  51   2
0176    TSETB   51  50   9
0177    TDUP    51  90
0178    TSETB   28  51   2
0179    TSETB    4  51   4
0180    TSETB   51  50  10
0181    TDUP    51  91
0182    TSETB   51  50  11
0183    TSETB   50  49   3
0184    TNEW    50   9
0185    TDUP    51  92
0186    TSETB   51  50   1
0187    TDUP    51  93
0188    TSETB   51  50   2
0189    TDUP    51  94
0190    TSETB   51  50   3
0191    TDUP    51  95
0192    TSETB   51  50   4
0193    TDUP    51  96
0194    TSETB    2  51   1
0195    TSETB   47  51   2
0196    TSETB   51  50   5
0197    TDUP    51  97
0198    TSETB    3  51   1
0199    TSETB    3  51   2
0200    TSETB   51  50   6
0201    TDUP    51  98
0202    TSETB   38  51   1
0203    TSETB   38  51   2
0204    TSETB   38  51   3
0205    TSETB   38  51   4
0206    TSETB   51  50   7
0207    TDUP    51  99
0208    TSETB   51  50   8
0209    TSETB   50  49   4
0210    TSETS   49  48 100  ; "keys"
0211    RET1    48   2

