
main <./spec/unit/autofrontlight_spec.lua:0,0> (5 instructions, 20 bytes at 0x7fbe69c068d0)
0+ params, 3 slots, 0 upvalues, 0 locals, 2 constants, 1 function
	1	[1]	GETGLOBAL	0 -1	; describe
	2	[1]	LOADK    	1 -2	; "AutoFrontlight widget tests"
	3	[142]	CLOSURE  	2 0	; 0x7fbe69c06b80
	4	[1]	CALL     	0 3 1
	5	[142]	RETURN   	0 1

function <./spec/unit/autofrontlight_spec.lua:1,142> (60 instructions, 240 bytes at 0x7fbe69c06b80)
0 params, 9 slots, 0 upvalues, 6 locals, 9 constants, 8 functions
	1	[4]	GETGLOBAL	6 -1	; setup
	2	[21]	CLOSURE  	7 0	; 0x7fbe69c06d80
	3	[21]	MOVE     	0 2
	4	[21]	MOVE     	0 1
	5	[4]	CALL     	6 2 1
	6	[23]	GETGLOBAL	6 -2	; teardown
	7	[27]	CLOSURE  	7 1	; 0x7fbe69c07910
	8	[27]	MOVE     	0 2
	9	[23]	CALL     	6 2 1
	10	[29]	GETGLOBAL	6 -3	; before_each
	11	[56]	CLOSURE  	7 2	; 0x7fbe69c07bb0
	12	[56]	MOVE     	0 0
	13	[56]	MOVE     	0 1
	14	[56]	MOVE     	0 5
	15	[56]	MOVE     	0 3
	16	[56]	MOVE     	0 2
	17	[29]	CALL     	6 2 1
	18	[58]	GETGLOBAL	6 -4	; after_each
	19	[65]	CLOSURE  	7 3	; 0x7fbe69c08460
	20	[65]	MOVE     	0 4
	21	[65]	MOVE     	0 2
	22	[65]	MOVE     	0 5
	23	[58]	CALL     	6 2 1
	24	[67]	GETGLOBAL	6 -5	; it
	25	[67]	LOADK    	7 -6	; "should automatically turn on or off frontlight"
	26	[109]	CLOSURE  	8 4	; 0x7fbe69c07870
	27	[109]	MOVE     	0 4
	28	[109]	MOVE     	0 3
	29	[109]	MOVE     	0 0
	30	[109]	MOVE     	0 2
	31	[109]	MOVE     	0 5
	32	[67]	CALL     	6 3 1
	33	[111]	GETGLOBAL	6 -5	; it
	34	[111]	LOADK    	7 -7	; "should turn on frontlight at the begining"
	35	[118]	CLOSURE  	8 5	; 0x7fbe69c083e0
	36	[118]	MOVE     	0 0
	37	[118]	MOVE     	0 4
	38	[118]	MOVE     	0 3
	39	[118]	MOVE     	0 2
	40	[118]	MOVE     	0 5
	41	[111]	CALL     	6 3 1
	42	[120]	GETGLOBAL	6 -5	; it
	43	[120]	LOADK    	7 -8	; "should turn off frontlight at the begining"
	44	[127]	CLOSURE  	8 6	; 0x7fbe69c08630
	45	[127]	MOVE     	0 0
	46	[127]	MOVE     	0 4
	47	[127]	MOVE     	0 3
	48	[127]	MOVE     	0 2
	49	[127]	MOVE     	0 5
	50	[120]	CALL     	6 3 1
	51	[129]	GETGLOBAL	6 -5	; it
	52	[129]	LOADK    	7 -9	; "should handle configuration update"
	53	[141]	CLOSURE  	8 7	; 0x7fbe69c06680
	54	[141]	MOVE     	0 0
	55	[141]	MOVE     	0 4
	56	[141]	MOVE     	0 3
	57	[141]	MOVE     	0 2
	58	[141]	MOVE     	0 5
	59	[129]	CALL     	6 3 1
	60	[142]	RETURN   	0 1

function <./spec/unit/autofrontlight_spec.lua:4,21> (36 instructions, 144 bytes at 0x7fbe69c06d80)
0 params, 4 slots, 2 upvalues, 0 locals, 15 constants, 2 functions
	1	[5]	GETGLOBAL	0 -1	; require
	2	[5]	LOADK    	1 -2	; "commonrequire"
	3	[5]	CALL     	0 2 1
	4	[6]	GETGLOBAL	0 -3	; package
	5	[6]	GETTABLE 	0 0 -4	; "unloadAll"
	6	[6]	CALL     	0 1 1
	7	[7]	GETGLOBAL	0 -1	; require
	8	[7]	LOADK    	1 -5	; "document/canvascontext"
	9	[7]	CALL     	0 2 2
	10	[7]	SELF     	0 0 -6	; "init"
	11	[7]	GETGLOBAL	2 -1	; require
	12	[7]	LOADK    	3 -7	; "device"
	13	[7]	CALL     	2 2 0
	14	[7]	CALL     	0 0 1
	15	[9]	GETGLOBAL	0 -1	; require
	16	[9]	LOADK    	1 -8	; "mock_time"
	17	[9]	CALL     	0 2 2
	18	[9]	SETUPVAL 	0 0	; MockTime
	19	[10]	GETUPVAL 	0 0	; MockTime
	20	[10]	SELF     	0 0 -9	; "install"
	21	[10]	CALL     	0 2 1
	22	[12]	GETGLOBAL	0 -1	; require
	23	[12]	LOADK    	1 -10	; "device/generic/powerd"
	24	[12]	CALL     	0 2 2
	25	[12]	SELF     	0 0 -11	; "new"
	26	[12]	NEWTABLE 	2 0 1
	27	[13]	SETTABLE 	2 -12 -13	; "frontlight" 0
	28	[12]	CALL     	0 3 2
	29	[14]	SETUPVAL 	0 1	; PowerD
	30	[15]	GETUPVAL 	0 1	; PowerD
	31	[17]	CLOSURE  	1 0	; 0x7fbe69c07440
	32	[17]	SETTABLE 	0 -14 1	; "frontlightIntensityHW" -
	33	[18]	GETUPVAL 	0 1	; PowerD
	34	[20]	CLOSURE  	1 1	; 0x7fbe69c07370
	35	[20]	SETTABLE 	0 -15 1	; "setIntensityHW" -
	36	[21]	RETURN   	0 1

function <./spec/unit/autofrontlight_spec.lua:15,17> (3 instructions, 12 bytes at 0x7fbe69c07440)
0 params, 2 slots, 0 upvalues, 0 locals, 1 constant, 0 functions
	1	[16]	LOADK    	0 -1	; 2
	2	[16]	RETURN   	0 2
	3	[17]	RETURN   	0 1

function <./spec/unit/autofrontlight_spec.lua:18,20> (2 instructions, 8 bytes at 0x7fbe69c07370)
2 params, 2 slots, 0 upvalues, 2 locals, 1 constant, 0 functions
	1	[19]	SETTABLE 	0 -1 1	; "frontlight" -
	2	[20]	RETURN   	0 1

function <./spec/unit/autofrontlight_spec.lua:23,27> (15 instructions, 60 bytes at 0x7fbe69c07910)
0 params, 4 slots, 1 upvalue, 0 locals, 7 constants, 0 functions
	1	[24]	GETUPVAL 	0 0	; MockTime
	2	[24]	SELF     	0 0 -1	; "uninstall"
	3	[24]	CALL     	0 2 1
	4	[25]	GETGLOBAL	0 -2	; package
	5	[25]	GETTABLE 	0 0 -3	; "unloadAll"
	6	[25]	CALL     	0 1 1
	7	[26]	GETGLOBAL	0 -4	; require
	8	[26]	LOADK    	1 -5	; "document/canvascontext"
	9	[26]	CALL     	0 2 2
	10	[26]	SELF     	0 0 -6	; "init"
	11	[26]	GETGLOBAL	2 -4	; require
	12	[26]	LOADK    	3 -7	; "device"
	13	[26]	CALL     	2 2 0
	14	[26]	CALL     	0 0 1
	15	[27]	RETURN   	0 1

function <./spec/unit/autofrontlight_spec.lua:29,56> (67 instructions, 268 bytes at 0x7fbe69c07bb0)
0 params, 5 slots, 5 upvalues, 0 locals, 31 constants, 4 functions
	1	[30]	GETGLOBAL	0 -1	; require
	2	[30]	LOADK    	1 -2	; "device"
	3	[30]	CALL     	0 2 2
	4	[30]	SETUPVAL 	0 0	; Device
	5	[31]	GETUPVAL 	0 0	; Device
	6	[31]	CLOSURE  	1 0	; 0x7fbe69c08190
	7	[31]	SETTABLE 	0 -3 1	; "isKindle" -
	8	[32]	GETUPVAL 	0 0	; Device
	9	[32]	SETTABLE 	0 -4 -5	; "model" "KindleVoyage"
	10	[33]	GETUPVAL 	0 0	; Device
	11	[33]	SETTABLE 	0 -6 -7	; "brightness" 0
	12	[34]	GETUPVAL 	0 0	; Device
	13	[34]	CLOSURE  	1 1	; 0x7fbe69c08080
	14	[34]	SETTABLE 	0 -8 1	; "hasFrontlight" -
	15	[35]	GETUPVAL 	0 0	; Device
	16	[35]	GETUPVAL 	1 1	; PowerD
	17	[35]	SELF     	1 1 -10	; "new"
	18	[35]	NEWTABLE 	3 0 1
	19	[36]	GETUPVAL 	4 0	; Device
	20	[36]	SETTABLE 	3 -2 4	; "device" -
	21	[35]	CALL     	1 3 2
	22	[37]	SETTABLE 	0 -9 1	; "powerd" -
	23	[38]	GETUPVAL 	0 0	; Device
	24	[40]	CLOSURE  	1 2	; 0x7fbe69c08850
	25	[40]	SETTABLE 	0 -11 1	; "ambientBrightnessLevel" -
	26	[41]	GETUPVAL 	0 0	; Device
	27	[41]	GETTABLE 	0 0 -12	; "input"
	28	[41]	CLOSURE  	1 3	; 0x7fbe69c08b00
	29	[41]	SETTABLE 	0 -13 1	; "waitEvent" -
	30	[42]	GETGLOBAL	0 -1	; require
	31	[42]	LOADK    	1 -14	; "luasettings"
	32	[42]	CALL     	0 2 2
	33	[43]	SELF     	0 0 -15	; "open"
	34	[43]	GETGLOBAL	2 -1	; require
	35	[43]	LOADK    	3 -16	; "datastorage"
	36	[43]	CALL     	2 2 2
	37	[43]	SELF     	2 2 -17	; "getSettingsDir"
	38	[43]	CALL     	2 2 2
	39	[43]	LOADK    	3 -18	; "/autofrontlight.lua"
	40	[43]	CONCAT   	2 2 3
	41	[43]	CALL     	0 3 2
	42	[44]	SELF     	0 0 -19	; "saveSetting"
	43	[44]	LOADK    	2 -20	; "enable"
	44	[44]	LOADK    	3 -21	; "true"
	45	[44]	CALL     	0 4 2
	46	[45]	SELF     	0 0 -22	; "close"
	47	[45]	CALL     	0 2 1
	48	[47]	GETGLOBAL	0 -1	; require
	49	[47]	LOADK    	1 -23	; "ui/uimanager"
	50	[47]	CALL     	0 2 2
	51	[47]	SETUPVAL 	0 2	; UIManager
	52	[48]	GETUPVAL 	0 2	; UIManager
	53	[48]	SETTABLE 	0 -24 -25	; "_run_forever" true
	54	[50]	GETGLOBAL	0 -26	; requireBackgroundRunner
	55	[50]	CALL     	0 1 1
	56	[51]	GETGLOBAL	0 -27	; dofile
	57	[51]	LOADK    	1 -28	; "plugins/autofrontlight.koplugin/main.lua"
	58	[51]	CALL     	0 2 2
	59	[51]	SETUPVAL 	0 3	; class
	60	[54]	GETUPVAL 	0 4	; MockTime
	61	[54]	SELF     	0 0 -29	; "increase"
	62	[54]	LOADK    	2 -30	; 2
	63	[54]	CALL     	0 3 1
	64	[55]	GETUPVAL 	0 2	; UIManager
	65	[55]	SELF     	0 0 -31	; "handleInput"
	66	[55]	CALL     	0 2 1
	67	[56]	RETURN   	0 1

function <./spec/unit/autofrontlight_spec.lua:31,31> (3 instructions, 12 bytes at 0x7fbe69c08190)
0 params, 2 slots, 0 upvalues, 0 locals, 0 constants, 0 functions
	1	[31]	LOADBOOL 	0 1 0
	2	[31]	RETURN   	0 2
	3	[31]	RETURN   	0 1

function <./spec/unit/autofrontlight_spec.lua:34,34> (3 instructions, 12 bytes at 0x7fbe69c08080)
0 params, 2 slots, 0 upvalues, 0 locals, 0 constants, 0 functions
	1	[34]	LOADBOOL 	0 1 0
	2	[34]	RETURN   	0 2
	3	[34]	RETURN   	0 1

function <./spec/unit/autofrontlight_spec.lua:38,40> (3 instructions, 12 bytes at 0x7fbe69c08850)
1 param, 2 slots, 0 upvalues, 1 local, 1 constant, 0 functions
	1	[39]	GETTABLE 	1 0 -1	; "brightness"
	2	[39]	RETURN   	1 2
	3	[40]	RETURN   	0 1

function <./spec/unit/autofrontlight_spec.lua:41,41> (1 instruction, 4 bytes at 0x7fbe69c08b00)
0 params, 2 slots, 0 upvalues, 0 locals, 0 constants, 0 functions
	1	[41]	RETURN   	0 1

function <./spec/unit/autofrontlight_spec.lua:58,65> (15 instructions, 60 bytes at 0x7fbe69c08460)
0 params, 3 slots, 3 upvalues, 0 locals, 5 constants, 0 functions
	1	[59]	GETUPVAL 	0 0	; AutoFrontlight
	2	[59]	SELF     	0 0 -1	; "deprecateLastTask"
	3	[59]	CALL     	0 2 1
	4	[61]	GETUPVAL 	0 1	; MockTime
	5	[61]	SELF     	0 0 -2	; "increase"
	6	[61]	LOADK    	2 -3	; 2
	7	[61]	CALL     	0 3 1
	8	[62]	GETUPVAL 	0 2	; UIManager
	9	[62]	SELF     	0 0 -4	; "handleInput"
	10	[62]	CALL     	0 2 1
	11	[63]	LOADNIL  	0 0
	12	[63]	SETUPVAL 	0 0	; AutoFrontlight
	13	[64]	GETGLOBAL	0 -5	; stopBackgroundRunner
	14	[64]	CALL     	0 1 1
	15	[65]	RETURN   	0 1

function <./spec/unit/autofrontlight_spec.lua:67,109> (185 instructions, 740 bytes at 0x7fbe69c07870)
0 params, 4 slots, 5 upvalues, 0 locals, 14 constants, 0 functions
	1	[68]	GETUPVAL 	0 1	; class
	2	[68]	SELF     	0 0 -1	; "new"
	3	[68]	CALL     	0 2 2
	4	[68]	SETUPVAL 	0 0	; AutoFrontlight
	5	[69]	GETUPVAL 	0 2	; Device
	6	[69]	SETTABLE 	0 -2 -3	; "brightness" 3
	7	[70]	GETUPVAL 	0 3	; MockTime
	8	[70]	SELF     	0 0 -4	; "increase"
	9	[70]	LOADK    	2 -5	; 2
	10	[70]	CALL     	0 3 1
	11	[71]	GETUPVAL 	0 4	; UIManager
	12	[71]	SELF     	0 0 -6	; "handleInput"
	13	[71]	CALL     	0 2 1
	14	[72]	GETGLOBAL	0 -7	; assert
	15	[72]	GETTABLE 	0 0 -8	; "are"
	16	[72]	GETTABLE 	0 0 -9	; "equal"
	17	[72]	LOADK    	1 -10	; 0
	18	[72]	GETUPVAL 	2 2	; Device
	19	[72]	SELF     	2 2 -11	; "getPowerDevice"
	20	[72]	CALL     	2 2 2
	21	[72]	GETTABLE 	2 2 -12	; "frontlight"
	22	[72]	CALL     	0 3 1
	23	[73]	GETUPVAL 	0 2	; Device
	24	[73]	SETTABLE 	0 -2 -10	; "brightness" 0
	25	[74]	GETUPVAL 	0 3	; MockTime
	26	[74]	SELF     	0 0 -4	; "increase"
	27	[74]	LOADK    	2 -5	; 2
	28	[74]	CALL     	0 3 1
	29	[75]	GETUPVAL 	0 4	; UIManager
	30	[75]	SELF     	0 0 -6	; "handleInput"
	31	[75]	CALL     	0 2 1
	32	[76]	GETGLOBAL	0 -7	; assert
	33	[76]	GETTABLE 	0 0 -8	; "are"
	34	[76]	GETTABLE 	0 0 -9	; "equal"
	35	[76]	LOADK    	1 -5	; 2
	36	[76]	GETUPVAL 	2 2	; Device
	37	[76]	SELF     	2 2 -11	; "getPowerDevice"
	38	[76]	CALL     	2 2 2
	39	[76]	GETTABLE 	2 2 -12	; "frontlight"
	40	[76]	CALL     	0 3 1
	41	[77]	GETUPVAL 	0 2	; Device
	42	[77]	SETTABLE 	0 -2 -13	; "brightness" 1
	43	[78]	GETUPVAL 	0 3	; MockTime
	44	[78]	SELF     	0 0 -4	; "increase"
	45	[78]	LOADK    	2 -5	; 2
	46	[78]	CALL     	0 3 1
	47	[79]	GETUPVAL 	0 4	; UIManager
	48	[79]	SELF     	0 0 -6	; "handleInput"
	49	[79]	CALL     	0 2 1
	50	[80]	GETGLOBAL	0 -7	; assert
	51	[80]	GETTABLE 	0 0 -8	; "are"
	52	[80]	GETTABLE 	0 0 -9	; "equal"
	53	[80]	LOADK    	1 -5	; 2
	54	[80]	GETUPVAL 	2 2	; Device
	55	[80]	SELF     	2 2 -11	; "getPowerDevice"
	56	[80]	CALL     	2 2 2
	57	[80]	GETTABLE 	2 2 -12	; "frontlight"
	58	[80]	CALL     	0 3 1
	59	[81]	GETUPVAL 	0 2	; Device
	60	[81]	SETTABLE 	0 -2 -5	; "brightness" 2
	61	[82]	GETUPVAL 	0 3	; MockTime
	62	[82]	SELF     	0 0 -4	; "increase"
	63	[82]	LOADK    	2 -5	; 2
	64	[82]	CALL     	0 3 1
	65	[83]	GETUPVAL 	0 4	; UIManager
	66	[83]	SELF     	0 0 -6	; "handleInput"
	67	[83]	CALL     	0 2 1
	68	[84]	GETGLOBAL	0 -7	; assert
	69	[84]	GETTABLE 	0 0 -8	; "are"
	70	[84]	GETTABLE 	0 0 -9	; "equal"
	71	[84]	LOADK    	1 -5	; 2
	72	[84]	GETUPVAL 	2 2	; Device
	73	[84]	SELF     	2 2 -11	; "getPowerDevice"
	74	[84]	CALL     	2 2 2
	75	[84]	GETTABLE 	2 2 -12	; "frontlight"
	76	[84]	CALL     	0 3 1
	77	[85]	GETUPVAL 	0 2	; Device
	78	[85]	SETTABLE 	0 -2 -3	; "brightness" 3
	79	[86]	GETUPVAL 	0 3	; MockTime
	80	[86]	SELF     	0 0 -4	; "increase"
	81	[86]	LOADK    	2 -5	; 2
	82	[86]	CALL     	0 3 1
	83	[87]	GETUPVAL 	0 4	; UIManager
	84	[87]	SELF     	0 0 -6	; "handleInput"
	85	[87]	CALL     	0 2 1
	86	[88]	GETGLOBAL	0 -7	; assert
	87	[88]	GETTABLE 	0 0 -8	; "are"
	88	[88]	GETTABLE 	0 0 -9	; "equal"
	89	[88]	LOADK    	1 -10	; 0
	90	[88]	GETUPVAL 	2 2	; Device
	91	[88]	SELF     	2 2 -11	; "getPowerDevice"
	92	[88]	CALL     	2 2 2
	93	[88]	GETTABLE 	2 2 -12	; "frontlight"
	94	[88]	CALL     	0 3 1
	95	[89]	GETUPVAL 	0 2	; Device
	96	[89]	SETTABLE 	0 -2 -14	; "brightness" 4
	97	[90]	GETUPVAL 	0 3	; MockTime
	98	[90]	SELF     	0 0 -4	; "increase"
	99	[90]	LOADK    	2 -5	; 2
	100	[90]	CALL     	0 3 1
	101	[91]	GETUPVAL 	0 4	; UIManager
	102	[91]	SELF     	0 0 -6	; "handleInput"
	103	[91]	CALL     	0 2 1
	104	[92]	GETGLOBAL	0 -7	; assert
	105	[92]	GETTABLE 	0 0 -8	; "are"
	106	[92]	GETTABLE 	0 0 -9	; "equal"
	107	[92]	LOADK    	1 -10	; 0
	108	[92]	GETUPVAL 	2 2	; Device
	109	[92]	SELF     	2 2 -11	; "getPowerDevice"
	110	[92]	CALL     	2 2 2
	111	[92]	GETTABLE 	2 2 -12	; "frontlight"
	112	[92]	CALL     	0 3 1
	113	[93]	GETUPVAL 	0 2	; Device
	114	[93]	SETTABLE 	0 -2 -3	; "brightness" 3
	115	[94]	GETUPVAL 	0 3	; MockTime
	116	[94]	SELF     	0 0 -4	; "increase"
	117	[94]	LOADK    	2 -5	; 2
	118	[94]	CALL     	0 3 1
	119	[95]	GETUPVAL 	0 4	; UIManager
	120	[95]	SELF     	0 0 -6	; "handleInput"
	121	[95]	CALL     	0 2 1
	122	[96]	GETGLOBAL	0 -7	; assert
	123	[96]	GETTABLE 	0 0 -8	; "are"
	124	[96]	GETTABLE 	0 0 -9	; "equal"
	125	[96]	LOADK    	1 -10	; 0
	126	[96]	GETUPVAL 	2 2	; Device
	127	[96]	SELF     	2 2 -11	; "getPowerDevice"
	128	[96]	CALL     	2 2 2
	129	[96]	GETTABLE 	2 2 -12	; "frontlight"
	130	[96]	CALL     	0 3 1
	131	[97]	GETUPVAL 	0 2	; Device
	132	[97]	SETTABLE 	0 -2 -5	; "brightness" 2
	133	[98]	GETUPVAL 	0 3	; MockTime
	134	[98]	SELF     	0 0 -4	; "increase"
	135	[98]	LOADK    	2 -5	; 2
	136	[98]	CALL     	0 3 1
	137	[99]	GETUPVAL 	0 4	; UIManager
	138	[99]	SELF     	0 0 -6	; "handleInput"
	139	[99]	CALL     	0 2 1
	140	[100]	GETGLOBAL	0 -7	; assert
	141	[100]	GETTABLE 	0 0 -8	; "are"
	142	[100]	GETTABLE 	0 0 -9	; "equal"
	143	[100]	LOADK    	1 -10	; 0
	144	[100]	GETUPVAL 	2 2	; Device
	145	[100]	SELF     	2 2 -11	; "getPowerDevice"
	146	[100]	CALL     	2 2 2
	147	[100]	GETTABLE 	2 2 -12	; "frontlight"
	148	[100]	CALL     	0 3 1
	149	[101]	GETUPVAL 	0 2	; Device
	150	[101]	SETTABLE 	0 -2 -13	; "brightness" 1
	151	[102]	GETUPVAL 	0 3	; MockTime
	152	[102]	SELF     	0 0 -4	; "increase"
	153	[102]	LOADK    	2 -5	; 2
	154	[102]	CALL     	0 3 1
	155	[103]	GETUPVAL 	0 4	; UIManager
	156	[103]	SELF     	0 0 -6	; "handleInput"
	157	[103]	CALL     	0 2 1
	158	[104]	GETGLOBAL	0 -7	; assert
	159	[104]	GETTABLE 	0 0 -8	; "are"
	160	[104]	GETTABLE 	0 0 -9	; "equal"
	161	[104]	LOADK    	1 -5	; 2
	162	[104]	GETUPVAL 	2 2	; Device
	163	[104]	SELF     	2 2 -11	; "getPowerDevice"
	164	[104]	CALL     	2 2 2
	165	[104]	GETTABLE 	2 2 -12	; "frontlight"
	166	[104]	CALL     	0 3 1
	167	[105]	GETUPVAL 	0 2	; Device
	168	[105]	SETTABLE 	0 -2 -10	; "brightness" 0
	169	[106]	GETUPVAL 	0 3	; MockTime
	170	[106]	SELF     	0 0 -4	; "increase"
	171	[106]	LOADK    	2 -5	; 2
	172	[106]	CALL     	0 3 1
	173	[107]	GETUPVAL 	0 4	; UIManager
	174	[107]	SELF     	0 0 -6	; "handleInput"
	175	[107]	CALL     	0 2 1
	176	[108]	GETGLOBAL	0 -7	; assert
	177	[108]	GETTABLE 	0 0 -8	; "are"
	178	[108]	GETTABLE 	0 0 -9	; "equal"
	179	[108]	LOADK    	1 -5	; 2
	180	[108]	GETUPVAL 	2 2	; Device
	181	[108]	SELF     	2 2 -11	; "getPowerDevice"
	182	[108]	CALL     	2 2 2
	183	[108]	GETTABLE 	2 2 -12	; "frontlight"
	184	[108]	CALL     	0 3 1
	185	[109]	RETURN   	0 1

function <./spec/unit/autofrontlight_spec.lua:111,118> (28 instructions, 112 bytes at 0x7fbe69c083e0)
0 params, 4 slots, 5 upvalues, 0 locals, 12 constants, 0 functions
	1	[112]	GETUPVAL 	0 0	; Device
	2	[112]	SELF     	0 0 -1	; "getPowerDevice"
	3	[112]	CALL     	0 2 2
	4	[112]	SELF     	0 0 -2	; "turnOffFrontlight"
	5	[112]	CALL     	0 2 1
	6	[113]	GETUPVAL 	0 0	; Device
	7	[113]	SETTABLE 	0 -3 -4	; "brightness" 0
	8	[114]	GETUPVAL 	0 2	; class
	9	[114]	SELF     	0 0 -5	; "new"
	10	[114]	CALL     	0 2 2
	11	[114]	SETUPVAL 	0 1	; AutoFrontlight
	12	[115]	GETUPVAL 	0 3	; MockTime
	13	[115]	SELF     	0 0 -6	; "increase"
	14	[115]	LOADK    	2 -7	; 2
	15	[115]	CALL     	0 3 1
	16	[116]	GETUPVAL 	0 4	; UIManager
	17	[116]	SELF     	0 0 -8	; "handleInput"
	18	[116]	CALL     	0 2 1
	19	[117]	GETGLOBAL	0 -9	; assert
	20	[117]	GETTABLE 	0 0 -10	; "are"
	21	[117]	GETTABLE 	0 0 -11	; "equal"
	22	[117]	LOADK    	1 -7	; 2
	23	[117]	GETUPVAL 	2 0	; Device
	24	[117]	SELF     	2 2 -1	; "getPowerDevice"
	25	[117]	CALL     	2 2 2
	26	[117]	GETTABLE 	2 2 -12	; "frontlight"
	27	[117]	CALL     	0 3 1
	28	[118]	RETURN   	0 1

function <./spec/unit/autofrontlight_spec.lua:120,127> (28 instructions, 112 bytes at 0x7fbe69c08630)
0 params, 4 slots, 5 upvalues, 0 locals, 13 constants, 0 functions
	1	[121]	GETUPVAL 	0 0	; Device
	2	[121]	SELF     	0 0 -1	; "getPowerDevice"
	3	[121]	CALL     	0 2 2
	4	[121]	SELF     	0 0 -2	; "turnOnFrontlight"
	5	[121]	CALL     	0 2 1
	6	[122]	GETUPVAL 	0 0	; Device
	7	[122]	SETTABLE 	0 -3 -4	; "brightness" 3
	8	[123]	GETUPVAL 	0 2	; class
	9	[123]	SELF     	0 0 -5	; "new"
	10	[123]	CALL     	0 2 2
	11	[123]	SETUPVAL 	0 1	; AutoFrontlight
	12	[124]	GETUPVAL 	0 3	; MockTime
	13	[124]	SELF     	0 0 -6	; "increase"
	14	[124]	LOADK    	2 -7	; 2
	15	[124]	CALL     	0 3 1
	16	[125]	GETUPVAL 	0 4	; UIManager
	17	[125]	SELF     	0 0 -8	; "handleInput"
	18	[125]	CALL     	0 2 1
	19	[126]	GETGLOBAL	0 -9	; assert
	20	[126]	GETTABLE 	0 0 -10	; "are"
	21	[126]	GETTABLE 	0 0 -11	; "equal"
	22	[126]	LOADK    	1 -12	; 0
	23	[126]	GETUPVAL 	2 0	; Device
	24	[126]	SELF     	2 2 -1	; "getPowerDevice"
	25	[126]	CALL     	2 2 2
	26	[126]	GETTABLE 	2 2 -13	; "frontlight"
	27	[126]	CALL     	0 3 1
	28	[127]	RETURN   	0 1

function <./spec/unit/autofrontlight_spec.lua:129,141> (49 instructions, 196 bytes at 0x7fbe69c06680)
0 params, 4 slots, 5 upvalues, 0 locals, 14 constants, 0 functions
	1	[130]	GETUPVAL 	0 0	; Device
	2	[130]	SELF     	0 0 -1	; "getPowerDevice"
	3	[130]	CALL     	0 2 2
	4	[130]	SELF     	0 0 -2	; "turnOffFrontlight"
	5	[130]	CALL     	0 2 1
	6	[131]	GETUPVAL 	0 0	; Device
	7	[131]	SETTABLE 	0 -3 -4	; "brightness" 0
	8	[132]	GETUPVAL 	0 2	; class
	9	[132]	SELF     	0 0 -5	; "new"
	10	[132]	CALL     	0 2 2
	11	[132]	SETUPVAL 	0 1	; AutoFrontlight
	12	[133]	GETUPVAL 	0 3	; MockTime
	13	[133]	SELF     	0 0 -6	; "increase"
	14	[133]	LOADK    	2 -7	; 2
	15	[133]	CALL     	0 3 1
	16	[134]	GETUPVAL 	0 4	; UIManager
	17	[134]	SELF     	0 0 -8	; "handleInput"
	18	[134]	CALL     	0 2 1
	19	[135]	GETGLOBAL	0 -9	; assert
	20	[135]	GETTABLE 	0 0 -10	; "are"
	21	[135]	GETTABLE 	0 0 -11	; "equal"
	22	[135]	LOADK    	1 -7	; 2
	23	[135]	GETUPVAL 	2 0	; Device
	24	[135]	SELF     	2 2 -1	; "getPowerDevice"
	25	[135]	CALL     	2 2 2
	26	[135]	GETTABLE 	2 2 -12	; "frontlight"
	27	[135]	CALL     	0 3 1
	28	[136]	GETUPVAL 	0 1	; AutoFrontlight
	29	[136]	SELF     	0 0 -13	; "flipSetting"
	30	[136]	CALL     	0 2 1
	31	[137]	GETUPVAL 	0 0	; Device
	32	[137]	SETTABLE 	0 -3 -14	; "brightness" 3
	33	[138]	GETUPVAL 	0 3	; MockTime
	34	[138]	SELF     	0 0 -6	; "increase"
	35	[138]	LOADK    	2 -7	; 2
	36	[138]	CALL     	0 3 1
	37	[139]	GETUPVAL 	0 4	; UIManager
	38	[139]	SELF     	0 0 -8	; "handleInput"
	39	[139]	CALL     	0 2 1
	40	[140]	GETGLOBAL	0 -9	; assert
	41	[140]	GETTABLE 	0 0 -10	; "are"
	42	[140]	GETTABLE 	0 0 -11	; "equal"
	43	[140]	LOADK    	1 -7	; 2
	44	[140]	GETUPVAL 	2 0	; Device
	45	[140]	SELF     	2 2 -1	; "getPowerDevice"
	46	[140]	CALL     	2 2 2
	47	[140]	GETTABLE 	2 2 -12	; "frontlight"
	48	[140]	CALL     	0 3 1
	49	[141]	RETURN   	0 1
