
main <./frontend/ui/elements/avoid_flashing_ui.lua:0,0> (14 instructions, 56 bytes at 0x7f81054068f0)
0+ params, 4 slots, 0 upvalues, 1 local, 6 constants, 2 functions
	1	[1]	GETGLOBAL	0 -1	; require
	2	[1]	LOADK    	1 -2	; "gettext"
	3	[1]	CALL     	0 2 2
	4	[3]	NEWTABLE 	1 0 3
	5	[4]	MOVE     	2 0
	6	[4]	LOADK    	3 -4	; "Avoid mandatory black flashes in UI"
	7	[4]	CALL     	2 2 2
	8	[4]	SETTABLE 	1 -3 2	; "text" -
	9	[7]	CLOSURE  	2 0	; 0x7f8105406bb0
	10	[7]	SETTABLE 	1 -5 2	; "checked_func" -
	11	[10]	CLOSURE  	2 1	; 0x7f8105407240
	12	[10]	SETTABLE 	1 -6 2	; "callback" -
	13	[11]	RETURN   	1 2
	14	[11]	RETURN   	0 1

function <./frontend/ui/elements/avoid_flashing_ui.lua:5,7> (6 instructions, 24 bytes at 0x7f8105406bb0)
0 params, 3 slots, 0 upvalues, 0 locals, 3 constants, 0 functions
	1	[6]	GETGLOBAL	0 -1	; G_reader_settings
	2	[6]	SELF     	0 0 -2	; "isTrue"
	3	[6]	LOADK    	2 -3	; "avoid_flashing_ui"
	4	[6]	TAILCALL 	0 3 0
	5	[6]	RETURN   	0 0
	6	[7]	RETURN   	0 1

function <./frontend/ui/elements/avoid_flashing_ui.lua:8,10> (5 instructions, 20 bytes at 0x7f8105407240)
0 params, 3 slots, 0 upvalues, 0 locals, 3 constants, 0 functions
	1	[9]	GETGLOBAL	0 -1	; G_reader_settings
	2	[9]	SELF     	0 0 -2	; "flipNilOrFalse"
	3	[9]	LOADK    	2 -3	; "avoid_flashing_ui"
	4	[9]	CALL     	0 3 1
	5	[10]	RETURN   	0 1
