
main <./spec/unit/background_task_plugin_spec.lua:0,0> (5 instructions, 20 bytes at 0x7f9b6b4068f0)
0+ params, 3 slots, 0 upvalues, 0 locals, 2 constants, 1 function
	1	[1]	GETGLOBAL	0 -1	; describe
	2	[1]	LOADK    	1 -2	; "BackgroundTaskPlugin"
	3	[140]	CLOSURE  	2 0	; 0x7f9b6b406b90
	4	[1]	CALL     	0 3 1
	5	[140]	RETURN   	0 1

function <./spec/unit/background_task_plugin_spec.lua:1,140> (43 instructions, 172 bytes at 0x7f9b6b406b90)
0 params, 8 slots, 0 upvalues, 5 locals, 12 constants, 6 functions
	1	[2]	GETGLOBAL	0 -1	; require
	2	[2]	LOADK    	1 -2	; "commonrequire"
	3	[2]	CALL     	0 2 1
	4	[3]	GETGLOBAL	0 -1	; require
	5	[3]	LOADK    	1 -3	; "ui/plugin/background_task_plugin"
	6	[3]	CALL     	0 2 2
	7	[4]	GETGLOBAL	1 -1	; require
	8	[4]	LOADK    	2 -4	; "mock_time"
	9	[4]	CALL     	1 2 2
	10	[5]	GETGLOBAL	2 -1	; require
	11	[5]	LOADK    	3 -5	; "ui/uimanager"
	12	[5]	CALL     	2 2 2
	13	[7]	GETGLOBAL	3 -6	; setup
	14	[13]	CLOSURE  	4 0	; 0x7f9b6b406ea0
	15	[13]	MOVE     	0 1
	16	[13]	MOVE     	0 2
	17	[7]	CALL     	3 2 1
	18	[15]	GETGLOBAL	3 -7	; teardown
	19	[20]	CLOSURE  	4 1	; 0x7f9b6b407970
	20	[20]	MOVE     	0 1
	21	[15]	CALL     	3 2 1
	22	[29]	CLOSURE  	3 2	; 0x7f9b6b406740
	23	[29]	MOVE     	0 0
	24	[31]	SELF     	4 0 -8	; "extend"
	25	[31]	CALL     	4 2 2
	26	[44]	CLOSURE  	5 3	; 0x7f9b6b406e20
	27	[44]	MOVE     	0 0
	28	[33]	SETTABLE 	4 -9 5	; "new" -
	29	[46]	GETGLOBAL	5 -10	; it
	30	[46]	LOADK    	6 -11	; "should be able to create a plugin"
	31	[93]	CLOSURE  	7 4	; 0x7f9b6b4087c0
	32	[93]	MOVE     	0 3
	33	[93]	MOVE     	0 1
	34	[93]	MOVE     	0 2
	35	[46]	CALL     	5 3 1
	36	[95]	GETGLOBAL	5 -10	; it
	37	[95]	LOADK    	6 -12	; "should be able to create a derived plugin"
	38	[139]	CLOSURE  	7 5	; 0x7f9b6b4078f0
	39	[139]	MOVE     	0 4
	40	[139]	MOVE     	0 1
	41	[139]	MOVE     	0 2
	42	[95]	CALL     	5 3 1
	43	[140]	RETURN   	0 1

function <./spec/unit/background_task_plugin_spec.lua:7,13> (14 instructions, 56 bytes at 0x7f9b6b406ea0)
0 params, 3 slots, 2 upvalues, 1 local, 8 constants, 1 function
	1	[8]	GETUPVAL 	0 0	; MockTime
	2	[8]	SELF     	0 0 -1	; "install"
	3	[8]	CALL     	0 2 1
	4	[9]	GETGLOBAL	0 -2	; require
	5	[9]	LOADK    	1 -3	; "device"
	6	[9]	CALL     	0 2 2
	7	[10]	GETTABLE 	1 0 -4	; "input"
	8	[10]	CLOSURE  	2 0	; 0x7f9b6b4073f0
	9	[10]	SETTABLE 	1 -5 2	; "waitEvent" -
	10	[11]	GETUPVAL 	1 1	; UIManager
	11	[11]	SETTABLE 	1 -6 -7	; "_run_forever" true
	12	[12]	GETGLOBAL	1 -8	; requireBackgroundRunner
	13	[12]	CALL     	1 1 1
	14	[13]	RETURN   	0 1

function <./spec/unit/background_task_plugin_spec.lua:10,10> (1 instruction, 4 bytes at 0x7f9b6b4073f0)
0 params, 2 slots, 0 upvalues, 0 locals, 0 constants, 0 functions
	1	[10]	RETURN   	0 1

function <./spec/unit/background_task_plugin_spec.lua:15,20> (17 instructions, 68 bytes at 0x7f9b6b407970)
0 params, 4 slots, 1 upvalue, 0 locals, 8 constants, 0 functions
	1	[16]	GETUPVAL 	0 0	; MockTime
	2	[16]	SELF     	0 0 -1	; "uninstall"
	3	[16]	CALL     	0 2 1
	4	[17]	GETGLOBAL	0 -2	; package
	5	[17]	GETTABLE 	0 0 -3	; "unloadAll"
	6	[17]	CALL     	0 1 1
	7	[18]	GETGLOBAL	0 -4	; require
	8	[18]	LOADK    	1 -5	; "document/canvascontext"
	9	[18]	CALL     	0 2 2
	10	[18]	SELF     	0 0 -6	; "init"
	11	[18]	GETGLOBAL	2 -4	; require
	12	[18]	LOADK    	3 -7	; "device"
	13	[18]	CALL     	2 2 0
	14	[18]	CALL     	0 0 1
	15	[19]	GETGLOBAL	0 -8	; stopBackgroundRunner
	16	[19]	CALL     	0 1 1
	17	[20]	RETURN   	0 1

function <./spec/unit/background_task_plugin_spec.lua:22,29> (10 instructions, 40 bytes at 0x7f9b6b406740)
1 param, 4 slots, 1 upvalue, 1 local, 8 constants, 0 functions
	1	[23]	GETUPVAL 	1 0	; BackgroundTaskPlugin
	2	[23]	SELF     	1 1 -1	; "new"
	3	[23]	NEWTABLE 	3 0 4
	4	[24]	SETTABLE 	3 -2 -3	; "name" "test_plugin"
	5	[25]	SETTABLE 	3 -4 -5	; "default_enable" true
	6	[26]	SETTABLE 	3 -6 -7	; "when" 2
	7	[27]	SETTABLE 	3 -8 0	; "executable" -
	8	[23]	TAILCALL 	1 3 0
	9	[28]	RETURN   	1 0
	10	[29]	RETURN   	0 1

function <./spec/unit/background_task_plugin_spec.lua:33,44> (19 instructions, 76 bytes at 0x7f9b6b406e20)
2 params, 5 slots, 1 upvalue, 2 locals, 10 constants, 1 function
	1	[34]	TEST     	1 0 1
	2	[34]	JMP      	2	; to 5
	3	[34]	NEWTABLE 	2 0 0
	4	[34]	MOVE     	1 2
	5	[35]	SETTABLE 	1 -1 -2	; "name" "test_plugin2"
	6	[36]	SETTABLE 	1 -3 -4	; "default_enable" true
	7	[37]	SETTABLE 	1 -5 -6	; "when" 2
	8	[38]	SETTABLE 	1 -7 -8	; "executed" 0
	9	[41]	CLOSURE  	2 0	; 0x7f9b6b408570
	10	[41]	MOVE     	0 1
	11	[41]	SETTABLE 	1 -9 2	; "executable" -
	12	[42]	GETUPVAL 	2 0	; BackgroundTaskPlugin
	13	[42]	GETTABLE 	2 2 -10	; "new"
	14	[42]	MOVE     	3 0
	15	[42]	MOVE     	4 1
	16	[42]	CALL     	2 3 2
	17	[42]	MOVE     	1 2
	18	[43]	RETURN   	1 2
	19	[44]	RETURN   	0 1

function <./spec/unit/background_task_plugin_spec.lua:39,41> (6 instructions, 24 bytes at 0x7f9b6b408570)
0 params, 2 slots, 1 upvalue, 0 locals, 2 constants, 0 functions
	1	[40]	GETUPVAL 	0 0	; o
	2	[40]	GETUPVAL 	1 0	; o
	3	[40]	GETTABLE 	1 1 -1	; "executed"
	4	[40]	ADD      	1 1 -2	; - 1
	5	[40]	SETTABLE 	0 -1 1	; "executed" -
	6	[41]	RETURN   	0 1

function <./spec/unit/background_task_plugin_spec.lua:46,93> (145 instructions, 580 bytes at 0x7f9b6b4087c0)
0 params, 5 slots, 3 upvalues, 2 locals, 14 constants, 1 function
	1	[47]	LOADK    	0 -1	; 0
	2	[48]	GETUPVAL 	1 0	; createTestPlugin
	3	[50]	CLOSURE  	2 0	; 0x7f9b6b407180
	4	[50]	MOVE     	0 0
	5	[48]	CALL     	1 2 2
	6	[51]	GETUPVAL 	2 1	; MockTime
	7	[51]	SELF     	2 2 -2	; "increase"
	8	[51]	LOADK    	4 -3	; 2
	9	[51]	CALL     	2 3 1
	10	[52]	GETUPVAL 	2 2	; UIManager
	11	[52]	SELF     	2 2 -4	; "handleInput"
	12	[52]	CALL     	2 2 1
	13	[54]	GETUPVAL 	2 1	; MockTime
	14	[54]	SELF     	2 2 -2	; "increase"
	15	[54]	LOADK    	4 -3	; 2
	16	[54]	CALL     	2 3 1
	17	[55]	GETUPVAL 	2 2	; UIManager
	18	[55]	SELF     	2 2 -4	; "handleInput"
	19	[55]	CALL     	2 2 1
	20	[56]	GETGLOBAL	2 -5	; assert
	21	[56]	GETTABLE 	2 2 -6	; "are"
	22	[56]	GETTABLE 	2 2 -7	; "equal"
	23	[56]	LOADK    	3 -8	; 1
	24	[56]	MOVE     	4 0
	25	[56]	CALL     	2 3 1
	26	[57]	GETUPVAL 	2 1	; MockTime
	27	[57]	SELF     	2 2 -2	; "increase"
	28	[57]	LOADK    	4 -3	; 2
	29	[57]	CALL     	2 3 1
	30	[58]	GETUPVAL 	2 2	; UIManager
	31	[58]	SELF     	2 2 -4	; "handleInput"
	32	[58]	CALL     	2 2 1
	33	[59]	GETGLOBAL	2 -5	; assert
	34	[59]	GETTABLE 	2 2 -6	; "are"
	35	[59]	GETTABLE 	2 2 -7	; "equal"
	36	[59]	LOADK    	3 -3	; 2
	37	[59]	MOVE     	4 0
	38	[59]	CALL     	2 3 1
	39	[61]	SELF     	2 1 -9	; "flipSetting"
	40	[61]	CALL     	2 2 1
	41	[62]	GETUPVAL 	2 1	; MockTime
	42	[62]	SELF     	2 2 -2	; "increase"
	43	[62]	LOADK    	4 -3	; 2
	44	[62]	CALL     	2 3 1
	45	[63]	GETUPVAL 	2 2	; UIManager
	46	[63]	SELF     	2 2 -4	; "handleInput"
	47	[63]	CALL     	2 2 1
	48	[64]	GETGLOBAL	2 -5	; assert
	49	[64]	GETTABLE 	2 2 -6	; "are"
	50	[64]	GETTABLE 	2 2 -7	; "equal"
	51	[64]	LOADK    	3 -10	; 3
	52	[64]	MOVE     	4 0
	53	[64]	CALL     	2 3 1
	54	[65]	GETUPVAL 	2 1	; MockTime
	55	[65]	SELF     	2 2 -2	; "increase"
	56	[65]	LOADK    	4 -3	; 2
	57	[65]	CALL     	2 3 1
	58	[66]	GETUPVAL 	2 2	; UIManager
	59	[66]	SELF     	2 2 -4	; "handleInput"
	60	[66]	CALL     	2 2 1
	61	[67]	GETGLOBAL	2 -5	; assert
	62	[67]	GETTABLE 	2 2 -6	; "are"
	63	[67]	GETTABLE 	2 2 -7	; "equal"
	64	[67]	LOADK    	3 -10	; 3
	65	[67]	MOVE     	4 0
	66	[67]	CALL     	2 3 1
	67	[69]	SELF     	2 1 -9	; "flipSetting"
	68	[69]	CALL     	2 2 1
	69	[70]	GETUPVAL 	2 1	; MockTime
	70	[70]	SELF     	2 2 -2	; "increase"
	71	[70]	LOADK    	4 -3	; 2
	72	[70]	CALL     	2 3 1
	73	[71]	GETUPVAL 	2 2	; UIManager
	74	[71]	SELF     	2 2 -4	; "handleInput"
	75	[71]	CALL     	2 2 1
	76	[72]	GETGLOBAL	2 -5	; assert
	77	[72]	GETTABLE 	2 2 -6	; "are"
	78	[72]	GETTABLE 	2 2 -7	; "equal"
	79	[72]	LOADK    	3 -10	; 3
	80	[72]	MOVE     	4 0
	81	[72]	CALL     	2 3 1
	82	[73]	GETUPVAL 	2 1	; MockTime
	83	[73]	SELF     	2 2 -2	; "increase"
	84	[73]	LOADK    	4 -3	; 2
	85	[73]	CALL     	2 3 1
	86	[74]	GETUPVAL 	2 2	; UIManager
	87	[74]	SELF     	2 2 -4	; "handleInput"
	88	[74]	CALL     	2 2 1
	89	[75]	GETGLOBAL	2 -5	; assert
	90	[75]	GETTABLE 	2 2 -6	; "are"
	91	[75]	GETTABLE 	2 2 -7	; "equal"
	92	[75]	LOADK    	3 -11	; 4
	93	[75]	MOVE     	4 0
	94	[75]	CALL     	2 3 1
	95	[78]	SELF     	2 1 -12	; "_init"
	96	[78]	CALL     	2 2 1
	97	[79]	GETUPVAL 	2 1	; MockTime
	98	[79]	SELF     	2 2 -2	; "increase"
	99	[79]	LOADK    	4 -3	; 2
	100	[79]	CALL     	2 3 1
	101	[80]	GETUPVAL 	2 2	; UIManager
	102	[80]	SELF     	2 2 -4	; "handleInput"
	103	[80]	CALL     	2 2 1
	104	[81]	GETGLOBAL	2 -5	; assert
	105	[81]	GETTABLE 	2 2 -6	; "are"
	106	[81]	GETTABLE 	2 2 -7	; "equal"
	107	[81]	LOADK    	3 -13	; 5
	108	[81]	MOVE     	4 0
	109	[81]	CALL     	2 3 1
	110	[82]	GETUPVAL 	2 1	; MockTime
	111	[82]	SELF     	2 2 -2	; "increase"
	112	[82]	LOADK    	4 -3	; 2
	113	[82]	CALL     	2 3 1
	114	[83]	GETUPVAL 	2 2	; UIManager
	115	[83]	SELF     	2 2 -4	; "handleInput"
	116	[83]	CALL     	2 2 1
	117	[84]	GETGLOBAL	2 -5	; assert
	118	[84]	GETTABLE 	2 2 -6	; "are"
	119	[84]	GETTABLE 	2 2 -7	; "equal"
	120	[84]	LOADK    	3 -13	; 5
	121	[84]	MOVE     	4 0
	122	[84]	CALL     	2 3 1
	123	[85]	GETUPVAL 	2 1	; MockTime
	124	[85]	SELF     	2 2 -2	; "increase"
	125	[85]	LOADK    	4 -3	; 2
	126	[85]	CALL     	2 3 1
	127	[86]	GETUPVAL 	2 2	; UIManager
	128	[86]	SELF     	2 2 -4	; "handleInput"
	129	[86]	CALL     	2 2 1
	130	[87]	GETGLOBAL	2 -5	; assert
	131	[87]	GETTABLE 	2 2 -6	; "are"
	132	[87]	GETTABLE 	2 2 -7	; "equal"
	133	[87]	LOADK    	3 -14	; 6
	134	[87]	MOVE     	4 0
	135	[87]	CALL     	2 3 1
	136	[90]	SELF     	2 1 -9	; "flipSetting"
	137	[90]	CALL     	2 2 1
	138	[91]	GETUPVAL 	2 1	; MockTime
	139	[91]	SELF     	2 2 -2	; "increase"
	140	[91]	LOADK    	4 -3	; 2
	141	[91]	CALL     	2 3 1
	142	[92]	GETUPVAL 	2 2	; UIManager
	143	[92]	SELF     	2 2 -4	; "handleInput"
	144	[92]	CALL     	2 2 1
	145	[93]	RETURN   	0 1

function <./spec/unit/background_task_plugin_spec.lua:48,50> (4 instructions, 16 bytes at 0x7f9b6b407180)
0 params, 2 slots, 1 upvalue, 0 locals, 1 constant, 0 functions
	1	[49]	GETUPVAL 	0 0	; executed
	2	[49]	ADD      	0 0 -1	; - 1
	3	[49]	SETUPVAL 	0 0	; executed
	4	[50]	RETURN   	0 1

function <./spec/unit/background_task_plugin_spec.lua:95,139> (143 instructions, 572 bytes at 0x7f9b6b4078f0)
0 params, 4 slots, 3 upvalues, 1 local, 15 constants, 0 functions
	1	[96]	GETUPVAL 	0 0	; TestPlugin2
	2	[96]	SELF     	0 0 -1	; "new"
	3	[96]	CALL     	0 2 2
	4	[97]	GETUPVAL 	1 1	; MockTime
	5	[97]	SELF     	1 1 -2	; "increase"
	6	[97]	LOADK    	3 -3	; 2
	7	[97]	CALL     	1 3 1
	8	[98]	GETUPVAL 	1 2	; UIManager
	9	[98]	SELF     	1 1 -4	; "handleInput"
	10	[98]	CALL     	1 2 1
	11	[100]	GETUPVAL 	1 1	; MockTime
	12	[100]	SELF     	1 1 -2	; "increase"
	13	[100]	LOADK    	3 -3	; 2
	14	[100]	CALL     	1 3 1
	15	[101]	GETUPVAL 	1 2	; UIManager
	16	[101]	SELF     	1 1 -4	; "handleInput"
	17	[101]	CALL     	1 2 1
	18	[102]	GETGLOBAL	1 -5	; assert
	19	[102]	GETTABLE 	1 1 -6	; "are"
	20	[102]	GETTABLE 	1 1 -7	; "equal"
	21	[102]	LOADK    	2 -8	; 1
	22	[102]	GETTABLE 	3 0 -9	; "executed"
	23	[102]	CALL     	1 3 1
	24	[103]	GETUPVAL 	1 1	; MockTime
	25	[103]	SELF     	1 1 -2	; "increase"
	26	[103]	LOADK    	3 -3	; 2
	27	[103]	CALL     	1 3 1
	28	[104]	GETUPVAL 	1 2	; UIManager
	29	[104]	SELF     	1 1 -4	; "handleInput"
	30	[104]	CALL     	1 2 1
	31	[105]	GETGLOBAL	1 -5	; assert
	32	[105]	GETTABLE 	1 1 -6	; "are"
	33	[105]	GETTABLE 	1 1 -7	; "equal"
	34	[105]	LOADK    	2 -3	; 2
	35	[105]	GETTABLE 	3 0 -9	; "executed"
	36	[105]	CALL     	1 3 1
	37	[107]	SELF     	1 0 -10	; "flipSetting"
	38	[107]	CALL     	1 2 1
	39	[108]	GETUPVAL 	1 1	; MockTime
	40	[108]	SELF     	1 1 -2	; "increase"
	41	[108]	LOADK    	3 -3	; 2
	42	[108]	CALL     	1 3 1
	43	[109]	GETUPVAL 	1 2	; UIManager
	44	[109]	SELF     	1 1 -4	; "handleInput"
	45	[109]	CALL     	1 2 1
	46	[110]	GETGLOBAL	1 -5	; assert
	47	[110]	GETTABLE 	1 1 -6	; "are"
	48	[110]	GETTABLE 	1 1 -7	; "equal"
	49	[110]	LOADK    	2 -11	; 3
	50	[110]	GETTABLE 	3 0 -9	; "executed"
	51	[110]	CALL     	1 3 1
	52	[111]	GETUPVAL 	1 1	; MockTime
	53	[111]	SELF     	1 1 -2	; "increase"
	54	[111]	LOADK    	3 -3	; 2
	55	[111]	CALL     	1 3 1
	56	[112]	GETUPVAL 	1 2	; UIManager
	57	[112]	SELF     	1 1 -4	; "handleInput"
	58	[112]	CALL     	1 2 1
	59	[113]	GETGLOBAL	1 -5	; assert
	60	[113]	GETTABLE 	1 1 -6	; "are"
	61	[113]	GETTABLE 	1 1 -7	; "equal"
	62	[113]	LOADK    	2 -11	; 3
	63	[113]	GETTABLE 	3 0 -9	; "executed"
	64	[113]	CALL     	1 3 1
	65	[115]	SELF     	1 0 -10	; "flipSetting"
	66	[115]	CALL     	1 2 1
	67	[116]	GETUPVAL 	1 1	; MockTime
	68	[116]	SELF     	1 1 -2	; "increase"
	69	[116]	LOADK    	3 -3	; 2
	70	[116]	CALL     	1 3 1
	71	[117]	GETUPVAL 	1 2	; UIManager
	72	[117]	SELF     	1 1 -4	; "handleInput"
	73	[117]	CALL     	1 2 1
	74	[118]	GETGLOBAL	1 -5	; assert
	75	[118]	GETTABLE 	1 1 -6	; "are"
	76	[118]	GETTABLE 	1 1 -7	; "equal"
	77	[118]	LOADK    	2 -11	; 3
	78	[118]	GETTABLE 	3 0 -9	; "executed"
	79	[118]	CALL     	1 3 1
	80	[119]	GETUPVAL 	1 1	; MockTime
	81	[119]	SELF     	1 1 -2	; "increase"
	82	[119]	LOADK    	3 -3	; 2
	83	[119]	CALL     	1 3 1
	84	[120]	GETUPVAL 	1 2	; UIManager
	85	[120]	SELF     	1 1 -4	; "handleInput"
	86	[120]	CALL     	1 2 1
	87	[121]	GETGLOBAL	1 -5	; assert
	88	[121]	GETTABLE 	1 1 -6	; "are"
	89	[121]	GETTABLE 	1 1 -7	; "equal"
	90	[121]	LOADK    	2 -12	; 4
	91	[121]	GETTABLE 	3 0 -9	; "executed"
	92	[121]	CALL     	1 3 1
	93	[124]	SELF     	1 0 -13	; "_init"
	94	[124]	CALL     	1 2 1
	95	[125]	GETUPVAL 	1 1	; MockTime
	96	[125]	SELF     	1 1 -2	; "increase"
	97	[125]	LOADK    	3 -3	; 2
	98	[125]	CALL     	1 3 1
	99	[126]	GETUPVAL 	1 2	; UIManager
	100	[126]	SELF     	1 1 -4	; "handleInput"
	101	[126]	CALL     	1 2 1
	102	[127]	GETGLOBAL	1 -5	; assert
	103	[127]	GETTABLE 	1 1 -6	; "are"
	104	[127]	GETTABLE 	1 1 -7	; "equal"
	105	[127]	LOADK    	2 -14	; 5
	106	[127]	GETTABLE 	3 0 -9	; "executed"
	107	[127]	CALL     	1 3 1
	108	[128]	GETUPVAL 	1 1	; MockTime
	109	[128]	SELF     	1 1 -2	; "increase"
	110	[128]	LOADK    	3 -3	; 2
	111	[128]	CALL     	1 3 1
	112	[129]	GETUPVAL 	1 2	; UIManager
	113	[129]	SELF     	1 1 -4	; "handleInput"
	114	[129]	CALL     	1 2 1
	115	[130]	GETGLOBAL	1 -5	; assert
	116	[130]	GETTABLE 	1 1 -6	; "are"
	117	[130]	GETTABLE 	1 1 -7	; "equal"
	118	[130]	LOADK    	2 -14	; 5
	119	[130]	GETTABLE 	3 0 -9	; "executed"
	120	[130]	CALL     	1 3 1
	121	[131]	GETUPVAL 	1 1	; MockTime
	122	[131]	SELF     	1 1 -2	; "increase"
	123	[131]	LOADK    	3 -3	; 2
	124	[131]	CALL     	1 3 1
	125	[132]	GETUPVAL 	1 2	; UIManager
	126	[132]	SELF     	1 1 -4	; "handleInput"
	127	[132]	CALL     	1 2 1
	128	[133]	GETGLOBAL	1 -5	; assert
	129	[133]	GETTABLE 	1 1 -6	; "are"
	130	[133]	GETTABLE 	1 1 -7	; "equal"
	131	[133]	LOADK    	2 -15	; 6
	132	[133]	GETTABLE 	3 0 -9	; "executed"
	133	[133]	CALL     	1 3 1
	134	[136]	SELF     	1 0 -10	; "flipSetting"
	135	[136]	CALL     	1 2 1
	136	[137]	GETUPVAL 	1 1	; MockTime
	137	[137]	SELF     	1 1 -2	; "increase"
	138	[137]	LOADK    	3 -3	; 2
	139	[137]	CALL     	1 3 1
	140	[138]	GETUPVAL 	1 2	; UIManager
	141	[138]	SELF     	1 1 -4	; "handleInput"
	142	[138]	CALL     	1 2 1
	143	[139]	RETURN   	0 1
