
main <./spec/unit/background_runner_spec.lua:0,0> (5 instructions, 20 bytes at 0x7fdf0cc068d0)
0+ params, 3 slots, 0 upvalues, 0 locals, 2 constants, 1 function
	1	[1]	GETGLOBAL	0 -1	; describe
	2	[1]	LOADK    	1 -2	; "BackgroundRunner widget tests"
	3	[358]	CLOSURE  	2 0	; 0x7fdf0cc06b80
	4	[1]	CALL     	0 3 1
	5	[358]	RETURN   	0 1

function <./spec/unit/background_runner_spec.lua:1,358> (100 instructions, 400 bytes at 0x7fdf0cc06b80)
0 params, 7 slots, 0 upvalues, 4 locals, 16 constants, 15 functions
	1	[4]	GETGLOBAL	4 -1	; setup
	2	[17]	CLOSURE  	5 0	; 0x7fdf0cc06f20
	3	[17]	MOVE     	0 0
	4	[17]	MOVE     	0 1
	5	[17]	MOVE     	0 2
	6	[17]	MOVE     	0 3
	7	[4]	CALL     	4 2 1
	8	[19]	GETGLOBAL	4 -2	; teardown
	9	[24]	CLOSURE  	5 1	; 0x7fdf0cc065c0
	10	[24]	MOVE     	0 2
	11	[19]	CALL     	4 2 1
	12	[26]	GETGLOBAL	4 -3	; before_each
	13	[28]	CLOSURE  	5 2	; 0x7fdf0cc07840
	14	[28]	MOVE     	0 1
	15	[26]	CALL     	4 2 1
	16	[30]	GETGLOBAL	4 -4	; it
	17	[30]	LOADK    	5 -5	; "should start job"
	18	[46]	CLOSURE  	6 3	; 0x7fdf0cc080c0
	19	[46]	MOVE     	0 1
	20	[46]	MOVE     	0 2
	21	[46]	MOVE     	0 3
	22	[30]	CALL     	4 3 1
	23	[48]	GETGLOBAL	4 -4	; it
	24	[48]	LOADK    	5 -6	; "should repeat job"
	25	[69]	CLOSURE  	6 4	; 0x7fdf0cc08210
	26	[69]	MOVE     	0 1
	27	[69]	MOVE     	0 2
	28	[69]	MOVE     	0 3
	29	[48]	CALL     	4 3 1
	30	[71]	GETGLOBAL	4 -4	; it
	31	[71]	LOADK    	5 -7	; "should repeat job for predefined times"
	32	[92]	CLOSURE  	6 5	; 0x7fdf0cc08570
	33	[92]	MOVE     	0 1
	34	[92]	MOVE     	0 2
	35	[92]	MOVE     	0 3
	36	[71]	CALL     	4 3 1
	37	[94]	GETGLOBAL	4 -4	; it
	38	[94]	LOADK    	5 -8	; "should block long job"
	39	[116]	CLOSURE  	6 6	; 0x7fdf0cc08040
	40	[116]	MOVE     	0 2
	41	[116]	MOVE     	0 1
	42	[116]	MOVE     	0 3
	43	[94]	CALL     	4 3 1
	44	[118]	GETGLOBAL	4 -4	; it
	45	[118]	LOADK    	5 -9	; "should execute binary"
	46	[139]	CLOSURE  	6 7	; 0x7fdf0cc07fc0
	47	[139]	MOVE     	0 1
	48	[139]	MOVE     	0 2
	49	[139]	MOVE     	0 3
	50	[118]	CALL     	4 3 1
	51	[141]	GETGLOBAL	4 -4	; it
	52	[141]	LOADK    	5 -10	; "should forward string environment to the executable"
	53	[183]	CLOSURE  	6 8	; 0x7fdf0cc09d00
	54	[183]	MOVE     	0 1
	55	[183]	MOVE     	0 2
	56	[183]	MOVE     	0 3
	57	[141]	CALL     	4 3 1
	58	[185]	GETGLOBAL	4 -4	; it
	59	[185]	LOADK    	5 -11	; "should forward function environment to the executable"
	60	[223]	CLOSURE  	6 9	; 0x7fdf0cc07b60
	61	[223]	MOVE     	0 1
	62	[223]	MOVE     	0 2
	63	[223]	MOVE     	0 3
	64	[185]	CALL     	4 3 1
	65	[225]	GETGLOBAL	4 -4	; it
	66	[225]	LOADK    	5 -12	; "should block long binary job"
	67	[244]	CLOSURE  	6 10	; 0x7fdf0cc08680
	68	[244]	MOVE     	0 1
	69	[244]	MOVE     	0 2
	70	[244]	MOVE     	0 3
	71	[225]	CALL     	4 3 1
	72	[246]	GETGLOBAL	4 -4	; it
	73	[246]	LOADK    	5 -13	; "should execute callback"
	74	[268]	CLOSURE  	6 11	; 0x7fdf0cc0b830
	75	[268]	MOVE     	0 1
	76	[268]	MOVE     	0 2
	77	[268]	MOVE     	0 3
	78	[246]	CALL     	4 3 1
	79	[270]	GETGLOBAL	4 -4	; it
	80	[270]	LOADK    	5 -14	; "should not execute two jobs sequentially"
	81	[296]	CLOSURE  	6 12	; 0x7fdf0cc0aa30
	82	[296]	MOVE     	0 1
	83	[296]	MOVE     	0 2
	84	[296]	MOVE     	0 3
	85	[270]	CALL     	4 3 1
	86	[298]	GETGLOBAL	4 -4	; it
	87	[298]	LOADK    	5 -15	; "should stop executing when suspending"
	88	[329]	CLOSURE  	6 13	; 0x7fdf0cc0be50
	89	[329]	MOVE     	0 1
	90	[329]	MOVE     	0 2
	91	[329]	MOVE     	0 3
	92	[298]	CALL     	4 3 1
	93	[331]	GETGLOBAL	4 -4	; it
	94	[331]	LOADK    	5 -16	; "should not start multiple times after multiple onResume"
	95	[357]	CLOSURE  	6 14	; 0x7fdf0cc0c8c0
	96	[357]	MOVE     	0 1
	97	[357]	MOVE     	0 2
	98	[357]	MOVE     	0 3
	99	[331]	CALL     	4 3 1
	100	[358]	RETURN   	0 1

function <./spec/unit/background_runner_spec.lua:4,17> (42 instructions, 168 bytes at 0x7fdf0cc06f20)
0 params, 4 slots, 4 upvalues, 0 locals, 16 constants, 1 function
	1	[5]	GETGLOBAL	0 -1	; require
	2	[5]	LOADK    	1 -2	; "commonrequire"
	3	[5]	CALL     	0 2 1
	4	[6]	GETGLOBAL	0 -3	; package
	5	[6]	GETTABLE 	0 0 -4	; "unloadAll"
	6	[6]	CALL     	0 1 1
	7	[7]	GETGLOBAL	0 -1	; require
	8	[7]	LOADK    	1 -5	; "document/canvascontext"
	9	[7]	CALL     	0 2 2
	10	[7]	SELF     	0 0 -6	; "init"
	11	[7]	GETGLOBAL	2 -1	; require
	12	[7]	LOADK    	3 -7	; "device"
	13	[7]	CALL     	2 2 0
	14	[7]	CALL     	0 0 1
	15	[9]	GETGLOBAL	0 -1	; require
	16	[9]	LOADK    	1 -7	; "device"
	17	[9]	CALL     	0 2 2
	18	[9]	SETUPVAL 	0 0	; Device
	19	[10]	GETUPVAL 	0 0	; Device
	20	[10]	GETTABLE 	0 0 -8	; "input"
	21	[10]	CLOSURE  	1 0	; 0x7fdf0cc072e0
	22	[10]	SETTABLE 	0 -9 1	; "waitEvent" -
	23	[11]	GETGLOBAL	0 -1	; require
	24	[11]	LOADK    	1 -10	; "pluginshare"
	25	[11]	CALL     	0 2 2
	26	[11]	SETUPVAL 	0 1	; PluginShare
	27	[12]	GETGLOBAL	0 -1	; require
	28	[12]	LOADK    	1 -11	; "mock_time"
	29	[12]	CALL     	0 2 2
	30	[12]	SETUPVAL 	0 2	; MockTime
	31	[13]	GETUPVAL 	0 2	; MockTime
	32	[13]	SELF     	0 0 -12	; "install"
	33	[13]	CALL     	0 2 1
	34	[14]	GETGLOBAL	0 -1	; require
	35	[14]	LOADK    	1 -13	; "ui/uimanager"
	36	[14]	CALL     	0 2 2
	37	[14]	SETUPVAL 	0 3	; UIManager
	38	[15]	GETUPVAL 	0 3	; UIManager
	39	[15]	SETTABLE 	0 -14 -15	; "_run_forever" true
	40	[16]	GETGLOBAL	0 -16	; requireBackgroundRunner
	41	[16]	CALL     	0 1 1
	42	[17]	RETURN   	0 1

function <./spec/unit/background_runner_spec.lua:10,10> (1 instruction, 4 bytes at 0x7fdf0cc072e0)
0 params, 2 slots, 0 upvalues, 0 locals, 0 constants, 0 functions
	1	[10]	RETURN   	0 1

function <./spec/unit/background_runner_spec.lua:19,24> (17 instructions, 68 bytes at 0x7fdf0cc065c0)
0 params, 4 slots, 1 upvalue, 0 locals, 8 constants, 0 functions
	1	[20]	GETUPVAL 	0 0	; MockTime
	2	[20]	SELF     	0 0 -1	; "uninstall"
	3	[20]	CALL     	0 2 1
	4	[21]	GETGLOBAL	0 -2	; package
	5	[21]	GETTABLE 	0 0 -3	; "unloadAll"
	6	[21]	CALL     	0 1 1
	7	[22]	GETGLOBAL	0 -4	; require
	8	[22]	LOADK    	1 -5	; "document/canvascontext"
	9	[22]	CALL     	0 2 2
	10	[22]	SELF     	0 0 -6	; "init"
	11	[22]	GETGLOBAL	2 -4	; require
	12	[22]	LOADK    	3 -7	; "device"
	13	[22]	CALL     	2 2 0
	14	[22]	CALL     	0 0 1
	15	[23]	GETGLOBAL	0 -8	; stopBackgroundRunner
	16	[23]	CALL     	0 1 1
	17	[24]	RETURN   	0 1

function <./spec/unit/background_runner_spec.lua:26,28> (8 instructions, 32 bytes at 0x7fdf0cc07840)
0 params, 2 slots, 1 upvalue, 0 locals, 4 constants, 0 functions
	1	[27]	GETGLOBAL	0 -1	; require
	2	[27]	LOADK    	1 -2	; "util"
	3	[27]	CALL     	0 2 2
	4	[27]	GETTABLE 	0 0 -3	; "clearTable"
	5	[27]	GETUPVAL 	1 0	; PluginShare
	6	[27]	GETTABLE 	1 1 -4	; "backgroundJobs"
	7	[27]	CALL     	0 2 1
	8	[28]	RETURN   	0 1

function <./spec/unit/background_runner_spec.lua:30,46> (41 instructions, 164 bytes at 0x7fdf0cc080c0)
0 params, 5 slots, 3 upvalues, 1 local, 13 constants, 1 function
	1	[31]	LOADBOOL 	0 0 0
	2	[32]	GETGLOBAL	1 -1	; table
	3	[32]	GETTABLE 	1 1 -2	; "insert"
	4	[32]	GETUPVAL 	2 0	; PluginShare
	5	[32]	GETTABLE 	2 2 -3	; "backgroundJobs"
	6	[32]	NEWTABLE 	3 0 2
	7	[33]	SETTABLE 	3 -4 -5	; "when" 10
	8	[36]	CLOSURE  	4 0	; 0x7fdf0cc082c0
	9	[36]	MOVE     	0 0
	10	[36]	SETTABLE 	3 -6 4	; "executable" -
	11	[32]	CALL     	1 3 1
	12	[38]	GETUPVAL 	1 1	; MockTime
	13	[38]	SELF     	1 1 -7	; "increase"
	14	[38]	LOADK    	3 -8	; 2
	15	[38]	CALL     	1 3 1
	16	[39]	GETUPVAL 	1 2	; UIManager
	17	[39]	SELF     	1 1 -9	; "handleInput"
	18	[39]	CALL     	1 2 1
	19	[40]	GETUPVAL 	1 1	; MockTime
	20	[40]	SELF     	1 1 -7	; "increase"
	21	[40]	LOADK    	3 -10	; 9
	22	[40]	CALL     	1 3 1
	23	[41]	GETUPVAL 	1 2	; UIManager
	24	[41]	SELF     	1 1 -9	; "handleInput"
	25	[41]	CALL     	1 2 1
	26	[42]	GETGLOBAL	1 -11	; assert
	27	[42]	GETTABLE 	1 1 -12	; "is_false"
	28	[42]	MOVE     	2 0
	29	[42]	CALL     	1 2 1
	30	[43]	GETUPVAL 	1 1	; MockTime
	31	[43]	SELF     	1 1 -7	; "increase"
	32	[43]	LOADK    	3 -8	; 2
	33	[43]	CALL     	1 3 1
	34	[44]	GETUPVAL 	1 2	; UIManager
	35	[44]	SELF     	1 1 -9	; "handleInput"
	36	[44]	CALL     	1 2 1
	37	[45]	GETGLOBAL	1 -11	; assert
	38	[45]	GETTABLE 	1 1 -13	; "is_true"
	39	[45]	MOVE     	2 0
	40	[45]	CALL     	1 2 1
	41	[46]	RETURN   	0 1

function <./spec/unit/background_runner_spec.lua:34,36> (3 instructions, 12 bytes at 0x7fdf0cc082c0)
0 params, 2 slots, 1 upvalue, 0 locals, 0 constants, 0 functions
	1	[35]	LOADBOOL 	0 1 0
	2	[35]	SETUPVAL 	0 0	; executed
	3	[36]	RETURN   	0 1

function <./spec/unit/background_runner_spec.lua:48,69> (53 instructions, 212 bytes at 0x7fdf0cc08210)
0 params, 8 slots, 3 upvalues, 5 locals, 15 constants, 2 functions
	1	[49]	LOADK    	0 -1	; 0
	2	[50]	GETGLOBAL	1 -2	; table
	3	[50]	GETTABLE 	1 1 -3	; "insert"
	4	[50]	GETUPVAL 	2 0	; PluginShare
	5	[50]	GETTABLE 	2 2 -4	; "backgroundJobs"
	6	[50]	NEWTABLE 	3 0 3
	7	[51]	SETTABLE 	3 -5 -6	; "when" 1
	8	[52]	CLOSURE  	4 0	; 0x7fdf0cc089a0
	9	[52]	MOVE     	0 0
	10	[52]	SETTABLE 	3 -7 4	; "repeated" -
	11	[55]	CLOSURE  	4 1	; 0x7fdf0cc08ea0
	12	[55]	MOVE     	0 0
	13	[55]	SETTABLE 	3 -8 4	; "executable" -
	14	[50]	CALL     	1 3 1
	15	[58]	GETUPVAL 	1 1	; MockTime
	16	[58]	SELF     	1 1 -9	; "increase"
	17	[58]	LOADK    	3 -10	; 2
	18	[58]	CALL     	1 3 1
	19	[59]	GETUPVAL 	1 2	; UIManager
	20	[59]	SELF     	1 1 -11	; "handleInput"
	21	[59]	CALL     	1 2 1
	22	[61]	LOADK    	1 -6	; 1
	23	[61]	LOADK    	2 -12	; 10
	24	[61]	LOADK    	3 -6	; 1
	25	[61]	FORPREP  	1 13	; to 39
	26	[62]	GETUPVAL 	5 1	; MockTime
	27	[62]	SELF     	5 5 -9	; "increase"
	28	[62]	LOADK    	7 -10	; 2
	29	[62]	CALL     	5 3 1
	30	[63]	GETUPVAL 	5 2	; UIManager
	31	[63]	SELF     	5 5 -11	; "handleInput"
	32	[63]	CALL     	5 2 1
	33	[64]	GETGLOBAL	5 -13	; assert
	34	[64]	GETTABLE 	5 5 -14	; "are"
	35	[64]	GETTABLE 	5 5 -15	; "equal"
	36	[64]	MOVE     	6 4
	37	[64]	MOVE     	7 0
	38	[64]	CALL     	5 3 1
	39	[61]	FORLOOP  	1 -14	; to 26
	40	[66]	GETUPVAL 	1 1	; MockTime
	41	[66]	SELF     	1 1 -9	; "increase"
	42	[66]	LOADK    	3 -10	; 2
	43	[66]	CALL     	1 3 1
	44	[67]	GETUPVAL 	1 2	; UIManager
	45	[67]	SELF     	1 1 -11	; "handleInput"
	46	[67]	CALL     	1 2 1
	47	[68]	GETGLOBAL	1 -13	; assert
	48	[68]	GETTABLE 	1 1 -14	; "are"
	49	[68]	GETTABLE 	1 1 -15	; "equal"
	50	[68]	LOADK    	2 -12	; 10
	51	[68]	MOVE     	3 0
	52	[68]	CALL     	1 3 1
	53	[69]	RETURN   	0 1

function <./spec/unit/background_runner_spec.lua:52,52> (7 instructions, 28 bytes at 0x7fdf0cc089a0)
0 params, 2 slots, 1 upvalue, 0 locals, 1 constant, 0 functions
	1	[52]	GETUPVAL 	0 0	; executed
	2	[52]	LT       	1 0 -1	; - 10
	3	[52]	JMP      	1	; to 5
	4	[52]	LOADBOOL 	0 0 1
	5	[52]	LOADBOOL 	0 1 0
	6	[52]	RETURN   	0 2
	7	[52]	RETURN   	0 1

function <./spec/unit/background_runner_spec.lua:53,55> (4 instructions, 16 bytes at 0x7fdf0cc08ea0)
0 params, 2 slots, 1 upvalue, 0 locals, 1 constant, 0 functions
	1	[54]	GETUPVAL 	0 0	; executed
	2	[54]	ADD      	0 0 -1	; - 1
	3	[54]	SETUPVAL 	0 0	; executed
	4	[55]	RETURN   	0 1

function <./spec/unit/background_runner_spec.lua:71,92> (51 instructions, 204 bytes at 0x7fdf0cc08570)
0 params, 8 slots, 3 upvalues, 5 locals, 15 constants, 1 function
	1	[72]	LOADK    	0 -1	; 0
	2	[73]	GETGLOBAL	1 -2	; table
	3	[73]	GETTABLE 	1 1 -3	; "insert"
	4	[73]	GETUPVAL 	2 0	; PluginShare
	5	[73]	GETTABLE 	2 2 -4	; "backgroundJobs"
	6	[73]	NEWTABLE 	3 0 3
	7	[74]	SETTABLE 	3 -5 -6	; "when" 1
	8	[75]	SETTABLE 	3 -7 -8	; "repeated" 10
	9	[78]	CLOSURE  	4 0	; 0x7fdf0cc08c20
	10	[78]	MOVE     	0 0
	11	[78]	SETTABLE 	3 -9 4	; "executable" -
	12	[73]	CALL     	1 3 1
	13	[81]	GETUPVAL 	1 1	; MockTime
	14	[81]	SELF     	1 1 -10	; "increase"
	15	[81]	LOADK    	3 -11	; 2
	16	[81]	CALL     	1 3 1
	17	[82]	GETUPVAL 	1 2	; UIManager
	18	[82]	SELF     	1 1 -12	; "handleInput"
	19	[82]	CALL     	1 2 1
	20	[84]	LOADK    	1 -6	; 1
	21	[84]	LOADK    	2 -8	; 10
	22	[84]	LOADK    	3 -6	; 1
	23	[84]	FORPREP  	1 13	; to 37
	24	[85]	GETUPVAL 	5 1	; MockTime
	25	[85]	SELF     	5 5 -10	; "increase"
	26	[85]	LOADK    	7 -11	; 2
	27	[85]	CALL     	5 3 1
	28	[86]	GETUPVAL 	5 2	; UIManager
	29	[86]	SELF     	5 5 -12	; "handleInput"
	30	[86]	CALL     	5 2 1
	31	[87]	GETGLOBAL	5 -13	; assert
	32	[87]	GETTABLE 	5 5 -14	; "are"
	33	[87]	GETTABLE 	5 5 -15	; "equal"
	34	[87]	MOVE     	6 4
	35	[87]	MOVE     	7 0
	36	[87]	CALL     	5 3 1
	37	[84]	FORLOOP  	1 -14	; to 24
	38	[89]	GETUPVAL 	1 1	; MockTime
	39	[89]	SELF     	1 1 -10	; "increase"
	40	[89]	LOADK    	3 -11	; 2
	41	[89]	CALL     	1 3 1
	42	[90]	GETUPVAL 	1 2	; UIManager
	43	[90]	SELF     	1 1 -12	; "handleInput"
	44	[90]	CALL     	1 2 1
	45	[91]	GETGLOBAL	1 -13	; assert
	46	[91]	GETTABLE 	1 1 -14	; "are"
	47	[91]	GETTABLE 	1 1 -15	; "equal"
	48	[91]	LOADK    	2 -8	; 10
	49	[91]	MOVE     	3 0
	50	[91]	CALL     	1 3 1
	51	[92]	RETURN   	0 1

function <./spec/unit/background_runner_spec.lua:76,78> (4 instructions, 16 bytes at 0x7fdf0cc08c20)
0 params, 2 slots, 1 upvalue, 0 locals, 1 constant, 0 functions
	1	[77]	GETUPVAL 	0 0	; executed
	2	[77]	ADD      	0 0 -1	; - 1
	3	[77]	SETUPVAL 	0 0	; executed
	4	[78]	RETURN   	0 1

function <./spec/unit/background_runner_spec.lua:94,116> (56 instructions, 224 bytes at 0x7fdf0cc08040)
0 params, 5 slots, 3 upvalues, 2 locals, 18 constants, 1 function
	1	[95]	LOADK    	0 -1	; 0
	2	[96]	NEWTABLE 	1 0 3
	3	[97]	SETTABLE 	1 -2 -3	; "when" 1
	4	[98]	SETTABLE 	1 -4 -5	; "repeated" true
	5	[102]	CLOSURE  	2 0	; 0x7fdf0cc07ae0
	6	[102]	MOVE     	0 0
	7	[102]	GETUPVAL 	0 0	; MockTime
	8	[102]	SETTABLE 	1 -6 2	; "executable" -
	9	[104]	GETGLOBAL	2 -7	; table
	10	[104]	GETTABLE 	2 2 -8	; "insert"
	11	[104]	GETUPVAL 	3 1	; PluginShare
	12	[104]	GETTABLE 	3 3 -9	; "backgroundJobs"
	13	[104]	MOVE     	4 1
	14	[104]	CALL     	2 3 1
	15	[106]	GETUPVAL 	2 0	; MockTime
	16	[106]	SELF     	2 2 -10	; "increase"
	17	[106]	LOADK    	4 -11	; 2
	18	[106]	CALL     	2 3 1
	19	[107]	GETUPVAL 	2 2	; UIManager
	20	[107]	SELF     	2 2 -12	; "handleInput"
	21	[107]	CALL     	2 2 1
	22	[108]	GETUPVAL 	2 0	; MockTime
	23	[108]	SELF     	2 2 -10	; "increase"
	24	[108]	LOADK    	4 -11	; 2
	25	[108]	CALL     	2 3 1
	26	[109]	GETUPVAL 	2 2	; UIManager
	27	[109]	SELF     	2 2 -12	; "handleInput"
	28	[109]	CALL     	2 2 1
	29	[110]	GETGLOBAL	2 -13	; assert
	30	[110]	GETTABLE 	2 2 -14	; "are"
	31	[110]	GETTABLE 	2 2 -15	; "equal"
	32	[110]	LOADK    	3 -3	; 1
	33	[110]	MOVE     	4 0
	34	[110]	CALL     	2 3 1
	35	[111]	GETGLOBAL	2 -13	; assert
	36	[111]	GETTABLE 	2 2 -16	; "is_true"
	37	[111]	GETTABLE 	3 1 -17	; "timeout"
	38	[111]	CALL     	2 2 1
	39	[112]	GETGLOBAL	2 -13	; assert
	40	[112]	GETTABLE 	2 2 -16	; "is_true"
	41	[112]	GETTABLE 	3 1 -18	; "blocked"
	42	[112]	CALL     	2 2 1
	43	[113]	GETUPVAL 	2 0	; MockTime
	44	[113]	SELF     	2 2 -10	; "increase"
	45	[113]	LOADK    	4 -11	; 2
	46	[113]	CALL     	2 3 1
	47	[114]	GETUPVAL 	2 2	; UIManager
	48	[114]	SELF     	2 2 -12	; "handleInput"
	49	[114]	CALL     	2 2 1
	50	[115]	GETGLOBAL	2 -13	; assert
	51	[115]	GETTABLE 	2 2 -14	; "are"
	52	[115]	GETTABLE 	2 2 -15	; "equal"
	53	[115]	LOADK    	3 -3	; 1
	54	[115]	MOVE     	4 0
	55	[115]	CALL     	2 3 1
	56	[116]	RETURN   	0 1

function <./spec/unit/background_runner_spec.lua:99,102> (8 instructions, 32 bytes at 0x7fdf0cc07ae0)
0 params, 3 slots, 2 upvalues, 0 locals, 3 constants, 0 functions
	1	[100]	GETUPVAL 	0 0	; executed
	2	[100]	ADD      	0 0 -1	; - 1
	3	[100]	SETUPVAL 	0 0	; executed
	4	[101]	GETUPVAL 	0 1	; MockTime
	5	[101]	SELF     	0 0 -2	; "increase"
	6	[101]	LOADK    	2 -3	; 2
	7	[101]	CALL     	0 3 1
	8	[102]	RETURN   	0 1

function <./spec/unit/background_runner_spec.lua:118,139> (43 instructions, 172 bytes at 0x7fdf0cc07fc0)
0 params, 5 slots, 3 upvalues, 2 locals, 21 constants, 1 function
	1	[119]	LOADBOOL 	0 0 0
	2	[120]	NEWTABLE 	1 0 3
	3	[121]	SETTABLE 	1 -1 -2	; "when" 1
	4	[122]	SETTABLE 	1 -3 -4	; "executable" "ls | grep this-should-not-be-a-file"
	5	[125]	CLOSURE  	2 0	; 0x7fdf0cc099d0
	6	[125]	MOVE     	0 0
	7	[125]	SETTABLE 	1 -5 2	; "callback" -
	8	[127]	GETGLOBAL	2 -6	; table
	9	[127]	GETTABLE 	2 2 -7	; "insert"
	10	[127]	GETUPVAL 	3 0	; PluginShare
	11	[127]	GETTABLE 	3 3 -8	; "backgroundJobs"
	12	[127]	MOVE     	4 1
	13	[127]	CALL     	2 3 1
	14	[129]	GETTABLE 	2 1 -9	; "end_sec"
	15	[129]	EQ       	0 2 -10	; - nil
	16	[129]	JMP      	8	; to 25
	17	[130]	GETUPVAL 	2 1	; MockTime
	18	[130]	SELF     	2 2 -11	; "increase"
	19	[130]	LOADK    	4 -12	; 2
	20	[130]	CALL     	2 3 1
	21	[131]	GETUPVAL 	2 2	; UIManager
	22	[131]	SELF     	2 2 -13	; "handleInput"
	23	[131]	CALL     	2 2 1
	24	[131]	JMP      	-11	; to 14
	25	[135]	GETGLOBAL	2 -14	; assert
	26	[135]	GETTABLE 	2 2 -15	; "are"
	27	[135]	GETTABLE 	2 2 -16	; "equal"
	28	[135]	LOADK    	3 -2	; 1
	29	[135]	GETTABLE 	4 1 -17	; "result"
	30	[135]	CALL     	2 3 1
	31	[136]	GETGLOBAL	2 -14	; assert
	32	[136]	GETTABLE 	2 2 -18	; "is_false"
	33	[136]	GETTABLE 	3 1 -19	; "timeout"
	34	[136]	CALL     	2 2 1
	35	[137]	GETGLOBAL	2 -14	; assert
	36	[137]	GETTABLE 	2 2 -18	; "is_false"
	37	[137]	GETTABLE 	3 1 -20	; "bad_command"
	38	[137]	CALL     	2 2 1
	39	[138]	GETGLOBAL	2 -14	; assert
	40	[138]	GETTABLE 	2 2 -21	; "is_true"
	41	[138]	MOVE     	3 0
	42	[138]	CALL     	2 2 1
	43	[139]	RETURN   	0 1

function <./spec/unit/background_runner_spec.lua:123,125> (3 instructions, 12 bytes at 0x7fdf0cc099d0)
0 params, 2 slots, 1 upvalue, 0 locals, 0 constants, 0 functions
	1	[124]	LOADBOOL 	0 1 0
	2	[124]	SETUPVAL 	0 0	; executed
	3	[125]	RETURN   	0 1

function <./spec/unit/background_runner_spec.lua:141,183> (103 instructions, 412 bytes at 0x7fdf0cc09d00)
0 params, 4 slots, 3 upvalues, 1 local, 30 constants, 0 functions
	1	[142]	NEWTABLE 	0 0 4
	2	[143]	SETTABLE 	0 -1 -2	; "when" 1
	3	[144]	SETTABLE 	0 -3 -4	; "repeated" false
	4	[145]	SETTABLE 	0 -5 -6	; "executable" "echo $ENV1 | grep $ENV2"
	5	[146]	NEWTABLE 	1 0 2
	6	[147]	SETTABLE 	1 -8 -9	; "ENV1" "yes"
	7	[148]	SETTABLE 	1 -10 -9	; "ENV2" "yes"
	8	[149]	SETTABLE 	0 -7 1	; "environment" -
	9	[151]	GETGLOBAL	1 -11	; table
	10	[151]	GETTABLE 	1 1 -12	; "insert"
	11	[151]	GETUPVAL 	2 0	; PluginShare
	12	[151]	GETTABLE 	2 2 -13	; "backgroundJobs"
	13	[151]	MOVE     	3 0
	14	[151]	CALL     	1 3 1
	15	[153]	GETTABLE 	1 0 -14	; "end_sec"
	16	[153]	EQ       	0 1 -15	; - nil
	17	[153]	JMP      	8	; to 26
	18	[154]	GETUPVAL 	1 1	; MockTime
	19	[154]	SELF     	1 1 -16	; "increase"
	20	[154]	LOADK    	3 -17	; 2
	21	[154]	CALL     	1 3 1
	22	[155]	GETUPVAL 	1 2	; UIManager
	23	[155]	SELF     	1 1 -18	; "handleInput"
	24	[155]	CALL     	1 2 1
	25	[155]	JMP      	-11	; to 15
	26	[159]	GETGLOBAL	1 -19	; assert
	27	[159]	GETTABLE 	1 1 -20	; "are"
	28	[159]	GETTABLE 	1 1 -21	; "equal"
	29	[159]	LOADK    	2 -22	; 0
	30	[159]	GETTABLE 	3 0 -23	; "result"
	31	[159]	CALL     	1 3 1
	32	[160]	GETGLOBAL	1 -19	; assert
	33	[160]	GETTABLE 	1 1 -24	; "is_false"
	34	[160]	GETTABLE 	2 0 -25	; "timeout"
	35	[160]	CALL     	1 2 1
	36	[161]	GETGLOBAL	1 -19	; assert
	37	[161]	GETTABLE 	1 1 -24	; "is_false"
	38	[161]	GETTABLE 	2 0 -26	; "bad_command"
	39	[161]	CALL     	1 2 1
	40	[163]	NEWTABLE 	1 0 2
	41	[164]	SETTABLE 	1 -8 -9	; "ENV1" "yes"
	42	[165]	SETTABLE 	1 -10 -27	; "ENV2" "no"
	43	[166]	SETTABLE 	0 -7 1	; "environment" -
	44	[167]	SETTABLE 	0 -14 -15	; "end_sec" nil
	45	[168]	GETGLOBAL	1 -11	; table
	46	[168]	GETTABLE 	1 1 -12	; "insert"
	47	[168]	GETUPVAL 	2 0	; PluginShare
	48	[168]	GETTABLE 	2 2 -13	; "backgroundJobs"
	49	[168]	MOVE     	3 0
	50	[168]	CALL     	1 3 1
	51	[170]	GETTABLE 	1 0 -14	; "end_sec"
	52	[170]	EQ       	0 1 -15	; - nil
	53	[170]	JMP      	8	; to 62
	54	[171]	GETUPVAL 	1 1	; MockTime
	55	[171]	SELF     	1 1 -16	; "increase"
	56	[171]	LOADK    	3 -17	; 2
	57	[171]	CALL     	1 3 1
	58	[172]	GETUPVAL 	1 2	; UIManager
	59	[172]	SELF     	1 1 -18	; "handleInput"
	60	[172]	CALL     	1 2 1
	61	[172]	JMP      	-11	; to 51
	62	[176]	GETGLOBAL	1 -19	; assert
	63	[176]	GETTABLE 	1 1 -20	; "are"
	64	[176]	GETTABLE 	1 1 -21	; "equal"
	65	[176]	LOADK    	2 -2	; 1
	66	[176]	GETTABLE 	3 0 -23	; "result"
	67	[176]	CALL     	1 3 1
	68	[177]	GETGLOBAL	1 -19	; assert
	69	[177]	GETTABLE 	1 1 -24	; "is_false"
	70	[177]	GETTABLE 	2 0 -25	; "timeout"
	71	[177]	CALL     	1 2 1
	72	[178]	GETGLOBAL	1 -19	; assert
	73	[178]	GETTABLE 	1 1 -24	; "is_false"
	74	[178]	GETTABLE 	2 0 -26	; "bad_command"
	75	[178]	CALL     	1 2 1
	76	[180]	GETGLOBAL	1 -19	; assert
	77	[180]	GETTABLE 	1 1 -20	; "are"
	78	[180]	GETTABLE 	1 1 -28	; "not_equal"
	79	[180]	GETGLOBAL	2 -29	; os
	80	[180]	GETTABLE 	2 2 -30	; "getenv"
	81	[180]	LOADK    	3 -8	; "ENV1"
	82	[180]	CALL     	2 2 2
	83	[180]	LOADK    	3 -9	; "yes"
	84	[180]	CALL     	1 3 1
	85	[181]	GETGLOBAL	1 -19	; assert
	86	[181]	GETTABLE 	1 1 -20	; "are"
	87	[181]	GETTABLE 	1 1 -28	; "not_equal"
	88	[181]	GETGLOBAL	2 -29	; os
	89	[181]	GETTABLE 	2 2 -30	; "getenv"
	90	[181]	LOADK    	3 -10	; "ENV2"
	91	[181]	CALL     	2 2 2
	92	[181]	LOADK    	3 -9	; "yes"
	93	[181]	CALL     	1 3 1
	94	[182]	GETGLOBAL	1 -19	; assert
	95	[182]	GETTABLE 	1 1 -20	; "are"
	96	[182]	GETTABLE 	1 1 -28	; "not_equal"
	97	[182]	GETGLOBAL	2 -29	; os
	98	[182]	GETTABLE 	2 2 -30	; "getenv"
	99	[182]	LOADK    	3 -10	; "ENV2"
	100	[182]	CALL     	2 2 2
	101	[182]	LOADK    	3 -27	; "no"
	102	[182]	CALL     	1 3 1
	103	[183]	RETURN   	0 1

function <./spec/unit/background_runner_spec.lua:185,223> (73 instructions, 292 bytes at 0x7fdf0cc07b60)
0 params, 5 slots, 3 upvalues, 2 locals, 25 constants, 1 function
	1	[186]	LOADK    	0 -1	; "yes"
	2	[187]	NEWTABLE 	1 0 4
	3	[188]	SETTABLE 	1 -2 -3	; "when" 1
	4	[189]	SETTABLE 	1 -4 -5	; "repeated" false
	5	[190]	SETTABLE 	1 -6 -7	; "executable" "echo $ENV1 | grep $ENV2"
	6	[196]	CLOSURE  	2 0	; 0x7fdf0cc07c90
	7	[196]	MOVE     	0 0
	8	[196]	SETTABLE 	1 -8 2	; "environment" -
	9	[198]	GETGLOBAL	2 -9	; table
	10	[198]	GETTABLE 	2 2 -10	; "insert"
	11	[198]	GETUPVAL 	3 0	; PluginShare
	12	[198]	GETTABLE 	3 3 -11	; "backgroundJobs"
	13	[198]	MOVE     	4 1
	14	[198]	CALL     	2 3 1
	15	[200]	GETTABLE 	2 1 -12	; "end_sec"
	16	[200]	EQ       	0 2 -13	; - nil
	17	[200]	JMP      	8	; to 26
	18	[201]	GETUPVAL 	2 1	; MockTime
	19	[201]	SELF     	2 2 -14	; "increase"
	20	[201]	LOADK    	4 -15	; 2
	21	[201]	CALL     	2 3 1
	22	[202]	GETUPVAL 	2 2	; UIManager
	23	[202]	SELF     	2 2 -16	; "handleInput"
	24	[202]	CALL     	2 2 1
	25	[202]	JMP      	-11	; to 15
	26	[206]	GETGLOBAL	2 -17	; assert
	27	[206]	GETTABLE 	2 2 -18	; "are"
	28	[206]	GETTABLE 	2 2 -19	; "equal"
	29	[206]	LOADK    	3 -20	; 0
	30	[206]	GETTABLE 	4 1 -21	; "result"
	31	[206]	CALL     	2 3 1
	32	[207]	GETGLOBAL	2 -17	; assert
	33	[207]	GETTABLE 	2 2 -22	; "is_false"
	34	[207]	GETTABLE 	3 1 -23	; "timeout"
	35	[207]	CALL     	2 2 1
	36	[208]	GETGLOBAL	2 -17	; assert
	37	[208]	GETTABLE 	2 2 -22	; "is_false"
	38	[208]	GETTABLE 	3 1 -24	; "bad_command"
	39	[208]	CALL     	2 2 1
	40	[210]	SETTABLE 	1 -12 -13	; "end_sec" nil
	41	[211]	LOADK    	0 -25	; "no"
	42	[212]	GETGLOBAL	2 -9	; table
	43	[212]	GETTABLE 	2 2 -10	; "insert"
	44	[212]	GETUPVAL 	3 0	; PluginShare
	45	[212]	GETTABLE 	3 3 -11	; "backgroundJobs"
	46	[212]	MOVE     	4 1
	47	[212]	CALL     	2 3 1
	48	[214]	GETTABLE 	2 1 -12	; "end_sec"
	49	[214]	EQ       	0 2 -13	; - nil
	50	[214]	JMP      	8	; to 59
	51	[215]	GETUPVAL 	2 1	; MockTime
	52	[215]	SELF     	2 2 -14	; "increase"
	53	[215]	LOADK    	4 -15	; 2
	54	[215]	CALL     	2 3 1
	55	[216]	GETUPVAL 	2 2	; UIManager
	56	[216]	SELF     	2 2 -16	; "handleInput"
	57	[216]	CALL     	2 2 1
	58	[216]	JMP      	-11	; to 48
	59	[220]	GETGLOBAL	2 -17	; assert
	60	[220]	GETTABLE 	2 2 -18	; "are"
	61	[220]	GETTABLE 	2 2 -19	; "equal"
	62	[220]	LOADK    	3 -3	; 1
	63	[220]	GETTABLE 	4 1 -21	; "result"
	64	[220]	CALL     	2 3 1
	65	[221]	GETGLOBAL	2 -17	; assert
	66	[221]	GETTABLE 	2 2 -22	; "is_false"
	67	[221]	GETTABLE 	3 1 -23	; "timeout"
	68	[221]	CALL     	2 2 1
	69	[222]	GETGLOBAL	2 -17	; assert
	70	[222]	GETTABLE 	2 2 -22	; "is_false"
	71	[222]	GETTABLE 	3 1 -24	; "bad_command"
	72	[222]	CALL     	2 2 1
	73	[223]	RETURN   	0 1

function <./spec/unit/background_runner_spec.lua:191,196> (6 instructions, 24 bytes at 0x7fdf0cc07c90)
0 params, 2 slots, 1 upvalue, 0 locals, 3 constants, 0 functions
	1	[192]	NEWTABLE 	0 0 2
	2	[193]	SETTABLE 	0 -1 -2	; "ENV1" "yes"
	3	[194]	GETUPVAL 	1 0	; env2
	4	[194]	SETTABLE 	0 -3 1	; "ENV2" -
	5	[195]	RETURN   	0 2
	6	[196]	RETURN   	0 1

function <./spec/unit/background_runner_spec.lua:225,244> (39 instructions, 156 bytes at 0x7fdf0cc08680)
0 params, 4 slots, 3 upvalues, 1 local, 24 constants, 0 functions
	1	[226]	NEWTABLE 	0 0 4
	2	[227]	SETTABLE 	0 -1 -2	; "when" 1
	3	[228]	SETTABLE 	0 -3 -4	; "repeated" true
	4	[229]	SETTABLE 	0 -5 -6	; "executable" "sleep 1h"
	5	[230]	NEWTABLE 	1 0 1
	6	[231]	SETTABLE 	1 -8 -2	; "TIMEOUT" 1
	7	[232]	SETTABLE 	0 -7 1	; "environment" -
	8	[234]	GETGLOBAL	1 -9	; table
	9	[234]	GETTABLE 	1 1 -10	; "insert"
	10	[234]	GETUPVAL 	2 0	; PluginShare
	11	[234]	GETTABLE 	2 2 -11	; "backgroundJobs"
	12	[234]	MOVE     	3 0
	13	[234]	CALL     	1 3 1
	14	[236]	GETTABLE 	1 0 -12	; "end_sec"
	15	[236]	EQ       	0 1 -13	; - nil
	16	[236]	JMP      	8	; to 25
	17	[237]	GETUPVAL 	1 1	; MockTime
	18	[237]	SELF     	1 1 -14	; "increase"
	19	[237]	LOADK    	3 -15	; 2
	20	[237]	CALL     	1 3 1
	21	[238]	GETUPVAL 	1 2	; UIManager
	22	[238]	SELF     	1 1 -16	; "handleInput"
	23	[238]	CALL     	1 2 1
	24	[238]	JMP      	-11	; to 14
	25	[241]	GETGLOBAL	1 -17	; assert
	26	[241]	GETTABLE 	1 1 -18	; "are"
	27	[241]	GETTABLE 	1 1 -19	; "equal"
	28	[241]	LOADK    	2 -20	; 255
	29	[241]	GETTABLE 	3 0 -21	; "result"
	30	[241]	CALL     	1 3 1
	31	[242]	GETGLOBAL	1 -17	; assert
	32	[242]	GETTABLE 	1 1 -22	; "is_true"
	33	[242]	GETTABLE 	2 0 -23	; "timeout"
	34	[242]	CALL     	1 2 1
	35	[243]	GETGLOBAL	1 -17	; assert
	36	[243]	GETTABLE 	1 1 -22	; "is_true"
	37	[243]	GETTABLE 	2 0 -24	; "blocked"
	38	[243]	CALL     	1 2 1
	39	[244]	RETURN   	0 1

function <./spec/unit/background_runner_spec.lua:246,268> (53 instructions, 212 bytes at 0x7fdf0cc0b830)
0 params, 8 slots, 3 upvalues, 5 locals, 16 constants, 2 functions
	1	[247]	LOADK    	0 -1	; 0
	2	[248]	GETGLOBAL	1 -2	; table
	3	[248]	GETTABLE 	1 1 -3	; "insert"
	4	[248]	GETUPVAL 	2 0	; PluginShare
	5	[248]	GETTABLE 	2 2 -4	; "backgroundJobs"
	6	[248]	NEWTABLE 	3 0 4
	7	[249]	SETTABLE 	3 -5 -6	; "when" 1
	8	[250]	SETTABLE 	3 -7 -8	; "repeated" 10
	9	[251]	CLOSURE  	4 0	; 0x7fdf0cc0aaf0
	10	[251]	SETTABLE 	3 -9 4	; "executable" -
	11	[254]	CLOSURE  	4 1	; 0x7fdf0cc0af70
	12	[254]	MOVE     	0 0
	13	[254]	SETTABLE 	3 -10 4	; "callback" -
	14	[248]	CALL     	1 3 1
	15	[257]	GETUPVAL 	1 1	; MockTime
	16	[257]	SELF     	1 1 -11	; "increase"
	17	[257]	LOADK    	3 -12	; 2
	18	[257]	CALL     	1 3 1
	19	[258]	GETUPVAL 	1 2	; UIManager
	20	[258]	SELF     	1 1 -13	; "handleInput"
	21	[258]	CALL     	1 2 1
	22	[260]	LOADK    	1 -6	; 1
	23	[260]	LOADK    	2 -8	; 10
	24	[260]	LOADK    	3 -6	; 1
	25	[260]	FORPREP  	1 13	; to 39
	26	[261]	GETUPVAL 	5 1	; MockTime
	27	[261]	SELF     	5 5 -11	; "increase"
	28	[261]	LOADK    	7 -12	; 2
	29	[261]	CALL     	5 3 1
	30	[262]	GETUPVAL 	5 2	; UIManager
	31	[262]	SELF     	5 5 -13	; "handleInput"
	32	[262]	CALL     	5 2 1
	33	[263]	GETGLOBAL	5 -14	; assert
	34	[263]	GETTABLE 	5 5 -15	; "are"
	35	[263]	GETTABLE 	5 5 -16	; "equal"
	36	[263]	MOVE     	6 4
	37	[263]	MOVE     	7 0
	38	[263]	CALL     	5 3 1
	39	[260]	FORLOOP  	1 -14	; to 26
	40	[265]	GETUPVAL 	1 1	; MockTime
	41	[265]	SELF     	1 1 -11	; "increase"
	42	[265]	LOADK    	3 -12	; 2
	43	[265]	CALL     	1 3 1
	44	[266]	GETUPVAL 	1 2	; UIManager
	45	[266]	SELF     	1 1 -13	; "handleInput"
	46	[266]	CALL     	1 2 1
	47	[267]	GETGLOBAL	1 -14	; assert
	48	[267]	GETTABLE 	1 1 -15	; "are"
	49	[267]	GETTABLE 	1 1 -16	; "equal"
	50	[267]	LOADK    	2 -8	; 10
	51	[267]	MOVE     	3 0
	52	[267]	CALL     	1 3 1
	53	[268]	RETURN   	0 1

function <./spec/unit/background_runner_spec.lua:251,251> (1 instruction, 4 bytes at 0x7fdf0cc0aaf0)
0 params, 2 slots, 0 upvalues, 0 locals, 0 constants, 0 functions
	1	[251]	RETURN   	0 1

function <./spec/unit/background_runner_spec.lua:252,254> (4 instructions, 16 bytes at 0x7fdf0cc0af70)
0 params, 2 slots, 1 upvalue, 0 locals, 1 constant, 0 functions
	1	[253]	GETUPVAL 	0 0	; executed
	2	[253]	ADD      	0 0 -1	; - 1
	3	[253]	SETUPVAL 	0 0	; executed
	4	[254]	RETURN   	0 1

function <./spec/unit/background_runner_spec.lua:270,296> (68 instructions, 272 bytes at 0x7fdf0cc0aa30)
0 params, 5 slots, 3 upvalues, 1 local, 13 constants, 2 functions
	1	[271]	LOADK    	0 -1	; 0
	2	[272]	GETGLOBAL	1 -2	; table
	3	[272]	GETTABLE 	1 1 -3	; "insert"
	4	[272]	GETUPVAL 	2 0	; PluginShare
	5	[272]	GETTABLE 	2 2 -4	; "backgroundJobs"
	6	[272]	NEWTABLE 	3 0 2
	7	[273]	SETTABLE 	3 -5 -6	; "when" 1
	8	[276]	CLOSURE  	4 0	; 0x7fdf0cc0bed0
	9	[276]	MOVE     	0 0
	10	[276]	SETTABLE 	3 -7 4	; "executable" -
	11	[272]	CALL     	1 3 1
	12	[278]	GETGLOBAL	1 -2	; table
	13	[278]	GETTABLE 	1 1 -3	; "insert"
	14	[278]	GETUPVAL 	2 0	; PluginShare
	15	[278]	GETTABLE 	2 2 -4	; "backgroundJobs"
	16	[278]	NEWTABLE 	3 0 2
	17	[279]	SETTABLE 	3 -5 -6	; "when" 1
	18	[282]	CLOSURE  	4 1	; 0x7fdf0cc0c130
	19	[282]	MOVE     	0 0
	20	[282]	SETTABLE 	3 -7 4	; "executable" -
	21	[278]	CALL     	1 3 1
	22	[285]	GETUPVAL 	1 1	; MockTime
	23	[285]	SELF     	1 1 -8	; "increase"
	24	[285]	LOADK    	3 -9	; 2
	25	[285]	CALL     	1 3 1
	26	[286]	GETUPVAL 	1 2	; UIManager
	27	[286]	SELF     	1 1 -10	; "handleInput"
	28	[286]	CALL     	1 2 1
	29	[287]	GETUPVAL 	1 1	; MockTime
	30	[287]	SELF     	1 1 -8	; "increase"
	31	[287]	LOADK    	3 -9	; 2
	32	[287]	CALL     	1 3 1
	33	[288]	GETUPVAL 	1 2	; UIManager
	34	[288]	SELF     	1 1 -10	; "handleInput"
	35	[288]	CALL     	1 2 1
	36	[289]	GETGLOBAL	1 -11	; assert
	37	[289]	GETTABLE 	1 1 -12	; "are"
	38	[289]	GETTABLE 	1 1 -13	; "equal"
	39	[289]	LOADK    	2 -6	; 1
	40	[289]	MOVE     	3 0
	41	[289]	CALL     	1 3 1
	42	[290]	GETUPVAL 	1 1	; MockTime
	43	[290]	SELF     	1 1 -8	; "increase"
	44	[290]	LOADK    	3 -9	; 2
	45	[290]	CALL     	1 3 1
	46	[291]	GETUPVAL 	1 2	; UIManager
	47	[291]	SELF     	1 1 -10	; "handleInput"
	48	[291]	CALL     	1 2 1
	49	[292]	GETGLOBAL	1 -11	; assert
	50	[292]	GETTABLE 	1 1 -12	; "are"
	51	[292]	GETTABLE 	1 1 -13	; "equal"
	52	[292]	LOADK    	2 -9	; 2
	53	[292]	MOVE     	3 0
	54	[292]	CALL     	1 3 1
	55	[293]	GETUPVAL 	1 1	; MockTime
	56	[293]	SELF     	1 1 -8	; "increase"
	57	[293]	LOADK    	3 -9	; 2
	58	[293]	CALL     	1 3 1
	59	[294]	GETUPVAL 	1 2	; UIManager
	60	[294]	SELF     	1 1 -10	; "handleInput"
	61	[294]	CALL     	1 2 1
	62	[295]	GETGLOBAL	1 -11	; assert
	63	[295]	GETTABLE 	1 1 -12	; "are"
	64	[295]	GETTABLE 	1 1 -13	; "equal"
	65	[295]	LOADK    	2 -9	; 2
	66	[295]	MOVE     	3 0
	67	[295]	CALL     	1 3 1
	68	[296]	RETURN   	0 1

function <./spec/unit/background_runner_spec.lua:274,276> (4 instructions, 16 bytes at 0x7fdf0cc0bed0)
0 params, 2 slots, 1 upvalue, 0 locals, 1 constant, 0 functions
	1	[275]	GETUPVAL 	0 0	; executed
	2	[275]	ADD      	0 0 -1	; - 1
	3	[275]	SETUPVAL 	0 0	; executed
	4	[276]	RETURN   	0 1

function <./spec/unit/background_runner_spec.lua:280,282> (4 instructions, 16 bytes at 0x7fdf0cc0c130)
0 params, 2 slots, 1 upvalue, 0 locals, 1 constant, 0 functions
	1	[281]	GETUPVAL 	0 0	; executed
	2	[281]	ADD      	0 0 -1	; - 1
	3	[281]	SETUPVAL 	0 0	; executed
	4	[282]	RETURN   	0 1

function <./spec/unit/background_runner_spec.lua:298,329> (86 instructions, 344 bytes at 0x7fdf0cc0be50)
0 params, 9 slots, 3 upvalues, 6 locals, 21 constants, 1 function
	1	[299]	LOADK    	0 -1	; 0
	2	[300]	NEWTABLE 	1 0 3
	3	[301]	SETTABLE 	1 -2 -3	; "when" 1
	4	[302]	SETTABLE 	1 -4 -5	; "repeated" true
	5	[305]	CLOSURE  	2 0	; 0x7fdf0cc0c030
	6	[305]	MOVE     	0 0
	7	[305]	SETTABLE 	1 -6 2	; "executable" -
	8	[307]	GETGLOBAL	2 -7	; table
	9	[307]	GETTABLE 	2 2 -8	; "insert"
	10	[307]	GETUPVAL 	3 0	; PluginShare
	11	[307]	GETTABLE 	3 3 -9	; "backgroundJobs"
	12	[307]	MOVE     	4 1
	13	[307]	CALL     	2 3 1
	14	[309]	GETUPVAL 	2 1	; MockTime
	15	[309]	SELF     	2 2 -10	; "increase"
	16	[309]	LOADK    	4 -11	; 2
	17	[309]	CALL     	2 3 1
	18	[310]	GETUPVAL 	2 2	; UIManager
	19	[310]	SELF     	2 2 -12	; "handleInput"
	20	[310]	CALL     	2 2 1
	21	[311]	GETUPVAL 	2 1	; MockTime
	22	[311]	SELF     	2 2 -10	; "increase"
	23	[311]	LOADK    	4 -11	; 2
	24	[311]	CALL     	2 3 1
	25	[312]	GETUPVAL 	2 2	; UIManager
	26	[312]	SELF     	2 2 -12	; "handleInput"
	27	[312]	CALL     	2 2 1
	28	[313]	GETGLOBAL	2 -13	; assert
	29	[313]	GETTABLE 	2 2 -14	; "are"
	30	[313]	GETTABLE 	2 2 -15	; "equal"
	31	[313]	LOADK    	3 -3	; 1
	32	[313]	MOVE     	4 0
	33	[313]	CALL     	2 3 1
	34	[315]	GETGLOBAL	2 -16	; requireBackgroundRunner
	35	[315]	CALL     	2 1 2
	36	[315]	SELF     	2 2 -17	; "onSuspend"
	37	[315]	CALL     	2 2 1
	38	[316]	LOADK    	2 -3	; 1
	39	[316]	LOADK    	3 -18	; 10
	40	[316]	LOADK    	4 -3	; 1
	41	[316]	FORPREP  	2 13	; to 55
	42	[317]	GETUPVAL 	6 1	; MockTime
	43	[317]	SELF     	6 6 -10	; "increase"
	44	[317]	LOADK    	8 -11	; 2
	45	[317]	CALL     	6 3 1
	46	[318]	GETUPVAL 	6 2	; UIManager
	47	[318]	SELF     	6 6 -12	; "handleInput"
	48	[318]	CALL     	6 2 1
	49	[319]	GETGLOBAL	6 -13	; assert
	50	[319]	GETTABLE 	6 6 -14	; "are"
	51	[319]	GETTABLE 	6 6 -15	; "equal"
	52	[319]	LOADK    	7 -11	; 2
	53	[319]	MOVE     	8 0
	54	[319]	CALL     	6 3 1
	55	[316]	FORLOOP  	2 -14	; to 42
	56	[322]	GETGLOBAL	2 -16	; requireBackgroundRunner
	57	[322]	CALL     	2 1 2
	58	[322]	SELF     	2 2 -19	; "onResume"
	59	[322]	CALL     	2 2 1
	60	[323]	GETUPVAL 	2 1	; MockTime
	61	[323]	SELF     	2 2 -10	; "increase"
	62	[323]	LOADK    	4 -11	; 2
	63	[323]	CALL     	2 3 1
	64	[324]	GETUPVAL 	2 2	; UIManager
	65	[324]	SELF     	2 2 -12	; "handleInput"
	66	[324]	CALL     	2 2 1
	67	[325]	GETGLOBAL	2 -13	; assert
	68	[325]	GETTABLE 	2 2 -14	; "are"
	69	[325]	GETTABLE 	2 2 -15	; "equal"
	70	[325]	LOADK    	3 -20	; 3
	71	[325]	MOVE     	4 0
	72	[325]	CALL     	2 3 1
	73	[326]	GETUPVAL 	2 1	; MockTime
	74	[326]	SELF     	2 2 -10	; "increase"
	75	[326]	LOADK    	4 -11	; 2
	76	[326]	CALL     	2 3 1
	77	[327]	GETUPVAL 	2 2	; UIManager
	78	[327]	SELF     	2 2 -12	; "handleInput"
	79	[327]	CALL     	2 2 1
	80	[328]	GETGLOBAL	2 -13	; assert
	81	[328]	GETTABLE 	2 2 -14	; "are"
	82	[328]	GETTABLE 	2 2 -15	; "equal"
	83	[328]	LOADK    	3 -21	; 4
	84	[328]	MOVE     	4 0
	85	[328]	CALL     	2 3 1
	86	[329]	RETURN   	0 1

function <./spec/unit/background_runner_spec.lua:303,305> (4 instructions, 16 bytes at 0x7fdf0cc0c030)
0 params, 2 slots, 1 upvalue, 0 locals, 1 constant, 0 functions
	1	[304]	GETUPVAL 	0 0	; executed
	2	[304]	ADD      	0 0 -1	; - 1
	3	[304]	SETUPVAL 	0 0	; executed
	4	[305]	RETURN   	0 1

function <./spec/unit/background_runner_spec.lua:331,357> (69 instructions, 276 bytes at 0x7fdf0cc0c8c0)
0 params, 8 slots, 3 upvalues, 6 locals, 19 constants, 1 function
	1	[332]	LOADK    	0 -1	; 0
	2	[333]	NEWTABLE 	1 0 3
	3	[334]	SETTABLE 	1 -2 -3	; "when" 1
	4	[335]	SETTABLE 	1 -4 -5	; "repeated" true
	5	[338]	CLOSURE  	2 0	; 0x7fdf0cc0cfd0
	6	[338]	MOVE     	0 0
	7	[338]	SETTABLE 	1 -6 2	; "executable" -
	8	[340]	GETGLOBAL	2 -7	; table
	9	[340]	GETTABLE 	2 2 -8	; "insert"
	10	[340]	GETUPVAL 	3 0	; PluginShare
	11	[340]	GETTABLE 	3 3 -9	; "backgroundJobs"
	12	[340]	MOVE     	4 1
	13	[340]	CALL     	2 3 1
	14	[342]	LOADK    	2 -3	; 1
	15	[342]	LOADK    	3 -10	; 10
	16	[342]	LOADK    	4 -3	; 1
	17	[342]	FORPREP  	2 4	; to 22
	18	[343]	GETGLOBAL	6 -11	; requireBackgroundRunner
	19	[343]	CALL     	6 1 2
	20	[343]	SELF     	6 6 -12	; "onResume"
	21	[343]	CALL     	6 2 1
	22	[342]	FORLOOP  	2 -5	; to 18
	23	[346]	GETUPVAL 	2 1	; MockTime
	24	[346]	SELF     	2 2 -13	; "increase"
	25	[346]	LOADK    	4 -14	; 2
	26	[346]	CALL     	2 3 1
	27	[347]	GETUPVAL 	2 2	; UIManager
	28	[347]	SELF     	2 2 -15	; "handleInput"
	29	[347]	CALL     	2 2 1
	30	[348]	GETUPVAL 	2 1	; MockTime
	31	[348]	SELF     	2 2 -13	; "increase"
	32	[348]	LOADK    	4 -14	; 2
	33	[348]	CALL     	2 3 1
	34	[349]	GETUPVAL 	2 2	; UIManager
	35	[349]	SELF     	2 2 -15	; "handleInput"
	36	[349]	CALL     	2 2 1
	37	[350]	GETGLOBAL	2 -16	; assert
	38	[350]	GETTABLE 	2 2 -17	; "are"
	39	[350]	GETTABLE 	2 2 -18	; "equal"
	40	[350]	LOADK    	3 -3	; 1
	41	[350]	MOVE     	4 0
	42	[350]	CALL     	2 3 1
	43	[351]	GETUPVAL 	2 1	; MockTime
	44	[351]	SELF     	2 2 -13	; "increase"
	45	[351]	LOADK    	4 -14	; 2
	46	[351]	CALL     	2 3 1
	47	[352]	GETUPVAL 	2 2	; UIManager
	48	[352]	SELF     	2 2 -15	; "handleInput"
	49	[352]	CALL     	2 2 1
	50	[353]	GETGLOBAL	2 -16	; assert
	51	[353]	GETTABLE 	2 2 -17	; "are"
	52	[353]	GETTABLE 	2 2 -18	; "equal"
	53	[353]	LOADK    	3 -14	; 2
	54	[353]	MOVE     	4 0
	55	[353]	CALL     	2 3 1
	56	[354]	GETUPVAL 	2 1	; MockTime
	57	[354]	SELF     	2 2 -13	; "increase"
	58	[354]	LOADK    	4 -14	; 2
	59	[354]	CALL     	2 3 1
	60	[355]	GETUPVAL 	2 2	; UIManager
	61	[355]	SELF     	2 2 -15	; "handleInput"
	62	[355]	CALL     	2 2 1
	63	[356]	GETGLOBAL	2 -16	; assert
	64	[356]	GETTABLE 	2 2 -17	; "are"
	65	[356]	GETTABLE 	2 2 -18	; "equal"
	66	[356]	LOADK    	3 -19	; 3
	67	[356]	MOVE     	4 0
	68	[356]	CALL     	2 3 1
	69	[357]	RETURN   	0 1

function <./spec/unit/background_runner_spec.lua:336,338> (4 instructions, 16 bytes at 0x7fdf0cc0cfd0)
0 params, 2 slots, 1 upvalue, 0 locals, 1 constant, 0 functions
	1	[337]	GETUPVAL 	0 0	; executed
	2	[337]	ADD      	0 0 -1	; - 1
	3	[337]	SETUPVAL 	0 0	; executed
	4	[338]	RETURN   	0 1
