
main <./frontend/ui/plugin/background_task_plugin.lua:0,0> (15 instructions, 60 bytes at 0x7fa422c068f0)
0+ params, 4 slots, 0 upvalues, 3 locals, 6 constants, 2 functions
	1	[7]	GETGLOBAL	0 -1	; require
	2	[7]	LOADK    	1 -2	; "pluginshare"
	3	[7]	CALL     	0 2 2
	4	[8]	GETGLOBAL	1 -1	; require
	5	[8]	LOADK    	2 -3	; "ui/plugin/switch_plugin"
	6	[8]	CALL     	1 2 2
	7	[10]	SELF     	2 1 -4	; "extend"
	8	[10]	CALL     	2 2 2
	9	[29]	CLOSURE  	3 0	; 0x7fa422c06c80
	10	[29]	MOVE     	0 0
	11	[12]	SETTABLE 	2 -5 3	; "_schedule" -
	12	[33]	CLOSURE  	3 1	; 0x7fa422c079a0
	13	[31]	SETTABLE 	2 -6 3	; "_start" -
	14	[35]	RETURN   	2 2
	15	[35]	RETURN   	0 1

function <./frontend/ui/plugin/background_task_plugin.lua:12,29> (15 instructions, 60 bytes at 0x7fa422c06c80)
2 params, 7 slots, 1 upvalue, 3 locals, 6 constants, 1 function
	1	[22]	CLOSURE  	2 0	; 0x7fa422c07260
	2	[22]	MOVE     	0 0
	3	[22]	MOVE     	0 1
	4	[24]	GETGLOBAL	3 -1	; table
	5	[24]	GETTABLE 	3 3 -2	; "insert"
	6	[24]	GETUPVAL 	4 0	; PluginShare
	7	[24]	GETTABLE 	4 4 -3	; "backgroundJobs"
	8	[24]	NEWTABLE 	5 0 3
	9	[25]	GETTABLE 	6 0 -4	; "when"
	10	[25]	SETTABLE 	5 -4 6	; "when" -
	11	[26]	SETTABLE 	5 -5 2	; "repeated" -
	12	[27]	GETTABLE 	6 0 -6	; "executable"
	13	[27]	SETTABLE 	5 -6 6	; "executable" -
	14	[24]	CALL     	3 3 1
	15	[29]	RETURN   	0 1

function <./frontend/ui/plugin/background_task_plugin.lua:13,22> (16 instructions, 64 bytes at 0x7fa422c07260)
0 params, 2 slots, 2 upvalues, 0 locals, 2 constants, 0 functions
	1	[14]	GETUPVAL 	0 0	; self
	2	[14]	GETTABLE 	0 0 -1	; "enabled"
	3	[14]	TEST     	0 0 1
	4	[14]	JMP      	2	; to 7
	5	[15]	LOADBOOL 	0 0 0
	6	[15]	RETURN   	0 2
	7	[17]	GETUPVAL 	0 1	; settings_id
	8	[17]	GETUPVAL 	1 0	; self
	9	[17]	GETTABLE 	1 1 -2	; "settings_id"
	10	[17]	EQ       	1 0 1
	11	[17]	JMP      	2	; to 14
	12	[18]	LOADBOOL 	0 0 0
	13	[18]	RETURN   	0 2
	14	[21]	LOADBOOL 	0 1 0
	15	[21]	RETURN   	0 2
	16	[22]	RETURN   	0 1

function <./frontend/ui/plugin/background_task_plugin.lua:31,33> (4 instructions, 16 bytes at 0x7fa422c079a0)
1 param, 4 slots, 0 upvalues, 1 local, 2 constants, 0 functions
	1	[32]	SELF     	1 0 -1	; "_schedule"
	2	[32]	GETTABLE 	3 0 -2	; "settings_id"
	3	[32]	CALL     	1 3 1
	4	[33]	RETURN   	0 1
