-- BYTECODE -- batterystat_spec.lua:4-6
0001    UGET     0   0      ; module
0002    MOV      1   0
0003    TGETS    0   0   0  ; "new"
0004    CALL     0   2   2
0005    MOV      1   0
0006    TGETS    0   0   1  ; "stat"
0007    CALLT    0   2

-- BYTECODE -- batterystat_spec.lua:8-14
0001    GGET     0   0      ; "require"
0002    KSTR     1   1      ; "commonrequire"
0003    CALL     0   1   2
0004    GGET     0   2      ; "package"
0005    TGETS    0   0   3  ; "unloadAll"
0006    CALL     0   1   1
0007    GGET     0   0      ; "require"
0008    KSTR     1   4      ; "document/canvascontext"
0009    CALL     0   2   2
0010    MOV      1   0
0011    TGETS    0   0   5  ; "init"
0012    GGET     2   0      ; "require"
0013    KSTR     3   6      ; "device"
0014    CALL     2   0   2
0015    CALLM    0   1   1
0016    GGET     0   0      ; "require"
0017    KSTR     1   7      ; "mock_time"
0018    CALL     0   2   2
0019    USETV    0   0      ; MockTime
0020    UGET     0   0      ; MockTime
0021    MOV      1   0
0022    TGETS    0   0   8  ; "install"
0023    CALL     0   1   2
0024    RET0     0   1

-- BYTECODE -- batterystat_spec.lua:16-20
0001    UGET     0   0      ; MockTime
0002    MOV      1   0
0003    TGETS    0   0   0  ; "uninstall"
0004    CALL     0   1   2
0005    GGET     0   1      ; "package"
0006    TGETS    0   0   2  ; "unloadAll"
0007    CALL     0   1   1
0008    GGET     0   3      ; "require"
0009    KSTR     1   4      ; "document/canvascontext"
0010    CALL     0   2   2
0011    MOV      1   0
0012    TGETS    0   0   5  ; "init"
0013    GGET     2   3      ; "require"
0014    KSTR     3   6      ; "device"
0015    CALL     2   0   2
0016    CALLM    0   1   1
0017    RET0     0   1

-- BYTECODE -- batterystat_spec.lua:22-24
0001    GGET     0   0      ; "dofile"
0002    KSTR     1   1      ; "plugins/batterystat.koplugin/main.lua"
0003    CALL     0   2   2
0004    USETV    0   0      ; module
0005    RET0     0   1

-- BYTECODE -- batterystat_spec.lua:26-70
0001    UGET     0   0      ; stat
0002    CALL     0   2   1
0003    GGET     1   0      ; "assert"
0004    TGETS    1   1   1  ; "is_false"
0005    TGETS    2   0   2  ; "was_charging"
0006    CALL     1   1   2
0007    GGET     1   0      ; "assert"
0008    TGETS    1   1   1  ; "is_false"
0009    TGETS    2   0   3  ; "was_suspending"
0010    CALL     1   1   2
0011    MOV      2   0
0012    TGETS    1   0   4  ; "resetAll"
0013    CALL     1   1   2
0014    UGET     1   1      ; MockTime
0015    MOV      2   1
0016    TGETS    1   1   5  ; "increase"
0017    KSHORT   3   1
0018    CALL     1   1   3
0019    MOV      2   0
0020    TGETS    1   0   6  ; "accumulate"
0021    CALL     1   1   2
0022    GGET     1   0      ; "assert"
0023    TGETS    1   1   7  ; "are"
0024    TGETS    1   1   8  ; "equal"
0025    KSHORT   2   1
0026    TGETS    3   0   9  ; "awake"
0027    TGETS    3   3  10  ; "time"
0028    CALL     1   1   3
0029    GGET     1   0      ; "assert"
0030    TGETS    1   1   7  ; "are"
0031    TGETS    1   1   8  ; "equal"
0032    KSHORT   2   0
0033    TGETS    3   0  11  ; "sleeping"
0034    TGETS    3   3  10  ; "time"
0035    CALL     1   1   3
0036    GGET     1   0      ; "assert"
0037    TGETS    1   1   7  ; "are"
0038    TGETS    1   1   8  ; "equal"
0039    KSHORT   2   1
0040    TGETS    3   0  12  ; "discharging"
0041    TGETS    3   3  10  ; "time"
0042    CALL     1   1   3
0043    GGET     1   0      ; "assert"
0044    TGETS    1   1   7  ; "are"
0045    TGETS    1   1   8  ; "equal"
0046    KSHORT   2   0
0047    TGETS    3   0  13  ; "charging"
0048    TGETS    3   3  10  ; "time"
0049    CALL     1   1   3
0050    MOV      2   0
0051    TGETS    1   0  14  ; "onCharging"
0052    CALL     1   1   2
0053    GGET     1   0      ; "assert"
0054    TGETS    1   1  15  ; "is_true"
0055    TGETS    2   0   2  ; "was_charging"
0056    CALL     1   1   2
0057    GGET     1   0      ; "assert"
0058    TGETS    1   1   1  ; "is_false"
0059    TGETS    2   0   3  ; "was_suspending"
0060    CALL     1   1   2
0061    UGET     1   1      ; MockTime
0062    MOV      2   1
0063    TGETS    1   1   5  ; "increase"
0064    KSHORT   3   1
0065    CALL     1   1   3
0066    MOV      2   0
0067    TGETS    1   0   6  ; "accumulate"
0068    CALL     1   1   2
0069    GGET     1   0      ; "assert"
0070    TGETS    1   1   7  ; "are"
0071    TGETS    1   1   8  ; "equal"
0072    KSHORT   2   0
0073    TGETS    3   0   9  ; "awake"
0074    TGETS    3   3  10  ; "time"
0075    CALL     1   1   3
0076    GGET     1   0      ; "assert"
0077    TGETS    1   1   7  ; "are"
0078    TGETS    1   1   8  ; "equal"
0079    KSHORT   2   0
0080    TGETS    3   0  11  ; "sleeping"
0081    TGETS    3   3  10  ; "time"
0082    CALL     1   1   3
0083    GGET     1   0      ; "assert"
0084    TGETS    1   1   7  ; "are"
0085    TGETS    1   1   8  ; "equal"
0086    KSHORT   2   0
0087    TGETS    3   0  12  ; "discharging"
0088    TGETS    3   3  10  ; "time"
0089    CALL     1   1   3
0090    GGET     1   0      ; "assert"
0091    TGETS    1   1   7  ; "are"
0092    TGETS    1   1   8  ; "equal"
0093    KSHORT   2   1
0094    TGETS    3   0  13  ; "charging"
0095    TGETS    3   3  10  ; "time"
0096    CALL     1   1   3
0097    MOV      2   0
0098    TGETS    1   0  16  ; "onNotCharging"
0099    CALL     1   1   2
0100    GGET     1   0      ; "assert"
0101    TGETS    1   1   1  ; "is_false"
0102    TGETS    2   0   2  ; "was_charging"
0103    CALL     1   1   2
0104    GGET     1   0      ; "assert"
0105    TGETS    1   1   1  ; "is_false"
0106    TGETS    2   0   3  ; "was_suspending"
0107    CALL     1   1   2
0108    UGET     1   1      ; MockTime
0109    MOV      2   1
0110    TGETS    1   1   5  ; "increase"
0111    KSHORT   3   1
0112    CALL     1   1   3
0113    MOV      2   0
0114    TGETS    1   0   6  ; "accumulate"
0115    CALL     1   1   2
0116    GGET     1   0      ; "assert"
0117    TGETS    1   1   7  ; "are"
0118    TGETS    1   1   8  ; "equal"
0119    KSHORT   2   1
0120    TGETS    3   0   9  ; "awake"
0121    TGETS    3   3  10  ; "time"
0122    CALL     1   1   3
0123    GGET     1   0      ; "assert"
0124    TGETS    1   1   7  ; "are"
0125    TGETS    1   1   8  ; "equal"
0126    KSHORT   2   0
0127    TGETS    3   0  11  ; "sleeping"
0128    TGETS    3   3  10  ; "time"
0129    CALL     1   1   3
0130    GGET     1   0      ; "assert"
0131    TGETS    1   1   7  ; "are"
0132    TGETS    1   1   8  ; "equal"
0133    KSHORT   2   1
0134    TGETS    3   0  12  ; "discharging"
0135    TGETS    3   3  10  ; "time"
0136    CALL     1   1   3
0137    GGET     1   0      ; "assert"
0138    TGETS    1   1   7  ; "are"
0139    TGETS    1   1   8  ; "equal"
0140    KSHORT   2   1
0141    TGETS    3   0  13  ; "charging"
0142    TGETS    3   3  10  ; "time"
0143    CALL     1   1   3
0144    MOV      2   0
0145    TGETS    1   0  14  ; "onCharging"
0146    CALL     1   1   2
0147    GGET     1   0      ; "assert"
0148    TGETS    1   1  15  ; "is_true"
0149    TGETS    2   0   2  ; "was_charging"
0150    CALL     1   1   2
0151    GGET     1   0      ; "assert"
0152    TGETS    1   1   1  ; "is_false"
0153    TGETS    2   0   3  ; "was_suspending"
0154    CALL     1   1   2
0155    UGET     1   1      ; MockTime
0156    MOV      2   1
0157    TGETS    1   1   5  ; "increase"
0158    KSHORT   3   1
0159    CALL     1   1   3
0160    MOV      2   0
0161    TGETS    1   0   6  ; "accumulate"
0162    CALL     1   1   2
0163    GGET     1   0      ; "assert"
0164    TGETS    1   1   7  ; "are"
0165    TGETS    1   1   8  ; "equal"
0166    KSHORT   2   0
0167    TGETS    3   0   9  ; "awake"
0168    TGETS    3   3  10  ; "time"
0169    CALL     1   1   3
0170    GGET     1   0      ; "assert"
0171    TGETS    1   1   7  ; "are"
0172    TGETS    1   1   8  ; "equal"
0173    KSHORT   2   0
0174    TGETS    3   0  11  ; "sleeping"
0175    TGETS    3   3  10  ; "time"
0176    CALL     1   1   3
0177    GGET     1   0      ; "assert"
0178    TGETS    1   1   7  ; "are"
0179    TGETS    1   1   8  ; "equal"
0180    KSHORT   2   0
0181    TGETS    3   0  12  ; "discharging"
0182    TGETS    3   3  10  ; "time"
0183    CALL     1   1   3
0184    GGET     1   0      ; "assert"
0185    TGETS    1   1   7  ; "are"
0186    TGETS    1   1   8  ; "equal"
0187    KSHORT   2   1
0188    TGETS    3   0  13  ; "charging"
0189    TGETS    3   3  10  ; "time"
0190    CALL     1   1   3
0191    RET0     0   1

-- BYTECODE -- batterystat_spec.lua:72-113
0001    UGET     0   0      ; stat
0002    CALL     0   2   1
0003    GGET     1   0      ; "assert"
0004    TGETS    1   1   1  ; "is_false"
0005    TGETS    2   0   2  ; "was_charging"
0006    CALL     1   1   2
0007    GGET     1   0      ; "assert"
0008    TGETS    1   1   1  ; "is_false"
0009    TGETS    2   0   3  ; "was_suspending"
0010    CALL     1   1   2
0011    MOV      2   0
0012    TGETS    1   0   4  ; "resetAll"
0013    CALL     1   1   2
0014    UGET     1   1      ; MockTime
0015    MOV      2   1
0016    TGETS    1   1   5  ; "increase"
0017    KSHORT   3   1
0018    CALL     1   1   3
0019    MOV      2   0
0020    TGETS    1   0   6  ; "accumulate"
0021    CALL     1   1   2
0022    GGET     1   0      ; "assert"
0023    TGETS    1   1   7  ; "are"
0024    TGETS    1   1   8  ; "equal"
0025    KSHORT   2   1
0026    TGETS    3   0   9  ; "awake"
0027    TGETS    3   3  10  ; "time"
0028    CALL     1   1   3
0029    GGET     1   0      ; "assert"
0030    TGETS    1   1   7  ; "are"
0031    TGETS    1   1   8  ; "equal"
0032    KSHORT   2   0
0033    TGETS    3   0  11  ; "sleeping"
0034    TGETS    3   3  10  ; "time"
0035    CALL     1   1   3
0036    GGET     1   0      ; "assert"
0037    TGETS    1   1   7  ; "are"
0038    TGETS    1   1   8  ; "equal"
0039    KSHORT   2   1
0040    TGETS    3   0  12  ; "discharging"
0041    TGETS    3   3  10  ; "time"
0042    CALL     1   1   3
0043    GGET     1   0      ; "assert"
0044    TGETS    1   1   7  ; "are"
0045    TGETS    1   1   8  ; "equal"
0046    KSHORT   2   0
0047    TGETS    3   0  13  ; "charging"
0048    TGETS    3   3  10  ; "time"
0049    CALL     1   1   3
0050    MOV      2   0
0051    TGETS    1   0  14  ; "onSuspend"
0052    CALL     1   1   2
0053    GGET     1   0      ; "assert"
0054    TGETS    1   1   1  ; "is_false"
0055    TGETS    2   0   2  ; "was_charging"
0056    CALL     1   1   2
0057    GGET     1   0      ; "assert"
0058    TGETS    1   1  15  ; "is_true"
0059    TGETS    2   0   3  ; "was_suspending"
0060    CALL     1   1   2
0061    UGET     1   1      ; MockTime
0062    MOV      2   1
0063    TGETS    1   1   5  ; "increase"
0064    KSHORT   3   1
0065    CALL     1   1   3
0066    MOV      2   0
0067    TGETS    1   0   6  ; "accumulate"
0068    CALL     1   1   2
0069    GGET     1   0      ; "assert"
0070    TGETS    1   1   7  ; "are"
0071    TGETS    1   1   8  ; "equal"
0072    KSHORT   2   1
0073    TGETS    3   0   9  ; "awake"
0074    TGETS    3   3  10  ; "time"
0075    CALL     1   1   3
0076    GGET     1   0      ; "assert"
0077    TGETS    1   1   7  ; "are"
0078    TGETS    1   1   8  ; "equal"
0079    KSHORT   2   1
0080    TGETS    3   0  11  ; "sleeping"
0081    TGETS    3   3  10  ; "time"
0082    CALL     1   1   3
0083    GGET     1   0      ; "assert"
0084    TGETS    1   1   7  ; "are"
0085    TGETS    1   1   8  ; "equal"
0086    KSHORT   2   2
0087    TGETS    3   0  12  ; "discharging"
0088    TGETS    3   3  10  ; "time"
0089    CALL     1   1   3
0090    GGET     1   0      ; "assert"
0091    TGETS    1   1   7  ; "are"
0092    TGETS    1   1   8  ; "equal"
0093    KSHORT   2   0
0094    TGETS    3   0  13  ; "charging"
0095    TGETS    3   3  10  ; "time"
0096    CALL     1   1   3
0097    MOV      2   0
0098    TGETS    1   0  16  ; "onResume"
0099    CALL     1   1   2
0100    GGET     1   0      ; "assert"
0101    TGETS    1   1   1  ; "is_false"
0102    TGETS    2   0   2  ; "was_charging"
0103    CALL     1   1   2
0104    GGET     1   0      ; "assert"
0105    TGETS    1   1   1  ; "is_false"
0106    TGETS    2   0   3  ; "was_suspending"
0107    CALL     1   1   2
0108    UGET     1   1      ; MockTime
0109    MOV      2   1
0110    TGETS    1   1   5  ; "increase"
0111    KSHORT   3   1
0112    CALL     1   1   3
0113    MOV      2   0
0114    TGETS    1   0   6  ; "accumulate"
0115    CALL     1   1   2
0116    GGET     1   0      ; "assert"
0117    TGETS    1   1   7  ; "are"
0118    TGETS    1   1   8  ; "equal"
0119    KSHORT   2   2
0120    TGETS    3   0   9  ; "awake"
0121    TGETS    3   3  10  ; "time"
0122    CALL     1   1   3
0123    GGET     1   0      ; "assert"
0124    TGETS    1   1   7  ; "are"
0125    TGETS    1   1   8  ; "equal"
0126    KSHORT   2   1
0127    TGETS    3   0  11  ; "sleeping"
0128    TGETS    3   3  10  ; "time"
0129    CALL     1   1   3
0130    GGET     1   0      ; "assert"
0131    TGETS    1   1   7  ; "are"
0132    TGETS    1   1   8  ; "equal"
0133    KSHORT   2   3
0134    TGETS    3   0  12  ; "discharging"
0135    TGETS    3   3  10  ; "time"
0136    CALL     1   1   3
0137    GGET     1   0      ; "assert"
0138    TGETS    1   1   7  ; "are"
0139    TGETS    1   1   8  ; "equal"
0140    KSHORT   2   0
0141    TGETS    3   0  13  ; "charging"
0142    TGETS    3   3  10  ; "time"
0143    CALL     1   1   3
0144    MOV      2   0
0145    TGETS    1   0  14  ; "onSuspend"
0146    CALL     1   1   2
0147    GGET     1   0      ; "assert"
0148    TGETS    1   1   1  ; "is_false"
0149    TGETS    2   0   2  ; "was_charging"
0150    CALL     1   1   2
0151    GGET     1   0      ; "assert"
0152    TGETS    1   1  15  ; "is_true"
0153    TGETS    2   0   3  ; "was_suspending"
0154    CALL     1   1   2
0155    UGET     1   1      ; MockTime
0156    MOV      2   1
0157    TGETS    1   1   5  ; "increase"
0158    KSHORT   3   1
0159    CALL     1   1   3
0160    MOV      2   0
0161    TGETS    1   0   6  ; "accumulate"
0162    CALL     1   1   2
0163    GGET     1   0      ; "assert"
0164    TGETS    1   1   7  ; "are"
0165    TGETS    1   1   8  ; "equal"
0166    KSHORT   2   2
0167    TGETS    3   0   9  ; "awake"
0168    TGETS    3   3  10  ; "time"
0169    CALL     1   1   3
0170    GGET     1   0      ; "assert"
0171    TGETS    1   1   7  ; "are"
0172    TGETS    1   1   8  ; "equal"
0173    KSHORT   2   2
0174    TGETS    3   0  11  ; "sleeping"
0175    TGETS    3   3  10  ; "time"
0176    CALL     1   1   3
0177    GGET     1   0      ; "assert"
0178    TGETS    1   1   7  ; "are"
0179    TGETS    1   1   8  ; "equal"
0180    KSHORT   2   4
0181    TGETS    3   0  12  ; "discharging"
0182    TGETS    3   3  10  ; "time"
0183    CALL     1   1   3
0184    GGET     1   0      ; "assert"
0185    TGETS    1   1   7  ; "are"
0186    TGETS    1   1   8  ; "equal"
0187    KSHORT   2   0
0188    TGETS    3   0  13  ; "charging"
0189    TGETS    3   3  10  ; "time"
0190    CALL     1   1   3
0191    RET0     0   1

-- BYTECODE -- batterystat_spec.lua:115-147
0001    UGET     0   0      ; stat
0002    CALL     0   2   1
0003    GGET     1   0      ; "assert"
0004    TGETS    1   1   1  ; "is_false"
0005    TGETS    2   0   2  ; "was_charging"
0006    CALL     1   1   2
0007    GGET     1   0      ; "assert"
0008    TGETS    1   1   1  ; "is_false"
0009    TGETS    2   0   3  ; "was_suspending"
0010    CALL     1   1   2
0011    MOV      2   0
0012    TGETS    1   0   4  ; "resetAll"
0013    CALL     1   1   2
0014    UGET     1   1      ; MockTime
0015    MOV      2   1
0016    TGETS    1   1   5  ; "increase"
0017    KSHORT   3   1
0018    CALL     1   1   3
0019    MOV      2   0
0020    TGETS    1   0   6  ; "accumulate"
0021    CALL     1   1   2
0022    GGET     1   0      ; "assert"
0023    TGETS    1   1   7  ; "are"
0024    TGETS    1   1   8  ; "equal"
0025    KSHORT   2   1
0026    TGETS    3   0   9  ; "awake"
0027    TGETS    3   3  10  ; "time"
0028    CALL     1   1   3
0029    GGET     1   0      ; "assert"
0030    TGETS    1   1   7  ; "are"
0031    TGETS    1   1   8  ; "equal"
0032    KSHORT   2   0
0033    TGETS    3   0  11  ; "sleeping"
0034    TGETS    3   3  10  ; "time"
0035    CALL     1   1   3
0036    GGET     1   0      ; "assert"
0037    TGETS    1   1   7  ; "are"
0038    TGETS    1   1   8  ; "equal"
0039    KSHORT   2   1
0040    TGETS    3   0  12  ; "discharging"
0041    TGETS    3   3  10  ; "time"
0042    CALL     1   1   3
0043    GGET     1   0      ; "assert"
0044    TGETS    1   1   7  ; "are"
0045    TGETS    1   1   8  ; "equal"
0046    KSHORT   2   0
0047    TGETS    3   0  13  ; "charging"
0048    TGETS    3   3  10  ; "time"
0049    CALL     1   1   3
0050    MOV      2   0
0051    TGETS    1   0  14  ; "onCharging"
0052    CALL     1   1   2
0053    GGET     1   0      ; "assert"
0054    TGETS    1   1  15  ; "is_true"
0055    TGETS    2   0   2  ; "was_charging"
0056    CALL     1   1   2
0057    GGET     1   0      ; "assert"
0058    TGETS    1   1   1  ; "is_false"
0059    TGETS    2   0   3  ; "was_suspending"
0060    CALL     1   1   2
0061    UGET     1   1      ; MockTime
0062    MOV      2   1
0063    TGETS    1   1   5  ; "increase"
0064    KSHORT   3   1
0065    CALL     1   1   3
0066    MOV      2   0
0067    TGETS    1   0   6  ; "accumulate"
0068    CALL     1   1   2
0069    GGET     1   0      ; "assert"
0070    TGETS    1   1   7  ; "are"
0071    TGETS    1   1   8  ; "equal"
0072    KSHORT   2   0
0073    TGETS    3   0   9  ; "awake"
0074    TGETS    3   3  10  ; "time"
0075    CALL     1   1   3
0076    GGET     1   0      ; "assert"
0077    TGETS    1   1   7  ; "are"
0078    TGETS    1   1   8  ; "equal"
0079    KSHORT   2   0
0080    TGETS    3   0  11  ; "sleeping"
0081    TGETS    3   3  10  ; "time"
0082    CALL     1   1   3
0083    GGET     1   0      ; "assert"
0084    TGETS    1   1   7  ; "are"
0085    TGETS    1   1   8  ; "equal"
0086    KSHORT   2   0
0087    TGETS    3   0  12  ; "discharging"
0088    TGETS    3   3  10  ; "time"
0089    CALL     1   1   3
0090    GGET     1   0      ; "assert"
0091    TGETS    1   1   7  ; "are"
0092    TGETS    1   1   8  ; "equal"
0093    KSHORT   2   1
0094    TGETS    3   0  13  ; "charging"
0095    TGETS    3   3  10  ; "time"
0096    CALL     1   1   3
0097    MOV      2   0
0098    TGETS    1   0  14  ; "onCharging"
0099    CALL     1   1   2
0100    GGET     1   0      ; "assert"
0101    TGETS    1   1  15  ; "is_true"
0102    TGETS    2   0   2  ; "was_charging"
0103    CALL     1   1   2
0104    GGET     1   0      ; "assert"
0105    TGETS    1   1   1  ; "is_false"
0106    TGETS    2   0   3  ; "was_suspending"
0107    CALL     1   1   2
0108    UGET     1   1      ; MockTime
0109    MOV      2   1
0110    TGETS    1   1   5  ; "increase"
0111    KSHORT   3   1
0112    CALL     1   1   3
0113    MOV      2   0
0114    TGETS    1   0   6  ; "accumulate"
0115    CALL     1   1   2
0116    GGET     1   0      ; "assert"
0117    TGETS    1   1   7  ; "are"
0118    TGETS    1   1   8  ; "equal"
0119    KSHORT   2   0
0120    TGETS    3   0   9  ; "awake"
0121    TGETS    3   3  10  ; "time"
0122    CALL     1   1   3
0123    GGET     1   0      ; "assert"
0124    TGETS    1   1   7  ; "are"
0125    TGETS    1   1   8  ; "equal"
0126    KSHORT   2   0
0127    TGETS    3   0  11  ; "sleeping"
0128    TGETS    3   3  10  ; "time"
0129    CALL     1   1   3
0130    GGET     1   0      ; "assert"
0131    TGETS    1   1   7  ; "are"
0132    TGETS    1   1   8  ; "equal"
0133    KSHORT   2   0
0134    TGETS    3   0  12  ; "discharging"
0135    TGETS    3   3  10  ; "time"
0136    CALL     1   1   3
0137    GGET     1   0      ; "assert"
0138    TGETS    1   1   7  ; "are"
0139    TGETS    1   1   8  ; "equal"
0140    KSHORT   2   2
0141    TGETS    3   0  13  ; "charging"
0142    TGETS    3   3  10  ; "time"
0143    CALL     1   1   3
0144    RET0     0   1

-- BYTECODE -- batterystat_spec.lua:149-190
0001    UGET     0   0      ; stat
0002    CALL     0   2   1
0003    GGET     1   0      ; "assert"
0004    TGETS    1   1   1  ; "is_false"
0005    TGETS    2   0   2  ; "was_charging"
0006    CALL     1   1   2
0007    GGET     1   0      ; "assert"
0008    TGETS    1   1   1  ; "is_false"
0009    TGETS    2   0   3  ; "was_suspending"
0010    CALL     1   1   2
0011    MOV      2   0
0012    TGETS    1   0   4  ; "resetAll"
0013    CALL     1   1   2
0014    UGET     1   1      ; MockTime
0015    MOV      2   1
0016    TGETS    1   1   5  ; "increase"
0017    KSHORT   3   1
0018    CALL     1   1   3
0019    MOV      2   0
0020    TGETS    1   0   6  ; "accumulate"
0021    CALL     1   1   2
0022    GGET     1   0      ; "assert"
0023    TGETS    1   1   7  ; "are"
0024    TGETS    1   1   8  ; "equal"
0025    KSHORT   2   1
0026    TGETS    3   0   9  ; "awake"
0027    TGETS    3   3  10  ; "time"
0028    CALL     1   1   3
0029    GGET     1   0      ; "assert"
0030    TGETS    1   1   7  ; "are"
0031    TGETS    1   1   8  ; "equal"
0032    KSHORT   2   0
0033    TGETS    3   0  11  ; "sleeping"
0034    TGETS    3   3  10  ; "time"
0035    CALL     1   1   3
0036    GGET     1   0      ; "assert"
0037    TGETS    1   1   7  ; "are"
0038    TGETS    1   1   8  ; "equal"
0039    KSHORT   2   1
0040    TGETS    3   0  12  ; "discharging"
0041    TGETS    3   3  10  ; "time"
0042    CALL     1   1   3
0043    GGET     1   0      ; "assert"
0044    TGETS    1   1   7  ; "are"
0045    TGETS    1   1   8  ; "equal"
0046    KSHORT   2   0
0047    TGETS    3   0  13  ; "charging"
0048    TGETS    3   3  10  ; "time"
0049    CALL     1   1   3
0050    MOV      2   0
0051    TGETS    1   0  14  ; "onSuspend"
0052    CALL     1   1   2
0053    GGET     1   0      ; "assert"
0054    TGETS    1   1   1  ; "is_false"
0055    TGETS    2   0   2  ; "was_charging"
0056    CALL     1   1   2
0057    GGET     1   0      ; "assert"
0058    TGETS    1   1  15  ; "is_true"
0059    TGETS    2   0   3  ; "was_suspending"
0060    CALL     1   1   2
0061    UGET     1   1      ; MockTime
0062    MOV      2   1
0063    TGETS    1   1   5  ; "increase"
0064    KSHORT   3   1
0065    CALL     1   1   3
0066    MOV      2   0
0067    TGETS    1   0   6  ; "accumulate"
0068    CALL     1   1   2
0069    GGET     1   0      ; "assert"
0070    TGETS    1   1   7  ; "are"
0071    TGETS    1   1   8  ; "equal"
0072    KSHORT   2   1
0073    TGETS    3   0   9  ; "awake"
0074    TGETS    3   3  10  ; "time"
0075    CALL     1   1   3
0076    GGET     1   0      ; "assert"
0077    TGETS    1   1   7  ; "are"
0078    TGETS    1   1   8  ; "equal"
0079    KSHORT   2   1
0080    TGETS    3   0  11  ; "sleeping"
0081    TGETS    3   3  10  ; "time"
0082    CALL     1   1   3
0083    GGET     1   0      ; "assert"
0084    TGETS    1   1   7  ; "are"
0085    TGETS    1   1   8  ; "equal"
0086    KSHORT   2   2
0087    TGETS    3   0  12  ; "discharging"
0088    TGETS    3   3  10  ; "time"
0089    CALL     1   1   3
0090    GGET     1   0      ; "assert"
0091    TGETS    1   1   7  ; "are"
0092    TGETS    1   1   8  ; "equal"
0093    KSHORT   2   0
0094    TGETS    3   0  13  ; "charging"
0095    TGETS    3   3  10  ; "time"
0096    CALL     1   1   3
0097    MOV      2   0
0098    TGETS    1   0  14  ; "onSuspend"
0099    CALL     1   1   2
0100    GGET     1   0      ; "assert"
0101    TGETS    1   1   1  ; "is_false"
0102    TGETS    2   0   2  ; "was_charging"
0103    CALL     1   1   2
0104    GGET     1   0      ; "assert"
0105    TGETS    1   1  15  ; "is_true"
0106    TGETS    2   0   3  ; "was_suspending"
0107    CALL     1   1   2
0108    UGET     1   1      ; MockTime
0109    MOV      2   1
0110    TGETS    1   1   5  ; "increase"
0111    KSHORT   3   1
0112    CALL     1   1   3
0113    MOV      2   0
0114    TGETS    1   0   6  ; "accumulate"
0115    CALL     1   1   2
0116    GGET     1   0      ; "assert"
0117    TGETS    1   1   7  ; "are"
0118    TGETS    1   1   8  ; "equal"
0119    KSHORT   2   1
0120    TGETS    3   0   9  ; "awake"
0121    TGETS    3   3  10  ; "time"
0122    CALL     1   1   3
0123    GGET     1   0      ; "assert"
0124    TGETS    1   1   7  ; "are"
0125    TGETS    1   1   8  ; "equal"
0126    KSHORT   2   2
0127    TGETS    3   0  11  ; "sleeping"
0128    TGETS    3   3  10  ; "time"
0129    CALL     1   1   3
0130    GGET     1   0      ; "assert"
0131    TGETS    1   1   7  ; "are"
0132    TGETS    1   1   8  ; "equal"
0133    KSHORT   2   3
0134    TGETS    3   0  12  ; "discharging"
0135    TGETS    3   3  10  ; "time"
0136    CALL     1   1   3
0137    GGET     1   0      ; "assert"
0138    TGETS    1   1   7  ; "are"
0139    TGETS    1   1   8  ; "equal"
0140    KSHORT   2   0
0141    TGETS    3   0  13  ; "charging"
0142    TGETS    3   3  10  ; "time"
0143    CALL     1   1   3
0144    MOV      2   0
0145    TGETS    1   0  14  ; "onSuspend"
0146    CALL     1   1   2
0147    GGET     1   0      ; "assert"
0148    TGETS    1   1   1  ; "is_false"
0149    TGETS    2   0   2  ; "was_charging"
0150    CALL     1   1   2
0151    GGET     1   0      ; "assert"
0152    TGETS    1   1  15  ; "is_true"
0153    TGETS    2   0   3  ; "was_suspending"
0154    CALL     1   1   2
0155    UGET     1   1      ; MockTime
0156    MOV      2   1
0157    TGETS    1   1   5  ; "increase"
0158    KSHORT   3   1
0159    CALL     1   1   3
0160    MOV      2   0
0161    TGETS    1   0   6  ; "accumulate"
0162    CALL     1   1   2
0163    GGET     1   0      ; "assert"
0164    TGETS    1   1   7  ; "are"
0165    TGETS    1   1   8  ; "equal"
0166    KSHORT   2   1
0167    TGETS    3   0   9  ; "awake"
0168    TGETS    3   3  10  ; "time"
0169    CALL     1   1   3
0170    GGET     1   0      ; "assert"
0171    TGETS    1   1   7  ; "are"
0172    TGETS    1   1   8  ; "equal"
0173    KSHORT   2   3
0174    TGETS    3   0  11  ; "sleeping"
0175    TGETS    3   3  10  ; "time"
0176    CALL     1   1   3
0177    GGET     1   0      ; "assert"
0178    TGETS    1   1   7  ; "are"
0179    TGETS    1   1   8  ; "equal"
0180    KSHORT   2   4
0181    TGETS    3   0  12  ; "discharging"
0182    TGETS    3   3  10  ; "time"
0183    CALL     1   1   3
0184    GGET     1   0      ; "assert"
0185    TGETS    1   1   7  ; "are"
0186    TGETS    1   1   8  ; "equal"
0187    KSHORT   2   0
0188    TGETS    3   0  13  ; "charging"
0189    TGETS    3   3  10  ; "time"
0190    CALL     1   1   3
0191    RET0     0   1

-- BYTECODE -- batterystat_spec.lua:1-191
0001    KNIL     0   1
0002    FNEW     2   0      ; batterystat_spec.lua:4
0003    GGET     3   1      ; "setup"
0004    FNEW     4   2      ; batterystat_spec.lua:8
0005    CALL     3   1   2
0006    GGET     3   3      ; "teardown"
0007    FNEW     4   4      ; batterystat_spec.lua:16
0008    CALL     3   1   2
0009    GGET     3   5      ; "before_each"
0010    FNEW     4   6      ; batterystat_spec.lua:22
0011    CALL     3   1   2
0012    GGET     3   7      ; "it"
0013    KSTR     4   8      ; "should record charging time"
0014    FNEW     5   9      ; batterystat_spec.lua:26
0015    CALL     3   1   3
0016    GGET     3   7      ; "it"
0017    KSTR     4  10      ; "should record suspending time"
0018    FNEW     5  11      ; batterystat_spec.lua:72
0019    CALL     3   1   3
0020    GGET     3   7      ; "it"
0021    KSTR     4  12      ; "should not swap the state when several c"~
0022    FNEW     5  13      ; batterystat_spec.lua:115
0023    CALL     3   1   3
0024    GGET     3   7      ; "it"
0025    KSTR     4  14      ; "should not swap the state when several s"~
0026    FNEW     5  15      ; batterystat_spec.lua:149
0027    CALL     3   1   3
0028    UCLO     0 => 0029
0029 => RET0     0   1

-- BYTECODE -- batterystat_spec.lua:0-192
0001    GGET     0   0      ; "describe"
0002    KSTR     1   1      ; "BatteryState plugin tests #nocov"
0003    FNEW     2   2      ; batterystat_spec.lua:1
0004    CALL     0   1   3
0005    RET0     0   1

