
main <./frontend/ui/widget/bboxwidget.lua:0,0> (77 instructions, 308 bytes at 0x7fef42c068d0)
0+ params, 13 slots, 0 upvalues, 9 locals, 33 constants, 14 functions
	1	[5]	GETGLOBAL	0 -1	; require
	2	[5]	LOADK    	1 -2	; "ui/widget/container/inputcontainer"
	3	[5]	CALL     	0 2 2
	4	[6]	GETGLOBAL	1 -1	; require
	5	[6]	LOADK    	2 -3	; "device"
	6	[6]	CALL     	1 2 2
	7	[7]	GETGLOBAL	2 -1	; require
	8	[7]	LOADK    	3 -4	; "ui/event"
	9	[7]	CALL     	2 2 2
	10	[8]	GETGLOBAL	3 -1	; require
	11	[8]	LOADK    	4 -5	; "ui/geometry"
	12	[8]	CALL     	3 2 2
	13	[9]	GETGLOBAL	4 -1	; require
	14	[9]	LOADK    	5 -6	; "ui/gesturerange"
	15	[9]	CALL     	4 2 2
	16	[10]	GETGLOBAL	5 -1	; require
	17	[10]	LOADK    	6 -7	; "optmath"
	18	[10]	CALL     	5 2 2
	19	[11]	GETGLOBAL	6 -1	; require
	20	[11]	LOADK    	7 -8	; "ui/size"
	21	[11]	CALL     	6 2 2
	22	[12]	GETGLOBAL	7 -1	; require
	23	[12]	LOADK    	8 -9	; "ui/uimanager"
	24	[12]	CALL     	7 2 2
	25	[14]	SELF     	8 0 -10	; "new"
	26	[14]	NEWTABLE 	10 0 5
	27	[15]	SETTABLE 	10 -11 -12	; "page_bbox" nil
	28	[16]	SETTABLE 	10 -13 -12	; "screen_bbox" nil
	29	[17]	GETTABLE 	11 6 -15	; "line"
	30	[17]	GETTABLE 	11 11 -16	; "thick"
	31	[17]	SETTABLE 	10 -14 11	; "linesize" -
	32	[18]	SETTABLE 	10 -17 -18	; "fine_factor" 10
	33	[19]	SELF     	11 3 -10	; "new"
	34	[19]	CALL     	11 2 2
	35	[19]	SETTABLE 	10 -19 11	; "dimen" -
	36	[14]	CALL     	8 3 2
	37	[56]	CLOSURE  	9 0	; 0x7fef42c070e0
	38	[56]	MOVE     	0 1
	39	[56]	MOVE     	0 4
	40	[22]	SETTABLE 	8 -20 9	; "init" -
	41	[60]	CLOSURE  	9 1	; 0x7fef42c07490
	42	[58]	SETTABLE 	8 -21 9	; "getSize" -
	43	[77]	CLOSURE  	9 2	; 0x7fef42c07720
	44	[62]	SETTABLE 	8 -22 9	; "paintTo" -
	45	[89]	CLOSURE  	9 3	; 0x7fef42c08210
	46	[89]	MOVE     	0 5
	47	[80]	SETTABLE 	8 -23 9	; "getScreenBBox" -
	48	[101]	CLOSURE  	9 4	; 0x7fef42c08ac0
	49	[101]	MOVE     	0 5
	50	[92]	SETTABLE 	8 -24 9	; "getPageBBox" -
	51	[108]	CLOSURE  	9 5	; 0x7fef42c084b0
	52	[108]	MOVE     	0 3
	53	[103]	SETTABLE 	8 -25 9	; "inPageArea" -
	54	[198]	CLOSURE  	9 6	; 0x7fef42c09230
	55	[198]	MOVE     	0 3
	56	[198]	MOVE     	0 5
	57	[198]	MOVE     	0 7
	58	[110]	SETTABLE 	8 -26 9	; "adjustScreenBBox" -
	59	[202]	CLOSURE  	9 7	; 0x7fef42c09570
	60	[200]	SETTABLE 	8 -27 9	; "getModifiedPageBBox" -
	61	[207]	CLOSURE  	9 8	; 0x7fef42c09fa0
	62	[204]	SETTABLE 	8 -28 9	; "onTapAdjust" -
	63	[212]	CLOSURE  	9 9	; 0x7fef42c0a490
	64	[209]	SETTABLE 	8 -29 9	; "onSwipeAdjust" -
	65	[220]	CLOSURE  	9 10	; 0x7fef42c0a5a0
	66	[214]	SETTABLE 	8 -30 9	; "onHoldAdjust" -
	67	[227]	CLOSURE  	9 11	; 0x7fef42c07160
	68	[227]	MOVE     	0 2
	69	[222]	SETTABLE 	8 -31 9	; "onConfirmAdjust" -
	70	[231]	CLOSURE  	9 12	; 0x7fef42c0aeb0
	71	[231]	MOVE     	0 2
	72	[229]	SETTABLE 	8 -32 9	; "onClose" -
	73	[235]	CLOSURE  	9 13	; 0x7fef42c0b280
	74	[235]	MOVE     	0 2
	75	[233]	SETTABLE 	8 -33 9	; "onSelect" -
	76	[238]	RETURN   	8 2
	77	[238]	RETURN   	0 1

function <./frontend/ui/widget/bboxwidget.lua:22,56> (80 instructions, 320 bytes at 0x7fef42c070e0)
1 param, 7 slots, 2 upvalues, 1 local, 29 constants, 0 functions
	1	[23]	GETTABLE 	1 0 -2	; "document"
	2	[23]	SELF     	1 1 -3	; "getPageBBox"
	3	[23]	GETTABLE 	3 0 -4	; "view"
	4	[23]	GETTABLE 	3 3 -5	; "state"
	5	[23]	GETTABLE 	3 3 -6	; "page"
	6	[23]	CALL     	1 3 2
	7	[23]	SETTABLE 	0 -1 1	; "page_bbox" -
	8	[24]	GETUPVAL 	1 0	; Device
	9	[24]	SELF     	1 1 -7	; "isTouchDevice"
	10	[24]	CALL     	1 2 2
	11	[24]	TEST     	1 0 0
	12	[24]	JMP      	46	; to 59
	13	[25]	NEWTABLE 	1 0 4
	14	[26]	NEWTABLE 	2 0 0
	15	[27]	GETUPVAL 	3 1	; GestureRange
	16	[27]	SELF     	3 3 -10	; "new"
	17	[27]	NEWTABLE 	5 0 2
	18	[28]	SETTABLE 	5 -11 -12	; "ges" "tap"
	19	[29]	GETTABLE 	6 0 -4	; "view"
	20	[29]	GETTABLE 	6 6 -14	; "dimen"
	21	[29]	SETTABLE 	5 -13 6	; "range" -
	22	[27]	CALL     	3 3 0
	23	[31]	SETLIST  	2 0 1	; 1
	24	[31]	SETTABLE 	1 -9 2	; "TapAdjust" -
	25	[32]	NEWTABLE 	2 0 0
	26	[33]	GETUPVAL 	3 1	; GestureRange
	27	[33]	SELF     	3 3 -10	; "new"
	28	[33]	NEWTABLE 	5 0 2
	29	[34]	SETTABLE 	5 -11 -16	; "ges" "swipe"
	30	[35]	GETTABLE 	6 0 -4	; "view"
	31	[35]	GETTABLE 	6 6 -14	; "dimen"
	32	[35]	SETTABLE 	5 -13 6	; "range" -
	33	[33]	CALL     	3 3 0
	34	[37]	SETLIST  	2 0 1	; 1
	35	[37]	SETTABLE 	1 -15 2	; "SwipeAdjust" -
	36	[38]	NEWTABLE 	2 0 0
	37	[39]	GETUPVAL 	3 1	; GestureRange
	38	[39]	SELF     	3 3 -10	; "new"
	39	[39]	NEWTABLE 	5 0 2
	40	[40]	SETTABLE 	5 -11 -18	; "ges" "hold"
	41	[41]	GETTABLE 	6 0 -4	; "view"
	42	[41]	GETTABLE 	6 6 -14	; "dimen"
	43	[41]	SETTABLE 	5 -13 6	; "range" -
	44	[39]	CALL     	3 3 0
	45	[43]	SETLIST  	2 0 1	; 1
	46	[43]	SETTABLE 	1 -17 2	; "HoldAdjust" -
	47	[44]	NEWTABLE 	2 0 0
	48	[45]	GETUPVAL 	3 1	; GestureRange
	49	[45]	SELF     	3 3 -10	; "new"
	50	[45]	NEWTABLE 	5 0 2
	51	[46]	SETTABLE 	5 -11 -20	; "ges" "double_tap"
	52	[47]	GETTABLE 	6 0 -4	; "view"
	53	[47]	GETTABLE 	6 6 -14	; "dimen"
	54	[47]	SETTABLE 	5 -13 6	; "range" -
	55	[45]	CALL     	3 3 0
	56	[49]	SETLIST  	2 0 1	; 1
	57	[49]	SETTABLE 	1 -19 2	; "ConfirmAdjust" -
	58	[50]	SETTABLE 	0 -8 1	; "ges_events" -
	59	[52]	GETUPVAL 	1 0	; Device
	60	[52]	SELF     	1 1 -21	; "hasKeys"
	61	[52]	CALL     	1 2 2
	62	[52]	TEST     	1 0 0
	63	[52]	JMP      	16	; to 80
	64	[53]	GETTABLE 	1 0 -22	; "key_events"
	65	[53]	NEWTABLE 	2 1 1
	66	[53]	NEWTABLE 	3 1 0
	67	[53]	LOADK    	4 -24	; "Back"
	68	[53]	SETLIST  	3 1 1	; 1
	69	[53]	SETTABLE 	2 -25 -26	; "doc" "close windows"
	70	[53]	SETLIST  	2 1 1	; 1
	71	[53]	SETTABLE 	1 -23 2	; "Close" -
	72	[54]	GETTABLE 	1 0 -22	; "key_events"
	73	[54]	NEWTABLE 	2 1 1
	74	[54]	NEWTABLE 	3 1 0
	75	[54]	LOADK    	4 -28	; "Press"
	76	[54]	SETLIST  	3 1 1	; 1
	77	[54]	SETTABLE 	2 -25 -29	; "doc" "confirm adjust"
	78	[54]	SETLIST  	2 1 1	; 1
	79	[54]	SETTABLE 	1 -27 2	; "Select" -
	80	[56]	RETURN   	0 1

function <./frontend/ui/widget/bboxwidget.lua:58,60> (4 instructions, 16 bytes at 0x7fef42c07490)
1 param, 2 slots, 0 upvalues, 1 local, 2 constants, 0 functions
	1	[59]	GETTABLE 	1 0 -1	; "view"
	2	[59]	GETTABLE 	1 1 -2	; "dimen"
	3	[59]	RETURN   	1 2
	4	[60]	RETURN   	0 1

function <./frontend/ui/widget/bboxwidget.lua:62,77> (61 instructions, 244 bytes at 0x7fef42c07720)
4 params, 12 slots, 0 upvalues, 5 locals, 14 constants, 0 functions
	1	[63]	GETTABLE 	4 0 -2	; "view"
	2	[63]	GETTABLE 	4 4 -1	; "dimen"
	3	[63]	SELF     	4 4 -3	; "copy"
	4	[63]	CALL     	4 2 2
	5	[63]	SETTABLE 	0 -1 4	; "dimen" -
	6	[64]	GETTABLE 	4 0 -1	; "dimen"
	7	[64]	GETTABLE 	5 0 -1	; "dimen"
	8	[64]	MOVE     	6 2
	9	[64]	SETTABLE 	5 -5 3	; "y" -
	10	[64]	SETTABLE 	4 -4 6	; "x" -
	11	[67]	GETTABLE 	4 0 -6	; "screen_bbox"
	12	[67]	TEST     	4 0 1
	13	[67]	JMP      	3	; to 17
	14	[67]	SELF     	4 0 -7	; "getScreenBBox"
	15	[67]	GETTABLE 	6 0 -8	; "page_bbox"
	16	[67]	CALL     	4 3 2
	17	[67]	SETTABLE 	0 -6 4	; "screen_bbox" -
	18	[68]	GETTABLE 	4 0 -6	; "screen_bbox"
	19	[70]	SELF     	5 1 -9	; "invertRect"
	20	[70]	GETTABLE 	7 4 -10	; "x0"
	21	[70]	GETTABLE 	8 0 -11	; "linesize"
	22	[70]	ADD      	7 7 8
	23	[70]	GETTABLE 	8 4 -12	; "y0"
	24	[70]	GETTABLE 	9 4 -13	; "x1"
	25	[70]	GETTABLE 	10 4 -10	; "x0"
	26	[70]	SUB      	9 9 10
	27	[70]	GETTABLE 	10 0 -11	; "linesize"
	28	[70]	CALL     	5 6 1
	29	[72]	SELF     	5 1 -9	; "invertRect"
	30	[72]	GETTABLE 	7 4 -10	; "x0"
	31	[72]	GETTABLE 	8 0 -11	; "linesize"
	32	[72]	ADD      	7 7 8
	33	[72]	GETTABLE 	8 4 -14	; "y1"
	34	[72]	GETTABLE 	9 4 -13	; "x1"
	35	[72]	GETTABLE 	10 4 -10	; "x0"
	36	[72]	SUB      	9 9 10
	37	[72]	GETTABLE 	10 0 -11	; "linesize"
	38	[72]	SUB      	9 9 10
	39	[72]	GETTABLE 	10 0 -11	; "linesize"
	40	[72]	CALL     	5 6 1
	41	[74]	SELF     	5 1 -9	; "invertRect"
	42	[74]	GETTABLE 	7 4 -10	; "x0"
	43	[74]	GETTABLE 	8 4 -12	; "y0"
	44	[74]	GETTABLE 	9 0 -11	; "linesize"
	45	[74]	GETTABLE 	10 4 -14	; "y1"
	46	[74]	GETTABLE 	11 4 -12	; "y0"
	47	[74]	SUB      	10 10 11
	48	[74]	GETTABLE 	11 0 -11	; "linesize"
	49	[74]	ADD      	10 10 11
	50	[74]	CALL     	5 6 1
	51	[76]	SELF     	5 1 -9	; "invertRect"
	52	[76]	GETTABLE 	7 4 -13	; "x1"
	53	[76]	GETTABLE 	8 4 -12	; "y0"
	54	[76]	GETTABLE 	9 0 -11	; "linesize"
	55	[76]	ADD      	8 8 9
	56	[76]	GETTABLE 	9 0 -11	; "linesize"
	57	[76]	GETTABLE 	10 4 -14	; "y1"
	58	[76]	GETTABLE 	11 4 -12	; "y0"
	59	[76]	SUB      	10 10 11
	60	[76]	CALL     	5 6 1
	61	[77]	RETURN   	0 1

function <./frontend/ui/widget/bboxwidget.lua:80,89> (41 instructions, 164 bytes at 0x7fef42c08210)
2 params, 8 slots, 1 upvalue, 5 locals, 11 constants, 0 functions
	1	[81]	NEWTABLE 	2 0 0
	2	[82]	GETTABLE 	3 0 -1	; "view"
	3	[82]	GETTABLE 	3 3 -2	; "state"
	4	[82]	GETTABLE 	3 3 -3	; "zoom"
	5	[83]	GETTABLE 	4 0 -1	; "view"
	6	[83]	GETTABLE 	4 4 -2	; "state"
	7	[83]	GETTABLE 	4 4 -4	; "offset"
	8	[84]	GETUPVAL 	5 0	; Math
	9	[84]	GETTABLE 	5 5 -6	; "round"
	10	[84]	GETTABLE 	6 1 -5	; "x0"
	11	[84]	MUL      	6 6 3
	12	[84]	GETTABLE 	7 4 -7	; "x"
	13	[84]	ADD      	6 6 7
	14	[84]	CALL     	5 2 2
	15	[84]	SETTABLE 	2 -5 5	; "x0" -
	16	[85]	GETUPVAL 	5 0	; Math
	17	[85]	GETTABLE 	5 5 -6	; "round"
	18	[85]	GETTABLE 	6 1 -8	; "y0"
	19	[85]	MUL      	6 6 3
	20	[85]	GETTABLE 	7 4 -9	; "y"
	21	[85]	ADD      	6 6 7
	22	[85]	CALL     	5 2 2
	23	[85]	SETTABLE 	2 -8 5	; "y0" -
	24	[86]	GETUPVAL 	5 0	; Math
	25	[86]	GETTABLE 	5 5 -6	; "round"
	26	[86]	GETTABLE 	6 1 -10	; "x1"
	27	[86]	MUL      	6 6 3
	28	[86]	GETTABLE 	7 4 -7	; "x"
	29	[86]	ADD      	6 6 7
	30	[86]	CALL     	5 2 2
	31	[86]	SETTABLE 	2 -10 5	; "x1" -
	32	[87]	GETUPVAL 	5 0	; Math
	33	[87]	GETTABLE 	5 5 -6	; "round"
	34	[87]	GETTABLE 	6 1 -11	; "y1"
	35	[87]	MUL      	6 6 3
	36	[87]	GETTABLE 	7 4 -9	; "y"
	37	[87]	ADD      	6 6 7
	38	[87]	CALL     	5 2 2
	39	[87]	SETTABLE 	2 -11 5	; "y1" -
	40	[88]	RETURN   	2 2
	41	[89]	RETURN   	0 1

function <./frontend/ui/widget/bboxwidget.lua:92,101> (41 instructions, 164 bytes at 0x7fef42c08ac0)
2 params, 8 slots, 1 upvalue, 5 locals, 11 constants, 0 functions
	1	[93]	NEWTABLE 	2 0 0
	2	[94]	GETTABLE 	3 0 -1	; "view"
	3	[94]	GETTABLE 	3 3 -2	; "state"
	4	[94]	GETTABLE 	3 3 -3	; "zoom"
	5	[95]	GETTABLE 	4 0 -1	; "view"
	6	[95]	GETTABLE 	4 4 -2	; "state"
	7	[95]	GETTABLE 	4 4 -4	; "offset"
	8	[96]	GETUPVAL 	5 0	; Math
	9	[96]	GETTABLE 	5 5 -6	; "round"
	10	[96]	GETTABLE 	6 1 -5	; "x0"
	11	[96]	GETTABLE 	7 4 -7	; "x"
	12	[96]	SUB      	6 6 7
	13	[96]	DIV      	6 6 3
	14	[96]	CALL     	5 2 2
	15	[96]	SETTABLE 	2 -5 5	; "x0" -
	16	[97]	GETUPVAL 	5 0	; Math
	17	[97]	GETTABLE 	5 5 -6	; "round"
	18	[97]	GETTABLE 	6 1 -8	; "y0"
	19	[97]	GETTABLE 	7 4 -9	; "y"
	20	[97]	SUB      	6 6 7
	21	[97]	DIV      	6 6 3
	22	[97]	CALL     	5 2 2
	23	[97]	SETTABLE 	2 -8 5	; "y0" -
	24	[98]	GETUPVAL 	5 0	; Math
	25	[98]	GETTABLE 	5 5 -6	; "round"
	26	[98]	GETTABLE 	6 1 -10	; "x1"
	27	[98]	GETTABLE 	7 4 -7	; "x"
	28	[98]	SUB      	6 6 7
	29	[98]	DIV      	6 6 3
	30	[98]	CALL     	5 2 2
	31	[98]	SETTABLE 	2 -10 5	; "x1" -
	32	[99]	GETUPVAL 	5 0	; Math
	33	[99]	GETTABLE 	5 5 -6	; "round"
	34	[99]	GETTABLE 	6 1 -11	; "y1"
	35	[99]	GETTABLE 	7 4 -9	; "y"
	36	[99]	SUB      	6 6 7
	37	[99]	DIV      	6 6 3
	38	[99]	CALL     	5 2 2
	39	[99]	SETTABLE 	2 -11 5	; "y1" -
	40	[100]	RETURN   	2 2
	41	[101]	RETURN   	0 1

function <./frontend/ui/widget/bboxwidget.lua:103,108> (24 instructions, 96 bytes at 0x7fef42c084b0)
2 params, 8 slots, 1 upvalue, 5 locals, 11 constants, 0 functions
	1	[104]	GETTABLE 	2 0 -1	; "view"
	2	[104]	GETTABLE 	2 2 -2	; "state"
	3	[104]	GETTABLE 	2 2 -3	; "offset"
	4	[105]	GETTABLE 	3 0 -1	; "view"
	5	[105]	GETTABLE 	3 3 -4	; "page_area"
	6	[106]	GETUPVAL 	4 0	; Geom
	7	[106]	SELF     	4 4 -5	; "new"
	8	[106]	NEWTABLE 	6 0 4
	9	[106]	GETTABLE 	7 2 -6	; "x"
	10	[106]	SETTABLE 	6 -6 7	; "x" -
	11	[106]	GETTABLE 	7 2 -7	; "y"
	12	[106]	SETTABLE 	6 -7 7	; "y" -
	13	[106]	GETTABLE 	7 3 -8	; "h"
	14	[106]	SETTABLE 	6 -8 7	; "h" -
	15	[106]	GETTABLE 	7 3 -9	; "w"
	16	[106]	SETTABLE 	6 -9 7	; "w" -
	17	[106]	CALL     	4 3 2
	18	[107]	GETTABLE 	5 1 -10	; "pos"
	19	[107]	SELF     	5 5 -11	; "notIntersectWith"
	20	[107]	MOVE     	7 4
	21	[107]	CALL     	5 3 2
	22	[107]	NOT      	5 5
	23	[107]	RETURN   	5 2
	24	[108]	RETURN   	0 1

function <./frontend/ui/widget/bboxwidget.lua:110,198> (269 instructions, 1076 bytes at 0x7fef42c09230)
3 params, 21 slots, 3 upvalues, 19 locals, 23 constants, 1 function
	1	[111]	SELF     	3 0 -1	; "inPageArea"
	2	[111]	MOVE     	5 1
	3	[111]	CALL     	3 3 2
	4	[111]	TEST     	3 0 1
	5	[111]	JMP      	1	; to 7
	6	[111]	RETURN   	0 1
	7	[112]	GETTABLE 	3 0 -2	; "screen_bbox"
	8	[113]	GETUPVAL 	4 0	; Geom
	9	[113]	SELF     	4 4 -3	; "new"
	10	[113]	NEWTABLE 	6 0 2
	11	[113]	GETTABLE 	7 3 -5	; "x0"
	12	[113]	SETTABLE 	6 -4 7	; "x" -
	13	[113]	GETTABLE 	7 3 -7	; "y0"
	14	[113]	SETTABLE 	6 -6 7	; "y" -
	15	[113]	CALL     	4 3 2
	16	[114]	GETUPVAL 	5 0	; Geom
	17	[114]	SELF     	5 5 -3	; "new"
	18	[114]	NEWTABLE 	7 0 2
	19	[114]	GETTABLE 	8 3 -8	; "x1"
	20	[114]	SETTABLE 	7 -4 8	; "x" -
	21	[114]	GETTABLE 	8 3 -7	; "y0"
	22	[114]	SETTABLE 	7 -6 8	; "y" -
	23	[114]	CALL     	5 3 2
	24	[115]	GETUPVAL 	6 0	; Geom
	25	[115]	SELF     	6 6 -3	; "new"
	26	[115]	NEWTABLE 	8 0 2
	27	[115]	GETTABLE 	9 3 -5	; "x0"
	28	[115]	SETTABLE 	8 -4 9	; "x" -
	29	[115]	GETTABLE 	9 3 -9	; "y1"
	30	[115]	SETTABLE 	8 -6 9	; "y" -
	31	[115]	CALL     	6 3 2
	32	[116]	GETUPVAL 	7 0	; Geom
	33	[116]	SELF     	7 7 -3	; "new"
	34	[116]	NEWTABLE 	9 0 2
	35	[116]	GETTABLE 	10 3 -8	; "x1"
	36	[116]	SETTABLE 	9 -4 10	; "x" -
	37	[116]	GETTABLE 	10 3 -9	; "y1"
	38	[116]	SETTABLE 	9 -6 10	; "y" -
	39	[116]	CALL     	7 3 2
	40	[117]	GETUPVAL 	8 0	; Geom
	41	[117]	SELF     	8 8 -3	; "new"
	42	[117]	NEWTABLE 	10 0 2
	43	[117]	GETTABLE 	11 3 -5	; "x0"
	44	[117]	GETTABLE 	12 3 -8	; "x1"
	45	[117]	ADD      	11 11 12
	46	[117]	DIV      	11 11 -10	; - 2
	47	[117]	SETTABLE 	10 -4 11	; "x" -
	48	[117]	GETTABLE 	11 3 -7	; "y0"
	49	[117]	SETTABLE 	10 -6 11	; "y" -
	50	[117]	CALL     	8 3 2
	51	[118]	GETUPVAL 	9 0	; Geom
	52	[118]	SELF     	9 9 -3	; "new"
	53	[118]	NEWTABLE 	11 0 2
	54	[118]	GETTABLE 	12 3 -5	; "x0"
	55	[118]	GETTABLE 	13 3 -8	; "x1"
	56	[118]	ADD      	12 12 13
	57	[118]	DIV      	12 12 -10	; - 2
	58	[118]	SETTABLE 	11 -4 12	; "x" -
	59	[118]	GETTABLE 	12 3 -9	; "y1"
	60	[118]	SETTABLE 	11 -6 12	; "y" -
	61	[118]	CALL     	9 3 2
	62	[119]	GETUPVAL 	10 0	; Geom
	63	[119]	SELF     	10 10 -3	; "new"
	64	[119]	NEWTABLE 	12 0 2
	65	[119]	GETTABLE 	13 3 -8	; "x1"
	66	[119]	SETTABLE 	12 -4 13	; "x" -
	67	[119]	GETTABLE 	13 3 -7	; "y0"
	68	[119]	GETTABLE 	14 3 -9	; "y1"
	69	[119]	ADD      	13 13 14
	70	[119]	DIV      	13 13 -10	; - 2
	71	[119]	SETTABLE 	12 -6 13	; "y" -
	72	[119]	CALL     	10 3 2
	73	[120]	GETUPVAL 	11 0	; Geom
	74	[120]	SELF     	11 11 -3	; "new"
	75	[120]	NEWTABLE 	13 0 2
	76	[120]	GETTABLE 	14 3 -5	; "x0"
	77	[120]	SETTABLE 	13 -4 14	; "x" -
	78	[120]	GETTABLE 	14 3 -7	; "y0"
	79	[120]	GETTABLE 	15 3 -9	; "y1"
	80	[120]	ADD      	14 14 15
	81	[120]	DIV      	14 14 -10	; - 2
	82	[120]	SETTABLE 	13 -6 14	; "y" -
	83	[120]	CALL     	11 3 2
	84	[121]	NEWTABLE 	12 8 0
	85	[122]	MOVE     	13 4
	86	[122]	MOVE     	14 8
	87	[122]	MOVE     	15 5
	88	[123]	MOVE     	16 11
	89	[123]	MOVE     	17 10
	90	[124]	MOVE     	18 6
	91	[124]	MOVE     	19 9
	92	[125]	MOVE     	20 7
	93	[125]	SETLIST  	12 8 1	; 1
	94	[126]	GETUPVAL 	13 1	; Math
	95	[126]	GETTABLE 	13 13 -11	; "tmin"
	96	[126]	MOVE     	14 12
	97	[128]	CLOSURE  	15 0	; 0x7fef42c09330
	98	[128]	MOVE     	0 1
	99	[126]	CALL     	13 3 3
	100	[129]	EQ       	0 14 4
	101	[129]	JMP      	7	; to 109
	102	[130]	GETTABLE 	15 1 -12	; "pos"
	103	[130]	GETTABLE 	15 15 -4	; "x"
	104	[130]	SETTABLE 	4 -4 15	; "x" -
	105	[131]	GETTABLE 	15 1 -12	; "pos"
	106	[131]	GETTABLE 	15 15 -6	; "y"
	107	[131]	SETTABLE 	4 -6 15	; "y" -
	108	[131]	JMP      	134	; to 243
	109	[132]	EQ       	0 14 7
	110	[132]	JMP      	7	; to 118
	111	[133]	GETTABLE 	15 1 -12	; "pos"
	112	[133]	GETTABLE 	15 15 -4	; "x"
	113	[133]	SETTABLE 	7 -4 15	; "x" -
	114	[134]	GETTABLE 	15 1 -12	; "pos"
	115	[134]	GETTABLE 	15 15 -6	; "y"
	116	[134]	SETTABLE 	7 -6 15	; "y" -
	117	[134]	JMP      	125	; to 243
	118	[135]	EQ       	0 14 5
	119	[135]	JMP      	7	; to 127
	120	[136]	GETTABLE 	15 1 -12	; "pos"
	121	[136]	GETTABLE 	15 15 -4	; "x"
	122	[136]	SETTABLE 	7 -4 15	; "x" -
	123	[137]	GETTABLE 	15 1 -12	; "pos"
	124	[137]	GETTABLE 	15 15 -6	; "y"
	125	[137]	SETTABLE 	4 -6 15	; "y" -
	126	[137]	JMP      	116	; to 243
	127	[138]	EQ       	0 14 6
	128	[138]	JMP      	7	; to 136
	129	[139]	GETTABLE 	15 1 -12	; "pos"
	130	[139]	GETTABLE 	15 15 -4	; "x"
	131	[139]	SETTABLE 	4 -4 15	; "x" -
	132	[140]	GETTABLE 	15 1 -12	; "pos"
	133	[140]	GETTABLE 	15 15 -6	; "y"
	134	[140]	SETTABLE 	7 -6 15	; "y" -
	135	[140]	JMP      	107	; to 243
	136	[141]	EQ       	0 14 8
	137	[141]	JMP      	25	; to 163
	138	[142]	TEST     	2 0 0
	139	[142]	JMP      	19	; to 159
	140	[143]	LOADK    	15 -13	; 0
	141	[144]	GETTABLE 	16 1 -14	; "direction"
	142	[144]	EQ       	0 16 -15	; - "north"
	143	[144]	JMP      	5	; to 149
	144	[145]	GETTABLE 	16 1 -16	; "distance"
	145	[145]	UNM      	16 16
	146	[145]	GETTABLE 	17 0 -17	; "fine_factor"
	147	[145]	DIV      	15 16 17
	148	[145]	JMP      	6	; to 155
	149	[146]	GETTABLE 	16 1 -14	; "direction"
	150	[146]	EQ       	0 16 -18	; - "south"
	151	[146]	JMP      	3	; to 155
	152	[147]	GETTABLE 	16 1 -16	; "distance"
	153	[147]	GETTABLE 	17 0 -17	; "fine_factor"
	154	[147]	DIV      	15 16 17
	155	[149]	GETTABLE 	16 4 -6	; "y"
	156	[149]	ADD      	16 16 15
	157	[149]	SETTABLE 	4 -6 16	; "y" -
	158	[149]	JMP      	84	; to 243
	159	[151]	GETTABLE 	15 1 -12	; "pos"
	160	[151]	GETTABLE 	15 15 -6	; "y"
	161	[151]	SETTABLE 	4 -6 15	; "y" -
	162	[152]	JMP      	80	; to 243
	163	[153]	EQ       	0 14 10
	164	[153]	JMP      	25	; to 190
	165	[154]	TEST     	2 0 0
	166	[154]	JMP      	19	; to 186
	167	[155]	LOADK    	15 -13	; 0
	168	[156]	GETTABLE 	16 1 -14	; "direction"
	169	[156]	EQ       	0 16 -19	; - "west"
	170	[156]	JMP      	5	; to 176
	171	[157]	GETTABLE 	16 1 -16	; "distance"
	172	[157]	UNM      	16 16
	173	[157]	GETTABLE 	17 0 -17	; "fine_factor"
	174	[157]	DIV      	15 16 17
	175	[157]	JMP      	6	; to 182
	176	[158]	GETTABLE 	16 1 -14	; "direction"
	177	[158]	EQ       	0 16 -20	; - "east"
	178	[158]	JMP      	3	; to 182
	179	[159]	GETTABLE 	16 1 -16	; "distance"
	180	[159]	GETTABLE 	17 0 -17	; "fine_factor"
	181	[159]	DIV      	15 16 17
	182	[161]	GETTABLE 	16 7 -4	; "x"
	183	[161]	ADD      	16 16 15
	184	[161]	SETTABLE 	7 -4 16	; "x" -
	185	[161]	JMP      	57	; to 243
	186	[163]	GETTABLE 	15 1 -12	; "pos"
	187	[163]	GETTABLE 	15 15 -4	; "x"
	188	[163]	SETTABLE 	7 -4 15	; "x" -
	189	[164]	JMP      	53	; to 243
	190	[165]	EQ       	0 14 9
	191	[165]	JMP      	25	; to 217
	192	[166]	TEST     	2 0 0
	193	[166]	JMP      	19	; to 213
	194	[167]	LOADK    	15 -13	; 0
	195	[168]	GETTABLE 	16 1 -14	; "direction"
	196	[168]	EQ       	0 16 -15	; - "north"
	197	[168]	JMP      	5	; to 203
	198	[169]	GETTABLE 	16 1 -16	; "distance"
	199	[169]	UNM      	16 16
	200	[169]	GETTABLE 	17 0 -17	; "fine_factor"
	201	[169]	DIV      	15 16 17
	202	[169]	JMP      	6	; to 209
	203	[170]	GETTABLE 	16 1 -14	; "direction"
	204	[170]	EQ       	0 16 -18	; - "south"
	205	[170]	JMP      	3	; to 209
	206	[171]	GETTABLE 	16 1 -16	; "distance"
	207	[171]	GETTABLE 	17 0 -17	; "fine_factor"
	208	[171]	DIV      	15 16 17
	209	[173]	GETTABLE 	16 7 -6	; "y"
	210	[173]	ADD      	16 16 15
	211	[173]	SETTABLE 	7 -6 16	; "y" -
	212	[173]	JMP      	30	; to 243
	213	[175]	GETTABLE 	15 1 -12	; "pos"
	214	[175]	GETTABLE 	15 15 -6	; "y"
	215	[175]	SETTABLE 	7 -6 15	; "y" -
	216	[176]	JMP      	26	; to 243
	217	[177]	EQ       	0 14 11
	218	[177]	JMP      	24	; to 243
	219	[178]	TEST     	2 0 0
	220	[178]	JMP      	19	; to 240
	221	[179]	LOADK    	15 -13	; 0
	222	[180]	GETTABLE 	16 1 -14	; "direction"
	223	[180]	EQ       	0 16 -19	; - "west"
	224	[180]	JMP      	5	; to 230
	225	[181]	GETTABLE 	16 1 -16	; "distance"
	226	[181]	UNM      	16 16
	227	[181]	GETTABLE 	17 0 -17	; "fine_factor"
	228	[181]	DIV      	15 16 17
	229	[181]	JMP      	6	; to 236
	230	[182]	GETTABLE 	16 1 -14	; "direction"
	231	[182]	EQ       	0 16 -20	; - "east"
	232	[182]	JMP      	3	; to 236
	233	[183]	GETTABLE 	16 1 -16	; "distance"
	234	[183]	GETTABLE 	17 0 -17	; "fine_factor"
	235	[183]	DIV      	15 16 17
	236	[185]	GETTABLE 	16 4 -4	; "x"
	237	[185]	ADD      	16 16 15
	238	[185]	SETTABLE 	4 -4 16	; "x" -
	239	[185]	JMP      	3	; to 243
	240	[187]	GETTABLE 	15 1 -12	; "pos"
	241	[187]	GETTABLE 	15 15 -4	; "x"
	242	[187]	SETTABLE 	4 -4 15	; "x" -
	243	[190]	NEWTABLE 	15 0 4
	244	[191]	GETUPVAL 	16 1	; Math
	245	[191]	GETTABLE 	16 16 -21	; "round"
	246	[191]	GETTABLE 	17 4 -4	; "x"
	247	[191]	CALL     	16 2 2
	248	[191]	SETTABLE 	15 -5 16	; "x0" -
	249	[192]	GETUPVAL 	16 1	; Math
	250	[192]	GETTABLE 	16 16 -21	; "round"
	251	[192]	GETTABLE 	17 4 -6	; "y"
	252	[192]	CALL     	16 2 2
	253	[192]	SETTABLE 	15 -7 16	; "y0" -
	254	[193]	GETUPVAL 	16 1	; Math
	255	[193]	GETTABLE 	16 16 -21	; "round"
	256	[193]	GETTABLE 	17 7 -4	; "x"
	257	[193]	CALL     	16 2 2
	258	[193]	SETTABLE 	15 -8 16	; "x1" -
	259	[194]	GETUPVAL 	16 1	; Math
	260	[194]	GETTABLE 	16 16 -21	; "round"
	261	[194]	GETTABLE 	17 7 -6	; "y"
	262	[194]	CALL     	16 2 2
	263	[194]	SETTABLE 	15 -9 16	; "y1" -
	264	[195]	SETTABLE 	0 -2 15	; "screen_bbox" -
	265	[197]	GETUPVAL 	15 2	; UIManager
	266	[197]	SELF     	15 15 -22	; "setDirty"
	267	[197]	LOADK    	17 -23	; "all"
	268	[197]	CALL     	15 3 1
	269	[198]	RETURN   	0 1

function <./frontend/ui/widget/bboxwidget.lua:126,128> (14 instructions, 56 bytes at 0x7fef42c09330)
2 params, 6 slots, 1 upvalue, 2 locals, 2 constants, 0 functions
	1	[127]	SELF     	2 0 -1	; "distance"
	2	[127]	GETUPVAL 	4 0	; ges
	3	[127]	GETTABLE 	4 4 -2	; "pos"
	4	[127]	CALL     	2 3 2
	5	[127]	SELF     	3 1 -1	; "distance"
	6	[127]	GETUPVAL 	5 0	; ges
	7	[127]	GETTABLE 	5 5 -2	; "pos"
	8	[127]	CALL     	3 3 2
	9	[127]	LT       	1 3 2
	10	[127]	JMP      	1	; to 12
	11	[127]	LOADBOOL 	2 0 1
	12	[127]	LOADBOOL 	2 1 0
	13	[127]	RETURN   	2 2
	14	[128]	RETURN   	0 1

function <./frontend/ui/widget/bboxwidget.lua:200,202> (5 instructions, 20 bytes at 0x7fef42c09570)
1 param, 4 slots, 0 upvalues, 1 local, 2 constants, 0 functions
	1	[201]	SELF     	1 0 -1	; "getPageBBox"
	2	[201]	GETTABLE 	3 0 -2	; "screen_bbox"
	3	[201]	TAILCALL 	1 3 0
	4	[201]	RETURN   	1 0
	5	[202]	RETURN   	0 1

function <./frontend/ui/widget/bboxwidget.lua:204,207> (6 instructions, 24 bytes at 0x7fef42c09fa0)
3 params, 6 slots, 0 upvalues, 3 locals, 1 constant, 0 functions
	1	[205]	SELF     	3 0 -1	; "adjustScreenBBox"
	2	[205]	MOVE     	5 2
	3	[205]	CALL     	3 3 1
	4	[206]	LOADBOOL 	3 1 0
	5	[206]	RETURN   	3 2
	6	[207]	RETURN   	0 1

function <./frontend/ui/widget/bboxwidget.lua:209,212> (7 instructions, 28 bytes at 0x7fef42c0a490)
3 params, 7 slots, 0 upvalues, 3 locals, 1 constant, 0 functions
	1	[210]	SELF     	3 0 -1	; "adjustScreenBBox"
	2	[210]	MOVE     	5 2
	3	[210]	LOADBOOL 	6 1 0
	4	[210]	CALL     	3 4 1
	5	[211]	LOADBOOL 	3 1 0
	6	[211]	RETURN   	3 2
	7	[212]	RETURN   	0 1

function <./frontend/ui/widget/bboxwidget.lua:214,220> (3 instructions, 12 bytes at 0x7fef42c0a5a0)
3 params, 4 slots, 0 upvalues, 3 locals, 0 constants, 0 functions
	1	[219]	LOADBOOL 	3 1 0
	2	[219]	RETURN   	3 2
	3	[220]	RETURN   	0 1

function <./frontend/ui/widget/bboxwidget.lua:222,227> (15 instructions, 60 bytes at 0x7fef42c07160)
3 params, 8 slots, 1 upvalue, 3 locals, 5 constants, 0 functions
	1	[223]	SELF     	3 0 -1	; "inPageArea"
	2	[223]	MOVE     	5 2
	3	[223]	CALL     	3 3 2
	4	[223]	TEST     	3 0 0
	5	[223]	JMP      	7	; to 13
	6	[224]	GETTABLE 	3 0 -2	; "ui"
	7	[224]	SELF     	3 3 -3	; "handleEvent"
	8	[224]	GETUPVAL 	5 0	; Event
	9	[224]	SELF     	5 5 -4	; "new"
	10	[224]	LOADK    	7 -5	; "ConfirmPageCrop"
	11	[224]	CALL     	5 3 0
	12	[224]	CALL     	3 0 1
	13	[226]	LOADBOOL 	3 1 0
	14	[226]	RETURN   	3 2
	15	[227]	RETURN   	0 1

function <./frontend/ui/widget/bboxwidget.lua:229,231> (8 instructions, 32 bytes at 0x7fef42c0aeb0)
1 param, 6 slots, 1 upvalue, 1 local, 4 constants, 0 functions
	1	[230]	GETTABLE 	1 0 -1	; "ui"
	2	[230]	SELF     	1 1 -2	; "handleEvent"
	3	[230]	GETUPVAL 	3 0	; Event
	4	[230]	SELF     	3 3 -3	; "new"
	5	[230]	LOADK    	5 -4	; "CancelPageCrop"
	6	[230]	CALL     	3 3 0
	7	[230]	CALL     	1 0 1
	8	[231]	RETURN   	0 1

function <./frontend/ui/widget/bboxwidget.lua:233,235> (8 instructions, 32 bytes at 0x7fef42c0b280)
1 param, 6 slots, 1 upvalue, 1 local, 4 constants, 0 functions
	1	[234]	GETTABLE 	1 0 -1	; "ui"
	2	[234]	SELF     	1 1 -2	; "handleEvent"
	3	[234]	GETUPVAL 	3 0	; Event
	4	[234]	SELF     	3 3 -3	; "new"
	5	[234]	LOADK    	5 -4	; "ConfirmPageCrop"
	6	[234]	CALL     	3 3 0
	7	[234]	CALL     	1 0 1
	8	[235]	RETURN   	0 1
