
main <./spec/unit/benchmark.lua:0,0> (25 instructions, 100 bytes at 0x7fa594c068c0)
0+ params, 6 slots, 0 upvalues, 3 locals, 7 constants, 3 functions
	1	[1]	GETGLOBAL	0 -1	; require
	2	[1]	LOADK    	1 -2	; "commonrequire"
	3	[1]	CALL     	0 2 1
	4	[2]	GETGLOBAL	0 -1	; require
	5	[2]	LOADK    	1 -3	; "document/documentregistry"
	6	[2]	CALL     	0 2 2
	7	[3]	GETGLOBAL	1 -1	; require
	8	[3]	LOADK    	2 -4	; "ffi/util"
	9	[3]	CALL     	1 2 2
	10	[14]	CLOSURE  	2 0	; 0x7fa594c06bd0
	11	[16]	GETGLOBAL	3 -5	; describe
	12	[16]	LOADK    	4 -6	; "PDF rendering benchmark"
	13	[27]	CLOSURE  	5 1	; 0x7fa594c06690
	14	[27]	MOVE     	0 0
	15	[27]	MOVE     	0 1
	16	[27]	MOVE     	0 2
	17	[16]	CALL     	3 3 1
	18	[29]	GETGLOBAL	3 -5	; describe
	19	[29]	LOADK    	4 -7	; "PDF reflowing benchmark"
	20	[42]	CLOSURE  	5 2	; 0x7fa594c07610
	21	[42]	MOVE     	0 0
	22	[42]	MOVE     	0 1
	23	[42]	MOVE     	0 2
	24	[29]	CALL     	3 3 1
	25	[42]	RETURN   	0 1

function <./spec/unit/benchmark.lua:5,14> (26 instructions, 104 bytes at 0x7fa594c06bd0)
3 params, 10 slots, 0 upvalues, 4 locals, 12 constants, 0 functions
	1	[6]	GETGLOBAL	3 -1	; io
	2	[6]	GETTABLE 	3 3 -2	; "open"
	3	[6]	MOVE     	4 0
	4	[6]	LOADK    	5 -3	; "a+"
	5	[6]	CALL     	3 3 2
	6	[7]	TEST     	3 0 0
	7	[7]	JMP      	18	; to 26
	8	[8]	SELF     	4 3 -4	; "seek"
	9	[8]	LOADK    	6 -5	; "end"
	10	[8]	CALL     	4 3 2
	11	[8]	EQ       	0 4 -6	; - 0
	12	[8]	JMP      	3	; to 16
	13	[9]	SELF     	4 3 -7	; "write"
	14	[9]	LOADK    	6 -8	; "PAGE\tDUR\n"
	15	[9]	CALL     	4 3 1
	16	[11]	SELF     	4 3 -7	; "write"
	17	[11]	GETGLOBAL	6 -9	; string
	18	[11]	GETTABLE 	6 6 -10	; "format"
	19	[11]	LOADK    	7 -11	; "%s\t%s\n"
	20	[11]	MOVE     	8 1
	21	[11]	MOVE     	9 2
	22	[11]	CALL     	6 4 0
	23	[11]	CALL     	4 0 1
	24	[12]	SELF     	4 3 -12	; "close"
	25	[12]	CALL     	4 2 1
	26	[14]	RETURN   	0 1

function <./spec/unit/benchmark.lua:16,27> (44 instructions, 176 bytes at 0x7fa594c06690)
0 params, 17 slots, 3 upvalues, 11 locals, 16 constants, 0 functions
	1	[17]	LOADK    	0 -1	; "spec/front/unit/data/sample.pdf"
	2	[18]	GETUPVAL 	1 0	; DocumentRegistry
	3	[18]	SELF     	1 1 -2	; "openDocument"
	4	[18]	MOVE     	3 0
	5	[18]	CALL     	1 3 2
	6	[19]	LOADK    	2 -3	; 1
	7	[19]	GETGLOBAL	3 -4	; math
	8	[19]	GETTABLE 	3 3 -5	; "min"
	9	[19]	LOADK    	4 -6	; 10
	10	[19]	GETTABLE 	5 1 -7	; "info"
	11	[19]	GETTABLE 	5 5 -8	; "number_of_pages"
	12	[19]	CALL     	3 3 2
	13	[19]	LOADK    	4 -3	; 1
	14	[19]	FORPREP  	2 26	; to 41
	15	[20]	GETUPVAL 	6 1	; util
	16	[20]	GETTABLE 	6 6 -9	; "gettime"
	17	[20]	CALL     	6 1 3
	18	[21]	GETGLOBAL	8 -10	; assert
	19	[21]	GETTABLE 	8 8 -11	; "truthy"
	20	[21]	SELF     	9 1 -12	; "renderPage"
	21	[21]	MOVE     	11 5
	22	[21]	LOADNIL  	12 12
	23	[21]	LOADK    	13 -3	; 1
	24	[21]	LOADK    	14 -13	; 0
	25	[21]	LOADK    	15 -3	; 1
	26	[21]	LOADK    	16 -13	; 0
	27	[21]	CALL     	9 8 0
	28	[21]	CALL     	8 0 1
	29	[22]	GETUPVAL 	8 1	; util
	30	[22]	GETTABLE 	8 8 -9	; "gettime"
	31	[22]	CALL     	8 1 3
	32	[23]	SUB      	10 8 6
	33	[23]	SUB      	11 9 7
	34	[23]	DIV      	11 11 -14	; - 1000000
	35	[23]	ADD      	10 10 11
	36	[24]	GETUPVAL 	11 2	; logDuration
	37	[24]	LOADK    	12 -15	; "pdf_rendering.log"
	38	[24]	MOVE     	13 5
	39	[24]	MOVE     	14 10
	40	[24]	CALL     	11 4 1
	41	[19]	FORLOOP  	2 -27	; to 15
	42	[26]	SELF     	2 1 -16	; "close"
	43	[26]	CALL     	2 2 1
	44	[27]	RETURN   	0 1

function <./spec/unit/benchmark.lua:29,42> (48 instructions, 192 bytes at 0x7fa594c07610)
0 params, 17 slots, 3 upvalues, 11 locals, 18 constants, 0 functions
	1	[30]	LOADK    	0 -1	; "spec/front/unit/data/sample.pdf"
	2	[31]	GETUPVAL 	1 0	; DocumentRegistry
	3	[31]	SELF     	1 1 -2	; "openDocument"
	4	[31]	MOVE     	3 0
	5	[31]	CALL     	1 3 2
	6	[32]	GETTABLE 	2 1 -3	; "configurable"
	7	[32]	SETTABLE 	2 -4 -5	; "text_wrap" 1
	8	[33]	LOADK    	2 -5	; 1
	9	[33]	GETGLOBAL	3 -6	; math
	10	[33]	GETTABLE 	3 3 -7	; "min"
	11	[33]	LOADK    	4 -8	; 10
	12	[33]	GETTABLE 	5 1 -9	; "info"
	13	[33]	GETTABLE 	5 5 -10	; "number_of_pages"
	14	[33]	CALL     	3 3 2
	15	[33]	LOADK    	4 -5	; 1
	16	[33]	FORPREP  	2 26	; to 43
	17	[34]	GETUPVAL 	6 1	; util
	18	[34]	GETTABLE 	6 6 -11	; "gettime"
	19	[34]	CALL     	6 1 3
	20	[35]	GETGLOBAL	8 -12	; assert
	21	[35]	GETTABLE 	8 8 -13	; "truthy"
	22	[35]	SELF     	9 1 -14	; "renderPage"
	23	[35]	MOVE     	11 5
	24	[35]	LOADNIL  	12 12
	25	[35]	LOADK    	13 -5	; 1
	26	[35]	LOADK    	14 -15	; 0
	27	[35]	LOADK    	15 -5	; 1
	28	[35]	LOADK    	16 -15	; 0
	29	[35]	CALL     	9 8 0
	30	[35]	CALL     	8 0 1
	31	[36]	GETUPVAL 	8 1	; util
	32	[36]	GETTABLE 	8 8 -11	; "gettime"
	33	[36]	CALL     	8 1 3
	34	[37]	SUB      	10 8 6
	35	[37]	SUB      	11 9 7
	36	[37]	DIV      	11 11 -16	; - 1000000
	37	[37]	ADD      	10 10 11
	38	[38]	GETUPVAL 	11 2	; logDuration
	39	[38]	LOADK    	12 -17	; "pdf_reflowing.log"
	40	[38]	MOVE     	13 5
	41	[38]	MOVE     	14 10
	42	[38]	CALL     	11 4 1
	43	[33]	FORLOOP  	2 -27	; to 17
	44	[40]	SELF     	2 1 -18	; "close"
	45	[40]	CALL     	2 2 1
	46	[41]	GETTABLE 	2 1 -3	; "configurable"
	47	[41]	SETTABLE 	2 -4 -15	; "text_wrap" 0
	48	[42]	RETURN   	0 1
