-- BYTECODE -- bidi.lua:104-116
0001    TNEW     1   0
0002    UGET     2   0      ; util
0003    TGETS    2   2   0  ; "gsplit"
0004    MOV      3   0
0005    KSTR     4   1      ; "\n"
0006    KPRI     5   2
0007    KPRI     6   2
0008    CALL     2   4   5
0009    JMP      5 => 0028
0010 => ISNES    5   1      ; "\n"
0011    JMP      6 => 0018
0012    GGET     6   2      ; "table"
0013    TGETS    6   6   3  ; "insert"
0014    MOV      7   1
0015    KSTR     8   1      ; "\n"
0016    CALL     6   1   3
0017    JMP      6 => 0028
0018 => ISEQS    5   4      ; ""
0019    JMP      6 => 0028
0020    GGET     6   2      ; "table"
0021    TGETS    6   6   3  ; "insert"
0022    MOV      7   1
0023    UGET     8   1      ; Bidi
0024    TGETS    8   8   5  ; "ltr"
0025    MOV      9   5
0026    CALL     8   0   2
0027    CALLM    6   1   1
0028 => ITERC    5   2   3
0029    ITERL    5 => 0010
0030    GGET     2   2      ; "table"
0031    TGETS    2   2   6  ; "concat"
0032    MOV      3   1
0033    CALLT    2   2

-- BYTECODE -- bidi.lua:49-120
0001    UGET     1   0      ; Language
0002    MOV      2   1
0003    TGETS    1   1   0  ; "isLanguageRTL"
0004    MOV      3   0
0005    CALL     1   2   3
0006    UGET     2   1      ; Bidi
0007    TSETS    1   2   1  ; "_mirrored_ui_layout"
0008    GGET     2   2      ; "G_reader_settings"
0009    MOV      3   2
0010    TGETS    2   2   3  ; "isTrue"
0011    KSTR     4   4      ; "dev_reverse_ui_layout_mirroring"
0012    CALL     2   2   3
0013    ISF          2
0014    JMP      3 => 0020
0015    UGET     2   1      ; Bidi
0016    UGET     3   1      ; Bidi
0017    TGETS    3   3   1  ; "_mirrored_ui_layout"
0018    NOT      3   3
0019    TSETS    3   2   1  ; "_mirrored_ui_layout"
0020 => GGET     2   2      ; "G_reader_settings"
0021    MOV      3   2
0022    TGETS    2   2   5  ; "nilOrTrue"
0023    KSTR     4   6      ; "use_xtext"
0024    CALL     2   2   3
0025    ISF          2
0026    JMP      3 => 0056
0027    GGET     2   7      ; "require"
0028    KSTR     3   8      ; "libs/libkoreader-xtext"
0029    CALL     2   2   2
0030    GGET     3   2      ; "G_reader_settings"
0031    MOV      4   3
0032    TGETS    3   3   3  ; "isTrue"
0033    KSTR     5   9      ; "dev_reverse_ui_text_direction"
0034    CALL     3   2   3
0035    ISF          3
0036    JMP      4 => 0038
0037    NOT      1   1
0038 => UGET     3   1      ; Bidi
0039    TSETS    1   3  10  ; "_rtl_ui_text"
0040    TGETS    3   2  11  ; "setDefaultParaDirection"
0041    MOV      4   1
0042    CALL     3   1   2
0043    GGET     3   2      ; "G_reader_settings"
0044    MOV      4   3
0045    TGETS    3   3  12  ; "readSetting"
0046    KSTR     5  13      ; "xtext_alt_lang"
0047    CALL     3   2   3
0048    IST          3
0049    JMP      4 => 0051
0050    MOV      3   0
0051 => ISF          3
0052    JMP      4 => 0056
0053    TGETS    4   2  14  ; "setDefaultLang"
0054    MOV      5   3
0055    CALL     4   1   2
0056 => UGET     2   1      ; Bidi
0057    TGETS    2   2  10  ; "_rtl_ui_text"
0058    ISF          2
0059    JMP      3 => 0093
0060    UGET     2   1      ; Bidi
0061    UGET     3   1      ; Bidi
0062    TGETS    3   3  16  ; "rtl"
0063    TSETS    3   2  15  ; "default"
0064    UGET     2   1      ; Bidi
0065    UGET     3   1      ; Bidi
0066    TGETS    3   3  16  ; "rtl"
0067    TSETS    3   2  17  ; "wrap"
0068    UGET     2   1      ; Bidi
0069    UGET     3   1      ; Bidi
0070    TGETS    3   3  19  ; "_filename_rtl"
0071    TSETS    3   2  18  ; "filename"
0072    UGET     2   1      ; Bidi
0073    UGET     3   1      ; Bidi
0074    TGETS    3   3  21  ; "_filepath_rtl"
0075    TSETS    3   2  20  ; "filepath"
0076    UGET     2   1      ; Bidi
0077    UGET     3   1      ; Bidi
0078    TGETS    3   3  23  ; "_path"
0079    TSETS    3   2  22  ; "directory"
0080    UGET     2   1      ; Bidi
0081    UGET     3   1      ; Bidi
0082    TGETS    3   3  23  ; "_path"
0083    TSETS    3   2  24  ; "dirpath"
0084    UGET     2   1      ; Bidi
0085    UGET     3   1      ; Bidi
0086    TGETS    3   3  23  ; "_path"
0087    TSETS    3   2  25  ; "path"
0088    UGET     2   1      ; Bidi
0089    UGET     3   1      ; Bidi
0090    TGETS    3   3  23  ; "_path"
0091    TSETS    3   2  26  ; "url"
0092    JMP      2 => 0125
0093 => UGET     2   1      ; Bidi
0094    UGET     3   1      ; Bidi
0095    TGETS    3   3  27  ; "ltr"
0096    TSETS    3   2  15  ; "default"
0097    UGET     2   1      ; Bidi
0098    UGET     3   1      ; Bidi
0099    TGETS    3   3  28  ; "nowrap"
0100    TSETS    3   2  17  ; "wrap"
0101    UGET     2   1      ; Bidi
0102    UGET     3   1      ; Bidi
0103    TGETS    3   3  29  ; "_filename_ltr"
0104    TSETS    3   2  18  ; "filename"
0105    UGET     2   1      ; Bidi
0106    UGET     3   1      ; Bidi
0107    TGETS    3   3  30  ; "_filepath_ltr"
0108    TSETS    3   2  20  ; "filepath"
0109    UGET     2   1      ; Bidi
0110    UGET     3   1      ; Bidi
0111    TGETS    3   3  23  ; "_path"
0112    TSETS    3   2  22  ; "directory"
0113    UGET     2   1      ; Bidi
0114    UGET     3   1      ; Bidi
0115    TGETS    3   3  23  ; "_path"
0116    TSETS    3   2  24  ; "dirpath"
0117    UGET     2   1      ; Bidi
0118    UGET     3   1      ; Bidi
0119    TGETS    3   3  23  ; "_path"
0120    TSETS    3   2  25  ; "path"
0121    UGET     2   1      ; Bidi
0122    UGET     3   1      ; Bidi
0123    TGETS    3   3  23  ; "_path"
0124    TSETS    3   2  26  ; "url"
0125 => UGET     2   1      ; Bidi
0126    TGETS    2   2  10  ; "_rtl_ui_text"
0127    ISF          2
0128    JMP      3 => 0133
0129    UGET     2   2      ; _
0130    FNEW     3  32      ; bidi.lua:104
0131    TSETS    3   2  31  ; "wrapUntranslated"
0132    JMP      2 => 0137
0133 => UGET     2   2      ; _
0134    UGET     3   2      ; _
0135    TGETS    3   3  33  ; "wrapUntranslated_nowrap"
0136    TSETS    3   2  31  ; "wrapUntranslated"
0137 => RET0     0   1

-- BYTECODE -- bidi.lua:125-127
0001    UGET     0   0      ; Bidi
0002    TGETS    0   0   0  ; "_mirrored_ui_layout"
0003    RET1     0   2

-- BYTECODE -- bidi.lua:131-133
0001    UGET     0   0      ; Bidi
0002    TGETS    0   0   0  ; "_rtl_ui_text"
0003    RET1     0   2

-- BYTECODE -- bidi.lua:145-150
0001    UGET     1   0      ; Bidi
0002    TGETS    1   1   0  ; "_mirrored_ui_layout"
0003    ISF          1
0004    JMP      2 => 0011
0005    UGET     1   1      ; mirrored_directions
0006    TGETV    1   1   0
0007    IST          1
0008    JMP      2 => 0010
0009    MOV      1   0
0010 => RET1     1   2
0011 => RET1     0   2

-- BYTECODE -- bidi.lua:152-157
0001    UGET     1   0      ; Bidi
0002    TGETS    1   1   0  ; "_mirrored_ui_layout"
0003    ISF          1
0004    JMP      2 => 0007
0005    NOT      1   0
0006    RET1     1   2
0007 => RET1     0   2

-- BYTECODE -- bidi.lua:182-184
0001    GGET     1   0      ; "string"
0002    TGETS    1   1   1  ; "format"
0003    KSTR     2   2      ; "%s%s%s"
0004    UGET     3   0      ; LRI
0005    MOV      4   0
0006    UGET     5   1      ; PDI
0007    CALLT    1   5

-- BYTECODE -- bidi.lua:186-188
0001    GGET     1   0      ; "string"
0002    TGETS    1   1   1  ; "format"
0003    KSTR     2   2      ; "%s%s%s"
0004    UGET     3   0      ; RLI
0005    MOV      4   0
0006    UGET     5   1      ; PDI
0007    CALLT    1   5

-- BYTECODE -- bidi.lua:190-192
0001    GGET     1   0      ; "string"
0002    TGETS    1   1   1  ; "format"
0003    KSTR     2   2      ; "%s%s%s"
0004    UGET     3   0      ; FSI
0005    MOV      4   0
0006    UGET     5   1      ; PDI
0007    CALLT    1   5

-- BYTECODE -- bidi.lua:194-196
0001    UGET     1   0      ; Bidi
0002    TGETS    1   1   0  ; "_rtl_ui_text"
0003    ISF          1
0004    JMP      2 => 0011
0005    UGET     1   0      ; Bidi
0006    TGETS    1   1   1  ; "rtl"
0007    MOV      2   0
0008    CALL     1   2   2
0009    IST          1
0010    JMP      2 => 0015
0011 => UGET     1   0      ; Bidi
0012    TGETS    1   1   2  ; "ltr"
0013    MOV      2   0
0014    CALL     1   2   2
0015 => RET1     1   2

-- BYTECODE -- bidi.lua:198-200
0001    RET1     0   2

-- BYTECODE -- bidi.lua:207-209
0001    UGET     1   0      ; Bidi
0002    TGETS    1   1   0  ; "_rtl_ui_text"
0003    ISF          1
0004    JMP      2 => 0011
0005    UGET     1   0      ; Bidi
0006    TGETS    1   1   1  ; "rtl"
0007    MOV      2   0
0008    CALL     1   2   2
0009    IST          1
0010    JMP      2 => 0012
0011 => MOV      1   0
0012 => RET1     1   2

-- BYTECODE -- bidi.lua:225-238
0001    UGET     1   0      ; util
0002    TGETS    1   1   0  ; "splitFileNameSuffix"
0003    MOV      2   0
0004    CALL     1   3   2
0005    ISNES    2   1      ; ""
0006    JMP      3 => 0011
0007    UGET     3   1      ; Bidi
0008    TGETS    3   3   2  ; "auto"
0009    MOV      4   1
0010    CALLT    3   2
0011 => UGET     3   1      ; Bidi
0012    TGETS    3   3   2  ; "auto"
0013    MOV      4   1
0014    CALL     3   2   2
0015    KSTR     4   3      ; "."
0016    MOV      5   2
0017    CAT      3   3   5
0018    RET1     3   2

-- BYTECODE -- bidi.lua:240-251
0001    UGET     1   0      ; util
0002    TGETS    1   1   0  ; "splitFileNameSuffix"
0003    MOV      2   0
0004    CALL     1   3   2
0005    ISNES    2   1      ; ""
0006    JMP      3 => 0011
0007    UGET     3   1      ; Bidi
0008    TGETS    3   3   2  ; "auto"
0009    MOV      4   1
0010    CALLT    3   2
0011 => UGET     3   1      ; Bidi
0012    TGETS    3   3   2  ; "auto"
0013    MOV      4   1
0014    KSTR     5   3      ; "."
0015    UGET     6   1      ; Bidi
0016    TGETS    6   6   4  ; "ltr"
0017    MOV      7   2
0018    CALL     6   2   2
0019    CAT      4   4   6
0020    CALLT    3   2

-- BYTECODE -- bidi.lua:253-261
0001    UGET     1   0      ; util
0002    TGETS    1   1   0  ; "splitFileNameSuffix"
0003    MOV      2   0
0004    CALL     1   3   2
0005    ISNES    2   1      ; ""
0006    JMP      3 => 0011
0007    UGET     3   1      ; Bidi
0008    TGETS    3   3   2  ; "auto"
0009    MOV      4   1
0010    CALLT    3   2
0011 => UGET     3   1      ; Bidi
0012    TGETS    3   3   3  ; "ltr"
0013    UGET     4   1      ; Bidi
0014    TGETS    4   4   2  ; "auto"
0015    MOV      5   1
0016    CALL     4   2   2
0017    KSTR     5   4      ; "."
0018    MOV      6   2
0019    CAT      4   4   6
0020    CALLT    3   2

-- BYTECODE -- bidi.lua:263-274
0001    TNEW     1   0
0002    UGET     2   0      ; util
0003    TGETS    2   2   0  ; "gsplit"
0004    MOV      3   0
0005    KSTR     4   1      ; "/"
0006    KPRI     5   2
0007    KPRI     6   2
0008    CALL     2   4   5
0009    JMP      5 => 0028
0010 => ISNES    5   1      ; "/"
0011    JMP      6 => 0018
0012    GGET     6   2      ; "table"
0013    TGETS    6   6   3  ; "insert"
0014    MOV      7   1
0015    KSTR     8   1      ; "/"
0016    CALL     6   1   3
0017    JMP      6 => 0028
0018 => ISEQS    5   4      ; ""
0019    JMP      6 => 0028
0020    GGET     6   2      ; "table"
0021    TGETS    6   6   3  ; "insert"
0022    MOV      7   1
0023    UGET     8   1      ; Bidi
0024    TGETS    8   8   5  ; "auto"
0025    MOV      9   5
0026    CALL     8   0   2
0027    CALLM    6   1   1
0028 => ITERC    5   2   3
0029    ITERL    5 => 0010
0030    UGET     2   1      ; Bidi
0031    TGETS    2   2   6  ; "ltr"
0032    GGET     3   2      ; "table"
0033    TGETS    3   3   7  ; "concat"
0034    MOV      4   1
0035    CALL     3   0   2
0036    CALLMT   2   0

-- BYTECODE -- bidi.lua:276-279
0001    UGET     1   0      ; util
0002    TGETS    1   1   0  ; "splitFilePathName"
0003    MOV      2   0
0004    CALL     1   3   2
0005    UGET     3   1      ; Bidi
0006    TGETS    3   3   1  ; "ltr"
0007    UGET     4   1      ; Bidi
0008    TGETS    4   4   2  ; "_path"
0009    MOV      5   1
0010    CALL     4   2   2
0011    MOV      5   2
0012    CAT      4   4   5
0013    CALLT    3   2

-- BYTECODE -- bidi.lua:281-284
0001    UGET     1   0      ; util
0002    TGETS    1   1   0  ; "splitFilePathName"
0003    MOV      2   0
0004    CALL     1   3   2
0005    UGET     3   1      ; Bidi
0006    TGETS    3   3   1  ; "ltr"
0007    UGET     4   1      ; Bidi
0008    TGETS    4   4   2  ; "_path"
0009    MOV      5   1
0010    CALL     4   2   2
0011    UGET     5   1      ; Bidi
0012    TGETS    5   5   3  ; "_filename_auto_ext_right"
0013    MOV      6   2
0014    CALL     5   2   2
0015    CAT      4   4   5
0016    CALLT    3   2

-- BYTECODE -- bidi.lua:0-287
0001    GGET     0   0      ; "require"
0002    KSTR     1   1      ; "ui/language"
0003    CALL     0   2   2
0004    GGET     1   0      ; "require"
0005    KSTR     2   2      ; "util"
0006    CALL     1   2   2
0007    GGET     2   0      ; "require"
0008    KSTR     3   3      ; "gettext"
0009    CALL     2   2   2
0010    TDUP     3   4
0011    FNEW     4   6      ; bidi.lua:49
0012    TSETS    4   3   5  ; "setup"
0013    FNEW     4   8      ; bidi.lua:125
0014    TSETS    4   3   7  ; "mirroredUILayout"
0015    FNEW     4  10      ; bidi.lua:131
0016    TSETS    4   3   9  ; "rtlUIText"
0017    TDUP     4  11
0018    FNEW     5  13      ; bidi.lua:145
0019    TSETS    5   3  12  ; "flipDirectionIfMirroredUILayout"
0020    FNEW     5  15      ; bidi.lua:152
0021    TSETS    5   3  14  ; "flipIfMirroredUILayout"
0022    KSTR     5  16      ; "⁦"
0023    KSTR     6  17      ; "⁧"
0024    KSTR     7  18      ; "⁨"
0025    KSTR     8  19      ; "⁩"
0026    FNEW     9  21      ; bidi.lua:182
0027    TSETS    9   3  20  ; "ltr"
0028    FNEW     9  23      ; bidi.lua:186
0029    TSETS    9   3  22  ; "rtl"
0030    FNEW     9  25      ; bidi.lua:190
0031    TSETS    9   3  24  ; "auto"
0032    FNEW     9  27      ; bidi.lua:194
0033    TSETS    9   3  26  ; "default"
0034    FNEW     9  29      ; bidi.lua:198
0035    TSETS    9   3  28  ; "nowrap"
0036    FNEW     9  31      ; bidi.lua:207
0037    TSETS    9   3  30  ; "wrap"
0038    TGETS    9   3  28  ; "nowrap"
0039    TSETS    9   3  32  ; "filename"
0040    TGETS    9   3  28  ; "nowrap"
0041    TSETS    9   3  33  ; "filepath"
0042    TGETS    9   3  28  ; "nowrap"
0043    TSETS    9   3  34  ; "directory"
0044    TGETS    9   3  28  ; "nowrap"
0045    TSETS    9   3  35  ; "dirpath"
0046    TGETS    9   3  28  ; "nowrap"
0047    TSETS    9   3  36  ; "path"
0048    TGETS    9   3  28  ; "nowrap"
0049    TSETS    9   3  37  ; "url"
0050    FNEW     9  39      ; bidi.lua:225
0051    TSETS    9   3  38  ; "_filename_ltr"
0052    FNEW     9  41      ; bidi.lua:240
0053    TSETS    9   3  40  ; "_filename_rtl"
0054    FNEW     9  43      ; bidi.lua:253
0055    TSETS    9   3  42  ; "_filename_auto_ext_right"
0056    FNEW     9  45      ; bidi.lua:263
0057    TSETS    9   3  44  ; "_path"
0058    FNEW     9  47      ; bidi.lua:276
0059    TSETS    9   3  46  ; "_filepath_ltr"
0060    FNEW     9  49      ; bidi.lua:281
0061    TSETS    9   3  48  ; "_filepath_rtl"
0062    UCLO     0 => 0063
0063 => RET1     3   2

