
main <./frontend/ui/widget/bookstatuswidget.lua:0,0> (241 instructions, 964 bytes at 0x7ff21ac068f0)
0+ params, 37 slots, 0 upvalues, 34 locals, 70 constants, 22 functions
	1	[1]	GETGLOBAL	0 -1	; require
	2	[1]	LOADK    	1 -2	; "ffi/blitbuffer"
	3	[1]	CALL     	0 2 2
	4	[2]	GETGLOBAL	1 -1	; require
	5	[2]	LOADK    	2 -3	; "ui/widget/button"
	6	[2]	CALL     	1 2 2
	7	[3]	GETGLOBAL	2 -1	; require
	8	[3]	LOADK    	3 -4	; "ui/widget/container/centercontainer"
	9	[3]	CALL     	2 2 2
	10	[4]	GETGLOBAL	3 -1	; require
	11	[4]	LOADK    	4 -5	; "ui/widget/closebutton"
	12	[4]	CALL     	3 2 2
	13	[5]	GETGLOBAL	4 -1	; require
	14	[5]	LOADK    	5 -6	; "device"
	15	[5]	CALL     	4 2 2
	16	[6]	GETGLOBAL	5 -1	; require
	17	[6]	LOADK    	6 -7	; "ui/font"
	18	[6]	CALL     	5 2 2
	19	[7]	GETGLOBAL	6 -1	; require
	20	[7]	LOADK    	7 -8	; "ui/widget/container/framecontainer"
	21	[7]	CALL     	6 2 2
	22	[8]	GETGLOBAL	7 -1	; require
	23	[8]	LOADK    	8 -9	; "ui/geometry"
	24	[8]	CALL     	7 2 2
	25	[9]	GETGLOBAL	8 -1	; require
	26	[9]	LOADK    	9 -10	; "ui/gesturerange"
	27	[9]	CALL     	8 2 2
	28	[10]	GETGLOBAL	9 -1	; require
	29	[10]	LOADK    	10 -11	; "ui/widget/horizontalgroup"
	30	[10]	CALL     	9 2 2
	31	[11]	GETGLOBAL	10 -1	; require
	32	[11]	LOADK    	11 -12	; "ui/widget/horizontalspan"
	33	[11]	CALL     	10 2 2
	34	[12]	GETGLOBAL	11 -1	; require
	35	[12]	LOADK    	12 -13	; "ui/widget/imagewidget"
	36	[12]	CALL     	11 2 2
	37	[13]	GETGLOBAL	12 -1	; require
	38	[13]	LOADK    	13 -14	; "ui/widget/container/inputcontainer"
	39	[13]	CALL     	12 2 2
	40	[14]	GETGLOBAL	13 -1	; require
	41	[14]	LOADK    	14 -15	; "ui/widget/inputdialog"
	42	[14]	CALL     	13 2 2
	43	[15]	GETGLOBAL	14 -1	; require
	44	[15]	LOADK    	15 -16	; "ui/widget/inputtext"
	45	[15]	CALL     	14 2 2
	46	[16]	GETGLOBAL	15 -1	; require
	47	[16]	LOADK    	16 -17	; "ui/widget/container/leftcontainer"
	48	[16]	CALL     	15 2 2
	49	[17]	GETGLOBAL	16 -1	; require
	50	[17]	LOADK    	17 -18	; "ui/widget/linewidget"
	51	[17]	CALL     	16 2 2
	52	[18]	GETGLOBAL	17 -1	; require
	53	[18]	LOADK    	18 -19	; "ui/widget/overlapgroup"
	54	[18]	CALL     	17 2 2
	55	[19]	GETGLOBAL	18 -1	; require
	56	[19]	LOADK    	19 -20	; "ui/widget/progresswidget"
	57	[19]	CALL     	18 2 2
	58	[20]	GETGLOBAL	19 -1	; require
	59	[20]	LOADK    	20 -21	; "ui/renderimage"
	60	[20]	CALL     	19 2 2
	61	[21]	GETGLOBAL	20 -1	; require
	62	[21]	LOADK    	21 -22	; "ui/size"
	63	[21]	CALL     	20 2 2
	64	[22]	GETGLOBAL	21 -1	; require
	65	[22]	LOADK    	22 -23	; "ui/widget/textboxwidget"
	66	[22]	CALL     	21 2 2
	67	[23]	GETGLOBAL	22 -1	; require
	68	[23]	LOADK    	23 -24	; "ui/widget/textwidget"
	69	[23]	CALL     	22 2 2
	70	[24]	GETGLOBAL	23 -1	; require
	71	[24]	LOADK    	24 -25	; "ui/timeval"
	72	[24]	CALL     	23 2 2
	73	[25]	GETGLOBAL	24 -1	; require
	74	[25]	LOADK    	25 -26	; "ui/widget/toggleswitch"
	75	[25]	CALL     	24 2 2
	76	[26]	GETGLOBAL	25 -1	; require
	77	[26]	LOADK    	26 -27	; "ui/uimanager"
	78	[26]	CALL     	25 2 2
	79	[27]	GETGLOBAL	26 -1	; require
	80	[27]	LOADK    	27 -28	; "ui/widget/verticalgroup"
	81	[27]	CALL     	26 2 2
	82	[28]	GETGLOBAL	27 -1	; require
	83	[28]	LOADK    	28 -29	; "ui/widget/verticalspan"
	84	[28]	CALL     	27 2 2
	85	[29]	GETGLOBAL	28 -1	; require
	86	[29]	LOADK    	29 -30	; "util"
	87	[29]	CALL     	28 2 2
	88	[30]	GETGLOBAL	29 -1	; require
	89	[30]	LOADK    	30 -31	; "gettext"
	90	[30]	CALL     	29 2 2
	91	[31]	GETTABLE 	30 4 -32	; "screen"
	92	[32]	GETGLOBAL	31 -1	; require
	93	[32]	LOADK    	32 -33	; "ffi/util"
	94	[32]	CALL     	31 2 2
	95	[32]	GETTABLE 	31 31 -34	; "template"
	96	[34]	NEWTABLE 	32 0 0
	97	[44]	SELF     	33 12 -35	; "new"
	98	[44]	NEWTABLE 	35 0 6
	99	[45]	GETTABLE 	36 20 -36	; "padding"
	100	[45]	GETTABLE 	36 36 -37	; "fullscreen"
	101	[45]	SETTABLE 	35 -36 36	; "padding" -
	102	[46]	SETTABLE 	35 -38 -39	; "settings" nil
	103	[47]	SETTABLE 	35 -40 -39	; "thumbnail" nil
	104	[48]	SETTABLE 	35 -41 -39	; "props" nil
	105	[49]	NEWTABLE 	36 0 0
	106	[49]	SETTABLE 	35 -42 36	; "star" -
	107	[50]	NEWTABLE 	36 0 4
	108	[51]	SETTABLE 	36 -44 -39	; "rating" nil
	109	[52]	SETTABLE 	36 -45 -39	; "note" nil
	110	[53]	SETTABLE 	36 -46 -47	; "status" ""
	111	[54]	SETTABLE 	36 -48 -47	; "modified" ""
	112	[55]	SETTABLE 	35 -43 36	; "summary" -
	113	[44]	CALL     	33 3 2
	114	[132]	CLOSURE  	34 0	; 0x7ff21ac070f0
	115	[132]	MOVE     	0 28
	116	[132]	MOVE     	0 32
	117	[132]	MOVE     	0 5
	118	[132]	MOVE     	0 1
	119	[132]	MOVE     	0 4
	120	[132]	MOVE     	0 8
	121	[132]	MOVE     	0 30
	122	[132]	MOVE     	0 6
	123	[132]	MOVE     	0 0
	124	[58]	SETTABLE 	33 -49 34	; "init" -
	125	[136]	CLOSURE  	34 1	; 0x7ff21ac089e0
	126	[134]	SETTABLE 	33 -50 34	; "getStats" -
	127	[144]	CLOSURE  	34 2	; 0x7ff21ac08bc0
	128	[144]	MOVE     	0 32
	129	[144]	MOVE     	0 29
	130	[138]	SETTABLE 	33 -51 34	; "getStatDays" -
	131	[152]	CLOSURE  	34 3	; 0x7ff21ac08d80
	132	[152]	MOVE     	0 32
	133	[152]	MOVE     	0 28
	134	[152]	MOVE     	0 29
	135	[146]	SETTABLE 	33 -52 34	; "getStatHours" -
	136	[160]	CLOSURE  	34 4	; 0x7ff21ac077b0
	137	[160]	MOVE     	0 32
	138	[160]	MOVE     	0 29
	139	[154]	SETTABLE 	33 -53 34	; "getStatReadPages" -
	140	[185]	CLOSURE  	34 5	; 0x7ff21ac097f0
	141	[185]	MOVE     	0 29
	142	[185]	MOVE     	0 3
	143	[185]	MOVE     	0 26
	144	[185]	MOVE     	0 17
	145	[185]	MOVE     	0 7
	146	[185]	MOVE     	0 20
	147	[162]	SETTABLE 	33 -54 34	; "getStatusContent" -
	148	[231]	CLOSURE  	34 6	; 0x7ff21ac09b40
	149	[231]	MOVE     	0 30
	150	[231]	MOVE     	0 20
	151	[231]	MOVE     	0 22
	152	[231]	MOVE     	0 0
	153	[231]	MOVE     	0 10
	154	[231]	MOVE     	0 15
	155	[231]	MOVE     	0 7
	156	[231]	MOVE     	0 16
	157	[231]	MOVE     	0 27
	158	[231]	MOVE     	0 26
	159	[231]	MOVE     	0 9
	160	[187]	SETTABLE 	33 -55 34	; "genHeader" -
	161	[239]	CLOSURE  	34 7	; 0x7ff21ac086f0
	162	[239]	MOVE     	0 23
	163	[233]	SETTABLE 	33 -56 34	; "onChangeBookStatus" -
	164	[248]	CLOSURE  	34 8	; 0x7ff21ac09670
	165	[248]	MOVE     	0 2
	166	[248]	MOVE     	0 7
	167	[241]	SETTABLE 	33 -57 34	; "generateRateGroup" -
	168	[279]	CLOSURE  	34 9	; 0x7ff21ac0af40
	169	[279]	MOVE     	0 9
	170	[279]	MOVE     	0 25
	171	[250]	SETTABLE 	33 -58 34	; "setStar" -
	172	[398]	CLOSURE  	34 10	; 0x7ff21ac0b5a0
	173	[398]	MOVE     	0 30
	174	[398]	MOVE     	0 26
	175	[398]	MOVE     	0 27
	176	[398]	MOVE     	0 21
	177	[398]	MOVE     	0 2
	178	[398]	MOVE     	0 7
	179	[398]	MOVE     	0 18
	180	[398]	MOVE     	0 22
	181	[398]	MOVE     	0 31
	182	[398]	MOVE     	0 29
	183	[398]	MOVE     	0 9
	184	[398]	MOVE     	0 10
	185	[398]	MOVE     	0 19
	186	[398]	MOVE     	0 11
	187	[281]	SETTABLE 	33 -59 34	; "genBookInfoGroup" -
	188	[466]	CLOSURE  	34 11	; 0x7ff21ac0bef0
	189	[466]	MOVE     	0 30
	190	[466]	MOVE     	0 2
	191	[466]	MOVE     	0 7
	192	[466]	MOVE     	0 26
	193	[466]	MOVE     	0 9
	194	[466]	MOVE     	0 22
	195	[466]	MOVE     	0 29
	196	[400]	SETTABLE 	33 -60 34	; "genStatisticsGroup" -
	197	[498]	CLOSURE  	34 12	; 0x7ff21ac0c7e0
	198	[498]	MOVE     	0 30
	199	[498]	MOVE     	0 20
	200	[498]	MOVE     	0 14
	201	[498]	MOVE     	0 29
	202	[498]	MOVE     	0 26
	203	[498]	MOVE     	0 27
	204	[498]	MOVE     	0 2
	205	[498]	MOVE     	0 7
	206	[468]	SETTABLE 	33 -61 34	; "genSummaryGroup" -
	207	[504]	CLOSURE  	34 13	; 0x7ff21ac0cca0
	208	[500]	SETTABLE 	33 -62 34	; "onUpdateNote" -
	209	[511]	CLOSURE  	34 14	; 0x7ff21ac0cee0
	210	[506]	SETTABLE 	33 -63 34	; "saveSummary" -
	211	[574]	CLOSURE  	34 15	; 0x7ff21ac0d110
	212	[574]	MOVE     	0 30
	213	[574]	MOVE     	0 29
	214	[574]	MOVE     	0 24
	215	[574]	MOVE     	0 26
	216	[574]	MOVE     	0 27
	217	[574]	MOVE     	0 2
	218	[574]	MOVE     	0 7
	219	[513]	SETTABLE 	33 -64 34	; "generateSwitchGroup" -
	220	[583]	CLOSURE  	34 16	; 0x7ff21ac0e200
	221	[583]	MOVE     	0 25
	222	[576]	SETTABLE 	33 -65 34	; "onConfigChoose" -
	223	[588]	CLOSURE  	34 17	; 0x7ff21ac09070
	224	[586]	SETTABLE 	33 -66 34	; "onAnyKeyPressed" -
	225	[604]	CLOSURE  	34 18	; 0x7ff21ac0ea80
	226	[604]	MOVE     	0 25
	227	[590]	SETTABLE 	33 -67 34	; "onSwipe" -
	228	[611]	CLOSURE  	34 19	; 0x7ff21ac0ed60
	229	[611]	MOVE     	0 25
	230	[606]	SETTABLE 	33 -68 34	; "onClose" -
	231	[644]	CLOSURE  	34 20	; 0x7ff21ac0ef30
	232	[644]	MOVE     	0 13
	233	[644]	MOVE     	0 29
	234	[644]	MOVE     	0 30
	235	[644]	MOVE     	0 25
	236	[613]	SETTABLE 	33 -69 34	; "onSwitchFocus" -
	237	[648]	CLOSURE  	34 21	; 0x7ff21ac0fe60
	238	[648]	MOVE     	0 25
	239	[646]	SETTABLE 	33 -70 34	; "closeInputDialog" -
	240	[650]	RETURN   	33 2
	241	[650]	RETURN   	0 1

function <./frontend/ui/widget/bookstatuswidget.lua:58,132> (127 instructions, 508 bytes at 0x7ff21ac070f0)
1 param, 9 slots, 9 upvalues, 5 locals, 62 constants, 1 function
	1	[59]	GETTABLE 	1 0 -1	; "settings"
	2	[59]	TEST     	1 0 0
	3	[59]	JMP      	24	; to 28
	4	[61]	NEWTABLE 	1 0 4
	5	[62]	SETTABLE 	1 -2 -3	; "rating" nil
	6	[63]	SETTABLE 	1 -4 -3	; "note" nil
	7	[64]	SETTABLE 	1 -5 -6	; "status" ""
	8	[65]	SETTABLE 	1 -7 -6	; "modified" ""
	9	[67]	GETTABLE 	2 0 -1	; "settings"
	10	[67]	SELF     	2 2 -8	; "readSetting"
	11	[67]	LOADK    	4 -9	; "summary"
	12	[67]	CALL     	2 3 2
	13	[69]	TEST     	2 0 0
	14	[69]	JMP      	12	; to 27
	15	[70]	GETTABLE 	3 2 -7	; "modified"
	16	[70]	TEST     	3 0 0
	17	[70]	JMP      	2	; to 20
	18	[72]	SETTABLE 	0 -9 2	; "summary" -
	19	[72]	JMP      	8	; to 28
	20	[75]	SETTABLE 	0 -9 1	; "summary" -
	21	[76]	GETUPVAL 	3 0	; util
	22	[76]	GETTABLE 	3 3 -10	; "tableMerge"
	23	[76]	GETTABLE 	4 0 -9	; "summary"
	24	[76]	MOVE     	5 2
	25	[76]	CALL     	3 3 1
	26	[77]	JMP      	1	; to 28
	27	[79]	SETTABLE 	0 -9 1	; "summary" -
	28	[82]	GETTABLE 	1 0 -12	; "view"
	29	[82]	GETTABLE 	1 1 -13	; "document"
	30	[82]	SELF     	1 1 -14	; "getPageCount"
	31	[82]	CALL     	1 2 2
	32	[82]	SETTABLE 	0 -11 1	; "total_pages" -
	33	[83]	SELF     	1 0 -15	; "getStats"
	34	[83]	CALL     	1 2 2
	35	[83]	SETUPVAL 	1 1	; stats_book
	36	[85]	GETUPVAL 	1 2	; Font
	37	[85]	SELF     	1 1 -17	; "getFace"
	38	[85]	LOADK    	3 -18	; "smallffont"
	39	[85]	CALL     	1 3 2
	40	[85]	SETTABLE 	0 -16 1	; "small_font_face" -
	41	[86]	GETUPVAL 	1 2	; Font
	42	[86]	SELF     	1 1 -17	; "getFace"
	43	[86]	LOADK    	3 -20	; "ffont"
	44	[86]	CALL     	1 3 2
	45	[86]	SETTABLE 	0 -19 1	; "medium_font_face" -
	46	[87]	GETUPVAL 	1 2	; Font
	47	[87]	SELF     	1 1 -17	; "getFace"
	48	[87]	LOADK    	3 -22	; "largeffont"
	49	[87]	CALL     	1 3 2
	50	[87]	SETTABLE 	0 -21 1	; "large_font_face" -
	51	[89]	LOADBOOL 	1 1 0
	52	[90]	GETTABLE 	2 0 -23	; "readonly"
	53	[90]	TEST     	2 0 0
	54	[90]	JMP      	1	; to 56
	55	[91]	LOADBOOL 	1 0 0
	56	[94]	GETUPVAL 	2 3	; Button
	57	[94]	SELF     	2 2 -25	; "new"
	58	[94]	NEWTABLE 	4 0 7
	59	[95]	SETTABLE 	4 -26 -27	; "icon" "resources/icons/stats.star.empty.png"
	60	[96]	SETTABLE 	4 -28 -29	; "bordersize" 0
	61	[97]	SETTABLE 	4 -30 -29	; "radius" 0
	62	[98]	SETTABLE 	4 -31 -29	; "margin" 0
	63	[99]	SETTABLE 	4 -32 1	; "enabled" -
	64	[100]	SETTABLE 	4 -33 0	; "show_parent" -
	65	[101]	GETTABLE 	5 0 -23	; "readonly"
	66	[101]	SETTABLE 	4 -23 5	; "readonly" -
	67	[94]	CALL     	2 3 2
	68	[102]	SETTABLE 	0 -24 2	; "star" -
	69	[104]	GETUPVAL 	2 4	; Device
	70	[104]	SELF     	2 2 -34	; "hasKeys"
	71	[104]	CALL     	2 2 2
	72	[104]	TEST     	2 0 0
	73	[104]	JMP      	13	; to 87
	74	[105]	NEWTABLE 	2 0 1
	75	[107]	NEWTABLE 	3 1 2
	76	[107]	NEWTABLE 	4 1 0
	77	[107]	GETUPVAL 	5 4	; Device
	78	[107]	GETTABLE 	5 5 -37	; "input"
	79	[107]	GETTABLE 	5 5 -38	; "group"
	80	[107]	GETTABLE 	5 5 -39	; "Any"
	81	[107]	SETLIST  	4 1 1	; 1
	82	[108]	SETTABLE 	3 -40 -41	; "seqtext" "any key"
	83	[108]	SETTABLE 	3 -42 -43	; "doc" "close dialog"
	84	[108]	SETLIST  	3 1 1	; 1
	85	[108]	SETTABLE 	2 -36 3	; "AnyKeyPressed" -
	86	[109]	SETTABLE 	0 -35 2	; "key_events" -
	87	[111]	GETUPVAL 	2 4	; Device
	88	[111]	SELF     	2 2 -44	; "isTouchDevice"
	89	[111]	CALL     	2 2 2
	90	[111]	TEST     	2 0 0
	91	[111]	JMP      	12	; to 104
	92	[112]	GETTABLE 	2 0 -45	; "ges_events"
	93	[112]	NEWTABLE 	3 0 0
	94	[113]	GETUPVAL 	4 5	; GestureRange
	95	[113]	SELF     	4 4 -25	; "new"
	96	[113]	NEWTABLE 	6 0 2
	97	[114]	SETTABLE 	6 -47 -48	; "ges" "swipe"
	98	[115]	CLOSURE  	7 0	; 0x7ff21ac085a0
	99	[115]	MOVE     	0 0
	100	[115]	SETTABLE 	6 -49 7	; "range" -
	101	[113]	CALL     	4 3 0
	102	[117]	SETLIST  	3 0 1	; 1
	103	[117]	SETTABLE 	2 -46 3	; "Swipe" -
	104	[120]	GETUPVAL 	2 6	; Screen
	105	[120]	SELF     	2 2 -50	; "getSize"
	106	[120]	CALL     	2 2 2
	107	[121]	SETTABLE 	0 -51 -52	; "covers_fullscreen" true
	108	[122]	GETUPVAL 	3 7	; FrameContainer
	109	[122]	SELF     	3 3 -25	; "new"
	110	[122]	NEWTABLE 	5 0 5
	111	[123]	GETTABLE 	6 2 -55	; "w"
	112	[123]	SETTABLE 	5 -54 6	; "width" -
	113	[124]	GETTABLE 	6 2 -57	; "h"
	114	[124]	SETTABLE 	5 -56 6	; "height" -
	115	[125]	GETUPVAL 	6 8	; Blitbuffer
	116	[125]	GETTABLE 	6 6 -59	; "COLOR_WHITE"
	117	[125]	SETTABLE 	5 -58 6	; "background" -
	118	[126]	SETTABLE 	5 -28 -29	; "bordersize" 0
	119	[127]	SETTABLE 	5 -60 -29	; "padding" 0
	120	[128]	SELF     	6 0 -61	; "getStatusContent"
	121	[128]	GETTABLE 	8 2 -55	; "w"
	122	[128]	CALL     	6 3 0
	123	[129]	SETLIST  	5 0 1	; 1
	124	[122]	CALL     	3 3 2
	125	[129]	SETTABLE 	0 -53 3	; 1 -
	126	[131]	SETTABLE 	0 -62 -52	; "dithered" true
	127	[132]	RETURN   	0 1

function <./frontend/ui/widget/bookstatuswidget.lua:115,115> (4 instructions, 16 bytes at 0x7ff21ac085a0)
0 params, 2 slots, 1 upvalue, 0 locals, 1 constant, 0 functions
	1	[115]	GETUPVAL 	0 0	; self
	2	[115]	GETTABLE 	0 0 -1	; "dimen"
	3	[115]	RETURN   	0 2
	4	[115]	RETURN   	0 1

function <./frontend/ui/widget/bookstatuswidget.lua:134,136> (3 instructions, 12 bytes at 0x7ff21ac089e0)
1 param, 2 slots, 0 upvalues, 1 local, 0 constants, 0 functions
	1	[135]	NEWTABLE 	1 0 0
	2	[135]	RETURN   	1 2
	3	[136]	RETURN   	0 1

function <./frontend/ui/widget/bookstatuswidget.lua:138,144> (15 instructions, 60 bytes at 0x7ff21ac08bc0)
1 param, 3 slots, 2 upvalues, 1 local, 3 constants, 0 functions
	1	[139]	GETUPVAL 	1 0	; stats_book
	2	[139]	GETTABLE 	1 1 -1	; "days"
	3	[139]	TEST     	1 0 0
	4	[139]	JMP      	6	; to 11
	5	[140]	GETGLOBAL	1 -2	; tostring
	6	[140]	GETUPVAL 	2 0	; stats_book
	7	[140]	GETTABLE 	2 2 -1	; "days"
	8	[140]	TAILCALL 	1 2 0
	9	[140]	RETURN   	1 0
	10	[140]	JMP      	4	; to 15
	11	[142]	GETUPVAL 	1 1	; _
	12	[142]	LOADK    	2 -3	; "N/A"
	13	[142]	TAILCALL 	1 2 0
	14	[142]	RETURN   	1 0
	15	[144]	RETURN   	0 1

function <./frontend/ui/widget/bookstatuswidget.lua:146,152> (17 instructions, 68 bytes at 0x7ff21ac08d80)
1 param, 4 slots, 3 upvalues, 1 local, 3 constants, 0 functions
	1	[147]	GETUPVAL 	1 0	; stats_book
	2	[147]	GETTABLE 	1 1 -1	; "time"
	3	[147]	TEST     	1 0 0
	4	[147]	JMP      	8	; to 13
	5	[148]	GETUPVAL 	1 1	; util
	6	[148]	GETTABLE 	1 1 -2	; "secondsToClock"
	7	[148]	GETUPVAL 	2 0	; stats_book
	8	[148]	GETTABLE 	2 2 -1	; "time"
	9	[148]	LOADBOOL 	3 0 0
	10	[148]	TAILCALL 	1 3 0
	11	[148]	RETURN   	1 0
	12	[148]	JMP      	4	; to 17
	13	[150]	GETUPVAL 	1 2	; _
	14	[150]	LOADK    	2 -3	; "N/A"
	15	[150]	TAILCALL 	1 2 0
	16	[150]	RETURN   	1 0
	17	[152]	RETURN   	0 1

function <./frontend/ui/widget/bookstatuswidget.lua:154,160> (18 instructions, 72 bytes at 0x7ff21ac077b0)
1 param, 5 slots, 2 upvalues, 1 local, 6 constants, 0 functions
	1	[155]	GETUPVAL 	1 0	; stats_book
	2	[155]	GETTABLE 	1 1 -1	; "pages"
	3	[155]	TEST     	1 0 0
	4	[155]	JMP      	9	; to 14
	5	[156]	GETGLOBAL	1 -2	; string
	6	[156]	GETTABLE 	1 1 -3	; "format"
	7	[156]	LOADK    	2 -4	; "%s/%s"
	8	[156]	GETUPVAL 	3 0	; stats_book
	9	[156]	GETTABLE 	3 3 -1	; "pages"
	10	[156]	GETTABLE 	4 0 -5	; "total_pages"
	11	[156]	TAILCALL 	1 4 0
	12	[156]	RETURN   	1 0
	13	[156]	JMP      	4	; to 18
	14	[158]	GETUPVAL 	1 1	; _
	15	[158]	LOADK    	2 -6	; "N/A"
	16	[158]	TAILCALL 	1 2 0
	17	[158]	RETURN   	1 0
	18	[160]	RETURN   	0 1

function <./frontend/ui/widget/bookstatuswidget.lua:162,185> (66 instructions, 264 bytes at 0x7ff21ac097f0)
2 params, 17 slots, 6 upvalues, 5 locals, 20 constants, 0 functions
	1	[164]	SELF     	3 0 -1	; "genHeader"
	2	[164]	GETUPVAL 	5 0	; _
	3	[164]	LOADK    	6 -2	; "Book Status"
	4	[164]	CALL     	5 2 0
	5	[164]	CALL     	3 0 2
	6	[166]	GETTABLE 	4 0 -3	; "readonly"
	7	[166]	EQ       	1 4 -4	; - true
	8	[166]	JMP      	12	; to 21
	9	[167]	GETUPVAL 	4 1	; CloseButton
	10	[167]	SELF     	4 4 -5	; "new"
	11	[167]	NEWTABLE 	6 0 1
	12	[167]	SETTABLE 	6 -6 0	; "window" -
	13	[167]	CALL     	4 3 2
	14	[167]	MOVE     	2 4
	15	[168]	SELF     	4 0 -1	; "genHeader"
	16	[168]	GETUPVAL 	6 0	; _
	17	[168]	LOADK    	7 -7	; "Update Status"
	18	[168]	CALL     	6 2 0
	19	[168]	CALL     	4 0 2
	20	[168]	MOVE     	3 4
	21	[170]	GETUPVAL 	4 2	; VerticalGroup
	22	[170]	SELF     	4 4 -5	; "new"
	23	[170]	NEWTABLE 	6 7 1
	24	[171]	SETTABLE 	6 -8 -9	; "align" "left"
	25	[172]	GETUPVAL 	7 3	; OverlapGroup
	26	[172]	SELF     	7 7 -5	; "new"
	27	[172]	NEWTABLE 	9 1 1
	28	[173]	GETUPVAL 	10 4	; Geom
	29	[173]	SELF     	10 10 -5	; "new"
	30	[173]	NEWTABLE 	12 0 2
	31	[173]	SETTABLE 	12 -11 1	; "w" -
	32	[173]	GETUPVAL 	13 5	; Size
	33	[173]	GETTABLE 	13 13 -13	; "item"
	34	[173]	GETTABLE 	13 13 -14	; "height_default"
	35	[173]	SETTABLE 	12 -12 13	; "h" -
	36	[173]	CALL     	10 3 2
	37	[173]	SETTABLE 	9 -10 10	; "dimen" -
	38	[175]	MOVE     	10 2
	39	[175]	SETLIST  	9 1 1	; 1
	40	[172]	CALL     	7 3 2
	41	[176]	SELF     	8 0 -15	; "genBookInfoGroup"
	42	[176]	CALL     	8 2 2
	43	[177]	SELF     	9 0 -1	; "genHeader"
	44	[177]	GETUPVAL 	11 0	; _
	45	[177]	LOADK    	12 -16	; "Statistics"
	46	[177]	CALL     	11 2 0
	47	[177]	CALL     	9 0 2
	48	[178]	SELF     	10 0 -17	; "genStatisticsGroup"
	49	[178]	MOVE     	12 1
	50	[178]	CALL     	10 3 2
	51	[179]	SELF     	11 0 -1	; "genHeader"
	52	[179]	GETUPVAL 	13 0	; _
	53	[179]	LOADK    	14 -18	; "Review"
	54	[179]	CALL     	13 2 0
	55	[179]	CALL     	11 0 2
	56	[180]	SELF     	12 0 -19	; "genSummaryGroup"
	57	[180]	MOVE     	14 1
	58	[180]	CALL     	12 3 2
	59	[181]	MOVE     	13 3
	60	[182]	SELF     	14 0 -20	; "generateSwitchGroup"
	61	[182]	MOVE     	16 1
	62	[182]	CALL     	14 3 0
	63	[183]	SETLIST  	6 0 1	; 1
	64	[170]	CALL     	4 3 2
	65	[184]	RETURN   	4 2
	66	[185]	RETURN   	0 1

function <./frontend/ui/widget/bookstatuswidget.lua:187,231> (124 instructions, 496 bytes at 0x7ff21ac09b40)
2 params, 24 slots, 11 upvalues, 10 locals, 27 constants, 0 functions
	1	[188]	GETUPVAL 	2 0	; Screen
	2	[188]	SELF     	2 2 -1	; "getWidth"
	3	[188]	CALL     	2 2 2
	4	[188]	GETUPVAL 	3 1	; Size
	5	[188]	GETTABLE 	3 3 -2	; "item"
	6	[188]	GETTABLE 	3 3 -3	; "height_default"
	7	[190]	GETUPVAL 	4 2	; TextWidget
	8	[190]	SELF     	4 4 -4	; "new"
	9	[190]	NEWTABLE 	6 0 3
	10	[191]	SETTABLE 	6 -5 1	; "text" -
	11	[192]	GETTABLE 	7 0 -7	; "medium_font_face"
	12	[192]	SETTABLE 	6 -6 7	; "face" -
	13	[193]	GETUPVAL 	7 3	; Blitbuffer
	14	[193]	GETTABLE 	7 7 -9	; "COLOR_WEB_GRAY"
	15	[193]	SETTABLE 	6 -8 7	; "fgcolor" -
	16	[190]	CALL     	4 3 2
	17	[196]	GETUPVAL 	5 4	; HorizontalSpan
	18	[196]	SELF     	5 5 -4	; "new"
	19	[196]	NEWTABLE 	7 0 1
	20	[196]	GETTABLE 	8 0 -11	; "padding"
	21	[196]	SETTABLE 	7 -10 8	; "width" -
	22	[196]	CALL     	5 3 2
	23	[197]	SELF     	6 4 -12	; "getSize"
	24	[197]	CALL     	6 2 2
	25	[197]	GETTABLE 	6 6 -13	; "w"
	26	[197]	SUB      	6 2 6
	27	[197]	DIV      	6 6 -14	; - 2
	28	[197]	GETTABLE 	7 0 -11	; "padding"
	29	[197]	MUL      	7 7 -14	; - 2
	30	[197]	SUB      	6 6 7
	31	[198]	GETUPVAL 	7 5	; LeftContainer
	32	[198]	SELF     	7 7 -4	; "new"
	33	[198]	NEWTABLE 	9 0 1
	34	[199]	GETUPVAL 	10 6	; Geom
	35	[199]	SELF     	10 10 -4	; "new"
	36	[199]	NEWTABLE 	12 0 2
	37	[199]	SETTABLE 	12 -13 6	; "w" -
	38	[199]	SETTABLE 	12 -16 3	; "h" -
	39	[199]	CALL     	10 3 2
	40	[199]	SETTABLE 	9 -15 10	; "dimen" -
	41	[200]	GETUPVAL 	10 7	; LineWidget
	42	[200]	SELF     	10 10 -4	; "new"
	43	[200]	NEWTABLE 	12 0 2
	44	[201]	GETUPVAL 	13 3	; Blitbuffer
	45	[201]	GETTABLE 	13 13 -18	; "COLOR_LIGHT_GRAY"
	46	[201]	SETTABLE 	12 -17 13	; "background" -
	47	[202]	GETUPVAL 	13 6	; Geom
	48	[202]	SELF     	13 13 -4	; "new"
	49	[202]	NEWTABLE 	15 0 2
	50	[203]	SETTABLE 	15 -13 6	; "w" -
	51	[204]	GETUPVAL 	16 1	; Size
	52	[204]	GETTABLE 	16 16 -19	; "line"
	53	[204]	GETTABLE 	16 16 -20	; "thick"
	54	[204]	SETTABLE 	15 -16 16	; "h" -
	55	[202]	CALL     	13 3 2
	56	[205]	SETTABLE 	12 -15 13	; "dimen" -
	57	[200]	CALL     	10 3 0
	58	[207]	SETLIST  	9 0 1	; 1
	59	[198]	CALL     	7 3 2
	60	[208]	LOADNIL  	8 9
	61	[209]	GETUPVAL 	10 0	; Screen
	62	[209]	SELF     	10 10 -21	; "getScreenMode"
	63	[209]	CALL     	10 2 2
	64	[209]	EQ       	0 10 -22	; - "landscape"
	65	[209]	JMP      	19	; to 85
	66	[210]	GETUPVAL 	10 8	; VerticalSpan
	67	[210]	SELF     	10 10 -4	; "new"
	68	[210]	NEWTABLE 	12 0 1
	69	[210]	GETUPVAL 	13 1	; Size
	70	[210]	GETTABLE 	13 13 -23	; "span"
	71	[210]	GETTABLE 	13 13 -24	; "horizontal_default"
	72	[210]	SETTABLE 	12 -10 13	; "width" -
	73	[210]	CALL     	10 3 2
	74	[210]	MOVE     	8 10
	75	[211]	GETUPVAL 	10 8	; VerticalSpan
	76	[211]	SELF     	10 10 -4	; "new"
	77	[211]	NEWTABLE 	12 0 1
	78	[211]	GETUPVAL 	13 1	; Size
	79	[211]	GETTABLE 	13 13 -23	; "span"
	80	[211]	GETTABLE 	13 13 -24	; "horizontal_default"
	81	[211]	SETTABLE 	12 -10 13	; "width" -
	82	[211]	CALL     	10 3 2
	83	[211]	MOVE     	9 10
	84	[211]	JMP      	18	; to 103
	85	[213]	GETUPVAL 	10 8	; VerticalSpan
	86	[213]	SELF     	10 10 -4	; "new"
	87	[213]	NEWTABLE 	12 0 1
	88	[213]	GETUPVAL 	13 1	; Size
	89	[213]	GETTABLE 	13 13 -2	; "item"
	90	[213]	GETTABLE 	13 13 -3	; "height_default"
	91	[213]	SETTABLE 	12 -10 13	; "width" -
	92	[213]	CALL     	10 3 2
	93	[213]	MOVE     	8 10
	94	[214]	GETUPVAL 	10 8	; VerticalSpan
	95	[214]	SELF     	10 10 -4	; "new"
	96	[214]	NEWTABLE 	12 0 1
	97	[214]	GETUPVAL 	13 1	; Size
	98	[214]	GETTABLE 	13 13 -23	; "span"
	99	[214]	GETTABLE 	13 13 -25	; "vertical_large"
	100	[214]	SETTABLE 	12 -10 13	; "width" -
	101	[214]	CALL     	10 3 2
	102	[214]	MOVE     	9 10
	103	[217]	GETUPVAL 	10 9	; VerticalGroup
	104	[217]	SELF     	10 10 -4	; "new"
	105	[217]	NEWTABLE 	12 3 0
	106	[218]	MOVE     	13 8
	107	[219]	GETUPVAL 	14 10	; HorizontalGroup
	108	[219]	SELF     	14 14 -4	; "new"
	109	[219]	NEWTABLE 	16 7 1
	110	[220]	SETTABLE 	16 -26 -27	; "align" "center"
	111	[221]	MOVE     	17 5
	112	[222]	MOVE     	18 7
	113	[223]	MOVE     	19 5
	114	[224]	MOVE     	20 4
	115	[225]	MOVE     	21 5
	116	[226]	MOVE     	22 7
	117	[228]	MOVE     	23 5
	118	[228]	SETLIST  	16 7 1	; 1
	119	[219]	CALL     	14 3 2
	120	[230]	MOVE     	15 9
	121	[230]	SETLIST  	12 3 1	; 1
	122	[217]	TAILCALL 	10 3 0
	123	[230]	RETURN   	10 0
	124	[231]	RETURN   	0 1

function <./frontend/ui/widget/bookstatuswidget.lua:233,239> (18 instructions, 72 bytes at 0x7ff21ac086f0)
3 params, 8 slots, 1 upvalue, 4 locals, 9 constants, 0 functions
	1	[234]	GETUPVAL 	3 0	; TimeVal
	2	[234]	SELF     	3 3 -1	; "now"
	3	[234]	CALL     	3 2 2
	4	[235]	GETTABLE 	4 0 -2	; "summary"
	5	[235]	GETTABLE 	5 1 2
	6	[235]	SETTABLE 	4 -3 5	; "status" -
	7	[236]	GETTABLE 	4 0 -2	; "summary"
	8	[236]	GETGLOBAL	5 -5	; os
	9	[236]	GETTABLE 	5 5 -6	; "date"
	10	[236]	LOADK    	6 -7	; "%Y-%m-%d"
	11	[236]	GETTABLE 	7 3 -8	; "sec"
	12	[236]	CALL     	5 3 2
	13	[236]	SETTABLE 	4 -4 5	; "modified" -
	14	[237]	SELF     	4 0 -9	; "saveSummary"
	15	[237]	CALL     	4 2 1
	16	[238]	LOADBOOL 	4 1 0
	17	[238]	RETURN   	4 2
	18	[239]	RETURN   	0 1

function <./frontend/ui/widget/bookstatuswidget.lua:241,248> (18 instructions, 72 bytes at 0x7ff21ac09670)
4 params, 10 slots, 2 upvalues, 4 locals, 6 constants, 0 functions
	1	[242]	GETUPVAL 	4 0	; CenterContainer
	2	[242]	SELF     	4 4 -2	; "new"
	3	[242]	NEWTABLE 	6 0 1
	4	[243]	GETUPVAL 	7 1	; Geom
	5	[243]	SELF     	7 7 -2	; "new"
	6	[243]	NEWTABLE 	9 0 2
	7	[243]	SETTABLE 	9 -4 1	; "w" -
	8	[243]	SETTABLE 	9 -5 2	; "h" -
	9	[243]	CALL     	7 3 2
	10	[243]	SETTABLE 	6 -3 7	; "dimen" -
	11	[242]	CALL     	4 3 2
	12	[244]	SETTABLE 	0 -1 4	; "stars_container" -
	13	[246]	SELF     	4 0 -6	; "setStar"
	14	[246]	MOVE     	6 3
	15	[246]	CALL     	4 3 1
	16	[247]	GETTABLE 	4 0 -1	; "stars_container"
	17	[247]	RETURN   	4 2
	18	[248]	RETURN   	0 1

function <./frontend/ui/widget/bookstatuswidget.lua:250,279> (68 instructions, 272 bytes at 0x7ff21ac0af40)
2 params, 13 slots, 2 upvalues, 11 locals, 19 constants, 2 functions
	1	[252]	GETTABLE 	2 0 -1	; "stars_container"
	2	[252]	SELF     	2 2 -2	; "clear"
	3	[252]	CALL     	2 2 1
	4	[254]	GETUPVAL 	2 0	; HorizontalGroup
	5	[254]	SELF     	2 2 -3	; "new"
	6	[254]	NEWTABLE 	4 0 1
	7	[254]	SETTABLE 	4 -4 -5	; "align" "center"
	8	[254]	CALL     	2 3 2
	9	[255]	TEST     	1 0 0
	10	[255]	JMP      	24	; to 35
	11	[256]	GETTABLE 	3 0 -6	; "summary"
	12	[256]	SETTABLE 	3 -7 1	; "rating" -
	13	[257]	SELF     	3 0 -8	; "saveSummary"
	14	[257]	CALL     	3 2 1
	15	[259]	LOADK    	3 -9	; 1
	16	[259]	MOVE     	4 1
	17	[259]	LOADK    	5 -9	; 1
	18	[259]	FORPREP  	3 14	; to 33
	19	[260]	GETGLOBAL	7 -10	; table
	20	[260]	GETTABLE 	7 7 -11	; "insert"
	21	[260]	MOVE     	8 2
	22	[260]	GETTABLE 	9 0 -12	; "star"
	23	[260]	SELF     	9 9 -3	; "new"
	24	[260]	NEWTABLE 	11 0 2
	25	[261]	SETTABLE 	11 -13 -14	; "icon" "resources/icons/stats.star.full.png"
	26	[262]	CLOSURE  	12 0	; 0x7ff21ac0b380
	27	[262]	MOVE     	0 0
	28	[262]	MOVE     	0 6
	29	[262]	SETTABLE 	11 -15 12	; "callback" -
	30	[260]	CALL     	9 3 0
	31	[260]	CALL     	7 0 1
	32	[263]	CLOSE    	6
	33	[259]	FORLOOP  	3 -15	; to 19
	34	[264]	JMP      	1	; to 36
	35	[266]	LOADK    	1 -16	; 0
	36	[269]	ADD      	3 1 -9	; - 1
	37	[269]	LOADK    	4 -17	; 5
	38	[269]	LOADK    	5 -9	; 1
	39	[269]	FORPREP  	3 13	; to 53
	40	[270]	GETGLOBAL	7 -10	; table
	41	[270]	GETTABLE 	7 7 -11	; "insert"
	42	[270]	MOVE     	8 2
	43	[270]	GETTABLE 	9 0 -12	; "star"
	44	[270]	SELF     	9 9 -3	; "new"
	45	[270]	NEWTABLE 	11 0 1
	46	[270]	CLOSURE  	12 1	; 0x7ff21ac0b150
	47	[270]	MOVE     	0 0
	48	[270]	MOVE     	0 6
	49	[270]	SETTABLE 	11 -15 12	; "callback" -
	50	[270]	CALL     	9 3 0
	51	[270]	CALL     	7 0 1
	52	[270]	CLOSE    	6
	53	[269]	FORLOOP  	3 -14	; to 40
	54	[273]	GETGLOBAL	3 -10	; table
	55	[273]	GETTABLE 	3 3 -11	; "insert"
	56	[273]	GETTABLE 	4 0 -1	; "stars_container"
	57	[273]	MOVE     	5 2
	58	[273]	CALL     	3 3 1
	59	[277]	GETUPVAL 	3 1	; UIManager
	60	[277]	SELF     	3 3 -18	; "setDirty"
	61	[277]	MOVE     	5 0
	62	[277]	LOADK    	6 -19	; "ui"
	63	[277]	LOADNIL  	7 7
	64	[277]	LOADBOOL 	8 1 0
	65	[277]	CALL     	3 6 1
	66	[278]	LOADBOOL 	3 1 0
	67	[278]	RETURN   	3 2
	68	[279]	RETURN   	0 1

function <./frontend/ui/widget/bookstatuswidget.lua:262,262> (5 instructions, 20 bytes at 0x7ff21ac0b380)
0 params, 3 slots, 2 upvalues, 0 locals, 1 constant, 0 functions
	1	[262]	GETUPVAL 	0 0	; self
	2	[262]	SELF     	0 0 -1	; "setStar"
	3	[262]	GETUPVAL 	2 1	; i
	4	[262]	CALL     	0 3 1
	5	[262]	RETURN   	0 1

function <./frontend/ui/widget/bookstatuswidget.lua:270,270> (5 instructions, 20 bytes at 0x7ff21ac0b150)
0 params, 3 slots, 2 upvalues, 0 locals, 1 constant, 0 functions
	1	[270]	GETUPVAL 	0 0	; self
	2	[270]	SELF     	0 0 -1	; "setStar"
	3	[270]	GETUPVAL 	2 1	; i
	4	[270]	CALL     	0 3 1
	5	[270]	RETURN   	0 1

function <./frontend/ui/widget/bookstatuswidget.lua:281,398> (306 instructions, 1224 bytes at 0x7ff21ac0b5a0)
1 param, 24 slots, 14 upvalues, 18 locals, 61 constants, 0 functions
	1	[282]	GETUPVAL 	1 0	; Screen
	2	[282]	SELF     	1 1 -1	; "getWidth"
	3	[282]	CALL     	1 2 2
	4	[283]	MUL      	2 1 -2	; - 0.05
	5	[285]	LOADNIL  	3 4
	6	[286]	GETUPVAL 	5 0	; Screen
	7	[286]	SELF     	5 5 -3	; "getScreenMode"
	8	[286]	CALL     	5 2 2
	9	[286]	EQ       	0 5 -4	; - "landscape"
	10	[286]	JMP      	11	; to 22
	11	[287]	GETUPVAL 	5 0	; Screen
	12	[287]	SELF     	5 5 -5	; "scaleBySize"
	13	[287]	LOADK    	7 -6	; 132
	14	[287]	CALL     	5 3 2
	15	[287]	MOVE     	3 5
	16	[288]	GETUPVAL 	5 0	; Screen
	17	[288]	SELF     	5 5 -5	; "scaleBySize"
	18	[288]	LOADK    	7 -7	; 184
	19	[288]	CALL     	5 3 2
	20	[288]	MOVE     	4 5
	21	[288]	JMP      	10	; to 32
	22	[290]	GETUPVAL 	5 0	; Screen
	23	[290]	SELF     	5 5 -5	; "scaleBySize"
	24	[290]	LOADK    	7 -8	; 198
	25	[290]	CALL     	5 3 2
	26	[290]	MOVE     	3 5
	27	[291]	GETUPVAL 	5 0	; Screen
	28	[291]	SELF     	5 5 -5	; "scaleBySize"
	29	[291]	LOADK    	7 -9	; 276
	30	[291]	CALL     	5 3 2
	31	[291]	MOVE     	4 5
	32	[294]	MOVE     	5 4
	33	[295]	SUB      	6 1 2
	34	[295]	SUB      	6 6 3
	35	[299]	LOADNIL  	7 7
	36	[300]	GETTABLE 	8 0 -10	; "props"
	37	[300]	GETTABLE 	8 8 -11	; "language"
	38	[300]	TEST     	8 0 0
	39	[300]	JMP      	6	; to 46
	40	[300]	GETTABLE 	8 0 -10	; "props"
	41	[300]	GETTABLE 	8 8 -11	; "language"
	42	[300]	EQ       	1 8 -12	; - ""
	43	[300]	JMP      	2	; to 46
	44	[301]	GETTABLE 	8 0 -10	; "props"
	45	[301]	GETTABLE 	7 8 -11	; "language"
	46	[304]	GETUPVAL 	8 1	; VerticalGroup
	47	[304]	SELF     	8 8 -13	; "new"
	48	[304]	NEWTABLE 	10 1 1
	49	[305]	SETTABLE 	10 -14 -15	; "align" "center"
	50	[306]	GETUPVAL 	11 2	; VerticalSpan
	51	[306]	SELF     	11 11 -13	; "new"
	52	[306]	NEWTABLE 	13 0 1
	53	[306]	MUL      	14 5 -17	; - 0.2
	54	[306]	SETTABLE 	13 -16 14	; "width" -
	55	[306]	CALL     	11 3 2
	56	[307]	GETUPVAL 	12 3	; TextBoxWidget
	57	[307]	SELF     	12 12 -13	; "new"
	58	[307]	NEWTABLE 	14 0 5
	59	[308]	GETTABLE 	15 0 -10	; "props"
	60	[308]	GETTABLE 	15 15 -19	; "title"
	61	[308]	SETTABLE 	14 -18 15	; "text" -
	62	[309]	SETTABLE 	14 -20 7	; "lang" -
	63	[310]	SETTABLE 	14 -16 6	; "width" -
	64	[311]	GETTABLE 	15 0 -22	; "medium_font_face"
	65	[311]	SETTABLE 	14 -21 15	; "face" -
	66	[312]	SETTABLE 	14 -23 -15	; "alignment" "center"
	67	[307]	CALL     	12 3 0
	68	[315]	SETLIST  	10 0 1	; 1
	69	[304]	CALL     	8 3 2
	70	[317]	GETUPVAL 	9 3	; TextBoxWidget
	71	[317]	SELF     	9 9 -13	; "new"
	72	[317]	NEWTABLE 	11 0 5
	73	[318]	GETTABLE 	12 0 -10	; "props"
	74	[318]	GETTABLE 	12 12 -24	; "authors"
	75	[318]	SETTABLE 	11 -18 12	; "text" -
	76	[319]	SETTABLE 	11 -20 7	; "lang" -
	77	[320]	GETTABLE 	12 0 -25	; "small_font_face"
	78	[320]	SETTABLE 	11 -21 12	; "face" -
	79	[321]	SETTABLE 	11 -16 6	; "width" -
	80	[322]	SETTABLE 	11 -23 -15	; "alignment" "center"
	81	[317]	CALL     	9 3 2
	82	[324]	GETGLOBAL	10 -26	; table
	83	[324]	GETTABLE 	10 10 -27	; "insert"
	84	[324]	MOVE     	11 8
	85	[325]	GETUPVAL 	12 4	; CenterContainer
	86	[325]	SELF     	12 12 -13	; "new"
	87	[325]	NEWTABLE 	14 1 1
	88	[326]	GETUPVAL 	15 5	; Geom
	89	[326]	SELF     	15 15 -13	; "new"
	90	[326]	NEWTABLE 	17 0 2
	91	[326]	SETTABLE 	17 -29 6	; "w" -
	92	[326]	SELF     	18 9 -31	; "getSize"
	93	[326]	CALL     	18 2 2
	94	[326]	GETTABLE 	18 18 -30	; "h"
	95	[326]	SETTABLE 	17 -30 18	; "h" -
	96	[326]	CALL     	15 3 2
	97	[326]	SETTABLE 	14 -28 15	; "dimen" -
	98	[328]	MOVE     	15 9
	99	[328]	SETLIST  	14 1 1	; 1
	100	[325]	CALL     	12 3 0
	101	[324]	CALL     	10 0 1
	102	[331]	GETTABLE 	10 0 -32	; "view"
	103	[331]	GETTABLE 	10 10 -33	; "state"
	104	[331]	GETTABLE 	10 10 -34	; "page"
	105	[331]	GETTABLE 	11 0 -35	; "total_pages"
	106	[331]	DIV      	10 10 11
	107	[332]	GETUPVAL 	11 6	; ProgressWidget
	108	[332]	SELF     	11 11 -13	; "new"
	109	[332]	NEWTABLE 	13 0 5
	110	[333]	MUL      	14 6 -36	; - 0.7
	111	[333]	SETTABLE 	13 -16 14	; "width" -
	112	[334]	GETUPVAL 	14 0	; Screen
	113	[334]	SELF     	14 14 -5	; "scaleBySize"
	114	[334]	LOADK    	16 -38	; 10
	115	[334]	CALL     	14 3 2
	116	[334]	SETTABLE 	13 -37 14	; "height" -
	117	[335]	SETTABLE 	13 -39 10	; "percentage" -
	118	[336]	SETTABLE 	13 -40 -41	; "ticks" nil
	119	[337]	SETTABLE 	13 -42 -41	; "last" nil
	120	[332]	CALL     	11 3 2
	121	[339]	GETGLOBAL	12 -26	; table
	122	[339]	GETTABLE 	12 12 -27	; "insert"
	123	[339]	MOVE     	13 8
	124	[340]	GETUPVAL 	14 4	; CenterContainer
	125	[340]	SELF     	14 14 -13	; "new"
	126	[340]	NEWTABLE 	16 1 1
	127	[341]	GETUPVAL 	17 5	; Geom
	128	[341]	SELF     	17 17 -13	; "new"
	129	[341]	NEWTABLE 	19 0 2
	130	[341]	SETTABLE 	19 -29 6	; "w" -
	131	[341]	SELF     	20 11 -31	; "getSize"
	132	[341]	CALL     	20 2 2
	133	[341]	GETTABLE 	20 20 -30	; "h"
	134	[341]	SETTABLE 	19 -30 20	; "h" -
	135	[341]	CALL     	17 3 2
	136	[341]	SETTABLE 	16 -28 17	; "dimen" -
	137	[343]	MOVE     	17 11
	138	[343]	SETLIST  	16 1 1	; 1
	139	[340]	CALL     	14 3 0
	140	[339]	CALL     	12 0 1
	141	[346]	GETUPVAL 	12 7	; TextWidget
	142	[346]	SELF     	12 12 -13	; "new"
	143	[346]	NEWTABLE 	14 0 2
	144	[347]	GETUPVAL 	15 8	; T
	145	[347]	GETUPVAL 	16 9	; _
	146	[347]	LOADK    	17 -43	; "%1% Completed"
	147	[347]	CALL     	16 2 2
	148	[348]	GETGLOBAL	17 -44	; string
	149	[348]	GETTABLE 	17 17 -45	; "format"
	150	[348]	LOADK    	18 -46	; "%1.f"
	151	[348]	MUL      	19 10 -47	; - 100
	152	[348]	CALL     	17 3 0
	153	[347]	CALL     	15 0 2
	154	[348]	SETTABLE 	14 -18 15	; "text" -
	155	[349]	GETTABLE 	15 0 -25	; "small_font_face"
	156	[349]	SETTABLE 	14 -21 15	; "face" -
	157	[346]	CALL     	12 3 2
	158	[351]	GETGLOBAL	13 -26	; table
	159	[351]	GETTABLE 	13 13 -27	; "insert"
	160	[351]	MOVE     	14 8
	161	[352]	GETUPVAL 	15 4	; CenterContainer
	162	[352]	SELF     	15 15 -13	; "new"
	163	[352]	NEWTABLE 	17 1 1
	164	[353]	GETUPVAL 	18 5	; Geom
	165	[353]	SELF     	18 18 -13	; "new"
	166	[353]	NEWTABLE 	20 0 2
	167	[353]	SETTABLE 	20 -29 6	; "w" -
	168	[353]	SELF     	21 12 -31	; "getSize"
	169	[353]	CALL     	21 2 2
	170	[353]	GETTABLE 	21 21 -30	; "h"
	171	[353]	SETTABLE 	20 -30 21	; "h" -
	172	[353]	CALL     	18 3 2
	173	[353]	SETTABLE 	17 -28 18	; "dimen" -
	174	[355]	MOVE     	18 12
	175	[355]	SETLIST  	17 1 1	; 1
	176	[352]	CALL     	15 3 0
	177	[351]	CALL     	13 0 1
	178	[358]	GETGLOBAL	13 -26	; table
	179	[358]	GETTABLE 	13 13 -27	; "insert"
	180	[358]	MOVE     	14 8
	181	[359]	GETUPVAL 	15 2	; VerticalSpan
	182	[359]	SELF     	15 15 -13	; "new"
	183	[359]	NEWTABLE 	17 0 1
	184	[359]	GETUPVAL 	18 0	; Screen
	185	[359]	SELF     	18 18 -5	; "scaleBySize"
	186	[359]	LOADK    	20 -48	; 30
	187	[359]	CALL     	18 3 2
	188	[359]	SETTABLE 	17 -16 18	; "width" -
	189	[359]	CALL     	15 3 0
	190	[358]	CALL     	13 0 1
	191	[360]	GETUPVAL 	13 0	; Screen
	192	[360]	SELF     	13 13 -5	; "scaleBySize"
	193	[360]	LOADK    	15 -49	; 60
	194	[360]	CALL     	13 3 2
	195	[361]	GETGLOBAL	14 -26	; table
	196	[361]	GETTABLE 	14 14 -27	; "insert"
	197	[361]	MOVE     	15 8
	198	[362]	SELF     	16 0 -50	; "generateRateGroup"
	199	[362]	MOVE     	18 1
	200	[362]	MOVE     	19 13
	201	[362]	GETTABLE 	20 0 -51	; "summary"
	202	[362]	GETTABLE 	20 20 -52	; "rating"
	203	[362]	CALL     	16 5 0
	204	[361]	CALL     	14 0 1
	205	[365]	GETUPVAL 	14 10	; HorizontalGroup
	206	[365]	SELF     	14 14 -13	; "new"
	207	[365]	NEWTABLE 	16 0 1
	208	[366]	SETTABLE 	16 -14 -53	; "align" "top"
	209	[367]	GETUPVAL 	17 11	; HorizontalSpan
	210	[367]	SELF     	17 17 -13	; "new"
	211	[367]	NEWTABLE 	19 0 1
	212	[367]	SETTABLE 	19 -16 2	; "width" -
	213	[367]	CALL     	17 3 0
	214	[368]	SETLIST  	16 0 1	; 1
	215	[365]	CALL     	14 3 2
	216	[370]	GETTABLE 	15 0 -54	; "thumbnail"
	217	[370]	TEST     	15 0 0
	218	[370]	JMP      	56	; to 275
	219	[372]	GETTABLE 	15 0 -54	; "thumbnail"
	220	[372]	SELF     	15 15 -1	; "getWidth"
	221	[372]	CALL     	15 2 2
	222	[372]	GETTABLE 	16 0 -54	; "thumbnail"
	223	[372]	SELF     	16 16 -55	; "getHeight"
	224	[372]	CALL     	16 2 2
	225	[373]	LT       	1 3 15
	226	[373]	JMP      	2	; to 229
	227	[373]	LT       	0 4 16
	228	[373]	JMP      	33	; to 262
	229	[374]	GETGLOBAL	17 -56	; math
	230	[374]	GETTABLE 	17 17 -57	; "min"
	231	[374]	DIV      	18 3 15
	232	[374]	DIV      	19 4 16
	233	[374]	CALL     	17 3 2
	234	[375]	GETGLOBAL	18 -56	; math
	235	[375]	GETTABLE 	18 18 -57	; "min"
	236	[375]	GETGLOBAL	19 -56	; math
	237	[375]	GETTABLE 	19 19 -58	; "floor"
	238	[375]	MUL      	20 15 17
	239	[375]	CALL     	19 2 2
	240	[375]	ADD      	19 19 -59	; - 1
	241	[375]	MOVE     	20 3
	242	[375]	CALL     	18 3 2
	243	[375]	MOVE     	15 18
	244	[376]	GETGLOBAL	18 -56	; math
	245	[376]	GETTABLE 	18 18 -57	; "min"
	246	[376]	GETGLOBAL	19 -56	; math
	247	[376]	GETTABLE 	19 19 -58	; "floor"
	248	[376]	MUL      	20 16 17
	249	[376]	CALL     	19 2 2
	250	[376]	ADD      	19 19 -59	; - 1
	251	[376]	MOVE     	20 4
	252	[376]	CALL     	18 3 2
	253	[376]	MOVE     	16 18
	254	[377]	GETUPVAL 	18 12	; RenderImage
	255	[377]	SELF     	18 18 -60	; "scaleBlitBuffer"
	256	[377]	GETTABLE 	20 0 -54	; "thumbnail"
	257	[377]	MOVE     	21 15
	258	[377]	MOVE     	22 16
	259	[377]	LOADBOOL 	23 1 0
	260	[377]	CALL     	18 6 2
	261	[377]	SETTABLE 	0 -54 18	; "thumbnail" -
	262	[380]	GETGLOBAL	17 -26	; table
	263	[380]	GETTABLE 	17 17 -27	; "insert"
	264	[380]	MOVE     	18 14
	265	[380]	GETUPVAL 	19 13	; ImageWidget
	266	[380]	SELF     	19 19 -13	; "new"
	267	[380]	NEWTABLE 	21 0 3
	268	[381]	GETTABLE 	22 0 -54	; "thumbnail"
	269	[381]	SETTABLE 	21 -61 22	; "image" -
	270	[382]	SETTABLE 	21 -16 15	; "width" -
	271	[383]	SETTABLE 	21 -37 16	; "height" -
	272	[380]	CALL     	19 3 0
	273	[380]	CALL     	17 0 1
	274	[386]	SETTABLE 	0 -54 -41	; "thumbnail" nil
	275	[389]	GETGLOBAL	15 -26	; table
	276	[389]	GETTABLE 	15 15 -27	; "insert"
	277	[389]	MOVE     	16 14
	278	[389]	GETUPVAL 	17 4	; CenterContainer
	279	[389]	SELF     	17 17 -13	; "new"
	280	[389]	NEWTABLE 	19 1 1
	281	[390]	GETUPVAL 	20 5	; Geom
	282	[390]	SELF     	20 20 -13	; "new"
	283	[390]	NEWTABLE 	22 0 2
	284	[390]	SETTABLE 	22 -29 6	; "w" -
	285	[390]	SETTABLE 	22 -30 5	; "h" -
	286	[390]	CALL     	20 3 2
	287	[390]	SETTABLE 	19 -28 20	; "dimen" -
	288	[392]	MOVE     	20 8
	289	[392]	SETLIST  	19 1 1	; 1
	290	[389]	CALL     	17 3 0
	291	[389]	CALL     	15 0 1
	292	[394]	GETUPVAL 	15 4	; CenterContainer
	293	[394]	SELF     	15 15 -13	; "new"
	294	[394]	NEWTABLE 	17 1 1
	295	[395]	GETUPVAL 	18 5	; Geom
	296	[395]	SELF     	18 18 -13	; "new"
	297	[395]	NEWTABLE 	20 0 2
	298	[395]	SETTABLE 	20 -29 1	; "w" -
	299	[395]	SETTABLE 	20 -30 4	; "h" -
	300	[395]	CALL     	18 3 2
	301	[395]	SETTABLE 	17 -28 18	; "dimen" -
	302	[397]	MOVE     	18 14
	303	[397]	SETLIST  	17 1 1	; 1
	304	[394]	TAILCALL 	15 3 0
	305	[397]	RETURN   	15 0
	306	[398]	RETURN   	0 1

function <./frontend/ui/widget/bookstatuswidget.lua:400,466> (180 instructions, 720 bytes at 0x7ff21ac0bef0)
2 params, 21 slots, 7 upvalues, 9 locals, 23 constants, 0 functions
	1	[401]	GETUPVAL 	2 0	; Screen
	2	[401]	SELF     	2 2 -1	; "scaleBySize"
	3	[401]	LOADK    	4 -2	; 60
	4	[401]	CALL     	2 3 2
	5	[402]	GETUPVAL 	3 1	; CenterContainer
	6	[402]	SELF     	3 3 -3	; "new"
	7	[402]	NEWTABLE 	5 0 1
	8	[403]	GETUPVAL 	6 2	; Geom
	9	[403]	SELF     	6 6 -3	; "new"
	10	[403]	NEWTABLE 	8 0 2
	11	[403]	SETTABLE 	8 -5 1	; "w" -
	12	[403]	SETTABLE 	8 -6 2	; "h" -
	13	[403]	CALL     	6 3 2
	14	[403]	SETTABLE 	5 -4 6	; "dimen" -
	15	[402]	CALL     	3 3 2
	16	[406]	GETUPVAL 	4 3	; VerticalGroup
	17	[406]	SELF     	4 4 -3	; "new"
	18	[406]	NEWTABLE 	6 0 1
	19	[406]	SETTABLE 	6 -7 -8	; "align" "left"
	20	[406]	CALL     	4 3 2
	21	[408]	DIV      	5 1 -9	; - 3
	22	[409]	DIV      	6 2 -10	; - 2
	23	[411]	GETUPVAL 	7 4	; HorizontalGroup
	24	[411]	SELF     	7 7 -3	; "new"
	25	[411]	NEWTABLE 	9 2 1
	26	[412]	SETTABLE 	9 -7 -11	; "align" "center"
	27	[413]	GETUPVAL 	10 1	; CenterContainer
	28	[413]	SELF     	10 10 -3	; "new"
	29	[413]	NEWTABLE 	12 0 1
	30	[414]	GETUPVAL 	13 2	; Geom
	31	[414]	SELF     	13 13 -3	; "new"
	32	[414]	NEWTABLE 	15 0 2
	33	[414]	SETTABLE 	15 -5 5	; "w" -
	34	[414]	SETTABLE 	15 -6 6	; "h" -
	35	[414]	CALL     	13 3 2
	36	[414]	SETTABLE 	12 -4 13	; "dimen" -
	37	[415]	GETUPVAL 	13 5	; TextWidget
	38	[415]	SELF     	13 13 -3	; "new"
	39	[415]	NEWTABLE 	15 0 2
	40	[416]	GETUPVAL 	16 6	; _
	41	[416]	LOADK    	17 -13	; "Days"
	42	[416]	CALL     	16 2 2
	43	[416]	SETTABLE 	15 -12 16	; "text" -
	44	[417]	GETTABLE 	16 0 -15	; "small_font_face"
	45	[417]	SETTABLE 	15 -14 16	; "face" -
	46	[415]	CALL     	13 3 0
	47	[419]	SETLIST  	12 0 1	; 1
	48	[413]	CALL     	10 3 2
	49	[420]	GETUPVAL 	11 1	; CenterContainer
	50	[420]	SELF     	11 11 -3	; "new"
	51	[420]	NEWTABLE 	13 0 1
	52	[421]	GETUPVAL 	14 2	; Geom
	53	[421]	SELF     	14 14 -3	; "new"
	54	[421]	NEWTABLE 	16 0 2
	55	[421]	SETTABLE 	16 -5 5	; "w" -
	56	[421]	SETTABLE 	16 -6 6	; "h" -
	57	[421]	CALL     	14 3 2
	58	[421]	SETTABLE 	13 -4 14	; "dimen" -
	59	[422]	GETUPVAL 	14 5	; TextWidget
	60	[422]	SELF     	14 14 -3	; "new"
	61	[422]	NEWTABLE 	16 0 2
	62	[423]	GETUPVAL 	17 6	; _
	63	[423]	LOADK    	18 -16	; "Time"
	64	[423]	CALL     	17 2 2
	65	[423]	SETTABLE 	16 -12 17	; "text" -
	66	[424]	GETTABLE 	17 0 -15	; "small_font_face"
	67	[424]	SETTABLE 	16 -14 17	; "face" -
	68	[422]	CALL     	14 3 0
	69	[426]	SETLIST  	13 0 1	; 1
	70	[420]	CALL     	11 3 2
	71	[427]	GETUPVAL 	12 1	; CenterContainer
	72	[427]	SELF     	12 12 -3	; "new"
	73	[427]	NEWTABLE 	14 0 1
	74	[428]	GETUPVAL 	15 2	; Geom
	75	[428]	SELF     	15 15 -3	; "new"
	76	[428]	NEWTABLE 	17 0 2
	77	[428]	SETTABLE 	17 -5 5	; "w" -
	78	[428]	SETTABLE 	17 -6 6	; "h" -
	79	[428]	CALL     	15 3 2
	80	[428]	SETTABLE 	14 -4 15	; "dimen" -
	81	[429]	GETUPVAL 	15 5	; TextWidget
	82	[429]	SELF     	15 15 -3	; "new"
	83	[429]	NEWTABLE 	17 0 2
	84	[430]	GETUPVAL 	18 6	; _
	85	[430]	LOADK    	19 -17	; "Read pages"
	86	[430]	CALL     	18 2 2
	87	[430]	SETTABLE 	17 -12 18	; "text" -
	88	[431]	GETTABLE 	18 0 -15	; "small_font_face"
	89	[431]	SETTABLE 	17 -14 18	; "face" -
	90	[429]	CALL     	15 3 0
	91	[433]	SETLIST  	14 0 1	; 1
	92	[427]	CALL     	12 3 0
	93	[434]	SETLIST  	9 0 1	; 1
	94	[411]	CALL     	7 3 2
	95	[436]	GETUPVAL 	8 4	; HorizontalGroup
	96	[436]	SELF     	8 8 -3	; "new"
	97	[436]	NEWTABLE 	10 2 1
	98	[437]	SETTABLE 	10 -7 -11	; "align" "center"
	99	[438]	GETUPVAL 	11 1	; CenterContainer
	100	[438]	SELF     	11 11 -3	; "new"
	101	[438]	NEWTABLE 	13 0 1
	102	[439]	GETUPVAL 	14 2	; Geom
	103	[439]	SELF     	14 14 -3	; "new"
	104	[439]	NEWTABLE 	16 0 2
	105	[439]	SETTABLE 	16 -5 5	; "w" -
	106	[439]	SETTABLE 	16 -6 6	; "h" -
	107	[439]	CALL     	14 3 2
	108	[439]	SETTABLE 	13 -4 14	; "dimen" -
	109	[440]	GETUPVAL 	14 5	; TextWidget
	110	[440]	SELF     	14 14 -3	; "new"
	111	[440]	NEWTABLE 	16 0 2
	112	[441]	SELF     	17 0 -18	; "getStatDays"
	113	[441]	CALL     	17 2 2
	114	[441]	SETTABLE 	16 -12 17	; "text" -
	115	[442]	GETTABLE 	17 0 -19	; "medium_font_face"
	116	[442]	SETTABLE 	16 -14 17	; "face" -
	117	[440]	CALL     	14 3 0
	118	[444]	SETLIST  	13 0 1	; 1
	119	[438]	CALL     	11 3 2
	120	[445]	GETUPVAL 	12 1	; CenterContainer
	121	[445]	SELF     	12 12 -3	; "new"
	122	[445]	NEWTABLE 	14 0 1
	123	[446]	GETUPVAL 	15 2	; Geom
	124	[446]	SELF     	15 15 -3	; "new"
	125	[446]	NEWTABLE 	17 0 2
	126	[446]	SETTABLE 	17 -5 5	; "w" -
	127	[446]	SETTABLE 	17 -6 6	; "h" -
	128	[446]	CALL     	15 3 2
	129	[446]	SETTABLE 	14 -4 15	; "dimen" -
	130	[447]	GETUPVAL 	15 5	; TextWidget
	131	[447]	SELF     	15 15 -3	; "new"
	132	[447]	NEWTABLE 	17 0 2
	133	[448]	SELF     	18 0 -20	; "getStatHours"
	134	[448]	CALL     	18 2 2
	135	[448]	SETTABLE 	17 -12 18	; "text" -
	136	[449]	GETTABLE 	18 0 -19	; "medium_font_face"
	137	[449]	SETTABLE 	17 -14 18	; "face" -
	138	[447]	CALL     	15 3 0
	139	[451]	SETLIST  	14 0 1	; 1
	140	[445]	CALL     	12 3 2
	141	[452]	GETUPVAL 	13 1	; CenterContainer
	142	[452]	SELF     	13 13 -3	; "new"
	143	[452]	NEWTABLE 	15 0 1
	144	[453]	GETUPVAL 	16 2	; Geom
	145	[453]	SELF     	16 16 -3	; "new"
	146	[453]	NEWTABLE 	18 0 2
	147	[453]	SETTABLE 	18 -5 5	; "w" -
	148	[453]	SETTABLE 	18 -6 6	; "h" -
	149	[453]	CALL     	16 3 2
	150	[453]	SETTABLE 	15 -4 16	; "dimen" -
	151	[454]	GETUPVAL 	16 5	; TextWidget
	152	[454]	SELF     	16 16 -3	; "new"
	153	[454]	NEWTABLE 	18 0 2
	154	[455]	SELF     	19 0 -21	; "getStatReadPages"
	155	[455]	CALL     	19 2 2
	156	[455]	SETTABLE 	18 -12 19	; "text" -
	157	[456]	GETTABLE 	19 0 -19	; "medium_font_face"
	158	[456]	SETTABLE 	18 -14 19	; "face" -
	159	[454]	CALL     	16 3 0
	160	[458]	SETLIST  	15 0 1	; 1
	161	[452]	CALL     	13 3 0
	162	[459]	SETLIST  	10 0 1	; 1
	163	[436]	CALL     	8 3 2
	164	[461]	GETGLOBAL	9 -22	; table
	165	[461]	GETTABLE 	9 9 -23	; "insert"
	166	[461]	MOVE     	10 4
	167	[461]	MOVE     	11 7
	168	[461]	CALL     	9 3 1
	169	[462]	GETGLOBAL	9 -22	; table
	170	[462]	GETTABLE 	9 9 -23	; "insert"
	171	[462]	MOVE     	10 4
	172	[462]	MOVE     	11 8
	173	[462]	CALL     	9 3 1
	174	[464]	GETGLOBAL	9 -22	; table
	175	[464]	GETTABLE 	9 9 -23	; "insert"
	176	[464]	MOVE     	10 3
	177	[464]	MOVE     	11 4
	178	[464]	CALL     	9 3 1
	179	[465]	RETURN   	3 2
	180	[466]	RETURN   	0 1

function <./frontend/ui/widget/bookstatuswidget.lua:468,498> (77 instructions, 308 bytes at 0x7ff21ac0c7e0)
2 params, 14 slots, 8 upvalues, 4 locals, 33 constants, 0 functions
	1	[470]	GETUPVAL 	3 0	; Screen
	2	[470]	SELF     	3 3 -1	; "getScreenMode"
	3	[470]	CALL     	3 2 2
	4	[470]	EQ       	0 3 -2	; - "landscape"
	5	[470]	JMP      	6	; to 12
	6	[471]	GETUPVAL 	3 0	; Screen
	7	[471]	SELF     	3 3 -3	; "scaleBySize"
	8	[471]	LOADK    	5 -4	; 80
	9	[471]	CALL     	3 3 2
	10	[471]	MOVE     	2 3
	11	[471]	JMP      	5	; to 17
	12	[473]	GETUPVAL 	3 0	; Screen
	13	[473]	SELF     	3 3 -3	; "scaleBySize"
	14	[473]	LOADK    	5 -5	; 160
	15	[473]	CALL     	3 3 2
	16	[473]	MOVE     	2 3
	17	[476]	GETUPVAL 	3 1	; Size
	18	[476]	GETTABLE 	3 3 -6	; "padding"
	19	[476]	GETTABLE 	3 3 -7	; "default"
	20	[477]	GETUPVAL 	4 2	; InputText
	21	[477]	SELF     	4 4 -9	; "new"
	22	[477]	NEWTABLE 	6 0 11
	23	[478]	GETTABLE 	7 0 -11	; "summary"
	24	[478]	GETTABLE 	7 7 -12	; "note"
	25	[478]	SETTABLE 	6 -10 7	; "text" -
	26	[479]	GETTABLE 	7 0 -14	; "medium_font_face"
	27	[479]	SETTABLE 	6 -13 7	; "face" -
	28	[480]	GETTABLE 	7 0 -6	; "padding"
	29	[480]	MUL      	7 7 -16	; - 3
	30	[480]	SUB      	7 1 7
	31	[480]	SETTABLE 	6 -15 7	; "width" -
	32	[481]	MUL      	7 2 -18	; - 0.75
	33	[481]	SETTABLE 	6 -17 7	; "height" -
	34	[482]	SETTABLE 	6 -19 -20	; "scroll" true
	35	[483]	GETUPVAL 	7 1	; Size
	36	[483]	GETTABLE 	7 7 -22	; "border"
	37	[483]	GETTABLE 	7 7 -7	; "default"
	38	[483]	SETTABLE 	6 -21 7	; "bordersize" -
	39	[484]	SETTABLE 	6 -23 -24	; "focused" false
	40	[485]	SETTABLE 	6 -6 3	; "padding" -
	41	[486]	SETTABLE 	6 -25 0	; "parent" -
	42	[487]	GETTABLE 	7 0 -26	; "readonly"
	43	[487]	SETTABLE 	6 -26 7	; "readonly" -
	44	[488]	GETUPVAL 	7 3	; _
	45	[488]	LOADK    	8 -28	; "A few words about the book"
	46	[488]	CALL     	7 2 2
	47	[488]	SETTABLE 	6 -27 7	; "hint" -
	48	[477]	CALL     	4 3 2
	49	[489]	SETTABLE 	0 -8 4	; "input_note" -
	50	[491]	GETUPVAL 	4 4	; VerticalGroup
	51	[491]	SELF     	4 4 -9	; "new"
	52	[491]	NEWTABLE 	6 1 0
	53	[492]	GETUPVAL 	7 5	; VerticalSpan
	54	[492]	SELF     	7 7 -9	; "new"
	55	[492]	NEWTABLE 	9 0 1
	56	[492]	GETUPVAL 	10 1	; Size
	57	[492]	GETTABLE 	10 10 -29	; "span"
	58	[492]	GETTABLE 	10 10 -30	; "vertical_large"
	59	[492]	SETTABLE 	9 -15 10	; "width" -
	60	[492]	CALL     	7 3 2
	61	[493]	GETUPVAL 	8 6	; CenterContainer
	62	[493]	SELF     	8 8 -9	; "new"
	63	[493]	NEWTABLE 	10 1 1
	64	[494]	GETUPVAL 	11 7	; Geom
	65	[494]	SELF     	11 11 -9	; "new"
	66	[494]	NEWTABLE 	13 0 2
	67	[494]	SETTABLE 	13 -32 1	; "w" -
	68	[494]	SETTABLE 	13 -33 2	; "h" -
	69	[494]	CALL     	11 3 2
	70	[494]	SETTABLE 	10 -31 11	; "dimen" -
	71	[496]	GETTABLE 	11 0 -8	; "input_note"
	72	[496]	SETLIST  	10 1 1	; 1
	73	[493]	CALL     	8 3 0
	74	[497]	SETLIST  	6 0 1	; 1
	75	[491]	TAILCALL 	4 3 0
	76	[497]	RETURN   	4 0
	77	[498]	RETURN   	0 1

function <./frontend/ui/widget/bookstatuswidget.lua:500,504> (10 instructions, 40 bytes at 0x7ff21ac0cca0)
1 param, 4 slots, 0 upvalues, 1 local, 5 constants, 0 functions
	1	[501]	GETTABLE 	1 0 -1	; "summary"
	2	[501]	GETTABLE 	2 0 -3	; "input_note"
	3	[501]	SELF     	2 2 -4	; "getText"
	4	[501]	CALL     	2 2 2
	5	[501]	SETTABLE 	1 -2 2	; "note" -
	6	[502]	SELF     	1 0 -5	; "saveSummary"
	7	[502]	CALL     	1 2 1
	8	[503]	LOADBOOL 	1 1 0
	9	[503]	RETURN   	1 2
	10	[504]	RETURN   	0 1

function <./frontend/ui/widget/bookstatuswidget.lua:506,511> (12 instructions, 48 bytes at 0x7ff21ac0cee0)
1 param, 5 slots, 0 upvalues, 1 local, 4 constants, 0 functions
	1	[507]	GETTABLE 	1 0 -1	; "summary"
	2	[507]	TEST     	1 0 0
	3	[507]	JMP      	8	; to 12
	4	[508]	GETTABLE 	1 0 -2	; "settings"
	5	[508]	SELF     	1 1 -3	; "saveSetting"
	6	[508]	LOADK    	3 -1	; "summary"
	7	[508]	GETTABLE 	4 0 -1	; "summary"
	8	[508]	CALL     	1 4 1
	9	[509]	GETTABLE 	1 0 -2	; "settings"
	10	[509]	SELF     	1 1 -4	; "flush"
	11	[509]	CALL     	1 2 1
	12	[511]	RETURN   	0 1

function <./frontend/ui/widget/bookstatuswidget.lua:513,574> (125 instructions, 500 bytes at 0x7ff21ac0d110)
2 params, 18 slots, 7 upvalues, 13 locals, 44 constants, 0 functions
	1	[515]	GETUPVAL 	3 0	; Screen
	2	[515]	SELF     	3 3 -1	; "getScreenMode"
	3	[515]	CALL     	3 2 2
	4	[515]	EQ       	0 3 -2	; - "landscape"
	5	[515]	JMP      	6	; to 12
	6	[517]	GETUPVAL 	3 0	; Screen
	7	[517]	SELF     	3 3 -3	; "scaleBySize"
	8	[517]	LOADK    	5 -4	; 60
	9	[517]	CALL     	3 3 2
	10	[517]	MOVE     	2 3
	11	[517]	JMP      	5	; to 17
	12	[520]	GETUPVAL 	3 0	; Screen
	13	[520]	SELF     	3 3 -3	; "scaleBySize"
	14	[520]	LOADK    	5 -5	; 105
	15	[520]	CALL     	3 3 2
	16	[520]	MOVE     	2 3
	17	[523]	NEWTABLE 	3 3 0
	18	[523]	LOADK    	4 -6	; "complete"
	19	[523]	LOADK    	5 -7	; "reading"
	20	[523]	LOADK    	6 -8	; "abandoned"
	21	[523]	SETLIST  	3 3 1	; 1
	22	[525]	GETTABLE 	4 0 -9	; "summary"
	23	[525]	GETTABLE 	4 4 -10	; "status"
	24	[526]	LOADK    	5 -11	; 2
	25	[527]	GETGLOBAL	6 -12	; pairs
	26	[527]	MOVE     	7 3
	27	[527]	CALL     	6 2 4
	28	[527]	JMP      	3	; to 32
	29	[528]	EQ       	0 10 4
	30	[528]	JMP      	1	; to 32
	31	[529]	MOVE     	5 9
	32	[527]	TFORLOOP 	6 2
	33	[530]	JMP      	-5	; to 29
	34	[533]	NEWTABLE 	6 0 9
	35	[534]	SETTABLE 	6 -13 -14	; "event" "ChangeBookStatus"
	36	[535]	SETTABLE 	6 -15 -11	; "default_value" 2
	37	[536]	SETTABLE 	6 -16 3	; "args" -
	38	[537]	SETTABLE 	6 -17 -7	; "default_arg" "reading"
	39	[538]	NEWTABLE 	7 2 0
	40	[538]	GETUPVAL 	8 1	; _
	41	[538]	LOADK    	9 -19	; "Finished"
	42	[538]	CALL     	8 2 2
	43	[538]	GETUPVAL 	9 1	; _
	44	[538]	LOADK    	10 -20	; "Reading"
	45	[538]	CALL     	9 2 2
	46	[538]	GETUPVAL 	10 1	; _
	47	[538]	LOADK    	11 -21	; "On hold"
	48	[538]	CALL     	10 2 0
	49	[538]	SETLIST  	7 0 1	; 1
	50	[538]	SETTABLE 	6 -18 7	; "toggle" -
	51	[539]	NEWTABLE 	7 3 0
	52	[539]	LOADK    	8 -23	; 1
	53	[539]	LOADK    	9 -11	; 2
	54	[539]	LOADK    	10 -24	; 3
	55	[539]	SETLIST  	7 3 1	; 1
	56	[539]	SETTABLE 	6 -22 7	; "values" -
	57	[540]	SETTABLE 	6 -25 -26	; "name" "book_status"
	58	[541]	SETTABLE 	6 -27 -28	; "alternate" false
	59	[542]	SETTABLE 	6 -29 -30	; "enabled" true
	60	[545]	GETTABLE 	7 0 -31	; "readonly"
	61	[545]	TEST     	7 0 0
	62	[545]	JMP      	1	; to 64
	63	[546]	SETTABLE 	6 -32 -28	; "enable" false
	64	[549]	GETUPVAL 	7 2	; ToggleSwitch
	65	[549]	SELF     	7 7 -33	; "new"
	66	[549]	NEWTABLE 	9 0 13
	67	[550]	MUL      	10 1 -35	; - 0.6
	68	[550]	SETTABLE 	9 -34 10	; "width" -
	69	[551]	GETTABLE 	10 6 -15	; "default_value"
	70	[551]	SETTABLE 	9 -15 10	; "default_value" -
	71	[552]	GETTABLE 	10 6 -25	; "name"
	72	[552]	SETTABLE 	9 -25 10	; "name" -
	73	[553]	GETTABLE 	10 6 -36	; "name_text"
	74	[553]	SETTABLE 	9 -36 10	; "name_text" -
	75	[554]	GETTABLE 	10 6 -13	; "event"
	76	[554]	SETTABLE 	9 -13 10	; "event" -
	77	[555]	GETTABLE 	10 6 -18	; "toggle"
	78	[555]	SETTABLE 	9 -18 10	; "toggle" -
	79	[556]	GETTABLE 	10 6 -16	; "args"
	80	[556]	SETTABLE 	9 -16 10	; "args" -
	81	[557]	GETTABLE 	10 6 -27	; "alternate"
	82	[557]	SETTABLE 	9 -27 10	; "alternate" -
	83	[558]	GETTABLE 	10 6 -17	; "default_arg"
	84	[558]	SETTABLE 	9 -17 10	; "default_arg" -
	85	[559]	GETTABLE 	10 6 -22	; "values"
	86	[559]	SETTABLE 	9 -22 10	; "values" -
	87	[560]	GETTABLE 	10 6 -32	; "enable"
	88	[560]	SETTABLE 	9 -29 10	; "enabled" -
	89	[561]	SETTABLE 	9 -37 0	; "config" -
	90	[562]	GETTABLE 	10 0 -31	; "readonly"
	91	[562]	SETTABLE 	9 -31 10	; "readonly" -
	92	[549]	CALL     	7 3 2
	93	[564]	SELF     	8 7 -38	; "setPosition"
	94	[564]	MOVE     	10 5
	95	[564]	CALL     	8 3 1
	96	[566]	GETUPVAL 	8 3	; VerticalGroup
	97	[566]	SELF     	8 8 -33	; "new"
	98	[566]	NEWTABLE 	10 1 0
	99	[567]	GETUPVAL 	11 4	; VerticalSpan
	100	[567]	SELF     	11 11 -33	; "new"
	101	[567]	NEWTABLE 	13 0 1
	102	[567]	GETUPVAL 	14 0	; Screen
	103	[567]	SELF     	14 14 -3	; "scaleBySize"
	104	[567]	LOADK    	16 -39	; 10
	105	[567]	CALL     	14 3 2
	106	[567]	SETTABLE 	13 -34 14	; "width" -
	107	[567]	CALL     	11 3 2
	108	[568]	GETUPVAL 	12 5	; CenterContainer
	109	[568]	SELF     	12 12 -33	; "new"
	110	[568]	NEWTABLE 	14 1 2
	111	[569]	SETTABLE 	14 -40 -41	; "ignore" "height"
	112	[570]	GETUPVAL 	15 6	; Geom
	113	[570]	SELF     	15 15 -33	; "new"
	114	[570]	NEWTABLE 	17 0 2
	115	[570]	SETTABLE 	17 -43 1	; "w" -
	116	[570]	SETTABLE 	17 -44 2	; "h" -
	117	[570]	CALL     	15 3 2
	118	[570]	SETTABLE 	14 -42 15	; "dimen" -
	119	[572]	MOVE     	15 7
	120	[572]	SETLIST  	14 1 1	; 1
	121	[568]	CALL     	12 3 0
	122	[573]	SETLIST  	10 0 1	; 1
	123	[566]	TAILCALL 	8 3 0
	124	[573]	RETURN   	8 0
	125	[574]	RETURN   	0 1

function <./frontend/ui/widget/bookstatuswidget.lua:576,583> (10 instructions, 40 bytes at 0x7ff21ac0e200)
7 params, 10 slots, 1 upvalue, 7 locals, 1 constant, 1 function
	1	[577]	GETUPVAL 	7 0	; UIManager
	2	[577]	SELF     	7 7 -1	; "tickAfterNext"
	3	[582]	CLOSURE  	9 0	; 0x7ff21ac0e280
	4	[582]	MOVE     	0 1
	5	[582]	MOVE     	0 0
	6	[582]	MOVE     	0 4
	7	[582]	MOVE     	0 6
	8	[582]	GETUPVAL 	0 0	; UIManager
	9	[577]	CALL     	7 3 1
	10	[583]	RETURN   	0 1

function <./frontend/ui/widget/bookstatuswidget.lua:577,582> (16 instructions, 64 bytes at 0x7ff21ac0e280)
0 params, 6 slots, 5 upvalues, 0 locals, 3 constants, 0 functions
	1	[578]	GETUPVAL 	0 0	; values
	2	[578]	TEST     	0 0 0
	3	[578]	JMP      	5	; to 9
	4	[579]	GETUPVAL 	0 1	; self
	5	[579]	SELF     	0 0 -1	; "onChangeBookStatus"
	6	[579]	GETUPVAL 	2 2	; args
	7	[579]	GETUPVAL 	3 3	; position
	8	[579]	CALL     	0 4 1
	9	[581]	GETUPVAL 	0 4	; UIManager
	10	[581]	SELF     	0 0 -2	; "setDirty"
	11	[581]	LOADNIL  	2 2
	12	[581]	LOADK    	3 -3	; "ui"
	13	[581]	LOADNIL  	4 4
	14	[581]	LOADBOOL 	5 1 0
	15	[581]	CALL     	0 6 1
	16	[582]	RETURN   	0 1

function <./frontend/ui/widget/bookstatuswidget.lua:586,588> (4 instructions, 16 bytes at 0x7ff21ac09070)
1 param, 3 slots, 0 upvalues, 1 local, 1 constant, 0 functions
	1	[587]	SELF     	1 0 -1	; "onClose"
	2	[587]	TAILCALL 	1 2 0
	3	[587]	RETURN   	1 0
	4	[588]	RETURN   	0 1

function <./frontend/ui/widget/bookstatuswidget.lua:590,604> (26 instructions, 104 bytes at 0x7ff21ac0ea80)
3 params, 9 slots, 1 upvalue, 3 locals, 8 constants, 0 functions
	1	[591]	GETTABLE 	3 2 -1	; "direction"
	2	[591]	EQ       	0 3 -2	; - "south"
	3	[591]	JMP      	3	; to 7
	4	[593]	SELF     	3 0 -3	; "onClose"
	5	[593]	CALL     	3 2 1
	6	[593]	JMP      	19	; to 26
	7	[594]	GETTABLE 	3 2 -1	; "direction"
	8	[594]	EQ       	1 3 -4	; - "east"
	9	[594]	JMP      	16	; to 26
	10	[594]	GETTABLE 	3 2 -1	; "direction"
	11	[594]	EQ       	1 3 -5	; - "west"
	12	[594]	JMP      	13	; to 26
	13	[594]	GETTABLE 	3 2 -1	; "direction"
	14	[594]	EQ       	0 3 -6	; - "north"
	15	[594]	JMP      	1	; to 17
	16	[596]	JMP      	9	; to 26
	17	[599]	GETUPVAL 	3 0	; UIManager
	18	[599]	SELF     	3 3 -7	; "setDirty"
	19	[599]	LOADNIL  	5 5
	20	[599]	LOADK    	6 -8	; "full"
	21	[599]	LOADNIL  	7 7
	22	[599]	LOADBOOL 	8 1 0
	23	[599]	CALL     	3 6 1
	24	[602]	LOADBOOL 	3 0 0
	25	[602]	RETURN   	3 2
	26	[604]	RETURN   	0 1

function <./frontend/ui/widget/bookstatuswidget.lua:606,611> (10 instructions, 40 bytes at 0x7ff21ac0ed60)
1 param, 5 slots, 1 upvalue, 1 local, 3 constants, 0 functions
	1	[607]	SELF     	1 0 -1	; "saveSummary"
	2	[607]	CALL     	1 2 1
	3	[609]	GETUPVAL 	1 0	; UIManager
	4	[609]	SELF     	1 1 -2	; "close"
	5	[609]	MOVE     	3 0
	6	[609]	LOADK    	4 -3	; "flashpartial"
	7	[609]	CALL     	1 4 1
	8	[610]	LOADBOOL 	1 1 0
	9	[610]	RETURN   	1 2
	10	[611]	RETURN   	0 1

function <./frontend/ui/widget/bookstatuswidget.lua:613,644> (52 instructions, 208 bytes at 0x7ff21ac0ef30)
2 params, 11 slots, 4 upvalues, 2 locals, 24 constants, 2 functions
	1	[614]	GETUPVAL 	2 0	; InputDialog
	2	[614]	SELF     	2 2 -2	; "new"
	3	[614]	NEWTABLE 	4 0 8
	4	[615]	GETUPVAL 	5 1	; _
	5	[615]	LOADK    	6 -4	; "Review"
	6	[615]	CALL     	5 2 2
	7	[615]	SETTABLE 	4 -3 5	; "title" -
	8	[616]	GETTABLE 	5 0 -6	; "input_note"
	9	[616]	SELF     	5 5 -7	; "getText"
	10	[616]	CALL     	5 2 2
	11	[616]	SETTABLE 	4 -5 5	; "input" -
	12	[617]	SETTABLE 	4 -8 -9	; "input_hint" ""
	13	[618]	SETTABLE 	4 -10 -11	; "input_type" "text"
	14	[619]	SETTABLE 	4 -12 -13	; "scroll" true
	15	[620]	SETTABLE 	4 -14 -13	; "allow_newline" true
	16	[621]	GETUPVAL 	5 2	; Screen
	17	[621]	SELF     	5 5 -16	; "scaleBySize"
	18	[621]	LOADK    	7 -17	; 150
	19	[621]	CALL     	5 3 2
	20	[621]	SETTABLE 	4 -15 5	; "text_height" -
	21	[622]	NEWTABLE 	5 1 0
	22	[622]	NEWTABLE 	6 2 0
	23	[623]	NEWTABLE 	7 0 2
	24	[625]	GETUPVAL 	8 1	; _
	25	[625]	LOADK    	9 -19	; "Cancel"
	26	[625]	CALL     	8 2 2
	27	[625]	SETTABLE 	7 -11 8	; "text" -
	28	[628]	CLOSURE  	8 0	; 0x7ff21ac0f580
	29	[628]	MOVE     	0 0
	30	[628]	SETTABLE 	7 -20 8	; "callback" -
	31	[629]	NEWTABLE 	8 0 3
	32	[631]	GETUPVAL 	9 1	; _
	33	[631]	LOADK    	10 -21	; "Save review"
	34	[631]	CALL     	9 2 2
	35	[631]	SETTABLE 	8 -11 9	; "text" -
	36	[632]	SETTABLE 	8 -22 -13	; "is_enter_default" true
	37	[637]	CLOSURE  	9 1	; 0x7ff21ac0f500
	38	[637]	MOVE     	0 0
	39	[637]	SETTABLE 	8 -20 9	; "callback" -
	40	[639]	SETLIST  	6 2 1	; 1
	41	[640]	SETLIST  	5 1 1	; 1
	42	[640]	SETTABLE 	4 -18 5	; "buttons" -
	43	[614]	CALL     	2 3 2
	44	[641]	SETTABLE 	0 -1 2	; "note_dialog" -
	45	[642]	GETUPVAL 	2 3	; UIManager
	46	[642]	SELF     	2 2 -23	; "show"
	47	[642]	GETTABLE 	4 0 -1	; "note_dialog"
	48	[642]	CALL     	2 3 1
	49	[643]	GETTABLE 	2 0 -1	; "note_dialog"
	50	[643]	SELF     	2 2 -24	; "onShowKeyboard"
	51	[643]	CALL     	2 2 1
	52	[644]	RETURN   	0 1

function <./frontend/ui/widget/bookstatuswidget.lua:626,628> (4 instructions, 16 bytes at 0x7ff21ac0f580)
0 params, 2 slots, 1 upvalue, 0 locals, 1 constant, 0 functions
	1	[627]	GETUPVAL 	0 0	; self
	2	[627]	SELF     	0 0 -1	; "closeInputDialog"
	3	[627]	CALL     	0 2 1
	4	[628]	RETURN   	0 1

function <./frontend/ui/widget/bookstatuswidget.lua:633,637> (15 instructions, 60 bytes at 0x7ff21ac0f500)
0 params, 4 slots, 1 upvalue, 0 locals, 6 constants, 0 functions
	1	[634]	GETUPVAL 	0 0	; self
	2	[634]	GETTABLE 	0 0 -1	; "input_note"
	3	[634]	SELF     	0 0 -2	; "setText"
	4	[634]	GETUPVAL 	2 0	; self
	5	[634]	GETTABLE 	2 2 -3	; "note_dialog"
	6	[634]	SELF     	2 2 -4	; "getInputText"
	7	[634]	CALL     	2 2 0
	8	[634]	CALL     	0 0 1
	9	[635]	GETUPVAL 	0 0	; self
	10	[635]	SELF     	0 0 -5	; "closeInputDialog"
	11	[635]	CALL     	0 2 1
	12	[636]	GETUPVAL 	0 0	; self
	13	[636]	SELF     	0 0 -6	; "onUpdateNote"
	14	[636]	CALL     	0 2 1
	15	[637]	RETURN   	0 1

function <./frontend/ui/widget/bookstatuswidget.lua:646,648> (5 instructions, 20 bytes at 0x7ff21ac0fe60)
1 param, 4 slots, 1 upvalue, 1 local, 2 constants, 0 functions
	1	[647]	GETUPVAL 	1 0	; UIManager
	2	[647]	SELF     	1 1 -1	; "close"
	3	[647]	GETTABLE 	3 0 -2	; "note_dialog"
	4	[647]	CALL     	1 3 1
	5	[648]	RETURN   	0 1
