
main <./frontend/ui/widget/buttonprogresswidget.lua:0,0> (85 instructions, 340 bytes at 0x7f81674068f0)
0+ params, 18 slots, 0 upvalues, 13 locals, 45 constants, 7 functions
	1	[1]	GETGLOBAL	0 -1	; require
	2	[1]	LOADK    	1 -2	; "ffi/blitbuffer"
	3	[1]	CALL     	0 2 2
	4	[2]	GETGLOBAL	1 -1	; require
	5	[2]	LOADK    	2 -3	; "ui/widget/button"
	6	[2]	CALL     	1 2 2
	7	[3]	GETGLOBAL	2 -1	; require
	8	[3]	LOADK    	3 -4	; "device"
	9	[3]	CALL     	2 2 2
	10	[4]	GETGLOBAL	3 -1	; require
	11	[4]	LOADK    	4 -5	; "ui/geometry"
	12	[4]	CALL     	3 2 2
	13	[5]	GETGLOBAL	4 -1	; require
	14	[5]	LOADK    	5 -6	; "ui/widget/horizontalgroup"
	15	[5]	CALL     	4 2 2
	16	[6]	GETGLOBAL	5 -1	; require
	17	[6]	LOADK    	6 -7	; "ui/widget/horizontalspan"
	18	[6]	CALL     	5 2 2
	19	[7]	GETGLOBAL	6 -1	; require
	20	[7]	LOADK    	7 -8	; "ui/widget/container/inputcontainer"
	21	[7]	CALL     	6 2 2
	22	[8]	GETGLOBAL	7 -1	; require
	23	[8]	LOADK    	8 -9	; "ui/widget/container/framecontainer"
	24	[8]	CALL     	7 2 2
	25	[9]	GETGLOBAL	8 -1	; require
	26	[9]	LOADK    	9 -10	; "ui/size"
	27	[9]	CALL     	8 2 2
	28	[10]	GETGLOBAL	9 -1	; require
	29	[10]	LOADK    	10 -11	; "ui/uimanager"
	30	[10]	CALL     	9 2 2
	31	[11]	GETGLOBAL	10 -1	; require
	32	[11]	LOADK    	11 -12	; "gettext"
	33	[11]	CALL     	10 2 2
	34	[12]	GETTABLE 	11 2 -13	; "screen"
	35	[14]	SELF     	12 6 -14	; "new"
	36	[14]	NEWTABLE 	14 0 12
	37	[15]	SELF     	15 11 -16	; "scaleBySize"
	38	[15]	LOADK    	17 -17	; 216
	39	[15]	CALL     	15 3 2
	40	[15]	SETTABLE 	14 -15 15	; "width" -
	41	[16]	GETTABLE 	15 8 -19	; "item"
	42	[16]	GETTABLE 	15 15 -20	; "height_default"
	43	[16]	SETTABLE 	14 -18 15	; "height" -
	44	[17]	GETTABLE 	15 8 -21	; "padding"
	45	[17]	GETTABLE 	15 15 -22	; "small"
	46	[17]	SETTABLE 	14 -21 15	; "padding" -
	47	[18]	SETTABLE 	14 -23 -24	; "font_face" "cfont"
	48	[19]	SETTABLE 	14 -25 -26	; "font_size" 16
	49	[20]	SETTABLE 	14 -27 -28	; "enabled" true
	50	[21]	SETTABLE 	14 -29 -30	; "num_buttons" 2
	51	[22]	SETTABLE 	14 -31 -32	; "position" 1
	52	[23]	SETTABLE 	14 -33 -34	; "default_position" nil
	53	[24]	SETTABLE 	14 -35 -36	; "thin_grey_style" false
	54	[25]	SETTABLE 	14 -37 -36	; "fine_tune" false
	55	[26]	SETTABLE 	14 -38 -36	; "more_options" false
	56	[14]	CALL     	12 3 2
	57	[52]	CLOSURE  	13 0	; 0x7f81674070f0
	58	[52]	MOVE     	0 7
	59	[52]	MOVE     	0 0
	60	[52]	MOVE     	0 8
	61	[52]	MOVE     	0 4
	62	[52]	MOVE     	0 5
	63	[52]	MOVE     	0 3
	64	[29]	SETTABLE 	12 -39 13	; "init" -
	65	[248]	CLOSURE  	13 1	; 0x7f81674078d0
	66	[248]	MOVE     	0 8
	67	[248]	MOVE     	0 1
	68	[248]	MOVE     	0 0
	69	[248]	MOVE     	0 7
	70	[248]	MOVE     	0 9
	71	[54]	SETTABLE 	12 -40 13	; "update" -
	72	[254]	CLOSURE  	13 2	; 0x7f81674065c0
	73	[250]	SETTABLE 	12 -41 13	; "setPosition" -
	74	[259]	CLOSURE  	13 3	; 0x7f8167406700
	75	[259]	MOVE     	0 0
	76	[256]	SETTABLE 	12 -42 13	; "onFocus" -
	77	[264]	CLOSURE  	13 4	; 0x7f816740a140
	78	[264]	MOVE     	0 0
	79	[261]	SETTABLE 	12 -43 13	; "onUnfocus" -
	80	[270]	CLOSURE  	13 5	; 0x7f816740a5a0
	81	[266]	SETTABLE 	12 -44 13	; "onTapSelect" -
	82	[281]	CLOSURE  	13 6	; 0x7f816740aa00
	83	[272]	SETTABLE 	12 -45 13	; "circlePosition" -
	84	[283]	RETURN   	12 2
	85	[283]	RETURN   	0 1

function <./frontend/ui/widget/buttonprogresswidget.lua:29,52> (60 instructions, 240 bytes at 0x7f81674070f0)
1 param, 5 slots, 6 upvalues, 1 local, 24 constants, 0 functions
	1	[30]	GETUPVAL 	1 0	; FrameContainer
	2	[30]	SELF     	1 1 -2	; "new"
	3	[30]	NEWTABLE 	3 0 6
	4	[31]	GETUPVAL 	4 1	; Blitbuffer
	5	[31]	GETTABLE 	4 4 -4	; "COLOR_WHITE"
	6	[31]	SETTABLE 	3 -3 4	; "background" -
	7	[32]	GETUPVAL 	4 1	; Blitbuffer
	8	[32]	GETTABLE 	4 4 -6	; "COLOR_DARK_GRAY"
	9	[32]	SETTABLE 	3 -5 4	; "color" -
	10	[33]	GETUPVAL 	4 2	; Size
	11	[33]	GETTABLE 	4 4 -7	; "radius"
	12	[33]	GETTABLE 	4 4 -8	; "window"
	13	[33]	SETTABLE 	3 -7 4	; "radius" -
	14	[34]	SETTABLE 	3 -9 -10	; "bordersize" 0
	15	[35]	GETTABLE 	4 0 -11	; "padding"
	16	[35]	SETTABLE 	3 -11 4	; "padding" -
	17	[36]	GETTABLE 	4 0 -13	; "enabled"
	18	[36]	NOT      	4 4
	19	[36]	SETTABLE 	3 -12 4	; "dim" -
	20	[30]	CALL     	1 3 2
	21	[37]	SETTABLE 	0 -1 1	; "buttonprogress_frame" -
	22	[40]	GETUPVAL 	1 3	; HorizontalGroup
	23	[40]	SELF     	1 1 -2	; "new"
	24	[40]	NEWTABLE 	3 0 0
	25	[40]	CALL     	1 3 2
	26	[40]	SETTABLE 	0 -14 1	; "buttonprogress_content" -
	27	[41]	SETTABLE 	0 -15 -10	; "horizontal_span_width" 0
	28	[42]	GETTABLE 	1 0 -16	; "fine_tune"
	29	[42]	TEST     	1 0 1
	30	[42]	JMP      	3	; to 34
	31	[42]	GETTABLE 	1 0 -17	; "more_options"
	32	[42]	TEST     	1 0 0
	33	[42]	JMP      	12	; to 46
	34	[43]	GETUPVAL 	1 4	; HorizontalSpan
	35	[43]	SELF     	1 1 -2	; "new"
	36	[43]	NEWTABLE 	3 0 1
	37	[44]	GETUPVAL 	4 2	; Size
	38	[44]	GETTABLE 	4 4 -20	; "margin"
	39	[44]	GETTABLE 	4 4 -16	; "fine_tune"
	40	[44]	SETTABLE 	3 -19 4	; "width" -
	41	[43]	CALL     	1 3 2
	42	[45]	SETTABLE 	0 -18 1	; "horizontal_span" -
	43	[46]	GETTABLE 	1 0 -18	; "horizontal_span"
	44	[46]	GETTABLE 	1 1 -19	; "width"
	45	[46]	SETTABLE 	0 -15 1	; "horizontal_span_width" -
	46	[48]	SELF     	1 0 -21	; "update"
	47	[48]	CALL     	1 2 1
	48	[49]	GETTABLE 	1 0 -1	; "buttonprogress_frame"
	49	[49]	GETTABLE 	2 0 -14	; "buttonprogress_content"
	50	[49]	SETTABLE 	1 -22 2	; 1 -
	51	[50]	GETTABLE 	1 0 -1	; "buttonprogress_frame"
	52	[50]	SETTABLE 	0 -22 1	; 1 -
	53	[51]	GETUPVAL 	1 5	; Geom
	54	[51]	SELF     	1 1 -2	; "new"
	55	[51]	GETTABLE 	3 0 -1	; "buttonprogress_frame"
	56	[51]	SELF     	3 3 -24	; "getSize"
	57	[51]	CALL     	3 2 0
	58	[51]	CALL     	1 0 2
	59	[51]	SETTABLE 	0 -23 1	; "dimen" -
	60	[52]	RETURN   	0 1

function <./frontend/ui/widget/buttonprogresswidget.lua:54,248> (335 instructions, 1340 bytes at 0x7f81674078d0)
1 param, 24 slots, 5 upvalues, 31 locals, 51 constants, 9 functions
	1	[55]	GETTABLE 	1 0 -1	; "buttonprogress_content"
	2	[55]	SELF     	1 1 -2	; "clear"
	3	[55]	CALL     	1 2 1
	4	[56]	GETUPVAL 	1 0	; Size
	5	[56]	GETTABLE 	1 1 -3	; "margin"
	6	[56]	GETTABLE 	1 1 -4	; "tiny"
	7	[57]	GETUPVAL 	2 0	; Size
	8	[57]	GETTABLE 	2 2 -5	; "padding"
	9	[57]	GETTABLE 	2 2 -6	; "button"
	10	[58]	GETTABLE 	3 0 -7	; "thin_grey_style"
	11	[58]	TEST     	3 0 0
	12	[58]	JMP      	5	; to 18
	13	[58]	GETUPVAL 	3 0	; Size
	14	[58]	GETTABLE 	3 3 -8	; "border"
	15	[58]	GETTABLE 	3 3 -9	; "thin"
	16	[58]	TEST     	3 0 1
	17	[58]	JMP      	3	; to 21
	18	[58]	GETUPVAL 	3 0	; Size
	19	[58]	GETTABLE 	3 3 -8	; "border"
	20	[58]	GETTABLE 	3 3 -6	; "button"
	21	[59]	GETTABLE 	4 0 -10	; "num_buttons"
	22	[60]	LOADK    	5 -11	; 0
	23	[61]	GETTABLE 	6 0 -12	; "fine_tune"
	24	[61]	TEST     	6 0 0
	25	[61]	JMP      	2	; to 28
	26	[62]	ADD      	4 4 -13	; - 2
	27	[63]	LOADK    	5 -13	; 2
	28	[65]	GETTABLE 	6 0 -14	; "more_options"
	29	[65]	TEST     	6 0 0
	30	[65]	JMP      	2	; to 33
	31	[66]	ADD      	4 4 -15	; - 1
	32	[67]	ADD      	5 5 -15	; - 1
	33	[69]	GETTABLE 	6 0 -16	; "width"
	34	[69]	GETTABLE 	7 0 -17	; "horizontal_span_width"
	35	[69]	MUL      	7 5 7
	36	[69]	SUB      	6 6 7
	37	[69]	DIV      	6 6 4
	38	[69]	MUL      	7 -13 2	; 2 -
	39	[69]	SUB      	6 6 7
	40	[69]	MUL      	7 -13 1	; 2 -
	41	[69]	SUB      	6 6 7
	42	[69]	MUL      	7 -13 3	; 2 -
	43	[69]	SUB      	6 6 7
	44	[70]	GETGLOBAL	7 -18	; math
	45	[70]	GETTABLE 	7 7 -19	; "floor"
	46	[70]	MOVE     	8 6
	47	[70]	CALL     	7 2 2
	48	[71]	SUB      	8 6 7
	49	[72]	LOADK    	9 -11	; 0
	50	[75]	GETTABLE 	10 0 -12	; "fine_tune"
	51	[75]	TEST     	10 0 0
	52	[75]	JMP      	46	; to 99
	53	[76]	ADD      	9 9 8
	54	[77]	MOVE     	10 1
	55	[78]	LOADK    	11 -11	; 0
	56	[79]	GETUPVAL 	12 1	; Button
	57	[79]	SELF     	12 12 -20	; "new"
	58	[79]	NEWTABLE 	14 0 13
	59	[80]	SETTABLE 	14 -21 -22	; "text" "-"
	60	[81]	SETTABLE 	14 -23 -11	; "radius" 0
	61	[82]	SETTABLE 	14 -3 10	; "margin" -
	62	[83]	SETTABLE 	14 -5 2	; "padding" -
	63	[84]	ADD      	15 3 11
	64	[84]	SETTABLE 	14 -24 15	; "bordersize" -
	65	[85]	SETTABLE 	14 -25 -26	; "enabled" true
	66	[86]	MUL      	15 -13 11	; 2 -
	67	[86]	SUB      	15 7 15
	68	[86]	SETTABLE 	14 -16 15	; "width" -
	69	[87]	SETTABLE 	14 -27 -28	; "preselect" false
	70	[88]	GETTABLE 	15 0 -30	; "font_face"
	71	[88]	SETTABLE 	14 -29 15	; "text_font_face" -
	72	[89]	GETTABLE 	15 0 -32	; "font_size"
	73	[89]	SETTABLE 	14 -31 15	; "text_font_size" -
	74	[93]	CLOSURE  	15 0	; 0x7f8167407f80
	75	[93]	MOVE     	0 0
	76	[93]	SETTABLE 	14 -33 15	; "callback" -
	77	[94]	SETTABLE 	14 -34 -26	; "no_focus" true
	78	[97]	CLOSURE  	15 1	; 0x7f81674083f0
	79	[97]	MOVE     	0 0
	80	[97]	SETTABLE 	14 -35 15	; "hold_callback" -
	81	[79]	CALL     	12 3 2
	82	[99]	GETTABLE 	13 0 -7	; "thin_grey_style"
	83	[99]	TEST     	13 0 0
	84	[99]	JMP      	4	; to 89
	85	[100]	GETTABLE 	13 12 -36	; "frame"
	86	[100]	GETUPVAL 	14 2	; Blitbuffer
	87	[100]	GETTABLE 	14 14 -38	; "COLOR_DARK_GRAY"
	88	[100]	SETTABLE 	13 -37 14	; "color" -
	89	[102]	GETGLOBAL	13 -39	; table
	90	[102]	GETTABLE 	13 13 -40	; "insert"
	91	[102]	GETTABLE 	14 0 -1	; "buttonprogress_content"
	92	[102]	MOVE     	15 12
	93	[102]	CALL     	13 3 1
	94	[103]	GETGLOBAL	13 -39	; table
	95	[103]	GETTABLE 	13 13 -40	; "insert"
	96	[103]	GETTABLE 	14 0 -1	; "buttonprogress_content"
	97	[103]	GETTABLE 	15 0 -41	; "horizontal_span"
	98	[103]	CALL     	13 3 1
	99	[107]	LOADK    	10 -15	; 1
	100	[107]	GETTABLE 	11 0 -10	; "num_buttons"
	101	[107]	LOADK    	12 -15	; 1
	102	[107]	FORPREP  	10 106	; to 209
	103	[108]	ADD      	9 9 8
	104	[109]	MOVE     	14 7
	105	[110]	LE       	0 -15 9	; 1 -
	106	[110]	JMP      	10	; to 117
	107	[112]	GETGLOBAL	15 -18	; math
	108	[112]	GETTABLE 	15 15 -19	; "floor"
	109	[112]	MOVE     	16 9
	110	[112]	CALL     	15 2 2
	111	[112]	ADD      	14 7 15
	112	[113]	GETGLOBAL	15 -18	; math
	113	[113]	GETTABLE 	15 15 -19	; "floor"
	114	[113]	MOVE     	16 9
	115	[113]	CALL     	15 2 2
	116	[113]	SUB      	9 9 15
	117	[115]	GETTABLE 	15 0 -42	; "position"
	118	[115]	LE       	1 13 15
	119	[115]	JMP      	1	; to 121
	120	[115]	LOADBOOL 	15 0 1
	121	[115]	LOADBOOL 	15 1 0
	122	[116]	GETTABLE 	16 0 -43	; "default_position"
	123	[116]	EQ       	1 13 16
	124	[116]	JMP      	1	; to 126
	125	[116]	LOADBOOL 	16 0 1
	126	[116]	LOADBOOL 	16 1 0
	127	[117]	MOVE     	17 1
	128	[118]	GETTABLE 	18 0 -7	; "thin_grey_style"
	129	[118]	TEST     	18 0 0
	130	[118]	JMP      	3	; to 134
	131	[118]	TEST     	15 0 0
	132	[118]	JMP      	1	; to 134
	133	[119]	LOADK    	17 -11	; 0
	134	[121]	LOADK    	18 -11	; 0
	135	[122]	GETTABLE 	19 0 -7	; "thin_grey_style"
	136	[122]	TEST     	19 0 1
	137	[122]	JMP      	5	; to 143
	138	[122]	TEST     	16 0 0
	139	[122]	JMP      	3	; to 143
	140	[124]	GETUPVAL 	19 0	; Size
	141	[124]	GETTABLE 	19 19 -8	; "border"
	142	[124]	GETTABLE 	18 19 -9	; "thin"
	143	[126]	GETUPVAL 	19 1	; Button
	144	[126]	SELF     	19 19 -20	; "new"
	145	[126]	NEWTABLE 	21 0 13
	146	[127]	SETTABLE 	21 -21 -44	; "text" ""
	147	[128]	SETTABLE 	21 -23 -11	; "radius" 0
	148	[129]	SETTABLE 	21 -3 17	; "margin" -
	149	[130]	SETTABLE 	21 -5 2	; "padding" -
	150	[131]	ADD      	22 3 18
	151	[131]	SETTABLE 	21 -24 22	; "bordersize" -
	152	[132]	SETTABLE 	21 -25 -26	; "enabled" true
	153	[133]	MUL      	22 -13 18	; 2 -
	154	[133]	SUB      	22 14 22
	155	[133]	SETTABLE 	21 -16 22	; "width" -
	156	[134]	SETTABLE 	21 -27 15	; "preselect" -
	157	[135]	GETTABLE 	22 0 -30	; "font_face"
	158	[135]	SETTABLE 	21 -29 22	; "text_font_face" -
	159	[136]	GETTABLE 	22 0 -32	; "font_size"
	160	[136]	SETTABLE 	21 -31 22	; "text_font_size" -
	161	[141]	CLOSURE  	22 2	; 0x7f81674084f0
	162	[141]	MOVE     	0 0
	163	[141]	MOVE     	0 13
	164	[141]	SETTABLE 	21 -33 22	; "callback" -
	165	[142]	SETTABLE 	21 -34 -26	; "no_focus" true
	166	[145]	CLOSURE  	22 3	; 0x7f8167408870
	167	[145]	MOVE     	0 0
	168	[145]	MOVE     	0 13
	169	[145]	SETTABLE 	21 -35 22	; "hold_callback" -
	170	[126]	CALL     	19 3 2
	171	[147]	GETTABLE 	20 0 -7	; "thin_grey_style"
	172	[147]	TEST     	20 0 0
	173	[147]	JMP      	29	; to 203
	174	[148]	TEST     	16 0 0
	175	[148]	JMP      	5	; to 181
	176	[150]	GETTABLE 	20 19 -36	; "frame"
	177	[150]	GETUPVAL 	21 2	; Blitbuffer
	178	[150]	GETTABLE 	21 21 -45	; "COLOR_BLACK"
	179	[150]	SETTABLE 	20 -37 21	; "color" -
	180	[150]	JMP      	4	; to 185
	181	[154]	GETTABLE 	20 19 -36	; "frame"
	182	[154]	GETUPVAL 	21 2	; Blitbuffer
	183	[154]	GETTABLE 	21 21 -38	; "COLOR_DARK_GRAY"
	184	[154]	SETTABLE 	20 -37 21	; "color" -
	185	[156]	TEST     	15 0 0
	186	[156]	JMP      	16	; to 203
	187	[159]	GETTABLE 	20 19 -36	; "frame"
	188	[159]	GETUPVAL 	21 2	; Blitbuffer
	189	[159]	GETTABLE 	21 21 -38	; "COLOR_DARK_GRAY"
	190	[159]	SELF     	21 21 -47	; "invert"
	191	[159]	CALL     	21 2 2
	192	[159]	SETTABLE 	20 -46 21	; "background" -
	193	[160]	GETUPVAL 	20 3	; FrameContainer
	194	[160]	SELF     	20 20 -20	; "new"
	195	[160]	NEWTABLE 	22 1 3
	196	[161]	SETTABLE 	22 -3 1	; "margin" -
	197	[162]	SETTABLE 	22 -5 -11	; "padding" 0
	198	[163]	SETTABLE 	22 -24 -11	; "bordersize" 0
	199	[165]	MOVE     	23 19
	200	[165]	SETLIST  	22 1 1	; 1
	201	[160]	CALL     	20 3 2
	202	[165]	MOVE     	19 20
	203	[168]	GETGLOBAL	20 -39	; table
	204	[168]	GETTABLE 	20 20 -40	; "insert"
	205	[168]	GETTABLE 	21 0 -1	; "buttonprogress_content"
	206	[168]	MOVE     	22 19
	207	[168]	CALL     	20 3 1
	208	[168]	CLOSE    	13
	209	[107]	FORLOOP  	10 -107	; to 103
	210	[172]	GETTABLE 	10 0 -12	; "fine_tune"
	211	[172]	TEST     	10 0 0
	212	[172]	JMP      	59	; to 272
	213	[173]	ADD      	9 9 8
	214	[174]	MOVE     	10 7
	215	[175]	LE       	0 -15 9	; 1 -
	216	[175]	JMP      	10	; to 227
	217	[177]	GETGLOBAL	11 -18	; math
	218	[177]	GETTABLE 	11 11 -19	; "floor"
	219	[177]	MOVE     	12 9
	220	[177]	CALL     	11 2 2
	221	[177]	ADD      	10 7 11
	222	[178]	GETGLOBAL	11 -18	; math
	223	[178]	GETTABLE 	11 11 -19	; "floor"
	224	[178]	MOVE     	12 9
	225	[178]	CALL     	11 2 2
	226	[178]	SUB      	9 9 11
	227	[180]	MOVE     	11 1
	228	[181]	LOADK    	12 -11	; 0
	229	[182]	GETUPVAL 	13 1	; Button
	230	[182]	SELF     	13 13 -20	; "new"
	231	[182]	NEWTABLE 	15 0 13
	232	[183]	SETTABLE 	15 -21 -48	; "text" "+"
	233	[184]	SETTABLE 	15 -23 -11	; "radius" 0
	234	[185]	SETTABLE 	15 -3 11	; "margin" -
	235	[186]	SETTABLE 	15 -5 2	; "padding" -
	236	[187]	ADD      	16 3 12
	237	[187]	SETTABLE 	15 -24 16	; "bordersize" -
	238	[188]	SETTABLE 	15 -25 -26	; "enabled" true
	239	[189]	MUL      	16 -13 12	; 2 -
	240	[189]	SUB      	16 10 16
	241	[189]	SETTABLE 	15 -16 16	; "width" -
	242	[190]	SETTABLE 	15 -27 -28	; "preselect" false
	243	[191]	GETTABLE 	16 0 -30	; "font_face"
	244	[191]	SETTABLE 	15 -29 16	; "text_font_face" -
	245	[192]	GETTABLE 	16 0 -32	; "font_size"
	246	[192]	SETTABLE 	15 -31 16	; "text_font_size" -
	247	[196]	CLOSURE  	16 4	; 0x7f8167408d90
	248	[196]	MOVE     	0 0
	249	[196]	SETTABLE 	15 -33 16	; "callback" -
	250	[197]	SETTABLE 	15 -34 -26	; "no_focus" true
	251	[200]	CLOSURE  	16 5	; 0x7f8167408ef0
	252	[200]	MOVE     	0 0
	253	[200]	SETTABLE 	15 -35 16	; "hold_callback" -
	254	[182]	CALL     	13 3 2
	255	[202]	GETTABLE 	14 0 -7	; "thin_grey_style"
	256	[202]	TEST     	14 0 0
	257	[202]	JMP      	4	; to 262
	258	[203]	GETTABLE 	14 13 -36	; "frame"
	259	[203]	GETUPVAL 	15 2	; Blitbuffer
	260	[203]	GETTABLE 	15 15 -38	; "COLOR_DARK_GRAY"
	261	[203]	SETTABLE 	14 -37 15	; "color" -
	262	[205]	GETGLOBAL	14 -39	; table
	263	[205]	GETTABLE 	14 14 -40	; "insert"
	264	[205]	GETTABLE 	15 0 -1	; "buttonprogress_content"
	265	[205]	GETTABLE 	16 0 -41	; "horizontal_span"
	266	[205]	CALL     	14 3 1
	267	[206]	GETGLOBAL	14 -39	; table
	268	[206]	GETTABLE 	14 14 -40	; "insert"
	269	[206]	GETTABLE 	15 0 -1	; "buttonprogress_content"
	270	[206]	MOVE     	16 13
	271	[206]	CALL     	14 3 1
	272	[209]	GETTABLE 	10 0 -14	; "more_options"
	273	[209]	TEST     	10 0 0
	274	[209]	JMP      	54	; to 329
	275	[210]	ADD      	9 9 8
	276	[211]	MOVE     	10 7
	277	[212]	LE       	0 -15 9	; 1 -
	278	[212]	JMP      	5	; to 284
	279	[214]	GETGLOBAL	11 -18	; math
	280	[214]	GETTABLE 	11 11 -19	; "floor"
	281	[214]	MOVE     	12 9
	282	[214]	CALL     	11 2 2
	283	[214]	ADD      	10 7 11
	284	[216]	MOVE     	11 1
	285	[217]	LOADK    	12 -11	; 0
	286	[218]	GETUPVAL 	13 1	; Button
	287	[218]	SELF     	13 13 -20	; "new"
	288	[218]	NEWTABLE 	15 0 13
	289	[219]	SETTABLE 	15 -21 -49	; "text" "\226\139\174"
	290	[220]	SETTABLE 	15 -23 -11	; "radius" 0
	291	[221]	SETTABLE 	15 -3 11	; "margin" -
	292	[222]	SETTABLE 	15 -5 2	; "padding" -
	293	[223]	ADD      	16 3 12
	294	[223]	SETTABLE 	15 -24 16	; "bordersize" -
	295	[224]	SETTABLE 	15 -25 -26	; "enabled" true
	296	[225]	MUL      	16 -13 12	; 2 -
	297	[225]	SUB      	16 10 16
	298	[225]	SETTABLE 	15 -16 16	; "width" -
	299	[226]	SETTABLE 	15 -27 -28	; "preselect" false
	300	[227]	GETTABLE 	16 0 -30	; "font_face"
	301	[227]	SETTABLE 	15 -29 16	; "text_font_face" -
	302	[228]	GETTABLE 	16 0 -32	; "font_size"
	303	[228]	SETTABLE 	15 -31 16	; "text_font_size" -
	304	[232]	CLOSURE  	16 6	; 0x7f8167409280
	305	[232]	MOVE     	0 0
	306	[232]	SETTABLE 	15 -33 16	; "callback" -
	307	[233]	SETTABLE 	15 -34 -26	; "no_focus" true
	308	[236]	CLOSURE  	16 7	; 0x7f81674095a0
	309	[236]	MOVE     	0 0
	310	[236]	SETTABLE 	15 -35 16	; "hold_callback" -
	311	[218]	CALL     	13 3 2
	312	[238]	GETTABLE 	14 0 -7	; "thin_grey_style"
	313	[238]	TEST     	14 0 0
	314	[238]	JMP      	4	; to 319
	315	[239]	GETTABLE 	14 13 -36	; "frame"
	316	[239]	GETUPVAL 	15 2	; Blitbuffer
	317	[239]	GETTABLE 	15 15 -38	; "COLOR_DARK_GRAY"
	318	[239]	SETTABLE 	14 -37 15	; "color" -
	319	[241]	GETGLOBAL	14 -39	; table
	320	[241]	GETTABLE 	14 14 -40	; "insert"
	321	[241]	GETTABLE 	15 0 -1	; "buttonprogress_content"
	322	[241]	GETTABLE 	16 0 -41	; "horizontal_span"
	323	[241]	CALL     	14 3 1
	324	[242]	GETGLOBAL	14 -39	; table
	325	[242]	GETTABLE 	14 14 -40	; "insert"
	326	[242]	GETTABLE 	15 0 -1	; "buttonprogress_content"
	327	[242]	MOVE     	16 13
	328	[242]	CALL     	14 3 1
	329	[245]	GETUPVAL 	10 4	; UIManager
	330	[245]	SELF     	10 10 -50	; "setDirty"
	331	[245]	GETTABLE 	12 0 -51	; "show_parrent"
	332	[247]	CLOSURE  	13 8	; 0x7f8167409760
	333	[247]	MOVE     	0 0
	334	[245]	CALL     	10 4 1
	335	[248]	RETURN   	0 1

function <./frontend/ui/widget/buttonprogresswidget.lua:90,93> (8 instructions, 32 bytes at 0x7f8167407f80)
0 params, 2 slots, 1 upvalue, 0 locals, 3 constants, 0 functions
	1	[91]	GETUPVAL 	0 0	; self
	2	[91]	GETTABLE 	0 0 -1	; "callback"
	3	[91]	LOADK    	1 -2	; "-"
	4	[91]	CALL     	0 2 1
	5	[92]	GETUPVAL 	0 0	; self
	6	[92]	SELF     	0 0 -3	; "update"
	7	[92]	CALL     	0 2 1
	8	[93]	RETURN   	0 1

function <./frontend/ui/widget/buttonprogresswidget.lua:95,97> (5 instructions, 20 bytes at 0x7f81674083f0)
0 params, 2 slots, 1 upvalue, 0 locals, 2 constants, 0 functions
	1	[96]	GETUPVAL 	0 0	; self
	2	[96]	GETTABLE 	0 0 -1	; "hold_callback"
	3	[96]	LOADK    	1 -2	; "-"
	4	[96]	CALL     	0 2 1
	5	[97]	RETURN   	0 1

function <./frontend/ui/widget/buttonprogresswidget.lua:137,141> (11 instructions, 44 bytes at 0x7f81674084f0)
0 params, 2 slots, 2 upvalues, 0 locals, 3 constants, 0 functions
	1	[138]	GETUPVAL 	0 0	; self
	2	[138]	GETTABLE 	0 0 -1	; "callback"
	3	[138]	GETUPVAL 	1 1	; i
	4	[138]	CALL     	0 2 1
	5	[139]	GETUPVAL 	0 0	; self
	6	[139]	GETUPVAL 	1 1	; i
	7	[139]	SETTABLE 	0 -2 1	; "position" -
	8	[140]	GETUPVAL 	0 0	; self
	9	[140]	SELF     	0 0 -3	; "update"
	10	[140]	CALL     	0 2 1
	11	[141]	RETURN   	0 1

function <./frontend/ui/widget/buttonprogresswidget.lua:143,145> (5 instructions, 20 bytes at 0x7f8167408870)
0 params, 2 slots, 2 upvalues, 0 locals, 1 constant, 0 functions
	1	[144]	GETUPVAL 	0 0	; self
	2	[144]	GETTABLE 	0 0 -1	; "hold_callback"
	3	[144]	GETUPVAL 	1 1	; i
	4	[144]	CALL     	0 2 1
	5	[145]	RETURN   	0 1

function <./frontend/ui/widget/buttonprogresswidget.lua:193,196> (8 instructions, 32 bytes at 0x7f8167408d90)
0 params, 2 slots, 1 upvalue, 0 locals, 3 constants, 0 functions
	1	[194]	GETUPVAL 	0 0	; self
	2	[194]	GETTABLE 	0 0 -1	; "callback"
	3	[194]	LOADK    	1 -2	; "+"
	4	[194]	CALL     	0 2 1
	5	[195]	GETUPVAL 	0 0	; self
	6	[195]	SELF     	0 0 -3	; "update"
	7	[195]	CALL     	0 2 1
	8	[196]	RETURN   	0 1

function <./frontend/ui/widget/buttonprogresswidget.lua:198,200> (5 instructions, 20 bytes at 0x7f8167408ef0)
0 params, 2 slots, 1 upvalue, 0 locals, 2 constants, 0 functions
	1	[199]	GETUPVAL 	0 0	; self
	2	[199]	GETTABLE 	0 0 -1	; "hold_callback"
	3	[199]	LOADK    	1 -2	; "+"
	4	[199]	CALL     	0 2 1
	5	[200]	RETURN   	0 1

function <./frontend/ui/widget/buttonprogresswidget.lua:229,232> (8 instructions, 32 bytes at 0x7f8167409280)
0 params, 2 slots, 1 upvalue, 0 locals, 3 constants, 0 functions
	1	[230]	GETUPVAL 	0 0	; self
	2	[230]	GETTABLE 	0 0 -1	; "callback"
	3	[230]	LOADK    	1 -2	; "\226\139\174"
	4	[230]	CALL     	0 2 1
	5	[231]	GETUPVAL 	0 0	; self
	6	[231]	SELF     	0 0 -3	; "update"
	7	[231]	CALL     	0 2 1
	8	[232]	RETURN   	0 1

function <./frontend/ui/widget/buttonprogresswidget.lua:234,236> (5 instructions, 20 bytes at 0x7f81674095a0)
0 params, 2 slots, 1 upvalue, 0 locals, 2 constants, 0 functions
	1	[235]	GETUPVAL 	0 0	; self
	2	[235]	GETTABLE 	0 0 -1	; "hold_callback"
	3	[235]	LOADK    	1 -2	; "\226\139\174"
	4	[235]	CALL     	0 2 1
	5	[236]	RETURN   	0 1

function <./frontend/ui/widget/buttonprogresswidget.lua:245,247> (5 instructions, 20 bytes at 0x7f8167409760)
0 params, 2 slots, 1 upvalue, 0 locals, 2 constants, 0 functions
	1	[246]	LOADK    	0 -1	; "ui"
	2	[246]	GETUPVAL 	1 0	; self
	3	[246]	GETTABLE 	1 1 -2	; "dimen"
	4	[246]	RETURN   	0 3
	5	[247]	RETURN   	0 1

function <./frontend/ui/widget/buttonprogresswidget.lua:250,254> (5 instructions, 20 bytes at 0x7f81674065c0)
3 params, 5 slots, 0 upvalues, 3 locals, 3 constants, 0 functions
	1	[251]	SETTABLE 	0 -1 1	; "position" -
	2	[252]	SETTABLE 	0 -2 2	; "default_position" -
	3	[253]	SELF     	3 0 -3	; "update"
	4	[253]	CALL     	3 2 1
	5	[254]	RETURN   	0 1

function <./frontend/ui/widget/buttonprogresswidget.lua:256,259> (7 instructions, 28 bytes at 0x7f8167406700)
1 param, 3 slots, 1 upvalue, 1 local, 3 constants, 0 functions
	1	[257]	GETTABLE 	1 0 -1	; "buttonprogress_frame"
	2	[257]	GETUPVAL 	2 0	; Blitbuffer
	3	[257]	GETTABLE 	2 2 -3	; "COLOR_BLACK"
	4	[257]	SETTABLE 	1 -2 2	; "background" -
	5	[258]	LOADBOOL 	1 1 0
	6	[258]	RETURN   	1 2
	7	[259]	RETURN   	0 1

function <./frontend/ui/widget/buttonprogresswidget.lua:261,264> (7 instructions, 28 bytes at 0x7f816740a140)
1 param, 3 slots, 1 upvalue, 1 local, 3 constants, 0 functions
	1	[262]	GETTABLE 	1 0 -1	; "buttonprogress_frame"
	2	[262]	GETUPVAL 	2 0	; Blitbuffer
	3	[262]	GETTABLE 	2 2 -3	; "COLOR_WHITE"
	4	[262]	SETTABLE 	1 -2 2	; "background" -
	5	[263]	LOADBOOL 	1 1 0
	6	[263]	RETURN   	1 2
	7	[264]	RETURN   	0 1

function <./frontend/ui/widget/buttonprogresswidget.lua:266,270> (5 instructions, 20 bytes at 0x7f816740a5a0)
3 params, 5 slots, 0 upvalues, 3 locals, 2 constants, 0 functions
	1	[267]	EQ       	0 2 -1	; - nil
	2	[267]	JMP      	2	; to 5
	3	[268]	SELF     	3 0 -2	; "circlePosition"
	4	[268]	CALL     	3 2 1
	5	[270]	RETURN   	0 1

function <./frontend/ui/widget/buttonprogresswidget.lua:272,281> (17 instructions, 68 bytes at 0x7f816740aa00)
1 param, 3 slots, 0 upvalues, 1 local, 5 constants, 0 functions
	1	[273]	GETTABLE 	1 0 -1	; "position"
	2	[273]	TEST     	1 0 0
	3	[273]	JMP      	13	; to 17
	4	[274]	GETTABLE 	1 0 -1	; "position"
	5	[274]	ADD      	1 1 -2	; - 1
	6	[274]	SETTABLE 	0 -1 1	; "position" -
	7	[275]	GETTABLE 	1 0 -1	; "position"
	8	[275]	GETTABLE 	2 0 -3	; "num_buttons"
	9	[275]	LT       	0 2 1
	10	[275]	JMP      	1	; to 12
	11	[276]	SETTABLE 	0 -1 -2	; "position" 1
	12	[278]	GETTABLE 	1 0 -4	; "callback"
	13	[278]	GETTABLE 	2 0 -1	; "position"
	14	[278]	CALL     	1 2 1
	15	[279]	SELF     	1 0 -5	; "update"
	16	[279]	CALL     	1 2 1
	17	[281]	RETURN   	0 1
