-- BYTECODE -- buttondialogtitle.lua:34-88
0001    TGETS    1   0   0  ; "dismissable"
0002    ISF          1
0003    JMP      2 => 0047
0004    UGET     1   0      ; Device
0005    MOV      2   1
0006    TGETS    1   1   1  ; "hasKeys"
0007    CALL     1   2   2
0008    ISF          1
0009    JMP      2 => 0016
0010    TDUP     1   5
0011    TDUP     2   4
0012    TDUP     3   3
0013    TSETB    3   2   1
0014    TSETS    2   1   6  ; "Close"
0015    TSETS    1   0   2  ; "key_events"
0016 => UGET     1   0      ; Device
0017    MOV      2   1
0018    TGETS    1   1   7  ; "isTouchDevice"
0019    CALL     1   2   2
0020    ISF          1
0021    JMP      2 => 0047
0022    TGETS    1   0   8  ; "ges_events"
0023    TNEW     2   3
0024    UGET     3   1      ; GestureRange
0025    MOV      4   3
0026    TGETS    3   3  10  ; "new"
0027    TDUP     5  11
0028    UGET     6   2      ; Geom
0029    MOV      7   6
0030    TGETS    6   6  10  ; "new"
0031    TDUP     8  12
0032    UGET     9   3      ; Screen
0033    MOV     10   9
0034    TGETS    9   9  13  ; "getWidth"
0035    CALL     9   2   2
0036    TSETS    9   8  14  ; "w"
0037    UGET     9   3      ; Screen
0038    MOV     10   9
0039    TGETS    9   9  15  ; "getHeight"
0040    CALL     9   2   2
0041    TSETS    9   8  16  ; "h"
0042    CALL     6   2   3
0043    TSETS    6   5  17  ; "range"
0044    CALL     3   0   3
0045    TSETM    3   0      ; 1
0046    TSETS    2   1   9  ; "TapClose"
0047 => UGET     1   4      ; CenterContainer
0048    MOV      2   1
0049    TGETS    1   1  10  ; "new"
0050    TDUP     3  19
0051    UGET     4   3      ; Screen
0052    MOV      5   4
0053    TGETS    4   4  18  ; "getSize"
0054    CALL     4   2   2
0055    TSETS    4   3  20  ; "dimen"
0056    UGET     4   5      ; MovableContainer
0057    MOV      5   4
0058    TGETS    4   4  10  ; "new"
0059    TNEW     6   3
0060    UGET     7   6      ; FrameContainer
0061    MOV      8   7
0062    TGETS    7   7  10  ; "new"
0063    TDUP     9  47
0064    UGET    10   7      ; VerticalGroup
0065    MOV     11  10
0066    TGETS   10  10  10  ; "new"
0067    TDUP    12  21
0068    UGET    13   6      ; FrameContainer
0069    MOV     14  13
0070    TGETS   13  13  10  ; "new"
0071    TDUP    15  25
0072    TGETS   16   0  22  ; "use_info_style"
0073    ISF         16
0074    JMP     17 => 0078
0075    TGETS   16   0  23  ; "info_padding"
0076    IST         16
0077    JMP     17 => 0079
0078 => TGETS   16   0  24  ; "title_padding"
0079 => TSETS   16  15  26  ; "padding"
0080    TGETS   16   0  22  ; "use_info_style"
0081    ISF         16
0082    JMP     17 => 0086
0083    TGETS   16   0  27  ; "info_margin"
0084    IST         16
0085    JMP     17 => 0087
0086 => TGETS   16   0  28  ; "title_margin"
0087 => TSETS   16  15  29  ; "margin"
0088    UGET    16   8      ; TextBoxWidget
0089    MOV     17  16
0090    TGETS   16  16  10  ; "new"
0091    TDUP    18  31
0092    TGETS   19   0  30  ; "title"
0093    TSETS   19  18  32  ; "text"
0094    UGET    19   3      ; Screen
0095    MOV     20  19
0096    TGETS   19  19  13  ; "getWidth"
0097    CALL    19   2   2
0098    MULVN   19  19   1  ; 0.8
0099    TSETS   19  18  33  ; "width"
0100    TGETS   19   0  22  ; "use_info_style"
0101    ISF         19
0102    JMP     20 => 0106
0103    TGETS   19   0  34  ; "info_face"
0104    IST         19
0105    JMP     20 => 0107
0106 => TGETS   19   0  35  ; "title_face"
0107 => TSETS   19  18  36  ; "face"
0108    TGETS   19   0  37  ; "title_align"
0109    IST         19
0110    JMP     20 => 0112
0111    KSTR    19  38      ; "left"
0112 => TSETS   19  18  39  ; "alignment"
0113    CALL    16   0   3
0114    TSETM   16   0      ; 1
0115    CALL    13   2   3
0116    TSETB   13  12   1
0117    UGET    13   9      ; VerticalSpan
0118    MOV     14  13
0119    TGETS   13  13  10  ; "new"
0120    TDUP    15  42
0121    UGET    16  10      ; Size
0122    TGETS   16  16  40  ; "span"
0123    TGETS   16  16  41  ; "vertical_default"
0124    TSETS   16  15  33  ; "width"
0125    CALL    13   2   3
0126    TSETB   13  12   2
0127    UGET    13  11      ; ButtonTable
0128    MOV     14  13
0129    TGETS   13  13  10  ; "new"
0130    TDUP    15  43
0131    UGET    16   3      ; Screen
0132    MOV     17  16
0133    TGETS   16  16  13  ; "getWidth"
0134    CALL    16   2   2
0135    MULVN   16  16   2  ; 0.9
0136    TSETS   16  15  33  ; "width"
0137    TGETS   16   0  44  ; "buttons"
0138    TSETS   16  15  44  ; "buttons"
0139    TSETS    0  15  45  ; "show_parent"
0140    CALL    13   0   3
0141    TSETM   13   3      ; 3
0142    CALL    10   2   3
0143    TSETB   10   9   1
0144    UGET    10  12      ; Blitbuffer
0145    TGETS   10  10  46  ; "COLOR_WHITE"
0146    TSETS   10   9  48  ; "background"
0147    UGET    10  10      ; Size
0148    TGETS   10  10  49  ; "border"
0149    TGETS   10  10  50  ; "window"
0150    TSETS   10   9  51  ; "bordersize"
0151    UGET    10  10      ; Size
0152    TGETS   10  10  52  ; "radius"
0153    TGETS   10  10  50  ; "window"
0154    TSETS   10   9  52  ; "radius"
0155    UGET    10  10      ; Size
0156    TGETS   10  10  26  ; "padding"
0157    TGETS   10  10  53  ; "button"
0158    TSETS   10   9  26  ; "padding"
0159    CALL     7   0   3
0160    TSETM    7   0      ; 1
0161    CALL     4   0   3
0162    TSETM    4   0      ; 1
0163    CALL     1   2   3
0164    TSETB    1   0   1
0165    RET0     0   1

-- BYTECODE -- buttondialogtitle.lua:91-93
0001    KSTR     0   0      ; "ui"
0002    UGET     1   0      ; self
0003    TGETB    1   1   1
0004    TGETB    1   1   1
0005    TGETS    1   1   1  ; "dimen"
0006    RET      0   3

-- BYTECODE -- buttondialogtitle.lua:90-94
0001    UGET     1   0      ; UIManager
0002    MOV      2   1
0003    TGETS    1   1   0  ; "setDirty"
0004    MOV      3   0
0005    FNEW     4   1      ; buttondialogtitle.lua:91
0006    CALL     1   1   4
0007    UCLO     0 => 0008
0008 => RET0     0   1

-- BYTECODE -- buttondialogtitle.lua:97-99
0001    KSTR     0   0      ; "partial"
0002    UGET     1   0      ; self
0003    TGETB    1   1   1
0004    TGETB    1   1   1
0005    TGETS    1   1   1  ; "dimen"
0006    RET      0   3

-- BYTECODE -- buttondialogtitle.lua:96-100
0001    UGET     1   0      ; UIManager
0002    MOV      2   1
0003    TGETS    1   1   0  ; "setDirty"
0004    KPRI     3   0
0005    FNEW     4   1      ; buttondialogtitle.lua:97
0006    CALL     1   1   4
0007    UCLO     0 => 0008
0008 => RET0     0   1

-- BYTECODE -- buttondialogtitle.lua:102-108
0001    UGET     1   0      ; UIManager
0002    MOV      2   1
0003    TGETS    1   1   0  ; "close"
0004    MOV      3   0
0005    CALL     1   1   3
0006    TGETS    1   0   1  ; "tap_close_callback"
0007    ISF          1
0008    JMP      2 => 0011
0009    TGETS    1   0   1  ; "tap_close_callback"
0010    CALL     1   1   1
0011 => KPRI     1   2
0012    RET1     1   2

-- BYTECODE -- buttondialogtitle.lua:110-113
0001    MOV      2   0
0002    TGETS    1   0   0  ; "onTapClose"
0003    CALL     1   1   2
0004    KPRI     1   2
0005    RET1     1   2

-- BYTECODE -- buttondialogtitle.lua:115-118
0001    UGET     1   0      ; InputContainer
0002    TGETS    1   1   0  ; "paintTo"
0003    MOV      2   0
0004    VARG     3   0   1
0005    CALLM    1   1   1
0006    TGETB    1   0   1
0007    TGETB    1   1   1
0008    TGETS    1   1   1  ; "dimen"
0009    TSETS    1   0   1  ; "dimen"
0010    RET0     0   1

-- BYTECODE -- buttondialogtitle.lua:0-121
0001    GGET     0   0      ; "require"
0002    KSTR     1   1      ; "ffi/blitbuffer"
0003    CALL     0   2   2
0004    GGET     1   0      ; "require"
0005    KSTR     2   2      ; "ui/widget/buttontable"
0006    CALL     1   2   2
0007    GGET     2   0      ; "require"
0008    KSTR     3   3      ; "ui/widget/container/centercontainer"
0009    CALL     2   2   2
0010    GGET     3   0      ; "require"
0011    KSTR     4   4      ; "device"
0012    CALL     3   2   2
0013    GGET     4   0      ; "require"
0014    KSTR     5   5      ; "ui/font"
0015    CALL     4   2   2
0016    GGET     5   0      ; "require"
0017    KSTR     6   6      ; "ui/widget/container/framecontainer"
0018    CALL     5   2   2
0019    GGET     6   0      ; "require"
0020    KSTR     7   7      ; "ui/geometry"
0021    CALL     6   2   2
0022    GGET     7   0      ; "require"
0023    KSTR     8   8      ; "ui/gesturerange"
0024    CALL     7   2   2
0025    GGET     8   0      ; "require"
0026    KSTR     9   9      ; "ui/widget/container/inputcontainer"
0027    CALL     8   2   2
0028    GGET     9   0      ; "require"
0029    KSTR    10  10      ; "ui/widget/container/movablecontainer"
0030    CALL     9   2   2
0031    GGET    10   0      ; "require"
0032    KSTR    11  11      ; "ui/size"
0033    CALL    10   2   2
0034    GGET    11   0      ; "require"
0035    KSTR    12  12      ; "ui/widget/textboxwidget"
0036    CALL    11   2   2
0037    GGET    12   0      ; "require"
0038    KSTR    13  13      ; "ui/widget/verticalgroup"
0039    CALL    12   2   2
0040    GGET    13   0      ; "require"
0041    KSTR    14  14      ; "ui/uimanager"
0042    CALL    13   2   2
0043    GGET    14   0      ; "require"
0044    KSTR    15  15      ; "ui/widget/verticalspan"
0045    CALL    14   2   2
0046    GGET    15   0      ; "require"
0047    KSTR    16  16      ; "gettext"
0048    CALL    15   2   2
0049    TGETS   16   3  17  ; "screen"
0050    MOV     18   8
0051    TGETS   17   8  18  ; "new"
0052    TDUP    19  19
0053    MOV     21   4
0054    TGETS   20   4  20  ; "getFace"
0055    KSTR    22  21      ; "x_smalltfont"
0056    CALL    20   2   3
0057    TSETS   20  19  22  ; "title_face"
0058    TGETS   20  10  23  ; "padding"
0059    TGETS   20  20  24  ; "large"
0060    TSETS   20  19  25  ; "title_padding"
0061    TGETS   20  10  26  ; "margin"
0062    TGETS   20  20  27  ; "title"
0063    TSETS   20  19  28  ; "title_margin"
0064    MOV     21   4
0065    TGETS   20   4  20  ; "getFace"
0066    KSTR    22  29      ; "infofont"
0067    CALL    20   2   3
0068    TSETS   20  19  30  ; "info_face"
0069    TGETS   20  10  23  ; "padding"
0070    TGETS   20  20  31  ; "default"
0071    TSETS   20  19  32  ; "info_padding"
0072    TGETS   20  10  26  ; "margin"
0073    TGETS   20  20  31  ; "default"
0074    TSETS   20  19  33  ; "info_margin"
0075    CALL    17   2   3
0076    FNEW    18  35      ; buttondialogtitle.lua:34
0077    TSETS   18  17  34  ; "init"
0078    FNEW    18  37      ; buttondialogtitle.lua:90
0079    TSETS   18  17  36  ; "onShow"
0080    FNEW    18  39      ; buttondialogtitle.lua:96
0081    TSETS   18  17  38  ; "onCloseWidget"
0082    FNEW    18  41      ; buttondialogtitle.lua:102
0083    TSETS   18  17  40  ; "onTapClose"
0084    FNEW    18  43      ; buttondialogtitle.lua:110
0085    TSETS   18  17  42  ; "onClose"
0086    FNEW    18  45      ; buttondialogtitle.lua:115
0087    TSETS   18  17  44  ; "paintTo"
0088    UCLO     0 => 0089
0089 => RET1    17   2

