
main <./frontend/ui/widget/buttondialogtitle.lua:0,0> (109 instructions, 436 bytes at 0x7fdf664068f0)
0+ params, 23 slots, 0 upvalues, 18 locals, 47 constants, 6 functions
	1	[1]	GETGLOBAL	0 -1	; require
	2	[1]	LOADK    	1 -2	; "ffi/blitbuffer"
	3	[1]	CALL     	0 2 2
	4	[2]	GETGLOBAL	1 -1	; require
	5	[2]	LOADK    	2 -3	; "ui/widget/buttontable"
	6	[2]	CALL     	1 2 2
	7	[3]	GETGLOBAL	2 -1	; require
	8	[3]	LOADK    	3 -4	; "ui/widget/container/centercontainer"
	9	[3]	CALL     	2 2 2
	10	[4]	GETGLOBAL	3 -1	; require
	11	[4]	LOADK    	4 -5	; "device"
	12	[4]	CALL     	3 2 2
	13	[5]	GETGLOBAL	4 -1	; require
	14	[5]	LOADK    	5 -6	; "ui/font"
	15	[5]	CALL     	4 2 2
	16	[6]	GETGLOBAL	5 -1	; require
	17	[6]	LOADK    	6 -7	; "ui/widget/container/framecontainer"
	18	[6]	CALL     	5 2 2
	19	[7]	GETGLOBAL	6 -1	; require
	20	[7]	LOADK    	7 -8	; "ui/geometry"
	21	[7]	CALL     	6 2 2
	22	[8]	GETGLOBAL	7 -1	; require
	23	[8]	LOADK    	8 -9	; "ui/gesturerange"
	24	[8]	CALL     	7 2 2
	25	[9]	GETGLOBAL	8 -1	; require
	26	[9]	LOADK    	9 -10	; "ui/widget/container/inputcontainer"
	27	[9]	CALL     	8 2 2
	28	[10]	GETGLOBAL	9 -1	; require
	29	[10]	LOADK    	10 -11	; "ui/widget/container/movablecontainer"
	30	[10]	CALL     	9 2 2
	31	[11]	GETGLOBAL	10 -1	; require
	32	[11]	LOADK    	11 -12	; "ui/size"
	33	[11]	CALL     	10 2 2
	34	[12]	GETGLOBAL	11 -1	; require
	35	[12]	LOADK    	12 -13	; "ui/widget/textboxwidget"
	36	[12]	CALL     	11 2 2
	37	[13]	GETGLOBAL	12 -1	; require
	38	[13]	LOADK    	13 -14	; "ui/widget/verticalgroup"
	39	[13]	CALL     	12 2 2
	40	[14]	GETGLOBAL	13 -1	; require
	41	[14]	LOADK    	14 -15	; "ui/uimanager"
	42	[14]	CALL     	13 2 2
	43	[15]	GETGLOBAL	14 -1	; require
	44	[15]	LOADK    	15 -16	; "ui/widget/verticalspan"
	45	[15]	CALL     	14 2 2
	46	[16]	GETGLOBAL	15 -1	; require
	47	[16]	LOADK    	16 -17	; "gettext"
	48	[16]	CALL     	15 2 2
	49	[17]	GETTABLE 	16 3 -18	; "screen"
	50	[19]	SELF     	17 8 -19	; "new"
	51	[19]	NEWTABLE 	19 0 12
	52	[20]	SETTABLE 	19 -20 -21	; "title" nil
	53	[21]	SETTABLE 	19 -22 -21	; "title_align" nil
	54	[22]	SELF     	20 4 -24	; "getFace"
	55	[22]	LOADK    	22 -25	; "x_smalltfont"
	56	[22]	CALL     	20 3 2
	57	[22]	SETTABLE 	19 -23 20	; "title_face" -
	58	[23]	GETTABLE 	20 10 -27	; "padding"
	59	[23]	GETTABLE 	20 20 -28	; "large"
	60	[23]	SETTABLE 	19 -26 20	; "title_padding" -
	61	[24]	GETTABLE 	20 10 -30	; "margin"
	62	[24]	GETTABLE 	20 20 -20	; "title"
	63	[24]	SETTABLE 	19 -29 20	; "title_margin" -
	64	[25]	SETTABLE 	19 -31 -32	; "use_info_style" false
	65	[26]	SELF     	20 4 -24	; "getFace"
	66	[26]	LOADK    	22 -34	; "infofont"
	67	[26]	CALL     	20 3 2
	68	[26]	SETTABLE 	19 -33 20	; "info_face" -
	69	[27]	GETTABLE 	20 10 -27	; "padding"
	70	[27]	GETTABLE 	20 20 -36	; "default"
	71	[27]	SETTABLE 	19 -35 20	; "info_padding" -
	72	[28]	GETTABLE 	20 10 -30	; "margin"
	73	[28]	GETTABLE 	20 20 -36	; "default"
	74	[28]	SETTABLE 	19 -37 20	; "info_margin" -
	75	[29]	SETTABLE 	19 -38 -21	; "buttons" nil
	76	[30]	SETTABLE 	19 -39 -21	; "tap_close_callback" nil
	77	[31]	SETTABLE 	19 -40 -41	; "dismissable" true
	78	[19]	CALL     	17 3 2
	79	[88]	CLOSURE  	18 0	; 0x7fdf66407080
	80	[88]	MOVE     	0 3
	81	[88]	MOVE     	0 7
	82	[88]	MOVE     	0 6
	83	[88]	MOVE     	0 16
	84	[88]	MOVE     	0 2
	85	[88]	MOVE     	0 9
	86	[88]	MOVE     	0 5
	87	[88]	MOVE     	0 12
	88	[88]	MOVE     	0 11
	89	[88]	MOVE     	0 14
	90	[88]	MOVE     	0 10
	91	[88]	MOVE     	0 1
	92	[88]	MOVE     	0 0
	93	[34]	SETTABLE 	17 -42 18	; "init" -
	94	[94]	CLOSURE  	18 1	; 0x7fdf66407f10
	95	[94]	MOVE     	0 13
	96	[90]	SETTABLE 	17 -43 18	; "onShow" -
	97	[100]	CLOSURE  	18 2	; 0x7fdf66408440
	98	[100]	MOVE     	0 13
	99	[96]	SETTABLE 	17 -44 18	; "onCloseWidget" -
	100	[108]	CLOSURE  	18 3	; 0x7fdf66408950
	101	[108]	MOVE     	0 13
	102	[102]	SETTABLE 	17 -45 18	; "onTapClose" -
	103	[113]	CLOSURE  	18 4	; 0x7fdf66408ce0
	104	[110]	SETTABLE 	17 -46 18	; "onClose" -
	105	[118]	CLOSURE  	18 5	; 0x7fdf66408d70
	106	[118]	MOVE     	0 8
	107	[115]	SETTABLE 	17 -47 18	; "paintTo" -
	108	[120]	RETURN   	17 2
	109	[120]	RETURN   	0 1

function <./frontend/ui/widget/buttondialogtitle.lua:34,88> (156 instructions, 624 bytes at 0x7fdf66407080)
1 param, 21 slots, 13 upvalues, 1 local, 58 constants, 0 functions
	1	[35]	GETTABLE 	1 0 -1	; "dismissable"
	2	[35]	TEST     	1 0 0
	3	[35]	JMP      	43	; to 47
	4	[36]	GETUPVAL 	1 0	; Device
	5	[36]	SELF     	1 1 -2	; "hasKeys"
	6	[36]	CALL     	1 2 2
	7	[36]	TEST     	1 0 0
	8	[36]	JMP      	9	; to 18
	9	[37]	NEWTABLE 	1 0 1
	10	[38]	NEWTABLE 	2 1 1
	11	[38]	NEWTABLE 	3 1 0
	12	[38]	LOADK    	4 -5	; "Back"
	13	[38]	SETLIST  	3 1 1	; 1
	14	[38]	SETTABLE 	2 -6 -7	; "doc" "close button dialog"
	15	[38]	SETLIST  	2 1 1	; 1
	16	[38]	SETTABLE 	1 -4 2	; "Close" -
	17	[39]	SETTABLE 	0 -3 1	; "key_events" -
	18	[41]	GETUPVAL 	1 0	; Device
	19	[41]	SELF     	1 1 -8	; "isTouchDevice"
	20	[41]	CALL     	1 2 2
	21	[41]	TEST     	1 0 0
	22	[41]	JMP      	24	; to 47
	23	[42]	GETTABLE 	1 0 -9	; "ges_events"
	24	[42]	NEWTABLE 	2 0 0
	25	[43]	GETUPVAL 	3 1	; GestureRange
	26	[43]	SELF     	3 3 -11	; "new"
	27	[43]	NEWTABLE 	5 0 2
	28	[44]	SETTABLE 	5 -12 -13	; "ges" "tap"
	29	[45]	GETUPVAL 	6 2	; Geom
	30	[45]	SELF     	6 6 -11	; "new"
	31	[45]	NEWTABLE 	8 0 4
	32	[46]	SETTABLE 	8 -15 -16	; "x" 0
	33	[47]	SETTABLE 	8 -17 -16	; "y" 0
	34	[48]	GETUPVAL 	9 3	; Screen
	35	[48]	SELF     	9 9 -19	; "getWidth"
	36	[48]	CALL     	9 2 2
	37	[48]	SETTABLE 	8 -18 9	; "w" -
	38	[49]	GETUPVAL 	9 3	; Screen
	39	[49]	SELF     	9 9 -21	; "getHeight"
	40	[49]	CALL     	9 2 2
	41	[49]	SETTABLE 	8 -20 9	; "h" -
	42	[45]	CALL     	6 3 2
	43	[50]	SETTABLE 	5 -14 6	; "range" -
	44	[43]	CALL     	3 3 0
	45	[52]	SETLIST  	2 0 1	; 1
	46	[52]	SETTABLE 	1 -10 2	; "TapClose" -
	47	[55]	GETUPVAL 	1 4	; CenterContainer
	48	[55]	SELF     	1 1 -11	; "new"
	49	[55]	NEWTABLE 	3 0 1
	50	[56]	GETUPVAL 	4 3	; Screen
	51	[56]	SELF     	4 4 -24	; "getSize"
	52	[56]	CALL     	4 2 2
	53	[56]	SETTABLE 	3 -23 4	; "dimen" -
	54	[57]	GETUPVAL 	4 5	; MovableContainer
	55	[57]	SELF     	4 4 -11	; "new"
	56	[57]	NEWTABLE 	6 0 0
	57	[58]	GETUPVAL 	7 6	; FrameContainer
	58	[58]	SELF     	7 7 -11	; "new"
	59	[58]	NEWTABLE 	9 1 5
	60	[59]	GETUPVAL 	10 7	; VerticalGroup
	61	[59]	SELF     	10 10 -11	; "new"
	62	[59]	NEWTABLE 	12 2 1
	63	[60]	SETTABLE 	12 -25 -26	; "align" "center"
	64	[61]	GETUPVAL 	13 6	; FrameContainer
	65	[61]	SELF     	13 13 -11	; "new"
	66	[61]	NEWTABLE 	15 0 3
	67	[62]	GETTABLE 	16 0 -28	; "use_info_style"
	68	[62]	TEST     	16 0 0
	69	[62]	JMP      	3	; to 73
	70	[62]	GETTABLE 	16 0 -29	; "info_padding"
	71	[62]	TEST     	16 0 1
	72	[62]	JMP      	1	; to 74
	73	[62]	GETTABLE 	16 0 -30	; "title_padding"
	74	[62]	SETTABLE 	15 -27 16	; "padding" -
	75	[63]	GETTABLE 	16 0 -28	; "use_info_style"
	76	[63]	TEST     	16 0 0
	77	[63]	JMP      	3	; to 81
	78	[63]	GETTABLE 	16 0 -32	; "info_margin"
	79	[63]	TEST     	16 0 1
	80	[63]	JMP      	1	; to 82
	81	[63]	GETTABLE 	16 0 -33	; "title_margin"
	82	[63]	SETTABLE 	15 -31 16	; "margin" -
	83	[64]	SETTABLE 	15 -34 -16	; "bordersize" 0
	84	[65]	GETUPVAL 	16 8	; TextBoxWidget
	85	[65]	SELF     	16 16 -11	; "new"
	86	[65]	NEWTABLE 	18 0 4
	87	[66]	GETTABLE 	19 0 -36	; "title"
	88	[66]	SETTABLE 	18 -35 19	; "text" -
	89	[67]	GETUPVAL 	19 3	; Screen
	90	[67]	SELF     	19 19 -19	; "getWidth"
	91	[67]	CALL     	19 2 2
	92	[67]	MUL      	19 19 -38	; - 0.8
	93	[67]	SETTABLE 	18 -37 19	; "width" -
	94	[68]	GETTABLE 	19 0 -28	; "use_info_style"
	95	[68]	TEST     	19 0 0
	96	[68]	JMP      	3	; to 100
	97	[68]	GETTABLE 	19 0 -40	; "info_face"
	98	[68]	TEST     	19 0 1
	99	[68]	JMP      	1	; to 101
	100	[68]	GETTABLE 	19 0 -41	; "title_face"
	101	[68]	SETTABLE 	18 -39 19	; "face" -
	102	[69]	GETTABLE 	19 0 -43	; "title_align"
	103	[69]	TEST     	19 0 1
	104	[69]	JMP      	1	; to 106
	105	[69]	LOADK    	19 -44	; "left"
	106	[69]	SETTABLE 	18 -42 19	; "alignment" -
	107	[65]	CALL     	16 3 0
	108	[71]	SETLIST  	15 0 1	; 1
	109	[61]	CALL     	13 3 2
	110	[72]	GETUPVAL 	14 9	; VerticalSpan
	111	[72]	SELF     	14 14 -11	; "new"
	112	[72]	NEWTABLE 	16 0 1
	113	[72]	GETUPVAL 	17 10	; Size
	114	[72]	GETTABLE 	17 17 -45	; "span"
	115	[72]	GETTABLE 	17 17 -46	; "vertical_default"
	116	[72]	SETTABLE 	16 -37 17	; "width" -
	117	[72]	CALL     	14 3 2
	118	[73]	GETUPVAL 	15 11	; ButtonTable
	119	[73]	SELF     	15 15 -11	; "new"
	120	[73]	NEWTABLE 	17 0 4
	121	[74]	GETUPVAL 	18 3	; Screen
	122	[74]	SELF     	18 18 -19	; "getWidth"
	123	[74]	CALL     	18 2 2
	124	[74]	MUL      	18 18 -47	; - 0.9
	125	[74]	SETTABLE 	17 -37 18	; "width" -
	126	[75]	GETTABLE 	18 0 -48	; "buttons"
	127	[75]	SETTABLE 	17 -48 18	; "buttons" -
	128	[76]	SETTABLE 	17 -49 -50	; "zero_sep" true
	129	[77]	SETTABLE 	17 -51 0	; "show_parent" -
	130	[73]	CALL     	15 3 0
	131	[79]	SETLIST  	12 0 1	; 1
	132	[59]	CALL     	10 3 2
	133	[80]	GETUPVAL 	11 12	; Blitbuffer
	134	[80]	GETTABLE 	11 11 -53	; "COLOR_WHITE"
	135	[80]	SETTABLE 	9 -52 11	; "background" -
	136	[81]	GETUPVAL 	11 10	; Size
	137	[81]	GETTABLE 	11 11 -54	; "border"
	138	[81]	GETTABLE 	11 11 -55	; "window"
	139	[81]	SETTABLE 	9 -34 11	; "bordersize" -
	140	[82]	GETUPVAL 	11 10	; Size
	141	[82]	GETTABLE 	11 11 -56	; "radius"
	142	[82]	GETTABLE 	11 11 -55	; "window"
	143	[82]	SETTABLE 	9 -56 11	; "radius" -
	144	[83]	GETUPVAL 	11 10	; Size
	145	[83]	GETTABLE 	11 11 -27	; "padding"
	146	[83]	GETTABLE 	11 11 -57	; "button"
	147	[83]	SETTABLE 	9 -27 11	; "padding" -
	148	[84]	SETTABLE 	9 -58 -16	; "padding_bottom" 0
	149	[85]	SETLIST  	9 1 1	; 1
	150	[58]	CALL     	7 3 0
	151	[86]	SETLIST  	6 0 1	; 1
	152	[57]	CALL     	4 3 0
	153	[87]	SETLIST  	3 0 1	; 1
	154	[55]	CALL     	1 3 2
	155	[87]	SETTABLE 	0 -22 1	; 1 -
	156	[88]	RETURN   	0 1

function <./frontend/ui/widget/buttondialogtitle.lua:90,94> (7 instructions, 28 bytes at 0x7fdf66407f10)
1 param, 5 slots, 1 upvalue, 1 local, 1 constant, 1 function
	1	[91]	GETUPVAL 	1 0	; UIManager
	2	[91]	SELF     	1 1 -1	; "setDirty"
	3	[91]	MOVE     	3 0
	4	[93]	CLOSURE  	4 0	; 0x7fdf66408150
	5	[93]	MOVE     	0 0
	6	[91]	CALL     	1 4 1
	7	[94]	RETURN   	0 1

function <./frontend/ui/widget/buttondialogtitle.lua:91,93> (7 instructions, 28 bytes at 0x7fdf66408150)
0 params, 2 slots, 1 upvalue, 0 locals, 3 constants, 0 functions
	1	[92]	LOADK    	0 -1	; "ui"
	2	[92]	GETUPVAL 	1 0	; self
	3	[92]	GETTABLE 	1 1 -2	; 1
	4	[92]	GETTABLE 	1 1 -2	; 1
	5	[92]	GETTABLE 	1 1 -3	; "dimen"
	6	[92]	RETURN   	0 3
	7	[93]	RETURN   	0 1

function <./frontend/ui/widget/buttondialogtitle.lua:96,100> (7 instructions, 28 bytes at 0x7fdf66408440)
1 param, 5 slots, 1 upvalue, 1 local, 1 constant, 1 function
	1	[97]	GETUPVAL 	1 0	; UIManager
	2	[97]	SELF     	1 1 -1	; "setDirty"
	3	[97]	LOADNIL  	3 3
	4	[99]	CLOSURE  	4 0	; 0x7fdf664088b0
	5	[99]	MOVE     	0 0
	6	[97]	CALL     	1 4 1
	7	[100]	RETURN   	0 1

function <./frontend/ui/widget/buttondialogtitle.lua:97,99> (7 instructions, 28 bytes at 0x7fdf664088b0)
0 params, 2 slots, 1 upvalue, 0 locals, 3 constants, 0 functions
	1	[98]	LOADK    	0 -1	; "partial"
	2	[98]	GETUPVAL 	1 0	; self
	3	[98]	GETTABLE 	1 1 -2	; 1
	4	[98]	GETTABLE 	1 1 -2	; 1
	5	[98]	GETTABLE 	1 1 -3	; "dimen"
	6	[98]	RETURN   	0 3
	7	[99]	RETURN   	0 1

function <./frontend/ui/widget/buttondialogtitle.lua:102,108> (12 instructions, 48 bytes at 0x7fdf66408950)
1 param, 4 slots, 1 upvalue, 1 local, 2 constants, 0 functions
	1	[103]	GETUPVAL 	1 0	; UIManager
	2	[103]	SELF     	1 1 -1	; "close"
	3	[103]	MOVE     	3 0
	4	[103]	CALL     	1 3 1
	5	[104]	GETTABLE 	1 0 -2	; "tap_close_callback"
	6	[104]	TEST     	1 0 0
	7	[104]	JMP      	2	; to 10
	8	[105]	GETTABLE 	1 0 -2	; "tap_close_callback"
	9	[105]	CALL     	1 1 1
	10	[107]	LOADBOOL 	1 1 0
	11	[107]	RETURN   	1 2
	12	[108]	RETURN   	0 1

function <./frontend/ui/widget/buttondialogtitle.lua:110,113> (5 instructions, 20 bytes at 0x7fdf66408ce0)
1 param, 3 slots, 0 upvalues, 1 local, 1 constant, 0 functions
	1	[111]	SELF     	1 0 -1	; "onTapClose"
	2	[111]	CALL     	1 2 1
	3	[112]	LOADBOOL 	1 1 0
	4	[112]	RETURN   	1 2
	5	[113]	RETURN   	0 1

function <./frontend/ui/widget/buttondialogtitle.lua:115,118> (10 instructions, 40 bytes at 0x7fdf66408d70)
1+ param, 5 slots, 1 upvalue, 2 locals, 3 constants, 0 functions
	1	[116]	GETUPVAL 	2 0	; InputContainer
	2	[116]	GETTABLE 	2 2 -1	; "paintTo"
	3	[116]	MOVE     	3 0
	4	[116]	VARARG   	4 0
	5	[116]	CALL     	2 0 1
	6	[117]	GETTABLE 	2 0 -3	; 1
	7	[117]	GETTABLE 	2 2 -3	; 1
	8	[117]	GETTABLE 	2 2 -2	; "dimen"
	9	[117]	SETTABLE 	0 -2 2	; "dimen" -
	10	[118]	RETURN   	0 1
