
main <./frontend/cache.lua:0,0> (75 instructions, 300 bytes at 0x7fc288c068a0)
0+ params, 11 slots, 0 upvalues, 10 locals, 26 constants, 12 functions
	1	[5]	GETGLOBAL	0 -1	; require
	2	[5]	LOADK    	1 -2	; "datastorage"
	3	[5]	CALL     	0 2 2
	4	[6]	GETGLOBAL	1 -1	; require
	5	[6]	LOADK    	2 -3	; "libs/libkoreader-lfs"
	6	[6]	CALL     	1 2 2
	7	[7]	GETGLOBAL	2 -1	; require
	8	[7]	LOADK    	3 -4	; "logger"
	9	[7]	CALL     	2 2 2
	10	[8]	GETGLOBAL	3 -1	; require
	11	[8]	LOADK    	4 -5	; "ffi/MD5"
	12	[8]	CALL     	3 2 2
	13	[10]	GETGLOBAL	4 -1	; require
	14	[10]	LOADK    	5 -6	; "document/canvascontext"
	15	[10]	CALL     	4 2 2
	16	[11]	GETTABLE 	5 4 -7	; "should_restrict_JIT"
	17	[11]	TEST     	5 0 0
	18	[11]	JMP      	7	; to 26
	19	[12]	GETGLOBAL	5 -1	; require
	20	[12]	LOADK    	6 -8	; "jit"
	21	[12]	CALL     	5 2 2
	22	[12]	GETTABLE 	5 5 -9	; "off"
	23	[12]	LOADBOOL 	6 1 0
	24	[12]	LOADBOOL 	7 1 0
	25	[12]	CALL     	5 3 1
	26	[31]	CLOSURE  	5 0	; 0x7fc288c06ba0
	27	[38]	CLOSURE  	6 1	; 0x7fc288c072f0
	28	[38]	MOVE     	0 5
	29	[40]	SELF     	7 0 -10	; "getDataDir"
	30	[40]	CALL     	7 2 2
	31	[40]	LOADK    	8 -11	; "/cache/"
	32	[40]	CONCAT   	7 7 8
	33	[54]	CLOSURE  	8 2	; 0x7fc288c06c50
	34	[54]	MOVE     	0 1
	35	[54]	MOVE     	0 7
	36	[56]	NEWTABLE 	9 0 5
	37	[58]	MOVE     	10 6
	38	[58]	CALL     	10 1 2
	39	[58]	SETTABLE 	9 -12 10	; "max_memsize" -
	40	[60]	SETTABLE 	9 -13 -14	; "current_memsize" 0
	41	[62]	NEWTABLE 	10 0 0
	42	[62]	SETTABLE 	9 -15 10	; "cache" -
	43	[64]	NEWTABLE 	10 0 0
	44	[64]	SETTABLE 	9 -16 10	; "cache_order" -
	45	[66]	MOVE     	10 8
	46	[66]	CALL     	10 1 2
	47	[66]	SETTABLE 	9 -17 10	; "cached" -
	48	[74]	CLOSURE  	10 3	; 0x7fc288c07010
	49	[69]	SETTABLE 	9 -18 10	; "new" -
	50	[83]	CLOSURE  	10 4	; 0x7fc288c07110
	51	[77]	SETTABLE 	9 -19 10	; "_unref" -
	52	[91]	CLOSURE  	10 5	; 0x7fc288c08610
	53	[86]	SETTABLE 	9 -20 10	; "_free" -
	54	[97]	CLOSURE  	10 6	; 0x7fc288c08d70
	55	[94]	SETTABLE 	9 -21 10	; "drop" -
	56	[117]	CLOSURE  	10 7	; 0x7fc288c08df0
	57	[117]	MOVE     	0 2
	58	[99]	SETTABLE 	9 -22 10	; "insert" -
	59	[144]	CLOSURE  	10 8	; 0x7fc288c09120
	60	[144]	MOVE     	0 3
	61	[144]	MOVE     	0 2
	62	[123]	SETTABLE 	9 -23 10	; "check" -
	63	[151]	CLOSURE  	10 9	; 0x7fc288c09a80
	64	[146]	SETTABLE 	9 -24 10	; "willAccept" -
	65	[188]	CLOSURE  	10 10	; 0x7fc288c09ba0
	66	[188]	MOVE     	0 1
	67	[188]	MOVE     	0 7
	68	[188]	MOVE     	0 3
	69	[188]	MOVE     	0 2
	70	[188]	MOVE     	0 8
	71	[153]	SETTABLE 	9 -25 10	; "serialize" -
	72	[198]	CLOSURE  	10 11	; 0x7fc288c0a0d0
	73	[191]	SETTABLE 	9 -26 10	; "clear" -
	74	[200]	RETURN   	9 2
	75	[200]	RETURN   	0 1

function <./frontend/cache.lua:15,31> (57 instructions, 228 bytes at 0x7fc288c06ba0)
0 params, 14 slots, 0 upvalues, 10 locals, 14 constants, 0 functions
	1	[16]	GETGLOBAL	0 -1	; io
	2	[16]	GETTABLE 	0 0 -2	; "open"
	3	[16]	LOADK    	1 -3	; "/proc/meminfo"
	4	[16]	LOADK    	2 -4	; "r"
	5	[16]	CALL     	0 3 2
	6	[17]	LOADK    	1 -5	; 0
	7	[18]	TEST     	0 0 0
	8	[18]	JMP      	47	; to 56
	9	[19]	SELF     	2 0 -6	; "lines"
	10	[19]	CALL     	2 2 4
	11	[19]	JMP      	40	; to 52
	12	[20]	LOADNIL  	6 9
	13	[21]	SELF     	10 5 -7	; "gsub"
	14	[21]	LOADK    	12 -8	; "^MemFree:%s-(%d+) kB"
	15	[21]	LOADK    	13 -9	; "%1"
	16	[21]	CALL     	10 4 3
	17	[21]	MOVE     	9 11
	18	[21]	MOVE     	6 10
	19	[22]	EQ       	1 9 -5	; - 0
	20	[22]	JMP      	5	; to 26
	21	[22]	GETGLOBAL	10 -10	; tonumber
	22	[22]	MOVE     	11 6
	23	[22]	CALL     	10 2 2
	24	[22]	MUL      	10 10 -11	; - 1024
	25	[22]	ADD      	1 1 10
	26	[23]	SELF     	10 5 -7	; "gsub"
	27	[23]	LOADK    	12 -12	; "^Buffers:%s-(%d+) kB"
	28	[23]	LOADK    	13 -9	; "%1"
	29	[23]	CALL     	10 4 3
	30	[23]	MOVE     	9 11
	31	[23]	MOVE     	7 10
	32	[24]	EQ       	1 9 -5	; - 0
	33	[24]	JMP      	5	; to 39
	34	[24]	GETGLOBAL	10 -10	; tonumber
	35	[24]	MOVE     	11 7
	36	[24]	CALL     	10 2 2
	37	[24]	MUL      	10 10 -11	; - 1024
	38	[24]	ADD      	1 1 10
	39	[25]	SELF     	10 5 -7	; "gsub"
	40	[25]	LOADK    	12 -13	; "^Cached:%s-(%d+) kB"
	41	[25]	LOADK    	13 -9	; "%1"
	42	[25]	CALL     	10 4 3
	43	[25]	MOVE     	9 11
	44	[25]	MOVE     	8 10
	45	[26]	EQ       	1 9 -5	; - 0
	46	[26]	JMP      	5	; to 52
	47	[26]	GETGLOBAL	10 -10	; tonumber
	48	[26]	MOVE     	11 8
	49	[26]	CALL     	10 2 2
	50	[26]	MUL      	10 10 -11	; - 1024
	51	[26]	ADD      	1 1 10
	52	[19]	TFORLOOP 	2 1
	53	[26]	JMP      	-42	; to 12
	54	[28]	SELF     	2 0 -14	; "close"
	55	[28]	CALL     	2 2 1
	56	[30]	RETURN   	1 2
	57	[31]	RETURN   	0 1

function <./frontend/cache.lua:33,38> (20 instructions, 80 bytes at 0x7fc288c072f0)
0 params, 8 slots, 1 upvalue, 3 locals, 7 constants, 0 functions
	1	[34]	GETGLOBAL	0 -1	; DGLOBAL_CACHE_SIZE_MINIMUM
	2	[35]	GETGLOBAL	1 -2	; DGLOBAL_CACHE_SIZE_MAXIMUM
	3	[36]	GETUPVAL 	2 0	; calcFreeMem
	4	[36]	CALL     	2 1 2
	5	[36]	GETGLOBAL	3 -3	; DGLOBAL_CACHE_FREE_PROPORTION
	6	[36]	TEST     	3 0 1
	7	[36]	JMP      	1	; to 9
	8	[36]	LOADK    	3 -4	; 0
	9	[36]	MUL      	2 2 3
	10	[37]	GETGLOBAL	3 -5	; math
	11	[37]	GETTABLE 	3 3 -6	; "min"
	12	[37]	MOVE     	4 1
	13	[37]	GETGLOBAL	5 -5	; math
	14	[37]	GETTABLE 	5 5 -7	; "max"
	15	[37]	MOVE     	6 0
	16	[37]	MOVE     	7 2
	17	[37]	CALL     	5 3 0
	18	[37]	TAILCALL 	3 0 0
	19	[37]	RETURN   	3 0
	20	[38]	RETURN   	0 1

function <./frontend/cache.lua:45,54> (21 instructions, 84 bytes at 0x7fc288c06c50)
0 params, 9 slots, 2 upvalues, 6 locals, 4 constants, 0 functions
	1	[46]	NEWTABLE 	0 0 0
	2	[47]	GETUPVAL 	1 0	; lfs
	3	[47]	GETTABLE 	1 1 -1	; "dir"
	4	[47]	GETUPVAL 	2 1	; cache_path
	5	[47]	CALL     	1 2 4
	6	[47]	JMP      	11	; to 18
	7	[48]	GETUPVAL 	5 1	; cache_path
	8	[48]	MOVE     	6 4
	9	[48]	CONCAT   	5 5 6
	10	[49]	GETUPVAL 	6 0	; lfs
	11	[49]	GETTABLE 	6 6 -2	; "attributes"
	12	[49]	MOVE     	7 5
	13	[49]	LOADK    	8 -3	; "mode"
	14	[49]	CALL     	6 3 2
	15	[49]	EQ       	0 6 -4	; - "file"
	16	[49]	JMP      	1	; to 18
	17	[50]	SETTABLE 	0 4 5
	18	[47]	TFORLOOP 	1 1
	19	[51]	JMP      	-13	; to 7
	20	[53]	RETURN   	0 2
	21	[54]	RETURN   	0 1

function <./frontend/cache.lua:69,74> (11 instructions, 44 bytes at 0x7fc288c07010)
2 params, 5 slots, 0 upvalues, 2 locals, 2 constants, 0 functions
	1	[70]	TEST     	1 0 1
	2	[70]	JMP      	2	; to 5
	3	[70]	NEWTABLE 	2 0 0
	4	[70]	MOVE     	1 2
	5	[71]	GETGLOBAL	2 -1	; setmetatable
	6	[71]	MOVE     	3 1
	7	[71]	MOVE     	4 0
	8	[71]	CALL     	2 3 1
	9	[72]	SETTABLE 	0 -2 0	; "__index" -
	10	[73]	RETURN   	1 2
	11	[74]	RETURN   	0 1

function <./frontend/cache.lua:77,83> (16 instructions, 64 bytes at 0x7fc288c07110)
2 params, 9 slots, 0 upvalues, 6 locals, 5 constants, 0 functions
	1	[78]	GETTABLE 	2 0 -1	; "cache_order"
	2	[78]	LEN      	2 2
	3	[78]	LOADK    	3 -2	; 1
	4	[78]	LOADK    	4 -3	; -1
	5	[78]	FORPREP  	2 9	; to 15
	6	[79]	GETTABLE 	6 0 -1	; "cache_order"
	7	[79]	GETTABLE 	6 6 5
	8	[79]	EQ       	0 6 1
	9	[79]	JMP      	5	; to 15
	10	[80]	GETGLOBAL	6 -4	; table
	11	[80]	GETTABLE 	6 6 -5	; "remove"
	12	[80]	GETTABLE 	7 0 -1	; "cache_order"
	13	[80]	MOVE     	8 5
	14	[80]	CALL     	6 3 1
	15	[78]	FORLOOP  	2 -10	; to 6
	16	[83]	RETURN   	0 1

function <./frontend/cache.lua:86,91> (18 instructions, 72 bytes at 0x7fc288c08610)
2 params, 4 slots, 0 upvalues, 2 locals, 5 constants, 0 functions
	1	[87]	GETTABLE 	2 0 -1	; "cache"
	2	[87]	GETTABLE 	2 2 1
	3	[87]	TEST     	2 0 1
	4	[87]	JMP      	1	; to 6
	5	[87]	RETURN   	0 1
	6	[88]	GETTABLE 	2 0 -2	; "current_memsize"
	7	[88]	GETTABLE 	3 0 -1	; "cache"
	8	[88]	GETTABLE 	3 3 1
	9	[88]	GETTABLE 	3 3 -3	; "size"
	10	[88]	SUB      	2 2 3
	11	[88]	SETTABLE 	0 -2 2	; "current_memsize" -
	12	[89]	GETTABLE 	2 0 -1	; "cache"
	13	[89]	GETTABLE 	2 2 1
	14	[89]	SELF     	2 2 -4	; "onFree"
	15	[89]	CALL     	2 2 1
	16	[90]	GETTABLE 	2 0 -1	; "cache"
	17	[90]	SETTABLE 	2 1 -5	; - nil
	18	[91]	RETURN   	0 1

function <./frontend/cache.lua:94,97> (7 instructions, 28 bytes at 0x7fc288c08d70)
2 params, 5 slots, 0 upvalues, 2 locals, 2 constants, 0 functions
	1	[95]	SELF     	2 0 -1	; "_unref"
	2	[95]	MOVE     	4 1
	3	[95]	CALL     	2 3 1
	4	[96]	SELF     	2 0 -2	; "_free"
	5	[96]	MOVE     	4 1
	6	[96]	CALL     	2 3 1
	7	[97]	RETURN   	0 1

function <./frontend/cache.lua:99,117> (40 instructions, 160 bytes at 0x7fc288c08df0)
3 params, 7 slots, 1 upvalue, 4 locals, 13 constants, 0 functions
	1	[101]	SELF     	3 0 -1	; "drop"
	2	[101]	MOVE     	5 1
	3	[101]	CALL     	3 3 1
	4	[103]	GETTABLE 	3 2 -2	; "size"
	5	[103]	GETTABLE 	4 0 -3	; "max_memsize"
	6	[103]	LT       	0 4 3
	7	[103]	JMP      	6	; to 14
	8	[104]	GETUPVAL 	3 0	; logger
	9	[104]	GETTABLE 	3 3 -4	; "warn"
	10	[104]	LOADK    	4 -5	; "too much memory claimed for"
	11	[104]	MOVE     	5 1
	12	[104]	CALL     	3 3 1
	13	[105]	RETURN   	0 1
	14	[109]	GETTABLE 	3 0 -6	; "current_memsize"
	15	[109]	GETTABLE 	4 2 -2	; "size"
	16	[109]	ADD      	3 3 4
	17	[109]	GETTABLE 	4 0 -3	; "max_memsize"
	18	[109]	LT       	0 4 3
	19	[109]	JMP      	8	; to 28
	20	[110]	GETGLOBAL	3 -7	; table
	21	[110]	GETTABLE 	3 3 -8	; "remove"
	22	[110]	GETTABLE 	4 0 -9	; "cache_order"
	23	[110]	CALL     	3 2 2
	24	[111]	SELF     	4 0 -10	; "_free"
	25	[111]	MOVE     	6 3
	26	[111]	CALL     	4 3 1
	27	[111]	JMP      	-14	; to 14
	28	[114]	GETGLOBAL	3 -7	; table
	29	[114]	GETTABLE 	3 3 -11	; "insert"
	30	[114]	GETTABLE 	4 0 -9	; "cache_order"
	31	[114]	LOADK    	5 -12	; 1
	32	[114]	MOVE     	6 1
	33	[114]	CALL     	3 4 1
	34	[115]	GETTABLE 	3 0 -13	; "cache"
	35	[115]	SETTABLE 	3 1 2
	36	[116]	GETTABLE 	3 0 -6	; "current_memsize"
	37	[116]	GETTABLE 	4 2 -2	; "size"
	38	[116]	ADD      	3 3 4
	39	[116]	SETTABLE 	0 -6 3	; "current_memsize" -
	40	[117]	RETURN   	0 1

function <./frontend/cache.lua:123,144> (53 instructions, 212 bytes at 0x7fc288c09120)
3 params, 11 slots, 2 upvalues, 7 locals, 13 constants, 0 functions
	1	[124]	GETTABLE 	3 0 -1	; "cache"
	2	[124]	GETTABLE 	3 3 1
	3	[124]	TEST     	3 0 0
	4	[124]	JMP      	17	; to 22
	5	[125]	GETTABLE 	3 0 -2	; "cache_order"
	6	[125]	GETTABLE 	3 3 -3	; 1
	7	[125]	EQ       	1 3 1
	8	[125]	JMP      	9	; to 18
	9	[127]	SELF     	3 0 -4	; "_unref"
	10	[127]	MOVE     	5 1
	11	[127]	CALL     	3 3 1
	12	[128]	GETGLOBAL	3 -5	; table
	13	[128]	GETTABLE 	3 3 -6	; "insert"
	14	[128]	GETTABLE 	4 0 -2	; "cache_order"
	15	[128]	LOADK    	5 -3	; 1
	16	[128]	MOVE     	6 1
	17	[128]	CALL     	3 4 1
	18	[130]	GETTABLE 	3 0 -1	; "cache"
	19	[130]	GETTABLE 	3 3 1
	20	[130]	RETURN   	3 2
	21	[130]	JMP      	31	; to 53
	22	[131]	TEST     	2 0 0
	23	[131]	JMP      	29	; to 53
	24	[132]	GETTABLE 	3 0 -7	; "cached"
	25	[132]	GETUPVAL 	4 0	; md5
	26	[132]	GETTABLE 	4 4 -8	; "sum"
	27	[132]	MOVE     	5 1
	28	[132]	CALL     	4 2 2
	29	[132]	GETTABLE 	3 3 4
	30	[133]	TEST     	3 0 0
	31	[133]	JMP      	21	; to 53
	32	[134]	SELF     	4 2 -9	; "new"
	33	[134]	NEWTABLE 	6 0 0
	34	[134]	CALL     	4 3 2
	35	[135]	GETGLOBAL	5 -10	; pcall
	36	[135]	GETTABLE 	6 4 -11	; "load"
	37	[135]	MOVE     	7 4
	38	[135]	MOVE     	8 3
	39	[135]	CALL     	5 4 3
	40	[136]	TEST     	5 0 0
	41	[136]	JMP      	6	; to 48
	42	[137]	SELF     	7 0 -6	; "insert"
	43	[137]	MOVE     	9 1
	44	[137]	MOVE     	10 4
	45	[137]	CALL     	7 4 1
	46	[138]	RETURN   	4 2
	47	[138]	JMP      	5	; to 53
	48	[140]	GETUPVAL 	7 1	; logger
	49	[140]	GETTABLE 	7 7 -12	; "warn"
	50	[140]	LOADK    	8 -13	; "discard cache"
	51	[140]	MOVE     	9 6
	52	[140]	CALL     	7 3 1
	53	[144]	RETURN   	0 1

function <./frontend/cache.lua:146,151> (8 instructions, 32 bytes at 0x7fc288c09a80)
2 params, 4 slots, 0 upvalues, 2 locals, 3 constants, 0 functions
	1	[148]	MUL      	2 1 -1	; - 4
	2	[148]	GETTABLE 	3 0 -2	; "max_memsize"
	3	[148]	MUL      	3 3 -3	; - 3
	4	[148]	LT       	0 2 3
	5	[148]	JMP      	2	; to 8
	6	[149]	LOADBOOL 	2 1 0
	7	[149]	RETURN   	2 2
	8	[151]	RETURN   	0 1

function <./frontend/cache.lua:153,188> (100 instructions, 400 bytes at 0x7fc288c09ba0)
1 param, 15 slots, 5 upvalues, 18 locals, 22 constants, 1 function
	1	[155]	LOADK    	1 -1	; 0
	2	[156]	NEWTABLE 	2 0 0
	3	[157]	GETGLOBAL	3 -2	; pairs
	4	[157]	GETTABLE 	4 0 -3	; "cached"
	5	[157]	CALL     	3 2 4
	6	[157]	JMP      	21	; to 28
	7	[158]	GETGLOBAL	8 -4	; table
	8	[158]	GETTABLE 	8 8 -5	; "insert"
	9	[158]	MOVE     	9 2
	10	[158]	NEWTABLE 	10 0 2
	11	[158]	SETTABLE 	10 -6 7	; "file" -
	12	[158]	GETUPVAL 	11 0	; lfs
	13	[158]	GETTABLE 	11 11 -8	; "attributes"
	14	[158]	MOVE     	12 7
	15	[158]	LOADK    	13 -9	; "access"
	16	[158]	CALL     	11 3 2
	17	[158]	SETTABLE 	10 -7 11	; "time" -
	18	[158]	CALL     	8 3 1
	19	[159]	GETUPVAL 	8 0	; lfs
	20	[159]	GETTABLE 	8 8 -8	; "attributes"
	21	[159]	MOVE     	9 7
	22	[159]	LOADK    	10 -10	; "size"
	23	[159]	CALL     	8 3 2
	24	[159]	TEST     	8 0 1
	25	[159]	JMP      	1	; to 27
	26	[159]	LOADK    	8 -1	; 0
	27	[159]	ADD      	1 1 8
	28	[157]	TFORLOOP 	3 2
	29	[159]	JMP      	-23	; to 7
	30	[161]	GETGLOBAL	3 -4	; table
	31	[161]	GETTABLE 	3 3 -11	; "sort"
	32	[161]	MOVE     	4 2
	33	[161]	CLOSURE  	5 0	; 0x7fc288c0a330
	34	[161]	CALL     	3 3 1
	35	[163]	LOADK    	3 -1	; 0
	36	[164]	GETGLOBAL	4 -12	; ipairs
	37	[164]	GETTABLE 	5 0 -13	; "cache_order"
	38	[164]	CALL     	4 2 4
	39	[164]	JMP      	35	; to 75
	40	[165]	GETTABLE 	9 0 -14	; "cache"
	41	[165]	GETTABLE 	9 9 8
	42	[168]	GETTABLE 	10 9 -15	; "persistent"
	43	[168]	TEST     	10 0 0
	44	[168]	JMP      	30	; to 75
	45	[168]	GETTABLE 	10 9 -16	; "dump"
	46	[168]	TEST     	10 0 0
	47	[168]	JMP      	27	; to 75
	48	[169]	GETUPVAL 	10 1	; cache_path
	49	[169]	GETUPVAL 	11 2	; md5
	50	[169]	GETTABLE 	11 11 -17	; "sum"
	51	[169]	MOVE     	12 8
	52	[169]	CALL     	11 2 2
	53	[169]	CONCAT   	10 10 11
	54	[170]	GETUPVAL 	11 0	; lfs
	55	[170]	GETTABLE 	11 11 -8	; "attributes"
	56	[170]	MOVE     	12 10
	57	[170]	CALL     	11 2 2
	58	[172]	TEST     	11 0 0
	59	[172]	JMP      	1	; to 61
	60	[172]	JMP      	16	; to 77
	61	[174]	GETUPVAL 	12 3	; logger
	62	[174]	GETTABLE 	12 12 -18	; "dbg"
	63	[174]	LOADK    	13 -19	; "dump cache item"
	64	[174]	MOVE     	14 8
	65	[174]	CALL     	12 3 1
	66	[175]	SELF     	12 9 -16	; "dump"
	67	[175]	MOVE     	14 10
	68	[175]	CALL     	12 3 2
	69	[175]	TESTSET  	3 12 1
	70	[175]	JMP      	1	; to 72
	71	[175]	LOADK    	3 -1	; 0
	72	[176]	LT       	0 -1 3	; 0 -
	73	[176]	JMP      	1	; to 75
	74	[176]	JMP      	2	; to 77
	75	[164]	TFORLOOP 	4 2
	76	[177]	JMP      	-37	; to 40
	77	[180]	ADD      	4 1 3
	78	[180]	GETTABLE 	5 0 -20	; "max_memsize"
	79	[180]	SUB      	4 4 5
	80	[180]	LT       	0 -1 4	; 0 -
	81	[180]	JMP      	15	; to 97
	82	[182]	GETGLOBAL	4 -4	; table
	83	[182]	GETTABLE 	4 4 -21	; "remove"
	84	[182]	MOVE     	5 2
	85	[182]	CALL     	4 2 2
	86	[183]	GETUPVAL 	5 0	; lfs
	87	[183]	GETTABLE 	5 5 -8	; "attributes"
	88	[183]	GETTABLE 	6 4 -6	; "file"
	89	[183]	LOADK    	7 -10	; "size"
	90	[183]	CALL     	5 3 2
	91	[183]	SUB      	1 1 5
	92	[184]	GETGLOBAL	5 -22	; os
	93	[184]	GETTABLE 	5 5 -21	; "remove"
	94	[184]	GETTABLE 	6 4 -6	; "file"
	95	[184]	CALL     	5 2 1
	96	[184]	JMP      	-20	; to 77
	97	[187]	GETUPVAL 	4 4	; getDiskCache
	98	[187]	CALL     	4 1 2
	99	[187]	SETTABLE 	0 -3 4	; "cached" -
	100	[188]	RETURN   	0 1

function <./frontend/cache.lua:161,161> (8 instructions, 32 bytes at 0x7fc288c0a330)
2 params, 4 slots, 0 upvalues, 2 locals, 1 constant, 0 functions
	1	[161]	GETTABLE 	2 0 -1	; "time"
	2	[161]	GETTABLE 	3 1 -1	; "time"
	3	[161]	LT       	1 3 2
	4	[161]	JMP      	1	; to 6
	5	[161]	LOADBOOL 	2 0 1
	6	[161]	LOADBOOL 	2 1 0
	7	[161]	RETURN   	2 2
	8	[161]	RETURN   	0 1

function <./frontend/cache.lua:191,198> (16 instructions, 64 bytes at 0x7fc288c0a0d0)
1 param, 8 slots, 0 upvalues, 6 locals, 6 constants, 0 functions
	1	[192]	GETGLOBAL	1 -1	; pairs
	2	[192]	GETTABLE 	2 0 -2	; "cache"
	3	[192]	CALL     	1 2 4
	4	[192]	JMP      	4	; to 9
	5	[193]	GETTABLE 	6 0 -2	; "cache"
	6	[193]	GETTABLE 	6 6 4
	7	[193]	SELF     	6 6 -3	; "onFree"
	8	[193]	CALL     	6 2 1
	9	[192]	TFORLOOP 	1 2
	10	[193]	JMP      	-6	; to 5
	11	[195]	NEWTABLE 	1 0 0
	12	[195]	SETTABLE 	0 -2 1	; "cache" -
	13	[196]	NEWTABLE 	1 0 0
	14	[196]	SETTABLE 	0 -4 1	; "cache_order" -
	15	[197]	SETTABLE 	0 -5 -6	; "current_memsize" 0
	16	[198]	RETURN   	0 1
