
main <./frontend/cacheitem.lua:0,0> (8 instructions, 32 bytes at 0x7fd568c068c0)
0+ params, 2 slots, 0 upvalues, 1 local, 4 constants, 2 functions
	1	[5]	NEWTABLE 	0 0 1
	2	[6]	SETTABLE 	0 -1 -2	; "size" 64
	3	[14]	CLOSURE  	1 0	; 0x7fd568c06cd0
	4	[9]	SETTABLE 	0 -3 1	; "new" -
	5	[17]	CLOSURE  	1 1	; 0x7fd568c06e00
	6	[16]	SETTABLE 	0 -4 1	; "onFree" -
	7	[19]	RETURN   	0 2
	8	[19]	RETURN   	0 1

function <./frontend/cacheitem.lua:9,14> (11 instructions, 44 bytes at 0x7fd568c06cd0)
2 params, 5 slots, 0 upvalues, 2 locals, 2 constants, 0 functions
	1	[10]	TEST     	1 0 1
	2	[10]	JMP      	2	; to 5
	3	[10]	NEWTABLE 	2 0 0
	4	[10]	MOVE     	1 2
	5	[11]	GETGLOBAL	2 -1	; setmetatable
	6	[11]	MOVE     	3 1
	7	[11]	MOVE     	4 0
	8	[11]	CALL     	2 3 1
	9	[12]	SETTABLE 	0 -2 0	; "__index" -
	10	[13]	RETURN   	1 2
	11	[14]	RETURN   	0 1

function <./frontend/cacheitem.lua:16,17> (1 instruction, 4 bytes at 0x7fd568c06e00)
1 param, 2 slots, 0 upvalues, 1 local, 0 constants, 0 functions
	1	[17]	RETURN   	0 1
