-- BYTECODE -- cacheitem.lua:9-14
0001    IST          1
0002    JMP      2 => 0004
0003    TNEW     1   0
0004 => GGET     2   0      ; "setmetatable"
0005    MOV      3   1
0006    MOV      4   0
0007    CALL     2   1   3
0008    TSETS    0   0   1  ; "__index"
0009    RET1     1   2

-- BYTECODE -- cacheitem.lua:16-17
0001    RET0     0   1

-- BYTECODE -- cacheitem.lua:0-20
0001    TDUP     0   0
0002    FNEW     1   2      ; cacheitem.lua:9
0003    TSETS    1   0   1  ; "new"
0004    FNEW     1   4      ; cacheitem.lua:16
0005    TSETS    1   0   3  ; "onFree"
0006    UCLO     0 => 0007
0007 => RET1     0   2

