-- BYTECODE -- cache_spec.lua:5-12
0001    GGET     0   0      ; "require"
0002    KSTR     1   1      ; "commonrequire"
0003    CALL     0   1   2
0004    GGET     0   0      ; "require"
0005    KSTR     1   2      ; "document/documentregistry"
0006    CALL     0   2   2
0007    USETV    0   0      ; DocumentRegistry
0008    GGET     0   0      ; "require"
0009    KSTR     1   3      ; "cache"
0010    CALL     0   2   2
0011    USETV    1   0      ; Cache
0012    KSTR     0   4      ; "spec/front/unit/data/sample.pdf"
0013    UGET     1   0      ; DocumentRegistry
0014    MOV      2   1
0015    TGETS    1   1   5  ; "openDocument"
0016    MOV      3   0
0017    CALL     1   2   3
0018    USETV    2   1      ; doc
0019    RET0     0   1

-- BYTECODE -- cache_spec.lua:14-16
0001    UGET     0   0      ; Cache
0002    MOV      1   0
0003    TGETS    0   0   0  ; "clear"
0004    CALL     0   1   2
0005    RET0     0   1

-- BYTECODE -- cache_spec.lua:18-24
0001    KSHORT   0   1
0002    GGET     1   0      ; "math"
0003    TGETS    1   1   1  ; "min"
0004    UGET     2   0      ; max_page
0005    UGET     3   1      ; doc
0006    TGETS    3   3   2  ; "info"
0007    TGETS    3   3   3  ; "number_of_pages"
0008    CALL     1   2   3
0009    KSHORT   2   1
0010    FORI     0 => 0026
0011 => UGET     4   1      ; doc
0012    MOV      5   4
0013    TGETS    4   4   4  ; "renderPage"
0014    MOV      6   3
0015    KPRI     7   0
0016    KSHORT   8   1
0017    KSHORT   9   0
0018    KSHORT  10   1
0019    KSHORT  11   0
0020    CALL     4   1   8
0021    UGET     4   2      ; Cache
0022    MOV      5   4
0023    TGETS    4   4   5  ; "serialize"
0024    CALL     4   1   2
0025    FORL     0 => 0011
0026 => UGET     0   2      ; Cache
0027    MOV      1   0
0028    TGETS    0   0   6  ; "clear"
0029    CALL     0   1   2
0030    RET0     0   1

-- BYTECODE -- cache_spec.lua:26-31
0001    KSHORT   0   1
0002    GGET     1   0      ; "math"
0003    TGETS    1   1   1  ; "min"
0004    UGET     2   0      ; max_page
0005    UGET     3   1      ; doc
0006    TGETS    3   3   2  ; "info"
0007    TGETS    3   3   3  ; "number_of_pages"
0008    CALL     1   2   3
0009    KSHORT   2   1
0010    FORI     0 => 0021
0011 => UGET     4   1      ; doc
0012    MOV      5   4
0013    TGETS    4   4   4  ; "hintPage"
0014    MOV      6   3
0015    KSHORT   7   1
0016    KSHORT   8   0
0017    KSHORT   9   1
0018    KSHORT  10   0
0019    CALL     4   1   7
0020    FORL     0 => 0011
0021 => UGET     0   2      ; Cache
0022    MOV      1   0
0023    TGETS    0   0   5  ; "clear"
0024    CALL     0   1   2
0025    RET0     0   1

-- BYTECODE -- cache_spec.lua:33-42
0001    UGET     0   0      ; doc
0002    TGETS    0   0   0  ; "configurable"
0003    KSHORT   1   1
0004    TSETS    1   0   1  ; "text_wrap"
0005    KSHORT   0   1
0006    GGET     1   2      ; "math"
0007    TGETS    1   1   3  ; "min"
0008    UGET     2   1      ; max_page
0009    UGET     3   0      ; doc
0010    TGETS    3   3   4  ; "info"
0011    TGETS    3   3   5  ; "number_of_pages"
0012    CALL     1   2   3
0013    KSHORT   2   1
0014    FORI     0 => 0035
0015 => UGET     4   0      ; doc
0016    MOV      5   4
0017    TGETS    4   4   6  ; "renderPage"
0018    MOV      6   3
0019    KPRI     7   0
0020    KSHORT   8   1
0021    KSHORT   9   0
0022    KSHORT  10   1
0023    KSHORT  11   0
0024    CALL     4   1   8
0025    UGET     4   0      ; doc
0026    MOV      5   4
0027    TGETS    4   4   7  ; "getPageDimensions"
0028    MOV      6   3
0029    CALL     4   1   3
0030    UGET     4   2      ; Cache
0031    MOV      5   4
0032    TGETS    4   4   8  ; "serialize"
0033    CALL     4   1   2
0034    FORL     0 => 0015
0035 => UGET     0   2      ; Cache
0036    MOV      1   0
0037    TGETS    0   0   9  ; "clear"
0038    CALL     0   1   2
0039    UGET     0   0      ; doc
0040    TGETS    0   0   0  ; "configurable"
0041    KSHORT   1   0
0042    TSETS    1   0   1  ; "text_wrap"
0043    RET0     0   1

-- BYTECODE -- cache_spec.lua:44-49
0001    KSHORT   0   1
0002    GGET     1   0      ; "math"
0003    TGETS    1   1   1  ; "min"
0004    UGET     2   0      ; max_page
0005    UGET     3   1      ; doc
0006    TGETS    3   3   2  ; "info"
0007    TGETS    3   3   3  ; "number_of_pages"
0008    CALL     1   2   3
0009    KSHORT   2   1
0010    FORI     0 => 0022
0011 => UGET     4   1      ; doc
0012    MOV      5   4
0013    TGETS    4   4   4  ; "renderPage"
0014    MOV      6   3
0015    KPRI     7   0
0016    KSHORT   8   1
0017    KSHORT   9   0
0018    KSHORT  10   1
0019    KSHORT  11   0
0020    CALL     4   1   8
0021    FORL     0 => 0011
0022 => UGET     0   2      ; Cache
0023    MOV      1   0
0024    TGETS    0   0   5  ; "clear"
0025    CALL     0   1   2
0026    RET0     0   1

-- BYTECODE -- cache_spec.lua:1-50
0001    KNIL     0   2
0002    KSHORT   3   1
0003    GGET     4   0      ; "setup"
0004    FNEW     5   1      ; cache_spec.lua:5
0005    CALL     4   1   2
0006    GGET     4   2      ; "it"
0007    KSTR     5   3      ; "should clear cache"
0008    FNEW     6   4      ; cache_spec.lua:14
0009    CALL     4   1   3
0010    GGET     4   2      ; "it"
0011    KSTR     5   5      ; "should serialize blitbuffer"
0012    FNEW     6   6      ; cache_spec.lua:18
0013    CALL     4   1   3
0014    GGET     4   2      ; "it"
0015    KSTR     5   7      ; "should deserialize blitbuffer"
0016    FNEW     6   8      ; cache_spec.lua:26
0017    CALL     4   1   3
0018    GGET     4   2      ; "it"
0019    KSTR     5   9      ; "should serialize koptcontext"
0020    FNEW     6  10      ; cache_spec.lua:33
0021    CALL     4   1   3
0022    GGET     4   2      ; "it"
0023    KSTR     5  11      ; "should deserialize koptcontext"
0024    FNEW     6  12      ; cache_spec.lua:44
0025    CALL     4   1   3
0026    UCLO     0 => 0027
0027 => RET0     0   1

-- BYTECODE -- cache_spec.lua:0-51
0001    GGET     0   0      ; "describe"
0002    KSTR     1   1      ; "Cache module"
0003    FNEW     2   2      ; cache_spec.lua:1
0004    CALL     0   1   3
0005    RET0     0   1

