
main <./plugins/statistics.koplugin/calendarview.lua:0,0> (293 instructions, 1172 bytes at 0x7f9f774068f0)
0+ params, 45 slots, 0 upvalues, 35 locals, 105 constants, 21 functions
	1	[1]	GETGLOBAL	0 -1	; require
	2	[1]	LOADK    	1 -2	; "ui/bidi"
	3	[1]	CALL     	0 2 2
	4	[2]	GETGLOBAL	1 -1	; require
	5	[2]	LOADK    	2 -3	; "ffi/blitbuffer"
	6	[2]	CALL     	1 2 2
	7	[3]	GETGLOBAL	2 -1	; require
	8	[3]	LOADK    	3 -4	; "ui/widget/container/bottomcontainer"
	9	[3]	CALL     	2 2 2
	10	[4]	GETGLOBAL	3 -1	; require
	11	[4]	LOADK    	4 -5	; "ui/widget/button"
	12	[4]	CALL     	3 2 2
	13	[5]	GETGLOBAL	4 -1	; require
	14	[5]	LOADK    	5 -6	; "ui/widget/container/centercontainer"
	15	[5]	CALL     	4 2 2
	16	[6]	GETGLOBAL	5 -1	; require
	17	[6]	LOADK    	6 -7	; "ui/widget/closebutton"
	18	[6]	CALL     	5 2 2
	19	[7]	GETGLOBAL	6 -1	; require
	20	[7]	LOADK    	7 -8	; "device"
	21	[7]	CALL     	6 2 2
	22	[8]	GETGLOBAL	7 -1	; require
	23	[8]	LOADK    	8 -9	; "ui/font"
	24	[8]	CALL     	7 2 2
	25	[9]	GETGLOBAL	8 -1	; require
	26	[9]	LOADK    	9 -10	; "ui/widget/container/framecontainer"
	27	[9]	CALL     	8 2 2
	28	[10]	GETGLOBAL	9 -1	; require
	29	[10]	LOADK    	10 -11	; "ui/geometry"
	30	[10]	CALL     	9 2 2
	31	[11]	GETGLOBAL	10 -1	; require
	32	[11]	LOADK    	11 -12	; "ui/gesturerange"
	33	[11]	CALL     	10 2 2
	34	[12]	GETGLOBAL	11 -1	; require
	35	[12]	LOADK    	12 -13	; "ui/widget/horizontalgroup"
	36	[12]	CALL     	11 2 2
	37	[13]	GETGLOBAL	12 -1	; require
	38	[13]	LOADK    	13 -14	; "ui/widget/horizontalspan"
	39	[13]	CALL     	12 2 2
	40	[14]	GETGLOBAL	13 -1	; require
	41	[14]	LOADK    	14 -15	; "ui/widget/container/inputcontainer"
	42	[14]	CALL     	13 2 2
	43	[15]	GETGLOBAL	14 -1	; require
	44	[15]	LOADK    	15 -16	; "ui/widget/keyvaluepage"
	45	[15]	CALL     	14 2 2
	46	[16]	GETGLOBAL	15 -1	; require
	47	[16]	LOADK    	16 -17	; "ui/widget/container/leftcontainer"
	48	[16]	CALL     	15 2 2
	49	[17]	GETGLOBAL	16 -1	; require
	50	[17]	LOADK    	17 -18	; "optmath"
	51	[17]	CALL     	16 2 2
	52	[18]	GETGLOBAL	17 -1	; require
	53	[18]	LOADK    	18 -19	; "ui/widget/overlapgroup"
	54	[18]	CALL     	17 2 2
	55	[19]	GETGLOBAL	18 -1	; require
	56	[19]	LOADK    	19 -20	; "ui/size"
	57	[19]	CALL     	18 2 2
	58	[20]	GETGLOBAL	19 -1	; require
	59	[20]	LOADK    	20 -21	; "ui/widget/textboxwidget"
	60	[20]	CALL     	19 2 2
	61	[21]	GETGLOBAL	20 -1	; require
	62	[21]	LOADK    	21 -22	; "ui/widget/textwidget"
	63	[21]	CALL     	20 2 2
	64	[22]	GETGLOBAL	21 -1	; require
	65	[22]	LOADK    	22 -23	; "ui/uimanager"
	66	[22]	CALL     	21 2 2
	67	[23]	GETGLOBAL	22 -1	; require
	68	[23]	LOADK    	23 -24	; "ui/widget/verticalgroup"
	69	[23]	CALL     	22 2 2
	70	[24]	GETGLOBAL	23 -1	; require
	71	[24]	LOADK    	24 -25	; "ui/widget/verticalspan"
	72	[24]	CALL     	23 2 2
	73	[25]	GETGLOBAL	24 -1	; require
	74	[25]	LOADK    	25 -26	; "ui/widget/widget"
	75	[25]	CALL     	24 2 2
	76	[26]	GETTABLE 	25 6 -27	; "input"
	77	[27]	GETTABLE 	26 6 -28	; "screen"
	78	[28]	GETGLOBAL	27 -1	; require
	79	[28]	LOADK    	28 -29	; "gettext"
	80	[28]	CALL     	27 2 2
	81	[30]	SELF     	28 22 -30	; "new"
	82	[30]	NEWTABLE 	30 0 4
	83	[31]	SETTABLE 	30 -31 -32	; "calendar_view" nil
	84	[32]	SETTABLE 	30 -33 -34	; "title" ""
	85	[33]	SELF     	31 7 -36	; "getFace"
	86	[33]	LOADK    	33 -37	; "tfont"
	87	[33]	CALL     	31 3 2
	88	[33]	SETTABLE 	30 -35 31	; "tface" -
	89	[34]	SETTABLE 	30 -38 -39	; "align" "left"
	90	[30]	CALL     	28 3 2
	91	[51]	CLOSURE  	29 0	; 0x7f9f77407090
	92	[51]	MOVE     	0 5
	93	[51]	MOVE     	0 20
	94	[51]	MOVE     	0 17
	95	[51]	MOVE     	0 23
	96	[51]	MOVE     	0 18
	97	[37]	SETTABLE 	28 -40 29	; "init" -
	98	[55]	CLOSURE  	29 1	; 0x7f9f77407c20
	99	[53]	SETTABLE 	28 -41 29	; "setTitle" -
	100	[60]	CLOSURE  	29 2	; 0x7f9f77408240
	101	[57]	SETTABLE 	28 -42 29	; "onClose" -
	102	[63]	SELF     	29 24 -30	; "new"
	103	[63]	NEWTABLE 	31 0 5
	104	[64]	SETTABLE 	31 -43 -32	; "width" nil
	105	[65]	SETTABLE 	31 -44 -32	; "height" nil
	106	[66]	GETTABLE 	32 1 -46	; "COLOR_BLACK"
	107	[66]	SETTABLE 	31 -45 32	; "color" -
	108	[67]	SETTABLE 	31 -47 -32	; "nb_items" nil
	109	[68]	SETTABLE 	31 -48 -32	; "ratios" nil
	110	[63]	CALL     	29 3 2
	111	[88]	CLOSURE  	30 3	; 0x7f9f77408730
	112	[88]	MOVE     	0 9
	113	[88]	MOVE     	0 0
	114	[71]	SETTABLE 	29 -40 30	; "init" -
	115	[105]	CLOSURE  	30 4	; 0x7f9f774089f0
	116	[105]	MOVE     	0 16
	117	[90]	SETTABLE 	29 -49 30	; "paintTo" -
	118	[108]	SELF     	30 13 -30	; "new"
	119	[108]	NEWTABLE 	32 0 11
	120	[109]	SETTABLE 	32 -50 -32	; "daynum" nil
	121	[110]	SETTABLE 	32 -51 -32	; "ratio_per_hour" nil
	122	[111]	SETTABLE 	32 -52 -53	; "filler" false
	123	[112]	SETTABLE 	32 -43 -32	; "width" nil
	124	[113]	SETTABLE 	32 -44 -32	; "height" nil
	125	[114]	SETTABLE 	32 -54 -55	; "border" 0
	126	[115]	SETTABLE 	32 -56 -53	; "is_future" false
	127	[116]	SETTABLE 	32 -57 -58	; "font_face" "xx_smallinfofont"
	128	[117]	SETTABLE 	32 -59 -32	; "font_size" nil
	129	[118]	SETTABLE 	32 -60 -61	; "show_histo" true
	130	[119]	SETTABLE 	32 -62 -32	; "histo_height" nil
	131	[108]	CALL     	30 3 2
	132	[184]	CLOSURE  	31 5	; 0x7f9f774097d0
	133	[184]	MOVE     	0 9
	134	[184]	MOVE     	0 6
	135	[184]	MOVE     	0 10
	136	[184]	MOVE     	0 20
	137	[184]	MOVE     	0 7
	138	[184]	MOVE     	0 1
	139	[184]	MOVE     	0 2
	140	[184]	MOVE     	0 29
	141	[184]	MOVE     	0 8
	142	[184]	MOVE     	0 17
	143	[122]	SETTABLE 	30 -40 31	; "init" -
	144	[188]	CLOSURE  	31 6	; 0x7f9f77409850
	145	[186]	SETTABLE 	30 -63 31	; "updateNbNotShown" -
	146	[195]	CLOSURE  	31 7	; 0x7f9f7740a000
	147	[190]	SETTABLE 	30 -64 31	; "onTap" -
	148	[199]	CLOSURE  	31 8	; 0x7f9f77409bc0
	149	[197]	SETTABLE 	30 -65 31	; "onHold" -
	150	[202]	SELF     	31 13 -30	; "new"
	151	[202]	NEWTABLE 	33 0 10
	152	[203]	SETTABLE 	33 -43 -32	; "width" nil
	153	[204]	SETTABLE 	33 -44 -32	; "height" nil
	154	[205]	SETTABLE 	33 -66 -55	; "day_width" 0
	155	[206]	SETTABLE 	33 -67 -55	; "day_padding" 0
	156	[207]	SETTABLE 	33 -68 -55	; "day_border" 0
	157	[208]	SETTABLE 	33 -69 -55	; "nb_book_spans" 0
	158	[209]	SETTABLE 	33 -70 -32	; "histo_shown" nil
	159	[210]	SETTABLE 	33 -71 -32	; "span_height" nil
	160	[211]	SETTABLE 	33 -59 -55	; "font_size" 0
	161	[212]	SETTABLE 	33 -57 -58	; "font_face" "xx_smallinfofont"
	162	[202]	CALL     	31 3 2
	163	[218]	CLOSURE  	32 9	; 0x7f9f7740a530
	164	[215]	SETTABLE 	31 -40 32	; "init" -
	165	[274]	CLOSURE  	32 10	; 0x7f9f7740a5c0
	166	[220]	SETTABLE 	31 -72 32	; "addDay" -
	167	[277]	NEWTABLE 	32 8 0
	168	[277]	NEWTABLE 	33 2 0
	169	[278]	GETTABLE 	34 1 -46	; "COLOR_BLACK"
	170	[278]	GETTABLE 	35 1 -73	; "COLOR_WHITE"
	171	[278]	SETLIST  	33 2 1	; 1
	172	[278]	NEWTABLE 	34 2 0
	173	[279]	GETTABLE 	35 1 -46	; "COLOR_BLACK"
	174	[279]	GETTABLE 	36 1 -74	; "COLOR_GRAY_E"
	175	[279]	SETLIST  	34 2 1	; 1
	176	[279]	NEWTABLE 	35 2 0
	177	[280]	GETTABLE 	36 1 -46	; "COLOR_BLACK"
	178	[280]	GETTABLE 	37 1 -75	; "COLOR_LIGHT_GRAY"
	179	[280]	SETLIST  	35 2 1	; 1
	180	[280]	NEWTABLE 	36 2 0
	181	[281]	GETTABLE 	37 1 -46	; "COLOR_BLACK"
	182	[281]	GETTABLE 	38 1 -76	; "COLOR_GRAY"
	183	[281]	SETLIST  	36 2 1	; 1
	184	[281]	NEWTABLE 	37 2 0
	185	[282]	GETTABLE 	38 1 -73	; "COLOR_WHITE"
	186	[282]	GETTABLE 	39 1 -77	; "COLOR_WEB_GRAY"
	187	[282]	SETLIST  	37 2 1	; 1
	188	[282]	NEWTABLE 	38 2 0
	189	[283]	GETTABLE 	39 1 -73	; "COLOR_WHITE"
	190	[283]	GETTABLE 	40 1 -78	; "COLOR_DARK_GRAY"
	191	[283]	SETLIST  	38 2 1	; 1
	192	[283]	NEWTABLE 	39 2 0
	193	[284]	GETTABLE 	40 1 -73	; "COLOR_WHITE"
	194	[284]	GETTABLE 	41 1 -79	; "COLOR_DIM_GRAY"
	195	[284]	SETLIST  	39 2 1	; 1
	196	[284]	NEWTABLE 	40 2 0
	197	[285]	GETTABLE 	41 1 -73	; "COLOR_WHITE"
	198	[285]	GETTABLE 	42 1 -46	; "COLOR_BLACK"
	199	[285]	SETLIST  	40 2 1	; 1
	200	[286]	SETLIST  	32 8 1	; 1
	201	[394]	CLOSURE  	33 11	; 0x7f9f77408630
	202	[394]	MOVE     	0 9
	203	[394]	MOVE     	0 11
	204	[394]	MOVE     	0 12
	205	[394]	MOVE     	0 17
	206	[394]	MOVE     	0 18
	207	[394]	MOVE     	0 19
	208	[394]	MOVE     	0 32
	209	[394]	MOVE     	0 8
	210	[394]	MOVE     	0 4
	211	[394]	MOVE     	0 20
	212	[394]	MOVE     	0 0
	213	[394]	MOVE     	0 7
	214	[394]	MOVE     	0 15
	215	[288]	SETTABLE 	31 -80 33	; "update" -
	216	[397]	LOADNIL  	33 33
	217	[399]	SELF     	34 13 -30	; "new"
	218	[399]	NEWTABLE 	36 0 14
	219	[400]	SETTABLE 	36 -81 -32	; "reader_statistics" nil
	220	[401]	SETTABLE 	36 -82 -32	; "monthTranslation" nil
	221	[402]	SETTABLE 	36 -83 -32	; "shortDayOfWeekTranslation" nil
	222	[403]	SETTABLE 	36 -84 -32	; "longDayOfWeekTranslation" nil
	223	[404]	SETTABLE 	36 -85 -86	; "start_day_of_week" 2
	224	[405]	SETTABLE 	36 -87 -61	; "show_hourly_histogram" true
	225	[406]	SETTABLE 	36 -88 -53	; "browse_future_months" false
	226	[407]	SETTABLE 	36 -69 -89	; "nb_book_spans" 3
	227	[408]	SETTABLE 	36 -57 -58	; "font_face" "xx_smallinfofont"
	228	[409]	SETTABLE 	36 -33 -34	; "title" ""
	229	[410]	SETTABLE 	36 -43 -32	; "width" nil
	230	[411]	SETTABLE 	36 -44 -32	; "height" nil
	231	[412]	SETTABLE 	36 -90 -32	; "cur_month" nil
	232	[413]	NEWTABLE 	37 7 0
	233	[413]	LOADK    	38 -92	; "Sun"
	234	[413]	LOADK    	39 -93	; "Mon"
	235	[413]	LOADK    	40 -94	; "Tue"
	236	[413]	LOADK    	41 -95	; "Wed"
	237	[413]	LOADK    	42 -96	; "Thu"
	238	[413]	LOADK    	43 -97	; "Fri"
	239	[413]	LOADK    	44 -98	; "Sat"
	240	[413]	SETLIST  	37 7 1	; 1
	241	[413]	SETTABLE 	36 -91 37	; "weekdays" -
	242	[399]	CALL     	34 3 2
	243	[631]	CLOSURE  	35 12	; 0x7f9f7740b6a0
	244	[631]	MOVE     	0 9
	245	[631]	MOVE     	0 26
	246	[631]	MOVE     	0 6
	247	[631]	MOVE     	0 25
	248	[631]	MOVE     	0 10
	249	[631]	MOVE     	0 18
	250	[631]	MOVE     	0 33
	251	[631]	MOVE     	0 0
	252	[631]	MOVE     	0 3
	253	[631]	MOVE     	0 12
	254	[631]	MOVE     	0 27
	255	[631]	MOVE     	0 21
	256	[631]	MOVE     	0 11
	257	[631]	MOVE     	0 2
	258	[631]	MOVE     	0 28
	259	[631]	MOVE     	0 20
	260	[631]	MOVE     	0 7
	261	[631]	MOVE     	0 8
	262	[631]	MOVE     	0 4
	263	[631]	MOVE     	0 19
	264	[631]	MOVE     	0 22
	265	[631]	MOVE     	0 17
	266	[631]	MOVE     	0 1
	267	[418]	SETTABLE 	34 -40 35	; "init" -
	268	[748]	CLOSURE  	35 13	; 0x7f9f7740be90
	269	[748]	MOVE     	0 23
	270	[748]	MOVE     	0 31
	271	[748]	MOVE     	0 30
	272	[748]	MOVE     	0 21
	273	[748]	MOVE     	0 14
	274	[633]	SETTABLE 	34 -99 35	; "_populateItems" -
	275	[762]	CLOSURE  	35 14	; 0x7f9f7740dc70
	276	[750]	SETTABLE 	34 -100 35	; "nextMonth" -
	277	[776]	CLOSURE  	35 15	; 0x7f9f7740e490
	278	[764]	SETTABLE 	34 -101 35	; "prevMonth" -
	279	[781]	CLOSURE  	35 16	; 0x7f9f7740e610
	280	[778]	SETTABLE 	34 -102 35	; "goToMonth" -
	281	[786]	CLOSURE  	35 17	; 0x7f9f7740a4b0
	282	[783]	SETTABLE 	34 -103 35	; "onNextMonth" -
	283	[791]	CLOSURE  	35 18	; 0x7f9f7740e9c0
	284	[788]	SETTABLE 	34 -104 35	; "onPrevMonth" -
	285	[814]	CLOSURE  	35 19	; 0x7f9f7740ec20
	286	[814]	MOVE     	0 0
	287	[814]	MOVE     	0 21
	288	[793]	SETTABLE 	34 -105 35	; "onSwipe" -
	289	[819]	CLOSURE  	35 20	; 0x7f9f7740f040
	290	[819]	MOVE     	0 21
	291	[816]	SETTABLE 	34 -42 35	; "onClose" -
	292	[821]	RETURN   	34 2
	293	[821]	RETURN   	0 1

function <./plugins/statistics.koplugin/calendarview.lua:37,51> (50 instructions, 200 bytes at 0x7f9f77407090)
1 param, 9 slots, 5 upvalues, 2 locals, 17 constants, 0 functions
	1	[38]	GETUPVAL 	1 0	; CloseButton
	2	[38]	SELF     	1 1 -2	; "new"
	3	[38]	NEWTABLE 	3 0 1
	4	[38]	SETTABLE 	3 -3 0	; "window" -
	5	[38]	CALL     	1 3 2
	6	[38]	SETTABLE 	0 -1 1	; "close_button" -
	7	[39]	GETTABLE 	1 0 -1	; "close_button"
	8	[39]	SELF     	1 1 -4	; "getSize"
	9	[39]	CALL     	1 2 2
	10	[39]	GETTABLE 	1 1 -5	; "w"
	11	[40]	GETUPVAL 	2 1	; TextWidget
	12	[40]	SELF     	2 2 -2	; "new"
	13	[40]	NEWTABLE 	4 0 3
	14	[41]	GETTABLE 	5 0 -8	; "title"
	15	[41]	SETTABLE 	4 -7 5	; "text" -
	16	[42]	GETTABLE 	5 0 -10	; "width"
	17	[42]	SUB      	5 5 1
	18	[42]	SETTABLE 	4 -9 5	; "max_width" -
	19	[43]	GETTABLE 	5 0 -12	; "tface"
	20	[43]	SETTABLE 	4 -11 5	; "face" -
	21	[40]	CALL     	2 3 2
	22	[44]	SETTABLE 	0 -6 2	; "text_w" -
	23	[45]	GETGLOBAL	2 -13	; table
	24	[45]	GETTABLE 	2 2 -14	; "insert"
	25	[45]	MOVE     	3 0
	26	[45]	GETUPVAL 	4 2	; OverlapGroup
	27	[45]	SELF     	4 4 -2	; "new"
	28	[45]	NEWTABLE 	6 2 1
	29	[46]	NEWTABLE 	7 0 1
	30	[46]	GETTABLE 	8 0 -10	; "width"
	31	[46]	SETTABLE 	7 -5 8	; "w" -
	32	[46]	SETTABLE 	6 -15 7	; "dimen" -
	33	[47]	GETTABLE 	7 0 -6	; "text_w"
	34	[49]	GETTABLE 	8 0 -1	; "close_button"
	35	[49]	SETLIST  	6 2 1	; 1
	36	[45]	CALL     	4 3 0
	37	[45]	CALL     	2 0 1
	38	[50]	GETGLOBAL	2 -13	; table
	39	[50]	GETTABLE 	2 2 -14	; "insert"
	40	[50]	MOVE     	3 0
	41	[50]	GETUPVAL 	4 3	; VerticalSpan
	42	[50]	SELF     	4 4 -2	; "new"
	43	[50]	NEWTABLE 	6 0 1
	44	[50]	GETUPVAL 	7 4	; Size
	45	[50]	GETTABLE 	7 7 -16	; "span"
	46	[50]	GETTABLE 	7 7 -17	; "vertical_large"
	47	[50]	SETTABLE 	6 -10 7	; "width" -
	48	[50]	CALL     	4 3 0
	49	[50]	CALL     	2 0 1
	50	[51]	RETURN   	0 1

function <./plugins/statistics.koplugin/calendarview.lua:53,55> (5 instructions, 20 bytes at 0x7f9f77407c20)
2 params, 5 slots, 0 upvalues, 2 locals, 2 constants, 0 functions
	1	[54]	GETTABLE 	2 0 -1	; "text_w"
	2	[54]	SELF     	2 2 -2	; "setText"
	3	[54]	MOVE     	4 1
	4	[54]	CALL     	2 3 1
	5	[55]	RETURN   	0 1

function <./plugins/statistics.koplugin/calendarview.lua:57,60> (6 instructions, 24 bytes at 0x7f9f77408240)
1 param, 3 slots, 0 upvalues, 1 local, 2 constants, 0 functions
	1	[58]	GETTABLE 	1 0 -1	; "calendar_view"
	2	[58]	SELF     	1 1 -2	; "onClose"
	3	[58]	CALL     	1 2 1
	4	[59]	LOADBOOL 	1 1 0
	5	[59]	RETURN   	1 2
	6	[60]	RETURN   	0 1

function <./plugins/statistics.koplugin/calendarview.lua:71,88> (51 instructions, 204 bytes at 0x7f9f77408730)
1 param, 12 slots, 2 upvalues, 9 locals, 17 constants, 0 functions
	1	[72]	GETUPVAL 	1 0	; Geom
	2	[72]	SELF     	1 1 -2	; "new"
	3	[72]	NEWTABLE 	3 0 2
	4	[72]	GETTABLE 	4 0 -4	; "width"
	5	[72]	SETTABLE 	3 -3 4	; "w" -
	6	[72]	GETTABLE 	4 0 -6	; "height"
	7	[72]	SETTABLE 	3 -5 4	; "h" -
	8	[72]	CALL     	1 3 2
	9	[72]	SETTABLE 	0 -1 1	; "dimen" -
	10	[73]	GETGLOBAL	1 -7	; math
	11	[73]	GETTABLE 	1 1 -8	; "floor"
	12	[73]	GETTABLE 	2 0 -4	; "width"
	13	[73]	GETTABLE 	3 0 -9	; "nb_items"
	14	[73]	DIV      	2 2 3
	15	[73]	CALL     	1 2 2
	16	[74]	GETTABLE 	2 0 -4	; "width"
	17	[74]	GETTABLE 	3 0 -9	; "nb_items"
	18	[74]	MUL      	3 3 1
	19	[74]	SUB      	2 2 3
	20	[75]	GETGLOBAL	3 -7	; math
	21	[75]	GETTABLE 	3 3 -8	; "floor"
	22	[75]	GETTABLE 	4 0 -9	; "nb_items"
	23	[75]	DIV      	4 4 2
	24	[75]	CALL     	3 2 2
	25	[76]	NEWTABLE 	4 0 0
	26	[76]	SETTABLE 	0 -10 4	; "item_widths" -
	27	[77]	LOADK    	4 -11	; 1
	28	[77]	GETTABLE 	5 0 -9	; "nb_items"
	29	[77]	LOADK    	6 -11	; 1
	30	[77]	FORPREP  	4 13	; to 44
	31	[78]	MOVE     	8 1
	32	[79]	LT       	0 -12 2	; 0 -
	33	[79]	JMP      	5	; to 39
	34	[79]	MOD      	9 7 3
	35	[79]	EQ       	0 9 -12	; - 0
	36	[79]	JMP      	2	; to 39
	37	[80]	ADD      	8 8 -11	; - 1
	38	[81]	SUB      	2 2 -11	; - 1
	39	[83]	GETGLOBAL	9 -13	; table
	40	[83]	GETTABLE 	9 9 -14	; "insert"
	41	[83]	GETTABLE 	10 0 -10	; "item_widths"
	42	[83]	MOVE     	11 8
	43	[83]	CALL     	9 3 1
	44	[77]	FORLOOP  	4 -14	; to 31
	45	[85]	GETUPVAL 	4 1	; BD
	46	[85]	GETTABLE 	4 4 -15	; "mirroredUILayout"
	47	[85]	CALL     	4 1 2
	48	[85]	TEST     	4 0 0
	49	[85]	JMP      	1	; to 51
	50	[86]	SETTABLE 	0 -16 -17	; "do_mirror" true
	51	[88]	RETURN   	0 1

function <./plugins/statistics.koplugin/calendarview.lua:90,105> (40 instructions, 160 bytes at 0x7f9f774089f0)
4 params, 20 slots, 1 upvalue, 13 locals, 10 constants, 0 functions
	1	[91]	LOADK    	4 -1	; 0
	2	[92]	LOADK    	5 -2	; 1
	3	[92]	GETTABLE 	6 0 -3	; "nb_items"
	4	[92]	LOADK    	7 -2	; 1
	5	[92]	FORPREP  	5 33	; to 39
	6	[93]	GETTABLE 	9 0 -4	; "do_mirror"
	7	[93]	TEST     	9 0 0
	8	[93]	JMP      	3	; to 12
	9	[94]	GETTABLE 	9 0 -3	; "nb_items"
	10	[94]	SUB      	9 9 8
	11	[94]	ADD      	8 9 -2	; - 1
	12	[96]	GETTABLE 	9 0 -5	; "item_widths"
	13	[96]	GETTABLE 	9 9 8
	14	[97]	GETTABLE 	10 0 -6	; "ratios"
	15	[97]	TEST     	10 0 0
	16	[97]	JMP      	4	; to 21
	17	[97]	GETTABLE 	10 0 -6	; "ratios"
	18	[97]	GETTABLE 	10 10 8
	19	[97]	TEST     	10 0 1
	20	[97]	JMP      	1	; to 22
	21	[97]	LOADK    	10 -1	; 0
	22	[98]	GETUPVAL 	11 0	; Math
	23	[98]	GETTABLE 	11 11 -7	; "round"
	24	[98]	GETTABLE 	12 0 -8	; "height"
	25	[98]	MUL      	12 10 12
	26	[98]	CALL     	11 2 2
	27	[99]	GETTABLE 	12 0 -8	; "height"
	28	[99]	SUB      	12 12 11
	29	[100]	LT       	0 -1 11	; 0 -
	30	[100]	JMP      	7	; to 38
	31	[101]	SELF     	13 1 -9	; "paintRect"
	32	[101]	ADD      	15 2 4
	33	[101]	ADD      	16 3 12
	34	[101]	MOVE     	17 9
	35	[101]	MOVE     	18 11
	36	[101]	GETTABLE 	19 0 -10	; "color"
	37	[101]	CALL     	13 7 1
	38	[103]	ADD      	4 4 9
	39	[92]	FORLOOP  	5 -34	; to 6
	40	[105]	RETURN   	0 1

function <./plugins/statistics.koplugin/calendarview.lua:122,184> (163 instructions, 652 bytes at 0x7f9f774097d0)
1 param, 12 slots, 10 upvalues, 3 locals, 51 constants, 0 functions
	1	[123]	GETUPVAL 	1 0	; Geom
	2	[123]	SELF     	1 1 -2	; "new"
	3	[123]	NEWTABLE 	3 0 2
	4	[123]	GETTABLE 	4 0 -4	; "width"
	5	[123]	SETTABLE 	3 -3 4	; "w" -
	6	[123]	GETTABLE 	4 0 -6	; "height"
	7	[123]	SETTABLE 	3 -5 4	; "h" -
	8	[123]	CALL     	1 3 2
	9	[123]	SETTABLE 	0 -1 1	; "dimen" -
	10	[124]	GETTABLE 	1 0 -7	; "filler"
	11	[124]	TEST     	1 0 0
	12	[124]	JMP      	1	; to 14
	13	[125]	RETURN   	0 1
	14	[127]	GETTABLE 	1 0 -8	; "callback"
	15	[127]	TEST     	1 0 0
	16	[127]	JMP      	27	; to 44
	17	[127]	GETUPVAL 	1 1	; Device
	18	[127]	SELF     	1 1 -9	; "isTouchDevice"
	19	[127]	CALL     	1 2 2
	20	[127]	TEST     	1 0 0
	21	[127]	JMP      	22	; to 44
	22	[128]	GETTABLE 	1 0 -10	; "ges_events"
	23	[128]	NEWTABLE 	2 0 0
	24	[129]	GETUPVAL 	3 2	; GestureRange
	25	[129]	SELF     	3 3 -2	; "new"
	26	[129]	NEWTABLE 	5 0 2
	27	[130]	SETTABLE 	5 -12 -13	; "ges" "tap"
	28	[131]	GETTABLE 	6 0 -1	; "dimen"
	29	[131]	SETTABLE 	5 -14 6	; "range" -
	30	[129]	CALL     	3 3 0
	31	[133]	SETLIST  	2 0 1	; 1
	32	[133]	SETTABLE 	1 -11 2	; "Tap" -
	33	[134]	GETTABLE 	1 0 -10	; "ges_events"
	34	[134]	NEWTABLE 	2 0 0
	35	[135]	GETUPVAL 	3 2	; GestureRange
	36	[135]	SELF     	3 3 -2	; "new"
	37	[135]	NEWTABLE 	5 0 2
	38	[136]	SETTABLE 	5 -12 -16	; "ges" "hold"
	39	[137]	GETTABLE 	6 0 -1	; "dimen"
	40	[137]	SETTABLE 	5 -14 6	; "range" -
	41	[135]	CALL     	3 3 0
	42	[139]	SETLIST  	2 0 1	; 1
	43	[139]	SETTABLE 	1 -15 2	; "Hold" -
	44	[142]	GETUPVAL 	1 3	; TextWidget
	45	[142]	SELF     	1 1 -2	; "new"
	46	[142]	NEWTABLE 	3 0 5
	47	[143]	LOADK    	4 -19	; " "
	48	[143]	GETGLOBAL	5 -20	; tostring
	49	[143]	GETTABLE 	6 0 -21	; "daynum"
	50	[143]	CALL     	5 2 2
	51	[143]	CONCAT   	4 4 5
	52	[143]	SETTABLE 	3 -18 4	; "text" -
	53	[144]	GETUPVAL 	4 4	; Font
	54	[144]	SELF     	4 4 -23	; "getFace"
	55	[144]	GETTABLE 	6 0 -24	; "font_face"
	56	[144]	GETTABLE 	7 0 -25	; "font_size"
	57	[144]	CALL     	4 4 2
	58	[144]	SETTABLE 	3 -22 4	; "face" -
	59	[145]	GETTABLE 	4 0 -27	; "is_future"
	60	[145]	TEST     	4 0 0
	61	[145]	JMP      	4	; to 66
	62	[145]	GETUPVAL 	4 5	; Blitbuffer
	63	[145]	GETTABLE 	4 4 -28	; "COLOR_GRAY"
	64	[145]	TEST     	4 0 1
	65	[145]	JMP      	2	; to 68
	66	[145]	GETUPVAL 	4 5	; Blitbuffer
	67	[145]	GETTABLE 	4 4 -29	; "COLOR_BLACK"
	68	[145]	SETTABLE 	3 -26 4	; "fgcolor" -
	69	[146]	SETTABLE 	3 -30 -31	; "padding" 0
	70	[147]	SETTABLE 	3 -32 -33	; "bold" true
	71	[142]	CALL     	1 3 2
	72	[148]	SETTABLE 	0 -17 1	; "daynum_w" -
	73	[149]	GETUPVAL 	1 3	; TextWidget
	74	[149]	SELF     	1 1 -2	; "new"
	75	[149]	NEWTABLE 	3 0 4
	76	[150]	SETTABLE 	3 -18 -35	; "text" ""
	77	[151]	GETUPVAL 	4 4	; Font
	78	[151]	SELF     	4 4 -23	; "getFace"
	79	[151]	GETTABLE 	6 0 -24	; "font_face"
	80	[151]	GETTABLE 	7 0 -25	; "font_size"
	81	[151]	SUB      	7 7 -36	; - 1
	82	[151]	CALL     	4 4 2
	83	[151]	SETTABLE 	3 -22 4	; "face" -
	84	[152]	GETUPVAL 	4 5	; Blitbuffer
	85	[152]	GETTABLE 	4 4 -37	; "COLOR_DARK_GRAY"
	86	[152]	SETTABLE 	3 -26 4	; "fgcolor" -
	87	[153]	SETTABLE 	3 -38 -39	; "overlap_align" "right"
	88	[149]	CALL     	1 3 2
	89	[154]	SETTABLE 	0 -34 1	; "nb_not_shown_w" -
	90	[155]	GETTABLE 	1 0 -4	; "width"
	91	[155]	GETTABLE 	2 0 -40	; "border"
	92	[155]	MUL      	2 -41 2	; 2 -
	93	[155]	SUB      	1 1 2
	94	[156]	GETTABLE 	2 0 -6	; "height"
	95	[156]	GETTABLE 	3 0 -40	; "border"
	96	[156]	MUL      	3 -41 3	; 2 -
	97	[156]	SUB      	2 2 3
	98	[157]	GETTABLE 	3 0 -42	; "show_histo"
	99	[157]	TEST     	3 0 0
	100	[157]	JMP      	28	; to 129
	101	[158]	GETTABLE 	3 0 -43	; "histo_height"
	102	[158]	TEST     	3 0 1
	103	[158]	JMP      	2	; to 106
	104	[159]	DIV      	3 2 -44	; - 3
	105	[159]	SETTABLE 	0 -43 3	; "histo_height" -
	106	[161]	GETUPVAL 	3 6	; BottomContainer
	107	[161]	SELF     	3 3 -2	; "new"
	108	[161]	NEWTABLE 	5 0 1
	109	[162]	GETUPVAL 	6 0	; Geom
	110	[162]	SELF     	6 6 -2	; "new"
	111	[162]	NEWTABLE 	8 0 2
	112	[162]	SETTABLE 	8 -3 1	; "w" -
	113	[162]	SETTABLE 	8 -5 2	; "h" -
	114	[162]	CALL     	6 3 2
	115	[162]	SETTABLE 	5 -1 6	; "dimen" -
	116	[163]	GETUPVAL 	6 7	; HistogramWidget
	117	[163]	SELF     	6 6 -2	; "new"
	118	[163]	NEWTABLE 	8 0 4
	119	[164]	SETTABLE 	8 -4 1	; "width" -
	120	[165]	GETTABLE 	9 0 -43	; "histo_height"
	121	[165]	SETTABLE 	8 -6 9	; "height" -
	122	[166]	SETTABLE 	8 -46 -47	; "nb_items" 24
	123	[167]	GETTABLE 	9 0 -49	; "ratio_per_hour"
	124	[167]	SETTABLE 	8 -48 9	; "ratios" -
	125	[163]	CALL     	6 3 0
	126	[169]	SETLIST  	5 0 1	; 1
	127	[161]	CALL     	3 3 2
	128	[169]	SETTABLE 	0 -45 3	; "histo_w" -
	129	[171]	GETUPVAL 	3 8	; FrameContainer
	130	[171]	SELF     	3 3 -2	; "new"
	131	[171]	NEWTABLE 	5 0 5
	132	[172]	SETTABLE 	5 -30 -31	; "padding" 0
	133	[173]	GETTABLE 	6 0 -27	; "is_future"
	134	[173]	TEST     	6 0 0
	135	[173]	JMP      	4	; to 140
	136	[173]	GETUPVAL 	6 5	; Blitbuffer
	137	[173]	GETTABLE 	6 6 -28	; "COLOR_GRAY"
	138	[173]	TEST     	6 0 1
	139	[173]	JMP      	2	; to 142
	140	[173]	GETUPVAL 	6 5	; Blitbuffer
	141	[173]	GETTABLE 	6 6 -29	; "COLOR_BLACK"
	142	[173]	SETTABLE 	5 -50 6	; "color" -
	143	[174]	GETTABLE 	6 0 -40	; "border"
	144	[174]	SETTABLE 	5 -51 6	; "bordersize" -
	145	[175]	GETTABLE 	6 0 -4	; "width"
	146	[175]	SETTABLE 	5 -4 6	; "width" -
	147	[176]	GETTABLE 	6 0 -6	; "height"
	148	[176]	SETTABLE 	5 -6 6	; "height" -
	149	[177]	GETUPVAL 	6 9	; OverlapGroup
	150	[177]	SELF     	6 6 -2	; "new"
	151	[177]	NEWTABLE 	8 3 1
	152	[178]	NEWTABLE 	9 0 1
	153	[178]	SETTABLE 	9 -3 1	; "w" -
	154	[178]	SETTABLE 	8 -1 9	; "dimen" -
	155	[179]	GETTABLE 	9 0 -17	; "daynum_w"
	156	[180]	GETTABLE 	10 0 -34	; "nb_not_shown_w"
	157	[182]	GETTABLE 	11 0 -45	; "histo_w"
	158	[182]	SETLIST  	8 3 1	; 1
	159	[177]	CALL     	6 3 0
	160	[183]	SETLIST  	5 0 1	; 1
	161	[171]	CALL     	3 3 2
	162	[183]	SETTABLE 	0 -36 3	; 1 -
	163	[184]	RETURN   	0 1

function <./plugins/statistics.koplugin/calendarview.lua:186,188> (9 instructions, 36 bytes at 0x7f9f77409850)
2 params, 7 slots, 0 upvalues, 2 locals, 5 constants, 0 functions
	1	[187]	GETTABLE 	2 0 -1	; "nb_not_shown_w"
	2	[187]	SELF     	2 2 -2	; "setText"
	3	[187]	GETGLOBAL	4 -3	; string
	4	[187]	GETTABLE 	4 4 -4	; "format"
	5	[187]	LOADK    	5 -5	; "+ %d "
	6	[187]	MOVE     	6 1
	7	[187]	CALL     	4 3 0
	8	[187]	CALL     	2 0 1
	9	[188]	RETURN   	0 1

function <./plugins/statistics.koplugin/calendarview.lua:190,195> (8 instructions, 32 bytes at 0x7f9f7740a000)
1 param, 2 slots, 0 upvalues, 1 local, 1 constant, 0 functions
	1	[191]	GETTABLE 	1 0 -1	; "callback"
	2	[191]	TEST     	1 0 0
	3	[191]	JMP      	2	; to 6
	4	[192]	GETTABLE 	1 0 -1	; "callback"
	5	[192]	CALL     	1 1 1
	6	[194]	LOADBOOL 	1 1 0
	7	[194]	RETURN   	1 2
	8	[195]	RETURN   	0 1

function <./plugins/statistics.koplugin/calendarview.lua:197,199> (4 instructions, 16 bytes at 0x7f9f77409bc0)
1 param, 3 slots, 0 upvalues, 1 local, 1 constant, 0 functions
	1	[198]	SELF     	1 0 -1	; "onTap"
	2	[198]	TAILCALL 	1 2 0
	3	[198]	RETURN   	1 0
	4	[199]	RETURN   	0 1

function <./plugins/statistics.koplugin/calendarview.lua:215,218> (5 instructions, 20 bytes at 0x7f9f7740a530)
1 param, 2 slots, 0 upvalues, 1 local, 2 constants, 0 functions
	1	[216]	NEWTABLE 	1 0 0
	2	[216]	SETTABLE 	0 -1 1	; "calday_widgets" -
	3	[217]	NEWTABLE 	1 0 0
	4	[217]	SETTABLE 	0 -2 1	; "days_books" -
	5	[218]	RETURN   	0 1

function <./plugins/statistics.koplugin/calendarview.lua:220,274> (104 instructions, 416 bytes at 0x7f9f7740a5c0)
2 params, 23 slots, 0 upvalues, 25 locals, 15 constants, 0 functions
	1	[224]	GETGLOBAL	2 -1	; table
	2	[224]	GETTABLE 	2 2 -2	; "insert"
	3	[224]	GETTABLE 	3 0 -3	; "calday_widgets"
	4	[224]	MOVE     	4 1
	5	[224]	CALL     	2 3 1
	6	[226]	GETTABLE 	2 0 -4	; "days_books"
	7	[226]	LEN      	2 2
	8	[227]	LT       	0 -5 2	; 0 -
	9	[227]	JMP      	5	; to 15
	10	[227]	GETTABLE 	3 0 -4	; "days_books"
	11	[227]	GETTABLE 	4 0 -4	; "days_books"
	12	[227]	LEN      	4 4
	13	[227]	GETTABLE 	3 3 4
	14	[227]	JMP      	2	; to 17
	15	[227]	LOADBOOL 	3 0 1
	16	[227]	LOADBOOL 	3 1 0
	17	[228]	ADD      	4 2 -6	; - 1
	18	[229]	NEWTABLE 	5 0 0
	19	[230]	GETGLOBAL	6 -1	; table
	20	[230]	GETTABLE 	6 6 -2	; "insert"
	21	[230]	GETTABLE 	7 0 -4	; "days_books"
	22	[230]	MOVE     	8 5
	23	[230]	CALL     	6 3 1
	24	[232]	GETTABLE 	6 1 -7	; "read_books"
	25	[232]	TEST     	6 0 1
	26	[232]	JMP      	2	; to 29
	27	[233]	NEWTABLE 	6 0 0
	28	[233]	SETTABLE 	1 -7 6	; "read_books" -
	29	[235]	GETTABLE 	6 1 -7	; "read_books"
	30	[235]	LEN      	6 6
	31	[236]	GETTABLE 	7 0 -8	; "nb_book_spans"
	32	[236]	LT       	0 7 6
	33	[236]	JMP      	4	; to 38
	34	[237]	SELF     	7 1 -9	; "updateNbNotShown"
	35	[237]	GETTABLE 	9 0 -8	; "nb_book_spans"
	36	[237]	SUB      	9 6 9
	37	[237]	CALL     	7 3 1
	38	[239]	LOADK    	7 -6	; 1
	39	[239]	GETTABLE 	8 0 -8	; "nb_book_spans"
	40	[239]	LOADK    	9 -6	; 1
	41	[239]	FORPREP  	7 15	; to 57
	42	[240]	GETTABLE 	11 1 -7	; "read_books"
	43	[240]	GETTABLE 	11 11 10
	44	[240]	TEST     	11 0 0
	45	[240]	JMP      	10	; to 56
	46	[241]	GETTABLE 	11 1 -7	; "read_books"
	47	[241]	GETTABLE 	11 11 10
	48	[241]	SETTABLE 	5 10 11
	49	[242]	GETTABLE 	11 5 10
	50	[242]	SETTABLE 	11 -10 -6	; "span_days" 1
	51	[243]	GETTABLE 	11 5 10
	52	[243]	SETTABLE 	11 -11 4	; "start_day" -
	53	[244]	GETTABLE 	11 5 10
	54	[244]	SETTABLE 	11 -12 -13	; "fixed" false
	55	[244]	JMP      	1	; to 57
	56	[246]	SETTABLE 	5 10 -13	; - false
	57	[239]	FORLOOP  	7 -16	; to 42
	58	[250]	TEST     	3 0 0
	59	[250]	JMP      	44	; to 104
	60	[252]	LOADK    	7 -6	; 1
	61	[252]	LEN      	8 3
	62	[252]	LOADK    	9 -6	; 1
	63	[252]	FORPREP  	7 39	; to 103
	64	[253]	GETTABLE 	11 3 10
	65	[254]	TEST     	11 0 0
	66	[254]	JMP      	36	; to 103
	67	[255]	LOADK    	12 -6	; 1
	68	[255]	LEN      	13 5
	69	[255]	LOADK    	14 -6	; 1
	70	[255]	FORPREP  	12 31	; to 102
	71	[256]	GETTABLE 	16 5 15
	72	[257]	TEST     	16 0 0
	73	[257]	JMP      	28	; to 102
	74	[257]	GETTABLE 	17 16 -14	; "id"
	75	[257]	GETTABLE 	18 11 -14	; "id"
	76	[257]	EQ       	0 17 18
	77	[257]	JMP      	24	; to 102
	78	[258]	GETTABLE 	17 11 -11	; "start_day"
	79	[258]	SETTABLE 	16 -11 17	; "start_day" -
	80	[259]	SETTABLE 	16 -12 -15	; "fixed" true
	81	[260]	GETTABLE 	17 11 -10	; "span_days"
	82	[260]	ADD      	17 17 -6	; - 1
	83	[260]	SETTABLE 	16 -10 17	; "span_days" -
	84	[262]	LOADK    	17 -6	; 1
	85	[262]	GETTABLE 	18 11 -10	; "span_days"
	86	[262]	LOADK    	19 -6	; 1
	87	[262]	FORPREP  	17 6	; to 94
	88	[263]	GETTABLE 	21 0 -4	; "days_books"
	89	[263]	SUB      	22 4 20
	90	[263]	GETTABLE 	21 21 22
	91	[263]	GETTABLE 	21 21 10
	92	[263]	GETTABLE 	22 16 -10	; "span_days"
	93	[263]	SETTABLE 	21 -10 22	; "span_days" -
	94	[262]	FORLOOP  	17 -7	; to 88
	95	[265]	EQ       	1 15 10
	96	[265]	JMP      	6	; to 103
	97	[266]	GETTABLE 	17 5 10
	98	[266]	GETTABLE 	18 5 15
	99	[266]	SETTABLE 	5 10 18
	100	[266]	SETTABLE 	5 15 17
	101	[268]	JMP      	1	; to 103
	102	[255]	FORLOOP  	12 -32	; to 71
	103	[252]	FORLOOP  	7 -40	; to 64
	104	[274]	RETURN   	0 1

function <./plugins/statistics.koplugin/calendarview.lua:288,394> (248 instructions, 992 bytes at 0x7f9f77408630)
1 param, 40 slots, 13 upvalues, 30 locals, 56 constants, 0 functions
	1	[289]	GETUPVAL 	1 0	; Geom
	2	[289]	SELF     	1 1 -2	; "new"
	3	[289]	NEWTABLE 	3 0 2
	4	[289]	GETTABLE 	4 0 -4	; "width"
	5	[289]	SETTABLE 	3 -3 4	; "w" -
	6	[289]	GETTABLE 	4 0 -6	; "height"
	7	[289]	SETTABLE 	3 -5 4	; "h" -
	8	[289]	CALL     	1 3 2
	9	[289]	SETTABLE 	0 -1 1	; "dimen" -
	10	[290]	GETUPVAL 	1 1	; HorizontalGroup
	11	[290]	SELF     	1 1 -2	; "new"
	12	[290]	NEWTABLE 	3 0 1
	13	[291]	GETTABLE 	4 0 -1	; "dimen"
	14	[291]	SELF     	4 4 -8	; "copy"
	15	[291]	CALL     	4 2 2
	16	[291]	SETTABLE 	3 -1 4	; "dimen" -
	17	[290]	CALL     	1 3 2
	18	[292]	SETTABLE 	0 -7 1	; "day_container" -
	19	[293]	GETGLOBAL	1 -9	; ipairs
	20	[293]	GETTABLE 	2 0 -10	; "calday_widgets"
	21	[293]	CALL     	1 2 4
	22	[293]	JMP      	19	; to 42
	23	[294]	GETGLOBAL	6 -11	; table
	24	[294]	GETTABLE 	6 6 -12	; "insert"
	25	[294]	GETTABLE 	7 0 -7	; "day_container"
	26	[294]	MOVE     	8 5
	27	[294]	CALL     	6 3 1
	28	[295]	GETTABLE 	6 0 -10	; "calday_widgets"
	29	[295]	LEN      	6 6
	30	[295]	LT       	0 4 6
	31	[295]	JMP      	10	; to 42
	32	[296]	GETGLOBAL	6 -11	; table
	33	[296]	GETTABLE 	6 6 -12	; "insert"
	34	[296]	GETTABLE 	7 0 -7	; "day_container"
	35	[296]	GETUPVAL 	8 2	; HorizontalSpan
	36	[296]	SELF     	8 8 -2	; "new"
	37	[296]	NEWTABLE 	10 0 1
	38	[296]	GETTABLE 	11 0 -13	; "day_padding"
	39	[296]	SETTABLE 	10 -4 11	; "width" -
	40	[296]	CALL     	8 3 0
	41	[296]	CALL     	6 0 1
	42	[293]	TFORLOOP 	1 2
	43	[297]	JMP      	-21	; to 23
	44	[300]	GETUPVAL 	1 3	; OverlapGroup
	45	[300]	SELF     	1 1 -2	; "new"
	46	[300]	NEWTABLE 	3 1 0
	47	[302]	GETTABLE 	4 0 -7	; "day_container"
	48	[302]	SETLIST  	3 1 1	; 1
	49	[300]	CALL     	1 3 2
	50	[304]	GETUPVAL 	2 4	; Size
	51	[304]	GETTABLE 	2 2 -14	; "margin"
	52	[304]	GETTABLE 	2 2 -15	; "tiny"
	53	[304]	GETTABLE 	3 0 -16	; "day_border"
	54	[304]	ADD      	2 2 3
	55	[305]	GETUPVAL 	3 4	; Size
	56	[305]	GETTABLE 	3 3 -14	; "margin"
	57	[305]	GETTABLE 	3 3 -15	; "tiny"
	58	[306]	GETUPVAL 	4 4	; Size
	59	[306]	GETTABLE 	4 4 -17	; "padding"
	60	[306]	GETTABLE 	4 4 -15	; "tiny"
	61	[307]	GETUPVAL 	5 4	; Size
	62	[307]	GETTABLE 	5 5 -18	; "border"
	63	[307]	GETTABLE 	5 5 -19	; "thin"
	64	[310]	GETTABLE 	6 0 -20	; "span_height"
	65	[310]	ADD      	7 3 5
	66	[310]	MUL      	7 -21 7	; 2 -
	67	[310]	SUB      	6 6 7
	68	[317]	GETUPVAL 	7 5	; TextBoxWidget
	69	[317]	SELF     	7 7 -22	; "getFontSizeToFitHeight"
	70	[317]	MOVE     	9 6
	71	[317]	LOADK    	10 -23	; 1
	72	[317]	LOADK    	11 -24	; 0.3
	73	[317]	CALL     	7 5 2
	74	[322]	LE       	0 7 -25	; - 12
	75	[322]	JMP      	8	; to 84
	76	[323]	GETUPVAL 	8 5	; TextBoxWidget
	77	[323]	SELF     	8 8 -22	; "getFontSizeToFitHeight"
	78	[323]	MOVE     	10 6
	79	[323]	LOADK    	11 -23	; 1
	80	[323]	LOADK    	12 -26	; 0.1
	81	[323]	CALL     	8 5 2
	82	[323]	MOVE     	7 8
	83	[323]	JMP      	9	; to 93
	84	[324]	LE       	0 7 -27	; - 15
	85	[324]	JMP      	7	; to 93
	86	[325]	GETUPVAL 	8 5	; TextBoxWidget
	87	[325]	SELF     	8 8 -22	; "getFontSizeToFitHeight"
	88	[325]	MOVE     	10 6
	89	[325]	LOADK    	11 -23	; 1
	90	[325]	LOADK    	12 -28	; 0.2
	91	[325]	CALL     	8 5 2
	92	[325]	MOVE     	7 8
	93	[328]	GETGLOBAL	8 -29	; math
	94	[328]	GETTABLE 	8 8 -30	; "min"
	95	[328]	MOVE     	9 7
	96	[328]	GETTABLE 	10 0 -31	; "font_size"
	97	[328]	CALL     	8 3 2
	98	[328]	MOVE     	7 8
	99	[330]	LOADNIL  	8 8
	100	[331]	GETTABLE 	9 0 -32	; "histo_shown"
	101	[331]	TEST     	9 0 0
	102	[331]	JMP      	4	; to 107
	103	[336]	GETUPVAL 	9 4	; Size
	104	[336]	GETTABLE 	9 9 -14	; "margin"
	105	[336]	GETTABLE 	8 9 -33	; "small"
	106	[336]	JMP      	7	; to 114
	107	[340]	GETTABLE 	9 0 -6	; "height"
	108	[340]	GETTABLE 	10 0 -20	; "span_height"
	109	[340]	GETTABLE 	11 0 -34	; "nb_book_spans"
	110	[340]	ADD      	11 11 -23	; - 1
	111	[340]	MUL      	10 10 11
	112	[340]	SUB      	9 9 10
	113	[340]	SUB      	8 9 3
	114	[343]	GETGLOBAL	9 -9	; ipairs
	115	[343]	GETTABLE 	10 0 -35	; "days_books"
	116	[343]	CALL     	9 2 4
	117	[343]	JMP      	117	; to 235
	118	[344]	GETGLOBAL	14 -9	; ipairs
	119	[344]	MOVE     	15 13
	120	[344]	CALL     	14 2 4
	121	[344]	JMP      	111	; to 233
	122	[345]	TEST     	18 0 0
	123	[345]	JMP      	109	; to 233
	124	[345]	GETTABLE 	19 18 -36	; "start_day"
	125	[345]	EQ       	0 19 12
	126	[345]	JMP      	106	; to 233
	127	[346]	GETGLOBAL	19 -37	; unpack
	128	[346]	GETUPVAL 	20 6	; SPAN_COLORS
	129	[346]	GETTABLE 	21 18 -38	; "id"
	130	[346]	GETUPVAL 	22 6	; SPAN_COLORS
	131	[346]	LEN      	22 22
	132	[346]	MOD      	21 21 22
	133	[346]	ADD      	21 21 -23	; - 1
	134	[346]	GETTABLE 	20 20 21
	135	[346]	CALL     	19 2 3
	136	[347]	SUB      	21 12 -23	; - 1
	137	[347]	GETTABLE 	22 0 -39	; "day_width"
	138	[347]	GETTABLE 	23 0 -13	; "day_padding"
	139	[347]	ADD      	22 22 23
	140	[347]	MUL      	21 21 22
	141	[348]	GETTABLE 	22 0 -20	; "span_height"
	142	[348]	MUL      	22 17 22
	143	[349]	ADD      	22 22 8
	144	[350]	GETTABLE 	23 18 -40	; "span_days"
	145	[350]	GETTABLE 	24 0 -39	; "day_width"
	146	[350]	MUL      	23 23 24
	147	[350]	GETTABLE 	24 0 -13	; "day_padding"
	148	[350]	GETTABLE 	25 18 -40	; "span_days"
	149	[350]	SUB      	25 25 -23	; - 1
	150	[350]	MUL      	24 24 25
	151	[350]	ADD      	23 23 24
	152	[353]	GETUPVAL 	24 7	; FrameContainer
	153	[353]	SELF     	24 24 -2	; "new"
	154	[353]	NEWTABLE 	26 0 9
	155	[354]	SETTABLE 	26 -4 23	; "width" -
	156	[355]	GETTABLE 	27 0 -20	; "span_height"
	157	[355]	SETTABLE 	26 -6 27	; "height" -
	158	[356]	SETTABLE 	26 -14 -41	; "margin" 0
	159	[357]	SETTABLE 	26 -42 -41	; "bordersize" 0
	160	[358]	SETTABLE 	26 -43 3	; "padding_top" -
	161	[359]	SETTABLE 	26 -44 3	; "padding_bottom" -
	162	[360]	SETTABLE 	26 -45 2	; "padding_left" -
	163	[361]	SETTABLE 	26 -46 2	; "padding_right" -
	164	[362]	NEWTABLE 	27 2 0
	165	[362]	MOVE     	28 21
	166	[362]	MOVE     	29 22
	167	[362]	SETLIST  	27 2 1	; 1
	168	[362]	SETTABLE 	26 -47 27	; "overlap_offset" -
	169	[363]	GETUPVAL 	27 7	; FrameContainer
	170	[363]	SELF     	27 27 -2	; "new"
	171	[363]	NEWTABLE 	29 0 6
	172	[364]	MUL      	30 -21 2	; 2 -
	173	[364]	SUB      	30 23 30
	174	[364]	SETTABLE 	29 -4 30	; "width" -
	175	[365]	GETTABLE 	30 0 -20	; "span_height"
	176	[365]	MUL      	31 -21 3	; 2 -
	177	[365]	SUB      	30 30 31
	178	[365]	SETTABLE 	29 -6 30	; "height" -
	179	[366]	SETTABLE 	29 -14 -41	; "margin" 0
	180	[367]	SETTABLE 	29 -17 -41	; "padding" 0
	181	[368]	SETTABLE 	29 -42 5	; "bordersize" -
	182	[369]	SETTABLE 	29 -48 20	; "background" -
	183	[370]	GETUPVAL 	30 8	; CenterContainer
	184	[370]	SELF     	30 30 -2	; "new"
	185	[370]	NEWTABLE 	32 0 1
	186	[371]	GETUPVAL 	33 0	; Geom
	187	[371]	SELF     	33 33 -2	; "new"
	188	[371]	NEWTABLE 	35 0 2
	189	[372]	ADD      	36 2 5
	190	[372]	MUL      	36 -21 36	; 2 -
	191	[372]	SUB      	36 23 36
	192	[372]	SETTABLE 	35 -3 36	; "w" -
	193	[373]	GETTABLE 	36 0 -20	; "span_height"
	194	[373]	ADD      	37 3 5
	195	[373]	MUL      	37 -21 37	; 2 -
	196	[373]	SUB      	36 36 37
	197	[373]	SETTABLE 	35 -5 36	; "h" -
	198	[371]	CALL     	33 3 2
	199	[374]	SETTABLE 	32 -1 33	; "dimen" -
	200	[375]	GETUPVAL 	33 9	; TextWidget
	201	[375]	SELF     	33 33 -2	; "new"
	202	[375]	NEWTABLE 	35 0 5
	203	[376]	GETUPVAL 	36 10	; BD
	204	[376]	GETTABLE 	36 36 -50	; "auto"
	205	[376]	GETTABLE 	37 18 -51	; "title"
	206	[376]	CALL     	36 2 2
	207	[376]	SETTABLE 	35 -49 36	; "text" -
	208	[377]	ADD      	36 2 5
	209	[377]	ADD      	36 36 4
	210	[377]	MUL      	36 -21 36	; 2 -
	211	[377]	SUB      	36 23 36
	212	[377]	SETTABLE 	35 -52 36	; "max_width" -
	213	[378]	GETUPVAL 	36 11	; Font
	214	[378]	SELF     	36 36 -54	; "getFace"
	215	[378]	GETTABLE 	38 0 -55	; "font_face"
	216	[378]	MOVE     	39 7
	217	[378]	CALL     	36 4 2
	218	[378]	SETTABLE 	35 -53 36	; "face" -
	219	[379]	SETTABLE 	35 -17 -41	; "padding" 0
	220	[380]	SETTABLE 	35 -56 19	; "fgcolor" -
	221	[375]	CALL     	33 3 0
	222	[382]	SETLIST  	32 0 1	; 1
	223	[370]	CALL     	30 3 0
	224	[383]	SETLIST  	29 0 1	; 1
	225	[363]	CALL     	27 3 0
	226	[384]	SETLIST  	26 0 1	; 1
	227	[353]	CALL     	24 3 2
	228	[385]	GETGLOBAL	25 -11	; table
	229	[385]	GETTABLE 	25 25 -12	; "insert"
	230	[385]	MOVE     	26 1
	231	[385]	MOVE     	27 24
	232	[385]	CALL     	25 3 1
	233	[344]	TFORLOOP 	14 2
	234	[386]	JMP      	-113	; to 122
	235	[343]	TFORLOOP 	9 2
	236	[387]	JMP      	-119	; to 118
	237	[390]	GETUPVAL 	9 12	; LeftContainer
	238	[390]	SELF     	9 9 -2	; "new"
	239	[390]	NEWTABLE 	11 1 1
	240	[391]	GETTABLE 	12 0 -1	; "dimen"
	241	[391]	SELF     	12 12 -8	; "copy"
	242	[391]	CALL     	12 2 2
	243	[391]	SETTABLE 	11 -1 12	; "dimen" -
	244	[393]	MOVE     	12 1
	245	[393]	SETLIST  	11 1 1	; 1
	246	[390]	CALL     	9 3 2
	247	[393]	SETTABLE 	0 -23 9	; 1 -
	248	[394]	RETURN   	0 1

function <./plugins/statistics.koplugin/calendarview.lua:418,631> (514 instructions, 2056 bytes at 0x7f9f7740b6a0)
1 param, 25 slots, 23 upvalues, 18 locals, 120 constants, 6 functions
	1	[419]	GETUPVAL 	1 0	; Geom
	2	[419]	SELF     	1 1 -2	; "new"
	3	[419]	NEWTABLE 	3 0 2
	4	[420]	GETTABLE 	4 0 -4	; "width"
	5	[420]	TEST     	4 0 1
	6	[420]	JMP      	3	; to 10
	7	[420]	GETUPVAL 	4 1	; Screen
	8	[420]	SELF     	4 4 -5	; "getWidth"
	9	[420]	CALL     	4 2 2
	10	[420]	SETTABLE 	3 -3 4	; "w" -
	11	[421]	GETTABLE 	4 0 -7	; "height"
	12	[421]	TEST     	4 0 1
	13	[421]	JMP      	3	; to 17
	14	[421]	GETUPVAL 	4 1	; Screen
	15	[421]	SELF     	4 4 -8	; "getHeight"
	16	[421]	CALL     	4 2 2
	17	[421]	SETTABLE 	3 -6 4	; "h" -
	18	[419]	CALL     	1 3 2
	19	[422]	SETTABLE 	0 -1 1	; "dimen" -
	20	[423]	GETTABLE 	1 0 -1	; "dimen"
	21	[423]	GETTABLE 	1 1 -3	; "w"
	22	[423]	GETUPVAL 	2 1	; Screen
	23	[423]	SELF     	2 2 -5	; "getWidth"
	24	[423]	CALL     	2 2 2
	25	[423]	EQ       	0 1 2
	26	[423]	JMP      	8	; to 35
	27	[423]	GETTABLE 	1 0 -1	; "dimen"
	28	[423]	GETTABLE 	1 1 -6	; "h"
	29	[423]	GETUPVAL 	2 1	; Screen
	30	[423]	SELF     	2 2 -8	; "getHeight"
	31	[423]	CALL     	2 2 2
	32	[423]	EQ       	0 1 2
	33	[423]	JMP      	1	; to 35
	34	[424]	SETTABLE 	0 -9 -10	; "covers_fullscreen" true
	35	[427]	GETUPVAL 	1 2	; Device
	36	[427]	SELF     	1 1 -11	; "hasKeys"
	37	[427]	CALL     	1 2 2
	38	[427]	TEST     	1 0 0
	39	[427]	JMP      	27	; to 67
	40	[428]	NEWTABLE 	1 0 3
	41	[429]	NEWTABLE 	2 1 1
	42	[429]	NEWTABLE 	3 1 0
	43	[429]	LOADK    	4 -14	; "Back"
	44	[429]	SETLIST  	3 1 1	; 1
	45	[429]	SETTABLE 	2 -15 -16	; "doc" "close page"
	46	[429]	SETLIST  	2 1 1	; 1
	47	[429]	SETTABLE 	1 -13 2	; "Close" -
	48	[430]	NEWTABLE 	2 1 1
	49	[430]	NEWTABLE 	3 1 0
	50	[430]	GETUPVAL 	4 3	; Input
	51	[430]	GETTABLE 	4 4 -18	; "group"
	52	[430]	GETTABLE 	4 4 -19	; "PgFwd"
	53	[430]	SETLIST  	3 1 1	; 1
	54	[430]	SETTABLE 	2 -15 -20	; "doc" "next page"
	55	[430]	SETLIST  	2 1 1	; 1
	56	[430]	SETTABLE 	1 -17 2	; "NextMonth" -
	57	[431]	NEWTABLE 	2 1 1
	58	[431]	NEWTABLE 	3 1 0
	59	[431]	GETUPVAL 	4 3	; Input
	60	[431]	GETTABLE 	4 4 -18	; "group"
	61	[431]	GETTABLE 	4 4 -22	; "PgBack"
	62	[431]	SETLIST  	3 1 1	; 1
	63	[431]	SETTABLE 	2 -15 -23	; "doc" "prev page"
	64	[431]	SETLIST  	2 1 1	; 1
	65	[431]	SETTABLE 	1 -21 2	; "PrevMonth" -
	66	[432]	SETTABLE 	0 -12 1	; "key_events" -
	67	[434]	GETUPVAL 	1 2	; Device
	68	[434]	SELF     	1 1 -24	; "isTouchDevice"
	69	[434]	CALL     	1 2 2
	70	[434]	TEST     	1 0 0
	71	[434]	JMP      	11	; to 83
	72	[435]	GETTABLE 	1 0 -25	; "ges_events"
	73	[435]	NEWTABLE 	2 0 0
	74	[436]	GETUPVAL 	3 4	; GestureRange
	75	[436]	SELF     	3 3 -2	; "new"
	76	[436]	NEWTABLE 	5 0 2
	77	[437]	SETTABLE 	5 -27 -28	; "ges" "swipe"
	78	[438]	GETTABLE 	6 0 -1	; "dimen"
	79	[438]	SETTABLE 	5 -29 6	; "range" -
	80	[436]	CALL     	3 3 0
	81	[440]	SETLIST  	2 0 1	; 1
	82	[440]	SETTABLE 	1 -26 2	; "Swipe" -
	83	[443]	GETUPVAL 	1 5	; Size
	84	[443]	GETTABLE 	1 1 -30	; "padding"
	85	[443]	GETTABLE 	1 1 -31	; "large"
	86	[444]	GETUPVAL 	2 5	; Size
	87	[444]	GETTABLE 	2 2 -30	; "padding"
	88	[444]	GETTABLE 	2 2 -33	; "small"
	89	[444]	SETTABLE 	0 -32 2	; "inner_padding" -
	90	[447]	GETGLOBAL	2 -35	; math
	91	[447]	GETTABLE 	2 2 -36	; "floor"
	92	[447]	GETTABLE 	3 0 -1	; "dimen"
	93	[447]	GETTABLE 	3 3 -3	; "w"
	94	[447]	MUL      	4 -37 1	; 2 -
	95	[447]	SUB      	3 3 4
	96	[447]	GETTABLE 	4 0 -32	; "inner_padding"
	97	[447]	MUL      	4 -38 4	; 6 -
	98	[447]	SUB      	3 3 4
	99	[447]	DIV      	3 3 -39	; - 7
	100	[447]	CALL     	2 2 2
	101	[447]	SETTABLE 	0 -34 2	; "day_width" -
	102	[449]	GETGLOBAL	2 -35	; math
	103	[449]	GETTABLE 	2 2 -36	; "floor"
	104	[449]	GETTABLE 	3 0 -1	; "dimen"
	105	[449]	GETTABLE 	3 3 -3	; "w"
	106	[449]	GETTABLE 	4 0 -34	; "day_width"
	107	[449]	MUL      	4 -39 4	; 7 -
	108	[449]	SUB      	3 3 4
	109	[449]	GETTABLE 	4 0 -32	; "inner_padding"
	110	[449]	MUL      	4 -38 4	; 6 -
	111	[449]	SUB      	3 3 4
	112	[449]	DIV      	3 3 -37	; - 2
	113	[449]	CALL     	2 2 2
	114	[449]	MOVE     	1 2
	115	[450]	GETTABLE 	2 0 -1	; "dimen"
	116	[450]	GETTABLE 	2 2 -3	; "w"
	117	[450]	MUL      	3 -37 1	; 2 -
	118	[450]	SUB      	2 2 3
	119	[450]	SETTABLE 	0 -40 2	; "content_width" -
	120	[452]	GETUPVAL 	2 6	; MIN_MONTH
	121	[452]	TEST     	2 0 1
	122	[452]	JMP      	15	; to 138
	123	[453]	GETTABLE 	2 0 -41	; "reader_statistics"
	124	[453]	SELF     	2 2 -42	; "getFirstTimestamp"
	125	[453]	CALL     	2 2 2
	126	[454]	TEST     	2 0 1
	127	[454]	JMP      	4	; to 132
	128	[454]	GETGLOBAL	3 -43	; os
	129	[454]	GETTABLE 	3 3 -44	; "time"
	130	[454]	CALL     	3 1 2
	131	[454]	MOVE     	2 3
	132	[455]	GETGLOBAL	3 -43	; os
	133	[455]	GETTABLE 	3 3 -45	; "date"
	134	[455]	LOADK    	4 -46	; "%Y-%m"
	135	[455]	MOVE     	5 2
	136	[455]	CALL     	3 3 2
	137	[455]	SETUPVAL 	3 6	; MIN_MONTH
	138	[457]	GETUPVAL 	2 6	; MIN_MONTH
	139	[457]	SETTABLE 	0 -47 2	; "min_month" -
	140	[458]	GETGLOBAL	2 -43	; os
	141	[458]	GETTABLE 	2 2 -45	; "date"
	142	[458]	LOADK    	3 -46	; "%Y-%m"
	143	[458]	GETGLOBAL	4 -43	; os
	144	[458]	GETTABLE 	4 4 -44	; "time"
	145	[458]	CALL     	4 1 0
	146	[458]	CALL     	2 0 2
	147	[458]	SETTABLE 	0 -48 2	; "max_month" -
	148	[459]	GETTABLE 	2 0 -49	; "cur_month"
	149	[459]	TEST     	2 0 1
	150	[459]	JMP      	2	; to 153
	151	[460]	GETTABLE 	2 0 -48	; "max_month"
	152	[460]	SETTABLE 	0 -49 2	; "cur_month" -
	153	[464]	LOADK    	2 -50	; "resources/icons/appbar.chevron.left.png"
	154	[465]	LOADK    	3 -51	; "resources/icons/appbar.chevron.right.png"
	155	[466]	LOADK    	4 -52	; "resources/icons/appbar.chevron.first.png"
	156	[467]	LOADK    	5 -53	; "resources/icons/appbar.chevron.last.png"
	157	[468]	GETUPVAL 	6 7	; BD
	158	[468]	GETTABLE 	6 6 -54	; "mirroredUILayout"
	159	[468]	CALL     	6 1 2
	160	[468]	TEST     	6 0 0
	161	[468]	JMP      	6	; to 168
	162	[469]	MOVE     	6 3
	163	[469]	MOVE     	3 2
	164	[469]	MOVE     	2 6
	165	[470]	MOVE     	6 5
	166	[470]	MOVE     	5 4
	167	[470]	MOVE     	4 6
	168	[472]	GETUPVAL 	6 8	; Button
	169	[472]	SELF     	6 6 -2	; "new"
	170	[472]	NEWTABLE 	8 0 4
	171	[473]	SETTABLE 	8 -56 2	; "icon" -
	172	[474]	CLOSURE  	9 0	; 0x7f9f7740bf30
	173	[474]	MOVE     	0 0
	174	[474]	SETTABLE 	8 -57 9	; "callback" -
	175	[475]	SETTABLE 	8 -58 -59	; "bordersize" 0
	176	[476]	SETTABLE 	8 -60 0	; "show_parent" -
	177	[472]	CALL     	6 3 2
	178	[477]	SETTABLE 	0 -55 6	; "page_info_left_chev" -
	179	[478]	GETUPVAL 	6 8	; Button
	180	[478]	SELF     	6 6 -2	; "new"
	181	[478]	NEWTABLE 	8 0 4
	182	[479]	SETTABLE 	8 -56 3	; "icon" -
	183	[480]	CLOSURE  	9 1	; 0x7f9f7740c190
	184	[480]	MOVE     	0 0
	185	[480]	SETTABLE 	8 -57 9	; "callback" -
	186	[481]	SETTABLE 	8 -58 -59	; "bordersize" 0
	187	[482]	SETTABLE 	8 -60 0	; "show_parent" -
	188	[478]	CALL     	6 3 2
	189	[483]	SETTABLE 	0 -61 6	; "page_info_right_chev" -
	190	[484]	GETUPVAL 	6 8	; Button
	191	[484]	SELF     	6 6 -2	; "new"
	192	[484]	NEWTABLE 	8 0 4
	193	[485]	SETTABLE 	8 -56 4	; "icon" -
	194	[486]	CLOSURE  	9 2	; 0x7f9f7740c3b0
	195	[486]	MOVE     	0 0
	196	[486]	SETTABLE 	8 -57 9	; "callback" -
	197	[487]	SETTABLE 	8 -58 -59	; "bordersize" 0
	198	[488]	SETTABLE 	8 -60 0	; "show_parent" -
	199	[484]	CALL     	6 3 2
	200	[489]	SETTABLE 	0 -62 6	; "page_info_first_chev" -
	201	[490]	GETUPVAL 	6 8	; Button
	202	[490]	SELF     	6 6 -2	; "new"
	203	[490]	NEWTABLE 	8 0 4
	204	[491]	SETTABLE 	8 -56 5	; "icon" -
	205	[492]	CLOSURE  	9 3	; 0x7f9f7740c5a0
	206	[492]	MOVE     	0 0
	207	[492]	SETTABLE 	8 -57 9	; "callback" -
	208	[493]	SETTABLE 	8 -58 -59	; "bordersize" 0
	209	[494]	SETTABLE 	8 -60 0	; "show_parent" -
	210	[490]	CALL     	6 3 2
	211	[495]	SETTABLE 	0 -63 6	; "page_info_last_chev" -
	212	[496]	GETUPVAL 	6 9	; HorizontalSpan
	213	[496]	SELF     	6 6 -2	; "new"
	214	[496]	NEWTABLE 	8 0 1
	215	[497]	GETUPVAL 	9 1	; Screen
	216	[497]	SELF     	9 9 -65	; "scaleBySize"
	217	[497]	LOADK    	11 -66	; 32
	218	[497]	CALL     	9 3 2
	219	[497]	SETTABLE 	8 -4 9	; "width" -
	220	[496]	CALL     	6 3 2
	221	[498]	SETTABLE 	0 -64 6	; "page_info_spacer" -
	222	[500]	GETUPVAL 	6 8	; Button
	223	[500]	SELF     	6 6 -2	; "new"
	224	[500]	NEWTABLE 	8 0 6
	225	[501]	SETTABLE 	8 -68 -69	; "text" ""
	226	[502]	NEWTABLE 	9 0 3
	227	[503]	GETUPVAL 	10 10	; _
	228	[503]	LOADK    	11 -72	; "Enter month"
	229	[503]	CALL     	10 2 2
	230	[503]	SETTABLE 	9 -71 10	; "title" -
	231	[504]	CLOSURE  	10 4	; 0x7f9f7740c8b0
	232	[504]	MOVE     	0 0
	233	[504]	SETTABLE 	9 -73 10	; "input_func" -
	234	[520]	CLOSURE  	10 5	; 0x7f9f7740c970
	235	[520]	MOVE     	0 0
	236	[520]	GETUPVAL 	0 11	; UIManager
	237	[520]	GETUPVAL 	0 10	; _
	238	[520]	SETTABLE 	9 -57 10	; "callback" -
	239	[521]	SETTABLE 	8 -70 9	; "hold_input" -
	240	[522]	SETTABLE 	8 -58 -59	; "bordersize" 0
	241	[523]	GETUPVAL 	9 1	; Screen
	242	[523]	SELF     	9 9 -65	; "scaleBySize"
	243	[523]	LOADK    	11 -75	; 20
	244	[523]	CALL     	9 3 2
	245	[523]	SETTABLE 	8 -74 9	; "margin" -
	246	[524]	SETTABLE 	8 -76 -77	; "text_font_face" "pgfont"
	247	[525]	SETTABLE 	8 -78 -79	; "text_font_bold" false
	248	[500]	CALL     	6 3 2
	249	[526]	SETTABLE 	0 -67 6	; "page_info_text" -
	250	[527]	GETUPVAL 	6 12	; HorizontalGroup
	251	[527]	SELF     	6 6 -2	; "new"
	252	[527]	NEWTABLE 	8 7 0
	253	[528]	GETTABLE 	9 0 -62	; "page_info_first_chev"
	254	[529]	GETTABLE 	10 0 -64	; "page_info_spacer"
	255	[530]	GETTABLE 	11 0 -55	; "page_info_left_chev"
	256	[531]	GETTABLE 	12 0 -67	; "page_info_text"
	257	[532]	GETTABLE 	13 0 -61	; "page_info_right_chev"
	258	[533]	GETTABLE 	14 0 -64	; "page_info_spacer"
	259	[535]	GETTABLE 	15 0 -63	; "page_info_last_chev"
	260	[535]	SETLIST  	8 7 1	; 1
	261	[527]	CALL     	6 3 2
	262	[535]	SETTABLE 	0 -80 6	; "page_info" -
	263	[537]	GETUPVAL 	6 13	; BottomContainer
	264	[537]	SELF     	6 6 -2	; "new"
	265	[537]	NEWTABLE 	8 1 1
	266	[538]	GETUPVAL 	9 0	; Geom
	267	[538]	SELF     	9 9 -2	; "new"
	268	[538]	NEWTABLE 	11 0 2
	269	[539]	GETTABLE 	12 0 -40	; "content_width"
	270	[539]	SETTABLE 	11 -3 12	; "w" -
	271	[540]	GETTABLE 	12 0 -1	; "dimen"
	272	[540]	GETTABLE 	12 12 -6	; "h"
	273	[540]	SETTABLE 	11 -6 12	; "h" -
	274	[538]	CALL     	9 3 2
	275	[541]	SETTABLE 	8 -1 9	; "dimen" -
	276	[543]	GETTABLE 	9 0 -80	; "page_info"
	277	[543]	SETLIST  	8 1 1	; 1
	278	[537]	CALL     	6 3 2
	279	[545]	GETUPVAL 	7 14	; CalendarTitle
	280	[545]	SELF     	7 7 -2	; "new"
	281	[545]	NEWTABLE 	9 0 4
	282	[546]	GETTABLE 	10 0 -71	; "title"
	283	[546]	SETTABLE 	9 -71 10	; "title" -
	284	[547]	GETTABLE 	10 0 -40	; "content_width"
	285	[547]	SETTABLE 	9 -4 10	; "width" -
	286	[548]	GETUPVAL 	10 5	; Size
	287	[548]	GETTABLE 	10 10 -82	; "item"
	288	[548]	GETTABLE 	10 10 -83	; "height_default"
	289	[548]	SETTABLE 	9 -7 10	; "height" -
	290	[549]	SETTABLE 	9 -84 0	; "calendar_view" -
	291	[545]	CALL     	7 3 2
	292	[550]	SETTABLE 	0 -81 7	; "title_bar" -
	293	[553]	GETUPVAL 	7 12	; HorizontalGroup
	294	[553]	SELF     	7 7 -2	; "new"
	295	[553]	NEWTABLE 	9 0 0
	296	[553]	CALL     	7 3 2
	297	[553]	SETTABLE 	0 -85 7	; "day_names" -
	298	[554]	LOADK    	7 -59	; 0
	299	[554]	LOADK    	8 -38	; 6
	300	[554]	LOADK    	9 -86	; 1
	301	[554]	FORPREP  	7 60	; to 362
	302	[555]	GETUPVAL 	11 15	; TextWidget
	303	[555]	SELF     	11 11 -2	; "new"
	304	[555]	NEWTABLE 	13 0 3
	305	[556]	GETTABLE 	14 0 -87	; "shortDayOfWeekTranslation"
	306	[556]	GETTABLE 	15 0 -88	; "weekdays"
	307	[556]	GETTABLE 	16 0 -89	; "start_day_of_week"
	308	[556]	SUB      	16 16 -86	; - 1
	309	[556]	ADD      	16 16 10
	310	[556]	MOD      	16 16 -39
	311	[556]	ADD      	16 16 -86	; - 1
	312	[556]	GETTABLE 	15 15 16
	313	[556]	GETTABLE 	14 14 15
	314	[556]	SETTABLE 	13 -68 14	; "text" -
	315	[557]	GETUPVAL 	14 16	; Font
	316	[557]	SELF     	14 14 -91	; "getFace"
	317	[557]	LOADK    	16 -92	; "xx_smallinfofont"
	318	[557]	CALL     	14 3 2
	319	[557]	SETTABLE 	13 -90 14	; "face" -
	320	[558]	SETTABLE 	13 -93 -10	; "bold" true
	321	[555]	CALL     	11 3 2
	322	[560]	GETGLOBAL	12 -94	; table
	323	[560]	GETTABLE 	12 12 -95	; "insert"
	324	[560]	GETTABLE 	13 0 -85	; "day_names"
	325	[560]	GETUPVAL 	14 17	; FrameContainer
	326	[560]	SELF     	14 14 -2	; "new"
	327	[560]	NEWTABLE 	16 0 2
	328	[561]	SETTABLE 	16 -30 -59	; "padding" 0
	329	[562]	SETTABLE 	16 -58 -59	; "bordersize" 0
	330	[563]	GETUPVAL 	17 18	; CenterContainer
	331	[563]	SELF     	17 17 -2	; "new"
	332	[563]	NEWTABLE 	19 1 1
	333	[564]	GETUPVAL 	20 0	; Geom
	334	[564]	SELF     	20 20 -2	; "new"
	335	[564]	NEWTABLE 	22 0 2
	336	[564]	GETTABLE 	23 0 -34	; "day_width"
	337	[564]	SETTABLE 	22 -3 23	; "w" -
	338	[564]	SELF     	23 11 -96	; "getSize"
	339	[564]	CALL     	23 2 2
	340	[564]	GETTABLE 	23 23 -6	; "h"
	341	[564]	SETTABLE 	22 -6 23	; "h" -
	342	[564]	CALL     	20 3 2
	343	[564]	SETTABLE 	19 -1 20	; "dimen" -
	344	[566]	MOVE     	20 11
	345	[566]	SETLIST  	19 1 1	; 1
	346	[563]	CALL     	17 3 0
	347	[567]	SETLIST  	16 0 1	; 1
	348	[560]	CALL     	14 3 0
	349	[560]	CALL     	12 0 1
	350	[568]	LT       	0 10 -38	; - 6
	351	[568]	JMP      	10	; to 362
	352	[569]	GETGLOBAL	12 -94	; table
	353	[569]	GETTABLE 	12 12 -95	; "insert"
	354	[569]	GETTABLE 	13 0 -85	; "day_names"
	355	[569]	GETUPVAL 	14 9	; HorizontalSpan
	356	[569]	SELF     	14 14 -2	; "new"
	357	[569]	NEWTABLE 	16 0 1
	358	[569]	GETTABLE 	17 0 -32	; "inner_padding"
	359	[569]	SETTABLE 	16 -4 17	; "width" -
	360	[569]	CALL     	14 3 0
	361	[569]	CALL     	12 0 1
	362	[554]	FORLOOP  	7 -61	; to 302
	363	[574]	GETTABLE 	7 0 -1	; "dimen"
	364	[574]	GETTABLE 	7 7 -6	; "h"
	365	[574]	GETTABLE 	8 0 -81	; "title_bar"
	366	[574]	SELF     	8 8 -96	; "getSize"
	367	[574]	CALL     	8 2 2
	368	[574]	GETTABLE 	8 8 -6	; "h"
	369	[574]	SUB      	7 7 8
	370	[575]	GETTABLE 	8 0 -80	; "page_info"
	371	[575]	SELF     	8 8 -96	; "getSize"
	372	[575]	CALL     	8 2 2
	373	[575]	GETTABLE 	8 8 -6	; "h"
	374	[575]	SUB      	7 7 8
	375	[575]	GETTABLE 	8 0 -85	; "day_names"
	376	[575]	SELF     	8 8 -96	; "getSize"
	377	[575]	CALL     	8 2 2
	378	[575]	GETTABLE 	8 8 -6	; "h"
	379	[575]	SUB      	7 7 8
	380	[576]	GETGLOBAL	8 -35	; math
	381	[576]	GETTABLE 	8 8 -36	; "floor"
	382	[576]	GETTABLE 	9 0 -32	; "inner_padding"
	383	[576]	MUL      	9 -98 9	; 5 -
	384	[576]	SUB      	9 7 9
	385	[576]	DIV      	9 9 -38	; - 6
	386	[576]	CALL     	8 2 2
	387	[576]	SETTABLE 	0 -97 8	; "week_height" -
	388	[577]	GETUPVAL 	8 5	; Size
	389	[577]	GETTABLE 	8 8 -100	; "border"
	390	[577]	GETTABLE 	8 8 -101	; "default"
	391	[577]	SETTABLE 	0 -99 8	; "day_border" -
	392	[578]	GETTABLE 	8 0 -102	; "show_hourly_histogram"
	393	[578]	TEST     	8 0 0
	394	[578]	JMP      	12	; to 407
	395	[581]	GETGLOBAL	8 -35	; math
	396	[581]	GETTABLE 	8 8 -104	; "ceil"
	397	[581]	GETTABLE 	9 0 -97	; "week_height"
	398	[581]	GETTABLE 	10 0 -99	; "day_border"
	399	[581]	MUL      	10 -37 10	; 2 -
	400	[581]	SUB      	9 9 10
	401	[581]	GETTABLE 	10 0 -105	; "nb_book_spans"
	402	[581]	ADD      	10 10 -37	; - 2
	403	[581]	DIV      	9 9 10
	404	[581]	CALL     	8 2 2
	405	[581]	SETTABLE 	0 -103 8	; "span_height" -
	406	[581]	JMP      	11	; to 418
	407	[584]	GETGLOBAL	8 -35	; math
	408	[584]	GETTABLE 	8 8 -36	; "floor"
	409	[584]	GETTABLE 	9 0 -97	; "week_height"
	410	[584]	GETTABLE 	10 0 -99	; "day_border"
	411	[584]	MUL      	10 -37 10	; 2 -
	412	[584]	SUB      	9 9 10
	413	[584]	GETTABLE 	10 0 -105	; "nb_book_spans"
	414	[584]	ADD      	10 10 -86	; - 1
	415	[584]	DIV      	9 9 10
	416	[584]	CALL     	8 2 2
	417	[584]	SETTABLE 	0 -103 8	; "span_height" -
	418	[588]	GETGLOBAL	8 -35	; math
	419	[588]	GETTABLE 	8 8 -106	; "min"
	420	[588]	GETTABLE 	9 0 -103	; "span_height"
	421	[588]	GETTABLE 	10 0 -97	; "week_height"
	422	[588]	DIV      	10 10 -107	; - 3
	423	[588]	CALL     	8 3 2
	424	[589]	GETUPVAL 	9 19	; TextBoxWidget
	425	[589]	SELF     	9 9 -109	; "getFontSizeToFitHeight"
	426	[589]	MOVE     	11 8
	427	[589]	LOADK    	12 -86	; 1
	428	[589]	LOADK    	13 -110	; 0.3
	429	[589]	CALL     	9 5 2
	430	[589]	SETTABLE 	0 -108 9	; "span_font_size" -
	431	[590]	GETTABLE 	9 0 -34	; "day_width"
	432	[590]	GETTABLE 	10 0 -99	; "day_border"
	433	[590]	MUL      	10 -37 10	; 2 -
	434	[590]	SUB      	9 9 10
	435	[590]	GETTABLE 	10 0 -32	; "inner_padding"
	436	[590]	MUL      	10 -37 10	; 2 -
	437	[590]	SUB      	9 9 10
	438	[592]	GETUPVAL 	10 15	; TextWidget
	439	[592]	SELF     	10 10 -2	; "new"
	440	[592]	NEWTABLE 	12 0 3
	441	[593]	SETTABLE 	12 -68 -111	; "text" " 30 + 99 "
	442	[594]	GETUPVAL 	13 16	; Font
	443	[594]	SELF     	13 13 -91	; "getFace"
	444	[594]	GETTABLE 	15 0 -112	; "font_face"
	445	[594]	GETTABLE 	16 0 -108	; "span_font_size"
	446	[594]	CALL     	13 4 2
	447	[594]	SETTABLE 	12 -90 13	; "face" -
	448	[595]	SETTABLE 	12 -93 -10	; "bold" true
	449	[592]	CALL     	10 3 2
	450	[597]	SELF     	11 10 -5	; "getWidth"
	451	[597]	CALL     	11 2 2
	452	[597]	LE       	0 11 9
	453	[597]	JMP      	3	; to 457
	454	[598]	SELF     	11 10 -113	; "free"
	455	[598]	CALL     	11 2 1
	456	[599]	JMP      	6	; to 463
	457	[601]	GETTABLE 	11 0 -108	; "span_font_size"
	458	[601]	SUB      	11 11 -86	; - 1
	459	[601]	SETTABLE 	0 -108 11	; "span_font_size" -
	460	[602]	SELF     	11 10 -113	; "free"
	461	[602]	CALL     	11 2 1
	462	[602]	JMP      	-25	; to 438
	463	[605]	GETUPVAL 	10 20	; VerticalGroup
	464	[605]	SELF     	10 10 -2	; "new"
	465	[605]	NEWTABLE 	12 0 0
	466	[605]	CALL     	10 3 2
	467	[605]	SETTABLE 	0 -114 10	; "main_content" -
	468	[606]	SELF     	10 0 -115	; "_populateItems"
	469	[606]	CALL     	10 2 1
	470	[608]	GETUPVAL 	10 21	; OverlapGroup
	471	[608]	SELF     	10 10 -2	; "new"
	472	[608]	NEWTABLE 	12 2 2
	473	[609]	GETUPVAL 	13 0	; Geom
	474	[609]	SELF     	13 13 -2	; "new"
	475	[609]	NEWTABLE 	15 0 2
	476	[610]	GETTABLE 	16 0 -40	; "content_width"
	477	[610]	SETTABLE 	15 -3 16	; "w" -
	478	[611]	GETTABLE 	16 0 -1	; "dimen"
	479	[611]	GETTABLE 	16 16 -6	; "h"
	480	[611]	SETTABLE 	15 -6 16	; "h" -
	481	[609]	CALL     	13 3 2
	482	[612]	SETTABLE 	12 -1 13	; "dimen" -
	483	[613]	SETTABLE 	12 -116 -79	; "allow_mirroring" false
	484	[614]	GETUPVAL 	13 20	; VerticalGroup
	485	[614]	SELF     	13 13 -2	; "new"
	486	[614]	NEWTABLE 	15 3 1
	487	[615]	SETTABLE 	15 -117 -118	; "align" "left"
	488	[616]	GETTABLE 	16 0 -81	; "title_bar"
	489	[617]	GETTABLE 	17 0 -85	; "day_names"
	490	[619]	GETTABLE 	18 0 -114	; "main_content"
	491	[619]	SETLIST  	15 3 1	; 1
	492	[614]	CALL     	13 3 2
	493	[621]	MOVE     	14 6
	494	[621]	SETLIST  	12 2 1	; 1
	495	[608]	CALL     	10 3 2
	496	[623]	GETUPVAL 	11 17	; FrameContainer
	497	[623]	SELF     	11 11 -2	; "new"
	498	[623]	NEWTABLE 	13 1 5
	499	[624]	GETTABLE 	14 0 -1	; "dimen"
	500	[624]	GETTABLE 	14 14 -3	; "w"
	501	[624]	SETTABLE 	13 -4 14	; "width" -
	502	[625]	GETTABLE 	14 0 -1	; "dimen"
	503	[625]	GETTABLE 	14 14 -6	; "h"
	504	[625]	SETTABLE 	13 -7 14	; "height" -
	505	[626]	SETTABLE 	13 -30 1	; "padding" -
	506	[627]	SETTABLE 	13 -58 -59	; "bordersize" 0
	507	[628]	GETUPVAL 	14 22	; Blitbuffer
	508	[628]	GETTABLE 	14 14 -120	; "COLOR_WHITE"
	509	[628]	SETTABLE 	13 -119 14	; "background" -
	510	[630]	MOVE     	14 10
	511	[630]	SETLIST  	13 1 1	; 1
	512	[623]	CALL     	11 3 2
	513	[630]	SETTABLE 	0 -86 11	; 1 -
	514	[631]	RETURN   	0 1

function <./plugins/statistics.koplugin/calendarview.lua:474,474> (4 instructions, 16 bytes at 0x7f9f7740bf30)
0 params, 2 slots, 1 upvalue, 0 locals, 1 constant, 0 functions
	1	[474]	GETUPVAL 	0 0	; self
	2	[474]	SELF     	0 0 -1	; "prevMonth"
	3	[474]	CALL     	0 2 1
	4	[474]	RETURN   	0 1

function <./plugins/statistics.koplugin/calendarview.lua:480,480> (4 instructions, 16 bytes at 0x7f9f7740c190)
0 params, 2 slots, 1 upvalue, 0 locals, 1 constant, 0 functions
	1	[480]	GETUPVAL 	0 0	; self
	2	[480]	SELF     	0 0 -1	; "nextMonth"
	3	[480]	CALL     	0 2 1
	4	[480]	RETURN   	0 1

function <./plugins/statistics.koplugin/calendarview.lua:486,486> (6 instructions, 24 bytes at 0x7f9f7740c3b0)
0 params, 3 slots, 1 upvalue, 0 locals, 2 constants, 0 functions
	1	[486]	GETUPVAL 	0 0	; self
	2	[486]	SELF     	0 0 -1	; "goToMonth"
	3	[486]	GETUPVAL 	2 0	; self
	4	[486]	GETTABLE 	2 2 -2	; "min_month"
	5	[486]	CALL     	0 3 1
	6	[486]	RETURN   	0 1

function <./plugins/statistics.koplugin/calendarview.lua:492,492> (6 instructions, 24 bytes at 0x7f9f7740c5a0)
0 params, 3 slots, 1 upvalue, 0 locals, 2 constants, 0 functions
	1	[492]	GETUPVAL 	0 0	; self
	2	[492]	SELF     	0 0 -1	; "goToMonth"
	3	[492]	GETUPVAL 	2 0	; self
	4	[492]	GETTABLE 	2 2 -2	; "max_month"
	5	[492]	CALL     	0 3 1
	6	[492]	RETURN   	0 1

function <./plugins/statistics.koplugin/calendarview.lua:504,504> (4 instructions, 16 bytes at 0x7f9f7740c8b0)
0 params, 2 slots, 1 upvalue, 0 locals, 1 constant, 0 functions
	1	[504]	GETUPVAL 	0 0	; self
	2	[504]	GETTABLE 	0 0 -1	; "cur_month"
	3	[504]	RETURN   	0 2
	4	[504]	RETURN   	0 1

function <./plugins/statistics.koplugin/calendarview.lua:505,520> (41 instructions, 164 bytes at 0x7f9f7740c970)
1 param, 11 slots, 3 upvalues, 4 locals, 13 constants, 0 functions
	1	[506]	SELF     	1 0 -1	; "match"
	2	[506]	LOADK    	3 -2	; "^(%d%d%d%d)-(%d%d)$"
	3	[506]	CALL     	1 3 3
	4	[507]	TEST     	1 0 0
	5	[507]	JMP      	22	; to 28
	6	[507]	TEST     	2 0 0
	7	[507]	JMP      	20	; to 28
	8	[508]	GETGLOBAL	3 -3	; tonumber
	9	[508]	MOVE     	4 2
	10	[508]	CALL     	3 2 2
	11	[508]	LE       	0 -4 3	; 1 -
	12	[508]	JMP      	15	; to 28
	13	[508]	GETGLOBAL	3 -3	; tonumber
	14	[508]	MOVE     	4 2
	15	[508]	CALL     	3 2 2
	16	[508]	LE       	0 3 -5	; - 12
	17	[508]	JMP      	10	; to 28
	18	[508]	GETGLOBAL	3 -3	; tonumber
	19	[508]	MOVE     	4 1
	20	[508]	CALL     	3 2 2
	21	[508]	LE       	0 -6 3	; 1000 -
	22	[508]	JMP      	5	; to 28
	23	[512]	GETUPVAL 	3 0	; self
	24	[512]	SELF     	3 3 -7	; "goToMonth"
	25	[512]	MOVE     	5 0
	26	[512]	CALL     	3 3 1
	27	[513]	RETURN   	0 1
	28	[516]	GETGLOBAL	3 -8	; require
	29	[516]	LOADK    	4 -9	; "ui/widget/infomessage"
	30	[516]	CALL     	3 2 2
	31	[517]	GETUPVAL 	4 1	; UIManager
	32	[517]	SELF     	4 4 -10	; "show"
	33	[517]	SELF     	6 3 -11	; "new"
	34	[517]	NEWTABLE 	8 0 1
	35	[518]	GETUPVAL 	9 2	; _
	36	[518]	LOADK    	10 -13	; "Invalid year-month string (YYYY-MM)"
	37	[518]	CALL     	9 2 2
	38	[518]	SETTABLE 	8 -12 9	; "text" -
	39	[517]	CALL     	6 3 0
	40	[517]	CALL     	4 0 1
	41	[520]	RETURN   	0 1

function <./plugins/statistics.koplugin/calendarview.lua:633,748> (297 instructions, 1188 bytes at 0x7f9f7740be90)
1 param, 20 slots, 5 upvalues, 20 locals, 80 constants, 2 functions
	1	[634]	GETTABLE 	1 0 -1	; "page_info"
	2	[634]	SELF     	1 1 -2	; "resetLayout"
	3	[634]	CALL     	1 2 1
	4	[635]	GETTABLE 	1 0 -3	; "main_content"
	5	[635]	SELF     	1 1 -4	; "clear"
	6	[635]	CALL     	1 2 1
	7	[638]	GETGLOBAL	1 -5	; os
	8	[638]	GETTABLE 	1 1 -6	; "time"
	9	[638]	NEWTABLE 	2 0 3
	10	[639]	GETTABLE 	3 0 -8	; "cur_month"
	11	[639]	SELF     	3 3 -9	; "sub"
	12	[639]	LOADK    	5 -10	; 1
	13	[639]	LOADK    	6 -11	; 4
	14	[639]	CALL     	3 4 2
	15	[639]	SETTABLE 	2 -7 3	; "year" -
	16	[640]	GETTABLE 	3 0 -8	; "cur_month"
	17	[640]	SELF     	3 3 -9	; "sub"
	18	[640]	LOADK    	5 -13	; 6
	19	[640]	CALL     	3 3 2
	20	[640]	SETTABLE 	2 -12 3	; "month" -
	21	[641]	SETTABLE 	2 -14 -10	; "day" 1
	22	[638]	CALL     	1 2 2
	23	[645]	GETTABLE 	2 0 -15	; "monthTranslation"
	24	[645]	GETGLOBAL	3 -5	; os
	25	[645]	GETTABLE 	3 3 -16	; "date"
	26	[645]	LOADK    	4 -17	; "%B"
	27	[645]	MOVE     	5 1
	28	[645]	CALL     	3 3 2
	29	[645]	GETTABLE 	2 2 3
	30	[645]	GETGLOBAL	3 -5	; os
	31	[645]	GETTABLE 	3 3 -16	; "date"
	32	[645]	LOADK    	4 -18	; " %Y"
	33	[645]	MOVE     	5 1
	34	[645]	CALL     	3 3 2
	35	[645]	CONCAT   	2 2 3
	36	[646]	GETTABLE 	3 0 -19	; "title_bar"
	37	[646]	SELF     	3 3 -20	; "setTitle"
	38	[646]	MOVE     	5 2
	39	[646]	CALL     	3 3 1
	40	[648]	GETTABLE 	3 0 -21	; "page_info_text"
	41	[648]	SELF     	3 3 -22	; "setText"
	42	[648]	GETTABLE 	5 0 -8	; "cur_month"
	43	[648]	CALL     	3 3 1
	44	[649]	GETTABLE 	3 0 -23	; "page_info_left_chev"
	45	[649]	SELF     	3 3 -24	; "enableDisable"
	46	[649]	GETTABLE 	5 0 -8	; "cur_month"
	47	[649]	GETTABLE 	6 0 -25	; "min_month"
	48	[649]	LT       	1 6 5
	49	[649]	JMP      	1	; to 51
	50	[649]	LOADBOOL 	5 0 1
	51	[649]	LOADBOOL 	5 1 0
	52	[649]	CALL     	3 3 1
	53	[650]	GETTABLE 	3 0 -26	; "page_info_right_chev"
	54	[650]	SELF     	3 3 -24	; "enableDisable"
	55	[650]	GETTABLE 	5 0 -8	; "cur_month"
	56	[650]	GETTABLE 	6 0 -27	; "max_month"
	57	[650]	LT       	1 5 6
	58	[650]	JMP      	3	; to 62
	59	[650]	GETTABLE 	5 0 -28	; "browse_future_months"
	60	[650]	JMP      	2	; to 63
	61	[650]	LOADBOOL 	5 0 1
	62	[650]	LOADBOOL 	5 1 0
	63	[650]	CALL     	3 3 1
	64	[651]	GETTABLE 	3 0 -29	; "page_info_first_chev"
	65	[651]	SELF     	3 3 -24	; "enableDisable"
	66	[651]	GETTABLE 	5 0 -8	; "cur_month"
	67	[651]	GETTABLE 	6 0 -25	; "min_month"
	68	[651]	LT       	1 6 5
	69	[651]	JMP      	1	; to 71
	70	[651]	LOADBOOL 	5 0 1
	71	[651]	LOADBOOL 	5 1 0
	72	[651]	CALL     	3 3 1
	73	[652]	GETTABLE 	3 0 -30	; "page_info_last_chev"
	74	[652]	SELF     	3 3 -24	; "enableDisable"
	75	[652]	GETTABLE 	5 0 -8	; "cur_month"
	76	[652]	GETTABLE 	6 0 -27	; "max_month"
	77	[652]	LT       	1 5 6
	78	[652]	JMP      	3	; to 82
	79	[652]	GETTABLE 	5 0 -28	; "browse_future_months"
	80	[652]	JMP      	2	; to 83
	81	[652]	LOADBOOL 	5 0 1
	82	[652]	LOADBOOL 	5 1 0
	83	[652]	CALL     	3 3 1
	84	[654]	GETTABLE 	3 0 -31	; "reader_statistics"
	85	[654]	SELF     	3 3 -32	; "getReadingRatioPerHourByDay"
	86	[654]	GETTABLE 	5 0 -8	; "cur_month"
	87	[654]	CALL     	3 3 2
	88	[655]	GETTABLE 	4 0 -31	; "reader_statistics"
	89	[655]	SELF     	4 4 -33	; "getReadBookByDay"
	90	[655]	GETTABLE 	6 0 -8	; "cur_month"
	91	[655]	CALL     	4 3 2
	92	[657]	GETGLOBAL	5 -34	; table
	93	[657]	GETTABLE 	5 5 -35	; "insert"
	94	[657]	GETTABLE 	6 0 -3	; "main_content"
	95	[657]	GETUPVAL 	7 0	; VerticalSpan
	96	[657]	SELF     	7 7 -36	; "new"
	97	[657]	NEWTABLE 	9 0 1
	98	[657]	GETTABLE 	10 0 -38	; "inner_padding"
	99	[657]	SETTABLE 	9 -37 10	; "width" -
	100	[657]	CALL     	7 3 0
	101	[657]	CALL     	5 0 1
	102	[658]	NEWTABLE 	5 0 0
	103	[658]	SETTABLE 	0 -39 5	; "weeks" -
	104	[659]	GETGLOBAL	5 -5	; os
	105	[659]	GETTABLE 	5 5 -16	; "date"
	106	[659]	LOADK    	6 -40	; "%Y-%m-%d"
	107	[659]	GETGLOBAL	7 -5	; os
	108	[659]	GETTABLE 	7 7 -6	; "time"
	109	[659]	CALL     	7 1 0
	110	[659]	CALL     	5 0 2
	111	[660]	MOVE     	6 1
	112	[661]	GETGLOBAL	7 -5	; os
	113	[661]	GETTABLE 	7 7 -16	; "date"
	114	[661]	LOADK    	8 -41	; "*t"
	115	[661]	MOVE     	9 6
	116	[661]	CALL     	7 3 2
	117	[662]	GETTABLE 	8 7 -12	; "month"
	118	[663]	LOADNIL  	9 9
	119	[665]	GETGLOBAL	10 -5	; os
	120	[665]	GETTABLE 	10 10 -16	; "date"
	121	[665]	LOADK    	11 -41	; "*t"
	122	[665]	MOVE     	12 6
	123	[665]	CALL     	10 3 2
	124	[665]	MOVE     	7 10
	125	[666]	GETTABLE 	10 7 -12	; "month"
	126	[666]	EQ       	1 10 8
	127	[666]	JMP      	1	; to 129
	128	[667]	JMP      	154	; to 283
	129	[669]	TEST     	9 0 0
	130	[669]	JMP      	4	; to 135
	131	[669]	GETTABLE 	10 7 -42	; "wday"
	132	[669]	GETTABLE 	11 0 -43	; "start_day_of_week"
	133	[669]	EQ       	0 10 11
	134	[669]	JMP      	75	; to 210
	135	[670]	TEST     	9 0 0
	136	[670]	JMP      	10	; to 147
	137	[671]	GETGLOBAL	10 -34	; table
	138	[671]	GETTABLE 	10 10 -35	; "insert"
	139	[671]	GETTABLE 	11 0 -3	; "main_content"
	140	[671]	GETUPVAL 	12 0	; VerticalSpan
	141	[671]	SELF     	12 12 -36	; "new"
	142	[671]	NEWTABLE 	14 0 1
	143	[671]	GETTABLE 	15 0 -38	; "inner_padding"
	144	[671]	SETTABLE 	14 -37 15	; "width" -
	145	[671]	CALL     	12 3 0
	146	[671]	CALL     	10 0 1
	147	[673]	GETUPVAL 	10 1	; CalendarWeek
	148	[673]	SELF     	10 10 -36	; "new"
	149	[673]	NEWTABLE 	12 0 11
	150	[674]	GETTABLE 	13 0 -45	; "week_height"
	151	[674]	SETTABLE 	12 -44 13	; "height" -
	152	[675]	GETTABLE 	13 0 -46	; "content_width"
	153	[675]	SETTABLE 	12 -37 13	; "width" -
	154	[676]	GETTABLE 	13 0 -47	; "day_width"
	155	[676]	SETTABLE 	12 -47 13	; "day_width" -
	156	[677]	GETTABLE 	13 0 -38	; "inner_padding"
	157	[677]	SETTABLE 	12 -48 13	; "day_padding" -
	158	[678]	GETTABLE 	13 0 -49	; "day_border"
	159	[678]	SETTABLE 	12 -49 13	; "day_border" -
	160	[679]	GETTABLE 	13 0 -50	; "nb_book_spans"
	161	[679]	SETTABLE 	12 -50 13	; "nb_book_spans" -
	162	[680]	GETTABLE 	13 0 -52	; "show_hourly_histogram"
	163	[680]	SETTABLE 	12 -51 13	; "histo_shown" -
	164	[681]	GETTABLE 	13 0 -53	; "span_height"
	165	[681]	SETTABLE 	12 -53 13	; "span_height" -
	166	[682]	GETTABLE 	13 0 -54	; "font_face"
	167	[682]	SETTABLE 	12 -54 13	; "font_face" -
	168	[683]	GETTABLE 	13 0 -56	; "span_font_size"
	169	[683]	SETTABLE 	12 -55 13	; "font_size" -
	170	[684]	SETTABLE 	12 -57 0	; "show_parent" -
	171	[673]	CALL     	10 3 2
	172	[685]	MOVE     	9 10
	173	[686]	GETGLOBAL	10 -34	; table
	174	[686]	GETTABLE 	10 10 -35	; "insert"
	175	[686]	GETTABLE 	11 0 -39	; "weeks"
	176	[686]	MOVE     	12 9
	177	[686]	CALL     	10 3 1
	178	[687]	GETGLOBAL	10 -34	; table
	179	[687]	GETTABLE 	10 10 -35	; "insert"
	180	[687]	GETTABLE 	11 0 -3	; "main_content"
	181	[687]	MOVE     	12 9
	182	[687]	CALL     	10 3 1
	183	[688]	GETTABLE 	10 7 -42	; "wday"
	184	[688]	GETTABLE 	11 0 -43	; "start_day_of_week"
	185	[688]	EQ       	1 10 11
	186	[688]	JMP      	23	; to 210
	187	[690]	GETTABLE 	10 0 -43	; "start_day_of_week"
	188	[691]	GETTABLE 	11 7 -42	; "wday"
	189	[691]	EQ       	1 10 11
	190	[691]	JMP      	19	; to 210
	191	[692]	SELF     	11 9 -58	; "addDay"
	192	[692]	GETUPVAL 	13 2	; CalendarDay
	193	[692]	SELF     	13 13 -36	; "new"
	194	[692]	NEWTABLE 	15 0 5
	195	[693]	SETTABLE 	15 -59 -60	; "filler" true
	196	[694]	GETTABLE 	16 0 -45	; "week_height"
	197	[694]	SETTABLE 	15 -44 16	; "height" -
	198	[695]	GETTABLE 	16 0 -47	; "day_width"
	199	[695]	SETTABLE 	15 -37 16	; "width" -
	200	[696]	GETTABLE 	16 0 -49	; "day_border"
	201	[696]	SETTABLE 	15 -61 16	; "border" -
	202	[697]	SETTABLE 	15 -57 0	; "show_parent" -
	203	[692]	CALL     	13 3 0
	204	[692]	CALL     	11 0 1
	205	[699]	ADD      	10 10 -10	; - 1
	206	[700]	EQ       	0 10 -62	; - 8
	207	[700]	JMP      	-20	; to 188
	208	[701]	LOADK    	10 -10	; 1
	209	[702]	JMP      	-22	; to 188
	210	[706]	GETGLOBAL	10 -5	; os
	211	[706]	GETTABLE 	10 10 -16	; "date"
	212	[706]	LOADK    	11 -40	; "%Y-%m-%d"
	213	[706]	MOVE     	12 6
	214	[706]	CALL     	10 3 2
	215	[707]	GETGLOBAL	11 -63	; string
	216	[707]	GETTABLE 	11 11 -64	; "format"
	217	[707]	LOADK    	12 -65	; "%s (%s)"
	218	[707]	MOVE     	13 10
	219	[708]	GETTABLE 	14 0 -66	; "longDayOfWeekTranslation"
	220	[708]	GETTABLE 	15 0 -67	; "weekdays"
	221	[708]	GETTABLE 	16 7 -42	; "wday"
	222	[708]	GETTABLE 	15 15 16
	223	[708]	GETTABLE 	14 14 15
	224	[707]	CALL     	11 4 2
	225	[709]	GETGLOBAL	12 -5	; os
	226	[709]	GETTABLE 	12 12 -6	; "time"
	227	[709]	NEWTABLE 	13 0 4
	228	[710]	GETTABLE 	14 7 -7	; "year"
	229	[710]	SETTABLE 	13 -7 14	; "year" -
	230	[711]	GETTABLE 	14 7 -12	; "month"
	231	[711]	SETTABLE 	13 -12 14	; "month" -
	232	[712]	GETTABLE 	14 7 -14	; "day"
	233	[712]	SETTABLE 	13 -14 14	; "day" -
	234	[713]	SETTABLE 	13 -68 -69	; "hour" 0
	235	[709]	CALL     	12 2 2
	236	[715]	LT       	1 5 10
	237	[715]	JMP      	1	; to 239
	238	[715]	LOADBOOL 	13 0 1
	239	[715]	LOADBOOL 	13 1 0
	240	[716]	SELF     	14 9 -58	; "addDay"
	241	[716]	GETUPVAL 	16 2	; CalendarDay
	242	[716]	SELF     	16 16 -36	; "new"
	243	[716]	NEWTABLE 	18 0 13
	244	[717]	GETTABLE 	19 0 -52	; "show_hourly_histogram"
	245	[717]	SETTABLE 	18 -70 19	; "show_histo" -
	246	[718]	GETTABLE 	19 0 -53	; "span_height"
	247	[718]	SETTABLE 	18 -71 19	; "histo_height" -
	248	[719]	GETTABLE 	19 0 -54	; "font_face"
	249	[719]	SETTABLE 	18 -54 19	; "font_face" -
	250	[720]	GETTABLE 	19 0 -56	; "span_font_size"
	251	[720]	SETTABLE 	18 -55 19	; "font_size" -
	252	[721]	GETTABLE 	19 0 -49	; "day_border"
	253	[721]	SETTABLE 	18 -61 19	; "border" -
	254	[722]	SETTABLE 	18 -72 13	; "is_future" -
	255	[723]	GETTABLE 	19 7 -14	; "day"
	256	[723]	SETTABLE 	18 -73 19	; "daynum" -
	257	[724]	GETTABLE 	19 0 -45	; "week_height"
	258	[724]	SETTABLE 	18 -44 19	; "height" -
	259	[725]	GETTABLE 	19 0 -47	; "day_width"
	260	[725]	SETTABLE 	18 -37 19	; "width" -
	261	[726]	GETTABLE 	19 3 10
	262	[726]	SETTABLE 	18 -74 19	; "ratio_per_hour" -
	263	[727]	GETTABLE 	19 4 10
	264	[727]	SETTABLE 	18 -75 19	; "read_books" -
	265	[728]	SETTABLE 	18 -57 0	; "show_parent" -
	266	[729]	TEST     	13 0 1
	267	[729]	JMP      	7	; to 275
	268	[737]	CLOSURE  	19 0	; 0x7f9f7740c710
	269	[737]	GETUPVAL 	0 3	; UIManager
	270	[737]	GETUPVAL 	0 4	; KeyValuePage
	271	[737]	MOVE     	0 11
	272	[737]	MOVE     	0 0
	273	[737]	MOVE     	0 12
	274	[737]	JMP      	2	; to 277
	275	[737]	LOADBOOL 	19 0 1
	276	[737]	LOADBOOL 	19 1 0
	277	[737]	SETTABLE 	18 -76 19	; "callback" -
	278	[716]	CALL     	16 3 0
	279	[716]	CALL     	14 0 1
	280	[739]	ADD      	6 6 -77	; - 86400
	281	[739]	CLOSE    	10
	282	[739]	JMP      	-164	; to 119
	283	[741]	GETGLOBAL	10 -78	; ipairs
	284	[741]	GETTABLE 	11 0 -39	; "weeks"
	285	[741]	CALL     	10 2 4
	286	[741]	JMP      	2	; to 289
	287	[742]	SELF     	15 14 -79	; "update"
	288	[742]	CALL     	15 2 1
	289	[741]	TFORLOOP 	10 2
	290	[742]	JMP      	-4	; to 287
	291	[745]	GETUPVAL 	10 3	; UIManager
	292	[745]	SELF     	10 10 -80	; "setDirty"
	293	[745]	MOVE     	12 0
	294	[747]	CLOSURE  	13 1	; 0x7f9f7740d8b0
	295	[747]	MOVE     	0 0
	296	[745]	CALL     	10 4 1
	297	[748]	RETURN   	0 1

function <./plugins/statistics.koplugin/calendarview.lua:729,737> (21 instructions, 84 bytes at 0x7f9f7740c710)
0 params, 9 slots, 5 upvalues, 0 locals, 10 constants, 1 function
	1	[731]	GETUPVAL 	0 0	; UIManager
	2	[731]	SELF     	0 0 -1	; "show"
	3	[731]	GETUPVAL 	2 1	; KeyValuePage
	4	[731]	SELF     	2 2 -2	; "new"
	5	[731]	NEWTABLE 	4 0 4
	6	[732]	GETUPVAL 	5 2	; day_text
	7	[732]	SETTABLE 	4 -3 5	; "title" -
	8	[733]	SETTABLE 	4 -4 -5	; "value_align" "right"
	9	[734]	GETUPVAL 	5 3	; self
	10	[734]	GETTABLE 	5 5 -7	; "reader_statistics"
	11	[734]	SELF     	5 5 -8	; "getBooksFromPeriod"
	12	[734]	GETUPVAL 	7 4	; day_ts
	13	[734]	GETUPVAL 	8 4	; day_ts
	14	[734]	ADD      	8 8 -9	; - 86400
	15	[734]	CALL     	5 4 2
	16	[734]	SETTABLE 	4 -6 5	; "kv_pairs" -
	17	[735]	CLOSURE  	5 0	; 0x7f9f7740dab0
	18	[735]	SETTABLE 	4 -10 5	; "callback_return" -
	19	[731]	CALL     	2 3 0
	20	[731]	CALL     	0 0 1
	21	[737]	RETURN   	0 1

function <./plugins/statistics.koplugin/calendarview.lua:735,735> (1 instruction, 4 bytes at 0x7f9f7740dab0)
0 params, 2 slots, 0 upvalues, 0 locals, 0 constants, 0 functions
	1	[735]	RETURN   	0 1

function <./plugins/statistics.koplugin/calendarview.lua:745,747> (5 instructions, 20 bytes at 0x7f9f7740d8b0)
0 params, 2 slots, 1 upvalue, 0 locals, 2 constants, 0 functions
	1	[746]	LOADK    	0 -1	; "ui"
	2	[746]	GETUPVAL 	1 0	; self
	3	[746]	GETTABLE 	1 1 -2	; "dimen"
	4	[746]	RETURN   	0 3
	5	[747]	RETURN   	0 1

function <./plugins/statistics.koplugin/calendarview.lua:750,762> (32 instructions, 128 bytes at 0x7f9f7740dc70)
1 param, 7 slots, 0 upvalues, 3 locals, 17 constants, 0 functions
	1	[751]	GETGLOBAL	1 -1	; os
	2	[751]	GETTABLE 	1 1 -2	; "time"
	3	[751]	NEWTABLE 	2 0 3
	4	[752]	GETTABLE 	3 0 -4	; "cur_month"
	5	[752]	SELF     	3 3 -5	; "sub"
	6	[752]	LOADK    	5 -6	; 1
	7	[752]	LOADK    	6 -7	; 4
	8	[752]	CALL     	3 4 2
	9	[752]	SETTABLE 	2 -3 3	; "year" -
	10	[753]	GETTABLE 	3 0 -4	; "cur_month"
	11	[753]	SELF     	3 3 -5	; "sub"
	12	[753]	LOADK    	5 -9	; 6
	13	[753]	CALL     	3 3 2
	14	[753]	SETTABLE 	2 -8 3	; "month" -
	15	[754]	SETTABLE 	2 -10 -11	; "day" 15
	16	[751]	CALL     	1 2 2
	17	[756]	ADD      	1 1 -12	; - 2592000
	18	[757]	GETGLOBAL	2 -1	; os
	19	[757]	GETTABLE 	2 2 -13	; "date"
	20	[757]	LOADK    	3 -14	; "%Y-%m"
	21	[757]	MOVE     	4 1
	22	[757]	CALL     	2 3 2
	23	[758]	GETTABLE 	3 0 -15	; "browse_future_months"
	24	[758]	TEST     	3 0 1
	25	[758]	JMP      	3	; to 29
	26	[758]	GETTABLE 	3 0 -16	; "max_month"
	27	[758]	LE       	0 2 3
	28	[758]	JMP      	3	; to 32
	29	[759]	SETTABLE 	0 -4 2	; "cur_month" -
	30	[760]	SELF     	3 0 -17	; "_populateItems"
	31	[760]	CALL     	3 2 1
	32	[762]	RETURN   	0 1

function <./plugins/statistics.koplugin/calendarview.lua:764,776> (29 instructions, 116 bytes at 0x7f9f7740e490)
1 param, 7 slots, 0 upvalues, 3 locals, 16 constants, 0 functions
	1	[765]	GETGLOBAL	1 -1	; os
	2	[765]	GETTABLE 	1 1 -2	; "time"
	3	[765]	NEWTABLE 	2 0 3
	4	[766]	GETTABLE 	3 0 -4	; "cur_month"
	5	[766]	SELF     	3 3 -5	; "sub"
	6	[766]	LOADK    	5 -6	; 1
	7	[766]	LOADK    	6 -7	; 4
	8	[766]	CALL     	3 4 2
	9	[766]	SETTABLE 	2 -3 3	; "year" -
	10	[767]	GETTABLE 	3 0 -4	; "cur_month"
	11	[767]	SELF     	3 3 -5	; "sub"
	12	[767]	LOADK    	5 -9	; 6
	13	[767]	CALL     	3 3 2
	14	[767]	SETTABLE 	2 -8 3	; "month" -
	15	[768]	SETTABLE 	2 -10 -11	; "day" 15
	16	[765]	CALL     	1 2 2
	17	[770]	SUB      	1 1 -12	; - 2592000
	18	[771]	GETGLOBAL	2 -1	; os
	19	[771]	GETTABLE 	2 2 -13	; "date"
	20	[771]	LOADK    	3 -14	; "%Y-%m"
	21	[771]	MOVE     	4 1
	22	[771]	CALL     	2 3 2
	23	[772]	GETTABLE 	3 0 -15	; "min_month"
	24	[772]	LE       	0 3 2
	25	[772]	JMP      	3	; to 29
	26	[773]	SETTABLE 	0 -4 2	; "cur_month" -
	27	[774]	SELF     	3 0 -16	; "_populateItems"
	28	[774]	CALL     	3 2 1
	29	[776]	RETURN   	0 1

function <./plugins/statistics.koplugin/calendarview.lua:778,781> (4 instructions, 16 bytes at 0x7f9f7740e610)
2 params, 4 slots, 0 upvalues, 2 locals, 2 constants, 0 functions
	1	[779]	SETTABLE 	0 -1 1	; "cur_month" -
	2	[780]	SELF     	2 0 -2	; "_populateItems"
	3	[780]	CALL     	2 2 1
	4	[781]	RETURN   	0 1

function <./plugins/statistics.koplugin/calendarview.lua:783,786> (5 instructions, 20 bytes at 0x7f9f7740a4b0)
1 param, 3 slots, 0 upvalues, 1 local, 1 constant, 0 functions
	1	[784]	SELF     	1 0 -1	; "nextMonth"
	2	[784]	CALL     	1 2 1
	3	[785]	LOADBOOL 	1 1 0
	4	[785]	RETURN   	1 2
	5	[786]	RETURN   	0 1

function <./plugins/statistics.koplugin/calendarview.lua:788,791> (5 instructions, 20 bytes at 0x7f9f7740e9c0)
1 param, 3 slots, 0 upvalues, 1 local, 1 constant, 0 functions
	1	[789]	SELF     	1 0 -1	; "prevMonth"
	2	[789]	CALL     	1 2 1
	3	[790]	LOADBOOL 	1 1 0
	4	[790]	RETURN   	1 2
	5	[791]	RETURN   	0 1

function <./plugins/statistics.koplugin/calendarview.lua:793,814> (34 instructions, 136 bytes at 0x7f9f7740ec20)
3 params, 8 slots, 2 upvalues, 4 locals, 11 constants, 0 functions
	1	[794]	GETUPVAL 	3 0	; BD
	2	[794]	GETTABLE 	3 3 -1	; "flipDirectionIfMirroredUILayout"
	3	[794]	GETTABLE 	4 2 -2	; "direction"
	4	[794]	CALL     	3 2 2
	5	[795]	EQ       	0 3 -3	; - "west"
	6	[795]	JMP      	5	; to 12
	7	[796]	SELF     	4 0 -4	; "nextMonth"
	8	[796]	CALL     	4 2 1
	9	[797]	LOADBOOL 	4 1 0
	10	[797]	RETURN   	4 2
	11	[797]	JMP      	22	; to 34
	12	[798]	EQ       	0 3 -5	; - "east"
	13	[798]	JMP      	5	; to 19
	14	[799]	SELF     	4 0 -6	; "prevMonth"
	15	[799]	CALL     	4 2 1
	16	[800]	LOADBOOL 	4 1 0
	17	[800]	RETURN   	4 2
	18	[800]	JMP      	15	; to 34
	19	[801]	EQ       	0 3 -7	; - "south"
	20	[801]	JMP      	3	; to 24
	21	[803]	SELF     	4 0 -8	; "onClose"
	22	[803]	CALL     	4 2 1
	23	[803]	JMP      	10	; to 34
	24	[804]	EQ       	0 3 -9	; - "north"
	25	[804]	JMP      	1	; to 27
	26	[806]	JMP      	7	; to 34
	27	[809]	GETUPVAL 	4 1	; UIManager
	28	[809]	SELF     	4 4 -10	; "setDirty"
	29	[809]	LOADNIL  	6 6
	30	[809]	LOADK    	7 -11	; "full"
	31	[809]	CALL     	4 4 1
	32	[812]	LOADBOOL 	4 0 0
	33	[812]	RETURN   	4 2
	34	[814]	RETURN   	0 1

function <./plugins/statistics.koplugin/calendarview.lua:816,819> (7 instructions, 28 bytes at 0x7f9f7740f040)
1 param, 4 slots, 1 upvalue, 1 local, 1 constant, 0 functions
	1	[817]	GETUPVAL 	1 0	; UIManager
	2	[817]	SELF     	1 1 -1	; "close"
	3	[817]	MOVE     	3 0
	4	[817]	CALL     	1 3 1
	5	[818]	LOADBOOL 	1 1 0
	6	[818]	RETURN   	1 2
	7	[819]	RETURN   	0 1
