
main <./frontend/document/canvascontext.lua:0,0> (24 instructions, 96 bytes at 0x7fa5d8c068d0)
0+ params, 3 slots, 0 upvalues, 2 locals, 13 constants, 7 functions
	1	[14]	GETGLOBAL	0 -1	; require
	2	[14]	LOADK    	1 -2	; "ffi/mupdf"
	3	[14]	CALL     	0 2 2
	4	[16]	NEWTABLE 	1 0 3
	5	[17]	SETTABLE 	1 -3 -4	; "should_restrict_JIT" false
	6	[18]	SETTABLE 	1 -5 -4	; "is_color_rendering_enabled" false
	7	[19]	SETTABLE 	1 -6 -4	; "is_bgr" false
	8	[51]	CLOSURE  	2 0	; 0x7fa5d8c06c50
	9	[51]	MOVE     	0 0
	10	[37]	SETTABLE 	1 -7 2	; "init" -
	11	[56]	CLOSURE  	2 1	; 0x7fa5d8c07370
	12	[54]	SETTABLE 	1 -8 2	; "setColorRenderingEnabled" -
	13	[60]	CLOSURE  	2 2	; 0x7fa5d8c06bd0
	14	[58]	SETTABLE 	1 -9 2	; "getWidth" -
	15	[64]	CLOSURE  	2 3	; 0x7fa5d8c07930
	16	[62]	SETTABLE 	1 -10 2	; "getHeight" -
	17	[68]	CLOSURE  	2 4	; 0x7fa5d8c066d0
	18	[66]	SETTABLE 	1 -11 2	; "getDPI" -
	19	[72]	CLOSURE  	2 5	; 0x7fa5d8c06d00
	20	[70]	SETTABLE 	1 -12 2	; "getSize" -
	21	[76]	CLOSURE  	2 6	; 0x7fa5d8c06d80
	22	[74]	SETTABLE 	1 -13 2	; "scaleBySize" -
	23	[78]	RETURN   	1 2
	24	[78]	RETURN   	0 1

function <./frontend/document/canvascontext.lua:37,51> (25 instructions, 100 bytes at 0x7fa5d8c06c50)
2 params, 5 slots, 1 upvalue, 2 locals, 12 constants, 0 functions
	1	[38]	GETTABLE 	2 1 -1	; "screen"
	2	[38]	SETTABLE 	0 -1 2	; "screen" -
	3	[39]	GETTABLE 	2 1 -2	; "isAndroid"
	4	[39]	SETTABLE 	0 -2 2	; "isAndroid" -
	5	[40]	GETTABLE 	2 1 -3	; "isDesktop"
	6	[40]	SETTABLE 	0 -3 2	; "isDesktop" -
	7	[41]	GETTABLE 	2 1 -4	; "isEmulator"
	8	[41]	SETTABLE 	0 -4 2	; "isEmulator" -
	9	[42]	GETTABLE 	2 1 -5	; "isKindle"
	10	[42]	SETTABLE 	0 -5 2	; "isKindle" -
	11	[43]	GETTABLE 	2 1 -6	; "should_restrict_JIT"
	12	[43]	SETTABLE 	0 -6 2	; "should_restrict_JIT" -
	13	[44]	SELF     	2 0 -7	; "setColorRenderingEnabled"
	14	[44]	GETTABLE 	4 1 -1	; "screen"
	15	[44]	GETTABLE 	4 4 -8	; "isColorEnabled"
	16	[44]	CALL     	4 1 0
	17	[44]	CALL     	2 0 1
	18	[47]	SELF     	2 1 -9	; "hasBGRFrameBuffer"
	19	[47]	CALL     	2 2 2
	20	[47]	TEST     	2 0 0
	21	[47]	JMP      	3	; to 25
	22	[48]	SETTABLE 	0 -10 -11	; "is_bgr" true
	23	[49]	GETUPVAL 	2 0	; Mupdf
	24	[49]	SETTABLE 	2 -12 -11	; "bgr" true
	25	[51]	RETURN   	0 1

function <./frontend/document/canvascontext.lua:54,56> (2 instructions, 8 bytes at 0x7fa5d8c07370)
2 params, 2 slots, 0 upvalues, 2 locals, 1 constant, 0 functions
	1	[55]	SETTABLE 	0 -1 1	; "is_color_rendering_enabled" -
	2	[56]	RETURN   	0 1

function <./frontend/document/canvascontext.lua:58,60> (5 instructions, 20 bytes at 0x7fa5d8c06bd0)
1 param, 3 slots, 0 upvalues, 1 local, 2 constants, 0 functions
	1	[59]	GETTABLE 	1 0 -1	; "screen"
	2	[59]	SELF     	1 1 -2	; "getWidth"
	3	[59]	TAILCALL 	1 2 0
	4	[59]	RETURN   	1 0
	5	[60]	RETURN   	0 1

function <./frontend/document/canvascontext.lua:62,64> (5 instructions, 20 bytes at 0x7fa5d8c07930)
1 param, 3 slots, 0 upvalues, 1 local, 2 constants, 0 functions
	1	[63]	GETTABLE 	1 0 -1	; "screen"
	2	[63]	SELF     	1 1 -2	; "getHeight"
	3	[63]	TAILCALL 	1 2 0
	4	[63]	RETURN   	1 0
	5	[64]	RETURN   	0 1

function <./frontend/document/canvascontext.lua:66,68> (5 instructions, 20 bytes at 0x7fa5d8c066d0)
1 param, 3 slots, 0 upvalues, 1 local, 2 constants, 0 functions
	1	[67]	GETTABLE 	1 0 -1	; "screen"
	2	[67]	SELF     	1 1 -2	; "getDPI"
	3	[67]	TAILCALL 	1 2 0
	4	[67]	RETURN   	1 0
	5	[68]	RETURN   	0 1

function <./frontend/document/canvascontext.lua:70,72> (5 instructions, 20 bytes at 0x7fa5d8c06d00)
1 param, 3 slots, 0 upvalues, 1 local, 2 constants, 0 functions
	1	[71]	GETTABLE 	1 0 -1	; "screen"
	2	[71]	SELF     	1 1 -2	; "getSize"
	3	[71]	TAILCALL 	1 2 0
	4	[71]	RETURN   	1 0
	5	[72]	RETURN   	0 1

function <./frontend/document/canvascontext.lua:74,76> (6 instructions, 24 bytes at 0x7fa5d8c06d80)
2 params, 5 slots, 0 upvalues, 2 locals, 2 constants, 0 functions
	1	[75]	GETTABLE 	2 0 -1	; "screen"
	2	[75]	SELF     	2 2 -2	; "scaleBySize"
	3	[75]	MOVE     	4 1
	4	[75]	TAILCALL 	2 3 0
	5	[75]	RETURN   	2 0
	6	[76]	RETURN   	0 1
