-- BYTECODE -- canvascontext.lua:37-51
0001    TGETS    2   1   0  ; "screen"
0002    TSETS    2   0   0  ; "screen"
0003    TGETS    2   1   1  ; "isAndroid"
0004    TSETS    2   0   1  ; "isAndroid"
0005    TGETS    2   1   2  ; "isDesktop"
0006    TSETS    2   0   2  ; "isDesktop"
0007    TGETS    2   1   3  ; "isEmulator"
0008    TSETS    2   0   3  ; "isEmulator"
0009    TGETS    2   1   4  ; "isKindle"
0010    TSETS    2   0   4  ; "isKindle"
0011    TGETS    2   1   5  ; "should_restrict_JIT"
0012    TSETS    2   0   5  ; "should_restrict_JIT"
0013    MOV      3   0
0014    TGETS    2   0   6  ; "setColorRenderingEnabled"
0015    TGETS    4   1   0  ; "screen"
0016    TGETS    4   4   7  ; "isColorEnabled"
0017    CALL     4   0   1
0018    CALLM    2   1   1
0019    MOV      3   1
0020    TGETS    2   1   8  ; "hasBGRFrameBuffer"
0021    CALL     2   2   2
0022    ISF          2
0023    JMP      3 => 0029
0024    KPRI     2   2
0025    TSETS    2   0   9  ; "is_bgr"
0026    UGET     2   0      ; Mupdf
0027    KPRI     3   2
0028    TSETS    3   2  10  ; "bgr"
0029 => RET0     0   1

-- BYTECODE -- canvascontext.lua:54-56
0001    TSETS    1   0   0  ; "is_color_rendering_enabled"
0002    RET0     0   1

-- BYTECODE -- canvascontext.lua:58-60
0001    TGETS    1   0   0  ; "screen"
0002    MOV      2   1
0003    TGETS    1   1   1  ; "getWidth"
0004    CALLT    1   2

-- BYTECODE -- canvascontext.lua:62-64
0001    TGETS    1   0   0  ; "screen"
0002    MOV      2   1
0003    TGETS    1   1   1  ; "getHeight"
0004    CALLT    1   2

-- BYTECODE -- canvascontext.lua:66-68
0001    TGETS    1   0   0  ; "screen"
0002    MOV      2   1
0003    TGETS    1   1   1  ; "getDPI"
0004    CALLT    1   2

-- BYTECODE -- canvascontext.lua:70-72
0001    TGETS    1   0   0  ; "screen"
0002    MOV      2   1
0003    TGETS    1   1   1  ; "getSize"
0004    CALLT    1   2

-- BYTECODE -- canvascontext.lua:74-76
0001    TGETS    2   0   0  ; "screen"
0002    MOV      3   2
0003    TGETS    2   2   1  ; "scaleBySize"
0004    MOV      4   1
0005    CALLT    2   3

-- BYTECODE -- canvascontext.lua:0-79
0001    GGET     0   0      ; "require"
0002    KSTR     1   1      ; "ffi/mupdf"
0003    CALL     0   2   2
0004    TDUP     1   2
0005    FNEW     2   4      ; canvascontext.lua:37
0006    TSETS    2   1   3  ; "init"
0007    FNEW     2   6      ; canvascontext.lua:54
0008    TSETS    2   1   5  ; "setColorRenderingEnabled"
0009    FNEW     2   8      ; canvascontext.lua:58
0010    TSETS    2   1   7  ; "getWidth"
0011    FNEW     2  10      ; canvascontext.lua:62
0012    TSETS    2   1   9  ; "getHeight"
0013    FNEW     2  12      ; canvascontext.lua:66
0014    TSETS    2   1  11  ; "getDPI"
0015    FNEW     2  14      ; canvascontext.lua:70
0016    TSETS    2   1  13  ; "getSize"
0017    FNEW     2  16      ; canvascontext.lua:74
0018    TSETS    2   1  15  ; "scaleBySize"
0019    UCLO     0 => 0020
0020 => RET1     1   2

