
main <./frontend/ui/widget/checkmark.lua:0,0> (40 instructions, 160 bytes at 0x7fd4064068d0)
0+ params, 12 slots, 0 upvalues, 7 locals, 22 constants, 1 function
	1	[17]	GETGLOBAL	0 -1	; require
	2	[17]	LOADK    	1 -2	; "ui/bidi"
	3	[17]	CALL     	0 2 2
	4	[18]	GETGLOBAL	1 -1	; require
	5	[18]	LOADK    	2 -3	; "ffi/blitbuffer"
	6	[18]	CALL     	1 2 2
	7	[19]	GETGLOBAL	2 -1	; require
	8	[19]	LOADK    	3 -4	; "ui/font"
	9	[19]	CALL     	2 2 2
	10	[20]	GETGLOBAL	3 -1	; require
	11	[20]	LOADK    	4 -5	; "ui/widget/container/inputcontainer"
	12	[20]	CALL     	3 2 2
	13	[21]	GETGLOBAL	4 -1	; require
	14	[21]	LOADK    	5 -6	; "ui/widget/overlapgroup"
	15	[21]	CALL     	4 2 2
	16	[22]	GETGLOBAL	5 -1	; require
	17	[22]	LOADK    	6 -7	; "ui/widget/textwidget"
	18	[22]	CALL     	5 2 2
	19	[24]	SELF     	6 3 -8	; "new"
	20	[24]	NEWTABLE 	8 0 7
	21	[25]	SETTABLE 	8 -9 -10	; "checkable" true
	22	[26]	SETTABLE 	8 -11 -12	; "checked" false
	23	[27]	SETTABLE 	8 -13 -10	; "enabled" true
	24	[28]	SELF     	9 2 -15	; "getFace"
	25	[28]	LOADK    	11 -16	; "smallinfofont"
	26	[28]	CALL     	9 3 2
	27	[28]	SETTABLE 	8 -14 9	; "face" -
	28	[29]	SETTABLE 	8 -17 -18	; "width" 0
	29	[30]	SETTABLE 	8 -19 -18	; "height" 0
	30	[31]	GETTABLE 	9 0 -21	; "mirroredUILayout"
	31	[31]	CALL     	9 1 2
	32	[31]	SETTABLE 	8 -20 9	; "_mirroredUI" -
	33	[24]	CALL     	6 3 2
	34	[84]	CLOSURE  	7 0	; 0x7fd406407070
	35	[84]	MOVE     	0 5
	36	[84]	MOVE     	0 1
	37	[84]	MOVE     	0 4
	38	[34]	SETTABLE 	6 -22 7	; "init" -
	39	[86]	RETURN   	6 2
	40	[86]	RETURN   	0 1

function <./frontend/ui/widget/checkmark.lua:34,84> (88 instructions, 352 bytes at 0x7fd406407070)
1 param, 13 slots, 3 upvalues, 8 locals, 16 constants, 0 functions
	1	[38]	GETTABLE 	1 0 -1	; "_mirroredUI"
	2	[39]	GETUPVAL 	2 0	; TextWidget
	3	[39]	SELF     	2 2 -2	; "new"
	4	[39]	NEWTABLE 	4 0 3
	5	[40]	SETTABLE 	4 -3 -4	; "text" "\226\128\137\226\156\147"
	6	[41]	GETTABLE 	5 0 -5	; "face"
	7	[41]	SETTABLE 	4 -5 5	; "face" -
	8	[42]	SETTABLE 	4 -6 1	; "para_direction_rtl" -
	9	[39]	CALL     	2 3 2
	10	[44]	GETUPVAL 	3 0	; TextWidget
	11	[44]	SELF     	3 3 -2	; "new"
	12	[44]	NEWTABLE 	5 0 3
	13	[45]	SETTABLE 	5 -3 -7	; "text" "\226\150\162 "
	14	[46]	GETTABLE 	6 0 -5	; "face"
	15	[46]	SETTABLE 	5 -5 6	; "face" -
	16	[47]	SETTABLE 	5 -6 1	; "para_direction_rtl" -
	17	[44]	CALL     	3 3 2
	18	[49]	GETUPVAL 	4 0	; TextWidget
	19	[49]	SELF     	4 4 -2	; "new"
	20	[49]	NEWTABLE 	6 0 4
	21	[50]	SETTABLE 	6 -3 -4	; "text" "\226\128\137\226\156\147"
	22	[51]	GETTABLE 	7 0 -5	; "face"
	23	[51]	SETTABLE 	6 -5 7	; "face" -
	24	[52]	GETUPVAL 	7 1	; Blitbuffer
	25	[52]	GETTABLE 	7 7 -9	; "COLOR_DARK_GRAY"
	26	[52]	SETTABLE 	6 -8 7	; "fgcolor" -
	27	[53]	SETTABLE 	6 -6 1	; "para_direction_rtl" -
	28	[49]	CALL     	4 3 2
	29	[55]	GETUPVAL 	5 0	; TextWidget
	30	[55]	SELF     	5 5 -2	; "new"
	31	[55]	NEWTABLE 	7 0 4
	32	[56]	SETTABLE 	7 -3 -7	; "text" "\226\150\162 "
	33	[57]	GETTABLE 	8 0 -5	; "face"
	34	[57]	SETTABLE 	7 -5 8	; "face" -
	35	[58]	GETUPVAL 	8 1	; Blitbuffer
	36	[58]	GETTABLE 	8 8 -9	; "COLOR_DARK_GRAY"
	37	[58]	SETTABLE 	7 -8 8	; "fgcolor" -
	38	[59]	SETTABLE 	7 -6 1	; "para_direction_rtl" -
	39	[55]	CALL     	5 3 2
	40	[61]	GETUPVAL 	6 0	; TextWidget
	41	[61]	SELF     	6 6 -2	; "new"
	42	[61]	NEWTABLE 	8 0 3
	43	[62]	SETTABLE 	8 -3 -10	; "text" ""
	44	[63]	GETTABLE 	9 0 -5	; "face"
	45	[63]	SETTABLE 	8 -5 9	; "face" -
	46	[64]	SETTABLE 	8 -6 1	; "para_direction_rtl" -
	47	[61]	CALL     	6 3 2
	48	[66]	LOADNIL  	7 7
	49	[67]	GETTABLE 	8 0 -11	; "checkable"
	50	[67]	TEST     	8 0 0
	51	[67]	JMP      	31	; to 83
	52	[68]	GETTABLE 	8 0 -12	; "enabled"
	53	[68]	TEST     	8 0 0
	54	[68]	JMP      	14	; to 69
	55	[69]	GETUPVAL 	8 2	; OverlapGroup
	56	[69]	SELF     	8 8 -2	; "new"
	57	[69]	NEWTABLE 	10 2 0
	58	[70]	GETTABLE 	11 0 -13	; "checked"
	59	[70]	TEST     	11 0 0
	60	[70]	JMP      	2	; to 63
	61	[70]	TESTSET  	11 2 1
	62	[70]	JMP      	1	; to 64
	63	[70]	MOVE     	11 6
	64	[72]	MOVE     	12 3
	65	[72]	SETLIST  	10 2 1	; 1
	66	[69]	CALL     	8 3 2
	67	[72]	MOVE     	7 8
	68	[72]	JMP      	15	; to 84
	69	[74]	GETUPVAL 	8 2	; OverlapGroup
	70	[74]	SELF     	8 8 -2	; "new"
	71	[74]	NEWTABLE 	10 2 0
	72	[75]	GETTABLE 	11 0 -13	; "checked"
	73	[75]	TEST     	11 0 0
	74	[75]	JMP      	2	; to 77
	75	[75]	TESTSET  	11 4 1
	76	[75]	JMP      	1	; to 78
	77	[75]	MOVE     	11 6
	78	[77]	MOVE     	12 5
	79	[77]	SETLIST  	10 2 1	; 1
	80	[74]	CALL     	8 3 2
	81	[77]	MOVE     	7 8
	82	[78]	JMP      	1	; to 84
	83	[80]	MOVE     	7 6
	84	[82]	SETTABLE 	0 -14 7	; 1 -
	85	[83]	SELF     	8 3 -16	; "getSize"
	86	[83]	CALL     	8 2 2
	87	[83]	SETTABLE 	0 -15 8	; "dimen" -
	88	[84]	RETURN   	0 1
