
main <./plugins/evernote.koplugin/clip.lua:0,0> (96 instructions, 384 bytes at 0x7fcdbf4068d0)
0+ params, 12 slots, 0 upvalues, 11 locals, 66 constants, 11 functions
	1	[1]	GETGLOBAL	0 -1	; require
	2	[1]	LOADK    	1 -2	; "document/documentregistry"
	3	[1]	CALL     	0 2 2
	4	[2]	GETGLOBAL	1 -1	; require
	5	[2]	LOADK    	2 -3	; "docsettings"
	6	[2]	CALL     	1 2 2
	7	[3]	GETGLOBAL	2 -1	; require
	8	[3]	LOADK    	3 -4	; "readhistory"
	9	[3]	CALL     	2 2 2
	10	[4]	GETGLOBAL	3 -1	; require
	11	[4]	LOADK    	4 -5	; "logger"
	12	[4]	CALL     	3 2 2
	13	[5]	GETGLOBAL	4 -1	; require
	14	[5]	LOADK    	5 -6	; "ffi/MD5"
	15	[5]	CALL     	4 2 2
	16	[6]	GETGLOBAL	5 -1	; require
	17	[6]	LOADK    	6 -7	; "util"
	18	[6]	CALL     	5 2 2
	19	[8]	NEWTABLE 	6 0 2
	20	[9]	SETTABLE 	6 -8 -9	; "my_clippings" "/mnt/us/documents/My Clippings.txt"
	21	[10]	SETTABLE 	6 -10 -11	; "history_dir" "./history"
	22	[18]	CLOSURE  	7 0	; 0x7fcdbf406bf0
	23	[13]	SETTABLE 	6 -12 7	; "new" -
	24	[88]	CLOSURE  	7 1	; 0x7fcdbf407250
	25	[41]	SETTABLE 	6 -13 7	; "parseMyClippings" -
	26	[90]	NEWTABLE 	7 0 8
	27	[91]	SETTABLE 	7 -14 -15	; ".pdf" true
	28	[92]	SETTABLE 	7 -16 -15	; ".djvu" true
	29	[93]	SETTABLE 	7 -17 -15	; ".epub" true
	30	[94]	SETTABLE 	7 -18 -15	; ".fb2" true
	31	[95]	SETTABLE 	7 -19 -15	; ".mobi" true
	32	[96]	SETTABLE 	7 -20 -15	; ".txt" true
	33	[97]	SETTABLE 	7 -21 -15	; ".html" true
	34	[98]	SETTABLE 	7 -22 -15	; ".doc" true
	35	[117]	CLOSURE  	8 2	; 0x7fcdbf407070
	36	[117]	MOVE     	0 7
	37	[104]	SETTABLE 	6 -23 8	; "getTitle" -
	38	[119]	NEWTABLE 	8 0 3
	39	[120]	NEWTABLE 	9 2 0
	40	[121]	LOADK    	10 -25	; "Highlight"
	41	[123]	LOADK    	11 -26	; "\230\160\135\230\179\168"
	42	[123]	SETLIST  	9 2 1	; 1
	43	[123]	SETTABLE 	8 -24 9	; "highlight" -
	44	[124]	NEWTABLE 	9 2 0
	45	[125]	LOADK    	10 -28	; "Note"
	46	[127]	LOADK    	11 -29	; "\231\172\148\232\174\176"
	47	[127]	SETLIST  	9 2 1	; 1
	48	[127]	SETTABLE 	8 -27 9	; "note" -
	49	[128]	NEWTABLE 	9 2 0
	50	[129]	LOADK    	10 -31	; "Bookmark"
	51	[131]	LOADK    	11 -32	; "\228\185\166\231\173\190"
	52	[131]	SETLIST  	9 2 1	; 1
	53	[131]	SETTABLE 	8 -30 9	; "bookmark" -
	54	[134]	NEWTABLE 	9 0 12
	55	[135]	SETTABLE 	9 -33 -34	; "Jan" 1
	56	[136]	SETTABLE 	9 -35 -36	; "Feb" 2
	57	[137]	SETTABLE 	9 -37 -38	; "Mar" 3
	58	[138]	SETTABLE 	9 -39 -40	; "Apr" 4
	59	[139]	SETTABLE 	9 -41 -42	; "May" 5
	60	[140]	SETTABLE 	9 -43 -44	; "Jun" 6
	61	[141]	SETTABLE 	9 -45 -46	; "Jul" 7
	62	[142]	SETTABLE 	9 -47 -48	; "Aug" 8
	63	[143]	SETTABLE 	9 -49 -50	; "Sep" 9
	64	[144]	SETTABLE 	9 -51 -52	; "Oct" 10
	65	[145]	SETTABLE 	9 -53 -54	; "Nov" 11
	66	[146]	SETTABLE 	9 -55 -56	; "Dec" 12
	67	[149]	NEWTABLE 	10 0 2
	68	[150]	SETTABLE 	10 -57 -56	; "PM" 12
	69	[151]	SETTABLE 	10 -58 -56	; "\228\184\139\229\141\136" 12
	70	[186]	CLOSURE  	11 3	; 0x7fcdbf4070f0
	71	[186]	MOVE     	0 9
	72	[186]	MOVE     	0 10
	73	[154]	SETTABLE 	6 -59 11	; "getTime" -
	74	[208]	CLOSURE  	11 4	; 0x7fcdbf408bf0
	75	[208]	MOVE     	0 8
	76	[188]	SETTABLE 	6 -60 11	; "getInfo" -
	77	[213]	CLOSURE  	11 5	; 0x7fcdbf409470
	78	[210]	SETTABLE 	6 -61 11	; "getText" -
	79	[227]	CLOSURE  	11 6	; 0x7fcdbf5040b0
	80	[227]	MOVE     	0 0
	81	[227]	MOVE     	0 4
	82	[216]	SETTABLE 	6 -62 11	; "getImage" -
	83	[264]	CLOSURE  	11 7	; 0x7fcdbf504330
	84	[229]	SETTABLE 	6 -63 11	; "parseHighlight" -
	85	[292]	CLOSURE  	11 8	; 0x7fcdbf504820
	86	[292]	MOVE     	0 3
	87	[292]	MOVE     	0 5
	88	[266]	SETTABLE 	6 -64 11	; "parseHistoryFile" -
	89	[309]	CLOSURE  	11 9	; 0x7fcdbf5055d0
	90	[309]	MOVE     	0 1
	91	[309]	MOVE     	0 2
	92	[294]	SETTABLE 	6 -65 11	; "parseHistory" -
	93	[324]	CLOSURE  	11 10	; 0x7fcdbf505ed0
	94	[311]	SETTABLE 	6 -66 11	; "parseCurrentDoc" -
	95	[326]	RETURN   	6 2
	96	[326]	RETURN   	0 1

function <./plugins/evernote.koplugin/clip.lua:13,18> (11 instructions, 44 bytes at 0x7fcdbf406bf0)
2 params, 5 slots, 0 upvalues, 2 locals, 3 constants, 0 functions
	1	[14]	EQ       	0 1 -1	; - nil
	2	[14]	JMP      	2	; to 5
	3	[14]	NEWTABLE 	2 0 0
	4	[14]	MOVE     	1 2
	5	[15]	GETGLOBAL	2 -2	; setmetatable
	6	[15]	MOVE     	3 1
	7	[15]	MOVE     	4 0
	8	[15]	CALL     	2 3 1
	9	[16]	SETTABLE 	0 -3 0	; "__index" -
	10	[17]	RETURN   	1 2
	11	[18]	RETURN   	0 1

function <./plugins/evernote.koplugin/clip.lua:41,88> (75 instructions, 300 bytes at 0x7fcdbf407250)
1 param, 17 slots, 0 upvalues, 13 locals, 26 constants, 0 functions
	1	[48]	GETGLOBAL	1 -1	; io
	2	[48]	GETTABLE 	1 1 -2	; "open"
	3	[48]	GETTABLE 	2 0 -3	; "my_clippings"
	4	[48]	LOADK    	3 -4	; "r"
	5	[48]	CALL     	1 3 2
	6	[49]	NEWTABLE 	2 0 0
	7	[50]	TEST     	1 0 0
	8	[50]	JMP      	65	; to 74
	9	[51]	LOADK    	3 -5	; 1
	10	[52]	LOADNIL  	4 7
	11	[53]	SELF     	8 1 -6	; "lines"
	12	[53]	CALL     	8 2 4
	13	[53]	JMP      	58	; to 72
	14	[54]	SELF     	12 11 -7	; "match"
	15	[54]	LOADK    	14 -8	; "^%s*(.-)%s*$"
	16	[54]	CALL     	12 3 2
	17	[54]	TESTSET  	11 12 1
	18	[54]	JMP      	1	; to 20
	19	[54]	LOADK    	11 -9	; ""
	20	[55]	EQ       	0 3 -5	; - 1
	21	[55]	JMP      	13	; to 35
	22	[56]	SELF     	12 0 -10	; "getTitle"
	23	[56]	MOVE     	14 11
	24	[56]	CALL     	12 3 3
	25	[56]	MOVE     	5 13
	26	[56]	MOVE     	4 12
	27	[57]	GETTABLE 	12 2 4
	28	[57]	TEST     	12 0 1
	29	[57]	JMP      	3	; to 33
	30	[57]	NEWTABLE 	12 0 2
	31	[58]	SETTABLE 	12 -11 4	; "title" -
	32	[59]	SETTABLE 	12 -12 5	; "author" -
	33	[60]	SETTABLE 	2 4 12
	34	[60]	JMP      	13	; to 48
	35	[61]	EQ       	0 3 -13	; - 2
	36	[61]	JMP      	5	; to 42
	37	[62]	SELF     	12 0 -14	; "getInfo"
	38	[62]	MOVE     	14 11
	39	[62]	CALL     	12 3 2
	40	[62]	MOVE     	6 12
	41	[62]	JMP      	6	; to 48
	42	[65]	EQ       	0 3 -15	; - 4
	43	[65]	JMP      	4	; to 48
	44	[66]	SELF     	12 0 -16	; "getText"
	45	[66]	MOVE     	14 11
	46	[66]	CALL     	12 3 2
	47	[66]	MOVE     	7 12
	48	[68]	EQ       	0 11 -17	; - "=========="
	49	[68]	JMP      	21	; to 71
	50	[69]	EQ       	0 3 -18	; - 5
	51	[69]	JMP      	18	; to 70
	52	[71]	NEWTABLE 	12 0 4
	53	[72]	GETTABLE 	13 6 -19	; "page"
	54	[72]	TEST     	13 0 1
	55	[72]	JMP      	1	; to 57
	56	[72]	GETTABLE 	13 6 -20	; "location"
	57	[72]	SETTABLE 	12 -19 13	; "page" -
	58	[73]	GETTABLE 	13 6 -21	; "sort"
	59	[73]	SETTABLE 	12 -21 13	; "sort" -
	60	[74]	GETTABLE 	13 6 -22	; "time"
	61	[74]	SETTABLE 	12 -22 13	; "time" -
	62	[75]	SETTABLE 	12 -23 7	; "text" -
	63	[79]	GETGLOBAL	13 -24	; table
	64	[79]	GETTABLE 	13 13 -25	; "insert"
	65	[79]	GETTABLE 	14 2 4
	66	[79]	NEWTABLE 	15 1 0
	67	[79]	MOVE     	16 12
	68	[79]	SETLIST  	15 1 1	; 1
	69	[79]	CALL     	13 3 1
	70	[81]	LOADK    	3 -26	; 0
	71	[83]	ADD      	3 3 -5	; - 1
	72	[53]	TFORLOOP 	8 1
	73	[83]	JMP      	-60	; to 14
	74	[87]	RETURN   	2 2
	75	[88]	RETURN   	0 1

function <./plugins/evernote.koplugin/clip.lua:104,117> (56 instructions, 224 bytes at 0x7fcdbf407070)
2 params, 10 slots, 1 upvalue, 6 locals, 12 constants, 0 functions
	1	[105]	SELF     	2 1 -1	; "match"
	2	[105]	LOADK    	4 -2	; "^%s*(.-)%s*$"
	3	[105]	CALL     	2 3 2
	4	[105]	TESTSET  	1 2 1
	5	[105]	JMP      	1	; to 7
	6	[105]	LOADK    	1 -3	; ""
	7	[106]	GETUPVAL 	2 0	; extensions
	8	[106]	SELF     	3 1 -4	; "sub"
	9	[106]	LOADK    	5 -5	; -4
	10	[106]	CALL     	3 3 2
	11	[106]	SELF     	3 3 -6	; "lower"
	12	[106]	CALL     	3 2 2
	13	[106]	GETTABLE 	2 2 3
	14	[106]	TEST     	2 0 0
	15	[106]	JMP      	6	; to 22
	16	[107]	SELF     	2 1 -4	; "sub"
	17	[107]	LOADK    	4 -7	; 1
	18	[107]	LOADK    	5 -8	; -5
	19	[107]	CALL     	2 4 2
	20	[107]	MOVE     	1 2
	21	[107]	JMP      	14	; to 36
	22	[108]	GETUPVAL 	2 0	; extensions
	23	[108]	SELF     	3 1 -4	; "sub"
	24	[108]	LOADK    	5 -8	; -5
	25	[108]	CALL     	3 3 2
	26	[108]	SELF     	3 3 -6	; "lower"
	27	[108]	CALL     	3 2 2
	28	[108]	GETTABLE 	2 2 3
	29	[108]	TEST     	2 0 0
	30	[108]	JMP      	5	; to 36
	31	[109]	SELF     	2 1 -4	; "sub"
	32	[109]	LOADK    	4 -7	; 1
	33	[109]	LOADK    	5 -9	; -6
	34	[109]	CALL     	2 4 2
	35	[109]	MOVE     	1 2
	36	[111]	SELF     	2 1 -10	; "find"
	37	[111]	LOADK    	4 -11	; "(.-)%s*%((.*)%)"
	38	[111]	CALL     	2 3 5
	39	[112]	TEST     	5 0 1
	40	[112]	JMP      	7	; to 48
	41	[113]	SELF     	6 1 -10	; "find"
	42	[113]	LOADK    	8 -12	; "(.-)%s*-%s*(.*)"
	43	[113]	CALL     	6 3 5
	44	[113]	MOVE     	5 9
	45	[113]	MOVE     	4 8
	46	[113]	MOVE     	3 7
	47	[113]	MOVE     	3 6
	48	[115]	TEST     	4 0 1
	49	[115]	JMP      	1	; to 51
	50	[115]	MOVE     	4 1
	51	[116]	SELF     	6 4 -1	; "match"
	52	[116]	LOADK    	8 -2	; "^%s*(.-)%s*$"
	53	[116]	CALL     	6 3 2
	54	[116]	MOVE     	7 5
	55	[116]	RETURN   	6 3
	56	[117]	RETURN   	0 1

function <./plugins/evernote.koplugin/clip.lua:154,186> (91 instructions, 364 bytes at 0x7fcdbf4070f0)
2 params, 20 slots, 2 upvalues, 23 locals, 15 constants, 0 functions
	1	[155]	TEST     	1 0 1
	2	[155]	JMP      	1	; to 4
	3	[155]	RETURN   	0 1
	4	[156]	SELF     	2 1 -1	; "find"
	5	[156]	LOADK    	4 -2	; "(%d+)\229\185\180(%d+)\230\156\136(%d+)\230\151\165"
	6	[156]	CALL     	2 3 6
	7	[157]	TEST     	4 0 0
	8	[157]	JMP      	4	; to 13
	9	[157]	TEST     	5 0 0
	10	[157]	JMP      	2	; to 13
	11	[157]	TEST     	6 0 1
	12	[157]	JMP      	8	; to 21
	13	[158]	SELF     	7 1 -1	; "find"
	14	[158]	LOADK    	9 -3	; "(%d%d%d%d)-(%d%d)-(%d%d)"
	15	[158]	CALL     	7 3 6
	16	[158]	MOVE     	6 11
	17	[158]	MOVE     	5 10
	18	[158]	MOVE     	4 9
	19	[158]	MOVE     	3 8
	20	[158]	MOVE     	3 7
	21	[160]	TEST     	4 0 0
	22	[160]	JMP      	4	; to 27
	23	[160]	TEST     	5 0 0
	24	[160]	JMP      	2	; to 27
	25	[160]	TEST     	6 0 1
	26	[160]	JMP      	25	; to 52
	27	[161]	GETGLOBAL	7 -4	; pairs
	28	[161]	GETUPVAL 	8 0	; months
	29	[161]	CALL     	7 2 4
	30	[161]	JMP      	19	; to 50
	31	[162]	SELF     	12 1 -1	; "find"
	32	[162]	MOVE     	14 10
	33	[162]	CALL     	12 3 2
	34	[162]	TEST     	12 0 0
	35	[162]	JMP      	14	; to 50
	36	[163]	MOVE     	5 11
	37	[164]	SELF     	12 1 -1	; "find"
	38	[164]	LOADK    	14 -5	; " (%d?%d),"
	39	[164]	CALL     	12 3 4
	40	[164]	MOVE     	6 14
	41	[164]	MOVE     	3 13
	42	[164]	MOVE     	3 12
	43	[165]	SELF     	12 1 -1	; "find"
	44	[165]	LOADK    	14 -6	; " (%d%d%d%d)"
	45	[165]	CALL     	12 3 4
	46	[165]	MOVE     	4 14
	47	[165]	MOVE     	3 13
	48	[165]	MOVE     	3 12
	49	[166]	JMP      	2	; to 52
	50	[161]	TFORLOOP 	7 2
	51	[167]	JMP      	-21	; to 31
	52	[171]	SELF     	7 1 -1	; "find"
	53	[171]	LOADK    	9 -7	; "(%d+):(%d+):(%d+)"
	54	[171]	CALL     	7 3 6
	55	[172]	TEST     	4 0 0
	56	[172]	JMP      	34	; to 91
	57	[172]	TEST     	5 0 0
	58	[172]	JMP      	32	; to 91
	59	[172]	TEST     	6 0 0
	60	[172]	JMP      	30	; to 91
	61	[172]	TEST     	9 0 0
	62	[172]	JMP      	28	; to 91
	63	[172]	TEST     	10 0 0
	64	[172]	JMP      	26	; to 91
	65	[172]	TEST     	11 0 0
	66	[172]	JMP      	24	; to 91
	67	[173]	GETGLOBAL	12 -4	; pairs
	68	[173]	GETUPVAL 	13 1	; pms
	69	[173]	CALL     	12 2 4
	70	[173]	JMP      	7	; to 78
	71	[174]	SELF     	17 1 -1	; "find"
	72	[174]	MOVE     	19 15
	73	[174]	CALL     	17 3 2
	74	[174]	TEST     	17 0 0
	75	[174]	JMP      	2	; to 78
	76	[175]	ADD      	9 9 16
	77	[176]	JMP      	2	; to 80
	78	[173]	TFORLOOP 	12 2
	79	[177]	JMP      	-9	; to 71
	80	[179]	GETGLOBAL	12 -8	; os
	81	[179]	GETTABLE 	12 12 -9	; "time"
	82	[179]	NEWTABLE 	13 0 6
	83	[180]	SETTABLE 	13 -10 4	; "year" -
	84	[180]	SETTABLE 	13 -11 5	; "month" -
	85	[180]	SETTABLE 	13 -12 6	; "day" -
	86	[181]	SETTABLE 	13 -13 9	; "hour" -
	87	[181]	SETTABLE 	13 -14 10	; "min" -
	88	[181]	SETTABLE 	13 -15 11	; "sec" -
	89	[179]	CALL     	12 2 2
	90	[184]	RETURN   	12 2
	91	[186]	RETURN   	0 1

function <./plugins/evernote.koplugin/clip.lua:188,208> (40 instructions, 160 bytes at 0x7fcdbf408bf0)
2 params, 20 slots, 1 upvalue, 17 locals, 11 constants, 0 functions
	1	[189]	NEWTABLE 	2 0 0
	2	[190]	TEST     	1 0 1
	3	[190]	JMP      	1	; to 5
	4	[190]	LOADK    	1 -1	; ""
	5	[191]	SELF     	3 1 -2	; "find"
	6	[191]	LOADK    	5 -3	; "(.+)%s*|%s*(.+)"
	7	[191]	CALL     	3 3 5
	8	[194]	GETGLOBAL	7 -4	; pairs
	9	[194]	GETUPVAL 	8 0	; keywords
	10	[194]	CALL     	7 2 4
	11	[194]	JMP      	19	; to 31
	12	[195]	GETGLOBAL	12 -5	; ipairs
	13	[195]	MOVE     	13 11
	14	[195]	CALL     	12 2 4
	15	[195]	JMP      	13	; to 29
	16	[196]	TEST     	5 0 0
	17	[196]	JMP      	11	; to 29
	18	[196]	SELF     	17 5 -2	; "find"
	19	[196]	MOVE     	19 16
	20	[196]	CALL     	17 3 2
	21	[196]	TEST     	17 0 0
	22	[196]	JMP      	6	; to 29
	23	[197]	SETTABLE 	2 -6 10	; "sort" -
	24	[198]	SELF     	17 5 -8	; "match"
	25	[198]	LOADK    	19 -9	; "(%d+-?%d+)"
	26	[198]	CALL     	17 3 2
	27	[198]	SETTABLE 	2 -7 17	; "location" -
	28	[199]	JMP      	2	; to 31
	29	[195]	TFORLOOP 	12 2
	30	[200]	JMP      	-15	; to 16
	31	[194]	TFORLOOP 	7 2
	32	[201]	JMP      	-21	; to 12
	33	[205]	SELF     	7 0 -11	; "getTime"
	34	[205]	TESTSET  	9 6 1
	35	[205]	JMP      	1	; to 37
	36	[205]	LOADK    	9 -1	; ""
	37	[205]	CALL     	7 3 2
	38	[205]	SETTABLE 	2 -10 7	; "time" -
	39	[207]	RETURN   	2 2
	40	[208]	RETURN   	0 1

function <./plugins/evernote.koplugin/clip.lua:210,213> (11 instructions, 44 bytes at 0x7fcdbf409470)
2 params, 5 slots, 0 upvalues, 2 locals, 3 constants, 0 functions
	1	[211]	TEST     	1 0 1
	2	[211]	JMP      	1	; to 4
	3	[211]	LOADK    	1 -1	; ""
	4	[212]	SELF     	2 1 -2	; "match"
	5	[212]	LOADK    	4 -3	; "^%s*(.-)%s*$"
	6	[212]	CALL     	2 3 2
	7	[212]	TEST     	2 0 1
	8	[212]	JMP      	1	; to 10
	9	[212]	LOADK    	2 -1	; ""
	10	[212]	RETURN   	2 2
	11	[213]	RETURN   	0 1

function <./plugins/evernote.koplugin/clip.lua:216,227> (25 instructions, 100 bytes at 0x7fcdbf5040b0)
2 params, 9 slots, 2 upvalues, 4 locals, 11 constants, 0 functions
	1	[218]	GETUPVAL 	2 0	; DocumentRegistry
	2	[218]	SELF     	2 2 -1	; "openDocument"
	3	[218]	GETTABLE 	4 1 -2	; "file"
	4	[218]	CALL     	2 3 2
	5	[219]	TEST     	2 0 0
	6	[219]	JMP      	18	; to 25
	7	[220]	SELF     	3 2 -3	; "clipPagePNGString"
	8	[220]	GETTABLE 	5 1 -4	; "pos0"
	9	[220]	GETTABLE 	6 1 -5	; "pos1"
	10	[221]	GETTABLE 	7 1 -6	; "pboxes"
	11	[221]	GETTABLE 	8 1 -7	; "drawer"
	12	[220]	CALL     	3 6 2
	13	[224]	SELF     	4 2 -8	; "close"
	14	[224]	CALL     	4 2 1
	15	[225]	TEST     	3 0 0
	16	[225]	JMP      	8	; to 25
	17	[225]	NEWTABLE 	4 0 2
	18	[225]	SETTABLE 	4 -9 3	; "png" -
	19	[225]	GETUPVAL 	5 1	; md5
	20	[225]	GETTABLE 	5 5 -11	; "sum"
	21	[225]	MOVE     	6 3
	22	[225]	CALL     	5 2 2
	23	[225]	SETTABLE 	4 -10 5	; "hash" -
	24	[225]	RETURN   	4 2
	25	[227]	RETURN   	0 1

function <./plugins/evernote.koplugin/clip.lua:229,264> (126 instructions, 504 bytes at 0x7fcdbf504330)
4 params, 25 slots, 0 upvalues, 22 locals, 27 constants, 1 function
	1	[231]	GETGLOBAL	4 -1	; pairs
	2	[231]	MOVE     	5 1
	3	[231]	CALL     	4 2 4
	4	[231]	JMP      	114	; to 119
	5	[232]	GETGLOBAL	9 -2	; ipairs
	6	[232]	MOVE     	10 8
	7	[232]	CALL     	9 2 4
	8	[232]	JMP      	108	; to 117
	9	[233]	NEWTABLE 	14 0 0
	10	[234]	SETTABLE 	14 -3 7	; "page" -
	11	[235]	SETTABLE 	14 -4 -5	; "sort" "highlight"
	12	[236]	SELF     	15 0 -7	; "getTime"
	13	[236]	GETTABLE 	17 13 -8	; "datetime"
	14	[236]	TEST     	17 0 1
	15	[236]	JMP      	1	; to 17
	16	[236]	LOADK    	17 -9	; ""
	17	[236]	CALL     	15 3 2
	18	[236]	SETTABLE 	14 -6 15	; "time" -
	19	[237]	SELF     	15 0 -11	; "getText"
	20	[237]	GETTABLE 	17 13 -10	; "text"
	21	[237]	CALL     	15 3 2
	22	[237]	SETTABLE 	14 -10 15	; "text" -
	23	[238]	GETGLOBAL	15 -1	; pairs
	24	[238]	MOVE     	16 2
	25	[238]	CALL     	15 2 4
	26	[238]	JMP      	20	; to 47
	27	[239]	GETTABLE 	20 19 -8	; "datetime"
	28	[239]	GETTABLE 	21 13 -8	; "datetime"
	29	[239]	EQ       	0 20 21
	30	[239]	JMP      	16	; to 47
	31	[239]	GETTABLE 	20 19 -10	; "text"
	32	[239]	TEST     	20 0 0
	33	[239]	JMP      	13	; to 47
	34	[240]	GETGLOBAL	20 -12	; string
	35	[240]	GETTABLE 	20 20 -13	; "gsub"
	36	[240]	GETTABLE 	21 19 -10	; "text"
	37	[240]	LOADK    	22 -14	; "Page %d+ "
	38	[240]	LOADK    	23 -9	; ""
	39	[240]	CALL     	20 4 2
	40	[241]	GETGLOBAL	21 -12	; string
	41	[241]	GETTABLE 	21 21 -13	; "gsub"
	42	[241]	MOVE     	22 20
	43	[241]	LOADK    	23 -15	; " @ %d%d%d%d%-%d%d%-%d%d %d%d:%d%d:%d%d"
	44	[241]	LOADK    	24 -9	; ""
	45	[241]	CALL     	21 4 2
	46	[241]	SETTABLE 	14 -10 21	; "text" -
	47	[238]	TFORLOOP 	15 2
	48	[242]	JMP      	-22	; to 27
	49	[244]	GETTABLE 	15 13 -10	; "text"
	50	[244]	EQ       	0 15 -9	; - ""
	51	[244]	JMP      	49	; to 101
	52	[244]	GETTABLE 	15 13 -16	; "pos0"
	53	[244]	TEST     	15 0 0
	54	[244]	JMP      	46	; to 101
	55	[244]	GETTABLE 	15 13 -17	; "pos1"
	56	[244]	TEST     	15 0 0
	57	[244]	JMP      	43	; to 101
	58	[245]	GETTABLE 	15 13 -16	; "pos0"
	59	[245]	GETTABLE 	15 15 -18	; "x"
	60	[245]	TEST     	15 0 0
	61	[245]	JMP      	39	; to 101
	62	[245]	GETTABLE 	15 13 -16	; "pos0"
	63	[245]	GETTABLE 	15 15 -19	; "y"
	64	[245]	TEST     	15 0 0
	65	[245]	JMP      	35	; to 101
	66	[246]	GETTABLE 	15 13 -17	; "pos1"
	67	[246]	GETTABLE 	15 15 -18	; "x"
	68	[246]	TEST     	15 0 0
	69	[246]	JMP      	31	; to 101
	70	[246]	GETTABLE 	15 13 -17	; "pos1"
	71	[246]	GETTABLE 	15 15 -19	; "y"
	72	[246]	TEST     	15 0 0
	73	[246]	JMP      	27	; to 101
	74	[248]	GETTABLE 	15 13 -16	; "pos0"
	75	[248]	GETTABLE 	15 15 -3	; "page"
	76	[248]	EQ       	0 15 -20	; - nil
	77	[248]	JMP      	2	; to 80
	78	[248]	GETTABLE 	15 13 -16	; "pos0"
	79	[248]	SETTABLE 	15 -3 7	; "page" -
	80	[249]	GETTABLE 	15 13 -17	; "pos1"
	81	[249]	GETTABLE 	15 15 -3	; "page"
	82	[249]	EQ       	0 15 -20	; - nil
	83	[249]	JMP      	2	; to 86
	84	[249]	GETTABLE 	15 13 -17	; "pos1"
	85	[249]	SETTABLE 	15 -3 7	; "page" -
	86	[250]	NEWTABLE 	15 0 0
	87	[251]	GETTABLE 	16 3 -21	; "file"
	88	[251]	SETTABLE 	15 -21 16	; "file" -
	89	[252]	GETTABLE 	16 13 -16	; "pos0"
	90	[252]	GETTABLE 	17 13 -17	; "pos1"
	91	[252]	SETTABLE 	15 -17 17	; "pos1" -
	92	[252]	SETTABLE 	15 -16 16	; "pos0" -
	93	[253]	GETTABLE 	16 13 -22	; "pboxes"
	94	[253]	SETTABLE 	15 -22 16	; "pboxes" -
	95	[254]	GETTABLE 	16 13 -23	; "drawer"
	96	[254]	SETTABLE 	15 -23 16	; "drawer" -
	97	[255]	SELF     	16 0 -25	; "getImage"
	98	[255]	MOVE     	18 15
	99	[255]	CALL     	16 3 2
	100	[255]	SETTABLE 	14 -24 16	; "image" -
	101	[258]	GETTABLE 	15 14 -10	; "text"
	102	[258]	TEST     	15 0 0
	103	[258]	JMP      	3	; to 107
	104	[258]	GETTABLE 	15 14 -10	; "text"
	105	[258]	EQ       	0 15 -9	; - ""
	106	[258]	JMP      	3	; to 110
	107	[258]	GETTABLE 	15 14 -24	; "image"
	108	[258]	TEST     	15 0 0
	109	[258]	JMP      	7	; to 117
	110	[259]	GETGLOBAL	15 -26	; table
	111	[259]	GETTABLE 	15 15 -27	; "insert"
	112	[259]	MOVE     	16 3
	113	[259]	NEWTABLE 	17 1 0
	114	[259]	MOVE     	18 14
	115	[259]	SETLIST  	17 1 1	; 1
	116	[259]	CALL     	15 3 1
	117	[232]	TFORLOOP 	9 2
	118	[260]	JMP      	-110	; to 9
	119	[231]	TFORLOOP 	4 2
	120	[261]	JMP      	-116	; to 5
	121	[263]	GETGLOBAL	4 -26	; table
	122	[263]	GETTABLE 	4 4 -4	; "sort"
	123	[263]	MOVE     	5 3
	124	[263]	CLOSURE  	6 0	; 0x7fcdbf504a30
	125	[263]	CALL     	4 3 1
	126	[264]	RETURN   	0 1

function <./plugins/evernote.koplugin/clip.lua:263,263> (10 instructions, 40 bytes at 0x7fcdbf504a30)
2 params, 4 slots, 0 upvalues, 2 locals, 2 constants, 0 functions
	1	[263]	GETTABLE 	2 0 -1	; 1
	2	[263]	GETTABLE 	2 2 -2	; "page"
	3	[263]	GETTABLE 	3 1 -1	; 1
	4	[263]	GETTABLE 	3 3 -2	; "page"
	5	[263]	LT       	1 2 3
	6	[263]	JMP      	1	; to 8
	7	[263]	LOADBOOL 	2 0 1
	8	[263]	LOADBOOL 	2 1 0
	9	[263]	RETURN   	2 2
	10	[263]	RETURN   	0 1

function <./plugins/evernote.koplugin/clip.lua:266,292> (63 instructions, 252 bytes at 0x7fcdbf504820)
4 params, 15 slots, 2 upvalues, 10 locals, 19 constants, 0 functions
	1	[267]	GETGLOBAL	4 -1	; lfs
	2	[267]	GETTABLE 	4 4 -2	; "attributes"
	3	[267]	MOVE     	5 2
	4	[267]	LOADK    	6 -3	; "mode"
	5	[267]	CALL     	4 3 2
	6	[267]	EQ       	0 4 -4	; - "file"
	7	[267]	JMP      	5	; to 13
	8	[268]	SELF     	4 2 -5	; "find"
	9	[268]	LOADK    	6 -6	; ".+%.lua$"
	10	[268]	CALL     	4 3 2
	11	[268]	TEST     	4 0 1
	12	[268]	JMP      	1	; to 14
	13	[269]	RETURN   	0 1
	14	[271]	GETGLOBAL	4 -1	; lfs
	15	[271]	GETTABLE 	4 4 -2	; "attributes"
	16	[271]	MOVE     	5 3
	17	[271]	LOADK    	6 -3	; "mode"
	18	[271]	CALL     	4 3 2
	19	[271]	EQ       	1 4 -4	; - "file"
	20	[271]	JMP      	1	; to 22
	21	[271]	RETURN   	0 1
	22	[272]	GETGLOBAL	4 -7	; pcall
	23	[272]	GETGLOBAL	5 -8	; dofile
	24	[272]	MOVE     	6 2
	25	[272]	CALL     	4 3 3
	26	[273]	TEST     	4 0 0
	27	[273]	JMP      	35	; to 63
	28	[274]	TEST     	5 0 1
	29	[274]	JMP      	9	; to 39
	30	[275]	GETUPVAL 	6 0	; logger
	31	[275]	GETTABLE 	6 6 -9	; "warn"
	32	[275]	LOADK    	7 -10	; "An empty history file "
	33	[276]	MOVE     	8 2
	34	[277]	LOADK    	9 -11	; "has been found. The book associated is "
	35	[278]	MOVE     	10 3
	36	[275]	CALL     	6 5 1
	37	[279]	RETURN   	0 1
	38	[279]	JMP      	4	; to 43
	39	[280]	GETTABLE 	6 5 -12	; "highlight"
	40	[280]	TEST     	6 0 1
	41	[280]	JMP      	1	; to 43
	42	[281]	RETURN   	0 1
	43	[283]	GETUPVAL 	6 1	; util
	44	[283]	GETTABLE 	6 6 -13	; "splitFilePathName"
	45	[283]	MOVE     	7 3
	46	[283]	CALL     	6 2 3
	47	[284]	SELF     	8 0 -14	; "getTitle"
	48	[284]	GETUPVAL 	10 1	; util
	49	[284]	GETTABLE 	10 10 -15	; "splitFileNameSuffix"
	50	[284]	MOVE     	11 7
	51	[284]	CALL     	10 2 0
	52	[284]	CALL     	8 0 3
	53	[285]	NEWTABLE 	10 0 3
	54	[286]	SETTABLE 	10 -4 3	; "file" -
	55	[287]	SETTABLE 	10 -16 8	; "title" -
	56	[288]	SETTABLE 	10 -17 9	; "author" -
	57	[289]	SETTABLE 	1 8 10
	58	[290]	SELF     	10 0 -18	; "parseHighlight"
	59	[290]	GETTABLE 	12 5 -12	; "highlight"
	60	[290]	GETTABLE 	13 5 -19	; "bookmarks"
	61	[290]	GETTABLE 	14 1 8
	62	[290]	CALL     	10 5 1
	63	[292]	RETURN   	0 1

function <./plugins/evernote.koplugin/clip.lua:294,309> (42 instructions, 168 bytes at 0x7fcdbf5055d0)
1 param, 15 slots, 2 upvalues, 11 locals, 11 constants, 0 functions
	1	[295]	NEWTABLE 	1 0 0
	2	[296]	GETGLOBAL	2 -1	; lfs
	3	[296]	GETTABLE 	2 2 -2	; "dir"
	4	[296]	GETTABLE 	3 0 -3	; "history_dir"
	5	[296]	CALL     	2 2 4
	6	[296]	JMP      	17	; to 24
	7	[297]	SELF     	6 0 -4	; "parseHistoryFile"
	8	[297]	MOVE     	8 1
	9	[298]	GETTABLE 	9 0 -3	; "history_dir"
	10	[298]	LOADK    	10 -5	; "/"
	11	[298]	MOVE     	11 5
	12	[298]	CONCAT   	9 9 11
	13	[299]	GETUPVAL 	10 0	; DocSettings
	14	[299]	SELF     	10 10 -6	; "getPathFromHistory"
	15	[299]	MOVE     	12 5
	16	[299]	CALL     	10 3 2
	17	[299]	LOADK    	11 -5	; "/"
	18	[300]	GETUPVAL 	12 0	; DocSettings
	19	[300]	SELF     	12 12 -7	; "getNameFromHistory"
	20	[300]	MOVE     	14 5
	21	[300]	CALL     	12 3 2
	22	[300]	CONCAT   	10 10 12
	23	[297]	CALL     	6 5 1
	24	[296]	TFORLOOP 	2 1
	25	[300]	JMP      	-19	; to 7
	26	[302]	GETGLOBAL	2 -8	; ipairs
	27	[302]	GETUPVAL 	3 1	; ReadHistory
	28	[302]	GETTABLE 	3 3 -9	; "hist"
	29	[302]	CALL     	2 2 4
	30	[302]	JMP      	8	; to 39
	31	[303]	SELF     	7 0 -4	; "parseHistoryFile"
	32	[303]	MOVE     	9 1
	33	[304]	GETUPVAL 	10 0	; DocSettings
	34	[304]	SELF     	10 10 -10	; "getSidecarFile"
	35	[304]	GETTABLE 	12 6 -11	; "file"
	36	[304]	CALL     	10 3 2
	37	[305]	GETTABLE 	11 6 -11	; "file"
	38	[303]	CALL     	7 5 1
	39	[302]	TFORLOOP 	2 2
	40	[305]	JMP      	-10	; to 31
	41	[308]	RETURN   	1 2
	42	[309]	RETURN   	0 1

function <./plugins/evernote.koplugin/clip.lua:311,324> (26 instructions, 104 bytes at 0x7fcdbf505ed0)
2 params, 14 slots, 0 upvalues, 9 locals, 13 constants, 0 functions
	1	[312]	NEWTABLE 	2 0 0
	2	[313]	GETTABLE 	3 1 -1	; "document"
	3	[313]	GETTABLE 	3 3 -2	; "file"
	4	[314]	SELF     	4 3 -3	; "find"
	5	[314]	LOADK    	6 -4	; ".*/(.*)"
	6	[314]	CALL     	4 3 4
	7	[315]	SELF     	7 0 -5	; "getTitle"
	8	[315]	MOVE     	9 6
	9	[315]	CALL     	7 3 3
	10	[316]	NEWTABLE 	9 0 3
	11	[317]	GETTABLE 	10 1 -1	; "document"
	12	[317]	GETTABLE 	10 10 -2	; "file"
	13	[317]	SETTABLE 	9 -2 10	; "file" -
	14	[318]	SETTABLE 	9 -6 7	; "title" -
	15	[319]	SETTABLE 	9 -7 8	; "author" -
	16	[320]	SETTABLE 	2 7 9
	17	[321]	SELF     	9 0 -8	; "parseHighlight"
	18	[321]	GETTABLE 	11 1 -9	; "highlight"
	19	[321]	GETTABLE 	11 11 -10	; "saved"
	20	[321]	GETTABLE 	12 1 -11	; "ui"
	21	[321]	GETTABLE 	12 12 -12	; "bookmark"
	22	[321]	GETTABLE 	12 12 -13	; "bookmarks"
	23	[321]	GETTABLE 	13 2 7
	24	[321]	CALL     	9 5 1
	25	[323]	RETURN   	2 2
	26	[324]	RETURN   	0 1
