-- BYTECODE -- closebutton.lua:58-58
0001    UGET     0   0      ; self
0002    TGETS    0   0   0  ; "dimen"
0003    RET1     0   2

-- BYTECODE -- closebutton.lua:66-66
0001    UGET     0   0      ; self
0002    TGETS    0   0   0  ; "dimen"
0003    RET1     0   2

-- BYTECODE -- closebutton.lua:31-70
0001    UGET     1   0      ; TextWidget
0002    MOV      2   1
0003    TGETS    1   1   0  ; "new"
0004    TDUP     3   1
0005    UGET     4   1      ; Font
0006    MOV      5   4
0007    TGETS    4   4   2  ; "getFace"
0008    KSTR     6   3      ; "cfont"
0009    KSHORT   7  30
0010    CALL     4   2   4
0011    TSETS    4   3   4  ; "face"
0012    CALL     1   2   3
0013    MOV      3   1
0014    TGETS    2   1   5  ; "getSize"
0015    CALL     2   2   2
0016    TGETS    3   2   6  ; "h"
0017    TGETS    4   2   7  ; "w"
0018    SUBVV    3   3   4
0019    DIVVN    3   3   0  ; 2
0020    UGET     4   2      ; FrameContainer
0021    MOV      5   4
0022    TGETS    4   4   0  ; "new"
0023    TDUP     6   8
0024    TGETS    7   0   9  ; "padding_top"
0025    TSETS    7   6   9  ; "padding_top"
0026    TGETS    7   0  10  ; "padding_bottom"
0027    TSETS    7   6  10  ; "padding_bottom"
0028    TGETS    7   0  11  ; "padding_left"
0029    TSETS    7   6  11  ; "padding_left"
0030    TGETS    7   0  12  ; "padding_right"
0031    ADDVV    7   7   3
0032    TSETS    7   6  12  ; "padding_right"
0033    TSETB    1   6   1
0034    CALL     4   2   3
0035    TSETB    4   0   1
0036    TGETS    4   0  13  ; "ges_events"
0037    TDUP     5  18
0038    UGET     6   3      ; GestureRange
0039    MOV      7   6
0040    TGETS    6   6   0  ; "new"
0041    TDUP     8  15
0042    FNEW     9  16      ; closebutton.lua:58
0043    TSETS    9   8  17  ; "range"
0044    CALL     6   2   3
0045    TSETB    6   5   1
0046    TSETS    5   4  14  ; "Close"
0047    TGETS    4   0  13  ; "ges_events"
0048    TDUP     5  22
0049    UGET     6   3      ; GestureRange
0050    MOV      7   6
0051    TGETS    6   6   0  ; "new"
0052    TDUP     8  20
0053    FNEW     9  21      ; closebutton.lua:66
0054    TSETS    9   8  17  ; "range"
0055    CALL     6   2   3
0056    TSETB    6   5   1
0057    TSETS    5   4  19  ; "HoldClose"
0058    UCLO     0 => 0059
0059 => RET0     0   1

-- BYTECODE -- closebutton.lua:72-77
0001    TGETS    1   0   0  ; "window"
0002    TGETS    1   1   1  ; "onClose"
0003    ISF          1
0004    JMP      2 => 0009
0005    TGETS    1   0   0  ; "window"
0006    MOV      2   1
0007    TGETS    1   1   1  ; "onClose"
0008    CALL     1   1   2
0009 => KPRI     1   2
0010    RET1     1   2

-- BYTECODE -- closebutton.lua:79-84
0001    TGETS    1   0   0  ; "window"
0002    TGETS    1   1   1  ; "onHoldClose"
0003    ISF          1
0004    JMP      2 => 0009
0005    TGETS    1   0   0  ; "window"
0006    MOV      2   1
0007    TGETS    1   1   1  ; "onHoldClose"
0008    CALL     1   1   2
0009 => KPRI     1   2
0010    RET1     1   2

-- BYTECODE -- closebutton.lua:0-87
0001    GGET     0   0      ; "require"
0002    KSTR     1   1      ; "ui/font"
0003    CALL     0   2   2
0004    GGET     1   0      ; "require"
0005    KSTR     2   2      ; "ui/widget/container/framecontainer"
0006    CALL     1   2   2
0007    GGET     2   0      ; "require"
0008    KSTR     3   3      ; "ui/gesturerange"
0009    CALL     2   2   2
0010    GGET     3   0      ; "require"
0011    KSTR     4   4      ; "ui/widget/container/inputcontainer"
0012    CALL     3   2   2
0013    GGET     4   0      ; "require"
0014    KSTR     5   5      ; "ui/widget/textwidget"
0015    CALL     4   2   2
0016    GGET     5   0      ; "require"
0017    KSTR     6   6      ; "device"
0018    CALL     5   2   2
0019    TGETS    5   5   7  ; "screen"
0020    MOV      7   3
0021    TGETS    6   3   8  ; "new"
0022    TDUP     8   9
0023    MOV     10   5
0024    TGETS    9   5  10  ; "scaleBySize"
0025    KSHORT  11  14
0026    CALL     9   2   3
0027    TSETS    9   8  11  ; "padding_left"
0028    CALL     6   2   3
0029    FNEW     7  13      ; closebutton.lua:31
0030    TSETS    7   6  12  ; "init"
0031    FNEW     7  15      ; closebutton.lua:72
0032    TSETS    7   6  14  ; "onClose"
0033    FNEW     7  17      ; closebutton.lua:79
0034    TSETS    7   6  16  ; "onHoldClose"
0035    UCLO     0 => 0036
0036 => RET1     6   2

