
main <./frontend/apps/cloudstorage/cloudstorage.lua:0,0> (165 instructions, 660 bytes at 0x7f8de34068f0)
0+ params, 23 slots, 0 upvalues, 17 locals, 55 constants, 19 functions
	1	[1]	GETGLOBAL	0 -1	; require
	2	[1]	LOADK    	1 -2	; "ui/bidi"
	3	[1]	CALL     	0 2 2
	4	[2]	GETGLOBAL	1 -1	; require
	5	[2]	LOADK    	2 -3	; "ui/widget/buttondialog"
	6	[2]	CALL     	1 2 2
	7	[3]	GETGLOBAL	2 -1	; require
	8	[3]	LOADK    	3 -4	; "ui/widget/buttondialogtitle"
	9	[3]	CALL     	2 2 2
	10	[4]	GETGLOBAL	3 -1	; require
	11	[4]	LOADK    	4 -5	; "ui/widget/confirmbox"
	12	[4]	CALL     	3 2 2
	13	[5]	GETGLOBAL	4 -1	; require
	14	[5]	LOADK    	5 -6	; "datastorage"
	15	[5]	CALL     	4 2 2
	16	[6]	GETGLOBAL	5 -1	; require
	17	[6]	LOADK    	6 -7	; "apps/cloudstorage/dropbox"
	18	[6]	CALL     	5 2 2
	19	[7]	GETGLOBAL	6 -1	; require
	20	[7]	LOADK    	7 -8	; "apps/cloudstorage/ftp"
	21	[7]	CALL     	6 2 2
	22	[8]	GETGLOBAL	7 -1	; require
	23	[8]	LOADK    	8 -9	; "ui/widget/infomessage"
	24	[8]	CALL     	7 2 2
	25	[9]	GETGLOBAL	8 -1	; require
	26	[9]	LOADK    	9 -10	; "luasettings"
	27	[9]	CALL     	8 2 2
	28	[10]	GETGLOBAL	9 -1	; require
	29	[10]	LOADK    	10 -11	; "ui/widget/menu"
	30	[10]	CALL     	9 2 2
	31	[11]	GETGLOBAL	10 -1	; require
	32	[11]	LOADK    	11 -12	; "ui/uimanager"
	33	[11]	CALL     	10 2 2
	34	[12]	GETGLOBAL	11 -1	; require
	35	[12]	LOADK    	12 -13	; "apps/cloudstorage/webdav"
	36	[12]	CALL     	11 2 2
	37	[13]	GETGLOBAL	12 -1	; require
	38	[13]	LOADK    	13 -14	; "libs/libkoreader-lfs"
	39	[13]	CALL     	12 2 2
	40	[14]	GETGLOBAL	13 -1	; require
	41	[14]	LOADK    	14 -15	; "ffi/util"
	42	[14]	CALL     	13 2 2
	43	[14]	GETTABLE 	13 13 -16	; "template"
	44	[15]	GETGLOBAL	14 -1	; require
	45	[15]	LOADK    	15 -17	; "gettext"
	46	[15]	CALL     	14 2 2
	47	[16]	GETGLOBAL	15 -1	; require
	48	[16]	LOADK    	16 -18	; "device"
	49	[16]	CALL     	15 2 2
	50	[16]	GETTABLE 	15 15 -19	; "screen"
	51	[18]	SELF     	16 9 -20	; "extend"
	52	[18]	NEWTABLE 	18 0 6
	53	[19]	NEWTABLE 	19 1 0
	54	[19]	NEWTABLE 	20 0 4
	55	[21]	MOVE     	21 14
	56	[21]	LOADK    	22 -23	; "Add new cloud storage"
	57	[21]	CALL     	21 2 2
	58	[21]	SETTABLE 	20 -22 21	; "text" -
	59	[22]	MOVE     	21 14
	60	[22]	LOADK    	22 -25	; "Choose cloud type"
	61	[22]	CALL     	21 2 2
	62	[22]	SETTABLE 	20 -24 21	; "title" -
	63	[23]	SETTABLE 	20 -26 -27	; "url" "add"
	64	[24]	SETTABLE 	20 -28 -29	; "editable" false
	65	[26]	SETLIST  	19 1 1	; 1
	66	[26]	SETTABLE 	18 -21 19	; "cloud_servers" -
	67	[27]	SETTABLE 	18 -30 -29	; "no_title" false
	68	[28]	SETTABLE 	18 -31 -32	; "show_parent" nil
	69	[29]	SETTABLE 	18 -33 -29	; "is_popout" false
	70	[30]	SETTABLE 	18 -34 -35	; "is_borderless" true
	71	[31]	MOVE     	19 14
	72	[31]	LOADK    	20 -36	; "Cloud storage"
	73	[31]	CALL     	19 2 2
	74	[31]	SETTABLE 	18 -24 19	; "title" -
	75	[18]	CALL     	16 3 2
	76	[49]	CLOSURE  	17 0	; 0x7f8de34070a0
	77	[49]	MOVE     	0 15
	78	[49]	MOVE     	0 9
	79	[34]	SETTABLE 	16 -37 17	; "init" -
	80	[81]	CLOSURE  	17 1	; 0x7f8de3407b70
	81	[81]	MOVE     	0 14
	82	[51]	SETTABLE 	16 -38 17	; "genItemTableFromRoot" -
	83	[106]	CLOSURE  	17 2	; 0x7f8de3408360
	84	[83]	SETTABLE 	16 -39 17	; "genItemTable" -
	85	[146]	CLOSURE  	17 3	; 0x7f8de34091d0
	86	[146]	MOVE     	0 14
	87	[146]	MOVE     	0 10
	88	[146]	MOVE     	0 2
	89	[108]	SETTABLE 	16 -40 17	; "selectCloudType" -
	90	[184]	CLOSURE  	17 4	; 0x7f8de340a0c0
	91	[184]	MOVE     	0 5
	92	[184]	MOVE     	0 6
	93	[184]	MOVE     	0 11
	94	[184]	MOVE     	0 10
	95	[184]	MOVE     	0 7
	96	[184]	MOVE     	0 14
	97	[148]	SETTABLE 	16 -41 17	; "openCloudServer" -
	98	[207]	CLOSURE  	17 5	; 0x7f8de340a9a0
	99	[186]	SETTABLE 	16 -42 17	; "onMenuSelect" -
	100	[215]	CLOSURE  	17 6	; 0x7f8de340b2b0
	101	[209]	SETTABLE 	16 -43 17	; "downloadFile" -
	102	[325]	CLOSURE  	17 7	; 0x7f8de3409980
	103	[325]	MOVE     	0 14
	104	[325]	MOVE     	0 10
	105	[325]	MOVE     	0 5
	106	[325]	MOVE     	0 7
	107	[325]	MOVE     	0 6
	108	[325]	MOVE     	0 11
	109	[325]	MOVE     	0 12
	110	[325]	MOVE     	0 3
	111	[325]	MOVE     	0 1
	112	[217]	SETTABLE 	16 -44 17	; "cloudFile" -
	113	[343]	CLOSURE  	17 8	; 0x7f8de340af10
	114	[327]	SETTABLE 	16 -45 17	; "updateSyncFolder" -
	115	[432]	CLOSURE  	17 9	; 0x7f8de340d690
	116	[432]	MOVE     	0 13
	117	[432]	MOVE     	0 14
	118	[432]	MOVE     	0 0
	119	[432]	MOVE     	0 2
	120	[432]	MOVE     	0 10
	121	[432]	MOVE     	0 1
	122	[345]	SETTABLE 	16 -46 17	; "onMenuHold" -
	123	[462]	CLOSURE  	17 10	; 0x7f8de340d5f0
	124	[462]	MOVE     	0 14
	125	[462]	MOVE     	0 13
	126	[462]	MOVE     	0 10
	127	[462]	MOVE     	0 7
	128	[434]	SETTABLE 	16 -47 17	; "synchronizeCloud" -
	129	[521]	CLOSURE  	17 11	; 0x7f8de340c560
	130	[521]	MOVE     	0 14
	131	[521]	MOVE     	0 12
	132	[521]	MOVE     	0 5
	133	[464]	SETTABLE 	16 -48 17	; "downloadListFiles" -
	134	[573]	CLOSURE  	17 12	; 0x7f8de340baf0
	135	[573]	MOVE     	0 2
	136	[573]	MOVE     	0 13
	137	[573]	MOVE     	0 14
	138	[573]	MOVE     	0 0
	139	[573]	MOVE     	0 10
	140	[523]	SETTABLE 	16 -49 17	; "synchronizeSettings" -
	141	[618]	CLOSURE  	17 13	; 0x7f8de34077d0
	142	[618]	MOVE     	0 5
	143	[618]	MOVE     	0 6
	144	[618]	MOVE     	0 11
	145	[575]	SETTABLE 	16 -50 17	; "configCloud" -
	146	[669]	CLOSURE  	17 14	; 0x7f8de3412350
	147	[669]	MOVE     	0 5
	148	[669]	MOVE     	0 6
	149	[669]	MOVE     	0 11
	150	[620]	SETTABLE 	16 -51 17	; "editCloudServer" -
	151	[683]	CLOSURE  	17 15	; 0x7f8de3412ca0
	152	[671]	SETTABLE 	16 -52 17	; "deleteCloudServer" -
	153	[693]	CLOSURE  	17 16	; 0x7f8de3413bf0
	154	[693]	MOVE     	0 5
	155	[693]	MOVE     	0 6
	156	[693]	MOVE     	0 11
	157	[685]	SETTABLE 	16 -53 17	; "infoServer" -
	158	[698]	CLOSURE  	17 17	; 0x7f8de340f0f0
	159	[698]	MOVE     	0 8
	160	[698]	MOVE     	0 4
	161	[695]	SETTABLE 	16 -54 17	; "readSettings" -
	162	[713]	CLOSURE  	17 18	; 0x7f8de34144c0
	163	[700]	SETTABLE 	16 -55 17	; "onReturn" -
	164	[715]	RETURN   	16 2
	165	[715]	RETURN   	0 1

function <./frontend/apps/cloudstorage/cloudstorage.lua:34,49> (36 instructions, 144 bytes at 0x7f8de34070a0)
1 param, 4 slots, 2 upvalues, 1 local, 16 constants, 0 functions
	1	[35]	SELF     	1 0 -2	; "readSettings"
	2	[35]	CALL     	1 2 2
	3	[35]	SETTABLE 	0 -1 1	; "cs_settings" -
	4	[36]	SETTABLE 	0 -3 0	; "show_parent" -
	5	[37]	GETTABLE 	1 0 -4	; "item"
	6	[37]	TEST     	1 0 0
	7	[37]	JMP      	6	; to 14
	8	[38]	SELF     	1 0 -6	; "genItemTable"
	9	[38]	GETTABLE 	3 0 -4	; "item"
	10	[38]	CALL     	1 3 2
	11	[38]	SETTABLE 	0 -5 1	; "item_table" -
	12	[39]	SETTABLE 	0 -7 -8	; "choose_folder_mode" true
	13	[39]	JMP      	3	; to 17
	14	[41]	SELF     	1 0 -9	; "genItemTableFromRoot"
	15	[41]	CALL     	1 2 2
	16	[41]	SETTABLE 	0 -5 1	; "item_table" -
	17	[43]	GETUPVAL 	1 0	; Screen
	18	[43]	SELF     	1 1 -11	; "getWidth"
	19	[43]	CALL     	1 2 2
	20	[43]	SETTABLE 	0 -10 1	; "width" -
	21	[44]	GETUPVAL 	1 0	; Screen
	22	[44]	SELF     	1 1 -13	; "getHeight"
	23	[44]	CALL     	1 2 2
	24	[44]	SETTABLE 	0 -12 1	; "height" -
	25	[45]	GETUPVAL 	1 1	; Menu
	26	[45]	GETTABLE 	1 1 -14	; "init"
	27	[45]	MOVE     	2 0
	28	[45]	CALL     	1 2 1
	29	[46]	GETTABLE 	1 0 -4	; "item"
	30	[46]	TEST     	1 0 0
	31	[46]	JMP      	4	; to 36
	32	[47]	GETTABLE 	1 0 -5	; "item_table"
	33	[47]	GETTABLE 	1 1 -15	; 1
	34	[47]	GETTABLE 	1 1 -16	; "callback"
	35	[47]	CALL     	1 1 1
	36	[49]	RETURN   	0 1

function <./frontend/apps/cloudstorage/cloudstorage.lua:51,81> (55 instructions, 220 bytes at 0x7f8de3407b70)
1 param, 12 slots, 1 upvalue, 8 locals, 19 constants, 2 functions
	1	[52]	NEWTABLE 	1 0 0
	2	[53]	GETGLOBAL	2 -1	; table
	3	[53]	GETTABLE 	2 2 -2	; "insert"
	4	[53]	MOVE     	3 1
	5	[53]	NEWTABLE 	4 0 2
	6	[54]	GETUPVAL 	5 0	; _
	7	[54]	LOADK    	6 -4	; "Add new cloud storage"
	8	[54]	CALL     	5 2 2
	9	[54]	SETTABLE 	4 -3 5	; "text" -
	10	[57]	CLOSURE  	5 0	; 0x7f8de3407f80
	11	[57]	MOVE     	0 0
	12	[57]	SETTABLE 	4 -5 5	; "callback" -
	13	[53]	CALL     	2 3 1
	14	[59]	GETTABLE 	2 0 -6	; "cs_settings"
	15	[59]	SELF     	2 2 -7	; "readSetting"
	16	[59]	LOADK    	4 -8	; "cs_servers"
	17	[59]	CALL     	2 3 2
	18	[59]	TEST     	2 0 1
	19	[59]	JMP      	1	; to 21
	20	[59]	NEWTABLE 	2 0 0
	21	[60]	GETGLOBAL	3 -9	; ipairs
	22	[60]	MOVE     	4 2
	23	[60]	CALL     	3 2 4
	24	[60]	JMP      	27	; to 52
	25	[61]	GETGLOBAL	8 -1	; table
	26	[61]	GETTABLE 	8 8 -2	; "insert"
	27	[61]	MOVE     	9 1
	28	[61]	NEWTABLE 	10 0 10
	29	[62]	GETTABLE 	11 7 -10	; "name"
	30	[62]	SETTABLE 	10 -3 11	; "text" -
	31	[63]	GETTABLE 	11 7 -11	; "address"
	32	[63]	SETTABLE 	10 -11 11	; "address" -
	33	[64]	GETTABLE 	11 7 -12	; "username"
	34	[64]	SETTABLE 	10 -12 11	; "username" -
	35	[65]	GETTABLE 	11 7 -13	; "password"
	36	[65]	SETTABLE 	10 -13 11	; "password" -
	37	[66]	GETTABLE 	11 7 -14	; "type"
	38	[66]	SETTABLE 	10 -14 11	; "type" -
	39	[67]	SETTABLE 	10 -15 -16	; "editable" true
	40	[68]	GETTABLE 	11 7 -17	; "url"
	41	[68]	SETTABLE 	10 -17 11	; "url" -
	42	[69]	GETTABLE 	11 7 -18	; "sync_source_folder"
	43	[69]	SETTABLE 	10 -18 11	; "sync_source_folder" -
	44	[70]	GETTABLE 	11 7 -19	; "sync_dest_folder"
	45	[70]	SETTABLE 	10 -19 11	; "sync_dest_folder" -
	46	[77]	CLOSURE  	11 1	; 0x7f8de3408450
	47	[77]	MOVE     	0 0
	48	[77]	MOVE     	0 7
	49	[77]	SETTABLE 	10 -5 11	; "callback" -
	50	[61]	CALL     	8 3 1
	51	[78]	CLOSE    	6
	52	[60]	TFORLOOP 	3 2
	53	[78]	JMP      	-29	; to 25
	54	[80]	RETURN   	1 2
	55	[81]	RETURN   	0 1

function <./frontend/apps/cloudstorage/cloudstorage.lua:55,57> (4 instructions, 16 bytes at 0x7f8de3407f80)
0 params, 2 slots, 1 upvalue, 0 locals, 1 constant, 0 functions
	1	[56]	GETUPVAL 	0 0	; self
	2	[56]	SELF     	0 0 -1	; "selectCloudType"
	3	[56]	CALL     	0 2 1
	4	[57]	RETURN   	0 1

function <./frontend/apps/cloudstorage/cloudstorage.lua:71,77> (22 instructions, 88 bytes at 0x7f8de3408450)
0 params, 3 slots, 2 upvalues, 0 locals, 6 constants, 0 functions
	1	[72]	GETUPVAL 	0 0	; self
	2	[72]	GETUPVAL 	1 1	; server
	3	[72]	GETTABLE 	1 1 -1	; "type"
	4	[72]	SETTABLE 	0 -1 1	; "type" -
	5	[73]	GETUPVAL 	0 0	; self
	6	[73]	GETUPVAL 	1 1	; server
	7	[73]	GETTABLE 	1 1 -2	; "password"
	8	[73]	SETTABLE 	0 -2 1	; "password" -
	9	[74]	GETUPVAL 	0 0	; self
	10	[74]	GETUPVAL 	1 1	; server
	11	[74]	GETTABLE 	1 1 -3	; "address"
	12	[74]	SETTABLE 	0 -3 1	; "address" -
	13	[75]	GETUPVAL 	0 0	; self
	14	[75]	GETUPVAL 	1 1	; server
	15	[75]	GETTABLE 	1 1 -4	; "username"
	16	[75]	SETTABLE 	0 -4 1	; "username" -
	17	[76]	GETUPVAL 	0 0	; self
	18	[76]	SELF     	0 0 -5	; "openCloudServer"
	19	[76]	GETUPVAL 	2 1	; server
	20	[76]	GETTABLE 	2 2 -6	; "url"
	21	[76]	CALL     	0 3 1
	22	[77]	RETURN   	0 1

function <./frontend/apps/cloudstorage/cloudstorage.lua:83,106> (50 instructions, 200 bytes at 0x7f8de3408360)
2 params, 13 slots, 0 upvalues, 9 locals, 14 constants, 1 function
	1	[84]	NEWTABLE 	2 0 0
	2	[85]	GETTABLE 	3 0 -1	; "cs_settings"
	3	[85]	SELF     	3 3 -2	; "readSetting"
	4	[85]	LOADK    	5 -3	; "cs_servers"
	5	[85]	CALL     	3 3 2
	6	[85]	TEST     	3 0 1
	7	[85]	JMP      	1	; to 9
	8	[85]	NEWTABLE 	3 0 0
	9	[86]	GETGLOBAL	4 -4	; ipairs
	10	[86]	MOVE     	5 3
	11	[86]	CALL     	4 2 4
	12	[86]	JMP      	34	; to 47
	13	[87]	GETTABLE 	9 8 -5	; "name"
	14	[87]	GETTABLE 	10 1 -6	; "text"
	15	[87]	EQ       	0 9 10
	16	[87]	JMP      	29	; to 46
	17	[87]	GETTABLE 	9 8 -7	; "password"
	18	[87]	GETTABLE 	10 1 -7	; "password"
	19	[87]	EQ       	0 9 10
	20	[87]	JMP      	25	; to 46
	21	[87]	GETTABLE 	9 8 -8	; "type"
	22	[87]	GETTABLE 	10 1 -8	; "type"
	23	[87]	EQ       	0 9 10
	24	[87]	JMP      	21	; to 46
	25	[88]	GETGLOBAL	9 -9	; table
	26	[88]	GETTABLE 	9 9 -10	; "insert"
	27	[88]	MOVE     	10 2
	28	[88]	NEWTABLE 	11 0 7
	29	[89]	GETTABLE 	12 8 -5	; "name"
	30	[89]	SETTABLE 	11 -6 12	; "text" -
	31	[90]	GETTABLE 	12 8 -11	; "address"
	32	[90]	SETTABLE 	11 -11 12	; "address" -
	33	[91]	GETTABLE 	12 8 -12	; "username"
	34	[91]	SETTABLE 	11 -12 12	; "username" -
	35	[92]	GETTABLE 	12 8 -7	; "password"
	36	[92]	SETTABLE 	11 -7 12	; "password" -
	37	[93]	GETTABLE 	12 8 -8	; "type"
	38	[93]	SETTABLE 	11 -8 12	; "type" -
	39	[94]	GETTABLE 	12 8 -13	; "url"
	40	[94]	SETTABLE 	11 -13 12	; "url" -
	41	[101]	CLOSURE  	12 0	; 0x7f8de3408e10
	42	[101]	MOVE     	0 0
	43	[101]	MOVE     	0 8
	44	[101]	SETTABLE 	11 -14 12	; "callback" -
	45	[88]	CALL     	9 3 1
	46	[103]	CLOSE    	7
	47	[86]	TFORLOOP 	4 2
	48	[103]	JMP      	-36	; to 13
	49	[105]	RETURN   	2 2
	50	[106]	RETURN   	0 1

function <./frontend/apps/cloudstorage/cloudstorage.lua:95,101> (22 instructions, 88 bytes at 0x7f8de3408e10)
0 params, 3 slots, 2 upvalues, 0 locals, 6 constants, 0 functions
	1	[96]	GETUPVAL 	0 0	; self
	2	[96]	GETUPVAL 	1 1	; server
	3	[96]	GETTABLE 	1 1 -1	; "type"
	4	[96]	SETTABLE 	0 -1 1	; "type" -
	5	[97]	GETUPVAL 	0 0	; self
	6	[97]	GETUPVAL 	1 1	; server
	7	[97]	GETTABLE 	1 1 -2	; "password"
	8	[97]	SETTABLE 	0 -2 1	; "password" -
	9	[98]	GETUPVAL 	0 0	; self
	10	[98]	GETUPVAL 	1 1	; server
	11	[98]	GETTABLE 	1 1 -3	; "address"
	12	[98]	SETTABLE 	0 -3 1	; "address" -
	13	[99]	GETUPVAL 	0 0	; self
	14	[99]	GETUPVAL 	1 1	; server
	15	[99]	GETTABLE 	1 1 -4	; "username"
	16	[99]	SETTABLE 	0 -4 1	; "username" -
	17	[100]	GETUPVAL 	0 0	; self
	18	[100]	SELF     	0 0 -5	; "openCloudServer"
	19	[100]	GETUPVAL 	2 1	; server
	20	[100]	GETTABLE 	2 2 -6	; "url"
	21	[100]	CALL     	0 3 1
	22	[101]	RETURN   	0 1

function <./frontend/apps/cloudstorage/cloudstorage.lua:108,146> (53 instructions, 212 bytes at 0x7f8de34091d0)
1 param, 8 slots, 3 upvalues, 2 locals, 13 constants, 3 functions
	1	[109]	NEWTABLE 	1 3 0
	2	[109]	NEWTABLE 	2 1 0
	3	[110]	NEWTABLE 	3 0 2
	4	[112]	GETUPVAL 	4 0	; _
	5	[112]	LOADK    	5 -2	; "Dropbox"
	6	[112]	CALL     	4 2 2
	7	[112]	SETTABLE 	3 -1 4	; "text" -
	8	[116]	CLOSURE  	4 0	; 0x7f8de3409630
	9	[116]	GETUPVAL 	0 1	; UIManager
	10	[116]	MOVE     	0 0
	11	[116]	SETTABLE 	3 -3 4	; "callback" -
	12	[118]	SETLIST  	2 1 1	; 1
	13	[118]	NEWTABLE 	3 1 0
	14	[119]	NEWTABLE 	4 0 2
	15	[121]	GETUPVAL 	5 0	; _
	16	[121]	LOADK    	6 -4	; "FTP"
	17	[121]	CALL     	5 2 2
	18	[121]	SETTABLE 	4 -1 5	; "text" -
	19	[125]	CLOSURE  	5 1	; 0x7f8de3409de0
	20	[125]	GETUPVAL 	0 1	; UIManager
	21	[125]	MOVE     	0 0
	22	[125]	SETTABLE 	4 -3 5	; "callback" -
	23	[127]	SETLIST  	3 1 1	; 1
	24	[127]	NEWTABLE 	4 1 0
	25	[128]	NEWTABLE 	5 0 2
	26	[130]	GETUPVAL 	6 0	; _
	27	[130]	LOADK    	7 -5	; "WebDAV"
	28	[130]	CALL     	6 2 2
	29	[130]	SETTABLE 	5 -1 6	; "text" -
	30	[134]	CLOSURE  	6 2	; 0x7f8de340a140
	31	[134]	GETUPVAL 	0 1	; UIManager
	32	[134]	MOVE     	0 0
	33	[134]	SETTABLE 	5 -3 6	; "callback" -
	34	[136]	SETLIST  	4 1 1	; 1
	35	[137]	SETLIST  	1 3 1	; 1
	36	[138]	GETUPVAL 	2 2	; ButtonDialogTitle
	37	[138]	SELF     	2 2 -7	; "new"
	38	[138]	NEWTABLE 	4 0 3
	39	[139]	GETUPVAL 	5 0	; _
	40	[139]	LOADK    	6 -9	; "Choose cloud storage type"
	41	[139]	CALL     	5 2 2
	42	[139]	SETTABLE 	4 -8 5	; "title" -
	43	[140]	SETTABLE 	4 -10 -11	; "title_align" "center"
	44	[141]	SETTABLE 	4 -12 1	; "buttons" -
	45	[138]	CALL     	2 3 2
	46	[142]	SETTABLE 	0 -6 2	; "cloud_dialog" -
	47	[144]	GETUPVAL 	2 1	; UIManager
	48	[144]	SELF     	2 2 -13	; "show"
	49	[144]	GETTABLE 	4 0 -6	; "cloud_dialog"
	50	[144]	CALL     	2 3 1
	51	[145]	LOADBOOL 	2 1 0
	52	[145]	RETURN   	2 2
	53	[146]	RETURN   	0 1

function <./frontend/apps/cloudstorage/cloudstorage.lua:113,116> (10 instructions, 40 bytes at 0x7f8de3409630)
0 params, 3 slots, 2 upvalues, 0 locals, 4 constants, 0 functions
	1	[114]	GETUPVAL 	0 0	; UIManager
	2	[114]	SELF     	0 0 -1	; "close"
	3	[114]	GETUPVAL 	2 1	; self
	4	[114]	GETTABLE 	2 2 -2	; "cloud_dialog"
	5	[114]	CALL     	0 3 1
	6	[115]	GETUPVAL 	0 1	; self
	7	[115]	SELF     	0 0 -3	; "configCloud"
	8	[115]	LOADK    	2 -4	; "dropbox"
	9	[115]	CALL     	0 3 1
	10	[116]	RETURN   	0 1

function <./frontend/apps/cloudstorage/cloudstorage.lua:122,125> (10 instructions, 40 bytes at 0x7f8de3409de0)
0 params, 3 slots, 2 upvalues, 0 locals, 4 constants, 0 functions
	1	[123]	GETUPVAL 	0 0	; UIManager
	2	[123]	SELF     	0 0 -1	; "close"
	3	[123]	GETUPVAL 	2 1	; self
	4	[123]	GETTABLE 	2 2 -2	; "cloud_dialog"
	5	[123]	CALL     	0 3 1
	6	[124]	GETUPVAL 	0 1	; self
	7	[124]	SELF     	0 0 -3	; "configCloud"
	8	[124]	LOADK    	2 -4	; "ftp"
	9	[124]	CALL     	0 3 1
	10	[125]	RETURN   	0 1

function <./frontend/apps/cloudstorage/cloudstorage.lua:131,134> (10 instructions, 40 bytes at 0x7f8de340a140)
0 params, 3 slots, 2 upvalues, 0 locals, 4 constants, 0 functions
	1	[132]	GETUPVAL 	0 0	; UIManager
	2	[132]	SELF     	0 0 -1	; "close"
	3	[132]	GETUPVAL 	2 1	; self
	4	[132]	GETTABLE 	2 2 -2	; "cloud_dialog"
	5	[132]	CALL     	0 3 1
	6	[133]	GETUPVAL 	0 1	; self
	7	[133]	SELF     	0 0 -3	; "configCloud"
	8	[133]	LOADK    	2 -4	; "webdav"
	9	[133]	CALL     	0 3 1
	10	[134]	RETURN   	0 1

function <./frontend/apps/cloudstorage/cloudstorage.lua:148,184> (105 instructions, 420 bytes at 0x7f8de340a0c0)
2 params, 11 slots, 6 upvalues, 4 locals, 26 constants, 0 functions
	1	[150]	GETGLOBAL	3 -1	; require
	2	[150]	LOADK    	4 -2	; "ui/network/manager"
	3	[150]	CALL     	3 2 2
	4	[151]	GETTABLE 	4 0 -3	; "type"
	5	[151]	EQ       	0 4 -4	; - "dropbox"
	6	[151]	JMP      	15	; to 22
	7	[152]	SELF     	4 3 -5	; "isOnline"
	8	[152]	CALL     	4 2 2
	9	[152]	TEST     	4 0 1
	10	[152]	JMP      	3	; to 14
	11	[153]	SELF     	4 3 -6	; "promptWifiOn"
	12	[153]	CALL     	4 2 1
	13	[154]	RETURN   	0 1
	14	[156]	GETUPVAL 	4 0	; DropBox
	15	[156]	SELF     	4 4 -7	; "run"
	16	[156]	MOVE     	6 1
	17	[156]	GETTABLE 	7 0 -8	; "password"
	18	[156]	GETTABLE 	8 0 -9	; "choose_folder_mode"
	19	[156]	CALL     	4 5 2
	20	[156]	MOVE     	2 4
	21	[156]	JMP      	37	; to 59
	22	[157]	GETTABLE 	4 0 -3	; "type"
	23	[157]	EQ       	0 4 -10	; - "ftp"
	24	[157]	JMP      	16	; to 41
	25	[158]	SELF     	4 3 -11	; "isConnected"
	26	[158]	CALL     	4 2 2
	27	[158]	TEST     	4 0 1
	28	[158]	JMP      	3	; to 32
	29	[159]	SELF     	4 3 -6	; "promptWifiOn"
	30	[159]	CALL     	4 2 1
	31	[160]	RETURN   	0 1
	32	[162]	GETUPVAL 	4 1	; Ftp
	33	[162]	SELF     	4 4 -7	; "run"
	34	[162]	GETTABLE 	6 0 -12	; "address"
	35	[162]	GETTABLE 	7 0 -13	; "username"
	36	[162]	GETTABLE 	8 0 -8	; "password"
	37	[162]	MOVE     	9 1
	38	[162]	CALL     	4 6 2
	39	[162]	MOVE     	2 4
	40	[162]	JMP      	18	; to 59
	41	[163]	GETTABLE 	4 0 -3	; "type"
	42	[163]	EQ       	0 4 -14	; - "webdav"
	43	[163]	JMP      	15	; to 59
	44	[164]	SELF     	4 3 -11	; "isConnected"
	45	[164]	CALL     	4 2 2
	46	[164]	TEST     	4 0 1
	47	[164]	JMP      	3	; to 51
	48	[165]	SELF     	4 3 -6	; "promptWifiOn"
	49	[165]	CALL     	4 2 1
	50	[166]	RETURN   	0 1
	51	[168]	GETUPVAL 	4 2	; WebDav
	52	[168]	SELF     	4 4 -7	; "run"
	53	[168]	GETTABLE 	6 0 -12	; "address"
	54	[168]	GETTABLE 	7 0 -13	; "username"
	55	[168]	GETTABLE 	8 0 -8	; "password"
	56	[168]	MOVE     	9 1
	57	[168]	CALL     	4 6 2
	58	[168]	MOVE     	2 4
	59	[170]	TEST     	2 0 0
	60	[170]	JMP      	10	; to 71
	61	[170]	LEN      	4 2
	62	[170]	LT       	0 -15 4	; 0 -
	63	[170]	JMP      	7	; to 71
	64	[171]	SELF     	4 0 -16	; "switchItemTable"
	65	[171]	MOVE     	6 1
	66	[171]	MOVE     	7 2
	67	[171]	CALL     	4 4 1
	68	[172]	LOADBOOL 	4 1 0
	69	[172]	RETURN   	4 2
	70	[172]	JMP      	34	; to 105
	71	[173]	TEST     	2 0 1
	72	[173]	JMP      	19	; to 92
	73	[174]	GETUPVAL 	4 3	; UIManager
	74	[174]	SELF     	4 4 -17	; "show"
	75	[174]	GETUPVAL 	6 4	; InfoMessage
	76	[174]	SELF     	6 6 -18	; "new"
	77	[174]	NEWTABLE 	8 0 2
	78	[175]	GETUPVAL 	9 5	; _
	79	[175]	LOADK    	10 -20	; "Cannot fetch list of folder contents\nPlease check your configuration or network connection."
	80	[175]	CALL     	9 2 2
	81	[175]	SETTABLE 	8 -19 9	; "text" -
	82	[176]	SETTABLE 	8 -21 -22	; "timeout" 3
	83	[174]	CALL     	6 3 0
	84	[174]	CALL     	4 0 1
	85	[178]	GETGLOBAL	4 -23	; table
	86	[178]	GETTABLE 	4 4 -24	; "remove"
	87	[178]	GETTABLE 	5 0 -25	; "paths"
	88	[178]	CALL     	4 2 1
	89	[179]	LOADBOOL 	4 0 0
	90	[179]	RETURN   	4 2
	91	[179]	JMP      	13	; to 105
	92	[181]	GETUPVAL 	4 3	; UIManager
	93	[181]	SELF     	4 4 -17	; "show"
	94	[181]	GETUPVAL 	6 4	; InfoMessage
	95	[181]	SELF     	6 6 -18	; "new"
	96	[181]	NEWTABLE 	8 0 1
	97	[181]	GETUPVAL 	9 5	; _
	98	[181]	LOADK    	10 -26	; "Empty folder"
	99	[181]	CALL     	9 2 2
	100	[181]	SETTABLE 	8 -19 9	; "text" -
	101	[181]	CALL     	6 3 0
	102	[181]	CALL     	4 0 1
	103	[182]	LOADBOOL 	4 0 0
	104	[182]	RETURN   	4 2
	105	[184]	RETURN   	0 1

function <./frontend/apps/cloudstorage/cloudstorage.lua:186,207> (48 instructions, 192 bytes at 0x7f8de340a9a0)
2 params, 6 slots, 0 upvalues, 2 locals, 12 constants, 0 functions
	1	[187]	GETTABLE 	2 1 -1	; "callback"
	2	[187]	TEST     	2 0 0
	3	[187]	JMP      	13	; to 17
	4	[188]	GETTABLE 	2 1 -2	; "url"
	5	[188]	EQ       	1 2 -3	; - nil
	6	[188]	JMP      	7	; to 14
	7	[189]	GETGLOBAL	2 -4	; table
	8	[189]	GETTABLE 	2 2 -5	; "insert"
	9	[189]	GETTABLE 	3 0 -6	; "paths"
	10	[189]	NEWTABLE 	4 0 1
	11	[190]	GETTABLE 	5 1 -2	; "url"
	12	[190]	SETTABLE 	4 -2 5	; "url" -
	13	[189]	CALL     	2 3 1
	14	[193]	GETTABLE 	2 1 -1	; "callback"
	15	[193]	CALL     	2 1 1
	16	[193]	JMP      	29	; to 46
	17	[194]	GETTABLE 	2 1 -7	; "type"
	18	[194]	EQ       	0 2 -8	; - "file"
	19	[194]	JMP      	4	; to 24
	20	[195]	SELF     	2 0 -9	; "downloadFile"
	21	[195]	MOVE     	4 1
	22	[195]	CALL     	2 3 1
	23	[195]	JMP      	22	; to 46
	24	[196]	GETTABLE 	2 1 -7	; "type"
	25	[196]	EQ       	0 2 -10	; - "other"
	26	[196]	JMP      	3	; to 30
	27	[197]	LOADBOOL 	2 1 0
	28	[197]	RETURN   	2 2
	29	[197]	JMP      	16	; to 46
	30	[199]	GETGLOBAL	2 -4	; table
	31	[199]	GETTABLE 	2 2 -5	; "insert"
	32	[199]	GETTABLE 	3 0 -6	; "paths"
	33	[199]	NEWTABLE 	4 0 1
	34	[200]	GETTABLE 	5 1 -2	; "url"
	35	[200]	SETTABLE 	4 -2 5	; "url" -
	36	[199]	CALL     	2 3 1
	37	[202]	SELF     	2 0 -11	; "openCloudServer"
	38	[202]	GETTABLE 	4 1 -2	; "url"
	39	[202]	CALL     	2 3 2
	40	[202]	TEST     	2 0 1
	41	[202]	JMP      	4	; to 46
	42	[203]	GETGLOBAL	2 -4	; table
	43	[203]	GETTABLE 	2 2 -12	; "remove"
	44	[203]	GETTABLE 	3 0 -6	; "paths"
	45	[203]	CALL     	2 2 1
	46	[206]	LOADBOOL 	2 1 0
	47	[206]	RETURN   	2 2
	48	[207]	RETURN   	0 1

function <./frontend/apps/cloudstorage/cloudstorage.lua:209,215> (21 instructions, 84 bytes at 0x7f8de340b2b0)
2 params, 10 slots, 0 upvalues, 6 locals, 8 constants, 0 functions
	1	[210]	GETGLOBAL	2 -1	; G_reader_settings
	2	[210]	SELF     	2 2 -2	; "readSetting"
	3	[210]	LOADK    	4 -3	; "lastdir"
	4	[210]	CALL     	2 3 2
	5	[211]	SELF     	3 0 -4	; "readSettings"
	6	[211]	CALL     	3 2 2
	7	[212]	SELF     	4 3 -2	; "readSetting"
	8	[212]	LOADK    	6 -5	; "download_dir"
	9	[212]	CALL     	4 3 2
	10	[212]	TEST     	4 0 1
	11	[212]	JMP      	1	; to 13
	12	[212]	MOVE     	4 2
	13	[213]	MOVE     	5 4
	14	[213]	LOADK    	6 -6	; "/"
	15	[213]	GETTABLE 	7 1 -7	; "text"
	16	[213]	CONCAT   	5 5 7
	17	[214]	SELF     	6 0 -8	; "cloudFile"
	18	[214]	MOVE     	8 1
	19	[214]	MOVE     	9 5
	20	[214]	CALL     	6 4 1
	21	[215]	RETURN   	0 1

function <./frontend/apps/cloudstorage/cloudstorage.lua:217,325> (67 instructions, 268 bytes at 0x7f8de3409980)
3 params, 15 slots, 9 upvalues, 10 locals, 10 constants, 5 functions
	1	[218]	GETUPVAL 	3 0	; _
	2	[218]	LOADK    	4 -1	; "Downloading. This might take a moment."
	3	[218]	CALL     	3 2 2
	4	[227]	CLOSURE  	4 0	; 0x7f8de340af90
	5	[227]	GETUPVAL 	0 1	; UIManager
	6	[227]	GETUPVAL 	0 2	; DropBox
	7	[227]	GETUPVAL 	0 3	; InfoMessage
	8	[227]	MOVE     	0 3
	9	[237]	CLOSURE  	5 1	; 0x7f8de340b4f0
	10	[237]	GETUPVAL 	0 1	; UIManager
	11	[237]	GETUPVAL 	0 4	; Ftp
	12	[237]	GETUPVAL 	0 3	; InfoMessage
	13	[237]	MOVE     	0 3
	14	[247]	CLOSURE  	6 2	; 0x7f8de340c670
	15	[247]	GETUPVAL 	0 1	; UIManager
	16	[247]	GETUPVAL 	0 5	; WebDav
	17	[247]	GETUPVAL 	0 3	; InfoMessage
	18	[247]	MOVE     	0 3
	19	[249]	MOVE     	7 2
	20	[250]	GETUPVAL 	8 0	; _
	21	[250]	LOADK    	9 -2	; "File already exists. Would you like to overwrite it?"
	22	[250]	CALL     	8 2 2
	23	[251]	NEWTABLE 	9 2 0
	24	[251]	NEWTABLE 	10 1 0
	25	[252]	NEWTABLE 	11 0 2
	26	[254]	GETUPVAL 	12 0	; _
	27	[254]	LOADK    	13 -4	; "Download file"
	28	[254]	CALL     	12 2 2
	29	[254]	SETTABLE 	11 -3 12	; "text" -
	30	[302]	CLOSURE  	12 3	; 0x7f8de340cff0
	31	[302]	MOVE     	0 0
	32	[302]	GETUPVAL 	0 1	; UIManager
	33	[302]	GETUPVAL 	0 6	; lfs
	34	[302]	MOVE     	0 2
	35	[302]	GETUPVAL 	0 7	; ConfirmBox
	36	[302]	MOVE     	0 8
	37	[302]	MOVE     	0 4
	38	[302]	MOVE     	0 1
	39	[302]	MOVE     	0 7
	40	[302]	MOVE     	0 5
	41	[302]	MOVE     	0 6
	42	[302]	SETTABLE 	11 -5 12	; "callback" -
	43	[304]	SETLIST  	10 1 1	; 1
	44	[304]	NEWTABLE 	11 1 0
	45	[305]	NEWTABLE 	12 0 2
	46	[307]	GETUPVAL 	13 0	; _
	47	[307]	LOADK    	14 -6	; "Choose download directory"
	48	[307]	CALL     	13 2 2
	49	[307]	SETTABLE 	12 -3 13	; "text" -
	50	[317]	CLOSURE  	13 4	; 0x7f8de340ce70
	51	[317]	MOVE     	0 0
	52	[317]	MOVE     	0 7
	53	[317]	MOVE     	0 1
	54	[317]	SETTABLE 	12 -5 13	; "callback" -
	55	[319]	SETLIST  	11 1 1	; 1
	56	[320]	SETLIST  	9 2 1	; 1
	57	[321]	GETUPVAL 	10 8	; ButtonDialog
	58	[321]	SELF     	10 10 -8	; "new"
	59	[321]	NEWTABLE 	12 0 1
	60	[322]	SETTABLE 	12 -9 9	; "buttons" -
	61	[321]	CALL     	10 3 2
	62	[323]	SETTABLE 	0 -7 10	; "download_dialog" -
	63	[324]	GETUPVAL 	10 1	; UIManager
	64	[324]	SELF     	10 10 -10	; "show"
	65	[324]	GETTABLE 	12 0 -7	; "download_dialog"
	66	[324]	CALL     	10 3 1
	67	[325]	RETURN   	0 1

function <./frontend/apps/cloudstorage/cloudstorage.lua:219,227> (21 instructions, 84 bytes at 0x7f8de340af90)
4 params, 10 slots, 4 upvalues, 4 locals, 6 constants, 1 function
	1	[220]	GETUPVAL 	4 0	; UIManager
	2	[220]	SELF     	4 4 -1	; "scheduleIn"
	3	[220]	LOADK    	6 -2	; 1
	4	[222]	CLOSURE  	7 0	; 0x7f8de340b670
	5	[222]	GETUPVAL 	0 1	; DropBox
	6	[222]	MOVE     	0 0
	7	[222]	MOVE     	0 1
	8	[222]	MOVE     	0 2
	9	[222]	MOVE     	0 3
	10	[220]	CALL     	4 4 1
	11	[223]	GETUPVAL 	4 0	; UIManager
	12	[223]	SELF     	4 4 -3	; "show"
	13	[223]	GETUPVAL 	6 2	; InfoMessage
	14	[223]	SELF     	6 6 -4	; "new"
	15	[223]	NEWTABLE 	8 0 2
	16	[224]	GETUPVAL 	9 3	; download_text
	17	[224]	SETTABLE 	8 -5 9	; "text" -
	18	[225]	SETTABLE 	8 -6 -2	; "timeout" 1
	19	[223]	CALL     	6 3 0
	20	[223]	CALL     	4 0 1
	21	[227]	RETURN   	0 1

function <./frontend/apps/cloudstorage/cloudstorage.lua:220,222> (8 instructions, 32 bytes at 0x7f8de340b670)
0 params, 6 slots, 5 upvalues, 0 locals, 1 constant, 0 functions
	1	[221]	GETUPVAL 	0 0	; DropBox
	2	[221]	SELF     	0 0 -1	; "downloadFile"
	3	[221]	GETUPVAL 	2 1	; unit_item
	4	[221]	GETUPVAL 	3 2	; password
	5	[221]	GETUPVAL 	4 3	; path_dir
	6	[221]	GETUPVAL 	5 4	; callback_close
	7	[221]	CALL     	0 6 1
	8	[222]	RETURN   	0 1

function <./frontend/apps/cloudstorage/cloudstorage.lua:229,237> (23 instructions, 92 bytes at 0x7f8de340b4f0)
6 params, 12 slots, 4 upvalues, 6 locals, 6 constants, 1 function
	1	[230]	GETUPVAL 	6 0	; UIManager
	2	[230]	SELF     	6 6 -1	; "scheduleIn"
	3	[230]	LOADK    	8 -2	; 1
	4	[232]	CLOSURE  	9 0	; 0x7f8de340bdd0
	5	[232]	GETUPVAL 	0 1	; Ftp
	6	[232]	MOVE     	0 0
	7	[232]	MOVE     	0 1
	8	[232]	MOVE     	0 2
	9	[232]	MOVE     	0 3
	10	[232]	MOVE     	0 4
	11	[232]	MOVE     	0 5
	12	[230]	CALL     	6 4 1
	13	[233]	GETUPVAL 	6 0	; UIManager
	14	[233]	SELF     	6 6 -3	; "show"
	15	[233]	GETUPVAL 	8 2	; InfoMessage
	16	[233]	SELF     	8 8 -4	; "new"
	17	[233]	NEWTABLE 	10 0 2
	18	[234]	GETUPVAL 	11 3	; download_text
	19	[234]	SETTABLE 	10 -5 11	; "text" -
	20	[235]	SETTABLE 	10 -6 -2	; "timeout" 1
	21	[233]	CALL     	8 3 0
	22	[233]	CALL     	6 0 1
	23	[237]	RETURN   	0 1

function <./frontend/apps/cloudstorage/cloudstorage.lua:230,232> (10 instructions, 40 bytes at 0x7f8de340bdd0)
0 params, 8 slots, 7 upvalues, 0 locals, 1 constant, 0 functions
	1	[231]	GETUPVAL 	0 0	; Ftp
	2	[231]	SELF     	0 0 -1	; "downloadFile"
	3	[231]	GETUPVAL 	2 1	; unit_item
	4	[231]	GETUPVAL 	3 2	; address
	5	[231]	GETUPVAL 	4 3	; username
	6	[231]	GETUPVAL 	5 4	; password
	7	[231]	GETUPVAL 	6 5	; path_dir
	8	[231]	GETUPVAL 	7 6	; callback_close
	9	[231]	CALL     	0 8 1
	10	[232]	RETURN   	0 1

function <./frontend/apps/cloudstorage/cloudstorage.lua:239,247> (23 instructions, 92 bytes at 0x7f8de340c670)
6 params, 12 slots, 4 upvalues, 6 locals, 6 constants, 1 function
	1	[240]	GETUPVAL 	6 0	; UIManager
	2	[240]	SELF     	6 6 -1	; "scheduleIn"
	3	[240]	LOADK    	8 -2	; 1
	4	[242]	CLOSURE  	9 0	; 0x7f8de340c860
	5	[242]	GETUPVAL 	0 1	; WebDav
	6	[242]	MOVE     	0 0
	7	[242]	MOVE     	0 1
	8	[242]	MOVE     	0 2
	9	[242]	MOVE     	0 3
	10	[242]	MOVE     	0 4
	11	[242]	MOVE     	0 5
	12	[240]	CALL     	6 4 1
	13	[243]	GETUPVAL 	6 0	; UIManager
	14	[243]	SELF     	6 6 -3	; "show"
	15	[243]	GETUPVAL 	8 2	; InfoMessage
	16	[243]	SELF     	8 8 -4	; "new"
	17	[243]	NEWTABLE 	10 0 2
	18	[244]	GETUPVAL 	11 3	; download_text
	19	[244]	SETTABLE 	10 -5 11	; "text" -
	20	[245]	SETTABLE 	10 -6 -2	; "timeout" 1
	21	[243]	CALL     	8 3 0
	22	[243]	CALL     	6 0 1
	23	[247]	RETURN   	0 1

function <./frontend/apps/cloudstorage/cloudstorage.lua:240,242> (10 instructions, 40 bytes at 0x7f8de340c860)
0 params, 8 slots, 7 upvalues, 0 locals, 1 constant, 0 functions
	1	[241]	GETUPVAL 	0 0	; WebDav
	2	[241]	SELF     	0 0 -1	; "downloadFile"
	3	[241]	GETUPVAL 	2 1	; unit_item
	4	[241]	GETUPVAL 	3 2	; address
	5	[241]	GETUPVAL 	4 3	; username
	6	[241]	GETUPVAL 	5 4	; password
	7	[241]	GETUPVAL 	6 5	; path_dir
	8	[241]	GETUPVAL 	7 6	; callback_close
	9	[241]	CALL     	0 8 1
	10	[242]	RETURN   	0 1

function <./frontend/apps/cloudstorage/cloudstorage.lua:255,302> (137 instructions, 548 bytes at 0x7f8de340cff0)
0 params, 8 slots, 11 upvalues, 3 locals, 14 constants, 6 functions
	1	[256]	GETUPVAL 	0 0	; self
	2	[256]	GETTABLE 	0 0 -1	; "type"
	3	[256]	EQ       	0 0 -2	; - "dropbox"
	4	[256]	JMP      	39	; to 44
	5	[259]	CLOSURE  	0 0	; 0x7f8de3409590
	6	[259]	GETUPVAL 	0 0	; self
	7	[260]	GETUPVAL 	1 1	; UIManager
	8	[260]	SELF     	1 1 -3	; "close"
	9	[260]	GETUPVAL 	3 0	; self
	10	[260]	GETTABLE 	3 3 -4	; "download_dialog"
	11	[260]	CALL     	1 3 1
	12	[261]	GETUPVAL 	1 2	; lfs
	13	[261]	GETTABLE 	1 1 -5	; "attributes"
	14	[261]	GETUPVAL 	2 3	; path
	15	[261]	CALL     	1 2 2
	16	[261]	TEST     	1 0 0
	17	[261]	JMP      	17	; to 35
	18	[262]	GETUPVAL 	1 1	; UIManager
	19	[262]	SELF     	1 1 -6	; "show"
	20	[262]	GETUPVAL 	3 4	; ConfirmBox
	21	[262]	SELF     	3 3 -7	; "new"
	22	[262]	NEWTABLE 	5 0 2
	23	[263]	GETUPVAL 	6 5	; overwrite_text
	24	[263]	SETTABLE 	5 -8 6	; "text" -
	25	[266]	CLOSURE  	6 1	; 0x7f8de340ca30
	26	[266]	GETUPVAL 	0 6	; dropboxDownloadFile
	27	[266]	GETUPVAL 	0 7	; item
	28	[266]	GETUPVAL 	0 0	; self
	29	[266]	GETUPVAL 	0 8	; path_dir
	30	[266]	MOVE     	0 0
	31	[266]	SETTABLE 	5 -9 6	; "ok_callback" -
	32	[262]	CALL     	3 3 0
	33	[262]	CALL     	1 0 1
	34	[267]	JMP      	7	; to 42
	35	[269]	GETUPVAL 	1 6	; dropboxDownloadFile
	36	[269]	GETUPVAL 	2 7	; item
	37	[269]	GETUPVAL 	3 0	; self
	38	[269]	GETTABLE 	3 3 -10	; "password"
	39	[269]	GETUPVAL 	4 8	; path_dir
	40	[269]	MOVE     	5 0
	41	[269]	CALL     	1 5 1
	42	[270]	CLOSE    	0
	43	[270]	JMP      	93	; to 137
	44	[271]	GETUPVAL 	0 0	; self
	45	[271]	GETTABLE 	0 0 -1	; "type"
	46	[271]	EQ       	0 0 -11	; - "ftp"
	47	[271]	JMP      	43	; to 91
	48	[274]	CLOSURE  	0 2	; 0x7f8de34093c0
	49	[274]	GETUPVAL 	0 0	; self
	50	[275]	GETUPVAL 	1 1	; UIManager
	51	[275]	SELF     	1 1 -3	; "close"
	52	[275]	GETUPVAL 	3 0	; self
	53	[275]	GETTABLE 	3 3 -4	; "download_dialog"
	54	[275]	CALL     	1 3 1
	55	[276]	GETUPVAL 	1 2	; lfs
	56	[276]	GETTABLE 	1 1 -5	; "attributes"
	57	[276]	GETUPVAL 	2 3	; path
	58	[276]	CALL     	1 2 2
	59	[276]	TEST     	1 0 0
	60	[276]	JMP      	17	; to 78
	61	[277]	GETUPVAL 	1 1	; UIManager
	62	[277]	SELF     	1 1 -6	; "show"
	63	[277]	GETUPVAL 	3 4	; ConfirmBox
	64	[277]	SELF     	3 3 -7	; "new"
	65	[277]	NEWTABLE 	5 0 2
	66	[278]	GETUPVAL 	6 5	; overwrite_text
	67	[278]	SETTABLE 	5 -8 6	; "text" -
	68	[281]	CLOSURE  	6 3	; 0x7f8de340d100
	69	[281]	GETUPVAL 	0 9	; ftpDownloadFile
	70	[281]	GETUPVAL 	0 7	; item
	71	[281]	GETUPVAL 	0 0	; self
	72	[281]	GETUPVAL 	0 8	; path_dir
	73	[281]	MOVE     	0 0
	74	[281]	SETTABLE 	5 -9 6	; "ok_callback" -
	75	[277]	CALL     	3 3 0
	76	[277]	CALL     	1 0 1
	77	[282]	JMP      	11	; to 89
	78	[284]	GETUPVAL 	1 9	; ftpDownloadFile
	79	[284]	GETUPVAL 	2 7	; item
	80	[284]	GETUPVAL 	3 0	; self
	81	[284]	GETTABLE 	3 3 -12	; "address"
	82	[284]	GETUPVAL 	4 0	; self
	83	[284]	GETTABLE 	4 4 -13	; "username"
	84	[284]	GETUPVAL 	5 0	; self
	85	[284]	GETTABLE 	5 5 -10	; "password"
	86	[284]	GETUPVAL 	6 8	; path_dir
	87	[284]	MOVE     	7 0
	88	[284]	CALL     	1 7 1
	89	[285]	CLOSE    	0
	90	[285]	JMP      	46	; to 137
	91	[286]	GETUPVAL 	0 0	; self
	92	[286]	GETTABLE 	0 0 -1	; "type"
	93	[286]	EQ       	0 0 -14	; - "webdav"
	94	[286]	JMP      	42	; to 137
	95	[289]	CLOSURE  	0 4	; 0x7f8de340d510
	96	[289]	GETUPVAL 	0 0	; self
	97	[290]	GETUPVAL 	1 1	; UIManager
	98	[290]	SELF     	1 1 -3	; "close"
	99	[290]	GETUPVAL 	3 0	; self
	100	[290]	GETTABLE 	3 3 -4	; "download_dialog"
	101	[290]	CALL     	1 3 1
	102	[291]	GETUPVAL 	1 2	; lfs
	103	[291]	GETTABLE 	1 1 -5	; "attributes"
	104	[291]	GETUPVAL 	2 3	; path
	105	[291]	CALL     	1 2 2
	106	[291]	TEST     	1 0 0
	107	[291]	JMP      	17	; to 125
	108	[292]	GETUPVAL 	1 1	; UIManager
	109	[292]	SELF     	1 1 -6	; "show"
	110	[292]	GETUPVAL 	3 4	; ConfirmBox
	111	[292]	SELF     	3 3 -7	; "new"
	112	[292]	NEWTABLE 	5 0 2
	113	[293]	GETUPVAL 	6 5	; overwrite_text
	114	[293]	SETTABLE 	5 -8 6	; "text" -
	115	[296]	CLOSURE  	6 5	; 0x7f8de340de50
	116	[296]	GETUPVAL 	0 10	; webdavDownloadFile
	117	[296]	GETUPVAL 	0 7	; item
	118	[296]	GETUPVAL 	0 0	; self
	119	[296]	GETUPVAL 	0 8	; path_dir
	120	[296]	MOVE     	0 0
	121	[296]	SETTABLE 	5 -9 6	; "ok_callback" -
	122	[292]	CALL     	3 3 0
	123	[292]	CALL     	1 0 1
	124	[297]	JMP      	11	; to 136
	125	[299]	GETUPVAL 	1 10	; webdavDownloadFile
	126	[299]	GETUPVAL 	2 7	; item
	127	[299]	GETUPVAL 	3 0	; self
	128	[299]	GETTABLE 	3 3 -12	; "address"
	129	[299]	GETUPVAL 	4 0	; self
	130	[299]	GETTABLE 	4 4 -13	; "username"
	131	[299]	GETUPVAL 	5 0	; self
	132	[299]	GETTABLE 	5 5 -10	; "password"
	133	[299]	GETUPVAL 	6 8	; path_dir
	134	[299]	MOVE     	7 0
	135	[299]	CALL     	1 7 1
	136	[300]	CLOSE    	0
	137	[302]	RETURN   	0 1

function <./frontend/apps/cloudstorage/cloudstorage.lua:257,259> (4 instructions, 16 bytes at 0x7f8de3409590)
0 params, 2 slots, 1 upvalue, 0 locals, 1 constant, 0 functions
	1	[258]	GETUPVAL 	0 0	; self
	2	[258]	SELF     	0 0 -1	; "onClose"
	3	[258]	CALL     	0 2 1
	4	[259]	RETURN   	0 1

function <./frontend/apps/cloudstorage/cloudstorage.lua:264,266> (8 instructions, 32 bytes at 0x7f8de340ca30)
0 params, 5 slots, 5 upvalues, 0 locals, 1 constant, 0 functions
	1	[265]	GETUPVAL 	0 0	; dropboxDownloadFile
	2	[265]	GETUPVAL 	1 1	; item
	3	[265]	GETUPVAL 	2 2	; self
	4	[265]	GETTABLE 	2 2 -1	; "password"
	5	[265]	GETUPVAL 	3 3	; path_dir
	6	[265]	GETUPVAL 	4 4	; callback_close
	7	[265]	CALL     	0 5 1
	8	[266]	RETURN   	0 1

function <./frontend/apps/cloudstorage/cloudstorage.lua:272,274> (4 instructions, 16 bytes at 0x7f8de34093c0)
0 params, 2 slots, 1 upvalue, 0 locals, 1 constant, 0 functions
	1	[273]	GETUPVAL 	0 0	; self
	2	[273]	SELF     	0 0 -1	; "onClose"
	3	[273]	CALL     	0 2 1
	4	[274]	RETURN   	0 1

function <./frontend/apps/cloudstorage/cloudstorage.lua:279,281> (12 instructions, 48 bytes at 0x7f8de340d100)
0 params, 7 slots, 5 upvalues, 0 locals, 3 constants, 0 functions
	1	[280]	GETUPVAL 	0 0	; ftpDownloadFile
	2	[280]	GETUPVAL 	1 1	; item
	3	[280]	GETUPVAL 	2 2	; self
	4	[280]	GETTABLE 	2 2 -1	; "address"
	5	[280]	GETUPVAL 	3 2	; self
	6	[280]	GETTABLE 	3 3 -2	; "username"
	7	[280]	GETUPVAL 	4 2	; self
	8	[280]	GETTABLE 	4 4 -3	; "password"
	9	[280]	GETUPVAL 	5 3	; path_dir
	10	[280]	GETUPVAL 	6 4	; callback_close
	11	[280]	CALL     	0 7 1
	12	[281]	RETURN   	0 1

function <./frontend/apps/cloudstorage/cloudstorage.lua:287,289> (4 instructions, 16 bytes at 0x7f8de340d510)
0 params, 2 slots, 1 upvalue, 0 locals, 1 constant, 0 functions
	1	[288]	GETUPVAL 	0 0	; self
	2	[288]	SELF     	0 0 -1	; "onClose"
	3	[288]	CALL     	0 2 1
	4	[289]	RETURN   	0 1

function <./frontend/apps/cloudstorage/cloudstorage.lua:294,296> (12 instructions, 48 bytes at 0x7f8de340de50)
0 params, 7 slots, 5 upvalues, 0 locals, 3 constants, 0 functions
	1	[295]	GETUPVAL 	0 0	; webdavDownloadFile
	2	[295]	GETUPVAL 	1 1	; item
	3	[295]	GETUPVAL 	2 2	; self
	4	[295]	GETTABLE 	2 2 -1	; "address"
	5	[295]	GETUPVAL 	3 2	; self
	6	[295]	GETTABLE 	3 3 -2	; "username"
	7	[295]	GETUPVAL 	4 2	; self
	8	[295]	GETTABLE 	4 4 -3	; "password"
	9	[295]	GETUPVAL 	5 3	; path_dir
	10	[295]	GETUPVAL 	6 4	; callback_close
	11	[295]	CALL     	0 7 1
	12	[296]	RETURN   	0 1

function <./frontend/apps/cloudstorage/cloudstorage.lua:308,317> (19 instructions, 76 bytes at 0x7f8de340ce70)
0 params, 6 slots, 3 upvalues, 0 locals, 8 constants, 1 function
	1	[309]	GETGLOBAL	0 -1	; require
	2	[309]	LOADK    	1 -2	; "ui/downloadmgr"
	3	[309]	CALL     	0 2 2
	4	[309]	SELF     	0 0 -3	; "new"
	5	[309]	NEWTABLE 	2 0 2
	6	[310]	GETGLOBAL	3 -5	; G_reader_settings
	7	[310]	SELF     	3 3 -6	; "readSetting"
	8	[310]	LOADK    	5 -4	; "show_hidden"
	9	[310]	CALL     	3 3 2
	10	[310]	SETTABLE 	2 -4 3	; "show_hidden" -
	11	[315]	CLOSURE  	3 0	; 0x7f8de340d790
	12	[315]	GETUPVAL 	0 0	; self
	13	[315]	GETUPVAL 	0 1	; path_dir
	14	[315]	GETUPVAL 	0 2	; item
	15	[315]	SETTABLE 	2 -7 3	; "onConfirm" -
	16	[309]	CALL     	0 3 2
	17	[316]	SELF     	0 0 -8	; "chooseDir"
	18	[316]	CALL     	0 2 1
	19	[317]	RETURN   	0 1

function <./frontend/apps/cloudstorage/cloudstorage.lua:311,315> (17 instructions, 68 bytes at 0x7f8de340d790)
1 param, 5 slots, 3 upvalues, 1 local, 6 constants, 0 functions
	1	[312]	GETUPVAL 	1 0	; self
	2	[312]	GETTABLE 	1 1 -1	; "cs_settings"
	3	[312]	SELF     	1 1 -2	; "saveSetting"
	4	[312]	LOADK    	3 -3	; "download_dir"
	5	[312]	MOVE     	4 0
	6	[312]	CALL     	1 4 1
	7	[313]	GETUPVAL 	1 0	; self
	8	[313]	GETTABLE 	1 1 -1	; "cs_settings"
	9	[313]	SELF     	1 1 -4	; "flush"
	10	[313]	CALL     	1 2 1
	11	[314]	MOVE     	1 0
	12	[314]	LOADK    	2 -5	; "/"
	13	[314]	GETUPVAL 	3 2	; item
	14	[314]	GETTABLE 	3 3 -6	; "text"
	15	[314]	CONCAT   	1 1 3
	16	[314]	SETUPVAL 	1 1	; path_dir
	17	[315]	RETURN   	0 1

function <./frontend/apps/cloudstorage/cloudstorage.lua:327,343> (40 instructions, 160 bytes at 0x7f8de340af10)
4 params, 13 slots, 0 upvalues, 11 locals, 12 constants, 0 functions
	1	[328]	SELF     	4 0 -1	; "readSettings"
	2	[328]	CALL     	4 2 2
	3	[329]	SELF     	5 4 -2	; "readSetting"
	4	[329]	LOADK    	7 -3	; "cs_servers"
	5	[329]	CALL     	5 3 2
	6	[329]	TEST     	5 0 1
	7	[329]	JMP      	1	; to 9
	8	[329]	NEWTABLE 	5 0 0
	9	[330]	GETGLOBAL	6 -4	; ipairs
	10	[330]	MOVE     	7 5
	11	[330]	CALL     	6 2 4
	12	[330]	JMP      	19	; to 32
	13	[331]	GETTABLE 	11 10 -5	; "name"
	14	[331]	GETTABLE 	12 1 -6	; "text"
	15	[331]	EQ       	0 11 12
	16	[331]	JMP      	15	; to 32
	17	[331]	GETTABLE 	11 10 -7	; "password"
	18	[331]	GETTABLE 	12 1 -7	; "password"
	19	[331]	EQ       	0 11 12
	20	[331]	JMP      	11	; to 32
	21	[331]	GETTABLE 	11 10 -8	; "type"
	22	[331]	GETTABLE 	12 1 -8	; "type"
	23	[331]	EQ       	0 11 12
	24	[331]	JMP      	7	; to 32
	25	[332]	TEST     	2 0 0
	26	[332]	JMP      	1	; to 28
	27	[333]	SETTABLE 	10 -9 2	; "sync_source_folder" -
	28	[335]	TEST     	3 0 0
	29	[335]	JMP      	4	; to 34
	30	[336]	SETTABLE 	10 -10 3	; "sync_dest_folder" -
	31	[338]	JMP      	2	; to 34
	32	[330]	TFORLOOP 	6 2
	33	[339]	JMP      	-21	; to 13
	34	[341]	SELF     	6 4 -11	; "saveSetting"
	35	[341]	LOADK    	8 -3	; "cs_servers"
	36	[341]	MOVE     	9 5
	37	[341]	CALL     	6 4 1
	38	[342]	SELF     	6 4 -12	; "flush"
	39	[342]	CALL     	6 2 1
	40	[343]	RETURN   	0 1

function <./frontend/apps/cloudstorage/cloudstorage.lua:345,432> (150 instructions, 600 bytes at 0x7f8de340d690)
2 params, 14 slots, 6 upvalues, 7 locals, 28 constants, 7 functions
	1	[346]	GETTABLE 	2 1 -1	; "type"
	2	[346]	EQ       	0 2 -2	; - "folder_long_press"
	3	[346]	JMP      	48	; to 52
	4	[347]	GETUPVAL 	2 0	; T
	5	[347]	GETUPVAL 	3 1	; _
	6	[347]	LOADK    	4 -3	; "Select this directory?\n\n%1"
	7	[347]	CALL     	3 2 2
	8	[347]	GETUPVAL 	4 2	; BD
	9	[347]	GETTABLE 	4 4 -4	; "dirpath"
	10	[347]	GETTABLE 	5 1 -5	; "url"
	11	[347]	CALL     	4 2 0
	12	[347]	CALL     	2 0 2
	13	[348]	GETTABLE 	3 0 -6	; "onConfirm"
	14	[349]	LOADNIL  	4 4
	15	[350]	GETUPVAL 	5 3	; ButtonDialogTitle
	16	[350]	SELF     	5 5 -7	; "new"
	17	[350]	NEWTABLE 	7 0 2
	18	[351]	SETTABLE 	7 -8 2	; "title" -
	19	[352]	NEWTABLE 	8 1 0
	20	[352]	NEWTABLE 	9 2 0
	21	[353]	NEWTABLE 	10 0 2
	22	[355]	GETUPVAL 	11 1	; _
	23	[355]	LOADK    	12 -11	; "Cancel"
	24	[355]	CALL     	11 2 2
	25	[355]	SETTABLE 	10 -10 11	; "text" -
	26	[358]	CLOSURE  	11 0	; 0x7f8de340f540
	27	[358]	GETUPVAL 	0 4	; UIManager
	28	[358]	MOVE     	0 4
	29	[358]	SETTABLE 	10 -12 11	; "callback" -
	30	[359]	NEWTABLE 	11 0 2
	31	[361]	GETUPVAL 	12 1	; _
	32	[361]	LOADK    	13 -13	; "Select"
	33	[361]	CALL     	12 2 2
	34	[361]	SETTABLE 	11 -10 12	; "text" -
	35	[368]	CLOSURE  	12 1	; 0x7f8de340f6c0
	36	[368]	MOVE     	0 3
	37	[368]	MOVE     	0 1
	38	[368]	GETUPVAL 	0 4	; UIManager
	39	[368]	MOVE     	0 4
	40	[368]	MOVE     	0 0
	41	[368]	SETTABLE 	11 -12 12	; "callback" -
	42	[370]	SETLIST  	9 2 1	; 1
	43	[371]	SETLIST  	8 1 1	; 1
	44	[371]	SETTABLE 	7 -9 8	; "buttons" -
	45	[350]	CALL     	5 3 2
	46	[372]	MOVE     	4 5
	47	[373]	GETUPVAL 	5 4	; UIManager
	48	[373]	SELF     	5 5 -14	; "show"
	49	[373]	MOVE     	7 4
	50	[373]	CALL     	5 3 1
	51	[373]	CLOSE    	2
	52	[375]	GETTABLE 	2 1 -15	; "editable"
	53	[375]	TEST     	2 0 0
	54	[375]	JMP      	95	; to 150
	55	[376]	LOADNIL  	2 2
	56	[377]	NEWTABLE 	3 1 0
	57	[377]	NEWTABLE 	4 3 0
	58	[378]	NEWTABLE 	5 0 3
	59	[380]	GETUPVAL 	6 1	; _
	60	[380]	LOADK    	7 -16	; "Info"
	61	[380]	CALL     	6 2 2
	62	[380]	SETTABLE 	5 -10 6	; "text" -
	63	[381]	SETTABLE 	5 -17 -18	; "enabled" true
	64	[385]	CLOSURE  	6 2	; 0x7f8de340f740
	65	[385]	GETUPVAL 	0 4	; UIManager
	66	[385]	MOVE     	0 2
	67	[385]	MOVE     	0 0
	68	[385]	MOVE     	0 1
	69	[385]	SETTABLE 	5 -12 6	; "callback" -
	70	[386]	NEWTABLE 	6 0 3
	71	[388]	GETUPVAL 	7 1	; _
	72	[388]	LOADK    	8 -19	; "Edit"
	73	[388]	CALL     	7 2 2
	74	[388]	SETTABLE 	6 -10 7	; "text" -
	75	[389]	SETTABLE 	6 -17 -18	; "enabled" true
	76	[394]	CLOSURE  	7 3	; 0x7f8de340f9b0
	77	[394]	GETUPVAL 	0 4	; UIManager
	78	[394]	MOVE     	0 2
	79	[394]	MOVE     	0 0
	80	[394]	MOVE     	0 1
	81	[394]	SETTABLE 	6 -12 7	; "callback" -
	82	[395]	NEWTABLE 	7 0 3
	83	[397]	GETUPVAL 	8 1	; _
	84	[397]	LOADK    	9 -20	; "Delete"
	85	[397]	CALL     	8 2 2
	86	[397]	SETTABLE 	7 -10 8	; "text" -
	87	[398]	SETTABLE 	7 -17 -18	; "enabled" true
	88	[402]	CLOSURE  	8 4	; 0x7f8de340fb00
	89	[402]	GETUPVAL 	0 4	; UIManager
	90	[402]	MOVE     	0 2
	91	[402]	MOVE     	0 0
	92	[402]	MOVE     	0 1
	93	[402]	SETTABLE 	7 -12 8	; "callback" -
	94	[404]	SETLIST  	4 3 1	; 1
	95	[405]	SETLIST  	3 1 1	; 1
	96	[406]	GETTABLE 	4 1 -1	; "type"
	97	[406]	EQ       	0 4 -21	; - "dropbox"
	98	[406]	JMP      	38	; to 137
	99	[407]	GETGLOBAL	4 -22	; table
	100	[407]	GETTABLE 	4 4 -23	; "insert"
	101	[407]	MOVE     	5 3
	102	[407]	NEWTABLE 	6 2 0
	103	[407]	NEWTABLE 	7 0 3
	104	[409]	GETUPVAL 	8 1	; _
	105	[409]	LOADK    	9 -24	; "Synchronize now"
	106	[409]	CALL     	8 2 2
	107	[409]	SETTABLE 	7 -10 8	; "text" -
	108	[410]	GETTABLE 	8 1 -25	; "sync_source_folder"
	109	[410]	EQ       	1 8 -26	; - nil
	110	[410]	JMP      	3	; to 114
	111	[410]	GETTABLE 	8 1 -27	; "sync_dest_folder"
	112	[410]	EQ       	0 8 -26	; - nil
	113	[410]	JMP      	1	; to 115
	114	[410]	LOADBOOL 	8 0 1
	115	[410]	LOADBOOL 	8 1 0
	116	[410]	SETTABLE 	7 -17 8	; "enabled" -
	117	[414]	CLOSURE  	8 5	; 0x7f8de3409a70
	118	[414]	GETUPVAL 	0 4	; UIManager
	119	[414]	MOVE     	0 2
	120	[414]	MOVE     	0 0
	121	[414]	MOVE     	0 1
	122	[414]	SETTABLE 	7 -12 8	; "callback" -
	123	[415]	NEWTABLE 	8 0 3
	124	[417]	GETUPVAL 	9 1	; _
	125	[417]	LOADK    	10 -28	; "Synchronize settings"
	126	[417]	CALL     	9 2 2
	127	[417]	SETTABLE 	8 -10 9	; "text" -
	128	[418]	SETTABLE 	8 -17 -18	; "enabled" true
	129	[422]	CLOSURE  	9 6	; 0x7f8de340c930
	130	[422]	GETUPVAL 	0 4	; UIManager
	131	[422]	MOVE     	0 2
	132	[422]	MOVE     	0 0
	133	[422]	MOVE     	0 1
	134	[422]	SETTABLE 	8 -12 9	; "callback" -
	135	[424]	SETLIST  	6 2 1	; 1
	136	[407]	CALL     	4 3 1
	137	[426]	GETUPVAL 	4 5	; ButtonDialog
	138	[426]	SELF     	4 4 -7	; "new"
	139	[426]	NEWTABLE 	6 0 1
	140	[427]	SETTABLE 	6 -9 3	; "buttons" -
	141	[426]	CALL     	4 3 2
	142	[428]	MOVE     	2 4
	143	[429]	GETUPVAL 	4 4	; UIManager
	144	[429]	SELF     	4 4 -14	; "show"
	145	[429]	MOVE     	6 2
	146	[429]	CALL     	4 3 1
	147	[430]	LOADBOOL 	4 1 0
	148	[430]	RETURN   	4 2
	149	[430]	CLOSE    	2
	150	[432]	RETURN   	0 1

function <./frontend/apps/cloudstorage/cloudstorage.lua:356,358> (5 instructions, 20 bytes at 0x7f8de340f540)
0 params, 3 slots, 2 upvalues, 0 locals, 1 constant, 0 functions
	1	[357]	GETUPVAL 	0 0	; UIManager
	2	[357]	SELF     	0 0 -1	; "close"
	3	[357]	GETUPVAL 	2 1	; button_dialog
	4	[357]	CALL     	0 3 1
	5	[358]	RETURN   	0 1

function <./frontend/apps/cloudstorage/cloudstorage.lua:362,368> (16 instructions, 64 bytes at 0x7f8de340f6c0)
0 params, 3 slots, 5 upvalues, 0 locals, 2 constants, 0 functions
	1	[363]	GETUPVAL 	0 0	; onConfirm
	2	[363]	TEST     	0 0 0
	3	[363]	JMP      	4	; to 8
	4	[364]	GETUPVAL 	0 0	; onConfirm
	5	[364]	GETUPVAL 	1 1	; item
	6	[364]	GETTABLE 	1 1 -1	; "url"
	7	[364]	CALL     	0 2 1
	8	[366]	GETUPVAL 	0 2	; UIManager
	9	[366]	SELF     	0 0 -2	; "close"
	10	[366]	GETUPVAL 	2 3	; button_dialog
	11	[366]	CALL     	0 3 1
	12	[367]	GETUPVAL 	0 2	; UIManager
	13	[367]	SELF     	0 0 -2	; "close"
	14	[367]	GETUPVAL 	2 4	; self
	15	[367]	CALL     	0 3 1
	16	[368]	RETURN   	0 1

function <./frontend/apps/cloudstorage/cloudstorage.lua:382,385> (9 instructions, 36 bytes at 0x7f8de340f740)
0 params, 3 slots, 4 upvalues, 0 locals, 2 constants, 0 functions
	1	[383]	GETUPVAL 	0 0	; UIManager
	2	[383]	SELF     	0 0 -1	; "close"
	3	[383]	GETUPVAL 	2 1	; cs_server_dialog
	4	[383]	CALL     	0 3 1
	5	[384]	GETUPVAL 	0 2	; self
	6	[384]	SELF     	0 0 -2	; "infoServer"
	7	[384]	GETUPVAL 	2 3	; item
	8	[384]	CALL     	0 3 1
	9	[385]	RETURN   	0 1

function <./frontend/apps/cloudstorage/cloudstorage.lua:390,394> (9 instructions, 36 bytes at 0x7f8de340f9b0)
0 params, 3 slots, 4 upvalues, 0 locals, 2 constants, 0 functions
	1	[391]	GETUPVAL 	0 0	; UIManager
	2	[391]	SELF     	0 0 -1	; "close"
	3	[391]	GETUPVAL 	2 1	; cs_server_dialog
	4	[391]	CALL     	0 3 1
	5	[392]	GETUPVAL 	0 2	; self
	6	[392]	SELF     	0 0 -2	; "editCloudServer"
	7	[392]	GETUPVAL 	2 3	; item
	8	[392]	CALL     	0 3 1
	9	[394]	RETURN   	0 1

function <./frontend/apps/cloudstorage/cloudstorage.lua:399,402> (9 instructions, 36 bytes at 0x7f8de340fb00)
0 params, 3 slots, 4 upvalues, 0 locals, 2 constants, 0 functions
	1	[400]	GETUPVAL 	0 0	; UIManager
	2	[400]	SELF     	0 0 -1	; "close"
	3	[400]	GETUPVAL 	2 1	; cs_server_dialog
	4	[400]	CALL     	0 3 1
	5	[401]	GETUPVAL 	0 2	; self
	6	[401]	SELF     	0 0 -2	; "deleteCloudServer"
	7	[401]	GETUPVAL 	2 3	; item
	8	[401]	CALL     	0 3 1
	9	[402]	RETURN   	0 1

function <./frontend/apps/cloudstorage/cloudstorage.lua:411,414> (9 instructions, 36 bytes at 0x7f8de3409a70)
0 params, 3 slots, 4 upvalues, 0 locals, 2 constants, 0 functions
	1	[412]	GETUPVAL 	0 0	; UIManager
	2	[412]	SELF     	0 0 -1	; "close"
	3	[412]	GETUPVAL 	2 1	; cs_server_dialog
	4	[412]	CALL     	0 3 1
	5	[413]	GETUPVAL 	0 2	; self
	6	[413]	SELF     	0 0 -2	; "synchronizeCloud"
	7	[413]	GETUPVAL 	2 3	; item
	8	[413]	CALL     	0 3 1
	9	[414]	RETURN   	0 1

function <./frontend/apps/cloudstorage/cloudstorage.lua:419,422> (9 instructions, 36 bytes at 0x7f8de340c930)
0 params, 3 slots, 4 upvalues, 0 locals, 2 constants, 0 functions
	1	[420]	GETUPVAL 	0 0	; UIManager
	2	[420]	SELF     	0 0 -1	; "close"
	3	[420]	GETUPVAL 	2 1	; cs_server_dialog
	4	[420]	CALL     	0 3 1
	5	[421]	GETUPVAL 	0 2	; self
	6	[421]	SELF     	0 0 -2	; "synchronizeSettings"
	7	[421]	GETUPVAL 	2 3	; item
	8	[421]	CALL     	0 3 1
	9	[422]	RETURN   	0 1

function <./frontend/apps/cloudstorage/cloudstorage.lua:434,462> (14 instructions, 56 bytes at 0x7f8de340d5f0)
2 params, 6 slots, 4 upvalues, 3 locals, 3 constants, 1 function
	1	[435]	GETGLOBAL	2 -1	; require
	2	[435]	LOADK    	3 -2	; "ui/trapper"
	3	[435]	CALL     	2 2 2
	4	[436]	SELF     	3 2 -3	; "wrap"
	5	[461]	CLOSURE  	5 0	; 0x7f8de3410940
	6	[461]	MOVE     	0 2
	7	[461]	MOVE     	0 0
	8	[461]	MOVE     	0 1
	9	[461]	GETUPVAL 	0 0	; _
	10	[461]	GETUPVAL 	0 1	; T
	11	[461]	GETUPVAL 	0 2	; UIManager
	12	[461]	GETUPVAL 	0 3	; InfoMessage
	13	[436]	CALL     	3 3 1
	14	[462]	RETURN   	0 1

function <./frontend/apps/cloudstorage/cloudstorage.lua:436,461> (73 instructions, 292 bytes at 0x7f8de3410940)
0 params, 10 slots, 7 upvalues, 4 locals, 15 constants, 0 functions
	1	[437]	GETUPVAL 	0 0	; Trapper
	2	[437]	SELF     	0 0 -1	; "setPausedText"
	3	[437]	LOADK    	2 -2	; "Download paused.\nDo you want to continue or abort downloading files?"
	4	[437]	CALL     	0 3 1
	5	[438]	GETGLOBAL	0 -3	; pcall
	6	[438]	GETUPVAL 	1 1	; self
	7	[438]	GETTABLE 	1 1 -4	; "downloadListFiles"
	8	[438]	GETUPVAL 	2 1	; self
	9	[438]	GETUPVAL 	3 2	; item
	10	[438]	CALL     	0 4 4
	11	[439]	TEST     	0 0 0
	12	[439]	JMP      	45	; to 58
	13	[439]	TEST     	1 0 0
	14	[439]	JMP      	43	; to 58
	15	[440]	TEST     	2 0 1
	16	[440]	JMP      	1	; to 18
	17	[440]	LOADK    	2 -5	; 0
	18	[441]	LOADNIL  	3 3
	19	[442]	EQ       	0 1 -5	; - 0
	20	[442]	JMP      	7	; to 28
	21	[442]	EQ       	0 2 -5	; - 0
	22	[442]	JMP      	5	; to 28
	23	[443]	GETUPVAL 	4 3	; _
	24	[443]	LOADK    	5 -6	; "No files to download from Dropbox."
	25	[443]	CALL     	4 2 2
	26	[443]	MOVE     	3 4
	27	[443]	JMP      	20	; to 48
	28	[444]	LT       	0 -5 1	; 0 -
	29	[444]	JMP      	10	; to 40
	30	[444]	EQ       	0 2 -5	; - 0
	31	[444]	JMP      	8	; to 40
	32	[445]	GETUPVAL 	4 4	; T
	33	[445]	GETUPVAL 	5 3	; _
	34	[445]	LOADK    	6 -7	; "Successfully downloaded %1 files from Dropbox to local storage."
	35	[445]	CALL     	5 2 2
	36	[445]	MOVE     	6 1
	37	[445]	CALL     	4 3 2
	38	[445]	MOVE     	3 4
	39	[445]	JMP      	8	; to 48
	40	[447]	GETUPVAL 	4 4	; T
	41	[447]	GETUPVAL 	5 3	; _
	42	[447]	LOADK    	6 -8	; "Successfully downloaded %1 files from Dropbox to local storage.\nFailed to download %2 files."
	43	[447]	CALL     	5 2 2
	44	[448]	MOVE     	6 1
	45	[448]	MOVE     	7 2
	46	[447]	CALL     	4 4 2
	47	[448]	MOVE     	3 4
	48	[450]	GETUPVAL 	4 5	; UIManager
	49	[450]	SELF     	4 4 -9	; "show"
	50	[450]	GETUPVAL 	6 6	; InfoMessage
	51	[450]	SELF     	6 6 -10	; "new"
	52	[450]	NEWTABLE 	8 0 2
	53	[451]	SETTABLE 	8 -11 3	; "text" -
	54	[452]	SETTABLE 	8 -12 -13	; "timeout" 3
	55	[450]	CALL     	6 3 0
	56	[450]	CALL     	4 0 1
	57	[453]	JMP      	15	; to 73
	58	[455]	GETUPVAL 	3 0	; Trapper
	59	[455]	SELF     	3 3 -14	; "reset"
	60	[455]	CALL     	3 2 1
	61	[456]	GETUPVAL 	3 5	; UIManager
	62	[456]	SELF     	3 3 -9	; "show"
	63	[456]	GETUPVAL 	5 6	; InfoMessage
	64	[456]	SELF     	5 5 -10	; "new"
	65	[456]	NEWTABLE 	7 0 2
	66	[457]	GETUPVAL 	8 3	; _
	67	[457]	LOADK    	9 -15	; "No files to download from Dropbox.\nPlease check your configuration and connection."
	68	[457]	CALL     	8 2 2
	69	[457]	SETTABLE 	7 -11 8	; "text" -
	70	[458]	SETTABLE 	7 -12 -13	; "timeout" 3
	71	[456]	CALL     	5 3 0
	72	[456]	CALL     	3 0 1
	73	[461]	RETURN   	0 1

function <./frontend/apps/cloudstorage/cloudstorage.lua:464,521> (125 instructions, 500 bytes at 0x7f8de340c560)
2 params, 28 slots, 3 upvalues, 32 locals, 28 constants, 0 functions
	1	[465]	NEWTABLE 	2 0 0
	2	[466]	GETTABLE 	3 1 -1	; "sync_dest_folder"
	3	[467]	GETGLOBAL	4 -2	; require
	4	[467]	LOADK    	5 -3	; "ui/trapper"
	5	[467]	CALL     	4 2 2
	6	[468]	SELF     	5 4 -4	; "info"
	7	[468]	GETUPVAL 	7 0	; _
	8	[468]	LOADK    	8 -5	; "Retrieving files\226\128\166"
	9	[468]	CALL     	7 2 0
	10	[468]	CALL     	5 0 1
	11	[470]	GETGLOBAL	5 -6	; pcall
	12	[470]	GETUPVAL 	6 1	; lfs
	13	[470]	GETTABLE 	6 6 -7	; "dir"
	14	[470]	MOVE     	7 3
	15	[470]	CALL     	5 3 4
	16	[471]	TEST     	5 0 0
	17	[471]	JMP      	19	; to 37
	18	[472]	MOVE     	8 6
	19	[472]	MOVE     	9 7
	20	[472]	LOADNIL  	10 10
	21	[472]	JMP      	13	; to 35
	22	[473]	MOVE     	12 3
	23	[473]	LOADK    	13 -8	; "/"
	24	[473]	MOVE     	14 11
	25	[473]	CONCAT   	12 12 14
	26	[474]	GETUPVAL 	13 1	; lfs
	27	[474]	GETTABLE 	13 13 -9	; "attributes"
	28	[474]	MOVE     	14 12
	29	[474]	CALL     	13 2 2
	30	[475]	GETTABLE 	14 13 -10	; "mode"
	31	[475]	EQ       	0 14 -11	; - "file"
	32	[475]	JMP      	2	; to 35
	33	[476]	GETTABLE 	14 13 -12	; "size"
	34	[476]	SETTABLE 	2 11 14
	35	[472]	TFORLOOP 	8 1
	36	[477]	JMP      	-15	; to 22
	37	[480]	GETUPVAL 	8 2	; DropBox
	38	[480]	SELF     	8 8 -13	; "showFiles"
	39	[480]	GETTABLE 	10 1 -14	; "sync_source_folder"
	40	[480]	GETTABLE 	11 1 -15	; "password"
	41	[480]	CALL     	8 4 2
	42	[481]	LEN      	9 8
	43	[481]	EQ       	0 9 -16	; - 0
	44	[481]	JMP      	4	; to 49
	45	[482]	SELF     	9 4 -17	; "clear"
	46	[482]	CALL     	9 2 1
	47	[483]	LOADBOOL 	9 0 0
	48	[483]	RETURN   	9 2
	49	[485]	LOADK    	9 -16	; 0
	50	[486]	GETGLOBAL	10 -18	; ipairs
	51	[486]	MOVE     	11 8
	52	[486]	CALL     	10 2 4
	53	[486]	JMP      	12	; to 66
	54	[487]	GETTABLE 	15 14 -19	; "text"
	55	[487]	GETTABLE 	15 2 15
	56	[487]	TEST     	15 0 0
	57	[487]	JMP      	5	; to 63
	58	[487]	GETTABLE 	15 14 -19	; "text"
	59	[487]	GETTABLE 	15 2 15
	60	[487]	GETTABLE 	16 14 -12	; "size"
	61	[487]	EQ       	1 15 16
	62	[487]	JMP      	3	; to 66
	63	[488]	ADD      	9 9 -20	; - 1
	64	[489]	GETTABLE 	15 8 13
	65	[489]	SETTABLE 	15 -21 -22	; "download" true
	66	[486]	TFORLOOP 	10 2
	67	[490]	JMP      	-14	; to 54
	68	[493]	EQ       	0 9 -16	; - 0
	69	[493]	JMP      	4	; to 74
	70	[494]	SELF     	10 4 -17	; "clear"
	71	[494]	CALL     	10 2 1
	72	[495]	LOADK    	10 -16	; 0
	73	[495]	RETURN   	10 2
	74	[498]	LOADNIL  	10 11
	75	[499]	LOADK    	12 -16	; 0
	76	[500]	LOADK    	13 -16	; 0
	77	[501]	LOADK    	14 -16	; 0
	78	[502]	GETGLOBAL	15 -18	; ipairs
	79	[502]	MOVE     	16 8
	80	[502]	CALL     	15 2 4
	81	[502]	JMP      	36	; to 118
	82	[503]	GETTABLE 	20 19 -21	; "download"
	83	[503]	TEST     	20 0 0
	84	[503]	JMP      	33	; to 118
	85	[504]	ADD      	12 12 -20	; - 1
	86	[505]	GETGLOBAL	20 -23	; print
	87	[505]	GETTABLE 	21 19 -24	; "url"
	88	[505]	CALL     	20 2 1
	89	[506]	GETGLOBAL	20 -25	; string
	90	[506]	GETTABLE 	20 20 -26	; "format"
	91	[506]	LOADK    	21 -27	; "Downloading file (%d/%d):\n%s"
	92	[506]	MOVE     	22 12
	93	[506]	MOVE     	23 9
	94	[506]	GETTABLE 	24 19 -19	; "text"
	95	[506]	CALL     	20 5 2
	96	[507]	SELF     	21 4 -4	; "info"
	97	[507]	MOVE     	23 20
	98	[507]	CALL     	21 3 2
	99	[507]	MOVE     	11 21
	100	[508]	TEST     	11 0 1
	101	[508]	JMP      	1	; to 103
	102	[509]	JMP      	17	; to 120
	103	[511]	GETUPVAL 	21 2	; DropBox
	104	[511]	SELF     	21 21 -28	; "downloadFileNoUI"
	105	[511]	GETTABLE 	23 19 -24	; "url"
	106	[511]	GETTABLE 	24 1 -15	; "password"
	107	[511]	GETTABLE 	25 1 -1	; "sync_dest_folder"
	108	[511]	LOADK    	26 -8	; "/"
	109	[511]	GETTABLE 	27 19 -19	; "text"
	110	[511]	CONCAT   	25 25 27
	111	[511]	CALL     	21 5 2
	112	[511]	MOVE     	10 21
	113	[512]	TEST     	10 0 0
	114	[512]	JMP      	2	; to 117
	115	[513]	ADD      	13 13 -20	; - 1
	116	[513]	JMP      	1	; to 118
	117	[515]	ADD      	14 14 -20	; - 1
	118	[502]	TFORLOOP 	15 2
	119	[517]	JMP      	-38	; to 82
	120	[519]	SELF     	15 4 -17	; "clear"
	121	[519]	CALL     	15 2 1
	122	[520]	MOVE     	15 13
	123	[520]	MOVE     	16 14
	124	[520]	RETURN   	15 3
	125	[521]	RETURN   	0 1

function <./frontend/apps/cloudstorage/cloudstorage.lua:523,573> (73 instructions, 292 bytes at 0x7f8de340baf0)
2 params, 15 slots, 5 upvalues, 5 locals, 16 constants, 3 functions
	1	[525]	GETTABLE 	3 1 -1	; "sync_source_folder"
	2	[525]	TEST     	3 0 1
	3	[525]	JMP      	1	; to 5
	4	[525]	LOADK    	3 -2	; "not set"
	5	[526]	GETTABLE 	4 1 -3	; "sync_dest_folder"
	6	[526]	TEST     	4 0 1
	7	[526]	JMP      	1	; to 9
	8	[526]	LOADK    	4 -2	; "not set"
	9	[527]	GETUPVAL 	5 0	; ButtonDialogTitle
	10	[527]	SELF     	5 5 -4	; "new"
	11	[527]	NEWTABLE 	7 0 3
	12	[528]	GETUPVAL 	8 1	; T
	13	[528]	GETUPVAL 	9 2	; _
	14	[528]	LOADK    	10 -6	; "Dropbox folder:\n%1\nLocal folder:\n%2"
	15	[528]	CALL     	9 2 2
	16	[528]	GETUPVAL 	10 3	; BD
	17	[528]	GETTABLE 	10 10 -7	; "dirpath"
	18	[528]	MOVE     	11 3
	19	[528]	CALL     	10 2 2
	20	[528]	GETUPVAL 	11 3	; BD
	21	[528]	GETTABLE 	11 11 -7	; "dirpath"
	22	[528]	MOVE     	12 4
	23	[528]	CALL     	11 2 0
	24	[528]	CALL     	8 0 2
	25	[528]	SETTABLE 	7 -5 8	; "title" -
	26	[529]	SETTABLE 	7 -8 -9	; "title_align" "center"
	27	[530]	NEWTABLE 	8 3 0
	28	[530]	NEWTABLE 	9 1 0
	29	[531]	NEWTABLE 	10 0 2
	30	[533]	GETUPVAL 	11 2	; _
	31	[533]	LOADK    	12 -12	; "Choose Dropbox folder"
	32	[533]	CALL     	11 2 2
	33	[533]	SETTABLE 	10 -11 11	; "text" -
	34	[544]	CLOSURE  	11 0	; 0x7f8de3407650
	35	[544]	GETUPVAL 	0 4	; UIManager
	36	[544]	MOVE     	0 2
	37	[544]	MOVE     	0 1
	38	[544]	MOVE     	0 0
	39	[544]	SETTABLE 	10 -13 11	; "callback" -
	40	[546]	SETLIST  	9 1 1	; 1
	41	[546]	NEWTABLE 	10 1 0
	42	[547]	NEWTABLE 	11 0 2
	43	[549]	GETUPVAL 	12 2	; _
	44	[549]	LOADK    	13 -14	; "Choose local folder"
	45	[549]	CALL     	12 2 2
	46	[549]	SETTABLE 	11 -11 12	; "text" -
	47	[559]	CLOSURE  	12 1	; 0x7f8de34111a0
	48	[559]	GETUPVAL 	0 4	; UIManager
	49	[559]	MOVE     	0 2
	50	[559]	MOVE     	0 0
	51	[559]	MOVE     	0 1
	52	[559]	SETTABLE 	11 -13 12	; "callback" -
	53	[561]	SETLIST  	10 1 1	; 1
	54	[561]	NEWTABLE 	11 1 0
	55	[562]	NEWTABLE 	12 0 2
	56	[564]	GETUPVAL 	13 2	; _
	57	[564]	LOADK    	14 -15	; "Close"
	58	[564]	CALL     	13 2 2
	59	[564]	SETTABLE 	12 -11 13	; "text" -
	60	[567]	CLOSURE  	13 2	; 0x7f8de3411a30
	61	[567]	GETUPVAL 	0 4	; UIManager
	62	[567]	MOVE     	0 2
	63	[567]	SETTABLE 	12 -13 13	; "callback" -
	64	[569]	SETLIST  	11 1 1	; 1
	65	[570]	SETLIST  	8 3 1	; 1
	66	[570]	SETTABLE 	7 -10 8	; "buttons" -
	67	[527]	CALL     	5 3 2
	68	[571]	MOVE     	2 5
	69	[572]	GETUPVAL 	5 4	; UIManager
	70	[572]	SELF     	5 5 -16	; "show"
	71	[572]	MOVE     	7 2
	72	[572]	CALL     	5 3 1
	73	[573]	RETURN   	0 1

function <./frontend/apps/cloudstorage/cloudstorage.lua:534,544> (19 instructions, 76 bytes at 0x7f8de3407650)
0 params, 4 slots, 4 upvalues, 0 locals, 7 constants, 1 function
	1	[535]	GETUPVAL 	0 0	; UIManager
	2	[535]	SELF     	0 0 -1	; "close"
	3	[535]	GETUPVAL 	2 1	; syn_dialog
	4	[535]	CALL     	0 3 1
	5	[536]	GETGLOBAL	0 -2	; require
	6	[536]	LOADK    	1 -3	; "ui/cloudmgr"
	7	[536]	CALL     	0 2 2
	8	[536]	SELF     	0 0 -4	; "new"
	9	[536]	NEWTABLE 	2 0 2
	10	[537]	GETUPVAL 	3 2	; item
	11	[537]	SETTABLE 	2 -5 3	; "item" -
	12	[542]	CLOSURE  	3 0	; 0x7f8de3410b40
	13	[542]	GETUPVAL 	0 3	; self
	14	[542]	GETUPVAL 	0 2	; item
	15	[542]	SETTABLE 	2 -6 3	; "onConfirm" -
	16	[536]	CALL     	0 3 2
	17	[543]	SELF     	0 0 -7	; "chooseDir"
	18	[543]	CALL     	0 2 1
	19	[544]	RETURN   	0 1

function <./frontend/apps/cloudstorage/cloudstorage.lua:538,542> (12 instructions, 48 bytes at 0x7f8de3410b40)
1 param, 5 slots, 2 upvalues, 1 local, 3 constants, 0 functions
	1	[539]	GETUPVAL 	1 0	; self
	2	[539]	SELF     	1 1 -1	; "updateSyncFolder"
	3	[539]	GETUPVAL 	3 1	; item
	4	[539]	MOVE     	4 0
	5	[539]	CALL     	1 4 1
	6	[540]	GETUPVAL 	1 1	; item
	7	[540]	SETTABLE 	1 -2 0	; "sync_source_folder" -
	8	[541]	GETUPVAL 	1 0	; self
	9	[541]	SELF     	1 1 -3	; "synchronizeSettings"
	10	[541]	GETUPVAL 	3 1	; item
	11	[541]	CALL     	1 3 1
	12	[542]	RETURN   	0 1

function <./frontend/apps/cloudstorage/cloudstorage.lua:550,559> (17 instructions, 68 bytes at 0x7f8de34111a0)
0 params, 4 slots, 4 upvalues, 0 locals, 6 constants, 1 function
	1	[551]	GETUPVAL 	0 0	; UIManager
	2	[551]	SELF     	0 0 -1	; "close"
	3	[551]	GETUPVAL 	2 1	; syn_dialog
	4	[551]	CALL     	0 3 1
	5	[552]	GETGLOBAL	0 -2	; require
	6	[552]	LOADK    	1 -3	; "ui/downloadmgr"
	7	[552]	CALL     	0 2 2
	8	[552]	SELF     	0 0 -4	; "new"
	9	[552]	NEWTABLE 	2 0 1
	10	[557]	CLOSURE  	3 0	; 0x7f8de34114c0
	11	[557]	GETUPVAL 	0 2	; self
	12	[557]	GETUPVAL 	0 3	; item
	13	[557]	SETTABLE 	2 -5 3	; "onConfirm" -
	14	[552]	CALL     	0 3 2
	15	[558]	SELF     	0 0 -6	; "chooseDir"
	16	[558]	CALL     	0 2 1
	17	[559]	RETURN   	0 1

function <./frontend/apps/cloudstorage/cloudstorage.lua:553,557> (13 instructions, 52 bytes at 0x7f8de34114c0)
1 param, 6 slots, 2 upvalues, 1 local, 3 constants, 0 functions
	1	[554]	GETUPVAL 	1 0	; self
	2	[554]	SELF     	1 1 -1	; "updateSyncFolder"
	3	[554]	GETUPVAL 	3 1	; item
	4	[554]	LOADNIL  	4 4
	5	[554]	MOVE     	5 0
	6	[554]	CALL     	1 5 1
	7	[555]	GETUPVAL 	1 1	; item
	8	[555]	SETTABLE 	1 -2 0	; "sync_dest_folder" -
	9	[556]	GETUPVAL 	1 0	; self
	10	[556]	SELF     	1 1 -3	; "synchronizeSettings"
	11	[556]	GETUPVAL 	3 1	; item
	12	[556]	CALL     	1 3 1
	13	[557]	RETURN   	0 1

function <./frontend/apps/cloudstorage/cloudstorage.lua:565,567> (5 instructions, 20 bytes at 0x7f8de3411a30)
0 params, 3 slots, 2 upvalues, 0 locals, 1 constant, 0 functions
	1	[566]	GETUPVAL 	0 0	; UIManager
	2	[566]	SELF     	0 0 -1	; "close"
	3	[566]	GETUPVAL 	2 1	; syn_dialog
	4	[566]	CALL     	0 3 1
	5	[567]	RETURN   	0 1

function <./frontend/apps/cloudstorage/cloudstorage.lua:575,618> (25 instructions, 100 bytes at 0x7f8de34077d0)
2 params, 7 slots, 3 upvalues, 3 locals, 4 constants, 1 function
	1	[608]	CLOSURE  	2 0	; 0x7f8de3407930
	2	[608]	MOVE     	0 0
	3	[608]	MOVE     	0 1
	4	[609]	EQ       	0 1 -1	; - "dropbox"
	5	[609]	JMP      	5	; to 11
	6	[610]	GETUPVAL 	3 0	; DropBox
	7	[610]	SELF     	3 3 -2	; "config"
	8	[610]	LOADNIL  	5 5
	9	[610]	MOVE     	6 2
	10	[610]	CALL     	3 4 1
	11	[612]	EQ       	0 1 -3	; - "ftp"
	12	[612]	JMP      	5	; to 18
	13	[613]	GETUPVAL 	3 1	; Ftp
	14	[613]	SELF     	3 3 -2	; "config"
	15	[613]	LOADNIL  	5 5
	16	[613]	MOVE     	6 2
	17	[613]	CALL     	3 4 1
	18	[615]	EQ       	0 1 -4	; - "webdav"
	19	[615]	JMP      	5	; to 25
	20	[616]	GETUPVAL 	3 2	; WebDav
	21	[616]	SELF     	3 3 -2	; "config"
	22	[616]	LOADNIL  	5 5
	23	[616]	MOVE     	6 2
	24	[616]	CALL     	3 4 1
	25	[618]	RETURN   	0 1

function <./frontend/apps/cloudstorage/cloudstorage.lua:576,608> (73 instructions, 292 bytes at 0x7f8de3407930)
1 param, 7 slots, 2 upvalues, 3 locals, 23 constants, 0 functions
	1	[577]	GETUPVAL 	1 0	; self
	2	[577]	SELF     	1 1 -1	; "readSettings"
	3	[577]	CALL     	1 2 2
	4	[578]	SELF     	2 1 -2	; "readSetting"
	5	[578]	LOADK    	4 -3	; "cs_servers"
	6	[578]	CALL     	2 3 2
	7	[578]	TEST     	2 0 1
	8	[578]	JMP      	1	; to 10
	9	[578]	NEWTABLE 	2 0 0
	10	[579]	GETUPVAL 	3 1	; type
	11	[579]	EQ       	0 3 -4	; - "dropbox"
	12	[579]	JMP      	12	; to 25
	13	[580]	GETGLOBAL	3 -5	; table
	14	[580]	GETTABLE 	3 3 -6	; "insert"
	15	[580]	MOVE     	4 2
	16	[580]	NEWTABLE 	5 0 4
	17	[581]	GETTABLE 	6 0 -8	; 1
	18	[581]	SETTABLE 	5 -7 6	; "name" -
	19	[582]	GETTABLE 	6 0 -10	; 2
	20	[582]	SETTABLE 	5 -9 6	; "password" -
	21	[583]	SETTABLE 	5 -11 -4	; "type" "dropbox"
	22	[584]	SETTABLE 	5 -12 -13	; "url" "/"
	23	[580]	CALL     	3 3 1
	24	[585]	JMP      	39	; to 64
	25	[586]	GETUPVAL 	3 1	; type
	26	[586]	EQ       	0 3 -14	; - "ftp"
	27	[586]	JMP      	17	; to 45
	28	[587]	GETGLOBAL	3 -5	; table
	29	[587]	GETTABLE 	3 3 -6	; "insert"
	30	[587]	MOVE     	4 2
	31	[587]	NEWTABLE 	5 0 6
	32	[588]	GETTABLE 	6 0 -8	; 1
	33	[588]	SETTABLE 	5 -7 6	; "name" -
	34	[589]	GETTABLE 	6 0 -10	; 2
	35	[589]	SETTABLE 	5 -15 6	; "address" -
	36	[590]	GETTABLE 	6 0 -17	; 3
	37	[590]	SETTABLE 	5 -16 6	; "username" -
	38	[591]	GETTABLE 	6 0 -18	; 4
	39	[591]	SETTABLE 	5 -9 6	; "password" -
	40	[592]	GETTABLE 	6 0 -19	; 5
	41	[592]	SETTABLE 	5 -12 6	; "url" -
	42	[593]	SETTABLE 	5 -11 -14	; "type" "ftp"
	43	[587]	CALL     	3 3 1
	44	[594]	JMP      	19	; to 64
	45	[595]	GETUPVAL 	3 1	; type
	46	[595]	EQ       	0 3 -20	; - "webdav"
	47	[595]	JMP      	16	; to 64
	48	[596]	GETGLOBAL	3 -5	; table
	49	[596]	GETTABLE 	3 3 -6	; "insert"
	50	[596]	MOVE     	4 2
	51	[596]	NEWTABLE 	5 0 6
	52	[597]	GETTABLE 	6 0 -8	; 1
	53	[597]	SETTABLE 	5 -7 6	; "name" -
	54	[598]	GETTABLE 	6 0 -10	; 2
	55	[598]	SETTABLE 	5 -15 6	; "address" -
	56	[599]	GETTABLE 	6 0 -17	; 3
	57	[599]	SETTABLE 	5 -16 6	; "username" -
	58	[600]	GETTABLE 	6 0 -18	; 4
	59	[600]	SETTABLE 	5 -9 6	; "password" -
	60	[601]	GETTABLE 	6 0 -19	; 5
	61	[601]	SETTABLE 	5 -12 6	; "url" -
	62	[602]	SETTABLE 	5 -11 -20	; "type" "webdav"
	63	[596]	CALL     	3 3 1
	64	[605]	SELF     	3 1 -21	; "saveSetting"
	65	[605]	LOADK    	5 -3	; "cs_servers"
	66	[605]	MOVE     	6 2
	67	[605]	CALL     	3 4 1
	68	[606]	SELF     	3 1 -22	; "flush"
	69	[606]	CALL     	3 2 1
	70	[607]	GETUPVAL 	3 0	; self
	71	[607]	SELF     	3 3 -23	; "init"
	72	[607]	CALL     	3 2 1
	73	[608]	RETURN   	0 1

function <./frontend/apps/cloudstorage/cloudstorage.lua:620,669> (30 instructions, 120 bytes at 0x7f8de3412350)
2 params, 7 slots, 3 upvalues, 3 locals, 5 constants, 1 function
	1	[661]	CLOSURE  	2 0	; 0x7f8de34123d0
	2	[661]	MOVE     	0 0
	3	[661]	MOVE     	0 1
	4	[662]	GETTABLE 	3 1 -1	; "type"
	5	[662]	EQ       	0 3 -2	; - "dropbox"
	6	[662]	JMP      	6	; to 13
	7	[663]	GETUPVAL 	3 0	; DropBox
	8	[663]	SELF     	3 3 -3	; "config"
	9	[663]	MOVE     	5 1
	10	[663]	MOVE     	6 2
	11	[663]	CALL     	3 4 1
	12	[663]	JMP      	17	; to 30
	13	[664]	GETTABLE 	3 1 -1	; "type"
	14	[664]	EQ       	0 3 -4	; - "ftp"
	15	[664]	JMP      	6	; to 22
	16	[665]	GETUPVAL 	3 1	; Ftp
	17	[665]	SELF     	3 3 -3	; "config"
	18	[665]	MOVE     	5 1
	19	[665]	MOVE     	6 2
	20	[665]	CALL     	3 4 1
	21	[665]	JMP      	8	; to 30
	22	[666]	GETTABLE 	3 1 -1	; "type"
	23	[666]	EQ       	0 3 -5	; - "webdav"
	24	[666]	JMP      	5	; to 30
	25	[667]	GETUPVAL 	3 2	; WebDav
	26	[667]	SELF     	3 3 -3	; "config"
	27	[667]	MOVE     	5 1
	28	[667]	MOVE     	6 2
	29	[667]	CALL     	3 4 1
	30	[669]	RETURN   	0 1

function <./frontend/apps/cloudstorage/cloudstorage.lua:621,661> (105 instructions, 420 bytes at 0x7f8de34123d0)
2 params, 11 slots, 2 upvalues, 19 locals, 22 constants, 0 functions
	1	[622]	GETUPVAL 	2 0	; self
	2	[622]	SELF     	2 2 -1	; "readSettings"
	3	[622]	CALL     	2 2 2
	4	[623]	SELF     	3 2 -2	; "readSetting"
	5	[623]	LOADK    	5 -3	; "cs_servers"
	6	[623]	CALL     	3 3 2
	7	[623]	TEST     	3 0 1
	8	[623]	JMP      	1	; to 10
	9	[623]	NEWTABLE 	3 0 0
	10	[624]	GETUPVAL 	4 1	; item
	11	[624]	GETTABLE 	4 4 -4	; "type"
	12	[624]	EQ       	0 4 -5	; - "dropbox"
	13	[624]	JMP      	21	; to 35
	14	[625]	GETGLOBAL	4 -6	; ipairs
	15	[625]	MOVE     	5 3
	16	[625]	CALL     	4 2 4
	17	[625]	JMP      	14	; to 32
	18	[626]	GETTABLE 	9 8 -7	; "name"
	19	[626]	GETTABLE 	10 0 -8	; "text"
	20	[626]	EQ       	0 9 10
	21	[626]	JMP      	10	; to 32
	22	[626]	GETTABLE 	9 8 -9	; "password"
	23	[626]	GETTABLE 	10 0 -9	; "password"
	24	[626]	EQ       	0 9 10
	25	[626]	JMP      	6	; to 32
	26	[627]	GETTABLE 	9 1 -10	; 1
	27	[627]	SETTABLE 	8 -7 9	; "name" -
	28	[628]	GETTABLE 	9 1 -11	; 2
	29	[628]	SETTABLE 	8 -9 9	; "password" -
	30	[629]	SETTABLE 	3 7 8
	31	[630]	JMP      	64	; to 96
	32	[625]	TFORLOOP 	4 2
	33	[631]	JMP      	-16	; to 18
	34	[632]	JMP      	61	; to 96
	35	[633]	GETUPVAL 	4 1	; item
	36	[633]	GETTABLE 	4 4 -4	; "type"
	37	[633]	EQ       	0 4 -12	; - "ftp"
	38	[633]	JMP      	27	; to 66
	39	[634]	GETGLOBAL	4 -6	; ipairs
	40	[634]	MOVE     	5 3
	41	[634]	CALL     	4 2 4
	42	[634]	JMP      	20	; to 63
	43	[635]	GETTABLE 	9 8 -7	; "name"
	44	[635]	GETTABLE 	10 0 -8	; "text"
	45	[635]	EQ       	0 9 10
	46	[635]	JMP      	16	; to 63
	47	[635]	GETTABLE 	9 8 -13	; "address"
	48	[635]	GETTABLE 	10 0 -13	; "address"
	49	[635]	EQ       	0 9 10
	50	[635]	JMP      	12	; to 63
	51	[636]	GETTABLE 	9 1 -10	; 1
	52	[636]	SETTABLE 	8 -7 9	; "name" -
	53	[637]	GETTABLE 	9 1 -11	; 2
	54	[637]	SETTABLE 	8 -13 9	; "address" -
	55	[638]	GETTABLE 	9 1 -15	; 3
	56	[638]	SETTABLE 	8 -14 9	; "username" -
	57	[639]	GETTABLE 	9 1 -16	; 4
	58	[639]	SETTABLE 	8 -9 9	; "password" -
	59	[640]	GETTABLE 	9 1 -18	; 5
	60	[640]	SETTABLE 	8 -17 9	; "url" -
	61	[641]	SETTABLE 	3 7 8
	62	[642]	JMP      	33	; to 96
	63	[634]	TFORLOOP 	4 2
	64	[643]	JMP      	-22	; to 43
	65	[644]	JMP      	30	; to 96
	66	[645]	GETUPVAL 	4 1	; item
	67	[645]	GETTABLE 	4 4 -4	; "type"
	68	[645]	EQ       	0 4 -19	; - "webdav"
	69	[645]	JMP      	26	; to 96
	70	[646]	GETGLOBAL	4 -6	; ipairs
	71	[646]	MOVE     	5 3
	72	[646]	CALL     	4 2 4
	73	[646]	JMP      	20	; to 94
	74	[647]	GETTABLE 	9 8 -7	; "name"
	75	[647]	GETTABLE 	10 0 -8	; "text"
	76	[647]	EQ       	0 9 10
	77	[647]	JMP      	16	; to 94
	78	[647]	GETTABLE 	9 8 -13	; "address"
	79	[647]	GETTABLE 	10 0 -13	; "address"
	80	[647]	EQ       	0 9 10
	81	[647]	JMP      	12	; to 94
	82	[648]	GETTABLE 	9 1 -10	; 1
	83	[648]	SETTABLE 	8 -7 9	; "name" -
	84	[649]	GETTABLE 	9 1 -11	; 2
	85	[649]	SETTABLE 	8 -13 9	; "address" -
	86	[650]	GETTABLE 	9 1 -15	; 3
	87	[650]	SETTABLE 	8 -14 9	; "username" -
	88	[651]	GETTABLE 	9 1 -16	; 4
	89	[651]	SETTABLE 	8 -9 9	; "password" -
	90	[652]	GETTABLE 	9 1 -18	; 5
	91	[652]	SETTABLE 	8 -17 9	; "url" -
	92	[653]	SETTABLE 	3 7 8
	93	[654]	JMP      	2	; to 96
	94	[646]	TFORLOOP 	4 2
	95	[655]	JMP      	-22	; to 74
	96	[658]	SELF     	4 2 -20	; "saveSetting"
	97	[658]	LOADK    	6 -3	; "cs_servers"
	98	[658]	MOVE     	7 3
	99	[658]	CALL     	4 4 1
	100	[659]	SELF     	4 2 -21	; "flush"
	101	[659]	CALL     	4 2 1
	102	[660]	GETUPVAL 	4 0	; self
	103	[660]	SELF     	4 4 -22	; "init"
	104	[660]	CALL     	4 2 1
	105	[661]	RETURN   	0 1

function <./frontend/apps/cloudstorage/cloudstorage.lua:671,683> (41 instructions, 164 bytes at 0x7f8de3412ca0)
2 params, 12 slots, 0 upvalues, 9 locals, 13 constants, 0 functions
	1	[672]	SELF     	2 0 -1	; "readSettings"
	2	[672]	CALL     	2 2 2
	3	[673]	SELF     	3 2 -2	; "readSetting"
	4	[673]	LOADK    	5 -3	; "cs_servers"
	5	[673]	CALL     	3 3 2
	6	[673]	TEST     	3 0 1
	7	[673]	JMP      	1	; to 9
	8	[673]	NEWTABLE 	3 0 0
	9	[674]	GETGLOBAL	4 -4	; ipairs
	10	[674]	MOVE     	5 3
	11	[674]	CALL     	4 2 4
	12	[674]	JMP      	18	; to 31
	13	[675]	GETTABLE 	9 8 -5	; "name"
	14	[675]	GETTABLE 	10 1 -6	; "text"
	15	[675]	EQ       	0 9 10
	16	[675]	JMP      	14	; to 31
	17	[675]	GETTABLE 	9 8 -7	; "password"
	18	[675]	GETTABLE 	10 1 -7	; "password"
	19	[675]	EQ       	0 9 10
	20	[675]	JMP      	10	; to 31
	21	[675]	GETTABLE 	9 8 -8	; "type"
	22	[675]	GETTABLE 	10 1 -8	; "type"
	23	[675]	EQ       	0 9 10
	24	[675]	JMP      	6	; to 31
	25	[676]	GETGLOBAL	9 -9	; table
	26	[676]	GETTABLE 	9 9 -10	; "remove"
	27	[676]	MOVE     	10 3
	28	[676]	MOVE     	11 7
	29	[676]	CALL     	9 3 1
	30	[677]	JMP      	2	; to 33
	31	[674]	TFORLOOP 	4 2
	32	[678]	JMP      	-20	; to 13
	33	[680]	SELF     	4 2 -11	; "saveSetting"
	34	[680]	LOADK    	6 -3	; "cs_servers"
	35	[680]	MOVE     	7 3
	36	[680]	CALL     	4 4 1
	37	[681]	SELF     	4 2 -12	; "flush"
	38	[681]	CALL     	4 2 1
	39	[682]	SELF     	4 0 -13	; "init"
	40	[682]	CALL     	4 2 1
	41	[683]	RETURN   	0 1

function <./frontend/apps/cloudstorage/cloudstorage.lua:685,693> (24 instructions, 96 bytes at 0x7f8de3413bf0)
2 params, 5 slots, 3 upvalues, 2 locals, 6 constants, 0 functions
	1	[686]	GETTABLE 	2 1 -1	; "type"
	2	[686]	EQ       	0 2 -2	; - "dropbox"
	3	[686]	JMP      	5	; to 9
	4	[687]	GETUPVAL 	2 0	; DropBox
	5	[687]	SELF     	2 2 -3	; "info"
	6	[687]	GETTABLE 	4 1 -4	; "password"
	7	[687]	CALL     	2 3 1
	8	[687]	JMP      	15	; to 24
	9	[688]	GETTABLE 	2 1 -1	; "type"
	10	[688]	EQ       	0 2 -5	; - "ftp"
	11	[688]	JMP      	5	; to 17
	12	[689]	GETUPVAL 	2 1	; Ftp
	13	[689]	SELF     	2 2 -3	; "info"
	14	[689]	MOVE     	4 1
	15	[689]	CALL     	2 3 1
	16	[689]	JMP      	7	; to 24
	17	[690]	GETTABLE 	2 1 -1	; "type"
	18	[690]	EQ       	0 2 -6	; - "webdav"
	19	[690]	JMP      	4	; to 24
	20	[691]	GETUPVAL 	2 2	; WebDav
	21	[691]	SELF     	2 2 -3	; "info"
	22	[691]	MOVE     	4 1
	23	[691]	CALL     	2 3 1
	24	[693]	RETURN   	0 1

function <./frontend/apps/cloudstorage/cloudstorage.lua:695,698> (12 instructions, 48 bytes at 0x7f8de340f0f0)
1 param, 5 slots, 2 upvalues, 1 local, 4 constants, 0 functions
	1	[696]	GETUPVAL 	1 0	; LuaSettings
	2	[696]	SELF     	1 1 -2	; "open"
	3	[696]	GETUPVAL 	3 1	; DataStorage
	4	[696]	SELF     	3 3 -3	; "getSettingsDir"
	5	[696]	CALL     	3 2 2
	6	[696]	LOADK    	4 -4	; "/cloudstorage.lua"
	7	[696]	CONCAT   	3 3 4
	8	[696]	CALL     	1 3 2
	9	[696]	SETTABLE 	0 -1 1	; "cs_settings" -
	10	[697]	GETTABLE 	1 0 -1	; "cs_settings"
	11	[697]	RETURN   	1 2
	12	[698]	RETURN   	0 1

function <./frontend/apps/cloudstorage/cloudstorage.lua:700,713> (23 instructions, 92 bytes at 0x7f8de34144c0)
1 param, 5 slots, 0 upvalues, 2 locals, 7 constants, 0 functions
	1	[701]	GETTABLE 	1 0 -1	; "paths"
	2	[701]	LEN      	1 1
	3	[701]	LT       	0 -2 1	; 0 -
	4	[701]	JMP      	16	; to 21
	5	[702]	GETGLOBAL	1 -3	; table
	6	[702]	GETTABLE 	1 1 -4	; "remove"
	7	[702]	GETTABLE 	2 0 -1	; "paths"
	8	[702]	CALL     	1 2 1
	9	[703]	GETTABLE 	1 0 -1	; "paths"
	10	[703]	GETTABLE 	2 0 -1	; "paths"
	11	[703]	LEN      	2 2
	12	[703]	GETTABLE 	1 1 2
	13	[704]	TEST     	1 0 0
	14	[704]	JMP      	4	; to 19
	15	[706]	SELF     	2 0 -5	; "openCloudServer"
	16	[706]	GETTABLE 	4 1 -6	; "url"
	17	[706]	CALL     	2 3 1
	18	[706]	JMP      	2	; to 21
	19	[709]	SELF     	2 0 -7	; "init"
	20	[709]	CALL     	2 2 1
	21	[712]	LOADBOOL 	1 1 0
	22	[712]	RETURN   	1 2
	23	[713]	RETURN   	0 1
