-- BYTECODE -- cloudmgr.lua:6-6
0001    RET0     0   1

-- BYTECODE -- cloudmgr.lua:9-14
0001    ISTC     2   1
0002    JMP      2 => 0004
0003    TNEW     2   0
0004 => GGET     3   0      ; "setmetatable"
0005    MOV      4   2
0006    MOV      5   0
0007    CALL     3   1   3
0008    TSETS    0   0   1  ; "__index"
0009    RET1     2   2

-- BYTECODE -- cloudmgr.lua:22-24
0001    UGET     1   0      ; self
0002    TGETS    1   1   0  ; "onConfirm"
0003    MOV      2   0
0004    CALL     1   1   2
0005    RET0     0   1

-- BYTECODE -- cloudmgr.lua:18-27
0001    UGET     1   0      ; CloudStorage
0002    MOV      2   1
0003    TGETS    1   1   0  ; "new"
0004    TDUP     3   2
0005    UGET     4   1      ; _
0006    KSTR     5   1      ; "Long-press to select directory"
0007    CALL     4   2   2
0008    TSETS    4   3   3  ; "title"
0009    TGETS    4   0   4  ; "item"
0010    TSETS    4   3   4  ; "item"
0011    FNEW     4   5      ; cloudmgr.lua:22
0012    TSETS    4   3   6  ; "onConfirm"
0013    CALL     1   2   3
0014    UGET     2   2      ; UIManager
0015    MOV      3   2
0016    TGETS    2   2   7  ; "show"
0017    MOV      4   1
0018    CALL     2   1   3
0019    UCLO     0 => 0020
0020 => RET0     0   1

-- BYTECODE -- cloudmgr.lua:0-30
0001    GGET     0   0      ; "require"
0002    KSTR     1   1      ; "apps/cloudstorage/cloudstorage"
0003    CALL     0   2   2
0004    GGET     1   0      ; "require"
0005    KSTR     2   2      ; "ui/uimanager"
0006    CALL     1   2   2
0007    GGET     2   0      ; "require"
0008    KSTR     3   3      ; "gettext"
0009    CALL     2   2   2
0010    TDUP     3   5
0011    FNEW     4   4      ; cloudmgr.lua:6
0012    TSETS    4   3   6  ; "onConfirm"
0013    FNEW     4   8      ; cloudmgr.lua:9
0014    TSETS    4   3   7  ; "new"
0015    FNEW     4  10      ; cloudmgr.lua:18
0016    TSETS    4   3   9  ; "chooseDir"
0017    UCLO     0 => 0018
0018 => RET1     3   2

