
main <./plugins/backgroundrunner.koplugin/commandrunner.lua:0,0> (20 instructions, 80 bytes at 0x7f93735068e0)
0+ params, 3 slots, 0 upvalues, 2 locals, 10 constants, 5 functions
	1	[1]	GETGLOBAL	0 -1	; require
	2	[1]	LOADK    	1 -2	; "logger"
	3	[1]	CALL     	0 2 2
	4	[3]	NEWTABLE 	1 0 2
	5	[4]	SETTABLE 	1 -3 -4	; "pio" nil
	6	[5]	SETTABLE 	1 -5 -4	; "job" nil
	7	[18]	CLOSURE  	2 0	; 0x7f9373506bd0
	8	[8]	SETTABLE 	1 -6 2	; "createEnvironmentFromTable" -
	9	[31]	CLOSURE  	2 1	; 0x7f93735071f0
	10	[20]	SETTABLE 	1 -7 2	; "createEnvironment" -
	11	[45]	CLOSURE  	2 2	; 0x7f9373507870
	12	[45]	MOVE     	0 0
	13	[33]	SETTABLE 	1 -8 2	; "start" -
	14	[81]	CLOSURE  	2 3	; 0x7f9373506aa0
	15	[81]	MOVE     	0 0
	16	[50]	SETTABLE 	1 -9 2	; "poll" -
	17	[88]	CLOSURE  	2 4	; 0x7f9373508230
	18	[85]	SETTABLE 	1 -10 2	; "pending" -
	19	[90]	RETURN   	1 2
	20	[90]	RETURN   	0 1

function <./plugins/backgroundrunner.koplugin/commandrunner.lua:8,18> (29 instructions, 116 bytes at 0x7f9373506bd0)
2 params, 13 slots, 0 upvalues, 8 locals, 10 constants, 0 functions
	1	[9]	EQ       	0 1 -1	; - nil
	2	[9]	JMP      	2	; to 5
	3	[9]	LOADK    	2 -2	; ""
	4	[9]	RETURN   	2 2
	5	[11]	LOADK    	2 -2	; ""
	6	[12]	GETGLOBAL	3 -3	; pairs
	7	[12]	MOVE     	4 1
	8	[12]	CALL     	3 2 4
	9	[12]	JMP      	6	; to 16
	10	[13]	MOVE     	8 2
	11	[13]	MOVE     	9 6
	12	[13]	LOADK    	10 -4	; "="
	13	[13]	MOVE     	11 7
	14	[13]	LOADK    	12 -5	; " "
	15	[13]	CONCAT   	2 8 12
	16	[12]	TFORLOOP 	3 2
	17	[13]	JMP      	-8	; to 10
	18	[16]	GETGLOBAL	3 -6	; string
	19	[16]	GETTABLE 	3 3 -7	; "len"
	20	[16]	MOVE     	4 2
	21	[16]	CALL     	3 2 2
	22	[16]	LT       	0 -8 3	; 0 -
	23	[16]	JMP      	4	; to 28
	24	[16]	LOADK    	3 -9	; "export "
	25	[16]	MOVE     	4 2
	26	[16]	LOADK    	5 -10	; ";"
	27	[16]	CONCAT   	2 3 5
	28	[17]	RETURN   	2 2
	29	[18]	RETURN   	0 1

function <./plugins/backgroundrunner.koplugin/commandrunner.lua:20,31> (30 instructions, 120 bytes at 0x7f93735071f0)
1 param, 6 slots, 0 upvalues, 3 locals, 8 constants, 0 functions
	1	[21]	GETGLOBAL	1 -1	; type
	2	[21]	GETTABLE 	2 0 -2	; "job"
	3	[21]	GETTABLE 	2 2 -3	; "environment"
	4	[21]	CALL     	1 2 2
	5	[21]	EQ       	0 1 -4	; - "table"
	6	[21]	JMP      	5	; to 12
	7	[22]	SELF     	1 0 -5	; "createEnvironmentFromTable"
	8	[22]	GETTABLE 	3 0 -2	; "job"
	9	[22]	GETTABLE 	3 3 -3	; "environment"
	10	[22]	TAILCALL 	1 3 0
	11	[22]	RETURN   	1 0
	12	[24]	GETGLOBAL	1 -1	; type
	13	[24]	GETTABLE 	2 0 -2	; "job"
	14	[24]	GETTABLE 	2 2 -3	; "environment"
	15	[24]	CALL     	1 2 2
	16	[24]	EQ       	0 1 -6	; - "function"
	17	[24]	JMP      	10	; to 28
	18	[25]	GETGLOBAL	1 -7	; pcall
	19	[25]	GETTABLE 	2 0 -2	; "job"
	20	[25]	GETTABLE 	2 2 -3	; "environment"
	21	[25]	CALL     	1 2 3
	22	[26]	TEST     	1 0 0
	23	[26]	JMP      	4	; to 28
	24	[27]	SELF     	3 0 -5	; "createEnvironmentFromTable"
	25	[27]	MOVE     	5 2
	26	[27]	TAILCALL 	3 3 0
	27	[27]	RETURN   	3 0
	28	[30]	LOADK    	1 -8	; ""
	29	[30]	RETURN   	1 2
	30	[31]	RETURN   	0 1

function <./plugins/backgroundrunner.koplugin/commandrunner.lua:33,45> (57 instructions, 228 bytes at 0x7f9373507870)
2 params, 8 slots, 1 upvalue, 3 locals, 18 constants, 0 functions
	1	[34]	GETGLOBAL	2 -1	; assert
	2	[34]	EQ       	0 0 -2	; - nil
	3	[34]	JMP      	1	; to 5
	4	[34]	LOADBOOL 	3 0 1
	5	[34]	LOADBOOL 	3 1 0
	6	[34]	CALL     	2 2 1
	7	[35]	GETGLOBAL	2 -1	; assert
	8	[35]	GETTABLE 	3 0 -3	; "pio"
	9	[35]	EQ       	1 3 -2	; - nil
	10	[35]	JMP      	1	; to 12
	11	[35]	LOADBOOL 	3 0 1
	12	[35]	LOADBOOL 	3 1 0
	13	[35]	CALL     	2 2 1
	14	[36]	GETGLOBAL	2 -1	; assert
	15	[36]	GETTABLE 	3 0 -4	; "job"
	16	[36]	EQ       	1 3 -2	; - nil
	17	[36]	JMP      	1	; to 19
	18	[36]	LOADBOOL 	3 0 1
	19	[36]	LOADBOOL 	3 1 0
	20	[36]	CALL     	2 2 1
	21	[37]	SETTABLE 	0 -4 1	; "job" -
	22	[38]	GETTABLE 	2 0 -4	; "job"
	23	[38]	GETGLOBAL	3 -6	; os
	24	[38]	GETTABLE 	3 3 -7	; "time"
	25	[38]	CALL     	3 1 2
	26	[38]	SETTABLE 	2 -5 3	; "start_sec" -
	27	[39]	GETGLOBAL	2 -1	; assert
	28	[39]	GETGLOBAL	3 -8	; type
	29	[39]	GETTABLE 	4 0 -4	; "job"
	30	[39]	GETTABLE 	4 4 -9	; "executable"
	31	[39]	CALL     	3 2 2
	32	[39]	EQ       	1 3 -10	; - "string"
	33	[39]	JMP      	1	; to 35
	34	[39]	LOADBOOL 	3 0 1
	35	[39]	LOADBOOL 	3 1 0
	36	[39]	CALL     	2 2 1
	37	[40]	SELF     	2 0 -11	; "createEnvironment"
	38	[40]	CALL     	2 2 2
	39	[40]	LOADK    	3 -12	; " "
	40	[41]	LOADK    	4 -13	; "sh plugins/backgroundrunner.koplugin/luawrapper.sh "
	41	[42]	LOADK    	5 -14	; "\""
	42	[42]	GETTABLE 	6 0 -4	; "job"
	43	[42]	GETTABLE 	6 6 -9	; "executable"
	44	[42]	LOADK    	7 -14	; "\""
	45	[42]	CONCAT   	2 2 7
	46	[43]	GETUPVAL 	3 0	; logger
	47	[43]	GETTABLE 	3 3 -15	; "dbg"
	48	[43]	LOADK    	4 -16	; "CommandRunner: Will execute command "
	49	[43]	MOVE     	5 2
	50	[43]	CONCAT   	4 4 5
	51	[43]	CALL     	3 2 1
	52	[44]	GETGLOBAL	3 -17	; io
	53	[44]	GETTABLE 	3 3 -18	; "popen"
	54	[44]	MOVE     	4 2
	55	[44]	CALL     	3 2 2
	56	[44]	SETTABLE 	0 -3 3	; "pio" -
	57	[45]	RETURN   	0 1

function <./plugins/backgroundrunner.koplugin/commandrunner.lua:50,81> (78 instructions, 312 bytes at 0x7f9373506aa0)
1 param, 10 slots, 1 upvalue, 10 locals, 19 constants, 0 functions
	1	[51]	GETGLOBAL	1 -1	; assert
	2	[51]	EQ       	0 0 -2	; - nil
	3	[51]	JMP      	1	; to 5
	4	[51]	LOADBOOL 	2 0 1
	5	[51]	LOADBOOL 	2 1 0
	6	[51]	CALL     	1 2 1
	7	[52]	GETGLOBAL	1 -1	; assert
	8	[52]	GETTABLE 	2 0 -3	; "pio"
	9	[52]	EQ       	0 2 -2	; - nil
	10	[52]	JMP      	1	; to 12
	11	[52]	LOADBOOL 	2 0 1
	12	[52]	LOADBOOL 	2 1 0
	13	[52]	CALL     	1 2 1
	14	[53]	GETGLOBAL	1 -1	; assert
	15	[53]	GETTABLE 	2 0 -4	; "job"
	16	[53]	EQ       	0 2 -2	; - nil
	17	[53]	JMP      	1	; to 19
	18	[53]	LOADBOOL 	2 0 1
	19	[53]	LOADBOOL 	2 1 0
	20	[53]	CALL     	1 2 1
	21	[54]	GETTABLE 	1 0 -3	; "pio"
	22	[54]	SELF     	1 1 -5	; "read"
	23	[54]	CALL     	1 2 2
	24	[55]	EQ       	0 1 -6	; - ""
	25	[55]	JMP      	3	; to 29
	26	[56]	LOADNIL  	2 2
	27	[56]	RETURN   	2 2
	28	[56]	JMP      	49	; to 78
	29	[58]	EQ       	0 1 -2	; - nil
	30	[58]	JMP      	3	; to 34
	31	[60]	GETTABLE 	2 0 -4	; "job"
	32	[60]	SETTABLE 	2 -7 -8	; "result" 223
	33	[60]	JMP      	32	; to 66
	34	[62]	MOVE     	2 1
	35	[62]	GETTABLE 	3 0 -3	; "pio"
	36	[62]	SELF     	3 3 -5	; "read"
	37	[62]	LOADK    	5 -9	; "*a"
	38	[62]	CALL     	3 3 2
	39	[62]	CONCAT   	1 2 3
	40	[63]	GETUPVAL 	2 0	; logger
	41	[63]	GETTABLE 	2 2 -10	; "dbg"
	42	[63]	LOADK    	3 -11	; "CommandRunner: Receive output "
	43	[63]	MOVE     	4 1
	44	[63]	CONCAT   	3 3 4
	45	[63]	CALL     	2 2 1
	46	[64]	GETGLOBAL	2 -12	; pcall
	47	[64]	GETGLOBAL	3 -13	; loadstring
	48	[64]	MOVE     	4 1
	49	[64]	CALL     	3 2 0
	50	[64]	CALL     	2 0 3
	51	[65]	TEST     	2 0 0
	52	[65]	JMP      	11	; to 64
	53	[65]	EQ       	1 3 -2	; - nil
	54	[65]	JMP      	9	; to 64
	55	[66]	GETGLOBAL	4 -14	; pairs
	56	[66]	MOVE     	5 3
	57	[66]	CALL     	4 2 4
	58	[66]	JMP      	2	; to 61
	59	[67]	GETTABLE 	9 0 -4	; "job"
	60	[67]	SETTABLE 	9 7 8
	61	[66]	TFORLOOP 	4 2
	62	[67]	JMP      	-4	; to 59
	63	[68]	JMP      	2	; to 66
	64	[71]	GETTABLE 	4 0 -4	; "job"
	65	[71]	SETTABLE 	4 -7 -15	; "result" 222
	66	[74]	GETTABLE 	2 0 -3	; "pio"
	67	[74]	SELF     	2 2 -16	; "close"
	68	[74]	CALL     	2 2 1
	69	[75]	SETTABLE 	0 -3 -2	; "pio" nil
	70	[76]	GETTABLE 	2 0 -4	; "job"
	71	[76]	GETGLOBAL	3 -18	; os
	72	[76]	GETTABLE 	3 3 -19	; "time"
	73	[76]	CALL     	3 1 2
	74	[76]	SETTABLE 	2 -17 3	; "end_sec" -
	75	[77]	GETTABLE 	2 0 -4	; "job"
	76	[78]	SETTABLE 	0 -4 -2	; "job" nil
	77	[79]	RETURN   	2 2
	78	[81]	RETURN   	0 1

function <./plugins/backgroundrunner.koplugin/commandrunner.lua:85,88> (13 instructions, 52 bytes at 0x7f9373508230)
1 param, 3 slots, 0 upvalues, 1 local, 3 constants, 0 functions
	1	[86]	GETGLOBAL	1 -1	; assert
	2	[86]	EQ       	0 0 -2	; - nil
	3	[86]	JMP      	1	; to 5
	4	[86]	LOADBOOL 	2 0 1
	5	[86]	LOADBOOL 	2 1 0
	6	[86]	CALL     	1 2 1
	7	[87]	GETTABLE 	1 0 -3	; "pio"
	8	[87]	EQ       	0 1 -2	; - nil
	9	[87]	JMP      	1	; to 11
	10	[87]	LOADBOOL 	1 0 1
	11	[87]	LOADBOOL 	1 1 0
	12	[87]	RETURN   	1 2
	13	[88]	RETURN   	0 1
