-- BYTECODE -- commonrequire.lua:6-10
0001    UGET     2   0      ; exists
0002    TGETV    2   2   0
0003    ISF          2
0004    JMP      3 => 0008
0005    UGET     2   0      ; exists
0006    TGETV    2   2   0
0007    RET1     2   2
0008 => UGET     2   0      ; exists
0009    UGET     3   1      ; old_metatype
0010    MOV      4   0
0011    MOV      5   1
0012    CALL     3   2   3
0013    TSETV    3   2   0
0014    UGET     2   0      ; exists
0015    TGETV    2   2   0
0016    RET1     2   2

-- BYTECODE -- commonrequire.lua:43-48
0001    GGET     1   0      ; "type"
0002    MOV      2   0
0003    CALL     1   2   2
0004    ISEQS    1   1      ; "string"
0005    JMP      1 => 0008
0006    KPRI     1   1
0007    RET1     1   2
0008 => GGET     1   2      ; "package"
0009    TGETS    1   1   3  ; "loaded"
0010    KPRI     2   0
0011    TSETV    2   1   0
0012    GGET     1   4      ; "_G"
0013    KPRI     2   0
0014    TSETV    2   1   0
0015    KPRI     1   2
0016    RET1     1   2

-- BYTECODE -- commonrequire.lua:50-55
0001    GGET     2   0      ; "type"
0002    MOV      3   0
0003    CALL     2   2   2
0004    ISEQS    2   1      ; "string"
0005    JMP      2 => 0008
0006    KPRI     2   1
0007    RET1     2   2
0008 => GGET     2   2      ; "assert"
0009    GGET     3   3      ; "package"
0010    TGETS    3   3   4  ; "unload"
0011    MOV      4   0
0012    CALL     3   0   2
0013    CALLM    2   1   0
0014    GGET     2   3      ; "package"
0015    TGETS    2   2   5  ; "loaded"
0016    TSETV    1   2   0
0017    KPRI     2   2
0018    RET1     2   2

-- BYTECODE -- commonrequire.lua:57-61
0001    GGET     1   0      ; "type"
0002    MOV      2   0
0003    CALL     1   2   2
0004    ISEQS    1   1      ; "string"
0005    JMP      1 => 0008
0006    KPRI     1   1
0007    RET1     1   2
0008 => GGET     1   2      ; "assert"
0009    GGET     2   3      ; "package"
0010    TGETS    2   2   4  ; "unload"
0011    MOV      3   0
0012    CALL     2   0   2
0013    CALLM    1   1   0
0014    GGET     1   5      ; "require"
0015    MOV      2   0
0016    CALLT    1   2

-- BYTECODE -- commonrequire.lua:63-88
0001    TDUP     0   0
0002    TNEW     1   0
0003    GGET     2   1      ; "pairs"
0004    GGET     3   2      ; "package"
0005    TGETS    3   3   3  ; "loaded"
0006    CALL     2   4   2
0007    ISNEXT   5 => 0033
0008 => GGET     7   2      ; "package"
0009    TGETS    7   7   4  ; "searchpath"
0010    MOV      8   5
0011    GGET     9   2      ; "package"
0012    TGETS    9   9   5  ; "path"
0013    CALL     7   2   3
0014    ISEQP    7   0
0015    JMP      8 => 0033
0016    GGET     8   6      ; "ipairs"
0017    MOV      9   0
0018    CALL     8   4   2
0019    JMP     11 => 0031
0020 => MOV     14   7
0021    TGETS   13   7   7  ; "find"
0022    MOV     15  12
0023    CALL    13   2   3
0024    ISNEN   13   0      ; 1
0025    JMP     13 => 0031
0026    GGET    13   8      ; "table"
0027    TGETS   13  13   9  ; "insert"
0028    MOV     14   1
0029    MOV     15   5
0030    CALL    13   1   3
0031 => ITERC   11   3   3
0032    ITERL   11 => 0020
0033 => ITERN    5   3   3
0034    ITERL    5 => 0008
0035    GGET     2   6      ; "ipairs"
0036    MOV      3   1
0037    CALL     2   4   2
0038    JMP      5 => 0047
0039 => ISEQS    6  10      ; "commonrequire"
0040    JMP      7 => 0047
0041    GGET     7  11      ; "assert"
0042    GGET     8   2      ; "package"
0043    TGETS    8   8  12  ; "unload"
0044    MOV      9   6
0045    CALL     8   0   2
0046    CALLM    7   1   0
0047 => ITERC    5   3   3
0048    ITERL    5 => 0039
0049    LEN      2   1
0050    RET1     2   2

-- BYTECODE -- commonrequire.lua:91-100
0001    GGET     0   0      ; "require"
0002    KSTR     1   1      ; "pluginshare"
0003    CALL     0   2   2
0004    KPRI     1   0
0005    TSETS    1   0   2  ; "stopBackgroundRunner"
0006    UGET     0   0      ; background_runner
0007    ISNEP    0   0
0008    JMP      0 => 0023
0009    GGET     0   3      ; "package"
0010    TGETS    0   0   4  ; "path"
0011    GGET     1   3      ; "package"
0012    KSTR     2   5      ; "plugins/backgroundrunner.koplugin/?.lua;"
0013    GGET     3   3      ; "package"
0014    TGETS    3   3   4  ; "path"
0015    CAT      2   2   3
0016    TSETS    2   1   4  ; "path"
0017    GGET     1   6      ; "dofile"
0018    KSTR     2   7      ; "plugins/backgroundrunner.koplugin/main.l"~
0019    CALL     1   2   2
0020    USETV    0   1      ; background_runner
0021    GGET     1   3      ; "package"
0022    TSETS    0   1   4  ; "path"
0023 => UGET     0   0      ; background_runner
0024    RET1     0   2

-- BYTECODE -- commonrequire.lua:102-105
0001    USETP    0   0      ; background_runner
0002    GGET     0   0      ; "require"
0003    KSTR     1   1      ; "pluginshare"
0004    CALL     0   2   2
0005    KPRI     1   2
0006    TSETS    1   0   2  ; "stopBackgroundRunner"
0007    RET0     0   1

-- BYTECODE -- commonrequire.lua:0-106
0001    GGET     0   0      ; "require"
0002    KSTR     1   1      ; "ffi"
0003    CALL     0   2   2
0004    TGETS    1   0   2  ; "metatype"
0005    TNEW     2   0
0006    FNEW     3   3      ; commonrequire.lua:6
0007    TSETS    3   0   2  ; "metatype"
0008    GGET     3   0      ; "require"
0009    KSTR     4   4      ; "defaults"
0010    CALL     3   1   2
0011    GGET     3   5      ; "package"
0012    KSTR     4   7      ; "?.lua;common/?.lua;rocks/share/lua/5.1/?"~
0013    GGET     5   5      ; "package"
0014    TGETS    5   5   6  ; "path"
0015    CAT      4   4   5
0016    TSETS    4   3   6  ; "path"
0017    GGET     3   5      ; "package"
0018    KSTR     4   9      ; "?.so;common/?.so;/usr/lib/lua/?.so;rocks"~
0019    GGET     5   5      ; "package"
0020    TGETS    5   5   8  ; "cpath"
0021    CAT      4   4   5
0022    TSETS    4   3   8  ; "cpath"
0023    GGET     3   0      ; "require"
0024    KSTR     4  10      ; "dbg"
0025    CALL     3   2   2
0026    MOV      4   3
0027    TGETS    3   3  11  ; "turnOff"
0028    CALL     3   1   2
0029    GGET     3   0      ; "require"
0030    KSTR     4  12      ; "logger"
0031    CALL     3   2   2
0032    MOV      5   3
0033    TGETS    4   3  13  ; "setLevel"
0034    TGETS    6   3  14  ; "levels"
0035    TGETS    6   6  15  ; "warn"
0036    CALL     4   1   3
0037    GGET     4   0      ; "require"
0038    KSTR     5  16      ; "datastorage"
0039    CALL     4   2   2
0040    GGET     5  17      ; "os"
0041    TGETS    5   5  18  ; "remove"
0042    MOV      7   4
0043    TGETS    6   4  19  ; "getDataDir"
0044    CALL     6   2   2
0045    KSTR     7  20      ; "/settings.reader.lua"
0046    CAT      6   6   7
0047    CALL     5   1   2
0048    GGET     5   0      ; "require"
0049    KSTR     6  21      ; "luasettings"
0050    CALL     5   2   2
0051    MOV      6   5
0052    TGETS    5   5  22  ; "open"
0053    KSTR     7  23      ; ".reader"
0054    CALL     5   2   3
0055    GSET     5  24      ; "G_reader_settings"
0056    GGET     5   0      ; "require"
0057    KSTR     6  25      ; "ffi/framebuffer"
0058    CALL     5   2   2
0059    GSET     5  26      ; "einkfb"
0060    GGET     5  26      ; "einkfb"
0061    KPRI     6   2
0062    TSETS    6   5  27  ; "dummy"
0063    GGET     5   0      ; "require"
0064    KSTR     6  28      ; "device"
0065    CALL     5   2   2
0066    TGETS    6   5  29  ; "screen"
0067    MOV      8   6
0068    TGETS    7   6  30  ; "init"
0069    CALL     7   1   2
0070    GGET     7   0      ; "require"
0071    KSTR     8  31      ; "document/canvascontext"
0072    CALL     7   2   2
0073    MOV      9   7
0074    TGETS    8   7  30  ; "init"
0075    MOV     10   5
0076    CALL     8   1   3
0077    TGETS    8   5  32  ; "input"
0078    KPRI     9   2
0079    TSETS    9   8  27  ; "dummy"
0080    GGET     9   5      ; "package"
0081    FNEW    10  34      ; commonrequire.lua:43
0082    TSETS   10   9  33  ; "unload"
0083    GGET     9   5      ; "package"
0084    FNEW    10  36      ; commonrequire.lua:50
0085    TSETS   10   9  35  ; "replace"
0086    GGET     9   5      ; "package"
0087    FNEW    10  38      ; commonrequire.lua:57
0088    TSETS   10   9  37  ; "reload"
0089    GGET     9   5      ; "package"
0090    FNEW    10  40      ; commonrequire.lua:63
0091    TSETS   10   9  39  ; "unloadAll"
0092    KPRI     9   0
0093    FNEW    10  41      ; commonrequire.lua:91
0094    GSET    10  42      ; "requireBackgroundRunner"
0095    FNEW    10  43      ; commonrequire.lua:102
0096    GSET    10  44      ; "stopBackgroundRunner"
0097    UCLO     0 => 0098
0098 => RET0     0   1

