-- BYTECODE -- common_info_menu_table.lua:19-23
0001    UGET     0   0      ; UIManager
0002    MOV      1   0
0003    TGETS    0   0   0  ; "show"
0004    UGET     2   1      ; InfoMessage
0005    MOV      3   2
0006    TGETS    2   2   1  ; "new"
0007    TDUP     4   2
0008    UGET     5   2      ; version
0009    TSETS    5   4   3  ; "text"
0010    CALL     2   0   3
0011    CALLM    0   1   1
0012    RET0     0   1

-- BYTECODE -- common_info_menu_table.lua:37-41
0001    GGET     0   0      ; "require"
0002    KSTR     1   1      ; "ui/quickstart"
0003    CALL     0   2   2
0004    GGET     1   0      ; "require"
0005    KSTR     2   2      ; "apps/reader/readerui"
0006    CALL     1   2   2
0007    MOV      3   1
0008    TGETS    2   1   3  ; "showReader"
0009    MOV      5   0
0010    TGETS    4   0   4  ; "getQuickStart"
0011    CALL     4   0   2
0012    CALLM    2   1   1
0013    RET0     0   1

-- BYTECODE -- common_info_menu_table.lua:46-52
0001    UGET     0   0      ; UIManager
0002    MOV      1   0
0003    TGETS    0   0   0  ; "show"
0004    UGET     2   1      ; InfoMessage
0005    MOV      3   2
0006    TGETS    2   2   1  ; "new"
0007    TDUP     4   4
0008    UGET     5   2      ; T
0009    UGET     6   3      ; _
0010    KSTR     7   2      ; "KOReader %1\n\nA document viewer for E I"~
0011    CALL     6   2   2
0012    UGET     7   4      ; BD
0013    TGETS    7   7   3  ; "ltr"
0014    UGET     8   5      ; version
0015    CALL     7   0   2
0016    CALLM    5   2   1
0017    TSETS    5   4   5  ; "text"
0018    CALL     2   0   3
0019    CALLM    0   1   1
0020    RET0     0   1

-- BYTECODE -- common_info_menu_table.lua:57-67
0001    UGET     0   0      ; Device
0002    TGETS    0   0   0  ; "model"
0003    UGET     1   0      ; Device
0004    MOV      2   1
0005    TGETS    1   1   1  ; "isAndroid"
0006    CALL     1   2   2
0007    ISF          1
0008    JMP      2 => 0014
0009    UGET     1   0      ; Device
0010    MOV      2   1
0011    TGETS    1   1   2  ; "info"
0012    CALL     1   2   2
0013    MOV      0   1
0014 => UGET     1   1      ; UIManager
0015    MOV      2   1
0016    TGETS    1   1   3  ; "show"
0017    UGET     3   2      ; InfoMessage
0018    MOV      4   3
0019    TGETS    3   3   4  ; "new"
0020    TDUP     5   6
0021    UGET     6   3      ; T
0022    UGET     7   4      ; _
0023    KSTR     8   5      ; "Please report bugs to \nhttps://github.c"~
0024    CALL     7   2   2
0025    UGET     8   5      ; version
0026    MOV      9   0
0027    CALL     6   2   4
0028    TSETS    6   5   7  ; "text"
0029    CALL     3   0   3
0030    CALLM    1   1   1
0031    RET0     0   1

-- BYTECODE -- common_info_menu_table.lua:73-75
0001    UGET     0   0      ; UIManager
0002    MOV      1   0
0003    TGETS    0   0   0  ; "suspend"
0004    CALL     0   1   2
0005    RET0     0   1

-- BYTECODE -- common_info_menu_table.lua:86-88
0001    UGET     0   0      ; UIManager
0002    MOV      1   0
0003    TGETS    0   0   0  ; "nextTick"
0004    UGET     2   0      ; UIManager
0005    TGETS    2   2   1  ; "reboot_action"
0006    CALL     0   1   3
0007    RET0     0   1

-- BYTECODE -- common_info_menu_table.lua:82-90
0001    UGET     0   0      ; UIManager
0002    MOV      1   0
0003    TGETS    0   0   0  ; "show"
0004    UGET     2   1      ; ConfirmBox
0005    MOV      3   2
0006    TGETS    2   2   1  ; "new"
0007    TDUP     4   3
0008    UGET     5   2      ; _
0009    KSTR     6   2      ; "Are you sure you want to reboot the devi"~
0010    CALL     5   2   2
0011    TSETS    5   4   4  ; "text"
0012    UGET     5   2      ; _
0013    KSTR     6   5      ; "Reboot"
0014    CALL     5   2   2
0015    TSETS    5   4   6  ; "ok_text"
0016    FNEW     5   7      ; common_info_menu_table.lua:86
0017    TSETS    5   4   8  ; "ok_callback"
0018    CALL     2   0   3
0019    CALLM    0   1   1
0020    RET0     0   1

-- BYTECODE -- common_info_menu_table.lua:101-103
0001    UGET     0   0      ; UIManager
0002    MOV      1   0
0003    TGETS    0   0   0  ; "nextTick"
0004    UGET     2   0      ; UIManager
0005    TGETS    2   2   1  ; "poweroff_action"
0006    CALL     0   1   3
0007    RET0     0   1

-- BYTECODE -- common_info_menu_table.lua:97-105
0001    UGET     0   0      ; UIManager
0002    MOV      1   0
0003    TGETS    0   0   0  ; "show"
0004    UGET     2   1      ; ConfirmBox
0005    MOV      3   2
0006    TGETS    2   2   1  ; "new"
0007    TDUP     4   3
0008    UGET     5   2      ; _
0009    KSTR     6   2      ; "Are you sure you want to power off the d"~
0010    CALL     5   2   2
0011    TSETS    5   4   4  ; "text"
0012    UGET     5   2      ; _
0013    KSTR     6   5      ; "Power off"
0014    CALL     5   2   2
0015    TSETS    5   4   6  ; "ok_text"
0016    FNEW     5   7      ; common_info_menu_table.lua:101
0017    TSETS    5   4   8  ; "ok_callback"
0018    CALL     2   0   3
0019    CALLM    0   1   1
0020    RET0     0   1

-- BYTECODE -- common_info_menu_table.lua:0-110
0001    GGET     0   0      ; "require"
0002    KSTR     1   1      ; "ui/bidi"
0003    CALL     0   2   2
0004    GGET     1   0      ; "require"
0005    KSTR     2   2      ; "ui/widget/confirmbox"
0006    CALL     1   2   2
0007    GGET     2   0      ; "require"
0008    KSTR     3   3      ; "device"
0009    CALL     2   2   2
0010    GGET     3   0      ; "require"
0011    KSTR     4   4      ; "ui/widget/infomessage"
0012    CALL     3   2   2
0013    GGET     4   0      ; "require"
0014    KSTR     5   5      ; "ui/uimanager"
0015    CALL     4   2   2
0016    GGET     5   0      ; "require"
0017    KSTR     6   6      ; "gettext"
0018    CALL     5   2   2
0019    GGET     6   0      ; "require"
0020    KSTR     7   7      ; "ffi/util"
0021    CALL     6   2   2
0022    TGETS    6   6   8  ; "template"
0023    TNEW     7   0
0024    MOV      9   2
0025    TGETS    8   2   9  ; "hasOTAUpdates"
0026    CALL     8   2   2
0027    ISF          8
0028    JMP      9 => 0036
0029    GGET     8   0      ; "require"
0030    KSTR     9  10      ; "ui/otamanager"
0031    CALL     8   2   2
0032    MOV     10   8
0033    TGETS    9   8  12  ; "getOTAMenuTable"
0034    CALL     9   2   2
0035    TSETS    9   7  11  ; "ota_update"
0036 => GGET     8   0      ; "require"
0037    KSTR     9  13      ; "version"
0038    CALL     8   2   2
0039    MOV      9   8
0040    TGETS    8   8  14  ; "getCurrentRevision"
0041    CALL     8   2   2
0042    TDUP     9  16
0043    MOV     10   5
0044    KSTR    11  15      ; "Version"
0045    CALL    10   2   2
0046    TSETS   10   9  17  ; "text"
0047    FNEW    10  18      ; common_info_menu_table.lua:19
0048    TSETS   10   9  19  ; "callback"
0049    TSETS    9   7  13  ; "version"
0050    TDUP     9  22
0051    MOV     10   5
0052    KSTR    11  21      ; "Help"
0053    CALL    10   2   2
0054    TSETS   10   9  17  ; "text"
0055    TSETS    9   7  20  ; "help"
0056    TDUP     9  25
0057    MOV     10   5
0058    KSTR    11  24      ; "More plugins"
0059    CALL    10   2   2
0060    TSETS   10   9  17  ; "text"
0061    TSETS    9   7  23  ; "more_plugins"
0062    TDUP     9  27
0063    MOV     10   5
0064    KSTR    11  26      ; "Device"
0065    CALL    10   2   2
0066    TSETS   10   9  17  ; "text"
0067    TSETS    9   7   3  ; "device"
0068    TDUP     9  30
0069    MOV     10   5
0070    KSTR    11  29      ; "Quickstart guide"
0071    CALL    10   2   2
0072    TSETS   10   9  17  ; "text"
0073    FNEW    10  31      ; common_info_menu_table.lua:37
0074    TSETS   10   9  19  ; "callback"
0075    TSETS    9   7  28  ; "quickstart_guide"
0076    TDUP     9  34
0077    MOV     10   5
0078    KSTR    11  33      ; "About"
0079    CALL    10   2   2
0080    TSETS   10   9  17  ; "text"
0081    FNEW    10  35      ; common_info_menu_table.lua:46
0082    TSETS   10   9  19  ; "callback"
0083    TSETS    9   7  32  ; "about"
0084    TDUP     9  38
0085    MOV     10   5
0086    KSTR    11  37      ; "Report a bug"
0087    CALL    10   2   2
0088    TSETS   10   9  17  ; "text"
0089    FNEW    10  39      ; common_info_menu_table.lua:57
0090    TSETS   10   9  19  ; "callback"
0091    TSETS    9   7  36  ; "report_bug"
0092    MOV     10   2
0093    TGETS    9   2  40  ; "isCervantes"
0094    CALL     9   2   2
0095    IST          9
0096    JMP     10 => 0107
0097    MOV     10   2
0098    TGETS    9   2  41  ; "isKindle"
0099    CALL     9   2   2
0100    IST          9
0101    JMP     10 => 0107
0102    MOV     10   2
0103    TGETS    9   2  42  ; "isKobo"
0104    CALL     9   2   2
0105    ISF          9
0106    JMP     10 => 0115
0107 => TDUP     9  45
0108    MOV     10   5
0109    KSTR    11  44      ; "Sleep"
0110    CALL    10   2   2
0111    TSETS   10   9  17  ; "text"
0112    FNEW    10  46      ; common_info_menu_table.lua:73
0113    TSETS   10   9  19  ; "callback"
0114    TSETS    9   7  43  ; "sleep"
0115 => MOV     10   2
0116    TGETS    9   2  47  ; "canReboot"
0117    CALL     9   2   2
0118    ISF          9
0119    JMP     10 => 0128
0120    TDUP     9  50
0121    MOV     10   5
0122    KSTR    11  49      ; "Reboot the device"
0123    CALL    10   2   2
0124    TSETS   10   9  17  ; "text"
0125    FNEW    10  51      ; common_info_menu_table.lua:82
0126    TSETS   10   9  19  ; "callback"
0127    TSETS    9   7  48  ; "reboot"
0128 => MOV     10   2
0129    TGETS    9   2  52  ; "canPowerOff"
0130    CALL     9   2   2
0131    ISF          9
0132    JMP     10 => 0141
0133    TDUP     9  55
0134    MOV     10   5
0135    KSTR    11  54      ; "Power off"
0136    CALL    10   2   2
0137    TSETS   10   9  17  ; "text"
0138    FNEW    10  56      ; common_info_menu_table.lua:97
0139    TSETS   10   9  19  ; "callback"
0140    TSETS    9   7  53  ; "poweroff"
0141 => UCLO     0 => 0142
0142 => RET1     7   2

