
main <./spec/unit/commonrequire.lua:0,0> (93 instructions, 372 bytes at 0x7fef9f4068c0)
0+ params, 11 slots, 0 upvalues, 10 locals, 39 constants, 7 functions
	1	[3]	GETGLOBAL	0 -1	; require
	2	[3]	LOADK    	1 -2	; "ffi"
	3	[3]	CALL     	0 2 2
	4	[4]	GETTABLE 	1 0 -3	; "metatype"
	5	[5]	NEWTABLE 	2 0 0
	6	[10]	CLOSURE  	3 0	; 0x7fef9f406a80
	7	[10]	MOVE     	0 2
	8	[10]	MOVE     	0 1
	9	[10]	SETTABLE 	0 -3 3	; "metatype" -
	10	[12]	GETGLOBAL	3 -1	; require
	11	[12]	LOADK    	4 -4	; "defaults"
	12	[12]	CALL     	3 2 1
	13	[13]	GETGLOBAL	3 -5	; package
	14	[13]	LOADK    	4 -7	; "?.lua;common/?.lua;rocks/share/lua/5.1/?.lua;frontend/?.lua;"
	15	[13]	GETGLOBAL	5 -5	; package
	16	[13]	GETTABLE 	5 5 -6	; "path"
	17	[13]	CONCAT   	4 4 5
	18	[13]	SETTABLE 	3 -6 4	; "path" -
	19	[14]	GETGLOBAL	3 -5	; package
	20	[14]	LOADK    	4 -9	; "?.so;common/?.so;/usr/lib/lua/?.so;rocks/lib/lua/5.1/?.so;"
	21	[14]	GETGLOBAL	5 -5	; package
	22	[14]	GETTABLE 	5 5 -8	; "cpath"
	23	[14]	CONCAT   	4 4 5
	24	[14]	SETTABLE 	3 -8 4	; "cpath" -
	25	[17]	GETGLOBAL	3 -1	; require
	26	[17]	LOADK    	4 -10	; "dbg"
	27	[17]	CALL     	3 2 2
	28	[17]	SELF     	3 3 -11	; "turnOff"
	29	[17]	CALL     	3 2 1
	30	[18]	GETGLOBAL	3 -1	; require
	31	[18]	LOADK    	4 -12	; "logger"
	32	[18]	CALL     	3 2 2
	33	[19]	SELF     	4 3 -13	; "setLevel"
	34	[19]	GETTABLE 	6 3 -14	; "levels"
	35	[19]	GETTABLE 	6 6 -15	; "warn"
	36	[19]	CALL     	4 3 1
	37	[22]	GETGLOBAL	4 -1	; require
	38	[22]	LOADK    	5 -16	; "datastorage"
	39	[22]	CALL     	4 2 2
	40	[23]	GETGLOBAL	5 -17	; os
	41	[23]	GETTABLE 	5 5 -18	; "remove"
	42	[23]	SELF     	6 4 -19	; "getDataDir"
	43	[23]	CALL     	6 2 2
	44	[23]	LOADK    	7 -20	; "/settings.reader.lua"
	45	[23]	CONCAT   	6 6 7
	46	[23]	CALL     	5 2 1
	47	[24]	GETGLOBAL	5 -1	; require
	48	[24]	LOADK    	6 -22	; "luasettings"
	49	[24]	CALL     	5 2 2
	50	[24]	SELF     	5 5 -23	; "open"
	51	[24]	LOADK    	7 -24	; ".reader"
	52	[24]	CALL     	5 3 2
	53	[24]	SETGLOBAL	5 -21	; G_reader_settings
	54	[27]	GETGLOBAL	5 -1	; require
	55	[27]	LOADK    	6 -26	; "ffi/framebuffer"
	56	[27]	CALL     	5 2 2
	57	[27]	SETGLOBAL	5 -25	; einkfb
	58	[28]	GETGLOBAL	5 -25	; einkfb
	59	[28]	SETTABLE 	5 -27 -28	; "dummy" true
	60	[30]	GETGLOBAL	5 -1	; require
	61	[30]	LOADK    	6 -29	; "device"
	62	[30]	CALL     	5 2 2
	63	[33]	GETTABLE 	6 5 -30	; "screen"
	64	[34]	SELF     	7 6 -31	; "init"
	65	[34]	CALL     	7 2 1
	66	[36]	GETGLOBAL	7 -1	; require
	67	[36]	LOADK    	8 -32	; "document/canvascontext"
	68	[36]	CALL     	7 2 2
	69	[37]	SELF     	8 7 -31	; "init"
	70	[37]	MOVE     	10 5
	71	[37]	CALL     	8 3 1
	72	[40]	GETTABLE 	8 5 -33	; "input"
	73	[41]	SETTABLE 	8 -27 -28	; "dummy" true
	74	[43]	GETGLOBAL	9 -5	; package
	75	[48]	CLOSURE  	10 1	; 0x7fef9f407500
	76	[48]	SETTABLE 	9 -34 10	; "unload" -
	77	[50]	GETGLOBAL	9 -5	; package
	78	[55]	CLOSURE  	10 2	; 0x7fef9f4076c0
	79	[55]	SETTABLE 	9 -35 10	; "replace" -
	80	[57]	GETGLOBAL	9 -5	; package
	81	[61]	CLOSURE  	10 3	; 0x7fef9f407bd0
	82	[61]	SETTABLE 	9 -36 10	; "reload" -
	83	[63]	GETGLOBAL	9 -5	; package
	84	[88]	CLOSURE  	10 4	; 0x7fef9f408590
	85	[88]	SETTABLE 	9 -37 10	; "unloadAll" -
	86	[90]	LOADNIL  	9 9
	87	[100]	CLOSURE  	10 5	; 0x7fef9f4067c0
	88	[100]	MOVE     	0 9
	89	[100]	SETGLOBAL	10 -38	; requireBackgroundRunner
	90	[105]	CLOSURE  	10 6	; 0x7fef9f408e70
	91	[105]	MOVE     	0 9
	92	[105]	SETGLOBAL	10 -39	; stopBackgroundRunner
	93	[105]	RETURN   	0 1

function <./spec/unit/commonrequire.lua:6,10> (17 instructions, 68 bytes at 0x7fef9f406a80)
2 params, 6 slots, 2 upvalues, 2 locals, 0 constants, 0 functions
	1	[7]	GETUPVAL 	2 0	; exists
	2	[7]	GETTABLE 	2 2 0
	3	[7]	TEST     	2 0 0
	4	[7]	JMP      	3	; to 8
	5	[7]	GETUPVAL 	2 0	; exists
	6	[7]	GETTABLE 	2 2 0
	7	[7]	RETURN   	2 2
	8	[8]	GETUPVAL 	2 0	; exists
	9	[8]	GETUPVAL 	3 1	; old_metatype
	10	[8]	MOVE     	4 0
	11	[8]	MOVE     	5 1
	12	[8]	CALL     	3 3 2
	13	[8]	SETTABLE 	2 0 3
	14	[9]	GETUPVAL 	2 0	; exists
	15	[9]	GETTABLE 	2 2 0
	16	[9]	RETURN   	2 2
	17	[10]	RETURN   	0 1

function <./spec/unit/commonrequire.lua:43,48> (15 instructions, 60 bytes at 0x7fef9f407500)
1 param, 3 slots, 0 upvalues, 1 local, 6 constants, 0 functions
	1	[44]	GETGLOBAL	1 -1	; type
	2	[44]	MOVE     	2 0
	3	[44]	CALL     	1 2 2
	4	[44]	EQ       	1 1 -2	; - "string"
	5	[44]	JMP      	2	; to 8
	6	[44]	LOADBOOL 	1 0 0
	7	[44]	RETURN   	1 2
	8	[45]	GETGLOBAL	1 -3	; package
	9	[45]	GETTABLE 	1 1 -4	; "loaded"
	10	[45]	SETTABLE 	1 0 -5	; - nil
	11	[46]	GETGLOBAL	1 -6	; _G
	12	[46]	SETTABLE 	1 0 -5	; - nil
	13	[47]	LOADBOOL 	1 1 0
	14	[47]	RETURN   	1 2
	15	[48]	RETURN   	0 1

function <./spec/unit/commonrequire.lua:50,55> (19 instructions, 76 bytes at 0x7fef9f4076c0)
2 params, 5 slots, 0 upvalues, 2 locals, 6 constants, 0 functions
	1	[51]	GETGLOBAL	2 -1	; type
	2	[51]	MOVE     	3 0
	3	[51]	CALL     	2 2 2
	4	[51]	EQ       	1 2 -2	; - "string"
	5	[51]	JMP      	2	; to 8
	6	[51]	LOADBOOL 	2 0 0
	7	[51]	RETURN   	2 2
	8	[52]	GETGLOBAL	2 -3	; assert
	9	[52]	GETGLOBAL	3 -4	; package
	10	[52]	GETTABLE 	3 3 -5	; "unload"
	11	[52]	MOVE     	4 0
	12	[52]	CALL     	3 2 0
	13	[52]	CALL     	2 0 1
	14	[53]	GETGLOBAL	2 -4	; package
	15	[53]	GETTABLE 	2 2 -6	; "loaded"
	16	[53]	SETTABLE 	2 0 1
	17	[54]	LOADBOOL 	2 1 0
	18	[54]	RETURN   	2 2
	19	[55]	RETURN   	0 1

function <./spec/unit/commonrequire.lua:57,61> (18 instructions, 72 bytes at 0x7fef9f407bd0)
1 param, 4 slots, 0 upvalues, 1 local, 6 constants, 0 functions
	1	[58]	GETGLOBAL	1 -1	; type
	2	[58]	MOVE     	2 0
	3	[58]	CALL     	1 2 2
	4	[58]	EQ       	1 1 -2	; - "string"
	5	[58]	JMP      	2	; to 8
	6	[58]	LOADBOOL 	1 0 0
	7	[58]	RETURN   	1 2
	8	[59]	GETGLOBAL	1 -3	; assert
	9	[59]	GETGLOBAL	2 -4	; package
	10	[59]	GETTABLE 	2 2 -5	; "unload"
	11	[59]	MOVE     	3 0
	12	[59]	CALL     	2 2 0
	13	[59]	CALL     	1 0 1
	14	[60]	GETGLOBAL	1 -6	; require
	15	[60]	MOVE     	2 0
	16	[60]	TAILCALL 	1 2 0
	17	[60]	RETURN   	1 0
	18	[61]	RETURN   	0 1

function <./spec/unit/commonrequire.lua:63,88> (56 instructions, 224 bytes at 0x7fef9f408590)
0 params, 16 slots, 0 upvalues, 18 locals, 19 constants, 0 functions
	1	[64]	NEWTABLE 	0 5 0
	2	[65]	LOADK    	1 -1	; "spec/"
	3	[66]	LOADK    	2 -2	; "frontend/"
	4	[67]	LOADK    	3 -3	; "plugins/"
	5	[68]	LOADK    	4 -4	; "datastorage.lua"
	6	[70]	LOADK    	5 -5	; "defaults.lua"
	7	[70]	SETLIST  	0 5 1	; 1
	8	[71]	NEWTABLE 	1 0 0
	9	[72]	GETGLOBAL	2 -6	; pairs
	10	[72]	GETGLOBAL	3 -7	; package
	11	[72]	GETTABLE 	3 3 -8	; "loaded"
	12	[72]	CALL     	2 2 4
	13	[72]	JMP      	24	; to 38
	14	[73]	GETGLOBAL	7 -7	; package
	15	[73]	GETTABLE 	7 7 -9	; "searchpath"
	16	[73]	MOVE     	8 5
	17	[73]	GETGLOBAL	9 -7	; package
	18	[73]	GETTABLE 	9 9 -10	; "path"
	19	[73]	CALL     	7 3 2
	20	[74]	EQ       	1 7 -11	; - nil
	21	[74]	JMP      	16	; to 38
	22	[75]	GETGLOBAL	8 -12	; ipairs
	23	[75]	MOVE     	9 0
	24	[75]	CALL     	8 2 4
	25	[75]	JMP      	10	; to 36
	26	[76]	SELF     	13 7 -13	; "find"
	27	[76]	MOVE     	15 12
	28	[76]	CALL     	13 3 2
	29	[76]	EQ       	0 13 -14	; - 1
	30	[76]	JMP      	5	; to 36
	31	[77]	GETGLOBAL	13 -15	; table
	32	[77]	GETTABLE 	13 13 -16	; "insert"
	33	[77]	MOVE     	14 1
	34	[77]	MOVE     	15 5
	35	[77]	CALL     	13 3 1
	36	[75]	TFORLOOP 	8 2
	37	[78]	JMP      	-12	; to 26
	38	[72]	TFORLOOP 	2 2
	39	[80]	JMP      	-26	; to 14
	40	[82]	GETGLOBAL	2 -12	; ipairs
	41	[82]	MOVE     	3 1
	42	[82]	CALL     	2 2 4
	43	[82]	JMP      	8	; to 52
	44	[83]	EQ       	1 6 -17	; - "commonrequire"
	45	[83]	JMP      	6	; to 52
	46	[84]	GETGLOBAL	7 -18	; assert
	47	[84]	GETGLOBAL	8 -7	; package
	48	[84]	GETTABLE 	8 8 -19	; "unload"
	49	[84]	MOVE     	9 6
	50	[84]	CALL     	8 2 0
	51	[84]	CALL     	7 0 1
	52	[82]	TFORLOOP 	2 2
	53	[85]	JMP      	-10	; to 44
	54	[87]	LEN      	2 1
	55	[87]	RETURN   	2 2
	56	[88]	RETURN   	0 1

function <./spec/unit/commonrequire.lua:91,100> (24 instructions, 96 bytes at 0x7fef9f4067c0)
0 params, 4 slots, 1 upvalue, 1 local, 9 constants, 0 functions
	1	[92]	GETGLOBAL	0 -1	; require
	2	[92]	LOADK    	1 -2	; "pluginshare"
	3	[92]	CALL     	0 2 2
	4	[92]	SETTABLE 	0 -3 -4	; "stopBackgroundRunner" nil
	5	[93]	GETUPVAL 	0 0	; background_runner
	6	[93]	EQ       	0 0 -4	; - nil
	7	[93]	JMP      	14	; to 22
	8	[94]	GETGLOBAL	0 -5	; package
	9	[94]	GETTABLE 	0 0 -6	; "path"
	10	[95]	GETGLOBAL	1 -5	; package
	11	[95]	LOADK    	2 -7	; "plugins/backgroundrunner.koplugin/?.lua;"
	12	[95]	GETGLOBAL	3 -5	; package
	13	[95]	GETTABLE 	3 3 -6	; "path"
	14	[95]	CONCAT   	2 2 3
	15	[95]	SETTABLE 	1 -6 2	; "path" -
	16	[96]	GETGLOBAL	1 -8	; dofile
	17	[96]	LOADK    	2 -9	; "plugins/backgroundrunner.koplugin/main.lua"
	18	[96]	CALL     	1 2 2
	19	[96]	SETUPVAL 	1 0	; background_runner
	20	[97]	GETGLOBAL	1 -5	; package
	21	[97]	SETTABLE 	1 -6 0	; "path" -
	22	[99]	GETUPVAL 	0 0	; background_runner
	23	[99]	RETURN   	0 2
	24	[100]	RETURN   	0 1

function <./spec/unit/commonrequire.lua:102,105> (6 instructions, 24 bytes at 0x7fef9f408e70)
0 params, 2 slots, 1 upvalue, 0 locals, 4 constants, 0 functions
	1	[103]	SETUPVAL 	0 0	; background_runner
	2	[104]	GETGLOBAL	0 -1	; require
	3	[104]	LOADK    	1 -2	; "pluginshare"
	4	[104]	CALL     	0 2 2
	5	[104]	SETTABLE 	0 -3 -4	; "stopBackgroundRunner" true
	6	[105]	RETURN   	0 1
