
main <./frontend/ui/elements/common_info_menu_table.lua:0,0> (161 instructions, 644 bytes at 0x7fedde406900)
0+ params, 12 slots, 0 upvalues, 10 locals, 42 constants, 7 functions
	1	[1]	GETGLOBAL	0 -1	; require
	2	[1]	LOADK    	1 -2	; "ui/bidi"
	3	[1]	CALL     	0 2 2
	4	[2]	GETGLOBAL	1 -1	; require
	5	[2]	LOADK    	2 -3	; "ui/widget/confirmbox"
	6	[2]	CALL     	1 2 2
	7	[3]	GETGLOBAL	2 -1	; require
	8	[3]	LOADK    	3 -4	; "device"
	9	[3]	CALL     	2 2 2
	10	[4]	GETGLOBAL	3 -1	; require
	11	[4]	LOADK    	4 -5	; "ui/widget/infomessage"
	12	[4]	CALL     	3 2 2
	13	[5]	GETGLOBAL	4 -1	; require
	14	[5]	LOADK    	5 -6	; "ui/uimanager"
	15	[5]	CALL     	4 2 2
	16	[6]	GETGLOBAL	5 -1	; require
	17	[6]	LOADK    	6 -7	; "gettext"
	18	[6]	CALL     	5 2 2
	19	[7]	GETGLOBAL	6 -1	; require
	20	[7]	LOADK    	7 -8	; "ffi/util"
	21	[7]	CALL     	6 2 2
	22	[7]	GETTABLE 	6 6 -9	; "template"
	23	[9]	NEWTABLE 	7 0 0
	24	[11]	SELF     	8 2 -10	; "hasOTAUpdates"
	25	[11]	CALL     	8 2 2
	26	[11]	TEST     	8 0 0
	27	[11]	JMP      	6	; to 34
	28	[12]	GETGLOBAL	8 -1	; require
	29	[12]	LOADK    	9 -11	; "ui/otamanager"
	30	[12]	CALL     	8 2 2
	31	[13]	SELF     	9 8 -13	; "getOTAMenuTable"
	32	[13]	CALL     	9 2 2
	33	[13]	SETTABLE 	7 -12 9	; "ota_update" -
	34	[15]	GETGLOBAL	8 -1	; require
	35	[15]	LOADK    	9 -14	; "version"
	36	[15]	CALL     	8 2 2
	37	[15]	SELF     	8 8 -15	; "getCurrentRevision"
	38	[15]	CALL     	8 2 2
	39	[16]	NEWTABLE 	9 0 3
	40	[17]	MOVE     	10 5
	41	[17]	LOADK    	11 -17	; "Version"
	42	[17]	CALL     	10 2 2
	43	[17]	SETTABLE 	9 -16 10	; "text" -
	44	[18]	SETTABLE 	9 -18 -19	; "keep_menu_open" true
	45	[23]	CLOSURE  	10 0	; 0x7fedde4070a0
	46	[23]	MOVE     	0 4
	47	[23]	MOVE     	0 3
	48	[23]	MOVE     	0 8
	49	[23]	SETTABLE 	9 -20 10	; "callback" -
	50	[24]	SETTABLE 	7 -14 9	; "version" -
	51	[25]	NEWTABLE 	9 0 1
	52	[26]	MOVE     	10 5
	53	[26]	LOADK    	11 -22	; "Help"
	54	[26]	CALL     	10 2 2
	55	[26]	SETTABLE 	9 -16 10	; "text" -
	56	[27]	SETTABLE 	7 -21 9	; "help" -
	57	[28]	NEWTABLE 	9 0 1
	58	[29]	MOVE     	10 5
	59	[29]	LOADK    	11 -24	; "More plugins"
	60	[29]	CALL     	10 2 2
	61	[29]	SETTABLE 	9 -16 10	; "text" -
	62	[30]	SETTABLE 	7 -23 9	; "more_plugins" -
	63	[32]	NEWTABLE 	9 0 1
	64	[33]	MOVE     	10 5
	65	[33]	LOADK    	11 -25	; "Device"
	66	[33]	CALL     	10 2 2
	67	[33]	SETTABLE 	9 -16 10	; "text" -
	68	[34]	SETTABLE 	7 -4 9	; "device" -
	69	[35]	NEWTABLE 	9 0 2
	70	[36]	MOVE     	10 5
	71	[36]	LOADK    	11 -27	; "Quickstart guide"
	72	[36]	CALL     	10 2 2
	73	[36]	SETTABLE 	9 -16 10	; "text" -
	74	[41]	CLOSURE  	10 1	; 0x7fedde406620
	75	[41]	SETTABLE 	9 -20 10	; "callback" -
	76	[42]	SETTABLE 	7 -26 9	; "quickstart_guide" -
	77	[43]	NEWTABLE 	9 0 3
	78	[44]	MOVE     	10 5
	79	[44]	LOADK    	11 -29	; "About"
	80	[44]	CALL     	10 2 2
	81	[44]	SETTABLE 	9 -16 10	; "text" -
	82	[45]	SETTABLE 	9 -18 -19	; "keep_menu_open" true
	83	[52]	CLOSURE  	10 2	; 0x7fedde407ab0
	84	[52]	MOVE     	0 4
	85	[52]	MOVE     	0 3
	86	[52]	MOVE     	0 6
	87	[52]	MOVE     	0 5
	88	[52]	MOVE     	0 0
	89	[52]	MOVE     	0 8
	90	[52]	SETTABLE 	9 -20 10	; "callback" -
	91	[53]	SETTABLE 	7 -28 9	; "about" -
	92	[54]	NEWTABLE 	9 0 3
	93	[55]	MOVE     	10 5
	94	[55]	LOADK    	11 -31	; "Report a bug"
	95	[55]	CALL     	10 2 2
	96	[55]	SETTABLE 	9 -16 10	; "text" -
	97	[56]	SETTABLE 	9 -18 -19	; "keep_menu_open" true
	98	[67]	CLOSURE  	10 3	; 0x7fedde408300
	99	[67]	MOVE     	0 2
	100	[67]	MOVE     	0 4
	101	[67]	MOVE     	0 3
	102	[67]	MOVE     	0 6
	103	[67]	MOVE     	0 5
	104	[67]	MOVE     	0 8
	105	[67]	SETTABLE 	9 -20 10	; "callback" -
	106	[68]	SETTABLE 	7 -30 9	; "report_bug" -
	107	[70]	SELF     	9 2 -32	; "isCervantes"
	108	[70]	CALL     	9 2 2
	109	[70]	TEST     	9 0 1
	110	[70]	JMP      	8	; to 119
	111	[70]	SELF     	9 2 -33	; "isKindle"
	112	[70]	CALL     	9 2 2
	113	[70]	TEST     	9 0 1
	114	[70]	JMP      	4	; to 119
	115	[70]	SELF     	9 2 -34	; "isKobo"
	116	[70]	CALL     	9 2 2
	117	[70]	TEST     	9 0 0
	118	[70]	JMP      	9	; to 128
	119	[71]	NEWTABLE 	9 0 2
	120	[72]	MOVE     	10 5
	121	[72]	LOADK    	11 -36	; "Sleep"
	122	[72]	CALL     	10 2 2
	123	[72]	SETTABLE 	9 -16 10	; "text" -
	124	[75]	CLOSURE  	10 4	; 0x7fedde407180
	125	[75]	MOVE     	0 4
	126	[75]	SETTABLE 	9 -20 10	; "callback" -
	127	[76]	SETTABLE 	7 -35 9	; "sleep" -
	128	[78]	SELF     	9 2 -37	; "canReboot"
	129	[78]	CALL     	9 2 2
	130	[78]	TEST     	9 0 0
	131	[78]	JMP      	12	; to 144
	132	[79]	NEWTABLE 	9 0 3
	133	[80]	MOVE     	10 5
	134	[80]	LOADK    	11 -39	; "Reboot the device"
	135	[80]	CALL     	10 2 2
	136	[80]	SETTABLE 	9 -16 10	; "text" -
	137	[81]	SETTABLE 	9 -18 -19	; "keep_menu_open" true
	138	[90]	CLOSURE  	10 5	; 0x7fedde4067c0
	139	[90]	MOVE     	0 4
	140	[90]	MOVE     	0 1
	141	[90]	MOVE     	0 5
	142	[90]	SETTABLE 	9 -20 10	; "callback" -
	143	[91]	SETTABLE 	7 -38 9	; "reboot" -
	144	[93]	SELF     	9 2 -40	; "canPowerOff"
	145	[93]	CALL     	9 2 2
	146	[93]	TEST     	9 0 0
	147	[93]	JMP      	12	; to 160
	148	[94]	NEWTABLE 	9 0 3
	149	[95]	MOVE     	10 5
	150	[95]	LOADK    	11 -42	; "Power off"
	151	[95]	CALL     	10 2 2
	152	[95]	SETTABLE 	9 -16 10	; "text" -
	153	[96]	SETTABLE 	9 -18 -19	; "keep_menu_open" true
	154	[105]	CLOSURE  	10 6	; 0x7fedde407610
	155	[105]	MOVE     	0 4
	156	[105]	MOVE     	0 1
	157	[105]	MOVE     	0 5
	158	[105]	SETTABLE 	9 -20 10	; "callback" -
	159	[106]	SETTABLE 	7 -41 9	; "poweroff" -
	160	[109]	RETURN   	7 2
	161	[109]	RETURN   	0 1

function <./frontend/ui/elements/common_info_menu_table.lua:19,23> (10 instructions, 40 bytes at 0x7fedde4070a0)
0 params, 6 slots, 3 upvalues, 0 locals, 3 constants, 0 functions
	1	[20]	GETUPVAL 	0 0	; UIManager
	2	[20]	SELF     	0 0 -1	; "show"
	3	[20]	GETUPVAL 	2 1	; InfoMessage
	4	[20]	SELF     	2 2 -2	; "new"
	5	[20]	NEWTABLE 	4 0 1
	6	[21]	GETUPVAL 	5 2	; version
	7	[21]	SETTABLE 	4 -3 5	; "text" -
	8	[20]	CALL     	2 3 0
	9	[20]	CALL     	0 0 1
	10	[23]	RETURN   	0 1

function <./frontend/ui/elements/common_info_menu_table.lua:37,41> (11 instructions, 44 bytes at 0x7fedde406620)
0 params, 6 slots, 0 upvalues, 2 locals, 5 constants, 0 functions
	1	[38]	GETGLOBAL	0 -1	; require
	2	[38]	LOADK    	1 -2	; "ui/quickstart"
	3	[38]	CALL     	0 2 2
	4	[39]	GETGLOBAL	1 -1	; require
	5	[39]	LOADK    	2 -3	; "apps/reader/readerui"
	6	[39]	CALL     	1 2 2
	7	[40]	SELF     	2 1 -4	; "showReader"
	8	[40]	SELF     	4 0 -5	; "getQuickStart"
	9	[40]	CALL     	4 2 0
	10	[40]	CALL     	2 0 1
	11	[41]	RETURN   	0 1

function <./frontend/ui/elements/common_info_menu_table.lua:46,52> (20 instructions, 80 bytes at 0x7fedde407ab0)
0 params, 9 slots, 6 upvalues, 0 locals, 9 constants, 0 functions
	1	[47]	GETUPVAL 	0 0	; UIManager
	2	[47]	SELF     	0 0 -1	; "show"
	3	[47]	GETUPVAL 	2 1	; InfoMessage
	4	[47]	SELF     	2 2 -2	; "new"
	5	[47]	NEWTABLE 	4 0 3
	6	[48]	GETUPVAL 	5 2	; T
	7	[48]	GETUPVAL 	6 3	; _
	8	[48]	LOADK    	7 -4	; "KOReader %1\n\nA document viewer for E Ink devices.\n\nLicensed under Affero GPL v3. All dependencies are free software.\n\nhttp://koreader.rocks/"
	9	[48]	CALL     	6 2 2
	10	[48]	GETUPVAL 	7 4	; BD
	11	[48]	GETTABLE 	7 7 -5	; "ltr"
	12	[48]	GETUPVAL 	8 5	; version
	13	[48]	CALL     	7 2 0
	14	[48]	CALL     	5 0 2
	15	[48]	SETTABLE 	4 -3 5	; "text" -
	16	[49]	SETTABLE 	4 -6 -7	; "icon_file" "resources/ko-icon.png"
	17	[50]	SETTABLE 	4 -8 -9	; "alpha" true
	18	[47]	CALL     	2 3 0
	19	[47]	CALL     	0 0 1
	20	[52]	RETURN   	0 1

function <./frontend/ui/elements/common_info_menu_table.lua:57,67> (27 instructions, 108 bytes at 0x7fedde408300)
0 params, 10 slots, 6 upvalues, 1 local, 7 constants, 0 functions
	1	[58]	GETUPVAL 	0 0	; Device
	2	[58]	GETTABLE 	0 0 -1	; "model"
	3	[59]	GETUPVAL 	1 0	; Device
	4	[59]	SELF     	1 1 -2	; "isAndroid"
	5	[59]	CALL     	1 2 2
	6	[59]	TEST     	1 0 0
	7	[59]	JMP      	4	; to 12
	8	[60]	GETUPVAL 	1 0	; Device
	9	[60]	SELF     	1 1 -3	; "info"
	10	[60]	CALL     	1 2 2
	11	[60]	MOVE     	0 1
	12	[63]	GETUPVAL 	1 1	; UIManager
	13	[63]	SELF     	1 1 -4	; "show"
	14	[63]	GETUPVAL 	3 2	; InfoMessage
	15	[63]	SELF     	3 3 -5	; "new"
	16	[63]	NEWTABLE 	5 0 1
	17	[64]	GETUPVAL 	6 3	; T
	18	[64]	GETUPVAL 	7 4	; _
	19	[64]	LOADK    	8 -7	; "Please report bugs to \nhttps://github.com/koreader/koreader/issues\n\nVersion:\n%1\n\nDetected device:\n%2"
	20	[64]	CALL     	7 2 2
	21	[65]	GETUPVAL 	8 5	; version
	22	[65]	MOVE     	9 0
	23	[64]	CALL     	6 4 2
	24	[65]	SETTABLE 	5 -6 6	; "text" -
	25	[63]	CALL     	3 3 0
	26	[63]	CALL     	1 0 1
	27	[67]	RETURN   	0 1

function <./frontend/ui/elements/common_info_menu_table.lua:73,75> (4 instructions, 16 bytes at 0x7fedde407180)
0 params, 2 slots, 1 upvalue, 0 locals, 1 constant, 0 functions
	1	[74]	GETUPVAL 	0 0	; UIManager
	2	[74]	SELF     	0 0 -1	; "suspend"
	3	[74]	CALL     	0 2 1
	4	[75]	RETURN   	0 1

function <./frontend/ui/elements/common_info_menu_table.lua:82,90> (19 instructions, 76 bytes at 0x7fedde4067c0)
0 params, 7 slots, 3 upvalues, 0 locals, 7 constants, 1 function
	1	[83]	GETUPVAL 	0 0	; UIManager
	2	[83]	SELF     	0 0 -1	; "show"
	3	[83]	GETUPVAL 	2 1	; ConfirmBox
	4	[83]	SELF     	2 2 -2	; "new"
	5	[83]	NEWTABLE 	4 0 3
	6	[84]	GETUPVAL 	5 2	; _
	7	[84]	LOADK    	6 -4	; "Are you sure you want to reboot the device?"
	8	[84]	CALL     	5 2 2
	9	[84]	SETTABLE 	4 -3 5	; "text" -
	10	[85]	GETUPVAL 	5 2	; _
	11	[85]	LOADK    	6 -6	; "Reboot"
	12	[85]	CALL     	5 2 2
	13	[85]	SETTABLE 	4 -5 5	; "ok_text" -
	14	[88]	CLOSURE  	5 0	; 0x7fedde407450
	15	[88]	GETUPVAL 	0 0	; UIManager
	16	[88]	SETTABLE 	4 -7 5	; "ok_callback" -
	17	[83]	CALL     	2 3 0
	18	[83]	CALL     	0 0 1
	19	[90]	RETURN   	0 1

function <./frontend/ui/elements/common_info_menu_table.lua:86,88> (6 instructions, 24 bytes at 0x7fedde407450)
0 params, 3 slots, 1 upvalue, 0 locals, 2 constants, 0 functions
	1	[87]	GETUPVAL 	0 0	; UIManager
	2	[87]	SELF     	0 0 -1	; "nextTick"
	3	[87]	GETUPVAL 	2 0	; UIManager
	4	[87]	GETTABLE 	2 2 -2	; "reboot_action"
	5	[87]	CALL     	0 3 1
	6	[88]	RETURN   	0 1

function <./frontend/ui/elements/common_info_menu_table.lua:97,105> (19 instructions, 76 bytes at 0x7fedde407610)
0 params, 7 slots, 3 upvalues, 0 locals, 7 constants, 1 function
	1	[98]	GETUPVAL 	0 0	; UIManager
	2	[98]	SELF     	0 0 -1	; "show"
	3	[98]	GETUPVAL 	2 1	; ConfirmBox
	4	[98]	SELF     	2 2 -2	; "new"
	5	[98]	NEWTABLE 	4 0 3
	6	[99]	GETUPVAL 	5 2	; _
	7	[99]	LOADK    	6 -4	; "Are you sure you want to power off the device?"
	8	[99]	CALL     	5 2 2
	9	[99]	SETTABLE 	4 -3 5	; "text" -
	10	[100]	GETUPVAL 	5 2	; _
	11	[100]	LOADK    	6 -6	; "Power off"
	12	[100]	CALL     	5 2 2
	13	[100]	SETTABLE 	4 -5 5	; "ok_text" -
	14	[103]	CLOSURE  	5 0	; 0x7fedde4077e0
	15	[103]	GETUPVAL 	0 0	; UIManager
	16	[103]	SETTABLE 	4 -7 5	; "ok_callback" -
	17	[98]	CALL     	2 3 0
	18	[98]	CALL     	0 0 1
	19	[105]	RETURN   	0 1

function <./frontend/ui/elements/common_info_menu_table.lua:101,103> (6 instructions, 24 bytes at 0x7fedde4077e0)
0 params, 3 slots, 1 upvalue, 0 locals, 2 constants, 0 functions
	1	[102]	GETUPVAL 	0 0	; UIManager
	2	[102]	SELF     	0 0 -1	; "nextTick"
	3	[102]	GETUPVAL 	2 0	; UIManager
	4	[102]	GETTABLE 	2 2 -2	; "poweroff_action"
	5	[102]	CALL     	0 3 1
	6	[103]	RETURN   	0 1
