
main <./frontend/ui/elements/common_settings_menu_table.lua:0,0> (777 instructions, 3108 bytes at 0x7f9929406900)
0+ params, 34 slots, 0 upvalues, 23 locals, 158 constants, 82 functions
	1	[1]	GETGLOBAL	0 -1	; require
	2	[1]	LOADK    	1 -2	; "ui/widget/datewidget"
	3	[1]	CALL     	0 2 2
	4	[2]	GETGLOBAL	1 -1	; require
	5	[2]	LOADK    	2 -3	; "device"
	6	[2]	CALL     	1 2 2
	7	[3]	GETGLOBAL	2 -1	; require
	8	[3]	LOADK    	3 -4	; "ui/event"
	9	[3]	CALL     	2 2 2
	10	[4]	GETGLOBAL	3 -1	; require
	11	[4]	LOADK    	4 -5	; "ui/widget/infomessage"
	12	[4]	CALL     	3 2 2
	13	[5]	GETGLOBAL	4 -1	; require
	14	[5]	LOADK    	5 -6	; "ui/language"
	15	[5]	CALL     	4 2 2
	16	[6]	GETGLOBAL	5 -1	; require
	17	[6]	LOADK    	6 -7	; "ui/network/manager"
	18	[6]	CALL     	5 2 2
	19	[7]	GETGLOBAL	6 -1	; require
	20	[7]	LOADK    	7 -8	; "ui/uimanager"
	21	[7]	CALL     	6 2 2
	22	[8]	GETGLOBAL	7 -1	; require
	23	[8]	LOADK    	8 -9	; "ui/widget/timewidget"
	24	[8]	CALL     	7 2 2
	25	[9]	GETGLOBAL	8 -1	; require
	26	[9]	LOADK    	9 -10	; "gettext"
	27	[9]	CALL     	8 2 2
	28	[10]	GETTABLE 	9 8 -11	; "ngettext"
	29	[11]	GETTABLE 	10 1 -12	; "screen"
	30	[12]	GETGLOBAL	11 -1	; require
	31	[12]	LOADK    	12 -13	; "ffi/util"
	32	[12]	CALL     	11 2 2
	33	[12]	GETTABLE 	11 11 -14	; "template"
	34	[14]	NEWTABLE 	12 0 0
	35	[16]	SELF     	13 1 -15	; "isCervantes"
	36	[16]	CALL     	13 2 2
	37	[16]	TEST     	13 0 0
	38	[16]	JMP      	20	; to 59
	39	[17]	GETGLOBAL	13 -1	; require
	40	[17]	LOADK    	14 -16	; "util"
	41	[17]	CALL     	13 2 2
	42	[18]	GETTABLE 	14 13 -17	; "pathExists"
	43	[18]	LOADK    	15 -18	; "/usr/bin/restart.sh"
	44	[18]	CALL     	14 2 2
	45	[18]	TEST     	14 0 0
	46	[18]	JMP      	12	; to 59
	47	[19]	NEWTABLE 	14 0 2
	48	[20]	MOVE     	15 11
	49	[20]	MOVE     	16 8
	50	[20]	LOADK    	17 -21	; "Start %1 reader app"
	51	[20]	CALL     	16 2 2
	52	[20]	LOADK    	17 -22	; "BQ"
	53	[20]	CALL     	15 3 2
	54	[20]	SETTABLE 	14 -20 15	; "text" -
	55	[24]	CLOSURE  	15 0	; 0x7f99294070e0
	56	[24]	MOVE     	0 6
	57	[24]	SETTABLE 	14 -23 15	; "callback" -
	58	[25]	SETTABLE 	12 -19 14	; "start_bq" -
	59	[29]	SELF     	13 1 -24	; "hasFrontlight"
	60	[29]	CALL     	13 2 2
	61	[29]	TEST     	13 0 0
	62	[29]	JMP      	13	; to 76
	63	[30]	GETGLOBAL	13 -1	; require
	64	[30]	LOADK    	14 -25	; "apps/reader/modules/readerfrontlight"
	65	[30]	CALL     	13 2 2
	66	[31]	NEWTABLE 	14 0 2
	67	[32]	MOVE     	15 8
	68	[32]	LOADK    	16 -27	; "Frontlight"
	69	[32]	CALL     	15 2 2
	70	[32]	SETTABLE 	14 -20 15	; "text" -
	71	[35]	CLOSURE  	15 1	; 0x7f99294071f0
	72	[35]	MOVE     	0 13
	73	[35]	SETTABLE 	14 -23 15	; "callback" -
	74	[36]	SETTABLE 	12 -26 14	; "frontlight" -
	75	[36]	CLOSE    	13
	76	[39]	SELF     	13 1 -28	; "canToggleMassStorage"
	77	[39]	CALL     	13 2 2
	78	[39]	TEST     	13 0 0
	79	[39]	JMP      	22	; to 102
	80	[40]	GETGLOBAL	13 -1	; require
	81	[40]	LOADK    	14 -29	; "ui/elements/mass_storage"
	82	[40]	CALL     	13 2 2
	83	[43]	NEWTABLE 	14 0 2
	84	[44]	MOVE     	15 8
	85	[44]	LOADK    	16 -31	; "USB mass storage"
	86	[44]	CALL     	15 2 2
	87	[44]	SETTABLE 	14 -20 15	; "text" -
	88	[45]	SELF     	15 13 -33	; "getSettingsMenuTable"
	89	[45]	CALL     	15 2 2
	90	[45]	SETTABLE 	14 -32 15	; "sub_item_table" -
	91	[46]	SETTABLE 	12 -30 14	; "mass_storage_settings" -
	92	[49]	NEWTABLE 	14 0 2
	93	[50]	MOVE     	15 8
	94	[50]	LOADK    	16 -35	; "Start USB storage"
	95	[50]	CALL     	15 2 2
	96	[50]	SETTABLE 	14 -20 15	; "text" -
	97	[51]	CLOSURE  	15 2	; 0x7f99294072d0
	98	[51]	MOVE     	0 13
	99	[51]	SETTABLE 	14 -23 15	; "callback" -
	100	[52]	SETTABLE 	12 -34 14	; "mass_storage_actions" -
	101	[52]	CLOSE    	13
	102	[56]	NEWTABLE 	13 0 2
	103	[57]	MOVE     	14 8
	104	[57]	LOADK    	15 -37	; "Time and date"
	105	[57]	CALL     	14 2 2
	106	[57]	SETTABLE 	13 -20 14	; "text" -
	107	[58]	NEWTABLE 	14 1 0
	108	[58]	NEWTABLE 	15 0 4
	109	[60]	MOVE     	16 8
	110	[60]	LOADK    	17 -38	; "12-hour clock"
	111	[60]	CALL     	16 2 2
	112	[60]	SETTABLE 	15 -20 16	; "text" -
	113	[61]	SETTABLE 	15 -39 -40	; "keep_menu_open" true
	114	[64]	CLOSURE  	16 3	; 0x7f9929407da0
	115	[64]	SETTABLE 	15 -41 16	; "checked_func" -
	116	[67]	CLOSURE  	16 4	; 0x7f9929407f00
	117	[67]	SETTABLE 	15 -23 16	; "callback" -
	118	[69]	SETLIST  	14 1 1	; 1
	119	[69]	SETTABLE 	13 -32 14	; "sub_item_table" -
	120	[70]	SETTABLE 	12 -36 13	; "time" -
	121	[71]	SELF     	13 1 -42	; "setDateTime"
	122	[71]	CALL     	13 2 2
	123	[71]	TEST     	13 0 0
	124	[71]	JMP      	38	; to 163
	125	[72]	GETGLOBAL	13 -43	; table
	126	[72]	GETTABLE 	13 13 -44	; "insert"
	127	[72]	GETTABLE 	14 12 -36	; "time"
	128	[72]	GETTABLE 	14 14 -32	; "sub_item_table"
	129	[72]	NEWTABLE 	15 0 3
	130	[73]	MOVE     	16 8
	131	[73]	LOADK    	17 -45	; "Set time"
	132	[73]	CALL     	16 2 2
	133	[73]	SETTABLE 	15 -20 16	; "text" -
	134	[74]	SETTABLE 	15 -39 -40	; "keep_menu_open" true
	135	[99]	CLOSURE  	16 5	; 0x7f9929407720
	136	[99]	MOVE     	0 7
	137	[99]	MOVE     	0 8
	138	[99]	MOVE     	0 1
	139	[99]	MOVE     	0 6
	140	[99]	MOVE     	0 3
	141	[99]	MOVE     	0 11
	142	[99]	SETTABLE 	15 -23 16	; "callback" -
	143	[72]	CALL     	13 3 1
	144	[101]	GETGLOBAL	13 -43	; table
	145	[101]	GETTABLE 	13 13 -44	; "insert"
	146	[101]	GETTABLE 	14 12 -36	; "time"
	147	[101]	GETTABLE 	14 14 -32	; "sub_item_table"
	148	[101]	NEWTABLE 	15 0 3
	149	[102]	MOVE     	16 8
	150	[102]	LOADK    	17 -46	; "Set date"
	151	[102]	CALL     	16 2 2
	152	[102]	SETTABLE 	15 -20 16	; "text" -
	153	[103]	SETTABLE 	15 -39 -40	; "keep_menu_open" true
	154	[131]	CLOSURE  	16 6	; 0x7f9929408230
	155	[131]	MOVE     	0 0
	156	[131]	MOVE     	0 8
	157	[131]	MOVE     	0 1
	158	[131]	MOVE     	0 6
	159	[131]	MOVE     	0 3
	160	[131]	MOVE     	0 11
	161	[131]	SETTABLE 	15 -23 16	; "callback" -
	162	[101]	CALL     	13 3 1
	163	[135]	SELF     	13 1 -47	; "isKobo"
	164	[135]	CALL     	13 2 2
	165	[135]	TEST     	13 0 0
	166	[135]	JMP      	26	; to 193
	167	[136]	NEWTABLE 	13 0 3
	168	[137]	MOVE     	14 8
	169	[137]	LOADK    	15 -49	; "Ignore all sleepcover events"
	170	[137]	CALL     	14 2 2
	171	[137]	SETTABLE 	13 -20 14	; "text" -
	172	[140]	CLOSURE  	14 7	; 0x7f9929408940
	173	[140]	SETTABLE 	13 -41 14	; "checked_func" -
	174	[147]	CLOSURE  	14 8	; 0x7f9929409270
	175	[147]	MOVE     	0 6
	176	[147]	MOVE     	0 3
	177	[147]	MOVE     	0 8
	178	[147]	SETTABLE 	13 -23 14	; "callback" -
	179	[148]	SETTABLE 	12 -48 13	; "ignore_sleepcover" -
	180	[150]	NEWTABLE 	13 0 3
	181	[151]	MOVE     	14 8
	182	[151]	LOADK    	15 -51	; "Ignore sleepcover wakeup events"
	183	[151]	CALL     	14 2 2
	184	[151]	SETTABLE 	13 -20 14	; "text" -
	185	[154]	CLOSURE  	14 9	; 0x7f9929409af0
	186	[154]	SETTABLE 	13 -41 14	; "checked_func" -
	187	[161]	CLOSURE  	14 10	; 0x7f9929409bb0
	188	[161]	MOVE     	0 6
	189	[161]	MOVE     	0 3
	190	[161]	MOVE     	0 8
	191	[161]	SETTABLE 	13 -23 14	; "callback" -
	192	[162]	SETTABLE 	12 -50 13	; "ignore_open_sleepcover" -
	193	[165]	NEWTABLE 	13 0 3
	194	[166]	MOVE     	14 8
	195	[166]	LOADK    	15 -53	; "Night mode"
	196	[166]	CALL     	14 2 2
	197	[166]	SETTABLE 	13 -20 14	; "text" -
	198	[167]	CLOSURE  	14 11	; 0x7f992940a300
	199	[167]	SETTABLE 	13 -41 14	; "checked_func" -
	200	[173]	CLOSURE  	14 12	; 0x7f992940a380
	201	[173]	MOVE     	0 10
	202	[173]	MOVE     	0 6
	203	[173]	SETTABLE 	13 -23 14	; "callback" -
	204	[174]	SETTABLE 	12 -52 13	; "night_mode" -
	205	[175]	NEWTABLE 	13 0 1
	206	[176]	MOVE     	14 8
	207	[176]	LOADK    	15 -55	; "Network"
	208	[176]	CALL     	14 2 2
	209	[176]	SETTABLE 	13 -20 14	; "text" -
	210	[177]	SETTABLE 	12 -54 13	; "network" -
	211	[178]	SELF     	13 5 -56	; "getMenuTable"
	212	[178]	MOVE     	15 12
	213	[178]	CALL     	13 3 1
	214	[180]	NEWTABLE 	13 0 1
	215	[181]	MOVE     	14 8
	216	[181]	LOADK    	15 -57	; "Screen"
	217	[181]	CALL     	14 2 2
	218	[181]	SETTABLE 	13 -20 14	; "text" -
	219	[182]	SETTABLE 	12 -12 13	; "screen" -
	220	[183]	GETGLOBAL	13 -1	; require
	221	[183]	LOADK    	14 -59	; "ui/elements/screen_dpi_menu_table"
	222	[183]	CALL     	13 2 2
	223	[183]	SETTABLE 	12 -58 13	; "screen_dpi" -
	224	[184]	GETGLOBAL	13 -1	; require
	225	[184]	LOADK    	14 -61	; "ui/elements/screen_eink_opt_menu_table"
	226	[184]	CALL     	13 2 2
	227	[184]	SETTABLE 	12 -60 13	; "screen_eink_opt" -
	228	[185]	GETGLOBAL	13 -1	; require
	229	[185]	LOADK    	14 -63	; "ui/elements/menu_activate"
	230	[185]	CALL     	13 2 2
	231	[185]	SETTABLE 	12 -62 13	; "menu_activate" -
	232	[186]	GETGLOBAL	13 -1	; require
	233	[186]	LOADK    	14 -65	; "ui/elements/screen_disable_double_tap_table"
	234	[186]	CALL     	13 2 2
	235	[186]	SETTABLE 	12 -64 13	; "screen_disable_double_tab" -
	236	[187]	NEWTABLE 	13 0 3
	237	[188]	MOVE     	14 8
	238	[188]	LOADK    	15 -67	; "Ignore hold on corners"
	239	[188]	CALL     	14 2 2
	240	[188]	SETTABLE 	13 -20 14	; "text" -
	241	[191]	CLOSURE  	14 13	; 0x7f992940ad30
	242	[191]	SETTABLE 	13 -41 14	; "checked_func" -
	243	[194]	CLOSURE  	14 14	; 0x7f992940aeb0
	244	[194]	MOVE     	0 6
	245	[194]	MOVE     	0 2
	246	[194]	SETTABLE 	13 -23 14	; "callback" -
	247	[195]	SETTABLE 	12 -66 13	; "ignore_hold_corners" -
	248	[197]	SELF     	13 1 -68	; "canToggleGSensor"
	249	[197]	CALL     	13 2 2
	250	[197]	TEST     	13 0 0
	251	[197]	JMP      	4	; to 256
	252	[198]	GETGLOBAL	13 -1	; require
	253	[198]	LOADK    	14 -70	; "ui/elements/screen_toggle_gsensor"
	254	[198]	CALL     	13 2 2
	255	[198]	SETTABLE 	12 -69 13	; "screen_toggle_gsensor" -
	256	[202]	SELF     	13 10 -71	; "isColorEnabled"
	257	[202]	CALL     	13 2 2
	258	[202]	TEST     	13 0 1
	259	[202]	JMP      	4	; to 264
	260	[202]	SELF     	13 10 -72	; "isColorScreen"
	261	[202]	CALL     	13 2 2
	262	[202]	TEST     	13 0 0
	263	[202]	JMP      	4	; to 268
	264	[203]	GETGLOBAL	13 -1	; require
	265	[203]	LOADK    	14 -74	; "ui/elements/screen_color_menu_table"
	266	[203]	CALL     	13 2 2
	267	[203]	SETTABLE 	12 -73 13	; "color_rendering" -
	268	[206]	SELF     	13 1 -75	; "isAndroid"
	269	[206]	CALL     	13 2 2
	270	[206]	TEST     	13 0 0
	271	[206]	JMP      	61	; to 333
	272	[208]	GETGLOBAL	13 -76	; pcall
	273	[208]	GETGLOBAL	14 -1	; require
	274	[208]	LOADK    	15 -77	; "android"
	275	[208]	CALL     	13 3 3
	276	[209]	TEST     	13 0 1
	277	[209]	JMP      	1	; to 279
	278	[209]	RETURN   	0 1
	279	[212]	GETGLOBAL	15 -1	; require
	280	[212]	LOADK    	16 -79	; "ui/elements/screen_android"
	281	[212]	CALL     	15 2 2
	282	[212]	SELF     	15 15 -80	; "getTimeoutMenuTable"
	283	[212]	CALL     	15 2 2
	284	[212]	SETTABLE 	12 -78 15	; "screen_timeout" -
	285	[215]	NEWTABLE 	15 0 3
	286	[216]	MOVE     	16 8
	287	[216]	LOADK    	17 -82	; "Force haptic feedback"
	288	[216]	CALL     	16 2 2
	289	[216]	SETTABLE 	15 -20 16	; "text" -
	290	[217]	CLOSURE  	16 15	; 0x7f992940b660
	291	[217]	SETTABLE 	15 -41 16	; "checked_func" -
	292	[221]	CLOSURE  	16 16	; 0x7f992940b720
	293	[221]	MOVE     	0 14
	294	[221]	SETTABLE 	15 -23 16	; "callback" -
	295	[222]	SETTABLE 	12 -81 15	; "android_haptic_feedback" -
	296	[225]	NEWTABLE 	15 0 3
	297	[226]	MOVE     	16 8
	298	[226]	LOADK    	17 -84	; "Volume key page turning"
	299	[226]	CALL     	16 2 2
	300	[226]	SETTABLE 	15 -20 16	; "text" -
	301	[227]	CLOSURE  	16 17	; 0x7f9929409a70
	302	[227]	MOVE     	0 14
	303	[227]	SETTABLE 	15 -41 16	; "checked_func" -
	304	[232]	CLOSURE  	16 18	; 0x7f992940b7e0
	305	[232]	MOVE     	0 14
	306	[232]	SETTABLE 	15 -23 16	; "callback" -
	307	[233]	SETTABLE 	12 -83 15	; "android_volume_keys" -
	308	[236]	NEWTABLE 	15 0 3
	309	[237]	MOVE     	16 8
	310	[237]	LOADK    	17 -86	; "Camera key toggles touchscreen support"
	311	[237]	CALL     	16 2 2
	312	[237]	SETTABLE 	15 -20 16	; "text" -
	313	[238]	CLOSURE  	16 19	; 0x7f9929409910
	314	[238]	SETTABLE 	15 -41 16	; "checked_func" -
	315	[239]	CLOSURE  	16 20	; 0x7f992940a8e0
	316	[239]	SETTABLE 	15 -23 16	; "callback" -
	317	[240]	SETTABLE 	12 -85 15	; "android_camera_key" -
	318	[243]	GETTABLE 	15 1 -87	; "firmware_rev"
	319	[243]	LT       	0 15 -88	; - 19
	320	[243]	JMP      	11	; to 332
	321	[244]	NEWTABLE 	15 0 3
	322	[245]	MOVE     	16 8
	323	[245]	LOADK    	17 -90	; "Fullscreen"
	324	[245]	CALL     	16 2 2
	325	[245]	SETTABLE 	15 -20 16	; "text" -
	326	[246]	CLOSURE  	16 21	; 0x7f992940ba60
	327	[246]	MOVE     	0 14
	328	[246]	SETTABLE 	15 -41 16	; "checked_func" -
	329	[247]	CLOSURE  	16 22	; 0x7f992940bc80
	330	[247]	SETTABLE 	15 -23 16	; "callback" -
	331	[248]	SETTABLE 	12 -89 15	; "fullscreen" -
	332	[249]	CLOSE    	13
	333	[252]	SELF     	13 1 -91	; "isTouchDevice"
	334	[252]	CALL     	13 2 2
	335	[252]	TEST     	13 0 0
	336	[252]	JMP      	16	; to 353
	337	[253]	NEWTABLE 	13 0 2
	338	[254]	MOVE     	14 8
	339	[254]	LOADK    	15 -93	; "Keyboard layout"
	340	[254]	CALL     	14 2 2
	341	[254]	SETTABLE 	13 -20 14	; "text" -
	342	[255]	GETGLOBAL	14 -1	; require
	343	[255]	LOADK    	15 -94	; "ui/elements/menu_keyboard_layout"
	344	[255]	CALL     	14 2 2
	345	[255]	SETTABLE 	13 -32 14	; "sub_item_table" -
	346	[256]	SETTABLE 	12 -92 13	; "keyboard_layout" -
	347	[257]	NEWTABLE 	13 0 1
	348	[258]	MOVE     	14 8
	349	[258]	LOADK    	15 -96	; "Taps and gestures"
	350	[258]	CALL     	14 2 2
	351	[258]	SETTABLE 	13 -20 14	; "text" -
	352	[259]	SETTABLE 	12 -95 13	; "taps_and_gestures" -
	353	[262]	NEWTABLE 	13 0 1
	354	[263]	MOVE     	14 8
	355	[263]	LOADK    	15 -98	; "Navigation"
	356	[263]	CALL     	14 2 2
	357	[263]	SETTABLE 	13 -20 14	; "text" -
	358	[264]	SETTABLE 	12 -97 13	; "navigation" -
	359	[265]	NEWTABLE 	13 0 3
	360	[266]	NEWTABLE 	14 1 0
	361	[266]	MOVE     	15 8
	362	[266]	LOADK    	16 -100	; "Prompt"
	363	[266]	CALL     	15 2 2
	364	[266]	MOVE     	16 8
	365	[266]	LOADK    	17 -99	; "prompt"
	366	[266]	CALL     	16 2 0
	367	[266]	SETLIST  	14 0 1	; 1
	368	[266]	SETTABLE 	13 -99 14	; "prompt" -
	369	[267]	NEWTABLE 	14 1 0
	370	[267]	MOVE     	15 8
	371	[267]	LOADK    	16 -102	; "Always"
	372	[267]	CALL     	15 2 2
	373	[267]	MOVE     	16 8
	374	[267]	LOADK    	17 -101	; "always"
	375	[267]	CALL     	16 2 0
	376	[267]	SETLIST  	14 0 1	; 1
	377	[267]	SETTABLE 	13 -101 14	; "always" -
	378	[268]	NEWTABLE 	14 1 0
	379	[268]	MOVE     	15 8
	380	[268]	LOADK    	16 -104	; "Disable"
	381	[268]	CALL     	15 2 2
	382	[268]	MOVE     	16 8
	383	[268]	LOADK    	17 -103	; "disable"
	384	[268]	CALL     	16 2 0
	385	[268]	SETLIST  	14 0 1	; 1
	386	[268]	SETTABLE 	13 -103 14	; "disable" -
	387	[270]	NEWTABLE 	14 0 2
	388	[275]	CLOSURE  	15 23	; 0x7f992940c120
	389	[275]	MOVE     	0 11
	390	[275]	MOVE     	0 8
	391	[275]	MOVE     	0 13
	392	[275]	SETTABLE 	14 -106 15	; "text_func" -
	393	[276]	NEWTABLE 	15 3 0
	394	[276]	NEWTABLE 	16 0 3
	395	[278]	GETTABLE 	17 13 -99	; "prompt"
	396	[278]	GETTABLE 	17 17 -107	; 1
	397	[278]	SETTABLE 	16 -20 17	; "text" -
	398	[282]	CLOSURE  	17 24	; 0x7f992940c740
	399	[282]	SETTABLE 	16 -41 17	; "checked_func" -
	400	[285]	CLOSURE  	17 25	; 0x7f992940c970
	401	[285]	SETTABLE 	16 -23 17	; "callback" -
	402	[286]	NEWTABLE 	17 0 3
	403	[288]	GETTABLE 	18 13 -101	; "always"
	404	[288]	GETTABLE 	18 18 -107	; 1
	405	[288]	SETTABLE 	17 -20 18	; "text" -
	406	[292]	CLOSURE  	18 26	; 0x7f992940ccf0
	407	[292]	SETTABLE 	17 -41 18	; "checked_func" -
	408	[295]	CLOSURE  	18 27	; 0x7f992940d140
	409	[295]	SETTABLE 	17 -23 18	; "callback" -
	410	[296]	NEWTABLE 	18 0 3
	411	[298]	GETTABLE 	19 13 -103	; "disable"
	412	[298]	GETTABLE 	19 19 -107	; 1
	413	[298]	SETTABLE 	18 -20 19	; "text" -
	414	[302]	CLOSURE  	19 28	; 0x7f992940d200
	415	[302]	SETTABLE 	18 -41 19	; "checked_func" -
	416	[305]	CLOSURE  	19 29	; 0x7f992940d6a0
	417	[305]	SETTABLE 	18 -23 19	; "callback" -
	418	[307]	SETLIST  	15 3 1	; 1
	419	[307]	SETTABLE 	14 -32 15	; "sub_item_table" -
	420	[308]	SETTABLE 	12 -105 14	; "back_to_exit" -
	421	[309]	NEWTABLE 	14 0 2
	422	[310]	MOVE     	15 8
	423	[310]	LOADK    	16 -109	; "Back in file browser"
	424	[310]	CALL     	15 2 2
	425	[310]	SETTABLE 	14 -20 15	; "text" -
	426	[311]	NEWTABLE 	15 2 0
	427	[311]	NEWTABLE 	16 0 3
	428	[317]	CLOSURE  	17 30	; 0x7f992940d760
	429	[317]	MOVE     	0 11
	430	[317]	MOVE     	0 8
	431	[317]	MOVE     	0 13
	432	[317]	SETTABLE 	16 -106 17	; "text_func" -
	433	[321]	CLOSURE  	17 31	; 0x7f992940dec0
	434	[321]	SETTABLE 	16 -41 17	; "checked_func" -
	435	[324]	CLOSURE  	17 32	; 0x7f992940e0a0
	436	[324]	SETTABLE 	16 -23 17	; "callback" -
	437	[325]	NEWTABLE 	17 0 3
	438	[327]	MOVE     	18 8
	439	[327]	LOADK    	19 -110	; "Go to parent folder"
	440	[327]	CALL     	18 2 2
	441	[327]	SETTABLE 	17 -20 18	; "text" -
	442	[331]	CLOSURE  	18 33	; 0x7f992940e420
	443	[331]	SETTABLE 	17 -41 18	; "checked_func" -
	444	[334]	CLOSURE  	18 34	; 0x7f992940b2a0
	445	[334]	SETTABLE 	17 -23 18	; "callback" -
	446	[336]	SETLIST  	15 2 1	; 1
	447	[336]	SETTABLE 	14 -32 15	; "sub_item_table" -
	448	[337]	SETTABLE 	12 -108 14	; "back_in_filemanager" -
	449	[338]	NEWTABLE 	14 0 3
	450	[339]	MOVE     	15 8
	451	[339]	LOADK    	16 -112	; "Enable back history"
	452	[339]	CALL     	15 2 2
	453	[339]	SETTABLE 	14 -20 15	; "text" -
	454	[342]	CLOSURE  	15 35	; 0x7f992940ea70
	455	[342]	SETTABLE 	14 -41 15	; "checked_func" -
	456	[345]	CLOSURE  	15 36	; 0x7f992940ed40
	457	[345]	SETTABLE 	14 -23 15	; "callback" -
	458	[346]	SETTABLE 	12 -111 14	; "enable_back_history" -
	459	[347]	SELF     	14 1 -113	; "hasKeys"
	460	[347]	CALL     	14 2 2
	461	[347]	TEST     	14 0 0
	462	[347]	JMP      	11	; to 474
	463	[348]	NEWTABLE 	14 0 3
	464	[349]	MOVE     	15 8
	465	[349]	LOADK    	16 -115	; "Invert page turn buttons"
	466	[349]	CALL     	15 2 2
	467	[349]	SETTABLE 	14 -20 15	; "text" -
	468	[352]	CLOSURE  	15 37	; 0x7f992940f100
	469	[352]	SETTABLE 	14 -41 15	; "checked_func" -
	470	[356]	CLOSURE  	15 38	; 0x7f992940f250
	471	[356]	MOVE     	0 1
	472	[356]	SETTABLE 	14 -23 15	; "callback" -
	473	[357]	SETTABLE 	12 -114 14	; "invert_page_turn_buttons" -
	474	[361]	GETGLOBAL	14 -116	; G_reader_settings
	475	[361]	SELF     	14 14 -117	; "readSetting"
	476	[361]	LOADK    	16 -118	; "auto_save_settings_interval_minutes"
	477	[361]	CALL     	14 3 2
	478	[361]	EQ       	0 14 -119	; - nil
	479	[361]	JMP      	5	; to 485
	480	[363]	GETGLOBAL	14 -116	; G_reader_settings
	481	[363]	SELF     	14 14 -120	; "saveSetting"
	482	[363]	LOADK    	16 -118	; "auto_save_settings_interval_minutes"
	483	[363]	LOADK    	17 -121	; 15
	484	[363]	CALL     	14 4 1
	485	[366]	MOVE     	14 8
	486	[371]	LOADK    	15 -122	; "This sets how often to rewrite to disk global settings and book metadata, including your current position and any highlights and bookmarks made, when you're reading a document.\n\nThe normal behavior is to save those only when the document is closed, or your device suspended, or when exiting KOReader.\n\nSetting it to some interval may help prevent losing new settings/sidecar data after a software crash, but will cause more I/O writes the lower the interval is, and may slowly wear out your storage media in the long run."
	487	[366]	CALL     	14 2 2
	488	[375]	SELF     	15 1 -47	; "isKobo"
	489	[375]	CALL     	15 2 2
	490	[375]	TEST     	15 0 1
	491	[375]	JMP      	14	; to 506
	492	[375]	SELF     	15 1 -123	; "isKindle"
	493	[375]	CALL     	15 2 2
	494	[375]	TEST     	15 0 1
	495	[375]	JMP      	10	; to 506
	496	[375]	SELF     	15 1 -15	; "isCervantes"
	497	[375]	CALL     	15 2 2
	498	[375]	TEST     	15 0 1
	499	[375]	JMP      	6	; to 506
	500	[375]	SELF     	15 1 -124	; "isPocketBook"
	501	[375]	CALL     	15 2 2
	502	[375]	TEST     	15 0 1
	503	[375]	JMP      	2	; to 506
	504	[375]	SELF     	15 1 -125	; "isSonyPRSTUX"
	505	[375]	CALL     	15 2 2
	506	[376]	TEST     	15 0 0
	507	[376]	JMP      	7	; to 515
	508	[377]	MOVE     	16 8
	509	[377]	LOADK    	17 -126	; "Please be warned that on this device, setting a low interval may exacerbate the potential for filesystem corruption and complete data loss after a hardware crash."
	510	[377]	CALL     	16 2 2
	511	[378]	MOVE     	17 14
	512	[378]	LOADK    	18 -127	; "\n\n"
	513	[378]	MOVE     	19 16
	514	[378]	CONCAT   	14 17 19
	515	[399]	CLOSURE  	16 39	; 0x7f992940fb50
	516	[399]	MOVE     	0 8
	517	[399]	MOVE     	0 11
	518	[399]	MOVE     	0 9
	519	[399]	MOVE     	0 14
	520	[401]	NEWTABLE 	17 0 2
	521	[402]	MOVE     	18 8
	522	[402]	LOADK    	19 -129	; "Document"
	523	[402]	CALL     	18 2 2
	524	[402]	SETTABLE 	17 -20 18	; "text" -
	525	[403]	NEWTABLE 	18 4 0
	526	[403]	NEWTABLE 	19 0 3
	527	[414]	CLOSURE  	20 40	; 0x7f9929410380
	528	[414]	MOVE     	0 11
	529	[414]	MOVE     	0 9
	530	[414]	MOVE     	0 8
	531	[414]	SETTABLE 	19 -106 20	; "text_func" -
	532	[415]	SETTABLE 	19 -130 14	; "help_text" -
	533	[416]	NEWTABLE 	20 5 0
	534	[417]	MOVE     	21 16
	535	[417]	LOADBOOL 	22 0 0
	536	[417]	CALL     	21 2 2
	537	[418]	MOVE     	22 16
	538	[418]	LOADK    	23 -131	; 5
	539	[418]	CALL     	22 2 2
	540	[419]	MOVE     	23 16
	541	[419]	LOADK    	24 -121	; 15
	542	[419]	CALL     	23 2 2
	543	[420]	MOVE     	24 16
	544	[420]	LOADK    	25 -132	; 60
	545	[420]	CALL     	24 2 2
	546	[421]	TEST     	15 0 0
	547	[421]	JMP      	13	; to 561
	548	[421]	NEWTABLE 	25 0 3
	549	[422]	MOVE     	26 8
	550	[422]	LOADK    	27 -133	; "Important info about this auto-save option"
	551	[422]	CALL     	26 2 2
	552	[422]	SETTABLE 	25 -20 26	; "text" -
	553	[423]	SETTABLE 	25 -39 -40	; "keep_menu_open" true
	554	[426]	CLOSURE  	26 41	; 0x7f992940bdd0
	555	[426]	MOVE     	0 6
	556	[426]	MOVE     	0 3
	557	[426]	MOVE     	0 14
	558	[426]	SETTABLE 	25 -23 26	; "callback" -
	559	[427]	TEST     	25 0 1
	560	[427]	JMP      	1	; to 562
	561	[428]	LOADNIL  	25 25
	562	[428]	SETLIST  	20 5 1	; 1
	563	[428]	SETTABLE 	19 -32 20	; "sub_item_table" -
	564	[429]	NEWTABLE 	20 0 2
	565	[431]	MOVE     	21 8
	566	[431]	LOADK    	22 -134	; "Save document (write highlights into PDF)"
	567	[431]	CALL     	21 2 2
	568	[431]	SETTABLE 	20 -20 21	; "text" -
	569	[432]	NEWTABLE 	21 3 0
	570	[432]	NEWTABLE 	22 0 3
	571	[434]	MOVE     	23 8
	572	[434]	LOADK    	24 -100	; "Prompt"
	573	[434]	CALL     	23 2 2
	574	[434]	SETTABLE 	22 -20 23	; "text" -
	575	[438]	CLOSURE  	23 42	; 0x7f992940bb70
	576	[438]	SETTABLE 	22 -41 23	; "checked_func" -
	577	[441]	CLOSURE  	23 43	; 0x7f992940efd0
	578	[441]	SETTABLE 	22 -23 23	; "callback" -
	579	[442]	NEWTABLE 	23 0 3
	580	[444]	MOVE     	24 8
	581	[444]	LOADK    	25 -102	; "Always"
	582	[444]	CALL     	24 2 2
	583	[444]	SETTABLE 	23 -20 24	; "text" -
	584	[448]	CLOSURE  	24 44	; 0x7f9929409310
	585	[448]	SETTABLE 	23 -41 24	; "checked_func" -
	586	[451]	CLOSURE  	24 45	; 0x7f9929409390
	587	[451]	SETTABLE 	23 -23 24	; "callback" -
	588	[452]	NEWTABLE 	24 0 3
	589	[454]	MOVE     	25 8
	590	[454]	LOADK    	26 -104	; "Disable"
	591	[454]	CALL     	25 2 2
	592	[454]	SETTABLE 	24 -20 25	; "text" -
	593	[458]	CLOSURE  	25 46	; 0x7f992940d000
	594	[458]	SETTABLE 	24 -41 25	; "checked_func" -
	595	[461]	CLOSURE  	25 47	; 0x7f992940d080
	596	[461]	SETTABLE 	24 -23 25	; "callback" -
	597	[463]	SETLIST  	21 3 1	; 1
	598	[463]	SETTABLE 	20 -32 21	; "sub_item_table" -
	599	[464]	NEWTABLE 	21 0 2
	600	[466]	MOVE     	22 8
	601	[466]	LOADK    	23 -135	; "End of document action"
	602	[466]	CALL     	22 2 2
	603	[466]	SETTABLE 	21 -20 22	; "text" -
	604	[467]	NEWTABLE 	22 9 0
	605	[467]	NEWTABLE 	23 0 3
	606	[469]	MOVE     	24 8
	607	[469]	LOADK    	25 -136	; "Ask with pop-up dialog"
	608	[469]	CALL     	24 2 2
	609	[469]	SETTABLE 	23 -20 24	; "text" -
	610	[473]	CLOSURE  	24 48	; 0x7f9929410220
	611	[473]	SETTABLE 	23 -41 24	; "checked_func" -
	612	[476]	CLOSURE  	24 49	; 0x7f992940f650
	613	[476]	SETTABLE 	23 -23 24	; "callback" -
	614	[477]	NEWTABLE 	24 0 3
	615	[479]	MOVE     	25 8
	616	[479]	LOADK    	26 -137	; "Do nothing"
	617	[479]	CALL     	25 2 2
	618	[479]	SETTABLE 	24 -20 25	; "text" -
	619	[482]	CLOSURE  	25 50	; 0x7f992940e540
	620	[482]	SETTABLE 	24 -41 25	; "checked_func" -
	621	[485]	CLOSURE  	25 51	; 0x7f992940e8e0
	622	[485]	SETTABLE 	24 -23 25	; "callback" -
	623	[486]	NEWTABLE 	25 0 3
	624	[488]	MOVE     	26 8
	625	[488]	LOADK    	27 -138	; "Book status"
	626	[488]	CALL     	26 2 2
	627	[488]	SETTABLE 	25 -20 26	; "text" -
	628	[491]	CLOSURE  	26 52	; 0x7f992940b9e0
	629	[491]	SETTABLE 	25 -41 26	; "checked_func" -
	630	[494]	CLOSURE  	26 53	; 0x7f9929410910
	631	[494]	SETTABLE 	25 -23 26	; "callback" -
	632	[495]	NEWTABLE 	26 0 3
	633	[497]	MOVE     	27 8
	634	[497]	LOADK    	28 -139	; "Delete file"
	635	[497]	CALL     	27 2 2
	636	[497]	SETTABLE 	26 -20 27	; "text" -
	637	[500]	CLOSURE  	27 54	; 0x7f992940cb70
	638	[500]	SETTABLE 	26 -41 27	; "checked_func" -
	639	[503]	CLOSURE  	27 55	; 0x7f992940e160
	640	[503]	SETTABLE 	26 -23 27	; "callback" -
	641	[504]	NEWTABLE 	27 0 4
	642	[506]	MOVE     	28 8
	643	[506]	LOADK    	29 -140	; "Open next file"
	644	[506]	CALL     	28 2 2
	645	[506]	SETTABLE 	27 -20 28	; "text" -
	646	[510]	CLOSURE  	28 56	; 0x7f992940e280
	647	[510]	SETTABLE 	27 -141 28	; "enabled_func" -
	648	[513]	CLOSURE  	28 57	; 0x7f9929410e50
	649	[513]	SETTABLE 	27 -41 28	; "checked_func" -
	650	[516]	CLOSURE  	28 58	; 0x7f9929411170
	651	[516]	SETTABLE 	27 -23 28	; "callback" -
	652	[517]	NEWTABLE 	28 0 3
	653	[519]	MOVE     	29 8
	654	[519]	LOADK    	30 -142	; "Go to beginning"
	655	[519]	CALL     	29 2 2
	656	[519]	SETTABLE 	28 -20 29	; "text" -
	657	[522]	CLOSURE  	29 59	; 0x7f9929411260
	658	[522]	SETTABLE 	28 -41 29	; "checked_func" -
	659	[525]	CLOSURE  	29 60	; 0x7f9929411700
	660	[525]	SETTABLE 	28 -23 29	; "callback" -
	661	[526]	NEWTABLE 	29 0 3
	662	[528]	MOVE     	30 8
	663	[528]	LOADK    	31 -143	; "Return to file browser"
	664	[528]	CALL     	30 2 2
	665	[528]	SETTABLE 	29 -20 30	; "text" -
	666	[531]	CLOSURE  	30 61	; 0x7f99294117f0
	667	[531]	SETTABLE 	29 -41 30	; "checked_func" -
	668	[534]	CLOSURE  	30 62	; 0x7f9929411c90
	669	[534]	SETTABLE 	29 -23 30	; "callback" -
	670	[535]	NEWTABLE 	30 0 3
	671	[537]	MOVE     	31 8
	672	[537]	LOADK    	32 -144	; "Mark book as read"
	673	[537]	CALL     	31 2 2
	674	[537]	SETTABLE 	30 -20 31	; "text" -
	675	[540]	CLOSURE  	31 63	; 0x7f9929411dc0
	676	[540]	SETTABLE 	30 -41 31	; "checked_func" -
	677	[543]	CLOSURE  	31 64	; 0x7f9929412260
	678	[543]	SETTABLE 	30 -23 31	; "callback" -
	679	[544]	NEWTABLE 	31 0 3
	680	[546]	MOVE     	32 8
	681	[546]	LOADK    	33 -145	; "Book status and return to file browser"
	682	[546]	CALL     	32 2 2
	683	[546]	SETTABLE 	31 -20 32	; "text" -
	684	[549]	CLOSURE  	32 65	; 0x7f9929412390
	685	[549]	SETTABLE 	31 -41 32	; "checked_func" -
	686	[552]	CLOSURE  	32 66	; 0x7f992940e710
	687	[552]	SETTABLE 	31 -23 32	; "callback" -
	688	[554]	SETLIST  	22 9 1	; 1
	689	[554]	SETTABLE 	21 -32 22	; "sub_item_table" -
	690	[555]	NEWTABLE 	22 0 2
	691	[557]	MOVE     	23 8
	692	[557]	LOADK    	24 -146	; "Highlight action"
	693	[557]	CALL     	23 2 2
	694	[557]	SETTABLE 	22 -20 23	; "text" -
	695	[558]	NEWTABLE 	23 7 0
	696	[558]	NEWTABLE 	24 0 4
	697	[560]	MOVE     	25 8
	698	[560]	LOADK    	26 -147	; "Enable on single word selection"
	699	[560]	CALL     	25 2 2
	700	[560]	SETTABLE 	24 -20 25	; "text" -
	701	[563]	CLOSURE  	25 67	; 0x7f9929412780
	702	[563]	SETTABLE 	24 -41 25	; "checked_func" -
	703	[566]	CLOSURE  	25 68	; 0x7f9929412a40
	704	[566]	SETTABLE 	24 -23 25	; "callback" -
	705	[567]	SETTABLE 	24 -148 -40	; "separator" true
	706	[568]	NEWTABLE 	25 0 3
	707	[570]	MOVE     	26 8
	708	[570]	LOADK    	27 -149	; "Ask with popup dialog"
	709	[570]	CALL     	26 2 2
	710	[570]	SETTABLE 	25 -20 26	; "text" -
	711	[573]	CLOSURE  	26 69	; 0x7f9929412d30
	712	[573]	SETTABLE 	25 -41 26	; "checked_func" -
	713	[576]	CLOSURE  	26 70	; 0x7f9929413000
	714	[576]	SETTABLE 	25 -23 26	; "callback" -
	715	[577]	NEWTABLE 	26 0 3
	716	[579]	MOVE     	27 8
	717	[579]	LOADK    	28 -150	; "Highlight"
	718	[579]	CALL     	27 2 2
	719	[579]	SETTABLE 	26 -20 27	; "text" -
	720	[582]	CLOSURE  	27 71	; 0x7f9929413300
	721	[582]	SETTABLE 	26 -41 27	; "checked_func" -
	722	[585]	CLOSURE  	27 72	; 0x7f99294137a0
	723	[585]	SETTABLE 	26 -23 27	; "callback" -
	724	[586]	NEWTABLE 	27 0 3
	725	[588]	MOVE     	28 8
	726	[588]	LOADK    	29 -151	; "Translate"
	727	[588]	CALL     	28 2 2
	728	[588]	SETTABLE 	27 -20 28	; "text" -
	729	[591]	CLOSURE  	28 73	; 0x7f99294138d0
	730	[591]	SETTABLE 	27 -41 28	; "checked_func" -
	731	[594]	CLOSURE  	28 74	; 0x7f9929413d70
	732	[594]	SETTABLE 	27 -23 28	; "callback" -
	733	[595]	NEWTABLE 	28 0 3
	734	[597]	MOVE     	29 8
	735	[597]	LOADK    	30 -152	; "Wikipedia"
	736	[597]	CALL     	29 2 2
	737	[597]	SETTABLE 	28 -20 29	; "text" -
	738	[600]	CLOSURE  	29 75	; 0x7f9929413e60
	739	[600]	SETTABLE 	28 -41 29	; "checked_func" -
	740	[603]	CLOSURE  	29 76	; 0x7f9929414300
	741	[603]	SETTABLE 	28 -23 29	; "callback" -
	742	[604]	NEWTABLE 	29 0 3
	743	[606]	MOVE     	30 8
	744	[606]	LOADK    	31 -153	; "Dictionary"
	745	[606]	CALL     	30 2 2
	746	[606]	SETTABLE 	29 -20 30	; "text" -
	747	[609]	CLOSURE  	30 77	; 0x7f9929414430
	748	[609]	SETTABLE 	29 -41 30	; "checked_func" -
	749	[612]	CLOSURE  	30 78	; 0x7f99294148d0
	750	[612]	SETTABLE 	29 -23 30	; "callback" -
	751	[613]	NEWTABLE 	30 0 3
	752	[615]	MOVE     	31 8
	753	[615]	LOADK    	32 -154	; "Fulltext search"
	754	[615]	CALL     	31 2 2
	755	[615]	SETTABLE 	30 -20 31	; "text" -
	756	[618]	CLOSURE  	31 79	; 0x7f99294149c0
	757	[618]	SETTABLE 	30 -41 31	; "checked_func" -
	758	[621]	CLOSURE  	31 80	; 0x7f9929414e60
	759	[621]	SETTABLE 	30 -23 31	; "callback" -
	760	[623]	SETLIST  	23 7 1	; 1
	761	[623]	SETTABLE 	22 -32 23	; "sub_item_table" -
	762	[625]	SETLIST  	18 4 1	; 1
	763	[625]	SETTABLE 	17 -32 18	; "sub_item_table" -
	764	[626]	SETTABLE 	12 -128 17	; "document" -
	765	[627]	SELF     	17 4 -156	; "getLangMenuTable"
	766	[627]	CALL     	17 2 2
	767	[627]	SETTABLE 	12 -155 17	; "language" -
	768	[629]	NEWTABLE 	17 0 2
	769	[630]	MOVE     	18 8
	770	[630]	LOADK    	19 -158	; "Screenshot directory"
	771	[630]	CALL     	18 2 2
	772	[630]	SETTABLE 	17 -20 18	; "text" -
	773	[634]	CLOSURE  	18 81	; 0x7f99294151c0
	774	[634]	SETTABLE 	17 -23 18	; "callback" -
	775	[635]	SETTABLE 	12 -157 17	; "screenshot" -
	776	[637]	RETURN   	12 2
	777	[637]	RETURN   	0 1

function <./frontend/ui/elements/common_settings_menu_table.lua:21,24> (6 instructions, 24 bytes at 0x7f99294070e0)
0 params, 2 slots, 1 upvalue, 0 locals, 3 constants, 0 functions
	1	[22]	GETUPVAL 	0 0	; UIManager
	2	[22]	SELF     	0 0 -1	; "quit"
	3	[22]	CALL     	0 2 1
	4	[23]	GETUPVAL 	0 0	; UIManager
	5	[23]	SETTABLE 	0 -2 -3	; "_exit_code" 87
	6	[24]	RETURN   	0 1

function <./frontend/ui/elements/common_settings_menu_table.lua:33,35> (4 instructions, 16 bytes at 0x7f99294071f0)
0 params, 2 slots, 1 upvalue, 0 locals, 1 constant, 0 functions
	1	[34]	GETUPVAL 	0 0	; ReaderFrontLight
	2	[34]	SELF     	0 0 -1	; "onShowFlDialog"
	3	[34]	CALL     	0 2 1
	4	[35]	RETURN   	0 1

function <./frontend/ui/elements/common_settings_menu_table.lua:51,51> (4 instructions, 16 bytes at 0x7f99294072d0)
0 params, 2 slots, 1 upvalue, 0 locals, 1 constant, 0 functions
	1	[51]	GETUPVAL 	0 0	; MassStorage
	2	[51]	SELF     	0 0 -1	; "start"
	3	[51]	CALL     	0 2 1
	4	[51]	RETURN   	0 1

function <./frontend/ui/elements/common_settings_menu_table.lua:62,64> (6 instructions, 24 bytes at 0x7f9929407da0)
0 params, 3 slots, 0 upvalues, 0 locals, 3 constants, 0 functions
	1	[63]	GETGLOBAL	0 -1	; G_reader_settings
	2	[63]	SELF     	0 0 -2	; "nilOrTrue"
	3	[63]	LOADK    	2 -3	; "twelve_hour_clock"
	4	[63]	TAILCALL 	0 3 0
	5	[63]	RETURN   	0 0
	6	[64]	RETURN   	0 1

function <./frontend/ui/elements/common_settings_menu_table.lua:65,67> (5 instructions, 20 bytes at 0x7f9929407f00)
0 params, 3 slots, 0 upvalues, 0 locals, 3 constants, 0 functions
	1	[66]	GETGLOBAL	0 -1	; G_reader_settings
	2	[66]	SELF     	0 0 -2	; "flipNilOrTrue"
	3	[66]	LOADK    	2 -3	; "twelve_hour_clock"
	4	[66]	CALL     	0 3 1
	5	[67]	RETURN   	0 1

function <./frontend/ui/elements/common_settings_menu_table.lua:75,99> (33 instructions, 132 bytes at 0x7f9929407720)
0 params, 8 slots, 6 upvalues, 4 locals, 11 constants, 1 function
	1	[76]	GETGLOBAL	0 -1	; os
	2	[76]	GETTABLE 	0 0 -2	; "date"
	3	[76]	LOADK    	1 -3	; "*t"
	4	[76]	CALL     	0 2 2
	5	[77]	GETTABLE 	1 0 -4	; "hour"
	6	[78]	GETTABLE 	2 0 -5	; "min"
	7	[79]	GETUPVAL 	3 0	; TimeWidget
	8	[79]	SELF     	3 3 -6	; "new"
	9	[79]	NEWTABLE 	5 0 5
	10	[80]	SETTABLE 	5 -4 1	; "hour" -
	11	[81]	SETTABLE 	5 -5 2	; "min" -
	12	[82]	GETUPVAL 	6 1	; _
	13	[82]	LOADK    	7 -8	; "Set time"
	14	[82]	CALL     	6 2 2
	15	[82]	SETTABLE 	5 -7 6	; "ok_text" -
	16	[83]	GETUPVAL 	6 1	; _
	17	[83]	LOADK    	7 -8	; "Set time"
	18	[83]	CALL     	6 2 2
	19	[83]	SETTABLE 	5 -9 6	; "title_text" -
	20	[96]	CLOSURE  	6 0	; 0x7f9929407fd0
	21	[96]	GETUPVAL 	0 2	; Device
	22	[96]	MOVE     	0 0
	23	[96]	GETUPVAL 	0 3	; UIManager
	24	[96]	GETUPVAL 	0 4	; InfoMessage
	25	[96]	GETUPVAL 	0 5	; T
	26	[96]	GETUPVAL 	0 1	; _
	27	[96]	SETTABLE 	5 -10 6	; "callback" -
	28	[79]	CALL     	3 3 2
	29	[98]	GETUPVAL 	4 3	; UIManager
	30	[98]	SELF     	4 4 -11	; "show"
	31	[98]	MOVE     	6 3
	32	[98]	CALL     	4 3 1
	33	[99]	RETURN   	0 1

function <./frontend/ui/elements/common_settings_menu_table.lua:84,96> (51 instructions, 204 bytes at 0x7f9929407fd0)
1 param, 12 slots, 6 upvalues, 1 local, 14 constants, 0 functions
	1	[85]	GETUPVAL 	1 0	; Device
	2	[85]	SELF     	1 1 -1	; "setDateTime"
	3	[85]	LOADNIL  	3 5
	4	[85]	GETTABLE 	6 0 -2	; "hour"
	5	[85]	GETTABLE 	7 0 -3	; "min"
	6	[85]	CALL     	1 7 2
	7	[85]	TEST     	1 0 0
	8	[85]	JMP      	31	; to 40
	9	[86]	GETGLOBAL	1 -4	; os
	10	[86]	GETTABLE 	1 1 -5	; "date"
	11	[86]	LOADK    	2 -6	; "*t"
	12	[86]	CALL     	1 2 2
	13	[86]	SETUPVAL 	1 1	; now_t
	14	[87]	GETUPVAL 	1 2	; UIManager
	15	[87]	SELF     	1 1 -7	; "show"
	16	[87]	GETUPVAL 	3 3	; InfoMessage
	17	[87]	SELF     	3 3 -8	; "new"
	18	[87]	NEWTABLE 	5 0 1
	19	[88]	GETUPVAL 	6 4	; T
	20	[88]	GETUPVAL 	7 5	; _
	21	[88]	LOADK    	8 -10	; "Current time: %1:%2"
	22	[88]	CALL     	7 2 2
	23	[88]	GETGLOBAL	8 -11	; string
	24	[88]	GETTABLE 	8 8 -12	; "format"
	25	[88]	LOADK    	9 -13	; "%02d"
	26	[88]	GETUPVAL 	10 1	; now_t
	27	[88]	GETTABLE 	10 10 -2	; "hour"
	28	[88]	CALL     	8 3 2
	29	[89]	GETGLOBAL	9 -11	; string
	30	[89]	GETTABLE 	9 9 -12	; "format"
	31	[89]	LOADK    	10 -13	; "%02d"
	32	[89]	GETUPVAL 	11 1	; now_t
	33	[89]	GETTABLE 	11 11 -3	; "min"
	34	[89]	CALL     	9 3 0
	35	[88]	CALL     	6 0 2
	36	[89]	SETTABLE 	5 -9 6	; "text" -
	37	[87]	CALL     	3 3 0
	38	[87]	CALL     	1 0 1
	39	[90]	JMP      	11	; to 51
	40	[92]	GETUPVAL 	1 2	; UIManager
	41	[92]	SELF     	1 1 -7	; "show"
	42	[92]	GETUPVAL 	3 3	; InfoMessage
	43	[92]	SELF     	3 3 -8	; "new"
	44	[92]	NEWTABLE 	5 0 1
	45	[93]	GETUPVAL 	6 5	; _
	46	[93]	LOADK    	7 -14	; "Time couldn't be set"
	47	[93]	CALL     	6 2 2
	48	[93]	SETTABLE 	5 -9 6	; "text" -
	49	[92]	CALL     	3 3 0
	50	[92]	CALL     	1 0 1
	51	[96]	RETURN   	0 1

function <./frontend/ui/elements/common_settings_menu_table.lua:104,131> (35 instructions, 140 bytes at 0x7f9929408230)
0 params, 9 slots, 6 upvalues, 5 locals, 12 constants, 1 function
	1	[105]	GETGLOBAL	0 -1	; os
	2	[105]	GETTABLE 	0 0 -2	; "date"
	3	[105]	LOADK    	1 -3	; "*t"
	4	[105]	CALL     	0 2 2
	5	[106]	GETTABLE 	1 0 -4	; "year"
	6	[107]	GETTABLE 	2 0 -5	; "month"
	7	[108]	GETTABLE 	3 0 -6	; "day"
	8	[109]	GETUPVAL 	4 0	; DateWidget
	9	[109]	SELF     	4 4 -7	; "new"
	10	[109]	NEWTABLE 	6 0 6
	11	[110]	SETTABLE 	6 -4 1	; "year" -
	12	[111]	SETTABLE 	6 -5 2	; "month" -
	13	[112]	SETTABLE 	6 -6 3	; "day" -
	14	[113]	GETUPVAL 	7 1	; _
	15	[113]	LOADK    	8 -9	; "Set date"
	16	[113]	CALL     	7 2 2
	17	[113]	SETTABLE 	6 -8 7	; "ok_text" -
	18	[114]	GETUPVAL 	7 1	; _
	19	[114]	LOADK    	8 -9	; "Set date"
	20	[114]	CALL     	7 2 2
	21	[114]	SETTABLE 	6 -10 7	; "title_text" -
	22	[128]	CLOSURE  	7 0	; 0x7f99294089c0
	23	[128]	MOVE     	0 0
	24	[128]	GETUPVAL 	0 2	; Device
	25	[128]	GETUPVAL 	0 3	; UIManager
	26	[128]	GETUPVAL 	0 4	; InfoMessage
	27	[128]	GETUPVAL 	0 5	; T
	28	[128]	GETUPVAL 	0 1	; _
	29	[128]	SETTABLE 	6 -11 7	; "callback" -
	30	[109]	CALL     	4 3 2
	31	[130]	GETUPVAL 	5 3	; UIManager
	32	[130]	SELF     	5 5 -12	; "show"
	33	[130]	MOVE     	7 4
	34	[130]	CALL     	5 3 1
	35	[131]	RETURN   	0 1

function <./frontend/ui/elements/common_settings_menu_table.lua:115,128> (64 instructions, 256 bytes at 0x7f99294089c0)
1 param, 13 slots, 6 upvalues, 1 local, 18 constants, 0 functions
	1	[116]	GETGLOBAL	1 -1	; os
	2	[116]	GETTABLE 	1 1 -2	; "date"
	3	[116]	LOADK    	2 -3	; "*t"
	4	[116]	CALL     	1 2 2
	5	[116]	SETUPVAL 	1 0	; now_t
	6	[117]	GETUPVAL 	1 1	; Device
	7	[117]	SELF     	1 1 -4	; "setDateTime"
	8	[117]	GETTABLE 	3 0 -5	; "year"
	9	[117]	GETTABLE 	4 0 -6	; "month"
	10	[117]	GETTABLE 	5 0 -7	; "day"
	11	[117]	GETUPVAL 	6 0	; now_t
	12	[117]	GETTABLE 	6 6 -8	; "hour"
	13	[117]	GETUPVAL 	7 0	; now_t
	14	[117]	GETTABLE 	7 7 -9	; "min"
	15	[117]	GETUPVAL 	8 0	; now_t
	16	[117]	GETTABLE 	8 8 -10	; "sec"
	17	[117]	CALL     	1 8 2
	18	[117]	TEST     	1 0 0
	19	[117]	JMP      	33	; to 53
	20	[118]	GETGLOBAL	1 -1	; os
	21	[118]	GETTABLE 	1 1 -2	; "date"
	22	[118]	LOADK    	2 -3	; "*t"
	23	[118]	CALL     	1 2 2
	24	[118]	SETUPVAL 	1 0	; now_t
	25	[119]	GETUPVAL 	1 2	; UIManager
	26	[119]	SELF     	1 1 -11	; "show"
	27	[119]	GETUPVAL 	3 3	; InfoMessage
	28	[119]	SELF     	3 3 -12	; "new"
	29	[119]	NEWTABLE 	5 0 1
	30	[120]	GETUPVAL 	6 4	; T
	31	[120]	GETUPVAL 	7 5	; _
	32	[120]	LOADK    	8 -14	; "Current date: %1-%2-%3"
	33	[120]	CALL     	7 2 2
	34	[120]	GETUPVAL 	8 0	; now_t
	35	[120]	GETTABLE 	8 8 -5	; "year"
	36	[120]	GETGLOBAL	9 -15	; string
	37	[120]	GETTABLE 	9 9 -16	; "format"
	38	[120]	LOADK    	10 -17	; "%02d"
	39	[120]	GETUPVAL 	11 0	; now_t
	40	[120]	GETTABLE 	11 11 -6	; "month"
	41	[120]	CALL     	9 3 2
	42	[121]	GETGLOBAL	10 -15	; string
	43	[121]	GETTABLE 	10 10 -16	; "format"
	44	[121]	LOADK    	11 -17	; "%02d"
	45	[121]	GETUPVAL 	12 0	; now_t
	46	[121]	GETTABLE 	12 12 -7	; "day"
	47	[121]	CALL     	10 3 0
	48	[120]	CALL     	6 0 2
	49	[121]	SETTABLE 	5 -13 6	; "text" -
	50	[119]	CALL     	3 3 0
	51	[119]	CALL     	1 0 1
	52	[122]	JMP      	11	; to 64
	53	[124]	GETUPVAL 	1 2	; UIManager
	54	[124]	SELF     	1 1 -11	; "show"
	55	[124]	GETUPVAL 	3 3	; InfoMessage
	56	[124]	SELF     	3 3 -12	; "new"
	57	[124]	NEWTABLE 	5 0 1
	58	[125]	GETUPVAL 	6 5	; _
	59	[125]	LOADK    	7 -18	; "Date couldn't be set"
	60	[125]	CALL     	6 2 2
	61	[125]	SETTABLE 	5 -13 6	; "text" -
	62	[124]	CALL     	3 3 0
	63	[124]	CALL     	1 0 1
	64	[128]	RETURN   	0 1

function <./frontend/ui/elements/common_settings_menu_table.lua:138,140> (6 instructions, 24 bytes at 0x7f9929408940)
0 params, 3 slots, 0 upvalues, 0 locals, 3 constants, 0 functions
	1	[139]	GETGLOBAL	0 -1	; G_reader_settings
	2	[139]	SELF     	0 0 -2	; "isTrue"
	3	[139]	LOADK    	2 -3	; "ignore_power_sleepcover"
	4	[139]	TAILCALL 	0 3 0
	5	[139]	RETURN   	0 0
	6	[140]	RETURN   	0 1

function <./frontend/ui/elements/common_settings_menu_table.lua:141,147> (20 instructions, 80 bytes at 0x7f9929409270)
0 params, 7 slots, 3 upvalues, 0 locals, 9 constants, 0 functions
	1	[142]	GETGLOBAL	0 -1	; G_reader_settings
	2	[142]	SELF     	0 0 -2	; "flipNilOrFalse"
	3	[142]	LOADK    	2 -3	; "ignore_power_sleepcover"
	4	[142]	CALL     	0 3 1
	5	[143]	GETGLOBAL	0 -1	; G_reader_settings
	6	[143]	SELF     	0 0 -4	; "flipFalse"
	7	[143]	LOADK    	2 -5	; "ignore_open_sleepcover"
	8	[143]	CALL     	0 3 1
	9	[144]	GETUPVAL 	0 0	; UIManager
	10	[144]	SELF     	0 0 -6	; "show"
	11	[144]	GETUPVAL 	2 1	; InfoMessage
	12	[144]	SELF     	2 2 -7	; "new"
	13	[144]	NEWTABLE 	4 0 1
	14	[145]	GETUPVAL 	5 2	; _
	15	[145]	LOADK    	6 -9	; "This will take effect on next restart."
	16	[145]	CALL     	5 2 2
	17	[145]	SETTABLE 	4 -8 5	; "text" -
	18	[144]	CALL     	2 3 0
	19	[144]	CALL     	0 0 1
	20	[147]	RETURN   	0 1

function <./frontend/ui/elements/common_settings_menu_table.lua:152,154> (6 instructions, 24 bytes at 0x7f9929409af0)
0 params, 3 slots, 0 upvalues, 0 locals, 3 constants, 0 functions
	1	[153]	GETGLOBAL	0 -1	; G_reader_settings
	2	[153]	SELF     	0 0 -2	; "isTrue"
	3	[153]	LOADK    	2 -3	; "ignore_open_sleepcover"
	4	[153]	TAILCALL 	0 3 0
	5	[153]	RETURN   	0 0
	6	[154]	RETURN   	0 1

function <./frontend/ui/elements/common_settings_menu_table.lua:155,161> (20 instructions, 80 bytes at 0x7f9929409bb0)
0 params, 7 slots, 3 upvalues, 0 locals, 9 constants, 0 functions
	1	[156]	GETGLOBAL	0 -1	; G_reader_settings
	2	[156]	SELF     	0 0 -2	; "flipNilOrFalse"
	3	[156]	LOADK    	2 -3	; "ignore_open_sleepcover"
	4	[156]	CALL     	0 3 1
	5	[157]	GETGLOBAL	0 -1	; G_reader_settings
	6	[157]	SELF     	0 0 -4	; "flipFalse"
	7	[157]	LOADK    	2 -5	; "ignore_power_sleepcover"
	8	[157]	CALL     	0 3 1
	9	[158]	GETUPVAL 	0 0	; UIManager
	10	[158]	SELF     	0 0 -6	; "show"
	11	[158]	GETUPVAL 	2 1	; InfoMessage
	12	[158]	SELF     	2 2 -7	; "new"
	13	[158]	NEWTABLE 	4 0 1
	14	[159]	GETUPVAL 	5 2	; _
	15	[159]	LOADK    	6 -9	; "This will take effect on next restart."
	16	[159]	CALL     	5 2 2
	17	[159]	SETTABLE 	4 -8 5	; "text" -
	18	[158]	CALL     	2 3 0
	19	[158]	CALL     	0 0 1
	20	[161]	RETURN   	0 1

function <./frontend/ui/elements/common_settings_menu_table.lua:167,167> (6 instructions, 24 bytes at 0x7f992940a300)
0 params, 3 slots, 0 upvalues, 0 locals, 3 constants, 0 functions
	1	[167]	GETGLOBAL	0 -1	; G_reader_settings
	2	[167]	SELF     	0 0 -2	; "isTrue"
	3	[167]	LOADK    	2 -3	; "night_mode"
	4	[167]	TAILCALL 	0 3 0
	5	[167]	RETURN   	0 0
	6	[167]	RETURN   	0 1

function <./frontend/ui/elements/common_settings_menu_table.lua:168,173> (18 instructions, 72 bytes at 0x7f992940a380)
0 params, 5 slots, 2 upvalues, 1 local, 7 constants, 0 functions
	1	[169]	GETGLOBAL	0 -1	; G_reader_settings
	2	[169]	SELF     	0 0 -2	; "isTrue"
	3	[169]	LOADK    	2 -3	; "night_mode"
	4	[169]	CALL     	0 3 2
	5	[170]	GETUPVAL 	1 0	; Screen
	6	[170]	SELF     	1 1 -4	; "toggleNightMode"
	7	[170]	CALL     	1 2 1
	8	[171]	GETUPVAL 	1 1	; UIManager
	9	[171]	SELF     	1 1 -5	; "setDirty"
	10	[171]	LOADNIL  	3 3
	11	[171]	LOADK    	4 -6	; "full"
	12	[171]	CALL     	1 4 1
	13	[172]	GETGLOBAL	1 -1	; G_reader_settings
	14	[172]	SELF     	1 1 -7	; "saveSetting"
	15	[172]	LOADK    	3 -3	; "night_mode"
	16	[172]	NOT      	4 0
	17	[172]	CALL     	1 4 1
	18	[173]	RETURN   	0 1

function <./frontend/ui/elements/common_settings_menu_table.lua:189,191> (6 instructions, 24 bytes at 0x7f992940ad30)
0 params, 3 slots, 0 upvalues, 0 locals, 3 constants, 0 functions
	1	[190]	GETGLOBAL	0 -1	; G_reader_settings
	2	[190]	SELF     	0 0 -2	; "isTrue"
	3	[190]	LOADK    	2 -3	; "ignore_hold_corners"
	4	[190]	TAILCALL 	0 3 0
	5	[190]	RETURN   	0 0
	6	[191]	RETURN   	0 1

function <./frontend/ui/elements/common_settings_menu_table.lua:192,194> (8 instructions, 32 bytes at 0x7f992940aeb0)
0 params, 5 slots, 2 upvalues, 0 locals, 3 constants, 0 functions
	1	[193]	GETUPVAL 	0 0	; UIManager
	2	[193]	SELF     	0 0 -1	; "broadcastEvent"
	3	[193]	GETUPVAL 	2 1	; Event
	4	[193]	SELF     	2 2 -2	; "new"
	5	[193]	LOADK    	4 -3	; "IgnoreHoldCorners"
	6	[193]	CALL     	2 3 0
	7	[193]	CALL     	0 0 1
	8	[194]	RETURN   	0 1

function <./frontend/ui/elements/common_settings_menu_table.lua:217,217> (6 instructions, 24 bytes at 0x7f992940b660)
0 params, 3 slots, 0 upvalues, 0 locals, 3 constants, 0 functions
	1	[217]	GETGLOBAL	0 -1	; G_reader_settings
	2	[217]	SELF     	0 0 -2	; "isTrue"
	3	[217]	LOADK    	2 -3	; "haptic_feedback_override"
	4	[217]	TAILCALL 	0 3 0
	5	[217]	RETURN   	0 0
	6	[217]	RETURN   	0 1

function <./frontend/ui/elements/common_settings_menu_table.lua:218,221> (12 instructions, 48 bytes at 0x7f992940b720)
0 params, 4 slots, 1 upvalue, 0 locals, 5 constants, 0 functions
	1	[219]	GETGLOBAL	0 -1	; G_reader_settings
	2	[219]	SELF     	0 0 -2	; "flipNilOrFalse"
	3	[219]	LOADK    	2 -3	; "haptic_feedback_override"
	4	[219]	CALL     	0 3 1
	5	[220]	GETUPVAL 	0 0	; android
	6	[220]	GETTABLE 	0 0 -4	; "setHapticOverride"
	7	[220]	GETGLOBAL	1 -1	; G_reader_settings
	8	[220]	SELF     	1 1 -5	; "isTrue"
	9	[220]	LOADK    	3 -3	; "haptic_feedback_override"
	10	[220]	CALL     	1 3 0
	11	[220]	CALL     	0 0 1
	12	[221]	RETURN   	0 1

function <./frontend/ui/elements/common_settings_menu_table.lua:227,227> (6 instructions, 24 bytes at 0x7f9929409a70)
0 params, 2 slots, 1 upvalue, 0 locals, 1 constant, 0 functions
	1	[227]	GETUPVAL 	0 0	; android
	2	[227]	GETTABLE 	0 0 -1	; "getVolumeKeysIgnored"
	3	[227]	CALL     	0 1 2
	4	[227]	NOT      	0 0
	5	[227]	RETURN   	0 2
	6	[227]	RETURN   	0 1

function <./frontend/ui/elements/common_settings_menu_table.lua:228,232> (13 instructions, 52 bytes at 0x7f992940b7e0)
0 params, 5 slots, 1 upvalue, 1 local, 5 constants, 0 functions
	1	[229]	GETUPVAL 	0 0	; android
	2	[229]	GETTABLE 	0 0 -1	; "getVolumeKeysIgnored"
	3	[229]	CALL     	0 1 2
	4	[230]	GETUPVAL 	1 0	; android
	5	[230]	GETTABLE 	1 1 -2	; "setVolumeKeysIgnored"
	6	[230]	NOT      	2 0
	7	[230]	CALL     	1 2 1
	8	[231]	GETGLOBAL	1 -3	; G_reader_settings
	9	[231]	SELF     	1 1 -4	; "saveSetting"
	10	[231]	LOADK    	3 -5	; "android_ignore_volume_keys"
	11	[231]	NOT      	4 0
	12	[231]	CALL     	1 4 1
	13	[232]	RETURN   	0 1

function <./frontend/ui/elements/common_settings_menu_table.lua:238,238> (6 instructions, 24 bytes at 0x7f9929409910)
0 params, 3 slots, 0 upvalues, 0 locals, 3 constants, 0 functions
	1	[238]	GETGLOBAL	0 -1	; G_reader_settings
	2	[238]	SELF     	0 0 -2	; "isTrue"
	3	[238]	LOADK    	2 -3	; "camera_key_toggles_touchscreen"
	4	[238]	TAILCALL 	0 3 0
	5	[238]	RETURN   	0 0
	6	[238]	RETURN   	0 1

function <./frontend/ui/elements/common_settings_menu_table.lua:239,239> (5 instructions, 20 bytes at 0x7f992940a8e0)
0 params, 3 slots, 0 upvalues, 0 locals, 3 constants, 0 functions
	1	[239]	GETGLOBAL	0 -1	; G_reader_settings
	2	[239]	SELF     	0 0 -2	; "flipNilOrFalse"
	3	[239]	LOADK    	2 -3	; "camera_key_toggles_touchscreen"
	4	[239]	CALL     	0 3 1
	5	[239]	RETURN   	0 1

function <./frontend/ui/elements/common_settings_menu_table.lua:246,246> (5 instructions, 20 bytes at 0x7f992940ba60)
0 params, 2 slots, 1 upvalue, 0 locals, 1 constant, 0 functions
	1	[246]	GETUPVAL 	0 0	; android
	2	[246]	GETTABLE 	0 0 -1	; "isFullscreen"
	3	[246]	TAILCALL 	0 1 0
	4	[246]	RETURN   	0 0
	5	[246]	RETURN   	0 1

function <./frontend/ui/elements/common_settings_menu_table.lua:247,247> (6 instructions, 24 bytes at 0x7f992940bc80)
0 params, 2 slots, 0 upvalues, 0 locals, 3 constants, 0 functions
	1	[247]	GETGLOBAL	0 -1	; require
	2	[247]	LOADK    	1 -2	; "ui/elements/screen_android"
	3	[247]	CALL     	0 2 2
	4	[247]	SELF     	0 0 -3	; "toggleFullscreen"
	5	[247]	CALL     	0 2 1
	6	[247]	RETURN   	0 1

function <./frontend/ui/elements/common_settings_menu_table.lua:271,275> (17 instructions, 68 bytes at 0x7f992940c120)
0 params, 4 slots, 3 upvalues, 1 local, 6 constants, 0 functions
	1	[272]	GETGLOBAL	0 -1	; G_reader_settings
	2	[272]	SELF     	0 0 -2	; "readSetting"
	3	[272]	LOADK    	2 -3	; "back_to_exit"
	4	[272]	CALL     	0 3 2
	5	[272]	TEST     	0 0 1
	6	[272]	JMP      	1	; to 8
	7	[272]	LOADK    	0 -4	; "prompt"
	8	[273]	GETUPVAL 	1 0	; T
	9	[273]	GETUPVAL 	2 1	; _
	10	[273]	LOADK    	3 -5	; "Back to exit (%1)"
	11	[273]	CALL     	2 2 2
	12	[274]	GETUPVAL 	3 2	; back_to_exit_str
	13	[274]	GETTABLE 	3 3 0
	14	[274]	GETTABLE 	3 3 -6	; 2
	15	[273]	TAILCALL 	1 3 0
	16	[274]	RETURN   	1 0
	17	[275]	RETURN   	0 1

function <./frontend/ui/elements/common_settings_menu_table.lua:279,282> (12 instructions, 48 bytes at 0x7f992940c740)
0 params, 3 slots, 0 upvalues, 1 local, 5 constants, 0 functions
	1	[280]	GETGLOBAL	0 -1	; G_reader_settings
	2	[280]	SELF     	0 0 -2	; "readSetting"
	3	[280]	LOADK    	2 -3	; "back_to_exit"
	4	[280]	CALL     	0 3 2
	5	[281]	EQ       	1 0 -4	; - "prompt"
	6	[281]	JMP      	3	; to 10
	7	[281]	EQ       	1 0 -5	; - nil
	8	[281]	JMP      	1	; to 10
	9	[281]	LOADBOOL 	1 0 1
	10	[281]	LOADBOOL 	1 1 0
	11	[281]	RETURN   	1 2
	12	[282]	RETURN   	0 1

function <./frontend/ui/elements/common_settings_menu_table.lua:283,285> (6 instructions, 24 bytes at 0x7f992940c970)
0 params, 4 slots, 0 upvalues, 0 locals, 4 constants, 0 functions
	1	[284]	GETGLOBAL	0 -1	; G_reader_settings
	2	[284]	SELF     	0 0 -2	; "saveSetting"
	3	[284]	LOADK    	2 -3	; "back_to_exit"
	4	[284]	LOADK    	3 -4	; "prompt"
	5	[284]	CALL     	0 4 1
	6	[285]	RETURN   	0 1

function <./frontend/ui/elements/common_settings_menu_table.lua:289,292> (10 instructions, 40 bytes at 0x7f992940ccf0)
0 params, 3 slots, 0 upvalues, 0 locals, 4 constants, 0 functions
	1	[290]	GETGLOBAL	0 -1	; G_reader_settings
	2	[290]	SELF     	0 0 -2	; "readSetting"
	3	[290]	LOADK    	2 -3	; "back_to_exit"
	4	[290]	CALL     	0 3 2
	5	[291]	EQ       	1 0 -4	; - "always"
	6	[291]	JMP      	1	; to 8
	7	[291]	LOADBOOL 	0 0 1
	8	[291]	LOADBOOL 	0 1 0
	9	[291]	RETURN   	0 2
	10	[292]	RETURN   	0 1

function <./frontend/ui/elements/common_settings_menu_table.lua:293,295> (6 instructions, 24 bytes at 0x7f992940d140)
0 params, 4 slots, 0 upvalues, 0 locals, 4 constants, 0 functions
	1	[294]	GETGLOBAL	0 -1	; G_reader_settings
	2	[294]	SELF     	0 0 -2	; "saveSetting"
	3	[294]	LOADK    	2 -3	; "back_to_exit"
	4	[294]	LOADK    	3 -4	; "always"
	5	[294]	CALL     	0 4 1
	6	[295]	RETURN   	0 1

function <./frontend/ui/elements/common_settings_menu_table.lua:299,302> (10 instructions, 40 bytes at 0x7f992940d200)
0 params, 3 slots, 0 upvalues, 0 locals, 4 constants, 0 functions
	1	[300]	GETGLOBAL	0 -1	; G_reader_settings
	2	[300]	SELF     	0 0 -2	; "readSetting"
	3	[300]	LOADK    	2 -3	; "back_to_exit"
	4	[300]	CALL     	0 3 2
	5	[301]	EQ       	1 0 -4	; - "disable"
	6	[301]	JMP      	1	; to 8
	7	[301]	LOADBOOL 	0 0 1
	8	[301]	LOADBOOL 	0 1 0
	9	[301]	RETURN   	0 2
	10	[302]	RETURN   	0 1

function <./frontend/ui/elements/common_settings_menu_table.lua:303,305> (6 instructions, 24 bytes at 0x7f992940d6a0)
0 params, 4 slots, 0 upvalues, 0 locals, 4 constants, 0 functions
	1	[304]	GETGLOBAL	0 -1	; G_reader_settings
	2	[304]	SELF     	0 0 -2	; "saveSetting"
	3	[304]	LOADK    	2 -3	; "back_to_exit"
	4	[304]	LOADK    	3 -4	; "disable"
	5	[304]	CALL     	0 4 1
	6	[305]	RETURN   	0 1

function <./frontend/ui/elements/common_settings_menu_table.lua:313,317> (17 instructions, 68 bytes at 0x7f992940d760)
0 params, 4 slots, 3 upvalues, 1 local, 6 constants, 0 functions
	1	[314]	GETGLOBAL	0 -1	; G_reader_settings
	2	[314]	SELF     	0 0 -2	; "readSetting"
	3	[314]	LOADK    	2 -3	; "back_to_exit"
	4	[314]	CALL     	0 3 2
	5	[314]	TEST     	0 0 1
	6	[314]	JMP      	1	; to 8
	7	[314]	LOADK    	0 -4	; "prompt"
	8	[315]	GETUPVAL 	1 0	; T
	9	[315]	GETUPVAL 	2 1	; _
	10	[315]	LOADK    	3 -5	; "Back to exit (%1)"
	11	[315]	CALL     	2 2 2
	12	[316]	GETUPVAL 	3 2	; back_to_exit_str
	13	[316]	GETTABLE 	3 3 0
	14	[316]	GETTABLE 	3 3 -6	; 2
	15	[315]	TAILCALL 	1 3 0
	16	[316]	RETURN   	1 0
	17	[317]	RETURN   	0 1

function <./frontend/ui/elements/common_settings_menu_table.lua:318,321> (12 instructions, 48 bytes at 0x7f992940dec0)
0 params, 3 slots, 0 upvalues, 1 local, 5 constants, 0 functions
	1	[319]	GETGLOBAL	0 -1	; G_reader_settings
	2	[319]	SELF     	0 0 -2	; "readSetting"
	3	[319]	LOADK    	2 -3	; "back_in_filemanager"
	4	[319]	CALL     	0 3 2
	5	[320]	EQ       	1 0 -4	; - nil
	6	[320]	JMP      	3	; to 10
	7	[320]	EQ       	1 0 -5	; - "default"
	8	[320]	JMP      	1	; to 10
	9	[320]	LOADBOOL 	1 0 1
	10	[320]	LOADBOOL 	1 1 0
	11	[320]	RETURN   	1 2
	12	[321]	RETURN   	0 1

function <./frontend/ui/elements/common_settings_menu_table.lua:322,324> (6 instructions, 24 bytes at 0x7f992940e0a0)
0 params, 4 slots, 0 upvalues, 0 locals, 4 constants, 0 functions
	1	[323]	GETGLOBAL	0 -1	; G_reader_settings
	2	[323]	SELF     	0 0 -2	; "saveSetting"
	3	[323]	LOADK    	2 -3	; "back_in_filemanager"
	4	[323]	LOADK    	3 -4	; "default"
	5	[323]	CALL     	0 4 1
	6	[324]	RETURN   	0 1

function <./frontend/ui/elements/common_settings_menu_table.lua:328,331> (10 instructions, 40 bytes at 0x7f992940e420)
0 params, 3 slots, 0 upvalues, 0 locals, 4 constants, 0 functions
	1	[329]	GETGLOBAL	0 -1	; G_reader_settings
	2	[329]	SELF     	0 0 -2	; "readSetting"
	3	[329]	LOADK    	2 -3	; "back_in_filemanager"
	4	[329]	CALL     	0 3 2
	5	[330]	EQ       	1 0 -4	; - "parent_folder"
	6	[330]	JMP      	1	; to 8
	7	[330]	LOADBOOL 	0 0 1
	8	[330]	LOADBOOL 	0 1 0
	9	[330]	RETURN   	0 2
	10	[331]	RETURN   	0 1

function <./frontend/ui/elements/common_settings_menu_table.lua:332,334> (6 instructions, 24 bytes at 0x7f992940b2a0)
0 params, 4 slots, 0 upvalues, 0 locals, 4 constants, 0 functions
	1	[333]	GETGLOBAL	0 -1	; G_reader_settings
	2	[333]	SELF     	0 0 -2	; "saveSetting"
	3	[333]	LOADK    	2 -3	; "back_in_filemanager"
	4	[333]	LOADK    	3 -4	; "parent_folder"
	5	[333]	CALL     	0 4 1
	6	[334]	RETURN   	0 1

function <./frontend/ui/elements/common_settings_menu_table.lua:340,342> (6 instructions, 24 bytes at 0x7f992940ea70)
0 params, 3 slots, 0 upvalues, 0 locals, 3 constants, 0 functions
	1	[341]	GETGLOBAL	0 -1	; G_reader_settings
	2	[341]	SELF     	0 0 -2	; "nilOrTrue"
	3	[341]	LOADK    	2 -3	; "enable_back_history"
	4	[341]	TAILCALL 	0 3 0
	5	[341]	RETURN   	0 0
	6	[342]	RETURN   	0 1

function <./frontend/ui/elements/common_settings_menu_table.lua:343,345> (5 instructions, 20 bytes at 0x7f992940ed40)
0 params, 3 slots, 0 upvalues, 0 locals, 3 constants, 0 functions
	1	[344]	GETGLOBAL	0 -1	; G_reader_settings
	2	[344]	SELF     	0 0 -2	; "flipNilOrTrue"
	3	[344]	LOADK    	2 -3	; "enable_back_history"
	4	[344]	CALL     	0 3 1
	5	[345]	RETURN   	0 1

function <./frontend/ui/elements/common_settings_menu_table.lua:350,352> (6 instructions, 24 bytes at 0x7f992940f100)
0 params, 3 slots, 0 upvalues, 0 locals, 3 constants, 0 functions
	1	[351]	GETGLOBAL	0 -1	; G_reader_settings
	2	[351]	SELF     	0 0 -2	; "isTrue"
	3	[351]	LOADK    	2 -3	; "input_invert_page_turn_keys"
	4	[351]	TAILCALL 	0 3 0
	5	[351]	RETURN   	0 0
	6	[352]	RETURN   	0 1

function <./frontend/ui/elements/common_settings_menu_table.lua:353,356> (8 instructions, 32 bytes at 0x7f992940f250)
0 params, 3 slots, 1 upvalue, 0 locals, 4 constants, 0 functions
	1	[354]	GETGLOBAL	0 -1	; G_reader_settings
	2	[354]	SELF     	0 0 -2	; "flipNilOrFalse"
	3	[354]	LOADK    	2 -3	; "input_invert_page_turn_keys"
	4	[354]	CALL     	0 3 1
	5	[355]	GETUPVAL 	0 0	; Device
	6	[355]	SELF     	0 0 -4	; "invertButtons"
	7	[355]	CALL     	0 2 1
	8	[356]	RETURN   	0 1

function <./frontend/ui/elements/common_settings_menu_table.lua:381,399> (32 instructions, 128 bytes at 0x7f992940fb50)
1 param, 8 slots, 4 upvalues, 3 locals, 8 constants, 2 functions
	1	[382]	LOADK    	1 -1	; "auto_save_settings_interval_minutes"
	2	[383]	LOADNIL  	2 2
	3	[384]	TEST     	0 0 1
	4	[384]	JMP      	5	; to 10
	5	[385]	GETUPVAL 	3 0	; _
	6	[385]	LOADK    	4 -2	; "Only on close, suspend and exit"
	7	[385]	CALL     	3 2 2
	8	[385]	MOVE     	2 3
	9	[385]	JMP      	9	; to 19
	10	[387]	GETUPVAL 	3 1	; T
	11	[387]	GETUPVAL 	4 2	; N_
	12	[387]	LOADK    	5 -3	; "Every minute"
	13	[387]	LOADK    	6 -4	; "Every %1 minutes"
	14	[387]	MOVE     	7 0
	15	[387]	CALL     	4 4 2
	16	[387]	MOVE     	5 0
	17	[387]	CALL     	3 3 2
	18	[387]	MOVE     	2 3
	19	[389]	NEWTABLE 	3 0 4
	20	[390]	SETTABLE 	3 -5 2	; "text" -
	21	[391]	GETUPVAL 	4 3	; auto_save_help_text
	22	[391]	SETTABLE 	3 -6 4	; "help_text" -
	23	[394]	CLOSURE  	4 0	; 0x7f992940fe90
	24	[394]	MOVE     	0 1
	25	[394]	MOVE     	0 0
	26	[394]	SETTABLE 	3 -7 4	; "checked_func" -
	27	[397]	CLOSURE  	4 1	; 0x7f9929410010
	28	[397]	MOVE     	0 1
	29	[397]	MOVE     	0 0
	30	[397]	SETTABLE 	3 -8 4	; "callback" -
	31	[398]	RETURN   	3 2
	32	[399]	RETURN   	0 1

function <./frontend/ui/elements/common_settings_menu_table.lua:392,394> (11 instructions, 44 bytes at 0x7f992940fe90)
0 params, 3 slots, 2 upvalues, 0 locals, 2 constants, 0 functions
	1	[393]	GETGLOBAL	0 -1	; G_reader_settings
	2	[393]	SELF     	0 0 -2	; "readSetting"
	3	[393]	GETUPVAL 	2 0	; setting_name
	4	[393]	CALL     	0 3 2
	5	[393]	GETUPVAL 	1 1	; value
	6	[393]	EQ       	1 0 1
	7	[393]	JMP      	1	; to 9
	8	[393]	LOADBOOL 	0 0 1
	9	[393]	LOADBOOL 	0 1 0
	10	[393]	RETURN   	0 2
	11	[394]	RETURN   	0 1

function <./frontend/ui/elements/common_settings_menu_table.lua:395,397> (6 instructions, 24 bytes at 0x7f9929410010)
0 params, 4 slots, 2 upvalues, 0 locals, 2 constants, 0 functions
	1	[396]	GETGLOBAL	0 -1	; G_reader_settings
	2	[396]	SELF     	0 0 -2	; "saveSetting"
	3	[396]	GETUPVAL 	2 0	; setting_name
	4	[396]	GETUPVAL 	3 1	; value
	5	[396]	CALL     	0 4 1
	6	[397]	RETURN   	0 1

function <./frontend/ui/elements/common_settings_menu_table.lua:405,414> (26 instructions, 104 bytes at 0x7f9929410380)
0 params, 7 slots, 3 upvalues, 2 locals, 8 constants, 0 functions
	1	[406]	GETGLOBAL	0 -1	; G_reader_settings
	2	[406]	SELF     	0 0 -2	; "readSetting"
	3	[406]	LOADK    	2 -3	; "auto_save_settings_interval_minutes"
	4	[406]	CALL     	0 3 2
	5	[407]	LOADNIL  	1 1
	6	[408]	EQ       	0 0 -4	; - false
	7	[408]	JMP      	2	; to 10
	8	[409]	LOADK    	1 -5	; "only on close"
	9	[409]	JMP      	9	; to 19
	10	[411]	GETUPVAL 	2 0	; T
	11	[411]	GETUPVAL 	3 1	; N_
	12	[411]	LOADK    	4 -6	; "every 1 m"
	13	[411]	LOADK    	5 -7	; "every %1 m"
	14	[411]	MOVE     	6 0
	15	[411]	CALL     	3 4 2
	16	[411]	MOVE     	4 0
	17	[411]	CALL     	2 3 2
	18	[411]	MOVE     	1 2
	19	[413]	GETUPVAL 	2 0	; T
	20	[413]	GETUPVAL 	3 2	; _
	21	[413]	LOADK    	4 -8	; "Auto-save book metadata: %1"
	22	[413]	CALL     	3 2 2
	23	[413]	MOVE     	4 1
	24	[413]	TAILCALL 	2 3 0
	25	[413]	RETURN   	2 0
	26	[414]	RETURN   	0 1

function <./frontend/ui/elements/common_settings_menu_table.lua:424,426> (10 instructions, 40 bytes at 0x7f992940bdd0)
0 params, 6 slots, 3 upvalues, 0 locals, 3 constants, 0 functions
	1	[425]	GETUPVAL 	0 0	; UIManager
	2	[425]	SELF     	0 0 -1	; "show"
	3	[425]	GETUPVAL 	2 1	; InfoMessage
	4	[425]	SELF     	2 2 -2	; "new"
	5	[425]	NEWTABLE 	4 0 1
	6	[425]	GETUPVAL 	5 2	; auto_save_help_text
	7	[425]	SETTABLE 	4 -3 5	; "text" -
	8	[425]	CALL     	2 3 0
	9	[425]	CALL     	0 0 1
	10	[426]	RETURN   	0 1

function <./frontend/ui/elements/common_settings_menu_table.lua:435,438> (12 instructions, 48 bytes at 0x7f992940bb70)
0 params, 3 slots, 0 upvalues, 1 local, 5 constants, 0 functions
	1	[436]	GETGLOBAL	0 -1	; G_reader_settings
	2	[436]	SELF     	0 0 -2	; "readSetting"
	3	[436]	LOADK    	2 -3	; "save_document"
	4	[436]	CALL     	0 3 2
	5	[437]	EQ       	1 0 -4	; - "prompt"
	6	[437]	JMP      	3	; to 10
	7	[437]	EQ       	1 0 -5	; - nil
	8	[437]	JMP      	1	; to 10
	9	[437]	LOADBOOL 	1 0 1
	10	[437]	LOADBOOL 	1 1 0
	11	[437]	RETURN   	1 2
	12	[438]	RETURN   	0 1

function <./frontend/ui/elements/common_settings_menu_table.lua:439,441> (5 instructions, 20 bytes at 0x7f992940efd0)
0 params, 3 slots, 0 upvalues, 0 locals, 3 constants, 0 functions
	1	[440]	GETGLOBAL	0 -1	; G_reader_settings
	2	[440]	SELF     	0 0 -2	; "delSetting"
	3	[440]	LOADK    	2 -3	; "save_document"
	4	[440]	CALL     	0 3 1
	5	[441]	RETURN   	0 1

function <./frontend/ui/elements/common_settings_menu_table.lua:445,448> (10 instructions, 40 bytes at 0x7f9929409310)
0 params, 3 slots, 0 upvalues, 0 locals, 4 constants, 0 functions
	1	[446]	GETGLOBAL	0 -1	; G_reader_settings
	2	[446]	SELF     	0 0 -2	; "readSetting"
	3	[446]	LOADK    	2 -3	; "save_document"
	4	[446]	CALL     	0 3 2
	5	[447]	EQ       	1 0 -4	; - "always"
	6	[447]	JMP      	1	; to 8
	7	[447]	LOADBOOL 	0 0 1
	8	[447]	LOADBOOL 	0 1 0
	9	[447]	RETURN   	0 2
	10	[448]	RETURN   	0 1

function <./frontend/ui/elements/common_settings_menu_table.lua:449,451> (6 instructions, 24 bytes at 0x7f9929409390)
0 params, 4 slots, 0 upvalues, 0 locals, 4 constants, 0 functions
	1	[450]	GETGLOBAL	0 -1	; G_reader_settings
	2	[450]	SELF     	0 0 -2	; "saveSetting"
	3	[450]	LOADK    	2 -3	; "save_document"
	4	[450]	LOADK    	3 -4	; "always"
	5	[450]	CALL     	0 4 1
	6	[451]	RETURN   	0 1

function <./frontend/ui/elements/common_settings_menu_table.lua:455,458> (10 instructions, 40 bytes at 0x7f992940d000)
0 params, 3 slots, 0 upvalues, 0 locals, 4 constants, 0 functions
	1	[456]	GETGLOBAL	0 -1	; G_reader_settings
	2	[456]	SELF     	0 0 -2	; "readSetting"
	3	[456]	LOADK    	2 -3	; "save_document"
	4	[456]	CALL     	0 3 2
	5	[457]	EQ       	1 0 -4	; - "disable"
	6	[457]	JMP      	1	; to 8
	7	[457]	LOADBOOL 	0 0 1
	8	[457]	LOADBOOL 	0 1 0
	9	[457]	RETURN   	0 2
	10	[458]	RETURN   	0 1

function <./frontend/ui/elements/common_settings_menu_table.lua:459,461> (6 instructions, 24 bytes at 0x7f992940d080)
0 params, 4 slots, 0 upvalues, 0 locals, 4 constants, 0 functions
	1	[460]	GETGLOBAL	0 -1	; G_reader_settings
	2	[460]	SELF     	0 0 -2	; "saveSetting"
	3	[460]	LOADK    	2 -3	; "save_document"
	4	[460]	LOADK    	3 -4	; "disable"
	5	[460]	CALL     	0 4 1
	6	[461]	RETURN   	0 1

function <./frontend/ui/elements/common_settings_menu_table.lua:470,473> (12 instructions, 48 bytes at 0x7f9929410220)
0 params, 3 slots, 0 upvalues, 1 local, 5 constants, 0 functions
	1	[471]	GETGLOBAL	0 -1	; G_reader_settings
	2	[471]	SELF     	0 0 -2	; "readSetting"
	3	[471]	LOADK    	2 -3	; "end_document_action"
	4	[471]	CALL     	0 3 2
	5	[472]	EQ       	1 0 -4	; - "pop-up"
	6	[472]	JMP      	3	; to 10
	7	[472]	EQ       	1 0 -5	; - nil
	8	[472]	JMP      	1	; to 10
	9	[472]	LOADBOOL 	1 0 1
	10	[472]	LOADBOOL 	1 1 0
	11	[472]	RETURN   	1 2
	12	[473]	RETURN   	0 1

function <./frontend/ui/elements/common_settings_menu_table.lua:474,476> (6 instructions, 24 bytes at 0x7f992940f650)
0 params, 4 slots, 0 upvalues, 0 locals, 4 constants, 0 functions
	1	[475]	GETGLOBAL	0 -1	; G_reader_settings
	2	[475]	SELF     	0 0 -2	; "saveSetting"
	3	[475]	LOADK    	2 -3	; "end_document_action"
	4	[475]	LOADK    	3 -4	; "pop-up"
	5	[475]	CALL     	0 4 1
	6	[476]	RETURN   	0 1

function <./frontend/ui/elements/common_settings_menu_table.lua:480,482> (10 instructions, 40 bytes at 0x7f992940e540)
0 params, 3 slots, 0 upvalues, 0 locals, 4 constants, 0 functions
	1	[481]	GETGLOBAL	0 -1	; G_reader_settings
	2	[481]	SELF     	0 0 -2	; "readSetting"
	3	[481]	LOADK    	2 -3	; "end_document_action"
	4	[481]	CALL     	0 3 2
	5	[481]	EQ       	1 0 -4	; - "nothing"
	6	[481]	JMP      	1	; to 8
	7	[481]	LOADBOOL 	0 0 1
	8	[481]	LOADBOOL 	0 1 0
	9	[481]	RETURN   	0 2
	10	[482]	RETURN   	0 1

function <./frontend/ui/elements/common_settings_menu_table.lua:483,485> (6 instructions, 24 bytes at 0x7f992940e8e0)
0 params, 4 slots, 0 upvalues, 0 locals, 4 constants, 0 functions
	1	[484]	GETGLOBAL	0 -1	; G_reader_settings
	2	[484]	SELF     	0 0 -2	; "saveSetting"
	3	[484]	LOADK    	2 -3	; "end_document_action"
	4	[484]	LOADK    	3 -4	; "nothing"
	5	[484]	CALL     	0 4 1
	6	[485]	RETURN   	0 1

function <./frontend/ui/elements/common_settings_menu_table.lua:489,491> (10 instructions, 40 bytes at 0x7f992940b9e0)
0 params, 3 slots, 0 upvalues, 0 locals, 4 constants, 0 functions
	1	[490]	GETGLOBAL	0 -1	; G_reader_settings
	2	[490]	SELF     	0 0 -2	; "readSetting"
	3	[490]	LOADK    	2 -3	; "end_document_action"
	4	[490]	CALL     	0 3 2
	5	[490]	EQ       	1 0 -4	; - "book_status"
	6	[490]	JMP      	1	; to 8
	7	[490]	LOADBOOL 	0 0 1
	8	[490]	LOADBOOL 	0 1 0
	9	[490]	RETURN   	0 2
	10	[491]	RETURN   	0 1

function <./frontend/ui/elements/common_settings_menu_table.lua:492,494> (6 instructions, 24 bytes at 0x7f9929410910)
0 params, 4 slots, 0 upvalues, 0 locals, 4 constants, 0 functions
	1	[493]	GETGLOBAL	0 -1	; G_reader_settings
	2	[493]	SELF     	0 0 -2	; "saveSetting"
	3	[493]	LOADK    	2 -3	; "end_document_action"
	4	[493]	LOADK    	3 -4	; "book_status"
	5	[493]	CALL     	0 4 1
	6	[494]	RETURN   	0 1

function <./frontend/ui/elements/common_settings_menu_table.lua:498,500> (10 instructions, 40 bytes at 0x7f992940cb70)
0 params, 3 slots, 0 upvalues, 0 locals, 4 constants, 0 functions
	1	[499]	GETGLOBAL	0 -1	; G_reader_settings
	2	[499]	SELF     	0 0 -2	; "readSetting"
	3	[499]	LOADK    	2 -3	; "end_document_action"
	4	[499]	CALL     	0 3 2
	5	[499]	EQ       	1 0 -4	; - "delete_file"
	6	[499]	JMP      	1	; to 8
	7	[499]	LOADBOOL 	0 0 1
	8	[499]	LOADBOOL 	0 1 0
	9	[499]	RETURN   	0 2
	10	[500]	RETURN   	0 1

function <./frontend/ui/elements/common_settings_menu_table.lua:501,503> (6 instructions, 24 bytes at 0x7f992940e160)
0 params, 4 slots, 0 upvalues, 0 locals, 4 constants, 0 functions
	1	[502]	GETGLOBAL	0 -1	; G_reader_settings
	2	[502]	SELF     	0 0 -2	; "saveSetting"
	3	[502]	LOADK    	2 -3	; "end_document_action"
	4	[502]	LOADK    	3 -4	; "delete_file"
	5	[502]	CALL     	0 4 1
	6	[503]	RETURN   	0 1

function <./frontend/ui/elements/common_settings_menu_table.lua:507,510> (10 instructions, 40 bytes at 0x7f992940e280)
0 params, 3 slots, 0 upvalues, 0 locals, 4 constants, 0 functions
	1	[508]	GETGLOBAL	0 -1	; G_reader_settings
	2	[508]	SELF     	0 0 -2	; "readSetting"
	3	[508]	LOADK    	2 -3	; "collate"
	4	[508]	CALL     	0 3 2
	5	[509]	EQ       	0 0 -4	; - "access"
	6	[509]	JMP      	1	; to 8
	7	[509]	LOADBOOL 	0 0 1
	8	[509]	LOADBOOL 	0 1 0
	9	[509]	RETURN   	0 2
	10	[510]	RETURN   	0 1

function <./frontend/ui/elements/common_settings_menu_table.lua:511,513> (10 instructions, 40 bytes at 0x7f9929410e50)
0 params, 3 slots, 0 upvalues, 0 locals, 4 constants, 0 functions
	1	[512]	GETGLOBAL	0 -1	; G_reader_settings
	2	[512]	SELF     	0 0 -2	; "readSetting"
	3	[512]	LOADK    	2 -3	; "end_document_action"
	4	[512]	CALL     	0 3 2
	5	[512]	EQ       	1 0 -4	; - "next_file"
	6	[512]	JMP      	1	; to 8
	7	[512]	LOADBOOL 	0 0 1
	8	[512]	LOADBOOL 	0 1 0
	9	[512]	RETURN   	0 2
	10	[513]	RETURN   	0 1

function <./frontend/ui/elements/common_settings_menu_table.lua:514,516> (6 instructions, 24 bytes at 0x7f9929411170)
0 params, 4 slots, 0 upvalues, 0 locals, 4 constants, 0 functions
	1	[515]	GETGLOBAL	0 -1	; G_reader_settings
	2	[515]	SELF     	0 0 -2	; "saveSetting"
	3	[515]	LOADK    	2 -3	; "end_document_action"
	4	[515]	LOADK    	3 -4	; "next_file"
	5	[515]	CALL     	0 4 1
	6	[516]	RETURN   	0 1

function <./frontend/ui/elements/common_settings_menu_table.lua:520,522> (10 instructions, 40 bytes at 0x7f9929411260)
0 params, 3 slots, 0 upvalues, 0 locals, 4 constants, 0 functions
	1	[521]	GETGLOBAL	0 -1	; G_reader_settings
	2	[521]	SELF     	0 0 -2	; "readSetting"
	3	[521]	LOADK    	2 -3	; "end_document_action"
	4	[521]	CALL     	0 3 2
	5	[521]	EQ       	1 0 -4	; - "goto_beginning"
	6	[521]	JMP      	1	; to 8
	7	[521]	LOADBOOL 	0 0 1
	8	[521]	LOADBOOL 	0 1 0
	9	[521]	RETURN   	0 2
	10	[522]	RETURN   	0 1

function <./frontend/ui/elements/common_settings_menu_table.lua:523,525> (6 instructions, 24 bytes at 0x7f9929411700)
0 params, 4 slots, 0 upvalues, 0 locals, 4 constants, 0 functions
	1	[524]	GETGLOBAL	0 -1	; G_reader_settings
	2	[524]	SELF     	0 0 -2	; "saveSetting"
	3	[524]	LOADK    	2 -3	; "end_document_action"
	4	[524]	LOADK    	3 -4	; "goto_beginning"
	5	[524]	CALL     	0 4 1
	6	[525]	RETURN   	0 1

function <./frontend/ui/elements/common_settings_menu_table.lua:529,531> (10 instructions, 40 bytes at 0x7f99294117f0)
0 params, 3 slots, 0 upvalues, 0 locals, 4 constants, 0 functions
	1	[530]	GETGLOBAL	0 -1	; G_reader_settings
	2	[530]	SELF     	0 0 -2	; "readSetting"
	3	[530]	LOADK    	2 -3	; "end_document_action"
	4	[530]	CALL     	0 3 2
	5	[530]	EQ       	1 0 -4	; - "file_browser"
	6	[530]	JMP      	1	; to 8
	7	[530]	LOADBOOL 	0 0 1
	8	[530]	LOADBOOL 	0 1 0
	9	[530]	RETURN   	0 2
	10	[531]	RETURN   	0 1

function <./frontend/ui/elements/common_settings_menu_table.lua:532,534> (6 instructions, 24 bytes at 0x7f9929411c90)
0 params, 4 slots, 0 upvalues, 0 locals, 4 constants, 0 functions
	1	[533]	GETGLOBAL	0 -1	; G_reader_settings
	2	[533]	SELF     	0 0 -2	; "saveSetting"
	3	[533]	LOADK    	2 -3	; "end_document_action"
	4	[533]	LOADK    	3 -4	; "file_browser"
	5	[533]	CALL     	0 4 1
	6	[534]	RETURN   	0 1

function <./frontend/ui/elements/common_settings_menu_table.lua:538,540> (10 instructions, 40 bytes at 0x7f9929411dc0)
0 params, 3 slots, 0 upvalues, 0 locals, 4 constants, 0 functions
	1	[539]	GETGLOBAL	0 -1	; G_reader_settings
	2	[539]	SELF     	0 0 -2	; "readSetting"
	3	[539]	LOADK    	2 -3	; "end_document_action"
	4	[539]	CALL     	0 3 2
	5	[539]	EQ       	1 0 -4	; - "mark_read"
	6	[539]	JMP      	1	; to 8
	7	[539]	LOADBOOL 	0 0 1
	8	[539]	LOADBOOL 	0 1 0
	9	[539]	RETURN   	0 2
	10	[540]	RETURN   	0 1

function <./frontend/ui/elements/common_settings_menu_table.lua:541,543> (6 instructions, 24 bytes at 0x7f9929412260)
0 params, 4 slots, 0 upvalues, 0 locals, 4 constants, 0 functions
	1	[542]	GETGLOBAL	0 -1	; G_reader_settings
	2	[542]	SELF     	0 0 -2	; "saveSetting"
	3	[542]	LOADK    	2 -3	; "end_document_action"
	4	[542]	LOADK    	3 -4	; "mark_read"
	5	[542]	CALL     	0 4 1
	6	[543]	RETURN   	0 1

function <./frontend/ui/elements/common_settings_menu_table.lua:547,549> (10 instructions, 40 bytes at 0x7f9929412390)
0 params, 3 slots, 0 upvalues, 0 locals, 4 constants, 0 functions
	1	[548]	GETGLOBAL	0 -1	; G_reader_settings
	2	[548]	SELF     	0 0 -2	; "readSetting"
	3	[548]	LOADK    	2 -3	; "end_document_action"
	4	[548]	CALL     	0 3 2
	5	[548]	EQ       	1 0 -4	; - "book_status_file_browser"
	6	[548]	JMP      	1	; to 8
	7	[548]	LOADBOOL 	0 0 1
	8	[548]	LOADBOOL 	0 1 0
	9	[548]	RETURN   	0 2
	10	[549]	RETURN   	0 1

function <./frontend/ui/elements/common_settings_menu_table.lua:550,552> (6 instructions, 24 bytes at 0x7f992940e710)
0 params, 4 slots, 0 upvalues, 0 locals, 4 constants, 0 functions
	1	[551]	GETGLOBAL	0 -1	; G_reader_settings
	2	[551]	SELF     	0 0 -2	; "saveSetting"
	3	[551]	LOADK    	2 -3	; "end_document_action"
	4	[551]	LOADK    	3 -4	; "book_status_file_browser"
	5	[551]	CALL     	0 4 1
	6	[552]	RETURN   	0 1

function <./frontend/ui/elements/common_settings_menu_table.lua:561,563> (6 instructions, 24 bytes at 0x7f9929412780)
0 params, 3 slots, 0 upvalues, 0 locals, 3 constants, 0 functions
	1	[562]	GETGLOBAL	0 -1	; G_reader_settings
	2	[562]	SELF     	0 0 -2	; "isTrue"
	3	[562]	LOADK    	2 -3	; "highlight_action_on_single_word"
	4	[562]	TAILCALL 	0 3 0
	5	[562]	RETURN   	0 0
	6	[563]	RETURN   	0 1

function <./frontend/ui/elements/common_settings_menu_table.lua:564,566> (6 instructions, 24 bytes at 0x7f9929412a40)
0 params, 4 slots, 0 upvalues, 0 locals, 3 constants, 0 functions
	1	[565]	GETGLOBAL	0 -1	; G_reader_settings
	2	[565]	SELF     	0 0 -2	; "flipNilOrFalse"
	3	[565]	LOADK    	2 -3	; "highlight_action_on_single_word"
	4	[565]	LOADNIL  	3 3
	5	[565]	CALL     	0 4 1
	6	[566]	RETURN   	0 1

function <./frontend/ui/elements/common_settings_menu_table.lua:571,573> (6 instructions, 24 bytes at 0x7f9929412d30)
0 params, 3 slots, 0 upvalues, 0 locals, 3 constants, 0 functions
	1	[572]	GETGLOBAL	0 -1	; G_reader_settings
	2	[572]	SELF     	0 0 -2	; "nilOrFalse"
	3	[572]	LOADK    	2 -3	; "default_highlight_action"
	4	[572]	TAILCALL 	0 3 0
	5	[572]	RETURN   	0 0
	6	[573]	RETURN   	0 1

function <./frontend/ui/elements/common_settings_menu_table.lua:574,576> (6 instructions, 24 bytes at 0x7f9929413000)
0 params, 4 slots, 0 upvalues, 0 locals, 3 constants, 0 functions
	1	[575]	GETGLOBAL	0 -1	; G_reader_settings
	2	[575]	SELF     	0 0 -2	; "saveSetting"
	3	[575]	LOADK    	2 -3	; "default_highlight_action"
	4	[575]	LOADNIL  	3 3
	5	[575]	CALL     	0 4 1
	6	[576]	RETURN   	0 1

function <./frontend/ui/elements/common_settings_menu_table.lua:580,582> (10 instructions, 40 bytes at 0x7f9929413300)
0 params, 3 slots, 0 upvalues, 0 locals, 4 constants, 0 functions
	1	[581]	GETGLOBAL	0 -1	; G_reader_settings
	2	[581]	SELF     	0 0 -2	; "readSetting"
	3	[581]	LOADK    	2 -3	; "default_highlight_action"
	4	[581]	CALL     	0 3 2
	5	[581]	EQ       	1 0 -4	; - "highlight"
	6	[581]	JMP      	1	; to 8
	7	[581]	LOADBOOL 	0 0 1
	8	[581]	LOADBOOL 	0 1 0
	9	[581]	RETURN   	0 2
	10	[582]	RETURN   	0 1

function <./frontend/ui/elements/common_settings_menu_table.lua:583,585> (6 instructions, 24 bytes at 0x7f99294137a0)
0 params, 4 slots, 0 upvalues, 0 locals, 4 constants, 0 functions
	1	[584]	GETGLOBAL	0 -1	; G_reader_settings
	2	[584]	SELF     	0 0 -2	; "saveSetting"
	3	[584]	LOADK    	2 -3	; "default_highlight_action"
	4	[584]	LOADK    	3 -4	; "highlight"
	5	[584]	CALL     	0 4 1
	6	[585]	RETURN   	0 1

function <./frontend/ui/elements/common_settings_menu_table.lua:589,591> (10 instructions, 40 bytes at 0x7f99294138d0)
0 params, 3 slots, 0 upvalues, 0 locals, 4 constants, 0 functions
	1	[590]	GETGLOBAL	0 -1	; G_reader_settings
	2	[590]	SELF     	0 0 -2	; "readSetting"
	3	[590]	LOADK    	2 -3	; "default_highlight_action"
	4	[590]	CALL     	0 3 2
	5	[590]	EQ       	1 0 -4	; - "translate"
	6	[590]	JMP      	1	; to 8
	7	[590]	LOADBOOL 	0 0 1
	8	[590]	LOADBOOL 	0 1 0
	9	[590]	RETURN   	0 2
	10	[591]	RETURN   	0 1

function <./frontend/ui/elements/common_settings_menu_table.lua:592,594> (6 instructions, 24 bytes at 0x7f9929413d70)
0 params, 4 slots, 0 upvalues, 0 locals, 4 constants, 0 functions
	1	[593]	GETGLOBAL	0 -1	; G_reader_settings
	2	[593]	SELF     	0 0 -2	; "saveSetting"
	3	[593]	LOADK    	2 -3	; "default_highlight_action"
	4	[593]	LOADK    	3 -4	; "translate"
	5	[593]	CALL     	0 4 1
	6	[594]	RETURN   	0 1

function <./frontend/ui/elements/common_settings_menu_table.lua:598,600> (10 instructions, 40 bytes at 0x7f9929413e60)
0 params, 3 slots, 0 upvalues, 0 locals, 4 constants, 0 functions
	1	[599]	GETGLOBAL	0 -1	; G_reader_settings
	2	[599]	SELF     	0 0 -2	; "readSetting"
	3	[599]	LOADK    	2 -3	; "default_highlight_action"
	4	[599]	CALL     	0 3 2
	5	[599]	EQ       	1 0 -4	; - "wikipedia"
	6	[599]	JMP      	1	; to 8
	7	[599]	LOADBOOL 	0 0 1
	8	[599]	LOADBOOL 	0 1 0
	9	[599]	RETURN   	0 2
	10	[600]	RETURN   	0 1

function <./frontend/ui/elements/common_settings_menu_table.lua:601,603> (6 instructions, 24 bytes at 0x7f9929414300)
0 params, 4 slots, 0 upvalues, 0 locals, 4 constants, 0 functions
	1	[602]	GETGLOBAL	0 -1	; G_reader_settings
	2	[602]	SELF     	0 0 -2	; "saveSetting"
	3	[602]	LOADK    	2 -3	; "default_highlight_action"
	4	[602]	LOADK    	3 -4	; "wikipedia"
	5	[602]	CALL     	0 4 1
	6	[603]	RETURN   	0 1

function <./frontend/ui/elements/common_settings_menu_table.lua:607,609> (10 instructions, 40 bytes at 0x7f9929414430)
0 params, 3 slots, 0 upvalues, 0 locals, 4 constants, 0 functions
	1	[608]	GETGLOBAL	0 -1	; G_reader_settings
	2	[608]	SELF     	0 0 -2	; "readSetting"
	3	[608]	LOADK    	2 -3	; "default_highlight_action"
	4	[608]	CALL     	0 3 2
	5	[608]	EQ       	1 0 -4	; - "dictionary"
	6	[608]	JMP      	1	; to 8
	7	[608]	LOADBOOL 	0 0 1
	8	[608]	LOADBOOL 	0 1 0
	9	[608]	RETURN   	0 2
	10	[609]	RETURN   	0 1

function <./frontend/ui/elements/common_settings_menu_table.lua:610,612> (6 instructions, 24 bytes at 0x7f99294148d0)
0 params, 4 slots, 0 upvalues, 0 locals, 4 constants, 0 functions
	1	[611]	GETGLOBAL	0 -1	; G_reader_settings
	2	[611]	SELF     	0 0 -2	; "saveSetting"
	3	[611]	LOADK    	2 -3	; "default_highlight_action"
	4	[611]	LOADK    	3 -4	; "dictionary"
	5	[611]	CALL     	0 4 1
	6	[612]	RETURN   	0 1

function <./frontend/ui/elements/common_settings_menu_table.lua:616,618> (10 instructions, 40 bytes at 0x7f99294149c0)
0 params, 3 slots, 0 upvalues, 0 locals, 4 constants, 0 functions
	1	[617]	GETGLOBAL	0 -1	; G_reader_settings
	2	[617]	SELF     	0 0 -2	; "readSetting"
	3	[617]	LOADK    	2 -3	; "default_highlight_action"
	4	[617]	CALL     	0 3 2
	5	[617]	EQ       	1 0 -4	; - "search"
	6	[617]	JMP      	1	; to 8
	7	[617]	LOADBOOL 	0 0 1
	8	[617]	LOADBOOL 	0 1 0
	9	[617]	RETURN   	0 2
	10	[618]	RETURN   	0 1

function <./frontend/ui/elements/common_settings_menu_table.lua:619,621> (6 instructions, 24 bytes at 0x7f9929414e60)
0 params, 4 slots, 0 upvalues, 0 locals, 4 constants, 0 functions
	1	[620]	GETGLOBAL	0 -1	; G_reader_settings
	2	[620]	SELF     	0 0 -2	; "saveSetting"
	3	[620]	LOADK    	2 -3	; "default_highlight_action"
	4	[620]	LOADK    	3 -4	; "search"
	5	[620]	CALL     	0 4 1
	6	[621]	RETURN   	0 1

function <./frontend/ui/elements/common_settings_menu_table.lua:631,634> (6 instructions, 24 bytes at 0x7f99294151c0)
0 params, 3 slots, 0 upvalues, 1 local, 3 constants, 0 functions
	1	[632]	GETGLOBAL	0 -1	; require
	2	[632]	LOADK    	1 -2	; "ui/widget/screenshoter"
	3	[632]	CALL     	0 2 2
	4	[633]	SELF     	1 0 -3	; "chooseFolder"
	5	[633]	CALL     	1 2 1
	6	[634]	RETURN   	0 1
