-- BYTECODE -- configurable.lua:3-8
0001    IST          1
0002    JMP      2 => 0004
0003    TNEW     1   0
0004 => GGET     2   0      ; "setmetatable"
0005    MOV      3   1
0006    MOV      4   0
0007    CALL     2   1   3
0008    TSETS    0   0   1  ; "__index"
0009    RET1     1   2

-- BYTECODE -- configurable.lua:10-17
0001    GGET     1   0      ; "pairs"
0002    MOV      2   0
0003    CALL     1   4   2
0004    ISNEXT   4 => 0014
0005 => GGET     6   1      ; "type"
0006    MOV      7   5
0007    CALL     6   2   2
0008    ISEQS    6   2      ; "number"
0009    JMP      7 => 0012
0010    ISNES    6   3      ; "string"
0011    JMP      7 => 0014
0012 => KPRI     7   0
0013    TSETV    7   0   4
0014 => ITERN    4   3   3
0015    ITERL    4 => 0005
0016    RET0     0   1

-- BYTECODE -- configurable.lua:19-28
0001    KSTR     2   0      ; ""
0002    GGET     3   1      ; "pairs"
0003    MOV      4   0
0004    CALL     3   4   2
0005    ISNEXT   6 => 0017
0006 => GGET     8   2      ; "type"
0007    MOV      9   7
0008    CALL     8   2   2
0009    ISEQS    8   3      ; "number"
0010    JMP      9 => 0013
0011    ISNES    8   4      ; "string"
0012    JMP      9 => 0017
0013 => MOV      9   2
0014    MOV     10   1
0015    MOV     11   7
0016    CAT      2   9  11
0017 => ITERN    6   3   3
0018    ITERL    6 => 0006
0019    RET1     2   2

-- BYTECODE -- configurable.lua:30-46
0001    MOV      3   0
0002    TGETS    2   0   0  ; "reset"
0003    CALL     2   1   2
0004    TGETS    2   1   1  ; "prefix"
0005    KSTR     3   2      ; "_"
0006    CAT      2   2   3
0007    KSHORT   3   1
0008    LEN      4   1
0009    KSHORT   5   1
0010    FORI     3 => 0040
0011 => TGETV    7   1   6
0012    TGETS    7   7   3  ; "options"
0013    KSHORT   8   1
0014    LEN      9   7
0015    KSHORT  10   1
0016    FORI     8 => 0039
0017 => TGETV   12   7  11
0018    TGETS   12  12   4  ; "name"
0019    MOV     13   2
0020    MOV     14  12
0021    CAT     13  13  14
0022    GGET    14   5      ; "G_reader_settings"
0023    MOV     15  14
0024    TGETS   14  14   6  ; "readSetting"
0025    MOV     16  13
0026    CALL    14   2   3
0027    ISTC    15  14
0028    JMP     15 => 0031
0029    TGETV   15   7  11
0030    TGETS   15  15   7  ; "default_value"
0031 => TSETV   15   0  12
0032    TGETV   15   0  12
0033    IST         15
0034    JMP     15 => 0038
0035    TGETV   15   7  11
0036    TGETS   15  15   8  ; "default_arg"
0037    TSETV   15   0  12
0038 => FORL     8 => 0017
0039 => FORL     3 => 0011
0040 => RET0     0   1

-- BYTECODE -- configurable.lua:48-59
0001    GGET     3   0      ; "pairs"
0002    MOV      4   0
0003    CALL     3   4   2
0004    ISNEXT   6 => 0023
0005 => GGET     8   1      ; "type"
0006    MOV      9   7
0007    CALL     8   2   2
0008    ISEQS    8   2      ; "number"
0009    JMP      9 => 0014
0010    ISEQS    8   3      ; "string"
0011    JMP      9 => 0014
0012    ISNES    8   4      ; "table"
0013    JMP      9 => 0023
0014 => MOV     10   1
0015    TGETS    9   1   5  ; "readSetting"
0016    MOV     11   2
0017    MOV     12   6
0018    CAT     11  11  12
0019    CALL     9   2   3
0020    ISEQP    9   0
0021    JMP     10 => 0023
0022    TSETV    9   0   6
0023 => ITERN    6   3   3
0024    ITERL    6 => 0005
0025    RET0     0   1

-- BYTECODE -- configurable.lua:61-69
0001    GGET     3   0      ; "pairs"
0002    MOV      4   0
0003    CALL     3   4   2
0004    ISNEXT   6 => 0021
0005 => GGET     8   1      ; "type"
0006    MOV      9   7
0007    CALL     8   2   2
0008    ISEQS    8   2      ; "number"
0009    JMP      9 => 0014
0010    ISEQS    8   3      ; "string"
0011    JMP      9 => 0014
0012    ISNES    8   4      ; "table"
0013    JMP      9 => 0021
0014 => MOV     10   1
0015    TGETS    9   1   5  ; "saveSetting"
0016    MOV     11   2
0017    MOV     12   6
0018    CAT     11  11  12
0019    MOV     12   7
0020    CALL     9   1   4
0021 => ITERN    6   3   3
0022    ITERL    6 => 0005
0023    RET0     0   1

-- BYTECODE -- configurable.lua:0-72
0001    TNEW     0   0
0002    FNEW     1   1      ; configurable.lua:3
0003    TSETS    1   0   0  ; "new"
0004    FNEW     1   3      ; configurable.lua:10
0005    TSETS    1   0   2  ; "reset"
0006    FNEW     1   5      ; configurable.lua:19
0007    TSETS    1   0   4  ; "hash"
0008    FNEW     1   7      ; configurable.lua:30
0009    TSETS    1   0   6  ; "loadDefaults"
0010    FNEW     1   9      ; configurable.lua:48
0011    TSETS    1   0   8  ; "loadSettings"
0012    FNEW     1  11      ; configurable.lua:61
0013    TSETS    1   0  10  ; "saveSettings"
0014    UCLO     0 => 0015
0015 => RET1     0   2

