
main <./frontend/ui/widget/configdialog.lua:0,0> (272 instructions, 1088 bytes at 0x7f91024068d0)
0+ params, 41 slots, 0 upvalues, 39 locals, 68 constants, 32 functions
	1	[1]	GETGLOBAL	0 -1	; require
	2	[1]	LOADK    	1 -2	; "ui/widget/button"
	3	[1]	CALL     	0 2 2
	4	[2]	GETGLOBAL	1 -1	; require
	5	[2]	LOADK    	2 -3	; "ui/widget/buttonprogresswidget"
	6	[2]	CALL     	1 2 2
	7	[3]	GETGLOBAL	2 -1	; require
	8	[3]	LOADK    	3 -4	; "ffi/blitbuffer"
	9	[3]	CALL     	2 2 2
	10	[4]	GETGLOBAL	3 -1	; require
	11	[4]	LOADK    	4 -5	; "ui/widget/container/bottomcontainer"
	12	[4]	CALL     	3 2 2
	13	[5]	GETGLOBAL	4 -1	; require
	14	[5]	LOADK    	5 -6	; "ui/widget/container/centercontainer"
	15	[5]	CALL     	4 2 2
	16	[6]	GETGLOBAL	5 -1	; require
	17	[6]	LOADK    	6 -7	; "ui/widget/confirmbox"
	18	[6]	CALL     	5 2 2
	19	[7]	GETGLOBAL	6 -1	; require
	20	[7]	LOADK    	7 -8	; "device"
	21	[7]	CALL     	6 2 2
	22	[8]	GETGLOBAL	7 -1	; require
	23	[8]	LOADK    	8 -9	; "ui/event"
	24	[8]	CALL     	7 2 2
	25	[9]	GETGLOBAL	8 -1	; require
	26	[9]	LOADK    	9 -10	; "ui/widget/fixedtextwidget"
	27	[9]	CALL     	8 2 2
	28	[10]	GETGLOBAL	9 -1	; require
	29	[10]	LOADK    	10 -11	; "ui/widget/focusmanager"
	30	[10]	CALL     	9 2 2
	31	[11]	GETGLOBAL	10 -1	; require
	32	[11]	LOADK    	11 -12	; "ui/font"
	33	[11]	CALL     	10 2 2
	34	[12]	GETGLOBAL	11 -1	; require
	35	[12]	LOADK    	12 -13	; "ui/widget/container/framecontainer"
	36	[12]	CALL     	11 2 2
	37	[13]	GETGLOBAL	12 -1	; require
	38	[13]	LOADK    	13 -14	; "ui/geometry"
	39	[13]	CALL     	12 2 2
	40	[14]	GETGLOBAL	13 -1	; require
	41	[14]	LOADK    	14 -15	; "ui/gesturerange"
	42	[14]	CALL     	13 2 2
	43	[15]	GETGLOBAL	14 -1	; require
	44	[15]	LOADK    	15 -16	; "ui/widget/horizontalgroup"
	45	[15]	CALL     	14 2 2
	46	[16]	GETGLOBAL	15 -1	; require
	47	[16]	LOADK    	16 -17	; "ui/widget/horizontalspan"
	48	[16]	CALL     	15 2 2
	49	[17]	GETGLOBAL	16 -1	; require
	50	[17]	LOADK    	17 -18	; "ui/widget/iconbutton"
	51	[17]	CALL     	16 2 2
	52	[18]	GETGLOBAL	17 -1	; require
	53	[18]	LOADK    	18 -19	; "ui/widget/imagewidget"
	54	[18]	CALL     	17 2 2
	55	[19]	GETGLOBAL	18 -1	; require
	56	[19]	LOADK    	19 -20	; "ui/widget/container/inputcontainer"
	57	[19]	CALL     	18 2 2
	58	[20]	GETGLOBAL	19 -1	; require
	59	[20]	LOADK    	20 -21	; "ui/widget/linewidget"
	60	[20]	CALL     	19 2 2
	61	[21]	GETGLOBAL	20 -1	; require
	62	[21]	LOADK    	21 -22	; "ui/widget/container/rightcontainer"
	63	[21]	CALL     	20 2 2
	64	[22]	GETGLOBAL	21 -1	; require
	65	[22]	LOADK    	22 -23	; "ui/size"
	66	[22]	CALL     	21 2 2
	67	[23]	GETGLOBAL	22 -1	; require
	68	[23]	LOADK    	23 -24	; "ui/widget/textwidget"
	69	[23]	CALL     	22 2 2
	70	[24]	GETGLOBAL	23 -1	; require
	71	[24]	LOADK    	24 -25	; "ui/widget/toggleswitch"
	72	[24]	CALL     	23 2 2
	73	[25]	GETGLOBAL	24 -1	; require
	74	[25]	LOADK    	25 -26	; "ui/uimanager"
	75	[25]	CALL     	24 2 2
	76	[26]	GETGLOBAL	25 -1	; require
	77	[26]	LOADK    	26 -27	; "ui/widget/container/underlinecontainer"
	78	[26]	CALL     	25 2 2
	79	[27]	GETGLOBAL	26 -1	; require
	80	[27]	LOADK    	27 -28	; "ui/widget/verticalgroup"
	81	[27]	CALL     	26 2 2
	82	[28]	GETGLOBAL	27 -1	; require
	83	[28]	LOADK    	28 -29	; "ui/widget/verticalspan"
	84	[28]	CALL     	27 2 2
	85	[29]	GETGLOBAL	28 -1	; require
	86	[29]	LOADK    	29 -30	; "dump"
	87	[29]	CALL     	28 2 2
	88	[30]	GETGLOBAL	29 -1	; require
	89	[30]	LOADK    	30 -31	; "logger"
	90	[30]	CALL     	29 2 2
	91	[31]	GETGLOBAL	30 -1	; require
	92	[31]	LOADK    	31 -32	; "gettext"
	93	[31]	CALL     	30 2 2
	94	[32]	GETTABLE 	31 6 -33	; "screen"
	95	[33]	GETGLOBAL	32 -1	; require
	96	[33]	LOADK    	33 -34	; "ffi/util"
	97	[33]	CALL     	32 2 2
	98	[33]	GETTABLE 	32 32 -35	; "template"
	99	[35]	SELF     	33 18 -36	; "new"
	100	[35]	NEWTABLE 	35 0 0
	101	[35]	CALL     	33 3 2
	102	[72]	CLOSURE  	34 0	; 0x7f9102407080
	103	[72]	MOVE     	0 25
	104	[72]	MOVE     	0 11
	105	[72]	MOVE     	0 6
	106	[72]	MOVE     	0 13
	107	[37]	SETTABLE 	33 -37 34	; "init" -
	108	[76]	CLOSURE  	34 1	; 0x7f91024067c0
	109	[76]	MOVE     	0 2
	110	[74]	SETTABLE 	33 -38 34	; "onFocus" -
	111	[80]	CLOSURE  	34 2	; 0x7f9102408280
	112	[80]	MOVE     	0 2
	113	[78]	SETTABLE 	33 -39 34	; "onUnfocus" -
	114	[95]	CLOSURE  	34 3	; 0x7f91024085d0
	115	[95]	MOVE     	0 2
	116	[95]	MOVE     	0 24
	117	[82]	SETTABLE 	33 -40 34	; "onTapSelect" -
	118	[103]	CLOSURE  	34 4	; 0x7f9102408ac0
	119	[97]	SETTABLE 	33 -41 34	; "onHoldSelect" -
	120	[105]	SELF     	34 18 -36	; "new"
	121	[105]	NEWTABLE 	36 0 0
	122	[105]	CALL     	34 3 2
	123	[141]	CLOSURE  	35 5	; 0x7f91024097a0
	124	[141]	MOVE     	0 25
	125	[141]	MOVE     	0 11
	126	[141]	MOVE     	0 6
	127	[141]	MOVE     	0 13
	128	[107]	SETTABLE 	34 -37 35	; "init" -
	129	[145]	CLOSURE  	35 6	; 0x7f9102409a70
	130	[143]	SETTABLE 	34 -38 35	; "onFocus" -
	131	[149]	CLOSURE  	35 7	; 0x7f9102409d30
	132	[147]	SETTABLE 	34 -39 35	; "onUnfocus" -
	133	[166]	CLOSURE  	35 8	; 0x7f91024099c0
	134	[166]	MOVE     	0 2
	135	[166]	MOVE     	0 24
	136	[151]	SETTABLE 	34 -40 35	; "onTapSelect" -
	137	[172]	CLOSURE  	35 9	; 0x7f91024078b0
	138	[168]	SETTABLE 	34 -41 35	; "onHoldSelect" -
	139	[174]	SELF     	35 4 -36	; "new"
	140	[174]	NEWTABLE 	37 0 0
	141	[174]	CALL     	35 3 2
	142	[619]	CLOSURE  	36 10	; 0x7f910240a660
	143	[619]	MOVE     	0 21
	144	[619]	MOVE     	0 10
	145	[619]	MOVE     	0 22
	146	[619]	MOVE     	0 31
	147	[619]	MOVE     	0 26
	148	[619]	MOVE     	0 27
	149	[619]	MOVE     	0 14
	150	[619]	MOVE     	0 20
	151	[619]	MOVE     	0 12
	152	[619]	MOVE     	0 0
	153	[619]	MOVE     	0 4
	154	[619]	MOVE     	0 29
	155	[619]	MOVE     	0 33
	156	[619]	MOVE     	0 8
	157	[619]	MOVE     	0 2
	158	[619]	MOVE     	0 34
	159	[619]	MOVE     	0 17
	160	[619]	MOVE     	0 23
	161	[619]	MOVE     	0 1
	162	[619]	MOVE     	0 24
	163	[176]	SETTABLE 	35 -37 36	; "init" -
	164	[634]	CLOSURE  	36 11	; 0x7f910240cc60
	165	[621]	SETTABLE 	35 -42 36	; "_itemGroupToLayoutLine" -
	166	[636]	SELF     	36 11 -36	; "new"
	167	[636]	NEWTABLE 	38 0 2
	168	[637]	GETTABLE 	39 2 -44	; "COLOR_WHITE"
	169	[637]	SETTABLE 	38 -43 39	; "background" -
	170	[638]	SETTABLE 	38 -45 -46	; "bordersize" 0
	171	[636]	CALL     	36 3 2
	172	[652]	CLOSURE  	37 12	; 0x7f910240d550
	173	[652]	MOVE     	0 35
	174	[641]	SETTABLE 	36 -37 37	; "init" -
	175	[654]	SELF     	37 11 -36	; "new"
	176	[654]	NEWTABLE 	39 0 3
	177	[655]	SETTABLE 	39 -45 -46	; "bordersize" 0
	178	[656]	SETTABLE 	39 -47 -46	; "padding" 0
	179	[657]	GETTABLE 	40 2 -44	; "COLOR_WHITE"
	180	[657]	SETTABLE 	39 -43 40	; "background" -
	181	[654]	CALL     	37 3 2
	182	[768]	CLOSURE  	38 13	; 0x7f910240d8c0
	183	[768]	MOVE     	0 21
	184	[768]	MOVE     	0 31
	185	[768]	MOVE     	0 16
	186	[768]	MOVE     	0 7
	187	[768]	MOVE     	0 19
	188	[768]	MOVE     	0 2
	189	[768]	MOVE     	0 12
	190	[768]	MOVE     	0 15
	191	[768]	MOVE     	0 14
	192	[768]	MOVE     	0 26
	193	[659]	SETTABLE 	37 -37 38	; "init" -
	194	[789]	SELF     	38 9 -36	; "new"
	195	[789]	NEWTABLE 	40 0 2
	196	[791]	SETTABLE 	40 -48 -49	; "panel_index" 1
	197	[792]	SETTABLE 	40 -50 -51	; "is_fresh" true
	198	[789]	CALL     	38 3 2
	199	[832]	CLOSURE  	39 14	; 0x7f910240e0e0
	200	[832]	MOVE     	0 6
	201	[832]	MOVE     	0 13
	202	[832]	MOVE     	0 12
	203	[832]	MOVE     	0 31
	204	[795]	SETTABLE 	38 -37 39	; "init" -
	205	[836]	CLOSURE  	39 15	; 0x7f910240e1a0
	206	[834]	SETTABLE 	38 -52 39	; "updateConfigPanel" -
	207	[863]	CLOSURE  	39 16	; 0x7f910240ea70
	208	[863]	MOVE     	0 37
	209	[863]	MOVE     	0 36
	210	[863]	MOVE     	0 11
	211	[863]	MOVE     	0 2
	212	[863]	MOVE     	0 26
	213	[863]	MOVE     	0 3
	214	[863]	MOVE     	0 31
	215	[838]	SETTABLE 	38 -53 39	; "update" -
	216	[870]	CLOSURE  	39 17	; 0x7f91024079f0
	217	[870]	MOVE     	0 24
	218	[865]	SETTABLE 	38 -54 39	; "onCloseWidget" -
	219	[893]	CLOSURE  	39 18	; 0x7f910240f8b0
	220	[893]	MOVE     	0 24
	221	[872]	SETTABLE 	38 -55 39	; "onShowConfigPanel" -
	222	[899]	CLOSURE  	39 19	; 0x7f9102410580
	223	[899]	MOVE     	0 7
	224	[895]	SETTABLE 	38 -56 39	; "onConfigChoice" -
	225	[904]	CLOSURE  	39 20	; 0x7f9102410750
	226	[904]	MOVE     	0 7
	227	[901]	SETTABLE 	38 -57 39	; "onConfigEvent" -
	228	[912]	CLOSURE  	39 21	; 0x7f9102410c90
	229	[912]	MOVE     	0 7
	230	[906]	SETTABLE 	38 -58 39	; "onConfigEvents" -
	231	[962]	CLOSURE  	39 22	; 0x7f9102411320
	232	[962]	MOVE     	0 24
	233	[914]	SETTABLE 	38 -59 39	; "onConfigChoose" -
	234	[1054]	CLOSURE  	39 23	; 0x7f91024122d0
	235	[1054]	MOVE     	0 24
	236	[965]	SETTABLE 	38 -60 39	; "onConfigFineTuneChoose" -
	237	[1264]	CLOSURE  	39 24	; 0x7f9102413450
	238	[1264]	MOVE     	0 24
	239	[1264]	MOVE     	0 31
	240	[1264]	MOVE     	0 30
	241	[1264]	MOVE     	0 32
	242	[1264]	MOVE     	0 5
	243	[1058]	SETTABLE 	38 -61 39	; "onConfigMoreChoose" -
	244	[1300]	CLOSURE  	39 25	; 0x7f9102416ca0
	245	[1300]	MOVE     	0 32
	246	[1300]	MOVE     	0 30
	247	[1300]	MOVE     	0 28
	248	[1300]	MOVE     	0 24
	249	[1300]	MOVE     	0 5
	250	[1266]	SETTABLE 	38 -62 39	; "onMakeDefault" -
	251	[1338]	CLOSURE  	39 26	; 0x7f9102417ba0
	252	[1338]	MOVE     	0 32
	253	[1338]	MOVE     	0 30
	254	[1338]	MOVE     	0 28
	255	[1338]	MOVE     	0 24
	256	[1338]	MOVE     	0 5
	257	[1304]	SETTABLE 	38 -63 39	; "onMakeFineTuneDefault" -
	258	[1346]	CLOSURE  	39 27	; 0x7f9102415690
	259	[1346]	MOVE     	0 24
	260	[1340]	SETTABLE 	38 -64 39	; "closeDialog" -
	261	[1353]	CLOSURE  	39 28	; 0x7f91024187b0
	262	[1348]	SETTABLE 	38 -65 39	; "onTapCloseMenu" -
	263	[1367]	CLOSURE  	39 29	; 0x7f910240c600
	264	[1367]	MOVE     	0 31
	265	[1355]	SETTABLE 	38 -66 39	; "onSwipeCloseMenu" -
	266	[1372]	CLOSURE  	39 30	; 0x7f910240e560
	267	[1369]	SETTABLE 	38 -67 39	; "onClose" -
	268	[1377]	CLOSURE  	39 31	; 0x7f910240e4e0
	269	[1377]	MOVE     	0 7
	270	[1374]	SETTABLE 	38 -68 39	; "onSelect" -
	271	[1379]	RETURN   	38 2
	272	[1379]	RETURN   	0 1

function <./frontend/ui/widget/configdialog.lua:37,72> (59 instructions, 236 bytes at 0x7f9102407080)
1 param, 8 slots, 4 upvalues, 2 locals, 23 constants, 0 functions
	1	[38]	GETTABLE 	1 0 -1	; 1
	2	[40]	GETUPVAL 	2 0	; UnderlineContainer
	3	[40]	SELF     	2 2 -3	; "new"
	4	[40]	NEWTABLE 	4 1 2
	5	[41]	MOVE     	5 1
	6	[42]	GETTABLE 	6 0 -5	; "underline_padding"
	7	[42]	SETTABLE 	4 -4 6	; "padding" -
	8	[43]	GETTABLE 	6 0 -6	; "color"
	9	[43]	SETTABLE 	4 -6 6	; "color" -
	10	[44]	SETLIST  	4 1 1	; 1
	11	[40]	CALL     	2 3 2
	12	[44]	SETTABLE 	0 -2 2	; "underline_container" -
	13	[45]	GETUPVAL 	2 1	; FrameContainer
	14	[45]	SELF     	2 2 -3	; "new"
	15	[45]	NEWTABLE 	4 1 4
	16	[46]	SETTABLE 	4 -4 -7	; "padding" 0
	17	[47]	GETTABLE 	5 0 -8	; "padding_left"
	18	[47]	SETTABLE 	4 -8 5	; "padding_left" -
	19	[48]	GETTABLE 	5 0 -9	; "padding_right"
	20	[48]	SETTABLE 	4 -9 5	; "padding_right" -
	21	[49]	SETTABLE 	4 -10 -7	; "bordersize" 0
	22	[51]	GETTABLE 	5 0 -2	; "underline_container"
	23	[51]	SETLIST  	4 1 1	; 1
	24	[45]	CALL     	2 3 2
	25	[51]	SETTABLE 	0 -1 2	; 1 -
	26	[52]	GETTABLE 	2 0 -1	; 1
	27	[52]	SELF     	2 2 -12	; "getSize"
	28	[52]	CALL     	2 2 2
	29	[52]	SETTABLE 	0 -11 2	; "dimen" -
	30	[54]	GETUPVAL 	2 2	; Device
	31	[54]	SELF     	2 2 -13	; "isTouchDevice"
	32	[54]	CALL     	2 2 2
	33	[54]	TEST     	2 0 0
	34	[54]	JMP      	24	; to 59
	35	[55]	NEWTABLE 	2 0 2
	36	[56]	NEWTABLE 	3 1 1
	37	[57]	GETUPVAL 	4 3	; GestureRange
	38	[57]	SELF     	4 4 -3	; "new"
	39	[57]	NEWTABLE 	6 0 2
	40	[58]	SETTABLE 	6 -16 -17	; "ges" "tap"
	41	[59]	GETTABLE 	7 0 -11	; "dimen"
	42	[59]	SETTABLE 	6 -18 7	; "range" -
	43	[57]	CALL     	4 3 2
	44	[61]	SETTABLE 	3 -19 -20	; "doc" "Select Option Item"
	45	[62]	SETLIST  	3 1 1	; 1
	46	[62]	SETTABLE 	2 -15 3	; "TapSelect" -
	47	[63]	NEWTABLE 	3 1 1
	48	[64]	GETUPVAL 	4 3	; GestureRange
	49	[64]	SELF     	4 4 -3	; "new"
	50	[64]	NEWTABLE 	6 0 2
	51	[65]	SETTABLE 	6 -16 -22	; "ges" "hold"
	52	[66]	GETTABLE 	7 0 -11	; "dimen"
	53	[66]	SETTABLE 	6 -18 7	; "range" -
	54	[64]	CALL     	4 3 2
	55	[68]	SETTABLE 	3 -19 -23	; "doc" "Hold Option Item"
	56	[69]	SETLIST  	3 1 1	; 1
	57	[69]	SETTABLE 	2 -21 3	; "HoldSelect" -
	58	[70]	SETTABLE 	0 -14 2	; "ges_events" -
	59	[72]	RETURN   	0 1

function <./frontend/ui/widget/configdialog.lua:74,76> (5 instructions, 20 bytes at 0x7f91024067c0)
1 param, 3 slots, 1 upvalue, 1 local, 3 constants, 0 functions
	1	[75]	GETTABLE 	1 0 -1	; "underline_container"
	2	[75]	GETUPVAL 	2 0	; Blitbuffer
	3	[75]	GETTABLE 	2 2 -3	; "COLOR_BLACK"
	4	[75]	SETTABLE 	1 -2 2	; "color" -
	5	[76]	RETURN   	0 1

function <./frontend/ui/widget/configdialog.lua:78,80> (5 instructions, 20 bytes at 0x7f9102408280)
1 param, 3 slots, 1 upvalue, 1 local, 3 constants, 0 functions
	1	[79]	GETTABLE 	1 0 -1	; "underline_container"
	2	[79]	GETUPVAL 	2 0	; Blitbuffer
	3	[79]	GETTABLE 	2 2 -3	; "COLOR_WHITE"
	4	[79]	SETTABLE 	1 -2 2	; "color" -
	5	[80]	RETURN   	0 1

function <./frontend/ui/widget/configdialog.lua:82,95> (37 instructions, 148 bytes at 0x7f91024085d0)
1 param, 9 slots, 2 upvalues, 6 locals, 16 constants, 1 function
	1	[83]	GETTABLE 	1 0 -1	; "enabled"
	2	[83]	TEST     	1 0 1
	3	[83]	JMP      	2	; to 6
	4	[83]	LOADBOOL 	1 1 0
	5	[83]	RETURN   	1 2
	6	[84]	GETGLOBAL	1 -2	; pairs
	7	[84]	GETTABLE 	2 0 -3	; "items"
	8	[84]	CALL     	1 2 4
	9	[84]	JMP      	4	; to 14
	10	[85]	GETTABLE 	6 5 -4	; "underline_container"
	11	[85]	GETUPVAL 	7 0	; Blitbuffer
	12	[85]	GETTABLE 	7 7 -6	; "COLOR_WHITE"
	13	[85]	SETTABLE 	6 -5 7	; "color" -
	14	[84]	TFORLOOP 	1 2
	15	[85]	JMP      	-6	; to 10
	16	[87]	GETTABLE 	1 0 -4	; "underline_container"
	17	[87]	GETUPVAL 	2 0	; Blitbuffer
	18	[87]	GETTABLE 	2 2 -7	; "COLOR_BLACK"
	19	[87]	SETTABLE 	1 -5 2	; "color" -
	20	[88]	GETTABLE 	1 0 -8	; "config"
	21	[88]	SELF     	1 1 -9	; "onConfigChoose"
	22	[88]	GETTABLE 	3 0 -10	; "values"
	23	[88]	GETTABLE 	4 0 -11	; "name"
	24	[89]	GETTABLE 	5 0 -12	; "event"
	25	[89]	GETTABLE 	6 0 -13	; "args"
	26	[90]	GETTABLE 	7 0 -14	; "events"
	27	[90]	GETTABLE 	8 0 -15	; "current_item"
	28	[88]	CALL     	1 8 1
	29	[91]	GETUPVAL 	1 1	; UIManager
	30	[91]	SELF     	1 1 -16	; "setDirty"
	31	[91]	GETTABLE 	3 0 -8	; "config"
	32	[93]	CLOSURE  	4 0	; 0x7f9102408a40
	33	[93]	MOVE     	0 0
	34	[91]	CALL     	1 4 1
	35	[94]	LOADBOOL 	1 1 0
	36	[94]	RETURN   	1 2
	37	[95]	RETURN   	0 1

function <./frontend/ui/widget/configdialog.lua:91,93> (6 instructions, 24 bytes at 0x7f9102408a40)
0 params, 2 slots, 1 upvalue, 0 locals, 3 constants, 0 functions
	1	[92]	LOADK    	0 -1	; "fast"
	2	[92]	GETUPVAL 	1 0	; self
	3	[92]	GETTABLE 	1 1 -2	; 1
	4	[92]	GETTABLE 	1 1 -3	; "dimen"
	5	[92]	RETURN   	0 3
	6	[93]	RETURN   	0 1

function <./frontend/ui/widget/configdialog.lua:97,103> (17 instructions, 68 bytes at 0x7f9102408ac0)
1 param, 8 slots, 0 upvalues, 1 local, 8 constants, 0 functions
	1	[98]	GETTABLE 	1 0 -1	; "config"
	2	[98]	SELF     	1 1 -2	; "onMakeDefault"
	3	[98]	GETTABLE 	3 0 -3	; "name"
	4	[98]	GETTABLE 	4 0 -4	; "name_text"
	5	[99]	GETTABLE 	5 0 -5	; "values"
	6	[99]	TEST     	5 0 1
	7	[99]	JMP      	1	; to 9
	8	[99]	GETTABLE 	5 0 -6	; "args"
	9	[100]	GETTABLE 	6 0 -5	; "values"
	10	[100]	TEST     	6 0 1
	11	[100]	JMP      	1	; to 13
	12	[100]	GETTABLE 	6 0 -7	; "item_text"
	13	[101]	GETTABLE 	7 0 -8	; "current_item"
	14	[98]	CALL     	1 7 1
	15	[102]	LOADBOOL 	1 1 0
	16	[102]	RETURN   	1 2
	17	[103]	RETURN   	0 1

function <./frontend/ui/widget/configdialog.lua:107,141> (58 instructions, 232 bytes at 0x7f91024097a0)
1 param, 7 slots, 4 upvalues, 1 local, 24 constants, 0 functions
	1	[108]	GETUPVAL 	1 0	; UnderlineContainer
	2	[108]	SELF     	1 1 -2	; "new"
	3	[108]	NEWTABLE 	3 1 2
	4	[109]	GETTABLE 	4 0 -3	; "icon"
	5	[110]	GETTABLE 	5 0 -5	; "underline_padding"
	6	[110]	SETTABLE 	3 -4 5	; "padding" -
	7	[111]	GETTABLE 	5 0 -6	; "color"
	8	[111]	SETTABLE 	3 -6 5	; "color" -
	9	[112]	SETLIST  	3 1 1	; 1
	10	[108]	CALL     	1 3 2
	11	[112]	SETTABLE 	0 -1 1	; "underline_container" -
	12	[113]	GETUPVAL 	1 1	; FrameContainer
	13	[113]	SELF     	1 1 -2	; "new"
	14	[113]	NEWTABLE 	3 1 4
	15	[114]	SETTABLE 	3 -4 -8	; "padding" 0
	16	[115]	GETTABLE 	4 0 -9	; "padding_left"
	17	[115]	SETTABLE 	3 -9 4	; "padding_left" -
	18	[116]	GETTABLE 	4 0 -10	; "padding_right"
	19	[116]	SETTABLE 	3 -10 4	; "padding_right" -
	20	[117]	SETTABLE 	3 -11 -8	; "bordersize" 0
	21	[119]	GETTABLE 	4 0 -1	; "underline_container"
	22	[119]	SETLIST  	3 1 1	; 1
	23	[113]	CALL     	1 3 2
	24	[119]	SETTABLE 	0 -7 1	; 1 -
	25	[120]	GETTABLE 	1 0 -7	; 1
	26	[120]	SELF     	1 1 -13	; "getSize"
	27	[120]	CALL     	1 2 2
	28	[120]	SETTABLE 	0 -12 1	; "dimen" -
	29	[122]	GETUPVAL 	1 2	; Device
	30	[122]	SELF     	1 1 -14	; "isTouchDevice"
	31	[122]	CALL     	1 2 2
	32	[122]	TEST     	1 0 0
	33	[122]	JMP      	24	; to 58
	34	[123]	NEWTABLE 	1 0 2
	35	[124]	NEWTABLE 	2 1 1
	36	[125]	GETUPVAL 	3 3	; GestureRange
	37	[125]	SELF     	3 3 -2	; "new"
	38	[125]	NEWTABLE 	5 0 2
	39	[126]	SETTABLE 	5 -17 -18	; "ges" "tap"
	40	[127]	GETTABLE 	6 0 -12	; "dimen"
	41	[127]	SETTABLE 	5 -19 6	; "range" -
	42	[125]	CALL     	3 3 2
	43	[129]	SETTABLE 	2 -20 -21	; "doc" "Select Option Item"
	44	[130]	SETLIST  	2 1 1	; 1
	45	[130]	SETTABLE 	1 -16 2	; "TapSelect" -
	46	[131]	NEWTABLE 	2 1 1
	47	[132]	GETUPVAL 	3 3	; GestureRange
	48	[132]	SELF     	3 3 -2	; "new"
	49	[132]	NEWTABLE 	5 0 2
	50	[133]	SETTABLE 	5 -17 -23	; "ges" "hold"
	51	[134]	GETTABLE 	6 0 -12	; "dimen"
	52	[134]	SETTABLE 	5 -19 6	; "range" -
	53	[132]	CALL     	3 3 2
	54	[136]	SETTABLE 	2 -20 -24	; "doc" "Hold Option Item"
	55	[137]	SETLIST  	2 1 1	; 1
	56	[137]	SETTABLE 	1 -22 2	; "HoldSelect" -
	57	[139]	SETTABLE 	0 -15 1	; "ges_events" -
	58	[141]	RETURN   	0 1

function <./frontend/ui/widget/configdialog.lua:143,145> (3 instructions, 12 bytes at 0x7f9102409a70)
1 param, 2 slots, 0 upvalues, 1 local, 3 constants, 0 functions
	1	[144]	GETTABLE 	1 0 -1	; "icon"
	2	[144]	SETTABLE 	1 -2 -3	; "invert" true
	3	[145]	RETURN   	0 1

function <./frontend/ui/widget/configdialog.lua:147,149> (3 instructions, 12 bytes at 0x7f9102409d30)
1 param, 2 slots, 0 upvalues, 1 local, 3 constants, 0 functions
	1	[148]	GETTABLE 	1 0 -1	; "icon"
	2	[148]	SETTABLE 	1 -2 -3	; "invert" false
	3	[149]	RETURN   	0 1

function <./frontend/ui/widget/configdialog.lua:151,166> (37 instructions, 148 bytes at 0x7f91024099c0)
1 param, 9 slots, 2 upvalues, 6 locals, 16 constants, 1 function
	1	[152]	GETTABLE 	1 0 -1	; "enabled"
	2	[152]	TEST     	1 0 1
	3	[152]	JMP      	2	; to 6
	4	[152]	LOADBOOL 	1 1 0
	5	[152]	RETURN   	1 2
	6	[153]	GETGLOBAL	1 -2	; pairs
	7	[153]	GETTABLE 	2 0 -3	; "items"
	8	[153]	CALL     	1 2 4
	9	[153]	JMP      	4	; to 14
	10	[155]	GETTABLE 	6 5 -4	; "underline_container"
	11	[155]	GETUPVAL 	7 0	; Blitbuffer
	12	[155]	GETTABLE 	7 7 -6	; "COLOR_WHITE"
	13	[155]	SETTABLE 	6 -5 7	; "color" -
	14	[153]	TFORLOOP 	1 2
	15	[155]	JMP      	-6	; to 10
	16	[158]	GETTABLE 	1 0 -4	; "underline_container"
	17	[158]	GETUPVAL 	2 0	; Blitbuffer
	18	[158]	GETTABLE 	2 2 -7	; "COLOR_BLACK"
	19	[158]	SETTABLE 	1 -5 2	; "color" -
	20	[159]	GETTABLE 	1 0 -8	; "config"
	21	[159]	SELF     	1 1 -9	; "onConfigChoose"
	22	[159]	GETTABLE 	3 0 -10	; "values"
	23	[159]	GETTABLE 	4 0 -11	; "name"
	24	[160]	GETTABLE 	5 0 -12	; "event"
	25	[160]	GETTABLE 	6 0 -13	; "args"
	26	[161]	GETTABLE 	7 0 -14	; "events"
	27	[161]	GETTABLE 	8 0 -15	; "current_item"
	28	[159]	CALL     	1 8 1
	29	[162]	GETUPVAL 	1 1	; UIManager
	30	[162]	SELF     	1 1 -16	; "setDirty"
	31	[162]	GETTABLE 	3 0 -8	; "config"
	32	[164]	CLOSURE  	4 0	; 0x7f9102407970
	33	[164]	MOVE     	0 0
	34	[162]	CALL     	1 4 1
	35	[165]	LOADBOOL 	1 1 0
	36	[165]	RETURN   	1 2
	37	[166]	RETURN   	0 1

function <./frontend/ui/widget/configdialog.lua:162,164> (6 instructions, 24 bytes at 0x7f9102407970)
0 params, 2 slots, 1 upvalue, 0 locals, 3 constants, 0 functions
	1	[163]	LOADK    	0 -1	; "fast"
	2	[163]	GETUPVAL 	1 0	; self
	3	[163]	GETTABLE 	1 1 -2	; 1
	4	[163]	GETTABLE 	1 1 -3	; "dimen"
	5	[163]	RETURN   	0 3
	6	[164]	RETURN   	0 1

function <./frontend/ui/widget/configdialog.lua:168,172> (11 instructions, 44 bytes at 0x7f91024078b0)
1 param, 8 slots, 0 upvalues, 1 local, 6 constants, 0 functions
	1	[169]	GETTABLE 	1 0 -1	; "config"
	2	[169]	SELF     	1 1 -2	; "onMakeDefault"
	3	[169]	GETTABLE 	3 0 -3	; "name"
	4	[169]	GETTABLE 	4 0 -4	; "name_text"
	5	[170]	GETTABLE 	5 0 -5	; "values"
	6	[170]	GETTABLE 	6 0 -5	; "values"
	7	[170]	GETTABLE 	7 0 -6	; "current_item"
	8	[169]	CALL     	1 7 1
	9	[171]	LOADBOOL 	1 1 0
	10	[171]	RETURN   	1 2
	11	[172]	RETURN   	0 1

function <./frontend/ui/widget/configdialog.lua:176,619> (1219 instructions, 4876 bytes at 0x7f910240a660)
1 param, 60 slots, 20 upvalues, 117 locals, 112 constants, 5 functions
	1	[178]	LOADK    	1 -1	; 20
	2	[179]	LOADK    	2 -2	; 16
	3	[180]	LOADK    	3 -3	; 40
	4	[181]	LOADK    	4 -4	; 50
	5	[183]	GETUPVAL 	5 0	; Size
	6	[183]	GETTABLE 	5 5 -5	; "padding"
	7	[183]	GETTABLE 	5 5 -6	; "large"
	8	[184]	GETUPVAL 	6 0	; Size
	9	[184]	GETTABLE 	6 6 -5	; "padding"
	10	[184]	GETTABLE 	6 6 -7	; "fullscreen"
	11	[186]	GETUPVAL 	7 0	; Size
	12	[186]	GETTABLE 	7 7 -5	; "padding"
	13	[186]	GETTABLE 	7 7 -8	; "small"
	14	[187]	GETUPVAL 	8 0	; Size
	15	[187]	GETTABLE 	8 8 -5	; "padding"
	16	[187]	GETTABLE 	8 8 -9	; "button"
	17	[191]	LOADBOOL 	9 1 0
	18	[194]	LOADK    	10 -10	; 0
	19	[195]	LOADK    	11 -11	; 1
	20	[195]	GETTABLE 	12 0 -12	; "options"
	21	[195]	LEN      	12 12
	22	[195]	LOADK    	13 -11	; 1
	23	[195]	FORPREP  	11 74	; to 98
	24	[197]	GETTABLE 	15 0 -12	; "options"
	25	[197]	GETTABLE 	15 15 14
	26	[197]	GETTABLE 	15 15 -13	; "advanced"
	27	[197]	TEST     	15 0 0
	28	[197]	JMP      	3	; to 32
	29	[197]	MOVE     	15 9
	30	[197]	JMP      	2	; to 33
	31	[197]	LOADBOOL 	15 0 1
	32	[197]	LOADBOOL 	15 1 0
	33	[198]	GETTABLE 	16 0 -12	; "options"
	34	[198]	GETTABLE 	16 16 14
	35	[198]	GETTABLE 	16 16 -14	; "show"
	36	[200]	GETTABLE 	17 0 -12	; "options"
	37	[200]	GETTABLE 	17 17 14
	38	[200]	GETTABLE 	17 17 -15	; "show_func"
	39	[200]	TEST     	17 0 0
	40	[200]	JMP      	5	; to 46
	41	[201]	GETTABLE 	17 0 -12	; "options"
	42	[201]	GETTABLE 	17 17 14
	43	[201]	GETTABLE 	17 17 -15	; "show_func"
	44	[201]	CALL     	17 1 2
	45	[201]	MOVE     	16 17
	46	[203]	EQ       	1 16 -16	; - false
	47	[203]	JMP      	50	; to 98
	48	[203]	TEST     	15 0 0
	49	[203]	JMP      	48	; to 98
	50	[204]	GETTABLE 	17 0 -12	; "options"
	51	[204]	GETTABLE 	17 17 14
	52	[204]	GETTABLE 	17 17 -17	; "name_font_face"
	53	[204]	TEST     	17 0 0
	54	[204]	JMP      	5	; to 60
	55	[204]	GETTABLE 	17 0 -12	; "options"
	56	[204]	GETTABLE 	17 17 14
	57	[204]	GETTABLE 	17 17 -17	; "name_font_face"
	58	[204]	TEST     	17 0 1
	59	[204]	JMP      	1	; to 61
	60	[204]	LOADK    	17 -18	; "cfont"
	61	[205]	GETTABLE 	18 0 -12	; "options"
	62	[205]	GETTABLE 	18 18 14
	63	[205]	GETTABLE 	18 18 -19	; "name_font_size"
	64	[205]	TEST     	18 0 0
	65	[205]	JMP      	5	; to 71
	66	[205]	GETTABLE 	18 0 -12	; "options"
	67	[205]	GETTABLE 	18 18 14
	68	[205]	GETTABLE 	18 18 -19	; "name_font_size"
	69	[205]	TEST     	18 0 1
	70	[205]	JMP      	1	; to 72
	71	[205]	MOVE     	18 1
	72	[206]	GETTABLE 	19 0 -12	; "options"
	73	[206]	GETTABLE 	19 19 14
	74	[206]	GETTABLE 	19 19 -20	; "name_text"
	75	[207]	GETUPVAL 	20 1	; Font
	76	[207]	SELF     	20 20 -21	; "getFace"
	77	[207]	MOVE     	22 17
	78	[207]	MOVE     	23 18
	79	[207]	CALL     	20 4 2
	80	[208]	LOADK    	21 -10	; 0
	81	[209]	EQ       	1 19 -22	; - nil
	82	[209]	JMP      	9	; to 92
	83	[210]	GETUPVAL 	22 2	; TextWidget
	84	[210]	SELF     	22 22 -23	; "new"
	85	[210]	NEWTABLE 	24 0 2
	86	[211]	SETTABLE 	24 -24 19	; "text" -
	87	[212]	SETTABLE 	24 -25 20	; "face" -
	88	[210]	CALL     	22 3 2
	89	[214]	SELF     	23 22 -26	; "getWidth"
	90	[214]	CALL     	23 2 2
	91	[214]	MOVE     	21 23
	92	[216]	GETGLOBAL	22 -27	; math
	93	[216]	GETTABLE 	22 22 -28	; "max"
	94	[216]	MOVE     	23 10
	95	[216]	MOVE     	24 21
	96	[216]	CALL     	22 3 2
	97	[216]	MOVE     	10 22
	98	[195]	FORLOOP  	11 -75	; to 24
	99	[223]	ADD      	11 10 6
	100	[223]	MUL      	12 -29 7	; 2 -
	101	[223]	ADD      	11 11 12
	102	[223]	GETUPVAL 	12 3	; Screen
	103	[223]	SELF     	12 12 -26	; "getWidth"
	104	[223]	CALL     	12 2 2
	105	[223]	DIV      	11 11 12
	106	[224]	GETGLOBAL	12 -27	; math
	107	[224]	GETTABLE 	12 12 -28	; "max"
	108	[224]	MOVE     	13 11
	109	[224]	LOADK    	14 -30	; 0.25
	110	[224]	CALL     	12 3 2
	111	[224]	MOVE     	11 12
	112	[225]	GETGLOBAL	12 -27	; math
	113	[225]	GETTABLE 	12 12 -31	; "min"
	114	[225]	MOVE     	13 11
	115	[225]	LOADK    	14 -32	; 0.5
	116	[225]	CALL     	12 3 2
	117	[225]	MOVE     	11 12
	118	[226]	SUB      	12 -11 11	; 1 -
	119	[229]	GETUPVAL 	13 4	; VerticalGroup
	120	[229]	SELF     	13 13 -23	; "new"
	121	[229]	NEWTABLE 	15 0 0
	122	[229]	CALL     	13 3 2
	123	[230]	GETGLOBAL	14 -33	; table
	124	[230]	GETTABLE 	14 14 -34	; "insert"
	125	[230]	MOVE     	15 13
	126	[230]	GETUPVAL 	16 5	; VerticalSpan
	127	[230]	SELF     	16 16 -23	; "new"
	128	[230]	NEWTABLE 	18 0 1
	129	[231]	SETTABLE 	18 -35 5	; "width" -
	130	[230]	CALL     	16 3 0
	131	[230]	CALL     	14 0 1
	132	[234]	LOADK    	14 -11	; 1
	133	[234]	GETTABLE 	15 0 -12	; "options"
	134	[234]	LEN      	15 15
	135	[234]	LOADK    	16 -11	; 1
	136	[234]	FORPREP  	14 1068	; to 1205
	137	[235]	GETTABLE 	18 0 -12	; "options"
	138	[235]	GETTABLE 	18 18 17
	139	[235]	GETTABLE 	18 18 -13	; "advanced"
	140	[235]	TEST     	18 0 0
	141	[235]	JMP      	3	; to 145
	142	[235]	MOVE     	18 9
	143	[235]	JMP      	2	; to 146
	144	[235]	LOADBOOL 	18 0 1
	145	[235]	LOADBOOL 	18 1 0
	146	[236]	GETTABLE 	19 0 -12	; "options"
	147	[236]	GETTABLE 	19 19 17
	148	[236]	GETTABLE 	19 19 -14	; "show"
	149	[238]	GETTABLE 	20 0 -12	; "options"
	150	[238]	GETTABLE 	20 20 17
	151	[238]	GETTABLE 	20 20 -15	; "show_func"
	152	[238]	TEST     	20 0 0
	153	[238]	JMP      	5	; to 159
	154	[239]	GETTABLE 	20 0 -12	; "options"
	155	[239]	GETTABLE 	20 20 17
	156	[239]	GETTABLE 	20 20 -15	; "show_func"
	157	[239]	CALL     	20 1 2
	158	[239]	MOVE     	19 20
	159	[241]	EQ       	1 19 -16	; - false
	160	[241]	JMP      	1043	; to 1204
	161	[241]	TEST     	18 0 0
	162	[241]	JMP      	1041	; to 1204
	163	[242]	GETTABLE 	20 0 -12	; "options"
	164	[242]	GETTABLE 	20 20 17
	165	[242]	GETTABLE 	20 20 -36	; "name_align_right"
	166	[242]	TEST     	20 0 0
	167	[242]	JMP      	5	; to 173
	168	[242]	GETTABLE 	20 0 -12	; "options"
	169	[242]	GETTABLE 	20 20 17
	170	[242]	GETTABLE 	20 20 -36	; "name_align_right"
	171	[242]	TEST     	20 0 1
	172	[242]	JMP      	1	; to 174
	173	[242]	MOVE     	20 11
	174	[243]	GETTABLE 	21 0 -12	; "options"
	175	[243]	GETTABLE 	21 21 17
	176	[243]	GETTABLE 	21 21 -37	; "item_align_center"
	177	[243]	TEST     	21 0 0
	178	[243]	JMP      	5	; to 184
	179	[243]	GETTABLE 	21 0 -12	; "options"
	180	[243]	GETTABLE 	21 21 17
	181	[243]	GETTABLE 	21 21 -37	; "item_align_center"
	182	[243]	TEST     	21 0 1
	183	[243]	JMP      	1	; to 185
	184	[243]	MOVE     	21 12
	185	[244]	GETTABLE 	22 0 -12	; "options"
	186	[244]	GETTABLE 	22 22 17
	187	[244]	GETTABLE 	22 22 -17	; "name_font_face"
	188	[244]	TEST     	22 0 0
	189	[244]	JMP      	5	; to 195
	190	[244]	GETTABLE 	22 0 -12	; "options"
	191	[244]	GETTABLE 	22 22 17
	192	[244]	GETTABLE 	22 22 -17	; "name_font_face"
	193	[244]	TEST     	22 0 1
	194	[244]	JMP      	1	; to 196
	195	[244]	LOADK    	22 -18	; "cfont"
	196	[245]	GETTABLE 	23 0 -12	; "options"
	197	[245]	GETTABLE 	23 23 17
	198	[245]	GETTABLE 	23 23 -19	; "name_font_size"
	199	[245]	TEST     	23 0 0
	200	[245]	JMP      	5	; to 206
	201	[245]	GETTABLE 	23 0 -12	; "options"
	202	[245]	GETTABLE 	23 23 17
	203	[245]	GETTABLE 	23 23 -19	; "name_font_size"
	204	[245]	TEST     	23 0 1
	205	[245]	JMP      	1	; to 207
	206	[245]	MOVE     	23 1
	207	[246]	GETTABLE 	24 0 -12	; "options"
	208	[246]	GETTABLE 	24 24 17
	209	[246]	GETTABLE 	24 24 -38	; "item_font_face"
	210	[246]	TEST     	24 0 0
	211	[246]	JMP      	5	; to 217
	212	[246]	GETTABLE 	24 0 -12	; "options"
	213	[246]	GETTABLE 	24 24 17
	214	[246]	GETTABLE 	24 24 -38	; "item_font_face"
	215	[246]	TEST     	24 0 1
	216	[246]	JMP      	1	; to 218
	217	[246]	LOADK    	24 -18	; "cfont"
	218	[247]	GETTABLE 	25 0 -12	; "options"
	219	[247]	GETTABLE 	25 25 17
	220	[247]	GETTABLE 	25 25 -39	; "item_font_size"
	221	[247]	TEST     	25 0 0
	222	[247]	JMP      	5	; to 228
	223	[247]	GETTABLE 	25 0 -12	; "options"
	224	[247]	GETTABLE 	25 25 17
	225	[247]	GETTABLE 	25 25 -39	; "item_font_size"
	226	[247]	TEST     	25 0 1
	227	[247]	JMP      	1	; to 229
	228	[247]	MOVE     	25 2
	229	[248]	GETUPVAL 	26 3	; Screen
	230	[248]	SELF     	26 26 -40	; "scaleBySize"
	231	[248]	GETTABLE 	28 0 -12	; "options"
	232	[248]	GETTABLE 	28 28 17
	233	[248]	GETTABLE 	28 28 -41	; "height"
	234	[248]	TEST     	28 0 0
	235	[248]	JMP      	5	; to 241
	236	[248]	GETTABLE 	28 0 -12	; "options"
	237	[248]	GETTABLE 	28 28 17
	238	[248]	GETTABLE 	28 28 -41	; "height"
	239	[248]	TEST     	28 0 1
	240	[248]	JMP      	15	; to 256
	241	[249]	GETTABLE 	28 0 -12	; "options"
	242	[249]	GETTABLE 	28 28 17
	243	[249]	GETTABLE 	28 28 -41	; "height"
	244	[249]	TEST     	28 0 1
	245	[249]	JMP      	1	; to 247
	246	[249]	LOADK    	28 -42	; 30
	247	[249]	GETTABLE 	29 0 -12	; "options"
	248	[249]	GETTABLE 	29 29 17
	249	[249]	GETTABLE 	29 29 -43	; "row_count"
	250	[249]	TEST     	29 0 1
	251	[249]	JMP      	1	; to 253
	252	[249]	LOADK    	29 -11	; 1
	253	[249]	SUB      	29 29 -11	; - 1
	254	[249]	MUL      	28 28 29
	255	[249]	ADD      	28 4 28
	256	[248]	CALL     	26 3 2
	257	[250]	GETUPVAL 	27 3	; Screen
	258	[250]	SELF     	27 27 -40	; "scaleBySize"
	259	[250]	GETTABLE 	29 0 -12	; "options"
	260	[250]	GETTABLE 	29 29 17
	261	[250]	GETTABLE 	29 29 -44	; "spacing"
	262	[250]	TEST     	29 0 0
	263	[250]	JMP      	5	; to 269
	264	[250]	GETTABLE 	29 0 -12	; "options"
	265	[250]	GETTABLE 	29 29 17
	266	[250]	GETTABLE 	29 29 -44	; "spacing"
	267	[250]	TEST     	29 0 1
	268	[250]	JMP      	1	; to 270
	269	[250]	MOVE     	29 3
	270	[250]	CALL     	27 3 2
	271	[251]	LOADBOOL 	28 1 0
	272	[252]	EQ       	0 21 -11	; - 1
	273	[252]	JMP      	1	; to 275
	274	[253]	LOADK    	20 -10	; 0
	275	[255]	ADD      	29 20 21
	276	[255]	LT       	0 -11 29	; 1 -
	277	[255]	JMP      	2	; to 280
	278	[256]	LOADK    	20 -32	; 0.5
	279	[257]	LOADK    	21 -32	; 0.5
	280	[259]	GETTABLE 	29 0 -12	; "options"
	281	[259]	GETTABLE 	29 29 17
	282	[259]	GETTABLE 	29 29 -45	; "enabled_func"
	283	[259]	TEST     	29 0 0
	284	[259]	JMP      	9	; to 294
	285	[260]	GETTABLE 	29 0 -12	; "options"
	286	[260]	GETTABLE 	29 29 17
	287	[260]	GETTABLE 	29 29 -45	; "enabled_func"
	288	[260]	GETTABLE 	30 0 -46	; "config"
	289	[260]	GETTABLE 	30 30 -47	; "configurable"
	290	[260]	GETTABLE 	31 0 -46	; "config"
	291	[260]	GETTABLE 	31 31 -48	; "document"
	292	[260]	CALL     	29 3 2
	293	[260]	MOVE     	28 29
	294	[262]	GETUPVAL 	29 6	; HorizontalGroup
	295	[262]	SELF     	29 29 -23	; "new"
	296	[262]	NEWTABLE 	31 0 0
	297	[262]	CALL     	29 3 2
	298	[265]	GETTABLE 	30 0 -12	; "options"
	299	[265]	GETTABLE 	30 30 17
	300	[265]	GETTABLE 	30 30 -20	; "name_text"
	301	[265]	TEST     	30 0 0
	302	[265]	JMP      	63	; to 366
	303	[267]	GETGLOBAL	30 -27	; math
	304	[267]	GETTABLE 	30 30 -49	; "floor"
	305	[267]	GETUPVAL 	31 3	; Screen
	306	[267]	SELF     	31 31 -26	; "getWidth"
	307	[267]	CALL     	31 2 2
	308	[267]	MUL      	31 20 31
	309	[267]	CALL     	30 2 2
	310	[271]	MUL      	31 -29 7	; 2 -
	311	[271]	SUB      	31 30 31
	312	[272]	GETTABLE 	32 0 -12	; "options"
	313	[272]	GETTABLE 	32 32 17
	314	[272]	GETTABLE 	32 32 -20	; "name_text"
	315	[273]	GETUPVAL 	33 1	; Font
	316	[273]	SELF     	33 33 -21	; "getFace"
	317	[273]	MOVE     	35 22
	318	[273]	MOVE     	36 23
	319	[273]	CALL     	33 4 2
	320	[274]	GETUPVAL 	34 7	; RightContainer
	321	[274]	SELF     	34 34 -23	; "new"
	322	[274]	NEWTABLE 	36 0 1
	323	[275]	GETUPVAL 	37 8	; Geom
	324	[275]	SELF     	37 37 -23	; "new"
	325	[275]	NEWTABLE 	39 0 2
	326	[275]	SETTABLE 	39 -51 30	; "w" -
	327	[275]	SETTABLE 	39 -52 26	; "h" -
	328	[275]	CALL     	37 3 2
	329	[275]	SETTABLE 	36 -50 37	; "dimen" -
	330	[274]	CALL     	34 3 2
	331	[277]	GETUPVAL 	35 9	; Button
	332	[277]	SELF     	35 35 -23	; "new"
	333	[277]	NEWTABLE 	37 0 11
	334	[278]	SETTABLE 	37 -24 32	; "text" -
	335	[279]	SETTABLE 	37 -53 31	; "max_width" -
	336	[280]	SETTABLE 	37 -54 -10	; "bordersize" 0
	337	[281]	SETTABLE 	37 -25 33	; "face" -
	338	[282]	SETTABLE 	37 -55 28	; "enabled" -
	339	[283]	GETTABLE 	38 0 -12	; "options"
	340	[283]	GETTABLE 	38 38 17
	341	[283]	GETTABLE 	38 38 -57	; "name_text_hold_callback"
	342	[283]	EQ       	0 38 -22	; - nil
	343	[283]	JMP      	1	; to 345
	344	[283]	LOADBOOL 	38 0 1
	345	[283]	LOADBOOL 	38 1 0
	346	[283]	SETTABLE 	37 -56 38	; "allow_hold_when_disabled" -
	347	[284]	SETTABLE 	37 -5 7	; "padding" -
	348	[285]	SETTABLE 	37 -58 22	; "text_font_face" -
	349	[286]	SETTABLE 	37 -59 23	; "text_font_size" -
	350	[287]	SETTABLE 	37 -60 -16	; "text_font_bold" false
	351	[293]	CLOSURE  	38 0	; 0x7f910240a2d0
	352	[293]	MOVE     	0 0
	353	[293]	MOVE     	0 17
	354	[293]	SETTABLE 	37 -61 38	; "hold_callback" -
	355	[277]	CALL     	35 3 2
	356	[295]	GETGLOBAL	36 -33	; table
	357	[295]	GETTABLE 	36 36 -34	; "insert"
	358	[295]	MOVE     	37 34
	359	[295]	MOVE     	38 35
	360	[295]	CALL     	36 3 1
	361	[296]	GETGLOBAL	36 -33	; table
	362	[296]	GETTABLE 	36 36 -34	; "insert"
	363	[296]	MOVE     	37 29
	364	[296]	MOVE     	38 34
	365	[296]	CALL     	36 3 1
	366	[302]	GETGLOBAL	30 -27	; math
	367	[302]	GETTABLE 	30 30 -49	; "floor"
	368	[302]	GETUPVAL 	31 3	; Screen
	369	[302]	SELF     	31 31 -26	; "getWidth"
	370	[302]	CALL     	31 2 2
	371	[302]	MUL      	31 21 31
	372	[302]	CALL     	30 2 2
	373	[303]	MUL      	31 -29 6	; 2 -
	374	[303]	SUB      	31 30 31
	375	[304]	GETUPVAL 	32 10	; CenterContainer
	376	[304]	SELF     	32 32 -23	; "new"
	377	[304]	NEWTABLE 	34 0 1
	378	[305]	GETUPVAL 	35 8	; Geom
	379	[305]	SELF     	35 35 -23	; "new"
	380	[305]	NEWTABLE 	37 0 2
	381	[306]	SETTABLE 	37 -51 30	; "w" -
	382	[307]	SETTABLE 	37 -52 26	; "h" -
	383	[305]	CALL     	35 3 2
	384	[308]	SETTABLE 	34 -50 35	; "dimen" -
	385	[304]	CALL     	32 3 2
	386	[310]	GETUPVAL 	33 6	; HorizontalGroup
	387	[310]	SELF     	33 33 -23	; "new"
	388	[310]	NEWTABLE 	35 0 0
	389	[310]	CALL     	33 3 2
	390	[311]	LOADBOOL 	34 0 0
	391	[312]	NEWTABLE 	35 0 0
	392	[313]	GETGLOBAL	36 -62	; type
	393	[313]	GETTABLE 	37 0 -12	; "options"
	394	[313]	GETTABLE 	37 37 17
	395	[313]	GETTABLE 	37 37 -39	; "item_font_size"
	396	[313]	CALL     	36 2 2
	397	[313]	EQ       	0 36 -33	; - "table"
	398	[313]	JMP      	2	; to 401
	399	[314]	SETTABLE 	33 -63 -64	; "align" "bottom"
	400	[315]	LOADBOOL 	34 1 0
	401	[319]	LOADNIL  	36 36
	402	[320]	GETTABLE 	37 0 -12	; "options"
	403	[320]	GETTABLE 	37 37 17
	404	[320]	GETTABLE 	37 37 -65	; "default_pos"
	405	[330]	CLOSURE  	38 1	; 0x7f910240b090
	406	[330]	GETUPVAL 	0 11	; logger
	407	[331]	GETTABLE 	39 0 -12	; "options"
	408	[331]	GETTABLE 	39 39 17
	409	[331]	GETTABLE 	39 39 -66	; "name"
	410	[331]	TEST     	39 0 0
	411	[331]	JMP      	191	; to 603
	412	[332]	GETTABLE 	39 0 -12	; "options"
	413	[332]	GETTABLE 	39 39 17
	414	[332]	GETTABLE 	39 39 -67	; "values"
	415	[332]	TEST     	39 0 0
	416	[332]	JMP      	75	; to 492
	417	[334]	GETTABLE 	39 0 -12	; "options"
	418	[334]	GETTABLE 	39 39 17
	419	[334]	GETTABLE 	39 39 -68	; "current_func"
	420	[334]	TEST     	39 0 0
	421	[334]	JMP      	6	; to 428
	422	[334]	GETTABLE 	39 0 -12	; "options"
	423	[334]	GETTABLE 	39 39 17
	424	[334]	GETTABLE 	39 39 -68	; "current_func"
	425	[334]	CALL     	39 1 2
	426	[335]	TEST     	39 0 1
	427	[335]	JMP      	6	; to 434
	428	[335]	GETTABLE 	39 0 -46	; "config"
	429	[335]	GETTABLE 	39 39 -47	; "configurable"
	430	[335]	GETTABLE 	40 0 -12	; "options"
	431	[335]	GETTABLE 	40 40 17
	432	[335]	GETTABLE 	40 40 -66	; "name"
	433	[335]	GETTABLE 	39 39 40
	434	[336]	LOADNIL  	40 40
	435	[337]	GETGLOBAL	41 -62	; type
	436	[337]	MOVE     	42 39
	437	[337]	CALL     	41 2 2
	438	[337]	EQ       	0 41 -33	; - "table"
	439	[337]	JMP      	10	; to 450
	440	[338]	MOVE     	41 38
	441	[338]	GETTABLE 	42 39 -11	; 1
	442	[338]	GETTABLE 	43 0 -12	; "options"
	443	[338]	GETTABLE 	43 43 17
	444	[338]	GETTABLE 	43 43 -67	; "values"
	445	[338]	GETTABLE 	43 43 -11	; 1
	446	[338]	GETTABLE 	43 43 -11	; 1
	447	[338]	CALL     	41 3 2
	448	[338]	MOVE     	40 41
	449	[338]	JMP      	8	; to 458
	450	[340]	MOVE     	41 38
	451	[340]	MOVE     	42 39
	452	[340]	GETTABLE 	43 0 -12	; "options"
	453	[340]	GETTABLE 	43 43 17
	454	[340]	GETTABLE 	43 43 -67	; "values"
	455	[340]	GETTABLE 	43 43 -11	; 1
	456	[340]	CALL     	41 3 2
	457	[340]	MOVE     	40 41
	458	[343]	LOADNIL  	41 41
	459	[344]	GETGLOBAL	42 -69	; pairs
	460	[344]	GETTABLE 	43 0 -12	; "options"
	461	[344]	GETTABLE 	43 43 17
	462	[344]	GETTABLE 	43 43 -67	; "values"
	463	[344]	CALL     	42 2 4
	464	[344]	JMP      	24	; to 489
	465	[345]	GETGLOBAL	47 -62	; type
	466	[345]	MOVE     	48 39
	467	[345]	CALL     	47 2 2
	468	[345]	EQ       	0 47 -33	; - "table"
	469	[345]	JMP      	6	; to 476
	470	[346]	MOVE     	47 38
	471	[346]	GETTABLE 	48 39 -11	; 1
	472	[346]	GETTABLE 	49 46 -11	; 1
	473	[346]	CALL     	47 3 2
	474	[346]	MOVE     	41 47
	475	[346]	JMP      	5	; to 481
	476	[348]	MOVE     	47 38
	477	[348]	MOVE     	48 39
	478	[348]	MOVE     	49 46
	479	[348]	CALL     	47 3 2
	480	[348]	MOVE     	41 47
	481	[350]	EQ       	0 39 46
	482	[350]	JMP      	2	; to 485
	483	[351]	MOVE     	36 45
	484	[352]	JMP      	41	; to 526
	485	[354]	LE       	0 41 40
	486	[354]	JMP      	2	; to 489
	487	[355]	MOVE     	40 41
	488	[356]	MOVE     	36 45
	489	[344]	TFORLOOP 	42 2
	490	[357]	JMP      	-26	; to 465
	491	[358]	JMP      	34	; to 526
	492	[364]	GETTABLE 	39 0 -12	; "options"
	493	[364]	GETTABLE 	39 39 17
	494	[364]	GETTABLE 	39 39 -70	; "args"
	495	[364]	TEST     	39 0 0
	496	[364]	JMP      	29	; to 526
	497	[366]	GETTABLE 	39 0 -12	; "options"
	498	[366]	GETTABLE 	39 39 17
	499	[366]	GETTABLE 	39 39 -68	; "current_func"
	500	[366]	TEST     	39 0 0
	501	[366]	JMP      	6	; to 508
	502	[366]	GETTABLE 	39 0 -12	; "options"
	503	[366]	GETTABLE 	39 39 17
	504	[366]	GETTABLE 	39 39 -68	; "current_func"
	505	[366]	CALL     	39 1 2
	506	[367]	TEST     	39 0 1
	507	[367]	JMP      	6	; to 514
	508	[367]	GETTABLE 	39 0 -46	; "config"
	509	[367]	GETTABLE 	39 39 -47	; "configurable"
	510	[367]	GETTABLE 	40 0 -12	; "options"
	511	[367]	GETTABLE 	40 40 17
	512	[367]	GETTABLE 	40 40 -66	; "name"
	513	[367]	GETTABLE 	39 39 40
	514	[368]	GETGLOBAL	40 -69	; pairs
	515	[368]	GETTABLE 	41 0 -12	; "options"
	516	[368]	GETTABLE 	41 41 17
	517	[368]	GETTABLE 	41 41 -70	; "args"
	518	[368]	CALL     	40 2 4
	519	[368]	JMP      	4	; to 524
	520	[369]	EQ       	0 44 39
	521	[369]	JMP      	2	; to 524
	522	[370]	MOVE     	36 43
	523	[371]	JMP      	2	; to 526
	524	[368]	TFORLOOP 	40 2
	525	[372]	JMP      	-6	; to 520
	526	[375]	GETTABLE 	39 0 -46	; "config"
	527	[375]	GETTABLE 	39 39 -71	; "config_options"
	528	[375]	GETTABLE 	39 39 -72	; "prefix"
	529	[375]	LOADK    	40 -73	; "_"
	530	[375]	GETTABLE 	41 0 -12	; "options"
	531	[375]	GETTABLE 	41 41 17
	532	[375]	GETTABLE 	41 41 -66	; "name"
	533	[375]	CONCAT   	39 39 41
	534	[376]	GETGLOBAL	40 -74	; G_reader_settings
	535	[376]	SELF     	40 40 -75	; "readSetting"
	536	[376]	MOVE     	42 39
	537	[376]	CALL     	40 3 2
	538	[377]	TEST     	40 0 0
	539	[377]	JMP      	63	; to 603
	540	[377]	GETTABLE 	41 0 -12	; "options"
	541	[377]	GETTABLE 	41 41 17
	542	[377]	GETTABLE 	41 41 -67	; "values"
	543	[377]	TEST     	41 0 0
	544	[377]	JMP      	58	; to 603
	545	[378]	MOVE     	41 40
	546	[379]	LOADNIL  	42 42
	547	[380]	GETGLOBAL	43 -62	; type
	548	[380]	MOVE     	44 41
	549	[380]	CALL     	43 2 2
	550	[380]	EQ       	0 43 -33	; - "table"
	551	[380]	JMP      	10	; to 562
	552	[381]	MOVE     	43 38
	553	[381]	GETTABLE 	44 41 -11	; 1
	554	[381]	GETTABLE 	45 0 -12	; "options"
	555	[381]	GETTABLE 	45 45 17
	556	[381]	GETTABLE 	45 45 -67	; "values"
	557	[381]	GETTABLE 	45 45 -11	; 1
	558	[381]	GETTABLE 	45 45 -11	; 1
	559	[381]	CALL     	43 3 2
	560	[381]	MOVE     	42 43
	561	[381]	JMP      	8	; to 570
	562	[383]	MOVE     	43 38
	563	[383]	MOVE     	44 41
	564	[383]	GETTABLE 	45 0 -12	; "options"
	565	[383]	GETTABLE 	45 45 17
	566	[383]	GETTABLE 	45 45 -67	; "values"
	567	[383]	GETTABLE 	45 45 -11	; 1
	568	[383]	CALL     	43 3 2
	569	[383]	MOVE     	42 43
	570	[386]	LOADNIL  	43 43
	571	[387]	GETGLOBAL	44 -69	; pairs
	572	[387]	GETTABLE 	45 0 -12	; "options"
	573	[387]	GETTABLE 	45 45 17
	574	[387]	GETTABLE 	45 45 -67	; "values"
	575	[387]	CALL     	44 2 4
	576	[387]	JMP      	24	; to 601
	577	[388]	GETGLOBAL	49 -62	; type
	578	[388]	MOVE     	50 41
	579	[388]	CALL     	49 2 2
	580	[388]	EQ       	0 49 -33	; - "table"
	581	[388]	JMP      	6	; to 588
	582	[389]	MOVE     	49 38
	583	[389]	GETTABLE 	50 41 -11	; 1
	584	[389]	GETTABLE 	51 48 -11	; 1
	585	[389]	CALL     	49 3 2
	586	[389]	MOVE     	43 49
	587	[389]	JMP      	5	; to 593
	588	[391]	MOVE     	49 38
	589	[391]	MOVE     	50 41
	590	[391]	MOVE     	51 48
	591	[391]	CALL     	49 3 2
	592	[391]	MOVE     	43 49
	593	[393]	EQ       	0 41 48
	594	[393]	JMP      	2	; to 597
	595	[394]	MOVE     	37 47
	596	[395]	JMP      	6	; to 603
	597	[397]	LE       	0 43 42
	598	[397]	JMP      	2	; to 601
	599	[398]	MOVE     	42 43
	600	[399]	MOVE     	37 47
	601	[387]	TFORLOOP 	44 2
	602	[400]	JMP      	-26	; to 577
	603	[408]	GETTABLE 	39 0 -12	; "options"
	604	[408]	GETTABLE 	39 39 17
	605	[408]	GETTABLE 	39 39 -76	; "item_text"
	606	[408]	TEST     	39 0 0
	607	[408]	JMP      	237	; to 845
	608	[409]	GETTABLE 	39 0 -12	; "options"
	609	[409]	GETTABLE 	39 39 17
	610	[409]	GETTABLE 	39 39 -76	; "item_text"
	611	[409]	LEN      	39 39
	612	[410]	LOADK    	40 -10	; 0
	613	[411]	LOADK    	41 -11	; 1
	614	[411]	GETTABLE 	42 0 -12	; "options"
	615	[411]	GETTABLE 	42 42 17
	616	[411]	GETTABLE 	42 42 -76	; "item_text"
	617	[411]	LEN      	42 42
	618	[411]	LOADK    	43 -11	; 1
	619	[411]	FORPREP  	41 29	; to 649
	620	[412]	GETUPVAL 	45 12	; OptionTextItem
	621	[412]	SELF     	45 45 -23	; "new"
	622	[412]	NEWTABLE 	47 0 0
	623	[413]	GETUPVAL 	48 2	; TextWidget
	624	[413]	SELF     	48 48 -23	; "new"
	625	[413]	NEWTABLE 	50 0 2
	626	[414]	GETTABLE 	51 0 -12	; "options"
	627	[414]	GETTABLE 	51 51 17
	628	[414]	GETTABLE 	51 51 -76	; "item_text"
	629	[414]	GETTABLE 	51 51 44
	630	[414]	SETTABLE 	50 -24 51	; "text" -
	631	[415]	GETUPVAL 	51 1	; Font
	632	[415]	SELF     	51 51 -21	; "getFace"
	633	[415]	MOVE     	53 24
	634	[416]	TEST     	34 0 0
	635	[416]	JMP      	3	; to 639
	636	[416]	GETTABLE 	54 25 44
	637	[417]	TEST     	54 0 1
	638	[417]	JMP      	1	; to 640
	639	[417]	MOVE     	54 25
	640	[415]	CALL     	51 4 2
	641	[417]	SETTABLE 	50 -25 51	; "face" -
	642	[413]	CALL     	48 3 0
	643	[419]	SETLIST  	47 0 1	; 1
	644	[412]	CALL     	45 3 2
	645	[420]	SELF     	46 45 -77	; "getSize"
	646	[420]	CALL     	46 2 2
	647	[420]	GETTABLE 	46 46 -51	; "w"
	648	[420]	ADD      	40 40 46
	649	[411]	FORLOOP  	41 -30	; to 620
	650	[422]	SUB      	41 31 40
	651	[422]	DIV      	41 41 39
	652	[423]	GETGLOBAL	42 -27	; math
	653	[423]	GETTABLE 	42 42 -31	; "min"
	654	[423]	MOVE     	43 41
	655	[423]	MOVE     	44 27
	656	[423]	CALL     	42 3 2
	657	[424]	DIV      	43 27 -29	; - 2
	658	[424]	LT       	0 41 43
	659	[424]	JMP      	1	; to 661
	660	[425]	DIV      	42 27 -29	; - 2
	661	[427]	DIV      	43 42 -29	; - 2
	662	[428]	MUL      	44 39 42
	663	[428]	SUB      	44 31 44
	664	[428]	DIV      	44 44 39
	665	[429]	LOADK    	45 -11	; 1
	666	[429]	GETTABLE 	46 0 -12	; "options"
	667	[429]	GETTABLE 	46 46 17
	668	[429]	GETTABLE 	46 46 -76	; "item_text"
	669	[429]	LEN      	46 46
	670	[429]	LOADK    	47 -11	; 1
	671	[429]	FORPREP  	45 172	; to 844
	672	[430]	LOADNIL  	49 49
	673	[431]	TEST     	34 0 0
	674	[431]	JMP      	66	; to 741
	675	[432]	GETUPVAL 	50 12	; OptionTextItem
	676	[432]	SELF     	50 50 -23	; "new"
	677	[432]	NEWTABLE 	52 1 5
	678	[433]	GETUPVAL 	53 13	; FixedTextWidget
	679	[433]	SELF     	53 53 -23	; "new"
	680	[433]	NEWTABLE 	55 0 3
	681	[434]	GETTABLE 	56 0 -12	; "options"
	682	[434]	GETTABLE 	56 56 17
	683	[434]	GETTABLE 	56 56 -76	; "item_text"
	684	[434]	GETTABLE 	56 56 48
	685	[434]	SETTABLE 	55 -24 56	; "text" -
	686	[435]	GETUPVAL 	56 1	; Font
	687	[435]	SELF     	56 56 -21	; "getFace"
	688	[435]	MOVE     	58 24
	689	[435]	GETTABLE 	59 25 48
	690	[435]	CALL     	56 4 2
	691	[435]	SETTABLE 	55 -25 56	; "face" -
	692	[436]	TEST     	28 0 0
	693	[436]	JMP      	4	; to 698
	694	[436]	GETUPVAL 	56 14	; Blitbuffer
	695	[436]	GETTABLE 	56 56 -79	; "COLOR_BLACK"
	696	[436]	TEST     	56 0 1
	697	[436]	JMP      	2	; to 700
	698	[436]	GETUPVAL 	56 14	; Blitbuffer
	699	[436]	GETTABLE 	56 56 -80	; "COLOR_DARK_GRAY"
	700	[436]	SETTABLE 	55 -78 56	; "fgcolor" -
	701	[433]	CALL     	53 3 2
	702	[438]	SETTABLE 	52 -81 8	; "underline_padding" -
	703	[439]	LT       	0 -11 48	; 1 -
	704	[439]	JMP      	2	; to 707
	705	[439]	MOVE     	54 43
	706	[439]	JMP      	2	; to 709
	707	[439]	LOADBOOL 	54 0 1
	708	[439]	LOADBOOL 	54 1 0
	709	[439]	SETTABLE 	52 -82 54	; "padding_left" -
	710	[440]	GETTABLE 	54 0 -12	; "options"
	711	[440]	GETTABLE 	54 54 17
	712	[440]	GETTABLE 	54 54 -76	; "item_text"
	713	[440]	LEN      	54 54
	714	[440]	LT       	0 48 54
	715	[440]	JMP      	2	; to 718
	716	[440]	MOVE     	54 43
	717	[440]	JMP      	2	; to 720
	718	[440]	LOADBOOL 	54 0 1
	719	[440]	LOADBOOL 	54 1 0
	720	[440]	SETTABLE 	52 -83 54	; "padding_right" -
	721	[441]	EQ       	0 48 36
	722	[441]	JMP      	10	; to 733
	723	[441]	TEST     	28 0 0
	724	[441]	JMP      	4	; to 729
	725	[441]	GETUPVAL 	54 14	; Blitbuffer
	726	[441]	GETTABLE 	54 54 -79	; "COLOR_BLACK"
	727	[441]	TEST     	54 0 1
	728	[441]	JMP      	6	; to 735
	729	[441]	GETUPVAL 	54 14	; Blitbuffer
	730	[441]	GETTABLE 	54 54 -80	; "COLOR_DARK_GRAY"
	731	[441]	TEST     	54 0 1
	732	[441]	JMP      	2	; to 735
	733	[441]	GETUPVAL 	54 14	; Blitbuffer
	734	[441]	GETTABLE 	54 54 -85	; "COLOR_WHITE"
	735	[441]	SETTABLE 	52 -84 54	; "color" -
	736	[442]	SETTABLE 	52 -55 28	; "enabled" -
	737	[443]	SETLIST  	52 1 1	; 1
	738	[432]	CALL     	50 3 2
	739	[443]	MOVE     	49 50
	740	[443]	JMP      	67	; to 808
	741	[445]	GETTABLE 	50 0 -12	; "options"
	742	[445]	GETTABLE 	50 50 17
	743	[445]	GETTABLE 	50 50 -76	; "item_text"
	744	[445]	GETTABLE 	50 50 48
	745	[446]	GETUPVAL 	51 1	; Font
	746	[446]	SELF     	51 51 -21	; "getFace"
	747	[446]	MOVE     	53 24
	748	[446]	MOVE     	54 25
	749	[446]	CALL     	51 4 2
	750	[447]	GETUPVAL 	52 12	; OptionTextItem
	751	[447]	SELF     	52 52 -23	; "new"
	752	[447]	NEWTABLE 	54 1 5
	753	[448]	GETUPVAL 	55 2	; TextWidget
	754	[448]	SELF     	55 55 -23	; "new"
	755	[448]	NEWTABLE 	57 0 4
	756	[449]	SETTABLE 	57 -24 50	; "text" -
	757	[450]	SETTABLE 	57 -53 44	; "max_width" -
	758	[451]	SETTABLE 	57 -25 51	; "face" -
	759	[452]	TEST     	28 0 0
	760	[452]	JMP      	4	; to 765
	761	[452]	GETUPVAL 	58 14	; Blitbuffer
	762	[452]	GETTABLE 	58 58 -79	; "COLOR_BLACK"
	763	[452]	TEST     	58 0 1
	764	[452]	JMP      	2	; to 767
	765	[452]	GETUPVAL 	58 14	; Blitbuffer
	766	[452]	GETTABLE 	58 58 -80	; "COLOR_DARK_GRAY"
	767	[452]	SETTABLE 	57 -78 58	; "fgcolor" -
	768	[448]	CALL     	55 3 2
	769	[454]	UNM      	56 8
	770	[454]	SETTABLE 	54 -81 56	; "underline_padding" -
	771	[455]	LT       	0 -11 48	; 1 -
	772	[455]	JMP      	2	; to 775
	773	[455]	MOVE     	56 43
	774	[455]	JMP      	2	; to 777
	775	[455]	LOADBOOL 	56 0 1
	776	[455]	LOADBOOL 	56 1 0
	777	[455]	SETTABLE 	54 -82 56	; "padding_left" -
	778	[456]	GETTABLE 	56 0 -12	; "options"
	779	[456]	GETTABLE 	56 56 17
	780	[456]	GETTABLE 	56 56 -76	; "item_text"
	781	[456]	LEN      	56 56
	782	[456]	LT       	0 48 56
	783	[456]	JMP      	2	; to 786
	784	[456]	MOVE     	56 43
	785	[456]	JMP      	2	; to 788
	786	[456]	LOADBOOL 	56 0 1
	787	[456]	LOADBOOL 	56 1 0
	788	[456]	SETTABLE 	54 -83 56	; "padding_right" -
	789	[457]	EQ       	0 48 36
	790	[457]	JMP      	10	; to 801
	791	[457]	TEST     	28 0 0
	792	[457]	JMP      	4	; to 797
	793	[457]	GETUPVAL 	56 14	; Blitbuffer
	794	[457]	GETTABLE 	56 56 -79	; "COLOR_BLACK"
	795	[457]	TEST     	56 0 1
	796	[457]	JMP      	6	; to 803
	797	[457]	GETUPVAL 	56 14	; Blitbuffer
	798	[457]	GETTABLE 	56 56 -80	; "COLOR_DARK_GRAY"
	799	[457]	TEST     	56 0 1
	800	[457]	JMP      	2	; to 803
	801	[457]	GETUPVAL 	56 14	; Blitbuffer
	802	[457]	GETTABLE 	56 56 -85	; "COLOR_WHITE"
	803	[457]	SETTABLE 	54 -84 56	; "color" -
	804	[458]	SETTABLE 	54 -55 28	; "enabled" -
	805	[459]	SETLIST  	54 1 1	; 1
	806	[447]	CALL     	52 3 2
	807	[459]	MOVE     	49 52
	808	[461]	SETTABLE 	35 48 49
	809	[462]	SETTABLE 	49 -86 35	; "items" -
	810	[463]	GETTABLE 	50 0 -12	; "options"
	811	[463]	GETTABLE 	50 50 17
	812	[463]	GETTABLE 	50 50 -66	; "name"
	813	[463]	SETTABLE 	49 -66 50	; "name" -
	814	[464]	GETTABLE 	50 0 -12	; "options"
	815	[464]	GETTABLE 	50 50 17
	816	[464]	GETTABLE 	50 50 -20	; "name_text"
	817	[464]	SETTABLE 	49 -20 50	; "name_text" -
	818	[465]	GETTABLE 	50 0 -12	; "options"
	819	[465]	GETTABLE 	50 50 17
	820	[465]	GETTABLE 	50 50 -76	; "item_text"
	821	[465]	SETTABLE 	49 -76 50	; "item_text" -
	822	[466]	GETTABLE 	50 0 -12	; "options"
	823	[466]	GETTABLE 	50 50 17
	824	[466]	GETTABLE 	50 50 -67	; "values"
	825	[466]	SETTABLE 	49 -67 50	; "values" -
	826	[467]	GETTABLE 	50 0 -12	; "options"
	827	[467]	GETTABLE 	50 50 17
	828	[467]	GETTABLE 	50 50 -70	; "args"
	829	[467]	SETTABLE 	49 -70 50	; "args" -
	830	[468]	GETTABLE 	50 0 -12	; "options"
	831	[468]	GETTABLE 	50 50 17
	832	[468]	GETTABLE 	50 50 -87	; "event"
	833	[468]	SETTABLE 	49 -87 50	; "event" -
	834	[469]	SETTABLE 	49 -88 48	; "current_item" -
	835	[470]	GETTABLE 	50 0 -46	; "config"
	836	[470]	SETTABLE 	49 -46 50	; "config" -
	837	[471]	GETTABLE 	50 0 -48	; "document"
	838	[471]	SETTABLE 	49 -48 50	; "document" -
	839	[472]	GETGLOBAL	50 -33	; table
	840	[472]	GETTABLE 	50 50 -34	; "insert"
	841	[472]	MOVE     	51 33
	842	[472]	MOVE     	52 49
	843	[472]	CALL     	50 3 1
	844	[429]	FORLOOP  	45 -173	; to 672
	845	[477]	GETTABLE 	39 0 -12	; "options"
	846	[477]	GETTABLE 	39 39 17
	847	[477]	GETTABLE 	39 39 -89	; "item_icons"
	848	[477]	TEST     	39 0 0
	849	[477]	JMP      	120	; to 970
	850	[478]	GETTABLE 	39 0 -12	; "options"
	851	[478]	GETTABLE 	39 39 17
	852	[478]	GETTABLE 	39 39 -89	; "item_icons"
	853	[478]	LEN      	39 39
	854	[479]	GETUPVAL 	40 15	; OptionIconItem
	855	[479]	SELF     	40 40 -23	; "new"
	856	[479]	NEWTABLE 	42 0 1
	857	[480]	GETUPVAL 	43 16	; ImageWidget
	858	[480]	SELF     	43 43 -23	; "new"
	859	[480]	NEWTABLE 	45 0 1
	860	[481]	GETTABLE 	46 0 -12	; "options"
	861	[481]	GETTABLE 	46 46 17
	862	[481]	GETTABLE 	46 46 -89	; "item_icons"
	863	[481]	GETTABLE 	46 46 -11	; 1
	864	[481]	SETTABLE 	45 -91 46	; "file" -
	865	[480]	CALL     	43 3 2
	866	[482]	SETTABLE 	42 -90 43	; "icon" -
	867	[479]	CALL     	40 3 2
	868	[485]	SELF     	41 40 -77	; "getSize"
	869	[485]	CALL     	41 2 2
	870	[485]	GETTABLE 	41 41 -51	; "w"
	871	[485]	MUL      	41 41 39
	872	[485]	SUB      	41 31 41
	873	[485]	DIV      	41 41 39
	874	[486]	GETGLOBAL	42 -27	; math
	875	[486]	GETTABLE 	42 42 -31	; "min"
	876	[486]	MOVE     	43 41
	877	[486]	MOVE     	44 27
	878	[486]	CALL     	42 3 2
	879	[486]	DIV      	42 42 -29	; - 2
	880	[487]	LOADK    	43 -11	; 1
	881	[487]	GETTABLE 	44 0 -12	; "options"
	882	[487]	GETTABLE 	44 44 17
	883	[487]	GETTABLE 	44 44 -89	; "item_icons"
	884	[487]	LEN      	44 44
	885	[487]	LOADK    	45 -11	; 1
	886	[487]	FORPREP  	43 82	; to 969
	887	[488]	GETUPVAL 	47 15	; OptionIconItem
	888	[488]	SELF     	47 47 -23	; "new"
	889	[488]	NEWTABLE 	49 0 6
	890	[489]	GETUPVAL 	50 16	; ImageWidget
	891	[489]	SELF     	50 50 -23	; "new"
	892	[489]	NEWTABLE 	52 0 2
	893	[490]	GETTABLE 	53 0 -12	; "options"
	894	[490]	GETTABLE 	53 53 17
	895	[490]	GETTABLE 	53 53 -89	; "item_icons"
	896	[490]	GETTABLE 	53 53 46
	897	[490]	SETTABLE 	52 -91 53	; "file" -
	898	[491]	NOT      	53 28
	899	[491]	SETTABLE 	52 -92 53	; "dim" -
	900	[489]	CALL     	50 3 2
	901	[492]	SETTABLE 	49 -90 50	; "icon" -
	902	[493]	UNM      	50 8
	903	[493]	SETTABLE 	49 -81 50	; "underline_padding" -
	904	[494]	LT       	0 -11 46	; 1 -
	905	[494]	JMP      	2	; to 908
	906	[494]	MOVE     	50 42
	907	[494]	JMP      	2	; to 910
	908	[494]	LOADBOOL 	50 0 1
	909	[494]	LOADBOOL 	50 1 0
	910	[494]	SETTABLE 	49 -82 50	; "padding_left" -
	911	[495]	GETTABLE 	50 0 -12	; "options"
	912	[495]	GETTABLE 	50 50 17
	913	[495]	GETTABLE 	50 50 -89	; "item_icons"
	914	[495]	LEN      	50 50
	915	[495]	LT       	0 46 50
	916	[495]	JMP      	2	; to 919
	917	[495]	MOVE     	50 42
	918	[495]	JMP      	2	; to 921
	919	[495]	LOADBOOL 	50 0 1
	920	[495]	LOADBOOL 	50 1 0
	921	[495]	SETTABLE 	49 -83 50	; "padding_right" -
	922	[496]	EQ       	0 46 36
	923	[496]	JMP      	10	; to 934
	924	[496]	TEST     	28 0 0
	925	[496]	JMP      	4	; to 930
	926	[496]	GETUPVAL 	50 14	; Blitbuffer
	927	[496]	GETTABLE 	50 50 -79	; "COLOR_BLACK"
	928	[496]	TEST     	50 0 1
	929	[496]	JMP      	6	; to 936
	930	[496]	GETUPVAL 	50 14	; Blitbuffer
	931	[496]	GETTABLE 	50 50 -80	; "COLOR_DARK_GRAY"
	932	[496]	TEST     	50 0 1
	933	[496]	JMP      	2	; to 936
	934	[496]	GETUPVAL 	50 14	; Blitbuffer
	935	[496]	GETTABLE 	50 50 -85	; "COLOR_WHITE"
	936	[496]	SETTABLE 	49 -84 50	; "color" -
	937	[497]	SETTABLE 	49 -55 28	; "enabled" -
	938	[488]	CALL     	47 3 2
	939	[499]	SETTABLE 	35 46 47
	940	[500]	SETTABLE 	47 -86 35	; "items" -
	941	[501]	GETTABLE 	48 0 -12	; "options"
	942	[501]	GETTABLE 	48 48 17
	943	[501]	GETTABLE 	48 48 -66	; "name"
	944	[501]	SETTABLE 	47 -66 48	; "name" -
	945	[502]	GETTABLE 	48 0 -12	; "options"
	946	[502]	GETTABLE 	48 48 17
	947	[502]	GETTABLE 	48 48 -20	; "name_text"
	948	[502]	SETTABLE 	47 -20 48	; "name_text" -
	949	[503]	GETTABLE 	48 0 -12	; "options"
	950	[503]	GETTABLE 	48 48 17
	951	[503]	GETTABLE 	48 48 -67	; "values"
	952	[503]	SETTABLE 	47 -67 48	; "values" -
	953	[504]	GETTABLE 	48 0 -12	; "options"
	954	[504]	GETTABLE 	48 48 17
	955	[504]	GETTABLE 	48 48 -70	; "args"
	956	[504]	SETTABLE 	47 -70 48	; "args" -
	957	[505]	GETTABLE 	48 0 -12	; "options"
	958	[505]	GETTABLE 	48 48 17
	959	[505]	GETTABLE 	48 48 -87	; "event"
	960	[505]	SETTABLE 	47 -87 48	; "event" -
	961	[506]	SETTABLE 	47 -88 46	; "current_item" -
	962	[507]	GETTABLE 	48 0 -46	; "config"
	963	[507]	SETTABLE 	47 -46 48	; "config" -
	964	[508]	GETGLOBAL	48 -33	; table
	965	[508]	GETTABLE 	48 48 -34	; "insert"
	966	[508]	MOVE     	49 33
	967	[508]	MOVE     	50 47
	968	[508]	CALL     	48 3 1
	969	[487]	FORLOOP  	43 -83	; to 887
	970	[513]	GETTABLE 	39 0 -12	; "options"
	971	[513]	GETTABLE 	39 39 17
	972	[513]	GETTABLE 	39 39 -93	; "toggle"
	973	[513]	TEST     	39 0 0
	974	[513]	JMP      	118	; to 1093
	975	[514]	MOVE     	39 31
	976	[515]	GETTABLE 	40 0 -12	; "options"
	977	[515]	GETTABLE 	40 40 17
	978	[515]	GETTABLE 	40 40 -35	; "width"
	979	[515]	TEST     	40 0 0
	980	[515]	JMP      	8	; to 989
	981	[515]	GETUPVAL 	40 3	; Screen
	982	[515]	SELF     	40 40 -40	; "scaleBySize"
	983	[515]	GETTABLE 	42 0 -12	; "options"
	984	[515]	GETTABLE 	42 42 17
	985	[515]	GETTABLE 	42 42 -35	; "width"
	986	[515]	CALL     	40 3 2
	987	[516]	TEST     	40 0 1
	988	[516]	JMP      	1	; to 990
	989	[516]	MOVE     	40 39
	990	[517]	GETTABLE 	41 0 -12	; "options"
	991	[517]	GETTABLE 	41 41 17
	992	[517]	GETTABLE 	41 41 -43	; "row_count"
	993	[517]	TEST     	41 0 1
	994	[517]	JMP      	1	; to 996
	995	[517]	LOADK    	41 -11	; 1
	996	[518]	GETUPVAL 	42 3	; Screen
	997	[518]	SELF     	42 42 -40	; "scaleBySize"
	998	[518]	GETTABLE 	44 0 -12	; "options"
	999	[518]	GETTABLE 	44 44 17
	1000	[519]	GETTABLE 	44 44 -41	; "height"
	1001	[519]	TEST     	44 0 1
	1002	[519]	JMP      	1	; to 1004
	1003	[519]	MUL      	44 -42 41	; 30 -
	1004	[518]	CALL     	42 3 2
	1005	[520]	GETTABLE 	43 0 -12	; "options"
	1006	[520]	GETTABLE 	43 43 17
	1007	[520]	GETTABLE 	43 43 -94	; "more_options"
	1008	[520]	TEST     	43 0 0
	1009	[520]	JMP      	17	; to 1027
	1010	[521]	GETGLOBAL	43 -33	; table
	1011	[521]	GETTABLE 	43 43 -34	; "insert"
	1012	[521]	GETTABLE 	44 0 -12	; "options"
	1013	[521]	GETTABLE 	44 44 17
	1014	[521]	GETTABLE 	44 44 -93	; "toggle"
	1015	[521]	LOADK    	45 -95	; "\226\139\174"
	1016	[521]	CALL     	43 3 1
	1017	[522]	GETGLOBAL	43 -33	; table
	1018	[522]	GETTABLE 	43 43 -34	; "insert"
	1019	[522]	GETTABLE 	44 0 -12	; "options"
	1020	[522]	GETTABLE 	44 44 17
	1021	[522]	GETTABLE 	44 44 -70	; "args"
	1022	[522]	LOADK    	45 -95	; "\226\139\174"
	1023	[522]	CALL     	43 3 1
	1024	[523]	GETTABLE 	43 0 -12	; "options"
	1025	[523]	GETTABLE 	43 43 17
	1026	[523]	SETTABLE 	43 -94 -16	; "more_options" false
	1027	[525]	GETUPVAL 	43 17	; ToggleSwitch
	1028	[525]	SELF     	43 43 -23	; "new"
	1029	[525]	NEWTABLE 	45 0 17
	1030	[526]	GETGLOBAL	46 -27	; math
	1031	[526]	GETTABLE 	46 46 -31	; "min"
	1032	[526]	MOVE     	47 39
	1033	[526]	MOVE     	48 40
	1034	[526]	CALL     	46 3 2
	1035	[526]	SETTABLE 	45 -35 46	; "width" -
	1036	[527]	SETTABLE 	45 -41 42	; "height" -
	1037	[528]	SETTABLE 	45 -96 24	; "font_face" -
	1038	[529]	SETTABLE 	45 -97 25	; "font_size" -
	1039	[530]	GETTABLE 	46 0 -12	; "options"
	1040	[530]	GETTABLE 	46 46 17
	1041	[530]	GETTABLE 	46 46 -66	; "name"
	1042	[530]	SETTABLE 	45 -66 46	; "name" -
	1043	[531]	GETTABLE 	46 0 -12	; "options"
	1044	[531]	GETTABLE 	46 46 17
	1045	[531]	GETTABLE 	46 46 -20	; "name_text"
	1046	[531]	SETTABLE 	45 -20 46	; "name_text" -
	1047	[532]	GETTABLE 	46 0 -12	; "options"
	1048	[532]	GETTABLE 	46 46 17
	1049	[532]	GETTABLE 	46 46 -93	; "toggle"
	1050	[532]	SETTABLE 	45 -93 46	; "toggle" -
	1051	[533]	GETTABLE 	46 0 -12	; "options"
	1052	[533]	GETTABLE 	46 46 17
	1053	[533]	GETTABLE 	46 46 -98	; "alternate"
	1054	[533]	SETTABLE 	45 -98 46	; "alternate" -
	1055	[534]	GETTABLE 	46 0 -12	; "options"
	1056	[534]	GETTABLE 	46 46 17
	1057	[534]	GETTABLE 	46 46 -67	; "values"
	1058	[534]	SETTABLE 	45 -67 46	; "values" -
	1059	[535]	GETTABLE 	46 0 -12	; "options"
	1060	[535]	GETTABLE 	46 46 17
	1061	[535]	GETTABLE 	46 46 -70	; "args"
	1062	[535]	SETTABLE 	45 -70 46	; "args" -
	1063	[536]	GETTABLE 	46 0 -12	; "options"
	1064	[536]	GETTABLE 	46 46 17
	1065	[536]	GETTABLE 	46 46 -87	; "event"
	1066	[536]	SETTABLE 	45 -87 46	; "event" -
	1067	[537]	GETTABLE 	46 0 -12	; "options"
	1068	[537]	GETTABLE 	46 46 17
	1069	[537]	GETTABLE 	46 46 -99	; "events"
	1070	[537]	SETTABLE 	45 -99 46	; "events" -
	1071	[538]	GETTABLE 	46 0 -12	; "options"
	1072	[538]	GETTABLE 	46 46 17
	1073	[538]	GETTABLE 	46 46 -100	; "delay_repaint"
	1074	[538]	SETTABLE 	45 -100 46	; "delay_repaint" -
	1075	[539]	GETTABLE 	46 0 -46	; "config"
	1076	[539]	SETTABLE 	45 -46 46	; "config" -
	1077	[540]	SETTABLE 	45 -55 28	; "enabled" -
	1078	[541]	SETTABLE 	45 -43 41	; "row_count" -
	1079	[550]	CLOSURE  	46 2	; 0x7f9102408730
	1080	[550]	MOVE     	0 0
	1081	[550]	MOVE     	0 17
	1082	[550]	SETTABLE 	45 -101 46	; "callback" -
	1083	[525]	CALL     	43 3 2
	1084	[552]	MOVE     	44 36
	1085	[553]	SELF     	45 43 -102	; "setPosition"
	1086	[553]	MOVE     	47 44
	1087	[553]	CALL     	45 3 1
	1088	[554]	GETGLOBAL	45 -33	; table
	1089	[554]	GETTABLE 	45 45 -34	; "insert"
	1090	[554]	MOVE     	46 33
	1091	[554]	MOVE     	47 43
	1092	[554]	CALL     	45 3 1
	1093	[558]	GETTABLE 	39 0 -12	; "options"
	1094	[558]	GETTABLE 	39 39 17
	1095	[558]	GETTABLE 	39 39 -103	; "buttonprogress"
	1096	[558]	TEST     	39 0 0
	1097	[558]	JMP      	80	; to 1178
	1098	[559]	MOVE     	39 31
	1099	[560]	GETTABLE 	40 0 -12	; "options"
	1100	[560]	GETTABLE 	40 40 17
	1101	[560]	GETTABLE 	40 40 -35	; "width"
	1102	[560]	TEST     	40 0 0
	1103	[560]	JMP      	8	; to 1112
	1104	[560]	GETUPVAL 	40 3	; Screen
	1105	[560]	SELF     	40 40 -40	; "scaleBySize"
	1106	[560]	GETTABLE 	42 0 -12	; "options"
	1107	[560]	GETTABLE 	42 42 17
	1108	[560]	GETTABLE 	42 42 -35	; "width"
	1109	[560]	CALL     	40 3 2
	1110	[561]	TEST     	40 0 1
	1111	[561]	JMP      	1	; to 1113
	1112	[561]	MOVE     	40 39
	1113	[562]	LOADNIL  	41 41
	1114	[563]	GETUPVAL 	42 18	; ButtonProgressWidget
	1115	[563]	SELF     	42 42 -23	; "new"
	1116	[563]	NEWTABLE 	44 0 16
	1117	[564]	GETGLOBAL	45 -27	; math
	1118	[564]	GETTABLE 	45 45 -31	; "min"
	1119	[564]	MOVE     	46 39
	1120	[564]	MOVE     	47 40
	1121	[564]	CALL     	45 3 2
	1122	[564]	SETTABLE 	44 -35 45	; "width" -
	1123	[565]	SETTABLE 	44 -41 26	; "height" -
	1124	[566]	SETTABLE 	44 -5 -10	; "padding" 0
	1125	[567]	SETTABLE 	44 -104 -105	; "thin_grey_style" true
	1126	[568]	SETTABLE 	44 -96 24	; "font_face" -
	1127	[569]	SETTABLE 	44 -97 25	; "font_size" -
	1128	[570]	GETTABLE 	45 0 -12	; "options"
	1129	[570]	GETTABLE 	45 45 17
	1130	[570]	GETTABLE 	45 45 -66	; "name"
	1131	[570]	SETTABLE 	44 -66 45	; "name" -
	1132	[571]	GETTABLE 	45 0 -12	; "options"
	1133	[571]	GETTABLE 	45 45 17
	1134	[571]	GETTABLE 	45 45 -67	; "values"
	1135	[571]	LEN      	45 45
	1136	[571]	SETTABLE 	44 -106 45	; "num_buttons" -
	1137	[572]	GETTABLE 	45 0 -12	; "options"
	1138	[572]	GETTABLE 	45 45 17
	1139	[572]	GETTABLE 	45 45 -65	; "default_pos"
	1140	[572]	SETTABLE 	44 -107 45	; "position" -
	1141	[587]	CLOSURE  	45 3	; 0x7f910240b180
	1142	[587]	MOVE     	0 0
	1143	[587]	MOVE     	0 17
	1144	[587]	GETUPVAL 	0 19	; UIManager
	1145	[587]	MOVE     	0 41
	1146	[587]	SETTABLE 	44 -101 45	; "callback" -
	1147	[596]	CLOSURE  	45 4	; 0x7f910240bd90
	1148	[596]	MOVE     	0 0
	1149	[596]	MOVE     	0 17
	1150	[596]	SETTABLE 	44 -61 45	; "hold_callback" -
	1151	[597]	GETTABLE 	45 0 -46	; "config"
	1152	[597]	SETTABLE 	44 -108 45	; "show_parrent" -
	1153	[598]	SETTABLE 	44 -55 28	; "enabled" -
	1154	[599]	GETTABLE 	45 0 -12	; "options"
	1155	[599]	GETTABLE 	45 45 17
	1156	[599]	GETTABLE 	45 45 -109	; "fine_tune"
	1157	[599]	SETTABLE 	44 -109 45	; "fine_tune" -
	1158	[600]	GETTABLE 	45 0 -12	; "options"
	1159	[600]	GETTABLE 	45 45 17
	1160	[600]	GETTABLE 	45 45 -94	; "more_options"
	1161	[600]	SETTABLE 	44 -94 45	; "more_options" -
	1162	[601]	GETTABLE 	45 0 -12	; "options"
	1163	[601]	GETTABLE 	45 45 17
	1164	[601]	GETTABLE 	45 45 -110	; "more_options_param"
	1165	[601]	SETTABLE 	44 -110 45	; "more_options_param" -
	1166	[563]	CALL     	42 3 2
	1167	[602]	MOVE     	41 42
	1168	[603]	SELF     	42 41 -102	; "setPosition"
	1169	[603]	MOVE     	44 36
	1170	[603]	MOVE     	45 37
	1171	[603]	CALL     	42 4 1
	1172	[604]	GETGLOBAL	42 -33	; table
	1173	[604]	GETTABLE 	42 42 -34	; "insert"
	1174	[604]	MOVE     	43 33
	1175	[604]	MOVE     	44 41
	1176	[604]	CALL     	42 3 1
	1177	[604]	CLOSE    	39
	1178	[608]	GETGLOBAL	39 -33	; table
	1179	[608]	GETTABLE 	39 39 -34	; "insert"
	1180	[608]	MOVE     	40 32
	1181	[608]	MOVE     	41 33
	1182	[608]	CALL     	39 3 1
	1183	[610]	GETGLOBAL	39 -33	; table
	1184	[610]	GETTABLE 	39 39 -34	; "insert"
	1185	[610]	GETTABLE 	40 0 -46	; "config"
	1186	[610]	GETTABLE 	40 40 -111	; "layout"
	1187	[610]	GETTABLE 	41 0 -46	; "config"
	1188	[610]	GETTABLE 	41 41 -111	; "layout"
	1189	[610]	LEN      	41 41
	1190	[610]	SELF     	42 0 -112	; "_itemGroupToLayoutLine"
	1191	[610]	MOVE     	44 33
	1192	[610]	CALL     	42 3 0
	1193	[610]	CALL     	39 0 1
	1194	[611]	GETGLOBAL	39 -33	; table
	1195	[611]	GETTABLE 	39 39 -34	; "insert"
	1196	[611]	MOVE     	40 29
	1197	[611]	MOVE     	41 32
	1198	[611]	CALL     	39 3 1
	1199	[612]	GETGLOBAL	39 -33	; table
	1200	[612]	GETTABLE 	39 39 -34	; "insert"
	1201	[612]	MOVE     	40 13
	1202	[612]	MOVE     	41 29
	1203	[612]	CALL     	39 3 1
	1204	[613]	CLOSE    	17
	1205	[234]	FORLOOP  	14 -1069	; to 137
	1206	[616]	GETGLOBAL	14 -33	; table
	1207	[616]	GETTABLE 	14 14 -34	; "insert"
	1208	[616]	MOVE     	15 13
	1209	[616]	GETUPVAL 	16 5	; VerticalSpan
	1210	[616]	SELF     	16 16 -23	; "new"
	1211	[616]	NEWTABLE 	18 0 1
	1212	[616]	SETTABLE 	18 -35 5	; "width" -
	1213	[616]	CALL     	16 3 0
	1214	[616]	CALL     	14 0 1
	1215	[617]	SETTABLE 	0 -11 13	; 1 -
	1216	[618]	SELF     	14 13 -77	; "getSize"
	1217	[618]	CALL     	14 2 2
	1218	[618]	SETTABLE 	0 -50 14	; "dimen" -
	1219	[619]	RETURN   	0 1

function <./frontend/ui/widget/configdialog.lua:288,293> (25 instructions, 100 bytes at 0x7f910240a2d0)
0 params, 4 slots, 2 upvalues, 0 locals, 6 constants, 0 functions
	1	[289]	GETUPVAL 	0 0	; self
	2	[289]	GETTABLE 	0 0 -1	; "options"
	3	[289]	GETUPVAL 	1 1	; c
	4	[289]	GETTABLE 	0 0 1
	5	[289]	GETTABLE 	0 0 -2	; "name_text_hold_callback"
	6	[289]	TEST     	0 0 0
	7	[289]	JMP      	17	; to 25
	8	[290]	GETUPVAL 	0 0	; self
	9	[290]	GETTABLE 	0 0 -1	; "options"
	10	[290]	GETUPVAL 	1 1	; c
	11	[290]	GETTABLE 	0 0 1
	12	[290]	GETTABLE 	0 0 -2	; "name_text_hold_callback"
	13	[290]	GETUPVAL 	1 0	; self
	14	[290]	GETTABLE 	1 1 -3	; "config"
	15	[290]	GETTABLE 	1 1 -4	; "configurable"
	16	[290]	GETUPVAL 	2 0	; self
	17	[290]	GETTABLE 	2 2 -1	; "options"
	18	[290]	GETUPVAL 	3 1	; c
	19	[290]	GETTABLE 	2 2 3
	20	[291]	GETUPVAL 	3 0	; self
	21	[291]	GETTABLE 	3 3 -3	; "config"
	22	[291]	GETTABLE 	3 3 -5	; "config_options"
	23	[291]	GETTABLE 	3 3 -6	; "prefix"
	24	[290]	CALL     	0 4 1
	25	[293]	RETURN   	0 1

function <./frontend/ui/widget/configdialog.lua:321,330> (36 instructions, 144 bytes at 0x7f910240b090)
3 params, 6 slots, 1 upvalue, 3 locals, 9 constants, 0 functions
	1	[322]	GETGLOBAL	3 -1	; type
	2	[322]	MOVE     	4 0
	3	[322]	CALL     	3 2 2
	4	[322]	GETGLOBAL	4 -1	; type
	5	[322]	MOVE     	5 1
	6	[322]	CALL     	4 2 2
	7	[322]	EQ       	1 3 4
	8	[322]	JMP      	4	; to 13
	9	[323]	GETUPVAL 	3 0	; logger
	10	[323]	GETTABLE 	3 3 -2	; "dbg"
	11	[323]	LOADK    	4 -3	; "different data types in option"
	12	[323]	CALL     	3 2 1
	13	[325]	GETGLOBAL	3 -1	; type
	14	[325]	MOVE     	4 0
	15	[325]	CALL     	3 2 2
	16	[325]	EQ       	0 3 -4	; - "number"
	17	[325]	JMP      	6	; to 24
	18	[326]	GETGLOBAL	3 -5	; math
	19	[326]	GETTABLE 	3 3 -6	; "abs"
	20	[326]	SUB      	4 0 1
	21	[326]	TAILCALL 	3 2 0
	22	[326]	RETURN   	3 0
	23	[326]	JMP      	12	; to 36
	24	[327]	GETGLOBAL	3 -1	; type
	25	[327]	MOVE     	4 0
	26	[327]	CALL     	3 2 2
	27	[327]	EQ       	0 3 -7	; - "string"
	28	[327]	JMP      	7	; to 36
	29	[328]	EQ       	0 0 1
	30	[328]	JMP      	3	; to 34
	31	[328]	LOADK    	3 -8	; 0
	32	[328]	TEST     	3 0 1
	33	[328]	JMP      	1	; to 35
	34	[328]	LOADK    	3 -9	; 1
	35	[328]	RETURN   	3 2
	36	[330]	RETURN   	0 1

function <./frontend/ui/widget/configdialog.lua:542,550> (70 instructions, 280 bytes at 0x7f9102408730)
1 param, 11 slots, 2 upvalues, 1 local, 12 constants, 0 functions
	1	[543]	GETUPVAL 	1 0	; self
	2	[543]	GETTABLE 	1 1 -1	; "options"
	3	[543]	GETUPVAL 	2 1	; c
	4	[543]	GETTABLE 	1 1 2
	5	[543]	GETTABLE 	1 1 -2	; "toggle"
	6	[543]	GETTABLE 	1 1 0
	7	[543]	EQ       	0 1 -3	; - "\226\139\174"
	8	[543]	JMP      	61	; to 70
	9	[544]	GETUPVAL 	1 0	; self
	10	[544]	GETTABLE 	1 1 -1	; "options"
	11	[544]	GETUPVAL 	2 1	; c
	12	[544]	GETTABLE 	1 1 2
	13	[544]	GETTABLE 	1 1 -4	; "show_true_value_func"
	14	[544]	TEST     	1 0 0
	15	[544]	JMP      	19	; to 35
	16	[544]	GETUPVAL 	1 0	; self
	17	[544]	GETTABLE 	1 1 -1	; "options"
	18	[544]	GETUPVAL 	2 1	; c
	19	[544]	GETTABLE 	1 1 2
	20	[544]	GETTABLE 	1 1 -5	; "more_options_param"
	21	[544]	GETTABLE 	1 1 -4	; "show_true_value_func"
	22	[544]	TEST     	1 0 1
	23	[544]	JMP      	11	; to 35
	24	[545]	GETUPVAL 	1 0	; self
	25	[545]	GETTABLE 	1 1 -1	; "options"
	26	[545]	GETUPVAL 	2 1	; c
	27	[545]	GETTABLE 	1 1 2
	28	[545]	GETTABLE 	1 1 -5	; "more_options_param"
	29	[545]	GETUPVAL 	2 0	; self
	30	[545]	GETTABLE 	2 2 -1	; "options"
	31	[545]	GETUPVAL 	3 1	; c
	32	[545]	GETTABLE 	2 2 3
	33	[545]	GETTABLE 	2 2 -4	; "show_true_value_func"
	34	[545]	SETTABLE 	1 -4 2	; "show_true_value_func" -
	35	[547]	GETUPVAL 	1 0	; self
	36	[547]	GETTABLE 	1 1 -6	; "config"
	37	[547]	SELF     	1 1 -7	; "onConfigMoreChoose"
	38	[547]	GETUPVAL 	3 0	; self
	39	[547]	GETTABLE 	3 3 -1	; "options"
	40	[547]	GETUPVAL 	4 1	; c
	41	[547]	GETTABLE 	3 3 4
	42	[547]	GETTABLE 	3 3 -8	; "values"
	43	[547]	GETUPVAL 	4 0	; self
	44	[547]	GETTABLE 	4 4 -1	; "options"
	45	[547]	GETUPVAL 	5 1	; c
	46	[547]	GETTABLE 	4 4 5
	47	[547]	GETTABLE 	4 4 -9	; "name"
	48	[548]	GETUPVAL 	5 0	; self
	49	[548]	GETTABLE 	5 5 -1	; "options"
	50	[548]	GETUPVAL 	6 1	; c
	51	[548]	GETTABLE 	5 5 6
	52	[548]	GETTABLE 	5 5 -10	; "event"
	53	[548]	MOVE     	6 0
	54	[548]	GETUPVAL 	7 0	; self
	55	[548]	GETTABLE 	7 7 -1	; "options"
	56	[548]	GETUPVAL 	8 1	; c
	57	[548]	GETTABLE 	7 7 8
	58	[548]	GETTABLE 	7 7 -11	; "name_text"
	59	[548]	GETUPVAL 	8 0	; self
	60	[548]	GETTABLE 	8 8 -1	; "options"
	61	[548]	GETUPVAL 	9 1	; c
	62	[548]	GETTABLE 	8 8 9
	63	[548]	GETTABLE 	8 8 -12	; "delay_repaint"
	64	[548]	GETUPVAL 	9 0	; self
	65	[548]	GETTABLE 	9 9 -1	; "options"
	66	[548]	GETUPVAL 	10 1	; c
	67	[548]	GETTABLE 	9 9 10
	68	[548]	GETTABLE 	9 9 -5	; "more_options_param"
	69	[547]	CALL     	1 9 1
	70	[550]	RETURN   	0 1

function <./frontend/ui/widget/configdialog.lua:573,587> (121 instructions, 484 bytes at 0x7f910240b180)
1 param, 11 slots, 4 upvalues, 1 local, 17 constants, 1 function
	1	[574]	EQ       	1 0 -1	; - "-"
	2	[574]	JMP      	2	; to 5
	3	[574]	EQ       	0 0 -2	; - "+"
	4	[574]	JMP      	36	; to 41
	5	[575]	GETUPVAL 	1 0	; self
	6	[575]	GETTABLE 	1 1 -3	; "config"
	7	[575]	SELF     	1 1 -4	; "onConfigFineTuneChoose"
	8	[575]	GETUPVAL 	3 0	; self
	9	[575]	GETTABLE 	3 3 -5	; "options"
	10	[575]	GETUPVAL 	4 1	; c
	11	[575]	GETTABLE 	3 3 4
	12	[575]	GETTABLE 	3 3 -6	; "values"
	13	[575]	GETUPVAL 	4 0	; self
	14	[575]	GETTABLE 	4 4 -5	; "options"
	15	[575]	GETUPVAL 	5 1	; c
	16	[575]	GETTABLE 	4 4 5
	17	[575]	GETTABLE 	4 4 -7	; "name"
	18	[576]	GETUPVAL 	5 0	; self
	19	[576]	GETTABLE 	5 5 -5	; "options"
	20	[576]	GETUPVAL 	6 1	; c
	21	[576]	GETTABLE 	5 5 6
	22	[576]	GETTABLE 	5 5 -8	; "event"
	23	[576]	GETUPVAL 	6 0	; self
	24	[576]	GETTABLE 	6 6 -5	; "options"
	25	[576]	GETUPVAL 	7 1	; c
	26	[576]	GETTABLE 	6 6 7
	27	[576]	GETTABLE 	6 6 -9	; "args"
	28	[576]	GETUPVAL 	7 0	; self
	29	[576]	GETTABLE 	7 7 -5	; "options"
	30	[576]	GETUPVAL 	8 1	; c
	31	[576]	GETTABLE 	7 7 8
	32	[576]	GETTABLE 	7 7 -10	; "events"
	33	[576]	MOVE     	8 0
	34	[576]	GETUPVAL 	9 0	; self
	35	[576]	GETTABLE 	9 9 -5	; "options"
	36	[576]	GETUPVAL 	10 1	; c
	37	[576]	GETTABLE 	9 9 10
	38	[576]	GETTABLE 	9 9 -11	; "delay_repaint"
	39	[575]	CALL     	1 9 1
	40	[576]	JMP      	73	; to 114
	41	[577]	EQ       	0 0 -12	; - "\226\139\174"
	42	[577]	JMP      	36	; to 79
	43	[578]	GETUPVAL 	1 0	; self
	44	[578]	GETTABLE 	1 1 -3	; "config"
	45	[578]	SELF     	1 1 -13	; "onConfigMoreChoose"
	46	[578]	GETUPVAL 	3 0	; self
	47	[578]	GETTABLE 	3 3 -5	; "options"
	48	[578]	GETUPVAL 	4 1	; c
	49	[578]	GETTABLE 	3 3 4
	50	[578]	GETTABLE 	3 3 -6	; "values"
	51	[578]	GETUPVAL 	4 0	; self
	52	[578]	GETTABLE 	4 4 -5	; "options"
	53	[578]	GETUPVAL 	5 1	; c
	54	[578]	GETTABLE 	4 4 5
	55	[578]	GETTABLE 	4 4 -7	; "name"
	56	[579]	GETUPVAL 	5 0	; self
	57	[579]	GETTABLE 	5 5 -5	; "options"
	58	[579]	GETUPVAL 	6 1	; c
	59	[579]	GETTABLE 	5 5 6
	60	[579]	GETTABLE 	5 5 -8	; "event"
	61	[579]	MOVE     	6 0
	62	[579]	GETUPVAL 	7 0	; self
	63	[579]	GETTABLE 	7 7 -5	; "options"
	64	[579]	GETUPVAL 	8 1	; c
	65	[579]	GETTABLE 	7 7 8
	66	[579]	GETTABLE 	7 7 -14	; "name_text"
	67	[579]	GETUPVAL 	8 0	; self
	68	[579]	GETTABLE 	8 8 -5	; "options"
	69	[579]	GETUPVAL 	9 1	; c
	70	[579]	GETTABLE 	8 8 9
	71	[579]	GETTABLE 	8 8 -11	; "delay_repaint"
	72	[579]	GETUPVAL 	9 0	; self
	73	[579]	GETTABLE 	9 9 -5	; "options"
	74	[579]	GETUPVAL 	10 1	; c
	75	[579]	GETTABLE 	9 9 10
	76	[579]	GETTABLE 	9 9 -15	; "more_options_param"
	77	[578]	CALL     	1 9 1
	78	[579]	JMP      	35	; to 114
	79	[581]	GETUPVAL 	1 0	; self
	80	[581]	GETTABLE 	1 1 -3	; "config"
	81	[581]	SELF     	1 1 -16	; "onConfigChoose"
	82	[581]	GETUPVAL 	3 0	; self
	83	[581]	GETTABLE 	3 3 -5	; "options"
	84	[581]	GETUPVAL 	4 1	; c
	85	[581]	GETTABLE 	3 3 4
	86	[581]	GETTABLE 	3 3 -6	; "values"
	87	[581]	GETUPVAL 	4 0	; self
	88	[581]	GETTABLE 	4 4 -5	; "options"
	89	[581]	GETUPVAL 	5 1	; c
	90	[581]	GETTABLE 	4 4 5
	91	[581]	GETTABLE 	4 4 -7	; "name"
	92	[582]	GETUPVAL 	5 0	; self
	93	[582]	GETTABLE 	5 5 -5	; "options"
	94	[582]	GETUPVAL 	6 1	; c
	95	[582]	GETTABLE 	5 5 6
	96	[582]	GETTABLE 	5 5 -8	; "event"
	97	[582]	GETUPVAL 	6 0	; self
	98	[582]	GETTABLE 	6 6 -5	; "options"
	99	[582]	GETUPVAL 	7 1	; c
	100	[582]	GETTABLE 	6 6 7
	101	[582]	GETTABLE 	6 6 -9	; "args"
	102	[582]	GETUPVAL 	7 0	; self
	103	[582]	GETTABLE 	7 7 -5	; "options"
	104	[582]	GETUPVAL 	8 1	; c
	105	[582]	GETTABLE 	7 7 8
	106	[582]	GETTABLE 	7 7 -10	; "events"
	107	[582]	MOVE     	8 0
	108	[582]	GETUPVAL 	9 0	; self
	109	[582]	GETTABLE 	9 9 -5	; "options"
	110	[582]	GETUPVAL 	10 1	; c
	111	[582]	GETTABLE 	9 9 10
	112	[582]	GETTABLE 	9 9 -11	; "delay_repaint"
	113	[581]	CALL     	1 9 1
	114	[584]	GETUPVAL 	1 2	; UIManager
	115	[584]	SELF     	1 1 -17	; "setDirty"
	116	[584]	GETUPVAL 	3 0	; self
	117	[584]	GETTABLE 	3 3 -3	; "config"
	118	[586]	CLOSURE  	4 0	; 0x7f910240c380
	119	[586]	GETUPVAL 	0 3	; switch
	120	[584]	CALL     	1 4 1
	121	[587]	RETURN   	0 1

function <./frontend/ui/widget/configdialog.lua:584,586> (5 instructions, 20 bytes at 0x7f910240c380)
0 params, 2 slots, 1 upvalue, 0 locals, 2 constants, 0 functions
	1	[585]	LOADK    	0 -1	; "fast"
	2	[585]	GETUPVAL 	1 0	; switch
	3	[585]	GETTABLE 	1 1 -2	; "dimen"
	4	[585]	RETURN   	0 3
	5	[586]	RETURN   	0 1

function <./frontend/ui/widget/configdialog.lua:588,596> (72 instructions, 288 bytes at 0x7f910240bd90)
1 param, 8 slots, 2 upvalues, 1 local, 12 constants, 0 functions
	1	[589]	EQ       	1 0 -1	; - "-"
	2	[589]	JMP      	2	; to 5
	3	[589]	EQ       	0 0 -2	; - "+"
	4	[589]	JMP      	33	; to 38
	5	[590]	GETUPVAL 	1 0	; self
	6	[590]	GETTABLE 	1 1 -3	; "config"
	7	[590]	SELF     	1 1 -4	; "onMakeFineTuneDefault"
	8	[590]	GETUPVAL 	3 0	; self
	9	[590]	GETTABLE 	3 3 -5	; "options"
	10	[590]	GETUPVAL 	4 1	; c
	11	[590]	GETTABLE 	3 3 4
	12	[590]	GETTABLE 	3 3 -6	; "name"
	13	[590]	GETUPVAL 	4 0	; self
	14	[590]	GETTABLE 	4 4 -5	; "options"
	15	[590]	GETUPVAL 	5 1	; c
	16	[590]	GETTABLE 	4 4 5
	17	[590]	GETTABLE 	4 4 -7	; "name_text"
	18	[590]	GETUPVAL 	5 0	; self
	19	[590]	GETTABLE 	5 5 -5	; "options"
	20	[590]	GETUPVAL 	6 1	; c
	21	[590]	GETTABLE 	5 5 6
	22	[590]	GETTABLE 	5 5 -8	; "values"
	23	[591]	GETUPVAL 	6 0	; self
	24	[591]	GETTABLE 	6 6 -5	; "options"
	25	[591]	GETUPVAL 	7 1	; c
	26	[591]	GETTABLE 	6 6 7
	27	[591]	GETTABLE 	6 6 -9	; "labels"
	28	[591]	TEST     	6 0 1
	29	[591]	JMP      	5	; to 35
	30	[591]	GETUPVAL 	6 0	; self
	31	[591]	GETTABLE 	6 6 -5	; "options"
	32	[591]	GETUPVAL 	7 1	; c
	33	[591]	GETTABLE 	6 6 7
	34	[591]	GETTABLE 	6 6 -10	; "args"
	35	[591]	MOVE     	7 0
	36	[590]	CALL     	1 7 1
	37	[591]	JMP      	34	; to 72
	38	[592]	EQ       	1 0 -11	; - "\226\139\174"
	39	[592]	JMP      	32	; to 72
	40	[593]	GETUPVAL 	1 0	; self
	41	[593]	GETTABLE 	1 1 -3	; "config"
	42	[593]	SELF     	1 1 -12	; "onMakeDefault"
	43	[593]	GETUPVAL 	3 0	; self
	44	[593]	GETTABLE 	3 3 -5	; "options"
	45	[593]	GETUPVAL 	4 1	; c
	46	[593]	GETTABLE 	3 3 4
	47	[593]	GETTABLE 	3 3 -6	; "name"
	48	[593]	GETUPVAL 	4 0	; self
	49	[593]	GETTABLE 	4 4 -5	; "options"
	50	[593]	GETUPVAL 	5 1	; c
	51	[593]	GETTABLE 	4 4 5
	52	[593]	GETTABLE 	4 4 -7	; "name_text"
	53	[593]	GETUPVAL 	5 0	; self
	54	[593]	GETTABLE 	5 5 -5	; "options"
	55	[593]	GETUPVAL 	6 1	; c
	56	[593]	GETTABLE 	5 5 6
	57	[593]	GETTABLE 	5 5 -8	; "values"
	58	[594]	GETUPVAL 	6 0	; self
	59	[594]	GETTABLE 	6 6 -5	; "options"
	60	[594]	GETUPVAL 	7 1	; c
	61	[594]	GETTABLE 	6 6 7
	62	[594]	GETTABLE 	6 6 -9	; "labels"
	63	[594]	TEST     	6 0 1
	64	[594]	JMP      	5	; to 70
	65	[594]	GETUPVAL 	6 0	; self
	66	[594]	GETTABLE 	6 6 -5	; "options"
	67	[594]	GETUPVAL 	7 1	; c
	68	[594]	GETTABLE 	6 6 7
	69	[594]	GETTABLE 	6 6 -10	; "args"
	70	[594]	MOVE     	7 0
	71	[593]	CALL     	1 7 1
	72	[596]	RETURN   	0 1

function <./frontend/ui/widget/configdialog.lua:621,634> (16 instructions, 64 bytes at 0x7f910240cc60)
2 params, 10 slots, 0 upvalues, 9 locals, 5 constants, 0 functions
	1	[622]	NEWTABLE 	2 0 0
	2	[626]	GETTABLE 	3 0 -1	; "config"
	3	[626]	GETTABLE 	3 3 -2	; "panel_index"
	4	[627]	GETGLOBAL	4 -3	; ipairs
	5	[627]	MOVE     	5 1
	6	[627]	CALL     	4 2 4
	7	[627]	JMP      	5	; to 13
	8	[628]	GETTABLE 	9 8 -4	; "name"
	9	[628]	TEST     	9 0 0
	10	[628]	JMP      	2	; to 13
	11	[629]	SETTABLE 	2 3 8
	12	[630]	ADD      	3 3 -5	; - 1
	13	[627]	TFORLOOP 	4 2
	14	[631]	JMP      	-7	; to 8
	15	[633]	RETURN   	2 2
	16	[634]	RETURN   	0 1

function <./frontend/ui/widget/configdialog.lua:641,652> (37 instructions, 148 bytes at 0x7f910240d550)
1 param, 7 slots, 1 upvalue, 4 locals, 13 constants, 0 functions
	1	[642]	GETTABLE 	1 0 -1	; "config_dialog"
	2	[642]	GETTABLE 	1 1 -2	; "config_options"
	3	[643]	GETTABLE 	2 1 -3	; "default_options"
	4	[643]	TEST     	2 0 0
	5	[643]	JMP      	3	; to 9
	6	[643]	GETTABLE 	2 1 -3	; "default_options"
	7	[644]	TEST     	2 0 1
	8	[644]	JMP      	2	; to 11
	9	[644]	GETTABLE 	2 1 -4	; 1
	10	[644]	GETTABLE 	2 2 -5	; "options"
	11	[645]	GETUPVAL 	3 0	; ConfigOption
	12	[645]	SELF     	3 3 -6	; "new"
	13	[645]	NEWTABLE 	5 0 3
	14	[646]	GETTABLE 	6 0 -7	; "index"
	15	[646]	TEST     	6 0 0
	16	[646]	JMP      	5	; to 22
	17	[646]	GETTABLE 	6 0 -7	; "index"
	18	[646]	GETTABLE 	6 1 6
	19	[646]	GETTABLE 	6 6 -5	; "options"
	20	[646]	TEST     	6 0 1
	21	[646]	JMP      	1	; to 23
	22	[646]	MOVE     	6 2
	23	[646]	SETTABLE 	5 -5 6	; "options" -
	24	[647]	GETTABLE 	6 0 -1	; "config_dialog"
	25	[647]	SETTABLE 	5 -8 6	; "config" -
	26	[648]	GETTABLE 	6 0 -9	; "document"
	27	[648]	SETTABLE 	5 -9 6	; "document" -
	28	[645]	CALL     	3 3 2
	29	[650]	SELF     	4 3 -11	; "getSize"
	30	[650]	CALL     	4 2 2
	31	[650]	SETTABLE 	0 -10 4	; "dimen" -
	32	[651]	GETGLOBAL	4 -12	; table
	33	[651]	GETTABLE 	4 4 -13	; "insert"
	34	[651]	MOVE     	5 0
	35	[651]	MOVE     	6 3
	36	[651]	CALL     	4 3 1
	37	[652]	RETURN   	0 1

function <./frontend/ui/widget/configdialog.lua:659,768> (296 instructions, 1184 bytes at 0x7f910240d8c0)
1 param, 33 slots, 10 upvalues, 33 locals, 40 constants, 1 function
	1	[660]	GETUPVAL 	1 0	; Size
	2	[660]	GETTABLE 	1 1 -1	; "padding"
	3	[660]	GETTABLE 	1 1 -2	; "button"
	4	[661]	GETUPVAL 	2 0	; Size
	5	[661]	GETTABLE 	2 2 -3	; "line"
	6	[661]	GETTABLE 	2 2 -4	; "thick"
	7	[662]	GETTABLE 	3 0 -5	; "config_dialog"
	8	[662]	GETTABLE 	3 3 -6	; "config_options"
	9	[663]	NEWTABLE 	4 0 0
	10	[664]	GETUPVAL 	5 1	; Screen
	11	[664]	SELF     	5 5 -7	; "scaleBySize"
	12	[664]	LOADK    	7 -8	; 40
	13	[664]	CALL     	5 3 2
	14	[665]	MOVE     	6 5
	15	[666]	MUL      	7 -9 1	; 2 -
	16	[666]	ADD      	7 5 7
	17	[666]	LEN      	8 3
	18	[666]	MUL      	7 7 8
	19	[667]	MOVE     	8 6
	20	[668]	LOADK    	9 -10	; 1
	21	[668]	LEN      	10 3
	22	[668]	LOADK    	11 -10	; 1
	23	[668]	FORPREP  	9 19	; to 43
	24	[669]	GETUPVAL 	13 2	; IconButton
	25	[669]	SELF     	13 13 -11	; "new"
	26	[669]	NEWTABLE 	15 0 6
	27	[670]	GETTABLE 	16 0 -5	; "config_dialog"
	28	[670]	SETTABLE 	15 -12 16	; "show_parent" -
	29	[671]	GETTABLE 	16 3 12
	30	[671]	GETTABLE 	16 16 -14	; "icon"
	31	[671]	SETTABLE 	15 -13 16	; "icon_file" -
	32	[672]	SETTABLE 	15 -15 5	; "width" -
	33	[673]	SETTABLE 	15 -16 6	; "height" -
	34	[674]	SETTABLE 	15 -17 -18	; "scale_for_dpi" false
	35	[677]	CLOSURE  	16 0	; 0x7f910240dee0
	36	[677]	MOVE     	0 0
	37	[677]	GETUPVAL 	0 3	; Event
	38	[677]	MOVE     	0 12
	39	[677]	SETTABLE 	15 -19 16	; "callback" -
	40	[669]	CALL     	13 3 2
	41	[679]	SETTABLE 	4 12 13
	42	[679]	CLOSE    	12
	43	[668]	FORLOOP  	9 -20	; to 24
	44	[681]	GETGLOBAL	9 -20	; table
	45	[681]	GETTABLE 	9 9 -21	; "insert"
	46	[681]	GETTABLE 	10 0 -5	; "config_dialog"
	47	[681]	GETTABLE 	10 10 -22	; "layout"
	48	[681]	MOVE     	11 4
	49	[681]	CALL     	9 3 1
	50	[682]	GETUPVAL 	9 1	; Screen
	51	[682]	SELF     	9 9 -23	; "getWidth"
	52	[682]	CALL     	9 2 2
	53	[682]	SUB      	9 9 7
	54	[685]	GETGLOBAL	10 -24	; math
	55	[685]	GETTABLE 	10 10 -25	; "min"
	56	[685]	GETGLOBAL	11 -24	; math
	57	[685]	GETTABLE 	11 11 -26	; "floor"
	58	[685]	LEN      	12 4
	59	[685]	DIV      	12 9 12
	60	[685]	DIV      	12 12 -9	; - 2
	61	[685]	CALL     	11 2 2
	62	[685]	GETUPVAL 	12 1	; Screen
	63	[685]	SELF     	12 12 -7	; "scaleBySize"
	64	[685]	LOADK    	14 -27	; 20
	65	[685]	CALL     	12 3 0
	66	[685]	CALL     	10 0 2
	67	[686]	LT       	0 -28 10	; 0 -
	68	[686]	JMP      	16	; to 85
	69	[687]	LOADK    	11 -10	; 1
	70	[687]	LEN      	12 4
	71	[687]	LOADK    	13 -10	; 1
	72	[687]	FORPREP  	11 7	; to 80
	73	[688]	GETTABLE 	15 4 14
	74	[688]	SETTABLE 	15 -29 10	; "padding_left" -
	75	[689]	GETTABLE 	15 4 14
	76	[689]	SETTABLE 	15 -30 10	; "padding_right" -
	77	[690]	GETTABLE 	15 4 14
	78	[690]	SELF     	15 15 -31	; "update"
	79	[690]	CALL     	15 2 1
	80	[687]	FORLOOP  	11 -8	; to 73
	81	[692]	MUL      	11 -9 10	; 2 -
	82	[692]	LEN      	12 4
	83	[692]	MUL      	11 11 12
	84	[692]	SUB      	9 9 11
	85	[694]	GETGLOBAL	11 -24	; math
	86	[694]	GETTABLE 	11 11 -32	; "ceil"
	87	[694]	LEN      	12 4
	88	[694]	ADD      	12 12 -10	; - 1
	89	[694]	DIV      	12 9 12
	90	[694]	CALL     	11 2 2
	91	[696]	GETUPVAL 	12 4	; LineWidget
	92	[696]	SELF     	12 12 -11	; "new"
	93	[696]	NEWTABLE 	14 0 2
	94	[697]	GETUPVAL 	15 5	; Blitbuffer
	95	[697]	GETTABLE 	15 15 -34	; "COLOR_BLACK"
	96	[697]	SETTABLE 	14 -33 15	; "background" -
	97	[698]	GETUPVAL 	15 6	; Geom
	98	[698]	SELF     	15 15 -11	; "new"
	99	[698]	NEWTABLE 	17 0 2
	100	[699]	SETTABLE 	17 -36 1	; "w" -
	101	[700]	SETTABLE 	17 -37 8	; "h" -
	102	[698]	CALL     	15 3 2
	103	[701]	SETTABLE 	14 -35 15	; "dimen" -
	104	[696]	CALL     	12 3 2
	105	[703]	GETUPVAL 	13 4	; LineWidget
	106	[703]	SELF     	13 13 -11	; "new"
	107	[703]	NEWTABLE 	15 0 2
	108	[704]	GETUPVAL 	16 5	; Blitbuffer
	109	[704]	GETTABLE 	16 16 -38	; "COLOR_WHITE"
	110	[704]	SETTABLE 	15 -33 16	; "background" -
	111	[705]	GETUPVAL 	16 6	; Geom
	112	[705]	SELF     	16 16 -11	; "new"
	113	[705]	NEWTABLE 	18 0 2
	114	[706]	SETTABLE 	18 -36 1	; "w" -
	115	[707]	SETTABLE 	18 -37 8	; "h" -
	116	[705]	CALL     	16 3 2
	117	[708]	SETTABLE 	15 -35 16	; "dimen" -
	118	[703]	CALL     	13 3 2
	119	[710]	GETUPVAL 	14 7	; HorizontalSpan
	120	[710]	SELF     	14 14 -11	; "new"
	121	[710]	NEWTABLE 	16 0 1
	122	[711]	SETTABLE 	16 -15 11	; "width" -
	123	[710]	CALL     	14 3 2
	124	[713]	GETUPVAL 	15 4	; LineWidget
	125	[713]	SELF     	15 15 -11	; "new"
	126	[713]	NEWTABLE 	17 0 1
	127	[714]	GETUPVAL 	18 6	; Geom
	128	[714]	SELF     	18 18 -11	; "new"
	129	[714]	NEWTABLE 	20 0 2
	130	[715]	SETTABLE 	20 -36 11	; "w" -
	131	[716]	SETTABLE 	20 -37 2	; "h" -
	132	[714]	CALL     	18 3 2
	133	[717]	SETTABLE 	17 -35 18	; "dimen" -
	134	[713]	CALL     	15 3 2
	135	[719]	GETUPVAL 	16 4	; LineWidget
	136	[719]	SELF     	16 16 -11	; "new"
	137	[719]	NEWTABLE 	18 0 1
	138	[720]	GETUPVAL 	19 6	; Geom
	139	[720]	SELF     	19 19 -11	; "new"
	140	[720]	NEWTABLE 	21 0 2
	141	[721]	SETTABLE 	21 -36 1	; "w" -
	142	[722]	SETTABLE 	21 -37 2	; "h" -
	143	[720]	CALL     	19 3 2
	144	[723]	SETTABLE 	18 -35 19	; "dimen" -
	145	[719]	CALL     	16 3 2
	146	[725]	GETUPVAL 	17 8	; HorizontalGroup
	147	[725]	SELF     	17 17 -11	; "new"
	148	[725]	NEWTABLE 	19 0 0
	149	[725]	CALL     	17 3 2
	150	[726]	GETUPVAL 	18 8	; HorizontalGroup
	151	[726]	SELF     	18 18 -11	; "new"
	152	[726]	NEWTABLE 	20 0 0
	153	[726]	CALL     	18 3 2
	154	[728]	LOADK    	19 -10	; 1
	155	[728]	LEN      	20 4
	156	[728]	LOADK    	21 -10	; 1
	157	[728]	FORPREP  	19 105	; to 263
	158	[729]	GETGLOBAL	23 -20	; table
	159	[729]	GETTABLE 	23 23 -21	; "insert"
	160	[729]	MOVE     	24 17
	161	[729]	MOVE     	25 14
	162	[729]	CALL     	23 3 1
	163	[730]	GETGLOBAL	23 -20	; table
	164	[730]	GETTABLE 	23 23 -21	; "insert"
	165	[730]	MOVE     	24 18
	166	[730]	MOVE     	25 15
	167	[730]	CALL     	23 3 1
	168	[731]	GETTABLE 	23 0 -39	; "panel_index"
	169	[731]	EQ       	0 22 23
	170	[731]	JMP      	48	; to 219
	171	[732]	GETGLOBAL	23 -20	; table
	172	[732]	GETTABLE 	23 23 -21	; "insert"
	173	[732]	MOVE     	24 17
	174	[732]	MOVE     	25 12
	175	[732]	CALL     	23 3 1
	176	[733]	GETGLOBAL	23 -20	; table
	177	[733]	GETTABLE 	23 23 -21	; "insert"
	178	[733]	MOVE     	24 18
	179	[733]	MOVE     	25 16
	180	[733]	CALL     	23 3 1
	181	[734]	GETGLOBAL	23 -20	; table
	182	[734]	GETTABLE 	23 23 -21	; "insert"
	183	[734]	MOVE     	24 17
	184	[734]	GETTABLE 	25 4 22
	185	[734]	CALL     	23 3 1
	186	[735]	GETGLOBAL	23 -20	; table
	187	[735]	GETTABLE 	23 23 -21	; "insert"
	188	[735]	MOVE     	24 18
	189	[735]	GETUPVAL 	25 4	; LineWidget
	190	[735]	SELF     	25 25 -11	; "new"
	191	[735]	NEWTABLE 	27 0 2
	192	[736]	GETUPVAL 	28 5	; Blitbuffer
	193	[736]	GETTABLE 	28 28 -38	; "COLOR_WHITE"
	194	[736]	SETTABLE 	27 -33 28	; "background" -
	195	[737]	GETUPVAL 	28 6	; Geom
	196	[737]	SELF     	28 28 -11	; "new"
	197	[737]	NEWTABLE 	30 0 2
	198	[738]	GETTABLE 	31 4 22
	199	[738]	SELF     	31 31 -40	; "getSize"
	200	[738]	CALL     	31 2 2
	201	[738]	GETTABLE 	31 31 -36	; "w"
	202	[738]	SETTABLE 	30 -36 31	; "w" -
	203	[739]	SETTABLE 	30 -37 2	; "h" -
	204	[737]	CALL     	28 3 2
	205	[740]	SETTABLE 	27 -35 28	; "dimen" -
	206	[735]	CALL     	25 3 0
	207	[735]	CALL     	23 0 1
	208	[742]	GETGLOBAL	23 -20	; table
	209	[742]	GETTABLE 	23 23 -21	; "insert"
	210	[742]	MOVE     	24 17
	211	[742]	MOVE     	25 12
	212	[742]	CALL     	23 3 1
	213	[743]	GETGLOBAL	23 -20	; table
	214	[743]	GETTABLE 	23 23 -21	; "insert"
	215	[743]	MOVE     	24 18
	216	[743]	MOVE     	25 16
	217	[743]	CALL     	23 3 1
	218	[743]	JMP      	44	; to 263
	219	[745]	GETGLOBAL	23 -20	; table
	220	[745]	GETTABLE 	23 23 -21	; "insert"
	221	[745]	MOVE     	24 17
	222	[745]	MOVE     	25 13
	223	[745]	CALL     	23 3 1
	224	[746]	GETGLOBAL	23 -20	; table
	225	[746]	GETTABLE 	23 23 -21	; "insert"
	226	[746]	MOVE     	24 18
	227	[746]	MOVE     	25 16
	228	[746]	CALL     	23 3 1
	229	[747]	GETGLOBAL	23 -20	; table
	230	[747]	GETTABLE 	23 23 -21	; "insert"
	231	[747]	MOVE     	24 17
	232	[747]	GETTABLE 	25 4 22
	233	[747]	CALL     	23 3 1
	234	[748]	GETGLOBAL	23 -20	; table
	235	[748]	GETTABLE 	23 23 -21	; "insert"
	236	[748]	MOVE     	24 18
	237	[748]	GETUPVAL 	25 4	; LineWidget
	238	[748]	SELF     	25 25 -11	; "new"
	239	[748]	NEWTABLE 	27 0 1
	240	[749]	GETUPVAL 	28 6	; Geom
	241	[749]	SELF     	28 28 -11	; "new"
	242	[749]	NEWTABLE 	30 0 2
	243	[750]	GETTABLE 	31 4 22
	244	[750]	SELF     	31 31 -40	; "getSize"
	245	[750]	CALL     	31 2 2
	246	[750]	GETTABLE 	31 31 -36	; "w"
	247	[750]	SETTABLE 	30 -36 31	; "w" -
	248	[751]	SETTABLE 	30 -37 2	; "h" -
	249	[749]	CALL     	28 3 2
	250	[752]	SETTABLE 	27 -35 28	; "dimen" -
	251	[748]	CALL     	25 3 0
	252	[748]	CALL     	23 0 1
	253	[754]	GETGLOBAL	23 -20	; table
	254	[754]	GETTABLE 	23 23 -21	; "insert"
	255	[754]	MOVE     	24 17
	256	[754]	MOVE     	25 13
	257	[754]	CALL     	23 3 1
	258	[755]	GETGLOBAL	23 -20	; table
	259	[755]	GETTABLE 	23 23 -21	; "insert"
	260	[755]	MOVE     	24 18
	261	[755]	MOVE     	25 16
	262	[755]	CALL     	23 3 1
	263	[728]	FORLOOP  	19 -106	; to 158
	264	[758]	GETGLOBAL	19 -20	; table
	265	[758]	GETTABLE 	19 19 -21	; "insert"
	266	[758]	MOVE     	20 17
	267	[758]	MOVE     	21 14
	268	[758]	CALL     	19 3 1
	269	[759]	GETGLOBAL	19 -20	; table
	270	[759]	GETTABLE 	19 19 -21	; "insert"
	271	[759]	MOVE     	20 18
	272	[759]	MOVE     	21 15
	273	[759]	CALL     	19 3 1
	274	[761]	GETUPVAL 	19 6	; Geom
	275	[761]	SELF     	19 19 -11	; "new"
	276	[761]	NEWTABLE 	21 0 2
	277	[761]	GETUPVAL 	22 1	; Screen
	278	[761]	SELF     	22 22 -23	; "getWidth"
	279	[761]	CALL     	22 2 2
	280	[761]	SETTABLE 	21 -36 22	; "w" -
	281	[761]	SETTABLE 	21 -37 8	; "h" -
	282	[761]	CALL     	19 3 2
	283	[761]	SETTABLE 	0 -35 19	; "dimen" -
	284	[762]	GETUPVAL 	19 9	; VerticalGroup
	285	[762]	SELF     	19 19 -11	; "new"
	286	[762]	NEWTABLE 	21 2 0
	287	[763]	MOVE     	22 18
	288	[765]	MOVE     	23 17
	289	[765]	SETLIST  	21 2 1	; 1
	290	[762]	CALL     	19 3 2
	291	[766]	GETGLOBAL	20 -20	; table
	292	[766]	GETTABLE 	20 20 -21	; "insert"
	293	[766]	MOVE     	21 0
	294	[766]	MOVE     	22 19
	295	[766]	CALL     	20 3 1
	296	[768]	RETURN   	0 1

function <./frontend/ui/widget/configdialog.lua:675,677> (10 instructions, 40 bytes at 0x7f910240dee0)
0 params, 6 slots, 3 upvalues, 0 locals, 4 constants, 0 functions
	1	[676]	GETUPVAL 	0 0	; self
	2	[676]	GETTABLE 	0 0 -1	; "config_dialog"
	3	[676]	SELF     	0 0 -2	; "handleEvent"
	4	[676]	GETUPVAL 	2 1	; Event
	5	[676]	SELF     	2 2 -3	; "new"
	6	[676]	LOADK    	4 -4	; "ShowConfigPanel"
	7	[676]	GETUPVAL 	5 2	; c
	8	[676]	CALL     	2 4 0
	9	[676]	CALL     	0 0 1
	10	[677]	RETURN   	0 1

function <./frontend/ui/widget/configdialog.lua:795,832> (82 instructions, 328 bytes at 0x7f910240e0e0)
1 param, 11 slots, 4 upvalues, 1 local, 27 constants, 0 functions
	1	[799]	SELF     	1 0 -1	; "update"
	2	[799]	CALL     	1 2 1
	3	[803]	GETUPVAL 	1 0	; Device
	4	[803]	SELF     	1 1 -2	; "isTouchDevice"
	5	[803]	CALL     	1 2 2
	6	[803]	TEST     	1 0 0
	7	[803]	JMP      	48	; to 56
	8	[804]	GETTABLE 	1 0 -3	; "ges_events"
	9	[804]	NEWTABLE 	2 0 0
	10	[805]	GETUPVAL 	3 1	; GestureRange
	11	[805]	SELF     	3 3 -5	; "new"
	12	[805]	NEWTABLE 	5 0 2
	13	[806]	SETTABLE 	5 -6 -7	; "ges" "tap"
	14	[807]	GETUPVAL 	6 2	; Geom
	15	[807]	SELF     	6 6 -5	; "new"
	16	[807]	NEWTABLE 	8 0 4
	17	[808]	SETTABLE 	8 -9 -10	; "x" 0
	18	[808]	SETTABLE 	8 -11 -10	; "y" 0
	19	[809]	GETUPVAL 	9 3	; Screen
	20	[809]	SELF     	9 9 -13	; "getWidth"
	21	[809]	CALL     	9 2 2
	22	[809]	SETTABLE 	8 -12 9	; "w" -
	23	[810]	GETUPVAL 	9 3	; Screen
	24	[810]	SELF     	9 9 -15	; "getHeight"
	25	[810]	CALL     	9 2 2
	26	[810]	SETTABLE 	8 -14 9	; "h" -
	27	[807]	CALL     	6 3 2
	28	[811]	SETTABLE 	5 -8 6	; "range" -
	29	[805]	CALL     	3 3 0
	30	[813]	SETLIST  	2 0 1	; 1
	31	[813]	SETTABLE 	1 -4 2	; "TapCloseMenu" -
	32	[814]	GETTABLE 	1 0 -3	; "ges_events"
	33	[814]	NEWTABLE 	2 0 0
	34	[815]	GETUPVAL 	3 1	; GestureRange
	35	[815]	SELF     	3 3 -5	; "new"
	36	[815]	NEWTABLE 	5 0 2
	37	[816]	SETTABLE 	5 -6 -17	; "ges" "swipe"
	38	[817]	GETUPVAL 	6 2	; Geom
	39	[817]	SELF     	6 6 -5	; "new"
	40	[817]	NEWTABLE 	8 0 4
	41	[818]	SETTABLE 	8 -9 -10	; "x" 0
	42	[818]	SETTABLE 	8 -11 -10	; "y" 0
	43	[819]	GETUPVAL 	9 3	; Screen
	44	[819]	SELF     	9 9 -13	; "getWidth"
	45	[819]	CALL     	9 2 2
	46	[819]	SETTABLE 	8 -12 9	; "w" -
	47	[820]	GETUPVAL 	9 3	; Screen
	48	[820]	SELF     	9 9 -15	; "getHeight"
	49	[820]	CALL     	9 2 2
	50	[820]	SETTABLE 	8 -14 9	; "h" -
	51	[817]	CALL     	6 3 2
	52	[821]	SETTABLE 	5 -8 6	; "range" -
	53	[815]	CALL     	3 3 0
	54	[823]	SETLIST  	2 0 1	; 1
	55	[823]	SETTABLE 	1 -16 2	; "SwipeCloseMenu" -
	56	[825]	GETUPVAL 	1 0	; Device
	57	[825]	SELF     	1 1 -18	; "hasKeys"
	58	[825]	CALL     	1 2 2
	59	[825]	TEST     	1 0 0
	60	[825]	JMP      	8	; to 69
	61	[827]	GETTABLE 	1 0 -19	; "key_events"
	62	[827]	NEWTABLE 	2 1 1
	63	[827]	NEWTABLE 	3 1 0
	64	[827]	LOADK    	4 -21	; "Back"
	65	[827]	SETLIST  	3 1 1	; 1
	66	[827]	SETTABLE 	2 -22 -23	; "doc" "close config menu"
	67	[827]	SETLIST  	2 1 1	; 1
	68	[827]	SETTABLE 	1 -20 2	; "Close" -
	69	[829]	GETUPVAL 	1 0	; Device
	70	[829]	SELF     	1 1 -24	; "hasDPad"
	71	[829]	CALL     	1 2 2
	72	[829]	TEST     	1 0 0
	73	[829]	JMP      	8	; to 82
	74	[830]	GETTABLE 	1 0 -19	; "key_events"
	75	[830]	NEWTABLE 	2 1 1
	76	[830]	NEWTABLE 	3 1 0
	77	[830]	LOADK    	4 -26	; "Press"
	78	[830]	SETLIST  	3 1 1	; 1
	79	[830]	SETTABLE 	2 -22 -27	; "doc" "select current menu item"
	80	[830]	SETLIST  	2 1 1	; 1
	81	[830]	SETTABLE 	1 -25 2	; "Select" -
	82	[832]	RETURN   	0 1

function <./frontend/ui/widget/configdialog.lua:834,836> (1 instruction, 4 bytes at 0x7f910240e1a0)
2 params, 2 slots, 0 upvalues, 2 locals, 0 constants, 0 functions
	1	[836]	RETURN   	0 1

function <./frontend/ui/widget/configdialog.lua:838,863> (53 instructions, 212 bytes at 0x7f910240ea70)
1 param, 9 slots, 7 upvalues, 1 local, 16 constants, 0 functions
	1	[839]	NEWTABLE 	1 0 0
	2	[839]	SETTABLE 	0 -1 1	; "layout" -
	3	[840]	GETUPVAL 	1 0	; MenuBar
	4	[840]	SELF     	1 1 -3	; "new"
	5	[840]	NEWTABLE 	3 0 2
	6	[841]	SETTABLE 	3 -4 0	; "config_dialog" -
	7	[842]	GETTABLE 	4 0 -5	; "panel_index"
	8	[842]	SETTABLE 	3 -5 4	; "panel_index" -
	9	[840]	CALL     	1 3 2
	10	[843]	SETTABLE 	0 -2 1	; "config_menubar" -
	11	[844]	GETUPVAL 	1 1	; ConfigPanel
	12	[844]	SELF     	1 1 -3	; "new"
	13	[844]	NEWTABLE 	3 0 2
	14	[845]	GETTABLE 	4 0 -5	; "panel_index"
	15	[845]	SETTABLE 	3 -7 4	; "index" -
	16	[846]	SETTABLE 	3 -4 0	; "config_dialog" -
	17	[844]	CALL     	1 3 2
	18	[847]	SETTABLE 	0 -6 1	; "config_panel" -
	19	[848]	GETUPVAL 	1 2	; FrameContainer
	20	[848]	SELF     	1 1 -3	; "new"
	21	[848]	NEWTABLE 	3 0 1
	22	[849]	GETUPVAL 	4 3	; Blitbuffer
	23	[849]	GETTABLE 	4 4 -10	; "COLOR_WHITE"
	24	[849]	SETTABLE 	3 -9 4	; "background" -
	25	[850]	GETUPVAL 	4 4	; VerticalGroup
	26	[850]	SELF     	4 4 -3	; "new"
	27	[850]	NEWTABLE 	6 2 0
	28	[851]	GETTABLE 	7 0 -6	; "config_panel"
	29	[853]	GETTABLE 	8 0 -2	; "config_menubar"
	30	[853]	SETLIST  	6 2 1	; 1
	31	[850]	CALL     	4 3 0
	32	[854]	SETLIST  	3 0 1	; 1
	33	[848]	CALL     	1 3 2
	34	[854]	SETTABLE 	0 -8 1	; "dialog_frame" -
	35	[856]	GETTABLE 	1 0 -11	; "selected"
	36	[856]	GETTABLE 	2 0 -1	; "layout"
	37	[856]	LEN      	2 2
	38	[856]	SETTABLE 	1 -12 2	; "y" -
	39	[857]	GETTABLE 	1 0 -11	; "selected"
	40	[857]	GETTABLE 	2 0 -5	; "panel_index"
	41	[857]	SETTABLE 	1 -13 2	; "x" -
	42	[859]	GETUPVAL 	1 5	; BottomContainer
	43	[859]	SELF     	1 1 -3	; "new"
	44	[859]	NEWTABLE 	3 1 1
	45	[860]	GETUPVAL 	4 6	; Screen
	46	[860]	SELF     	4 4 -16	; "getSize"
	47	[860]	CALL     	4 2 2
	48	[860]	SETTABLE 	3 -15 4	; "dimen" -
	49	[862]	GETTABLE 	4 0 -8	; "dialog_frame"
	50	[862]	SETLIST  	3 1 1	; 1
	51	[859]	CALL     	1 3 2
	52	[862]	SETTABLE 	0 -14 1	; 1 -
	53	[863]	RETURN   	0 1

function <./frontend/ui/widget/configdialog.lua:865,870> (7 instructions, 28 bytes at 0x7f91024079f0)
1 param, 5 slots, 1 upvalue, 1 local, 1 constant, 1 function
	1	[867]	GETUPVAL 	1 0	; UIManager
	2	[867]	SELF     	1 1 -1	; "setDirty"
	3	[867]	LOADNIL  	3 3
	4	[869]	CLOSURE  	4 0	; 0x7f910240f810
	5	[869]	MOVE     	0 0
	6	[867]	CALL     	1 4 1
	7	[870]	RETURN   	0 1

function <./frontend/ui/widget/configdialog.lua:867,869> (6 instructions, 24 bytes at 0x7f910240f810)
0 params, 2 slots, 1 upvalue, 0 locals, 3 constants, 0 functions
	1	[868]	LOADK    	0 -1	; "partial"
	2	[868]	GETUPVAL 	1 0	; self
	3	[868]	GETTABLE 	1 1 -2	; "dialog_frame"
	4	[868]	GETTABLE 	1 1 -3	; "dimen"
	5	[868]	RETURN   	0 3
	6	[869]	RETURN   	0 1

function <./frontend/ui/widget/configdialog.lua:872,893> (41 instructions, 164 bytes at 0x7f910240f8b0)
2 params, 9 slots, 1 upvalue, 5 locals, 9 constants, 1 function
	1	[873]	SETTABLE 	0 -1 1	; "panel_index" -
	2	[874]	GETTABLE 	2 0 -2	; "dialog_frame"
	3	[874]	GETTABLE 	2 2 -3	; "dimen"
	4	[874]	TEST     	2 0 0
	5	[874]	JMP      	4	; to 10
	6	[874]	GETTABLE 	2 0 -2	; "dialog_frame"
	7	[874]	GETTABLE 	2 2 -3	; "dimen"
	8	[874]	SELF     	2 2 -4	; "copy"
	9	[874]	CALL     	2 2 2
	10	[875]	GETTABLE 	3 0 -5	; "layout"
	11	[875]	TEST     	3 0 0
	12	[875]	JMP      	2	; to 15
	13	[875]	GETTABLE 	3 0 -5	; "layout"
	14	[875]	LEN      	3 3
	15	[876]	SELF     	4 0 -6	; "update"
	16	[876]	CALL     	4 2 1
	17	[884]	TESTSET  	4 3 0
	18	[884]	JMP      	6	; to 25
	19	[884]	GETTABLE 	4 0 -5	; "layout"
	20	[884]	LEN      	4 4
	21	[884]	LT       	1 3 4
	22	[884]	JMP      	1	; to 24
	23	[884]	LOADBOOL 	4 0 1
	24	[884]	LOADBOOL 	4 1 0
	25	[885]	GETUPVAL 	5 0	; UIManager
	26	[885]	SELF     	5 5 -7	; "setDirty"
	27	[885]	GETTABLE 	7 0 -8	; "is_fresh"
	28	[885]	TEST     	7 0 1
	29	[885]	JMP      	2	; to 32
	30	[885]	TEST     	4 0 0
	31	[885]	JMP      	2	; to 34
	32	[885]	TESTSET  	7 0 1
	33	[885]	JMP      	1	; to 35
	34	[885]	LOADK    	7 -9	; "all"
	35	[891]	CLOSURE  	8 0	; 0x7f910240fc10
	36	[891]	MOVE     	0 2
	37	[891]	MOVE     	0 0
	38	[885]	CALL     	5 4 1
	39	[892]	LOADBOOL 	5 1 0
	40	[892]	RETURN   	5 2
	41	[893]	RETURN   	0 1

function <./frontend/ui/widget/configdialog.lua:885,891> (20 instructions, 80 bytes at 0x7f910240fc10)
0 params, 3 slots, 2 upvalues, 1 local, 6 constants, 0 functions
	1	[887]	GETUPVAL 	0 0	; old_dimen
	2	[887]	TEST     	0 0 0
	3	[887]	JMP      	8	; to 12
	4	[887]	GETUPVAL 	0 0	; old_dimen
	5	[887]	SELF     	0 0 -1	; "combine"
	6	[887]	GETUPVAL 	2 1	; self
	7	[887]	GETTABLE 	2 2 -2	; "dialog_frame"
	8	[887]	GETTABLE 	2 2 -3	; "dimen"
	9	[887]	CALL     	0 3 2
	10	[888]	TEST     	0 0 1
	11	[888]	JMP      	3	; to 15
	12	[888]	GETUPVAL 	0 1	; self
	13	[888]	GETTABLE 	0 0 -2	; "dialog_frame"
	14	[888]	GETTABLE 	0 0 -3	; "dimen"
	15	[889]	GETUPVAL 	1 1	; self
	16	[889]	SETTABLE 	1 -4 -5	; "is_fresh" false
	17	[890]	LOADK    	1 -6	; "ui"
	18	[890]	MOVE     	2 0
	19	[890]	RETURN   	1 3
	20	[891]	RETURN   	0 1

function <./frontend/ui/widget/configdialog.lua:895,899> (12 instructions, 48 bytes at 0x7f9102410580)
3 params, 8 slots, 1 upvalue, 3 locals, 5 constants, 0 functions
	1	[896]	GETTABLE 	3 0 -1	; "configurable"
	2	[896]	SETTABLE 	3 1 2
	3	[897]	GETTABLE 	3 0 -2	; "ui"
	4	[897]	SELF     	3 3 -3	; "handleEvent"
	5	[897]	GETUPVAL 	5 0	; Event
	6	[897]	SELF     	5 5 -4	; "new"
	7	[897]	LOADK    	7 -5	; "StartActivityIndicator"
	8	[897]	CALL     	5 3 0
	9	[897]	CALL     	3 0 1
	10	[898]	LOADBOOL 	3 1 0
	11	[898]	RETURN   	3 2
	12	[899]	RETURN   	0 1

function <./frontend/ui/widget/configdialog.lua:901,904> (12 instructions, 48 bytes at 0x7f9102410750)
4 params, 11 slots, 1 upvalue, 4 locals, 3 constants, 0 functions
	1	[902]	GETTABLE 	4 0 -1	; "ui"
	2	[902]	SELF     	4 4 -2	; "handleEvent"
	3	[902]	GETUPVAL 	6 0	; Event
	4	[902]	SELF     	6 6 -3	; "new"
	5	[902]	MOVE     	8 1
	6	[902]	MOVE     	9 2
	7	[902]	MOVE     	10 3
	8	[902]	CALL     	6 5 0
	9	[902]	CALL     	4 0 1
	10	[903]	LOADBOOL 	4 1 0
	11	[903]	RETURN   	4 2
	12	[904]	RETURN   	0 1

function <./frontend/ui/widget/configdialog.lua:906,912> (26 instructions, 104 bytes at 0x7f9102410c90)
3 params, 13 slots, 1 upvalue, 7 locals, 6 constants, 0 functions
	1	[907]	LOADK    	3 -1	; 1
	2	[907]	LEN      	4 1
	3	[907]	LOADK    	5 -1	; 1
	4	[907]	FORPREP  	3 18	; to 23
	5	[908]	GETTABLE 	7 1 6
	6	[908]	GETTABLE 	8 1 6
	7	[908]	GETTABLE 	8 8 -2	; "args"
	8	[908]	TEST     	8 0 1
	9	[908]	JMP      	1	; to 11
	10	[908]	NEWTABLE 	8 0 0
	11	[908]	SETTABLE 	7 -2 8	; "args" -
	12	[909]	GETTABLE 	7 0 -3	; "ui"
	13	[909]	SELF     	7 7 -4	; "handleEvent"
	14	[909]	GETUPVAL 	9 0	; Event
	15	[909]	SELF     	9 9 -5	; "new"
	16	[909]	GETTABLE 	11 1 6
	17	[909]	GETTABLE 	11 11 -6	; "event"
	18	[909]	GETTABLE 	12 1 6
	19	[909]	GETTABLE 	12 12 -2	; "args"
	20	[909]	GETTABLE 	12 12 2
	21	[909]	CALL     	9 4 0
	22	[909]	CALL     	7 0 1
	23	[907]	FORLOOP  	3 -19	; to 5
	24	[911]	LOADBOOL 	3 1 0
	25	[911]	RETURN   	3 2
	26	[912]	RETURN   	0 1

function <./frontend/ui/widget/configdialog.lua:914,962> (14 instructions, 56 bytes at 0x7f9102411320)
8 params, 11 slots, 1 upvalue, 8 locals, 1 constant, 1 function
	1	[915]	GETUPVAL 	8 0	; UIManager
	2	[915]	SELF     	8 8 -1	; "tickAfterNext"
	3	[961]	CLOSURE  	10 0	; 0x7f9102411480
	4	[961]	MOVE     	0 0
	5	[961]	GETUPVAL 	0 0	; UIManager
	6	[961]	MOVE     	0 7
	7	[961]	MOVE     	0 1
	8	[961]	MOVE     	0 2
	9	[961]	MOVE     	0 6
	10	[961]	MOVE     	0 3
	11	[961]	MOVE     	0 4
	12	[961]	MOVE     	0 5
	13	[915]	CALL     	8 3 1
	14	[962]	RETURN   	0 1

function <./frontend/ui/widget/configdialog.lua:915,961> (66 instructions, 264 bytes at 0x7f9102411480)
0 params, 7 slots, 9 upvalues, 2 locals, 9 constants, 1 function
	1	[931]	CLOSURE  	0 0	; 0x7f91024115f0
	2	[931]	GETUPVAL 	0 0	; self
	3	[931]	GETUPVAL 	0 1	; UIManager
	4	[932]	LOADNIL  	1 1
	5	[933]	GETGLOBAL	2 -1	; type
	6	[933]	GETUPVAL 	3 2	; delay_repaint
	7	[933]	CALL     	2 2 2
	8	[933]	EQ       	0 2 -2	; - "number"
	9	[933]	JMP      	8	; to 18
	10	[934]	GETUPVAL 	2 1	; UIManager
	11	[934]	SELF     	2 2 -3	; "scheduleIn"
	12	[934]	GETUPVAL 	4 2	; delay_repaint
	13	[934]	MOVE     	5 0
	14	[934]	CALL     	2 4 1
	15	[935]	GETUPVAL 	2 0	; self
	16	[935]	SETTABLE 	2 -4 -5	; "skip_paint" true
	17	[935]	JMP      	6	; to 24
	18	[936]	GETUPVAL 	2 2	; delay_repaint
	19	[936]	TEST     	2 0 0
	20	[936]	JMP      	3	; to 24
	21	[940]	MOVE     	1 0
	22	[941]	GETUPVAL 	2 0	; self
	23	[941]	SETTABLE 	2 -4 -5	; "skip_paint" true
	24	[943]	GETUPVAL 	2 3	; values
	25	[943]	TEST     	2 0 0
	26	[943]	JMP      	7	; to 34
	27	[944]	GETUPVAL 	2 0	; self
	28	[944]	SELF     	2 2 -6	; "onConfigChoice"
	29	[944]	GETUPVAL 	4 4	; name
	30	[944]	GETUPVAL 	5 3	; values
	31	[944]	GETUPVAL 	6 5	; position
	32	[944]	GETTABLE 	5 5 6
	33	[944]	CALL     	2 4 1
	34	[946]	GETUPVAL 	2 6	; event
	35	[946]	TEST     	2 0 0
	36	[946]	JMP      	13	; to 50
	37	[947]	GETUPVAL 	2 7	; args
	38	[947]	TEST     	2 0 1
	39	[947]	JMP      	1	; to 41
	40	[947]	NEWTABLE 	2 0 0
	41	[947]	SETUPVAL 	2 7	; args
	42	[948]	GETUPVAL 	2 0	; self
	43	[948]	SELF     	2 2 -7	; "onConfigEvent"
	44	[948]	GETUPVAL 	4 6	; event
	45	[948]	GETUPVAL 	5 7	; args
	46	[948]	GETUPVAL 	6 5	; position
	47	[948]	GETTABLE 	5 5 6
	48	[948]	MOVE     	6 1
	49	[948]	CALL     	2 5 1
	50	[950]	GETUPVAL 	2 8	; events
	51	[950]	TEST     	2 0 0
	52	[950]	JMP      	5	; to 58
	53	[951]	GETUPVAL 	2 0	; self
	54	[951]	SELF     	2 2 -8	; "onConfigEvents"
	55	[951]	GETUPVAL 	4 8	; events
	56	[951]	GETUPVAL 	5 5	; position
	57	[951]	CALL     	2 4 1
	58	[957]	GETUPVAL 	2 0	; self
	59	[957]	SELF     	2 2 -9	; "update"
	60	[957]	CALL     	2 2 1
	61	[958]	GETUPVAL 	2 2	; delay_repaint
	62	[958]	TEST     	2 0 1
	63	[958]	JMP      	2	; to 66
	64	[959]	MOVE     	2 0
	65	[959]	CALL     	2 1 1
	66	[961]	RETURN   	0 1

function <./frontend/ui/widget/configdialog.lua:917,931> (20 instructions, 80 bytes at 0x7f91024115f0)
0 params, 4 slots, 2 upvalues, 0 locals, 7 constants, 1 function
	1	[918]	GETUPVAL 	0 0	; self
	2	[918]	SETTABLE 	0 -1 -2	; "skip_paint" nil
	3	[919]	GETUPVAL 	0 0	; self
	4	[919]	GETTABLE 	0 0 -3	; "config_options"
	5	[919]	GETTABLE 	0 0 -4	; "needs_redraw_on_change"
	6	[919]	TEST     	0 0 0
	7	[919]	JMP      	6	; to 14
	8	[923]	GETUPVAL 	0 1	; UIManager
	9	[923]	SELF     	0 0 -5	; "setDirty"
	10	[923]	LOADK    	2 -6	; "all"
	11	[923]	LOADK    	3 -7	; "partial"
	12	[923]	CALL     	0 4 1
	13	[923]	JMP      	6	; to 20
	14	[927]	GETUPVAL 	0 1	; UIManager
	15	[927]	SELF     	0 0 -5	; "setDirty"
	16	[927]	GETUPVAL 	2 0	; self
	17	[929]	CLOSURE  	3 0	; 0x7f9102411ad0
	18	[929]	GETUPVAL 	0 0	; self
	19	[927]	CALL     	0 4 1
	20	[931]	RETURN   	0 1

function <./frontend/ui/widget/configdialog.lua:927,929> (6 instructions, 24 bytes at 0x7f9102411ad0)
0 params, 2 slots, 1 upvalue, 0 locals, 3 constants, 0 functions
	1	[928]	LOADK    	0 -1	; "ui"
	2	[928]	GETUPVAL 	1 0	; self
	3	[928]	GETTABLE 	1 1 -2	; "dialog_frame"
	4	[928]	GETTABLE 	1 1 -3	; "dimen"
	5	[928]	RETURN   	0 3
	6	[929]	RETURN   	0 1

function <./frontend/ui/widget/configdialog.lua:965,1054> (14 instructions, 56 bytes at 0x7f91024122d0)
8 params, 11 slots, 1 upvalue, 8 locals, 1 constant, 1 function
	1	[966]	GETUPVAL 	8 0	; UIManager
	2	[966]	SELF     	8 8 -1	; "tickAfterNext"
	3	[1053]	CLOSURE  	10 0	; 0x7f9102412350
	4	[1053]	MOVE     	0 0
	5	[1053]	GETUPVAL 	0 0	; UIManager
	6	[1053]	MOVE     	0 7
	7	[1053]	MOVE     	0 1
	8	[1053]	MOVE     	0 6
	9	[1053]	MOVE     	0 2
	10	[1053]	MOVE     	0 3
	11	[1053]	MOVE     	0 4
	12	[1053]	MOVE     	0 5
	13	[966]	CALL     	8 3 1
	14	[1054]	RETURN   	0 1

function <./frontend/ui/widget/configdialog.lua:966,1053> (156 instructions, 624 bytes at 0x7f9102412350)
0 params, 8 slots, 9 upvalues, 12 locals, 14 constants, 1 function
	1	[982]	CLOSURE  	0 0	; 0x7f9102412cd0
	2	[982]	GETUPVAL 	0 0	; self
	3	[982]	GETUPVAL 	0 1	; UIManager
	4	[983]	LOADNIL  	1 1
	5	[984]	GETGLOBAL	2 -1	; type
	6	[984]	GETUPVAL 	3 2	; delay_repaint
	7	[984]	CALL     	2 2 2
	8	[984]	EQ       	0 2 -2	; - "number"
	9	[984]	JMP      	8	; to 18
	10	[985]	GETUPVAL 	2 1	; UIManager
	11	[985]	SELF     	2 2 -3	; "scheduleIn"
	12	[985]	GETUPVAL 	4 2	; delay_repaint
	13	[985]	MOVE     	5 0
	14	[985]	CALL     	2 4 1
	15	[986]	GETUPVAL 	2 0	; self
	16	[986]	SETTABLE 	2 -4 -5	; "skip_paint" true
	17	[986]	JMP      	6	; to 24
	18	[987]	GETUPVAL 	2 2	; delay_repaint
	19	[987]	TEST     	2 0 0
	20	[987]	JMP      	3	; to 24
	21	[991]	MOVE     	1 0
	22	[992]	GETUPVAL 	2 0	; self
	23	[992]	SETTABLE 	2 -4 -5	; "skip_paint" true
	24	[994]	GETUPVAL 	2 3	; values
	25	[994]	TEST     	2 0 0
	26	[994]	JMP      	65	; to 92
	27	[995]	LOADNIL  	2 2
	28	[996]	GETUPVAL 	3 4	; direction
	29	[996]	EQ       	0 3 -6	; - "-"
	30	[996]	JMP      	31	; to 62
	31	[997]	GETUPVAL 	3 0	; self
	32	[997]	GETTABLE 	3 3 -7	; "configurable"
	33	[997]	GETUPVAL 	4 5	; name
	34	[997]	GETTABLE 	3 3 4
	35	[997]	TESTSET  	2 3 1
	36	[997]	JMP      	2	; to 39
	37	[997]	GETUPVAL 	3 3	; values
	38	[997]	GETTABLE 	2 3 -8	; 1
	39	[998]	GETGLOBAL	3 -1	; type
	40	[998]	MOVE     	4 2
	41	[998]	CALL     	3 2 2
	42	[998]	EQ       	0 3 -9	; - "table"
	43	[998]	JMP      	13	; to 57
	44	[999]	LOADK    	3 -8	; 1
	45	[999]	LEN      	4 2
	46	[999]	LOADK    	5 -8	; 1
	47	[999]	FORPREP  	3 7	; to 55
	48	[1000]	GETTABLE 	7 2 6
	49	[1000]	SUB      	7 7 -8	; - 1
	50	[1000]	SETTABLE 	2 6 7
	51	[1001]	GETTABLE 	7 2 6
	52	[1001]	LT       	0 7 -10	; - 0
	53	[1001]	JMP      	1	; to 55
	54	[1002]	SETTABLE 	2 6 -10	; - 0
	55	[999]	FORLOOP  	3 -8	; to 48
	56	[1004]	JMP      	30	; to 87
	57	[1006]	SUB      	2 2 -8	; - 1
	58	[1007]	LT       	0 2 -10	; - 0
	59	[1007]	JMP      	27	; to 87
	60	[1008]	LOADK    	2 -10	; 0
	61	[1010]	JMP      	25	; to 87
	62	[1012]	GETUPVAL 	3 0	; self
	63	[1012]	GETTABLE 	3 3 -7	; "configurable"
	64	[1012]	GETUPVAL 	4 5	; name
	65	[1012]	GETTABLE 	3 3 4
	66	[1012]	TESTSET  	2 3 1
	67	[1012]	JMP      	4	; to 72
	68	[1012]	GETUPVAL 	3 3	; values
	69	[1012]	GETUPVAL 	4 3	; values
	70	[1012]	LEN      	4 4
	71	[1012]	GETTABLE 	2 3 4
	72	[1013]	GETGLOBAL	3 -1	; type
	73	[1013]	MOVE     	4 2
	74	[1013]	CALL     	3 2 2
	75	[1013]	EQ       	0 3 -9	; - "table"
	76	[1013]	JMP      	9	; to 86
	77	[1014]	LOADK    	3 -8	; 1
	78	[1014]	LEN      	4 2
	79	[1014]	LOADK    	5 -8	; 1
	80	[1014]	FORPREP  	3 3	; to 84
	81	[1015]	GETTABLE 	7 2 6
	82	[1015]	ADD      	7 7 -8	; - 1
	83	[1015]	SETTABLE 	2 6 7
	84	[1014]	FORLOOP  	3 -4	; to 81
	85	[1016]	JMP      	1	; to 87
	86	[1018]	ADD      	2 2 -8	; - 1
	87	[1021]	GETUPVAL 	3 0	; self
	88	[1021]	SELF     	3 3 -11	; "onConfigChoice"
	89	[1021]	GETUPVAL 	5 5	; name
	90	[1021]	MOVE     	6 2
	91	[1021]	CALL     	3 4 1
	92	[1023]	GETUPVAL 	2 6	; event
	93	[1023]	TEST     	2 0 0
	94	[1023]	JMP      	45	; to 140
	95	[1024]	GETUPVAL 	2 7	; args
	96	[1024]	TEST     	2 0 1
	97	[1024]	JMP      	1	; to 99
	98	[1024]	NEWTABLE 	2 0 0
	99	[1024]	SETUPVAL 	2 7	; args
	100	[1025]	LOADNIL  	2 2
	101	[1026]	GETUPVAL 	3 4	; direction
	102	[1026]	EQ       	0 3 -6	; - "-"
	103	[1026]	JMP      	16	; to 120
	104	[1027]	GETUPVAL 	3 0	; self
	105	[1027]	GETTABLE 	3 3 -7	; "configurable"
	106	[1027]	GETUPVAL 	4 5	; name
	107	[1027]	GETTABLE 	3 3 4
	108	[1027]	TESTSET  	2 3 1
	109	[1027]	JMP      	2	; to 112
	110	[1027]	GETUPVAL 	3 7	; args
	111	[1027]	GETTABLE 	2 3 -8	; 1
	112	[1028]	GETUPVAL 	3 3	; values
	113	[1028]	TEST     	3 0 1
	114	[1028]	JMP      	19	; to 134
	115	[1029]	SUB      	2 2 -8	; - 1
	116	[1030]	LT       	0 2 -10	; - 0
	117	[1030]	JMP      	16	; to 134
	118	[1031]	LOADK    	2 -10	; 0
	119	[1033]	JMP      	14	; to 134
	120	[1035]	GETUPVAL 	3 0	; self
	121	[1035]	GETTABLE 	3 3 -7	; "configurable"
	122	[1035]	GETUPVAL 	4 5	; name
	123	[1035]	GETTABLE 	3 3 4
	124	[1035]	TESTSET  	2 3 1
	125	[1035]	JMP      	4	; to 130
	126	[1035]	GETUPVAL 	3 7	; args
	127	[1035]	GETUPVAL 	4 7	; args
	128	[1035]	LEN      	4 4
	129	[1035]	GETTABLE 	2 3 4
	130	[1036]	GETUPVAL 	3 3	; values
	131	[1036]	TEST     	3 0 1
	132	[1036]	JMP      	1	; to 134
	133	[1037]	ADD      	2 2 -8	; - 1
	134	[1040]	GETUPVAL 	3 0	; self
	135	[1040]	SELF     	3 3 -12	; "onConfigEvent"
	136	[1040]	GETUPVAL 	5 6	; event
	137	[1040]	MOVE     	6 2
	138	[1040]	MOVE     	7 1
	139	[1040]	CALL     	3 5 1
	140	[1042]	GETUPVAL 	2 8	; events
	141	[1042]	TEST     	2 0 0
	142	[1042]	JMP      	5	; to 148
	143	[1043]	GETUPVAL 	2 0	; self
	144	[1043]	SELF     	2 2 -13	; "onConfigEvents"
	145	[1043]	GETUPVAL 	4 8	; events
	146	[1043]	GETUPVAL 	5 4	; direction
	147	[1043]	CALL     	2 4 1
	148	[1049]	GETUPVAL 	2 0	; self
	149	[1049]	SELF     	2 2 -14	; "update"
	150	[1049]	CALL     	2 2 1
	151	[1050]	GETUPVAL 	2 2	; delay_repaint
	152	[1050]	TEST     	2 0 1
	153	[1050]	JMP      	2	; to 156
	154	[1051]	MOVE     	2 0
	155	[1051]	CALL     	2 1 1
	156	[1053]	RETURN   	0 1

function <./frontend/ui/widget/configdialog.lua:968,982> (20 instructions, 80 bytes at 0x7f9102412cd0)
0 params, 4 slots, 2 upvalues, 0 locals, 7 constants, 1 function
	1	[969]	GETUPVAL 	0 0	; self
	2	[969]	SETTABLE 	0 -1 -2	; "skip_paint" nil
	3	[970]	GETUPVAL 	0 0	; self
	4	[970]	GETTABLE 	0 0 -3	; "config_options"
	5	[970]	GETTABLE 	0 0 -4	; "needs_redraw_on_change"
	6	[970]	TEST     	0 0 0
	7	[970]	JMP      	6	; to 14
	8	[974]	GETUPVAL 	0 1	; UIManager
	9	[974]	SELF     	0 0 -5	; "setDirty"
	10	[974]	LOADK    	2 -6	; "all"
	11	[974]	LOADK    	3 -7	; "partial"
	12	[974]	CALL     	0 4 1
	13	[974]	JMP      	6	; to 20
	14	[978]	GETUPVAL 	0 1	; UIManager
	15	[978]	SELF     	0 0 -5	; "setDirty"
	16	[978]	GETUPVAL 	2 0	; self
	17	[980]	CLOSURE  	3 0	; 0x7f9102412dd0
	18	[980]	GETUPVAL 	0 0	; self
	19	[978]	CALL     	0 4 1
	20	[982]	RETURN   	0 1

function <./frontend/ui/widget/configdialog.lua:978,980> (6 instructions, 24 bytes at 0x7f9102412dd0)
0 params, 2 slots, 1 upvalue, 0 locals, 3 constants, 0 functions
	1	[979]	LOADK    	0 -1	; "ui"
	2	[979]	GETUPVAL 	1 0	; self
	3	[979]	GETTABLE 	1 1 -2	; "dialog_frame"
	4	[979]	GETTABLE 	1 1 -3	; "dimen"
	5	[979]	RETURN   	0 3
	6	[980]	RETURN   	0 1

function <./frontend/ui/widget/configdialog.lua:1058,1264> (22 instructions, 88 bytes at 0x7f9102413450)
8 params, 11 slots, 5 upvalues, 8 locals, 1 constant, 1 function
	1	[1059]	TEST     	7 0 1
	2	[1059]	JMP      	2	; to 5
	3	[1060]	NEWTABLE 	8 0 0
	4	[1060]	MOVE     	7 8
	5	[1062]	GETUPVAL 	8 0	; UIManager
	6	[1062]	SELF     	8 8 -1	; "tickAfterNext"
	7	[1263]	CLOSURE  	10 0	; 0x7f9102413b90
	8	[1263]	MOVE     	0 0
	9	[1263]	GETUPVAL 	0 0	; UIManager
	10	[1263]	MOVE     	0 6
	11	[1263]	MOVE     	0 1
	12	[1263]	MOVE     	0 3
	13	[1263]	MOVE     	0 7
	14	[1263]	MOVE     	0 2
	15	[1263]	MOVE     	0 5
	16	[1263]	GETUPVAL 	0 1	; Screen
	17	[1263]	GETUPVAL 	0 2	; _
	18	[1263]	MOVE     	0 4
	19	[1263]	GETUPVAL 	0 3	; T
	20	[1263]	GETUPVAL 	0 4	; ConfirmBox
	21	[1062]	CALL     	8 3 1
	22	[1264]	RETURN   	0 1

function <./frontend/ui/widget/configdialog.lua:1062,1263> (276 instructions, 1104 bytes at 0x7f9102413b90)
0 params, 13 slots, 13 upvalues, 14 locals, 52 constants, 5 functions
	1	[1078]	CLOSURE  	0 0	; 0x7f9102413890
	2	[1078]	GETUPVAL 	0 0	; self
	3	[1078]	GETUPVAL 	0 1	; UIManager
	4	[1079]	LOADNIL  	1 1
	5	[1080]	GETGLOBAL	2 -1	; type
	6	[1080]	GETUPVAL 	3 2	; delay_repaint
	7	[1080]	CALL     	2 2 2
	8	[1080]	EQ       	0 2 -2	; - "number"
	9	[1080]	JMP      	8	; to 18
	10	[1081]	GETUPVAL 	2 1	; UIManager
	11	[1081]	SELF     	2 2 -3	; "scheduleIn"
	12	[1081]	GETUPVAL 	4 2	; delay_repaint
	13	[1081]	MOVE     	5 0
	14	[1081]	CALL     	2 4 1
	15	[1082]	GETUPVAL 	2 0	; self
	16	[1082]	SETTABLE 	2 -4 -5	; "skip_paint" true
	17	[1082]	JMP      	6	; to 24
	18	[1083]	GETUPVAL 	2 2	; delay_repaint
	19	[1083]	TEST     	2 0 0
	20	[1083]	JMP      	3	; to 24
	21	[1087]	MOVE     	1 0
	22	[1088]	GETUPVAL 	2 0	; self
	23	[1088]	SETTABLE 	2 -4 -5	; "skip_paint" true
	24	[1090]	GETUPVAL 	2 3	; values
	25	[1090]	TEST     	2 0 0
	26	[1090]	JMP      	244	; to 271
	27	[1090]	GETUPVAL 	2 4	; event
	28	[1090]	TEST     	2 0 0
	29	[1090]	JMP      	241	; to 271
	30	[1091]	GETUPVAL 	2 5	; more_options_param
	31	[1091]	GETTABLE 	2 2 -6	; "name"
	32	[1091]	TEST     	2 0 0
	33	[1091]	JMP      	3	; to 37
	34	[1092]	GETUPVAL 	2 5	; more_options_param
	35	[1092]	GETTABLE 	2 2 -6	; "name"
	36	[1092]	SETUPVAL 	2 6	; name
	37	[1094]	GETUPVAL 	2 5	; more_options_param
	38	[1094]	GETTABLE 	2 2 -7	; "name_text"
	39	[1094]	TEST     	2 0 0
	40	[1094]	JMP      	3	; to 44
	41	[1095]	GETUPVAL 	2 5	; more_options_param
	42	[1095]	GETTABLE 	2 2 -7	; "name_text"
	43	[1095]	SETUPVAL 	2 7	; name_text
	44	[1097]	GETUPVAL 	2 5	; more_options_param
	45	[1097]	GETTABLE 	2 2 -8	; "event"
	46	[1097]	TEST     	2 0 0
	47	[1097]	JMP      	3	; to 51
	48	[1098]	GETUPVAL 	2 5	; more_options_param
	49	[1098]	GETTABLE 	2 2 -8	; "event"
	50	[1098]	SETUPVAL 	2 4	; event
	51	[1100]	LOADNIL  	2 2
	52	[1101]	GETUPVAL 	3 5	; more_options_param
	53	[1101]	GETTABLE 	3 3 -9	; "left_min"
	54	[1101]	TEST     	3 0 0
	55	[1101]	JMP      	84	; to 140
	56	[1102]	GETGLOBAL	3 -10	; require
	57	[1102]	LOADK    	4 -11	; "ui/widget/doublespinwidget"
	58	[1102]	CALL     	3 2 2
	59	[1104]	GETUPVAL 	4 0	; self
	60	[1104]	GETTABLE 	4 4 -12	; "configurable"
	61	[1104]	GETUPVAL 	5 6	; name
	62	[1104]	GETTABLE 	4 4 5
	63	[1105]	SELF     	5 3 -13	; "new"
	64	[1105]	NEWTABLE 	7 0 18
	65	[1106]	GETUPVAL 	8 8	; Screen
	66	[1106]	SELF     	8 8 -15	; "getWidth"
	67	[1106]	CALL     	8 2 2
	68	[1106]	MUL      	8 8 -16	; - 0.6
	69	[1106]	SETTABLE 	7 -14 8	; "width" -
	70	[1107]	GETUPVAL 	8 5	; more_options_param
	71	[1107]	GETTABLE 	8 8 -17	; "left_text"
	72	[1107]	SETTABLE 	7 -17 8	; "left_text" -
	73	[1108]	GETUPVAL 	8 5	; more_options_param
	74	[1108]	GETTABLE 	8 8 -18	; "right_text"
	75	[1108]	SETTABLE 	7 -18 8	; "right_text" -
	76	[1109]	GETTABLE 	8 4 -20	; 1
	77	[1109]	SETTABLE 	7 -19 8	; "left_value" -
	78	[1110]	GETUPVAL 	8 5	; more_options_param
	79	[1110]	GETTABLE 	8 8 -9	; "left_min"
	80	[1110]	SETTABLE 	7 -9 8	; "left_min" -
	81	[1111]	GETUPVAL 	8 5	; more_options_param
	82	[1111]	GETTABLE 	8 8 -21	; "left_max"
	83	[1111]	SETTABLE 	7 -21 8	; "left_max" -
	84	[1112]	GETUPVAL 	8 5	; more_options_param
	85	[1112]	GETTABLE 	8 8 -22	; "left_step"
	86	[1112]	SETTABLE 	7 -22 8	; "left_step" -
	87	[1113]	GETUPVAL 	8 5	; more_options_param
	88	[1113]	GETTABLE 	8 8 -23	; "left_hold_step"
	89	[1113]	SETTABLE 	7 -23 8	; "left_hold_step" -
	90	[1114]	GETTABLE 	8 4 -25	; 2
	91	[1114]	SETTABLE 	7 -24 8	; "right_value" -
	92	[1115]	GETUPVAL 	8 5	; more_options_param
	93	[1115]	GETTABLE 	8 8 -26	; "right_min"
	94	[1115]	SETTABLE 	7 -26 8	; "right_min" -
	95	[1116]	GETUPVAL 	8 5	; more_options_param
	96	[1116]	GETTABLE 	8 8 -27	; "right_max"
	97	[1116]	SETTABLE 	7 -27 8	; "right_max" -
	98	[1117]	GETUPVAL 	8 5	; more_options_param
	99	[1117]	GETTABLE 	8 8 -28	; "right_step"
	100	[1117]	SETTABLE 	7 -28 8	; "right_step" -
	101	[1118]	GETUPVAL 	8 5	; more_options_param
	102	[1118]	GETTABLE 	8 8 -29	; "right_hold_step"
	103	[1118]	SETTABLE 	7 -29 8	; "right_hold_step" -
	104	[1119]	GETUPVAL 	8 7	; name_text
	105	[1119]	TEST     	8 0 1
	106	[1119]	JMP      	3	; to 110
	107	[1119]	GETUPVAL 	8 9	; _
	108	[1119]	LOADK    	9 -31	; "Set values"
	109	[1119]	CALL     	8 2 2
	110	[1119]	SETTABLE 	7 -30 8	; "title_text" -
	111	[1120]	GETUPVAL 	8 5	; more_options_param
	112	[1120]	GETTABLE 	8 8 -32	; "info_text"
	113	[1120]	SETTABLE 	7 -32 8	; "info_text" -
	114	[1121]	SETTABLE 	7 -33 -5	; "keep_shown_on_apply" true
	115	[1136]	CLOSURE  	8 1	; 0x7f9102414410
	116	[1136]	MOVE     	0 2
	117	[1136]	GETUPVAL 	0 0	; self
	118	[1136]	GETUPVAL 	0 6	; name
	119	[1136]	GETUPVAL 	0 4	; event
	120	[1136]	GETUPVAL 	0 10	; args
	121	[1136]	MOVE     	0 1
	122	[1136]	SETTABLE 	7 -34 8	; "callback" -
	123	[1137]	GETUPVAL 	8 9	; _
	124	[1137]	LOADK    	9 -36	; "Set as default"
	125	[1137]	CALL     	8 2 2
	126	[1137]	SETTABLE 	7 -35 8	; "extra_text" -
	127	[1159]	CLOSURE  	8 2	; 0x7f9102414e60
	128	[1159]	GETUPVAL 	0 5	; more_options_param
	129	[1159]	GETUPVAL 	0 11	; T
	130	[1159]	GETUPVAL 	0 1	; UIManager
	131	[1159]	GETUPVAL 	0 12	; ConfirmBox
	132	[1159]	GETUPVAL 	0 9	; _
	133	[1159]	GETUPVAL 	0 7	; name_text
	134	[1159]	GETUPVAL 	0 6	; name
	135	[1159]	GETUPVAL 	0 0	; self
	136	[1159]	SETTABLE 	7 -37 8	; "extra_callback" -
	137	[1105]	CALL     	5 3 2
	138	[1160]	MOVE     	2 5
	139	[1160]	JMP      	126	; to 266
	140	[1162]	GETGLOBAL	3 -10	; require
	141	[1162]	LOADK    	4 -38	; "ui/widget/spinwidget"
	142	[1162]	CALL     	3 2 2
	143	[1163]	LOADK    	4 -39	; 0
	144	[1164]	GETUPVAL 	5 5	; more_options_param
	145	[1164]	GETTABLE 	5 5 -40	; "value_hold_step"
	146	[1164]	TEST     	5 0 0
	147	[1164]	JMP      	3	; to 151
	148	[1165]	GETUPVAL 	5 5	; more_options_param
	149	[1165]	GETTABLE 	4 5 -40	; "value_hold_step"
	150	[1165]	JMP      	12	; to 163
	151	[1166]	GETUPVAL 	5 3	; values
	152	[1166]	TEST     	5 0 0
	153	[1166]	JMP      	9	; to 163
	154	[1166]	GETUPVAL 	5 3	; values
	155	[1166]	LEN      	5 5
	156	[1166]	LT       	0 -20 5	; 1 -
	157	[1166]	JMP      	5	; to 163
	158	[1167]	GETUPVAL 	5 3	; values
	159	[1167]	GETTABLE 	5 5 -25	; 2
	160	[1167]	GETUPVAL 	6 3	; values
	161	[1167]	GETTABLE 	6 6 -20	; 1
	162	[1167]	SUB      	4 5 6
	163	[1169]	GETUPVAL 	5 0	; self
	164	[1169]	GETTABLE 	5 5 -12	; "configurable"
	165	[1169]	GETUPVAL 	6 6	; name
	166	[1169]	GETTABLE 	5 5 6
	167	[1170]	LOADNIL  	6 6
	168	[1171]	GETUPVAL 	7 5	; more_options_param
	169	[1171]	GETTABLE 	7 7 -41	; "value_table"
	170	[1171]	TEST     	7 0 0
	171	[1171]	JMP      	17	; to 189
	172	[1172]	GETUPVAL 	7 5	; more_options_param
	173	[1172]	GETTABLE 	7 7 -42	; "args_table"
	174	[1172]	TEST     	7 0 0
	175	[1172]	JMP      	12	; to 188
	176	[1173]	GETGLOBAL	7 -43	; pairs
	177	[1173]	GETUPVAL 	8 5	; more_options_param
	178	[1173]	GETTABLE 	8 8 -42	; "args_table"
	179	[1173]	CALL     	7 2 4
	180	[1173]	JMP      	4	; to 185
	181	[1174]	EQ       	0 11 5
	182	[1174]	JMP      	2	; to 185
	183	[1175]	MOVE     	6 10
	184	[1176]	JMP      	4	; to 189
	185	[1173]	TFORLOOP 	7 2
	186	[1177]	JMP      	-6	; to 181
	187	[1178]	JMP      	1	; to 189
	188	[1180]	MOVE     	6 5
	189	[1183]	SELF     	7 3 -13	; "new"
	190	[1183]	NEWTABLE 	9 0 15
	191	[1184]	GETUPVAL 	10 8	; Screen
	192	[1184]	SELF     	10 10 -15	; "getWidth"
	193	[1184]	CALL     	10 2 2
	194	[1184]	MUL      	10 10 -16	; - 0.6
	195	[1184]	SETTABLE 	9 -14 10	; "width" -
	196	[1185]	SETTABLE 	9 -44 5	; "value" -
	197	[1186]	SETTABLE 	9 -45 6	; "value_index" -
	198	[1187]	GETUPVAL 	10 5	; more_options_param
	199	[1187]	GETTABLE 	10 10 -41	; "value_table"
	200	[1187]	SETTABLE 	9 -41 10	; "value_table" -
	201	[1188]	GETUPVAL 	10 5	; more_options_param
	202	[1188]	GETTABLE 	10 10 -46	; "value_min"
	203	[1188]	TEST     	10 0 1
	204	[1188]	JMP      	2	; to 207
	205	[1188]	GETUPVAL 	10 3	; values
	206	[1188]	GETTABLE 	10 10 -20	; 1
	207	[1188]	SETTABLE 	9 -46 10	; "value_min" -
	208	[1189]	GETUPVAL 	10 5	; more_options_param
	209	[1189]	GETTABLE 	10 10 -47	; "value_step"
	210	[1189]	TEST     	10 0 1
	211	[1189]	JMP      	1	; to 213
	212	[1189]	LOADK    	10 -20	; 1
	213	[1189]	SETTABLE 	9 -47 10	; "value_step" -
	214	[1190]	SETTABLE 	9 -40 4	; "value_hold_step" -
	215	[1191]	GETUPVAL 	10 5	; more_options_param
	216	[1191]	GETTABLE 	10 10 -48	; "value_max"
	217	[1191]	TEST     	10 0 1
	218	[1191]	JMP      	4	; to 223
	219	[1191]	GETUPVAL 	10 3	; values
	220	[1191]	GETUPVAL 	11 3	; values
	221	[1191]	LEN      	11 11
	222	[1191]	GETTABLE 	10 10 11
	223	[1191]	SETTABLE 	9 -48 10	; "value_max" -
	224	[1192]	GETUPVAL 	10 5	; more_options_param
	225	[1192]	GETTABLE 	10 10 -49	; "precision"
	226	[1192]	TEST     	10 0 1
	227	[1192]	JMP      	1	; to 229
	228	[1192]	LOADK    	10 -50	; "%02d"
	229	[1192]	SETTABLE 	9 -49 10	; "precision" -
	230	[1193]	SETTABLE 	9 -33 -5	; "keep_shown_on_apply" true
	231	[1194]	GETUPVAL 	10 9	; _
	232	[1194]	LOADK    	11 -36	; "Set as default"
	233	[1194]	CALL     	10 2 2
	234	[1194]	SETTABLE 	9 -35 10	; "extra_text" -
	235	[1223]	CLOSURE  	10 3	; 0x7f9102414710
	236	[1223]	GETUPVAL 	0 5	; more_options_param
	237	[1223]	GETUPVAL 	0 1	; UIManager
	238	[1223]	GETUPVAL 	0 12	; ConfirmBox
	239	[1223]	GETUPVAL 	0 11	; T
	240	[1223]	GETUPVAL 	0 9	; _
	241	[1223]	GETUPVAL 	0 7	; name_text
	242	[1223]	GETUPVAL 	0 6	; name
	243	[1223]	GETUPVAL 	0 0	; self
	244	[1223]	SETTABLE 	9 -37 10	; "extra_callback" -
	245	[1224]	GETUPVAL 	10 7	; name_text
	246	[1224]	TEST     	10 0 1
	247	[1224]	JMP      	3	; to 251
	248	[1224]	GETUPVAL 	10 9	; _
	249	[1224]	LOADK    	11 -51	; "Set value"
	250	[1224]	CALL     	10 2 2
	251	[1224]	SETTABLE 	9 -30 10	; "title_text" -
	252	[1225]	GETUPVAL 	10 5	; more_options_param
	253	[1225]	GETTABLE 	10 10 -32	; "info_text"
	254	[1225]	SETTABLE 	9 -32 10	; "info_text" -
	255	[1255]	CLOSURE  	10 4	; 0x7f9102416520
	256	[1255]	MOVE     	0 2
	257	[1255]	GETUPVAL 	0 0	; self
	258	[1255]	GETUPVAL 	0 5	; more_options_param
	259	[1255]	GETUPVAL 	0 6	; name
	260	[1255]	GETUPVAL 	0 4	; event
	261	[1255]	GETUPVAL 	0 10	; args
	262	[1255]	MOVE     	0 1
	263	[1255]	SETTABLE 	9 -34 10	; "callback" -
	264	[1183]	CALL     	7 3 2
	265	[1256]	MOVE     	2 7
	266	[1258]	GETUPVAL 	3 1	; UIManager
	267	[1258]	SELF     	3 3 -52	; "show"
	268	[1258]	MOVE     	5 2
	269	[1258]	CALL     	3 3 1
	270	[1258]	CLOSE    	2
	271	[1260]	GETUPVAL 	2 2	; delay_repaint
	272	[1260]	TEST     	2 0 1
	273	[1260]	JMP      	2	; to 276
	274	[1261]	MOVE     	2 0
	275	[1261]	CALL     	2 1 1
	276	[1263]	RETURN   	0 1

function <./frontend/ui/widget/configdialog.lua:1064,1078> (20 instructions, 80 bytes at 0x7f9102413890)
0 params, 4 slots, 2 upvalues, 0 locals, 7 constants, 1 function
	1	[1065]	GETUPVAL 	0 0	; self
	2	[1065]	SETTABLE 	0 -1 -2	; "skip_paint" nil
	3	[1066]	GETUPVAL 	0 0	; self
	4	[1066]	GETTABLE 	0 0 -3	; "config_options"
	5	[1066]	GETTABLE 	0 0 -4	; "needs_redraw_on_change"
	6	[1066]	TEST     	0 0 0
	7	[1066]	JMP      	6	; to 14
	8	[1070]	GETUPVAL 	0 1	; UIManager
	9	[1070]	SELF     	0 0 -5	; "setDirty"
	10	[1070]	LOADK    	2 -6	; "all"
	11	[1070]	LOADK    	3 -7	; "partial"
	12	[1070]	CALL     	0 4 1
	13	[1070]	JMP      	6	; to 20
	14	[1074]	GETUPVAL 	0 1	; UIManager
	15	[1074]	SELF     	0 0 -5	; "setDirty"
	16	[1074]	GETUPVAL 	2 0	; self
	17	[1076]	CLOSURE  	3 0	; 0x7f9102413dd0
	18	[1076]	GETUPVAL 	0 0	; self
	19	[1074]	CALL     	0 4 1
	20	[1078]	RETURN   	0 1

function <./frontend/ui/widget/configdialog.lua:1074,1076> (6 instructions, 24 bytes at 0x7f9102413dd0)
0 params, 2 slots, 1 upvalue, 0 locals, 3 constants, 0 functions
	1	[1075]	LOADK    	0 -1	; "ui"
	2	[1075]	GETUPVAL 	1 0	; self
	3	[1075]	GETTABLE 	1 1 -2	; "dialog_frame"
	4	[1075]	GETTABLE 	1 1 -3	; "dimen"
	5	[1075]	RETURN   	0 3
	6	[1076]	RETURN   	0 1

function <./frontend/ui/widget/configdialog.lua:1122,1136> (41 instructions, 164 bytes at 0x7f9102414410)
2 params, 8 slots, 6 upvalues, 3 locals, 7 constants, 0 functions
	1	[1123]	GETUPVAL 	2 0	; widget
	2	[1123]	SELF     	2 2 -1	; "hasMoved"
	3	[1123]	CALL     	2 2 2
	4	[1123]	TEST     	2 0 0
	5	[1123]	JMP      	9	; to 15
	6	[1123]	GETUPVAL 	2 1	; self
	7	[1123]	GETTABLE 	2 2 -2	; "_dialog_closed"
	8	[1123]	TEST     	2 0 1
	9	[1123]	JMP      	5	; to 15
	10	[1126]	GETUPVAL 	2 1	; self
	11	[1126]	SETTABLE 	2 -2 -3	; "_dialog_closed" true
	12	[1127]	GETUPVAL 	2 1	; self
	13	[1127]	SELF     	2 2 -4	; "closeDialog"
	14	[1127]	CALL     	2 2 1
	15	[1129]	NEWTABLE 	2 2 0
	16	[1129]	MOVE     	3 0
	17	[1129]	MOVE     	4 1
	18	[1129]	SETLIST  	2 2 1	; 1
	19	[1130]	GETUPVAL 	3 1	; self
	20	[1130]	SELF     	3 3 -5	; "onConfigChoice"
	21	[1130]	GETUPVAL 	5 2	; name
	22	[1130]	MOVE     	6 2
	23	[1130]	CALL     	3 4 1
	24	[1131]	GETUPVAL 	3 3	; event
	25	[1131]	TEST     	3 0 0
	26	[1131]	JMP      	14	; to 41
	27	[1132]	GETUPVAL 	3 4	; args
	28	[1132]	TEST     	3 0 1
	29	[1132]	JMP      	1	; to 31
	30	[1132]	NEWTABLE 	3 0 0
	31	[1132]	SETUPVAL 	3 4	; args
	32	[1133]	GETUPVAL 	3 1	; self
	33	[1133]	SELF     	3 3 -6	; "onConfigEvent"
	34	[1133]	GETUPVAL 	5 3	; event
	35	[1133]	MOVE     	6 2
	36	[1133]	GETUPVAL 	7 5	; refresh_callback
	37	[1133]	CALL     	3 5 1
	38	[1134]	GETUPVAL 	3 1	; self
	39	[1134]	SELF     	3 3 -7	; "update"
	40	[1134]	CALL     	3 2 1
	41	[1136]	RETURN   	0 1

function <./frontend/ui/widget/configdialog.lua:1138,1159> (52 instructions, 208 bytes at 0x7f9102414e60)
2 params, 13 slots, 8 upvalues, 4 locals, 10 constants, 1 function
	1	[1139]	NEWTABLE 	2 2 0
	2	[1139]	MOVE     	3 0
	3	[1139]	MOVE     	4 1
	4	[1139]	SETLIST  	2 2 1	; 1
	5	[1140]	LOADNIL  	3 3
	6	[1141]	GETUPVAL 	4 0	; more_options_param
	7	[1141]	GETTABLE 	4 4 -1	; "show_true_value_func"
	8	[1141]	TEST     	4 0 0
	9	[1141]	JMP      	6	; to 16
	10	[1142]	GETUPVAL 	4 0	; more_options_param
	11	[1142]	GETTABLE 	4 4 -1	; "show_true_value_func"
	12	[1142]	MOVE     	5 2
	13	[1142]	CALL     	4 2 2
	14	[1142]	MOVE     	3 4
	15	[1142]	JMP      	6	; to 22
	16	[1144]	GETUPVAL 	4 1	; T
	17	[1144]	LOADK    	5 -2	; "%1, %2"
	18	[1144]	MOVE     	6 0
	19	[1144]	MOVE     	7 1
	20	[1144]	CALL     	4 4 2
	21	[1144]	MOVE     	3 4
	22	[1146]	GETUPVAL 	4 2	; UIManager
	23	[1146]	SELF     	4 4 -3	; "show"
	24	[1146]	GETUPVAL 	6 3	; ConfirmBox
	25	[1146]	SELF     	6 6 -4	; "new"
	26	[1146]	NEWTABLE 	8 0 3
	27	[1147]	GETUPVAL 	9 1	; T
	28	[1147]	GETUPVAL 	10 4	; _
	29	[1147]	LOADK    	11 -6	; "Set default %1 to %2?"
	30	[1147]	CALL     	10 2 2
	31	[1147]	GETUPVAL 	11 5	; name_text
	32	[1147]	TEST     	11 0 1
	33	[1147]	JMP      	1	; to 35
	34	[1147]	LOADK    	11 -7	; ""
	35	[1147]	MOVE     	12 3
	36	[1147]	CALL     	9 4 2
	37	[1147]	SETTABLE 	8 -5 9	; "text" -
	38	[1148]	GETUPVAL 	9 1	; T
	39	[1148]	GETUPVAL 	10 4	; _
	40	[1148]	LOADK    	11 -9	; "Set as default"
	41	[1148]	CALL     	10 2 0
	42	[1148]	CALL     	9 0 2
	43	[1148]	SETTABLE 	8 -8 9	; "ok_text" -
	44	[1156]	CLOSURE  	9 0	; 0x7f91024150d0
	45	[1156]	GETUPVAL 	0 6	; name
	46	[1156]	GETUPVAL 	0 7	; self
	47	[1156]	MOVE     	0 2
	48	[1156]	GETUPVAL 	0 2	; UIManager
	49	[1156]	SETTABLE 	8 -10 9	; "ok_callback" -
	50	[1146]	CALL     	6 3 0
	51	[1146]	CALL     	4 0 1
	52	[1159]	RETURN   	0 1

function <./frontend/ui/widget/configdialog.lua:1149,1156> (22 instructions, 88 bytes at 0x7f91024150d0)
0 params, 4 slots, 4 upvalues, 0 locals, 7 constants, 1 function
	1	[1150]	GETUPVAL 	0 1	; self
	2	[1150]	GETTABLE 	0 0 -1	; "config_options"
	3	[1150]	GETTABLE 	0 0 -2	; "prefix"
	4	[1150]	LOADK    	1 -3	; "_"
	5	[1150]	GETUPVAL 	2 0	; name
	6	[1150]	CONCAT   	0 0 2
	7	[1150]	SETUPVAL 	0 0	; name
	8	[1151]	GETGLOBAL	0 -4	; G_reader_settings
	9	[1151]	SELF     	0 0 -5	; "saveSetting"
	10	[1151]	GETUPVAL 	2 0	; name
	11	[1151]	GETUPVAL 	3 2	; value_tables
	12	[1151]	CALL     	0 4 1
	13	[1152]	GETUPVAL 	0 1	; self
	14	[1152]	SELF     	0 0 -6	; "update"
	15	[1152]	CALL     	0 2 1
	16	[1153]	GETUPVAL 	0 3	; UIManager
	17	[1153]	SELF     	0 0 -7	; "setDirty"
	18	[1153]	GETUPVAL 	2 1	; self
	19	[1155]	CLOSURE  	3 0	; 0x7f9102415910
	20	[1155]	GETUPVAL 	0 1	; self
	21	[1153]	CALL     	0 4 1
	22	[1156]	RETURN   	0 1

function <./frontend/ui/widget/configdialog.lua:1153,1155> (6 instructions, 24 bytes at 0x7f9102415910)
0 params, 2 slots, 1 upvalue, 0 locals, 3 constants, 0 functions
	1	[1154]	LOADK    	0 -1	; "ui"
	2	[1154]	GETUPVAL 	1 0	; self
	3	[1154]	GETTABLE 	1 1 -2	; "dialog_frame"
	4	[1154]	GETTABLE 	1 1 -3	; "dimen"
	5	[1154]	RETURN   	0 3
	6	[1155]	RETURN   	0 1

function <./frontend/ui/widget/configdialog.lua:1195,1223> (43 instructions, 172 bytes at 0x7f9102414710)
1 param, 11 slots, 8 upvalues, 2 locals, 10 constants, 1 function
	1	[1197]	GETUPVAL 	2 0	; more_options_param
	2	[1197]	GETTABLE 	2 2 -1	; "show_true_value_func"
	3	[1197]	TEST     	2 0 0
	4	[1197]	JMP      	6	; to 11
	5	[1198]	GETUPVAL 	2 0	; more_options_param
	6	[1198]	GETTABLE 	2 2 -1	; "show_true_value_func"
	7	[1198]	GETTABLE 	3 0 -2	; "value"
	8	[1198]	CALL     	2 2 2
	9	[1198]	MOVE     	1 2
	10	[1198]	JMP      	1	; to 12
	11	[1200]	GETTABLE 	1 0 -2	; "value"
	12	[1202]	GETUPVAL 	2 1	; UIManager
	13	[1202]	SELF     	2 2 -3	; "show"
	14	[1202]	GETUPVAL 	4 2	; ConfirmBox
	15	[1202]	SELF     	4 4 -4	; "new"
	16	[1202]	NEWTABLE 	6 0 3
	17	[1203]	GETUPVAL 	7 3	; T
	18	[1203]	GETUPVAL 	8 4	; _
	19	[1203]	LOADK    	9 -6	; "Set default %1 to %2?"
	20	[1203]	CALL     	8 2 2
	21	[1203]	GETUPVAL 	9 5	; name_text
	22	[1203]	TEST     	9 0 1
	23	[1203]	JMP      	1	; to 25
	24	[1203]	LOADK    	9 -7	; ""
	25	[1203]	MOVE     	10 1
	26	[1203]	CALL     	7 4 2
	27	[1203]	SETTABLE 	6 -5 7	; "text" -
	28	[1204]	GETUPVAL 	7 3	; T
	29	[1204]	GETUPVAL 	8 4	; _
	30	[1204]	LOADK    	9 -9	; "Set as default"
	31	[1204]	CALL     	8 2 0
	32	[1204]	CALL     	7 0 2
	33	[1204]	SETTABLE 	6 -8 7	; "ok_text" -
	34	[1220]	CLOSURE  	7 0	; 0x7f9102415fa0
	35	[1220]	GETUPVAL 	0 6	; name
	36	[1220]	GETUPVAL 	0 7	; self
	37	[1220]	GETUPVAL 	0 0	; more_options_param
	38	[1220]	MOVE     	0 0
	39	[1220]	GETUPVAL 	0 1	; UIManager
	40	[1220]	SETTABLE 	6 -10 7	; "ok_callback" -
	41	[1202]	CALL     	4 3 0
	42	[1202]	CALL     	2 0 1
	43	[1223]	RETURN   	0 1

function <./frontend/ui/widget/configdialog.lua:1205,1220> (48 instructions, 192 bytes at 0x7f9102415fa0)
0 params, 5 slots, 5 upvalues, 0 locals, 11 constants, 1 function
	1	[1206]	GETUPVAL 	0 1	; self
	2	[1206]	GETTABLE 	0 0 -1	; "config_options"
	3	[1206]	GETTABLE 	0 0 -2	; "prefix"
	4	[1206]	LOADK    	1 -3	; "_"
	5	[1206]	GETUPVAL 	2 0	; name
	6	[1206]	CONCAT   	0 0 2
	7	[1206]	SETUPVAL 	0 0	; name
	8	[1207]	GETUPVAL 	0 2	; more_options_param
	9	[1207]	GETTABLE 	0 0 -4	; "value_table"
	10	[1207]	TEST     	0 0 0
	11	[1207]	JMP      	21	; to 33
	12	[1208]	GETUPVAL 	0 2	; more_options_param
	13	[1208]	GETTABLE 	0 0 -5	; "args_table"
	14	[1208]	TEST     	0 0 0
	15	[1208]	JMP      	10	; to 26
	16	[1209]	GETGLOBAL	0 -6	; G_reader_settings
	17	[1209]	SELF     	0 0 -7	; "saveSetting"
	18	[1209]	GETUPVAL 	2 0	; name
	19	[1209]	GETUPVAL 	3 2	; more_options_param
	20	[1209]	GETTABLE 	3 3 -5	; "args_table"
	21	[1209]	GETUPVAL 	4 3	; spin
	22	[1209]	GETTABLE 	4 4 -8	; "value_index"
	23	[1209]	GETTABLE 	3 3 4
	24	[1209]	CALL     	0 4 1
	25	[1209]	JMP      	13	; to 39
	26	[1211]	GETGLOBAL	0 -6	; G_reader_settings
	27	[1211]	SELF     	0 0 -7	; "saveSetting"
	28	[1211]	GETUPVAL 	2 0	; name
	29	[1211]	GETUPVAL 	3 3	; spin
	30	[1211]	GETTABLE 	3 3 -8	; "value_index"
	31	[1211]	CALL     	0 4 1
	32	[1212]	JMP      	6	; to 39
	33	[1214]	GETGLOBAL	0 -6	; G_reader_settings
	34	[1214]	SELF     	0 0 -7	; "saveSetting"
	35	[1214]	GETUPVAL 	2 0	; name
	36	[1214]	GETUPVAL 	3 3	; spin
	37	[1214]	GETTABLE 	3 3 -9	; "value"
	38	[1214]	CALL     	0 4 1
	39	[1216]	GETUPVAL 	0 1	; self
	40	[1216]	SELF     	0 0 -10	; "update"
	41	[1216]	CALL     	0 2 1
	42	[1217]	GETUPVAL 	0 4	; UIManager
	43	[1217]	SELF     	0 0 -11	; "setDirty"
	44	[1217]	GETUPVAL 	2 1	; self
	45	[1219]	CLOSURE  	3 0	; 0x7f9102416460
	46	[1219]	GETUPVAL 	0 1	; self
	47	[1217]	CALL     	0 4 1
	48	[1220]	RETURN   	0 1

function <./frontend/ui/widget/configdialog.lua:1217,1219> (6 instructions, 24 bytes at 0x7f9102416460)
0 params, 2 slots, 1 upvalue, 0 locals, 3 constants, 0 functions
	1	[1218]	LOADK    	0 -1	; "ui"
	2	[1218]	GETUPVAL 	1 0	; self
	3	[1218]	GETTABLE 	1 1 -2	; "dialog_frame"
	4	[1218]	GETTABLE 	1 1 -3	; "dimen"
	5	[1218]	RETURN   	0 3
	6	[1219]	RETURN   	0 1

function <./frontend/ui/widget/configdialog.lua:1226,1255> (85 instructions, 340 bytes at 0x7f9102416520)
1 param, 6 slots, 7 upvalues, 1 local, 11 constants, 0 functions
	1	[1227]	GETUPVAL 	1 0	; widget
	2	[1227]	SELF     	1 1 -1	; "hasMoved"
	3	[1227]	CALL     	1 2 2
	4	[1227]	TEST     	1 0 0
	5	[1227]	JMP      	9	; to 15
	6	[1227]	GETUPVAL 	1 1	; self
	7	[1227]	GETTABLE 	1 1 -2	; "_dialog_closed"
	8	[1227]	TEST     	1 0 1
	9	[1227]	JMP      	5	; to 15
	10	[1230]	GETUPVAL 	1 1	; self
	11	[1230]	SETTABLE 	1 -2 -3	; "_dialog_closed" true
	12	[1231]	GETUPVAL 	1 1	; self
	13	[1231]	SELF     	1 1 -4	; "closeDialog"
	14	[1231]	CALL     	1 2 1
	15	[1233]	GETUPVAL 	1 2	; more_options_param
	16	[1233]	GETTABLE 	1 1 -5	; "value_table"
	17	[1233]	TEST     	1 0 0
	18	[1233]	JMP      	19	; to 38
	19	[1234]	GETUPVAL 	1 2	; more_options_param
	20	[1234]	GETTABLE 	1 1 -6	; "args_table"
	21	[1234]	TEST     	1 0 0
	22	[1234]	JMP      	9	; to 32
	23	[1235]	GETUPVAL 	1 1	; self
	24	[1235]	SELF     	1 1 -7	; "onConfigChoice"
	25	[1235]	GETUPVAL 	3 3	; name
	26	[1235]	GETUPVAL 	4 2	; more_options_param
	27	[1235]	GETTABLE 	4 4 -6	; "args_table"
	28	[1235]	GETTABLE 	5 0 -8	; "value_index"
	29	[1235]	GETTABLE 	4 4 5
	30	[1235]	CALL     	1 4 1
	31	[1235]	JMP      	11	; to 43
	32	[1237]	GETUPVAL 	1 1	; self
	33	[1237]	SELF     	1 1 -7	; "onConfigChoice"
	34	[1237]	GETUPVAL 	3 3	; name
	35	[1237]	GETTABLE 	4 0 -8	; "value_index"
	36	[1237]	CALL     	1 4 1
	37	[1238]	JMP      	5	; to 43
	38	[1240]	GETUPVAL 	1 1	; self
	39	[1240]	SELF     	1 1 -7	; "onConfigChoice"
	40	[1240]	GETUPVAL 	3 3	; name
	41	[1240]	GETTABLE 	4 0 -9	; "value"
	42	[1240]	CALL     	1 4 1
	43	[1242]	GETUPVAL 	1 4	; event
	44	[1242]	TEST     	1 0 0
	45	[1242]	JMP      	39	; to 85
	46	[1243]	GETUPVAL 	1 5	; args
	47	[1243]	TEST     	1 0 1
	48	[1243]	JMP      	1	; to 50
	49	[1243]	NEWTABLE 	1 0 0
	50	[1243]	SETUPVAL 	1 5	; args
	51	[1244]	GETUPVAL 	1 2	; more_options_param
	52	[1244]	GETTABLE 	1 1 -5	; "value_table"
	53	[1244]	TEST     	1 0 0
	54	[1244]	JMP      	21	; to 76
	55	[1245]	GETUPVAL 	1 2	; more_options_param
	56	[1245]	GETTABLE 	1 1 -6	; "args_table"
	57	[1245]	TEST     	1 0 0
	58	[1245]	JMP      	10	; to 69
	59	[1246]	GETUPVAL 	1 1	; self
	60	[1246]	SELF     	1 1 -10	; "onConfigEvent"
	61	[1246]	GETUPVAL 	3 4	; event
	62	[1246]	GETUPVAL 	4 2	; more_options_param
	63	[1246]	GETTABLE 	4 4 -6	; "args_table"
	64	[1246]	GETTABLE 	5 0 -8	; "value_index"
	65	[1246]	GETTABLE 	4 4 5
	66	[1246]	GETUPVAL 	5 6	; refresh_callback
	67	[1246]	CALL     	1 5 1
	68	[1246]	JMP      	13	; to 82
	69	[1248]	GETUPVAL 	1 1	; self
	70	[1248]	SELF     	1 1 -10	; "onConfigEvent"
	71	[1248]	GETUPVAL 	3 4	; event
	72	[1248]	GETTABLE 	4 0 -8	; "value_index"
	73	[1248]	GETUPVAL 	5 6	; refresh_callback
	74	[1248]	CALL     	1 5 1
	75	[1249]	JMP      	6	; to 82
	76	[1251]	GETUPVAL 	1 1	; self
	77	[1251]	SELF     	1 1 -10	; "onConfigEvent"
	78	[1251]	GETUPVAL 	3 4	; event
	79	[1251]	GETTABLE 	4 0 -9	; "value"
	80	[1251]	GETUPVAL 	5 6	; refresh_callback
	81	[1251]	CALL     	1 5 1
	82	[1253]	GETUPVAL 	1 1	; self
	83	[1253]	SELF     	1 1 -11	; "update"
	84	[1253]	CALL     	1 2 1
	85	[1255]	RETURN   	0 1

function <./frontend/ui/widget/configdialog.lua:1266,1300> (55 instructions, 220 bytes at 0x7f9102416ca0)
6 params, 16 slots, 5 upvalues, 7 locals, 15 constants, 1 function
	1	[1267]	GETTABLE 	6 4 5
	2	[1268]	EQ       	0 1 -1	; - "font_fine_tune"
	3	[1268]	JMP      	2	; to 6
	4	[1269]	RETURN   	0 1
	5	[1269]	JMP      	10	; to 16
	6	[1271]	EQ       	0 1 -2	; - "h_page_margins"
	7	[1271]	JMP      	8	; to 16
	8	[1272]	GETUPVAL 	7 0	; T
	9	[1272]	GETUPVAL 	8 1	; _
	10	[1276]	LOADK    	9 -3	; "\n  left:  %1\n  right: %2\n"
	11	[1272]	CALL     	8 2 2
	12	[1277]	GETTABLE 	9 6 -4	; 1
	13	[1277]	GETTABLE 	10 6 -5	; 2
	14	[1272]	CALL     	7 4 2
	15	[1277]	MOVE     	6 7
	16	[1280]	GETGLOBAL	7 -6	; type
	17	[1280]	MOVE     	8 6
	18	[1280]	CALL     	7 2 2
	19	[1280]	EQ       	0 7 -7	; - "table"
	20	[1280]	JMP      	4	; to 25
	21	[1281]	GETUPVAL 	7 2	; dump
	22	[1281]	MOVE     	8 6
	23	[1281]	CALL     	7 2 2
	24	[1281]	MOVE     	6 7
	25	[1284]	GETUPVAL 	7 3	; UIManager
	26	[1284]	SELF     	7 7 -8	; "show"
	27	[1284]	GETUPVAL 	9 4	; ConfirmBox
	28	[1284]	SELF     	9 9 -9	; "new"
	29	[1284]	NEWTABLE 	11 0 3
	30	[1285]	GETUPVAL 	12 0	; T
	31	[1286]	GETUPVAL 	13 1	; _
	32	[1286]	LOADK    	14 -11	; "Set default %1 to %2?"
	33	[1286]	CALL     	13 2 2
	34	[1287]	TESTSET  	14 2 1
	35	[1287]	JMP      	1	; to 37
	36	[1287]	LOADK    	14 -12	; ""
	37	[1289]	MOVE     	15 6
	38	[1285]	CALL     	12 4 2
	39	[1289]	SETTABLE 	11 -10 12	; "text" -
	40	[1290]	GETUPVAL 	12 0	; T
	41	[1290]	GETUPVAL 	13 1	; _
	42	[1290]	LOADK    	14 -14	; "Set as default"
	43	[1290]	CALL     	13 2 0
	44	[1290]	CALL     	12 0 2
	45	[1290]	SETTABLE 	11 -13 12	; "ok_text" -
	46	[1298]	CLOSURE  	12 0	; 0x7f9102417390
	47	[1298]	MOVE     	0 1
	48	[1298]	MOVE     	0 0
	49	[1298]	MOVE     	0 3
	50	[1298]	MOVE     	0 5
	51	[1298]	GETUPVAL 	0 3	; UIManager
	52	[1298]	SETTABLE 	11 -15 12	; "ok_callback" -
	53	[1284]	CALL     	9 3 0
	54	[1284]	CALL     	7 0 1
	55	[1300]	RETURN   	0 1

function <./frontend/ui/widget/configdialog.lua:1291,1298> (24 instructions, 96 bytes at 0x7f9102417390)
0 params, 5 slots, 5 upvalues, 0 locals, 7 constants, 1 function
	1	[1292]	GETUPVAL 	0 1	; self
	2	[1292]	GETTABLE 	0 0 -1	; "config_options"
	3	[1292]	GETTABLE 	0 0 -2	; "prefix"
	4	[1292]	LOADK    	1 -3	; "_"
	5	[1292]	GETUPVAL 	2 0	; name
	6	[1292]	CONCAT   	0 0 2
	7	[1292]	SETUPVAL 	0 0	; name
	8	[1293]	GETGLOBAL	0 -4	; G_reader_settings
	9	[1293]	SELF     	0 0 -5	; "saveSetting"
	10	[1293]	GETUPVAL 	2 0	; name
	11	[1293]	GETUPVAL 	3 2	; values
	12	[1293]	GETUPVAL 	4 3	; position
	13	[1293]	GETTABLE 	3 3 4
	14	[1293]	CALL     	0 4 1
	15	[1294]	GETUPVAL 	0 1	; self
	16	[1294]	SELF     	0 0 -6	; "update"
	17	[1294]	CALL     	0 2 1
	18	[1295]	GETUPVAL 	0 4	; UIManager
	19	[1295]	SELF     	0 0 -7	; "setDirty"
	20	[1295]	GETUPVAL 	2 1	; self
	21	[1297]	CLOSURE  	3 0	; 0x7f9102417310
	22	[1297]	GETUPVAL 	0 1	; self
	23	[1295]	CALL     	0 4 1
	24	[1298]	RETURN   	0 1

function <./frontend/ui/widget/configdialog.lua:1295,1297> (6 instructions, 24 bytes at 0x7f9102417310)
0 params, 2 slots, 1 upvalue, 0 locals, 3 constants, 0 functions
	1	[1296]	LOADK    	0 -1	; "ui"
	2	[1296]	GETUPVAL 	1 0	; self
	3	[1296]	GETTABLE 	1 1 -2	; "dialog_frame"
	4	[1296]	GETTABLE 	1 1 -3	; "dimen"
	5	[1296]	RETURN   	0 3
	6	[1297]	RETURN   	0 1

function <./frontend/ui/widget/configdialog.lua:1304,1338> (64 instructions, 256 bytes at 0x7f9102417ba0)
6 params, 17 slots, 5 upvalues, 8 locals, 16 constants, 1 function
	1	[1305]	GETTABLE 	6 0 -1	; "configurable"
	2	[1305]	GETTABLE 	6 6 1
	3	[1305]	TEST     	6 0 1
	4	[1305]	JMP      	7	; to 12
	5	[1305]	EQ       	0 5 -2	; - "-"
	6	[1305]	JMP      	3	; to 10
	7	[1305]	GETTABLE 	6 4 -3	; 1
	8	[1305]	TEST     	6 0 1
	9	[1305]	JMP      	2	; to 12
	10	[1305]	LEN      	6 4
	11	[1305]	GETTABLE 	6 4 6
	12	[1307]	LOADNIL  	7 7
	13	[1309]	EQ       	0 1 -4	; - "h_page_margins"
	14	[1309]	JMP      	9	; to 24
	15	[1310]	GETUPVAL 	8 0	; T
	16	[1310]	GETUPVAL 	9 1	; _
	17	[1314]	LOADK    	10 -5	; "\n  left:  %1\n  right: %2\n"
	18	[1310]	CALL     	9 2 2
	19	[1315]	GETTABLE 	10 6 -3	; 1
	20	[1315]	GETTABLE 	11 6 -6	; 2
	21	[1310]	CALL     	8 4 2
	22	[1315]	MOVE     	7 8
	23	[1315]	JMP      	11	; to 35
	24	[1316]	GETGLOBAL	8 -7	; type
	25	[1316]	MOVE     	9 6
	26	[1316]	CALL     	8 2 2
	27	[1316]	EQ       	0 8 -8	; - "table"
	28	[1316]	JMP      	5	; to 34
	29	[1317]	GETUPVAL 	8 2	; dump
	30	[1317]	MOVE     	9 6
	31	[1317]	CALL     	8 2 2
	32	[1317]	MOVE     	7 8
	33	[1317]	JMP      	1	; to 35
	34	[1319]	MOVE     	7 6
	35	[1322]	GETUPVAL 	8 3	; UIManager
	36	[1322]	SELF     	8 8 -9	; "show"
	37	[1322]	GETUPVAL 	10 4	; ConfirmBox
	38	[1322]	SELF     	10 10 -10	; "new"
	39	[1322]	NEWTABLE 	12 0 3
	40	[1323]	GETUPVAL 	13 0	; T
	41	[1324]	GETUPVAL 	14 1	; _
	42	[1324]	LOADK    	15 -12	; "Set default %1 to %2?"
	43	[1324]	CALL     	14 2 2
	44	[1325]	TESTSET  	15 2 1
	45	[1325]	JMP      	1	; to 47
	46	[1325]	LOADK    	15 -13	; ""
	47	[1327]	MOVE     	16 7
	48	[1323]	CALL     	13 4 2
	49	[1327]	SETTABLE 	12 -11 13	; "text" -
	50	[1328]	GETUPVAL 	13 0	; T
	51	[1328]	GETUPVAL 	14 1	; _
	52	[1328]	LOADK    	15 -15	; "Set as default"
	53	[1328]	CALL     	14 2 0
	54	[1328]	CALL     	13 0 2
	55	[1328]	SETTABLE 	12 -14 13	; "ok_text" -
	56	[1336]	CLOSURE  	13 0	; 0x7f9102417fd0
	57	[1336]	MOVE     	0 1
	58	[1336]	MOVE     	0 0
	59	[1336]	MOVE     	0 6
	60	[1336]	GETUPVAL 	0 3	; UIManager
	61	[1336]	SETTABLE 	12 -16 13	; "ok_callback" -
	62	[1322]	CALL     	10 3 0
	63	[1322]	CALL     	8 0 1
	64	[1338]	RETURN   	0 1

function <./frontend/ui/widget/configdialog.lua:1329,1336> (22 instructions, 88 bytes at 0x7f9102417fd0)
0 params, 4 slots, 4 upvalues, 0 locals, 7 constants, 1 function
	1	[1330]	GETUPVAL 	0 1	; self
	2	[1330]	GETTABLE 	0 0 -1	; "config_options"
	3	[1330]	GETTABLE 	0 0 -2	; "prefix"
	4	[1330]	LOADK    	1 -3	; "_"
	5	[1330]	GETUPVAL 	2 0	; name
	6	[1330]	CONCAT   	0 0 2
	7	[1330]	SETUPVAL 	0 0	; name
	8	[1331]	GETGLOBAL	0 -4	; G_reader_settings
	9	[1331]	SELF     	0 0 -5	; "saveSetting"
	10	[1331]	GETUPVAL 	2 0	; name
	11	[1331]	GETUPVAL 	3 2	; current_value
	12	[1331]	CALL     	0 4 1
	13	[1332]	GETUPVAL 	0 1	; self
	14	[1332]	SELF     	0 0 -6	; "update"
	15	[1332]	CALL     	0 2 1
	16	[1333]	GETUPVAL 	0 3	; UIManager
	17	[1333]	SELF     	0 0 -7	; "setDirty"
	18	[1333]	GETUPVAL 	2 1	; self
	19	[1335]	CLOSURE  	3 0	; 0x7f9102418440
	20	[1335]	GETUPVAL 	0 1	; self
	21	[1333]	CALL     	0 4 1
	22	[1336]	RETURN   	0 1

function <./frontend/ui/widget/configdialog.lua:1333,1335> (6 instructions, 24 bytes at 0x7f9102418440)
0 params, 2 slots, 1 upvalue, 0 locals, 3 constants, 0 functions
	1	[1334]	LOADK    	0 -1	; "ui"
	2	[1334]	GETUPVAL 	1 0	; self
	3	[1334]	GETTABLE 	1 1 -2	; "dialog_frame"
	4	[1334]	GETTABLE 	1 1 -3	; "dimen"
	5	[1334]	RETURN   	0 3
	6	[1335]	RETURN   	0 1

function <./frontend/ui/widget/configdialog.lua:1340,1346> (12 instructions, 48 bytes at 0x7f9102415690)
1 param, 4 slots, 1 upvalue, 1 local, 2 constants, 0 functions
	1	[1341]	GETUPVAL 	1 0	; UIManager
	2	[1341]	SELF     	1 1 -1	; "close"
	3	[1341]	MOVE     	3 0
	4	[1341]	CALL     	1 3 1
	5	[1342]	GETTABLE 	1 0 -2	; "close_callback"
	6	[1342]	TEST     	1 0 0
	7	[1342]	JMP      	2	; to 10
	8	[1343]	GETTABLE 	1 0 -2	; "close_callback"
	9	[1343]	CALL     	1 1 1
	10	[1345]	LOADBOOL 	1 1 0
	11	[1345]	RETURN   	1 2
	12	[1346]	RETURN   	0 1

function <./frontend/ui/widget/configdialog.lua:1348,1353> (12 instructions, 48 bytes at 0x7f91024187b0)
3 params, 6 slots, 0 upvalues, 3 locals, 5 constants, 0 functions
	1	[1349]	GETTABLE 	3 2 -1	; "pos"
	2	[1349]	SELF     	3 3 -2	; "notIntersectWith"
	3	[1349]	GETTABLE 	5 0 -3	; "dialog_frame"
	4	[1349]	GETTABLE 	5 5 -4	; "dimen"
	5	[1349]	CALL     	3 3 2
	6	[1349]	TEST     	3 0 0
	7	[1349]	JMP      	4	; to 12
	8	[1350]	SELF     	3 0 -5	; "closeDialog"
	9	[1350]	CALL     	3 2 1
	10	[1351]	LOADBOOL 	3 1 0
	11	[1351]	RETURN   	3 2
	12	[1353]	RETURN   	0 1

function <./frontend/ui/widget/configdialog.lua:1355,1367> (50 instructions, 200 bytes at 0x7f910240c600)
3 params, 7 slots, 1 upvalue, 4 locals, 14 constants, 0 functions
	1	[1356]	NEWTABLE 	3 0 4
	2	[1357]	GETGLOBAL	4 -2	; DTAP_ZONE_CONFIG
	3	[1357]	GETTABLE 	4 4 -1	; "x"
	4	[1357]	GETUPVAL 	5 0	; Screen
	5	[1357]	SELF     	5 5 -3	; "getWidth"
	6	[1357]	CALL     	5 2 2
	7	[1357]	MUL      	4 4 5
	8	[1357]	SETTABLE 	3 -1 4	; "x" -
	9	[1358]	GETGLOBAL	4 -2	; DTAP_ZONE_CONFIG
	10	[1358]	GETTABLE 	4 4 -4	; "y"
	11	[1358]	GETUPVAL 	5 0	; Screen
	12	[1358]	SELF     	5 5 -5	; "getHeight"
	13	[1358]	CALL     	5 2 2
	14	[1358]	MUL      	4 4 5
	15	[1358]	SETTABLE 	3 -4 4	; "y" -
	16	[1359]	GETGLOBAL	4 -2	; DTAP_ZONE_CONFIG
	17	[1359]	GETTABLE 	4 4 -6	; "w"
	18	[1359]	GETUPVAL 	5 0	; Screen
	19	[1359]	SELF     	5 5 -3	; "getWidth"
	20	[1359]	CALL     	5 2 2
	21	[1359]	MUL      	4 4 5
	22	[1359]	SETTABLE 	3 -6 4	; "w" -
	23	[1360]	GETGLOBAL	4 -2	; DTAP_ZONE_CONFIG
	24	[1360]	GETTABLE 	4 4 -7	; "h"
	25	[1360]	GETUPVAL 	5 0	; Screen
	26	[1360]	SELF     	5 5 -5	; "getHeight"
	27	[1360]	CALL     	5 2 2
	28	[1360]	MUL      	4 4 5
	29	[1360]	SETTABLE 	3 -7 4	; "h" -
	30	[1362]	GETTABLE 	4 2 -8	; "direction"
	31	[1362]	EQ       	0 4 -9	; - "south"
	32	[1362]	JMP      	17	; to 50
	33	[1362]	GETTABLE 	4 2 -10	; "pos"
	34	[1362]	SELF     	4 4 -11	; "intersectWith"
	35	[1362]	GETTABLE 	6 0 -12	; "dialog_frame"
	36	[1362]	GETTABLE 	6 6 -13	; "dimen"
	37	[1362]	CALL     	4 3 2
	38	[1363]	TEST     	4 0 1
	39	[1363]	JMP      	6	; to 46
	40	[1363]	GETTABLE 	4 2 -10	; "pos"
	41	[1363]	SELF     	4 4 -11	; "intersectWith"
	42	[1363]	MOVE     	6 3
	43	[1363]	CALL     	4 3 2
	44	[1363]	TEST     	4 0 0
	45	[1363]	JMP      	4	; to 50
	46	[1364]	SELF     	4 0 -14	; "closeDialog"
	47	[1364]	CALL     	4 2 1
	48	[1365]	LOADBOOL 	4 1 0
	49	[1365]	RETURN   	4 2
	50	[1367]	RETURN   	0 1

function <./frontend/ui/widget/configdialog.lua:1369,1372> (5 instructions, 20 bytes at 0x7f910240e560)
1 param, 3 slots, 0 upvalues, 1 local, 1 constant, 0 functions
	1	[1370]	SELF     	1 0 -1	; "closeDialog"
	2	[1370]	CALL     	1 2 1
	3	[1371]	LOADBOOL 	1 1 0
	4	[1371]	RETURN   	1 2
	5	[1372]	RETURN   	0 1

function <./frontend/ui/widget/configdialog.lua:1374,1377> (11 instructions, 44 bytes at 0x7f910240e4e0)
1 param, 6 slots, 1 upvalue, 1 local, 4 constants, 0 functions
	1	[1375]	SELF     	1 0 -1	; "getFocusItem"
	2	[1375]	CALL     	1 2 2
	3	[1375]	SELF     	1 1 -2	; "handleEvent"
	4	[1375]	GETUPVAL 	3 0	; Event
	5	[1375]	SELF     	3 3 -3	; "new"
	6	[1375]	LOADK    	5 -4	; "TapSelect"
	7	[1375]	CALL     	3 3 0
	8	[1375]	CALL     	1 0 1
	9	[1376]	LOADBOOL 	1 1 0
	10	[1376]	RETURN   	1 2
	11	[1377]	RETURN   	0 1
