
main <./plugins/coverbrowser.koplugin/covermenu.lua:0,0> (90 instructions, 360 bytes at 0x7fd8344068f0)
0+ params, 16 slots, 0 upvalues, 15 locals, 18 constants, 5 functions
	1	[1]	GETGLOBAL	0 -1	; require
	2	[1]	LOADK    	1 -2	; "ui/bidi"
	3	[1]	CALL     	0 2 2
	4	[2]	GETGLOBAL	1 -1	; require
	5	[2]	LOADK    	2 -3	; "document/documentregistry"
	6	[2]	CALL     	1 2 2
	7	[3]	GETGLOBAL	2 -1	; require
	8	[3]	LOADK    	3 -4	; "docsettings"
	9	[3]	CALL     	2 2 2
	10	[4]	GETGLOBAL	3 -1	; require
	11	[4]	LOADK    	4 -5	; "apps/filemanager/filemanagerbookinfo"
	12	[4]	CALL     	3 2 2
	13	[5]	GETGLOBAL	4 -1	; require
	14	[5]	LOADK    	5 -6	; "ui/widget/imageviewer"
	15	[5]	CALL     	4 2 2
	16	[6]	GETGLOBAL	5 -1	; require
	17	[6]	LOADK    	6 -7	; "ui/widget/infomessage"
	18	[6]	CALL     	5 2 2
	19	[7]	GETGLOBAL	6 -1	; require
	20	[7]	LOADK    	7 -8	; "ui/widget/menu"
	21	[7]	CALL     	6 2 2
	22	[8]	GETGLOBAL	7 -1	; require
	23	[8]	LOADK    	8 -9	; "ui/widget/textviewer"
	24	[8]	CALL     	7 2 2
	25	[9]	GETGLOBAL	8 -1	; require
	26	[9]	LOADK    	9 -10	; "ui/uimanager"
	27	[9]	CALL     	8 2 2
	28	[10]	GETGLOBAL	9 -1	; require
	29	[10]	LOADK    	10 -11	; "logger"
	30	[10]	CALL     	9 2 2
	31	[11]	GETGLOBAL	10 -1	; require
	32	[11]	LOADK    	11 -12	; "gettext"
	33	[11]	CALL     	10 2 2
	34	[13]	GETGLOBAL	11 -1	; require
	35	[13]	LOADK    	12 -13	; "bookinfomanager"
	36	[13]	CALL     	11 2 2
	37	[34]	LOADNIL  	12 12
	38	[35]	LOADBOOL 	13 0 0
	39	[39]	NEWTABLE 	14 0 0
	40	[396]	CLOSURE  	15 0	; 0x7fd8344070c0
	41	[396]	MOVE     	0 8
	42	[396]	MOVE     	0 12
	43	[396]	MOVE     	0 13
	44	[396]	MOVE     	0 0
	45	[396]	MOVE     	0 11
	46	[396]	MOVE     	0 5
	47	[396]	MOVE     	0 10
	48	[396]	MOVE     	0 9
	49	[396]	MOVE     	0 3
	50	[396]	MOVE     	0 2
	51	[396]	MOVE     	0 1
	52	[396]	MOVE     	0 4
	53	[396]	MOVE     	0 7
	54	[41]	SETTABLE 	14 -14 15	; "updateItems" -
	55	[522]	CLOSURE  	15 1	; 0x7fd834409f80
	56	[522]	MOVE     	0 11
	57	[522]	MOVE     	0 8
	58	[522]	MOVE     	0 3
	59	[522]	MOVE     	0 10
	60	[522]	MOVE     	0 1
	61	[522]	MOVE     	0 4
	62	[522]	MOVE     	0 5
	63	[522]	MOVE     	0 7
	64	[400]	SETTABLE 	14 -15 15	; "onHistoryMenuHold" -
	65	[640]	CLOSURE  	15 2	; 0x7fd83440c550
	66	[640]	MOVE     	0 11
	67	[640]	MOVE     	0 8
	68	[640]	MOVE     	0 3
	69	[640]	MOVE     	0 10
	70	[640]	MOVE     	0 1
	71	[640]	MOVE     	0 4
	72	[640]	MOVE     	0 5
	73	[640]	MOVE     	0 7
	74	[526]	SETTABLE 	14 -16 15	; "onCollectionsMenuHold" -
	75	[671]	CLOSURE  	15 3	; 0x7fd834406dc0
	76	[671]	MOVE     	0 9
	77	[671]	MOVE     	0 11
	78	[671]	MOVE     	0 8
	79	[671]	MOVE     	0 6
	80	[642]	SETTABLE 	14 -17 15	; "onCloseWidget" -
	81	[711]	CLOSURE  	15 4	; 0x7fd83440f3a0
	82	[711]	MOVE     	0 14
	83	[711]	MOVE     	0 8
	84	[711]	MOVE     	0 10
	85	[711]	MOVE     	0 11
	86	[711]	MOVE     	0 12
	87	[711]	MOVE     	0 13
	88	[673]	SETTABLE 	14 -18 15	; "tapPlus" -
	89	[713]	RETURN   	14 2
	90	[713]	RETURN   	0 1

function <./plugins/coverbrowser.koplugin/covermenu.lua:41,396> (160 instructions, 640 bytes at 0x7fd8344070c0)
2 params, 12 slots, 13 upvalues, 8 locals, 42 constants, 4 functions
	1	[43]	GETTABLE 	2 0 -1	; "dimen"
	2	[43]	TEST     	2 0 0
	3	[43]	JMP      	3	; to 7
	4	[43]	GETTABLE 	2 0 -1	; "dimen"
	5	[43]	SELF     	2 2 -2	; "copy"
	6	[43]	CALL     	2 2 2
	7	[45]	NEWTABLE 	3 0 0
	8	[45]	SETTABLE 	0 -3 3	; "layout" -
	9	[46]	GETTABLE 	3 0 -4	; "item_group"
	10	[46]	SELF     	3 3 -5	; "free"
	11	[46]	CALL     	3 2 1
	12	[47]	GETTABLE 	3 0 -4	; "item_group"
	13	[47]	SELF     	3 3 -6	; "clear"
	14	[47]	CALL     	3 2 1
	15	[50]	SELF     	3 0 -7	; "_recalculateDimen"
	16	[50]	CALL     	3 2 1
	17	[51]	GETTABLE 	3 0 -8	; "page_info"
	18	[51]	SELF     	3 3 -9	; "resetLayout"
	19	[51]	CALL     	3 2 1
	20	[52]	GETTABLE 	3 0 -10	; "return_button"
	21	[52]	SELF     	3 3 -9	; "resetLayout"
	22	[52]	CALL     	3 2 1
	23	[53]	GETTABLE 	3 0 -11	; "vertical_span"
	24	[53]	SELF     	3 3 -6	; "clear"
	25	[53]	CALL     	3 2 1
	26	[54]	GETTABLE 	3 0 -12	; "content_group"
	27	[54]	SELF     	3 3 -9	; "resetLayout"
	28	[54]	CALL     	3 2 1
	29	[56]	TEST     	1 0 1
	30	[56]	JMP      	1	; to 32
	31	[57]	LOADK    	1 -13	; 1
	32	[62]	NEWTABLE 	3 0 0
	33	[62]	SETTABLE 	0 -14 3	; "items_to_update" -
	34	[64]	GETTABLE 	3 0 -15	; "items_update_action"
	35	[64]	TEST     	3 0 0
	36	[64]	JMP      	5	; to 42
	37	[65]	GETUPVAL 	3 0	; UIManager
	38	[65]	SELF     	3 3 -16	; "unschedule"
	39	[65]	GETTABLE 	5 0 -15	; "items_update_action"
	40	[65]	CALL     	3 3 1
	41	[66]	SETTABLE 	0 -15 -17	; "items_update_action" nil
	42	[81]	GETGLOBAL	3 -18	; collectgarbage
	43	[81]	CALL     	3 1 1
	44	[82]	GETGLOBAL	3 -18	; collectgarbage
	45	[82]	CALL     	3 1 1
	46	[85]	SETTABLE 	0 -19 -20	; "_has_cover_images" false
	47	[86]	SELF     	3 0 -21	; "_updateItemsBuildUI"
	48	[86]	CALL     	3 2 1
	49	[92]	GETTABLE 	3 0 -22	; "path"
	50	[92]	TEST     	3 0 0
	51	[92]	JMP      	4	; to 56
	52	[93]	GETTABLE 	3 0 -22	; "path"
	53	[93]	SETUPVAL 	3 1	; current_path
	54	[94]	GETTABLE 	3 0 -23	; "cover_specs"
	55	[94]	SETUPVAL 	3 2	; current_cover_specs
	56	[98]	SELF     	3 0 -24	; "updatePageInfo"
	57	[98]	MOVE     	5 1
	58	[98]	CALL     	3 3 1
	59	[100]	GETTABLE 	3 0 -25	; "show_path"
	60	[100]	TEST     	3 0 0
	61	[100]	JMP      	7	; to 69
	62	[101]	GETTABLE 	3 0 -26	; "path_text"
	63	[101]	SELF     	3 3 -27	; "setText"
	64	[101]	GETUPVAL 	5 3	; BD
	65	[101]	GETTABLE 	5 5 -28	; "directory"
	66	[101]	GETTABLE 	6 0 -22	; "path"
	67	[101]	CALL     	5 2 0
	68	[101]	CALL     	3 0 1
	69	[103]	GETTABLE 	3 0 -29	; "show_parent"
	70	[103]	GETTABLE 	4 0 -19	; "_has_cover_images"
	71	[103]	SETTABLE 	3 -30 4	; "dithered" -
	72	[104]	GETUPVAL 	3 0	; UIManager
	73	[104]	SELF     	3 3 -31	; "setDirty"
	74	[104]	GETTABLE 	5 0 -29	; "show_parent"
	75	[109]	CLOSURE  	6 0	; 0x7fd834407870
	76	[109]	MOVE     	0 2
	77	[109]	MOVE     	0 0
	78	[104]	CALL     	3 4 1
	79	[112]	GETTABLE 	3 0 -32	; "path_items"
	80	[112]	TEST     	3 0 0
	81	[112]	JMP      	11	; to 93
	82	[113]	GETTABLE 	3 0 -32	; "path_items"
	83	[113]	GETTABLE 	4 0 -22	; "path"
	84	[113]	GETTABLE 	5 0 -33	; "page"
	85	[113]	SUB      	5 5 -13	; - 1
	86	[113]	GETTABLE 	6 0 -34	; "perpage"
	87	[113]	MUL      	5 5 6
	88	[113]	TESTSET  	6 1 1
	89	[113]	JMP      	1	; to 91
	90	[113]	LOADK    	6 -13	; 1
	91	[113]	ADD      	5 5 6
	92	[113]	SETTABLE 	3 4 5
	93	[117]	GETTABLE 	3 0 -14	; "items_to_update"
	94	[117]	LEN      	3 3
	95	[117]	LT       	0 -35 3	; 0 -
	96	[117]	JMP      	42	; to 139
	97	[119]	NEWTABLE 	3 0 0
	98	[120]	LOADK    	4 -13	; 1
	99	[120]	GETTABLE 	5 0 -14	; "items_to_update"
	100	[120]	LEN      	5 5
	101	[120]	LOADK    	6 -13	; 1
	102	[120]	FORPREP  	4 13	; to 116
	103	[121]	GETGLOBAL	8 -36	; table
	104	[121]	GETTABLE 	8 8 -37	; "insert"
	105	[121]	MOVE     	9 3
	106	[121]	NEWTABLE 	10 0 2
	107	[122]	GETTABLE 	11 0 -14	; "items_to_update"
	108	[122]	GETTABLE 	11 11 7
	109	[122]	GETTABLE 	11 11 -38	; "filepath"
	110	[122]	SETTABLE 	10 -38 11	; "filepath" -
	111	[123]	GETTABLE 	11 0 -14	; "items_to_update"
	112	[123]	GETTABLE 	11 11 7
	113	[123]	GETTABLE 	11 11 -23	; "cover_specs"
	114	[123]	SETTABLE 	10 -23 11	; "cover_specs" -
	115	[121]	CALL     	8 3 1
	116	[120]	FORLOOP  	4 -14	; to 103
	117	[127]	GETUPVAL 	4 0	; UIManager
	118	[127]	SELF     	4 4 -39	; "nextTick"
	119	[139]	CLOSURE  	6 1	; 0x7fd834407a80
	120	[139]	GETUPVAL 	0 4	; BookInfoManager
	121	[139]	MOVE     	0 3
	122	[139]	MOVE     	0 0
	123	[139]	GETUPVAL 	0 0	; UIManager
	124	[139]	GETUPVAL 	0 5	; InfoMessage
	125	[139]	GETUPVAL 	0 6	; _
	126	[127]	CALL     	4 3 1
	127	[178]	CLOSURE  	4 2	; 0x7fd834408740
	128	[178]	GETUPVAL 	0 7	; logger
	129	[178]	MOVE     	0 0
	130	[178]	GETUPVAL 	0 4	; BookInfoManager
	131	[178]	GETUPVAL 	0 0	; UIManager
	132	[178]	SETTABLE 	0 -15 4	; "items_update_action" -
	133	[179]	GETUPVAL 	4 0	; UIManager
	134	[179]	SELF     	4 4 -40	; "scheduleIn"
	135	[179]	LOADK    	6 -13	; 1
	136	[179]	GETTABLE 	7 0 -15	; "items_update_action"
	137	[179]	CALL     	4 4 1
	138	[179]	CLOSE    	3
	139	[193]	GETTABLE 	3 0 -41	; "onFileHold_ours"
	140	[194]	TEST     	3 0 0
	141	[194]	JMP      	4	; to 146
	142	[194]	GETTABLE 	3 0 -42	; "onFileHold"
	143	[194]	GETTABLE 	4 0 -41	; "onFileHold_ours"
	144	[194]	EQ       	1 3 4
	145	[194]	JMP      	14	; to 160
	146	[197]	GETUPVAL 	3 0	; UIManager
	147	[197]	SELF     	3 3 -39	; "nextTick"
	148	[394]	CLOSURE  	5 3	; 0x7fd834407b40
	149	[394]	MOVE     	0 0
	150	[394]	GETUPVAL 	0 4	; BookInfoManager
	151	[394]	GETUPVAL 	0 0	; UIManager
	152	[394]	GETUPVAL 	0 8	; FileManagerBookInfo
	153	[394]	GETUPVAL 	0 6	; _
	154	[394]	GETUPVAL 	0 9	; DocSettings
	155	[394]	GETUPVAL 	0 10	; DocumentRegistry
	156	[394]	GETUPVAL 	0 11	; ImageViewer
	157	[394]	GETUPVAL 	0 5	; InfoMessage
	158	[394]	GETUPVAL 	0 12	; TextViewer
	159	[197]	CALL     	3 3 1
	160	[396]	RETURN   	0 1

function <./plugins/coverbrowser.koplugin/covermenu.lua:104,109> (19 instructions, 76 bytes at 0x7fd834407870)
0 params, 4 slots, 2 upvalues, 1 local, 5 constants, 0 functions
	1	[106]	GETUPVAL 	0 0	; old_dimen
	2	[106]	TEST     	0 0 0
	3	[106]	JMP      	7	; to 11
	4	[106]	GETUPVAL 	0 0	; old_dimen
	5	[106]	SELF     	0 0 -1	; "combine"
	6	[106]	GETUPVAL 	2 1	; self
	7	[106]	GETTABLE 	2 2 -2	; "dimen"
	8	[106]	CALL     	0 3 2
	9	[107]	TEST     	0 0 1
	10	[107]	JMP      	2	; to 13
	11	[107]	GETUPVAL 	0 1	; self
	12	[107]	GETTABLE 	0 0 -2	; "dimen"
	13	[108]	LOADK    	1 -3	; "ui"
	14	[108]	MOVE     	2 0
	15	[108]	GETUPVAL 	3 1	; self
	16	[108]	GETTABLE 	3 3 -4	; "show_parent"
	17	[108]	GETTABLE 	3 3 -5	; "dithered"
	18	[108]	RETURN   	1 4
	19	[109]	RETURN   	0 1

function <./plugins/coverbrowser.koplugin/covermenu.lua:127,139> (29 instructions, 116 bytes at 0x7fd834407a80)
0 params, 8 slots, 6 upvalues, 1 local, 8 constants, 0 functions
	1	[128]	GETUPVAL 	0 0	; BookInfoManager
	2	[128]	SELF     	0 0 -1	; "extractInBackground"
	3	[128]	GETUPVAL 	2 1	; files_to_index
	4	[128]	CALL     	0 3 2
	5	[129]	TEST     	0 0 1
	6	[129]	JMP      	22	; to 29
	7	[131]	GETUPVAL 	1 2	; self
	8	[131]	GETTABLE 	1 1 -2	; "items_update_action"
	9	[131]	TEST     	1 0 0
	10	[131]	JMP      	7	; to 18
	11	[132]	GETUPVAL 	1 3	; UIManager
	12	[132]	SELF     	1 1 -3	; "unschedule"
	13	[132]	GETUPVAL 	3 2	; self
	14	[132]	GETTABLE 	3 3 -2	; "items_update_action"
	15	[132]	CALL     	1 3 1
	16	[133]	GETUPVAL 	1 2	; self
	17	[133]	SETTABLE 	1 -2 -4	; "items_update_action" nil
	18	[135]	GETUPVAL 	1 3	; UIManager
	19	[135]	SELF     	1 1 -5	; "show"
	20	[135]	GETUPVAL 	3 4	; InfoMessage
	21	[135]	SELF     	3 3 -6	; "new"
	22	[135]	NEWTABLE 	5 0 1
	23	[136]	GETUPVAL 	6 5	; _
	24	[136]	LOADK    	7 -8	; "Start-up of background extraction job failed.\nPlease restart KOReader or your device."
	25	[136]	CALL     	6 2 2
	26	[136]	SETTABLE 	5 -7 6	; "text" -
	27	[135]	CALL     	3 3 0
	28	[135]	CALL     	1 0 1
	29	[139]	RETURN   	0 1

function <./plugins/coverbrowser.koplugin/covermenu.lua:142,178> (90 instructions, 360 bytes at 0x7fd834408740)
0 params, 8 slots, 4 upvalues, 4 locals, 24 constants, 1 function
	1	[143]	GETUPVAL 	0 0	; logger
	2	[143]	GETTABLE 	0 0 -1	; "dbg"
	3	[143]	LOADK    	1 -2	; "Scheduled items update:"
	4	[143]	GETUPVAL 	2 1	; self
	5	[143]	GETTABLE 	2 2 -3	; "items_to_update"
	6	[143]	LEN      	2 2
	7	[143]	LOADK    	3 -4	; "waiting"
	8	[143]	CALL     	0 4 1
	9	[144]	GETUPVAL 	0 2	; BookInfoManager
	10	[144]	SELF     	0 0 -5	; "isExtractingInBackground"
	11	[144]	CALL     	0 2 2
	12	[145]	LOADK    	1 -6	; 1
	13	[146]	GETUPVAL 	2 1	; self
	14	[146]	GETTABLE 	2 2 -3	; "items_to_update"
	15	[146]	LEN      	2 2
	16	[146]	LE       	0 1 2
	17	[146]	JMP      	41	; to 59
	18	[147]	GETUPVAL 	2 1	; self
	19	[147]	GETTABLE 	2 2 -3	; "items_to_update"
	20	[147]	GETTABLE 	2 2 1
	21	[148]	SELF     	3 2 -7	; "update"
	22	[148]	CALL     	3 2 1
	23	[149]	GETTABLE 	3 2 -8	; "bookinfo_found"
	24	[149]	TEST     	3 0 0
	25	[149]	JMP      	25	; to 51
	26	[150]	GETUPVAL 	3 0	; logger
	27	[150]	GETTABLE 	3 3 -1	; "dbg"
	28	[150]	LOADK    	4 -9	; "  found"
	29	[150]	GETTABLE 	5 2 -10	; "text"
	30	[150]	CALL     	3 3 1
	31	[151]	GETUPVAL 	3 1	; self
	32	[151]	GETTABLE 	3 3 -11	; "show_parent"
	33	[151]	GETTABLE 	4 2 -13	; "_has_cover_image"
	34	[151]	SETTABLE 	3 -12 4	; "dithered" -
	35	[160]	CLOSURE  	3 0	; 0x7fd834408a90
	36	[160]	MOVE     	0 2
	37	[160]	GETUPVAL 	0 1	; self
	38	[161]	GETUPVAL 	4 3	; UIManager
	39	[161]	SELF     	4 4 -14	; "setDirty"
	40	[161]	GETUPVAL 	6 1	; self
	41	[161]	GETTABLE 	6 6 -11	; "show_parent"
	42	[161]	MOVE     	7 3
	43	[161]	CALL     	4 4 1
	44	[162]	GETGLOBAL	4 -15	; table
	45	[162]	GETTABLE 	4 4 -16	; "remove"
	46	[162]	GETUPVAL 	5 1	; self
	47	[162]	GETTABLE 	5 5 -3	; "items_to_update"
	48	[162]	MOVE     	6 1
	49	[162]	CALL     	4 3 1
	50	[162]	JMP      	6	; to 57
	51	[164]	GETUPVAL 	3 0	; logger
	52	[164]	GETTABLE 	3 3 -1	; "dbg"
	53	[164]	LOADK    	4 -17	; "  not yet found"
	54	[164]	GETTABLE 	5 2 -10	; "text"
	55	[164]	CALL     	3 3 1
	56	[165]	ADD      	1 1 -6	; - 1
	57	[166]	CLOSE    	2
	58	[166]	JMP      	-46	; to 13
	59	[168]	GETUPVAL 	2 1	; self
	60	[168]	GETTABLE 	2 2 -3	; "items_to_update"
	61	[168]	LEN      	2 2
	62	[168]	LT       	0 -18 2	; 0 -
	63	[168]	JMP      	22	; to 86
	64	[169]	TEST     	0 0 0
	65	[169]	JMP      	15	; to 81
	66	[170]	GETUPVAL 	2 0	; logger
	67	[170]	GETTABLE 	2 2 -1	; "dbg"
	68	[170]	LOADK    	3 -19	; "re-scheduling items update:"
	69	[170]	GETUPVAL 	4 1	; self
	70	[170]	GETTABLE 	4 4 -3	; "items_to_update"
	71	[170]	LEN      	4 4
	72	[170]	LOADK    	5 -20	; "still waiting"
	73	[170]	CALL     	2 4 1
	74	[171]	GETUPVAL 	2 3	; UIManager
	75	[171]	SELF     	2 2 -21	; "scheduleIn"
	76	[171]	LOADK    	4 -6	; 1
	77	[171]	GETUPVAL 	5 1	; self
	78	[171]	GETTABLE 	5 5 -22	; "items_update_action"
	79	[171]	CALL     	2 4 1
	80	[171]	JMP      	9	; to 90
	81	[173]	GETUPVAL 	2 0	; logger
	82	[173]	GETTABLE 	2 2 -1	; "dbg"
	83	[173]	LOADK    	3 -23	; "Not all items found, but background extraction has stopped, not re-scheduling"
	84	[173]	CALL     	2 2 1
	85	[174]	JMP      	4	; to 90
	86	[176]	GETUPVAL 	2 0	; logger
	87	[176]	GETTABLE 	2 2 -1	; "dbg"
	88	[176]	LOADK    	3 -24	; "items update completed"
	89	[176]	CALL     	2 2 1
	90	[178]	RETURN   	0 1

function <./plugins/coverbrowser.koplugin/covermenu.lua:152,160> (21 instructions, 84 bytes at 0x7fd834408a90)
0 params, 3 slots, 2 upvalues, 0 locals, 6 constants, 0 functions
	1	[153]	GETUPVAL 	0 0	; item
	2	[153]	GETTABLE 	0 0 -1	; "refresh_dimen"
	3	[153]	TEST     	0 0 0
	4	[153]	JMP      	8	; to 13
	5	[156]	LOADK    	0 -2	; "ui"
	6	[156]	GETUPVAL 	1 0	; item
	7	[156]	GETTABLE 	1 1 -1	; "refresh_dimen"
	8	[156]	GETUPVAL 	2 1	; self
	9	[156]	GETTABLE 	2 2 -3	; "show_parent"
	10	[156]	GETTABLE 	2 2 -4	; "dithered"
	11	[156]	RETURN   	0 4
	12	[156]	JMP      	8	; to 21
	13	[158]	LOADK    	0 -2	; "ui"
	14	[158]	GETUPVAL 	1 0	; item
	15	[158]	GETTABLE 	1 1 -5	; 1
	16	[158]	GETTABLE 	1 1 -6	; "dimen"
	17	[158]	GETUPVAL 	2 1	; self
	18	[158]	GETTABLE 	2 2 -3	; "show_parent"
	19	[158]	GETTABLE 	2 2 -4	; "dithered"
	20	[158]	RETURN   	0 4
	21	[160]	RETURN   	0 1

function <./plugins/coverbrowser.koplugin/covermenu.lua:197,394> (21 instructions, 84 bytes at 0x7fd834407b40)
0 params, 2 slots, 10 upvalues, 0 locals, 3 constants, 1 function
	1	[199]	GETUPVAL 	0 0	; self
	2	[199]	GETUPVAL 	1 0	; self
	3	[199]	GETTABLE 	1 1 -2	; "onFileHold"
	4	[199]	SETTABLE 	0 -1 1	; "onFileHold_orig" -
	5	[204]	GETUPVAL 	0 0	; self
	6	[390]	CLOSURE  	1 0	; 0x7fd834407d90
	7	[390]	GETUPVAL 	0 1	; BookInfoManager
	8	[390]	GETUPVAL 	0 2	; UIManager
	9	[390]	GETUPVAL 	0 3	; FileManagerBookInfo
	10	[390]	GETUPVAL 	0 4	; _
	11	[390]	GETUPVAL 	0 5	; DocSettings
	12	[390]	GETUPVAL 	0 6	; DocumentRegistry
	13	[390]	GETUPVAL 	0 7	; ImageViewer
	14	[390]	GETUPVAL 	0 8	; InfoMessage
	15	[390]	GETUPVAL 	0 9	; TextViewer
	16	[390]	SETTABLE 	0 -2 1	; "onFileHold" -
	17	[393]	GETUPVAL 	0 0	; self
	18	[393]	GETUPVAL 	1 0	; self
	19	[393]	GETTABLE 	1 1 -2	; "onFileHold"
	20	[393]	SETTABLE 	0 -3 1	; "onFileHold_ours" -
	21	[394]	RETURN   	0 1

function <./plugins/coverbrowser.koplugin/covermenu.lua:204,390> (223 instructions, 892 bytes at 0x7fd834407d90)
2 params, 14 slots, 9 upvalues, 8 locals, 38 constants, 9 functions
	1	[207]	GETTABLE 	2 0 -1	; "onFileHold_orig"
	2	[207]	MOVE     	3 0
	3	[207]	MOVE     	4 1
	4	[207]	CALL     	2 3 1
	5	[209]	GETUPVAL 	2 0	; BookInfoManager
	6	[209]	SELF     	2 2 -2	; "getBookInfo"
	7	[209]	MOVE     	4 1
	8	[209]	CALL     	2 3 2
	9	[210]	TEST     	2 0 0
	10	[210]	JMP      	3	; to 14
	11	[210]	GETTABLE 	3 2 -3	; "_is_directory"
	12	[210]	TEST     	3 0 0
	13	[210]	JMP      	2	; to 16
	14	[212]	LOADBOOL 	3 1 0
	15	[212]	RETURN   	3 2
	16	[216]	GETTABLE 	3 0 -4	; "file_dialog"
	17	[216]	GETTABLE 	3 3 -5	; "title"
	18	[217]	GETTABLE 	4 0 -4	; "file_dialog"
	19	[217]	GETTABLE 	4 4 -6	; "title_align"
	20	[218]	GETTABLE 	5 0 -4	; "file_dialog"
	21	[218]	GETTABLE 	5 5 -7	; "buttons"
	22	[221]	GETUPVAL 	6 1	; UIManager
	23	[221]	SELF     	6 6 -8	; "close"
	24	[221]	GETTABLE 	8 0 -4	; "file_dialog"
	25	[221]	CALL     	6 3 1
	26	[223]	GETUPVAL 	6 1	; UIManager
	27	[223]	SELF     	6 6 -9	; "clearRenderStack"
	28	[223]	CALL     	6 2 1
	29	[226]	GETTABLE 	6 5 -10	; 4
	30	[226]	GETTABLE 	6 6 -11	; 2
	31	[229]	CLOSURE  	7 0	; 0x7fd834409800
	32	[229]	GETUPVAL 	0 2	; FileManagerBookInfo
	33	[229]	MOVE     	0 1
	34	[229]	MOVE     	0 2
	35	[229]	GETUPVAL 	0 1	; UIManager
	36	[229]	MOVE     	0 0
	37	[229]	SETTABLE 	6 -12 7	; "callback" -
	38	[232]	GETTABLE 	6 5 -13	; 1
	39	[232]	GETTABLE 	6 6 -14	; 3
	40	[232]	GETTABLE 	6 6 -12	; "callback"
	41	[233]	GETTABLE 	7 5 -13	; 1
	42	[233]	GETTABLE 	7 7 -14	; 3
	43	[240]	CLOSURE  	8 1	; 0x7fd834409900
	44	[240]	MOVE     	0 0
	45	[240]	MOVE     	0 1
	46	[240]	MOVE     	0 6
	47	[240]	SETTABLE 	7 -12 8	; "callback" -
	48	[243]	GETGLOBAL	7 -15	; table
	49	[243]	GETTABLE 	7 7 -16	; "insert"
	50	[243]	GETTABLE 	8 5 -17	; 5
	51	[243]	LOADK    	9 -13	; 1
	52	[243]	NEWTABLE 	10 0 3
	53	[258]	CLOSURE  	11 2	; 0x7fd834409a60
	54	[258]	MOVE     	0 0
	55	[258]	MOVE     	0 1
	56	[258]	GETUPVAL 	0 3	; _
	57	[258]	SETTABLE 	10 -18 11	; "text_func" -
	58	[259]	SETTABLE 	10 -19 -20	; "enabled" true
	59	[294]	CLOSURE  	11 3	; 0x7fd83440ab60
	60	[294]	MOVE     	0 0
	61	[294]	MOVE     	0 1
	62	[294]	GETUPVAL 	0 4	; DocSettings
	63	[294]	GETUPVAL 	0 1	; UIManager
	64	[294]	SETTABLE 	10 -12 11	; "callback" -
	65	[243]	CALL     	7 4 1
	66	[299]	GETGLOBAL	7 -15	; table
	67	[299]	GETTABLE 	7 7 -16	; "insert"
	68	[299]	MOVE     	8 5
	69	[299]	NEWTABLE 	9 2 0
	70	[299]	NEWTABLE 	10 0 3
	71	[301]	GETUPVAL 	11 3	; _
	72	[301]	LOADK    	12 -22	; "View full size cover"
	73	[301]	CALL     	11 2 2
	74	[301]	SETTABLE 	10 -21 11	; "text" -
	75	[302]	GETTABLE 	11 2 -23	; "has_cover"
	76	[302]	TEST     	11 0 0
	77	[302]	JMP      	3	; to 81
	78	[302]	LOADBOOL 	11 1 0
	79	[302]	TEST     	11 0 1
	80	[302]	JMP      	1	; to 82
	81	[302]	LOADBOOL 	11 0 0
	82	[302]	SETTABLE 	10 -19 11	; "enabled" -
	83	[325]	CLOSURE  	11 4	; 0x7fd83440abe0
	84	[325]	GETUPVAL 	0 5	; DocumentRegistry
	85	[325]	MOVE     	0 1
	86	[325]	GETUPVAL 	0 6	; ImageViewer
	87	[325]	GETUPVAL 	0 1	; UIManager
	88	[325]	GETUPVAL 	0 7	; InfoMessage
	89	[325]	GETUPVAL 	0 3	; _
	90	[325]	MOVE     	0 0
	91	[325]	SETTABLE 	10 -12 11	; "callback" -
	92	[326]	NEWTABLE 	11 0 3
	93	[328]	GETTABLE 	12 2 -24	; "description"
	94	[328]	TEST     	12 0 0
	95	[328]	JMP      	5	; to 101
	96	[328]	GETUPVAL 	12 3	; _
	97	[328]	LOADK    	13 -25	; "View book description"
	98	[328]	CALL     	12 2 2
	99	[328]	TEST     	12 0 1
	100	[328]	JMP      	3	; to 104
	101	[328]	GETUPVAL 	12 3	; _
	102	[328]	LOADK    	13 -26	; "No book description"
	103	[328]	CALL     	12 2 2
	104	[328]	SETTABLE 	11 -21 12	; "text" -
	105	[329]	GETTABLE 	12 2 -24	; "description"
	106	[329]	TEST     	12 0 0
	107	[329]	JMP      	3	; to 111
	108	[329]	LOADBOOL 	12 1 0
	109	[329]	TEST     	12 0 1
	110	[329]	JMP      	1	; to 112
	111	[329]	LOADBOOL 	12 0 0
	112	[329]	SETTABLE 	11 -19 12	; "enabled" -
	113	[338]	CLOSURE  	12 5	; 0x7fd83440bd90
	114	[338]	MOVE     	0 2
	115	[338]	GETUPVAL 	0 8	; TextViewer
	116	[338]	GETUPVAL 	0 1	; UIManager
	117	[338]	MOVE     	0 0
	118	[338]	SETTABLE 	11 -12 12	; "callback" -
	119	[340]	SETLIST  	9 2 1	; 1
	120	[299]	CALL     	7 3 1
	121	[341]	GETGLOBAL	7 -15	; table
	122	[341]	GETTABLE 	7 7 -16	; "insert"
	123	[341]	MOVE     	8 5
	124	[341]	NEWTABLE 	9 2 0
	125	[341]	NEWTABLE 	10 0 3
	126	[343]	GETTABLE 	11 2 -27	; "ignore_cover"
	127	[343]	TEST     	11 0 0
	128	[343]	JMP      	5	; to 134
	129	[343]	GETUPVAL 	11 3	; _
	130	[343]	LOADK    	12 -28	; "Unignore cover"
	131	[343]	CALL     	11 2 2
	132	[343]	TEST     	11 0 1
	133	[343]	JMP      	3	; to 137
	134	[343]	GETUPVAL 	11 3	; _
	135	[343]	LOADK    	12 -29	; "Ignore cover"
	136	[343]	CALL     	11 2 2
	137	[343]	SETTABLE 	10 -21 11	; "text" -
	138	[344]	GETTABLE 	11 2 -23	; "has_cover"
	139	[344]	TEST     	11 0 0
	140	[344]	JMP      	3	; to 144
	141	[344]	LOADBOOL 	11 1 0
	142	[344]	TEST     	11 0 1
	143	[344]	JMP      	1	; to 145
	144	[344]	LOADBOOL 	11 0 0
	145	[344]	SETTABLE 	10 -19 11	; "enabled" -
	146	[351]	CLOSURE  	11 6	; 0x7fd83440b670
	147	[351]	GETUPVAL 	0 0	; BookInfoManager
	148	[351]	MOVE     	0 1
	149	[351]	MOVE     	0 2
	150	[351]	GETUPVAL 	0 1	; UIManager
	151	[351]	MOVE     	0 0
	152	[351]	SETTABLE 	10 -12 11	; "callback" -
	153	[352]	NEWTABLE 	11 0 3
	154	[354]	GETTABLE 	12 2 -30	; "ignore_meta"
	155	[354]	TEST     	12 0 0
	156	[354]	JMP      	5	; to 162
	157	[354]	GETUPVAL 	12 3	; _
	158	[354]	LOADK    	13 -31	; "Unignore metadata"
	159	[354]	CALL     	12 2 2
	160	[354]	TEST     	12 0 1
	161	[354]	JMP      	3	; to 165
	162	[354]	GETUPVAL 	12 3	; _
	163	[354]	LOADK    	13 -32	; "Ignore metadata"
	164	[354]	CALL     	12 2 2
	165	[354]	SETTABLE 	11 -21 12	; "text" -
	166	[355]	GETTABLE 	12 2 -33	; "has_meta"
	167	[355]	TEST     	12 0 0
	168	[355]	JMP      	3	; to 172
	169	[355]	LOADBOOL 	12 1 0
	170	[355]	TEST     	12 0 1
	171	[355]	JMP      	1	; to 173
	172	[355]	LOADBOOL 	12 0 0
	173	[355]	SETTABLE 	11 -19 12	; "enabled" -
	174	[362]	CLOSURE  	12 7	; 0x7fd83440a6f0
	175	[362]	GETUPVAL 	0 0	; BookInfoManager
	176	[362]	MOVE     	0 1
	177	[362]	MOVE     	0 2
	178	[362]	GETUPVAL 	0 1	; UIManager
	179	[362]	MOVE     	0 0
	180	[362]	SETTABLE 	11 -12 12	; "callback" -
	181	[364]	SETLIST  	9 2 1	; 1
	182	[341]	CALL     	7 3 1
	183	[365]	GETGLOBAL	7 -15	; table
	184	[365]	GETTABLE 	7 7 -16	; "insert"
	185	[365]	MOVE     	8 5
	186	[365]	NEWTABLE 	9 1 0
	187	[365]	NEWTABLE 	10 0 3
	188	[367]	GETUPVAL 	11 3	; _
	189	[367]	LOADK    	12 -34	; "Refresh cached book information"
	190	[367]	CALL     	11 2 2
	191	[367]	SETTABLE 	10 -21 11	; "text" -
	192	[368]	TEST     	2 0 0
	193	[368]	JMP      	3	; to 197
	194	[368]	LOADBOOL 	11 1 0
	195	[368]	TEST     	11 0 1
	196	[368]	JMP      	1	; to 198
	197	[368]	LOADBOOL 	11 0 0
	198	[368]	SETTABLE 	10 -19 11	; "enabled" -
	199	[377]	CLOSURE  	11 8	; 0x7fd83440a770
	200	[377]	MOVE     	0 0
	201	[377]	MOVE     	0 1
	202	[377]	GETUPVAL 	0 0	; BookInfoManager
	203	[377]	GETUPVAL 	0 1	; UIManager
	204	[377]	SETTABLE 	10 -12 11	; "callback" -
	205	[379]	SETLIST  	9 1 1	; 1
	206	[365]	CALL     	7 3 1
	207	[382]	GETGLOBAL	7 -35	; require
	208	[382]	LOADK    	8 -36	; "ui/widget/buttondialogtitle"
	209	[382]	CALL     	7 2 2
	210	[383]	SELF     	8 7 -37	; "new"
	211	[383]	NEWTABLE 	10 0 3
	212	[384]	SETTABLE 	10 -5 3	; "title" -
	213	[385]	SETTABLE 	10 -6 4	; "title_align" -
	214	[386]	SETTABLE 	10 -7 5	; "buttons" -
	215	[383]	CALL     	8 3 2
	216	[387]	SETTABLE 	0 -4 8	; "file_dialog" -
	217	[388]	GETUPVAL 	8 1	; UIManager
	218	[388]	SELF     	8 8 -38	; "show"
	219	[388]	GETTABLE 	10 0 -4	; "file_dialog"
	220	[388]	CALL     	8 3 1
	221	[389]	LOADBOOL 	8 1 0
	222	[389]	RETURN   	8 2
	223	[390]	RETURN   	0 1

function <./plugins/coverbrowser.koplugin/covermenu.lua:226,229> (11 instructions, 44 bytes at 0x7fd834409800)
0 params, 4 slots, 5 upvalues, 0 locals, 3 constants, 0 functions
	1	[227]	GETUPVAL 	0 0	; FileManagerBookInfo
	2	[227]	SELF     	0 0 -1	; "show"
	3	[227]	GETUPVAL 	2 1	; file
	4	[227]	GETUPVAL 	3 2	; bookinfo
	5	[227]	CALL     	0 4 1
	6	[228]	GETUPVAL 	0 3	; UIManager
	7	[228]	SELF     	0 0 -2	; "close"
	8	[228]	GETUPVAL 	2 4	; self
	9	[228]	GETTABLE 	2 2 -3	; "file_dialog"
	10	[228]	CALL     	0 3 1
	11	[229]	RETURN   	0 1

function <./plugins/coverbrowser.koplugin/covermenu.lua:233,240> (17 instructions, 68 bytes at 0x7fd834409900)
0 params, 2 slots, 3 upvalues, 0 locals, 2 constants, 0 functions
	1	[235]	GETUPVAL 	0 0	; self
	2	[235]	GETTABLE 	0 0 -1	; "cover_info_cache"
	3	[235]	TEST     	0 0 0
	4	[235]	JMP      	10	; to 15
	5	[235]	GETUPVAL 	0 0	; self
	6	[235]	GETTABLE 	0 0 -1	; "cover_info_cache"
	7	[235]	GETUPVAL 	1 1	; file
	8	[235]	GETTABLE 	0 0 1
	9	[235]	TEST     	0 0 0
	10	[235]	JMP      	4	; to 15
	11	[236]	GETUPVAL 	0 0	; self
	12	[236]	GETTABLE 	0 0 -1	; "cover_info_cache"
	13	[236]	GETUPVAL 	1 1	; file
	14	[236]	SETTABLE 	0 1 -2	; - nil
	15	[239]	GETUPVAL 	0 2	; orig_purge_callback
	16	[239]	CALL     	0 1 1
	17	[240]	RETURN   	0 1

function <./plugins/coverbrowser.koplugin/covermenu.lua:245,258> (29 instructions, 116 bytes at 0x7fd834409a60)
0 params, 4 slots, 3 upvalues, 4 locals, 5 constants, 0 functions
	1	[248]	GETUPVAL 	1 0	; self
	2	[248]	GETTABLE 	1 1 -1	; "cover_info_cache"
	3	[248]	TEST     	1 0 0
	4	[248]	JMP      	13	; to 18
	5	[248]	GETUPVAL 	1 0	; self
	6	[248]	GETTABLE 	1 1 -1	; "cover_info_cache"
	7	[248]	GETUPVAL 	2 1	; file
	8	[248]	GETTABLE 	1 1 2
	9	[248]	TEST     	1 0 0
	10	[248]	JMP      	7	; to 18
	11	[249]	GETGLOBAL	1 -2	; unpack
	12	[249]	GETUPVAL 	2 0	; self
	13	[249]	GETTABLE 	2 2 -1	; "cover_info_cache"
	14	[249]	GETUPVAL 	3 1	; file
	15	[249]	GETTABLE 	2 2 3
	16	[249]	CALL     	1 2 4
	17	[250]	MOVE     	0 3
	18	[257]	EQ       	0 0 -3	; - "complete"
	19	[257]	JMP      	5	; to 25
	20	[257]	GETUPVAL 	1 2	; _
	21	[257]	LOADK    	2 -4	; "Mark as reading"
	22	[257]	CALL     	1 2 2
	23	[257]	TEST     	1 0 1
	24	[257]	JMP      	3	; to 28
	25	[257]	GETUPVAL 	1 2	; _
	26	[257]	LOADK    	2 -5	; "Mark as read"
	27	[257]	CALL     	1 2 2
	28	[257]	RETURN   	1 2
	29	[258]	RETURN   	0 1

function <./plugins/coverbrowser.koplugin/covermenu.lua:260,294> (82 instructions, 328 bytes at 0x7fd83440ab60)
0 params, 10 slots, 4 upvalues, 7 locals, 16 constants, 0 functions
	1	[262]	GETUPVAL 	1 0	; self
	2	[262]	GETTABLE 	1 1 -1	; "cover_info_cache"
	3	[262]	TEST     	1 0 0
	4	[262]	JMP      	28	; to 33
	5	[262]	GETUPVAL 	1 0	; self
	6	[262]	GETTABLE 	1 1 -1	; "cover_info_cache"
	7	[262]	GETUPVAL 	2 1	; file
	8	[262]	GETTABLE 	1 1 2
	9	[262]	TEST     	1 0 0
	10	[262]	JMP      	22	; to 33
	11	[263]	GETGLOBAL	1 -2	; unpack
	12	[263]	GETUPVAL 	2 0	; self
	13	[263]	GETTABLE 	2 2 -1	; "cover_info_cache"
	14	[263]	GETUPVAL 	3 1	; file
	15	[263]	GETTABLE 	2 2 3
	16	[263]	CALL     	1 2 4
	17	[264]	EQ       	0 3 -3	; - "complete"
	18	[264]	JMP      	3	; to 22
	19	[264]	LOADK    	4 -4	; "reading"
	20	[264]	TESTSET  	0 4 1
	21	[264]	JMP      	1	; to 23
	22	[264]	LOADK    	0 -3	; "complete"
	23	[266]	GETUPVAL 	4 0	; self
	24	[266]	GETTABLE 	4 4 -1	; "cover_info_cache"
	25	[266]	GETUPVAL 	5 1	; file
	26	[266]	NEWTABLE 	6 3 0
	27	[266]	MOVE     	7 1
	28	[266]	MOVE     	8 2
	29	[266]	MOVE     	9 0
	30	[266]	SETLIST  	6 3 1	; 1
	31	[266]	SETTABLE 	4 5 6
	32	[266]	JMP      	1	; to 34
	33	[269]	LOADK    	0 -3	; "complete"
	34	[273]	GETUPVAL 	1 2	; DocSettings
	35	[273]	SELF     	1 1 -5	; "open"
	36	[273]	GETUPVAL 	3 1	; file
	37	[273]	CALL     	1 3 2
	38	[274]	GETTABLE 	2 1 -6	; "data"
	39	[274]	GETTABLE 	2 2 -7	; "summary"
	40	[274]	TEST     	2 0 0
	41	[274]	JMP      	9	; to 51
	42	[274]	GETTABLE 	2 1 -6	; "data"
	43	[274]	GETTABLE 	2 2 -7	; "summary"
	44	[274]	GETTABLE 	2 2 -8	; "status"
	45	[274]	TEST     	2 0 0
	46	[274]	JMP      	4	; to 51
	47	[276]	GETTABLE 	2 1 -6	; "data"
	48	[276]	GETTABLE 	2 2 -7	; "summary"
	49	[276]	SETTABLE 	2 -8 0	; "status" -
	50	[276]	JMP      	21	; to 72
	51	[279]	GETTABLE 	2 1 -6	; "data"
	52	[279]	GETTABLE 	2 2 -7	; "summary"
	53	[279]	TEST     	2 0 0
	54	[279]	JMP      	11	; to 66
	55	[281]	NEWTABLE 	2 0 1
	56	[281]	SETTABLE 	2 -8 0	; "status" -
	57	[283]	GETGLOBAL	3 -9	; require
	58	[283]	LOADK    	4 -10	; "util"
	59	[283]	CALL     	3 2 2
	60	[283]	GETTABLE 	3 3 -11	; "tableMerge"
	61	[283]	GETTABLE 	4 1 -6	; "data"
	62	[283]	GETTABLE 	4 4 -7	; "summary"
	63	[283]	MOVE     	5 2
	64	[283]	CALL     	3 3 1
	65	[283]	JMP      	6	; to 72
	66	[286]	NEWTABLE 	2 0 1
	67	[286]	SETTABLE 	2 -8 0	; "status" -
	68	[287]	SELF     	3 1 -12	; "saveSetting"
	69	[287]	LOADK    	5 -7	; "summary"
	70	[287]	MOVE     	6 2
	71	[287]	CALL     	3 4 1
	72	[290]	SELF     	2 1 -13	; "flush"
	73	[290]	CALL     	2 2 1
	74	[292]	GETUPVAL 	2 3	; UIManager
	75	[292]	SELF     	2 2 -14	; "close"
	76	[292]	GETUPVAL 	4 0	; self
	77	[292]	GETTABLE 	4 4 -15	; "file_dialog"
	78	[292]	CALL     	2 3 1
	79	[293]	GETUPVAL 	2 0	; self
	80	[293]	SELF     	2 2 -16	; "updateItems"
	81	[293]	CALL     	2 2 1
	82	[294]	RETURN   	0 1

function <./plugins/coverbrowser.koplugin/covermenu.lua:303,325> (49 instructions, 196 bytes at 0x7fd83440abe0)
0 params, 9 slots, 7 upvalues, 3 locals, 15 constants, 0 functions
	1	[304]	GETUPVAL 	0 0	; DocumentRegistry
	2	[304]	SELF     	0 0 -1	; "openDocument"
	3	[304]	GETUPVAL 	2 1	; file
	4	[304]	CALL     	0 3 2
	5	[305]	TEST     	0 0 0
	6	[305]	JMP      	42	; to 49
	7	[306]	GETTABLE 	1 0 -2	; "loadDocument"
	8	[306]	TEST     	1 0 0
	9	[306]	JMP      	3	; to 13
	10	[307]	SELF     	1 0 -2	; "loadDocument"
	11	[307]	LOADBOOL 	3 0 0
	12	[307]	CALL     	1 3 1
	13	[309]	SELF     	1 0 -3	; "getCoverPageImage"
	14	[309]	CALL     	1 2 2
	15	[310]	TEST     	1 0 0
	16	[310]	JMP      	12	; to 29
	17	[311]	GETUPVAL 	2 2	; ImageViewer
	18	[311]	SELF     	2 2 -4	; "new"
	19	[311]	NEWTABLE 	4 0 3
	20	[312]	SETTABLE 	4 -5 1	; "image" -
	21	[313]	SETTABLE 	4 -6 -7	; "with_title_bar" false
	22	[314]	SETTABLE 	4 -8 -9	; "fullscreen" true
	23	[311]	CALL     	2 3 2
	24	[316]	GETUPVAL 	3 3	; UIManager
	25	[316]	SELF     	3 3 -10	; "show"
	26	[316]	MOVE     	5 2
	27	[316]	CALL     	3 3 1
	28	[316]	JMP      	11	; to 40
	29	[318]	GETUPVAL 	2 3	; UIManager
	30	[318]	SELF     	2 2 -10	; "show"
	31	[318]	GETUPVAL 	4 4	; InfoMessage
	32	[318]	SELF     	4 4 -4	; "new"
	33	[318]	NEWTABLE 	6 0 1
	34	[319]	GETUPVAL 	7 5	; _
	35	[319]	LOADK    	8 -12	; "No cover image available."
	36	[319]	CALL     	7 2 2
	37	[319]	SETTABLE 	6 -11 7	; "text" -
	38	[318]	CALL     	4 3 0
	39	[318]	CALL     	2 0 1
	40	[322]	GETUPVAL 	2 3	; UIManager
	41	[322]	SELF     	2 2 -13	; "close"
	42	[322]	GETUPVAL 	4 6	; self
	43	[322]	GETTABLE 	4 4 -14	; "file_dialog"
	44	[322]	CALL     	2 3 1
	45	[323]	GETUPVAL 	2 0	; DocumentRegistry
	46	[323]	SELF     	2 2 -15	; "closeDocument"
	47	[323]	GETUPVAL 	4 1	; file
	48	[323]	CALL     	2 3 1
	49	[325]	RETURN   	0 1

function <./plugins/coverbrowser.koplugin/covermenu.lua:330,338> (25 instructions, 100 bytes at 0x7fd83440bd90)
0 params, 5 slots, 4 upvalues, 2 locals, 10 constants, 0 functions
	1	[331]	GETGLOBAL	0 -1	; require
	2	[331]	LOADK    	1 -2	; "util"
	3	[331]	CALL     	0 2 2
	4	[331]	GETTABLE 	0 0 -3	; "htmlToPlainTextIfHtml"
	5	[331]	GETUPVAL 	1 0	; bookinfo
	6	[331]	GETTABLE 	1 1 -4	; "description"
	7	[331]	CALL     	0 2 2
	8	[332]	GETUPVAL 	1 1	; TextViewer
	9	[332]	SELF     	1 1 -5	; "new"
	10	[332]	NEWTABLE 	3 0 2
	11	[333]	GETUPVAL 	4 0	; bookinfo
	12	[333]	GETTABLE 	4 4 -6	; "title"
	13	[333]	SETTABLE 	3 -6 4	; "title" -
	14	[334]	SETTABLE 	3 -7 0	; "text" -
	15	[332]	CALL     	1 3 2
	16	[336]	GETUPVAL 	2 2	; UIManager
	17	[336]	SELF     	2 2 -8	; "close"
	18	[336]	GETUPVAL 	4 3	; self
	19	[336]	GETTABLE 	4 4 -9	; "file_dialog"
	20	[336]	CALL     	2 3 1
	21	[337]	GETUPVAL 	2 2	; UIManager
	22	[337]	SELF     	2 2 -10	; "show"
	23	[337]	MOVE     	4 1
	24	[337]	CALL     	2 3 1
	25	[338]	RETURN   	0 1

function <./plugins/coverbrowser.koplugin/covermenu.lua:345,351> (23 instructions, 92 bytes at 0x7fd83440b670)
0 params, 5 slots, 5 upvalues, 0 locals, 6 constants, 0 functions
	1	[346]	GETUPVAL 	0 0	; BookInfoManager
	2	[346]	SELF     	0 0 -1	; "setBookInfoProperties"
	3	[346]	GETUPVAL 	2 1	; file
	4	[346]	NEWTABLE 	3 0 1
	5	[347]	GETUPVAL 	4 2	; bookinfo
	6	[347]	GETTABLE 	4 4 -2	; "ignore_cover"
	7	[347]	TEST     	4 0 1
	8	[347]	JMP      	3	; to 12
	9	[347]	LOADK    	4 -3	; "Y"
	10	[347]	TEST     	4 0 1
	11	[347]	JMP      	1	; to 13
	12	[347]	LOADBOOL 	4 0 0
	13	[347]	SETTABLE 	3 -2 4	; "ignore_cover" -
	14	[346]	CALL     	0 4 1
	15	[349]	GETUPVAL 	0 3	; UIManager
	16	[349]	SELF     	0 0 -4	; "close"
	17	[349]	GETUPVAL 	2 4	; self
	18	[349]	GETTABLE 	2 2 -5	; "file_dialog"
	19	[349]	CALL     	0 3 1
	20	[350]	GETUPVAL 	0 4	; self
	21	[350]	SELF     	0 0 -6	; "updateItems"
	22	[350]	CALL     	0 2 1
	23	[351]	RETURN   	0 1

function <./plugins/coverbrowser.koplugin/covermenu.lua:356,362> (23 instructions, 92 bytes at 0x7fd83440a6f0)
0 params, 5 slots, 5 upvalues, 0 locals, 6 constants, 0 functions
	1	[357]	GETUPVAL 	0 0	; BookInfoManager
	2	[357]	SELF     	0 0 -1	; "setBookInfoProperties"
	3	[357]	GETUPVAL 	2 1	; file
	4	[357]	NEWTABLE 	3 0 1
	5	[358]	GETUPVAL 	4 2	; bookinfo
	6	[358]	GETTABLE 	4 4 -2	; "ignore_meta"
	7	[358]	TEST     	4 0 1
	8	[358]	JMP      	3	; to 12
	9	[358]	LOADK    	4 -3	; "Y"
	10	[358]	TEST     	4 0 1
	11	[358]	JMP      	1	; to 13
	12	[358]	LOADBOOL 	4 0 0
	13	[358]	SETTABLE 	3 -2 4	; "ignore_meta" -
	14	[357]	CALL     	0 4 1
	15	[360]	GETUPVAL 	0 3	; UIManager
	16	[360]	SELF     	0 0 -4	; "close"
	17	[360]	GETUPVAL 	2 4	; self
	18	[360]	GETTABLE 	2 2 -5	; "file_dialog"
	19	[360]	CALL     	0 3 1
	20	[361]	GETUPVAL 	0 4	; self
	21	[361]	SELF     	0 0 -6	; "updateItems"
	22	[361]	CALL     	0 2 1
	23	[362]	RETURN   	0 1

function <./plugins/coverbrowser.koplugin/covermenu.lua:369,377> (27 instructions, 108 bytes at 0x7fd83440a770)
0 params, 3 slots, 4 upvalues, 0 locals, 6 constants, 0 functions
	1	[371]	GETUPVAL 	0 0	; self
	2	[371]	GETTABLE 	0 0 -1	; "cover_info_cache"
	3	[371]	TEST     	0 0 0
	4	[371]	JMP      	10	; to 15
	5	[371]	GETUPVAL 	0 0	; self
	6	[371]	GETTABLE 	0 0 -1	; "cover_info_cache"
	7	[371]	GETUPVAL 	1 1	; file
	8	[371]	GETTABLE 	0 0 1
	9	[371]	TEST     	0 0 0
	10	[371]	JMP      	4	; to 15
	11	[372]	GETUPVAL 	0 0	; self
	12	[372]	GETTABLE 	0 0 -1	; "cover_info_cache"
	13	[372]	GETUPVAL 	1 1	; file
	14	[372]	SETTABLE 	0 1 -2	; - nil
	15	[374]	GETUPVAL 	0 2	; BookInfoManager
	16	[374]	SELF     	0 0 -3	; "deleteBookInfo"
	17	[374]	GETUPVAL 	2 1	; file
	18	[374]	CALL     	0 3 1
	19	[375]	GETUPVAL 	0 3	; UIManager
	20	[375]	SELF     	0 0 -4	; "close"
	21	[375]	GETUPVAL 	2 0	; self
	22	[375]	GETTABLE 	2 2 -5	; "file_dialog"
	23	[375]	CALL     	0 3 1
	24	[376]	GETUPVAL 	0 0	; self
	25	[376]	SELF     	0 0 -6	; "updateItems"
	26	[376]	CALL     	0 2 1
	27	[377]	RETURN   	0 1

function <./plugins/coverbrowser.koplugin/covermenu.lua:400,522> (207 instructions, 828 bytes at 0x7fd834409f80)
2 params, 15 slots, 8 upvalues, 9 locals, 33 constants, 6 functions
	1	[403]	GETTABLE 	2 0 -1	; "onMenuHold_orig"
	2	[403]	MOVE     	3 0
	3	[403]	MOVE     	4 1
	4	[403]	CALL     	2 3 1
	5	[404]	GETTABLE 	2 1 -2	; "file"
	6	[406]	GETUPVAL 	3 0	; BookInfoManager
	7	[406]	SELF     	3 3 -3	; "getBookInfo"
	8	[406]	MOVE     	5 2
	9	[406]	CALL     	3 3 2
	10	[407]	TEST     	3 0 1
	11	[407]	JMP      	2	; to 14
	12	[409]	LOADBOOL 	4 1 0
	13	[409]	RETURN   	4 2
	14	[413]	GETTABLE 	4 0 -4	; "histfile_dialog"
	15	[413]	GETTABLE 	4 4 -5	; "title"
	16	[414]	GETTABLE 	5 0 -4	; "histfile_dialog"
	17	[414]	GETTABLE 	5 5 -6	; "title_align"
	18	[415]	GETTABLE 	6 0 -4	; "histfile_dialog"
	19	[415]	GETTABLE 	6 6 -7	; "buttons"
	20	[418]	GETUPVAL 	7 1	; UIManager
	21	[418]	SELF     	7 7 -8	; "close"
	22	[418]	GETTABLE 	9 0 -4	; "histfile_dialog"
	23	[418]	CALL     	7 3 1
	24	[419]	GETUPVAL 	7 1	; UIManager
	25	[419]	SELF     	7 7 -9	; "clearRenderStack"
	26	[419]	CALL     	7 2 1
	27	[422]	GETTABLE 	7 6 -10	; 2
	28	[422]	GETTABLE 	7 7 -10	; 2
	29	[425]	CLOSURE  	8 0	; 0x7fd83440c600
	30	[425]	GETUPVAL 	0 2	; FileManagerBookInfo
	31	[425]	MOVE     	0 2
	32	[425]	MOVE     	0 3
	33	[425]	GETUPVAL 	0 1	; UIManager
	34	[425]	MOVE     	0 0
	35	[425]	SETTABLE 	7 -11 8	; "callback" -
	36	[429]	GETGLOBAL	7 -12	; table
	37	[429]	GETTABLE 	7 7 -13	; "remove"
	38	[429]	MOVE     	8 6
	39	[429]	CALL     	7 2 2
	40	[432]	GETGLOBAL	8 -12	; table
	41	[432]	GETTABLE 	8 8 -14	; "insert"
	42	[432]	MOVE     	9 6
	43	[432]	NEWTABLE 	10 2 0
	44	[432]	NEWTABLE 	11 0 3
	45	[434]	GETUPVAL 	12 3	; _
	46	[434]	LOADK    	13 -16	; "View full size cover"
	47	[434]	CALL     	12 2 2
	48	[434]	SETTABLE 	11 -15 12	; "text" -
	49	[435]	GETTABLE 	12 3 -18	; "has_cover"
	50	[435]	TEST     	12 0 0
	51	[435]	JMP      	3	; to 55
	52	[435]	LOADBOOL 	12 1 0
	53	[435]	TEST     	12 0 1
	54	[435]	JMP      	1	; to 56
	55	[435]	LOADBOOL 	12 0 0
	56	[435]	SETTABLE 	11 -17 12	; "enabled" -
	57	[458]	CLOSURE  	12 1	; 0x7fd834407cf0
	58	[458]	GETUPVAL 	0 4	; DocumentRegistry
	59	[458]	MOVE     	0 2
	60	[458]	GETUPVAL 	0 5	; ImageViewer
	61	[458]	GETUPVAL 	0 1	; UIManager
	62	[458]	GETUPVAL 	0 6	; InfoMessage
	63	[458]	GETUPVAL 	0 3	; _
	64	[458]	MOVE     	0 0
	65	[458]	SETTABLE 	11 -11 12	; "callback" -
	66	[459]	NEWTABLE 	12 0 3
	67	[461]	GETTABLE 	13 3 -19	; "description"
	68	[461]	TEST     	13 0 0
	69	[461]	JMP      	5	; to 75
	70	[461]	GETUPVAL 	13 3	; _
	71	[461]	LOADK    	14 -20	; "View book description"
	72	[461]	CALL     	13 2 2
	73	[461]	TEST     	13 0 1
	74	[461]	JMP      	3	; to 78
	75	[461]	GETUPVAL 	13 3	; _
	76	[461]	LOADK    	14 -21	; "No book description"
	77	[461]	CALL     	13 2 2
	78	[461]	SETTABLE 	12 -15 13	; "text" -
	79	[462]	GETTABLE 	13 3 -19	; "description"
	80	[462]	TEST     	13 0 0
	81	[462]	JMP      	3	; to 85
	82	[462]	LOADBOOL 	13 1 0
	83	[462]	TEST     	13 0 1
	84	[462]	JMP      	1	; to 86
	85	[462]	LOADBOOL 	13 0 0
	86	[462]	SETTABLE 	12 -17 13	; "enabled" -
	87	[471]	CLOSURE  	13 2	; 0x7fd83440c6f0
	88	[471]	MOVE     	0 3
	89	[471]	GETUPVAL 	0 7	; TextViewer
	90	[471]	GETUPVAL 	0 1	; UIManager
	91	[471]	MOVE     	0 0
	92	[471]	SETTABLE 	12 -11 13	; "callback" -
	93	[473]	SETLIST  	10 2 1	; 1
	94	[432]	CALL     	8 3 1
	95	[474]	GETGLOBAL	8 -12	; table
	96	[474]	GETTABLE 	8 8 -14	; "insert"
	97	[474]	MOVE     	9 6
	98	[474]	NEWTABLE 	10 2 0
	99	[474]	NEWTABLE 	11 0 3
	100	[476]	GETTABLE 	12 3 -22	; "ignore_cover"
	101	[476]	TEST     	12 0 0
	102	[476]	JMP      	5	; to 108
	103	[476]	GETUPVAL 	12 3	; _
	104	[476]	LOADK    	13 -23	; "Unignore cover"
	105	[476]	CALL     	12 2 2
	106	[476]	TEST     	12 0 1
	107	[476]	JMP      	3	; to 111
	108	[476]	GETUPVAL 	12 3	; _
	109	[476]	LOADK    	13 -24	; "Ignore cover"
	110	[476]	CALL     	12 2 2
	111	[476]	SETTABLE 	11 -15 12	; "text" -
	112	[477]	GETTABLE 	12 3 -18	; "has_cover"
	113	[477]	TEST     	12 0 0
	114	[477]	JMP      	3	; to 118
	115	[477]	LOADBOOL 	12 1 0
	116	[477]	TEST     	12 0 1
	117	[477]	JMP      	1	; to 119
	118	[477]	LOADBOOL 	12 0 0
	119	[477]	SETTABLE 	11 -17 12	; "enabled" -
	120	[484]	CLOSURE  	12 3	; 0x7fd83440cd20
	121	[484]	GETUPVAL 	0 0	; BookInfoManager
	122	[484]	MOVE     	0 2
	123	[484]	MOVE     	0 3
	124	[484]	GETUPVAL 	0 1	; UIManager
	125	[484]	MOVE     	0 0
	126	[484]	SETTABLE 	11 -11 12	; "callback" -
	127	[485]	NEWTABLE 	12 0 3
	128	[487]	GETTABLE 	13 3 -25	; "ignore_meta"
	129	[487]	TEST     	13 0 0
	130	[487]	JMP      	5	; to 136
	131	[487]	GETUPVAL 	13 3	; _
	132	[487]	LOADK    	14 -26	; "Unignore metadata"
	133	[487]	CALL     	13 2 2
	134	[487]	TEST     	13 0 1
	135	[487]	JMP      	3	; to 139
	136	[487]	GETUPVAL 	13 3	; _
	137	[487]	LOADK    	14 -27	; "Ignore metadata"
	138	[487]	CALL     	13 2 2
	139	[487]	SETTABLE 	12 -15 13	; "text" -
	140	[488]	GETTABLE 	13 3 -28	; "has_meta"
	141	[488]	TEST     	13 0 0
	142	[488]	JMP      	3	; to 146
	143	[488]	LOADBOOL 	13 1 0
	144	[488]	TEST     	13 0 1
	145	[488]	JMP      	1	; to 147
	146	[488]	LOADBOOL 	13 0 0
	147	[488]	SETTABLE 	12 -17 13	; "enabled" -
	148	[495]	CLOSURE  	13 4	; 0x7fd83440da20
	149	[495]	GETUPVAL 	0 0	; BookInfoManager
	150	[495]	MOVE     	0 2
	151	[495]	MOVE     	0 3
	152	[495]	GETUPVAL 	0 1	; UIManager
	153	[495]	MOVE     	0 0
	154	[495]	SETTABLE 	12 -11 13	; "callback" -
	155	[497]	SETLIST  	10 2 1	; 1
	156	[474]	CALL     	8 3 1
	157	[498]	GETGLOBAL	8 -12	; table
	158	[498]	GETTABLE 	8 8 -14	; "insert"
	159	[498]	MOVE     	9 6
	160	[498]	NEWTABLE 	10 1 0
	161	[498]	NEWTABLE 	11 0 3
	162	[500]	GETUPVAL 	12 3	; _
	163	[500]	LOADK    	13 -29	; "Refresh cached book information"
	164	[500]	CALL     	12 2 2
	165	[500]	SETTABLE 	11 -15 12	; "text" -
	166	[501]	TEST     	3 0 0
	167	[501]	JMP      	3	; to 171
	168	[501]	LOADBOOL 	12 1 0
	169	[501]	TEST     	12 0 1
	170	[501]	JMP      	1	; to 172
	171	[501]	LOADBOOL 	12 0 0
	172	[501]	SETTABLE 	11 -17 12	; "enabled" -
	173	[506]	CLOSURE  	12 5	; 0x7fd83440d520
	174	[506]	GETUPVAL 	0 0	; BookInfoManager
	175	[506]	MOVE     	0 2
	176	[506]	GETUPVAL 	0 1	; UIManager
	177	[506]	MOVE     	0 0
	178	[506]	SETTABLE 	11 -11 12	; "callback" -
	179	[508]	SETLIST  	10 1 1	; 1
	180	[498]	CALL     	8 3 1
	181	[509]	GETGLOBAL	8 -12	; table
	182	[509]	GETTABLE 	8 8 -14	; "insert"
	183	[509]	MOVE     	9 6
	184	[509]	NEWTABLE 	10 0 0
	185	[509]	CALL     	8 3 1
	186	[511]	GETGLOBAL	8 -12	; table
	187	[511]	GETTABLE 	8 8 -14	; "insert"
	188	[511]	MOVE     	9 6
	189	[511]	MOVE     	10 7
	190	[511]	CALL     	8 3 1
	191	[514]	GETGLOBAL	8 -30	; require
	192	[514]	LOADK    	9 -31	; "ui/widget/buttondialogtitle"
	193	[514]	CALL     	8 2 2
	194	[515]	SELF     	9 8 -32	; "new"
	195	[515]	NEWTABLE 	11 0 3
	196	[516]	SETTABLE 	11 -5 4	; "title" -
	197	[517]	SETTABLE 	11 -6 5	; "title_align" -
	198	[518]	SETTABLE 	11 -7 6	; "buttons" -
	199	[515]	CALL     	9 3 2
	200	[519]	SETTABLE 	0 -4 9	; "histfile_dialog" -
	201	[520]	GETUPVAL 	9 1	; UIManager
	202	[520]	SELF     	9 9 -33	; "show"
	203	[520]	GETTABLE 	11 0 -4	; "histfile_dialog"
	204	[520]	CALL     	9 3 1
	205	[521]	LOADBOOL 	9 1 0
	206	[521]	RETURN   	9 2
	207	[522]	RETURN   	0 1

function <./plugins/coverbrowser.koplugin/covermenu.lua:422,425> (11 instructions, 44 bytes at 0x7fd83440c600)
0 params, 4 slots, 5 upvalues, 0 locals, 3 constants, 0 functions
	1	[423]	GETUPVAL 	0 0	; FileManagerBookInfo
	2	[423]	SELF     	0 0 -1	; "show"
	3	[423]	GETUPVAL 	2 1	; file
	4	[423]	GETUPVAL 	3 2	; bookinfo
	5	[423]	CALL     	0 4 1
	6	[424]	GETUPVAL 	0 3	; UIManager
	7	[424]	SELF     	0 0 -2	; "close"
	8	[424]	GETUPVAL 	2 4	; self
	9	[424]	GETTABLE 	2 2 -3	; "histfile_dialog"
	10	[424]	CALL     	0 3 1
	11	[425]	RETURN   	0 1

function <./plugins/coverbrowser.koplugin/covermenu.lua:436,458> (49 instructions, 196 bytes at 0x7fd834407cf0)
0 params, 9 slots, 7 upvalues, 3 locals, 15 constants, 0 functions
	1	[437]	GETUPVAL 	0 0	; DocumentRegistry
	2	[437]	SELF     	0 0 -1	; "openDocument"
	3	[437]	GETUPVAL 	2 1	; file
	4	[437]	CALL     	0 3 2
	5	[438]	TEST     	0 0 0
	6	[438]	JMP      	42	; to 49
	7	[439]	GETTABLE 	1 0 -2	; "loadDocument"
	8	[439]	TEST     	1 0 0
	9	[439]	JMP      	3	; to 13
	10	[440]	SELF     	1 0 -2	; "loadDocument"
	11	[440]	LOADBOOL 	3 0 0
	12	[440]	CALL     	1 3 1
	13	[442]	SELF     	1 0 -3	; "getCoverPageImage"
	14	[442]	CALL     	1 2 2
	15	[443]	TEST     	1 0 0
	16	[443]	JMP      	12	; to 29
	17	[444]	GETUPVAL 	2 2	; ImageViewer
	18	[444]	SELF     	2 2 -4	; "new"
	19	[444]	NEWTABLE 	4 0 3
	20	[445]	SETTABLE 	4 -5 1	; "image" -
	21	[446]	SETTABLE 	4 -6 -7	; "with_title_bar" false
	22	[447]	SETTABLE 	4 -8 -9	; "fullscreen" true
	23	[444]	CALL     	2 3 2
	24	[449]	GETUPVAL 	3 3	; UIManager
	25	[449]	SELF     	3 3 -10	; "show"
	26	[449]	MOVE     	5 2
	27	[449]	CALL     	3 3 1
	28	[449]	JMP      	11	; to 40
	29	[451]	GETUPVAL 	2 3	; UIManager
	30	[451]	SELF     	2 2 -10	; "show"
	31	[451]	GETUPVAL 	4 4	; InfoMessage
	32	[451]	SELF     	4 4 -4	; "new"
	33	[451]	NEWTABLE 	6 0 1
	34	[452]	GETUPVAL 	7 5	; _
	35	[452]	LOADK    	8 -12	; "No cover image available."
	36	[452]	CALL     	7 2 2
	37	[452]	SETTABLE 	6 -11 7	; "text" -
	38	[451]	CALL     	4 3 0
	39	[451]	CALL     	2 0 1
	40	[455]	GETUPVAL 	2 3	; UIManager
	41	[455]	SELF     	2 2 -13	; "close"
	42	[455]	GETUPVAL 	4 6	; self
	43	[455]	GETTABLE 	4 4 -14	; "histfile_dialog"
	44	[455]	CALL     	2 3 1
	45	[456]	GETUPVAL 	2 0	; DocumentRegistry
	46	[456]	SELF     	2 2 -15	; "closeDocument"
	47	[456]	GETUPVAL 	4 1	; file
	48	[456]	CALL     	2 3 1
	49	[458]	RETURN   	0 1

function <./plugins/coverbrowser.koplugin/covermenu.lua:463,471> (25 instructions, 100 bytes at 0x7fd83440c6f0)
0 params, 5 slots, 4 upvalues, 2 locals, 10 constants, 0 functions
	1	[464]	GETGLOBAL	0 -1	; require
	2	[464]	LOADK    	1 -2	; "util"
	3	[464]	CALL     	0 2 2
	4	[464]	GETTABLE 	0 0 -3	; "htmlToPlainTextIfHtml"
	5	[464]	GETUPVAL 	1 0	; bookinfo
	6	[464]	GETTABLE 	1 1 -4	; "description"
	7	[464]	CALL     	0 2 2
	8	[465]	GETUPVAL 	1 1	; TextViewer
	9	[465]	SELF     	1 1 -5	; "new"
	10	[465]	NEWTABLE 	3 0 2
	11	[466]	GETUPVAL 	4 0	; bookinfo
	12	[466]	GETTABLE 	4 4 -6	; "title"
	13	[466]	SETTABLE 	3 -6 4	; "title" -
	14	[467]	SETTABLE 	3 -7 0	; "text" -
	15	[465]	CALL     	1 3 2
	16	[469]	GETUPVAL 	2 2	; UIManager
	17	[469]	SELF     	2 2 -8	; "close"
	18	[469]	GETUPVAL 	4 3	; self
	19	[469]	GETTABLE 	4 4 -9	; "histfile_dialog"
	20	[469]	CALL     	2 3 1
	21	[470]	GETUPVAL 	2 2	; UIManager
	22	[470]	SELF     	2 2 -10	; "show"
	23	[470]	MOVE     	4 1
	24	[470]	CALL     	2 3 1
	25	[471]	RETURN   	0 1

function <./plugins/coverbrowser.koplugin/covermenu.lua:478,484> (23 instructions, 92 bytes at 0x7fd83440cd20)
0 params, 5 slots, 5 upvalues, 0 locals, 6 constants, 0 functions
	1	[479]	GETUPVAL 	0 0	; BookInfoManager
	2	[479]	SELF     	0 0 -1	; "setBookInfoProperties"
	3	[479]	GETUPVAL 	2 1	; file
	4	[479]	NEWTABLE 	3 0 1
	5	[480]	GETUPVAL 	4 2	; bookinfo
	6	[480]	GETTABLE 	4 4 -2	; "ignore_cover"
	7	[480]	TEST     	4 0 1
	8	[480]	JMP      	3	; to 12
	9	[480]	LOADK    	4 -3	; "Y"
	10	[480]	TEST     	4 0 1
	11	[480]	JMP      	1	; to 13
	12	[480]	LOADBOOL 	4 0 0
	13	[480]	SETTABLE 	3 -2 4	; "ignore_cover" -
	14	[479]	CALL     	0 4 1
	15	[482]	GETUPVAL 	0 3	; UIManager
	16	[482]	SELF     	0 0 -4	; "close"
	17	[482]	GETUPVAL 	2 4	; self
	18	[482]	GETTABLE 	2 2 -5	; "histfile_dialog"
	19	[482]	CALL     	0 3 1
	20	[483]	GETUPVAL 	0 4	; self
	21	[483]	SELF     	0 0 -6	; "updateItems"
	22	[483]	CALL     	0 2 1
	23	[484]	RETURN   	0 1

function <./plugins/coverbrowser.koplugin/covermenu.lua:489,495> (23 instructions, 92 bytes at 0x7fd83440da20)
0 params, 5 slots, 5 upvalues, 0 locals, 6 constants, 0 functions
	1	[490]	GETUPVAL 	0 0	; BookInfoManager
	2	[490]	SELF     	0 0 -1	; "setBookInfoProperties"
	3	[490]	GETUPVAL 	2 1	; file
	4	[490]	NEWTABLE 	3 0 1
	5	[491]	GETUPVAL 	4 2	; bookinfo
	6	[491]	GETTABLE 	4 4 -2	; "ignore_meta"
	7	[491]	TEST     	4 0 1
	8	[491]	JMP      	3	; to 12
	9	[491]	LOADK    	4 -3	; "Y"
	10	[491]	TEST     	4 0 1
	11	[491]	JMP      	1	; to 13
	12	[491]	LOADBOOL 	4 0 0
	13	[491]	SETTABLE 	3 -2 4	; "ignore_meta" -
	14	[490]	CALL     	0 4 1
	15	[493]	GETUPVAL 	0 3	; UIManager
	16	[493]	SELF     	0 0 -4	; "close"
	17	[493]	GETUPVAL 	2 4	; self
	18	[493]	GETTABLE 	2 2 -5	; "histfile_dialog"
	19	[493]	CALL     	0 3 1
	20	[494]	GETUPVAL 	0 4	; self
	21	[494]	SELF     	0 0 -6	; "updateItems"
	22	[494]	CALL     	0 2 1
	23	[495]	RETURN   	0 1

function <./plugins/coverbrowser.koplugin/covermenu.lua:502,506> (13 instructions, 52 bytes at 0x7fd83440d520)
0 params, 3 slots, 4 upvalues, 0 locals, 4 constants, 0 functions
	1	[503]	GETUPVAL 	0 0	; BookInfoManager
	2	[503]	SELF     	0 0 -1	; "deleteBookInfo"
	3	[503]	GETUPVAL 	2 1	; file
	4	[503]	CALL     	0 3 1
	5	[504]	GETUPVAL 	0 2	; UIManager
	6	[504]	SELF     	0 0 -2	; "close"
	7	[504]	GETUPVAL 	2 3	; self
	8	[504]	GETTABLE 	2 2 -3	; "histfile_dialog"
	9	[504]	CALL     	0 3 1
	10	[505]	GETUPVAL 	0 3	; self
	11	[505]	SELF     	0 0 -4	; "updateItems"
	12	[505]	CALL     	0 2 1
	13	[506]	RETURN   	0 1

function <./plugins/coverbrowser.koplugin/covermenu.lua:526,640> (193 instructions, 772 bytes at 0x7fd83440c550)
2 params, 14 slots, 8 upvalues, 8 locals, 33 constants, 6 functions
	1	[529]	GETTABLE 	2 0 -1	; "onMenuHold_orig"
	2	[529]	MOVE     	3 0
	3	[529]	MOVE     	4 1
	4	[529]	CALL     	2 3 1
	5	[530]	GETTABLE 	2 1 -2	; "file"
	6	[532]	GETUPVAL 	3 0	; BookInfoManager
	7	[532]	SELF     	3 3 -3	; "getBookInfo"
	8	[532]	MOVE     	5 2
	9	[532]	CALL     	3 3 2
	10	[533]	TEST     	3 0 1
	11	[533]	JMP      	2	; to 14
	12	[535]	LOADBOOL 	4 1 0
	13	[535]	RETURN   	4 2
	14	[539]	GETTABLE 	4 0 -4	; "collfile_dialog"
	15	[539]	GETTABLE 	4 4 -5	; "title"
	16	[540]	GETTABLE 	5 0 -4	; "collfile_dialog"
	17	[540]	GETTABLE 	5 5 -6	; "title_align"
	18	[541]	GETTABLE 	6 0 -4	; "collfile_dialog"
	19	[541]	GETTABLE 	6 6 -7	; "buttons"
	20	[544]	GETUPVAL 	7 1	; UIManager
	21	[544]	SELF     	7 7 -8	; "close"
	22	[544]	GETTABLE 	9 0 -4	; "collfile_dialog"
	23	[544]	CALL     	7 3 1
	24	[545]	GETUPVAL 	7 1	; UIManager
	25	[545]	SELF     	7 7 -9	; "clearRenderStack"
	26	[545]	CALL     	7 2 1
	27	[548]	GETTABLE 	7 6 -10	; 2
	28	[548]	GETTABLE 	7 7 -11	; 1
	29	[551]	CLOSURE  	8 0	; 0x7fd83440cee0
	30	[551]	GETUPVAL 	0 2	; FileManagerBookInfo
	31	[551]	MOVE     	0 2
	32	[551]	MOVE     	0 3
	33	[551]	GETUPVAL 	0 1	; UIManager
	34	[551]	MOVE     	0 0
	35	[551]	SETTABLE 	7 -12 8	; "callback" -
	36	[554]	GETGLOBAL	7 -13	; table
	37	[554]	GETTABLE 	7 7 -14	; "insert"
	38	[554]	MOVE     	8 6
	39	[554]	NEWTABLE 	9 2 0
	40	[554]	NEWTABLE 	10 0 3
	41	[556]	GETUPVAL 	11 3	; _
	42	[556]	LOADK    	12 -16	; "View full size cover"
	43	[556]	CALL     	11 2 2
	44	[556]	SETTABLE 	10 -15 11	; "text" -
	45	[557]	GETTABLE 	11 3 -18	; "has_cover"
	46	[557]	TEST     	11 0 0
	47	[557]	JMP      	3	; to 51
	48	[557]	LOADBOOL 	11 1 0
	49	[557]	TEST     	11 0 1
	50	[557]	JMP      	1	; to 52
	51	[557]	LOADBOOL 	11 0 0
	52	[557]	SETTABLE 	10 -17 11	; "enabled" -
	53	[580]	CLOSURE  	11 1	; 0x7fd83440cf60
	54	[580]	GETUPVAL 	0 4	; DocumentRegistry
	55	[580]	MOVE     	0 2
	56	[580]	GETUPVAL 	0 5	; ImageViewer
	57	[580]	GETUPVAL 	0 1	; UIManager
	58	[580]	GETUPVAL 	0 6	; InfoMessage
	59	[580]	GETUPVAL 	0 3	; _
	60	[580]	MOVE     	0 0
	61	[580]	SETTABLE 	10 -12 11	; "callback" -
	62	[581]	NEWTABLE 	11 0 3
	63	[583]	GETTABLE 	12 3 -19	; "description"
	64	[583]	TEST     	12 0 0
	65	[583]	JMP      	5	; to 71
	66	[583]	GETUPVAL 	12 3	; _
	67	[583]	LOADK    	13 -20	; "View book description"
	68	[583]	CALL     	12 2 2
	69	[583]	TEST     	12 0 1
	70	[583]	JMP      	3	; to 74
	71	[583]	GETUPVAL 	12 3	; _
	72	[583]	LOADK    	13 -21	; "No book description"
	73	[583]	CALL     	12 2 2
	74	[583]	SETTABLE 	11 -15 12	; "text" -
	75	[584]	GETTABLE 	12 3 -19	; "description"
	76	[584]	TEST     	12 0 0
	77	[584]	JMP      	3	; to 81
	78	[584]	LOADBOOL 	12 1 0
	79	[584]	TEST     	12 0 1
	80	[584]	JMP      	1	; to 82
	81	[584]	LOADBOOL 	12 0 0
	82	[584]	SETTABLE 	11 -17 12	; "enabled" -
	83	[593]	CLOSURE  	12 2	; 0x7fd83440ece0
	84	[593]	MOVE     	0 3
	85	[593]	GETUPVAL 	0 7	; TextViewer
	86	[593]	GETUPVAL 	0 1	; UIManager
	87	[593]	MOVE     	0 0
	88	[593]	SETTABLE 	11 -12 12	; "callback" -
	89	[595]	SETLIST  	9 2 1	; 1
	90	[554]	CALL     	7 3 1
	91	[596]	GETGLOBAL	7 -13	; table
	92	[596]	GETTABLE 	7 7 -14	; "insert"
	93	[596]	MOVE     	8 6
	94	[596]	NEWTABLE 	9 2 0
	95	[596]	NEWTABLE 	10 0 3
	96	[598]	GETTABLE 	11 3 -22	; "ignore_cover"
	97	[598]	TEST     	11 0 0
	98	[598]	JMP      	5	; to 104
	99	[598]	GETUPVAL 	11 3	; _
	100	[598]	LOADK    	12 -23	; "Unignore cover"
	101	[598]	CALL     	11 2 2
	102	[598]	TEST     	11 0 1
	103	[598]	JMP      	3	; to 107
	104	[598]	GETUPVAL 	11 3	; _
	105	[598]	LOADK    	12 -24	; "Ignore cover"
	106	[598]	CALL     	11 2 2
	107	[598]	SETTABLE 	10 -15 11	; "text" -
	108	[599]	GETTABLE 	11 3 -18	; "has_cover"
	109	[599]	TEST     	11 0 0
	110	[599]	JMP      	3	; to 114
	111	[599]	LOADBOOL 	11 1 0
	112	[599]	TEST     	11 0 1
	113	[599]	JMP      	1	; to 115
	114	[599]	LOADBOOL 	11 0 0
	115	[599]	SETTABLE 	10 -17 11	; "enabled" -
	116	[606]	CLOSURE  	11 3	; 0x7fd83440e4e0
	117	[606]	GETUPVAL 	0 0	; BookInfoManager
	118	[606]	MOVE     	0 2
	119	[606]	MOVE     	0 3
	120	[606]	GETUPVAL 	0 1	; UIManager
	121	[606]	MOVE     	0 0
	122	[606]	SETTABLE 	10 -12 11	; "callback" -
	123	[607]	NEWTABLE 	11 0 3
	124	[609]	GETTABLE 	12 3 -25	; "ignore_meta"
	125	[609]	TEST     	12 0 0
	126	[609]	JMP      	5	; to 132
	127	[609]	GETUPVAL 	12 3	; _
	128	[609]	LOADK    	13 -26	; "Unignore metadata"
	129	[609]	CALL     	12 2 2
	130	[609]	TEST     	12 0 1
	131	[609]	JMP      	3	; to 135
	132	[609]	GETUPVAL 	12 3	; _
	133	[609]	LOADK    	13 -27	; "Ignore metadata"
	134	[609]	CALL     	12 2 2
	135	[609]	SETTABLE 	11 -15 12	; "text" -
	136	[610]	GETTABLE 	12 3 -28	; "has_meta"
	137	[610]	TEST     	12 0 0
	138	[610]	JMP      	3	; to 142
	139	[610]	LOADBOOL 	12 1 0
	140	[610]	TEST     	12 0 1
	141	[610]	JMP      	1	; to 143
	142	[610]	LOADBOOL 	12 0 0
	143	[610]	SETTABLE 	11 -17 12	; "enabled" -
	144	[617]	CLOSURE  	12 4	; 0x7fd83440f5e0
	145	[617]	GETUPVAL 	0 0	; BookInfoManager
	146	[617]	MOVE     	0 2
	147	[617]	MOVE     	0 3
	148	[617]	GETUPVAL 	0 1	; UIManager
	149	[617]	MOVE     	0 0
	150	[617]	SETTABLE 	11 -12 12	; "callback" -
	151	[619]	SETLIST  	9 2 1	; 1
	152	[596]	CALL     	7 3 1
	153	[620]	GETGLOBAL	7 -13	; table
	154	[620]	GETTABLE 	7 7 -14	; "insert"
	155	[620]	MOVE     	8 6
	156	[620]	NEWTABLE 	9 1 0
	157	[620]	NEWTABLE 	10 0 3
	158	[622]	GETUPVAL 	11 3	; _
	159	[622]	LOADK    	12 -29	; "Refresh cached book information"
	160	[622]	CALL     	11 2 2
	161	[622]	SETTABLE 	10 -15 11	; "text" -
	162	[623]	TEST     	3 0 0
	163	[623]	JMP      	3	; to 167
	164	[623]	LOADBOOL 	11 1 0
	165	[623]	TEST     	11 0 1
	166	[623]	JMP      	1	; to 168
	167	[623]	LOADBOOL 	11 0 0
	168	[623]	SETTABLE 	10 -17 11	; "enabled" -
	169	[628]	CLOSURE  	11 5	; 0x7fd83440f2a0
	170	[628]	GETUPVAL 	0 0	; BookInfoManager
	171	[628]	MOVE     	0 2
	172	[628]	GETUPVAL 	0 1	; UIManager
	173	[628]	MOVE     	0 0
	174	[628]	SETTABLE 	10 -12 11	; "callback" -
	175	[630]	SETLIST  	9 1 1	; 1
	176	[620]	CALL     	7 3 1
	177	[632]	GETGLOBAL	7 -30	; require
	178	[632]	LOADK    	8 -31	; "ui/widget/buttondialogtitle"
	179	[632]	CALL     	7 2 2
	180	[633]	SELF     	8 7 -32	; "new"
	181	[633]	NEWTABLE 	10 0 3
	182	[634]	SETTABLE 	10 -5 4	; "title" -
	183	[635]	SETTABLE 	10 -6 5	; "title_align" -
	184	[636]	SETTABLE 	10 -7 6	; "buttons" -
	185	[633]	CALL     	8 3 2
	186	[637]	SETTABLE 	0 -4 8	; "collfile_dialog" -
	187	[638]	GETUPVAL 	8 1	; UIManager
	188	[638]	SELF     	8 8 -33	; "show"
	189	[638]	GETTABLE 	10 0 -4	; "collfile_dialog"
	190	[638]	CALL     	8 3 1
	191	[639]	LOADBOOL 	8 1 0
	192	[639]	RETURN   	8 2
	193	[640]	RETURN   	0 1

function <./plugins/coverbrowser.koplugin/covermenu.lua:548,551> (11 instructions, 44 bytes at 0x7fd83440cee0)
0 params, 4 slots, 5 upvalues, 0 locals, 3 constants, 0 functions
	1	[549]	GETUPVAL 	0 0	; FileManagerBookInfo
	2	[549]	SELF     	0 0 -1	; "show"
	3	[549]	GETUPVAL 	2 1	; file
	4	[549]	GETUPVAL 	3 2	; bookinfo
	5	[549]	CALL     	0 4 1
	6	[550]	GETUPVAL 	0 3	; UIManager
	7	[550]	SELF     	0 0 -2	; "close"
	8	[550]	GETUPVAL 	2 4	; self
	9	[550]	GETTABLE 	2 2 -3	; "collfile_dialog"
	10	[550]	CALL     	0 3 1
	11	[551]	RETURN   	0 1

function <./plugins/coverbrowser.koplugin/covermenu.lua:558,580> (49 instructions, 196 bytes at 0x7fd83440cf60)
0 params, 9 slots, 7 upvalues, 3 locals, 15 constants, 0 functions
	1	[559]	GETUPVAL 	0 0	; DocumentRegistry
	2	[559]	SELF     	0 0 -1	; "openDocument"
	3	[559]	GETUPVAL 	2 1	; file
	4	[559]	CALL     	0 3 2
	5	[560]	TEST     	0 0 0
	6	[560]	JMP      	42	; to 49
	7	[561]	GETTABLE 	1 0 -2	; "loadDocument"
	8	[561]	TEST     	1 0 0
	9	[561]	JMP      	3	; to 13
	10	[562]	SELF     	1 0 -2	; "loadDocument"
	11	[562]	LOADBOOL 	3 0 0
	12	[562]	CALL     	1 3 1
	13	[564]	SELF     	1 0 -3	; "getCoverPageImage"
	14	[564]	CALL     	1 2 2
	15	[565]	TEST     	1 0 0
	16	[565]	JMP      	12	; to 29
	17	[566]	GETUPVAL 	2 2	; ImageViewer
	18	[566]	SELF     	2 2 -4	; "new"
	19	[566]	NEWTABLE 	4 0 3
	20	[567]	SETTABLE 	4 -5 1	; "image" -
	21	[568]	SETTABLE 	4 -6 -7	; "with_title_bar" false
	22	[569]	SETTABLE 	4 -8 -9	; "fullscreen" true
	23	[566]	CALL     	2 3 2
	24	[571]	GETUPVAL 	3 3	; UIManager
	25	[571]	SELF     	3 3 -10	; "show"
	26	[571]	MOVE     	5 2
	27	[571]	CALL     	3 3 1
	28	[571]	JMP      	11	; to 40
	29	[573]	GETUPVAL 	2 3	; UIManager
	30	[573]	SELF     	2 2 -10	; "show"
	31	[573]	GETUPVAL 	4 4	; InfoMessage
	32	[573]	SELF     	4 4 -4	; "new"
	33	[573]	NEWTABLE 	6 0 1
	34	[574]	GETUPVAL 	7 5	; _
	35	[574]	LOADK    	8 -12	; "No cover image available."
	36	[574]	CALL     	7 2 2
	37	[574]	SETTABLE 	6 -11 7	; "text" -
	38	[573]	CALL     	4 3 0
	39	[573]	CALL     	2 0 1
	40	[577]	GETUPVAL 	2 3	; UIManager
	41	[577]	SELF     	2 2 -13	; "close"
	42	[577]	GETUPVAL 	4 6	; self
	43	[577]	GETTABLE 	4 4 -14	; "collfile_dialog"
	44	[577]	CALL     	2 3 1
	45	[578]	GETUPVAL 	2 0	; DocumentRegistry
	46	[578]	SELF     	2 2 -15	; "closeDocument"
	47	[578]	GETUPVAL 	4 1	; file
	48	[578]	CALL     	2 3 1
	49	[580]	RETURN   	0 1

function <./plugins/coverbrowser.koplugin/covermenu.lua:585,593> (25 instructions, 100 bytes at 0x7fd83440ece0)
0 params, 5 slots, 4 upvalues, 2 locals, 10 constants, 0 functions
	1	[586]	GETGLOBAL	0 -1	; require
	2	[586]	LOADK    	1 -2	; "util"
	3	[586]	CALL     	0 2 2
	4	[586]	GETTABLE 	0 0 -3	; "htmlToPlainTextIfHtml"
	5	[586]	GETUPVAL 	1 0	; bookinfo
	6	[586]	GETTABLE 	1 1 -4	; "description"
	7	[586]	CALL     	0 2 2
	8	[587]	GETUPVAL 	1 1	; TextViewer
	9	[587]	SELF     	1 1 -5	; "new"
	10	[587]	NEWTABLE 	3 0 2
	11	[588]	GETUPVAL 	4 0	; bookinfo
	12	[588]	GETTABLE 	4 4 -6	; "title"
	13	[588]	SETTABLE 	3 -6 4	; "title" -
	14	[589]	SETTABLE 	3 -7 0	; "text" -
	15	[587]	CALL     	1 3 2
	16	[591]	GETUPVAL 	2 2	; UIManager
	17	[591]	SELF     	2 2 -8	; "close"
	18	[591]	GETUPVAL 	4 3	; self
	19	[591]	GETTABLE 	4 4 -9	; "collfile_dialog"
	20	[591]	CALL     	2 3 1
	21	[592]	GETUPVAL 	2 2	; UIManager
	22	[592]	SELF     	2 2 -10	; "show"
	23	[592]	MOVE     	4 1
	24	[592]	CALL     	2 3 1
	25	[593]	RETURN   	0 1

function <./plugins/coverbrowser.koplugin/covermenu.lua:600,606> (23 instructions, 92 bytes at 0x7fd83440e4e0)
0 params, 5 slots, 5 upvalues, 0 locals, 6 constants, 0 functions
	1	[601]	GETUPVAL 	0 0	; BookInfoManager
	2	[601]	SELF     	0 0 -1	; "setBookInfoProperties"
	3	[601]	GETUPVAL 	2 1	; file
	4	[601]	NEWTABLE 	3 0 1
	5	[602]	GETUPVAL 	4 2	; bookinfo
	6	[602]	GETTABLE 	4 4 -2	; "ignore_cover"
	7	[602]	TEST     	4 0 1
	8	[602]	JMP      	3	; to 12
	9	[602]	LOADK    	4 -3	; "Y"
	10	[602]	TEST     	4 0 1
	11	[602]	JMP      	1	; to 13
	12	[602]	LOADBOOL 	4 0 0
	13	[602]	SETTABLE 	3 -2 4	; "ignore_cover" -
	14	[601]	CALL     	0 4 1
	15	[604]	GETUPVAL 	0 3	; UIManager
	16	[604]	SELF     	0 0 -4	; "close"
	17	[604]	GETUPVAL 	2 4	; self
	18	[604]	GETTABLE 	2 2 -5	; "collfile_dialog"
	19	[604]	CALL     	0 3 1
	20	[605]	GETUPVAL 	0 4	; self
	21	[605]	SELF     	0 0 -6	; "updateItems"
	22	[605]	CALL     	0 2 1
	23	[606]	RETURN   	0 1

function <./plugins/coverbrowser.koplugin/covermenu.lua:611,617> (23 instructions, 92 bytes at 0x7fd83440f5e0)
0 params, 5 slots, 5 upvalues, 0 locals, 6 constants, 0 functions
	1	[612]	GETUPVAL 	0 0	; BookInfoManager
	2	[612]	SELF     	0 0 -1	; "setBookInfoProperties"
	3	[612]	GETUPVAL 	2 1	; file
	4	[612]	NEWTABLE 	3 0 1
	5	[613]	GETUPVAL 	4 2	; bookinfo
	6	[613]	GETTABLE 	4 4 -2	; "ignore_meta"
	7	[613]	TEST     	4 0 1
	8	[613]	JMP      	3	; to 12
	9	[613]	LOADK    	4 -3	; "Y"
	10	[613]	TEST     	4 0 1
	11	[613]	JMP      	1	; to 13
	12	[613]	LOADBOOL 	4 0 0
	13	[613]	SETTABLE 	3 -2 4	; "ignore_meta" -
	14	[612]	CALL     	0 4 1
	15	[615]	GETUPVAL 	0 3	; UIManager
	16	[615]	SELF     	0 0 -4	; "close"
	17	[615]	GETUPVAL 	2 4	; self
	18	[615]	GETTABLE 	2 2 -5	; "collfile_dialog"
	19	[615]	CALL     	0 3 1
	20	[616]	GETUPVAL 	0 4	; self
	21	[616]	SELF     	0 0 -6	; "updateItems"
	22	[616]	CALL     	0 2 1
	23	[617]	RETURN   	0 1

function <./plugins/coverbrowser.koplugin/covermenu.lua:624,628> (13 instructions, 52 bytes at 0x7fd83440f2a0)
0 params, 3 slots, 4 upvalues, 0 locals, 4 constants, 0 functions
	1	[625]	GETUPVAL 	0 0	; BookInfoManager
	2	[625]	SELF     	0 0 -1	; "deleteBookInfo"
	3	[625]	GETUPVAL 	2 1	; file
	4	[625]	CALL     	0 3 1
	5	[626]	GETUPVAL 	0 2	; UIManager
	6	[626]	SELF     	0 0 -2	; "close"
	7	[626]	GETUPVAL 	2 3	; self
	8	[626]	GETTABLE 	2 2 -3	; "collfile_dialog"
	9	[626]	CALL     	0 3 1
	10	[627]	GETUPVAL 	0 3	; self
	11	[627]	SELF     	0 0 -4	; "updateItems"
	12	[627]	CALL     	0 2 1
	13	[628]	RETURN   	0 1

function <./plugins/coverbrowser.koplugin/covermenu.lua:642,671> (38 instructions, 152 bytes at 0x7fd834406dc0)
1 param, 4 slots, 4 upvalues, 1 local, 14 constants, 0 functions
	1	[647]	GETUPVAL 	1 0	; logger
	2	[647]	GETTABLE 	1 1 -1	; "dbg"
	3	[647]	LOADK    	2 -2	; "CoverMenu:onCloseWidget: terminating jobs if needed"
	4	[647]	CALL     	1 2 1
	5	[648]	GETUPVAL 	1 1	; BookInfoManager
	6	[648]	SELF     	1 1 -3	; "terminateBackgroundJobs"
	7	[648]	CALL     	1 2 1
	8	[649]	GETUPVAL 	1 1	; BookInfoManager
	9	[649]	SELF     	1 1 -4	; "closeDbConnection"
	10	[649]	CALL     	1 2 1
	11	[650]	GETUPVAL 	1 1	; BookInfoManager
	12	[650]	SELF     	1 1 -5	; "cleanUp"
	13	[650]	CALL     	1 2 1
	14	[653]	GETTABLE 	1 0 -6	; "items_update_action"
	15	[653]	TEST     	1 0 0
	16	[653]	JMP      	9	; to 26
	17	[654]	GETUPVAL 	1 0	; logger
	18	[654]	GETTABLE 	1 1 -1	; "dbg"
	19	[654]	LOADK    	2 -7	; "CoverMenu:onCloseWidget: unscheduling items_update_action"
	20	[654]	CALL     	1 2 1
	21	[655]	GETUPVAL 	1 2	; UIManager
	22	[655]	SELF     	1 1 -8	; "unschedule"
	23	[655]	GETTABLE 	3 0 -6	; "items_update_action"
	24	[655]	CALL     	1 3 1
	25	[656]	SETTABLE 	0 -6 -9	; "items_update_action" nil
	26	[660]	GETTABLE 	1 0 -10	; "item_group"
	27	[660]	SELF     	1 1 -11	; "free"
	28	[660]	CALL     	1 2 1
	29	[663]	SETTABLE 	0 -12 -9	; "cover_info_cache" nil
	30	[666]	GETGLOBAL	1 -13	; collectgarbage
	31	[666]	CALL     	1 1 1
	32	[667]	GETGLOBAL	1 -13	; collectgarbage
	33	[667]	CALL     	1 1 1
	34	[670]	GETUPVAL 	1 3	; Menu
	35	[670]	GETTABLE 	1 1 -14	; "onCloseWidget"
	36	[670]	MOVE     	2 0
	37	[670]	CALL     	1 2 1
	38	[671]	RETURN   	0 1

function <./plugins/coverbrowser.koplugin/covermenu.lua:673,711> (57 instructions, 228 bytes at 0x7fd83440f3a0)
1 param, 10 slots, 6 upvalues, 5 locals, 16 constants, 1 function
	1	[676]	GETUPVAL 	1 0	; CoverMenu
	2	[676]	GETTABLE 	1 1 -1	; "_FileManager_tapPlus_orig"
	3	[676]	MOVE     	2 0
	4	[676]	CALL     	1 2 1
	5	[679]	GETTABLE 	1 0 -2	; "file_dialog"
	6	[679]	GETTABLE 	1 1 -3	; "title"
	7	[680]	GETTABLE 	2 0 -2	; "file_dialog"
	8	[680]	GETTABLE 	2 2 -4	; "title_align"
	9	[681]	GETTABLE 	3 0 -2	; "file_dialog"
	10	[681]	GETTABLE 	3 3 -5	; "buttons"
	11	[684]	GETUPVAL 	4 1	; UIManager
	12	[684]	SELF     	4 4 -6	; "close"
	13	[684]	GETTABLE 	6 0 -2	; "file_dialog"
	14	[684]	CALL     	4 3 1
	15	[685]	GETUPVAL 	4 1	; UIManager
	16	[685]	SELF     	4 4 -7	; "clearRenderStack"
	17	[685]	CALL     	4 2 1
	18	[688]	GETGLOBAL	4 -8	; table
	19	[688]	GETTABLE 	4 4 -9	; "insert"
	20	[688]	MOVE     	5 3
	21	[688]	NEWTABLE 	6 0 0
	22	[688]	CALL     	4 3 1
	23	[689]	GETGLOBAL	4 -8	; table
	24	[689]	GETTABLE 	4 4 -9	; "insert"
	25	[689]	MOVE     	5 3
	26	[689]	NEWTABLE 	6 1 0
	27	[689]	NEWTABLE 	7 0 2
	28	[691]	GETUPVAL 	8 2	; _
	29	[691]	LOADK    	9 -11	; "Extract and cache book information"
	30	[691]	CALL     	8 2 2
	31	[691]	SETTABLE 	7 -10 8	; "text" -
	32	[698]	CLOSURE  	8 0	; 0x7fd8344065c0
	33	[698]	GETUPVAL 	0 1	; UIManager
	34	[698]	MOVE     	0 0
	35	[698]	GETUPVAL 	0 3	; BookInfoManager
	36	[698]	GETUPVAL 	0 4	; current_path
	37	[698]	GETUPVAL 	0 5	; current_cover_specs
	38	[698]	SETTABLE 	7 -12 8	; "callback" -
	39	[700]	SETLIST  	6 1 1	; 1
	40	[689]	CALL     	4 3 1
	41	[703]	GETGLOBAL	4 -13	; require
	42	[703]	LOADK    	5 -14	; "ui/widget/buttondialogtitle"
	43	[703]	CALL     	4 2 2
	44	[704]	SELF     	5 4 -15	; "new"
	45	[704]	NEWTABLE 	7 0 3
	46	[705]	SETTABLE 	7 -3 1	; "title" -
	47	[706]	SETTABLE 	7 -4 2	; "title_align" -
	48	[707]	SETTABLE 	7 -5 3	; "buttons" -
	49	[704]	CALL     	5 3 2
	50	[708]	SETTABLE 	0 -2 5	; "file_dialog" -
	51	[709]	GETUPVAL 	5 1	; UIManager
	52	[709]	SELF     	5 5 -16	; "show"
	53	[709]	GETTABLE 	7 0 -2	; "file_dialog"
	54	[709]	CALL     	5 3 1
	55	[710]	LOADBOOL 	5 1 0
	56	[710]	RETURN   	5 2
	57	[711]	RETURN   	0 1

function <./plugins/coverbrowser.koplugin/covermenu.lua:692,698> (15 instructions, 60 bytes at 0x7fd8344065c0)
0 params, 4 slots, 5 upvalues, 1 local, 5 constants, 1 function
	1	[693]	GETUPVAL 	0 0	; UIManager
	2	[693]	SELF     	0 0 -1	; "close"
	3	[693]	GETUPVAL 	2 1	; self
	4	[693]	GETTABLE 	2 2 -2	; "file_dialog"
	5	[693]	CALL     	0 3 1
	6	[694]	GETGLOBAL	0 -3	; require
	7	[694]	LOADK    	1 -4	; "ui/trapper"
	8	[694]	CALL     	0 2 2
	9	[695]	SELF     	1 0 -5	; "wrap"
	10	[697]	CLOSURE  	3 0	; 0x7fd8344109c0
	11	[697]	GETUPVAL 	0 2	; BookInfoManager
	12	[697]	GETUPVAL 	0 3	; current_path
	13	[697]	GETUPVAL 	0 4	; current_cover_specs
	14	[695]	CALL     	1 3 1
	15	[698]	RETURN   	0 1

function <./plugins/coverbrowser.koplugin/covermenu.lua:695,697> (6 instructions, 24 bytes at 0x7fd8344109c0)
0 params, 4 slots, 3 upvalues, 0 locals, 1 constant, 0 functions
	1	[696]	GETUPVAL 	0 0	; BookInfoManager
	2	[696]	SELF     	0 0 -1	; "extractBooksInDirectory"
	3	[696]	GETUPVAL 	2 1	; current_path
	4	[696]	GETUPVAL 	3 2	; current_cover_specs
	5	[696]	CALL     	0 4 1
	6	[697]	RETURN   	0 1
