
main <./frontend/document/credocument.lua:0,0> (389 instructions, 1556 bytes at 0x7fa4a64068d0)
0+ params, 24 slots, 0 upvalues, 14 locals, 170 constants, 125 functions
	1	[1]	GETGLOBAL	0 -1	; require
	2	[1]	LOADK    	1 -2	; "ffi/blitbuffer"
	3	[1]	CALL     	0 2 2
	4	[2]	GETGLOBAL	1 -1	; require
	5	[2]	LOADK    	2 -3	; "document/canvascontext"
	6	[2]	CALL     	1 2 2
	7	[3]	GETGLOBAL	2 -1	; require
	8	[3]	LOADK    	3 -4	; "datastorage"
	9	[3]	CALL     	2 2 2
	10	[4]	GETGLOBAL	3 -1	; require
	11	[4]	LOADK    	4 -5	; "document/document"
	12	[4]	CALL     	3 2 2
	13	[5]	GETGLOBAL	4 -1	; require
	14	[5]	LOADK    	5 -6	; "fontlist"
	15	[5]	CALL     	4 2 2
	16	[6]	GETGLOBAL	5 -1	; require
	17	[6]	LOADK    	6 -7	; "ui/geometry"
	18	[6]	CALL     	5 2 2
	19	[7]	GETGLOBAL	6 -1	; require
	20	[7]	LOADK    	7 -8	; "ui/renderimage"
	21	[7]	CALL     	6 2 2
	22	[8]	GETGLOBAL	7 -1	; require
	23	[8]	LOADK    	8 -9	; "device"
	24	[8]	CALL     	7 2 2
	25	[8]	GETTABLE 	7 7 -10	; "screen"
	26	[9]	GETGLOBAL	8 -1	; require
	27	[9]	LOADK    	9 -11	; "ffi"
	28	[9]	CALL     	8 2 2
	29	[10]	GETTABLE 	9 8 -12	; "C"
	30	[11]	GETGLOBAL	10 -1	; require
	31	[11]	LOADK    	11 -13	; "libs/libkoreader-lfs"
	32	[11]	CALL     	10 2 2
	33	[12]	GETGLOBAL	11 -1	; require
	34	[12]	LOADK    	12 -14	; "logger"
	35	[12]	CALL     	11 2 2
	36	[15]	LOADBOOL 	12 0 0
	37	[17]	SELF     	13 3 -15	; "new"
	38	[17]	NEWTABLE 	15 0 14
	39	[19]	SETTABLE 	15 -16 -17	; "SCROLL_VIEW_MODE" 0
	40	[20]	SETTABLE 	15 -18 -19	; "PAGE_VIEW_MODE" 1
	41	[22]	SETTABLE 	15 -20 -21	; "_document" false
	42	[23]	SETTABLE 	15 -22 -21	; "_loaded" false
	43	[24]	SETTABLE 	15 -23 -24	; "_view_mode" nil
	44	[25]	SETTABLE 	15 -25 -21	; "_smooth_scaling" false
	45	[26]	SETTABLE 	15 -26 -27	; "_nightmode_images" true
	46	[28]	SETTABLE 	15 -28 -29	; "line_space_percent" 100
	47	[29]	SETTABLE 	15 -30 -31	; "default_font" "Noto Serif"
	48	[30]	SETTABLE 	15 -32 -33	; "header_font" "Noto Sans"
	49	[47]	NEWTABLE 	16 7 0
	50	[48]	LOADK    	17 -35	; "Noto Sans CJK SC"
	51	[49]	LOADK    	18 -36	; "Noto Sans Arabic UI"
	52	[50]	LOADK    	19 -37	; "Noto Sans Devanagari UI"
	53	[51]	LOADK    	20 -38	; "FreeSans"
	54	[52]	LOADK    	21 -39	; "FreeSerif"
	55	[53]	LOADK    	22 -31	; "Noto Serif"
	56	[55]	LOADK    	23 -33	; "Noto Sans"
	57	[55]	SETLIST  	16 7 1	; 1
	58	[55]	SETTABLE 	15 -34 16	; "fallback_fonts" -
	59	[57]	SETTABLE 	15 -40 -41	; "default_css" "./data/cr3.css"
	60	[58]	SETTABLE 	15 -42 -43	; "provider" "crengine"
	61	[59]	SETTABLE 	15 -44 -45	; "provider_name" "Cool Reader Engine"
	62	[17]	CALL     	13 3 2
	63	[72]	CLOSURE  	14 0	; 0x7fa4a64070c0
	64	[63]	SETTABLE 	13 -46 14	; "zipContentExt" -
	65	[94]	CLOSURE  	14 1	; 0x7fa4a6407ac0
	66	[94]	MOVE     	0 10
	67	[94]	MOVE     	0 2
	68	[74]	SETTABLE 	13 -47 14	; "cacheInit" -
	69	[118]	CLOSURE  	14 2	; 0x7fa4a6407fd0
	70	[118]	MOVE     	0 12
	71	[118]	MOVE     	0 4
	72	[118]	MOVE     	0 11
	73	[96]	SETTABLE 	13 -48 14	; "engineInit" -
	74	[164]	CLOSURE  	14 3	; 0x7fa4a64065f0
	75	[164]	MOVE     	0 1
	76	[120]	SETTABLE 	13 -49 14	; "init" -
	77	[168]	CLOSURE  	14 4	; 0x7fa4a6406700
	78	[166]	SETTABLE 	13 -50 14	; "getDomVersionWithNormalizedXPointers" -
	79	[172]	CLOSURE  	14 5	; 0x7fa4a6409520
	80	[170]	SETTABLE 	13 -51 14	; "getLatestDomVersion" -
	81	[176]	CLOSURE  	14 6	; 0x7fa4a6409780
	82	[174]	SETTABLE 	13 -52 14	; "getOldestDomVersion" -
	83	[181]	CLOSURE  	14 7	; 0x7fa4a6409a30
	84	[181]	MOVE     	0 11
	85	[178]	SETTABLE 	13 -53 14	; "requestDomVersion" -
	86	[208]	CLOSURE  	14 8	; 0x7fa4a6409e30
	87	[208]	MOVE     	0 11
	88	[208]	MOVE     	0 1
	89	[183]	SETTABLE 	13 -54 14	; "setupDefaultView" -
	90	[227]	CLOSURE  	14 9	; 0x7fa4a640a320
	91	[227]	MOVE     	0 11
	92	[210]	SETTABLE 	13 -55 14	; "loadDocument" -
	93	[243]	CLOSURE  	14 10	; 0x7fa4a640aa40
	94	[243]	MOVE     	0 11
	95	[229]	SETTABLE 	13 -56 14	; "render" -
	96	[253]	CLOSURE  	14 11	; 0x7fa4a640b3b0
	97	[253]	MOVE     	0 3
	98	[245]	SETTABLE 	13 -57 14	; "_readMetadata" -
	99	[261]	CLOSURE  	14 12	; 0x7fa4a640b5a0
	100	[261]	MOVE     	0 3
	101	[255]	SETTABLE 	13 -58 14	; "close" -
	102	[271]	CLOSURE  	14 13	; 0x7fa4a640b9a0
	103	[271]	MOVE     	0 3
	104	[263]	SETTABLE 	13 -59 14	; "updateColorRendering" -
	105	[275]	CLOSURE  	14 14	; 0x7fa4a640bdd0
	106	[273]	SETTABLE 	13 -60 14	; "getPageCount" -
	107	[288]	CLOSURE  	14 15	; 0x7fa4a640ba70
	108	[288]	MOVE     	0 6
	109	[288]	MOVE     	0 9
	110	[277]	SETTABLE 	13 -61 14	; "getCoverPageImage" -
	111	[298]	CLOSURE  	14 16	; 0x7fa4a6409b50
	112	[298]	MOVE     	0 11
	113	[298]	MOVE     	0 6
	114	[298]	MOVE     	0 9
	115	[290]	SETTABLE 	13 -62 14	; "getImageFromPosition" -
	116	[328]	CLOSURE  	14 17	; 0x7fa4a640a230
	117	[328]	MOVE     	0 11
	118	[328]	MOVE     	0 5
	119	[300]	SETTABLE 	13 -63 14	; "getWordFromPosition" -
	120	[342]	CLOSURE  	14 18	; 0x7fa4a640c370
	121	[342]	MOVE     	0 11
	122	[330]	SETTABLE 	13 -64 14	; "getTextFromPositions" -
	123	[358]	CLOSURE  	14 19	; 0x7fa4a640c1b0
	124	[358]	MOVE     	0 5
	125	[344]	SETTABLE 	13 -65 14	; "getScreenBoxesFromPositions" -
	126	[363]	CLOSURE  	14 20	; 0x7fa4a640d030
	127	[360]	SETTABLE 	13 -66 14	; "compareXPointers" -
	128	[367]	CLOSURE  	14 21	; 0x7fa4a640d3f0
	129	[365]	SETTABLE 	13 -67 14	; "getNextVisibleWordStart" -
	130	[371]	CLOSURE  	14 22	; 0x7fa4a640d6b0
	131	[369]	SETTABLE 	13 -68 14	; "getNextVisibleWordEnd" -
	132	[375]	CLOSURE  	14 23	; 0x7fa4a64085b0
	133	[373]	SETTABLE 	13 -69 14	; "getPrevVisibleWordStart" -
	134	[379]	CLOSURE  	14 24	; 0x7fa4a64087f0
	135	[377]	SETTABLE 	13 -70 14	; "getPrevVisibleWordEnd" -
	136	[383]	CLOSURE  	14 25	; 0x7fa4a640d8f0
	137	[381]	SETTABLE 	13 -71 14	; "getPrevVisibleChar" -
	138	[387]	CLOSURE  	14 26	; 0x7fa4a640ddd0
	139	[385]	SETTABLE 	13 -72 14	; "getNextVisibleChar" -
	140	[419]	CLOSURE  	14 27	; 0x7fa4a640e080
	141	[419]	MOVE     	0 0
	142	[419]	MOVE     	0 7
	143	[389]	SETTABLE 	13 -73 14	; "drawCurrentView" -
	144	[424]	CLOSURE  	14 28	; 0x7fa4a640e4f0
	145	[421]	SETTABLE 	13 -74 14	; "drawCurrentViewByPos" -
	146	[429]	CLOSURE  	14 29	; 0x7fa4a640eb50
	147	[426]	SETTABLE 	13 -75 14	; "drawCurrentViewByPage" -
	148	[432]	CLOSURE  	14 30	; 0x7fa4a640f050
	149	[431]	SETTABLE 	13 -76 14	; "hintPage" -
	150	[435]	CLOSURE  	14 31	; 0x7fa4a640f630
	151	[434]	SETTABLE 	13 -77 14	; "drawPage" -
	152	[438]	CLOSURE  	14 32	; 0x7fa4a640f810
	153	[437]	SETTABLE 	13 -78 14	; "renderPage" -
	154	[442]	CLOSURE  	14 33	; 0x7fa4a640f790
	155	[440]	SETTABLE 	13 -79 14	; "getPageMargins" -
	156	[446]	CLOSURE  	14 34	; 0x7fa4a640b1c0
	157	[444]	SETTABLE 	13 -80 14	; "getHeaderHeight" -
	158	[451]	CLOSURE  	14 35	; 0x7fa4a6410130
	159	[451]	MOVE     	0 11
	160	[448]	SETTABLE 	13 -81 14	; "gotoXPointer" -
	161	[455]	CLOSURE  	14 36	; 0x7fa4a6410540
	162	[453]	SETTABLE 	13 -82 14	; "getXPointer" -
	163	[459]	CLOSURE  	14 37	; 0x7fa4a6410900
	164	[457]	SETTABLE 	13 -83 14	; "isXPointerInDocument" -
	165	[463]	CLOSURE  	14 38	; 0x7fa4a6410b60
	166	[461]	SETTABLE 	13 -84 14	; "getPosFromXPointer" -
	167	[467]	CLOSURE  	14 39	; 0x7fa4a6410e40
	168	[465]	SETTABLE 	13 -85 14	; "getPageFromXPointer" -
	169	[471]	CLOSURE  	14 40	; 0x7fa4a64110f0
	170	[469]	SETTABLE 	13 -86 14	; "getPageOffsetX" -
	171	[498]	CLOSURE  	14 41	; 0x7fa4a64113a0
	172	[473]	SETTABLE 	13 -87 14	; "getScreenPositionFromXPointer" -
	173	[502]	CLOSURE  	14 42	; 0x7fa4a640d830
	174	[500]	SETTABLE 	13 -88 14	; "getFontFace" -
	175	[506]	CLOSURE  	14 43	; 0x7fa4a640d7b0
	176	[504]	SETTABLE 	13 -89 14	; "getCurrentPos" -
	177	[510]	CLOSURE  	14 44	; 0x7fa4a640e140
	178	[508]	SETTABLE 	13 -90 14	; "getPageLinks" -
	179	[514]	CLOSURE  	14 45	; 0x7fa4a640e1c0
	180	[512]	SETTABLE 	13 -91 14	; "getLinkFromPosition" -
	181	[518]	CLOSURE  	14 46	; 0x7fa4a64109f0
	182	[516]	SETTABLE 	13 -92 14	; "isLinkToFootnote" -
	183	[523]	CLOSURE  	14 47	; 0x7fa4a640d490
	184	[520]	SETTABLE 	13 -93 14	; "highlightXPointer" -
	185	[529]	CLOSURE  	14 48	; 0x7fa4a640d510
	186	[525]	SETTABLE 	13 -94 14	; "getDocumentFileContent" -
	187	[535]	CLOSURE  	14 49	; 0x7fa4a640f1b0
	188	[531]	SETTABLE 	13 -95 14	; "getTextFromXPointer" -
	189	[539]	CLOSURE  	14 50	; 0x7fa4a640f2d0
	190	[537]	SETTABLE 	13 -96 14	; "getTextFromXPointers" -
	191	[545]	CLOSURE  	14 51	; 0x7fa4a640f970
	192	[541]	SETTABLE 	13 -97 14	; "getHTMLFromXPointer" -
	193	[551]	CLOSURE  	14 52	; 0x7fa4a6411860
	194	[547]	SETTABLE 	13 -98 14	; "getHTMLFromXPointers" -
	195	[558]	CLOSURE  	14 53	; 0x7fa4a6411d40
	196	[553]	SETTABLE 	13 -99 14	; "getNormalizedXPointer" -
	197	[563]	CLOSURE  	14 54	; 0x7fa4a6412150
	198	[563]	MOVE     	0 11
	199	[560]	SETTABLE 	13 -100 14	; "gotoPos" -
	200	[568]	CLOSURE  	14 55	; 0x7fa4a64124c0
	201	[568]	MOVE     	0 11
	202	[565]	SETTABLE 	13 -101 14	; "gotoPage" -
	203	[573]	CLOSURE  	14 56	; 0x7fa4a6412960
	204	[573]	MOVE     	0 11
	205	[570]	SETTABLE 	13 -102 14	; "gotoLink" -
	206	[578]	CLOSURE  	14 57	; 0x7fa4a6412d40
	207	[578]	MOVE     	0 11
	208	[575]	SETTABLE 	13 -103 14	; "goBack" -
	209	[583]	CLOSURE  	14 58	; 0x7fa4a6413200
	210	[583]	MOVE     	0 11
	211	[580]	SETTABLE 	13 -104 14	; "goForward" -
	212	[587]	CLOSURE  	14 59	; 0x7fa4a6413480
	213	[585]	SETTABLE 	13 -105 14	; "getCurrentPage" -
	214	[626]	CLOSURE  	14 60	; 0x7fa4a64135c0
	215	[626]	MOVE     	0 11
	216	[589]	SETTABLE 	13 -106 14	; "setFontFace" -
	217	[654]	CLOSURE  	14 61	; 0x7fa4a64140d0
	218	[654]	MOVE     	0 11
	219	[628]	SETTABLE 	13 -107 14	; "setupFallbackFontFaces" -
	220	[663]	CLOSURE  	14 62	; 0x7fa4a6414510
	221	[663]	MOVE     	0 11
	222	[658]	SETTABLE 	13 -108 14	; "setTextMainLang" -
	223	[668]	CLOSURE  	14 63	; 0x7fa4a6414bd0
	224	[668]	MOVE     	0 11
	225	[665]	SETTABLE 	13 -109 14	; "setTextEmbeddedLangs" -
	226	[673]	CLOSURE  	14 64	; 0x7fa4a64150d0
	227	[673]	MOVE     	0 11
	228	[670]	SETTABLE 	13 -110 14	; "setTextHyphenation" -
	229	[678]	CLOSURE  	14 65	; 0x7fa4a6415600
	230	[678]	MOVE     	0 11
	231	[675]	SETTABLE 	13 -111 14	; "setTextHyphenationSoftHyphensOnly" -
	232	[683]	CLOSURE  	14 66	; 0x7fa4a6415a20
	233	[683]	MOVE     	0 11
	234	[680]	SETTABLE 	13 -112 14	; "setTextHyphenationForceAlgorithmic" -
	235	[688]	CLOSURE  	14 67	; 0x7fa4a6415f40
	236	[685]	SETTABLE 	13 -113 14	; "getTextMainLangDefaultHyphDictionary" -
	237	[696]	CLOSURE  	14 68	; 0x7fa4a64164e0
	238	[696]	MOVE     	0 11
	239	[691]	SETTABLE 	13 -114 14	; "setHyphDictionary" -
	240	[702]	CLOSURE  	14 69	; 0x7fa4a6416db0
	241	[702]	MOVE     	0 11
	242	[698]	SETTABLE 	13 -115 14	; "setHyphLeftHyphenMin" -
	243	[707]	CLOSURE  	14 70	; 0x7fa4a6416fe0
	244	[707]	MOVE     	0 11
	245	[704]	SETTABLE 	13 -116 14	; "setHyphRightHyphenMin" -
	246	[712]	CLOSURE  	14 71	; 0x7fa4a6417540
	247	[712]	MOVE     	0 11
	248	[709]	SETTABLE 	13 -117 14	; "setTrustSoftHyphens" -
	249	[721]	CLOSURE  	14 72	; 0x7fa4a6417ba0
	250	[721]	MOVE     	0 11
	251	[714]	SETTABLE 	13 -118 14	; "setRenderDPI" -
	252	[727]	CLOSURE  	14 73	; 0x7fa4a6418080
	253	[727]	MOVE     	0 11
	254	[723]	SETTABLE 	13 -119 14	; "setRenderScaleFontWithDPI" -
	255	[732]	CLOSURE  	14 74	; 0x7fa4a6418530
	256	[732]	MOVE     	0 11
	257	[729]	SETTABLE 	13 -120 14	; "clearSelection" -
	258	[736]	CLOSURE  	14 75	; 0x7fa4a6418970
	259	[734]	SETTABLE 	13 -121 14	; "getFontSize" -
	260	[743]	CLOSURE  	14 76	; 0x7fa4a6418bf0
	261	[743]	MOVE     	0 11
	262	[738]	SETTABLE 	13 -122 14	; "setFontSize" -
	263	[755]	CLOSURE  	14 77	; 0x7fa4a6418fa0
	264	[755]	MOVE     	0 11
	265	[745]	SETTABLE 	13 -123 14	; "setViewMode" -
	266	[760]	CLOSURE  	14 78	; 0x7fa4a64193c0
	267	[760]	MOVE     	0 11
	268	[757]	SETTABLE 	13 -124 14	; "setViewDimen" -
	269	[767]	CLOSURE  	14 79	; 0x7fa4a6419aa0
	270	[767]	MOVE     	0 11
	271	[762]	SETTABLE 	13 -125 14	; "setHeaderFont" -
	272	[772]	CLOSURE  	14 80	; 0x7fa4a6419f50
	273	[772]	MOVE     	0 11
	274	[769]	SETTABLE 	13 -126 14	; "zoomFont" -
	275	[777]	CLOSURE  	14 81	; 0x7fa4a641a430
	276	[777]	MOVE     	0 11
	277	[774]	SETTABLE 	13 -127 14	; "setInterlineSpacePercent" -
	278	[782]	CLOSURE  	14 82	; 0x7fa4a641a950
	279	[782]	MOVE     	0 11
	280	[779]	SETTABLE 	13 -128 14	; "toggleFontBolder" -
	281	[786]	CLOSURE  	14 83	; 0x7fa4a641ae70
	282	[784]	SETTABLE 	13 -129 14	; "getGammaLevel" -
	283	[791]	CLOSURE  	14 84	; 0x7fa4a641b230
	284	[791]	MOVE     	0 11
	285	[788]	SETTABLE 	13 -130 14	; "setGammaIndex" -
	286	[796]	CLOSURE  	14 85	; 0x7fa4a641b600
	287	[796]	MOVE     	0 11
	288	[793]	SETTABLE 	13 -131 14	; "setFontHinting" -
	289	[801]	CLOSURE  	14 86	; 0x7fa4a641bb20
	290	[801]	MOVE     	0 11
	291	[798]	SETTABLE 	13 -132 14	; "setFontKerning" -
	292	[813]	CLOSURE  	14 87	; 0x7fa4a641c040
	293	[813]	MOVE     	0 11
	294	[803]	SETTABLE 	13 -133 14	; "setWordSpacing" -
	295	[818]	CLOSURE  	14 88	; 0x7fa4a6409f70
	296	[818]	MOVE     	0 11
	297	[815]	SETTABLE 	13 -134 14	; "setWordExpansion" -
	298	[825]	CLOSURE  	14 89	; 0x7fa4a641c5e0
	299	[825]	MOVE     	0 11
	300	[820]	SETTABLE 	13 -135 14	; "setStyleSheet" -
	301	[831]	CLOSURE  	14 90	; 0x7fa4a6410ce0
	302	[831]	MOVE     	0 11
	303	[827]	SETTABLE 	13 -136 14	; "setEmbeddedStyleSheet" -
	304	[836]	CLOSURE  	14 91	; 0x7fa4a640f570
	305	[836]	MOVE     	0 11
	306	[833]	SETTABLE 	13 -137 14	; "setEmbeddedFonts" -
	307	[844]	CLOSURE  	14 92	; 0x7fa4a6410030
	308	[844]	MOVE     	0 11
	309	[838]	SETTABLE 	13 -138 14	; "setPageMargins" -
	310	[849]	CLOSURE  	14 93	; 0x7fa4a64139e0
	311	[849]	MOVE     	0 11
	312	[846]	SETTABLE 	13 -139 14	; "setBlockRenderingFlags" -
	313	[854]	CLOSURE  	14 94	; 0x7fa4a6418b10
	314	[854]	MOVE     	0 11
	315	[851]	SETTABLE 	13 -140 14	; "setImageScaling" -
	316	[859]	CLOSURE  	14 95	; 0x7fa4a6413290
	317	[859]	MOVE     	0 11
	318	[856]	SETTABLE 	13 -141 14	; "setNightmodeImages" -
	319	[865]	CLOSURE  	14 96	; 0x7fa4a6413310
	320	[865]	MOVE     	0 11
	321	[861]	SETTABLE 	13 -142 14	; "setFloatingPunctuation" -
	322	[870]	CLOSURE  	14 97	; 0x7fa4a6413dd0
	323	[870]	MOVE     	0 11
	324	[867]	SETTABLE 	13 -143 14	; "setTxtPreFormatted" -
	325	[874]	CLOSURE  	14 98	; 0x7fa4a6415290
	326	[872]	SETTABLE 	13 -144 14	; "getVisiblePageCount" -
	327	[879]	CLOSURE  	14 99	; 0x7fa4a6415ce0
	328	[879]	MOVE     	0 11
	329	[876]	SETTABLE 	13 -145 14	; "setVisiblePageCount" -
	330	[884]	CLOSURE  	14 100	; 0x7fa4a64160f0
	331	[884]	MOVE     	0 11
	332	[881]	SETTABLE 	13 -146 14	; "setBatteryState" -
	333	[889]	CLOSURE  	14 101	; 0x7fa4a6416250
	334	[889]	MOVE     	0 11
	335	[886]	SETTABLE 	13 -147 14	; "isXPointerInCurrentPage" -
	336	[894]	CLOSURE  	14 102	; 0x7fa4a6419140
	337	[894]	MOVE     	0 11
	338	[891]	SETTABLE 	13 -148 14	; "setStatusLineProp" -
	339	[899]	CLOSURE  	14 103	; 0x7fa4a6419c50
	340	[899]	MOVE     	0 11
	341	[896]	SETTABLE 	13 -149 14	; "setBackgroundImage" -
	342	[905]	CLOSURE  	14 104	; 0x7fa4a641aa90
	343	[905]	MOVE     	0 11
	344	[901]	SETTABLE 	13 -150 14	; "findText" -
	345	[918]	CLOSURE  	14 105	; 0x7fa4a64125f0
	346	[918]	MOVE     	0 11
	347	[907]	SETTABLE 	13 -151 14	; "enableInternalHistory" -
	348	[922]	CLOSURE  	14 106	; 0x7fa4a64127e0
	349	[920]	SETTABLE 	13 -152 14	; "setCallback" -
	350	[926]	CLOSURE  	14 107	; 0x7fa4a641a150
	351	[924]	SETTABLE 	13 -153 14	; "isBuiltDomStale" -
	352	[930]	CLOSURE  	14 108	; 0x7fa4a641a240
	353	[928]	SETTABLE 	13 -154 14	; "hasCacheFile" -
	354	[934]	CLOSURE  	14 109	; 0x7fa4a6417220
	355	[932]	SETTABLE 	13 -155 14	; "invalidateCacheFile" -
	356	[938]	CLOSURE  	14 110	; 0x7fa4a6417740
	357	[936]	SETTABLE 	13 -156 14	; "getCacheFilePath" -
	358	[942]	CLOSURE  	14 111	; 0x7fa4a641b160
	359	[940]	SETTABLE 	13 -157 14	; "getStatistics" -
	360	[946]	CLOSURE  	14 112	; 0x7fa4a641c920
	361	[944]	SETTABLE 	13 -158 14	; "canHaveAlternativeToc" -
	362	[950]	CLOSURE  	14 113	; 0x7fa4a641cdc0
	363	[948]	SETTABLE 	13 -159 14	; "isTocAlternativeToc" -
	364	[954]	CLOSURE  	14 114	; 0x7fa4a641ce50
	365	[952]	SETTABLE 	13 -160 14	; "buildAlternativeToc" -
	366	[958]	CLOSURE  	14 115	; 0x7fa4a641d2c0
	367	[956]	SETTABLE 	13 -161 14	; "hasPageMap" -
	368	[962]	CLOSURE  	14 116	; 0x7fa4a641d350
	369	[960]	SETTABLE 	13 -162 14	; "getPageMap" -
	370	[966]	CLOSURE  	14 117	; 0x7fa4a641d590
	371	[964]	SETTABLE 	13 -163 14	; "getPageMapSource" -
	372	[970]	CLOSURE  	14 118	; 0x7fa4a641d810
	373	[968]	SETTABLE 	13 -164 14	; "getPageMapCurrentPageLabel" -
	374	[974]	CLOSURE  	14 119	; 0x7fa4a641daf0
	375	[972]	SETTABLE 	13 -165 14	; "getPageMapFirstPageLabel" -
	376	[978]	CLOSURE  	14 120	; 0x7fa4a641dd60
	377	[976]	SETTABLE 	13 -166 14	; "getPageMapLastPageLabel" -
	378	[982]	CLOSURE  	14 121	; 0x7fa4a641e050
	379	[980]	SETTABLE 	13 -167 14	; "getPageMapXPointerPageLabel" -
	380	[986]	CLOSURE  	14 122	; 0x7fa4a641e310
	381	[984]	SETTABLE 	13 -168 14	; "getPageMapVisiblePageLabels" -
	382	[1020]	CLOSURE  	14 123	; 0x7fa4a641e5b0
	383	[988]	SETTABLE 	13 -169 14	; "register" -
	384	[1411]	CLOSURE  	14 124	; 0x7fa4a641ea80
	385	[1411]	MOVE     	0 11
	386	[1411]	MOVE     	0 13
	387	[1025]	SETTABLE 	13 -170 14	; "setupCallCache" -
	388	[1413]	RETURN   	13 2
	389	[1413]	RETURN   	0 1

function <./frontend/document/credocument.lua:63,72> (30 instructions, 120 bytes at 0x7fa4a64070c0)
2 params, 11 slots, 0 upvalues, 9 locals, 10 constants, 0 functions
	1	[64]	GETGLOBAL	2 -1	; io
	2	[64]	GETTABLE 	2 2 -2	; "popen"
	3	[64]	LOADK    	3 -3	; "unzip "
	4	[64]	LOADK    	4 -4	; "-qql \""
	5	[64]	MOVE     	5 1
	6	[64]	LOADK    	6 -5	; "\""
	7	[64]	CONCAT   	3 3 6
	8	[64]	CALL     	2 2 2
	9	[65]	TEST     	2 0 0
	10	[65]	JMP      	19	; to 30
	11	[66]	SELF     	3 2 -6	; "lines"
	12	[66]	CALL     	3 2 4
	13	[66]	JMP      	14	; to 28
	14	[67]	GETGLOBAL	7 -7	; string
	15	[67]	GETTABLE 	7 7 -8	; "match"
	16	[67]	MOVE     	8 6
	17	[67]	LOADK    	9 -9	; "%s+(%d+)%s+.+%.([^.]+)"
	18	[67]	CALL     	7 3 3
	19	[69]	TEST     	7 0 0
	20	[69]	JMP      	7	; to 28
	21	[69]	TEST     	8 0 0
	22	[69]	JMP      	5	; to 28
	23	[69]	GETGLOBAL	9 -7	; string
	24	[69]	GETTABLE 	9 9 -10	; "lower"
	25	[69]	MOVE     	10 8
	26	[69]	TAILCALL 	9 2 0
	27	[69]	RETURN   	9 0
	28	[66]	TFORLOOP 	3 1
	29	[69]	JMP      	-16	; to 14
	30	[72]	RETURN   	0 1

function <./frontend/document/credocument.lua:74,94> (42 instructions, 168 bytes at 0x7fa4a6407ac0)
1 param, 10 slots, 2 upvalues, 3 locals, 20 constants, 0 functions
	1	[76]	GETUPVAL 	1 0	; lfs
	2	[76]	GETTABLE 	1 1 -1	; "attributes"
	3	[76]	LOADK    	2 -2	; "./cr3cache"
	4	[76]	LOADK    	3 -3	; "mode"
	5	[76]	CALL     	1 3 2
	6	[76]	EQ       	0 1 -4	; - "directory"
	7	[76]	JMP      	4	; to 12
	8	[77]	GETGLOBAL	1 -5	; os
	9	[77]	GETTABLE 	1 1 -6	; "execute"
	10	[77]	LOADK    	2 -7	; "rm -r ./cr3cache"
	11	[77]	CALL     	1 2 1
	12	[81]	LOADK    	1 -8	; 64
	13	[89]	LOADK    	2 -9	; 40
	14	[90]	GETGLOBAL	3 -10	; cre
	15	[90]	GETTABLE 	3 3 -11	; "initCache"
	16	[90]	GETUPVAL 	4 1	; DataStorage
	17	[90]	SELF     	4 4 -12	; "getDataDir"
	18	[90]	CALL     	4 2 2
	19	[90]	LOADK    	5 -13	; "/cache/cr3cache"
	20	[90]	CONCAT   	4 4 5
	21	[91]	GETGLOBAL	5 -14	; G_reader_settings
	22	[91]	SELF     	5 5 -15	; "readSetting"
	23	[91]	LOADK    	7 -16	; "cre_disk_cache_max_size"
	24	[91]	CALL     	5 3 2
	25	[91]	TEST     	5 0 1
	26	[91]	JMP      	1	; to 28
	27	[91]	MOVE     	5 1
	28	[91]	MUL      	5 5 -17	; - 1024
	29	[91]	MUL      	5 5 -17	; - 1024
	30	[92]	GETGLOBAL	6 -14	; G_reader_settings
	31	[92]	SELF     	6 6 -18	; "nilOrTrue"
	32	[92]	LOADK    	8 -19	; "cre_compress_cached_data"
	33	[92]	CALL     	6 3 2
	34	[93]	GETGLOBAL	7 -14	; G_reader_settings
	35	[93]	SELF     	7 7 -15	; "readSetting"
	36	[93]	LOADK    	9 -20	; "cre_storage_size_factor"
	37	[93]	CALL     	7 3 2
	38	[93]	TEST     	7 0 1
	39	[93]	JMP      	1	; to 41
	40	[93]	MOVE     	7 2
	41	[90]	CALL     	3 5 1
	42	[94]	RETURN   	0 1

function <./frontend/document/credocument.lua:96,118> (46 instructions, 184 bytes at 0x7fa4a6407fd0)
1 param, 12 slots, 3 upvalues, 9 locals, 15 constants, 0 functions
	1	[97]	GETUPVAL 	1 0	; engine_initialized
	2	[97]	TEST     	1 0 1
	3	[97]	JMP      	42	; to 46
	4	[98]	GETGLOBAL	1 -1	; require
	5	[98]	LOADK    	2 -2	; "libs/libkoreader-cre"
	6	[98]	CALL     	1 2 1
	7	[100]	SELF     	1 0 -3	; "cacheInit"
	8	[100]	CALL     	1 2 1
	9	[103]	GETGLOBAL	1 -4	; cre
	10	[103]	GETTABLE 	1 1 -5	; "initHyphDict"
	11	[103]	LOADK    	2 -6	; "./data/hyph/"
	12	[103]	CALL     	1 2 1
	13	[106]	GETUPVAL 	1 1	; FontList
	14	[106]	SELF     	1 1 -7	; "getFontList"
	15	[106]	CALL     	1 2 2
	16	[107]	GETGLOBAL	2 -8	; ipairs
	17	[107]	MOVE     	3 1
	18	[107]	CALL     	2 2 4
	19	[107]	JMP      	22	; to 42
	20	[108]	SELF     	7 6 -9	; "find"
	21	[108]	LOADK    	9 -10	; "/urw/"
	22	[108]	CALL     	7 3 2
	23	[108]	TEST     	7 0 1
	24	[108]	JMP      	17	; to 42
	25	[108]	SELF     	7 6 -9	; "find"
	26	[108]	LOADK    	9 -11	; "/nerdfonts/symbols.ttf"
	27	[108]	CALL     	7 3 2
	28	[108]	TEST     	7 0 1
	29	[108]	JMP      	12	; to 42
	30	[109]	GETGLOBAL	7 -12	; pcall
	31	[109]	GETGLOBAL	8 -4	; cre
	32	[109]	GETTABLE 	8 8 -13	; "registerFont"
	33	[109]	MOVE     	9 6
	34	[109]	CALL     	7 3 3
	35	[110]	TEST     	7 0 1
	36	[110]	JMP      	5	; to 42
	37	[111]	GETUPVAL 	9 2	; logger
	38	[111]	GETTABLE 	9 9 -14	; "err"
	39	[111]	LOADK    	10 -15	; "failed to register crengine font:"
	40	[111]	MOVE     	11 8
	41	[111]	CALL     	9 3 1
	42	[107]	TFORLOOP 	2 2
	43	[113]	JMP      	-24	; to 20
	44	[116]	LOADBOOL 	2 1 0
	45	[116]	SETUPVAL 	2 0	; engine_initialized
	46	[118]	RETURN   	0 1

function <./frontend/document/credocument.lua:120,164> (63 instructions, 252 bytes at 0x7fa4a64065f0)
1 param, 8 slots, 1 upvalue, 3 locals, 35 constants, 0 functions
	1	[121]	SELF     	1 0 -1	; "updateColorRendering"
	2	[121]	CALL     	1 2 1
	3	[122]	SELF     	1 0 -2	; "engineInit"
	4	[122]	CALL     	1 2 1
	5	[124]	GETGLOBAL	1 -3	; string
	6	[124]	GETTABLE 	1 1 -4	; "lower"
	7	[124]	GETGLOBAL	2 -3	; string
	8	[124]	GETTABLE 	2 2 -5	; "match"
	9	[124]	GETTABLE 	3 0 -6	; "file"
	10	[124]	LOADK    	4 -7	; ".+%.([^.]+)"
	11	[124]	CALL     	2 3 0
	12	[124]	CALL     	1 0 2
	13	[125]	EQ       	0 1 -8	; - "zip"
	14	[125]	JMP      	6	; to 21
	15	[128]	SELF     	2 0 -9	; "zipContentExt"
	16	[128]	GETTABLE 	4 0 -6	; "file"
	17	[128]	CALL     	2 3 2
	18	[128]	TESTSET  	1 2 1
	19	[128]	JMP      	1	; to 21
	20	[128]	LOADK    	1 -10	; "unknown"
	21	[138]	SETTABLE 	0 -11 -12	; "default_css" "./data/epub.css"
	22	[139]	EQ       	1 1 -13	; - "fb2"
	23	[139]	JMP      	2	; to 26
	24	[139]	EQ       	0 1 -14	; - "fb3"
	25	[139]	JMP      	1	; to 27
	26	[140]	SETTABLE 	0 -11 -15	; "default_css" "./data/fb2.css"
	27	[144]	GETGLOBAL	2 -17	; DCREREADER_VIEW_MODE
	28	[144]	EQ       	0 2 -18	; - "scroll"
	29	[144]	JMP      	3	; to 33
	30	[144]	GETTABLE 	2 0 -19	; "SCROLL_VIEW_MODE"
	31	[144]	TEST     	2 0 1
	32	[144]	JMP      	1	; to 34
	33	[144]	GETTABLE 	2 0 -20	; "PAGE_VIEW_MODE"
	34	[144]	SETTABLE 	0 -16 2	; "_view_mode" -
	35	[146]	LOADNIL  	2 2
	36	[147]	GETGLOBAL	3 -22	; pcall
	37	[147]	GETGLOBAL	4 -23	; cre
	38	[147]	GETTABLE 	4 4 -24	; "newDocView"
	39	[147]	GETUPVAL 	5 0	; CanvasContext
	40	[147]	SELF     	5 5 -25	; "getWidth"
	41	[147]	CALL     	5 2 2
	42	[147]	GETUPVAL 	6 0	; CanvasContext
	43	[147]	SELF     	6 6 -26	; "getHeight"
	44	[147]	CALL     	6 2 2
	45	[147]	GETTABLE 	7 0 -16	; "_view_mode"
	46	[147]	CALL     	3 5 3
	47	[147]	SETTABLE 	0 -21 4	; "_document" -
	48	[147]	MOVE     	2 3
	49	[148]	TEST     	2 0 1
	50	[148]	JMP      	3	; to 54
	51	[149]	GETGLOBAL	3 -27	; error
	52	[149]	GETTABLE 	4 0 -21	; "_document"
	53	[149]	CALL     	3 2 1
	54	[157]	SETTABLE 	0 -28 -29	; "is_open" true
	55	[158]	GETTABLE 	3 0 -30	; "info"
	56	[158]	SETTABLE 	3 -31 -32	; "has_pages" false
	57	[159]	SELF     	3 0 -33	; "_readMetadata"
	58	[159]	CALL     	3 2 1
	59	[160]	GETTABLE 	3 0 -30	; "info"
	60	[160]	SETTABLE 	3 -34 -29	; "configurable" true
	61	[163]	SELF     	3 0 -35	; "setupCallCache"
	62	[163]	CALL     	3 2 1
	63	[164]	RETURN   	0 1

function <./frontend/document/credocument.lua:166,168> (5 instructions, 20 bytes at 0x7fa4a6406700)
1 param, 2 slots, 0 upvalues, 1 local, 2 constants, 0 functions
	1	[167]	GETGLOBAL	1 -1	; cre
	2	[167]	GETTABLE 	1 1 -2	; "getDomVersionWithNormalizedXPointers"
	3	[167]	TAILCALL 	1 1 0
	4	[167]	RETURN   	1 0
	5	[168]	RETURN   	0 1

function <./frontend/document/credocument.lua:170,172> (5 instructions, 20 bytes at 0x7fa4a6409520)
1 param, 2 slots, 0 upvalues, 1 local, 2 constants, 0 functions
	1	[171]	GETGLOBAL	1 -1	; cre
	2	[171]	GETTABLE 	1 1 -2	; "getLatestDomVersion"
	3	[171]	TAILCALL 	1 1 0
	4	[171]	RETURN   	1 0
	5	[172]	RETURN   	0 1

function <./frontend/document/credocument.lua:174,176> (3 instructions, 12 bytes at 0x7fa4a6409780)
1 param, 2 slots, 0 upvalues, 1 local, 1 constant, 0 functions
	1	[175]	LOADK    	1 -1	; 20171225
	2	[175]	RETURN   	1 2
	3	[176]	RETURN   	0 1

function <./frontend/document/credocument.lua:178,181> (10 instructions, 40 bytes at 0x7fa4a6409a30)
2 params, 5 slots, 1 upvalue, 2 locals, 4 constants, 0 functions
	1	[179]	GETUPVAL 	2 0	; logger
	2	[179]	GETTABLE 	2 2 -1	; "dbg"
	3	[179]	LOADK    	3 -2	; "CreDocument: requesting DOM version:"
	4	[179]	MOVE     	4 1
	5	[179]	CALL     	2 3 1
	6	[180]	GETGLOBAL	2 -3	; cre
	7	[180]	GETTABLE 	2 2 -4	; "requestDomVersion"
	8	[180]	MOVE     	3 1
	9	[180]	CALL     	2 2 1
	10	[181]	RETURN   	0 1

function <./frontend/document/credocument.lua:183,208> (34 instructions, 136 bytes at 0x7fa4a6409e30)
1 param, 7 slots, 2 upvalues, 1 local, 13 constants, 0 functions
	1	[184]	GETTABLE 	1 0 -1	; "loaded"
	2	[184]	TEST     	1 0 0
	3	[184]	JMP      	1	; to 5
	4	[187]	RETURN   	0 1
	5	[190]	GETTABLE 	1 0 -2	; "_document"
	6	[190]	SELF     	1 1 -3	; "readDefaults"
	7	[190]	CALL     	1 2 1
	8	[191]	GETUPVAL 	1 0	; logger
	9	[191]	GETTABLE 	1 1 -4	; "dbg"
	10	[191]	LOADK    	2 -5	; "CreDocument: applied cr3.ini default settings."
	11	[191]	CALL     	1 2 1
	12	[198]	SELF     	1 0 -6	; "setupFallbackFontFaces"
	13	[198]	CALL     	1 2 1
	14	[201]	GETTABLE 	1 0 -2	; "_document"
	15	[201]	SELF     	1 1 -7	; "adjustFontSizes"
	16	[201]	GETUPVAL 	3 1	; CanvasContext
	17	[201]	SELF     	3 3 -8	; "getDPI"
	18	[201]	CALL     	3 2 0
	19	[201]	CALL     	1 0 1
	20	[204]	GETGLOBAL	1 -9	; G_reader_settings
	21	[204]	SELF     	1 1 -10	; "readSetting"
	22	[204]	LOADK    	3 -11	; "cre_header_status_font_size"
	23	[204]	CALL     	1 3 2
	24	[204]	TEST     	1 0 0
	25	[204]	JMP      	8	; to 34
	26	[205]	GETTABLE 	1 0 -2	; "_document"
	27	[205]	SELF     	1 1 -12	; "setIntProperty"
	28	[205]	LOADK    	3 -13	; "crengine.page.header.font.size"
	29	[206]	GETGLOBAL	4 -9	; G_reader_settings
	30	[206]	SELF     	4 4 -10	; "readSetting"
	31	[206]	LOADK    	6 -11	; "cre_header_status_font_size"
	32	[206]	CALL     	4 3 0
	33	[205]	CALL     	1 0 1
	34	[208]	RETURN   	0 1

function <./frontend/document/credocument.lua:210,227> (36 instructions, 144 bytes at 0x7fa4a640a320)
2 params, 7 slots, 1 upvalue, 3 locals, 12 constants, 0 functions
	1	[211]	GETTABLE 	2 0 -1	; "_loaded"
	2	[211]	TEST     	2 0 1
	3	[211]	JMP      	30	; to 34
	4	[212]	EQ       	1 1 -2	; - false
	5	[212]	JMP      	1	; to 7
	6	[212]	LOADBOOL 	2 0 1
	7	[212]	LOADBOOL 	2 1 0
	8	[213]	GETUPVAL 	3 0	; logger
	9	[213]	GETTABLE 	3 3 -3	; "dbg"
	10	[213]	LOADK    	4 -4	; "CreDocument: loading document..."
	11	[213]	CALL     	3 2 1
	12	[214]	TEST     	2 0 0
	13	[214]	JMP      	3	; to 17
	14	[217]	SELF     	3 0 -5	; "setFontFace"
	15	[217]	GETTABLE 	5 0 -6	; "default_font"
	16	[217]	CALL     	3 3 1
	17	[219]	GETTABLE 	3 0 -7	; "_document"
	18	[219]	SELF     	3 3 -8	; "loadDocument"
	19	[219]	GETTABLE 	5 0 -9	; "file"
	20	[219]	MOVE     	6 2
	21	[219]	CALL     	3 4 2
	22	[219]	TEST     	3 0 0
	23	[219]	JMP      	6	; to 30
	24	[220]	SETTABLE 	0 -1 -10	; "_loaded" true
	25	[221]	GETUPVAL 	3 0	; logger
	26	[221]	GETTABLE 	3 3 -3	; "dbg"
	27	[221]	LOADK    	4 -11	; "CreDocument: loading done."
	28	[221]	CALL     	3 2 1
	29	[221]	JMP      	4	; to 34
	30	[223]	GETUPVAL 	3 0	; logger
	31	[223]	GETTABLE 	3 3 -3	; "dbg"
	32	[223]	LOADK    	4 -12	; "CreDocument: loading failed."
	33	[223]	CALL     	3 2 1
	34	[226]	GETTABLE 	2 0 -1	; "_loaded"
	35	[226]	RETURN   	2 2
	36	[227]	RETURN   	0 1

function <./frontend/document/credocument.lua:229,243> (20 instructions, 80 bytes at 0x7fa4a640aa40)
1 param, 4 slots, 1 upvalue, 1 local, 11 constants, 0 functions
	1	[231]	SELF     	1 0 -1	; "loadDocument"
	2	[231]	CALL     	1 2 1
	3	[238]	GETUPVAL 	1 0	; logger
	4	[238]	GETTABLE 	1 1 -2	; "dbg"
	5	[238]	LOADK    	2 -3	; "CreDocument: rendering document..."
	6	[238]	CALL     	1 2 1
	7	[239]	GETTABLE 	1 0 -4	; "_document"
	8	[239]	SELF     	1 1 -5	; "renderDocument"
	9	[239]	CALL     	1 2 1
	10	[240]	GETTABLE 	1 0 -6	; "info"
	11	[240]	GETTABLE 	2 0 -4	; "_document"
	12	[240]	SELF     	2 2 -8	; "getFullHeight"
	13	[240]	CALL     	2 2 2
	14	[240]	SETTABLE 	1 -7 2	; "doc_height" -
	15	[241]	SETTABLE 	0 -9 -10	; "been_rendered" true
	16	[242]	GETUPVAL 	1 0	; logger
	17	[242]	GETTABLE 	1 1 -2	; "dbg"
	18	[242]	LOADK    	2 -11	; "CreDocument: rendering done."
	19	[242]	CALL     	1 2 1
	20	[243]	RETURN   	0 1

function <./frontend/document/credocument.lua:245,253> (15 instructions, 60 bytes at 0x7fa4a640b3b0)
1 param, 4 slots, 1 upvalue, 1 local, 6 constants, 0 functions
	1	[246]	GETUPVAL 	1 0	; Document
	2	[246]	GETTABLE 	1 1 -1	; "_readMetadata"
	3	[246]	MOVE     	2 0
	4	[246]	CALL     	1 2 1
	5	[247]	GETTABLE 	1 0 -2	; "been_rendered"
	6	[247]	TEST     	1 0 0
	7	[247]	JMP      	5	; to 13
	8	[250]	GETTABLE 	1 0 -3	; "info"
	9	[250]	GETTABLE 	2 0 -5	; "_document"
	10	[250]	SELF     	2 2 -6	; "getFullHeight"
	11	[250]	CALL     	2 2 2
	12	[250]	SETTABLE 	1 -4 2	; "doc_height" -
	13	[252]	LOADBOOL 	1 1 0
	14	[252]	RETURN   	1 2
	15	[253]	RETURN   	0 1

function <./frontend/document/credocument.lua:255,261> (12 instructions, 48 bytes at 0x7fa4a640b5a0)
1 param, 3 slots, 1 upvalue, 1 local, 4 constants, 0 functions
	1	[256]	GETUPVAL 	1 0	; Document
	2	[256]	GETTABLE 	1 1 -1	; "close"
	3	[256]	MOVE     	2 0
	4	[256]	CALL     	1 2 1
	5	[257]	GETTABLE 	1 0 -2	; "buffer"
	6	[257]	TEST     	1 0 0
	7	[257]	JMP      	4	; to 12
	8	[258]	GETTABLE 	1 0 -2	; "buffer"
	9	[258]	SELF     	1 1 -3	; "free"
	10	[258]	CALL     	1 2 1
	11	[259]	SETTABLE 	0 -2 -4	; "buffer" nil
	12	[261]	RETURN   	0 1

function <./frontend/document/credocument.lua:263,271> (12 instructions, 48 bytes at 0x7fa4a640b9a0)
1 param, 3 slots, 1 upvalue, 1 local, 4 constants, 0 functions
	1	[264]	GETUPVAL 	1 0	; Document
	2	[264]	GETTABLE 	1 1 -1	; "updateColorRendering"
	3	[264]	MOVE     	2 0
	4	[264]	CALL     	1 2 1
	5	[267]	GETTABLE 	1 0 -2	; "buffer"
	6	[267]	TEST     	1 0 0
	7	[267]	JMP      	4	; to 12
	8	[268]	GETTABLE 	1 0 -2	; "buffer"
	9	[268]	SELF     	1 1 -3	; "free"
	10	[268]	CALL     	1 2 1
	11	[269]	SETTABLE 	0 -2 -4	; "buffer" nil
	12	[271]	RETURN   	0 1

function <./frontend/document/credocument.lua:273,275> (5 instructions, 20 bytes at 0x7fa4a640bdd0)
1 param, 3 slots, 0 upvalues, 1 local, 2 constants, 0 functions
	1	[274]	GETTABLE 	1 0 -1	; "_document"
	2	[274]	SELF     	1 1 -2	; "getPages"
	3	[274]	TAILCALL 	1 2 0
	4	[274]	RETURN   	1 0
	5	[275]	RETURN   	0 1

function <./frontend/document/credocument.lua:277,288> (24 instructions, 96 bytes at 0x7fa4a640ba70)
1 param, 7 slots, 2 upvalues, 4 locals, 5 constants, 0 functions
	1	[279]	SELF     	1 0 -1	; "loadDocument"
	2	[279]	CALL     	1 2 2
	3	[279]	TEST     	1 0 1
	4	[279]	JMP      	2	; to 7
	5	[280]	LOADNIL  	1 1
	6	[280]	RETURN   	1 2
	7	[282]	GETTABLE 	1 0 -2	; "_document"
	8	[282]	SELF     	1 1 -3	; "getCoverPageImageData"
	9	[282]	CALL     	1 2 3
	10	[283]	TEST     	1 0 0
	11	[283]	JMP      	12	; to 24
	12	[283]	TEST     	2 0 0
	13	[283]	JMP      	10	; to 24
	14	[284]	GETUPVAL 	3 0	; RenderImage
	15	[284]	SELF     	3 3 -4	; "renderImageData"
	16	[284]	MOVE     	5 1
	17	[284]	MOVE     	6 2
	18	[284]	CALL     	3 4 2
	19	[285]	GETUPVAL 	4 1	; C
	20	[285]	GETTABLE 	4 4 -5	; "free"
	21	[285]	MOVE     	5 1
	22	[285]	CALL     	4 2 1
	23	[286]	RETURN   	3 2
	24	[288]	RETURN   	0 1

function <./frontend/document/credocument.lua:290,298> (27 instructions, 108 bytes at 0x7fa4a6409b50)
3 params, 10 slots, 3 upvalues, 6 locals, 8 constants, 0 functions
	1	[291]	GETTABLE 	3 0 -1	; "_document"
	2	[291]	SELF     	3 3 -2	; "getImageDataFromPosition"
	3	[291]	GETTABLE 	5 1 -3	; "x"
	4	[291]	GETTABLE 	6 1 -4	; "y"
	5	[291]	CALL     	3 4 3
	6	[292]	TEST     	3 0 0
	7	[292]	JMP      	19	; to 27
	8	[292]	TEST     	4 0 0
	9	[292]	JMP      	17	; to 27
	10	[293]	GETUPVAL 	5 0	; logger
	11	[293]	GETTABLE 	5 5 -5	; "dbg"
	12	[293]	LOADK    	6 -6	; "CreDocument: got image data from position"
	13	[293]	MOVE     	7 3
	14	[293]	MOVE     	8 4
	15	[293]	CALL     	5 4 1
	16	[294]	GETUPVAL 	5 1	; RenderImage
	17	[294]	SELF     	5 5 -7	; "renderImageData"
	18	[294]	MOVE     	7 3
	19	[294]	MOVE     	8 4
	20	[294]	MOVE     	9 2
	21	[294]	CALL     	5 5 2
	22	[295]	GETUPVAL 	6 2	; C
	23	[295]	GETTABLE 	6 6 -8	; "free"
	24	[295]	MOVE     	7 3
	25	[295]	CALL     	6 2 1
	26	[296]	RETURN   	5 2
	27	[298]	RETURN   	0 1

function <./frontend/document/credocument.lua:300,328> (75 instructions, 300 bytes at 0x7fa4a640a230)
2 params, 10 slots, 2 upvalues, 5 locals, 24 constants, 0 functions
	1	[301]	GETTABLE 	2 0 -1	; "_document"
	2	[301]	SELF     	2 2 -2	; "getWordFromPosition"
	3	[301]	GETTABLE 	4 1 -3	; "x"
	4	[301]	GETTABLE 	5 1 -4	; "y"
	5	[301]	CALL     	2 4 2
	6	[302]	GETUPVAL 	3 0	; logger
	7	[302]	GETTABLE 	3 3 -5	; "dbg"
	8	[302]	LOADK    	4 -6	; "CreDocument: get word box"
	9	[302]	MOVE     	5 2
	10	[302]	CALL     	3 3 1
	11	[303]	GETTABLE 	3 0 -1	; "_document"
	12	[303]	SELF     	3 3 -7	; "getTextFromPositions"
	13	[303]	GETTABLE 	5 1 -3	; "x"
	14	[303]	GETTABLE 	6 1 -4	; "y"
	15	[303]	GETTABLE 	7 1 -3	; "x"
	16	[303]	GETTABLE 	8 1 -4	; "y"
	17	[303]	CALL     	3 6 2
	18	[304]	GETUPVAL 	4 0	; logger
	19	[304]	GETTABLE 	4 4 -5	; "dbg"
	20	[304]	LOADK    	5 -8	; "CreDocument: get text range"
	21	[304]	MOVE     	6 3
	22	[304]	CALL     	4 3 1
	23	[305]	NEWTABLE 	4 0 2
	24	[306]	GETTABLE 	5 3 -10	; "text"
	25	[306]	EQ       	0 5 -11	; - ""
	26	[306]	JMP      	3	; to 30
	27	[306]	GETTABLE 	5 2 -9	; "word"
	28	[306]	TEST     	5 0 1
	29	[306]	JMP      	1	; to 31
	30	[306]	GETTABLE 	5 3 -10	; "text"
	31	[306]	SETTABLE 	4 -9 5	; "word" -
	32	[307]	GETTABLE 	5 0 -1	; "_document"
	33	[307]	SELF     	5 5 -13	; "getCurrentPage"
	34	[307]	CALL     	5 2 2
	35	[307]	SETTABLE 	4 -12 5	; "page" -
	36	[309]	GETTABLE 	5 2 -9	; "word"
	37	[309]	TEST     	5 0 0
	38	[309]	JMP      	18	; to 57
	39	[310]	GETUPVAL 	5 1	; Geom
	40	[310]	SELF     	5 5 -15	; "new"
	41	[310]	NEWTABLE 	7 0 4
	42	[311]	GETTABLE 	8 2 -16	; "x0"
	43	[311]	SETTABLE 	7 -3 8	; "x" -
	44	[311]	GETTABLE 	8 2 -17	; "y0"
	45	[311]	SETTABLE 	7 -4 8	; "y" -
	46	[312]	GETTABLE 	8 2 -19	; "x1"
	47	[312]	GETTABLE 	9 2 -16	; "x0"
	48	[312]	SUB      	8 8 9
	49	[312]	SETTABLE 	7 -18 8	; "w" -
	50	[313]	GETTABLE 	8 2 -21	; "y1"
	51	[313]	GETTABLE 	9 2 -17	; "y0"
	52	[313]	SUB      	8 8 9
	53	[313]	SETTABLE 	7 -20 8	; "h" -
	54	[310]	CALL     	5 3 2
	55	[314]	SETTABLE 	4 -14 5	; "sbox" -
	56	[314]	JMP      	11	; to 68
	57	[317]	GETUPVAL 	5 1	; Geom
	58	[317]	SELF     	5 5 -15	; "new"
	59	[317]	NEWTABLE 	7 0 4
	60	[318]	GETTABLE 	8 1 -3	; "x"
	61	[318]	SETTABLE 	7 -3 8	; "x" -
	62	[318]	GETTABLE 	8 1 -4	; "y"
	63	[318]	SETTABLE 	7 -4 8	; "y" -
	64	[319]	SETTABLE 	7 -18 -22	; "w" 20
	65	[319]	SETTABLE 	7 -20 -22	; "h" 20
	66	[317]	CALL     	5 3 2
	67	[320]	SETTABLE 	4 -14 5	; "sbox" -
	68	[322]	TEST     	3 0 0
	69	[322]	JMP      	4	; to 74
	70	[324]	GETTABLE 	5 3 -23	; "pos0"
	71	[324]	SETTABLE 	4 -23 5	; "pos0" -
	72	[325]	GETTABLE 	5 3 -24	; "pos1"
	73	[325]	SETTABLE 	4 -24 5	; "pos1" -
	74	[327]	RETURN   	4 2
	75	[328]	RETURN   	0 1

function <./frontend/document/credocument.lua:330,342> (23 instructions, 92 bytes at 0x7fa4a640c370)
3 params, 9 slots, 1 upvalue, 4 locals, 9 constants, 0 functions
	1	[331]	GETTABLE 	3 0 -1	; "_document"
	2	[331]	SELF     	3 3 -2	; "getTextFromPositions"
	3	[331]	GETTABLE 	5 1 -3	; "x"
	4	[331]	GETTABLE 	6 1 -4	; "y"
	5	[331]	GETTABLE 	7 2 -3	; "x"
	6	[331]	GETTABLE 	8 2 -4	; "y"
	7	[331]	CALL     	3 6 2
	8	[332]	GETUPVAL 	4 0	; logger
	9	[332]	GETTABLE 	4 4 -5	; "dbg"
	10	[332]	LOADK    	5 -6	; "CreDocument: get text range"
	11	[332]	MOVE     	6 3
	12	[332]	CALL     	4 3 1
	13	[333]	TEST     	3 0 0
	14	[333]	JMP      	8	; to 23
	15	[335]	NEWTABLE 	4 0 3
	16	[336]	GETTABLE 	5 3 -7	; "text"
	17	[336]	SETTABLE 	4 -7 5	; "text" -
	18	[337]	GETTABLE 	5 3 -8	; "pos0"
	19	[337]	SETTABLE 	4 -8 5	; "pos0" -
	20	[338]	GETTABLE 	5 3 -9	; "pos1"
	21	[338]	SETTABLE 	4 -9 5	; "pos1" -
	22	[340]	RETURN   	4 2
	23	[342]	RETURN   	0 1

function <./frontend/document/credocument.lua:344,358> (39 instructions, 156 bytes at 0x7fa4a640c1b0)
4 params, 18 slots, 1 upvalue, 11 locals, 14 constants, 0 functions
	1	[345]	NEWTABLE 	4 0 0
	2	[346]	TEST     	1 0 0
	3	[346]	JMP      	34	; to 38
	4	[346]	TEST     	2 0 0
	5	[346]	JMP      	32	; to 38
	6	[347]	GETTABLE 	5 0 -1	; "_document"
	7	[347]	SELF     	5 5 -2	; "getWordBoxesFromPositions"
	8	[347]	MOVE     	7 1
	9	[347]	MOVE     	8 2
	10	[347]	MOVE     	9 3
	11	[347]	CALL     	5 5 2
	12	[348]	LOADK    	6 -3	; 1
	13	[348]	LEN      	7 5
	14	[348]	LOADK    	8 -3	; 1
	15	[348]	FORPREP  	6 21	; to 37
	16	[349]	GETTABLE 	10 5 9
	17	[350]	GETGLOBAL	11 -4	; table
	18	[350]	GETTABLE 	11 11 -5	; "insert"
	19	[350]	MOVE     	12 4
	20	[350]	GETUPVAL 	13 0	; Geom
	21	[350]	SELF     	13 13 -6	; "new"
	22	[350]	NEWTABLE 	15 0 4
	23	[351]	GETTABLE 	16 10 -8	; "x0"
	24	[351]	SETTABLE 	15 -7 16	; "x" -
	25	[351]	GETTABLE 	16 10 -10	; "y0"
	26	[351]	SETTABLE 	15 -9 16	; "y" -
	27	[352]	GETTABLE 	16 10 -12	; "x1"
	28	[352]	GETTABLE 	17 10 -8	; "x0"
	29	[352]	SUB      	16 16 17
	30	[352]	SETTABLE 	15 -11 16	; "w" -
	31	[353]	GETTABLE 	16 10 -14	; "y1"
	32	[353]	GETTABLE 	17 10 -10	; "y0"
	33	[353]	SUB      	16 16 17
	34	[353]	SETTABLE 	15 -13 16	; "h" -
	35	[350]	CALL     	13 3 0
	36	[350]	CALL     	11 0 1
	37	[348]	FORLOOP  	6 -22	; to 16
	38	[357]	RETURN   	4 2
	39	[358]	RETURN   	0 1

function <./frontend/document/credocument.lua:360,363> (7 instructions, 28 bytes at 0x7fa4a640d030)
3 params, 7 slots, 0 upvalues, 3 locals, 2 constants, 0 functions
	1	[362]	GETTABLE 	3 0 -1	; "_document"
	2	[362]	SELF     	3 3 -2	; "compareXPointers"
	3	[362]	MOVE     	5 1
	4	[362]	MOVE     	6 2
	5	[362]	TAILCALL 	3 4 0
	6	[362]	RETURN   	3 0
	7	[363]	RETURN   	0 1

function <./frontend/document/credocument.lua:365,367> (6 instructions, 24 bytes at 0x7fa4a640d3f0)
2 params, 5 slots, 0 upvalues, 2 locals, 2 constants, 0 functions
	1	[366]	GETTABLE 	2 0 -1	; "_document"
	2	[366]	SELF     	2 2 -2	; "getNextVisibleWordStart"
	3	[366]	MOVE     	4 1
	4	[366]	TAILCALL 	2 3 0
	5	[366]	RETURN   	2 0
	6	[367]	RETURN   	0 1

function <./frontend/document/credocument.lua:369,371> (6 instructions, 24 bytes at 0x7fa4a640d6b0)
2 params, 5 slots, 0 upvalues, 2 locals, 2 constants, 0 functions
	1	[370]	GETTABLE 	2 0 -1	; "_document"
	2	[370]	SELF     	2 2 -2	; "getNextVisibleWordEnd"
	3	[370]	MOVE     	4 1
	4	[370]	TAILCALL 	2 3 0
	5	[370]	RETURN   	2 0
	6	[371]	RETURN   	0 1

function <./frontend/document/credocument.lua:373,375> (6 instructions, 24 bytes at 0x7fa4a64085b0)
2 params, 5 slots, 0 upvalues, 2 locals, 2 constants, 0 functions
	1	[374]	GETTABLE 	2 0 -1	; "_document"
	2	[374]	SELF     	2 2 -2	; "getPrevVisibleWordStart"
	3	[374]	MOVE     	4 1
	4	[374]	TAILCALL 	2 3 0
	5	[374]	RETURN   	2 0
	6	[375]	RETURN   	0 1

function <./frontend/document/credocument.lua:377,379> (6 instructions, 24 bytes at 0x7fa4a64087f0)
2 params, 5 slots, 0 upvalues, 2 locals, 2 constants, 0 functions
	1	[378]	GETTABLE 	2 0 -1	; "_document"
	2	[378]	SELF     	2 2 -2	; "getPrevVisibleWordEnd"
	3	[378]	MOVE     	4 1
	4	[378]	TAILCALL 	2 3 0
	5	[378]	RETURN   	2 0
	6	[379]	RETURN   	0 1

function <./frontend/document/credocument.lua:381,383> (6 instructions, 24 bytes at 0x7fa4a640d8f0)
2 params, 5 slots, 0 upvalues, 2 locals, 2 constants, 0 functions
	1	[382]	GETTABLE 	2 0 -1	; "_document"
	2	[382]	SELF     	2 2 -2	; "getPrevVisibleChar"
	3	[382]	MOVE     	4 1
	4	[382]	TAILCALL 	2 3 0
	5	[382]	RETURN   	2 0
	6	[383]	RETURN   	0 1

function <./frontend/document/credocument.lua:385,387> (6 instructions, 24 bytes at 0x7fa4a640ddd0)
2 params, 5 slots, 0 upvalues, 2 locals, 2 constants, 0 functions
	1	[386]	GETTABLE 	2 0 -1	; "_document"
	2	[386]	SELF     	2 2 -2	; "getNextVisibleChar"
	3	[386]	MOVE     	4 1
	4	[386]	TAILCALL 	2 3 0
	5	[386]	RETURN   	2 0
	6	[387]	RETURN   	0 1

function <./frontend/document/credocument.lua:389,419> (59 instructions, 236 bytes at 0x7fa4a640e080)
6 params, 15 slots, 2 upvalues, 6 locals, 18 constants, 0 functions
	1	[390]	GETTABLE 	6 0 -1	; "buffer"
	2	[390]	TEST     	6 0 0
	3	[390]	JMP      	14	; to 18
	4	[390]	GETTABLE 	6 0 -1	; "buffer"
	5	[390]	GETTABLE 	6 6 -2	; "w"
	6	[390]	GETTABLE 	7 4 -2	; "w"
	7	[390]	EQ       	0 6 7
	8	[390]	JMP      	5	; to 14
	9	[390]	GETTABLE 	6 0 -1	; "buffer"
	10	[390]	GETTABLE 	6 6 -3	; "h"
	11	[390]	GETTABLE 	7 4 -3	; "h"
	12	[390]	EQ       	1 6 7
	13	[390]	JMP      	4	; to 18
	14	[391]	GETTABLE 	6 0 -1	; "buffer"
	15	[391]	SELF     	6 6 -4	; "free"
	16	[391]	CALL     	6 2 1
	17	[392]	SETTABLE 	0 -1 -5	; "buffer" nil
	18	[394]	GETTABLE 	6 0 -1	; "buffer"
	19	[394]	TEST     	6 0 1
	20	[394]	JMP      	14	; to 35
	21	[398]	GETUPVAL 	6 0	; Blitbuffer
	22	[398]	GETTABLE 	6 6 -6	; "new"
	23	[398]	GETTABLE 	7 4 -2	; "w"
	24	[398]	GETTABLE 	8 4 -3	; "h"
	25	[398]	GETTABLE 	9 0 -7	; "render_color"
	26	[398]	TEST     	9 0 0
	27	[398]	JMP      	4	; to 32
	28	[398]	GETUPVAL 	9 0	; Blitbuffer
	29	[398]	GETTABLE 	9 9 -8	; "TYPE_BBRGB32"
	30	[398]	TEST     	9 0 1
	31	[398]	JMP      	1	; to 33
	32	[398]	LOADNIL  	9 9
	33	[398]	CALL     	6 4 2
	34	[398]	SETTABLE 	0 -1 6	; "buffer" -
	35	[413]	GETTABLE 	6 0 -11	; "_document"
	36	[413]	SELF     	6 6 -12	; "drawCurrentPage"
	37	[413]	GETTABLE 	8 0 -1	; "buffer"
	38	[413]	GETTABLE 	9 0 -7	; "render_color"
	39	[413]	GETUPVAL 	10 1	; Screen
	40	[413]	GETTABLE 	10 10 -13	; "night_mode"
	41	[413]	TEST     	10 0 0
	42	[413]	JMP      	1	; to 44
	43	[413]	GETTABLE 	10 0 -14	; "_nightmode_images"
	44	[413]	GETTABLE 	11 0 -15	; "_smooth_scaling"
	45	[413]	GETUPVAL 	12 1	; Screen
	46	[413]	GETTABLE 	12 12 -16	; "sw_dithering"
	47	[413]	CALL     	6 7 3
	48	[413]	SETTABLE 	0 -10 7	; "_drawn_images_surface_ratio" -
	49	[413]	SETTABLE 	0 -9 6	; "_drawn_images_count" -
	50	[417]	SELF     	6 1 -17	; "blitFrom"
	51	[417]	GETTABLE 	8 0 -1	; "buffer"
	52	[417]	MOVE     	9 2
	53	[417]	MOVE     	10 3
	54	[417]	LOADK    	11 -18	; 0
	55	[417]	LOADK    	12 -18	; 0
	56	[417]	GETTABLE 	13 4 -2	; "w"
	57	[417]	GETTABLE 	14 4 -3	; "h"
	58	[417]	CALL     	6 9 1
	59	[419]	RETURN   	0 1

function <./frontend/document/credocument.lua:421,424> (11 instructions, 44 bytes at 0x7fa4a640e4f0)
6 params, 12 slots, 0 upvalues, 6 locals, 3 constants, 0 functions
	1	[422]	GETTABLE 	6 0 -1	; "_document"
	2	[422]	SELF     	6 6 -2	; "gotoPos"
	3	[422]	MOVE     	8 5
	4	[422]	CALL     	6 3 1
	5	[423]	SELF     	6 0 -3	; "drawCurrentView"
	6	[423]	MOVE     	8 1
	7	[423]	MOVE     	9 2
	8	[423]	MOVE     	10 3
	9	[423]	MOVE     	11 4
	10	[423]	CALL     	6 6 1
	11	[424]	RETURN   	0 1

function <./frontend/document/credocument.lua:426,429> (11 instructions, 44 bytes at 0x7fa4a640eb50)
6 params, 12 slots, 0 upvalues, 6 locals, 3 constants, 0 functions
	1	[427]	GETTABLE 	6 0 -1	; "_document"
	2	[427]	SELF     	6 6 -2	; "gotoPage"
	3	[427]	MOVE     	8 5
	4	[427]	CALL     	6 3 1
	5	[428]	SELF     	6 0 -3	; "drawCurrentView"
	6	[428]	MOVE     	8 1
	7	[428]	MOVE     	9 2
	8	[428]	MOVE     	10 3
	9	[428]	MOVE     	11 4
	10	[428]	CALL     	6 6 1
	11	[429]	RETURN   	0 1

function <./frontend/document/credocument.lua:431,432> (1 instruction, 4 bytes at 0x7fa4a640f050)
4 params, 4 slots, 0 upvalues, 4 locals, 0 constants, 0 functions
	1	[432]	RETURN   	0 1

function <./frontend/document/credocument.lua:434,435> (1 instruction, 4 bytes at 0x7fa4a640f630)
8 params, 8 slots, 0 upvalues, 8 locals, 0 constants, 0 functions
	1	[435]	RETURN   	0 1

function <./frontend/document/credocument.lua:437,438> (1 instruction, 4 bytes at 0x7fa4a640f810)
5 params, 5 slots, 0 upvalues, 5 locals, 0 constants, 0 functions
	1	[438]	RETURN   	0 1

function <./frontend/document/credocument.lua:440,442> (5 instructions, 20 bytes at 0x7fa4a640f790)
1 param, 3 slots, 0 upvalues, 1 local, 2 constants, 0 functions
	1	[441]	GETTABLE 	1 0 -1	; "_document"
	2	[441]	SELF     	1 1 -2	; "getPageMargins"
	3	[441]	TAILCALL 	1 2 0
	4	[441]	RETURN   	1 0
	5	[442]	RETURN   	0 1

function <./frontend/document/credocument.lua:444,446> (5 instructions, 20 bytes at 0x7fa4a640b1c0)
1 param, 3 slots, 0 upvalues, 1 local, 2 constants, 0 functions
	1	[445]	GETTABLE 	1 0 -1	; "_document"
	2	[445]	SELF     	1 1 -2	; "getHeaderHeight"
	3	[445]	TAILCALL 	1 2 0
	4	[445]	RETURN   	1 0
	5	[446]	RETURN   	0 1

function <./frontend/document/credocument.lua:448,451> (10 instructions, 40 bytes at 0x7fa4a6410130)
2 params, 5 slots, 1 upvalue, 2 locals, 4 constants, 0 functions
	1	[449]	GETUPVAL 	2 0	; logger
	2	[449]	GETTABLE 	2 2 -1	; "dbg"
	3	[449]	LOADK    	3 -2	; "CreDocument: goto xpointer"
	4	[449]	MOVE     	4 1
	5	[449]	CALL     	2 3 1
	6	[450]	GETTABLE 	2 0 -3	; "_document"
	7	[450]	SELF     	2 2 -4	; "gotoXPointer"
	8	[450]	MOVE     	4 1
	9	[450]	CALL     	2 3 1
	10	[451]	RETURN   	0 1

function <./frontend/document/credocument.lua:453,455> (5 instructions, 20 bytes at 0x7fa4a6410540)
1 param, 3 slots, 0 upvalues, 1 local, 2 constants, 0 functions
	1	[454]	GETTABLE 	1 0 -1	; "_document"
	2	[454]	SELF     	1 1 -2	; "getXPointer"
	3	[454]	TAILCALL 	1 2 0
	4	[454]	RETURN   	1 0
	5	[455]	RETURN   	0 1

function <./frontend/document/credocument.lua:457,459> (6 instructions, 24 bytes at 0x7fa4a6410900)
2 params, 5 slots, 0 upvalues, 2 locals, 2 constants, 0 functions
	1	[458]	GETTABLE 	2 0 -1	; "_document"
	2	[458]	SELF     	2 2 -2	; "isXPointerInDocument"
	3	[458]	MOVE     	4 1
	4	[458]	TAILCALL 	2 3 0
	5	[458]	RETURN   	2 0
	6	[459]	RETURN   	0 1

function <./frontend/document/credocument.lua:461,463> (6 instructions, 24 bytes at 0x7fa4a6410b60)
2 params, 5 slots, 0 upvalues, 2 locals, 2 constants, 0 functions
	1	[462]	GETTABLE 	2 0 -1	; "_document"
	2	[462]	SELF     	2 2 -2	; "getPosFromXPointer"
	3	[462]	MOVE     	4 1
	4	[462]	TAILCALL 	2 3 0
	5	[462]	RETURN   	2 0
	6	[463]	RETURN   	0 1

function <./frontend/document/credocument.lua:465,467> (6 instructions, 24 bytes at 0x7fa4a6410e40)
2 params, 5 slots, 0 upvalues, 2 locals, 2 constants, 0 functions
	1	[466]	GETTABLE 	2 0 -1	; "_document"
	2	[466]	SELF     	2 2 -2	; "getPageFromXPointer"
	3	[466]	MOVE     	4 1
	4	[466]	TAILCALL 	2 3 0
	5	[466]	RETURN   	2 0
	6	[467]	RETURN   	0 1

function <./frontend/document/credocument.lua:469,471> (6 instructions, 24 bytes at 0x7fa4a64110f0)
2 params, 5 slots, 0 upvalues, 2 locals, 2 constants, 0 functions
	1	[470]	GETTABLE 	2 0 -1	; "_document"
	2	[470]	SELF     	2 2 -2	; "getPageOffsetX"
	3	[470]	MOVE     	4 1
	4	[470]	TAILCALL 	2 3 0
	5	[470]	RETURN   	2 0
	6	[471]	RETURN   	0 1

function <./frontend/document/credocument.lua:473,498> (46 instructions, 184 bytes at 0x7fa4a64113a0)
2 params, 13 slots, 0 upvalues, 10 locals, 15 constants, 0 functions
	1	[476]	SELF     	2 0 -1	; "getPageMargins"
	2	[476]	CALL     	2 2 2
	3	[477]	SELF     	3 0 -2	; "getPosFromXPointer"
	4	[477]	MOVE     	5 1
	5	[477]	CALL     	3 3 3
	6	[478]	SELF     	5 0 -3	; "getCurrentPos"
	7	[478]	CALL     	5 2 2
	8	[479]	SUB      	6 3 5
	9	[480]	GETTABLE 	7 2 -4	; "left"
	10	[480]	ADD      	7 4 7
	11	[481]	GETTABLE 	8 0 -5	; "_view_mode"
	12	[481]	GETTABLE 	9 0 -6	; "PAGE_VIEW_MODE"
	13	[481]	EQ       	0 8 9
	14	[481]	JMP      	28	; to 43
	15	[482]	SELF     	8 0 -7	; "getVisiblePageCount"
	16	[482]	CALL     	8 2 2
	17	[482]	LT       	0 -8 8	; 1 -
	18	[482]	JMP      	19	; to 38
	19	[484]	SELF     	8 0 -9	; "getCurrentPage"
	20	[484]	CALL     	8 2 2
	21	[484]	ADD      	8 8 -8	; - 1
	22	[485]	SELF     	9 0 -10	; "getPageCount"
	23	[485]	CALL     	9 2 2
	24	[485]	LE       	0 8 9
	25	[485]	JMP      	12	; to 38
	26	[486]	GETTABLE 	9 0 -11	; "_document"
	27	[486]	SELF     	9 9 -12	; "getPageStartY"
	28	[486]	MOVE     	11 8
	29	[486]	CALL     	9 3 2
	30	[487]	LE       	0 9 3
	31	[487]	JMP      	6	; to 38
	32	[488]	SUB      	6 3 9
	33	[489]	GETTABLE 	10 0 -11	; "_document"
	34	[489]	SELF     	10 10 -13	; "getPageOffsetX"
	35	[489]	MOVE     	12 8
	36	[489]	CALL     	10 3 2
	37	[489]	ADD      	7 7 10
	38	[493]	GETTABLE 	8 2 -14	; "top"
	39	[493]	ADD      	8 6 8
	40	[493]	SELF     	9 0 -15	; "getHeaderHeight"
	41	[493]	CALL     	9 2 2
	42	[493]	ADD      	6 8 9
	43	[497]	MOVE     	8 6
	44	[497]	MOVE     	9 7
	45	[497]	RETURN   	8 3
	46	[498]	RETURN   	0 1

function <./frontend/document/credocument.lua:500,502> (5 instructions, 20 bytes at 0x7fa4a640d830)
1 param, 3 slots, 0 upvalues, 1 local, 2 constants, 0 functions
	1	[501]	GETTABLE 	1 0 -1	; "_document"
	2	[501]	SELF     	1 1 -2	; "getFontFace"
	3	[501]	TAILCALL 	1 2 0
	4	[501]	RETURN   	1 0
	5	[502]	RETURN   	0 1

function <./frontend/document/credocument.lua:504,506> (5 instructions, 20 bytes at 0x7fa4a640d7b0)
1 param, 3 slots, 0 upvalues, 1 local, 2 constants, 0 functions
	1	[505]	GETTABLE 	1 0 -1	; "_document"
	2	[505]	SELF     	1 1 -2	; "getCurrentPos"
	3	[505]	TAILCALL 	1 2 0
	4	[505]	RETURN   	1 0
	5	[506]	RETURN   	0 1

function <./frontend/document/credocument.lua:508,510> (6 instructions, 24 bytes at 0x7fa4a640e140)
2 params, 5 slots, 0 upvalues, 2 locals, 2 constants, 0 functions
	1	[509]	GETTABLE 	2 0 -1	; "_document"
	2	[509]	SELF     	2 2 -2	; "getPageLinks"
	3	[509]	MOVE     	4 1
	4	[509]	TAILCALL 	2 3 0
	5	[509]	RETURN   	2 0
	6	[510]	RETURN   	0 1

function <./frontend/document/credocument.lua:512,514> (7 instructions, 28 bytes at 0x7fa4a640e1c0)
2 params, 6 slots, 0 upvalues, 2 locals, 4 constants, 0 functions
	1	[513]	GETTABLE 	2 0 -1	; "_document"
	2	[513]	SELF     	2 2 -2	; "getLinkFromPosition"
	3	[513]	GETTABLE 	4 1 -3	; "x"
	4	[513]	GETTABLE 	5 1 -4	; "y"
	5	[513]	TAILCALL 	2 4 0
	6	[513]	RETURN   	2 0
	7	[514]	RETURN   	0 1

function <./frontend/document/credocument.lua:516,518> (9 instructions, 36 bytes at 0x7fa4a64109f0)
5 params, 11 slots, 0 upvalues, 5 locals, 2 constants, 0 functions
	1	[517]	GETTABLE 	5 0 -1	; "_document"
	2	[517]	SELF     	5 5 -2	; "isLinkToFootnote"
	3	[517]	MOVE     	7 1
	4	[517]	MOVE     	8 2
	5	[517]	MOVE     	9 3
	6	[517]	MOVE     	10 4
	7	[517]	TAILCALL 	5 6 0
	8	[517]	RETURN   	5 0
	9	[518]	RETURN   	0 1

function <./frontend/document/credocument.lua:520,523> (6 instructions, 24 bytes at 0x7fa4a640d490)
2 params, 5 slots, 0 upvalues, 2 locals, 2 constants, 0 functions
	1	[522]	GETTABLE 	2 0 -1	; "_document"
	2	[522]	SELF     	2 2 -2	; "highlightXPointer"
	3	[522]	MOVE     	4 1
	4	[522]	TAILCALL 	2 3 0
	5	[522]	RETURN   	2 0
	6	[523]	RETURN   	0 1

function <./frontend/document/credocument.lua:525,529> (8 instructions, 32 bytes at 0x7fa4a640d510)
2 params, 5 slots, 0 upvalues, 2 locals, 2 constants, 0 functions
	1	[526]	TEST     	1 0 0
	2	[526]	JMP      	5	; to 8
	3	[527]	GETTABLE 	2 0 -1	; "_document"
	4	[527]	SELF     	2 2 -2	; "getDocumentFileContent"
	5	[527]	MOVE     	4 1
	6	[527]	TAILCALL 	2 3 0
	7	[527]	RETURN   	2 0
	8	[529]	RETURN   	0 1

function <./frontend/document/credocument.lua:531,535> (8 instructions, 32 bytes at 0x7fa4a640f1b0)
2 params, 5 slots, 0 upvalues, 2 locals, 2 constants, 0 functions
	1	[532]	TEST     	1 0 0
	2	[532]	JMP      	5	; to 8
	3	[533]	GETTABLE 	2 0 -1	; "_document"
	4	[533]	SELF     	2 2 -2	; "getTextFromXPointer"
	5	[533]	MOVE     	4 1
	6	[533]	TAILCALL 	2 3 0
	7	[533]	RETURN   	2 0
	8	[535]	RETURN   	0 1

function <./frontend/document/credocument.lua:537,539> (7 instructions, 28 bytes at 0x7fa4a640f2d0)
3 params, 7 slots, 0 upvalues, 3 locals, 2 constants, 0 functions
	1	[538]	GETTABLE 	3 0 -1	; "_document"
	2	[538]	SELF     	3 3 -2	; "getTextFromXPointers"
	3	[538]	MOVE     	5 1
	4	[538]	MOVE     	6 2
	5	[538]	TAILCALL 	3 4 0
	6	[538]	RETURN   	3 0
	7	[539]	RETURN   	0 1

function <./frontend/document/credocument.lua:541,545> (10 instructions, 40 bytes at 0x7fa4a640f970)
4 params, 9 slots, 0 upvalues, 4 locals, 2 constants, 0 functions
	1	[542]	TEST     	1 0 0
	2	[542]	JMP      	7	; to 10
	3	[543]	GETTABLE 	4 0 -1	; "_document"
	4	[543]	SELF     	4 4 -2	; "getHTMLFromXPointer"
	5	[543]	MOVE     	6 1
	6	[543]	MOVE     	7 2
	7	[543]	MOVE     	8 3
	8	[543]	TAILCALL 	4 5 0
	9	[543]	RETURN   	4 0
	10	[545]	RETURN   	0 1

function <./frontend/document/credocument.lua:547,551> (13 instructions, 52 bytes at 0x7fa4a6411860)
5 params, 11 slots, 0 upvalues, 5 locals, 2 constants, 0 functions
	1	[548]	TEST     	1 0 0
	2	[548]	JMP      	10	; to 13
	3	[548]	TEST     	2 0 0
	4	[548]	JMP      	8	; to 13
	5	[549]	GETTABLE 	5 0 -1	; "_document"
	6	[549]	SELF     	5 5 -2	; "getHTMLFromXPointers"
	7	[549]	MOVE     	7 1
	8	[549]	MOVE     	8 2
	9	[549]	MOVE     	9 3
	10	[549]	MOVE     	10 4
	11	[549]	TAILCALL 	5 6 0
	12	[549]	RETURN   	5 0
	13	[551]	RETURN   	0 1

function <./frontend/document/credocument.lua:553,558> (6 instructions, 24 bytes at 0x7fa4a6411d40)
2 params, 5 slots, 0 upvalues, 2 locals, 2 constants, 0 functions
	1	[557]	GETTABLE 	2 0 -1	; "_document"
	2	[557]	SELF     	2 2 -2	; "getNormalizedXPointer"
	3	[557]	MOVE     	4 1
	4	[557]	TAILCALL 	2 3 0
	5	[557]	RETURN   	2 0
	6	[558]	RETURN   	0 1

function <./frontend/document/credocument.lua:560,563> (10 instructions, 40 bytes at 0x7fa4a6412150)
2 params, 5 slots, 1 upvalue, 2 locals, 4 constants, 0 functions
	1	[561]	GETUPVAL 	2 0	; logger
	2	[561]	GETTABLE 	2 2 -1	; "dbg"
	3	[561]	LOADK    	3 -2	; "CreDocument: goto position"
	4	[561]	MOVE     	4 1
	5	[561]	CALL     	2 3 1
	6	[562]	GETTABLE 	2 0 -3	; "_document"
	7	[562]	SELF     	2 2 -4	; "gotoPos"
	8	[562]	MOVE     	4 1
	9	[562]	CALL     	2 3 1
	10	[563]	RETURN   	0 1

function <./frontend/document/credocument.lua:565,568> (10 instructions, 40 bytes at 0x7fa4a64124c0)
2 params, 5 slots, 1 upvalue, 2 locals, 4 constants, 0 functions
	1	[566]	GETUPVAL 	2 0	; logger
	2	[566]	GETTABLE 	2 2 -1	; "dbg"
	3	[566]	LOADK    	3 -2	; "CreDocument: goto page"
	4	[566]	MOVE     	4 1
	5	[566]	CALL     	2 3 1
	6	[567]	GETTABLE 	2 0 -3	; "_document"
	7	[567]	SELF     	2 2 -4	; "gotoPage"
	8	[567]	MOVE     	4 1
	9	[567]	CALL     	2 3 1
	10	[568]	RETURN   	0 1

function <./frontend/document/credocument.lua:570,573> (10 instructions, 40 bytes at 0x7fa4a6412960)
2 params, 5 slots, 1 upvalue, 2 locals, 4 constants, 0 functions
	1	[571]	GETUPVAL 	2 0	; logger
	2	[571]	GETTABLE 	2 2 -1	; "dbg"
	3	[571]	LOADK    	3 -2	; "CreDocument: goto link"
	4	[571]	MOVE     	4 1
	5	[571]	CALL     	2 3 1
	6	[572]	GETTABLE 	2 0 -3	; "_document"
	7	[572]	SELF     	2 2 -4	; "gotoLink"
	8	[572]	MOVE     	4 1
	9	[572]	CALL     	2 3 1
	10	[573]	RETURN   	0 1

function <./frontend/document/credocument.lua:575,578> (8 instructions, 32 bytes at 0x7fa4a6412d40)
1 param, 3 slots, 1 upvalue, 1 local, 4 constants, 0 functions
	1	[576]	GETUPVAL 	1 0	; logger
	2	[576]	GETTABLE 	1 1 -1	; "dbg"
	3	[576]	LOADK    	2 -2	; "CreDocument: go back"
	4	[576]	CALL     	1 2 1
	5	[577]	GETTABLE 	1 0 -3	; "_document"
	6	[577]	SELF     	1 1 -4	; "goBack"
	7	[577]	CALL     	1 2 1
	8	[578]	RETURN   	0 1

function <./frontend/document/credocument.lua:580,583> (8 instructions, 32 bytes at 0x7fa4a6413200)
2 params, 4 slots, 1 upvalue, 2 locals, 4 constants, 0 functions
	1	[581]	GETUPVAL 	2 0	; logger
	2	[581]	GETTABLE 	2 2 -1	; "dbg"
	3	[581]	LOADK    	3 -2	; "CreDocument: go forward"
	4	[581]	CALL     	2 2 1
	5	[582]	GETTABLE 	2 0 -3	; "_document"
	6	[582]	SELF     	2 2 -4	; "goForward"
	7	[582]	CALL     	2 2 1
	8	[583]	RETURN   	0 1

function <./frontend/document/credocument.lua:585,587> (5 instructions, 20 bytes at 0x7fa4a6413480)
1 param, 3 slots, 0 upvalues, 1 local, 2 constants, 0 functions
	1	[586]	GETTABLE 	1 0 -1	; "_document"
	2	[586]	SELF     	1 1 -2	; "getCurrentPage"
	3	[586]	TAILCALL 	1 2 0
	4	[586]	RETURN   	1 0
	5	[587]	RETURN   	0 1

function <./frontend/document/credocument.lua:589,626> (23 instructions, 92 bytes at 0x7fa4a64135c0)
2 params, 6 slots, 1 upvalue, 2 locals, 8 constants, 0 functions
	1	[590]	TEST     	1 0 0
	2	[590]	JMP      	20	; to 23
	3	[591]	GETUPVAL 	2 0	; logger
	4	[591]	GETTABLE 	2 2 -1	; "dbg"
	5	[591]	LOADK    	3 -2	; "CreDocument: set font face"
	6	[591]	MOVE     	4 1
	7	[591]	CALL     	2 3 1
	8	[592]	GETTABLE 	2 0 -3	; "_document"
	9	[592]	SELF     	2 2 -4	; "setStringProperty"
	10	[592]	LOADK    	4 -5	; "font.face.default"
	11	[592]	MOVE     	5 1
	12	[592]	CALL     	2 4 1
	13	[612]	GETTABLE 	2 0 -3	; "_document"
	14	[612]	SELF     	2 2 -6	; "setAsPreferredFontWithBias"
	15	[612]	MOVE     	4 1
	16	[612]	LOADK    	5 -7	; 1
	17	[612]	CALL     	2 4 1
	18	[624]	GETTABLE 	2 0 -3	; "_document"
	19	[624]	SELF     	2 2 -6	; "setAsPreferredFontWithBias"
	20	[624]	MOVE     	4 1
	21	[624]	LOADK    	5 -8	; 1921
	22	[624]	CALL     	2 4 1
	23	[626]	RETURN   	0 1

function <./frontend/document/credocument.lua:628,654> (61 instructions, 244 bytes at 0x7fa4a64140d0)
1 param, 12 slots, 1 upvalue, 14 locals, 20 constants, 0 functions
	1	[629]	NEWTABLE 	1 0 0
	2	[630]	NEWTABLE 	2 0 0
	3	[631]	GETGLOBAL	3 -1	; G_reader_settings
	4	[631]	SELF     	3 3 -2	; "readSetting"
	5	[631]	LOADK    	5 -3	; "fallback_font"
	6	[631]	CALL     	3 3 2
	7	[632]	TEST     	3 0 0
	8	[632]	JMP      	6	; to 15
	9	[633]	GETGLOBAL	4 -4	; table
	10	[633]	GETTABLE 	4 4 -5	; "insert"
	11	[633]	MOVE     	5 1
	12	[633]	MOVE     	6 3
	13	[633]	CALL     	4 3 1
	14	[634]	SETTABLE 	2 3 -6	; - true
	15	[636]	GETGLOBAL	4 -7	; pairs
	16	[636]	GETTABLE 	5 0 -8	; "fallback_fonts"
	17	[636]	CALL     	4 2 4
	18	[636]	JMP      	9	; to 28
	19	[637]	GETTABLE 	9 2 8
	20	[637]	TEST     	9 0 1
	21	[637]	JMP      	6	; to 28
	22	[638]	GETGLOBAL	9 -4	; table
	23	[638]	GETTABLE 	9 9 -5	; "insert"
	24	[638]	MOVE     	10 1
	25	[638]	MOVE     	11 8
	26	[638]	CALL     	9 3 1
	27	[639]	SETTABLE 	2 8 -6	; - true
	28	[636]	TFORLOOP 	4 2
	29	[640]	JMP      	-11	; to 19
	30	[642]	GETGLOBAL	4 -1	; G_reader_settings
	31	[642]	SELF     	4 4 -9	; "isFalse"
	32	[642]	LOADK    	6 -10	; "additional_fallback_fonts"
	33	[642]	CALL     	4 3 2
	34	[642]	TEST     	4 0 0
	35	[642]	JMP      	10	; to 46
	36	[645]	LEN      	4 1
	37	[645]	LOADK    	5 -11	; 2
	38	[645]	LOADK    	6 -12	; -1
	39	[645]	FORPREP  	4 5	; to 45
	40	[646]	GETGLOBAL	8 -4	; table
	41	[646]	GETTABLE 	8 8 -13	; "remove"
	42	[646]	MOVE     	9 1
	43	[646]	MOVE     	10 7
	44	[646]	CALL     	8 3 1
	45	[645]	FORLOOP  	4 -6	; to 40
	46	[651]	GETGLOBAL	4 -4	; table
	47	[651]	GETTABLE 	4 4 -14	; "concat"
	48	[651]	MOVE     	5 1
	49	[651]	LOADK    	6 -15	; "|"
	50	[651]	CALL     	4 3 2
	51	[652]	GETUPVAL 	5 0	; logger
	52	[652]	GETTABLE 	5 5 -16	; "dbg"
	53	[652]	LOADK    	6 -17	; "CreDocument: set fallback font faces:"
	54	[652]	MOVE     	7 4
	55	[652]	CALL     	5 3 1
	56	[653]	GETTABLE 	5 0 -18	; "_document"
	57	[653]	SELF     	5 5 -19	; "setStringProperty"
	58	[653]	LOADK    	7 -20	; "crengine.font.fallback.face"
	59	[653]	MOVE     	8 4
	60	[653]	CALL     	5 4 1
	61	[654]	RETURN   	0 1

function <./frontend/document/credocument.lua:658,663> (13 instructions, 52 bytes at 0x7fa4a6414510)
2 params, 6 slots, 1 upvalue, 2 locals, 5 constants, 0 functions
	1	[659]	TEST     	1 0 0
	2	[659]	JMP      	10	; to 13
	3	[660]	GETUPVAL 	2 0	; logger
	4	[660]	GETTABLE 	2 2 -1	; "dbg"
	5	[660]	LOADK    	3 -2	; "CreDocument: set textlang main lang"
	6	[660]	MOVE     	4 1
	7	[660]	CALL     	2 3 1
	8	[661]	GETTABLE 	2 0 -3	; "_document"
	9	[661]	SELF     	2 2 -4	; "setStringProperty"
	10	[661]	LOADK    	4 -5	; "crengine.textlang.main.lang"
	11	[661]	MOVE     	5 1
	12	[661]	CALL     	2 4 1
	13	[663]	RETURN   	0 1

function <./frontend/document/credocument.lua:665,668> (16 instructions, 64 bytes at 0x7fa4a6414bd0)
2 params, 6 slots, 1 upvalue, 2 locals, 7 constants, 0 functions
	1	[666]	GETUPVAL 	2 0	; logger
	2	[666]	GETTABLE 	2 2 -1	; "dbg"
	3	[666]	LOADK    	3 -2	; "CreDocument: set textlang embedded langs"
	4	[666]	MOVE     	4 1
	5	[666]	CALL     	2 3 1
	6	[667]	GETTABLE 	2 0 -3	; "_document"
	7	[667]	SELF     	2 2 -4	; "setStringProperty"
	8	[667]	LOADK    	4 -5	; "crengine.textlang.embedded.langs.enabled"
	9	[667]	TEST     	1 0 0
	10	[667]	JMP      	3	; to 14
	11	[667]	LOADK    	5 -6	; 1
	12	[667]	TEST     	5 0 1
	13	[667]	JMP      	1	; to 15
	14	[667]	LOADK    	5 -7	; 0
	15	[667]	CALL     	2 4 1
	16	[668]	RETURN   	0 1

function <./frontend/document/credocument.lua:670,673> (16 instructions, 64 bytes at 0x7fa4a64150d0)
2 params, 6 slots, 1 upvalue, 2 locals, 7 constants, 0 functions
	1	[671]	GETUPVAL 	2 0	; logger
	2	[671]	GETTABLE 	2 2 -1	; "dbg"
	3	[671]	LOADK    	3 -2	; "CreDocument: set textlang hyphenation enabled"
	4	[671]	MOVE     	4 1
	5	[671]	CALL     	2 3 1
	6	[672]	GETTABLE 	2 0 -3	; "_document"
	7	[672]	SELF     	2 2 -4	; "setStringProperty"
	8	[672]	LOADK    	4 -5	; "crengine.textlang.hyphenation.enabled"
	9	[672]	TEST     	1 0 0
	10	[672]	JMP      	3	; to 14
	11	[672]	LOADK    	5 -6	; 1
	12	[672]	TEST     	5 0 1
	13	[672]	JMP      	1	; to 15
	14	[672]	LOADK    	5 -7	; 0
	15	[672]	CALL     	2 4 1
	16	[673]	RETURN   	0 1

function <./frontend/document/credocument.lua:675,678> (16 instructions, 64 bytes at 0x7fa4a6415600)
2 params, 6 slots, 1 upvalue, 2 locals, 7 constants, 0 functions
	1	[676]	GETUPVAL 	2 0	; logger
	2	[676]	GETTABLE 	2 2 -1	; "dbg"
	3	[676]	LOADK    	3 -2	; "CreDocument: set textlang hyphenation soft hyphens only"
	4	[676]	MOVE     	4 1
	5	[676]	CALL     	2 3 1
	6	[677]	GETTABLE 	2 0 -3	; "_document"
	7	[677]	SELF     	2 2 -4	; "setStringProperty"
	8	[677]	LOADK    	4 -5	; "crengine.textlang.hyphenation.soft.hyphens.only"
	9	[677]	TEST     	1 0 0
	10	[677]	JMP      	3	; to 14
	11	[677]	LOADK    	5 -6	; 1
	12	[677]	TEST     	5 0 1
	13	[677]	JMP      	1	; to 15
	14	[677]	LOADK    	5 -7	; 0
	15	[677]	CALL     	2 4 1
	16	[678]	RETURN   	0 1

function <./frontend/document/credocument.lua:680,683> (16 instructions, 64 bytes at 0x7fa4a6415a20)
2 params, 6 slots, 1 upvalue, 2 locals, 7 constants, 0 functions
	1	[681]	GETUPVAL 	2 0	; logger
	2	[681]	GETTABLE 	2 2 -1	; "dbg"
	3	[681]	LOADK    	3 -2	; "CreDocument: set textlang hyphenation force algorithmic"
	4	[681]	MOVE     	4 1
	5	[681]	CALL     	2 3 1
	6	[682]	GETTABLE 	2 0 -3	; "_document"
	7	[682]	SELF     	2 2 -4	; "setStringProperty"
	8	[682]	LOADK    	4 -5	; "crengine.textlang.hyphenation.force.algorithmic"
	9	[682]	TEST     	1 0 0
	10	[682]	JMP      	3	; to 14
	11	[682]	LOADK    	5 -6	; 1
	12	[682]	TEST     	5 0 1
	13	[682]	JMP      	1	; to 15
	14	[682]	LOADK    	5 -7	; 0
	15	[682]	CALL     	2 4 1
	16	[683]	RETURN   	0 1

function <./frontend/document/credocument.lua:685,688> (10 instructions, 40 bytes at 0x7fa4a6415f40)
1 param, 5 slots, 0 upvalues, 4 locals, 3 constants, 0 functions
	1	[686]	GETGLOBAL	1 -1	; cre
	2	[686]	GETTABLE 	1 1 -2	; "getTextLangStatus"
	3	[686]	CALL     	1 1 4
	4	[687]	GETTABLE 	4 3 1
	5	[687]	TEST     	4 0 0
	6	[687]	JMP      	2	; to 9
	7	[687]	GETTABLE 	4 3 1
	8	[687]	GETTABLE 	4 4 -3	; "hyph_dict_name"
	9	[687]	RETURN   	4 2
	10	[688]	RETURN   	0 1

function <./frontend/document/credocument.lua:691,696> (13 instructions, 52 bytes at 0x7fa4a64164e0)
2 params, 6 slots, 1 upvalue, 2 locals, 5 constants, 0 functions
	1	[692]	TEST     	1 0 0
	2	[692]	JMP      	10	; to 13
	3	[693]	GETUPVAL 	2 0	; logger
	4	[693]	GETTABLE 	2 2 -1	; "dbg"
	5	[693]	LOADK    	3 -2	; "CreDocument: set hyphenation dictionary"
	6	[693]	MOVE     	4 1
	7	[693]	CALL     	2 3 1
	8	[694]	GETTABLE 	2 0 -3	; "_document"
	9	[694]	SELF     	2 2 -4	; "setStringProperty"
	10	[694]	LOADK    	4 -5	; "crengine.hyphenation.directory"
	11	[694]	MOVE     	5 1
	12	[694]	CALL     	2 4 1
	13	[696]	RETURN   	0 1

function <./frontend/document/credocument.lua:698,702> (15 instructions, 60 bytes at 0x7fa4a6416db0)
2 params, 6 slots, 1 upvalue, 2 locals, 6 constants, 0 functions
	1	[700]	GETUPVAL 	2 0	; logger
	2	[700]	GETTABLE 	2 2 -1	; "dbg"
	3	[700]	LOADK    	3 -2	; "CreDocument: set hyphenation left hyphen min"
	4	[700]	TESTSET  	4 1 1
	5	[700]	JMP      	1	; to 7
	6	[700]	LOADK    	4 -3	; 2
	7	[700]	CALL     	2 3 1
	8	[701]	GETTABLE 	2 0 -4	; "_document"
	9	[701]	SELF     	2 2 -5	; "setIntProperty"
	10	[701]	LOADK    	4 -6	; "crengine.hyphenation.left.hyphen.min"
	11	[701]	TESTSET  	5 1 1
	12	[701]	JMP      	1	; to 14
	13	[701]	LOADK    	5 -3	; 2
	14	[701]	CALL     	2 4 1
	15	[702]	RETURN   	0 1

function <./frontend/document/credocument.lua:704,707> (15 instructions, 60 bytes at 0x7fa4a6416fe0)
2 params, 6 slots, 1 upvalue, 2 locals, 6 constants, 0 functions
	1	[705]	GETUPVAL 	2 0	; logger
	2	[705]	GETTABLE 	2 2 -1	; "dbg"
	3	[705]	LOADK    	3 -2	; "CreDocument: set hyphenation right hyphen min"
	4	[705]	TESTSET  	4 1 1
	5	[705]	JMP      	1	; to 7
	6	[705]	LOADK    	4 -3	; 2
	7	[705]	CALL     	2 3 1
	8	[706]	GETTABLE 	2 0 -4	; "_document"
	9	[706]	SELF     	2 2 -5	; "setIntProperty"
	10	[706]	LOADK    	4 -6	; "crengine.hyphenation.right.hyphen.min"
	11	[706]	TESTSET  	5 1 1
	12	[706]	JMP      	1	; to 14
	13	[706]	LOADK    	5 -3	; 2
	14	[706]	CALL     	2 4 1
	15	[707]	RETURN   	0 1

function <./frontend/document/credocument.lua:709,712> (21 instructions, 84 bytes at 0x7fa4a6417540)
2 params, 6 slots, 1 upvalue, 2 locals, 7 constants, 0 functions
	1	[710]	GETUPVAL 	2 0	; logger
	2	[710]	GETTABLE 	2 2 -1	; "dbg"
	3	[710]	LOADK    	3 -2	; "CreDocument: set hyphenation trust soft hyphens"
	4	[710]	TEST     	1 0 0
	5	[710]	JMP      	3	; to 9
	6	[710]	LOADK    	4 -3	; 1
	7	[710]	TEST     	4 0 1
	8	[710]	JMP      	1	; to 10
	9	[710]	LOADK    	4 -4	; 0
	10	[710]	CALL     	2 3 1
	11	[711]	GETTABLE 	2 0 -5	; "_document"
	12	[711]	SELF     	2 2 -6	; "setIntProperty"
	13	[711]	LOADK    	4 -7	; "crengine.hyphenation.trust.soft.hyphens"
	14	[711]	TEST     	1 0 0
	15	[711]	JMP      	3	; to 19
	16	[711]	LOADK    	5 -3	; 1
	17	[711]	TEST     	5 0 1
	18	[711]	JMP      	1	; to 20
	19	[711]	LOADK    	5 -4	; 0
	20	[711]	CALL     	2 4 1
	21	[712]	RETURN   	0 1

function <./frontend/document/credocument.lua:714,721> (15 instructions, 60 bytes at 0x7fa4a6417ba0)
2 params, 6 slots, 1 upvalue, 2 locals, 6 constants, 0 functions
	1	[719]	GETUPVAL 	2 0	; logger
	2	[719]	GETTABLE 	2 2 -1	; "dbg"
	3	[719]	LOADK    	3 -2	; "CreDocument: set render dpi"
	4	[719]	TESTSET  	4 1 1
	5	[719]	JMP      	1	; to 7
	6	[719]	LOADK    	4 -3	; 96
	7	[719]	CALL     	2 3 1
	8	[720]	GETTABLE 	2 0 -4	; "_document"
	9	[720]	SELF     	2 2 -5	; "setIntProperty"
	10	[720]	LOADK    	4 -6	; "crengine.render.dpi"
	11	[720]	TESTSET  	5 1 1
	12	[720]	JMP      	1	; to 14
	13	[720]	LOADK    	5 -3	; 96
	14	[720]	CALL     	2 4 1
	15	[721]	RETURN   	0 1

function <./frontend/document/credocument.lua:723,727> (11 instructions, 44 bytes at 0x7fa4a6418080)
2 params, 6 slots, 1 upvalue, 2 locals, 5 constants, 0 functions
	1	[725]	GETUPVAL 	2 0	; logger
	2	[725]	GETTABLE 	2 2 -1	; "dbg"
	3	[725]	LOADK    	3 -2	; "CreDocument: set render scale font with dpi"
	4	[725]	MOVE     	4 1
	5	[725]	CALL     	2 3 1
	6	[726]	GETTABLE 	2 0 -3	; "_document"
	7	[726]	SELF     	2 2 -4	; "setIntProperty"
	8	[726]	LOADK    	4 -5	; "crengine.render.scale.font.with.dpi"
	9	[726]	MOVE     	5 1
	10	[726]	CALL     	2 4 1
	11	[727]	RETURN   	0 1

function <./frontend/document/credocument.lua:729,732> (8 instructions, 32 bytes at 0x7fa4a6418530)
1 param, 3 slots, 1 upvalue, 1 local, 4 constants, 0 functions
	1	[730]	GETUPVAL 	1 0	; logger
	2	[730]	GETTABLE 	1 1 -1	; "dbg"
	3	[730]	LOADK    	2 -2	; "clear selection"
	4	[730]	CALL     	1 2 1
	5	[731]	GETTABLE 	1 0 -3	; "_document"
	6	[731]	SELF     	1 1 -4	; "clearSelection"
	7	[731]	CALL     	1 2 1
	8	[732]	RETURN   	0 1

function <./frontend/document/credocument.lua:734,736> (5 instructions, 20 bytes at 0x7fa4a6418970)
1 param, 3 slots, 0 upvalues, 1 local, 2 constants, 0 functions
	1	[735]	GETTABLE 	1 0 -1	; "_document"
	2	[735]	SELF     	1 1 -2	; "getFontSize"
	3	[735]	TAILCALL 	1 2 0
	4	[735]	RETURN   	1 0
	5	[736]	RETURN   	0 1

function <./frontend/document/credocument.lua:738,743> (12 instructions, 48 bytes at 0x7fa4a6418bf0)
2 params, 5 slots, 1 upvalue, 2 locals, 4 constants, 0 functions
	1	[739]	TEST     	1 0 0
	2	[739]	JMP      	9	; to 12
	3	[740]	GETUPVAL 	2 0	; logger
	4	[740]	GETTABLE 	2 2 -1	; "dbg"
	5	[740]	LOADK    	3 -2	; "CreDocument: set font size"
	6	[740]	MOVE     	4 1
	7	[740]	CALL     	2 3 1
	8	[741]	GETTABLE 	2 0 -3	; "_document"
	9	[741]	SELF     	2 2 -4	; "setFontSize"
	10	[741]	MOVE     	4 1
	11	[741]	CALL     	2 3 1
	12	[743]	RETURN   	0 1

function <./frontend/document/credocument.lua:745,755> (19 instructions, 76 bytes at 0x7fa4a6418fa0)
2 params, 5 slots, 1 upvalue, 2 locals, 8 constants, 0 functions
	1	[746]	TEST     	1 0 0
	2	[746]	JMP      	16	; to 19
	3	[747]	GETUPVAL 	2 0	; logger
	4	[747]	GETTABLE 	2 2 -1	; "dbg"
	5	[747]	LOADK    	3 -2	; "CreDocument: set view mode"
	6	[747]	MOVE     	4 1
	7	[747]	CALL     	2 3 1
	8	[748]	EQ       	0 1 -3	; - "scroll"
	9	[748]	JMP      	3	; to 13
	10	[749]	GETTABLE 	2 0 -5	; "SCROLL_VIEW_MODE"
	11	[749]	SETTABLE 	0 -4 2	; "_view_mode" -
	12	[749]	JMP      	2	; to 15
	13	[751]	GETTABLE 	2 0 -6	; "PAGE_VIEW_MODE"
	14	[751]	SETTABLE 	0 -4 2	; "_view_mode" -
	15	[753]	GETTABLE 	2 0 -7	; "_document"
	16	[753]	SELF     	2 2 -8	; "setViewMode"
	17	[753]	GETTABLE 	4 0 -4	; "_view_mode"
	18	[753]	CALL     	2 3 1
	19	[755]	RETURN   	0 1

function <./frontend/document/credocument.lua:757,760> (11 instructions, 44 bytes at 0x7fa4a64193c0)
2 params, 6 slots, 1 upvalue, 2 locals, 6 constants, 0 functions
	1	[758]	GETUPVAL 	2 0	; logger
	2	[758]	GETTABLE 	2 2 -1	; "dbg"
	3	[758]	LOADK    	3 -2	; "CreDocument: set view dimen"
	4	[758]	MOVE     	4 1
	5	[758]	CALL     	2 3 1
	6	[759]	GETTABLE 	2 0 -3	; "_document"
	7	[759]	SELF     	2 2 -4	; "setViewDimen"
	8	[759]	GETTABLE 	4 1 -5	; "w"
	9	[759]	GETTABLE 	5 1 -6	; "h"
	10	[759]	CALL     	2 4 1
	11	[760]	RETURN   	0 1

function <./frontend/document/credocument.lua:762,767> (12 instructions, 48 bytes at 0x7fa4a6419aa0)
2 params, 5 slots, 1 upvalue, 2 locals, 4 constants, 0 functions
	1	[763]	TEST     	1 0 0
	2	[763]	JMP      	9	; to 12
	3	[764]	GETUPVAL 	2 0	; logger
	4	[764]	GETTABLE 	2 2 -1	; "dbg"
	5	[764]	LOADK    	3 -2	; "CreDocument: set header font"
	6	[764]	MOVE     	4 1
	7	[764]	CALL     	2 3 1
	8	[765]	GETTABLE 	2 0 -3	; "_document"
	9	[765]	SELF     	2 2 -4	; "setHeaderFont"
	10	[765]	MOVE     	4 1
	11	[765]	CALL     	2 3 1
	12	[767]	RETURN   	0 1

function <./frontend/document/credocument.lua:769,772> (10 instructions, 40 bytes at 0x7fa4a6419f50)
2 params, 5 slots, 1 upvalue, 2 locals, 4 constants, 0 functions
	1	[770]	GETUPVAL 	2 0	; logger
	2	[770]	GETTABLE 	2 2 -1	; "dbg"
	3	[770]	LOADK    	3 -2	; "CreDocument: zoom font"
	4	[770]	MOVE     	4 1
	5	[770]	CALL     	2 3 1
	6	[771]	GETTABLE 	2 0 -3	; "_document"
	7	[771]	SELF     	2 2 -4	; "zoomFont"
	8	[771]	MOVE     	4 1
	9	[771]	CALL     	2 3 1
	10	[772]	RETURN   	0 1

function <./frontend/document/credocument.lua:774,777> (10 instructions, 40 bytes at 0x7fa4a641a430)
2 params, 5 slots, 1 upvalue, 2 locals, 4 constants, 0 functions
	1	[775]	GETUPVAL 	2 0	; logger
	2	[775]	GETTABLE 	2 2 -1	; "dbg"
	3	[775]	LOADK    	3 -2	; "CreDocument: set interline space"
	4	[775]	MOVE     	4 1
	5	[775]	CALL     	2 3 1
	6	[776]	GETTABLE 	2 0 -3	; "_document"
	7	[776]	SELF     	2 2 -4	; "setDefaultInterlineSpace"
	8	[776]	MOVE     	4 1
	9	[776]	CALL     	2 3 1
	10	[777]	RETURN   	0 1

function <./frontend/document/credocument.lua:779,782> (11 instructions, 44 bytes at 0x7fa4a641a950)
2 params, 6 slots, 1 upvalue, 2 locals, 5 constants, 0 functions
	1	[780]	GETUPVAL 	2 0	; logger
	2	[780]	GETTABLE 	2 2 -1	; "dbg"
	3	[780]	LOADK    	3 -2	; "CreDocument: toggle font bolder"
	4	[780]	MOVE     	4 1
	5	[780]	CALL     	2 3 1
	6	[781]	GETTABLE 	2 0 -3	; "_document"
	7	[781]	SELF     	2 2 -4	; "setIntProperty"
	8	[781]	LOADK    	4 -5	; "font.face.weight.embolden"
	9	[781]	MOVE     	5 1
	10	[781]	CALL     	2 4 1
	11	[782]	RETURN   	0 1

function <./frontend/document/credocument.lua:784,786> (5 instructions, 20 bytes at 0x7fa4a641ae70)
1 param, 2 slots, 0 upvalues, 1 local, 2 constants, 0 functions
	1	[785]	GETGLOBAL	1 -1	; cre
	2	[785]	GETTABLE 	1 1 -2	; "getGammaLevel"
	3	[785]	TAILCALL 	1 1 0
	4	[785]	RETURN   	1 0
	5	[786]	RETURN   	0 1

function <./frontend/document/credocument.lua:788,791> (10 instructions, 40 bytes at 0x7fa4a641b230)
2 params, 5 slots, 1 upvalue, 2 locals, 4 constants, 0 functions
	1	[789]	GETUPVAL 	2 0	; logger
	2	[789]	GETTABLE 	2 2 -1	; "dbg"
	3	[789]	LOADK    	3 -2	; "CreDocument: set gamma index"
	4	[789]	MOVE     	4 1
	5	[789]	CALL     	2 3 1
	6	[790]	GETGLOBAL	2 -3	; cre
	7	[790]	GETTABLE 	2 2 -4	; "setGammaIndex"
	8	[790]	MOVE     	3 1
	9	[790]	CALL     	2 2 1
	10	[791]	RETURN   	0 1

function <./frontend/document/credocument.lua:793,796> (11 instructions, 44 bytes at 0x7fa4a641b600)
2 params, 6 slots, 1 upvalue, 2 locals, 5 constants, 0 functions
	1	[794]	GETUPVAL 	2 0	; logger
	2	[794]	GETTABLE 	2 2 -1	; "dbg"
	3	[794]	LOADK    	3 -2	; "CreDocument: set font hinting mode"
	4	[794]	MOVE     	4 1
	5	[794]	CALL     	2 3 1
	6	[795]	GETTABLE 	2 0 -3	; "_document"
	7	[795]	SELF     	2 2 -4	; "setIntProperty"
	8	[795]	LOADK    	4 -5	; "font.hinting.mode"
	9	[795]	MOVE     	5 1
	10	[795]	CALL     	2 4 1
	11	[796]	RETURN   	0 1

function <./frontend/document/credocument.lua:798,801> (11 instructions, 44 bytes at 0x7fa4a641bb20)
2 params, 6 slots, 1 upvalue, 2 locals, 5 constants, 0 functions
	1	[799]	GETUPVAL 	2 0	; logger
	2	[799]	GETTABLE 	2 2 -1	; "dbg"
	3	[799]	LOADK    	3 -2	; "CreDocument: set font kerning mode"
	4	[799]	MOVE     	4 1
	5	[799]	CALL     	2 3 1
	6	[800]	GETTABLE 	2 0 -3	; "_document"
	7	[800]	SELF     	2 2 -4	; "setIntProperty"
	8	[800]	LOADK    	4 -5	; "font.kerning.mode"
	9	[800]	MOVE     	5 1
	10	[800]	CALL     	2 4 1
	11	[801]	RETURN   	0 1

function <./frontend/document/credocument.lua:803,813> (21 instructions, 84 bytes at 0x7fa4a641c040)
2 params, 6 slots, 1 upvalue, 2 locals, 9 constants, 0 functions
	1	[809]	GETUPVAL 	2 0	; logger
	2	[809]	GETTABLE 	2 2 -1	; "dbg"
	3	[809]	LOADK    	3 -2	; "CreDocument: set space width scale"
	4	[809]	GETTABLE 	4 1 -3	; 1
	5	[809]	CALL     	2 3 1
	6	[810]	GETTABLE 	2 0 -4	; "_document"
	7	[810]	SELF     	2 2 -5	; "setIntProperty"
	8	[810]	LOADK    	4 -6	; "crengine.style.space.width.scale.percent"
	9	[810]	GETTABLE 	5 1 -3	; 1
	10	[810]	CALL     	2 4 1
	11	[811]	GETUPVAL 	2 0	; logger
	12	[811]	GETTABLE 	2 2 -1	; "dbg"
	13	[811]	LOADK    	3 -7	; "CreDocument: set space condensing"
	14	[811]	GETTABLE 	4 1 -8	; 2
	15	[811]	CALL     	2 3 1
	16	[812]	GETTABLE 	2 0 -4	; "_document"
	17	[812]	SELF     	2 2 -5	; "setIntProperty"
	18	[812]	LOADK    	4 -9	; "crengine.style.space.condensing.percent"
	19	[812]	GETTABLE 	5 1 -8	; 2
	20	[812]	CALL     	2 4 1
	21	[813]	RETURN   	0 1

function <./frontend/document/credocument.lua:815,818> (13 instructions, 52 bytes at 0x7fa4a6409f70)
2 params, 6 slots, 1 upvalue, 2 locals, 6 constants, 0 functions
	1	[816]	GETUPVAL 	2 0	; logger
	2	[816]	GETTABLE 	2 2 -1	; "dbg"
	3	[816]	LOADK    	3 -2	; "CreDocument: set word expansion"
	4	[816]	MOVE     	4 1
	5	[816]	CALL     	2 3 1
	6	[817]	GETTABLE 	2 0 -3	; "_document"
	7	[817]	SELF     	2 2 -4	; "setIntProperty"
	8	[817]	LOADK    	4 -5	; "crengine.style.max.added.letter.spacing.percent"
	9	[817]	TESTSET  	5 1 1
	10	[817]	JMP      	1	; to 12
	11	[817]	LOADK    	5 -6	; 0
	12	[817]	CALL     	2 4 1
	13	[818]	RETURN   	0 1

function <./frontend/document/credocument.lua:820,825> (24 instructions, 96 bytes at 0x7fa4a641c5e0)
3 params, 9 slots, 1 upvalue, 3 locals, 8 constants, 0 functions
	1	[821]	GETUPVAL 	3 0	; logger
	2	[821]	GETTABLE 	3 3 -1	; "dbg"
	3	[821]	LOADK    	4 -2	; "CreDocument: set style sheet:"
	4	[822]	TEST     	1 0 0
	5	[822]	JMP      	2	; to 8
	6	[822]	TESTSET  	5 1 1
	7	[822]	JMP      	1	; to 9
	8	[822]	LOADK    	5 -3	; "no file"
	9	[823]	TEST     	2 0 0
	10	[823]	JMP      	6	; to 17
	11	[823]	LOADK    	6 -4	; "and appended content ("
	12	[823]	LEN      	7 2
	13	[823]	LOADK    	8 -5	; " bytes)"
	14	[823]	CONCAT   	6 6 8
	15	[823]	TEST     	6 0 1
	16	[823]	JMP      	1	; to 18
	17	[823]	LOADK    	6 -6	; "(no appended content)"
	18	[821]	CALL     	3 4 1
	19	[824]	GETTABLE 	3 0 -7	; "_document"
	20	[824]	SELF     	3 3 -8	; "setStyleSheet"
	21	[824]	MOVE     	5 1
	22	[824]	MOVE     	6 2
	23	[824]	CALL     	3 4 1
	24	[825]	RETURN   	0 1

function <./frontend/document/credocument.lua:827,831> (11 instructions, 44 bytes at 0x7fa4a6410ce0)
2 params, 6 slots, 1 upvalue, 2 locals, 5 constants, 0 functions
	1	[829]	GETUPVAL 	2 0	; logger
	2	[829]	GETTABLE 	2 2 -1	; "dbg"
	3	[829]	LOADK    	3 -2	; "CreDocument: set embedded style sheet"
	4	[829]	MOVE     	4 1
	5	[829]	CALL     	2 3 1
	6	[830]	GETTABLE 	2 0 -3	; "_document"
	7	[830]	SELF     	2 2 -4	; "setIntProperty"
	8	[830]	LOADK    	4 -5	; "crengine.doc.embedded.styles.enabled"
	9	[830]	MOVE     	5 1
	10	[830]	CALL     	2 4 1
	11	[831]	RETURN   	0 1

function <./frontend/document/credocument.lua:833,836> (11 instructions, 44 bytes at 0x7fa4a640f570)
2 params, 6 slots, 1 upvalue, 2 locals, 5 constants, 0 functions
	1	[834]	GETUPVAL 	2 0	; logger
	2	[834]	GETTABLE 	2 2 -1	; "dbg"
	3	[834]	LOADK    	3 -2	; "CreDocument: set embedded fonts"
	4	[834]	MOVE     	4 1
	5	[834]	CALL     	2 3 1
	6	[835]	GETTABLE 	2 0 -3	; "_document"
	7	[835]	SELF     	2 2 -4	; "setIntProperty"
	8	[835]	LOADK    	4 -5	; "crengine.doc.embedded.fonts.enabled"
	9	[835]	MOVE     	5 1
	10	[835]	CALL     	2 4 1
	11	[836]	RETURN   	0 1

function <./frontend/document/credocument.lua:838,844> (29 instructions, 116 bytes at 0x7fa4a6410030)
5 params, 11 slots, 1 upvalue, 5 locals, 8 constants, 0 functions
	1	[839]	GETUPVAL 	5 0	; logger
	2	[839]	GETTABLE 	5 5 -1	; "dbg"
	3	[839]	LOADK    	6 -2	; "CreDocument: set page margins"
	4	[839]	MOVE     	7 1
	5	[839]	MOVE     	8 2
	6	[839]	MOVE     	9 3
	7	[839]	MOVE     	10 4
	8	[839]	CALL     	5 6 1
	9	[840]	GETTABLE 	5 0 -3	; "_document"
	10	[840]	SELF     	5 5 -4	; "setIntProperty"
	11	[840]	LOADK    	7 -5	; "crengine.page.margin.left"
	12	[840]	MOVE     	8 1
	13	[840]	CALL     	5 4 1
	14	[841]	GETTABLE 	5 0 -3	; "_document"
	15	[841]	SELF     	5 5 -4	; "setIntProperty"
	16	[841]	LOADK    	7 -6	; "crengine.page.margin.top"
	17	[841]	MOVE     	8 2
	18	[841]	CALL     	5 4 1
	19	[842]	GETTABLE 	5 0 -3	; "_document"
	20	[842]	SELF     	5 5 -4	; "setIntProperty"
	21	[842]	LOADK    	7 -7	; "crengine.page.margin.right"
	22	[842]	MOVE     	8 3
	23	[842]	CALL     	5 4 1
	24	[843]	GETTABLE 	5 0 -3	; "_document"
	25	[843]	SELF     	5 5 -4	; "setIntProperty"
	26	[843]	LOADK    	7 -8	; "crengine.page.margin.bottom"
	27	[843]	MOVE     	8 4
	28	[843]	CALL     	5 4 1
	29	[844]	RETURN   	0 1

function <./frontend/document/credocument.lua:846,849> (15 instructions, 60 bytes at 0x7fa4a64139e0)
2 params, 7 slots, 1 upvalue, 2 locals, 8 constants, 0 functions
	1	[847]	GETUPVAL 	2 0	; logger
	2	[847]	GETTABLE 	2 2 -1	; "dbg"
	3	[847]	LOADK    	3 -2	; "CreDocument: set block rendering flags"
	4	[847]	GETGLOBAL	4 -3	; string
	5	[847]	GETTABLE 	4 4 -4	; "format"
	6	[847]	LOADK    	5 -5	; "0x%x"
	7	[847]	MOVE     	6 1
	8	[847]	CALL     	4 3 0
	9	[847]	CALL     	2 0 1
	10	[848]	GETTABLE 	2 0 -6	; "_document"
	11	[848]	SELF     	2 2 -7	; "setIntProperty"
	12	[848]	LOADK    	4 -8	; "crengine.render.block.rendering.flags"
	13	[848]	MOVE     	5 1
	14	[848]	CALL     	2 4 1
	15	[849]	RETURN   	0 1

function <./frontend/document/credocument.lua:851,854> (7 instructions, 28 bytes at 0x7fa4a6418b10)
2 params, 5 slots, 1 upvalue, 2 locals, 3 constants, 0 functions
	1	[852]	GETUPVAL 	2 0	; logger
	2	[852]	GETTABLE 	2 2 -1	; "dbg"
	3	[852]	LOADK    	3 -2	; "CreDocument: set smooth scaling"
	4	[852]	MOVE     	4 1
	5	[852]	CALL     	2 3 1
	6	[853]	SETTABLE 	0 -3 1	; "_smooth_scaling" -
	7	[854]	RETURN   	0 1

function <./frontend/document/credocument.lua:856,859> (7 instructions, 28 bytes at 0x7fa4a6413290)
2 params, 5 slots, 1 upvalue, 2 locals, 3 constants, 0 functions
	1	[857]	GETUPVAL 	2 0	; logger
	2	[857]	GETTABLE 	2 2 -1	; "dbg"
	3	[857]	LOADK    	3 -2	; "CreDocument: set nightmode images"
	4	[857]	MOVE     	4 1
	5	[857]	CALL     	2 3 1
	6	[858]	SETTABLE 	0 -3 1	; "_nightmode_images" -
	7	[859]	RETURN   	0 1

function <./frontend/document/credocument.lua:861,865> (11 instructions, 44 bytes at 0x7fa4a6413310)
2 params, 6 slots, 1 upvalue, 2 locals, 5 constants, 0 functions
	1	[863]	GETUPVAL 	2 0	; logger
	2	[863]	GETTABLE 	2 2 -1	; "dbg"
	3	[863]	LOADK    	3 -2	; "CreDocument: set floating punctuation"
	4	[863]	MOVE     	4 1
	5	[863]	CALL     	2 3 1
	6	[864]	GETTABLE 	2 0 -3	; "_document"
	7	[864]	SELF     	2 2 -4	; "setIntProperty"
	8	[864]	LOADK    	4 -5	; "crengine.style.floating.punctuation.enabled"
	9	[864]	MOVE     	5 1
	10	[864]	CALL     	2 4 1
	11	[865]	RETURN   	0 1

function <./frontend/document/credocument.lua:867,870> (11 instructions, 44 bytes at 0x7fa4a6413dd0)
2 params, 6 slots, 1 upvalue, 2 locals, 5 constants, 0 functions
	1	[868]	GETUPVAL 	2 0	; logger
	2	[868]	GETTABLE 	2 2 -1	; "dbg"
	3	[868]	LOADK    	3 -2	; "CreDocument: set txt preformatted"
	4	[868]	MOVE     	4 1
	5	[868]	CALL     	2 3 1
	6	[869]	GETTABLE 	2 0 -3	; "_document"
	7	[869]	SELF     	2 2 -4	; "setIntProperty"
	8	[869]	LOADK    	4 -5	; "crengine.file.txt.preformatted"
	9	[869]	MOVE     	5 1
	10	[869]	CALL     	2 4 1
	11	[870]	RETURN   	0 1

function <./frontend/document/credocument.lua:872,874> (5 instructions, 20 bytes at 0x7fa4a6415290)
1 param, 3 slots, 0 upvalues, 1 local, 2 constants, 0 functions
	1	[873]	GETTABLE 	1 0 -1	; "_document"
	2	[873]	SELF     	1 1 -2	; "getVisiblePageCount"
	3	[873]	TAILCALL 	1 2 0
	4	[873]	RETURN   	1 0
	5	[874]	RETURN   	0 1

function <./frontend/document/credocument.lua:876,879> (10 instructions, 40 bytes at 0x7fa4a6415ce0)
2 params, 5 slots, 1 upvalue, 2 locals, 4 constants, 0 functions
	1	[877]	GETUPVAL 	2 0	; logger
	2	[877]	GETTABLE 	2 2 -1	; "dbg"
	3	[877]	LOADK    	3 -2	; "CreDocument: set visible page count"
	4	[877]	MOVE     	4 1
	5	[877]	CALL     	2 3 1
	6	[878]	GETTABLE 	2 0 -3	; "_document"
	7	[878]	SELF     	2 2 -4	; "setVisiblePageCount"
	8	[878]	MOVE     	4 1
	9	[878]	CALL     	2 3 1
	10	[879]	RETURN   	0 1

function <./frontend/document/credocument.lua:881,884> (10 instructions, 40 bytes at 0x7fa4a64160f0)
2 params, 5 slots, 1 upvalue, 2 locals, 4 constants, 0 functions
	1	[882]	GETUPVAL 	2 0	; logger
	2	[882]	GETTABLE 	2 2 -1	; "dbg"
	3	[882]	LOADK    	3 -2	; "CreDocument: set battery state"
	4	[882]	MOVE     	4 1
	5	[882]	CALL     	2 3 1
	6	[883]	GETTABLE 	2 0 -3	; "_document"
	7	[883]	SELF     	2 2 -4	; "setBatteryState"
	8	[883]	MOVE     	4 1
	9	[883]	CALL     	2 3 1
	10	[884]	RETURN   	0 1

function <./frontend/document/credocument.lua:886,889> (11 instructions, 44 bytes at 0x7fa4a6416250)
2 params, 5 slots, 1 upvalue, 2 locals, 4 constants, 0 functions
	1	[887]	GETUPVAL 	2 0	; logger
	2	[887]	GETTABLE 	2 2 -1	; "dbg"
	3	[887]	LOADK    	3 -2	; "CreDocument: check xpointer in current page"
	4	[887]	MOVE     	4 1
	5	[887]	CALL     	2 3 1
	6	[888]	GETTABLE 	2 0 -3	; "_document"
	7	[888]	SELF     	2 2 -4	; "isXPointerInCurrentPage"
	8	[888]	MOVE     	4 1
	9	[888]	TAILCALL 	2 3 0
	10	[888]	RETURN   	2 0
	11	[889]	RETURN   	0 1

function <./frontend/document/credocument.lua:891,894> (11 instructions, 44 bytes at 0x7fa4a6419140)
2 params, 6 slots, 1 upvalue, 2 locals, 5 constants, 0 functions
	1	[892]	GETUPVAL 	2 0	; logger
	2	[892]	GETTABLE 	2 2 -1	; "dbg"
	3	[892]	LOADK    	3 -2	; "CreDocument: set status line property"
	4	[892]	MOVE     	4 1
	5	[892]	CALL     	2 3 1
	6	[893]	GETTABLE 	2 0 -3	; "_document"
	7	[893]	SELF     	2 2 -4	; "setStringProperty"
	8	[893]	LOADK    	4 -5	; "window.status.line"
	9	[893]	MOVE     	5 1
	10	[893]	CALL     	2 4 1
	11	[894]	RETURN   	0 1

function <./frontend/document/credocument.lua:896,899> (10 instructions, 40 bytes at 0x7fa4a6419c50)
2 params, 5 slots, 1 upvalue, 2 locals, 4 constants, 0 functions
	1	[897]	GETUPVAL 	2 0	; logger
	2	[897]	GETTABLE 	2 2 -1	; "dbg"
	3	[897]	LOADK    	3 -2	; "CreDocument: set background image"
	4	[897]	MOVE     	4 1
	5	[897]	CALL     	2 3 1
	6	[898]	GETTABLE 	2 0 -3	; "_document"
	7	[898]	SELF     	2 2 -4	; "setBackgroundImage"
	8	[898]	MOVE     	4 1
	9	[898]	CALL     	2 3 1
	10	[899]	RETURN   	0 1

function <./frontend/document/credocument.lua:901,905> (22 instructions, 88 bytes at 0x7fa4a641aa90)
5 params, 11 slots, 1 upvalue, 5 locals, 6 constants, 0 functions
	1	[902]	GETUPVAL 	5 0	; logger
	2	[902]	GETTABLE 	5 5 -1	; "dbg"
	3	[902]	LOADK    	6 -2	; "CreDocument: find text"
	4	[902]	MOVE     	7 1
	5	[902]	MOVE     	8 2
	6	[902]	MOVE     	9 3
	7	[902]	MOVE     	10 4
	8	[902]	CALL     	5 6 1
	9	[903]	GETTABLE 	5 0 -3	; "_document"
	10	[903]	SELF     	5 5 -4	; "findText"
	11	[904]	MOVE     	7 1
	12	[904]	MOVE     	8 2
	13	[904]	MOVE     	9 3
	14	[904]	TEST     	4 0 0
	15	[904]	JMP      	3	; to 19
	16	[904]	LOADK    	10 -5	; 1
	17	[904]	TEST     	10 0 1
	18	[904]	JMP      	1	; to 20
	19	[904]	LOADK    	10 -6	; 0
	20	[903]	TAILCALL 	5 6 0
	21	[904]	RETURN   	5 0
	22	[905]	RETURN   	0 1

function <./frontend/document/credocument.lua:907,918> (16 instructions, 64 bytes at 0x7fa4a64125f0)
2 params, 6 slots, 1 upvalue, 2 locals, 7 constants, 0 functions
	1	[916]	GETUPVAL 	2 0	; logger
	2	[916]	GETTABLE 	2 2 -1	; "dbg"
	3	[916]	LOADK    	3 -2	; "CreDocument: set bookmarks highlight and internal history"
	4	[916]	MOVE     	4 1
	5	[916]	CALL     	2 3 1
	6	[917]	GETTABLE 	2 0 -3	; "_document"
	7	[917]	SELF     	2 2 -4	; "setIntProperty"
	8	[917]	LOADK    	4 -5	; "crengine.highlight.bookmarks"
	9	[917]	TEST     	1 0 0
	10	[917]	JMP      	3	; to 14
	11	[917]	LOADK    	5 -6	; 2
	12	[917]	TEST     	5 0 1
	13	[917]	JMP      	1	; to 15
	14	[917]	LOADK    	5 -7	; 0
	15	[917]	CALL     	2 4 1
	16	[918]	RETURN   	0 1

function <./frontend/document/credocument.lua:920,922> (6 instructions, 24 bytes at 0x7fa4a64127e0)
2 params, 5 slots, 0 upvalues, 2 locals, 2 constants, 0 functions
	1	[921]	GETTABLE 	2 0 -1	; "_document"
	2	[921]	SELF     	2 2 -2	; "setCallback"
	3	[921]	MOVE     	4 1
	4	[921]	TAILCALL 	2 3 0
	5	[921]	RETURN   	2 0
	6	[922]	RETURN   	0 1

function <./frontend/document/credocument.lua:924,926> (5 instructions, 20 bytes at 0x7fa4a641a150)
1 param, 3 slots, 0 upvalues, 1 local, 2 constants, 0 functions
	1	[925]	GETTABLE 	1 0 -1	; "_document"
	2	[925]	SELF     	1 1 -2	; "isBuiltDomStale"
	3	[925]	TAILCALL 	1 2 0
	4	[925]	RETURN   	1 0
	5	[926]	RETURN   	0 1

function <./frontend/document/credocument.lua:928,930> (5 instructions, 20 bytes at 0x7fa4a641a240)
1 param, 3 slots, 0 upvalues, 1 local, 2 constants, 0 functions
	1	[929]	GETTABLE 	1 0 -1	; "_document"
	2	[929]	SELF     	1 1 -2	; "hasCacheFile"
	3	[929]	TAILCALL 	1 2 0
	4	[929]	RETURN   	1 0
	5	[930]	RETURN   	0 1

function <./frontend/document/credocument.lua:932,934> (4 instructions, 16 bytes at 0x7fa4a6417220)
1 param, 3 slots, 0 upvalues, 1 local, 2 constants, 0 functions
	1	[933]	GETTABLE 	1 0 -1	; "_document"
	2	[933]	SELF     	1 1 -2	; "invalidateCacheFile"
	3	[933]	CALL     	1 2 1
	4	[934]	RETURN   	0 1

function <./frontend/document/credocument.lua:936,938> (5 instructions, 20 bytes at 0x7fa4a6417740)
1 param, 3 slots, 0 upvalues, 1 local, 2 constants, 0 functions
	1	[937]	GETTABLE 	1 0 -1	; "_document"
	2	[937]	SELF     	1 1 -2	; "getCacheFilePath"
	3	[937]	TAILCALL 	1 2 0
	4	[937]	RETURN   	1 0
	5	[938]	RETURN   	0 1

function <./frontend/document/credocument.lua:940,942> (5 instructions, 20 bytes at 0x7fa4a641b160)
1 param, 3 slots, 0 upvalues, 1 local, 2 constants, 0 functions
	1	[941]	GETTABLE 	1 0 -1	; "_document"
	2	[941]	SELF     	1 1 -2	; "getStatistics"
	3	[941]	TAILCALL 	1 2 0
	4	[941]	RETURN   	1 0
	5	[942]	RETURN   	0 1

function <./frontend/document/credocument.lua:944,946> (3 instructions, 12 bytes at 0x7fa4a641c920)
1 param, 2 slots, 0 upvalues, 1 local, 0 constants, 0 functions
	1	[945]	LOADBOOL 	1 1 0
	2	[945]	RETURN   	1 2
	3	[946]	RETURN   	0 1

function <./frontend/document/credocument.lua:948,950> (5 instructions, 20 bytes at 0x7fa4a641cdc0)
1 param, 3 slots, 0 upvalues, 1 local, 2 constants, 0 functions
	1	[949]	GETTABLE 	1 0 -1	; "_document"
	2	[949]	SELF     	1 1 -2	; "isTocAlternativeToc"
	3	[949]	TAILCALL 	1 2 0
	4	[949]	RETURN   	1 0
	5	[950]	RETURN   	0 1

function <./frontend/document/credocument.lua:952,954> (4 instructions, 16 bytes at 0x7fa4a641ce50)
1 param, 3 slots, 0 upvalues, 1 local, 2 constants, 0 functions
	1	[953]	GETTABLE 	1 0 -1	; "_document"
	2	[953]	SELF     	1 1 -2	; "buildAlternativeToc"
	3	[953]	CALL     	1 2 1
	4	[954]	RETURN   	0 1

function <./frontend/document/credocument.lua:956,958> (5 instructions, 20 bytes at 0x7fa4a641d2c0)
1 param, 3 slots, 0 upvalues, 1 local, 2 constants, 0 functions
	1	[957]	GETTABLE 	1 0 -1	; "_document"
	2	[957]	SELF     	1 1 -2	; "hasPageMap"
	3	[957]	TAILCALL 	1 2 0
	4	[957]	RETURN   	1 0
	5	[958]	RETURN   	0 1

function <./frontend/document/credocument.lua:960,962> (5 instructions, 20 bytes at 0x7fa4a641d350)
1 param, 3 slots, 0 upvalues, 1 local, 2 constants, 0 functions
	1	[961]	GETTABLE 	1 0 -1	; "_document"
	2	[961]	SELF     	1 1 -2	; "getPageMap"
	3	[961]	TAILCALL 	1 2 0
	4	[961]	RETURN   	1 0
	5	[962]	RETURN   	0 1

function <./frontend/document/credocument.lua:964,966> (5 instructions, 20 bytes at 0x7fa4a641d590)
1 param, 3 slots, 0 upvalues, 1 local, 2 constants, 0 functions
	1	[965]	GETTABLE 	1 0 -1	; "_document"
	2	[965]	SELF     	1 1 -2	; "getPageMapSource"
	3	[965]	TAILCALL 	1 2 0
	4	[965]	RETURN   	1 0
	5	[966]	RETURN   	0 1

function <./frontend/document/credocument.lua:968,970> (5 instructions, 20 bytes at 0x7fa4a641d810)
1 param, 3 slots, 0 upvalues, 1 local, 2 constants, 0 functions
	1	[969]	GETTABLE 	1 0 -1	; "_document"
	2	[969]	SELF     	1 1 -2	; "getPageMapCurrentPageLabel"
	3	[969]	TAILCALL 	1 2 0
	4	[969]	RETURN   	1 0
	5	[970]	RETURN   	0 1

function <./frontend/document/credocument.lua:972,974> (5 instructions, 20 bytes at 0x7fa4a641daf0)
1 param, 3 slots, 0 upvalues, 1 local, 2 constants, 0 functions
	1	[973]	GETTABLE 	1 0 -1	; "_document"
	2	[973]	SELF     	1 1 -2	; "getPageMapFirstPageLabel"
	3	[973]	TAILCALL 	1 2 0
	4	[973]	RETURN   	1 0
	5	[974]	RETURN   	0 1

function <./frontend/document/credocument.lua:976,978> (5 instructions, 20 bytes at 0x7fa4a641dd60)
1 param, 3 slots, 0 upvalues, 1 local, 2 constants, 0 functions
	1	[977]	GETTABLE 	1 0 -1	; "_document"
	2	[977]	SELF     	1 1 -2	; "getPageMapLastPageLabel"
	3	[977]	TAILCALL 	1 2 0
	4	[977]	RETURN   	1 0
	5	[978]	RETURN   	0 1

function <./frontend/document/credocument.lua:980,982> (6 instructions, 24 bytes at 0x7fa4a641e050)
2 params, 5 slots, 0 upvalues, 2 locals, 2 constants, 0 functions
	1	[981]	GETTABLE 	2 0 -1	; "_document"
	2	[981]	SELF     	2 2 -2	; "getPageMapXPointerPageLabel"
	3	[981]	MOVE     	4 1
	4	[981]	TAILCALL 	2 3 0
	5	[981]	RETURN   	2 0
	6	[982]	RETURN   	0 1

function <./frontend/document/credocument.lua:984,986> (5 instructions, 20 bytes at 0x7fa4a641e310)
1 param, 3 slots, 0 upvalues, 1 local, 2 constants, 0 functions
	1	[985]	GETTABLE 	1 0 -1	; "_document"
	2	[985]	SELF     	1 1 -2	; "getPageMapVisiblePageLabels"
	3	[985]	TAILCALL 	1 2 0
	4	[985]	RETURN   	1 0
	5	[986]	RETURN   	0 1

function <./frontend/document/credocument.lua:988,1020> (163 instructions, 652 bytes at 0x7fa4a641e5b0)
2 params, 8 slots, 0 upvalues, 2 locals, 49 constants, 0 functions
	1	[989]	SELF     	2 1 -1	; "addProvider"
	2	[989]	LOADK    	4 -2	; "azw"
	3	[989]	LOADK    	5 -3	; "application/vnd.amazon.mobi8-ebook"
	4	[989]	MOVE     	6 0
	5	[989]	LOADK    	7 -4	; 90
	6	[989]	CALL     	2 6 1
	7	[990]	SELF     	2 1 -1	; "addProvider"
	8	[990]	LOADK    	4 -5	; "chm"
	9	[990]	LOADK    	5 -6	; "application/vnd.ms-htmlhelp"
	10	[990]	MOVE     	6 0
	11	[990]	LOADK    	7 -4	; 90
	12	[990]	CALL     	2 6 1
	13	[991]	SELF     	2 1 -1	; "addProvider"
	14	[991]	LOADK    	4 -7	; "doc"
	15	[991]	LOADK    	5 -8	; "application/msword"
	16	[991]	MOVE     	6 0
	17	[991]	LOADK    	7 -4	; 90
	18	[991]	CALL     	2 6 1
	19	[992]	SELF     	2 1 -1	; "addProvider"
	20	[992]	LOADK    	4 -9	; "docx"
	21	[992]	LOADK    	5 -10	; "application/vnd.openxmlformats-officedocument.wordprocessingml.document"
	22	[992]	MOVE     	6 0
	23	[992]	LOADK    	7 -4	; 90
	24	[992]	CALL     	2 6 1
	25	[993]	SELF     	2 1 -1	; "addProvider"
	26	[993]	LOADK    	4 -11	; "epub"
	27	[993]	LOADK    	5 -12	; "application/epub+zip"
	28	[993]	MOVE     	6 0
	29	[993]	LOADK    	7 -13	; 100
	30	[993]	CALL     	2 6 1
	31	[994]	SELF     	2 1 -1	; "addProvider"
	32	[994]	LOADK    	4 -14	; "epub3"
	33	[994]	LOADK    	5 -12	; "application/epub+zip"
	34	[994]	MOVE     	6 0
	35	[994]	LOADK    	7 -13	; 100
	36	[994]	CALL     	2 6 1
	37	[995]	SELF     	2 1 -1	; "addProvider"
	38	[995]	LOADK    	4 -15	; "fb2"
	39	[995]	LOADK    	5 -16	; "application/fb2"
	40	[995]	MOVE     	6 0
	41	[995]	LOADK    	7 -4	; 90
	42	[995]	CALL     	2 6 1
	43	[996]	SELF     	2 1 -1	; "addProvider"
	44	[996]	LOADK    	4 -17	; "fb2.zip"
	45	[996]	LOADK    	5 -18	; "application/zip"
	46	[996]	MOVE     	6 0
	47	[996]	LOADK    	7 -4	; 90
	48	[996]	CALL     	2 6 1
	49	[997]	SELF     	2 1 -1	; "addProvider"
	50	[997]	LOADK    	4 -19	; "fb3"
	51	[997]	LOADK    	5 -20	; "application/fb3"
	52	[997]	MOVE     	6 0
	53	[997]	LOADK    	7 -4	; 90
	54	[997]	CALL     	2 6 1
	55	[998]	SELF     	2 1 -1	; "addProvider"
	56	[998]	LOADK    	4 -21	; "htm"
	57	[998]	LOADK    	5 -22	; "text/html"
	58	[998]	MOVE     	6 0
	59	[998]	LOADK    	7 -13	; 100
	60	[998]	CALL     	2 6 1
	61	[999]	SELF     	2 1 -1	; "addProvider"
	62	[999]	LOADK    	4 -23	; "html"
	63	[999]	LOADK    	5 -22	; "text/html"
	64	[999]	MOVE     	6 0
	65	[999]	LOADK    	7 -13	; 100
	66	[999]	CALL     	2 6 1
	67	[1000]	SELF     	2 1 -1	; "addProvider"
	68	[1000]	LOADK    	4 -24	; "htm.zip"
	69	[1000]	LOADK    	5 -18	; "application/zip"
	70	[1000]	MOVE     	6 0
	71	[1000]	LOADK    	7 -13	; 100
	72	[1000]	CALL     	2 6 1
	73	[1001]	SELF     	2 1 -1	; "addProvider"
	74	[1001]	LOADK    	4 -25	; "html.zip"
	75	[1001]	LOADK    	5 -18	; "application/zip"
	76	[1001]	MOVE     	6 0
	77	[1001]	LOADK    	7 -13	; 100
	78	[1001]	CALL     	2 6 1
	79	[1002]	SELF     	2 1 -1	; "addProvider"
	80	[1002]	LOADK    	4 -26	; "log"
	81	[1002]	LOADK    	5 -27	; "text/plain"
	82	[1002]	MOVE     	6 0
	83	[1002]	CALL     	2 5 1
	84	[1003]	SELF     	2 1 -1	; "addProvider"
	85	[1003]	LOADK    	4 -28	; "log.zip"
	86	[1003]	LOADK    	5 -18	; "application/zip"
	87	[1003]	MOVE     	6 0
	88	[1003]	CALL     	2 5 1
	89	[1004]	SELF     	2 1 -1	; "addProvider"
	90	[1004]	LOADK    	4 -29	; "md"
	91	[1004]	LOADK    	5 -27	; "text/plain"
	92	[1004]	MOVE     	6 0
	93	[1004]	CALL     	2 5 1
	94	[1005]	SELF     	2 1 -1	; "addProvider"
	95	[1005]	LOADK    	4 -30	; "md.zip"
	96	[1005]	LOADK    	5 -18	; "application/zip"
	97	[1005]	MOVE     	6 0
	98	[1005]	CALL     	2 5 1
	99	[1006]	SELF     	2 1 -1	; "addProvider"
	100	[1006]	LOADK    	4 -31	; "mobi"
	101	[1006]	LOADK    	5 -32	; "application/x-mobipocket-ebook"
	102	[1006]	MOVE     	6 0
	103	[1006]	LOADK    	7 -4	; 90
	104	[1006]	CALL     	2 6 1
	105	[1008]	SELF     	2 1 -1	; "addProvider"
	106	[1008]	LOADK    	4 -33	; "pdb"
	107	[1008]	LOADK    	5 -34	; "application/vnd.palm"
	108	[1008]	MOVE     	6 0
	109	[1008]	LOADK    	7 -4	; 90
	110	[1008]	CALL     	2 6 1
	111	[1010]	SELF     	2 1 -1	; "addProvider"
	112	[1010]	LOADK    	4 -35	; "prc"
	113	[1010]	LOADK    	5 -34	; "application/vnd.palm"
	114	[1010]	MOVE     	6 0
	115	[1010]	CALL     	2 5 1
	116	[1011]	SELF     	2 1 -1	; "addProvider"
	117	[1011]	LOADK    	4 -36	; "tcr"
	118	[1011]	LOADK    	5 -37	; "application/tcr"
	119	[1011]	MOVE     	6 0
	120	[1011]	CALL     	2 5 1
	121	[1012]	SELF     	2 1 -1	; "addProvider"
	122	[1012]	LOADK    	4 -38	; "txt"
	123	[1012]	LOADK    	5 -27	; "text/plain"
	124	[1012]	MOVE     	6 0
	125	[1012]	LOADK    	7 -4	; 90
	126	[1012]	CALL     	2 6 1
	127	[1013]	SELF     	2 1 -1	; "addProvider"
	128	[1013]	LOADK    	4 -39	; "txt.zip"
	129	[1013]	LOADK    	5 -18	; "application/zip"
	130	[1013]	MOVE     	6 0
	131	[1013]	LOADK    	7 -4	; 90
	132	[1013]	CALL     	2 6 1
	133	[1014]	SELF     	2 1 -1	; "addProvider"
	134	[1014]	LOADK    	4 -40	; "rtf"
	135	[1014]	LOADK    	5 -41	; "application/rtf"
	136	[1014]	MOVE     	6 0
	137	[1014]	LOADK    	7 -4	; 90
	138	[1014]	CALL     	2 6 1
	139	[1015]	SELF     	2 1 -1	; "addProvider"
	140	[1015]	LOADK    	4 -42	; "xhtml"
	141	[1015]	LOADK    	5 -43	; "application/xhtml+xml"
	142	[1015]	MOVE     	6 0
	143	[1015]	LOADK    	7 -4	; 90
	144	[1015]	CALL     	2 6 1
	145	[1016]	SELF     	2 1 -1	; "addProvider"
	146	[1016]	LOADK    	4 -44	; "zip"
	147	[1016]	LOADK    	5 -18	; "application/zip"
	148	[1016]	MOVE     	6 0
	149	[1016]	LOADK    	7 -45	; 10
	150	[1016]	CALL     	2 6 1
	151	[1018]	SELF     	2 1 -1	; "addProvider"
	152	[1018]	LOADK    	4 -46	; "sh"
	153	[1018]	LOADK    	5 -47	; "application/x-shellscript"
	154	[1018]	MOVE     	6 0
	155	[1018]	LOADK    	7 -4	; 90
	156	[1018]	CALL     	2 6 1
	157	[1019]	SELF     	2 1 -1	; "addProvider"
	158	[1019]	LOADK    	4 -48	; "py"
	159	[1019]	LOADK    	5 -49	; "text/x-python"
	160	[1019]	MOVE     	6 0
	161	[1019]	LOADK    	7 -4	; 90
	162	[1019]	CALL     	2 6 1
	163	[1020]	RETURN   	0 1

function <./frontend/document/credocument.lua:1025,1411> (382 instructions, 1528 bytes at 0x7fa4a641ea80)
1 param, 27 slots, 2 upvalues, 25 locals, 78 constants, 22 functions
	1	[1026]	GETGLOBAL	1 -1	; G_reader_settings
	2	[1026]	SELF     	1 1 -2	; "nilOrTrue"
	3	[1026]	LOADK    	3 -3	; "use_cre_call_cache"
	4	[1026]	CALL     	1 3 2
	5	[1026]	TEST     	1 0 1
	6	[1026]	JMP      	5	; to 12
	7	[1027]	GETUPVAL 	1 0	; logger
	8	[1027]	GETTABLE 	1 1 -4	; "dbg"
	9	[1027]	LOADK    	2 -5	; "CreDocument: not using cre call cache"
	10	[1027]	CALL     	1 2 1
	11	[1028]	RETURN   	0 1
	12	[1030]	GETUPVAL 	1 0	; logger
	13	[1030]	GETTABLE 	1 1 -4	; "dbg"
	14	[1030]	LOADK    	2 -6	; "CreDocument: using cre call cache"
	15	[1030]	CALL     	1 2 1
	16	[1031]	GETGLOBAL	1 -1	; G_reader_settings
	17	[1031]	SELF     	1 1 -7	; "isTrue"
	18	[1031]	LOADK    	3 -8	; "use_cre_call_cache_log_stats"
	19	[1031]	CALL     	1 3 2
	20	[1033]	LOADBOOL 	2 0 0
	21	[1034]	LOADBOOL 	3 0 0
	22	[1047]	CLOSURE  	4 0	; 0x7fa4a641f190
	23	[1047]	MOVE     	0 0
	24	[1047]	SETTABLE 	0 -9 4	; "_callCacheReset" -
	25	[1051]	CLOSURE  	4 1	; 0x7fa4a641f6d0
	26	[1051]	MOVE     	0 0
	27	[1051]	SETTABLE 	0 -10 4	; "_callCacheGet" -
	28	[1054]	CLOSURE  	4 2	; 0x7fa4a641f860
	29	[1054]	MOVE     	0 0
	30	[1054]	SETTABLE 	0 -11 4	; "_callCacheSet" -
	31	[1057]	SETTABLE 	0 -12 -13	; "_call_cache_keep_tags_nb" 10
	32	[1076]	CLOSURE  	4 3	; 0x7fa4a641fd80
	33	[1076]	MOVE     	0 0
	34	[1076]	SETTABLE 	0 -14 4	; "_callCacheSetCurrentTag" -
	35	[1079]	CLOSURE  	4 4	; 0x7fa4a641f310
	36	[1079]	MOVE     	0 0
	37	[1079]	SETTABLE 	0 -15 4	; "_callCacheGetCurrentTag" -
	38	[1085]	CLOSURE  	4 5	; 0x7fa4a6420490
	39	[1085]	MOVE     	0 0
	40	[1085]	SETTABLE 	0 -16 4	; "_callCacheTagGet" -
	41	[1090]	CLOSURE  	4 6	; 0x7fa4a641f3c0
	42	[1090]	MOVE     	0 0
	43	[1090]	SETTABLE 	0 -17 4	; "_callCacheTagSet" -
	44	[1091]	GETTABLE 	4 0 -9	; "_callCacheReset"
	45	[1091]	CALL     	4 1 1
	46	[1112]	CLOSURE  	4 7	; 0x7fa4a6420e30
	47	[1114]	CLOSURE  	5 8	; 0x7fa4a64212f0
	48	[1115]	MOVE     	6 5
	49	[1116]	MOVE     	7 5
	50	[1117]	MOVE     	8 5
	51	[1118]	MOVE     	9 5
	52	[1119]	TEST     	1 0 0
	53	[1119]	JMP      	21	; to 75
	54	[1121]	NEWTABLE 	10 0 0
	55	[1121]	SETTABLE 	0 -18 10	; "_call_cache_stats" -
	56	[1122]	GETGLOBAL	10 -19	; require
	57	[1122]	LOADK    	11 -20	; "ffi/util"
	58	[1122]	CALL     	10 2 2
	59	[1122]	GETTABLE 	10 10 -21	; "gettime"
	60	[1126]	CLOSURE  	6 9	; 0x7fa4a6420db0
	61	[1126]	MOVE     	0 10
	62	[1136]	CLOSURE  	7 10	; 0x7fa4a6421ae0
	63	[1136]	MOVE     	0 6
	64	[1136]	MOVE     	0 0
	65	[1147]	CLOSURE  	8 11	; 0x7fa4a6422000
	66	[1147]	MOVE     	0 6
	67	[1147]	MOVE     	0 0
	68	[1150]	CLOSURE  	9 12	; 0x7fa4a641ff40
	69	[1150]	GETUPVAL 	0 0	; logger
	70	[1150]	MOVE     	0 0
	71	[1222]	CLOSURE  	11 13	; 0x7fa4a6422740
	72	[1222]	MOVE     	0 0
	73	[1222]	SETTABLE 	0 -22 11	; "getCallCacheStatistics" -
	74	[1222]	CLOSE    	10
	75	[1228]	GETGLOBAL	10 -23	; pairs
	76	[1228]	GETUPVAL 	11 1	; CreDocument
	77	[1228]	CALL     	10 2 4
	78	[1228]	JMP      	286	; to 365
	79	[1229]	GETGLOBAL	15 -24	; type
	80	[1229]	MOVE     	16 14
	81	[1229]	CALL     	15 2 2
	82	[1229]	EQ       	0 15 -25	; - "function"
	83	[1229]	JMP      	280	; to 364
	84	[1231]	LOADBOOL 	15 0 0
	85	[1232]	LOADBOOL 	16 0 0
	86	[1233]	LOADBOOL 	17 0 0
	87	[1234]	LOADBOOL 	18 0 0
	88	[1235]	LOADBOOL 	19 0 0
	89	[1236]	LOADNIL  	20 21
	90	[1238]	LOADBOOL 	22 0 0
	91	[1241]	EQ       	0 13 -26	; - "setBatteryState"
	92	[1241]	JMP      	2	; to 95
	93	[1241]	LOADBOOL 	15 1 0
	94	[1241]	JMP      	195	; to 290
	95	[1242]	SELF     	23 13 -27	; "sub"
	96	[1242]	LOADK    	25 -28	; 1
	97	[1242]	LOADK    	26 -29	; 3
	98	[1242]	CALL     	23 4 2
	99	[1242]	EQ       	0 23 -30	; - "set"
	100	[1242]	JMP      	2	; to 103
	101	[1242]	LOADBOOL 	16 1 0
	102	[1242]	JMP      	187	; to 290
	103	[1243]	SELF     	23 13 -27	; "sub"
	104	[1243]	LOADK    	25 -28	; 1
	105	[1243]	LOADK    	26 -31	; 6
	106	[1243]	CALL     	23 4 2
	107	[1243]	EQ       	0 23 -32	; - "toggle"
	108	[1243]	JMP      	2	; to 111
	109	[1243]	LOADBOOL 	16 1 0
	110	[1243]	JMP      	179	; to 290
	111	[1244]	SELF     	23 13 -27	; "sub"
	112	[1244]	LOADK    	25 -28	; 1
	113	[1244]	LOADK    	26 -31	; 6
	114	[1244]	CALL     	23 4 2
	115	[1244]	EQ       	0 23 -33	; - "update"
	116	[1244]	JMP      	2	; to 119
	117	[1244]	LOADBOOL 	16 1 0
	118	[1244]	JMP      	171	; to 290
	119	[1245]	SELF     	23 13 -27	; "sub"
	120	[1245]	LOADK    	25 -28	; 1
	121	[1245]	LOADK    	26 -31	; 6
	122	[1245]	CALL     	23 4 2
	123	[1245]	EQ       	0 23 -34	; - "enable"
	124	[1245]	JMP      	2	; to 127
	125	[1245]	LOADBOOL 	16 1 0
	126	[1245]	JMP      	163	; to 290
	127	[1246]	EQ       	0 13 -35	; - "zoomFont"
	128	[1246]	JMP      	2	; to 131
	129	[1246]	LOADBOOL 	16 1 0
	130	[1246]	JMP      	159	; to 290
	131	[1251]	EQ       	0 13 -36	; - "clearSelection"
	132	[1251]	JMP      	2	; to 135
	133	[1251]	LOADBOOL 	17 1 0
	134	[1251]	JMP      	155	; to 290
	135	[1252]	EQ       	0 13 -37	; - "highlightXPointer"
	136	[1252]	JMP      	2	; to 139
	137	[1252]	LOADBOOL 	17 1 0
	138	[1252]	JMP      	151	; to 290
	139	[1253]	EQ       	0 13 -38	; - "getWordFromPosition"
	140	[1253]	JMP      	2	; to 143
	141	[1253]	LOADBOOL 	17 1 0
	142	[1253]	JMP      	147	; to 290
	143	[1254]	EQ       	0 13 -39	; - "getTextFromPositions"
	144	[1254]	JMP      	2	; to 147
	145	[1254]	LOADBOOL 	17 1 0
	146	[1254]	JMP      	143	; to 290
	147	[1255]	EQ       	0 13 -40	; - "findText"
	148	[1255]	JMP      	2	; to 151
	149	[1255]	LOADBOOL 	17 1 0
	150	[1255]	JMP      	139	; to 290
	151	[1258]	EQ       	0 13 -41	; - "gotoPage"
	152	[1258]	JMP      	3	; to 156
	153	[1258]	LOADK    	20 -42	; "page"
	154	[1258]	LOADK    	21 -43	; 2
	155	[1258]	JMP      	134	; to 290
	156	[1259]	EQ       	0 13 -44	; - "gotoPos"
	157	[1259]	JMP      	3	; to 161
	158	[1259]	LOADK    	20 -45	; "pos"
	159	[1259]	LOADK    	21 -43	; 2
	160	[1259]	JMP      	129	; to 290
	161	[1260]	EQ       	0 13 -46	; - "drawCurrentViewByPage"
	162	[1260]	JMP      	3	; to 166
	163	[1260]	LOADK    	20 -42	; "page"
	164	[1260]	LOADK    	21 -31	; 6
	165	[1260]	JMP      	124	; to 290
	166	[1261]	EQ       	0 13 -47	; - "drawCurrentViewByPos"
	167	[1261]	JMP      	3	; to 171
	168	[1261]	LOADK    	20 -45	; "pos"
	169	[1261]	LOADK    	21 -31	; 6
	170	[1261]	JMP      	119	; to 290
	171	[1268]	EQ       	0 13 -48	; - "getCurrentPage"
	172	[1268]	JMP      	2	; to 175
	173	[1268]	LOADBOOL 	15 1 0
	174	[1268]	JMP      	115	; to 290
	175	[1269]	EQ       	0 13 -49	; - "getCurrentPos"
	176	[1269]	JMP      	2	; to 179
	177	[1269]	LOADBOOL 	15 1 0
	178	[1269]	JMP      	111	; to 290
	179	[1270]	EQ       	0 13 -50	; - "getVisiblePageCount"
	180	[1270]	JMP      	2	; to 183
	181	[1270]	LOADBOOL 	15 1 0
	182	[1270]	JMP      	107	; to 290
	183	[1271]	EQ       	0 13 -51	; - "getCoverPageImage"
	184	[1271]	JMP      	2	; to 187
	185	[1271]	LOADBOOL 	15 1 0
	186	[1271]	JMP      	103	; to 290
	187	[1272]	EQ       	0 13 -52	; - "getDocumentFileContent"
	188	[1272]	JMP      	2	; to 191
	189	[1272]	LOADBOOL 	15 1 0
	190	[1272]	JMP      	99	; to 290
	191	[1273]	EQ       	0 13 -53	; - "getHTMLFromXPointer"
	192	[1273]	JMP      	2	; to 195
	193	[1273]	LOADBOOL 	15 1 0
	194	[1273]	JMP      	95	; to 290
	195	[1274]	EQ       	0 13 -54	; - "getHTMLFromXPointers"
	196	[1274]	JMP      	2	; to 199
	197	[1274]	LOADBOOL 	15 1 0
	198	[1274]	JMP      	91	; to 290
	199	[1275]	EQ       	0 13 -55	; - "getImageFromPosition"
	200	[1275]	JMP      	2	; to 203
	201	[1275]	LOADBOOL 	15 1 0
	202	[1275]	JMP      	87	; to 290
	203	[1276]	EQ       	0 13 -56	; - "getTextFromXPointer"
	204	[1276]	JMP      	2	; to 207
	205	[1276]	LOADBOOL 	15 1 0
	206	[1276]	JMP      	83	; to 290
	207	[1277]	EQ       	0 13 -57	; - "getTextFromXPointers"
	208	[1277]	JMP      	2	; to 211
	209	[1277]	LOADBOOL 	15 1 0
	210	[1277]	JMP      	79	; to 290
	211	[1278]	EQ       	0 13 -58	; - "getPageOffsetX"
	212	[1278]	JMP      	2	; to 215
	213	[1278]	LOADBOOL 	15 1 0
	214	[1278]	JMP      	75	; to 290
	215	[1279]	EQ       	0 13 -59	; - "getNextVisibleWordStart"
	216	[1279]	JMP      	2	; to 219
	217	[1279]	LOADBOOL 	15 1 0
	218	[1279]	JMP      	71	; to 290
	219	[1280]	EQ       	0 13 -60	; - "getNextVisibleWordEnd"
	220	[1280]	JMP      	2	; to 223
	221	[1280]	LOADBOOL 	15 1 0
	222	[1280]	JMP      	67	; to 290
	223	[1281]	EQ       	0 13 -61	; - "getPrevVisibleWordStart"
	224	[1281]	JMP      	2	; to 227
	225	[1281]	LOADBOOL 	15 1 0
	226	[1281]	JMP      	63	; to 290
	227	[1282]	EQ       	0 13 -62	; - "getPrevVisibleWordEnd"
	228	[1282]	JMP      	2	; to 231
	229	[1282]	LOADBOOL 	15 1 0
	230	[1282]	JMP      	59	; to 290
	231	[1283]	EQ       	0 13 -63	; - "getPrevVisibleChar"
	232	[1283]	JMP      	2	; to 235
	233	[1283]	LOADBOOL 	15 1 0
	234	[1283]	JMP      	55	; to 290
	235	[1284]	EQ       	0 13 -64	; - "getNextVisibleChar"
	236	[1284]	JMP      	2	; to 239
	237	[1284]	LOADBOOL 	15 1 0
	238	[1284]	JMP      	51	; to 290
	239	[1285]	EQ       	0 13 -65	; - "getCacheFilePath"
	240	[1285]	JMP      	2	; to 243
	241	[1285]	LOADBOOL 	15 1 0
	242	[1285]	JMP      	47	; to 290
	243	[1286]	EQ       	0 13 -66	; - "getStatistics"
	244	[1286]	JMP      	2	; to 247
	245	[1286]	LOADBOOL 	15 1 0
	246	[1286]	JMP      	43	; to 290
	247	[1287]	EQ       	0 13 -67	; - "getNormalizedXPointer"
	248	[1287]	JMP      	2	; to 251
	249	[1287]	LOADBOOL 	15 1 0
	250	[1287]	JMP      	39	; to 290
	251	[1290]	EQ       	0 13 -68	; - "getLinkFromPosition"
	252	[1290]	JMP      	2	; to 255
	253	[1290]	LOADBOOL 	18 1 0
	254	[1290]	JMP      	35	; to 290
	255	[1291]	EQ       	0 13 -69	; - "getPageLinks"
	256	[1291]	JMP      	2	; to 259
	257	[1291]	LOADBOOL 	18 1 0
	258	[1291]	JMP      	31	; to 290
	259	[1292]	EQ       	0 13 -70	; - "getScreenBoxesFromPositions"
	260	[1292]	JMP      	2	; to 263
	261	[1292]	LOADBOOL 	18 1 0
	262	[1292]	JMP      	27	; to 290
	263	[1293]	EQ       	0 13 -71	; - "getScreenPositionFromXPointer"
	264	[1293]	JMP      	2	; to 267
	265	[1293]	LOADBOOL 	18 1 0
	266	[1293]	JMP      	23	; to 290
	267	[1294]	EQ       	0 13 -72	; - "getXPointer"
	268	[1294]	JMP      	2	; to 271
	269	[1294]	LOADBOOL 	18 1 0
	270	[1294]	JMP      	19	; to 290
	271	[1295]	EQ       	0 13 -73	; - "isXPointerInCurrentPage"
	272	[1295]	JMP      	2	; to 275
	273	[1295]	LOADBOOL 	18 1 0
	274	[1295]	JMP      	15	; to 290
	275	[1296]	EQ       	0 13 -74	; - "getPageMapCurrentPageLabel"
	276	[1296]	JMP      	2	; to 279
	277	[1296]	LOADBOOL 	18 1 0
	278	[1296]	JMP      	11	; to 290
	279	[1297]	EQ       	0 13 -75	; - "getPageMapVisiblePageLabels"
	280	[1297]	JMP      	2	; to 283
	281	[1297]	LOADBOOL 	18 1 0
	282	[1297]	JMP      	7	; to 290
	283	[1301]	SELF     	23 13 -27	; "sub"
	284	[1301]	LOADK    	25 -28	; 1
	285	[1301]	LOADK    	26 -29	; 3
	286	[1301]	CALL     	23 4 2
	287	[1301]	EQ       	0 23 -76	; - "get"
	288	[1301]	JMP      	1	; to 290
	289	[1301]	LOADBOOL 	19 1 0
	290	[1306]	TEST     	16 0 0
	291	[1306]	JMP      	8	; to 300
	292	[1312]	CLOSURE  	23 14	; 0x7fa4a6423360
	293	[1312]	MOVE     	0 3
	294	[1312]	GETUPVAL 	0 0	; logger
	295	[1312]	MOVE     	0 13
	296	[1312]	MOVE     	0 0
	297	[1312]	MOVE     	0 14
	298	[1312]	SETTABLE 	0 13 23
	299	[1312]	JMP      	51	; to 351
	300	[1313]	TEST     	17 0 0
	301	[1313]	JMP      	8	; to 310
	302	[1318]	CLOSURE  	23 15	; 0x7fa4a6422540
	303	[1318]	MOVE     	0 3
	304	[1318]	GETUPVAL 	0 0	; logger
	305	[1318]	MOVE     	0 13
	306	[1318]	MOVE     	0 0
	307	[1318]	MOVE     	0 14
	308	[1318]	SETTABLE 	0 13 23
	309	[1318]	JMP      	41	; to 351
	310	[1319]	TEST     	20 0 0
	311	[1319]	JMP      	10	; to 322
	312	[1325]	CLOSURE  	23 16	; 0x7fa4a6420bb0
	313	[1325]	MOVE     	0 3
	314	[1325]	GETUPVAL 	0 0	; logger
	315	[1325]	MOVE     	0 13
	316	[1325]	MOVE     	0 21
	317	[1325]	MOVE     	0 0
	318	[1325]	MOVE     	0 20
	319	[1325]	MOVE     	0 14
	320	[1325]	SETTABLE 	0 13 23
	321	[1325]	JMP      	29	; to 351
	322	[1326]	TEST     	18 0 0
	323	[1326]	JMP      	13	; to 337
	324	[1327]	LOADBOOL 	22 1 0
	325	[1346]	CLOSURE  	23 17	; 0x7fa4a6421240
	326	[1346]	MOVE     	0 6
	327	[1346]	MOVE     	0 13
	328	[1346]	MOVE     	0 4
	329	[1346]	MOVE     	0 0
	330	[1346]	MOVE     	0 3
	331	[1346]	GETUPVAL 	0 0	; logger
	332	[1346]	MOVE     	0 8
	333	[1346]	MOVE     	0 14
	334	[1346]	MOVE     	0 7
	335	[1346]	SETTABLE 	0 13 23
	336	[1346]	JMP      	14	; to 351
	337	[1347]	TEST     	19 0 0
	338	[1347]	JMP      	12	; to 351
	339	[1348]	LOADBOOL 	22 1 0
	340	[1365]	CLOSURE  	23 18	; 0x7fa4a64240c0
	341	[1365]	MOVE     	0 6
	342	[1365]	MOVE     	0 13
	343	[1365]	MOVE     	0 4
	344	[1365]	MOVE     	0 0
	345	[1365]	MOVE     	0 3
	346	[1365]	GETUPVAL 	0 0	; logger
	347	[1365]	MOVE     	0 8
	348	[1365]	MOVE     	0 14
	349	[1365]	MOVE     	0 7
	350	[1365]	SETTABLE 	0 13 23
	351	[1367]	TEST     	2 0 0
	352	[1367]	JMP      	10	; to 363
	353	[1367]	TEST     	22 0 1
	354	[1367]	JMP      	8	; to 363
	355	[1368]	GETTABLE 	23 0 13
	356	[1374]	CLOSURE  	24 19	; 0x7fa4a6424280
	357	[1374]	MOVE     	0 6
	358	[1374]	MOVE     	0 23
	359	[1374]	MOVE     	0 7
	360	[1374]	MOVE     	0 13
	361	[1374]	SETTABLE 	0 13 24
	362	[1374]	CLOSE    	23
	363	[1375]	CLOSE    	15
	364	[1376]	CLOSE    	13
	365	[1228]	TFORLOOP 	10 2
	366	[1376]	JMP      	-288	; to 79
	367	[1403]	CLOSURE  	10 20	; 0x7fa4a6424a60
	368	[1403]	MOVE     	0 0
	369	[1403]	MOVE     	0 6
	370	[1403]	MOVE     	0 3
	371	[1403]	GETUPVAL 	0 0	; logger
	372	[1403]	GETUPVAL 	0 1	; CreDocument
	373	[1403]	MOVE     	0 7
	374	[1403]	MOVE     	0 8
	375	[1403]	SETTABLE 	0 -77 10	; "drawCurrentView" -
	376	[1405]	TEST     	1 0 0
	377	[1405]	JMP      	4	; to 382
	378	[1409]	CLOSURE  	10 21	; 0x7fa4a6425360
	379	[1409]	GETUPVAL 	0 1	; CreDocument
	380	[1409]	MOVE     	0 9
	381	[1409]	SETTABLE 	0 -78 10	; "close" -
	382	[1411]	RETURN   	0 1

function <./frontend/document/credocument.lua:1044,1047> (7 instructions, 28 bytes at 0x7fa4a641f190)
0 params, 2 slots, 1 upvalue, 0 locals, 2 constants, 0 functions
	1	[1045]	GETUPVAL 	0 0	; self
	2	[1045]	NEWTABLE 	1 0 0
	3	[1045]	SETTABLE 	0 -1 1	; "_call_cache" -
	4	[1046]	GETUPVAL 	0 0	; self
	5	[1046]	NEWTABLE 	1 0 0
	6	[1046]	SETTABLE 	0 -2 1	; "_call_cache_tags_lru" -
	7	[1047]	RETURN   	0 1

function <./frontend/document/credocument.lua:1049,1051> (5 instructions, 20 bytes at 0x7fa4a641f6d0)
1 param, 2 slots, 1 upvalue, 1 local, 1 constant, 0 functions
	1	[1050]	GETUPVAL 	1 0	; self
	2	[1050]	GETTABLE 	1 1 -1	; "_call_cache"
	3	[1050]	GETTABLE 	1 1 0
	4	[1050]	RETURN   	1 2
	5	[1051]	RETURN   	0 1

function <./frontend/document/credocument.lua:1052,1054> (4 instructions, 16 bytes at 0x7fa4a641f860)
2 params, 3 slots, 1 upvalue, 2 locals, 1 constant, 0 functions
	1	[1053]	GETUPVAL 	2 0	; self
	2	[1053]	GETTABLE 	2 2 -1	; "_call_cache"
	3	[1053]	SETTABLE 	2 0 1
	4	[1054]	RETURN   	0 1

function <./frontend/document/credocument.lua:1059,1076> (59 instructions, 236 bytes at 0x7fa4a641fd80)
1 param, 8 slots, 1 upvalue, 5 locals, 10 constants, 0 functions
	1	[1060]	GETUPVAL 	1 0	; self
	2	[1060]	GETTABLE 	1 1 -1	; "_call_cache"
	3	[1060]	GETTABLE 	1 1 0
	4	[1060]	TEST     	1 0 1
	5	[1060]	JMP      	4	; to 10
	6	[1061]	GETUPVAL 	1 0	; self
	7	[1061]	GETTABLE 	1 1 -1	; "_call_cache"
	8	[1061]	NEWTABLE 	2 0 0
	9	[1061]	SETTABLE 	1 0 2
	10	[1063]	GETUPVAL 	1 0	; self
	11	[1063]	SETTABLE 	1 -2 0	; "_call_cache_current_tag" -
	12	[1065]	GETUPVAL 	1 0	; self
	13	[1065]	GETTABLE 	1 1 -3	; "_call_cache_tags_lru"
	14	[1065]	GETTABLE 	1 1 -4	; 1
	15	[1065]	EQ       	1 1 0
	16	[1065]	JMP      	42	; to 59
	17	[1066]	GETUPVAL 	1 0	; self
	18	[1066]	GETTABLE 	1 1 -3	; "_call_cache_tags_lru"
	19	[1066]	LEN      	1 1
	20	[1066]	LOADK    	2 -4	; 1
	21	[1066]	LOADK    	3 -5	; -1
	22	[1066]	FORPREP  	1 28	; to 51
	23	[1067]	GETUPVAL 	5 0	; self
	24	[1067]	GETTABLE 	5 5 -3	; "_call_cache_tags_lru"
	25	[1067]	GETTABLE 	5 5 4
	26	[1067]	EQ       	0 5 0
	27	[1067]	JMP      	7	; to 35
	28	[1068]	GETGLOBAL	5 -6	; table
	29	[1068]	GETTABLE 	5 5 -7	; "remove"
	30	[1068]	GETUPVAL 	6 0	; self
	31	[1068]	GETTABLE 	6 6 -3	; "_call_cache_tags_lru"
	32	[1068]	MOVE     	7 4
	33	[1068]	CALL     	5 3 1
	34	[1068]	JMP      	16	; to 51
	35	[1069]	GETUPVAL 	5 0	; self
	36	[1069]	GETTABLE 	5 5 -8	; "_call_cache_keep_tags_nb"
	37	[1069]	LT       	0 5 4
	38	[1069]	JMP      	12	; to 51
	39	[1070]	GETUPVAL 	5 0	; self
	40	[1070]	GETTABLE 	5 5 -1	; "_call_cache"
	41	[1070]	GETUPVAL 	6 0	; self
	42	[1070]	GETTABLE 	6 6 -3	; "_call_cache_tags_lru"
	43	[1070]	GETTABLE 	6 6 4
	44	[1070]	SETTABLE 	5 6 -9	; - nil
	45	[1071]	GETGLOBAL	5 -6	; table
	46	[1071]	GETTABLE 	5 5 -7	; "remove"
	47	[1071]	GETUPVAL 	6 0	; self
	48	[1071]	GETTABLE 	6 6 -3	; "_call_cache_tags_lru"
	49	[1071]	MOVE     	7 4
	50	[1071]	CALL     	5 3 1
	51	[1066]	FORLOOP  	1 -29	; to 23
	52	[1074]	GETGLOBAL	1 -6	; table
	53	[1074]	GETTABLE 	1 1 -10	; "insert"
	54	[1074]	GETUPVAL 	2 0	; self
	55	[1074]	GETTABLE 	2 2 -3	; "_call_cache_tags_lru"
	56	[1074]	LOADK    	3 -4	; 1
	57	[1074]	MOVE     	4 0
	58	[1074]	CALL     	1 4 1
	59	[1076]	RETURN   	0 1

function <./frontend/document/credocument.lua:1077,1079> (4 instructions, 16 bytes at 0x7fa4a641f310)
1 param, 2 slots, 1 upvalue, 1 local, 1 constant, 0 functions
	1	[1078]	GETUPVAL 	1 0	; self
	2	[1078]	GETTABLE 	1 1 -1	; "_call_cache_current_tag"
	3	[1078]	RETURN   	1 2
	4	[1079]	RETURN   	0 1

function <./frontend/document/credocument.lua:1081,1085> (19 instructions, 76 bytes at 0x7fa4a6420490)
1 param, 3 slots, 1 upvalue, 1 local, 2 constants, 0 functions
	1	[1082]	GETUPVAL 	1 0	; self
	2	[1082]	GETTABLE 	1 1 -1	; "_call_cache_current_tag"
	3	[1082]	TEST     	1 0 0
	4	[1082]	JMP      	14	; to 19
	5	[1082]	GETUPVAL 	1 0	; self
	6	[1082]	GETTABLE 	1 1 -2	; "_call_cache"
	7	[1082]	GETUPVAL 	2 0	; self
	8	[1082]	GETTABLE 	2 2 -1	; "_call_cache_current_tag"
	9	[1082]	GETTABLE 	1 1 2
	10	[1082]	TEST     	1 0 0
	11	[1082]	JMP      	7	; to 19
	12	[1083]	GETUPVAL 	1 0	; self
	13	[1083]	GETTABLE 	1 1 -2	; "_call_cache"
	14	[1083]	GETUPVAL 	2 0	; self
	15	[1083]	GETTABLE 	2 2 -1	; "_call_cache_current_tag"
	16	[1083]	GETTABLE 	1 1 2
	17	[1083]	GETTABLE 	1 1 0
	18	[1083]	RETURN   	1 2
	19	[1085]	RETURN   	0 1

function <./frontend/document/credocument.lua:1086,1090> (18 instructions, 72 bytes at 0x7fa4a641f3c0)
2 params, 4 slots, 1 upvalue, 2 locals, 2 constants, 0 functions
	1	[1087]	GETUPVAL 	2 0	; self
	2	[1087]	GETTABLE 	2 2 -1	; "_call_cache_current_tag"
	3	[1087]	TEST     	2 0 0
	4	[1087]	JMP      	13	; to 18
	5	[1087]	GETUPVAL 	2 0	; self
	6	[1087]	GETTABLE 	2 2 -2	; "_call_cache"
	7	[1087]	GETUPVAL 	3 0	; self
	8	[1087]	GETTABLE 	3 3 -1	; "_call_cache_current_tag"
	9	[1087]	GETTABLE 	2 2 3
	10	[1087]	TEST     	2 0 0
	11	[1087]	JMP      	6	; to 18
	12	[1088]	GETUPVAL 	2 0	; self
	13	[1088]	GETTABLE 	2 2 -2	; "_call_cache"
	14	[1088]	GETUPVAL 	3 0	; self
	15	[1088]	GETTABLE 	3 3 -1	; "_call_cache_current_tag"
	16	[1088]	GETTABLE 	2 2 3
	17	[1088]	SETTABLE 	2 0 1
	18	[1090]	RETURN   	0 1

function <./frontend/document/credocument.lua:1094,1112> (60 instructions, 240 bytes at 0x7fa4a6420e30)
0+ params, 19 slots, 0 upvalues, 14 locals, 9 constants, 0 functions
	1	[1095]	NEWTABLE 	1 0 0
	2	[1096]	GETGLOBAL	2 -1	; ipairs
	3	[1096]	NEWTABLE 	3 0 0
	4	[1096]	VARARG   	4 0
	5	[1096]	SETLIST  	3 0 1	; 1
	6	[1096]	CALL     	2 2 4
	7	[1096]	JMP      	44	; to 52
	8	[1097]	LOADNIL  	7 7
	9	[1098]	GETGLOBAL	8 -2	; type
	10	[1098]	MOVE     	9 6
	11	[1098]	CALL     	8 2 2
	12	[1098]	EQ       	0 8 -3	; - "table"
	13	[1098]	JMP      	29	; to 43
	14	[1100]	NEWTABLE 	8 0 0
	15	[1101]	GETGLOBAL	9 -4	; pairs
	16	[1101]	MOVE     	10 6
	17	[1101]	CALL     	9 2 4
	18	[1101]	JMP      	11	; to 30
	19	[1102]	GETGLOBAL	14 -3	; table
	20	[1102]	GETTABLE 	14 14 -5	; "insert"
	21	[1102]	MOVE     	15 8
	22	[1102]	GETGLOBAL	16 -6	; tostring
	23	[1102]	MOVE     	17 12
	24	[1102]	CALL     	16 2 2
	25	[1102]	GETGLOBAL	17 -6	; tostring
	26	[1102]	MOVE     	18 13
	27	[1102]	CALL     	17 2 2
	28	[1102]	CONCAT   	16 16 17
	29	[1102]	CALL     	14 3 1
	30	[1101]	TFORLOOP 	9 2
	31	[1102]	JMP      	-13	; to 19
	32	[1104]	GETGLOBAL	9 -3	; table
	33	[1104]	GETTABLE 	9 9 -7	; "sort"
	34	[1104]	MOVE     	10 8
	35	[1104]	CALL     	9 2 1
	36	[1105]	GETGLOBAL	9 -3	; table
	37	[1105]	GETTABLE 	9 9 -8	; "concat"
	38	[1105]	MOVE     	10 8
	39	[1105]	LOADK    	11 -9	; "|"
	40	[1105]	CALL     	9 3 2
	41	[1105]	MOVE     	7 9
	42	[1105]	JMP      	4	; to 47
	43	[1107]	GETGLOBAL	8 -6	; tostring
	44	[1107]	MOVE     	9 6
	45	[1107]	CALL     	8 2 2
	46	[1107]	MOVE     	7 8
	47	[1109]	GETGLOBAL	8 -3	; table
	48	[1109]	GETTABLE 	8 8 -5	; "insert"
	49	[1109]	MOVE     	9 1
	50	[1109]	MOVE     	10 7
	51	[1109]	CALL     	8 3 1
	52	[1096]	TFORLOOP 	2 2
	53	[1109]	JMP      	-46	; to 8
	54	[1111]	GETGLOBAL	2 -3	; table
	55	[1111]	GETTABLE 	2 2 -8	; "concat"
	56	[1111]	MOVE     	3 1
	57	[1111]	LOADK    	4 -9	; "|"
	58	[1111]	TAILCALL 	2 3 0
	59	[1111]	RETURN   	2 0
	60	[1112]	RETURN   	0 1

function <./frontend/document/credocument.lua:1114,1114> (1 instruction, 4 bytes at 0x7fa4a64212f0)
0 params, 2 slots, 0 upvalues, 0 locals, 0 constants, 0 functions
	1	[1114]	RETURN   	0 1

function <./frontend/document/credocument.lua:1123,1126> (6 instructions, 24 bytes at 0x7fa4a6420db0)
0 params, 3 slots, 1 upvalue, 2 locals, 1 constant, 0 functions
	1	[1124]	GETUPVAL 	0 0	; _gettime
	2	[1124]	CALL     	0 1 3
	3	[1125]	DIV      	2 1 -1	; - 1000000
	4	[1125]	ADD      	2 0 2
	5	[1125]	RETURN   	2 2
	6	[1126]	RETURN   	0 1

function <./frontend/document/credocument.lua:1127,1136> (29 instructions, 116 bytes at 0x7fa4a6421ae0)
3 params, 11 slots, 2 upvalues, 5 locals, 5 constants, 0 functions
	1	[1128]	GETUPVAL 	3 0	; getTime
	2	[1128]	CALL     	3 1 2
	3	[1128]	SUB      	3 3 1
	4	[1129]	GETUPVAL 	4 1	; self
	5	[1129]	GETTABLE 	4 4 -1	; "_call_cache_stats"
	6	[1129]	GETTABLE 	4 4 0
	7	[1129]	TEST     	4 0 1
	8	[1129]	JMP      	11	; to 20
	9	[1130]	GETUPVAL 	4 1	; self
	10	[1130]	GETTABLE 	4 4 -1	; "_call_cache_stats"
	11	[1130]	NEWTABLE 	5 5 0
	12	[1130]	LOADK    	6 -2	; 0
	13	[1130]	LOADK    	7 -2	; 0
	14	[1130]	LOADK    	8 -3	; 1
	15	[1130]	MOVE     	9 3
	16	[1130]	MOVE     	10 2
	17	[1130]	SETLIST  	5 5 1	; 1
	18	[1130]	SETTABLE 	4 0 5
	19	[1130]	JMP      	9	; to 29
	20	[1132]	GETUPVAL 	4 1	; self
	21	[1132]	GETTABLE 	4 4 -1	; "_call_cache_stats"
	22	[1132]	GETTABLE 	4 4 0
	23	[1133]	GETTABLE 	5 4 -4	; 3
	24	[1133]	ADD      	5 5 -3	; - 1
	25	[1133]	SETTABLE 	4 -4 5	; 3 -
	26	[1134]	GETTABLE 	5 4 -5	; 4
	27	[1134]	ADD      	5 5 3
	28	[1134]	SETTABLE 	4 -5 5	; 4 -
	29	[1136]	RETURN   	0 1

function <./frontend/document/credocument.lua:1137,1147> (31 instructions, 124 bytes at 0x7fa4a6422000)
2 params, 9 slots, 2 upvalues, 4 locals, 4 constants, 0 functions
	1	[1138]	GETUPVAL 	2 0	; getTime
	2	[1138]	CALL     	2 1 2
	3	[1138]	SUB      	2 2 1
	4	[1139]	TEST     	2 0 1
	5	[1139]	JMP      	1	; to 7
	6	[1139]	LOADK    	2 -1	; 0
	7	[1140]	GETUPVAL 	3 1	; self
	8	[1140]	GETTABLE 	3 3 -2	; "_call_cache_stats"
	9	[1140]	GETTABLE 	3 3 0
	10	[1140]	TEST     	3 0 1
	11	[1140]	JMP      	10	; to 22
	12	[1141]	GETUPVAL 	3 1	; self
	13	[1141]	GETTABLE 	3 3 -2	; "_call_cache_stats"
	14	[1141]	NEWTABLE 	4 4 0
	15	[1141]	LOADK    	5 -3	; 1
	16	[1141]	MOVE     	6 2
	17	[1141]	LOADK    	7 -1	; 0
	18	[1141]	LOADK    	8 -1	; 0
	19	[1141]	SETLIST  	4 4 1	; 1
	20	[1141]	SETTABLE 	3 0 4
	21	[1141]	JMP      	9	; to 31
	22	[1143]	GETUPVAL 	3 1	; self
	23	[1143]	GETTABLE 	3 3 -2	; "_call_cache_stats"
	24	[1143]	GETTABLE 	3 3 0
	25	[1144]	GETTABLE 	4 3 -3	; 1
	26	[1144]	ADD      	4 4 -3	; - 1
	27	[1144]	SETTABLE 	3 -3 4	; 1 -
	28	[1145]	GETTABLE 	4 3 -4	; 2
	29	[1145]	ADD      	4 4 2
	30	[1145]	SETTABLE 	3 -4 4	; 2 -
	31	[1147]	RETURN   	0 1

function <./frontend/document/credocument.lua:1148,1150> (9 instructions, 36 bytes at 0x7fa4a641ff40)
0 params, 3 slots, 2 upvalues, 0 locals, 3 constants, 0 functions
	1	[1149]	GETUPVAL 	0 0	; logger
	2	[1149]	GETTABLE 	0 0 -1	; "info"
	3	[1149]	LOADK    	1 -2	; "cre call cache statistics:\n"
	4	[1149]	GETUPVAL 	2 1	; self
	5	[1149]	GETTABLE 	2 2 -3	; "getCallCacheStatistics"
	6	[1149]	CALL     	2 1 2
	7	[1149]	CONCAT   	1 1 2
	8	[1149]	CALL     	0 2 1
	9	[1150]	RETURN   	0 1

function <./frontend/document/credocument.lua:1152,1222> (292 instructions, 1168 bytes at 0x7fa4a6422740)
0 params, 33 slots, 1 upvalue, 58 locals, 38 constants, 0 functions
	1	[1153]	GETGLOBAL	0 -1	; require
	2	[1153]	LOADK    	1 -2	; "util"
	3	[1153]	CALL     	0 2 2
	4	[1154]	NEWTABLE 	1 0 0
	5	[1155]	GETGLOBAL	2 -3	; table
	6	[1155]	GETTABLE 	2 2 -4	; "insert"
	7	[1155]	MOVE     	3 1
	8	[1155]	LOADK    	4 -5	; "CRE call cache content:"
	9	[1155]	CALL     	2 3 1
	10	[1156]	GETGLOBAL	2 -3	; table
	11	[1156]	GETTABLE 	2 2 -4	; "insert"
	12	[1156]	MOVE     	3 1
	13	[1156]	GETGLOBAL	4 -6	; string
	14	[1156]	GETTABLE 	4 4 -7	; "format"
	15	[1156]	LOADK    	5 -8	; "     all: %d items"
	16	[1156]	GETTABLE 	6 0 -9	; "tableSize"
	17	[1156]	GETUPVAL 	7 0	; self
	18	[1156]	GETTABLE 	7 7 -10	; "_call_cache"
	19	[1156]	CALL     	6 2 0
	20	[1156]	CALL     	4 0 0
	21	[1156]	CALL     	2 0 1
	22	[1157]	GETGLOBAL	2 -3	; table
	23	[1157]	GETTABLE 	2 2 -4	; "insert"
	24	[1157]	MOVE     	3 1
	25	[1157]	GETGLOBAL	4 -6	; string
	26	[1157]	GETTABLE 	4 4 -7	; "format"
	27	[1157]	LOADK    	5 -11	; "  global: %d items"
	28	[1157]	GETTABLE 	6 0 -9	; "tableSize"
	29	[1157]	GETUPVAL 	7 0	; self
	30	[1157]	GETTABLE 	7 7 -10	; "_call_cache"
	31	[1157]	CALL     	6 2 2
	32	[1157]	GETUPVAL 	7 0	; self
	33	[1157]	GETTABLE 	7 7 -12	; "_call_cache_tags_lru"
	34	[1157]	LEN      	7 7
	35	[1157]	SUB      	6 6 7
	36	[1157]	CALL     	4 3 0
	37	[1157]	CALL     	2 0 1
	38	[1158]	GETGLOBAL	2 -3	; table
	39	[1158]	GETTABLE 	2 2 -4	; "insert"
	40	[1158]	MOVE     	3 1
	41	[1158]	GETGLOBAL	4 -6	; string
	42	[1158]	GETTABLE 	4 4 -7	; "format"
	43	[1158]	LOADK    	5 -13	; "    tags: %d items"
	44	[1158]	GETUPVAL 	6 0	; self
	45	[1158]	GETTABLE 	6 6 -12	; "_call_cache_tags_lru"
	46	[1158]	LEN      	6 6
	47	[1158]	CALL     	4 3 0
	48	[1158]	CALL     	2 0 1
	49	[1159]	LOADK    	2 -14	; 1
	50	[1159]	GETUPVAL 	3 0	; self
	51	[1159]	GETTABLE 	3 3 -12	; "_call_cache_tags_lru"
	52	[1159]	LEN      	3 3
	53	[1159]	LOADK    	4 -14	; 1
	54	[1159]	FORPREP  	2 19	; to 74
	55	[1160]	GETGLOBAL	6 -3	; table
	56	[1160]	GETTABLE 	6 6 -4	; "insert"
	57	[1160]	MOVE     	7 1
	58	[1160]	GETGLOBAL	8 -6	; string
	59	[1160]	GETTABLE 	8 8 -7	; "format"
	60	[1160]	LOADK    	9 -15	; "          '%s': %d items"
	61	[1160]	GETUPVAL 	10 0	; self
	62	[1160]	GETTABLE 	10 10 -12	; "_call_cache_tags_lru"
	63	[1160]	GETTABLE 	10 10 5
	64	[1161]	GETTABLE 	11 0 -9	; "tableSize"
	65	[1161]	GETUPVAL 	12 0	; self
	66	[1161]	GETTABLE 	12 12 -10	; "_call_cache"
	67	[1161]	GETUPVAL 	13 0	; self
	68	[1161]	GETTABLE 	13 13 -12	; "_call_cache_tags_lru"
	69	[1161]	GETTABLE 	13 13 5
	70	[1161]	GETTABLE 	12 12 13
	71	[1161]	CALL     	11 2 0
	72	[1160]	CALL     	8 0 0
	73	[1160]	CALL     	6 0 1
	74	[1159]	FORLOOP  	2 -20	; to 55
	75	[1163]	NEWTABLE 	2 0 0
	76	[1164]	NEWTABLE 	3 0 0
	77	[1165]	NEWTABLE 	4 0 0
	78	[1166]	GETGLOBAL	5 -16	; pairs
	79	[1166]	GETUPVAL 	6 0	; self
	80	[1166]	GETTABLE 	6 6 -17	; "_call_cache_stats"
	81	[1166]	CALL     	5 2 4
	82	[1166]	JMP      	26	; to 109
	83	[1167]	GETUPVAL 	10 0	; self
	84	[1167]	GETTABLE 	10 10 -17	; "_call_cache_stats"
	85	[1167]	GETTABLE 	10 10 8
	86	[1167]	GETTABLE 	10 10 -14	; 1
	87	[1167]	LT       	0 -18 10	; 0 -
	88	[1167]	JMP      	6	; to 95
	89	[1168]	GETGLOBAL	10 -3	; table
	90	[1168]	GETTABLE 	10 10 -4	; "insert"
	91	[1168]	MOVE     	11 2
	92	[1168]	MOVE     	12 8
	93	[1168]	CALL     	10 3 1
	94	[1168]	JMP      	14	; to 109
	95	[1170]	LEN      	10 9
	96	[1170]	LT       	0 -19 10	; 4 -
	97	[1170]	JMP      	6	; to 104
	98	[1171]	GETGLOBAL	10 -3	; table
	99	[1171]	GETTABLE 	10 10 -4	; "insert"
	100	[1171]	MOVE     	11 4
	101	[1171]	MOVE     	12 8
	102	[1171]	CALL     	10 3 1
	103	[1171]	JMP      	5	; to 109
	104	[1173]	GETGLOBAL	10 -3	; table
	105	[1173]	GETTABLE 	10 10 -4	; "insert"
	106	[1173]	MOVE     	11 3
	107	[1173]	MOVE     	12 8
	108	[1173]	CALL     	10 3 1
	109	[1166]	TFORLOOP 	5 2
	110	[1175]	JMP      	-28	; to 83
	111	[1177]	GETGLOBAL	5 -3	; table
	112	[1177]	GETTABLE 	5 5 -20	; "sort"
	113	[1177]	MOVE     	6 2
	114	[1177]	CALL     	5 2 1
	115	[1178]	GETGLOBAL	5 -3	; table
	116	[1178]	GETTABLE 	5 5 -20	; "sort"
	117	[1178]	MOVE     	6 3
	118	[1178]	CALL     	5 2 1
	119	[1179]	GETGLOBAL	5 -3	; table
	120	[1179]	GETTABLE 	5 5 -20	; "sort"
	121	[1179]	MOVE     	6 4
	122	[1179]	CALL     	5 2 1
	123	[1180]	GETGLOBAL	5 -3	; table
	124	[1180]	GETTABLE 	5 5 -4	; "insert"
	125	[1180]	MOVE     	6 1
	126	[1180]	LOADK    	7 -21	; "CRE call cache hits statistics:"
	127	[1180]	CALL     	5 3 1
	128	[1181]	LOADK    	5 -18	; 0
	129	[1182]	LOADK    	6 -18	; 0
	130	[1183]	GETGLOBAL	7 -22	; ipairs
	131	[1183]	MOVE     	8 2
	132	[1183]	CALL     	7 2 4
	133	[1183]	JMP      	44	; to 178
	134	[1184]	GETGLOBAL	12 -23	; unpack
	135	[1184]	GETUPVAL 	13 0	; self
	136	[1184]	GETTABLE 	13 13 -17	; "_call_cache_stats"
	137	[1184]	GETTABLE 	13 13 11
	138	[1184]	CALL     	12 2 5
	139	[1185]	ADD      	16 12 14
	140	[1186]	MUL      	17 -24 12	; 100 -
	141	[1186]	DIV      	17 17 16
	142	[1187]	MUL      	18 -14 12	; 1 -
	143	[1187]	MUL      	18 18 15
	144	[1187]	DIV      	18 18 14
	145	[1188]	LOADK    	19 -25	; ""
	146	[1189]	LE       	0 -26 13	; 0.001 -
	147	[1189]	JMP      	6	; to 154
	148	[1190]	GETGLOBAL	20 -6	; string
	149	[1190]	GETTABLE 	20 20 -7	; "format"
	150	[1190]	LOADK    	21 -27	; " (-%.3fs)"
	151	[1190]	MOVE     	22 13
	152	[1190]	CALL     	20 3 2
	153	[1190]	MOVE     	19 20
	154	[1192]	MUL      	20 -24 18	; 100 -
	155	[1192]	ADD      	21 15 13
	156	[1192]	ADD      	21 21 18
	157	[1192]	DIV      	20 20 21
	158	[1193]	GETGLOBAL	21 -3	; table
	159	[1193]	GETTABLE 	21 21 -4	; "insert"
	160	[1193]	MOVE     	22 1
	161	[1193]	GETGLOBAL	23 -6	; string
	162	[1193]	GETTABLE 	23 23 -7	; "format"
	163	[1193]	LOADK    	24 -28	; "    %s: %d/%d hits (%d%%) %.3fs%s saved, %.3fs used (%d%% saved)"
	164	[1193]	MOVE     	25 11
	165	[1193]	MOVE     	26 12
	166	[1193]	MOVE     	27 16
	167	[1194]	MOVE     	28 17
	168	[1194]	MOVE     	29 18
	169	[1194]	MOVE     	30 19
	170	[1194]	MOVE     	31 15
	171	[1194]	MOVE     	32 20
	172	[1193]	CALL     	23 10 0
	173	[1193]	CALL     	21 0 1
	174	[1195]	ADD      	21 5 15
	175	[1195]	ADD      	5 21 13
	176	[1196]	ADD      	21 6 18
	177	[1196]	SUB      	6 21 13
	178	[1183]	TFORLOOP 	7 2
	179	[1196]	JMP      	-46	; to 134
	180	[1198]	GETGLOBAL	7 -3	; table
	181	[1198]	GETTABLE 	7 7 -4	; "insert"
	182	[1198]	MOVE     	8 1
	183	[1198]	LOADK    	9 -29	; "  By call times (hits | misses):"
	184	[1198]	CALL     	7 3 1
	185	[1199]	GETGLOBAL	7 -22	; ipairs
	186	[1199]	MOVE     	8 2
	187	[1199]	CALL     	7 2 4
	188	[1199]	JMP      	20	; to 209
	189	[1200]	GETGLOBAL	12 -23	; unpack
	190	[1200]	GETUPVAL 	13 0	; self
	191	[1200]	GETTABLE 	13 13 -17	; "_call_cache_stats"
	192	[1200]	GETTABLE 	13 13 11
	193	[1200]	CALL     	12 2 5
	194	[1201]	GETGLOBAL	16 -3	; table
	195	[1201]	GETTABLE 	16 16 -4	; "insert"
	196	[1201]	MOVE     	17 1
	197	[1201]	GETGLOBAL	18 -6	; string
	198	[1201]	GETTABLE 	18 18 -7	; "format"
	199	[1201]	LOADK    	19 -30	; "    %s: (%d) %.3f ms | %.3f ms (%d)"
	200	[1201]	MOVE     	20 11
	201	[1201]	MOVE     	21 12
	202	[1201]	MUL      	22 -31 13	; 1000 -
	203	[1201]	DIV      	22 22 12
	204	[1201]	MUL      	23 -31 15	; 1000 -
	205	[1201]	DIV      	23 23 14
	206	[1201]	MOVE     	24 14
	207	[1201]	CALL     	18 7 0
	208	[1201]	CALL     	16 0 1
	209	[1199]	TFORLOOP 	7 2
	210	[1201]	JMP      	-22	; to 189
	211	[1203]	GETGLOBAL	7 -3	; table
	212	[1203]	GETTABLE 	7 7 -4	; "insert"
	213	[1203]	MOVE     	8 1
	214	[1203]	LOADK    	9 -32	; "  No hit for:"
	215	[1203]	CALL     	7 3 1
	216	[1204]	GETGLOBAL	7 -22	; ipairs
	217	[1204]	MOVE     	8 3
	218	[1204]	CALL     	7 2 4
	219	[1204]	JMP      	18	; to 238
	220	[1205]	GETGLOBAL	12 -23	; unpack
	221	[1205]	GETUPVAL 	13 0	; self
	222	[1205]	GETTABLE 	13 13 -17	; "_call_cache_stats"
	223	[1205]	GETTABLE 	13 13 11
	224	[1205]	CALL     	12 2 5
	225	[1206]	GETGLOBAL	16 -3	; table
	226	[1206]	GETTABLE 	16 16 -4	; "insert"
	227	[1206]	MOVE     	17 1
	228	[1206]	GETGLOBAL	18 -6	; string
	229	[1206]	GETTABLE 	18 18 -7	; "format"
	230	[1206]	LOADK    	19 -33	; "    %s: %d misses %.3fs"
	231	[1207]	MOVE     	20 11
	232	[1207]	MOVE     	21 14
	233	[1207]	MOVE     	22 15
	234	[1206]	CALL     	18 5 0
	235	[1206]	CALL     	16 0 1
	236	[1208]	ADD      	16 5 15
	237	[1208]	ADD      	5 16 13
	238	[1204]	TFORLOOP 	7 2
	239	[1208]	JMP      	-20	; to 220
	240	[1210]	LEN      	7 4
	241	[1210]	LT       	0 -18 7	; 0 -
	242	[1210]	JMP      	29	; to 272
	243	[1211]	GETGLOBAL	7 -3	; table
	244	[1211]	GETTABLE 	7 7 -4	; "insert"
	245	[1211]	MOVE     	8 1
	246	[1211]	LOADK    	9 -34	; "  No cache for:"
	247	[1211]	CALL     	7 3 1
	248	[1212]	GETGLOBAL	7 -22	; ipairs
	249	[1212]	MOVE     	8 4
	250	[1212]	CALL     	7 2 4
	251	[1212]	JMP      	18	; to 270
	252	[1213]	GETGLOBAL	12 -23	; unpack
	253	[1213]	GETUPVAL 	13 0	; self
	254	[1213]	GETTABLE 	13 13 -17	; "_call_cache_stats"
	255	[1213]	GETTABLE 	13 13 11
	256	[1213]	CALL     	12 2 5
	257	[1214]	GETGLOBAL	16 -3	; table
	258	[1214]	GETTABLE 	16 16 -4	; "insert"
	259	[1214]	MOVE     	17 1
	260	[1214]	GETGLOBAL	18 -6	; string
	261	[1214]	GETTABLE 	18 18 -7	; "format"
	262	[1214]	LOADK    	19 -35	; "    %s: %d calls %.3fs"
	263	[1215]	MOVE     	20 11
	264	[1215]	MOVE     	21 14
	265	[1215]	MOVE     	22 15
	266	[1214]	CALL     	18 5 0
	267	[1214]	CALL     	16 0 1
	268	[1216]	ADD      	16 5 15
	269	[1216]	ADD      	5 16 13
	270	[1212]	TFORLOOP 	7 2
	271	[1216]	JMP      	-20	; to 252
	272	[1219]	MUL      	7 -24 6	; 100 -
	273	[1219]	ADD      	8 5 6
	274	[1219]	DIV      	7 7 8
	275	[1220]	GETGLOBAL	8 -3	; table
	276	[1220]	GETTABLE 	8 8 -4	; "insert"
	277	[1220]	MOVE     	9 1
	278	[1220]	GETGLOBAL	10 -6	; string
	279	[1220]	GETTABLE 	10 10 -7	; "format"
	280	[1220]	LOADK    	11 -36	; "  cpu time used: %.3fs, saved: %.3fs (%d%% saved)"
	281	[1220]	MOVE     	12 5
	282	[1220]	MOVE     	13 6
	283	[1220]	MOVE     	14 7
	284	[1220]	CALL     	10 5 0
	285	[1220]	CALL     	8 0 1
	286	[1221]	GETGLOBAL	8 -3	; table
	287	[1221]	GETTABLE 	8 8 -37	; "concat"
	288	[1221]	MOVE     	9 1
	289	[1221]	LOADK    	10 -38	; "\n"
	290	[1221]	TAILCALL 	8 3 0
	291	[1221]	RETURN   	8 0
	292	[1222]	RETURN   	0 1

function <./frontend/document/credocument.lua:1307,1312> (17 instructions, 68 bytes at 0x7fa4a6423360)
0+ params, 5 slots, 5 upvalues, 1 local, 4 constants, 0 functions
	1	[1309]	GETUPVAL 	1 0	; do_log
	2	[1309]	TEST     	1 0 0
	3	[1309]	JMP      	6	; to 10
	4	[1309]	GETUPVAL 	1 1	; logger
	5	[1309]	GETTABLE 	1 1 -1	; "dbg"
	6	[1309]	LOADK    	2 -2	; "callCache:"
	7	[1309]	GETUPVAL 	3 2	; name
	8	[1309]	LOADK    	4 -3	; "reseting cache"
	9	[1309]	CALL     	1 4 1
	10	[1310]	GETUPVAL 	1 3	; self
	11	[1310]	GETTABLE 	1 1 -4	; "_callCacheReset"
	12	[1310]	CALL     	1 1 1
	13	[1311]	GETUPVAL 	1 4	; func
	14	[1311]	VARARG   	2 0
	15	[1311]	TAILCALL 	1 0 0
	16	[1311]	RETURN   	1 0
	17	[1312]	RETURN   	0 1

function <./frontend/document/credocument.lua:1314,1318> (19 instructions, 76 bytes at 0x7fa4a6422540)
0+ params, 5 slots, 5 upvalues, 1 local, 5 constants, 0 functions
	1	[1315]	GETUPVAL 	1 0	; do_log
	2	[1315]	TEST     	1 0 0
	3	[1315]	JMP      	6	; to 10
	4	[1315]	GETUPVAL 	1 1	; logger
	5	[1315]	GETTABLE 	1 1 -1	; "dbg"
	6	[1315]	LOADK    	2 -2	; "callCache:"
	7	[1315]	GETUPVAL 	3 2	; name
	8	[1315]	LOADK    	4 -3	; "reseting buffer"
	9	[1315]	CALL     	1 4 1
	10	[1316]	GETUPVAL 	1 3	; self
	11	[1316]	GETTABLE 	1 1 -4	; "_callCacheSet"
	12	[1316]	LOADK    	2 -5	; "current_buffer_tag"
	13	[1316]	LOADNIL  	3 3
	14	[1316]	CALL     	1 3 1
	15	[1317]	GETUPVAL 	1 4	; func
	16	[1317]	VARARG   	2 0
	17	[1317]	TAILCALL 	1 0 0
	18	[1317]	RETURN   	1 0
	19	[1318]	RETURN   	0 1

function <./frontend/document/credocument.lua:1320,1325> (24 instructions, 96 bytes at 0x7fa4a6420bb0)
0+ params, 5 slots, 7 upvalues, 2 locals, 5 constants, 0 functions
	1	[1321]	GETUPVAL 	1 0	; do_log
	2	[1321]	TEST     	1 0 0
	3	[1321]	JMP      	6	; to 10
	4	[1321]	GETUPVAL 	1 1	; logger
	5	[1321]	GETTABLE 	1 1 -1	; "dbg"
	6	[1321]	LOADK    	2 -2	; "callCache:"
	7	[1321]	GETUPVAL 	3 2	; name
	8	[1321]	LOADK    	4 -3	; "setting tag"
	9	[1321]	CALL     	1 4 1
	10	[1322]	GETGLOBAL	1 -4	; select
	11	[1322]	GETUPVAL 	2 3	; set_arg
	12	[1322]	VARARG   	3 0
	13	[1322]	CALL     	1 0 2
	14	[1323]	GETUPVAL 	2 4	; self
	15	[1323]	GETTABLE 	2 2 -5	; "_callCacheSetCurrentTag"
	16	[1323]	GETUPVAL 	3 5	; set_tag
	17	[1323]	MOVE     	4 1
	18	[1323]	CONCAT   	3 3 4
	19	[1323]	CALL     	2 2 1
	20	[1324]	GETUPVAL 	2 6	; func
	21	[1324]	VARARG   	3 0
	22	[1324]	TAILCALL 	2 0 0
	23	[1324]	RETURN   	2 0
	24	[1325]	RETURN   	0 1

function <./frontend/document/credocument.lua:1328,1346> (65 instructions, 260 bytes at 0x7fa4a6421240)
0+ params, 9 slots, 9 upvalues, 4 locals, 9 constants, 0 functions
	1	[1329]	GETUPVAL 	1 0	; getTime
	2	[1329]	CALL     	1 1 2
	3	[1330]	GETUPVAL 	2 1	; name
	4	[1330]	GETUPVAL 	3 2	; asString
	5	[1330]	GETGLOBAL	4 -1	; select
	6	[1330]	LOADK    	5 -2	; 2
	7	[1330]	VARARG   	6 0
	8	[1330]	CALL     	4 0 0
	9	[1330]	CALL     	3 0 2
	10	[1330]	CONCAT   	2 2 3
	11	[1331]	GETUPVAL 	3 3	; self
	12	[1331]	GETTABLE 	3 3 -3	; "_callCacheTagGet"
	13	[1331]	MOVE     	4 2
	14	[1331]	CALL     	3 2 2
	15	[1332]	TEST     	3 0 0
	16	[1332]	JMP      	19	; to 36
	17	[1333]	GETUPVAL 	4 4	; do_log
	18	[1333]	TEST     	4 0 0
	19	[1333]	JMP      	7	; to 27
	20	[1333]	GETUPVAL 	4 5	; logger
	21	[1333]	GETTABLE 	4 4 -4	; "dbg"
	22	[1333]	LOADK    	5 -5	; "callCache:"
	23	[1333]	GETUPVAL 	6 1	; name
	24	[1333]	LOADK    	7 -6	; "cache hit:"
	25	[1333]	MOVE     	8 2
	26	[1333]	CALL     	4 5 1
	27	[1334]	GETUPVAL 	4 6	; addStatHit
	28	[1334]	GETUPVAL 	5 1	; name
	29	[1334]	MOVE     	6 1
	30	[1334]	CALL     	4 3 1
	31	[1338]	GETGLOBAL	4 -7	; unpack
	32	[1338]	MOVE     	5 3
	33	[1338]	TAILCALL 	4 2 0
	34	[1338]	RETURN   	4 0
	35	[1338]	JMP      	29	; to 65
	36	[1340]	GETUPVAL 	4 4	; do_log
	37	[1340]	TEST     	4 0 0
	38	[1340]	JMP      	7	; to 46
	39	[1340]	GETUPVAL 	4 5	; logger
	40	[1340]	GETTABLE 	4 4 -4	; "dbg"
	41	[1340]	LOADK    	5 -5	; "callCache:"
	42	[1340]	GETUPVAL 	6 1	; name
	43	[1340]	LOADK    	7 -8	; "cache miss:"
	44	[1340]	MOVE     	8 2
	45	[1340]	CALL     	4 5 1
	46	[1341]	NEWTABLE 	4 0 0
	47	[1341]	GETUPVAL 	5 7	; func
	48	[1341]	VARARG   	6 0
	49	[1341]	CALL     	5 0 0
	50	[1341]	SETLIST  	4 0 1	; 1
	51	[1341]	MOVE     	3 4
	52	[1342]	GETUPVAL 	4 3	; self
	53	[1342]	GETTABLE 	4 4 -9	; "_callCacheTagSet"
	54	[1342]	MOVE     	5 2
	55	[1342]	MOVE     	6 3
	56	[1342]	CALL     	4 3 1
	57	[1343]	GETUPVAL 	4 8	; addStatMiss
	58	[1343]	GETUPVAL 	5 1	; name
	59	[1343]	MOVE     	6 1
	60	[1343]	CALL     	4 3 1
	61	[1344]	GETGLOBAL	4 -7	; unpack
	62	[1344]	MOVE     	5 3
	63	[1344]	TAILCALL 	4 2 0
	64	[1344]	RETURN   	4 0
	65	[1346]	RETURN   	0 1

function <./frontend/document/credocument.lua:1349,1365> (65 instructions, 260 bytes at 0x7fa4a64240c0)
0+ params, 9 slots, 9 upvalues, 4 locals, 9 constants, 0 functions
	1	[1350]	GETUPVAL 	1 0	; getTime
	2	[1350]	CALL     	1 1 2
	3	[1351]	GETUPVAL 	2 1	; name
	4	[1351]	GETUPVAL 	3 2	; asString
	5	[1351]	GETGLOBAL	4 -1	; select
	6	[1351]	LOADK    	5 -2	; 2
	7	[1351]	VARARG   	6 0
	8	[1351]	CALL     	4 0 0
	9	[1351]	CALL     	3 0 2
	10	[1351]	CONCAT   	2 2 3
	11	[1352]	GETUPVAL 	3 3	; self
	12	[1352]	GETTABLE 	3 3 -3	; "_callCacheGet"
	13	[1352]	MOVE     	4 2
	14	[1352]	CALL     	3 2 2
	15	[1353]	TEST     	3 0 0
	16	[1353]	JMP      	19	; to 36
	17	[1354]	GETUPVAL 	4 4	; do_log
	18	[1354]	TEST     	4 0 0
	19	[1354]	JMP      	7	; to 27
	20	[1354]	GETUPVAL 	4 5	; logger
	21	[1354]	GETTABLE 	4 4 -4	; "dbg"
	22	[1354]	LOADK    	5 -5	; "callCache:"
	23	[1354]	GETUPVAL 	6 1	; name
	24	[1354]	LOADK    	7 -6	; "cache hit:"
	25	[1354]	MOVE     	8 2
	26	[1354]	CALL     	4 5 1
	27	[1355]	GETUPVAL 	4 6	; addStatHit
	28	[1355]	GETUPVAL 	5 1	; name
	29	[1355]	MOVE     	6 1
	30	[1355]	CALL     	4 3 1
	31	[1357]	GETGLOBAL	4 -7	; unpack
	32	[1357]	MOVE     	5 3
	33	[1357]	TAILCALL 	4 2 0
	34	[1357]	RETURN   	4 0
	35	[1357]	JMP      	29	; to 65
	36	[1359]	GETUPVAL 	4 4	; do_log
	37	[1359]	TEST     	4 0 0
	38	[1359]	JMP      	7	; to 46
	39	[1359]	GETUPVAL 	4 5	; logger
	40	[1359]	GETTABLE 	4 4 -4	; "dbg"
	41	[1359]	LOADK    	5 -5	; "callCache:"
	42	[1359]	GETUPVAL 	6 1	; name
	43	[1359]	LOADK    	7 -8	; "cache miss:"
	44	[1359]	MOVE     	8 2
	45	[1359]	CALL     	4 5 1
	46	[1360]	NEWTABLE 	4 0 0
	47	[1360]	GETUPVAL 	5 7	; func
	48	[1360]	VARARG   	6 0
	49	[1360]	CALL     	5 0 0
	50	[1360]	SETLIST  	4 0 1	; 1
	51	[1360]	MOVE     	3 4
	52	[1361]	GETUPVAL 	4 3	; self
	53	[1361]	GETTABLE 	4 4 -9	; "_callCacheSet"
	54	[1361]	MOVE     	5 2
	55	[1361]	MOVE     	6 3
	56	[1361]	CALL     	4 3 1
	57	[1362]	GETUPVAL 	4 8	; addStatMiss
	58	[1362]	GETUPVAL 	5 1	; name
	59	[1362]	MOVE     	6 1
	60	[1362]	CALL     	4 3 1
	61	[1363]	GETGLOBAL	4 -7	; unpack
	62	[1363]	MOVE     	5 3
	63	[1363]	TAILCALL 	4 2 0
	64	[1363]	RETURN   	4 0
	65	[1365]	RETURN   	0 1

function <./frontend/document/credocument.lua:1369,1374> (17 instructions, 68 bytes at 0x7fa4a6424280)
0+ params, 7 slots, 4 upvalues, 3 locals, 1 constant, 0 functions
	1	[1370]	GETUPVAL 	1 0	; getTime
	2	[1370]	CALL     	1 1 2
	3	[1371]	NEWTABLE 	2 0 0
	4	[1371]	GETUPVAL 	3 1	; func2
	5	[1371]	VARARG   	4 0
	6	[1371]	CALL     	3 0 0
	7	[1371]	SETLIST  	2 0 1	; 1
	8	[1372]	GETUPVAL 	3 2	; addStatMiss
	9	[1372]	GETUPVAL 	4 3	; name
	10	[1372]	MOVE     	5 1
	11	[1372]	LOADBOOL 	6 1 0
	12	[1372]	CALL     	3 4 1
	13	[1373]	GETGLOBAL	3 -1	; unpack
	14	[1373]	MOVE     	4 2
	15	[1373]	TAILCALL 	3 2 0
	16	[1373]	RETURN   	3 0
	17	[1374]	RETURN   	0 1

function <./frontend/document/credocument.lua:1379,1403> (86 instructions, 344 bytes at 0x7fa4a6424a60)
6 params, 19 slots, 7 upvalues, 10 locals, 13 constants, 0 functions
	1	[1380]	LOADBOOL 	6 0 0
	2	[1381]	GETUPVAL 	7 0	; self
	3	[1381]	GETTABLE 	7 7 -1	; "_callCacheGetCurrentTag"
	4	[1381]	CALL     	7 1 2
	5	[1382]	GETUPVAL 	8 0	; self
	6	[1382]	GETTABLE 	8 8 -2	; "_callCacheGet"
	7	[1382]	LOADK    	9 -3	; "current_buffer_tag"
	8	[1382]	CALL     	8 2 2
	9	[1383]	GETTABLE 	9 0 -4	; "buffer"
	10	[1383]	TEST     	9 0 0
	11	[1383]	JMP      	12	; to 24
	12	[1383]	GETTABLE 	9 0 -4	; "buffer"
	13	[1383]	GETTABLE 	9 9 -5	; "w"
	14	[1383]	GETTABLE 	10 4 -5	; "w"
	15	[1383]	EQ       	0 9 10
	16	[1383]	JMP      	5	; to 22
	17	[1383]	GETTABLE 	9 0 -4	; "buffer"
	18	[1383]	GETTABLE 	9 9 -6	; "h"
	19	[1383]	GETTABLE 	10 4 -6	; "h"
	20	[1383]	EQ       	1 9 10
	21	[1383]	JMP      	2	; to 24
	22	[1384]	LOADBOOL 	6 1 0
	23	[1384]	JMP      	12	; to 36
	24	[1385]	GETTABLE 	9 0 -4	; "buffer"
	25	[1385]	TEST     	9 0 1
	26	[1385]	JMP      	2	; to 29
	27	[1386]	LOADBOOL 	6 1 0
	28	[1386]	JMP      	7	; to 36
	29	[1387]	TEST     	8 0 1
	30	[1387]	JMP      	2	; to 33
	31	[1388]	LOADBOOL 	6 1 0
	32	[1388]	JMP      	3	; to 36
	33	[1389]	EQ       	1 8 7
	34	[1389]	JMP      	1	; to 36
	35	[1390]	LOADBOOL 	6 1 0
	36	[1392]	GETUPVAL 	9 1	; getTime
	37	[1392]	CALL     	9 1 2
	38	[1393]	TEST     	6 0 0
	39	[1393]	JMP      	26	; to 66
	40	[1394]	GETUPVAL 	10 2	; do_log
	41	[1394]	TEST     	10 0 0
	42	[1394]	JMP      	4	; to 47
	43	[1394]	GETUPVAL 	10 3	; logger
	44	[1394]	GETTABLE 	10 10 -7	; "dbg"
	45	[1394]	LOADK    	11 -8	; "callCache: ########## drawCurrentView: full draw"
	46	[1394]	CALL     	10 2 1
	47	[1395]	GETUPVAL 	10 4	; CreDocument
	48	[1395]	GETTABLE 	10 10 -9	; "drawCurrentView"
	49	[1395]	MOVE     	11 0
	50	[1395]	MOVE     	12 1
	51	[1395]	MOVE     	13 2
	52	[1395]	MOVE     	14 3
	53	[1395]	MOVE     	15 4
	54	[1395]	MOVE     	16 5
	55	[1395]	CALL     	10 7 1
	56	[1396]	GETUPVAL 	10 5	; addStatMiss
	57	[1396]	LOADK    	11 -9	; "drawCurrentView"
	58	[1396]	MOVE     	12 9
	59	[1396]	CALL     	10 3 1
	60	[1397]	GETUPVAL 	10 0	; self
	61	[1397]	GETTABLE 	10 10 -10	; "_callCacheSet"
	62	[1397]	LOADK    	11 -3	; "current_buffer_tag"
	63	[1397]	MOVE     	12 7
	64	[1397]	CALL     	10 3 1
	65	[1397]	JMP      	20	; to 86
	66	[1399]	GETUPVAL 	10 2	; do_log
	67	[1399]	TEST     	10 0 0
	68	[1399]	JMP      	4	; to 73
	69	[1399]	GETUPVAL 	10 3	; logger
	70	[1399]	GETTABLE 	10 10 -7	; "dbg"
	71	[1399]	LOADK    	11 -11	; "callCache: ---------- drawCurrentView: light draw"
	72	[1399]	CALL     	10 2 1
	73	[1400]	SELF     	10 1 -12	; "blitFrom"
	74	[1400]	GETTABLE 	12 0 -4	; "buffer"
	75	[1400]	MOVE     	13 2
	76	[1400]	MOVE     	14 3
	77	[1400]	LOADK    	15 -13	; 0
	78	[1400]	LOADK    	16 -13	; 0
	79	[1400]	GETTABLE 	17 4 -5	; "w"
	80	[1400]	GETTABLE 	18 4 -6	; "h"
	81	[1400]	CALL     	10 9 1
	82	[1401]	GETUPVAL 	10 6	; addStatHit
	83	[1401]	LOADK    	11 -9	; "drawCurrentView"
	84	[1401]	MOVE     	12 9
	85	[1401]	CALL     	10 3 1
	86	[1403]	RETURN   	0 1

function <./frontend/document/credocument.lua:1406,1409> (7 instructions, 28 bytes at 0x7fa4a6425360)
1 param, 3 slots, 2 upvalues, 1 local, 1 constant, 0 functions
	1	[1407]	GETUPVAL 	1 0	; CreDocument
	2	[1407]	GETTABLE 	1 1 -1	; "close"
	3	[1407]	MOVE     	2 0
	4	[1407]	CALL     	1 2 1
	5	[1408]	GETUPVAL 	1 1	; dumpStats
	6	[1408]	CALL     	1 1 1
	7	[1409]	RETURN   	0 1
