-- BYTECODE -- css_tweaks.lua:0-814
0001    GGET     0   0      ; "require"
0002    KSTR     1   1      ; "gettext"
0003    CALL     0   2   2
0004    TGETS    1   0   2  ; "pgettext"
0005    TNEW     2   0
0006    KPRI     3   2
0007    TSETS    3   2   3  ; "footnote-inpage_epub_smaller"
0008    KPRI     3   2
0009    TSETS    3   2   4  ; "footnote-inpage_fb2"
0010    TDUP     3   5
0011    TSETS    2   3   6  ; "DEFAULT_GLOBAL_STYLE_TWEAKS"
0012    TDUP     4   9
0013    MOV      5   1
0014    KSTR     6   7      ; "Style tweaks category"
0015    KSTR     7   8      ; "Pages"
0016    CALL     5   2   3
0017    TSETS    5   4  10  ; "title"
0018    TDUP     5  11
0019    MOV      6   0
0020    KSTR     7  12      ; "Ignore publisher page margins"
0021    CALL     6   2   2
0022    TSETS    6   5  10  ; "title"
0023    MOV      6   0
0024    KSTR     7  13      ; "Force page margins to be 0, and may allo"~
0025    CALL     6   2   2
0026    TSETS    6   5  14  ; "description"
0027    TSETB    5   4   1
0028    TDUP     5  16
0029    MOV      6   0
0030    KSTR     7  15      ; "Ignore margin and padding"
0031    CALL     6   2   2
0032    TSETS    6   5  10  ; "title"
0033    TDUP     6  17
0034    MOV      7   0
0035    KSTR     8  18      ; "Ignore horizontal margins"
0036    CALL     7   2   2
0037    TSETS    7   6  10  ; "title"
0038    TSETB    6   5   1
0039    TDUP     6  19
0040    MOV      7   0
0041    KSTR     8  20      ; "Ignore vertical margins"
0042    CALL     7   2   2
0043    TSETS    7   6  10  ; "title"
0044    TSETB    6   5   2
0045    TDUP     6  21
0046    MOV      7   0
0047    KSTR     8  22      ; "Ignore horizontal padding"
0048    CALL     7   2   2
0049    TSETS    7   6  10  ; "title"
0050    TSETB    6   5   3
0051    TDUP     6  23
0052    MOV      7   0
0053    KSTR     8  24      ; "Ignore vertical padding"
0054    CALL     7   2   2
0055    TSETS    7   6  10  ; "title"
0056    TSETB    6   5   4
0057    TSETB    5   4   2
0058    TDUP     5  26
0059    MOV      6   0
0060    KSTR     7  25      ; "Page breaks and blank pages"
0061    CALL     6   2   2
0062    TSETS    6   5  10  ; "title"
0063    TDUP     6  27
0064    MOV      7   0
0065    KSTR     8  28      ; "Avoid blank page on chapter start"
0066    CALL     7   2   2
0067    TSETS    7   6  10  ; "title"
0068    TSETB    6   5   1
0069    TDUP     6  29
0070    MOV      7   0
0071    KSTR     8  30      ; "Avoid blank page on chapter end"
0072    CALL     7   2   2
0073    TSETS    7   6  10  ; "title"
0074    TSETB    6   5   2
0075    TDUP     6  31
0076    MOV      7   0
0077    KSTR     8  32      ; "Avoid publisher page breaks"
0078    CALL     7   2   2
0079    TSETS    7   6  10  ; "title"
0080    MOV      7   0
0081    KSTR     8  33      ; "Disable all publisher page breaks, keepi"~
0082    CALL     7   2   2
0083    TSETS    7   6  14  ; "description"
0084    TSETB    6   5   3
0085    TDUP     6  35
0086    MOV      7   0
0087    KSTR     8  34      ; "New page on headings"
0088    CALL     7   2   2
0089    TSETS    7   6  10  ; "title"
0090    TDUP     7  36
0091    MOV      8   0
0092    KSTR     9  37      ; "New page on <H1>"
0093    CALL     8   2   2
0094    TSETS    8   7  10  ; "title"
0095    TSETB    7   6   1
0096    TDUP     7  38
0097    MOV      8   0
0098    KSTR     9  39      ; "New page on <H2>"
0099    CALL     8   2   2
0100    TSETS    8   7  10  ; "title"
0101    TSETB    7   6   2
0102    TDUP     7  40
0103    MOV      8   0
0104    KSTR     9  41      ; "New page on <H3>"
0105    CALL     8   2   2
0106    TSETS    8   7  10  ; "title"
0107    TSETB    7   6   3
0108    TDUP     7  42
0109    MOV      8   0
0110    KSTR     9  43      ; "New page on <H4>"
0111    CALL     8   2   2
0112    TSETS    8   7  10  ; "title"
0113    TSETB    7   6   4
0114    TDUP     7  44
0115    MOV      8   0
0116    KSTR     9  45      ; "New page on <H5>"
0117    CALL     8   2   2
0118    TSETS    8   7  10  ; "title"
0119    TSETB    7   6   5
0120    TDUP     7  46
0121    MOV      8   0
0122    KSTR     9  47      ; "New page on <H6>"
0123    CALL     8   2   2
0124    TSETS    8   7  10  ; "title"
0125    TSETB    7   6   6
0126    TSETB    6   5   4
0127    TSETB    5   4   3
0128    TSETB    4   3   1
0129    TDUP     4  49
0130    MOV      5   0
0131    KSTR     6  48      ; "Text"
0132    CALL     5   2   2
0133    TSETS    5   4  10  ; "title"
0134    TDUP     5  51
0135    MOV      6   0
0136    KSTR     7  50      ; "Text alignment"
0137    CALL     6   2   2
0138    TSETS    6   5  10  ; "title"
0139    TDUP     6  52
0140    MOV      7   0
0141    KSTR     8  53      ; "Left align most text"
0142    CALL     7   2   2
0143    TSETS    7   6  10  ; "title"
0144    MOV      7   0
0145    KSTR     8  54      ; "Enforce left alignment of text in common"~
0146    CALL     7   2   2
0147    TSETS    7   6  14  ; "description"
0148    TSETB    6   5   1
0149    TDUP     6  55
0150    MOV      7   0
0151    KSTR     8  56      ; "Left align all elements"
0152    CALL     7   2   2
0153    TSETS    7   6  10  ; "title"
0154    MOV      7   0
0155    KSTR     8  57      ; "Enforce left alignment of text in all el"~
0156    CALL     7   2   2
0157    TSETS    7   6  14  ; "description"
0158    TSETB    6   5   2
0159    TDUP     6  58
0160    MOV      7   0
0161    KSTR     8  59      ; "Justify most text"
0162    CALL     7   2   2
0163    TSETS    7   6  10  ; "title"
0164    MOV      7   0
0165    KSTR     8  60      ; "Text justification is the default, but i"~
0166    CALL     7   2   2
0167    TSETS    7   6  14  ; "description"
0168    TSETB    6   5   3
0169    TDUP     6  61
0170    MOV      7   0
0171    KSTR     8  62      ; "Justify all elements"
0172    CALL     7   2   2
0173    TSETS    7   6  10  ; "title"
0174    MOV      7   0
0175    KSTR     8  63      ; "Text justification is the default, but i"~
0176    CALL     7   2   2
0177    TSETS    7   6  14  ; "description"
0178    TSETB    6   5   4
0179    TDUP     6  64
0180    MOV      7   0
0181    KSTR     8  65      ; "Center headings"
0182    CALL     7   2   2
0183    TSETS    7   6  10  ; "title"
0184    TSETB    6   5   5
0185    TSETB    5   4   1
0186    TDUP     5  67
0187    MOV      6   0
0188    KSTR     7  66      ; "Text direction"
0189    CALL     6   2   2
0190    TSETS    6   5  10  ; "title"
0191    TDUP     6  69
0192    MOV      7   0
0193    KSTR     8  68      ; "About text direction"
0194    CALL     7   2   2
0195    TSETS    7   6  10  ; "title"
0196    MOV      7   0
0197    KSTR     8  70      ; "Languages like Arabic or Hebrew use righ"~
0198    CALL     7   2   2
0199    TSETS    7   6  71  ; "info_text"
0200    TSETB    6   5   1
0201    TDUP     6  72
0202    MOV      7   0
0203    KSTR     8  73      ; "Document direction RTL"
0204    CALL     7   2   2
0205    TSETS    7   6  10  ; "title"
0206    TSETB    6   5   2
0207    TDUP     6  74
0208    MOV      7   0
0209    KSTR     8  75      ; "Right align most text"
0210    CALL     7   2   2
0211    TSETS    7   6  10  ; "title"
0212    MOV      7   0
0213    KSTR     8  76      ; "Enforce right alignment of text in commo"~
0214    CALL     7   2   2
0215    TSETS    7   6  14  ; "description"
0216    TSETB    6   5   3
0217    TDUP     6  77
0218    MOV      7   0
0219    KSTR     8  78      ; "Right align all elements"
0220    CALL     7   2   2
0221    TSETS    7   6  10  ; "title"
0222    MOV      7   0
0223    KSTR     8  79      ; "Enforce right alignment of text in all e"~
0224    CALL     7   2   2
0225    TSETS    7   6  14  ; "description"
0226    TSETB    6   5   4
0227    TDUP     6  80
0228    MOV      7   0
0229    KSTR     8  81      ; "Document direction LTR"
0230    CALL     7   2   2
0231    TSETS    7   6  10  ; "title"
0232    TSETB    6   5   5
0233    TSETB    5   4   2
0234    TDUP     5  83
0235    MOV      6   0
0236    KSTR     7  82      ; "Widows and orphans"
0237    CALL     6   2   2
0238    TSETS    6   5  10  ; "title"
0239    TDUP     6  85
0240    MOV      7   0
0241    KSTR     8  84      ; "About widow and orphan lines"
0242    CALL     7   2   2
0243    TSETS    7   6  10  ; "title"
0244    MOV      7   0
0245    KSTR     8  86      ; "Widows and orphans are lines at the begi"~
0246    CALL     7   2   2
0247    TSETS    7   6  71  ; "info_text"
0248    TSETB    6   5   1
0249    TDUP     6  87
0250    MOV      7   0
0251    KSTR     8  88      ; "Avoid widows and orphans"
0252    CALL     7   2   2
0253    TSETS    7   6  10  ; "title"
0254    MOV      7   0
0255    KSTR     8  89      ; "Avoid widow and orphan lines, allowing f"~
0256    CALL     7   2   2
0257    TSETS    7   6  14  ; "description"
0258    TSETB    6   5   2
0259    TDUP     6  90
0260    MOV      7   0
0261    KSTR     8  91      ; "Avoid widows but allow orphans"
0262    CALL     7   2   2
0263    TSETS    7   6  10  ; "title"
0264    MOV      7   0
0265    KSTR     8  92      ; "Avoid widow lines, but allow orphan line"~
0266    CALL     7   2   2
0267    TSETS    7   6  14  ; "description"
0268    TSETB    6   5   3
0269    TDUP     6  93
0270    MOV      7   0
0271    KSTR     8  94      ; "Ignore publisher orphan and widow rules"
0272    CALL     7   2   2
0273    TSETS    7   6  10  ; "title"
0274    MOV      7   0
0275    KSTR     8  95      ; "Disable orphan and widow rules specified"~
0276    CALL     7   2   2
0277    TSETS    7   6  14  ; "description"
0278    TSETB    6   5   4
0279    TSETB    5   4   3
0280    TDUP     5  96
0281    MOV      6   0
0282    KSTR     7  97      ; "Allow hyphenation on all text"
0283    CALL     6   2   2
0284    TSETS    6   5  10  ; "title"
0285    MOV      6   0
0286    KSTR     7  98      ; "Allow hyphenation on all text (except he"~
0287    CALL     6   2   2
0288    TSETS    6   5  14  ; "description"
0289    TSETB    5   4   4
0290    TDUP     5 100
0291    MOV      6   0
0292    KSTR     7  99      ; "Fonts and line heights"
0293    CALL     6   2   2
0294    TSETS    6   5  10  ; "title"
0295    TDUP     6 101
0296    MOV      7   0
0297    KSTR     8 102      ; "Ignore publisher font families"
0298    CALL     7   2   2
0299    TSETS    7   6  10  ; "title"
0300    MOV      7   0
0301    KSTR     8 103      ; "Disable font-family specified in embedde"~
0302    CALL     7   2   2
0303    TSETS    7   6  14  ; "description"
0304    TSETB    6   5   1
0305    TDUP     6 104
0306    MOV      7   0
0307    KSTR     8 105      ; "Ignore publisher font sizes"
0308    CALL     7   2   2
0309    TSETS    7   6  10  ; "title"
0310    MOV      7   0
0311    KSTR     8 106      ; "Disable font-size specified in embedded "~
0312    CALL     7   2   2
0313    TSETS    7   6  14  ; "description"
0314    TSETB    6   5   2
0315    TDUP     6 107
0316    MOV      7   0
0317    KSTR     8 108      ; "Ignore publisher line heights"
0318    CALL     7   2   2
0319    TSETS    7   6  10  ; "title"
0320    MOV      7   0
0321    KSTR     8 109      ; "Disable line-height specified in embedde"~
0322    CALL     7   2   2
0323    TSETS    7   6  14  ; "description"
0324    TSETB    6   5   3
0325    TDUP     6 110
0326    MOV      7   0
0327    KSTR     8 111      ; "Enforce steady line heights"
0328    CALL     7   2   2
0329    TSETS    7   6  10  ; "title"
0330    MOV      7   0
0331    KSTR     8 112      ; "Prevent inline content like sub- and sup"~
0332    CALL     7   2   2
0333    TSETS    7   6  14  ; "description"
0334    TSETB    6   5   4
0335    TDUP     6 113
0336    MOV      7   0
0337    KSTR     8 114      ; "Smaller sub- and superscript"
0338    CALL     7   2   2
0339    TSETS    7   6  10  ; "title"
0340    MOV      7   0
0341    KSTR     8 115      ; "Prevent sub- and superscript from affect"~
0342    CALL     7   2   2
0343    TSETS    7   6  14  ; "description"
0344    TSETB    6   5   5
0345    TSETB    5   4   5
0346    TSETB    4   3   2
0347    TDUP     4 117
0348    MOV      5   0
0349    KSTR     6 116      ; "Paragraphs"
0350    CALL     5   2   2
0351    TSETS    5   4  10  ; "title"
0352    TDUP     5 118
0353    MOV      6   0
0354    KSTR     7 119      ; "Generic web browser paragraph style"
0355    CALL     6   2   2
0356    TSETS    6   5  10  ; "title"
0357    MOV      6   0
0358    KSTR     7 120      ; "Display paragraphs as browsers do, in fu"~
0359    CALL     6   2   2
0360    TSETS    6   5  14  ; "description"
0361    TSETB    5   4   1
0362    TDUP     5 122
0363    MOV      6   0
0364    KSTR     7 121      ; "Paragraph first-line indentation"
0365    CALL     6   2   2
0366    TSETS    6   5  10  ; "title"
0367    TDUP     6 123
0368    MOV      7   0
0369    KSTR     8 124      ; "No indentation on first paragraph line"
0370    CALL     7   2   2
0371    TSETS    7   6  10  ; "title"
0372    MOV      7   0
0373    KSTR     8 125      ; "Do not indent the first line of paragrap"~
0374    CALL     7   2   2
0375    TSETS    7   6  14  ; "description"
0376    TSETB    6   5   1
0377    TDUP     6 126
0378    MOV      7   0
0379    KSTR     8 127      ; "Indentation on first paragraph line"
0380    CALL     7   2   2
0381    TSETS    7   6  10  ; "title"
0382    MOV      7   0
0383    KSTR     8 128      ; "Indentation on the first line of a parag"~
0384    CALL     7   2   2
0385    TSETS    7   6  14  ; "description"
0386    TSETB    6   5   2
0387    TDUP     6 129
0388    MOV      7   0
0389    KSTR     8 130      ; "No indentation on first paragraph"
0390    CALL     7   2   2
0391    TSETS    7   6  10  ; "title"
0392    MOV      7   0
0393    KSTR     8 131      ; "Do not indent the first line of the firs"~
0394    CALL     7   2   2
0395    TSETS    7   6  14  ; "description"
0396    TSETB    6   5   3
0397    TDUP     6 132
0398    MOV      7   0
0399    KSTR     8 133      ; "No indentation on following paragraphs"
0400    CALL     7   2   2
0401    TSETS    7   6  10  ; "title"
0402    MOV      7   0
0403    KSTR     8 134      ; "Do not indent the first line of followin"~
0404    CALL     7   2   2
0405    TSETS    7   6  14  ; "description"
0406    TSETB    6   5   4
0407    TSETB    5   4   2
0408    TDUP     5 136
0409    MOV      6   0
0410    KSTR     7 135      ; "Spacing between paragraphs"
0411    CALL     6   2   2
0412    TSETS    6   5  10  ; "title"
0413    TDUP     6 137
0414    MOV      7   0
0415    KSTR     8 135      ; "Spacing between paragraphs"
0416    CALL     7   2   2
0417    TSETS    7   6  10  ; "title"
0418    MOV      7   0
0419    KSTR     8 138      ; "Add a line of whitespace between paragra"~
0420    CALL     7   2   2
0421    TSETS    7   6  14  ; "description"
0422    TSETB    6   5   1
0423    TDUP     6 139
0424    MOV      7   0
0425    KSTR     8 140      ; "Spacing between paragraphs (half)"
0426    CALL     7   2   2
0427    TSETS    7   6  10  ; "title"
0428    MOV      7   0
0429    KSTR     8 141      ; "Add half a line of whitespace between pa"~
0430    CALL     7   2   2
0431    TSETS    7   6  14  ; "description"
0432    TSETB    6   5   2
0433    TDUP     6 142
0434    MOV      7   0
0435    KSTR     8 143      ; "No spacing between paragraphs"
0436    CALL     7   2   2
0437    TSETS    7   6  10  ; "title"
0438    MOV      7   0
0439    KSTR     8 144      ; "No whitespace between paragraphs is the "~
0440    CALL     7   2   2
0441    TSETS    7   6  14  ; "description"
0442    TSETB    6   5   3
0443    TDUP     6 145
0444    MOV      7   0
0445    KSTR     8 146      ; "Ignore vertical paragraph padding"
0446    CALL     7   2   2
0447    TSETS    7   6  10  ; "title"
0448    TSETB    6   5   4
0449    TSETB    5   4   3
0450    TDUP     5 148
0451    MOV      6   0
0452    KSTR     7 147      ; "Horizontal paragraph margins"
0453    CALL     6   2   2
0454    TSETS    6   5  10  ; "title"
0455    TDUP     6 149
0456    MOV      7   0
0457    KSTR     8 150      ; "Ignore horizontal paragraph margins"
0458    CALL     7   2   2
0459    TSETS    7   6  10  ; "title"
0460    TSETB    6   5   1
0461    TDUP     6 151
0462    MOV      7   0
0463    KSTR     8 152      ; "Ignore horizontal paragraph padding"
0464    CALL     7   2   2
0465    TSETS    7   6  10  ; "title"
0466    TSETB    6   5   2
0467    TSETB    5   4   4
0468    TDUP     5 154
0469    MOV      6   0
0470    KSTR     7 153      ; "List items"
0471    CALL     6   2   2
0472    TSETS    6   5  10  ; "title"
0473    TDUP     6 155
0474    MOV      7   0
0475    KSTR     8 156      ; "Force bullets with unordered lists"
0476    CALL     7   2   2
0477    TSETS    7   6  10  ; "title"
0478    TSETB    6   5   1
0479    TDUP     6 157
0480    MOV      7   0
0481    KSTR     8 158      ; "Force decimal numbers with ordered lists"
0482    CALL     7   2   2
0483    TSETS    7   6  10  ; "title"
0484    TSETB    6   5   2
0485    TSETB    5   4   5
0486    TSETB    4   3   3
0487    TDUP     4 160
0488    MOV      5   0
0489    KSTR     6 159      ; "Tables"
0490    CALL     5   2   2
0491    TSETS    5   4  10  ; "title"
0492    TDUP     5 161
0493    MOV      6   0
0494    KSTR     7 162      ; "Full-width tables"
0495    CALL     6   2   2
0496    TSETS    6   5  10  ; "title"
0497    MOV      6   0
0498    KSTR     7 163      ; "Make table expand to the full width of t"~
0499    CALL     6   2   2
0500    TSETS    6   5  14  ; "description"
0501    TSETB    5   4   1
0502    TDUP     5 164
0503    MOV      6   0
0504    KSTR     7 165      ; "Ignore publisher table and cell widths"
0505    CALL     6   2   2
0506    TSETS    6   5  10  ; "title"
0507    MOV      6   0
0508    KSTR     7 166      ; "Ignore table and cells widths specified "~
0509    CALL     6   2   2
0510    TSETS    6   5  14  ; "description"
0511    TSETB    5   4   2
0512    TDUP     5 167
0513    MOV      6   0
0514    KSTR     7 168      ; "Center small tables"
0515    CALL     6   2   2
0516    TSETS    6   5  10  ; "title"
0517    MOV      6   0
0518    KSTR     7 169      ; "Horizontally center tables that do not u"~
0519    CALL     6   2   2
0520    TSETS    6   5  14  ; "description"
0521    TSETB    5   4   3
0522    TDUP     5 170
0523    MOV      6   0
0524    KSTR     7 171      ; "Ignore publisher vertical alignment in t"~
0525    CALL     6   2   2
0526    TSETS    6   5  10  ; "title"
0527    TSETB    5   4   4
0528    TDUP     5 172
0529    MOV      6   0
0530    KSTR     7 173      ; "Alternate background color of table rows"
0531    CALL     6   2   2
0532    TSETS    6   5  10  ; "title"
0533    TSETB    5   4   5
0534    TDUP     5 174
0535    MOV      6   0
0536    KSTR     7 175      ; "Show borders on all tables"
0537    CALL     6   2   2
0538    TSETS    6   5  10  ; "title"
0539    TSETB    5   4   6
0540    TSETB    4   3   4
0541    TDUP     4 177
0542    MOV      5   0
0543    KSTR     6 176      ; "Links"
0544    CALL     5   2   2
0545    TSETS    5   4  10  ; "title"
0546    TDUP     5 178
0547    MOV      6   0
0548    KSTR     7 179      ; "Links always black"
0549    CALL     6   2   2
0550    TSETS    6   5  10  ; "title"
0551    TSETB    5   4   1
0552    TDUP     5 180
0553    MOV      6   0
0554    KSTR     7 181      ; "Links always blue"
0555    CALL     6   2   2
0556    TSETS    6   5  10  ; "title"
0557    TSETB    5   4   2
0558    TDUP     5 182
0559    MOV      6   0
0560    KSTR     7 183      ; "Links always bold"
0561    CALL     6   2   2
0562    TSETS    6   5  10  ; "title"
0563    TSETB    5   4   3
0564    TDUP     5 184
0565    MOV      6   0
0566    KSTR     7 185      ; "Links never bold"
0567    CALL     6   2   2
0568    TSETS    6   5  10  ; "title"
0569    TSETB    5   4   4
0570    TDUP     5 186
0571    MOV      6   0
0572    KSTR     7 187      ; "Links always underlined"
0573    CALL     6   2   2
0574    TSETS    6   5  10  ; "title"
0575    TSETB    5   4   5
0576    TDUP     5 188
0577    MOV      6   0
0578    KSTR     7 189      ; "Links never underlined"
0579    CALL     6   2   2
0580    TSETS    6   5  10  ; "title"
0581    TSETB    5   4   6
0582    TSETB    4   3   5
0583    TDUP     4 191
0584    MOV      5   0
0585    KSTR     6 190      ; "Images"
0586    CALL     5   2   2
0587    TSETS    5   4  10  ; "title"
0588    TDUP     5 192
0589    MOV      6   0
0590    KSTR     7 193      ; "Full-width images"
0591    CALL     6   2   2
0592    TSETS    6   5  10  ; "title"
0593    MOV      6   0
0594    KSTR     7 194      ; "Useful for books containing only images,"~
0595    CALL     6   2   2
0596    TSETS    6   5  14  ; "description"
0597    TSETB    5   4   1
0598    TDUP     5 195
0599    MOV      6   0
0600    KSTR     7 196      ; "Vertically center-align images relative "~
0601    CALL     6   2   2
0602    TSETS    6   5  10  ; "title"
0603    TSETB    5   4   2
0604    TSETB    4   3   6
0605    TDUP     4 198
0606    MOV      5   0
0607    KSTR     6 197      ; "Miscellaneous"
0608    CALL     5   2   2
0609    TSETS    5   4  10  ; "title"
0610    TDUP     5 200
0611    MOV      6   0
0612    KSTR     7 199      ; "Alternative TOC hints"
0613    CALL     6   2   2
0614    TSETS    6   5  10  ; "title"
0615    TDUP     6 202
0616    MOV      7   0
0617    KSTR     8 201      ; "About alternative TOC"
0618    CALL     7   2   2
0619    TSETS    7   6  10  ; "title"
0620    MOV      7   0
0621    KSTR     8 203      ; "An alternative table of contents can be "~
0622    CALL     7   2   2
0623    TSETS    7   6  71  ; "info_text"
0624    TSETB    6   5   1
0625    TDUP     6 204
0626    MOV      7   0
0627    KSTR     8 205      ; "Ignore all <H1> to <H6>"
0628    CALL     7   2   2
0629    TSETS    7   6  10  ; "title"
0630    TSETB    6   5   2
0631    TDUP     6 206
0632    MOV      7   0
0633    KSTR     8 207      ; "Ignore <H1>"
0634    CALL     7   2   2
0635    TSETS    7   6  10  ; "title"
0636    TSETB    6   5   3
0637    TDUP     6 208
0638    MOV      7   0
0639    KSTR     8 209      ; "Ignore <H2>"
0640    CALL     7   2   2
0641    TSETS    7   6  10  ; "title"
0642    TSETB    6   5   4
0643    TDUP     6 210
0644    MOV      7   0
0645    KSTR     8 211      ; "Ignore <H3>"
0646    CALL     7   2   2
0647    TSETS    7   6  10  ; "title"
0648    TSETB    6   5   5
0649    TDUP     6 212
0650    MOV      7   0
0651    KSTR     8 213      ; "Ignore <H4>"
0652    CALL     7   2   2
0653    TSETS    7   6  10  ; "title"
0654    TSETB    6   5   6
0655    TDUP     6 214
0656    MOV      7   0
0657    KSTR     8 215      ; "Ignore <H5>"
0658    CALL     7   2   2
0659    TSETS    7   6  10  ; "title"
0660    TSETB    6   5   7
0661    TDUP     6 216
0662    MOV      7   0
0663    KSTR     8 217      ; "Ignore <H6>"
0664    CALL     7   2   2
0665    TSETS    7   6  10  ; "title"
0666    TSETB    6   5   8
0667    TDUP     6 218
0668    MOV      7   0
0669    KSTR     8 219      ; "Example of book specific TOC hints"
0670    CALL     7   2   2
0671    TSETS    7   6  10  ; "title"
0672    MOV      7   0
0673    KSTR     8 220      ; "If headings or document fragments do not"~
0674    CALL     7   2   2
0675    TSETS    7   6  14  ; "description"
0676    TSETB    6   5   9
0677    TSETB    5   4   1
0678    TDUP     5 222
0679    MOV      6   0
0680    KSTR     7 221      ; "In-page footnotes"
0681    CALL     6   2   2
0682    TSETS    6   5  10  ; "title"
0683    TDUP     6 224
0684    MOV      7   0
0685    KSTR     8 223      ; "In-page FB2 footnotes"
0686    CALL     7   2   2
0687    TSETS    7   6  10  ; "title"
0688    TDUP     7 225
0689    MOV      8   0
0690    KSTR     9 223      ; "In-page FB2 footnotes"
0691    CALL     8   2   2
0692    TSETS    8   7  10  ; "title"
0693    MOV      8   0
0694    KSTR     9 226      ; "Show FB2 footnote text at the bottom of "~
0695    CALL     8   2   2
0696    TSETS    8   7  14  ; "description"
0697    TSETB    7   6   1
0698    TDUP     7 227
0699    MOV      8   0
0700    KSTR     9 228      ; "In-page FB2 endnotes"
0701    CALL     8   2   2
0702    TSETS    8   7  10  ; "title"
0703    MOV      8   0
0704    KSTR     9 229      ; "Show FB2 endnote text at the bottom of p"~
0705    CALL     8   2   2
0706    TSETS    8   7  14  ; "description"
0707    TSETB    7   6   2
0708    TDUP     7 230
0709    MOV      8   0
0710    KSTR     9 231      ; "Keep regular font size"
0711    CALL     8   2   2
0712    TSETS    8   7  10  ; "title"
0713    MOV      8   0
0714    KSTR     9 232      ; "FB2 footnotes and endnotes get a smaller"~
0715    CALL     8   2   2
0716    TSETS    8   7  14  ; "description"
0717    TSETB    7   6   3
0718    TSETB    6   5   1
0719    TDUP     6 233
0720    MOV      7   0
0721    KSTR     8 234      ; "In-page EPUB footnotes"
0722    CALL     7   2   2
0723    TSETS    7   6  10  ; "title"
0724    MOV      7   0
0725    KSTR     8 235      ; "Show EPUB footnote text at the bottom of"~
0726    CALL     7   2   2
0727    TSETS    7   6  14  ; "description"
0728    TSETB    6   5   2
0729    TDUP     6 236
0730    MOV      7   0
0731    KSTR     8 237      ; "In-page EPUB footnotes (smaller)"
0732    CALL     7   2   2
0733    TSETS    7   6  10  ; "title"
0734    MOV      7   0
0735    KSTR     8 235      ; "Show EPUB footnote text at the bottom of"~
0736    CALL     7   2   2
0737    TSETS    7   6  14  ; "description"
0738    TSETB    6   5   3
0739    TDUP     6 238
0740    MOV      7   0
0741    KSTR     8 239      ; "In-page Wikipedia footnotes"
0742    CALL     7   2   2
0743    TSETS    7   6  10  ; "title"
0744    MOV      7   0
0745    KSTR     8 240      ; "Show footnotes at the bottom of pages in"~
0746    CALL     7   2   2
0747    TSETS    7   6  14  ; "description"
0748    TSETB    6   5   4
0749    TDUP     6 241
0750    MOV      7   0
0751    KSTR     8 242      ; "In-page Wikipedia footnotes (smaller)"
0752    CALL     7   2   2
0753    TSETS    7   6  10  ; "title"
0754    MOV      7   0
0755    KSTR     8 240      ; "Show footnotes at the bottom of pages in"~
0756    CALL     7   2   2
0757    TSETS    7   6  14  ; "description"
0758    TSETB    6   5   5
0759    TDUP     6 243
0760    MOV      7   0
0761    KSTR     8 244      ; "In-page classic classname footnotes"
0762    CALL     7   2   2
0763    TSETS    7   6  10  ; "title"
0764    MOV      7   0
0765    KSTR     8 245      ; "Show footnotes with classic class names "~
0766    CALL     7   2   2
0767    TSETS    7   6  14  ; "description"
0768    TSETB    6   5   6
0769    TDUP     6 246
0770    MOV      7   0
0771    KSTR     8 247      ; "In-page classic classname footnotes (sma"~
0772    CALL     7   2   2
0773    TSETS    7   6  10  ; "title"
0774    MOV      7   0
0775    KSTR     8 248      ; "Show footnotes with classic classname at"~
0776    CALL     7   2   2
0777    TSETS    7   6  14  ; "description"
0778    TSETB    6   5   7
0779    TSETB    5   4   2
0780    TDUP     5 249
0781    MOV      6   0
0782    KSTR     7 250      ; "Toggle alternative EPUB content"
0783    CALL     6   2   2
0784    TSETS    6   5  10  ; "title"
0785    MOV      6   0
0786    KSTR     7 251      ; "The EPUB3 format allows a\n<epub:switch>"~
0787    CALL     6   2   2
0788    TSETS    6   5  14  ; "description"
0789    TSETB    5   4   3
0790    TDUP     5 252
0791    MOV      6   0
0792    KSTR     7 253      ; "Pure black and white"
0793    CALL     6   2   2
0794    TSETS    6   5  10  ; "title"
0795    MOV      6   0
0796    KSTR     7 254      ; "Enforce black text and borders, and remo"~
0797    CALL     6   2   2
0798    TSETS    6   5  14  ; "description"
0799    TSETB    5   4   4
0800    TSETB    4   3   7
0801    RET1     3   2

