
main <./plugins/newsdownloader.koplugin/lib/dateparser.lua:0,0> (144 instructions, 576 bytes at 0x7f9673c06900)
0+ params, 22 slots, 0 upvalues, 21 locals, 101 constants, 7 functions
	1	[1]	GETGLOBAL	0 -1	; os
	2	[1]	GETTABLE 	0 0 -2	; "difftime"
	3	[1]	GETGLOBAL	1 -1	; os
	4	[1]	GETTABLE 	1 1 -3	; "time"
	5	[1]	GETGLOBAL	2 -1	; os
	6	[1]	GETTABLE 	2 2 -4	; "date"
	7	[2]	GETGLOBAL	3 -5	; string
	8	[2]	GETTABLE 	3 3 -6	; "format"
	9	[3]	GETGLOBAL	4 -7	; table
	10	[3]	GETTABLE 	4 4 -8	; "remove"
	11	[3]	GETGLOBAL	5 -7	; table
	12	[3]	GETTABLE 	5 5 -9	; "insert"
	13	[4]	GETGLOBAL	6 -10	; pcall
	14	[4]	GETGLOBAL	7 -11	; pairs
	15	[4]	GETGLOBAL	8 -12	; ipairs
	16	[4]	GETGLOBAL	9 -13	; tostring
	17	[4]	GETGLOBAL	10 -14	; tonumber
	18	[4]	GETGLOBAL	11 -15	; type
	19	[4]	GETGLOBAL	12 -16	; setmetatable
	20	[6]	NEWTABLE 	13 0 0
	21	[9]	LOADNIL  	14 14
	22	[11]	MOVE     	15 1
	23	[11]	CALL     	15 1 2
	24	[12]	MOVE     	16 0
	25	[12]	MOVE     	17 1
	26	[12]	MOVE     	18 2
	27	[12]	LOADK    	19 -17	; "!*t"
	28	[12]	MOVE     	20 15
	29	[12]	CALL     	18 3 0
	30	[12]	CALL     	17 0 2
	31	[12]	MOVE     	18 1
	32	[12]	MOVE     	19 2
	33	[12]	LOADK    	20 -18	; "*t"
	34	[12]	MOVE     	21 15
	35	[12]	CALL     	19 3 0
	36	[12]	CALL     	18 0 0
	37	[12]	CALL     	16 0 2
	38	[17]	CLOSURE  	14 0	; 0x7f9673c06e20
	39	[17]	MOVE     	0 6
	40	[17]	MOVE     	0 1
	41	[17]	MOVE     	0 16
	42	[17]	CLOSE    	15
	43	[20]	NEWTABLE 	15 0 0
	44	[21]	MOVE     	16 12
	45	[21]	NEWTABLE 	17 0 0
	46	[21]	NEWTABLE 	18 0 1
	47	[21]	SETTABLE 	18 -19 -20	; "__mode" "v"
	48	[21]	CALL     	16 3 2
	49	[39]	CLOSURE  	17 1	; 0x7f9673c075c0
	50	[39]	MOVE     	0 11
	51	[39]	MOVE     	0 8
	52	[39]	MOVE     	0 16
	53	[39]	MOVE     	0 5
	54	[39]	MOVE     	0 15
	55	[24]	SETTABLE 	13 -21 17	; "register_format" -
	56	[45]	CLOSURE  	17 2	; 0x7f9673c07a30
	57	[45]	MOVE     	0 11
	58	[45]	MOVE     	0 15
	59	[42]	SETTABLE 	13 -22 17	; "unregister_format" -
	60	[50]	CLOSURE  	17 3	; 0x7f9673c07d90
	61	[50]	MOVE     	0 15
	62	[48]	SETTABLE 	13 -23 17	; "get_format_function" -
	63	[68]	CLOSURE  	17 4	; 0x7f9673c08230
	64	[68]	MOVE     	0 15
	65	[68]	MOVE     	0 9
	66	[68]	MOVE     	0 6
	67	[68]	MOVE     	0 8
	68	[68]	MOVE     	0 16
	69	[56]	SETTABLE 	13 -24 17	; "parse" -
	70	[70]	GETTABLE 	17 13 -21	; "register_format"
	71	[70]	LOADK    	18 -25	; "W3CDTF"
	72	[124]	CLOSURE  	19 5	; 0x7f9673c085a0
	73	[124]	MOVE     	0 10
	74	[124]	MOVE     	0 14
	75	[70]	CALL     	17 3 1
	76	[128]	NEWTABLE 	17 0 25
	77	[129]	SETTABLE 	17 -26 -27	; "A" 1
	78	[129]	SETTABLE 	17 -28 -29	; "B" 2
	79	[129]	SETTABLE 	17 -30 -31	; "C" 3
	80	[129]	SETTABLE 	17 -32 -33	; "D" 4
	81	[129]	SETTABLE 	17 -34 -35	; "E" 5
	82	[129]	SETTABLE 	17 -36 -37	; "F" 6
	83	[129]	SETTABLE 	17 -38 -39	; "G" 7
	84	[129]	SETTABLE 	17 -40 -41	; "H" 8
	85	[129]	SETTABLE 	17 -42 -43	; "I" 9
	86	[130]	SETTABLE 	17 -44 -45	; "K" 10
	87	[130]	SETTABLE 	17 -46 -47	; "L" 11
	88	[130]	SETTABLE 	17 -48 -49	; "M" 12
	89	[130]	SETTABLE 	17 -50 -51	; "N" -1
	90	[130]	SETTABLE 	17 -52 -53	; "O" -2
	91	[130]	SETTABLE 	17 -54 -55	; "P" -3
	92	[130]	SETTABLE 	17 -56 -57	; "Q" -4
	93	[130]	SETTABLE 	17 -58 -59	; "R" -5
	94	[131]	SETTABLE 	17 -60 -61	; "S" -6
	95	[131]	SETTABLE 	17 -62 -63	; "T" -7
	96	[131]	SETTABLE 	17 -64 -65	; "U" -8
	97	[131]	SETTABLE 	17 -66 -67	; "V" -9
	98	[131]	SETTABLE 	17 -68 -69	; "W" -10
	99	[131]	SETTABLE 	17 -70 -71	; "X" -11
	100	[131]	SETTABLE 	17 -72 -73	; "Y" -12
	101	[132]	SETTABLE 	17 -74 -75	; "Z" 0
	102	[134]	SETTABLE 	17 -76 -59	; "EST" -5
	103	[134]	SETTABLE 	17 -77 -57	; "EDT" -4
	104	[134]	SETTABLE 	17 -78 -61	; "CST" -6
	105	[134]	SETTABLE 	17 -79 -59	; "CDT" -5
	106	[135]	SETTABLE 	17 -80 -63	; "MST" -7
	107	[135]	SETTABLE 	17 -81 -61	; "MDT" -6
	108	[135]	SETTABLE 	17 -82 -65	; "PST" -8
	109	[135]	SETTABLE 	17 -83 -63	; "PDT" -7
	110	[137]	SETTABLE 	17 -84 -75	; "GMT" 0
	111	[137]	SETTABLE 	17 -85 -75	; "UT" 0
	112	[137]	SETTABLE 	17 -86 -75	; "UTC" 0
	113	[140]	NEWTABLE 	18 0 12
	114	[140]	SETTABLE 	18 -87 -27	; "Jan" 1
	115	[140]	SETTABLE 	18 -88 -29	; "Feb" 2
	116	[140]	SETTABLE 	18 -89 -31	; "Mar" 3
	117	[140]	SETTABLE 	18 -90 -33	; "Apr" 4
	118	[140]	SETTABLE 	18 -91 -35	; "May" 5
	119	[140]	SETTABLE 	18 -92 -37	; "Jun" 6
	120	[140]	SETTABLE 	18 -93 -39	; "Jul" 7
	121	[140]	SETTABLE 	18 -94 -41	; "Aug" 8
	122	[140]	SETTABLE 	18 -95 -43	; "Sep" 9
	123	[140]	SETTABLE 	18 -96 -45	; "Oct" 10
	124	[140]	SETTABLE 	18 -97 -47	; "Nov" 11
	125	[140]	SETTABLE 	18 -98 -49	; "Dec" 12
	126	[142]	GETTABLE 	19 13 -21	; "register_format"
	127	[142]	LOADK    	20 -99	; "RFC2822"
	128	[185]	CLOSURE  	21 6	; 0x7f9673c08e00
	129	[185]	MOVE     	0 18
	130	[185]	MOVE     	0 17
	131	[185]	MOVE     	0 10
	132	[185]	MOVE     	0 14
	133	[142]	CALL     	19 3 1
	134	[185]	CLOSE    	17
	135	[188]	GETTABLE 	17 13 -21	; "register_format"
	136	[188]	LOADK    	18 -100	; "RFC822"
	137	[188]	GETTABLE 	19 15 -99	; "RFC2822"
	138	[188]	CALL     	17 3 1
	139	[189]	GETTABLE 	17 13 -21	; "register_format"
	140	[189]	LOADK    	18 -101	; "RFC3339"
	141	[189]	GETTABLE 	19 15 -25	; "W3CDTF"
	142	[189]	CALL     	17 3 1
	143	[192]	RETURN   	13 2
	144	[192]	RETURN   	0 1

function <./plugins/newsdownloader.koplugin/lib/dateparser.lua:13,17> (20 instructions, 80 bytes at 0x7f9673c06e20)
2 params, 7 slots, 3 upvalues, 4 locals, 2 constants, 0 functions
	1	[14]	GETUPVAL 	2 0	; pcall
	2	[14]	GETUPVAL 	3 1	; time
	3	[14]	MOVE     	4 0
	4	[14]	CALL     	2 3 3
	5	[15]	TEST     	2 0 0
	6	[15]	JMP      	2	; to 9
	7	[15]	TEST     	3 0 1
	8	[15]	JMP      	7	; to 16
	9	[15]	LOADNIL  	4 4
	10	[15]	LOADK    	5 -1	; "invalid date. os.time says: "
	11	[15]	TESTSET  	6 3 1
	12	[15]	JMP      	1	; to 14
	13	[15]	LOADK    	6 -2	; "nothing"
	14	[15]	CONCAT   	5 5 6
	15	[15]	RETURN   	4 3
	16	[16]	GETUPVAL 	4 2	; local_UTC_offset_sec
	17	[16]	SUB      	4 3 4
	18	[16]	SUB      	4 4 1
	19	[16]	RETURN   	4 2
	20	[17]	RETURN   	0 1

function <./plugins/newsdownloader.koplugin/lib/dateparser.lua:24,39> (35 instructions, 140 bytes at 0x7f9673c075c0)
2 params, 9 slots, 5 upvalues, 8 locals, 3 constants, 0 functions
	1	[25]	GETUPVAL 	2 0	; type
	2	[25]	MOVE     	3 0
	3	[25]	CALL     	2 2 2
	4	[25]	EQ       	0 2 -1	; - "string"
	5	[25]	JMP      	5	; to 11
	6	[25]	GETUPVAL 	2 0	; type
	7	[25]	MOVE     	3 1
	8	[25]	CALL     	2 2 2
	9	[25]	EQ       	1 2 -2	; - "function"
	10	[25]	JMP      	3	; to 14
	11	[25]	LOADNIL  	2 2
	12	[25]	LOADK    	3 -3	; "improper arguments, can't register format handler"
	13	[25]	RETURN   	2 3
	14	[27]	LOADNIL  	2 2
	15	[28]	GETUPVAL 	3 1	; ipairs
	16	[28]	GETUPVAL 	4 2	; format_func
	17	[28]	CALL     	3 2 4
	18	[28]	JMP      	4	; to 23
	19	[29]	EQ       	0 7 1
	20	[29]	JMP      	2	; to 23
	21	[30]	LOADBOOL 	2 1 0
	22	[31]	JMP      	2	; to 25
	23	[28]	TFORLOOP 	3 2
	24	[32]	JMP      	-6	; to 19
	25	[34]	TEST     	2 0 1
	26	[34]	JMP      	4	; to 31
	27	[35]	GETUPVAL 	3 3	; tinsert
	28	[35]	GETUPVAL 	4 2	; format_func
	29	[35]	MOVE     	5 1
	30	[35]	CALL     	3 3 1
	31	[37]	GETUPVAL 	3 4	; formats
	32	[37]	SETTABLE 	3 0 1
	33	[38]	LOADBOOL 	3 1 0
	34	[38]	RETURN   	3 2
	35	[39]	RETURN   	0 1

function <./plugins/newsdownloader.koplugin/lib/dateparser.lua:42,45> (11 instructions, 44 bytes at 0x7f9673c07a30)
1 param, 3 slots, 2 upvalues, 1 local, 3 constants, 0 functions
	1	[43]	GETUPVAL 	1 0	; type
	2	[43]	MOVE     	2 0
	3	[43]	CALL     	1 2 2
	4	[43]	EQ       	1 1 -1	; - "string"
	5	[43]	JMP      	3	; to 9
	6	[43]	LOADNIL  	1 1
	7	[43]	LOADK    	2 -2	; "format name must be a string"
	8	[43]	RETURN   	1 3
	9	[44]	GETUPVAL 	1 1	; formats
	10	[44]	SETTABLE 	1 0 -3	; - nil
	11	[45]	RETURN   	0 1

function <./plugins/newsdownloader.koplugin/lib/dateparser.lua:48,50> (11 instructions, 44 bytes at 0x7f9673c07d90)
1 param, 5 slots, 1 upvalue, 1 local, 2 constants, 0 functions
	1	[49]	GETUPVAL 	1 0	; formats
	2	[49]	GETTABLE 	1 1 0
	3	[49]	TEST     	1 0 1
	4	[49]	JMP      	1	; to 6
	5	[49]	LOADNIL  	1 1
	6	[49]	LOADK    	2 -1	; "format %s not registered"
	7	[49]	SELF     	2 2 -2	; "format"
	8	[49]	MOVE     	4 0
	9	[49]	CALL     	2 3 0
	10	[49]	RETURN   	1 0
	11	[50]	RETURN   	0 1

function <./plugins/newsdownloader.koplugin/lib/dateparser.lua:56,68> (42 instructions, 168 bytes at 0x7f9673c08230)
2 params, 13 slots, 5 upvalues, 10 locals, 1 constant, 0 functions
	1	[58]	TEST     	1 0 0
	2	[58]	JMP      	18	; to 21
	3	[59]	GETUPVAL 	5 0	; formats
	4	[59]	GETTABLE 	5 5 1
	5	[59]	TEST     	5 0 1
	6	[59]	JMP      	6	; to 13
	7	[59]	LOADK    	5 -1	; "unknown date format: "
	8	[59]	GETUPVAL 	6 1	; tostring
	9	[59]	MOVE     	7 1
	10	[59]	CALL     	6 2 2
	11	[59]	CONCAT   	5 5 6
	12	[59]	RETURN   	5 2
	13	[60]	GETUPVAL 	5 2	; pcall
	14	[60]	GETUPVAL 	6 0	; formats
	15	[60]	GETTABLE 	6 6 1
	16	[60]	MOVE     	7 0
	17	[60]	CALL     	5 3 3
	18	[60]	MOVE     	3 6
	19	[60]	MOVE     	2 5
	20	[60]	JMP      	17	; to 38
	21	[62]	GETUPVAL 	5 3	; ipairs
	22	[62]	GETUPVAL 	6 4	; format_func
	23	[62]	CALL     	5 2 4
	24	[62]	JMP      	11	; to 36
	25	[63]	GETUPVAL 	10 2	; pcall
	26	[63]	MOVE     	11 9
	27	[63]	MOVE     	12 0
	28	[63]	CALL     	10 3 3
	29	[63]	MOVE     	3 11
	30	[63]	MOVE     	2 10
	31	[64]	TEST     	2 0 0
	32	[64]	JMP      	3	; to 36
	33	[64]	TEST     	3 0 0
	34	[64]	JMP      	1	; to 36
	35	[64]	RETURN   	3 2
	36	[62]	TFORLOOP 	5 2
	37	[64]	JMP      	-13	; to 25
	38	[67]	TESTSET  	5 2 0
	39	[67]	JMP      	1	; to 41
	40	[67]	MOVE     	5 3
	41	[67]	RETURN   	5 2
	42	[68]	RETURN   	0 1

function <./plugins/newsdownloader.koplugin/lib/dateparser.lua:70,124> (162 instructions, 648 bytes at 0x7f9673c085a0)
1 param, 20 slots, 2 upvalues, 19 locals, 30 constants, 0 functions
	1	[77]	SELF     	12 0 -1	; "match"
	2	[77]	LOADK    	14 -2	; "^(%d%d%d%d)%-?(.*)$"
	3	[77]	CALL     	12 3 3
	4	[77]	MOVE     	0 13
	5	[77]	MOVE     	1 12
	6	[79]	SELF     	12 0 -1	; "match"
	7	[79]	LOADK    	14 -3	; "^(%d%d%d)%-?(.*)$"
	8	[79]	CALL     	12 3 3
	9	[79]	MOVE     	11 13
	10	[79]	MOVE     	2 12
	11	[81]	TEST     	2 0 0
	12	[81]	JMP      	1	; to 14
	13	[81]	MOVE     	0 11
	14	[83]	SELF     	12 0 -1	; "match"
	15	[83]	LOADK    	14 -4	; "^(%d%d)%-?(.*)$"
	16	[83]	CALL     	12 3 3
	17	[83]	MOVE     	0 13
	18	[83]	MOVE     	3 12
	19	[85]	SELF     	12 0 -1	; "match"
	20	[85]	LOADK    	14 -5	; "^(%d%d)(.*)$"
	21	[85]	CALL     	12 3 3
	22	[85]	MOVE     	0 13
	23	[85]	MOVE     	4 12
	24	[86]	LEN      	12 0
	25	[86]	LT       	0 -6 12	; 0 -
	26	[86]	JMP      	63	; to 90
	27	[87]	SELF     	12 0 -1	; "match"
	28	[87]	LOADK    	14 -7	; "^T(.*)$"
	29	[87]	CALL     	12 3 2
	30	[87]	MOVE     	0 12
	31	[88]	SELF     	12 0 -1	; "match"
	32	[88]	LOADK    	14 -8	; "^([0-2][0-9]):?(.*)$"
	33	[88]	CALL     	12 3 3
	34	[88]	MOVE     	0 13
	35	[88]	MOVE     	6 12
	36	[89]	SELF     	12 0 -1	; "match"
	37	[89]	LOADK    	14 -9	; "^([0-6][0-9]):?(.*)$"
	38	[89]	CALL     	12 3 3
	39	[89]	MOVE     	0 13
	40	[89]	MOVE     	7 12
	41	[90]	SELF     	12 0 -1	; "match"
	42	[90]	LOADK    	14 -10	; "^([0-6][0-9])(.*)$"
	43	[90]	CALL     	12 3 3
	44	[90]	MOVE     	0 13
	45	[90]	MOVE     	8 12
	46	[91]	SELF     	12 0 -1	; "match"
	47	[91]	LOADK    	14 -11	; "^%.(%d+)(.*)$"
	48	[91]	CALL     	12 3 3
	49	[91]	MOVE     	11 13
	50	[91]	MOVE     	9 12
	51	[92]	TEST     	9 0 0
	52	[92]	JMP      	1	; to 54
	53	[93]	MOVE     	0 11
	54	[95]	EQ       	0 0 -12	; - "Z"
	55	[95]	JMP      	3	; to 59
	56	[96]	LOADK    	0 -13	; ""
	57	[97]	LOADK    	10 -6	; 0
	58	[97]	JMP      	26	; to 85
	59	[99]	LOADNIL  	12 14
	60	[100]	SELF     	15 0 -1	; "match"
	61	[100]	LOADK    	17 -14	; "^([+-])(%d%d)%:?(.*)$"
	62	[100]	CALL     	15 3 4
	63	[100]	MOVE     	0 17
	64	[100]	MOVE     	13 16
	65	[100]	MOVE     	12 15
	66	[101]	SELF     	15 0 -1	; "match"
	67	[101]	LOADK    	17 -5	; "^(%d%d)(.*)$"
	68	[101]	CALL     	15 3 3
	69	[102]	TEST     	15 0 0
	70	[102]	JMP      	1	; to 72
	71	[102]	MOVE     	0 16
	72	[103]	GETUPVAL 	17 0	; tonumber
	73	[103]	MOVE     	18 12
	74	[103]	MOVE     	19 13
	75	[103]	CONCAT   	18 18 19
	76	[103]	CALL     	17 2 2
	77	[103]	GETUPVAL 	18 0	; tonumber
	78	[103]	MOVE     	19 15
	79	[103]	CALL     	18 2 2
	80	[103]	TEST     	18 0 1
	81	[103]	JMP      	1	; to 83
	82	[103]	LOADK    	18 -6	; 0
	83	[103]	DIV      	18 18 -15	; - 60
	84	[103]	ADD      	10 17 18
	85	[105]	LEN      	12 0
	86	[105]	LT       	0 -6 12	; 0 -
	87	[105]	JMP      	2	; to 90
	88	[105]	LOADNIL  	12 12
	89	[105]	RETURN   	12 2
	90	[108]	GETUPVAL 	12 0	; tonumber
	91	[108]	MOVE     	13 1
	92	[108]	CALL     	12 2 2
	93	[108]	MOVE     	1 12
	94	[109]	NEWTABLE 	12 0 7
	95	[110]	TESTSET  	13 1 0
	96	[110]	JMP      	10	; to 107
	97	[110]	LT       	0 -17 1	; 100 -
	98	[110]	JMP      	2	; to 101
	99	[110]	TESTSET  	13 1 1
	100	[110]	JMP      	6	; to 107
	101	[110]	LT       	0 1 -18	; - 50
	102	[110]	JMP      	3	; to 106
	103	[110]	ADD      	13 1 -19	; - 2000
	104	[110]	TEST     	13 0 1
	105	[110]	JMP      	1	; to 107
	106	[110]	ADD      	13 1 -20	; - 1900
	107	[110]	SETTABLE 	12 -16 13	; "year" -
	108	[111]	GETUPVAL 	13 0	; tonumber
	109	[111]	MOVE     	14 3
	110	[111]	CALL     	13 2 2
	111	[111]	TEST     	13 0 1
	112	[111]	JMP      	1	; to 114
	113	[111]	LOADK    	13 -22	; 1
	114	[111]	SETTABLE 	12 -21 13	; "month" -
	115	[112]	GETUPVAL 	13 0	; tonumber
	116	[112]	MOVE     	14 4
	117	[112]	CALL     	13 2 2
	118	[112]	TEST     	13 0 1
	119	[112]	JMP      	1	; to 121
	120	[112]	LOADK    	13 -22	; 1
	121	[112]	SETTABLE 	12 -23 13	; "day" -
	122	[113]	GETUPVAL 	13 0	; tonumber
	123	[113]	MOVE     	14 6
	124	[113]	CALL     	13 2 2
	125	[113]	TEST     	13 0 1
	126	[113]	JMP      	1	; to 128
	127	[113]	LOADK    	13 -6	; 0
	128	[113]	SETTABLE 	12 -24 13	; "hour" -
	129	[114]	GETUPVAL 	13 0	; tonumber
	130	[114]	MOVE     	14 7
	131	[114]	CALL     	13 2 2
	132	[114]	TEST     	13 0 1
	133	[114]	JMP      	1	; to 135
	134	[114]	LOADK    	13 -6	; 0
	135	[114]	SETTABLE 	12 -25 13	; "min" -
	136	[115]	GETUPVAL 	13 0	; tonumber
	137	[115]	MOVE     	14 8
	138	[115]	CALL     	13 2 2
	139	[115]	TEST     	13 0 1
	140	[115]	JMP      	1	; to 142
	141	[115]	LOADK    	13 -6	; 0
	142	[115]	SETTABLE 	12 -26 13	; "sec" -
	143	[116]	SETTABLE 	12 -27 -28	; "isdst" false
	144	[118]	GETUPVAL 	13 1	; unix_timestamp
	145	[118]	MOVE     	14 12
	146	[118]	TESTSET  	15 10 1
	147	[118]	JMP      	1	; to 149
	148	[118]	LOADK    	15 -6	; 0
	149	[118]	MUL      	15 15 -29	; - 3600
	150	[118]	CALL     	13 3 2
	151	[119]	TEST     	9 0 0
	152	[119]	JMP      	8	; to 161
	153	[120]	GETUPVAL 	14 0	; tonumber
	154	[120]	LOADK    	15 -30	; "0."
	155	[120]	MOVE     	16 9
	156	[120]	CONCAT   	15 15 16
	157	[120]	CALL     	14 2 2
	158	[120]	ADD      	14 13 14
	159	[120]	RETURN   	14 2
	160	[120]	JMP      	1	; to 162
	161	[122]	RETURN   	13 2
	162	[124]	RETURN   	0 1

function <./plugins/newsdownloader.koplugin/lib/dateparser.lua:142,185> (141 instructions, 564 bytes at 0x7f9673c08e00)
1 param, 21 slots, 4 upvalues, 18 locals, 25 constants, 0 functions
	1	[149]	SELF     	13 0 -1	; "match"
	2	[149]	LOADK    	15 -2	; "^(%w%w%w),%s+(.*)$"
	3	[149]	CALL     	13 3 3
	4	[149]	MOVE     	12 14
	5	[149]	MOVE     	6 13
	6	[150]	TEST     	6 0 0
	7	[150]	JMP      	1	; to 9
	8	[150]	MOVE     	0 12
	9	[151]	SELF     	13 0 -1	; "match"
	10	[151]	LOADK    	15 -3	; "^(%d%d?)%s+(.*)$"
	11	[151]	CALL     	13 3 3
	12	[151]	MOVE     	0 14
	13	[151]	MOVE     	3 13
	14	[152]	SELF     	13 0 -1	; "match"
	15	[152]	LOADK    	15 -4	; "^(%w%w%w)%s+(.*)$"
	16	[152]	CALL     	13 3 3
	17	[152]	MOVE     	0 14
	18	[152]	MOVE     	2 13
	19	[153]	GETUPVAL 	13 0	; month_val
	20	[153]	GETTABLE 	2 13 2
	21	[154]	SELF     	13 0 -1	; "match"
	22	[154]	LOADK    	15 -5	; "^(%d%d%d?%d?)%s+(.*)$"
	23	[154]	CALL     	13 3 3
	24	[154]	MOVE     	0 14
	25	[154]	MOVE     	1 13
	26	[155]	SELF     	13 0 -1	; "match"
	27	[155]	LOADK    	15 -6	; "^(%d%d?):(.*)$"
	28	[155]	CALL     	13 3 3
	29	[155]	MOVE     	0 14
	30	[155]	MOVE     	7 13
	31	[156]	SELF     	13 0 -1	; "match"
	32	[156]	LOADK    	15 -7	; "^(%d%d?)(.*)$"
	33	[156]	CALL     	13 3 3
	34	[156]	MOVE     	0 14
	35	[156]	MOVE     	8 13
	36	[157]	SELF     	13 0 -1	; "match"
	37	[157]	LOADK    	15 -8	; "^:(%d%d)(.*)$"
	38	[157]	CALL     	13 3 3
	39	[157]	MOVE     	12 14
	40	[157]	MOVE     	9 13
	41	[158]	TEST     	9 0 0
	42	[158]	JMP      	1	; to 44
	43	[158]	MOVE     	0 12
	44	[159]	LOADNIL  	13 16
	45	[160]	SELF     	17 0 -1	; "match"
	46	[160]	LOADK    	19 -9	; "^%s+(%u+)(.*)$"
	47	[160]	CALL     	17 3 3
	48	[160]	MOVE     	12 18
	49	[160]	MOVE     	13 17
	50	[161]	TEST     	13 0 0
	51	[161]	JMP      	4	; to 56
	52	[162]	MOVE     	0 12
	53	[163]	GETUPVAL 	17 1	; tz_table
	54	[163]	GETTABLE 	11 17 13
	55	[163]	JMP      	20	; to 76
	56	[165]	SELF     	17 0 -1	; "match"
	57	[165]	LOADK    	19 -10	; "^%s+([+-])(%d%d)(%d%d)%s*(.*)$"
	58	[165]	CALL     	17 3 5
	59	[165]	MOVE     	0 20
	60	[165]	MOVE     	16 19
	61	[165]	MOVE     	15 18
	62	[165]	MOVE     	14 17
	63	[166]	GETUPVAL 	17 2	; tonumber
	64	[166]	MOVE     	18 14
	65	[166]	MOVE     	19 15
	66	[166]	CONCAT   	18 18 19
	67	[166]	CALL     	17 2 2
	68	[166]	GETUPVAL 	18 2	; tonumber
	69	[166]	MOVE     	19 16
	70	[166]	CALL     	18 2 2
	71	[166]	TEST     	18 0 1
	72	[166]	JMP      	1	; to 74
	73	[166]	LOADK    	18 -11	; 0
	74	[166]	DIV      	18 18 -12	; - 60
	75	[166]	ADD      	11 17 18
	76	[169]	LEN      	17 0
	77	[169]	LT       	1 -11 17	; 0 -
	78	[169]	JMP      	10	; to 89
	79	[169]	TEST     	1 0 0
	80	[169]	JMP      	8	; to 89
	81	[169]	TEST     	3 0 0
	82	[169]	JMP      	6	; to 89
	83	[169]	TEST     	2 0 0
	84	[169]	JMP      	4	; to 89
	85	[169]	TEST     	7 0 0
	86	[169]	JMP      	2	; to 89
	87	[169]	TEST     	8 0 1
	88	[169]	JMP      	2	; to 91
	89	[170]	LOADNIL  	17 17
	90	[170]	RETURN   	17 2
	91	[173]	GETUPVAL 	17 2	; tonumber
	92	[173]	MOVE     	18 1
	93	[173]	CALL     	17 2 2
	94	[173]	MOVE     	1 17
	95	[174]	NEWTABLE 	17 0 7
	96	[175]	TESTSET  	18 1 0
	97	[175]	JMP      	10	; to 108
	98	[175]	LT       	0 -14 1	; 100 -
	99	[175]	JMP      	2	; to 102
	100	[175]	TESTSET  	18 1 1
	101	[175]	JMP      	6	; to 108
	102	[175]	LT       	0 1 -15	; - 50
	103	[175]	JMP      	3	; to 107
	104	[175]	ADD      	18 1 -16	; - 2000
	105	[175]	TEST     	18 0 1
	106	[175]	JMP      	1	; to 108
	107	[175]	ADD      	18 1 -17	; - 1900
	108	[175]	SETTABLE 	17 -13 18	; "year" -
	109	[176]	SETTABLE 	17 -18 2	; "month" -
	110	[177]	GETUPVAL 	18 2	; tonumber
	111	[177]	MOVE     	19 3
	112	[177]	CALL     	18 2 2
	113	[177]	SETTABLE 	17 -19 18	; "day" -
	114	[179]	GETUPVAL 	18 2	; tonumber
	115	[179]	MOVE     	19 7
	116	[179]	CALL     	18 2 2
	117	[179]	TEST     	18 0 1
	118	[179]	JMP      	1	; to 120
	119	[179]	LOADK    	18 -11	; 0
	120	[179]	SETTABLE 	17 -20 18	; "hour" -
	121	[180]	GETUPVAL 	18 2	; tonumber
	122	[180]	MOVE     	19 8
	123	[180]	CALL     	18 2 2
	124	[180]	TEST     	18 0 1
	125	[180]	JMP      	1	; to 127
	126	[180]	LOADK    	18 -11	; 0
	127	[180]	SETTABLE 	17 -21 18	; "min" -
	128	[181]	GETUPVAL 	18 2	; tonumber
	129	[181]	MOVE     	19 9
	130	[181]	CALL     	18 2 2
	131	[181]	TEST     	18 0 1
	132	[181]	JMP      	1	; to 134
	133	[181]	LOADK    	18 -11	; 0
	134	[181]	SETTABLE 	17 -22 18	; "sec" -
	135	[182]	SETTABLE 	17 -23 -24	; "isdst" false
	136	[184]	GETUPVAL 	18 3	; unix_timestamp
	137	[184]	MOVE     	19 17
	138	[184]	MUL      	20 11 -25	; - 3600
	139	[184]	TAILCALL 	18 3 0
	140	[184]	RETURN   	18 0
	141	[185]	RETURN   	0 1
