-- BYTECODE -- dbg_spec.lua:3-7
0001    GGET     0   0      ; "package"
0002    KSTR     1   2      ; "?.lua;common/?.lua;rocks/share/lua/5.1/?"~
0003    GGET     2   0      ; "package"
0004    TGETS    2   2   1  ; "path"
0005    CAT      1   1   2
0006    TSETS    1   0   1  ; "path"
0007    GGET     0   3      ; "require"
0008    KSTR     1   4      ; "dbg"
0009    CALL     0   2   2
0010    USETV    0   0      ; dbg
0011    UGET     0   0      ; dbg
0012    TGETS    0   0   5  ; "is_on"
0013    USETV    1   0      ; dbg_on
0014    RET0     0   1

-- BYTECODE -- dbg_spec.lua:9-15
0001    UGET     0   0      ; dbg_on
0002    ISF          0
0003    JMP      1 => 0009
0004    UGET     0   1      ; dbg
0005    MOV      1   0
0006    TGETS    0   0   0  ; "turnOn"
0007    CALL     0   1   2
0008    JMP      0 => 0013
0009 => UGET     0   1      ; dbg
0010    MOV      1   0
0011    TGETS    0   0   1  ; "turnOff"
0012    CALL     0   1   2
0013 => RET0     0   1

-- BYTECODE -- dbg_spec.lua:17-24
0001    UGET     0   0      ; dbg
0002    MOV      1   0
0003    TGETS    0   0   0  ; "turnOff"
0004    CALL     0   1   2
0005    GGET     0   1      ; "getmetatable"
0006    UGET     1   0      ; dbg
0007    CALL     0   2   2
0008    TGETS    0   0   2  ; "__call"
0009    UGET     1   0      ; dbg
0010    TGETS    1   1   3  ; "guard"
0011    UGET     2   0      ; dbg
0012    MOV      3   2
0013    TGETS    2   2   4  ; "turnOn"
0014    CALL     2   1   2
0015    GGET     2   5      ; "assert"
0016    TGETS    2   2   6  ; "is_not"
0017    TGETS    2   2   7  ; "same"
0018    MOV      3   0
0019    GGET     4   1      ; "getmetatable"
0020    UGET     5   0      ; dbg
0021    CALL     4   2   2
0022    TGETS    4   4   2  ; "__call"
0023    CALL     2   1   3
0024    GGET     2   5      ; "assert"
0025    TGETS    2   2   6  ; "is_not"
0026    TGETS    2   2   7  ; "same"
0027    MOV      3   1
0028    UGET     4   0      ; dbg
0029    TGETS    4   4   3  ; "guard"
0030    CALL     2   1   3
0031    RET0     0   1

-- BYTECODE -- dbg_spec.lua:29-29
0001    RET0     0   1

-- BYTECODE -- dbg_spec.lua:36-36
0001    USETP    0   2      ; called
0002    RET0     0   1

-- BYTECODE -- dbg_spec.lua:26-39
0001    KPRI     0   1
0002    TNEW     1   0
0003    FNEW     2   1      ; dbg_spec.lua:29
0004    TSETS    2   1   0  ; "bar"
0005    GGET     2   2      ; "assert"
0006    TGETS    2   2   3  ; "is"
0007    TGETS    2   2   4  ; "falsy"
0008    MOV      3   0
0009    CALL     2   1   2
0010    UGET     2   0      ; dbg
0011    MOV      3   2
0012    TGETS    2   2   5  ; "turnOff"
0013    CALL     2   1   2
0014    GGET     2   2      ; "assert"
0015    TGETS    2   2   3  ; "is"
0016    TGETS    2   2   4  ; "falsy"
0017    MOV      3   0
0018    CALL     2   1   2
0019    UGET     2   0      ; dbg
0020    MOV      3   2
0021    TGETS    2   2   6  ; "turnOn"
0022    CALL     2   1   2
0023    UGET     2   0      ; dbg
0024    MOV      3   2
0025    TGETS    2   2   7  ; "guard"
0026    MOV      4   1
0027    KSTR     5   0      ; "bar"
0028    FNEW     6   8      ; dbg_spec.lua:36
0029    CALL     2   1   5
0030    MOV      3   1
0031    TGETS    2   1   0  ; "bar"
0032    CALL     2   1   2
0033    GGET     2   2      ; "assert"
0034    TGETS    2   2   3  ; "is"
0035    TGETS    2   2   9  ; "truthy"
0036    MOV      3   0
0037    CALL     2   1   2
0038    UCLO     0 => 0039
0039 => RET0     0   1

-- BYTECODE -- dbg_spec.lua:44-44
0001    RET0     0   1

-- BYTECODE -- dbg_spec.lua:51-51
0001    USETP    0   2      ; called
0002    RET0     0   1

-- BYTECODE -- dbg_spec.lua:41-54
0001    KPRI     0   1
0002    TNEW     1   0
0003    FNEW     2   1      ; dbg_spec.lua:44
0004    TSETS    2   1   0  ; "bar"
0005    GGET     2   2      ; "assert"
0006    TGETS    2   2   3  ; "is"
0007    TGETS    2   2   4  ; "falsy"
0008    MOV      3   0
0009    CALL     2   1   2
0010    UGET     2   0      ; dbg
0011    MOV      3   2
0012    TGETS    2   2   5  ; "turnOff"
0013    CALL     2   1   2
0014    GGET     2   2      ; "assert"
0015    TGETS    2   2   3  ; "is"
0016    TGETS    2   2   4  ; "falsy"
0017    MOV      3   0
0018    CALL     2   1   2
0019    UGET     2   0      ; dbg
0020    MOV      3   2
0021    TGETS    2   2   6  ; "turnOn"
0022    CALL     2   1   2
0023    UGET     2   0      ; dbg
0024    MOV      3   2
0025    TGETS    2   2   7  ; "guard"
0026    MOV      4   1
0027    KSTR     5   0      ; "bar"
0028    KPRI     6   0
0029    FNEW     7   8      ; dbg_spec.lua:51
0030    CALL     2   1   6
0031    MOV      3   1
0032    TGETS    2   1   0  ; "bar"
0033    CALL     2   1   2
0034    GGET     2   2      ; "assert"
0035    TGETS    2   2   3  ; "is"
0036    TGETS    2   2   9  ; "truthy"
0037    MOV      3   0
0038    CALL     2   1   2
0039    UCLO     0 => 0040
0040 => RET0     0   1

-- BYTECODE -- dbg_spec.lua:60-60
0001    KSHORT   1   1
0002    RET1     1   2

-- BYTECODE -- dbg_spec.lua:64-64
0001    USETP    0   2      ; called
0002    RET0     0   1

-- BYTECODE -- dbg_spec.lua:70-70
0001    KSHORT   1   1
0002    KSHORT   2   2
0003    KSHORT   3   3
0004    RET      1   4

-- BYTECODE -- dbg_spec.lua:71-71
0001    USETP    0   2      ; called
0002    RET0     0   1

-- BYTECODE -- dbg_spec.lua:56-75
0001    KPRI     0   1
0002    KPRI     1   0
0003    TNEW     2   0
0004    FNEW     3   1      ; dbg_spec.lua:60
0005    TSETS    3   2   0  ; "bar"
0006    GGET     3   2      ; "assert"
0007    TGETS    3   3   3  ; "is"
0008    TGETS    3   3   4  ; "falsy"
0009    MOV      4   0
0010    CALL     3   1   2
0011    UGET     3   0      ; dbg
0012    MOV      4   3
0013    TGETS    3   3   5  ; "turnOn"
0014    CALL     3   1   2
0015    UGET     3   0      ; dbg
0016    MOV      4   3
0017    TGETS    3   3   6  ; "guard"
0018    MOV      5   2
0019    KSTR     6   0      ; "bar"
0020    FNEW     7   7      ; dbg_spec.lua:64
0021    CALL     3   1   5
0022    TNEW     3   3
0023    MOV      5   2
0024    TGETS    4   2   0  ; "bar"
0025    CALL     4   0   2
0026    TSETM    4   0      ; 1
0027    MOV      1   3
0028    GGET     3   2      ; "assert"
0029    TGETS    3   3   3  ; "is"
0030    TGETS    3   3   8  ; "truthy"
0031    MOV      4   0
0032    CALL     3   1   2
0033    GGET     3   2      ; "assert"
0034    TGETS    3   3   3  ; "is"
0035    TGETS    3   3   9  ; "same"
0036    MOV      4   1
0037    TDUP     5  10
0038    CALL     3   1   3
0039    KPRI     0   1
0040    FNEW     3  11      ; dbg_spec.lua:70
0041    TSETS    3   2   0  ; "bar"
0042    UGET     3   0      ; dbg
0043    MOV      4   3
0044    TGETS    3   3   6  ; "guard"
0045    MOV      5   2
0046    KSTR     6   0      ; "bar"
0047    FNEW     7  12      ; dbg_spec.lua:71
0048    CALL     3   1   5
0049    GGET     3   2      ; "assert"
0050    TGETS    3   3   3  ; "is"
0051    TGETS    3   3   4  ; "falsy"
0052    MOV      4   0
0053    CALL     3   1   2
0054    TNEW     3   3
0055    MOV      5   2
0056    TGETS    4   2   0  ; "bar"
0057    CALL     4   0   2
0058    TSETM    4   0      ; 1
0059    MOV      1   3
0060    GGET     3   2      ; "assert"
0061    TGETS    3   3   3  ; "is"
0062    TGETS    3   3   9  ; "same"
0063    MOV      4   1
0064    TDUP     5  13
0065    CALL     3   1   3
0066    UCLO     0 => 0067
0067 => RET0     0   1

-- BYTECODE -- dbg_spec.lua:77-85
0001    GGET     0   0      ; "assert"
0002    TGETS    0   0   1  ; "is_nil"
0003    UGET     1   0      ; dbg
0004    TGETS    1   1   2  ; "is_verbose"
0005    CALL     0   1   2
0006    UGET     0   0      ; dbg
0007    MOV      1   0
0008    TGETS    0   0   3  ; "setVerbose"
0009    KPRI     2   2
0010    CALL     0   1   3
0011    GGET     0   0      ; "assert"
0012    TGETS    0   0   4  ; "is_true"
0013    UGET     1   0      ; dbg
0014    TGETS    1   1   2  ; "is_verbose"
0015    CALL     0   1   2
0016    UGET     0   0      ; dbg
0017    MOV      1   0
0018    TGETS    0   0   3  ; "setVerbose"
0019    KPRI     2   1
0020    CALL     0   1   3
0021    GGET     0   0      ; "assert"
0022    TGETS    0   0   5  ; "is_false"
0023    UGET     1   0      ; dbg
0024    TGETS    1   1   2  ; "is_verbose"
0025    CALL     0   1   2
0026    UGET     0   0      ; dbg
0027    MOV      1   0
0028    TGETS    0   0   3  ; "setVerbose"
0029    CALL     0   1   2
0030    GGET     0   0      ; "assert"
0031    TGETS    0   0   1  ; "is_nil"
0032    UGET     1   0      ; dbg
0033    TGETS    1   1   2  ; "is_verbose"
0034    CALL     0   1   2
0035    RET0     0   1

-- BYTECODE -- dbg_spec.lua:1-86
0001    KNIL     0   1
0002    GGET     2   0      ; "setup"
0003    FNEW     3   1      ; dbg_spec.lua:3
0004    CALL     2   1   2
0005    GGET     2   2      ; "after_each"
0006    FNEW     3   3      ; dbg_spec.lua:9
0007    CALL     2   1   2
0008    GGET     2   4      ; "it"
0009    KSTR     3   5      ; "setup mt.__call and guard after tunrnOn "~
0010    FNEW     4   6      ; dbg_spec.lua:17
0011    CALL     2   1   3
0012    GGET     2   4      ; "it"
0013    KSTR     3   7      ; "should call pre_gard callback"
0014    FNEW     4   8      ; dbg_spec.lua:26
0015    CALL     2   1   3
0016    GGET     2   4      ; "it"
0017    KSTR     3   9      ; "should call post_gard callback"
0018    FNEW     4  10      ; dbg_spec.lua:41
0019    CALL     2   1   3
0020    GGET     2   4      ; "it"
0021    KSTR     3  11      ; "should return all values returned by the"~
0022    FNEW     4  12      ; dbg_spec.lua:56
0023    CALL     2   1   3
0024    GGET     2   4      ; "it"
0025    KSTR     3  13      ; "should set verbose"
0026    FNEW     4  14      ; dbg_spec.lua:77
0027    CALL     2   1   3
0028    UCLO     0 => 0029
0029 => RET0     0   1

-- BYTECODE -- dbg_spec.lua:0-87
0001    GGET     0   0      ; "describe"
0002    KSTR     1   1      ; "Dbg module"
0003    FNEW     2   2      ; dbg_spec.lua:1
0004    CALL     0   1   3
0005    RET0     0   1

