
main <./defaults.lua:0,0> (319 instructions, 1276 bytes at 0x7fb72d4068a0)
0+ params, 12 slots, 0 upvalues, 0 locals, 169 constants, 0 functions
	1	[11]	LOADK    	0 -2	; 1
	2	[11]	SETGLOBAL	0 -1	; DHINTCOUNT
	3	[27]	LOADK    	0 -4	; 0
	4	[27]	SETGLOBAL	0 -3	; DRENDER_MODE
	5	[30]	LOADK    	0 -6	; 10485760
	6	[30]	SETGLOBAL	0 -5	; DGLOBAL_CACHE_SIZE_MINIMUM
	7	[33]	LOADK    	0 -8	; 0.4
	8	[33]	SETGLOBAL	0 -7	; DGLOBAL_CACHE_FREE_PROPORTION
	9	[36]	LOADK    	0 -10	; 62914560
	10	[36]	SETGLOBAL	0 -9	; DGLOBAL_CACHE_SIZE_MAXIMUM
	11	[39]	LOADK    	0 -4	; 0
	12	[39]	SETGLOBAL	0 -11	; DBACKGROUND_COLOR
	13	[42]	LOADK    	0 -4	; 0
	14	[42]	SETGLOBAL	0 -12	; DOUTER_PAGE_COLOR
	15	[45]	LOADK    	0 -14	; "page"
	16	[45]	SETGLOBAL	0 -13	; DCREREADER_VIEW_MODE
	17	[49]	LOADBOOL 	0 0 0
	18	[49]	SETGLOBAL	0 -15	; DSHOWOVERLAP
	19	[53]	LOADBOOL 	0 0 0
	20	[53]	SETGLOBAL	0 -16	; DSHOWHIDDENFILES
	21	[57]	LOADBOOL 	0 1 0
	22	[57]	SETGLOBAL	0 -17	; DLANDSCAPE_CLOCKWISE_ROTATION
	23	[60]	LOADK    	0 -19	; 7
	24	[60]	SETGLOBAL	0 -18	; DCREREADER_TWO_PAGE_THRESHOLD
	25	[63]	LOADK    	0 -21	; 30
	26	[63]	SETGLOBAL	0 -20	; DOVERLAPPIXELS
	27	[68]	LOADK    	0 -23	; 0.5
	28	[68]	SETGLOBAL	0 -22	; FOLLOW_LINK_TIMEOUT
	29	[75]	NEWTABLE 	0 0 4
	30	[75]	SETTABLE 	0 -25 -26	; "x" 0.125
	31	[75]	SETTABLE 	0 -27 -4	; "y" 0
	32	[75]	SETTABLE 	0 -28 -29	; "w" 0.75
	33	[75]	SETTABLE 	0 -30 -26	; "h" 0.125
	34	[75]	SETGLOBAL	0 -24	; DTAP_ZONE_MENU
	35	[76]	NEWTABLE 	0 0 4
	36	[76]	SETTABLE 	0 -25 -26	; "x" 0.125
	37	[76]	SETTABLE 	0 -27 -32	; "y" 0.875
	38	[76]	SETTABLE 	0 -28 -29	; "w" 0.75
	39	[76]	SETTABLE 	0 -30 -26	; "h" 0.125
	40	[76]	SETGLOBAL	0 -31	; DTAP_ZONE_CONFIG
	41	[77]	NEWTABLE 	0 0 4
	42	[77]	SETTABLE 	0 -25 -4	; "x" 0
	43	[77]	SETTABLE 	0 -27 -34	; "y" 0.96875
	44	[77]	SETTABLE 	0 -28 -2	; "w" 1
	45	[77]	SETTABLE 	0 -30 -35	; "h" 0.03125
	46	[77]	SETGLOBAL	0 -33	; DTAP_ZONE_MINIBAR
	47	[78]	NEWTABLE 	0 0 4
	48	[78]	SETTABLE 	0 -25 -37	; "x" 0.25
	49	[78]	SETTABLE 	0 -27 -4	; "y" 0
	50	[78]	SETTABLE 	0 -28 -29	; "w" 0.75
	51	[78]	SETTABLE 	0 -30 -2	; "h" 1
	52	[78]	SETGLOBAL	0 -36	; DTAP_ZONE_FORWARD
	53	[79]	NEWTABLE 	0 0 4
	54	[79]	SETTABLE 	0 -25 -4	; "x" 0
	55	[79]	SETTABLE 	0 -27 -4	; "y" 0
	56	[79]	SETTABLE 	0 -28 -37	; "w" 0.25
	57	[79]	SETTABLE 	0 -30 -2	; "h" 1
	58	[79]	SETGLOBAL	0 -38	; DTAP_ZONE_BACKWARD
	59	[82]	NEWTABLE 	0 0 4
	60	[82]	SETTABLE 	0 -25 -4	; "x" 0
	61	[82]	SETTABLE 	0 -27 -4	; "y" 0
	62	[82]	SETTABLE 	0 -28 -26	; "w" 0.125
	63	[82]	SETTABLE 	0 -30 -26	; "h" 0.125
	64	[82]	SETGLOBAL	0 -39	; DTAP_ZONE_TOP_LEFT
	65	[83]	NEWTABLE 	0 0 4
	66	[83]	SETTABLE 	0 -25 -32	; "x" 0.875
	67	[83]	SETTABLE 	0 -27 -4	; "y" 0
	68	[83]	SETTABLE 	0 -28 -26	; "w" 0.125
	69	[83]	SETTABLE 	0 -30 -26	; "h" 0.125
	70	[83]	SETGLOBAL	0 -40	; DTAP_ZONE_TOP_RIGHT
	71	[84]	NEWTABLE 	0 0 4
	72	[84]	SETTABLE 	0 -25 -4	; "x" 0
	73	[84]	SETTABLE 	0 -27 -32	; "y" 0.875
	74	[84]	SETTABLE 	0 -28 -26	; "w" 0.125
	75	[84]	SETTABLE 	0 -30 -26	; "h" 0.125
	76	[84]	SETGLOBAL	0 -41	; DTAP_ZONE_BOTTOM_LEFT
	77	[85]	NEWTABLE 	0 0 4
	78	[85]	SETTABLE 	0 -25 -32	; "x" 0.875
	79	[85]	SETTABLE 	0 -27 -32	; "y" 0.875
	80	[85]	SETTABLE 	0 -28 -26	; "w" 0.125
	81	[85]	SETTABLE 	0 -30 -26	; "h" 0.125
	82	[85]	SETGLOBAL	0 -42	; DTAP_ZONE_BOTTOM_RIGHT
	83	[86]	NEWTABLE 	0 0 4
	84	[86]	SETTABLE 	0 -25 -29	; "x" 0.75
	85	[86]	SETTABLE 	0 -27 -4	; "y" 0
	86	[86]	SETTABLE 	0 -28 -37	; "w" 0.25
	87	[86]	SETTABLE 	0 -30 -37	; "h" 0.25
	88	[86]	SETGLOBAL	0 -43	; DDOUBLE_TAP_ZONE_NEXT_CHAPTER
	89	[87]	NEWTABLE 	0 0 4
	90	[87]	SETTABLE 	0 -25 -4	; "x" 0
	91	[87]	SETTABLE 	0 -27 -4	; "y" 0
	92	[87]	SETTABLE 	0 -28 -37	; "w" 0.25
	93	[87]	SETTABLE 	0 -30 -37	; "h" 0.25
	94	[87]	SETGLOBAL	0 -44	; DDOUBLE_TAP_ZONE_PREV_CHAPTER
	95	[90]	LOADBOOL 	0 0 0
	96	[90]	SETGLOBAL	0 -45	; DCHANGE_WEST_SWIPE_TO_EAST
	97	[91]	LOADBOOL 	0 0 0
	98	[91]	SETGLOBAL	0 -46	; DCHANGE_EAST_SWIPE_TO_WEST
	99	[94]	LOADK    	0 -2	; 1
	100	[94]	SETGLOBAL	0 -47	; DKOPTREADER_CONFIG_FONT_SIZE
	101	[95]	LOADK    	0 -4	; 0
	102	[95]	SETGLOBAL	0 -48	; DKOPTREADER_CONFIG_TEXT_WRAP
	103	[96]	LOADK    	0 -2	; 1
	104	[96]	SETGLOBAL	0 -49	; DKOPTREADER_CONFIG_TRIM_PAGE
	105	[97]	LOADK    	0 -2	; 1
	106	[97]	SETGLOBAL	0 -50	; DKOPTREADER_CONFIG_DETECT_INDENT
	107	[98]	LOADK    	0 -2	; 1
	108	[98]	SETGLOBAL	0 -51	; DKOPTREADER_CONFIG_DEFECT_SIZE
	109	[99]	LOADK    	0 -53	; 0.1
	110	[99]	SETGLOBAL	0 -52	; DKOPTREADER_CONFIG_PAGE_MARGIN
	111	[100]	LOADK    	0 -55	; 1.2
	112	[100]	SETGLOBAL	0 -54	; DKOPTREADER_CONFIG_LINE_SPACING
	113	[101]	LOADK    	0 -2	; 1
	114	[101]	SETGLOBAL	0 -56	; DKOPTREADER_CONFIG_RENDER_QUALITY
	115	[102]	LOADK    	0 -4	; 0
	116	[102]	SETGLOBAL	0 -57	; DKOPTREADER_CONFIG_AUTO_STRAIGHTEN
	117	[103]	LOADK    	0 -59	; 3
	118	[103]	SETGLOBAL	0 -58	; DKOPTREADER_CONFIG_JUSTIFICATION
	119	[104]	LOADK    	0 -61	; 2
	120	[104]	SETGLOBAL	0 -60	; DKOPTREADER_CONFIG_MAX_COLUMNS
	121	[105]	LOADK    	0 -2	; 1
	122	[105]	SETGLOBAL	0 -62	; DKOPTREADER_CONFIG_CONTRAST
	123	[108]	NEWTABLE 	0 3 0
	124	[108]	LOADK    	1 -64	; 0.05
	125	[108]	LOADK    	2 -65	; -0.2
	126	[108]	LOADK    	3 -66	; 0.375
	127	[108]	SETLIST  	0 3 1	; 1
	128	[108]	SETGLOBAL	0 -63	; DKOPTREADER_CONFIG_WORD_SPACINGS
	129	[109]	LOADK    	0 -65	; -0.2
	130	[109]	SETGLOBAL	0 -67	; DKOPTREADER_CONFIG_DEFAULT_WORD_SPACING
	131	[111]	NEWTABLE 	0 2 0
	132	[111]	LOADK    	1 -69	; "English"
	133	[111]	LOADK    	2 -70	; "Chinese"
	134	[111]	SETLIST  	0 2 1	; 1
	135	[111]	SETGLOBAL	0 -68	; DKOPTREADER_CONFIG_DOC_LANGS_TEXT
	136	[112]	NEWTABLE 	0 2 0
	137	[112]	LOADK    	1 -72	; "eng"
	138	[112]	LOADK    	2 -73	; "chi_sim"
	139	[112]	SETLIST  	0 2 1	; 1
	140	[112]	SETGLOBAL	0 -71	; DKOPTREADER_CONFIG_DOC_LANGS_CODE
	141	[113]	LOADK    	0 -72	; "eng"
	142	[113]	SETGLOBAL	0 -74	; DKOPTREADER_CONFIG_DOC_DEFAULT_LANG_CODE
	143	[117]	NEWTABLE 	0 11 0
	144	[117]	LOADK    	1 -76	; 12
	145	[117]	LOADK    	2 -77	; 16
	146	[117]	LOADK    	3 -78	; 20
	147	[117]	LOADK    	4 -79	; 22
	148	[117]	LOADK    	5 -80	; 24
	149	[117]	LOADK    	6 -81	; 26
	150	[117]	LOADK    	7 -82	; 28
	151	[117]	LOADK    	8 -21	; 30
	152	[117]	LOADK    	9 -83	; 34
	153	[117]	LOADK    	10 -84	; 38
	154	[117]	LOADK    	11 -85	; 44
	155	[117]	SETLIST  	0 11 1	; 1
	156	[117]	SETGLOBAL	0 -75	; DCREREADER_CONFIG_FONT_SIZES
	157	[118]	LOADK    	0 -79	; 22
	158	[118]	SETGLOBAL	0 -86	; DCREREADER_CONFIG_DEFAULT_FONT_SIZE
	159	[122]	NEWTABLE 	0 2 0
	160	[122]	LOADK    	1 -88	; 5
	161	[122]	LOADK    	2 -88	; 5
	162	[122]	SETLIST  	0 2 1	; 1
	163	[122]	SETGLOBAL	0 -87	; DCREREADER_CONFIG_H_MARGIN_SIZES_SMALL
	164	[123]	NEWTABLE 	0 2 0
	165	[123]	LOADK    	1 -90	; 10
	166	[123]	LOADK    	2 -90	; 10
	167	[123]	SETLIST  	0 2 1	; 1
	168	[123]	SETGLOBAL	0 -89	; DCREREADER_CONFIG_H_MARGIN_SIZES_MEDIUM
	169	[124]	NEWTABLE 	0 2 0
	170	[124]	LOADK    	1 -92	; 15
	171	[124]	LOADK    	2 -92	; 15
	172	[124]	SETLIST  	0 2 1	; 1
	173	[124]	SETGLOBAL	0 -91	; DCREREADER_CONFIG_H_MARGIN_SIZES_LARGE
	174	[125]	NEWTABLE 	0 2 0
	175	[125]	LOADK    	1 -78	; 20
	176	[125]	LOADK    	2 -78	; 20
	177	[125]	SETLIST  	0 2 1	; 1
	178	[125]	SETGLOBAL	0 -93	; DCREREADER_CONFIG_H_MARGIN_SIZES_X_LARGE
	179	[126]	NEWTABLE 	0 2 0
	180	[126]	LOADK    	1 -21	; 30
	181	[126]	LOADK    	2 -21	; 30
	182	[126]	SETLIST  	0 2 1	; 1
	183	[126]	SETGLOBAL	0 -94	; DCREREADER_CONFIG_H_MARGIN_SIZES_XX_LARGE
	184	[127]	NEWTABLE 	0 2 0
	185	[127]	LOADK    	1 -96	; 50
	186	[127]	LOADK    	2 -96	; 50
	187	[127]	SETLIST  	0 2 1	; 1
	188	[127]	SETGLOBAL	0 -95	; DCREREADER_CONFIG_H_MARGIN_SIZES_XXX_LARGE
	189	[128]	NEWTABLE 	0 2 0
	190	[128]	LOADK    	1 -98	; 70
	191	[128]	LOADK    	2 -98	; 70
	192	[128]	SETLIST  	0 2 1	; 1
	193	[128]	SETGLOBAL	0 -97	; DCREREADER_CONFIG_H_MARGIN_SIZES_HUGE
	194	[129]	NEWTABLE 	0 2 0
	195	[129]	LOADK    	1 -100	; 100
	196	[129]	LOADK    	2 -100	; 100
	197	[129]	SETLIST  	0 2 1	; 1
	198	[129]	SETGLOBAL	0 -99	; DCREREADER_CONFIG_H_MARGIN_SIZES_X_HUGE
	199	[130]	NEWTABLE 	0 2 0
	200	[130]	LOADK    	1 -102	; 140
	201	[130]	LOADK    	2 -102	; 140
	202	[130]	SETLIST  	0 2 1	; 1
	203	[130]	SETGLOBAL	0 -101	; DCREREADER_CONFIG_H_MARGIN_SIZES_XX_HUGE
	204	[133]	LOADK    	0 -88	; 5
	205	[133]	SETGLOBAL	0 -103	; DCREREADER_CONFIG_T_MARGIN_SIZES_SMALL
	206	[134]	LOADK    	0 -90	; 10
	207	[134]	SETGLOBAL	0 -104	; DCREREADER_CONFIG_T_MARGIN_SIZES_MEDIUM
	208	[135]	LOADK    	0 -92	; 15
	209	[135]	SETGLOBAL	0 -105	; DCREREADER_CONFIG_T_MARGIN_SIZES_LARGE
	210	[136]	LOADK    	0 -78	; 20
	211	[136]	SETGLOBAL	0 -106	; DCREREADER_CONFIG_T_MARGIN_SIZES_X_LARGE
	212	[137]	LOADK    	0 -21	; 30
	213	[137]	SETGLOBAL	0 -107	; DCREREADER_CONFIG_T_MARGIN_SIZES_XX_LARGE
	214	[138]	LOADK    	0 -96	; 50
	215	[138]	SETGLOBAL	0 -108	; DCREREADER_CONFIG_T_MARGIN_SIZES_XXX_LARGE
	216	[139]	LOADK    	0 -98	; 70
	217	[139]	SETGLOBAL	0 -109	; DCREREADER_CONFIG_T_MARGIN_SIZES_HUGE
	218	[140]	LOADK    	0 -100	; 100
	219	[140]	SETGLOBAL	0 -110	; DCREREADER_CONFIG_T_MARGIN_SIZES_X_HUGE
	220	[141]	LOADK    	0 -102	; 140
	221	[141]	SETGLOBAL	0 -111	; DCREREADER_CONFIG_T_MARGIN_SIZES_XX_HUGE
	222	[144]	LOADK    	0 -88	; 5
	223	[144]	SETGLOBAL	0 -112	; DCREREADER_CONFIG_B_MARGIN_SIZES_SMALL
	224	[145]	LOADK    	0 -90	; 10
	225	[145]	SETGLOBAL	0 -113	; DCREREADER_CONFIG_B_MARGIN_SIZES_MEDIUM
	226	[146]	LOADK    	0 -92	; 15
	227	[146]	SETGLOBAL	0 -114	; DCREREADER_CONFIG_B_MARGIN_SIZES_LARGE
	228	[147]	LOADK    	0 -78	; 20
	229	[147]	SETGLOBAL	0 -115	; DCREREADER_CONFIG_B_MARGIN_SIZES_X_LARGE
	230	[148]	LOADK    	0 -21	; 30
	231	[148]	SETGLOBAL	0 -116	; DCREREADER_CONFIG_B_MARGIN_SIZES_XX_LARGE
	232	[149]	LOADK    	0 -96	; 50
	233	[149]	SETGLOBAL	0 -117	; DCREREADER_CONFIG_B_MARGIN_SIZES_XXX_LARGE
	234	[150]	LOADK    	0 -98	; 70
	235	[150]	SETGLOBAL	0 -118	; DCREREADER_CONFIG_B_MARGIN_SIZES_HUGE
	236	[151]	LOADK    	0 -100	; 100
	237	[151]	SETGLOBAL	0 -119	; DCREREADER_CONFIG_B_MARGIN_SIZES_X_HUGE
	238	[152]	LOADK    	0 -102	; 140
	239	[152]	SETGLOBAL	0 -120	; DCREREADER_CONFIG_B_MARGIN_SIZES_XX_HUGE
	240	[160]	LOADK    	0 -98	; 70
	241	[160]	SETGLOBAL	0 -121	; DCREREADER_CONFIG_LINE_SPACE_PERCENT_X_TINY
	242	[161]	LOADK    	0 -123	; 75
	243	[161]	SETGLOBAL	0 -122	; DCREREADER_CONFIG_LINE_SPACE_PERCENT_TINY
	244	[162]	LOADK    	0 -125	; 80
	245	[162]	SETGLOBAL	0 -124	; DCREREADER_CONFIG_LINE_SPACE_PERCENT_XX_SMALL
	246	[163]	LOADK    	0 -127	; 85
	247	[163]	SETGLOBAL	0 -126	; DCREREADER_CONFIG_LINE_SPACE_PERCENT_X_SMALL
	248	[164]	LOADK    	0 -129	; 90
	249	[164]	SETGLOBAL	0 -128	; DCREREADER_CONFIG_LINE_SPACE_PERCENT_SMALL
	250	[165]	LOADK    	0 -131	; 95
	251	[165]	SETGLOBAL	0 -130	; DCREREADER_CONFIG_LINE_SPACE_PERCENT_L_SMALL
	252	[166]	LOADK    	0 -100	; 100
	253	[166]	SETGLOBAL	0 -132	; DCREREADER_CONFIG_LINE_SPACE_PERCENT_MEDIUM
	254	[167]	LOADK    	0 -134	; 105
	255	[167]	SETGLOBAL	0 -133	; DCREREADER_CONFIG_LINE_SPACE_PERCENT_L_MEDIUM
	256	[168]	LOADK    	0 -136	; 110
	257	[168]	SETGLOBAL	0 -135	; DCREREADER_CONFIG_LINE_SPACE_PERCENT_XL_MEDIUM
	258	[169]	LOADK    	0 -138	; 115
	259	[169]	SETGLOBAL	0 -137	; DCREREADER_CONFIG_LINE_SPACE_PERCENT_XXL_MEDIUM
	260	[170]	LOADK    	0 -140	; 120
	261	[170]	SETGLOBAL	0 -139	; DCREREADER_CONFIG_LINE_SPACE_PERCENT_LARGE
	262	[171]	LOADK    	0 -142	; 125
	263	[171]	SETGLOBAL	0 -141	; DCREREADER_CONFIG_LINE_SPACE_PERCENT_X_LARGE
	264	[172]	LOADK    	0 -144	; 130
	265	[172]	SETGLOBAL	0 -143	; DCREREADER_CONFIG_LINE_SPACE_PERCENT_XX_LARGE
	266	[184]	NEWTABLE 	0 2 0
	267	[184]	LOADK    	1 -123	; 75
	268	[184]	LOADK    	2 -96	; 50
	269	[184]	SETLIST  	0 2 1	; 1
	270	[184]	SETGLOBAL	0 -145	; DCREREADER_CONFIG_WORD_SPACING_SMALL
	271	[185]	NEWTABLE 	0 2 0
	272	[185]	LOADK    	1 -131	; 95
	273	[185]	LOADK    	2 -123	; 75
	274	[185]	SETLIST  	0 2 1	; 1
	275	[185]	SETGLOBAL	0 -146	; DCREREADER_CONFIG_WORD_SPACING_MEDIUM
	276	[186]	NEWTABLE 	0 2 0
	277	[186]	LOADK    	1 -100	; 100
	278	[186]	LOADK    	2 -129	; 90
	279	[186]	SETLIST  	0 2 1	; 1
	280	[186]	SETGLOBAL	0 -147	; DCREREADER_CONFIG_WORD_SPACING_LARGE
	281	[191]	LOADK    	0 -4	; 0
	282	[191]	SETGLOBAL	0 -148	; DCREREADER_CONFIG_WORD_EXPANSION_NONE
	283	[192]	LOADK    	0 -88	; 5
	284	[192]	SETGLOBAL	0 -149	; DCREREADER_CONFIG_WORD_EXPANSION_SOME
	285	[193]	LOADK    	0 -92	; 15
	286	[193]	SETGLOBAL	0 -150	; DCREREADER_CONFIG_WORD_EXPANSION_MORE
	287	[203]	LOADK    	0 -152	; 14
	288	[203]	SETGLOBAL	0 -151	; DMINIBAR_CONTAINER_HEIGHT
	289	[219]	LOADK    	0 -61	; 2
	290	[219]	SETGLOBAL	0 -153	; FRONTLIGHT_SENSITIVITY_DECREASE
	291	[225]	LOADBOOL 	0 1 0
	292	[225]	SETGLOBAL	0 -154	; DALPHA_SORT_CASE_INSENSITIVE
	293	[232]	LOADK    	0 -156	; ""
	294	[232]	SETGLOBAL	0 -155	; SEARCH_LIBRARY_PATH
	295	[233]	LOADK    	0 -156	; ""
	296	[233]	SETGLOBAL	0 -157	; SEARCH_LIBRARY_PATH2
	297	[236]	LOADBOOL 	0 0 0
	298	[236]	SETGLOBAL	0 -158	; SEARCH_CASESENSITIVE
	299	[238]	LOADBOOL 	0 1 0
	300	[238]	SETGLOBAL	0 -159	; SEARCH_AUTHORS
	301	[239]	LOADBOOL 	0 1 0
	302	[239]	SETGLOBAL	0 -160	; SEARCH_TITLE
	303	[240]	LOADBOOL 	0 1 0
	304	[240]	SETGLOBAL	0 -161	; SEARCH_TAGS
	305	[241]	LOADBOOL 	0 1 0
	306	[241]	SETGLOBAL	0 -162	; SEARCH_SERIES
	307	[242]	LOADBOOL 	0 1 0
	308	[242]	SETGLOBAL	0 -163	; SEARCH_PATH
	309	[245]	LOADK    	0 -165	; -2
	310	[245]	SETGLOBAL	0 -164	; KOBO_LIGHT_ON_START
	311	[249]	LOADBOOL 	0 1 0
	312	[249]	SETGLOBAL	0 -166	; KOBO_SYNC_BRIGHTNESS_WITH_NICKEL
	313	[255]	LOADNIL  	0 0
	314	[255]	SETGLOBAL	0 -167	; NETWORK_PROXY
	315	[259]	LOADBOOL 	0 0 0
	316	[259]	SETGLOBAL	0 -168	; DUSE_TURBO_LIB
	317	[263]	LOADNIL  	0 0
	318	[263]	SETGLOBAL	0 -169	; STARDICT_DATA_DIR
	319	[263]	RETURN   	0 1
