-- BYTECODE -- defaults_spec.lua:3-7
0001    GGET     0   0      ; "require"
0002    KSTR     1   1      ; "commonrequire"
0003    CALL     0   1   2
0004    GGET     0   0      ; "require"
0005    KSTR     1   2      ; "apps/filemanager/filemanagersetdefaults"
0006    CALL     0   2   2
0007    USETV    0   0      ; Defaults
0008    GGET     0   0      ; "require"
0009    KSTR     1   3      ; "datastorage"
0010    CALL     0   2   2
0011    USETV    1   0      ; DataStorage
0012    RET0     0   1

-- BYTECODE -- defaults_spec.lua:9-12
0001    UGET     0   0      ; Defaults
0002    MOV      1   0
0003    TGETS    0   0   0  ; "init"
0004    CALL     0   1   2
0005    GGET     0   1      ; "assert"
0006    TGETS    0   0   2  ; "is_same"
0007    KSHORT   1 106
0008    UGET     2   0      ; Defaults
0009    TGETS    2   2   3  ; "defaults_name"
0010    LEN      2   2
0011    CALL     0   1   3
0012    RET0     0   1

-- BYTECODE -- defaults_spec.lua:14-106
0001    UGET     0   0      ; DataStorage
0002    MOV      1   0
0003    TGETS    0   0   0  ; "getDataDir"
0004    CALL     0   2   2
0005    KSTR     1   1      ; "/defaults.persistent.lua"
0006    CAT      0   0   1
0007    GGET     1   2      ; "os"
0008    TGETS    1   1   3  ; "remove"
0009    MOV      2   0
0010    CALL     1   1   2
0011    UGET     1   1      ; Defaults
0012    TGETS    1   1   4  ; "changed"
0013    KPRI     2   2
0014    TSETB    2   1  20
0015    UGET     1   1      ; Defaults
0016    TGETS    1   1   4  ; "changed"
0017    KPRI     2   2
0018    TSETB    2   1  50
0019    UGET     1   1      ; Defaults
0020    TGETS    1   1   4  ; "changed"
0021    KPRI     2   2
0022    TSETB    2   1  56
0023    UGET     1   1      ; Defaults
0024    TGETS    1   1   4  ; "changed"
0025    KPRI     2   2
0026    TSETB    2   1  85
0027    UGET     1   1      ; Defaults
0028    TGETS    1   1   4  ; "changed"
0029    KPRI     2   2
0030    TSETB    2   1 101
0031    UGET     1   1      ; Defaults
0032    MOV      2   1
0033    TGETS    1   1   5  ; "saveSettings"
0034    CALL     1   1   2
0035    GGET     1   6      ; "assert"
0036    TGETS    1   1   7  ; "is_same"
0037    KSHORT   2 106
0038    UGET     3   1      ; Defaults
0039    TGETS    3   3   8  ; "defaults_name"
0040    LEN      3   3
0041    CALL     1   1   3
0042    GGET     1   6      ; "assert"
0043    TGETS    1   1   7  ; "is_same"
0044    KSTR     2   9      ; "SEARCH_LIBRARY_PATH"
0045    UGET     3   1      ; Defaults
0046    TGETS    3   3   8  ; "defaults_name"
0047    TGETB    3   3 101
0048    CALL     1   1   3
0049    GGET     1   6      ; "assert"
0050    TGETS    1   1   7  ; "is_same"
0051    KSTR     2  10      ; "DTAP_ZONE_BACKWARD"
0052    UGET     3   1      ; Defaults
0053    TGETS    3   3   8  ; "defaults_name"
0054    TGETB    3   3  85
0055    CALL     1   1   3
0056    GGET     1   6      ; "assert"
0057    TGETS    1   1   7  ; "is_same"
0058    KSTR     2  11      ; "DCREREADER_CONFIG_WORD_SPACING_LARGE"
0059    UGET     3   1      ; Defaults
0060    TGETS    3   3   8  ; "defaults_name"
0061    TGETB    3   3  50
0062    CALL     1   1   3
0063    GGET     1   6      ; "assert"
0064    TGETS    1   1   7  ; "is_same"
0065    KSTR     2  12      ; "DCREREADER_CONFIG_H_MARGIN_SIZES_XXX_LAR"~
0066    UGET     3   1      ; Defaults
0067    TGETS    3   3   8  ; "defaults_name"
0068    TGETB    3   3  20
0069    CALL     1   1   3
0070    GGET     1  13      ; "io"
0071    TGETS    1   1  14  ; "open"
0072    MOV      2   0
0073    KSTR     3  15      ; "r"
0074    CALL     1   2   3
0075    GGET     2   6      ; "assert"
0076    TGETS    2   2  16  ; "Equals"
0077    KSTR     3  17      ; "-- For configuration changes that persis"~
0078    MOV      5   1
0079    TGETS    4   1  18  ; "read"
0080    KSTR     6  19      ; "*a"
0081    CALL     4   0   3
0082    CALLM    2   1   1
0083    MOV      3   1
0084    TGETS    2   1  20  ; "close"
0085    CALL     2   1   2
0086    UGET     2   1      ; Defaults
0087    MOV      3   2
0088    TGETS    2   2  21  ; "init"
0089    CALL     2   1   2
0090    UGET     2   1      ; Defaults
0091    TGETS    2   2   4  ; "changed"
0092    KPRI     3   2
0093    TSETB    3   2  56
0094    UGET     2   1      ; Defaults
0095    TGETS    2   2  22  ; "defaults_value"
0096    TDUP     3  23
0097    TSETB    3   2  56
0098    UGET     2   1      ; Defaults
0099    TGETS    2   2   4  ; "changed"
0100    KPRI     3   2
0101    TSETB    3   2  85
0102    UGET     2   1      ; Defaults
0103    TGETS    2   2  22  ; "defaults_value"
0104    TDUP     3  24
0105    TSETB    3   2  85
0106    UGET     2   1      ; Defaults
0107    MOV      3   2
0108    TGETS    2   2   5  ; "saveSettings"
0109    CALL     2   1   2
0110    GGET     2  13      ; "io"
0111    TGETS    2   2  14  ; "open"
0112    MOV      3   0
0113    CALL     2   2   2
0114    MOV      1   2
0115    GGET     2   6      ; "assert"
0116    TGETS    2   2  16  ; "Equals"
0117    KSTR     3  25      ; "-- For configuration changes that persis"~
0118    MOV      5   1
0119    TGETS    4   1  18  ; "read"
0120    KSTR     6  19      ; "*a"
0121    CALL     4   0   3
0122    CALLM    2   1   1
0123    MOV      3   1
0124    TGETS    2   1  20  ; "close"
0125    CALL     2   1   2
0126    GGET     2   2      ; "os"
0127    TGETS    2   2   3  ; "remove"
0128    MOV      3   0
0129    CALL     2   1   2
0130    RET0     0   1

-- BYTECODE -- defaults_spec.lua:108-143
0001    UGET     0   0      ; DataStorage
0002    MOV      1   0
0003    TGETS    0   0   0  ; "getDataDir"
0004    CALL     0   2   2
0005    KSTR     1   1      ; "/defaults.persistent.lua"
0006    CAT      0   0   1
0007    GGET     1   2      ; "io"
0008    TGETS    1   1   3  ; "open"
0009    MOV      2   0
0010    KSTR     3   4      ; "w"
0011    CALL     1   2   3
0012    MOV      3   1
0013    TGETS    2   1   5  ; "write"
0014    KSTR     4   6      ; "-- For configuration changes that persis"~
0015    CALL     2   1   3
0016    MOV      3   1
0017    TGETS    2   1   7  ; "close"
0018    CALL     2   1   2
0019    UGET     2   1      ; Defaults
0020    MOV      3   2
0021    TGETS    2   2   8  ; "init"
0022    CALL     2   1   2
0023    UGET     2   1      ; Defaults
0024    TGETS    2   2   9  ; "changed"
0025    KPRI     3   2
0026    TSETB    3   2  57
0027    UGET     2   1      ; Defaults
0028    TGETS    2   2  10  ; "defaults_value"
0029    KSHORT   3   1
0030    TSETB    3   2  57
0031    UGET     2   1      ; Defaults
0032    MOV      3   2
0033    TGETS    2   2  11  ; "saveSettings"
0034    CALL     2   1   2
0035    GGET     2   2      ; "io"
0036    TGETS    2   2   3  ; "open"
0037    MOV      3   0
0038    CALL     2   2   2
0039    MOV      1   2
0040    GGET     2  12      ; "assert"
0041    TGETS    2   2  13  ; "Equals"
0042    KSTR     3  14      ; "-- For configuration changes that persis"~
0043    MOV      5   1
0044    TGETS    4   1  15  ; "read"
0045    KSTR     6  16      ; "*a"
0046    CALL     4   0   3
0047    CALLM    2   1   1
0048    MOV      3   1
0049    TGETS    2   1   7  ; "close"
0050    CALL     2   1   2
0051    GGET     2  17      ; "os"
0052    TGETS    2   2  18  ; "remove"
0053    MOV      3   0
0054    CALL     2   1   2
0055    RET0     0   1

-- BYTECODE -- defaults_spec.lua:1-144
0001    KNIL     0   1
0002    GGET     2   0      ; "setup"
0003    FNEW     3   1      ; defaults_spec.lua:3
0004    CALL     2   1   2
0005    GGET     2   2      ; "it"
0006    KSTR     3   3      ; "should load all defaults from defaults.l"~
0007    FNEW     4   4      ; defaults_spec.lua:9
0008    CALL     2   1   3
0009    GGET     2   2      ; "it"
0010    KSTR     3   5      ; "should save changes to defaults.persiste"~
0011    FNEW     4   6      ; defaults_spec.lua:14
0012    CALL     2   1   3
0013    GGET     2   2      ; "it"
0014    KSTR     3   7      ; "should delete entry from defaults.persis"~
0015    FNEW     4   8      ; defaults_spec.lua:108
0016    CALL     2   1   3
0017    UCLO     0 => 0018
0018 => RET0     0   1

-- BYTECODE -- defaults_spec.lua:0-145
0001    GGET     0   0      ; "describe"
0002    KSTR     1   1      ; "defaults module"
0003    FNEW     2   2      ; defaults_spec.lua:1
0004    CALL     0   1   3
0005    RET0     0   1

