-- BYTECODE -- depgraph_spec.lua:3-6
0001    GGET     0   0      ; "require"
0002    KSTR     1   1      ; "commonrequire"
0003    CALL     0   1   2
0004    GGET     0   0      ; "require"
0005    KSTR     1   2      ; "depgraph"
0006    CALL     0   2   2
0007    USETV    0   0      ; DepGraph
0008    RET0     0   1

-- BYTECODE -- depgraph_spec.lua:8-14
0001    UGET     0   0      ; DepGraph
0002    MOV      1   0
0003    TGETS    0   0   0  ; "new"
0004    TNEW     2   0
0005    CALL     0   2   3
0006    MOV      2   0
0007    TGETS    1   0   1  ; "addNode"
0008    KSTR     3   2      ; "a1"
0009    TDUP     4   3
0010    CALL     1   1   4
0011    MOV      2   0
0012    TGETS    1   0   1  ; "addNode"
0013    KSTR     3   4      ; "b1"
0014    TDUP     4   5
0015    CALL     1   1   4
0016    MOV      2   0
0017    TGETS    1   0   1  ; "addNode"
0018    KSTR     3   6      ; "c1"
0019    CALL     1   1   3
0020    GGET     1   7      ; "assert"
0021    TGETS    1   1   8  ; "are"
0022    TGETS    1   1   9  ; "same"
0023    TDUP     2  10
0024    MOV      4   0
0025    TGETS    3   0  11  ; "serialize"
0026    CALL     3   0   2
0027    CALLM    1   1   1
0028    RET0     0   1

-- BYTECODE -- depgraph_spec.lua:16-44
0001    UGET     0   0      ; DepGraph
0002    MOV      1   0
0003    TGETS    0   0   0  ; "new"
0004    TNEW     2   0
0005    CALL     0   2   3
0006    MOV      2   0
0007    TGETS    1   0   1  ; "addNode"
0008    KSTR     3   2      ; "readerfooter_tap"
0009    CALL     1   1   3
0010    MOV      2   0
0011    TGETS    1   0   1  ; "addNode"
0012    KSTR     3   3      ; "readerfooter_hold"
0013    TNEW     4   0
0014    CALL     1   1   4
0015    MOV      2   0
0016    TGETS    1   0   1  ; "addNode"
0017    KSTR     3   4      ; "readerhighlight_tap"
0018    TDUP     4   5
0019    CALL     1   1   4
0020    MOV      2   0
0021    TGETS    1   0   1  ; "addNode"
0022    KSTR     3   6      ; "tap_backward"
0023    TDUP     4   7
0024    CALL     1   1   4
0025    MOV      2   0
0026    TGETS    1   0   1  ; "addNode"
0027    KSTR     3   8      ; "tap_forward"
0028    TDUP     4   9
0029    CALL     1   1   4
0030    MOV      2   0
0031    TGETS    1   0   1  ; "addNode"
0032    KSTR     3  10      ; "readerhighlight_hold"
0033    TDUP     4  11
0034    CALL     1   1   4
0035    MOV      2   0
0036    TGETS    1   0   1  ; "addNode"
0037    KSTR     3  12      ; "readerhighlight_hold_release"
0038    TNEW     4   0
0039    CALL     1   1   4
0040    MOV      2   0
0041    TGETS    1   0   1  ; "addNode"
0042    KSTR     3  13      ; "readerhighlight_hold_pan"
0043    TNEW     4   0
0044    CALL     1   1   4
0045    MOV      2   0
0046    TGETS    1   0   1  ; "addNode"
0047    KSTR     3  14      ; "readermenu_tap"
0048    TDUP     4  15
0049    CALL     1   1   4
0050    MOV      2   0
0051    TGETS    1   0   1  ; "addNode"
0052    KSTR     3  16      ; "paging_swipe"
0053    TNEW     4   0
0054    CALL     1   1   4
0055    MOV      2   0
0056    TGETS    1   0   1  ; "addNode"
0057    KSTR     3  17      ; "paging_pan"
0058    TNEW     4   0
0059    CALL     1   1   4
0060    MOV      2   0
0061    TGETS    1   0   1  ; "addNode"
0062    KSTR     3  18      ; "paging_pan_release"
0063    TNEW     4   0
0064    CALL     1   1   4
0065    GGET     1  19      ; "assert"
0066    TGETS    1   1  20  ; "are"
0067    TGETS    1   1  21  ; "same"
0068    TDUP     2  22
0069    MOV      4   0
0070    TGETS    3   0  23  ; "serialize"
0071    CALL     3   0   2
0072    CALLM    1   1   1
0073    RET0     0   1

-- BYTECODE -- depgraph_spec.lua:46-68
0001    UGET     0   0      ; DepGraph
0002    MOV      1   0
0003    TGETS    0   0   0  ; "new"
0004    TNEW     2   0
0005    CALL     0   2   3
0006    MOV      2   0
0007    TGETS    1   0   1  ; "addNode"
0008    KSTR     3   2      ; "readerfooter_tap"
0009    CALL     1   1   3
0010    MOV      2   0
0011    TGETS    1   0   1  ; "addNode"
0012    KSTR     3   3      ; "readerfooter_hold"
0013    TNEW     4   0
0014    CALL     1   1   4
0015    MOV      2   0
0016    TGETS    1   0   1  ; "addNode"
0017    KSTR     3   4      ; "readerhighlight_tap"
0018    TNEW     4   0
0019    CALL     1   1   4
0020    MOV      2   0
0021    TGETS    1   0   1  ; "addNode"
0022    KSTR     3   5      ; "tap_backward"
0023    TDUP     4   6
0024    CALL     1   1   4
0025    MOV      2   0
0026    TGETS    1   0   1  ; "addNode"
0027    KSTR     3   7      ; "tap_forward"
0028    TDUP     4   8
0029    CALL     1   1   4
0030    MOV      2   0
0031    TGETS    1   0   1  ; "addNode"
0032    KSTR     3   9      ; "readerhighlight_hold"
0033    TDUP     4  10
0034    CALL     1   1   4
0035    MOV      2   0
0036    TGETS    1   0   1  ; "addNode"
0037    KSTR     3  11      ; "readerhighlight_hold_release"
0038    TNEW     4   0
0039    CALL     1   1   4
0040    MOV      2   0
0041    TGETS    1   0   1  ; "addNode"
0042    KSTR     3  12      ; "readerhighlight_hold_pan"
0043    TNEW     4   0
0044    CALL     1   1   4
0045    MOV      2   0
0046    TGETS    1   0   1  ; "addNode"
0047    KSTR     3  13      ; "readermenu_tap"
0048    TDUP     4  14
0049    CALL     1   1   4
0050    GGET     1  15      ; "assert"
0051    TGETS    1   1  16  ; "are"
0052    TGETS    1   1  17  ; "same"
0053    TDUP     2  18
0054    MOV      4   0
0055    TGETS    3   0  19  ; "serialize"
0056    CALL     3   0   2
0057    CALLM    1   1   1
0058    RET0     0   1

-- BYTECODE -- depgraph_spec.lua:71-100
0001    UGET     0   0      ; DepGraph
0002    MOV      1   0
0003    TGETS    0   0   0  ; "new"
0004    TNEW     2   0
0005    CALL     0   2   3
0006    MOV      2   0
0007    TGETS    1   0   1  ; "addNode"
0008    KSTR     3   2      ; "readerfooter_tap"
0009    TNEW     4   0
0010    CALL     1   1   4
0011    MOV      2   0
0012    TGETS    1   0   1  ; "addNode"
0013    KSTR     3   3      ; "readerfooter_hold"
0014    TNEW     4   0
0015    CALL     1   1   4
0016    MOV      2   0
0017    TGETS    1   0   1  ; "addNode"
0018    KSTR     3   4      ; "readerhighlight_tap"
0019    TDUP     4   5
0020    CALL     1   1   4
0021    MOV      2   0
0022    TGETS    1   0   1  ; "addNode"
0023    KSTR     3   6      ; "tap_backward"
0024    TDUP     4   7
0025    CALL     1   1   4
0026    MOV      2   0
0027    TGETS    1   0   1  ; "addNode"
0028    KSTR     3   8      ; "tap_forward"
0029    TDUP     4   9
0030    CALL     1   1   4
0031    MOV      2   0
0032    TGETS    1   0   1  ; "addNode"
0033    KSTR     3  10      ; "readerhighlight_hold"
0034    TDUP     4  11
0035    CALL     1   1   4
0036    MOV      2   0
0037    TGETS    1   0   1  ; "addNode"
0038    KSTR     3  12      ; "readerhighlight_hold_release"
0039    TNEW     4   0
0040    CALL     1   1   4
0041    MOV      2   0
0042    TGETS    1   0   1  ; "addNode"
0043    KSTR     3  13      ; "readerhighlight_hold_pan"
0044    TNEW     4   0
0045    CALL     1   1   4
0046    MOV      2   0
0047    TGETS    1   0   1  ; "addNode"
0048    KSTR     3  14      ; "readermenu_tap"
0049    TDUP     4  15
0050    CALL     1   1   4
0051    MOV      2   0
0052    TGETS    1   0   1  ; "addNode"
0053    KSTR     3  16      ; "paging_swipe"
0054    TNEW     4   0
0055    CALL     1   1   4
0056    MOV      2   0
0057    TGETS    1   0   1  ; "addNode"
0058    KSTR     3  17      ; "paging_pan"
0059    TNEW     4   0
0060    CALL     1   1   4
0061    MOV      2   0
0062    TGETS    1   0   1  ; "addNode"
0063    KSTR     3  18      ; "paging_pan_release"
0064    TNEW     4   0
0065    CALL     1   1   4
0066    GGET     1  19      ; "assert"
0067    TGETS    1   1  20  ; "are"
0068    TGETS    1   1  21  ; "same"
0069    TDUP     2  22
0070    MOV      4   0
0071    TGETS    3   0  23  ; "serialize"
0072    CALL     3   0   2
0073    CALLM    1   1   1
0074    RET0     0   1

-- BYTECODE -- depgraph_spec.lua:102-139
0001    UGET     0   0      ; DepGraph
0002    MOV      1   0
0003    TGETS    0   0   0  ; "new"
0004    TNEW     2   0
0005    CALL     0   2   3
0006    MOV      2   0
0007    TGETS    1   0   1  ; "addNode"
0008    KSTR     3   2      ; "tap_backward"
0009    CALL     1   1   3
0010    MOV      2   0
0011    TGETS    1   0   1  ; "addNode"
0012    KSTR     3   3      ; "tap_forward"
0013    CALL     1   1   3
0014    MOV      2   0
0015    TGETS    1   0   1  ; "addNode"
0016    KSTR     3   4      ; "readermenu_tap"
0017    CALL     1   1   3
0018    MOV      2   0
0019    TGETS    1   0   5  ; "addNodeDep"
0020    KSTR     3   2      ; "tap_backward"
0021    KSTR     4   4      ; "readermenu_tap"
0022    CALL     1   1   4
0023    MOV      2   0
0024    TGETS    1   0   5  ; "addNodeDep"
0025    KSTR     3   3      ; "tap_forward"
0026    KSTR     4   4      ; "readermenu_tap"
0027    CALL     1   1   4
0028    MOV      2   0
0029    TGETS    1   0   6  ; "removeNode"
0030    KSTR     3   3      ; "tap_forward"
0031    CALL     1   1   3
0032    MOV      2   0
0033    TGETS    1   0   6  ; "removeNode"
0034    KSTR     3   2      ; "tap_backward"
0035    CALL     1   1   3
0036    MOV      2   0
0037    TGETS    1   0   1  ; "addNode"
0038    KSTR     3   3      ; "tap_forward"
0039    CALL     1   1   3
0040    MOV      2   0
0041    TGETS    1   0   1  ; "addNode"
0042    KSTR     3   2      ; "tap_backward"
0043    CALL     1   1   3
0044    GGET     1   7      ; "assert"
0045    TGETS    1   1   8  ; "are"
0046    TGETS    1   1   9  ; "same"
0047    TDUP     2  10
0048    MOV      4   0
0049    TGETS    3   0  11  ; "serialize"
0050    CALL     3   0   2
0051    CALLM    1   1   1
0052    GGET     1   7      ; "assert"
0053    TGETS    1   1  12  ; "is_true"
0054    GGET     2  13      ; "type"
0055    TGETS    3   0  14  ; "nodes"
0056    TGETS    3   3   3  ; "tap_forward"
0057    TGETS    3   3  15  ; "deps"
0058    CALL     2   2   2
0059    ISEQS    2  16      ; "table"
0060    JMP      2 => 0063
0061    KPRI     2   1
0062    JMP      3 => 0064
0063 => KPRI     2   2
0064 => CALL     1   1   2
0065    GGET     1   7      ; "assert"
0066    TGETS    1   1  12  ; "is_true"
0067    TGETS    2   0  14  ; "nodes"
0068    TGETS    2   2   3  ; "tap_forward"
0069    TGETS    2   2  15  ; "deps"
0070    LEN      2   2
0071    KSHORT   3   0
0072    ISLT     3   2
0073    JMP      2 => 0076
0074    KPRI     2   1
0075    JMP      3 => 0077
0076 => KPRI     2   2
0077 => CALL     1   1   2
0078    GGET     1   7      ; "assert"
0079    TGETS    1   1  12  ; "is_true"
0080    GGET     2  13      ; "type"
0081    TGETS    3   0  14  ; "nodes"
0082    TGETS    3   3   2  ; "tap_backward"
0083    TGETS    3   3  15  ; "deps"
0084    CALL     2   2   2
0085    ISEQS    2  16      ; "table"
0086    JMP      2 => 0089
0087    KPRI     2   1
0088    JMP      3 => 0090
0089 => KPRI     2   2
0090 => CALL     1   1   2
0091    GGET     1   7      ; "assert"
0092    TGETS    1   1  12  ; "is_true"
0093    TGETS    2   0  14  ; "nodes"
0094    TGETS    2   2   2  ; "tap_backward"
0095    TGETS    2   2  15  ; "deps"
0096    LEN      2   2
0097    KSHORT   3   0
0098    ISLT     3   2
0099    JMP      2 => 0102
0100    KPRI     2   1
0101    JMP      3 => 0103
0102 => KPRI     2   2
0103 => CALL     1   1   2
0104    RET0     0   1

-- BYTECODE -- depgraph_spec.lua:1-140
0001    KPRI     0   0
0002    GGET     1   0      ; "setup"
0003    FNEW     2   1      ; depgraph_spec.lua:3
0004    CALL     1   1   2
0005    GGET     1   2      ; "it"
0006    KSTR     2   3      ; "should serialize simple graph"
0007    FNEW     3   4      ; depgraph_spec.lua:8
0008    CALL     1   1   3
0009    GGET     1   2      ; "it"
0010    KSTR     2   5      ; "should serialize complex graph"
0011    FNEW     3   6      ; depgraph_spec.lua:16
0012    CALL     1   1   3
0013    GGET     1   2      ; "it"
0014    KSTR     2   7      ; "should serialize complex graph2"
0015    FNEW     3   8      ; depgraph_spec.lua:46
0016    CALL     1   1   3
0017    GGET     1   2      ; "it"
0018    KSTR     2   9      ; "should serialize complex graph with dupl"~
0019    FNEW     3  10      ; depgraph_spec.lua:71
0020    CALL     1   1   3
0021    GGET     1   2      ; "it"
0022    KSTR     2  11      ; "should serialize complex graph and keep "~
0023    FNEW     3  12      ; depgraph_spec.lua:102
0024    CALL     1   1   3
0025    UCLO     0 => 0026
0026 => RET0     0   1

-- BYTECODE -- depgraph_spec.lua:0-141
0001    GGET     0   0      ; "describe"
0002    KSTR     1   1      ; "DepGraph module"
0003    FNEW     2   2      ; depgraph_spec.lua:1
0004    CALL     0   1   3
0005    RET0     0   1

