
main <./spec/unit/device_spec.lua:0,0> (5 instructions, 20 bytes at 0x7ff5954068c0)
0+ params, 3 slots, 0 upvalues, 0 locals, 2 constants, 1 function
	1	[1]	GETGLOBAL	0 -1	; describe
	2	[1]	LOADK    	1 -2	; "device module"
	3	[299]	CLOSURE  	2 0	; 0x7ff595406b60
	4	[1]	CALL     	0 3 1
	5	[299]	RETURN   	0 1

function <./spec/unit/device_spec.lua:1,299> (30 instructions, 120 bytes at 0x7ff595406b60)
0 params, 7 slots, 0 upvalues, 4 locals, 10 constants, 5 functions
	1	[4]	GETGLOBAL	2 -1	; io
	2	[4]	GETTABLE 	2 2 -2	; "open"
	3	[5]	GETGLOBAL	3 -3	; os
	4	[5]	GETTABLE 	3 3 -4	; "getenv"
	5	[7]	GETGLOBAL	4 -5	; setup
	6	[24]	CLOSURE  	5 0	; 0x7ff595406ca0
	7	[24]	MOVE     	0 0
	8	[7]	CALL     	4 2 1
	9	[26]	GETGLOBAL	4 -6	; before_each
	10	[32]	CLOSURE  	5 1	; 0x7ff595408720
	11	[32]	MOVE     	0 0
	12	[32]	MOVE     	0 1
	13	[26]	CALL     	4 2 1
	14	[34]	GETGLOBAL	4 -7	; after_each
	15	[41]	CLOSURE  	5 2	; 0x7ff595408de0
	16	[41]	MOVE     	0 1
	17	[41]	MOVE     	0 3
	18	[41]	MOVE     	0 2
	19	[34]	CALL     	4 2 1
	20	[43]	GETGLOBAL	4 -8	; describe
	21	[43]	LOADK    	5 -9	; "kobo"
	22	[194]	CLOSURE  	6 3	; 0x7ff595406d80
	23	[194]	MOVE     	0 3
	24	[43]	CALL     	4 3 1
	25	[196]	GETGLOBAL	4 -8	; describe
	26	[196]	LOADK    	5 -10	; "kindle"
	27	[297]	CLOSURE  	6 4	; 0x7ff5954073e0
	28	[297]	MOVE     	0 2
	29	[196]	CALL     	4 3 1
	30	[299]	RETURN   	0 1

function <./spec/unit/device_spec.lua:7,24> (19 instructions, 76 bytes at 0x7ff595406ca0)
0 params, 4 slots, 1 upvalue, 0 locals, 8 constants, 1 function
	1	[8]	NEWTABLE 	0 0 1
	2	[19]	CLOSURE  	1 0	; 0x7ff5954072f0
	3	[19]	SETTABLE 	0 -1 1	; "new" -
	4	[20]	SETUPVAL 	0 0	; mock_fb
	5	[21]	GETGLOBAL	0 -2	; require
	6	[21]	LOADK    	1 -3	; "commonrequire"
	7	[21]	CALL     	0 2 1
	8	[22]	GETGLOBAL	0 -4	; package
	9	[22]	GETTABLE 	0 0 -5	; "unloadAll"
	10	[22]	CALL     	0 1 1
	11	[23]	GETGLOBAL	0 -2	; require
	12	[23]	LOADK    	1 -6	; "document/canvascontext"
	13	[23]	CALL     	0 2 2
	14	[23]	SELF     	0 0 -7	; "init"
	15	[23]	GETGLOBAL	2 -2	; require
	16	[23]	LOADK    	3 -8	; "device"
	17	[23]	CALL     	2 2 0
	18	[23]	CALL     	0 0 1
	19	[24]	RETURN   	0 1

function <./spec/unit/device_spec.lua:9,19> (17 instructions, 68 bytes at 0x7ff5954072f0)
0 params, 2 slots, 0 upvalues, 0 locals, 7 constants, 7 functions
	1	[10]	NEWTABLE 	0 0 7
	2	[11]	CLOSURE  	1 0	; 0x7ff5954074c0
	3	[11]	SETTABLE 	0 -1 1	; "getSize" -
	4	[12]	CLOSURE  	1 1	; 0x7ff5954077e0
	5	[12]	SETTABLE 	0 -2 1	; "getWidth" -
	6	[13]	CLOSURE  	1 2	; 0x7ff595407b00
	7	[13]	SETTABLE 	0 -3 1	; "getDPI" -
	8	[14]	CLOSURE  	1 3	; 0x7ff595407c40
	9	[14]	SETTABLE 	0 -4 1	; "setViewport" -
	10	[15]	CLOSURE  	1 4	; 0x7ff595407df0
	11	[15]	SETTABLE 	0 -5 1	; "getRotationMode" -
	12	[16]	CLOSURE  	1 5	; 0x7ff595407e70
	13	[16]	SETTABLE 	0 -6 1	; "getScreenMode" -
	14	[17]	CLOSURE  	1 6	; 0x7ff5954079c0
	15	[17]	SETTABLE 	0 -7 1	; "setRotationMode" -
	16	[18]	RETURN   	0 2
	17	[19]	RETURN   	0 1

function <./spec/unit/device_spec.lua:11,11> (5 instructions, 20 bytes at 0x7ff5954074c0)
0 params, 2 slots, 0 upvalues, 0 locals, 4 constants, 0 functions
	1	[11]	NEWTABLE 	0 0 2
	2	[11]	SETTABLE 	0 -1 -2	; "w" 600
	3	[11]	SETTABLE 	0 -3 -4	; "h" 800
	4	[11]	RETURN   	0 2
	5	[11]	RETURN   	0 1

function <./spec/unit/device_spec.lua:12,12> (3 instructions, 12 bytes at 0x7ff5954077e0)
0 params, 2 slots, 0 upvalues, 0 locals, 1 constant, 0 functions
	1	[12]	LOADK    	0 -1	; 600
	2	[12]	RETURN   	0 2
	3	[12]	RETURN   	0 1

function <./spec/unit/device_spec.lua:13,13> (3 instructions, 12 bytes at 0x7ff595407b00)
0 params, 2 slots, 0 upvalues, 0 locals, 1 constant, 0 functions
	1	[13]	LOADK    	0 -1	; 72
	2	[13]	RETURN   	0 2
	3	[13]	RETURN   	0 1

function <./spec/unit/device_spec.lua:14,14> (1 instruction, 4 bytes at 0x7ff595407c40)
0 params, 2 slots, 0 upvalues, 0 locals, 0 constants, 0 functions
	1	[14]	RETURN   	0 1

function <./spec/unit/device_spec.lua:15,15> (3 instructions, 12 bytes at 0x7ff595407df0)
0 params, 2 slots, 0 upvalues, 0 locals, 1 constant, 0 functions
	1	[15]	LOADK    	0 -1	; 0
	2	[15]	RETURN   	0 2
	3	[15]	RETURN   	0 1

function <./spec/unit/device_spec.lua:16,16> (3 instructions, 12 bytes at 0x7ff595407e70)
0 params, 2 slots, 0 upvalues, 0 locals, 1 constant, 0 functions
	1	[16]	LOADK    	0 -1	; "portrait"
	2	[16]	RETURN   	0 2
	3	[16]	RETURN   	0 1

function <./spec/unit/device_spec.lua:17,17> (1 instruction, 4 bytes at 0x7ff5954079c0)
0 params, 2 slots, 0 upvalues, 0 locals, 0 constants, 0 functions
	1	[17]	RETURN   	0 1

function <./spec/unit/device_spec.lua:26,32> (21 instructions, 84 bytes at 0x7ff595408720)
0 params, 3 slots, 2 upvalues, 0 locals, 10 constants, 0 functions
	1	[27]	GETGLOBAL	0 -1	; package
	2	[27]	GETTABLE 	0 0 -2	; "loaded"
	3	[27]	GETUPVAL 	1 0	; mock_fb
	4	[27]	SETTABLE 	0 -3 1	; "ffi/framebuffer_mxcfb" -
	5	[28]	GETGLOBAL	0 -4	; require
	6	[28]	LOADK    	1 -5	; "device/input"
	7	[28]	CALL     	0 2 2
	8	[28]	SETUPVAL 	0 1	; mock_input
	9	[29]	GETGLOBAL	0 -6	; stub
	10	[29]	GETUPVAL 	1 1	; mock_input
	11	[29]	LOADK    	2 -7	; "open"
	12	[29]	CALL     	0 3 1
	13	[30]	GETGLOBAL	0 -6	; stub
	14	[30]	GETGLOBAL	1 -8	; os
	15	[30]	LOADK    	2 -9	; "getenv"
	16	[30]	CALL     	0 3 1
	17	[31]	GETGLOBAL	0 -6	; stub
	18	[31]	GETGLOBAL	1 -8	; os
	19	[31]	LOADK    	2 -10	; "execute"
	20	[31]	CALL     	0 3 1
	21	[32]	RETURN   	0 1

function <./spec/unit/device_spec.lua:34,41> (19 instructions, 76 bytes at 0x7ff595408de0)
0 params, 2 slots, 3 upvalues, 0 locals, 6 constants, 0 functions
	1	[35]	GETUPVAL 	0 0	; mock_input
	2	[35]	GETTABLE 	0 0 -1	; "open"
	3	[35]	SELF     	0 0 -2	; "revert"
	4	[35]	CALL     	0 2 1
	5	[36]	GETGLOBAL	0 -3	; os
	6	[36]	GETTABLE 	0 0 -4	; "getenv"
	7	[36]	SELF     	0 0 -2	; "revert"
	8	[36]	CALL     	0 2 1
	9	[37]	GETGLOBAL	0 -3	; os
	10	[37]	GETTABLE 	0 0 -5	; "execute"
	11	[37]	SELF     	0 0 -2	; "revert"
	12	[37]	CALL     	0 2 1
	13	[39]	GETGLOBAL	0 -3	; os
	14	[39]	GETUPVAL 	1 1	; osgetenv
	15	[39]	SETTABLE 	0 -4 1	; "getenv" -
	16	[40]	GETGLOBAL	0 -6	; io
	17	[40]	GETUPVAL 	1 2	; iopen
	18	[40]	SETTABLE 	0 -1 1	; "open" -
	19	[41]	RETURN   	0 1

function <./spec/unit/device_spec.lua:43,194> (35 instructions, 140 bytes at 0x7ff595406d80)
0 params, 5 slots, 1 upvalue, 2 locals, 8 constants, 7 functions
	1	[46]	GETGLOBAL	2 -1	; setup
	2	[49]	CLOSURE  	3 0	; 0x7ff595409770
	3	[49]	MOVE     	0 0
	4	[49]	MOVE     	0 1
	5	[46]	CALL     	2 2 1
	6	[51]	GETGLOBAL	2 -2	; before_each
	7	[55]	CLOSURE  	3 1	; 0x7ff595409880
	8	[55]	MOVE     	0 1
	9	[51]	CALL     	2 2 1
	10	[57]	GETGLOBAL	2 -3	; after_each
	11	[60]	CLOSURE  	3 2	; 0x7ff595409ef0
	12	[60]	MOVE     	0 1
	13	[57]	CALL     	2 2 1
	14	[62]	GETGLOBAL	2 -4	; it
	15	[62]	LOADK    	3 -5	; "should initialize properly on Kobo dahlia"
	16	[68]	CLOSURE  	4 3	; 0x7ff595409f70
	17	[62]	CALL     	2 3 1
	18	[70]	GETGLOBAL	2 -4	; it
	19	[70]	LOADK    	3 -6	; "should setup eventAdjustHooks properly for input in trilogy"
	20	[117]	CLOSURE  	4 4	; 0x7ff5954076a0
	21	[117]	GETUPVAL 	0 0	; osgetenv
	22	[117]	MOVE     	0 0
	23	[70]	CALL     	2 3 1
	24	[119]	GETGLOBAL	2 -4	; it
	25	[119]	LOADK    	3 -7	; "should setup eventAdjustHooks properly for trilogy with non-epoch ev time"
	26	[163]	CLOSURE  	4 5	; 0x7ff595408c50
	27	[163]	GETUPVAL 	0 0	; osgetenv
	28	[163]	MOVE     	0 0
	29	[119]	CALL     	2 3 1
	30	[165]	GETGLOBAL	2 -4	; it
	31	[165]	LOADK    	3 -8	; "should flush book settings before suspend"
	32	[193]	CLOSURE  	4 6	; 0x7ff59540acc0
	33	[193]	MOVE     	0 1
	34	[165]	CALL     	2 3 1
	35	[194]	RETURN   	0 1

function <./spec/unit/device_spec.lua:46,49> (9 instructions, 36 bytes at 0x7ff595409770)
0 params, 2 slots, 2 upvalues, 0 locals, 3 constants, 0 functions
	1	[47]	GETGLOBAL	0 -1	; require
	2	[47]	LOADK    	1 -2	; "ui/timeval"
	3	[47]	CALL     	0 2 2
	4	[47]	SETUPVAL 	0 0	; TimeVal
	5	[48]	GETGLOBAL	0 -1	; require
	6	[48]	LOADK    	1 -3	; "device/kobo/nickel_conf"
	7	[48]	CALL     	0 2 2
	8	[48]	SETUPVAL 	0 1	; NickelConf
	9	[49]	RETURN   	0 1

function <./spec/unit/device_spec.lua:51,55> (17 instructions, 68 bytes at 0x7ff595409880)
0 params, 3 slots, 1 upvalue, 0 locals, 6 constants, 0 functions
	1	[52]	GETGLOBAL	0 -1	; stub
	2	[52]	GETUPVAL 	1 0	; NickelConf
	3	[52]	GETTABLE 	1 1 -2	; "frontLightLevel"
	4	[52]	LOADK    	2 -3	; "get"
	5	[52]	CALL     	0 3 1
	6	[53]	GETUPVAL 	0 0	; NickelConf
	7	[53]	GETTABLE 	0 0 -2	; "frontLightLevel"
	8	[53]	GETTABLE 	0 0 -3	; "get"
	9	[53]	GETTABLE 	0 0 -4	; "returns"
	10	[53]	LOADK    	1 -5	; 0
	11	[53]	CALL     	0 2 1
	12	[54]	GETGLOBAL	0 -1	; stub
	13	[54]	GETUPVAL 	1 0	; NickelConf
	14	[54]	GETTABLE 	1 1 -6	; "frontLightState"
	15	[54]	LOADK    	2 -3	; "get"
	16	[54]	CALL     	0 3 1
	17	[55]	RETURN   	0 1

function <./spec/unit/device_spec.lua:57,60> (11 instructions, 44 bytes at 0x7ff595409ef0)
0 params, 2 slots, 1 upvalue, 0 locals, 4 constants, 0 functions
	1	[58]	GETUPVAL 	0 0	; NickelConf
	2	[58]	GETTABLE 	0 0 -1	; "frontLightLevel"
	3	[58]	GETTABLE 	0 0 -2	; "get"
	4	[58]	SELF     	0 0 -3	; "revert"
	5	[58]	CALL     	0 2 1
	6	[59]	GETUPVAL 	0 0	; NickelConf
	7	[59]	GETTABLE 	0 0 -4	; "frontLightState"
	8	[59]	GETTABLE 	0 0 -2	; "get"
	9	[59]	SELF     	0 0 -3	; "revert"
	10	[59]	CALL     	0 2 1
	11	[60]	RETURN   	0 1

function <./spec/unit/device_spec.lua:62,68> (17 instructions, 68 bytes at 0x7ff595409f70)
0 params, 4 slots, 0 upvalues, 1 local, 12 constants, 0 functions
	1	[63]	GETGLOBAL	0 -1	; os
	2	[63]	GETTABLE 	0 0 -2	; "getenv"
	3	[63]	GETTABLE 	0 0 -3	; "returns"
	4	[63]	LOADK    	1 -4	; "dahlia"
	5	[63]	CALL     	0 2 1
	6	[64]	GETGLOBAL	0 -5	; require
	7	[64]	LOADK    	1 -6	; "device/kobo/device"
	8	[64]	CALL     	0 2 2
	9	[66]	SELF     	1 0 -7	; "init"
	10	[66]	CALL     	1 2 1
	11	[67]	GETGLOBAL	1 -8	; assert
	12	[67]	GETTABLE 	1 1 -9	; "is"
	13	[67]	GETTABLE 	1 1 -10	; "same"
	14	[67]	LOADK    	2 -11	; "Kobo_dahlia"
	15	[67]	GETTABLE 	3 0 -12	; "model"
	16	[67]	CALL     	1 3 1
	17	[68]	RETURN   	0 1

function <./spec/unit/device_spec.lua:70,117> (99 instructions, 396 bytes at 0x7ff5954076a0)
0 params, 12 slots, 2 upvalues, 9 locals, 36 constants, 2 functions
	1	[71]	GETGLOBAL	0 -1	; os
	2	[71]	GETTABLE 	0 0 -2	; "getenv"
	3	[71]	GETTABLE 	0 0 -3	; "invokes"
	4	[77]	CLOSURE  	1 0	; 0x7ff5954099a0
	5	[77]	GETUPVAL 	0 0	; osgetenv
	6	[71]	CALL     	0 2 1
	7	[79]	GETGLOBAL	0 -4	; package
	8	[79]	GETTABLE 	0 0 -5	; "loaded"
	9	[79]	SETTABLE 	0 -6 -7	; "device/kobo/device" nil
	10	[80]	GETGLOBAL	0 -8	; require
	11	[80]	LOADK    	1 -6	; "device/kobo/device"
	12	[80]	CALL     	0 2 2
	13	[81]	SELF     	1 0 -9	; "init"
	14	[81]	CALL     	1 2 1
	15	[82]	GETTABLE 	1 0 -10	; "screen"
	16	[84]	GETGLOBAL	2 -11	; assert
	17	[84]	GETTABLE 	2 2 -12	; "is"
	18	[84]	GETTABLE 	2 2 -13	; "same"
	19	[84]	LOADK    	3 -14	; "Kobo_trilogy"
	20	[84]	GETTABLE 	4 0 -15	; "model"
	21	[84]	CALL     	2 3 1
	22	[85]	GETGLOBAL	2 -11	; assert
	23	[85]	GETTABLE 	2 2 -16	; "truthy"
	24	[85]	SELF     	3 0 -17	; "needsTouchScreenProbe"
	25	[85]	CALL     	3 2 0
	26	[85]	CALL     	2 0 1
	27	[87]	GETGLOBAL	2 -11	; assert
	28	[87]	GETTABLE 	2 2 -18	; "falsy"
	29	[87]	GETTABLE 	3 0 -19	; "touch_probe_ev_epoch_time"
	30	[87]	CALL     	2 2 1
	31	[88]	GETGLOBAL	2 -20	; G_reader_settings
	32	[88]	SELF     	2 2 -21	; "saveSetting"
	33	[88]	LOADK    	4 -22	; "kobo_touch_switch_xy"
	34	[88]	LOADBOOL 	5 1 0
	35	[88]	CALL     	2 4 1
	36	[89]	SELF     	2 0 -23	; "touchScreenProbe"
	37	[89]	CALL     	2 2 1
	38	[90]	SELF     	2 1 -24	; "getWidth"
	39	[90]	CALL     	2 2 2
	40	[90]	SUB      	2 2 -25	; - 5
	41	[90]	LOADK    	3 -26	; 10
	42	[91]	LOADK    	4 -27	; 3
	43	[92]	LOADK    	5 -28	; 0
	44	[93]	LOADK    	6 -29	; 1
	45	[95]	NEWTABLE 	7 0 4
	46	[96]	SETTABLE 	7 -30 4	; "type" -
	47	[97]	SETTABLE 	7 -31 5	; "code" -
	48	[98]	SETTABLE 	7 -32 3	; "value" -
	49	[99]	GETUPVAL 	8 1	; TimeVal
	50	[99]	SELF     	8 8 -34	; "now"
	51	[99]	CALL     	8 2 2
	52	[99]	SETTABLE 	7 -33 8	; "time" -
	53	[101]	NEWTABLE 	8 0 4
	54	[102]	SETTABLE 	8 -30 4	; "type" -
	55	[103]	SETTABLE 	8 -31 6	; "code" -
	56	[104]	SELF     	9 1 -24	; "getWidth"
	57	[104]	CALL     	9 2 2
	58	[104]	SUB      	9 9 2
	59	[104]	SETTABLE 	8 -32 9	; "value" -
	60	[105]	GETUPVAL 	9 1	; TimeVal
	61	[105]	SELF     	9 9 -34	; "now"
	62	[105]	CALL     	9 2 2
	63	[105]	SETTABLE 	8 -33 9	; "time" -
	64	[108]	GETTABLE 	9 0 -35	; "input"
	65	[108]	SELF     	9 9 -36	; "eventAdjustHook"
	66	[108]	MOVE     	11 7
	67	[108]	CALL     	9 3 1
	68	[109]	GETTABLE 	9 0 -35	; "input"
	69	[109]	SELF     	9 9 -36	; "eventAdjustHook"
	70	[109]	MOVE     	11 8
	71	[109]	CALL     	9 3 1
	72	[110]	GETGLOBAL	9 -11	; assert
	73	[110]	GETTABLE 	9 9 -12	; "is"
	74	[110]	GETTABLE 	9 9 -13	; "same"
	75	[110]	MOVE     	10 2
	76	[110]	GETTABLE 	11 8 -32	; "value"
	77	[110]	CALL     	9 3 1
	78	[111]	GETGLOBAL	9 -11	; assert
	79	[111]	GETTABLE 	9 9 -12	; "is"
	80	[111]	GETTABLE 	9 9 -13	; "same"
	81	[111]	MOVE     	10 5
	82	[111]	GETTABLE 	11 8 -31	; "code"
	83	[111]	CALL     	9 3 1
	84	[112]	GETGLOBAL	9 -11	; assert
	85	[112]	GETTABLE 	9 9 -12	; "is"
	86	[112]	GETTABLE 	9 9 -13	; "same"
	87	[112]	MOVE     	10 3
	88	[112]	GETTABLE 	11 7 -32	; "value"
	89	[112]	CALL     	9 3 1
	90	[113]	GETGLOBAL	9 -11	; assert
	91	[113]	GETTABLE 	9 9 -12	; "is"
	92	[113]	GETTABLE 	9 9 -13	; "same"
	93	[113]	MOVE     	10 6
	94	[113]	GETTABLE 	11 7 -31	; "code"
	95	[113]	CALL     	9 3 1
	96	[116]	GETTABLE 	9 0 -35	; "input"
	97	[116]	CLOSURE  	10 1	; 0x7ff595408b30
	98	[116]	SETTABLE 	9 -36 10	; "eventAdjustHook" -
	99	[117]	RETURN   	0 1

function <./spec/unit/device_spec.lua:71,77> (10 instructions, 40 bytes at 0x7ff5954099a0)
1 param, 3 slots, 1 upvalue, 1 local, 2 constants, 0 functions
	1	[72]	EQ       	0 0 -1	; - "PRODUCT"
	2	[72]	JMP      	3	; to 6
	3	[73]	LOADK    	1 -2	; "trilogy"
	4	[73]	RETURN   	1 2
	5	[73]	JMP      	4	; to 10
	6	[75]	GETUPVAL 	1 0	; osgetenv
	7	[75]	MOVE     	2 0
	8	[75]	TAILCALL 	1 2 0
	9	[75]	RETURN   	1 0
	10	[77]	RETURN   	0 1

function <./spec/unit/device_spec.lua:116,116> (1 instruction, 4 bytes at 0x7ff595408b30)
0 params, 2 slots, 0 upvalues, 0 locals, 0 constants, 0 functions
	1	[116]	RETURN   	0 1

function <./spec/unit/device_spec.lua:119,163> (89 instructions, 356 bytes at 0x7ff595408c50)
0 params, 12 slots, 2 upvalues, 10 locals, 35 constants, 2 functions
	1	[120]	GETGLOBAL	0 -1	; os
	2	[120]	GETTABLE 	0 0 -2	; "getenv"
	3	[120]	GETTABLE 	0 0 -3	; "invokes"
	4	[126]	CLOSURE  	1 0	; 0x7ff59540ab00
	5	[126]	GETUPVAL 	0 0	; osgetenv
	6	[120]	CALL     	0 2 1
	7	[128]	GETGLOBAL	0 -4	; package
	8	[128]	GETTABLE 	0 0 -5	; "loaded"
	9	[128]	SETTABLE 	0 -6 -7	; "device/kobo/device" nil
	10	[129]	GETGLOBAL	0 -8	; require
	11	[129]	LOADK    	1 -6	; "device/kobo/device"
	12	[129]	CALL     	0 2 2
	13	[130]	SELF     	1 0 -9	; "init"
	14	[130]	CALL     	1 2 1
	15	[131]	GETTABLE 	1 0 -10	; "screen"
	16	[133]	GETGLOBAL	2 -11	; assert
	17	[133]	GETTABLE 	2 2 -12	; "is"
	18	[133]	GETTABLE 	2 2 -13	; "same"
	19	[133]	LOADK    	3 -14	; "Kobo_trilogy"
	20	[133]	GETTABLE 	4 0 -15	; "model"
	21	[133]	CALL     	2 3 1
	22	[134]	GETGLOBAL	2 -11	; assert
	23	[134]	GETTABLE 	2 2 -16	; "truthy"
	24	[134]	SELF     	3 0 -17	; "needsTouchScreenProbe"
	25	[134]	CALL     	3 2 0
	26	[134]	CALL     	2 0 1
	27	[136]	GETGLOBAL	2 -11	; assert
	28	[136]	GETTABLE 	2 2 -18	; "falsy"
	29	[136]	GETTABLE 	3 0 -19	; "touch_probe_ev_epoch_time"
	30	[136]	CALL     	2 2 1
	31	[137]	SELF     	2 0 -20	; "touchScreenProbe"
	32	[137]	CALL     	2 2 1
	33	[138]	SELF     	2 1 -21	; "getWidth"
	34	[138]	CALL     	2 2 2
	35	[138]	SUB      	2 2 -22	; - 5
	36	[138]	LOADK    	3 -23	; 10
	37	[139]	LOADK    	4 -24	; 3
	38	[140]	LOADK    	5 -25	; 0
	39	[141]	LOADK    	6 -26	; 1
	40	[142]	NEWTABLE 	7 0 4
	41	[143]	SETTABLE 	7 -27 4	; "type" -
	42	[144]	SETTABLE 	7 -28 5	; "code" -
	43	[145]	SETTABLE 	7 -29 2	; "value" -
	44	[146]	NEWTABLE 	8 0 1
	45	[146]	SETTABLE 	8 -31 -32	; "sec" 1000
	46	[146]	SETTABLE 	7 -30 8	; "time" -
	47	[148]	NEWTABLE 	8 0 4
	48	[149]	SETTABLE 	8 -27 4	; "type" -
	49	[150]	SETTABLE 	8 -28 6	; "code" -
	50	[151]	SETTABLE 	8 -29 3	; "value" -
	51	[152]	NEWTABLE 	9 0 1
	52	[152]	SETTABLE 	9 -31 -32	; "sec" 1000
	53	[152]	SETTABLE 	8 -30 9	; "time" -
	54	[155]	GETTABLE 	9 0 -33	; "input"
	55	[155]	SELF     	9 9 -34	; "eventAdjustHook"
	56	[155]	MOVE     	11 7
	57	[155]	CALL     	9 3 1
	58	[156]	GETTABLE 	9 0 -33	; "input"
	59	[156]	SELF     	9 9 -34	; "eventAdjustHook"
	60	[156]	MOVE     	11 8
	61	[156]	CALL     	9 3 1
	62	[157]	GETUPVAL 	9 1	; TimeVal
	63	[157]	SELF     	9 9 -35	; "now"
	64	[157]	CALL     	9 2 2
	65	[157]	GETTABLE 	9 9 -31	; "sec"
	66	[158]	GETGLOBAL	10 -11	; assert
	67	[158]	GETTABLE 	10 10 -16	; "truthy"
	68	[158]	GETTABLE 	11 7 -30	; "time"
	69	[158]	GETTABLE 	11 11 -31	; "sec"
	70	[158]	SUB      	11 9 11
	71	[158]	LT       	1 11 -23	; - 10
	72	[158]	JMP      	1	; to 74
	73	[158]	LOADBOOL 	11 0 1
	74	[158]	LOADBOOL 	11 1 0
	75	[158]	CALL     	10 2 1
	76	[159]	GETGLOBAL	10 -11	; assert
	77	[159]	GETTABLE 	10 10 -16	; "truthy"
	78	[159]	GETTABLE 	11 8 -30	; "time"
	79	[159]	GETTABLE 	11 11 -31	; "sec"
	80	[159]	SUB      	11 9 11
	81	[159]	LT       	1 11 -23	; - 10
	82	[159]	JMP      	1	; to 84
	83	[159]	LOADBOOL 	11 0 1
	84	[159]	LOADBOOL 	11 1 0
	85	[159]	CALL     	10 2 1
	86	[162]	GETTABLE 	10 0 -33	; "input"
	87	[162]	CLOSURE  	11 1	; 0x7ff59540aa50
	88	[162]	SETTABLE 	10 -34 11	; "eventAdjustHook" -
	89	[163]	RETURN   	0 1

function <./spec/unit/device_spec.lua:120,126> (10 instructions, 40 bytes at 0x7ff59540ab00)
1 param, 3 slots, 1 upvalue, 1 local, 2 constants, 0 functions
	1	[121]	EQ       	0 0 -1	; - "PRODUCT"
	2	[121]	JMP      	3	; to 6
	3	[122]	LOADK    	1 -2	; "trilogy"
	4	[122]	RETURN   	1 2
	5	[122]	JMP      	4	; to 10
	6	[124]	GETUPVAL 	1 0	; osgetenv
	7	[124]	MOVE     	2 0
	8	[124]	TAILCALL 	1 2 0
	9	[124]	RETURN   	1 0
	10	[126]	RETURN   	0 1

function <./spec/unit/device_spec.lua:162,162> (1 instruction, 4 bytes at 0x7ff59540aa50)
0 params, 2 slots, 0 upvalues, 0 locals, 0 constants, 0 functions
	1	[162]	RETURN   	0 1

function <./spec/unit/device_spec.lua:165,193> (77 instructions, 308 bytes at 0x7ff59540acc0)
0 params, 8 slots, 1 upvalue, 5 locals, 27 constants, 0 functions
	1	[166]	LOADK    	0 -1	; "spec/front/unit/data/tall.pdf"
	2	[167]	GETGLOBAL	1 -2	; require
	3	[167]	LOADK    	2 -3	; "apps/reader/readerui"
	4	[167]	CALL     	1 2 2
	5	[168]	GETGLOBAL	2 -2	; require
	6	[168]	LOADK    	3 -4	; "device"
	7	[168]	CALL     	2 2 2
	8	[170]	GETUPVAL 	3 0	; NickelConf
	9	[170]	GETTABLE 	3 3 -5	; "frontLightLevel"
	10	[170]	GETTABLE 	3 3 -6	; "get"
	11	[170]	GETTABLE 	3 3 -7	; "returns"
	12	[170]	LOADK    	4 -8	; 1
	13	[170]	CALL     	3 2 1
	14	[171]	GETUPVAL 	3 0	; NickelConf
	15	[171]	GETTABLE 	3 3 -9	; "frontLightState"
	16	[171]	GETTABLE 	3 3 -6	; "get"
	17	[171]	GETTABLE 	3 3 -7	; "returns"
	18	[171]	LOADK    	4 -10	; 0
	19	[171]	CALL     	3 2 1
	20	[173]	GETGLOBAL	3 -2	; require
	21	[173]	LOADK    	4 -11	; "ui/uimanager"
	22	[173]	CALL     	3 2 2
	23	[174]	GETGLOBAL	4 -12	; stub
	24	[174]	MOVE     	5 2
	25	[174]	LOADK    	6 -13	; "suspend"
	26	[174]	CALL     	4 3 1
	27	[175]	GETGLOBAL	4 -12	; stub
	28	[175]	GETTABLE 	5 2 -14	; "powerd"
	29	[175]	LOADK    	6 -15	; "beforeSuspend"
	30	[175]	CALL     	4 3 1
	31	[176]	GETGLOBAL	4 -12	; stub
	32	[176]	MOVE     	5 2
	33	[176]	LOADK    	6 -16	; "isKobo"
	34	[176]	CALL     	4 3 1
	35	[178]	GETTABLE 	4 2 -16	; "isKobo"
	36	[178]	GETTABLE 	4 4 -7	; "returns"
	37	[178]	LOADBOOL 	5 1 0
	38	[178]	CALL     	4 2 1
	39	[179]	SELF     	4 3 -17	; "init"
	40	[179]	CALL     	4 2 1
	41	[181]	SELF     	4 1 -18	; "doShowReader"
	42	[181]	MOVE     	6 0
	43	[181]	CALL     	4 3 1
	44	[182]	GETTABLE 	4 1 -19	; "_getRunningInstance"
	45	[182]	CALL     	4 1 2
	46	[183]	GETGLOBAL	5 -12	; stub
	47	[183]	MOVE     	6 4
	48	[183]	LOADK    	7 -20	; "onFlushSettings"
	49	[183]	CALL     	5 3 1
	50	[184]	GETTABLE 	5 3 -21	; "event_handlers"
	51	[184]	GETTABLE 	5 5 -22	; "PowerPress"
	52	[184]	CALL     	5 1 1
	53	[185]	GETTABLE 	5 3 -21	; "event_handlers"
	54	[185]	GETTABLE 	5 5 -23	; "PowerRelease"
	55	[185]	CALL     	5 1 1
	56	[186]	GETGLOBAL	5 -24	; assert
	57	[186]	GETTABLE 	5 5 -12	; "stub"
	58	[186]	GETTABLE 	6 4 -20	; "onFlushSettings"
	59	[186]	CALL     	5 2 2
	60	[186]	GETTABLE 	5 5 -25	; "was_called"
	61	[186]	CALL     	5 1 1
	62	[188]	GETTABLE 	5 2 -13	; "suspend"
	63	[188]	SELF     	5 5 -26	; "revert"
	64	[188]	CALL     	5 2 1
	65	[189]	GETTABLE 	5 2 -14	; "powerd"
	66	[189]	GETTABLE 	5 5 -15	; "beforeSuspend"
	67	[189]	SELF     	5 5 -26	; "revert"
	68	[189]	CALL     	5 2 1
	69	[190]	GETTABLE 	5 2 -16	; "isKobo"
	70	[190]	SELF     	5 5 -26	; "revert"
	71	[190]	CALL     	5 2 1
	72	[191]	GETTABLE 	5 4 -20	; "onFlushSettings"
	73	[191]	SELF     	5 5 -26	; "revert"
	74	[191]	CALL     	5 2 1
	75	[192]	SELF     	5 4 -27	; "onClose"
	76	[192]	CALL     	5 2 1
	77	[193]	RETURN   	0 1

function <./spec/unit/device_spec.lua:196,297> (16 instructions, 64 bytes at 0x7ff5954073e0)
0 params, 3 slots, 1 upvalue, 0 locals, 4 constants, 3 functions
	1	[197]	GETGLOBAL	0 -1	; it
	2	[197]	LOADK    	1 -2	; "should initialize voyage without error"
	3	[217]	CLOSURE  	2 0	; 0x7ff5954078d0
	4	[217]	GETUPVAL 	0 0	; iopen
	5	[197]	CALL     	0 3 1
	6	[219]	GETGLOBAL	0 -1	; it
	7	[219]	LOADK    	1 -3	; "should toggle frontlight"
	8	[255]	CLOSURE  	2 1	; 0x7ff59540c090
	9	[255]	GETUPVAL 	0 0	; iopen
	10	[219]	CALL     	0 3 1
	11	[257]	GETGLOBAL	0 -1	; it
	12	[257]	LOADK    	1 -4	; "oasis should interpret orientation event"
	13	[296]	CLOSURE  	2 2	; 0x7ff59540d7d0
	14	[296]	GETUPVAL 	0 0	; iopen
	15	[257]	CALL     	0 3 1
	16	[297]	RETURN   	0 1

function <./spec/unit/device_spec.lua:197,217> (46 instructions, 184 bytes at 0x7ff5954078d0)
0 params, 4 slots, 1 upvalue, 1 local, 21 constants, 1 function
	1	[198]	GETGLOBAL	0 -1	; io
	2	[207]	CLOSURE  	1 0	; 0x7ff595409d40
	3	[207]	GETUPVAL 	0 0	; iopen
	4	[207]	SETTABLE 	0 -2 1	; "open" -
	5	[209]	GETGLOBAL	0 -3	; require
	6	[209]	LOADK    	1 -4	; "device/kindle/device"
	7	[209]	CALL     	0 2 2
	8	[210]	GETGLOBAL	1 -5	; assert
	9	[210]	GETTABLE 	1 1 -6	; "is"
	10	[210]	GETTABLE 	1 1 -7	; "same"
	11	[210]	GETTABLE 	2 0 -8	; "model"
	12	[210]	LOADK    	3 -9	; "KindleVoyage"
	13	[210]	CALL     	1 3 1
	14	[211]	SELF     	1 0 -10	; "init"
	15	[211]	CALL     	1 2 1
	16	[212]	GETGLOBAL	1 -5	; assert
	17	[212]	GETTABLE 	1 1 -6	; "is"
	18	[212]	GETTABLE 	1 1 -7	; "same"
	19	[212]	GETTABLE 	2 0 -11	; "input"
	20	[212]	GETTABLE 	2 2 -12	; "event_map"
	21	[212]	GETTABLE 	2 2 -13	; 104
	22	[212]	LOADK    	3 -14	; "LPgBack"
	23	[212]	CALL     	1 3 1
	24	[213]	GETGLOBAL	1 -5	; assert
	25	[213]	GETTABLE 	1 1 -6	; "is"
	26	[213]	GETTABLE 	1 1 -7	; "same"
	27	[213]	GETTABLE 	2 0 -11	; "input"
	28	[213]	GETTABLE 	2 2 -12	; "event_map"
	29	[213]	GETTABLE 	2 2 -15	; 109
	30	[213]	LOADK    	3 -16	; "LPgFwd"
	31	[213]	CALL     	1 3 1
	32	[214]	GETGLOBAL	1 -5	; assert
	33	[214]	GETTABLE 	1 1 -6	; "is"
	34	[214]	GETTABLE 	1 1 -7	; "same"
	35	[214]	GETTABLE 	2 0 -17	; "powerd"
	36	[214]	GETTABLE 	2 2 -18	; "fl_min"
	37	[214]	LOADK    	3 -19	; 0
	38	[214]	CALL     	1 3 1
	39	[216]	GETGLOBAL	1 -5	; assert
	40	[216]	GETTABLE 	1 1 -6	; "is"
	41	[216]	GETTABLE 	1 1 -7	; "same"
	42	[216]	GETTABLE 	2 0 -17	; "powerd"
	43	[216]	GETTABLE 	2 2 -20	; "fl_max"
	44	[216]	LOADK    	3 -21	; 25
	45	[216]	CALL     	1 3 1
	46	[217]	RETURN   	0 1

function <./spec/unit/device_spec.lua:198,207> (15 instructions, 60 bytes at 0x7ff595409d40)
2 params, 5 slots, 1 upvalue, 2 locals, 3 constants, 2 functions
	1	[199]	EQ       	0 0 -1	; - "/proc/usid"
	2	[199]	JMP      	7	; to 10
	3	[200]	NEWTABLE 	2 0 2
	4	[201]	CLOSURE  	3 0	; 0x7ff59540b020
	5	[201]	SETTABLE 	2 -2 3	; "read" -
	6	[202]	CLOSURE  	3 1	; 0x7ff595409100
	7	[202]	SETTABLE 	2 -3 3	; "close" -
	8	[203]	RETURN   	2 2
	9	[203]	JMP      	5	; to 15
	10	[205]	GETUPVAL 	2 0	; iopen
	11	[205]	MOVE     	3 0
	12	[205]	MOVE     	4 1
	13	[205]	TAILCALL 	2 3 0
	14	[205]	RETURN   	2 0
	15	[207]	RETURN   	0 1

function <./spec/unit/device_spec.lua:201,201> (3 instructions, 12 bytes at 0x7ff59540b020)
0 params, 2 slots, 0 upvalues, 0 locals, 1 constant, 0 functions
	1	[201]	LOADK    	0 -1	; "B013XX"
	2	[201]	RETURN   	0 2
	3	[201]	RETURN   	0 1

function <./spec/unit/device_spec.lua:202,202> (1 instruction, 4 bytes at 0x7ff595409100)
0 params, 2 slots, 0 upvalues, 0 locals, 0 constants, 0 functions
	1	[202]	RETURN   	0 1

function <./spec/unit/device_spec.lua:219,255> (56 instructions, 224 bytes at 0x7ff59540c090)
0 params, 4 slots, 1 upvalue, 1 local, 19 constants, 1 function
	1	[220]	GETGLOBAL	0 -1	; io
	2	[234]	CLOSURE  	1 0	; 0x7ff59540c380
	3	[234]	GETUPVAL 	0 0	; iopen
	4	[234]	SETTABLE 	0 -2 1	; "open" -
	5	[236]	GETGLOBAL	0 -3	; require
	6	[236]	LOADK    	1 -4	; "device/kindle/device"
	7	[236]	CALL     	0 2 2
	8	[237]	SELF     	1 0 -5	; "init"
	9	[237]	CALL     	1 2 1
	10	[239]	GETGLOBAL	1 -6	; assert
	11	[239]	GETTABLE 	1 1 -7	; "is"
	12	[239]	GETTABLE 	1 1 -8	; "same"
	13	[239]	GETTABLE 	2 0 -9	; "powerd"
	14	[239]	GETTABLE 	2 2 -10	; "fl_intensity"
	15	[239]	LOADK    	3 -11	; 12
	16	[239]	CALL     	1 3 1
	17	[240]	GETTABLE 	1 0 -9	; "powerd"
	18	[240]	SELF     	1 1 -12	; "setIntensity"
	19	[240]	LOADK    	3 -13	; 5
	20	[240]	CALL     	1 3 1
	21	[241]	GETGLOBAL	1 -6	; assert
	22	[241]	GETTABLE 	1 1 -7	; "is"
	23	[241]	GETTABLE 	1 1 -8	; "same"
	24	[241]	GETTABLE 	2 0 -9	; "powerd"
	25	[241]	GETTABLE 	2 2 -10	; "fl_intensity"
	26	[241]	LOADK    	3 -13	; 5
	27	[241]	CALL     	1 3 1
	28	[243]	GETTABLE 	1 0 -9	; "powerd"
	29	[243]	SELF     	1 1 -14	; "toggleFrontlight"
	30	[243]	CALL     	1 2 1
	31	[244]	GETGLOBAL	1 -6	; assert
	32	[244]	GETTABLE 	1 1 -15	; "stub"
	33	[244]	GETGLOBAL	2 -16	; os
	34	[244]	GETTABLE 	2 2 -17	; "execute"
	35	[244]	CALL     	1 2 2
	36	[244]	GETTABLE 	1 1 -18	; "was_called_with"
	37	[245]	LOADK    	2 -19	; "echo -n 0 > /sys/class/backlight/max77696-bl/brightness"
	38	[244]	CALL     	1 2 1
	39	[248]	GETGLOBAL	1 -6	; assert
	40	[248]	GETTABLE 	1 1 -7	; "is"
	41	[248]	GETTABLE 	1 1 -8	; "same"
	42	[248]	GETTABLE 	2 0 -9	; "powerd"
	43	[248]	GETTABLE 	2 2 -10	; "fl_intensity"
	44	[248]	LOADK    	3 -13	; 5
	45	[248]	CALL     	1 3 1
	46	[251]	GETTABLE 	1 0 -9	; "powerd"
	47	[251]	SELF     	1 1 -14	; "toggleFrontlight"
	48	[251]	CALL     	1 2 1
	49	[252]	GETGLOBAL	1 -6	; assert
	50	[252]	GETTABLE 	1 1 -7	; "is"
	51	[252]	GETTABLE 	1 1 -8	; "same"
	52	[252]	GETTABLE 	2 0 -9	; "powerd"
	53	[252]	GETTABLE 	2 2 -10	; "fl_intensity"
	54	[252]	LOADK    	3 -13	; 5
	55	[252]	CALL     	1 3 1
	56	[255]	RETURN   	0 1

function <./spec/unit/device_spec.lua:220,234> (24 instructions, 96 bytes at 0x7ff59540c380)
2 params, 5 slots, 1 upvalue, 2 locals, 4 constants, 4 functions
	1	[221]	EQ       	0 0 -1	; - "/proc/usid"
	2	[221]	JMP      	7	; to 10
	3	[222]	NEWTABLE 	2 0 2
	4	[223]	CLOSURE  	3 0	; 0x7ff59540c970
	5	[223]	SETTABLE 	2 -2 3	; "read" -
	6	[224]	CLOSURE  	3 1	; 0x7ff59540c830
	7	[224]	SETTABLE 	2 -3 3	; "close" -
	8	[225]	RETURN   	2 2
	9	[225]	JMP      	14	; to 24
	10	[226]	EQ       	0 0 -4	; - "/sys/class/backlight/max77696-bl/brightness"
	11	[226]	JMP      	7	; to 19
	12	[227]	NEWTABLE 	2 0 2
	13	[228]	CLOSURE  	3 2	; 0x7ff59540cd60
	14	[228]	SETTABLE 	2 -2 3	; "read" -
	15	[229]	CLOSURE  	3 3	; 0x7ff59540cf50
	16	[229]	SETTABLE 	2 -3 3	; "close" -
	17	[230]	RETURN   	2 2
	18	[230]	JMP      	5	; to 24
	19	[232]	GETUPVAL 	2 0	; iopen
	20	[232]	MOVE     	3 0
	21	[232]	MOVE     	4 1
	22	[232]	TAILCALL 	2 3 0
	23	[232]	RETURN   	2 0
	24	[234]	RETURN   	0 1

function <./spec/unit/device_spec.lua:223,223> (3 instructions, 12 bytes at 0x7ff59540c970)
0 params, 2 slots, 0 upvalues, 0 locals, 1 constant, 0 functions
	1	[223]	LOADK    	0 -1	; "B013XX"
	2	[223]	RETURN   	0 2
	3	[223]	RETURN   	0 1

function <./spec/unit/device_spec.lua:224,224> (1 instruction, 4 bytes at 0x7ff59540c830)
0 params, 2 slots, 0 upvalues, 0 locals, 0 constants, 0 functions
	1	[224]	RETURN   	0 1

function <./spec/unit/device_spec.lua:228,228> (3 instructions, 12 bytes at 0x7ff59540cd60)
0 params, 2 slots, 0 upvalues, 0 locals, 1 constant, 0 functions
	1	[228]	LOADK    	0 -1	; "12"
	2	[228]	RETURN   	0 2
	3	[228]	RETURN   	0 1

function <./spec/unit/device_spec.lua:229,229> (1 instruction, 4 bytes at 0x7ff59540cf50)
0 params, 2 slots, 0 upvalues, 0 locals, 0 constants, 0 functions
	1	[229]	RETURN   	0 1

function <./spec/unit/device_spec.lua:257,296> (63 instructions, 252 bytes at 0x7ff59540d7d0)
0 params, 5 slots, 1 upvalue, 2 locals, 34 constants, 1 function
	1	[258]	GETGLOBAL	0 -1	; package
	2	[258]	GETTABLE 	0 0 -2	; "unload"
	3	[258]	LOADK    	1 -3	; "device/kindle/device"
	4	[258]	CALL     	0 2 1
	5	[259]	GETGLOBAL	0 -4	; io
	6	[270]	CLOSURE  	1 0	; 0x7ff59540b7d0
	7	[270]	GETUPVAL 	0 0	; iopen
	8	[270]	SETTABLE 	0 -5 1	; "open" -
	9	[272]	GETGLOBAL	0 -7	; require
	10	[272]	LOADK    	1 -8	; "ffi/input"
	11	[272]	CALL     	0 2 2
	12	[272]	SETGLOBAL	0 -6	; mock_ffi_input
	13	[273]	GETGLOBAL	0 -9	; stub
	14	[273]	GETGLOBAL	1 -6	; mock_ffi_input
	15	[273]	LOADK    	2 -10	; "waitForEvent"
	16	[273]	CALL     	0 3 1
	17	[274]	GETGLOBAL	0 -6	; mock_ffi_input
	18	[274]	GETTABLE 	0 0 -10	; "waitForEvent"
	19	[274]	GETTABLE 	0 0 -11	; "returns"
	20	[274]	NEWTABLE 	1 0 4
	21	[275]	SETTABLE 	1 -12 -13	; "type" 3
	22	[276]	NEWTABLE 	2 0 2
	23	[277]	SETTABLE 	2 -15 -16	; "usec" 450565
	24	[278]	SETTABLE 	2 -17 -18	; "sec" 1471081881
	25	[279]	SETTABLE 	1 -14 2	; "time" -
	26	[280]	SETTABLE 	1 -19 -20	; "code" 24
	27	[281]	SETTABLE 	1 -21 -22	; "value" 16
	28	[274]	CALL     	0 2 1
	29	[284]	GETGLOBAL	0 -7	; require
	30	[284]	LOADK    	1 -23	; "ui/uimanager"
	31	[284]	CALL     	0 2 2
	32	[285]	GETGLOBAL	1 -9	; stub
	33	[285]	MOVE     	2 0
	34	[285]	LOADK    	3 -24	; "onRotation"
	35	[285]	CALL     	1 3 1
	36	[287]	GETGLOBAL	1 -7	; require
	37	[287]	LOADK    	2 -3	; "device/kindle/device"
	38	[287]	CALL     	1 2 2
	39	[288]	GETGLOBAL	2 -25	; assert
	40	[288]	GETTABLE 	2 2 -26	; "is"
	41	[288]	GETTABLE 	2 2 -27	; "same"
	42	[288]	LOADK    	3 -28	; "KindleOasis"
	43	[288]	GETTABLE 	4 1 -29	; "model"
	44	[288]	CALL     	2 3 1
	45	[289]	SELF     	2 1 -30	; "init"
	46	[289]	CALL     	2 2 1
	47	[291]	GETTABLE 	2 1 -31	; "input"
	48	[291]	SELF     	2 2 -32	; "waitEvent"
	49	[291]	CALL     	2 2 1
	50	[292]	GETGLOBAL	2 -25	; assert
	51	[292]	GETTABLE 	2 2 -9	; "stub"
	52	[292]	GETTABLE 	3 0 -24	; "onRotation"
	53	[292]	CALL     	2 2 2
	54	[292]	GETTABLE 	2 2 -33	; "was_called"
	55	[292]	CALL     	2 1 1
	56	[294]	GETGLOBAL	2 -6	; mock_ffi_input
	57	[294]	GETTABLE 	2 2 -10	; "waitForEvent"
	58	[294]	SELF     	2 2 -34	; "revert"
	59	[294]	CALL     	2 2 1
	60	[295]	GETTABLE 	2 0 -24	; "onRotation"
	61	[295]	SELF     	2 2 -34	; "revert"
	62	[295]	CALL     	2 2 1
	63	[296]	RETURN   	0 1

function <./spec/unit/device_spec.lua:259,270> (15 instructions, 60 bytes at 0x7ff59540b7d0)
2 params, 5 slots, 1 upvalue, 2 locals, 3 constants, 2 functions
	1	[260]	EQ       	0 0 -1	; - "/proc/usid"
	2	[260]	JMP      	7	; to 10
	3	[261]	NEWTABLE 	2 0 2
	4	[264]	CLOSURE  	3 0	; 0x7ff59540dc80
	5	[264]	SETTABLE 	2 -2 3	; "read" -
	6	[265]	CLOSURE  	3 1	; 0x7ff59540da60
	7	[265]	SETTABLE 	2 -3 3	; "close" -
	8	[266]	RETURN   	2 2
	9	[266]	JMP      	5	; to 15
	10	[268]	GETUPVAL 	2 0	; iopen
	11	[268]	MOVE     	3 0
	12	[268]	MOVE     	4 1
	13	[268]	TAILCALL 	2 3 0
	14	[268]	RETURN   	2 0
	15	[270]	RETURN   	0 1

function <./spec/unit/device_spec.lua:262,264> (3 instructions, 12 bytes at 0x7ff59540dc80)
0 params, 2 slots, 0 upvalues, 0 locals, 1 constant, 0 functions
	1	[263]	LOADK    	0 -1	; "G0B0GCXXX"
	2	[263]	RETURN   	0 2
	3	[264]	RETURN   	0 1

function <./spec/unit/device_spec.lua:265,265> (1 instruction, 4 bytes at 0x7ff59540da60)
0 params, 2 slots, 0 upvalues, 0 locals, 0 constants, 0 functions
	1	[265]	RETURN   	0 1
