-- BYTECODE -- device_spec.lua:11-11
0001    TDUP     0   0
0002    RET1     0   2

-- BYTECODE -- device_spec.lua:12-12
0001    KSHORT   0 600
0002    RET1     0   2

-- BYTECODE -- device_spec.lua:13-13
0001    KSHORT   0  72
0002    RET1     0   2

-- BYTECODE -- device_spec.lua:14-14
0001    RET0     0   1

-- BYTECODE -- device_spec.lua:15-15
0001    KSHORT   0   0
0002    RET1     0   2

-- BYTECODE -- device_spec.lua:16-16
0001    KSTR     0   0      ; "portrait"
0002    RET1     0   2

-- BYTECODE -- device_spec.lua:17-17
0001    RET0     0   1

-- BYTECODE -- device_spec.lua:9-19
0001    TDUP     0   1
0002    FNEW     1   0      ; device_spec.lua:11
0003    TSETS    1   0   2  ; "getSize"
0004    FNEW     1   3      ; device_spec.lua:12
0005    TSETS    1   0   4  ; "getWidth"
0006    FNEW     1   5      ; device_spec.lua:13
0007    TSETS    1   0   6  ; "getDPI"
0008    FNEW     1   7      ; device_spec.lua:14
0009    TSETS    1   0   8  ; "setViewport"
0010    FNEW     1   9      ; device_spec.lua:15
0011    TSETS    1   0  10  ; "getRotationMode"
0012    FNEW     1  11      ; device_spec.lua:16
0013    TSETS    1   0  12  ; "getScreenMode"
0014    FNEW     1  13      ; device_spec.lua:17
0015    TSETS    1   0  14  ; "setRotationMode"
0016    UCLO     0 => 0017
0017 => RET1     0   2

-- BYTECODE -- device_spec.lua:7-24
0001    TDUP     0   1
0002    FNEW     1   0      ; device_spec.lua:9
0003    TSETS    1   0   2  ; "new"
0004    USETV    0   0      ; mock_fb
0005    GGET     0   3      ; "require"
0006    KSTR     1   4      ; "commonrequire"
0007    CALL     0   1   2
0008    GGET     0   5      ; "package"
0009    TGETS    0   0   6  ; "unloadAll"
0010    CALL     0   1   1
0011    GGET     0   3      ; "require"
0012    KSTR     1   7      ; "document/canvascontext"
0013    CALL     0   2   2
0014    MOV      1   0
0015    TGETS    0   0   8  ; "init"
0016    GGET     2   3      ; "require"
0017    KSTR     3   9      ; "device"
0018    CALL     2   0   2
0019    CALLM    0   1   1
0020    RET0     0   1

-- BYTECODE -- device_spec.lua:26-32
0001    GGET     0   0      ; "package"
0002    TGETS    0   0   1  ; "loaded"
0003    UGET     1   0      ; mock_fb
0004    TSETS    1   0   2  ; "ffi/framebuffer_mxcfb"
0005    GGET     0   3      ; "require"
0006    KSTR     1   4      ; "device/input"
0007    CALL     0   2   2
0008    USETV    1   0      ; mock_input
0009    GGET     0   5      ; "stub"
0010    UGET     1   1      ; mock_input
0011    KSTR     2   6      ; "open"
0012    CALL     0   1   3
0013    GGET     0   5      ; "stub"
0014    GGET     1   7      ; "os"
0015    KSTR     2   8      ; "getenv"
0016    CALL     0   1   3
0017    GGET     0   5      ; "stub"
0018    GGET     1   7      ; "os"
0019    KSTR     2   9      ; "execute"
0020    CALL     0   1   3
0021    RET0     0   1

-- BYTECODE -- device_spec.lua:34-41
0001    UGET     0   0      ; mock_input
0002    TGETS    0   0   0  ; "open"
0003    MOV      1   0
0004    TGETS    0   0   1  ; "revert"
0005    CALL     0   1   2
0006    GGET     0   2      ; "os"
0007    TGETS    0   0   3  ; "getenv"
0008    MOV      1   0
0009    TGETS    0   0   1  ; "revert"
0010    CALL     0   1   2
0011    GGET     0   2      ; "os"
0012    TGETS    0   0   4  ; "execute"
0013    MOV      1   0
0014    TGETS    0   0   1  ; "revert"
0015    CALL     0   1   2
0016    GGET     0   2      ; "os"
0017    UGET     1   1      ; osgetenv
0018    TSETS    1   0   3  ; "getenv"
0019    GGET     0   5      ; "io"
0020    UGET     1   2      ; iopen
0021    TSETS    1   0   0  ; "open"
0022    RET0     0   1

-- BYTECODE -- device_spec.lua:46-49
0001    GGET     0   0      ; "require"
0002    KSTR     1   1      ; "ui/timeval"
0003    CALL     0   2   2
0004    USETV    0   0      ; TimeVal
0005    GGET     0   0      ; "require"
0006    KSTR     1   2      ; "device/kobo/nickel_conf"
0007    CALL     0   2   2
0008    USETV    1   0      ; NickelConf
0009    RET0     0   1

-- BYTECODE -- device_spec.lua:51-55
0001    GGET     0   0      ; "stub"
0002    UGET     1   0      ; NickelConf
0003    TGETS    1   1   1  ; "frontLightLevel"
0004    KSTR     2   2      ; "get"
0005    CALL     0   1   3
0006    UGET     0   0      ; NickelConf
0007    TGETS    0   0   1  ; "frontLightLevel"
0008    TGETS    0   0   2  ; "get"
0009    TGETS    0   0   3  ; "returns"
0010    KSHORT   1   0
0011    CALL     0   1   2
0012    GGET     0   0      ; "stub"
0013    UGET     1   0      ; NickelConf
0014    TGETS    1   1   4  ; "frontLightState"
0015    KSTR     2   2      ; "get"
0016    CALL     0   1   3
0017    RET0     0   1

-- BYTECODE -- device_spec.lua:57-60
0001    UGET     0   0      ; NickelConf
0002    TGETS    0   0   0  ; "frontLightLevel"
0003    TGETS    0   0   1  ; "get"
0004    MOV      1   0
0005    TGETS    0   0   2  ; "revert"
0006    CALL     0   1   2
0007    UGET     0   0      ; NickelConf
0008    TGETS    0   0   3  ; "frontLightState"
0009    TGETS    0   0   1  ; "get"
0010    MOV      1   0
0011    TGETS    0   0   2  ; "revert"
0012    CALL     0   1   2
0013    RET0     0   1

-- BYTECODE -- device_spec.lua:62-68
0001    GGET     0   0      ; "os"
0002    TGETS    0   0   1  ; "getenv"
0003    TGETS    0   0   2  ; "returns"
0004    KSTR     1   3      ; "dahlia"
0005    CALL     0   1   2
0006    GGET     0   4      ; "require"
0007    KSTR     1   5      ; "device/kobo/device"
0008    CALL     0   2   2
0009    MOV      2   0
0010    TGETS    1   0   6  ; "init"
0011    CALL     1   1   2
0012    GGET     1   7      ; "assert"
0013    TGETS    1   1   8  ; "is"
0014    TGETS    1   1   9  ; "same"
0015    KSTR     2  10      ; "Kobo_dahlia"
0016    TGETS    3   0  11  ; "model"
0017    CALL     1   1   3
0018    RET0     0   1

-- BYTECODE -- device_spec.lua:71-77
0001    ISNES    0   0      ; "PRODUCT"
0002    JMP      1 => 0006
0003    KSTR     1   1      ; "trilogy"
0004    RET1     1   2
0005    JMP      1 => 0009
0006 => UGET     1   0      ; osgetenv
0007    MOV      2   0
0008    CALLT    1   2
0009 => RET0     0   1

-- BYTECODE -- device_spec.lua:116-116
0001    RET0     0   1

-- BYTECODE -- device_spec.lua:70-117
0001    GGET     0   0      ; "os"
0002    TGETS    0   0   1  ; "getenv"
0003    TGETS    0   0   2  ; "invokes"
0004    FNEW     1   3      ; device_spec.lua:71
0005    CALL     0   1   2
0006    GGET     0   4      ; "package"
0007    TGETS    0   0   5  ; "loaded"
0008    KPRI     1   0
0009    TSETS    1   0   6  ; "device/kobo/device"
0010    GGET     0   7      ; "require"
0011    KSTR     1   6      ; "device/kobo/device"
0012    CALL     0   2   2
0013    MOV      2   0
0014    TGETS    1   0   8  ; "init"
0015    CALL     1   1   2
0016    TGETS    1   0   9  ; "screen"
0017    GGET     2  10      ; "assert"
0018    TGETS    2   2  11  ; "is"
0019    TGETS    2   2  12  ; "same"
0020    KSTR     3  13      ; "Kobo_trilogy"
0021    TGETS    4   0  14  ; "model"
0022    CALL     2   1   3
0023    GGET     2  10      ; "assert"
0024    TGETS    2   2  15  ; "truthy"
0025    MOV      4   0
0026    TGETS    3   0  16  ; "needsTouchScreenProbe"
0027    CALL     3   0   2
0028    CALLM    2   1   0
0029    GGET     2  10      ; "assert"
0030    TGETS    2   2  17  ; "falsy"
0031    TGETS    3   0  18  ; "touch_probe_ev_epoch_time"
0032    CALL     2   1   2
0033    GGET     2  19      ; "G_reader_settings"
0034    MOV      3   2
0035    TGETS    2   2  20  ; "saveSetting"
0036    KSTR     4  21      ; "kobo_touch_switch_xy"
0037    KPRI     5   2
0038    CALL     2   1   4
0039    MOV      3   0
0040    TGETS    2   0  22  ; "touchScreenProbe"
0041    CALL     2   1   2
0042    MOV      3   1
0043    TGETS    2   1  23  ; "getWidth"
0044    CALL     2   2   2
0045    SUBVN    2   2   0  ; 5
0046    KSHORT   3  10
0047    KSHORT   4   3
0048    KSHORT   5   0
0049    KSHORT   6   1
0050    TDUP     7  24
0051    TSETS    4   7  25  ; "type"
0052    TSETS    5   7  26  ; "code"
0053    TSETS    3   7  27  ; "value"
0054    UGET     8   1      ; TimeVal
0055    MOV      9   8
0056    TGETS    8   8  28  ; "now"
0057    CALL     8   2   2
0058    TSETS    8   7  29  ; "time"
0059    TDUP     8  30
0060    TSETS    4   8  25  ; "type"
0061    TSETS    6   8  26  ; "code"
0062    MOV     10   1
0063    TGETS    9   1  23  ; "getWidth"
0064    CALL     9   2   2
0065    SUBVV    9   9   2
0066    TSETS    9   8  27  ; "value"
0067    UGET     9   1      ; TimeVal
0068    MOV     10   9
0069    TGETS    9   9  28  ; "now"
0070    CALL     9   2   2
0071    TSETS    9   8  29  ; "time"
0072    TGETS    9   0  31  ; "input"
0073    MOV     10   9
0074    TGETS    9   9  32  ; "eventAdjustHook"
0075    MOV     11   7
0076    CALL     9   1   3
0077    TGETS    9   0  31  ; "input"
0078    MOV     10   9
0079    TGETS    9   9  32  ; "eventAdjustHook"
0080    MOV     11   8
0081    CALL     9   1   3
0082    GGET     9  10      ; "assert"
0083    TGETS    9   9  11  ; "is"
0084    TGETS    9   9  12  ; "same"
0085    MOV     10   2
0086    TGETS   11   8  27  ; "value"
0087    CALL     9   1   3
0088    GGET     9  10      ; "assert"
0089    TGETS    9   9  11  ; "is"
0090    TGETS    9   9  12  ; "same"
0091    MOV     10   5
0092    TGETS   11   8  26  ; "code"
0093    CALL     9   1   3
0094    GGET     9  10      ; "assert"
0095    TGETS    9   9  11  ; "is"
0096    TGETS    9   9  12  ; "same"
0097    MOV     10   3
0098    TGETS   11   7  27  ; "value"
0099    CALL     9   1   3
0100    GGET     9  10      ; "assert"
0101    TGETS    9   9  11  ; "is"
0102    TGETS    9   9  12  ; "same"
0103    MOV     10   6
0104    TGETS   11   7  26  ; "code"
0105    CALL     9   1   3
0106    TGETS    9   0  31  ; "input"
0107    FNEW    10  33      ; device_spec.lua:116
0108    TSETS   10   9  32  ; "eventAdjustHook"
0109    RET0     0   1

-- BYTECODE -- device_spec.lua:120-126
0001    ISNES    0   0      ; "PRODUCT"
0002    JMP      1 => 0006
0003    KSTR     1   1      ; "trilogy"
0004    RET1     1   2
0005    JMP      1 => 0009
0006 => UGET     1   0      ; osgetenv
0007    MOV      2   0
0008    CALLT    1   2
0009 => RET0     0   1

-- BYTECODE -- device_spec.lua:162-162
0001    RET0     0   1

-- BYTECODE -- device_spec.lua:119-163
0001    GGET     0   0      ; "os"
0002    TGETS    0   0   1  ; "getenv"
0003    TGETS    0   0   2  ; "invokes"
0004    FNEW     1   3      ; device_spec.lua:120
0005    CALL     0   1   2
0006    GGET     0   4      ; "package"
0007    TGETS    0   0   5  ; "loaded"
0008    KPRI     1   0
0009    TSETS    1   0   6  ; "device/kobo/device"
0010    GGET     0   7      ; "require"
0011    KSTR     1   6      ; "device/kobo/device"
0012    CALL     0   2   2
0013    MOV      2   0
0014    TGETS    1   0   8  ; "init"
0015    CALL     1   1   2
0016    TGETS    1   0   9  ; "screen"
0017    GGET     2  10      ; "assert"
0018    TGETS    2   2  11  ; "is"
0019    TGETS    2   2  12  ; "same"
0020    KSTR     3  13      ; "Kobo_trilogy"
0021    TGETS    4   0  14  ; "model"
0022    CALL     2   1   3
0023    GGET     2  10      ; "assert"
0024    TGETS    2   2  15  ; "truthy"
0025    MOV      4   0
0026    TGETS    3   0  16  ; "needsTouchScreenProbe"
0027    CALL     3   0   2
0028    CALLM    2   1   0
0029    GGET     2  10      ; "assert"
0030    TGETS    2   2  17  ; "falsy"
0031    TGETS    3   0  18  ; "touch_probe_ev_epoch_time"
0032    CALL     2   1   2
0033    MOV      3   0
0034    TGETS    2   0  19  ; "touchScreenProbe"
0035    CALL     2   1   2
0036    MOV      3   1
0037    TGETS    2   1  20  ; "getWidth"
0038    CALL     2   2   2
0039    SUBVN    2   2   0  ; 5
0040    KSHORT   3  10
0041    KSHORT   4   3
0042    KSHORT   5   0
0043    KSHORT   6   1
0044    TDUP     7  21
0045    TSETS    4   7  22  ; "type"
0046    TSETS    5   7  23  ; "code"
0047    TSETS    2   7  24  ; "value"
0048    TDUP     8  25
0049    TSETS    8   7  26  ; "time"
0050    TDUP     8  27
0051    TSETS    4   8  22  ; "type"
0052    TSETS    6   8  23  ; "code"
0053    TSETS    3   8  24  ; "value"
0054    TDUP     9  28
0055    TSETS    9   8  26  ; "time"
0056    TGETS    9   0  29  ; "input"
0057    MOV     10   9
0058    TGETS    9   9  30  ; "eventAdjustHook"
0059    MOV     11   7
0060    CALL     9   1   3
0061    TGETS    9   0  29  ; "input"
0062    MOV     10   9
0063    TGETS    9   9  30  ; "eventAdjustHook"
0064    MOV     11   8
0065    CALL     9   1   3
0066    UGET     9   1      ; TimeVal
0067    MOV     10   9
0068    TGETS    9   9  31  ; "now"
0069    CALL     9   2   2
0070    TGETS    9   9  32  ; "sec"
0071    GGET    10  10      ; "assert"
0072    TGETS   10  10  15  ; "truthy"
0073    TGETS   11   7  26  ; "time"
0074    TGETS   11  11  32  ; "sec"
0075    SUBVV   11   9  11
0076    KSHORT  12  10
0077    ISLT    11  12
0078    JMP     11 => 0081
0079    KPRI    11   1
0080    JMP     12 => 0082
0081 => KPRI    11   2
0082 => CALL    10   1   2
0083    GGET    10  10      ; "assert"
0084    TGETS   10  10  15  ; "truthy"
0085    TGETS   11   8  26  ; "time"
0086    TGETS   11  11  32  ; "sec"
0087    SUBVV   11   9  11
0088    KSHORT  12  10
0089    ISLT    11  12
0090    JMP     11 => 0093
0091    KPRI    11   1
0092    JMP     12 => 0094
0093 => KPRI    11   2
0094 => CALL    10   1   2
0095    TGETS   10   0  29  ; "input"
0096    FNEW    11  33      ; device_spec.lua:162
0097    TSETS   11  10  30  ; "eventAdjustHook"
0098    RET0     0   1

-- BYTECODE -- device_spec.lua:165-193
0001    KSTR     0   0      ; "spec/front/unit/data/tall.pdf"
0002    GGET     1   1      ; "require"
0003    KSTR     2   2      ; "apps/reader/readerui"
0004    CALL     1   2   2
0005    GGET     2   1      ; "require"
0006    KSTR     3   3      ; "device"
0007    CALL     2   2   2
0008    UGET     3   0      ; NickelConf
0009    TGETS    3   3   4  ; "frontLightLevel"
0010    TGETS    3   3   5  ; "get"
0011    TGETS    3   3   6  ; "returns"
0012    KSHORT   4   1
0013    CALL     3   1   2
0014    UGET     3   0      ; NickelConf
0015    TGETS    3   3   7  ; "frontLightState"
0016    TGETS    3   3   5  ; "get"
0017    TGETS    3   3   6  ; "returns"
0018    KSHORT   4   0
0019    CALL     3   1   2
0020    GGET     3   1      ; "require"
0021    KSTR     4   8      ; "ui/uimanager"
0022    CALL     3   2   2
0023    GGET     4   9      ; "stub"
0024    MOV      5   2
0025    KSTR     6  10      ; "suspend"
0026    CALL     4   1   3
0027    GGET     4   9      ; "stub"
0028    TGETS    5   2  11  ; "powerd"
0029    KSTR     6  12      ; "beforeSuspend"
0030    CALL     4   1   3
0031    GGET     4   9      ; "stub"
0032    MOV      5   2
0033    KSTR     6  13      ; "isKobo"
0034    CALL     4   1   3
0035    TGETS    4   2  13  ; "isKobo"
0036    TGETS    4   4   6  ; "returns"
0037    KPRI     5   2
0038    CALL     4   1   2
0039    MOV      5   3
0040    TGETS    4   3  14  ; "init"
0041    CALL     4   1   2
0042    MOV      5   1
0043    TGETS    4   1  15  ; "doShowReader"
0044    MOV      6   0
0045    CALL     4   1   3
0046    TGETS    4   1  16  ; "_getRunningInstance"
0047    CALL     4   2   1
0048    GGET     5   9      ; "stub"
0049    MOV      6   4
0050    KSTR     7  17      ; "onFlushSettings"
0051    CALL     5   1   3
0052    TGETS    5   3  18  ; "event_handlers"
0053    TGETS    5   5  19  ; "PowerPress"
0054    CALL     5   1   1
0055    TGETS    5   3  18  ; "event_handlers"
0056    TGETS    5   5  20  ; "PowerRelease"
0057    CALL     5   1   1
0058    GGET     5  21      ; "assert"
0059    TGETS    5   5   9  ; "stub"
0060    TGETS    6   4  17  ; "onFlushSettings"
0061    CALL     5   2   2
0062    TGETS    5   5  22  ; "was_called"
0063    CALL     5   1   1
0064    TGETS    5   2  10  ; "suspend"
0065    MOV      6   5
0066    TGETS    5   5  23  ; "revert"
0067    CALL     5   1   2
0068    TGETS    5   2  11  ; "powerd"
0069    TGETS    5   5  12  ; "beforeSuspend"
0070    MOV      6   5
0071    TGETS    5   5  23  ; "revert"
0072    CALL     5   1   2
0073    TGETS    5   2  13  ; "isKobo"
0074    MOV      6   5
0075    TGETS    5   5  23  ; "revert"
0076    CALL     5   1   2
0077    TGETS    5   4  17  ; "onFlushSettings"
0078    MOV      6   5
0079    TGETS    5   5  23  ; "revert"
0080    CALL     5   1   2
0081    MOV      6   4
0082    TGETS    5   4  24  ; "onClose"
0083    CALL     5   1   2
0084    RET0     0   1

-- BYTECODE -- device_spec.lua:43-194
0001    KNIL     0   1
0002    GGET     2   0      ; "setup"
0003    FNEW     3   1      ; device_spec.lua:46
0004    CALL     2   1   2
0005    GGET     2   2      ; "before_each"
0006    FNEW     3   3      ; device_spec.lua:51
0007    CALL     2   1   2
0008    GGET     2   4      ; "after_each"
0009    FNEW     3   5      ; device_spec.lua:57
0010    CALL     2   1   2
0011    GGET     2   6      ; "it"
0012    KSTR     3   7      ; "should initialize properly on Kobo dahli"~
0013    FNEW     4   8      ; device_spec.lua:62
0014    CALL     2   1   3
0015    GGET     2   6      ; "it"
0016    KSTR     3   9      ; "should setup eventAdjustHooks properly f"~
0017    FNEW     4  10      ; device_spec.lua:70
0018    CALL     2   1   3
0019    GGET     2   6      ; "it"
0020    KSTR     3  11      ; "should setup eventAdjustHooks properly f"~
0021    FNEW     4  12      ; device_spec.lua:119
0022    CALL     2   1   3
0023    GGET     2   6      ; "it"
0024    KSTR     3  13      ; "should flush book settings before suspen"~
0025    FNEW     4  14      ; device_spec.lua:165
0026    CALL     2   1   3
0027    UCLO     0 => 0028
0028 => RET0     0   1

-- BYTECODE -- device_spec.lua:201-201
0001    KSTR     0   0      ; "B013XX"
0002    RET1     0   2

-- BYTECODE -- device_spec.lua:202-202
0001    RET0     0   1

-- BYTECODE -- device_spec.lua:198-207
0001    ISNES    0   0      ; "/proc/usid"
0002    JMP      2 => 0011
0003    TDUP     2   2
0004    FNEW     3   1      ; device_spec.lua:201
0005    TSETS    3   2   3  ; "read"
0006    FNEW     3   4      ; device_spec.lua:202
0007    TSETS    3   2   5  ; "close"
0008    UCLO     0 => 0009
0009 => RET1     2   2
0010    JMP      2 => 0016
0011 => UGET     2   0      ; iopen
0012    MOV      3   0
0013    MOV      4   1
0014    UCLO     0 => 0015
0015 => CALLT    2   3
0016 => RET0     0   1

-- BYTECODE -- device_spec.lua:197-217
0001    GGET     0   0      ; "io"
0002    FNEW     1   2      ; device_spec.lua:198
0003    TSETS    1   0   1  ; "open"
0004    GGET     0   3      ; "require"
0005    KSTR     1   4      ; "device/kindle/device"
0006    CALL     0   2   2
0007    GGET     1   5      ; "assert"
0008    TGETS    1   1   6  ; "is"
0009    TGETS    1   1   7  ; "same"
0010    TGETS    2   0   8  ; "model"
0011    KSTR     3   9      ; "KindleVoyage"
0012    CALL     1   1   3
0013    MOV      2   0
0014    TGETS    1   0  10  ; "init"
0015    CALL     1   1   2
0016    GGET     1   5      ; "assert"
0017    TGETS    1   1   6  ; "is"
0018    TGETS    1   1   7  ; "same"
0019    TGETS    2   0  11  ; "input"
0020    TGETS    2   2  12  ; "event_map"
0021    TGETB    2   2 104
0022    KSTR     3  13      ; "LPgBack"
0023    CALL     1   1   3
0024    GGET     1   5      ; "assert"
0025    TGETS    1   1   6  ; "is"
0026    TGETS    1   1   7  ; "same"
0027    TGETS    2   0  11  ; "input"
0028    TGETS    2   2  12  ; "event_map"
0029    TGETB    2   2 109
0030    KSTR     3  14      ; "LPgFwd"
0031    CALL     1   1   3
0032    GGET     1   5      ; "assert"
0033    TGETS    1   1   6  ; "is"
0034    TGETS    1   1   7  ; "same"
0035    TGETS    2   0  15  ; "powerd"
0036    TGETS    2   2  16  ; "fl_min"
0037    KSHORT   3   0
0038    CALL     1   1   3
0039    GGET     1   5      ; "assert"
0040    TGETS    1   1   6  ; "is"
0041    TGETS    1   1   7  ; "same"
0042    TGETS    2   0  15  ; "powerd"
0043    TGETS    2   2  17  ; "fl_max"
0044    KSHORT   3  25
0045    CALL     1   1   3
0046    RET0     0   1

-- BYTECODE -- device_spec.lua:223-223
0001    KSTR     0   0      ; "B013XX"
0002    RET1     0   2

-- BYTECODE -- device_spec.lua:224-224
0001    RET0     0   1

-- BYTECODE -- device_spec.lua:228-228
0001    KSTR     0   0      ; "12"
0002    RET1     0   2

-- BYTECODE -- device_spec.lua:229-229
0001    RET0     0   1

-- BYTECODE -- device_spec.lua:220-234
0001    ISNES    0   0      ; "/proc/usid"
0002    JMP      2 => 0011
0003    TDUP     2   2
0004    FNEW     3   1      ; device_spec.lua:223
0005    TSETS    3   2   3  ; "read"
0006    FNEW     3   4      ; device_spec.lua:224
0007    TSETS    3   2   5  ; "close"
0008    UCLO     0 => 0009
0009 => RET1     2   2
0010    JMP      2 => 0026
0011 => ISNES    0   6      ; "/sys/class/backlight/max77696-bl/brightn"~
0012    JMP      2 => 0021
0013    TDUP     2   8
0014    FNEW     3   7      ; device_spec.lua:228
0015    TSETS    3   2   3  ; "read"
0016    FNEW     3   9      ; device_spec.lua:229
0017    TSETS    3   2   5  ; "close"
0018    UCLO     0 => 0019
0019 => RET1     2   2
0020    JMP      2 => 0026
0021 => UGET     2   0      ; iopen
0022    MOV      3   0
0023    MOV      4   1
0024    UCLO     0 => 0025
0025 => CALLT    2   3
0026 => RET0     0   1

-- BYTECODE -- device_spec.lua:219-255
0001    GGET     0   0      ; "io"
0002    FNEW     1   2      ; device_spec.lua:220
0003    TSETS    1   0   1  ; "open"
0004    GGET     0   3      ; "require"
0005    KSTR     1   4      ; "device/kindle/device"
0006    CALL     0   2   2
0007    MOV      2   0
0008    TGETS    1   0   5  ; "init"
0009    CALL     1   1   2
0010    GGET     1   6      ; "assert"
0011    TGETS    1   1   7  ; "is"
0012    TGETS    1   1   8  ; "same"
0013    TGETS    2   0   9  ; "powerd"
0014    TGETS    2   2  10  ; "fl_intensity"
0015    KSHORT   3  12
0016    CALL     1   1   3
0017    TGETS    1   0   9  ; "powerd"
0018    MOV      2   1
0019    TGETS    1   1  11  ; "setIntensity"
0020    KSHORT   3   5
0021    CALL     1   1   3
0022    GGET     1   6      ; "assert"
0023    TGETS    1   1   7  ; "is"
0024    TGETS    1   1   8  ; "same"
0025    TGETS    2   0   9  ; "powerd"
0026    TGETS    2   2  10  ; "fl_intensity"
0027    KSHORT   3   5
0028    CALL     1   1   3
0029    TGETS    1   0   9  ; "powerd"
0030    MOV      2   1
0031    TGETS    1   1  12  ; "toggleFrontlight"
0032    CALL     1   1   2
0033    GGET     1   6      ; "assert"
0034    TGETS    1   1  13  ; "stub"
0035    GGET     2  14      ; "os"
0036    TGETS    2   2  15  ; "execute"
0037    CALL     1   2   2
0038    TGETS    1   1  16  ; "was_called_with"
0039    KSTR     2  17      ; "echo -n 0 > /sys/class/backlight/max7769"~
0040    CALL     1   1   2
0041    GGET     1   6      ; "assert"
0042    TGETS    1   1   7  ; "is"
0043    TGETS    1   1   8  ; "same"
0044    TGETS    2   0   9  ; "powerd"
0045    TGETS    2   2  10  ; "fl_intensity"
0046    KSHORT   3   5
0047    CALL     1   1   3
0048    TGETS    1   0   9  ; "powerd"
0049    MOV      2   1
0050    TGETS    1   1  12  ; "toggleFrontlight"
0051    CALL     1   1   2
0052    GGET     1   6      ; "assert"
0053    TGETS    1   1   7  ; "is"
0054    TGETS    1   1   8  ; "same"
0055    TGETS    2   0   9  ; "powerd"
0056    TGETS    2   2  10  ; "fl_intensity"
0057    KSHORT   3   5
0058    CALL     1   1   3
0059    RET0     0   1

-- BYTECODE -- device_spec.lua:262-264
0001    KSTR     0   0      ; "G0B0GCXXX"
0002    RET1     0   2

-- BYTECODE -- device_spec.lua:265-265
0001    RET0     0   1

-- BYTECODE -- device_spec.lua:259-270
0001    ISNES    0   0      ; "/proc/usid"
0002    JMP      2 => 0011
0003    TDUP     2   2
0004    FNEW     3   1      ; device_spec.lua:262
0005    TSETS    3   2   3  ; "read"
0006    FNEW     3   4      ; device_spec.lua:265
0007    TSETS    3   2   5  ; "close"
0008    UCLO     0 => 0009
0009 => RET1     2   2
0010    JMP      2 => 0016
0011 => UGET     2   0      ; iopen
0012    MOV      3   0
0013    MOV      4   1
0014    UCLO     0 => 0015
0015 => CALLT    2   3
0016 => RET0     0   1

-- BYTECODE -- device_spec.lua:257-296
0001    GGET     0   0      ; "package"
0002    TGETS    0   0   1  ; "unload"
0003    KSTR     1   2      ; "device/kindle/device"
0004    CALL     0   1   2
0005    GGET     0   3      ; "io"
0006    FNEW     1   5      ; device_spec.lua:259
0007    TSETS    1   0   4  ; "open"
0008    GGET     0   6      ; "require"
0009    KSTR     1   7      ; "ffi/input"
0010    CALL     0   2   2
0011    GSET     0   8      ; "mock_ffi_input"
0012    GGET     0   9      ; "stub"
0013    GGET     1   8      ; "mock_ffi_input"
0014    KSTR     2  10      ; "waitForEvent"
0015    CALL     0   1   3
0016    GGET     0   8      ; "mock_ffi_input"
0017    TGETS    0   0  10  ; "waitForEvent"
0018    TGETS    0   0  11  ; "returns"
0019    TDUP     1  12
0020    TDUP     2  13
0021    TSETS    2   1  14  ; "time"
0022    CALL     0   1   2
0023    GGET     0   6      ; "require"
0024    KSTR     1  15      ; "ui/uimanager"
0025    CALL     0   2   2
0026    GGET     1   9      ; "stub"
0027    MOV      2   0
0028    KSTR     3  16      ; "onRotation"
0029    CALL     1   1   3
0030    GGET     1   6      ; "require"
0031    KSTR     2   2      ; "device/kindle/device"
0032    CALL     1   2   2
0033    GGET     2  17      ; "assert"
0034    TGETS    2   2  18  ; "is"
0035    TGETS    2   2  19  ; "same"
0036    KSTR     3  20      ; "KindleOasis"
0037    TGETS    4   1  21  ; "model"
0038    CALL     2   1   3
0039    MOV      3   1
0040    TGETS    2   1  22  ; "init"
0041    CALL     2   1   2
0042    TGETS    2   1  23  ; "input"
0043    MOV      3   2
0044    TGETS    2   2  24  ; "waitEvent"
0045    CALL     2   1   2
0046    GGET     2  17      ; "assert"
0047    TGETS    2   2   9  ; "stub"
0048    TGETS    3   0  16  ; "onRotation"
0049    CALL     2   2   2
0050    TGETS    2   2  25  ; "was_called"
0051    CALL     2   1   1
0052    GGET     2   8      ; "mock_ffi_input"
0053    TGETS    2   2  10  ; "waitForEvent"
0054    MOV      3   2
0055    TGETS    2   2  26  ; "revert"
0056    CALL     2   1   2
0057    TGETS    2   0  16  ; "onRotation"
0058    MOV      3   2
0059    TGETS    2   2  26  ; "revert"
0060    CALL     2   1   2
0061    RET0     0   1

-- BYTECODE -- device_spec.lua:196-297
0001    GGET     0   0      ; "it"
0002    KSTR     1   1      ; "should initialize voyage without error"
0003    FNEW     2   2      ; device_spec.lua:197
0004    CALL     0   1   3
0005    GGET     0   0      ; "it"
0006    KSTR     1   3      ; "should toggle frontlight"
0007    FNEW     2   4      ; device_spec.lua:219
0008    CALL     0   1   3
0009    GGET     0   0      ; "it"
0010    KSTR     1   5      ; "oasis should interpret orientation event"
0011    FNEW     2   6      ; device_spec.lua:257
0012    CALL     0   1   3
0013    RET0     0   1

-- BYTECODE -- device_spec.lua:1-299
0001    KNIL     0   1
0002    GGET     2   0      ; "io"
0003    TGETS    2   2   1  ; "open"
0004    GGET     3   2      ; "os"
0005    TGETS    3   3   3  ; "getenv"
0006    GGET     4   4      ; "setup"
0007    FNEW     5   5      ; device_spec.lua:7
0008    CALL     4   1   2
0009    GGET     4   6      ; "before_each"
0010    FNEW     5   7      ; device_spec.lua:26
0011    CALL     4   1   2
0012    GGET     4   8      ; "after_each"
0013    FNEW     5   9      ; device_spec.lua:34
0014    CALL     4   1   2
0015    GGET     4  10      ; "describe"
0016    KSTR     5  11      ; "kobo"
0017    FNEW     6  12      ; device_spec.lua:43
0018    CALL     4   1   3
0019    GGET     4  10      ; "describe"
0020    KSTR     5  13      ; "kindle"
0021    FNEW     6  14      ; device_spec.lua:196
0022    CALL     4   1   3
0023    UCLO     0 => 0024
0024 => RET0     0   1

-- BYTECODE -- device_spec.lua:0-300
0001    GGET     0   0      ; "describe"
0002    KSTR     1   1      ; "device module"
0003    FNEW     2   2      ; device_spec.lua:1
0004    CALL     0   1   3
0005    RET0     0   1

