-- BYTECODE -- dictionaries.lua:0-21
0001    GGET     0   0      ; "require"
0002    KSTR     1   1      ; "datastorage"
0003    CALL     0   2   2
0004    MOV      1   0
0005    TGETS    0   0   2  ; "getDataDir"
0006    CALL     0   2   2
0007    KSTR     1   3      ; "/dictionaries.lua"
0008    CAT      0   0   1
0009    GGET     1   4      ; "pcall"
0010    GGET     2   5      ; "dofile"
0011    MOV      3   0
0012    CALL     1   3   3
0013    ISF          1
0014    JMP      3 => 0017
0015    RET1     2   2
0016    JMP      3 => 0039
0017 => TNEW     3  11
0018    TDUP     4   6
0019    TSETB    4   3   1
0020    TDUP     4   7
0021    TSETB    4   3   2
0022    TDUP     4   8
0023    TSETB    4   3   3
0024    TDUP     4   9
0025    TSETB    4   3   4
0026    TDUP     4  10
0027    TSETB    4   3   5
0028    TDUP     4  11
0029    TSETB    4   3   6
0030    TDUP     4  12
0031    TSETB    4   3   7
0032    TDUP     4  13
0033    TSETB    4   3   8
0034    TDUP     4  14
0035    TSETB    4   3   9
0036    TDUP     4  15
0037    TSETB    4   3  10
0038    RET1     3   2
0039 => RET0     0   1

