
main <./frontend/ui/widget/dictquicklookup.lua:0,0> (278 instructions, 1112 bytes at 0x7fd305c068f0)
0+ params, 38 slots, 0 upvalues, 33 locals, 112 constants, 30 functions
	1	[1]	GETGLOBAL	0 -1	; require
	2	[1]	LOADK    	1 -2	; "ui/bidi"
	3	[1]	CALL     	0 2 2
	4	[2]	GETGLOBAL	1 -1	; require
	5	[2]	LOADK    	2 -3	; "ffi/blitbuffer"
	6	[2]	CALL     	1 2 2
	7	[3]	GETGLOBAL	2 -1	; require
	8	[3]	LOADK    	3 -4	; "ui/widget/button"
	9	[3]	CALL     	2 2 2
	10	[4]	GETGLOBAL	3 -1	; require
	11	[4]	LOADK    	4 -5	; "ui/widget/buttontable"
	12	[4]	CALL     	3 2 2
	13	[5]	GETGLOBAL	4 -1	; require
	14	[5]	LOADK    	5 -6	; "ui/widget/container/centercontainer"
	15	[5]	CALL     	4 2 2
	16	[6]	GETGLOBAL	5 -1	; require
	17	[6]	LOADK    	6 -7	; "ui/widget/closebutton"
	18	[6]	CALL     	5 2 2
	19	[7]	GETGLOBAL	6 -1	; require
	20	[7]	LOADK    	7 -8	; "device"
	21	[7]	CALL     	6 2 2
	22	[8]	GETGLOBAL	7 -1	; require
	23	[8]	LOADK    	8 -9	; "ui/geometry"
	24	[8]	CALL     	7 2 2
	25	[9]	GETGLOBAL	8 -1	; require
	26	[9]	LOADK    	9 -10	; "ui/event"
	27	[9]	CALL     	8 2 2
	28	[10]	GETGLOBAL	9 -1	; require
	29	[10]	LOADK    	10 -11	; "ui/font"
	30	[10]	CALL     	9 2 2
	31	[11]	GETGLOBAL	10 -1	; require
	32	[11]	LOADK    	11 -12	; "ui/widget/container/framecontainer"
	33	[11]	CALL     	10 2 2
	34	[12]	GETGLOBAL	11 -1	; require
	35	[12]	LOADK    	12 -13	; "ui/gesturerange"
	36	[12]	CALL     	11 2 2
	37	[13]	GETGLOBAL	12 -1	; require
	38	[13]	LOADK    	13 -14	; "ui/widget/container/inputcontainer"
	39	[13]	CALL     	12 2 2
	40	[14]	GETGLOBAL	13 -1	; require
	41	[14]	LOADK    	14 -15	; "ui/widget/inputdialog"
	42	[14]	CALL     	13 2 2
	43	[15]	GETGLOBAL	14 -1	; require
	44	[15]	LOADK    	15 -16	; "ui/widget/container/leftcontainer"
	45	[15]	CALL     	14 2 2
	46	[16]	GETGLOBAL	15 -1	; require
	47	[16]	LOADK    	16 -17	; "ui/widget/linewidget"
	48	[16]	CALL     	15 2 2
	49	[17]	GETGLOBAL	16 -1	; require
	50	[17]	LOADK    	17 -18	; "ui/widget/container/movablecontainer"
	51	[17]	CALL     	16 2 2
	52	[18]	GETGLOBAL	17 -1	; require
	53	[18]	LOADK    	18 -19	; "ui/widget/overlapgroup"
	54	[18]	CALL     	17 2 2
	55	[19]	GETGLOBAL	18 -1	; require
	56	[19]	LOADK    	19 -20	; "ui/widget/scrollhtmlwidget"
	57	[19]	CALL     	18 2 2
	58	[20]	GETGLOBAL	19 -1	; require
	59	[20]	LOADK    	20 -21	; "ui/widget/scrolltextwidget"
	60	[20]	CALL     	19 2 2
	61	[21]	GETGLOBAL	20 -1	; require
	62	[21]	LOADK    	21 -22	; "ui/size"
	63	[21]	CALL     	20 2 2
	64	[22]	GETGLOBAL	21 -1	; require
	65	[22]	LOADK    	22 -23	; "ui/widget/textwidget"
	66	[22]	CALL     	21 2 2
	67	[23]	GETGLOBAL	22 -1	; require
	68	[23]	LOADK    	23 -24	; "ui/uimanager"
	69	[23]	CALL     	22 2 2
	70	[24]	GETGLOBAL	23 -1	; require
	71	[24]	LOADK    	24 -25	; "ui/widget/verticalgroup"
	72	[24]	CALL     	23 2 2
	73	[25]	GETGLOBAL	24 -1	; require
	74	[25]	LOADK    	25 -26	; "ui/widget/container/widgetcontainer"
	75	[25]	CALL     	24 2 2
	76	[26]	GETGLOBAL	25 -1	; require
	77	[26]	LOADK    	26 -27	; "logger"
	78	[26]	CALL     	25 2 2
	79	[27]	GETGLOBAL	26 -1	; require
	80	[27]	LOADK    	27 -28	; "util"
	81	[27]	CALL     	26 2 2
	82	[28]	GETGLOBAL	27 -1	; require
	83	[28]	LOADK    	28 -29	; "gettext"
	84	[28]	CALL     	27 2 2
	85	[29]	GETTABLE 	28 27 -30	; "pgettext"
	86	[30]	GETTABLE 	29 6 -31	; "screen"
	87	[31]	GETGLOBAL	30 -1	; require
	88	[31]	LOADK    	31 -32	; "ffi/util"
	89	[31]	CALL     	30 2 2
	90	[31]	GETTABLE 	30 30 -33	; "template"
	91	[36]	SELF     	31 12 -34	; "new"
	92	[36]	NEWTABLE 	33 0 22
	93	[37]	SETTABLE 	33 -35 -36	; "results" nil
	94	[38]	SETTABLE 	33 -37 -36	; "lookupword" nil
	95	[39]	SETTABLE 	33 -38 -36	; "dictionary" nil
	96	[40]	SETTABLE 	33 -39 -36	; "definition" nil
	97	[41]	SETTABLE 	33 -40 -36	; "displayword" nil
	98	[42]	SETTABLE 	33 -41 -36	; "images" nil
	99	[43]	SETTABLE 	33 -42 -43	; "is_wiki" false
	100	[44]	SETTABLE 	33 -44 -43	; "is_fullpage" false
	101	[45]	SETTABLE 	33 -45 -43	; "is_html" false
	102	[46]	SETTABLE 	33 -46 -47	; "dict_index" 1
	103	[47]	SELF     	34 9 -49	; "getFace"
	104	[47]	LOADK    	36 -50	; "x_smalltfont"
	105	[47]	CALL     	34 3 2
	106	[47]	SETTABLE 	33 -48 34	; "title_face" -
	107	[48]	SELF     	34 9 -49	; "getFace"
	108	[48]	LOADK    	36 -52	; "cfont"
	109	[48]	LOADK    	37 -53	; 20
	110	[48]	CALL     	34 4 2
	111	[48]	SETTABLE 	33 -51 34	; "content_face" -
	112	[49]	SELF     	34 9 -49	; "getFace"
	113	[49]	LOADK    	36 -52	; "cfont"
	114	[49]	LOADK    	37 -55	; 16
	115	[49]	CALL     	34 4 2
	116	[49]	SETTABLE 	33 -54 34	; "image_alt_face" -
	117	[50]	SETTABLE 	33 -56 -36	; "width" nil
	118	[51]	SETTABLE 	33 -57 -36	; "height" nil
	119	[53]	SETTABLE 	33 -58 -36	; "word_box" nil
	120	[55]	GETTABLE 	34 20 -60	; "padding"
	121	[55]	GETTABLE 	34 34 -61	; "default"
	122	[55]	SETTABLE 	33 -59 34	; "title_padding" -
	123	[56]	GETTABLE 	34 20 -63	; "margin"
	124	[56]	GETTABLE 	34 34 -64	; "title"
	125	[56]	SETTABLE 	33 -62 34	; "title_margin" -
	126	[57]	GETTABLE 	34 20 -60	; "padding"
	127	[57]	GETTABLE 	34 34 -61	; "default"
	128	[57]	SETTABLE 	33 -65 34	; "word_padding" -
	129	[58]	GETTABLE 	34 20 -63	; "margin"
	130	[58]	GETTABLE 	34 34 -61	; "default"
	131	[58]	SETTABLE 	33 -66 34	; "word_margin" -
	132	[60]	SELF     	34 29 -68	; "scaleBySize"
	133	[60]	LOADK    	36 -69	; 7
	134	[60]	CALL     	34 3 2
	135	[60]	SETTABLE 	33 -67 34	; "wiki_word_padding" -
	136	[61]	SELF     	34 29 -68	; "scaleBySize"
	137	[61]	LOADK    	36 -71	; 3
	138	[61]	CALL     	34 3 2
	139	[61]	SETTABLE 	33 -70 34	; "wiki_word_margin" -
	140	[62]	SELF     	34 29 -68	; "scaleBySize"
	141	[62]	LOADK    	36 -73	; 2
	142	[62]	CALL     	34 3 2
	143	[62]	SETTABLE 	33 -72 34	; "definition_padding" -
	144	[63]	SELF     	34 29 -68	; "scaleBySize"
	145	[63]	LOADK    	36 -73	; 2
	146	[63]	CALL     	34 3 2
	147	[63]	SETTABLE 	33 -74 34	; "definition_margin" -
	148	[64]	SELF     	34 29 -68	; "scaleBySize"
	149	[64]	LOADK    	36 -76	; 14
	150	[64]	CALL     	34 3 2
	151	[64]	SETTABLE 	33 -75 34	; "button_padding" -
	152	[66]	SETTABLE 	33 -77 -36	; "refresh_callback" nil
	153	[67]	SETTABLE 	33 -78 -36	; "html_dictionary_link_tapped_callback" nil
	154	[36]	CALL     	31 3 2
	155	[70]	NEWTABLE 	32 0 2
	156	[71]	MOVE     	33 27
	157	[71]	LOADK    	34 -80	; "Highlight"
	158	[71]	CALL     	33 2 2
	159	[71]	SETTABLE 	32 -79 33	; "highlight" -
	160	[72]	MOVE     	33 27
	161	[72]	LOADK    	34 -82	; "Unhighlight"
	162	[72]	CALL     	33 2 2
	163	[72]	SETTABLE 	32 -81 33	; "unhighlight" -
	164	[170]	CLOSURE  	33 0	; 0x7fd305c07500
	165	[170]	MOVE     	0 9
	166	[170]	MOVE     	0 6
	167	[170]	MOVE     	0 7
	168	[170]	MOVE     	0 29
	169	[170]	MOVE     	0 11
	170	[170]	MOVE     	0 8
	171	[75]	SETTABLE 	31 -83 33	; "init" -
	172	[175]	CLOSURE  	33 1	; 0x7fd305c08780
	173	[173]	SETTABLE 	31 -84 33	; "isDocless" -
	174	[212]	CLOSURE  	33 2	; 0x7fd305c08460
	175	[177]	SETTABLE 	31 -85 33	; "getHtmlDictionaryCss" -
	176	[603]	CLOSURE  	33 3	; 0x7fd305c08ef0
	177	[603]	MOVE     	0 7
	178	[603]	MOVE     	0 29
	179	[603]	MOVE     	0 5
	180	[603]	MOVE     	0 20
	181	[603]	MOVE     	0 21
	182	[603]	MOVE     	0 4
	183	[603]	MOVE     	0 10
	184	[603]	MOVE     	0 2
	185	[603]	MOVE     	0 18
	186	[603]	MOVE     	0 19
	187	[603]	MOVE     	0 27
	188	[603]	MOVE     	0 26
	189	[603]	MOVE     	0 22
	190	[603]	MOVE     	0 30
	191	[603]	MOVE     	0 0
	192	[603]	MOVE     	0 32
	193	[603]	MOVE     	0 8
	194	[603]	MOVE     	0 28
	195	[603]	MOVE     	0 3
	196	[603]	MOVE     	0 15
	197	[603]	MOVE     	0 17
	198	[603]	MOVE     	0 1
	199	[603]	MOVE     	0 23
	200	[603]	MOVE     	0 14
	201	[603]	MOVE     	0 16
	202	[603]	MOVE     	0 24
	203	[603]	MOVE     	0 25
	204	[214]	SETTABLE 	31 -86 33	; "update" -
	205	[628]	CLOSURE  	33 4	; 0x7fd305c0eb70
	206	[628]	MOVE     	0 25
	207	[628]	MOVE     	0 22
	208	[605]	SETTABLE 	31 -87 33	; "onCloseWidget" -
	209	[635]	CLOSURE  	33 5	; 0x7fd305c0ee50
	210	[635]	MOVE     	0 22
	211	[630]	SETTABLE 	31 -88 33	; "onShow" -
	212	[640]	CLOSURE  	33 6	; 0x7fd305c0f9e0
	213	[637]	SETTABLE 	31 -89 33	; "getHighlightedItem" -
	214	[651]	CLOSURE  	33 7	; 0x7fd305c0fb60
	215	[651]	MOVE     	0 32
	216	[642]	SETTABLE 	31 -90 33	; "getHighlightText" -
	217	[655]	CLOSURE  	33 8	; 0x7fd305c100f0
	218	[653]	SETTABLE 	31 -91 33	; "isPrevDictAvaiable" -
	219	[659]	CLOSURE  	33 9	; 0x7fd305c10200
	220	[657]	SETTABLE 	31 -92 33	; "isNextDictAvaiable" -
	221	[667]	CLOSURE  	33 10	; 0x7fd305c106b0
	222	[661]	SETTABLE 	31 -93 33	; "changeToPrevDict" -
	223	[675]	CLOSURE  	33 11	; 0x7fd305c0c210
	224	[669]	SETTABLE 	31 -94 33	; "changeToNextDict" -
	225	[714]	CLOSURE  	33 12	; 0x7fd305c0c4e0
	226	[714]	MOVE     	0 30
	227	[714]	MOVE     	0 27
	228	[677]	SETTABLE 	31 -95 33	; "changeDictionary" -
	229	[743]	CLOSURE  	33 13	; 0x7fd305c09c60
	230	[716]	SETTABLE 	31 -96 33	; "changeToDefaultDict" -
	231	[749]	CLOSURE  	33 14	; 0x7fd305c0b090
	232	[749]	MOVE     	0 22
	233	[745]	SETTABLE 	31 -97 33	; "onAnyKeyPressed" -
	234	[775]	CLOSURE  	33 15	; 0x7fd305c0d240
	235	[775]	MOVE     	0 8
	236	[775]	MOVE     	0 0
	237	[775]	MOVE     	0 29
	238	[751]	SETTABLE 	31 -98 33	; "onTapCloseDict" -
	239	[794]	CLOSURE  	33 16	; 0x7fd305c10960
	240	[794]	MOVE     	0 22
	241	[777]	SETTABLE 	31 -99 33	; "onClose" -
	242	[811]	CLOSURE  	33 17	; 0x7fd305c10180
	243	[811]	MOVE     	0 22
	244	[796]	SETTABLE 	31 -100 33	; "onHoldClose" -
	245	[834]	CLOSURE  	33 18	; 0x7fd305c0f740
	246	[834]	MOVE     	0 0
	247	[834]	MOVE     	0 22
	248	[813]	SETTABLE 	31 -101 33	; "onSwipe" -
	249	[840]	CLOSURE  	33 19	; 0x7fd305c116e0
	250	[836]	SETTABLE 	31 -102 33	; "onHoldStartText" -
	251	[849]	CLOSURE  	33 20	; 0x7fd305c11b80
	252	[842]	SETTABLE 	31 -103 33	; "onHoldPanText" -
	253	[855]	CLOSURE  	33 21	; 0x7fd305c11d70
	254	[851]	SETTABLE 	31 -104 33	; "onHoldReleaseText" -
	255	[870]	CLOSURE  	33 22	; 0x7fd305c12350
	256	[861]	SETTABLE 	31 -105 33	; "onForwardingTouch" -
	257	[877]	CLOSURE  	33 23	; 0x7fd305c12640
	258	[872]	SETTABLE 	31 -106 33	; "onForwardingPan" -
	259	[882]	CLOSURE  	33 24	; 0x7fd305c12830
	260	[879]	SETTABLE 	31 -107 33	; "onForwardingPanRelease" -
	261	[912]	CLOSURE  	33 25	; 0x7fd305c129b0
	262	[912]	MOVE     	0 13
	263	[912]	MOVE     	0 27
	264	[912]	MOVE     	0 22
	265	[884]	SETTABLE 	31 -108 33	; "lookupInputWord" -
	266	[926]	CLOSURE  	33 26	; 0x7fd305c130a0
	267	[926]	MOVE     	0 8
	268	[914]	SETTABLE 	31 -109 33	; "inputLookup" -
	269	[930]	CLOSURE  	33 27	; 0x7fd305c13c60
	270	[930]	MOVE     	0 22
	271	[928]	SETTABLE 	31 -110 33	; "closeInputDialog" -
	272	[949]	CLOSURE  	33 28	; 0x7fd305c13d20
	273	[932]	SETTABLE 	31 -111 33	; "resyncWikiLanguages" -
	274	[965]	CLOSURE  	33 29	; 0x7fd305c14200
	275	[965]	MOVE     	0 8
	276	[951]	SETTABLE 	31 -112 33	; "lookupWikipedia" -
	277	[967]	RETURN   	31 2
	278	[967]	RETURN   	0 1

function <./frontend/ui/widget/dictquicklookup.lua:75,170> (137 instructions, 548 bytes at 0x7fd305c07500)
1 param, 9 slots, 6 upvalues, 4 locals, 45 constants, 1 function
	1	[76]	GETGLOBAL	1 -1	; G_reader_settings
	2	[76]	SELF     	1 1 -2	; "readSetting"
	3	[76]	LOADK    	3 -3	; "dict_font_size"
	4	[76]	CALL     	1 3 2
	5	[76]	TEST     	1 0 1
	6	[76]	JMP      	1	; to 8
	7	[76]	LOADK    	1 -4	; 20
	8	[77]	GETUPVAL 	2 0	; Font
	9	[77]	SELF     	2 2 -6	; "getFace"
	10	[77]	LOADK    	4 -7	; "cfont"
	11	[77]	MOVE     	5 1
	12	[77]	CALL     	2 4 2
	13	[77]	SETTABLE 	0 -5 2	; "content_face" -
	14	[78]	SUB      	2 1 -8	; - 4
	15	[79]	LT       	0 2 -9	; - 8
	16	[79]	JMP      	1	; to 18
	17	[80]	LOADK    	2 -9	; 8
	18	[82]	GETUPVAL 	3 0	; Font
	19	[82]	SELF     	3 3 -6	; "getFace"
	20	[82]	LOADK    	5 -7	; "cfont"
	21	[82]	MOVE     	6 2
	22	[82]	CALL     	3 4 2
	23	[82]	SETTABLE 	0 -10 3	; "image_alt_face" -
	24	[83]	SELF     	3 0 -11	; "changeToDefaultDict"
	25	[83]	CALL     	3 2 1
	26	[84]	GETUPVAL 	3 1	; Device
	27	[84]	SELF     	3 3 -12	; "hasKeys"
	28	[84]	CALL     	3 2 2
	29	[84]	TEST     	3 0 0
	30	[84]	JMP      	9	; to 40
	31	[85]	NEWTABLE 	3 0 1
	32	[86]	NEWTABLE 	4 1 1
	33	[86]	NEWTABLE 	5 1 0
	34	[86]	LOADK    	6 -15	; "Back"
	35	[86]	SETLIST  	5 1 1	; 1
	36	[86]	SETTABLE 	4 -16 -17	; "doc" "close quick lookup"
	37	[86]	SETLIST  	4 1 1	; 1
	38	[86]	SETTABLE 	3 -14 4	; "Close" -
	39	[87]	SETTABLE 	0 -13 3	; "key_events" -
	40	[89]	GETUPVAL 	3 1	; Device
	41	[89]	SELF     	3 3 -18	; "isTouchDevice"
	42	[89]	CALL     	3 2 2
	43	[89]	TEST     	3 0 0
	44	[89]	JMP      	92	; to 137
	45	[90]	GETUPVAL 	3 2	; Geom
	46	[90]	SELF     	3 3 -19	; "new"
	47	[90]	NEWTABLE 	5 0 4
	48	[91]	SETTABLE 	5 -20 -21	; "x" 0
	49	[91]	SETTABLE 	5 -22 -21	; "y" 0
	50	[92]	GETUPVAL 	6 3	; Screen
	51	[92]	SELF     	6 6 -24	; "getWidth"
	52	[92]	CALL     	6 2 2
	53	[92]	SETTABLE 	5 -23 6	; "w" -
	54	[93]	GETUPVAL 	6 3	; Screen
	55	[93]	SELF     	6 6 -26	; "getHeight"
	56	[93]	CALL     	6 2 2
	57	[93]	SETTABLE 	5 -25 6	; "h" -
	58	[90]	CALL     	3 3 2
	59	[95]	NEWTABLE 	4 0 8
	60	[96]	NEWTABLE 	5 0 0
	61	[97]	GETUPVAL 	6 4	; GestureRange
	62	[97]	SELF     	6 6 -19	; "new"
	63	[97]	NEWTABLE 	8 0 2
	64	[98]	SETTABLE 	8 -29 -30	; "ges" "tap"
	65	[99]	SETTABLE 	8 -31 3	; "range" -
	66	[97]	CALL     	6 3 0
	67	[101]	SETLIST  	5 0 1	; 1
	68	[101]	SETTABLE 	4 -28 5	; "TapCloseDict" -
	69	[102]	NEWTABLE 	5 0 0
	70	[103]	GETUPVAL 	6 4	; GestureRange
	71	[103]	SELF     	6 6 -19	; "new"
	72	[103]	NEWTABLE 	8 0 2
	73	[104]	SETTABLE 	8 -29 -33	; "ges" "swipe"
	74	[105]	SETTABLE 	8 -31 3	; "range" -
	75	[103]	CALL     	6 3 0
	76	[107]	SETLIST  	5 0 1	; 1
	77	[107]	SETTABLE 	4 -32 5	; "Swipe" -
	78	[126]	NEWTABLE 	5 0 0
	79	[127]	GETUPVAL 	6 4	; GestureRange
	80	[127]	SELF     	6 6 -19	; "new"
	81	[127]	NEWTABLE 	8 0 2
	82	[128]	SETTABLE 	8 -29 -35	; "ges" "hold"
	83	[129]	SETTABLE 	8 -31 3	; "range" -
	84	[127]	CALL     	6 3 0
	85	[131]	SETLIST  	5 0 1	; 1
	86	[131]	SETTABLE 	4 -34 5	; "HoldStartText" -
	87	[132]	NEWTABLE 	5 0 0
	88	[133]	GETUPVAL 	6 4	; GestureRange
	89	[133]	SELF     	6 6 -19	; "new"
	90	[133]	NEWTABLE 	8 0 2
	91	[134]	SETTABLE 	8 -29 -35	; "ges" "hold"
	92	[135]	SETTABLE 	8 -31 3	; "range" -
	93	[133]	CALL     	6 3 0
	94	[137]	SETLIST  	5 0 1	; 1
	95	[137]	SETTABLE 	4 -36 5	; "HoldPanText" -
	96	[138]	NEWTABLE 	5 1 1
	97	[139]	GETUPVAL 	6 4	; GestureRange
	98	[139]	SELF     	6 6 -19	; "new"
	99	[139]	NEWTABLE 	8 0 2
	100	[140]	SETTABLE 	8 -29 -38	; "ges" "hold_release"
	101	[141]	SETTABLE 	8 -31 3	; "range" -
	102	[139]	CALL     	6 3 2
	103	[162]	CLOSURE  	7 0	; 0x7fd305c08070
	104	[162]	MOVE     	0 0
	105	[162]	GETUPVAL 	0 5	; Event
	106	[162]	SETTABLE 	5 -39 7	; "args" -
	107	[163]	SETLIST  	5 1 1	; 1
	108	[163]	SETTABLE 	4 -37 5	; "HoldReleaseText" -
	109	[165]	NEWTABLE 	5 0 0
	110	[165]	GETUPVAL 	6 4	; GestureRange
	111	[165]	SELF     	6 6 -19	; "new"
	112	[165]	NEWTABLE 	8 0 2
	113	[165]	SETTABLE 	8 -29 -41	; "ges" "touch"
	114	[165]	SETTABLE 	8 -31 3	; "range" -
	115	[165]	CALL     	6 3 0
	116	[165]	SETLIST  	5 0 1	; 1
	117	[165]	SETTABLE 	4 -40 5	; "ForwardingTouch" -
	118	[166]	NEWTABLE 	5 0 0
	119	[166]	GETUPVAL 	6 4	; GestureRange
	120	[166]	SELF     	6 6 -19	; "new"
	121	[166]	NEWTABLE 	8 0 2
	122	[166]	SETTABLE 	8 -29 -43	; "ges" "pan"
	123	[166]	SETTABLE 	8 -31 3	; "range" -
	124	[166]	CALL     	6 3 0
	125	[166]	SETLIST  	5 0 1	; 1
	126	[166]	SETTABLE 	4 -42 5	; "ForwardingPan" -
	127	[167]	NEWTABLE 	5 0 0
	128	[167]	GETUPVAL 	6 4	; GestureRange
	129	[167]	SELF     	6 6 -19	; "new"
	130	[167]	NEWTABLE 	8 0 2
	131	[167]	SETTABLE 	8 -29 -45	; "ges" "pan_release"
	132	[167]	SETTABLE 	8 -31 3	; "range" -
	133	[167]	CALL     	6 3 0
	134	[167]	SETLIST  	5 0 1	; 1
	135	[167]	SETTABLE 	4 -44 5	; "ForwardingPanRelease" -
	136	[168]	SETTABLE 	0 -27 4	; "ges_events" -
	137	[170]	RETURN   	0 1

function <./frontend/ui/widget/dictquicklookup.lua:144,162> (34 instructions, 136 bytes at 0x7fd305c08070)
2 params, 9 slots, 2 upvalues, 3 locals, 8 constants, 0 functions
	1	[146]	LT       	0 1 -1	; - 3
	2	[146]	JMP      	9	; to 12
	3	[148]	GETUPVAL 	3 0	; self
	4	[148]	GETTABLE 	3 3 -2	; "is_wiki"
	5	[148]	TEST     	3 0 0
	6	[148]	JMP      	3	; to 10
	7	[148]	LOADK    	3 -3	; "LookupWikipedia"
	8	[148]	TESTSET  	2 3 1
	9	[148]	JMP      	1	; to 11
	10	[148]	LOADK    	2 -4	; "LookupWord"
	11	[148]	JMP      	8	; to 20
	12	[151]	GETUPVAL 	3 0	; self
	13	[151]	GETTABLE 	3 3 -2	; "is_wiki"
	14	[151]	TEST     	3 0 0
	15	[151]	JMP      	3	; to 19
	16	[151]	LOADK    	3 -4	; "LookupWord"
	17	[151]	TESTSET  	2 3 1
	18	[151]	JMP      	1	; to 20
	19	[151]	LOADK    	2 -3	; "LookupWikipedia"
	20	[153]	EQ       	0 2 -3	; - "LookupWikipedia"
	21	[153]	JMP      	3	; to 25
	22	[154]	GETUPVAL 	3 0	; self
	23	[154]	SELF     	3 3 -5	; "resyncWikiLanguages"
	24	[154]	CALL     	3 2 1
	25	[156]	GETUPVAL 	3 0	; self
	26	[156]	GETTABLE 	3 3 -6	; "ui"
	27	[156]	SELF     	3 3 -7	; "handleEvent"
	28	[160]	GETUPVAL 	5 1	; Event
	29	[160]	SELF     	5 5 -8	; "new"
	30	[160]	MOVE     	7 2
	31	[160]	MOVE     	8 0
	32	[160]	CALL     	5 4 0
	33	[156]	CALL     	3 0 1
	34	[162]	RETURN   	0 1

function <./frontend/ui/widget/dictquicklookup.lua:173,175> (11 instructions, 44 bytes at 0x7fd305c08780)
1 param, 2 slots, 0 upvalues, 1 local, 3 constants, 0 functions
	1	[174]	GETTABLE 	1 0 -1	; "ui"
	2	[174]	EQ       	1 1 -2	; - nil
	3	[174]	JMP      	5	; to 9
	4	[174]	GETTABLE 	1 0 -1	; "ui"
	5	[174]	GETTABLE 	1 1 -3	; "highlight"
	6	[174]	EQ       	1 1 -2	; - nil
	7	[174]	JMP      	1	; to 9
	8	[174]	LOADBOOL 	1 0 1
	9	[174]	LOADBOOL 	1 1 0
	10	[174]	RETURN   	1 2
	11	[175]	RETURN   	0 1

function <./frontend/ui/widget/dictquicklookup.lua:177,212> (23 instructions, 92 bytes at 0x7fd305c08460)
1 param, 5 slots, 0 upvalues, 3 locals, 8 constants, 0 functions
	1	[181]	GETGLOBAL	1 -1	; G_reader_settings
	2	[181]	SELF     	1 1 -2	; "nilOrTrue"
	3	[181]	LOADK    	3 -3	; "dict_justify"
	4	[181]	CALL     	1 3 2
	5	[181]	TEST     	1 0 0
	6	[181]	JMP      	3	; to 10
	7	[181]	LOADK    	1 -4	; "text-align: justify;"
	8	[181]	TEST     	1 0 1
	9	[181]	JMP      	1	; to 11
	10	[181]	LOADK    	1 -5	; ""
	11	[191]	LOADK    	2 -6	; "        @page {\n            margin: 0;\n            font-family: 'Noto Sans';\n        }\n\n        body {\n            margin: 0;\n            line-height: 1.3;\n            "
	12	[191]	MOVE     	3 1
	13	[197]	LOADK    	4 -7	; "        }\n\n        blockquote, dd {\n            margin: 0 1em;\n        }\n    "
	14	[197]	CONCAT   	2 2 4
	15	[208]	GETTABLE 	3 0 -8	; "css"
	16	[208]	TEST     	3 0 0
	17	[208]	JMP      	4	; to 22
	18	[209]	MOVE     	3 2
	19	[209]	GETTABLE 	4 0 -8	; "css"
	20	[209]	CONCAT   	3 3 4
	21	[209]	RETURN   	3 2
	22	[211]	RETURN   	2 2
	23	[212]	RETURN   	0 1

function <./frontend/ui/widget/dictquicklookup.lua:214,603> (665 instructions, 2660 bytes at 0x7fd305c08ef0)
1 param, 33 slots, 27 upvalues, 18 locals, 138 constants, 12 functions
	1	[215]	GETTABLE 	1 0 -1	; "dict_frame"
	2	[215]	TEST     	1 0 0
	3	[215]	JMP      	4	; to 8
	4	[215]	GETTABLE 	1 0 -1	; "dict_frame"
	5	[215]	GETTABLE 	1 1 -2	; "dimen"
	6	[215]	TEST     	1 0 1
	7	[215]	JMP      	4	; to 12
	8	[215]	GETUPVAL 	1 0	; Geom
	9	[215]	SELF     	1 1 -3	; "new"
	10	[215]	NEWTABLE 	3 0 0
	11	[215]	CALL     	1 3 2
	12	[216]	GETTABLE 	2 0 -4	; "movable"
	13	[216]	TEST     	2 0 0
	14	[216]	JMP      	3	; to 18
	15	[216]	GETTABLE 	2 0 -4	; "movable"
	16	[216]	SELF     	2 2 -5	; "getMovedOffset"
	17	[216]	CALL     	2 2 2
	18	[220]	GETTABLE 	3 0 -6	; 1
	19	[220]	TEST     	3 0 0
	20	[220]	JMP      	3	; to 24
	21	[221]	GETTABLE 	3 0 -6	; 1
	22	[221]	SELF     	3 3 -7	; "free"
	23	[221]	CALL     	3 2 1
	24	[224]	SETTABLE 	0 -8 -9	; "align" "center"
	25	[225]	GETUPVAL 	3 0	; Geom
	26	[225]	SELF     	3 3 -3	; "new"
	27	[225]	NEWTABLE 	5 0 4
	28	[226]	SETTABLE 	5 -11 -12	; "x" 0
	29	[226]	SETTABLE 	5 -13 -12	; "y" 0
	30	[227]	GETUPVAL 	6 1	; Screen
	31	[227]	SELF     	6 6 -15	; "getWidth"
	32	[227]	CALL     	6 2 2
	33	[227]	SETTABLE 	5 -14 6	; "w" -
	34	[228]	GETUPVAL 	6 1	; Screen
	35	[228]	SELF     	6 6 -17	; "getHeight"
	36	[228]	CALL     	6 2 2
	37	[228]	SETTABLE 	5 -16 6	; "h" -
	38	[225]	CALL     	3 3 2
	39	[229]	SETTABLE 	0 -10 3	; "region" -
	40	[230]	GETTABLE 	3 0 -18	; "is_fullpage"
	41	[230]	TEST     	3 0 1
	42	[230]	JMP      	6	; to 49
	43	[230]	GETGLOBAL	3 -19	; G_reader_settings
	44	[230]	SELF     	3 3 -20	; "isTrue"
	45	[230]	LOADK    	5 -21	; "dict_largewindow"
	46	[230]	CALL     	3 3 2
	47	[230]	TEST     	3 0 0
	48	[230]	JMP      	14	; to 63
	49	[233]	GETUPVAL 	3 1	; Screen
	50	[233]	SELF     	3 3 -17	; "getHeight"
	51	[233]	CALL     	3 2 2
	52	[233]	SETTABLE 	0 -22 3	; "height" -
	53	[234]	GETUPVAL 	3 1	; Screen
	54	[234]	SELF     	3 3 -15	; "getWidth"
	55	[234]	CALL     	3 2 2
	56	[234]	GETUPVAL 	4 1	; Screen
	57	[234]	SELF     	4 4 -24	; "scaleBySize"
	58	[234]	LOADK    	6 -25	; 40
	59	[234]	CALL     	4 3 2
	60	[234]	SUB      	3 3 4
	61	[234]	SETTABLE 	0 -23 3	; "width" -
	62	[234]	JMP      	57	; to 120
	63	[238]	GETTABLE 	3 0 -26	; "word_box"
	64	[238]	TEST     	3 0 0
	65	[238]	JMP      	43	; to 109
	66	[239]	GETTABLE 	3 0 -26	; "word_box"
	67	[240]	GETTABLE 	4 3 -13	; "y"
	68	[240]	GETTABLE 	5 3 -16	; "h"
	69	[240]	DIV      	5 5 -27	; - 2
	70	[240]	ADD      	4 4 5
	71	[240]	GETUPVAL 	5 1	; Screen
	72	[240]	SELF     	5 5 -17	; "getHeight"
	73	[240]	CALL     	5 2 2
	74	[240]	MUL      	5 5 -28	; - 0.3
	75	[240]	LT       	0 4 5
	76	[240]	JMP      	16	; to 93
	77	[241]	GETTABLE 	4 0 -10	; "region"
	78	[241]	GETTABLE 	5 3 -13	; "y"
	79	[241]	GETTABLE 	6 3 -16	; "h"
	80	[241]	ADD      	5 5 6
	81	[241]	SETTABLE 	4 -13 5	; "y" -
	82	[242]	GETTABLE 	4 0 -10	; "region"
	83	[242]	GETUPVAL 	5 1	; Screen
	84	[242]	SELF     	5 5 -17	; "getHeight"
	85	[242]	CALL     	5 2 2
	86	[242]	GETTABLE 	6 3 -13	; "y"
	87	[242]	SUB      	5 5 6
	88	[242]	GETTABLE 	6 3 -16	; "h"
	89	[242]	SUB      	5 5 6
	90	[242]	SETTABLE 	4 -16 5	; "h" -
	91	[243]	SETTABLE 	0 -8 -29	; "align" "top"
	92	[243]	JMP      	16	; to 109
	93	[244]	GETTABLE 	4 3 -13	; "y"
	94	[244]	GETTABLE 	5 3 -16	; "h"
	95	[244]	DIV      	5 5 -27	; - 2
	96	[244]	ADD      	4 4 5
	97	[244]	GETUPVAL 	5 1	; Screen
	98	[244]	SELF     	5 5 -17	; "getHeight"
	99	[244]	CALL     	5 2 2
	100	[244]	MUL      	5 5 -30	; - 0.7
	101	[244]	LT       	0 5 4
	102	[244]	JMP      	6	; to 109
	103	[245]	GETTABLE 	4 0 -10	; "region"
	104	[245]	SETTABLE 	4 -13 -12	; "y" 0
	105	[246]	GETTABLE 	4 0 -10	; "region"
	106	[246]	GETTABLE 	5 3 -13	; "y"
	107	[246]	SETTABLE 	4 -16 5	; "h" -
	108	[247]	SETTABLE 	0 -8 -31	; "align" "bottom"
	109	[250]	GETGLOBAL	3 -32	; math
	110	[250]	GETTABLE 	3 3 -33	; "min"
	111	[250]	GETTABLE 	4 0 -10	; "region"
	112	[250]	GETTABLE 	4 4 -16	; "h"
	113	[250]	MUL      	4 4 -30	; - 0.7
	114	[250]	GETUPVAL 	5 1	; Screen
	115	[250]	SELF     	5 5 -17	; "getHeight"
	116	[250]	CALL     	5 2 2
	117	[250]	MUL      	5 5 -34	; - 0.5
	118	[250]	CALL     	3 3 2
	119	[250]	SETTABLE 	0 -22 3	; "height" -
	120	[253]	GETUPVAL 	3 2	; CloseButton
	121	[253]	SELF     	3 3 -3	; "new"
	122	[253]	NEWTABLE 	5 0 2
	123	[253]	SETTABLE 	5 -35 0	; "window" -
	124	[253]	GETTABLE 	6 0 -37	; "title_margin"
	125	[253]	SETTABLE 	5 -36 6	; "padding_top" -
	126	[253]	CALL     	3 3 2
	127	[254]	SELF     	4 3 -38	; "getSize"
	128	[254]	CALL     	4 2 2
	129	[254]	GETTABLE 	4 4 -14	; "w"
	130	[254]	GETUPVAL 	5 3	; Size
	131	[254]	GETTABLE 	5 5 -39	; "padding"
	132	[254]	GETTABLE 	5 5 -40	; "default"
	133	[254]	MUL      	5 5 -27	; - 2
	134	[254]	ADD      	4 4 5
	135	[255]	GETUPVAL 	5 4	; TextWidget
	136	[255]	SELF     	5 5 -3	; "new"
	137	[255]	NEWTABLE 	7 0 4
	138	[256]	GETTABLE 	8 0 -42	; "dictionary"
	139	[256]	SETTABLE 	7 -41 8	; "text" -
	140	[257]	GETTABLE 	8 0 -44	; "title_face"
	141	[257]	SETTABLE 	7 -43 8	; "face" -
	142	[258]	SETTABLE 	7 -45 -46	; "bold" true
	143	[259]	GETTABLE 	8 0 -23	; "width"
	144	[259]	SUB      	8 8 4
	145	[259]	SETTABLE 	7 -47 8	; "max_width" -
	146	[255]	CALL     	5 3 2
	147	[262]	LOADNIL  	6 9
	148	[264]	GETTABLE 	10 0 -48	; "is_wiki"
	149	[264]	TEST     	10 0 0
	150	[264]	JMP      	34	; to 185
	151	[266]	GETUPVAL 	10 5	; CenterContainer
	152	[266]	SELF     	10 10 -3	; "new"
	153	[266]	NEWTABLE 	12 1 1
	154	[267]	GETUPVAL 	13 0	; Geom
	155	[267]	SELF     	13 13 -3	; "new"
	156	[267]	NEWTABLE 	15 0 2
	157	[268]	GETTABLE 	16 0 -23	; "width"
	158	[268]	SETTABLE 	15 -14 16	; "w" -
	159	[269]	SELF     	16 5 -38	; "getSize"
	160	[269]	CALL     	16 2 2
	161	[269]	GETTABLE 	16 16 -16	; "h"
	162	[269]	SETTABLE 	15 -16 16	; "h" -
	163	[267]	CALL     	13 3 2
	164	[270]	SETTABLE 	12 -2 13	; "dimen" -
	165	[272]	MOVE     	13 5
	166	[272]	SETLIST  	12 1 1	; 1
	167	[266]	CALL     	10 3 2
	168	[272]	MOVE     	9 10
	169	[274]	LOADK    	6 -49	; 18
	170	[275]	GETTABLE 	7 0 -50	; "wiki_word_padding"
	171	[276]	GETTABLE 	8 0 -51	; "wiki_word_margin"
	172	[279]	GETTABLE 	10 0 -53	; "wiki_languages"
	173	[279]	TEST     	10 0 0
	174	[279]	JMP      	7	; to 182
	175	[279]	NEWTABLE 	10 0 0
	176	[279]	GETGLOBAL	11 -54	; unpack
	177	[279]	GETTABLE 	12 0 -53	; "wiki_languages"
	178	[279]	CALL     	11 2 0
	179	[279]	SETLIST  	10 0 1	; 1
	180	[279]	TEST     	10 0 1
	181	[279]	JMP      	1	; to 183
	182	[279]	LOADNIL  	10 10
	183	[279]	SETTABLE 	0 -52 10	; "wiki_languages_copy" -
	184	[279]	JMP      	4	; to 189
	185	[281]	MOVE     	9 5
	186	[283]	LOADK    	6 -55	; 22
	187	[284]	GETTABLE 	7 0 -56	; "word_padding"
	188	[285]	GETTABLE 	8 0 -57	; "word_margin"
	189	[287]	GETUPVAL 	10 6	; FrameContainer
	190	[287]	SELF     	10 10 -3	; "new"
	191	[287]	NEWTABLE 	12 1 3
	192	[288]	GETTABLE 	13 0 -59	; "title_padding"
	193	[288]	SETTABLE 	12 -39 13	; "padding" -
	194	[289]	GETTABLE 	13 0 -37	; "title_margin"
	195	[289]	SETTABLE 	12 -60 13	; "margin" -
	196	[290]	SETTABLE 	12 -61 -12	; "bordersize" 0
	197	[292]	MOVE     	13 9
	198	[292]	SETLIST  	12 1 1	; 1
	199	[287]	CALL     	10 3 2
	200	[292]	SETTABLE 	0 -58 10	; "dict_title" -
	201	[294]	GETUPVAL 	10 7	; Button
	202	[294]	SELF     	10 10 -3	; "new"
	203	[294]	NEWTABLE 	12 0 8
	204	[295]	SETTABLE 	12 -39 7	; "padding" -
	205	[296]	SETTABLE 	12 -60 8	; "margin" -
	206	[297]	SETTABLE 	12 -61 -12	; "bordersize" 0
	207	[298]	GETTABLE 	13 0 -23	; "width"
	208	[298]	SETTABLE 	12 -47 13	; "max_width" -
	209	[299]	GETTABLE 	13 0 -62	; "displayword"
	210	[299]	SETTABLE 	12 -41 13	; "text" -
	211	[300]	SETTABLE 	12 -63 -64	; "text_font_face" "tfont"
	212	[301]	SETTABLE 	12 -65 6	; "text_font_size" -
	213	[302]	CLOSURE  	13 0	; 0x7fd305c097c0
	214	[302]	MOVE     	0 0
	215	[302]	SETTABLE 	12 -66 13	; "hold_callback" -
	216	[294]	CALL     	10 3 2
	217	[305]	LOADNIL  	11 11
	218	[307]	GETTABLE 	12 0 -67	; "is_html"
	219	[307]	TEST     	12 0 0
	220	[307]	JMP      	38	; to 259
	221	[308]	GETUPVAL 	12 8	; ScrollHtmlWidget
	222	[308]	SELF     	12 12 -3	; "new"
	223	[308]	NEWTABLE 	14 0 7
	224	[309]	GETTABLE 	15 0 -69	; "definition"
	225	[309]	SETTABLE 	14 -68 15	; "html_body" -
	226	[310]	SELF     	15 0 -71	; "getHtmlDictionaryCss"
	227	[310]	CALL     	15 2 2
	228	[310]	SETTABLE 	14 -70 15	; "css" -
	229	[311]	GETUPVAL 	15 1	; Screen
	230	[311]	SELF     	15 15 -24	; "scaleBySize"
	231	[311]	GETGLOBAL	17 -19	; G_reader_settings
	232	[311]	SELF     	17 17 -73	; "readSetting"
	233	[311]	LOADK    	19 -74	; "dict_font_size"
	234	[311]	CALL     	17 3 2
	235	[311]	TEST     	17 0 1
	236	[311]	JMP      	1	; to 238
	237	[311]	LOADK    	17 -75	; 20
	238	[311]	CALL     	15 3 2
	239	[311]	SETTABLE 	14 -72 15	; "default_font_size" -
	240	[312]	GETTABLE 	15 0 -23	; "width"
	241	[312]	SETTABLE 	14 -23 15	; "width" -
	242	[313]	GETTABLE 	15 0 -18	; "is_fullpage"
	243	[313]	TEST     	15 0 0
	244	[313]	JMP      	4	; to 249
	245	[313]	GETTABLE 	15 0 -22	; "height"
	246	[313]	MUL      	15 15 -76	; - 0.75
	247	[313]	TEST     	15 0 1
	248	[313]	JMP      	2	; to 251
	249	[313]	GETTABLE 	15 0 -22	; "height"
	250	[313]	MUL      	15 15 -30	; - 0.7
	251	[313]	SETTABLE 	14 -22 15	; "height" -
	252	[314]	SETTABLE 	14 -77 0	; "dialog" -
	253	[317]	CLOSURE  	15 1	; 0x7fd305c099d0
	254	[317]	MOVE     	0 0
	255	[317]	SETTABLE 	14 -78 15	; "html_link_tapped_callback" -
	256	[308]	CALL     	12 3 2
	257	[318]	MOVE     	11 12
	258	[318]	JMP      	43	; to 302
	259	[320]	GETUPVAL 	12 9	; ScrollTextWidget
	260	[320]	SELF     	12 12 -3	; "new"
	261	[320]	NEWTABLE 	14 0 11
	262	[321]	GETTABLE 	15 0 -69	; "definition"
	263	[321]	SETTABLE 	14 -41 15	; "text" -
	264	[322]	GETTABLE 	15 0 -79	; "content_face"
	265	[322]	SETTABLE 	14 -43 15	; "face" -
	266	[323]	GETTABLE 	15 0 -23	; "width"
	267	[323]	SETTABLE 	14 -23 15	; "width" -
	268	[325]	GETTABLE 	15 0 -18	; "is_fullpage"
	269	[325]	TEST     	15 0 0
	270	[325]	JMP      	4	; to 275
	271	[325]	GETTABLE 	15 0 -22	; "height"
	272	[325]	MUL      	15 15 -76	; - 0.75
	273	[325]	TEST     	15 0 1
	274	[325]	JMP      	2	; to 277
	275	[325]	GETTABLE 	15 0 -22	; "height"
	276	[325]	MUL      	15 15 -30	; - 0.7
	277	[325]	SETTABLE 	14 -22 15	; "height" -
	278	[326]	SETTABLE 	14 -77 0	; "dialog" -
	279	[328]	GETGLOBAL	15 -19	; G_reader_settings
	280	[328]	SELF     	15 15 -81	; "nilOrTrue"
	281	[328]	LOADK    	17 -82	; "dict_justify"
	282	[328]	CALL     	15 3 2
	283	[328]	SETTABLE 	14 -80 15	; "justified" -
	284	[329]	GETTABLE 	15 0 -83	; "lang"
	285	[329]	TEST     	15 0 0
	286	[329]	JMP      	3	; to 290
	287	[329]	GETTABLE 	15 0 -83	; "lang"
	288	[329]	SELF     	15 15 -84	; "lower"
	289	[329]	CALL     	15 2 2
	290	[329]	SETTABLE 	14 -83 15	; "lang" -
	291	[330]	GETTABLE 	15 0 -86	; "rtl_lang"
	292	[330]	SETTABLE 	14 -85 15	; "para_direction_rtl" -
	293	[331]	GETTABLE 	15 0 -48	; "is_wiki"
	294	[331]	NOT      	15 15
	295	[331]	SETTABLE 	14 -87 15	; "auto_para_direction" -
	296	[332]	GETTABLE 	15 0 -88	; "image_alt_face"
	297	[332]	SETTABLE 	14 -88 15	; "image_alt_face" -
	298	[333]	GETTABLE 	15 0 -89	; "images"
	299	[333]	SETTABLE 	14 -89 15	; "images" -
	300	[320]	CALL     	12 3 2
	301	[334]	MOVE     	11 12
	302	[338]	GETUPVAL 	12 6	; FrameContainer
	303	[338]	SELF     	12 12 -3	; "new"
	304	[338]	NEWTABLE 	14 1 3
	305	[339]	GETTABLE 	15 0 -91	; "definition_padding"
	306	[339]	SETTABLE 	14 -39 15	; "padding" -
	307	[340]	GETTABLE 	15 0 -92	; "definition_margin"
	308	[340]	SETTABLE 	14 -60 15	; "margin" -
	309	[341]	SETTABLE 	14 -61 -12	; "bordersize" 0
	310	[343]	MOVE     	15 11
	311	[343]	SETLIST  	14 1 1	; 1
	312	[338]	CALL     	12 3 2
	313	[343]	SETTABLE 	0 -90 12	; "definition_widget" -
	314	[345]	LOADNIL  	12 12
	315	[346]	GETTABLE 	13 0 -18	; "is_fullpage"
	316	[346]	TEST     	13 0 0
	317	[346]	JMP      	28	; to 346
	318	[348]	NEWTABLE 	13 1 0
	319	[348]	NEWTABLE 	14 2 0
	320	[349]	NEWTABLE 	15 0 2
	321	[351]	GETUPVAL 	16 10	; _
	322	[351]	LOADK    	17 -93	; "Save as EPUB"
	323	[351]	CALL     	16 2 2
	324	[351]	SETTABLE 	15 -41 16	; "text" -
	325	[416]	CLOSURE  	16 2	; 0x7fd305c09db0
	326	[416]	MOVE     	0 0
	327	[416]	GETUPVAL 	0 11	; util
	328	[416]	GETUPVAL 	0 12	; UIManager
	329	[416]	GETUPVAL 	0 10	; _
	330	[416]	GETUPVAL 	0 13	; T
	331	[416]	GETUPVAL 	0 14	; BD
	332	[416]	SETTABLE 	15 -94 16	; "callback" -
	333	[417]	NEWTABLE 	16 0 2
	334	[419]	GETUPVAL 	17 10	; _
	335	[419]	LOADK    	18 -95	; "Close"
	336	[419]	CALL     	17 2 2
	337	[419]	SETTABLE 	16 -41 17	; "text" -
	338	[422]	CLOSURE  	17 3	; 0x7fd305c0b670
	339	[422]	GETUPVAL 	0 12	; UIManager
	340	[422]	MOVE     	0 0
	341	[422]	SETTABLE 	16 -94 17	; "callback" -
	342	[424]	SETLIST  	14 2 1	; 1
	343	[425]	SETLIST  	13 1 1	; 1
	344	[425]	MOVE     	12 13
	345	[425]	JMP      	127	; to 473
	346	[427]	LOADK    	13 -96	; "\226\151\129\226\151\129"
	347	[428]	LOADK    	14 -97	; "\226\150\183\226\150\183"
	348	[429]	GETUPVAL 	15 14	; BD
	349	[429]	GETTABLE 	15 15 -98	; "mirroredUILayout"
	350	[429]	CALL     	15 1 2
	351	[429]	TEST     	15 0 0
	352	[429]	JMP      	3	; to 356
	353	[430]	MOVE     	15 14
	354	[430]	MOVE     	14 13
	355	[430]	MOVE     	13 15
	356	[432]	NEWTABLE 	15 2 0
	357	[432]	NEWTABLE 	16 3 0
	358	[433]	NEWTABLE 	17 0 3
	359	[435]	SETTABLE 	17 -41 13	; "text" -
	360	[436]	SELF     	18 0 -100	; "isPrevDictAvaiable"
	361	[436]	CALL     	18 2 2
	362	[436]	SETTABLE 	17 -99 18	; "enabled" -
	363	[439]	CLOSURE  	18 4	; 0x7fd305c0c310
	364	[439]	MOVE     	0 0
	365	[439]	SETTABLE 	17 -94 18	; "callback" -
	366	[440]	NEWTABLE 	18 0 3
	367	[442]	SELF     	19 0 -101	; "getHighlightText"
	368	[442]	CALL     	19 2 2
	369	[442]	SETTABLE 	18 -41 19	; "text" -
	370	[443]	GETTABLE 	19 0 -102	; "highlight"
	371	[443]	EQ       	0 19 -103	; - nil
	372	[443]	JMP      	1	; to 374
	373	[443]	LOADBOOL 	19 0 1
	374	[443]	LOADBOOL 	19 1 0
	375	[443]	SETTABLE 	18 -99 19	; "enabled" -
	376	[451]	CLOSURE  	19 5	; 0x7fd305c0c5c0
	377	[451]	MOVE     	0 0
	378	[451]	GETUPVAL 	0 15	; highlight_strings
	379	[451]	GETUPVAL 	0 16	; Event
	380	[451]	SETTABLE 	18 -94 19	; "callback" -
	381	[452]	NEWTABLE 	19 0 3
	382	[454]	SETTABLE 	19 -41 14	; "text" -
	383	[455]	SELF     	20 0 -104	; "isNextDictAvaiable"
	384	[455]	CALL     	20 2 2
	385	[455]	SETTABLE 	19 -99 20	; "enabled" -
	386	[458]	CLOSURE  	20 6	; 0x7fd305c0cbb0
	387	[458]	MOVE     	0 0
	388	[458]	SETTABLE 	19 -94 20	; "callback" -
	389	[460]	SETLIST  	16 3 1	; 1
	390	[460]	NEWTABLE 	17 3 0
	391	[461]	NEWTABLE 	18 0 2
	392	[472]	CLOSURE  	19 7	; 0x7fd305c0cd60
	393	[472]	MOVE     	0 0
	394	[472]	GETUPVAL 	0 17	; C_
	395	[472]	GETUPVAL 	0 10	; _
	396	[472]	SETTABLE 	18 -105 19	; "text_func" -
	397	[477]	CLOSURE  	19 8	; 0x7fd305c0cf00
	398	[477]	GETUPVAL 	0 12	; UIManager
	399	[477]	MOVE     	0 0
	400	[477]	SETTABLE 	18 -94 19	; "callback" -
	401	[478]	NEWTABLE 	19 0 3
	402	[485]	GETTABLE 	20 0 -48	; "is_wiki"
	403	[485]	TEST     	20 0 0
	404	[485]	JMP      	22	; to 427
	405	[485]	GETTABLE 	20 0 -53	; "wiki_languages"
	406	[485]	LEN      	20 20
	407	[485]	LT       	0 -6 20	; 1 -
	408	[485]	JMP      	14	; to 423
	409	[485]	GETUPVAL 	20 14	; BD
	410	[485]	GETTABLE 	20 20 -106	; "wrap"
	411	[485]	GETTABLE 	21 0 -53	; "wiki_languages"
	412	[485]	GETTABLE 	21 21 -6	; 1
	413	[485]	CALL     	20 2 2
	414	[485]	LOADK    	21 -107	; " > "
	415	[485]	GETUPVAL 	22 14	; BD
	416	[485]	GETTABLE 	22 22 -106	; "wrap"
	417	[485]	GETTABLE 	23 0 -53	; "wiki_languages"
	418	[485]	GETTABLE 	23 23 -27	; 2
	419	[485]	CALL     	22 2 2
	420	[485]	CONCAT   	20 20 22
	421	[486]	TEST     	20 0 1
	422	[486]	JMP      	7	; to 430
	423	[486]	GETTABLE 	20 0 -53	; "wiki_languages"
	424	[486]	GETTABLE 	20 20 -6	; 1
	425	[487]	TEST     	20 0 1
	426	[487]	JMP      	3	; to 430
	427	[487]	GETUPVAL 	20 10	; _
	428	[487]	LOADK    	21 -108	; "Follow Link"
	429	[487]	CALL     	20 2 2
	430	[487]	SETTABLE 	19 -41 20	; "text" -
	431	[488]	GETTABLE 	20 0 -48	; "is_wiki"
	432	[488]	TEST     	20 0 0
	433	[488]	JMP      	4	; to 438
	434	[488]	GETTABLE 	20 0 -53	; "wiki_languages"
	435	[488]	LEN      	20 20
	436	[488]	LT       	1 -6 20	; 1 -
	437	[488]	JMP      	4	; to 442
	438	[488]	GETTABLE 	20 0 -109	; "selected_link"
	439	[488]	EQ       	0 20 -103	; - nil
	440	[488]	JMP      	1	; to 442
	441	[488]	LOADBOOL 	20 0 1
	442	[488]	LOADBOOL 	20 1 0
	443	[488]	SETTABLE 	19 -99 20	; "enabled" -
	444	[499]	CLOSURE  	20 9	; 0x7fd305c0d720
	445	[499]	MOVE     	0 0
	446	[499]	GETUPVAL 	0 12	; UIManager
	447	[499]	SETTABLE 	19 -94 20	; "callback" -
	448	[500]	NEWTABLE 	20 0 2
	449	[502]	GETTABLE 	21 0 -48	; "is_wiki"
	450	[502]	TEST     	21 0 1
	451	[502]	JMP      	4	; to 456
	452	[502]	SELF     	21 0 -110	; "isDocless"
	453	[502]	CALL     	21 2 2
	454	[502]	TEST     	21 0 0
	455	[502]	JMP      	5	; to 461
	456	[502]	GETUPVAL 	21 10	; _
	457	[502]	LOADK    	22 -95	; "Close"
	458	[502]	CALL     	21 2 2
	459	[502]	TEST     	21 0 1
	460	[502]	JMP      	3	; to 464
	461	[502]	GETUPVAL 	21 10	; _
	462	[502]	LOADK    	22 -111	; "Search"
	463	[502]	CALL     	21 2 2
	464	[502]	SETTABLE 	20 -41 21	; "text" -
	465	[508]	CLOSURE  	21 10	; 0x7fd305c0d980
	466	[508]	MOVE     	0 0
	467	[508]	GETUPVAL 	0 16	; Event
	468	[508]	GETUPVAL 	0 12	; UIManager
	469	[508]	SETTABLE 	20 -94 21	; "callback" -
	470	[510]	SETLIST  	17 3 1	; 1
	471	[511]	SETLIST  	15 2 1	; 1
	472	[511]	MOVE     	12 15
	473	[514]	GETUPVAL 	13 18	; ButtonTable
	474	[514]	SELF     	13 13 -3	; "new"
	475	[514]	NEWTABLE 	15 0 6
	476	[515]	GETGLOBAL	16 -32	; math
	477	[515]	GETTABLE 	16 16 -112	; "max"
	478	[515]	GETTABLE 	17 0 -23	; "width"
	479	[515]	GETTABLE 	18 0 -90	; "definition_widget"
	480	[515]	SELF     	18 18 -38	; "getSize"
	481	[515]	CALL     	18 2 2
	482	[515]	GETTABLE 	18 18 -14	; "w"
	483	[515]	CALL     	16 3 2
	484	[515]	SETTABLE 	15 -23 16	; "width" -
	485	[516]	SETTABLE 	15 -113 -114	; "button_font_face" "cfont"
	486	[517]	SETTABLE 	15 -115 -75	; "button_font_size" 20
	487	[518]	SETTABLE 	15 -116 12	; "buttons" -
	488	[519]	SETTABLE 	15 -117 -46	; "zero_sep" true
	489	[520]	SETTABLE 	15 -118 0	; "show_parent" -
	490	[514]	CALL     	13 3 2
	491	[522]	GETUPVAL 	14 19	; LineWidget
	492	[522]	SELF     	14 14 -3	; "new"
	493	[522]	NEWTABLE 	16 0 1
	494	[523]	GETUPVAL 	17 0	; Geom
	495	[523]	SELF     	17 17 -3	; "new"
	496	[523]	NEWTABLE 	19 0 2
	497	[524]	SELF     	20 13 -38	; "getSize"
	498	[524]	CALL     	20 2 2
	499	[524]	GETTABLE 	20 20 -14	; "w"
	500	[524]	GETTABLE 	21 0 -119	; "button_padding"
	501	[524]	ADD      	20 20 21
	502	[524]	SETTABLE 	19 -14 20	; "w" -
	503	[525]	GETUPVAL 	20 3	; Size
	504	[525]	GETTABLE 	20 20 -120	; "line"
	505	[525]	GETTABLE 	20 20 -121	; "thick"
	506	[525]	SETTABLE 	19 -16 20	; "h" -
	507	[523]	CALL     	17 3 2
	508	[526]	SETTABLE 	16 -2 17	; "dimen" -
	509	[522]	CALL     	14 3 2
	510	[529]	GETUPVAL 	15 20	; OverlapGroup
	511	[529]	SELF     	15 15 -3	; "new"
	512	[529]	NEWTABLE 	17 2 1
	513	[530]	NEWTABLE 	18 0 2
	514	[531]	SELF     	19 13 -38	; "getSize"
	515	[531]	CALL     	19 2 2
	516	[531]	GETTABLE 	19 19 -14	; "w"
	517	[531]	GETTABLE 	20 0 -119	; "button_padding"
	518	[531]	ADD      	19 19 20
	519	[531]	SETTABLE 	18 -14 19	; "w" -
	520	[532]	GETTABLE 	19 0 -58	; "dict_title"
	521	[532]	SELF     	19 19 -38	; "getSize"
	522	[532]	CALL     	19 2 2
	523	[532]	GETTABLE 	19 19 -16	; "h"
	524	[532]	SETTABLE 	18 -16 19	; "h" -
	525	[533]	SETTABLE 	17 -2 18	; "dimen" -
	526	[534]	GETTABLE 	18 0 -58	; "dict_title"
	527	[536]	MOVE     	19 3
	528	[536]	SETLIST  	17 2 1	; 1
	529	[529]	CALL     	15 3 2
	530	[536]	SETTABLE 	0 -122 15	; "dict_bar" -
	531	[538]	SELF     	15 5 -123	; "setMaxWidth"
	532	[538]	GETTABLE 	17 0 -122	; "dict_bar"
	533	[538]	GETTABLE 	17 17 -2	; "dimen"
	534	[538]	GETTABLE 	17 17 -14	; "w"
	535	[538]	SELF     	18 3 -38	; "getSize"
	536	[538]	CALL     	18 2 2
	537	[538]	GETTABLE 	18 18 -14	; "w"
	538	[538]	SUB      	17 17 18
	539	[538]	CALL     	15 3 1
	540	[540]	GETUPVAL 	15 6	; FrameContainer
	541	[540]	SELF     	15 15 -3	; "new"
	542	[540]	NEWTABLE 	17 0 5
	543	[541]	GETUPVAL 	18 3	; Size
	544	[541]	GETTABLE 	18 18 -124	; "radius"
	545	[541]	GETTABLE 	18 18 -35	; "window"
	546	[541]	SETTABLE 	17 -124 18	; "radius" -
	547	[542]	GETUPVAL 	18 3	; Size
	548	[542]	GETTABLE 	18 18 -125	; "border"
	549	[542]	GETTABLE 	18 18 -35	; "window"
	550	[542]	SETTABLE 	17 -61 18	; "bordersize" -
	551	[543]	SETTABLE 	17 -39 -12	; "padding" 0
	552	[544]	SETTABLE 	17 -60 -12	; "margin" 0
	553	[545]	GETUPVAL 	18 21	; Blitbuffer
	554	[545]	GETTABLE 	18 18 -127	; "COLOR_WHITE"
	555	[545]	SETTABLE 	17 -126 18	; "background" -
	556	[546]	GETUPVAL 	18 22	; VerticalGroup
	557	[546]	SELF     	18 18 -3	; "new"
	558	[546]	NEWTABLE 	20 4 1
	559	[547]	SETTABLE 	20 -8 -128	; "align" "left"
	560	[548]	GETTABLE 	21 0 -122	; "dict_bar"
	561	[549]	MOVE     	22 14
	562	[551]	GETUPVAL 	23 23	; LeftContainer
	563	[551]	SELF     	23 23 -3	; "new"
	564	[551]	NEWTABLE 	25 1 1
	565	[552]	GETUPVAL 	26 0	; Geom
	566	[552]	SELF     	26 26 -3	; "new"
	567	[552]	NEWTABLE 	28 0 2
	568	[553]	SELF     	29 14 -38	; "getSize"
	569	[553]	CALL     	29 2 2
	570	[553]	GETTABLE 	29 29 -14	; "w"
	571	[553]	SETTABLE 	28 -14 29	; "w" -
	572	[554]	SELF     	29 10 -38	; "getSize"
	573	[554]	CALL     	29 2 2
	574	[554]	GETTABLE 	29 29 -16	; "h"
	575	[554]	SETTABLE 	28 -16 29	; "h" -
	576	[552]	CALL     	26 3 2
	577	[555]	SETTABLE 	25 -2 26	; "dimen" -
	578	[557]	MOVE     	26 10
	579	[557]	SETLIST  	25 1 1	; 1
	580	[551]	CALL     	23 3 2
	581	[559]	GETUPVAL 	24 5	; CenterContainer
	582	[559]	SELF     	24 24 -3	; "new"
	583	[559]	NEWTABLE 	26 1 1
	584	[560]	GETUPVAL 	27 0	; Geom
	585	[560]	SELF     	27 27 -3	; "new"
	586	[560]	NEWTABLE 	29 0 2
	587	[561]	SELF     	30 14 -38	; "getSize"
	588	[561]	CALL     	30 2 2
	589	[561]	GETTABLE 	30 30 -14	; "w"
	590	[561]	SETTABLE 	29 -14 30	; "w" -
	591	[562]	GETTABLE 	30 0 -90	; "definition_widget"
	592	[562]	SELF     	30 30 -38	; "getSize"
	593	[562]	CALL     	30 2 2
	594	[562]	GETTABLE 	30 30 -16	; "h"
	595	[562]	SETTABLE 	29 -16 30	; "h" -
	596	[560]	CALL     	27 3 2
	597	[563]	SETTABLE 	26 -2 27	; "dimen" -
	598	[565]	GETTABLE 	27 0 -90	; "definition_widget"
	599	[565]	SETLIST  	26 1 1	; 1
	600	[559]	CALL     	24 3 2
	601	[567]	GETUPVAL 	25 5	; CenterContainer
	602	[567]	SELF     	25 25 -3	; "new"
	603	[567]	NEWTABLE 	27 1 1
	604	[568]	GETUPVAL 	28 0	; Geom
	605	[568]	SELF     	28 28 -3	; "new"
	606	[568]	NEWTABLE 	30 0 2
	607	[569]	SELF     	31 14 -38	; "getSize"
	608	[569]	CALL     	31 2 2
	609	[569]	GETTABLE 	31 31 -14	; "w"
	610	[569]	SETTABLE 	30 -14 31	; "w" -
	611	[570]	SELF     	31 13 -38	; "getSize"
	612	[570]	CALL     	31 2 2
	613	[570]	GETTABLE 	31 31 -16	; "h"
	614	[570]	SETTABLE 	30 -16 31	; "h" -
	615	[568]	CALL     	28 3 2
	616	[571]	SETTABLE 	27 -2 28	; "dimen" -
	617	[573]	MOVE     	28 13
	618	[573]	SETLIST  	27 1 1	; 1
	619	[567]	CALL     	25 3 0
	620	[574]	SETLIST  	20 0 1	; 1
	621	[546]	CALL     	18 3 0
	622	[575]	SETLIST  	17 0 1	; 1
	623	[540]	CALL     	15 3 2
	624	[575]	SETTABLE 	0 -1 15	; "dict_frame" -
	625	[577]	GETUPVAL 	15 24	; MovableContainer
	626	[577]	SELF     	15 15 -3	; "new"
	627	[577]	NEWTABLE 	17 1 1
	628	[580]	NEWTABLE 	18 7 0
	629	[583]	LOADK    	19 -130	; "swipe"
	630	[583]	LOADK    	20 -131	; "hold"
	631	[583]	LOADK    	21 -132	; "hold_release"
	632	[583]	LOADK    	22 -133	; "hold_pan"
	633	[587]	LOADK    	23 -134	; "touch"
	634	[587]	LOADK    	24 -135	; "pan"
	635	[588]	LOADK    	25 -136	; "pan_release"
	636	[588]	SETLIST  	18 7 1	; 1
	637	[588]	SETTABLE 	17 -129 18	; "ignore_events" -
	638	[590]	GETTABLE 	18 0 -1	; "dict_frame"
	639	[590]	SETLIST  	17 1 1	; 1
	640	[577]	CALL     	15 3 2
	641	[590]	SETTABLE 	0 -4 15	; "movable" -
	642	[591]	GETTABLE 	15 0 -4	; "movable"
	643	[591]	SELF     	15 15 -137	; "setMovedOffset"
	644	[591]	MOVE     	17 2
	645	[591]	CALL     	15 3 1
	646	[593]	GETUPVAL 	15 25	; WidgetContainer
	647	[593]	SELF     	15 15 -3	; "new"
	648	[593]	NEWTABLE 	17 1 2
	649	[594]	GETTABLE 	18 0 -8	; "align"
	650	[594]	SETTABLE 	17 -8 18	; "align" -
	651	[595]	GETTABLE 	18 0 -10	; "region"
	652	[595]	SETTABLE 	17 -2 18	; "dimen" -
	653	[597]	GETTABLE 	18 0 -4	; "movable"
	654	[597]	SETLIST  	17 1 1	; 1
	655	[593]	CALL     	15 3 2
	656	[597]	SETTABLE 	0 -6 15	; 1 -
	657	[598]	GETUPVAL 	15 12	; UIManager
	658	[598]	SELF     	15 15 -138	; "setDirty"
	659	[598]	MOVE     	17 0
	660	[602]	CLOSURE  	18 11	; 0x7fd305c0e4e0
	661	[602]	MOVE     	0 0
	662	[602]	MOVE     	0 1
	663	[602]	GETUPVAL 	0 26	; logger
	664	[598]	CALL     	15 4 1
	665	[603]	RETURN   	0 1

function <./frontend/ui/widget/dictquicklookup.lua:302,302> (6 instructions, 24 bytes at 0x7fd305c097c0)
0 params, 3 slots, 1 upvalue, 0 locals, 2 constants, 0 functions
	1	[302]	GETUPVAL 	0 0	; self
	2	[302]	SELF     	0 0 -1	; "lookupInputWord"
	3	[302]	GETUPVAL 	2 0	; self
	4	[302]	GETTABLE 	2 2 -2	; "lookupword"
	5	[302]	CALL     	0 3 1
	6	[302]	RETURN   	0 1

function <./frontend/ui/widget/dictquicklookup.lua:315,317> (7 instructions, 28 bytes at 0x7fd305c099d0)
1 param, 4 slots, 1 upvalue, 1 local, 2 constants, 0 functions
	1	[316]	GETUPVAL 	1 0	; self
	2	[316]	GETTABLE 	1 1 -1	; "html_dictionary_link_tapped_callback"
	3	[316]	GETUPVAL 	2 0	; self
	4	[316]	GETTABLE 	2 2 -2	; "dictionary"
	5	[316]	MOVE     	3 0
	6	[316]	CALL     	1 3 1
	7	[317]	RETURN   	0 1

function <./frontend/ui/widget/dictquicklookup.lua:352,416> (125 instructions, 500 bytes at 0x7fd305c09db0)
0 params, 16 slots, 6 upvalues, 8 locals, 36 constants, 1 function
	1	[353]	GETGLOBAL	0 -1	; require
	2	[353]	LOADK    	1 -2	; "ui/widget/infomessage"
	3	[353]	CALL     	0 2 2
	4	[354]	GETGLOBAL	1 -1	; require
	5	[354]	LOADK    	2 -3	; "ui/widget/confirmbox"
	6	[354]	CALL     	1 2 2
	7	[357]	GETUPVAL 	2 0	; self
	8	[357]	GETTABLE 	2 2 -4	; "lang"
	9	[357]	TEST     	2 0 1
	10	[357]	JMP      	3	; to 14
	11	[357]	GETUPVAL 	2 0	; self
	12	[357]	GETTABLE 	2 2 -5	; "wiki_languages_copy"
	13	[357]	GETTABLE 	2 2 -6	; 1
	14	[360]	GETUPVAL 	3 1	; util
	15	[360]	GETTABLE 	3 3 -7	; "getSafeFilename"
	16	[360]	GETUPVAL 	4 0	; self
	17	[360]	GETTABLE 	4 4 -8	; "lookupword"
	18	[360]	SELF     	4 4 -9	; "gsub"
	19	[360]	LOADK    	6 -10	; "_"
	20	[360]	LOADK    	7 -11	; " "
	21	[360]	CALL     	4 4 0
	22	[360]	CALL     	3 0 2
	23	[361]	MOVE     	4 3
	24	[361]	LOADK    	5 -12	; "."
	25	[361]	GETGLOBAL	6 -13	; string
	26	[361]	GETTABLE 	6 6 -14	; "upper"
	27	[361]	MOVE     	7 2
	28	[361]	CALL     	6 2 2
	29	[361]	LOADK    	7 -15	; ".epub"
	30	[361]	CONCAT   	4 4 7
	31	[363]	LOADNIL  	5 5
	32	[364]	GETGLOBAL	6 -16	; G_reader_settings
	33	[364]	SELF     	6 6 -17	; "isTrue"
	34	[364]	LOADK    	8 -18	; "wikipedia_save_in_book_dir"
	35	[364]	CALL     	6 3 2
	36	[364]	TEST     	6 0 0
	37	[364]	JMP      	15	; to 53
	38	[364]	GETUPVAL 	6 0	; self
	39	[364]	SELF     	6 6 -19	; "isDocless"
	40	[364]	CALL     	6 2 2
	41	[364]	TEST     	6 0 1
	42	[364]	JMP      	10	; to 53
	43	[365]	GETGLOBAL	6 -16	; G_reader_settings
	44	[365]	SELF     	6 6 -20	; "readSetting"
	45	[365]	LOADK    	8 -21	; "lastfile"
	46	[365]	CALL     	6 3 2
	47	[366]	TEST     	6 0 0
	48	[366]	JMP      	4	; to 53
	49	[367]	SELF     	7 6 -22	; "match"
	50	[367]	LOADK    	9 -23	; "(.*)/"
	51	[367]	CALL     	7 3 2
	52	[367]	MOVE     	5 7
	53	[370]	TEST     	5 0 1
	54	[370]	JMP      	5	; to 60
	55	[370]	GETGLOBAL	6 -16	; G_reader_settings
	56	[370]	SELF     	6 6 -20	; "readSetting"
	57	[370]	LOADK    	8 -24	; "wikipedia_save_dir"
	58	[370]	CALL     	6 3 2
	59	[370]	MOVE     	5 6
	60	[371]	TEST     	5 0 1
	61	[371]	JMP      	5	; to 67
	62	[371]	GETGLOBAL	6 -16	; G_reader_settings
	63	[371]	SELF     	6 6 -20	; "readSetting"
	64	[371]	LOADK    	8 -25	; "home_dir"
	65	[371]	CALL     	6 3 2
	66	[371]	MOVE     	5 6
	67	[372]	TEST     	5 0 1
	68	[372]	JMP      	6	; to 75
	69	[372]	GETGLOBAL	6 -1	; require
	70	[372]	LOADK    	7 -26	; "apps/filemanager/filemanagerutil"
	71	[372]	CALL     	6 2 2
	72	[372]	GETTABLE 	6 6 -27	; "getDefaultDir"
	73	[372]	CALL     	6 1 2
	74	[372]	MOVE     	5 6
	75	[373]	TEST     	5 0 0
	76	[373]	JMP      	6	; to 83
	77	[373]	GETUPVAL 	6 1	; util
	78	[373]	GETTABLE 	6 6 -28	; "pathExists"
	79	[373]	MOVE     	7 5
	80	[373]	CALL     	6 2 2
	81	[373]	TEST     	6 0 1
	82	[373]	JMP      	11	; to 94
	83	[374]	GETUPVAL 	6 2	; UIManager
	84	[374]	SELF     	6 6 -29	; "show"
	85	[374]	SELF     	8 0 -30	; "new"
	86	[374]	NEWTABLE 	10 0 1
	87	[375]	GETUPVAL 	11 3	; _
	88	[375]	LOADK    	12 -32	; "No directory to save article to could be found."
	89	[375]	CALL     	11 2 2
	90	[375]	SETTABLE 	10 -31 11	; "text" -
	91	[374]	CALL     	8 3 0
	92	[374]	CALL     	6 0 1
	93	[377]	RETURN   	0 1
	94	[379]	MOVE     	6 5
	95	[379]	LOADK    	7 -33	; "/"
	96	[379]	MOVE     	8 4
	97	[379]	CONCAT   	6 6 8
	98	[380]	GETUPVAL 	7 2	; UIManager
	99	[380]	SELF     	7 7 -29	; "show"
	100	[380]	SELF     	9 1 -30	; "new"
	101	[380]	NEWTABLE 	11 0 2
	102	[381]	GETUPVAL 	12 4	; T
	103	[381]	GETUPVAL 	13 3	; _
	104	[381]	LOADK    	14 -34	; "Save as %1?"
	105	[381]	CALL     	13 2 2
	106	[381]	GETUPVAL 	14 5	; BD
	107	[381]	GETTABLE 	14 14 -35	; "filename"
	108	[381]	MOVE     	15 4
	109	[381]	CALL     	14 2 0
	110	[381]	CALL     	12 0 2
	111	[381]	SETTABLE 	11 -31 12	; "text" -
	112	[414]	CLOSURE  	12 0	; 0x7fd305c0a250
	113	[414]	GETUPVAL 	0 2	; UIManager
	114	[414]	MOVE     	0 6
	115	[414]	GETUPVAL 	0 0	; self
	116	[414]	MOVE     	0 2
	117	[414]	MOVE     	0 1
	118	[414]	GETUPVAL 	0 4	; T
	119	[414]	GETUPVAL 	0 3	; _
	120	[414]	GETUPVAL 	0 5	; BD
	121	[414]	MOVE     	0 0
	122	[414]	SETTABLE 	11 -36 12	; "ok_callback" -
	123	[380]	CALL     	9 3 0
	124	[380]	CALL     	7 0 1
	125	[416]	RETURN   	0 1

function <./frontend/ui/widget/dictquicklookup.lua:382,414> (15 instructions, 60 bytes at 0x7fd305c0a250)
0 params, 4 slots, 9 upvalues, 0 locals, 2 constants, 1 function
	1	[383]	GETUPVAL 	0 0	; UIManager
	2	[383]	SELF     	0 0 -1	; "scheduleIn"
	3	[383]	LOADK    	2 -2	; 0.1
	4	[413]	CLOSURE  	3 0	; 0x7fd305c0a720
	5	[413]	GETUPVAL 	0 1	; epub_path
	6	[413]	GETUPVAL 	0 2	; self
	7	[413]	GETUPVAL 	0 3	; lang
	8	[413]	GETUPVAL 	0 0	; UIManager
	9	[413]	GETUPVAL 	0 4	; ConfirmBox
	10	[413]	GETUPVAL 	0 5	; T
	11	[413]	GETUPVAL 	0 6	; _
	12	[413]	GETUPVAL 	0 7	; BD
	13	[413]	GETUPVAL 	0 8	; InfoMessage
	14	[383]	CALL     	0 4 1
	15	[414]	RETURN   	0 1

function <./frontend/ui/widget/dictquicklookup.lua:383,413> (19 instructions, 76 bytes at 0x7fd305c0a720)
0 params, 7 slots, 9 upvalues, 1 local, 4 constants, 1 function
	1	[384]	GETGLOBAL	0 -1	; require
	2	[384]	LOADK    	1 -2	; "ui/wikipedia"
	3	[384]	CALL     	0 2 2
	4	[385]	SELF     	1 0 -3	; "createEpubWithUI"
	5	[385]	GETUPVAL 	3 0	; epub_path
	6	[385]	GETUPVAL 	4 1	; self
	7	[385]	GETTABLE 	4 4 -4	; "lookupword"
	8	[385]	GETUPVAL 	5 2	; lang
	9	[412]	CLOSURE  	6 0	; 0x7fd305c0ac40
	10	[412]	GETUPVAL 	0 3	; UIManager
	11	[412]	GETUPVAL 	0 4	; ConfirmBox
	12	[412]	GETUPVAL 	0 5	; T
	13	[412]	GETUPVAL 	0 6	; _
	14	[412]	GETUPVAL 	0 7	; BD
	15	[412]	GETUPVAL 	0 0	; epub_path
	16	[412]	GETUPVAL 	0 1	; self
	17	[412]	GETUPVAL 	0 8	; InfoMessage
	18	[385]	CALL     	1 6 1
	19	[413]	RETURN   	0 1

function <./frontend/ui/widget/dictquicklookup.lua:385,412> (37 instructions, 148 bytes at 0x7fd305c0ac40)
1 param, 10 slots, 8 upvalues, 1 local, 7 constants, 1 function
	1	[386]	TEST     	0 0 0
	2	[386]	JMP      	23	; to 26
	3	[387]	GETUPVAL 	1 0	; UIManager
	4	[387]	SELF     	1 1 -1	; "show"
	5	[387]	GETUPVAL 	3 1	; ConfirmBox
	6	[387]	SELF     	3 3 -2	; "new"
	7	[387]	NEWTABLE 	5 0 2
	8	[388]	GETUPVAL 	6 2	; T
	9	[388]	GETUPVAL 	7 3	; _
	10	[388]	LOADK    	8 -4	; "Article saved to:\n%1\n\nWould you like to read the downloaded article now?"
	11	[388]	CALL     	7 2 2
	12	[388]	GETUPVAL 	8 4	; BD
	13	[388]	GETTABLE 	8 8 -5	; "filepath"
	14	[388]	GETUPVAL 	9 5	; epub_path
	15	[388]	CALL     	8 2 0
	16	[388]	CALL     	6 0 2
	17	[388]	SETTABLE 	5 -3 6	; "text" -
	18	[405]	CLOSURE  	6 0	; 0x7fd305c0b6f0
	19	[405]	GETUPVAL 	0 6	; self
	20	[405]	GETUPVAL 	0 0	; UIManager
	21	[405]	GETUPVAL 	0 5	; epub_path
	22	[405]	SETTABLE 	5 -6 6	; "ok_callback" -
	23	[387]	CALL     	3 3 0
	24	[387]	CALL     	1 0 1
	25	[406]	JMP      	11	; to 37
	26	[408]	GETUPVAL 	1 0	; UIManager
	27	[408]	SELF     	1 1 -1	; "show"
	28	[408]	GETUPVAL 	3 7	; InfoMessage
	29	[408]	SELF     	3 3 -2	; "new"
	30	[408]	NEWTABLE 	5 0 1
	31	[409]	GETUPVAL 	6 3	; _
	32	[409]	LOADK    	7 -7	; "Saving Wikipedia article failed or canceled."
	33	[409]	CALL     	6 2 2
	34	[409]	SETTABLE 	5 -3 6	; "text" -
	35	[408]	CALL     	3 3 0
	36	[408]	CALL     	1 0 1
	37	[412]	RETURN   	0 1

function <./frontend/ui/widget/dictquicklookup.lua:389,405> (11 instructions, 44 bytes at 0x7fd305c0b6f0)
0 params, 4 slots, 3 upvalues, 0 locals, 3 constants, 1 function
	1	[391]	GETUPVAL 	0 0	; self
	2	[391]	SELF     	0 0 -1	; "onHoldClose"
	3	[391]	LOADBOOL 	2 1 0
	4	[391]	CALL     	0 3 1
	5	[393]	GETUPVAL 	0 1	; UIManager
	6	[393]	SELF     	0 0 -2	; "scheduleIn"
	7	[393]	LOADK    	2 -3	; 1
	8	[404]	CLOSURE  	3 0	; 0x7fd305c0b770
	9	[404]	GETUPVAL 	0 2	; epub_path
	10	[393]	CALL     	0 4 1
	11	[405]	RETURN   	0 1

function <./frontend/ui/widget/dictquicklookup.lua:393,404> (19 instructions, 76 bytes at 0x7fd305c0b770)
0 params, 5 slots, 1 upvalue, 2 locals, 6 constants, 0 functions
	1	[394]	GETGLOBAL	0 -1	; require
	2	[394]	LOADK    	1 -2	; "apps/reader/readerui"
	3	[394]	CALL     	0 2 2
	4	[395]	SELF     	1 0 -3	; "_getRunningInstance"
	5	[395]	CALL     	1 2 2
	6	[396]	TEST     	1 0 0
	7	[396]	JMP      	8	; to 16
	8	[398]	GETTABLE 	2 1 -4	; "highlight"
	9	[398]	TEST     	2 0 0
	10	[398]	JMP      	3	; to 14
	11	[399]	GETTABLE 	2 1 -4	; "highlight"
	12	[399]	SELF     	2 2 -5	; "onClose"
	13	[399]	CALL     	2 2 1
	14	[401]	SELF     	2 1 -5	; "onClose"
	15	[401]	CALL     	2 2 1
	16	[403]	SELF     	2 0 -6	; "showReader"
	17	[403]	GETUPVAL 	4 0	; epub_path
	18	[403]	CALL     	2 3 1
	19	[404]	RETURN   	0 1

function <./frontend/ui/widget/dictquicklookup.lua:420,422> (5 instructions, 20 bytes at 0x7fd305c0b670)
0 params, 3 slots, 2 upvalues, 0 locals, 1 constant, 0 functions
	1	[421]	GETUPVAL 	0 0	; UIManager
	2	[421]	SELF     	0 0 -1	; "close"
	3	[421]	GETUPVAL 	2 1	; self
	4	[421]	CALL     	0 3 1
	5	[422]	RETURN   	0 1

function <./frontend/ui/widget/dictquicklookup.lua:437,439> (4 instructions, 16 bytes at 0x7fd305c0c310)
0 params, 2 slots, 1 upvalue, 0 locals, 1 constant, 0 functions
	1	[438]	GETUPVAL 	0 0	; self
	2	[438]	SELF     	0 0 -1	; "changeToPrevDict"
	3	[438]	CALL     	0 2 1
	4	[439]	RETURN   	0 1

function <./frontend/ui/widget/dictquicklookup.lua:444,451> (28 instructions, 112 bytes at 0x7fd305c0c5c0)
0 params, 5 slots, 3 upvalues, 0 locals, 8 constants, 0 functions
	1	[445]	GETUPVAL 	0 0	; self
	2	[445]	SELF     	0 0 -1	; "getHighlightText"
	3	[445]	CALL     	0 2 2
	4	[445]	GETUPVAL 	1 1	; highlight_strings
	5	[445]	GETTABLE 	1 1 -2	; "highlight"
	6	[445]	EQ       	0 0 1
	7	[445]	JMP      	9	; to 17
	8	[446]	GETUPVAL 	0 0	; self
	9	[446]	GETTABLE 	0 0 -3	; "ui"
	10	[446]	SELF     	0 0 -4	; "handleEvent"
	11	[446]	GETUPVAL 	2 2	; Event
	12	[446]	SELF     	2 2 -5	; "new"
	13	[446]	LOADK    	4 -6	; "Highlight"
	14	[446]	CALL     	2 3 0
	15	[446]	CALL     	0 0 1
	16	[446]	JMP      	8	; to 25
	17	[448]	GETUPVAL 	0 0	; self
	18	[448]	GETTABLE 	0 0 -3	; "ui"
	19	[448]	SELF     	0 0 -4	; "handleEvent"
	20	[448]	GETUPVAL 	2 2	; Event
	21	[448]	SELF     	2 2 -5	; "new"
	22	[448]	LOADK    	4 -7	; "Unhighlight"
	23	[448]	CALL     	2 3 0
	24	[448]	CALL     	0 0 1
	25	[450]	GETUPVAL 	0 0	; self
	26	[450]	SELF     	0 0 -8	; "update"
	27	[450]	CALL     	0 2 1
	28	[451]	RETURN   	0 1

function <./frontend/ui/widget/dictquicklookup.lua:456,458> (4 instructions, 16 bytes at 0x7fd305c0cbb0)
0 params, 2 slots, 1 upvalue, 0 locals, 1 constant, 0 functions
	1	[457]	GETUPVAL 	0 0	; self
	2	[457]	SELF     	0 0 -1	; "changeToNextDict"
	3	[457]	CALL     	0 2 1
	4	[458]	RETURN   	0 1

function <./frontend/ui/widget/dictquicklookup.lua:465,472> (15 instructions, 60 bytes at 0x7fd305c0cd60)
0 params, 3 slots, 3 upvalues, 0 locals, 4 constants, 0 functions
	1	[466]	GETUPVAL 	0 0	; self
	2	[466]	GETTABLE 	0 0 -1	; "is_wiki"
	3	[466]	TEST     	0 0 0
	4	[466]	JMP      	6	; to 11
	5	[468]	GETUPVAL 	0 1	; C_
	6	[468]	LOADK    	1 -2	; "Button"
	7	[468]	LOADK    	2 -3	; "Wikipedia full"
	8	[468]	TAILCALL 	0 3 0
	9	[468]	RETURN   	0 0
	10	[468]	JMP      	4	; to 15
	11	[470]	GETUPVAL 	0 2	; _
	12	[470]	LOADK    	1 -4	; "Wikipedia"
	13	[470]	TAILCALL 	0 2 0
	14	[470]	RETURN   	0 0
	15	[472]	RETURN   	0 1

function <./frontend/ui/widget/dictquicklookup.lua:473,477> (7 instructions, 28 bytes at 0x7fd305c0cf00)
0 params, 4 slots, 2 upvalues, 0 locals, 2 constants, 1 function
	1	[474]	GETUPVAL 	0 0	; UIManager
	2	[474]	SELF     	0 0 -1	; "scheduleIn"
	3	[474]	LOADK    	2 -2	; 0.1
	4	[476]	CLOSURE  	3 0	; 0x7fd305c0d3a0
	5	[476]	GETUPVAL 	0 1	; self
	6	[474]	CALL     	0 4 1
	7	[477]	RETURN   	0 1

function <./frontend/ui/widget/dictquicklookup.lua:474,476> (6 instructions, 24 bytes at 0x7fd305c0d3a0)
0 params, 3 slots, 1 upvalue, 0 locals, 2 constants, 0 functions
	1	[475]	GETUPVAL 	0 0	; self
	2	[475]	SELF     	0 0 -1	; "lookupWikipedia"
	3	[475]	GETUPVAL 	2 0	; self
	4	[475]	GETTABLE 	2 2 -2	; "is_wiki"
	5	[475]	CALL     	0 3 1
	6	[476]	RETURN   	0 1

function <./frontend/ui/widget/dictquicklookup.lua:489,499> (33 instructions, 132 bytes at 0x7fd305c0d720)
0 params, 4 slots, 2 upvalues, 1 local, 9 constants, 0 functions
	1	[490]	GETUPVAL 	0 0	; self
	2	[490]	GETTABLE 	0 0 -1	; "is_wiki"
	3	[490]	TEST     	0 0 0
	4	[490]	JMP      	12	; to 17
	5	[491]	GETUPVAL 	0 0	; self
	6	[491]	SELF     	0 0 -2	; "resyncWikiLanguages"
	7	[491]	LOADBOOL 	2 1 0
	8	[491]	CALL     	0 3 1
	9	[492]	GETUPVAL 	0 1	; UIManager
	10	[492]	SELF     	0 0 -3	; "close"
	11	[492]	GETUPVAL 	2 0	; self
	12	[492]	CALL     	0 3 1
	13	[493]	GETUPVAL 	0 0	; self
	14	[493]	SELF     	0 0 -4	; "lookupWikipedia"
	15	[493]	CALL     	0 2 1
	16	[493]	JMP      	16	; to 33
	17	[495]	GETUPVAL 	0 0	; self
	18	[495]	GETTABLE 	0 0 -5	; "selected_link"
	19	[495]	GETTABLE 	0 0 -6	; "link"
	20	[495]	TEST     	0 0 1
	21	[495]	JMP      	2	; to 24
	22	[495]	GETUPVAL 	0 0	; self
	23	[495]	GETTABLE 	0 0 -5	; "selected_link"
	24	[496]	GETUPVAL 	1 0	; self
	25	[496]	GETTABLE 	1 1 -7	; "ui"
	26	[496]	GETTABLE 	1 1 -6	; "link"
	27	[496]	SELF     	1 1 -8	; "onGotoLink"
	28	[496]	MOVE     	3 0
	29	[496]	CALL     	1 3 1
	30	[497]	GETUPVAL 	1 0	; self
	31	[497]	SELF     	1 1 -9	; "onClose"
	32	[497]	CALL     	1 2 1
	33	[499]	RETURN   	0 1

function <./frontend/ui/widget/dictquicklookup.lua:503,508> (17 instructions, 68 bytes at 0x7fd305c0d980)
0 params, 5 slots, 3 upvalues, 0 locals, 6 constants, 0 functions
	1	[504]	GETUPVAL 	0 0	; self
	2	[504]	GETTABLE 	0 0 -1	; "is_wiki"
	3	[504]	TEST     	0 0 1
	4	[504]	JMP      	8	; to 13
	5	[505]	GETUPVAL 	0 0	; self
	6	[505]	GETTABLE 	0 0 -2	; "ui"
	7	[505]	SELF     	0 0 -3	; "handleEvent"
	8	[505]	GETUPVAL 	2 1	; Event
	9	[505]	SELF     	2 2 -4	; "new"
	10	[505]	LOADK    	4 -5	; "HighlightSearch"
	11	[505]	CALL     	2 3 0
	12	[505]	CALL     	0 0 1
	13	[507]	GETUPVAL 	0 2	; UIManager
	14	[507]	SELF     	0 0 -6	; "close"
	15	[507]	GETUPVAL 	2 0	; self
	16	[507]	CALL     	0 3 1
	17	[508]	RETURN   	0 1

function <./frontend/ui/widget/dictquicklookup.lua:598,602> (27 instructions, 108 bytes at 0x7fd305c0e4e0)
0 params, 4 slots, 3 upvalues, 1 local, 6 constants, 0 functions
	1	[599]	GETUPVAL 	0 0	; self
	2	[599]	GETTABLE 	0 0 -1	; "dict_frame"
	3	[599]	TEST     	0 0 0
	4	[599]	JMP      	13	; to 18
	5	[599]	GETUPVAL 	0 0	; self
	6	[599]	GETTABLE 	0 0 -1	; "dict_frame"
	7	[599]	GETTABLE 	0 0 -2	; "dimen"
	8	[599]	TEST     	0 0 0
	9	[599]	JMP      	8	; to 18
	10	[599]	GETUPVAL 	0 0	; self
	11	[599]	GETTABLE 	0 0 -1	; "dict_frame"
	12	[599]	GETTABLE 	0 0 -2	; "dimen"
	13	[599]	SELF     	0 0 -3	; "combine"
	14	[599]	GETUPVAL 	2 1	; orig_dimen
	15	[599]	CALL     	0 3 2
	16	[599]	TEST     	0 0 1
	17	[599]	JMP      	1	; to 19
	18	[599]	GETUPVAL 	0 1	; orig_dimen
	19	[600]	GETUPVAL 	1 2	; logger
	20	[600]	GETTABLE 	1 1 -4	; "dbg"
	21	[600]	LOADK    	2 -5	; "update dict region"
	22	[600]	MOVE     	3 0
	23	[600]	CALL     	1 3 1
	24	[601]	LOADK    	1 -6	; "partial"
	25	[601]	MOVE     	2 0
	26	[601]	RETURN   	1 3
	27	[602]	RETURN   	0 1

function <./frontend/ui/widget/dictquicklookup.lua:605,628> (52 instructions, 208 bytes at 0x7fd305c0eb70)
1 param, 13 slots, 2 upvalues, 11 locals, 12 constants, 1 function
	1	[609]	GETTABLE 	1 0 -1	; 1
	2	[609]	TEST     	1 0 0
	3	[609]	JMP      	3	; to 7
	4	[610]	GETTABLE 	1 0 -1	; 1
	5	[610]	SELF     	1 1 -2	; "free"
	6	[610]	CALL     	1 2 1
	7	[612]	GETTABLE 	1 0 -3	; "images_cleanup_needed"
	8	[612]	TEST     	1 0 0
	9	[612]	JMP      	35	; to 45
	10	[613]	GETUPVAL 	1 0	; logger
	11	[613]	GETTABLE 	1 1 -4	; "dbg"
	12	[613]	LOADK    	2 -5	; "freeing lookup results images blitbuffers"
	13	[613]	CALL     	1 2 1
	14	[614]	GETGLOBAL	1 -6	; ipairs
	15	[614]	GETTABLE 	2 0 -7	; "results"
	16	[614]	CALL     	1 2 4
	17	[614]	JMP      	25	; to 43
	18	[615]	GETTABLE 	6 5 -8	; "images"
	19	[615]	TEST     	6 0 0
	20	[615]	JMP      	22	; to 43
	21	[615]	GETTABLE 	6 5 -8	; "images"
	22	[615]	LEN      	6 6
	23	[615]	LT       	0 -9 6	; 0 -
	24	[615]	JMP      	18	; to 43
	25	[616]	GETGLOBAL	6 -6	; ipairs
	26	[616]	GETTABLE 	7 5 -8	; "images"
	27	[616]	CALL     	6 2 4
	28	[616]	JMP      	12	; to 41
	29	[617]	GETTABLE 	11 10 -10	; "bb"
	30	[617]	TEST     	11 0 0
	31	[617]	JMP      	3	; to 35
	32	[617]	GETTABLE 	11 10 -10	; "bb"
	33	[617]	SELF     	11 11 -2	; "free"
	34	[617]	CALL     	11 2 1
	35	[618]	GETTABLE 	11 10 -11	; "hi_bb"
	36	[618]	TEST     	11 0 0
	37	[618]	JMP      	3	; to 41
	38	[618]	GETTABLE 	11 10 -11	; "hi_bb"
	39	[618]	SELF     	11 11 -2	; "free"
	40	[618]	CALL     	11 2 1
	41	[616]	TFORLOOP 	6 2
	42	[618]	JMP      	-14	; to 29
	43	[614]	TFORLOOP 	1 2
	44	[620]	JMP      	-27	; to 18
	45	[624]	GETUPVAL 	1 1	; UIManager
	46	[624]	SELF     	1 1 -12	; "setDirty"
	47	[624]	LOADNIL  	3 3
	48	[626]	CLOSURE  	4 0	; 0x7fd305c0ef70
	49	[624]	CALL     	1 4 1
	50	[627]	LOADBOOL 	1 1 0
	51	[627]	RETURN   	1 2
	52	[628]	RETURN   	0 1

function <./frontend/ui/widget/dictquicklookup.lua:624,626> (4 instructions, 16 bytes at 0x7fd305c0ef70)
0 params, 2 slots, 0 upvalues, 0 locals, 1 constant, 0 functions
	1	[625]	LOADK    	0 -1	; "flashui"
	2	[625]	LOADNIL  	1 1
	3	[625]	RETURN   	0 3
	4	[626]	RETURN   	0 1

function <./frontend/ui/widget/dictquicklookup.lua:630,635> (9 instructions, 36 bytes at 0x7fd305c0ee50)
1 param, 5 slots, 1 upvalue, 1 local, 1 constant, 1 function
	1	[631]	GETUPVAL 	1 0	; UIManager
	2	[631]	SELF     	1 1 -1	; "setDirty"
	3	[631]	MOVE     	3 0
	4	[633]	CLOSURE  	4 0	; 0x7fd305c0f5c0
	5	[633]	MOVE     	0 0
	6	[631]	CALL     	1 4 1
	7	[634]	LOADBOOL 	1 1 0
	8	[634]	RETURN   	1 2
	9	[635]	RETURN   	0 1

function <./frontend/ui/widget/dictquicklookup.lua:631,633> (6 instructions, 24 bytes at 0x7fd305c0f5c0)
0 params, 2 slots, 1 upvalue, 0 locals, 3 constants, 0 functions
	1	[632]	LOADK    	0 -1	; "flashui"
	2	[632]	GETUPVAL 	1 0	; self
	3	[632]	GETTABLE 	1 1 -2	; "dict_frame"
	4	[632]	GETTABLE 	1 1 -3	; "dimen"
	5	[632]	RETURN   	0 3
	6	[633]	RETURN   	0 1

function <./frontend/ui/widget/dictquicklookup.lua:637,640> (11 instructions, 44 bytes at 0x7fd305c0f9e0)
1 param, 3 slots, 0 upvalues, 1 local, 4 constants, 0 functions
	1	[638]	SELF     	1 0 -1	; "isDocless"
	2	[638]	CALL     	1 2 2
	3	[638]	TEST     	1 0 0
	4	[638]	JMP      	1	; to 6
	5	[638]	RETURN   	0 1
	6	[639]	GETTABLE 	1 0 -2	; "ui"
	7	[639]	GETTABLE 	1 1 -3	; "highlight"
	8	[639]	SELF     	1 1 -4	; "getHighlightBookmarkItem"
	9	[639]	TAILCALL 	1 2 0
	10	[639]	RETURN   	1 0
	11	[640]	RETURN   	0 1

function <./frontend/ui/widget/dictquicklookup.lua:642,651> (26 instructions, 104 bytes at 0x7fd305c0fb60)
1 param, 5 slots, 1 upvalue, 2 locals, 6 constants, 0 functions
	1	[643]	SELF     	1 0 -1	; "getHighlightedItem"
	2	[643]	CALL     	1 2 2
	3	[644]	TEST     	1 0 1
	4	[644]	JMP      	5	; to 10
	5	[645]	GETUPVAL 	2 0	; highlight_strings
	6	[645]	GETTABLE 	2 2 -2	; "highlight"
	7	[645]	LOADBOOL 	3 0 0
	8	[645]	RETURN   	2 3
	9	[645]	JMP      	16	; to 26
	10	[646]	GETTABLE 	2 0 -3	; "ui"
	11	[646]	GETTABLE 	2 2 -4	; "bookmark"
	12	[646]	SELF     	2 2 -5	; "isBookmarkAdded"
	13	[646]	MOVE     	4 1
	14	[646]	CALL     	2 3 2
	15	[646]	TEST     	2 0 0
	16	[646]	JMP      	5	; to 22
	17	[647]	GETUPVAL 	2 0	; highlight_strings
	18	[647]	GETTABLE 	2 2 -6	; "unhighlight"
	19	[647]	LOADBOOL 	3 0 0
	20	[647]	RETURN   	2 3
	21	[647]	JMP      	4	; to 26
	22	[649]	GETUPVAL 	2 0	; highlight_strings
	23	[649]	GETTABLE 	2 2 -2	; "highlight"
	24	[649]	LOADBOOL 	3 1 0
	25	[649]	RETURN   	2 3
	26	[651]	RETURN   	0 1

function <./frontend/ui/widget/dictquicklookup.lua:653,655> (7 instructions, 28 bytes at 0x7fd305c100f0)
1 param, 2 slots, 0 upvalues, 1 local, 2 constants, 0 functions
	1	[654]	GETTABLE 	1 0 -1	; "dict_index"
	2	[654]	LT       	1 -2 1	; 1 -
	3	[654]	JMP      	1	; to 5
	4	[654]	LOADBOOL 	1 0 1
	5	[654]	LOADBOOL 	1 1 0
	6	[654]	RETURN   	1 2
	7	[655]	RETURN   	0 1

function <./frontend/ui/widget/dictquicklookup.lua:657,659> (9 instructions, 36 bytes at 0x7fd305c10200)
1 param, 3 slots, 0 upvalues, 1 local, 2 constants, 0 functions
	1	[658]	GETTABLE 	1 0 -1	; "dict_index"
	2	[658]	GETTABLE 	2 0 -2	; "results"
	3	[658]	LEN      	2 2
	4	[658]	LT       	1 1 2
	5	[658]	JMP      	1	; to 7
	6	[658]	LOADBOOL 	1 0 1
	7	[658]	LOADBOOL 	1 1 0
	8	[658]	RETURN   	1 2
	9	[659]	RETURN   	0 1

function <./frontend/ui/widget/dictquicklookup.lua:661,667> (18 instructions, 72 bytes at 0x7fd305c106b0)
1 param, 4 slots, 0 upvalues, 1 local, 5 constants, 0 functions
	1	[662]	SELF     	1 0 -1	; "isPrevDictAvaiable"
	2	[662]	CALL     	1 2 2
	3	[662]	TEST     	1 0 0
	4	[662]	JMP      	5	; to 10
	5	[663]	SELF     	1 0 -2	; "changeDictionary"
	6	[663]	GETTABLE 	3 0 -3	; "dict_index"
	7	[663]	SUB      	3 3 -4	; - 1
	8	[663]	CALL     	1 3 1
	9	[663]	JMP      	8	; to 18
	10	[664]	GETTABLE 	1 0 -5	; "results"
	11	[664]	LEN      	1 1
	12	[664]	LT       	0 -4 1	; 1 -
	13	[664]	JMP      	4	; to 18
	14	[665]	SELF     	1 0 -2	; "changeDictionary"
	15	[665]	GETTABLE 	3 0 -5	; "results"
	16	[665]	LEN      	3 3
	17	[665]	CALL     	1 3 1
	18	[667]	RETURN   	0 1

function <./frontend/ui/widget/dictquicklookup.lua:669,675> (17 instructions, 68 bytes at 0x7fd305c0c210)
1 param, 4 slots, 0 upvalues, 1 local, 5 constants, 0 functions
	1	[670]	SELF     	1 0 -1	; "isNextDictAvaiable"
	2	[670]	CALL     	1 2 2
	3	[670]	TEST     	1 0 0
	4	[670]	JMP      	5	; to 10
	5	[671]	SELF     	1 0 -2	; "changeDictionary"
	6	[671]	GETTABLE 	3 0 -3	; "dict_index"
	7	[671]	ADD      	3 3 -4	; - 1
	8	[671]	CALL     	1 3 1
	9	[671]	JMP      	7	; to 17
	10	[672]	GETTABLE 	1 0 -5	; "results"
	11	[672]	LEN      	1 1
	12	[672]	LT       	0 -4 1	; 1 -
	13	[672]	JMP      	3	; to 17
	14	[673]	SELF     	1 0 -2	; "changeDictionary"
	15	[673]	LOADK    	3 -4	; 1
	16	[673]	CALL     	1 3 1
	17	[675]	RETURN   	0 1

function <./frontend/ui/widget/dictquicklookup.lua:677,714> (90 instructions, 360 bytes at 0x7fd305c0c4e0)
2 params, 7 slots, 2 upvalues, 2 locals, 24 constants, 0 functions
	1	[678]	GETTABLE 	2 0 -1	; "results"
	2	[678]	GETTABLE 	2 2 1
	3	[678]	TEST     	2 0 1
	4	[678]	JMP      	1	; to 6
	5	[678]	RETURN   	0 1
	6	[679]	SETTABLE 	0 -2 1	; "dict_index" -
	7	[680]	GETTABLE 	2 0 -1	; "results"
	8	[680]	GETTABLE 	2 2 1
	9	[680]	GETTABLE 	2 2 -4	; "dict"
	10	[680]	SETTABLE 	0 -3 2	; "dictionary" -
	11	[681]	GETTABLE 	2 0 -1	; "results"
	12	[681]	GETTABLE 	2 2 1
	13	[681]	GETTABLE 	2 2 -6	; "word"
	14	[681]	SETTABLE 	0 -5 2	; "lookupword" -
	15	[682]	GETTABLE 	2 0 -1	; "results"
	16	[682]	GETTABLE 	2 2 1
	17	[682]	GETTABLE 	2 2 -7	; "definition"
	18	[682]	SETTABLE 	0 -7 2	; "definition" -
	19	[683]	GETTABLE 	2 0 -1	; "results"
	20	[683]	GETTABLE 	2 2 1
	21	[683]	GETTABLE 	2 2 -8	; "is_fullpage"
	22	[683]	SETTABLE 	0 -8 2	; "is_fullpage" -
	23	[684]	GETTABLE 	2 0 -1	; "results"
	24	[684]	GETTABLE 	2 2 1
	25	[684]	GETTABLE 	2 2 -9	; "is_html"
	26	[684]	SETTABLE 	0 -9 2	; "is_html" -
	27	[685]	GETTABLE 	2 0 -1	; "results"
	28	[685]	GETTABLE 	2 2 1
	29	[685]	GETTABLE 	2 2 -10	; "css"
	30	[685]	SETTABLE 	0 -10 2	; "css" -
	31	[686]	GETTABLE 	2 0 -1	; "results"
	32	[686]	GETTABLE 	2 2 1
	33	[686]	GETTABLE 	2 2 -11	; "lang"
	34	[686]	SETTABLE 	0 -11 2	; "lang" -
	35	[687]	GETTABLE 	2 0 -1	; "results"
	36	[687]	GETTABLE 	2 2 1
	37	[687]	GETTABLE 	2 2 -12	; "rtl_lang"
	38	[687]	SETTABLE 	0 -12 2	; "rtl_lang" -
	39	[688]	GETTABLE 	2 0 -1	; "results"
	40	[688]	GETTABLE 	2 2 1
	41	[688]	GETTABLE 	2 2 -13	; "images"
	42	[688]	SETTABLE 	0 -13 2	; "images" -
	43	[689]	GETTABLE 	2 0 -13	; "images"
	44	[689]	TEST     	2 0 0
	45	[689]	JMP      	5	; to 51
	46	[689]	GETTABLE 	2 0 -13	; "images"
	47	[689]	LEN      	2 2
	48	[689]	LT       	0 -14 2	; 0 -
	49	[689]	JMP      	1	; to 51
	50	[693]	SETTABLE 	0 -15 -16	; "images_cleanup_needed" true
	51	[695]	GETTABLE 	2 0 -8	; "is_fullpage"
	52	[695]	TEST     	2 0 0
	53	[695]	JMP      	3	; to 57
	54	[696]	GETTABLE 	2 0 -5	; "lookupword"
	55	[696]	SETTABLE 	0 -17 2	; "displayword" -
	56	[696]	JMP      	31	; to 88
	57	[700]	GETTABLE 	2 0 -5	; "lookupword"
	58	[700]	LOADK    	3 -18	; "   "
	59	[700]	MOVE     	4 1
	60	[700]	LOADK    	5 -19	; " / "
	61	[700]	GETTABLE 	6 0 -1	; "results"
	62	[700]	LEN      	6 6
	63	[700]	CONCAT   	2 2 6
	64	[700]	SETTABLE 	0 -17 2	; "displayword" -
	65	[703]	EQ       	0 1 -20	; - 1
	66	[703]	JMP      	21	; to 88
	67	[704]	GETTABLE 	2 0 -9	; "is_html"
	68	[704]	TEST     	2 0 0
	69	[704]	JMP      	5	; to 75
	70	[705]	GETTABLE 	2 0 -7	; "definition"
	71	[705]	LOADK    	3 -21	; "<br/>_______<br/>"
	72	[705]	CONCAT   	2 2 3
	73	[705]	SETTABLE 	0 -7 2	; "definition" -
	74	[705]	JMP      	4	; to 79
	75	[707]	GETTABLE 	2 0 -7	; "definition"
	76	[707]	LOADK    	3 -22	; "\n_______\n"
	77	[707]	CONCAT   	2 2 3
	78	[707]	SETTABLE 	0 -7 2	; "definition" -
	79	[709]	GETTABLE 	2 0 -7	; "definition"
	80	[709]	GETUPVAL 	3 0	; T
	81	[709]	GETUPVAL 	4 1	; _
	82	[709]	LOADK    	5 -23	; "(query : %1)"
	83	[709]	CALL     	4 2 2
	84	[709]	GETTABLE 	5 0 -6	; "word"
	85	[709]	CALL     	3 3 2
	86	[709]	CONCAT   	2 2 3
	87	[709]	SETTABLE 	0 -7 2	; "definition" -
	88	[713]	SELF     	2 0 -24	; "update"
	89	[713]	CALL     	2 2 1
	90	[714]	RETURN   	0 1

function <./frontend/ui/widget/dictquicklookup.lua:716,743> (46 instructions, 184 bytes at 0x7fd305c09c60)
1 param, 10 slots, 0 upvalues, 11 locals, 6 constants, 0 functions
	1	[717]	GETTABLE 	1 0 -1	; "dictionary"
	2	[717]	TEST     	1 0 0
	3	[717]	JMP      	39	; to 43
	4	[720]	LOADNIL  	1 1
	5	[721]	GETTABLE 	2 0 -2	; "results"
	6	[721]	GETTABLE 	2 2 -3	; 1
	7	[721]	GETTABLE 	2 2 -4	; "word"
	8	[722]	LOADK    	3 -3	; 1
	9	[722]	GETTABLE 	4 0 -2	; "results"
	10	[722]	LEN      	4 4
	11	[722]	LOADK    	5 -3	; 1
	12	[722]	FORPREP  	3 8	; to 21
	13	[723]	GETTABLE 	7 0 -2	; "results"
	14	[723]	GETTABLE 	7 7 6
	15	[723]	GETTABLE 	7 7 -4	; "word"
	16	[723]	EQ       	0 7 2
	17	[723]	JMP      	4	; to 22
	18	[724]	MOVE     	1 6
	19	[724]	JMP      	1	; to 21
	20	[726]	JMP      	1	; to 22
	21	[722]	FORLOOP  	3 -9	; to 13
	22	[730]	LOADK    	3 -3	; 1
	23	[730]	MOVE     	4 1
	24	[730]	LOADK    	5 -3	; 1
	25	[730]	FORPREP  	3 15	; to 41
	26	[731]	GETTABLE 	7 0 -2	; "results"
	27	[731]	GETTABLE 	7 7 6
	28	[731]	GETTABLE 	7 7 -5	; "dict"
	29	[731]	GETTABLE 	8 0 -1	; "dictionary"
	30	[731]	EQ       	0 7 8
	31	[731]	JMP      	4	; to 36
	32	[732]	SELF     	7 0 -6	; "changeDictionary"
	33	[732]	MOVE     	9 6
	34	[732]	CALL     	7 3 1
	35	[733]	JMP      	10	; to 46
	36	[736]	EQ       	0 6 1
	37	[736]	JMP      	3	; to 41
	38	[737]	SELF     	7 0 -6	; "changeDictionary"
	39	[737]	LOADK    	9 -3	; 1
	40	[737]	CALL     	7 3 1
	41	[730]	FORLOOP  	3 -16	; to 26
	42	[739]	JMP      	3	; to 46
	43	[741]	SELF     	1 0 -6	; "changeDictionary"
	44	[741]	LOADK    	3 -3	; 1
	45	[741]	CALL     	1 3 1
	46	[743]	RETURN   	0 1

function <./frontend/ui/widget/dictquicklookup.lua:745,749> (7 instructions, 28 bytes at 0x7fd305c0b090)
1 param, 4 slots, 1 upvalue, 1 local, 1 constant, 0 functions
	1	[747]	GETUPVAL 	1 0	; UIManager
	2	[747]	SELF     	1 1 -1	; "close"
	3	[747]	MOVE     	3 0
	4	[747]	CALL     	1 3 1
	5	[748]	LOADBOOL 	1 1 0
	6	[748]	RETURN   	1 2
	7	[749]	RETURN   	0 1

function <./frontend/ui/widget/dictquicklookup.lua:751,775> (64 instructions, 256 bytes at 0x7fd305c0d240)
3 params, 9 slots, 3 upvalues, 4 locals, 22 constants, 0 functions
	1	[752]	GETTABLE 	3 2 -1	; "pos"
	2	[752]	SELF     	3 3 -2	; "notIntersectWith"
	3	[752]	GETTABLE 	5 0 -3	; "dict_frame"
	4	[752]	GETTABLE 	5 5 -4	; "dimen"
	5	[752]	CALL     	3 3 2
	6	[752]	TEST     	3 0 0
	7	[752]	JMP      	5	; to 13
	8	[753]	SELF     	3 0 -5	; "onClose"
	9	[753]	CALL     	3 2 1
	10	[754]	LOADBOOL 	3 1 0
	11	[754]	RETURN   	3 2
	12	[754]	JMP      	20	; to 33
	13	[755]	GETTABLE 	3 2 -1	; "pos"
	14	[755]	SELF     	3 3 -2	; "notIntersectWith"
	15	[755]	GETTABLE 	5 0 -6	; "dict_title"
	16	[755]	GETTABLE 	5 5 -4	; "dimen"
	17	[755]	CALL     	3 3 2
	18	[755]	TEST     	3 0 1
	19	[755]	JMP      	13	; to 33
	20	[755]	GETTABLE 	3 0 -7	; "is_wiki"
	21	[755]	TEST     	3 0 1
	22	[755]	JMP      	10	; to 33
	23	[756]	GETTABLE 	3 0 -8	; "ui"
	24	[756]	SELF     	3 3 -9	; "handleEvent"
	25	[756]	GETUPVAL 	5 0	; Event
	26	[756]	SELF     	5 5 -10	; "new"
	27	[756]	LOADK    	7 -11	; "UpdateDefaultDict"
	28	[756]	GETTABLE 	8 0 -12	; "dictionary"
	29	[756]	CALL     	5 4 0
	30	[756]	CALL     	3 0 1
	31	[757]	LOADBOOL 	3 1 0
	32	[757]	RETURN   	3 2
	33	[763]	GETUPVAL 	3 1	; BD
	34	[763]	GETTABLE 	3 3 -13	; "flipIfMirroredUILayout"
	35	[763]	GETTABLE 	4 2 -1	; "pos"
	36	[763]	GETTABLE 	4 4 -14	; "x"
	37	[763]	GETUPVAL 	5 2	; Screen
	38	[763]	SELF     	5 5 -15	; "getWidth"
	39	[763]	CALL     	5 2 2
	40	[763]	DIV      	5 5 -16	; - 2
	41	[763]	LT       	1 4 5
	42	[763]	JMP      	1	; to 44
	43	[763]	LOADBOOL 	4 0 1
	44	[763]	LOADBOOL 	4 1 0
	45	[763]	CALL     	3 2 2
	46	[763]	TEST     	3 0 0
	47	[763]	JMP      	12	; to 60
	48	[764]	GETTABLE 	3 0 -17	; "dict_index"
	49	[765]	SELF     	4 0 -18	; "changeToPrevDict"
	50	[765]	CALL     	4 2 1
	51	[766]	GETTABLE 	4 0 -17	; "dict_index"
	52	[766]	EQ       	1 4 3
	53	[766]	JMP      	8	; to 62
	54	[769]	GETTABLE 	4 0 -19	; "definition_widget"
	55	[769]	GETTABLE 	4 4 -20	; 1
	56	[769]	SELF     	4 4 -21	; "scrollToRatio"
	57	[769]	LOADK    	6 -20	; 1
	58	[769]	CALL     	4 3 1
	59	[770]	JMP      	2	; to 62
	60	[772]	SELF     	3 0 -22	; "changeToNextDict"
	61	[772]	CALL     	3 2 1
	62	[774]	LOADBOOL 	3 1 0
	63	[774]	RETURN   	3 2
	64	[775]	RETURN   	0 1

function <./frontend/ui/widget/dictquicklookup.lua:777,794> (36 instructions, 144 bytes at 0x7fd305c10960)
1 param, 9 slots, 1 upvalue, 7 locals, 10 constants, 1 function
	1	[778]	GETUPVAL 	1 0	; UIManager
	2	[778]	SELF     	1 1 -1	; "close"
	3	[778]	MOVE     	3 0
	4	[778]	CALL     	1 3 1
	5	[779]	GETTABLE 	1 0 -2	; "window_list"
	6	[779]	LEN      	1 1
	7	[779]	LOADK    	2 -3	; 1
	8	[779]	LOADK    	3 -4	; -1
	9	[779]	FORPREP  	1 9	; to 19
	10	[780]	GETTABLE 	5 0 -2	; "window_list"
	11	[780]	GETTABLE 	5 5 4
	12	[781]	EQ       	0 5 0
	13	[781]	JMP      	5	; to 19
	14	[782]	GETGLOBAL	6 -5	; table
	15	[782]	GETTABLE 	6 6 -6	; "remove"
	16	[782]	GETTABLE 	7 0 -2	; "window_list"
	17	[782]	MOVE     	8 4
	18	[782]	CALL     	6 3 1
	19	[779]	FORLOOP  	1 -10	; to 10
	20	[785]	GETTABLE 	1 0 -7	; "highlight"
	21	[785]	TEST     	1 0 0
	22	[785]	JMP      	11	; to 34
	23	[788]	GETTABLE 	1 0 -7	; "highlight"
	24	[788]	SELF     	1 1 -8	; "getClearId"
	25	[788]	CALL     	1 2 2
	26	[789]	GETUPVAL 	2 0	; UIManager
	27	[789]	SELF     	2 2 -9	; "scheduleIn"
	28	[789]	LOADK    	4 -10	; 0.5
	29	[791]	CLOSURE  	5 0	; 0x7fd305c08c00
	30	[791]	MOVE     	0 0
	31	[791]	MOVE     	0 1
	32	[789]	CALL     	2 4 1
	33	[791]	CLOSE    	1
	34	[793]	LOADBOOL 	1 1 0
	35	[793]	RETURN   	1 2
	36	[794]	RETURN   	0 1

function <./frontend/ui/widget/dictquicklookup.lua:789,791> (6 instructions, 24 bytes at 0x7fd305c08c00)
0 params, 3 slots, 2 upvalues, 0 locals, 2 constants, 0 functions
	1	[790]	GETUPVAL 	0 0	; self
	2	[790]	GETTABLE 	0 0 -1	; "highlight"
	3	[790]	SELF     	0 0 -2	; "clear"
	4	[790]	GETUPVAL 	2 1	; clear_id
	5	[790]	CALL     	0 3 1
	6	[791]	RETURN   	0 1

function <./frontend/ui/widget/dictquicklookup.lua:796,811> (39 instructions, 156 bytes at 0x7fd305c10180)
2 params, 12 slots, 1 upvalue, 8 locals, 11 constants, 1 function
	1	[797]	SELF     	2 0 -1	; "onClose"
	2	[797]	CALL     	2 2 1
	3	[798]	GETTABLE 	2 0 -2	; "window_list"
	4	[798]	LEN      	2 2
	5	[798]	LOADK    	3 -3	; 1
	6	[798]	LOADK    	4 -4	; -1
	7	[798]	FORPREP  	2 28	; to 36
	8	[799]	GETTABLE 	6 0 -2	; "window_list"
	9	[799]	GETTABLE 	6 6 5
	10	[801]	GETTABLE 	7 6 -5	; "highlight"
	11	[801]	TEST     	7 0 0
	12	[801]	JMP      	13	; to 26
	13	[801]	TEST     	1 0 1
	14	[801]	JMP      	11	; to 26
	15	[802]	GETTABLE 	7 6 -5	; "highlight"
	16	[802]	SELF     	7 7 -6	; "getClearId"
	17	[802]	CALL     	7 2 2
	18	[803]	GETUPVAL 	8 0	; UIManager
	19	[803]	SELF     	8 8 -7	; "scheduleIn"
	20	[803]	LOADK    	10 -8	; 0.5
	21	[805]	CLOSURE  	11 0	; 0x7fd305c10f20
	22	[805]	MOVE     	0 6
	23	[805]	MOVE     	0 7
	24	[803]	CALL     	8 4 1
	25	[805]	CLOSE    	7
	26	[807]	GETUPVAL 	7 0	; UIManager
	27	[807]	SELF     	7 7 -9	; "close"
	28	[807]	MOVE     	9 6
	29	[807]	CALL     	7 3 1
	30	[808]	GETGLOBAL	7 -10	; table
	31	[808]	GETTABLE 	7 7 -11	; "remove"
	32	[808]	GETTABLE 	8 0 -2	; "window_list"
	33	[808]	MOVE     	9 5
	34	[808]	CALL     	7 3 1
	35	[808]	CLOSE    	6
	36	[798]	FORLOOP  	2 -29	; to 8
	37	[810]	LOADBOOL 	2 1 0
	38	[810]	RETURN   	2 2
	39	[811]	RETURN   	0 1

function <./frontend/ui/widget/dictquicklookup.lua:803,805> (6 instructions, 24 bytes at 0x7fd305c10f20)
0 params, 3 slots, 2 upvalues, 0 locals, 2 constants, 0 functions
	1	[804]	GETUPVAL 	0 0	; window
	2	[804]	GETTABLE 	0 0 -1	; "highlight"
	3	[804]	SELF     	0 0 -2	; "clear"
	4	[804]	GETUPVAL 	2 1	; clear_id
	5	[804]	CALL     	0 3 1
	6	[805]	RETURN   	0 1

function <./frontend/ui/widget/dictquicklookup.lua:813,834> (42 instructions, 168 bytes at 0x7fd305c0f740)
3 params, 8 slots, 2 upvalues, 4 locals, 15 constants, 0 functions
	1	[814]	GETTABLE 	3 2 -1	; "pos"
	2	[814]	SELF     	3 3 -2	; "intersectWith"
	3	[814]	GETTABLE 	5 0 -3	; "definition_widget"
	4	[814]	GETTABLE 	5 5 -4	; "dimen"
	5	[814]	CALL     	3 3 2
	6	[814]	TEST     	3 0 0
	7	[814]	JMP      	28	; to 36
	8	[817]	GETUPVAL 	3 0	; BD
	9	[817]	GETTABLE 	3 3 -5	; "flipDirectionIfMirroredUILayout"
	10	[817]	GETTABLE 	4 2 -6	; "direction"
	11	[817]	CALL     	3 2 2
	12	[818]	EQ       	0 3 -7	; - "west"
	13	[818]	JMP      	3	; to 17
	14	[819]	SELF     	4 0 -8	; "changeToNextDict"
	15	[819]	CALL     	4 2 1
	16	[819]	JMP      	17	; to 34
	17	[820]	EQ       	0 3 -9	; - "east"
	18	[820]	JMP      	3	; to 22
	19	[821]	SELF     	4 0 -10	; "changeToPrevDict"
	20	[821]	CALL     	4 2 1
	21	[821]	JMP      	12	; to 34
	22	[823]	GETTABLE 	4 0 -11	; "refresh_callback"
	23	[823]	TEST     	4 0 0
	24	[823]	JMP      	2	; to 27
	25	[823]	GETTABLE 	4 0 -11	; "refresh_callback"
	26	[823]	CALL     	4 1 1
	27	[825]	GETUPVAL 	4 1	; UIManager
	28	[825]	SELF     	4 4 -12	; "setDirty"
	29	[825]	LOADNIL  	6 6
	30	[825]	LOADK    	7 -13	; "full"
	31	[825]	CALL     	4 4 1
	32	[828]	LOADBOOL 	4 0 0
	33	[828]	RETURN   	4 2
	34	[830]	LOADBOOL 	4 1 0
	35	[830]	RETURN   	4 2
	36	[833]	GETTABLE 	3 0 -14	; "movable"
	37	[833]	SELF     	3 3 -15	; "onMovableSwipe"
	38	[833]	MOVE     	5 1
	39	[833]	MOVE     	6 2
	40	[833]	TAILCALL 	3 4 0
	41	[833]	RETURN   	3 0
	42	[834]	RETURN   	0 1

function <./frontend/ui/widget/dictquicklookup.lua:836,840> (7 instructions, 28 bytes at 0x7fd305c116e0)
3 params, 7 slots, 0 upvalues, 3 locals, 2 constants, 0 functions
	1	[839]	GETTABLE 	3 0 -1	; "movable"
	2	[839]	SELF     	3 3 -2	; "onMovableHold"
	3	[839]	MOVE     	5 1
	4	[839]	MOVE     	6 2
	5	[839]	TAILCALL 	3 4 0
	6	[839]	RETURN   	3 0
	7	[840]	RETURN   	0 1

function <./frontend/ui/widget/dictquicklookup.lua:842,849> (11 instructions, 44 bytes at 0x7fd305c11b80)
3 params, 7 slots, 0 upvalues, 3 locals, 4 constants, 0 functions
	1	[846]	GETTABLE 	3 0 -1	; "movable"
	2	[846]	GETTABLE 	3 3 -2	; "_touch_pre_pan_was_inside"
	3	[846]	TEST     	3 0 0
	4	[846]	JMP      	6	; to 11
	5	[847]	GETTABLE 	3 0 -1	; "movable"
	6	[847]	SELF     	3 3 -3	; "onMovableHoldPan"
	7	[847]	GETGLOBAL	5 -4	; arg
	8	[847]	MOVE     	6 2
	9	[847]	TAILCALL 	3 4 0
	10	[847]	RETURN   	3 0
	11	[849]	RETURN   	0 1

function <./frontend/ui/widget/dictquicklookup.lua:851,855> (7 instructions, 28 bytes at 0x7fd305c11d70)
3 params, 7 slots, 0 upvalues, 3 locals, 2 constants, 0 functions
	1	[854]	GETTABLE 	3 0 -1	; "movable"
	2	[854]	SELF     	3 3 -2	; "onMovableHoldRelease"
	3	[854]	MOVE     	5 1
	4	[854]	MOVE     	6 2
	5	[854]	TAILCALL 	3 4 0
	6	[854]	RETURN   	3 0
	7	[855]	RETURN   	0 1

function <./frontend/ui/widget/dictquicklookup.lua:861,870> (17 instructions, 68 bytes at 0x7fd305c12350)
3 params, 7 slots, 0 upvalues, 3 locals, 8 constants, 0 functions
	1	[864]	GETTABLE 	3 2 -1	; "pos"
	2	[864]	SELF     	3 3 -2	; "intersectWith"
	3	[864]	GETTABLE 	5 0 -3	; "definition_widget"
	4	[864]	GETTABLE 	5 5 -4	; "dimen"
	5	[864]	CALL     	3 3 2
	6	[864]	TEST     	3 0 1
	7	[864]	JMP      	7	; to 15
	8	[865]	GETTABLE 	3 0 -5	; "movable"
	9	[865]	SELF     	3 3 -6	; "onMovableTouch"
	10	[865]	MOVE     	5 1
	11	[865]	MOVE     	6 2
	12	[865]	TAILCALL 	3 4 0
	13	[865]	RETURN   	3 0
	14	[865]	JMP      	2	; to 17
	15	[868]	GETTABLE 	3 0 -5	; "movable"
	16	[868]	SETTABLE 	3 -7 -8	; "_touch_pre_pan_was_inside" false
	17	[870]	RETURN   	0 1

function <./frontend/ui/widget/dictquicklookup.lua:872,877> (15 instructions, 60 bytes at 0x7fd305c12640)
3 params, 7 slots, 0 upvalues, 3 locals, 4 constants, 0 functions
	1	[874]	GETTABLE 	3 0 -1	; "movable"
	2	[874]	GETTABLE 	3 3 -2	; "_touch_pre_pan_was_inside"
	3	[874]	TEST     	3 0 1
	4	[874]	JMP      	4	; to 9
	5	[874]	GETTABLE 	3 0 -1	; "movable"
	6	[874]	GETTABLE 	3 3 -3	; "_moving"
	7	[874]	TEST     	3 0 0
	8	[874]	JMP      	6	; to 15
	9	[875]	GETTABLE 	3 0 -1	; "movable"
	10	[875]	SELF     	3 3 -4	; "onMovablePan"
	11	[875]	MOVE     	5 1
	12	[875]	MOVE     	6 2
	13	[875]	TAILCALL 	3 4 0
	14	[875]	RETURN   	3 0
	15	[877]	RETURN   	0 1

function <./frontend/ui/widget/dictquicklookup.lua:879,882> (7 instructions, 28 bytes at 0x7fd305c12830)
3 params, 7 slots, 0 upvalues, 3 locals, 2 constants, 0 functions
	1	[881]	GETTABLE 	3 0 -1	; "movable"
	2	[881]	SELF     	3 3 -2	; "onMovablePanRelease"
	3	[881]	MOVE     	5 1
	4	[881]	MOVE     	6 2
	5	[881]	TAILCALL 	3 4 0
	6	[881]	RETURN   	3 0
	7	[882]	RETURN   	0 1

function <./frontend/ui/widget/dictquicklookup.lua:884,912> (47 instructions, 188 bytes at 0x7fd305c129b0)
2 params, 11 slots, 3 upvalues, 2 locals, 18 constants, 2 functions
	1	[885]	SELF     	2 0 -1	; "onClose"
	2	[885]	CALL     	2 2 1
	3	[886]	GETUPVAL 	2 0	; InputDialog
	4	[886]	SELF     	2 2 -3	; "new"
	5	[886]	NEWTABLE 	4 0 5
	6	[887]	GETUPVAL 	5 1	; _
	7	[887]	LOADK    	6 -5	; "Input lookup word"
	8	[887]	CALL     	5 2 2
	9	[887]	SETTABLE 	4 -4 5	; "title" -
	10	[888]	SETTABLE 	4 -6 1	; "input" -
	11	[889]	TESTSET  	5 1 1
	12	[889]	JMP      	1	; to 14
	13	[889]	LOADK    	5 -8	; ""
	14	[889]	SETTABLE 	4 -7 5	; "input_hint" -
	15	[890]	SETTABLE 	4 -9 -10	; "input_type" "text"
	16	[891]	NEWTABLE 	5 1 0
	17	[891]	NEWTABLE 	6 2 0
	18	[892]	NEWTABLE 	7 0 2
	19	[894]	GETUPVAL 	8 1	; _
	20	[894]	LOADK    	9 -12	; "Cancel"
	21	[894]	CALL     	8 2 2
	22	[894]	SETTABLE 	7 -10 8	; "text" -
	23	[897]	CLOSURE  	8 0	; 0x7fd305c13120
	24	[897]	MOVE     	0 0
	25	[897]	SETTABLE 	7 -13 8	; "callback" -
	26	[898]	NEWTABLE 	8 0 3
	27	[900]	GETUPVAL 	9 1	; _
	28	[900]	LOADK    	10 -14	; "Lookup"
	29	[900]	CALL     	9 2 2
	30	[900]	SETTABLE 	8 -10 9	; "text" -
	31	[901]	SETTABLE 	8 -15 -16	; "is_enter_default" true
	32	[905]	CLOSURE  	9 1	; 0x7fd305c134b0
	33	[905]	MOVE     	0 0
	34	[905]	SETTABLE 	8 -13 9	; "callback" -
	35	[907]	SETLIST  	6 2 1	; 1
	36	[908]	SETLIST  	5 1 1	; 1
	37	[908]	SETTABLE 	4 -11 5	; "buttons" -
	38	[886]	CALL     	2 3 2
	39	[909]	SETTABLE 	0 -2 2	; "input_dialog" -
	40	[910]	GETUPVAL 	2 2	; UIManager
	41	[910]	SELF     	2 2 -17	; "show"
	42	[910]	GETTABLE 	4 0 -2	; "input_dialog"
	43	[910]	CALL     	2 3 1
	44	[911]	GETTABLE 	2 0 -2	; "input_dialog"
	45	[911]	SELF     	2 2 -18	; "onShowKeyboard"
	46	[911]	CALL     	2 2 1
	47	[912]	RETURN   	0 1

function <./frontend/ui/widget/dictquicklookup.lua:895,897> (4 instructions, 16 bytes at 0x7fd305c13120)
0 params, 2 slots, 1 upvalue, 0 locals, 1 constant, 0 functions
	1	[896]	GETUPVAL 	0 0	; self
	2	[896]	SELF     	0 0 -1	; "closeInputDialog"
	3	[896]	CALL     	0 2 1
	4	[897]	RETURN   	0 1

function <./frontend/ui/widget/dictquicklookup.lua:902,905> (7 instructions, 28 bytes at 0x7fd305c134b0)
0 params, 2 slots, 1 upvalue, 0 locals, 2 constants, 0 functions
	1	[903]	GETUPVAL 	0 0	; self
	2	[903]	SELF     	0 0 -1	; "closeInputDialog"
	3	[903]	CALL     	0 2 1
	4	[904]	GETUPVAL 	0 0	; self
	5	[904]	SELF     	0 0 -2	; "inputLookup"
	6	[904]	CALL     	0 2 1
	7	[905]	RETURN   	0 1

function <./frontend/ui/widget/dictquicklookup.lua:914,926> (25 instructions, 100 bytes at 0x7fd305c130a0)
1 param, 9 slots, 1 upvalue, 3 locals, 10 constants, 0 functions
	1	[915]	GETTABLE 	1 0 -1	; "input_dialog"
	2	[915]	SELF     	1 1 -2	; "getInputText"
	3	[915]	CALL     	1 2 2
	4	[916]	TEST     	1 0 0
	5	[916]	JMP      	19	; to 25
	6	[916]	EQ       	1 1 -3	; - ""
	7	[916]	JMP      	17	; to 25
	8	[917]	LOADNIL  	2 2
	9	[918]	GETTABLE 	3 0 -4	; "is_wiki"
	10	[918]	TEST     	3 0 0
	11	[918]	JMP      	4	; to 16
	12	[919]	LOADK    	2 -5	; "LookupWikipedia"
	13	[920]	SELF     	3 0 -6	; "resyncWikiLanguages"
	14	[920]	CALL     	3 2 1
	15	[920]	JMP      	1	; to 17
	16	[922]	LOADK    	2 -7	; "LookupWord"
	17	[924]	GETTABLE 	3 0 -8	; "ui"
	18	[924]	SELF     	3 3 -9	; "handleEvent"
	19	[924]	GETUPVAL 	5 0	; Event
	20	[924]	SELF     	5 5 -10	; "new"
	21	[924]	MOVE     	7 2
	22	[924]	MOVE     	8 1
	23	[924]	CALL     	5 4 0
	24	[924]	CALL     	3 0 1
	25	[926]	RETURN   	0 1

function <./frontend/ui/widget/dictquicklookup.lua:928,930> (5 instructions, 20 bytes at 0x7fd305c13c60)
1 param, 4 slots, 1 upvalue, 1 local, 2 constants, 0 functions
	1	[929]	GETUPVAL 	1 0	; UIManager
	2	[929]	SELF     	1 1 -1	; "close"
	3	[929]	GETTABLE 	3 0 -2	; "input_dialog"
	4	[929]	CALL     	1 3 1
	5	[930]	RETURN   	0 1

function <./frontend/ui/widget/dictquicklookup.lua:932,949> (25 instructions, 100 bytes at 0x7fd305c13d20)
2 params, 8 slots, 0 upvalues, 8 locals, 7 constants, 0 functions
	1	[937]	GETTABLE 	2 0 -1	; "wiki_languages_copy"
	2	[937]	TEST     	2 0 1
	3	[937]	JMP      	1	; to 5
	4	[938]	RETURN   	0 1
	5	[940]	TEST     	1 0 0
	6	[940]	JMP      	10	; to 17
	7	[942]	GETGLOBAL	2 -2	; table
	8	[942]	GETTABLE 	2 2 -3	; "remove"
	9	[942]	GETTABLE 	3 0 -1	; "wiki_languages_copy"
	10	[942]	LOADK    	4 -4	; 1
	11	[942]	CALL     	2 3 2
	12	[943]	GETGLOBAL	3 -2	; table
	13	[943]	GETTABLE 	3 3 -5	; "insert"
	14	[943]	GETTABLE 	4 0 -1	; "wiki_languages_copy"
	15	[943]	MOVE     	5 2
	16	[943]	CALL     	3 3 1
	17	[946]	GETGLOBAL	2 -6	; ipairs
	18	[946]	GETTABLE 	3 0 -1	; "wiki_languages_copy"
	19	[946]	CALL     	2 2 4
	20	[946]	JMP      	2	; to 23
	21	[947]	GETTABLE 	7 0 -7	; "wiki_languages"
	22	[947]	SETTABLE 	7 5 6
	23	[946]	TFORLOOP 	2 2
	24	[947]	JMP      	-4	; to 21
	25	[949]	RETURN   	0 1

function <./frontend/ui/widget/dictquicklookup.lua:951,965> (24 instructions, 96 bytes at 0x7fd305c14200)
2 params, 11 slots, 1 upvalue, 3 locals, 8 constants, 0 functions
	1	[953]	TEST     	1 0 0
	2	[953]	JMP      	2	; to 5
	3	[956]	GETTABLE 	2 0 -1	; "lookupword"
	4	[956]	JMP      	1	; to 6
	5	[959]	GETTABLE 	2 0 -2	; "word"
	6	[961]	SELF     	3 0 -3	; "resyncWikiLanguages"
	7	[961]	CALL     	3 2 1
	8	[964]	GETTABLE 	3 0 -4	; "ui"
	9	[964]	SELF     	3 3 -5	; "handleEvent"
	10	[964]	GETUPVAL 	5 0	; Event
	11	[964]	SELF     	5 5 -6	; "new"
	12	[964]	LOADK    	7 -7	; "LookupWikipedia"
	13	[964]	MOVE     	8 2
	14	[964]	GETTABLE 	9 0 -8	; "word_box"
	15	[964]	TEST     	9 0 0
	16	[964]	JMP      	3	; to 20
	17	[964]	GETTABLE 	9 0 -8	; "word_box"
	18	[964]	TEST     	9 0 1
	19	[964]	JMP      	1	; to 21
	20	[964]	LOADBOOL 	9 0 0
	21	[964]	MOVE     	10 1
	22	[964]	CALL     	5 6 0
	23	[964]	CALL     	3 0 1
	24	[965]	RETURN   	0 1
