
main <./frontend/device/android/dictionaries.lua:0,0> (89 instructions, 356 bytes at 0x7fda9dc068f0)
0+ params, 19 slots, 0 upvalues, 3 locals, 35 constants, 0 functions
	1	[1]	GETGLOBAL	0 -1	; require
	2	[1]	LOADK    	1 -2	; "datastorage"
	3	[1]	CALL     	0 2 2
	4	[1]	SELF     	0 0 -3	; "getDataDir"
	5	[1]	CALL     	0 2 2
	6	[1]	LOADK    	1 -4	; "/dictionaries.lua"
	7	[1]	CONCAT   	0 0 1
	8	[2]	GETGLOBAL	1 -5	; pcall
	9	[2]	GETGLOBAL	2 -6	; dofile
	10	[2]	MOVE     	3 0
	11	[2]	CALL     	1 3 3
	12	[4]	TEST     	1 0 0
	13	[4]	JMP      	2	; to 16
	14	[5]	RETURN   	2 2
	15	[5]	JMP      	73	; to 89
	16	[7]	NEWTABLE 	3 10 0
	17	[7]	NEWTABLE 	4 5 0
	18	[9]	LOADK    	5 -7	; "Aard2"
	19	[9]	LOADK    	6 -7	; "Aard2"
	20	[9]	LOADBOOL 	7 0 0
	21	[9]	LOADK    	8 -8	; "itkach.aard2"
	22	[9]	LOADK    	9 -9	; "aard2"
	23	[9]	SETLIST  	4 5 1	; 1
	24	[9]	NEWTABLE 	5 5 0
	25	[10]	LOADK    	6 -10	; "Alpus"
	26	[10]	LOADK    	7 -10	; "Alpus"
	27	[10]	LOADBOOL 	8 0 0
	28	[10]	LOADK    	9 -11	; "com.ngcomputing.fora.android"
	29	[10]	LOADK    	10 -12	; "search"
	30	[10]	SETLIST  	5 5 1	; 1
	31	[10]	NEWTABLE 	6 5 0
	32	[11]	LOADK    	7 -13	; "ColorDict"
	33	[11]	LOADK    	8 -13	; "ColorDict"
	34	[11]	LOADBOOL 	9 0 0
	35	[11]	LOADK    	10 -14	; "com.socialnmobile.colordict"
	36	[11]	LOADK    	11 -15	; "colordict"
	37	[11]	SETLIST  	6 5 1	; 1
	38	[11]	NEWTABLE 	7 5 0
	39	[12]	LOADK    	8 -16	; "Eudic"
	40	[12]	LOADK    	9 -16	; "Eudic"
	41	[12]	LOADBOOL 	10 0 0
	42	[12]	LOADK    	11 -17	; "com.eusoft.eudic"
	43	[12]	LOADK    	12 -18	; "send"
	44	[12]	SETLIST  	7 5 1	; 1
	45	[12]	NEWTABLE 	8 5 0
	46	[13]	LOADK    	9 -19	; "Fora"
	47	[13]	LOADK    	10 -20	; "Fora Dict"
	48	[13]	LOADBOOL 	11 0 0
	49	[13]	LOADK    	12 -21	; "com.ngc.fora"
	50	[13]	LOADK    	13 -12	; "search"
	51	[13]	SETLIST  	8 5 1	; 1
	52	[13]	NEWTABLE 	9 5 0
	53	[14]	LOADK    	10 -22	; "GoldenFree"
	54	[14]	LOADK    	11 -23	; "GoldenDict Free"
	55	[14]	LOADBOOL 	12 0 0
	56	[14]	LOADK    	13 -24	; "mobi.goldendict.android.free"
	57	[14]	LOADK    	14 -18	; "send"
	58	[14]	SETLIST  	9 5 1	; 1
	59	[14]	NEWTABLE 	10 5 0
	60	[15]	LOADK    	11 -25	; "GoldenPro"
	61	[15]	LOADK    	12 -26	; "GoldenDict Pro"
	62	[15]	LOADBOOL 	13 0 0
	63	[15]	LOADK    	14 -27	; "mobi.goldendict.android"
	64	[15]	LOADK    	15 -18	; "send"
	65	[15]	SETLIST  	10 5 1	; 1
	66	[15]	NEWTABLE 	11 5 0
	67	[16]	LOADK    	12 -28	; "Kiwix"
	68	[16]	LOADK    	13 -28	; "Kiwix"
	69	[16]	LOADBOOL 	14 0 0
	70	[16]	LOADK    	15 -29	; "org.kiwix.kiwixmobile"
	71	[16]	LOADK    	16 -30	; "text"
	72	[16]	SETLIST  	11 5 1	; 1
	73	[16]	NEWTABLE 	12 5 0
	74	[17]	LOADK    	13 -31	; "Mdict"
	75	[17]	LOADK    	14 -31	; "Mdict"
	76	[17]	LOADBOOL 	15 0 0
	77	[17]	LOADK    	16 -32	; "cn.mdict"
	78	[17]	LOADK    	17 -18	; "send"
	79	[17]	SETLIST  	12 5 1	; 1
	80	[17]	NEWTABLE 	13 5 0
	81	[18]	LOADK    	14 -33	; "QuickDic"
	82	[18]	LOADK    	15 -33	; "QuickDic"
	83	[18]	LOADBOOL 	16 0 0
	84	[18]	LOADK    	17 -34	; "de.reimardoeffinger.quickdic"
	85	[18]	LOADK    	18 -35	; "quickdic"
	86	[18]	SETLIST  	13 5 1	; 1
	87	[19]	SETLIST  	3 10 1	; 1
	88	[19]	RETURN   	3 2
	89	[20]	RETURN   	0 1
