
main <./frontend/document/djvudocument.lua:0,0> (72 instructions, 288 bytes at 0x7fc7c6c068d0)
0+ params, 7 slots, 0 upvalues, 5 locals, 41 constants, 23 functions
	1	[1]	GETGLOBAL	0 -1	; require
	2	[1]	LOADK    	1 -2	; "ffi/blitbuffer"
	3	[1]	CALL     	0 2 2
	4	[2]	GETGLOBAL	1 -1	; require
	5	[2]	LOADK    	2 -3	; "document/document"
	6	[2]	CALL     	1 2 2
	7	[3]	GETGLOBAL	2 -1	; require
	8	[3]	LOADK    	3 -4	; "ffi/drawcontext"
	9	[3]	CALL     	2 2 2
	10	[5]	SELF     	3 1 -5	; "new"
	11	[5]	NEWTABLE 	5 0 8
	12	[6]	SETTABLE 	5 -6 -7	; "_document" false
	13	[8]	SETTABLE 	5 -8 -9	; "is_djvu" true
	14	[9]	SETTABLE 	5 -10 -11	; "djvulibre_cache_size" nil
	15	[10]	GETTABLE 	6 2 -5	; "new"
	16	[10]	CALL     	6 1 2
	17	[10]	SETTABLE 	5 -12 6	; "dc_null" -
	18	[11]	SETTABLE 	5 -13 -11	; "koptinterface" nil
	19	[12]	GETTABLE 	6 0 -15	; "TYPE_BBRGB24"
	20	[12]	SETTABLE 	5 -14 6	; "color_bb_type" -
	21	[13]	SETTABLE 	5 -16 -17	; "provider" "djvulibre"
	22	[14]	SETTABLE 	5 -18 -19	; "provider_name" "DjVu Libre"
	23	[5]	CALL     	3 3 2
	24	[25]	CLOSURE  	4 0	; 0x7fc7c6c06f80
	25	[45]	CLOSURE  	5 1	; 0x7fc7c6c07390
	26	[45]	MOVE     	0 4
	27	[27]	SETTABLE 	3 -20 5	; "init" -
	28	[52]	CLOSURE  	5 2	; 0x7fc7c6c07710
	29	[52]	MOVE     	0 1
	30	[47]	SETTABLE 	3 -21 5	; "updateColorRendering" -
	31	[69]	CLOSURE  	5 3	; 0x7fc7c6c07dc0
	32	[54]	SETTABLE 	3 -22 5	; "getProps" -
	33	[73]	CLOSURE  	5 4	; 0x7fc7c6c086a0
	34	[71]	SETTABLE 	3 -23 5	; "getPageTextBoxes" -
	35	[77]	CLOSURE  	5 5	; 0x7fc7c6c06d90
	36	[75]	SETTABLE 	3 -24 5	; "getWordFromPosition" -
	37	[81]	CLOSURE  	5 6	; 0x7fc7c6c080d0
	38	[79]	SETTABLE 	3 -25 5	; "getTextFromPositions" -
	39	[85]	CLOSURE  	5 7	; 0x7fc7c6c08f70
	40	[83]	SETTABLE 	3 -26 5	; "getPageBoxesFromPositions" -
	41	[89]	CLOSURE  	5 8	; 0x7fc7c6c09160
	42	[87]	SETTABLE 	3 -27 5	; "nativeToPageRectTransform" -
	43	[93]	CLOSURE  	5 9	; 0x7fc7c6c09710
	44	[91]	SETTABLE 	3 -28 5	; "getOCRWord" -
	45	[97]	CLOSURE  	5 10	; 0x7fc7c6c09a30
	46	[95]	SETTABLE 	3 -29 5	; "getOCRText" -
	47	[101]	CLOSURE  	5 11	; 0x7fc7c6c09b60
	48	[99]	SETTABLE 	3 -30 5	; "getPageBlock" -
	49	[109]	CLOSURE  	5 12	; 0x7fc7c6c09ee0
	50	[103]	SETTABLE 	3 -31 5	; "getUsedBBox" -
	51	[113]	CLOSURE  	5 13	; 0x7fc7c6c0a7c0
	52	[111]	SETTABLE 	3 -32 5	; "clipPagePNGFile" -
	53	[117]	CLOSURE  	5 14	; 0x7fc7c6c0a9f0
	54	[115]	SETTABLE 	3 -33 5	; "clipPagePNGString" -
	55	[121]	CLOSURE  	5 15	; 0x7fc7c6c0ade0
	56	[119]	SETTABLE 	3 -34 5	; "getPageBBox" -
	57	[125]	CLOSURE  	5 16	; 0x7fc7c6c070d0
	58	[123]	SETTABLE 	3 -35 5	; "getPageDimensions" -
	59	[129]	CLOSURE  	5 17	; 0x7fc7c6c09540
	60	[127]	SETTABLE 	3 -36 5	; "getCoverPageImage" -
	61	[133]	CLOSURE  	5 18	; 0x7fc7c6c0b820
	62	[131]	SETTABLE 	3 -37 5	; "findText" -
	63	[137]	CLOSURE  	5 19	; 0x7fc7c6c0bc10
	64	[135]	SETTABLE 	3 -38 5	; "renderPage" -
	65	[141]	CLOSURE  	5 20	; 0x7fc7c6c0c170
	66	[139]	SETTABLE 	3 -39 5	; "hintPage" -
	67	[145]	CLOSURE  	5 21	; 0x7fc7c6c0c630
	68	[143]	SETTABLE 	3 -40 5	; "drawPage" -
	69	[150]	CLOSURE  	5 22	; 0x7fc7c6c0cde0
	70	[147]	SETTABLE 	3 -41 5	; "register" -
	71	[152]	RETURN   	3 2
	72	[152]	RETURN   	0 1

function <./frontend/document/djvudocument.lua:18,25> (23 instructions, 92 bytes at 0x7fc7c6c06f80)
1 param, 5 slots, 0 upvalues, 3 locals, 7 constants, 0 functions
	1	[19]	GETGLOBAL	1 -1	; io
	2	[19]	GETTABLE 	1 1 -2	; "open"
	3	[19]	MOVE     	2 0
	4	[19]	LOADK    	3 -3	; "r"
	5	[19]	CALL     	1 3 2
	6	[20]	TEST     	1 0 1
	7	[20]	JMP      	2	; to 10
	8	[20]	LOADBOOL 	2 0 0
	9	[20]	RETURN   	2 2
	10	[21]	SELF     	2 1 -4	; "read"
	11	[21]	LOADK    	4 -5	; 8
	12	[21]	CALL     	2 3 2
	13	[22]	SELF     	3 1 -6	; "close"
	14	[22]	CALL     	3 2 1
	15	[23]	TEST     	2 0 0
	16	[23]	JMP      	2	; to 19
	17	[23]	EQ       	1 2 -7	; - "AT&TFORM"
	18	[23]	JMP      	2	; to 21
	19	[23]	LOADBOOL 	3 0 0
	20	[23]	RETURN   	3 2
	21	[24]	LOADBOOL 	3 1 0
	22	[24]	RETURN   	3 2
	23	[25]	RETURN   	0 1

function <./frontend/document/djvudocument.lua:27,45> (43 instructions, 172 bytes at 0x7fc7c6c07390)
1 param, 8 slots, 1 upvalue, 3 locals, 20 constants, 0 functions
	1	[28]	SELF     	1 0 -1	; "updateColorRendering"
	2	[28]	CALL     	1 2 1
	3	[29]	GETGLOBAL	1 -2	; require
	4	[29]	LOADK    	2 -3	; "libs/libkoreader-djvu"
	5	[29]	CALL     	1 2 2
	6	[30]	GETGLOBAL	2 -2	; require
	7	[30]	LOADK    	3 -5	; "document/koptinterface"
	8	[30]	CALL     	2 2 2
	9	[30]	SETTABLE 	0 -4 2	; "koptinterface" -
	10	[31]	GETTABLE 	2 0 -4	; "koptinterface"
	11	[31]	SELF     	2 2 -6	; "setDefaultConfigurable"
	12	[31]	GETTABLE 	4 0 -7	; "configurable"
	13	[31]	CALL     	2 3 1
	14	[32]	GETUPVAL 	2 0	; validDjvuFile
	15	[32]	GETTABLE 	3 0 -8	; "file"
	16	[32]	CALL     	2 2 2
	17	[32]	TEST     	2 0 1
	18	[32]	JMP      	3	; to 22
	19	[33]	GETGLOBAL	2 -9	; error
	20	[33]	LOADK    	3 -10	; "Not a valid DjVu file"
	21	[33]	CALL     	2 2 1
	22	[36]	LOADNIL  	2 2
	23	[37]	GETGLOBAL	3 -12	; pcall
	24	[37]	GETTABLE 	4 1 -13	; "openDocument"
	25	[37]	GETTABLE 	5 0 -8	; "file"
	26	[37]	GETTABLE 	6 0 -14	; "render_color"
	27	[37]	GETTABLE 	7 0 -15	; "djvulibre_cache_size"
	28	[37]	CALL     	3 5 3
	29	[37]	SETTABLE 	0 -11 4	; "_document" -
	30	[37]	MOVE     	2 3
	31	[38]	TEST     	2 0 1
	32	[38]	JMP      	3	; to 36
	33	[39]	GETGLOBAL	3 -9	; error
	34	[39]	GETTABLE 	4 0 -11	; "_document"
	35	[39]	CALL     	3 2 1
	36	[41]	SETTABLE 	0 -16 -17	; "is_open" true
	37	[42]	GETTABLE 	3 0 -18	; "info"
	38	[42]	SETTABLE 	3 -19 -17	; "has_pages" true
	39	[43]	GETTABLE 	3 0 -18	; "info"
	40	[43]	SETTABLE 	3 -7 -17	; "configurable" true
	41	[44]	SELF     	3 0 -20	; "_readMetadata"
	42	[44]	CALL     	3 2 1
	43	[45]	RETURN   	0 1

function <./frontend/document/djvudocument.lua:47,52> (12 instructions, 48 bytes at 0x7fc7c6c07710)
1 param, 4 slots, 1 upvalue, 1 local, 4 constants, 0 functions
	1	[48]	GETUPVAL 	1 0	; Document
	2	[48]	GETTABLE 	1 1 -1	; "updateColorRendering"
	3	[48]	MOVE     	2 0
	4	[48]	CALL     	1 2 1
	5	[49]	GETTABLE 	1 0 -2	; "_document"
	6	[49]	TEST     	1 0 0
	7	[49]	JMP      	4	; to 12
	8	[50]	GETTABLE 	1 0 -2	; "_document"
	9	[50]	SELF     	1 1 -3	; "setColorRendering"
	10	[50]	GETTABLE 	3 0 -4	; "render_color"
	11	[50]	CALL     	1 3 1
	12	[52]	RETURN   	0 1

function <./frontend/document/djvudocument.lua:54,69> (47 instructions, 188 bytes at 0x7fc7c6c07dc0)
1 param, 8 slots, 0 upvalues, 5 locals, 20 constants, 0 functions
	1	[55]	GETTABLE 	1 0 -1	; "_document"
	2	[55]	SELF     	1 1 -2	; "getMetadata"
	3	[55]	CALL     	1 2 2
	4	[56]	GETTABLE 	2 0 -3	; "file"
	5	[56]	SELF     	2 2 -4	; "find"
	6	[56]	LOADK    	4 -5	; ".*/(.*)"
	7	[56]	CALL     	2 3 4
	8	[57]	TEST     	4 0 1
	9	[57]	JMP      	1	; to 11
	10	[57]	GETTABLE 	4 0 -3	; "file"
	11	[61]	GETTABLE 	5 1 -6	; "title"
	12	[61]	TEST     	5 0 1
	13	[61]	JMP      	6	; to 20
	14	[61]	GETTABLE 	5 1 -7	; "Title"
	15	[61]	TEST     	5 0 1
	16	[61]	JMP      	3	; to 20
	17	[61]	SELF     	5 4 -8	; "match"
	18	[61]	LOADK    	7 -9	; "(.*)%."
	19	[61]	CALL     	5 3 2
	20	[61]	SETTABLE 	1 -6 5	; "title" -
	21	[62]	GETTABLE 	5 1 -11	; "author"
	22	[62]	TEST     	5 0 1
	23	[62]	JMP      	1	; to 25
	24	[62]	GETTABLE 	5 1 -12	; "Author"
	25	[62]	SETTABLE 	1 -10 5	; "authors" -
	26	[63]	GETTABLE 	5 1 -13	; "series"
	27	[63]	TEST     	5 0 1
	28	[63]	JMP      	1	; to 30
	29	[63]	GETTABLE 	5 1 -14	; "Series"
	30	[63]	SETTABLE 	1 -13 5	; "series" -
	31	[64]	GETTABLE 	5 1 -15	; "language"
	32	[64]	TEST     	5 0 1
	33	[64]	JMP      	1	; to 35
	34	[64]	GETTABLE 	5 1 -16	; "Language"
	35	[64]	SETTABLE 	1 -15 5	; "language" -
	36	[65]	GETTABLE 	5 1 -17	; "keywords"
	37	[65]	TEST     	5 0 1
	38	[65]	JMP      	1	; to 40
	39	[65]	GETTABLE 	5 1 -18	; "Keywords"
	40	[65]	SETTABLE 	1 -17 5	; "keywords" -
	41	[66]	GETTABLE 	5 1 -19	; "description"
	42	[66]	TEST     	5 0 1
	43	[66]	JMP      	1	; to 45
	44	[66]	GETTABLE 	5 1 -20	; "Description"
	45	[66]	SETTABLE 	1 -19 5	; "description" -
	46	[68]	RETURN   	1 2
	47	[69]	RETURN   	0 1

function <./frontend/document/djvudocument.lua:71,73> (6 instructions, 24 bytes at 0x7fc7c6c086a0)
2 params, 5 slots, 0 upvalues, 2 locals, 2 constants, 0 functions
	1	[72]	GETTABLE 	2 0 -1	; "_document"
	2	[72]	SELF     	2 2 -2	; "getPageText"
	3	[72]	MOVE     	4 1
	4	[72]	TAILCALL 	2 3 0
	5	[72]	RETURN   	2 0
	6	[73]	RETURN   	0 1

function <./frontend/document/djvudocument.lua:75,77> (7 instructions, 28 bytes at 0x7fc7c6c06d90)
2 params, 6 slots, 0 upvalues, 2 locals, 2 constants, 0 functions
	1	[76]	GETTABLE 	2 0 -1	; "koptinterface"
	2	[76]	SELF     	2 2 -2	; "getWordFromPosition"
	3	[76]	MOVE     	4 0
	4	[76]	MOVE     	5 1
	5	[76]	TAILCALL 	2 4 0
	6	[76]	RETURN   	2 0
	7	[77]	RETURN   	0 1

function <./frontend/document/djvudocument.lua:79,81> (8 instructions, 32 bytes at 0x7fc7c6c080d0)
3 params, 8 slots, 0 upvalues, 3 locals, 2 constants, 0 functions
	1	[80]	GETTABLE 	3 0 -1	; "koptinterface"
	2	[80]	SELF     	3 3 -2	; "getTextFromPositions"
	3	[80]	MOVE     	5 0
	4	[80]	MOVE     	6 1
	5	[80]	MOVE     	7 2
	6	[80]	TAILCALL 	3 5 0
	7	[80]	RETURN   	3 0
	8	[81]	RETURN   	0 1

function <./frontend/document/djvudocument.lua:83,85> (9 instructions, 36 bytes at 0x7fc7c6c08f70)
4 params, 10 slots, 0 upvalues, 4 locals, 2 constants, 0 functions
	1	[84]	GETTABLE 	4 0 -1	; "koptinterface"
	2	[84]	SELF     	4 4 -2	; "getPageBoxesFromPositions"
	3	[84]	MOVE     	6 0
	4	[84]	MOVE     	7 1
	5	[84]	MOVE     	8 2
	6	[84]	MOVE     	9 3
	7	[84]	TAILCALL 	4 6 0
	8	[84]	RETURN   	4 0
	9	[85]	RETURN   	0 1

function <./frontend/document/djvudocument.lua:87,89> (8 instructions, 32 bytes at 0x7fc7c6c09160)
3 params, 8 slots, 0 upvalues, 3 locals, 2 constants, 0 functions
	1	[88]	GETTABLE 	3 0 -1	; "koptinterface"
	2	[88]	SELF     	3 3 -2	; "nativeToPageRectTransform"
	3	[88]	MOVE     	5 0
	4	[88]	MOVE     	6 1
	5	[88]	MOVE     	7 2
	6	[88]	TAILCALL 	3 5 0
	7	[88]	RETURN   	3 0
	8	[89]	RETURN   	0 1

function <./frontend/document/djvudocument.lua:91,93> (8 instructions, 32 bytes at 0x7fc7c6c09710)
3 params, 8 slots, 0 upvalues, 3 locals, 2 constants, 0 functions
	1	[92]	GETTABLE 	3 0 -1	; "koptinterface"
	2	[92]	SELF     	3 3 -2	; "getOCRWord"
	3	[92]	MOVE     	5 0
	4	[92]	MOVE     	6 1
	5	[92]	MOVE     	7 2
	6	[92]	TAILCALL 	3 5 0
	7	[92]	RETURN   	3 0
	8	[93]	RETURN   	0 1

function <./frontend/document/djvudocument.lua:95,97> (8 instructions, 32 bytes at 0x7fc7c6c09a30)
3 params, 8 slots, 0 upvalues, 3 locals, 2 constants, 0 functions
	1	[96]	GETTABLE 	3 0 -1	; "koptinterface"
	2	[96]	SELF     	3 3 -2	; "getOCRText"
	3	[96]	MOVE     	5 0
	4	[96]	MOVE     	6 1
	5	[96]	MOVE     	7 2
	6	[96]	TAILCALL 	3 5 0
	7	[96]	RETURN   	3 0
	8	[97]	RETURN   	0 1

function <./frontend/document/djvudocument.lua:99,101> (9 instructions, 36 bytes at 0x7fc7c6c09b60)
4 params, 10 slots, 0 upvalues, 4 locals, 2 constants, 0 functions
	1	[100]	GETTABLE 	4 0 -1	; "koptinterface"
	2	[100]	SELF     	4 4 -2	; "getPageBlock"
	3	[100]	MOVE     	6 0
	4	[100]	MOVE     	7 1
	5	[100]	MOVE     	8 2
	6	[100]	MOVE     	9 3
	7	[100]	TAILCALL 	4 6 0
	8	[100]	RETURN   	4 0
	9	[101]	RETURN   	0 1

function <./frontend/document/djvudocument.lua:103,109> (14 instructions, 56 bytes at 0x7fc7c6c09ee0)
2 params, 8 slots, 0 upvalues, 4 locals, 8 constants, 0 functions
	1	[105]	NEWTABLE 	2 0 0
	2	[106]	SELF     	3 0 -1	; "getNativePageDimensions"
	3	[106]	MOVE     	5 1
	4	[106]	CALL     	3 3 2
	5	[107]	LOADK    	4 -6	; 0
	6	[107]	LOADK    	5 -6	; 0
	7	[107]	GETTABLE 	6 3 -7	; "w"
	8	[107]	GETTABLE 	7 3 -8	; "h"
	9	[107]	SETTABLE 	2 -5 7	; "y1" -
	10	[107]	SETTABLE 	2 -4 6	; "x1" -
	11	[107]	SETTABLE 	2 -3 5	; "y0" -
	12	[107]	SETTABLE 	2 -2 4	; "x0" -
	13	[108]	RETURN   	2 2
	14	[109]	RETURN   	0 1

function <./frontend/document/djvudocument.lua:111,113> (11 instructions, 44 bytes at 0x7fc7c6c0a7c0)
6 params, 14 slots, 0 upvalues, 6 locals, 2 constants, 0 functions
	1	[112]	GETTABLE 	6 0 -1	; "koptinterface"
	2	[112]	SELF     	6 6 -2	; "clipPagePNGFile"
	3	[112]	MOVE     	8 0
	4	[112]	MOVE     	9 1
	5	[112]	MOVE     	10 2
	6	[112]	MOVE     	11 3
	7	[112]	MOVE     	12 4
	8	[112]	MOVE     	13 5
	9	[112]	TAILCALL 	6 8 0
	10	[112]	RETURN   	6 0
	11	[113]	RETURN   	0 1

function <./frontend/document/djvudocument.lua:115,117> (10 instructions, 40 bytes at 0x7fc7c6c0a9f0)
5 params, 12 slots, 0 upvalues, 5 locals, 2 constants, 0 functions
	1	[116]	GETTABLE 	5 0 -1	; "koptinterface"
	2	[116]	SELF     	5 5 -2	; "clipPagePNGString"
	3	[116]	MOVE     	7 0
	4	[116]	MOVE     	8 1
	5	[116]	MOVE     	9 2
	6	[116]	MOVE     	10 3
	7	[116]	MOVE     	11 4
	8	[116]	TAILCALL 	5 7 0
	9	[116]	RETURN   	5 0
	10	[117]	RETURN   	0 1

function <./frontend/document/djvudocument.lua:119,121> (7 instructions, 28 bytes at 0x7fc7c6c0ade0)
2 params, 6 slots, 0 upvalues, 2 locals, 2 constants, 0 functions
	1	[120]	GETTABLE 	2 0 -1	; "koptinterface"
	2	[120]	SELF     	2 2 -2	; "getPageBBox"
	3	[120]	MOVE     	4 0
	4	[120]	MOVE     	5 1
	5	[120]	TAILCALL 	2 4 0
	6	[120]	RETURN   	2 0
	7	[121]	RETURN   	0 1

function <./frontend/document/djvudocument.lua:123,125> (9 instructions, 36 bytes at 0x7fc7c6c070d0)
4 params, 10 slots, 0 upvalues, 4 locals, 2 constants, 0 functions
	1	[124]	GETTABLE 	4 0 -1	; "koptinterface"
	2	[124]	SELF     	4 4 -2	; "getPageDimensions"
	3	[124]	MOVE     	6 0
	4	[124]	MOVE     	7 1
	5	[124]	MOVE     	8 2
	6	[124]	MOVE     	9 3
	7	[124]	TAILCALL 	4 6 0
	8	[124]	RETURN   	4 0
	9	[125]	RETURN   	0 1

function <./frontend/document/djvudocument.lua:127,129> (6 instructions, 24 bytes at 0x7fc7c6c09540)
1 param, 4 slots, 0 upvalues, 1 local, 2 constants, 0 functions
	1	[128]	GETTABLE 	1 0 -1	; "koptinterface"
	2	[128]	SELF     	1 1 -2	; "getCoverPageImage"
	3	[128]	MOVE     	3 0
	4	[128]	TAILCALL 	1 3 0
	5	[128]	RETURN   	1 0
	6	[129]	RETURN   	0 1

function <./frontend/document/djvudocument.lua:131,133> (11 instructions, 44 bytes at 0x7fc7c6c0b820)
6 params, 14 slots, 0 upvalues, 6 locals, 2 constants, 0 functions
	1	[132]	GETTABLE 	6 0 -1	; "koptinterface"
	2	[132]	SELF     	6 6 -2	; "findText"
	3	[132]	MOVE     	8 0
	4	[132]	MOVE     	9 1
	5	[132]	MOVE     	10 2
	6	[132]	MOVE     	11 3
	7	[132]	MOVE     	12 4
	8	[132]	MOVE     	13 5
	9	[132]	TAILCALL 	6 8 0
	10	[132]	RETURN   	6 0
	11	[133]	RETURN   	0 1

function <./frontend/document/djvudocument.lua:135,137> (12 instructions, 48 bytes at 0x7fc7c6c0bc10)
7 params, 16 slots, 0 upvalues, 7 locals, 2 constants, 0 functions
	1	[136]	GETTABLE 	7 0 -1	; "koptinterface"
	2	[136]	SELF     	7 7 -2	; "renderPage"
	3	[136]	MOVE     	9 0
	4	[136]	MOVE     	10 1
	5	[136]	MOVE     	11 2
	6	[136]	MOVE     	12 3
	7	[136]	MOVE     	13 4
	8	[136]	MOVE     	14 5
	9	[136]	MOVE     	15 6
	10	[136]	TAILCALL 	7 9 0
	11	[136]	RETURN   	7 0
	12	[137]	RETURN   	0 1

function <./frontend/document/djvudocument.lua:139,141> (11 instructions, 44 bytes at 0x7fc7c6c0c170)
6 params, 14 slots, 0 upvalues, 6 locals, 2 constants, 0 functions
	1	[140]	GETTABLE 	6 0 -1	; "koptinterface"
	2	[140]	SELF     	6 6 -2	; "hintPage"
	3	[140]	MOVE     	8 0
	4	[140]	MOVE     	9 1
	5	[140]	MOVE     	10 2
	6	[140]	MOVE     	11 3
	7	[140]	MOVE     	12 4
	8	[140]	MOVE     	13 5
	9	[140]	TAILCALL 	6 8 0
	10	[140]	RETURN   	6 0
	11	[141]	RETURN   	0 1

function <./frontend/document/djvudocument.lua:143,145> (15 instructions, 60 bytes at 0x7fc7c6c0c630)
10 params, 22 slots, 0 upvalues, 10 locals, 2 constants, 0 functions
	1	[144]	GETTABLE 	10 0 -1	; "koptinterface"
	2	[144]	SELF     	10 10 -2	; "drawPage"
	3	[144]	MOVE     	12 0
	4	[144]	MOVE     	13 1
	5	[144]	MOVE     	14 2
	6	[144]	MOVE     	15 3
	7	[144]	MOVE     	16 4
	8	[144]	MOVE     	17 5
	9	[144]	MOVE     	18 6
	10	[144]	MOVE     	19 7
	11	[144]	MOVE     	20 8
	12	[144]	MOVE     	21 9
	13	[144]	TAILCALL 	10 12 0
	14	[144]	RETURN   	10 0
	15	[145]	RETURN   	0 1

function <./frontend/document/djvudocument.lua:147,150> (13 instructions, 52 bytes at 0x7fc7c6c0cde0)
2 params, 8 slots, 0 upvalues, 2 locals, 5 constants, 0 functions
	1	[148]	SELF     	2 1 -1	; "addProvider"
	2	[148]	LOADK    	4 -2	; "djv"
	3	[148]	LOADK    	5 -3	; "image/vnd.djvu"
	4	[148]	MOVE     	6 0
	5	[148]	LOADK    	7 -4	; 100
	6	[148]	CALL     	2 6 1
	7	[149]	SELF     	2 1 -1	; "addProvider"
	8	[149]	LOADK    	4 -5	; "djvu"
	9	[149]	LOADK    	5 -3	; "image/vnd.djvu"
	10	[149]	MOVE     	6 0
	11	[149]	LOADK    	7 -4	; 100
	12	[149]	CALL     	2 6 1
	13	[150]	RETURN   	0 1
