-- BYTECODE -- document_registry_spec.lua:4-8
0001    GGET     0   0      ; "require"
0002    KSTR     1   1      ; "commonrequire"
0003    CALL     0   1   2
0004    GGET     0   0      ; "require"
0005    KSTR     1   2      ; "docsettings"
0006    CALL     0   2   2
0007    USETV    0   0      ; DocSettings
0008    GGET     0   0      ; "require"
0009    KSTR     1   3      ; "document/documentregistry"
0010    CALL     0   2   2
0011    USETV    1   0      ; DocumentRegistry
0012    RET0     0   1

-- BYTECODE -- document_registry_spec.lua:10-15
0001    GGET     0   0      ; "assert"
0002    TGETS    0   0   1  ; "is_equal"
0003    KSTR     1   2      ; "crengine"
0004    UGET     2   0      ; DocumentRegistry
0005    MOV      3   2
0006    TGETS    2   2   3  ; "getProvider"
0007    KSTR     4   4      ; "bla.epub"
0008    CALL     2   2   3
0009    TGETS    2   2   5  ; "provider"
0010    CALL     0   1   3
0011    GGET     0   0      ; "assert"
0012    TGETS    0   0   1  ; "is_equal"
0013    KSTR     1   6      ; "mupdf"
0014    UGET     2   0      ; DocumentRegistry
0015    MOV      3   2
0016    TGETS    2   2   3  ; "getProvider"
0017    KSTR     4   7      ; "bla.pdf"
0018    CALL     2   2   3
0019    TGETS    2   2   5  ; "provider"
0020    CALL     0   1   3
0021    RET0     0   1

-- BYTECODE -- document_registry_spec.lua:17-23
0001    UGET     0   0      ; DocumentRegistry
0002    MOV      1   0
0003    TGETS    0   0   0  ; "getProviders"
0004    KSTR     2   1      ; "bla.epub"
0005    CALL     0   2   3
0006    GGET     1   2      ; "assert"
0007    TGETS    1   1   3  ; "is_equal"
0008    KSTR     2   4      ; "crengine"
0009    TGETB    3   0   1
0010    TGETS    3   3   5  ; "provider"
0011    TGETS    3   3   5  ; "provider"
0012    CALL     1   1   3
0013    GGET     1   2      ; "assert"
0014    TGETS    1   1   3  ; "is_equal"
0015    KSTR     2   6      ; "mupdf"
0016    TGETB    3   0   2
0017    TGETS    3   3   5  ; "provider"
0018    TGETS    3   3   5  ; "provider"
0019    CALL     1   1   3
0020    RET0     0   1

-- BYTECODE -- document_registry_spec.lua:25-37
0001    KSTR     0   0      ; "../../foo.epub"
0002    UGET     1   0      ; DocumentRegistry
0003    MOV      2   1
0004    TGETS    1   1   1  ; "getProvider"
0005    KSTR     3   2      ; "bla.pdf"
0006    CALL     1   2   3
0007    UGET     2   0      ; DocumentRegistry
0008    MOV      3   2
0009    TGETS    2   2   3  ; "setProvider"
0010    MOV      4   0
0011    MOV      5   1
0012    KPRI     6   1
0013    CALL     2   1   5
0014    UGET     2   0      ; DocumentRegistry
0015    MOV      3   2
0016    TGETS    2   2   1  ; "getProvider"
0017    MOV      4   0
0018    CALL     2   2   3
0019    GGET     3   4      ; "assert"
0020    TGETS    3   3   5  ; "is_equal"
0021    KSTR     4   6      ; "mupdf"
0022    TGETS    5   2   7  ; "provider"
0023    CALL     3   1   3
0024    UGET     3   1      ; DocSettings
0025    MOV      4   3
0026    TGETS    3   3   8  ; "open"
0027    MOV      5   0
0028    CALL     3   2   3
0029    MOV      5   3
0030    TGETS    4   3   9  ; "purge"
0031    CALL     4   1   2
0032    MOV      5   3
0033    TGETS    4   3  10  ; "flush"
0034    CALL     4   1   2
0035    RET0     0   1

-- BYTECODE -- document_registry_spec.lua:38-48
0001    KSTR     0   0      ; "../../foo.fb2"
0002    UGET     1   0      ; DocumentRegistry
0003    MOV      2   1
0004    TGETS    1   1   1  ; "getProvider"
0005    KSTR     3   2      ; "bla.pdf"
0006    CALL     1   2   3
0007    UGET     2   0      ; DocumentRegistry
0008    MOV      3   2
0009    TGETS    2   2   3  ; "setProvider"
0010    MOV      4   0
0011    MOV      5   1
0012    KPRI     6   2
0013    CALL     2   1   5
0014    UGET     2   0      ; DocumentRegistry
0015    MOV      3   2
0016    TGETS    2   2   1  ; "getProvider"
0017    MOV      4   0
0018    CALL     2   2   3
0019    GGET     3   4      ; "assert"
0020    TGETS    3   3   5  ; "is_equal"
0021    KSTR     4   6      ; "mupdf"
0022    TGETS    5   2   7  ; "provider"
0023    CALL     3   1   3
0024    GGET     3   8      ; "G_reader_settings"
0025    MOV      4   3
0026    TGETS    3   3   9  ; "delSetting"
0027    KSTR     5   7      ; "provider"
0028    CALL     3   1   3
0029    RET0     0   1

-- BYTECODE -- document_registry_spec.lua:50-62
0001    KSTR     0   0      ; "../../foofoo.epub"
0002    UGET     1   0      ; DocSettings
0003    MOV      2   1
0004    TGETS    1   1   1  ; "open"
0005    MOV      3   0
0006    CALL     1   2   3
0007    MOV      3   1
0008    TGETS    2   1   2  ; "saveSetting"
0009    KSTR     4   3      ; "provider"
0010    KSTR     5   4      ; "mupdf"
0011    CALL     2   1   4
0012    MOV      3   1
0013    TGETS    2   1   5  ; "flush"
0014    CALL     2   1   2
0015    UGET     2   1      ; DocumentRegistry
0016    MOV      3   2
0017    TGETS    2   2   6  ; "getProvider"
0018    MOV      4   0
0019    CALL     2   2   3
0020    GGET     3   7      ; "assert"
0021    TGETS    3   3   8  ; "is_equal"
0022    KSTR     4   4      ; "mupdf"
0023    TGETS    5   2   3  ; "provider"
0024    CALL     3   1   3
0025    MOV      4   1
0026    TGETS    3   1   9  ; "purge"
0027    CALL     3   1   2
0028    MOV      4   1
0029    TGETS    3   1   5  ; "flush"
0030    CALL     3   1   2
0031    RET0     0   1

-- BYTECODE -- document_registry_spec.lua:63-74
0001    KSTR     0   0      ; "../../foofoo.fb2"
0002    TNEW     1   0
0003    KSTR     2   2      ; "mupdf"
0004    TSETS    2   1   1  ; "fb2"
0005    GGET     2   3      ; "G_reader_settings"
0006    MOV      3   2
0007    TGETS    2   2   4  ; "saveSetting"
0008    KSTR     4   5      ; "provider"
0009    MOV      5   1
0010    CALL     2   1   4
0011    UGET     2   0      ; DocumentRegistry
0012    MOV      3   2
0013    TGETS    2   2   6  ; "getProvider"
0014    MOV      4   0
0015    CALL     2   2   3
0016    GGET     3   7      ; "assert"
0017    TGETS    3   3   8  ; "is_equal"
0018    KSTR     4   2      ; "mupdf"
0019    TGETS    5   2   5  ; "provider"
0020    CALL     3   1   3
0021    GGET     3   3      ; "G_reader_settings"
0022    MOV      4   3
0023    TGETS    3   3   9  ; "delSetting"
0024    KSTR     5   5      ; "provider"
0025    CALL     3   1   3
0026    RET0     0   1

-- BYTECODE -- document_registry_spec.lua:1-75
0001    KNIL     0   1
0002    GGET     2   0      ; "setup"
0003    FNEW     3   1      ; document_registry_spec.lua:4
0004    CALL     2   1   2
0005    GGET     2   2      ; "it"
0006    KSTR     3   3      ; "should get preferred rendering engine"
0007    FNEW     4   4      ; document_registry_spec.lua:10
0008    CALL     2   1   3
0009    GGET     2   2      ; "it"
0010    KSTR     3   5      ; "should return all supported rendering en"~
0011    FNEW     4   6      ; document_registry_spec.lua:17
0012    CALL     2   1   3
0013    GGET     2   2      ; "it"
0014    KSTR     3   7      ; "should set per-document setting for rend"~
0015    FNEW     4   8      ; document_registry_spec.lua:25
0016    CALL     2   1   3
0017    GGET     2   2      ; "it"
0018    KSTR     3   9      ; "should set global setting for rendering "~
0019    FNEW     4  10      ; document_registry_spec.lua:38
0020    CALL     2   1   3
0021    GGET     2   2      ; "it"
0022    KSTR     3  11      ; "should return per-document setting for r"~
0023    FNEW     4  12      ; document_registry_spec.lua:50
0024    CALL     2   1   3
0025    GGET     2   2      ; "it"
0026    KSTR     3  13      ; "should return global setting for renderi"~
0027    FNEW     4  14      ; document_registry_spec.lua:63
0028    CALL     2   1   3
0029    UCLO     0 => 0030
0030 => RET0     0   1

-- BYTECODE -- document_registry_spec.lua:0-76
0001    GGET     0   0      ; "describe"
0002    KSTR     1   1      ; "document registry module"
0003    FNEW     2   2      ; document_registry_spec.lua:1
0004    CALL     0   1   3
0005    RET0     0   1

