
main <./frontend/document/documentregistry.lua:0,0> (64 instructions, 256 bytes at 0x7fc0424068f0)
0+ params, 7 slots, 0 upvalues, 4 locals, 20 constants, 8 functions
	1	[5]	GETGLOBAL	0 -1	; require
	2	[5]	LOADK    	1 -2	; "logger"
	3	[5]	CALL     	0 2 2
	4	[6]	GETGLOBAL	1 -1	; require
	5	[6]	LOADK    	2 -3	; "libs/libkoreader-lfs"
	6	[6]	CALL     	1 2 2
	7	[7]	GETGLOBAL	2 -1	; require
	8	[7]	LOADK    	3 -4	; "util"
	9	[7]	CALL     	2 2 2
	10	[9]	NEWTABLE 	3 0 3
	11	[10]	NEWTABLE 	4 0 0
	12	[10]	SETTABLE 	3 -5 4	; "registry" -
	13	[11]	NEWTABLE 	4 0 0
	14	[11]	SETTABLE 	3 -6 4	; "providers" -
	15	[12]	NEWTABLE 	4 0 0
	16	[12]	SETTABLE 	3 -7 4	; "filetype_provider" -
	17	[24]	CLOSURE  	4 0	; 0x7fc042406c40
	18	[15]	SETTABLE 	3 -8 4	; "addProvider" -
	19	[51]	CLOSURE  	4 1	; 0x7fc042406d80
	20	[51]	MOVE     	0 1
	21	[51]	MOVE     	0 2
	22	[26]	SETTABLE 	3 -9 4	; "getRandomFile" -
	23	[71]	CLOSURE  	4 2	; 0x7fc0424079a0
	24	[71]	MOVE     	0 2
	25	[56]	SETTABLE 	3 -10 4	; "hasProvider" -
	26	[114]	CLOSURE  	4 3	; 0x7fc042408300
	27	[114]	MOVE     	0 2
	28	[76]	SETTABLE 	3 -11 4	; "getProvider" -
	29	[149]	CLOSURE  	4 4	; 0x7fc0424067b0
	30	[119]	SETTABLE 	3 -12 4	; "getProviders" -
	31	[168]	CLOSURE  	4 5	; 0x7fc042408670
	32	[168]	MOVE     	0 2
	33	[154]	SETTABLE 	3 -13 4	; "setProvider" -
	34	[196]	CLOSURE  	4 6	; 0x7fc0424072e0
	35	[196]	MOVE     	0 0
	36	[170]	SETTABLE 	3 -14 4	; "openDocument" -
	37	[210]	CLOSURE  	4 7	; 0x7fc0424093e0
	38	[198]	SETTABLE 	3 -15 4	; "closeDocument" -
	39	[214]	GETGLOBAL	4 -1	; require
	40	[214]	LOADK    	5 -16	; "document/credocument"
	41	[214]	CALL     	4 2 2
	42	[214]	SELF     	4 4 -17	; "register"
	43	[214]	MOVE     	6 3
	44	[214]	CALL     	4 3 1
	45	[215]	GETGLOBAL	4 -1	; require
	46	[215]	LOADK    	5 -18	; "document/pdfdocument"
	47	[215]	CALL     	4 2 2
	48	[215]	SELF     	4 4 -17	; "register"
	49	[215]	MOVE     	6 3
	50	[215]	CALL     	4 3 1
	51	[216]	GETGLOBAL	4 -1	; require
	52	[216]	LOADK    	5 -19	; "document/djvudocument"
	53	[216]	CALL     	4 2 2
	54	[216]	SELF     	4 4 -17	; "register"
	55	[216]	MOVE     	6 3
	56	[216]	CALL     	4 3 1
	57	[217]	GETGLOBAL	4 -1	; require
	58	[217]	LOADK    	5 -20	; "document/picdocument"
	59	[217]	CALL     	4 2 2
	60	[217]	SELF     	4 4 -17	; "register"
	61	[217]	MOVE     	6 3
	62	[217]	CALL     	4 3 1
	63	[219]	RETURN   	3 2
	64	[219]	RETURN   	0 1

function <./frontend/document/documentregistry.lua:15,24> (20 instructions, 80 bytes at 0x7fc042406c40)
5 params, 9 slots, 0 upvalues, 5 locals, 12 constants, 0 functions
	1	[16]	GETGLOBAL	5 -1	; string
	2	[16]	GETTABLE 	5 5 -2	; "lower"
	3	[16]	MOVE     	6 1
	4	[16]	CALL     	5 2 2
	5	[16]	MOVE     	1 5
	6	[17]	GETGLOBAL	5 -3	; table
	7	[17]	GETTABLE 	5 5 -4	; "insert"
	8	[17]	GETTABLE 	6 0 -5	; "providers"
	9	[17]	NEWTABLE 	7 0 4
	10	[18]	SETTABLE 	7 -6 1	; "extension" -
	11	[19]	SETTABLE 	7 -7 2	; "mimetype" -
	12	[20]	SETTABLE 	7 -8 3	; "provider" -
	13	[21]	TESTSET  	8 4 1
	14	[21]	JMP      	1	; to 16
	15	[21]	LOADK    	8 -10	; 100
	16	[21]	SETTABLE 	7 -9 8	; "weight" -
	17	[17]	CALL     	5 3 1
	18	[23]	GETTABLE 	5 0 -11	; "filetype_provider"
	19	[23]	SETTABLE 	5 1 -12	; - true
	20	[24]	RETURN   	0 1

function <./frontend/document/documentregistry.lua:26,51> (89 instructions, 356 bytes at 0x7fc042406d80)
4 params, 18 slots, 2 upvalues, 14 locals, 22 constants, 0 functions
	1	[27]	GETGLOBAL	4 -1	; require
	2	[27]	LOADK    	5 -2	; "docsettings"
	3	[27]	CALL     	4 2 2
	4	[28]	GETGLOBAL	5 -3	; string
	5	[28]	GETTABLE 	5 5 -4	; "sub"
	6	[28]	MOVE     	6 1
	7	[28]	GETGLOBAL	7 -3	; string
	8	[28]	GETTABLE 	7 7 -5	; "len"
	9	[28]	MOVE     	8 1
	10	[28]	CALL     	7 2 0
	11	[28]	CALL     	5 0 2
	12	[28]	EQ       	1 5 -6	; - "/"
	13	[28]	JMP      	3	; to 17
	14	[29]	MOVE     	5 1
	15	[29]	LOADK    	6 -6	; "/"
	16	[29]	CONCAT   	1 5 6
	17	[31]	NEWTABLE 	5 0 0
	18	[32]	LOADK    	6 -7	; 0
	19	[33]	GETGLOBAL	7 -8	; pcall
	20	[33]	GETUPVAL 	8 0	; lfs
	21	[33]	GETTABLE 	8 8 -9	; "dir"
	22	[33]	MOVE     	9 1
	23	[33]	CALL     	7 3 4
	24	[34]	TEST     	7 0 0
	25	[34]	JMP      	47	; to 73
	26	[35]	MOVE     	10 8
	27	[35]	MOVE     	11 9
	28	[35]	LOADNIL  	12 12
	29	[35]	JMP      	36	; to 66
	30	[36]	GETUPVAL 	14 0	; lfs
	31	[36]	GETTABLE 	14 14 -10	; "attributes"
	32	[36]	MOVE     	15 1
	33	[36]	MOVE     	16 13
	34	[36]	CONCAT   	15 15 16
	35	[36]	LOADK    	16 -11	; "mode"
	36	[36]	CALL     	14 3 2
	37	[36]	EQ       	0 14 -12	; - "file"
	38	[36]	JMP      	27	; to 66
	39	[36]	SELF     	14 0 -13	; "hasProvider"
	40	[36]	MOVE     	16 1
	41	[36]	MOVE     	17 13
	42	[36]	CONCAT   	16 16 17
	43	[36]	CALL     	14 3 2
	44	[37]	TEST     	14 0 0
	45	[37]	JMP      	20	; to 66
	46	[37]	EQ       	1 2 -14	; - nil
	47	[37]	JMP      	7	; to 55
	48	[37]	SELF     	14 4 -15	; "hasSidecarFile"
	49	[37]	MOVE     	16 1
	50	[37]	MOVE     	17 13
	51	[37]	CONCAT   	16 16 17
	52	[37]	CALL     	14 3 2
	53	[37]	EQ       	0 14 2
	54	[37]	JMP      	11	; to 66
	55	[38]	EQ       	1 3 -14	; - nil
	56	[38]	JMP      	7	; to 64
	57	[38]	GETUPVAL 	14 1	; util
	58	[38]	GETTABLE 	14 14 -16	; "getFileNameSuffix"
	59	[38]	MOVE     	15 13
	60	[38]	CALL     	14 2 2
	61	[38]	GETTABLE 	14 3 14
	62	[38]	TEST     	14 0 0
	63	[38]	JMP      	2	; to 66
	64	[39]	ADD      	6 6 -17	; - 1
	65	[40]	SETTABLE 	5 6 13
	66	[35]	TFORLOOP 	10 1
	67	[41]	JMP      	-38	; to 30
	68	[43]	EQ       	0 6 -7	; - 0
	69	[43]	JMP      	5	; to 75
	70	[44]	LOADNIL  	10 10
	71	[44]	RETURN   	10 2
	72	[45]	JMP      	2	; to 75
	73	[47]	LOADNIL  	10 10
	74	[47]	RETURN   	10 2
	75	[49]	GETGLOBAL	10 -18	; math
	76	[49]	GETTABLE 	10 10 -19	; "randomseed"
	77	[49]	GETGLOBAL	11 -20	; os
	78	[49]	GETTABLE 	11 11 -21	; "time"
	79	[49]	CALL     	11 1 0
	80	[49]	CALL     	10 0 1
	81	[50]	MOVE     	10 1
	82	[50]	GETGLOBAL	11 -18	; math
	83	[50]	GETTABLE 	11 11 -22	; "random"
	84	[50]	MOVE     	12 6
	85	[50]	CALL     	11 2 2
	86	[50]	GETTABLE 	11 5 11
	87	[50]	CONCAT   	10 10 11
	88	[50]	RETURN   	10 2
	89	[51]	RETURN   	0 1

function <./frontend/document/documentregistry.lua:56,71> (44 instructions, 176 bytes at 0x7fc0424079a0)
2 params, 8 slots, 1 upvalue, 6 locals, 11 constants, 0 functions
	1	[57]	GETGLOBAL	2 -1	; string
	2	[57]	GETTABLE 	2 2 -2	; "lower"
	3	[57]	GETUPVAL 	3 0	; util
	4	[57]	GETTABLE 	3 3 -3	; "getFileNameSuffix"
	5	[57]	MOVE     	4 1
	6	[57]	CALL     	3 2 0
	7	[57]	CALL     	2 0 2
	8	[59]	GETGLOBAL	3 -4	; G_reader_settings
	9	[59]	SELF     	3 3 -5	; "readSetting"
	10	[59]	LOADK    	5 -6	; "provider"
	11	[59]	CALL     	3 3 2
	12	[59]	TEST     	3 0 1
	13	[59]	JMP      	1	; to 15
	14	[59]	NEWTABLE 	3 0 0
	15	[60]	GETTABLE 	4 0 -7	; "filetype_provider"
	16	[60]	GETTABLE 	4 4 2
	17	[60]	TEST     	4 0 1
	18	[60]	JMP      	3	; to 22
	19	[60]	GETTABLE 	4 3 2
	20	[60]	TEST     	4 0 0
	21	[60]	JMP      	2	; to 24
	22	[61]	LOADBOOL 	4 1 0
	23	[61]	RETURN   	4 2
	24	[63]	GETGLOBAL	4 -8	; require
	25	[63]	LOADK    	5 -9	; "docsettings"
	26	[63]	CALL     	4 2 2
	27	[64]	SELF     	5 4 -10	; "hasSidecarFile"
	28	[64]	MOVE     	7 1
	29	[64]	CALL     	5 3 2
	30	[64]	TEST     	5 0 0
	31	[64]	JMP      	10	; to 42
	32	[65]	SELF     	5 4 -11	; "open"
	33	[65]	MOVE     	7 1
	34	[65]	CALL     	5 3 2
	35	[65]	SELF     	5 5 -5	; "readSetting"
	36	[65]	LOADK    	7 -6	; "provider"
	37	[65]	CALL     	5 3 2
	38	[66]	TEST     	5 0 0
	39	[66]	JMP      	2	; to 42
	40	[67]	LOADBOOL 	6 1 0
	41	[67]	RETURN   	6 2
	42	[70]	LOADBOOL 	5 0 0
	43	[70]	RETURN   	5 2
	44	[71]	RETURN   	0 1

function <./frontend/document/documentregistry.lua:76,114> (75 instructions, 300 bytes at 0x7fc042408300)
2 params, 13 slots, 1 upvalue, 22 locals, 14 constants, 0 functions
	1	[77]	SELF     	2 0 -1	; "getProviders"
	2	[77]	MOVE     	4 1
	3	[77]	CALL     	2 3 2
	4	[79]	TEST     	2 0 0
	5	[79]	JMP      	58	; to 64
	6	[81]	GETGLOBAL	3 -2	; require
	7	[81]	LOADK    	4 -3	; "docsettings"
	8	[81]	CALL     	3 2 2
	9	[82]	SELF     	4 3 -4	; "hasSidecarFile"
	10	[82]	MOVE     	6 1
	11	[82]	CALL     	4 3 2
	12	[82]	TEST     	4 0 0
	13	[82]	JMP      	20	; to 34
	14	[83]	SELF     	4 3 -5	; "open"
	15	[83]	MOVE     	6 1
	16	[83]	CALL     	4 3 2
	17	[83]	SELF     	4 4 -6	; "readSetting"
	18	[83]	LOADK    	6 -7	; "provider"
	19	[83]	CALL     	4 3 2
	20	[84]	TEST     	4 0 0
	21	[84]	JMP      	12	; to 34
	22	[85]	GETGLOBAL	5 -8	; ipairs
	23	[85]	MOVE     	6 2
	24	[85]	CALL     	5 2 4
	25	[85]	JMP      	6	; to 32
	26	[86]	GETTABLE 	10 9 -7	; "provider"
	27	[86]	GETTABLE 	10 10 -7	; "provider"
	28	[86]	EQ       	0 10 4
	29	[86]	JMP      	2	; to 32
	30	[87]	GETTABLE 	10 9 -7	; "provider"
	31	[87]	RETURN   	10 2
	32	[85]	TFORLOOP 	5 2
	33	[88]	JMP      	-8	; to 26
	34	[94]	GETUPVAL 	4 0	; util
	35	[94]	GETTABLE 	4 4 -9	; "getFileNameSuffix"
	36	[94]	MOVE     	5 1
	37	[94]	CALL     	4 2 2
	38	[95]	GETGLOBAL	5 -10	; G_reader_settings
	39	[95]	SELF     	5 5 -6	; "readSetting"
	40	[95]	LOADK    	7 -7	; "provider"
	41	[95]	CALL     	5 3 2
	42	[97]	TEST     	5 0 0
	43	[97]	JMP      	16	; to 60
	44	[97]	GETTABLE 	6 5 4
	45	[97]	TEST     	6 0 0
	46	[97]	JMP      	13	; to 60
	47	[98]	GETGLOBAL	6 -8	; ipairs
	48	[98]	MOVE     	7 2
	49	[98]	CALL     	6 2 4
	50	[98]	JMP      	7	; to 58
	51	[99]	GETTABLE 	11 10 -7	; "provider"
	52	[99]	GETTABLE 	11 11 -7	; "provider"
	53	[99]	GETTABLE 	12 5 4
	54	[99]	EQ       	0 11 12
	55	[99]	JMP      	2	; to 58
	56	[100]	GETTABLE 	11 10 -7	; "provider"
	57	[100]	RETURN   	11 2
	58	[98]	TFORLOOP 	6 2
	59	[101]	JMP      	-9	; to 51
	60	[106]	GETTABLE 	6 2 -11	; 1
	61	[106]	GETTABLE 	6 6 -7	; "provider"
	62	[106]	RETURN   	6 2
	63	[106]	JMP      	11	; to 75
	64	[108]	GETGLOBAL	3 -8	; ipairs
	65	[108]	GETTABLE 	4 0 -12	; "providers"
	66	[108]	CALL     	3 2 4
	67	[108]	JMP      	5	; to 73
	68	[109]	GETTABLE 	8 7 -13	; "extension"
	69	[109]	EQ       	0 8 -14	; - "txt"
	70	[109]	JMP      	2	; to 73
	71	[110]	GETTABLE 	8 7 -7	; "provider"
	72	[110]	RETURN   	8 2
	73	[108]	TFORLOOP 	3 2
	74	[111]	JMP      	-7	; to 68
	75	[114]	RETURN   	0 1

function <./frontend/document/documentregistry.lua:119,149> (77 instructions, 308 bytes at 0x7fc0424067b0)
2 params, 18 slots, 0 upvalues, 15 locals, 14 constants, 0 functions
	1	[120]	NEWTABLE 	2 0 0
	2	[123]	GETGLOBAL	3 -1	; ipairs
	3	[123]	GETTABLE 	4 0 -2	; "providers"
	4	[123]	CALL     	3 2 4
	5	[123]	JMP      	65	; to 71
	6	[124]	LOADBOOL 	8 0 0
	7	[125]	GETGLOBAL	9 -3	; string
	8	[125]	GETTABLE 	9 9 -4	; "sub"
	9	[125]	MOVE     	10 1
	10	[125]	GETGLOBAL	11 -3	; string
	11	[125]	GETTABLE 	11 11 -5	; "len"
	12	[125]	GETTABLE 	12 7 -6	; "extension"
	13	[125]	CALL     	11 2 2
	14	[125]	UNM      	11 11
	15	[125]	SUB      	11 11 -7	; - 1
	16	[125]	CALL     	9 3 2
	17	[126]	GETGLOBAL	10 -3	; string
	18	[126]	GETTABLE 	10 10 -8	; "lower"
	19	[126]	MOVE     	11 9
	20	[126]	CALL     	10 2 2
	21	[126]	LOADK    	11 -9	; "."
	22	[126]	GETTABLE 	12 7 -6	; "extension"
	23	[126]	CONCAT   	11 11 12
	24	[126]	EQ       	0 10 11
	25	[126]	JMP      	45	; to 71
	26	[127]	GETGLOBAL	10 -1	; ipairs
	27	[127]	MOVE     	11 2
	28	[127]	CALL     	10 2 4
	29	[127]	JMP      	15	; to 45
	30	[128]	GETTABLE 	15 14 -10	; "provider"
	31	[128]	GETTABLE 	16 7 -10	; "provider"
	32	[128]	EQ       	0 15 16
	33	[128]	JMP      	11	; to 45
	34	[129]	GETTABLE 	15 14 -11	; "weight"
	35	[129]	GETTABLE 	16 7 -11	; "weight"
	36	[129]	LE       	0 16 15
	37	[129]	JMP      	2	; to 40
	38	[130]	LOADBOOL 	8 1 0
	39	[130]	JMP      	5	; to 45
	40	[132]	GETGLOBAL	15 -12	; table
	41	[132]	GETTABLE 	15 15 -13	; "remove"
	42	[132]	MOVE     	16 2
	43	[132]	MOVE     	17 13
	44	[132]	CALL     	15 3 1
	45	[127]	TFORLOOP 	10 2
	46	[134]	JMP      	-17	; to 30
	47	[138]	TEST     	8 0 1
	48	[138]	JMP      	15	; to 64
	49	[138]	LEN      	10 2
	50	[138]	LE       	0 -7 10	; 1 -
	51	[138]	JMP      	12	; to 64
	52	[138]	GETTABLE 	10 7 -11	; "weight"
	53	[138]	GETTABLE 	11 2 -7	; 1
	54	[138]	GETTABLE 	11 11 -11	; "weight"
	55	[138]	LT       	0 11 10
	56	[138]	JMP      	7	; to 64
	57	[139]	GETGLOBAL	10 -12	; table
	58	[139]	GETTABLE 	10 10 -14	; "insert"
	59	[139]	MOVE     	11 2
	60	[139]	LOADK    	12 -7	; 1
	61	[139]	MOVE     	13 7
	62	[139]	CALL     	10 4 1
	63	[139]	JMP      	7	; to 71
	64	[140]	TEST     	8 0 1
	65	[140]	JMP      	5	; to 71
	66	[141]	GETGLOBAL	10 -12	; table
	67	[141]	GETTABLE 	10 10 -14	; "insert"
	68	[141]	MOVE     	11 2
	69	[141]	MOVE     	12 7
	70	[141]	CALL     	10 3 1
	71	[123]	TFORLOOP 	3 2
	72	[143]	JMP      	-67	; to 6
	73	[146]	LEN      	3 2
	74	[146]	LE       	0 -7 3	; 1 -
	75	[146]	JMP      	1	; to 77
	76	[147]	RETURN   	2 2
	77	[149]	RETURN   	0 1

function <./frontend/document/documentregistry.lua:154,168> (34 instructions, 136 bytes at 0x7fc042408670)
4 params, 11 slots, 1 upvalue, 8 locals, 9 constants, 0 functions
	1	[155]	GETUPVAL 	4 0	; util
	2	[155]	GETTABLE 	4 4 -1	; "splitFileNameSuffix"
	3	[155]	MOVE     	5 1
	4	[155]	CALL     	4 2 3
	5	[158]	TEST     	3 0 1
	6	[158]	JMP      	13	; to 20
	7	[159]	GETGLOBAL	6 -2	; require
	8	[159]	LOADK    	7 -3	; "docsettings"
	9	[159]	CALL     	6 2 2
	10	[159]	SELF     	6 6 -4	; "open"
	11	[159]	MOVE     	8 1
	12	[159]	CALL     	6 3 2
	13	[160]	SELF     	7 6 -5	; "saveSetting"
	14	[160]	LOADK    	9 -6	; "provider"
	15	[160]	GETTABLE 	10 2 -6	; "provider"
	16	[160]	CALL     	7 4 1
	17	[161]	SELF     	7 6 -7	; "flush"
	18	[161]	CALL     	7 2 1
	19	[161]	JMP      	14	; to 34
	20	[164]	GETGLOBAL	6 -8	; G_reader_settings
	21	[164]	SELF     	6 6 -9	; "readSetting"
	22	[164]	LOADK    	8 -6	; "provider"
	23	[164]	CALL     	6 3 2
	24	[164]	TEST     	6 0 1
	25	[164]	JMP      	1	; to 27
	26	[164]	NEWTABLE 	6 0 0
	27	[165]	GETTABLE 	7 2 -6	; "provider"
	28	[165]	SETTABLE 	6 5 7
	29	[166]	GETGLOBAL	7 -8	; G_reader_settings
	30	[166]	SELF     	7 7 -5	; "saveSetting"
	31	[166]	LOADK    	9 -6	; "provider"
	32	[166]	MOVE     	10 6
	33	[166]	CALL     	7 4 1
	34	[168]	RETURN   	0 1

function <./frontend/document/documentregistry.lua:170,196> (53 instructions, 212 bytes at 0x7fc0424072e0)
3 params, 9 slots, 1 upvalue, 5 locals, 12 constants, 0 functions
	1	[174]	GETGLOBAL	3 -1	; collectgarbage
	2	[174]	CALL     	3 1 1
	3	[175]	GETGLOBAL	3 -1	; collectgarbage
	4	[175]	CALL     	3 1 1
	5	[176]	GETTABLE 	3 0 -2	; "registry"
	6	[176]	GETTABLE 	3 3 1
	7	[176]	TEST     	3 0 1
	8	[176]	JMP      	29	; to 38
	9	[177]	TEST     	2 0 1
	10	[177]	JMP      	4	; to 15
	11	[177]	SELF     	3 0 -3	; "getProvider"
	12	[177]	MOVE     	5 1
	13	[177]	CALL     	3 3 2
	14	[177]	MOVE     	2 3
	15	[179]	EQ       	1 2 -4	; - nil
	16	[179]	JMP      	28	; to 45
	17	[180]	GETGLOBAL	3 -5	; pcall
	18	[180]	GETTABLE 	4 2 -6	; "new"
	19	[180]	MOVE     	5 2
	20	[180]	NEWTABLE 	6 0 1
	21	[180]	SETTABLE 	6 -7 1	; "file" -
	22	[180]	CALL     	3 4 3
	23	[181]	TEST     	3 0 0
	24	[181]	JMP      	6	; to 31
	25	[182]	GETTABLE 	5 0 -2	; "registry"
	26	[182]	NEWTABLE 	6 0 2
	27	[183]	SETTABLE 	6 -8 4	; "doc" -
	28	[184]	SETTABLE 	6 -9 -10	; "refs" 1
	29	[185]	SETTABLE 	5 1 6
	30	[185]	JMP      	14	; to 45
	31	[187]	GETUPVAL 	5 0	; logger
	32	[187]	GETTABLE 	5 5 -11	; "warn"
	33	[187]	LOADK    	6 -12	; "cannot open document"
	34	[187]	MOVE     	7 1
	35	[187]	MOVE     	8 4
	36	[187]	CALL     	5 4 1
	37	[189]	JMP      	7	; to 45
	38	[191]	GETTABLE 	3 0 -2	; "registry"
	39	[191]	GETTABLE 	3 3 1
	40	[191]	GETTABLE 	4 0 -2	; "registry"
	41	[191]	GETTABLE 	4 4 1
	42	[191]	GETTABLE 	4 4 -9	; "refs"
	43	[191]	ADD      	4 4 -10	; - 1
	44	[191]	SETTABLE 	3 -9 4	; "refs" -
	45	[193]	GETTABLE 	3 0 -2	; "registry"
	46	[193]	GETTABLE 	3 3 1
	47	[193]	TEST     	3 0 0
	48	[193]	JMP      	4	; to 53
	49	[194]	GETTABLE 	3 0 -2	; "registry"
	50	[194]	GETTABLE 	3 3 1
	51	[194]	GETTABLE 	3 3 -8	; "doc"
	52	[194]	RETURN   	3 2
	53	[196]	RETURN   	0 1

function <./frontend/document/documentregistry.lua:198,210> (30 instructions, 120 bytes at 0x7fc0424093e0)
2 params, 4 slots, 0 upvalues, 2 locals, 7 constants, 0 functions
	1	[199]	GETTABLE 	2 0 -1	; "registry"
	2	[199]	GETTABLE 	2 2 1
	3	[199]	TEST     	2 0 0
	4	[199]	JMP      	22	; to 27
	5	[200]	GETTABLE 	2 0 -1	; "registry"
	6	[200]	GETTABLE 	2 2 1
	7	[200]	GETTABLE 	3 0 -1	; "registry"
	8	[200]	GETTABLE 	3 3 1
	9	[200]	GETTABLE 	3 3 -2	; "refs"
	10	[200]	SUB      	3 3 -3	; - 1
	11	[200]	SETTABLE 	2 -2 3	; "refs" -
	12	[201]	GETTABLE 	2 0 -1	; "registry"
	13	[201]	GETTABLE 	2 2 1
	14	[201]	GETTABLE 	2 2 -2	; "refs"
	15	[201]	EQ       	0 2 -4	; - 0
	16	[201]	JMP      	5	; to 22
	17	[202]	GETTABLE 	2 0 -1	; "registry"
	18	[202]	SETTABLE 	2 1 -5	; - nil
	19	[203]	LOADK    	2 -4	; 0
	20	[203]	RETURN   	2 2
	21	[203]	JMP      	8	; to 30
	22	[205]	GETTABLE 	2 0 -1	; "registry"
	23	[205]	GETTABLE 	2 2 1
	24	[205]	GETTABLE 	2 2 -2	; "refs"
	25	[205]	RETURN   	2 2
	26	[206]	JMP      	3	; to 30
	27	[208]	GETGLOBAL	2 -6	; error
	28	[208]	LOADK    	3 -7	; "Try to close unregistered file."
	29	[208]	CALL     	2 2 1
	30	[210]	RETURN   	0 1
