
main <./frontend/ui/widget/doublespinwidget.lua:0,0> (159 instructions, 636 bytes at 0x7f85a1c068f0)
0+ params, 30 slots, 0 upvalues, 25 locals, 68 constants, 8 functions
	1	[1]	GETGLOBAL	0 -1	; require
	2	[1]	LOADK    	1 -2	; "ffi/blitbuffer"
	3	[1]	CALL     	0 2 2
	4	[2]	GETGLOBAL	1 -1	; require
	5	[2]	LOADK    	2 -3	; "ui/widget/buttontable"
	6	[2]	CALL     	1 2 2
	7	[3]	GETGLOBAL	2 -1	; require
	8	[3]	LOADK    	3 -4	; "ui/widget/container/centercontainer"
	9	[3]	CALL     	2 2 2
	10	[4]	GETGLOBAL	3 -1	; require
	11	[4]	LOADK    	4 -5	; "ui/widget/closebutton"
	12	[4]	CALL     	3 2 2
	13	[5]	GETGLOBAL	4 -1	; require
	14	[5]	LOADK    	5 -6	; "device"
	15	[5]	CALL     	4 2 2
	16	[6]	GETGLOBAL	5 -1	; require
	17	[6]	LOADK    	6 -7	; "ui/widget/container/framecontainer"
	18	[6]	CALL     	5 2 2
	19	[7]	GETGLOBAL	6 -1	; require
	20	[7]	LOADK    	7 -8	; "ui/geometry"
	21	[7]	CALL     	6 2 2
	22	[8]	GETGLOBAL	7 -1	; require
	23	[8]	LOADK    	8 -9	; "ui/gesturerange"
	24	[8]	CALL     	7 2 2
	25	[9]	GETGLOBAL	8 -1	; require
	26	[9]	LOADK    	9 -10	; "ui/font"
	27	[9]	CALL     	8 2 2
	28	[10]	GETGLOBAL	9 -1	; require
	29	[10]	LOADK    	10 -11	; "ui/widget/horizontalgroup"
	30	[10]	CALL     	9 2 2
	31	[11]	GETGLOBAL	10 -1	; require
	32	[11]	LOADK    	11 -12	; "ui/widget/container/inputcontainer"
	33	[11]	CALL     	10 2 2
	34	[12]	GETGLOBAL	11 -1	; require
	35	[12]	LOADK    	12 -13	; "ui/widget/linewidget"
	36	[12]	CALL     	11 2 2
	37	[13]	GETGLOBAL	12 -1	; require
	38	[13]	LOADK    	13 -14	; "ui/widget/container/movablecontainer"
	39	[13]	CALL     	12 2 2
	40	[14]	GETGLOBAL	13 -1	; require
	41	[14]	LOADK    	14 -15	; "ui/widget/overlapgroup"
	42	[14]	CALL     	13 2 2
	43	[15]	GETGLOBAL	14 -1	; require
	44	[15]	LOADK    	15 -16	; "ui/widget/numberpickerwidget"
	45	[15]	CALL     	14 2 2
	46	[16]	GETGLOBAL	15 -1	; require
	47	[16]	LOADK    	16 -17	; "ui/size"
	48	[16]	CALL     	15 2 2
	49	[17]	GETGLOBAL	16 -1	; require
	50	[17]	LOADK    	17 -18	; "ui/widget/textboxwidget"
	51	[17]	CALL     	16 2 2
	52	[18]	GETGLOBAL	17 -1	; require
	53	[18]	LOADK    	18 -19	; "ui/widget/textwidget"
	54	[18]	CALL     	17 2 2
	55	[19]	GETGLOBAL	18 -1	; require
	56	[19]	LOADK    	19 -20	; "ui/uimanager"
	57	[19]	CALL     	18 2 2
	58	[20]	GETGLOBAL	19 -1	; require
	59	[20]	LOADK    	20 -21	; "ui/widget/verticalgroup"
	60	[20]	CALL     	19 2 2
	61	[21]	GETGLOBAL	20 -1	; require
	62	[21]	LOADK    	21 -22	; "ui/widget/verticalspan"
	63	[21]	CALL     	20 2 2
	64	[22]	GETGLOBAL	21 -1	; require
	65	[22]	LOADK    	22 -23	; "ui/widget/container/widgetcontainer"
	66	[22]	CALL     	21 2 2
	67	[23]	GETGLOBAL	22 -1	; require
	68	[23]	LOADK    	23 -24	; "gettext"
	69	[23]	CALL     	22 2 2
	70	[24]	GETTABLE 	23 4 -25	; "screen"
	71	[26]	SELF     	24 10 -26	; "new"
	72	[26]	NEWTABLE 	26 0 19
	73	[27]	SETTABLE 	26 -27 -28	; "title_text" ""
	74	[28]	SELF     	27 8 -30	; "getFace"
	75	[28]	LOADK    	29 -31	; "x_smalltfont"
	76	[28]	CALL     	27 3 2
	77	[28]	SETTABLE 	26 -29 27	; "title_face" -
	78	[29]	SETTABLE 	26 -32 -33	; "info_text" nil
	79	[30]	SETTABLE 	26 -34 -33	; "width" nil
	80	[31]	SETTABLE 	26 -35 -33	; "height" nil
	81	[32]	SETTABLE 	26 -36 -37	; "left_min" 1
	82	[33]	SETTABLE 	26 -38 -39	; "left_max" 20
	83	[34]	SETTABLE 	26 -40 -37	; "left_value" 1
	84	[35]	SETTABLE 	26 -41 -33	; "left_default" nil
	85	[36]	MOVE     	27 22
	86	[36]	LOADK    	28 -43	; "Left"
	87	[36]	CALL     	27 2 2
	88	[36]	SETTABLE 	26 -42 27	; "left_text" -
	89	[37]	SETTABLE 	26 -44 -37	; "right_min" 1
	90	[38]	SETTABLE 	26 -45 -39	; "right_max" 20
	91	[39]	SETTABLE 	26 -46 -37	; "right_value" 1
	92	[40]	SETTABLE 	26 -47 -33	; "right_default" nil
	93	[41]	MOVE     	27 22
	94	[41]	LOADK    	28 -49	; "Right"
	95	[41]	CALL     	27 2 2
	96	[41]	SETTABLE 	26 -48 27	; "right_text" -
	97	[42]	MOVE     	27 22
	98	[42]	LOADK    	28 -51	; "Close"
	99	[42]	CALL     	27 2 2
	100	[42]	SETTABLE 	26 -50 27	; "cancel_text" -
	101	[43]	MOVE     	27 22
	102	[43]	LOADK    	28 -53	; "Apply"
	103	[43]	CALL     	27 2 2
	104	[43]	SETTABLE 	26 -52 27	; "ok_text" -
	105	[44]	SETTABLE 	26 -54 -55	; "keep_shown_on_apply" false
	106	[46]	SETTABLE 	26 -56 -33	; "default_values" nil
	107	[47]	MOVE     	27 22
	108	[47]	LOADK    	28 -58	; "Use defaults"
	109	[47]	CALL     	27 2 2
	110	[47]	SETTABLE 	26 -57 27	; "default_text" -
	111	[49]	SETTABLE 	26 -59 -33	; "extra_text" nil
	112	[50]	SETTABLE 	26 -60 -33	; "extra_callback" nil
	113	[26]	CALL     	24 3 2
	114	[78]	CLOSURE  	25 0	; 0x7f85a1d04410
	115	[78]	MOVE     	0 8
	116	[78]	MOVE     	0 23
	117	[78]	MOVE     	0 4
	118	[78]	MOVE     	0 7
	119	[78]	MOVE     	0 6
	120	[53]	SETTABLE 	24 -61 25	; "init" -
	121	[288]	CLOSURE  	25 1	; 0x7f85a1d04720
	122	[288]	MOVE     	0 14
	123	[288]	MOVE     	0 19
	124	[288]	MOVE     	0 20
	125	[288]	MOVE     	0 15
	126	[288]	MOVE     	0 17
	127	[288]	MOVE     	0 9
	128	[288]	MOVE     	0 2
	129	[288]	MOVE     	0 6
	130	[288]	MOVE     	0 5
	131	[288]	MOVE     	0 11
	132	[288]	MOVE     	0 13
	133	[288]	MOVE     	0 3
	134	[288]	MOVE     	0 16
	135	[288]	MOVE     	0 8
	136	[288]	MOVE     	0 1
	137	[288]	MOVE     	0 0
	138	[288]	MOVE     	0 12
	139	[288]	MOVE     	0 21
	140	[288]	MOVE     	0 18
	141	[80]	SETTABLE 	24 -62 25	; "update" -
	142	[293]	CLOSURE  	25 2	; 0x7f85a1d06520
	143	[290]	SETTABLE 	24 -63 25	; "hasMoved" -
	144	[300]	CLOSURE  	25 3	; 0x7f85a1d06b80
	145	[300]	MOVE     	0 18
	146	[295]	SETTABLE 	24 -64 25	; "onCloseWidget" -
	147	[307]	CLOSURE  	25 4	; 0x7f85a1d075e0
	148	[307]	MOVE     	0 18
	149	[302]	SETTABLE 	24 -65 25	; "onShow" -
	150	[312]	CLOSURE  	25 5	; 0x7f85a1d07bf0
	151	[312]	MOVE     	0 18
	152	[309]	SETTABLE 	24 -66 25	; "onAnyKeyPressed" -
	153	[319]	CLOSURE  	25 6	; 0x7f85a1d07c80
	154	[314]	SETTABLE 	24 -67 25	; "onTapClose" -
	155	[324]	CLOSURE  	25 7	; 0x7f85a1d08090
	156	[324]	MOVE     	0 18
	157	[321]	SETTABLE 	24 -68 25	; "onClose" -
	158	[326]	RETURN   	24 2
	159	[326]	RETURN   	0 1

function <./frontend/ui/widget/doublespinwidget.lua:53,78> (63 instructions, 252 bytes at 0x7f85a1d04410)
1 param, 10 slots, 5 upvalues, 1 local, 27 constants, 0 functions
	1	[54]	GETUPVAL 	1 0	; Font
	2	[54]	SELF     	1 1 -2	; "getFace"
	3	[54]	LOADK    	3 -3	; "ffont"
	4	[54]	CALL     	1 3 2
	5	[54]	SETTABLE 	0 -1 1	; "medium_font_face" -
	6	[55]	GETUPVAL 	1 1	; Screen
	7	[55]	SELF     	1 1 -5	; "getWidth"
	8	[55]	CALL     	1 2 2
	9	[55]	SETTABLE 	0 -4 1	; "screen_width" -
	10	[56]	GETUPVAL 	1 1	; Screen
	11	[56]	SELF     	1 1 -7	; "getHeight"
	12	[56]	CALL     	1 2 2
	13	[56]	SETTABLE 	0 -6 1	; "screen_height" -
	14	[57]	GETTABLE 	1 0 -8	; "width"
	15	[57]	TEST     	1 0 1
	16	[57]	JMP      	2	; to 19
	17	[57]	GETTABLE 	1 0 -4	; "screen_width"
	18	[57]	MUL      	1 1 -9	; - 0.8
	19	[57]	SETTABLE 	0 -8 1	; "width" -
	20	[58]	GETTABLE 	1 0 -4	; "screen_width"
	21	[58]	MUL      	1 1 -11	; - 0.25
	22	[58]	SETTABLE 	0 -10 1	; "picker_width" -
	23	[59]	GETUPVAL 	1 2	; Device
	24	[59]	SELF     	1 1 -12	; "hasKeys"
	25	[59]	CALL     	1 2 2
	26	[59]	TEST     	1 0 0
	27	[59]	JMP      	9	; to 37
	28	[60]	NEWTABLE 	1 0 1
	29	[61]	NEWTABLE 	2 1 1
	30	[61]	NEWTABLE 	3 1 0
	31	[61]	LOADK    	4 -15	; "Back"
	32	[61]	SETLIST  	3 1 1	; 1
	33	[61]	SETTABLE 	2 -16 -17	; "doc" "close time widget"
	34	[61]	SETLIST  	2 1 1	; 1
	35	[61]	SETTABLE 	1 -14 2	; "Close" -
	36	[62]	SETTABLE 	0 -13 1	; "key_events" -
	37	[64]	GETUPVAL 	1 2	; Device
	38	[64]	SELF     	1 1 -18	; "isTouchDevice"
	39	[64]	CALL     	1 2 2
	40	[64]	TEST     	1 0 0
	41	[64]	JMP      	19	; to 61
	42	[65]	NEWTABLE 	1 0 1
	43	[66]	NEWTABLE 	2 0 0
	44	[67]	GETUPVAL 	3 3	; GestureRange
	45	[67]	SELF     	3 3 -21	; "new"
	46	[67]	NEWTABLE 	5 0 2
	47	[68]	SETTABLE 	5 -22 -23	; "ges" "tap"
	48	[69]	GETUPVAL 	6 4	; Geom
	49	[69]	SELF     	6 6 -21	; "new"
	50	[69]	NEWTABLE 	8 0 2
	51	[70]	GETTABLE 	9 0 -4	; "screen_width"
	52	[70]	SETTABLE 	8 -25 9	; "w" -
	53	[71]	GETTABLE 	9 0 -6	; "screen_height"
	54	[71]	SETTABLE 	8 -26 9	; "h" -
	55	[69]	CALL     	6 3 2
	56	[72]	SETTABLE 	5 -24 6	; "range" -
	57	[67]	CALL     	3 3 0
	58	[74]	SETLIST  	2 0 1	; 1
	59	[74]	SETTABLE 	1 -20 2	; "TapClose" -
	60	[75]	SETTABLE 	0 -19 1	; "ges_events" -
	61	[77]	SELF     	1 0 -27	; "update"
	62	[77]	CALL     	1 2 1
	63	[78]	RETURN   	0 1

function <./frontend/ui/widget/doublespinwidget.lua:80,288> (409 instructions, 1636 bytes at 0x7f85a1d04720)
1 param, 33 slots, 19 upvalues, 13 locals, 79 constants, 9 functions
	1	[85]	CLOSURE  	1 0	; 0x7f85a1d04f00
	2	[86]	GETUPVAL 	2 0	; NumberPickerWidget
	3	[86]	SELF     	2 2 -1	; "new"
	4	[86]	NEWTABLE 	4 0 9
	5	[87]	SETTABLE 	4 -2 0	; "show_parent" -
	6	[88]	GETTABLE 	5 0 -4	; "picker_width"
	7	[88]	SETTABLE 	4 -3 5	; "width" -
	8	[89]	GETTABLE 	5 0 -6	; "left_value"
	9	[89]	SETTABLE 	4 -5 5	; "value" -
	10	[90]	GETTABLE 	5 0 -8	; "left_min"
	11	[90]	SETTABLE 	4 -7 5	; "value_min" -
	12	[91]	GETTABLE 	5 0 -10	; "left_max"
	13	[91]	SETTABLE 	4 -9 5	; "value_max" -
	14	[92]	GETTABLE 	5 0 -12	; "left_step"
	15	[92]	SETTABLE 	4 -11 5	; "value_step" -
	16	[93]	GETTABLE 	5 0 -14	; "left_hold_step"
	17	[93]	SETTABLE 	4 -13 5	; "value_hold_step" -
	18	[94]	SETTABLE 	4 -15 -16	; "wrap" false
	19	[95]	CLOSURE  	5 1	; 0x7f85a1d052d0
	20	[95]	MOVE     	0 1
	21	[95]	SETTABLE 	4 -17 5	; "update_callback" -
	22	[86]	CALL     	2 3 2
	23	[97]	GETUPVAL 	3 0	; NumberPickerWidget
	24	[97]	SELF     	3 3 -1	; "new"
	25	[97]	NEWTABLE 	5 0 9
	26	[98]	SETTABLE 	5 -2 0	; "show_parent" -
	27	[99]	GETTABLE 	6 0 -4	; "picker_width"
	28	[99]	SETTABLE 	5 -3 6	; "width" -
	29	[100]	GETTABLE 	6 0 -18	; "right_value"
	30	[100]	SETTABLE 	5 -5 6	; "value" -
	31	[101]	GETTABLE 	6 0 -19	; "right_min"
	32	[101]	SETTABLE 	5 -7 6	; "value_min" -
	33	[102]	GETTABLE 	6 0 -20	; "right_max"
	34	[102]	SETTABLE 	5 -9 6	; "value_max" -
	35	[103]	GETTABLE 	6 0 -21	; "right_step"
	36	[103]	SETTABLE 	5 -11 6	; "value_step" -
	37	[104]	GETTABLE 	6 0 -22	; "right_hold_step"
	38	[104]	SETTABLE 	5 -13 6	; "value_hold_step" -
	39	[105]	SETTABLE 	5 -15 -16	; "wrap" false
	40	[106]	CLOSURE  	6 2	; 0x7f85a1d05250
	41	[106]	MOVE     	0 1
	42	[106]	SETTABLE 	5 -17 6	; "update_callback" -
	43	[97]	CALL     	3 3 2
	44	[108]	GETUPVAL 	4 1	; VerticalGroup
	45	[108]	SELF     	4 4 -1	; "new"
	46	[108]	NEWTABLE 	6 3 1
	47	[109]	SETTABLE 	6 -23 -24	; "align" "center"
	48	[110]	GETUPVAL 	7 2	; VerticalSpan
	49	[110]	SELF     	7 7 -1	; "new"
	50	[110]	NEWTABLE 	9 0 1
	51	[110]	GETUPVAL 	10 3	; Size
	52	[110]	GETTABLE 	10 10 -25	; "span"
	53	[110]	GETTABLE 	10 10 -26	; "vertical_large"
	54	[110]	SETTABLE 	9 -3 10	; "width" -
	55	[110]	CALL     	7 3 2
	56	[111]	GETUPVAL 	8 4	; TextWidget
	57	[111]	SELF     	8 8 -1	; "new"
	58	[111]	NEWTABLE 	10 0 3
	59	[112]	GETTABLE 	11 0 -28	; "left_text"
	60	[112]	SETTABLE 	10 -27 11	; "text" -
	61	[113]	GETTABLE 	11 0 -30	; "title_face"
	62	[113]	SETTABLE 	10 -29 11	; "face" -
	63	[114]	GETTABLE 	11 0 -3	; "width"
	64	[114]	MUL      	11 -32 11	; 0.95 -
	65	[114]	DIV      	11 11 -33	; - 2
	66	[114]	SETTABLE 	10 -31 11	; "max_width" -
	67	[111]	CALL     	8 3 2
	68	[117]	MOVE     	9 2
	69	[117]	SETLIST  	6 3 1	; 1
	70	[108]	CALL     	4 3 2
	71	[118]	GETUPVAL 	5 1	; VerticalGroup
	72	[118]	SELF     	5 5 -1	; "new"
	73	[118]	NEWTABLE 	7 3 1
	74	[119]	SETTABLE 	7 -23 -24	; "align" "center"
	75	[120]	GETUPVAL 	8 2	; VerticalSpan
	76	[120]	SELF     	8 8 -1	; "new"
	77	[120]	NEWTABLE 	10 0 1
	78	[120]	GETUPVAL 	11 3	; Size
	79	[120]	GETTABLE 	11 11 -25	; "span"
	80	[120]	GETTABLE 	11 11 -26	; "vertical_large"
	81	[120]	SETTABLE 	10 -3 11	; "width" -
	82	[120]	CALL     	8 3 2
	83	[121]	GETUPVAL 	9 4	; TextWidget
	84	[121]	SELF     	9 9 -1	; "new"
	85	[121]	NEWTABLE 	11 0 3
	86	[122]	GETTABLE 	12 0 -34	; "right_text"
	87	[122]	SETTABLE 	11 -27 12	; "text" -
	88	[123]	GETTABLE 	12 0 -30	; "title_face"
	89	[123]	SETTABLE 	11 -29 12	; "face" -
	90	[124]	GETTABLE 	12 0 -3	; "width"
	91	[124]	MUL      	12 -32 12	; 0.95 -
	92	[124]	DIV      	12 12 -33	; - 2
	93	[124]	SETTABLE 	11 -31 12	; "max_width" -
	94	[121]	CALL     	9 3 2
	95	[127]	MOVE     	10 3
	96	[127]	SETLIST  	7 3 1	; 1
	97	[118]	CALL     	5 3 2
	98	[128]	GETUPVAL 	6 5	; HorizontalGroup
	99	[128]	SELF     	6 6 -1	; "new"
	100	[128]	NEWTABLE 	8 1 1
	101	[129]	SETTABLE 	8 -23 -24	; "align" "center"
	102	[130]	GETUPVAL 	9 6	; CenterContainer
	103	[130]	SELF     	9 9 -1	; "new"
	104	[130]	NEWTABLE 	11 1 1
	105	[131]	GETUPVAL 	12 7	; Geom
	106	[131]	SELF     	12 12 -1	; "new"
	107	[131]	NEWTABLE 	14 0 2
	108	[132]	GETTABLE 	15 0 -3	; "width"
	109	[132]	DIV      	15 15 -33	; - 2
	110	[132]	SETTABLE 	14 -36 15	; "w" -
	111	[133]	SELF     	15 4 -38	; "getSize"
	112	[133]	CALL     	15 2 2
	113	[133]	GETTABLE 	15 15 -37	; "h"
	114	[133]	SETTABLE 	14 -37 15	; "h" -
	115	[131]	CALL     	12 3 2
	116	[134]	SETTABLE 	11 -35 12	; "dimen" -
	117	[136]	MOVE     	12 4
	118	[136]	SETLIST  	11 1 1	; 1
	119	[130]	CALL     	9 3 2
	120	[137]	GETUPVAL 	10 6	; CenterContainer
	121	[137]	SELF     	10 10 -1	; "new"
	122	[137]	NEWTABLE 	12 1 1
	123	[138]	GETUPVAL 	13 7	; Geom
	124	[138]	SELF     	13 13 -1	; "new"
	125	[138]	NEWTABLE 	15 0 2
	126	[139]	GETTABLE 	16 0 -3	; "width"
	127	[139]	DIV      	16 16 -33	; - 2
	128	[139]	SETTABLE 	15 -36 16	; "w" -
	129	[140]	SELF     	16 5 -38	; "getSize"
	130	[140]	CALL     	16 2 2
	131	[140]	GETTABLE 	16 16 -37	; "h"
	132	[140]	SETTABLE 	15 -37 16	; "h" -
	133	[138]	CALL     	13 3 2
	134	[141]	SETTABLE 	12 -35 13	; "dimen" -
	135	[143]	MOVE     	13 5
	136	[143]	SETLIST  	12 1 1	; 1
	137	[137]	CALL     	10 3 0
	138	[144]	SETLIST  	8 0 1	; 1
	139	[128]	CALL     	6 3 2
	140	[145]	GETUPVAL 	7 8	; FrameContainer
	141	[145]	SELF     	7 7 -1	; "new"
	142	[145]	NEWTABLE 	9 0 3
	143	[146]	GETUPVAL 	10 3	; Size
	144	[146]	GETTABLE 	10 10 -39	; "padding"
	145	[146]	GETTABLE 	10 10 -40	; "default"
	146	[146]	SETTABLE 	9 -39 10	; "padding" -
	147	[147]	GETUPVAL 	10 3	; Size
	148	[147]	GETTABLE 	10 10 -41	; "margin"
	149	[147]	GETTABLE 	10 10 -42	; "title"
	150	[147]	SETTABLE 	9 -41 10	; "margin" -
	151	[148]	SETTABLE 	9 -43 -44	; "bordersize" 0
	152	[149]	GETUPVAL 	10 4	; TextWidget
	153	[149]	SELF     	10 10 -1	; "new"
	154	[149]	NEWTABLE 	12 0 4
	155	[150]	GETTABLE 	13 0 -45	; "title_text"
	156	[150]	SETTABLE 	12 -27 13	; "text" -
	157	[151]	GETTABLE 	13 0 -30	; "title_face"
	158	[151]	SETTABLE 	12 -29 13	; "face" -
	159	[152]	SETTABLE 	12 -46 -47	; "bold" true
	160	[153]	GETTABLE 	13 0 -3	; "width"
	161	[153]	SETTABLE 	12 -3 13	; "width" -
	162	[149]	CALL     	10 3 0
	163	[155]	SETLIST  	9 0 1	; 1
	164	[145]	CALL     	7 3 2
	165	[156]	GETUPVAL 	8 9	; LineWidget
	166	[156]	SELF     	8 8 -1	; "new"
	167	[156]	NEWTABLE 	10 0 1
	168	[157]	GETUPVAL 	11 7	; Geom
	169	[157]	SELF     	11 11 -1	; "new"
	170	[157]	NEWTABLE 	13 0 2
	171	[158]	GETTABLE 	14 0 -3	; "width"
	172	[158]	SETTABLE 	13 -36 14	; "w" -
	173	[159]	GETUPVAL 	14 3	; Size
	174	[159]	GETTABLE 	14 14 -48	; "line"
	175	[159]	GETTABLE 	14 14 -49	; "thick"
	176	[159]	SETTABLE 	13 -37 14	; "h" -
	177	[157]	CALL     	11 3 2
	178	[160]	SETTABLE 	10 -35 11	; "dimen" -
	179	[156]	CALL     	8 3 2
	180	[162]	GETUPVAL 	9 10	; OverlapGroup
	181	[162]	SELF     	9 9 -1	; "new"
	182	[162]	NEWTABLE 	11 1 1
	183	[163]	NEWTABLE 	12 0 2
	184	[164]	GETTABLE 	13 0 -3	; "width"
	185	[164]	SETTABLE 	12 -36 13	; "w" -
	186	[165]	SELF     	13 7 -38	; "getSize"
	187	[165]	CALL     	13 2 2
	188	[165]	GETTABLE 	13 13 -37	; "h"
	189	[165]	SETTABLE 	12 -37 13	; "h" -
	190	[166]	SETTABLE 	11 -35 12	; "dimen" -
	191	[167]	MOVE     	12 7
	192	[168]	GETUPVAL 	13 11	; CloseButton
	193	[168]	SELF     	13 13 -1	; "new"
	194	[168]	NEWTABLE 	15 0 2
	195	[168]	SETTABLE 	15 -50 0	; "window" -
	196	[168]	GETUPVAL 	16 3	; Size
	197	[168]	GETTABLE 	16 16 -41	; "margin"
	198	[168]	GETTABLE 	16 16 -42	; "title"
	199	[168]	SETTABLE 	15 -51 16	; "padding_top" -
	200	[168]	CALL     	13 3 0
	201	[169]	SETLIST  	11 0 1	; 1
	202	[162]	CALL     	9 3 2
	203	[170]	GETUPVAL 	10 8	; FrameContainer
	204	[170]	SELF     	10 10 -1	; "new"
	205	[170]	NEWTABLE 	12 0 3
	206	[171]	GETUPVAL 	13 3	; Size
	207	[171]	GETTABLE 	13 13 -39	; "padding"
	208	[171]	GETTABLE 	13 13 -40	; "default"
	209	[171]	SETTABLE 	12 -39 13	; "padding" -
	210	[172]	GETUPVAL 	13 3	; Size
	211	[172]	GETTABLE 	13 13 -41	; "margin"
	212	[172]	GETTABLE 	13 13 -52	; "small"
	213	[172]	SETTABLE 	12 -41 13	; "margin" -
	214	[173]	SETTABLE 	12 -43 -44	; "bordersize" 0
	215	[174]	GETUPVAL 	13 12	; TextBoxWidget
	216	[174]	SELF     	13 13 -1	; "new"
	217	[174]	NEWTABLE 	15 0 3
	218	[175]	GETTABLE 	16 0 -53	; "info_text"
	219	[175]	TEST     	16 0 1
	220	[175]	JMP      	1	; to 222
	221	[175]	LOADK    	16 -54	; ""
	222	[175]	SETTABLE 	15 -27 16	; "text" -
	223	[176]	GETUPVAL 	16 13	; Font
	224	[176]	SELF     	16 16 -55	; "getFace"
	225	[176]	LOADK    	18 -56	; "x_smallinfofont"
	226	[176]	CALL     	16 3 2
	227	[176]	SETTABLE 	15 -29 16	; "face" -
	228	[177]	GETTABLE 	16 0 -3	; "width"
	229	[177]	MUL      	16 16 -57	; - 0.9
	230	[177]	SETTABLE 	15 -3 16	; "width" -
	231	[174]	CALL     	13 3 0
	232	[179]	SETLIST  	12 0 1	; 1
	233	[170]	CALL     	10 3 2
	234	[180]	NEWTABLE 	11 1 0
	235	[180]	NEWTABLE 	12 2 0
	236	[181]	NEWTABLE 	13 0 2
	237	[183]	GETTABLE 	14 0 -58	; "cancel_text"
	238	[183]	SETTABLE 	13 -27 14	; "text" -
	239	[186]	CLOSURE  	14 3	; 0x7f85a1d05890
	240	[186]	MOVE     	0 0
	241	[186]	SETTABLE 	13 -59 14	; "callback" -
	242	[187]	NEWTABLE 	14 0 2
	243	[189]	GETTABLE 	15 0 -60	; "ok_text"
	244	[189]	SETTABLE 	14 -27 15	; "text" -
	245	[197]	CLOSURE  	15 4	; 0x7f85a1d05c90
	246	[197]	MOVE     	0 0
	247	[197]	MOVE     	0 2
	248	[197]	MOVE     	0 3
	249	[197]	SETTABLE 	14 -59 15	; "callback" -
	250	[199]	SETLIST  	12 2 1	; 1
	251	[200]	SETLIST  	11 1 1	; 1
	252	[201]	GETTABLE 	12 0 -61	; "default_values"
	253	[201]	TEST     	12 0 0
	254	[201]	JMP      	14	; to 269
	255	[202]	GETGLOBAL	12 -62	; table
	256	[202]	GETTABLE 	12 12 -63	; "insert"
	257	[202]	MOVE     	13 11
	258	[202]	NEWTABLE 	14 1 0
	259	[202]	NEWTABLE 	15 0 2
	260	[204]	GETTABLE 	16 0 -64	; "default_text"
	261	[204]	SETTABLE 	15 -27 16	; "text" -
	262	[211]	CLOSURE  	16 5	; 0x7f85a1d05eb0
	263	[211]	MOVE     	0 2
	264	[211]	MOVE     	0 0
	265	[211]	MOVE     	0 3
	266	[211]	SETTABLE 	15 -59 16	; "callback" -
	267	[213]	SETLIST  	14 1 1	; 1
	268	[202]	CALL     	12 3 1
	269	[215]	GETTABLE 	12 0 -65	; "extra_text"
	270	[215]	TEST     	12 0 0
	271	[215]	JMP      	14	; to 286
	272	[216]	GETGLOBAL	12 -62	; table
	273	[216]	GETTABLE 	12 12 -63	; "insert"
	274	[216]	MOVE     	13 11
	275	[216]	NEWTABLE 	14 1 0
	276	[216]	NEWTABLE 	15 0 2
	277	[218]	GETTABLE 	16 0 -65	; "extra_text"
	278	[218]	SETTABLE 	15 -27 16	; "text" -
	279	[226]	CLOSURE  	16 6	; 0x7f85a1d063c0
	280	[226]	MOVE     	0 0
	281	[226]	MOVE     	0 2
	282	[226]	MOVE     	0 3
	283	[226]	SETTABLE 	15 -59 16	; "callback" -
	284	[228]	SETLIST  	14 1 1	; 1
	285	[216]	CALL     	12 3 1
	286	[231]	GETUPVAL 	12 14	; ButtonTable
	287	[231]	SELF     	12 12 -1	; "new"
	288	[231]	NEWTABLE 	14 0 4
	289	[232]	GETTABLE 	15 0 -3	; "width"
	290	[232]	GETUPVAL 	16 3	; Size
	291	[232]	GETTABLE 	16 16 -39	; "padding"
	292	[232]	GETTABLE 	16 16 -40	; "default"
	293	[232]	MUL      	16 -33 16	; 2 -
	294	[232]	SUB      	15 15 16
	295	[232]	SETTABLE 	14 -3 15	; "width" -
	296	[233]	SETTABLE 	14 -66 11	; "buttons" -
	297	[234]	SETTABLE 	14 -67 -47	; "zero_sep" true
	298	[235]	SETTABLE 	14 -2 0	; "show_parent" -
	299	[231]	CALL     	12 3 2
	300	[238]	GETUPVAL 	13 8	; FrameContainer
	301	[238]	SELF     	13 13 -1	; "new"
	302	[238]	NEWTABLE 	15 0 4
	303	[239]	GETUPVAL 	16 3	; Size
	304	[239]	GETTABLE 	16 16 -69	; "radius"
	305	[239]	GETTABLE 	16 16 -50	; "window"
	306	[239]	SETTABLE 	15 -69 16	; "radius" -
	307	[240]	SETTABLE 	15 -39 -44	; "padding" 0
	308	[241]	SETTABLE 	15 -41 -44	; "margin" 0
	309	[242]	GETUPVAL 	16 15	; Blitbuffer
	310	[242]	GETTABLE 	16 16 -71	; "COLOR_WHITE"
	311	[242]	SETTABLE 	15 -70 16	; "background" -
	312	[243]	GETUPVAL 	16 1	; VerticalGroup
	313	[243]	SELF     	16 16 -1	; "new"
	314	[243]	NEWTABLE 	18 6 1
	315	[244]	SETTABLE 	18 -23 -72	; "align" "left"
	316	[245]	MOVE     	19 9
	317	[246]	MOVE     	20 8
	318	[247]	MOVE     	21 10
	319	[248]	GETUPVAL 	22 2	; VerticalSpan
	320	[248]	SELF     	22 22 -1	; "new"
	321	[248]	NEWTABLE 	24 0 1
	322	[248]	GETUPVAL 	25 3	; Size
	323	[248]	GETTABLE 	25 25 -25	; "span"
	324	[248]	GETTABLE 	25 25 -26	; "vertical_large"
	325	[248]	SETTABLE 	24 -3 25	; "width" -
	326	[248]	CALL     	22 3 2
	327	[249]	GETUPVAL 	23 6	; CenterContainer
	328	[249]	SELF     	23 23 -1	; "new"
	329	[249]	NEWTABLE 	25 1 1
	330	[250]	GETUPVAL 	26 7	; Geom
	331	[250]	SELF     	26 26 -1	; "new"
	332	[250]	NEWTABLE 	28 0 2
	333	[251]	GETTABLE 	29 0 -3	; "width"
	334	[251]	SETTABLE 	28 -36 29	; "w" -
	335	[252]	SELF     	29 6 -38	; "getSize"
	336	[252]	CALL     	29 2 2
	337	[252]	GETTABLE 	29 29 -37	; "h"
	338	[252]	SETTABLE 	28 -37 29	; "h" -
	339	[250]	CALL     	26 3 2
	340	[253]	SETTABLE 	25 -35 26	; "dimen" -
	341	[255]	MOVE     	26 6
	342	[255]	SETLIST  	25 1 1	; 1
	343	[249]	CALL     	23 3 2
	344	[256]	GETUPVAL 	24 2	; VerticalSpan
	345	[256]	SELF     	24 24 -1	; "new"
	346	[256]	NEWTABLE 	26 0 1
	347	[256]	GETUPVAL 	27 3	; Size
	348	[256]	GETTABLE 	27 27 -25	; "span"
	349	[256]	GETTABLE 	27 27 -26	; "vertical_large"
	350	[256]	SETTABLE 	26 -3 27	; "width" -
	351	[256]	CALL     	24 3 2
	352	[257]	GETUPVAL 	25 6	; CenterContainer
	353	[257]	SELF     	25 25 -1	; "new"
	354	[257]	NEWTABLE 	27 1 1
	355	[258]	GETUPVAL 	28 7	; Geom
	356	[258]	SELF     	28 28 -1	; "new"
	357	[258]	NEWTABLE 	30 0 2
	358	[259]	GETTABLE 	31 0 -3	; "width"
	359	[259]	SETTABLE 	30 -36 31	; "w" -
	360	[260]	SELF     	31 12 -38	; "getSize"
	361	[260]	CALL     	31 2 2
	362	[260]	GETTABLE 	31 31 -37	; "h"
	363	[260]	SETTABLE 	30 -37 31	; "h" -
	364	[258]	CALL     	28 3 2
	365	[261]	SETTABLE 	27 -35 28	; "dimen" -
	366	[263]	MOVE     	28 12
	367	[263]	SETLIST  	27 1 1	; 1
	368	[257]	CALL     	25 3 0
	369	[264]	SETLIST  	18 0 1	; 1
	370	[243]	CALL     	16 3 0
	371	[265]	SETLIST  	15 0 1	; 1
	372	[238]	CALL     	13 3 2
	373	[265]	SETTABLE 	0 -68 13	; "widget_frame" -
	374	[266]	GETUPVAL 	13 16	; MovableContainer
	375	[266]	SELF     	13 13 -1	; "new"
	376	[266]	NEWTABLE 	15 1 0
	377	[268]	GETTABLE 	16 0 -68	; "widget_frame"
	378	[268]	SETLIST  	15 1 1	; 1
	379	[266]	CALL     	13 3 2
	380	[268]	SETTABLE 	0 -73 13	; "movable" -
	381	[269]	GETUPVAL 	13 17	; WidgetContainer
	382	[269]	SELF     	13 13 -1	; "new"
	383	[269]	NEWTABLE 	15 1 2
	384	[270]	SETTABLE 	15 -23 -24	; "align" "center"
	385	[271]	GETUPVAL 	16 7	; Geom
	386	[271]	SELF     	16 16 -1	; "new"
	387	[271]	NEWTABLE 	18 0 4
	388	[272]	SETTABLE 	18 -75 -44	; "x" 0
	389	[272]	SETTABLE 	18 -76 -44	; "y" 0
	390	[273]	GETTABLE 	19 0 -77	; "screen_width"
	391	[273]	SETTABLE 	18 -36 19	; "w" -
	392	[274]	GETTABLE 	19 0 -78	; "screen_height"
	393	[274]	SETTABLE 	18 -37 19	; "h" -
	394	[271]	CALL     	16 3 2
	395	[275]	SETTABLE 	15 -35 16	; "dimen" -
	396	[277]	GETTABLE 	16 0 -73	; "movable"
	397	[277]	SETLIST  	15 1 1	; 1
	398	[269]	CALL     	13 3 2
	399	[277]	SETTABLE 	0 -74 13	; 1 -
	400	[278]	GETUPVAL 	13 18	; UIManager
	401	[278]	SELF     	13 13 -79	; "setDirty"
	402	[278]	MOVE     	15 0
	403	[280]	CLOSURE  	16 7	; 0x7f85a1d05760
	404	[280]	MOVE     	0 0
	405	[278]	CALL     	13 4 1
	406	[287]	CLOSURE  	1 8	; 0x7f85a1d06e90
	407	[287]	GETUPVAL 	0 18	; UIManager
	408	[287]	MOVE     	0 0
	409	[288]	RETURN   	0 1

function <./frontend/ui/widget/doublespinwidget.lua:85,85> (1 instruction, 4 bytes at 0x7f85a1d04f00)
0 params, 2 slots, 0 upvalues, 0 locals, 0 constants, 0 functions
	1	[85]	RETURN   	0 1

function <./frontend/ui/widget/doublespinwidget.lua:95,95> (3 instructions, 12 bytes at 0x7f85a1d052d0)
0 params, 2 slots, 1 upvalue, 0 locals, 0 constants, 0 functions
	1	[95]	GETUPVAL 	0 0	; picker_update_callback
	2	[95]	CALL     	0 1 1
	3	[95]	RETURN   	0 1

function <./frontend/ui/widget/doublespinwidget.lua:106,106> (3 instructions, 12 bytes at 0x7f85a1d05250)
0 params, 2 slots, 1 upvalue, 0 locals, 0 constants, 0 functions
	1	[106]	GETUPVAL 	0 0	; picker_update_callback
	2	[106]	CALL     	0 1 1
	3	[106]	RETURN   	0 1

function <./frontend/ui/widget/doublespinwidget.lua:184,186> (4 instructions, 16 bytes at 0x7f85a1d05890)
0 params, 2 slots, 1 upvalue, 0 locals, 1 constant, 0 functions
	1	[185]	GETUPVAL 	0 0	; self
	2	[185]	SELF     	0 0 -1	; "onClose"
	3	[185]	CALL     	0 2 1
	4	[186]	RETURN   	0 1

function <./frontend/ui/widget/doublespinwidget.lua:190,197> (21 instructions, 84 bytes at 0x7f85a1d05c90)
0 params, 4 slots, 3 upvalues, 0 locals, 4 constants, 0 functions
	1	[191]	GETUPVAL 	0 0	; self
	2	[191]	GETTABLE 	0 0 -1	; "callback"
	3	[191]	TEST     	0 0 0
	4	[191]	JMP      	9	; to 14
	5	[192]	GETUPVAL 	0 0	; self
	6	[192]	GETTABLE 	0 0 -1	; "callback"
	7	[192]	GETUPVAL 	1 1	; left_widget
	8	[192]	SELF     	1 1 -2	; "getValue"
	9	[192]	CALL     	1 2 2
	10	[192]	GETUPVAL 	2 2	; right_widget
	11	[192]	SELF     	2 2 -2	; "getValue"
	12	[192]	CALL     	2 2 0
	13	[192]	CALL     	0 0 1
	14	[194]	GETUPVAL 	0 0	; self
	15	[194]	GETTABLE 	0 0 -3	; "keep_shown_on_apply"
	16	[194]	TEST     	0 0 1
	17	[194]	JMP      	3	; to 21
	18	[195]	GETUPVAL 	0 0	; self
	19	[195]	SELF     	0 0 -4	; "onClose"
	20	[195]	CALL     	0 2 1
	21	[197]	RETURN   	0 1

function <./frontend/ui/widget/doublespinwidget.lua:205,211> (19 instructions, 76 bytes at 0x7f85a1d05eb0)
0 params, 3 slots, 3 upvalues, 0 locals, 5 constants, 0 functions
	1	[206]	GETUPVAL 	0 0	; left_widget
	2	[206]	GETUPVAL 	1 1	; self
	3	[206]	GETTABLE 	1 1 -2	; "left_default"
	4	[206]	SETTABLE 	0 -1 1	; "value" -
	5	[207]	GETUPVAL 	0 2	; right_widget
	6	[207]	GETUPVAL 	1 1	; self
	7	[207]	GETTABLE 	1 1 -3	; "right_default"
	8	[207]	SETTABLE 	0 -1 1	; "value" -
	9	[208]	GETUPVAL 	0 0	; left_widget
	10	[208]	SELF     	0 0 -4	; "update"
	11	[208]	CALL     	0 2 1
	12	[209]	GETUPVAL 	0 2	; right_widget
	13	[209]	SELF     	0 0 -4	; "update"
	14	[209]	CALL     	0 2 1
	15	[210]	GETUPVAL 	0 1	; self
	16	[210]	GETTABLE 	0 0 -5	; "callback"
	17	[210]	LOADNIL  	1 2
	18	[210]	CALL     	0 3 1
	19	[211]	RETURN   	0 1

function <./frontend/ui/widget/doublespinwidget.lua:219,226> (21 instructions, 84 bytes at 0x7f85a1d063c0)
0 params, 4 slots, 3 upvalues, 0 locals, 4 constants, 0 functions
	1	[220]	GETUPVAL 	0 0	; self
	2	[220]	GETTABLE 	0 0 -1	; "extra_callback"
	3	[220]	TEST     	0 0 0
	4	[220]	JMP      	9	; to 14
	5	[221]	GETUPVAL 	0 0	; self
	6	[221]	GETTABLE 	0 0 -1	; "extra_callback"
	7	[221]	GETUPVAL 	1 1	; left_widget
	8	[221]	SELF     	1 1 -2	; "getValue"
	9	[221]	CALL     	1 2 2
	10	[221]	GETUPVAL 	2 2	; right_widget
	11	[221]	SELF     	2 2 -2	; "getValue"
	12	[221]	CALL     	2 2 0
	13	[221]	CALL     	0 0 1
	14	[223]	GETUPVAL 	0 0	; self
	15	[223]	GETTABLE 	0 0 -3	; "keep_shown_on_apply"
	16	[223]	TEST     	0 0 1
	17	[223]	JMP      	3	; to 21
	18	[224]	GETUPVAL 	0 0	; self
	19	[224]	SELF     	0 0 -4	; "onClose"
	20	[224]	CALL     	0 2 1
	21	[226]	RETURN   	0 1

function <./frontend/ui/widget/doublespinwidget.lua:278,280> (6 instructions, 24 bytes at 0x7f85a1d05760)
0 params, 2 slots, 1 upvalue, 0 locals, 3 constants, 0 functions
	1	[279]	LOADK    	0 -1	; "ui"
	2	[279]	GETUPVAL 	1 0	; self
	3	[279]	GETTABLE 	1 1 -2	; "widget_frame"
	4	[279]	GETTABLE 	1 1 -3	; "dimen"
	5	[279]	RETURN   	0 3
	6	[280]	RETURN   	0 1

function <./frontend/ui/widget/doublespinwidget.lua:281,287> (7 instructions, 28 bytes at 0x7f85a1d06e90)
0 params, 4 slots, 2 upvalues, 0 locals, 2 constants, 1 function
	1	[282]	GETUPVAL 	0 0	; UIManager
	2	[282]	SELF     	0 0 -1	; "setDirty"
	3	[282]	LOADK    	2 -2	; "all"
	4	[284]	CLOSURE  	3 0	; 0x7f85a1d05380
	5	[284]	GETUPVAL 	0 1	; self
	6	[282]	CALL     	0 4 1
	7	[287]	RETURN   	0 1

function <./frontend/ui/widget/doublespinwidget.lua:282,284> (6 instructions, 24 bytes at 0x7f85a1d05380)
0 params, 2 slots, 1 upvalue, 0 locals, 3 constants, 0 functions
	1	[283]	LOADK    	0 -1	; "ui"
	2	[283]	GETUPVAL 	1 0	; self
	3	[283]	GETTABLE 	1 1 -2	; "movable"
	4	[283]	GETTABLE 	1 1 -3	; "dimen"
	5	[283]	RETURN   	0 3
	6	[284]	RETURN   	0 1

function <./frontend/ui/widget/doublespinwidget.lua:290,293> (13 instructions, 52 bytes at 0x7f85a1d06520)
1 param, 3 slots, 0 upvalues, 2 locals, 5 constants, 0 functions
	1	[291]	GETTABLE 	1 0 -1	; "movable"
	2	[291]	SELF     	1 1 -2	; "getMovedOffset"
	3	[291]	CALL     	1 2 2
	4	[292]	GETTABLE 	2 1 -3	; "x"
	5	[292]	EQ       	0 2 -4	; - 0
	6	[292]	JMP      	4	; to 11
	7	[292]	GETTABLE 	2 1 -5	; "y"
	8	[292]	EQ       	0 2 -4	; - 0
	9	[292]	JMP      	1	; to 11
	10	[292]	LOADBOOL 	2 0 1
	11	[292]	LOADBOOL 	2 1 0
	12	[292]	RETURN   	2 2
	13	[293]	RETURN   	0 1

function <./frontend/ui/widget/doublespinwidget.lua:295,300> (9 instructions, 36 bytes at 0x7f85a1d06b80)
1 param, 5 slots, 1 upvalue, 1 local, 1 constant, 1 function
	1	[296]	GETUPVAL 	1 0	; UIManager
	2	[296]	SELF     	1 1 -1	; "setDirty"
	3	[296]	LOADNIL  	3 3
	4	[298]	CLOSURE  	4 0	; 0x7f85a1d06160
	5	[298]	MOVE     	0 0
	6	[296]	CALL     	1 4 1
	7	[299]	LOADBOOL 	1 1 0
	8	[299]	RETURN   	1 2
	9	[300]	RETURN   	0 1

function <./frontend/ui/widget/doublespinwidget.lua:296,298> (6 instructions, 24 bytes at 0x7f85a1d06160)
0 params, 2 slots, 1 upvalue, 0 locals, 3 constants, 0 functions
	1	[297]	LOADK    	0 -1	; "partial"
	2	[297]	GETUPVAL 	1 0	; self
	3	[297]	GETTABLE 	1 1 -2	; "widget_frame"
	4	[297]	GETTABLE 	1 1 -3	; "dimen"
	5	[297]	RETURN   	0 3
	6	[298]	RETURN   	0 1

function <./frontend/ui/widget/doublespinwidget.lua:302,307> (9 instructions, 36 bytes at 0x7f85a1d075e0)
1 param, 5 slots, 1 upvalue, 1 local, 1 constant, 1 function
	1	[303]	GETUPVAL 	1 0	; UIManager
	2	[303]	SELF     	1 1 -1	; "setDirty"
	3	[303]	MOVE     	3 0
	4	[305]	CLOSURE  	4 0	; 0x7f85a1d077d0
	5	[305]	MOVE     	0 0
	6	[303]	CALL     	1 4 1
	7	[306]	LOADBOOL 	1 1 0
	8	[306]	RETURN   	1 2
	9	[307]	RETURN   	0 1

function <./frontend/ui/widget/doublespinwidget.lua:303,305> (6 instructions, 24 bytes at 0x7f85a1d077d0)
0 params, 2 slots, 1 upvalue, 0 locals, 3 constants, 0 functions
	1	[304]	LOADK    	0 -1	; "ui"
	2	[304]	GETUPVAL 	1 0	; self
	3	[304]	GETTABLE 	1 1 -2	; "widget_frame"
	4	[304]	GETTABLE 	1 1 -3	; "dimen"
	5	[304]	RETURN   	0 3
	6	[305]	RETURN   	0 1

function <./frontend/ui/widget/doublespinwidget.lua:309,312> (7 instructions, 28 bytes at 0x7f85a1d07bf0)
1 param, 4 slots, 1 upvalue, 1 local, 1 constant, 0 functions
	1	[310]	GETUPVAL 	1 0	; UIManager
	2	[310]	SELF     	1 1 -1	; "close"
	3	[310]	MOVE     	3 0
	4	[310]	CALL     	1 3 1
	5	[311]	LOADBOOL 	1 1 0
	6	[311]	RETURN   	1 2
	7	[312]	RETURN   	0 1

function <./frontend/ui/widget/doublespinwidget.lua:314,319> (12 instructions, 48 bytes at 0x7f85a1d07c80)
3 params, 6 slots, 0 upvalues, 3 locals, 5 constants, 0 functions
	1	[315]	GETTABLE 	3 2 -1	; "pos"
	2	[315]	SELF     	3 3 -2	; "notIntersectWith"
	3	[315]	GETTABLE 	5 0 -3	; "widget_frame"
	4	[315]	GETTABLE 	5 5 -4	; "dimen"
	5	[315]	CALL     	3 3 2
	6	[315]	TEST     	3 0 0
	7	[315]	JMP      	2	; to 10
	8	[316]	SELF     	3 0 -5	; "onClose"
	9	[316]	CALL     	3 2 1
	10	[318]	LOADBOOL 	3 1 0
	11	[318]	RETURN   	3 2
	12	[319]	RETURN   	0 1

function <./frontend/ui/widget/doublespinwidget.lua:321,324> (7 instructions, 28 bytes at 0x7f85a1d08090)
1 param, 4 slots, 1 upvalue, 1 local, 1 constant, 0 functions
	1	[322]	GETUPVAL 	1 0	; UIManager
	2	[322]	SELF     	1 1 -1	; "close"
	3	[322]	MOVE     	3 0
	4	[322]	CALL     	1 3 1
	5	[323]	LOADBOOL 	1 1 0
	6	[323]	RETURN   	1 2
	7	[324]	RETURN   	0 1
