
main <./frontend/ui/downloadmgr.lua:0,0> (29 instructions, 116 bytes at 0x7fca1d4068c0)
0+ params, 7 slots, 0 upvalues, 6 locals, 10 constants, 3 functions
	1	[20]	GETGLOBAL	0 -1	; require
	2	[20]	LOADK    	1 -2	; "ui/widget/pathchooser"
	3	[20]	CALL     	0 2 2
	4	[21]	GETGLOBAL	1 -1	; require
	5	[21]	LOADK    	2 -3	; "ui/uimanager"
	6	[21]	CALL     	1 2 2
	7	[22]	GETGLOBAL	2 -1	; require
	8	[22]	LOADK    	3 -4	; "device"
	9	[22]	CALL     	2 2 2
	10	[22]	GETTABLE 	2 2 -5	; "screen"
	11	[23]	GETGLOBAL	3 -1	; require
	12	[23]	LOADK    	4 -6	; "ffi/util"
	13	[23]	CALL     	3 2 2
	14	[24]	GETGLOBAL	4 -1	; require
	15	[24]	LOADK    	5 -7	; "gettext"
	16	[24]	CALL     	4 2 2
	17	[26]	NEWTABLE 	5 0 1
	18	[28]	CLOSURE  	6 0	; 0x7fca1d504130
	19	[28]	SETTABLE 	5 -8 6	; "onConfirm" -
	20	[36]	CLOSURE  	6 1	; 0x7fca1d504380
	21	[31]	SETTABLE 	5 -9 6	; "new" -
	22	[56]	CLOSURE  	6 2	; 0x7fca1d5045e0
	23	[56]	MOVE     	0 3
	24	[56]	MOVE     	0 0
	25	[56]	MOVE     	0 2
	26	[56]	MOVE     	0 1
	27	[40]	SETTABLE 	5 -10 6	; "chooseDir" -
	28	[58]	RETURN   	5 2
	29	[58]	RETURN   	0 1

function <./frontend/ui/downloadmgr.lua:28,28> (1 instruction, 4 bytes at 0x7fca1d504130)
0 params, 2 slots, 0 upvalues, 0 locals, 0 constants, 0 functions
	1	[28]	RETURN   	0 1

function <./frontend/ui/downloadmgr.lua:31,36> (10 instructions, 40 bytes at 0x7fca1d504380)
2 params, 6 slots, 0 upvalues, 3 locals, 2 constants, 0 functions
	1	[32]	TESTSET  	2 1 1
	2	[32]	JMP      	1	; to 4
	3	[32]	NEWTABLE 	2 0 0
	4	[33]	GETGLOBAL	3 -1	; setmetatable
	5	[33]	MOVE     	4 2
	6	[33]	MOVE     	5 0
	7	[33]	CALL     	3 3 1
	8	[34]	SETTABLE 	0 -2 0	; "__index" -
	9	[35]	RETURN   	2 2
	10	[36]	RETURN   	0 1

function <./frontend/ui/downloadmgr.lua:40,56> (44 instructions, 176 bytes at 0x7fca1d5045e0)
1 param, 9 slots, 4 upvalues, 5 locals, 18 constants, 1 function
	1	[41]	GETGLOBAL	1 -1	; G_reader_settings
	2	[41]	SELF     	1 1 -2	; "readSetting"
	3	[41]	LOADK    	3 -3	; "lastdir"
	4	[41]	CALL     	1 3 2
	5	[42]	GETGLOBAL	2 -1	; G_reader_settings
	6	[42]	SELF     	2 2 -2	; "readSetting"
	7	[42]	LOADK    	4 -4	; "download_dir"
	8	[42]	CALL     	2 3 2
	9	[43]	TEST     	2 0 0
	10	[43]	JMP      	8	; to 19
	11	[43]	GETUPVAL 	3 0	; util
	12	[43]	GETTABLE 	3 3 -5	; "realpath"
	13	[43]	MOVE     	4 2
	14	[43]	LOADK    	5 -6	; "/.."
	15	[43]	CONCAT   	4 4 5
	16	[43]	CALL     	3 2 2
	17	[43]	TEST     	3 0 1
	18	[43]	JMP      	1	; to 20
	19	[43]	MOVE     	3 1
	20	[44]	GETUPVAL 	4 1	; PathChooser
	21	[44]	SELF     	4 4 -7	; "new"
	22	[44]	NEWTABLE 	6 0 7
	23	[45]	GETTABLE 	7 0 -8	; "title"
	24	[45]	TEST     	7 0 1
	25	[45]	JMP      	1	; to 27
	26	[45]	LOADBOOL 	7 1 0
	27	[45]	SETTABLE 	6 -8 7	; "title" -
	28	[46]	SETTABLE 	6 -9 -10	; "select_directory" true
	29	[47]	SETTABLE 	6 -11 -12	; "select_file" false
	30	[48]	SETTABLE 	6 -13 -12	; "show_files" false
	31	[49]	GETUPVAL 	7 2	; Screen
	32	[49]	SELF     	7 7 -15	; "getHeight"
	33	[49]	CALL     	7 2 2
	34	[49]	SETTABLE 	6 -14 7	; "height" -
	35	[50]	SETTABLE 	6 -16 3	; "path" -
	36	[53]	CLOSURE  	7 0	; 0x7fca1d504f20
	37	[53]	MOVE     	0 0
	38	[53]	SETTABLE 	6 -17 7	; "onConfirm" -
	39	[44]	CALL     	4 3 2
	40	[55]	GETUPVAL 	5 3	; UIManager
	41	[55]	SELF     	5 5 -18	; "show"
	42	[55]	MOVE     	7 4
	43	[55]	CALL     	5 3 1
	44	[56]	RETURN   	0 1

function <./frontend/ui/downloadmgr.lua:51,53> (5 instructions, 20 bytes at 0x7fca1d504f20)
1 param, 3 slots, 1 upvalue, 1 local, 1 constant, 0 functions
	1	[52]	GETUPVAL 	1 0	; self
	2	[52]	GETTABLE 	1 1 -1	; "onConfirm"
	3	[52]	MOVE     	2 0
	4	[52]	CALL     	1 2 1
	5	[53]	RETURN   	0 1
