-- BYTECODE -- downloadmgr.lua:28-28
0001    RET0     0   1

-- BYTECODE -- downloadmgr.lua:31-36
0001    ISTC     2   1
0002    JMP      2 => 0004
0003    TNEW     2   0
0004 => GGET     3   0      ; "setmetatable"
0005    MOV      4   2
0006    MOV      5   0
0007    CALL     3   1   3
0008    TSETS    0   0   1  ; "__index"
0009    RET1     2   2

-- BYTECODE -- downloadmgr.lua:51-53
0001    UGET     1   0      ; self
0002    TGETS    1   1   0  ; "onConfirm"
0003    MOV      2   0
0004    CALL     1   1   2
0005    RET0     0   1

-- BYTECODE -- downloadmgr.lua:40-56
0001    GGET     1   0      ; "G_reader_settings"
0002    MOV      2   1
0003    TGETS    1   1   1  ; "readSetting"
0004    KSTR     3   2      ; "lastdir"
0005    CALL     1   2   3
0006    GGET     2   0      ; "G_reader_settings"
0007    MOV      3   2
0008    TGETS    2   2   1  ; "readSetting"
0009    KSTR     4   3      ; "download_dir"
0010    CALL     2   2   3
0011    ISF          2
0012    JMP      3 => 0021
0013    UGET     3   0      ; util
0014    TGETS    3   3   4  ; "realpath"
0015    MOV      4   2
0016    KSTR     5   5      ; "/.."
0017    CAT      4   4   5
0018    CALL     3   2   2
0019    IST          3
0020    JMP      4 => 0022
0021 => MOV      3   1
0022 => UGET     4   1      ; PathChooser
0023    MOV      5   4
0024    TGETS    4   4   6  ; "new"
0025    TDUP     6   8
0026    TGETS    7   0   7  ; "title"
0027    IST          7
0028    JMP      8 => 0030
0029    KPRI     7   2
0030 => TSETS    7   6   7  ; "title"
0031    UGET     7   2      ; Screen
0032    MOV      8   7
0033    TGETS    7   7   9  ; "getHeight"
0034    CALL     7   2   2
0035    TSETS    7   6  10  ; "height"
0036    TSETS    3   6  11  ; "path"
0037    FNEW     7  12      ; downloadmgr.lua:51
0038    TSETS    7   6  13  ; "onConfirm"
0039    CALL     4   2   3
0040    UGET     5   3      ; UIManager
0041    MOV      6   5
0042    TGETS    5   5  14  ; "show"
0043    MOV      7   4
0044    CALL     5   1   3
0045    UCLO     0 => 0046
0046 => RET0     0   1

-- BYTECODE -- downloadmgr.lua:0-59
0001    GGET     0   0      ; "require"
0002    KSTR     1   1      ; "ui/widget/pathchooser"
0003    CALL     0   2   2
0004    GGET     1   0      ; "require"
0005    KSTR     2   2      ; "ui/uimanager"
0006    CALL     1   2   2
0007    GGET     2   0      ; "require"
0008    KSTR     3   3      ; "device"
0009    CALL     2   2   2
0010    TGETS    2   2   4  ; "screen"
0011    GGET     3   0      ; "require"
0012    KSTR     4   5      ; "ffi/util"
0013    CALL     3   2   2
0014    GGET     4   0      ; "require"
0015    KSTR     5   6      ; "gettext"
0016    CALL     4   2   2
0017    TDUP     5   8
0018    FNEW     6   7      ; downloadmgr.lua:28
0019    TSETS    6   5   9  ; "onConfirm"
0020    FNEW     6  11      ; downloadmgr.lua:31
0021    TSETS    6   5  10  ; "new"
0022    FNEW     6  13      ; downloadmgr.lua:40
0023    TSETS    6   5  12  ; "chooseDir"
0024    UCLO     0 => 0025
0025 => RET1     5   2

