
main <./frontend/dump.lua:0,0> (20 instructions, 80 bytes at 0x7fbc6ec068a0)
0+ params, 5 slots, 0 upvalues, 5 locals, 7 constants, 2 functions
	1	[5]	GETGLOBAL	0 -1	; os
	2	[5]	GETTABLE 	0 0 -2	; "getenv"
	3	[5]	LOADK    	1 -3	; "UBUNTU_APPLICATION_ISOLATION"
	4	[5]	CALL     	0 2 2
	5	[5]	EQ       	0 0 -4	; - nil
	6	[5]	JMP      	1	; to 8
	7	[5]	LOADBOOL 	0 0 1
	8	[5]	LOADBOOL 	0 1 0
	9	[6]	GETGLOBAL	1 -5	; table
	10	[6]	GETTABLE 	1 1 -6	; "insert"
	11	[7]	LOADK    	2 -7	; "    "
	12	[67]	CLOSURE  	3 0	; 0x7fbc6ec06c50
	13	[67]	MOVE     	0 1
	14	[67]	MOVE     	0 2
	15	[67]	MOVE     	0 3
	16	[67]	MOVE     	0 0
	17	[80]	CLOSURE  	4 1	; 0x7fbc6ec07590
	18	[80]	MOVE     	0 3
	19	[82]	RETURN   	4 2
	20	[82]	RETURN   	0 1

function <./frontend/dump.lua:9,67> (190 instructions, 760 bytes at 0x7fbc6ec06c50)
5 params, 18 slots, 4 upvalues, 17 locals, 26 constants, 0 functions
	1	[10]	TEST     	3 0 1
	2	[10]	JMP      	2	; to 5
	3	[11]	GETGLOBAL	5 -1	; math
	4	[11]	GETTABLE 	3 5 -2	; "huge"
	5	[14]	LT       	0 3 2
	6	[14]	JMP      	1	; to 8
	7	[15]	RETURN   	0 1
	8	[18]	GETGLOBAL	5 -3	; type
	9	[18]	MOVE     	6 0
	10	[18]	CALL     	5 2 2
	11	[18]	EQ       	0 5 -4	; - "table"
	12	[18]	JMP      	106	; to 119
	13	[19]	TEST     	4 0 1
	14	[19]	JMP      	2	; to 17
	15	[19]	NEWTABLE 	5 0 0
	16	[19]	MOVE     	4 5
	17	[20]	GETGLOBAL	5 -5	; ipairs
	18	[20]	MOVE     	6 4
	19	[20]	CALL     	5 2 4
	20	[20]	JMP      	19	; to 40
	21	[21]	EQ       	0 9 0
	22	[21]	JMP      	17	; to 40
	23	[22]	GETUPVAL 	10 0	; insert
	24	[22]	MOVE     	11 1
	25	[22]	LOADK    	12 -6	; "nil --[[ LOOP:\n"
	26	[22]	CALL     	10 3 1
	27	[23]	GETUPVAL 	10 0	; insert
	28	[23]	MOVE     	11 1
	29	[23]	GETGLOBAL	12 -7	; string
	30	[23]	GETTABLE 	12 12 -8	; "rep"
	31	[23]	GETUPVAL 	13 1	; indent_prefix
	32	[23]	SUB      	14 2 8
	33	[23]	CALL     	12 3 0
	34	[23]	CALL     	10 0 1
	35	[24]	GETUPVAL 	10 0	; insert
	36	[24]	MOVE     	11 1
	37	[24]	LOADK    	12 -9	; "^------- ]]"
	38	[24]	CALL     	10 3 1
	39	[25]	RETURN   	0 1
	40	[20]	TFORLOOP 	5 2
	41	[26]	JMP      	-21	; to 21
	42	[28]	NEWTABLE 	5 1 0
	43	[28]	MOVE     	6 0
	44	[28]	GETGLOBAL	7 -10	; unpack
	45	[28]	MOVE     	8 4
	46	[28]	CALL     	7 2 0
	47	[28]	SETLIST  	5 0 1	; 1
	48	[29]	LOADBOOL 	6 0 0
	49	[30]	GETUPVAL 	7 0	; insert
	50	[30]	MOVE     	8 1
	51	[30]	LOADK    	9 -11	; "{"
	52	[30]	CALL     	7 3 1
	53	[31]	GETGLOBAL	7 -12	; pairs
	54	[31]	MOVE     	8 0
	55	[31]	CALL     	7 2 4
	56	[31]	JMP      	41	; to 98
	57	[32]	TEST     	6 0 0
	58	[32]	JMP      	4	; to 63
	59	[33]	GETUPVAL 	12 0	; insert
	60	[33]	MOVE     	13 1
	61	[33]	LOADK    	14 -13	; ","
	62	[33]	CALL     	12 3 1
	63	[35]	GETUPVAL 	12 0	; insert
	64	[35]	MOVE     	13 1
	65	[35]	LOADK    	14 -14	; "\n"
	66	[35]	CALL     	12 3 1
	67	[36]	GETUPVAL 	12 0	; insert
	68	[36]	MOVE     	13 1
	69	[36]	GETGLOBAL	14 -7	; string
	70	[36]	GETTABLE 	14 14 -8	; "rep"
	71	[36]	GETUPVAL 	15 1	; indent_prefix
	72	[36]	ADD      	16 2 -15	; - 1
	73	[36]	CALL     	14 3 0
	74	[36]	CALL     	12 0 1
	75	[37]	GETUPVAL 	12 0	; insert
	76	[37]	MOVE     	13 1
	77	[37]	LOADK    	14 -16	; "["
	78	[37]	CALL     	12 3 1
	79	[38]	GETUPVAL 	12 2	; _serialize
	80	[38]	MOVE     	13 10
	81	[38]	MOVE     	14 1
	82	[38]	ADD      	15 2 -15	; - 1
	83	[38]	MOVE     	16 3
	84	[38]	MOVE     	17 5
	85	[38]	CALL     	12 6 1
	86	[39]	GETUPVAL 	12 0	; insert
	87	[39]	MOVE     	13 1
	88	[39]	LOADK    	14 -17	; "] = "
	89	[39]	CALL     	12 3 1
	90	[40]	GETUPVAL 	12 2	; _serialize
	91	[40]	MOVE     	13 11
	92	[40]	MOVE     	14 1
	93	[40]	ADD      	15 2 -15	; - 1
	94	[40]	MOVE     	16 3
	95	[40]	MOVE     	17 5
	96	[40]	CALL     	12 6 1
	97	[41]	LOADBOOL 	6 1 0
	98	[31]	TFORLOOP 	7 2
	99	[41]	JMP      	-43	; to 57
	100	[43]	TEST     	6 0 0
	101	[43]	JMP      	12	; to 114
	102	[44]	GETUPVAL 	7 0	; insert
	103	[44]	MOVE     	8 1
	104	[44]	LOADK    	9 -14	; "\n"
	105	[44]	CALL     	7 3 1
	106	[45]	GETUPVAL 	7 0	; insert
	107	[45]	MOVE     	8 1
	108	[45]	GETGLOBAL	9 -7	; string
	109	[45]	GETTABLE 	9 9 -8	; "rep"
	110	[45]	GETUPVAL 	10 1	; indent_prefix
	111	[45]	MOVE     	11 2
	112	[45]	CALL     	9 3 0
	113	[45]	CALL     	7 0 1
	114	[47]	GETUPVAL 	7 0	; insert
	115	[47]	MOVE     	8 1
	116	[47]	LOADK    	9 -18	; "}"
	117	[47]	CALL     	7 3 1
	118	[47]	JMP      	71	; to 190
	119	[48]	GETGLOBAL	5 -3	; type
	120	[48]	MOVE     	6 0
	121	[48]	CALL     	5 2 2
	122	[48]	EQ       	0 5 -7	; - "string"
	123	[48]	JMP      	9	; to 133
	124	[49]	GETUPVAL 	5 0	; insert
	125	[49]	MOVE     	6 1
	126	[49]	GETGLOBAL	7 -7	; string
	127	[49]	GETTABLE 	7 7 -19	; "format"
	128	[49]	LOADK    	8 -20	; "%q"
	129	[49]	MOVE     	9 0
	130	[49]	CALL     	7 3 0
	131	[49]	CALL     	5 0 1
	132	[49]	JMP      	57	; to 190
	133	[50]	GETGLOBAL	5 -3	; type
	134	[50]	MOVE     	6 0
	135	[50]	CALL     	5 2 2
	136	[50]	EQ       	0 5 -21	; - "number"
	137	[50]	JMP      	19	; to 157
	138	[51]	GETUPVAL 	5 3	; isUbuntuTouch
	139	[51]	TEST     	5 0 0
	140	[51]	JMP      	9	; to 150
	141	[56]	GETUPVAL 	5 0	; insert
	142	[56]	MOVE     	6 1
	143	[56]	GETGLOBAL	7 -7	; string
	144	[56]	GETTABLE 	7 7 -19	; "format"
	145	[56]	LOADK    	8 -22	; "%.13e"
	146	[56]	MOVE     	9 0
	147	[56]	CALL     	7 3 0
	148	[56]	CALL     	5 0 1
	149	[56]	JMP      	40	; to 190
	150	[58]	GETUPVAL 	5 0	; insert
	151	[58]	MOVE     	6 1
	152	[58]	GETGLOBAL	7 -23	; tostring
	153	[58]	MOVE     	8 0
	154	[58]	CALL     	7 2 0
	155	[58]	CALL     	5 0 1
	156	[59]	JMP      	33	; to 190
	157	[60]	GETGLOBAL	5 -3	; type
	158	[60]	MOVE     	6 0
	159	[60]	CALL     	5 2 2
	160	[60]	EQ       	0 5 -24	; - "boolean"
	161	[60]	JMP      	7	; to 169
	162	[61]	GETUPVAL 	5 0	; insert
	163	[61]	MOVE     	6 1
	164	[61]	GETGLOBAL	7 -23	; tostring
	165	[61]	MOVE     	8 0
	166	[61]	CALL     	7 2 0
	167	[61]	CALL     	5 0 1
	168	[61]	JMP      	21	; to 190
	169	[62]	GETGLOBAL	5 -3	; type
	170	[62]	MOVE     	6 0
	171	[62]	CALL     	5 2 2
	172	[62]	EQ       	0 5 -25	; - "function"
	173	[62]	JMP      	7	; to 181
	174	[63]	GETUPVAL 	5 0	; insert
	175	[63]	MOVE     	6 1
	176	[63]	GETGLOBAL	7 -23	; tostring
	177	[63]	MOVE     	8 0
	178	[63]	CALL     	7 2 0
	179	[63]	CALL     	5 0 1
	180	[63]	JMP      	9	; to 190
	181	[64]	GETGLOBAL	5 -3	; type
	182	[64]	MOVE     	6 0
	183	[64]	CALL     	5 2 2
	184	[64]	EQ       	0 5 -26	; - "nil"
	185	[64]	JMP      	4	; to 190
	186	[65]	GETUPVAL 	5 0	; insert
	187	[65]	MOVE     	6 1
	188	[65]	LOADK    	7 -26	; "nil"
	189	[65]	CALL     	5 3 1
	190	[67]	RETURN   	0 1

function <./frontend/dump.lua:76,80> (13 instructions, 52 bytes at 0x7fbc6ec07590)
2 params, 8 slots, 1 upvalue, 3 locals, 3 constants, 0 functions
	1	[77]	NEWTABLE 	2 0 0
	2	[78]	GETUPVAL 	3 0	; _serialize
	3	[78]	MOVE     	4 0
	4	[78]	MOVE     	5 2
	5	[78]	LOADK    	6 -1	; 0
	6	[78]	MOVE     	7 1
	7	[78]	CALL     	3 5 1
	8	[79]	GETGLOBAL	3 -2	; table
	9	[79]	GETTABLE 	3 3 -3	; "concat"
	10	[79]	MOVE     	4 2
	11	[79]	TAILCALL 	3 2 0
	12	[79]	RETURN   	3 0
	13	[80]	RETURN   	0 1
