-- BYTECODE -- dump.lua:9-67
0001    IST          3
0002    JMP      5 => 0005
0003    GGET     5   0      ; "math"
0004    TGETS    3   5   1  ; "huge"
0005 => ISGE     3   2
0006    JMP      5 => 0008
0007    RET0     0   1
0008 => GGET     5   2      ; "type"
0009    MOV      6   0
0010    CALL     5   2   2
0011    ISNES    5   3      ; "table"
0012    JMP      5 => 0118
0013    IST          4
0014    JMP      5 => 0016
0015    TNEW     4   0
0016 => GGET     5   4      ; "ipairs"
0017    MOV      6   4
0018    CALL     5   4   2
0019    JMP      8 => 0039
0020 => ISNEV    9   0
0021    JMP     10 => 0039
0022    UGET    10   0      ; insert
0023    MOV     11   1
0024    KSTR    12   5      ; "nil --[[ LOOP:\n"
0025    CALL    10   1   3
0026    UGET    10   0      ; insert
0027    MOV     11   1
0028    GGET    12   6      ; "string"
0029    TGETS   12  12   7  ; "rep"
0030    UGET    13   1      ; indent_prefix
0031    SUBVV   14   2   8
0032    CALL    12   0   3
0033    CALLM   10   1   1
0034    UGET    10   0      ; insert
0035    MOV     11   1
0036    KSTR    12   8      ; "^------- ]]"
0037    CALL    10   1   3
0038    RET0     0   1
0039 => ITERC    8   3   3
0040    ITERL    8 => 0020
0041    TNEW     5   3
0042    TSETB    0   5   1
0043    GGET     6   9      ; "unpack"
0044    MOV      7   4
0045    CALL     6   0   2
0046    TSETM    6   0      ; 2
0047    KPRI     6   1
0048    UGET     7   0      ; insert
0049    MOV      8   1
0050    KSTR     9  10      ; "{"
0051    CALL     7   1   3
0052    GGET     7  11      ; "pairs"
0053    MOV      8   0
0054    CALL     7   4   2
0055    ISNEXT  10 => 0097
0056 => ISF          6
0057    JMP     12 => 0062
0058    UGET    12   0      ; insert
0059    MOV     13   1
0060    KSTR    14  12      ; ","
0061    CALL    12   1   3
0062 => UGET    12   0      ; insert
0063    MOV     13   1
0064    KSTR    14  13      ; "\n"
0065    CALL    12   1   3
0066    UGET    12   0      ; insert
0067    MOV     13   1
0068    GGET    14   6      ; "string"
0069    TGETS   14  14   7  ; "rep"
0070    UGET    15   1      ; indent_prefix
0071    ADDVN   16   2   1  ; 1
0072    CALL    14   0   3
0073    CALLM   12   1   1
0074    UGET    12   0      ; insert
0075    MOV     13   1
0076    KSTR    14  14      ; "["
0077    CALL    12   1   3
0078    UGET    12   2      ; _serialize
0079    MOV     13  10
0080    MOV     14   1
0081    ADDVN   15   2   1  ; 1
0082    MOV     16   3
0083    MOV     17   5
0084    CALL    12   1   6
0085    UGET    12   0      ; insert
0086    MOV     13   1
0087    KSTR    14  15      ; "] = "
0088    CALL    12   1   3
0089    UGET    12   2      ; _serialize
0090    MOV     13  11
0091    MOV     14   1
0092    ADDVN   15   2   1  ; 1
0093    MOV     16   3
0094    MOV     17   5
0095    CALL    12   1   6
0096    KPRI     6   2
0097 => ITERN   10   3   3
0098    ITERL   10 => 0056
0099    ISF          6
0100    JMP      7 => 0113
0101    UGET     7   0      ; insert
0102    MOV      8   1
0103    KSTR     9  13      ; "\n"
0104    CALL     7   1   3
0105    UGET     7   0      ; insert
0106    MOV      8   1
0107    GGET     9   6      ; "string"
0108    TGETS    9   9   7  ; "rep"
0109    UGET    10   1      ; indent_prefix
0110    MOV     11   2
0111    CALL     9   0   3
0112    CALLM    7   1   1
0113 => UGET     7   0      ; insert
0114    MOV      8   1
0115    KSTR     9  16      ; "}"
0116    CALL     7   1   3
0117    JMP      5 => 0189
0118 => GGET     5   2      ; "type"
0119    MOV      6   0
0120    CALL     5   2   2
0121    ISNES    5   6      ; "string"
0122    JMP      5 => 0132
0123    UGET     5   0      ; insert
0124    MOV      6   1
0125    GGET     7   6      ; "string"
0126    TGETS    7   7  17  ; "format"
0127    KSTR     8  18      ; "%q"
0128    MOV      9   0
0129    CALL     7   0   3
0130    CALLM    5   1   1
0131    JMP      5 => 0189
0132 => GGET     5   2      ; "type"
0133    MOV      6   0
0134    CALL     5   2   2
0135    ISNES    5  19      ; "number"
0136    JMP      5 => 0156
0137    UGET     5   3      ; isUbuntuTouch
0138    ISF          5
0139    JMP      6 => 0149
0140    UGET     5   0      ; insert
0141    MOV      6   1
0142    GGET     7   6      ; "string"
0143    TGETS    7   7  17  ; "format"
0144    KSTR     8  20      ; "%.13e"
0145    MOV      9   0
0146    CALL     7   0   3
0147    CALLM    5   1   1
0148    JMP      5 => 0189
0149 => UGET     5   0      ; insert
0150    MOV      6   1
0151    GGET     7  21      ; "tostring"
0152    MOV      8   0
0153    CALL     7   0   2
0154    CALLM    5   1   1
0155    JMP      5 => 0189
0156 => GGET     5   2      ; "type"
0157    MOV      6   0
0158    CALL     5   2   2
0159    ISNES    5  22      ; "boolean"
0160    JMP      5 => 0168
0161    UGET     5   0      ; insert
0162    MOV      6   1
0163    GGET     7  21      ; "tostring"
0164    MOV      8   0
0165    CALL     7   0   2
0166    CALLM    5   1   1
0167    JMP      5 => 0189
0168 => GGET     5   2      ; "type"
0169    MOV      6   0
0170    CALL     5   2   2
0171    ISNES    5  23      ; "function"
0172    JMP      5 => 0180
0173    UGET     5   0      ; insert
0174    MOV      6   1
0175    GGET     7  21      ; "tostring"
0176    MOV      8   0
0177    CALL     7   0   2
0178    CALLM    5   1   1
0179    JMP      5 => 0189
0180 => GGET     5   2      ; "type"
0181    MOV      6   0
0182    CALL     5   2   2
0183    ISNES    5  24      ; "nil"
0184    JMP      5 => 0189
0185    UGET     5   0      ; insert
0186    MOV      6   1
0187    KSTR     7  24      ; "nil"
0188    CALL     5   1   3
0189 => RET0     0   1

-- BYTECODE -- dump.lua:76-80
0001    TNEW     2   0
0002    UGET     3   0      ; _serialize
0003    MOV      4   0
0004    MOV      5   2
0005    KSHORT   6   0
0006    MOV      7   1
0007    CALL     3   1   5
0008    GGET     3   0      ; "table"
0009    TGETS    3   3   1  ; "concat"
0010    MOV      4   2
0011    CALLT    3   2

-- BYTECODE -- dump.lua:0-83
0001    GGET     0   0      ; "os"
0002    TGETS    0   0   1  ; "getenv"
0003    KSTR     1   2      ; "UBUNTU_APPLICATION_ISOLATION"
0004    CALL     0   2   2
0005    ISNEP    0   0
0006    JMP      0 => 0009
0007    KPRI     0   1
0008    JMP      1 => 0010
0009 => KPRI     0   2
0010 => GGET     1   3      ; "table"
0011    TGETS    1   1   4  ; "insert"
0012    KSTR     2   5      ; "    "
0013    FNEW     3   6      ; dump.lua:9
0014    FNEW     4   7      ; dump.lua:76
0015    UCLO     0 => 0016
0016 => RET1     4   2

