-- BYTECODE -- eink_optimization_spec.lua:2-4
0001    GGET     0   0      ; "require"
0002    KSTR     1   1      ; "commonrequire"
0003    CALL     0   1   2
0004    RET0     0   1

-- BYTECODE -- eink_optimization_spec.lua:6-9
0001    GGET     0   0      ; "G_reader_settings"
0002    MOV      1   0
0003    TGETS    0   0   1  ; "saveSetting"
0004    KSTR     2   2      ; "low_pan_rate"
0005    KPRI     3   2
0006    CALL     0   1   4
0007    GGET     0   3      ; "assert"
0008    TGETS    0   0   4  ; "Equals"
0009    GGET     1   5      ; "require"
0010    KSTR     2   6      ; "device"
0011    CALL     1   2   2
0012    TGETS    1   1   7  ; "screen"
0013    TGETS    1   1   2  ; "low_pan_rate"
0014    KPRI     2   2
0015    CALL     0   1   3
0016    RET0     0   1

-- BYTECODE -- eink_optimization_spec.lua:1-10
0001    GGET     0   0      ; "setup"
0002    FNEW     1   1      ; eink_optimization_spec.lua:2
0003    CALL     0   1   2
0004    GGET     0   2      ; "it"
0005    KSTR     1   3      ; "should be correctly loaded"
0006    FNEW     2   4      ; eink_optimization_spec.lua:6
0007    CALL     0   1   3
0008    RET0     0   1

-- BYTECODE -- eink_optimization_spec.lua:0-11
0001    GGET     0   0      ; "describe"
0002    KSTR     1   1      ; "eink optimization setting"
0003    FNEW     2   2      ; eink_optimization_spec.lua:1
0004    CALL     0   1   3
0005    RET0     0   1

