-- BYTECODE -- el_keyboard.lua:0-130
0001    GGET     0   0      ; "require"
0002    KSTR     1   1      ; "ui/data/keyboardlayouts/keypopup/en_popu"~
0003    CALL     0   2   2
0004    TGETS    1   0   2  ; "com"
0005    TGETS    2   0   3  ; "prd"
0006    TGETS    3   0   4  ; "_at"
0007    TGETS    4   0   5  ; "_eq"
0008    GGET     5   0      ; "require"
0009    KSTR     6   6      ; "ui/data/keyboardlayouts/keypopup/el_popu"~
0010    CALL     5   2   2
0011    TGETS    6   5   7  ; "_A_el"
0012    TGETS    7   5   8  ; "_a_el"
0013    TGETS    8   5   9  ; "_B_el"
0014    TGETS    9   5  10  ; "_b_el"
0015    TGETS   10   5  11  ; "_C_el"
0016    TGETS   11   5  12  ; "_c_el"
0017    TGETS   12   5  13  ; "_D_el"
0018    TGETS   13   5  14  ; "_d_el"
0019    TGETS   14   5  15  ; "_E_el"
0020    TGETS   15   5  16  ; "_e_el"
0021    TGETS   16   5  17  ; "_F_el"
0022    TGETS   17   5  18  ; "_f_el"
0023    TGETS   18   5  19  ; "_G_el"
0024    TGETS   19   5  20  ; "_g_el"
0025    TGETS   20   5  21  ; "_H_el"
0026    TGETS   21   5  22  ; "_h_el"
0027    TGETS   22   5  23  ; "_I_el"
0028    TGETS   23   5  24  ; "_i_el"
0029    TGETS   24   5  25  ; "_J_el"
0030    TGETS   25   5  26  ; "_j_el"
0031    TGETS   26   5  27  ; "_K_el"
0032    TGETS   27   5  28  ; "_k_el"
0033    TGETS   28   5  29  ; "_L_el"
0034    TGETS   29   5  30  ; "_l_el"
0035    TGETS   30   5  31  ; "_M_el"
0036    TGETS   31   5  32  ; "_m_el"
0037    TGETS   32   5  33  ; "_N_el"
0038    TGETS   33   5  34  ; "_n_el"
0039    TGETS   34   5  35  ; "_O_el"
0040    TGETS   35   5  36  ; "_o_el"
0041    TGETS   36   5  37  ; "_P_el"
0042    TGETS   37   5  38  ; "_p_el"
0043    TGETS   38   5  39  ; "_R_el"
0044    TGETS   39   5  40  ; "_r_el"
0045    TGETS   40   5  41  ; "_S_el"
0046    TGETS   41   5  42  ; "_s_el"
0047    TGETS   42   5  43  ; "_T_el"
0048    TGETS   43   5  44  ; "_t_el"
0049    TGETS   44   5  45  ; "_U_el"
0050    TGETS   45   5  46  ; "_u_el"
0051    TGETS   46   5  47  ; "_V_el"
0052    TGETS   47   5  48  ; "_v_el"
0053    TGETS   48   5  49  ; "_X_el"
0054    TGETS   49   5  50  ; "_x_el"
0055    TGETS   50   5  51  ; "_Y_el"
0056    TGETS   51   5  52  ; "_y_el"
0057    TGETS   52   5  53  ; "_Z_el"
0058    TGETS   53   5  54  ; "_z_el"
0059    TDUP    54  55
0060    TDUP    55  56
0061    TSETS   55  54  57  ; "shiftmode_keys"
0062    TDUP    55  58
0063    TSETS   55  54  59  ; "symbolmode_keys"
0064    TDUP    55  60
0065    TSETS   55  54  61  ; "utf8mode_keys"
0066    TDUP    55  62
0067    TSETS   55  54  63  ; "umlautmode_keys"
0068    TNEW    55   5
0069    TNEW    56  11
0070    TDUP    57  64
0071    TSETB   57  56   1
0072    TDUP    57  65
0073    TSETB   57  56   2
0074    TDUP    57  66
0075    TSETB   14  57   1
0076    TSETB   15  57   2
0077    TSETB    3  57   3
0078    TSETB   57  56   3
0079    TDUP    57  67
0080    TSETB   38  57   1
0081    TSETB   39  57   2
0082    TSETB   57  56   4
0083    TDUP    57  68
0084    TSETB   42  57   1
0085    TSETB   43  57   2
0086    TSETB    4  57   4
0087    TSETB   57  56   5
0088    TDUP    57  69
0089    TSETB   50  57   1
0090    TSETB   51  57   2
0091    TSETB   57  56   6
0092    TDUP    57  70
0093    TSETB   44  57   1
0094    TSETB   45  57   2
0095    TSETB   57  56   7
0096    TDUP    57  71
0097    TSETB   22  57   1
0098    TSETB   23  57   2
0099    TSETB   57  56   8
0100    TDUP    57  72
0101    TSETB   34  57   1
0102    TSETB   35  57   2
0103    TSETB   57  56   9
0104    TDUP    57  73
0105    TSETB   36  57   1
0106    TSETB   37  57   2
0107    TSETB   57  56  10
0108    TSETB   56  55   1
0109    TNEW    56  10
0110    TDUP    57  74
0111    TSETB    6  57   1
0112    TSETB    7  57   2
0113    TSETB    3  57   4
0114    TSETB   57  56   1
0115    TDUP    57  75
0116    TSETB   40  57   1
0117    TSETB   41  57   2
0118    TSETB   57  56   2
0119    TDUP    57  76
0120    TSETB   12  57   1
0121    TSETB   13  57   2
0122    TSETB   57  56   3
0123    TDUP    57  77
0124    TSETB   16  57   1
0125    TSETB   17  57   2
0126    TSETB   57  56   4
0127    TDUP    57  78
0128    TSETB   18  57   1
0129    TSETB   19  57   2
0130    TSETB   57  56   5
0131    TDUP    57  79
0132    TSETB   20  57   1
0133    TSETB   21  57   2
0134    TSETB   57  56   6
0135    TDUP    57  80
0136    TSETB   24  57   1
0137    TSETB   25  57   2
0138    TSETB   57  56   7
0139    TDUP    57  81
0140    TSETB   26  57   1
0141    TSETB   27  57   2
0142    TSETB   57  56   8
0143    TDUP    57  82
0144    TSETB   28  57   1
0145    TSETB   29  57   2
0146    TSETB   57  56   9
0147    TSETB   56  55   2
0148    TNEW    56  10
0149    TDUP    57  83
0150    TSETB   57  56   1
0151    TDUP    57  84
0152    TSETB   52  57   1
0153    TSETB   53  57   2
0154    TSETB   57  56   2
0155    TDUP    57  85
0156    TSETB   48  57   1
0157    TSETB   49  57   2
0158    TSETB   57  56   3
0159    TDUP    57  86
0160    TSETB   10  57   1
0161    TSETB   11  57   2
0162    TSETB   57  56   4
0163    TDUP    57  87
0164    TSETB   46  57   1
0165    TSETB   47  57   2
0166    TSETB    1  57   4
0167    TSETB   57  56   5
0168    TDUP    57  88
0169    TSETB    8  57   1
0170    TSETB    9  57   2
0171    TSETB    2  57   4
0172    TSETB   57  56   6
0173    TDUP    57  89
0174    TSETB   32  57   1
0175    TSETB   33  57   2
0176    TSETB   57  56   7
0177    TDUP    57  90
0178    TSETB   30  57   1
0179    TSETB   31  57   2
0180    TSETB   57  56   8
0181    TDUP    57  91
0182    TSETB   57  56   9
0183    TSETB   56  55   3
0184    TNEW    56   8
0185    TDUP    57  92
0186    TSETB   57  56   1
0187    TDUP    57  93
0188    TSETB   57  56   2
0189    TDUP    57  94
0190    TSETB   57  56   3
0191    TDUP    57  95
0192    TSETB   57  56   4
0193    TDUP    57  96
0194    TSETB    1  57   1
0195    TSETB    1  57   2
0196    TSETB    1  57   7
0197    TSETB    1  57   8
0198    TSETB   57  56   5
0199    TDUP    57  97
0200    TSETB    2  57   1
0201    TSETB    2  57   2
0202    TSETB    2  57   7
0203    TSETB    2  57   8
0204    TSETB   57  56   6
0205    TDUP    57  98
0206    TSETB   57  56   7
0207    TSETB   56  55   4
0208    TSETS   55  54  99  ; "keys"
0209    RET1    54   2

