-- BYTECODE -- en_keyboard.lua:0-128
0001    GGET     0   0      ; "require"
0002    KSTR     1   1      ; "ui/data/keyboardlayouts/keypopup/en_popu"~
0003    CALL     0   2   2
0004    TGETS    1   0   2  ; "com"
0005    TGETS    2   0   3  ; "prd"
0006    TGETS    3   0   4  ; "_at"
0007    TGETS    4   0   5  ; "_eq"
0008    TGETS    5   0   6  ; "_A_"
0009    TGETS    6   0   7  ; "_a_"
0010    TGETS    7   0   8  ; "_B_"
0011    TGETS    8   0   9  ; "_b_"
0012    TGETS    9   0  10  ; "_C_"
0013    TGETS   10   0  11  ; "_c_"
0014    TGETS   11   0  12  ; "_D_"
0015    TGETS   12   0  13  ; "_d_"
0016    TGETS   13   0  14  ; "_E_"
0017    TGETS   14   0  15  ; "_e_"
0018    TGETS   15   0  16  ; "_F_"
0019    TGETS   16   0  17  ; "_f_"
0020    TGETS   17   0  18  ; "_G_"
0021    TGETS   18   0  19  ; "_g_"
0022    TGETS   19   0  20  ; "_H_"
0023    TGETS   20   0  21  ; "_h_"
0024    TGETS   21   0  22  ; "_I_"
0025    TGETS   22   0  23  ; "_i_"
0026    TGETS   23   0  24  ; "_J_"
0027    TGETS   24   0  25  ; "_j_"
0028    TGETS   25   0  26  ; "_K_"
0029    TGETS   26   0  27  ; "_k_"
0030    TGETS   27   0  28  ; "_L_"
0031    TGETS   28   0  29  ; "_l_"
0032    TGETS   29   0  30  ; "_M_"
0033    TGETS   30   0  31  ; "_m_"
0034    TGETS   31   0  32  ; "_N_"
0035    TGETS   32   0  33  ; "_n_"
0036    TGETS   33   0  34  ; "_O_"
0037    TGETS   34   0  35  ; "_o_"
0038    TGETS   35   0  36  ; "_P_"
0039    TGETS   36   0  37  ; "_p_"
0040    TGETS   37   0  38  ; "_Q_"
0041    TGETS   38   0  39  ; "_q_"
0042    TGETS   39   0  40  ; "_R_"
0043    TGETS   40   0  41  ; "_r_"
0044    TGETS   41   0  42  ; "_S_"
0045    TGETS   42   0  43  ; "_s_"
0046    TGETS   43   0  44  ; "_T_"
0047    TGETS   44   0  45  ; "_t_"
0048    TGETS   45   0  46  ; "_U_"
0049    TGETS   46   0  47  ; "_u_"
0050    TGETS   47   0  48  ; "_V_"
0051    TGETS   48   0  49  ; "_v_"
0052    TGETS   49   0  50  ; "_W_"
0053    TGETS   50   0  51  ; "_w_"
0054    TGETS   51   0  52  ; "_X_"
0055    TGETS   52   0  53  ; "_x_"
0056    TGETS   53   0  54  ; "_Y_"
0057    TGETS   54   0  55  ; "_y_"
0058    TGETS   55   0  56  ; "_Z_"
0059    TGETS   56   0  57  ; "_z_"
0060    TDUP    57  58
0061    TDUP    58  59
0062    TSETS   58  57  60  ; "shiftmode_keys"
0063    TDUP    58  61
0064    TSETS   58  57  62  ; "symbolmode_keys"
0065    TDUP    58  63
0066    TSETS   58  57  64  ; "utf8mode_keys"
0067    TDUP    58  65
0068    TSETS   58  57  66  ; "umlautmode_keys"
0069    TNEW    58   5
0070    TNEW    59  11
0071    TDUP    60  67
0072    TSETB   37  60   1
0073    TSETB   38  60   2
0074    TSETB   60  59   1
0075    TDUP    60  68
0076    TSETB   49  60   1
0077    TSETB   50  60   2
0078    TSETB   60  59   2
0079    TDUP    60  69
0080    TSETB   13  60   1
0081    TSETB   14  60   2
0082    TSETB    3  60   3
0083    TSETB   60  59   3
0084    TDUP    60  70
0085    TSETB   39  60   1
0086    TSETB   40  60   2
0087    TSETB   60  59   4
0088    TDUP    60  71
0089    TSETB   43  60   1
0090    TSETB   44  60   2
0091    TSETB    4  60   4
0092    TSETB   60  59   5
0093    TDUP    60  72
0094    TSETB   53  60   1
0095    TSETB   54  60   2
0096    TSETB   60  59   6
0097    TDUP    60  73
0098    TSETB   45  60   1
0099    TSETB   46  60   2
0100    TSETB   60  59   7
0101    TDUP    60  74
0102    TSETB   21  60   1
0103    TSETB   22  60   2
0104    TSETB   60  59   8
0105    TDUP    60  75
0106    TSETB   33  60   1
0107    TSETB   34  60   2
0108    TSETB   60  59   9
0109    TDUP    60  76
0110    TSETB   35  60   1
0111    TSETB   36  60   2
0112    TSETB   60  59  10
0113    TSETB   59  58   1
0114    TNEW    59  10
0115    TDUP    60  77
0116    TSETB    5  60   1
0117    TSETB    6  60   2
0118    TSETB    3  60   4
0119    TSETB   60  59   1
0120    TDUP    60  78
0121    TSETB   41  60   1
0122    TSETB   42  60   2
0123    TSETB   60  59   2
0124    TDUP    60  79
0125    TSETB   11  60   1
0126    TSETB   12  60   2
0127    TSETB   60  59   3
0128    TDUP    60  80
0129    TSETB   15  60   1
0130    TSETB   16  60   2
0131    TSETB   60  59   4
0132    TDUP    60  81
0133    TSETB   17  60   1
0134    TSETB   18  60   2
0135    TSETB   60  59   5
0136    TDUP    60  82
0137    TSETB   19  60   1
0138    TSETB   20  60   2
0139    TSETB   60  59   6
0140    TDUP    60  83
0141    TSETB   23  60   1
0142    TSETB   24  60   2
0143    TSETB   60  59   7
0144    TDUP    60  84
0145    TSETB   25  60   1
0146    TSETB   26  60   2
0147    TSETB   60  59   8
0148    TDUP    60  85
0149    TSETB   27  60   1
0150    TSETB   28  60   2
0151    TSETB   60  59   9
0152    TSETB   59  58   2
0153    TNEW    59  10
0154    TDUP    60  86
0155    TSETB   60  59   1
0156    TDUP    60  87
0157    TSETB   55  60   1
0158    TSETB   56  60   2
0159    TSETB   60  59   2
0160    TDUP    60  88
0161    TSETB   51  60   1
0162    TSETB   52  60   2
0163    TSETB   60  59   3
0164    TDUP    60  89
0165    TSETB    9  60   1
0166    TSETB   10  60   2
0167    TSETB   60  59   4
0168    TDUP    60  90
0169    TSETB   47  60   1
0170    TSETB   48  60   2
0171    TSETB    1  60   4
0172    TSETB   60  59   5
0173    TDUP    60  91
0174    TSETB    7  60   1
0175    TSETB    8  60   2
0176    TSETB    2  60   4
0177    TSETB   60  59   6
0178    TDUP    60  92
0179    TSETB   31  60   1
0180    TSETB   32  60   2
0181    TSETB   60  59   7
0182    TDUP    60  93
0183    TSETB   29  60   1
0184    TSETB   30  60   2
0185    TSETB   60  59   8
0186    TDUP    60  94
0187    TSETB   60  59   9
0188    TSETB   59  58   3
0189    TNEW    59   8
0190    TDUP    60  95
0191    TSETB   60  59   1
0192    TDUP    60  96
0193    TSETB   60  59   2
0194    TDUP    60  97
0195    TSETB   60  59   3
0196    TDUP    60  98
0197    TSETB   60  59   4
0198    TDUP    60  99
0199    TSETB    1  60   1
0200    TSETB    1  60   2
0201    TSETB    1  60   7
0202    TSETB    1  60   8
0203    TSETB   60  59   5
0204    TDUP    60 100
0205    TSETB    2  60   1
0206    TSETB    2  60   2
0207    TSETB    2  60   7
0208    TSETB    2  60   8
0209    TSETB   60  59   6
0210    TDUP    60 101
0211    TSETB   60  59   7
0212    TSETB   59  58   4
0213    TSETS   58  57 102  ; "keys"
0214    RET1    57   2

