
main <./frontend/ui/data/keyboardlayouts/es_keyboard.lua:0,0> (23 instructions, 92 bytes at 0x7fb3e4406900)
0+ params, 13 slots, 0 upvalues, 2 locals, 11 constants, 0 functions
	1	[2]	GETGLOBAL	0 -1	; dofile
	2	[2]	LOADK    	1 -2	; "frontend/ui/data/keyboardlayouts/en_keyboard.lua"
	3	[2]	CALL     	0 2 2
	4	[4]	GETTABLE 	1 0 -3	; "keys"
	5	[7]	GETGLOBAL	2 -4	; table
	6	[7]	GETTABLE 	2 2 -5	; "insert"
	7	[7]	GETTABLE 	3 1 -6	; 2
	8	[7]	NEWTABLE 	4 8 0
	9	[9]	LOADK    	5 -7	; "\195\145"
	10	[9]	LOADK    	6 -8	; "\195\177"
	11	[9]	LOADK    	7 -7	; "\195\145"
	12	[9]	LOADK    	8 -8	; "\195\177"
	13	[9]	LOADK    	9 -7	; "\195\145"
	14	[9]	LOADK    	10 -8	; "\195\177"
	15	[9]	LOADK    	11 -7	; "\195\145"
	16	[9]	LOADK    	12 -8	; "\195\177"
	17	[9]	SETLIST  	4 8 1	; 1
	18	[7]	CALL     	2 3 1
	19	[13]	GETTABLE 	2 1 -9	; 4
	20	[13]	GETTABLE 	2 2 -9	; 4
	21	[13]	SETTABLE 	2 -10 -11	; "label" "espacio"
	22	[15]	RETURN   	0 2
	23	[15]	RETURN   	0 1
