
main <./frontend/ui/widget/eventlistener.lua:0,0> (7 instructions, 28 bytes at 0x7fe7a85040a0)
0+ params, 2 slots, 0 upvalues, 1 local, 2 constants, 2 functions
	1	[10]	NEWTABLE 	0 0 0
	2	[18]	CLOSURE  	1 0	; 0x7fe7a8504350
	3	[12]	SETTABLE 	0 -1 1	; "new" -
	4	[33]	CLOSURE  	1 1	; 0x7fe7a85045b0
	5	[29]	SETTABLE 	0 -2 1	; "handleEvent" -
	6	[35]	RETURN   	0 2
	7	[35]	RETURN   	0 1

function <./frontend/ui/widget/eventlistener.lua:12,18> (15 instructions, 60 bytes at 0x7fe7a8504350)
2 params, 6 slots, 0 upvalues, 3 locals, 3 constants, 0 functions
	1	[13]	TESTSET  	2 1 1
	2	[13]	JMP      	1	; to 4
	3	[13]	NEWTABLE 	2 0 0
	4	[14]	GETGLOBAL	3 -1	; setmetatable
	5	[14]	MOVE     	4 2
	6	[14]	MOVE     	5 0
	7	[14]	CALL     	3 3 1
	8	[15]	SETTABLE 	0 -2 0	; "__index" -
	9	[16]	GETTABLE 	3 2 -3	; "init"
	10	[16]	TEST     	3 0 0
	11	[16]	JMP      	2	; to 14
	12	[16]	SELF     	3 2 -3	; "init"
	13	[16]	CALL     	3 2 1
	14	[17]	RETURN   	2 2
	15	[18]	RETURN   	0 1

function <./frontend/ui/widget/eventlistener.lua:29,33> (13 instructions, 52 bytes at 0x7fe7a85045b0)
2 params, 6 slots, 0 upvalues, 2 locals, 3 constants, 0 functions
	1	[30]	GETTABLE 	2 1 -1	; "handler"
	2	[30]	GETTABLE 	2 0 2
	3	[30]	TEST     	2 0 0
	4	[30]	JMP      	8	; to 13
	5	[31]	GETTABLE 	2 1 -1	; "handler"
	6	[31]	GETTABLE 	2 0 2
	7	[31]	MOVE     	3 0
	8	[31]	GETGLOBAL	4 -2	; unpack
	9	[31]	GETTABLE 	5 1 -3	; "args"
	10	[31]	CALL     	4 2 0
	11	[31]	TAILCALL 	2 0 0
	12	[31]	RETURN   	2 0
	13	[33]	RETURN   	0 1
