-- BYTECODE -- event.lua:30-38
0001    TDUP     2   1
0002    KSTR     3   0      ; "on"
0003    MOV      4   1
0004    CAT      3   3   4
0005    TSETS    3   2   2  ; "handler"
0006    TNEW     3   3
0007    VARG     4   0   2
0008    TSETM    4   0      ; 1
0009    TSETS    3   2   3  ; "args"
0010    GGET     3   4      ; "setmetatable"
0011    MOV      4   2
0012    MOV      5   0
0013    CALL     3   1   3
0014    TSETS    0   0   5  ; "__index"
0015    RET1     2   2

-- BYTECODE -- event.lua:0-41
0001    TNEW     0   0
0002    FNEW     1   1      ; event.lua:30
0003    TSETS    1   0   0  ; "new"
0004    UCLO     0 => 0005
0005 => RET1     0   2

