
main <./spec/unit/evernote_plugin_main_spec.lua:0,0> (5 instructions, 20 bytes at 0x7fb65fc068f0)
0+ params, 3 slots, 0 upvalues, 0 locals, 2 constants, 1 function
	1	[1]	GETGLOBAL	0 -1	; describe
	2	[1]	LOADK    	1 -2	; "Evernote plugin module"
	3	[102]	CLOSURE  	2 0	; 0x7fb65fc06b90
	4	[1]	CALL     	0 3 1
	5	[102]	RETURN   	0 1

function <./spec/unit/evernote_plugin_main_spec.lua:1,102> (23 instructions, 92 bytes at 0x7fb65fc06b90)
0 params, 8 slots, 0 upvalues, 5 locals, 4 constants, 3 functions
	1	[5]	GETGLOBAL	5 -1	; setup
	2	[68]	CLOSURE  	6 0	; 0x7fb65fc06d00
	3	[68]	MOVE     	0 1
	4	[68]	MOVE     	0 4
	5	[68]	MOVE     	0 3
	6	[68]	MOVE     	0 0
	7	[68]	MOVE     	0 2
	8	[5]	CALL     	5 2 1
	9	[70]	GETGLOBAL	5 -2	; it
	10	[70]	LOADK    	6 -3	; "should write clippings to txt file"
	11	[91]	CLOSURE  	7 1	; 0x7fb65fc06df0
	12	[91]	MOVE     	0 0
	13	[91]	MOVE     	0 2
	14	[91]	MOVE     	0 1
	15	[70]	CALL     	5 3 1
	16	[93]	GETGLOBAL	5 -2	; it
	17	[93]	LOADK    	6 -4	; "should not export booknotes with exported_stamp"
	18	[99]	CLOSURE  	7 2	; 0x7fb65fc07d30
	19	[99]	MOVE     	0 0
	20	[99]	MOVE     	0 2
	21	[99]	MOVE     	0 1
	22	[93]	CALL     	5 3 1
	23	[102]	RETURN   	0 1

function <./spec/unit/evernote_plugin_main_spec.lua:5,68> (78 instructions, 312 bytes at 0x7fb65fc06d00)
0 params, 7 slots, 5 upvalues, 1 local, 43 constants, 0 functions
	1	[6]	GETGLOBAL	0 -1	; require
	2	[6]	LOADK    	1 -2	; "commonrequire"
	3	[6]	CALL     	0 2 1
	4	[7]	GETGLOBAL	0 -1	; require
	5	[7]	LOADK    	1 -3	; "luassert.match"
	6	[7]	CALL     	0 2 2
	7	[7]	SETUPVAL 	0 0	; match
	8	[8]	GETGLOBAL	0 -1	; require
	9	[8]	LOADK    	1 -4	; "apps/reader/readerui"
	10	[8]	CALL     	0 2 2
	11	[9]	GETGLOBAL	1 -1	; require
	12	[9]	LOADK    	2 -5	; "document/documentregistry"
	13	[9]	CALL     	1 2 2
	14	[9]	SETUPVAL 	1 1	; DocumentRegistry
	15	[10]	LOADK    	1 -6	; "spec/front/unit/data/juliet.epub"
	16	[10]	SETUPVAL 	1 2	; sample_epub
	17	[11]	SELF     	1 0 -7	; "new"
	18	[11]	NEWTABLE 	3 0 1
	19	[12]	GETUPVAL 	4 1	; DocumentRegistry
	20	[12]	SELF     	4 4 -9	; "openDocument"
	21	[12]	GETUPVAL 	6 2	; sample_epub
	22	[12]	CALL     	4 3 2
	23	[12]	SETTABLE 	3 -8 4	; "document" -
	24	[11]	CALL     	1 3 2
	25	[13]	SETUPVAL 	1 3	; readerui
	26	[15]	NEWTABLE 	1 0 2
	27	[16]	NEWTABLE 	2 0 5
	28	[17]	NEWTABLE 	3 0 1
	29	[18]	NEWTABLE 	4 0 4
	30	[19]	SETTABLE 	4 -12 -13	; "page" 6
	31	[20]	SETTABLE 	4 -14 -15	; "time" 1578946897
	32	[21]	SETTABLE 	4 -16 -17	; "sort" "highlight"
	33	[22]	SETTABLE 	4 -18 -19	; "text" "Some important stuff 1"
	34	[23]	SETTABLE 	3 -11 4	; 1 -
	35	[24]	SETTABLE 	2 -11 3	; 1 -
	36	[25]	NEWTABLE 	3 0 1
	37	[26]	NEWTABLE 	4 0 4
	38	[27]	SETTABLE 	4 -12 -21	; "page" 13
	39	[28]	SETTABLE 	4 -14 -22	; "time" 1578946903
	40	[29]	SETTABLE 	4 -16 -17	; "sort" "highlight"
	41	[30]	SETTABLE 	4 -18 -23	; "text" "Some important stuff 2"
	42	[31]	SETTABLE 	3 -11 4	; 1 -
	43	[32]	SETTABLE 	2 -20 3	; 2 -
	44	[33]	SETTABLE 	2 -24 -25	; "file" "path/to/title1"
	45	[34]	NEWTABLE 	3 0 2
	46	[35]	SETTABLE 	3 -27 -28	; "txt" true
	47	[36]	SETTABLE 	3 -29 -28	; "html" true
	48	[37]	SETTABLE 	2 -26 3	; "exported" -
	49	[38]	SETTABLE 	2 -30 -10	; "title" "Title1"
	50	[39]	SETTABLE 	1 -10 2	; "Title1" -
	51	[40]	NEWTABLE 	2 0 5
	52	[41]	NEWTABLE 	3 0 1
	53	[42]	NEWTABLE 	4 0 4
	54	[43]	SETTABLE 	4 -12 -32	; "page" 233
	55	[44]	SETTABLE 	4 -14 -33	; "time" 1578946918
	56	[45]	SETTABLE 	4 -16 -17	; "sort" "highlight"
	57	[46]	SETTABLE 	4 -18 -34	; "text" "Some important stuff 3"
	58	[47]	SETTABLE 	3 -11 4	; 1 -
	59	[48]	SETTABLE 	2 -11 3	; 1 -
	60	[49]	NEWTABLE 	3 0 1
	61	[50]	NEWTABLE 	4 0 5
	62	[51]	SETTABLE 	4 -12 -35	; "page" 237
	63	[52]	SETTABLE 	4 -14 -36	; "time" 1578947501
	64	[53]	SETTABLE 	4 -16 -17	; "sort" "highlight"
	65	[54]	SETTABLE 	4 -18 -37	; "text" ""
	66	[55]	NEWTABLE 	5 0 2
	67	[56]	SETTABLE 	5 -39 -40	; "hash" "cb7b40a63afc89f0aa452f2b655877e6"
	68	[57]	SETTABLE 	5 -41 -42	; "png" "Binary Encoding of image"
	69	[58]	SETTABLE 	4 -38 5	; "image" -
	70	[59]	SETTABLE 	3 -11 4	; 1 -
	71	[60]	SETTABLE 	2 -20 3	; 2 -
	72	[61]	SETTABLE 	2 -24 -43	; "file" "path/to/title2"
	73	[62]	NEWTABLE 	3 0 0
	74	[63]	SETTABLE 	2 -26 3	; "exported" -
	75	[64]	SETTABLE 	2 -30 -31	; "title" "Title2"
	76	[65]	SETTABLE 	1 -31 2	; "Title2" -
	77	[66]	SETUPVAL 	1 4	; sample_clippings
	78	[68]	RETURN   	0 1

function <./spec/unit/evernote_plugin_main_spec.lua:70,91> (49 instructions, 196 bytes at 0x7fb65fc06df0)
0 params, 6 slots, 3 upvalues, 2 locals, 16 constants, 3 functions
	1	[71]	GETGLOBAL	0 -1	; mock
	2	[71]	NEWTABLE 	1 0 2
	3	[72]	CLOSURE  	2 0	; 0x7fb65fc07e70
	4	[72]	SETTABLE 	1 -2 2	; "write" -
	5	[73]	CLOSURE  	2 1	; 0x7fb65fc07ef0
	6	[73]	SETTABLE 	1 -3 2	; "close" -
	7	[71]	CALL     	0 2 2
	8	[75]	GETGLOBAL	1 -4	; _G
	9	[75]	GETTABLE 	1 1 -5	; "io"
	10	[76]	GETGLOBAL	2 -4	; _G
	11	[76]	GETGLOBAL	3 -1	; mock
	12	[76]	NEWTABLE 	4 0 1
	13	[83]	CLOSURE  	5 2	; 0x7fb65fc07df0
	14	[83]	GETUPVAL 	0 0	; readerui
	15	[83]	MOVE     	0 0
	16	[83]	MOVE     	0 1
	17	[83]	SETTABLE 	4 -6 5	; "open" -
	18	[76]	CALL     	3 2 2
	19	[84]	SETTABLE 	2 -5 3	; "io" -
	20	[86]	GETUPVAL 	2 0	; readerui
	21	[86]	GETTABLE 	2 2 -7	; "evernote"
	22	[86]	SELF     	2 2 -8	; "exportBooknotesToTXT"
	23	[86]	LOADK    	4 -9	; "Title1"
	24	[86]	GETUPVAL 	5 1	; sample_clippings
	25	[86]	GETTABLE 	5 5 -9	; "Title1"
	26	[86]	CALL     	2 4 1
	27	[87]	GETGLOBAL	2 -10	; assert
	28	[87]	GETTABLE 	2 2 -11	; "spy"
	29	[87]	GETGLOBAL	3 -5	; io
	30	[87]	GETTABLE 	3 3 -6	; "open"
	31	[87]	CALL     	2 2 2
	32	[87]	GETTABLE 	2 2 -12	; "was"
	33	[87]	GETTABLE 	2 2 -13	; "called"
	34	[87]	CALL     	2 1 1
	35	[88]	GETGLOBAL	2 -10	; assert
	36	[88]	GETTABLE 	2 2 -11	; "spy"
	37	[88]	GETTABLE 	3 0 -2	; "write"
	38	[88]	CALL     	2 2 2
	39	[88]	GETTABLE 	2 2 -12	; "was"
	40	[88]	GETTABLE 	2 2 -14	; "called_with"
	41	[88]	GETUPVAL 	3 2	; match
	42	[88]	GETTABLE 	3 3 -15	; "is_ref"
	43	[88]	MOVE     	4 0
	44	[88]	CALL     	3 2 2
	45	[88]	LOADK    	4 -16	; "Some important stuff 1"
	46	[88]	CALL     	2 3 1
	47	[89]	GETGLOBAL	2 -4	; _G
	48	[89]	SETTABLE 	2 -5 1	; "io" -
	49	[91]	RETURN   	0 1

function <./spec/unit/evernote_plugin_main_spec.lua:72,72> (2 instructions, 8 bytes at 0x7fb65fc07e70)
0 params, 2 slots, 0 upvalues, 0 locals, 0 constants, 0 functions
	1	[72]	RETURN   	0 1
	2	[72]	RETURN   	0 1

function <./spec/unit/evernote_plugin_main_spec.lua:73,73> (2 instructions, 8 bytes at 0x7fb65fc07ef0)
0 params, 2 slots, 0 upvalues, 0 locals, 0 constants, 0 functions
	1	[73]	RETURN   	0 1
	2	[73]	RETURN   	0 1

function <./spec/unit/evernote_plugin_main_spec.lua:77,83> (15 instructions, 60 bytes at 0x7fb65fc07df0)
2 params, 5 slots, 3 upvalues, 2 locals, 3 constants, 0 functions
	1	[78]	GETUPVAL 	2 0	; readerui
	2	[78]	GETTABLE 	2 2 -1	; "evernote"
	3	[78]	GETTABLE 	2 2 -2	; "text_clipping_file"
	4	[78]	EQ       	0 0 2
	5	[78]	JMP      	3	; to 9
	6	[79]	GETUPVAL 	2 1	; file_mock
	7	[79]	RETURN   	2 2
	8	[79]	JMP      	6	; to 15
	9	[81]	GETUPVAL 	2 2	; old_io
	10	[81]	GETTABLE 	2 2 -3	; "open"
	11	[81]	MOVE     	3 0
	12	[81]	MOVE     	4 1
	13	[81]	TAILCALL 	2 3 0
	14	[81]	RETURN   	2 0
	15	[83]	RETURN   	0 1

function <./spec/unit/evernote_plugin_main_spec.lua:93,99> (44 instructions, 176 bytes at 0x7fb65fc07d30)
0 params, 4 slots, 3 upvalues, 0 locals, 12 constants, 0 functions
	1	[94]	GETUPVAL 	0 0	; readerui
	2	[94]	GETTABLE 	0 0 -1	; "evernote"
	3	[94]	SETTABLE 	0 -2 -3	; "html_export" true
	4	[95]	GETGLOBAL	0 -4	; stub
	5	[95]	GETUPVAL 	1 0	; readerui
	6	[95]	GETTABLE 	1 1 -1	; "evernote"
	7	[95]	LOADK    	2 -5	; "exportBooknotesToHTML"
	8	[95]	CALL     	0 3 1
	9	[96]	GETUPVAL 	0 0	; readerui
	10	[96]	GETTABLE 	0 0 -1	; "evernote"
	11	[96]	SELF     	0 0 -6	; "exportClippings"
	12	[96]	GETUPVAL 	2 1	; sample_clippings
	13	[96]	CALL     	0 3 1
	14	[97]	GETGLOBAL	0 -7	; assert
	15	[97]	GETTABLE 	0 0 -4	; "stub"
	16	[97]	GETUPVAL 	1 0	; readerui
	17	[97]	GETTABLE 	1 1 -1	; "evernote"
	18	[97]	GETTABLE 	1 1 -5	; "exportBooknotesToHTML"
	19	[97]	CALL     	0 2 2
	20	[97]	GETTABLE 	0 0 -8	; "was_called_with"
	21	[97]	GETUPVAL 	1 2	; match
	22	[97]	GETTABLE 	1 1 -9	; "is_truthy"
	23	[97]	CALL     	1 1 2
	24	[97]	LOADK    	2 -10	; "Title2"
	25	[97]	GETUPVAL 	3 2	; match
	26	[97]	GETTABLE 	3 3 -9	; "is_truthy"
	27	[97]	CALL     	3 1 0
	28	[97]	CALL     	0 0 1
	29	[98]	GETGLOBAL	0 -7	; assert
	30	[98]	GETTABLE 	0 0 -4	; "stub"
	31	[98]	GETUPVAL 	1 0	; readerui
	32	[98]	GETTABLE 	1 1 -1	; "evernote"
	33	[98]	GETTABLE 	1 1 -5	; "exportBooknotesToHTML"
	34	[98]	CALL     	0 2 2
	35	[98]	GETTABLE 	0 0 -11	; "was_not_called_with"
	36	[98]	GETUPVAL 	1 2	; match
	37	[98]	GETTABLE 	1 1 -9	; "is_truthy"
	38	[98]	CALL     	1 1 2
	39	[98]	LOADK    	2 -12	; "Title1"
	40	[98]	GETUPVAL 	3 2	; match
	41	[98]	GETTABLE 	3 3 -9	; "is_truthy"
	42	[98]	CALL     	3 1 0
	43	[98]	CALL     	0 0 1
	44	[99]	RETURN   	0 1
