
main <./plugins/newsdownloader.koplugin/feed_config.lua:0,0> (14 instructions, 56 bytes at 0x7fc343c06900)
0+ params, 4 slots, 0 upvalues, 0 locals, 8 constants, 0 functions
	1	[1]	NEWTABLE 	0 2 0
	2	[1]	NEWTABLE 	1 1 2
	3	[29]	LOADK    	2 -1	; "http://feeds.reuters.com/Reuters/worldNews?format=xml"
	4	[29]	SETTABLE 	1 -2 -3	; "limit" 2
	5	[29]	SETTABLE 	1 -4 -5	; "download_full_article" true
	6	[29]	SETLIST  	1 1 1	; 1
	7	[29]	NEWTABLE 	2 1 2
	8	[31]	LOADK    	3 -6	; "https://www.pcworld.com/index.rss"
	9	[31]	SETTABLE 	2 -2 -7	; "limit" 7
	10	[31]	SETTABLE 	2 -4 -8	; "download_full_article" false
	11	[31]	SETLIST  	2 1 1	; 1
	12	[35]	SETLIST  	0 2 1	; 1
	13	[35]	RETURN   	0 2
	14	[35]	RETURN   	0 1
