
main <./frontend/apps/filemanager/filemanagersearch.lua:0,0> (144 instructions, 576 bytes at 0x7fbf27406900)
0+ params, 21 slots, 0 upvalues, 19 locals, 61 constants, 9 functions
	1	[1]	GETGLOBAL	0 -1	; require
	2	[1]	LOADK    	1 -2	; "ui/widget/container/centercontainer"
	3	[1]	CALL     	0 2 2
	4	[2]	GETGLOBAL	1 -1	; require
	5	[2]	LOADK    	2 -3	; "document/documentregistry"
	6	[2]	CALL     	1 2 2
	7	[3]	GETGLOBAL	2 -1	; require
	8	[3]	LOADK    	3 -4	; "ui/font"
	9	[3]	CALL     	2 2 2
	10	[4]	GETGLOBAL	3 -1	; require
	11	[4]	LOADK    	4 -5	; "ui/widget/inputdialog"
	12	[4]	CALL     	3 2 2
	13	[5]	GETGLOBAL	4 -1	; require
	14	[5]	LOADK    	5 -6	; "ui/widget/infomessage"
	15	[5]	CALL     	4 2 2
	16	[6]	GETGLOBAL	5 -1	; require
	17	[6]	LOADK    	6 -7	; "ui/widget/container/inputcontainer"
	18	[6]	CALL     	5 2 2
	19	[7]	GETGLOBAL	6 -1	; require
	20	[7]	LOADK    	7 -8	; "ui/widget/menu"
	21	[7]	CALL     	6 2 2
	22	[8]	GETGLOBAL	7 -1	; require
	23	[8]	LOADK    	8 -9	; "device"
	24	[8]	CALL     	7 2 2
	25	[8]	GETTABLE 	7 7 -10	; "screen"
	26	[9]	GETGLOBAL	8 -1	; require
	27	[9]	LOADK    	9 -11	; "ui/uimanager"
	28	[9]	CALL     	8 2 2
	29	[10]	GETGLOBAL	9 -1	; require
	30	[10]	LOADK    	10 -12	; "libs/libkoreader-lfs"
	31	[10]	CALL     	9 2 2
	32	[11]	GETGLOBAL	10 -1	; require
	33	[11]	LOADK    	11 -13	; "logger"
	34	[11]	CALL     	10 2 2
	35	[12]	GETGLOBAL	11 -1	; require
	36	[12]	LOADK    	12 -14	; "ffi/util"
	37	[12]	CALL     	11 2 2
	38	[13]	GETGLOBAL	12 -1	; require
	39	[13]	LOADK    	13 -15	; "util"
	40	[13]	CALL     	12 2 2
	41	[14]	GETGLOBAL	13 -1	; require
	42	[14]	LOADK    	14 -16	; "gettext"
	43	[14]	CALL     	13 2 2
	44	[15]	GETGLOBAL	14 -1	; require
	45	[15]	LOADK    	15 -14	; "ffi/util"
	46	[15]	CALL     	14 2 2
	47	[15]	GETTABLE 	14 14 -17	; "template"
	48	[17]	LOADK    	15 -18	; "metadata.calibre"
	49	[18]	LOADK    	16 -19	; "temp/metadata.koreader"
	50	[20]	SELF     	17 5 -20	; "new"
	51	[20]	NEWTABLE 	19 0 19
	52	[21]	SETTABLE 	19 -21 -22	; "search_dialog" nil
	53	[22]	SETTABLE 	19 -23 -24	; "title" 1
	54	[23]	SETTABLE 	19 -25 -26	; "authors" 2
	55	[24]	SETTABLE 	19 -27 -28	; "authors2" 3
	56	[25]	SETTABLE 	19 -29 -30	; "path" 4
	57	[26]	SETTABLE 	19 -31 -32	; "series" 5
	58	[27]	SETTABLE 	19 -33 -34	; "series_index" 6
	59	[28]	SETTABLE 	19 -35 -36	; "tags" 7
	60	[29]	SETTABLE 	19 -37 -38	; "tags2" 8
	61	[30]	SETTABLE 	19 -39 -40	; "tags3" 9
	62	[31]	SETTABLE 	19 -41 -42	; "count" 0
	63	[32]	NEWTABLE 	20 0 0
	64	[32]	SETTABLE 	19 -43 20	; "data" -
	65	[33]	NEWTABLE 	20 0 0
	66	[33]	SETTABLE 	19 -44 20	; "results" -
	67	[34]	NEWTABLE 	20 0 0
	68	[34]	SETTABLE 	19 -45 20	; "browse_tags" -
	69	[35]	NEWTABLE 	20 0 0
	70	[35]	SETTABLE 	19 -46 20	; "browse_series" -
	71	[36]	SETTABLE 	19 -47 -22	; "error" nil
	72	[37]	SETTABLE 	19 -48 -49	; "use_previous_search_results" false
	73	[38]	SETTABLE 	19 -50 -22	; "lastsearch" nil
	74	[39]	SETTABLE 	19 -51 -49	; "use_own_metadata_file" false
	75	[40]	SETTABLE 	19 -52 -22	; "metafile_1" nil
	76	[41]	SETTABLE 	19 -53 -22	; "metafile_2" nil
	77	[20]	CALL     	17 3 2
	78	[74]	CLOSURE  	18 0	; 0x7fbf27407110
	79	[74]	MOVE     	0 9
	80	[74]	MOVE     	0 15
	81	[74]	MOVE     	0 10
	82	[74]	MOVE     	0 18
	83	[144]	CLOSURE  	19 1	; 0x7fbf27407dc0
	84	[144]	MOVE     	0 10
	85	[144]	MOVE     	0 18
	86	[144]	MOVE     	0 13
	87	[144]	MOVE     	0 15
	88	[144]	MOVE     	0 8
	89	[144]	MOVE     	0 4
	90	[144]	MOVE     	0 9
	91	[144]	MOVE     	0 16
	92	[76]	SETTABLE 	17 -54 19	; "getCalibre" -
	93	[224]	CLOSURE  	19 2	; 0x7fbf274085c0
	94	[224]	MOVE     	0 3
	95	[224]	MOVE     	0 13
	96	[224]	MOVE     	0 8
	97	[224]	MOVE     	0 7
	98	[224]	MOVE     	0 4
	99	[146]	SETTABLE 	17 -55 19	; "ShowSearch" -
	100	[230]	CLOSURE  	19 3	; 0x7fbf27409410
	101	[226]	SETTABLE 	17 -56 19	; "init" -
	102	[240]	CLOSURE  	19 4	; 0x7fbf274094d0
	103	[240]	MOVE     	0 8
	104	[232]	SETTABLE 	17 -57 19	; "close" -
	105	[490]	CLOSURE  	19 5	; 0x7fbf2740a2d0
	106	[490]	MOVE     	0 12
	107	[490]	MOVE     	0 16
	108	[490]	MOVE     	0 1
	109	[490]	MOVE     	0 10
	110	[490]	MOVE     	0 9
	111	[490]	MOVE     	0 8
	112	[490]	MOVE     	0 4
	113	[490]	MOVE     	0 14
	114	[490]	MOVE     	0 13
	115	[242]	SETTABLE 	17 -58 19	; "find" -
	116	[522]	CLOSURE  	19 6	; 0x7fbf2740bc90
	117	[522]	MOVE     	0 13
	118	[522]	MOVE     	0 9
	119	[522]	MOVE     	0 1
	120	[522]	MOVE     	0 7
	121	[522]	MOVE     	0 8
	122	[522]	MOVE     	0 4
	123	[492]	SETTABLE 	17 -59 19	; "onMenuHold" -
	124	[570]	CLOSURE  	19 7	; 0x7fbf2740ba40
	125	[570]	MOVE     	0 0
	126	[570]	MOVE     	0 7
	127	[570]	MOVE     	0 6
	128	[570]	MOVE     	0 2
	129	[570]	MOVE     	0 8
	130	[570]	MOVE     	0 14
	131	[570]	MOVE     	0 13
	132	[524]	SETTABLE 	17 -60 19	; "showresults" -
	133	[687]	CLOSURE  	19 8	; 0x7fbf27409700
	134	[687]	MOVE     	0 0
	135	[687]	MOVE     	0 7
	136	[687]	MOVE     	0 6
	137	[687]	MOVE     	0 2
	138	[687]	MOVE     	0 8
	139	[687]	MOVE     	0 11
	140	[687]	MOVE     	0 14
	141	[687]	MOVE     	0 13
	142	[572]	SETTABLE 	17 -61 19	; "browse" -
	143	[689]	RETURN   	17 2
	144	[689]	RETURN   	0 1

function <./frontend/apps/filemanager/filemanagersearch.lua:44,74> (63 instructions, 252 bytes at 0x7fbf27407110)
1 param, 14 slots, 4 upvalues, 11 locals, 13 constants, 0 functions
	1	[47]	GETGLOBAL	2 -1	; pcall
	2	[47]	GETUPVAL 	3 0	; lfs
	3	[47]	GETTABLE 	3 3 -2	; "dir"
	4	[47]	MOVE     	4 0
	5	[47]	CALL     	2 3 4
	6	[48]	TEST     	2 0 0
	7	[48]	JMP      	54	; to 62
	8	[49]	MOVE     	5 3
	9	[49]	MOVE     	6 4
	10	[49]	LOADNIL  	7 7
	11	[49]	JMP      	48	; to 60
	12	[50]	TEST     	1 0 0
	13	[50]	JMP      	2	; to 16
	14	[51]	JMP      	47	; to 62
	15	[51]	JMP      	44	; to 60
	16	[53]	EQ       	1 8 -3	; - "."
	17	[53]	JMP      	42	; to 60
	18	[53]	EQ       	1 8 -4	; - ".."
	19	[53]	JMP      	40	; to 60
	20	[54]	MOVE     	9 0
	21	[54]	LOADK    	10 -5	; "/"
	22	[54]	MOVE     	11 8
	23	[54]	CONCAT   	9 9 11
	24	[55]	GETUPVAL 	10 0	; lfs
	25	[55]	GETTABLE 	10 10 -6	; "attributes"
	26	[55]	MOVE     	11 9
	27	[55]	LOADK    	12 -7	; "mode"
	28	[55]	CALL     	10 3 2
	29	[56]	EQ       	0 10 -8	; - "file"
	30	[56]	JMP      	23	; to 54
	31	[57]	GETUPVAL 	11 1	; calibre
	32	[57]	EQ       	1 8 11
	33	[57]	JMP      	5	; to 39
	34	[57]	LOADK    	11 -3	; "."
	35	[57]	GETUPVAL 	12 1	; calibre
	36	[57]	CONCAT   	11 11 12
	37	[57]	EQ       	0 8 11
	38	[57]	JMP      	21	; to 60
	39	[58]	MOVE     	11 0
	40	[58]	LOADK    	12 -5	; "/"
	41	[58]	MOVE     	13 8
	42	[58]	CONCAT   	1 11 13
	43	[63]	GETGLOBAL	11 -9	; _G
	44	[63]	MOVE     	12 0
	45	[63]	LOADK    	13 -5	; "/"
	46	[63]	CONCAT   	12 12 13
	47	[63]	SETTABLE 	11 -10 12	; "SEARCH_LIBRARY_PATH" -
	48	[64]	GETUPVAL 	11 2	; logger
	49	[64]	GETTABLE 	11 11 -11	; "info"
	50	[64]	LOADK    	12 -12	; "FMSearch: Found a SEARCH_LIBRARY_PATH @"
	51	[64]	GETGLOBAL	13 -10	; SEARCH_LIBRARY_PATH
	52	[64]	CALL     	11 3 1
	53	[65]	JMP      	6	; to 60
	54	[66]	EQ       	0 10 -13	; - "directory"
	55	[66]	JMP      	4	; to 60
	56	[67]	GETUPVAL 	11 3	; findcalibre
	57	[67]	MOVE     	12 9
	58	[67]	CALL     	11 2 2
	59	[67]	MOVE     	1 11
	60	[49]	TFORLOOP 	5 1
	61	[70]	JMP      	-50	; to 12
	62	[73]	RETURN   	1 2
	63	[74]	RETURN   	0 1

function <./frontend/apps/filemanager/filemanagersearch.lua:76,144> (220 instructions, 880 bytes at 0x7fbf27407dc0)
1 param, 8 slots, 8 upvalues, 2 locals, 41 constants, 0 functions
	1	[79]	GETGLOBAL	1 -1	; SEARCH_LIBRARY_PATH
	2	[79]	EQ       	0 1 -2	; - nil
	3	[79]	JMP      	16	; to 20
	4	[80]	GETUPVAL 	1 0	; logger
	5	[80]	GETTABLE 	1 1 -3	; "dbg"
	6	[80]	LOADK    	2 -4	; "search Calibre database"
	7	[80]	CALL     	1 2 1
	8	[81]	GETUPVAL 	1 1	; findcalibre
	9	[81]	LOADK    	2 -6	; "/mnt"
	10	[81]	CALL     	1 2 2
	11	[81]	SETTABLE 	0 -5 1	; "metafile_1" -
	12	[82]	GETTABLE 	1 0 -5	; "metafile_1"
	13	[82]	TEST     	1 0 1
	14	[82]	JMP      	97	; to 112
	15	[83]	GETUPVAL 	1 2	; _
	16	[83]	LOADK    	2 -8	; "The SEARCH_LIBRARY_PATH variable must be defined in 'persistent.defaults.lua' in order to use the calibre file search functionality."
	17	[83]	CALL     	1 2 2
	18	[83]	SETTABLE 	0 -7 1	; "error" -
	19	[84]	JMP      	92	; to 112
	20	[86]	GETGLOBAL	1 -9	; string
	21	[86]	GETTABLE 	1 1 -10	; "sub"
	22	[86]	GETGLOBAL	2 -1	; SEARCH_LIBRARY_PATH
	23	[86]	GETGLOBAL	3 -9	; string
	24	[86]	GETTABLE 	3 3 -11	; "len"
	25	[86]	GETGLOBAL	4 -1	; SEARCH_LIBRARY_PATH
	26	[86]	CALL     	3 2 0
	27	[86]	CALL     	1 0 2
	28	[86]	EQ       	1 1 -12	; - "/"
	29	[86]	JMP      	5	; to 35
	30	[87]	GETGLOBAL	1 -13	; _G
	31	[87]	GETGLOBAL	2 -1	; SEARCH_LIBRARY_PATH
	32	[87]	LOADK    	3 -12	; "/"
	33	[87]	CONCAT   	2 2 3
	34	[87]	SETTABLE 	1 -1 2	; "SEARCH_LIBRARY_PATH" -
	35	[89]	GETGLOBAL	1 -14	; io
	36	[89]	GETTABLE 	1 1 -15	; "open"
	37	[89]	GETGLOBAL	2 -1	; SEARCH_LIBRARY_PATH
	38	[89]	GETUPVAL 	3 3	; calibre
	39	[89]	CONCAT   	2 2 3
	40	[89]	LOADK    	3 -16	; "r"
	41	[89]	CALL     	1 3 2
	42	[89]	EQ       	0 1 -2	; - nil
	43	[89]	JMP      	29	; to 73
	44	[90]	GETGLOBAL	1 -14	; io
	45	[90]	GETTABLE 	1 1 -15	; "open"
	46	[90]	GETGLOBAL	2 -1	; SEARCH_LIBRARY_PATH
	47	[90]	LOADK    	3 -17	; "."
	48	[90]	GETUPVAL 	4 3	; calibre
	49	[90]	CONCAT   	2 2 4
	50	[90]	LOADK    	3 -16	; "r"
	51	[90]	CALL     	1 3 2
	52	[90]	EQ       	0 1 -2	; - nil
	53	[90]	JMP      	13	; to 67
	54	[91]	GETGLOBAL	1 -1	; SEARCH_LIBRARY_PATH
	55	[91]	GETUPVAL 	2 3	; calibre
	56	[91]	LOADK    	3 -18	; " "
	57	[91]	GETUPVAL 	4 2	; _
	58	[91]	LOADK    	5 -19	; "not found."
	59	[91]	CALL     	4 2 2
	60	[91]	CONCAT   	1 1 4
	61	[91]	SETTABLE 	0 -7 1	; "error" -
	62	[92]	GETUPVAL 	1 0	; logger
	63	[92]	GETTABLE 	1 1 -20	; "err"
	64	[92]	GETTABLE 	2 0 -7	; "error"
	65	[92]	CALL     	1 2 1
	66	[92]	JMP      	10	; to 77
	67	[94]	GETGLOBAL	1 -1	; SEARCH_LIBRARY_PATH
	68	[94]	LOADK    	2 -17	; "."
	69	[94]	GETUPVAL 	3 3	; calibre
	70	[94]	CONCAT   	1 1 3
	71	[94]	SETTABLE 	0 -5 1	; "metafile_1" -
	72	[95]	JMP      	4	; to 77
	73	[97]	GETGLOBAL	1 -1	; SEARCH_LIBRARY_PATH
	74	[97]	GETUPVAL 	2 3	; calibre
	75	[97]	CONCAT   	1 1 2
	76	[97]	SETTABLE 	0 -5 1	; "metafile_1" -
	77	[100]	GETGLOBAL	1 -21	; SEARCH_AUTHORS
	78	[100]	TEST     	1 0 1
	79	[100]	JMP      	25	; to 105
	80	[100]	GETGLOBAL	1 -22	; SEARCH_TITLE
	81	[100]	TEST     	1 0 1
	82	[100]	JMP      	22	; to 105
	83	[100]	GETGLOBAL	1 -23	; SEARCH_PATH
	84	[100]	TEST     	1 0 1
	85	[100]	JMP      	19	; to 105
	86	[100]	GETGLOBAL	1 -24	; SEARCH_SERIES
	87	[100]	TEST     	1 0 1
	88	[100]	JMP      	16	; to 105
	89	[100]	GETGLOBAL	1 -25	; SEARCH_TAGS
	90	[100]	TEST     	1 0 1
	91	[100]	JMP      	13	; to 105
	92	[101]	SETTABLE 	0 -5 -2	; "metafile_1" nil
	93	[102]	GETUPVAL 	1 4	; UIManager
	94	[102]	SELF     	1 1 -26	; "show"
	95	[102]	GETUPVAL 	3 5	; InfoMessage
	96	[102]	SELF     	3 3 -27	; "new"
	97	[102]	NEWTABLE 	5 0 1
	98	[102]	GETUPVAL 	6 2	; _
	99	[102]	LOADK    	7 -29	; "You must specify at least one field to search at! (SEARCH_XXX = true in defaults.lua)"
	100	[102]	CALL     	6 2 2
	101	[102]	SETTABLE 	5 -28 6	; "text" -
	102	[102]	CALL     	3 3 0
	103	[102]	CALL     	1 0 1
	104	[102]	JMP      	7	; to 112
	105	[103]	GETTABLE 	1 0 -5	; "metafile_1"
	106	[103]	EQ       	0 1 -2	; - nil
	107	[103]	JMP      	4	; to 112
	108	[104]	GETUPVAL 	1 1	; findcalibre
	109	[104]	LOADK    	2 -6	; "/mnt"
	110	[104]	CALL     	1 2 2
	111	[104]	SETTABLE 	0 -5 1	; "metafile_1" -
	112	[108]	LOADNIL  	1 1
	113	[110]	GETGLOBAL	2 -9	; string
	114	[110]	GETTABLE 	2 2 -10	; "sub"
	115	[110]	GETGLOBAL	3 -30	; SEARCH_LIBRARY_PATH2
	116	[110]	GETGLOBAL	4 -9	; string
	117	[110]	GETTABLE 	4 4 -11	; "len"
	118	[110]	GETGLOBAL	5 -30	; SEARCH_LIBRARY_PATH2
	119	[110]	CALL     	4 2 0
	120	[110]	CALL     	2 0 2
	121	[110]	EQ       	1 2 -12	; - "/"
	122	[110]	JMP      	5	; to 128
	123	[111]	GETGLOBAL	2 -13	; _G
	124	[111]	GETGLOBAL	3 -30	; SEARCH_LIBRARY_PATH2
	125	[111]	LOADK    	4 -12	; "/"
	126	[111]	CONCAT   	3 3 4
	127	[111]	SETTABLE 	2 -30 3	; "SEARCH_LIBRARY_PATH2" -
	128	[113]	GETGLOBAL	2 -14	; io
	129	[113]	GETTABLE 	2 2 -15	; "open"
	130	[113]	GETGLOBAL	3 -30	; SEARCH_LIBRARY_PATH2
	131	[113]	GETUPVAL 	4 3	; calibre
	132	[113]	CONCAT   	3 3 4
	133	[113]	LOADK    	4 -16	; "r"
	134	[113]	CALL     	2 3 2
	135	[113]	EQ       	0 2 -2	; - nil
	136	[113]	JMP      	15	; to 152
	137	[114]	GETGLOBAL	2 -14	; io
	138	[114]	GETTABLE 	2 2 -15	; "open"
	139	[114]	GETGLOBAL	3 -30	; SEARCH_LIBRARY_PATH2
	140	[114]	LOADK    	4 -17	; "."
	141	[114]	GETUPVAL 	5 3	; calibre
	142	[114]	CONCAT   	3 3 5
	143	[114]	LOADK    	4 -16	; "r"
	144	[114]	CALL     	2 3 2
	145	[114]	EQ       	1 2 -2	; - nil
	146	[114]	JMP      	8	; to 155
	147	[115]	GETGLOBAL	2 -30	; SEARCH_LIBRARY_PATH2
	148	[115]	LOADK    	3 -17	; "."
	149	[115]	GETUPVAL 	4 3	; calibre
	150	[115]	CONCAT   	1 2 4
	151	[116]	JMP      	3	; to 155
	152	[118]	GETGLOBAL	2 -30	; SEARCH_LIBRARY_PATH2
	153	[118]	GETUPVAL 	3 3	; calibre
	154	[118]	CONCAT   	1 2 3
	155	[120]	TEST     	1 0 0
	156	[120]	JMP      	5	; to 162
	157	[120]	GETTABLE 	2 0 -5	; "metafile_1"
	158	[120]	EQ       	1 1 2
	159	[120]	JMP      	2	; to 162
	160	[121]	SETTABLE 	0 -31 1	; "metafile_2" -
	161	[121]	JMP      	1	; to 163
	162	[123]	SETTABLE 	0 -31 -2	; "metafile_2" nil
	163	[127]	SETTABLE 	0 -32 -33	; "use_own_metadata_file" false
	164	[128]	GETTABLE 	2 0 -5	; "metafile_1"
	165	[128]	TEST     	2 0 0
	166	[128]	JMP      	53	; to 220
	167	[129]	GETGLOBAL	2 -34	; pcall
	168	[129]	GETUPVAL 	3 6	; lfs
	169	[129]	GETTABLE 	3 3 -35	; "mkdir"
	170	[129]	LOADK    	4 -36	; "temp"
	171	[129]	CALL     	3 2 0
	172	[129]	CALL     	2 0 1
	173	[130]	GETGLOBAL	2 -14	; io
	174	[130]	GETTABLE 	2 2 -15	; "open"
	175	[130]	GETUPVAL 	3 7	; koreaderfile
	176	[130]	LOADK    	4 -16	; "r"
	177	[130]	CALL     	2 3 2
	178	[130]	TEST     	2 0 0
	179	[130]	JMP      	40	; to 220
	180	[131]	GETUPVAL 	2 6	; lfs
	181	[131]	GETTABLE 	2 2 -37	; "attributes"
	182	[131]	GETUPVAL 	3 7	; koreaderfile
	183	[131]	LOADK    	4 -38	; "modification"
	184	[131]	CALL     	2 3 2
	185	[131]	GETUPVAL 	3 6	; lfs
	186	[131]	GETTABLE 	3 3 -37	; "attributes"
	187	[131]	GETTABLE 	4 0 -5	; "metafile_1"
	188	[131]	LOADK    	5 -38	; "modification"
	189	[131]	CALL     	3 3 2
	190	[131]	LT       	0 3 2
	191	[131]	JMP      	28	; to 220
	192	[132]	GETTABLE 	2 0 -31	; "metafile_2"
	193	[132]	TEST     	2 0 0
	194	[132]	JMP      	19	; to 214
	195	[133]	GETUPVAL 	2 6	; lfs
	196	[133]	GETTABLE 	2 2 -37	; "attributes"
	197	[133]	GETUPVAL 	3 7	; koreaderfile
	198	[133]	LOADK    	4 -38	; "modification"
	199	[133]	CALL     	2 3 2
	200	[133]	GETUPVAL 	3 6	; lfs
	201	[133]	GETTABLE 	3 3 -37	; "attributes"
	202	[133]	GETTABLE 	4 0 -31	; "metafile_2"
	203	[133]	LOADK    	5 -38	; "modification"
	204	[133]	CALL     	3 3 2
	205	[133]	LT       	0 3 2
	206	[133]	JMP      	13	; to 220
	207	[134]	SETTABLE 	0 -32 -39	; "use_own_metadata_file" true
	208	[135]	GETUPVAL 	2 0	; logger
	209	[135]	GETTABLE 	2 2 -40	; "info"
	210	[135]	LOADK    	3 -41	; "FMSearch: Using our own simplified metadata file as it's newer than"
	211	[135]	GETTABLE 	4 0 -31	; "metafile_2"
	212	[135]	CALL     	2 3 1
	213	[136]	JMP      	6	; to 220
	214	[138]	SETTABLE 	0 -32 -39	; "use_own_metadata_file" true
	215	[139]	GETUPVAL 	2 0	; logger
	216	[139]	GETTABLE 	2 2 -40	; "info"
	217	[139]	LOADK    	3 -41	; "FMSearch: Using our own simplified metadata file as it's newer than"
	218	[139]	GETTABLE 	4 0 -5	; "metafile_1"
	219	[139]	CALL     	2 3 1
	220	[144]	RETURN   	0 1

function <./frontend/apps/filemanager/filemanagersearch.lua:146,224> (100 instructions, 400 bytes at 0x7fbf274085c0)
1 param, 12 slots, 5 upvalues, 2 locals, 29 constants, 4 functions
	1	[147]	GETTABLE 	1 0 -1	; "metafile_1"
	2	[147]	EQ       	1 1 -2	; - nil
	3	[147]	JMP      	78	; to 82
	4	[148]	GETTABLE 	1 0 -3	; "search_value"
	5	[149]	GETUPVAL 	2 0	; InputDialog
	6	[149]	SELF     	2 2 -5	; "new"
	7	[149]	NEWTABLE 	4 0 5
	8	[150]	GETUPVAL 	5 1	; _
	9	[150]	LOADK    	6 -7	; "Search books"
	10	[150]	CALL     	5 2 2
	11	[150]	SETTABLE 	4 -6 5	; "title" -
	12	[151]	GETTABLE 	5 0 -3	; "search_value"
	13	[151]	SETTABLE 	4 -8 5	; "input" -
	14	[152]	NEWTABLE 	5 2 0
	15	[152]	NEWTABLE 	6 2 0
	16	[153]	NEWTABLE 	7 0 3
	17	[155]	GETUPVAL 	8 1	; _
	18	[155]	LOADK    	9 -11	; "Browse series"
	19	[155]	CALL     	8 2 2
	20	[155]	SETTABLE 	7 -10 8	; "text" -
	21	[156]	SETTABLE 	7 -12 -13	; "enabled" true
	22	[166]	CLOSURE  	8 0	; 0x7fbf27408cb0
	23	[166]	MOVE     	0 0
	24	[166]	MOVE     	0 1
	25	[166]	SETTABLE 	7 -14 8	; "callback" -
	26	[167]	NEWTABLE 	8 0 3
	27	[169]	GETUPVAL 	9 1	; _
	28	[169]	LOADK    	10 -15	; "Browse tags"
	29	[169]	CALL     	9 2 2
	30	[169]	SETTABLE 	8 -10 9	; "text" -
	31	[170]	SETTABLE 	8 -12 -13	; "enabled" true
	32	[180]	CLOSURE  	9 1	; 0x7fbf27408e50
	33	[180]	MOVE     	0 0
	34	[180]	MOVE     	0 1
	35	[180]	SETTABLE 	8 -14 9	; "callback" -
	36	[182]	SETLIST  	6 2 1	; 1
	37	[182]	NEWTABLE 	7 2 0
	38	[183]	NEWTABLE 	8 0 3
	39	[185]	GETUPVAL 	9 1	; _
	40	[185]	LOADK    	10 -16	; "Cancel"
	41	[185]	CALL     	9 2 2
	42	[185]	SETTABLE 	8 -10 9	; "text" -
	43	[186]	SETTABLE 	8 -12 -13	; "enabled" true
	44	[190]	CLOSURE  	9 2	; 0x7fbf27408be0
	45	[190]	MOVE     	0 0
	46	[190]	GETUPVAL 	0 2	; UIManager
	47	[190]	SETTABLE 	8 -14 9	; "callback" -
	48	[191]	NEWTABLE 	9 0 3
	49	[194]	GETUPVAL 	10 1	; _
	50	[194]	LOADK    	11 -17	; "Find books"
	51	[194]	CALL     	10 2 2
	52	[194]	SETTABLE 	9 -10 10	; "text" -
	53	[195]	SETTABLE 	9 -12 -13	; "enabled" true
	54	[205]	CLOSURE  	10 3	; 0x7fbf27409660
	55	[205]	MOVE     	0 0
	56	[205]	MOVE     	0 1
	57	[205]	SETTABLE 	9 -14 10	; "callback" -
	58	[207]	SETLIST  	7 2 1	; 1
	59	[208]	SETLIST  	5 2 1	; 1
	60	[208]	SETTABLE 	4 -9 5	; "buttons" -
	61	[209]	GETUPVAL 	5 3	; Screen
	62	[209]	SELF     	5 5 -19	; "getWidth"
	63	[209]	CALL     	5 2 2
	64	[209]	MUL      	5 5 -20	; - 0.8
	65	[209]	SETTABLE 	4 -18 5	; "width" -
	66	[210]	GETUPVAL 	5 3	; Screen
	67	[210]	SELF     	5 5 -22	; "getHeight"
	68	[210]	CALL     	5 2 2
	69	[210]	MUL      	5 5 -23	; - 0.2
	70	[210]	SETTABLE 	4 -21 5	; "height" -
	71	[149]	CALL     	2 3 2
	72	[211]	SETTABLE 	0 -4 2	; "search_dialog" -
	73	[212]	GETUPVAL 	2 2	; UIManager
	74	[212]	SELF     	2 2 -24	; "show"
	75	[212]	GETTABLE 	4 0 -4	; "search_dialog"
	76	[212]	CALL     	2 3 1
	77	[213]	GETTABLE 	2 0 -4	; "search_dialog"
	78	[213]	SELF     	2 2 -25	; "onShowKeyboard"
	79	[213]	CALL     	2 2 1
	80	[213]	CLOSE    	1
	81	[213]	JMP      	18	; to 100
	82	[215]	GETTABLE 	1 0 -26	; "error"
	83	[215]	TEST     	1 0 0
	84	[215]	JMP      	15	; to 100
	85	[216]	GETUPVAL 	1 2	; UIManager
	86	[216]	SELF     	1 1 -24	; "show"
	87	[216]	GETUPVAL 	3 4	; InfoMessage
	88	[216]	SELF     	3 3 -5	; "new"
	89	[216]	NEWTABLE 	5 0 1
	90	[217]	LOADK    	6 -27	; "%s\n%s"
	91	[217]	SELF     	6 6 -28	; "format"
	92	[218]	GETTABLE 	8 0 -26	; "error"
	93	[219]	GETUPVAL 	9 1	; _
	94	[219]	LOADK    	10 -29	; "Unable to find a calibre metadata file."
	95	[219]	CALL     	9 2 0
	96	[217]	CALL     	6 0 2
	97	[219]	SETTABLE 	5 -10 6	; "text" -
	98	[216]	CALL     	3 3 0
	99	[216]	CALL     	1 0 1
	100	[224]	RETURN   	0 1

function <./frontend/apps/filemanager/filemanagersearch.lua:157,166> (26 instructions, 104 bytes at 0x7fbf27408cb0)
0 params, 3 slots, 2 upvalues, 0 locals, 9 constants, 0 functions
	1	[158]	GETUPVAL 	0 0	; self
	2	[158]	GETUPVAL 	1 0	; self
	3	[158]	GETTABLE 	1 1 -2	; "search_dialog"
	4	[158]	SELF     	1 1 -3	; "getInputText"
	5	[158]	CALL     	1 2 2
	6	[158]	SETTABLE 	0 -1 1	; "search_value" -
	7	[159]	GETUPVAL 	0 0	; self
	8	[159]	GETTABLE 	0 0 -1	; "search_value"
	9	[159]	GETUPVAL 	1 1	; dummy
	10	[159]	EQ       	0 0 1
	11	[159]	JMP      	7	; to 19
	12	[159]	GETUPVAL 	0 0	; self
	13	[159]	GETTABLE 	0 0 -4	; "lastsearch"
	14	[159]	EQ       	0 0 -5	; - "series"
	15	[159]	JMP      	3	; to 19
	16	[160]	GETUPVAL 	0 0	; self
	17	[160]	SETTABLE 	0 -6 -7	; "use_previous_search_results" true
	18	[160]	JMP      	2	; to 21
	19	[162]	GETUPVAL 	0 0	; self
	20	[162]	SETTABLE 	0 -6 -8	; "use_previous_search_results" false
	21	[164]	GETUPVAL 	0 0	; self
	22	[164]	SETTABLE 	0 -4 -5	; "lastsearch" "series"
	23	[165]	GETUPVAL 	0 0	; self
	24	[165]	SELF     	0 0 -9	; "close"
	25	[165]	CALL     	0 2 1
	26	[166]	RETURN   	0 1

function <./frontend/apps/filemanager/filemanagersearch.lua:171,180> (26 instructions, 104 bytes at 0x7fbf27408e50)
0 params, 3 slots, 2 upvalues, 0 locals, 9 constants, 0 functions
	1	[172]	GETUPVAL 	0 0	; self
	2	[172]	GETUPVAL 	1 0	; self
	3	[172]	GETTABLE 	1 1 -2	; "search_dialog"
	4	[172]	SELF     	1 1 -3	; "getInputText"
	5	[172]	CALL     	1 2 2
	6	[172]	SETTABLE 	0 -1 1	; "search_value" -
	7	[173]	GETUPVAL 	0 0	; self
	8	[173]	GETTABLE 	0 0 -1	; "search_value"
	9	[173]	GETUPVAL 	1 1	; dummy
	10	[173]	EQ       	0 0 1
	11	[173]	JMP      	7	; to 19
	12	[173]	GETUPVAL 	0 0	; self
	13	[173]	GETTABLE 	0 0 -4	; "lastsearch"
	14	[173]	EQ       	0 0 -5	; - "tags"
	15	[173]	JMP      	3	; to 19
	16	[174]	GETUPVAL 	0 0	; self
	17	[174]	SETTABLE 	0 -6 -7	; "use_previous_search_results" true
	18	[174]	JMP      	2	; to 21
	19	[176]	GETUPVAL 	0 0	; self
	20	[176]	SETTABLE 	0 -6 -8	; "use_previous_search_results" false
	21	[178]	GETUPVAL 	0 0	; self
	22	[178]	SETTABLE 	0 -4 -5	; "lastsearch" "tags"
	23	[179]	GETUPVAL 	0 0	; self
	24	[179]	SELF     	0 0 -9	; "close"
	25	[179]	CALL     	0 2 1
	26	[180]	RETURN   	0 1

function <./frontend/apps/filemanager/filemanagersearch.lua:187,190> (10 instructions, 40 bytes at 0x7fbf27408be0)
0 params, 3 slots, 2 upvalues, 0 locals, 3 constants, 0 functions
	1	[188]	GETUPVAL 	0 0	; self
	2	[188]	GETTABLE 	0 0 -1	; "search_dialog"
	3	[188]	SELF     	0 0 -2	; "onClose"
	4	[188]	CALL     	0 2 1
	5	[189]	GETUPVAL 	0 1	; UIManager
	6	[189]	SELF     	0 0 -3	; "close"
	7	[189]	GETUPVAL 	2 0	; self
	8	[189]	GETTABLE 	2 2 -1	; "search_dialog"
	9	[189]	CALL     	0 3 1
	10	[190]	RETURN   	0 1

function <./frontend/apps/filemanager/filemanagersearch.lua:196,205> (26 instructions, 104 bytes at 0x7fbf27409660)
0 params, 3 slots, 2 upvalues, 0 locals, 9 constants, 0 functions
	1	[197]	GETUPVAL 	0 0	; self
	2	[197]	GETUPVAL 	1 0	; self
	3	[197]	GETTABLE 	1 1 -2	; "search_dialog"
	4	[197]	SELF     	1 1 -3	; "getInputText"
	5	[197]	CALL     	1 2 2
	6	[197]	SETTABLE 	0 -1 1	; "search_value" -
	7	[198]	GETUPVAL 	0 0	; self
	8	[198]	GETTABLE 	0 0 -1	; "search_value"
	9	[198]	GETUPVAL 	1 1	; dummy
	10	[198]	EQ       	0 0 1
	11	[198]	JMP      	7	; to 19
	12	[198]	GETUPVAL 	0 0	; self
	13	[198]	GETTABLE 	0 0 -4	; "lastsearch"
	14	[198]	EQ       	0 0 -5	; - "find"
	15	[198]	JMP      	3	; to 19
	16	[199]	GETUPVAL 	0 0	; self
	17	[199]	SETTABLE 	0 -6 -7	; "use_previous_search_results" true
	18	[199]	JMP      	2	; to 21
	19	[201]	GETUPVAL 	0 0	; self
	20	[201]	SETTABLE 	0 -6 -8	; "use_previous_search_results" false
	21	[203]	GETUPVAL 	0 0	; self
	22	[203]	SETTABLE 	0 -4 -5	; "lastsearch" "find"
	23	[204]	GETUPVAL 	0 0	; self
	24	[204]	SELF     	0 0 -9	; "close"
	25	[204]	CALL     	0 2 1
	26	[205]	RETURN   	0 1

function <./frontend/apps/filemanager/filemanagersearch.lua:226,230> (6 instructions, 24 bytes at 0x7fbf27409410)
1 param, 2 slots, 0 upvalues, 1 local, 4 constants, 0 functions
	1	[227]	SETTABLE 	0 -1 -2	; "error" nil
	2	[228]	NEWTABLE 	1 0 0
	3	[228]	SETTABLE 	0 -3 1	; "data" -
	4	[229]	NEWTABLE 	1 0 0
	5	[229]	SETTABLE 	0 -4 1	; "results" -
	6	[230]	RETURN   	0 1

function <./frontend/apps/filemanager/filemanagersearch.lua:232,240> (23 instructions, 92 bytes at 0x7fbf274094d0)
1 param, 4 slots, 1 upvalue, 1 local, 9 constants, 0 functions
	1	[233]	GETTABLE 	1 0 -1	; "search_value"
	2	[233]	TEST     	1 0 0
	3	[233]	JMP      	19	; to 23
	4	[234]	GETTABLE 	1 0 -2	; "search_dialog"
	5	[234]	SELF     	1 1 -3	; "onClose"
	6	[234]	CALL     	1 2 1
	7	[235]	GETUPVAL 	1 0	; UIManager
	8	[235]	SELF     	1 1 -4	; "close"
	9	[235]	GETTABLE 	3 0 -2	; "search_dialog"
	10	[235]	CALL     	1 3 1
	11	[236]	GETGLOBAL	1 -5	; string
	12	[236]	GETTABLE 	1 1 -6	; "len"
	13	[236]	GETTABLE 	2 0 -1	; "search_value"
	14	[236]	CALL     	1 2 2
	15	[236]	LT       	1 -7 1	; 0 -
	16	[236]	JMP      	3	; to 20
	17	[236]	GETTABLE 	1 0 -8	; "lastsearch"
	18	[236]	EQ       	1 1 -9	; - "find"
	19	[236]	JMP      	3	; to 23
	20	[237]	SELF     	1 0 -9	; "find"
	21	[237]	GETTABLE 	3 0 -8	; "lastsearch"
	22	[237]	CALL     	1 3 1
	23	[240]	RETURN   	0 1

function <./frontend/apps/filemanager/filemanagersearch.lua:242,490> (724 instructions, 2896 bytes at 0x7fbf2740a2d0)
2 params, 22 slots, 9 upvalues, 35 locals, 80 constants, 2 functions
	1	[245]	LOADK    	4 -1	; 1
	2	[246]	LOADNIL  	5 6
	3	[262]	CLOSURE  	7 0	; 0x7fbf2740a140
	4	[262]	GETUPVAL 	0 0	; util
	5	[294]	CLOSURE  	8 1	; 0x7fbf2740a870
	6	[294]	MOVE     	0 0
	7	[294]	MOVE     	0 4
	8	[294]	MOVE     	0 3
	9	[294]	MOVE     	0 2
	10	[294]	MOVE     	0 7
	11	[296]	GETTABLE 	9 0 -2	; "use_previous_search_results"
	12	[296]	TEST     	9 0 1
	13	[296]	JMP      	679	; to 693
	14	[297]	NEWTABLE 	9 0 0
	15	[297]	SETTABLE 	0 -3 9	; "results" -
	16	[298]	NEWTABLE 	9 0 0
	17	[298]	SETTABLE 	0 -4 9	; "data" -
	18	[299]	NEWTABLE 	9 0 0
	19	[299]	SETTABLE 	0 -5 9	; "browse_series" -
	20	[300]	NEWTABLE 	9 0 0
	21	[300]	SETTABLE 	0 -6 9	; "browse_tags" -
	22	[302]	GETGLOBAL	9 -7	; SEARCH_CASESENSITIVE
	23	[302]	TEST     	9 0 0
	24	[302]	JMP      	5	; to 30
	25	[303]	GETTABLE 	9 0 -8	; "search_value"
	26	[303]	TESTSET  	5 9 1
	27	[303]	JMP      	1	; to 29
	28	[303]	LOADK    	5 -9	; ""
	29	[303]	JMP      	8	; to 38
	30	[305]	GETGLOBAL	9 -10	; string
	31	[305]	GETTABLE 	9 9 -11	; "upper"
	32	[305]	GETTABLE 	10 0 -8	; "search_value"
	33	[305]	TEST     	10 0 1
	34	[305]	JMP      	1	; to 36
	35	[305]	LOADK    	10 -9	; ""
	36	[305]	CALL     	9 2 2
	37	[305]	MOVE     	5 9
	38	[308]	LOADBOOL 	6 1 0
	39	[310]	GETTABLE 	9 0 -4	; "data"
	40	[310]	NEWTABLE 	10 9 0
	41	[310]	LOADK    	11 -12	; "-"
	42	[310]	LOADK    	12 -12	; "-"
	43	[310]	LOADK    	13 -12	; "-"
	44	[310]	LOADK    	14 -12	; "-"
	45	[310]	LOADK    	15 -12	; "-"
	46	[310]	LOADK    	16 -12	; "-"
	47	[310]	LOADK    	17 -12	; "-"
	48	[310]	LOADK    	18 -12	; "-"
	49	[310]	LOADK    	19 -12	; "-"
	50	[310]	SETLIST  	10 9 1	; 1
	51	[310]	SETTABLE 	9 4 10
	52	[312]	GETTABLE 	9 0 -13	; "use_own_metadata_file"
	53	[312]	TEST     	9 0 0
	54	[312]	JMP      	239	; to 294
	55	[313]	GETGLOBAL	9 -14	; io
	56	[313]	GETTABLE 	9 9 -15	; "open"
	57	[313]	GETUPVAL 	10 1	; koreaderfile
	58	[313]	LOADK    	11 -16	; "r"
	59	[313]	CALL     	9 3 2
	60	[314]	SELF     	10 9 -17	; "read"
	61	[314]	CALL     	10 2 2
	62	[314]	MOVE     	3 10
	63	[315]	EQ       	1 3 -18	; - "#metadata.Koreader Version 1.1"
	64	[315]	JMP      	6	; to 71
	65	[315]	EQ       	1 3 -19	; - "#metadata.koreader Version 1.1"
	66	[315]	JMP      	4	; to 71
	67	[316]	SETTABLE 	0 -13 -20	; "use_own_metadata_file" false
	68	[317]	SELF     	10 9 -21	; "close"
	69	[317]	CALL     	10 2 1
	70	[317]	JMP      	3	; to 74
	71	[319]	SELF     	10 9 -17	; "read"
	72	[319]	CALL     	10 2 2
	73	[319]	MOVE     	3 10
	74	[321]	GETTABLE 	10 0 -13	; "use_own_metadata_file"
	75	[321]	TEST     	10 0 0
	76	[321]	JMP      	217	; to 294
	77	[322]	TEST     	3 0 0
	78	[322]	JMP      	213	; to 292
	79	[324]	LOADK    	10 -1	; 1
	80	[324]	LOADK    	11 -22	; 9
	81	[324]	LOADK    	12 -1	; 1
	82	[324]	FORPREP  	10 9	; to 92
	83	[325]	GETTABLE 	14 0 -4	; "data"
	84	[325]	GETTABLE 	14 14 4
	85	[325]	TESTSET  	15 3 1
	86	[325]	JMP      	1	; to 88
	87	[325]	LOADK    	15 -9	; ""
	88	[325]	SETTABLE 	14 13 15
	89	[326]	SELF     	14 9 -17	; "read"
	90	[326]	CALL     	14 2 2
	91	[326]	MOVE     	3 14
	92	[324]	FORLOOP  	10 -10	; to 83
	93	[329]	LOADK    	10 -9	; ""
	94	[330]	EQ       	0 1 -23	; - "find"
	95	[330]	JMP      	10	; to 106
	96	[330]	GETGLOBAL	11 -24	; SEARCH_AUTHORS
	97	[330]	TEST     	11 0 0
	98	[330]	JMP      	7	; to 106
	99	[331]	MOVE     	11 10
	100	[331]	GETTABLE 	12 0 -4	; "data"
	101	[331]	GETTABLE 	12 12 4
	102	[331]	GETTABLE 	13 0 -25	; "authors"
	103	[331]	GETTABLE 	12 12 13
	104	[331]	LOADK    	13 -26	; "\n"
	105	[331]	CONCAT   	10 11 13
	106	[333]	EQ       	0 1 -23	; - "find"
	107	[333]	JMP      	10	; to 118
	108	[333]	GETGLOBAL	11 -27	; SEARCH_TITLE
	109	[333]	TEST     	11 0 0
	110	[333]	JMP      	7	; to 118
	111	[334]	MOVE     	11 10
	112	[334]	GETTABLE 	12 0 -4	; "data"
	113	[334]	GETTABLE 	12 12 4
	114	[334]	GETTABLE 	13 0 -28	; "title"
	115	[334]	GETTABLE 	12 12 13
	116	[334]	LOADK    	13 -26	; "\n"
	117	[334]	CONCAT   	10 11 13
	118	[336]	EQ       	0 1 -23	; - "find"
	119	[336]	JMP      	10	; to 130
	120	[336]	GETGLOBAL	11 -29	; SEARCH_PATH
	121	[336]	TEST     	11 0 0
	122	[336]	JMP      	7	; to 130
	123	[337]	MOVE     	11 10
	124	[337]	GETTABLE 	12 0 -4	; "data"
	125	[337]	GETTABLE 	12 12 4
	126	[337]	GETTABLE 	13 0 -30	; "path"
	127	[337]	GETTABLE 	12 12 13
	128	[337]	LOADK    	13 -26	; "\n"
	129	[337]	CONCAT   	10 11 13
	130	[339]	EQ       	1 1 -31	; - "series"
	131	[339]	JMP      	3	; to 135
	132	[339]	GETGLOBAL	11 -32	; SEARCH_SERIES
	133	[339]	TEST     	11 0 0
	134	[339]	JMP      	29	; to 164
	135	[339]	GETTABLE 	11 0 -4	; "data"
	136	[339]	GETTABLE 	11 11 4
	137	[339]	GETTABLE 	12 0 -31	; "series"
	138	[339]	GETTABLE 	11 11 12
	139	[339]	EQ       	1 11 -12	; - "-"
	140	[339]	JMP      	23	; to 164
	141	[340]	MOVE     	11 10
	142	[340]	GETTABLE 	12 0 -4	; "data"
	143	[340]	GETTABLE 	12 12 4
	144	[340]	GETTABLE 	13 0 -31	; "series"
	145	[340]	GETTABLE 	12 12 13
	146	[340]	LOADK    	13 -26	; "\n"
	147	[340]	CONCAT   	10 11 13
	148	[341]	GETTABLE 	11 0 -5	; "browse_series"
	149	[341]	GETTABLE 	12 0 -4	; "data"
	150	[341]	GETTABLE 	12 12 4
	151	[341]	GETTABLE 	13 0 -31	; "series"
	152	[341]	GETTABLE 	12 12 13
	153	[341]	GETTABLE 	13 0 -5	; "browse_series"
	154	[341]	GETTABLE 	14 0 -4	; "data"
	155	[341]	GETTABLE 	14 14 4
	156	[341]	GETTABLE 	15 0 -31	; "series"
	157	[341]	GETTABLE 	14 14 15
	158	[341]	GETTABLE 	13 13 14
	159	[341]	TEST     	13 0 1
	160	[341]	JMP      	1	; to 162
	161	[341]	LOADK    	13 -33	; 0
	162	[341]	ADD      	13 13 -1	; - 1
	163	[341]	SETTABLE 	11 12 13
	164	[343]	EQ       	1 1 -34	; - "tags"
	165	[343]	JMP      	3	; to 169
	166	[343]	GETGLOBAL	11 -35	; SEARCH_TAGS
	167	[343]	TEST     	11 0 0
	168	[343]	JMP      	7	; to 176
	169	[344]	MOVE     	11 10
	170	[344]	GETTABLE 	12 0 -4	; "data"
	171	[344]	GETTABLE 	12 12 4
	172	[344]	GETTABLE 	13 0 -34	; "tags"
	173	[344]	GETTABLE 	12 12 13
	174	[344]	LOADK    	13 -26	; "\n"
	175	[344]	CONCAT   	10 11 13
	176	[346]	GETGLOBAL	11 -7	; SEARCH_CASESENSITIVE
	177	[346]	TEST     	11 0 1
	178	[346]	JMP      	5	; to 184
	179	[346]	GETGLOBAL	11 -10	; string
	180	[346]	GETTABLE 	11 11 -11	; "upper"
	181	[346]	MOVE     	12 10
	182	[346]	CALL     	11 2 2
	183	[346]	MOVE     	10 11
	184	[348]	GETGLOBAL	11 -10	; string
	185	[348]	GETTABLE 	11 11 -36	; "gmatch"
	186	[348]	GETTABLE 	12 0 -4	; "data"
	187	[348]	GETTABLE 	12 12 4
	188	[348]	GETTABLE 	13 0 -37	; "tags3"
	189	[348]	GETTABLE 	12 12 13
	190	[348]	LOADK    	13 -38	; "\t[^\t]+"
	191	[348]	CALL     	11 3 4
	192	[348]	JMP      	20	; to 213
	193	[349]	EQ       	1 14 -39	; - "\t"
	194	[349]	JMP      	18	; to 213
	195	[350]	GETTABLE 	15 0 -6	; "browse_tags"
	196	[350]	GETGLOBAL	16 -10	; string
	197	[350]	GETTABLE 	16 16 -40	; "sub"
	198	[350]	MOVE     	17 14
	199	[350]	LOADK    	18 -41	; 2
	200	[350]	CALL     	16 3 2
	201	[350]	GETTABLE 	17 0 -6	; "browse_tags"
	202	[350]	GETGLOBAL	18 -10	; string
	203	[350]	GETTABLE 	18 18 -40	; "sub"
	204	[350]	MOVE     	19 14
	205	[350]	LOADK    	20 -41	; 2
	206	[350]	CALL     	18 3 2
	207	[350]	GETTABLE 	17 17 18
	208	[350]	TEST     	17 0 1
	209	[350]	JMP      	1	; to 211
	210	[350]	LOADK    	17 -33	; 0
	211	[350]	ADD      	17 17 -1	; - 1
	212	[350]	SETTABLE 	15 16 17
	213	[348]	TFORLOOP 	11 1
	214	[351]	JMP      	-22	; to 193
	215	[355]	GETUPVAL 	11 2	; DocumentRegistry
	216	[355]	SELF     	11 11 -42	; "hasProvider"
	217	[355]	GETTABLE 	13 0 -4	; "data"
	218	[355]	GETTABLE 	13 13 4
	219	[355]	GETTABLE 	14 0 -30	; "path"
	220	[355]	GETTABLE 	13 13 14
	221	[355]	CALL     	11 3 2
	222	[355]	TEST     	11 0 0
	223	[355]	JMP      	54	; to 278
	224	[356]	EQ       	1 5 -9	; - ""
	225	[356]	JMP      	11	; to 237
	226	[357]	GETGLOBAL	11 -10	; string
	227	[357]	GETTABLE 	11 11 -23	; "find"
	228	[357]	MOVE     	12 10
	229	[357]	MOVE     	13 5
	230	[357]	LOADNIL  	14 14
	231	[357]	LOADBOOL 	15 1 0
	232	[357]	CALL     	11 5 2
	233	[357]	TEST     	11 0 0
	234	[357]	JMP      	43	; to 278
	235	[358]	ADD      	4 4 -1	; - 1
	236	[359]	JMP      	41	; to 278
	237	[361]	EQ       	0 1 -31	; - "series"
	238	[361]	JMP      	10	; to 249
	239	[362]	GETTABLE 	11 0 -5	; "browse_series"
	240	[362]	GETTABLE 	12 0 -4	; "data"
	241	[362]	GETTABLE 	12 12 4
	242	[362]	GETTABLE 	13 0 -31	; "series"
	243	[362]	GETTABLE 	12 12 13
	244	[362]	GETTABLE 	11 11 12
	245	[362]	TEST     	11 0 0
	246	[362]	JMP      	31	; to 278
	247	[363]	ADD      	4 4 -1	; - 1
	248	[364]	JMP      	29	; to 278
	249	[365]	EQ       	0 1 -34	; - "tags"
	250	[365]	JMP      	27	; to 278
	251	[366]	LOADBOOL 	11 0 0
	252	[367]	GETGLOBAL	12 -10	; string
	253	[367]	GETTABLE 	12 12 -36	; "gmatch"
	254	[367]	GETTABLE 	13 0 -4	; "data"
	255	[367]	GETTABLE 	13 13 4
	256	[367]	GETTABLE 	14 0 -37	; "tags3"
	257	[367]	GETTABLE 	13 13 14
	258	[367]	LOADK    	14 -38	; "\t[^\t]+"
	259	[367]	CALL     	12 3 4
	260	[367]	JMP      	12	; to 273
	261	[368]	EQ       	1 15 -39	; - "\t"
	262	[368]	JMP      	10	; to 273
	263	[368]	GETTABLE 	16 0 -6	; "browse_tags"
	264	[368]	GETGLOBAL	17 -10	; string
	265	[368]	GETTABLE 	17 17 -40	; "sub"
	266	[368]	MOVE     	18 15
	267	[368]	LOADK    	19 -41	; 2
	268	[368]	CALL     	17 3 2
	269	[368]	GETTABLE 	16 16 17
	270	[368]	TEST     	16 0 0
	271	[368]	JMP      	1	; to 273
	272	[369]	LOADBOOL 	11 1 0
	273	[367]	TFORLOOP 	12 1
	274	[370]	JMP      	-14	; to 261
	275	[372]	TEST     	11 0 0
	276	[372]	JMP      	1	; to 278
	277	[373]	ADD      	4 4 -1	; - 1
	278	[378]	GETTABLE 	11 0 -4	; "data"
	279	[378]	NEWTABLE 	12 9 0
	280	[378]	LOADK    	13 -12	; "-"
	281	[378]	LOADK    	14 -12	; "-"
	282	[378]	LOADK    	15 -12	; "-"
	283	[378]	LOADK    	16 -12	; "-"
	284	[378]	LOADK    	17 -12	; "-"
	285	[378]	LOADK    	18 -12	; "-"
	286	[378]	LOADK    	19 -12	; "-"
	287	[378]	LOADK    	20 -12	; "-"
	288	[378]	LOADK    	21 -12	; "-"
	289	[378]	SETLIST  	12 9 1	; 1
	290	[378]	SETTABLE 	11 4 12
	291	[378]	JMP      	-215	; to 77
	292	[380]	GETTABLE 	10 9 -21	; "close"
	293	[380]	CALL     	10 1 1
	294	[383]	GETTABLE 	9 0 -13	; "use_own_metadata_file"
	295	[383]	TEST     	9 0 1
	296	[383]	JMP      	394	; to 691
	297	[384]	GETUPVAL 	9 3	; logger
	298	[384]	GETTABLE 	9 9 -43	; "info"
	299	[384]	LOADK    	10 -44	; "FMSearch: Writing our own simplified metadata file . . ."
	300	[384]	CALL     	9 2 1
	301	[385]	GETGLOBAL	9 -14	; io
	302	[385]	GETTABLE 	9 9 -15	; "open"
	303	[385]	GETUPVAL 	10 1	; koreaderfile
	304	[385]	LOADK    	11 -45	; "w"
	305	[385]	CALL     	9 3 2
	306	[386]	SELF     	10 9 -46	; "write"
	307	[386]	LOADK    	12 -47	; "#metadata.koreader Version 1.1\n"
	308	[386]	CALL     	10 3 1
	309	[388]	GETGLOBAL	10 -14	; io
	310	[388]	GETTABLE 	10 10 -15	; "open"
	311	[388]	GETTABLE 	11 0 -48	; "metafile_1"
	312	[388]	LOADK    	12 -16	; "r"
	313	[388]	CALL     	10 3 2
	314	[388]	MOVE     	2 10
	315	[389]	SELF     	10 2 -17	; "read"
	316	[389]	CALL     	10 2 2
	317	[389]	MOVE     	3 10
	318	[390]	TEST     	3 0 0
	319	[390]	JMP      	310	; to 630
	320	[391]	EQ       	1 3 -49	; - "  }, "
	321	[391]	JMP      	2	; to 324
	322	[391]	EQ       	0 3 -50	; - "  }"
	323	[391]	JMP      	171	; to 495
	324	[394]	LOADK    	10 -9	; ""
	325	[395]	EQ       	0 1 -23	; - "find"
	326	[395]	JMP      	10	; to 337
	327	[395]	GETGLOBAL	11 -24	; SEARCH_AUTHORS
	328	[395]	TEST     	11 0 0
	329	[395]	JMP      	7	; to 337
	330	[395]	MOVE     	11 10
	331	[395]	GETTABLE 	12 0 -4	; "data"
	332	[395]	GETTABLE 	12 12 4
	333	[395]	GETTABLE 	13 0 -25	; "authors"
	334	[395]	GETTABLE 	12 12 13
	335	[395]	LOADK    	13 -26	; "\n"
	336	[395]	CONCAT   	10 11 13
	337	[396]	EQ       	0 1 -23	; - "find"
	338	[396]	JMP      	10	; to 349
	339	[396]	GETGLOBAL	11 -27	; SEARCH_TITLE
	340	[396]	TEST     	11 0 0
	341	[396]	JMP      	7	; to 349
	342	[396]	MOVE     	11 10
	343	[396]	GETTABLE 	12 0 -4	; "data"
	344	[396]	GETTABLE 	12 12 4
	345	[396]	GETTABLE 	13 0 -28	; "title"
	346	[396]	GETTABLE 	12 12 13
	347	[396]	LOADK    	13 -26	; "\n"
	348	[396]	CONCAT   	10 11 13
	349	[397]	EQ       	0 1 -23	; - "find"
	350	[397]	JMP      	10	; to 361
	351	[397]	GETGLOBAL	11 -29	; SEARCH_PATH
	352	[397]	TEST     	11 0 0
	353	[397]	JMP      	7	; to 361
	354	[397]	MOVE     	11 10
	355	[397]	GETTABLE 	12 0 -4	; "data"
	356	[397]	GETTABLE 	12 12 4
	357	[397]	GETTABLE 	13 0 -30	; "path"
	358	[397]	GETTABLE 	12 12 13
	359	[397]	LOADK    	13 -26	; "\n"
	360	[397]	CONCAT   	10 11 13
	361	[398]	EQ       	1 1 -31	; - "series"
	362	[398]	JMP      	3	; to 366
	363	[398]	GETGLOBAL	11 -32	; SEARCH_SERIES
	364	[398]	TEST     	11 0 0
	365	[398]	JMP      	29	; to 395
	366	[398]	GETTABLE 	11 0 -4	; "data"
	367	[398]	GETTABLE 	11 11 4
	368	[398]	GETTABLE 	12 0 -31	; "series"
	369	[398]	GETTABLE 	11 11 12
	370	[398]	EQ       	1 11 -12	; - "-"
	371	[398]	JMP      	23	; to 395
	372	[399]	MOVE     	11 10
	373	[399]	GETTABLE 	12 0 -4	; "data"
	374	[399]	GETTABLE 	12 12 4
	375	[399]	GETTABLE 	13 0 -31	; "series"
	376	[399]	GETTABLE 	12 12 13
	377	[399]	LOADK    	13 -26	; "\n"
	378	[399]	CONCAT   	10 11 13
	379	[400]	GETTABLE 	11 0 -5	; "browse_series"
	380	[400]	GETTABLE 	12 0 -4	; "data"
	381	[400]	GETTABLE 	12 12 4
	382	[400]	GETTABLE 	13 0 -31	; "series"
	383	[400]	GETTABLE 	12 12 13
	384	[400]	GETTABLE 	13 0 -5	; "browse_series"
	385	[400]	GETTABLE 	14 0 -4	; "data"
	386	[400]	GETTABLE 	14 14 4
	387	[400]	GETTABLE 	15 0 -31	; "series"
	388	[400]	GETTABLE 	14 14 15
	389	[400]	GETTABLE 	13 13 14
	390	[400]	TEST     	13 0 1
	391	[400]	JMP      	1	; to 393
	392	[400]	LOADK    	13 -33	; 0
	393	[400]	ADD      	13 13 -1	; - 1
	394	[400]	SETTABLE 	11 12 13
	395	[402]	EQ       	1 1 -34	; - "tags"
	396	[402]	JMP      	3	; to 400
	397	[402]	GETGLOBAL	11 -35	; SEARCH_TAGS
	398	[402]	TEST     	11 0 0
	399	[402]	JMP      	7	; to 407
	400	[402]	MOVE     	11 10
	401	[402]	GETTABLE 	12 0 -4	; "data"
	402	[402]	GETTABLE 	12 12 4
	403	[402]	GETTABLE 	13 0 -34	; "tags"
	404	[402]	GETTABLE 	12 12 13
	405	[402]	LOADK    	13 -26	; "\n"
	406	[402]	CONCAT   	10 11 13
	407	[403]	GETGLOBAL	11 -7	; SEARCH_CASESENSITIVE
	408	[403]	TEST     	11 0 1
	409	[403]	JMP      	5	; to 415
	410	[403]	GETGLOBAL	11 -10	; string
	411	[403]	GETTABLE 	11 11 -11	; "upper"
	412	[403]	MOVE     	12 10
	413	[403]	CALL     	11 2 2
	414	[403]	MOVE     	10 11
	415	[405]	LOADK    	11 -1	; 1
	416	[405]	LOADK    	12 -22	; 9
	417	[405]	LOADK    	13 -1	; 1
	418	[405]	FORPREP  	11 7	; to 426
	419	[406]	SELF     	15 9 -46	; "write"
	420	[406]	GETTABLE 	17 0 -4	; "data"
	421	[406]	GETTABLE 	17 17 4
	422	[406]	GETTABLE 	17 17 14
	423	[406]	LOADK    	18 -26	; "\n"
	424	[406]	CONCAT   	17 17 18
	425	[406]	CALL     	15 3 1
	426	[405]	FORLOOP  	11 -8	; to 419
	427	[409]	EQ       	1 5 -9	; - ""
	428	[409]	JMP      	11	; to 440
	429	[410]	GETGLOBAL	11 -10	; string
	430	[410]	GETTABLE 	11 11 -23	; "find"
	431	[410]	MOVE     	12 10
	432	[410]	MOVE     	13 5
	433	[410]	LOADNIL  	14 14
	434	[410]	LOADBOOL 	15 1 0
	435	[410]	CALL     	11 5 2
	436	[410]	TEST     	11 0 0
	437	[410]	JMP      	43	; to 481
	438	[411]	ADD      	4 4 -1	; - 1
	439	[412]	JMP      	41	; to 481
	440	[414]	EQ       	0 1 -31	; - "series"
	441	[414]	JMP      	10	; to 452
	442	[415]	GETTABLE 	11 0 -5	; "browse_series"
	443	[415]	GETTABLE 	12 0 -4	; "data"
	444	[415]	GETTABLE 	12 12 4
	445	[415]	GETTABLE 	13 0 -31	; "series"
	446	[415]	GETTABLE 	12 12 13
	447	[415]	GETTABLE 	11 11 12
	448	[415]	TEST     	11 0 0
	449	[415]	JMP      	31	; to 481
	450	[416]	ADD      	4 4 -1	; - 1
	451	[417]	JMP      	29	; to 481
	452	[418]	EQ       	0 1 -34	; - "tags"
	453	[418]	JMP      	27	; to 481
	454	[419]	LOADBOOL 	11 0 0
	455	[420]	GETGLOBAL	12 -10	; string
	456	[420]	GETTABLE 	12 12 -36	; "gmatch"
	457	[420]	GETTABLE 	13 0 -4	; "data"
	458	[420]	GETTABLE 	13 13 4
	459	[420]	GETTABLE 	14 0 -37	; "tags3"
	460	[420]	GETTABLE 	13 13 14
	461	[420]	LOADK    	14 -38	; "\t[^\t]+"
	462	[420]	CALL     	12 3 4
	463	[420]	JMP      	12	; to 476
	464	[421]	EQ       	1 15 -39	; - "\t"
	465	[421]	JMP      	10	; to 476
	466	[421]	GETTABLE 	16 0 -6	; "browse_tags"
	467	[421]	GETGLOBAL	17 -10	; string
	468	[421]	GETTABLE 	17 17 -40	; "sub"
	469	[421]	MOVE     	18 15
	470	[421]	LOADK    	19 -41	; 2
	471	[421]	CALL     	17 3 2
	472	[421]	GETTABLE 	16 16 17
	473	[421]	TEST     	16 0 0
	474	[421]	JMP      	1	; to 476
	475	[422]	LOADBOOL 	11 1 0
	476	[420]	TFORLOOP 	12 1
	477	[423]	JMP      	-14	; to 464
	478	[425]	TEST     	11 0 0
	479	[425]	JMP      	1	; to 481
	480	[426]	ADD      	4 4 -1	; - 1
	481	[431]	GETTABLE 	11 0 -4	; "data"
	482	[431]	NEWTABLE 	12 9 0
	483	[431]	LOADK    	13 -12	; "-"
	484	[431]	LOADK    	14 -12	; "-"
	485	[431]	LOADK    	15 -12	; "-"
	486	[431]	LOADK    	16 -12	; "-"
	487	[431]	LOADK    	17 -12	; "-"
	488	[431]	LOADK    	18 -12	; "-"
	489	[431]	LOADK    	19 -12	; "-"
	490	[431]	LOADK    	20 -12	; "-"
	491	[431]	LOADK    	21 -12	; "-"
	492	[431]	SETLIST  	12 9 1	; 1
	493	[431]	SETTABLE 	11 4 12
	494	[431]	JMP      	110	; to 605
	495	[433]	EQ       	0 3 -51	; - "    \"authors\": ["
	496	[433]	JMP      	4	; to 501
	497	[434]	MOVE     	10 8
	498	[434]	GETTABLE 	11 0 -25	; "authors"
	499	[434]	CALL     	10 2 1
	500	[434]	JMP      	104	; to 605
	501	[435]	EQ       	0 3 -52	; - "    \"tags\": ["
	502	[435]	JMP      	4	; to 507
	503	[436]	MOVE     	10 8
	504	[436]	GETTABLE 	11 0 -34	; "tags"
	505	[436]	CALL     	10 2 1
	506	[436]	JMP      	98	; to 605
	507	[437]	GETGLOBAL	10 -10	; string
	508	[437]	GETTABLE 	10 10 -40	; "sub"
	509	[437]	MOVE     	11 3
	510	[437]	LOADK    	12 -1	; 1
	511	[437]	LOADK    	13 -53	; 11
	512	[437]	CALL     	10 4 2
	513	[437]	EQ       	0 10 -54	; - "    \"title\""
	514	[437]	JMP      	10	; to 525
	515	[438]	GETTABLE 	10 0 -4	; "data"
	516	[438]	GETTABLE 	10 10 4
	517	[438]	GETTABLE 	11 0 -28	; "title"
	518	[438]	MOVE     	12 7
	519	[438]	MOVE     	13 3
	520	[438]	LOADK    	14 -55	; 15
	521	[438]	LOADK    	15 -56	; 3
	522	[438]	CALL     	12 4 2
	523	[438]	SETTABLE 	10 11 12
	524	[438]	JMP      	80	; to 605
	525	[439]	GETGLOBAL	10 -10	; string
	526	[439]	GETTABLE 	10 10 -40	; "sub"
	527	[439]	MOVE     	11 3
	528	[439]	LOADK    	12 -1	; 1
	529	[439]	LOADK    	13 -53	; 11
	530	[439]	CALL     	10 4 2
	531	[439]	EQ       	0 10 -57	; - "    \"lpath\""
	532	[439]	JMP      	33	; to 566
	533	[440]	GETTABLE 	10 0 -4	; "data"
	534	[440]	GETTABLE 	10 10 4
	535	[440]	GETTABLE 	11 0 -30	; "path"
	536	[440]	MOVE     	12 7
	537	[440]	MOVE     	13 3
	538	[440]	LOADK    	14 -55	; 15
	539	[440]	LOADK    	15 -56	; 3
	540	[440]	CALL     	12 4 2
	541	[440]	SETTABLE 	10 11 12
	542	[441]	TEST     	6 0 0
	543	[441]	JMP      	11	; to 555
	544	[442]	GETTABLE 	10 0 -4	; "data"
	545	[442]	GETTABLE 	10 10 4
	546	[442]	GETTABLE 	11 0 -30	; "path"
	547	[442]	GETGLOBAL	12 -58	; SEARCH_LIBRARY_PATH
	548	[442]	GETTABLE 	13 0 -4	; "data"
	549	[442]	GETTABLE 	13 13 4
	550	[442]	GETTABLE 	14 0 -30	; "path"
	551	[442]	GETTABLE 	13 13 14
	552	[442]	CONCAT   	12 12 13
	553	[442]	SETTABLE 	10 11 12
	554	[442]	JMP      	50	; to 605
	555	[444]	GETTABLE 	10 0 -4	; "data"
	556	[444]	GETTABLE 	10 10 4
	557	[444]	GETTABLE 	11 0 -30	; "path"
	558	[444]	GETGLOBAL	12 -59	; SEARCH_LIBRARY_PATH2
	559	[444]	GETTABLE 	13 0 -4	; "data"
	560	[444]	GETTABLE 	13 13 4
	561	[444]	GETTABLE 	14 0 -30	; "path"
	562	[444]	GETTABLE 	13 13 14
	563	[444]	CONCAT   	12 12 13
	564	[444]	SETTABLE 	10 11 12
	565	[445]	JMP      	39	; to 605
	566	[446]	GETGLOBAL	10 -10	; string
	567	[446]	GETTABLE 	10 10 -40	; "sub"
	568	[446]	MOVE     	11 3
	569	[446]	LOADK    	12 -1	; 1
	570	[446]	LOADK    	13 -60	; 12
	571	[446]	CALL     	10 4 2
	572	[446]	EQ       	0 10 -61	; - "    \"series\""
	573	[446]	JMP      	12	; to 586
	574	[446]	EQ       	1 3 -62	; - "    \"series\": null, "
	575	[446]	JMP      	10	; to 586
	576	[447]	GETTABLE 	10 0 -4	; "data"
	577	[447]	GETTABLE 	10 10 4
	578	[447]	GETTABLE 	11 0 -31	; "series"
	579	[447]	MOVE     	12 7
	580	[447]	MOVE     	13 3
	581	[447]	LOADK    	14 -63	; 16
	582	[447]	LOADK    	15 -56	; 3
	583	[447]	CALL     	12 4 2
	584	[447]	SETTABLE 	10 11 12
	585	[447]	JMP      	19	; to 605
	586	[448]	GETGLOBAL	10 -10	; string
	587	[448]	GETTABLE 	10 10 -40	; "sub"
	588	[448]	MOVE     	11 3
	589	[448]	LOADK    	12 -1	; 1
	590	[448]	LOADK    	13 -64	; 18
	591	[448]	CALL     	10 4 2
	592	[448]	EQ       	0 10 -65	; - "    \"series_index\""
	593	[448]	JMP      	11	; to 605
	594	[448]	EQ       	1 3 -66	; - "    \"series_index\": null, "
	595	[448]	JMP      	9	; to 605
	596	[449]	GETTABLE 	10 0 -4	; "data"
	597	[449]	GETTABLE 	10 10 4
	598	[449]	GETTABLE 	11 0 -67	; "series_index"
	599	[449]	MOVE     	12 7
	600	[449]	MOVE     	13 3
	601	[449]	LOADK    	14 -68	; 21
	602	[449]	LOADK    	15 -41	; 2
	603	[449]	CALL     	12 4 2
	604	[449]	SETTABLE 	10 11 12
	605	[451]	SELF     	10 2 -17	; "read"
	606	[451]	CALL     	10 2 2
	607	[451]	MOVE     	3 10
	608	[453]	TEST     	3 0 1
	609	[453]	JMP      	-292	; to 318
	610	[453]	TEST     	6 0 0
	611	[453]	JMP      	-294	; to 318
	612	[454]	EQ       	1 2 -69	; - nil
	613	[454]	JMP      	2	; to 616
	614	[454]	SELF     	10 2 -21	; "close"
	615	[454]	CALL     	10 2 1
	616	[455]	LOADBOOL 	6 0 0
	617	[457]	GETTABLE 	10 0 -70	; "metafile_2"
	618	[457]	TEST     	10 0 0
	619	[457]	JMP      	-302	; to 318
	620	[458]	GETGLOBAL	10 -14	; io
	621	[458]	GETTABLE 	10 10 -15	; "open"
	622	[458]	GETTABLE 	11 0 -70	; "metafile_2"
	623	[458]	LOADK    	12 -16	; "r"
	624	[458]	CALL     	10 3 2
	625	[458]	MOVE     	2 10
	626	[459]	SELF     	10 2 -17	; "read"
	627	[459]	CALL     	10 2 2
	628	[459]	MOVE     	3 10
	629	[461]	JMP      	-312	; to 318
	630	[463]	GETTABLE 	10 9 -21	; "close"
	631	[463]	CALL     	10 1 1
	632	[464]	GETUPVAL 	10 4	; lfs
	633	[464]	GETTABLE 	10 10 -71	; "attributes"
	634	[464]	GETUPVAL 	11 1	; koreaderfile
	635	[464]	LOADK    	12 -72	; "modification"
	636	[464]	CALL     	10 3 2
	637	[464]	GETUPVAL 	11 4	; lfs
	638	[464]	GETTABLE 	11 11 -71	; "attributes"
	639	[464]	GETTABLE 	12 0 -48	; "metafile_1"
	640	[464]	LOADK    	13 -72	; "modification"
	641	[464]	CALL     	11 3 2
	642	[464]	LT       	0 10 11
	643	[464]	JMP      	16	; to 660
	644	[465]	GETUPVAL 	10 4	; lfs
	645	[465]	GETTABLE 	10 10 -73	; "touch"
	646	[465]	GETUPVAL 	11 1	; koreaderfile
	647	[466]	GETUPVAL 	12 4	; lfs
	648	[466]	GETTABLE 	12 12 -71	; "attributes"
	649	[466]	GETTABLE 	13 0 -48	; "metafile_1"
	650	[466]	LOADK    	14 -72	; "modification"
	651	[466]	CALL     	12 3 2
	652	[466]	ADD      	12 12 -1	; - 1
	653	[467]	GETUPVAL 	13 4	; lfs
	654	[467]	GETTABLE 	13 13 -71	; "attributes"
	655	[467]	GETTABLE 	14 0 -48	; "metafile_1"
	656	[467]	LOADK    	15 -72	; "modification"
	657	[467]	CALL     	13 3 2
	658	[467]	ADD      	13 13 -1	; - 1
	659	[465]	CALL     	10 4 1
	660	[469]	GETTABLE 	10 0 -70	; "metafile_2"
	661	[469]	TEST     	10 0 0
	662	[469]	JMP      	28	; to 691
	663	[470]	GETUPVAL 	10 4	; lfs
	664	[470]	GETTABLE 	10 10 -71	; "attributes"
	665	[470]	GETUPVAL 	11 1	; koreaderfile
	666	[470]	LOADK    	12 -72	; "modification"
	667	[470]	CALL     	10 3 2
	668	[470]	GETUPVAL 	11 4	; lfs
	669	[470]	GETTABLE 	11 11 -71	; "attributes"
	670	[470]	GETTABLE 	12 0 -70	; "metafile_2"
	671	[470]	LOADK    	13 -72	; "modification"
	672	[470]	CALL     	11 3 2
	673	[470]	LT       	0 10 11
	674	[470]	JMP      	16	; to 691
	675	[471]	GETUPVAL 	10 4	; lfs
	676	[471]	GETTABLE 	10 10 -73	; "touch"
	677	[471]	GETUPVAL 	11 1	; koreaderfile
	678	[471]	GETUPVAL 	12 4	; lfs
	679	[471]	GETTABLE 	12 12 -71	; "attributes"
	680	[471]	GETTABLE 	13 0 -70	; "metafile_2"
	681	[471]	LOADK    	14 -72	; "modification"
	682	[471]	CALL     	12 3 2
	683	[471]	ADD      	12 12 -1	; - 1
	684	[471]	GETUPVAL 	13 4	; lfs
	685	[471]	GETTABLE 	13 13 -71	; "attributes"
	686	[471]	GETTABLE 	14 0 -70	; "metafile_2"
	687	[471]	LOADK    	15 -72	; "modification"
	688	[471]	CALL     	13 3 2
	689	[471]	ADD      	13 13 -1	; - 1
	690	[471]	CALL     	10 4 1
	691	[475]	SUB      	4 4 -1	; - 1
	692	[476]	SETTABLE 	0 -74 4	; "count" -
	693	[478]	GETTABLE 	9 0 -74	; "count"
	694	[478]	LT       	0 -33 9	; 0 -
	695	[478]	JMP      	14	; to 710
	696	[479]	GETTABLE 	9 0 -4	; "data"
	697	[479]	GETTABLE 	10 0 -74	; "count"
	698	[479]	ADD      	10 10 -1	; - 1
	699	[479]	SETTABLE 	9 10 -69	; - nil
	700	[480]	EQ       	0 1 -23	; - "find"
	701	[480]	JMP      	3	; to 705
	702	[481]	SELF     	9 0 -75	; "showresults"
	703	[481]	CALL     	9 2 1
	704	[481]	JMP      	19	; to 724
	705	[483]	SELF     	9 0 -76	; "browse"
	706	[483]	MOVE     	11 1
	707	[483]	LOADK    	12 -1	; 1
	708	[483]	CALL     	9 4 1
	709	[484]	JMP      	14	; to 724
	710	[486]	GETUPVAL 	9 5	; UIManager
	711	[486]	SELF     	9 9 -77	; "show"
	712	[486]	GETUPVAL 	11 6	; InfoMessage
	713	[486]	SELF     	11 11 -78	; "new"
	714	[486]	NEWTABLE 	13 0 1
	715	[487]	GETUPVAL 	14 7	; T
	716	[487]	GETUPVAL 	15 8	; _
	717	[487]	LOADK    	16 -80	; "No match for %1."
	718	[487]	CALL     	15 2 2
	719	[487]	GETTABLE 	16 0 -8	; "search_value"
	720	[487]	CALL     	14 3 2
	721	[487]	SETTABLE 	13 -79 14	; "text" -
	722	[486]	CALL     	11 3 0
	723	[486]	CALL     	9 0 1
	724	[490]	RETURN   	0 1

function <./frontend/apps/filemanager/filemanagersearch.lua:250,262> (45 instructions, 180 bytes at 0x7fbf2740a140)
3 params, 9 slots, 1 upvalue, 4 locals, 7 constants, 1 function
	1	[251]	GETGLOBAL	3 -1	; string
	2	[251]	GETTABLE 	3 3 -2	; "len"
	3	[251]	MOVE     	4 0
	4	[251]	CALL     	3 2 2
	5	[253]	GETGLOBAL	4 -1	; string
	6	[253]	GETTABLE 	4 4 -3	; "sub"
	7	[253]	MOVE     	5 0
	8	[253]	MOVE     	6 3
	9	[253]	MOVE     	7 3
	10	[253]	CALL     	4 4 2
	11	[253]	EQ       	0 4 -4	; - "\""
	12	[253]	JMP      	12	; to 25
	13	[254]	GETGLOBAL	4 -1	; string
	14	[254]	GETTABLE 	4 4 -3	; "sub"
	15	[254]	MOVE     	5 0
	16	[254]	MOVE     	6 1
	17	[254]	GETGLOBAL	7 -1	; string
	18	[254]	GETTABLE 	7 7 -2	; "len"
	19	[254]	MOVE     	8 0
	20	[254]	CALL     	7 2 2
	21	[254]	SUB      	7 7 -5	; - 1
	22	[254]	CALL     	4 4 2
	23	[254]	MOVE     	0 4
	24	[254]	JMP      	11	; to 36
	25	[256]	GETGLOBAL	4 -1	; string
	26	[256]	GETTABLE 	4 4 -3	; "sub"
	27	[256]	MOVE     	5 0
	28	[256]	MOVE     	6 1
	29	[256]	GETGLOBAL	7 -1	; string
	30	[256]	GETTABLE 	7 7 -2	; "len"
	31	[256]	MOVE     	8 0
	32	[256]	CALL     	7 2 2
	33	[256]	SUB      	7 7 2
	34	[256]	CALL     	4 4 2
	35	[256]	MOVE     	0 4
	36	[259]	GETGLOBAL	4 -1	; string
	37	[259]	GETTABLE 	4 4 -6	; "gsub"
	38	[259]	MOVE     	5 0
	39	[259]	LOADK    	6 -7	; "\\u([a-f0-9][a-f0-9][a-f0-9][a-f0-9])"
	40	[259]	CLOSURE  	7 0	; 0x7fbf2740a8f0
	41	[259]	GETUPVAL 	0 0	; util
	42	[259]	CALL     	4 4 2
	43	[259]	MOVE     	0 4
	44	[261]	RETURN   	0 2
	45	[262]	RETURN   	0 1

function <./frontend/apps/filemanager/filemanagersearch.lua:259,259> (9 instructions, 36 bytes at 0x7fbf2740a8f0)
1 param, 5 slots, 1 upvalue, 1 local, 3 constants, 0 functions
	1	[259]	GETUPVAL 	1 0	; util
	2	[259]	GETTABLE 	1 1 -1	; "unicodeCodepointToUtf8"
	3	[259]	GETGLOBAL	2 -2	; tonumber
	4	[259]	MOVE     	3 0
	5	[259]	LOADK    	4 -3	; 16
	6	[259]	CALL     	2 3 0
	7	[259]	TAILCALL 	1 0 0
	8	[259]	RETURN   	1 0
	9	[259]	RETURN   	0 1

function <./frontend/apps/filemanager/filemanagersearch.lua:265,294> (224 instructions, 896 bytes at 0x7fbf2740a870)
1 param, 9 slots, 5 upvalues, 2 locals, 22 constants, 0 functions
	1	[266]	GETUPVAL 	1 0	; self
	2	[266]	GETTABLE 	1 1 -1	; "data"
	3	[266]	GETUPVAL 	2 1	; i
	4	[266]	GETTABLE 	1 1 2
	5	[266]	SETTABLE 	1 0 -2	; - ""
	6	[267]	GETUPVAL 	1 0	; self
	7	[267]	GETTABLE 	1 1 -3	; "authors"
	8	[267]	EQ       	0 0 1
	9	[267]	JMP      	8	; to 18
	10	[268]	GETUPVAL 	1 0	; self
	11	[268]	GETTABLE 	1 1 -1	; "data"
	12	[268]	GETUPVAL 	2 1	; i
	13	[268]	GETTABLE 	1 1 2
	14	[268]	GETUPVAL 	2 0	; self
	15	[268]	GETTABLE 	2 2 -4	; "authors2"
	16	[268]	SETTABLE 	1 2 -2	; - ""
	17	[268]	JMP      	18	; to 36
	18	[269]	GETUPVAL 	1 0	; self
	19	[269]	GETTABLE 	1 1 -5	; "tags"
	20	[269]	EQ       	0 0 1
	21	[269]	JMP      	14	; to 36
	22	[270]	GETUPVAL 	1 0	; self
	23	[270]	GETTABLE 	1 1 -1	; "data"
	24	[270]	GETUPVAL 	2 1	; i
	25	[270]	GETTABLE 	1 1 2
	26	[270]	GETUPVAL 	2 0	; self
	27	[270]	GETTABLE 	2 2 -6	; "tags2"
	28	[270]	SETTABLE 	1 2 -2	; - ""
	29	[271]	GETUPVAL 	1 0	; self
	30	[271]	GETTABLE 	1 1 -1	; "data"
	31	[271]	GETUPVAL 	2 1	; i
	32	[271]	GETTABLE 	1 1 2
	33	[271]	GETUPVAL 	2 0	; self
	34	[271]	GETTABLE 	2 2 -7	; "tags3"
	35	[271]	SETTABLE 	1 2 -2	; - ""
	36	[273]	GETUPVAL 	1 2	; line
	37	[273]	EQ       	1 1 -8	; - "    ], "
	38	[273]	JMP      	110	; to 149
	39	[273]	GETUPVAL 	1 2	; line
	40	[273]	EQ       	1 1 -9	; - "    ]"
	41	[273]	JMP      	107	; to 149
	42	[274]	GETUPVAL 	1 3	; f
	43	[274]	SELF     	1 1 -10	; "read"
	44	[274]	CALL     	1 2 2
	45	[274]	SETUPVAL 	1 2	; line
	46	[275]	GETUPVAL 	1 2	; line
	47	[275]	EQ       	1 1 -8	; - "    ], "
	48	[275]	JMP      	-13	; to 36
	49	[275]	GETUPVAL 	1 2	; line
	50	[275]	EQ       	1 1 -9	; - "    ]"
	51	[275]	JMP      	-16	; to 36
	52	[276]	GETUPVAL 	1 0	; self
	53	[276]	GETTABLE 	1 1 -1	; "data"
	54	[276]	GETUPVAL 	2 1	; i
	55	[276]	GETTABLE 	1 1 2
	56	[276]	GETUPVAL 	2 0	; self
	57	[276]	GETTABLE 	2 2 -1	; "data"
	58	[276]	GETUPVAL 	3 1	; i
	59	[276]	GETTABLE 	2 2 3
	60	[276]	GETTABLE 	2 2 0
	61	[276]	LOADK    	3 -11	; ","
	62	[276]	GETUPVAL 	4 4	; ReplaceHexChars
	63	[276]	GETUPVAL 	5 2	; line
	64	[276]	LOADK    	6 -12	; 8
	65	[276]	LOADK    	7 -13	; 3
	66	[276]	CALL     	4 4 2
	67	[276]	CONCAT   	2 2 4
	68	[276]	SETTABLE 	1 0 2
	69	[277]	GETUPVAL 	1 0	; self
	70	[277]	GETTABLE 	1 1 -3	; "authors"
	71	[277]	EQ       	0 0 1
	72	[277]	JMP      	22	; to 95
	73	[278]	GETUPVAL 	1 0	; self
	74	[278]	GETTABLE 	1 1 -1	; "data"
	75	[278]	GETUPVAL 	2 1	; i
	76	[278]	GETTABLE 	1 1 2
	77	[278]	GETUPVAL 	2 0	; self
	78	[278]	GETTABLE 	2 2 -4	; "authors2"
	79	[278]	GETUPVAL 	3 0	; self
	80	[278]	GETTABLE 	3 3 -1	; "data"
	81	[278]	GETUPVAL 	4 1	; i
	82	[278]	GETTABLE 	3 3 4
	83	[278]	GETUPVAL 	4 0	; self
	84	[278]	GETTABLE 	4 4 -4	; "authors2"
	85	[278]	GETTABLE 	3 3 4
	86	[278]	LOADK    	4 -14	; " & "
	87	[278]	GETUPVAL 	5 4	; ReplaceHexChars
	88	[278]	GETUPVAL 	6 2	; line
	89	[278]	LOADK    	7 -12	; 8
	90	[278]	LOADK    	8 -13	; 3
	91	[278]	CALL     	5 4 2
	92	[278]	CONCAT   	3 3 5
	93	[278]	SETTABLE 	1 2 3
	94	[278]	JMP      	-59	; to 36
	95	[279]	GETUPVAL 	1 0	; self
	96	[279]	GETTABLE 	1 1 -5	; "tags"
	97	[279]	EQ       	0 0 1
	98	[279]	JMP      	-63	; to 36
	99	[280]	GETUPVAL 	1 4	; ReplaceHexChars
	100	[280]	GETUPVAL 	2 2	; line
	101	[280]	LOADK    	3 -12	; 8
	102	[280]	LOADK    	4 -13	; 3
	103	[280]	CALL     	1 4 2
	104	[281]	GETUPVAL 	2 0	; self
	105	[281]	GETTABLE 	2 2 -1	; "data"
	106	[281]	GETUPVAL 	3 1	; i
	107	[281]	GETTABLE 	2 2 3
	108	[281]	GETUPVAL 	3 0	; self
	109	[281]	GETTABLE 	3 3 -6	; "tags2"
	110	[281]	GETUPVAL 	4 0	; self
	111	[281]	GETTABLE 	4 4 -1	; "data"
	112	[281]	GETUPVAL 	5 1	; i
	113	[281]	GETTABLE 	4 4 5
	114	[281]	GETUPVAL 	5 0	; self
	115	[281]	GETTABLE 	5 5 -6	; "tags2"
	116	[281]	GETTABLE 	4 4 5
	117	[281]	LOADK    	5 -14	; " & "
	118	[281]	MOVE     	6 1
	119	[281]	CONCAT   	4 4 6
	120	[281]	SETTABLE 	2 3 4
	121	[282]	GETUPVAL 	2 0	; self
	122	[282]	GETTABLE 	2 2 -1	; "data"
	123	[282]	GETUPVAL 	3 1	; i
	124	[282]	GETTABLE 	2 2 3
	125	[282]	GETUPVAL 	3 0	; self
	126	[282]	GETTABLE 	3 3 -7	; "tags3"
	127	[282]	GETUPVAL 	4 0	; self
	128	[282]	GETTABLE 	4 4 -1	; "data"
	129	[282]	GETUPVAL 	5 1	; i
	130	[282]	GETTABLE 	4 4 5
	131	[282]	GETUPVAL 	5 0	; self
	132	[282]	GETTABLE 	5 5 -7	; "tags3"
	133	[282]	GETTABLE 	4 4 5
	134	[282]	LOADK    	5 -15	; "\t"
	135	[282]	MOVE     	6 1
	136	[282]	CONCAT   	4 4 6
	137	[282]	SETTABLE 	2 3 4
	138	[283]	GETUPVAL 	2 0	; self
	139	[283]	GETTABLE 	2 2 -16	; "browse_tags"
	140	[283]	GETUPVAL 	3 0	; self
	141	[283]	GETTABLE 	3 3 -16	; "browse_tags"
	142	[283]	GETTABLE 	3 3 1
	143	[283]	TEST     	3 0 1
	144	[283]	JMP      	1	; to 146
	145	[283]	LOADK    	3 -17	; 0
	146	[283]	ADD      	3 3 -18	; - 1
	147	[283]	SETTABLE 	2 1 3
	148	[285]	JMP      	-113	; to 36
	149	[287]	GETUPVAL 	1 0	; self
	150	[287]	GETTABLE 	1 1 -1	; "data"
	151	[287]	GETUPVAL 	2 1	; i
	152	[287]	GETTABLE 	1 1 2
	153	[287]	GETGLOBAL	2 -19	; string
	154	[287]	GETTABLE 	2 2 -20	; "sub"
	155	[287]	GETUPVAL 	3 0	; self
	156	[287]	GETTABLE 	3 3 -1	; "data"
	157	[287]	GETUPVAL 	4 1	; i
	158	[287]	GETTABLE 	3 3 4
	159	[287]	GETTABLE 	3 3 0
	160	[287]	LOADK    	4 -21	; 2
	161	[287]	CALL     	2 3 2
	162	[287]	SETTABLE 	1 0 2
	163	[288]	GETUPVAL 	1 0	; self
	164	[288]	GETTABLE 	1 1 -3	; "authors"
	165	[288]	EQ       	0 0 1
	166	[288]	JMP      	19	; to 186
	167	[289]	GETUPVAL 	1 0	; self
	168	[289]	GETTABLE 	1 1 -1	; "data"
	169	[289]	GETUPVAL 	2 1	; i
	170	[289]	GETTABLE 	1 1 2
	171	[289]	GETUPVAL 	2 0	; self
	172	[289]	GETTABLE 	2 2 -4	; "authors2"
	173	[289]	GETGLOBAL	3 -19	; string
	174	[289]	GETTABLE 	3 3 -20	; "sub"
	175	[289]	GETUPVAL 	4 0	; self
	176	[289]	GETTABLE 	4 4 -1	; "data"
	177	[289]	GETUPVAL 	5 1	; i
	178	[289]	GETTABLE 	4 4 5
	179	[289]	GETUPVAL 	5 0	; self
	180	[289]	GETTABLE 	5 5 -4	; "authors2"
	181	[289]	GETTABLE 	4 4 5
	182	[289]	LOADK    	5 -22	; 4
	183	[289]	CALL     	3 3 2
	184	[289]	SETTABLE 	1 2 3
	185	[289]	JMP      	38	; to 224
	186	[290]	GETUPVAL 	1 0	; self
	187	[290]	GETTABLE 	1 1 -5	; "tags"
	188	[290]	EQ       	0 0 1
	189	[290]	JMP      	34	; to 224
	190	[291]	GETUPVAL 	1 0	; self
	191	[291]	GETTABLE 	1 1 -1	; "data"
	192	[291]	GETUPVAL 	2 1	; i
	193	[291]	GETTABLE 	1 1 2
	194	[291]	GETUPVAL 	2 0	; self
	195	[291]	GETTABLE 	2 2 -6	; "tags2"
	196	[291]	GETGLOBAL	3 -19	; string
	197	[291]	GETTABLE 	3 3 -20	; "sub"
	198	[291]	GETUPVAL 	4 0	; self
	199	[291]	GETTABLE 	4 4 -1	; "data"
	200	[291]	GETUPVAL 	5 1	; i
	201	[291]	GETTABLE 	4 4 5
	202	[291]	GETUPVAL 	5 0	; self
	203	[291]	GETTABLE 	5 5 -6	; "tags2"
	204	[291]	GETTABLE 	4 4 5
	205	[291]	LOADK    	5 -22	; 4
	206	[291]	CALL     	3 3 2
	207	[291]	SETTABLE 	1 2 3
	208	[292]	GETUPVAL 	1 0	; self
	209	[292]	GETTABLE 	1 1 -1	; "data"
	210	[292]	GETUPVAL 	2 1	; i
	211	[292]	GETTABLE 	1 1 2
	212	[292]	GETUPVAL 	2 0	; self
	213	[292]	GETTABLE 	2 2 -7	; "tags3"
	214	[292]	GETUPVAL 	3 0	; self
	215	[292]	GETTABLE 	3 3 -1	; "data"
	216	[292]	GETUPVAL 	4 1	; i
	217	[292]	GETTABLE 	3 3 4
	218	[292]	GETUPVAL 	4 0	; self
	219	[292]	GETTABLE 	4 4 -7	; "tags3"
	220	[292]	GETTABLE 	3 3 4
	221	[292]	LOADK    	4 -15	; "\t"
	222	[292]	CONCAT   	3 3 4
	223	[292]	SETTABLE 	1 2 3
	224	[294]	RETURN   	0 1

function <./frontend/apps/filemanager/filemanagersearch.lua:492,522> (94 instructions, 376 bytes at 0x7fbf2740bc90)
2 params, 12 slots, 6 upvalues, 6 locals, 36 constants, 0 functions
	1	[493]	GETTABLE 	2 1 -1	; "info"
	2	[493]	TEST     	2 0 0
	3	[493]	JMP      	5	; to 9
	4	[493]	GETTABLE 	2 1 -1	; "info"
	5	[493]	SELF     	2 2 -2	; "len"
	6	[493]	CALL     	2 2 2
	7	[493]	LE       	0 2 -3	; - 0
	8	[493]	JMP      	1	; to 10
	9	[493]	RETURN   	0 1
	10	[495]	GETTABLE 	2 1 -4	; "notchecked"
	11	[495]	TEST     	2 0 0
	12	[495]	JMP      	41	; to 54
	13	[496]	GETTABLE 	2 1 -1	; "info"
	14	[496]	GETTABLE 	3 1 -5	; "path"
	15	[496]	CONCAT   	2 2 3
	16	[496]	SETTABLE 	1 -1 2	; "info" -
	17	[497]	GETGLOBAL	2 -6	; io
	18	[497]	GETTABLE 	2 2 -7	; "open"
	19	[497]	GETTABLE 	3 1 -5	; "path"
	20	[497]	LOADK    	4 -8	; "r"
	21	[497]	CALL     	2 3 2
	22	[498]	EQ       	0 2 -9	; - nil
	23	[498]	JMP      	8	; to 32
	24	[499]	GETTABLE 	3 1 -1	; "info"
	25	[499]	LOADK    	4 -10	; "\n"
	26	[499]	GETUPVAL 	5 0	; _
	27	[499]	LOADK    	6 -11	; "File not found."
	28	[499]	CALL     	5 2 2
	29	[499]	CONCAT   	3 3 5
	30	[499]	SETTABLE 	1 -1 3	; "info" -
	31	[499]	JMP      	21	; to 53
	32	[501]	GETTABLE 	3 1 -1	; "info"
	33	[501]	LOADK    	4 -10	; "\n"
	34	[501]	GETUPVAL 	5 0	; _
	35	[501]	LOADK    	6 -12	; "Size:"
	36	[501]	CALL     	5 2 2
	37	[501]	LOADK    	6 -13	; " "
	38	[501]	GETGLOBAL	7 -14	; string
	39	[501]	GETTABLE 	7 7 -15	; "format"
	40	[501]	LOADK    	8 -16	; "%4.1fM"
	41	[501]	GETUPVAL 	9 1	; lfs
	42	[501]	GETTABLE 	9 9 -17	; "attributes"
	43	[501]	GETTABLE 	10 1 -5	; "path"
	44	[501]	LOADK    	11 -18	; "size"
	45	[501]	CALL     	9 3 2
	46	[501]	DIV      	9 9 -19	; - 1024
	47	[501]	DIV      	9 9 -19	; - 1024
	48	[501]	CALL     	7 3 2
	49	[501]	CONCAT   	3 3 7
	50	[501]	SETTABLE 	1 -1 3	; "info" -
	51	[502]	SELF     	3 2 -20	; "close"
	52	[502]	CALL     	3 2 1
	53	[504]	SETTABLE 	1 -4 -21	; "notchecked" false
	54	[506]	LOADNIL  	2 2
	55	[507]	GETUPVAL 	3 2	; DocumentRegistry
	56	[507]	SELF     	3 3 -22	; "openDocument"
	57	[507]	GETTABLE 	5 1 -5	; "path"
	58	[507]	CALL     	3 3 2
	59	[508]	TEST     	3 0 0
	60	[508]	JMP      	11	; to 72
	61	[509]	GETTABLE 	4 3 -23	; "loadDocument"
	62	[509]	TEST     	4 0 0
	63	[509]	JMP      	3	; to 67
	64	[510]	SELF     	4 3 -23	; "loadDocument"
	65	[510]	LOADBOOL 	6 0 0
	66	[510]	CALL     	4 3 1
	67	[512]	SELF     	4 3 -24	; "getCoverPageImage"
	68	[512]	CALL     	4 2 2
	69	[512]	MOVE     	2 4
	70	[513]	SELF     	4 3 -20	; "close"
	71	[513]	CALL     	4 2 1
	72	[515]	GETGLOBAL	4 -25	; math
	73	[515]	GETTABLE 	4 4 -26	; "min"
	74	[515]	LOADK    	5 -27	; 240
	75	[515]	GETUPVAL 	6 3	; Screen
	76	[515]	SELF     	6 6 -28	; "getWidth"
	77	[515]	CALL     	6 2 2
	78	[515]	DIV      	6 6 -29	; - 3
	79	[515]	CALL     	4 3 2
	80	[516]	GETUPVAL 	5 4	; UIManager
	81	[516]	SELF     	5 5 -30	; "show"
	82	[516]	GETUPVAL 	7 5	; InfoMessage
	83	[516]	SELF     	7 7 -31	; "new"
	84	[516]	NEWTABLE 	9 0 4
	85	[517]	GETTABLE 	10 1 -1	; "info"
	86	[517]	SETTABLE 	9 -32 10	; "text" -
	87	[518]	SETTABLE 	9 -33 2	; "image" -
	88	[519]	SETTABLE 	9 -34 4	; "image_width" -
	89	[520]	DIV      	10 4 -36	; - 2
	90	[520]	MUL      	10 10 -29	; - 3
	91	[520]	SETTABLE 	9 -35 10	; "image_height" -
	92	[516]	CALL     	7 3 0
	93	[516]	CALL     	5 0 1
	94	[522]	RETURN   	0 1

function <./frontend/apps/filemanager/filemanagersearch.lua:524,570> (184 instructions, 736 bytes at 0x7fbf2740ba40)
1 param, 14 slots, 7 upvalues, 6 locals, 55 constants, 3 functions
	1	[525]	GETGLOBAL	1 -1	; require
	2	[525]	LOADK    	2 -2	; "apps/reader/readerui"
	3	[525]	CALL     	1 2 2
	4	[526]	GETUPVAL 	2 0	; CenterContainer
	5	[526]	SELF     	2 2 -3	; "new"
	6	[526]	NEWTABLE 	4 0 1
	7	[527]	GETUPVAL 	5 1	; Screen
	8	[527]	SELF     	5 5 -5	; "getSize"
	9	[527]	CALL     	5 2 2
	10	[527]	SETTABLE 	4 -4 5	; "dimen" -
	11	[526]	CALL     	2 3 2
	12	[529]	GETUPVAL 	3 2	; Menu
	13	[529]	SELF     	3 3 -3	; "new"
	14	[529]	NEWTABLE 	5 0 6
	15	[530]	GETUPVAL 	6 1	; Screen
	16	[530]	SELF     	6 6 -8	; "getWidth"
	17	[530]	CALL     	6 2 2
	18	[530]	SUB      	6 6 -9	; - 15
	19	[530]	SETTABLE 	5 -7 6	; "width" -
	20	[531]	GETUPVAL 	6 1	; Screen
	21	[531]	SELF     	6 6 -11	; "getHeight"
	22	[531]	CALL     	6 2 2
	23	[531]	SUB      	6 6 -9	; - 15
	24	[531]	SETTABLE 	5 -10 6	; "height" -
	25	[532]	SETTABLE 	5 -12 2	; "show_parent" -
	26	[533]	GETTABLE 	6 0 -13	; "onMenuHold"
	27	[533]	SETTABLE 	5 -13 6	; "onMenuHold" -
	28	[534]	GETUPVAL 	6 3	; Font
	29	[534]	SELF     	6 6 -15	; "getFace"
	30	[534]	LOADK    	8 -16	; "smallinfofont"
	31	[534]	CALL     	6 3 2
	32	[534]	SETTABLE 	5 -14 6	; "cface" -
	33	[535]	SETTABLE 	5 -17 0	; "_manager" -
	34	[529]	CALL     	3 3 2
	35	[536]	SETTABLE 	0 -6 3	; "search_menu" -
	36	[537]	GETGLOBAL	3 -18	; table
	37	[537]	GETTABLE 	3 3 -19	; "insert"
	38	[537]	MOVE     	4 2
	39	[537]	GETTABLE 	5 0 -6	; "search_menu"
	40	[537]	CALL     	3 3 1
	41	[538]	GETTABLE 	3 0 -6	; "search_menu"
	42	[540]	CLOSURE  	4 0	; 0x7fbf2740be70
	43	[540]	GETUPVAL 	0 4	; UIManager
	44	[540]	MOVE     	0 2
	45	[540]	SETTABLE 	3 -20 4	; "close_callback" -
	46	[541]	GETTABLE 	3 0 -21	; "use_previous_search_results"
	47	[541]	TEST     	3 0 1
	48	[541]	JMP      	119	; to 168
	49	[542]	NEWTABLE 	3 0 0
	50	[542]	SETTABLE 	0 -22 3	; "results" -
	51	[543]	LOADK    	3 -23	; 1
	52	[544]	GETTABLE 	4 0 -24	; "count"
	53	[544]	LE       	0 3 4
	54	[544]	JMP      	113	; to 168
	55	[545]	GETUPVAL 	4 5	; T
	56	[545]	GETUPVAL 	5 6	; _
	57	[545]	LOADK    	6 -25	; "Title: %1"
	58	[545]	CALL     	5 2 2
	59	[545]	GETTABLE 	6 0 -26	; "data"
	60	[545]	GETTABLE 	6 6 3
	61	[545]	GETTABLE 	7 0 -27	; "title"
	62	[545]	GETTABLE 	6 6 7
	63	[545]	TEST     	6 0 1
	64	[545]	JMP      	1	; to 66
	65	[545]	LOADK    	6 -28	; "-"
	66	[545]	CALL     	4 3 2
	67	[545]	LOADK    	5 -29	; "\n \n"
	68	[546]	GETUPVAL 	6 5	; T
	69	[546]	GETUPVAL 	7 6	; _
	70	[546]	LOADK    	8 -30	; "Author(s): %1"
	71	[546]	CALL     	7 2 2
	72	[546]	GETTABLE 	8 0 -26	; "data"
	73	[546]	GETTABLE 	8 8 3
	74	[546]	GETTABLE 	9 0 -31	; "authors2"
	75	[546]	GETTABLE 	8 8 9
	76	[546]	TEST     	8 0 1
	77	[546]	JMP      	1	; to 79
	78	[546]	LOADK    	8 -28	; "-"
	79	[546]	CALL     	6 3 2
	80	[546]	LOADK    	7 -29	; "\n \n"
	81	[547]	GETUPVAL 	8 5	; T
	82	[547]	GETUPVAL 	9 6	; _
	83	[547]	LOADK    	10 -32	; "Tags: %1"
	84	[547]	CALL     	9 2 2
	85	[547]	GETTABLE 	10 0 -26	; "data"
	86	[547]	GETTABLE 	10 10 3
	87	[547]	GETTABLE 	11 0 -33	; "tags2"
	88	[547]	GETTABLE 	10 10 11
	89	[547]	TEST     	10 0 1
	90	[547]	JMP      	1	; to 92
	91	[547]	LOADK    	10 -28	; "-"
	92	[547]	CALL     	8 3 2
	93	[547]	LOADK    	9 -29	; "\n \n"
	94	[548]	GETUPVAL 	10 5	; T
	95	[548]	GETUPVAL 	11 6	; _
	96	[548]	LOADK    	12 -34	; "Series: %1"
	97	[548]	CALL     	11 2 2
	98	[548]	GETTABLE 	12 0 -26	; "data"
	99	[548]	GETTABLE 	12 12 3
	100	[548]	GETTABLE 	13 0 -35	; "series"
	101	[548]	GETTABLE 	12 12 13
	102	[548]	TEST     	12 0 1
	103	[548]	JMP      	1	; to 105
	104	[548]	LOADK    	12 -28	; "-"
	105	[548]	CALL     	10 3 2
	106	[548]	CONCAT   	4 4 10
	107	[549]	GETTABLE 	5 0 -26	; "data"
	108	[549]	GETTABLE 	5 5 3
	109	[549]	GETTABLE 	6 0 -35	; "series"
	110	[549]	GETTABLE 	5 5 6
	111	[549]	EQ       	1 5 -28	; - "-"
	112	[549]	JMP      	14	; to 127
	113	[550]	MOVE     	5 4
	114	[550]	LOADK    	6 -36	; " ("
	115	[550]	GETGLOBAL	7 -37	; tostring
	116	[550]	GETTABLE 	8 0 -26	; "data"
	117	[550]	GETTABLE 	8 8 3
	118	[550]	GETTABLE 	9 0 -38	; "series_index"
	119	[550]	GETTABLE 	8 8 9
	120	[550]	CALL     	7 2 2
	121	[550]	SELF     	7 7 -39	; "gsub"
	122	[550]	LOADK    	9 -40	; ".0$"
	123	[550]	LOADK    	10 -41	; ""
	124	[550]	CALL     	7 4 2
	125	[550]	LOADK    	8 -42	; ")"
	126	[550]	CONCAT   	4 5 8
	127	[552]	MOVE     	5 4
	128	[552]	LOADK    	6 -29	; "\n \n"
	129	[552]	GETUPVAL 	7 6	; _
	130	[552]	LOADK    	8 -43	; "Path: "
	131	[552]	CALL     	7 2 2
	132	[552]	CONCAT   	4 5 7
	133	[553]	GETTABLE 	5 0 -26	; "data"
	134	[553]	GETTABLE 	5 5 3
	135	[553]	GETTABLE 	6 0 -44	; "path"
	136	[553]	GETTABLE 	5 5 6
	137	[554]	GETGLOBAL	6 -18	; table
	138	[554]	GETTABLE 	6 6 -19	; "insert"
	139	[554]	GETTABLE 	7 0 -22	; "results"
	140	[554]	NEWTABLE 	8 0 5
	141	[555]	SETTABLE 	8 -45 4	; "info" -
	142	[556]	SETTABLE 	8 -46 -47	; "notchecked" true
	143	[557]	GETTABLE 	9 0 -26	; "data"
	144	[557]	GETTABLE 	9 9 3
	145	[557]	GETTABLE 	10 0 -44	; "path"
	146	[557]	GETTABLE 	9 9 10
	147	[557]	SETTABLE 	8 -44 9	; "path" -
	148	[558]	GETTABLE 	9 0 -26	; "data"
	149	[558]	GETTABLE 	9 9 3
	150	[558]	GETTABLE 	10 0 -49	; "authors"
	151	[558]	GETTABLE 	9 9 10
	152	[558]	LOADK    	10 -50	; ": "
	153	[558]	GETTABLE 	11 0 -26	; "data"
	154	[558]	GETTABLE 	11 11 3
	155	[558]	GETTABLE 	12 0 -27	; "title"
	156	[558]	GETTABLE 	11 11 12
	157	[558]	CONCAT   	9 9 11
	158	[558]	SETTABLE 	8 -48 9	; "text" -
	159	[562]	CLOSURE  	9 1	; 0x7fbf2740ca10
	160	[562]	MOVE     	0 1
	161	[562]	MOVE     	0 5
	162	[562]	MOVE     	0 0
	163	[562]	SETTABLE 	8 -51 9	; "callback" -
	164	[554]	CALL     	6 3 1
	165	[564]	ADD      	3 3 -23	; - 1
	166	[564]	CLOSE    	4
	167	[564]	JMP      	-116	; to 52
	168	[567]	GETGLOBAL	3 -18	; table
	169	[567]	GETTABLE 	3 3 -52	; "sort"
	170	[567]	GETTABLE 	4 0 -22	; "results"
	171	[567]	CLOSURE  	5 2	; 0x7fbf2740ca90
	172	[567]	CALL     	3 3 1
	173	[568]	GETTABLE 	3 0 -6	; "search_menu"
	174	[568]	SELF     	3 3 -53	; "switchItemTable"
	175	[568]	GETUPVAL 	5 6	; _
	176	[568]	LOADK    	6 -54	; "Search Results"
	177	[568]	CALL     	5 2 2
	178	[568]	GETTABLE 	6 0 -22	; "results"
	179	[568]	CALL     	3 4 1
	180	[569]	GETUPVAL 	3 4	; UIManager
	181	[569]	SELF     	3 3 -55	; "show"
	182	[569]	MOVE     	5 2
	183	[569]	CALL     	3 3 1
	184	[570]	RETURN   	0 1

function <./frontend/apps/filemanager/filemanagersearch.lua:538,540> (5 instructions, 20 bytes at 0x7fbf2740be70)
0 params, 3 slots, 2 upvalues, 0 locals, 1 constant, 0 functions
	1	[539]	GETUPVAL 	0 0	; UIManager
	2	[539]	SELF     	0 0 -1	; "close"
	3	[539]	GETUPVAL 	2 1	; menu_container
	4	[539]	CALL     	0 3 1
	5	[540]	RETURN   	0 1

function <./frontend/apps/filemanager/filemanagersearch.lua:559,562> (9 instructions, 36 bytes at 0x7fbf2740ca10)
0 params, 3 slots, 3 upvalues, 0 locals, 3 constants, 0 functions
	1	[560]	GETUPVAL 	0 0	; ReaderUI
	2	[560]	SELF     	0 0 -1	; "showReader"
	3	[560]	GETUPVAL 	2 1	; book
	4	[560]	CALL     	0 3 1
	5	[561]	GETUPVAL 	0 2	; self
	6	[561]	GETTABLE 	0 0 -2	; "search_menu"
	7	[561]	SELF     	0 0 -3	; "onClose"
	8	[561]	CALL     	0 2 1
	9	[562]	RETURN   	0 1

function <./frontend/apps/filemanager/filemanagersearch.lua:567,567> (8 instructions, 32 bytes at 0x7fbf2740ca90)
2 params, 4 slots, 0 upvalues, 2 locals, 1 constant, 0 functions
	1	[567]	GETTABLE 	2 0 -1	; "text"
	2	[567]	GETTABLE 	3 1 -1	; "text"
	3	[567]	LT       	1 2 3
	4	[567]	JMP      	1	; to 6
	5	[567]	LOADBOOL 	2 0 1
	6	[567]	LOADBOOL 	2 1 0
	7	[567]	RETURN   	2 2
	8	[567]	RETURN   	0 1

function <./frontend/apps/filemanager/filemanagersearch.lua:572,687> (379 instructions, 1516 bytes at 0x7fbf27409700)
4 params, 21 slots, 8 upvalues, 24 locals, 69 constants, 5 functions
	1	[573]	GETGLOBAL	4 -1	; require
	2	[573]	LOADK    	5 -2	; "apps/reader/readerui"
	3	[573]	CALL     	4 2 2
	4	[574]	LOADBOOL 	5 0 0
	5	[575]	GETUPVAL 	6 0	; CenterContainer
	6	[575]	SELF     	6 6 -3	; "new"
	7	[575]	NEWTABLE 	8 0 1
	8	[576]	GETUPVAL 	9 1	; Screen
	9	[576]	SELF     	9 9 -5	; "getSize"
	10	[576]	CALL     	9 2 2
	11	[576]	SETTABLE 	8 -4 9	; "dimen" -
	12	[575]	CALL     	6 3 2
	13	[578]	GETUPVAL 	7 2	; Menu
	14	[578]	SELF     	7 7 -3	; "new"
	15	[578]	NEWTABLE 	9 0 6
	16	[579]	GETUPVAL 	10 1	; Screen
	17	[579]	SELF     	10 10 -8	; "getWidth"
	18	[579]	CALL     	10 2 2
	19	[579]	SUB      	10 10 -9	; - 15
	20	[579]	SETTABLE 	9 -7 10	; "width" -
	21	[580]	GETUPVAL 	10 1	; Screen
	22	[580]	SELF     	10 10 -11	; "getHeight"
	23	[580]	CALL     	10 2 2
	24	[580]	SUB      	10 10 -9	; - 15
	25	[580]	SETTABLE 	9 -10 10	; "height" -
	26	[581]	SETTABLE 	9 -12 6	; "show_parent" -
	27	[582]	GETTABLE 	10 0 -13	; "onMenuHold"
	28	[582]	SETTABLE 	9 -13 10	; "onMenuHold" -
	29	[583]	GETUPVAL 	10 3	; Font
	30	[583]	SELF     	10 10 -15	; "getFace"
	31	[583]	LOADK    	12 -16	; "smallinfofont"
	32	[583]	CALL     	10 3 2
	33	[583]	SETTABLE 	9 -14 10	; "cface" -
	34	[584]	SETTABLE 	9 -17 0	; "_manager" -
	35	[578]	CALL     	7 3 2
	36	[585]	SETTABLE 	0 -6 7	; "search_menu" -
	37	[586]	GETGLOBAL	7 -18	; table
	38	[586]	GETTABLE 	7 7 -19	; "insert"
	39	[586]	MOVE     	8 6
	40	[586]	GETTABLE 	9 0 -6	; "search_menu"
	41	[586]	CALL     	7 3 1
	42	[588]	GETTABLE 	7 0 -6	; "search_menu"
	43	[598]	CLOSURE  	8 0	; 0x7fbf2740a560
	44	[598]	GETUPVAL 	0 4	; UIManager
	45	[598]	MOVE     	0 6
	46	[598]	MOVE     	0 5
	47	[598]	MOVE     	0 0
	48	[598]	SETTABLE 	7 -20 8	; "close_callback" -
	49	[599]	LOADNIL  	7 8
	50	[601]	GETGLOBAL	9 -21	; SEARCH_CASESENSITIVE
	51	[601]	TEST     	9 0 0
	52	[601]	JMP      	5	; to 58
	53	[602]	GETTABLE 	9 0 -22	; "search_value"
	54	[602]	TESTSET  	7 9 1
	55	[602]	JMP      	1	; to 57
	56	[602]	LOADK    	7 -23	; ""
	57	[602]	JMP      	8	; to 66
	58	[604]	GETGLOBAL	9 -24	; string
	59	[604]	GETTABLE 	9 9 -25	; "upper"
	60	[604]	GETTABLE 	10 0 -22	; "search_value"
	61	[604]	TEST     	10 0 1
	62	[604]	JMP      	1	; to 64
	63	[604]	LOADK    	10 -23	; ""
	64	[604]	CALL     	9 2 2
	65	[604]	MOVE     	7 9
	66	[607]	EQ       	0 2 -26	; - 1
	67	[607]	JMP      	96	; to 164
	68	[608]	NEWTABLE 	9 0 0
	69	[608]	SETTABLE 	0 -27 9	; "results" -
	70	[609]	EQ       	0 1 -28	; - "series"
	71	[609]	JMP      	46	; to 118
	72	[610]	GETUPVAL 	9 5	; FFIUtil
	73	[610]	GETTABLE 	9 9 -29	; "orderedPairs"
	74	[610]	GETTABLE 	10 0 -30	; "browse_series"
	75	[610]	CALL     	9 2 4
	76	[610]	JMP      	38	; to 115
	77	[611]	MOVE     	8 12
	78	[612]	GETGLOBAL	14 -21	; SEARCH_CASESENSITIVE
	79	[612]	TEST     	14 0 1
	80	[612]	JMP      	5	; to 86
	81	[612]	GETGLOBAL	14 -24	; string
	82	[612]	GETTABLE 	14 14 -25	; "upper"
	83	[612]	MOVE     	15 8
	84	[612]	CALL     	14 2 2
	85	[612]	MOVE     	8 14
	86	[613]	GETGLOBAL	14 -24	; string
	87	[613]	GETTABLE 	14 14 -31	; "find"
	88	[613]	MOVE     	15 8
	89	[613]	MOVE     	16 7
	90	[613]	LOADNIL  	17 17
	91	[613]	LOADBOOL 	18 1 0
	92	[613]	CALL     	14 5 2
	93	[613]	TEST     	14 0 0
	94	[613]	JMP      	19	; to 114
	95	[614]	GETGLOBAL	14 -18	; table
	96	[614]	GETTABLE 	14 14 -19	; "insert"
	97	[614]	GETTABLE 	15 0 -27	; "results"
	98	[614]	NEWTABLE 	16 0 2
	99	[615]	MOVE     	17 12
	100	[615]	LOADK    	18 -33	; " ("
	101	[615]	GETGLOBAL	19 -34	; tostring
	102	[615]	GETTABLE 	20 0 -30	; "browse_series"
	103	[615]	GETTABLE 	20 20 12
	104	[615]	CALL     	19 2 2
	105	[615]	LOADK    	20 -35	; ")"
	106	[615]	CONCAT   	17 17 20
	107	[615]	SETTABLE 	16 -32 17	; "text" -
	108	[618]	CLOSURE  	17 1	; 0x7fbf274075b0
	109	[618]	MOVE     	0 0
	110	[618]	MOVE     	0 1
	111	[618]	MOVE     	0 12
	112	[618]	SETTABLE 	16 -36 17	; "callback" -
	113	[614]	CALL     	14 3 1
	114	[620]	CLOSE    	12
	115	[610]	TFORLOOP 	9 2
	116	[620]	JMP      	-40	; to 77
	117	[621]	JMP      	236	; to 354
	118	[623]	GETUPVAL 	9 5	; FFIUtil
	119	[623]	GETTABLE 	9 9 -29	; "orderedPairs"
	120	[623]	GETTABLE 	10 0 -37	; "browse_tags"
	121	[623]	CALL     	9 2 4
	122	[623]	JMP      	38	; to 161
	123	[624]	MOVE     	8 12
	124	[625]	GETGLOBAL	14 -21	; SEARCH_CASESENSITIVE
	125	[625]	TEST     	14 0 1
	126	[625]	JMP      	5	; to 132
	127	[625]	GETGLOBAL	14 -24	; string
	128	[625]	GETTABLE 	14 14 -25	; "upper"
	129	[625]	MOVE     	15 8
	130	[625]	CALL     	14 2 2
	131	[625]	MOVE     	8 14
	132	[626]	GETGLOBAL	14 -24	; string
	133	[626]	GETTABLE 	14 14 -31	; "find"
	134	[626]	MOVE     	15 8
	135	[626]	MOVE     	16 7
	136	[626]	LOADNIL  	17 17
	137	[626]	LOADBOOL 	18 1 0
	138	[626]	CALL     	14 5 2
	139	[626]	TEST     	14 0 0
	140	[626]	JMP      	19	; to 160
	141	[627]	GETGLOBAL	14 -18	; table
	142	[627]	GETTABLE 	14 14 -19	; "insert"
	143	[627]	GETTABLE 	15 0 -27	; "results"
	144	[627]	NEWTABLE 	16 0 2
	145	[628]	MOVE     	17 12
	146	[628]	LOADK    	18 -33	; " ("
	147	[628]	GETGLOBAL	19 -34	; tostring
	148	[628]	GETTABLE 	20 0 -37	; "browse_tags"
	149	[628]	GETTABLE 	20 20 12
	150	[628]	CALL     	19 2 2
	151	[628]	LOADK    	20 -35	; ")"
	152	[628]	CONCAT   	17 17 20
	153	[628]	SETTABLE 	16 -32 17	; "text" -
	154	[631]	CLOSURE  	17 2	; 0x7fbf27407830
	155	[631]	MOVE     	0 0
	156	[631]	MOVE     	0 1
	157	[631]	MOVE     	0 12
	158	[631]	SETTABLE 	16 -36 17	; "callback" -
	159	[627]	CALL     	14 3 1
	160	[633]	CLOSE    	12
	161	[623]	TFORLOOP 	9 2
	162	[633]	JMP      	-40	; to 123
	163	[635]	JMP      	190	; to 354
	164	[637]	LOADBOOL 	5 1 0
	165	[638]	NEWTABLE 	9 0 0
	166	[638]	SETTABLE 	0 -27 9	; "results" -
	167	[639]	LOADK    	9 -26	; 1
	168	[640]	GETTABLE 	10 0 -38	; "count"
	169	[640]	LE       	0 9 10
	170	[640]	JMP      	183	; to 354
	171	[641]	EQ       	0 1 -39	; - "tags"
	172	[641]	JMP      	14	; to 187
	173	[641]	GETTABLE 	10 0 -40	; "data"
	174	[641]	GETTABLE 	10 10 9
	175	[641]	GETTABLE 	11 0 -41	; "tags3"
	176	[641]	GETTABLE 	10 10 11
	177	[641]	SELF     	10 10 -31	; "find"
	178	[641]	LOADK    	12 -42	; "\t"
	179	[641]	MOVE     	13 3
	180	[641]	LOADK    	14 -42	; "\t"
	181	[641]	CONCAT   	12 12 14
	182	[641]	LOADNIL  	13 13
	183	[641]	LOADBOOL 	14 1 0
	184	[641]	CALL     	10 5 2
	185	[641]	TEST     	10 0 1
	186	[641]	JMP      	8	; to 195
	187	[641]	EQ       	0 1 -28	; - "series"
	188	[641]	JMP      	163	; to 352
	189	[641]	GETTABLE 	10 0 -40	; "data"
	190	[641]	GETTABLE 	10 10 9
	191	[641]	GETTABLE 	11 0 -28	; "series"
	192	[641]	GETTABLE 	10 10 11
	193	[641]	EQ       	0 3 10
	194	[641]	JMP      	157	; to 352
	195	[642]	GETUPVAL 	10 6	; T
	196	[642]	GETUPVAL 	11 7	; _
	197	[642]	LOADK    	12 -43	; "Title: %1"
	198	[642]	CALL     	11 2 2
	199	[642]	GETTABLE 	12 0 -40	; "data"
	200	[642]	GETTABLE 	12 12 9
	201	[642]	GETTABLE 	13 0 -44	; "title"
	202	[642]	GETTABLE 	12 12 13
	203	[642]	TEST     	12 0 1
	204	[642]	JMP      	1	; to 206
	205	[642]	LOADK    	12 -45	; "-"
	206	[642]	CALL     	10 3 2
	207	[642]	LOADK    	11 -46	; "\n \n"
	208	[643]	GETUPVAL 	12 6	; T
	209	[643]	GETUPVAL 	13 7	; _
	210	[643]	LOADK    	14 -47	; "Author(s): %1"
	211	[643]	CALL     	13 2 2
	212	[643]	GETTABLE 	14 0 -40	; "data"
	213	[643]	GETTABLE 	14 14 9
	214	[643]	GETTABLE 	15 0 -48	; "authors2"
	215	[643]	GETTABLE 	14 14 15
	216	[643]	TEST     	14 0 1
	217	[643]	JMP      	1	; to 219
	218	[643]	LOADK    	14 -45	; "-"
	219	[643]	CALL     	12 3 2
	220	[643]	LOADK    	13 -46	; "\n \n"
	221	[644]	GETUPVAL 	14 6	; T
	222	[644]	GETUPVAL 	15 7	; _
	223	[644]	LOADK    	16 -49	; "Tags: %1"
	224	[644]	CALL     	15 2 2
	225	[644]	GETTABLE 	16 0 -40	; "data"
	226	[644]	GETTABLE 	16 16 9
	227	[644]	GETTABLE 	17 0 -50	; "tags2"
	228	[644]	GETTABLE 	16 16 17
	229	[644]	TEST     	16 0 1
	230	[644]	JMP      	1	; to 232
	231	[644]	LOADK    	16 -45	; "-"
	232	[644]	CALL     	14 3 2
	233	[644]	LOADK    	15 -46	; "\n \n"
	234	[645]	GETUPVAL 	16 6	; T
	235	[645]	GETUPVAL 	17 7	; _
	236	[645]	LOADK    	18 -51	; "Series: %1"
	237	[645]	CALL     	17 2 2
	238	[645]	GETTABLE 	18 0 -40	; "data"
	239	[645]	GETTABLE 	18 18 9
	240	[645]	GETTABLE 	19 0 -28	; "series"
	241	[645]	GETTABLE 	18 18 19
	242	[645]	TEST     	18 0 1
	243	[645]	JMP      	1	; to 245
	244	[645]	LOADK    	18 -45	; "-"
	245	[645]	CALL     	16 3 2
	246	[645]	CONCAT   	10 10 16
	247	[646]	GETTABLE 	11 0 -40	; "data"
	248	[646]	GETTABLE 	11 11 9
	249	[646]	GETTABLE 	12 0 -28	; "series"
	250	[646]	GETTABLE 	11 11 12
	251	[646]	EQ       	1 11 -45	; - "-"
	252	[646]	JMP      	14	; to 267
	253	[647]	MOVE     	11 10
	254	[647]	LOADK    	12 -33	; " ("
	255	[647]	GETGLOBAL	13 -34	; tostring
	256	[647]	GETTABLE 	14 0 -40	; "data"
	257	[647]	GETTABLE 	14 14 9
	258	[647]	GETTABLE 	15 0 -52	; "series_index"
	259	[647]	GETTABLE 	14 14 15
	260	[647]	CALL     	13 2 2
	261	[647]	SELF     	13 13 -53	; "gsub"
	262	[647]	LOADK    	15 -54	; ".0$"
	263	[647]	LOADK    	16 -23	; ""
	264	[647]	CALL     	13 4 2
	265	[647]	LOADK    	14 -35	; ")"
	266	[647]	CONCAT   	10 11 14
	267	[649]	MOVE     	11 10
	268	[649]	LOADK    	12 -46	; "\n \n"
	269	[649]	GETUPVAL 	13 7	; _
	270	[649]	LOADK    	14 -55	; "Path: "
	271	[649]	CALL     	13 2 2
	272	[649]	CONCAT   	10 11 13
	273	[650]	GETTABLE 	11 0 -40	; "data"
	274	[650]	GETTABLE 	11 11 9
	275	[650]	GETTABLE 	12 0 -56	; "path"
	276	[650]	GETTABLE 	11 11 12
	277	[651]	LOADNIL  	12 12
	278	[652]	EQ       	0 1 -28	; - "series"
	279	[652]	JMP      	43	; to 323
	280	[653]	GETTABLE 	13 0 -40	; "data"
	281	[653]	GETTABLE 	13 13 9
	282	[653]	GETTABLE 	14 0 -52	; "series_index"
	283	[653]	GETTABLE 	13 13 14
	284	[653]	EQ       	0 13 -57	; - "0.0"
	285	[653]	JMP      	12	; to 298
	286	[654]	GETTABLE 	13 0 -40	; "data"
	287	[654]	GETTABLE 	13 13 9
	288	[654]	GETTABLE 	14 0 -44	; "title"
	289	[654]	GETTABLE 	13 13 14
	290	[654]	LOADK    	14 -33	; " ("
	291	[654]	GETTABLE 	15 0 -40	; "data"
	292	[654]	GETTABLE 	15 15 9
	293	[654]	GETTABLE 	16 0 -58	; "authors"
	294	[654]	GETTABLE 	15 15 16
	295	[654]	LOADK    	16 -35	; ")"
	296	[654]	CONCAT   	12 13 16
	297	[654]	JMP      	35	; to 333
	298	[656]	GETGLOBAL	13 -24	; string
	299	[656]	GETTABLE 	13 13 -59	; "format"
	300	[656]	LOADK    	14 -60	; "%6.1f"
	301	[656]	GETTABLE 	15 0 -40	; "data"
	302	[656]	GETTABLE 	15 15 9
	303	[656]	GETTABLE 	16 0 -52	; "series_index"
	304	[656]	GETTABLE 	15 15 16
	305	[656]	SELF     	15 15 -53	; "gsub"
	306	[656]	LOADK    	17 -54	; ".0$"
	307	[656]	LOADK    	18 -23	; ""
	308	[656]	CALL     	15 4 0
	309	[656]	CALL     	13 0 2
	310	[656]	LOADK    	14 -61	; ": "
	311	[656]	GETTABLE 	15 0 -40	; "data"
	312	[656]	GETTABLE 	15 15 9
	313	[656]	GETTABLE 	16 0 -44	; "title"
	314	[656]	GETTABLE 	15 15 16
	315	[656]	LOADK    	16 -33	; " ("
	316	[656]	GETTABLE 	17 0 -40	; "data"
	317	[656]	GETTABLE 	17 17 9
	318	[656]	GETTABLE 	18 0 -58	; "authors"
	319	[656]	GETTABLE 	17 17 18
	320	[656]	LOADK    	18 -35	; ")"
	321	[656]	CONCAT   	12 13 18
	322	[657]	JMP      	10	; to 333
	323	[659]	GETTABLE 	13 0 -40	; "data"
	324	[659]	GETTABLE 	13 13 9
	325	[659]	GETTABLE 	14 0 -58	; "authors"
	326	[659]	GETTABLE 	13 13 14
	327	[659]	LOADK    	14 -61	; ": "
	328	[659]	GETTABLE 	15 0 -40	; "data"
	329	[659]	GETTABLE 	15 15 9
	330	[659]	GETTABLE 	16 0 -44	; "title"
	331	[659]	GETTABLE 	15 15 16
	332	[659]	CONCAT   	12 13 15
	333	[661]	GETGLOBAL	13 -18	; table
	334	[661]	GETTABLE 	13 13 -19	; "insert"
	335	[661]	GETTABLE 	14 0 -27	; "results"
	336	[661]	NEWTABLE 	15 0 5
	337	[662]	SETTABLE 	15 -32 12	; "text" -
	338	[663]	SETTABLE 	15 -62 10	; "info" -
	339	[664]	SETTABLE 	15 -63 -64	; "notchecked" true
	340	[665]	GETTABLE 	16 0 -40	; "data"
	341	[665]	GETTABLE 	16 16 9
	342	[665]	GETTABLE 	17 0 -56	; "path"
	343	[665]	GETTABLE 	16 16 17
	344	[665]	SETTABLE 	15 -56 16	; "path" -
	345	[669]	CLOSURE  	16 3	; 0x7fbf2740ccf0
	346	[669]	MOVE     	0 4
	347	[669]	MOVE     	0 11
	348	[669]	MOVE     	0 0
	349	[669]	SETTABLE 	15 -36 16	; "callback" -
	350	[661]	CALL     	13 3 1
	351	[670]	CLOSE    	10
	352	[672]	ADD      	9 9 -26	; - 1
	353	[672]	JMP      	-186	; to 168
	354	[676]	LOADNIL  	9 9
	355	[677]	EQ       	0 2 -26	; - 1
	356	[677]	JMP      	7	; to 364
	357	[678]	GETUPVAL 	10 7	; _
	358	[678]	LOADK    	11 -65	; "Browse"
	359	[678]	CALL     	10 2 2
	360	[678]	LOADK    	11 -66	; " "
	361	[678]	MOVE     	12 1
	362	[678]	CONCAT   	9 10 12
	363	[678]	JMP      	1	; to 365
	364	[680]	MOVE     	9 3
	365	[683]	GETGLOBAL	10 -18	; table
	366	[683]	GETTABLE 	10 10 -67	; "sort"
	367	[683]	GETTABLE 	11 0 -27	; "results"
	368	[683]	CLOSURE  	12 4	; 0x7fbf2740d410
	369	[683]	CALL     	10 3 1
	370	[685]	GETTABLE 	10 0 -6	; "search_menu"
	371	[685]	SELF     	10 10 -68	; "switchItemTable"
	372	[685]	MOVE     	12 9
	373	[685]	GETTABLE 	13 0 -27	; "results"
	374	[685]	CALL     	10 4 1
	375	[686]	GETUPVAL 	10 4	; UIManager
	376	[686]	SELF     	10 10 -69	; "show"
	377	[686]	MOVE     	12 6
	378	[686]	CALL     	10 3 1
	379	[687]	RETURN   	0 1

function <./frontend/apps/filemanager/filemanagersearch.lua:588,598> (30 instructions, 120 bytes at 0x7fbf2740a560)
0 params, 3 slots, 4 upvalues, 0 locals, 11 constants, 0 functions
	1	[589]	GETUPVAL 	0 0	; UIManager
	2	[589]	SELF     	0 0 -1	; "close"
	3	[589]	GETUPVAL 	2 1	; menu_container
	4	[589]	CALL     	0 3 1
	5	[590]	GETUPVAL 	0 2	; restart_me
	6	[590]	TEST     	0 0 0
	7	[590]	JMP      	22	; to 30
	8	[591]	GETGLOBAL	0 -2	; string
	9	[591]	GETTABLE 	0 0 -3	; "len"
	10	[591]	GETUPVAL 	1 3	; self
	11	[591]	GETTABLE 	1 1 -4	; "search_value"
	12	[591]	CALL     	0 2 2
	13	[591]	LT       	1 -5 0	; 0 -
	14	[591]	JMP      	4	; to 19
	15	[591]	GETUPVAL 	0 3	; self
	16	[591]	GETTABLE 	0 0 -6	; "lastsearch"
	17	[591]	EQ       	1 0 -7	; - "find"
	18	[591]	JMP      	11	; to 30
	19	[592]	GETUPVAL 	0 3	; self
	20	[592]	SETTABLE 	0 -8 -9	; "use_previous_search_results" true
	21	[593]	GETUPVAL 	0 3	; self
	22	[593]	SELF     	0 0 -10	; "getCalibre"
	23	[593]	LOADK    	2 -11	; 1
	24	[593]	CALL     	0 3 1
	25	[594]	GETUPVAL 	0 3	; self
	26	[594]	SELF     	0 0 -7	; "find"
	27	[594]	GETUPVAL 	2 3	; self
	28	[594]	GETTABLE 	2 2 -6	; "lastsearch"
	29	[594]	CALL     	0 3 1
	30	[598]	RETURN   	0 1

function <./frontend/apps/filemanager/filemanagersearch.lua:616,618> (7 instructions, 28 bytes at 0x7fbf274075b0)
0 params, 5 slots, 3 upvalues, 0 locals, 2 constants, 0 functions
	1	[617]	GETUPVAL 	0 0	; self
	2	[617]	SELF     	0 0 -1	; "browse"
	3	[617]	GETUPVAL 	2 1	; option
	4	[617]	LOADK    	3 -2	; 2
	5	[617]	GETUPVAL 	4 2	; v
	6	[617]	CALL     	0 5 1
	7	[618]	RETURN   	0 1

function <./frontend/apps/filemanager/filemanagersearch.lua:629,631> (7 instructions, 28 bytes at 0x7fbf27407830)
0 params, 5 slots, 3 upvalues, 0 locals, 2 constants, 0 functions
	1	[630]	GETUPVAL 	0 0	; self
	2	[630]	SELF     	0 0 -1	; "browse"
	3	[630]	GETUPVAL 	2 1	; option
	4	[630]	LOADK    	3 -2	; 2
	5	[630]	GETUPVAL 	4 2	; v
	6	[630]	CALL     	0 5 1
	7	[631]	RETURN   	0 1

function <./frontend/apps/filemanager/filemanagersearch.lua:666,669> (9 instructions, 36 bytes at 0x7fbf2740ccf0)
0 params, 3 slots, 3 upvalues, 0 locals, 3 constants, 0 functions
	1	[667]	GETUPVAL 	0 0	; ReaderUI
	2	[667]	SELF     	0 0 -1	; "showReader"
	3	[667]	GETUPVAL 	2 1	; book
	4	[667]	CALL     	0 3 1
	5	[668]	GETUPVAL 	0 2	; self
	6	[668]	GETTABLE 	0 0 -2	; "search_menu"
	7	[668]	SELF     	0 0 -3	; "onClose"
	8	[668]	CALL     	0 2 1
	9	[669]	RETURN   	0 1

function <./frontend/apps/filemanager/filemanagersearch.lua:683,683> (8 instructions, 32 bytes at 0x7fbf2740d410)
2 params, 4 slots, 0 upvalues, 2 locals, 1 constant, 0 functions
	1	[683]	GETTABLE 	2 0 -1	; "text"
	2	[683]	GETTABLE 	3 1 -1	; "text"
	3	[683]	LT       	1 2 3
	4	[683]	JMP      	1	; to 6
	5	[683]	LOADBOOL 	2 0 1
	6	[683]	LOADBOOL 	2 1 0
	7	[683]	RETURN   	2 2
	8	[683]	RETURN   	0 1
