-- BYTECODE -- filemanagersetdefaults.lua:21-29
0001    UGET     0   0      ; DataStorage
0002    MOV      1   0
0003    TGETS    0   0   0  ; "getDataDir"
0004    CALL     0   2   2
0005    KSTR     1   1      ; "/defaults.lua"
0006    CAT      0   0   1
0007    UGET     1   1      ; isAndroid
0008    ISF          1
0009    JMP      2 => 0015
0010    UGET     1   2      ; android
0011    TGETS    1   1   2  ; "dir"
0012    KSTR     2   1      ; "/defaults.lua"
0013    CAT      0   1   2
0014    JMP      1 => 0019
0015 => UGET     1   3      ; is_appimage
0016    ISF          1
0017    JMP      2 => 0019
0018    KSTR     0   3      ; "defaults.lua"
0019 => RET1     0   2

-- BYTECODE -- filemanagersetdefaults.lua:47-50
0001    UGET     0   0      ; self
0002    KPRI     1   2
0003    TSETS    1   0   0  ; "EditConfirmed"
0004    UGET     0   0      ; self
0005    MOV      1   0
0006    TGETS    0   0   1  ; "init"
0007    CALL     0   1   2
0008    RET0     0   1

-- BYTECODE -- filemanagersetdefaults.lua:43-55
0001    UGET     1   0      ; SetDefaults
0002    TGETS    1   1   0  ; "EditConfirmed"
0003    IST          1
0004    JMP      1 => 0021
0005    UGET     1   1      ; UIManager
0006    MOV      2   1
0007    TGETS    1   1   1  ; "show"
0008    UGET     3   2      ; ConfirmBox
0009    MOV      4   3
0010    TGETS    3   3   2  ; "new"
0011    TDUP     5   4
0012    UGET     6   3      ; _
0013    KSTR     7   3      ; "Some changes will not work until the nex"~
0014    CALL     6   2   2
0015    TSETS    6   5   5  ; "text"
0016    FNEW     6   6      ; filemanagersetdefaults.lua:47
0017    TSETS    6   5   7  ; "ok_callback"
0018    CALL     3   0   3
0019    CALLM    1   1   1
0020    JMP      1 => 0024
0021 => MOV      2   0
0022    TGETS    1   0   8  ; "init"
0023    CALL     1   1   2
0024 => UCLO     0 => 0025
0025 => RET0     0   1

-- BYTECODE -- filemanagersetdefaults.lua:87-89
0001    UGET     0   0      ; UIManager
0002    MOV      1   0
0003    TGETS    0   0   0  ; "setDirty"
0004    KPRI     2   0
0005    KSTR     3   1      ; "partial"
0006    CALL     0   1   4
0007    RET0     0   1

-- BYTECODE -- filemanagersetdefaults.lua:100-102
0001    TGETS    2   1   0  ; "callback"
0002    CALL     2   1   1
0003    RET0     0   1

-- BYTECODE -- filemanagersetdefaults.lua:105-109
0001    UGET     0   0      ; logger
0002    TGETS    0   0   0  ; "dbg"
0003    KSTR     1   1      ; "Closing defaults menu"
0004    CALL     0   1   2
0005    UGET     0   1      ; self
0006    MOV      1   0
0007    TGETS    0   0   2  ; "saveBeforeExit"
0008    CALL     0   1   2
0009    UGET     0   2      ; UIManager
0010    MOV      1   0
0011    TGETS    0   0   3  ; "close"
0012    UGET     2   3      ; menu_container
0013    CALL     0   1   3
0014    RET0     0   1

-- BYTECODE -- filemanagersetdefaults.lua:114-116
0001    UGET     0   0      ; self
0002    MOV      1   0
0003    TGETS    0   0   0  ; "close"
0004    CALL     0   1   2
0005    RET0     0   1

-- BYTECODE -- filemanagersetdefaults.lua:134-142
0001    UGET     0   0      ; self
0002    TGETS    0   0   0  ; "defaults_value"
0003    UGET     1   1      ; i
0004    KPRI     2   2
0005    TSETV    2   0   1
0006    GGET     0   1      ; "_G"
0007    UGET     1   2      ; setting_name
0008    KPRI     2   2
0009    TSETV    2   0   1
0010    UGET     0   0      ; self
0011    KPRI     1   2
0012    TSETS    1   0   2  ; "settings_changed"
0013    UGET     0   0      ; self
0014    TGETS    0   0   3  ; "changed"
0015    UGET     1   1      ; i
0016    KPRI     2   2
0017    TSETV    2   0   1
0018    UGET     0   0      ; self
0019    TGETS    0   0   4  ; "results"
0020    UGET     1   1      ; i
0021    TGETV    0   0   1
0022    UGET     1   0      ; self
0023    MOV      2   1
0024    TGETS    1   1   6  ; "build_setting"
0025    UGET     3   1      ; i
0026    CALL     1   2   3
0027    TSETS    1   0   5  ; "text"
0028    UGET     0   0      ; self
0029    MOV      1   0
0030    TGETS    0   0   7  ; "close"
0031    CALL     0   1   2
0032    UGET     0   0      ; self
0033    TGETS    0   0   8  ; "defaults_menu"
0034    MOV      1   0
0035    TGETS    0   0   9  ; "switchItemTable"
0036    KSTR     2  10      ; "Defaults"
0037    UGET     3   0      ; self
0038    TGETS    3   3   4  ; "results"
0039    UGET     4   1      ; i
0040    CALL     0   1   5
0041    RET0     0   1

-- BYTECODE -- filemanagersetdefaults.lua:147-155
0001    UGET     0   0      ; self
0002    TGETS    0   0   0  ; "defaults_value"
0003    UGET     1   1      ; i
0004    KPRI     2   1
0005    TSETV    2   0   1
0006    GGET     0   1      ; "_G"
0007    UGET     1   2      ; setting_name
0008    KPRI     2   1
0009    TSETV    2   0   1
0010    UGET     0   0      ; self
0011    KPRI     1   2
0012    TSETS    1   0   2  ; "settings_changed"
0013    UGET     0   0      ; self
0014    TGETS    0   0   3  ; "changed"
0015    UGET     1   1      ; i
0016    KPRI     2   2
0017    TSETV    2   0   1
0018    UGET     0   0      ; self
0019    TGETS    0   0   4  ; "results"
0020    UGET     1   1      ; i
0021    TGETV    0   0   1
0022    UGET     1   0      ; self
0023    MOV      2   1
0024    TGETS    1   1   6  ; "build_setting"
0025    UGET     3   1      ; i
0026    CALL     1   2   3
0027    TSETS    1   0   5  ; "text"
0028    UGET     0   0      ; self
0029    TGETS    0   0   7  ; "defaults_menu"
0030    MOV      1   0
0031    TGETS    0   0   8  ; "switchItemTable"
0032    KSTR     2   9      ; "Defaults"
0033    UGET     3   0      ; self
0034    TGETS    3   3   4  ; "results"
0035    UGET     4   1      ; i
0036    CALL     0   1   5
0037    UGET     0   0      ; self
0038    MOV      1   0
0039    TGETS    0   0  10  ; "close"
0040    CALL     0   1   2
0041    RET0     0   1

-- BYTECODE -- filemanagersetdefaults.lua:124-164
0001    UGET     0   0      ; self
0002    UGET     1   1      ; InputDialog
0003    MOV      2   1
0004    TGETS    1   1   1  ; "new"
0005    TDUP     3   2
0006    UGET     4   2      ; setting_name
0007    TSETS    4   3   3  ; "title"
0008    GGET     4   4      ; "tostring"
0009    UGET     5   0      ; self
0010    TGETS    5   5   5  ; "defaults_value"
0011    UGET     6   3      ; i
0012    TGETV    5   5   6
0013    CALL     4   2   2
0014    TSETS    4   3   6  ; "input"
0015    TNEW     4   3
0016    TNEW     5   4
0017    UGET     6   4      ; cancel_button
0018    TSETB    6   5   1
0019    TDUP     6   7
0020    FNEW     7   8      ; filemanagersetdefaults.lua:134
0021    TSETS    7   6   9  ; "callback"
0022    TSETB    6   5   2
0023    TDUP     6  10
0024    FNEW     7  11      ; filemanagersetdefaults.lua:147
0025    TSETS    7   6   9  ; "callback"
0026    TSETB    6   5   3
0027    TSETB    5   4   1
0028    TSETS    4   3  12  ; "buttons"
0029    UGET     4   5      ; setting_type
0030    TSETS    4   3  13  ; "input_type"
0031    UGET     4   6      ; Screen
0032    MOV      5   4
0033    TGETS    4   4  14  ; "getWidth"
0034    CALL     4   2   2
0035    MULVN    4   4   0  ; 0.95
0036    TSETS    4   3  15  ; "width"
0037    CALL     1   2   3
0038    TSETS    1   0   0  ; "set_dialog"
0039    UGET     0   7      ; UIManager
0040    MOV      1   0
0041    TGETS    0   0  16  ; "show"
0042    UGET     2   0      ; self
0043    TGETS    2   2   0  ; "set_dialog"
0044    CALL     0   1   3
0045    UGET     0   0      ; self
0046    TGETS    0   0   0  ; "set_dialog"
0047    MOV      1   0
0048    TGETS    0   0  17  ; "onShowKeyboard"
0049    CALL     0   1   2
0050    RET0     0   1

-- BYTECODE -- filemanagersetdefaults.lua:191-207
0001    TNEW     0   0
0002    GGET     1   0      ; "ipairs"
0003    UGET     2   0      ; MultiInputDialog
0004    MOV      3   2
0005    TGETS    2   2   1  ; "getFields"
0006    CALL     2   0   2
0007    CALLM    1   4   0
0008    JMP      4 => 0030
0009 => MOV      7   5
0010    TGETS    6   5   2  ; "match"
0011    KSTR     8   3      ; "^[^= ]+"
0012    CALL     6   2   3
0013    MOV      8   5
0014    TGETS    7   5   2  ; "match"
0015    KSTR     9   4      ; "[^= ]+$"
0016    CALL     7   2   3
0017    GGET     8   5      ; "tonumber"
0018    MOV      9   6
0019    CALL     8   2   2
0020    IST          8
0021    JMP      9 => 0023
0022    MOV      8   6
0023 => GGET     9   5      ; "tonumber"
0024    MOV     10   7
0025    CALL     9   2   2
0026    IST          9
0027    JMP     10 => 0029
0028    MOV      9   7
0029 => TSETV    9   0   8
0030 => ITERC    4   3   3
0031    ITERL    4 => 0009
0032    GGET     1   6      ; "_G"
0033    UGET     2   1      ; setting_name
0034    TSETV    0   1   2
0035    UGET     1   2      ; self
0036    TGETS    1   1   7  ; "defaults_value"
0037    UGET     2   3      ; i
0038    GGET     3   6      ; "_G"
0039    UGET     4   1      ; setting_name
0040    TGETV    3   3   4
0041    TSETV    3   1   2
0042    UGET     1   2      ; self
0043    KPRI     2   2
0044    TSETS    2   1   8  ; "settings_changed"
0045    UGET     1   2      ; self
0046    TGETS    1   1   9  ; "changed"
0047    UGET     2   3      ; i
0048    KPRI     3   2
0049    TSETV    3   1   2
0050    UGET     1   2      ; self
0051    TGETS    1   1  10  ; "results"
0052    UGET     2   3      ; i
0053    TGETV    1   1   2
0054    UGET     2   2      ; self
0055    MOV      3   2
0056    TGETS    2   2  12  ; "build_setting"
0057    UGET     4   3      ; i
0058    CALL     2   2   3
0059    TSETS    2   1  11  ; "text"
0060    UGET     1   2      ; self
0061    MOV      2   1
0062    TGETS    1   1  13  ; "close"
0063    CALL     1   1   2
0064    UGET     1   2      ; self
0065    TGETS    1   1  14  ; "defaults_menu"
0066    MOV      2   1
0067    TGETS    1   1  15  ; "switchItemTable"
0068    KSTR     3  16      ; "Defaults"
0069    UGET     4   2      ; self
0070    TGETS    4   4  10  ; "results"
0071    UGET     5   3      ; i
0072    CALL     1   1   5
0073    RET0     0   1

-- BYTECODE -- filemanagersetdefaults.lua:171-216
0001    TNEW     0   0
0002    UGET     1   0      ; util
0003    TGETS    1   1   0  ; "orderedPairs"
0004    GGET     2   1      ; "_G"
0005    UGET     3   1      ; setting_name
0006    TGETV    2   2   3
0007    CALL     1   4   2
0008    JMP      4 => 0035
0009 => GGET     6   2      ; "table"
0010    TGETS    6   6   3  ; "insert"
0011    MOV      7   0
0012    TDUP     8   6
0013    GGET     9   4      ; "tostring"
0014    MOV     10   4
0015    CALL     9   2   2
0016    KSTR    10   5      ; " = "
0017    GGET    11   4      ; "tostring"
0018    MOV     12   5
0019    CALL    11   2   2
0020    CAT      9   9  11
0021    TSETS    9   8   7  ; "text"
0022    UGET     9   2      ; Screen
0023    MOV     10   9
0024    TGETS    9   9   8  ; "scaleBySize"
0025    KSHORT  11   2
0026    CALL     9   2   3
0027    TSETS    9   8   9  ; "padding"
0028    UGET     9   2      ; Screen
0029    MOV     10   9
0030    TGETS    9   9   8  ; "scaleBySize"
0031    KSHORT  11   2
0032    CALL     9   2   3
0033    TSETS    9   8  10  ; "margin"
0034    CALL     6   1   3
0035 => ITERC    4   3   3
0036    ITERL    4 => 0009
0037    UGET     1   3      ; self
0038    UGET     2   4      ; MultiInputDialog
0039    MOV      3   2
0040    TGETS    2   2  12  ; "new"
0041    TDUP     4  13
0042    UGET     5   1      ; setting_name
0043    TSETS    5   4  14  ; "title"
0044    TSETS    0   4  15  ; "fields"
0045    TNEW     5   3
0046    TNEW     6   3
0047    UGET     7   5      ; cancel_button
0048    TSETB    7   6   1
0049    TDUP     7  17
0050    UGET     8   6      ; _
0051    KSTR     9  16      ; "OK"
0052    CALL     8   2   2
0053    TSETS    8   7   7  ; "text"
0054    FNEW     8  18      ; filemanagersetdefaults.lua:191
0055    TSETS    8   7  19  ; "callback"
0056    TSETB    7   6   2
0057    TSETB    6   5   1
0058    TSETS    5   4  20  ; "buttons"
0059    UGET     5   2      ; Screen
0060    MOV      6   5
0061    TGETS    5   5  21  ; "getWidth"
0062    CALL     5   2   2
0063    MULVN    5   5   0  ; 0.95
0064    TSETS    5   4  22  ; "width"
0065    UGET     5   2      ; Screen
0066    MOV      6   5
0067    TGETS    5   5  23  ; "getHeight"
0068    CALL     5   2   2
0069    MULVN    5   5   1  ; 0.2
0070    TSETS    5   4  24  ; "height"
0071    CALL     2   2   3
0072    TSETS    2   1  11  ; "set_dialog"
0073    UGET     1   8      ; UIManager
0074    MOV      2   1
0075    TGETS    1   1  25  ; "show"
0076    UGET     3   3      ; self
0077    TGETS    3   3  11  ; "set_dialog"
0078    CALL     1   1   3
0079    UGET     1   3      ; self
0080    TGETS    1   1  11  ; "set_dialog"
0081    MOV      2   1
0082    TGETS    1   1  26  ; "onShowKeyboard"
0083    CALL     1   1   2
0084    RET0     0   1

-- BYTECODE -- filemanagersetdefaults.lua:234-245
0001    UGET     0   0      ; self
0002    TGETS    0   0   0  ; "set_dialog"
0003    MOV      1   0
0004    TGETS    0   0   1  ; "getInputValue"
0005    CALL     0   2   2
0006    GGET     1   2      ; "_G"
0007    UGET     2   1      ; setting_name
0008    TGETV    1   1   2
0009    ISEQV    1   0
0010    JMP      1 => 0036
0011    GGET     1   2      ; "_G"
0012    UGET     2   1      ; setting_name
0013    TSETV    0   1   2
0014    UGET     1   0      ; self
0015    TGETS    1   1   3  ; "defaults_value"
0016    UGET     2   2      ; i
0017    TSETV    0   1   2
0018    UGET     1   0      ; self
0019    KPRI     2   2
0020    TSETS    2   1   4  ; "settings_changed"
0021    UGET     1   0      ; self
0022    TGETS    1   1   5  ; "changed"
0023    UGET     2   2      ; i
0024    KPRI     3   2
0025    TSETV    3   1   2
0026    UGET     1   0      ; self
0027    TGETS    1   1   6  ; "results"
0028    UGET     2   2      ; i
0029    TGETV    1   1   2
0030    UGET     2   0      ; self
0031    MOV      3   2
0032    TGETS    2   2   8  ; "build_setting"
0033    UGET     4   2      ; i
0034    CALL     2   2   3
0035    TSETS    2   1   7  ; "text"
0036 => UGET     1   0      ; self
0037    MOV      2   1
0038    TGETS    1   1   9  ; "close"
0039    CALL     1   1   2
0040    UGET     1   0      ; self
0041    TGETS    1   1  10  ; "defaults_menu"
0042    MOV      2   1
0043    TGETS    1   1  11  ; "switchItemTable"
0044    KSTR     3  12      ; "Defaults"
0045    UGET     4   0      ; self
0046    TGETS    4   4   6  ; "results"
0047    UGET     5   2      ; i
0048    CALL     1   1   5
0049    RET0     0   1

-- BYTECODE -- filemanagersetdefaults.lua:223-254
0001    UGET     0   0      ; self
0002    UGET     1   1      ; InputDialog
0003    MOV      2   1
0004    TGETS    1   1   1  ; "new"
0005    TDUP     3   2
0006    UGET     4   2      ; setting_name
0007    TSETS    4   3   3  ; "title"
0008    GGET     4   4      ; "tostring"
0009    UGET     5   0      ; self
0010    TGETS    5   5   5  ; "defaults_value"
0011    UGET     6   3      ; i
0012    TGETV    5   5   6
0013    CALL     4   2   2
0014    TSETS    4   3   6  ; "input"
0015    TNEW     4   3
0016    TNEW     5   3
0017    UGET     6   4      ; cancel_button
0018    TSETB    6   5   1
0019    TDUP     6   8
0020    UGET     7   5      ; _
0021    KSTR     8   7      ; "OK"
0022    CALL     7   2   2
0023    TSETS    7   6   9  ; "text"
0024    FNEW     7  10      ; filemanagersetdefaults.lua:234
0025    TSETS    7   6  11  ; "callback"
0026    TSETB    6   5   2
0027    TSETB    5   4   1
0028    TSETS    4   3  12  ; "buttons"
0029    UGET     4   6      ; setting_type
0030    TSETS    4   3  13  ; "input_type"
0031    UGET     4   7      ; Screen
0032    MOV      5   4
0033    TGETS    4   4  14  ; "getWidth"
0034    CALL     4   2   2
0035    MULVN    4   4   0  ; 0.95
0036    TSETS    4   3  15  ; "width"
0037    CALL     1   2   3
0038    TSETS    1   0   0  ; "set_dialog"
0039    UGET     0   8      ; UIManager
0040    MOV      1   0
0041    TGETS    0   0  16  ; "show"
0042    UGET     2   0      ; self
0043    TGETS    2   2   0  ; "set_dialog"
0044    CALL     0   1   3
0045    UGET     0   0      ; self
0046    TGETS    0   0   0  ; "set_dialog"
0047    MOV      1   0
0048    TGETS    0   0  17  ; "onShowKeyboard"
0049    CALL     0   1   2
0050    RET0     0   1

-- BYTECODE -- filemanagersetdefaults.lua:57-264
0001    TNEW     1   0
0002    TSETS    1   0   0  ; "results"
0003    TNEW     1   0
0004    GGET     2   1      ; "loadfile"
0005    UGET     3   0      ; defaults_path
0006    CALL     2   2   2
0007    GGET     3   2      ; "setfenv"
0008    MOV      4   2
0009    MOV      5   1
0010    CALL     3   1   3
0011    MOV      3   2
0012    CALL     3   1   1
0013    GGET     3   3      ; "io"
0014    TGETS    3   3   4  ; "open"
0015    UGET     4   1      ; persistent_defaults_path
0016    KSTR     5   5      ; "r"
0017    CALL     3   2   3
0018    ISEQP    3   0
0019    JMP      4 => 0033
0020    MOV      5   3
0021    TGETS    4   3   6  ; "close"
0022    CALL     4   1   2
0023    GGET     4   1      ; "loadfile"
0024    UGET     5   1      ; persistent_defaults_path
0025    CALL     4   2   2
0026    MOV      2   4
0027    GGET     4   2      ; "setfenv"
0028    MOV      5   2
0029    MOV      6   1
0030    CALL     4   1   3
0031    MOV      4   2
0032    CALL     4   1   1
0033 => KSHORT   4   1
0034    UGET     5   2      ; util
0035    TGETS    5   5   7  ; "orderedPairs"
0036    MOV      6   1
0037    CALL     5   4   2
0038    JMP      8 => 0044
0039 => TGETS   10   0   8  ; "defaults_name"
0040    TSETV    8  10   4
0041    TGETS   10   0   9  ; "defaults_value"
0042    TSETV    9  10   4
0043    ADDVN    4   4   0  ; 1
0044 => ITERC    8   3   3
0045    ITERL    8 => 0039
0046    UGET     5   3      ; CenterContainer
0047    MOV      6   5
0048    TGETS    5   5  10  ; "new"
0049    TDUP     7  12
0050    UGET     8   4      ; Screen
0051    MOV      9   8
0052    TGETS    8   8  11  ; "getSize"
0053    CALL     8   2   2
0054    TSETS    8   7  13  ; "dimen"
0055    CALL     5   2   3
0056    FNEW     6  15      ; filemanagersetdefaults.lua:87
0057    TSETS    6   5  14  ; "onShow"
0058    UGET     6   6      ; Menu
0059    MOV      7   6
0060    TGETS    6   6  10  ; "new"
0061    TDUP     8  18
0062    UGET     9   4      ; Screen
0063    MOV     10   9
0064    TGETS    9   9  17  ; "getWidth"
0065    CALL     9   2   2
0066    SUBVN    9   9   1  ; 15
0067    TSETS    9   8  19  ; "width"
0068    UGET     9   4      ; Screen
0069    MOV     10   9
0070    TGETS    9   9  20  ; "getHeight"
0071    CALL     9   2   2
0072    SUBVN    9   9   1  ; 15
0073    TSETS    9   8  21  ; "height"
0074    UGET     9   7      ; Font
0075    MOV     10   9
0076    TGETS    9   9  22  ; "getFace"
0077    KSTR    11  23      ; "smallinfofont"
0078    CALL     9   2   3
0079    TSETS    9   8  24  ; "cface"
0080    GGET     9  25      ; "G_reader_settings"
0081    MOV     10   9
0082    TGETS    9   9  26  ; "readSetting"
0083    KSTR    11  27      ; "items_per_page"
0084    CALL     9   2   3
0085    IST          9
0086    JMP     10 => 0088
0087    KSHORT   9  14
0088 => TSETS    9   8  28  ; "perpage"
0089    TSETS    5   8  29  ; "show_parent"
0090    TSETS    0   8  30  ; "_manager"
0091    CALL     6   2   3
0092    TSETS    6   0  16  ; "defaults_menu"
0093    TGETS    6   0  16  ; "defaults_menu"
0094    FNEW     7  32      ; filemanagersetdefaults.lua:100
0095    TSETS    7   6  31  ; "onMenuSelect"
0096    GGET     6  33      ; "table"
0097    TGETS    6   6  34  ; "insert"
0098    MOV      7   5
0099    TGETS    8   0  16  ; "defaults_menu"
0100    CALL     6   1   3
0101    TGETS    6   0  16  ; "defaults_menu"
0102    FNEW     7  36      ; filemanagersetdefaults.lua:105
0103    TSETS    7   6  35  ; "close_callback"
0104    TDUP     6  38
0105    UGET     7   9      ; _
0106    KSTR     8  37      ; "Cancel"
0107    CALL     7   2   2
0108    TSETS    7   6  39  ; "text"
0109    FNEW     7  40      ; filemanagersetdefaults.lua:114
0110    TSETS    7   6  41  ; "callback"
0111    KSHORT   7   1
0112    TGETS    8   0   8  ; "defaults_name"
0113    LEN      8   8
0114    KSHORT   9   1
0115    FORI     7 => 0170
0116 => TGETS   11   0  42  ; "changed"
0117    KPRI    12   1
0118    TSETV   12  11  10
0119    TGETS   11   0   8  ; "defaults_name"
0120    TGETV   11  11  10
0121    GGET    12  43      ; "type"
0122    GGET    13  44      ; "_G"
0123    TGETV   13  13  11
0124    CALL    12   2   2
0125    ISNES   12  45      ; "boolean"
0126    JMP     13 => 0140
0127    FNEW    13  46      ; filemanagersetdefaults.lua:124
0128    GGET    14  33      ; "table"
0129    TGETS   14  14  34  ; "insert"
0130    TGETS   15   0   0  ; "results"
0131    TDUP    16  48
0132    MOV     18   0
0133    TGETS   17   0  47  ; "build_setting"
0134    MOV     19  10
0135    CALL    17   2   3
0136    TSETS   17  16  39  ; "text"
0137    TSETS   13  16  41  ; "callback"
0138    CALL    14   1   3
0139    JMP     13 => 0167
0140 => ISNES   12  33      ; "table"
0141    JMP     13 => 0155
0142    FNEW    13  49      ; filemanagersetdefaults.lua:171
0143    GGET    14  33      ; "table"
0144    TGETS   14  14  34  ; "insert"
0145    TGETS   15   0   0  ; "results"
0146    TDUP    16  50
0147    MOV     18   0
0148    TGETS   17   0  47  ; "build_setting"
0149    MOV     19  10
0150    CALL    17   2   3
0151    TSETS   17  16  39  ; "text"
0152    TSETS   13  16  41  ; "callback"
0153    CALL    14   1   3
0154    JMP     13 => 0167
0155 => FNEW    13  51      ; filemanagersetdefaults.lua:223
0156    GGET    14  33      ; "table"
0157    TGETS   14  14  34  ; "insert"
0158    TGETS   15   0   0  ; "results"
0159    TDUP    16  52
0160    MOV     18   0
0161    TGETS   17   0  47  ; "build_setting"
0162    MOV     19  10
0163    CALL    17   2   3
0164    TSETS   17  16  39  ; "text"
0165    TSETS   13  16  41  ; "callback"
0166    CALL    14   1   3
0167 => UCLO    11 => 0168
0168 => UCLO    10 => 0169
0169 => FORL     7 => 0116
0170 => TGETS    7   0  16  ; "defaults_menu"
0171    MOV      8   7
0172    TGETS    7   7  53  ; "switchItemTable"
0173    KSTR     9  54      ; "Defaults"
0174    TGETS   10   0   0  ; "results"
0175    CALL     7   1   4
0176    UGET     7   5      ; UIManager
0177    MOV      8   7
0178    TGETS    7   7  55  ; "show"
0179    MOV      9   5
0180    CALL     7   1   3
0181    UCLO     0 => 0182
0182 => RET0     0   1

-- BYTECODE -- filemanagersetdefaults.lua:266-268
0001    UGET     1   0      ; UIManager
0002    MOV      2   1
0003    TGETS    1   1   0  ; "close"
0004    TGETS    3   0   1  ; "set_dialog"
0005    CALL     1   1   3
0006    RET0     0   1

-- BYTECODE -- filemanagersetdefaults.lua:273-275
0001    UGET     0   0      ; self
0002    MOV      1   0
0003    TGETS    0   0   0  ; "saveSettings"
0004    CALL     0   1   2
0005    RET0     0   1

-- BYTECODE -- filemanagersetdefaults.lua:270-277
0001    UGET     1   0      ; UIManager
0002    MOV      2   1
0003    TGETS    1   1   0  ; "show"
0004    UGET     3   1      ; ConfirmBox
0005    MOV      4   3
0006    TGETS    3   3   1  ; "new"
0007    TDUP     5   3
0008    UGET     6   2      ; _
0009    KSTR     7   2      ; "Are you sure you want to save the settin"~
0010    CALL     6   2   2
0011    TSETS    6   5   4  ; "text"
0012    FNEW     6   5      ; filemanagersetdefaults.lua:273
0013    TSETS    6   5   6  ; "ok_callback"
0014    CALL     3   0   3
0015    CALLM    1   1   1
0016    UCLO     0 => 0017
0017 => RET0     0   1

-- BYTECODE -- filemanagersetdefaults.lua:279-291
0001    TGETS    2   0   0  ; "defaults_name"
0002    TGETV    2   2   1
0003    MOV      3   2
0004    KSTR     4   1      ; " = "
0005    CAT      3   3   4
0006    GGET     4   2      ; "type"
0007    GGET     5   3      ; "_G"
0008    TGETV    5   5   2
0009    CALL     4   2   2
0010    ISNES    4   4      ; "boolean"
0011    JMP      4 => 0020
0012    MOV      4   3
0013    GGET     5   5      ; "tostring"
0014    TGETS    6   0   6  ; "defaults_value"
0015    TGETV    6   6   1
0016    CALL     5   2   2
0017    CAT      4   4   5
0018    RET1     4   2
0019    JMP      4 => 0056
0020 => GGET     4   2      ; "type"
0021    GGET     5   3      ; "_G"
0022    TGETV    5   5   2
0023    CALL     4   2   2
0024    ISNES    4   7      ; "table"
0025    JMP      4 => 0031
0026    MOV      4   3
0027    KSTR     5   8      ; "{...}"
0028    CAT      4   4   5
0029    RET1     4   2
0030    JMP      4 => 0056
0031 => GGET     4   9      ; "tonumber"
0032    TGETS    5   0   6  ; "defaults_value"
0033    TGETV    5   5   1
0034    CALL     4   2   2
0035    ISF          4
0036    JMP      5 => 0047
0037    MOV      4   3
0038    GGET     5   5      ; "tostring"
0039    GGET     6   9      ; "tonumber"
0040    TGETS    7   0   6  ; "defaults_value"
0041    TGETV    7   7   1
0042    CALL     6   0   2
0043    CALLM    5   2   0
0044    CAT      4   4   5
0045    RET1     4   2
0046    JMP      4 => 0056
0047 => MOV      4   3
0048    KSTR     5  10      ; """
0049    GGET     6   5      ; "tostring"
0050    TGETS    7   0   6  ; "defaults_value"
0051    TGETV    7   7   1
0052    CALL     6   2   2
0053    KSTR     7  10      ; """
0054    CAT      4   4   7
0055    RET1     4   2
0056 => RET0     0   1

-- BYTECODE -- filemanagersetdefaults.lua:293-356
0001    TNEW     1   0
0002    TSETS    1   0   0  ; "results"
0003    TNEW     1   0
0004    GGET     2   1      ; "io"
0005    TGETS    2   2   2  ; "open"
0006    UGET     3   0      ; persistent_defaults_path
0007    KSTR     4   3      ; "r"
0008    CALL     2   2   3
0009    ISEQP    2   0
0010    JMP      3 => 0023
0011    MOV      4   2
0012    TGETS    3   2   4  ; "close"
0013    CALL     3   1   2
0014    GGET     3   5      ; "loadfile"
0015    UGET     4   0      ; persistent_defaults_path
0016    CALL     3   2   2
0017    GGET     4   6      ; "setfenv"
0018    MOV      5   3
0019    MOV      6   1
0020    CALL     4   1   3
0021    MOV      4   3
0022    CALL     4   1   1
0023 => TNEW     3   0
0024    KSHORT   4   1
0025    TGETS    5   0   7  ; "defaults_name"
0026    LEN      5   5
0027    KSHORT   6   1
0028    FORI     4 => 0036
0029 => TGETS    8   0   8  ; "changed"
0030    TGETV    8   8   7
0031    IST          8
0032    JMP      8 => 0035
0033    KPRI     8   2
0034    TSETV    8   3   7
0035 => FORL     4 => 0029
0036 => TNEW     4   0
0037    GGET     5   5      ; "loadfile"
0038    UGET     6   1      ; defaults_path
0039    CALL     5   2   2
0040    GGET     6   6      ; "setfenv"
0041    MOV      7   5
0042    MOV      8   4
0043    CALL     6   1   3
0044    MOV      6   5
0045    CALL     6   1   1
0046    GGET     6   9      ; "pairs"
0047    MOV      7   1
0048    CALL     6   4   2
0049    ISNEXT   9 => 0076
0050 => KSHORT  11   1
0051    TGETS   12   0   7  ; "defaults_name"
0052    LEN     12  12
0053    KSHORT  13   1
0054    FORI    11 => 0076
0055 => TGETV   15   3  14
0056    IST         15
0057    JMP     15 => 0075
0058    TGETS   15   0   7  ; "defaults_name"
0059    TGETV   15  15  14
0060    ISNEV    9  15
0061    JMP     15 => 0075
0062    TGETV   15   4   9
0063    TGETS   16   0  10  ; "defaults_value"
0064    TGETV   16  16  14
0065    ISNEV   15  16
0066    JMP     15 => 0070
0067    KPRI    15   0
0068    TSETV   15   1   9
0069    JMP     15 => 0073
0070 => TGETS   15   0  10  ; "defaults_value"
0071    TGETV   15  15  14
0072    TSETV   15   1   9
0073 => KPRI    15   2
0074    TSETV   15   3  14
0075 => FORL    11 => 0055
0076 => ITERN    9   3   3
0077    ITERL    9 => 0050
0078    KSHORT   6   1
0079    TGETS    7   0   7  ; "defaults_name"
0080    LEN      7   7
0081    KSHORT   8   1
0082    FORI     6 => 0092
0083 => TGETV   10   3   9
0084    IST         10
0085    JMP     10 => 0091
0086    TGETS   10   0   7  ; "defaults_name"
0087    TGETV   10  10   9
0088    TGETS   11   0  10  ; "defaults_value"
0089    TGETV   11  11   9
0090    TSETV   11   1  10
0091 => FORL     6 => 0083
0092 => GGET     6   1      ; "io"
0093    TGETS    6   6   2  ; "open"
0094    UGET     7   0      ; persistent_defaults_path
0095    KSTR     8  11      ; "w"
0096    CALL     6   2   3
0097    MOV      2   6
0098    ISF          2
0099    JMP      6 => 0156
0100    MOV      7   2
0101    TGETS    6   2  12  ; "write"
0102    KSTR     8  13      ; "-- For configuration changes that persis"~
0103    CALL     6   1   3
0104    GGET     6   9      ; "pairs"
0105    MOV      7   1
0106    CALL     6   4   2
0107    ISNEXT   9 => 0138
0108 => TNEW    11   0
0109    GGET    12  14      ; "table"
0110    TGETS   12  12  15  ; "insert"
0111    MOV     13  11
0112    MOV     14   9
0113    CALL    12   1   3
0114    GGET    12  14      ; "table"
0115    TGETS   12  12  15  ; "insert"
0116    MOV     13  11
0117    KSTR    14  16      ; " = "
0118    CALL    12   1   3
0119    GGET    12  14      ; "table"
0120    TGETS   12  12  15  ; "insert"
0121    MOV     13  11
0122    UGET    14   2      ; dump
0123    MOV     15  10
0124    CALL    14   0   2
0125    CALLM   12   1   1
0126    GGET    12  14      ; "table"
0127    TGETS   12  12  15  ; "insert"
0128    MOV     13  11
0129    KSTR    14  17      ; "\n"
0130    CALL    12   1   3
0131    MOV     13   2
0132    TGETS   12   2  12  ; "write"
0133    GGET    14  14      ; "table"
0134    TGETS   14  14  18  ; "concat"
0135    MOV     15  11
0136    CALL    14   0   2
0137    CALLM   12   1   1
0138 => ITERN    9   3   3
0139    ITERL    9 => 0108
0140    MOV      7   2
0141    TGETS    6   2   4  ; "close"
0142    CALL     6   1   2
0143    UGET     6   3      ; UIManager
0144    MOV      7   6
0145    TGETS    6   6  19  ; "show"
0146    UGET     8   4      ; InfoMessage
0147    MOV      9   8
0148    TGETS    8   8  20  ; "new"
0149    TDUP    10  22
0150    UGET    11   5      ; _
0151    KSTR    12  21      ; "Default settings saved."
0152    CALL    11   2   2
0153    TSETS   11  10  23  ; "text"
0154    CALL     8   0   3
0155    CALLM    6   1   1
0156 => KPRI     6   1
0157    TSETS    6   0  24  ; "settings_changed"
0158    RET0     0   1

-- BYTECODE -- filemanagersetdefaults.lua:367-375
0001    UGET     0   0      ; self
0002    KPRI     1   1
0003    TSETS    1   0   0  ; "settings_changed"
0004    UGET     0   0      ; self
0005    MOV      1   0
0006    TGETS    0   0   1  ; "saveSettings"
0007    CALL     0   1   2
0008    UGET     0   1      ; Device
0009    MOV      1   0
0010    TGETS    0   0   2  ; "canRestart"
0011    CALL     0   2   2
0012    ISF          0
0013    JMP      1 => 0019
0014    UGET     0   2      ; UIManager
0015    MOV      1   0
0016    TGETS    0   0   3  ; "restartKOReader"
0017    CALL     0   1   2
0018    JMP      0 => 0023
0019 => UGET     0   2      ; UIManager
0020    MOV      1   0
0021    TGETS    0   0   4  ; "quit"
0022    CALL     0   1   2
0023 => RET0     0   1

-- BYTECODE -- filemanagersetdefaults.lua:377-382
0001    UGET     0   0      ; logger
0002    TGETS    0   0   0  ; "info"
0003    KSTR     1   1      ; "discard defaults"
0004    CALL     0   1   2
0005    GGET     0   2      ; "pcall"
0006    GGET     1   3      ; "dofile"
0007    UGET     2   1      ; defaults_path
0008    CALL     0   1   3
0009    GGET     0   2      ; "pcall"
0010    GGET     1   3      ; "dofile"
0011    UGET     2   2      ; persistent_defaults_path
0012    CALL     0   1   3
0013    UGET     0   3      ; self
0014    KPRI     1   1
0015    TSETS    1   0   4  ; "settings_changed"
0016    RET0     0   1

-- BYTECODE -- filemanagersetdefaults.lua:358-385
0001    UGET     2   0      ; _
0002    KSTR     3   0      ; "Save and quit"
0003    CALL     2   2   2
0004    UGET     3   1      ; Device
0005    MOV      4   3
0006    TGETS    3   3   1  ; "canRestart"
0007    CALL     3   2   2
0008    ISF          3
0009    JMP      4 => 0014
0010    UGET     3   0      ; _
0011    KSTR     4   2      ; "Save and restart"
0012    CALL     3   2   2
0013    MOV      2   3
0014 => TGETS    3   0   3  ; "settings_changed"
0015    ISF          3
0016    JMP      4 => 0039
0017    UGET     3   2      ; UIManager
0018    MOV      4   3
0019    TGETS    3   3   4  ; "show"
0020    UGET     5   3      ; ConfirmBox
0021    MOV      6   5
0022    TGETS    5   5   5  ; "new"
0023    TDUP     7   7
0024    UGET     8   0      ; _
0025    KSTR     9   6      ; "KOReader needs to be restarted to apply "~
0026    CALL     8   2   2
0027    TSETS    8   7   8  ; "text"
0028    TSETS    2   7   9  ; "ok_text"
0029    FNEW     8  10      ; filemanagersetdefaults.lua:367
0030    TSETS    8   7  11  ; "ok_callback"
0031    UGET     8   0      ; _
0032    KSTR     9  12      ; "Discard changes"
0033    CALL     8   2   2
0034    TSETS    8   7  13  ; "cancel_text"
0035    FNEW     8  14      ; filemanagersetdefaults.lua:377
0036    TSETS    8   7  15  ; "cancel_callback"
0037    CALL     5   0   3
0038    CALLM    3   1   1
0039 => UCLO     0 => 0040
0040 => RET0     0   1

-- BYTECODE -- filemanagersetdefaults.lua:0-388
0001    GGET     0   0      ; "require"
0002    KSTR     1   1      ; "ui/widget/container/centercontainer"
0003    CALL     0   2   2
0004    GGET     1   0      ; "require"
0005    KSTR     2   2      ; "ui/widget/confirmbox"
0006    CALL     1   2   2
0007    GGET     2   0      ; "require"
0008    KSTR     3   3      ; "datastorage"
0009    CALL     2   2   2
0010    GGET     3   0      ; "require"
0011    KSTR     4   4      ; "device"
0012    CALL     3   2   2
0013    GGET     4   0      ; "require"
0014    KSTR     5   5      ; "ui/font"
0015    CALL     4   2   2
0016    GGET     5   0      ; "require"
0017    KSTR     6   6      ; "ui/widget/infomessage"
0018    CALL     5   2   2
0019    GGET     6   0      ; "require"
0020    KSTR     7   7      ; "ui/widget/container/inputcontainer"
0021    CALL     6   2   2
0022    GGET     7   0      ; "require"
0023    KSTR     8   8      ; "ui/widget/inputdialog"
0024    CALL     7   2   2
0025    GGET     8   0      ; "require"
0026    KSTR     9   9      ; "ui/widget/menu"
0027    CALL     8   2   2
0028    GGET     9   0      ; "require"
0029    KSTR    10  10      ; "ui/widget/multiinputdialog"
0030    CALL     9   2   2
0031    GGET    10   0      ; "require"
0032    KSTR    11  11      ; "ui/uimanager"
0033    CALL    10   2   2
0034    GGET    11   0      ; "require"
0035    KSTR    12  12      ; "dump"
0036    CALL    11   2   2
0037    GGET    12  13      ; "pcall"
0038    GGET    13   0      ; "require"
0039    KSTR    14  14      ; "android"
0040    CALL    12   3   3
0041    GGET    14   0      ; "require"
0042    KSTR    15  15      ; "logger"
0043    CALL    14   2   2
0044    GGET    15   0      ; "require"
0045    KSTR    16  16      ; "ffi/util"
0046    CALL    15   2   2
0047    GGET    16   0      ; "require"
0048    KSTR    17  17      ; "gettext"
0049    CALL    16   2   2
0050    GGET    17   0      ; "require"
0051    KSTR    18   4      ; "device"
0052    CALL    17   2   2
0053    TGETS   17  17  18  ; "screen"
0054    GGET    18  19      ; "os"
0055    TGETS   18  18  20  ; "getenv"
0056    KSTR    19  21      ; "APPIMAGE"
0057    CALL    18   2   2
0058    FNEW    19  22      ; filemanagersetdefaults.lua:21
0059    MOV     20  19
0060    CALL    20   2   1
0061    MOV     22   2
0062    TGETS   21   2  23  ; "getDataDir"
0063    CALL    21   2   2
0064    KSTR    22  24      ; "/defaults.persistent.lua"
0065    CAT     21  21  22
0066    MOV     23   6
0067    TGETS   22   6  25  ; "new"
0068    TDUP    24  26
0069    TNEW    25   0
0070    TSETS   25  24  27  ; "defaults_name"
0071    TNEW    25   0
0072    TSETS   25  24  28  ; "defaults_value"
0073    TNEW    25   0
0074    TSETS   25  24  29  ; "results"
0075    TNEW    25   0
0076    TSETS   25  24  30  ; "defaults_menu"
0077    TNEW    25   0
0078    TSETS   25  24  31  ; "changed"
0079    CALL    22   2   3
0080    FNEW    23  33      ; filemanagersetdefaults.lua:43
0081    TSETS   23  22  32  ; "ConfirmEdit"
0082    FNEW    23  35      ; filemanagersetdefaults.lua:57
0083    TSETS   23  22  34  ; "init"
0084    FNEW    23  37      ; filemanagersetdefaults.lua:266
0085    TSETS   23  22  36  ; "close"
0086    FNEW    23  39      ; filemanagersetdefaults.lua:270
0087    TSETS   23  22  38  ; "ConfirmSave"
0088    FNEW    23  41      ; filemanagersetdefaults.lua:279
0089    TSETS   23  22  40  ; "build_setting"
0090    FNEW    23  43      ; filemanagersetdefaults.lua:293
0091    TSETS   23  22  42  ; "saveSettings"
0092    FNEW    23  45      ; filemanagersetdefaults.lua:358
0093    TSETS   23  22  44  ; "saveBeforeExit"
0094    UCLO     0 => 0095
0095 => RET1    22   2

