
main <./frontend/apps/filemanager/filemanagerconverter.lua:0,0> (70 instructions, 280 bytes at 0x7ff610406900)
0+ params, 13 slots, 0 upvalues, 9 locals, 28 constants, 5 functions
	1	[5]	GETGLOBAL	0 -1	; require
	2	[5]	LOADK    	1 -2	; "ui/widget/buttondialogtitle"
	3	[5]	CALL     	0 2 2
	4	[6]	GETGLOBAL	1 -1	; require
	5	[6]	LOADK    	2 -3	; "ui/widget/confirmbox"
	6	[6]	CALL     	1 2 2
	7	[7]	GETGLOBAL	2 -1	; require
	8	[7]	LOADK    	3 -4	; "ui/uimanager"
	9	[7]	CALL     	2 2 2
	10	[8]	GETGLOBAL	3 -1	; require
	11	[8]	LOADK    	4 -5	; "libs/libkoreader-lfs"
	12	[8]	CALL     	3 2 2
	13	[9]	GETGLOBAL	4 -1	; require
	14	[9]	LOADK    	5 -6	; "logger"
	15	[9]	CALL     	4 2 2
	16	[10]	GETGLOBAL	5 -1	; require
	17	[10]	LOADK    	6 -7	; "util"
	18	[10]	CALL     	5 2 2
	19	[11]	GETGLOBAL	6 -1	; require
	20	[11]	LOADK    	7 -8	; "gettext"
	21	[11]	CALL     	6 2 2
	22	[12]	GETGLOBAL	7 -1	; require
	23	[12]	LOADK    	8 -9	; "ffi/util"
	24	[12]	CALL     	7 2 2
	25	[12]	GETTABLE 	7 7 -10	; "template"
	26	[14]	NEWTABLE 	8 0 3
	27	[15]	NEWTABLE 	9 0 1
	28	[16]	NEWTABLE 	10 0 2
	29	[18]	MOVE     	11 6
	30	[18]	LOADK    	12 -14	; "Markdown"
	31	[18]	CALL     	11 2 2
	32	[18]	SETTABLE 	10 -13 11	; "name" -
	33	[19]	SETTABLE 	10 -15 -16	; "from" "markdown"
	34	[20]	SETTABLE 	9 -12 10	; "md" -
	35	[21]	SETTABLE 	8 -11 9	; "formats_from" -
	36	[22]	NEWTABLE 	9 0 3
	37	[23]	NEWTABLE 	10 0 1
	38	[24]	SETTABLE 	10 -19 -18	; "to" "epub"
	39	[25]	SETTABLE 	9 -18 10	; "epub" -
	40	[26]	NEWTABLE 	10 0 1
	41	[27]	SETTABLE 	10 -19 -20	; "to" "html"
	42	[28]	SETTABLE 	9 -20 10	; "html" -
	43	[29]	NEWTABLE 	10 0 1
	44	[30]	SETTABLE 	10 -19 -21	; "to" "pdf"
	45	[31]	SETTABLE 	9 -21 10	; "pdf" -
	46	[32]	SETTABLE 	8 -17 9	; "formats_to" -
	47	[34]	SETTABLE 	8 -22 -23	; "docverter_url" "http://c.docverter.com/convert"
	48	[53]	CLOSURE  	9 0	; 0x7ff6104070a0
	49	[53]	MOVE     	0 4
	50	[41]	SETTABLE 	8 -24 9	; "mdToHtml" -
	51	[61]	CLOSURE  	9 1	; 0x7ff6104076f0
	52	[55]	SETTABLE 	8 -25 9	; "_mdFileToHtml" -
	53	[67]	CLOSURE  	9 2	; 0x7ff610407cb0
	54	[63]	SETTABLE 	8 -26 9	; "writeStringToFile" -
	55	[71]	CLOSURE  	9 3	; 0x7ff610407f50
	56	[71]	MOVE     	0 8
	57	[71]	MOVE     	0 5
	58	[69]	SETTABLE 	8 -27 9	; "isSupported" -
	59	[107]	CLOSURE  	9 4	; 0x7ff6104083f0
	60	[107]	MOVE     	0 5
	61	[107]	MOVE     	0 0
	62	[107]	MOVE     	0 7
	63	[107]	MOVE     	0 6
	64	[107]	MOVE     	0 8
	65	[107]	MOVE     	0 3
	66	[107]	MOVE     	0 2
	67	[107]	MOVE     	0 1
	68	[73]	SETTABLE 	8 -28 9	; "showConvertButtons" -
	69	[109]	RETURN   	8 2
	70	[109]	RETURN   	0 1

function <./frontend/apps/filemanager/filemanagerconverter.lua:41,53> (25 instructions, 100 bytes at 0x7ff6104070a0)
3 params, 10 slots, 1 upvalue, 7 locals, 12 constants, 0 functions
	1	[42]	GETGLOBAL	3 -1	; require
	2	[42]	LOADK    	4 -2	; "apps/filemanager/lib/md"
	3	[42]	CALL     	3 2 2
	4	[43]	NEWTABLE 	4 0 3
	5	[44]	SETTABLE 	4 -3 -4	; "prependHead" "<!DOCTYPE html>\n<html>\n<head>\n"
	6	[45]	GETGLOBAL	5 -6	; string
	7	[45]	GETTABLE 	5 5 -7	; "format"
	8	[45]	LOADK    	6 -8	; "<title>%s</title>\n</head>\n<body>\n"
	9	[45]	MOVE     	7 2
	10	[45]	CALL     	5 3 2
	11	[45]	SETTABLE 	4 -5 5	; "insertHead" -
	12	[46]	SETTABLE 	4 -9 -10	; "appendTail" "\n</body>\n</html>"
	13	[48]	MOVE     	5 3
	14	[48]	MOVE     	6 1
	15	[48]	MOVE     	7 4
	16	[48]	CALL     	5 3 3
	17	[49]	TEST     	6 0 0
	18	[49]	JMP      	5	; to 24
	19	[50]	GETUPVAL 	7 0	; logger
	20	[50]	GETTABLE 	7 7 -11	; "warn"
	21	[50]	LOADK    	8 -12	; "FileManagerConverter: could not generate HTML"
	22	[50]	MOVE     	9 6
	23	[50]	CALL     	7 3 1
	24	[52]	RETURN   	5 2
	25	[53]	RETURN   	0 1

function <./frontend/apps/filemanager/filemanagerconverter.lua:55,61> (16 instructions, 64 bytes at 0x7ff6104076f0)
3 params, 9 slots, 0 upvalues, 6 locals, 7 constants, 0 functions
	1	[56]	GETGLOBAL	3 -1	; io
	2	[56]	GETTABLE 	3 3 -2	; "open"
	3	[56]	MOVE     	4 1
	4	[56]	LOADK    	5 -3	; "rb"
	5	[56]	CALL     	3 3 2
	6	[57]	SELF     	4 3 -4	; "read"
	7	[57]	LOADK    	6 -5	; "*all"
	8	[57]	CALL     	4 3 2
	9	[58]	SELF     	5 3 -6	; "close"
	10	[58]	CALL     	5 2 1
	11	[59]	SELF     	5 0 -7	; "mdToHtml"
	12	[59]	MOVE     	7 4
	13	[59]	MOVE     	8 2
	14	[59]	CALL     	5 4 2
	15	[60]	RETURN   	5 2
	16	[61]	RETURN   	0 1

function <./frontend/apps/filemanager/filemanagerconverter.lua:63,67> (11 instructions, 44 bytes at 0x7ff610407cb0)
3 params, 7 slots, 0 upvalues, 4 locals, 5 constants, 0 functions
	1	[64]	GETGLOBAL	3 -1	; io
	2	[64]	GETTABLE 	3 3 -2	; "open"
	3	[64]	MOVE     	4 2
	4	[64]	LOADK    	5 -3	; "w"
	5	[64]	CALL     	3 3 2
	6	[65]	SELF     	4 3 -4	; "write"
	7	[65]	MOVE     	6 1
	8	[65]	CALL     	4 3 1
	9	[66]	SELF     	4 3 -5	; "close"
	10	[66]	CALL     	4 2 1
	11	[67]	RETURN   	0 1

function <./frontend/apps/filemanager/filemanagerconverter.lua:69,71> (15 instructions, 60 bytes at 0x7ff610407f50)
2 params, 5 slots, 2 upvalues, 2 locals, 2 constants, 0 functions
	1	[70]	GETUPVAL 	2 0	; FileConverter
	2	[70]	GETTABLE 	2 2 -1	; "formats_from"
	3	[70]	GETUPVAL 	3 1	; util
	4	[70]	GETTABLE 	3 3 -2	; "getFileNameSuffix"
	5	[70]	MOVE     	4 1
	6	[70]	CALL     	3 2 2
	7	[70]	GETTABLE 	2 2 3
	8	[70]	TEST     	2 0 0
	9	[70]	JMP      	3	; to 13
	10	[70]	LOADBOOL 	2 1 0
	11	[70]	TEST     	2 0 1
	12	[70]	JMP      	1	; to 14
	13	[70]	LOADBOOL 	2 0 0
	14	[70]	RETURN   	2 2
	15	[71]	RETURN   	0 1

function <./frontend/apps/filemanager/filemanagerconverter.lua:73,107> (49 instructions, 196 bytes at 0x7ff6104083f0)
3 params, 15 slots, 8 upvalues, 7 locals, 13 constants, 1 function
	1	[74]	GETUPVAL 	3 0	; util
	2	[74]	GETTABLE 	3 3 -1	; "splitFilePathName"
	3	[74]	MOVE     	4 1
	4	[74]	CALL     	3 2 3
	5	[75]	GETUPVAL 	5 0	; util
	6	[75]	GETTABLE 	5 5 -2	; "getFileNameSuffix"
	7	[75]	MOVE     	6 1
	8	[75]	CALL     	5 2 2
	9	[76]	GETTABLE 	6 0 -3	; "formats_from"
	10	[76]	GETTABLE 	6 6 5
	11	[76]	GETTABLE 	6 6 -4	; "name"
	12	[77]	GETUPVAL 	7 1	; ButtonDialogTitle
	13	[77]	SELF     	7 7 -6	; "new"
	14	[77]	NEWTABLE 	9 0 2
	15	[78]	GETUPVAL 	10 2	; T
	16	[78]	GETUPVAL 	11 3	; _
	17	[78]	LOADK    	12 -8	; "Convert %1 to:"
	18	[78]	CALL     	11 2 2
	19	[78]	MOVE     	12 6
	20	[78]	CALL     	10 3 2
	21	[78]	SETTABLE 	9 -7 10	; "title" -
	22	[79]	NEWTABLE 	10 1 0
	23	[79]	NEWTABLE 	11 1 0
	24	[80]	NEWTABLE 	12 0 2
	25	[82]	GETUPVAL 	13 3	; _
	26	[82]	LOADK    	14 -11	; "HTML"
	27	[82]	CALL     	13 2 2
	28	[82]	SETTABLE 	12 -10 13	; "text" -
	29	[101]	CLOSURE  	13 0	; 0x7ff6104085c0
	30	[101]	GETUPVAL 	0 4	; FileConverter
	31	[101]	MOVE     	0 1
	32	[101]	MOVE     	0 4
	33	[101]	GETUPVAL 	0 5	; lfs
	34	[101]	GETUPVAL 	0 6	; UIManager
	35	[101]	GETUPVAL 	0 7	; ConfirmBox
	36	[101]	GETUPVAL 	0 3	; _
	37	[101]	MOVE     	0 0
	38	[101]	MOVE     	0 2
	39	[101]	SETTABLE 	12 -12 13	; "callback" -
	40	[103]	SETLIST  	11 1 1	; 1
	41	[104]	SETLIST  	10 1 1	; 1
	42	[104]	SETTABLE 	9 -9 10	; "buttons" -
	43	[77]	CALL     	7 3 2
	44	[105]	SETTABLE 	0 -5 7	; "convert_dialog" -
	45	[106]	GETUPVAL 	7 6	; UIManager
	46	[106]	SELF     	7 7 -13	; "show"
	47	[106]	GETTABLE 	9 0 -5	; "convert_dialog"
	48	[106]	CALL     	7 3 1
	49	[107]	RETURN   	0 1

function <./frontend/apps/filemanager/filemanagerconverter.lua:83,101> (55 instructions, 220 bytes at 0x7ff6104085c0)
0 params, 9 slots, 9 upvalues, 2 locals, 16 constants, 1 function
	1	[84]	GETUPVAL 	0 0	; FileConverter
	2	[84]	SELF     	0 0 -1	; "_mdFileToHtml"
	3	[84]	GETUPVAL 	2 1	; file
	4	[84]	GETUPVAL 	3 2	; filename_pure
	5	[84]	CALL     	0 4 2
	6	[85]	TEST     	0 0 1
	7	[85]	JMP      	1	; to 9
	8	[85]	RETURN   	0 1
	9	[86]	GETUPVAL 	1 1	; file
	10	[86]	LOADK    	2 -2	; ".html"
	11	[86]	CONCAT   	1 1 2
	12	[87]	GETUPVAL 	2 3	; lfs
	13	[87]	GETTABLE 	2 2 -3	; "attributes"
	14	[87]	MOVE     	3 1
	15	[87]	LOADK    	4 -4	; "mode"
	16	[87]	CALL     	2 3 2
	17	[87]	EQ       	0 2 -5	; - "file"
	18	[87]	JMP      	23	; to 42
	19	[88]	GETUPVAL 	2 4	; UIManager
	20	[88]	SELF     	2 2 -6	; "show"
	21	[88]	GETUPVAL 	4 5	; ConfirmBox
	22	[88]	SELF     	4 4 -7	; "new"
	23	[88]	NEWTABLE 	6 0 3
	24	[89]	GETUPVAL 	7 6	; _
	25	[89]	LOADK    	8 -9	; "Overwrite existing HTML file?"
	26	[89]	CALL     	7 2 2
	27	[89]	SETTABLE 	6 -8 7	; "text" -
	28	[90]	GETUPVAL 	7 6	; _
	29	[90]	LOADK    	8 -11	; "Overwrite"
	30	[90]	CALL     	7 2 2
	31	[90]	SETTABLE 	6 -10 7	; "ok_text" -
	32	[94]	CLOSURE  	7 0	; 0x7ff610408a60
	33	[94]	GETUPVAL 	0 0	; FileConverter
	34	[94]	MOVE     	0 0
	35	[94]	MOVE     	0 1
	36	[94]	GETUPVAL 	0 4	; UIManager
	37	[94]	GETUPVAL 	0 7	; self
	38	[94]	SETTABLE 	6 -12 7	; "ok_callback" -
	39	[88]	CALL     	4 3 0
	40	[88]	CALL     	2 0 1
	41	[95]	JMP      	13	; to 55
	42	[97]	GETUPVAL 	2 0	; FileConverter
	43	[97]	SELF     	2 2 -13	; "writeStringToFile"
	44	[97]	MOVE     	4 0
	45	[97]	MOVE     	5 1
	46	[97]	CALL     	2 4 1
	47	[98]	GETUPVAL 	2 8	; ui
	48	[98]	SELF     	2 2 -14	; "refreshPath"
	49	[98]	CALL     	2 2 1
	50	[99]	GETUPVAL 	2 4	; UIManager
	51	[99]	SELF     	2 2 -15	; "close"
	52	[99]	GETUPVAL 	4 7	; self
	53	[99]	GETTABLE 	4 4 -16	; "convert_dialog"
	54	[99]	CALL     	2 3 1
	55	[101]	RETURN   	0 1

function <./frontend/apps/filemanager/filemanagerconverter.lua:91,94> (11 instructions, 44 bytes at 0x7ff610408a60)
0 params, 4 slots, 5 upvalues, 0 locals, 3 constants, 0 functions
	1	[92]	GETUPVAL 	0 0	; FileConverter
	2	[92]	SELF     	0 0 -1	; "writeStringToFile"
	3	[92]	GETUPVAL 	2 1	; html
	4	[92]	GETUPVAL 	3 2	; filename_html
	5	[92]	CALL     	0 4 1
	6	[93]	GETUPVAL 	0 3	; UIManager
	7	[93]	SELF     	0 0 -2	; "close"
	8	[93]	GETUPVAL 	2 4	; self
	9	[93]	GETTABLE 	2 2 -3	; "convert_dialog"
	10	[93]	CALL     	0 3 1
	11	[94]	RETURN   	0 1
