
main <./frontend/apps/filemanager/filemanagermenu.lua:0,0> (122 instructions, 488 bytes at 0x7f971ac068f0)
0+ params, 24 slots, 0 upvalues, 19 locals, 38 constants, 13 functions
	1	[1]	GETGLOBAL	0 -1	; require
	2	[1]	LOADK    	1 -2	; "ui/bidi"
	3	[1]	CALL     	0 2 2
	4	[2]	GETGLOBAL	1 -1	; require
	5	[2]	LOADK    	2 -3	; "ui/widget/container/centercontainer"
	6	[2]	CALL     	1 2 2
	7	[3]	GETGLOBAL	2 -1	; require
	8	[3]	LOADK    	3 -4	; "apps/cloudstorage/cloudstorage"
	9	[3]	CALL     	2 2 2
	10	[4]	GETGLOBAL	3 -1	; require
	11	[4]	LOADK    	4 -5	; "ui/widget/confirmbox"
	12	[4]	CALL     	3 2 2
	13	[5]	GETGLOBAL	4 -1	; require
	14	[5]	LOADK    	5 -6	; "device"
	15	[5]	CALL     	4 2 2
	16	[6]	GETGLOBAL	5 -1	; require
	17	[6]	LOADK    	6 -7	; "ui/event"
	18	[6]	CALL     	5 2 2
	19	[7]	GETGLOBAL	6 -1	; require
	20	[7]	LOADK    	7 -8	; "ui/widget/container/inputcontainer"
	21	[7]	CALL     	6 2 2
	22	[8]	GETGLOBAL	7 -1	; require
	23	[8]	LOADK    	8 -9	; "pluginloader"
	24	[8]	CALL     	7 2 2
	25	[9]	GETGLOBAL	8 -1	; require
	26	[9]	LOADK    	9 -10	; "apps/filemanager/filemanagersearch"
	27	[9]	CALL     	8 2 2
	28	[10]	GETGLOBAL	9 -1	; require
	29	[10]	LOADK    	10 -11	; "apps/filemanager/filemanagersetdefaults"
	30	[10]	CALL     	9 2 2
	31	[11]	GETGLOBAL	10 -1	; require
	32	[11]	LOADK    	11 -12	; "ui/uimanager"
	33	[11]	CALL     	10 2 2
	34	[12]	GETTABLE 	11 4 -13	; "screen"
	35	[13]	GETGLOBAL	12 -1	; require
	36	[13]	LOADK    	13 -14	; "dbg"
	37	[13]	CALL     	12 2 2
	38	[14]	GETGLOBAL	13 -1	; require
	39	[14]	LOADK    	14 -15	; "libs/libkoreader-lfs"
	40	[14]	CALL     	13 2 2
	41	[15]	GETGLOBAL	14 -1	; require
	42	[15]	LOADK    	15 -16	; "logger"
	43	[15]	CALL     	14 2 2
	44	[16]	GETGLOBAL	15 -1	; require
	45	[16]	LOADK    	16 -17	; "util"
	46	[16]	CALL     	15 2 2
	47	[17]	GETGLOBAL	16 -1	; require
	48	[17]	LOADK    	17 -18	; "gettext"
	49	[17]	CALL     	16 2 2
	50	[18]	GETGLOBAL	17 -1	; require
	51	[18]	LOADK    	18 -19	; "ffi/util"
	52	[18]	CALL     	17 2 2
	53	[18]	GETTABLE 	17 17 -20	; "template"
	54	[20]	SELF     	18 6 -21	; "extend"
	55	[20]	NEWTABLE 	20 0 3
	56	[21]	SETTABLE 	20 -22 -23	; "tab_item_table" nil
	57	[22]	NEWTABLE 	21 0 0
	58	[22]	SETTABLE 	20 -24 21	; "menu_items" -
	59	[23]	SETTABLE 	20 -25 -23	; "registered_widgets" nil
	60	[20]	CALL     	18 3 2
	61	[60]	CLOSURE  	19 0	; 0x7f971ac07110
	62	[60]	MOVE     	0 4
	63	[26]	SETTABLE 	18 -26 19	; "init" -
	64	[89]	CLOSURE  	19 1	; 0x7f971ac07cf0
	65	[89]	MOVE     	0 4
	66	[62]	SETTABLE 	18 -27 19	; "initGesListener" -
	67	[110]	CLOSURE  	19 2	; 0x7f971ac071c0
	68	[110]	MOVE     	0 13
	69	[110]	MOVE     	0 10
	70	[110]	MOVE     	0 16
	71	[91]	SETTABLE 	18 -28 19	; "openLastDoc" -
	72	[567]	CLOSURE  	19 3	; 0x7f971ac09200
	73	[567]	MOVE     	0 14
	74	[567]	MOVE     	0 16
	75	[567]	MOVE     	0 11
	76	[567]	MOVE     	0 10
	77	[567]	MOVE     	0 4
	78	[567]	MOVE     	0 9
	79	[567]	MOVE     	0 7
	80	[567]	MOVE     	0 3
	81	[567]	MOVE     	0 13
	82	[567]	MOVE     	0 12
	83	[567]	MOVE     	0 2
	84	[567]	MOVE     	0 8
	85	[567]	MOVE     	0 5
	86	[567]	MOVE     	0 15
	87	[567]	MOVE     	0 17
	88	[567]	MOVE     	0 0
	89	[112]	SETTABLE 	18 -29 19	; "setUpdateItemTable" -
	90	[568]	SELF     	19 12 -30	; "guard"
	91	[568]	MOVE     	21 18
	92	[568]	LOADK    	22 -29	; "setUpdateItemTable"
	93	[575]	CLOSURE  	23 4	; 0x7f971ae07600
	94	[568]	CALL     	19 5 1
	95	[583]	CLOSURE  	19 5	; 0x7f971ae05590
	96	[583]	MOVE     	0 10
	97	[577]	SETTABLE 	18 -31 19	; "exitOrRestart" -
	98	[627]	CLOSURE  	19 6	; 0x7f971ae065b0
	99	[627]	MOVE     	0 1
	100	[627]	MOVE     	0 11
	101	[627]	MOVE     	0 4
	102	[627]	MOVE     	0 16
	103	[627]	MOVE     	0 10
	104	[585]	SETTABLE 	18 -32 19	; "onShowMenu" -
	105	[634]	CLOSURE  	19 7	; 0x7f971ae09ed0
	106	[634]	MOVE     	0 10
	107	[629]	SETTABLE 	18 -33 19	; "onCloseFileManagerMenu" -
	108	[653]	CLOSURE  	19 8	; 0x7f971ae0c5b0
	109	[653]	MOVE     	0 11
	110	[653]	MOVE     	0 0
	111	[636]	SETTABLE 	18 -34 19	; "_getTabIndexFromLocation" -
	112	[660]	CLOSURE  	19 9	; 0x7f971ae0c700
	113	[655]	SETTABLE 	18 -35 19	; "onTapShowMenu" -
	114	[667]	CLOSURE  	19 10	; 0x7f971ae0ce50
	115	[662]	SETTABLE 	18 -36 19	; "onSwipeShowMenu" -
	116	[674]	CLOSURE  	19 11	; 0x7f971ae0d370
	117	[674]	MOVE     	0 4
	118	[669]	SETTABLE 	18 -37 19	; "onSetDimensions" -
	119	[678]	CLOSURE  	19 12	; 0x7f971ae0d730
	120	[676]	SETTABLE 	18 -38 19	; "registerToMainMenu" -
	121	[680]	RETURN   	18 2
	122	[680]	RETURN   	0 1

function <./frontend/apps/filemanager/filemanagermenu.lua:26,60> (45 instructions, 180 bytes at 0x7f971ac07110)
1 param, 5 slots, 1 upvalue, 1 local, 26 constants, 0 functions
	1	[27]	NEWTABLE 	1 0 6
	2	[28]	NEWTABLE 	2 0 0
	3	[30]	SETTABLE 	1 -2 2	; "KOMenu:menu_buttons" -
	4	[32]	NEWTABLE 	2 0 1
	5	[33]	SETTABLE 	2 -4 -5	; "icon" "resources/icons/appbar.cabinet.files.png"
	6	[34]	SETTABLE 	1 -3 2	; "filemanager_settings" -
	7	[35]	NEWTABLE 	2 0 1
	8	[36]	SETTABLE 	2 -4 -7	; "icon" "resources/icons/appbar.settings.png"
	9	[37]	SETTABLE 	1 -6 2	; "setting" -
	10	[38]	NEWTABLE 	2 0 1
	11	[39]	SETTABLE 	2 -4 -9	; "icon" "resources/icons/appbar.tools.png"
	12	[40]	SETTABLE 	1 -8 2	; "tools" -
	13	[41]	NEWTABLE 	2 0 1
	14	[42]	SETTABLE 	2 -4 -11	; "icon" "resources/icons/appbar.magnify.browse.png"
	15	[43]	SETTABLE 	1 -10 2	; "search" -
	16	[44]	NEWTABLE 	2 0 1
	17	[45]	SETTABLE 	2 -4 -13	; "icon" "resources/icons/menu-icon.png"
	18	[46]	SETTABLE 	1 -12 2	; "main" -
	19	[47]	SETTABLE 	0 -1 1	; "menu_items" -
	20	[49]	NEWTABLE 	1 0 0
	21	[49]	SETTABLE 	0 -14 1	; "registered_widgets" -
	22	[51]	GETUPVAL 	1 0	; Device
	23	[51]	SELF     	1 1 -15	; "hasKeys"
	24	[51]	CALL     	1 2 2
	25	[51]	TEST     	1 0 0
	26	[51]	JMP      	9	; to 36
	27	[52]	NEWTABLE 	1 0 1
	28	[53]	NEWTABLE 	2 1 1
	29	[53]	NEWTABLE 	3 1 0
	30	[53]	LOADK    	4 -18	; "Menu"
	31	[53]	SETLIST  	3 1 1	; 1
	32	[53]	SETTABLE 	2 -19 -20	; "doc" "show menu"
	33	[53]	SETLIST  	2 1 1	; 1
	34	[53]	SETTABLE 	1 -17 2	; "ShowMenu" -
	35	[54]	SETTABLE 	0 -16 1	; "key_events" -
	36	[56]	GETGLOBAL	1 -22	; G_reader_settings
	37	[56]	SELF     	1 1 -23	; "readSetting"
	38	[56]	LOADK    	3 -24	; "activate_menu"
	39	[56]	CALL     	1 3 2
	40	[56]	SETTABLE 	0 -21 1	; "activation_menu" -
	41	[57]	GETTABLE 	1 0 -21	; "activation_menu"
	42	[57]	EQ       	0 1 -25	; - nil
	43	[57]	JMP      	1	; to 45
	44	[58]	SETTABLE 	0 -21 -26	; "activation_menu" "swipe_tap"
	45	[60]	RETURN   	0 1

function <./frontend/apps/filemanager/filemanagermenu.lua:62,89> (56 instructions, 224 bytes at 0x7f971ac07cf0)
1 param, 9 slots, 1 upvalue, 1 local, 22 constants, 2 functions
	1	[63]	GETUPVAL 	1 0	; Device
	2	[63]	SELF     	1 1 -1	; "isTouchDevice"
	3	[63]	CALL     	1 2 2
	4	[63]	TEST     	1 0 1
	5	[63]	JMP      	1	; to 7
	6	[63]	RETURN   	0 1
	7	[65]	SELF     	1 0 -2	; "registerTouchZones"
	8	[65]	NEWTABLE 	3 2 0
	9	[65]	NEWTABLE 	4 0 4
	10	[67]	SETTABLE 	4 -3 -4	; "id" "filemanager_tap"
	11	[68]	SETTABLE 	4 -5 -6	; "ges" "tap"
	12	[69]	NEWTABLE 	5 0 4
	13	[70]	GETGLOBAL	6 -9	; DTAP_ZONE_MENU
	14	[70]	GETTABLE 	6 6 -10	; "x"
	15	[70]	SETTABLE 	5 -8 6	; "ratio_x" -
	16	[70]	GETGLOBAL	6 -9	; DTAP_ZONE_MENU
	17	[70]	GETTABLE 	6 6 -12	; "y"
	18	[70]	SETTABLE 	5 -11 6	; "ratio_y" -
	19	[71]	GETGLOBAL	6 -9	; DTAP_ZONE_MENU
	20	[71]	GETTABLE 	6 6 -14	; "w"
	21	[71]	SETTABLE 	5 -13 6	; "ratio_w" -
	22	[71]	GETGLOBAL	6 -9	; DTAP_ZONE_MENU
	23	[71]	GETTABLE 	6 6 -16	; "h"
	24	[71]	SETTABLE 	5 -15 6	; "ratio_h" -
	25	[72]	SETTABLE 	4 -7 5	; "screen_zone" -
	26	[73]	CLOSURE  	5 0	; 0x7f971ac08360
	27	[73]	MOVE     	0 0
	28	[73]	SETTABLE 	4 -17 5	; "handler" -
	29	[74]	NEWTABLE 	5 0 5
	30	[76]	SETTABLE 	5 -3 -18	; "id" "filemanager_swipe"
	31	[77]	SETTABLE 	5 -5 -19	; "ges" "swipe"
	32	[78]	NEWTABLE 	6 0 4
	33	[79]	GETGLOBAL	7 -9	; DTAP_ZONE_MENU
	34	[79]	GETTABLE 	7 7 -10	; "x"
	35	[79]	SETTABLE 	6 -8 7	; "ratio_x" -
	36	[79]	GETGLOBAL	7 -9	; DTAP_ZONE_MENU
	37	[79]	GETTABLE 	7 7 -12	; "y"
	38	[79]	SETTABLE 	6 -11 7	; "ratio_y" -
	39	[80]	GETGLOBAL	7 -9	; DTAP_ZONE_MENU
	40	[80]	GETTABLE 	7 7 -14	; "w"
	41	[80]	SETTABLE 	6 -13 7	; "ratio_w" -
	42	[80]	GETGLOBAL	7 -9	; DTAP_ZONE_MENU
	43	[80]	GETTABLE 	7 7 -16	; "h"
	44	[80]	SETTABLE 	6 -15 7	; "ratio_h" -
	45	[81]	SETTABLE 	5 -7 6	; "screen_zone" -
	46	[82]	NEWTABLE 	6 2 0
	47	[83]	LOADK    	7 -21	; "rolling_swipe"
	48	[85]	LOADK    	8 -22	; "paging_swipe"
	49	[85]	SETLIST  	6 2 1	; 1
	50	[85]	SETTABLE 	5 -20 6	; "overrides" -
	51	[86]	CLOSURE  	6 1	; 0x7f971ac08280
	52	[86]	MOVE     	0 0
	53	[86]	SETTABLE 	5 -17 6	; "handler" -
	54	[88]	SETLIST  	3 2 1	; 1
	55	[65]	CALL     	1 3 1
	56	[89]	RETURN   	0 1

function <./frontend/apps/filemanager/filemanagermenu.lua:73,73> (6 instructions, 24 bytes at 0x7f971ac08360)
1 param, 4 slots, 1 upvalue, 1 local, 1 constant, 0 functions
	1	[73]	GETUPVAL 	1 0	; self
	2	[73]	SELF     	1 1 -1	; "onTapShowMenu"
	3	[73]	MOVE     	3 0
	4	[73]	TAILCALL 	1 3 0
	5	[73]	RETURN   	1 0
	6	[73]	RETURN   	0 1

function <./frontend/apps/filemanager/filemanagermenu.lua:86,86> (6 instructions, 24 bytes at 0x7f971ac08280)
1 param, 4 slots, 1 upvalue, 1 local, 1 constant, 0 functions
	1	[86]	GETUPVAL 	1 0	; self
	2	[86]	SELF     	1 1 -1	; "onSwipeShowMenu"
	3	[86]	MOVE     	3 0
	4	[86]	TAILCALL 	1 3 0
	5	[86]	RETURN   	1 0
	6	[86]	RETURN   	0 1

function <./frontend/apps/filemanager/filemanagermenu.lua:91,110> (45 instructions, 180 bytes at 0x7f971ac071c0)
1 param, 10 slots, 3 upvalues, 5 locals, 19 constants, 0 functions
	1	[92]	GETGLOBAL	1 -1	; G_reader_settings
	2	[92]	SELF     	1 1 -2	; "readSetting"
	3	[92]	LOADK    	3 -3	; "lastfile"
	4	[92]	CALL     	1 3 2
	5	[93]	TEST     	1 0 0
	6	[93]	JMP      	7	; to 14
	7	[93]	GETUPVAL 	2 0	; lfs
	8	[93]	GETTABLE 	2 2 -4	; "attributes"
	9	[93]	MOVE     	3 1
	10	[93]	LOADK    	4 -5	; "mode"
	11	[93]	CALL     	2 3 2
	12	[93]	EQ       	1 2 -6	; - "file"
	13	[93]	JMP      	14	; to 28
	14	[94]	GETGLOBAL	2 -7	; require
	15	[94]	LOADK    	3 -8	; "ui/widget/infomessage"
	16	[94]	CALL     	2 2 2
	17	[95]	GETUPVAL 	3 1	; UIManager
	18	[95]	SELF     	3 3 -9	; "show"
	19	[95]	SELF     	5 2 -10	; "new"
	20	[95]	NEWTABLE 	7 0 1
	21	[96]	GETUPVAL 	8 2	; _
	22	[96]	LOADK    	9 -12	; "Cannot open last document"
	23	[96]	CALL     	8 2 2
	24	[96]	SETTABLE 	7 -11 8	; "text" -
	25	[95]	CALL     	5 3 0
	26	[95]	CALL     	3 0 1
	27	[98]	RETURN   	0 1
	28	[100]	GETGLOBAL	2 -7	; require
	29	[100]	LOADK    	3 -13	; "apps/reader/readerui"
	30	[100]	CALL     	2 2 2
	31	[101]	SELF     	3 2 -14	; "showReader"
	32	[101]	MOVE     	5 1
	33	[101]	CALL     	3 3 1
	34	[104]	GETTABLE 	3 0 -15	; "menu_container"
	35	[104]	TEST     	3 0 0
	36	[104]	JMP      	2	; to 39
	37	[105]	SELF     	3 0 -16	; "onCloseFileManagerMenu"
	38	[105]	CALL     	3 2 1
	39	[108]	GETGLOBAL	3 -7	; require
	40	[108]	LOADK    	4 -17	; "apps/filemanager/filemanager"
	41	[108]	CALL     	3 2 2
	42	[109]	GETTABLE 	4 3 -18	; "instance"
	43	[109]	SELF     	4 4 -19	; "onClose"
	44	[109]	CALL     	4 2 1
	45	[110]	RETURN   	0 1

function <./frontend/apps/filemanager/filemanagermenu.lua:112,567> (562 instructions, 2248 bytes at 0x7f971ac09200)
1 param, 12 slots, 16 upvalues, 20 locals, 97 constants, 53 functions
	1	[113]	GETGLOBAL	1 -1	; pairs
	2	[113]	GETTABLE 	2 0 -2	; "registered_widgets"
	3	[113]	CALL     	1 2 4
	4	[113]	JMP      	13	; to 18
	5	[114]	GETGLOBAL	6 -3	; pcall
	6	[114]	GETTABLE 	7 5 -4	; "addToMainMenu"
	7	[114]	MOVE     	8 5
	8	[114]	GETTABLE 	9 0 -5	; "menu_items"
	9	[114]	CALL     	6 4 3
	10	[115]	TEST     	6 0 1
	11	[115]	JMP      	6	; to 18
	12	[116]	GETUPVAL 	8 0	; logger
	13	[116]	GETTABLE 	8 8 -6	; "err"
	14	[116]	LOADK    	9 -7	; "failed to register widget"
	15	[116]	GETTABLE 	10 5 -8	; "name"
	16	[116]	MOVE     	11 7
	17	[116]	CALL     	8 4 1
	18	[113]	TFORLOOP 	1 2
	19	[117]	JMP      	-15	; to 5
	20	[121]	GETTABLE 	1 0 -5	; "menu_items"
	21	[121]	NEWTABLE 	2 0 3
	22	[122]	GETUPVAL 	3 1	; _
	23	[122]	LOADK    	4 -11	; "Show hidden files"
	24	[122]	CALL     	3 2 2
	25	[122]	SETTABLE 	2 -10 3	; "text" -
	26	[123]	CLOSURE  	3 0	; 0x7f971ac099f0
	27	[123]	MOVE     	0 0
	28	[123]	SETTABLE 	2 -12 3	; "checked_func" -
	29	[124]	CLOSURE  	3 1	; 0x7f971ac0a0e0
	30	[124]	MOVE     	0 0
	31	[124]	SETTABLE 	2 -13 3	; "callback" -
	32	[125]	SETTABLE 	1 -9 2	; "show_hidden_files" -
	33	[126]	GETTABLE 	1 0 -5	; "menu_items"
	34	[126]	NEWTABLE 	2 0 3
	35	[127]	GETUPVAL 	3 1	; _
	36	[127]	LOADK    	4 -15	; "Show unsupported files"
	37	[127]	CALL     	3 2 2
	38	[127]	SETTABLE 	2 -10 3	; "text" -
	39	[128]	CLOSURE  	3 2	; 0x7f971ac09c00
	40	[128]	MOVE     	0 0
	41	[128]	SETTABLE 	2 -12 3	; "checked_func" -
	42	[129]	CLOSURE  	3 3	; 0x7f971ac0a540
	43	[129]	MOVE     	0 0
	44	[129]	SETTABLE 	2 -13 3	; "callback" -
	45	[130]	SETTABLE 	1 -14 2	; "show_unsupported_files" -
	46	[131]	GETTABLE 	1 0 -5	; "menu_items"
	47	[131]	NEWTABLE 	2 0 2
	48	[132]	GETUPVAL 	3 1	; _
	49	[132]	LOADK    	4 -17	; "Items"
	50	[132]	CALL     	3 2 2
	51	[132]	SETTABLE 	2 -10 3	; "text" -
	52	[133]	NEWTABLE 	3 3 0
	53	[133]	NEWTABLE 	4 0 4
	54	[135]	GETUPVAL 	5 1	; _
	55	[135]	LOADK    	6 -19	; "Items per page"
	56	[135]	CALL     	5 2 2
	57	[135]	SETTABLE 	4 -10 5	; "text" -
	58	[136]	GETUPVAL 	5 1	; _
	59	[140]	LOADK    	6 -21	; "This sets the number of items per page in:\n- File browser and history in 'classic' display mode\n- File and directory selection\n- Table of contents\n- Bookmarks list"
	60	[136]	CALL     	5 2 2
	61	[140]	SETTABLE 	4 -20 5	; "help_text" -
	62	[141]	SETTABLE 	4 -22 -23	; "keep_menu_open" true
	63	[158]	CLOSURE  	5 4	; 0x7f971ac0ace0
	64	[158]	GETUPVAL 	0 2	; Screen
	65	[158]	GETUPVAL 	0 1	; _
	66	[158]	MOVE     	0 0
	67	[158]	GETUPVAL 	0 3	; UIManager
	68	[158]	SETTABLE 	4 -13 5	; "callback" -
	69	[159]	NEWTABLE 	5 0 3
	70	[161]	GETUPVAL 	6 1	; _
	71	[161]	LOADK    	7 -24	; "Font size"
	72	[161]	CALL     	6 2 2
	73	[161]	SETTABLE 	5 -10 6	; "text" -
	74	[162]	SETTABLE 	5 -22 -23	; "keep_menu_open" true
	75	[182]	CLOSURE  	6 5	; 0x7f971ac0b360
	76	[182]	GETUPVAL 	0 2	; Screen
	77	[182]	GETUPVAL 	0 1	; _
	78	[182]	MOVE     	0 0
	79	[182]	GETUPVAL 	0 3	; UIManager
	80	[182]	SETTABLE 	5 -13 6	; "callback" -
	81	[183]	NEWTABLE 	6 0 4
	82	[185]	GETUPVAL 	7 1	; _
	83	[185]	LOADK    	8 -25	; "Reduce font size to show more text"
	84	[185]	CALL     	7 2 2
	85	[185]	SETTABLE 	6 -10 7	; "text" -
	86	[186]	SETTABLE 	6 -22 -23	; "keep_menu_open" true
	87	[189]	CLOSURE  	7 6	; 0x7f971ac0c450
	88	[189]	SETTABLE 	6 -12 7	; "checked_func" -
	89	[192]	CLOSURE  	7 7	; 0x7f971ac0c870
	90	[192]	SETTABLE 	6 -13 7	; "callback" -
	91	[194]	SETLIST  	3 3 1	; 1
	92	[194]	SETTABLE 	2 -18 3	; "sub_item_table" -
	93	[195]	SETTABLE 	1 -16 2	; "items" -
	94	[196]	GETTABLE 	1 0 -5	; "menu_items"
	95	[196]	GETTABLE 	2 0 -27	; "ui"
	96	[196]	SELF     	2 2 -28	; "getSortingMenuTable"
	97	[196]	CALL     	2 2 2
	98	[196]	SETTABLE 	1 -26 2	; "sort_by" -
	99	[197]	GETTABLE 	1 0 -5	; "menu_items"
	100	[197]	NEWTABLE 	2 0 3
	101	[198]	GETUPVAL 	3 1	; _
	102	[198]	LOADK    	4 -30	; "Reverse sorting"
	103	[198]	CALL     	3 2 2
	104	[198]	SETTABLE 	2 -10 3	; "text" -
	105	[199]	CLOSURE  	3 8	; 0x7f971ac0cc50
	106	[199]	MOVE     	0 0
	107	[199]	SETTABLE 	2 -12 3	; "checked_func" -
	108	[200]	CLOSURE  	3 9	; 0x7f971ac0cfd0
	109	[200]	MOVE     	0 0
	110	[200]	SETTABLE 	2 -13 3	; "callback" -
	111	[201]	SETTABLE 	1 -29 2	; "reverse_sorting" -
	112	[202]	GETTABLE 	1 0 -5	; "menu_items"
	113	[202]	GETTABLE 	2 0 -27	; "ui"
	114	[202]	SELF     	2 2 -32	; "getStartWithMenuTable"
	115	[202]	CALL     	2 2 2
	116	[202]	SETTABLE 	1 -31 2	; "start_with" -
	117	[203]	GETUPVAL 	1 4	; Device
	118	[203]	SELF     	1 1 -33	; "supportsScreensaver"
	119	[203]	CALL     	1 2 2
	120	[203]	TEST     	1 0 0
	121	[203]	JMP      	11	; to 133
	122	[204]	GETTABLE 	1 0 -5	; "menu_items"
	123	[204]	NEWTABLE 	2 0 2
	124	[205]	GETUPVAL 	3 1	; _
	125	[205]	LOADK    	4 -35	; "Screensaver"
	126	[205]	CALL     	3 2 2
	127	[205]	SETTABLE 	2 -10 3	; "text" -
	128	[206]	GETGLOBAL	3 -36	; require
	129	[206]	LOADK    	4 -37	; "ui/elements/screensaver_menu"
	130	[206]	CALL     	3 2 2
	131	[206]	SETTABLE 	2 -18 3	; "sub_item_table" -
	132	[207]	SETTABLE 	1 -34 2	; "screensaver" -
	133	[210]	GETGLOBAL	1 -1	; pairs
	134	[210]	GETGLOBAL	2 -38	; dofile
	135	[210]	LOADK    	3 -39	; "frontend/ui/elements/common_settings_menu_table.lua"
	136	[210]	CALL     	2 2 0
	137	[210]	CALL     	1 0 4
	138	[210]	JMP      	2	; to 141
	139	[211]	GETTABLE 	6 0 -5	; "menu_items"
	140	[211]	SETTABLE 	6 4 5
	141	[210]	TFORLOOP 	1 2
	142	[211]	JMP      	-4	; to 139
	143	[215]	GETTABLE 	1 0 -5	; "menu_items"
	144	[215]	NEWTABLE 	2 0 3
	145	[216]	GETUPVAL 	3 1	; _
	146	[216]	LOADK    	4 -41	; "Advanced settings"
	147	[216]	CALL     	3 2 2
	148	[216]	SETTABLE 	2 -10 3	; "text" -
	149	[219]	CLOSURE  	3 10	; 0x7f971ac09b00
	150	[219]	GETUPVAL 	0 5	; SetDefaults
	151	[219]	SETTABLE 	2 -13 3	; "callback" -
	152	[222]	CLOSURE  	3 11	; 0x7f971ac0b050
	153	[222]	GETUPVAL 	0 5	; SetDefaults
	154	[222]	SETTABLE 	2 -42 3	; "hold_callback" -
	155	[223]	SETTABLE 	1 -40 2	; "advanced_settings" -
	156	[224]	GETTABLE 	1 0 -5	; "menu_items"
	157	[224]	NEWTABLE 	2 0 2
	158	[225]	GETUPVAL 	3 1	; _
	159	[225]	LOADK    	4 -44	; "Plugin management"
	160	[225]	CALL     	3 2 2
	161	[225]	SETTABLE 	2 -10 3	; "text" -
	162	[226]	GETUPVAL 	3 6	; PluginLoader
	163	[226]	SELF     	3 3 -45	; "genPluginManagerSubItem"
	164	[226]	CALL     	3 2 2
	165	[226]	SETTABLE 	2 -18 3	; "sub_item_table" -
	166	[227]	SETTABLE 	1 -43 2	; "plugin_management" -
	167	[229]	GETTABLE 	1 0 -5	; "menu_items"
	168	[229]	NEWTABLE 	2 0 2
	169	[230]	GETUPVAL 	3 1	; _
	170	[230]	LOADK    	4 -47	; "OPDS catalog"
	171	[230]	CALL     	3 2 2
	172	[230]	SETTABLE 	2 -10 3	; "text" -
	173	[239]	CLOSURE  	3 12	; 0x7f971ac0d0e0
	174	[239]	MOVE     	0 0
	175	[239]	GETUPVAL 	0 3	; UIManager
	176	[239]	SETTABLE 	2 -13 3	; "callback" -
	177	[240]	SETTABLE 	1 -46 2	; "opds_catalog" -
	178	[241]	GETTABLE 	1 0 -5	; "menu_items"
	179	[241]	NEWTABLE 	2 0 2
	180	[242]	GETUPVAL 	3 1	; _
	181	[242]	LOADK    	4 -49	; "Developer options"
	182	[242]	CALL     	3 2 2
	183	[242]	SETTABLE 	2 -10 3	; "text" -
	184	[243]	NEWTABLE 	3 3 0
	185	[243]	NEWTABLE 	4 0 2
	186	[245]	GETUPVAL 	5 1	; _
	187	[245]	LOADK    	6 -50	; "Clear readers' caches"
	188	[245]	CALL     	5 2 2
	189	[245]	SETTABLE 	4 -10 5	; "text" -
	190	[267]	CLOSURE  	5 13	; 0x7f971ac0ce90
	191	[267]	GETUPVAL 	0 3	; UIManager
	192	[267]	GETUPVAL 	0 7	; ConfirmBox
	193	[267]	GETUPVAL 	0 1	; _
	194	[267]	GETUPVAL 	0 8	; lfs
	195	[267]	SETTABLE 	4 -13 5	; "callback" -
	196	[268]	NEWTABLE 	5 0 3
	197	[270]	GETUPVAL 	6 1	; _
	198	[270]	LOADK    	7 -51	; "Enable debug logging"
	199	[270]	CALL     	6 2 2
	200	[270]	SETTABLE 	5 -10 6	; "text" -
	201	[273]	CLOSURE  	6 14	; 0x7f971ae041d0
	202	[273]	SETTABLE 	5 -12 6	; "checked_func" -
	203	[283]	CLOSURE  	6 15	; 0x7f971ae04350
	204	[283]	GETUPVAL 	0 9	; dbg
	205	[283]	SETTABLE 	5 -13 6	; "callback" -
	206	[284]	NEWTABLE 	6 0 4
	207	[286]	GETUPVAL 	7 1	; _
	208	[286]	LOADK    	8 -52	; "Enable verbose debug logging"
	209	[286]	CALL     	7 2 2
	210	[286]	SETTABLE 	6 -10 7	; "text" -
	211	[289]	CLOSURE  	7 16	; 0x7f971ae04810
	212	[289]	SETTABLE 	6 -53 7	; "enabled_func" -
	213	[292]	CLOSURE  	7 17	; 0x7f971ae04ca0
	214	[292]	SETTABLE 	6 -12 7	; "checked_func" -
	215	[300]	CLOSURE  	7 18	; 0x7f971ae05050
	216	[300]	GETUPVAL 	0 9	; dbg
	217	[300]	SETTABLE 	6 -13 7	; "callback" -
	218	[302]	SETLIST  	3 3 1	; 1
	219	[302]	SETTABLE 	2 -18 3	; "sub_item_table" -
	220	[303]	SETTABLE 	1 -48 2	; "developer_options" -
	221	[304]	GETUPVAL 	1 4	; Device
	222	[304]	SELF     	1 1 -54	; "isKobo"
	223	[304]	CALL     	1 2 2
	224	[304]	TEST     	1 0 0
	225	[304]	JMP      	17	; to 243
	226	[305]	GETGLOBAL	1 -55	; table
	227	[305]	GETTABLE 	1 1 -56	; "insert"
	228	[305]	GETTABLE 	2 0 -5	; "menu_items"
	229	[305]	GETTABLE 	2 2 -48	; "developer_options"
	230	[305]	GETTABLE 	2 2 -18	; "sub_item_table"
	231	[305]	NEWTABLE 	3 0 3
	232	[306]	GETUPVAL 	4 1	; _
	233	[306]	LOADK    	5 -57	; "Disable forced 8-bit pixel depth"
	234	[306]	CALL     	4 2 2
	235	[306]	SETTABLE 	3 -10 4	; "text" -
	236	[309]	CLOSURE  	4 19	; 0x7f971ae05420
	237	[309]	SETTABLE 	3 -12 4	; "checked_func" -
	238	[316]	CLOSURE  	4 20	; 0x7f971ae05860
	239	[316]	GETUPVAL 	0 3	; UIManager
	240	[316]	GETUPVAL 	0 1	; _
	241	[316]	SETTABLE 	3 -13 4	; "callback" -
	242	[305]	CALL     	1 3 1
	243	[320]	GETUPVAL 	1 4	; Device
	244	[320]	SELF     	1 1 -54	; "isKobo"
	245	[320]	CALL     	1 2 2
	246	[320]	TEST     	1 0 0
	247	[320]	JMP      	17	; to 265
	248	[321]	GETGLOBAL	1 -55	; table
	249	[321]	GETTABLE 	1 1 -56	; "insert"
	250	[321]	GETTABLE 	2 0 -5	; "menu_items"
	251	[321]	GETTABLE 	2 2 -48	; "developer_options"
	252	[321]	GETTABLE 	2 2 -18	; "sub_item_table"
	253	[321]	NEWTABLE 	3 0 3
	254	[322]	GETUPVAL 	4 1	; _
	255	[322]	LOADK    	5 -58	; "Always abort on crash"
	256	[322]	CALL     	4 2 2
	257	[322]	SETTABLE 	3 -10 4	; "text" -
	258	[325]	CLOSURE  	4 21	; 0x7f971ae06070
	259	[325]	SETTABLE 	3 -12 4	; "checked_func" -
	260	[332]	CLOSURE  	4 22	; 0x7f971ae060f0
	261	[332]	GETUPVAL 	0 3	; UIManager
	262	[332]	GETUPVAL 	0 1	; _
	263	[332]	SETTABLE 	3 -13 4	; "callback" -
	264	[321]	CALL     	1 3 1
	265	[335]	GETUPVAL 	1 4	; Device
	266	[335]	GETTABLE 	1 1 -59	; "should_restrict_JIT"
	267	[335]	TEST     	1 0 1
	268	[335]	JMP      	20	; to 289
	269	[336]	GETGLOBAL	1 -55	; table
	270	[336]	GETTABLE 	1 1 -56	; "insert"
	271	[336]	GETTABLE 	2 0 -5	; "menu_items"
	272	[336]	GETTABLE 	2 2 -48	; "developer_options"
	273	[336]	GETTABLE 	2 2 -18	; "sub_item_table"
	274	[336]	NEWTABLE 	3 0 4
	275	[337]	GETUPVAL 	4 1	; _
	276	[337]	LOADK    	5 -60	; "Disable C blitter"
	277	[337]	CALL     	4 2 2
	278	[337]	SETTABLE 	3 -10 4	; "text" -
	279	[340]	CLOSURE  	4 23	; 0x7f971ae06880
	280	[340]	GETUPVAL 	0 8	; lfs
	281	[340]	SETTABLE 	3 -53 4	; "enabled_func" -
	282	[343]	CLOSURE  	4 24	; 0x7f971ae06b70
	283	[343]	SETTABLE 	3 -12 4	; "checked_func" -
	284	[350]	CLOSURE  	4 25	; 0x7f971ae06c70
	285	[350]	GETUPVAL 	0 3	; UIManager
	286	[350]	GETUPVAL 	0 1	; _
	287	[350]	SETTABLE 	3 -13 4	; "callback" -
	288	[336]	CALL     	1 3 1
	289	[353]	GETUPVAL 	1 4	; Device
	290	[353]	SELF     	1 1 -61	; "hasEinkScreen"
	291	[353]	CALL     	1 2 2
	292	[353]	TEST     	1 0 0
	293	[353]	JMP      	23	; to 317
	294	[353]	GETUPVAL 	1 4	; Device
	295	[353]	SELF     	1 1 -62	; "canHWDither"
	296	[353]	CALL     	1 2 2
	297	[353]	TEST     	1 0 0
	298	[353]	JMP      	18	; to 317
	299	[354]	GETGLOBAL	1 -55	; table
	300	[354]	GETTABLE 	1 1 -56	; "insert"
	301	[354]	GETTABLE 	2 0 -5	; "menu_items"
	302	[354]	GETTABLE 	2 2 -48	; "developer_options"
	303	[354]	GETTABLE 	2 2 -18	; "sub_item_table"
	304	[354]	NEWTABLE 	3 0 3
	305	[355]	GETUPVAL 	4 1	; _
	306	[355]	LOADK    	5 -63	; "Disable HW dithering"
	307	[355]	CALL     	4 2 2
	308	[355]	SETTABLE 	3 -10 4	; "text" -
	309	[358]	CLOSURE  	4 26	; 0x7f971ae07430
	310	[358]	GETUPVAL 	0 4	; Device
	311	[358]	SETTABLE 	3 -12 4	; "checked_func" -
	312	[367]	CLOSURE  	4 27	; 0x7f971ae07520
	313	[367]	GETUPVAL 	0 4	; Device
	314	[367]	GETUPVAL 	0 3	; UIManager
	315	[367]	SETTABLE 	3 -13 4	; "callback" -
	316	[354]	CALL     	1 3 1
	317	[370]	GETUPVAL 	1 4	; Device
	318	[370]	SELF     	1 1 -61	; "hasEinkScreen"
	319	[370]	CALL     	1 2 2
	320	[370]	TEST     	1 0 0
	321	[370]	JMP      	21	; to 343
	322	[371]	GETGLOBAL	1 -55	; table
	323	[371]	GETTABLE 	1 1 -56	; "insert"
	324	[371]	GETTABLE 	2 0 -5	; "menu_items"
	325	[371]	GETTABLE 	2 2 -48	; "developer_options"
	326	[371]	GETTABLE 	2 2 -18	; "sub_item_table"
	327	[371]	NEWTABLE 	3 0 4
	328	[372]	GETUPVAL 	4 1	; _
	329	[372]	LOADK    	5 -64	; "Disable SW dithering"
	330	[372]	CALL     	4 2 2
	331	[372]	SETTABLE 	3 -10 4	; "text" -
	332	[375]	CLOSURE  	4 28	; 0x7f971ae07a20
	333	[375]	GETUPVAL 	0 4	; Device
	334	[375]	SETTABLE 	3 -53 4	; "enabled_func" -
	335	[378]	CLOSURE  	4 29	; 0x7f971ae07c00
	336	[378]	GETUPVAL 	0 4	; Device
	337	[378]	SETTABLE 	3 -12 4	; "checked_func" -
	338	[387]	CLOSURE  	4 30	; 0x7f971ae07f60
	339	[387]	GETUPVAL 	0 4	; Device
	340	[387]	GETUPVAL 	0 3	; UIManager
	341	[387]	SETTABLE 	3 -13 4	; "callback" -
	342	[371]	CALL     	1 3 1
	343	[390]	GETUPVAL 	1 4	; Device
	344	[390]	SELF     	1 1 -65	; "isAndroid"
	345	[390]	CALL     	1 2 2
	346	[390]	TEST     	1 0 0
	347	[390]	JMP      	14	; to 362
	348	[391]	GETGLOBAL	1 -55	; table
	349	[391]	GETTABLE 	1 1 -56	; "insert"
	350	[391]	GETTABLE 	2 0 -5	; "menu_items"
	351	[391]	GETTABLE 	2 2 -48	; "developer_options"
	352	[391]	GETTABLE 	2 2 -18	; "sub_item_table"
	353	[391]	NEWTABLE 	3 0 2
	354	[392]	GETUPVAL 	4 1	; _
	355	[392]	LOADK    	5 -66	; "Start E-ink test"
	356	[392]	CALL     	4 2 2
	357	[392]	SETTABLE 	3 -10 4	; "text" -
	358	[395]	CLOSURE  	4 31	; 0x7f971ae083e0
	359	[395]	GETUPVAL 	0 4	; Device
	360	[395]	SETTABLE 	3 -13 4	; "callback" -
	361	[391]	CALL     	1 3 1
	362	[399]	GETGLOBAL	1 -55	; table
	363	[399]	GETTABLE 	1 1 -56	; "insert"
	364	[399]	GETTABLE 	2 0 -5	; "menu_items"
	365	[399]	GETTABLE 	2 2 -48	; "developer_options"
	366	[399]	GETTABLE 	2 2 -18	; "sub_item_table"
	367	[399]	NEWTABLE 	3 0 3
	368	[400]	GETUPVAL 	4 1	; _
	369	[400]	LOADK    	5 -67	; "Disable enhanced UI text shaping (xtext)"
	370	[400]	CALL     	4 2 2
	371	[400]	SETTABLE 	3 -10 4	; "text" -
	372	[403]	CLOSURE  	4 32	; 0x7f971ae08540
	373	[403]	SETTABLE 	3 -12 4	; "checked_func" -
	374	[410]	CLOSURE  	4 33	; 0x7f971ae087e0
	375	[410]	GETUPVAL 	0 3	; UIManager
	376	[410]	GETUPVAL 	0 1	; _
	377	[410]	SETTABLE 	3 -13 4	; "callback" -
	378	[399]	CALL     	1 3 1
	379	[412]	GETGLOBAL	1 -55	; table
	380	[412]	GETTABLE 	1 1 -56	; "insert"
	381	[412]	GETTABLE 	2 0 -5	; "menu_items"
	382	[412]	GETTABLE 	2 2 -48	; "developer_options"
	383	[412]	GETTABLE 	2 2 -18	; "sub_item_table"
	384	[412]	NEWTABLE 	3 0 2
	385	[413]	SETTABLE 	3 -10 -68	; "text" "UI layout mirroring and text direction"
	386	[414]	NEWTABLE 	4 2 0
	387	[414]	NEWTABLE 	5 0 3
	388	[416]	GETUPVAL 	6 1	; _
	389	[416]	LOADK    	7 -69	; "Reverse UI layout mirroring"
	390	[416]	CALL     	6 2 2
	391	[416]	SETTABLE 	5 -10 6	; "text" -
	392	[419]	CLOSURE  	6 34	; 0x7f971ae090a0
	393	[419]	SETTABLE 	5 -12 6	; "checked_func" -
	394	[426]	CLOSURE  	6 35	; 0x7f971ae091b0
	395	[426]	GETUPVAL 	0 3	; UIManager
	396	[426]	GETUPVAL 	0 1	; _
	397	[426]	SETTABLE 	5 -13 6	; "callback" -
	398	[427]	NEWTABLE 	6 0 3
	399	[429]	GETUPVAL 	7 1	; _
	400	[429]	LOADK    	8 -70	; "Reverse UI text direction"
	401	[429]	CALL     	7 2 2
	402	[429]	SETTABLE 	6 -10 7	; "text" -
	403	[432]	CLOSURE  	7 36	; 0x7f971ae09940
	404	[432]	SETTABLE 	6 -12 7	; "checked_func" -
	405	[439]	CLOSURE  	7 37	; 0x7f971ae09a50
	406	[439]	GETUPVAL 	0 3	; UIManager
	407	[439]	GETUPVAL 	0 1	; _
	408	[439]	SETTABLE 	6 -13 7	; "callback" -
	409	[441]	SETLIST  	4 2 1	; 1
	410	[441]	SETTABLE 	3 -18 4	; "sub_item_table" -
	411	[412]	CALL     	1 3 1
	412	[443]	GETGLOBAL	1 -55	; table
	413	[443]	GETTABLE 	1 1 -56	; "insert"
	414	[443]	GETTABLE 	2 0 -5	; "menu_items"
	415	[443]	GETTABLE 	2 2 -48	; "developer_options"
	416	[443]	GETTABLE 	2 2 -18	; "sub_item_table"
	417	[443]	NEWTABLE 	3 0 4
	418	[450]	CLOSURE  	4 38	; 0x7f971ae0a1e0
	419	[450]	GETUPVAL 	0 1	; _
	420	[450]	SETTABLE 	3 -71 4	; "text_func" -
	421	[453]	CLOSURE  	4 39	; 0x7f971ae0a780
	422	[453]	SETTABLE 	3 -12 4	; "checked_func" -
	423	[458]	CLOSURE  	4 40	; 0x7f971ae0a8c0
	424	[458]	SETTABLE 	3 -13 4	; "callback" -
	425	[462]	CLOSURE  	4 41	; 0x7f971ae0ac00
	426	[462]	SETTABLE 	3 -42 4	; "hold_callback" -
	427	[443]	CALL     	1 3 1
	428	[465]	GETTABLE 	1 0 -5	; "menu_items"
	429	[465]	NEWTABLE 	2 0 2
	430	[466]	GETUPVAL 	3 1	; _
	431	[466]	LOADK    	4 -73	; "Cloud storage"
	432	[466]	CALL     	3 2 2
	433	[466]	SETTABLE 	2 -10 3	; "text" -
	434	[475]	CLOSURE  	3 42	; 0x7f971ae0af60
	435	[475]	GETUPVAL 	0 10	; CloudStorage
	436	[475]	GETUPVAL 	0 3	; UIManager
	437	[475]	MOVE     	0 0
	438	[475]	SETTABLE 	2 -13 3	; "callback" -
	439	[476]	SETTABLE 	1 -72 2	; "cloud_storage" -
	440	[479]	GETTABLE 	1 0 -5	; "menu_items"
	441	[479]	NEWTABLE 	2 0 2
	442	[480]	GETUPVAL 	3 1	; _
	443	[480]	LOADK    	4 -75	; "Find a book via calibre metadata"
	444	[480]	CALL     	3 2 2
	445	[480]	SETTABLE 	2 -10 3	; "text" -
	446	[484]	CLOSURE  	3 43	; 0x7f971ae0b9d0
	447	[484]	GETUPVAL 	0 11	; Search
	448	[484]	SETTABLE 	2 -13 3	; "callback" -
	449	[485]	SETTABLE 	1 -74 2	; "find_book_in_calibre_catalog" -
	450	[486]	GETTABLE 	1 0 -5	; "menu_items"
	451	[486]	NEWTABLE 	2 0 2
	452	[488]	GETUPVAL 	3 1	; _
	453	[488]	LOADK    	4 -77	; "Find a file"
	454	[488]	CALL     	3 2 2
	455	[488]	SETTABLE 	2 -10 3	; "text" -
	456	[491]	CLOSURE  	3 44	; 0x7f971ae0bbb0
	457	[491]	MOVE     	0 0
	458	[491]	GETUPVAL 	0 12	; Event
	459	[491]	SETTABLE 	2 -13 3	; "callback" -
	460	[492]	SETTABLE 	1 -76 2	; "find_file" -
	461	[495]	GETTABLE 	1 0 -5	; "menu_items"
	462	[495]	NEWTABLE 	2 0 4
	463	[503]	CLOSURE  	3 45	; 0x7f971ae0bdd0
	464	[503]	GETUPVAL 	0 1	; _
	465	[503]	GETUPVAL 	0 13	; util
	466	[503]	GETUPVAL 	0 14	; T
	467	[503]	GETUPVAL 	0 15	; BD
	468	[503]	SETTABLE 	2 -71 3	; "text_func" -
	469	[506]	CLOSURE  	3 46	; 0x7f971ae0c210
	470	[506]	SETTABLE 	2 -53 3	; "enabled_func" -
	471	[509]	CLOSURE  	3 47	; 0x7f971ae0be90
	472	[509]	MOVE     	0 0
	473	[509]	SETTABLE 	2 -13 3	; "callback" -
	474	[519]	CLOSURE  	3 48	; 0x7f971ae0ab10
	475	[519]	GETUPVAL 	0 3	; UIManager
	476	[519]	GETUPVAL 	0 7	; ConfirmBox
	477	[519]	GETUPVAL 	0 14	; T
	478	[519]	GETUPVAL 	0 1	; _
	479	[519]	GETUPVAL 	0 15	; BD
	480	[519]	MOVE     	0 0
	481	[519]	SETTABLE 	2 -42 3	; "hold_callback" -
	482	[520]	SETTABLE 	1 -78 2	; "open_last_document" -
	483	[522]	GETGLOBAL	1 -1	; pairs
	484	[522]	GETGLOBAL	2 -38	; dofile
	485	[522]	LOADK    	3 -79	; "frontend/ui/elements/common_info_menu_table.lua"
	486	[522]	CALL     	2 2 0
	487	[522]	CALL     	1 0 4
	488	[522]	JMP      	2	; to 491
	489	[523]	GETTABLE 	6 0 -5	; "menu_items"
	490	[523]	SETTABLE 	6 4 5
	491	[522]	TFORLOOP 	1 2
	492	[523]	JMP      	-4	; to 489
	493	[525]	GETTABLE 	1 0 -5	; "menu_items"
	494	[525]	NEWTABLE 	2 0 2
	495	[526]	GETUPVAL 	3 1	; _
	496	[526]	LOADK    	4 -81	; "Exit"
	497	[526]	CALL     	3 2 2
	498	[526]	SETTABLE 	2 -10 3	; "text" -
	499	[529]	CLOSURE  	3 49	; 0x7f971ae04a90
	500	[529]	MOVE     	0 0
	501	[529]	SETTABLE 	2 -42 3	; "hold_callback" -
	502	[530]	SETTABLE 	1 -80 2	; "exit_menu" -
	503	[531]	GETTABLE 	1 0 -5	; "menu_items"
	504	[531]	NEWTABLE 	2 0 2
	505	[532]	GETUPVAL 	3 1	; _
	506	[532]	LOADK    	4 -81	; "Exit"
	507	[532]	CALL     	3 2 2
	508	[532]	SETTABLE 	2 -10 3	; "text" -
	509	[535]	CLOSURE  	3 50	; 0x7f971ae0aa00
	510	[535]	MOVE     	0 0
	511	[535]	SETTABLE 	2 -13 3	; "callback" -
	512	[536]	SETTABLE 	1 -82 2	; "exit" -
	513	[537]	GETTABLE 	1 0 -5	; "menu_items"
	514	[537]	NEWTABLE 	2 0 2
	515	[538]	GETUPVAL 	3 1	; _
	516	[538]	LOADK    	4 -84	; "Restart KOReader"
	517	[538]	CALL     	3 2 2
	518	[538]	SETTABLE 	2 -10 3	; "text" -
	519	[543]	CLOSURE  	3 51	; 0x7f971ae0ae10
	520	[543]	MOVE     	0 0
	521	[543]	GETUPVAL 	0 3	; UIManager
	522	[543]	SETTABLE 	2 -13 3	; "callback" -
	523	[544]	SETTABLE 	1 -83 2	; "restart_koreader" -
	524	[545]	GETUPVAL 	1 4	; Device
	525	[545]	SELF     	1 1 -85	; "canRestart"
	526	[545]	CALL     	1 2 2
	527	[545]	TEST     	1 0 1
	528	[545]	JMP      	8	; to 537
	529	[546]	GETTABLE 	1 0 -5	; "menu_items"
	530	[546]	GETTABLE 	2 0 -5	; "menu_items"
	531	[546]	GETTABLE 	2 2 -82	; "exit"
	532	[546]	SETTABLE 	1 -80 2	; "exit_menu" -
	533	[547]	GETTABLE 	1 0 -5	; "menu_items"
	534	[547]	SETTABLE 	1 -82 -86	; "exit" nil
	535	[548]	GETTABLE 	1 0 -5	; "menu_items"
	536	[548]	SETTABLE 	1 -83 -86	; "restart_koreader" nil
	537	[550]	GETUPVAL 	1 4	; Device
	538	[550]	SELF     	1 1 -87	; "isTouchDevice"
	539	[550]	CALL     	1 2 2
	540	[550]	TEST     	1 0 1
	541	[550]	JMP      	8	; to 550
	542	[553]	GETTABLE 	1 0 -5	; "menu_items"
	543	[553]	NEWTABLE 	2 0 3
	544	[554]	SETTABLE 	2 -89 -90	; "icon" "resources/icons/appbar.plus.png"
	545	[555]	SETTABLE 	2 -91 -92	; "remember" false
	546	[559]	CLOSURE  	3 52	; 0x7f971ae06d20
	547	[559]	MOVE     	0 0
	548	[559]	SETTABLE 	2 -13 3	; "callback" -
	549	[560]	SETTABLE 	1 -88 2	; "plus_menu" -
	550	[563]	GETGLOBAL	1 -36	; require
	551	[563]	LOADK    	2 -93	; "ui/elements/filemanager_menu_order"
	552	[563]	CALL     	1 2 2
	553	[565]	GETGLOBAL	2 -36	; require
	554	[565]	LOADK    	3 -94	; "ui/menusorter"
	555	[565]	CALL     	2 2 2
	556	[566]	SELF     	3 2 -96	; "mergeAndSort"
	557	[566]	LOADK    	5 -97	; "filemanager"
	558	[566]	GETTABLE 	6 0 -5	; "menu_items"
	559	[566]	MOVE     	7 1
	560	[566]	CALL     	3 5 2
	561	[566]	SETTABLE 	0 -95 3	; "tab_item_table" -
	562	[567]	RETURN   	0 1

function <./frontend/apps/filemanager/filemanagermenu.lua:123,123> (6 instructions, 24 bytes at 0x7f971ac099f0)
0 params, 2 slots, 1 upvalue, 0 locals, 3 constants, 0 functions
	1	[123]	GETUPVAL 	0 0	; self
	2	[123]	GETTABLE 	0 0 -1	; "ui"
	3	[123]	GETTABLE 	0 0 -2	; "file_chooser"
	4	[123]	GETTABLE 	0 0 -3	; "show_hidden"
	5	[123]	RETURN   	0 2
	6	[123]	RETURN   	0 1

function <./frontend/apps/filemanager/filemanagermenu.lua:124,124> (5 instructions, 20 bytes at 0x7f971ac0a0e0)
0 params, 2 slots, 1 upvalue, 0 locals, 2 constants, 0 functions
	1	[124]	GETUPVAL 	0 0	; self
	2	[124]	GETTABLE 	0 0 -1	; "ui"
	3	[124]	SELF     	0 0 -2	; "toggleHiddenFiles"
	4	[124]	CALL     	0 2 1
	5	[124]	RETURN   	0 1

function <./frontend/apps/filemanager/filemanagermenu.lua:128,128> (6 instructions, 24 bytes at 0x7f971ac09c00)
0 params, 2 slots, 1 upvalue, 0 locals, 3 constants, 0 functions
	1	[128]	GETUPVAL 	0 0	; self
	2	[128]	GETTABLE 	0 0 -1	; "ui"
	3	[128]	GETTABLE 	0 0 -2	; "file_chooser"
	4	[128]	GETTABLE 	0 0 -3	; "show_unsupported"
	5	[128]	RETURN   	0 2
	6	[128]	RETURN   	0 1

function <./frontend/apps/filemanager/filemanagermenu.lua:129,129> (5 instructions, 20 bytes at 0x7f971ac0a540)
0 params, 2 slots, 1 upvalue, 0 locals, 2 constants, 0 functions
	1	[129]	GETUPVAL 	0 0	; self
	2	[129]	GETTABLE 	0 0 -1	; "ui"
	3	[129]	SELF     	0 0 -2	; "toggleUnsupportedFiles"
	4	[129]	CALL     	0 2 1
	5	[129]	RETURN   	0 1

function <./frontend/apps/filemanager/filemanagermenu.lua:142,158> (34 instructions, 136 bytes at 0x7f971ac0ace0)
0 params, 7 slots, 4 upvalues, 3 locals, 21 constants, 1 function
	1	[143]	GETGLOBAL	0 -1	; require
	2	[143]	LOADK    	1 -2	; "ui/widget/spinwidget"
	3	[143]	CALL     	0 2 2
	4	[144]	GETGLOBAL	1 -3	; G_reader_settings
	5	[144]	SELF     	1 1 -4	; "readSetting"
	6	[144]	LOADK    	3 -5	; "items_per_page"
	7	[144]	CALL     	1 3 2
	8	[144]	TEST     	1 0 1
	9	[144]	JMP      	1	; to 11
	10	[144]	LOADK    	1 -6	; 14
	11	[145]	SELF     	2 0 -7	; "new"
	12	[145]	NEWTABLE 	4 0 7
	13	[146]	GETUPVAL 	5 0	; Screen
	14	[146]	SELF     	5 5 -9	; "getWidth"
	15	[146]	CALL     	5 2 2
	16	[146]	MUL      	5 5 -10	; - 0.6
	17	[146]	SETTABLE 	4 -8 5	; "width" -
	18	[147]	SETTABLE 	4 -11 1	; "value" -
	19	[148]	SETTABLE 	4 -12 -13	; "value_min" 6
	20	[149]	SETTABLE 	4 -14 -15	; "value_max" 24
	21	[150]	GETUPVAL 	5 1	; _
	22	[150]	LOADK    	6 -17	; "Items per page"
	23	[150]	CALL     	5 2 2
	24	[150]	SETTABLE 	4 -16 5	; "title_text" -
	25	[151]	SETTABLE 	4 -18 -19	; "keep_shown_on_apply" true
	26	[155]	CLOSURE  	5 0	; 0x7f971ac0af50
	27	[155]	GETUPVAL 	0 2	; self
	28	[155]	SETTABLE 	4 -20 5	; "callback" -
	29	[145]	CALL     	2 3 2
	30	[157]	GETUPVAL 	3 3	; UIManager
	31	[157]	SELF     	3 3 -21	; "show"
	32	[157]	MOVE     	5 2
	33	[157]	CALL     	3 3 1
	34	[158]	RETURN   	0 1

function <./frontend/apps/filemanager/filemanagermenu.lua:152,155> (10 instructions, 40 bytes at 0x7f971ac0af50)
1 param, 5 slots, 1 upvalue, 1 local, 6 constants, 0 functions
	1	[153]	GETGLOBAL	1 -1	; G_reader_settings
	2	[153]	SELF     	1 1 -2	; "saveSetting"
	3	[153]	LOADK    	3 -3	; "items_per_page"
	4	[153]	GETTABLE 	4 0 -4	; "value"
	5	[153]	CALL     	1 4 1
	6	[154]	GETUPVAL 	1 0	; self
	7	[154]	GETTABLE 	1 1 -5	; "ui"
	8	[154]	SELF     	1 1 -6	; "onRefresh"
	9	[154]	CALL     	1 2 1
	10	[155]	RETURN   	0 1

function <./frontend/apps/filemanager/filemanagermenu.lua:163,182> (49 instructions, 196 bytes at 0x7f971ac0b360)
0 params, 9 slots, 4 upvalues, 5 locals, 28 constants, 1 function
	1	[164]	GETGLOBAL	0 -1	; require
	2	[164]	LOADK    	1 -2	; "ui/widget/spinwidget"
	3	[164]	CALL     	0 2 2
	4	[165]	GETGLOBAL	1 -3	; G_reader_settings
	5	[165]	SELF     	1 1 -4	; "readSetting"
	6	[165]	LOADK    	3 -5	; "items_per_page"
	7	[165]	CALL     	1 3 2
	8	[165]	TEST     	1 0 1
	9	[165]	JMP      	1	; to 11
	10	[165]	LOADK    	1 -6	; 14
	11	[166]	GETGLOBAL	2 -7	; math
	12	[166]	GETTABLE 	2 2 -8	; "floor"
	13	[166]	SUB      	3 1 -9	; - 6
	14	[166]	DIV      	3 3 -10	; - 18
	15	[166]	MUL      	3 3 -11	; - 10
	16	[166]	SUB      	3 -12 3	; 24 -
	17	[166]	CALL     	2 2 2
	18	[167]	GETGLOBAL	3 -3	; G_reader_settings
	19	[167]	SELF     	3 3 -4	; "readSetting"
	20	[167]	LOADK    	5 -13	; "items_font_size"
	21	[167]	CALL     	3 3 2
	22	[167]	TEST     	3 0 1
	23	[167]	JMP      	1	; to 25
	24	[167]	MOVE     	3 2
	25	[168]	SELF     	4 0 -14	; "new"
	26	[168]	NEWTABLE 	6 0 8
	27	[169]	GETUPVAL 	7 0	; Screen
	28	[169]	SELF     	7 7 -16	; "getWidth"
	29	[169]	CALL     	7 2 2
	30	[169]	MUL      	7 7 -17	; - 0.6
	31	[169]	SETTABLE 	6 -15 7	; "width" -
	32	[170]	SETTABLE 	6 -18 3	; "value" -
	33	[171]	SETTABLE 	6 -19 -11	; "value_min" 10
	34	[172]	SETTABLE 	6 -20 -21	; "value_max" 72
	35	[173]	SETTABLE 	6 -22 2	; "default_value" -
	36	[174]	SETTABLE 	6 -23 -24	; "keep_shown_on_apply" true
	37	[175]	GETUPVAL 	7 1	; _
	38	[175]	LOADK    	8 -26	; "Maximum font size for item"
	39	[175]	CALL     	7 2 2
	40	[175]	SETTABLE 	6 -25 7	; "title_text" -
	41	[179]	CLOSURE  	7 0	; 0x7f971ac0bf10
	42	[179]	GETUPVAL 	0 2	; self
	43	[179]	SETTABLE 	6 -27 7	; "callback" -
	44	[168]	CALL     	4 3 2
	45	[181]	GETUPVAL 	5 3	; UIManager
	46	[181]	SELF     	5 5 -28	; "show"
	47	[181]	MOVE     	7 4
	48	[181]	CALL     	5 3 1
	49	[182]	RETURN   	0 1

function <./frontend/apps/filemanager/filemanagermenu.lua:176,179> (10 instructions, 40 bytes at 0x7f971ac0bf10)
1 param, 5 slots, 1 upvalue, 1 local, 6 constants, 0 functions
	1	[177]	GETGLOBAL	1 -1	; G_reader_settings
	2	[177]	SELF     	1 1 -2	; "saveSetting"
	3	[177]	LOADK    	3 -3	; "items_font_size"
	4	[177]	GETTABLE 	4 0 -4	; "value"
	5	[177]	CALL     	1 4 1
	6	[178]	GETUPVAL 	1 0	; self
	7	[178]	GETTABLE 	1 1 -5	; "ui"
	8	[178]	SELF     	1 1 -6	; "onRefresh"
	9	[178]	CALL     	1 2 1
	10	[179]	RETURN   	0 1

function <./frontend/apps/filemanager/filemanagermenu.lua:187,189> (6 instructions, 24 bytes at 0x7f971ac0c450)
0 params, 3 slots, 0 upvalues, 0 locals, 3 constants, 0 functions
	1	[188]	GETGLOBAL	0 -1	; G_reader_settings
	2	[188]	SELF     	0 0 -2	; "isTrue"
	3	[188]	LOADK    	2 -3	; "items_multilines_show_more_text"
	4	[188]	TAILCALL 	0 3 0
	5	[188]	RETURN   	0 0
	6	[189]	RETURN   	0 1

function <./frontend/apps/filemanager/filemanagermenu.lua:190,192> (5 instructions, 20 bytes at 0x7f971ac0c870)
0 params, 3 slots, 0 upvalues, 0 locals, 3 constants, 0 functions
	1	[191]	GETGLOBAL	0 -1	; G_reader_settings
	2	[191]	SELF     	0 0 -2	; "flipNilOrFalse"
	3	[191]	LOADK    	2 -3	; "items_multilines_show_more_text"
	4	[191]	CALL     	0 3 1
	5	[192]	RETURN   	0 1

function <./frontend/apps/filemanager/filemanagermenu.lua:199,199> (6 instructions, 24 bytes at 0x7f971ac0cc50)
0 params, 2 slots, 1 upvalue, 0 locals, 3 constants, 0 functions
	1	[199]	GETUPVAL 	0 0	; self
	2	[199]	GETTABLE 	0 0 -1	; "ui"
	3	[199]	GETTABLE 	0 0 -2	; "file_chooser"
	4	[199]	GETTABLE 	0 0 -3	; "reverse_collate"
	5	[199]	RETURN   	0 2
	6	[199]	RETURN   	0 1

function <./frontend/apps/filemanager/filemanagermenu.lua:200,200> (5 instructions, 20 bytes at 0x7f971ac0cfd0)
0 params, 2 slots, 1 upvalue, 0 locals, 2 constants, 0 functions
	1	[200]	GETUPVAL 	0 0	; self
	2	[200]	GETTABLE 	0 0 -1	; "ui"
	3	[200]	SELF     	0 0 -2	; "toggleReverseCollate"
	4	[200]	CALL     	0 2 1
	5	[200]	RETURN   	0 1

function <./frontend/apps/filemanager/filemanagermenu.lua:217,219> (4 instructions, 16 bytes at 0x7f971ac09b00)
0 params, 2 slots, 1 upvalue, 0 locals, 1 constant, 0 functions
	1	[218]	GETUPVAL 	0 0	; SetDefaults
	2	[218]	SELF     	0 0 -1	; "ConfirmEdit"
	3	[218]	CALL     	0 2 1
	4	[219]	RETURN   	0 1

function <./frontend/apps/filemanager/filemanagermenu.lua:220,222> (4 instructions, 16 bytes at 0x7f971ac0b050)
0 params, 2 slots, 1 upvalue, 0 locals, 1 constant, 0 functions
	1	[221]	GETUPVAL 	0 0	; SetDefaults
	2	[221]	SELF     	0 0 -1	; "ConfirmSave"
	3	[221]	CALL     	0 2 1
	4	[222]	RETURN   	0 1

function <./frontend/apps/filemanager/filemanagermenu.lua:231,239> (12 instructions, 48 bytes at 0x7f971ac0d0e0)
0 params, 4 slots, 2 upvalues, 2 locals, 4 constants, 2 functions
	1	[232]	GETGLOBAL	0 -1	; require
	2	[232]	LOADK    	1 -2	; "apps/opdscatalog/opdscatalog"
	3	[232]	CALL     	0 2 2
	4	[233]	CLOSURE  	1 0	; 0x7f971ac0a020
	5	[233]	GETUPVAL 	0 0	; self
	6	[237]	CLOSURE  	2 1	; 0x7f971ac087a0
	7	[237]	MOVE     	0 1
	8	[237]	GETUPVAL 	0 1	; UIManager
	9	[234]	SETTABLE 	0 -3 2	; "onClose" -
	10	[238]	SELF     	2 0 -4	; "showCatalog"
	11	[238]	CALL     	2 2 1
	12	[239]	RETURN   	0 1

function <./frontend/apps/filemanager/filemanagermenu.lua:233,233> (5 instructions, 20 bytes at 0x7f971ac0a020)
0 params, 2 slots, 1 upvalue, 0 locals, 2 constants, 0 functions
	1	[233]	GETUPVAL 	0 0	; self
	2	[233]	GETTABLE 	0 0 -1	; "ui"
	3	[233]	SELF     	0 0 -2	; "onRefresh"
	4	[233]	CALL     	0 2 1
	5	[233]	RETURN   	0 1

function <./frontend/apps/filemanager/filemanagermenu.lua:234,237> (7 instructions, 28 bytes at 0x7f971ac087a0)
1 param, 4 slots, 2 upvalues, 1 local, 1 constant, 0 functions
	1	[235]	GETUPVAL 	1 0	; filemanagerRefresh
	2	[235]	CALL     	1 1 1
	3	[236]	GETUPVAL 	1 1	; UIManager
	4	[236]	SELF     	1 1 -1	; "close"
	5	[236]	MOVE     	3 0
	6	[236]	CALL     	1 3 1
	7	[237]	RETURN   	0 1

function <./frontend/apps/filemanager/filemanagermenu.lua:246,267> (17 instructions, 68 bytes at 0x7f971ac0ce90)
0 params, 7 slots, 4 upvalues, 0 locals, 5 constants, 1 function
	1	[247]	GETUPVAL 	0 0	; UIManager
	2	[247]	SELF     	0 0 -1	; "show"
	3	[247]	GETUPVAL 	2 1	; ConfirmBox
	4	[247]	SELF     	2 2 -2	; "new"
	5	[247]	NEWTABLE 	4 0 2
	6	[248]	GETUPVAL 	5 2	; _
	7	[248]	LOADK    	6 -4	; "Clear cache/ and cr3cache/ ?"
	8	[248]	CALL     	5 2 2
	9	[248]	SETTABLE 	4 -3 5	; "text" -
	10	[265]	CLOSURE  	5 0	; 0x7f971ac0c7e0
	11	[265]	GETUPVAL 	0 3	; lfs
	12	[265]	GETUPVAL 	0 0	; UIManager
	13	[265]	GETUPVAL 	0 2	; _
	14	[265]	SETTABLE 	4 -5 5	; "ok_callback" -
	15	[247]	CALL     	2 3 0
	16	[247]	CALL     	0 0 1
	17	[267]	RETURN   	0 1

function <./frontend/apps/filemanager/filemanagermenu.lua:249,265> (44 instructions, 176 bytes at 0x7f971ac0c7e0)
0 params, 12 slots, 3 upvalues, 5 locals, 17 constants, 0 functions
	1	[250]	GETGLOBAL	0 -1	; require
	2	[250]	LOADK    	1 -2	; "ffi/util"
	3	[250]	CALL     	0 2 2
	4	[250]	GETTABLE 	0 0 -3	; "purgeDir"
	5	[251]	GETGLOBAL	1 -1	; require
	6	[251]	LOADK    	2 -4	; "datastorage"
	7	[251]	CALL     	1 2 2
	8	[252]	SELF     	2 1 -5	; "getDataDir"
	9	[252]	CALL     	2 2 2
	10	[252]	LOADK    	3 -6	; "/cache"
	11	[252]	CONCAT   	2 2 3
	12	[253]	GETUPVAL 	3 0	; lfs
	13	[253]	GETTABLE 	3 3 -7	; "attributes"
	14	[253]	MOVE     	4 2
	15	[253]	LOADK    	5 -8	; "mode"
	16	[253]	CALL     	3 3 2
	17	[253]	EQ       	0 3 -9	; - "directory"
	18	[253]	JMP      	3	; to 22
	19	[254]	MOVE     	3 0
	20	[254]	MOVE     	4 2
	21	[254]	CALL     	3 2 1
	22	[256]	GETUPVAL 	3 0	; lfs
	23	[256]	GETTABLE 	3 3 -10	; "mkdir"
	24	[256]	MOVE     	4 2
	25	[256]	CALL     	3 2 1
	26	[259]	GETGLOBAL	3 -1	; require
	27	[259]	LOADK    	4 -11	; "cache"
	28	[259]	CALL     	3 2 2
	29	[260]	NEWTABLE 	4 0 0
	30	[260]	SETTABLE 	3 -12 4	; "cached" -
	31	[261]	GETGLOBAL	4 -1	; require
	32	[261]	LOADK    	5 -13	; "ui/widget/infomessage"
	33	[261]	CALL     	4 2 2
	34	[262]	GETUPVAL 	5 1	; UIManager
	35	[262]	SELF     	5 5 -14	; "show"
	36	[262]	SELF     	7 4 -15	; "new"
	37	[262]	NEWTABLE 	9 0 1
	38	[263]	GETUPVAL 	10 2	; _
	39	[263]	LOADK    	11 -17	; "Caches cleared. Please exit and restart KOReader."
	40	[263]	CALL     	10 2 2
	41	[263]	SETTABLE 	9 -16 10	; "text" -
	42	[262]	CALL     	7 3 0
	43	[262]	CALL     	5 0 1
	44	[265]	RETURN   	0 1

function <./frontend/apps/filemanager/filemanagermenu.lua:271,273> (6 instructions, 24 bytes at 0x7f971ae041d0)
0 params, 3 slots, 0 upvalues, 0 locals, 3 constants, 0 functions
	1	[272]	GETGLOBAL	0 -1	; G_reader_settings
	2	[272]	SELF     	0 0 -2	; "isTrue"
	3	[272]	LOADK    	2 -3	; "debug"
	4	[272]	TAILCALL 	0 3 0
	5	[272]	RETURN   	0 0
	6	[273]	RETURN   	0 1

function <./frontend/apps/filemanager/filemanagermenu.lua:274,283> (26 instructions, 104 bytes at 0x7f971ae04350)
0 params, 3 slots, 1 upvalue, 0 locals, 9 constants, 0 functions
	1	[275]	GETGLOBAL	0 -1	; G_reader_settings
	2	[275]	SELF     	0 0 -2	; "flipNilOrFalse"
	3	[275]	LOADK    	2 -3	; "debug"
	4	[275]	CALL     	0 3 1
	5	[276]	GETGLOBAL	0 -1	; G_reader_settings
	6	[276]	SELF     	0 0 -4	; "isTrue"
	7	[276]	LOADK    	2 -3	; "debug"
	8	[276]	CALL     	0 3 2
	9	[276]	TEST     	0 0 0
	10	[276]	JMP      	4	; to 15
	11	[277]	GETUPVAL 	0 0	; dbg
	12	[277]	SELF     	0 0 -5	; "turnOn"
	13	[277]	CALL     	0 2 1
	14	[277]	JMP      	11	; to 26
	15	[279]	GETUPVAL 	0 0	; dbg
	16	[279]	SELF     	0 0 -6	; "setVerbose"
	17	[279]	LOADBOOL 	2 0 0
	18	[279]	CALL     	0 3 1
	19	[280]	GETUPVAL 	0 0	; dbg
	20	[280]	SELF     	0 0 -7	; "turnOff"
	21	[280]	CALL     	0 2 1
	22	[281]	GETGLOBAL	0 -1	; G_reader_settings
	23	[281]	SELF     	0 0 -8	; "flipFalse"
	24	[281]	LOADK    	2 -9	; "debug_verbose"
	25	[281]	CALL     	0 3 1
	26	[283]	RETURN   	0 1

function <./frontend/apps/filemanager/filemanagermenu.lua:287,289> (6 instructions, 24 bytes at 0x7f971ae04810)
0 params, 3 slots, 0 upvalues, 0 locals, 3 constants, 0 functions
	1	[288]	GETGLOBAL	0 -1	; G_reader_settings
	2	[288]	SELF     	0 0 -2	; "isTrue"
	3	[288]	LOADK    	2 -3	; "debug"
	4	[288]	TAILCALL 	0 3 0
	5	[288]	RETURN   	0 0
	6	[289]	RETURN   	0 1

function <./frontend/apps/filemanager/filemanagermenu.lua:290,292> (6 instructions, 24 bytes at 0x7f971ae04ca0)
0 params, 3 slots, 0 upvalues, 0 locals, 3 constants, 0 functions
	1	[291]	GETGLOBAL	0 -1	; G_reader_settings
	2	[291]	SELF     	0 0 -2	; "isTrue"
	3	[291]	LOADK    	2 -3	; "debug_verbose"
	4	[291]	TAILCALL 	0 3 0
	5	[291]	RETURN   	0 0
	6	[292]	RETURN   	0 1

function <./frontend/apps/filemanager/filemanagermenu.lua:293,300> (20 instructions, 80 bytes at 0x7f971ae05050)
0 params, 3 slots, 1 upvalue, 0 locals, 5 constants, 0 functions
	1	[294]	GETGLOBAL	0 -1	; G_reader_settings
	2	[294]	SELF     	0 0 -2	; "flipNilOrFalse"
	3	[294]	LOADK    	2 -3	; "debug_verbose"
	4	[294]	CALL     	0 3 1
	5	[295]	GETGLOBAL	0 -1	; G_reader_settings
	6	[295]	SELF     	0 0 -4	; "isTrue"
	7	[295]	LOADK    	2 -3	; "debug_verbose"
	8	[295]	CALL     	0 3 2
	9	[295]	TEST     	0 0 0
	10	[295]	JMP      	5	; to 16
	11	[296]	GETUPVAL 	0 0	; dbg
	12	[296]	SELF     	0 0 -5	; "setVerbose"
	13	[296]	LOADBOOL 	2 1 0
	14	[296]	CALL     	0 3 1
	15	[296]	JMP      	4	; to 20
	16	[298]	GETUPVAL 	0 0	; dbg
	17	[298]	SELF     	0 0 -5	; "setVerbose"
	18	[298]	LOADBOOL 	2 0 0
	19	[298]	CALL     	0 3 1
	20	[300]	RETURN   	0 1

function <./frontend/apps/filemanager/filemanagermenu.lua:307,309> (6 instructions, 24 bytes at 0x7f971ae05420)
0 params, 3 slots, 0 upvalues, 0 locals, 3 constants, 0 functions
	1	[308]	GETGLOBAL	0 -1	; G_reader_settings
	2	[308]	SELF     	0 0 -2	; "isTrue"
	3	[308]	LOADK    	2 -3	; "dev_startup_no_fbdepth"
	4	[308]	TAILCALL 	0 3 0
	5	[308]	RETURN   	0 0
	6	[309]	RETURN   	0 1

function <./frontend/apps/filemanager/filemanagermenu.lua:310,316> (18 instructions, 72 bytes at 0x7f971ae05860)
0 params, 8 slots, 2 upvalues, 1 local, 9 constants, 0 functions
	1	[311]	GETGLOBAL	0 -1	; G_reader_settings
	2	[311]	SELF     	0 0 -2	; "flipNilOrFalse"
	3	[311]	LOADK    	2 -3	; "dev_startup_no_fbdepth"
	4	[311]	CALL     	0 3 1
	5	[312]	GETGLOBAL	0 -4	; require
	6	[312]	LOADK    	1 -5	; "ui/widget/infomessage"
	7	[312]	CALL     	0 2 2
	8	[313]	GETUPVAL 	1 0	; UIManager
	9	[313]	SELF     	1 1 -6	; "show"
	10	[313]	SELF     	3 0 -7	; "new"
	11	[313]	NEWTABLE 	5 0 1
	12	[314]	GETUPVAL 	6 1	; _
	13	[314]	LOADK    	7 -9	; "This will take effect on next restart."
	14	[314]	CALL     	6 2 2
	15	[314]	SETTABLE 	5 -8 6	; "text" -
	16	[313]	CALL     	3 3 0
	17	[313]	CALL     	1 0 1
	18	[316]	RETURN   	0 1

function <./frontend/apps/filemanager/filemanagermenu.lua:323,325> (6 instructions, 24 bytes at 0x7f971ae06070)
0 params, 3 slots, 0 upvalues, 0 locals, 3 constants, 0 functions
	1	[324]	GETGLOBAL	0 -1	; G_reader_settings
	2	[324]	SELF     	0 0 -2	; "isTrue"
	3	[324]	LOADK    	2 -3	; "dev_abort_on_crash"
	4	[324]	TAILCALL 	0 3 0
	5	[324]	RETURN   	0 0
	6	[325]	RETURN   	0 1

function <./frontend/apps/filemanager/filemanagermenu.lua:326,332> (18 instructions, 72 bytes at 0x7f971ae060f0)
0 params, 8 slots, 2 upvalues, 1 local, 9 constants, 0 functions
	1	[327]	GETGLOBAL	0 -1	; G_reader_settings
	2	[327]	SELF     	0 0 -2	; "flipNilOrFalse"
	3	[327]	LOADK    	2 -3	; "dev_abort_on_crash"
	4	[327]	CALL     	0 3 1
	5	[328]	GETGLOBAL	0 -4	; require
	6	[328]	LOADK    	1 -5	; "ui/widget/infomessage"
	7	[328]	CALL     	0 2 2
	8	[329]	GETUPVAL 	1 0	; UIManager
	9	[329]	SELF     	1 1 -6	; "show"
	10	[329]	SELF     	3 0 -7	; "new"
	11	[329]	NEWTABLE 	5 0 1
	12	[330]	GETUPVAL 	6 1	; _
	13	[330]	LOADK    	7 -9	; "This will take effect on next restart."
	14	[330]	CALL     	6 2 2
	15	[330]	SETTABLE 	5 -8 6	; "text" -
	16	[329]	CALL     	3 3 0
	17	[329]	CALL     	1 0 1
	18	[332]	RETURN   	0 1

function <./frontend/apps/filemanager/filemanagermenu.lua:338,340> (11 instructions, 44 bytes at 0x7f971ae06880)
0 params, 3 slots, 1 upvalue, 0 locals, 4 constants, 0 functions
	1	[339]	GETUPVAL 	0 0	; lfs
	2	[339]	GETTABLE 	0 0 -1	; "attributes"
	3	[339]	LOADK    	1 -2	; "libs/libblitbuffer.so"
	4	[339]	LOADK    	2 -3	; "mode"
	5	[339]	CALL     	0 3 2
	6	[339]	EQ       	1 0 -4	; - "file"
	7	[339]	JMP      	1	; to 9
	8	[339]	LOADBOOL 	0 0 1
	9	[339]	LOADBOOL 	0 1 0
	10	[339]	RETURN   	0 2
	11	[340]	RETURN   	0 1

function <./frontend/apps/filemanager/filemanagermenu.lua:341,343> (6 instructions, 24 bytes at 0x7f971ae06b70)
0 params, 3 slots, 0 upvalues, 0 locals, 3 constants, 0 functions
	1	[342]	GETGLOBAL	0 -1	; G_reader_settings
	2	[342]	SELF     	0 0 -2	; "isTrue"
	3	[342]	LOADK    	2 -3	; "dev_no_c_blitter"
	4	[342]	TAILCALL 	0 3 0
	5	[342]	RETURN   	0 0
	6	[343]	RETURN   	0 1

function <./frontend/apps/filemanager/filemanagermenu.lua:344,350> (18 instructions, 72 bytes at 0x7f971ae06c70)
0 params, 8 slots, 2 upvalues, 1 local, 9 constants, 0 functions
	1	[345]	GETGLOBAL	0 -1	; G_reader_settings
	2	[345]	SELF     	0 0 -2	; "flipNilOrFalse"
	3	[345]	LOADK    	2 -3	; "dev_no_c_blitter"
	4	[345]	CALL     	0 3 1
	5	[346]	GETGLOBAL	0 -4	; require
	6	[346]	LOADK    	1 -5	; "ui/widget/infomessage"
	7	[346]	CALL     	0 2 2
	8	[347]	GETUPVAL 	1 0	; UIManager
	9	[347]	SELF     	1 1 -6	; "show"
	10	[347]	SELF     	3 0 -7	; "new"
	11	[347]	NEWTABLE 	5 0 1
	12	[348]	GETUPVAL 	6 1	; _
	13	[348]	LOADK    	7 -9	; "This will take effect on next restart."
	14	[348]	CALL     	6 2 2
	15	[348]	SETTABLE 	5 -8 6	; "text" -
	16	[347]	CALL     	3 3 0
	17	[347]	CALL     	1 0 1
	18	[350]	RETURN   	0 1

function <./frontend/apps/filemanager/filemanagermenu.lua:356,358> (6 instructions, 24 bytes at 0x7f971ae07430)
0 params, 2 slots, 1 upvalue, 0 locals, 2 constants, 0 functions
	1	[357]	GETUPVAL 	0 0	; Device
	2	[357]	GETTABLE 	0 0 -1	; "screen"
	3	[357]	GETTABLE 	0 0 -2	; "hw_dithering"
	4	[357]	NOT      	0 0
	5	[357]	RETURN   	0 2
	6	[358]	RETURN   	0 1

function <./frontend/apps/filemanager/filemanagermenu.lua:359,367> (28 instructions, 112 bytes at 0x7f971ae07520)
0 params, 4 slots, 2 upvalues, 0 locals, 11 constants, 0 functions
	1	[360]	GETGLOBAL	0 -1	; G_reader_settings
	2	[360]	SELF     	0 0 -2	; "flipNilOrFalse"
	3	[360]	LOADK    	2 -3	; "dev_no_hw_dither"
	4	[360]	CALL     	0 3 1
	5	[361]	GETUPVAL 	0 0	; Device
	6	[361]	GETTABLE 	0 0 -4	; "screen"
	7	[361]	SELF     	0 0 -5	; "toggleHWDithering"
	8	[361]	CALL     	0 2 1
	9	[363]	GETUPVAL 	0 0	; Device
	10	[363]	GETTABLE 	0 0 -4	; "screen"
	11	[363]	GETTABLE 	0 0 -6	; "hw_dithering"
	12	[363]	TEST     	0 0 0
	13	[363]	JMP      	9	; to 23
	14	[363]	GETUPVAL 	0 0	; Device
	15	[363]	GETTABLE 	0 0 -4	; "screen"
	16	[363]	GETTABLE 	0 0 -7	; "sw_dithering"
	17	[363]	TEST     	0 0 0
	18	[363]	JMP      	4	; to 23
	19	[364]	GETUPVAL 	0 0	; Device
	20	[364]	GETTABLE 	0 0 -4	; "screen"
	21	[364]	SELF     	0 0 -8	; "toggleSWDithering"
	22	[364]	CALL     	0 2 1
	23	[366]	GETUPVAL 	0 1	; UIManager
	24	[366]	SELF     	0 0 -9	; "setDirty"
	25	[366]	LOADK    	2 -10	; "all"
	26	[366]	LOADK    	3 -11	; "full"
	27	[366]	CALL     	0 4 1
	28	[367]	RETURN   	0 1

function <./frontend/apps/filemanager/filemanagermenu.lua:373,375> (9 instructions, 36 bytes at 0x7f971ae07a20)
0 params, 2 slots, 1 upvalue, 0 locals, 3 constants, 0 functions
	1	[374]	GETUPVAL 	0 0	; Device
	2	[374]	GETTABLE 	0 0 -1	; "screen"
	3	[374]	GETTABLE 	0 0 -2	; "fb_bpp"
	4	[374]	EQ       	1 0 -3	; - 8
	5	[374]	JMP      	1	; to 7
	6	[374]	LOADBOOL 	0 0 1
	7	[374]	LOADBOOL 	0 1 0
	8	[374]	RETURN   	0 2
	9	[375]	RETURN   	0 1

function <./frontend/apps/filemanager/filemanagermenu.lua:376,378> (6 instructions, 24 bytes at 0x7f971ae07c00)
0 params, 2 slots, 1 upvalue, 0 locals, 2 constants, 0 functions
	1	[377]	GETUPVAL 	0 0	; Device
	2	[377]	GETTABLE 	0 0 -1	; "screen"
	3	[377]	GETTABLE 	0 0 -2	; "sw_dithering"
	4	[377]	NOT      	0 0
	5	[377]	RETURN   	0 2
	6	[378]	RETURN   	0 1

function <./frontend/apps/filemanager/filemanagermenu.lua:379,387> (28 instructions, 112 bytes at 0x7f971ae07f60)
0 params, 4 slots, 2 upvalues, 0 locals, 11 constants, 0 functions
	1	[380]	GETGLOBAL	0 -1	; G_reader_settings
	2	[380]	SELF     	0 0 -2	; "flipNilOrFalse"
	3	[380]	LOADK    	2 -3	; "dev_no_sw_dither"
	4	[380]	CALL     	0 3 1
	5	[381]	GETUPVAL 	0 0	; Device
	6	[381]	GETTABLE 	0 0 -4	; "screen"
	7	[381]	SELF     	0 0 -5	; "toggleSWDithering"
	8	[381]	CALL     	0 2 1
	9	[383]	GETUPVAL 	0 0	; Device
	10	[383]	GETTABLE 	0 0 -4	; "screen"
	11	[383]	GETTABLE 	0 0 -6	; "hw_dithering"
	12	[383]	TEST     	0 0 0
	13	[383]	JMP      	9	; to 23
	14	[383]	GETUPVAL 	0 0	; Device
	15	[383]	GETTABLE 	0 0 -4	; "screen"
	16	[383]	GETTABLE 	0 0 -7	; "sw_dithering"
	17	[383]	TEST     	0 0 0
	18	[383]	JMP      	4	; to 23
	19	[384]	GETUPVAL 	0 0	; Device
	20	[384]	GETTABLE 	0 0 -4	; "screen"
	21	[384]	SELF     	0 0 -8	; "toggleHWDithering"
	22	[384]	CALL     	0 2 1
	23	[386]	GETUPVAL 	0 1	; UIManager
	24	[386]	SELF     	0 0 -9	; "setDirty"
	25	[386]	LOADK    	2 -10	; "all"
	26	[386]	LOADK    	3 -11	; "full"
	27	[386]	CALL     	0 4 1
	28	[387]	RETURN   	0 1

function <./frontend/apps/filemanager/filemanagermenu.lua:393,395> (4 instructions, 16 bytes at 0x7f971ae083e0)
0 params, 2 slots, 1 upvalue, 0 locals, 1 constant, 0 functions
	1	[394]	GETUPVAL 	0 0	; Device
	2	[394]	SELF     	0 0 -1	; "epdTest"
	3	[394]	CALL     	0 2 1
	4	[395]	RETURN   	0 1

function <./frontend/apps/filemanager/filemanagermenu.lua:401,403> (6 instructions, 24 bytes at 0x7f971ae08540)
0 params, 3 slots, 0 upvalues, 0 locals, 3 constants, 0 functions
	1	[402]	GETGLOBAL	0 -1	; G_reader_settings
	2	[402]	SELF     	0 0 -2	; "isFalse"
	3	[402]	LOADK    	2 -3	; "use_xtext"
	4	[402]	TAILCALL 	0 3 0
	5	[402]	RETURN   	0 0
	6	[403]	RETURN   	0 1

function <./frontend/apps/filemanager/filemanagermenu.lua:404,410> (18 instructions, 72 bytes at 0x7f971ae087e0)
0 params, 8 slots, 2 upvalues, 1 local, 9 constants, 0 functions
	1	[405]	GETGLOBAL	0 -1	; G_reader_settings
	2	[405]	SELF     	0 0 -2	; "flipNilOrTrue"
	3	[405]	LOADK    	2 -3	; "use_xtext"
	4	[405]	CALL     	0 3 1
	5	[406]	GETGLOBAL	0 -4	; require
	6	[406]	LOADK    	1 -5	; "ui/widget/infomessage"
	7	[406]	CALL     	0 2 2
	8	[407]	GETUPVAL 	1 0	; UIManager
	9	[407]	SELF     	1 1 -6	; "show"
	10	[407]	SELF     	3 0 -7	; "new"
	11	[407]	NEWTABLE 	5 0 1
	12	[408]	GETUPVAL 	6 1	; _
	13	[408]	LOADK    	7 -9	; "This will take effect on next restart."
	14	[408]	CALL     	6 2 2
	15	[408]	SETTABLE 	5 -8 6	; "text" -
	16	[407]	CALL     	3 3 0
	17	[407]	CALL     	1 0 1
	18	[410]	RETURN   	0 1

function <./frontend/apps/filemanager/filemanagermenu.lua:417,419> (6 instructions, 24 bytes at 0x7f971ae090a0)
0 params, 3 slots, 0 upvalues, 0 locals, 3 constants, 0 functions
	1	[418]	GETGLOBAL	0 -1	; G_reader_settings
	2	[418]	SELF     	0 0 -2	; "isTrue"
	3	[418]	LOADK    	2 -3	; "dev_reverse_ui_layout_mirroring"
	4	[418]	TAILCALL 	0 3 0
	5	[418]	RETURN   	0 0
	6	[419]	RETURN   	0 1

function <./frontend/apps/filemanager/filemanagermenu.lua:420,426> (18 instructions, 72 bytes at 0x7f971ae091b0)
0 params, 8 slots, 2 upvalues, 1 local, 9 constants, 0 functions
	1	[421]	GETGLOBAL	0 -1	; G_reader_settings
	2	[421]	SELF     	0 0 -2	; "flipNilOrFalse"
	3	[421]	LOADK    	2 -3	; "dev_reverse_ui_layout_mirroring"
	4	[421]	CALL     	0 3 1
	5	[422]	GETGLOBAL	0 -4	; require
	6	[422]	LOADK    	1 -5	; "ui/widget/infomessage"
	7	[422]	CALL     	0 2 2
	8	[423]	GETUPVAL 	1 0	; UIManager
	9	[423]	SELF     	1 1 -6	; "show"
	10	[423]	SELF     	3 0 -7	; "new"
	11	[423]	NEWTABLE 	5 0 1
	12	[424]	GETUPVAL 	6 1	; _
	13	[424]	LOADK    	7 -9	; "This will take effect on next restart."
	14	[424]	CALL     	6 2 2
	15	[424]	SETTABLE 	5 -8 6	; "text" -
	16	[423]	CALL     	3 3 0
	17	[423]	CALL     	1 0 1
	18	[426]	RETURN   	0 1

function <./frontend/apps/filemanager/filemanagermenu.lua:430,432> (6 instructions, 24 bytes at 0x7f971ae09940)
0 params, 3 slots, 0 upvalues, 0 locals, 3 constants, 0 functions
	1	[431]	GETGLOBAL	0 -1	; G_reader_settings
	2	[431]	SELF     	0 0 -2	; "isTrue"
	3	[431]	LOADK    	2 -3	; "dev_reverse_ui_text_direction"
	4	[431]	TAILCALL 	0 3 0
	5	[431]	RETURN   	0 0
	6	[432]	RETURN   	0 1

function <./frontend/apps/filemanager/filemanagermenu.lua:433,439> (18 instructions, 72 bytes at 0x7f971ae09a50)
0 params, 8 slots, 2 upvalues, 1 local, 9 constants, 0 functions
	1	[434]	GETGLOBAL	0 -1	; G_reader_settings
	2	[434]	SELF     	0 0 -2	; "flipNilOrFalse"
	3	[434]	LOADK    	2 -3	; "dev_reverse_ui_text_direction"
	4	[434]	CALL     	0 3 1
	5	[435]	GETGLOBAL	0 -4	; require
	6	[435]	LOADK    	1 -5	; "ui/widget/infomessage"
	7	[435]	CALL     	0 2 2
	8	[436]	GETUPVAL 	1 0	; UIManager
	9	[436]	SELF     	1 1 -6	; "show"
	10	[436]	SELF     	3 0 -7	; "new"
	11	[436]	NEWTABLE 	5 0 1
	12	[437]	GETUPVAL 	6 1	; _
	13	[437]	LOADK    	7 -9	; "This will take effect on next restart."
	14	[437]	CALL     	6 2 2
	15	[437]	SETTABLE 	5 -8 6	; "text" -
	16	[436]	CALL     	3 3 0
	17	[436]	CALL     	1 0 1
	18	[439]	RETURN   	0 1

function <./frontend/apps/filemanager/filemanagermenu.lua:444,450> (21 instructions, 84 bytes at 0x7f971ae0a1e0)
0 params, 3 slots, 1 upvalue, 0 locals, 7 constants, 0 functions
	1	[445]	GETGLOBAL	0 -1	; G_reader_settings
	2	[445]	SELF     	0 0 -2	; "nilOrTrue"
	3	[445]	LOADK    	2 -3	; "use_cre_call_cache"
	4	[445]	CALL     	0 3 2
	5	[446]	TEST     	0 0 0
	6	[446]	JMP      	10	; to 17
	7	[446]	GETGLOBAL	0 -1	; G_reader_settings
	8	[446]	SELF     	0 0 -4	; "isTrue"
	9	[446]	LOADK    	2 -5	; "use_cre_call_cache_log_stats"
	10	[446]	CALL     	0 3 2
	11	[446]	TEST     	0 0 0
	12	[446]	JMP      	4	; to 17
	13	[447]	GETUPVAL 	0 0	; _
	14	[447]	LOADK    	1 -6	; "Enable CRE call cache (with stats)"
	15	[447]	TAILCALL 	0 2 0
	16	[447]	RETURN   	0 0
	17	[449]	GETUPVAL 	0 0	; _
	18	[449]	LOADK    	1 -7	; "Enable CRE call cache"
	19	[449]	TAILCALL 	0 2 0
	20	[449]	RETURN   	0 0
	21	[450]	RETURN   	0 1

function <./frontend/apps/filemanager/filemanagermenu.lua:451,453> (6 instructions, 24 bytes at 0x7f971ae0a780)
0 params, 3 slots, 0 upvalues, 0 locals, 3 constants, 0 functions
	1	[452]	GETGLOBAL	0 -1	; G_reader_settings
	2	[452]	SELF     	0 0 -2	; "nilOrTrue"
	3	[452]	LOADK    	2 -3	; "use_cre_call_cache"
	4	[452]	TAILCALL 	0 3 0
	5	[452]	RETURN   	0 0
	6	[453]	RETURN   	0 1

function <./frontend/apps/filemanager/filemanagermenu.lua:454,458> (5 instructions, 20 bytes at 0x7f971ae0a8c0)
0 params, 3 slots, 0 upvalues, 0 locals, 3 constants, 0 functions
	1	[455]	GETGLOBAL	0 -1	; G_reader_settings
	2	[455]	SELF     	0 0 -2	; "flipNilOrTrue"
	3	[455]	LOADK    	2 -3	; "use_cre_call_cache"
	4	[455]	CALL     	0 3 1
	5	[458]	RETURN   	0 1

function <./frontend/apps/filemanager/filemanagermenu.lua:459,462> (7 instructions, 28 bytes at 0x7f971ae0ac00)
1 param, 4 slots, 0 upvalues, 1 local, 4 constants, 0 functions
	1	[460]	GETGLOBAL	1 -1	; G_reader_settings
	2	[460]	SELF     	1 1 -2	; "flipNilOrFalse"
	3	[460]	LOADK    	3 -3	; "use_cre_call_cache_log_stats"
	4	[460]	CALL     	1 3 1
	5	[461]	SELF     	1 0 -4	; "updateItems"
	6	[461]	CALL     	1 2 1
	7	[462]	RETURN   	0 1

function <./frontend/apps/filemanager/filemanagermenu.lua:467,475> (16 instructions, 64 bytes at 0x7f971ae0af60)
0 params, 4 slots, 3 upvalues, 2 locals, 3 constants, 2 functions
	1	[468]	GETUPVAL 	0 0	; CloudStorage
	2	[468]	SELF     	0 0 -1	; "new"
	3	[468]	NEWTABLE 	2 0 0
	4	[468]	CALL     	0 3 2
	5	[469]	GETUPVAL 	1 1	; UIManager
	6	[469]	SELF     	1 1 -2	; "show"
	7	[469]	MOVE     	3 0
	8	[469]	CALL     	1 3 1
	9	[470]	CLOSURE  	1 0	; 0x7f971ae0b070
	10	[470]	GETUPVAL 	0 2	; self
	11	[474]	CLOSURE  	2 1	; 0x7f971ae0b150
	12	[474]	MOVE     	0 1
	13	[474]	GETUPVAL 	0 1	; UIManager
	14	[474]	MOVE     	0 0
	15	[471]	SETTABLE 	0 -3 2	; "onClose" -
	16	[475]	RETURN   	0 1

function <./frontend/apps/filemanager/filemanagermenu.lua:470,470> (5 instructions, 20 bytes at 0x7f971ae0b070)
0 params, 2 slots, 1 upvalue, 0 locals, 2 constants, 0 functions
	1	[470]	GETUPVAL 	0 0	; self
	2	[470]	GETTABLE 	0 0 -1	; "ui"
	3	[470]	SELF     	0 0 -2	; "onRefresh"
	4	[470]	CALL     	0 2 1
	5	[470]	RETURN   	0 1

function <./frontend/apps/filemanager/filemanagermenu.lua:471,474> (7 instructions, 28 bytes at 0x7f971ae0b150)
1 param, 4 slots, 3 upvalues, 1 local, 1 constant, 0 functions
	1	[472]	GETUPVAL 	1 0	; filemanagerRefresh
	2	[472]	CALL     	1 1 1
	3	[473]	GETUPVAL 	1 1	; UIManager
	4	[473]	SELF     	1 1 -1	; "close"
	5	[473]	GETUPVAL 	3 2	; cloud_storage
	6	[473]	CALL     	1 3 1
	7	[474]	RETURN   	0 1

function <./frontend/apps/filemanager/filemanagermenu.lua:481,484> (7 instructions, 28 bytes at 0x7f971ae0b9d0)
0 params, 2 slots, 1 upvalue, 0 locals, 2 constants, 0 functions
	1	[482]	GETUPVAL 	0 0	; Search
	2	[482]	SELF     	0 0 -1	; "getCalibre"
	3	[482]	CALL     	0 2 1
	4	[483]	GETUPVAL 	0 0	; Search
	5	[483]	SELF     	0 0 -2	; "ShowSearch"
	6	[483]	CALL     	0 2 1
	7	[484]	RETURN   	0 1

function <./frontend/apps/filemanager/filemanagermenu.lua:489,491> (13 instructions, 52 bytes at 0x7f971ae0bbb0)
0 params, 6 slots, 2 upvalues, 0 locals, 6 constants, 0 functions
	1	[490]	GETUPVAL 	0 0	; self
	2	[490]	GETTABLE 	0 0 -1	; "ui"
	3	[490]	SELF     	0 0 -2	; "handleEvent"
	4	[490]	GETUPVAL 	2 1	; Event
	5	[490]	SELF     	2 2 -3	; "new"
	6	[490]	LOADK    	4 -4	; "ShowFileSearch"
	7	[490]	GETUPVAL 	5 0	; self
	8	[490]	GETTABLE 	5 5 -1	; "ui"
	9	[490]	GETTABLE 	5 5 -5	; "file_chooser"
	10	[490]	GETTABLE 	5 5 -6	; "path"
	11	[490]	CALL     	2 4 0
	12	[490]	CALL     	0 0 1
	13	[491]	RETURN   	0 1

function <./frontend/apps/filemanager/filemanagermenu.lua:496,503> (35 instructions, 140 bytes at 0x7f971ae0bdd0)
0 params, 7 slots, 4 upvalues, 3 locals, 9 constants, 0 functions
	1	[497]	GETGLOBAL	0 -1	; G_reader_settings
	2	[497]	SELF     	0 0 -2	; "isTrue"
	3	[497]	LOADK    	2 -3	; "open_last_menu_show_filename"
	4	[497]	CALL     	0 3 2
	5	[497]	TEST     	0 0 0
	6	[497]	JMP      	6	; to 13
	7	[497]	GETGLOBAL	0 -1	; G_reader_settings
	8	[497]	SELF     	0 0 -4	; "readSetting"
	9	[497]	LOADK    	2 -5	; "lastfile"
	10	[497]	CALL     	0 3 2
	11	[497]	TEST     	0 0 1
	12	[497]	JMP      	4	; to 17
	13	[498]	GETUPVAL 	0 0	; _
	14	[498]	LOADK    	1 -6	; "Open last document"
	15	[498]	TAILCALL 	0 2 0
	16	[498]	RETURN   	0 0
	17	[500]	GETGLOBAL	0 -1	; G_reader_settings
	18	[500]	SELF     	0 0 -4	; "readSetting"
	19	[500]	LOADK    	2 -5	; "lastfile"
	20	[500]	CALL     	0 3 2
	21	[501]	GETUPVAL 	1 1	; util
	22	[501]	GETTABLE 	1 1 -7	; "splitFilePathName"
	23	[501]	MOVE     	2 0
	24	[501]	CALL     	1 2 3
	25	[502]	GETUPVAL 	3 2	; T
	26	[502]	GETUPVAL 	4 0	; _
	27	[502]	LOADK    	5 -8	; "Last: %1"
	28	[502]	CALL     	4 2 2
	29	[502]	GETUPVAL 	5 3	; BD
	30	[502]	GETTABLE 	5 5 -9	; "filename"
	31	[502]	MOVE     	6 2
	32	[502]	CALL     	5 2 0
	33	[502]	TAILCALL 	3 0 0
	34	[502]	RETURN   	3 0
	35	[503]	RETURN   	0 1

function <./frontend/apps/filemanager/filemanagermenu.lua:504,506> (10 instructions, 40 bytes at 0x7f971ae0c210)
0 params, 3 slots, 0 upvalues, 0 locals, 4 constants, 0 functions
	1	[505]	GETGLOBAL	0 -1	; G_reader_settings
	2	[505]	SELF     	0 0 -2	; "readSetting"
	3	[505]	LOADK    	2 -3	; "lastfile"
	4	[505]	CALL     	0 3 2
	5	[505]	EQ       	0 0 -4	; - nil
	6	[505]	JMP      	1	; to 8
	7	[505]	LOADBOOL 	0 0 1
	8	[505]	LOADBOOL 	0 1 0
	9	[505]	RETURN   	0 2
	10	[506]	RETURN   	0 1

function <./frontend/apps/filemanager/filemanagermenu.lua:507,509> (4 instructions, 16 bytes at 0x7f971ae0be90)
0 params, 2 slots, 1 upvalue, 0 locals, 1 constant, 0 functions
	1	[508]	GETUPVAL 	0 0	; self
	2	[508]	SELF     	0 0 -1	; "openLastDoc"
	3	[508]	CALL     	0 2 1
	4	[509]	RETURN   	0 1

function <./frontend/apps/filemanager/filemanagermenu.lua:510,519> (29 instructions, 116 bytes at 0x7f971ae0ab10)
0 params, 10 slots, 6 upvalues, 1 local, 11 constants, 1 function
	1	[511]	GETGLOBAL	0 -1	; G_reader_settings
	2	[511]	SELF     	0 0 -2	; "readSetting"
	3	[511]	LOADK    	2 -3	; "lastfile"
	4	[511]	CALL     	0 3 2
	5	[512]	GETUPVAL 	1 0	; UIManager
	6	[512]	SELF     	1 1 -4	; "show"
	7	[512]	GETUPVAL 	3 1	; ConfirmBox
	8	[512]	SELF     	3 3 -5	; "new"
	9	[512]	NEWTABLE 	5 0 3
	10	[513]	GETUPVAL 	6 2	; T
	11	[513]	GETUPVAL 	7 3	; _
	12	[513]	LOADK    	8 -7	; "Would you like to open the last document: %1?"
	13	[513]	CALL     	7 2 2
	14	[513]	GETUPVAL 	8 4	; BD
	15	[513]	GETTABLE 	8 8 -8	; "filepath"
	16	[513]	MOVE     	9 0
	17	[513]	CALL     	8 2 0
	18	[513]	CALL     	6 0 2
	19	[513]	SETTABLE 	5 -6 6	; "text" -
	20	[514]	GETUPVAL 	6 3	; _
	21	[514]	LOADK    	7 -10	; "OK"
	22	[514]	CALL     	6 2 2
	23	[514]	SETTABLE 	5 -9 6	; "ok_text" -
	24	[517]	CLOSURE  	6 0	; 0x7f971ae08000
	25	[517]	GETUPVAL 	0 5	; self
	26	[517]	SETTABLE 	5 -11 6	; "ok_callback" -
	27	[512]	CALL     	3 3 0
	28	[512]	CALL     	1 0 1
	29	[519]	RETURN   	0 1

function <./frontend/apps/filemanager/filemanagermenu.lua:515,517> (4 instructions, 16 bytes at 0x7f971ae08000)
0 params, 2 slots, 1 upvalue, 0 locals, 1 constant, 0 functions
	1	[516]	GETUPVAL 	0 0	; self
	2	[516]	SELF     	0 0 -1	; "openLastDoc"
	3	[516]	CALL     	0 2 1
	4	[517]	RETURN   	0 1

function <./frontend/apps/filemanager/filemanagermenu.lua:527,529> (4 instructions, 16 bytes at 0x7f971ae04a90)
0 params, 2 slots, 1 upvalue, 0 locals, 1 constant, 0 functions
	1	[528]	GETUPVAL 	0 0	; self
	2	[528]	SELF     	0 0 -1	; "exitOrRestart"
	3	[528]	CALL     	0 2 1
	4	[529]	RETURN   	0 1

function <./frontend/apps/filemanager/filemanagermenu.lua:533,535> (4 instructions, 16 bytes at 0x7f971ae0aa00)
0 params, 2 slots, 1 upvalue, 0 locals, 1 constant, 0 functions
	1	[534]	GETUPVAL 	0 0	; self
	2	[534]	SELF     	0 0 -1	; "exitOrRestart"
	3	[534]	CALL     	0 2 1
	4	[535]	RETURN   	0 1

function <./frontend/apps/filemanager/filemanagermenu.lua:539,543> (6 instructions, 24 bytes at 0x7f971ae0ae10)
0 params, 3 slots, 2 upvalues, 0 locals, 1 constant, 1 function
	1	[540]	GETUPVAL 	0 0	; self
	2	[540]	SELF     	0 0 -1	; "exitOrRestart"
	3	[542]	CLOSURE  	2 0	; 0x7f971ae04490
	4	[542]	GETUPVAL 	0 1	; UIManager
	5	[540]	CALL     	0 3 1
	6	[543]	RETURN   	0 1

function <./frontend/apps/filemanager/filemanagermenu.lua:540,542> (4 instructions, 16 bytes at 0x7f971ae04490)
0 params, 2 slots, 1 upvalue, 0 locals, 1 constant, 0 functions
	1	[541]	GETUPVAL 	0 0	; UIManager
	2	[541]	SELF     	0 0 -1	; "restartKOReader"
	3	[541]	CALL     	0 2 1
	4	[542]	RETURN   	0 1

function <./frontend/apps/filemanager/filemanagermenu.lua:556,559> (8 instructions, 32 bytes at 0x7f971ae06d20)
0 params, 2 slots, 1 upvalue, 0 locals, 3 constants, 0 functions
	1	[557]	GETUPVAL 	0 0	; self
	2	[557]	SELF     	0 0 -1	; "onCloseFileManagerMenu"
	3	[557]	CALL     	0 2 1
	4	[558]	GETUPVAL 	0 0	; self
	5	[558]	GETTABLE 	0 0 -2	; "ui"
	6	[558]	SELF     	0 0 -3	; "tapPlus"
	7	[558]	CALL     	0 2 1
	8	[559]	RETURN   	0 1

function <./frontend/apps/filemanager/filemanagermenu.lua:569,575> (11 instructions, 44 bytes at 0x7f971ae07600)
1 param, 10 slots, 0 upvalues, 7 locals, 3 constants, 0 functions
	1	[570]	NEWTABLE 	1 0 0
	2	[571]	GETGLOBAL	2 -1	; pairs
	3	[571]	GETTABLE 	3 0 -2	; "registered_widgets"
	4	[571]	CALL     	2 2 4
	5	[571]	JMP      	3	; to 9
	6	[573]	SELF     	7 6 -3	; "addToMainMenu"
	7	[573]	MOVE     	9 1
	8	[573]	CALL     	7 3 1
	9	[571]	TFORLOOP 	2 2
	10	[573]	JMP      	-5	; to 6
	11	[575]	RETURN   	0 1

function <./frontend/apps/filemanager/filemanagermenu.lua:577,583> (12 instructions, 48 bytes at 0x7f971ae05590)
2 params, 5 slots, 1 upvalue, 2 locals, 4 constants, 0 functions
	1	[578]	GETUPVAL 	2 0	; UIManager
	2	[578]	SELF     	2 2 -1	; "close"
	3	[578]	GETTABLE 	4 0 -2	; "menu_container"
	4	[578]	CALL     	2 3 1
	5	[579]	GETTABLE 	2 0 -3	; "ui"
	6	[579]	SELF     	2 2 -4	; "onClose"
	7	[579]	CALL     	2 2 1
	8	[580]	TEST     	1 0 0
	9	[580]	JMP      	2	; to 12
	10	[581]	MOVE     	2 1
	11	[581]	CALL     	2 1 1
	12	[583]	RETURN   	0 1

function <./frontend/apps/filemanager/filemanagermenu.lua:585,627> (83 instructions, 332 bytes at 0x7f971ae065b0)
2 params, 10 slots, 5 upvalues, 6 locals, 29 constants, 1 function
	1	[586]	GETTABLE 	2 0 -1	; "tab_item_table"
	2	[586]	EQ       	0 2 -2	; - nil
	3	[586]	JMP      	2	; to 6
	4	[587]	SELF     	2 0 -3	; "setUpdateItemTable"
	5	[587]	CALL     	2 2 1
	6	[590]	TEST     	1 0 1
	7	[590]	JMP      	7	; to 15
	8	[591]	GETGLOBAL	2 -4	; G_reader_settings
	9	[591]	SELF     	2 2 -5	; "readSetting"
	10	[591]	LOADK    	4 -6	; "filemanagermenu_tab_index"
	11	[591]	CALL     	2 3 2
	12	[591]	TESTSET  	1 2 1
	13	[591]	JMP      	1	; to 15
	14	[591]	LOADK    	1 -7	; 1
	15	[594]	GETUPVAL 	2 0	; CenterContainer
	16	[594]	SELF     	2 2 -8	; "new"
	17	[594]	NEWTABLE 	4 0 2
	18	[595]	SETTABLE 	4 -9 -10	; "ignore" "height"
	19	[596]	GETUPVAL 	5 1	; Screen
	20	[596]	SELF     	5 5 -12	; "getSize"
	21	[596]	CALL     	5 2 2
	22	[596]	SETTABLE 	4 -11 5	; "dimen" -
	23	[594]	CALL     	2 3 2
	24	[599]	LOADNIL  	3 3
	25	[600]	GETUPVAL 	4 2	; Device
	26	[600]	SELF     	4 4 -13	; "isTouchDevice"
	27	[600]	CALL     	4 2 2
	28	[600]	TEST     	4 0 1
	29	[600]	JMP      	5	; to 35
	30	[600]	GETUPVAL 	4 2	; Device
	31	[600]	SELF     	4 4 -14	; "hasDPad"
	32	[600]	CALL     	4 2 2
	33	[600]	TEST     	4 0 0
	34	[600]	JMP      	16	; to 51
	35	[601]	GETGLOBAL	4 -15	; require
	36	[601]	LOADK    	5 -16	; "ui/widget/touchmenu"
	37	[601]	CALL     	4 2 2
	38	[602]	SELF     	5 4 -8	; "new"
	39	[602]	NEWTABLE 	7 0 4
	40	[603]	GETUPVAL 	8 1	; Screen
	41	[603]	SELF     	8 8 -18	; "getWidth"
	42	[603]	CALL     	8 2 2
	43	[603]	SETTABLE 	7 -17 8	; "width" -
	44	[604]	SETTABLE 	7 -19 1	; "last_index" -
	45	[605]	GETTABLE 	8 0 -1	; "tab_item_table"
	46	[605]	SETTABLE 	7 -1 8	; "tab_item_table" -
	47	[606]	SETTABLE 	7 -20 2	; "show_parent" -
	48	[602]	CALL     	5 3 2
	49	[607]	MOVE     	3 5
	50	[607]	JMP      	21	; to 72
	51	[609]	GETGLOBAL	4 -15	; require
	52	[609]	LOADK    	5 -21	; "ui/widget/menu"
	53	[609]	CALL     	4 2 2
	54	[610]	SELF     	5 4 -8	; "new"
	55	[610]	NEWTABLE 	7 0 4
	56	[611]	GETUPVAL 	8 3	; _
	57	[611]	LOADK    	9 -23	; "File manager menu"
	58	[611]	CALL     	8 2 2
	59	[611]	SETTABLE 	7 -22 8	; "title" -
	60	[612]	GETTABLE 	8 4 -25	; "itemTableFromTouchMenu"
	61	[612]	GETTABLE 	9 0 -1	; "tab_item_table"
	62	[612]	CALL     	8 2 2
	63	[612]	SETTABLE 	7 -24 8	; "item_table" -
	64	[613]	GETUPVAL 	8 1	; Screen
	65	[613]	SELF     	8 8 -18	; "getWidth"
	66	[613]	CALL     	8 2 2
	67	[613]	SUB      	8 8 -26	; - 10
	68	[613]	SETTABLE 	7 -17 8	; "width" -
	69	[614]	SETTABLE 	7 -20 2	; "show_parent" -
	70	[610]	CALL     	5 3 2
	71	[615]	MOVE     	3 5
	72	[620]	CLOSURE  	4 0	; 0x7f971ae0a6f0
	73	[620]	MOVE     	0 0
	74	[620]	SETTABLE 	3 -27 4	; "close_callback" -
	75	[622]	SETTABLE 	2 -7 3	; 1 -
	76	[624]	SETTABLE 	0 -28 2	; "menu_container" -
	77	[625]	GETUPVAL 	4 4	; UIManager
	78	[625]	SELF     	4 4 -29	; "show"
	79	[625]	MOVE     	6 2
	80	[625]	CALL     	4 3 1
	81	[626]	LOADBOOL 	4 1 0
	82	[626]	RETURN   	4 2
	83	[627]	RETURN   	0 1

function <./frontend/apps/filemanager/filemanagermenu.lua:618,620> (4 instructions, 16 bytes at 0x7f971ae0a6f0)
0 params, 2 slots, 1 upvalue, 0 locals, 1 constant, 0 functions
	1	[619]	GETUPVAL 	0 0	; self
	2	[619]	SELF     	0 0 -1	; "onCloseFileManagerMenu"
	3	[619]	CALL     	0 2 1
	4	[620]	RETURN   	0 1

function <./frontend/apps/filemanager/filemanagermenu.lua:629,634> (15 instructions, 60 bytes at 0x7f971ae09ed0)
1 param, 6 slots, 1 upvalue, 2 locals, 7 constants, 0 functions
	1	[630]	GETTABLE 	1 0 -1	; "menu_container"
	2	[630]	GETTABLE 	1 1 -2	; 1
	3	[630]	GETTABLE 	1 1 -3	; "last_index"
	4	[631]	GETGLOBAL	2 -4	; G_reader_settings
	5	[631]	SELF     	2 2 -5	; "saveSetting"
	6	[631]	LOADK    	4 -6	; "filemanagermenu_tab_index"
	7	[631]	MOVE     	5 1
	8	[631]	CALL     	2 4 1
	9	[632]	GETUPVAL 	2 0	; UIManager
	10	[632]	SELF     	2 2 -7	; "close"
	11	[632]	GETTABLE 	4 0 -1	; "menu_container"
	12	[632]	CALL     	2 3 1
	13	[633]	LOADBOOL 	2 1 0
	14	[633]	RETURN   	2 2
	15	[634]	RETURN   	0 1

function <./frontend/apps/filemanager/filemanagermenu.lua:636,653> (59 instructions, 236 bytes at 0x7f971ae0c5b0)
2 params, 6 slots, 2 upvalues, 3 locals, 13 constants, 0 functions
	1	[637]	GETTABLE 	2 0 -1	; "tab_item_table"
	2	[637]	EQ       	0 2 -2	; - nil
	3	[637]	JMP      	2	; to 6
	4	[638]	SELF     	2 0 -3	; "setUpdateItemTable"
	5	[638]	CALL     	2 2 1
	6	[640]	GETGLOBAL	2 -4	; G_reader_settings
	7	[640]	SELF     	2 2 -5	; "readSetting"
	8	[640]	LOADK    	4 -6	; "filemanagermenu_tab_index"
	9	[640]	CALL     	2 3 2
	10	[640]	TEST     	2 0 1
	11	[640]	JMP      	1	; to 13
	12	[640]	LOADK    	2 -7	; 1
	13	[641]	TEST     	1 0 1
	14	[641]	JMP      	2	; to 17
	15	[642]	RETURN   	2 2
	16	[642]	JMP      	42	; to 59
	17	[644]	GETTABLE 	3 1 -8	; "pos"
	18	[644]	GETTABLE 	3 3 -9	; "x"
	19	[644]	GETUPVAL 	4 0	; Screen
	20	[644]	SELF     	4 4 -10	; "getWidth"
	21	[644]	CALL     	4 2 2
	22	[644]	MUL      	4 -11 4	; 2 -
	23	[644]	DIV      	4 4 -12	; - 3
	24	[644]	LT       	0 4 3
	25	[644]	JMP      	12	; to 38
	26	[645]	GETUPVAL 	3 1	; BD
	27	[645]	GETTABLE 	3 3 -13	; "mirroredUILayout"
	28	[645]	CALL     	3 1 2
	29	[645]	TEST     	3 0 0
	30	[645]	JMP      	3	; to 34
	31	[645]	LOADK    	3 -7	; 1
	32	[645]	TEST     	3 0 1
	33	[645]	JMP      	2	; to 36
	34	[645]	GETTABLE 	3 0 -1	; "tab_item_table"
	35	[645]	LEN      	3 3
	36	[645]	RETURN   	3 2
	37	[645]	JMP      	21	; to 59
	38	[647]	GETTABLE 	3 1 -8	; "pos"
	39	[647]	GETTABLE 	3 3 -9	; "x"
	40	[647]	GETUPVAL 	4 0	; Screen
	41	[647]	SELF     	4 4 -10	; "getWidth"
	42	[647]	CALL     	4 2 2
	43	[647]	DIV      	4 4 -12	; - 3
	44	[647]	LT       	0 3 4
	45	[647]	JMP      	12	; to 58
	46	[648]	GETUPVAL 	3 1	; BD
	47	[648]	GETTABLE 	3 3 -13	; "mirroredUILayout"
	48	[648]	CALL     	3 1 2
	49	[648]	TEST     	3 0 0
	50	[648]	JMP      	4	; to 55
	51	[648]	GETTABLE 	3 0 -1	; "tab_item_table"
	52	[648]	LEN      	3 3
	53	[648]	TEST     	3 0 1
	54	[648]	JMP      	1	; to 56
	55	[648]	LOADK    	3 -7	; 1
	56	[648]	RETURN   	3 2
	57	[648]	JMP      	1	; to 59
	58	[651]	RETURN   	2 2
	59	[653]	RETURN   	0 1

function <./frontend/apps/filemanager/filemanagermenu.lua:655,660> (11 instructions, 44 bytes at 0x7f971ae0c700)
2 params, 7 slots, 0 upvalues, 2 locals, 4 constants, 0 functions
	1	[656]	GETTABLE 	2 0 -1	; "activation_menu"
	2	[656]	EQ       	1 2 -2	; - "swipe"
	3	[656]	JMP      	7	; to 11
	4	[657]	SELF     	2 0 -3	; "onShowMenu"
	5	[657]	SELF     	4 0 -4	; "_getTabIndexFromLocation"
	6	[657]	MOVE     	6 1
	7	[657]	CALL     	4 3 0
	8	[657]	CALL     	2 0 1
	9	[658]	LOADBOOL 	2 1 0
	10	[658]	RETURN   	2 2
	11	[660]	RETURN   	0 1

function <./frontend/apps/filemanager/filemanagermenu.lua:662,667> (14 instructions, 56 bytes at 0x7f971ae0ce50)
2 params, 7 slots, 0 upvalues, 2 locals, 6 constants, 0 functions
	1	[663]	GETTABLE 	2 0 -1	; "activation_menu"
	2	[663]	EQ       	1 2 -2	; - "tap"
	3	[663]	JMP      	10	; to 14
	4	[663]	GETTABLE 	2 1 -3	; "direction"
	5	[663]	EQ       	0 2 -4	; - "south"
	6	[663]	JMP      	7	; to 14
	7	[664]	SELF     	2 0 -5	; "onShowMenu"
	8	[664]	SELF     	4 0 -6	; "_getTabIndexFromLocation"
	9	[664]	MOVE     	6 1
	10	[664]	CALL     	4 3 0
	11	[664]	CALL     	2 0 1
	12	[665]	LOADBOOL 	2 1 0
	13	[665]	RETURN   	2 2
	14	[667]	RETURN   	0 1

function <./frontend/apps/filemanager/filemanagermenu.lua:669,674> (8 instructions, 32 bytes at 0x7f971ae0d370)
2 params, 4 slots, 1 upvalue, 2 locals, 2 constants, 0 functions
	1	[671]	GETUPVAL 	2 0	; Device
	2	[671]	SELF     	2 2 -1	; "isTouchDevice"
	3	[671]	CALL     	2 2 2
	4	[671]	TEST     	2 0 0
	5	[671]	JMP      	2	; to 8
	6	[672]	SELF     	2 0 -2	; "initGesListener"
	7	[672]	CALL     	2 2 1
	8	[674]	RETURN   	0 1

function <./frontend/apps/filemanager/filemanagermenu.lua:676,678> (6 instructions, 24 bytes at 0x7f971ae0d730)
2 params, 5 slots, 0 upvalues, 2 locals, 3 constants, 0 functions
	1	[677]	GETGLOBAL	2 -1	; table
	2	[677]	GETTABLE 	2 2 -2	; "insert"
	3	[677]	GETTABLE 	3 0 -3	; "registered_widgets"
	4	[677]	MOVE     	4 1
	5	[677]	CALL     	2 3 1
	6	[678]	RETURN   	0 1
