
main <./frontend/apps/filemanager/filemanagerfilesearcher.lua:0,0> (84 instructions, 336 bytes at 0x7fda4cc06910)
0+ params, 17 slots, 0 upvalues, 14 locals, 32 constants, 5 functions
	1	[1]	GETGLOBAL	0 -1	; require
	2	[1]	LOADK    	1 -2	; "ui/widget/container/centercontainer"
	3	[1]	CALL     	0 2 2
	4	[2]	GETGLOBAL	1 -1	; require
	5	[2]	LOADK    	2 -3	; "document/documentregistry"
	6	[2]	CALL     	1 2 2
	7	[3]	GETGLOBAL	2 -1	; require
	8	[3]	LOADK    	3 -4	; "ui/font"
	9	[3]	CALL     	2 2 2
	10	[4]	GETGLOBAL	3 -1	; require
	11	[4]	LOADK    	4 -5	; "ui/widget/infomessage"
	12	[4]	CALL     	3 2 2
	13	[5]	GETGLOBAL	4 -1	; require
	14	[5]	LOADK    	5 -6	; "ui/widget/container/inputcontainer"
	15	[5]	CALL     	4 2 2
	16	[6]	GETGLOBAL	5 -1	; require
	17	[6]	LOADK    	6 -7	; "ui/widget/inputdialog"
	18	[6]	CALL     	5 2 2
	19	[7]	GETGLOBAL	6 -1	; require
	20	[7]	LOADK    	7 -8	; "ui/widget/menu"
	21	[7]	CALL     	6 2 2
	22	[8]	GETGLOBAL	7 -1	; require
	23	[8]	LOADK    	8 -9	; "ui/uimanager"
	24	[8]	CALL     	7 2 2
	25	[9]	GETGLOBAL	8 -1	; require
	26	[9]	LOADK    	9 -10	; "libs/libkoreader-lfs"
	27	[9]	CALL     	8 2 2
	28	[10]	GETGLOBAL	9 -1	; require
	29	[10]	LOADK    	10 -11	; "ffi/util"
	30	[10]	CALL     	9 2 2
	31	[11]	GETGLOBAL	10 -1	; require
	32	[11]	LOADK    	11 -12	; "util"
	33	[11]	CALL     	10 2 2
	34	[12]	GETGLOBAL	11 -1	; require
	35	[12]	LOADK    	12 -13	; "gettext"
	36	[12]	CALL     	11 2 2
	37	[13]	GETGLOBAL	12 -1	; require
	38	[13]	LOADK    	13 -14	; "device"
	39	[13]	CALL     	12 2 2
	40	[13]	GETTABLE 	12 12 -15	; "screen"
	41	[15]	SELF     	13 4 -16	; "new"
	42	[15]	NEWTABLE 	15 0 8
	43	[16]	SETTABLE 	15 -17 -18	; "search_dialog" nil
	44	[20]	NEWTABLE 	16 0 0
	45	[20]	SETTABLE 	15 -19 16	; "dirs" -
	46	[21]	NEWTABLE 	16 0 0
	47	[21]	SETTABLE 	15 -20 16	; "files" -
	48	[22]	NEWTABLE 	16 0 0
	49	[22]	SETTABLE 	15 -21 16	; "results" -
	50	[23]	SETTABLE 	15 -22 -23	; "items" 0
	51	[24]	SETTABLE 	15 -24 -18	; "commands" nil
	52	[27]	SETTABLE 	15 -25 -26	; "use_previous_search_results" false
	53	[28]	SETTABLE 	15 -27 -18	; "lastsearch" nil
	54	[15]	CALL     	13 3 2
	55	[54]	CLOSURE  	14 0	; 0x7fda4cc07120
	56	[54]	MOVE     	0 8
	57	[54]	MOVE     	0 10
	58	[54]	MOVE     	0 1
	59	[31]	SETTABLE 	13 -28 14	; "readDir" -
	60	[86]	CLOSURE  	14 1	; 0x7fda4cc07910
	61	[56]	SETTABLE 	13 -29 14	; "setSearchResults" -
	62	[106]	CLOSURE  	14 2	; 0x7fda4cc08c10
	63	[106]	MOVE     	0 7
	64	[106]	MOVE     	0 3
	65	[106]	MOVE     	0 9
	66	[106]	MOVE     	0 11
	67	[88]	SETTABLE 	13 -30 14	; "close" -
	68	[161]	CLOSURE  	14 3	; 0x7fda4cc09270
	69	[161]	MOVE     	0 5
	70	[161]	MOVE     	0 11
	71	[161]	MOVE     	0 12
	72	[161]	MOVE     	0 7
	73	[161]	MOVE     	0 8
	74	[108]	SETTABLE 	13 -31 14	; "onShowFileSearch" -
	75	[183]	CLOSURE  	14 4	; 0x7fda4cc0a610
	76	[183]	MOVE     	0 0
	77	[183]	MOVE     	0 12
	78	[183]	MOVE     	0 6
	79	[183]	MOVE     	0 2
	80	[183]	MOVE     	0 7
	81	[183]	MOVE     	0 11
	82	[163]	SETTABLE 	13 -32 14	; "showSearchResults" -
	83	[185]	RETURN   	13 2
	84	[185]	RETURN   	0 1

function <./frontend/apps/filemanager/filemanagerfilesearcher.lua:31,54> (96 instructions, 384 bytes at 0x7fda4cc07120)
1 param, 16 slots, 3 upvalues, 13 locals, 23 constants, 0 functions
	1	[32]	NEWTABLE 	1 1 0
	2	[32]	GETTABLE 	2 0 -2	; "path"
	3	[32]	SETLIST  	1 1 1	; 1
	4	[32]	SETTABLE 	0 -1 1	; "dirs" -
	5	[33]	NEWTABLE 	1 0 0
	6	[33]	SETTABLE 	0 -3 1	; "files" -
	7	[34]	GETTABLE 	1 0 -1	; "dirs"
	8	[34]	LEN      	1 1
	9	[34]	EQ       	1 1 -4	; - 0
	10	[34]	JMP      	85	; to 96
	11	[35]	NEWTABLE 	1 0 0
	12	[37]	GETGLOBAL	2 -5	; pairs
	13	[37]	GETTABLE 	3 0 -1	; "dirs"
	14	[37]	CALL     	2 2 4
	15	[37]	JMP      	76	; to 92
	16	[39]	GETUPVAL 	7 0	; lfs
	17	[39]	GETTABLE 	7 7 -6	; "dir"
	18	[39]	MOVE     	8 6
	19	[39]	CALL     	7 2 4
	20	[39]	JMP      	69	; to 90
	21	[40]	MOVE     	11 6
	22	[40]	LOADK    	12 -7	; "/"
	23	[40]	MOVE     	13 10
	24	[40]	CONCAT   	11 11 13
	25	[41]	GETUPVAL 	12 0	; lfs
	26	[41]	GETTABLE 	12 12 -8	; "attributes"
	27	[41]	MOVE     	13 11
	28	[41]	CALL     	12 2 2
	29	[41]	TEST     	12 0 1
	30	[41]	JMP      	1	; to 32
	31	[41]	NEWTABLE 	12 0 0
	32	[43]	GETTABLE 	13 12 -9	; "mode"
	33	[43]	EQ       	0 13 -10	; - "directory"
	34	[43]	JMP      	31	; to 66
	35	[43]	EQ       	1 10 -11	; - "."
	36	[43]	JMP      	29	; to 66
	37	[43]	EQ       	1 10 -12	; - ".."
	38	[43]	JMP      	27	; to 66
	39	[43]	GETGLOBAL	13 -13	; G_reader_settings
	40	[43]	SELF     	13 13 -14	; "isTrue"
	41	[43]	LOADK    	15 -15	; "show_hidden"
	42	[43]	CALL     	13 3 2
	43	[43]	TEST     	13 0 1
	44	[43]	JMP      	7	; to 52
	45	[43]	GETUPVAL 	13 1	; util
	46	[43]	GETTABLE 	13 13 -16	; "stringStartsWith"
	47	[43]	MOVE     	14 10
	48	[43]	LOADK    	15 -11	; "."
	49	[43]	CALL     	13 3 2
	50	[43]	TEST     	13 0 1
	51	[43]	JMP      	14	; to 66
	52	[44]	GETGLOBAL	13 -17	; table
	53	[44]	GETTABLE 	13 13 -18	; "insert"
	54	[44]	MOVE     	14 1
	55	[44]	MOVE     	15 11
	56	[44]	CALL     	13 3 1
	57	[45]	GETGLOBAL	13 -17	; table
	58	[45]	GETTABLE 	13 13 -18	; "insert"
	59	[45]	GETTABLE 	14 0 -3	; "files"
	60	[45]	NEWTABLE 	15 0 3
	61	[45]	SETTABLE 	15 -19 10	; "name" -
	62	[45]	SETTABLE 	15 -2 11	; "path" -
	63	[45]	SETTABLE 	15 -20 12	; "attr" -
	64	[45]	CALL     	13 3 1
	65	[45]	JMP      	24	; to 90
	66	[47]	GETTABLE 	13 12 -9	; "mode"
	67	[47]	EQ       	0 13 -21	; - "file"
	68	[47]	JMP      	21	; to 90
	69	[47]	GETUPVAL 	13 1	; util
	70	[47]	GETTABLE 	13 13 -16	; "stringStartsWith"
	71	[47]	MOVE     	14 10
	72	[47]	LOADK    	15 -22	; "._"
	73	[47]	CALL     	13 3 2
	74	[47]	TEST     	13 0 1
	75	[47]	JMP      	14	; to 90
	76	[47]	GETUPVAL 	13 2	; DocumentRegistry
	77	[47]	SELF     	13 13 -23	; "hasProvider"
	78	[47]	MOVE     	15 11
	79	[47]	CALL     	13 3 2
	80	[47]	TEST     	13 0 0
	81	[47]	JMP      	8	; to 90
	82	[48]	GETGLOBAL	13 -17	; table
	83	[48]	GETTABLE 	13 13 -18	; "insert"
	84	[48]	GETTABLE 	14 0 -3	; "files"
	85	[48]	NEWTABLE 	15 0 3
	86	[48]	SETTABLE 	15 -19 10	; "name" -
	87	[48]	SETTABLE 	15 -2 11	; "path" -
	88	[48]	SETTABLE 	15 -20 12	; "attr" -
	89	[48]	CALL     	13 3 1
	90	[39]	TFORLOOP 	7 1
	91	[49]	JMP      	-71	; to 21
	92	[37]	TFORLOOP 	2 2
	93	[50]	JMP      	-78	; to 16
	94	[52]	SETTABLE 	0 -1 1	; "dirs" -
	95	[52]	JMP      	-89	; to 7
	96	[54]	RETURN   	0 1

function <./frontend/apps/filemanager/filemanagerfilesearcher.lua:56,86> (77 instructions, 308 bytes at 0x7fda4cc07910)
1 param, 13 slots, 0 upvalues, 9 locals, 26 constants, 2 functions
	1	[57]	GETGLOBAL	1 -1	; require
	2	[57]	LOADK    	2 -2	; "apps/filemanager/filemanager"
	3	[57]	CALL     	1 2 2
	4	[58]	GETGLOBAL	2 -1	; require
	5	[58]	LOADK    	3 -3	; "apps/reader/readerui"
	6	[58]	CALL     	2 2 2
	7	[59]	GETTABLE 	3 0 -4	; "search_value"
	8	[60]	NEWTABLE 	4 0 0
	9	[60]	SETTABLE 	0 -5 4	; "results" -
	10	[61]	EQ       	0 3 -6	; - " "
	11	[61]	JMP      	3	; to 15
	12	[62]	GETTABLE 	4 0 -7	; "files"
	13	[62]	SETTABLE 	0 -5 4	; "results" -
	14	[62]	JMP      	58	; to 73
	15	[64]	GETGLOBAL	4 -8	; pairs
	16	[64]	GETTABLE 	5 0 -7	; "files"
	17	[64]	CALL     	4 2 4
	18	[64]	JMP      	52	; to 71
	19	[65]	GETGLOBAL	9 -9	; string
	20	[65]	GETTABLE 	9 9 -10	; "find"
	21	[65]	GETGLOBAL	10 -9	; string
	22	[65]	GETTABLE 	10 10 -11	; "lower"
	23	[65]	GETTABLE 	11 8 -12	; "name"
	24	[65]	CALL     	10 2 2
	25	[65]	GETGLOBAL	11 -9	; string
	26	[65]	GETTABLE 	11 11 -11	; "lower"
	27	[65]	MOVE     	12 3
	28	[65]	CALL     	11 2 0
	29	[65]	CALL     	9 0 2
	30	[65]	TEST     	9 0 0
	31	[65]	JMP      	38	; to 70
	32	[65]	GETGLOBAL	9 -9	; string
	33	[65]	GETTABLE 	9 9 -13	; "sub"
	34	[65]	GETTABLE 	10 8 -12	; "name"
	35	[65]	LOADK    	11 -14	; -4
	36	[65]	CALL     	9 3 2
	37	[65]	EQ       	1 9 -15	; - ".sdr"
	38	[65]	JMP      	31	; to 70
	39	[66]	GETTABLE 	9 8 -16	; "attr"
	40	[66]	GETTABLE 	9 9 -17	; "mode"
	41	[66]	EQ       	0 9 -18	; - "directory"
	42	[66]	JMP      	15	; to 58
	43	[67]	GETTABLE 	9 8 -12	; "name"
	44	[67]	LOADK    	10 -20	; "/"
	45	[67]	CONCAT   	9 9 10
	46	[67]	SETTABLE 	8 -19 9	; "text" -
	47	[68]	SETTABLE 	8 -12 -21	; "name" nil
	48	[71]	CLOSURE  	9 0	; 0x7fda4cc08360
	49	[71]	MOVE     	0 1
	50	[71]	MOVE     	0 8
	51	[71]	SETTABLE 	8 -22 9	; "callback" -
	52	[72]	GETGLOBAL	9 -23	; table
	53	[72]	GETTABLE 	9 9 -24	; "insert"
	54	[72]	GETTABLE 	10 0 -5	; "results"
	55	[72]	MOVE     	11 8
	56	[72]	CALL     	9 3 1
	57	[72]	JMP      	12	; to 70
	58	[74]	GETTABLE 	9 8 -12	; "name"
	59	[74]	SETTABLE 	8 -19 9	; "text" -
	60	[75]	SETTABLE 	8 -12 -21	; "name" nil
	61	[78]	CLOSURE  	9 1	; 0x7fda4cc08530
	62	[78]	MOVE     	0 2
	63	[78]	MOVE     	0 8
	64	[78]	SETTABLE 	8 -22 9	; "callback" -
	65	[79]	GETGLOBAL	9 -23	; table
	66	[79]	GETTABLE 	9 9 -24	; "insert"
	67	[79]	GETTABLE 	10 0 -5	; "results"
	68	[79]	MOVE     	11 8
	69	[79]	CALL     	9 3 1
	70	[81]	CLOSE    	7
	71	[64]	TFORLOOP 	4 2
	72	[81]	JMP      	-54	; to 19
	73	[84]	SETTABLE 	0 -25 3	; "keywords" -
	74	[85]	GETTABLE 	4 0 -5	; "results"
	75	[85]	LEN      	4 4
	76	[85]	SETTABLE 	0 -26 4	; "items" -
	77	[86]	RETURN   	0 1

function <./frontend/apps/filemanager/filemanagerfilesearcher.lua:69,71> (6 instructions, 24 bytes at 0x7fda4cc08360)
0 params, 3 slots, 2 upvalues, 0 locals, 2 constants, 0 functions
	1	[70]	GETUPVAL 	0 0	; FileManager
	2	[70]	SELF     	0 0 -1	; "showFiles"
	3	[70]	GETUPVAL 	2 1	; f
	4	[70]	GETTABLE 	2 2 -2	; "path"
	5	[70]	CALL     	0 3 1
	6	[71]	RETURN   	0 1

function <./frontend/apps/filemanager/filemanagerfilesearcher.lua:76,78> (6 instructions, 24 bytes at 0x7fda4cc08530)
0 params, 3 slots, 2 upvalues, 0 locals, 2 constants, 0 functions
	1	[77]	GETUPVAL 	0 0	; ReaderUI
	2	[77]	SELF     	0 0 -1	; "showReader"
	3	[77]	GETUPVAL 	2 1	; f
	4	[77]	GETTABLE 	2 2 -2	; "path"
	5	[77]	CALL     	0 3 1
	6	[78]	RETURN   	0 1

function <./frontend/apps/filemanager/filemanagerfilesearcher.lua:88,106> (40 instructions, 160 bytes at 0x7fda4cc08c10)
1 param, 9 slots, 4 upvalues, 1 local, 15 constants, 0 functions
	1	[89]	GETTABLE 	1 0 -1	; "search_value"
	2	[89]	TEST     	1 0 0
	3	[89]	JMP      	36	; to 40
	4	[90]	GETUPVAL 	1 0	; UIManager
	5	[90]	SELF     	1 1 -2	; "close"
	6	[90]	GETTABLE 	3 0 -3	; "search_dialog"
	7	[90]	CALL     	1 3 1
	8	[91]	GETGLOBAL	1 -4	; string
	9	[91]	GETTABLE 	1 1 -5	; "len"
	10	[91]	GETTABLE 	2 0 -1	; "search_value"
	11	[91]	CALL     	1 2 2
	12	[91]	LT       	0 -6 1	; 0 -
	13	[91]	JMP      	26	; to 40
	14	[92]	SELF     	1 0 -7	; "readDir"
	15	[92]	CALL     	1 2 1
	16	[93]	SELF     	1 0 -8	; "setSearchResults"
	17	[93]	CALL     	1 2 1
	18	[94]	GETTABLE 	1 0 -9	; "results"
	19	[94]	LEN      	1 1
	20	[94]	LT       	0 -6 1	; 0 -
	21	[94]	JMP      	3	; to 25
	22	[95]	SELF     	1 0 -10	; "showSearchResults"
	23	[95]	CALL     	1 2 1
	24	[95]	JMP      	15	; to 40
	25	[97]	GETUPVAL 	1 0	; UIManager
	26	[97]	SELF     	1 1 -11	; "show"
	27	[98]	GETUPVAL 	3 1	; InfoMessage
	28	[98]	SELF     	3 3 -12	; "new"
	29	[98]	NEWTABLE 	5 0 1
	30	[99]	GETUPVAL 	6 2	; BaseUtil
	31	[99]	GETTABLE 	6 6 -14	; "template"
	32	[99]	GETUPVAL 	7 3	; _
	33	[99]	LOADK    	8 -15	; "Found no files matching '%1'."
	34	[99]	CALL     	7 2 2
	35	[100]	GETTABLE 	8 0 -1	; "search_value"
	36	[99]	CALL     	6 3 2
	37	[100]	SETTABLE 	5 -13 6	; "text" -
	38	[98]	CALL     	3 3 0
	39	[97]	CALL     	1 0 1
	40	[106]	RETURN   	0 1

function <./frontend/apps/filemanager/filemanagerfilesearcher.lua:108,161> (70 instructions, 280 bytes at 0x7fda4cc09270)
2 params, 14 slots, 5 upvalues, 4 locals, 22 constants, 3 functions
	1	[109]	GETTABLE 	2 0 -1	; "search_value"
	2	[110]	LOADBOOL 	3 1 0
	3	[111]	GETGLOBAL	4 -2	; G_reader_settings
	4	[111]	SELF     	4 4 -3	; "readSetting"
	5	[111]	LOADK    	6 -4	; "home_dir"
	6	[111]	CALL     	4 3 2
	7	[111]	TEST     	4 0 1
	8	[111]	JMP      	1	; to 10
	9	[112]	LOADBOOL 	3 0 0
	10	[114]	GETUPVAL 	4 0	; InputDialog
	11	[114]	SELF     	4 4 -6	; "new"
	12	[114]	NEWTABLE 	6 0 4
	13	[115]	GETUPVAL 	7 1	; _
	14	[115]	LOADK    	8 -8	; "Search for books by filename"
	15	[115]	CALL     	7 2 2
	16	[115]	SETTABLE 	6 -7 7	; "title" -
	17	[116]	GETTABLE 	7 0 -1	; "search_value"
	18	[116]	SETTABLE 	6 -9 7	; "input" -
	19	[117]	GETUPVAL 	7 2	; Screen
	20	[117]	SELF     	7 7 -11	; "getWidth"
	21	[117]	CALL     	7 2 2
	22	[117]	MUL      	7 7 -12	; - 0.9
	23	[117]	SETTABLE 	6 -10 7	; "width" -
	24	[118]	NEWTABLE 	7 1 0
	25	[118]	NEWTABLE 	8 3 0
	26	[119]	NEWTABLE 	9 0 3
	27	[121]	GETUPVAL 	10 1	; _
	28	[121]	LOADK    	11 -15	; "Cancel"
	29	[121]	CALL     	10 2 2
	30	[121]	SETTABLE 	9 -14 10	; "text" -
	31	[122]	SETTABLE 	9 -16 -17	; "enabled" true
	32	[126]	CLOSURE  	10 0	; 0x7fda4cc065c0
	33	[126]	MOVE     	0 0
	34	[126]	GETUPVAL 	0 3	; UIManager
	35	[126]	SETTABLE 	9 -18 10	; "callback" -
	36	[127]	NEWTABLE 	10 0 3
	37	[129]	GETUPVAL 	11 1	; _
	38	[129]	LOADK    	12 -19	; "Current folder"
	39	[129]	CALL     	11 2 2
	40	[129]	SETTABLE 	10 -14 11	; "text" -
	41	[130]	SETTABLE 	10 -16 -17	; "enabled" true
	42	[140]	CLOSURE  	11 1	; 0x7fda4cc09b30
	43	[140]	MOVE     	0 0
	44	[140]	MOVE     	0 1
	45	[140]	GETUPVAL 	0 4	; lfs
	46	[140]	MOVE     	0 2
	47	[140]	SETTABLE 	10 -18 11	; "callback" -
	48	[141]	NEWTABLE 	11 0 3
	49	[143]	GETUPVAL 	12 1	; _
	50	[143]	LOADK    	13 -20	; "Home folder"
	51	[143]	CALL     	12 2 2
	52	[143]	SETTABLE 	11 -14 12	; "text" -
	53	[144]	SETTABLE 	11 -16 3	; "enabled" -
	54	[154]	CLOSURE  	12 2	; 0x7fda4cc0a380
	55	[154]	MOVE     	0 0
	56	[154]	MOVE     	0 2
	57	[154]	SETTABLE 	11 -18 12	; "callback" -
	58	[156]	SETLIST  	8 3 1	; 1
	59	[157]	SETLIST  	7 1 1	; 1
	60	[157]	SETTABLE 	6 -13 7	; "buttons" -
	61	[114]	CALL     	4 3 2
	62	[158]	SETTABLE 	0 -5 4	; "search_dialog" -
	63	[159]	GETUPVAL 	4 3	; UIManager
	64	[159]	SELF     	4 4 -21	; "show"
	65	[159]	GETTABLE 	6 0 -5	; "search_dialog"
	66	[159]	CALL     	4 3 1
	67	[160]	GETTABLE 	4 0 -5	; "search_dialog"
	68	[160]	SELF     	4 4 -22	; "onShowKeyboard"
	69	[160]	CALL     	4 2 1
	70	[161]	RETURN   	0 1

function <./frontend/apps/filemanager/filemanagerfilesearcher.lua:123,126> (10 instructions, 40 bytes at 0x7fda4cc065c0)
0 params, 3 slots, 2 upvalues, 0 locals, 3 constants, 0 functions
	1	[124]	GETUPVAL 	0 0	; self
	2	[124]	GETTABLE 	0 0 -1	; "search_dialog"
	3	[124]	SELF     	0 0 -2	; "onClose"
	4	[124]	CALL     	0 2 1
	5	[125]	GETUPVAL 	0 1	; UIManager
	6	[125]	SELF     	0 0 -3	; "close"
	7	[125]	GETUPVAL 	2 0	; self
	8	[125]	GETTABLE 	2 2 -1	; "search_dialog"
	9	[125]	CALL     	0 3 1
	10	[126]	RETURN   	0 1

function <./frontend/apps/filemanager/filemanagerfilesearcher.lua:131,140> (28 instructions, 112 bytes at 0x7fda4cc09b30)
0 params, 3 slots, 4 upvalues, 0 locals, 9 constants, 0 functions
	1	[132]	GETUPVAL 	0 0	; self
	2	[132]	GETUPVAL 	1 1	; search_path
	3	[132]	TEST     	1 0 1
	4	[132]	JMP      	3	; to 8
	5	[132]	GETUPVAL 	1 2	; lfs
	6	[132]	GETTABLE 	1 1 -2	; "currentdir"
	7	[132]	CALL     	1 1 2
	8	[132]	SETTABLE 	0 -1 1	; "path" -
	9	[133]	GETUPVAL 	0 0	; self
	10	[133]	GETUPVAL 	1 0	; self
	11	[133]	GETTABLE 	1 1 -4	; "search_dialog"
	12	[133]	SELF     	1 1 -5	; "getInputText"
	13	[133]	CALL     	1 2 2
	14	[133]	SETTABLE 	0 -3 1	; "search_value" -
	15	[134]	GETUPVAL 	0 0	; self
	16	[134]	GETTABLE 	0 0 -3	; "search_value"
	17	[134]	GETUPVAL 	1 3	; dummy
	18	[134]	EQ       	0 0 1
	19	[134]	JMP      	3	; to 23
	20	[135]	GETUPVAL 	0 0	; self
	21	[135]	SETTABLE 	0 -6 -7	; "use_previous_search_results" true
	22	[135]	JMP      	2	; to 25
	23	[137]	GETUPVAL 	0 0	; self
	24	[137]	SETTABLE 	0 -6 -8	; "use_previous_search_results" false
	25	[139]	GETUPVAL 	0 0	; self
	26	[139]	SELF     	0 0 -9	; "close"
	27	[139]	CALL     	0 2 1
	28	[140]	RETURN   	0 1

function <./frontend/apps/filemanager/filemanagerfilesearcher.lua:145,154> (26 instructions, 104 bytes at 0x7fda4cc0a380)
0 params, 4 slots, 2 upvalues, 0 locals, 11 constants, 0 functions
	1	[146]	GETUPVAL 	0 0	; self
	2	[146]	GETGLOBAL	1 -2	; G_reader_settings
	3	[146]	SELF     	1 1 -3	; "readSetting"
	4	[146]	LOADK    	3 -4	; "home_dir"
	5	[146]	CALL     	1 3 2
	6	[146]	SETTABLE 	0 -1 1	; "path" -
	7	[147]	GETUPVAL 	0 0	; self
	8	[147]	GETUPVAL 	1 0	; self
	9	[147]	GETTABLE 	1 1 -6	; "search_dialog"
	10	[147]	SELF     	1 1 -7	; "getInputText"
	11	[147]	CALL     	1 2 2
	12	[147]	SETTABLE 	0 -5 1	; "search_value" -
	13	[148]	GETUPVAL 	0 0	; self
	14	[148]	GETTABLE 	0 0 -5	; "search_value"
	15	[148]	GETUPVAL 	1 1	; dummy
	16	[148]	EQ       	0 0 1
	17	[148]	JMP      	3	; to 21
	18	[149]	GETUPVAL 	0 0	; self
	19	[149]	SETTABLE 	0 -8 -9	; "use_previous_search_results" true
	20	[149]	JMP      	2	; to 23
	21	[151]	GETUPVAL 	0 0	; self
	22	[151]	SETTABLE 	0 -8 -10	; "use_previous_search_results" false
	23	[153]	GETUPVAL 	0 0	; self
	24	[153]	SELF     	0 0 -11	; "close"
	25	[153]	CALL     	0 2 1
	26	[154]	RETURN   	0 1

function <./frontend/apps/filemanager/filemanagerfilesearcher.lua:163,183> (67 instructions, 268 bytes at 0x7fda4cc0a610)
1 param, 8 slots, 6 upvalues, 2 locals, 28 constants, 2 functions
	1	[164]	GETUPVAL 	1 0	; CenterContainer
	2	[164]	SELF     	1 1 -1	; "new"
	3	[164]	NEWTABLE 	3 0 1
	4	[165]	GETUPVAL 	4 1	; Screen
	5	[165]	SELF     	4 4 -3	; "getSize"
	6	[165]	CALL     	4 2 2
	7	[165]	SETTABLE 	3 -2 4	; "dimen" -
	8	[164]	CALL     	1 3 2
	9	[167]	GETUPVAL 	2 2	; Menu
	10	[167]	SELF     	2 2 -1	; "new"
	11	[167]	NEWTABLE 	4 0 7
	12	[168]	GETUPVAL 	5 1	; Screen
	13	[168]	SELF     	5 5 -6	; "getWidth"
	14	[168]	CALL     	5 2 2
	15	[168]	SUB      	5 5 -7	; - 15
	16	[168]	SETTABLE 	4 -5 5	; "width" -
	17	[169]	GETUPVAL 	5 1	; Screen
	18	[169]	SELF     	5 5 -9	; "getHeight"
	19	[169]	CALL     	5 2 2
	20	[169]	SUB      	5 5 -7	; - 15
	21	[169]	SETTABLE 	4 -8 5	; "height" -
	22	[170]	SETTABLE 	4 -10 1	; "show_parent" -
	23	[171]	GETTABLE 	5 0 -11	; "onMenuHold"
	24	[171]	SETTABLE 	4 -11 5	; "onMenuHold" -
	25	[172]	GETUPVAL 	5 3	; Font
	26	[172]	SELF     	5 5 -13	; "getFace"
	27	[172]	LOADK    	7 -14	; "smallinfofont"
	28	[172]	CALL     	5 3 2
	29	[172]	SETTABLE 	4 -12 5	; "cface" -
	30	[173]	GETGLOBAL	5 -16	; G_reader_settings
	31	[173]	SELF     	5 5 -17	; "readSetting"
	32	[173]	LOADK    	7 -18	; "items_per_page"
	33	[173]	CALL     	5 3 2
	34	[173]	TEST     	5 0 1
	35	[173]	JMP      	1	; to 37
	36	[173]	LOADK    	5 -19	; 14
	37	[173]	SETTABLE 	4 -15 5	; "perpage" -
	38	[174]	SETTABLE 	4 -20 0	; "_manager" -
	39	[167]	CALL     	2 3 2
	40	[175]	SETTABLE 	0 -4 2	; "search_menu" -
	41	[176]	GETGLOBAL	2 -21	; table
	42	[176]	GETTABLE 	2 2 -22	; "insert"
	43	[176]	MOVE     	3 1
	44	[176]	GETTABLE 	4 0 -4	; "search_menu"
	45	[176]	CALL     	2 3 1
	46	[177]	GETTABLE 	2 0 -4	; "search_menu"
	47	[179]	CLOSURE  	3 0	; 0x7fda4cc0a1d0
	48	[179]	GETUPVAL 	0 4	; UIManager
	49	[179]	MOVE     	0 1
	50	[179]	SETTABLE 	2 -23 3	; "close_callback" -
	51	[180]	GETGLOBAL	2 -21	; table
	52	[180]	GETTABLE 	2 2 -24	; "sort"
	53	[180]	GETTABLE 	3 0 -25	; "results"
	54	[180]	CLOSURE  	4 1	; 0x7fda4cc0b350
	55	[180]	CALL     	2 3 1
	56	[181]	GETTABLE 	2 0 -4	; "search_menu"
	57	[181]	SELF     	2 2 -26	; "switchItemTable"
	58	[181]	GETUPVAL 	4 5	; _
	59	[181]	LOADK    	5 -27	; "Search Results"
	60	[181]	CALL     	4 2 2
	61	[181]	GETTABLE 	5 0 -25	; "results"
	62	[181]	CALL     	2 4 1
	63	[182]	GETUPVAL 	2 4	; UIManager
	64	[182]	SELF     	2 2 -28	; "show"
	65	[182]	MOVE     	4 1
	66	[182]	CALL     	2 3 1
	67	[183]	RETURN   	0 1

function <./frontend/apps/filemanager/filemanagerfilesearcher.lua:177,179> (5 instructions, 20 bytes at 0x7fda4cc0a1d0)
0 params, 3 slots, 2 upvalues, 0 locals, 1 constant, 0 functions
	1	[178]	GETUPVAL 	0 0	; UIManager
	2	[178]	SELF     	0 0 -1	; "close"
	3	[178]	GETUPVAL 	2 1	; menu_container
	4	[178]	CALL     	0 3 1
	5	[179]	RETURN   	0 1

function <./frontend/apps/filemanager/filemanagerfilesearcher.lua:180,180> (8 instructions, 32 bytes at 0x7fda4cc0b350)
2 params, 4 slots, 0 upvalues, 2 locals, 1 constant, 0 functions
	1	[180]	GETTABLE 	2 0 -1	; "text"
	2	[180]	GETTABLE 	3 1 -1	; "text"
	3	[180]	LT       	1 2 3
	4	[180]	JMP      	1	; to 6
	5	[180]	LOADBOOL 	2 0 1
	6	[180]	LOADBOOL 	2 1 0
	7	[180]	RETURN   	2 2
	8	[180]	RETURN   	0 1
