
main <./frontend/apps/filemanager/filemanagershortcuts.lua:0,0> (81 instructions, 324 bytes at 0x7f800bc06900)
0+ params, 14 slots, 0 upvalues, 12 locals, 23 constants, 9 functions
	1	[1]	GETGLOBAL	0 -1	; require
	2	[1]	LOADK    	1 -2	; "ui/bidi"
	3	[1]	CALL     	0 2 2
	4	[2]	GETGLOBAL	1 -1	; require
	5	[2]	LOADK    	2 -3	; "ui/widget/buttondialog"
	6	[2]	CALL     	1 2 2
	7	[3]	GETGLOBAL	2 -1	; require
	8	[3]	LOADK    	3 -4	; "ui/widget/infomessage"
	9	[3]	CALL     	2 2 2
	10	[4]	GETGLOBAL	3 -1	; require
	11	[4]	LOADK    	4 -5	; "ui/widget/container/inputcontainer"
	12	[4]	CALL     	3 2 2
	13	[5]	GETGLOBAL	4 -1	; require
	14	[5]	LOADK    	5 -6	; "ui/widget/inputdialog"
	15	[5]	CALL     	4 2 2
	16	[6]	GETGLOBAL	5 -1	; require
	17	[6]	LOADK    	6 -7	; "ui/widget/menu"
	18	[6]	CALL     	5 2 2
	19	[7]	GETGLOBAL	6 -1	; require
	20	[7]	LOADK    	7 -8	; "device"
	21	[7]	CALL     	6 2 2
	22	[7]	GETTABLE 	6 6 -9	; "screen"
	23	[8]	GETGLOBAL	7 -1	; require
	24	[8]	LOADK    	8 -10	; "ui/uimanager"
	25	[8]	CALL     	7 2 2
	26	[9]	GETGLOBAL	8 -1	; require
	27	[9]	LOADK    	9 -11	; "ffi/util"
	28	[9]	CALL     	8 2 2
	29	[10]	GETGLOBAL	9 -1	; require
	30	[10]	LOADK    	10 -12	; "gettext"
	31	[10]	CALL     	9 2 2
	32	[11]	GETGLOBAL	10 -1	; require
	33	[11]	LOADK    	11 -11	; "ffi/util"
	34	[11]	CALL     	10 2 2
	35	[11]	GETTABLE 	10 10 -13	; "template"
	36	[13]	SELF     	11 3 -14	; "extend"
	37	[13]	NEWTABLE 	13 0 0
	38	[13]	CALL     	11 3 2
	39	[62]	CLOSURE  	12 0	; 0x7f800bc070a0
	40	[62]	MOVE     	0 9
	41	[62]	MOVE     	0 7
	42	[15]	SETTABLE 	11 -15 12	; "updateItemTable" -
	43	[102]	CLOSURE  	12 1	; 0x7f800bc074c0
	44	[102]	MOVE     	0 8
	45	[102]	MOVE     	0 9
	46	[102]	MOVE     	0 4
	47	[102]	MOVE     	0 10
	48	[102]	MOVE     	0 0
	49	[102]	MOVE     	0 7
	50	[64]	SETTABLE 	11 -16 12	; "addNewFolder" -
	51	[120]	CLOSURE  	12 2	; 0x7f800bc06da0
	52	[120]	MOVE     	0 7
	53	[120]	MOVE     	0 2
	54	[120]	MOVE     	0 9
	55	[104]	SETTABLE 	11 -17 12	; "addFolderFromInput" -
	56	[158]	CLOSURE  	12 3	; 0x7f800bc09b40
	57	[158]	MOVE     	0 1
	58	[158]	MOVE     	0 9
	59	[158]	MOVE     	0 7
	60	[122]	SETTABLE 	11 -18 12	; "onMenuHold" -
	61	[188]	CLOSURE  	12 4	; 0x7f800bc0a840
	62	[188]	MOVE     	0 4
	63	[188]	MOVE     	0 9
	64	[188]	MOVE     	0 10
	65	[188]	MOVE     	0 0
	66	[188]	MOVE     	0 7
	67	[160]	SETTABLE 	11 -19 12	; "editFolderShortcut" -
	68	[200]	CLOSURE  	12 5	; 0x7f800bc0b6b0
	69	[190]	SETTABLE 	11 -20 12	; "renameFolderShortcut" -
	70	[211]	CLOSURE  	12 6	; 0x7f800bc07180
	71	[202]	SETTABLE 	11 -21 12	; "deleteFolderShortcut" -
	72	[215]	CLOSURE  	12 7	; 0x7f800bc0c600
	73	[213]	SETTABLE 	11 -22 12	; "onSetDimensions" -
	74	[234]	CLOSURE  	12 8	; 0x7f800bc0ca20
	75	[234]	MOVE     	0 5
	76	[234]	MOVE     	0 9
	77	[234]	MOVE     	0 6
	78	[234]	MOVE     	0 7
	79	[217]	SETTABLE 	11 -23 12	; "onShowFolderShortcutsDialog" -
	80	[236]	RETURN   	11 2
	81	[236]	RETURN   	0 1

function <./frontend/apps/filemanager/filemanagershortcuts.lua:15,62> (73 instructions, 292 bytes at 0x7f800bc070a0)
1 param, 15 slots, 2 upvalues, 9 locals, 22 constants, 2 functions
	1	[16]	NEWTABLE 	1 0 0
	2	[17]	GETGLOBAL	2 -1	; G_reader_settings
	3	[17]	SELF     	2 2 -2	; "readSetting"
	4	[17]	LOADK    	4 -3	; "folder_shortcuts"
	5	[17]	CALL     	2 3 2
	6	[17]	TEST     	2 0 1
	7	[17]	JMP      	1	; to 9
	8	[17]	NEWTABLE 	2 0 0
	9	[18]	GETGLOBAL	3 -4	; table
	10	[18]	GETTABLE 	3 3 -5	; "insert"
	11	[18]	MOVE     	4 1
	12	[18]	NEWTABLE 	5 0 2
	13	[19]	GETUPVAL 	6 0	; _
	14	[19]	LOADK    	7 -7	; "Add new folder shortcut"
	15	[19]	CALL     	6 2 2
	16	[19]	SETTABLE 	5 -6 6	; "text" -
	17	[22]	CLOSURE  	6 0	; 0x7f800bc07750
	18	[22]	MOVE     	0 0
	19	[22]	SETTABLE 	5 -8 6	; "callback" -
	20	[18]	CALL     	3 3 1
	21	[24]	GETGLOBAL	3 -9	; ipairs
	22	[24]	MOVE     	4 2
	23	[24]	CALL     	3 2 4
	24	[24]	JMP      	24	; to 49
	25	[25]	GETGLOBAL	8 -4	; table
	26	[25]	GETTABLE 	8 8 -5	; "insert"
	27	[25]	MOVE     	9 1
	28	[25]	NEWTABLE 	10 0 6
	29	[26]	GETGLOBAL	11 -10	; string
	30	[26]	GETTABLE 	11 11 -11	; "format"
	31	[26]	LOADK    	12 -12	; "%s (%s)"
	32	[26]	GETTABLE 	13 7 -6	; "text"
	33	[26]	GETTABLE 	14 7 -13	; "folder"
	34	[26]	CALL     	11 4 2
	35	[26]	SETTABLE 	10 -6 11	; "text" -
	36	[27]	GETTABLE 	11 7 -13	; "folder"
	37	[27]	SETTABLE 	10 -13 11	; "folder" -
	38	[28]	GETTABLE 	11 7 -6	; "text"
	39	[28]	SETTABLE 	10 -14 11	; "friendly_name" -
	40	[29]	SETTABLE 	10 -15 -16	; "deletable" true
	41	[30]	SETTABLE 	10 -17 -16	; "editable" true
	42	[49]	CLOSURE  	11 1	; 0x7f800bc079d0
	43	[49]	GETUPVAL 	0 1	; UIManager
	44	[49]	MOVE     	0 0
	45	[49]	MOVE     	0 7
	46	[49]	SETTABLE 	10 -8 11	; "callback" -
	47	[25]	CALL     	8 3 1
	48	[50]	CLOSE    	6
	49	[24]	TFORLOOP 	3 2
	50	[50]	JMP      	-26	; to 25
	51	[54]	LOADNIL  	3 3
	52	[56]	GETTABLE 	4 0 -18	; "fm_bookmark"
	53	[56]	GETTABLE 	4 4 -19	; "page"
	54	[56]	TEST     	4 0 0
	55	[56]	JMP      	11	; to 67
	56	[56]	GETTABLE 	4 0 -18	; "fm_bookmark"
	57	[56]	GETTABLE 	4 4 -20	; "perpage"
	58	[56]	TEST     	4 0 0
	59	[56]	JMP      	7	; to 67
	60	[57]	GETTABLE 	4 0 -18	; "fm_bookmark"
	61	[57]	GETTABLE 	4 4 -19	; "page"
	62	[57]	SUB      	4 4 -21	; - 1
	63	[57]	GETTABLE 	5 0 -18	; "fm_bookmark"
	64	[57]	GETTABLE 	5 5 -20	; "perpage"
	65	[57]	MUL      	4 4 5
	66	[57]	ADD      	3 4 -21	; - 1
	67	[60]	GETTABLE 	4 0 -18	; "fm_bookmark"
	68	[60]	SELF     	4 4 -22	; "switchItemTable"
	69	[60]	LOADNIL  	6 6
	70	[61]	MOVE     	7 1
	71	[61]	MOVE     	8 3
	72	[60]	CALL     	4 5 1
	73	[62]	RETURN   	0 1

function <./frontend/apps/filemanager/filemanagershortcuts.lua:20,22> (4 instructions, 16 bytes at 0x7f800bc07750)
0 params, 2 slots, 1 upvalue, 0 locals, 1 constant, 0 functions
	1	[21]	GETUPVAL 	0 0	; self
	2	[21]	SELF     	0 0 -1	; "addNewFolder"
	3	[21]	CALL     	0 2 1
	4	[22]	RETURN   	0 1

function <./frontend/apps/filemanager/filemanagershortcuts.lua:31,49> (47 instructions, 188 bytes at 0x7f800bc079d0)
0 params, 5 slots, 3 upvalues, 2 locals, 17 constants, 0 functions
	1	[32]	GETUPVAL 	0 0	; UIManager
	2	[32]	SELF     	0 0 -1	; "close"
	3	[32]	GETUPVAL 	2 1	; self
	4	[32]	GETTABLE 	2 2 -2	; "fm_bookmark"
	5	[32]	CALL     	0 3 1
	6	[34]	GETUPVAL 	0 2	; item
	7	[34]	GETTABLE 	0 0 -3	; "folder"
	8	[35]	EQ       	1 0 -4	; - nil
	9	[35]	JMP      	37	; to 47
	10	[35]	GETGLOBAL	1 -5	; lfs
	11	[35]	GETTABLE 	1 1 -6	; "attributes"
	12	[35]	MOVE     	2 0
	13	[35]	LOADK    	3 -7	; "mode"
	14	[35]	CALL     	1 3 2
	15	[35]	EQ       	0 1 -8	; - "directory"
	16	[35]	JMP      	30	; to 47
	17	[36]	GETUPVAL 	1 1	; self
	18	[36]	GETTABLE 	1 1 -9	; "ui"
	19	[36]	GETTABLE 	1 1 -10	; "file_chooser"
	20	[36]	TEST     	1 0 0
	21	[36]	JMP      	7	; to 29
	22	[37]	GETUPVAL 	1 1	; self
	23	[37]	GETTABLE 	1 1 -9	; "ui"
	24	[37]	GETTABLE 	1 1 -10	; "file_chooser"
	25	[37]	SELF     	1 1 -11	; "changeToPath"
	26	[37]	MOVE     	3 0
	27	[37]	CALL     	1 3 1
	28	[37]	JMP      	18	; to 47
	29	[39]	GETGLOBAL	1 -12	; require
	30	[39]	LOADK    	2 -13	; "apps/filemanager/filemanager"
	31	[39]	CALL     	1 2 2
	32	[41]	GETUPVAL 	2 1	; self
	33	[41]	GETTABLE 	2 2 -9	; "ui"
	34	[41]	SELF     	2 2 -14	; "onClose"
	35	[41]	CALL     	2 2 1
	36	[42]	GETTABLE 	2 1 -15	; "instance"
	37	[42]	TEST     	2 0 0
	38	[42]	JMP      	5	; to 44
	39	[43]	GETTABLE 	2 1 -15	; "instance"
	40	[43]	SELF     	2 2 -16	; "reinit"
	41	[43]	MOVE     	4 0
	42	[43]	CALL     	2 3 1
	43	[43]	JMP      	3	; to 47
	44	[45]	SELF     	2 1 -17	; "showFiles"
	45	[45]	MOVE     	4 0
	46	[45]	CALL     	2 3 1
	47	[49]	RETURN   	0 1

function <./frontend/apps/filemanager/filemanagershortcuts.lua:64,102> (25 instructions, 100 bytes at 0x7f800bc074c0)
1 param, 6 slots, 6 upvalues, 3 locals, 12 constants, 1 function
	1	[65]	GETGLOBAL	1 -1	; require
	2	[65]	LOADK    	2 -2	; "ui/widget/pathchooser"
	3	[65]	CALL     	1 2 2
	4	[66]	SELF     	2 1 -3	; "new"
	5	[66]	NEWTABLE 	4 0 4
	6	[67]	SETTABLE 	4 -4 -5	; "select_directory" true
	7	[68]	SETTABLE 	4 -6 -7	; "select_file" false
	8	[69]	GETTABLE 	5 0 -9	; "fm_bookmark"
	9	[69]	GETTABLE 	5 5 -10	; "curr_path"
	10	[69]	SETTABLE 	4 -8 5	; "path" -
	11	[99]	CLOSURE  	5 0	; 0x7f800bc08a40
	12	[99]	GETUPVAL 	0 0	; util
	13	[99]	GETUPVAL 	0 1	; _
	14	[99]	GETUPVAL 	0 2	; InputDialog
	15	[99]	MOVE     	0 0
	16	[99]	GETUPVAL 	0 3	; T
	17	[99]	GETUPVAL 	0 4	; BD
	18	[99]	GETUPVAL 	0 5	; UIManager
	19	[99]	SETTABLE 	4 -11 5	; "onConfirm" -
	20	[66]	CALL     	2 3 2
	21	[101]	GETUPVAL 	3 5	; UIManager
	22	[101]	SELF     	3 3 -12	; "show"
	23	[101]	MOVE     	5 2
	24	[101]	CALL     	3 3 1
	25	[102]	RETURN   	0 1

function <./frontend/apps/filemanager/filemanagershortcuts.lua:70,99> (62 instructions, 248 bytes at 0x7f800bc08a40)
1 param, 12 slots, 7 upvalues, 3 locals, 18 constants, 2 functions
	1	[72]	GETUPVAL 	2 0	; util
	2	[72]	GETTABLE 	2 2 -1	; "basename"
	3	[72]	MOVE     	3 0
	4	[72]	CALL     	2 2 2
	5	[72]	TEST     	2 0 1
	6	[72]	JMP      	3	; to 10
	7	[72]	GETUPVAL 	2 1	; _
	8	[72]	LOADK    	3 -2	; "my folder"
	9	[72]	CALL     	2 2 2
	10	[73]	GETUPVAL 	3 2	; InputDialog
	11	[73]	SELF     	3 3 -3	; "new"
	12	[73]	NEWTABLE 	5 0 5
	13	[74]	GETUPVAL 	6 3	; self
	14	[74]	GETTABLE 	6 6 -4	; "title"
	15	[74]	SETTABLE 	5 -4 6	; "title" -
	16	[75]	SETTABLE 	5 -5 2	; "input" -
	17	[76]	SETTABLE 	5 -6 -7	; "input_type" "text"
	18	[77]	GETUPVAL 	6 4	; T
	19	[77]	GETUPVAL 	7 1	; _
	20	[77]	LOADK    	8 -9	; "Title for selected folder:\n%1"
	21	[77]	CALL     	7 2 2
	22	[77]	GETUPVAL 	8 5	; BD
	23	[77]	GETTABLE 	8 8 -10	; "dirpath"
	24	[77]	MOVE     	9 0
	25	[77]	CALL     	8 2 0
	26	[77]	CALL     	6 0 2
	27	[77]	SETTABLE 	5 -8 6	; "description" -
	28	[78]	NEWTABLE 	6 1 0
	29	[78]	NEWTABLE 	7 2 0
	30	[79]	NEWTABLE 	8 0 2
	31	[81]	GETUPVAL 	9 1	; _
	32	[81]	LOADK    	10 -12	; "Cancel"
	33	[81]	CALL     	9 2 2
	34	[81]	SETTABLE 	8 -7 9	; "text" -
	35	[84]	CLOSURE  	9 0	; 0x7f800bc08d40
	36	[84]	GETUPVAL 	0 6	; UIManager
	37	[84]	MOVE     	0 1
	38	[84]	SETTABLE 	8 -13 9	; "callback" -
	39	[85]	NEWTABLE 	9 0 3
	40	[87]	GETUPVAL 	10 1	; _
	41	[87]	LOADK    	11 -14	; "Add"
	42	[87]	CALL     	10 2 2
	43	[87]	SETTABLE 	9 -7 10	; "text" -
	44	[88]	SETTABLE 	9 -15 -16	; "is_enter_default" true
	45	[92]	CLOSURE  	10 1	; 0x7f800bc091e0
	46	[92]	GETUPVAL 	0 3	; self
	47	[92]	MOVE     	0 1
	48	[92]	MOVE     	0 0
	49	[92]	GETUPVAL 	0 6	; UIManager
	50	[92]	SETTABLE 	9 -13 10	; "callback" -
	51	[94]	SETLIST  	7 2 1	; 1
	52	[95]	SETLIST  	6 1 1	; 1
	53	[95]	SETTABLE 	5 -11 6	; "buttons" -
	54	[73]	CALL     	3 3 2
	55	[96]	MOVE     	1 3
	56	[97]	GETUPVAL 	3 6	; UIManager
	57	[97]	SELF     	3 3 -17	; "show"
	58	[97]	MOVE     	5 1
	59	[97]	CALL     	3 3 1
	60	[98]	SELF     	3 1 -18	; "onShowKeyboard"
	61	[98]	CALL     	3 2 1
	62	[99]	RETURN   	0 1

function <./frontend/apps/filemanager/filemanagershortcuts.lua:82,84> (5 instructions, 20 bytes at 0x7f800bc08d40)
0 params, 3 slots, 2 upvalues, 0 locals, 1 constant, 0 functions
	1	[83]	GETUPVAL 	0 0	; UIManager
	2	[83]	SELF     	0 0 -1	; "close"
	3	[83]	GETUPVAL 	2 1	; add_folder_input
	4	[83]	CALL     	0 3 1
	5	[84]	RETURN   	0 1

function <./frontend/apps/filemanager/filemanagershortcuts.lua:89,92> (12 instructions, 48 bytes at 0x7f800bc091e0)
0 params, 4 slots, 4 upvalues, 0 locals, 3 constants, 0 functions
	1	[90]	GETUPVAL 	0 0	; self
	2	[90]	SELF     	0 0 -1	; "addFolderFromInput"
	3	[90]	GETUPVAL 	2 1	; add_folder_input
	4	[90]	SELF     	2 2 -2	; "getInputValue"
	5	[90]	CALL     	2 2 2
	6	[90]	GETUPVAL 	3 2	; path
	7	[90]	CALL     	0 4 1
	8	[91]	GETUPVAL 	0 3	; UIManager
	9	[91]	SELF     	0 0 -3	; "close"
	10	[91]	GETUPVAL 	2 1	; add_folder_input
	11	[91]	CALL     	0 3 1
	12	[92]	RETURN   	0 1

function <./frontend/apps/filemanager/filemanagershortcuts.lua:104,120> (52 instructions, 208 bytes at 0x7f800bc06da0)
3 params, 15 slots, 3 upvalues, 9 locals, 13 constants, 0 functions
	1	[105]	GETGLOBAL	3 -1	; ipairs
	2	[105]	GETGLOBAL	4 -2	; G_reader_settings
	3	[105]	SELF     	4 4 -3	; "readSetting"
	4	[105]	LOADK    	6 -4	; "folder_shortcuts"
	5	[105]	CALL     	4 3 2
	6	[105]	TEST     	4 0 1
	7	[105]	JMP      	1	; to 9
	8	[105]	NEWTABLE 	4 0 0
	9	[105]	CALL     	3 2 4
	10	[105]	JMP      	18	; to 29
	11	[106]	GETTABLE 	8 7 -5	; "text"
	12	[106]	EQ       	0 8 1
	13	[106]	JMP      	15	; to 29
	14	[106]	GETTABLE 	8 7 -6	; "folder"
	15	[106]	EQ       	0 8 2
	16	[106]	JMP      	12	; to 29
	17	[107]	GETUPVAL 	8 0	; UIManager
	18	[107]	SELF     	8 8 -7	; "show"
	19	[107]	GETUPVAL 	10 1	; InfoMessage
	20	[107]	SELF     	10 10 -8	; "new"
	21	[107]	NEWTABLE 	12 0 1
	22	[108]	GETUPVAL 	13 2	; _
	23	[108]	LOADK    	14 -9	; "A shortcut to this folder already exists."
	24	[108]	CALL     	13 2 2
	25	[108]	SETTABLE 	12 -5 13	; "text" -
	26	[107]	CALL     	10 3 0
	27	[107]	CALL     	8 0 1
	28	[110]	RETURN   	0 1
	29	[105]	TFORLOOP 	3 2
	30	[111]	JMP      	-20	; to 11
	31	[113]	GETGLOBAL	3 -2	; G_reader_settings
	32	[113]	SELF     	3 3 -3	; "readSetting"
	33	[113]	LOADK    	5 -4	; "folder_shortcuts"
	34	[113]	CALL     	3 3 2
	35	[113]	TEST     	3 0 1
	36	[113]	JMP      	1	; to 38
	37	[113]	NEWTABLE 	3 0 0
	38	[114]	GETGLOBAL	4 -10	; table
	39	[114]	GETTABLE 	4 4 -11	; "insert"
	40	[114]	MOVE     	5 3
	41	[114]	NEWTABLE 	6 0 2
	42	[115]	SETTABLE 	6 -5 1	; "text" -
	43	[116]	SETTABLE 	6 -6 2	; "folder" -
	44	[114]	CALL     	4 3 1
	45	[118]	GETGLOBAL	4 -2	; G_reader_settings
	46	[118]	SELF     	4 4 -12	; "saveSetting"
	47	[118]	LOADK    	6 -4	; "folder_shortcuts"
	48	[118]	MOVE     	7 3
	49	[118]	CALL     	4 4 1
	50	[119]	SELF     	4 0 -13	; "updateItemTable"
	51	[119]	CALL     	4 2 1
	52	[120]	RETURN   	0 1

function <./frontend/apps/filemanager/filemanagershortcuts.lua:122,158> (77 instructions, 308 bytes at 0x7f800bc09b40)
2 params, 13 slots, 3 upvalues, 3 locals, 15 constants, 3 functions
	1	[123]	GETTABLE 	2 1 -1	; "deletable"
	2	[123]	TEST     	2 0 1
	3	[123]	JMP      	3	; to 7
	4	[123]	GETTABLE 	2 1 -2	; "editable"
	5	[123]	TEST     	2 0 0
	6	[123]	JMP      	70	; to 77
	7	[124]	LOADNIL  	2 2
	8	[125]	GETUPVAL 	3 0	; ButtonDialog
	9	[125]	SELF     	3 3 -3	; "new"
	10	[125]	NEWTABLE 	5 0 1
	11	[126]	NEWTABLE 	6 1 0
	12	[126]	NEWTABLE 	7 3 0
	13	[127]	NEWTABLE 	8 0 3
	14	[129]	GETUPVAL 	9 1	; _
	15	[129]	LOADK    	10 -6	; "Paste file"
	16	[129]	CALL     	9 2 2
	17	[129]	SETTABLE 	8 -5 9	; "text" -
	18	[130]	GETTABLE 	9 0 -8	; "_manager"
	19	[130]	GETTABLE 	9 9 -9	; "ui"
	20	[130]	GETTABLE 	9 9 -10	; "file_chooser"
	21	[130]	TEST     	9 0 0
	22	[130]	JMP      	8	; to 31
	23	[130]	GETTABLE 	9 0 -8	; "_manager"
	24	[130]	GETTABLE 	9 9 -9	; "ui"
	25	[130]	GETTABLE 	9 9 -11	; "clipboard"
	26	[130]	TEST     	9 0 0
	27	[130]	JMP      	3	; to 31
	28	[130]	LOADBOOL 	9 1 0
	29	[130]	TEST     	9 0 1
	30	[130]	JMP      	1	; to 32
	31	[130]	LOADBOOL 	9 0 0
	32	[130]	SETTABLE 	8 -7 9	; "enabled" -
	33	[134]	CLOSURE  	9 0	; 0x7f800bc0a000
	34	[134]	GETUPVAL 	0 2	; UIManager
	35	[134]	MOVE     	0 2
	36	[134]	MOVE     	0 0
	37	[134]	MOVE     	0 1
	38	[134]	SETTABLE 	8 -12 9	; "callback" -
	39	[135]	NEWTABLE 	9 0 3
	40	[137]	GETUPVAL 	10 1	; _
	41	[137]	LOADK    	11 -13	; "Edit"
	42	[137]	CALL     	10 2 2
	43	[137]	SETTABLE 	9 -5 10	; "text" -
	44	[138]	GETTABLE 	10 1 -2	; "editable"
	45	[138]	SETTABLE 	9 -7 10	; "enabled" -
	46	[142]	CLOSURE  	10 1	; 0x7f800bc0a3c0
	47	[142]	GETUPVAL 	0 2	; UIManager
	48	[142]	MOVE     	0 2
	49	[142]	MOVE     	0 0
	50	[142]	MOVE     	0 1
	51	[142]	SETTABLE 	9 -12 10	; "callback" -
	52	[143]	NEWTABLE 	10 0 3
	53	[145]	GETUPVAL 	11 1	; _
	54	[145]	LOADK    	12 -14	; "Delete"
	55	[145]	CALL     	11 2 2
	56	[145]	SETTABLE 	10 -5 11	; "text" -
	57	[146]	GETTABLE 	11 1 -1	; "deletable"
	58	[146]	SETTABLE 	10 -7 11	; "enabled" -
	59	[150]	CLOSURE  	11 2	; 0x7f800bc0a500
	60	[150]	GETUPVAL 	0 2	; UIManager
	61	[150]	MOVE     	0 2
	62	[150]	MOVE     	0 0
	63	[150]	MOVE     	0 1
	64	[150]	SETTABLE 	10 -12 11	; "callback" -
	65	[152]	SETLIST  	7 3 1	; 1
	66	[153]	SETLIST  	6 1 1	; 1
	67	[153]	SETTABLE 	5 -4 6	; "buttons" -
	68	[125]	CALL     	3 3 2
	69	[154]	MOVE     	2 3
	70	[155]	GETUPVAL 	3 2	; UIManager
	71	[155]	SELF     	3 3 -15	; "show"
	72	[155]	MOVE     	5 2
	73	[155]	CALL     	3 3 1
	74	[156]	LOADBOOL 	3 1 0
	75	[156]	RETURN   	3 2
	76	[156]	CLOSE    	2
	77	[158]	RETURN   	0 1

function <./frontend/apps/filemanager/filemanagershortcuts.lua:131,134> (12 instructions, 48 bytes at 0x7f800bc0a000)
0 params, 3 slots, 4 upvalues, 0 locals, 5 constants, 0 functions
	1	[132]	GETUPVAL 	0 0	; UIManager
	2	[132]	SELF     	0 0 -1	; "close"
	3	[132]	GETUPVAL 	2 1	; folder_shortcuts_dialog
	4	[132]	CALL     	0 3 1
	5	[133]	GETUPVAL 	0 2	; self
	6	[133]	GETTABLE 	0 0 -2	; "_manager"
	7	[133]	GETTABLE 	0 0 -3	; "ui"
	8	[133]	SELF     	0 0 -4	; "pasteHere"
	9	[133]	GETUPVAL 	2 3	; item
	10	[133]	GETTABLE 	2 2 -5	; "folder"
	11	[133]	CALL     	0 3 1
	12	[134]	RETURN   	0 1

function <./frontend/apps/filemanager/filemanagershortcuts.lua:139,142> (10 instructions, 40 bytes at 0x7f800bc0a3c0)
0 params, 3 slots, 4 upvalues, 0 locals, 3 constants, 0 functions
	1	[140]	GETUPVAL 	0 0	; UIManager
	2	[140]	SELF     	0 0 -1	; "close"
	3	[140]	GETUPVAL 	2 1	; folder_shortcuts_dialog
	4	[140]	CALL     	0 3 1
	5	[141]	GETUPVAL 	0 2	; self
	6	[141]	GETTABLE 	0 0 -2	; "_manager"
	7	[141]	SELF     	0 0 -3	; "editFolderShortcut"
	8	[141]	GETUPVAL 	2 3	; item
	9	[141]	CALL     	0 3 1
	10	[142]	RETURN   	0 1

function <./frontend/apps/filemanager/filemanagershortcuts.lua:147,150> (10 instructions, 40 bytes at 0x7f800bc0a500)
0 params, 3 slots, 4 upvalues, 0 locals, 3 constants, 0 functions
	1	[148]	GETUPVAL 	0 0	; UIManager
	2	[148]	SELF     	0 0 -1	; "close"
	3	[148]	GETUPVAL 	2 1	; folder_shortcuts_dialog
	4	[148]	CALL     	0 3 1
	5	[149]	GETUPVAL 	0 2	; self
	6	[149]	GETTABLE 	0 0 -2	; "_manager"
	7	[149]	SELF     	0 0 -3	; "deleteFolderShortcut"
	8	[149]	GETUPVAL 	2 3	; item
	9	[149]	CALL     	0 3 1
	10	[150]	RETURN   	0 1

function <./frontend/apps/filemanager/filemanagershortcuts.lua:160,188> (55 instructions, 220 bytes at 0x7f800bc0a840)
2 params, 12 slots, 5 upvalues, 3 locals, 19 constants, 2 functions
	1	[162]	GETUPVAL 	3 0	; InputDialog
	2	[162]	SELF     	3 3 -1	; "new"
	3	[162]	NEWTABLE 	5 0 5
	4	[163]	GETUPVAL 	6 1	; _
	5	[163]	LOADK    	7 -3	; "Edit friendly name"
	6	[163]	CALL     	6 2 2
	7	[163]	SETTABLE 	5 -2 6	; "title" -
	8	[164]	GETTABLE 	6 1 -5	; "friendly_name"
	9	[164]	SETTABLE 	5 -4 6	; "input" -
	10	[165]	SETTABLE 	5 -6 -7	; "input_type" "text"
	11	[166]	GETUPVAL 	6 2	; T
	12	[166]	GETUPVAL 	7 1	; _
	13	[166]	LOADK    	8 -9	; "Rename title for selected folder:\n%1"
	14	[166]	CALL     	7 2 2
	15	[166]	GETUPVAL 	8 3	; BD
	16	[166]	GETTABLE 	8 8 -10	; "dirpath"
	17	[166]	GETTABLE 	9 1 -11	; "folder"
	18	[166]	CALL     	8 2 0
	19	[166]	CALL     	6 0 2
	20	[166]	SETTABLE 	5 -8 6	; "description" -
	21	[167]	NEWTABLE 	6 1 0
	22	[167]	NEWTABLE 	7 2 0
	23	[168]	NEWTABLE 	8 0 2
	24	[170]	GETUPVAL 	9 1	; _
	25	[170]	LOADK    	10 -13	; "Cancel"
	26	[170]	CALL     	9 2 2
	27	[170]	SETTABLE 	8 -7 9	; "text" -
	28	[173]	CLOSURE  	9 0	; 0x7f800bc0b3c0
	29	[173]	GETUPVAL 	0 4	; UIManager
	30	[173]	MOVE     	0 2
	31	[173]	SETTABLE 	8 -14 9	; "callback" -
	32	[174]	NEWTABLE 	9 0 3
	33	[176]	GETUPVAL 	10 1	; _
	34	[176]	LOADK    	11 -15	; "Apply"
	35	[176]	CALL     	10 2 2
	36	[176]	SETTABLE 	9 -7 10	; "text" -
	37	[177]	SETTABLE 	9 -16 -17	; "is_enter_default" true
	38	[181]	CLOSURE  	10 1	; 0x7f800bc0b340
	39	[181]	MOVE     	0 0
	40	[181]	MOVE     	0 1
	41	[181]	MOVE     	0 2
	42	[181]	GETUPVAL 	0 4	; UIManager
	43	[181]	SETTABLE 	9 -14 10	; "callback" -
	44	[183]	SETLIST  	7 2 1	; 1
	45	[184]	SETLIST  	6 1 1	; 1
	46	[184]	SETTABLE 	5 -12 6	; "buttons" -
	47	[162]	CALL     	3 3 2
	48	[185]	MOVE     	2 3
	49	[186]	GETUPVAL 	3 4	; UIManager
	50	[186]	SELF     	3 3 -18	; "show"
	51	[186]	MOVE     	5 2
	52	[186]	CALL     	3 3 1
	53	[187]	SELF     	3 2 -19	; "onShowKeyboard"
	54	[187]	CALL     	3 2 1
	55	[188]	RETURN   	0 1

function <./frontend/apps/filemanager/filemanagershortcuts.lua:171,173> (5 instructions, 20 bytes at 0x7f800bc0b3c0)
0 params, 3 slots, 2 upvalues, 0 locals, 1 constant, 0 functions
	1	[172]	GETUPVAL 	0 0	; UIManager
	2	[172]	SELF     	0 0 -1	; "close"
	3	[172]	GETUPVAL 	2 1	; edit_folder_input
	4	[172]	CALL     	0 3 1
	5	[173]	RETURN   	0 1

function <./frontend/apps/filemanager/filemanagershortcuts.lua:178,181> (12 instructions, 48 bytes at 0x7f800bc0b340)
0 params, 5 slots, 4 upvalues, 0 locals, 3 constants, 0 functions
	1	[179]	GETUPVAL 	0 0	; self
	2	[179]	SELF     	0 0 -1	; "renameFolderShortcut"
	3	[179]	GETUPVAL 	2 1	; item
	4	[179]	GETUPVAL 	3 2	; edit_folder_input
	5	[179]	SELF     	3 3 -2	; "getInputText"
	6	[179]	CALL     	3 2 0
	7	[179]	CALL     	0 0 1
	8	[180]	GETUPVAL 	0 3	; UIManager
	9	[180]	SELF     	0 0 -3	; "close"
	10	[180]	GETUPVAL 	2 2	; edit_folder_input
	11	[180]	CALL     	0 3 1
	12	[181]	RETURN   	0 1

function <./frontend/apps/filemanager/filemanagershortcuts.lua:190,200> (35 instructions, 140 bytes at 0x7f800bc0b6b0)
3 params, 12 slots, 0 upvalues, 9 locals, 11 constants, 0 functions
	1	[191]	NEWTABLE 	3 0 0
	2	[192]	GETGLOBAL	4 -1	; ipairs
	3	[192]	GETGLOBAL	5 -2	; G_reader_settings
	4	[192]	SELF     	5 5 -3	; "readSetting"
	5	[192]	LOADK    	7 -4	; "folder_shortcuts"
	6	[192]	CALL     	5 3 2
	7	[192]	TEST     	5 0 1
	8	[192]	JMP      	1	; to 10
	9	[192]	NEWTABLE 	5 0 0
	10	[192]	CALL     	4 2 4
	11	[192]	JMP      	14	; to 26
	12	[193]	GETTABLE 	9 8 -5	; "text"
	13	[193]	GETTABLE 	10 1 -6	; "friendly_name"
	14	[193]	EQ       	0 9 10
	15	[193]	JMP      	5	; to 21
	16	[193]	GETTABLE 	9 8 -7	; "folder"
	17	[193]	GETTABLE 	10 1 -7	; "folder"
	18	[193]	EQ       	0 9 10
	19	[193]	JMP      	1	; to 21
	20	[194]	SETTABLE 	8 -5 2	; "text" -
	21	[196]	GETGLOBAL	9 -8	; table
	22	[196]	GETTABLE 	9 9 -9	; "insert"
	23	[196]	MOVE     	10 3
	24	[196]	MOVE     	11 8
	25	[196]	CALL     	9 3 1
	26	[192]	TFORLOOP 	4 2
	27	[196]	JMP      	-16	; to 12
	28	[198]	GETGLOBAL	4 -2	; G_reader_settings
	29	[198]	SELF     	4 4 -10	; "saveSetting"
	30	[198]	LOADK    	6 -4	; "folder_shortcuts"
	31	[198]	MOVE     	7 3
	32	[198]	CALL     	4 4 1
	33	[199]	SELF     	4 0 -11	; "updateItemTable"
	34	[199]	CALL     	4 2 1
	35	[200]	RETURN   	0 1

function <./frontend/apps/filemanager/filemanagershortcuts.lua:202,211> (34 instructions, 136 bytes at 0x7f800bc07180)
2 params, 11 slots, 0 upvalues, 8 locals, 11 constants, 0 functions
	1	[203]	NEWTABLE 	2 0 0
	2	[204]	GETGLOBAL	3 -1	; ipairs
	3	[204]	GETGLOBAL	4 -2	; G_reader_settings
	4	[204]	SELF     	4 4 -3	; "readSetting"
	5	[204]	LOADK    	6 -4	; "folder_shortcuts"
	6	[204]	CALL     	4 3 2
	7	[204]	TEST     	4 0 1
	8	[204]	JMP      	1	; to 10
	9	[204]	NEWTABLE 	4 0 0
	10	[204]	CALL     	3 2 4
	11	[204]	JMP      	13	; to 25
	12	[205]	GETTABLE 	8 7 -5	; "text"
	13	[205]	GETTABLE 	9 1 -6	; "friendly_name"
	14	[205]	EQ       	0 8 9
	15	[205]	JMP      	4	; to 20
	16	[205]	GETTABLE 	8 7 -7	; "folder"
	17	[205]	GETTABLE 	9 1 -7	; "folder"
	18	[205]	EQ       	1 8 9
	19	[205]	JMP      	5	; to 25
	20	[206]	GETGLOBAL	8 -8	; table
	21	[206]	GETTABLE 	8 8 -9	; "insert"
	22	[206]	MOVE     	9 2
	23	[206]	MOVE     	10 7
	24	[206]	CALL     	8 3 1
	25	[204]	TFORLOOP 	3 2
	26	[207]	JMP      	-15	; to 12
	27	[209]	GETGLOBAL	3 -2	; G_reader_settings
	28	[209]	SELF     	3 3 -10	; "saveSetting"
	29	[209]	LOADK    	5 -4	; "folder_shortcuts"
	30	[209]	MOVE     	6 2
	31	[209]	CALL     	3 4 1
	32	[210]	SELF     	3 0 -11	; "updateItemTable"
	33	[210]	CALL     	3 2 1
	34	[211]	RETURN   	0 1

function <./frontend/apps/filemanager/filemanagershortcuts.lua:213,215> (2 instructions, 8 bytes at 0x7f800bc0c600)
2 params, 2 slots, 0 upvalues, 2 locals, 1 constant, 0 functions
	1	[214]	SETTABLE 	0 -1 1	; "dimen" -
	2	[215]	RETURN   	0 1

function <./frontend/apps/filemanager/filemanagershortcuts.lua:217,234> (47 instructions, 188 bytes at 0x7f800bc0ca20)
1 param, 6 slots, 4 upvalues, 1 local, 26 constants, 0 functions
	1	[218]	GETUPVAL 	1 0	; Menu
	2	[218]	SELF     	1 1 -2	; "new"
	3	[218]	NEWTABLE 	3 0 12
	4	[219]	GETUPVAL 	4 1	; _
	5	[219]	LOADK    	5 -4	; "Folder shortcuts"
	6	[219]	CALL     	4 2 2
	7	[219]	SETTABLE 	3 -3 4	; "title" -
	8	[220]	GETTABLE 	4 0 -6	; "ui"
	9	[220]	SETTABLE 	3 -5 4	; "show_parent" -
	10	[221]	GETUPVAL 	4 2	; Screen
	11	[221]	SELF     	4 4 -8	; "getWidth"
	12	[221]	CALL     	4 2 2
	13	[221]	SETTABLE 	3 -7 4	; "width" -
	14	[222]	GETUPVAL 	4 2	; Screen
	15	[222]	SELF     	4 4 -10	; "getHeight"
	16	[222]	CALL     	4 2 2
	17	[222]	SETTABLE 	3 -9 4	; "height" -
	18	[223]	SETTABLE 	3 -11 -12	; "no_title" false
	19	[224]	SETTABLE 	3 -13 -14	; "parent" nil
	20	[225]	SETTABLE 	3 -15 -16	; "has_close_button" true
	21	[226]	SETTABLE 	3 -17 -12	; "is_popout" false
	22	[227]	SETTABLE 	3 -18 -16	; "is_borderless" true
	23	[228]	GETTABLE 	4 0 -6	; "ui"
	24	[228]	GETTABLE 	4 4 -20	; "file_chooser"
	25	[228]	TEST     	4 0 0
	26	[228]	JMP      	5	; to 32
	27	[228]	GETTABLE 	4 0 -6	; "ui"
	28	[228]	GETTABLE 	4 4 -20	; "file_chooser"
	29	[228]	GETTABLE 	4 4 -21	; "path"
	30	[228]	TEST     	4 0 1
	31	[228]	JMP      	3	; to 35
	32	[228]	GETTABLE 	4 0 -6	; "ui"
	33	[228]	SELF     	4 4 -22	; "getLastDirFile"
	34	[228]	CALL     	4 2 2
	35	[228]	SETTABLE 	3 -19 4	; "curr_path" -
	36	[229]	GETTABLE 	4 0 -23	; "onMenuHold"
	37	[229]	SETTABLE 	3 -23 4	; "onMenuHold" -
	38	[230]	SETTABLE 	3 -24 0	; "_manager" -
	39	[218]	CALL     	1 3 2
	40	[231]	SETTABLE 	0 -1 1	; "fm_bookmark" -
	41	[232]	SELF     	1 0 -25	; "updateItemTable"
	42	[232]	CALL     	1 2 1
	43	[233]	GETUPVAL 	1 3	; UIManager
	44	[233]	SELF     	1 1 -26	; "show"
	45	[233]	GETTABLE 	3 0 -1	; "fm_bookmark"
	46	[233]	CALL     	1 3 1
	47	[234]	RETURN   	0 1
