
main <./frontend/ui/widget/fixedtextwidget.lua:0,0> (18 instructions, 72 bytes at 0x7fba554068f0)
0+ params, 5 slots, 0 upvalues, 3 locals, 6 constants, 2 functions
	1	[1]	GETGLOBAL	0 -1	; require
	2	[1]	LOADK    	1 -2	; "ui/widget/textwidget"
	3	[1]	CALL     	0 2 2
	4	[2]	GETGLOBAL	1 -1	; require
	5	[2]	LOADK    	2 -3	; "ui/geometry"
	6	[2]	CALL     	1 2 2
	7	[7]	SELF     	2 0 -4	; "new"
	8	[7]	NEWTABLE 	4 0 0
	9	[7]	CALL     	2 3 2
	10	[15]	CLOSURE  	3 0	; 0x7fba55406fb0
	11	[15]	MOVE     	0 0
	12	[9]	SETTABLE 	2 -5 3	; "updateSize" -
	13	[23]	CLOSURE  	3 1	; 0x7fba554071a0
	14	[23]	MOVE     	0 1
	15	[23]	MOVE     	0 0
	16	[17]	SETTABLE 	2 -6 3	; "getSize" -
	17	[25]	RETURN   	2 2
	18	[25]	RETURN   	0 1

function <./frontend/ui/widget/fixedtextwidget.lua:9,15> (11 instructions, 44 bytes at 0x7fba55406fb0)
1 param, 3 slots, 1 upvalue, 1 local, 5 constants, 0 functions
	1	[10]	GETUPVAL 	1 0	; TextWidget
	2	[10]	GETTABLE 	1 1 -1	; "updateSize"
	3	[10]	MOVE     	2 0
	4	[10]	CALL     	1 2 1
	5	[13]	GETTABLE 	1 0 -3	; "face"
	6	[13]	GETTABLE 	1 1 -4	; "size"
	7	[13]	SETTABLE 	0 -2 1	; "_height" -
	8	[14]	GETTABLE 	1 0 -3	; "face"
	9	[14]	GETTABLE 	1 1 -4	; "size"
	10	[14]	SETTABLE 	0 -5 1	; "_baseline_h" -
	11	[15]	RETURN   	0 1

function <./frontend/ui/widget/fixedtextwidget.lua:17,23> (16 instructions, 64 bytes at 0x7fba554071a0)
1 param, 4 slots, 2 upvalues, 1 local, 5 constants, 0 functions
	1	[18]	SELF     	1 0 -1	; "updateSize"
	2	[18]	CALL     	1 2 1
	3	[19]	GETTABLE 	1 0 -2	; "_length"
	4	[19]	EQ       	0 1 -3	; - 0
	5	[19]	JMP      	5	; to 11
	6	[20]	GETUPVAL 	1 0	; Geom
	7	[20]	SELF     	1 1 -4	; "new"
	8	[20]	NEWTABLE 	3 0 0
	9	[20]	TAILCALL 	1 3 0
	10	[20]	RETURN   	1 0
	11	[22]	GETUPVAL 	1 1	; TextWidget
	12	[22]	GETTABLE 	1 1 -5	; "getSize"
	13	[22]	MOVE     	2 0
	14	[22]	TAILCALL 	1 2 0
	15	[22]	RETURN   	1 0
	16	[23]	RETURN   	0 1
