-- BYTECODE -- fixedtextwidget.lua:9-15
0001    UGET     1   0      ; TextWidget
0002    TGETS    1   1   0  ; "updateSize"
0003    MOV      2   0
0004    CALL     1   1   2
0005    TGETS    1   0   2  ; "face"
0006    TGETS    1   1   3  ; "size"
0007    TSETS    1   0   1  ; "_height"
0008    TGETS    1   0   2  ; "face"
0009    TGETS    1   1   3  ; "size"
0010    TSETS    1   0   4  ; "_baseline_h"
0011    RET0     0   1

-- BYTECODE -- fixedtextwidget.lua:17-23
0001    MOV      2   0
0002    TGETS    1   0   0  ; "updateSize"
0003    CALL     1   1   2
0004    TGETS    1   0   1  ; "_length"
0005    ISNEN    1   0      ; 0
0006    JMP      1 => 0012
0007    UGET     1   0      ; Geom
0008    MOV      2   1
0009    TGETS    1   1   2  ; "new"
0010    TNEW     3   0
0011    CALLT    1   3
0012 => UGET     1   1      ; TextWidget
0013    TGETS    1   1   3  ; "getSize"
0014    MOV      2   0
0015    CALLT    1   2

-- BYTECODE -- fixedtextwidget.lua:0-26
0001    GGET     0   0      ; "require"
0002    KSTR     1   1      ; "ui/widget/textwidget"
0003    CALL     0   2   2
0004    GGET     1   0      ; "require"
0005    KSTR     2   2      ; "ui/geometry"
0006    CALL     1   2   2
0007    MOV      3   0
0008    TGETS    2   0   3  ; "new"
0009    TNEW     4   0
0010    CALL     2   2   3
0011    FNEW     3   5      ; fixedtextwidget.lua:9
0012    TSETS    3   2   4  ; "updateSize"
0013    FNEW     3   7      ; fixedtextwidget.lua:17
0014    TSETS    3   2   6  ; "getSize"
0015    UCLO     0 => 0016
0016 => RET1     2   2

