-- BYTECODE -- focusmanager_spec.lua:5-5
0001    MOV      2   0
0002    TGETS    1   0   0  ; "onFocusMove"
0003    TDUP     3   1
0004    CALL     1   1   3
0005    RET0     0   1

-- BYTECODE -- focusmanager_spec.lua:6-6
0001    MOV      2   0
0002    TGETS    1   0   0  ; "onFocusMove"
0003    TDUP     3   1
0004    CALL     1   1   3
0005    RET0     0   1

-- BYTECODE -- focusmanager_spec.lua:7-7
0001    MOV      2   0
0002    TGETS    1   0   0  ; "onFocusMove"
0003    TDUP     3   1
0004    CALL     1   1   3
0005    RET0     0   1

-- BYTECODE -- focusmanager_spec.lua:8-8
0001    MOV      2   0
0002    TGETS    1   0   0  ; "onFocusMove"
0003    TDUP     3   1
0004    CALL     1   1   3
0005    RET0     0   1

-- BYTECODE -- focusmanager_spec.lua:9-20
0001    GGET     0   0      ; "require"
0002    KSTR     1   1      ; "commonrequire"
0003    CALL     0   1   2
0004    GGET     0   0      ; "require"
0005    KSTR     1   2      ; "ui/widget/focusmanager"
0006    CALL     0   2   2
0007    USETV    0   0      ; FocusManager
0008    GGET     0   0      ; "require"
0009    KSTR     1   3      ; "ui/widget/textwidget"
0010    CALL     0   2   2
0011    MOV      2   0
0012    TGETS    1   0   4  ; "new"
0013    TNEW     3   0
0014    CALL     1   2   3
0015    TNEW     2   4
0016    TNEW     3   4
0017    TSETB    1   3   1
0018    TSETB    1   3   2
0019    TSETB    1   3   3
0020    TSETB    3   2   1
0021    TDUP     3   5
0022    TSETB    1   3   2
0023    TSETB    3   2   2
0024    TDUP     3   6
0025    TSETB    1   3   2
0026    TSETB    3   2   3
0027    USETV    1   2      ; layout
0028    RET0     0   1

-- BYTECODE -- focusmanager_spec.lua:21-27
0001    UGET     0   0      ; FocusManager
0002    MOV      1   0
0003    TGETS    0   0   0  ; "new"
0004    TNEW     2   0
0005    CALL     0   2   3
0006    UGET     1   1      ; layout
0007    TSETS    1   0   1  ; "layout"
0008    TDUP     1   3
0009    TSETS    1   0   2  ; "selected"
0010    UGET     1   2      ; Right
0011    MOV      2   0
0012    CALL     1   1   2
0013    GGET     1   4      ; "assert"
0014    TGETS    1   1   5  ; "are"
0015    TGETS    1   1   6  ; "same"
0016    TDUP     2   7
0017    TGETS    3   0   2  ; "selected"
0018    CALL     1   1   3
0019    RET0     0   1

-- BYTECODE -- focusmanager_spec.lua:28-34
0001    UGET     0   0      ; FocusManager
0002    MOV      1   0
0003    TGETS    0   0   0  ; "new"
0004    TNEW     2   0
0005    CALL     0   2   3
0006    UGET     1   1      ; layout
0007    TSETS    1   0   1  ; "layout"
0008    TDUP     1   3
0009    TSETS    1   0   2  ; "selected"
0010    UGET     1   2      ; Left
0011    MOV      2   0
0012    CALL     1   1   2
0013    GGET     1   4      ; "assert"
0014    TGETS    1   1   5  ; "are"
0015    TGETS    1   1   6  ; "same"
0016    TDUP     2   7
0017    TGETS    3   0   2  ; "selected"
0018    CALL     1   1   3
0019    RET0     0   1

-- BYTECODE -- focusmanager_spec.lua:35-41
0001    UGET     0   0      ; FocusManager
0002    MOV      1   0
0003    TGETS    0   0   0  ; "new"
0004    TNEW     2   0
0005    CALL     0   2   3
0006    UGET     1   1      ; layout
0007    TSETS    1   0   1  ; "layout"
0008    TDUP     1   3
0009    TSETS    1   0   2  ; "selected"
0010    UGET     1   2      ; Up
0011    MOV      2   0
0012    CALL     1   1   2
0013    GGET     1   4      ; "assert"
0014    TGETS    1   1   5  ; "are"
0015    TGETS    1   1   6  ; "same"
0016    TDUP     2   7
0017    TGETS    3   0   2  ; "selected"
0018    CALL     1   1   3
0019    RET0     0   1

-- BYTECODE -- focusmanager_spec.lua:42-48
0001    UGET     0   0      ; FocusManager
0002    MOV      1   0
0003    TGETS    0   0   0  ; "new"
0004    TNEW     2   0
0005    CALL     0   2   3
0006    UGET     1   1      ; layout
0007    TSETS    1   0   1  ; "layout"
0008    TDUP     1   3
0009    TSETS    1   0   2  ; "selected"
0010    UGET     1   2      ; Down
0011    MOV      2   0
0012    CALL     1   1   2
0013    GGET     1   4      ; "assert"
0014    TGETS    1   1   5  ; "are"
0015    TGETS    1   1   6  ; "same"
0016    TDUP     2   7
0017    TGETS    3   0   2  ; "selected"
0018    CALL     1   1   3
0019    RET0     0   1

-- BYTECODE -- focusmanager_spec.lua:49-55
0001    UGET     0   0      ; FocusManager
0002    MOV      1   0
0003    TGETS    0   0   0  ; "new"
0004    TNEW     2   0
0005    CALL     0   2   3
0006    UGET     1   1      ; layout
0007    TSETS    1   0   1  ; "layout"
0008    TDUP     1   3
0009    TSETS    1   0   2  ; "selected"
0010    UGET     1   2      ; Up
0011    MOV      2   0
0012    CALL     1   1   2
0013    GGET     1   4      ; "assert"
0014    TGETS    1   1   5  ; "are"
0015    TGETS    1   1   6  ; "same"
0016    TDUP     2   7
0017    TGETS    3   0   2  ; "selected"
0018    CALL     1   1   3
0019    RET0     0   1

-- BYTECODE -- focusmanager_spec.lua:56-62
0001    UGET     0   0      ; FocusManager
0002    MOV      1   0
0003    TGETS    0   0   0  ; "new"
0004    TNEW     2   0
0005    CALL     0   2   3
0006    UGET     1   1      ; layout
0007    TSETS    1   0   1  ; "layout"
0008    TDUP     1   3
0009    TSETS    1   0   2  ; "selected"
0010    UGET     1   2      ; Down
0011    MOV      2   0
0012    CALL     1   1   2
0013    GGET     1   4      ; "assert"
0014    TGETS    1   1   5  ; "are"
0015    TGETS    1   1   6  ; "same"
0016    TDUP     2   7
0017    TGETS    3   0   2  ; "selected"
0018    CALL     1   1   3
0019    RET0     0   1

-- BYTECODE -- focusmanager_spec.lua:63-69
0001    UGET     0   0      ; FocusManager
0002    MOV      1   0
0003    TGETS    0   0   0  ; "new"
0004    TNEW     2   0
0005    CALL     0   2   3
0006    UGET     1   1      ; layout
0007    TSETS    1   0   1  ; "layout"
0008    TDUP     1   3
0009    TSETS    1   0   2  ; "selected"
0010    UGET     1   2      ; Down
0011    MOV      2   0
0012    CALL     1   1   2
0013    GGET     1   4      ; "assert"
0014    TGETS    1   1   5  ; "are"
0015    TGETS    1   1   6  ; "same"
0016    TDUP     2   7
0017    TGETS    3   0   2  ; "selected"
0018    CALL     1   1   3
0019    RET0     0   1

-- BYTECODE -- focusmanager_spec.lua:70-76
0001    UGET     0   0      ; FocusManager
0002    MOV      1   0
0003    TGETS    0   0   0  ; "new"
0004    TNEW     2   0
0005    CALL     0   2   3
0006    UGET     1   1      ; layout
0007    TSETS    1   0   1  ; "layout"
0008    TDUP     1   3
0009    TSETS    1   0   2  ; "selected"
0010    UGET     1   2      ; Down
0011    MOV      2   0
0012    CALL     1   1   2
0013    GGET     1   4      ; "assert"
0014    TGETS    1   1   5  ; "are"
0015    TGETS    1   1   6  ; "same"
0016    TDUP     2   7
0017    TGETS    3   0   2  ; "selected"
0018    CALL     1   1   3
0019    RET0     0   1

-- BYTECODE -- focusmanager_spec.lua:77-83
0001    UGET     0   0      ; FocusManager
0002    MOV      1   0
0003    TGETS    0   0   0  ; "new"
0004    TNEW     2   0
0005    CALL     0   2   3
0006    UGET     1   1      ; layout
0007    TSETS    1   0   1  ; "layout"
0008    TDUP     1   3
0009    TSETS    1   0   2  ; "selected"
0010    UGET     1   2      ; Left
0011    MOV      2   0
0012    CALL     1   1   2
0013    GGET     1   4      ; "assert"
0014    TGETS    1   1   5  ; "are"
0015    TGETS    1   1   6  ; "same"
0016    TDUP     2   7
0017    TGETS    3   0   2  ; "selected"
0018    CALL     1   1   3
0019    RET0     0   1

-- BYTECODE -- focusmanager_spec.lua:84-90
0001    UGET     0   0      ; FocusManager
0002    MOV      1   0
0003    TGETS    0   0   0  ; "new"
0004    TNEW     2   0
0005    CALL     0   2   3
0006    UGET     1   1      ; layout
0007    TSETS    1   0   1  ; "layout"
0008    TDUP     1   3
0009    TSETS    1   0   2  ; "selected"
0010    UGET     1   2      ; Right
0011    MOV      2   0
0012    CALL     1   1   2
0013    GGET     1   4      ; "assert"
0014    TGETS    1   1   5  ; "are"
0015    TGETS    1   1   6  ; "same"
0016    TDUP     2   7
0017    TGETS    3   0   2  ; "selected"
0018    CALL     1   1   3
0019    RET0     0   1

-- BYTECODE -- focusmanager_spec.lua:1-91
0001    KNIL     0   5
0002    FNEW     2   0      ; focusmanager_spec.lua:5
0003    FNEW     3   1      ; focusmanager_spec.lua:6
0004    FNEW     4   2      ; focusmanager_spec.lua:7
0005    FNEW     5   3      ; focusmanager_spec.lua:8
0006    GGET     6   4      ; "setup"
0007    FNEW     7   5      ; focusmanager_spec.lua:9
0008    CALL     6   1   2
0009    GGET     6   6      ; "it"
0010    KSTR     7   7      ; "should go right"
0011    FNEW     8   8      ; focusmanager_spec.lua:21
0012    CALL     6   1   3
0013    GGET     6   6      ; "it"
0014    KSTR     7   9      ; "should go left"
0015    FNEW     8  10      ; focusmanager_spec.lua:28
0016    CALL     6   1   3
0017    GGET     6   6      ; "it"
0018    KSTR     7  11      ; "should go up"
0019    FNEW     8  12      ; focusmanager_spec.lua:35
0020    CALL     6   1   3
0021    GGET     6   6      ; "it"
0022    KSTR     7  13      ; "should go down"
0023    FNEW     8  14      ; focusmanager_spec.lua:42
0024    CALL     6   1   3
0025    GGET     6   6      ; "it"
0026    KSTR     7  15      ; "should vertical wrapAround up"
0027    FNEW     8  16      ; focusmanager_spec.lua:49
0028    CALL     6   1   3
0029    GGET     6   6      ; "it"
0030    KSTR     7  17      ; "should vertical wrapAround down"
0031    FNEW     8  18      ; focusmanager_spec.lua:56
0032    CALL     6   1   3
0033    GGET     6   6      ; "it"
0034    KSTR     7  19      ; "should do vertical step to the right"
0035    FNEW     8  20      ; focusmanager_spec.lua:63
0036    CALL     6   1   3
0037    GGET     6   6      ; "it"
0038    KSTR     7  21      ; "should do vertical step to the left"
0039    FNEW     8  22      ; focusmanager_spec.lua:70
0040    CALL     6   1   3
0041    GGET     6   6      ; "it"
0042    KSTR     7  23      ; "should respect left limit"
0043    FNEW     8  24      ; focusmanager_spec.lua:77
0044    CALL     6   1   3
0045    GGET     6   6      ; "it"
0046    KSTR     7  25      ; "should respect right limit"
0047    FNEW     8  26      ; focusmanager_spec.lua:84
0048    CALL     6   1   3
0049    UCLO     0 => 0050
0050 => RET0     0   1

-- BYTECODE -- focusmanager_spec.lua:0-92
0001    GGET     0   0      ; "describe"
0002    KSTR     1   1      ; "FocusManager module"
0003    FNEW     2   2      ; focusmanager_spec.lua:1
0004    CALL     0   1   3
0005    RET0     0   1

