
main <./frontend/ui/widget/focusmanager.lua:0,0> (41 instructions, 164 bytes at 0x7fb20f4068d0)
0+ params, 9 slots, 0 upvalues, 6 locals, 19 constants, 5 functions
	1	[1]	GETGLOBAL	0 -1	; require
	2	[1]	LOADK    	1 -2	; "device"
	3	[1]	CALL     	0 2 2
	4	[2]	GETGLOBAL	1 -1	; require
	5	[2]	LOADK    	2 -3	; "ui/event"
	6	[2]	CALL     	1 2 2
	7	[3]	GETGLOBAL	2 -1	; require
	8	[3]	LOADK    	3 -4	; "ui/widget/container/inputcontainer"
	9	[3]	CALL     	2 2 2
	10	[4]	GETGLOBAL	3 -1	; require
	11	[4]	LOADK    	4 -5	; "logger"
	12	[4]	CALL     	3 2 2
	13	[5]	GETGLOBAL	4 -1	; require
	14	[5]	LOADK    	5 -6	; "ui/uimanager"
	15	[5]	CALL     	4 2 2
	16	[27]	SELF     	5 2 -7	; "new"
	17	[27]	NEWTABLE 	7 0 3
	18	[28]	SETTABLE 	7 -8 -9	; "selected" nil
	19	[29]	SETTABLE 	7 -10 -9	; "layout" nil
	20	[30]	NEWTABLE 	8 0 2
	21	[30]	SETTABLE 	8 -12 -13	; "x" true
	22	[30]	SETTABLE 	8 -14 -13	; "y" true
	23	[30]	SETTABLE 	7 -11 8	; "movement_allowed" -
	24	[27]	CALL     	5 3 2
	25	[47]	CLOSURE  	6 0	; 0x7fb20f406bb0
	26	[47]	MOVE     	0 0
	27	[33]	SETTABLE 	5 -15 6	; "init" -
	28	[94]	CLOSURE  	6 1	; 0x7fb20f4072b0
	29	[94]	MOVE     	0 3
	30	[94]	MOVE     	0 1
	31	[94]	MOVE     	0 4
	32	[49]	SETTABLE 	5 -16 6	; "onFocusMove" -
	33	[113]	CLOSURE  	6 2	; 0x7fb20f407b70
	34	[96]	SETTABLE 	5 -17 6	; "_wrapAround" -
	35	[135]	CLOSURE  	6 3	; 0x7fb20f4070b0
	36	[135]	MOVE     	0 3
	37	[115]	SETTABLE 	5 -18 6	; "_verticalStep" -
	38	[139]	CLOSURE  	6 4	; 0x7fb20f407660
	39	[137]	SETTABLE 	5 -19 6	; "getFocusItem" -
	40	[141]	RETURN   	5 2
	41	[141]	RETURN   	0 1

function <./frontend/ui/widget/focusmanager.lua:33,47> (67 instructions, 268 bytes at 0x7fb20f406bb0)
1 param, 7 slots, 1 upvalue, 1 local, 24 constants, 0 functions
	1	[34]	GETTABLE 	1 0 -1	; "selected"
	2	[34]	TEST     	1 0 1
	3	[34]	JMP      	4	; to 8
	4	[35]	NEWTABLE 	1 0 2
	5	[35]	SETTABLE 	1 -2 -3	; "x" 1
	6	[35]	SETTABLE 	1 -4 -3	; "y" 1
	7	[35]	SETTABLE 	0 -1 1	; "selected" -
	8	[38]	GETUPVAL 	1 0	; Device
	9	[38]	SELF     	1 1 -5	; "hasDPad"
	10	[38]	CALL     	1 2 2
	11	[38]	TEST     	1 0 0
	12	[38]	JMP      	54	; to 67
	13	[39]	NEWTABLE 	1 0 4
	14	[41]	NEWTABLE 	2 1 3
	15	[41]	NEWTABLE 	3 1 0
	16	[41]	LOADK    	4 -8	; "Up"
	17	[41]	SETLIST  	3 1 1	; 1
	18	[41]	SETTABLE 	2 -9 -10	; "doc" "move focus up"
	19	[41]	SETTABLE 	2 -11 -12	; "event" "FocusMove"
	20	[41]	NEWTABLE 	4 2 0
	21	[41]	LOADK    	5 -14	; 0
	22	[41]	LOADK    	6 -15	; -1
	23	[41]	SETLIST  	4 2 1	; 1
	24	[41]	SETTABLE 	2 -13 4	; "args" -
	25	[41]	SETLIST  	2 1 1	; 1
	26	[41]	SETTABLE 	1 -7 2	; "FocusUp" -
	27	[42]	NEWTABLE 	2 1 3
	28	[42]	NEWTABLE 	3 1 0
	29	[42]	LOADK    	4 -17	; "Down"
	30	[42]	SETLIST  	3 1 1	; 1
	31	[42]	SETTABLE 	2 -9 -18	; "doc" "move focus down"
	32	[42]	SETTABLE 	2 -11 -12	; "event" "FocusMove"
	33	[42]	NEWTABLE 	4 2 0
	34	[42]	LOADK    	5 -14	; 0
	35	[42]	LOADK    	6 -3	; 1
	36	[42]	SETLIST  	4 2 1	; 1
	37	[42]	SETTABLE 	2 -13 4	; "args" -
	38	[42]	SETLIST  	2 1 1	; 1
	39	[42]	SETTABLE 	1 -16 2	; "FocusDown" -
	40	[43]	NEWTABLE 	2 1 3
	41	[43]	NEWTABLE 	3 1 0
	42	[43]	LOADK    	4 -20	; "Left"
	43	[43]	SETLIST  	3 1 1	; 1
	44	[43]	SETTABLE 	2 -9 -21	; "doc" "move focus left"
	45	[43]	SETTABLE 	2 -11 -12	; "event" "FocusMove"
	46	[43]	NEWTABLE 	4 2 0
	47	[43]	LOADK    	5 -15	; -1
	48	[43]	LOADK    	6 -14	; 0
	49	[43]	SETLIST  	4 2 1	; 1
	50	[43]	SETTABLE 	2 -13 4	; "args" -
	51	[43]	SETLIST  	2 1 1	; 1
	52	[43]	SETTABLE 	1 -19 2	; "FocusLeft" -
	53	[44]	NEWTABLE 	2 1 3
	54	[44]	NEWTABLE 	3 1 0
	55	[44]	LOADK    	4 -23	; "Right"
	56	[44]	SETLIST  	3 1 1	; 1
	57	[44]	SETTABLE 	2 -9 -24	; "doc" "move focus right"
	58	[44]	SETTABLE 	2 -11 -12	; "event" "FocusMove"
	59	[44]	NEWTABLE 	4 2 0
	60	[44]	LOADK    	5 -3	; 1
	61	[44]	LOADK    	6 -14	; 0
	62	[44]	SETLIST  	4 2 1	; 1
	63	[44]	SETTABLE 	2 -13 4	; "args" -
	64	[44]	SETLIST  	2 1 1	; 1
	65	[44]	SETTABLE 	1 -22 2	; "FocusRight" -
	66	[45]	SETTABLE 	0 -6 1	; "key_events" -
	67	[47]	RETURN   	0 1

function <./frontend/ui/widget/focusmanager.lua:49,94> (159 instructions, 636 bytes at 0x7fb20f4072b0)
2 params, 10 slots, 3 upvalues, 5 locals, 20 constants, 0 functions
	1	[50]	GETGLOBAL	2 -1	; unpack
	2	[50]	MOVE     	3 1
	3	[50]	CALL     	2 2 3
	4	[52]	EQ       	1 2 -2	; - 0
	5	[52]	JMP      	4	; to 10
	6	[52]	GETTABLE 	4 0 -3	; "movement_allowed"
	7	[52]	GETTABLE 	4 4 -4	; "x"
	8	[53]	TEST     	4 0 0
	9	[53]	JMP      	6	; to 16
	10	[53]	EQ       	1 3 -2	; - 0
	11	[53]	JMP      	6	; to 18
	12	[53]	GETTABLE 	4 0 -3	; "movement_allowed"
	13	[53]	GETTABLE 	4 4 -5	; "y"
	14	[53]	TEST     	4 0 1
	15	[53]	JMP      	2	; to 18
	16	[54]	LOADBOOL 	4 1 0
	17	[54]	RETURN   	4 2
	18	[57]	GETTABLE 	4 0 -6	; "layout"
	19	[57]	TEST     	4 0 0
	20	[57]	JMP      	15	; to 36
	21	[57]	GETTABLE 	4 0 -6	; "layout"
	22	[57]	GETTABLE 	5 0 -7	; "selected"
	23	[57]	GETTABLE 	5 5 -5	; "y"
	24	[57]	GETTABLE 	4 4 5
	25	[57]	TEST     	4 0 0
	26	[57]	JMP      	9	; to 36
	27	[57]	GETTABLE 	4 0 -6	; "layout"
	28	[57]	GETTABLE 	5 0 -7	; "selected"
	29	[57]	GETTABLE 	5 5 -5	; "y"
	30	[57]	GETTABLE 	4 4 5
	31	[57]	GETTABLE 	5 0 -7	; "selected"
	32	[57]	GETTABLE 	5 5 -4	; "x"
	33	[57]	GETTABLE 	4 4 5
	34	[57]	TEST     	4 0 1
	35	[57]	JMP      	2	; to 38
	36	[58]	LOADBOOL 	4 1 0
	37	[58]	RETURN   	4 2
	38	[60]	GETTABLE 	4 0 -6	; "layout"
	39	[60]	GETTABLE 	5 0 -7	; "selected"
	40	[60]	GETTABLE 	5 5 -5	; "y"
	41	[60]	GETTABLE 	4 4 5
	42	[60]	GETTABLE 	5 0 -7	; "selected"
	43	[60]	GETTABLE 	5 5 -4	; "x"
	44	[60]	GETTABLE 	4 4 5
	45	[62]	GETTABLE 	5 0 -6	; "layout"
	46	[62]	GETTABLE 	6 0 -7	; "selected"
	47	[62]	GETTABLE 	6 6 -5	; "y"
	48	[62]	ADD      	6 6 3
	49	[62]	GETTABLE 	5 5 6
	50	[62]	TEST     	5 0 1
	51	[62]	JMP      	7	; to 59
	52	[64]	SELF     	5 0 -8	; "_wrapAround"
	53	[64]	MOVE     	7 3
	54	[64]	CALL     	5 3 2
	55	[64]	TEST     	5 0 1
	56	[64]	JMP      	42	; to 99
	57	[65]	JMP      	99	; to 157
	58	[66]	JMP      	40	; to 99
	59	[67]	GETTABLE 	5 0 -6	; "layout"
	60	[67]	GETTABLE 	6 0 -7	; "selected"
	61	[67]	GETTABLE 	6 6 -5	; "y"
	62	[67]	ADD      	6 6 3
	63	[67]	GETTABLE 	5 5 6
	64	[67]	GETTABLE 	6 0 -7	; "selected"
	65	[67]	GETTABLE 	6 6 -4	; "x"
	66	[67]	GETTABLE 	5 5 6
	67	[67]	TEST     	5 0 1
	68	[67]	JMP      	7	; to 76
	69	[69]	SELF     	5 0 -9	; "_verticalStep"
	70	[69]	MOVE     	7 3
	71	[69]	CALL     	5 3 2
	72	[69]	TEST     	5 0 1
	73	[69]	JMP      	25	; to 99
	74	[70]	JMP      	82	; to 157
	75	[71]	JMP      	23	; to 99
	76	[72]	GETTABLE 	5 0 -6	; "layout"
	77	[72]	GETTABLE 	6 0 -7	; "selected"
	78	[72]	GETTABLE 	6 6 -5	; "y"
	79	[72]	ADD      	6 6 3
	80	[72]	GETTABLE 	5 5 6
	81	[72]	GETTABLE 	6 0 -7	; "selected"
	82	[72]	GETTABLE 	6 6 -4	; "x"
	83	[72]	ADD      	6 6 2
	84	[72]	GETTABLE 	5 5 6
	85	[72]	TEST     	5 0 1
	86	[72]	JMP      	2	; to 89
	87	[74]	JMP      	69	; to 157
	88	[74]	JMP      	10	; to 99
	89	[76]	GETTABLE 	5 0 -7	; "selected"
	90	[76]	GETTABLE 	6 0 -7	; "selected"
	91	[76]	GETTABLE 	6 6 -5	; "y"
	92	[76]	ADD      	6 6 3
	93	[76]	SETTABLE 	5 -5 6	; "y" -
	94	[77]	GETTABLE 	5 0 -7	; "selected"
	95	[77]	GETTABLE 	6 0 -7	; "selected"
	96	[77]	GETTABLE 	6 6 -4	; "x"
	97	[77]	ADD      	6 6 2
	98	[77]	SETTABLE 	5 -4 6	; "x" -
	99	[79]	GETUPVAL 	5 0	; logger
	100	[79]	GETTABLE 	5 5 -10	; "dbg"
	101	[79]	LOADK    	6 -11	; "Cursor position : "
	102	[79]	GETTABLE 	7 0 -7	; "selected"
	103	[79]	GETTABLE 	7 7 -5	; "y"
	104	[79]	LOADK    	8 -12	; " : "
	105	[79]	GETTABLE 	9 0 -7	; "selected"
	106	[79]	GETTABLE 	9 9 -4	; "x"
	107	[79]	CONCAT   	6 6 9
	108	[79]	CALL     	5 2 1
	109	[81]	GETTABLE 	5 0 -6	; "layout"
	110	[81]	GETTABLE 	6 0 -7	; "selected"
	111	[81]	GETTABLE 	6 6 -5	; "y"
	112	[81]	GETTABLE 	5 5 6
	113	[81]	GETTABLE 	6 0 -7	; "selected"
	114	[81]	GETTABLE 	6 6 -4	; "x"
	115	[81]	GETTABLE 	5 5 6
	116	[81]	EQ       	0 5 4
	117	[81]	JMP      	10	; to 128
	118	[82]	GETTABLE 	5 0 -6	; "layout"
	119	[82]	GETTABLE 	6 0 -7	; "selected"
	120	[82]	GETTABLE 	6 6 -5	; "y"
	121	[82]	GETTABLE 	5 5 6
	122	[82]	GETTABLE 	6 0 -7	; "selected"
	123	[82]	GETTABLE 	6 6 -4	; "x"
	124	[82]	GETTABLE 	5 5 6
	125	[82]	GETTABLE 	5 5 -13	; "is_inactive"
	126	[82]	TEST     	5 0 1
	127	[82]	JMP      	-83	; to 45
	128	[84]	SELF     	5 4 -14	; "handleEvent"
	129	[84]	GETUPVAL 	7 1	; Event
	130	[84]	SELF     	7 7 -15	; "new"
	131	[84]	LOADK    	9 -16	; "Unfocus"
	132	[84]	CALL     	7 3 0
	133	[84]	CALL     	5 0 1
	134	[85]	GETTABLE 	5 0 -6	; "layout"
	135	[85]	GETTABLE 	6 0 -7	; "selected"
	136	[85]	GETTABLE 	6 6 -5	; "y"
	137	[85]	GETTABLE 	5 5 6
	138	[85]	GETTABLE 	6 0 -7	; "selected"
	139	[85]	GETTABLE 	6 6 -4	; "x"
	140	[85]	GETTABLE 	5 5 6
	141	[85]	SELF     	5 5 -14	; "handleEvent"
	142	[85]	GETUPVAL 	7 1	; Event
	143	[85]	SELF     	7 7 -15	; "new"
	144	[85]	LOADK    	9 -17	; "Focus"
	145	[85]	CALL     	7 3 0
	146	[85]	CALL     	5 0 1
	147	[89]	GETUPVAL 	5 2	; UIManager
	148	[89]	SELF     	5 5 -18	; "setDirty"
	149	[89]	GETTABLE 	7 0 -19	; "show_parent"
	150	[89]	TEST     	7 0 1
	151	[89]	JMP      	1	; to 153
	152	[89]	MOVE     	7 0
	153	[89]	LOADK    	8 -20	; "fast"
	154	[89]	CALL     	5 4 1
	155	[90]	JMP      	1	; to 157
	156	[91]	JMP      	-112	; to 45
	157	[93]	LOADBOOL 	5 1 0
	158	[93]	RETURN   	5 2
	159	[94]	RETURN   	0 1

function <./frontend/ui/widget/focusmanager.lua:96,113> (34 instructions, 136 bytes at 0x7fb20f407b70)
2 params, 6 slots, 0 upvalues, 3 locals, 6 constants, 0 functions
	1	[99]	GETTABLE 	2 0 -1	; "selected"
	2	[99]	GETTABLE 	2 2 -2	; "y"
	3	[100]	GETTABLE 	3 0 -3	; "layout"
	4	[100]	SUB      	4 2 1
	5	[100]	GETTABLE 	3 3 4
	6	[100]	TEST     	3 0 0
	7	[100]	JMP      	2	; to 10
	8	[101]	SUB      	2 2 1
	9	[101]	JMP      	-7	; to 3
	10	[103]	GETTABLE 	3 0 -1	; "selected"
	11	[103]	GETTABLE 	3 3 -2	; "y"
	12	[103]	EQ       	1 2 3
	13	[103]	JMP      	18	; to 32
	14	[104]	GETTABLE 	3 0 -1	; "selected"
	15	[104]	SETTABLE 	3 -2 2	; "y" -
	16	[105]	GETTABLE 	3 0 -3	; "layout"
	17	[105]	GETTABLE 	4 0 -1	; "selected"
	18	[105]	GETTABLE 	4 4 -2	; "y"
	19	[105]	GETTABLE 	3 3 4
	20	[105]	GETTABLE 	4 0 -1	; "selected"
	21	[105]	GETTABLE 	4 4 -4	; "x"
	22	[105]	GETTABLE 	3 3 4
	23	[105]	TEST     	3 0 1
	24	[105]	JMP      	4	; to 29
	25	[107]	SELF     	3 0 -5	; "_verticalStep"
	26	[107]	LOADK    	5 -6	; 0
	27	[107]	TAILCALL 	3 3 0
	28	[107]	RETURN   	3 0
	29	[109]	LOADBOOL 	3 1 0
	30	[109]	RETURN   	3 2
	31	[109]	JMP      	2	; to 34
	32	[111]	LOADBOOL 	3 0 0
	33	[111]	RETURN   	3 2
	34	[113]	RETURN   	0 1

function <./frontend/ui/widget/focusmanager.lua:115,135> (59 instructions, 236 bytes at 0x7fb20f4070b0)
2 params, 6 slots, 1 upvalue, 3 locals, 10 constants, 0 functions
	1	[116]	GETTABLE 	2 0 -1	; "selected"
	2	[116]	GETTABLE 	2 2 -2	; "x"
	3	[117]	GETGLOBAL	3 -3	; type
	4	[117]	GETTABLE 	4 0 -4	; "layout"
	5	[117]	GETTABLE 	5 0 -1	; "selected"
	6	[117]	GETTABLE 	5 5 -5	; "y"
	7	[117]	ADD      	5 5 1
	8	[117]	GETTABLE 	4 4 5
	9	[117]	CALL     	3 2 2
	10	[117]	EQ       	0 3 -6	; - "table"
	11	[117]	JMP      	8	; to 20
	12	[117]	GETTABLE 	3 0 -4	; "layout"
	13	[117]	GETTABLE 	4 0 -1	; "selected"
	14	[117]	GETTABLE 	4 4 -5	; "y"
	15	[117]	ADD      	4 4 1
	16	[117]	GETTABLE 	3 3 4
	17	[117]	NEWTABLE 	4 0 0
	18	[117]	EQ       	0 3 4
	19	[117]	JMP      	6	; to 26
	20	[118]	GETUPVAL 	3 0	; logger
	21	[118]	GETTABLE 	3 3 -7	; "err"
	22	[118]	LOADK    	4 -8	; "[FocusManager] : Malformed layout"
	23	[118]	CALL     	3 2 1
	24	[119]	LOADBOOL 	3 0 0
	25	[119]	RETURN   	3 2
	26	[122]	GETTABLE 	3 0 -4	; "layout"
	27	[122]	GETTABLE 	4 0 -1	; "selected"
	28	[122]	GETTABLE 	4 4 -5	; "y"
	29	[122]	ADD      	4 4 1
	30	[122]	GETTABLE 	3 3 4
	31	[122]	GETTABLE 	3 3 2
	32	[122]	TEST     	3 0 1
	33	[122]	JMP      	16	; to 50
	34	[123]	SUB      	2 2 -9	; - 1
	35	[124]	EQ       	0 2 -10	; - 0
	36	[124]	JMP      	-11	; to 26
	37	[126]	GETTABLE 	3 0 -1	; "selected"
	38	[126]	GETTABLE 	2 3 -2	; "x"
	39	[127]	GETTABLE 	3 0 -4	; "layout"
	40	[127]	GETTABLE 	4 0 -1	; "selected"
	41	[127]	GETTABLE 	4 4 -5	; "y"
	42	[127]	ADD      	4 4 1
	43	[127]	GETTABLE 	3 3 4
	44	[127]	GETTABLE 	3 3 2
	45	[127]	TEST     	3 0 1
	46	[127]	JMP      	-21	; to 26
	47	[128]	ADD      	2 2 -9	; - 1
	48	[128]	JMP      	-10	; to 39
	49	[130]	JMP      	-24	; to 26
	50	[132]	GETTABLE 	3 0 -1	; "selected"
	51	[132]	SETTABLE 	3 -2 2	; "x" -
	52	[133]	GETTABLE 	3 0 -1	; "selected"
	53	[133]	GETTABLE 	4 0 -1	; "selected"
	54	[133]	GETTABLE 	4 4 -5	; "y"
	55	[133]	ADD      	4 4 1
	56	[133]	SETTABLE 	3 -5 4	; "y" -
	57	[134]	LOADBOOL 	3 1 0
	58	[134]	RETURN   	3 2
	59	[135]	RETURN   	0 1

function <./frontend/ui/widget/focusmanager.lua:137,139> (9 instructions, 36 bytes at 0x7fb20f407660)
1 param, 3 slots, 0 upvalues, 1 local, 4 constants, 0 functions
	1	[138]	GETTABLE 	1 0 -1	; "layout"
	2	[138]	GETTABLE 	2 0 -2	; "selected"
	3	[138]	GETTABLE 	2 2 -3	; "y"
	4	[138]	GETTABLE 	1 1 2
	5	[138]	GETTABLE 	2 0 -2	; "selected"
	6	[138]	GETTABLE 	2 2 -4	; "x"
	7	[138]	GETTABLE 	1 1 2
	8	[138]	RETURN   	1 2
	9	[139]	RETURN   	0 1
