-- BYTECODE -- font_spec.lua:3-6
0001    GGET     0   0      ; "require"
0002    KSTR     1   1      ; "commonrequire"
0003    CALL     0   1   2
0004    GGET     0   0      ; "require"
0005    KSTR     1   2      ; "ui/font"
0006    CALL     0   2   2
0007    USETV    0   0      ; Font
0008    RET0     0   1

-- BYTECODE -- font_spec.lua:7-15
0001    KPRI     0   0
0002    UGET     1   0      ; Font
0003    MOV      2   1
0004    TGETS    1   1   0  ; "getFace"
0005    KSTR     3   1      ; "cfont"
0006    KSHORT   4  18
0007    CALL     1   2   4
0008    MOV      0   1
0009    GGET     1   2      ; "assert"
0010    TGETS    1   1   3  ; "are_not"
0011    TGETS    1   1   4  ; "equals"
0012    TGETS    2   0   5  ; "ftface"
0013    KPRI     3   0
0014    CALL     1   1   3
0015    UGET     1   0      ; Font
0016    MOV      2   1
0017    TGETS    1   1   0  ; "getFace"
0018    KSTR     3   6      ; "tfont"
0019    KSHORT   4  16
0020    CALL     1   2   4
0021    MOV      0   1
0022    GGET     1   2      ; "assert"
0023    TGETS    1   1   3  ; "are_not"
0024    TGETS    1   1   4  ; "equals"
0025    TGETS    2   0   5  ; "ftface"
0026    KPRI     3   0
0027    CALL     1   1   3
0028    UGET     1   0      ; Font
0029    MOV      2   1
0030    TGETS    1   1   0  ; "getFace"
0031    KSTR     3   7      ; "hfont"
0032    KSHORT   4  12
0033    CALL     1   2   4
0034    MOV      0   1
0035    GGET     1   2      ; "assert"
0036    TGETS    1   1   3  ; "are_not"
0037    TGETS    1   1   4  ; "equals"
0038    TGETS    2   0   5  ; "ftface"
0039    KPRI     3   0
0040    CALL     1   1   3
0041    RET0     0   1

-- BYTECODE -- font_spec.lua:1-16
0001    KPRI     0   0
0002    GGET     1   0      ; "setup"
0003    FNEW     2   1      ; font_spec.lua:3
0004    CALL     1   1   2
0005    GGET     1   2      ; "it"
0006    KSTR     2   3      ; "should get face"
0007    FNEW     3   4      ; font_spec.lua:7
0008    CALL     1   1   3
0009    UCLO     0 => 0010
0010 => RET0     0   1

-- BYTECODE -- font_spec.lua:0-17
0001    GGET     0   0      ; "describe"
0002    KSTR     1   1      ; "Font module"
0003    FNEW     2   2      ; font_spec.lua:1
0004    CALL     0   1   3
0005    RET0     0   1

