
main <./frontend/ui/font.lua:0,0> (116 instructions, 464 bytes at 0x7f9d7a4068a0)
0+ params, 12 slots, 0 upvalues, 15 locals, 74 constants, 8 functions
	1	[5]	GETGLOBAL	0 -1	; require
	2	[5]	LOADK    	1 -2	; "fontlist"
	3	[5]	CALL     	0 2 2
	4	[6]	GETGLOBAL	1 -1	; require
	5	[6]	LOADK    	2 -3	; "ffi/freetype"
	6	[6]	CALL     	1 2 2
	7	[7]	GETGLOBAL	2 -1	; require
	8	[7]	LOADK    	3 -4	; "device"
	9	[7]	CALL     	2 2 2
	10	[7]	GETTABLE 	2 2 -5	; "screen"
	11	[8]	GETGLOBAL	3 -1	; require
	12	[8]	LOADK    	4 -6	; "logger"
	13	[8]	CALL     	3 2 2
	14	[11]	NEWTABLE 	4 0 0
	15	[12]	SETTABLE 	4 -7 -8	; "NotoSans-Regular.ttf" "NotoSans-Bold.ttf"
	16	[13]	SETTABLE 	4 -9 -10	; "NotoSans-Italic.ttf" "NotoSans-BoldItalic.ttf"
	17	[14]	SETTABLE 	4 -11 -12	; "NotoSansArabicUI-Regular.ttf" "NotoSansArabicUI-Bold.ttf"
	18	[15]	SETTABLE 	4 -13 -14	; "NotoSerif-Regular.ttf" "NotoSerif-Bold.ttf"
	19	[16]	SETTABLE 	4 -15 -16	; "NotoSerif-Italic.ttf" "NotoSerif-BoldItalic.ttf"
	20	[19]	NEWTABLE 	5 0 0
	21	[20]	GETGLOBAL	6 -17	; pairs
	22	[20]	MOVE     	7 4
	23	[20]	CALL     	6 2 4
	24	[20]	JMP      	1	; to 26
	25	[21]	SETTABLE 	5 10 9
	26	[20]	TFORLOOP 	6 2
	27	[21]	JMP      	-3	; to 25
	28	[24]	NEWTABLE 	6 0 8
	29	[27]	SETTABLE 	6 -18 4	; "bold_font_variant" -
	30	[28]	SETTABLE 	6 -19 5	; "regular_font_variant" -
	31	[32]	GETGLOBAL	7 -21	; G_reader_settings
	32	[32]	SELF     	7 7 -22	; "nilOrTrue"
	33	[32]	LOADK    	9 -20	; "use_bold_font_for_bold"
	34	[32]	CALL     	7 3 2
	35	[32]	SETTABLE 	6 -20 7	; "use_bold_font_for_bold" -
	36	[37]	SETTABLE 	6 -23 -23	; "FORCE_SYNTHETIZED_BOLD" "FORCE_SYNTHETIZED_BOLD"
	37	[39]	NEWTABLE 	7 0 18
	38	[41]	SETTABLE 	7 -25 -7	; "cfont" "NotoSans-Regular.ttf"
	39	[44]	SETTABLE 	7 -26 -8	; "tfont" "NotoSans-Bold.ttf"
	40	[45]	SETTABLE 	7 -27 -8	; "smalltfont" "NotoSans-Bold.ttf"
	41	[46]	SETTABLE 	7 -28 -8	; "x_smalltfont" "NotoSans-Bold.ttf"
	42	[48]	SETTABLE 	7 -29 -7	; "ffont" "NotoSans-Regular.ttf"
	43	[49]	SETTABLE 	7 -30 -7	; "smallffont" "NotoSans-Regular.ttf"
	44	[50]	SETTABLE 	7 -31 -7	; "largeffont" "NotoSans-Regular.ttf"
	45	[53]	SETTABLE 	7 -32 -7	; "rifont" "NotoSans-Regular.ttf"
	46	[56]	SETTABLE 	7 -33 -7	; "pgfont" "NotoSans-Regular.ttf"
	47	[59]	SETTABLE 	7 -34 -35	; "scfont" "DroidSansMono.ttf"
	48	[62]	SETTABLE 	7 -36 -35	; "hpkfont" "DroidSansMono.ttf"
	49	[64]	SETTABLE 	7 -37 -7	; "hfont" "NotoSans-Regular.ttf"
	50	[68]	SETTABLE 	7 -38 -35	; "infont" "DroidSansMono.ttf"
	51	[70]	SETTABLE 	7 -39 -35	; "smallinfont" "DroidSansMono.ttf"
	52	[73]	SETTABLE 	7 -40 -7	; "infofont" "NotoSans-Regular.ttf"
	53	[76]	SETTABLE 	7 -41 -7	; "smallinfofont" "NotoSans-Regular.ttf"
	54	[78]	SETTABLE 	7 -42 -8	; "smallinfofontbold" "NotoSans-Bold.ttf"
	55	[80]	SETTABLE 	7 -43 -7	; "x_smallinfofont" "NotoSans-Regular.ttf"
	56	[82]	SETTABLE 	7 -44 -7	; "xx_smallinfofont" "NotoSans-Regular.ttf"
	57	[83]	SETTABLE 	6 -24 7	; "fontmap" -
	58	[84]	NEWTABLE 	7 0 18
	59	[85]	SETTABLE 	7 -25 -46	; "cfont" 24
	60	[86]	SETTABLE 	7 -26 -47	; "tfont" 26
	61	[87]	SETTABLE 	7 -27 -46	; "smalltfont" 24
	62	[88]	SETTABLE 	7 -28 -48	; "x_smalltfont" 22
	63	[89]	SETTABLE 	7 -29 -49	; "ffont" 20
	64	[90]	SETTABLE 	7 -30 -50	; "smallffont" 15
	65	[91]	SETTABLE 	7 -31 -51	; "largeffont" 25
	66	[92]	SETTABLE 	7 -33 -49	; "pgfont" 20
	67	[93]	SETTABLE 	7 -34 -49	; "scfont" 20
	68	[94]	SETTABLE 	7 -32 -52	; "rifont" 16
	69	[95]	SETTABLE 	7 -36 -49	; "hpkfont" 20
	70	[96]	SETTABLE 	7 -37 -46	; "hfont" 24
	71	[97]	SETTABLE 	7 -38 -48	; "infont" 22
	72	[98]	SETTABLE 	7 -39 -52	; "smallinfont" 16
	73	[99]	SETTABLE 	7 -40 -46	; "infofont" 24
	74	[100]	SETTABLE 	7 -41 -48	; "smallinfofont" 22
	75	[101]	SETTABLE 	7 -42 -48	; "smallinfofontbold" 22
	76	[102]	SETTABLE 	7 -43 -49	; "x_smallinfofont" 20
	77	[103]	SETTABLE 	7 -44 -53	; "xx_smallinfofont" 18
	78	[104]	SETTABLE 	6 -45 7	; "sizemap" -
	79	[107]	NEWTABLE 	7 0 7
	80	[108]	SETTABLE 	7 -55 -7	; 1 "NotoSans-Regular.ttf"
	81	[109]	SETTABLE 	7 -56 -57	; 2 "NotoSansCJKsc-Regular.otf"
	82	[110]	SETTABLE 	7 -58 -11	; 3 "NotoSansArabicUI-Regular.ttf"
	83	[111]	SETTABLE 	7 -59 -60	; 4 "NotoSansDevanagariUI-Regular.ttf"
	84	[112]	SETTABLE 	7 -61 -62	; 5 "nerdfonts/symbols.ttf"
	85	[113]	SETTABLE 	7 -63 -64	; 6 "freefont/FreeSans.ttf"
	86	[114]	SETTABLE 	7 -65 -66	; 7 "freefont/FreeSerif.ttf"
	87	[115]	SETTABLE 	6 -54 7	; "fallbacks" -
	88	[118]	NEWTABLE 	7 0 0
	89	[118]	SETTABLE 	6 -67 7	; "faces" -
	90	[125]	CLOSURE  	7 0	; 0x7f9d7a407380
	91	[123]	SETTABLE 	6 -68 7	; "hasBoldVariant" -
	92	[129]	CLOSURE  	7 1	; 0x7f9d7a407a30
	93	[127]	SETTABLE 	6 -69 7	; "getBoldVariantName" -
	94	[133]	CLOSURE  	7 2	; 0x7f9d7a408000
	95	[131]	SETTABLE 	6 -70 7	; "isRealBoldFont" -
	96	[137]	CLOSURE  	7 3	; 0x7f9d7a4080c0
	97	[135]	SETTABLE 	6 -71 7	; "getRegularVariantName" -
	98	[142]	LOADK    	7 -72	; 0.375
	99	[150]	CLOSURE  	8 4	; 0x7f9d7a4084e0
	100	[150]	MOVE     	0 7
	101	[212]	CLOSURE  	9 5	; 0x7f9d7a408860
	102	[212]	MOVE     	0 8
	103	[212]	MOVE     	0 6
	104	[304]	CLOSURE  	10 6	; 0x7f9d7a408e80
	105	[304]	MOVE     	0 2
	106	[304]	MOVE     	0 0
	107	[304]	MOVE     	0 1
	108	[304]	MOVE     	0 3
	109	[304]	MOVE     	0 9
	110	[218]	SETTABLE 	6 -73 10	; "getFace" -
	111	[384]	CLOSURE  	10 7	; 0x7f9d7a409990
	112	[384]	MOVE     	0 6
	113	[384]	MOVE     	0 9
	114	[321]	SETTABLE 	6 -74 10	; "getAdjustedFace" -
	115	[386]	RETURN   	6 2
	116	[386]	RETURN   	0 1

function <./frontend/ui/font.lua:123,125> (10 instructions, 40 bytes at 0x7f9d7a407380)
2 params, 3 slots, 0 upvalues, 2 locals, 1 constant, 0 functions
	1	[124]	GETTABLE 	2 0 -1	; "bold_font_variant"
	2	[124]	GETTABLE 	2 2 1
	3	[124]	TEST     	2 0 0
	4	[124]	JMP      	3	; to 8
	5	[124]	LOADBOOL 	2 1 0
	6	[124]	TEST     	2 0 1
	7	[124]	JMP      	1	; to 9
	8	[124]	LOADBOOL 	2 0 0
	9	[124]	RETURN   	2 2
	10	[125]	RETURN   	0 1

function <./frontend/ui/font.lua:127,129> (4 instructions, 16 bytes at 0x7f9d7a407a30)
2 params, 3 slots, 0 upvalues, 2 locals, 1 constant, 0 functions
	1	[128]	GETTABLE 	2 0 -1	; "bold_font_variant"
	2	[128]	GETTABLE 	2 2 1
	3	[128]	RETURN   	2 2
	4	[129]	RETURN   	0 1

function <./frontend/ui/font.lua:131,133> (10 instructions, 40 bytes at 0x7f9d7a408000)
2 params, 3 slots, 0 upvalues, 2 locals, 1 constant, 0 functions
	1	[132]	GETTABLE 	2 0 -1	; "regular_font_variant"
	2	[132]	GETTABLE 	2 2 1
	3	[132]	TEST     	2 0 0
	4	[132]	JMP      	3	; to 8
	5	[132]	LOADBOOL 	2 1 0
	6	[132]	TEST     	2 0 1
	7	[132]	JMP      	1	; to 9
	8	[132]	LOADBOOL 	2 0 0
	9	[132]	RETURN   	2 2
	10	[133]	RETURN   	0 1

function <./frontend/ui/font.lua:135,137> (7 instructions, 28 bytes at 0x7f9d7a4080c0)
2 params, 3 slots, 0 upvalues, 2 locals, 1 constant, 0 functions
	1	[136]	GETTABLE 	2 0 -1	; "regular_font_variant"
	2	[136]	GETTABLE 	2 2 1
	3	[136]	TEST     	2 0 1
	4	[136]	JMP      	1	; to 6
	5	[136]	MOVE     	2 1
	6	[136]	RETURN   	2 2
	7	[137]	RETURN   	0 1

function <./frontend/ui/font.lua:145,150> (9 instructions, 36 bytes at 0x7f9d7a4084e0)
1 param, 4 slots, 1 upvalue, 1 local, 3 constants, 0 functions
	1	[146]	GETTABLE 	1 0 -1	; "embolden_half_strength"
	2	[146]	TEST     	1 0 1
	3	[146]	JMP      	5	; to 9
	4	[148]	GETTABLE 	1 0 -2	; "ftface"
	5	[148]	SELF     	1 1 -3	; "getEmboldenHalfStrength"
	6	[148]	GETUPVAL 	3 0	; bold_strength_factor
	7	[148]	CALL     	1 3 2
	8	[148]	SETTABLE 	0 -1 1	; "embolden_half_strength" -
	9	[150]	RETURN   	0 1

function <./frontend/ui/font.lua:156,212> (91 instructions, 364 bytes at 0x7f9d7a408860)
2 params, 15 slots, 2 upvalues, 13 locals, 14 constants, 0 functions
	1	[157]	TEST     	1 0 0
	2	[157]	JMP      	2	; to 5
	3	[157]	EQ       	0 1 -1	; - 0
	4	[157]	JMP      	4	; to 9
	5	[158]	GETUPVAL 	2 0	; _completeFaceProperties
	6	[158]	MOVE     	3 0
	7	[158]	CALL     	2 2 1
	8	[159]	RETURN   	0 2
	9	[161]	GETTABLE 	2 0 -2	; "fallbacks"
	10	[161]	TEST     	2 0 1
	11	[161]	JMP      	2	; to 14
	12	[162]	NEWTABLE 	2 0 0
	13	[162]	SETTABLE 	0 -2 2	; "fallbacks" -
	14	[164]	GETTABLE 	2 0 -2	; "fallbacks"
	15	[164]	GETTABLE 	2 2 1
	16	[164]	EQ       	1 2 -3	; - nil
	17	[164]	JMP      	3	; to 21
	18	[165]	GETTABLE 	2 0 -2	; "fallbacks"
	19	[165]	GETTABLE 	2 2 1
	20	[165]	RETURN   	2 2
	21	[167]	GETTABLE 	2 0 -2	; "fallbacks"
	22	[167]	LEN      	2 2
	23	[167]	ADD      	2 2 -4	; - 1
	24	[168]	LOADK    	3 -1	; 0
	25	[169]	GETTABLE 	4 0 -5	; "realname"
	26	[170]	GETTABLE 	5 0 -6	; "is_real_bold"
	27	[170]	TEST     	5 0 0
	28	[170]	JMP      	5	; to 34
	29	[172]	GETUPVAL 	5 1	; Font
	30	[172]	SELF     	5 5 -7	; "getRegularVariantName"
	31	[172]	MOVE     	7 4
	32	[172]	CALL     	5 3 2
	33	[172]	MOVE     	4 5
	34	[174]	GETGLOBAL	5 -8	; pairs
	35	[174]	GETUPVAL 	6 1	; Font
	36	[174]	GETTABLE 	6 6 -2	; "fallbacks"
	37	[174]	CALL     	5 2 4
	38	[174]	JMP      	46	; to 85
	39	[175]	EQ       	1 9 4
	40	[175]	JMP      	44	; to 85
	41	[181]	GETTABLE 	10 0 -6	; "is_real_bold"
	42	[181]	TEST     	10 0 1
	43	[181]	JMP      	3	; to 47
	44	[181]	GETTABLE 	10 0 -9	; "wants_bold"
	45	[181]	EQ       	0 10 -10	; - true
	46	[181]	JMP      	22	; to 69
	47	[183]	GETUPVAL 	10 1	; Font
	48	[183]	SELF     	10 10 -11	; "getBoldVariantName"
	49	[183]	MOVE     	12 9
	50	[183]	CALL     	10 3 2
	51	[184]	TEST     	10 0 0
	52	[184]	JMP      	16	; to 69
	53	[186]	GETUPVAL 	11 1	; Font
	54	[186]	SELF     	11 11 -12	; "getFace"
	55	[186]	MOVE     	13 10
	56	[186]	GETTABLE 	14 0 -13	; "orig_size"
	57	[186]	CALL     	11 4 2
	58	[187]	EQ       	1 11 -3	; - nil
	59	[187]	JMP      	9	; to 69
	60	[188]	ADD      	3 3 -4	; - 1
	61	[189]	EQ       	0 3 2
	62	[189]	JMP      	6	; to 69
	63	[190]	GETUPVAL 	12 0	; _completeFaceProperties
	64	[190]	MOVE     	13 11
	65	[190]	CALL     	12 2 1
	66	[191]	GETTABLE 	12 0 -2	; "fallbacks"
	67	[191]	SETTABLE 	12 2 11
	68	[192]	RETURN   	11 2
	69	[198]	GETUPVAL 	10 1	; Font
	70	[198]	SELF     	10 10 -12	; "getFace"
	71	[198]	MOVE     	12 9
	72	[198]	GETTABLE 	13 0 -13	; "orig_size"
	73	[198]	CALL     	10 4 2
	74	[199]	EQ       	1 10 -3	; - nil
	75	[199]	JMP      	9	; to 85
	76	[200]	ADD      	3 3 -4	; - 1
	77	[201]	EQ       	0 3 2
	78	[201]	JMP      	6	; to 85
	79	[202]	GETUPVAL 	11 0	; _completeFaceProperties
	80	[202]	MOVE     	12 10
	81	[202]	CALL     	11 2 1
	82	[203]	GETTABLE 	11 0 -2	; "fallbacks"
	83	[203]	SETTABLE 	11 2 10
	84	[204]	RETURN   	10 2
	85	[174]	TFORLOOP 	5 2
	86	[207]	JMP      	-48	; to 39
	87	[210]	GETTABLE 	5 0 -2	; "fallbacks"
	88	[210]	SETTABLE 	5 2 -14	; - false
	89	[211]	LOADBOOL 	5 0 0
	90	[211]	RETURN   	5 2
	91	[212]	RETURN   	0 1

function <./frontend/ui/font.lua:218,304> (112 instructions, 448 bytes at 0x7f9d7a408e80)
3 params, 23 slots, 5 upvalues, 18 locals, 34 constants, 1 function
	1	[220]	TEST     	1 0 1
	2	[220]	JMP      	1	; to 4
	3	[220]	GETTABLE 	1 0 -1	; "cfont"
	4	[222]	TEST     	2 0 1
	5	[222]	JMP      	2	; to 8
	6	[222]	GETTABLE 	3 0 -2	; "sizemap"
	7	[222]	GETTABLE 	2 3 1
	8	[224]	MOVE     	3 2
	9	[225]	GETUPVAL 	4 0	; Screen
	10	[225]	SELF     	4 4 -3	; "scaleBySize"
	11	[225]	MOVE     	6 2
	12	[225]	CALL     	4 3 2
	13	[225]	MOVE     	2 4
	14	[227]	GETTABLE 	4 0 -4	; "fontmap"
	15	[227]	GETTABLE 	4 4 1
	16	[228]	TEST     	4 0 1
	17	[228]	JMP      	1	; to 19
	18	[229]	MOVE     	4 1
	19	[233]	SELF     	5 0 -5	; "isRealBoldFont"
	20	[233]	MOVE     	7 4
	21	[233]	CALL     	5 3 2
	22	[237]	MOVE     	6 4
	23	[237]	MOVE     	7 2
	24	[237]	CONCAT   	6 6 7
	25	[239]	GETTABLE 	7 0 -6	; "faces"
	26	[239]	GETTABLE 	7 7 6
	27	[241]	TEST     	7 0 1
	28	[241]	JMP      	82	; to 111
	29	[242]	GETUPVAL 	8 1	; FontList
	30	[242]	GETTABLE 	8 8 -7	; "fontdir"
	31	[242]	LOADK    	9 -8	; "/"
	32	[242]	MOVE     	10 4
	33	[242]	CONCAT   	8 8 10
	34	[243]	GETGLOBAL	9 -9	; pcall
	35	[243]	GETUPVAL 	10 2	; Freetype
	36	[243]	GETTABLE 	10 10 -10	; "newFace"
	37	[243]	MOVE     	11 8
	38	[243]	MOVE     	12 2
	39	[243]	CALL     	9 4 3
	40	[247]	TEST     	9 0 1
	41	[247]	JMP      	36	; to 78
	42	[248]	GETUPVAL 	11 1	; FontList
	43	[248]	SELF     	11 11 -11	; "getFontList"
	44	[248]	CALL     	11 2 2
	45	[249]	SELF     	12 4 -12	; "gsub"
	46	[249]	LOADK    	14 -13	; "[-]"
	47	[249]	LOADK    	15 -14	; "%%-"
	48	[249]	CALL     	12 4 2
	49	[251]	GETGLOBAL	13 -15	; ipairs
	50	[251]	MOVE     	14 11
	51	[251]	CALL     	13 2 4
	52	[251]	JMP      	23	; to 76
	53	[252]	SELF     	18 17 -16	; "find"
	54	[252]	MOVE     	20 12
	55	[252]	CALL     	18 3 2
	56	[252]	TEST     	18 0 0
	57	[252]	JMP      	18	; to 76
	58	[253]	GETUPVAL 	18 3	; logger
	59	[253]	GETTABLE 	18 18 -17	; "dbg"
	60	[253]	LOADK    	19 -18	; "Found font:"
	61	[253]	MOVE     	20 4
	62	[253]	LOADK    	21 -19	; "in"
	63	[253]	MOVE     	22 17
	64	[253]	CALL     	18 5 1
	65	[254]	GETGLOBAL	18 -9	; pcall
	66	[254]	GETUPVAL 	19 2	; Freetype
	67	[254]	GETTABLE 	19 19 -10	; "newFace"
	68	[254]	MOVE     	20 17
	69	[254]	MOVE     	21 2
	70	[254]	CALL     	18 4 3
	71	[254]	MOVE     	10 19
	72	[254]	MOVE     	9 18
	73	[256]	TEST     	9 0 0
	74	[256]	JMP      	1	; to 76
	75	[256]	JMP      	2	; to 78
	76	[251]	TFORLOOP 	13 2
	77	[257]	JMP      	-25	; to 53
	78	[260]	TEST     	9 0 1
	79	[260]	JMP      	11	; to 91
	80	[261]	GETUPVAL 	11 3	; logger
	81	[261]	GETTABLE 	11 11 -20	; "err"
	82	[261]	LOADK    	12 -21	; "#! Font "
	83	[261]	MOVE     	13 1
	84	[261]	LOADK    	14 -22	; " ("
	85	[261]	MOVE     	15 4
	86	[261]	LOADK    	16 -23	; ") not supported: "
	87	[261]	MOVE     	17 10
	88	[261]	CALL     	11 7 1
	89	[262]	LOADNIL  	11 11
	90	[262]	RETURN   	11 2
	91	[271]	NEWTABLE 	11 0 7
	92	[272]	SETTABLE 	11 -24 1	; "orig_font" -
	93	[273]	SETTABLE 	11 -25 4	; "realname" -
	94	[274]	SETTABLE 	11 -26 2	; "size" -
	95	[275]	SETTABLE 	11 -27 3	; "orig_size" -
	96	[276]	SETTABLE 	11 -28 10	; "ftface" -
	97	[277]	SETTABLE 	11 -29 6	; "hash" -
	98	[278]	SETTABLE 	11 -30 5	; "is_real_bold" -
	99	[279]	MOVE     	7 11
	100	[280]	GETTABLE 	11 0 -6	; "faces"
	101	[280]	SETTABLE 	11 6 7
	102	[286]	CLOSURE  	11 0	; 0x7f9d7a409770
	103	[286]	GETUPVAL 	0 4	; _getFallbackFont
	104	[286]	MOVE     	0 7
	105	[286]	SETTABLE 	7 -31 11	; "getFallbackFont" -
	106	[293]	NEWTABLE 	11 2 0
	107	[293]	LOADK    	12 -33	; "+kern"
	108	[293]	LOADK    	13 -34	; "+liga"
	109	[293]	SETLIST  	11 2 1	; 1
	110	[293]	SETTABLE 	7 -32 11	; "hb_features" -
	111	[303]	RETURN   	7 2
	112	[304]	RETURN   	0 1

function <./frontend/ui/font.lua:284,286> (6 instructions, 24 bytes at 0x7f9d7a409770)
1 param, 4 slots, 2 upvalues, 1 local, 0 constants, 0 functions
	1	[285]	GETUPVAL 	1 0	; _getFallbackFont
	2	[285]	GETUPVAL 	2 1	; face_obj
	3	[285]	MOVE     	3 0
	4	[285]	TAILCALL 	1 3 0
	5	[285]	RETURN   	1 0
	6	[286]	RETURN   	0 1

function <./frontend/ui/font.lua:321,384> (79 instructions, 316 bytes at 0x7f9d7a409990)
3 params, 8 slots, 2 upvalues, 6 locals, 18 constants, 1 function
	1	[322]	GETTABLE 	3 1 -1	; "is_real_bold"
	2	[322]	TEST     	3 0 0
	3	[322]	JMP      	3	; to 7
	4	[330]	MOVE     	3 1
	5	[330]	LOADBOOL 	4 1 0
	6	[330]	RETURN   	3 3
	7	[332]	TEST     	2 0 1
	8	[332]	JMP      	3	; to 12
	9	[335]	MOVE     	3 1
	10	[335]	LOADBOOL 	4 0 0
	11	[335]	RETURN   	3 3
	12	[338]	GETTABLE 	3 0 -2	; "use_bold_font_for_bold"
	13	[338]	TEST     	3 0 1
	14	[338]	JMP      	2	; to 17
	15	[340]	GETUPVAL 	3 0	; Font
	16	[340]	GETTABLE 	2 3 -3	; "FORCE_SYNTHETIZED_BOLD"
	17	[342]	GETUPVAL 	3 0	; Font
	18	[342]	GETTABLE 	3 3 -3	; "FORCE_SYNTHETIZED_BOLD"
	19	[342]	EQ       	1 2 3
	20	[342]	JMP      	14	; to 35
	21	[344]	SELF     	3 0 -4	; "getBoldVariantName"
	22	[344]	GETTABLE 	5 1 -5	; "realname"
	23	[344]	CALL     	3 3 2
	24	[345]	TEST     	3 0 0
	25	[345]	JMP      	9	; to 35
	26	[346]	GETUPVAL 	4 0	; Font
	27	[346]	SELF     	4 4 -6	; "getFace"
	28	[346]	MOVE     	6 3
	29	[346]	GETTABLE 	7 1 -7	; "orig_size"
	30	[346]	CALL     	4 4 2
	31	[346]	MOVE     	1 4
	32	[348]	MOVE     	4 1
	33	[348]	LOADBOOL 	5 1 0
	34	[348]	RETURN   	4 3
	35	[359]	GETTABLE 	3 1 -8	; "hash"
	36	[359]	GETUPVAL 	4 0	; Font
	37	[359]	GETTABLE 	4 4 -3	; "FORCE_SYNTHETIZED_BOLD"
	38	[359]	EQ       	0 2 4
	39	[359]	JMP      	3	; to 43
	40	[359]	LOADK    	4 -9	; "synthbold"
	41	[359]	TEST     	4 0 1
	42	[359]	JMP      	1	; to 44
	43	[359]	LOADK    	4 -10	; "realbold"
	44	[359]	CONCAT   	3 3 4
	45	[360]	GETTABLE 	4 0 -11	; "faces"
	46	[360]	GETTABLE 	4 4 3
	47	[361]	TEST     	4 0 0
	48	[361]	JMP      	3	; to 52
	49	[362]	MOVE     	5 4
	50	[362]	MOVE     	6 2
	51	[362]	RETURN   	5 3
	52	[364]	NEWTABLE 	5 0 9
	53	[365]	GETTABLE 	6 1 -12	; "orig_font"
	54	[365]	SETTABLE 	5 -12 6	; "orig_font" -
	55	[366]	GETTABLE 	6 1 -5	; "realname"
	56	[366]	SETTABLE 	5 -5 6	; "realname" -
	57	[367]	GETTABLE 	6 1 -13	; "size"
	58	[367]	SETTABLE 	5 -13 6	; "size" -
	59	[368]	GETTABLE 	6 1 -7	; "orig_size"
	60	[368]	SETTABLE 	5 -7 6	; "orig_size" -
	61	[372]	GETTABLE 	6 1 -14	; "ftface"
	62	[372]	SETTABLE 	5 -14 6	; "ftface" -
	63	[373]	GETTABLE 	6 1 -8	; "hash"
	64	[373]	SETTABLE 	5 -8 6	; "hash" -
	65	[374]	GETTABLE 	6 1 -15	; "hb_features"
	66	[374]	SETTABLE 	5 -15 6	; "hb_features" -
	67	[375]	SETTABLE 	5 -1 -16	; "is_real_bold" nil
	68	[376]	SETTABLE 	5 -17 2	; "wants_bold" -
	69	[378]	MOVE     	4 5
	70	[381]	CLOSURE  	5 0	; 0x7f9d7a40a530
	71	[381]	GETUPVAL 	0 1	; _getFallbackFont
	72	[381]	MOVE     	0 4
	73	[381]	SETTABLE 	4 -18 5	; "getFallbackFont" -
	74	[382]	GETTABLE 	5 0 -11	; "faces"
	75	[382]	SETTABLE 	5 3 4
	76	[383]	MOVE     	5 4
	77	[383]	MOVE     	6 2
	78	[383]	RETURN   	5 3
	79	[384]	RETURN   	0 1

function <./frontend/ui/font.lua:379,381> (6 instructions, 24 bytes at 0x7f9d7a40a530)
1 param, 4 slots, 2 upvalues, 1 local, 0 constants, 0 functions
	1	[380]	GETUPVAL 	1 0	; _getFallbackFont
	2	[380]	GETUPVAL 	2 1	; face_obj
	3	[380]	MOVE     	3 0
	4	[380]	TAILCALL 	1 3 0
	5	[380]	RETURN   	1 0
	6	[381]	RETURN   	0 1
