-- BYTECODE -- font_settings.lua:13-24
0001    GGET     0   0      ; "pcall"
0002    GGET     1   1      ; "require"
0003    KSTR     2   2      ; "android"
0004    CALL     0   3   3
0005    IST          0
0006    JMP      2 => 0008
0007    RET0     0   1
0008 => TGETS    2   1   3  ; "getExternalStoragePath"
0009    CALL     2   2   1
0010    ISEQS    2   4      ; "Unknown"
0011    JMP      3 => 0014
0012    RET1     2   2
0013    JMP      3 => 0016
0014 => KSTR     3   5      ; "/sdcard"
0015    RET1     3   2
0016 => RET0     0   1

-- BYTECODE -- font_settings.lua:28-36
0001    UGET     0   0      ; Device
0002    MOV      1   0
0003    TGETS    0   0   0  ; "isDesktop"
0004    CALL     0   2   2
0005    IST          0
0006    JMP      1 => 0013
0007    UGET     0   0      ; Device
0008    MOV      1   0
0009    TGETS    0   0   1  ; "isEmulator"
0010    CALL     0   2   2
0011    ISF          0
0012    JMP      1 => 0024
0013 => GGET     0   2      ; "os"
0014    TGETS    0   0   3  ; "getenv"
0015    KSTR     1   4      ; "HOME"
0016    CALL     0   2   2
0017    ISF          0
0018    JMP      1 => 0038
0019    MOV      1   0
0020    UGET     2   1      ; DESKTOP_USER_FONT_DIR
0021    CAT      1   1   2
0022    RET1     1   2
0023    JMP      0 => 0038
0024 => UGET     0   0      ; Device
0025    MOV      1   0
0026    TGETS    0   0   5  ; "isAndroid"
0027    CALL     0   2   2
0028    ISF          0
0029    JMP      1 => 0038
0030    UGET     0   2      ; getAndroidPrimaryStorage
0031    CALL     0   2   1
0032    MOV      1   0
0033    KSTR     2   6      ; "/koreader/fonts;"
0034    MOV      3   0
0035    KSTR     4   7      ; "/fonts"
0036    CAT      1   1   4
0037    RET1     1   2
0038 => RET0     0   1

-- BYTECODE -- font_settings.lua:39-47
0001    UGET     0   0      ; Device
0002    MOV      1   0
0003    TGETS    0   0   0  ; "isDesktop"
0004    CALL     0   2   2
0005    IST          0
0006    JMP      1 => 0013
0007    UGET     0   0      ; Device
0008    MOV      1   0
0009    TGETS    0   0   1  ; "isEmulator"
0010    CALL     0   2   2
0011    ISF          0
0012    JMP      1 => 0025
0013 => UGET     0   1      ; util
0014    TGETS    0   0   2  ; "pathExists"
0015    UGET     1   2      ; LINUX_SYSTEM_FONT_DIR
0016    CALL     0   2   2
0017    ISF          0
0018    JMP      1 => 0022
0019    UGET     0   2      ; LINUX_SYSTEM_FONT_DIR
0020    RET1     0   2
0021    JMP      0 => 0033
0022 => KPRI     0   0
0023    RET1     0   2
0024    JMP      0 => 0033
0025 => UGET     0   0      ; Device
0026    MOV      1   0
0027    TGETS    0   0   3  ; "isAndroid"
0028    CALL     0   2   2
0029    ISF          0
0030    JMP      1 => 0033
0031    UGET     0   3      ; ANDROID_SYSTEM_FONT_DIR
0032    RET1     0   2
0033 => RET0     0   1

-- BYTECODE -- font_settings.lua:49-51
0001    GGET     0   0      ; "G_reader_settings"
0002    MOV      1   0
0003    TGETS    0   0   1  ; "isTrue"
0004    KSTR     2   2      ; "system_fonts"
0005    CALLT    0   3

-- BYTECODE -- font_settings.lua:53-66
0001    UGET     0   0      ; Device
0002    MOV      1   0
0003    TGETS    0   0   0  ; "canOpenLink"
0004    CALL     0   2   2
0005    IST          0
0006    JMP      0 => 0008
0007    RET0     0   1
0008 => UGET     0   1      ; getUserDir
0009    CALL     0   2   1
0010    UGET     1   2      ; util
0011    TGETS    1   1   1  ; "pathExists"
0012    MOV      2   0
0013    CALL     1   2   2
0014    IST          1
0015    JMP      2 => 0028
0016    ISF          0
0017    JMP      2 => 0028
0018    UGET     2   3      ; logger
0019    TGETS    2   2   2  ; "info"
0020    KSTR     3   3      ; "Font path not found, making one in "
0021    MOV      4   0
0022    CALL     2   1   3
0023    UGET     2   2      ; util
0024    TGETS    2   2   4  ; "makePath"
0025    MOV      3   0
0026    CALL     2   2   2
0027    MOV      1   2
0028 => IST          1
0029    JMP      2 => 0036
0030    UGET     2   3      ; logger
0031    TGETS    2   2   5  ; "warn"
0032    KSTR     3   6      ; "Unable to create the folder "
0033    MOV      4   0
0034    CALL     2   1   3
0035    RET0     0   1
0036 => UGET     2   0      ; Device
0037    MOV      3   2
0038    TGETS    2   2   7  ; "openLink"
0039    MOV      4   0
0040    CALL     2   1   3
0041    RET0     0   1

-- BYTECODE -- font_settings.lua:70-78
0001    UGET     1   0      ; usesSystemFonts
0002    CALL     1   2   1
0003    ISF          1
0004    JMP      2 => 0015
0005    UGET     1   1      ; getSystemDir
0006    CALL     1   2   1
0007    ISEQP    1   0
0008    JMP      2 => 0015
0009    UGET     2   2      ; getUserDir
0010    CALL     2   2   1
0011    KSTR     3   0      ; ";"
0012    MOV      4   1
0013    CAT      2   2   4
0014    RET1     2   2
0015 => UGET     1   2      ; getUserDir
0016    CALLT    1   1

-- BYTECODE -- font_settings.lua:84-91
0001    GGET     0   0      ; "G_reader_settings"
0002    MOV      1   0
0003    TGETS    0   0   1  ; "saveSetting"
0004    KSTR     2   2      ; "system_fonts"
0005    UGET     3   0      ; usesSystemFonts
0006    CALL     3   2   1
0007    NOT      3   3
0008    CALL     0   1   4
0009    GGET     0   3      ; "require"
0010    KSTR     1   4      ; "ui/uimanager"
0011    CALL     0   2   2
0012    GGET     1   3      ; "require"
0013    KSTR     2   5      ; "ui/widget/infomessage"
0014    CALL     1   2   2
0015    MOV      3   0
0016    TGETS    2   0   6  ; "show"
0017    MOV      5   1
0018    TGETS    4   1   7  ; "new"
0019    TDUP     6   9
0020    UGET     7   1      ; _
0021    KSTR     8   8      ; "This will take effect on next restart."
0022    CALL     7   2   2
0023    TSETS    7   6  10  ; "text"
0024    CALL     4   0   3
0025    CALLM    2   1   1
0026    RET0     0   1

-- BYTECODE -- font_settings.lua:80-102
0001    TNEW     1   3
0002    TDUP     2   1
0003    UGET     3   0      ; _
0004    KSTR     4   0      ; "Enable system fonts"
0005    CALL     3   2   2
0006    TSETS    3   2   2  ; "text"
0007    UGET     3   1      ; usesSystemFonts
0008    TSETS    3   2   3  ; "checked_func"
0009    FNEW     3   4      ; font_settings.lua:84
0010    TSETS    3   2   5  ; "callback"
0011    TSETB    2   1   1
0012    UGET     2   2      ; Device
0013    MOV      3   2
0014    TGETS    2   2   6  ; "isDesktop"
0015    CALL     2   2   2
0016    IST          2
0017    JMP      3 => 0024
0018    UGET     2   2      ; Device
0019    MOV      3   2
0020    TGETS    2   2   7  ; "isEmulator"
0021    CALL     2   2   2
0022    ISF          2
0023    JMP      3 => 0036
0024 => GGET     2   8      ; "table"
0025    TGETS    2   2   9  ; "insert"
0026    MOV      3   1
0027    KSHORT   4   2
0028    TDUP     5  11
0029    UGET     6   0      ; _
0030    KSTR     7  10      ; "Open fonts folder"
0031    CALL     6   2   2
0032    TSETS    6   5   2  ; "text"
0033    UGET     6   3      ; openFontDir
0034    TSETS    6   5   5  ; "callback"
0035    CALL     2   1   4
0036 => UCLO     0 => 0037
0037 => RET1     1   2

-- BYTECODE -- font_settings.lua:0-105
0001    GGET     0   0      ; "require"
0002    KSTR     1   1      ; "device"
0003    CALL     0   2   2
0004    GGET     1   0      ; "require"
0005    KSTR     2   2      ; "logger"
0006    CALL     1   2   2
0007    GGET     2   0      ; "require"
0008    KSTR     3   3      ; "util"
0009    CALL     2   2   2
0010    GGET     3   0      ; "require"
0011    KSTR     4   4      ; "gettext"
0012    CALL     3   2   2
0013    KSTR     4   5      ; "/system/fonts"
0014    KSTR     5   6      ; "/usr/share/fonts"
0015    KSTR     6   7      ; "/.local/share/fonts"
0016    FNEW     7   8      ; font_settings.lua:13
0017    FNEW     8   9      ; font_settings.lua:28
0018    FNEW     9  10      ; font_settings.lua:39
0019    FNEW    10  11      ; font_settings.lua:49
0020    FNEW    11  12      ; font_settings.lua:53
0021    TNEW    12   0
0022    FNEW    13  14      ; font_settings.lua:70
0023    TSETS   13  12  13  ; "getPath"
0024    FNEW    13  16      ; font_settings.lua:80
0025    TSETS   13  12  15  ; "getSystemFontMenuItems"
0026    UCLO     0 => 0027
0027 => RET1    12   2

