-- BYTECODE -- fr_keyboard.lua:0-50
0001    GGET     0   0      ; "dofile"
0002    KSTR     1   1      ; "frontend/ui/data/keyboardlayouts/en_keyb"~
0003    CALL     0   2   2
0004    TGETS    1   0   2  ; "keys"
0005    TGETB    2   1   1
0006    TGETB    2   2   1
0007    TGETB    3   1   2
0008    TGETB    3   3   1
0009    TGETB    4   1   2
0010    TGETB    4   4   1
0011    TGETB    4   4   1
0012    TGETB    5   1   1
0013    TGETB    5   5   1
0014    TGETB    5   5   1
0015    TSETB    5   3   1
0016    TSETB    4   2   1
0017    TGETB    2   1   1
0018    TGETB    2   2   1
0019    TGETB    3   1   2
0020    TGETB    3   3   1
0021    TGETB    4   1   2
0022    TGETB    4   4   1
0023    TGETB    4   4   2
0024    TGETB    5   1   1
0025    TGETB    5   5   1
0026    TGETB    5   5   2
0027    TSETB    5   3   2
0028    TSETB    4   2   2
0029    TGETB    2   1   1
0030    TGETB    2   2   2
0031    TGETB    3   1   3
0032    TGETB    3   3   2
0033    TGETB    4   1   3
0034    TGETB    4   4   2
0035    TGETB    4   4   1
0036    TGETB    5   1   1
0037    TGETB    5   5   2
0038    TGETB    5   5   1
0039    TSETB    5   3   1
0040    TSETB    4   2   1
0041    TGETB    2   1   1
0042    TGETB    2   2   2
0043    TGETB    3   1   3
0044    TGETB    3   3   2
0045    TGETB    4   1   3
0046    TGETB    4   4   2
0047    TGETB    4   4   2
0048    TGETB    5   1   1
0049    TGETB    5   5   2
0050    TGETB    5   5   2
0051    TSETB    5   3   2
0052    TSETB    4   2   2
0053    GGET     2   3      ; "table"
0054    TGETS    2   2   4  ; "insert"
0055    TGETB    3   1   2
0056    TDUP     4   5
0057    CALL     2   1   3
0058    TGETB    2   1   3
0059    TGETB    2   2   8
0060    KSTR     3   6      ; ","
0061    TSETB    3   2   1
0062    TGETB    2   1   3
0063    TGETB    2   2   8
0064    KSTR     3   6      ; ","
0065    TSETB    3   2   2
0066    TGETB    2   1   4
0067    TGETB    2   2   5
0068    TGETB    2   2   1
0069    KSTR     3   7      ; ";"
0070    TSETB    3   2   1
0071    KSTR     3   6      ; ","
0072    TSETS    3   2   8  ; "north"
0073    TNEW     3  11
0074    TGETB    4   1   1
0075    TGETB    4   4   1
0076    TGETB    4   4   1
0077    TSETB    4   3   1
0078    TGETB    4   1   1
0079    TGETB    4   4   1
0080    TGETB    4   4   2
0081    TSETB    4   3   2
0082    TGETB    4   1   1
0083    TGETB    4   4   3
0084    TGETB    4   4   1
0085    TSETB    4   3   3
0086    TGETB    4   1   1
0087    TGETB    4   4   3
0088    TGETB    4   4   2
0089    TSETB    4   3   4
0090    TGETB    4   1   1
0091    TGETB    4   4   7
0092    TGETB    4   4   1
0093    TSETB    4   3   5
0094    TGETB    4   1   1
0095    TGETB    4   4   7
0096    TGETB    4   4   2
0097    TSETB    4   3   6
0098    TGETB    4   1   1
0099    TGETB    4   4   8
0100    TGETB    4   4   1
0101    TSETB    4   3   7
0102    TGETB    4   1   1
0103    TGETB    4   4   8
0104    TGETB    4   4   2
0105    TSETB    4   3   8
0106    TGETB    4   1   1
0107    TGETB    4   4   9
0108    TGETB    4   4   1
0109    TSETB    4   3   9
0110    TGETB    4   1   1
0111    TGETB    4   4   9
0112    TGETB    4   4   2
0113    TSETB    4   3  10
0114    GGET     4   9      ; "ipairs"
0115    MOV      5   3
0116    CALL     4   4   2
0117    JMP      7 => 0122
0118 => TGETS    9   8  10  ; "east"
0119    TGETS   10   8   8  ; "north"
0120    TSETS   10   8  10  ; "east"
0121    TSETS    9   8   8  ; "north"
0122 => ITERC    7   3   3
0123    ITERL    7 => 0118
0124    TGETB    4   1   4
0125    TGETB    4   4   4
0126    KSTR     5  12      ; ""
0127    TSETS    5   4  11  ; "label"
0128    RET1     0   2

