
main <./frontend/ui/widget/container/framecontainer.lua:0,0> (49 instructions, 196 bytes at 0x7fe56f406900)
0+ params, 9 slots, 0 upvalues, 6 locals, 34 constants, 2 functions
	1	[21]	GETGLOBAL	0 -1	; require
	2	[21]	LOADK    	1 -2	; "ui/bidi"
	3	[21]	CALL     	0 2 2
	4	[22]	GETGLOBAL	1 -1	; require
	5	[22]	LOADK    	2 -3	; "ffi/blitbuffer"
	6	[22]	CALL     	1 2 2
	7	[23]	GETGLOBAL	2 -1	; require
	8	[23]	LOADK    	3 -4	; "ui/geometry"
	9	[23]	CALL     	2 2 2
	10	[24]	GETGLOBAL	3 -1	; require
	11	[24]	LOADK    	4 -5	; "ui/size"
	12	[24]	CALL     	3 2 2
	13	[25]	GETGLOBAL	4 -1	; require
	14	[25]	LOADK    	5 -6	; "ui/widget/container/widgetcontainer"
	15	[25]	CALL     	4 2 2
	16	[27]	SELF     	5 4 -7	; "new"
	17	[27]	NEWTABLE 	7 0 16
	18	[28]	SETTABLE 	7 -8 -9	; "background" nil
	19	[29]	GETTABLE 	8 1 -11	; "COLOR_BLACK"
	20	[29]	SETTABLE 	7 -10 8	; "color" -
	21	[30]	SETTABLE 	7 -12 -13	; "margin" 0
	22	[31]	SETTABLE 	7 -14 -13	; "radius" 0
	23	[32]	SETTABLE 	7 -15 -13	; "inner_bordersize" 0
	24	[33]	GETTABLE 	8 3 -17	; "border"
	25	[33]	GETTABLE 	8 8 -18	; "window"
	26	[33]	SETTABLE 	7 -16 8	; "bordersize" -
	27	[34]	GETTABLE 	8 3 -19	; "padding"
	28	[34]	GETTABLE 	8 8 -20	; "default"
	29	[34]	SETTABLE 	7 -19 8	; "padding" -
	30	[35]	SETTABLE 	7 -21 -9	; "padding_top" nil
	31	[36]	SETTABLE 	7 -22 -9	; "padding_right" nil
	32	[37]	SETTABLE 	7 -23 -9	; "padding_bottom" nil
	33	[38]	SETTABLE 	7 -24 -9	; "padding_left" nil
	34	[39]	SETTABLE 	7 -25 -9	; "width" nil
	35	[40]	SETTABLE 	7 -26 -9	; "height" nil
	36	[41]	SETTABLE 	7 -27 -28	; "invert" false
	37	[42]	SETTABLE 	7 -29 -30	; "allow_mirroring" true
	38	[43]	GETTABLE 	8 0 -32	; "mirroredUILayout"
	39	[43]	CALL     	8 1 2
	40	[43]	SETTABLE 	7 -31 8	; "_mirroredUI" -
	41	[27]	CALL     	5 3 2
	42	[59]	CLOSURE  	6 0	; 0x7fe56f4070a0
	43	[59]	MOVE     	0 2
	44	[46]	SETTABLE 	5 -33 6	; "getSize" -
	45	[110]	CLOSURE  	6 1	; 0x7fe56f407450
	46	[110]	MOVE     	0 2
	47	[61]	SETTABLE 	5 -34 6	; "paintTo" -
	48	[112]	RETURN   	5 2
	49	[112]	RETURN   	0 1

function <./frontend/ui/widget/container/framecontainer.lua:46,59> (61 instructions, 244 bytes at 0x7fe56f4070a0)
1 param, 8 slots, 1 upvalue, 2 locals, 19 constants, 0 functions
	1	[47]	GETTABLE 	1 0 -1	; 1
	2	[47]	SELF     	1 1 -2	; "getSize"
	3	[47]	CALL     	1 2 2
	4	[48]	GETTABLE 	2 0 -4	; "padding_top"
	5	[48]	TEST     	2 0 1
	6	[48]	JMP      	1	; to 8
	7	[48]	GETTABLE 	2 0 -5	; "padding"
	8	[48]	SETTABLE 	0 -3 2	; "_padding_top" -
	9	[49]	GETTABLE 	2 0 -7	; "padding_right"
	10	[49]	TEST     	2 0 1
	11	[49]	JMP      	1	; to 13
	12	[49]	GETTABLE 	2 0 -5	; "padding"
	13	[49]	SETTABLE 	0 -6 2	; "_padding_right" -
	14	[50]	GETTABLE 	2 0 -9	; "padding_bottom"
	15	[50]	TEST     	2 0 1
	16	[50]	JMP      	1	; to 18
	17	[50]	GETTABLE 	2 0 -5	; "padding"
	18	[50]	SETTABLE 	0 -8 2	; "_padding_bottom" -
	19	[51]	GETTABLE 	2 0 -11	; "padding_left"
	20	[51]	TEST     	2 0 1
	21	[51]	JMP      	1	; to 23
	22	[51]	GETTABLE 	2 0 -5	; "padding"
	23	[51]	SETTABLE 	0 -10 2	; "_padding_left" -
	24	[52]	GETTABLE 	2 0 -12	; "_mirroredUI"
	25	[52]	TEST     	2 0 0
	26	[52]	JMP      	7	; to 34
	27	[52]	GETTABLE 	2 0 -13	; "allow_mirroring"
	28	[52]	TEST     	2 0 0
	29	[52]	JMP      	4	; to 34
	30	[53]	GETTABLE 	2 0 -6	; "_padding_right"
	31	[53]	GETTABLE 	3 0 -10	; "_padding_left"
	32	[53]	SETTABLE 	0 -6 3	; "_padding_right" -
	33	[53]	SETTABLE 	0 -10 2	; "_padding_left" -
	34	[55]	GETUPVAL 	2 0	; Geom
	35	[55]	SELF     	2 2 -14	; "new"
	36	[55]	NEWTABLE 	4 0 2
	37	[56]	GETTABLE 	5 1 -15	; "w"
	38	[56]	GETTABLE 	6 0 -16	; "margin"
	39	[56]	GETTABLE 	7 0 -17	; "bordersize"
	40	[56]	ADD      	6 6 7
	41	[56]	MUL      	6 6 -18	; - 2
	42	[56]	ADD      	5 5 6
	43	[56]	GETTABLE 	6 0 -10	; "_padding_left"
	44	[56]	ADD      	5 5 6
	45	[56]	GETTABLE 	6 0 -6	; "_padding_right"
	46	[56]	ADD      	5 5 6
	47	[56]	SETTABLE 	4 -15 5	; "w" -
	48	[57]	GETTABLE 	5 1 -19	; "h"
	49	[57]	GETTABLE 	6 0 -16	; "margin"
	50	[57]	GETTABLE 	7 0 -17	; "bordersize"
	51	[57]	ADD      	6 6 7
	52	[57]	MUL      	6 6 -18	; - 2
	53	[57]	ADD      	5 5 6
	54	[57]	GETTABLE 	6 0 -3	; "_padding_top"
	55	[57]	ADD      	5 5 6
	56	[57]	GETTABLE 	6 0 -8	; "_padding_bottom"
	57	[57]	ADD      	5 5 6
	58	[57]	SETTABLE 	4 -19 5	; "h" -
	59	[55]	TAILCALL 	2 3 0
	60	[58]	RETURN   	2 0
	61	[59]	RETURN   	0 1

function <./frontend/ui/widget/container/framecontainer.lua:61,110> (128 instructions, 512 bytes at 0x7fe56f407450)
4 params, 17 slots, 1 upvalue, 8 locals, 30 constants, 0 functions
	1	[62]	SELF     	4 0 -1	; "getSize"
	2	[62]	CALL     	4 2 2
	3	[63]	GETUPVAL 	5 0	; Geom
	4	[63]	SELF     	5 5 -3	; "new"
	5	[63]	NEWTABLE 	7 0 4
	6	[64]	SETTABLE 	7 -4 2	; "x" -
	7	[64]	SETTABLE 	7 -5 3	; "y" -
	8	[65]	GETTABLE 	8 4 -6	; "w"
	9	[65]	SETTABLE 	7 -6 8	; "w" -
	10	[66]	GETTABLE 	8 4 -7	; "h"
	11	[66]	SETTABLE 	7 -7 8	; "h" -
	12	[63]	CALL     	5 3 2
	13	[67]	SETTABLE 	0 -2 5	; "dimen" -
	14	[68]	GETTABLE 	5 0 -8	; "width"
	15	[68]	TEST     	5 0 1
	16	[68]	JMP      	1	; to 18
	17	[68]	GETTABLE 	5 4 -6	; "w"
	18	[69]	GETTABLE 	6 0 -9	; "height"
	19	[69]	TEST     	6 0 1
	20	[69]	JMP      	1	; to 22
	21	[69]	GETTABLE 	6 4 -7	; "h"
	22	[71]	LOADK    	7 -10	; 0
	23	[72]	GETTABLE 	8 0 -11	; "_mirroredUI"
	24	[72]	TEST     	8 0 0
	25	[72]	JMP      	5	; to 31
	26	[72]	GETTABLE 	8 0 -12	; "allow_mirroring"
	27	[72]	TEST     	8 0 0
	28	[72]	JMP      	2	; to 31
	29	[73]	GETTABLE 	8 4 -6	; "w"
	30	[73]	SUB      	7 5 8
	31	[77]	GETTABLE 	8 0 -13	; "background"
	32	[77]	TEST     	8 0 0
	33	[77]	JMP      	8	; to 42
	34	[78]	SELF     	8 1 -14	; "paintRoundedRect"
	35	[78]	MOVE     	10 2
	36	[78]	MOVE     	11 3
	37	[79]	MOVE     	12 5
	38	[79]	MOVE     	13 6
	39	[80]	GETTABLE 	14 0 -13	; "background"
	40	[80]	GETTABLE 	15 0 -15	; "radius"
	41	[78]	CALL     	8 8 1
	42	[82]	GETTABLE 	8 0 -16	; "inner_bordersize"
	43	[82]	LT       	0 -10 8	; 0 -
	44	[82]	JMP      	15	; to 60
	45	[84]	SELF     	8 1 -17	; "paintInnerBorder"
	46	[84]	GETTABLE 	10 0 -18	; "margin"
	47	[84]	ADD      	10 2 10
	48	[84]	GETTABLE 	11 0 -18	; "margin"
	49	[84]	ADD      	11 3 11
	50	[85]	GETTABLE 	12 0 -18	; "margin"
	51	[85]	MUL      	12 12 -19	; - 2
	52	[85]	SUB      	12 5 12
	53	[86]	GETTABLE 	13 0 -18	; "margin"
	54	[86]	MUL      	13 13 -19	; - 2
	55	[86]	SUB      	13 6 13
	56	[87]	GETTABLE 	14 0 -16	; "inner_bordersize"
	57	[87]	GETTABLE 	15 0 -20	; "color"
	58	[87]	GETTABLE 	16 0 -15	; "radius"
	59	[84]	CALL     	8 9 1
	60	[89]	GETTABLE 	8 0 -21	; "bordersize"
	61	[89]	LT       	0 -10 8	; 0 -
	62	[89]	JMP      	15	; to 78
	63	[90]	SELF     	8 1 -22	; "paintBorder"
	64	[90]	GETTABLE 	10 0 -18	; "margin"
	65	[90]	ADD      	10 2 10
	66	[90]	GETTABLE 	11 0 -18	; "margin"
	67	[90]	ADD      	11 3 11
	68	[91]	GETTABLE 	12 0 -18	; "margin"
	69	[91]	MUL      	12 12 -19	; - 2
	70	[91]	SUB      	12 5 12
	71	[92]	GETTABLE 	13 0 -18	; "margin"
	72	[92]	MUL      	13 13 -19	; - 2
	73	[92]	SUB      	13 6 13
	74	[93]	GETTABLE 	14 0 -21	; "bordersize"
	75	[93]	GETTABLE 	15 0 -20	; "color"
	76	[93]	GETTABLE 	16 0 -15	; "radius"
	77	[90]	CALL     	8 9 1
	78	[95]	GETTABLE 	8 0 -23	; 1
	79	[95]	TEST     	8 0 0
	80	[95]	JMP      	17	; to 98
	81	[96]	GETTABLE 	8 0 -23	; 1
	82	[96]	SELF     	8 8 -24	; "paintTo"
	83	[96]	MOVE     	10 1
	84	[97]	GETTABLE 	11 0 -18	; "margin"
	85	[97]	ADD      	11 2 11
	86	[97]	GETTABLE 	12 0 -21	; "bordersize"
	87	[97]	ADD      	11 11 12
	88	[97]	GETTABLE 	12 0 -25	; "_padding_left"
	89	[97]	ADD      	11 11 12
	90	[97]	ADD      	11 11 7
	91	[98]	GETTABLE 	12 0 -18	; "margin"
	92	[98]	ADD      	12 3 12
	93	[98]	GETTABLE 	13 0 -21	; "bordersize"
	94	[98]	ADD      	12 12 13
	95	[98]	GETTABLE 	13 0 -26	; "_padding_top"
	96	[98]	ADD      	12 12 13
	97	[96]	CALL     	8 5 1
	98	[100]	GETTABLE 	8 0 -27	; "invert"
	99	[100]	TEST     	8 0 0
	100	[100]	JMP      	12	; to 113
	101	[101]	SELF     	8 1 -28	; "invertRect"
	102	[101]	GETTABLE 	10 0 -21	; "bordersize"
	103	[101]	ADD      	10 2 10
	104	[101]	GETTABLE 	11 0 -21	; "bordersize"
	105	[101]	ADD      	11 3 11
	106	[102]	GETTABLE 	12 0 -21	; "bordersize"
	107	[102]	MUL      	12 -19 12	; 2 -
	108	[102]	SUB      	12 5 12
	109	[103]	GETTABLE 	13 0 -21	; "bordersize"
	110	[103]	MUL      	13 -19 13	; 2 -
	111	[103]	SUB      	13 6 13
	112	[101]	CALL     	8 6 1
	113	[105]	GETTABLE 	8 0 -29	; "dim"
	114	[105]	TEST     	8 0 0
	115	[105]	JMP      	12	; to 128
	116	[106]	SELF     	8 1 -30	; "dimRect"
	117	[106]	GETTABLE 	10 0 -21	; "bordersize"
	118	[106]	ADD      	10 2 10
	119	[106]	GETTABLE 	11 0 -21	; "bordersize"
	120	[106]	ADD      	11 3 11
	121	[107]	GETTABLE 	12 0 -21	; "bordersize"
	122	[107]	MUL      	12 -19 12	; 2 -
	123	[107]	SUB      	12 5 12
	124	[108]	GETTABLE 	13 0 -21	; "bordersize"
	125	[108]	MUL      	13 -19 13	; 2 -
	126	[108]	SUB      	13 6 13
	127	[106]	CALL     	8 6 1
	128	[110]	RETURN   	0 1
