
main <./spec/unit/frontlight_spec.lua:0,0> (5 instructions, 20 bytes at 0x7fe903c068c0)
0+ params, 3 slots, 0 upvalues, 0 locals, 2 constants, 1 function
	1	[1]	GETGLOBAL	0 -1	; describe
	2	[1]	LOADK    	1 -2	; "Frontlight function in PowerD"
	3	[209]	CLOSURE  	2 0	; 0x7fe903c06b70
	4	[1]	CALL     	0 3 1
	5	[209]	RETURN   	0 1

function <./spec/unit/frontlight_spec.lua:1,209> (47 instructions, 188 bytes at 0x7fe903c06b70)
0 params, 8 slots, 0 upvalues, 5 locals, 9 constants, 10 functions
	1	[4]	GETGLOBAL	5 -1	; setup
	2	[27]	CLOSURE  	6 0	; 0x7fe903c06cc0
	3	[27]	MOVE     	0 1
	4	[27]	MOVE     	0 2
	5	[4]	CALL     	5 2 1
	6	[29]	GETGLOBAL	5 -2	; teardown
	7	[32]	CLOSURE  	6 1	; 0x7fe903c06d80
	8	[29]	CALL     	5 2 1
	9	[34]	GETGLOBAL	5 -3	; before_each
	10	[50]	CLOSURE  	6 2	; 0x7fe903c07c70
	11	[50]	MOVE     	0 0
	12	[50]	MOVE     	0 2
	13	[50]	MOVE     	0 1
	14	[34]	CALL     	5 2 1
	15	[52]	GETGLOBAL	5 -4	; it
	16	[52]	LOADK    	6 -5	; "should read frontlight intensity during initialization"
	17	[59]	CLOSURE  	7 3	; 0x7fe903c08710
	18	[59]	MOVE     	0 1
	19	[59]	MOVE     	0 2
	20	[52]	CALL     	5 3 1
	21	[138]	CLOSURE  	4 4	; 0x7fe903c08c60
	22	[138]	MOVE     	0 2
	23	[138]	MOVE     	0 1
	24	[194]	CLOSURE  	3 5	; 0x7fe903c067c0
	25	[194]	MOVE     	0 2
	26	[194]	MOVE     	0 1
	27	[196]	GETGLOBAL	5 -4	; it
	28	[196]	LOADK    	6 -6	; "should turn on and off frontlight when the frontlight was off"
	29	[198]	CLOSURE  	7 6	; 0x7fe903c08ce0
	30	[198]	MOVE     	0 4
	31	[196]	CALL     	5 3 1
	32	[200]	GETGLOBAL	5 -4	; it
	33	[200]	LOADK    	6 -7	; "should turn on and off frontlight when the minimum level is 1 and frontlight was off"
	34	[201]	CLOSURE  	7 7	; 0x7fe903c089a0
	35	[201]	MOVE     	0 4
	36	[200]	CALL     	5 3 1
	37	[203]	GETGLOBAL	5 -4	; it
	38	[203]	LOADK    	6 -8	; "should turn on and off frontlight when the frontlight was on"
	39	[205]	CLOSURE  	7 8	; 0x7fe903c09530
	40	[205]	MOVE     	0 3
	41	[203]	CALL     	5 3 1
	42	[207]	GETGLOBAL	5 -4	; it
	43	[207]	LOADK    	6 -9	; "should turn on and off frontlight when the minimum level is 1 and frontlight was on"
	44	[208]	CLOSURE  	7 9	; 0x7fe903c08690
	45	[208]	MOVE     	0 3
	46	[207]	CALL     	5 3 1
	47	[209]	RETURN   	0 1

function <./spec/unit/frontlight_spec.lua:4,27> (36 instructions, 144 bytes at 0x7fe903c06cc0)
0 params, 4 slots, 2 upvalues, 0 locals, 21 constants, 2 functions
	1	[5]	GETGLOBAL	0 -1	; require
	2	[5]	LOADK    	1 -2	; "commonrequire"
	3	[5]	CALL     	0 2 1
	4	[6]	GETGLOBAL	0 -3	; package
	5	[6]	GETTABLE 	0 0 -4	; "unloadAll"
	6	[6]	CALL     	0 1 1
	7	[7]	GETGLOBAL	0 -1	; require
	8	[7]	LOADK    	1 -5	; "document/canvascontext"
	9	[7]	CALL     	0 2 2
	10	[7]	SELF     	0 0 -6	; "init"
	11	[7]	GETGLOBAL	2 -1	; require
	12	[7]	LOADK    	3 -7	; "device"
	13	[7]	CALL     	2 2 0
	14	[7]	CALL     	0 0 1
	15	[9]	GETGLOBAL	0 -1	; require
	16	[9]	LOADK    	1 -8	; "device/generic/powerd"
	17	[9]	CALL     	0 2 2
	18	[9]	SELF     	0 0 -9	; "new"
	19	[9]	NEWTABLE 	2 0 1
	20	[10]	SETTABLE 	2 -10 -11	; "frontlight" 2
	21	[9]	CALL     	0 3 2
	22	[11]	SETUPVAL 	0 0	; PowerD
	23	[13]	NEWTABLE 	0 0 5
	24	[14]	SETTABLE 	0 -12 -13	; "fl_min" 1
	25	[15]	SETTABLE 	0 -14 -15	; "fl_max" 5
	26	[16]	SETTABLE 	0 -16 -11	; "fl_intensity" 2
	27	[17]	SETTABLE 	0 -7 -17	; "device" nil
	28	[18]	SETTABLE 	0 -18 -19	; "is_fl_on" true
	29	[19]	SETUPVAL 	0 1	; param
	30	[21]	GETUPVAL 	0 0	; PowerD
	31	[23]	CLOSURE  	1 0	; 0x7fe903c072c0
	32	[23]	SETTABLE 	0 -20 1	; "frontlightIntensityHW" -
	33	[24]	GETUPVAL 	0 0	; PowerD
	34	[26]	CLOSURE  	1 1	; 0x7fe903c071f0
	35	[26]	SETTABLE 	0 -21 1	; "setIntensityHW" -
	36	[27]	RETURN   	0 1

function <./spec/unit/frontlight_spec.lua:21,23> (3 instructions, 12 bytes at 0x7fe903c072c0)
1 param, 2 slots, 0 upvalues, 1 local, 1 constant, 0 functions
	1	[22]	GETTABLE 	1 0 -1	; "frontlight"
	2	[22]	RETURN   	1 2
	3	[23]	RETURN   	0 1

function <./spec/unit/frontlight_spec.lua:24,26> (2 instructions, 8 bytes at 0x7fe903c071f0)
2 params, 2 slots, 0 upvalues, 2 locals, 1 constant, 0 functions
	1	[25]	SETTABLE 	0 -1 1	; "frontlight" -
	2	[26]	RETURN   	0 1

function <./spec/unit/frontlight_spec.lua:29,32> (12 instructions, 48 bytes at 0x7fe903c06d80)
0 params, 4 slots, 0 upvalues, 0 locals, 6 constants, 0 functions
	1	[30]	GETGLOBAL	0 -1	; package
	2	[30]	GETTABLE 	0 0 -2	; "unloadAll"
	3	[30]	CALL     	0 1 1
	4	[31]	GETGLOBAL	0 -3	; require
	5	[31]	LOADK    	1 -4	; "document/canvascontext"
	6	[31]	CALL     	0 2 2
	7	[31]	SELF     	0 0 -5	; "init"
	8	[31]	GETGLOBAL	2 -3	; require
	9	[31]	LOADK    	3 -6	; "device"
	10	[31]	CALL     	2 2 0
	11	[31]	CALL     	0 0 1
	12	[32]	RETURN   	0 1

function <./spec/unit/frontlight_spec.lua:34,50> (48 instructions, 192 bytes at 0x7fe903c07c70)
0 params, 5 slots, 3 upvalues, 0 locals, 16 constants, 2 functions
	1	[35]	GETGLOBAL	0 -1	; require
	2	[35]	LOADK    	1 -2	; "device"
	3	[35]	CALL     	0 2 2
	4	[35]	SETUPVAL 	0 0	; Device
	5	[36]	GETUPVAL 	0 0	; Device
	6	[36]	CLOSURE  	1 0	; 0x7fe903c08190
	7	[36]	SETTABLE 	0 -3 1	; "isKobo" -
	8	[37]	GETUPVAL 	0 0	; Device
	9	[37]	SETTABLE 	0 -4 -5	; "model" "Kobo_dahlia"
	10	[38]	GETUPVAL 	0 0	; Device
	11	[38]	CLOSURE  	1 1	; 0x7fe903c083b0
	12	[38]	SETTABLE 	0 -6 1	; "hasFrontlight" -
	13	[39]	GETUPVAL 	0 1	; param
	14	[39]	GETUPVAL 	1 0	; Device
	15	[39]	SETTABLE 	0 -2 1	; "device" -
	16	[40]	GETUPVAL 	0 0	; Device
	17	[40]	GETUPVAL 	1 2	; PowerD
	18	[40]	SELF     	1 1 -8	; "new"
	19	[40]	NEWTABLE 	3 1 0
	20	[42]	GETUPVAL 	4 1	; param
	21	[42]	SETLIST  	3 1 1	; 1
	22	[40]	CALL     	1 3 2
	23	[42]	SETTABLE 	0 -7 1	; "powerd" -
	24	[45]	GETGLOBAL	0 -9	; stub
	25	[45]	GETUPVAL 	1 2	; PowerD
	26	[45]	LOADK    	2 -10	; "init"
	27	[45]	CALL     	0 3 1
	28	[46]	GETGLOBAL	0 -11	; spy
	29	[46]	GETTABLE 	0 0 -12	; "on"
	30	[46]	GETUPVAL 	1 2	; PowerD
	31	[46]	LOADK    	2 -13	; "frontlightIntensityHW"
	32	[46]	CALL     	0 3 1
	33	[47]	GETGLOBAL	0 -11	; spy
	34	[47]	GETTABLE 	0 0 -12	; "on"
	35	[47]	GETUPVAL 	1 2	; PowerD
	36	[47]	LOADK    	2 -14	; "setIntensityHW"
	37	[47]	CALL     	0 3 1
	38	[48]	GETGLOBAL	0 -11	; spy
	39	[48]	GETTABLE 	0 0 -12	; "on"
	40	[48]	GETUPVAL 	1 2	; PowerD
	41	[48]	LOADK    	2 -15	; "turnOnFrontlightHW"
	42	[48]	CALL     	0 3 1
	43	[49]	GETGLOBAL	0 -11	; spy
	44	[49]	GETTABLE 	0 0 -12	; "on"
	45	[49]	GETUPVAL 	1 2	; PowerD
	46	[49]	LOADK    	2 -16	; "turnOffFrontlightHW"
	47	[49]	CALL     	0 3 1
	48	[50]	RETURN   	0 1

function <./spec/unit/frontlight_spec.lua:36,36> (3 instructions, 12 bytes at 0x7fe903c08190)
0 params, 2 slots, 0 upvalues, 0 locals, 0 constants, 0 functions
	1	[36]	LOADBOOL 	0 1 0
	2	[36]	RETURN   	0 2
	3	[36]	RETURN   	0 1

function <./spec/unit/frontlight_spec.lua:38,38> (3 instructions, 12 bytes at 0x7fe903c083b0)
0 params, 2 slots, 0 upvalues, 0 locals, 0 constants, 0 functions
	1	[38]	LOADBOOL 	0 1 0
	2	[38]	RETURN   	0 2
	3	[38]	RETURN   	0 1

function <./spec/unit/frontlight_spec.lua:52,59> (39 instructions, 156 bytes at 0x7fe903c08710)
0 params, 5 slots, 2 upvalues, 1 local, 15 constants, 0 functions
	1	[53]	GETUPVAL 	0 0	; PowerD
	2	[53]	SELF     	0 0 -1	; "new"
	3	[53]	GETUPVAL 	2 1	; param
	4	[53]	CALL     	0 3 2
	5	[54]	GETGLOBAL	1 -2	; assert
	6	[54]	GETTABLE 	1 1 -3	; "are"
	7	[54]	GETTABLE 	1 1 -4	; "equal"
	8	[54]	LOADK    	2 -5	; 2
	9	[54]	SELF     	3 0 -6	; "frontlightIntensityHW"
	10	[54]	CALL     	3 2 0
	11	[54]	CALL     	1 0 1
	12	[55]	GETGLOBAL	1 -2	; assert
	13	[55]	GETTABLE 	1 1 -3	; "are"
	14	[55]	GETTABLE 	1 1 -4	; "equal"
	15	[55]	LOADK    	2 -5	; 2
	16	[55]	SELF     	3 0 -7	; "frontlightIntensity"
	17	[55]	CALL     	3 2 0
	18	[55]	CALL     	1 0 1
	19	[56]	GETGLOBAL	1 -2	; assert
	20	[56]	GETTABLE 	1 1 -8	; "is"
	21	[56]	GETTABLE 	1 1 -9	; "truthy"
	22	[56]	SELF     	2 0 -10	; "isFrontlightOn"
	23	[56]	CALL     	2 2 0
	24	[56]	CALL     	1 0 1
	25	[57]	GETGLOBAL	1 -2	; assert
	26	[57]	GETTABLE 	1 1 -11	; "stub"
	27	[57]	GETTABLE 	2 0 -12	; "init"
	28	[57]	CALL     	1 2 2
	29	[57]	GETTABLE 	1 1 -13	; "is_called"
	30	[57]	LOADK    	2 -14	; 1
	31	[57]	CALL     	1 2 1
	32	[58]	GETGLOBAL	1 -2	; assert
	33	[58]	GETTABLE 	1 1 -15	; "spy"
	34	[58]	GETTABLE 	2 0 -6	; "frontlightIntensityHW"
	35	[58]	CALL     	1 2 2
	36	[58]	GETTABLE 	1 1 -13	; "is_called"
	37	[58]	LOADK    	2 -5	; 2
	38	[58]	CALL     	1 2 1
	39	[59]	RETURN   	0 1

function <./spec/unit/frontlight_spec.lua:61,138> (428 instructions, 1712 bytes at 0x7fe903c08c60)
1 param, 6 slots, 2 upvalues, 2 locals, 32 constants, 0 functions
	1	[62]	GETUPVAL 	1 0	; param
	2	[62]	SETTABLE 	1 -1 0	; "fl_min" -
	3	[63]	GETUPVAL 	1 0	; param
	4	[63]	SETTABLE 	1 -2 -3	; "fl_intensity" 0
	5	[64]	GETUPVAL 	1 1	; PowerD
	6	[64]	SELF     	1 1 -4	; "new"
	7	[64]	GETUPVAL 	3 0	; param
	8	[64]	CALL     	1 3 2
	9	[65]	SELF     	2 1 -5	; "setIntensity"
	10	[65]	LOADK    	4 -3	; 0
	11	[65]	CALL     	2 3 1
	12	[66]	GETGLOBAL	2 -6	; assert
	13	[66]	GETTABLE 	2 2 -7	; "are"
	14	[66]	GETTABLE 	2 2 -8	; "equal"
	15	[66]	GETUPVAL 	3 0	; param
	16	[66]	GETTABLE 	3 3 -1	; "fl_min"
	17	[66]	SELF     	4 1 -9	; "frontlightIntensityHW"
	18	[66]	CALL     	4 2 0
	19	[66]	CALL     	2 0 1
	20	[67]	GETGLOBAL	2 -6	; assert
	21	[67]	GETTABLE 	2 2 -7	; "are"
	22	[67]	GETTABLE 	2 2 -8	; "equal"
	23	[67]	LOADK    	3 -3	; 0
	24	[67]	SELF     	4 1 -10	; "frontlightIntensity"
	25	[67]	CALL     	4 2 0
	26	[67]	CALL     	2 0 1
	27	[68]	GETGLOBAL	2 -6	; assert
	28	[68]	GETTABLE 	2 2 -11	; "is"
	29	[68]	GETTABLE 	2 2 -12	; "truthy"
	30	[68]	SELF     	3 1 -13	; "isFrontlightOff"
	31	[68]	CALL     	3 2 0
	32	[68]	CALL     	2 0 1
	33	[69]	GETGLOBAL	2 -6	; assert
	34	[69]	GETTABLE 	2 2 -14	; "stub"
	35	[69]	GETTABLE 	3 1 -15	; "init"
	36	[69]	CALL     	2 2 2
	37	[69]	GETTABLE 	2 2 -16	; "is_called"
	38	[69]	LOADK    	3 -17	; 1
	39	[69]	CALL     	2 2 1
	40	[70]	GETGLOBAL	2 -6	; assert
	41	[70]	GETTABLE 	2 2 -18	; "spy"
	42	[70]	GETTABLE 	3 1 -19	; "setIntensityHW"
	43	[70]	CALL     	2 2 2
	44	[70]	GETTABLE 	2 2 -16	; "is_called"
	45	[70]	LOADK    	3 -17	; 1
	46	[70]	CALL     	2 2 1
	47	[71]	GETGLOBAL	2 -6	; assert
	48	[71]	GETTABLE 	2 2 -7	; "are"
	49	[71]	GETTABLE 	2 2 -8	; "equal"
	50	[71]	GETUPVAL 	3 0	; param
	51	[71]	GETTABLE 	3 3 -1	; "fl_min"
	52	[71]	GETTABLE 	4 1 -20	; "frontlight"
	53	[71]	CALL     	2 3 1
	54	[72]	GETGLOBAL	2 -6	; assert
	55	[72]	GETTABLE 	2 2 -18	; "spy"
	56	[72]	GETTABLE 	3 1 -9	; "frontlightIntensityHW"
	57	[72]	CALL     	2 2 2
	58	[72]	GETTABLE 	2 2 -16	; "is_called"
	59	[72]	LOADK    	3 -21	; 2
	60	[72]	CALL     	2 2 1
	61	[73]	GETGLOBAL	2 -6	; assert
	62	[73]	GETTABLE 	2 2 -18	; "spy"
	63	[73]	GETTABLE 	3 1 -22	; "turnOnFrontlightHW"
	64	[73]	CALL     	2 2 2
	65	[73]	GETTABLE 	2 2 -16	; "is_called"
	66	[73]	LOADK    	3 -3	; 0
	67	[73]	CALL     	2 2 1
	68	[74]	GETGLOBAL	2 -6	; assert
	69	[74]	GETTABLE 	2 2 -18	; "spy"
	70	[74]	GETTABLE 	3 1 -23	; "turnOffFrontlightHW"
	71	[74]	CALL     	2 2 2
	72	[74]	GETTABLE 	2 2 -16	; "is_called"
	73	[74]	LOADK    	3 -3	; 0
	74	[74]	CALL     	2 2 1
	75	[77]	GETGLOBAL	2 -6	; assert
	76	[77]	GETTABLE 	2 2 -11	; "is"
	77	[77]	GETTABLE 	2 2 -24	; "falsy"
	78	[77]	SELF     	3 1 -25	; "turnOnFrontlight"
	79	[77]	CALL     	3 2 0
	80	[77]	CALL     	2 0 1
	81	[78]	GETGLOBAL	2 -6	; assert
	82	[78]	GETTABLE 	2 2 -7	; "are"
	83	[78]	GETTABLE 	2 2 -8	; "equal"
	84	[78]	LOADK    	3 -3	; 0
	85	[78]	SELF     	4 1 -10	; "frontlightIntensity"
	86	[78]	CALL     	4 2 0
	87	[78]	CALL     	2 0 1
	88	[79]	GETGLOBAL	2 -6	; assert
	89	[79]	GETTABLE 	2 2 -11	; "is"
	90	[79]	GETTABLE 	2 2 -12	; "truthy"
	91	[79]	SELF     	3 1 -13	; "isFrontlightOff"
	92	[79]	CALL     	3 2 0
	93	[79]	CALL     	2 0 1
	94	[80]	GETGLOBAL	2 -6	; assert
	95	[80]	GETTABLE 	2 2 -18	; "spy"
	96	[80]	GETTABLE 	3 1 -19	; "setIntensityHW"
	97	[80]	CALL     	2 2 2
	98	[80]	GETTABLE 	2 2 -16	; "is_called"
	99	[80]	LOADK    	3 -17	; 1
	100	[80]	CALL     	2 2 1
	101	[81]	GETGLOBAL	2 -6	; assert
	102	[81]	GETTABLE 	2 2 -18	; "spy"
	103	[81]	GETTABLE 	3 1 -22	; "turnOnFrontlightHW"
	104	[81]	CALL     	2 2 2
	105	[81]	GETTABLE 	2 2 -16	; "is_called"
	106	[81]	LOADK    	3 -3	; 0
	107	[81]	CALL     	2 2 1
	108	[82]	GETGLOBAL	2 -6	; assert
	109	[82]	GETTABLE 	2 2 -18	; "spy"
	110	[82]	GETTABLE 	3 1 -23	; "turnOffFrontlightHW"
	111	[82]	CALL     	2 2 2
	112	[82]	GETTABLE 	2 2 -16	; "is_called"
	113	[82]	LOADK    	3 -3	; 0
	114	[82]	CALL     	2 2 1
	115	[85]	GETGLOBAL	2 -6	; assert
	116	[85]	GETTABLE 	2 2 -11	; "is"
	117	[85]	GETTABLE 	2 2 -24	; "falsy"
	118	[85]	SELF     	3 1 -26	; "toggleFrontlight"
	119	[85]	CALL     	3 2 0
	120	[85]	CALL     	2 0 1
	121	[86]	GETGLOBAL	2 -6	; assert
	122	[86]	GETTABLE 	2 2 -7	; "are"
	123	[86]	GETTABLE 	2 2 -8	; "equal"
	124	[86]	LOADK    	3 -3	; 0
	125	[86]	SELF     	4 1 -10	; "frontlightIntensity"
	126	[86]	CALL     	4 2 0
	127	[86]	CALL     	2 0 1
	128	[87]	GETGLOBAL	2 -6	; assert
	129	[87]	GETTABLE 	2 2 -11	; "is"
	130	[87]	GETTABLE 	2 2 -12	; "truthy"
	131	[87]	SELF     	3 1 -13	; "isFrontlightOff"
	132	[87]	CALL     	3 2 0
	133	[87]	CALL     	2 0 1
	134	[88]	GETGLOBAL	2 -6	; assert
	135	[88]	GETTABLE 	2 2 -18	; "spy"
	136	[88]	GETTABLE 	3 1 -19	; "setIntensityHW"
	137	[88]	CALL     	2 2 2
	138	[88]	GETTABLE 	2 2 -16	; "is_called"
	139	[88]	LOADK    	3 -17	; 1
	140	[88]	CALL     	2 2 1
	141	[89]	GETGLOBAL	2 -6	; assert
	142	[89]	GETTABLE 	2 2 -18	; "spy"
	143	[89]	GETTABLE 	3 1 -22	; "turnOnFrontlightHW"
	144	[89]	CALL     	2 2 2
	145	[89]	GETTABLE 	2 2 -16	; "is_called"
	146	[89]	LOADK    	3 -3	; 0
	147	[89]	CALL     	2 2 1
	148	[90]	GETGLOBAL	2 -6	; assert
	149	[90]	GETTABLE 	2 2 -18	; "spy"
	150	[90]	GETTABLE 	3 1 -23	; "turnOffFrontlightHW"
	151	[90]	CALL     	2 2 2
	152	[90]	GETTABLE 	2 2 -16	; "is_called"
	153	[90]	LOADK    	3 -3	; 0
	154	[90]	CALL     	2 2 1
	155	[92]	GETGLOBAL	2 -6	; assert
	156	[92]	GETTABLE 	2 2 -11	; "is"
	157	[92]	GETTABLE 	2 2 -12	; "truthy"
	158	[92]	SELF     	3 1 -5	; "setIntensity"
	159	[92]	LOADK    	5 -21	; 2
	160	[92]	CALL     	3 3 0
	161	[92]	CALL     	2 0 1
	162	[93]	GETGLOBAL	2 -6	; assert
	163	[93]	GETTABLE 	2 2 -7	; "are"
	164	[93]	GETTABLE 	2 2 -8	; "equal"
	165	[93]	LOADK    	3 -21	; 2
	166	[93]	SELF     	4 1 -10	; "frontlightIntensity"
	167	[93]	CALL     	4 2 0
	168	[93]	CALL     	2 0 1
	169	[94]	GETGLOBAL	2 -6	; assert
	170	[94]	GETTABLE 	2 2 -11	; "is"
	171	[94]	GETTABLE 	2 2 -12	; "truthy"
	172	[94]	SELF     	3 1 -27	; "isFrontlightOn"
	173	[94]	CALL     	3 2 0
	174	[94]	CALL     	2 0 1
	175	[95]	GETGLOBAL	2 -6	; assert
	176	[95]	GETTABLE 	2 2 -18	; "spy"
	177	[95]	GETTABLE 	3 1 -19	; "setIntensityHW"
	178	[95]	CALL     	2 2 2
	179	[95]	GETTABLE 	2 2 -16	; "is_called"
	180	[95]	LOADK    	3 -21	; 2
	181	[95]	CALL     	2 2 1
	182	[96]	GETGLOBAL	2 -6	; assert
	183	[96]	GETTABLE 	2 2 -7	; "are"
	184	[96]	GETTABLE 	2 2 -8	; "equal"
	185	[96]	LOADK    	3 -21	; 2
	186	[96]	GETTABLE 	4 1 -20	; "frontlight"
	187	[96]	CALL     	2 3 1
	188	[97]	GETGLOBAL	2 -6	; assert
	189	[97]	GETTABLE 	2 2 -18	; "spy"
	190	[97]	GETTABLE 	3 1 -22	; "turnOnFrontlightHW"
	191	[97]	CALL     	2 2 2
	192	[97]	GETTABLE 	2 2 -16	; "is_called"
	193	[97]	LOADK    	3 -3	; 0
	194	[97]	CALL     	2 2 1
	195	[98]	GETGLOBAL	2 -6	; assert
	196	[98]	GETTABLE 	2 2 -18	; "spy"
	197	[98]	GETTABLE 	3 1 -23	; "turnOffFrontlightHW"
	198	[98]	CALL     	2 2 2
	199	[98]	GETTABLE 	2 2 -16	; "is_called"
	200	[98]	LOADK    	3 -3	; 0
	201	[98]	CALL     	2 2 1
	202	[100]	GETGLOBAL	2 -6	; assert
	203	[100]	GETTABLE 	2 2 -11	; "is"
	204	[100]	GETTABLE 	2 2 -24	; "falsy"
	205	[100]	SELF     	3 1 -25	; "turnOnFrontlight"
	206	[100]	CALL     	3 2 0
	207	[100]	CALL     	2 0 1
	208	[101]	GETGLOBAL	2 -6	; assert
	209	[101]	GETTABLE 	2 2 -7	; "are"
	210	[101]	GETTABLE 	2 2 -8	; "equal"
	211	[101]	LOADK    	3 -21	; 2
	212	[101]	SELF     	4 1 -10	; "frontlightIntensity"
	213	[101]	CALL     	4 2 0
	214	[101]	CALL     	2 0 1
	215	[102]	GETGLOBAL	2 -6	; assert
	216	[102]	GETTABLE 	2 2 -11	; "is"
	217	[102]	GETTABLE 	2 2 -12	; "truthy"
	218	[102]	SELF     	3 1 -27	; "isFrontlightOn"
	219	[102]	CALL     	3 2 0
	220	[102]	CALL     	2 0 1
	221	[103]	GETGLOBAL	2 -6	; assert
	222	[103]	GETTABLE 	2 2 -18	; "spy"
	223	[103]	GETTABLE 	3 1 -19	; "setIntensityHW"
	224	[103]	CALL     	2 2 2
	225	[103]	GETTABLE 	2 2 -16	; "is_called"
	226	[103]	LOADK    	3 -21	; 2
	227	[103]	CALL     	2 2 1
	228	[104]	GETGLOBAL	2 -6	; assert
	229	[104]	GETTABLE 	2 2 -18	; "spy"
	230	[104]	GETTABLE 	3 1 -22	; "turnOnFrontlightHW"
	231	[104]	CALL     	2 2 2
	232	[104]	GETTABLE 	2 2 -16	; "is_called"
	233	[104]	LOADK    	3 -3	; 0
	234	[104]	CALL     	2 2 1
	235	[105]	GETGLOBAL	2 -6	; assert
	236	[105]	GETTABLE 	2 2 -18	; "spy"
	237	[105]	GETTABLE 	3 1 -23	; "turnOffFrontlightHW"
	238	[105]	CALL     	2 2 2
	239	[105]	GETTABLE 	2 2 -16	; "is_called"
	240	[105]	LOADK    	3 -3	; 0
	241	[105]	CALL     	2 2 1
	242	[107]	GETGLOBAL	2 -6	; assert
	243	[107]	GETTABLE 	2 2 -11	; "is"
	244	[107]	GETTABLE 	2 2 -12	; "truthy"
	245	[107]	SELF     	3 1 -28	; "turnOffFrontlight"
	246	[107]	CALL     	3 2 0
	247	[107]	CALL     	2 0 1
	248	[108]	GETGLOBAL	2 -6	; assert
	249	[108]	GETTABLE 	2 2 -7	; "are"
	250	[108]	GETTABLE 	2 2 -8	; "equal"
	251	[108]	LOADK    	3 -3	; 0
	252	[108]	SELF     	4 1 -10	; "frontlightIntensity"
	253	[108]	CALL     	4 2 0
	254	[108]	CALL     	2 0 1
	255	[109]	GETGLOBAL	2 -6	; assert
	256	[109]	GETTABLE 	2 2 -11	; "is"
	257	[109]	GETTABLE 	2 2 -12	; "truthy"
	258	[109]	SELF     	3 1 -13	; "isFrontlightOff"
	259	[109]	CALL     	3 2 0
	260	[109]	CALL     	2 0 1
	261	[110]	GETGLOBAL	2 -6	; assert
	262	[110]	GETTABLE 	2 2 -18	; "spy"
	263	[110]	GETTABLE 	3 1 -19	; "setIntensityHW"
	264	[110]	CALL     	2 2 2
	265	[110]	GETTABLE 	2 2 -16	; "is_called"
	266	[110]	LOADK    	3 -29	; 3
	267	[110]	CALL     	2 2 1
	268	[111]	GETGLOBAL	2 -6	; assert
	269	[111]	GETTABLE 	2 2 -7	; "are"
	270	[111]	GETTABLE 	2 2 -8	; "equal"
	271	[111]	GETUPVAL 	3 0	; param
	272	[111]	GETTABLE 	3 3 -1	; "fl_min"
	273	[111]	GETTABLE 	4 1 -20	; "frontlight"
	274	[111]	CALL     	2 3 1
	275	[112]	GETGLOBAL	2 -6	; assert
	276	[112]	GETTABLE 	2 2 -18	; "spy"
	277	[112]	GETTABLE 	3 1 -22	; "turnOnFrontlightHW"
	278	[112]	CALL     	2 2 2
	279	[112]	GETTABLE 	2 2 -16	; "is_called"
	280	[112]	LOADK    	3 -3	; 0
	281	[112]	CALL     	2 2 1
	282	[113]	GETGLOBAL	2 -6	; assert
	283	[113]	GETTABLE 	2 2 -18	; "spy"
	284	[113]	GETTABLE 	3 1 -23	; "turnOffFrontlightHW"
	285	[113]	CALL     	2 2 2
	286	[113]	GETTABLE 	2 2 -16	; "is_called"
	287	[113]	LOADK    	3 -17	; 1
	288	[113]	CALL     	2 2 1
	289	[115]	GETGLOBAL	2 -6	; assert
	290	[115]	GETTABLE 	2 2 -11	; "is"
	291	[115]	GETTABLE 	2 2 -12	; "truthy"
	292	[115]	SELF     	3 1 -25	; "turnOnFrontlight"
	293	[115]	CALL     	3 2 0
	294	[115]	CALL     	2 0 1
	295	[116]	GETGLOBAL	2 -6	; assert
	296	[116]	GETTABLE 	2 2 -7	; "are"
	297	[116]	GETTABLE 	2 2 -8	; "equal"
	298	[116]	LOADK    	3 -21	; 2
	299	[116]	SELF     	4 1 -10	; "frontlightIntensity"
	300	[116]	CALL     	4 2 0
	301	[116]	CALL     	2 0 1
	302	[117]	GETGLOBAL	2 -6	; assert
	303	[117]	GETTABLE 	2 2 -11	; "is"
	304	[117]	GETTABLE 	2 2 -12	; "truthy"
	305	[117]	SELF     	3 1 -27	; "isFrontlightOn"
	306	[117]	CALL     	3 2 0
	307	[117]	CALL     	2 0 1
	308	[118]	GETGLOBAL	2 -6	; assert
	309	[118]	GETTABLE 	2 2 -18	; "spy"
	310	[118]	GETTABLE 	3 1 -19	; "setIntensityHW"
	311	[118]	CALL     	2 2 2
	312	[118]	GETTABLE 	2 2 -16	; "is_called"
	313	[118]	LOADK    	3 -30	; 4
	314	[118]	CALL     	2 2 1
	315	[119]	GETGLOBAL	2 -6	; assert
	316	[119]	GETTABLE 	2 2 -7	; "are"
	317	[119]	GETTABLE 	2 2 -8	; "equal"
	318	[119]	LOADK    	3 -21	; 2
	319	[119]	GETTABLE 	4 1 -20	; "frontlight"
	320	[119]	CALL     	2 3 1
	321	[120]	GETGLOBAL	2 -6	; assert
	322	[120]	GETTABLE 	2 2 -18	; "spy"
	323	[120]	GETTABLE 	3 1 -22	; "turnOnFrontlightHW"
	324	[120]	CALL     	2 2 2
	325	[120]	GETTABLE 	2 2 -16	; "is_called"
	326	[120]	LOADK    	3 -17	; 1
	327	[120]	CALL     	2 2 1
	328	[121]	GETGLOBAL	2 -6	; assert
	329	[121]	GETTABLE 	2 2 -18	; "spy"
	330	[121]	GETTABLE 	3 1 -23	; "turnOffFrontlightHW"
	331	[121]	CALL     	2 2 2
	332	[121]	GETTABLE 	2 2 -16	; "is_called"
	333	[121]	LOADK    	3 -17	; 1
	334	[121]	CALL     	2 2 1
	335	[123]	GETGLOBAL	2 -6	; assert
	336	[123]	GETTABLE 	2 2 -11	; "is"
	337	[123]	GETTABLE 	2 2 -12	; "truthy"
	338	[123]	SELF     	3 1 -26	; "toggleFrontlight"
	339	[123]	CALL     	3 2 0
	340	[123]	CALL     	2 0 1
	341	[124]	GETGLOBAL	2 -6	; assert
	342	[124]	GETTABLE 	2 2 -7	; "are"
	343	[124]	GETTABLE 	2 2 -8	; "equal"
	344	[124]	LOADK    	3 -3	; 0
	345	[124]	SELF     	4 1 -10	; "frontlightIntensity"
	346	[124]	CALL     	4 2 0
	347	[124]	CALL     	2 0 1
	348	[125]	GETGLOBAL	2 -6	; assert
	349	[125]	GETTABLE 	2 2 -11	; "is"
	350	[125]	GETTABLE 	2 2 -12	; "truthy"
	351	[125]	SELF     	3 1 -13	; "isFrontlightOff"
	352	[125]	CALL     	3 2 0
	353	[125]	CALL     	2 0 1
	354	[126]	GETGLOBAL	2 -6	; assert
	355	[126]	GETTABLE 	2 2 -18	; "spy"
	356	[126]	GETTABLE 	3 1 -19	; "setIntensityHW"
	357	[126]	CALL     	2 2 2
	358	[126]	GETTABLE 	2 2 -16	; "is_called"
	359	[126]	LOADK    	3 -31	; 5
	360	[126]	CALL     	2 2 1
	361	[127]	GETGLOBAL	2 -6	; assert
	362	[127]	GETTABLE 	2 2 -7	; "are"
	363	[127]	GETTABLE 	2 2 -8	; "equal"
	364	[127]	GETUPVAL 	3 0	; param
	365	[127]	GETTABLE 	3 3 -1	; "fl_min"
	366	[127]	GETTABLE 	4 1 -20	; "frontlight"
	367	[127]	CALL     	2 3 1
	368	[128]	GETGLOBAL	2 -6	; assert
	369	[128]	GETTABLE 	2 2 -18	; "spy"
	370	[128]	GETTABLE 	3 1 -22	; "turnOnFrontlightHW"
	371	[128]	CALL     	2 2 2
	372	[128]	GETTABLE 	2 2 -16	; "is_called"
	373	[128]	LOADK    	3 -17	; 1
	374	[128]	CALL     	2 2 1
	375	[129]	GETGLOBAL	2 -6	; assert
	376	[129]	GETTABLE 	2 2 -18	; "spy"
	377	[129]	GETTABLE 	3 1 -23	; "turnOffFrontlightHW"
	378	[129]	CALL     	2 2 2
	379	[129]	GETTABLE 	2 2 -16	; "is_called"
	380	[129]	LOADK    	3 -21	; 2
	381	[129]	CALL     	2 2 1
	382	[131]	GETGLOBAL	2 -6	; assert
	383	[131]	GETTABLE 	2 2 -11	; "is"
	384	[131]	GETTABLE 	2 2 -12	; "truthy"
	385	[131]	SELF     	3 1 -26	; "toggleFrontlight"
	386	[131]	CALL     	3 2 0
	387	[131]	CALL     	2 0 1
	388	[132]	GETGLOBAL	2 -6	; assert
	389	[132]	GETTABLE 	2 2 -7	; "are"
	390	[132]	GETTABLE 	2 2 -8	; "equal"
	391	[132]	LOADK    	3 -21	; 2
	392	[132]	SELF     	4 1 -10	; "frontlightIntensity"
	393	[132]	CALL     	4 2 0
	394	[132]	CALL     	2 0 1
	395	[133]	GETGLOBAL	2 -6	; assert
	396	[133]	GETTABLE 	2 2 -11	; "is"
	397	[133]	GETTABLE 	2 2 -12	; "truthy"
	398	[133]	SELF     	3 1 -27	; "isFrontlightOn"
	399	[133]	CALL     	3 2 0
	400	[133]	CALL     	2 0 1
	401	[134]	GETGLOBAL	2 -6	; assert
	402	[134]	GETTABLE 	2 2 -18	; "spy"
	403	[134]	GETTABLE 	3 1 -19	; "setIntensityHW"
	404	[134]	CALL     	2 2 2
	405	[134]	GETTABLE 	2 2 -16	; "is_called"
	406	[134]	LOADK    	3 -32	; 6
	407	[134]	CALL     	2 2 1
	408	[135]	GETGLOBAL	2 -6	; assert
	409	[135]	GETTABLE 	2 2 -7	; "are"
	410	[135]	GETTABLE 	2 2 -8	; "equal"
	411	[135]	LOADK    	3 -21	; 2
	412	[135]	GETTABLE 	4 1 -20	; "frontlight"
	413	[135]	CALL     	2 3 1
	414	[136]	GETGLOBAL	2 -6	; assert
	415	[136]	GETTABLE 	2 2 -18	; "spy"
	416	[136]	GETTABLE 	3 1 -22	; "turnOnFrontlightHW"
	417	[136]	CALL     	2 2 2
	418	[136]	GETTABLE 	2 2 -16	; "is_called"
	419	[136]	LOADK    	3 -21	; 2
	420	[136]	CALL     	2 2 1
	421	[137]	GETGLOBAL	2 -6	; assert
	422	[137]	GETTABLE 	2 2 -18	; "spy"
	423	[137]	GETTABLE 	3 1 -23	; "turnOffFrontlightHW"
	424	[137]	CALL     	2 2 2
	425	[137]	GETTABLE 	2 2 -16	; "is_called"
	426	[137]	LOADK    	3 -21	; 2
	427	[137]	CALL     	2 2 1
	428	[138]	RETURN   	0 1

function <./spec/unit/frontlight_spec.lua:140,194> (263 instructions, 1052 bytes at 0x7fe903c067c0)
1 param, 6 slots, 2 upvalues, 2 locals, 27 constants, 0 functions
	1	[141]	GETGLOBAL	1 -1	; assert
	2	[141]	LT       	1 0 -2	; - 2
	3	[141]	JMP      	1	; to 5
	4	[141]	LOADBOOL 	2 0 1
	5	[141]	LOADBOOL 	2 1 0
	6	[141]	CALL     	1 2 1
	7	[142]	GETUPVAL 	1 0	; param
	8	[142]	SETTABLE 	1 -3 0	; "fl_min" -
	9	[143]	GETUPVAL 	1 0	; param
	10	[143]	SETTABLE 	1 -4 -2	; "fl_intensity" 2
	11	[144]	GETUPVAL 	1 1	; PowerD
	12	[144]	SELF     	1 1 -5	; "new"
	13	[144]	GETUPVAL 	3 0	; param
	14	[144]	CALL     	1 3 2
	15	[145]	SELF     	2 1 -6	; "setIntensity"
	16	[145]	LOADK    	4 -2	; 2
	17	[145]	CALL     	2 3 1
	18	[146]	GETGLOBAL	2 -1	; assert
	19	[146]	GETTABLE 	2 2 -7	; "are"
	20	[146]	GETTABLE 	2 2 -8	; "equal"
	21	[146]	LOADK    	3 -2	; 2
	22	[146]	SELF     	4 1 -9	; "frontlightIntensityHW"
	23	[146]	CALL     	4 2 0
	24	[146]	CALL     	2 0 1
	25	[147]	GETGLOBAL	2 -1	; assert
	26	[147]	GETTABLE 	2 2 -7	; "are"
	27	[147]	GETTABLE 	2 2 -8	; "equal"
	28	[147]	LOADK    	3 -2	; 2
	29	[147]	SELF     	4 1 -10	; "frontlightIntensity"
	30	[147]	CALL     	4 2 0
	31	[147]	CALL     	2 0 1
	32	[148]	GETGLOBAL	2 -1	; assert
	33	[148]	GETTABLE 	2 2 -11	; "is"
	34	[148]	GETTABLE 	2 2 -12	; "truthy"
	35	[148]	SELF     	3 1 -13	; "isFrontlightOn"
	36	[148]	CALL     	3 2 0
	37	[148]	CALL     	2 0 1
	38	[149]	GETGLOBAL	2 -1	; assert
	39	[149]	GETTABLE 	2 2 -14	; "stub"
	40	[149]	GETTABLE 	3 1 -15	; "init"
	41	[149]	CALL     	2 2 2
	42	[149]	GETTABLE 	2 2 -16	; "is_called"
	43	[149]	LOADK    	3 -17	; 1
	44	[149]	CALL     	2 2 1
	45	[151]	GETGLOBAL	2 -1	; assert
	46	[151]	GETTABLE 	2 2 -7	; "are"
	47	[151]	GETTABLE 	2 2 -8	; "equal"
	48	[151]	LOADK    	3 -2	; 2
	49	[151]	GETTABLE 	4 1 -18	; "frontlight"
	50	[151]	CALL     	2 3 1
	51	[152]	GETGLOBAL	2 -1	; assert
	52	[152]	GETTABLE 	2 2 -19	; "spy"
	53	[152]	GETTABLE 	3 1 -20	; "turnOnFrontlightHW"
	54	[152]	CALL     	2 2 2
	55	[152]	GETTABLE 	2 2 -16	; "is_called"
	56	[152]	LOADK    	3 -21	; 0
	57	[152]	CALL     	2 2 1
	58	[153]	GETGLOBAL	2 -1	; assert
	59	[153]	GETTABLE 	2 2 -19	; "spy"
	60	[153]	GETTABLE 	3 1 -22	; "turnOffFrontlightHW"
	61	[153]	CALL     	2 2 2
	62	[153]	GETTABLE 	2 2 -16	; "is_called"
	63	[153]	LOADK    	3 -21	; 0
	64	[153]	CALL     	2 2 1
	65	[155]	GETGLOBAL	2 -1	; assert
	66	[155]	GETTABLE 	2 2 -11	; "is"
	67	[155]	GETTABLE 	2 2 -23	; "falsy"
	68	[155]	SELF     	3 1 -6	; "setIntensity"
	69	[155]	LOADK    	5 -2	; 2
	70	[155]	CALL     	3 3 0
	71	[155]	CALL     	2 0 1
	72	[156]	GETGLOBAL	2 -1	; assert
	73	[156]	GETTABLE 	2 2 -7	; "are"
	74	[156]	GETTABLE 	2 2 -8	; "equal"
	75	[156]	LOADK    	3 -2	; 2
	76	[156]	SELF     	4 1 -10	; "frontlightIntensity"
	77	[156]	CALL     	4 2 0
	78	[156]	CALL     	2 0 1
	79	[157]	GETGLOBAL	2 -1	; assert
	80	[157]	GETTABLE 	2 2 -11	; "is"
	81	[157]	GETTABLE 	2 2 -12	; "truthy"
	82	[157]	SELF     	3 1 -13	; "isFrontlightOn"
	83	[157]	CALL     	3 2 0
	84	[157]	CALL     	2 0 1
	85	[159]	GETGLOBAL	2 -1	; assert
	86	[159]	GETTABLE 	2 2 -7	; "are"
	87	[159]	GETTABLE 	2 2 -8	; "equal"
	88	[159]	LOADK    	3 -2	; 2
	89	[159]	GETTABLE 	4 1 -18	; "frontlight"
	90	[159]	CALL     	2 3 1
	91	[160]	GETGLOBAL	2 -1	; assert
	92	[160]	GETTABLE 	2 2 -19	; "spy"
	93	[160]	GETTABLE 	3 1 -20	; "turnOnFrontlightHW"
	94	[160]	CALL     	2 2 2
	95	[160]	GETTABLE 	2 2 -16	; "is_called"
	96	[160]	LOADK    	3 -21	; 0
	97	[160]	CALL     	2 2 1
	98	[161]	GETGLOBAL	2 -1	; assert
	99	[161]	GETTABLE 	2 2 -19	; "spy"
	100	[161]	GETTABLE 	3 1 -22	; "turnOffFrontlightHW"
	101	[161]	CALL     	2 2 2
	102	[161]	GETTABLE 	2 2 -16	; "is_called"
	103	[161]	LOADK    	3 -21	; 0
	104	[161]	CALL     	2 2 1
	105	[163]	GETGLOBAL	2 -1	; assert
	106	[163]	GETTABLE 	2 2 -11	; "is"
	107	[163]	GETTABLE 	2 2 -23	; "falsy"
	108	[163]	SELF     	3 1 -24	; "turnOnFrontlight"
	109	[163]	CALL     	3 2 0
	110	[163]	CALL     	2 0 1
	111	[164]	GETGLOBAL	2 -1	; assert
	112	[164]	GETTABLE 	2 2 -7	; "are"
	113	[164]	GETTABLE 	2 2 -8	; "equal"
	114	[164]	LOADK    	3 -2	; 2
	115	[164]	SELF     	4 1 -10	; "frontlightIntensity"
	116	[164]	CALL     	4 2 0
	117	[164]	CALL     	2 0 1
	118	[165]	GETGLOBAL	2 -1	; assert
	119	[165]	GETTABLE 	2 2 -11	; "is"
	120	[165]	GETTABLE 	2 2 -12	; "truthy"
	121	[165]	SELF     	3 1 -13	; "isFrontlightOn"
	122	[165]	CALL     	3 2 0
	123	[165]	CALL     	2 0 1
	124	[167]	GETGLOBAL	2 -1	; assert
	125	[167]	GETTABLE 	2 2 -7	; "are"
	126	[167]	GETTABLE 	2 2 -8	; "equal"
	127	[167]	LOADK    	3 -2	; 2
	128	[167]	GETTABLE 	4 1 -18	; "frontlight"
	129	[167]	CALL     	2 3 1
	130	[168]	GETGLOBAL	2 -1	; assert
	131	[168]	GETTABLE 	2 2 -19	; "spy"
	132	[168]	GETTABLE 	3 1 -20	; "turnOnFrontlightHW"
	133	[168]	CALL     	2 2 2
	134	[168]	GETTABLE 	2 2 -16	; "is_called"
	135	[168]	LOADK    	3 -21	; 0
	136	[168]	CALL     	2 2 1
	137	[169]	GETGLOBAL	2 -1	; assert
	138	[169]	GETTABLE 	2 2 -19	; "spy"
	139	[169]	GETTABLE 	3 1 -22	; "turnOffFrontlightHW"
	140	[169]	CALL     	2 2 2
	141	[169]	GETTABLE 	2 2 -16	; "is_called"
	142	[169]	LOADK    	3 -21	; 0
	143	[169]	CALL     	2 2 1
	144	[171]	GETGLOBAL	2 -1	; assert
	145	[171]	GETTABLE 	2 2 -11	; "is"
	146	[171]	GETTABLE 	2 2 -12	; "truthy"
	147	[171]	SELF     	3 1 -25	; "turnOffFrontlight"
	148	[171]	CALL     	3 2 0
	149	[171]	CALL     	2 0 1
	150	[172]	GETGLOBAL	2 -1	; assert
	151	[172]	GETTABLE 	2 2 -7	; "are"
	152	[172]	GETTABLE 	2 2 -8	; "equal"
	153	[172]	LOADK    	3 -21	; 0
	154	[172]	SELF     	4 1 -10	; "frontlightIntensity"
	155	[172]	CALL     	4 2 0
	156	[172]	CALL     	2 0 1
	157	[173]	GETGLOBAL	2 -1	; assert
	158	[173]	GETTABLE 	2 2 -11	; "is"
	159	[173]	GETTABLE 	2 2 -12	; "truthy"
	160	[173]	SELF     	3 1 -26	; "isFrontlightOff"
	161	[173]	CALL     	3 2 0
	162	[173]	CALL     	2 0 1
	163	[175]	GETGLOBAL	2 -1	; assert
	164	[175]	GETTABLE 	2 2 -7	; "are"
	165	[175]	GETTABLE 	2 2 -8	; "equal"
	166	[175]	GETUPVAL 	3 0	; param
	167	[175]	GETTABLE 	3 3 -3	; "fl_min"
	168	[175]	GETTABLE 	4 1 -18	; "frontlight"
	169	[175]	CALL     	2 3 1
	170	[176]	GETGLOBAL	2 -1	; assert
	171	[176]	GETTABLE 	2 2 -19	; "spy"
	172	[176]	GETTABLE 	3 1 -20	; "turnOnFrontlightHW"
	173	[176]	CALL     	2 2 2
	174	[176]	GETTABLE 	2 2 -16	; "is_called"
	175	[176]	LOADK    	3 -21	; 0
	176	[176]	CALL     	2 2 1
	177	[177]	GETGLOBAL	2 -1	; assert
	178	[177]	GETTABLE 	2 2 -19	; "spy"
	179	[177]	GETTABLE 	3 1 -22	; "turnOffFrontlightHW"
	180	[177]	CALL     	2 2 2
	181	[177]	GETTABLE 	2 2 -16	; "is_called"
	182	[177]	LOADK    	3 -17	; 1
	183	[177]	CALL     	2 2 1
	184	[179]	GETGLOBAL	2 -1	; assert
	185	[179]	GETTABLE 	2 2 -11	; "is"
	186	[179]	GETTABLE 	2 2 -12	; "truthy"
	187	[179]	SELF     	3 1 -27	; "toggleFrontlight"
	188	[179]	CALL     	3 2 0
	189	[179]	CALL     	2 0 1
	190	[180]	GETGLOBAL	2 -1	; assert
	191	[180]	GETTABLE 	2 2 -7	; "are"
	192	[180]	GETTABLE 	2 2 -8	; "equal"
	193	[180]	LOADK    	3 -2	; 2
	194	[180]	SELF     	4 1 -10	; "frontlightIntensity"
	195	[180]	CALL     	4 2 0
	196	[180]	CALL     	2 0 1
	197	[181]	GETGLOBAL	2 -1	; assert
	198	[181]	GETTABLE 	2 2 -11	; "is"
	199	[181]	GETTABLE 	2 2 -12	; "truthy"
	200	[181]	SELF     	3 1 -13	; "isFrontlightOn"
	201	[181]	CALL     	3 2 0
	202	[181]	CALL     	2 0 1
	203	[183]	GETGLOBAL	2 -1	; assert
	204	[183]	GETTABLE 	2 2 -7	; "are"
	205	[183]	GETTABLE 	2 2 -8	; "equal"
	206	[183]	LOADK    	3 -2	; 2
	207	[183]	GETTABLE 	4 1 -18	; "frontlight"
	208	[183]	CALL     	2 3 1
	209	[184]	GETGLOBAL	2 -1	; assert
	210	[184]	GETTABLE 	2 2 -19	; "spy"
	211	[184]	GETTABLE 	3 1 -20	; "turnOnFrontlightHW"
	212	[184]	CALL     	2 2 2
	213	[184]	GETTABLE 	2 2 -16	; "is_called"
	214	[184]	LOADK    	3 -17	; 1
	215	[184]	CALL     	2 2 1
	216	[185]	GETGLOBAL	2 -1	; assert
	217	[185]	GETTABLE 	2 2 -19	; "spy"
	218	[185]	GETTABLE 	3 1 -22	; "turnOffFrontlightHW"
	219	[185]	CALL     	2 2 2
	220	[185]	GETTABLE 	2 2 -16	; "is_called"
	221	[185]	LOADK    	3 -17	; 1
	222	[185]	CALL     	2 2 1
	223	[187]	GETGLOBAL	2 -1	; assert
	224	[187]	GETTABLE 	2 2 -11	; "is"
	225	[187]	GETTABLE 	2 2 -12	; "truthy"
	226	[187]	SELF     	3 1 -27	; "toggleFrontlight"
	227	[187]	CALL     	3 2 0
	228	[187]	CALL     	2 0 1
	229	[188]	GETGLOBAL	2 -1	; assert
	230	[188]	GETTABLE 	2 2 -7	; "are"
	231	[188]	GETTABLE 	2 2 -8	; "equal"
	232	[188]	LOADK    	3 -21	; 0
	233	[188]	SELF     	4 1 -10	; "frontlightIntensity"
	234	[188]	CALL     	4 2 0
	235	[188]	CALL     	2 0 1
	236	[189]	GETGLOBAL	2 -1	; assert
	237	[189]	GETTABLE 	2 2 -11	; "is"
	238	[189]	GETTABLE 	2 2 -12	; "truthy"
	239	[189]	SELF     	3 1 -26	; "isFrontlightOff"
	240	[189]	CALL     	3 2 0
	241	[189]	CALL     	2 0 1
	242	[191]	GETGLOBAL	2 -1	; assert
	243	[191]	GETTABLE 	2 2 -7	; "are"
	244	[191]	GETTABLE 	2 2 -8	; "equal"
	245	[191]	GETUPVAL 	3 0	; param
	246	[191]	GETTABLE 	3 3 -3	; "fl_min"
	247	[191]	GETTABLE 	4 1 -18	; "frontlight"
	248	[191]	CALL     	2 3 1
	249	[192]	GETGLOBAL	2 -1	; assert
	250	[192]	GETTABLE 	2 2 -19	; "spy"
	251	[192]	GETTABLE 	3 1 -20	; "turnOnFrontlightHW"
	252	[192]	CALL     	2 2 2
	253	[192]	GETTABLE 	2 2 -16	; "is_called"
	254	[192]	LOADK    	3 -17	; 1
	255	[192]	CALL     	2 2 1
	256	[193]	GETGLOBAL	2 -1	; assert
	257	[193]	GETTABLE 	2 2 -19	; "spy"
	258	[193]	GETTABLE 	3 1 -22	; "turnOffFrontlightHW"
	259	[193]	CALL     	2 2 2
	260	[193]	GETTABLE 	2 2 -16	; "is_called"
	261	[193]	LOADK    	3 -2	; 2
	262	[193]	CALL     	2 2 1
	263	[194]	RETURN   	0 1

function <./spec/unit/frontlight_spec.lua:196,198> (4 instructions, 16 bytes at 0x7fe903c08ce0)
0 params, 2 slots, 1 upvalue, 0 locals, 1 constant, 0 functions
	1	[197]	GETUPVAL 	0 0	; test_when_off
	2	[197]	LOADK    	1 -1	; 0
	3	[197]	CALL     	0 2 1
	4	[198]	RETURN   	0 1

function <./spec/unit/frontlight_spec.lua:201,201> (4 instructions, 16 bytes at 0x7fe903c089a0)
0 params, 2 slots, 1 upvalue, 0 locals, 1 constant, 0 functions
	1	[201]	GETUPVAL 	0 0	; test_when_off
	2	[201]	LOADK    	1 -1	; 1
	3	[201]	CALL     	0 2 1
	4	[201]	RETURN   	0 1

function <./spec/unit/frontlight_spec.lua:203,205> (4 instructions, 16 bytes at 0x7fe903c09530)
0 params, 2 slots, 1 upvalue, 0 locals, 1 constant, 0 functions
	1	[204]	GETUPVAL 	0 0	; test_when_on
	2	[204]	LOADK    	1 -1	; 0
	3	[204]	CALL     	0 2 1
	4	[205]	RETURN   	0 1

function <./spec/unit/frontlight_spec.lua:208,208> (4 instructions, 16 bytes at 0x7fe903c08690)
0 params, 2 slots, 1 upvalue, 0 locals, 1 constant, 0 functions
	1	[208]	GETUPVAL 	0 0	; test_when_on
	2	[208]	LOADK    	1 -1	; 1
	3	[208]	CALL     	0 2 1
	4	[208]	RETURN   	0 1
