
main <./frontend/ui/widget/frontlightwidget.lua:0,0> (191 instructions, 764 bytes at 0x7fd9b14068f0)
0+ params, 34 slots, 0 upvalues, 29 locals, 59 constants, 13 functions
	1	[1]	GETGLOBAL	0 -1	; require
	2	[1]	LOADK    	1 -2	; "ffi/blitbuffer"
	3	[1]	CALL     	0 2 2
	4	[2]	GETGLOBAL	1 -1	; require
	5	[2]	LOADK    	2 -3	; "ui/widget/button"
	6	[2]	CALL     	1 2 2
	7	[3]	GETGLOBAL	2 -1	; require
	8	[3]	LOADK    	3 -4	; "ui/widget/container/centercontainer"
	9	[3]	CALL     	2 2 2
	10	[4]	GETGLOBAL	3 -1	; require
	11	[4]	LOADK    	4 -5	; "ui/widget/checkbutton"
	12	[4]	CALL     	3 2 2
	13	[5]	GETGLOBAL	4 -1	; require
	14	[5]	LOADK    	5 -6	; "ui/widget/closebutton"
	15	[5]	CALL     	4 2 2
	16	[6]	GETGLOBAL	5 -1	; require
	17	[6]	LOADK    	6 -7	; "device"
	18	[6]	CALL     	5 2 2
	19	[7]	GETGLOBAL	6 -1	; require
	20	[7]	LOADK    	7 -8	; "ui/widget/container/framecontainer"
	21	[7]	CALL     	6 2 2
	22	[8]	GETGLOBAL	7 -1	; require
	23	[8]	LOADK    	8 -9	; "ui/geometry"
	24	[8]	CALL     	7 2 2
	25	[9]	GETGLOBAL	8 -1	; require
	26	[9]	LOADK    	9 -10	; "ui/gesturerange"
	27	[9]	CALL     	8 2 2
	28	[10]	GETGLOBAL	9 -1	; require
	29	[10]	LOADK    	10 -11	; "ui/font"
	30	[10]	CALL     	9 2 2
	31	[11]	GETGLOBAL	10 -1	; require
	32	[11]	LOADK    	11 -12	; "ui/widget/horizontalgroup"
	33	[11]	CALL     	10 2 2
	34	[12]	GETGLOBAL	11 -1	; require
	35	[12]	LOADK    	12 -13	; "ui/widget/horizontalspan"
	36	[12]	CALL     	11 2 2
	37	[13]	GETGLOBAL	12 -1	; require
	38	[13]	LOADK    	13 -14	; "ui/widget/container/inputcontainer"
	39	[13]	CALL     	12 2 2
	40	[14]	GETGLOBAL	13 -1	; require
	41	[14]	LOADK    	14 -15	; "ui/widget/linewidget"
	42	[14]	CALL     	13 2 2
	43	[15]	GETGLOBAL	14 -1	; require
	44	[15]	LOADK    	15 -16	; "optmath"
	45	[15]	CALL     	14 2 2
	46	[16]	GETGLOBAL	15 -1	; require
	47	[16]	LOADK    	16 -17	; "ui/widget/naturallightwidget"
	48	[16]	CALL     	15 2 2
	49	[17]	GETGLOBAL	16 -1	; require
	50	[17]	LOADK    	17 -18	; "ui/widget/overlapgroup"
	51	[17]	CALL     	16 2 2
	52	[18]	GETGLOBAL	17 -1	; require
	53	[18]	LOADK    	18 -19	; "ui/widget/progresswidget"
	54	[18]	CALL     	17 2 2
	55	[19]	GETGLOBAL	18 -1	; require
	56	[19]	LOADK    	19 -20	; "ui/size"
	57	[19]	CALL     	18 2 2
	58	[20]	GETGLOBAL	19 -1	; require
	59	[20]	LOADK    	20 -21	; "ui/widget/textboxwidget"
	60	[20]	CALL     	19 2 2
	61	[21]	GETGLOBAL	20 -1	; require
	62	[21]	LOADK    	21 -22	; "ui/widget/textwidget"
	63	[21]	CALL     	20 2 2
	64	[22]	GETGLOBAL	21 -1	; require
	65	[22]	LOADK    	22 -23	; "ui/timeval"
	66	[22]	CALL     	21 2 2
	67	[23]	GETGLOBAL	22 -1	; require
	68	[23]	LOADK    	23 -24	; "ui/uimanager"
	69	[23]	CALL     	22 2 2
	70	[24]	GETGLOBAL	23 -1	; require
	71	[24]	LOADK    	24 -25	; "ui/widget/verticalgroup"
	72	[24]	CALL     	23 2 2
	73	[25]	GETGLOBAL	24 -1	; require
	74	[25]	LOADK    	25 -26	; "ui/widget/verticalspan"
	75	[25]	CALL     	24 2 2
	76	[26]	GETGLOBAL	25 -1	; require
	77	[26]	LOADK    	26 -27	; "ui/widget/container/widgetcontainer"
	78	[26]	CALL     	25 2 2
	79	[27]	GETGLOBAL	26 -1	; require
	80	[27]	LOADK    	27 -28	; "gettext"
	81	[27]	CALL     	26 2 2
	82	[28]	GETTABLE 	27 5 -29	; "screen"
	83	[30]	SELF     	28 12 -30	; "new"
	84	[30]	NEWTABLE 	30 0 7
	85	[31]	SELF     	31 9 -32	; "getFace"
	86	[31]	LOADK    	33 -33	; "x_smalltfont"
	87	[31]	CALL     	31 3 2
	88	[31]	SETTABLE 	30 -31 31	; "title_face" -
	89	[32]	SETTABLE 	30 -34 -35	; "width" nil
	90	[33]	SETTABLE 	30 -36 -35	; "height" nil
	91	[35]	SETTABLE 	30 -37 -38	; "is_always_active" true
	92	[36]	SETTABLE 	30 -39 -40	; "use_system_fl" false
	93	[37]	GETTABLE 	31 27 -42	; "low_pan_rate"
	94	[37]	TEST     	31 0 0
	95	[37]	JMP      	3	; to 99
	96	[37]	LOADK    	31 -43	; 3
	97	[37]	TEST     	31 0 1
	98	[37]	JMP      	1	; to 100
	99	[37]	LOADK    	31 -44	; 30
	100	[37]	SETTABLE 	30 -41 31	; "rate" -
	101	[38]	SELF     	31 21 -30	; "new"
	102	[38]	NEWTABLE 	33 0 0
	103	[38]	CALL     	31 3 2
	104	[38]	SETTABLE 	30 -45 31	; "last_time" -
	105	[30]	CALL     	28 3 2
	106	[119]	CLOSURE  	29 0	; 0x7fd9b1407070
	107	[119]	MOVE     	0 9
	108	[119]	MOVE     	0 27
	109	[119]	MOVE     	0 5
	110	[119]	MOVE     	0 18
	111	[119]	MOVE     	0 1
	112	[119]	MOVE     	0 8
	113	[119]	MOVE     	0 7
	114	[41]	SETTABLE 	28 -46 29	; "init" -
	115	[127]	CLOSURE  	29 1	; 0x7fd9b14086f0
	116	[127]	MOVE     	0 2
	117	[127]	MOVE     	0 7
	118	[121]	SETTABLE 	28 -47 29	; "generateProgressGroup" -
	119	[301]	CLOSURE  	29 2	; 0x7fd9b1408dd0
	120	[301]	MOVE     	0 24
	121	[301]	MOVE     	0 10
	122	[301]	MOVE     	0 23
	123	[301]	MOVE     	0 17
	124	[301]	MOVE     	0 18
	125	[301]	MOVE     	0 27
	126	[301]	MOVE     	0 19
	127	[301]	MOVE     	0 26
	128	[301]	MOVE     	0 1
	129	[301]	MOVE     	0 11
	130	[301]	MOVE     	0 3
	131	[301]	MOVE     	0 22
	132	[301]	MOVE     	0 15
	133	[129]	SETTABLE 	28 -48 29	; "setProgress" -
	134	[509]	CLOSURE  	29 3	; 0x7fd9b140a930
	135	[509]	MOVE     	0 10
	136	[509]	MOVE     	0 24
	137	[509]	MOVE     	0 0
	138	[509]	MOVE     	0 19
	139	[509]	MOVE     	0 26
	140	[509]	MOVE     	0 1
	141	[509]	MOVE     	0 18
	142	[509]	MOVE     	0 11
	143	[509]	MOVE     	0 3
	144	[305]	SETTABLE 	28 -49 29	; "addWarmthWidgets" -
	145	[533]	CLOSURE  	29 4	; 0x7fd9b140d520
	146	[533]	MOVE     	0 5
	147	[511]	SETTABLE 	28 -50 29	; "setFrontLightIntensity" -
	148	[600]	CLOSURE  	29 5	; 0x7fd9b140d960
	149	[600]	MOVE     	0 6
	150	[600]	MOVE     	0 18
	151	[600]	MOVE     	0 20
	152	[600]	MOVE     	0 26
	153	[600]	MOVE     	0 13
	154	[600]	MOVE     	0 7
	155	[600]	MOVE     	0 16
	156	[600]	MOVE     	0 4
	157	[600]	MOVE     	0 0
	158	[600]	MOVE     	0 23
	159	[600]	MOVE     	0 2
	160	[600]	MOVE     	0 25
	161	[535]	SETTABLE 	28 -51 29	; "update" -
	162	[607]	CLOSURE  	29 6	; 0x7fd9b140e2c0
	163	[607]	MOVE     	0 22
	164	[602]	SETTABLE 	28 -52 29	; "onCloseWidget" -
	165	[615]	CLOSURE  	29 7	; 0x7fd9b140e580
	166	[615]	MOVE     	0 22
	167	[609]	SETTABLE 	28 -53 29	; "onShow" -
	168	[620]	CLOSURE  	29 8	; 0x7fd9b140ed40
	169	[620]	MOVE     	0 22
	170	[617]	SETTABLE 	28 -54 29	; "onAnyKeyPressed" -
	171	[625]	CLOSURE  	29 9	; 0x7fd9b140ee50
	172	[625]	MOVE     	0 22
	173	[622]	SETTABLE 	28 -55 29	; "onClose" -
	174	[637]	CLOSURE  	29 10	; 0x7fd9b140f0c0
	175	[637]	MOVE     	0 22
	176	[628]	SETTABLE 	28 -56 29	; "naturalLightConfigOpen" -
	177	[647]	CLOSURE  	29 11	; 0x7fd9b140b950
	178	[647]	MOVE     	0 4
	179	[647]	MOVE     	0 18
	180	[647]	MOVE     	0 22
	181	[639]	SETTABLE 	28 -57 29	; "naturalLightConfigClose" -
	182	[683]	CLOSURE  	29 12	; 0x7fd9b140c970
	183	[683]	MOVE     	0 22
	184	[683]	MOVE     	0 14
	185	[683]	MOVE     	0 27
	186	[683]	MOVE     	0 21
	187	[649]	SETTABLE 	28 -58 29	; "onTapProgress" -
	188	[685]	GETTABLE 	29 28 -58	; "onTapProgress"
	189	[685]	SETTABLE 	28 -59 29	; "onPanProgress" -
	190	[687]	RETURN   	28 2
	191	[687]	RETURN   	0 1

function <./frontend/ui/widget/frontlightwidget.lua:41,119> (204 instructions, 816 bytes at 0x7fd9b1407070)
1 param, 14 slots, 7 upvalues, 5 locals, 80 constants, 0 functions
	1	[42]	GETTABLE 	1 0 -2	; "use_system_fl"
	2	[42]	TEST     	1 0 0
	3	[42]	JMP      	4	; to 8
	4	[42]	GETGLOBAL	1 -3	; G_reader_settings
	5	[42]	SELF     	1 1 -4	; "nilOrTrue"
	6	[42]	LOADK    	3 -1	; "light_fallback"
	7	[42]	CALL     	1 3 2
	8	[42]	SETTABLE 	0 -1 1	; "light_fallback" -
	9	[43]	GETUPVAL 	1 0	; Font
	10	[43]	SELF     	1 1 -6	; "getFace"
	11	[43]	LOADK    	3 -7	; "ffont"
	12	[43]	CALL     	1 3 2
	13	[43]	SETTABLE 	0 -5 1	; "medium_font_face" -
	14	[44]	GETUPVAL 	1 0	; Font
	15	[44]	SELF     	1 1 -6	; "getFace"
	16	[44]	LOADK    	3 -9	; "cfont"
	17	[44]	CALL     	1 3 2
	18	[44]	SETTABLE 	0 -8 1	; "larger_font_face" -
	19	[45]	NEWTABLE 	1 0 0
	20	[45]	SETTABLE 	0 -10 1	; "light_bar" -
	21	[46]	GETUPVAL 	1 1	; Screen
	22	[46]	SELF     	1 1 -12	; "getWidth"
	23	[46]	CALL     	1 2 2
	24	[46]	SETTABLE 	0 -11 1	; "screen_width" -
	25	[47]	GETUPVAL 	1 1	; Screen
	26	[47]	SELF     	1 1 -14	; "getHeight"
	27	[47]	CALL     	1 2 2
	28	[47]	SETTABLE 	0 -13 1	; "screen_height" -
	29	[48]	GETGLOBAL	1 -16	; math
	30	[48]	GETTABLE 	1 1 -17	; "ceil"
	31	[48]	GETTABLE 	2 0 -13	; "screen_height"
	32	[48]	MUL      	2 2 -18	; - 0.01
	33	[48]	CALL     	1 2 2
	34	[48]	SETTABLE 	0 -15 1	; "span" -
	35	[49]	GETTABLE 	1 0 -11	; "screen_width"
	36	[49]	MUL      	1 1 -20	; - 0.95
	37	[49]	SETTABLE 	0 -19 1	; "width" -
	38	[50]	GETUPVAL 	1 2	; Device
	39	[50]	SELF     	1 1 -22	; "getPowerDevice"
	40	[50]	CALL     	1 2 2
	41	[50]	SETTABLE 	0 -21 1	; "powerd" -
	42	[51]	GETTABLE 	1 0 -21	; "powerd"
	43	[51]	GETTABLE 	1 1 -23	; "fl_min"
	44	[51]	SETTABLE 	0 -23 1	; "fl_min" -
	45	[52]	GETTABLE 	1 0 -21	; "powerd"
	46	[52]	GETTABLE 	1 1 -24	; "fl_max"
	47	[52]	SETTABLE 	0 -24 1	; "fl_max" -
	48	[53]	GETTABLE 	1 0 -21	; "powerd"
	49	[53]	SELF     	1 1 -26	; "frontlightIntensity"
	50	[53]	CALL     	1 2 2
	51	[53]	SETTABLE 	0 -25 1	; "fl_cur" -
	52	[54]	GETTABLE 	1 0 -24	; "fl_max"
	53	[54]	GETTABLE 	2 0 -23	; "fl_min"
	54	[54]	SUB      	1 1 2
	55	[54]	ADD      	1 1 -27	; - 1
	56	[55]	GETGLOBAL	2 -16	; math
	57	[55]	GETTABLE 	2 2 -17	; "ceil"
	58	[55]	DIV      	3 1 -29	; - 25
	59	[55]	CALL     	2 2 2
	60	[55]	SETTABLE 	0 -28 2	; "one_step" -
	61	[56]	GETGLOBAL	2 -16	; math
	62	[56]	GETTABLE 	2 2 -17	; "ceil"
	63	[56]	GETTABLE 	3 0 -28	; "one_step"
	64	[56]	DIV      	3 1 3
	65	[56]	CALL     	2 2 2
	66	[56]	SETTABLE 	0 -30 2	; "steps" -
	67	[57]	GETTABLE 	2 0 -30	; "steps"
	68	[57]	SUB      	2 2 -27	; - 1
	69	[57]	GETTABLE 	3 0 -28	; "one_step"
	70	[57]	MUL      	2 2 3
	71	[57]	GETTABLE 	3 0 -24	; "fl_max"
	72	[57]	GETTABLE 	4 0 -23	; "fl_min"
	73	[57]	SUB      	3 3 4
	74	[57]	LT       	0 2 3
	75	[57]	JMP      	3	; to 79
	76	[58]	GETTABLE 	2 0 -30	; "steps"
	77	[58]	ADD      	2 2 -27	; - 1
	78	[58]	SETTABLE 	0 -30 2	; "steps" -
	79	[60]	GETGLOBAL	2 -16	; math
	80	[60]	GETTABLE 	2 2 -31	; "min"
	81	[60]	GETTABLE 	3 0 -30	; "steps"
	82	[60]	MOVE     	4 1
	83	[60]	CALL     	2 3 2
	84	[60]	SETTABLE 	0 -30 2	; "steps" -
	85	[61]	GETUPVAL 	2 2	; Device
	86	[61]	SELF     	2 2 -33	; "hasNaturalLight"
	87	[61]	CALL     	2 2 2
	88	[61]	SETTABLE 	0 -32 2	; "natural_light" -
	89	[62]	GETUPVAL 	2 2	; Device
	90	[62]	SELF     	2 2 -35	; "hasNaturalLightMixer"
	91	[62]	CALL     	2 2 2
	92	[62]	SETTABLE 	0 -34 2	; "has_nl_mixer" -
	93	[64]	GETTABLE 	2 0 -32	; "natural_light"
	94	[64]	TEST     	2 0 0
	95	[64]	JMP      	9	; to 105
	96	[65]	GETTABLE 	2 0 -21	; "powerd"
	97	[65]	GETTABLE 	2 2 -37	; "fl_warmth_min"
	98	[65]	SETTABLE 	0 -36 2	; "nl_min" -
	99	[66]	GETTABLE 	2 0 -21	; "powerd"
	100	[66]	GETTABLE 	2 2 -39	; "fl_warmth_max"
	101	[66]	SETTABLE 	0 -38 2	; "nl_max" -
	102	[68]	GETTABLE 	2 0 -38	; "nl_max"
	103	[68]	DIV      	2 -41 2	; 100 -
	104	[68]	SETTABLE 	0 -40 2	; "nl_scale" -
	105	[72]	GETUPVAL 	2 3	; Size
	106	[72]	GETTABLE 	2 2 -42	; "margin"
	107	[72]	GETTABLE 	2 2 -43	; "tiny"
	108	[73]	GETUPVAL 	3 3	; Size
	109	[73]	GETTABLE 	3 3 -44	; "padding"
	110	[73]	GETTABLE 	3 3 -45	; "button"
	111	[74]	GETUPVAL 	4 3	; Size
	112	[74]	GETTABLE 	4 4 -46	; "border"
	113	[74]	GETTABLE 	4 4 -45	; "button"
	114	[75]	SETTABLE 	0 -47 -48	; "auto_nl" false
	115	[76]	GETGLOBAL	5 -16	; math
	116	[76]	GETTABLE 	5 5 -50	; "floor"
	117	[76]	GETTABLE 	6 0 -11	; "screen_width"
	118	[76]	MUL      	6 6 -51	; - 0.9
	119	[76]	GETTABLE 	7 0 -30	; "steps"
	120	[76]	DIV      	6 6 7
	121	[76]	CALL     	5 2 2
	122	[77]	ADD      	6 2 3
	123	[77]	ADD      	6 6 4
	124	[77]	MUL      	6 -52 6	; 2 -
	125	[77]	SUB      	5 5 6
	126	[77]	SETTABLE 	0 -49 5	; "button_width" -
	127	[79]	GETUPVAL 	5 4	; Button
	128	[79]	SELF     	5 5 -54	; "new"
	129	[79]	NEWTABLE 	7 0 8
	130	[80]	SETTABLE 	7 -55 -56	; "text" ""
	131	[81]	SETTABLE 	7 -57 -58	; "radius" 0
	132	[82]	SETTABLE 	7 -42 2	; "margin" -
	133	[83]	SETTABLE 	7 -44 3	; "padding" -
	134	[84]	SETTABLE 	7 -59 4	; "bordersize" -
	135	[85]	GETTABLE 	8 0 -1	; "light_fallback"
	136	[85]	NOT      	8 8
	137	[85]	SETTABLE 	7 -60 8	; "enabled" -
	138	[86]	GETTABLE 	8 0 -49	; "button_width"
	139	[86]	SETTABLE 	7 -19 8	; "width" -
	140	[87]	SETTABLE 	7 -61 0	; "show_parent" -
	141	[79]	CALL     	5 3 2
	142	[88]	SETTABLE 	0 -53 5	; "fl_prog_button" -
	143	[89]	GETUPVAL 	5 2	; Device
	144	[89]	SELF     	5 5 -62	; "hasKeys"
	145	[89]	CALL     	5 2 2
	146	[89]	TEST     	5 0 0
	147	[89]	JMP      	9	; to 157
	148	[90]	NEWTABLE 	5 0 1
	149	[91]	NEWTABLE 	6 1 1
	150	[91]	NEWTABLE 	7 1 0
	151	[91]	LOADK    	8 -65	; "Back"
	152	[91]	SETLIST  	7 1 1	; 1
	153	[91]	SETTABLE 	6 -66 -67	; "doc" "close frontlight"
	154	[91]	SETLIST  	6 1 1	; 1
	155	[91]	SETTABLE 	5 -64 6	; "Close" -
	156	[92]	SETTABLE 	0 -63 5	; "key_events" -
	157	[94]	GETUPVAL 	5 2	; Device
	158	[94]	SELF     	5 5 -68	; "isTouchDevice"
	159	[94]	CALL     	5 2 2
	160	[94]	TEST     	5 0 0
	161	[94]	JMP      	40	; to 202
	162	[95]	NEWTABLE 	5 0 2
	163	[96]	NEWTABLE 	6 0 0
	164	[97]	GETUPVAL 	7 5	; GestureRange
	165	[97]	SELF     	7 7 -54	; "new"
	166	[97]	NEWTABLE 	9 0 2
	167	[98]	SETTABLE 	9 -71 -72	; "ges" "tap"
	168	[99]	GETUPVAL 	10 6	; Geom
	169	[99]	SELF     	10 10 -54	; "new"
	170	[99]	NEWTABLE 	12 0 4
	171	[100]	SETTABLE 	12 -74 -58	; "x" 0
	172	[100]	SETTABLE 	12 -75 -58	; "y" 0
	173	[101]	GETTABLE 	13 0 -11	; "screen_width"
	174	[101]	SETTABLE 	12 -76 13	; "w" -
	175	[102]	GETTABLE 	13 0 -13	; "screen_height"
	176	[102]	SETTABLE 	12 -77 13	; "h" -
	177	[99]	CALL     	10 3 2
	178	[103]	SETTABLE 	9 -73 10	; "range" -
	179	[97]	CALL     	7 3 0
	180	[105]	SETLIST  	6 0 1	; 1
	181	[105]	SETTABLE 	5 -70 6	; "TapProgress" -
	182	[106]	NEWTABLE 	6 0 0
	183	[107]	GETUPVAL 	7 5	; GestureRange
	184	[107]	SELF     	7 7 -54	; "new"
	185	[107]	NEWTABLE 	9 0 2
	186	[108]	SETTABLE 	9 -71 -79	; "ges" "pan"
	187	[109]	GETUPVAL 	10 6	; Geom
	188	[109]	SELF     	10 10 -54	; "new"
	189	[109]	NEWTABLE 	12 0 4
	190	[110]	SETTABLE 	12 -74 -58	; "x" 0
	191	[110]	SETTABLE 	12 -75 -58	; "y" 0
	192	[111]	GETTABLE 	13 0 -11	; "screen_width"
	193	[111]	SETTABLE 	12 -76 13	; "w" -
	194	[112]	GETTABLE 	13 0 -13	; "screen_height"
	195	[112]	SETTABLE 	12 -77 13	; "h" -
	196	[109]	CALL     	10 3 2
	197	[113]	SETTABLE 	9 -73 10	; "range" -
	198	[107]	CALL     	7 3 0
	199	[115]	SETLIST  	6 0 1	; 1
	200	[115]	SETTABLE 	5 -78 6	; "PanProgress" -
	201	[116]	SETTABLE 	0 -69 5	; "ges_events" -
	202	[118]	SELF     	5 0 -80	; "update"
	203	[118]	CALL     	5 2 1
	204	[119]	RETURN   	0 1

function <./frontend/ui/widget/frontlightwidget.lua:121,127> (19 instructions, 76 bytes at 0x7fd9b14086f0)
5 params, 11 slots, 2 upvalues, 5 locals, 6 constants, 0 functions
	1	[122]	GETUPVAL 	5 0	; CenterContainer
	2	[122]	SELF     	5 5 -2	; "new"
	3	[122]	NEWTABLE 	7 0 1
	4	[123]	GETUPVAL 	8 1	; Geom
	5	[123]	SELF     	8 8 -2	; "new"
	6	[123]	NEWTABLE 	10 0 2
	7	[123]	SETTABLE 	10 -4 1	; "w" -
	8	[123]	SETTABLE 	10 -5 2	; "h" -
	9	[123]	CALL     	8 3 2
	10	[123]	SETTABLE 	7 -3 8	; "dimen" -
	11	[122]	CALL     	5 3 2
	12	[124]	SETTABLE 	0 -1 5	; "fl_container" -
	13	[125]	SELF     	5 0 -6	; "setProgress"
	14	[125]	MOVE     	7 3
	15	[125]	MOVE     	8 4
	16	[125]	CALL     	5 4 1
	17	[126]	GETTABLE 	5 0 -1	; "fl_container"
	18	[126]	RETURN   	5 2
	19	[127]	RETURN   	0 1

function <./frontend/ui/widget/frontlightwidget.lua:129,301> (428 instructions, 1712 bytes at 0x7fd9b1408dd0)
4 params, 28 slots, 13 upvalues, 26 locals, 69 constants, 8 functions
	1	[130]	GETTABLE 	4 0 -1	; "fl_container"
	2	[130]	SELF     	4 4 -2	; "clear"
	3	[130]	CALL     	4 2 1
	4	[131]	GETUPVAL 	4 0	; VerticalSpan
	5	[131]	SELF     	4 4 -3	; "new"
	6	[131]	NEWTABLE 	6 0 1
	7	[131]	GETTABLE 	7 0 -5	; "span"
	8	[131]	SETTABLE 	6 -4 7	; "width" -
	9	[131]	CALL     	4 3 2
	10	[132]	GETUPVAL 	5 1	; HorizontalGroup
	11	[132]	SELF     	5 5 -3	; "new"
	12	[132]	NEWTABLE 	7 0 1
	13	[132]	SETTABLE 	7 -6 -7	; "align" "center"
	14	[132]	CALL     	5 3 2
	15	[133]	GETUPVAL 	6 1	; HorizontalGroup
	16	[133]	SELF     	6 6 -3	; "new"
	17	[133]	NEWTABLE 	8 0 1
	18	[133]	SETTABLE 	8 -6 -7	; "align" "center"
	19	[133]	CALL     	6 3 2
	20	[134]	GETUPVAL 	7 2	; VerticalGroup
	21	[134]	SELF     	7 7 -3	; "new"
	22	[134]	NEWTABLE 	9 0 1
	23	[134]	SETTABLE 	9 -6 -7	; "align" "center"
	24	[134]	CALL     	7 3 2
	25	[135]	GETTABLE 	8 0 -8	; "fl_prog_button"
	26	[135]	GETTABLE 	9 0 -10	; "light_fallback"
	27	[135]	NOT      	9 9
	28	[135]	SETTABLE 	8 -9 9	; "enabled" -
	29	[136]	LOADBOOL 	8 1 0
	30	[137]	LOADBOOL 	9 1 0
	31	[138]	GETTABLE 	10 0 -11	; "natural_light"
	32	[138]	TEST     	10 0 0
	33	[138]	JMP      	4	; to 38
	34	[139]	TEST     	3 0 1
	35	[139]	JMP      	2	; to 38
	36	[139]	GETTABLE 	10 0 -12	; "powerd"
	37	[139]	GETTABLE 	3 10 -13	; "fl_warmth"
	38	[141]	TEST     	1 0 0
	39	[141]	JMP      	19	; to 59
	40	[144]	GETTABLE 	10 0 -14	; "fl_min"
	41	[144]	EQ       	1 1 10
	42	[144]	JMP      	3	; to 46
	43	[144]	GETTABLE 	10 0 -15	; "fl_cur"
	44	[144]	EQ       	1 1 10
	45	[144]	JMP      	3	; to 49
	46	[145]	SELF     	10 0 -16	; "setFrontLightIntensity"
	47	[145]	MOVE     	12 1
	48	[145]	CALL     	10 3 1
	49	[148]	GETTABLE 	10 0 -15	; "fl_cur"
	50	[148]	GETTABLE 	11 0 -17	; "fl_max"
	51	[148]	EQ       	0 10 11
	52	[148]	JMP      	1	; to 54
	53	[148]	LOADBOOL 	8 0 0
	54	[149]	GETTABLE 	10 0 -15	; "fl_cur"
	55	[149]	GETTABLE 	11 0 -14	; "fl_min"
	56	[149]	EQ       	0 10 11
	57	[149]	JMP      	1	; to 59
	58	[149]	LOADBOOL 	9 0 0
	59	[152]	NEWTABLE 	10 0 0
	60	[153]	LOADK    	11 -18	; 1
	61	[153]	GETTABLE 	12 0 -19	; "steps"
	62	[153]	SUB      	12 12 -20	; - 2
	63	[153]	LOADK    	13 -18	; 1
	64	[153]	FORPREP  	11 6	; to 71
	65	[154]	GETGLOBAL	15 -21	; table
	66	[154]	GETTABLE 	15 15 -22	; "insert"
	67	[154]	MOVE     	16 10
	68	[154]	GETTABLE 	17 0 -23	; "one_step"
	69	[154]	MUL      	17 14 17
	70	[154]	CALL     	15 3 1
	71	[153]	FORLOOP  	11 -7	; to 65
	72	[157]	GETUPVAL 	11 3	; ProgressWidget
	73	[157]	SELF     	11 11 -3	; "new"
	74	[157]	NEWTABLE 	13 0 6
	75	[158]	GETTABLE 	14 0 -25	; "screen_width"
	76	[158]	MUL      	14 14 -26	; - 0.9
	77	[158]	SETTABLE 	13 -4 14	; "width" -
	78	[159]	GETUPVAL 	14 4	; Size
	79	[159]	GETTABLE 	14 14 -28	; "item"
	80	[159]	GETTABLE 	14 14 -29	; "height_big"
	81	[159]	SETTABLE 	13 -27 14	; "height" -
	82	[160]	GETTABLE 	14 0 -15	; "fl_cur"
	83	[160]	GETTABLE 	15 0 -17	; "fl_max"
	84	[160]	DIV      	14 14 15
	85	[160]	SETTABLE 	13 -30 14	; "percentage" -
	86	[161]	SETTABLE 	13 -31 10	; "ticks" -
	87	[162]	GETUPVAL 	14 5	; Screen
	88	[162]	SELF     	14 14 -33	; "scaleBySize"
	89	[162]	LOADK    	16 -34	; 0.5
	90	[162]	CALL     	14 3 2
	91	[162]	SETTABLE 	13 -32 14	; "tick_width" -
	92	[163]	GETTABLE 	14 0 -17	; "fl_max"
	93	[163]	SETTABLE 	13 -35 14	; "last" -
	94	[157]	CALL     	11 3 2
	95	[164]	SETTABLE 	0 -24 11	; "fl_group" -
	96	[165]	GETUPVAL 	11 6	; TextBoxWidget
	97	[165]	SELF     	11 11 -3	; "new"
	98	[165]	NEWTABLE 	13 0 5
	99	[166]	GETUPVAL 	14 7	; _
	100	[166]	LOADK    	15 -37	; "Brightness"
	101	[166]	CALL     	14 2 2
	102	[166]	SETTABLE 	13 -36 14	; "text" -
	103	[167]	GETTABLE 	14 0 -39	; "medium_font_face"
	104	[167]	SETTABLE 	13 -38 14	; "face" -
	105	[168]	SETTABLE 	13 -40 -41	; "bold" true
	106	[169]	SETTABLE 	13 -42 -7	; "alignment" "center"
	107	[170]	GETTABLE 	14 0 -25	; "screen_width"
	108	[170]	MUL      	14 14 -43	; - 0.95
	109	[170]	SETTABLE 	13 -4 14	; "width" -
	110	[165]	CALL     	11 3 2
	111	[172]	GETUPVAL 	12 8	; Button
	112	[172]	SELF     	12 12 -3	; "new"
	113	[172]	NEWTABLE 	14 0 7
	114	[173]	SETTABLE 	14 -36 -44	; "text" "-1"
	115	[174]	GETUPVAL 	15 4	; Size
	116	[174]	GETTABLE 	15 15 -45	; "margin"
	117	[174]	GETTABLE 	15 15 -46	; "small"
	118	[174]	SETTABLE 	14 -45 15	; "margin" -
	119	[175]	SETTABLE 	14 -47 -48	; "radius" 0
	120	[176]	TESTSET  	15 9 0
	121	[176]	JMP      	2	; to 124
	122	[176]	GETTABLE 	15 0 -10	; "light_fallback"
	123	[176]	NOT      	15 15
	124	[176]	SETTABLE 	14 -9 15	; "enabled" -
	125	[177]	GETTABLE 	15 0 -25	; "screen_width"
	126	[177]	MUL      	15 15 -49	; - 0.2
	127	[177]	SETTABLE 	14 -4 15	; "width" -
	128	[178]	SETTABLE 	14 -50 0	; "show_parent" -
	129	[179]	CLOSURE  	15 0	; 0x7fd9b14096d0
	130	[179]	MOVE     	0 0
	131	[179]	MOVE     	0 2
	132	[179]	SETTABLE 	14 -51 15	; "callback" -
	133	[172]	CALL     	12 3 2
	134	[181]	GETUPVAL 	13 8	; Button
	135	[181]	SELF     	13 13 -3	; "new"
	136	[181]	NEWTABLE 	15 0 7
	137	[182]	SETTABLE 	15 -36 -52	; "text" "+1"
	138	[183]	GETUPVAL 	16 4	; Size
	139	[183]	GETTABLE 	16 16 -45	; "margin"
	140	[183]	GETTABLE 	16 16 -46	; "small"
	141	[183]	SETTABLE 	15 -45 16	; "margin" -
	142	[184]	SETTABLE 	15 -47 -48	; "radius" 0
	143	[185]	TESTSET  	16 8 0
	144	[185]	JMP      	2	; to 147
	145	[185]	GETTABLE 	16 0 -10	; "light_fallback"
	146	[185]	NOT      	16 16
	147	[185]	SETTABLE 	15 -9 16	; "enabled" -
	148	[186]	GETTABLE 	16 0 -25	; "screen_width"
	149	[186]	MUL      	16 16 -49	; - 0.2
	150	[186]	SETTABLE 	15 -4 16	; "width" -
	151	[187]	SETTABLE 	15 -50 0	; "show_parent" -
	152	[188]	CLOSURE  	16 1	; 0x7fd9b1409850
	153	[188]	MOVE     	0 0
	154	[188]	MOVE     	0 2
	155	[188]	SETTABLE 	15 -51 16	; "callback" -
	156	[181]	CALL     	13 3 2
	157	[190]	GETUPVAL 	14 6	; TextBoxWidget
	158	[190]	SELF     	14 14 -3	; "new"
	159	[190]	NEWTABLE 	16 0 4
	160	[191]	GETTABLE 	17 0 -15	; "fl_cur"
	161	[191]	SETTABLE 	16 -36 17	; "text" -
	162	[192]	GETTABLE 	17 0 -39	; "medium_font_face"
	163	[192]	SETTABLE 	16 -38 17	; "face" -
	164	[193]	SETTABLE 	16 -42 -7	; "alignment" "center"
	165	[194]	GETTABLE 	17 0 -25	; "screen_width"
	166	[194]	MUL      	17 17 -43	; - 0.95
	167	[194]	GETTABLE 	18 12 -4	; "width"
	168	[194]	MUL      	18 -53 18	; 1.275 -
	169	[194]	SUB      	17 17 18
	170	[194]	GETTABLE 	18 13 -4	; "width"
	171	[194]	MUL      	18 -53 18	; 1.275 -
	172	[194]	SUB      	17 17 18
	173	[194]	SETTABLE 	16 -4 17	; "width" -
	174	[190]	CALL     	14 3 2
	175	[196]	GETUPVAL 	15 8	; Button
	176	[196]	SELF     	15 15 -3	; "new"
	177	[196]	NEWTABLE 	17 0 7
	178	[197]	GETUPVAL 	18 7	; _
	179	[197]	LOADK    	19 -54	; "Min"
	180	[197]	CALL     	18 2 2
	181	[197]	SETTABLE 	17 -36 18	; "text" -
	182	[198]	GETUPVAL 	18 4	; Size
	183	[198]	GETTABLE 	18 18 -45	; "margin"
	184	[198]	GETTABLE 	18 18 -46	; "small"
	185	[198]	SETTABLE 	17 -45 18	; "margin" -
	186	[199]	SETTABLE 	17 -47 -48	; "radius" 0
	187	[200]	GETTABLE 	18 0 -10	; "light_fallback"
	188	[200]	NOT      	18 18
	189	[200]	SETTABLE 	17 -9 18	; "enabled" -
	190	[201]	GETTABLE 	18 0 -25	; "screen_width"
	191	[201]	MUL      	18 18 -49	; - 0.2
	192	[201]	SETTABLE 	17 -4 18	; "width" -
	193	[202]	SETTABLE 	17 -50 0	; "show_parent" -
	194	[203]	CLOSURE  	18 2	; 0x7fd9b1409c70
	195	[203]	MOVE     	0 0
	196	[203]	MOVE     	0 2
	197	[203]	SETTABLE 	17 -51 18	; "callback" -
	198	[196]	CALL     	15 3 2
	199	[205]	GETUPVAL 	16 8	; Button
	200	[205]	SELF     	16 16 -3	; "new"
	201	[205]	NEWTABLE 	18 0 7
	202	[206]	GETUPVAL 	19 7	; _
	203	[206]	LOADK    	20 -55	; "Max"
	204	[206]	CALL     	19 2 2
	205	[206]	SETTABLE 	18 -36 19	; "text" -
	206	[207]	GETUPVAL 	19 4	; Size
	207	[207]	GETTABLE 	19 19 -45	; "margin"
	208	[207]	GETTABLE 	19 19 -46	; "small"
	209	[207]	SETTABLE 	18 -45 19	; "margin" -
	210	[208]	SETTABLE 	18 -47 -48	; "radius" 0
	211	[209]	GETTABLE 	19 0 -10	; "light_fallback"
	212	[209]	NOT      	19 19
	213	[209]	SETTABLE 	18 -9 19	; "enabled" -
	214	[210]	GETTABLE 	19 0 -25	; "screen_width"
	215	[210]	MUL      	19 19 -49	; - 0.2
	216	[210]	SETTABLE 	18 -4 19	; "width" -
	217	[211]	SETTABLE 	18 -50 0	; "show_parent" -
	218	[212]	CLOSURE  	19 3	; 0x7fd9b1409ef0
	219	[212]	MOVE     	0 0
	220	[212]	MOVE     	0 2
	221	[212]	SETTABLE 	18 -51 19	; "callback" -
	222	[205]	CALL     	16 3 2
	223	[214]	GETUPVAL 	17 8	; Button
	224	[214]	SELF     	17 17 -3	; "new"
	225	[214]	NEWTABLE 	19 0 7
	226	[215]	GETUPVAL 	20 7	; _
	227	[215]	LOADK    	21 -56	; "Toggle"
	228	[215]	CALL     	20 2 2
	229	[215]	SETTABLE 	19 -36 20	; "text" -
	230	[216]	GETUPVAL 	20 4	; Size
	231	[216]	GETTABLE 	20 20 -45	; "margin"
	232	[216]	GETTABLE 	20 20 -46	; "small"
	233	[216]	SETTABLE 	19 -45 20	; "margin" -
	234	[217]	SETTABLE 	19 -47 -48	; "radius" 0
	235	[218]	GETTABLE 	20 0 -10	; "light_fallback"
	236	[218]	NOT      	20 20
	237	[218]	SETTABLE 	19 -9 20	; "enabled" -
	238	[219]	GETTABLE 	20 0 -25	; "screen_width"
	239	[219]	MUL      	20 20 -49	; - 0.2
	240	[219]	SETTABLE 	19 -4 20	; "width" -
	241	[220]	SETTABLE 	19 -50 0	; "show_parent" -
	242	[223]	CLOSURE  	20 4	; 0x7fd9b1409fb0
	243	[223]	MOVE     	0 0
	244	[223]	MOVE     	0 2
	245	[223]	SETTABLE 	19 -51 20	; "callback" -
	246	[214]	CALL     	17 3 2
	247	[225]	GETUPVAL 	18 9	; HorizontalSpan
	248	[225]	SELF     	18 18 -3	; "new"
	249	[225]	NEWTABLE 	20 0 1
	250	[226]	GETTABLE 	21 0 -25	; "screen_width"
	251	[226]	MUL      	21 21 -43	; - 0.95
	252	[226]	GETTABLE 	22 12 -4	; "width"
	253	[226]	MUL      	22 -57 22	; 1.2 -
	254	[226]	SUB      	21 21 22
	255	[226]	GETTABLE 	22 13 -4	; "width"
	256	[226]	MUL      	22 -57 22	; 1.2 -
	257	[226]	SUB      	21 21 22
	258	[226]	GETTABLE 	22 17 -4	; "width"
	259	[226]	MUL      	22 -57 22	; 1.2 -
	260	[226]	SUB      	21 21 22
	261	[226]	DIV      	21 21 -20	; - 2
	262	[226]	SETTABLE 	20 -4 21	; "width" -
	263	[225]	CALL     	18 3 2
	264	[228]	GETUPVAL 	19 1	; HorizontalGroup
	265	[228]	SELF     	19 19 -3	; "new"
	266	[228]	NEWTABLE 	21 3 1
	267	[229]	SETTABLE 	21 -6 -7	; "align" "center"
	268	[230]	MOVE     	22 12
	269	[231]	MOVE     	23 14
	270	[233]	MOVE     	24 13
	271	[233]	SETLIST  	21 3 1	; 1
	272	[228]	CALL     	19 3 2
	273	[234]	GETUPVAL 	20 1	; HorizontalGroup
	274	[234]	SELF     	20 20 -3	; "new"
	275	[234]	NEWTABLE 	22 5 1
	276	[235]	SETTABLE 	22 -6 -7	; "align" "center"
	277	[236]	MOVE     	23 15
	278	[237]	MOVE     	24 18
	279	[238]	MOVE     	25 17
	280	[239]	MOVE     	26 18
	281	[241]	MOVE     	27 16
	282	[241]	SETLIST  	22 5 1	; 1
	283	[234]	CALL     	20 3 2
	284	[242]	GETTABLE 	21 0 -11	; "natural_light"
	285	[242]	TEST     	21 0 0
	286	[242]	JMP      	5	; to 292
	287	[245]	GETGLOBAL	21 -21	; table
	288	[245]	GETTABLE 	21 21 -22	; "insert"
	289	[245]	MOVE     	22 7
	290	[245]	MOVE     	23 11
	291	[245]	CALL     	21 3 1
	292	[247]	LOADNIL  	21 21
	293	[248]	GETUPVAL 	22 10	; CheckButton
	294	[248]	SELF     	22 22 -3	; "new"
	295	[248]	NEWTABLE 	24 0 3
	296	[249]	GETUPVAL 	25 7	; _
	297	[249]	LOADK    	26 -58	; "Use system settings"
	298	[249]	CALL     	25 2 2
	299	[249]	SETTABLE 	24 -36 25	; "text" -
	300	[250]	GETTABLE 	25 0 -10	; "light_fallback"
	301	[250]	SETTABLE 	24 -59 25	; "checked" -
	302	[259]	CLOSURE  	25 5	; 0x7fd9b1408ad0
	303	[259]	MOVE     	0 21
	304	[259]	MOVE     	0 0
	305	[259]	MOVE     	0 2
	306	[259]	SETTABLE 	24 -51 25	; "callback" -
	307	[248]	CALL     	22 3 2
	308	[260]	MOVE     	21 22
	309	[261]	GETGLOBAL	22 -21	; table
	310	[261]	GETTABLE 	22 22 -22	; "insert"
	311	[261]	MOVE     	23 6
	312	[261]	MOVE     	24 19
	313	[261]	CALL     	22 3 1
	314	[262]	GETGLOBAL	22 -21	; table
	315	[262]	GETTABLE 	22 22 -22	; "insert"
	316	[262]	MOVE     	23 5
	317	[262]	MOVE     	24 20
	318	[262]	CALL     	22 3 1
	319	[263]	GETGLOBAL	22 -21	; table
	320	[263]	GETTABLE 	22 22 -22	; "insert"
	321	[263]	MOVE     	23 7
	322	[263]	MOVE     	24 4
	323	[263]	CALL     	22 3 1
	324	[264]	GETGLOBAL	22 -21	; table
	325	[264]	GETTABLE 	22 22 -22	; "insert"
	326	[264]	MOVE     	23 7
	327	[264]	MOVE     	24 6
	328	[264]	CALL     	22 3 1
	329	[265]	GETGLOBAL	22 -21	; table
	330	[265]	GETTABLE 	22 22 -22	; "insert"
	331	[265]	MOVE     	23 7
	332	[265]	MOVE     	24 4
	333	[265]	CALL     	22 3 1
	334	[266]	GETGLOBAL	22 -21	; table
	335	[266]	GETTABLE 	22 22 -22	; "insert"
	336	[266]	MOVE     	23 7
	337	[266]	GETTABLE 	24 0 -24	; "fl_group"
	338	[266]	CALL     	22 3 1
	339	[267]	GETGLOBAL	22 -21	; table
	340	[267]	GETTABLE 	22 22 -22	; "insert"
	341	[267]	MOVE     	23 7
	342	[267]	MOVE     	24 4
	343	[267]	CALL     	22 3 1
	344	[268]	GETGLOBAL	22 -21	; table
	345	[268]	GETTABLE 	22 22 -22	; "insert"
	346	[268]	MOVE     	23 7
	347	[268]	MOVE     	24 5
	348	[268]	CALL     	22 3 1
	349	[269]	GETGLOBAL	22 -21	; table
	350	[269]	GETTABLE 	22 22 -22	; "insert"
	351	[269]	MOVE     	23 7
	352	[269]	MOVE     	24 4
	353	[269]	CALL     	22 3 1
	354	[270]	GETTABLE 	22 0 -60	; "use_system_fl"
	355	[270]	TEST     	22 0 0
	356	[270]	JMP      	10	; to 367
	357	[271]	GETGLOBAL	22 -21	; table
	358	[271]	GETTABLE 	22 22 -22	; "insert"
	359	[271]	MOVE     	23 7
	360	[271]	MOVE     	24 21
	361	[271]	CALL     	22 3 1
	362	[272]	GETGLOBAL	22 -21	; table
	363	[272]	GETTABLE 	22 22 -22	; "insert"
	364	[272]	MOVE     	23 7
	365	[272]	MOVE     	24 4
	366	[272]	CALL     	22 3 1
	367	[274]	GETTABLE 	22 0 -11	; "natural_light"
	368	[274]	TEST     	22 0 0
	369	[274]	JMP      	39	; to 409
	370	[277]	SELF     	22 0 -61	; "addWarmthWidgets"
	371	[277]	MOVE     	24 3
	372	[277]	MOVE     	25 2
	373	[277]	MOVE     	26 7
	374	[277]	CALL     	22 5 1
	375	[278]	GETTABLE 	22 0 -62	; "has_nl_mixer"
	376	[278]	TEST     	22 0 1
	377	[278]	JMP      	31	; to 409
	378	[279]	GETUPVAL 	22 8	; Button
	379	[279]	SELF     	22 22 -3	; "new"
	380	[279]	NEWTABLE 	24 0 7
	381	[280]	GETUPVAL 	25 7	; _
	382	[280]	LOADK    	26 -64	; "Configure"
	383	[280]	CALL     	25 2 2
	384	[280]	SETTABLE 	24 -36 25	; "text" -
	385	[281]	GETUPVAL 	25 4	; Size
	386	[281]	GETTABLE 	25 25 -45	; "margin"
	387	[281]	GETTABLE 	25 25 -46	; "small"
	388	[281]	SETTABLE 	24 -45 25	; "margin" -
	389	[282]	SETTABLE 	24 -47 -48	; "radius" 0
	390	[283]	GETTABLE 	25 0 -25	; "screen_width"
	391	[283]	MUL      	25 25 -49	; - 0.2
	392	[283]	SETTABLE 	24 -4 25	; "width" -
	393	[284]	GETTABLE 	25 0 -65	; "nl_configure_open"
	394	[284]	NOT      	25 25
	395	[284]	SETTABLE 	24 -9 25	; "enabled" -
	396	[285]	SETTABLE 	24 -50 0	; "show_parent" -
	397	[288]	CLOSURE  	25 6	; 0x7fd9b1408c60
	398	[288]	GETUPVAL 	0 11	; UIManager
	399	[288]	GETUPVAL 	0 12	; NaturalLight
	400	[288]	MOVE     	0 0
	401	[288]	SETTABLE 	24 -51 25	; "callback" -
	402	[279]	CALL     	22 3 2
	403	[289]	SETTABLE 	0 -63 22	; "configure_button" -
	404	[290]	GETGLOBAL	22 -21	; table
	405	[290]	GETTABLE 	22 22 -22	; "insert"
	406	[290]	MOVE     	23 7
	407	[290]	GETTABLE 	24 0 -63	; "configure_button"
	408	[290]	CALL     	22 3 1
	409	[293]	GETGLOBAL	22 -21	; table
	410	[293]	GETTABLE 	22 22 -22	; "insert"
	411	[293]	GETTABLE 	23 0 -1	; "fl_container"
	412	[293]	MOVE     	24 7
	413	[293]	CALL     	22 3 1
	414	[295]	GETTABLE 	22 0 -1	; "fl_container"
	415	[295]	GETTABLE 	22 22 -66	; "dimen"
	416	[295]	SELF     	23 7 -68	; "getSize"
	417	[295]	CALL     	23 2 2
	418	[295]	GETTABLE 	23 23 -67	; "h"
	419	[295]	SETTABLE 	22 -67 23	; "h" -
	420	[297]	GETUPVAL 	22 11	; UIManager
	421	[297]	SELF     	22 22 -69	; "setDirty"
	422	[297]	MOVE     	24 0
	423	[299]	CLOSURE  	25 7	; 0x7fd9b140a680
	424	[299]	MOVE     	0 0
	425	[297]	CALL     	22 4 1
	426	[300]	LOADBOOL 	22 1 0
	427	[300]	RETURN   	22 2
	428	[301]	RETURN   	0 1

function <./frontend/ui/widget/frontlightwidget.lua:179,179> (8 instructions, 32 bytes at 0x7fd9b14096d0)
0 params, 4 slots, 2 upvalues, 0 locals, 3 constants, 0 functions
	1	[179]	GETUPVAL 	0 0	; self
	2	[179]	SELF     	0 0 -1	; "setProgress"
	3	[179]	GETUPVAL 	2 0	; self
	4	[179]	GETTABLE 	2 2 -2	; "fl_cur"
	5	[179]	SUB      	2 2 -3	; - 1
	6	[179]	GETUPVAL 	3 1	; step
	7	[179]	CALL     	0 4 1
	8	[179]	RETURN   	0 1

function <./frontend/ui/widget/frontlightwidget.lua:188,188> (8 instructions, 32 bytes at 0x7fd9b1409850)
0 params, 4 slots, 2 upvalues, 0 locals, 3 constants, 0 functions
	1	[188]	GETUPVAL 	0 0	; self
	2	[188]	SELF     	0 0 -1	; "setProgress"
	3	[188]	GETUPVAL 	2 0	; self
	4	[188]	GETTABLE 	2 2 -2	; "fl_cur"
	5	[188]	ADD      	2 2 -3	; - 1
	6	[188]	GETUPVAL 	3 1	; step
	7	[188]	CALL     	0 4 1
	8	[188]	RETURN   	0 1

function <./frontend/ui/widget/frontlightwidget.lua:203,203> (8 instructions, 32 bytes at 0x7fd9b1409c70)
0 params, 4 slots, 2 upvalues, 0 locals, 3 constants, 0 functions
	1	[203]	GETUPVAL 	0 0	; self
	2	[203]	SELF     	0 0 -1	; "setProgress"
	3	[203]	GETUPVAL 	2 0	; self
	4	[203]	GETTABLE 	2 2 -2	; "fl_min"
	5	[203]	ADD      	2 2 -3	; - 1
	6	[203]	GETUPVAL 	3 1	; step
	7	[203]	CALL     	0 4 1
	8	[203]	RETURN   	0 1

function <./frontend/ui/widget/frontlightwidget.lua:212,212> (7 instructions, 28 bytes at 0x7fd9b1409ef0)
0 params, 4 slots, 2 upvalues, 0 locals, 2 constants, 0 functions
	1	[212]	GETUPVAL 	0 0	; self
	2	[212]	SELF     	0 0 -1	; "setProgress"
	3	[212]	GETUPVAL 	2 0	; self
	4	[212]	GETTABLE 	2 2 -2	; "fl_max"
	5	[212]	GETUPVAL 	3 1	; step
	6	[212]	CALL     	0 4 1
	7	[212]	RETURN   	0 1

function <./frontend/ui/widget/frontlightwidget.lua:221,223> (7 instructions, 28 bytes at 0x7fd9b1409fb0)
0 params, 4 slots, 2 upvalues, 0 locals, 2 constants, 0 functions
	1	[222]	GETUPVAL 	0 0	; self
	2	[222]	SELF     	0 0 -1	; "setProgress"
	3	[222]	GETUPVAL 	2 0	; self
	4	[222]	GETTABLE 	2 2 -2	; "fl_min"
	5	[222]	GETUPVAL 	3 1	; step
	6	[222]	CALL     	0 4 1
	7	[223]	RETURN   	0 1

function <./frontend/ui/widget/frontlightwidget.lua:251,259> (22 instructions, 88 bytes at 0x7fd9b1408ad0)
0 params, 4 slots, 3 upvalues, 0 locals, 8 constants, 0 functions
	1	[252]	GETUPVAL 	0 0	; system_level_checkbutton
	2	[252]	GETTABLE 	0 0 -1	; "checked"
	3	[252]	TEST     	0 0 0
	4	[252]	JMP      	3	; to 8
	5	[253]	GETUPVAL 	0 1	; self
	6	[253]	SETTABLE 	0 -2 -3	; "light_fallback" false
	7	[253]	JMP      	2	; to 10
	8	[255]	GETUPVAL 	0 1	; self
	9	[255]	SETTABLE 	0 -2 -4	; "light_fallback" true
	10	[257]	GETGLOBAL	0 -5	; G_reader_settings
	11	[257]	SELF     	0 0 -6	; "saveSetting"
	12	[257]	LOADK    	2 -2	; "light_fallback"
	13	[257]	GETUPVAL 	3 1	; self
	14	[257]	GETTABLE 	3 3 -2	; "light_fallback"
	15	[257]	CALL     	0 4 1
	16	[258]	GETUPVAL 	0 1	; self
	17	[258]	SELF     	0 0 -7	; "setProgress"
	18	[258]	GETUPVAL 	2 1	; self
	19	[258]	GETTABLE 	2 2 -8	; "fl_cur"
	20	[258]	GETUPVAL 	3 2	; step
	21	[258]	CALL     	0 4 1
	22	[259]	RETURN   	0 1

function <./frontend/ui/widget/frontlightwidget.lua:286,288> (10 instructions, 40 bytes at 0x7fd9b1408c60)
0 params, 6 slots, 3 upvalues, 0 locals, 3 constants, 0 functions
	1	[287]	GETUPVAL 	0 0	; UIManager
	2	[287]	SELF     	0 0 -1	; "show"
	3	[287]	GETUPVAL 	2 1	; NaturalLight
	4	[287]	SELF     	2 2 -2	; "new"
	5	[287]	NEWTABLE 	4 0 1
	6	[287]	GETUPVAL 	5 2	; self
	7	[287]	SETTABLE 	4 -3 5	; "fl_widget" -
	8	[287]	CALL     	2 3 0
	9	[287]	CALL     	0 0 1
	10	[288]	RETURN   	0 1

function <./frontend/ui/widget/frontlightwidget.lua:297,299> (6 instructions, 24 bytes at 0x7fd9b140a680)
0 params, 2 slots, 1 upvalue, 0 locals, 3 constants, 0 functions
	1	[298]	LOADK    	0 -1	; "ui"
	2	[298]	GETUPVAL 	1 0	; self
	3	[298]	GETTABLE 	1 1 -2	; "light_frame"
	4	[298]	GETTABLE 	1 1 -3	; "dimen"
	5	[298]	RETURN   	0 3
	6	[299]	RETURN   	0 1

function <./frontend/ui/widget/frontlightwidget.lua:305,509> (503 instructions, 2012 bytes at 0x7fd9b140a930)
4 params, 31 slots, 9 upvalues, 34 locals, 69 constants, 11 functions
	1	[306]	GETUPVAL 	4 0	; HorizontalGroup
	2	[306]	SELF     	4 4 -1	; "new"
	3	[306]	NEWTABLE 	6 0 1
	4	[306]	SETTABLE 	6 -2 -3	; "align" "center"
	5	[306]	CALL     	4 3 2
	6	[307]	GETUPVAL 	5 0	; HorizontalGroup
	7	[307]	SELF     	5 5 -1	; "new"
	8	[307]	NEWTABLE 	7 0 1
	9	[307]	SETTABLE 	7 -2 -3	; "align" "center"
	10	[307]	CALL     	5 3 2
	11	[308]	GETUPVAL 	6 0	; HorizontalGroup
	12	[308]	SELF     	6 6 -1	; "new"
	13	[308]	NEWTABLE 	8 0 1
	14	[308]	SETTABLE 	8 -2 -3	; "align" "center"
	15	[308]	CALL     	6 3 2
	16	[309]	GETUPVAL 	7 0	; HorizontalGroup
	17	[309]	SELF     	7 7 -1	; "new"
	18	[309]	NEWTABLE 	9 0 1
	19	[309]	SETTABLE 	9 -2 -3	; "align" "center"
	20	[309]	CALL     	7 3 2
	21	[310]	GETUPVAL 	8 1	; VerticalSpan
	22	[310]	SELF     	8 8 -1	; "new"
	23	[310]	NEWTABLE 	10 0 1
	24	[310]	GETTABLE 	11 0 -5	; "span"
	25	[310]	SETTABLE 	10 -4 11	; "width" -
	26	[310]	CALL     	8 3 2
	27	[311]	LOADBOOL 	9 1 0
	28	[312]	LOADBOOL 	10 1 0
	29	[313]	GETUPVAL 	11 2	; Blitbuffer
	30	[313]	GETTABLE 	11 11 -6	; "COLOR_WHITE"
	31	[315]	GETTABLE 	12 0 -7	; 1
	32	[315]	TEST     	12 0 0
	33	[315]	JMP      	8	; to 42
	34	[317]	GETTABLE 	12 0 -8	; "powerd"
	35	[317]	GETTABLE 	12 12 -9	; "fl_warmth"
	36	[317]	EQ       	1 1 12
	37	[317]	JMP      	4	; to 42
	38	[318]	GETTABLE 	12 0 -8	; "powerd"
	39	[318]	SELF     	12 12 -10	; "setWarmth"
	40	[318]	MOVE     	14 1
	41	[318]	CALL     	12 3 1
	42	[322]	GETTABLE 	12 0 -8	; "powerd"
	43	[322]	GETTABLE 	12 12 -11	; "auto_warmth"
	44	[322]	TEST     	12 0 0
	45	[322]	JMP      	5	; to 51
	46	[323]	LOADBOOL 	9 0 0
	47	[324]	LOADBOOL 	10 0 0
	48	[325]	GETUPVAL 	12 2	; Blitbuffer
	49	[325]	GETTABLE 	11 12 -12	; "COLOR_DARK_GRAY"
	50	[325]	JMP      	18	; to 69
	51	[327]	GETGLOBAL	12 -13	; math
	52	[327]	GETTABLE 	12 12 -14	; "floor"
	53	[327]	GETTABLE 	13 0 -15	; "nl_scale"
	54	[327]	DIV      	13 1 13
	55	[327]	CALL     	12 2 2
	56	[327]	GETTABLE 	13 0 -16	; "nl_min"
	57	[327]	LE       	0 12 13
	58	[327]	JMP      	1	; to 60
	59	[327]	LOADBOOL 	10 0 0
	60	[328]	GETGLOBAL	12 -13	; math
	61	[328]	GETTABLE 	12 12 -17	; "ceil"
	62	[328]	GETTABLE 	13 0 -15	; "nl_scale"
	63	[328]	DIV      	13 1 13
	64	[328]	CALL     	12 2 2
	65	[328]	GETTABLE 	13 0 -18	; "nl_max"
	66	[328]	LE       	0 13 12
	67	[328]	JMP      	1	; to 69
	68	[328]	LOADBOOL 	9 0 0
	69	[331]	GETTABLE 	12 0 -19	; "natural_light"
	70	[331]	TEST     	12 0 0
	71	[331]	JMP      	60	; to 132
	72	[331]	TEST     	1 0 0
	73	[331]	JMP      	58	; to 132
	74	[332]	LOADK    	12 -20	; 0
	75	[332]	GETGLOBAL	13 -13	; math
	76	[332]	GETTABLE 	13 13 -14	; "floor"
	77	[332]	DIV      	14 1 2
	78	[332]	CALL     	13 2 2
	79	[332]	LOADK    	14 -7	; 1
	80	[332]	FORPREP  	12 21	; to 102
	81	[333]	GETGLOBAL	16 -21	; table
	82	[333]	GETTABLE 	16 16 -22	; "insert"
	83	[333]	MOVE     	17 6
	84	[333]	GETTABLE 	18 0 -23	; "fl_prog_button"
	85	[333]	SELF     	18 18 -1	; "new"
	86	[333]	NEWTABLE 	20 0 5
	87	[334]	SETTABLE 	20 -24 -25	; "text" ""
	88	[335]	SETTABLE 	20 -26 -27	; "preselect" true
	89	[336]	GETTABLE 	21 0 -8	; "powerd"
	90	[336]	GETTABLE 	21 21 -11	; "auto_warmth"
	91	[336]	NOT      	21 21
	92	[336]	SETTABLE 	20 -28 21	; "enabled" -
	93	[337]	SETTABLE 	20 -29 11	; "background" -
	94	[340]	CLOSURE  	21 0	; 0x7fd9b14078d0
	95	[340]	MOVE     	0 0
	96	[340]	MOVE     	0 2
	97	[340]	MOVE     	0 15
	98	[340]	SETTABLE 	20 -30 21	; "callback" -
	99	[333]	CALL     	18 3 0
	100	[333]	CALL     	16 0 1
	101	[341]	CLOSE    	15
	102	[332]	FORLOOP  	12 -22	; to 81
	103	[344]	GETGLOBAL	12 -13	; math
	104	[344]	GETTABLE 	12 12 -14	; "floor"
	105	[344]	DIV      	13 1 2
	106	[344]	CALL     	12 2 2
	107	[344]	ADD      	12 12 -7	; - 1
	108	[344]	GETTABLE 	13 0 -31	; "steps"
	109	[344]	SUB      	13 13 -7	; - 1
	110	[344]	LOADK    	14 -7	; 1
	111	[344]	FORPREP  	12 19	; to 131
	112	[345]	GETGLOBAL	16 -21	; table
	113	[345]	GETTABLE 	16 16 -22	; "insert"
	114	[345]	MOVE     	17 6
	115	[345]	GETTABLE 	18 0 -23	; "fl_prog_button"
	116	[345]	SELF     	18 18 -1	; "new"
	117	[345]	NEWTABLE 	20 0 3
	118	[346]	SETTABLE 	20 -24 -25	; "text" ""
	119	[347]	GETTABLE 	21 0 -8	; "powerd"
	120	[347]	GETTABLE 	21 21 -11	; "auto_warmth"
	121	[347]	NOT      	21 21
	122	[347]	SETTABLE 	20 -28 21	; "enabled" -
	123	[350]	CLOSURE  	21 1	; 0x7fd9b14076f0
	124	[350]	MOVE     	0 0
	125	[350]	MOVE     	0 2
	126	[350]	MOVE     	0 15
	127	[350]	SETTABLE 	20 -30 21	; "callback" -
	128	[345]	CALL     	18 3 0
	129	[345]	CALL     	16 0 1
	130	[351]	CLOSE    	15
	131	[344]	FORLOOP  	12 -20	; to 112
	132	[355]	GETUPVAL 	12 3	; TextBoxWidget
	133	[355]	SELF     	12 12 -1	; "new"
	134	[355]	NEWTABLE 	14 0 5
	135	[356]	LOADK    	15 -32	; "\n"
	136	[356]	GETUPVAL 	16 4	; _
	137	[356]	LOADK    	17 -33	; "Warmth"
	138	[356]	CALL     	16 2 2
	139	[356]	CONCAT   	15 15 16
	140	[356]	SETTABLE 	14 -24 15	; "text" -
	141	[357]	GETTABLE 	15 0 -35	; "medium_font_face"
	142	[357]	SETTABLE 	14 -34 15	; "face" -
	143	[358]	SETTABLE 	14 -36 -27	; "bold" true
	144	[359]	SETTABLE 	14 -37 -3	; "alignment" "center"
	145	[360]	GETTABLE 	15 0 -38	; "screen_width"
	146	[360]	MUL      	15 15 -39	; - 0.95
	147	[360]	SETTABLE 	14 -4 15	; "width" -
	148	[355]	CALL     	12 3 2
	149	[362]	GETUPVAL 	13 5	; Button
	150	[362]	SELF     	13 13 -1	; "new"
	151	[362]	NEWTABLE 	15 0 7
	152	[363]	LOADK    	16 -40	; "-"
	153	[363]	GETTABLE 	17 0 -15	; "nl_scale"
	154	[363]	MUL      	17 -7 17	; 1 -
	155	[363]	CONCAT   	16 16 17
	156	[363]	SETTABLE 	15 -24 16	; "text" -
	157	[364]	GETUPVAL 	16 6	; Size
	158	[364]	GETTABLE 	16 16 -41	; "margin"
	159	[364]	GETTABLE 	16 16 -42	; "small"
	160	[364]	SETTABLE 	15 -41 16	; "margin" -
	161	[365]	SETTABLE 	15 -43 -20	; "radius" 0
	162	[366]	SETTABLE 	15 -28 10	; "enabled" -
	163	[367]	GETTABLE 	16 0 -38	; "screen_width"
	164	[367]	MUL      	16 16 -44	; - 0.2
	165	[367]	SETTABLE 	15 -4 16	; "width" -
	166	[368]	SETTABLE 	15 -45 0	; "show_parent" -
	167	[369]	CLOSURE  	16 2	; 0x7fd9b140ae40
	168	[369]	MOVE     	0 0
	169	[369]	MOVE     	0 2
	170	[369]	MOVE     	0 1
	171	[369]	SETTABLE 	15 -30 16	; "callback" -
	172	[362]	CALL     	13 3 2
	173	[371]	GETUPVAL 	14 5	; Button
	174	[371]	SELF     	14 14 -1	; "new"
	175	[371]	NEWTABLE 	16 0 7
	176	[372]	LOADK    	17 -46	; "+"
	177	[372]	GETTABLE 	18 0 -15	; "nl_scale"
	178	[372]	MUL      	18 -7 18	; 1 -
	179	[372]	CONCAT   	17 17 18
	180	[372]	SETTABLE 	16 -24 17	; "text" -
	181	[373]	GETUPVAL 	17 6	; Size
	182	[373]	GETTABLE 	17 17 -41	; "margin"
	183	[373]	GETTABLE 	17 17 -42	; "small"
	184	[373]	SETTABLE 	16 -41 17	; "margin" -
	185	[374]	SETTABLE 	16 -43 -20	; "radius" 0
	186	[375]	SETTABLE 	16 -28 9	; "enabled" -
	187	[376]	GETTABLE 	17 0 -38	; "screen_width"
	188	[376]	MUL      	17 17 -44	; - 0.2
	189	[376]	SETTABLE 	16 -4 17	; "width" -
	190	[377]	SETTABLE 	16 -45 0	; "show_parent" -
	191	[378]	CLOSURE  	17 3	; 0x7fd9b140b1a0
	192	[378]	MOVE     	0 0
	193	[378]	MOVE     	0 2
	194	[378]	MOVE     	0 1
	195	[378]	SETTABLE 	16 -30 17	; "callback" -
	196	[371]	CALL     	14 3 2
	197	[380]	GETUPVAL 	15 3	; TextBoxWidget
	198	[380]	SELF     	15 15 -1	; "new"
	199	[380]	NEWTABLE 	17 0 4
	200	[381]	SETTABLE 	17 -24 1	; "text" -
	201	[382]	GETTABLE 	18 0 -35	; "medium_font_face"
	202	[382]	SETTABLE 	17 -34 18	; "face" -
	203	[383]	SETTABLE 	17 -37 -3	; "alignment" "center"
	204	[384]	GETTABLE 	18 0 -38	; "screen_width"
	205	[384]	MUL      	18 18 -39	; - 0.95
	206	[384]	GETTABLE 	19 13 -4	; "width"
	207	[384]	MUL      	19 -47 19	; 1.275 -
	208	[384]	SUB      	18 18 19
	209	[384]	GETTABLE 	19 14 -4	; "width"
	210	[384]	MUL      	19 -47 19	; 1.275 -
	211	[384]	SUB      	18 18 19
	212	[384]	SETTABLE 	17 -4 18	; "width" -
	213	[380]	CALL     	15 3 2
	214	[386]	GETUPVAL 	16 5	; Button
	215	[386]	SELF     	16 16 -1	; "new"
	216	[386]	NEWTABLE 	18 0 7
	217	[387]	GETUPVAL 	19 4	; _
	218	[387]	LOADK    	20 -48	; "Min"
	219	[387]	CALL     	19 2 2
	220	[387]	SETTABLE 	18 -24 19	; "text" -
	221	[388]	GETUPVAL 	19 6	; Size
	222	[388]	GETTABLE 	19 19 -41	; "margin"
	223	[388]	GETTABLE 	19 19 -42	; "small"
	224	[388]	SETTABLE 	18 -41 19	; "margin" -
	225	[389]	SETTABLE 	18 -43 -20	; "radius" 0
	226	[390]	GETTABLE 	19 0 -8	; "powerd"
	227	[390]	GETTABLE 	19 19 -11	; "auto_warmth"
	228	[390]	NOT      	19 19
	229	[390]	SETTABLE 	18 -28 19	; "enabled" -
	230	[391]	GETTABLE 	19 0 -38	; "screen_width"
	231	[391]	MUL      	19 19 -44	; - 0.2
	232	[391]	SETTABLE 	18 -4 19	; "width" -
	233	[392]	SETTABLE 	18 -45 0	; "show_parent" -
	234	[393]	CLOSURE  	19 4	; 0x7fd9b140b320
	235	[393]	MOVE     	0 0
	236	[393]	MOVE     	0 2
	237	[393]	SETTABLE 	18 -30 19	; "callback" -
	238	[386]	CALL     	16 3 2
	239	[395]	GETUPVAL 	17 5	; Button
	240	[395]	SELF     	17 17 -1	; "new"
	241	[395]	NEWTABLE 	19 0 7
	242	[396]	GETUPVAL 	20 4	; _
	243	[396]	LOADK    	21 -49	; "Max"
	244	[396]	CALL     	20 2 2
	245	[396]	SETTABLE 	19 -24 20	; "text" -
	246	[397]	GETUPVAL 	20 6	; Size
	247	[397]	GETTABLE 	20 20 -41	; "margin"
	248	[397]	GETTABLE 	20 20 -42	; "small"
	249	[397]	SETTABLE 	19 -41 20	; "margin" -
	250	[398]	SETTABLE 	19 -43 -20	; "radius" 0
	251	[399]	GETTABLE 	20 0 -8	; "powerd"
	252	[399]	GETTABLE 	20 20 -11	; "auto_warmth"
	253	[399]	NOT      	20 20
	254	[399]	SETTABLE 	19 -28 20	; "enabled" -
	255	[400]	GETTABLE 	20 0 -38	; "screen_width"
	256	[400]	MUL      	20 20 -44	; - 0.2
	257	[400]	SETTABLE 	19 -4 20	; "width" -
	258	[401]	SETTABLE 	19 -45 0	; "show_parent" -
	259	[402]	CLOSURE  	20 5	; 0x7fd9b140bb30
	260	[402]	MOVE     	0 0
	261	[402]	MOVE     	0 2
	262	[402]	SETTABLE 	19 -30 20	; "callback" -
	263	[395]	CALL     	17 3 2
	264	[404]	GETUPVAL 	18 7	; HorizontalSpan
	265	[404]	SELF     	18 18 -1	; "new"
	266	[404]	NEWTABLE 	20 0 1
	267	[405]	GETTABLE 	21 0 -38	; "screen_width"
	268	[405]	MUL      	21 21 -39	; - 0.95
	269	[405]	GETTABLE 	22 13 -4	; "width"
	270	[405]	MUL      	22 -50 22	; 1.2 -
	271	[405]	SUB      	21 21 22
	272	[405]	GETTABLE 	22 14 -4	; "width"
	273	[405]	MUL      	22 -50 22	; 1.2 -
	274	[405]	SUB      	21 21 22
	275	[405]	DIV      	21 21 -51	; - 2
	276	[405]	SETTABLE 	20 -4 21	; "width" -
	277	[404]	CALL     	18 3 2
	278	[407]	GETUPVAL 	19 0	; HorizontalGroup
	279	[407]	SELF     	19 19 -1	; "new"
	280	[407]	NEWTABLE 	21 3 1
	281	[408]	SETTABLE 	21 -2 -3	; "align" "center"
	282	[409]	MOVE     	22 13
	283	[410]	MOVE     	23 15
	284	[412]	MOVE     	24 14
	285	[412]	SETLIST  	21 3 1	; 1
	286	[407]	CALL     	19 3 2
	287	[413]	GETUPVAL 	20 0	; HorizontalGroup
	288	[413]	SELF     	20 20 -1	; "new"
	289	[413]	NEWTABLE 	22 3 1
	290	[414]	SETTABLE 	22 -2 -3	; "align" "center"
	291	[415]	MOVE     	23 16
	292	[416]	MOVE     	24 18
	293	[418]	MOVE     	25 17
	294	[418]	SETLIST  	22 3 1	; 1
	295	[413]	CALL     	20 3 2
	296	[419]	GETUPVAL 	21 8	; CheckButton
	297	[419]	SELF     	21 21 -1	; "new"
	298	[419]	NEWTABLE 	23 0 3
	299	[420]	GETUPVAL 	24 4	; _
	300	[420]	LOADK    	25 -52	; "Auto"
	301	[420]	CALL     	24 2 2
	302	[420]	SETTABLE 	23 -24 24	; "text" -
	303	[421]	GETTABLE 	24 0 -8	; "powerd"
	304	[421]	GETTABLE 	24 24 -11	; "auto_warmth"
	305	[421]	SETTABLE 	23 -53 24	; "checked" -
	306	[430]	CLOSURE  	24 6	; 0x7fd9b140bea0
	307	[430]	MOVE     	0 0
	308	[430]	MOVE     	0 2
	309	[430]	SETTABLE 	23 -30 24	; "callback" -
	310	[419]	CALL     	21 3 2
	311	[433]	GETUPVAL 	22 3	; TextBoxWidget
	312	[433]	SELF     	22 22 -1	; "new"
	313	[433]	NEWTABLE 	24 0 5
	314	[435]	GETUPVAL 	25 4	; _
	315	[435]	LOADK    	26 -54	; "Max. at:"
	316	[435]	CALL     	25 2 2
	317	[435]	LOADK    	26 -55	; "  "
	318	[435]	CONCAT   	25 25 26
	319	[435]	SETTABLE 	24 -24 25	; "text" -
	320	[436]	GETTABLE 	25 0 -56	; "larger_font_face"
	321	[436]	SETTABLE 	24 -34 25	; "face" -
	322	[437]	SETTABLE 	24 -37 -57	; "alignment" "right"
	323	[438]	GETTABLE 	25 0 -8	; "powerd"
	324	[438]	GETTABLE 	25 25 -11	; "auto_warmth"
	325	[438]	TEST     	25 0 0
	326	[438]	JMP      	4	; to 331
	327	[438]	GETUPVAL 	25 2	; Blitbuffer
	328	[438]	GETTABLE 	25 25 -59	; "COLOR_BLACK"
	329	[438]	TEST     	25 0 1
	330	[438]	JMP      	2	; to 333
	331	[439]	GETUPVAL 	25 2	; Blitbuffer
	332	[439]	GETTABLE 	25 25 -12	; "COLOR_DARK_GRAY"
	333	[439]	SETTABLE 	24 -58 25	; "fgcolor" -
	334	[440]	GETTABLE 	25 0 -38	; "screen_width"
	335	[440]	MUL      	25 25 -60	; - 0.3
	336	[440]	SETTABLE 	24 -4 25	; "width" -
	337	[433]	CALL     	22 3 2
	338	[442]	GETUPVAL 	23 3	; TextBoxWidget
	339	[442]	SELF     	23 23 -1	; "new"
	340	[442]	NEWTABLE 	25 0 5
	341	[443]	LOADK    	26 -61	; " "
	342	[443]	GETGLOBAL	27 -13	; math
	343	[443]	GETTABLE 	27 27 -14	; "floor"
	344	[443]	GETTABLE 	28 0 -8	; "powerd"
	345	[443]	GETTABLE 	28 28 -62	; "max_warmth_hour"
	346	[443]	CALL     	27 2 2
	347	[443]	LOADK    	28 -63	; ":"
	348	[444]	GETTABLE 	29 0 -8	; "powerd"
	349	[444]	GETTABLE 	29 29 -62	; "max_warmth_hour"
	350	[444]	MOD      	29 29 -7
	351	[444]	MUL      	29 29 -64	; - 6
	352	[444]	LOADK    	30 -65	; "0"
	353	[444]	CONCAT   	26 26 30
	354	[444]	SETTABLE 	25 -24 26	; "text" -
	355	[445]	GETTABLE 	26 0 -56	; "larger_font_face"
	356	[445]	SETTABLE 	25 -34 26	; "face" -
	357	[446]	SETTABLE 	25 -37 -3	; "alignment" "center"
	358	[447]	GETTABLE 	26 0 -8	; "powerd"
	359	[447]	GETTABLE 	26 26 -11	; "auto_warmth"
	360	[447]	TEST     	26 0 0
	361	[447]	JMP      	4	; to 366
	362	[447]	GETUPVAL 	26 2	; Blitbuffer
	363	[447]	GETTABLE 	26 26 -59	; "COLOR_BLACK"
	364	[447]	TEST     	26 0 1
	365	[447]	JMP      	2	; to 368
	366	[448]	GETUPVAL 	26 2	; Blitbuffer
	367	[448]	GETTABLE 	26 26 -12	; "COLOR_DARK_GRAY"
	368	[448]	SETTABLE 	25 -58 26	; "fgcolor" -
	369	[449]	GETTABLE 	26 0 -38	; "screen_width"
	370	[449]	MUL      	26 26 -66	; - 0.15
	371	[449]	SETTABLE 	25 -4 26	; "width" -
	372	[442]	CALL     	23 3 2
	373	[451]	GETUPVAL 	24 5	; Button
	374	[451]	SELF     	24 24 -1	; "new"
	375	[451]	NEWTABLE 	26 0 8
	376	[452]	SETTABLE 	26 -24 -67	; "text" "\226\136\146"
	377	[453]	GETUPVAL 	27 6	; Size
	378	[453]	GETTABLE 	27 27 -41	; "margin"
	379	[453]	GETTABLE 	27 27 -42	; "small"
	380	[453]	SETTABLE 	26 -41 27	; "margin" -
	381	[454]	SETTABLE 	26 -43 -20	; "radius" 0
	382	[455]	GETTABLE 	27 0 -8	; "powerd"
	383	[455]	GETTABLE 	27 27 -11	; "auto_warmth"
	384	[455]	SETTABLE 	26 -28 27	; "enabled" -
	385	[456]	GETTABLE 	27 0 -38	; "screen_width"
	386	[456]	MUL      	27 27 -68	; - 0.1
	387	[456]	SETTABLE 	26 -4 27	; "width" -
	388	[457]	SETTABLE 	26 -45 0	; "show_parent" -
	389	[463]	CLOSURE  	27 7	; 0x7fd9b140b4b0
	390	[463]	MOVE     	0 0
	391	[463]	MOVE     	0 2
	392	[463]	SETTABLE 	26 -30 27	; "callback" -
	393	[469]	CLOSURE  	27 8	; 0x7fd9b140c5f0
	394	[469]	MOVE     	0 0
	395	[469]	MOVE     	0 2
	396	[469]	SETTABLE 	26 -69 27	; "hold_callback" -
	397	[451]	CALL     	24 3 2
	398	[471]	GETUPVAL 	25 5	; Button
	399	[471]	SELF     	25 25 -1	; "new"
	400	[471]	NEWTABLE 	27 0 8
	401	[472]	SETTABLE 	27 -24 -46	; "text" "+"
	402	[473]	GETUPVAL 	28 6	; Size
	403	[473]	GETTABLE 	28 28 -41	; "margin"
	404	[473]	GETTABLE 	28 28 -42	; "small"
	405	[473]	SETTABLE 	27 -41 28	; "margin" -
	406	[474]	SETTABLE 	27 -43 -20	; "radius" 0
	407	[475]	GETTABLE 	28 0 -8	; "powerd"
	408	[475]	GETTABLE 	28 28 -11	; "auto_warmth"
	409	[475]	SETTABLE 	27 -28 28	; "enabled" -
	410	[476]	GETTABLE 	28 0 -38	; "screen_width"
	411	[476]	MUL      	28 28 -68	; - 0.1
	412	[476]	SETTABLE 	27 -4 28	; "width" -
	413	[477]	SETTABLE 	27 -45 0	; "show_parent" -
	414	[483]	CLOSURE  	28 9	; 0x7fd9b140c6f0
	415	[483]	MOVE     	0 0
	416	[483]	MOVE     	0 2
	417	[483]	SETTABLE 	27 -30 28	; "callback" -
	418	[489]	CLOSURE  	28 10	; 0x7fd9b140d120
	419	[489]	MOVE     	0 0
	420	[489]	MOVE     	0 2
	421	[489]	SETTABLE 	27 -69 28	; "hold_callback" -
	422	[471]	CALL     	25 3 2
	423	[492]	GETGLOBAL	26 -21	; table
	424	[492]	GETTABLE 	26 26 -22	; "insert"
	425	[492]	MOVE     	27 3
	426	[492]	MOVE     	28 12
	427	[492]	CALL     	26 3 1
	428	[493]	GETGLOBAL	26 -21	; table
	429	[493]	GETTABLE 	26 26 -22	; "insert"
	430	[493]	MOVE     	27 5
	431	[493]	MOVE     	28 19
	432	[493]	CALL     	26 3 1
	433	[494]	GETGLOBAL	26 -21	; table
	434	[494]	GETTABLE 	26 26 -22	; "insert"
	435	[494]	MOVE     	27 4
	436	[494]	MOVE     	28 20
	437	[494]	CALL     	26 3 1
	438	[495]	GETGLOBAL	26 -21	; table
	439	[495]	GETTABLE 	26 26 -22	; "insert"
	440	[495]	MOVE     	27 7
	441	[495]	MOVE     	28 21
	442	[495]	CALL     	26 3 1
	443	[496]	GETGLOBAL	26 -21	; table
	444	[496]	GETTABLE 	26 26 -22	; "insert"
	445	[496]	MOVE     	27 7
	446	[496]	MOVE     	28 22
	447	[496]	CALL     	26 3 1
	448	[497]	GETGLOBAL	26 -21	; table
	449	[497]	GETTABLE 	26 26 -22	; "insert"
	450	[497]	MOVE     	27 7
	451	[497]	MOVE     	28 24
	452	[497]	CALL     	26 3 1
	453	[498]	GETGLOBAL	26 -21	; table
	454	[498]	GETTABLE 	26 26 -22	; "insert"
	455	[498]	MOVE     	27 7
	456	[498]	MOVE     	28 23
	457	[498]	CALL     	26 3 1
	458	[499]	GETGLOBAL	26 -21	; table
	459	[499]	GETTABLE 	26 26 -22	; "insert"
	460	[499]	MOVE     	27 7
	461	[499]	MOVE     	28 25
	462	[499]	CALL     	26 3 1
	463	[501]	GETGLOBAL	26 -21	; table
	464	[501]	GETTABLE 	26 26 -22	; "insert"
	465	[501]	MOVE     	27 3
	466	[501]	MOVE     	28 8
	467	[501]	CALL     	26 3 1
	468	[502]	GETGLOBAL	26 -21	; table
	469	[502]	GETTABLE 	26 26 -22	; "insert"
	470	[502]	MOVE     	27 3
	471	[502]	MOVE     	28 5
	472	[502]	CALL     	26 3 1
	473	[503]	GETGLOBAL	26 -21	; table
	474	[503]	GETTABLE 	26 26 -22	; "insert"
	475	[503]	MOVE     	27 3
	476	[503]	MOVE     	28 8
	477	[503]	CALL     	26 3 1
	478	[504]	GETGLOBAL	26 -21	; table
	479	[504]	GETTABLE 	26 26 -22	; "insert"
	480	[504]	MOVE     	27 3
	481	[504]	MOVE     	28 6
	482	[504]	CALL     	26 3 1
	483	[505]	GETGLOBAL	26 -21	; table
	484	[505]	GETTABLE 	26 26 -22	; "insert"
	485	[505]	MOVE     	27 3
	486	[505]	MOVE     	28 8
	487	[505]	CALL     	26 3 1
	488	[506]	GETGLOBAL	26 -21	; table
	489	[506]	GETTABLE 	26 26 -22	; "insert"
	490	[506]	MOVE     	27 3
	491	[506]	MOVE     	28 4
	492	[506]	CALL     	26 3 1
	493	[507]	GETGLOBAL	26 -21	; table
	494	[507]	GETTABLE 	26 26 -22	; "insert"
	495	[507]	MOVE     	27 3
	496	[507]	MOVE     	28 8
	497	[507]	CALL     	26 3 1
	498	[508]	GETGLOBAL	26 -21	; table
	499	[508]	GETTABLE 	26 26 -22	; "insert"
	500	[508]	MOVE     	27 3
	501	[508]	MOVE     	28 7
	502	[508]	CALL     	26 3 1
	503	[509]	RETURN   	0 1

function <./frontend/ui/widget/frontlightwidget.lua:338,340> (10 instructions, 40 bytes at 0x7fd9b14078d0)
0 params, 6 slots, 3 upvalues, 0 locals, 2 constants, 0 functions
	1	[339]	GETUPVAL 	0 0	; self
	2	[339]	SELF     	0 0 -1	; "setProgress"
	3	[339]	GETUPVAL 	2 0	; self
	4	[339]	GETTABLE 	2 2 -2	; "fl_cur"
	5	[339]	GETUPVAL 	3 1	; step
	6	[339]	GETUPVAL 	4 2	; i
	7	[339]	GETUPVAL 	5 1	; step
	8	[339]	MUL      	4 4 5
	9	[339]	CALL     	0 5 1
	10	[340]	RETURN   	0 1

function <./frontend/ui/widget/frontlightwidget.lua:348,350> (10 instructions, 40 bytes at 0x7fd9b14076f0)
0 params, 6 slots, 3 upvalues, 0 locals, 2 constants, 0 functions
	1	[349]	GETUPVAL 	0 0	; self
	2	[349]	SELF     	0 0 -1	; "setProgress"
	3	[349]	GETUPVAL 	2 0	; self
	4	[349]	GETTABLE 	2 2 -2	; "fl_cur"
	5	[349]	GETUPVAL 	3 1	; step
	6	[349]	GETUPVAL 	4 2	; i
	7	[349]	GETUPVAL 	5 1	; step
	8	[349]	MUL      	4 4 5
	9	[349]	CALL     	0 5 1
	10	[350]	RETURN   	0 1

function <./frontend/ui/widget/frontlightwidget.lua:369,369> (12 instructions, 48 bytes at 0x7fd9b140ae40)
0 params, 6 slots, 3 upvalues, 0 locals, 4 constants, 0 functions
	1	[369]	GETUPVAL 	0 0	; self
	2	[369]	SELF     	0 0 -1	; "setProgress"
	3	[369]	GETUPVAL 	2 0	; self
	4	[369]	GETTABLE 	2 2 -2	; "fl_cur"
	5	[369]	GETUPVAL 	3 1	; step
	6	[369]	GETUPVAL 	4 2	; num_warmth
	7	[369]	GETUPVAL 	5 0	; self
	8	[369]	GETTABLE 	5 5 -3	; "nl_scale"
	9	[369]	MUL      	5 -4 5	; 1 -
	10	[369]	SUB      	4 4 5
	11	[369]	CALL     	0 5 1
	12	[369]	RETURN   	0 1

function <./frontend/ui/widget/frontlightwidget.lua:378,378> (12 instructions, 48 bytes at 0x7fd9b140b1a0)
0 params, 6 slots, 3 upvalues, 0 locals, 4 constants, 0 functions
	1	[378]	GETUPVAL 	0 0	; self
	2	[378]	SELF     	0 0 -1	; "setProgress"
	3	[378]	GETUPVAL 	2 0	; self
	4	[378]	GETTABLE 	2 2 -2	; "fl_cur"
	5	[378]	GETUPVAL 	3 1	; step
	6	[378]	GETUPVAL 	4 2	; num_warmth
	7	[378]	GETUPVAL 	5 0	; self
	8	[378]	GETTABLE 	5 5 -3	; "nl_scale"
	9	[378]	MUL      	5 -4 5	; 1 -
	10	[378]	ADD      	4 4 5
	11	[378]	CALL     	0 5 1
	12	[378]	RETURN   	0 1

function <./frontend/ui/widget/frontlightwidget.lua:393,393> (9 instructions, 36 bytes at 0x7fd9b140b320)
0 params, 5 slots, 2 upvalues, 0 locals, 3 constants, 0 functions
	1	[393]	GETUPVAL 	0 0	; self
	2	[393]	SELF     	0 0 -1	; "setProgress"
	3	[393]	GETUPVAL 	2 0	; self
	4	[393]	GETTABLE 	2 2 -2	; "fl_cur"
	5	[393]	GETUPVAL 	3 1	; step
	6	[393]	GETUPVAL 	4 0	; self
	7	[393]	GETTABLE 	4 4 -3	; "nl_min"
	8	[393]	CALL     	0 5 1
	9	[393]	RETURN   	0 1

function <./frontend/ui/widget/frontlightwidget.lua:402,402> (12 instructions, 48 bytes at 0x7fd9b140bb30)
0 params, 6 slots, 2 upvalues, 0 locals, 4 constants, 0 functions
	1	[402]	GETUPVAL 	0 0	; self
	2	[402]	SELF     	0 0 -1	; "setProgress"
	3	[402]	GETUPVAL 	2 0	; self
	4	[402]	GETTABLE 	2 2 -2	; "fl_cur"
	5	[402]	GETUPVAL 	3 1	; step
	6	[402]	GETUPVAL 	4 0	; self
	7	[402]	GETTABLE 	4 4 -3	; "nl_max"
	8	[402]	GETUPVAL 	5 0	; self
	9	[402]	GETTABLE 	5 5 -4	; "nl_scale"
	10	[402]	MUL      	4 4 5
	11	[402]	CALL     	0 5 1
	12	[402]	RETURN   	0 1

function <./frontend/ui/widget/frontlightwidget.lua:422,430> (23 instructions, 92 bytes at 0x7fd9b140bea0)
0 params, 4 slots, 2 upvalues, 0 locals, 7 constants, 0 functions
	1	[423]	GETUPVAL 	0 0	; self
	2	[423]	GETTABLE 	0 0 -1	; "powerd"
	3	[423]	GETTABLE 	0 0 -2	; "auto_warmth"
	4	[423]	TEST     	0 0 0
	5	[423]	JMP      	4	; to 10
	6	[424]	GETUPVAL 	0 0	; self
	7	[424]	GETTABLE 	0 0 -1	; "powerd"
	8	[424]	SETTABLE 	0 -2 -3	; "auto_warmth" false
	9	[424]	JMP      	7	; to 17
	10	[426]	GETUPVAL 	0 0	; self
	11	[426]	GETTABLE 	0 0 -1	; "powerd"
	12	[426]	SETTABLE 	0 -2 -4	; "auto_warmth" true
	13	[427]	GETUPVAL 	0 0	; self
	14	[427]	GETTABLE 	0 0 -1	; "powerd"
	15	[427]	SELF     	0 0 -5	; "calculateAutoWarmth"
	16	[427]	CALL     	0 2 1
	17	[429]	GETUPVAL 	0 0	; self
	18	[429]	SELF     	0 0 -6	; "setProgress"
	19	[429]	GETUPVAL 	2 0	; self
	20	[429]	GETTABLE 	2 2 -7	; "fl_cur"
	21	[429]	GETUPVAL 	3 1	; step
	22	[429]	CALL     	0 4 1
	23	[430]	RETURN   	0 1

function <./frontend/ui/widget/frontlightwidget.lua:458,463> (19 instructions, 76 bytes at 0x7fd9b140b4b0)
0 params, 4 slots, 2 upvalues, 0 locals, 7 constants, 0 functions
	1	[459]	GETUPVAL 	0 0	; self
	2	[459]	GETTABLE 	0 0 -1	; "powerd"
	3	[460]	GETUPVAL 	1 0	; self
	4	[460]	GETTABLE 	1 1 -1	; "powerd"
	5	[460]	GETTABLE 	1 1 -2	; "max_warmth_hour"
	6	[460]	SUB      	1 1 -3	; - 1
	7	[460]	MOD      	1 1 -4
	8	[460]	SETTABLE 	0 -2 1	; "max_warmth_hour" -
	9	[461]	GETUPVAL 	0 0	; self
	10	[461]	GETTABLE 	0 0 -1	; "powerd"
	11	[461]	SELF     	0 0 -5	; "calculateAutoWarmth"
	12	[461]	CALL     	0 2 1
	13	[462]	GETUPVAL 	0 0	; self
	14	[462]	SELF     	0 0 -6	; "setProgress"
	15	[462]	GETUPVAL 	2 0	; self
	16	[462]	GETTABLE 	2 2 -7	; "fl_cur"
	17	[462]	GETUPVAL 	3 1	; step
	18	[462]	CALL     	0 4 1
	19	[463]	RETURN   	0 1

function <./frontend/ui/widget/frontlightwidget.lua:464,469> (19 instructions, 76 bytes at 0x7fd9b140c5f0)
0 params, 4 slots, 2 upvalues, 0 locals, 7 constants, 0 functions
	1	[465]	GETUPVAL 	0 0	; self
	2	[465]	GETTABLE 	0 0 -1	; "powerd"
	3	[466]	GETUPVAL 	1 0	; self
	4	[466]	GETTABLE 	1 1 -1	; "powerd"
	5	[466]	GETTABLE 	1 1 -2	; "max_warmth_hour"
	6	[466]	SUB      	1 1 -3	; - 0.5
	7	[466]	MOD      	1 1 -4
	8	[466]	SETTABLE 	0 -2 1	; "max_warmth_hour" -
	9	[467]	GETUPVAL 	0 0	; self
	10	[467]	GETTABLE 	0 0 -1	; "powerd"
	11	[467]	SELF     	0 0 -5	; "calculateAutoWarmth"
	12	[467]	CALL     	0 2 1
	13	[468]	GETUPVAL 	0 0	; self
	14	[468]	SELF     	0 0 -6	; "setProgress"
	15	[468]	GETUPVAL 	2 0	; self
	16	[468]	GETTABLE 	2 2 -7	; "fl_cur"
	17	[468]	GETUPVAL 	3 1	; step
	18	[468]	CALL     	0 4 1
	19	[469]	RETURN   	0 1

function <./frontend/ui/widget/frontlightwidget.lua:478,483> (19 instructions, 76 bytes at 0x7fd9b140c6f0)
0 params, 4 slots, 2 upvalues, 0 locals, 7 constants, 0 functions
	1	[479]	GETUPVAL 	0 0	; self
	2	[479]	GETTABLE 	0 0 -1	; "powerd"
	3	[480]	GETUPVAL 	1 0	; self
	4	[480]	GETTABLE 	1 1 -1	; "powerd"
	5	[480]	GETTABLE 	1 1 -2	; "max_warmth_hour"
	6	[480]	ADD      	1 1 -3	; - 1
	7	[480]	MOD      	1 1 -4
	8	[480]	SETTABLE 	0 -2 1	; "max_warmth_hour" -
	9	[481]	GETUPVAL 	0 0	; self
	10	[481]	GETTABLE 	0 0 -1	; "powerd"
	11	[481]	SELF     	0 0 -5	; "calculateAutoWarmth"
	12	[481]	CALL     	0 2 1
	13	[482]	GETUPVAL 	0 0	; self
	14	[482]	SELF     	0 0 -6	; "setProgress"
	15	[482]	GETUPVAL 	2 0	; self
	16	[482]	GETTABLE 	2 2 -7	; "fl_cur"
	17	[482]	GETUPVAL 	3 1	; step
	18	[482]	CALL     	0 4 1
	19	[483]	RETURN   	0 1

function <./frontend/ui/widget/frontlightwidget.lua:484,489> (19 instructions, 76 bytes at 0x7fd9b140d120)
0 params, 4 slots, 2 upvalues, 0 locals, 7 constants, 0 functions
	1	[485]	GETUPVAL 	0 0	; self
	2	[485]	GETTABLE 	0 0 -1	; "powerd"
	3	[486]	GETUPVAL 	1 0	; self
	4	[486]	GETTABLE 	1 1 -1	; "powerd"
	5	[486]	GETTABLE 	1 1 -2	; "max_warmth_hour"
	6	[486]	ADD      	1 1 -3	; - 0.5
	7	[486]	MOD      	1 1 -4
	8	[486]	SETTABLE 	0 -2 1	; "max_warmth_hour" -
	9	[487]	GETUPVAL 	0 0	; self
	10	[487]	GETTABLE 	0 0 -1	; "powerd"
	11	[487]	SELF     	0 0 -5	; "calculateAutoWarmth"
	12	[487]	CALL     	0 2 1
	13	[488]	GETUPVAL 	0 0	; self
	14	[488]	SELF     	0 0 -6	; "setProgress"
	15	[488]	GETUPVAL 	2 0	; self
	16	[488]	GETTABLE 	2 2 -7	; "fl_cur"
	17	[488]	GETUPVAL 	3 1	; step
	18	[488]	CALL     	0 4 1
	19	[489]	RETURN   	0 1

function <./frontend/ui/widget/frontlightwidget.lua:511,533> (50 instructions, 200 bytes at 0x7fd9b140d520)
2 params, 7 slots, 1 upvalue, 3 locals, 18 constants, 0 functions
	1	[512]	SETTABLE 	0 -1 1	; "fl_cur" -
	2	[513]	GETGLOBAL	2 -2	; math
	3	[513]	GETTABLE 	2 2 -3	; "min"
	4	[513]	GETTABLE 	3 0 -1	; "fl_cur"
	5	[513]	GETTABLE 	4 0 -4	; "fl_max"
	6	[513]	CALL     	2 3 2
	7	[516]	GETTABLE 	3 0 -5	; 1
	8	[516]	TEST     	3 0 0
	9	[516]	JMP      	40	; to 50
	10	[517]	GETTABLE 	3 0 -6	; "fl_min"
	11	[517]	EQ       	0 2 3
	12	[517]	JMP      	4	; to 17
	13	[518]	GETTABLE 	3 0 -7	; "powerd"
	14	[518]	SELF     	3 3 -8	; "toggleFrontlight"
	15	[518]	CALL     	3 2 1
	16	[518]	JMP      	4	; to 21
	17	[520]	GETTABLE 	3 0 -7	; "powerd"
	18	[520]	SELF     	3 3 -9	; "setIntensity"
	19	[520]	MOVE     	5 2
	20	[520]	CALL     	3 3 1
	21	[523]	GETTABLE 	3 0 -10	; "light_fallback"
	22	[523]	TEST     	3 0 1
	23	[523]	JMP      	10	; to 34
	24	[523]	GETTABLE 	3 0 -1	; "fl_cur"
	25	[523]	LE       	0 -11 3	; 0 -
	26	[523]	JMP      	7	; to 34
	27	[524]	GETGLOBAL	3 -12	; G_reader_settings
	28	[524]	SELF     	3 3 -13	; "saveSetting"
	29	[524]	LOADK    	5 -14	; "fl_last_level"
	30	[524]	GETTABLE 	6 0 -1	; "fl_cur"
	31	[524]	MUL      	6 6 -15	; - 10
	32	[524]	CALL     	3 4 1
	33	[524]	JMP      	12	; to 46
	34	[525]	GETTABLE 	3 0 -10	; "light_fallback"
	35	[525]	TEST     	3 0 0
	36	[525]	JMP      	9	; to 46
	37	[526]	GETGLOBAL	3 -12	; G_reader_settings
	38	[526]	SELF     	3 3 -13	; "saveSetting"
	39	[526]	LOADK    	5 -14	; "fl_last_level"
	40	[526]	LOADNIL  	6 6
	41	[526]	CALL     	3 4 1
	42	[527]	GETUPVAL 	3 0	; Device
	43	[527]	SELF     	3 3 -16	; "setScreenBrightness"
	44	[527]	LOADK    	5 -17	; -1
	45	[527]	CALL     	3 3 1
	46	[531]	GETTABLE 	3 0 -7	; "powerd"
	47	[531]	SELF     	3 3 -18	; "frontlightIntensity"
	48	[531]	CALL     	3 2 2
	49	[531]	SETTABLE 	0 -1 3	; "fl_cur" -
	50	[533]	RETURN   	0 1

function <./frontend/ui/widget/frontlightwidget.lua:535,600> (163 instructions, 652 bytes at 0x7fd9b140d960)
1 param, 19 slots, 12 upvalues, 3 locals, 44 constants, 0 functions
	1	[537]	GETUPVAL 	1 0	; FrameContainer
	2	[537]	SELF     	1 1 -2	; "new"
	3	[537]	NEWTABLE 	3 0 3
	4	[538]	GETUPVAL 	4 1	; Size
	5	[538]	GETTABLE 	4 4 -3	; "padding"
	6	[538]	GETTABLE 	4 4 -4	; "default"
	7	[538]	SETTABLE 	3 -3 4	; "padding" -
	8	[539]	GETUPVAL 	4 1	; Size
	9	[539]	GETTABLE 	4 4 -5	; "margin"
	10	[539]	GETTABLE 	4 4 -6	; "title"
	11	[539]	SETTABLE 	3 -5 4	; "margin" -
	12	[540]	SETTABLE 	3 -7 -8	; "bordersize" 0
	13	[541]	GETUPVAL 	4 2	; TextWidget
	14	[541]	SELF     	4 4 -2	; "new"
	15	[541]	NEWTABLE 	6 0 4
	16	[542]	GETUPVAL 	7 3	; _
	17	[542]	LOADK    	8 -10	; "Frontlight"
	18	[542]	CALL     	7 2 2
	19	[542]	SETTABLE 	6 -9 7	; "text" -
	20	[543]	GETTABLE 	7 0 -12	; "title_face"
	21	[543]	SETTABLE 	6 -11 7	; "face" -
	22	[544]	SETTABLE 	6 -13 -14	; "bold" true
	23	[545]	GETTABLE 	7 0 -16	; "screen_width"
	24	[545]	MUL      	7 7 -17	; - 0.95
	25	[545]	SETTABLE 	6 -15 7	; "width" -
	26	[541]	CALL     	4 3 0
	27	[547]	SETLIST  	3 0 1	; 1
	28	[537]	CALL     	1 3 2
	29	[547]	SETTABLE 	0 -1 1	; "light_title" -
	30	[548]	GETUPVAL 	1 0	; FrameContainer
	31	[548]	SELF     	1 1 -2	; "new"
	32	[548]	NEWTABLE 	3 0 3
	33	[549]	GETUPVAL 	4 1	; Size
	34	[549]	GETTABLE 	4 4 -3	; "padding"
	35	[549]	GETTABLE 	4 4 -18	; "button"
	36	[549]	SETTABLE 	3 -3 4	; "padding" -
	37	[550]	GETUPVAL 	4 1	; Size
	38	[550]	GETTABLE 	4 4 -5	; "margin"
	39	[550]	GETTABLE 	4 4 -19	; "small"
	40	[550]	SETTABLE 	3 -5 4	; "margin" -
	41	[551]	SETTABLE 	3 -7 -8	; "bordersize" 0
	42	[552]	SELF     	4 0 -20	; "generateProgressGroup"
	43	[552]	GETTABLE 	6 0 -16	; "screen_width"
	44	[552]	MUL      	6 6 -17	; - 0.95
	45	[552]	GETTABLE 	7 0 -21	; "screen_height"
	46	[552]	MUL      	7 7 -22	; - 0.2
	47	[553]	GETTABLE 	8 0 -23	; "fl_cur"
	48	[553]	GETTABLE 	9 0 -24	; "one_step"
	49	[552]	CALL     	4 6 0
	50	[554]	SETLIST  	3 0 1	; 1
	51	[548]	CALL     	1 3 2
	52	[555]	GETUPVAL 	2 4	; LineWidget
	53	[555]	SELF     	2 2 -2	; "new"
	54	[555]	NEWTABLE 	4 0 1
	55	[556]	GETUPVAL 	5 5	; Geom
	56	[556]	SELF     	5 5 -2	; "new"
	57	[556]	NEWTABLE 	7 0 2
	58	[557]	GETTABLE 	8 0 -15	; "width"
	59	[557]	SETTABLE 	7 -26 8	; "w" -
	60	[558]	GETUPVAL 	8 1	; Size
	61	[558]	GETTABLE 	8 8 -28	; "line"
	62	[558]	GETTABLE 	8 8 -29	; "thick"
	63	[558]	SETTABLE 	7 -27 8	; "h" -
	64	[556]	CALL     	5 3 2
	65	[559]	SETTABLE 	4 -25 5	; "dimen" -
	66	[555]	CALL     	2 3 2
	67	[561]	GETUPVAL 	3 6	; OverlapGroup
	68	[561]	SELF     	3 3 -2	; "new"
	69	[561]	NEWTABLE 	5 1 1
	70	[562]	NEWTABLE 	6 0 2
	71	[563]	GETTABLE 	7 0 -15	; "width"
	72	[563]	SETTABLE 	6 -26 7	; "w" -
	73	[564]	GETTABLE 	7 0 -1	; "light_title"
	74	[564]	SELF     	7 7 -31	; "getSize"
	75	[564]	CALL     	7 2 2
	76	[564]	GETTABLE 	7 7 -27	; "h"
	77	[564]	SETTABLE 	6 -27 7	; "h" -
	78	[565]	SETTABLE 	5 -25 6	; "dimen" -
	79	[566]	GETTABLE 	6 0 -1	; "light_title"
	80	[567]	GETUPVAL 	7 7	; CloseButton
	81	[567]	SELF     	7 7 -2	; "new"
	82	[567]	NEWTABLE 	9 0 2
	83	[567]	SETTABLE 	9 -32 0	; "window" -
	84	[567]	GETUPVAL 	10 1	; Size
	85	[567]	GETTABLE 	10 10 -5	; "margin"
	86	[567]	GETTABLE 	10 10 -6	; "title"
	87	[567]	SETTABLE 	9 -33 10	; "padding_top" -
	88	[567]	CALL     	7 3 0
	89	[568]	SETLIST  	5 0 1	; 1
	90	[561]	CALL     	3 3 2
	91	[568]	SETTABLE 	0 -30 3	; "light_bar" -
	92	[569]	GETUPVAL 	3 0	; FrameContainer
	93	[569]	SELF     	3 3 -2	; "new"
	94	[569]	NEWTABLE 	5 0 5
	95	[570]	GETUPVAL 	6 1	; Size
	96	[570]	GETTABLE 	6 6 -35	; "radius"
	97	[570]	GETTABLE 	6 6 -32	; "window"
	98	[570]	SETTABLE 	5 -35 6	; "radius" -
	99	[571]	GETUPVAL 	6 1	; Size
	100	[571]	GETTABLE 	6 6 -36	; "border"
	101	[571]	GETTABLE 	6 6 -32	; "window"
	102	[571]	SETTABLE 	5 -7 6	; "bordersize" -
	103	[572]	SETTABLE 	5 -3 -8	; "padding" 0
	104	[573]	SETTABLE 	5 -5 -8	; "margin" 0
	105	[574]	GETUPVAL 	6 8	; Blitbuffer
	106	[574]	GETTABLE 	6 6 -38	; "COLOR_WHITE"
	107	[574]	SETTABLE 	5 -37 6	; "background" -
	108	[575]	GETUPVAL 	6 9	; VerticalGroup
	109	[575]	SELF     	6 6 -2	; "new"
	110	[575]	NEWTABLE 	8 2 1
	111	[576]	SETTABLE 	8 -39 -40	; "align" "left"
	112	[577]	GETTABLE 	9 0 -30	; "light_bar"
	113	[578]	MOVE     	10 2
	114	[579]	GETUPVAL 	11 10	; CenterContainer
	115	[579]	SELF     	11 11 -2	; "new"
	116	[579]	NEWTABLE 	13 1 1
	117	[580]	GETUPVAL 	14 5	; Geom
	118	[580]	SELF     	14 14 -2	; "new"
	119	[580]	NEWTABLE 	16 0 2
	120	[581]	SELF     	17 2 -31	; "getSize"
	121	[581]	CALL     	17 2 2
	122	[581]	GETTABLE 	17 17 -26	; "w"
	123	[581]	SETTABLE 	16 -26 17	; "w" -
	124	[582]	SELF     	17 1 -31	; "getSize"
	125	[582]	CALL     	17 2 2
	126	[582]	GETTABLE 	17 17 -27	; "h"
	127	[582]	SETTABLE 	16 -27 17	; "h" -
	128	[580]	CALL     	14 3 2
	129	[583]	SETTABLE 	13 -25 14	; "dimen" -
	130	[585]	MOVE     	14 1
	131	[585]	SETLIST  	13 1 1	; 1
	132	[579]	CALL     	11 3 0
	133	[586]	SETLIST  	8 0 1	; 1
	134	[575]	CALL     	6 3 0
	135	[587]	SETLIST  	5 0 1	; 1
	136	[569]	CALL     	3 3 2
	137	[587]	SETTABLE 	0 -34 3	; "light_frame" -
	138	[588]	GETUPVAL 	3 11	; WidgetContainer
	139	[588]	SELF     	3 3 -2	; "new"
	140	[588]	NEWTABLE 	5 0 2
	141	[589]	SETTABLE 	5 -39 -42	; "align" "center"
	142	[590]	GETUPVAL 	6 5	; Geom
	143	[590]	SELF     	6 6 -2	; "new"
	144	[590]	NEWTABLE 	8 0 4
	145	[591]	SETTABLE 	8 -43 -8	; "x" 0
	146	[591]	SETTABLE 	8 -44 -8	; "y" 0
	147	[592]	GETTABLE 	9 0 -16	; "screen_width"
	148	[592]	SETTABLE 	8 -26 9	; "w" -
	149	[593]	GETTABLE 	9 0 -21	; "screen_height"
	150	[593]	SETTABLE 	8 -27 9	; "h" -
	151	[590]	CALL     	6 3 2
	152	[594]	SETTABLE 	5 -25 6	; "dimen" -
	153	[595]	GETUPVAL 	6 0	; FrameContainer
	154	[595]	SELF     	6 6 -2	; "new"
	155	[595]	NEWTABLE 	8 1 1
	156	[596]	SETTABLE 	8 -7 -8	; "bordersize" 0
	157	[598]	GETTABLE 	9 0 -34	; "light_frame"
	158	[598]	SETLIST  	8 1 1	; 1
	159	[595]	CALL     	6 3 0
	160	[599]	SETLIST  	5 0 1	; 1
	161	[588]	CALL     	3 3 2
	162	[599]	SETTABLE 	0 -41 3	; 1 -
	163	[600]	RETURN   	0 1

function <./frontend/ui/widget/frontlightwidget.lua:602,607> (9 instructions, 36 bytes at 0x7fd9b140e2c0)
1 param, 5 slots, 1 upvalue, 1 local, 1 constant, 1 function
	1	[603]	GETUPVAL 	1 0	; UIManager
	2	[603]	SELF     	1 1 -1	; "setDirty"
	3	[603]	LOADNIL  	3 3
	4	[605]	CLOSURE  	4 0	; 0x7fd9b140e1e0
	5	[605]	MOVE     	0 0
	6	[603]	CALL     	1 4 1
	7	[606]	LOADBOOL 	1 1 0
	8	[606]	RETURN   	1 2
	9	[607]	RETURN   	0 1

function <./frontend/ui/widget/frontlightwidget.lua:603,605> (6 instructions, 24 bytes at 0x7fd9b140e1e0)
0 params, 2 slots, 1 upvalue, 0 locals, 3 constants, 0 functions
	1	[604]	LOADK    	0 -1	; "flashpartial"
	2	[604]	GETUPVAL 	1 0	; self
	3	[604]	GETTABLE 	1 1 -2	; "light_frame"
	4	[604]	GETTABLE 	1 1 -3	; "dimen"
	5	[604]	RETURN   	0 3
	6	[605]	RETURN   	0 1

function <./frontend/ui/widget/frontlightwidget.lua:609,615> (9 instructions, 36 bytes at 0x7fd9b140e580)
1 param, 5 slots, 1 upvalue, 1 local, 1 constant, 1 function
	1	[611]	GETUPVAL 	1 0	; UIManager
	2	[611]	SELF     	1 1 -1	; "setDirty"
	3	[611]	MOVE     	3 0
	4	[613]	CLOSURE  	4 0	; 0x7fd9b140e920
	5	[613]	MOVE     	0 0
	6	[611]	CALL     	1 4 1
	7	[614]	LOADBOOL 	1 1 0
	8	[614]	RETURN   	1 2
	9	[615]	RETURN   	0 1

function <./frontend/ui/widget/frontlightwidget.lua:611,613> (6 instructions, 24 bytes at 0x7fd9b140e920)
0 params, 2 slots, 1 upvalue, 0 locals, 3 constants, 0 functions
	1	[612]	LOADK    	0 -1	; "ui"
	2	[612]	GETUPVAL 	1 0	; self
	3	[612]	GETTABLE 	1 1 -2	; "light_frame"
	4	[612]	GETTABLE 	1 1 -3	; "dimen"
	5	[612]	RETURN   	0 3
	6	[613]	RETURN   	0 1

function <./frontend/ui/widget/frontlightwidget.lua:617,620> (7 instructions, 28 bytes at 0x7fd9b140ed40)
1 param, 4 slots, 1 upvalue, 1 local, 1 constant, 0 functions
	1	[618]	GETUPVAL 	1 0	; UIManager
	2	[618]	SELF     	1 1 -1	; "close"
	3	[618]	MOVE     	3 0
	4	[618]	CALL     	1 3 1
	5	[619]	LOADBOOL 	1 1 0
	6	[619]	RETURN   	1 2
	7	[620]	RETURN   	0 1

function <./frontend/ui/widget/frontlightwidget.lua:622,625> (7 instructions, 28 bytes at 0x7fd9b140ee50)
1 param, 4 slots, 1 upvalue, 1 local, 1 constant, 0 functions
	1	[623]	GETUPVAL 	1 0	; UIManager
	2	[623]	SELF     	1 1 -1	; "close"
	3	[623]	MOVE     	3 0
	4	[623]	CALL     	1 3 1
	5	[624]	LOADBOOL 	1 1 0
	6	[624]	RETURN   	1 2
	7	[625]	RETURN   	0 1

function <./frontend/ui/widget/frontlightwidget.lua:628,637> (16 instructions, 64 bytes at 0x7fd9b140f0c0)
1 param, 5 slots, 1 upvalue, 1 local, 12 constants, 0 functions
	1	[630]	GETGLOBAL	1 -1	; table
	2	[630]	GETTABLE 	1 1 -2	; "remove"
	3	[630]	GETTABLE 	2 0 -3	; "light_bar"
	4	[630]	CALL     	1 2 1
	5	[632]	GETTABLE 	1 0 -4	; "configure_button"
	6	[632]	SELF     	1 1 -5	; "disable"
	7	[632]	CALL     	1 2 1
	8	[633]	SETTABLE 	0 -6 -7	; "nl_configure_open" true
	9	[635]	GETTABLE 	1 0 -8	; 1
	10	[635]	SETTABLE 	1 -9 -10	; "align" "bottom"
	11	[636]	GETUPVAL 	1 0	; UIManager
	12	[636]	SELF     	1 1 -11	; "setDirty"
	13	[636]	MOVE     	3 0
	14	[636]	LOADK    	4 -12	; "ui"
	15	[636]	CALL     	1 4 1
	16	[637]	RETURN   	0 1

function <./frontend/ui/widget/frontlightwidget.lua:639,647> (25 instructions, 100 bytes at 0x7fd9b140b950)
1 param, 7 slots, 3 upvalues, 1 local, 17 constants, 0 functions
	1	[640]	GETGLOBAL	1 -1	; table
	2	[640]	GETTABLE 	1 1 -2	; "insert"
	3	[640]	GETTABLE 	2 0 -3	; "light_bar"
	4	[641]	GETUPVAL 	3 0	; CloseButton
	5	[641]	SELF     	3 3 -4	; "new"
	6	[641]	NEWTABLE 	5 0 2
	7	[641]	SETTABLE 	5 -5 0	; "window" -
	8	[642]	GETUPVAL 	6 1	; Size
	9	[642]	GETTABLE 	6 6 -7	; "margin"
	10	[642]	GETTABLE 	6 6 -8	; "title"
	11	[642]	SETTABLE 	5 -6 6	; "padding_top" -
	12	[641]	CALL     	3 3 0
	13	[640]	CALL     	1 0 1
	14	[643]	GETTABLE 	1 0 -9	; "configure_button"
	15	[643]	SELF     	1 1 -10	; "enable"
	16	[643]	CALL     	1 2 1
	17	[644]	SETTABLE 	0 -11 -12	; "nl_configure_open" false
	18	[645]	GETTABLE 	1 0 -13	; 1
	19	[645]	SETTABLE 	1 -14 -15	; "align" "center"
	20	[646]	GETUPVAL 	1 2	; UIManager
	21	[646]	SELF     	1 1 -16	; "setDirty"
	22	[646]	MOVE     	3 0
	23	[646]	LOADK    	4 -17	; "ui"
	24	[646]	CALL     	1 4 1
	25	[647]	RETURN   	0 1

function <./frontend/ui/widget/frontlightwidget.lua:649,683> (79 instructions, 316 bytes at 0x7fd9b140c970)
3 params, 12 slots, 4 upvalues, 7 locals, 23 constants, 0 functions
	1	[650]	GETTABLE 	3 2 -1	; "pos"
	2	[650]	SELF     	3 3 -2	; "intersectWith"
	3	[650]	GETTABLE 	5 0 -3	; "fl_group"
	4	[650]	GETTABLE 	5 5 -4	; "dimen"
	5	[650]	CALL     	3 3 2
	6	[650]	TEST     	3 0 0
	7	[650]	JMP      	57	; to 65
	8	[652]	GETUPVAL 	3 0	; UIManager
	9	[652]	SELF     	3 3 -5	; "unschedule"
	10	[652]	GETTABLE 	5 0 -6	; "update"
	11	[652]	CALL     	3 3 1
	12	[654]	GETTABLE 	3 0 -3	; "fl_group"
	13	[654]	SELF     	3 3 -7	; "getPercentageFromPosition"
	14	[654]	GETTABLE 	5 2 -1	; "pos"
	15	[654]	CALL     	3 3 2
	16	[655]	TEST     	3 0 1
	17	[655]	JMP      	2	; to 20
	18	[656]	LOADBOOL 	4 1 0
	19	[656]	RETURN   	4 2
	20	[658]	GETUPVAL 	4 1	; Math
	21	[658]	GETTABLE 	4 4 -8	; "round"
	22	[658]	GETTABLE 	5 0 -9	; "fl_max"
	23	[658]	MUL      	5 3 5
	24	[658]	CALL     	4 2 2
	25	[661]	SELF     	5 0 -10	; "setFrontLightIntensity"
	26	[661]	MOVE     	7 4
	27	[661]	CALL     	5 3 1
	28	[664]	GETUPVAL 	5 2	; Screen
	29	[664]	GETTABLE 	5 5 -11	; "low_pan_rate"
	30	[664]	TEST     	5 0 0
	31	[664]	JMP      	30	; to 62
	32	[665]	GETUPVAL 	5 3	; TimeVal
	33	[665]	SELF     	5 5 -12	; "now"
	34	[665]	CALL     	5 2 2
	35	[666]	GETTABLE 	6 0 -13	; "last_time"
	36	[666]	TEST     	6 0 1
	37	[666]	JMP      	4	; to 42
	38	[666]	GETUPVAL 	6 3	; TimeVal
	39	[666]	SELF     	6 6 -14	; "new"
	40	[666]	NEWTABLE 	8 0 0
	41	[666]	CALL     	6 3 2
	42	[667]	SUB      	7 5 6
	43	[667]	GETUPVAL 	8 3	; TimeVal
	44	[667]	SELF     	8 8 -14	; "new"
	45	[667]	NEWTABLE 	10 0 1
	46	[667]	GETTABLE 	11 0 -16	; "rate"
	47	[667]	DIV      	11 -17 11	; 1000000 -
	48	[667]	SETTABLE 	10 -15 11	; "usec" -
	49	[667]	CALL     	8 3 2
	50	[667]	LT       	0 8 7
	51	[667]	JMP      	2	; to 54
	52	[668]	SETTABLE 	0 -13 5	; "last_time" -
	53	[668]	JMP      	8	; to 62
	54	[671]	GETUPVAL 	7 0	; UIManager
	55	[671]	SELF     	7 7 -18	; "scheduleIn"
	56	[671]	LOADK    	9 -19	; 0.075
	57	[671]	GETTABLE 	10 0 -6	; "update"
	58	[671]	MOVE     	11 0
	59	[671]	CALL     	7 5 1
	60	[672]	LOADBOOL 	7 1 0
	61	[672]	RETURN   	7 2
	62	[676]	SELF     	5 0 -6	; "update"
	63	[676]	CALL     	5 2 1
	64	[676]	JMP      	12	; to 77
	65	[677]	GETTABLE 	3 2 -1	; "pos"
	66	[677]	SELF     	3 3 -2	; "intersectWith"
	67	[677]	GETTABLE 	5 0 -20	; "light_frame"
	68	[677]	GETTABLE 	5 5 -4	; "dimen"
	69	[677]	CALL     	3 3 2
	70	[677]	TEST     	3 0 1
	71	[677]	JMP      	5	; to 77
	72	[677]	GETTABLE 	3 2 -21	; "ges"
	73	[677]	EQ       	0 3 -22	; - "tap"
	74	[677]	JMP      	2	; to 77
	75	[679]	SELF     	3 0 -23	; "onClose"
	76	[679]	CALL     	3 2 1
	77	[682]	LOADBOOL 	3 1 0
	78	[682]	RETURN   	3 2
	79	[683]	RETURN   	0 1
