
main <./frontend/apps/cloudstorage/ftp.lua:0,0> (74 instructions, 296 bytes at 0x7fcc684068d0)
0+ params, 15 slots, 0 upvalues, 14 locals, 20 constants, 4 functions
	1	[1]	GETGLOBAL	0 -1	; require
	2	[1]	LOADK    	1 -2	; "ui/bidi"
	3	[1]	CALL     	0 2 2
	4	[2]	GETGLOBAL	1 -1	; require
	5	[2]	LOADK    	2 -3	; "ui/widget/confirmbox"
	6	[2]	CALL     	1 2 2
	7	[3]	GETGLOBAL	2 -1	; require
	8	[3]	LOADK    	3 -4	; "document/documentregistry"
	9	[3]	CALL     	2 2 2
	10	[4]	GETGLOBAL	3 -1	; require
	11	[4]	LOADK    	4 -5	; "apps/cloudstorage/ftpapi"
	12	[4]	CALL     	3 2 2
	13	[5]	GETGLOBAL	4 -1	; require
	14	[5]	LOADK    	5 -6	; "ui/widget/infomessage"
	15	[5]	CALL     	4 2 2
	16	[6]	GETGLOBAL	5 -1	; require
	17	[6]	LOADK    	6 -7	; "ui/widget/multiinputdialog"
	18	[6]	CALL     	5 2 2
	19	[7]	GETGLOBAL	6 -1	; require
	20	[7]	LOADK    	7 -8	; "apps/reader/readerui"
	21	[7]	CALL     	6 2 2
	22	[8]	GETGLOBAL	7 -1	; require
	23	[8]	LOADK    	8 -9	; "device"
	24	[8]	CALL     	7 2 2
	25	[8]	GETTABLE 	7 7 -10	; "screen"
	26	[9]	GETGLOBAL	8 -1	; require
	27	[9]	LOADK    	9 -11	; "ui/uimanager"
	28	[9]	CALL     	8 2 2
	29	[10]	GETGLOBAL	9 -1	; require
	30	[10]	LOADK    	10 -12	; "logger"
	31	[10]	CALL     	9 2 2
	32	[11]	GETGLOBAL	10 -1	; require
	33	[11]	LOADK    	11 -13	; "util"
	34	[11]	CALL     	10 2 2
	35	[12]	GETGLOBAL	11 -1	; require
	36	[12]	LOADK    	12 -14	; "gettext"
	37	[12]	CALL     	11 2 2
	38	[13]	GETGLOBAL	12 -1	; require
	39	[13]	LOADK    	13 -15	; "ffi/util"
	40	[13]	CALL     	12 2 2
	41	[13]	GETTABLE 	12 12 -16	; "template"
	42	[15]	NEWTABLE 	13 0 0
	43	[20]	CLOSURE  	14 0	; 0x7fcc684070b0
	44	[20]	MOVE     	0 3
	45	[20]	MOVE     	0 10
	46	[17]	SETTABLE 	13 -17 14	; "run" -
	47	[52]	CLOSURE  	14 1	; 0x7fcc684078e0
	48	[52]	MOVE     	0 3
	49	[52]	MOVE     	0 10
	50	[52]	MOVE     	0 9
	51	[52]	MOVE     	0 2
	52	[52]	MOVE     	0 8
	53	[52]	MOVE     	0 4
	54	[52]	MOVE     	0 12
	55	[52]	MOVE     	0 11
	56	[52]	MOVE     	0 0
	57	[52]	MOVE     	0 1
	58	[52]	MOVE     	0 6
	59	[22]	SETTABLE 	13 -18 14	; "downloadFile" -
	60	[155]	CLOSURE  	14 2	; 0x7fcc68408900
	61	[155]	MOVE     	0 11
	62	[155]	MOVE     	0 5
	63	[155]	MOVE     	0 8
	64	[155]	MOVE     	0 4
	65	[155]	MOVE     	0 7
	66	[54]	SETTABLE 	13 -19 14	; "config" -
	67	[160]	CLOSURE  	14 3	; 0x7fcc68409af0
	68	[160]	MOVE     	0 12
	69	[160]	MOVE     	0 11
	70	[160]	MOVE     	0 8
	71	[160]	MOVE     	0 4
	72	[157]	SETTABLE 	13 -20 14	; "info" -
	73	[162]	RETURN   	13 2
	74	[162]	RETURN   	0 1

function <./frontend/apps/cloudstorage/ftp.lua:17,20> (21 instructions, 84 bytes at 0x7fcc684070b0)
5 params, 11 slots, 2 upvalues, 6 locals, 3 constants, 0 functions
	1	[18]	GETUPVAL 	5 0	; FtpApi
	2	[18]	SELF     	5 5 -1	; "generateUrl"
	3	[18]	MOVE     	7 1
	4	[18]	GETUPVAL 	8 1	; util
	5	[18]	GETTABLE 	8 8 -2	; "urlEncode"
	6	[18]	MOVE     	9 2
	7	[18]	CALL     	8 2 2
	8	[18]	GETUPVAL 	9 1	; util
	9	[18]	GETTABLE 	9 9 -2	; "urlEncode"
	10	[18]	MOVE     	10 3
	11	[18]	CALL     	9 2 0
	12	[18]	CALL     	5 0 2
	13	[18]	MOVE     	6 4
	14	[18]	CONCAT   	5 5 6
	15	[19]	GETUPVAL 	6 0	; FtpApi
	16	[19]	SELF     	6 6 -3	; "listFolder"
	17	[19]	MOVE     	8 5
	18	[19]	MOVE     	9 4
	19	[19]	TAILCALL 	6 4 0
	20	[19]	RETURN   	6 0
	21	[20]	RETURN   	0 1

function <./frontend/apps/cloudstorage/ftp.lua:22,52> (118 instructions, 472 bytes at 0x7fcc684078e0)
7 params, 21 slots, 11 upvalues, 12 locals, 30 constants, 1 function
	1	[23]	GETUPVAL 	7 0	; FtpApi
	2	[23]	SELF     	7 7 -1	; "generateUrl"
	3	[23]	MOVE     	9 2
	4	[23]	GETUPVAL 	10 1	; util
	5	[23]	GETTABLE 	10 10 -2	; "urlEncode"
	6	[23]	MOVE     	11 3
	7	[23]	CALL     	10 2 2
	8	[23]	GETUPVAL 	11 1	; util
	9	[23]	GETTABLE 	11 11 -2	; "urlEncode"
	10	[23]	MOVE     	12 4
	11	[23]	CALL     	11 2 0
	12	[23]	CALL     	7 0 2
	13	[23]	GETTABLE 	8 1 -3	; "url"
	14	[23]	CONCAT   	7 7 8
	15	[24]	GETUPVAL 	8 2	; logger
	16	[24]	GETTABLE 	8 8 -4	; "dbg"
	17	[24]	LOADK    	9 -5	; "downloadFile url"
	18	[24]	MOVE     	10 7
	19	[24]	CALL     	8 3 1
	20	[25]	GETUPVAL 	8 0	; FtpApi
	21	[25]	SELF     	8 8 -6	; "ftpGet"
	22	[25]	MOVE     	10 7
	23	[25]	LOADK    	11 -7	; "retr"
	24	[25]	CALL     	8 4 2
	25	[26]	EQ       	1 8 -8	; - nil
	26	[26]	JMP      	73	; to 100
	27	[27]	GETUPVAL 	9 1	; util
	28	[27]	GETTABLE 	9 9 -9	; "fixUtf8"
	29	[27]	MOVE     	10 5
	30	[27]	LOADK    	11 -10	; "_"
	31	[27]	CALL     	9 3 2
	32	[27]	MOVE     	5 9
	33	[28]	GETGLOBAL	9 -11	; io
	34	[28]	GETTABLE 	9 9 -12	; "open"
	35	[28]	MOVE     	10 5
	36	[28]	LOADK    	11 -13	; "w"
	37	[28]	CALL     	9 3 2
	38	[29]	SELF     	10 9 -14	; "write"
	39	[29]	MOVE     	12 8
	40	[29]	CALL     	10 3 1
	41	[30]	SELF     	10 9 -15	; "close"
	42	[30]	CALL     	10 2 1
	43	[31]	GETUPVAL 	10 1	; util
	44	[31]	GETTABLE 	10 10 -16	; "splitFilePathName"
	45	[31]	MOVE     	11 5
	46	[31]	CALL     	10 2 3
	47	[32]	GETGLOBAL	12 -17	; G_reader_settings
	48	[32]	SELF     	12 12 -18	; "isTrue"
	49	[32]	LOADK    	14 -19	; "show_unsupported"
	50	[32]	CALL     	12 3 2
	51	[32]	TEST     	12 0 0
	52	[32]	JMP      	24	; to 77
	53	[32]	GETUPVAL 	12 3	; DocumentRegistry
	54	[32]	SELF     	12 12 -20	; "hasProvider"
	55	[32]	MOVE     	14 11
	56	[32]	CALL     	12 3 2
	57	[32]	TEST     	12 0 1
	58	[32]	JMP      	18	; to 77
	59	[33]	GETUPVAL 	12 4	; UIManager
	60	[33]	SELF     	12 12 -21	; "show"
	61	[33]	GETUPVAL 	14 5	; InfoMessage
	62	[33]	SELF     	14 14 -22	; "new"
	63	[33]	NEWTABLE 	16 0 1
	64	[34]	GETUPVAL 	17 6	; T
	65	[34]	GETUPVAL 	18 7	; _
	66	[34]	LOADK    	19 -24	; "File saved to:\n%1"
	67	[34]	CALL     	18 2 2
	68	[34]	GETUPVAL 	19 8	; BD
	69	[34]	GETTABLE 	19 19 -25	; "filepath"
	70	[34]	MOVE     	20 5
	71	[34]	CALL     	19 2 0
	72	[34]	CALL     	17 0 2
	73	[34]	SETTABLE 	16 -23 17	; "text" -
	74	[33]	CALL     	14 3 0
	75	[33]	CALL     	12 0 1
	76	[35]	JMP      	41	; to 118
	77	[37]	GETUPVAL 	12 4	; UIManager
	78	[37]	SELF     	12 12 -21	; "show"
	79	[37]	GETUPVAL 	14 9	; ConfirmBox
	80	[37]	SELF     	14 14 -22	; "new"
	81	[37]	NEWTABLE 	16 0 2
	82	[38]	GETUPVAL 	17 6	; T
	83	[38]	GETUPVAL 	18 7	; _
	84	[38]	LOADK    	19 -26	; "File saved to:\n%1\nWould you like to read the downloaded book now?"
	85	[38]	CALL     	18 2 2
	86	[39]	GETUPVAL 	19 8	; BD
	87	[39]	GETTABLE 	19 19 -25	; "filepath"
	88	[39]	MOVE     	20 5
	89	[39]	CALL     	19 2 0
	90	[38]	CALL     	17 0 2
	91	[39]	SETTABLE 	16 -23 17	; "text" -
	92	[43]	CLOSURE  	17 0	; 0x7fcc684085e0
	93	[43]	MOVE     	0 6
	94	[43]	GETUPVAL 	0 10	; ReaderUI
	95	[43]	MOVE     	0 5
	96	[43]	SETTABLE 	16 -27 17	; "ok_callback" -
	97	[37]	CALL     	14 3 0
	98	[37]	CALL     	12 0 1
	99	[45]	JMP      	18	; to 118
	100	[47]	GETUPVAL 	9 4	; UIManager
	101	[47]	SELF     	9 9 -21	; "show"
	102	[47]	GETUPVAL 	11 5	; InfoMessage
	103	[47]	SELF     	11 11 -22	; "new"
	104	[47]	NEWTABLE 	13 0 2
	105	[48]	GETUPVAL 	14 6	; T
	106	[48]	GETUPVAL 	15 7	; _
	107	[48]	LOADK    	16 -28	; "Could not save file to:\n%1"
	108	[48]	CALL     	15 2 2
	109	[48]	GETUPVAL 	16 8	; BD
	110	[48]	GETTABLE 	16 16 -25	; "filepath"
	111	[48]	MOVE     	17 5
	112	[48]	CALL     	16 2 0
	113	[48]	CALL     	14 0 2
	114	[48]	SETTABLE 	13 -23 14	; "text" -
	115	[49]	SETTABLE 	13 -29 -30	; "timeout" 3
	116	[47]	CALL     	11 3 0
	117	[47]	CALL     	9 0 1
	118	[52]	RETURN   	0 1

function <./frontend/apps/cloudstorage/ftp.lua:40,43> (7 instructions, 28 bytes at 0x7fcc684085e0)
0 params, 3 slots, 3 upvalues, 0 locals, 1 constant, 0 functions
	1	[41]	GETUPVAL 	0 0	; close
	2	[41]	CALL     	0 1 1
	3	[42]	GETUPVAL 	0 1	; ReaderUI
	4	[42]	SELF     	0 0 -1	; "showReader"
	5	[42]	GETUPVAL 	2 2	; path
	6	[42]	CALL     	0 3 1
	7	[43]	RETURN   	0 1

function <./frontend/apps/cloudstorage/ftp.lua:54,155> (132 instructions, 528 bytes at 0x7fcc68408900)
3 params, 25 slots, 5 upvalues, 16 locals, 39 constants, 3 functions
	1	[55]	LOADK    	3 -1	; "FTP address must be in the format ftp://example.domain.com\n"
	2	[56]	LOADK    	4 -2	; "Also supported is format with IP e.g: ftp://10.10.10.1\n"
	3	[57]	LOADK    	5 -3	; "Username and password are optional."
	4	[57]	CONCAT   	3 3 5
	5	[58]	GETUPVAL 	4 0	; _
	6	[58]	LOADK    	5 -4	; "Your FTP name"
	7	[58]	CALL     	4 2 2
	8	[59]	LOADK    	5 -5	; ""
	9	[60]	GETUPVAL 	6 0	; _
	10	[60]	LOADK    	7 -6	; "FTP address eg ftp://example.com"
	11	[60]	CALL     	6 2 2
	12	[61]	LOADK    	7 -5	; ""
	13	[62]	GETUPVAL 	8 0	; _
	14	[62]	LOADK    	9 -7	; "FTP username"
	15	[62]	CALL     	8 2 2
	16	[63]	LOADK    	9 -5	; ""
	17	[64]	GETUPVAL 	10 0	; _
	18	[64]	LOADK    	11 -8	; "FTP password"
	19	[64]	CALL     	10 2 2
	20	[65]	LOADK    	11 -5	; ""
	21	[66]	GETUPVAL 	12 0	; _
	22	[66]	LOADK    	13 -9	; "FTP folder"
	23	[66]	CALL     	12 2 2
	24	[67]	LOADK    	13 -10	; "/"
	25	[68]	LOADNIL  	14 14
	26	[69]	GETUPVAL 	15 0	; _
	27	[69]	LOADK    	16 -11	; "Add"
	28	[69]	CALL     	15 2 2
	29	[70]	TEST     	1 0 0
	30	[70]	JMP      	14	; to 45
	31	[71]	GETUPVAL 	16 0	; _
	32	[71]	LOADK    	17 -12	; "Edit FTP account"
	33	[71]	CALL     	16 2 2
	34	[71]	MOVE     	14 16
	35	[72]	GETUPVAL 	16 0	; _
	36	[72]	LOADK    	17 -13	; "Apply"
	37	[72]	CALL     	16 2 2
	38	[72]	MOVE     	15 16
	39	[73]	GETTABLE 	5 1 -14	; "text"
	40	[74]	GETTABLE 	7 1 -15	; "address"
	41	[75]	GETTABLE 	9 1 -16	; "username"
	42	[76]	GETTABLE 	11 1 -17	; "password"
	43	[77]	GETTABLE 	13 1 -18	; "url"
	44	[77]	JMP      	4	; to 49
	45	[79]	GETUPVAL 	16 0	; _
	46	[79]	LOADK    	17 -19	; "Add FTP account"
	47	[79]	CALL     	16 2 2
	48	[79]	MOVE     	14 16
	49	[81]	GETUPVAL 	16 1	; MultiInputDialog
	50	[81]	SELF     	16 16 -21	; "new"
	51	[81]	NEWTABLE 	18 0 6
	52	[82]	SETTABLE 	18 -22 14	; "title" -
	53	[83]	NEWTABLE 	19 5 0
	54	[83]	NEWTABLE 	20 0 3
	55	[85]	SETTABLE 	20 -14 5	; "text" -
	56	[86]	SETTABLE 	20 -24 -25	; "input_type" "string"
	57	[87]	SETTABLE 	20 -26 4	; "hint" -
	58	[88]	NEWTABLE 	21 0 3
	59	[90]	SETTABLE 	21 -14 7	; "text" -
	60	[91]	SETTABLE 	21 -24 -25	; "input_type" "string"
	61	[92]	SETTABLE 	21 -26 6	; "hint" -
	62	[93]	NEWTABLE 	22 0 3
	63	[95]	SETTABLE 	22 -14 9	; "text" -
	64	[96]	SETTABLE 	22 -24 -25	; "input_type" "string"
	65	[97]	SETTABLE 	22 -26 8	; "hint" -
	66	[98]	NEWTABLE 	23 0 4
	67	[100]	SETTABLE 	23 -14 11	; "text" -
	68	[101]	SETTABLE 	23 -24 -25	; "input_type" "string"
	69	[102]	SETTABLE 	23 -27 -17	; "text_type" "password"
	70	[103]	SETTABLE 	23 -26 10	; "hint" -
	71	[104]	NEWTABLE 	24 0 3
	72	[106]	SETTABLE 	24 -14 13	; "text" -
	73	[107]	SETTABLE 	24 -24 -25	; "input_type" "string"
	74	[108]	SETTABLE 	24 -26 12	; "hint" -
	75	[110]	SETLIST  	19 5 1	; 1
	76	[110]	SETTABLE 	18 -23 19	; "fields" -
	77	[111]	NEWTABLE 	19 1 0
	78	[111]	NEWTABLE 	20 3 0
	79	[112]	NEWTABLE 	21 0 2
	80	[114]	GETUPVAL 	22 0	; _
	81	[114]	LOADK    	23 -29	; "Cancel"
	82	[114]	CALL     	22 2 2
	83	[114]	SETTABLE 	21 -14 22	; "text" -
	84	[118]	CLOSURE  	22 0	; 0x7fcc684075e0
	85	[118]	MOVE     	0 0
	86	[118]	GETUPVAL 	0 2	; UIManager
	87	[118]	SETTABLE 	21 -30 22	; "callback" -
	88	[119]	NEWTABLE 	22 0 2
	89	[121]	GETUPVAL 	23 0	; _
	90	[121]	LOADK    	24 -31	; "Info"
	91	[121]	CALL     	23 2 2
	92	[121]	SETTABLE 	22 -14 23	; "text" -
	93	[124]	CLOSURE  	23 1	; 0x7fcc684096a0
	94	[124]	GETUPVAL 	0 2	; UIManager
	95	[124]	GETUPVAL 	0 3	; InfoMessage
	96	[124]	MOVE     	0 3
	97	[124]	SETTABLE 	22 -30 23	; "callback" -
	98	[125]	NEWTABLE 	23 0 2
	99	[127]	SETTABLE 	23 -14 15	; "text" -
	100	[145]	CLOSURE  	24 2	; 0x7fcc68409800
	101	[145]	GETUPVAL 	0 1	; MultiInputDialog
	102	[145]	MOVE     	0 1
	103	[145]	MOVE     	0 2
	104	[145]	MOVE     	0 0
	105	[145]	GETUPVAL 	0 2	; UIManager
	106	[145]	GETUPVAL 	0 3	; InfoMessage
	107	[145]	GETUPVAL 	0 0	; _
	108	[145]	SETTABLE 	23 -30 24	; "callback" -
	109	[147]	SETLIST  	20 3 1	; 1
	110	[148]	SETLIST  	19 1 1	; 1
	111	[148]	SETTABLE 	18 -28 19	; "buttons" -
	112	[149]	GETUPVAL 	19 4	; Screen
	113	[149]	SELF     	19 19 -33	; "getWidth"
	114	[149]	CALL     	19 2 2
	115	[149]	MUL      	19 19 -34	; - 0.95
	116	[149]	SETTABLE 	18 -32 19	; "width" -
	117	[150]	GETUPVAL 	19 4	; Screen
	118	[150]	SELF     	19 19 -36	; "getHeight"
	119	[150]	CALL     	19 2 2
	120	[150]	MUL      	19 19 -37	; - 0.2
	121	[150]	SETTABLE 	18 -35 19	; "height" -
	122	[151]	SETTABLE 	18 -24 -14	; "input_type" "text"
	123	[81]	CALL     	16 3 2
	124	[152]	SETTABLE 	0 -20 16	; "settings_dialog" -
	125	[153]	GETUPVAL 	16 2	; UIManager
	126	[153]	SELF     	16 16 -38	; "show"
	127	[153]	GETTABLE 	18 0 -20	; "settings_dialog"
	128	[153]	CALL     	16 3 1
	129	[154]	GETTABLE 	16 0 -20	; "settings_dialog"
	130	[154]	SELF     	16 16 -39	; "onShowKeyboard"
	131	[154]	CALL     	16 2 1
	132	[155]	RETURN   	0 1

function <./frontend/apps/cloudstorage/ftp.lua:115,118> (10 instructions, 40 bytes at 0x7fcc684075e0)
0 params, 3 slots, 2 upvalues, 0 locals, 3 constants, 0 functions
	1	[116]	GETUPVAL 	0 0	; self
	2	[116]	GETTABLE 	0 0 -1	; "settings_dialog"
	3	[116]	SELF     	0 0 -2	; "onClose"
	4	[116]	CALL     	0 2 1
	5	[117]	GETUPVAL 	0 1	; UIManager
	6	[117]	SELF     	0 0 -3	; "close"
	7	[117]	GETUPVAL 	2 0	; self
	8	[117]	GETTABLE 	2 2 -1	; "settings_dialog"
	9	[117]	CALL     	0 3 1
	10	[118]	RETURN   	0 1

function <./frontend/apps/cloudstorage/ftp.lua:122,124> (10 instructions, 40 bytes at 0x7fcc684096a0)
0 params, 6 slots, 3 upvalues, 0 locals, 3 constants, 0 functions
	1	[123]	GETUPVAL 	0 0	; UIManager
	2	[123]	SELF     	0 0 -1	; "show"
	3	[123]	GETUPVAL 	2 1	; InfoMessage
	4	[123]	SELF     	2 2 -2	; "new"
	5	[123]	NEWTABLE 	4 0 1
	6	[123]	GETUPVAL 	5 2	; text_info
	7	[123]	SETTABLE 	4 -3 5	; "text" -
	8	[123]	CALL     	2 3 0
	9	[123]	CALL     	0 0 1
	10	[124]	RETURN   	0 1

function <./frontend/apps/cloudstorage/ftp.lua:128,145> (42 instructions, 168 bytes at 0x7fcc68409800)
0 params, 8 slots, 7 upvalues, 1 local, 11 constants, 0 functions
	1	[129]	GETUPVAL 	0 0	; MultiInputDialog
	2	[129]	SELF     	0 0 -1	; "getFields"
	3	[129]	CALL     	0 2 2
	4	[130]	GETTABLE 	1 0 -2	; 1
	5	[130]	EQ       	1 1 -3	; - ""
	6	[130]	JMP      	24	; to 31
	7	[130]	GETTABLE 	1 0 -4	; 2
	8	[130]	EQ       	1 1 -3	; - ""
	9	[130]	JMP      	21	; to 31
	10	[131]	GETUPVAL 	1 1	; item
	11	[131]	TEST     	1 0 0
	12	[131]	JMP      	5	; to 18
	13	[133]	GETUPVAL 	1 2	; callback
	14	[133]	GETUPVAL 	2 1	; item
	15	[133]	MOVE     	3 0
	16	[133]	CALL     	1 3 1
	17	[133]	JMP      	3	; to 21
	18	[136]	GETUPVAL 	1 2	; callback
	19	[136]	MOVE     	2 0
	20	[136]	CALL     	1 2 1
	21	[138]	GETUPVAL 	1 3	; self
	22	[138]	GETTABLE 	1 1 -5	; "settings_dialog"
	23	[138]	SELF     	1 1 -6	; "onClose"
	24	[138]	CALL     	1 2 1
	25	[139]	GETUPVAL 	1 4	; UIManager
	26	[139]	SELF     	1 1 -7	; "close"
	27	[139]	GETUPVAL 	3 3	; self
	28	[139]	GETTABLE 	3 3 -5	; "settings_dialog"
	29	[139]	CALL     	1 3 1
	30	[139]	JMP      	11	; to 42
	31	[141]	GETUPVAL 	1 4	; UIManager
	32	[141]	SELF     	1 1 -8	; "show"
	33	[141]	GETUPVAL 	3 5	; InfoMessage
	34	[141]	SELF     	3 3 -9	; "new"
	35	[141]	NEWTABLE 	5 0 1
	36	[142]	GETUPVAL 	6 6	; _
	37	[142]	LOADK    	7 -11	; "Please fill in all fields."
	38	[142]	CALL     	6 2 2
	39	[142]	SETTABLE 	5 -10 6	; "text" -
	40	[141]	CALL     	3 3 0
	41	[141]	CALL     	1 0 1
	42	[145]	RETURN   	0 1

function <./frontend/apps/cloudstorage/ftp.lua:157,160> (17 instructions, 68 bytes at 0x7fcc68409af0)
2 params, 8 slots, 4 upvalues, 3 locals, 6 constants, 0 functions
	1	[158]	GETUPVAL 	2 0	; T
	2	[158]	GETUPVAL 	3 1	; _
	3	[158]	LOADK    	4 -1	; "Type: %1\nName: %2\nAddress: %3"
	4	[158]	CALL     	3 2 2
	5	[158]	LOADK    	4 -2	; "FTP"
	6	[158]	GETTABLE 	5 1 -3	; "text"
	7	[158]	GETTABLE 	6 1 -4	; "address"
	8	[158]	CALL     	2 5 2
	9	[159]	GETUPVAL 	3 2	; UIManager
	10	[159]	SELF     	3 3 -5	; "show"
	11	[159]	GETUPVAL 	5 3	; InfoMessage
	12	[159]	SELF     	5 5 -6	; "new"
	13	[159]	NEWTABLE 	7 0 1
	14	[159]	SETTABLE 	7 -3 2	; "text" -
	15	[159]	CALL     	5 3 0
	16	[159]	CALL     	3 0 1
	17	[160]	RETURN   	0 1
