-- BYTECODE -- geometry.lua:34-39
0001    IST          1
0002    JMP      2 => 0004
0003    TNEW     1   0
0004 => GGET     2   0      ; "setmetatable"
0005    MOV      3   1
0006    MOV      4   0
0007    CALL     2   1   3
0008    TSETS    0   0   1  ; "__index"
0009    RET1     1   2

-- BYTECODE -- geometry.lua:45-52
0001    UGET     1   0      ; Geom
0002    MOV      2   1
0003    TGETS    1   1   0  ; "new"
0004    CALL     1   2   2
0005    TGETS    2   0   1  ; "x"
0006    TSETS    2   1   1  ; "x"
0007    TGETS    2   0   2  ; "y"
0008    TSETS    2   1   2  ; "y"
0009    TGETS    2   0   3  ; "w"
0010    TSETS    2   1   3  ; "w"
0011    TGETS    2   0   4  ; "h"
0012    TSETS    2   1   4  ; "h"
0013    RET1     1   2

-- BYTECODE -- geometry.lua:54-56
0001    TGETS    1   0   0  ; "w"
0002    KSTR     2   1      ; "x"
0003    TGETS    3   0   2  ; "h"
0004    KSTR     4   3      ; "+"
0005    TGETS    5   0   1  ; "x"
0006    KSTR     6   3      ; "+"
0007    TGETS    7   0   4  ; "y"
0008    CAT      1   1   7
0009    RET1     1   2

-- BYTECODE -- geometry.lua:63-67
0001    TGETS    3   0   0  ; "x"
0002    ADDVV    3   3   1
0003    TSETS    3   0   0  ; "x"
0004    TGETS    3   0   1  ; "y"
0005    ADDVV    3   3   2
0006    TSETS    3   0   1  ; "y"
0007    RET1     0   2

-- BYTECODE -- geometry.lua:74-78
0001    TSETS    1   0   0  ; "x"
0002    TSETS    2   0   1  ; "y"
0003    RET1     0   2

-- BYTECODE -- geometry.lua:88-92
0001    UGET     3   0      ; Math
0002    TGETS    3   3   1  ; "round"
0003    TGETS    4   0   0  ; "w"
0004    MULVV    4   4   1
0005    CALL     3   2   2
0006    TSETS    3   0   0  ; "w"
0007    UGET     3   0      ; Math
0008    TGETS    3   3   1  ; "round"
0009    TGETS    4   0   2  ; "h"
0010    ISTC     5   2
0011    JMP      5 => 0013
0012    MOV      5   1
0013 => MULVV    4   4   5
0014    CALL     3   2   2
0015    TSETS    3   0   2  ; "h"
0016    RET1     0   2

-- BYTECODE -- geometry.lua:100-104
0001    UGET     3   0      ; Math
0002    TGETS    3   3   1  ; "round"
0003    TGETS    4   0   0  ; "x"
0004    MULVV    4   4   1
0005    CALL     3   2   2
0006    TSETS    3   0   0  ; "x"
0007    UGET     3   0      ; Math
0008    TGETS    3   3   1  ; "round"
0009    TGETS    4   0   2  ; "y"
0010    ISTC     5   1
0011    JMP      5 => 0013
0012    MOV      5   2
0013 => MULVV    4   4   5
0014    CALL     3   2   2
0015    TSETS    3   0   2  ; "y"
0016    MOV      4   0
0017    TGETS    3   0   3  ; "scaleBy"
0018    MOV      5   1
0019    MOV      6   2
0020    CALL     3   1   4
0021    RET0     0   1

-- BYTECODE -- geometry.lua:111-117
0001    TGETS    1   0   0  ; "w"
0002    ISF          1
0003    JMP      1 => 0007
0004    TGETS    1   0   1  ; "h"
0005    IST          1
0006    JMP      1 => 0010
0007 => KSHORT   1   0
0008    RET1     1   2
0009    JMP      1 => 0014
0010 => TGETS    1   0   0  ; "w"
0011    TGETS    2   0   1  ; "h"
0012    MULVV    1   1   2
0013    RET1     1   2
0014 => RET0     0   1

-- BYTECODE -- geometry.lua:127-131
0001    TGETS    3   0   0  ; "w"
0002    ADDVV    3   3   1
0003    TSETS    3   0   0  ; "w"
0004    TGETS    3   0   1  ; "h"
0005    ADDVV    3   3   2
0006    TSETS    3   0   1  ; "h"
0007    RET1     0   2

-- BYTECODE -- geometry.lua:141-161
0001    MOV      3   0
0002    TGETS    2   0   0  ; "copy"
0003    CALL     2   2   2
0004    ISF          1
0005    JMP      3 => 0011
0006    MOV      4   1
0007    TGETS    3   1   1  ; "area"
0008    CALL     3   2   2
0009    ISNEN    3   0      ; 0
0010    JMP      3 => 0012
0011 => RET1     2   2
0012 => TGETS    3   2   2  ; "x"
0013    TGETS    4   1   2  ; "x"
0014    ISGE     4   3
0015    JMP      3 => 0018
0016    TGETS    3   1   2  ; "x"
0017    TSETS    3   2   2  ; "x"
0018 => TGETS    3   2   3  ; "y"
0019    TGETS    4   1   3  ; "y"
0020    ISGE     4   3
0021    JMP      3 => 0024
0022    TGETS    3   1   3  ; "y"
0023    TSETS    3   2   3  ; "y"
0024 => TGETS    3   0   2  ; "x"
0025    TGETS    4   0   4  ; "w"
0026    ADDVV    3   3   4
0027    TGETS    4   1   2  ; "x"
0028    TGETS    5   1   4  ; "w"
0029    ADDVV    4   4   5
0030    ISGE     4   3
0031    JMP      3 => 0039
0032    TGETS    3   0   2  ; "x"
0033    TGETS    4   0   4  ; "w"
0034    ADDVV    3   3   4
0035    TGETS    4   2   2  ; "x"
0036    SUBVV    3   3   4
0037    TSETS    3   2   4  ; "w"
0038    JMP      3 => 0045
0039 => TGETS    3   1   2  ; "x"
0040    TGETS    4   1   4  ; "w"
0041    ADDVV    3   3   4
0042    TGETS    4   2   2  ; "x"
0043    SUBVV    3   3   4
0044    TSETS    3   2   4  ; "w"
0045 => TGETS    3   0   3  ; "y"
0046    TGETS    4   0   5  ; "h"
0047    ADDVV    3   3   4
0048    TGETS    4   1   3  ; "y"
0049    TGETS    5   1   5  ; "h"
0050    ADDVV    4   4   5
0051    ISGE     4   3
0052    JMP      3 => 0060
0053    TGETS    3   0   3  ; "y"
0054    TGETS    4   0   5  ; "h"
0055    ADDVV    3   3   4
0056    TGETS    4   2   3  ; "y"
0057    SUBVV    3   3   4
0058    TSETS    3   2   5  ; "h"
0059    JMP      3 => 0066
0060 => TGETS    3   1   3  ; "y"
0061    TGETS    4   1   5  ; "h"
0062    ADDVV    3   3   4
0063    TGETS    4   2   3  ; "y"
0064    SUBVV    3   3   4
0065    TSETS    3   2   5  ; "h"
0066 => RET1     2   2

-- BYTECODE -- geometry.lua:170-190
0001    MOV      3   0
0002    TGETS    2   0   0  ; "copy"
0003    CALL     2   2   2
0004    TGETS    3   0   1  ; "x"
0005    TGETS    4   1   1  ; "x"
0006    ISGE     3   4
0007    JMP      3 => 0010
0008    TGETS    3   1   1  ; "x"
0009    TSETS    3   2   1  ; "x"
0010 => TGETS    3   0   2  ; "y"
0011    TGETS    4   1   2  ; "y"
0012    ISGE     3   4
0013    JMP      3 => 0016
0014    TGETS    3   1   2  ; "y"
0015    TSETS    3   2   2  ; "y"
0016 => TGETS    3   0   1  ; "x"
0017    TGETS    4   0   3  ; "w"
0018    ADDVV    3   3   4
0019    TGETS    4   1   1  ; "x"
0020    TGETS    5   1   3  ; "w"
0021    ADDVV    4   4   5
0022    ISGE     3   4
0023    JMP      3 => 0031
0024    TGETS    3   0   1  ; "x"
0025    TGETS    4   0   3  ; "w"
0026    ADDVV    3   3   4
0027    TGETS    4   2   1  ; "x"
0028    SUBVV    3   3   4
0029    TSETS    3   2   3  ; "w"
0030    JMP      3 => 0037
0031 => TGETS    3   1   1  ; "x"
0032    TGETS    4   1   3  ; "w"
0033    ADDVV    3   3   4
0034    TGETS    4   2   1  ; "x"
0035    SUBVV    3   3   4
0036    TSETS    3   2   3  ; "w"
0037 => TGETS    3   0   2  ; "y"
0038    TGETS    4   0   4  ; "h"
0039    ADDVV    3   3   4
0040    TGETS    4   1   2  ; "y"
0041    TGETS    5   1   4  ; "h"
0042    ADDVV    4   4   5
0043    ISGE     3   4
0044    JMP      3 => 0052
0045    TGETS    3   0   2  ; "y"
0046    TGETS    4   0   4  ; "h"
0047    ADDVV    3   3   4
0048    TGETS    4   2   2  ; "y"
0049    SUBVV    3   3   4
0050    TSETS    3   2   4  ; "h"
0051    JMP      3 => 0058
0052 => TGETS    3   1   2  ; "y"
0053    TGETS    4   1   4  ; "h"
0054    ADDVV    3   3   4
0055    TGETS    4   2   2  ; "y"
0056    SUBVV    3   3   4
0057    TSETS    3   2   4  ; "h"
0058 => RET1     2   2

-- BYTECODE -- geometry.lua:197-205
0001    TGETS    2   0   0  ; "x"
0002    TGETS    3   1   0  ; "x"
0003    TGETS    4   1   1  ; "w"
0004    ADDVV    3   3   4
0005    ISLE     3   2
0006    JMP      2 => 0025
0007    TGETS    2   0   2  ; "y"
0008    TGETS    3   1   2  ; "y"
0009    TGETS    4   1   3  ; "h"
0010    ADDVV    3   3   4
0011    ISLE     3   2
0012    JMP      2 => 0025
0013    TGETS    2   1   0  ; "x"
0014    TGETS    3   0   0  ; "x"
0015    TGETS    4   0   1  ; "w"
0016    ADDVV    3   3   4
0017    ISLE     3   2
0018    JMP      2 => 0025
0019    TGETS    2   1   2  ; "y"
0020    TGETS    3   0   2  ; "y"
0021    TGETS    4   0   3  ; "h"
0022    ADDVV    3   3   4
0023    ISGT     3   2
0024    JMP      2 => 0027
0025 => KPRI     2   2
0026    RET1     2   2
0027 => KPRI     2   1
0028    RET1     2   2

-- BYTECODE -- geometry.lua:212-214
0001    MOV      3   0
0002    TGETS    2   0   0  ; "notIntersectWith"
0003    MOV      4   1
0004    CALL     2   2   3
0005    NOT      2   2
0006    RET1     2   2

-- BYTECODE -- geometry.lua:221-225
0001    TGETS    2   1   0  ; "w"
0002    TSETS    2   0   0  ; "w"
0003    TGETS    2   1   1  ; "h"
0004    TSETS    2   0   1  ; "h"
0005    RET1     0   2

-- BYTECODE -- geometry.lua:234-243
0001    TGETS    2   0   0  ; "x"
0002    TGETS    3   1   0  ; "x"
0003    ISGT     2   3
0004    JMP      2 => 0027
0005    TGETS    2   0   1  ; "y"
0006    TGETS    3   1   1  ; "y"
0007    ISGT     2   3
0008    JMP      2 => 0027
0009    TGETS    2   0   0  ; "x"
0010    TGETS    3   0   2  ; "w"
0011    ADDVV    2   2   3
0012    TGETS    3   1   0  ; "x"
0013    TGETS    4   1   2  ; "w"
0014    ADDVV    3   3   4
0015    ISGT     3   2
0016    JMP      2 => 0027
0017    TGETS    2   0   1  ; "y"
0018    TGETS    3   0   3  ; "h"
0019    ADDVV    2   2   3
0020    TGETS    3   1   1  ; "y"
0021    TGETS    4   1   3  ; "h"
0022    ADDVV    3   3   4
0023    ISGT     3   2
0024    JMP      2 => 0027
0025    KPRI     2   2
0026    RET1     2   2
0027 => KPRI     2   1
0028    RET1     2   2

-- BYTECODE -- geometry.lua:252-260
0001    TGETS    2   0   0  ; "x"
0002    TGETS    3   1   0  ; "x"
0003    ISNEV    2   3
0004    JMP      2 => 0017
0005    TGETS    2   0   1  ; "y"
0006    TGETS    3   1   1  ; "y"
0007    ISNEV    2   3
0008    JMP      2 => 0017
0009    MOV      3   0
0010    TGETS    2   0   2  ; "equalSize"
0011    MOV      4   1
0012    CALL     2   2   3
0013    ISF          2
0014    JMP      3 => 0017
0015    KPRI     2   2
0016    RET1     2   2
0017 => KPRI     2   1
0018    RET1     2   2

-- BYTECODE -- geometry.lua:267-272
0001    TGETS    2   0   0  ; "w"
0002    TGETS    3   1   0  ; "w"
0003    ISNEV    2   3
0004    JMP      2 => 0011
0005    TGETS    2   0   1  ; "h"
0006    TGETS    3   1   1  ; "h"
0007    ISNEV    2   3
0008    JMP      2 => 0011
0009    KPRI     2   2
0010    RET1     2   2
0011 => KPRI     2   1
0012    RET1     2   2

-- BYTECODE -- geometry.lua:279-284
0001    TGETS    2   0   0  ; "w"
0002    TGETS    3   1   0  ; "w"
0003    ISGE     2   3
0004    JMP      2 => 0011
0005    TGETS    2   0   1  ; "h"
0006    TGETS    3   1   1  ; "h"
0007    ISGE     2   3
0008    JMP      2 => 0011
0009    KPRI     2   2
0010    RET1     2   2
0011 => KPRI     2   1
0012    RET1     2   2

-- BYTECODE -- geometry.lua:290-295
0001    TGETS    2   0   0  ; "w"
0002    TGETS    3   1   0  ; "w"
0003    ISGT     2   3
0004    JMP      2 => 0011
0005    TGETS    2   0   1  ; "h"
0006    TGETS    3   1   1  ; "h"
0007    ISGT     2   3
0008    JMP      2 => 0011
0009    KPRI     2   2
0010    RET1     2   2
0011 => KPRI     2   1
0012    RET1     2   2

-- BYTECODE -- geometry.lua:308-332
0001    TGETS    4   0   0  ; "w"
0002    TGETS    5   1   0  ; "w"
0003    ISGE     5   4
0004    JMP      4 => 0007
0005    TGETS    4   1   0  ; "w"
0006    TSETS    4   0   0  ; "w"
0007 => TGETS    4   0   1  ; "h"
0008    TGETS    5   1   1  ; "h"
0009    ISGE     5   4
0010    JMP      4 => 0013
0011    TGETS    4   1   1  ; "h"
0012    TSETS    4   0   1  ; "h"
0013 => TGETS    4   0   2  ; "x"
0014    ADDVV    4   4   2
0015    TSETS    4   0   2  ; "x"
0016    TGETS    4   0   3  ; "y"
0017    ADDVV    4   4   3
0018    TSETS    4   0   3  ; "y"
0019    TGETS    4   0   2  ; "x"
0020    TGETS    5   1   2  ; "x"
0021    ISGE     4   5
0022    JMP      4 => 0025
0023    TGETS    4   1   2  ; "x"
0024    TSETS    4   0   2  ; "x"
0025 => TGETS    4   0   3  ; "y"
0026    TGETS    5   1   3  ; "y"
0027    ISGE     4   5
0028    JMP      4 => 0031
0029    TGETS    4   1   3  ; "y"
0030    TSETS    4   0   3  ; "y"
0031 => TGETS    4   0   2  ; "x"
0032    TGETS    5   0   0  ; "w"
0033    ADDVV    4   4   5
0034    TGETS    5   1   2  ; "x"
0035    TGETS    6   1   0  ; "w"
0036    ADDVV    5   5   6
0037    ISGE     5   4
0038    JMP      4 => 0045
0039    TGETS    4   1   2  ; "x"
0040    TGETS    5   1   0  ; "w"
0041    ADDVV    4   4   5
0042    TGETS    5   0   0  ; "w"
0043    SUBVV    4   4   5
0044    TSETS    4   0   2  ; "x"
0045 => TGETS    4   0   3  ; "y"
0046    TGETS    5   0   1  ; "h"
0047    ADDVV    4   4   5
0048    TGETS    5   1   3  ; "y"
0049    TGETS    6   1   1  ; "h"
0050    ADDVV    5   5   6
0051    ISGE     5   4
0052    JMP      4 => 0059
0053    TGETS    4   1   3  ; "y"
0054    TGETS    5   1   1  ; "h"
0055    ADDVV    4   4   5
0056    TGETS    5   0   1  ; "h"
0057    SUBVV    4   4   5
0058    TSETS    4   0   3  ; "y"
0059 => RET0     0   1

-- BYTECODE -- geometry.lua:341-365
0001    TGETS    4   0   0  ; "w"
0002    TGETS    5   1   0  ; "w"
0003    ISGE     5   4
0004    JMP      4 => 0007
0005    TGETS    4   1   0  ; "w"
0006    TSETS    4   0   0  ; "w"
0007 => TGETS    4   0   1  ; "h"
0008    TGETS    5   1   1  ; "h"
0009    ISGE     5   4
0010    JMP      4 => 0013
0011    TGETS    4   1   1  ; "h"
0012    TSETS    4   0   1  ; "h"
0013 => TGETS    4   0   0  ; "w"
0014    DIVVN    4   4   0  ; 2
0015    SUBVV    4   2   4
0016    TSETS    4   0   2  ; "x"
0017    TGETS    4   0   1  ; "h"
0018    DIVVN    4   4   0  ; 2
0019    SUBVV    4   3   4
0020    TSETS    4   0   3  ; "y"
0021    TGETS    4   0   2  ; "x"
0022    TGETS    5   1   2  ; "x"
0023    ISGE     4   5
0024    JMP      4 => 0027
0025    TGETS    4   1   2  ; "x"
0026    TSETS    4   0   2  ; "x"
0027 => TGETS    4   0   3  ; "y"
0028    TGETS    5   1   3  ; "y"
0029    ISGE     4   5
0030    JMP      4 => 0033
0031    TGETS    4   1   3  ; "y"
0032    TSETS    4   0   3  ; "y"
0033 => TGETS    4   0   2  ; "x"
0034    TGETS    5   0   0  ; "w"
0035    ADDVV    4   4   5
0036    TGETS    5   1   2  ; "x"
0037    TGETS    6   1   0  ; "w"
0038    ADDVV    5   5   6
0039    ISGE     5   4
0040    JMP      4 => 0047
0041    TGETS    4   1   2  ; "x"
0042    TGETS    5   1   0  ; "w"
0043    ADDVV    4   4   5
0044    TGETS    5   0   0  ; "w"
0045    SUBVV    4   4   5
0046    TSETS    4   0   2  ; "x"
0047 => TGETS    4   0   3  ; "y"
0048    TGETS    5   0   1  ; "h"
0049    ADDVV    4   4   5
0050    TGETS    5   1   3  ; "y"
0051    TGETS    6   1   1  ; "h"
0052    ADDVV    5   5   6
0053    ISGE     5   4
0054    JMP      4 => 0061
0055    TGETS    4   1   3  ; "y"
0056    TGETS    5   1   1  ; "h"
0057    ADDVV    4   4   5
0058    TGETS    5   0   1  ; "h"
0059    SUBVV    4   4   5
0060    TSETS    4   0   3  ; "y"
0061 => RET0     0   1

-- BYTECODE -- geometry.lua:367-370
0001    MOV      5   0
0002    TGETS    4   0   0  ; "offsetBy"
0003    MOV      6   2
0004    MOV      7   3
0005    CALL     4   1   4
0006    MOV      5   0
0007    TGETS    4   0   1  ; "intersect"
0008    MOV      6   1
0009    CALLT    4   3

-- BYTECODE -- geometry.lua:377-379
0001    GGET     2   0      ; "math"
0002    TGETS    2   2   1  ; "sqrt"
0003    GGET     3   0      ; "math"
0004    TGETS    3   3   2  ; "pow"
0005    TGETS    4   0   3  ; "x"
0006    TGETS    5   1   3  ; "x"
0007    SUBVV    4   4   5
0008    KSHORT   5   2
0009    CALL     3   2   3
0010    GGET     4   0      ; "math"
0011    TGETS    4   4   2  ; "pow"
0012    TGETS    5   0   4  ; "y"
0013    TGETS    6   1   4  ; "y"
0014    SUBVV    5   5   6
0015    KSHORT   6   2
0016    CALL     4   2   3
0017    ADDVV    3   3   4
0018    CALLT    2   2

-- BYTECODE -- geometry.lua:387-393
0001    UGET     2   0      ; Geom
0002    MOV      3   2
0003    TGETS    2   2   0  ; "new"
0004    TDUP     4   3
0005    UGET     5   1      ; Math
0006    TGETS    5   5   1  ; "round"
0007    TGETS    6   0   2  ; "x"
0008    TGETS    7   1   2  ; "x"
0009    ADDVV    6   6   7
0010    DIVVN    6   6   0  ; 2
0011    CALL     5   2   2
0012    TSETS    5   4   2  ; "x"
0013    UGET     5   1      ; Math
0014    TGETS    5   5   1  ; "round"
0015    TGETS    6   0   4  ; "y"
0016    TGETS    7   1   4  ; "y"
0017    ADDVV    6   6   7
0018    DIVVN    6   6   0  ; 2
0019    CALL     5   2   2
0020    TSETS    5   4   4  ; "y"
0021    CALLT    2   3

-- BYTECODE -- geometry.lua:399-405
0001    UGET     1   0      ; Geom
0002    MOV      2   1
0003    TGETS    1   1   0  ; "new"
0004    TDUP     3   4
0005    TGETS    4   0   1  ; "x"
0006    UGET     5   1      ; Math
0007    TGETS    5   5   2  ; "round"
0008    TGETS    6   0   3  ; "w"
0009    DIVVN    6   6   0  ; 2
0010    CALL     5   2   2
0011    ADDVV    4   4   5
0012    TSETS    4   3   1  ; "x"
0013    TGETS    4   0   5  ; "y"
0014    UGET     5   1      ; Math
0015    TGETS    5   5   2  ; "round"
0016    TGETS    6   0   6  ; "h"
0017    DIVVN    6   6   0  ; 2
0018    CALL     5   2   2
0019    ADDVV    4   4   5
0020    TSETS    4   3   5  ; "y"
0021    CALLT    1   3

-- BYTECODE -- geometry.lua:0-408
0001    GGET     0   0      ; "require"
0002    KSTR     1   1      ; "optmath"
0003    CALL     0   2   2
0004    TDUP     1   2
0005    FNEW     2   4      ; geometry.lua:34
0006    TSETS    2   1   3  ; "new"
0007    FNEW     2   6      ; geometry.lua:45
0008    TSETS    2   1   5  ; "copy"
0009    FNEW     2   8      ; geometry.lua:54
0010    TSETS    2   1   7  ; "__tostring"
0011    FNEW     2  10      ; geometry.lua:63
0012    TSETS    2   1   9  ; "offsetBy"
0013    FNEW     2  12      ; geometry.lua:74
0014    TSETS    2   1  11  ; "offsetTo"
0015    FNEW     2  14      ; geometry.lua:88
0016    TSETS    2   1  13  ; "scaleBy"
0017    FNEW     2  16      ; geometry.lua:100
0018    TSETS    2   1  15  ; "transformByScale"
0019    FNEW     2  18      ; geometry.lua:111
0020    TSETS    2   1  17  ; "area"
0021    FNEW     2  20      ; geometry.lua:127
0022    TSETS    2   1  19  ; "changeSizeBy"
0023    FNEW     2  22      ; geometry.lua:141
0024    TSETS    2   1  21  ; "combine"
0025    FNEW     2  24      ; geometry.lua:170
0026    TSETS    2   1  23  ; "intersect"
0027    FNEW     2  26      ; geometry.lua:197
0028    TSETS    2   1  25  ; "notIntersectWith"
0029    FNEW     2  28      ; geometry.lua:212
0030    TSETS    2   1  27  ; "intersectWith"
0031    FNEW     2  30      ; geometry.lua:221
0032    TSETS    2   1  29  ; "setSizeTo"
0033    FNEW     2  32      ; geometry.lua:234
0034    TSETS    2   1  31  ; "contains"
0035    FNEW     2  34      ; geometry.lua:252
0036    TSETS    2   1  33  ; "__eq"
0037    FNEW     2  36      ; geometry.lua:267
0038    TSETS    2   1  35  ; "equalSize"
0039    FNEW     2  38      ; geometry.lua:279
0040    TSETS    2   1  37  ; "__lt"
0041    FNEW     2  40      ; geometry.lua:290
0042    TSETS    2   1  39  ; "__le"
0043    FNEW     2  42      ; geometry.lua:308
0044    TSETS    2   1  41  ; "offsetWithin"
0045    FNEW     2  44      ; geometry.lua:341
0046    TSETS    2   1  43  ; "centerWithin"
0047    FNEW     2  46      ; geometry.lua:367
0048    TSETS    2   1  45  ; "shrinkInside"
0049    FNEW     2  48      ; geometry.lua:377
0050    TSETS    2   1  47  ; "distance"
0051    FNEW     2  50      ; geometry.lua:387
0052    TSETS    2   1  49  ; "midpoint"
0053    FNEW     2  52      ; geometry.lua:399
0054    TSETS    2   1  51  ; "center"
0055    UCLO     0 => 0056
0056 => RET1     1   2

