
main <./spec/unit/gesturedetector_spec.lua:0,0> (5 instructions, 20 bytes at 0x7fe459c068d0)
0+ params, 3 slots, 0 upvalues, 0 locals, 2 constants, 1 function
	1	[1]	GETGLOBAL	0 -1	; describe
	2	[1]	LOADK    	1 -2	; "gesturedetector module"
	3	[50]	CLOSURE  	2 0	; 0x7fe459c06b70
	4	[1]	CALL     	0 3 1
	5	[50]	RETURN   	0 1

function <./spec/unit/gesturedetector_spec.lua:1,50> (10 instructions, 40 bytes at 0x7fe459c06b70)
0 params, 4 slots, 0 upvalues, 1 local, 3 constants, 2 functions
	1	[3]	GETGLOBAL	1 -1	; setup
	2	[6]	CLOSURE  	2 0	; 0x7fe459c06da0
	3	[6]	MOVE     	0 0
	4	[3]	CALL     	1 2 1
	5	[8]	GETGLOBAL	1 -2	; describe
	6	[8]	LOADK    	2 -3	; "adjustGesCoordinate"
	7	[49]	CLOSURE  	3 1	; 0x7fe459c06c80
	8	[49]	MOVE     	0 0
	9	[8]	CALL     	1 3 1
	10	[50]	RETURN   	0 1

function <./spec/unit/gesturedetector_spec.lua:3,6> (8 instructions, 32 bytes at 0x7fe459c06da0)
0 params, 2 slots, 1 upvalue, 0 locals, 3 constants, 0 functions
	1	[4]	GETGLOBAL	0 -1	; require
	2	[4]	LOADK    	1 -2	; "commonrequire"
	3	[4]	CALL     	0 2 1
	4	[5]	GETGLOBAL	0 -1	; require
	5	[5]	LOADK    	1 -3	; "device/gesturedetector"
	6	[5]	CALL     	0 2 2
	7	[5]	SETUPVAL 	0 0	; GestureDetector
	8	[6]	RETURN   	0 1

function <./spec/unit/gesturedetector_spec.lua:8,49> (23 instructions, 92 bytes at 0x7fe459c06c80)
0 params, 4 slots, 1 upvalue, 1 local, 5 constants, 5 functions
	1	[19]	CLOSURE  	0 0	; 0x7fe459c073e0
	2	[19]	GETUPVAL 	0 0	; GestureDetector
	3	[21]	GETGLOBAL	1 -1	; it
	4	[21]	LOADK    	2 -2	; "should not translate rotation 0"
	5	[27]	CLOSURE  	3 1	; 0x7fe459c07c70
	6	[27]	MOVE     	0 0
	7	[21]	CALL     	1 3 1
	8	[28]	GETGLOBAL	1 -1	; it
	9	[28]	LOADK    	2 -3	; "should translate rotation 90"
	10	[34]	CLOSURE  	3 2	; 0x7fe459c08260
	11	[34]	MOVE     	0 0
	12	[28]	CALL     	1 3 1
	13	[35]	GETGLOBAL	1 -1	; it
	14	[35]	LOADK    	2 -4	; "should translate rotation 180"
	15	[41]	CLOSURE  	3 3	; 0x7fe459c084c0
	16	[41]	MOVE     	0 0
	17	[35]	CALL     	1 3 1
	18	[42]	GETGLOBAL	1 -1	; it
	19	[42]	LOADK    	2 -5	; "should translate rotation 270"
	20	[48]	CLOSURE  	3 4	; 0x7fe459c09180
	21	[48]	MOVE     	0 0
	22	[42]	CALL     	1 3 1
	23	[49]	RETURN   	0 1

function <./spec/unit/gesturedetector_spec.lua:9,19> (17 instructions, 68 bytes at 0x7fe459c073e0)
3 params, 7 slots, 1 upvalue, 4 locals, 6 constants, 0 functions
	1	[10]	NEWTABLE 	3 0 3
	2	[11]	SETTABLE 	3 -1 0	; "ges" -
	3	[12]	SETTABLE 	3 -2 1	; "direction" -
	4	[13]	SETTABLE 	3 -3 1	; "multiswipe_directions" -
	5	[15]	GETUPVAL 	4 0	; GestureDetector
	6	[15]	NEWTABLE 	5 0 0
	7	[15]	SETTABLE 	4 -4 5	; "screen" -
	8	[16]	GETUPVAL 	4 0	; GestureDetector
	9	[16]	GETTABLE 	4 4 -4	; "screen"
	10	[16]	SETTABLE 	4 -5 2	; "cur_rotation_mode" -
	11	[18]	GETUPVAL 	4 0	; GestureDetector
	12	[18]	SELF     	4 4 -6	; "adjustGesCoordinate"
	13	[18]	MOVE     	6 3
	14	[18]	CALL     	4 3 2
	15	[18]	GETTABLE 	4 4 -2	; "direction"
	16	[18]	RETURN   	4 2
	17	[19]	RETURN   	0 1

function <./spec/unit/gesturedetector_spec.lua:21,27> (51 instructions, 204 bytes at 0x7fe459c07c70)
0 params, 6 slots, 1 upvalue, 0 locals, 10 constants, 0 functions
	1	[22]	GETGLOBAL	0 -1	; assert
	2	[22]	GETTABLE 	0 0 -2	; "are"
	3	[22]	GETTABLE 	0 0 -3	; "equal"
	4	[22]	LOADK    	1 -4	; "north"
	5	[22]	GETUPVAL 	2 0	; adjustTest
	6	[22]	LOADK    	3 -5	; "swipe"
	7	[22]	LOADK    	4 -4	; "north"
	8	[22]	LOADK    	5 -6	; 0
	9	[22]	CALL     	2 4 0
	10	[22]	CALL     	0 0 1
	11	[23]	GETGLOBAL	0 -1	; assert
	12	[23]	GETTABLE 	0 0 -2	; "are"
	13	[23]	GETTABLE 	0 0 -3	; "equal"
	14	[23]	LOADK    	1 -4	; "north"
	15	[23]	GETUPVAL 	2 0	; adjustTest
	16	[23]	LOADK    	3 -7	; "multiswipe"
	17	[23]	LOADK    	4 -4	; "north"
	18	[23]	LOADK    	5 -6	; 0
	19	[23]	CALL     	2 4 0
	20	[23]	CALL     	0 0 1
	21	[24]	GETGLOBAL	0 -1	; assert
	22	[24]	GETTABLE 	0 0 -2	; "are"
	23	[24]	GETTABLE 	0 0 -3	; "equal"
	24	[24]	LOADK    	1 -4	; "north"
	25	[24]	GETUPVAL 	2 0	; adjustTest
	26	[24]	LOADK    	3 -8	; "pan"
	27	[24]	LOADK    	4 -4	; "north"
	28	[24]	LOADK    	5 -6	; 0
	29	[24]	CALL     	2 4 0
	30	[24]	CALL     	0 0 1
	31	[25]	GETGLOBAL	0 -1	; assert
	32	[25]	GETTABLE 	0 0 -2	; "are"
	33	[25]	GETTABLE 	0 0 -3	; "equal"
	34	[25]	LOADK    	1 -4	; "north"
	35	[25]	GETUPVAL 	2 0	; adjustTest
	36	[25]	LOADK    	3 -9	; "two_finger_swipe"
	37	[25]	LOADK    	4 -4	; "north"
	38	[25]	LOADK    	5 -6	; 0
	39	[25]	CALL     	2 4 0
	40	[25]	CALL     	0 0 1
	41	[26]	GETGLOBAL	0 -1	; assert
	42	[26]	GETTABLE 	0 0 -2	; "are"
	43	[26]	GETTABLE 	0 0 -3	; "equal"
	44	[26]	LOADK    	1 -4	; "north"
	45	[26]	GETUPVAL 	2 0	; adjustTest
	46	[26]	LOADK    	3 -10	; "two_finger_pan"
	47	[26]	LOADK    	4 -4	; "north"
	48	[26]	LOADK    	5 -6	; 0
	49	[26]	CALL     	2 4 0
	50	[26]	CALL     	0 0 1
	51	[27]	RETURN   	0 1

function <./spec/unit/gesturedetector_spec.lua:28,34> (51 instructions, 204 bytes at 0x7fe459c08260)
0 params, 6 slots, 1 upvalue, 0 locals, 11 constants, 0 functions
	1	[29]	GETGLOBAL	0 -1	; assert
	2	[29]	GETTABLE 	0 0 -2	; "are"
	3	[29]	GETTABLE 	0 0 -3	; "equal"
	4	[29]	LOADK    	1 -4	; "west"
	5	[29]	GETUPVAL 	2 0	; adjustTest
	6	[29]	LOADK    	3 -5	; "swipe"
	7	[29]	LOADK    	4 -6	; "north"
	8	[29]	LOADK    	5 -7	; 3
	9	[29]	CALL     	2 4 0
	10	[29]	CALL     	0 0 1
	11	[30]	GETGLOBAL	0 -1	; assert
	12	[30]	GETTABLE 	0 0 -2	; "are"
	13	[30]	GETTABLE 	0 0 -3	; "equal"
	14	[30]	LOADK    	1 -4	; "west"
	15	[30]	GETUPVAL 	2 0	; adjustTest
	16	[30]	LOADK    	3 -8	; "multiswipe"
	17	[30]	LOADK    	4 -6	; "north"
	18	[30]	LOADK    	5 -7	; 3
	19	[30]	CALL     	2 4 0
	20	[30]	CALL     	0 0 1
	21	[31]	GETGLOBAL	0 -1	; assert
	22	[31]	GETTABLE 	0 0 -2	; "are"
	23	[31]	GETTABLE 	0 0 -3	; "equal"
	24	[31]	LOADK    	1 -4	; "west"
	25	[31]	GETUPVAL 	2 0	; adjustTest
	26	[31]	LOADK    	3 -9	; "pan"
	27	[31]	LOADK    	4 -6	; "north"
	28	[31]	LOADK    	5 -7	; 3
	29	[31]	CALL     	2 4 0
	30	[31]	CALL     	0 0 1
	31	[32]	GETGLOBAL	0 -1	; assert
	32	[32]	GETTABLE 	0 0 -2	; "are"
	33	[32]	GETTABLE 	0 0 -3	; "equal"
	34	[32]	LOADK    	1 -4	; "west"
	35	[32]	GETUPVAL 	2 0	; adjustTest
	36	[32]	LOADK    	3 -10	; "two_finger_swipe"
	37	[32]	LOADK    	4 -6	; "north"
	38	[32]	LOADK    	5 -7	; 3
	39	[32]	CALL     	2 4 0
	40	[32]	CALL     	0 0 1
	41	[33]	GETGLOBAL	0 -1	; assert
	42	[33]	GETTABLE 	0 0 -2	; "are"
	43	[33]	GETTABLE 	0 0 -3	; "equal"
	44	[33]	LOADK    	1 -4	; "west"
	45	[33]	GETUPVAL 	2 0	; adjustTest
	46	[33]	LOADK    	3 -11	; "two_finger_pan"
	47	[33]	LOADK    	4 -6	; "north"
	48	[33]	LOADK    	5 -7	; 3
	49	[33]	CALL     	2 4 0
	50	[33]	CALL     	0 0 1
	51	[34]	RETURN   	0 1

function <./spec/unit/gesturedetector_spec.lua:35,41> (51 instructions, 204 bytes at 0x7fe459c084c0)
0 params, 6 slots, 1 upvalue, 0 locals, 11 constants, 0 functions
	1	[36]	GETGLOBAL	0 -1	; assert
	2	[36]	GETTABLE 	0 0 -2	; "are"
	3	[36]	GETTABLE 	0 0 -3	; "equal"
	4	[36]	LOADK    	1 -4	; "south"
	5	[36]	GETUPVAL 	2 0	; adjustTest
	6	[36]	LOADK    	3 -5	; "swipe"
	7	[36]	LOADK    	4 -6	; "north"
	8	[36]	LOADK    	5 -7	; 2
	9	[36]	CALL     	2 4 0
	10	[36]	CALL     	0 0 1
	11	[37]	GETGLOBAL	0 -1	; assert
	12	[37]	GETTABLE 	0 0 -2	; "are"
	13	[37]	GETTABLE 	0 0 -3	; "equal"
	14	[37]	LOADK    	1 -4	; "south"
	15	[37]	GETUPVAL 	2 0	; adjustTest
	16	[37]	LOADK    	3 -8	; "multiswipe"
	17	[37]	LOADK    	4 -6	; "north"
	18	[37]	LOADK    	5 -7	; 2
	19	[37]	CALL     	2 4 0
	20	[37]	CALL     	0 0 1
	21	[38]	GETGLOBAL	0 -1	; assert
	22	[38]	GETTABLE 	0 0 -2	; "are"
	23	[38]	GETTABLE 	0 0 -3	; "equal"
	24	[38]	LOADK    	1 -4	; "south"
	25	[38]	GETUPVAL 	2 0	; adjustTest
	26	[38]	LOADK    	3 -9	; "pan"
	27	[38]	LOADK    	4 -6	; "north"
	28	[38]	LOADK    	5 -7	; 2
	29	[38]	CALL     	2 4 0
	30	[38]	CALL     	0 0 1
	31	[39]	GETGLOBAL	0 -1	; assert
	32	[39]	GETTABLE 	0 0 -2	; "are"
	33	[39]	GETTABLE 	0 0 -3	; "equal"
	34	[39]	LOADK    	1 -4	; "south"
	35	[39]	GETUPVAL 	2 0	; adjustTest
	36	[39]	LOADK    	3 -10	; "two_finger_swipe"
	37	[39]	LOADK    	4 -6	; "north"
	38	[39]	LOADK    	5 -7	; 2
	39	[39]	CALL     	2 4 0
	40	[39]	CALL     	0 0 1
	41	[40]	GETGLOBAL	0 -1	; assert
	42	[40]	GETTABLE 	0 0 -2	; "are"
	43	[40]	GETTABLE 	0 0 -3	; "equal"
	44	[40]	LOADK    	1 -4	; "south"
	45	[40]	GETUPVAL 	2 0	; adjustTest
	46	[40]	LOADK    	3 -11	; "two_finger_pan"
	47	[40]	LOADK    	4 -6	; "north"
	48	[40]	LOADK    	5 -7	; 2
	49	[40]	CALL     	2 4 0
	50	[40]	CALL     	0 0 1
	51	[41]	RETURN   	0 1

function <./spec/unit/gesturedetector_spec.lua:42,48> (51 instructions, 204 bytes at 0x7fe459c09180)
0 params, 6 slots, 1 upvalue, 0 locals, 11 constants, 0 functions
	1	[43]	GETGLOBAL	0 -1	; assert
	2	[43]	GETTABLE 	0 0 -2	; "are"
	3	[43]	GETTABLE 	0 0 -3	; "equal"
	4	[43]	LOADK    	1 -4	; "east"
	5	[43]	GETUPVAL 	2 0	; adjustTest
	6	[43]	LOADK    	3 -5	; "swipe"
	7	[43]	LOADK    	4 -6	; "north"
	8	[43]	LOADK    	5 -7	; 1
	9	[43]	CALL     	2 4 0
	10	[43]	CALL     	0 0 1
	11	[44]	GETGLOBAL	0 -1	; assert
	12	[44]	GETTABLE 	0 0 -2	; "are"
	13	[44]	GETTABLE 	0 0 -3	; "equal"
	14	[44]	LOADK    	1 -4	; "east"
	15	[44]	GETUPVAL 	2 0	; adjustTest
	16	[44]	LOADK    	3 -8	; "multiswipe"
	17	[44]	LOADK    	4 -6	; "north"
	18	[44]	LOADK    	5 -7	; 1
	19	[44]	CALL     	2 4 0
	20	[44]	CALL     	0 0 1
	21	[45]	GETGLOBAL	0 -1	; assert
	22	[45]	GETTABLE 	0 0 -2	; "are"
	23	[45]	GETTABLE 	0 0 -3	; "equal"
	24	[45]	LOADK    	1 -4	; "east"
	25	[45]	GETUPVAL 	2 0	; adjustTest
	26	[45]	LOADK    	3 -9	; "pan"
	27	[45]	LOADK    	4 -6	; "north"
	28	[45]	LOADK    	5 -7	; 1
	29	[45]	CALL     	2 4 0
	30	[45]	CALL     	0 0 1
	31	[46]	GETGLOBAL	0 -1	; assert
	32	[46]	GETTABLE 	0 0 -2	; "are"
	33	[46]	GETTABLE 	0 0 -3	; "equal"
	34	[46]	LOADK    	1 -4	; "east"
	35	[46]	GETUPVAL 	2 0	; adjustTest
	36	[46]	LOADK    	3 -10	; "two_finger_swipe"
	37	[46]	LOADK    	4 -6	; "north"
	38	[46]	LOADK    	5 -7	; 1
	39	[46]	CALL     	2 4 0
	40	[46]	CALL     	0 0 1
	41	[47]	GETGLOBAL	0 -1	; assert
	42	[47]	GETTABLE 	0 0 -2	; "are"
	43	[47]	GETTABLE 	0 0 -3	; "equal"
	44	[47]	LOADK    	1 -4	; "east"
	45	[47]	GETUPVAL 	2 0	; adjustTest
	46	[47]	LOADK    	3 -11	; "two_finger_pan"
	47	[47]	LOADK    	4 -6	; "north"
	48	[47]	LOADK    	5 -7	; 1
	49	[47]	CALL     	2 4 0
	50	[47]	CALL     	0 0 1
	51	[48]	RETURN   	0 1
