-- BYTECODE -- gesturedetector_spec.lua:3-6
0001    GGET     0   0      ; "require"
0002    KSTR     1   1      ; "commonrequire"
0003    CALL     0   1   2
0004    GGET     0   0      ; "require"
0005    KSTR     1   2      ; "device/gesturedetector"
0006    CALL     0   2   2
0007    USETV    0   0      ; GestureDetector
0008    RET0     0   1

-- BYTECODE -- gesturedetector_spec.lua:9-19
0001    TDUP     3   0
0002    TSETS    0   3   1  ; "ges"
0003    TSETS    1   3   2  ; "direction"
0004    TSETS    1   3   3  ; "multiswipe_directions"
0005    UGET     4   0      ; GestureDetector
0006    TNEW     5   0
0007    TSETS    5   4   4  ; "screen"
0008    UGET     4   0      ; GestureDetector
0009    TGETS    4   4   4  ; "screen"
0010    TSETS    2   4   5  ; "cur_rotation_mode"
0011    UGET     4   0      ; GestureDetector
0012    MOV      5   4
0013    TGETS    4   4   6  ; "adjustGesCoordinate"
0014    MOV      6   3
0015    CALL     4   2   3
0016    TGETS    4   4   2  ; "direction"
0017    RET1     4   2

-- BYTECODE -- gesturedetector_spec.lua:21-27
0001    GGET     0   0      ; "assert"
0002    TGETS    0   0   1  ; "are"
0003    TGETS    0   0   2  ; "equal"
0004    KSTR     1   3      ; "north"
0005    UGET     2   0      ; adjustTest
0006    KSTR     3   4      ; "swipe"
0007    KSTR     4   3      ; "north"
0008    KSHORT   5   0
0009    CALL     2   0   4
0010    CALLM    0   1   1
0011    GGET     0   0      ; "assert"
0012    TGETS    0   0   1  ; "are"
0013    TGETS    0   0   2  ; "equal"
0014    KSTR     1   3      ; "north"
0015    UGET     2   0      ; adjustTest
0016    KSTR     3   5      ; "multiswipe"
0017    KSTR     4   3      ; "north"
0018    KSHORT   5   0
0019    CALL     2   0   4
0020    CALLM    0   1   1
0021    GGET     0   0      ; "assert"
0022    TGETS    0   0   1  ; "are"
0023    TGETS    0   0   2  ; "equal"
0024    KSTR     1   3      ; "north"
0025    UGET     2   0      ; adjustTest
0026    KSTR     3   6      ; "pan"
0027    KSTR     4   3      ; "north"
0028    KSHORT   5   0
0029    CALL     2   0   4
0030    CALLM    0   1   1
0031    GGET     0   0      ; "assert"
0032    TGETS    0   0   1  ; "are"
0033    TGETS    0   0   2  ; "equal"
0034    KSTR     1   3      ; "north"
0035    UGET     2   0      ; adjustTest
0036    KSTR     3   7      ; "two_finger_swipe"
0037    KSTR     4   3      ; "north"
0038    KSHORT   5   0
0039    CALL     2   0   4
0040    CALLM    0   1   1
0041    GGET     0   0      ; "assert"
0042    TGETS    0   0   1  ; "are"
0043    TGETS    0   0   2  ; "equal"
0044    KSTR     1   3      ; "north"
0045    UGET     2   0      ; adjustTest
0046    KSTR     3   8      ; "two_finger_pan"
0047    KSTR     4   3      ; "north"
0048    KSHORT   5   0
0049    CALL     2   0   4
0050    CALLM    0   1   1
0051    RET0     0   1

-- BYTECODE -- gesturedetector_spec.lua:28-34
0001    GGET     0   0      ; "assert"
0002    TGETS    0   0   1  ; "are"
0003    TGETS    0   0   2  ; "equal"
0004    KSTR     1   3      ; "west"
0005    UGET     2   0      ; adjustTest
0006    KSTR     3   4      ; "swipe"
0007    KSTR     4   5      ; "north"
0008    KSHORT   5   3
0009    CALL     2   0   4
0010    CALLM    0   1   1
0011    GGET     0   0      ; "assert"
0012    TGETS    0   0   1  ; "are"
0013    TGETS    0   0   2  ; "equal"
0014    KSTR     1   3      ; "west"
0015    UGET     2   0      ; adjustTest
0016    KSTR     3   6      ; "multiswipe"
0017    KSTR     4   5      ; "north"
0018    KSHORT   5   3
0019    CALL     2   0   4
0020    CALLM    0   1   1
0021    GGET     0   0      ; "assert"
0022    TGETS    0   0   1  ; "are"
0023    TGETS    0   0   2  ; "equal"
0024    KSTR     1   3      ; "west"
0025    UGET     2   0      ; adjustTest
0026    KSTR     3   7      ; "pan"
0027    KSTR     4   5      ; "north"
0028    KSHORT   5   3
0029    CALL     2   0   4
0030    CALLM    0   1   1
0031    GGET     0   0      ; "assert"
0032    TGETS    0   0   1  ; "are"
0033    TGETS    0   0   2  ; "equal"
0034    KSTR     1   3      ; "west"
0035    UGET     2   0      ; adjustTest
0036    KSTR     3   8      ; "two_finger_swipe"
0037    KSTR     4   5      ; "north"
0038    KSHORT   5   3
0039    CALL     2   0   4
0040    CALLM    0   1   1
0041    GGET     0   0      ; "assert"
0042    TGETS    0   0   1  ; "are"
0043    TGETS    0   0   2  ; "equal"
0044    KSTR     1   3      ; "west"
0045    UGET     2   0      ; adjustTest
0046    KSTR     3   9      ; "two_finger_pan"
0047    KSTR     4   5      ; "north"
0048    KSHORT   5   3
0049    CALL     2   0   4
0050    CALLM    0   1   1
0051    RET0     0   1

-- BYTECODE -- gesturedetector_spec.lua:35-41
0001    GGET     0   0      ; "assert"
0002    TGETS    0   0   1  ; "are"
0003    TGETS    0   0   2  ; "equal"
0004    KSTR     1   3      ; "south"
0005    UGET     2   0      ; adjustTest
0006    KSTR     3   4      ; "swipe"
0007    KSTR     4   5      ; "north"
0008    KSHORT   5   2
0009    CALL     2   0   4
0010    CALLM    0   1   1
0011    GGET     0   0      ; "assert"
0012    TGETS    0   0   1  ; "are"
0013    TGETS    0   0   2  ; "equal"
0014    KSTR     1   3      ; "south"
0015    UGET     2   0      ; adjustTest
0016    KSTR     3   6      ; "multiswipe"
0017    KSTR     4   5      ; "north"
0018    KSHORT   5   2
0019    CALL     2   0   4
0020    CALLM    0   1   1
0021    GGET     0   0      ; "assert"
0022    TGETS    0   0   1  ; "are"
0023    TGETS    0   0   2  ; "equal"
0024    KSTR     1   3      ; "south"
0025    UGET     2   0      ; adjustTest
0026    KSTR     3   7      ; "pan"
0027    KSTR     4   5      ; "north"
0028    KSHORT   5   2
0029    CALL     2   0   4
0030    CALLM    0   1   1
0031    GGET     0   0      ; "assert"
0032    TGETS    0   0   1  ; "are"
0033    TGETS    0   0   2  ; "equal"
0034    KSTR     1   3      ; "south"
0035    UGET     2   0      ; adjustTest
0036    KSTR     3   8      ; "two_finger_swipe"
0037    KSTR     4   5      ; "north"
0038    KSHORT   5   2
0039    CALL     2   0   4
0040    CALLM    0   1   1
0041    GGET     0   0      ; "assert"
0042    TGETS    0   0   1  ; "are"
0043    TGETS    0   0   2  ; "equal"
0044    KSTR     1   3      ; "south"
0045    UGET     2   0      ; adjustTest
0046    KSTR     3   9      ; "two_finger_pan"
0047    KSTR     4   5      ; "north"
0048    KSHORT   5   2
0049    CALL     2   0   4
0050    CALLM    0   1   1
0051    RET0     0   1

-- BYTECODE -- gesturedetector_spec.lua:42-48
0001    GGET     0   0      ; "assert"
0002    TGETS    0   0   1  ; "are"
0003    TGETS    0   0   2  ; "equal"
0004    KSTR     1   3      ; "east"
0005    UGET     2   0      ; adjustTest
0006    KSTR     3   4      ; "swipe"
0007    KSTR     4   5      ; "north"
0008    KSHORT   5   1
0009    CALL     2   0   4
0010    CALLM    0   1   1
0011    GGET     0   0      ; "assert"
0012    TGETS    0   0   1  ; "are"
0013    TGETS    0   0   2  ; "equal"
0014    KSTR     1   3      ; "east"
0015    UGET     2   0      ; adjustTest
0016    KSTR     3   6      ; "multiswipe"
0017    KSTR     4   5      ; "north"
0018    KSHORT   5   1
0019    CALL     2   0   4
0020    CALLM    0   1   1
0021    GGET     0   0      ; "assert"
0022    TGETS    0   0   1  ; "are"
0023    TGETS    0   0   2  ; "equal"
0024    KSTR     1   3      ; "east"
0025    UGET     2   0      ; adjustTest
0026    KSTR     3   7      ; "pan"
0027    KSTR     4   5      ; "north"
0028    KSHORT   5   1
0029    CALL     2   0   4
0030    CALLM    0   1   1
0031    GGET     0   0      ; "assert"
0032    TGETS    0   0   1  ; "are"
0033    TGETS    0   0   2  ; "equal"
0034    KSTR     1   3      ; "east"
0035    UGET     2   0      ; adjustTest
0036    KSTR     3   8      ; "two_finger_swipe"
0037    KSTR     4   5      ; "north"
0038    KSHORT   5   1
0039    CALL     2   0   4
0040    CALLM    0   1   1
0041    GGET     0   0      ; "assert"
0042    TGETS    0   0   1  ; "are"
0043    TGETS    0   0   2  ; "equal"
0044    KSTR     1   3      ; "east"
0045    UGET     2   0      ; adjustTest
0046    KSTR     3   9      ; "two_finger_pan"
0047    KSTR     4   5      ; "north"
0048    KSHORT   5   1
0049    CALL     2   0   4
0050    CALLM    0   1   1
0051    RET0     0   1

-- BYTECODE -- gesturedetector_spec.lua:8-49
0001    FNEW     0   0      ; gesturedetector_spec.lua:9
0002    GGET     1   1      ; "it"
0003    KSTR     2   2      ; "should not translate rotation 0"
0004    FNEW     3   3      ; gesturedetector_spec.lua:21
0005    CALL     1   1   3
0006    GGET     1   1      ; "it"
0007    KSTR     2   4      ; "should translate rotation 90"
0008    FNEW     3   5      ; gesturedetector_spec.lua:28
0009    CALL     1   1   3
0010    GGET     1   1      ; "it"
0011    KSTR     2   6      ; "should translate rotation 180"
0012    FNEW     3   7      ; gesturedetector_spec.lua:35
0013    CALL     1   1   3
0014    GGET     1   1      ; "it"
0015    KSTR     2   8      ; "should translate rotation 270"
0016    FNEW     3   9      ; gesturedetector_spec.lua:42
0017    CALL     1   1   3
0018    UCLO     0 => 0019
0019 => RET0     0   1

-- BYTECODE -- gesturedetector_spec.lua:1-50
0001    KPRI     0   0
0002    GGET     1   0      ; "setup"
0003    FNEW     2   1      ; gesturedetector_spec.lua:3
0004    CALL     1   1   2
0005    GGET     1   2      ; "describe"
0006    KSTR     2   3      ; "adjustGesCoordinate"
0007    FNEW     3   4      ; gesturedetector_spec.lua:8
0008    CALL     1   1   3
0009    UCLO     0 => 0010
0010 => RET0     0   1

-- BYTECODE -- gesturedetector_spec.lua:0-51
0001    GGET     0   0      ; "describe"
0002    KSTR     1   1      ; "gesturedetector module"
0003    FNEW     2   2      ; gesturedetector_spec.lua:1
0004    CALL     0   1   3
0005    RET0     0   1

