
main <./frontend/ui/gesturerange.lua:0,0> (15 instructions, 60 bytes at 0x7f8efa4068c0)
0+ params, 3 slots, 0 upvalues, 2 locals, 9 constants, 2 functions
	1	[1]	GETGLOBAL	0 -1	; require
	2	[1]	LOADK    	1 -2	; "ui/timeval"
	3	[1]	CALL     	0 2 2
	4	[3]	NEWTABLE 	1 0 4
	5	[5]	SETTABLE 	1 -3 -4	; "ges" nil
	6	[7]	SETTABLE 	1 -5 -4	; "range" nil
	7	[9]	SETTABLE 	1 -6 -4	; "rate" nil
	8	[11]	SETTABLE 	1 -7 -4	; "scale" nil
	9	[19]	CLOSURE  	2 0	; 0x7f8efa406c20
	10	[14]	SETTABLE 	1 -8 2	; "new" -
	11	[67]	CLOSURE  	2 1	; 0x7f8efa406aa0
	12	[67]	MOVE     	0 0
	13	[21]	SETTABLE 	1 -9 2	; "match" -
	14	[69]	RETURN   	1 2
	15	[69]	RETURN   	0 1

function <./frontend/ui/gesturerange.lua:14,19> (10 instructions, 40 bytes at 0x7f8efa406c20)
2 params, 6 slots, 0 upvalues, 3 locals, 2 constants, 0 functions
	1	[15]	TESTSET  	2 1 1
	2	[15]	JMP      	1	; to 4
	3	[15]	NEWTABLE 	2 0 0
	4	[16]	GETGLOBAL	3 -1	; setmetatable
	5	[16]	MOVE     	4 2
	6	[16]	MOVE     	5 0
	7	[16]	CALL     	3 3 1
	8	[17]	SETTABLE 	0 -2 0	; "__index" -
	9	[18]	RETURN   	2 2
	10	[19]	RETURN   	0 1

function <./frontend/ui/gesturerange.lua:21,67> (84 instructions, 336 bytes at 0x7f8efa406aa0)
2 params, 8 slots, 1 upvalue, 5 locals, 18 constants, 0 functions
	1	[22]	GETTABLE 	2 1 -1	; "ges"
	2	[22]	GETTABLE 	3 0 -1	; "ges"
	3	[22]	EQ       	1 2 3
	4	[22]	JMP      	2	; to 7
	5	[23]	LOADBOOL 	2 0 0
	6	[23]	RETURN   	2 2
	7	[25]	GETTABLE 	2 0 -2	; "range"
	8	[25]	TEST     	2 0 0
	9	[25]	JMP      	20	; to 30
	10	[32]	LOADNIL  	2 2
	11	[33]	GETGLOBAL	3 -3	; type
	12	[33]	GETTABLE 	4 0 -2	; "range"
	13	[33]	CALL     	3 2 2
	14	[33]	EQ       	0 3 -4	; - "function"
	15	[33]	JMP      	4	; to 20
	16	[34]	GETTABLE 	3 0 -2	; "range"
	17	[34]	CALL     	3 1 2
	18	[34]	MOVE     	2 3
	19	[34]	JMP      	1	; to 21
	20	[36]	GETTABLE 	2 0 -2	; "range"
	21	[38]	TEST     	2 0 0
	22	[38]	JMP      	5	; to 28
	23	[38]	SELF     	3 2 -5	; "contains"
	24	[38]	GETTABLE 	5 1 -6	; "pos"
	25	[38]	CALL     	3 3 2
	26	[38]	TEST     	3 0 1
	27	[38]	JMP      	2	; to 30
	28	[39]	LOADBOOL 	3 0 0
	29	[39]	RETURN   	3 2
	30	[43]	GETTABLE 	2 0 -7	; "rate"
	31	[43]	TEST     	2 0 0
	32	[43]	JMP      	23	; to 56
	33	[48]	GETTABLE 	2 0 -8	; "last_time"
	34	[48]	TEST     	2 0 1
	35	[48]	JMP      	4	; to 40
	36	[48]	GETUPVAL 	2 0	; TimeVal
	37	[48]	SELF     	2 2 -9	; "new"
	38	[48]	NEWTABLE 	4 0 0
	39	[48]	CALL     	2 3 2
	40	[49]	GETTABLE 	3 1 -10	; "time"
	41	[49]	SUB      	3 3 2
	42	[49]	GETUPVAL 	4 0	; TimeVal
	43	[49]	SELF     	4 4 -9	; "new"
	44	[49]	NEWTABLE 	6 0 1
	45	[49]	GETTABLE 	7 0 -7	; "rate"
	46	[49]	DIV      	7 -12 7	; 1000000 -
	47	[49]	SETTABLE 	6 -11 7	; "usec" -
	48	[49]	CALL     	4 3 2
	49	[49]	LT       	0 4 3
	50	[49]	JMP      	3	; to 54
	51	[50]	GETTABLE 	3 1 -10	; "time"
	52	[50]	SETTABLE 	0 -8 3	; "last_time" -
	53	[50]	JMP      	2	; to 56
	54	[52]	LOADBOOL 	3 0 0
	55	[52]	RETURN   	3 2
	56	[55]	GETTABLE 	2 0 -13	; "scale"
	57	[55]	TEST     	2 0 0
	58	[55]	JMP      	14	; to 73
	59	[56]	GETTABLE 	2 1 -14	; "distance"
	60	[56]	TEST     	2 0 1
	61	[56]	JMP      	1	; to 63
	62	[56]	GETTABLE 	2 1 -15	; "span"
	63	[57]	GETTABLE 	3 0 -13	; "scale"
	64	[57]	GETTABLE 	3 3 -16	; 1
	65	[57]	LT       	1 2 3
	66	[57]	JMP      	4	; to 71
	67	[57]	GETTABLE 	3 0 -13	; "scale"
	68	[57]	GETTABLE 	3 3 -17	; 2
	69	[57]	LT       	0 3 2
	70	[57]	JMP      	2	; to 73
	71	[58]	LOADBOOL 	3 0 0
	72	[58]	RETURN   	3 2
	73	[61]	GETTABLE 	2 0 -18	; "direction"
	74	[61]	TEST     	2 0 0
	75	[61]	JMP      	6	; to 82
	76	[62]	GETTABLE 	2 0 -18	; "direction"
	77	[62]	GETTABLE 	3 1 -18	; "direction"
	78	[62]	EQ       	1 2 3
	79	[62]	JMP      	2	; to 82
	80	[63]	LOADBOOL 	2 0 0
	81	[63]	RETURN   	2 2
	82	[66]	LOADBOOL 	2 1 0
	83	[66]	RETURN   	2 2
	84	[67]	RETURN   	0 1
