
main <./spec/unit/gesturerange_spec.lua:0,0> (5 instructions, 20 bytes at 0x7febe1c068d0)
0+ params, 3 slots, 0 upvalues, 0 locals, 2 constants, 1 function
	1	[1]	GETGLOBAL	0 -1	; describe
	2	[1]	LOADK    	1 -2	; "gesturerange module"
	3	[41]	CLOSURE  	2 0	; 0x7febe1c06b70
	4	[1]	CALL     	0 3 1
	5	[41]	RETURN   	0 1

function <./spec/unit/gesturerange_spec.lua:1,41> (24 instructions, 96 bytes at 0x7febe1c06b70)
0 params, 5 slots, 0 upvalues, 2 locals, 5 constants, 4 functions
	1	[3]	GETGLOBAL	2 -1	; setup
	2	[7]	CLOSURE  	3 0	; 0x7febe1c06ef0
	3	[7]	MOVE     	0 0
	4	[7]	MOVE     	0 1
	5	[3]	CALL     	2 2 1
	6	[9]	GETGLOBAL	2 -2	; it
	7	[9]	LOADK    	3 -3	; "should match tap event within range"
	8	[18]	CLOSURE  	4 1	; 0x7febe1c072c0
	9	[18]	MOVE     	0 0
	10	[18]	MOVE     	0 1
	11	[9]	CALL     	2 3 1
	12	[20]	GETGLOBAL	2 -2	; it
	13	[20]	LOADK    	3 -4	; "should not match tap event outside of range"
	14	[29]	CLOSURE  	4 2	; 0x7febe1c076c0
	15	[29]	MOVE     	0 0
	16	[29]	MOVE     	0 1
	17	[20]	CALL     	2 3 1
	18	[31]	GETGLOBAL	2 -2	; it
	19	[31]	LOADK    	3 -5	; "should match any event within nil range"
	20	[40]	CLOSURE  	4 3	; 0x7febe1c06de0
	21	[40]	MOVE     	0 0
	22	[40]	MOVE     	0 1
	23	[31]	CALL     	2 3 1
	24	[41]	RETURN   	0 1

function <./spec/unit/gesturerange_spec.lua:3,7> (12 instructions, 48 bytes at 0x7febe1c06ef0)
0 params, 2 slots, 2 upvalues, 0 locals, 4 constants, 0 functions
	1	[4]	GETGLOBAL	0 -1	; require
	2	[4]	LOADK    	1 -2	; "commonrequire"
	3	[4]	CALL     	0 2 1
	4	[5]	GETGLOBAL	0 -1	; require
	5	[5]	LOADK    	1 -3	; "ui/gesturerange"
	6	[5]	CALL     	0 2 2
	7	[5]	SETUPVAL 	0 0	; GestureRange
	8	[6]	GETGLOBAL	0 -1	; require
	9	[6]	LOADK    	1 -4	; "ui/geometry"
	10	[6]	CALL     	0 2 2
	11	[6]	SETUPVAL 	0 1	; Geom
	12	[7]	RETURN   	0 1

function <./spec/unit/gesturerange_spec.lua:9,18> (31 instructions, 124 bytes at 0x7febe1c072c0)
0 params, 8 slots, 2 upvalues, 1 local, 15 constants, 0 functions
	1	[10]	GETUPVAL 	0 0	; GestureRange
	2	[10]	SELF     	0 0 -1	; "new"
	3	[10]	NEWTABLE 	2 0 2
	4	[11]	SETTABLE 	2 -2 -3	; "ges" "tap"
	5	[12]	GETUPVAL 	3 1	; Geom
	6	[12]	SELF     	3 3 -1	; "new"
	7	[12]	NEWTABLE 	5 0 4
	8	[12]	SETTABLE 	5 -5 -6	; "x" 0
	9	[12]	SETTABLE 	5 -7 -6	; "y" 0
	10	[12]	SETTABLE 	5 -8 -9	; "w" 200
	11	[12]	SETTABLE 	5 -10 -9	; "h" 200
	12	[12]	CALL     	3 3 2
	13	[12]	SETTABLE 	2 -4 3	; "range" -
	14	[10]	CALL     	0 3 2
	15	[14]	GETGLOBAL	1 -11	; assert
	16	[14]	GETTABLE 	1 1 -12	; "truthy"
	17	[14]	SELF     	2 0 -13	; "match"
	18	[14]	NEWTABLE 	4 0 2
	19	[15]	SETTABLE 	4 -2 -3	; "ges" "tap"
	20	[16]	GETUPVAL 	5 1	; Geom
	21	[16]	SELF     	5 5 -1	; "new"
	22	[16]	NEWTABLE 	7 0 4
	23	[16]	SETTABLE 	7 -5 -15	; "x" 1
	24	[16]	SETTABLE 	7 -7 -15	; "y" 1
	25	[16]	SETTABLE 	7 -8 -6	; "w" 0
	26	[16]	SETTABLE 	7 -10 -6	; "h" 0
	27	[16]	CALL     	5 3 2
	28	[16]	SETTABLE 	4 -14 5	; "pos" -
	29	[14]	CALL     	2 3 0
	30	[14]	CALL     	1 0 1
	31	[18]	RETURN   	0 1

function <./spec/unit/gesturerange_spec.lua:20,29> (31 instructions, 124 bytes at 0x7febe1c076c0)
0 params, 8 slots, 2 upvalues, 1 local, 16 constants, 0 functions
	1	[21]	GETUPVAL 	0 0	; GestureRange
	2	[21]	SELF     	0 0 -1	; "new"
	3	[21]	NEWTABLE 	2 0 2
	4	[22]	SETTABLE 	2 -2 -3	; "ges" "tap"
	5	[23]	GETUPVAL 	3 1	; Geom
	6	[23]	SELF     	3 3 -1	; "new"
	7	[23]	NEWTABLE 	5 0 4
	8	[23]	SETTABLE 	5 -5 -6	; "x" 0
	9	[23]	SETTABLE 	5 -7 -6	; "y" 0
	10	[23]	SETTABLE 	5 -8 -9	; "w" 100
	11	[23]	SETTABLE 	5 -10 -9	; "h" 100
	12	[23]	CALL     	3 3 2
	13	[23]	SETTABLE 	2 -4 3	; "range" -
	14	[21]	CALL     	0 3 2
	15	[25]	GETGLOBAL	1 -11	; assert
	16	[25]	GETTABLE 	1 1 -12	; "falsy"
	17	[25]	SELF     	2 0 -13	; "match"
	18	[25]	NEWTABLE 	4 0 2
	19	[26]	SETTABLE 	4 -2 -3	; "ges" "tap"
	20	[27]	GETUPVAL 	5 1	; Geom
	21	[27]	SELF     	5 5 -1	; "new"
	22	[27]	NEWTABLE 	7 0 4
	23	[27]	SETTABLE 	7 -5 -15	; "x" 105
	24	[27]	SETTABLE 	7 -7 -16	; "y" 1
	25	[27]	SETTABLE 	7 -8 -6	; "w" 0
	26	[27]	SETTABLE 	7 -10 -6	; "h" 0
	27	[27]	CALL     	5 3 2
	28	[27]	SETTABLE 	4 -14 5	; "pos" -
	29	[25]	CALL     	2 3 0
	30	[25]	CALL     	1 0 1
	31	[29]	RETURN   	0 1

function <./spec/unit/gesturerange_spec.lua:31,40> (23 instructions, 92 bytes at 0x7febe1c06de0)
0 params, 8 slots, 2 upvalues, 1 local, 16 constants, 0 functions
	1	[32]	GETUPVAL 	0 0	; GestureRange
	2	[32]	SELF     	0 0 -1	; "new"
	3	[32]	NEWTABLE 	2 0 2
	4	[33]	SETTABLE 	2 -2 -3	; "ges" "tap"
	5	[34]	SETTABLE 	2 -4 -5	; "range" nil
	6	[32]	CALL     	0 3 2
	7	[36]	GETGLOBAL	1 -6	; assert
	8	[36]	GETTABLE 	1 1 -7	; "truthy"
	9	[36]	SELF     	2 0 -8	; "match"
	10	[36]	NEWTABLE 	4 0 2
	11	[37]	SETTABLE 	4 -2 -3	; "ges" "tap"
	12	[38]	GETUPVAL 	5 1	; Geom
	13	[38]	SELF     	5 5 -1	; "new"
	14	[38]	NEWTABLE 	7 0 4
	15	[38]	SETTABLE 	7 -10 -11	; "x" 1
	16	[38]	SETTABLE 	7 -12 -11	; "y" 1
	17	[38]	SETTABLE 	7 -13 -14	; "w" 1e+18
	18	[38]	SETTABLE 	7 -15 -16	; "h" 100
	19	[38]	CALL     	5 3 2
	20	[38]	SETTABLE 	4 -9 5	; "pos" -
	21	[36]	CALL     	2 3 0
	22	[36]	CALL     	1 0 1
	23	[40]	RETURN   	0 1
