
main <./frontend/gettext.lua:0,0> (149 instructions, 596 bytes at 0x7fe9cbc068a0)
0+ params, 18 slots, 0 upvalues, 14 locals, 40 constants, 11 functions
	1	[22]	GETGLOBAL	0 -1	; pcall
	2	[22]	GETGLOBAL	1 -2	; require
	3	[22]	LOADK    	2 -3	; "android"
	4	[22]	CALL     	0 3 3
	5	[23]	GETGLOBAL	2 -2	; require
	6	[23]	LOADK    	3 -4	; "logger"
	7	[23]	CALL     	2 2 2
	8	[25]	NEWTABLE 	3 0 5
	9	[26]	NEWTABLE 	4 0 0
	10	[26]	SETTABLE 	3 -5 4	; "translation" -
	11	[27]	SETTABLE 	3 -6 -7	; "current_lang" "C"
	12	[28]	SETTABLE 	3 -8 -9	; "dirname" "l10n"
	13	[29]	SETTABLE 	3 -10 -11	; "textdomain" "koreader"
	14	[30]	SETTABLE 	3 -12 -13	; "plural_default" "n != 1"
	15	[33]	NEWTABLE 	4 0 1
	16	[34]	NEWTABLE 	5 0 0
	17	[34]	SETTABLE 	4 -14 5	; "__index" -
	18	[40]	CLOSURE  	5 0	; 0x7fe9cbc06e80
	19	[40]	SETTABLE 	3 -15 5	; "wrapUntranslated_nowrap" -
	20	[41]	GETTABLE 	5 3 -15	; "wrapUntranslated_nowrap"
	21	[41]	SETTABLE 	3 -16 5	; "wrapUntranslated" -
	22	[61]	CLOSURE  	5 1	; 0x7fe9cbc06ba0
	23	[59]	SETTABLE 	4 -17 5	; "__call" -
	24	[76]	CLOSURE  	5 2	; 0x7fe9cbc065c0
	25	[84]	CLOSURE  	6 3	; 0x7fe9cbc07960
	26	[93]	CLOSURE  	7 4	; 0x7fe9cbc07d80
	27	[136]	CLOSURE  	8 5	; 0x7fe9cbc06cc0
	28	[136]	MOVE     	0 6
	29	[136]	MOVE     	0 7
	30	[136]	MOVE     	0 2
	31	[163]	CLOSURE  	9 6	; 0x7fe9cbc080a0
	32	[163]	MOVE     	0 5
	33	[163]	MOVE     	0 3
	34	[169]	GETTABLE 	10 4 -14	; "__index"
	35	[277]	CLOSURE  	11 7	; 0x7fe9cbc06e00
	36	[277]	MOVE     	0 3
	37	[277]	MOVE     	0 2
	38	[277]	MOVE     	0 9
	39	[277]	MOVE     	0 8
	40	[277]	MOVE     	0 7
	41	[169]	SETTABLE 	10 -18 11	; "changeLang" -
	42	[279]	GETTABLE 	10 4 -14	; "__index"
	43	[279]	SETTABLE 	10 -19 7	; "getPlural" -
	44	[310]	GETTABLE 	10 4 -14	; "__index"
	45	[318]	CLOSURE  	11 8	; 0x7fe9cbc09a60
	46	[318]	MOVE     	0 3
	47	[310]	SETTABLE 	10 -20 11	; "ngettext" -
	48	[343]	GETTABLE 	10 4 -14	; "__index"
	49	[351]	CLOSURE  	11 9	; 0x7fe9cbc09ce0
	50	[351]	MOVE     	0 3
	51	[343]	SETTABLE 	10 -21 11	; "npgettext" -
	52	[379]	GETTABLE 	10 4 -14	; "__index"
	53	[381]	CLOSURE  	11 10	; 0x7fe9cbc09ef0
	54	[381]	MOVE     	0 3
	55	[379]	SETTABLE 	10 -22 11	; "pgettext" -
	56	[383]	GETGLOBAL	10 -23	; setmetatable
	57	[383]	MOVE     	11 3
	58	[383]	MOVE     	12 4
	59	[383]	CALL     	10 3 1
	60	[385]	GETGLOBAL	10 -24	; os
	61	[385]	GETTABLE 	10 10 -25	; "getenv"
	62	[385]	LOADK    	11 -26	; "LANGUAGE"
	63	[385]	CALL     	10 2 2
	64	[385]	TEST     	10 0 0
	65	[385]	JMP      	7	; to 73
	66	[386]	GETTABLE 	10 3 -18	; "changeLang"
	67	[386]	GETGLOBAL	11 -24	; os
	68	[386]	GETTABLE 	11 11 -25	; "getenv"
	69	[386]	LOADK    	12 -26	; "LANGUAGE"
	70	[386]	CALL     	11 2 0
	71	[386]	CALL     	10 0 1
	72	[386]	JMP      	38	; to 111
	73	[387]	GETGLOBAL	10 -24	; os
	74	[387]	GETTABLE 	10 10 -25	; "getenv"
	75	[387]	LOADK    	11 -27	; "LC_ALL"
	76	[387]	CALL     	10 2 2
	77	[387]	TEST     	10 0 0
	78	[387]	JMP      	7	; to 86
	79	[388]	GETTABLE 	10 3 -18	; "changeLang"
	80	[388]	GETGLOBAL	11 -24	; os
	81	[388]	GETTABLE 	11 11 -25	; "getenv"
	82	[388]	LOADK    	12 -27	; "LC_ALL"
	83	[388]	CALL     	11 2 0
	84	[388]	CALL     	10 0 1
	85	[388]	JMP      	25	; to 111
	86	[389]	GETGLOBAL	10 -24	; os
	87	[389]	GETTABLE 	10 10 -25	; "getenv"
	88	[389]	LOADK    	11 -28	; "LC_MESSAGES"
	89	[389]	CALL     	10 2 2
	90	[389]	TEST     	10 0 0
	91	[389]	JMP      	7	; to 99
	92	[390]	GETTABLE 	10 3 -18	; "changeLang"
	93	[390]	GETGLOBAL	11 -24	; os
	94	[390]	GETTABLE 	11 11 -25	; "getenv"
	95	[390]	LOADK    	12 -28	; "LC_MESSAGES"
	96	[390]	CALL     	11 2 0
	97	[390]	CALL     	10 0 1
	98	[390]	JMP      	12	; to 111
	99	[391]	GETGLOBAL	10 -24	; os
	100	[391]	GETTABLE 	10 10 -25	; "getenv"
	101	[391]	LOADK    	11 -29	; "LANG"
	102	[391]	CALL     	10 2 2
	103	[391]	TEST     	10 0 0
	104	[391]	JMP      	6	; to 111
	105	[392]	GETTABLE 	10 3 -18	; "changeLang"
	106	[392]	GETGLOBAL	11 -24	; os
	107	[392]	GETTABLE 	11 11 -25	; "getenv"
	108	[392]	LOADK    	12 -29	; "LANG"
	109	[392]	CALL     	11 2 0
	110	[392]	CALL     	10 0 1
	111	[395]	TEST     	0 0 0
	112	[395]	JMP      	35	; to 148
	113	[396]	GETGLOBAL	10 -2	; require
	114	[396]	LOADK    	11 -30	; "ffi"
	115	[396]	CALL     	10 2 2
	116	[397]	GETTABLE 	11 10 -31	; "new"
	117	[397]	LOADK    	12 -32	; "char[?]"
	118	[397]	LOADK    	13 -33	; 16
	119	[397]	CALL     	11 3 2
	120	[398]	GETTABLE 	12 1 -34	; "lib"
	121	[398]	GETTABLE 	12 12 -35	; "AConfiguration_getLanguage"
	122	[398]	GETTABLE 	13 1 -36	; "app"
	123	[398]	GETTABLE 	13 13 -37	; "config"
	124	[398]	MOVE     	14 11
	125	[398]	CALL     	12 3 1
	126	[399]	GETTABLE 	12 10 -38	; "string"
	127	[399]	MOVE     	13 11
	128	[399]	CALL     	12 2 2
	129	[400]	GETTABLE 	13 1 -34	; "lib"
	130	[400]	GETTABLE 	13 13 -39	; "AConfiguration_getCountry"
	131	[400]	GETTABLE 	14 1 -36	; "app"
	132	[400]	GETTABLE 	14 14 -37	; "config"
	133	[400]	MOVE     	15 11
	134	[400]	CALL     	13 3 1
	135	[401]	GETTABLE 	13 10 -38	; "string"
	136	[401]	MOVE     	14 11
	137	[401]	CALL     	13 2 2
	138	[402]	TEST     	12 0 0
	139	[402]	JMP      	8	; to 148
	140	[402]	TEST     	13 0 0
	141	[402]	JMP      	6	; to 148
	142	[403]	GETTABLE 	14 3 -18	; "changeLang"
	143	[403]	MOVE     	15 12
	144	[403]	LOADK    	16 -40	; "_"
	145	[403]	MOVE     	17 13
	146	[403]	CONCAT   	15 15 17
	147	[403]	CALL     	14 2 1
	148	[407]	RETURN   	3 2
	149	[407]	RETURN   	0 1

function <./frontend/gettext.lua:40,40> (2 instructions, 8 bytes at 0x7fe9cbc06e80)
1 param, 2 slots, 0 upvalues, 1 local, 0 constants, 0 functions
	1	[40]	RETURN   	0 2
	2	[40]	RETURN   	0 1

function <./frontend/gettext.lua:59,61> (9 instructions, 36 bytes at 0x7fe9cbc06ba0)
2 params, 4 slots, 0 upvalues, 2 locals, 2 constants, 0 functions
	1	[60]	GETTABLE 	2 0 -1	; "translation"
	2	[60]	GETTABLE 	2 2 1
	3	[60]	TEST     	2 0 1
	4	[60]	JMP      	3	; to 8
	5	[60]	GETTABLE 	2 0 -2	; "wrapUntranslated"
	6	[60]	MOVE     	3 1
	7	[60]	CALL     	2 2 2
	8	[60]	RETURN   	2 2
	9	[61]	RETURN   	0 1

function <./frontend/gettext.lua:63,76> (47 instructions, 188 bytes at 0x7fe9cbc065c0)
1 param, 2 slots, 0 upvalues, 1 local, 17 constants, 0 functions
	1	[64]	EQ       	0 0 -1	; - "\n"
	2	[64]	JMP      	3	; to 6
	3	[64]	LOADK    	1 -2	; ""
	4	[64]	RETURN   	1 2
	5	[64]	JMP      	41	; to 47
	6	[65]	EQ       	0 0 -3	; - "a"
	7	[65]	JMP      	3	; to 11
	8	[65]	LOADK    	1 -4	; "\a"
	9	[65]	RETURN   	1 2
	10	[65]	JMP      	36	; to 47
	11	[66]	EQ       	0 0 -5	; - "b"
	12	[66]	JMP      	3	; to 16
	13	[66]	LOADK    	1 -6	; "\b"
	14	[66]	RETURN   	1 2
	15	[66]	JMP      	31	; to 47
	16	[67]	EQ       	0 0 -7	; - "f"
	17	[67]	JMP      	3	; to 21
	18	[67]	LOADK    	1 -8	; "\f"
	19	[67]	RETURN   	1 2
	20	[67]	JMP      	26	; to 47
	21	[68]	EQ       	0 0 -9	; - "n"
	22	[68]	JMP      	3	; to 26
	23	[68]	LOADK    	1 -1	; "\n"
	24	[68]	RETURN   	1 2
	25	[68]	JMP      	21	; to 47
	26	[69]	EQ       	0 0 -10	; - "r"
	27	[69]	JMP      	3	; to 31
	28	[69]	LOADK    	1 -11	; "\r"
	29	[69]	RETURN   	1 2
	30	[69]	JMP      	16	; to 47
	31	[70]	EQ       	0 0 -12	; - "t"
	32	[70]	JMP      	3	; to 36
	33	[70]	LOADK    	1 -13	; "\t"
	34	[70]	RETURN   	1 2
	35	[70]	JMP      	11	; to 47
	36	[71]	EQ       	0 0 -14	; - "v"
	37	[71]	JMP      	3	; to 41
	38	[71]	LOADK    	1 -15	; "\v"
	39	[71]	RETURN   	1 2
	40	[71]	JMP      	6	; to 47
	41	[72]	EQ       	0 0 -16	; - "0"
	42	[72]	JMP      	3	; to 46
	43	[72]	LOADK    	1 -17	; "\000"
	44	[72]	RETURN   	1 2
	45	[72]	JMP      	1	; to 47
	46	[74]	RETURN   	0 2
	47	[76]	RETURN   	0 1

function <./frontend/gettext.lua:79,84> (17 instructions, 68 bytes at 0x7fe9cbc07960)
1 param, 5 slots, 0 upvalues, 1 local, 7 constants, 0 functions
	1	[80]	SELF     	1 0 -1	; "gsub"
	2	[80]	LOADK    	3 -2	; "&&"
	3	[80]	LOADK    	4 -3	; "and"
	4	[80]	CALL     	1 4 2
	5	[80]	MOVE     	0 1
	6	[81]	SELF     	1 0 -1	; "gsub"
	7	[81]	LOADK    	3 -4	; "!="
	8	[81]	LOADK    	4 -5	; "~="
	9	[81]	CALL     	1 4 2
	10	[81]	MOVE     	0 1
	11	[82]	SELF     	1 0 -1	; "gsub"
	12	[82]	LOADK    	3 -6	; "||"
	13	[82]	LOADK    	4 -7	; "or"
	14	[82]	CALL     	1 4 2
	15	[82]	MOVE     	0 1
	16	[83]	RETURN   	0 2
	17	[84]	RETURN   	0 1

function <./frontend/gettext.lua:87,93> (8 instructions, 32 bytes at 0x7fe9cbc07d80)
1 param, 2 slots, 0 upvalues, 1 local, 2 constants, 0 functions
	1	[88]	EQ       	1 0 -1	; - 1
	2	[88]	JMP      	3	; to 6
	3	[89]	LOADK    	1 -1	; 1
	4	[89]	RETURN   	1 2
	5	[89]	JMP      	2	; to 8
	6	[91]	LOADK    	1 -2	; 0
	7	[91]	RETURN   	1 2
	8	[93]	RETURN   	0 1

function <./frontend/gettext.lua:96,136> (78 instructions, 312 bytes at 0x7fe9cbc06cc0)
3 params, 13 slots, 3 upvalues, 10 locals, 16 constants, 0 functions
	1	[98]	LOADK    	3 -1	; "return function(n) if "
	2	[100]	LEN      	4 0
	3	[100]	LT       	0 -2 4	; 1 -
	4	[100]	JMP      	40	; to 45
	5	[101]	LOADK    	4 -2	; 1
	6	[101]	LEN      	5 0
	7	[101]	LOADK    	6 -2	; 1
	8	[101]	FORPREP  	4 31	; to 40
	9	[102]	GETTABLE 	8 0 7
	10	[103]	GETUPVAL 	9 0	; logicalCtoLua
	11	[103]	MOVE     	10 8
	12	[103]	CALL     	9 2 2
	13	[103]	MOVE     	8 9
	14	[105]	LT       	0 -2 7	; 1 -
	15	[105]	JMP      	8	; to 24
	16	[105]	GETGLOBAL	9 -3	; tonumber
	17	[105]	MOVE     	10 8
	18	[105]	CALL     	9 2 2
	19	[105]	EQ       	0 9 -4	; - nil
	20	[105]	JMP      	3	; to 24
	21	[106]	LOADK    	9 -5	; " elseif "
	22	[106]	MOVE     	10 8
	23	[106]	CONCAT   	8 9 10
	24	[108]	GETGLOBAL	9 -3	; tonumber
	25	[108]	MOVE     	10 8
	26	[108]	CALL     	9 2 2
	27	[108]	EQ       	1 9 -4	; - nil
	28	[108]	JMP      	3	; to 32
	29	[110]	LOADK    	9 -6	; " else return "
	30	[110]	MOVE     	10 8
	31	[110]	CONCAT   	8 9 10
	32	[112]	SELF     	9 8 -7	; "gsub"
	33	[112]	LOADK    	11 -8	; "?"
	34	[112]	LOADK    	12 -9	; " then return"
	35	[112]	CALL     	9 4 2
	36	[112]	MOVE     	8 9
	37	[115]	MOVE     	9 3
	38	[115]	MOVE     	10 8
	39	[115]	CONCAT   	3 9 10
	40	[101]	FORLOOP  	4 -32	; to 9
	41	[117]	MOVE     	4 3
	42	[117]	LOADK    	5 -10	; " end end"
	43	[117]	CONCAT   	3 4 5
	44	[117]	JMP      	23	; to 68
	45	[119]	GETTABLE 	4 0 -2	; 1
	46	[123]	EQ       	0 4 2
	47	[123]	JMP      	2	; to 50
	48	[124]	GETUPVAL 	5 1	; getDefaultPlural
	49	[124]	RETURN   	5 2
	50	[127]	GETGLOBAL	5 -3	; tonumber
	51	[127]	MOVE     	6 4
	52	[127]	CALL     	5 2 2
	53	[127]	EQ       	1 5 -4	; - nil
	54	[127]	JMP      	5	; to 60
	55	[128]	LOADK    	5 -11	; "return function(n) return "
	56	[128]	MOVE     	6 4
	57	[128]	LOADK    	7 -12	; " end"
	58	[128]	CONCAT   	3 5 7
	59	[128]	JMP      	8	; to 68
	60	[130]	GETUPVAL 	5 0	; logicalCtoLua
	61	[130]	MOVE     	6 4
	62	[130]	CALL     	5 2 2
	63	[130]	MOVE     	4 5
	64	[131]	LOADK    	5 -1	; "return function(n) if "
	65	[131]	MOVE     	6 4
	66	[131]	LOADK    	7 -13	; " then return 1 else return 0 end end"
	67	[131]	CONCAT   	3 5 7
	68	[134]	GETUPVAL 	4 2	; logger
	69	[134]	GETTABLE 	4 4 -14	; "dbg"
	70	[134]	LOADK    	5 -15	; "gettext: plural function"
	71	[134]	MOVE     	6 3
	72	[134]	CALL     	4 3 1
	73	[135]	GETGLOBAL	4 -16	; loadstring
	74	[135]	MOVE     	5 3
	75	[135]	CALL     	4 2 2
	76	[135]	TAILCALL 	4 1 0
	77	[135]	RETURN   	4 0
	78	[136]	RETURN   	0 1

function <./frontend/gettext.lua:138,163> (83 instructions, 332 bytes at 0x7fe9cbc080a0)
4 params, 8 slots, 2 upvalues, 5 locals, 6 constants, 0 functions
	1	[140]	GETGLOBAL	4 -1	; string
	2	[140]	GETTABLE 	4 4 -2	; "gsub"
	3	[140]	MOVE     	5 2
	4	[140]	LOADK    	6 -3	; "\\(.)"
	5	[140]	GETUPVAL 	7 0	; c_escape
	6	[140]	CALL     	4 4 2
	7	[141]	TEST     	0 0 0
	8	[141]	JMP      	45	; to 54
	9	[141]	EQ       	1 0 -4	; - ""
	10	[141]	JMP      	43	; to 54
	11	[142]	GETUPVAL 	5 1	; GetText
	12	[142]	GETTABLE 	5 5 -5	; "context"
	13	[142]	GETTABLE 	5 5 0
	14	[142]	TEST     	5 0 1
	15	[142]	JMP      	4	; to 20
	16	[143]	GETUPVAL 	5 1	; GetText
	17	[143]	GETTABLE 	5 5 -5	; "context"
	18	[143]	NEWTABLE 	6 0 0
	19	[143]	SETTABLE 	5 0 6
	20	[145]	TEST     	3 0 0
	21	[145]	JMP      	22	; to 44
	22	[146]	GETUPVAL 	5 1	; GetText
	23	[146]	GETTABLE 	5 5 -5	; "context"
	24	[146]	GETTABLE 	5 5 0
	25	[146]	GETTABLE 	5 5 1
	26	[146]	TEST     	5 0 1
	27	[146]	JMP      	5	; to 33
	28	[147]	GETUPVAL 	5 1	; GetText
	29	[147]	GETTABLE 	5 5 -5	; "context"
	30	[147]	GETTABLE 	5 5 0
	31	[147]	NEWTABLE 	6 0 0
	32	[147]	SETTABLE 	5 1 6
	33	[149]	GETUPVAL 	5 1	; GetText
	34	[149]	GETTABLE 	5 5 -5	; "context"
	35	[149]	GETTABLE 	5 5 0
	36	[149]	GETTABLE 	5 5 1
	37	[149]	EQ       	1 4 -4	; - ""
	38	[149]	JMP      	2	; to 41
	39	[149]	TESTSET  	6 4 1
	40	[149]	JMP      	1	; to 42
	41	[149]	LOADNIL  	6 6
	42	[149]	SETTABLE 	5 3 6
	43	[149]	JMP      	39	; to 83
	44	[151]	GETUPVAL 	5 1	; GetText
	45	[151]	GETTABLE 	5 5 -5	; "context"
	46	[151]	GETTABLE 	5 5 0
	47	[151]	EQ       	1 4 -4	; - ""
	48	[151]	JMP      	2	; to 51
	49	[151]	TESTSET  	6 4 1
	50	[151]	JMP      	1	; to 52
	51	[151]	LOADNIL  	6 6
	52	[151]	SETTABLE 	5 1 6
	53	[152]	JMP      	29	; to 83
	54	[154]	TEST     	3 0 0
	55	[154]	JMP      	19	; to 75
	56	[155]	GETUPVAL 	5 1	; GetText
	57	[155]	GETTABLE 	5 5 -6	; "translation"
	58	[155]	GETTABLE 	5 5 1
	59	[155]	TEST     	5 0 1
	60	[155]	JMP      	4	; to 65
	61	[156]	GETUPVAL 	5 1	; GetText
	62	[156]	GETTABLE 	5 5 -6	; "translation"
	63	[156]	NEWTABLE 	6 0 0
	64	[156]	SETTABLE 	5 1 6
	65	[158]	GETUPVAL 	5 1	; GetText
	66	[158]	GETTABLE 	5 5 -6	; "translation"
	67	[158]	GETTABLE 	5 5 1
	68	[158]	EQ       	1 4 -4	; - ""
	69	[158]	JMP      	2	; to 72
	70	[158]	TESTSET  	6 4 1
	71	[158]	JMP      	1	; to 73
	72	[158]	LOADNIL  	6 6
	73	[158]	SETTABLE 	5 3 6
	74	[158]	JMP      	8	; to 83
	75	[160]	GETUPVAL 	5 1	; GetText
	76	[160]	GETTABLE 	5 5 -6	; "translation"
	77	[160]	EQ       	1 4 -4	; - ""
	78	[160]	JMP      	2	; to 81
	79	[160]	TESTSET  	6 4 1
	80	[160]	JMP      	1	; to 82
	81	[160]	LOADNIL  	6 6
	82	[160]	SETTABLE 	5 1 6
	83	[163]	RETURN   	0 1

function <./frontend/gettext.lua:169,277> (227 instructions, 908 bytes at 0x7fe9cbc06e00)
1 param, 20 slots, 5 upvalues, 25 locals, 55 constants, 0 functions
	1	[170]	GETUPVAL 	1 0	; GetText
	2	[170]	NEWTABLE 	2 0 0
	3	[170]	SETTABLE 	1 -1 2	; "context" -
	4	[171]	GETUPVAL 	1 0	; GetText
	5	[171]	NEWTABLE 	2 0 0
	6	[171]	SETTABLE 	1 -2 2	; "translation" -
	7	[172]	GETUPVAL 	1 0	; GetText
	8	[172]	SETTABLE 	1 -3 -4	; "current_lang" "C"
	9	[176]	EQ       	1 0 -4	; - "C"
	10	[176]	JMP      	9	; to 20
	11	[176]	EQ       	1 0 -5	; - nil
	12	[176]	JMP      	7	; to 20
	13	[176]	EQ       	1 0 -6	; - ""
	14	[176]	JMP      	5	; to 20
	15	[177]	SELF     	1 0 -7	; "match"
	16	[177]	LOADK    	3 -8	; "^en_US"
	17	[177]	CALL     	1 3 2
	18	[177]	EQ       	0 1 -9	; - "en_US"
	19	[177]	JMP      	1	; to 21
	20	[177]	RETURN   	0 1
	21	[180]	SELF     	1 0 -10	; "sub"
	22	[180]	LOADK    	3 -11	; 1
	23	[180]	SELF     	4 0 -12	; "find"
	24	[180]	LOADK    	6 -13	; ".%."
	25	[180]	CALL     	4 3 0
	26	[180]	CALL     	1 0 2
	27	[180]	MOVE     	0 1
	28	[182]	GETUPVAL 	1 0	; GetText
	29	[182]	GETTABLE 	1 1 -14	; "dirname"
	30	[182]	LOADK    	2 -15	; "/"
	31	[182]	MOVE     	3 0
	32	[182]	LOADK    	4 -15	; "/"
	33	[182]	GETUPVAL 	5 0	; GetText
	34	[182]	GETTABLE 	5 5 -16	; "textdomain"
	35	[182]	LOADK    	6 -17	; ".po"
	36	[182]	CONCAT   	1 1 6
	37	[183]	GETGLOBAL	2 -18	; io
	38	[183]	GETTABLE 	2 2 -19	; "open"
	39	[183]	MOVE     	3 1
	40	[183]	LOADK    	4 -20	; "r"
	41	[183]	CALL     	2 3 2
	42	[185]	TEST     	2 0 1
	43	[185]	JMP      	7	; to 51
	44	[186]	GETUPVAL 	3 1	; logger
	45	[186]	GETTABLE 	3 3 -21	; "dbg"
	46	[186]	LOADK    	4 -22	; "cannot open translation file:"
	47	[186]	MOVE     	5 1
	48	[186]	CALL     	3 3 1
	49	[187]	LOADBOOL 	3 0 0
	50	[187]	RETURN   	3 2
	51	[190]	NEWTABLE 	3 0 0
	52	[191]	LOADBOOL 	4 0 0
	53	[192]	LOADNIL  	5 6
	54	[195]	SELF     	7 2 -23	; "read"
	55	[195]	LOADK    	9 -24	; "*l"
	56	[195]	CALL     	7 3 2
	57	[196]	EQ       	1 7 -5	; - nil
	58	[196]	JMP      	2	; to 61
	59	[196]	EQ       	0 7 -6	; - ""
	60	[196]	JMP      	115	; to 176
	61	[197]	GETTABLE 	8 3 -25	; "msgid"
	62	[197]	TEST     	8 0 0
	63	[197]	JMP      	29	; to 93
	64	[197]	GETTABLE 	8 3 -26	; "msgid_plural"
	65	[197]	TEST     	8 0 0
	66	[197]	JMP      	26	; to 93
	67	[197]	GETTABLE 	8 3 -27	; "msgstr[0]"
	68	[197]	TEST     	8 0 0
	69	[197]	JMP      	23	; to 93
	70	[198]	GETGLOBAL	8 -28	; pairs
	71	[198]	MOVE     	9 3
	72	[198]	CALL     	8 2 4
	73	[198]	JMP      	16	; to 90
	74	[199]	GETGLOBAL	13 -29	; tonumber
	75	[199]	SELF     	14 11 -7	; "match"
	76	[199]	LOADK    	16 -30	; "msgstr%[([0-9]+)%]"
	77	[199]	CALL     	14 3 0
	78	[199]	CALL     	13 0 2
	79	[200]	MOVE     	14 12
	80	[202]	TEST     	13 0 0
	81	[202]	JMP      	8	; to 90
	82	[202]	TEST     	14 0 0
	83	[202]	JMP      	6	; to 90
	84	[203]	GETUPVAL 	15 2	; addTranslation
	85	[203]	GETTABLE 	16 3 -31	; "msgctxt"
	86	[203]	GETTABLE 	17 3 -25	; "msgid"
	87	[203]	MOVE     	18 14
	88	[203]	MOVE     	19 13
	89	[203]	CALL     	15 5 1
	90	[198]	TFORLOOP 	8 2
	91	[204]	JMP      	-18	; to 74
	92	[205]	JMP      	76	; to 169
	93	[206]	GETTABLE 	8 3 -25	; "msgid"
	94	[206]	TEST     	8 0 0
	95	[206]	JMP      	73	; to 169
	96	[206]	GETTABLE 	8 3 -32	; "msgstr"
	97	[206]	TEST     	8 0 0
	98	[206]	JMP      	70	; to 169
	99	[206]	GETTABLE 	8 3 -32	; "msgstr"
	100	[206]	EQ       	1 8 -6	; - ""
	101	[206]	JMP      	67	; to 169
	102	[208]	TEST     	5 0 1
	103	[208]	JMP      	60	; to 164
	104	[208]	GETTABLE 	8 3 -25	; "msgid"
	105	[208]	EQ       	0 8 -6	; - ""
	106	[208]	JMP      	57	; to 164
	107	[209]	GETTABLE 	5 3 -32	; "msgstr"
	108	[210]	GETTABLE 	8 3 -32	; "msgstr"
	109	[210]	SELF     	8 8 -7	; "match"
	110	[210]	LOADK    	10 -33	; "Plural%-Forms: (.*)"
	111	[210]	CALL     	8 3 2
	112	[211]	SELF     	9 8 -7	; "match"
	113	[211]	LOADK    	11 -34	; "nplurals=([0-9]+);"
	114	[211]	CALL     	9 3 2
	115	[211]	TEST     	9 0 1
	116	[211]	JMP      	1	; to 118
	117	[211]	LOADK    	9 -35	; 2
	118	[212]	SELF     	10 8 -7	; "match"
	119	[212]	LOADK    	12 -36	; "plural=%((.*)%);"
	120	[212]	CALL     	10 3 2
	121	[215]	EQ       	0 10 -37	; - "n == 1) ? 0 : ((n == 0 || n != 1 && n % 100 >= 1 && n % 100 <= 19) ? 1 : 2"
	122	[215]	JMP      	1	; to 124
	123	[216]	LOADK    	10 -38	; "n == 1 ? 0 : (n == 0 || n != 1 && n % 100 >= 1 && n % 100 <= 19) ? 1 : 2"
	124	[219]	TEST     	10 0 1
	125	[219]	JMP      	4	; to 130
	126	[225]	SELF     	11 8 -7	; "match"
	127	[225]	LOADK    	13 -39	; "plural=(.*);"
	128	[225]	CALL     	11 3 2
	129	[225]	MOVE     	10 11
	130	[228]	SELF     	11 10 -12	; "find"
	131	[228]	LOADK    	13 -40	; "[^n!=%%<>&:%(%)|?0-9 ]"
	132	[228]	CALL     	11 3 2
	133	[228]	TEST     	11 0 0
	134	[228]	JMP      	2	; to 137
	135	[230]	GETUPVAL 	11 0	; GetText
	136	[230]	GETTABLE 	10 11 -41	; "plural_default"
	137	[233]	NEWTABLE 	11 0 0
	138	[234]	SELF     	12 10 -42	; "gmatch"
	139	[234]	LOADK    	14 -43	; "[^:]+"
	140	[234]	CALL     	12 3 4
	141	[234]	JMP      	5	; to 147
	142	[235]	GETGLOBAL	16 -44	; table
	143	[235]	GETTABLE 	16 16 -45	; "insert"
	144	[235]	MOVE     	17 11
	145	[235]	MOVE     	18 15
	146	[235]	CALL     	16 3 1
	147	[234]	TFORLOOP 	12 1
	148	[235]	JMP      	-7	; to 142
	149	[238]	GETUPVAL 	12 0	; GetText
	150	[238]	GETUPVAL 	13 3	; getPluralFunc
	151	[238]	MOVE     	14 11
	152	[238]	MOVE     	15 9
	153	[238]	GETUPVAL 	16 0	; GetText
	154	[238]	GETTABLE 	16 16 -41	; "plural_default"
	155	[238]	CALL     	13 4 2
	156	[238]	SETTABLE 	12 -46 13	; "getPlural" -
	157	[239]	GETUPVAL 	12 0	; GetText
	158	[239]	GETTABLE 	12 12 -46	; "getPlural"
	159	[239]	TEST     	12 0 1
	160	[239]	JMP      	3	; to 164
	161	[240]	GETUPVAL 	12 0	; GetText
	162	[240]	GETUPVAL 	13 4	; getDefaultPlural
	163	[240]	SETTABLE 	12 -46 13	; "getPlural" -
	164	[244]	GETUPVAL 	8 2	; addTranslation
	165	[244]	GETTABLE 	9 3 -31	; "msgctxt"
	166	[244]	GETTABLE 	10 3 -25	; "msgid"
	167	[244]	GETTABLE 	11 3 -32	; "msgstr"
	168	[244]	CALL     	8 4 1
	169	[247]	EQ       	0 7 -5	; - nil
	170	[247]	JMP      	1	; to 172
	171	[247]	JMP      	53	; to 225
	172	[248]	NEWTABLE 	8 0 0
	173	[248]	MOVE     	3 8
	174	[249]	LOADNIL  	6 6
	175	[249]	JMP      	-122	; to 54
	176	[252]	SELF     	8 7 -7	; "match"
	177	[252]	LOADK    	10 -47	; "^#"
	178	[252]	CALL     	8 3 2
	179	[252]	TEST     	8 0 1
	180	[252]	JMP      	37	; to 218
	181	[254]	SELF     	8 7 -7	; "match"
	182	[254]	LOADK    	10 -48	; "^%s*([%a_%[%]0-9]+)%s+\"(.*)\"%s*$"
	183	[254]	CALL     	8 3 3
	184	[255]	TEST     	8 0 0
	185	[255]	JMP      	2	; to 188
	186	[256]	MOVE     	6 8
	187	[256]	JMP      	4	; to 192
	188	[259]	SELF     	10 7 -7	; "match"
	189	[259]	LOADK    	12 -49	; "^%s*\"(.*)\"%s*$"
	190	[259]	CALL     	10 3 2
	191	[259]	MOVE     	9 10
	192	[261]	TEST     	6 0 0
	193	[261]	JMP      	22	; to 216
	194	[261]	TEST     	9 0 0
	195	[261]	JMP      	20	; to 216
	196	[261]	TEST     	4 0 1
	197	[261]	JMP      	18	; to 216
	198	[263]	SELF     	10 9 -50	; "gsub"
	199	[263]	LOADK    	12 -51	; "\\n"
	200	[263]	LOADK    	13 -52	; "\n"
	201	[263]	CALL     	10 4 2
	202	[263]	MOVE     	9 10
	203	[265]	SELF     	10 9 -50	; "gsub"
	204	[265]	LOADK    	12 -53	; "\\\""
	205	[265]	LOADK    	13 -54	; "\""
	206	[265]	CALL     	10 4 2
	207	[265]	MOVE     	9 10
	208	[266]	GETTABLE 	10 3 6
	209	[266]	TEST     	10 0 1
	210	[266]	JMP      	1	; to 212
	211	[266]	LOADK    	10 -6	; ""
	212	[266]	MOVE     	11 9
	213	[266]	CONCAT   	10 10 11
	214	[266]	SETTABLE 	3 6 10
	215	[266]	JMP      	-162	; to 54
	216	[269]	LOADBOOL 	4 0 0
	217	[270]	JMP      	-164	; to 54
	218	[271]	SELF     	8 7 -7	; "match"
	219	[271]	LOADK    	10 -55	; "#, fuzzy"
	220	[271]	CALL     	8 3 2
	221	[271]	TEST     	8 0 0
	222	[271]	JMP      	-169	; to 54
	223	[272]	LOADBOOL 	4 1 0
	224	[274]	JMP      	-171	; to 54
	225	[276]	GETUPVAL 	7 0	; GetText
	226	[276]	SETTABLE 	7 -3 0	; "current_lang" -
	227	[277]	RETURN   	0 1

function <./frontend/gettext.lua:310,318> (40 instructions, 160 bytes at 0x7fe9cbc09a60)
3 params, 6 slots, 1 upvalue, 4 locals, 4 constants, 0 functions
	1	[311]	GETUPVAL 	3 0	; GetText
	2	[311]	GETTABLE 	3 3 -1	; "getPlural"
	3	[311]	MOVE     	4 2
	4	[311]	CALL     	3 2 2
	5	[313]	EQ       	0 3 -2	; - 0
	6	[313]	JMP      	17	; to 24
	7	[314]	GETUPVAL 	4 0	; GetText
	8	[314]	GETTABLE 	4 4 -3	; "translation"
	9	[314]	GETTABLE 	4 4 0
	10	[314]	TEST     	4 0 0
	11	[314]	JMP      	6	; to 18
	12	[314]	GETUPVAL 	4 0	; GetText
	13	[314]	GETTABLE 	4 4 -3	; "translation"
	14	[314]	GETTABLE 	4 4 0
	15	[314]	GETTABLE 	4 4 3
	16	[314]	TEST     	4 0 1
	17	[314]	JMP      	4	; to 22
	18	[314]	GETUPVAL 	4 0	; GetText
	19	[314]	GETTABLE 	4 4 -4	; "wrapUntranslated"
	20	[314]	MOVE     	5 0
	21	[314]	CALL     	4 2 2
	22	[314]	RETURN   	4 2
	23	[314]	JMP      	16	; to 40
	24	[316]	GETUPVAL 	4 0	; GetText
	25	[316]	GETTABLE 	4 4 -3	; "translation"
	26	[316]	GETTABLE 	4 4 0
	27	[316]	TEST     	4 0 0
	28	[316]	JMP      	6	; to 35
	29	[316]	GETUPVAL 	4 0	; GetText
	30	[316]	GETTABLE 	4 4 -3	; "translation"
	31	[316]	GETTABLE 	4 4 0
	32	[316]	GETTABLE 	4 4 3
	33	[316]	TEST     	4 0 1
	34	[316]	JMP      	4	; to 39
	35	[316]	GETUPVAL 	4 0	; GetText
	36	[316]	GETTABLE 	4 4 -4	; "wrapUntranslated"
	37	[316]	MOVE     	5 1
	38	[316]	CALL     	4 2 2
	39	[316]	RETURN   	4 2
	40	[318]	RETURN   	0 1

function <./frontend/gettext.lua:343,351> (54 instructions, 216 bytes at 0x7fe9cbc09ce0)
4 params, 7 slots, 1 upvalue, 5 locals, 4 constants, 0 functions
	1	[344]	GETUPVAL 	4 0	; GetText
	2	[344]	GETTABLE 	4 4 -1	; "getPlural"
	3	[344]	MOVE     	5 3
	4	[344]	CALL     	4 2 2
	5	[346]	EQ       	0 4 -2	; - 0
	6	[346]	JMP      	24	; to 31
	7	[347]	GETUPVAL 	5 0	; GetText
	8	[347]	GETTABLE 	5 5 -3	; "context"
	9	[347]	GETTABLE 	5 5 0
	10	[347]	TEST     	5 0 0
	11	[347]	JMP      	13	; to 25
	12	[347]	GETUPVAL 	5 0	; GetText
	13	[347]	GETTABLE 	5 5 -3	; "context"
	14	[347]	GETTABLE 	5 5 0
	15	[347]	GETTABLE 	5 5 1
	16	[347]	TEST     	5 0 0
	17	[347]	JMP      	7	; to 25
	18	[347]	GETUPVAL 	5 0	; GetText
	19	[347]	GETTABLE 	5 5 -3	; "context"
	20	[347]	GETTABLE 	5 5 0
	21	[347]	GETTABLE 	5 5 1
	22	[347]	GETTABLE 	5 5 4
	23	[347]	TEST     	5 0 1
	24	[347]	JMP      	4	; to 29
	25	[347]	GETUPVAL 	5 0	; GetText
	26	[347]	GETTABLE 	5 5 -4	; "wrapUntranslated"
	27	[347]	MOVE     	6 1
	28	[347]	CALL     	5 2 2
	29	[347]	RETURN   	5 2
	30	[347]	JMP      	23	; to 54
	31	[349]	GETUPVAL 	5 0	; GetText
	32	[349]	GETTABLE 	5 5 -3	; "context"
	33	[349]	GETTABLE 	5 5 0
	34	[349]	TEST     	5 0 0
	35	[349]	JMP      	13	; to 49
	36	[349]	GETUPVAL 	5 0	; GetText
	37	[349]	GETTABLE 	5 5 -3	; "context"
	38	[349]	GETTABLE 	5 5 0
	39	[349]	GETTABLE 	5 5 1
	40	[349]	TEST     	5 0 0
	41	[349]	JMP      	7	; to 49
	42	[349]	GETUPVAL 	5 0	; GetText
	43	[349]	GETTABLE 	5 5 -3	; "context"
	44	[349]	GETTABLE 	5 5 0
	45	[349]	GETTABLE 	5 5 1
	46	[349]	GETTABLE 	5 5 4
	47	[349]	TEST     	5 0 1
	48	[349]	JMP      	4	; to 53
	49	[349]	GETUPVAL 	5 0	; GetText
	50	[349]	GETTABLE 	5 5 -4	; "wrapUntranslated"
	51	[349]	MOVE     	6 2
	52	[349]	CALL     	5 2 2
	53	[349]	RETURN   	5 2
	54	[351]	RETURN   	0 1

function <./frontend/gettext.lua:379,381> (17 instructions, 68 bytes at 0x7fe9cbc09ef0)
2 params, 4 slots, 1 upvalue, 2 locals, 2 constants, 0 functions
	1	[380]	GETUPVAL 	2 0	; GetText
	2	[380]	GETTABLE 	2 2 -1	; "context"
	3	[380]	GETTABLE 	2 2 0
	4	[380]	TEST     	2 0 0
	5	[380]	JMP      	6	; to 12
	6	[380]	GETUPVAL 	2 0	; GetText
	7	[380]	GETTABLE 	2 2 -1	; "context"
	8	[380]	GETTABLE 	2 2 0
	9	[380]	GETTABLE 	2 2 1
	10	[380]	TEST     	2 0 1
	11	[380]	JMP      	4	; to 16
	12	[380]	GETUPVAL 	2 0	; GetText
	13	[380]	GETTABLE 	2 2 -2	; "wrapUntranslated"
	14	[380]	MOVE     	3 1
	15	[380]	CALL     	2 2 2
	16	[380]	RETURN   	2 2
	17	[381]	RETURN   	0 1
