-- BYTECODE -- goodreadsbook.lua:37-39
0001    KSTR     0   0      ; "ui"
0002    UGET     1   0      ; self
0003    TGETS    1   1   1  ; "dimen"
0004    RET      0   3

-- BYTECODE -- goodreadsbook.lua:31-48
0001    UGET     1   0      ; Font
0002    MOV      2   1
0003    TGETS    1   1   1  ; "getFace"
0004    KSTR     3   2      ; "smallffont"
0005    CALL     1   2   3
0006    TSETS    1   0   0  ; "small_font_face"
0007    UGET     1   0      ; Font
0008    MOV      2   1
0009    TGETS    1   1   1  ; "getFace"
0010    KSTR     3   4      ; "ffont"
0011    CALL     1   2   3
0012    TSETS    1   0   3  ; "medium_font_face"
0013    UGET     1   0      ; Font
0014    MOV      2   1
0015    TGETS    1   1   1  ; "getFace"
0016    KSTR     3   6      ; "largeffont"
0017    CALL     1   2   3
0018    TSETS    1   0   5  ; "large_font_face"
0019    UGET     1   1      ; Screen
0020    MOV      2   1
0021    TGETS    1   1   8  ; "getWidth"
0022    CALL     1   2   2
0023    TSETS    1   0   7  ; "screen_width"
0024    UGET     1   1      ; Screen
0025    MOV      2   1
0026    TGETS    1   1  10  ; "getHeight"
0027    CALL     1   2   2
0028    TSETS    1   0   9  ; "screen_height"
0029    UGET     1   2      ; UIManager
0030    MOV      2   1
0031    TGETS    1   1  11  ; "setDirty"
0032    MOV      3   0
0033    FNEW     4  12      ; goodreadsbook.lua:37
0034    CALL     1   1   4
0035    UGET     1   3      ; FrameContainer
0036    MOV      2   1
0037    TGETS    1   1  13  ; "new"
0038    TDUP     3  14
0039    TGETS    4   0   7  ; "screen_width"
0040    TSETS    4   3  15  ; "width"
0041    TGETS    4   0   9  ; "screen_height"
0042    TSETS    4   3  16  ; "height"
0043    UGET     4   4      ; Blitbuffer
0044    TGETS    4   4  17  ; "COLOR_WHITE"
0045    TSETS    4   3  18  ; "background"
0046    MOV      5   0
0047    TGETS    4   0  19  ; "getStatusContent"
0048    TGETS    6   0   7  ; "screen_width"
0049    CALL     4   0   3
0050    TSETM    4   0      ; 1
0051    CALL     1   2   3
0052    TSETB    1   0   1
0053    UCLO     0 => 0054
0054 => RET0     0   1

-- BYTECODE -- goodreadsbook.lua:50-62
0001    UGET     2   0      ; VerticalGroup
0002    MOV      3   2
0003    TGETS    2   2   0  ; "new"
0004    TDUP     4   1
0005    UGET     5   1      ; OverlapGroup
0006    MOV      6   5
0007    TGETS    5   5   0  ; "new"
0008    TDUP     7   7
0009    UGET     8   2      ; Geom
0010    MOV      9   8
0011    TGETS    8   8   0  ; "new"
0012    TDUP    10   2
0013    TSETS    1  10   3  ; "w"
0014    UGET    11   3      ; Size
0015    TGETS   11  11   4  ; "item"
0016    TGETS   11  11   5  ; "height_default"
0017    TSETS   11  10   6  ; "h"
0018    CALL     8   2   3
0019    TSETS    8   7   8  ; "dimen"
0020    UGET     8   4      ; CloseButton
0021    MOV      9   8
0022    TGETS    8   8   0  ; "new"
0023    TDUP    10   9
0024    TSETS    0  10  10  ; "window"
0025    CALL     8   0   3
0026    TSETM    8   0      ; 1
0027    CALL     5   2   3
0028    TSETB    5   4   1
0029    MOV      6   0
0030    TGETS    5   0  11  ; "genHeader"
0031    UGET     7   5      ; _
0032    KSTR     8  12      ; "Book info"
0033    CALL     7   0   2
0034    CALLM    5   2   1
0035    TSETB    5   4   2
0036    MOV      6   0
0037    TGETS    5   0  13  ; "genBookInfoGroup"
0038    CALL     5   2   2
0039    TSETB    5   4   3
0040    MOV      6   0
0041    TGETS    5   0  11  ; "genHeader"
0042    UGET     7   5      ; _
0043    KSTR     8  14      ; "Review"
0044    CALL     7   0   2
0045    CALLM    5   2   1
0046    TSETB    5   4   4
0047    MOV      6   0
0048    TGETS    5   0  15  ; "bookReview"
0049    CALL     5   0   2
0050    TSETM    5   1      ; 5
0051    CALLT    2   3

-- BYTECODE -- goodreadsbook.lua:64-97
0001    UGET     2   0      ; TextWidget
0002    MOV      3   2
0003    TGETS    2   2   0  ; "new"
0004    TDUP     4   1
0005    TSETS    1   4   2  ; "text"
0006    TGETS    5   0   3  ; "medium_font_face"
0007    TSETS    5   4   4  ; "face"
0008    UGET     5   1      ; Blitbuffer
0009    TGETS    5   5   5  ; "COLOR_WEB_GRAY"
0010    TSETS    5   4   6  ; "fgcolor"
0011    CALL     2   2   3
0012    UGET     3   2      ; HorizontalSpan
0013    MOV      4   3
0014    TGETS    3   3   0  ; "new"
0015    TDUP     5   8
0016    TGETS    6   0   7  ; "padding"
0017    TSETS    6   5   9  ; "width"
0018    CALL     3   2   3
0019    TGETS    4   0  10  ; "screen_width"
0020    MOV      6   2
0021    TGETS    5   2  11  ; "getSize"
0022    CALL     5   2   2
0023    TGETS    5   5  12  ; "w"
0024    SUBVV    4   4   5
0025    DIVVN    4   4   0  ; 2
0026    TGETS    5   0   7  ; "padding"
0027    MULVN    5   5   0  ; 2
0028    SUBVV    4   4   5
0029    UGET     5   3      ; LeftContainer
0030    MOV      6   5
0031    TGETS    5   5   0  ; "new"
0032    TDUP     7  16
0033    UGET     8   4      ; Geom
0034    MOV      9   8
0035    TGETS    8   8   0  ; "new"
0036    TDUP    10  13
0037    TSETS    4  10  12  ; "w"
0038    TGETS   11   0  14  ; "screen_height"
0039    DIVVN   11  11   1  ; 25
0040    TSETS   11  10  15  ; "h"
0041    CALL     8   2   3
0042    TSETS    8   7  17  ; "dimen"
0043    UGET     8   5      ; LineWidget
0044    MOV      9   8
0045    TGETS    8   8   0  ; "new"
0046    TDUP    10  19
0047    UGET    11   1      ; Blitbuffer
0048    TGETS   11  11  18  ; "COLOR_LIGHT_GRAY"
0049    TSETS   11  10  20  ; "background"
0050    UGET    11   4      ; Geom
0051    MOV     12  11
0052    TGETS   11  11   0  ; "new"
0053    TDUP    13  21
0054    TSETS    4  13  12  ; "w"
0055    UGET    14   6      ; Size
0056    TGETS   14  14  22  ; "line"
0057    TGETS   14  14  23  ; "thick"
0058    TSETS   14  13  15  ; "h"
0059    CALL    11   2   3
0060    TSETS   11  10  17  ; "dimen"
0061    CALL     8   0   3
0062    TSETM    8   2      ; 1
0063    CALL     5   2   3
0064    UGET     6   7      ; VerticalGroup
0065    MOV      7   6
0066    TGETS    6   6   0  ; "new"
0067    TNEW     8   4
0068    UGET     9   8      ; VerticalSpan
0069    MOV     10   9
0070    TGETS    9   9   0  ; "new"
0071    TDUP    11  26
0072    UGET    12   6      ; Size
0073    TGETS   12  12  24  ; "span"
0074    TGETS   12  12  25  ; "vertical_large"
0075    TSETS   12  11   9  ; "width"
0076    CALL     9   2   3
0077    TSETB    9   8   1
0078    UGET     9   9      ; HorizontalGroup
0079    MOV     10   9
0080    TGETS    9   9   0  ; "new"
0081    TDUP    11  27
0082    TSETB    3  11   1
0083    TSETB    5  11   2
0084    TSETB    3  11   3
0085    TSETB    2  11   4
0086    TSETB    3  11   5
0087    TSETB    5  11   6
0088    TSETB    3  11   7
0089    CALL     9   2   3
0090    TSETB    9   8   2
0091    UGET     9   8      ; VerticalSpan
0092    MOV     10   9
0093    TGETS    9   9   0  ; "new"
0094    TDUP    11  28
0095    UGET    12   6      ; Size
0096    TGETS   12  12  24  ; "span"
0097    TGETS   12  12  25  ; "vertical_large"
0098    TSETS   12  11   9  ; "width"
0099    CALL     9   0   3
0100    TSETM    9   3      ; 3
0101    CALLT    6   3

-- BYTECODE -- goodreadsbook.lua:99-224
0001    TGETS    1   0   0  ; "screen_width"
0002    MULVN    1   1   0  ; 0.05
0003    KNIL     2   3
0004    UGET     4   0      ; Screen
0005    MOV      5   4
0006    TGETS    4   4   1  ; "getScreenMode"
0007    CALL     4   2   2
0008    ISNES    4   2      ; "landscape"
0009    JMP      4 => 0023
0010    UGET     4   0      ; Screen
0011    MOV      5   4
0012    TGETS    4   4   3  ; "scaleBySize"
0013    KSHORT   6 132
0014    CALL     4   2   3
0015    MOV      2   4
0016    UGET     4   0      ; Screen
0017    MOV      5   4
0018    TGETS    4   4   3  ; "scaleBySize"
0019    KSHORT   6 184
0020    CALL     4   2   3
0021    MOV      3   4
0022    JMP      4 => 0035
0023 => UGET     4   0      ; Screen
0024    MOV      5   4
0025    TGETS    4   4   3  ; "scaleBySize"
0026    KSHORT   6 198
0027    CALL     4   2   3
0028    MOV      2   4
0029    UGET     4   0      ; Screen
0030    MOV      5   4
0031    TGETS    4   4   3  ; "scaleBySize"
0032    KSHORT   6 276
0033    CALL     4   2   3
0034    MOV      3   4
0035 => MOV      4   3
0036    TGETS    5   0   0  ; "screen_width"
0037    MULNV    6   1   1  ; 1.5
0038    SUBVV    5   5   6
0039    SUBVV    5   5   2
0040    UGET     6   1      ; VerticalGroup
0041    MOV      7   6
0042    TGETS    6   6   4  ; "new"
0043    TDUP     8   5
0044    UGET     9   2      ; TextBoxWidget
0045    MOV     10   9
0046    TGETS    9   9   4  ; "new"
0047    TDUP    11   8
0048    TGETS   12   0   6  ; "dates"
0049    TGETS   12  12   7  ; "title"
0050    TSETS   12  11   9  ; "text"
0051    TGETS   12   0  10  ; "medium_font_face"
0052    TSETS   12  11  11  ; "face"
0053    UGET    12   3      ; Size
0054    TGETS   12  12  12  ; "padding"
0055    TGETS   12  12  13  ; "small"
0056    TSETS   12  11  12  ; "padding"
0057    TSETS    5  11  14  ; "width"
0058    CALL     9   0   3
0059    TSETM    9   2      ; 1
0060    CALL     6   2   3
0061    UGET     7   2      ; TextBoxWidget
0062    MOV      8   7
0063    TGETS    7   7   4  ; "new"
0064    TDUP     9  16
0065    TGETS   10   0   6  ; "dates"
0066    TGETS   10  10  15  ; "author"
0067    TSETS   10   9   9  ; "text"
0068    TSETS    5   9  14  ; "width"
0069    TGETS   10   0  17  ; "large_font_face"
0070    TSETS   10   9  11  ; "face"
0071    CALL     7   2   3
0072    GGET     8  18      ; "table"
0073    TGETS    8   8  19  ; "insert"
0074    MOV      9   6
0075    UGET    10   4      ; CenterContainer
0076    MOV     11  10
0077    TGETS   10  10   4  ; "new"
0078    TDUP    12  24
0079    UGET    13   5      ; Geom
0080    MOV     14  13
0081    TGETS   13  13   4  ; "new"
0082    TDUP    15  20
0083    TSETS    5  15  21  ; "w"
0084    MOV     17   7
0085    TGETS   16   7  22  ; "getSize"
0086    CALL    16   2   2
0087    TGETS   16  16  23  ; "h"
0088    TSETS   16  15  23  ; "h"
0089    CALL    13   2   3
0090    TSETS   13  12  25  ; "dimen"
0091    TSETB    7  12   1
0092    CALL    10   0   3
0093    CALLM    8   1   1
0094    UGET     8   6      ; VerticalSpan
0095    MOV      9   8
0096    TGETS    8   8   4  ; "new"
0097    TDUP    10  26
0098    MULVN   11   4   3  ; 0.1
0099    TSETS   11  10  14  ; "width"
0100    CALL     8   2   3
0101    GGET     9  18      ; "table"
0102    TGETS    9   9  19  ; "insert"
0103    MOV     10   6
0104    UGET    11   4      ; CenterContainer
0105    MOV     12  11
0106    TGETS   11  11   4  ; "new"
0107    TDUP    13  28
0108    UGET    14   5      ; Geom
0109    MOV     15  14
0110    TGETS   14  14   4  ; "new"
0111    TDUP    16  27
0112    TSETS    5  16  21  ; "w"
0113    UGET    17   0      ; Screen
0114    MOV     18  17
0115    TGETS   17  17   3  ; "scaleBySize"
0116    KSHORT  19  10
0117    CALL    17   2   3
0118    TSETS   17  16  23  ; "h"
0119    CALL    14   2   3
0120    TSETS   14  13  25  ; "dimen"
0121    TSETB    8  13   1
0122    CALL    11   0   3
0123    CALLM    9   1   1
0124    UGET     9   7      ; TextWidget
0125    MOV     10   9
0126    TGETS    9   9   4  ; "new"
0127    TDUP    11  31
0128    UGET    12   8      ; T
0129    UGET    13   9      ; _
0130    KSTR    14  29      ; "Series: %1"
0131    CALL    13   2   2
0132    TGETS   14   0   6  ; "dates"
0133    TGETS   14  14  30  ; "series"
0134    CALL    12   2   3
0135    TSETS   12  11   9  ; "text"
0136    TGETS   12   0  32  ; "small_font_face"
0137    TSETS   12  11  11  ; "face"
0138    UGET    12   3      ; Size
0139    TGETS   12  12  12  ; "padding"
0140    TGETS   12  12  13  ; "small"
0141    TSETS   12  11  12  ; "padding"
0142    CALL     9   2   3
0143    GGET    10  18      ; "table"
0144    TGETS   10  10  19  ; "insert"
0145    MOV     11   6
0146    UGET    12   4      ; CenterContainer
0147    MOV     13  12
0148    TGETS   12  12   4  ; "new"
0149    TDUP    14  34
0150    UGET    15   5      ; Geom
0151    MOV     16  15
0152    TGETS   15  15   4  ; "new"
0153    TDUP    17  33
0154    TSETS    5  17  21  ; "w"
0155    MOV     19   9
0156    TGETS   18   9  22  ; "getSize"
0157    CALL    18   2   2
0158    TGETS   18  18  23  ; "h"
0159    TSETS   18  17  23  ; "h"
0160    CALL    15   2   3
0161    TSETS   15  14  25  ; "dimen"
0162    TSETB    9  14   1
0163    CALL    12   0   3
0164    CALLM   10   1   1
0165    UGET    10   7      ; TextWidget
0166    MOV     11  10
0167    TGETS   10  10   4  ; "new"
0168    TDUP    12  37
0169    UGET    13   8      ; T
0170    UGET    14   9      ; _
0171    KSTR    15  35      ; "Rating: %1"
0172    CALL    14   2   2
0173    TGETS   15   0   6  ; "dates"
0174    TGETS   15  15  36  ; "rating"
0175    CALL    13   2   3
0176    TSETS   13  12   9  ; "text"
0177    TGETS   13   0  32  ; "small_font_face"
0178    TSETS   13  12  11  ; "face"
0179    UGET    13   3      ; Size
0180    TGETS   13  13  12  ; "padding"
0181    TGETS   13  13  13  ; "small"
0182    TSETS   13  12  12  ; "padding"
0183    CALL    10   2   3
0184    GGET    11  18      ; "table"
0185    TGETS   11  11  19  ; "insert"
0186    MOV     12   6
0187    UGET    13   4      ; CenterContainer
0188    MOV     14  13
0189    TGETS   13  13   4  ; "new"
0190    TDUP    15  39
0191    UGET    16   5      ; Geom
0192    MOV     17  16
0193    TGETS   16  16   4  ; "new"
0194    TDUP    18  38
0195    TSETS    5  18  21  ; "w"
0196    MOV     20  10
0197    TGETS   19  10  22  ; "getSize"
0198    CALL    19   2   2
0199    TGETS   19  19  23  ; "h"
0200    TSETS   19  18  23  ; "h"
0201    CALL    16   2   3
0202    TSETS   16  15  25  ; "dimen"
0203    TSETB   10  15   1
0204    CALL    13   0   3
0205    CALLM   11   1   1
0206    UGET    11   7      ; TextWidget
0207    MOV     12  11
0208    TGETS   11  11   4  ; "new"
0209    TDUP    13  42
0210    UGET    14   8      ; T
0211    UGET    15   9      ; _
0212    KSTR    16  40      ; "Pages: %1"
0213    CALL    15   2   2
0214    TGETS   16   0   6  ; "dates"
0215    TGETS   16  16  41  ; "pages"
0216    CALL    14   2   3
0217    TSETS   14  13   9  ; "text"
0218    TGETS   14   0  32  ; "small_font_face"
0219    TSETS   14  13  11  ; "face"
0220    UGET    14   3      ; Size
0221    TGETS   14  14  12  ; "padding"
0222    TGETS   14  14  13  ; "small"
0223    TSETS   14  13  12  ; "padding"
0224    CALL    11   2   3
0225    GGET    12  18      ; "table"
0226    TGETS   12  12  19  ; "insert"
0227    MOV     13   6
0228    UGET    14   4      ; CenterContainer
0229    MOV     15  14
0230    TGETS   14  14   4  ; "new"
0231    TDUP    16  44
0232    UGET    17   5      ; Geom
0233    MOV     18  17
0234    TGETS   17  17   4  ; "new"
0235    TDUP    19  43
0236    TSETS    5  19  21  ; "w"
0237    MOV     21  11
0238    TGETS   20  11  22  ; "getSize"
0239    CALL    20   2   2
0240    TGETS   20  20  23  ; "h"
0241    TSETS   20  19  23  ; "h"
0242    CALL    17   2   3
0243    TSETS   17  16  25  ; "dimen"
0244    TSETB   11  16   1
0245    CALL    14   0   3
0246    CALLM   12   1   1
0247    UGET    12   7      ; TextWidget
0248    MOV     13  12
0249    TGETS   12  12   4  ; "new"
0250    TDUP    14  47
0251    UGET    15   8      ; T
0252    UGET    16   9      ; _
0253    KSTR    17  45      ; "Release date: %1"
0254    CALL    16   2   2
0255    TGETS   17   0   6  ; "dates"
0256    TGETS   17  17  46  ; "release"
0257    CALL    15   2   3
0258    TSETS   15  14   9  ; "text"
0259    TGETS   15   0  32  ; "small_font_face"
0260    TSETS   15  14  11  ; "face"
0261    UGET    15   3      ; Size
0262    TGETS   15  15  12  ; "padding"
0263    TGETS   15  15  13  ; "small"
0264    TSETS   15  14  12  ; "padding"
0265    CALL    12   2   3
0266    GGET    13  18      ; "table"
0267    TGETS   13  13  19  ; "insert"
0268    MOV     14   6
0269    UGET    15   4      ; CenterContainer
0270    MOV     16  15
0271    TGETS   15  15   4  ; "new"
0272    TDUP    17  49
0273    UGET    18   5      ; Geom
0274    MOV     19  18
0275    TGETS   18  18   4  ; "new"
0276    TDUP    20  48
0277    TSETS    5  20  21  ; "w"
0278    MOV     22  12
0279    TGETS   21  12  22  ; "getSize"
0280    CALL    21   2   2
0281    TGETS   21  21  23  ; "h"
0282    TSETS   21  20  23  ; "h"
0283    CALL    18   2   3
0284    TSETS   18  17  25  ; "dimen"
0285    TSETB   12  17   1
0286    CALL    15   0   3
0287    CALLM   13   1   1
0288    UGET    13  10      ; HorizontalGroup
0289    MOV     14  13
0290    TGETS   13  13   4  ; "new"
0291    TDUP    15  50
0292    UGET    16  11      ; HorizontalSpan
0293    MOV     17  16
0294    TGETS   16  16   4  ; "new"
0295    TDUP    18  51
0296    TSETS    1  18  14  ; "width"
0297    CALL    16   0   3
0298    TSETM   16   2      ; 1
0299    CALL    13   2   3
0300    UGET    14  12      ; https
0301    TGETS   14  14  52  ; "request"
0302    TGETS   15   0   6  ; "dates"
0303    TGETS   15  15  53  ; "image"
0304    CALL    14   2   2
0305    KPRI    15   0
0306    ISF         14
0307    JMP     16 => 0318
0308    UGET    16  13      ; RenderImage
0309    MOV     17  16
0310    TGETS   16  16  54  ; "renderImageData"
0311    MOV     18  14
0312    LEN     19  14
0313    KPRI    20   1
0314    MOV     21   2
0315    MOV     22   3
0316    CALL    16   2   7
0317    MOV     15  16
0318 => ISF         15
0319    JMP     16 => 0331
0320    GGET    16  18      ; "table"
0321    TGETS   16  16  19  ; "insert"
0322    MOV     17  13
0323    UGET    18  14      ; ImageWidget
0324    MOV     19  18
0325    TGETS   18  18   4  ; "new"
0326    TDUP    20  55
0327    TSETS   15  20  53  ; "image"
0328    CALL    18   0   3
0329    CALLM   16   1   1
0330    JMP     16 => 0342
0331 => GGET    16  18      ; "table"
0332    TGETS   16  16  19  ; "insert"
0333    MOV     17  13
0334    UGET    18  14      ; ImageWidget
0335    MOV     19  18
0336    TGETS   18  18   4  ; "new"
0337    TDUP    20  56
0338    TSETS    2  20  14  ; "width"
0339    TSETS    3  20  57  ; "height"
0340    CALL    18   0   3
0341    CALLM   16   1   1
0342 => UGET    16  10      ; HorizontalGroup
0343    MOV     17  16
0344    TGETS   16  16   4  ; "new"
0345    TDUP    18  58
0346    UGET    19  11      ; HorizontalSpan
0347    MOV     20  19
0348    TGETS   19  19   4  ; "new"
0349    TDUP    21  59
0350    DIVVN   22   1   4  ; 2
0351    TSETS   22  21  14  ; "width"
0352    CALL    19   0   3
0353    TSETM   19   2      ; 1
0354    CALL    16   2   3
0355    GGET    17  18      ; "table"
0356    TGETS   17  17  19  ; "insert"
0357    MOV     18  13
0358    MOV     19  16
0359    CALL    17   1   3
0360    GGET    17  18      ; "table"
0361    TGETS   17  17  19  ; "insert"
0362    MOV     18  13
0363    UGET    19   4      ; CenterContainer
0364    MOV     20  19
0365    TGETS   19  19   4  ; "new"
0366    TDUP    21  61
0367    UGET    22   5      ; Geom
0368    MOV     23  22
0369    TGETS   22  22   4  ; "new"
0370    TDUP    24  60
0371    TSETS    5  24  21  ; "w"
0372    TSETS    4  24  23  ; "h"
0373    CALL    22   2   3
0374    TSETS   22  21  25  ; "dimen"
0375    TSETB    6  21   1
0376    CALL    19   0   3
0377    CALLM   17   1   1
0378    UGET    17   4      ; CenterContainer
0379    MOV     18  17
0380    TGETS   17  17   4  ; "new"
0381    TDUP    19  64
0382    UGET    20   5      ; Geom
0383    MOV     21  20
0384    TGETS   20  20   4  ; "new"
0385    TDUP    22  62
0386    TGETS   23   0   0  ; "screen_width"
0387    TSETS   23  22  21  ; "w"
0388    TGETS   23   0  63  ; "screen_height"
0389    MULVN   23  23   5  ; 0.35
0390    TSETS   23  22  23  ; "h"
0391    CALL    20   2   3
0392    TSETS   20  19  25  ; "dimen"
0393    TSETB   13  19   1
0394    CALLT   17   3

-- BYTECODE -- goodreadsbook.lua:226-256
0001    KSTR     1   0      ; "        @page {\n            margin: 0;\"~
0002    UGET     2   0      ; VerticalGroup
0003    MOV      3   2
0004    TGETS    2   2   1  ; "new"
0005    TDUP     4   2
0006    UGET     5   1      ; ScrollHtmlWidget
0007    MOV      6   5
0008    TGETS    5   5   1  ; "new"
0009    TDUP     7   5
0010    TGETS    8   0   3  ; "dates"
0011    TGETS    8   8   4  ; "description"
0012    TSETS    8   7   6  ; "html_body"
0013    TSETS    1   7   7  ; "css"
0014    TGETS    8   0   8  ; "screen_width"
0015    MULVN    8   8   0  ; 0.9
0016    TSETS    8   7   9  ; "width"
0017    TGETS    8   0  10  ; "screen_height"
0018    MULVN    8   8   1  ; 0.48
0019    TSETS    8   7  11  ; "height"
0020    TSETS    0   7  12  ; "dialog"
0021    CALL     5   0   3
0022    TSETM    5   2      ; 1
0023    CALL     2   2   3
0024    UGET     3   2      ; CenterContainer
0025    MOV      4   3
0026    TGETS    3   3   1  ; "new"
0027    TDUP     5  16
0028    UGET     6   3      ; Geom
0029    MOV      7   6
0030    TGETS    6   6   1  ; "new"
0031    TDUP     8  13
0032    TGETS    9   0   8  ; "screen_width"
0033    TSETS    9   8  14  ; "w"
0034    TGETS    9   0  10  ; "screen_height"
0035    MULVN    9   9   3  ; 0.5
0036    TSETS    9   8  15  ; "h"
0037    CALL     6   2   3
0038    TSETS    6   5  17  ; "dimen"
0039    TSETB    2   5   1
0040    CALLT    3   3

-- BYTECODE -- goodreadsbook.lua:258-260
0001    MOV      2   0
0002    TGETS    1   0   0  ; "onClose"
0003    CALLT    1   2

-- BYTECODE -- goodreadsbook.lua:262-265
0001    UGET     1   0      ; UIManager
0002    MOV      2   1
0003    TGETS    1   1   0  ; "close"
0004    MOV      3   0
0005    KSTR     4   1      ; "flashui"
0006    CALL     1   1   4
0007    KPRI     1   2
0008    RET1     1   2

-- BYTECODE -- goodreadsbook.lua:0-268
0001    GGET     0   0      ; "require"
0002    KSTR     1   1      ; "ffi/blitbuffer"
0003    CALL     0   2   2
0004    GGET     1   0      ; "require"
0005    KSTR     2   2      ; "ui/widget/container/centercontainer"
0006    CALL     1   2   2
0007    GGET     2   0      ; "require"
0008    KSTR     3   3      ; "ui/widget/closebutton"
0009    CALL     2   2   2
0010    GGET     3   0      ; "require"
0011    KSTR     4   4      ; "ui/widget/container/framecontainer"
0012    CALL     3   2   2
0013    GGET     4   0      ; "require"
0014    KSTR     5   5      ; "ui/geometry"
0015    CALL     4   2   2
0016    GGET     5   0      ; "require"
0017    KSTR     6   6      ; "ui/font"
0018    CALL     5   2   2
0019    GGET     6   0      ; "require"
0020    KSTR     7   7      ; "ui/widget/horizontalgroup"
0021    CALL     6   2   2
0022    GGET     7   0      ; "require"
0023    KSTR     8   8      ; "ui/widget/horizontalspan"
0024    CALL     7   2   2
0025    GGET     8   0      ; "require"
0026    KSTR     9   9      ; "ui/widget/imagewidget"
0027    CALL     8   2   2
0028    GGET     9   0      ; "require"
0029    KSTR    10  10      ; "ui/widget/container/inputcontainer"
0030    CALL     9   2   2
0031    GGET    10   0      ; "require"
0032    KSTR    11  11      ; "ui/widget/container/leftcontainer"
0033    CALL    10   2   2
0034    GGET    11   0      ; "require"
0035    KSTR    12  12      ; "ui/widget/linewidget"
0036    CALL    11   2   2
0037    GGET    12   0      ; "require"
0038    KSTR    13  13      ; "ui/widget/overlapgroup"
0039    CALL    12   2   2
0040    GGET    13   0      ; "require"
0041    KSTR    14  14      ; "ui/renderimage"
0042    CALL    13   2   2
0043    GGET    14   0      ; "require"
0044    KSTR    15  15      ; "ui/widget/scrollhtmlwidget"
0045    CALL    14   2   2
0046    GGET    15   0      ; "require"
0047    KSTR    16  16      ; "ui/size"
0048    CALL    15   2   2
0049    GGET    16   0      ; "require"
0050    KSTR    17  17      ; "ui/widget/textboxwidget"
0051    CALL    16   2   2
0052    GGET    17   0      ; "require"
0053    KSTR    18  18      ; "ui/widget/textwidget"
0054    CALL    17   2   2
0055    GGET    18   0      ; "require"
0056    KSTR    19  19      ; "ui/uimanager"
0057    CALL    18   2   2
0058    GGET    19   0      ; "require"
0059    KSTR    20  20      ; "ui/widget/verticalgroup"
0060    CALL    19   2   2
0061    GGET    20   0      ; "require"
0062    KSTR    21  21      ; "ui/widget/verticalspan"
0063    CALL    20   2   2
0064    GGET    21   0      ; "require"
0065    KSTR    22  22      ; "ssl.https"
0066    CALL    21   2   2
0067    GGET    22   0      ; "require"
0068    KSTR    23  23      ; "gettext"
0069    CALL    22   2   2
0070    GGET    23   0      ; "require"
0071    KSTR    24  24      ; "device"
0072    CALL    23   2   2
0073    TGETS   23  23  25  ; "screen"
0074    GGET    24   0      ; "require"
0075    KSTR    25  26      ; "ffi/util"
0076    CALL    24   2   2
0077    TGETS   24  24  27  ; "template"
0078    MOV     26   9
0079    TGETS   25   9  28  ; "new"
0080    TDUP    27  31
0081    TGETS   28  15  29  ; "padding"
0082    TGETS   28  28  30  ; "fullscreen"
0083    TSETS   28  27  29  ; "padding"
0084    CALL    25   2   3
0085    FNEW    26  33      ; goodreadsbook.lua:31
0086    TSETS   26  25  32  ; "init"
0087    FNEW    26  35      ; goodreadsbook.lua:50
0088    TSETS   26  25  34  ; "getStatusContent"
0089    FNEW    26  37      ; goodreadsbook.lua:64
0090    TSETS   26  25  36  ; "genHeader"
0091    FNEW    26  39      ; goodreadsbook.lua:99
0092    TSETS   26  25  38  ; "genBookInfoGroup"
0093    FNEW    26  41      ; goodreadsbook.lua:226
0094    TSETS   26  25  40  ; "bookReview"
0095    FNEW    26  43      ; goodreadsbook.lua:258
0096    TSETS   26  25  42  ; "onAnyKeyPressed"
0097    FNEW    26  45      ; goodreadsbook.lua:262
0098    TSETS   26  25  44  ; "onClose"
0099    UCLO     0 => 0100
0100 => RET1    25   2

