
main <./plugins/goodreads.koplugin/goodreadsbook.lua:0,0> (140 instructions, 560 bytes at 0x7ffe1cc068f0)
0+ params, 29 slots, 0 upvalues, 26 locals, 38 constants, 7 functions
	1	[1]	GETGLOBAL	0 -1	; require
	2	[1]	LOADK    	1 -2	; "ffi/blitbuffer"
	3	[1]	CALL     	0 2 2
	4	[2]	GETGLOBAL	1 -1	; require
	5	[2]	LOADK    	2 -3	; "ui/widget/container/centercontainer"
	6	[2]	CALL     	1 2 2
	7	[3]	GETGLOBAL	2 -1	; require
	8	[3]	LOADK    	3 -4	; "ui/widget/closebutton"
	9	[3]	CALL     	2 2 2
	10	[4]	GETGLOBAL	3 -1	; require
	11	[4]	LOADK    	4 -5	; "ui/widget/container/framecontainer"
	12	[4]	CALL     	3 2 2
	13	[5]	GETGLOBAL	4 -1	; require
	14	[5]	LOADK    	5 -6	; "ui/geometry"
	15	[5]	CALL     	4 2 2
	16	[6]	GETGLOBAL	5 -1	; require
	17	[6]	LOADK    	6 -7	; "ui/font"
	18	[6]	CALL     	5 2 2
	19	[7]	GETGLOBAL	6 -1	; require
	20	[7]	LOADK    	7 -8	; "ui/widget/horizontalgroup"
	21	[7]	CALL     	6 2 2
	22	[8]	GETGLOBAL	7 -1	; require
	23	[8]	LOADK    	8 -9	; "ui/widget/horizontalspan"
	24	[8]	CALL     	7 2 2
	25	[9]	GETGLOBAL	8 -1	; require
	26	[9]	LOADK    	9 -10	; "ui/widget/imagewidget"
	27	[9]	CALL     	8 2 2
	28	[10]	GETGLOBAL	9 -1	; require
	29	[10]	LOADK    	10 -11	; "ui/widget/container/inputcontainer"
	30	[10]	CALL     	9 2 2
	31	[11]	GETGLOBAL	10 -1	; require
	32	[11]	LOADK    	11 -12	; "ui/widget/container/leftcontainer"
	33	[11]	CALL     	10 2 2
	34	[12]	GETGLOBAL	11 -1	; require
	35	[12]	LOADK    	12 -13	; "ui/widget/linewidget"
	36	[12]	CALL     	11 2 2
	37	[13]	GETGLOBAL	12 -1	; require
	38	[13]	LOADK    	13 -14	; "ui/widget/overlapgroup"
	39	[13]	CALL     	12 2 2
	40	[14]	GETGLOBAL	13 -1	; require
	41	[14]	LOADK    	14 -15	; "ui/renderimage"
	42	[14]	CALL     	13 2 2
	43	[15]	GETGLOBAL	14 -1	; require
	44	[15]	LOADK    	15 -16	; "ui/widget/scrollhtmlwidget"
	45	[15]	CALL     	14 2 2
	46	[16]	GETGLOBAL	15 -1	; require
	47	[16]	LOADK    	16 -17	; "ui/size"
	48	[16]	CALL     	15 2 2
	49	[17]	GETGLOBAL	16 -1	; require
	50	[17]	LOADK    	17 -18	; "ui/widget/textboxwidget"
	51	[17]	CALL     	16 2 2
	52	[18]	GETGLOBAL	17 -1	; require
	53	[18]	LOADK    	18 -19	; "ui/widget/textwidget"
	54	[18]	CALL     	17 2 2
	55	[19]	GETGLOBAL	18 -1	; require
	56	[19]	LOADK    	19 -20	; "ui/uimanager"
	57	[19]	CALL     	18 2 2
	58	[20]	GETGLOBAL	19 -1	; require
	59	[20]	LOADK    	20 -21	; "ui/widget/verticalgroup"
	60	[20]	CALL     	19 2 2
	61	[21]	GETGLOBAL	20 -1	; require
	62	[21]	LOADK    	21 -22	; "ui/widget/verticalspan"
	63	[21]	CALL     	20 2 2
	64	[22]	GETGLOBAL	21 -1	; require
	65	[22]	LOADK    	22 -23	; "ssl.https"
	66	[22]	CALL     	21 2 2
	67	[23]	GETGLOBAL	22 -1	; require
	68	[23]	LOADK    	23 -24	; "gettext"
	69	[23]	CALL     	22 2 2
	70	[24]	GETGLOBAL	23 -1	; require
	71	[24]	LOADK    	24 -25	; "device"
	72	[24]	CALL     	23 2 2
	73	[24]	GETTABLE 	23 23 -26	; "screen"
	74	[25]	GETGLOBAL	24 -1	; require
	75	[25]	LOADK    	25 -27	; "ffi/util"
	76	[25]	CALL     	24 2 2
	77	[25]	GETTABLE 	24 24 -28	; "template"
	78	[27]	SELF     	25 9 -29	; "new"
	79	[27]	NEWTABLE 	27 0 1
	80	[28]	GETTABLE 	28 15 -30	; "padding"
	81	[28]	GETTABLE 	28 28 -31	; "fullscreen"
	82	[28]	SETTABLE 	27 -30 28	; "padding" -
	83	[27]	CALL     	25 3 2
	84	[48]	CLOSURE  	26 0	; 0x7ffe1cc070f0
	85	[48]	MOVE     	0 5
	86	[48]	MOVE     	0 23
	87	[48]	MOVE     	0 18
	88	[48]	MOVE     	0 3
	89	[48]	MOVE     	0 0
	90	[31]	SETTABLE 	25 -32 26	; "init" -
	91	[62]	CLOSURE  	26 1	; 0x7ffe1cc080a0
	92	[62]	MOVE     	0 19
	93	[62]	MOVE     	0 12
	94	[62]	MOVE     	0 4
	95	[62]	MOVE     	0 15
	96	[62]	MOVE     	0 2
	97	[62]	MOVE     	0 22
	98	[50]	SETTABLE 	25 -33 26	; "getStatusContent" -
	99	[97]	CLOSURE  	26 2	; 0x7ffe1cc07390
	100	[97]	MOVE     	0 17
	101	[97]	MOVE     	0 0
	102	[97]	MOVE     	0 7
	103	[97]	MOVE     	0 10
	104	[97]	MOVE     	0 4
	105	[97]	MOVE     	0 11
	106	[97]	MOVE     	0 15
	107	[97]	MOVE     	0 19
	108	[97]	MOVE     	0 20
	109	[97]	MOVE     	0 6
	110	[64]	SETTABLE 	25 -34 26	; "genHeader" -
	111	[224]	CLOSURE  	26 3	; 0x7ffe1cc08dc0
	112	[224]	MOVE     	0 23
	113	[224]	MOVE     	0 19
	114	[224]	MOVE     	0 16
	115	[224]	MOVE     	0 15
	116	[224]	MOVE     	0 1
	117	[224]	MOVE     	0 4
	118	[224]	MOVE     	0 20
	119	[224]	MOVE     	0 17
	120	[224]	MOVE     	0 24
	121	[224]	MOVE     	0 22
	122	[224]	MOVE     	0 6
	123	[224]	MOVE     	0 7
	124	[224]	MOVE     	0 21
	125	[224]	MOVE     	0 13
	126	[224]	MOVE     	0 8
	127	[99]	SETTABLE 	25 -35 26	; "genBookInfoGroup" -
	128	[256]	CLOSURE  	26 4	; 0x7ffe1cc09630
	129	[256]	MOVE     	0 19
	130	[256]	MOVE     	0 14
	131	[256]	MOVE     	0 1
	132	[256]	MOVE     	0 4
	133	[226]	SETTABLE 	25 -36 26	; "bookReview" -
	134	[260]	CLOSURE  	26 5	; 0x7ffe1cc0a310
	135	[258]	SETTABLE 	25 -37 26	; "onAnyKeyPressed" -
	136	[265]	CLOSURE  	26 6	; 0x7ffe1cc07940
	137	[265]	MOVE     	0 18
	138	[262]	SETTABLE 	25 -38 26	; "onClose" -
	139	[267]	RETURN   	25 2
	140	[267]	RETURN   	0 1

function <./plugins/goodreads.koplugin/goodreadsbook.lua:31,48> (48 instructions, 192 bytes at 0x7ffe1cc070f0)
1 param, 7 slots, 5 upvalues, 1 local, 22 constants, 1 function
	1	[32]	GETUPVAL 	1 0	; Font
	2	[32]	SELF     	1 1 -2	; "getFace"
	3	[32]	LOADK    	3 -3	; "smallffont"
	4	[32]	CALL     	1 3 2
	5	[32]	SETTABLE 	0 -1 1	; "small_font_face" -
	6	[33]	GETUPVAL 	1 0	; Font
	7	[33]	SELF     	1 1 -2	; "getFace"
	8	[33]	LOADK    	3 -5	; "ffont"
	9	[33]	CALL     	1 3 2
	10	[33]	SETTABLE 	0 -4 1	; "medium_font_face" -
	11	[34]	GETUPVAL 	1 0	; Font
	12	[34]	SELF     	1 1 -2	; "getFace"
	13	[34]	LOADK    	3 -7	; "largeffont"
	14	[34]	CALL     	1 3 2
	15	[34]	SETTABLE 	0 -6 1	; "large_font_face" -
	16	[35]	GETUPVAL 	1 1	; Screen
	17	[35]	SELF     	1 1 -9	; "getWidth"
	18	[35]	CALL     	1 2 2
	19	[35]	SETTABLE 	0 -8 1	; "screen_width" -
	20	[36]	GETUPVAL 	1 1	; Screen
	21	[36]	SELF     	1 1 -11	; "getHeight"
	22	[36]	CALL     	1 2 2
	23	[36]	SETTABLE 	0 -10 1	; "screen_height" -
	24	[37]	GETUPVAL 	1 2	; UIManager
	25	[37]	SELF     	1 1 -12	; "setDirty"
	26	[37]	MOVE     	3 0
	27	[39]	CLOSURE  	4 0	; 0x7ffe1cc07f70
	28	[39]	MOVE     	0 0
	29	[37]	CALL     	1 4 1
	30	[40]	GETUPVAL 	1 3	; FrameContainer
	31	[40]	SELF     	1 1 -14	; "new"
	32	[40]	NEWTABLE 	3 0 5
	33	[41]	GETTABLE 	4 0 -8	; "screen_width"
	34	[41]	SETTABLE 	3 -15 4	; "width" -
	35	[42]	GETTABLE 	4 0 -10	; "screen_height"
	36	[42]	SETTABLE 	3 -16 4	; "height" -
	37	[43]	GETUPVAL 	4 4	; Blitbuffer
	38	[43]	GETTABLE 	4 4 -18	; "COLOR_WHITE"
	39	[43]	SETTABLE 	3 -17 4	; "background" -
	40	[44]	SETTABLE 	3 -19 -20	; "bordersize" 0
	41	[45]	SETTABLE 	3 -21 -20	; "padding" 0
	42	[46]	SELF     	4 0 -22	; "getStatusContent"
	43	[46]	GETTABLE 	6 0 -8	; "screen_width"
	44	[46]	CALL     	4 3 0
	45	[47]	SETLIST  	3 0 1	; 1
	46	[40]	CALL     	1 3 2
	47	[47]	SETTABLE 	0 -13 1	; 1 -
	48	[48]	RETURN   	0 1

function <./plugins/goodreads.koplugin/goodreadsbook.lua:37,39> (5 instructions, 20 bytes at 0x7ffe1cc07f70)
0 params, 2 slots, 1 upvalue, 0 locals, 2 constants, 0 functions
	1	[38]	LOADK    	0 -1	; "ui"
	2	[38]	GETUPVAL 	1 0	; self
	3	[38]	GETTABLE 	1 1 -2	; "dimen"
	4	[38]	RETURN   	0 3
	5	[39]	RETURN   	0 1

function <./plugins/goodreads.koplugin/goodreadsbook.lua:50,62> (42 instructions, 168 bytes at 0x7ffe1cc080a0)
2 params, 12 slots, 6 upvalues, 2 locals, 14 constants, 0 functions
	1	[51]	GETUPVAL 	2 0	; VerticalGroup
	2	[51]	SELF     	2 2 -1	; "new"
	3	[51]	NEWTABLE 	4 4 1
	4	[52]	SETTABLE 	4 -2 -3	; "align" "left"
	5	[53]	GETUPVAL 	5 1	; OverlapGroup
	6	[53]	SELF     	5 5 -1	; "new"
	7	[53]	NEWTABLE 	7 0 1
	8	[54]	GETUPVAL 	8 2	; Geom
	9	[54]	SELF     	8 8 -1	; "new"
	10	[54]	NEWTABLE 	10 0 2
	11	[54]	SETTABLE 	10 -5 1	; "w" -
	12	[54]	GETUPVAL 	11 3	; Size
	13	[54]	GETTABLE 	11 11 -7	; "item"
	14	[54]	GETTABLE 	11 11 -8	; "height_default"
	15	[54]	SETTABLE 	10 -6 11	; "h" -
	16	[54]	CALL     	8 3 2
	17	[54]	SETTABLE 	7 -4 8	; "dimen" -
	18	[55]	GETUPVAL 	8 4	; CloseButton
	19	[55]	SELF     	8 8 -1	; "new"
	20	[55]	NEWTABLE 	10 0 1
	21	[55]	SETTABLE 	10 -9 0	; "window" -
	22	[55]	CALL     	8 3 0
	23	[56]	SETLIST  	7 0 1	; 1
	24	[53]	CALL     	5 3 2
	25	[57]	SELF     	6 0 -10	; "genHeader"
	26	[57]	GETUPVAL 	8 5	; _
	27	[57]	LOADK    	9 -11	; "Book info"
	28	[57]	CALL     	8 2 0
	29	[57]	CALL     	6 0 2
	30	[58]	SELF     	7 0 -12	; "genBookInfoGroup"
	31	[58]	CALL     	7 2 2
	32	[59]	SELF     	8 0 -10	; "genHeader"
	33	[59]	GETUPVAL 	10 5	; _
	34	[59]	LOADK    	11 -13	; "Review"
	35	[59]	CALL     	10 2 0
	36	[59]	CALL     	8 0 2
	37	[60]	SELF     	9 0 -14	; "bookReview"
	38	[60]	CALL     	9 2 0
	39	[61]	SETLIST  	4 0 1	; 1
	40	[51]	TAILCALL 	2 3 0
	41	[61]	RETURN   	2 0
	42	[62]	RETURN   	0 1

function <./plugins/goodreads.koplugin/goodreadsbook.lua:64,97> (92 instructions, 368 bytes at 0x7ffe1cc07390)
2 params, 20 slots, 10 upvalues, 6 locals, 24 constants, 0 functions
	1	[65]	GETUPVAL 	2 0	; TextWidget
	2	[65]	SELF     	2 2 -1	; "new"
	3	[65]	NEWTABLE 	4 0 3
	4	[66]	SETTABLE 	4 -2 1	; "text" -
	5	[67]	GETTABLE 	5 0 -4	; "medium_font_face"
	6	[67]	SETTABLE 	4 -3 5	; "face" -
	7	[68]	GETUPVAL 	5 1	; Blitbuffer
	8	[68]	GETTABLE 	5 5 -6	; "COLOR_WEB_GRAY"
	9	[68]	SETTABLE 	4 -5 5	; "fgcolor" -
	10	[65]	CALL     	2 3 2
	11	[70]	GETUPVAL 	3 2	; HorizontalSpan
	12	[70]	SELF     	3 3 -1	; "new"
	13	[70]	NEWTABLE 	5 0 1
	14	[70]	GETTABLE 	6 0 -8	; "padding"
	15	[70]	SETTABLE 	5 -7 6	; "width" -
	16	[70]	CALL     	3 3 2
	17	[71]	GETTABLE 	4 0 -9	; "screen_width"
	18	[71]	SELF     	5 2 -10	; "getSize"
	19	[71]	CALL     	5 2 2
	20	[71]	GETTABLE 	5 5 -11	; "w"
	21	[71]	SUB      	4 4 5
	22	[71]	DIV      	4 4 -12	; - 2
	23	[71]	GETTABLE 	5 0 -8	; "padding"
	24	[71]	MUL      	5 5 -12	; - 2
	25	[71]	SUB      	4 4 5
	26	[72]	GETUPVAL 	5 3	; LeftContainer
	27	[72]	SELF     	5 5 -1	; "new"
	28	[72]	NEWTABLE 	7 0 1
	29	[73]	GETUPVAL 	8 4	; Geom
	30	[73]	SELF     	8 8 -1	; "new"
	31	[73]	NEWTABLE 	10 0 2
	32	[73]	SETTABLE 	10 -11 4	; "w" -
	33	[73]	GETTABLE 	11 0 -15	; "screen_height"
	34	[73]	DIV      	11 11 -16	; - 25
	35	[73]	SETTABLE 	10 -14 11	; "h" -
	36	[73]	CALL     	8 3 2
	37	[73]	SETTABLE 	7 -13 8	; "dimen" -
	38	[74]	GETUPVAL 	8 5	; LineWidget
	39	[74]	SELF     	8 8 -1	; "new"
	40	[74]	NEWTABLE 	10 0 2
	41	[75]	GETUPVAL 	11 1	; Blitbuffer
	42	[75]	GETTABLE 	11 11 -18	; "COLOR_LIGHT_GRAY"
	43	[75]	SETTABLE 	10 -17 11	; "background" -
	44	[76]	GETUPVAL 	11 4	; Geom
	45	[76]	SELF     	11 11 -1	; "new"
	46	[76]	NEWTABLE 	13 0 2
	47	[77]	SETTABLE 	13 -11 4	; "w" -
	48	[78]	GETUPVAL 	14 6	; Size
	49	[78]	GETTABLE 	14 14 -19	; "line"
	50	[78]	GETTABLE 	14 14 -20	; "thick"
	51	[78]	SETTABLE 	13 -14 14	; "h" -
	52	[76]	CALL     	11 3 2
	53	[79]	SETTABLE 	10 -13 11	; "dimen" -
	54	[74]	CALL     	8 3 0
	55	[81]	SETLIST  	7 0 1	; 1
	56	[72]	CALL     	5 3 2
	57	[83]	GETUPVAL 	6 7	; VerticalGroup
	58	[83]	SELF     	6 6 -1	; "new"
	59	[83]	NEWTABLE 	8 2 0
	60	[84]	GETUPVAL 	9 8	; VerticalSpan
	61	[84]	SELF     	9 9 -1	; "new"
	62	[84]	NEWTABLE 	11 0 1
	63	[84]	GETUPVAL 	12 6	; Size
	64	[84]	GETTABLE 	12 12 -21	; "span"
	65	[84]	GETTABLE 	12 12 -22	; "vertical_large"
	66	[84]	SETTABLE 	11 -7 12	; "width" -
	67	[84]	CALL     	9 3 2
	68	[85]	GETUPVAL 	10 9	; HorizontalGroup
	69	[85]	SELF     	10 10 -1	; "new"
	70	[85]	NEWTABLE 	12 7 1
	71	[86]	SETTABLE 	12 -23 -24	; "align" "center"
	72	[87]	MOVE     	13 3
	73	[88]	MOVE     	14 5
	74	[89]	MOVE     	15 3
	75	[90]	MOVE     	16 2
	76	[91]	MOVE     	17 3
	77	[92]	MOVE     	18 5
	78	[94]	MOVE     	19 3
	79	[94]	SETLIST  	12 7 1	; 1
	80	[85]	CALL     	10 3 2
	81	[95]	GETUPVAL 	11 8	; VerticalSpan
	82	[95]	SELF     	11 11 -1	; "new"
	83	[95]	NEWTABLE 	13 0 1
	84	[95]	GETUPVAL 	14 6	; Size
	85	[95]	GETTABLE 	14 14 -21	; "span"
	86	[95]	GETTABLE 	14 14 -22	; "vertical_large"
	87	[95]	SETTABLE 	13 -7 14	; "width" -
	88	[95]	CALL     	11 3 0
	89	[96]	SETLIST  	8 0 1	; 1
	90	[83]	TAILCALL 	6 3 0
	91	[96]	RETURN   	6 0
	92	[97]	RETURN   	0 1

function <./plugins/goodreads.koplugin/goodreadsbook.lua:99,224> (368 instructions, 1472 bytes at 0x7ffe1cc08dc0)
1 param, 25 slots, 15 upvalues, 17 locals, 51 constants, 0 functions
	1	[100]	GETTABLE 	1 0 -1	; "screen_width"
	2	[100]	MUL      	1 1 -2	; - 0.05
	3	[101]	LOADNIL  	2 3
	4	[102]	GETUPVAL 	4 0	; Screen
	5	[102]	SELF     	4 4 -3	; "getScreenMode"
	6	[102]	CALL     	4 2 2
	7	[102]	EQ       	0 4 -4	; - "landscape"
	8	[102]	JMP      	11	; to 20
	9	[103]	GETUPVAL 	4 0	; Screen
	10	[103]	SELF     	4 4 -5	; "scaleBySize"
	11	[103]	LOADK    	6 -6	; 132
	12	[103]	CALL     	4 3 2
	13	[103]	MOVE     	2 4
	14	[104]	GETUPVAL 	4 0	; Screen
	15	[104]	SELF     	4 4 -5	; "scaleBySize"
	16	[104]	LOADK    	6 -7	; 184
	17	[104]	CALL     	4 3 2
	18	[104]	MOVE     	3 4
	19	[104]	JMP      	10	; to 30
	20	[106]	GETUPVAL 	4 0	; Screen
	21	[106]	SELF     	4 4 -5	; "scaleBySize"
	22	[106]	LOADK    	6 -8	; 198
	23	[106]	CALL     	4 3 2
	24	[106]	MOVE     	2 4
	25	[107]	GETUPVAL 	4 0	; Screen
	26	[107]	SELF     	4 4 -5	; "scaleBySize"
	27	[107]	LOADK    	6 -9	; 276
	28	[107]	CALL     	4 3 2
	29	[107]	MOVE     	3 4
	30	[109]	MOVE     	4 3
	31	[110]	GETTABLE 	5 0 -1	; "screen_width"
	32	[110]	MUL      	6 -10 1	; 1.5 -
	33	[110]	SUB      	5 5 6
	34	[110]	SUB      	5 5 2
	35	[112]	GETUPVAL 	6 1	; VerticalGroup
	36	[112]	SELF     	6 6 -11	; "new"
	37	[112]	NEWTABLE 	8 0 1
	38	[113]	SETTABLE 	8 -12 -13	; "align" "center"
	39	[114]	GETUPVAL 	9 2	; TextBoxWidget
	40	[114]	SELF     	9 9 -11	; "new"
	41	[114]	NEWTABLE 	11 0 5
	42	[115]	GETTABLE 	12 0 -15	; "dates"
	43	[115]	GETTABLE 	12 12 -16	; "title"
	44	[115]	SETTABLE 	11 -14 12	; "text" -
	45	[116]	GETTABLE 	12 0 -18	; "medium_font_face"
	46	[116]	SETTABLE 	11 -17 12	; "face" -
	47	[117]	GETUPVAL 	12 3	; Size
	48	[117]	GETTABLE 	12 12 -19	; "padding"
	49	[117]	GETTABLE 	12 12 -20	; "small"
	50	[117]	SETTABLE 	11 -19 12	; "padding" -
	51	[118]	SETTABLE 	11 -21 -13	; "alignment" "center"
	52	[119]	SETTABLE 	11 -22 5	; "width" -
	53	[114]	CALL     	9 3 0
	54	[121]	SETLIST  	8 0 1	; 1
	55	[112]	CALL     	6 3 2
	56	[123]	GETUPVAL 	7 2	; TextBoxWidget
	57	[123]	SELF     	7 7 -11	; "new"
	58	[123]	NEWTABLE 	9 0 4
	59	[124]	GETTABLE 	10 0 -15	; "dates"
	60	[124]	GETTABLE 	10 10 -23	; "author"
	61	[124]	SETTABLE 	9 -14 10	; "text" -
	62	[125]	SETTABLE 	9 -22 5	; "width" -
	63	[126]	GETTABLE 	10 0 -24	; "large_font_face"
	64	[126]	SETTABLE 	9 -17 10	; "face" -
	65	[127]	SETTABLE 	9 -21 -13	; "alignment" "center"
	66	[123]	CALL     	7 3 2
	67	[129]	GETGLOBAL	8 -25	; table
	68	[129]	GETTABLE 	8 8 -26	; "insert"
	69	[129]	MOVE     	9 6
	70	[130]	GETUPVAL 	10 4	; CenterContainer
	71	[130]	SELF     	10 10 -11	; "new"
	72	[130]	NEWTABLE 	12 1 1
	73	[131]	GETUPVAL 	13 5	; Geom
	74	[131]	SELF     	13 13 -11	; "new"
	75	[131]	NEWTABLE 	15 0 2
	76	[131]	SETTABLE 	15 -28 5	; "w" -
	77	[131]	SELF     	16 7 -30	; "getSize"
	78	[131]	CALL     	16 2 2
	79	[131]	GETTABLE 	16 16 -29	; "h"
	80	[131]	SETTABLE 	15 -29 16	; "h" -
	81	[131]	CALL     	13 3 2
	82	[131]	SETTABLE 	12 -27 13	; "dimen" -
	83	[133]	MOVE     	13 7
	84	[133]	SETLIST  	12 1 1	; 1
	85	[130]	CALL     	10 3 0
	86	[129]	CALL     	8 0 1
	87	[136]	GETUPVAL 	8 6	; VerticalSpan
	88	[136]	SELF     	8 8 -11	; "new"
	89	[136]	NEWTABLE 	10 0 1
	90	[136]	MUL      	11 4 -31	; - 0.1
	91	[136]	SETTABLE 	10 -22 11	; "width" -
	92	[136]	CALL     	8 3 2
	93	[137]	GETGLOBAL	9 -25	; table
	94	[137]	GETTABLE 	9 9 -26	; "insert"
	95	[137]	MOVE     	10 6
	96	[138]	GETUPVAL 	11 4	; CenterContainer
	97	[138]	SELF     	11 11 -11	; "new"
	98	[138]	NEWTABLE 	13 1 1
	99	[139]	GETUPVAL 	14 5	; Geom
	100	[139]	SELF     	14 14 -11	; "new"
	101	[139]	NEWTABLE 	16 0 2
	102	[139]	SETTABLE 	16 -28 5	; "w" -
	103	[139]	GETUPVAL 	17 0	; Screen
	104	[139]	SELF     	17 17 -5	; "scaleBySize"
	105	[139]	LOADK    	19 -32	; 10
	106	[139]	CALL     	17 3 2
	107	[139]	SETTABLE 	16 -29 17	; "h" -
	108	[139]	CALL     	14 3 2
	109	[139]	SETTABLE 	13 -27 14	; "dimen" -
	110	[141]	MOVE     	14 8
	111	[141]	SETLIST  	13 1 1	; 1
	112	[138]	CALL     	11 3 0
	113	[137]	CALL     	9 0 1
	114	[144]	GETUPVAL 	9 7	; TextWidget
	115	[144]	SELF     	9 9 -11	; "new"
	116	[144]	NEWTABLE 	11 0 3
	117	[145]	GETUPVAL 	12 8	; T
	118	[145]	GETUPVAL 	13 9	; _
	119	[145]	LOADK    	14 -33	; "Series: %1"
	120	[145]	CALL     	13 2 2
	121	[145]	GETTABLE 	14 0 -15	; "dates"
	122	[145]	GETTABLE 	14 14 -34	; "series"
	123	[145]	CALL     	12 3 2
	124	[145]	SETTABLE 	11 -14 12	; "text" -
	125	[146]	GETTABLE 	12 0 -35	; "small_font_face"
	126	[146]	SETTABLE 	11 -17 12	; "face" -
	127	[147]	GETUPVAL 	12 3	; Size
	128	[147]	GETTABLE 	12 12 -19	; "padding"
	129	[147]	GETTABLE 	12 12 -20	; "small"
	130	[147]	SETTABLE 	11 -19 12	; "padding" -
	131	[144]	CALL     	9 3 2
	132	[149]	GETGLOBAL	10 -25	; table
	133	[149]	GETTABLE 	10 10 -26	; "insert"
	134	[149]	MOVE     	11 6
	135	[150]	GETUPVAL 	12 4	; CenterContainer
	136	[150]	SELF     	12 12 -11	; "new"
	137	[150]	NEWTABLE 	14 1 1
	138	[151]	GETUPVAL 	15 5	; Geom
	139	[151]	SELF     	15 15 -11	; "new"
	140	[151]	NEWTABLE 	17 0 2
	141	[151]	SETTABLE 	17 -28 5	; "w" -
	142	[151]	SELF     	18 9 -30	; "getSize"
	143	[151]	CALL     	18 2 2
	144	[151]	GETTABLE 	18 18 -29	; "h"
	145	[151]	SETTABLE 	17 -29 18	; "h" -
	146	[151]	CALL     	15 3 2
	147	[151]	SETTABLE 	14 -27 15	; "dimen" -
	148	[153]	MOVE     	15 9
	149	[153]	SETLIST  	14 1 1	; 1
	150	[150]	CALL     	12 3 0
	151	[149]	CALL     	10 0 1
	152	[156]	GETUPVAL 	10 7	; TextWidget
	153	[156]	SELF     	10 10 -11	; "new"
	154	[156]	NEWTABLE 	12 0 3
	155	[157]	GETUPVAL 	13 8	; T
	156	[157]	GETUPVAL 	14 9	; _
	157	[157]	LOADK    	15 -36	; "Rating: %1"
	158	[157]	CALL     	14 2 2
	159	[157]	GETTABLE 	15 0 -15	; "dates"
	160	[157]	GETTABLE 	15 15 -37	; "rating"
	161	[157]	CALL     	13 3 2
	162	[157]	SETTABLE 	12 -14 13	; "text" -
	163	[158]	GETTABLE 	13 0 -35	; "small_font_face"
	164	[158]	SETTABLE 	12 -17 13	; "face" -
	165	[159]	GETUPVAL 	13 3	; Size
	166	[159]	GETTABLE 	13 13 -19	; "padding"
	167	[159]	GETTABLE 	13 13 -20	; "small"
	168	[159]	SETTABLE 	12 -19 13	; "padding" -
	169	[156]	CALL     	10 3 2
	170	[161]	GETGLOBAL	11 -25	; table
	171	[161]	GETTABLE 	11 11 -26	; "insert"
	172	[161]	MOVE     	12 6
	173	[162]	GETUPVAL 	13 4	; CenterContainer
	174	[162]	SELF     	13 13 -11	; "new"
	175	[162]	NEWTABLE 	15 1 1
	176	[163]	GETUPVAL 	16 5	; Geom
	177	[163]	SELF     	16 16 -11	; "new"
	178	[163]	NEWTABLE 	18 0 2
	179	[163]	SETTABLE 	18 -28 5	; "w" -
	180	[163]	SELF     	19 10 -30	; "getSize"
	181	[163]	CALL     	19 2 2
	182	[163]	GETTABLE 	19 19 -29	; "h"
	183	[163]	SETTABLE 	18 -29 19	; "h" -
	184	[163]	CALL     	16 3 2
	185	[163]	SETTABLE 	15 -27 16	; "dimen" -
	186	[165]	MOVE     	16 10
	187	[165]	SETLIST  	15 1 1	; 1
	188	[162]	CALL     	13 3 0
	189	[161]	CALL     	11 0 1
	190	[168]	GETUPVAL 	11 7	; TextWidget
	191	[168]	SELF     	11 11 -11	; "new"
	192	[168]	NEWTABLE 	13 0 3
	193	[169]	GETUPVAL 	14 8	; T
	194	[169]	GETUPVAL 	15 9	; _
	195	[169]	LOADK    	16 -38	; "Pages: %1"
	196	[169]	CALL     	15 2 2
	197	[169]	GETTABLE 	16 0 -15	; "dates"
	198	[169]	GETTABLE 	16 16 -39	; "pages"
	199	[169]	CALL     	14 3 2
	200	[169]	SETTABLE 	13 -14 14	; "text" -
	201	[170]	GETTABLE 	14 0 -35	; "small_font_face"
	202	[170]	SETTABLE 	13 -17 14	; "face" -
	203	[171]	GETUPVAL 	14 3	; Size
	204	[171]	GETTABLE 	14 14 -19	; "padding"
	205	[171]	GETTABLE 	14 14 -20	; "small"
	206	[171]	SETTABLE 	13 -19 14	; "padding" -
	207	[168]	CALL     	11 3 2
	208	[173]	GETGLOBAL	12 -25	; table
	209	[173]	GETTABLE 	12 12 -26	; "insert"
	210	[173]	MOVE     	13 6
	211	[174]	GETUPVAL 	14 4	; CenterContainer
	212	[174]	SELF     	14 14 -11	; "new"
	213	[174]	NEWTABLE 	16 1 1
	214	[175]	GETUPVAL 	17 5	; Geom
	215	[175]	SELF     	17 17 -11	; "new"
	216	[175]	NEWTABLE 	19 0 2
	217	[175]	SETTABLE 	19 -28 5	; "w" -
	218	[175]	SELF     	20 11 -30	; "getSize"
	219	[175]	CALL     	20 2 2
	220	[175]	GETTABLE 	20 20 -29	; "h"
	221	[175]	SETTABLE 	19 -29 20	; "h" -
	222	[175]	CALL     	17 3 2
	223	[175]	SETTABLE 	16 -27 17	; "dimen" -
	224	[177]	MOVE     	17 11
	225	[177]	SETLIST  	16 1 1	; 1
	226	[174]	CALL     	14 3 0
	227	[173]	CALL     	12 0 1
	228	[180]	GETUPVAL 	12 7	; TextWidget
	229	[180]	SELF     	12 12 -11	; "new"
	230	[180]	NEWTABLE 	14 0 3
	231	[181]	GETUPVAL 	15 8	; T
	232	[181]	GETUPVAL 	16 9	; _
	233	[181]	LOADK    	17 -40	; "Release date: %1"
	234	[181]	CALL     	16 2 2
	235	[181]	GETTABLE 	17 0 -15	; "dates"
	236	[181]	GETTABLE 	17 17 -41	; "release"
	237	[181]	CALL     	15 3 2
	238	[181]	SETTABLE 	14 -14 15	; "text" -
	239	[182]	GETTABLE 	15 0 -35	; "small_font_face"
	240	[182]	SETTABLE 	14 -17 15	; "face" -
	241	[183]	GETUPVAL 	15 3	; Size
	242	[183]	GETTABLE 	15 15 -19	; "padding"
	243	[183]	GETTABLE 	15 15 -20	; "small"
	244	[183]	SETTABLE 	14 -19 15	; "padding" -
	245	[180]	CALL     	12 3 2
	246	[185]	GETGLOBAL	13 -25	; table
	247	[185]	GETTABLE 	13 13 -26	; "insert"
	248	[185]	MOVE     	14 6
	249	[186]	GETUPVAL 	15 4	; CenterContainer
	250	[186]	SELF     	15 15 -11	; "new"
	251	[186]	NEWTABLE 	17 1 1
	252	[187]	GETUPVAL 	18 5	; Geom
	253	[187]	SELF     	18 18 -11	; "new"
	254	[187]	NEWTABLE 	20 0 2
	255	[187]	SETTABLE 	20 -28 5	; "w" -
	256	[187]	SELF     	21 12 -30	; "getSize"
	257	[187]	CALL     	21 2 2
	258	[187]	GETTABLE 	21 21 -29	; "h"
	259	[187]	SETTABLE 	20 -29 21	; "h" -
	260	[187]	CALL     	18 3 2
	261	[187]	SETTABLE 	17 -27 18	; "dimen" -
	262	[189]	MOVE     	18 12
	263	[189]	SETLIST  	17 1 1	; 1
	264	[186]	CALL     	15 3 0
	265	[185]	CALL     	13 0 1
	266	[191]	GETUPVAL 	13 10	; HorizontalGroup
	267	[191]	SELF     	13 13 -11	; "new"
	268	[191]	NEWTABLE 	15 0 1
	269	[192]	SETTABLE 	15 -12 -42	; "align" "top"
	270	[193]	GETUPVAL 	16 11	; HorizontalSpan
	271	[193]	SELF     	16 16 -11	; "new"
	272	[193]	NEWTABLE 	18 0 1
	273	[193]	SETTABLE 	18 -22 1	; "width" -
	274	[193]	CALL     	16 3 0
	275	[194]	SETLIST  	15 0 1	; 1
	276	[191]	CALL     	13 3 2
	277	[196]	GETUPVAL 	14 12	; https
	278	[196]	GETTABLE 	14 14 -43	; "request"
	279	[196]	GETTABLE 	15 0 -15	; "dates"
	280	[196]	GETTABLE 	15 15 -44	; "image"
	281	[196]	CALL     	14 2 2
	282	[197]	LOADNIL  	15 15
	283	[198]	TEST     	14 0 0
	284	[198]	JMP      	9	; to 294
	285	[198]	GETUPVAL 	16 13	; RenderImage
	286	[198]	SELF     	16 16 -45	; "renderImageData"
	287	[198]	MOVE     	18 14
	288	[198]	LEN      	19 14
	289	[198]	LOADBOOL 	20 0 0
	290	[198]	MOVE     	21 2
	291	[198]	MOVE     	22 3
	292	[198]	CALL     	16 7 2
	293	[198]	MOVE     	15 16
	294	[199]	TEST     	15 0 0
	295	[199]	JMP      	10	; to 306
	296	[200]	GETGLOBAL	16 -25	; table
	297	[200]	GETTABLE 	16 16 -26	; "insert"
	298	[200]	MOVE     	17 13
	299	[200]	GETUPVAL 	18 14	; ImageWidget
	300	[200]	SELF     	18 18 -11	; "new"
	301	[200]	NEWTABLE 	20 0 1
	302	[201]	SETTABLE 	20 -44 15	; "image" -
	303	[200]	CALL     	18 3 0
	304	[200]	CALL     	16 0 1
	305	[202]	JMP      	11	; to 317
	306	[204]	GETGLOBAL	16 -25	; table
	307	[204]	GETTABLE 	16 16 -26	; "insert"
	308	[204]	MOVE     	17 13
	309	[204]	GETUPVAL 	18 14	; ImageWidget
	310	[204]	SELF     	18 18 -11	; "new"
	311	[204]	NEWTABLE 	20 0 3
	312	[205]	SETTABLE 	20 -46 -47	; "file" "resources/goodreadsnophoto.png"
	313	[206]	SETTABLE 	20 -22 2	; "width" -
	314	[207]	SETTABLE 	20 -48 3	; "height" -
	315	[204]	CALL     	18 3 0
	316	[204]	CALL     	16 0 1
	317	[211]	GETUPVAL 	16 10	; HorizontalGroup
	318	[211]	SELF     	16 16 -11	; "new"
	319	[211]	NEWTABLE 	18 0 1
	320	[212]	SETTABLE 	18 -12 -42	; "align" "top"
	321	[213]	GETUPVAL 	19 11	; HorizontalSpan
	322	[213]	SELF     	19 19 -11	; "new"
	323	[213]	NEWTABLE 	21 0 1
	324	[213]	DIV      	22 1 -49	; - 2
	325	[213]	SETTABLE 	21 -22 22	; "width" -
	326	[213]	CALL     	19 3 0
	327	[214]	SETLIST  	18 0 1	; 1
	328	[211]	CALL     	16 3 2
	329	[215]	GETGLOBAL	17 -25	; table
	330	[215]	GETTABLE 	17 17 -26	; "insert"
	331	[215]	MOVE     	18 13
	332	[215]	MOVE     	19 16
	333	[215]	CALL     	17 3 1
	334	[216]	GETGLOBAL	17 -25	; table
	335	[216]	GETTABLE 	17 17 -26	; "insert"
	336	[216]	MOVE     	18 13
	337	[216]	GETUPVAL 	19 4	; CenterContainer
	338	[216]	SELF     	19 19 -11	; "new"
	339	[216]	NEWTABLE 	21 1 1
	340	[217]	GETUPVAL 	22 5	; Geom
	341	[217]	SELF     	22 22 -11	; "new"
	342	[217]	NEWTABLE 	24 0 2
	343	[217]	SETTABLE 	24 -28 5	; "w" -
	344	[217]	SETTABLE 	24 -29 4	; "h" -
	345	[217]	CALL     	22 3 2
	346	[217]	SETTABLE 	21 -27 22	; "dimen" -
	347	[219]	MOVE     	22 6
	348	[219]	SETLIST  	21 1 1	; 1
	349	[216]	CALL     	19 3 0
	350	[216]	CALL     	17 0 1
	351	[220]	GETUPVAL 	17 4	; CenterContainer
	352	[220]	SELF     	17 17 -11	; "new"
	353	[220]	NEWTABLE 	19 1 1
	354	[221]	GETUPVAL 	20 5	; Geom
	355	[221]	SELF     	20 20 -11	; "new"
	356	[221]	NEWTABLE 	22 0 2
	357	[221]	GETTABLE 	23 0 -1	; "screen_width"
	358	[221]	SETTABLE 	22 -28 23	; "w" -
	359	[221]	GETTABLE 	23 0 -50	; "screen_height"
	360	[221]	MUL      	23 23 -51	; - 0.35
	361	[221]	SETTABLE 	22 -29 23	; "h" -
	362	[221]	CALL     	20 3 2
	363	[221]	SETTABLE 	19 -27 20	; "dimen" -
	364	[223]	MOVE     	20 13
	365	[223]	SETLIST  	19 1 1	; 1
	366	[220]	TAILCALL 	17 3 0
	367	[223]	RETURN   	17 0
	368	[224]	RETURN   	0 1

function <./plugins/goodreads.koplugin/goodreadsbook.lua:226,256> (42 instructions, 168 bytes at 0x7ffe1cc09630)
1 param, 10 slots, 4 upvalues, 3 locals, 22 constants, 0 functions
	1	[238]	LOADK    	1 -1	; "        @page {\n            margin: 0;\n            font-family: 'Noto Sans';\n        }\n\n        body {\n            margin: 0;\n            line-height: 1.3;\n            text-align: justify;\n        }\n        "
	2	[240]	GETUPVAL 	2 0	; VerticalGroup
	3	[240]	SELF     	2 2 -2	; "new"
	4	[240]	NEWTABLE 	4 0 3
	5	[241]	SETTABLE 	4 -3 -4	; "align" "center"
	6	[242]	SETTABLE 	4 -5 -6	; "padding" 0
	7	[243]	SETTABLE 	4 -7 -6	; "bordersize" 0
	8	[244]	GETUPVAL 	5 1	; ScrollHtmlWidget
	9	[244]	SELF     	5 5 -2	; "new"
	10	[244]	NEWTABLE 	7 0 5
	11	[245]	GETTABLE 	8 0 -9	; "dates"
	12	[245]	GETTABLE 	8 8 -10	; "description"
	13	[245]	SETTABLE 	7 -8 8	; "html_body" -
	14	[246]	SETTABLE 	7 -11 1	; "css" -
	15	[247]	GETTABLE 	8 0 -13	; "screen_width"
	16	[247]	MUL      	8 8 -14	; - 0.9
	17	[247]	SETTABLE 	7 -12 8	; "width" -
	18	[248]	GETTABLE 	8 0 -16	; "screen_height"
	19	[248]	MUL      	8 8 -17	; - 0.48
	20	[248]	SETTABLE 	7 -15 8	; "height" -
	21	[249]	SETTABLE 	7 -18 0	; "dialog" -
	22	[244]	CALL     	5 3 0
	23	[251]	SETLIST  	4 0 1	; 1
	24	[240]	CALL     	2 3 2
	25	[252]	GETUPVAL 	3 2	; CenterContainer
	26	[252]	SELF     	3 3 -2	; "new"
	27	[252]	NEWTABLE 	5 1 1
	28	[253]	GETUPVAL 	6 3	; Geom
	29	[253]	SELF     	6 6 -2	; "new"
	30	[253]	NEWTABLE 	8 0 2
	31	[253]	GETTABLE 	9 0 -13	; "screen_width"
	32	[253]	SETTABLE 	8 -20 9	; "w" -
	33	[253]	GETTABLE 	9 0 -16	; "screen_height"
	34	[253]	MUL      	9 9 -22	; - 0.5
	35	[253]	SETTABLE 	8 -21 9	; "h" -
	36	[253]	CALL     	6 3 2
	37	[253]	SETTABLE 	5 -19 6	; "dimen" -
	38	[255]	MOVE     	6 2
	39	[255]	SETLIST  	5 1 1	; 1
	40	[252]	TAILCALL 	3 3 0
	41	[255]	RETURN   	3 0
	42	[256]	RETURN   	0 1

function <./plugins/goodreads.koplugin/goodreadsbook.lua:258,260> (4 instructions, 16 bytes at 0x7ffe1cc0a310)
1 param, 3 slots, 0 upvalues, 1 local, 1 constant, 0 functions
	1	[259]	SELF     	1 0 -1	; "onClose"
	2	[259]	TAILCALL 	1 2 0
	3	[259]	RETURN   	1 0
	4	[260]	RETURN   	0 1

function <./plugins/goodreads.koplugin/goodreadsbook.lua:262,265> (8 instructions, 32 bytes at 0x7ffe1cc07940)
1 param, 5 slots, 1 upvalue, 1 local, 2 constants, 0 functions
	1	[263]	GETUPVAL 	1 0	; UIManager
	2	[263]	SELF     	1 1 -1	; "close"
	3	[263]	MOVE     	3 0
	4	[263]	LOADK    	4 -2	; "flashui"
	5	[263]	CALL     	1 4 1
	6	[264]	LOADBOOL 	1 1 0
	7	[264]	RETURN   	1 2
	8	[265]	RETURN   	0 1
