-- BYTECODE -- he_keyboard.lua:0-97
0001    GGET     0   0      ; "require"
0002    KSTR     1   1      ; "ui/data/keyboardlayouts/keypopup/en_popu"~
0003    CALL     0   2   2
0004    GGET     1   0      ; "require"
0005    KSTR     2   2      ; "ui/data/keyboardlayouts/keypopup/he_popu"~
0006    CALL     1   2   2
0007    TGETS    2   0   3  ; "com"
0008    TGETS    3   0   4  ; "prd"
0009    TGETS    4   0   5  ; "_at"
0010    TGETS    5   0   6  ; "_eq"
0011    TGETS    6   1   7  ; "aleph"
0012    TGETS    7   1   8  ; "beis"
0013    TGETS    8   1   9  ; "gimmel"
0014    TGETS    9   1  10  ; "daled"
0015    TGETS   10   1  11  ; "hey"
0016    TGETS   11   1  12  ; "vov"
0017    TGETS   12   1  13  ; "zayin"
0018    TGETS   13   1  14  ; "tes"
0019    TGETS   14   1  15  ; "yud"
0020    TGETS   15   1  16  ; "chof"
0021    TGETS   16   1  17  ; "lamed"
0022    TGETS   17   1  18  ; "mem"
0023    TGETS   18   1  19  ; "mem_sofis"
0024    TGETS   19   1  20  ; "nun"
0025    TGETS   20   1  21  ; "samech"
0026    TGETS   21   1  22  ; "ayin"
0027    TGETS   22   1  23  ; "pey"
0028    TGETS   23   1  24  ; "pey_sofis"
0029    TGETS   24   1  25  ; "tzadik"
0030    TGETS   25   1  26  ; "kuf"
0031    TGETS   26   1  27  ; "reish"
0032    TGETS   27   1  28  ; "shin"
0033    TGETS   28   1  29  ; "taf"
0034    TDUP    29  30
0035    TDUP    30  31
0036    TSETS   30  29  32  ; "shiftmode_keys"
0037    TDUP    30  33
0038    TSETS   30  29  34  ; "symbolmode_keys"
0039    TDUP    30  35
0040    TSETS   30  29  36  ; "utf8mode_keys"
0041    TNEW    30   5
0042    TNEW    31  11
0043    TDUP    32  37
0044    TSETB   32  31   1
0045    TDUP    32  38
0046    TSETB   25  32   2
0047    TSETB   32  31   2
0048    TDUP    32  39
0049    TSETB   26  32   2
0050    TSETB    4  32   3
0051    TSETB   32  31   3
0052    TDUP    32  40
0053    TSETB    6  32   2
0054    TSETB   32  31   4
0055    TDUP    32  41
0056    TSETB   13  32   2
0057    TSETB    5  32   4
0058    TSETB   32  31   5
0059    TDUP    32  42
0060    TSETB   11  32   2
0061    TSETB   32  31   6
0062    TDUP    32  43
0063    TSETB   32  31   7
0064    TDUP    32  44
0065    TSETB   18  32   2
0066    TSETB   32  31   8
0067    TDUP    32  45
0068    TSETB   22  32   2
0069    TSETB   32  31   9
0070    TDUP    32  46
0071    TSETB   23  32   2
0072    TSETB   32  31  10
0073    TSETB   31  30   1
0074    TNEW    31  10
0075    TDUP    32  47
0076    TSETB   27  32   2
0077    TSETB    4  32   4
0078    TSETB   32  31   1
0079    TDUP    32  48
0080    TSETB    9  32   2
0081    TSETB   32  31   2
0082    TDUP    32  49
0083    TSETB    8  32   2
0084    TSETB   32  31   3
0085    TDUP    32  50
0086    TSETB   15  32   2
0087    TSETB   32  31   4
0088    TDUP    32  51
0089    TSETB   21  32   2
0090    TSETB   32  31   5
0091    TDUP    32  52
0092    TSETB   14  32   2
0093    TSETB   32  31   6
0094    TDUP    32  53
0095    TSETB   32  31   7
0096    TDUP    32  54
0097    TSETB   16  32   2
0098    TSETB   32  31   8
0099    TDUP    32  55
0100    TSETB   32  31   9
0101    TSETB   31  30   2
0102    TNEW    31  10
0103    TDUP    32  56
0104    TSETB   32  31   1
0105    TDUP    32  57
0106    TSETB   12  32   2
0107    TSETB   32  31   2
0108    TDUP    32  58
0109    TSETB   20  32   2
0110    TSETB   32  31   3
0111    TDUP    32  59
0112    TSETB    7  32   2
0113    TSETB   32  31   4
0114    TDUP    32  60
0115    TSETB   10  32   2
0116    TSETB    2  32   4
0117    TSETB   32  31   5
0118    TDUP    32  61
0119    TSETB   19  32   2
0120    TSETB    3  32   4
0121    TSETB   32  31   6
0122    TDUP    32  62
0123    TSETB   17  32   2
0124    TSETB   32  31   7
0125    TDUP    32  63
0126    TSETB   24  32   2
0127    TSETB   32  31   8
0128    TDUP    32  64
0129    TSETB   32  31   9
0130    TSETB   31  30   3
0131    TNEW    31   7
0132    TDUP    32  65
0133    TSETB   32  31   1
0134    TDUP    32  66
0135    TSETB   32  31   2
0136    TDUP    32  67
0137    TSETB   32  31   3
0138    TDUP    32  68
0139    TSETB    2  32   1
0140    TSETB   28  32   2
0141    TSETB   32  31   4
0142    TDUP    32  69
0143    TSETB    3  32   1
0144    TSETB   32  31   5
0145    TDUP    32  70
0146    TSETB   32  31   6
0147    TSETB   31  30   4
0148    TSETS   30  29  71  ; "keys"
0149    RET1    29   2

