
main <./frontend/ui/data/keyboardlayouts/he_keyboard.lua:0,0> (259 instructions, 1036 bytes at 0x7f7f76406900)
0+ params, 46 slots, 0 upvalues, 29 locals, 135 constants, 0 functions
	1	[1]	GETGLOBAL	0 -1	; require
	2	[1]	LOADK    	1 -2	; "ui/data/keyboardlayouts/keypopup/en_popup"
	3	[1]	CALL     	0 2 2
	4	[2]	GETGLOBAL	1 -1	; require
	5	[2]	LOADK    	2 -3	; "ui/data/keyboardlayouts/keypopup/he_popup"
	6	[2]	CALL     	1 2 2
	7	[3]	GETTABLE 	2 0 -4	; "com"
	8	[4]	GETTABLE 	3 0 -5	; "prd"
	9	[5]	GETTABLE 	4 0 -6	; "_at"
	10	[6]	GETTABLE 	5 0 -7	; "_eq"
	11	[7]	GETTABLE 	6 1 -8	; "aleph"
	12	[8]	GETTABLE 	7 1 -9	; "beis"
	13	[9]	GETTABLE 	8 1 -10	; "gimmel"
	14	[10]	GETTABLE 	9 1 -11	; "daled"
	15	[11]	GETTABLE 	10 1 -12	; "hey"
	16	[12]	GETTABLE 	11 1 -13	; "vov"
	17	[13]	GETTABLE 	12 1 -14	; "zayin"
	18	[14]	GETTABLE 	13 1 -15	; "tes"
	19	[15]	GETTABLE 	14 1 -16	; "yud"
	20	[16]	GETTABLE 	15 1 -17	; "chof"
	21	[17]	GETTABLE 	16 1 -18	; "lamed"
	22	[18]	GETTABLE 	17 1 -19	; "mem"
	23	[19]	GETTABLE 	18 1 -20	; "mem_sofis"
	24	[20]	GETTABLE 	19 1 -21	; "nun"
	25	[21]	GETTABLE 	20 1 -22	; "samech"
	26	[22]	GETTABLE 	21 1 -23	; "ayin"
	27	[23]	GETTABLE 	22 1 -24	; "pey"
	28	[24]	GETTABLE 	23 1 -25	; "pey_sofis"
	29	[25]	GETTABLE 	24 1 -26	; "tzadik"
	30	[26]	GETTABLE 	25 1 -27	; "kuf"
	31	[27]	GETTABLE 	26 1 -28	; "reish"
	32	[28]	GETTABLE 	27 1 -29	; "shin"
	33	[29]	GETTABLE 	28 1 -30	; "taf"
	34	[31]	NEWTABLE 	29 0 6
	35	[32]	SETTABLE 	29 -31 -32	; "min_layer" 1
	36	[33]	SETTABLE 	29 -33 -34	; "max_layer" 4
	37	[34]	NEWTABLE 	30 0 1
	38	[34]	SETTABLE 	30 -36 -37	; "\238\180\181" true
	39	[34]	SETTABLE 	29 -35 30	; "shiftmode_keys" -
	40	[35]	NEWTABLE 	30 0 2
	41	[35]	SETTABLE 	30 -39 -37	; "Sym" true
	42	[35]	SETTABLE 	30 -40 -37	; "\215\144\215\145\215\146" true
	43	[35]	SETTABLE 	29 -38 30	; "symbolmode_keys" -
	44	[36]	NEWTABLE 	30 0 1
	45	[36]	SETTABLE 	30 -42 -37	; "\240\159\140\144" true
	46	[36]	SETTABLE 	29 -41 30	; "utf8mode_keys" -
	47	[37]	NEWTABLE 	30 4 0
	48	[37]	NEWTABLE 	31 10 0
	49	[39]	NEWTABLE 	32 4 0
	50	[40]	LOADK    	33 -44	; "\215\179"
	51	[40]	LOADK    	34 -45	; "\215\180"
	52	[40]	LOADK    	35 -46	; "\226\128\158"
	53	[40]	LOADK    	36 -47	; "0"
	54	[40]	SETLIST  	32 4 1	; 1
	55	[40]	NEWTABLE 	33 4 0
	56	[41]	LOADK    	34 -48	; "\214\152\214\152\214\153\214\153 "
	57	[41]	MOVE     	35 25
	58	[41]	LOADK    	36 -49	; "!"
	59	[41]	LOADK    	37 -50	; "1"
	60	[41]	SETLIST  	33 4 1	; 1
	61	[41]	NEWTABLE 	34 4 0
	62	[42]	LOADK    	35 -51	; "\214\152 "
	63	[42]	MOVE     	36 26
	64	[42]	MOVE     	37 4
	65	[42]	LOADK    	38 -52	; "2"
	66	[42]	SETLIST  	34 4 1	; 1
	67	[42]	NEWTABLE 	35 4 0
	68	[43]	LOADK    	36 -53	; "\214\151"
	69	[43]	MOVE     	37 6
	70	[43]	LOADK    	38 -54	; "#"
	71	[43]	LOADK    	39 -55	; "3"
	72	[43]	SETLIST  	35 4 1	; 1
	73	[43]	NEWTABLE 	36 4 0
	74	[44]	LOADK    	37 -56	; "\214\150 "
	75	[44]	MOVE     	38 13
	76	[44]	LOADK    	39 -57	; "+"
	77	[44]	MOVE     	40 5
	78	[44]	SETLIST  	36 4 1	; 1
	79	[44]	NEWTABLE 	37 4 0
	80	[45]	LOADK    	38 -58	; "\214\149 "
	81	[45]	MOVE     	39 11
	82	[45]	LOADK    	40 -59	; "\226\130\172"
	83	[45]	LOADK    	41 -60	; "("
	84	[45]	SETLIST  	37 4 1	; 1
	85	[45]	NEWTABLE 	38 4 0
	86	[46]	LOADK    	39 -61	; "\214\148 "
	87	[46]	LOADK    	40 -62	; "\215\159"
	88	[46]	LOADK    	41 -63	; "\226\128\176"
	89	[46]	LOADK    	42 -64	; ")"
	90	[46]	SETLIST  	38 4 1	; 1
	91	[46]	NEWTABLE 	39 4 0
	92	[47]	LOADK    	40 -65	; "\214\147 "
	93	[47]	MOVE     	41 18
	94	[47]	LOADK    	42 -66	; "|"
	95	[47]	LOADK    	43 -67	; "\\"
	96	[47]	SETLIST  	39 4 1	; 1
	97	[47]	NEWTABLE 	40 4 0
	98	[48]	LOADK    	41 -68	; "\214\146 "
	99	[48]	MOVE     	42 22
	100	[48]	LOADK    	43 -69	; "?"
	101	[48]	LOADK    	44 -70	; "/"
	102	[48]	SETLIST  	40 4 1	; 1
	103	[48]	NEWTABLE 	41 4 0
	104	[49]	LOADK    	42 -71	; "\214\145 "
	105	[49]	MOVE     	43 23
	106	[49]	LOADK    	44 -72	; "~"
	107	[49]	LOADK    	45 -73	; "`"
	108	[49]	SETLIST  	41 4 1	; 1
	109	[50]	SETLIST  	31 10 1	; 1
	110	[50]	NEWTABLE 	32 9 0
	111	[52]	NEWTABLE 	33 4 0
	112	[53]	LOADK    	34 -74	; "\214\188 "
	113	[53]	MOVE     	35 27
	114	[53]	LOADK    	36 -75	; "\226\128\166"
	115	[53]	MOVE     	37 4
	116	[53]	SETLIST  	33 4 1	; 1
	117	[53]	NEWTABLE 	34 4 0
	118	[54]	LOADK    	35 -76	; "\214\187 "
	119	[54]	MOVE     	36 9
	120	[54]	LOADK    	37 -77	; "$"
	121	[54]	LOADK    	38 -78	; "4"
	122	[54]	SETLIST  	34 4 1	; 1
	123	[54]	NEWTABLE 	35 4 0
	124	[55]	LOADK    	36 -79	; "\214\180 "
	125	[55]	MOVE     	37 8
	126	[55]	LOADK    	38 -80	; "%"
	127	[55]	LOADK    	39 -81	; "5"
	128	[55]	SETLIST  	35 4 1	; 1
	129	[55]	NEWTABLE 	36 4 0
	130	[56]	LOADK    	37 -82	; "\214\185"
	131	[56]	MOVE     	38 15
	132	[56]	LOADK    	39 -83	; "^"
	133	[56]	LOADK    	40 -84	; "6"
	134	[56]	SETLIST  	36 4 1	; 1
	135	[56]	NEWTABLE 	37 4 0
	136	[57]	LOADK    	38 -85	; "\214\176 "
	137	[57]	MOVE     	39 21
	138	[57]	LOADK    	40 -86	; ":"
	139	[57]	LOADK    	41 -87	; ";"
	140	[57]	SETLIST  	37 4 1	; 1
	141	[57]	NEWTABLE 	38 4 0
	142	[58]	LOADK    	39 -88	; "\214\181 "
	143	[58]	MOVE     	40 14
	144	[58]	LOADK    	41 -89	; "\""
	145	[58]	LOADK    	42 -90	; "'"
	146	[58]	SETLIST  	38 4 1	; 1
	147	[58]	NEWTABLE 	39 4 0
	148	[59]	LOADK    	40 -91	; "\214\182 "
	149	[59]	LOADK    	41 -92	; "\215\151"
	150	[59]	LOADK    	42 -93	; "{"
	151	[59]	LOADK    	43 -94	; "["
	152	[59]	SETLIST  	39 4 1	; 1
	153	[59]	NEWTABLE 	40 4 0
	154	[60]	LOADK    	41 -95	; "\214\183 "
	155	[60]	MOVE     	42 16
	156	[60]	LOADK    	43 -96	; "}"
	157	[60]	LOADK    	44 -97	; "]"
	158	[60]	SETLIST  	40 4 1	; 1
	159	[60]	NEWTABLE 	41 4 0
	160	[61]	LOADK    	42 -98	; "\214\184 "
	161	[61]	LOADK    	43 -99	; "\215\154"
	162	[61]	LOADK    	44 -100	; "_"
	163	[61]	LOADK    	45 -101	; "-"
	164	[61]	SETLIST  	41 4 1	; 1
	165	[62]	SETLIST  	32 9 1	; 1
	166	[62]	NEWTABLE 	33 9 0
	167	[64]	NEWTABLE 	34 0 2
	168	[65]	SETTABLE 	34 -102 -36	; "label" "\238\180\181"
	169	[66]	SETTABLE 	34 -103 -104	; "width" 1.5
	170	[67]	NEWTABLE 	35 4 0
	171	[68]	LOADK    	36 -105	; "\215\131"
	172	[68]	MOVE     	37 12
	173	[68]	LOADK    	38 -106	; "&"
	174	[68]	LOADK    	39 -107	; "7"
	175	[68]	SETLIST  	35 4 1	; 1
	176	[68]	NEWTABLE 	36 4 0
	177	[69]	LOADK    	37 -108	; "\215\128"
	178	[69]	MOVE     	38 20
	179	[69]	LOADK    	39 -109	; "*"
	180	[69]	LOADK    	40 -110	; "8"
	181	[69]	SETLIST  	36 4 1	; 1
	182	[69]	NEWTABLE 	37 4 0
	183	[70]	LOADK    	38 -111	; "\215\132 "
	184	[70]	MOVE     	39 7
	185	[70]	LOADK    	40 -112	; "\194\163"
	186	[70]	LOADK    	41 -113	; "9"
	187	[70]	SETLIST  	37 4 1	; 1
	188	[70]	NEWTABLE 	38 4 0
	189	[71]	LOADK    	39 -114	; "\215\133 "
	190	[71]	MOVE     	40 10
	191	[71]	LOADK    	41 -115	; "<"
	192	[71]	MOVE     	42 2
	193	[71]	SETLIST  	38 4 1	; 1
	194	[71]	NEWTABLE 	39 4 0
	195	[72]	LOADK    	40 -116	; "\214\190"
	196	[72]	MOVE     	41 19
	197	[72]	LOADK    	42 -117	; ">"
	198	[72]	MOVE     	43 3
	199	[72]	SETLIST  	39 4 1	; 1
	200	[72]	NEWTABLE 	40 4 0
	201	[73]	LOADK    	41 -118	; "\214\191 "
	202	[73]	MOVE     	42 17
	203	[73]	LOADK    	43 -119	; "\226\128\152"
	204	[73]	LOADK    	44 -120	; "\226\134\145"
	205	[73]	SETLIST  	40 4 1	; 1
	206	[73]	NEWTABLE 	41 4 0
	207	[74]	LOADK    	42 -121	; "\214\189 "
	208	[74]	MOVE     	43 24
	209	[74]	LOADK    	44 -122	; "\226\128\153"
	210	[74]	LOADK    	45 -123	; "\226\134\147"
	211	[74]	SETLIST  	41 4 1	; 1
	212	[74]	NEWTABLE 	42 0 3
	213	[75]	SETTABLE 	42 -102 -124	; "label" "\238\157\173"
	214	[76]	SETTABLE 	42 -103 -104	; "width" 1.5
	215	[77]	SETTABLE 	42 -125 -126	; "bold" false
	216	[79]	SETLIST  	33 9 1	; 1
	217	[79]	NEWTABLE 	34 6 0
	218	[81]	NEWTABLE 	35 4 1
	219	[82]	LOADK    	36 -39	; "Sym"
	220	[82]	LOADK    	37 -39	; "Sym"
	221	[82]	LOADK    	38 -40	; "\215\144\215\145\215\146"
	222	[82]	LOADK    	39 -40	; "\215\144\215\145\215\146"
	223	[83]	SETTABLE 	35 -103 -104	; "width" 1.5
	224	[83]	SETLIST  	35 4 1	; 1
	225	[83]	NEWTABLE 	36 0 1
	226	[84]	SETTABLE 	36 -102 -42	; "label" "\240\159\140\144"
	227	[84]	NEWTABLE 	37 4 1
	228	[85]	LOADK    	38 -127	; " "
	229	[85]	LOADK    	39 -127	; " "
	230	[85]	LOADK    	40 -127	; " "
	231	[85]	LOADK    	41 -127	; " "
	232	[86]	SETTABLE 	37 -103 -128	; "width" 3
	233	[86]	SETLIST  	37 4 1	; 1
	234	[86]	NEWTABLE 	38 4 0
	235	[87]	MOVE     	39 2
	236	[87]	MOVE     	40 28
	237	[87]	LOADK    	41 -129	; "\226\128\156"
	238	[87]	LOADK    	42 -130	; "\226\134\144"
	239	[87]	SETLIST  	38 4 1	; 1
	240	[87]	NEWTABLE 	39 4 0
	241	[88]	MOVE     	40 3
	242	[88]	LOADK    	41 -131	; "\215\165"
	243	[88]	LOADK    	42 -132	; "\226\128\157"
	244	[88]	LOADK    	43 -133	; "\226\134\146"
	245	[88]	SETLIST  	39 4 1	; 1
	246	[88]	NEWTABLE 	40 4 3
	247	[89]	SETTABLE 	40 -102 -134	; "label" "\226\174\160"
	248	[90]	LOADK    	41 -135	; "\n"
	249	[90]	LOADK    	42 -135	; "\n"
	250	[90]	LOADK    	43 -135	; "\n"
	251	[90]	LOADK    	44 -135	; "\n"
	252	[91]	SETTABLE 	40 -103 -104	; "width" 1.5
	253	[92]	SETTABLE 	40 -125 -37	; "bold" true
	254	[93]	SETLIST  	40 4 1	; 1
	255	[94]	SETLIST  	34 6 1	; 1
	256	[95]	SETLIST  	30 4 1	; 1
	257	[95]	SETTABLE 	29 -43 30	; "keys" -
	258	[96]	RETURN   	29 2
	259	[96]	RETURN   	0 1
