-- BYTECODE -- hook_container.lua:10-15
0001    IST          1
0002    JMP      2 => 0004
0003    TNEW     1   0
0004 => GGET     2   0      ; "setmetatable"
0005    MOV      3   1
0006    MOV      4   0
0007    CALL     2   1   3
0008    TSETS    0   0   1  ; "__index"
0009    RET1     1   2

-- BYTECODE -- hook_container.lua:17-21
0001    GGET     2   0      ; "assert"
0002    ISNEP    0   0
0003    JMP      3 => 0006
0004    KPRI     3   1
0005    JMP      4 => 0007
0006 => KPRI     3   2
0007 => CALL     2   1   2
0008    GGET     2   0      ; "assert"
0009    GGET     3   1      ; "type"
0010    MOV      4   1
0011    CALL     3   2   2
0012    ISEQS    3   2      ; "string"
0013    JMP      3 => 0016
0014    KPRI     3   1
0015    JMP      4 => 0017
0016 => KPRI     3   2
0017 => CALL     2   1   2
0018    GGET     2   0      ; "assert"
0019    GGET     3   2      ; "string"
0020    TGETS    3   3   3  ; "len"
0021    MOV      4   1
0022    CALL     3   2   2
0023    KSHORT   4   0
0024    ISLT     4   3
0025    JMP      3 => 0028
0026    KPRI     3   1
0027    JMP      4 => 0029
0028 => KPRI     3   2
0029 => CALL     2   1   2
0030    RET0     0   1

-- BYTECODE -- hook_container.lua:23-26
0001    GGET     2   0      ; "assert"
0002    ISNEP    0   0
0003    JMP      3 => 0006
0004    KPRI     3   1
0005    JMP      4 => 0007
0006 => KPRI     3   2
0007 => CALL     2   1   2
0008    GGET     2   0      ; "assert"
0009    GGET     3   1      ; "type"
0010    MOV      4   1
0011    CALL     3   2   2
0012    ISEQS    3   2      ; "function"
0013    JMP      3 => 0021
0014    GGET     3   1      ; "type"
0015    MOV      4   1
0016    CALL     3   2   2
0017    ISEQS    3   3      ; "table"
0018    JMP      3 => 0021
0019    KPRI     3   1
0020    JMP      4 => 0022
0021 => KPRI     3   2
0022 => CALL     2   1   2
0023    RET0     0   1

-- BYTECODE -- hook_container.lua:28-32
0001    GGET     2   0      ; "assert"
0002    ISNEP    0   0
0003    JMP      3 => 0006
0004    KPRI     3   1
0005    JMP      4 => 0007
0006 => KPRI     3   2
0007 => CALL     2   1   2
0008    ISNEP    1   0
0009    JMP      2 => 0011
0010    RET0     0   1
0011 => MOV      3   0
0012    TGETS    2   0   1  ; "_assertIsValidFunction"
0013    MOV      4   1
0014    CALL     2   1   3
0015    RET0     0   1

-- BYTECODE -- hook_container.lua:37-44
0001    MOV      4   0
0002    TGETS    3   0   0  ; "_assertIsValidName"
0003    MOV      5   1
0004    CALL     3   1   3
0005    MOV      4   0
0006    TGETS    3   0   1  ; "_assertIsValidFunction"
0007    MOV      5   2
0008    CALL     3   1   3
0009    TGETV    3   0   1
0010    ISNEP    3   0
0011    JMP      3 => 0014
0012    TNEW     3   0
0013    TSETV    3   0   1
0014 => GGET     3   2      ; "table"
0015    TGETS    3   3   3  ; "insert"
0016    TGETV    4   0   1
0017    MOV      5   2
0018    CALL     3   1   3
0019    RET0     0   1

-- BYTECODE -- hook_container.lua:52-56
0001    UGET     1   0      ; widget
0002    KSTR     2   0      ; "on"
0003    UGET     3   1      ; name
0004    CAT      2   2   3
0005    TGETV    1   1   2
0006    UGET     2   2      ; self
0007    MOV      3   2
0008    TGETS    2   2   1  ; "_assertIsValidFunction"
0009    MOV      4   1
0010    CALL     2   1   3
0011    MOV      2   1
0012    UGET     3   0      ; widget
0013    MOV      4   0
0014    CALL     2   1   3
0015    RET0     0   1

-- BYTECODE -- hook_container.lua:59-62
0001    UGET     0   0      ; original_close_widget
0002    ISF          0
0003    JMP      1 => 0007
0004    UGET     0   0      ; original_close_widget
0005    UGET     1   1      ; widget
0006    CALL     0   1   2
0007 => UGET     0   2      ; self
0008    MOV      1   0
0009    TGETS    0   0   0  ; "unregister"
0010    UGET     2   3      ; name
0011    UGET     3   1      ; widget
0012    KSTR     4   1      ; "on"
0013    UGET     5   3      ; name
0014    CAT      4   4   5
0015    TGETV    3   3   4
0016    CALL     0   1   4
0017    RET0     0   1

-- BYTECODE -- hook_container.lua:49-63
0001    MOV      4   0
0002    TGETS    3   0   0  ; "_assertIsValidName"
0003    MOV      5   1
0004    CALL     3   1   3
0005    GGET     3   1      ; "assert"
0006    GGET     4   2      ; "type"
0007    MOV      5   2
0008    CALL     4   2   2
0009    ISEQS    4   3      ; "table"
0010    JMP      4 => 0013
0011    KPRI     4   1
0012    JMP      5 => 0014
0013 => KPRI     4   2
0014 => CALL     3   1   2
0015    MOV      4   0
0016    TGETS    3   0   4  ; "register"
0017    MOV      5   1
0018    FNEW     6   5      ; hook_container.lua:52
0019    CALL     3   1   4
0020    TGETS    3   2   6  ; "onCloseWidget"
0021    MOV      5   0
0022    TGETS    4   0   7  ; "_assertIsValidFunctionOrNil"
0023    MOV      6   3
0024    CALL     4   1   3
0025    FNEW     4   8      ; hook_container.lua:59
0026    TSETS    4   2   6  ; "onCloseWidget"
0027    UCLO     0 => 0028
0028 => RET0     0   1

-- BYTECODE -- hook_container.lua:69-83
0001    MOV      4   0
0002    TGETS    3   0   0  ; "_assertIsValidName"
0003    MOV      5   1
0004    CALL     3   1   3
0005    MOV      4   0
0006    TGETS    3   0   1  ; "_assertIsValidFunction"
0007    MOV      5   2
0008    CALL     3   1   3
0009    TGETV    3   0   1
0010    ISNEP    3   0
0011    JMP      3 => 0014
0012    KPRI     3   1
0013    RET1     3   2
0014 => GGET     3   2      ; "ipairs"
0015    TGETV    4   0   1
0016    CALL     3   4   2
0017    JMP      6 => 0027
0018 => ISNEV    7   2
0019    JMP      8 => 0027
0020    GGET     8   3      ; "table"
0021    TGETS    8   8   4  ; "remove"
0022    TGETV    9   0   1
0023    MOV     10   6
0024    CALL     8   1   3
0025    KPRI     8   2
0026    RET1     8   2
0027 => ITERC    6   3   3
0028    ITERL    6 => 0018
0029    KPRI     3   1
0030    RET1     3   2

-- BYTECODE -- hook_container.lua:89-99
0001    MOV      4   0
0002    TGETS    3   0   0  ; "_assertIsValidName"
0003    MOV      5   1
0004    CALL     3   1   3
0005    TGETV    3   0   1
0006    ISEQP    3   0
0007    JMP      3 => 0012
0008    TGETV    3   0   1
0009    LEN      3   3
0010    ISNEN    3   0      ; 0
0011    JMP      3 => 0014
0012 => KSHORT   3   0
0013    RET1     3   2
0014 => GGET     3   1      ; "ipairs"
0015    TGETV    4   0   1
0016    CALL     3   4   2
0017    JMP      6 => 0021
0018 => MOV      8   7
0019    MOV      9   2
0020    CALL     8   1   2
0021 => ITERC    6   3   3
0022    ITERL    6 => 0018
0023    TGETV    3   0   1
0024    LEN      3   3
0025    RET1     3   2

-- BYTECODE -- hook_container.lua:0-102
0001    TNEW     0   0
0002    FNEW     1   1      ; hook_container.lua:10
0003    TSETS    1   0   0  ; "new"
0004    FNEW     1   3      ; hook_container.lua:17
0005    TSETS    1   0   2  ; "_assertIsValidName"
0006    FNEW     1   5      ; hook_container.lua:23
0007    TSETS    1   0   4  ; "_assertIsValidFunction"
0008    FNEW     1   7      ; hook_container.lua:28
0009    TSETS    1   0   6  ; "_assertIsValidFunctionOrNil"
0010    FNEW     1   9      ; hook_container.lua:37
0011    TSETS    1   0   8  ; "register"
0012    FNEW     1  11      ; hook_container.lua:49
0013    TSETS    1   0  10  ; "registerWidget"
0014    FNEW     1  13      ; hook_container.lua:69
0015    TSETS    1   0  12  ; "unregister"
0016    FNEW     1  15      ; hook_container.lua:89
0017    TSETS    1   0  14  ; "execute"
0018    UCLO     0 => 0019
0019 => RET1     0   2

