
main <./frontend/ui/hook_container.lua:0,0> (19 instructions, 76 bytes at 0x7f83934068d0)
0+ params, 2 slots, 0 upvalues, 1 local, 8 constants, 8 functions
	1	[8]	NEWTABLE 	0 0 0
	2	[15]	CLOSURE  	1 0	; 0x7f8393406b80
	3	[10]	SETTABLE 	0 -1 1	; "new" -
	4	[21]	CLOSURE  	1 1	; 0x7f8393406d00
	5	[17]	SETTABLE 	0 -2 1	; "_assertIsValidName" -
	6	[26]	CLOSURE  	1 2	; 0x7f8393407220
	7	[23]	SETTABLE 	0 -3 1	; "_assertIsValidFunction" -
	8	[32]	CLOSURE  	1 3	; 0x7f83934078c0
	9	[28]	SETTABLE 	0 -4 1	; "_assertIsValidFunctionOrNil" -
	10	[44]	CLOSURE  	1 4	; 0x7f8393407e20
	11	[37]	SETTABLE 	0 -5 1	; "register" -
	12	[63]	CLOSURE  	1 5	; 0x7f8393406f80
	13	[49]	SETTABLE 	0 -6 1	; "registerWidget" -
	14	[83]	CLOSURE  	1 6	; 0x7f83934090d0
	15	[69]	SETTABLE 	0 -7 1	; "unregister" -
	16	[99]	CLOSURE  	1 7	; 0x7f8393409710
	17	[89]	SETTABLE 	0 -8 1	; "execute" -
	18	[101]	RETURN   	0 2
	19	[101]	RETURN   	0 1

function <./frontend/ui/hook_container.lua:10,15> (11 instructions, 44 bytes at 0x7f8393406b80)
2 params, 5 slots, 0 upvalues, 2 locals, 2 constants, 0 functions
	1	[11]	TEST     	1 0 1
	2	[11]	JMP      	2	; to 5
	3	[11]	NEWTABLE 	2 0 0
	4	[11]	MOVE     	1 2
	5	[12]	GETGLOBAL	2 -1	; setmetatable
	6	[12]	MOVE     	3 1
	7	[12]	MOVE     	4 0
	8	[12]	CALL     	2 3 1
	9	[13]	SETTABLE 	0 -2 0	; "__index" -
	10	[14]	RETURN   	1 2
	11	[15]	RETURN   	0 1

function <./frontend/ui/hook_container.lua:17,21> (26 instructions, 104 bytes at 0x7f8393406d00)
2 params, 5 slots, 0 upvalues, 2 locals, 6 constants, 0 functions
	1	[18]	GETGLOBAL	2 -1	; assert
	2	[18]	EQ       	0 0 -2	; - nil
	3	[18]	JMP      	1	; to 5
	4	[18]	LOADBOOL 	3 0 1
	5	[18]	LOADBOOL 	3 1 0
	6	[18]	CALL     	2 2 1
	7	[19]	GETGLOBAL	2 -1	; assert
	8	[19]	GETGLOBAL	3 -3	; type
	9	[19]	MOVE     	4 1
	10	[19]	CALL     	3 2 2
	11	[19]	EQ       	1 3 -4	; - "string"
	12	[19]	JMP      	1	; to 14
	13	[19]	LOADBOOL 	3 0 1
	14	[19]	LOADBOOL 	3 1 0
	15	[19]	CALL     	2 2 1
	16	[20]	GETGLOBAL	2 -1	; assert
	17	[20]	GETGLOBAL	3 -4	; string
	18	[20]	GETTABLE 	3 3 -5	; "len"
	19	[20]	MOVE     	4 1
	20	[20]	CALL     	3 2 2
	21	[20]	LT       	1 -6 3	; 0 -
	22	[20]	JMP      	1	; to 24
	23	[20]	LOADBOOL 	3 0 1
	24	[20]	LOADBOOL 	3 1 0
	25	[20]	CALL     	2 2 1
	26	[21]	RETURN   	0 1

function <./frontend/ui/hook_container.lua:23,26> (21 instructions, 84 bytes at 0x7f8393407220)
2 params, 5 slots, 0 upvalues, 2 locals, 5 constants, 0 functions
	1	[24]	GETGLOBAL	2 -1	; assert
	2	[24]	EQ       	0 0 -2	; - nil
	3	[24]	JMP      	1	; to 5
	4	[24]	LOADBOOL 	3 0 1
	5	[24]	LOADBOOL 	3 1 0
	6	[24]	CALL     	2 2 1
	7	[25]	GETGLOBAL	2 -1	; assert
	8	[25]	GETGLOBAL	3 -3	; type
	9	[25]	MOVE     	4 1
	10	[25]	CALL     	3 2 2
	11	[25]	EQ       	1 3 -4	; - "function"
	12	[25]	JMP      	6	; to 19
	13	[25]	GETGLOBAL	3 -3	; type
	14	[25]	MOVE     	4 1
	15	[25]	CALL     	3 2 2
	16	[25]	EQ       	1 3 -5	; - "table"
	17	[25]	JMP      	1	; to 19
	18	[25]	LOADBOOL 	3 0 1
	19	[25]	LOADBOOL 	3 1 0
	20	[25]	CALL     	2 2 1
	21	[26]	RETURN   	0 1

function <./frontend/ui/hook_container.lua:28,32> (13 instructions, 52 bytes at 0x7f83934078c0)
2 params, 5 slots, 0 upvalues, 2 locals, 3 constants, 0 functions
	1	[29]	GETGLOBAL	2 -1	; assert
	2	[29]	EQ       	0 0 -2	; - nil
	3	[29]	JMP      	1	; to 5
	4	[29]	LOADBOOL 	3 0 1
	5	[29]	LOADBOOL 	3 1 0
	6	[29]	CALL     	2 2 1
	7	[30]	EQ       	0 1 -2	; - nil
	8	[30]	JMP      	1	; to 10
	9	[30]	RETURN   	0 1
	10	[31]	SELF     	2 0 -3	; "_assertIsValidFunction"
	11	[31]	MOVE     	4 1
	12	[31]	CALL     	2 3 1
	13	[32]	RETURN   	0 1

function <./frontend/ui/hook_container.lua:37,44> (17 instructions, 68 bytes at 0x7f8393407e20)
3 params, 6 slots, 0 upvalues, 3 locals, 5 constants, 0 functions
	1	[38]	SELF     	3 0 -1	; "_assertIsValidName"
	2	[38]	MOVE     	5 1
	3	[38]	CALL     	3 3 1
	4	[39]	SELF     	3 0 -2	; "_assertIsValidFunction"
	5	[39]	MOVE     	5 2
	6	[39]	CALL     	3 3 1
	7	[40]	GETTABLE 	3 0 1
	8	[40]	EQ       	0 3 -3	; - nil
	9	[40]	JMP      	2	; to 12
	10	[41]	NEWTABLE 	3 0 0
	11	[41]	SETTABLE 	0 1 3
	12	[43]	GETGLOBAL	3 -4	; table
	13	[43]	GETTABLE 	3 3 -5	; "insert"
	14	[43]	GETTABLE 	4 0 1
	15	[43]	MOVE     	5 2
	16	[43]	CALL     	3 3 1
	17	[44]	RETURN   	0 1

function <./frontend/ui/hook_container.lua:49,63> (30 instructions, 120 bytes at 0x7f8393406f80)
3 params, 7 slots, 0 upvalues, 4 locals, 7 constants, 2 functions
	1	[50]	SELF     	3 0 -1	; "_assertIsValidName"
	2	[50]	MOVE     	5 1
	3	[50]	CALL     	3 3 1
	4	[51]	GETGLOBAL	3 -2	; assert
	5	[51]	GETGLOBAL	4 -3	; type
	6	[51]	MOVE     	5 2
	7	[51]	CALL     	4 2 2
	8	[51]	EQ       	1 4 -4	; - "table"
	9	[51]	JMP      	1	; to 11
	10	[51]	LOADBOOL 	4 0 1
	11	[51]	LOADBOOL 	4 1 0
	12	[51]	CALL     	3 2 1
	13	[52]	SELF     	3 0 -5	; "register"
	14	[52]	MOVE     	5 1
	15	[56]	CLOSURE  	6 0	; 0x7f83934089b0
	16	[56]	MOVE     	0 2
	17	[56]	MOVE     	0 1
	18	[56]	MOVE     	0 0
	19	[52]	CALL     	3 4 1
	20	[57]	GETTABLE 	3 2 -6	; "onCloseWidget"
	21	[58]	SELF     	4 0 -7	; "_assertIsValidFunctionOrNil"
	22	[58]	MOVE     	6 3
	23	[58]	CALL     	4 3 1
	24	[62]	CLOSURE  	4 1	; 0x7f83934066c0
	25	[62]	MOVE     	0 3
	26	[62]	MOVE     	0 2
	27	[62]	MOVE     	0 0
	28	[62]	MOVE     	0 1
	29	[62]	SETTABLE 	2 -6 4	; "onCloseWidget" -
	30	[63]	RETURN   	0 1

function <./frontend/ui/hook_container.lua:52,56> (14 instructions, 56 bytes at 0x7f83934089b0)
1 param, 5 slots, 3 upvalues, 2 locals, 2 constants, 0 functions
	1	[53]	GETUPVAL 	1 0	; widget
	2	[53]	LOADK    	2 -1	; "on"
	3	[53]	GETUPVAL 	3 1	; name
	4	[53]	CONCAT   	2 2 3
	5	[53]	GETTABLE 	1 1 2
	6	[54]	GETUPVAL 	2 2	; self
	7	[54]	SELF     	2 2 -2	; "_assertIsValidFunction"
	8	[54]	MOVE     	4 1
	9	[54]	CALL     	2 3 1
	10	[55]	MOVE     	2 1
	11	[55]	GETUPVAL 	3 0	; widget
	12	[55]	MOVE     	4 0
	13	[55]	CALL     	2 3 1
	14	[56]	RETURN   	0 1

function <./frontend/ui/hook_container.lua:59,62> (16 instructions, 64 bytes at 0x7f83934066c0)
0 params, 6 slots, 4 upvalues, 0 locals, 2 constants, 0 functions
	1	[60]	GETUPVAL 	0 0	; original_close_widget
	2	[60]	TEST     	0 0 0
	3	[60]	JMP      	3	; to 7
	4	[60]	GETUPVAL 	0 0	; original_close_widget
	5	[60]	GETUPVAL 	1 1	; widget
	6	[60]	CALL     	0 2 1
	7	[61]	GETUPVAL 	0 2	; self
	8	[61]	SELF     	0 0 -1	; "unregister"
	9	[61]	GETUPVAL 	2 3	; name
	10	[61]	GETUPVAL 	3 1	; widget
	11	[61]	LOADK    	4 -2	; "on"
	12	[61]	GETUPVAL 	5 3	; name
	13	[61]	CONCAT   	4 4 5
	14	[61]	GETTABLE 	3 3 4
	15	[61]	CALL     	0 4 1
	16	[62]	RETURN   	0 1

function <./frontend/ui/hook_container.lua:69,83> (29 instructions, 116 bytes at 0x7f83934090d0)
3 params, 11 slots, 0 upvalues, 8 locals, 6 constants, 0 functions
	1	[70]	SELF     	3 0 -1	; "_assertIsValidName"
	2	[70]	MOVE     	5 1
	3	[70]	CALL     	3 3 1
	4	[71]	SELF     	3 0 -2	; "_assertIsValidFunction"
	5	[71]	MOVE     	5 2
	6	[71]	CALL     	3 3 1
	7	[72]	GETTABLE 	3 0 1
	8	[72]	EQ       	0 3 -3	; - nil
	9	[72]	JMP      	2	; to 12
	10	[73]	LOADBOOL 	3 0 0
	11	[73]	RETURN   	3 2
	12	[76]	GETGLOBAL	3 -4	; ipairs
	13	[76]	GETTABLE 	4 0 1
	14	[76]	CALL     	3 2 4
	15	[76]	JMP      	9	; to 25
	16	[77]	EQ       	0 7 2
	17	[77]	JMP      	7	; to 25
	18	[78]	GETGLOBAL	8 -5	; table
	19	[78]	GETTABLE 	8 8 -6	; "remove"
	20	[78]	GETTABLE 	9 0 1
	21	[78]	MOVE     	10 6
	22	[78]	CALL     	8 3 1
	23	[79]	LOADBOOL 	8 1 0
	24	[79]	RETURN   	8 2
	25	[76]	TFORLOOP 	3 2
	26	[80]	JMP      	-11	; to 16
	27	[82]	LOADBOOL 	3 0 0
	28	[82]	RETURN   	3 2
	29	[83]	RETURN   	0 1

function <./frontend/ui/hook_container.lua:89,99> (25 instructions, 100 bytes at 0x7f8393409710)
3 params, 10 slots, 0 upvalues, 8 locals, 4 constants, 0 functions
	1	[90]	SELF     	3 0 -1	; "_assertIsValidName"
	2	[90]	MOVE     	5 1
	3	[90]	CALL     	3 3 1
	4	[91]	GETTABLE 	3 0 1
	5	[91]	EQ       	1 3 -2	; - nil
	6	[91]	JMP      	4	; to 11
	7	[91]	GETTABLE 	3 0 1
	8	[91]	LEN      	3 3
	9	[91]	EQ       	0 3 -3	; - 0
	10	[91]	JMP      	2	; to 13
	11	[92]	LOADK    	3 -3	; 0
	12	[92]	RETURN   	3 2
	13	[95]	GETGLOBAL	3 -4	; ipairs
	14	[95]	GETTABLE 	4 0 1
	15	[95]	CALL     	3 2 4
	16	[95]	JMP      	3	; to 20
	17	[96]	MOVE     	8 7
	18	[96]	MOVE     	9 2
	19	[96]	CALL     	8 2 1
	20	[95]	TFORLOOP 	3 2
	21	[96]	JMP      	-5	; to 17
	22	[98]	GETTABLE 	3 0 1
	23	[98]	LEN      	3 3
	24	[98]	RETURN   	3 2
	25	[99]	RETURN   	0 1
