
main <./spec/unit/hook_container_spec.lua:0,0> (5 instructions, 20 bytes at 0x7fa2144068d0)
0+ params, 3 slots, 0 upvalues, 0 locals, 2 constants, 1 function
	1	[1]	GETGLOBAL	0 -1	; describe
	2	[1]	LOADK    	1 -2	; "HookContainer tests"
	3	[72]	CLOSURE  	2 0	; 0x7fa214406b70
	4	[1]	CALL     	0 3 1
	5	[72]	RETURN   	0 1

function <./spec/unit/hook_container_spec.lua:1,72> (16 instructions, 64 bytes at 0x7fa214406b70)
0 params, 3 slots, 0 upvalues, 0 locals, 5 constants, 4 functions
	1	[2]	GETGLOBAL	0 -1	; setup
	2	[4]	CLOSURE  	1 0	; 0x7fa214406cb0
	3	[2]	CALL     	0 2 1
	4	[6]	GETGLOBAL	0 -2	; it
	5	[6]	LOADK    	1 -3	; "should register and unregister functions"
	6	[34]	CLOSURE  	2 1	; 0x7fa214406fd0
	7	[6]	CALL     	0 3 1
	8	[36]	GETGLOBAL	0 -2	; it
	9	[36]	LOADK    	1 -4	; "should register and automatically unregister widget"
	10	[50]	CLOSURE  	2 2	; 0x7fa214406f10
	11	[36]	CALL     	0 3 1
	12	[52]	GETGLOBAL	0 -2	; it
	13	[52]	LOADK    	1 -5	; "should pass widget itself"
	14	[71]	CLOSURE  	2 3	; 0x7fa2144066f0
	15	[52]	CALL     	0 3 1
	16	[72]	RETURN   	0 1

function <./spec/unit/hook_container_spec.lua:2,4> (4 instructions, 16 bytes at 0x7fa214406cb0)
0 params, 2 slots, 0 upvalues, 0 locals, 2 constants, 0 functions
	1	[3]	GETGLOBAL	0 -1	; require
	2	[3]	LOADK    	1 -2	; "commonrequire"
	3	[3]	CALL     	0 2 1
	4	[4]	RETURN   	0 1

function <./spec/unit/hook_container_spec.lua:6,34> (166 instructions, 664 bytes at 0x7fa214406fd0)
0 params, 9 slots, 0 upvalues, 4 locals, 23 constants, 3 functions
	1	[7]	GETGLOBAL	0 -1	; require
	2	[7]	LOADK    	1 -2	; "ui/hook_container"
	3	[7]	CALL     	0 2 2
	4	[7]	SELF     	0 0 -3	; "new"
	5	[7]	CALL     	0 2 2
	6	[8]	GETGLOBAL	1 -4	; spy
	7	[8]	GETTABLE 	1 1 -3	; "new"
	8	[8]	CLOSURE  	2 0	; 0x7fa2144073c0
	9	[8]	CALL     	1 2 2
	10	[9]	GETGLOBAL	2 -4	; spy
	11	[9]	GETTABLE 	2 2 -3	; "new"
	12	[9]	CLOSURE  	3 1	; 0x7fa214407280
	13	[9]	CALL     	2 2 2
	14	[10]	GETGLOBAL	3 -4	; spy
	15	[10]	GETTABLE 	3 3 -3	; "new"
	16	[10]	CLOSURE  	4 2	; 0x7fa214407770
	17	[10]	CALL     	3 2 2
	18	[11]	SELF     	4 0 -5	; "register"
	19	[11]	LOADK    	6 -6	; "a"
	20	[11]	MOVE     	7 1
	21	[11]	CALL     	4 4 1
	22	[12]	SELF     	4 0 -5	; "register"
	23	[12]	LOADK    	6 -6	; "a"
	24	[12]	MOVE     	7 2
	25	[12]	CALL     	4 4 1
	26	[13]	SELF     	4 0 -5	; "register"
	27	[13]	LOADK    	6 -7	; "b"
	28	[13]	MOVE     	7 3
	29	[13]	CALL     	4 4 1
	30	[14]	GETGLOBAL	4 -8	; assert
	31	[14]	GETTABLE 	4 4 -9	; "are"
	32	[14]	GETTABLE 	4 4 -10	; "equal"
	33	[14]	SELF     	5 0 -11	; "execute"
	34	[14]	LOADK    	7 -6	; "a"
	35	[14]	LOADK    	8 -12	; 100
	36	[14]	CALL     	5 4 2
	37	[14]	LOADK    	6 -13	; 2
	38	[14]	CALL     	4 3 1
	39	[15]	GETGLOBAL	4 -8	; assert
	40	[15]	GETTABLE 	4 4 -9	; "are"
	41	[15]	GETTABLE 	4 4 -10	; "equal"
	42	[15]	SELF     	5 0 -11	; "execute"
	43	[15]	LOADK    	7 -7	; "b"
	44	[15]	LOADK    	8 -14	; 200
	45	[15]	CALL     	5 4 2
	46	[15]	LOADK    	6 -15	; 1
	47	[15]	CALL     	4 3 1
	48	[16]	GETGLOBAL	4 -8	; assert
	49	[16]	GETTABLE 	4 4 -4	; "spy"
	50	[16]	MOVE     	5 1
	51	[16]	CALL     	4 2 2
	52	[16]	GETTABLE 	4 4 -16	; "was_called"
	53	[16]	LOADK    	5 -15	; 1
	54	[16]	CALL     	4 2 1
	55	[17]	GETGLOBAL	4 -8	; assert
	56	[17]	GETTABLE 	4 4 -4	; "spy"
	57	[17]	MOVE     	5 1
	58	[17]	CALL     	4 2 2
	59	[17]	GETTABLE 	4 4 -17	; "was_called_with"
	60	[17]	LOADK    	5 -12	; 100
	61	[17]	CALL     	4 2 1
	62	[18]	GETGLOBAL	4 -8	; assert
	63	[18]	GETTABLE 	4 4 -4	; "spy"
	64	[18]	MOVE     	5 2
	65	[18]	CALL     	4 2 2
	66	[18]	GETTABLE 	4 4 -16	; "was_called"
	67	[18]	LOADK    	5 -15	; 1
	68	[18]	CALL     	4 2 1
	69	[19]	GETGLOBAL	4 -8	; assert
	70	[19]	GETTABLE 	4 4 -4	; "spy"
	71	[19]	MOVE     	5 2
	72	[19]	CALL     	4 2 2
	73	[19]	GETTABLE 	4 4 -17	; "was_called_with"
	74	[19]	LOADK    	5 -12	; 100
	75	[19]	CALL     	4 2 1
	76	[20]	GETGLOBAL	4 -8	; assert
	77	[20]	GETTABLE 	4 4 -4	; "spy"
	78	[20]	MOVE     	5 3
	79	[20]	CALL     	4 2 2
	80	[20]	GETTABLE 	4 4 -16	; "was_called"
	81	[20]	LOADK    	5 -15	; 1
	82	[20]	CALL     	4 2 1
	83	[21]	GETGLOBAL	4 -8	; assert
	84	[21]	GETTABLE 	4 4 -4	; "spy"
	85	[21]	MOVE     	5 3
	86	[21]	CALL     	4 2 2
	87	[21]	GETTABLE 	4 4 -17	; "was_called_with"
	88	[21]	LOADK    	5 -14	; 200
	89	[21]	CALL     	4 2 1
	90	[23]	GETGLOBAL	4 -8	; assert
	91	[23]	GETTABLE 	4 4 -18	; "is"
	92	[23]	GETTABLE 	4 4 -19	; "truthy"
	93	[23]	SELF     	5 0 -20	; "unregister"
	94	[23]	LOADK    	7 -6	; "a"
	95	[23]	MOVE     	8 1
	96	[23]	CALL     	5 4 0
	97	[23]	CALL     	4 0 1
	98	[24]	GETGLOBAL	4 -8	; assert
	99	[24]	GETTABLE 	4 4 -18	; "is"
	100	[24]	GETTABLE 	4 4 -21	; "falsy"
	101	[24]	SELF     	5 0 -20	; "unregister"
	102	[24]	LOADK    	7 -7	; "b"
	103	[24]	MOVE     	8 2
	104	[24]	CALL     	5 4 0
	105	[24]	CALL     	4 0 1
	106	[26]	GETGLOBAL	4 -8	; assert
	107	[26]	GETTABLE 	4 4 -9	; "are"
	108	[26]	GETTABLE 	4 4 -10	; "equal"
	109	[26]	SELF     	5 0 -11	; "execute"
	110	[26]	LOADK    	7 -6	; "a"
	111	[26]	LOADK    	8 -22	; 300
	112	[26]	CALL     	5 4 2
	113	[26]	LOADK    	6 -15	; 1
	114	[26]	CALL     	4 3 1
	115	[27]	GETGLOBAL	4 -8	; assert
	116	[27]	GETTABLE 	4 4 -9	; "are"
	117	[27]	GETTABLE 	4 4 -10	; "equal"
	118	[27]	SELF     	5 0 -11	; "execute"
	119	[27]	LOADK    	7 -7	; "b"
	120	[27]	LOADK    	8 -23	; 400
	121	[27]	CALL     	5 4 2
	122	[27]	LOADK    	6 -15	; 1
	123	[27]	CALL     	4 3 1
	124	[28]	GETGLOBAL	4 -8	; assert
	125	[28]	GETTABLE 	4 4 -4	; "spy"
	126	[28]	MOVE     	5 1
	127	[28]	CALL     	4 2 2
	128	[28]	GETTABLE 	4 4 -16	; "was_called"
	129	[28]	LOADK    	5 -15	; 1
	130	[28]	CALL     	4 2 1
	131	[29]	GETGLOBAL	4 -8	; assert
	132	[29]	GETTABLE 	4 4 -4	; "spy"
	133	[29]	MOVE     	5 1
	134	[29]	CALL     	4 2 2
	135	[29]	GETTABLE 	4 4 -17	; "was_called_with"
	136	[29]	LOADK    	5 -12	; 100
	137	[29]	CALL     	4 2 1
	138	[30]	GETGLOBAL	4 -8	; assert
	139	[30]	GETTABLE 	4 4 -4	; "spy"
	140	[30]	MOVE     	5 2
	141	[30]	CALL     	4 2 2
	142	[30]	GETTABLE 	4 4 -16	; "was_called"
	143	[30]	LOADK    	5 -13	; 2
	144	[30]	CALL     	4 2 1
	145	[31]	GETGLOBAL	4 -8	; assert
	146	[31]	GETTABLE 	4 4 -4	; "spy"
	147	[31]	MOVE     	5 2
	148	[31]	CALL     	4 2 2
	149	[31]	GETTABLE 	4 4 -17	; "was_called_with"
	150	[31]	LOADK    	5 -22	; 300
	151	[31]	CALL     	4 2 1
	152	[32]	GETGLOBAL	4 -8	; assert
	153	[32]	GETTABLE 	4 4 -4	; "spy"
	154	[32]	MOVE     	5 3
	155	[32]	CALL     	4 2 2
	156	[32]	GETTABLE 	4 4 -16	; "was_called"
	157	[32]	LOADK    	5 -13	; 2
	158	[32]	CALL     	4 2 1
	159	[33]	GETGLOBAL	4 -8	; assert
	160	[33]	GETTABLE 	4 4 -4	; "spy"
	161	[33]	MOVE     	5 3
	162	[33]	CALL     	4 2 2
	163	[33]	GETTABLE 	4 4 -17	; "was_called_with"
	164	[33]	LOADK    	5 -23	; 400
	165	[33]	CALL     	4 2 1
	166	[34]	RETURN   	0 1

function <./spec/unit/hook_container_spec.lua:8,8> (1 instruction, 4 bytes at 0x7fa2144073c0)
0 params, 2 slots, 0 upvalues, 0 locals, 0 constants, 0 functions
	1	[8]	RETURN   	0 1

function <./spec/unit/hook_container_spec.lua:9,9> (1 instruction, 4 bytes at 0x7fa214407280)
0 params, 2 slots, 0 upvalues, 0 locals, 0 constants, 0 functions
	1	[9]	RETURN   	0 1

function <./spec/unit/hook_container_spec.lua:10,10> (1 instruction, 4 bytes at 0x7fa214407770)
0 params, 2 slots, 0 upvalues, 0 locals, 0 constants, 0 functions
	1	[10]	RETURN   	0 1

function <./spec/unit/hook_container_spec.lua:36,50> (69 instructions, 276 bytes at 0x7fa214406f10)
0 params, 8 slots, 0 upvalues, 3 locals, 20 constants, 2 functions
	1	[37]	GETGLOBAL	0 -1	; require
	2	[37]	LOADK    	1 -2	; "ui/hook_container"
	3	[37]	CALL     	0 2 2
	4	[37]	SELF     	0 0 -3	; "new"
	5	[37]	CALL     	0 2 2
	6	[38]	GETGLOBAL	1 -1	; require
	7	[38]	LOADK    	2 -4	; "ui/widget/widget"
	8	[38]	CALL     	1 2 2
	9	[38]	SELF     	1 1 -3	; "new"
	10	[38]	CALL     	1 2 2
	11	[39]	GETGLOBAL	2 -6	; spy
	12	[39]	GETTABLE 	2 2 -3	; "new"
	13	[39]	CLOSURE  	3 0	; 0x7fa214407640
	14	[39]	CALL     	2 2 2
	15	[39]	SETTABLE 	1 -5 2	; "onEvent" -
	16	[40]	GETGLOBAL	2 -6	; spy
	17	[40]	GETTABLE 	2 2 -3	; "new"
	18	[40]	CLOSURE  	3 1	; 0x7fa214406640
	19	[40]	CALL     	2 2 2
	20	[41]	SETTABLE 	1 -7 2	; "onCloseWidget" -
	21	[42]	SELF     	3 0 -8	; "registerWidget"
	22	[42]	LOADK    	5 -9	; "Event"
	23	[42]	MOVE     	6 1
	24	[42]	CALL     	3 4 1
	25	[43]	GETGLOBAL	3 -10	; assert
	26	[43]	GETTABLE 	3 3 -11	; "are"
	27	[43]	GETTABLE 	3 3 -12	; "equal"
	28	[43]	SELF     	4 0 -13	; "execute"
	29	[43]	LOADK    	6 -9	; "Event"
	30	[43]	NEWTABLE 	7 0 2
	31	[43]	SETTABLE 	7 -14 -15	; "a" 100
	32	[43]	SETTABLE 	7 -16 -17	; "b" 200
	33	[43]	CALL     	4 4 2
	34	[43]	LOADK    	5 -18	; 1
	35	[43]	CALL     	3 3 1
	36	[44]	GETGLOBAL	3 -10	; assert
	37	[44]	GETTABLE 	3 3 -6	; "spy"
	38	[44]	GETTABLE 	4 1 -5	; "onEvent"
	39	[44]	CALL     	3 2 2
	40	[44]	GETTABLE 	3 3 -19	; "was_called"
	41	[44]	LOADK    	4 -18	; 1
	42	[44]	CALL     	3 2 1
	43	[45]	GETGLOBAL	3 -10	; assert
	44	[45]	GETTABLE 	3 3 -6	; "spy"
	45	[45]	GETTABLE 	4 1 -5	; "onEvent"
	46	[45]	CALL     	3 2 2
	47	[45]	GETTABLE 	3 3 -20	; "was_called_with"
	48	[45]	MOVE     	4 1
	49	[45]	NEWTABLE 	5 0 2
	50	[45]	SETTABLE 	5 -14 -15	; "a" 100
	51	[45]	SETTABLE 	5 -16 -17	; "b" 200
	52	[45]	CALL     	3 3 1
	53	[47]	SELF     	3 1 -7	; "onCloseWidget"
	54	[47]	CALL     	3 2 1
	55	[48]	GETGLOBAL	3 -10	; assert
	56	[48]	GETTABLE 	3 3 -6	; "spy"
	57	[48]	MOVE     	4 2
	58	[48]	CALL     	3 2 2
	59	[48]	GETTABLE 	3 3 -19	; "was_called"
	60	[48]	LOADK    	4 -18	; 1
	61	[48]	CALL     	3 2 1
	62	[49]	GETGLOBAL	3 -10	; assert
	63	[49]	GETTABLE 	3 3 -6	; "spy"
	64	[49]	MOVE     	4 2
	65	[49]	CALL     	3 2 2
	66	[49]	GETTABLE 	3 3 -20	; "was_called_with"
	67	[49]	MOVE     	4 1
	68	[49]	CALL     	3 2 1
	69	[50]	RETURN   	0 1

function <./spec/unit/hook_container_spec.lua:39,39> (1 instruction, 4 bytes at 0x7fa214407640)
0 params, 2 slots, 0 upvalues, 0 locals, 0 constants, 0 functions
	1	[39]	RETURN   	0 1

function <./spec/unit/hook_container_spec.lua:40,40> (1 instruction, 4 bytes at 0x7fa214406640)
0 params, 2 slots, 0 upvalues, 0 locals, 0 constants, 0 functions
	1	[40]	RETURN   	0 1

function <./spec/unit/hook_container_spec.lua:52,71> (46 instructions, 184 bytes at 0x7fa2144066f0)
0 params, 9 slots, 0 upvalues, 4 locals, 19 constants, 2 functions
	1	[53]	GETGLOBAL	0 -1	; require
	2	[53]	LOADK    	1 -2	; "ui/hook_container"
	3	[53]	CALL     	0 2 2
	4	[53]	SELF     	0 0 -3	; "new"
	5	[53]	CALL     	0 2 2
	6	[54]	GETGLOBAL	1 -1	; require
	7	[54]	LOADK    	2 -4	; "ui/widget/widget"
	8	[54]	CALL     	1 2 2
	9	[54]	SELF     	1 1 -3	; "new"
	10	[54]	CALL     	1 2 2
	11	[55]	LOADBOOL 	2 0 0
	12	[56]	LOADBOOL 	3 0 0
	13	[61]	CLOSURE  	4 0	; 0x7fa214407fa0
	14	[61]	MOVE     	0 2
	15	[57]	SETTABLE 	1 -5 4	; "onEvent" -
	16	[65]	CLOSURE  	4 1	; 0x7fa214408c60
	17	[65]	MOVE     	0 3
	18	[62]	SETTABLE 	1 -6 4	; "onCloseWidget" -
	19	[66]	SELF     	4 0 -7	; "registerWidget"
	20	[66]	LOADK    	6 -8	; "Event"
	21	[66]	MOVE     	7 1
	22	[66]	CALL     	4 4 1
	23	[67]	GETGLOBAL	4 -9	; assert
	24	[67]	GETTABLE 	4 4 -10	; "are"
	25	[67]	GETTABLE 	4 4 -11	; "equal"
	26	[67]	SELF     	5 0 -12	; "execute"
	27	[67]	LOADK    	7 -8	; "Event"
	28	[67]	NEWTABLE 	8 0 2
	29	[67]	SETTABLE 	8 -13 -14	; "c" 300
	30	[67]	SETTABLE 	8 -15 -16	; "d" 400
	31	[67]	CALL     	5 4 2
	32	[67]	LOADK    	6 -17	; 1
	33	[67]	CALL     	4 3 1
	34	[68]	SELF     	4 1 -6	; "onCloseWidget"
	35	[68]	CALL     	4 2 1
	36	[69]	GETGLOBAL	4 -9	; assert
	37	[69]	GETTABLE 	4 4 -18	; "is"
	38	[69]	GETTABLE 	4 4 -19	; "truthy"
	39	[69]	MOVE     	5 2
	40	[69]	CALL     	4 2 1
	41	[70]	GETGLOBAL	4 -9	; assert
	42	[70]	GETTABLE 	4 4 -18	; "is"
	43	[70]	GETTABLE 	4 4 -19	; "truthy"
	44	[70]	MOVE     	5 3
	45	[70]	CALL     	4 2 1
	46	[71]	RETURN   	0 1

function <./spec/unit/hook_container_spec.lua:57,61> (19 instructions, 76 bytes at 0x7fa214407fa0)
2 params, 5 slots, 1 upvalue, 2 locals, 10 constants, 0 functions
	1	[58]	GETGLOBAL	2 -1	; assert
	2	[58]	GETTABLE 	2 2 -2	; "is"
	3	[58]	GETTABLE 	2 2 -3	; "truthy"
	4	[58]	EQ       	0 0 -4	; - nil
	5	[58]	JMP      	1	; to 7
	6	[58]	LOADBOOL 	3 0 1
	7	[58]	LOADBOOL 	3 1 0
	8	[58]	CALL     	2 2 1
	9	[59]	GETGLOBAL	2 -1	; assert
	10	[59]	GETTABLE 	2 2 -5	; "are"
	11	[59]	GETTABLE 	2 2 -6	; "same"
	12	[59]	MOVE     	3 1
	13	[59]	NEWTABLE 	4 0 2
	14	[59]	SETTABLE 	4 -7 -8	; "c" 300
	15	[59]	SETTABLE 	4 -9 -10	; "d" 400
	16	[59]	CALL     	2 3 1
	17	[60]	LOADBOOL 	2 1 0
	18	[60]	SETUPVAL 	2 0	; onEvent_called
	19	[61]	RETURN   	0 1

function <./spec/unit/hook_container_spec.lua:62,65> (11 instructions, 44 bytes at 0x7fa214408c60)
1 param, 3 slots, 1 upvalue, 1 local, 4 constants, 0 functions
	1	[63]	GETGLOBAL	1 -1	; assert
	2	[63]	GETTABLE 	1 1 -2	; "is"
	3	[63]	GETTABLE 	1 1 -3	; "truthy"
	4	[63]	EQ       	0 0 -4	; - nil
	5	[63]	JMP      	1	; to 7
	6	[63]	LOADBOOL 	2 0 1
	7	[63]	LOADBOOL 	2 1 0
	8	[63]	CALL     	1 2 1
	9	[64]	LOADBOOL 	1 1 0
	10	[64]	SETUPVAL 	1 0	; onCloseWidget_called
	11	[65]	RETURN   	0 1
