
main <./frontend/ui/widget/horizontalgroup.lua:0,0> (34 instructions, 136 bytes at 0x7ff240c068f0)
0+ params, 7 slots, 0 upvalues, 4 locals, 18 constants, 5 functions
	1	[5]	GETGLOBAL	0 -1	; require
	2	[5]	LOADK    	1 -2	; "ui/bidi"
	3	[5]	CALL     	0 2 2
	4	[6]	GETGLOBAL	1 -1	; require
	5	[6]	LOADK    	2 -3	; "ui/widget/container/widgetcontainer"
	6	[6]	CALL     	1 2 2
	7	[7]	GETGLOBAL	2 -1	; require
	8	[7]	LOADK    	3 -4	; "util"
	9	[7]	CALL     	2 2 2
	10	[9]	SELF     	3 1 -5	; "new"
	11	[9]	NEWTABLE 	5 0 4
	12	[10]	SETTABLE 	5 -6 -7	; "align" "center"
	13	[11]	SETTABLE 	5 -8 -9	; "allow_mirroring" true
	14	[12]	GETTABLE 	6 0 -11	; "mirroredUILayout"
	15	[12]	CALL     	6 1 2
	16	[12]	SETTABLE 	5 -10 6	; "_mirroredUI" -
	17	[13]	SETTABLE 	5 -12 -13	; "_size" nil
	18	[9]	CALL     	3 3 2
	19	[39]	CLOSURE  	4 0	; 0x7ff240c06e10
	20	[39]	MOVE     	0 2
	21	[16]	SETTABLE 	3 -14 4	; "getSize" -
	22	[64]	CLOSURE  	4 1	; 0x7ff240c07110
	23	[64]	MOVE     	0 2
	24	[41]	SETTABLE 	3 -15 4	; "paintTo" -
	25	[69]	CLOSURE  	4 2	; 0x7ff240c07710
	26	[69]	MOVE     	0 1
	27	[66]	SETTABLE 	3 -16 4	; "clear" -
	28	[74]	CLOSURE  	4 3	; 0x7ff240c07eb0
	29	[71]	SETTABLE 	3 -17 4	; "resetLayout" -
	30	[79]	CLOSURE  	4 4	; 0x7ff240c07050
	31	[79]	MOVE     	0 1
	32	[76]	SETTABLE 	3 -18 4	; "free" -
	33	[81]	RETURN   	3 2
	34	[81]	RETURN   	0 1

function <./frontend/ui/widget/horizontalgroup.lua:16,39> (62 instructions, 248 bytes at 0x7ff240c06e10)
1 param, 10 slots, 1 upvalue, 7 locals, 12 constants, 0 functions
	1	[17]	GETTABLE 	1 0 -1	; "_size"
	2	[17]	TEST     	1 0 1
	3	[17]	JMP      	56	; to 60
	4	[18]	NEWTABLE 	1 0 2
	5	[18]	SETTABLE 	1 -2 -3	; "w" 0
	6	[18]	SETTABLE 	1 -4 -3	; "h" 0
	7	[18]	SETTABLE 	0 -1 1	; "_size" -
	8	[19]	NEWTABLE 	1 0 0
	9	[19]	SETTABLE 	0 -5 1	; "_offsets" -
	10	[20]	GETTABLE 	1 0 -6	; "_mirroredUI"
	11	[20]	TEST     	1 0 0
	12	[20]	JMP      	7	; to 20
	13	[20]	GETTABLE 	1 0 -7	; "allow_mirroring"
	14	[20]	TEST     	1 0 0
	15	[20]	JMP      	4	; to 20
	16	[21]	GETUPVAL 	1 0	; util
	17	[21]	GETTABLE 	1 1 -8	; "arrayReverse"
	18	[21]	MOVE     	2 0
	19	[21]	CALL     	1 2 1
	20	[23]	GETGLOBAL	1 -9	; ipairs
	21	[23]	MOVE     	2 0
	22	[23]	CALL     	1 2 4
	23	[23]	JMP      	24	; to 48
	24	[24]	SELF     	6 5 -10	; "getSize"
	25	[24]	CALL     	6 2 2
	26	[25]	GETTABLE 	7 0 -5	; "_offsets"
	27	[25]	NEWTABLE 	8 0 2
	28	[26]	GETTABLE 	9 0 -1	; "_size"
	29	[26]	GETTABLE 	9 9 -2	; "w"
	30	[26]	SETTABLE 	8 -11 9	; "x" -
	31	[27]	GETTABLE 	9 6 -4	; "h"
	32	[27]	SETTABLE 	8 -12 9	; "y" -
	33	[28]	SETTABLE 	7 4 8
	34	[29]	GETTABLE 	7 0 -1	; "_size"
	35	[29]	GETTABLE 	8 0 -1	; "_size"
	36	[29]	GETTABLE 	8 8 -2	; "w"
	37	[29]	GETTABLE 	9 6 -2	; "w"
	38	[29]	ADD      	8 8 9
	39	[29]	SETTABLE 	7 -2 8	; "w" -
	40	[30]	GETTABLE 	7 6 -4	; "h"
	41	[30]	GETTABLE 	8 0 -1	; "_size"
	42	[30]	GETTABLE 	8 8 -4	; "h"
	43	[30]	LT       	0 8 7
	44	[30]	JMP      	3	; to 48
	45	[31]	GETTABLE 	7 0 -1	; "_size"
	46	[31]	GETTABLE 	8 6 -4	; "h"
	47	[31]	SETTABLE 	7 -4 8	; "h" -
	48	[23]	TFORLOOP 	1 2
	49	[32]	JMP      	-26	; to 24
	50	[34]	GETTABLE 	1 0 -6	; "_mirroredUI"
	51	[34]	TEST     	1 0 0
	52	[34]	JMP      	7	; to 60
	53	[34]	GETTABLE 	1 0 -7	; "allow_mirroring"
	54	[34]	TEST     	1 0 0
	55	[34]	JMP      	4	; to 60
	56	[35]	GETUPVAL 	1 0	; util
	57	[35]	GETTABLE 	1 1 -8	; "arrayReverse"
	58	[35]	MOVE     	2 0
	59	[35]	CALL     	1 2 1
	60	[38]	GETTABLE 	1 0 -1	; "_size"
	61	[38]	RETURN   	1 2
	62	[39]	RETURN   	0 1

function <./frontend/ui/widget/horizontalgroup.lua:41,64> (85 instructions, 340 bytes at 0x7ff240c07110)
4 params, 17 slots, 1 upvalue, 10 locals, 21 constants, 0 functions
	1	[42]	SELF     	4 0 -1	; "getSize"
	2	[42]	CALL     	4 2 2
	3	[44]	GETTABLE 	5 0 -2	; "_mirroredUI"
	4	[44]	TEST     	5 0 0
	5	[44]	JMP      	7	; to 13
	6	[44]	GETTABLE 	5 0 -3	; "allow_mirroring"
	7	[44]	TEST     	5 0 0
	8	[44]	JMP      	4	; to 13
	9	[45]	GETUPVAL 	5 0	; util
	10	[45]	GETTABLE 	5 5 -4	; "arrayReverse"
	11	[45]	MOVE     	6 0
	12	[45]	CALL     	5 2 1
	13	[47]	GETGLOBAL	5 -5	; ipairs
	14	[47]	MOVE     	6 0
	15	[47]	CALL     	5 2 4
	16	[47]	JMP      	56	; to 73
	17	[48]	GETTABLE 	10 0 -6	; "align"
	18	[48]	EQ       	0 10 -7	; - "center"
	19	[48]	JMP      	18	; to 38
	20	[49]	SELF     	10 9 -8	; "paintTo"
	21	[49]	MOVE     	12 1
	22	[50]	GETTABLE 	13 0 -9	; "_offsets"
	23	[50]	GETTABLE 	13 13 8
	24	[50]	GETTABLE 	13 13 -10	; "x"
	25	[50]	ADD      	13 2 13
	26	[51]	GETGLOBAL	14 -11	; math
	27	[51]	GETTABLE 	14 14 -12	; "floor"
	28	[51]	GETTABLE 	15 4 -13	; "h"
	29	[51]	GETTABLE 	16 0 -9	; "_offsets"
	30	[51]	GETTABLE 	16 16 8
	31	[51]	GETTABLE 	16 16 -14	; "y"
	32	[51]	SUB      	15 15 16
	33	[51]	DIV      	15 15 -15	; - 2
	34	[51]	CALL     	14 2 2
	35	[51]	ADD      	14 3 14
	36	[49]	CALL     	10 5 1
	37	[51]	JMP      	35	; to 73
	38	[52]	GETTABLE 	10 0 -6	; "align"
	39	[52]	EQ       	0 10 -16	; - "top"
	40	[52]	JMP      	9	; to 50
	41	[53]	SELF     	10 9 -8	; "paintTo"
	42	[53]	MOVE     	12 1
	43	[53]	GETTABLE 	13 0 -9	; "_offsets"
	44	[53]	GETTABLE 	13 13 8
	45	[53]	GETTABLE 	13 13 -10	; "x"
	46	[53]	ADD      	13 2 13
	47	[53]	MOVE     	14 3
	48	[53]	CALL     	10 5 1
	49	[53]	JMP      	23	; to 73
	50	[54]	GETTABLE 	10 0 -6	; "align"
	51	[54]	EQ       	0 10 -17	; - "bottom"
	52	[54]	JMP      	14	; to 67
	53	[55]	SELF     	10 9 -8	; "paintTo"
	54	[55]	MOVE     	12 1
	55	[55]	GETTABLE 	13 0 -9	; "_offsets"
	56	[55]	GETTABLE 	13 13 8
	57	[55]	GETTABLE 	13 13 -10	; "x"
	58	[55]	ADD      	13 2 13
	59	[55]	GETTABLE 	14 4 -13	; "h"
	60	[55]	ADD      	14 3 14
	61	[55]	GETTABLE 	15 0 -9	; "_offsets"
	62	[55]	GETTABLE 	15 15 8
	63	[55]	GETTABLE 	15 15 -14	; "y"
	64	[55]	SUB      	14 14 15
	65	[55]	CALL     	10 5 1
	66	[55]	JMP      	6	; to 73
	67	[57]	GETGLOBAL	10 -18	; io
	68	[57]	GETTABLE 	10 10 -19	; "stderr"
	69	[57]	SELF     	10 10 -20	; "write"
	70	[57]	LOADK    	12 -21	; "[!] invalid alignment for HorizontalGroup: "
	71	[58]	GETTABLE 	13 0 -6	; "align"
	72	[57]	CALL     	10 4 1
	73	[47]	TFORLOOP 	5 2
	74	[59]	JMP      	-58	; to 17
	75	[61]	GETTABLE 	5 0 -2	; "_mirroredUI"
	76	[61]	TEST     	5 0 0
	77	[61]	JMP      	7	; to 85
	78	[61]	GETTABLE 	5 0 -3	; "allow_mirroring"
	79	[61]	TEST     	5 0 0
	80	[61]	JMP      	4	; to 85
	81	[62]	GETUPVAL 	5 0	; util
	82	[62]	GETTABLE 	5 5 -4	; "arrayReverse"
	83	[62]	MOVE     	6 0
	84	[62]	CALL     	5 2 1
	85	[64]	RETURN   	0 1

function <./frontend/ui/widget/horizontalgroup.lua:66,69> (7 instructions, 28 bytes at 0x7ff240c07710)
1 param, 3 slots, 1 upvalue, 1 local, 2 constants, 0 functions
	1	[67]	SELF     	1 0 -1	; "free"
	2	[67]	CALL     	1 2 1
	3	[68]	GETUPVAL 	1 0	; WidgetContainer
	4	[68]	GETTABLE 	1 1 -2	; "clear"
	5	[68]	MOVE     	2 0
	6	[68]	CALL     	1 2 1
	7	[69]	RETURN   	0 1

function <./frontend/ui/widget/horizontalgroup.lua:71,74> (4 instructions, 16 bytes at 0x7ff240c07eb0)
1 param, 2 slots, 0 upvalues, 1 local, 3 constants, 0 functions
	1	[72]	SETTABLE 	0 -1 -2	; "_size" nil
	2	[73]	NEWTABLE 	1 0 0
	3	[73]	SETTABLE 	0 -3 1	; "_offsets" -
	4	[74]	RETURN   	0 1

function <./frontend/ui/widget/horizontalgroup.lua:76,79> (7 instructions, 28 bytes at 0x7ff240c07050)
1 param, 3 slots, 1 upvalue, 1 local, 2 constants, 0 functions
	1	[77]	SELF     	1 0 -1	; "resetLayout"
	2	[77]	CALL     	1 2 1
	3	[78]	GETUPVAL 	1 0	; WidgetContainer
	4	[78]	GETTABLE 	1 1 -2	; "free"
	5	[78]	MOVE     	2 0
	6	[78]	CALL     	1 2 1
	7	[79]	RETURN   	0 1
