-- BYTECODE -- horizontalgroup.lua:16-39
0001    TGETS    1   0   0  ; "_size"
0002    IST          1
0003    JMP      1 => 0059
0004    TDUP     1   1
0005    TSETS    1   0   0  ; "_size"
0006    TNEW     1   0
0007    TSETS    1   0   2  ; "_offsets"
0008    TGETS    1   0   3  ; "_mirroredUI"
0009    ISF          1
0010    JMP      2 => 0018
0011    TGETS    1   0   4  ; "allow_mirroring"
0012    ISF          1
0013    JMP      2 => 0018
0014    UGET     1   0      ; util
0015    TGETS    1   1   5  ; "arrayReverse"
0016    MOV      2   0
0017    CALL     1   1   2
0018 => GGET     1   6      ; "ipairs"
0019    MOV      2   0
0020    CALL     1   4   2
0021    JMP      4 => 0047
0022 => MOV      7   5
0023    TGETS    6   5   7  ; "getSize"
0024    CALL     6   2   2
0025    TGETS    7   0   2  ; "_offsets"
0026    TDUP     8   9
0027    TGETS    9   0   0  ; "_size"
0028    TGETS    9   9   8  ; "w"
0029    TSETS    9   8  10  ; "x"
0030    TGETS    9   6  11  ; "h"
0031    TSETS    9   8  12  ; "y"
0032    TSETV    8   7   4
0033    TGETS    7   0   0  ; "_size"
0034    TGETS    8   0   0  ; "_size"
0035    TGETS    8   8   8  ; "w"
0036    TGETS    9   6   8  ; "w"
0037    ADDVV    8   8   9
0038    TSETS    8   7   8  ; "w"
0039    TGETS    7   6  11  ; "h"
0040    TGETS    8   0   0  ; "_size"
0041    TGETS    8   8  11  ; "h"
0042    ISGE     8   7
0043    JMP      7 => 0047
0044    TGETS    7   0   0  ; "_size"
0045    TGETS    8   6  11  ; "h"
0046    TSETS    8   7  11  ; "h"
0047 => ITERC    4   3   3
0048    ITERL    4 => 0022
0049    TGETS    1   0   3  ; "_mirroredUI"
0050    ISF          1
0051    JMP      2 => 0059
0052    TGETS    1   0   4  ; "allow_mirroring"
0053    ISF          1
0054    JMP      2 => 0059
0055    UGET     1   0      ; util
0056    TGETS    1   1   5  ; "arrayReverse"
0057    MOV      2   0
0058    CALL     1   1   2
0059 => TGETS    1   0   0  ; "_size"
0060    RET1     1   2

-- BYTECODE -- horizontalgroup.lua:41-64
0001    MOV      5   0
0002    TGETS    4   0   0  ; "getSize"
0003    CALL     4   2   2
0004    TGETS    5   0   1  ; "_mirroredUI"
0005    ISF          5
0006    JMP      6 => 0014
0007    TGETS    5   0   2  ; "allow_mirroring"
0008    ISF          5
0009    JMP      6 => 0014
0010    UGET     5   0      ; util
0011    TGETS    5   5   3  ; "arrayReverse"
0012    MOV      6   0
0013    CALL     5   1   2
0014 => GGET     5   4      ; "ipairs"
0015    MOV      6   0
0016    CALL     5   4   2
0017    JMP      8 => 0078
0018 => TGETS   10   0   5  ; "align"
0019    ISNES   10   6      ; "center"
0020    JMP     10 => 0040
0021    MOV     11   9
0022    TGETS   10   9   7  ; "paintTo"
0023    MOV     12   1
0024    TGETS   13   0   8  ; "_offsets"
0025    TGETV   13  13   8
0026    TGETS   13  13   9  ; "x"
0027    ADDVV   13   2  13
0028    GGET    14  10      ; "math"
0029    TGETS   14  14  11  ; "floor"
0030    TGETS   15   4  12  ; "h"
0031    TGETS   16   0   8  ; "_offsets"
0032    TGETV   16  16   8
0033    TGETS   16  16  13  ; "y"
0034    SUBVV   15  15  16
0035    DIVVN   15  15   0  ; 2
0036    CALL    14   2   2
0037    ADDVV   14   3  14
0038    CALL    10   1   5
0039    JMP     10 => 0078
0040 => TGETS   10   0   5  ; "align"
0041    ISNES   10  14      ; "top"
0042    JMP     10 => 0053
0043    MOV     11   9
0044    TGETS   10   9   7  ; "paintTo"
0045    MOV     12   1
0046    TGETS   13   0   8  ; "_offsets"
0047    TGETV   13  13   8
0048    TGETS   13  13   9  ; "x"
0049    ADDVV   13   2  13
0050    MOV     14   3
0051    CALL    10   1   5
0052    JMP     10 => 0078
0053 => TGETS   10   0   5  ; "align"
0054    ISNES   10  15      ; "bottom"
0055    JMP     10 => 0071
0056    MOV     11   9
0057    TGETS   10   9   7  ; "paintTo"
0058    MOV     12   1
0059    TGETS   13   0   8  ; "_offsets"
0060    TGETV   13  13   8
0061    TGETS   13  13   9  ; "x"
0062    ADDVV   13   2  13
0063    TGETS   14   4  12  ; "h"
0064    ADDVV   14   3  14
0065    TGETS   15   0   8  ; "_offsets"
0066    TGETV   15  15   8
0067    TGETS   15  15  13  ; "y"
0068    SUBVV   14  14  15
0069    CALL    10   1   5
0070    JMP     10 => 0078
0071 => GGET    10  16      ; "io"
0072    TGETS   10  10  17  ; "stderr"
0073    MOV     11  10
0074    TGETS   10  10  18  ; "write"
0075    KSTR    12  19      ; "[!] invalid alignment for HorizontalGrou"~
0076    TGETS   13   0   5  ; "align"
0077    CALL    10   1   4
0078 => ITERC    8   3   3
0079    ITERL    8 => 0018
0080    TGETS    5   0   1  ; "_mirroredUI"
0081    ISF          5
0082    JMP      6 => 0090
0083    TGETS    5   0   2  ; "allow_mirroring"
0084    ISF          5
0085    JMP      6 => 0090
0086    UGET     5   0      ; util
0087    TGETS    5   5   3  ; "arrayReverse"
0088    MOV      6   0
0089    CALL     5   1   2
0090 => RET0     0   1

-- BYTECODE -- horizontalgroup.lua:66-69
0001    MOV      2   0
0002    TGETS    1   0   0  ; "free"
0003    CALL     1   1   2
0004    UGET     1   0      ; WidgetContainer
0005    TGETS    1   1   1  ; "clear"
0006    MOV      2   0
0007    CALL     1   1   2
0008    RET0     0   1

-- BYTECODE -- horizontalgroup.lua:71-74
0001    KPRI     1   0
0002    TSETS    1   0   0  ; "_size"
0003    TNEW     1   0
0004    TSETS    1   0   1  ; "_offsets"
0005    RET0     0   1

-- BYTECODE -- horizontalgroup.lua:76-79
0001    MOV      2   0
0002    TGETS    1   0   0  ; "resetLayout"
0003    CALL     1   1   2
0004    UGET     1   0      ; WidgetContainer
0005    TGETS    1   1   1  ; "free"
0006    MOV      2   0
0007    CALL     1   1   2
0008    RET0     0   1

-- BYTECODE -- horizontalgroup.lua:0-82
0001    GGET     0   0      ; "require"
0002    KSTR     1   1      ; "ui/bidi"
0003    CALL     0   2   2
0004    GGET     1   0      ; "require"
0005    KSTR     2   2      ; "ui/widget/container/widgetcontainer"
0006    CALL     1   2   2
0007    GGET     2   0      ; "require"
0008    KSTR     3   3      ; "util"
0009    CALL     2   2   2
0010    MOV      4   1
0011    TGETS    3   1   4  ; "new"
0012    TDUP     5   5
0013    TGETS    6   0   6  ; "mirroredUILayout"
0014    CALL     6   2   1
0015    TSETS    6   5   7  ; "_mirroredUI"
0016    CALL     3   2   3
0017    FNEW     4   9      ; horizontalgroup.lua:16
0018    TSETS    4   3   8  ; "getSize"
0019    FNEW     4  11      ; horizontalgroup.lua:41
0020    TSETS    4   3  10  ; "paintTo"
0021    FNEW     4  13      ; horizontalgroup.lua:66
0022    TSETS    4   3  12  ; "clear"
0023    FNEW     4  15      ; horizontalgroup.lua:71
0024    TSETS    4   3  14  ; "resetLayout"
0025    FNEW     4  17      ; horizontalgroup.lua:76
0026    TSETS    4   3  16  ; "free"
0027    UCLO     0 => 0028
0028 => RET1     3   2

