
main <./frontend/ui/widget/htmlboxwidget.lua:0,0> (84 instructions, 336 bytes at 0x7fe38f4068d0)
0+ params, 13 slots, 0 upvalues, 11 locals, 39 constants, 16 functions
	1	[5]	GETGLOBAL	0 -1	; require
	2	[5]	LOADK    	1 -2	; "device"
	3	[5]	CALL     	0 2 2
	4	[6]	GETGLOBAL	1 -1	; require
	5	[6]	LOADK    	2 -3	; "ffi/drawcontext"
	6	[6]	CALL     	1 2 2
	7	[7]	GETGLOBAL	2 -1	; require
	8	[7]	LOADK    	3 -4	; "ui/geometry"
	9	[7]	CALL     	2 2 2
	10	[8]	GETGLOBAL	3 -1	; require
	11	[8]	LOADK    	4 -5	; "ui/gesturerange"
	12	[8]	CALL     	3 2 2
	13	[9]	GETGLOBAL	4 -1	; require
	14	[9]	LOADK    	5 -6	; "ui/widget/container/inputcontainer"
	15	[9]	CALL     	4 2 2
	16	[10]	GETGLOBAL	5 -1	; require
	17	[10]	LOADK    	6 -7	; "ffi/mupdf"
	18	[10]	CALL     	5 2 2
	19	[11]	GETTABLE 	6 0 -8	; "screen"
	20	[12]	GETGLOBAL	7 -1	; require
	21	[12]	LOADK    	8 -9	; "ui/timeval"
	22	[12]	CALL     	7 2 2
	23	[13]	GETGLOBAL	8 -1	; require
	24	[13]	LOADK    	9 -10	; "logger"
	25	[13]	CALL     	8 2 2
	26	[14]	GETGLOBAL	9 -1	; require
	27	[14]	LOADK    	10 -11	; "util"
	28	[14]	CALL     	9 2 2
	29	[16]	SELF     	10 4 -12	; "new"
	30	[16]	NEWTABLE 	12 0 8
	31	[17]	SETTABLE 	12 -13 -14	; "bb" nil
	32	[18]	SETTABLE 	12 -15 -14	; "dimen" nil
	33	[19]	SETTABLE 	12 -16 -14	; "document" nil
	34	[20]	SETTABLE 	12 -17 -18	; "page_count" 0
	35	[21]	SETTABLE 	12 -19 -20	; "page_number" 1
	36	[22]	SETTABLE 	12 -21 -14	; "hold_start_pos" nil
	37	[23]	SETTABLE 	12 -22 -14	; "hold_start_tv" nil
	38	[24]	SETTABLE 	12 -23 -14	; "html_link_tapped_callback" nil
	39	[16]	CALL     	10 3 2
	40	[38]	CLOSURE  	11 0	; 0x7fe38f407020
	41	[38]	MOVE     	0 0
	42	[38]	MOVE     	0 3
	43	[27]	SETTABLE 	10 -24 11	; "init" -
	44	[76]	CLOSURE  	11 1	; 0x7fe38f407af0
	45	[76]	MOVE     	0 5
	46	[76]	MOVE     	0 8
	47	[76]	MOVE     	0 9
	48	[40]	SETTABLE 	10 -25 11	; "setContent" -
	49	[94]	CLOSURE  	11 2	; 0x7fe38f407e80
	50	[94]	MOVE     	0 5
	51	[94]	MOVE     	0 6
	52	[94]	MOVE     	0 1
	53	[78]	SETTABLE 	10 -26 11	; "_render" -
	54	[98]	CLOSURE  	11 3	; 0x7fe38f408880
	55	[96]	SETTABLE 	10 -27 11	; "getSize" -
	56	[107]	CLOSURE  	11 4	; 0x7fe38f408af0
	57	[100]	SETTABLE 	10 -28 11	; "getSinglePageHeight" -
	58	[118]	CLOSURE  	11 5	; 0x7fe38f408cd0
	59	[109]	SETTABLE 	10 -29 11	; "paintTo" -
	60	[126]	CLOSURE  	11 6	; 0x7fe38f407740
	61	[120]	SETTABLE 	10 -30 11	; "freeBb" -
	62	[139]	CLOSURE  	11 7	; 0x7fe38f4093b0
	63	[132]	SETTABLE 	10 -31 11	; "free" -
	64	[144]	CLOSURE  	11 8	; 0x7fe38f4097b0
	65	[141]	SETTABLE 	10 -32 11	; "onCloseWidget" -
	66	[158]	CLOSURE  	11 9	; 0x7fe38f409870
	67	[158]	MOVE     	0 2
	68	[146]	SETTABLE 	10 -33 11	; "getPosFromAbsPos" -
	69	[170]	CLOSURE  	11 10	; 0x7fe38f406600
	70	[170]	MOVE     	0 7
	71	[160]	SETTABLE 	10 -34 11	; "onHoldStartText" -
	72	[179]	CLOSURE  	11 11	; 0x7fe38f40a270
	73	[172]	SETTABLE 	10 -35 11	; "onHoldPan" -
	74	[211]	CLOSURE  	11 12	; 0x7fe38f40a3b0
	75	[181]	SETTABLE 	10 -36 11	; "getSelectedText" -
	76	[243]	CLOSURE  	11 13	; 0x7fe38f40a6a0
	77	[243]	MOVE     	0 7
	78	[213]	SETTABLE 	10 -37 11	; "onHoldReleaseText" -
	79	[255]	CLOSURE  	11 14	; 0x7fe38f40acc0
	80	[245]	SETTABLE 	10 -38 11	; "getLinkByPosition" -
	81	[272]	CLOSURE  	11 15	; 0x7fe38f40b370
	82	[257]	SETTABLE 	10 -39 11	; "onTapText" -
	83	[274]	RETURN   	10 2
	84	[274]	RETURN   	0 1

function <./frontend/ui/widget/htmlboxwidget.lua:27,38> (19 instructions, 76 bytes at 0x7fe38f407020)
1 param, 7 slots, 2 upvalues, 1 local, 7 constants, 1 function
	1	[28]	GETUPVAL 	1 0	; Device
	2	[28]	SELF     	1 1 -1	; "isTouchDevice"
	3	[28]	CALL     	1 2 2
	4	[28]	TEST     	1 0 0
	5	[28]	JMP      	13	; to 19
	6	[29]	NEWTABLE 	1 0 1
	7	[30]	NEWTABLE 	2 0 0
	8	[31]	GETUPVAL 	3 1	; GestureRange
	9	[31]	SELF     	3 3 -4	; "new"
	10	[31]	NEWTABLE 	5 0 2
	11	[32]	SETTABLE 	5 -5 -6	; "ges" "tap"
	12	[33]	CLOSURE  	6 0	; 0x7fe38f407840
	13	[33]	MOVE     	0 0
	14	[33]	SETTABLE 	5 -7 6	; "range" -
	15	[31]	CALL     	3 3 0
	16	[35]	SETLIST  	2 0 1	; 1
	17	[35]	SETTABLE 	1 -3 2	; "TapText" -
	18	[36]	SETTABLE 	0 -2 1	; "ges_events" -
	19	[38]	RETURN   	0 1

function <./frontend/ui/widget/htmlboxwidget.lua:33,33> (4 instructions, 16 bytes at 0x7fe38f407840)
0 params, 2 slots, 1 upvalue, 0 locals, 1 constant, 0 functions
	1	[33]	GETUPVAL 	0 0	; self
	2	[33]	GETTABLE 	0 0 -1	; "dimen"
	3	[33]	RETURN   	0 2
	4	[33]	RETURN   	0 1

function <./frontend/ui/widget/htmlboxwidget.lua:40,76> (84 instructions, 336 bytes at 0x7fe38f407af0)
4 params, 12 slots, 3 upvalues, 7 locals, 24 constants, 0 functions
	1	[44]	LOADK    	4 -1	; ""
	2	[45]	TEST     	2 0 0
	3	[45]	JMP      	6	; to 10
	4	[46]	GETGLOBAL	5 -2	; string
	5	[46]	GETTABLE 	5 5 -3	; "format"
	6	[46]	LOADK    	6 -4	; "<head><style>%s</style></head>"
	7	[46]	MOVE     	7 2
	8	[46]	CALL     	5 3 2
	9	[46]	MOVE     	4 5
	10	[48]	GETGLOBAL	5 -2	; string
	11	[48]	GETTABLE 	5 5 -3	; "format"
	12	[48]	LOADK    	6 -5	; "<html>%s<body>%s</body></html>"
	13	[48]	MOVE     	7 4
	14	[48]	MOVE     	8 1
	15	[48]	CALL     	5 4 2
	16	[53]	SELF     	6 5 -6	; "gsub"
	17	[53]	LOADK    	8 -7	; "%<br ?/?%>"
	18	[53]	LOADK    	9 -8	; "&nbsp;<div></div>"
	19	[53]	CALL     	6 4 2
	20	[53]	MOVE     	5 6
	21	[55]	LOADNIL  	6 6
	22	[56]	GETGLOBAL	7 -10	; pcall
	23	[56]	GETUPVAL 	8 0	; Mupdf
	24	[56]	GETTABLE 	8 8 -11	; "openDocumentFromText"
	25	[56]	MOVE     	9 5
	26	[56]	LOADK    	10 -12	; "html"
	27	[56]	CALL     	7 4 3
	28	[56]	SETTABLE 	0 -9 8	; "document" -
	29	[56]	MOVE     	6 7
	30	[57]	TEST     	6 0 1
	31	[57]	JMP      	40	; to 72
	32	[59]	GETUPVAL 	7 1	; logger
	33	[59]	GETTABLE 	7 7 -13	; "warn"
	34	[59]	LOADK    	8 -14	; "HTML loading error:"
	35	[59]	GETTABLE 	9 0 -9	; "document"
	36	[59]	CALL     	7 3 1
	37	[61]	GETUPVAL 	7 2	; util
	38	[61]	GETTABLE 	7 7 -15	; "htmlToPlainText"
	39	[61]	MOVE     	8 1
	40	[61]	CALL     	7 2 2
	41	[61]	MOVE     	1 7
	42	[62]	GETUPVAL 	7 2	; util
	43	[62]	GETTABLE 	7 7 -16	; "htmlEscape"
	44	[62]	MOVE     	8 1
	45	[62]	CALL     	7 2 2
	46	[62]	MOVE     	1 7
	47	[64]	SELF     	7 1 -6	; "gsub"
	48	[64]	LOADK    	9 -17	; "\n"
	49	[64]	LOADK    	10 -8	; "&nbsp;<div></div>"
	50	[64]	CALL     	7 4 2
	51	[64]	MOVE     	1 7
	52	[65]	GETGLOBAL	7 -2	; string
	53	[65]	GETTABLE 	7 7 -3	; "format"
	54	[65]	LOADK    	8 -5	; "<html>%s<body>%s</body></html>"
	55	[65]	MOVE     	9 4
	56	[65]	MOVE     	10 1
	57	[65]	CALL     	7 4 2
	58	[65]	MOVE     	5 7
	59	[67]	GETGLOBAL	7 -10	; pcall
	60	[67]	GETUPVAL 	8 0	; Mupdf
	61	[67]	GETTABLE 	8 8 -11	; "openDocumentFromText"
	62	[67]	MOVE     	9 5
	63	[67]	LOADK    	10 -12	; "html"
	64	[67]	CALL     	7 4 3
	65	[67]	SETTABLE 	0 -9 8	; "document" -
	66	[67]	MOVE     	6 7
	67	[68]	TEST     	6 0 1
	68	[68]	JMP      	3	; to 72
	69	[69]	GETGLOBAL	7 -18	; error
	70	[69]	GETTABLE 	8 0 -9	; "document"
	71	[69]	CALL     	7 2 1
	72	[73]	GETTABLE 	7 0 -9	; "document"
	73	[73]	SELF     	7 7 -19	; "layoutDocument"
	74	[73]	GETTABLE 	9 0 -20	; "dimen"
	75	[73]	GETTABLE 	9 9 -21	; "w"
	76	[73]	GETTABLE 	10 0 -20	; "dimen"
	77	[73]	GETTABLE 	10 10 -22	; "h"
	78	[73]	MOVE     	11 3
	79	[73]	CALL     	7 5 1
	80	[75]	GETTABLE 	7 0 -9	; "document"
	81	[75]	SELF     	7 7 -24	; "getPages"
	82	[75]	CALL     	7 2 2
	83	[75]	SETTABLE 	0 -23 7	; "page_count" -
	84	[76]	RETURN   	0 1

function <./frontend/ui/widget/htmlboxwidget.lua:78,94> (31 instructions, 124 bytes at 0x7fe38f407e80)
1 param, 10 slots, 3 upvalues, 3 locals, 14 constants, 0 functions
	1	[79]	GETTABLE 	1 0 -1	; "bb"
	2	[79]	TEST     	1 0 0
	3	[79]	JMP      	1	; to 5
	4	[80]	RETURN   	0 1
	5	[86]	GETUPVAL 	1 0	; Mupdf
	6	[86]	GETUPVAL 	2 1	; Screen
	7	[86]	SELF     	2 2 -3	; "isColorEnabled"
	8	[86]	CALL     	2 2 2
	9	[86]	SETTABLE 	1 -2 2	; "color" -
	10	[88]	GETTABLE 	1 0 -4	; "document"
	11	[88]	SELF     	1 1 -5	; "openPage"
	12	[88]	GETTABLE 	3 0 -6	; "page_number"
	13	[88]	CALL     	1 3 2
	14	[89]	GETUPVAL 	2 2	; DrawContext
	15	[89]	GETTABLE 	2 2 -7	; "new"
	16	[89]	CALL     	2 1 2
	17	[90]	SELF     	3 1 -8	; "draw_new"
	18	[90]	MOVE     	5 2
	19	[90]	GETTABLE 	6 0 -9	; "dimen"
	20	[90]	GETTABLE 	6 6 -10	; "w"
	21	[90]	GETTABLE 	7 0 -9	; "dimen"
	22	[90]	GETTABLE 	7 7 -11	; "h"
	23	[90]	LOADK    	8 -12	; 0
	24	[90]	LOADK    	9 -12	; 0
	25	[90]	CALL     	3 7 2
	26	[90]	SETTABLE 	0 -1 3	; "bb" -
	27	[91]	SELF     	3 1 -13	; "close"
	28	[91]	CALL     	3 2 1
	29	[93]	GETUPVAL 	3 0	; Mupdf
	30	[93]	SETTABLE 	3 -2 -14	; "color" false
	31	[94]	RETURN   	0 1

function <./frontend/ui/widget/htmlboxwidget.lua:96,98> (3 instructions, 12 bytes at 0x7fe38f408880)
1 param, 2 slots, 0 upvalues, 1 local, 1 constant, 0 functions
	1	[97]	GETTABLE 	1 0 -1	; "dimen"
	2	[97]	RETURN   	1 2
	3	[98]	RETURN   	0 1

function <./frontend/ui/widget/htmlboxwidget.lua:100,107> (17 instructions, 68 bytes at 0x7fe38f408af0)
1 param, 8 slots, 0 upvalues, 6 locals, 8 constants, 0 functions
	1	[101]	GETTABLE 	1 0 -1	; "page_count"
	2	[101]	EQ       	0 1 -2	; - 1
	3	[101]	JMP      	13	; to 17
	4	[102]	GETTABLE 	1 0 -3	; "document"
	5	[102]	SELF     	1 1 -4	; "openPage"
	6	[102]	LOADK    	3 -2	; 1
	7	[102]	CALL     	1 3 2
	8	[103]	SELF     	2 1 -5	; "getUsedBBox"
	9	[103]	CALL     	2 2 5
	10	[104]	SELF     	6 1 -6	; "close"
	11	[104]	CALL     	6 2 1
	12	[105]	GETGLOBAL	6 -7	; math
	13	[105]	GETTABLE 	6 6 -8	; "ceil"
	14	[105]	MOVE     	7 5
	15	[105]	TAILCALL 	6 2 0
	16	[105]	RETURN   	6 0
	17	[107]	RETURN   	0 1

function <./frontend/ui/widget/htmlboxwidget.lua:109,118> (18 instructions, 72 bytes at 0x7fe38f408cd0)
4 params, 14 slots, 0 upvalues, 5 locals, 10 constants, 0 functions
	1	[110]	GETTABLE 	4 0 -1	; "dimen"
	2	[110]	SETTABLE 	4 -2 2	; "x" -
	3	[111]	GETTABLE 	4 0 -1	; "dimen"
	4	[111]	SETTABLE 	4 -3 3	; "y" -
	5	[113]	SELF     	4 0 -4	; "_render"
	6	[113]	CALL     	4 2 1
	7	[115]	SELF     	4 0 -5	; "getSize"
	8	[115]	CALL     	4 2 2
	9	[117]	SELF     	5 1 -6	; "blitFrom"
	10	[117]	GETTABLE 	7 0 -7	; "bb"
	11	[117]	MOVE     	8 2
	12	[117]	MOVE     	9 3
	13	[117]	LOADK    	10 -8	; 0
	14	[117]	LOADK    	11 -8	; 0
	15	[117]	GETTABLE 	12 4 -9	; "w"
	16	[117]	GETTABLE 	13 4 -10	; "h"
	17	[117]	CALL     	5 9 1
	18	[118]	RETURN   	0 1

function <./frontend/ui/widget/htmlboxwidget.lua:120,126> (12 instructions, 48 bytes at 0x7fe38f407740)
1 param, 3 slots, 0 upvalues, 1 local, 3 constants, 0 functions
	1	[121]	GETTABLE 	1 0 -1	; "bb"
	2	[121]	TEST     	1 0 0
	3	[121]	JMP      	7	; to 11
	4	[121]	GETTABLE 	1 0 -1	; "bb"
	5	[121]	GETTABLE 	1 1 -2	; "free"
	6	[121]	TEST     	1 0 0
	7	[121]	JMP      	3	; to 11
	8	[122]	GETTABLE 	1 0 -1	; "bb"
	9	[122]	SELF     	1 1 -2	; "free"
	10	[122]	CALL     	1 2 1
	11	[125]	SETTABLE 	0 -1 -3	; "bb" nil
	12	[126]	RETURN   	0 1

function <./frontend/ui/widget/htmlboxwidget.lua:132,139> (10 instructions, 40 bytes at 0x7fe38f4093b0)
1 param, 3 slots, 0 upvalues, 1 local, 4 constants, 0 functions
	1	[133]	SELF     	1 0 -1	; "freeBb"
	2	[133]	CALL     	1 2 1
	3	[135]	GETTABLE 	1 0 -2	; "document"
	4	[135]	TEST     	1 0 0
	5	[135]	JMP      	4	; to 10
	6	[136]	GETTABLE 	1 0 -2	; "document"
	7	[136]	SELF     	1 1 -3	; "close"
	8	[136]	CALL     	1 2 1
	9	[137]	SETTABLE 	0 -2 -4	; "document" nil
	10	[139]	RETURN   	0 1

function <./frontend/ui/widget/htmlboxwidget.lua:141,144> (3 instructions, 12 bytes at 0x7fe38f4097b0)
1 param, 3 slots, 0 upvalues, 1 local, 1 constant, 0 functions
	1	[143]	SELF     	1 0 -1	; "free"
	2	[143]	CALL     	1 2 1
	3	[144]	RETURN   	0 1

function <./frontend/ui/widget/htmlboxwidget.lua:146,158> (34 instructions, 136 bytes at 0x7fe38f409870)
2 params, 7 slots, 1 upvalue, 3 locals, 7 constants, 0 functions
	1	[147]	GETUPVAL 	2 0	; Geom
	2	[147]	SELF     	2 2 -1	; "new"
	3	[147]	NEWTABLE 	4 0 2
	4	[148]	GETTABLE 	5 1 -2	; "x"
	5	[148]	GETTABLE 	6 0 -3	; "dimen"
	6	[148]	GETTABLE 	6 6 -2	; "x"
	7	[148]	SUB      	5 5 6
	8	[148]	SETTABLE 	4 -2 5	; "x" -
	9	[149]	GETTABLE 	5 1 -4	; "y"
	10	[149]	GETTABLE 	6 0 -3	; "dimen"
	11	[149]	GETTABLE 	6 6 -4	; "y"
	12	[149]	SUB      	5 5 6
	13	[149]	SETTABLE 	4 -4 5	; "y" -
	14	[147]	CALL     	2 3 2
	15	[153]	GETTABLE 	3 2 -2	; "x"
	16	[153]	LT       	1 3 -5	; - 0
	17	[153]	JMP      	13	; to 31
	18	[153]	GETTABLE 	3 2 -2	; "x"
	19	[153]	GETTABLE 	4 0 -3	; "dimen"
	20	[153]	GETTABLE 	4 4 -6	; "w"
	21	[153]	LE       	1 4 3
	22	[153]	JMP      	8	; to 31
	23	[153]	GETTABLE 	3 2 -4	; "y"
	24	[153]	LT       	1 3 -5	; - 0
	25	[153]	JMP      	5	; to 31
	26	[153]	GETTABLE 	3 2 -4	; "y"
	27	[153]	GETTABLE 	4 0 -3	; "dimen"
	28	[153]	GETTABLE 	4 4 -7	; "h"
	29	[153]	LE       	0 4 3
	30	[153]	JMP      	2	; to 33
	31	[154]	LOADNIL  	3 3
	32	[154]	RETURN   	3 2
	33	[157]	RETURN   	2 2
	34	[158]	RETURN   	0 1

function <./frontend/ui/widget/htmlboxwidget.lua:160,170> (16 instructions, 64 bytes at 0x7fe38f406600)
3 params, 6 slots, 1 upvalue, 3 locals, 5 constants, 0 functions
	1	[161]	SELF     	3 0 -2	; "getPosFromAbsPos"
	2	[161]	GETTABLE 	5 2 -3	; "pos"
	3	[161]	CALL     	3 3 2
	4	[161]	SETTABLE 	0 -1 3	; "hold_start_pos" -
	5	[163]	GETTABLE 	3 0 -1	; "hold_start_pos"
	6	[163]	TEST     	3 0 1
	7	[163]	JMP      	2	; to 10
	8	[164]	LOADBOOL 	3 0 0
	9	[164]	RETURN   	3 2
	10	[167]	GETUPVAL 	3 0	; TimeVal
	11	[167]	GETTABLE 	3 3 -5	; "now"
	12	[167]	CALL     	3 1 2
	13	[167]	SETTABLE 	0 -4 3	; "hold_start_tv" -
	14	[169]	LOADBOOL 	3 1 0
	15	[169]	RETURN   	3 2
	16	[170]	RETURN   	0 1

function <./frontend/ui/widget/htmlboxwidget.lua:172,179> (8 instructions, 32 bytes at 0x7fe38f40a270)
3 params, 4 slots, 0 upvalues, 3 locals, 1 constant, 0 functions
	1	[175]	GETTABLE 	3 0 -1	; "hold_start_pos"
	2	[175]	TEST     	3 0 1
	3	[175]	JMP      	2	; to 6
	4	[176]	LOADBOOL 	3 0 0
	5	[176]	RETURN   	3 2
	6	[178]	LOADBOOL 	3 1 0
	7	[178]	RETURN   	3 2
	8	[179]	RETURN   	0 1

function <./frontend/ui/widget/htmlboxwidget.lua:181,211> (85 instructions, 340 bytes at 0x7fe38f40a3b0)
4 params, 19 slots, 0 upvalues, 16 locals, 11 constants, 0 functions
	1	[182]	LOADBOOL 	4 0 0
	2	[183]	NEWTABLE 	5 0 0
	3	[185]	GETGLOBAL	6 -1	; pairs
	4	[185]	MOVE     	7 1
	5	[185]	CALL     	6 2 4
	6	[185]	JMP      	75	; to 82
	7	[186]	GETGLOBAL	11 -1	; pairs
	8	[186]	MOVE     	12 10
	9	[186]	CALL     	11 2 4
	10	[186]	JMP      	69	; to 80
	11	[187]	GETGLOBAL	16 -2	; type
	12	[187]	MOVE     	17 15
	13	[187]	CALL     	16 2 2
	14	[187]	EQ       	0 16 -3	; - "table"
	15	[187]	JMP      	64	; to 80
	16	[188]	TEST     	4 0 1
	17	[188]	JMP      	38	; to 56
	18	[189]	GETTABLE 	16 2 -4	; "x"
	19	[189]	GETTABLE 	17 15 -5	; "x0"
	20	[189]	LE       	0 17 16
	21	[189]	JMP      	14	; to 36
	22	[189]	GETTABLE 	16 2 -4	; "x"
	23	[189]	GETTABLE 	17 15 -6	; "x1"
	24	[189]	LT       	0 16 17
	25	[189]	JMP      	10	; to 36
	26	[189]	GETTABLE 	16 2 -7	; "y"
	27	[189]	GETTABLE 	17 15 -8	; "y0"
	28	[189]	LE       	0 17 16
	29	[189]	JMP      	6	; to 36
	30	[189]	GETTABLE 	16 2 -7	; "y"
	31	[189]	GETTABLE 	17 15 -9	; "y1"
	32	[189]	LT       	0 16 17
	33	[189]	JMP      	2	; to 36
	34	[190]	LOADBOOL 	4 1 0
	35	[190]	JMP      	20	; to 56
	36	[191]	GETTABLE 	16 3 -4	; "x"
	37	[191]	GETTABLE 	17 15 -5	; "x0"
	38	[191]	LE       	0 17 16
	39	[191]	JMP      	16	; to 56
	40	[191]	GETTABLE 	16 3 -4	; "x"
	41	[191]	GETTABLE 	17 15 -6	; "x1"
	42	[191]	LT       	0 16 17
	43	[191]	JMP      	12	; to 56
	44	[191]	GETTABLE 	16 3 -7	; "y"
	45	[191]	GETTABLE 	17 15 -8	; "y0"
	46	[191]	LE       	0 17 16
	47	[191]	JMP      	8	; to 56
	48	[191]	GETTABLE 	16 3 -7	; "y"
	49	[191]	GETTABLE 	17 15 -9	; "y1"
	50	[191]	LT       	0 16 17
	51	[191]	JMP      	4	; to 56
	52	[193]	LOADBOOL 	4 1 0
	53	[194]	MOVE     	16 3
	54	[194]	MOVE     	3 2
	55	[194]	MOVE     	2 16
	56	[198]	TEST     	4 0 0
	57	[198]	JMP      	22	; to 80
	58	[199]	GETGLOBAL	16 -3	; table
	59	[199]	GETTABLE 	16 16 -10	; "insert"
	60	[199]	MOVE     	17 5
	61	[199]	GETTABLE 	18 15 -11	; "word"
	62	[199]	CALL     	16 3 1
	63	[202]	GETTABLE 	16 3 -4	; "x"
	64	[202]	GETTABLE 	17 15 -5	; "x0"
	65	[202]	LE       	0 17 16
	66	[202]	JMP      	13	; to 80
	67	[202]	GETTABLE 	16 3 -4	; "x"
	68	[202]	GETTABLE 	17 15 -6	; "x1"
	69	[202]	LT       	0 16 17
	70	[202]	JMP      	9	; to 80
	71	[202]	GETTABLE 	16 3 -7	; "y"
	72	[202]	GETTABLE 	17 15 -8	; "y0"
	73	[202]	LE       	0 17 16
	74	[202]	JMP      	5	; to 80
	75	[202]	GETTABLE 	16 3 -7	; "y"
	76	[202]	GETTABLE 	17 15 -9	; "y1"
	77	[202]	LT       	0 16 17
	78	[202]	JMP      	1	; to 80
	79	[203]	RETURN   	5 2
	80	[186]	TFORLOOP 	11 2
	81	[206]	JMP      	-71	; to 11
	82	[185]	TFORLOOP 	6 2
	83	[207]	JMP      	-77	; to 7
	84	[210]	RETURN   	5 2
	85	[211]	RETURN   	0 1

function <./frontend/ui/widget/htmlboxwidget.lua:213,243> (52 instructions, 208 bytes at 0x7fe38f40a6a0)
3 params, 13 slots, 1 upvalue, 10 locals, 18 constants, 0 functions
	1	[214]	TEST     	1 0 1
	2	[214]	JMP      	2	; to 5
	3	[215]	LOADBOOL 	3 0 0
	4	[215]	RETURN   	3 2
	5	[219]	GETTABLE 	3 0 -1	; "hold_start_pos"
	6	[219]	TEST     	3 0 1
	7	[219]	JMP      	2	; to 10
	8	[220]	LOADBOOL 	3 0 0
	9	[220]	RETURN   	3 2
	10	[223]	GETTABLE 	3 0 -1	; "hold_start_pos"
	11	[224]	SETTABLE 	0 -1 -2	; "hold_start_pos" nil
	12	[226]	SELF     	4 0 -3	; "getPosFromAbsPos"
	13	[226]	GETTABLE 	6 2 -4	; "pos"
	14	[226]	CALL     	4 3 2
	15	[227]	TEST     	4 0 1
	16	[227]	JMP      	2	; to 19
	17	[228]	LOADBOOL 	5 0 0
	18	[228]	RETURN   	5 2
	19	[231]	GETUPVAL 	5 0	; TimeVal
	20	[231]	GETTABLE 	5 5 -5	; "now"
	21	[231]	CALL     	5 1 2
	22	[231]	GETTABLE 	6 0 -6	; "hold_start_tv"
	23	[231]	SUB      	5 5 6
	24	[232]	GETTABLE 	6 5 -7	; "sec"
	25	[232]	GETTABLE 	7 5 -8	; "usec"
	26	[232]	DIV      	7 7 -9	; - 1000000
	27	[232]	ADD      	5 6 7
	28	[234]	GETTABLE 	6 0 -10	; "document"
	29	[234]	SELF     	6 6 -11	; "openPage"
	30	[234]	GETTABLE 	8 0 -12	; "page_number"
	31	[234]	CALL     	6 3 2
	32	[235]	SELF     	7 6 -13	; "getPageText"
	33	[235]	CALL     	7 2 2
	34	[236]	SELF     	8 6 -14	; "close"
	35	[236]	CALL     	8 2 1
	36	[238]	SELF     	8 0 -15	; "getSelectedText"
	37	[238]	MOVE     	10 7
	38	[238]	MOVE     	11 3
	39	[238]	MOVE     	12 4
	40	[238]	CALL     	8 5 2
	41	[239]	GETGLOBAL	9 -16	; table
	42	[239]	GETTABLE 	9 9 -17	; "concat"
	43	[239]	MOVE     	10 8
	44	[239]	LOADK    	11 -18	; " "
	45	[239]	CALL     	9 3 2
	46	[240]	MOVE     	10 1
	47	[240]	MOVE     	11 9
	48	[240]	MOVE     	12 5
	49	[240]	CALL     	10 3 1
	50	[242]	LOADBOOL 	10 1 0
	51	[242]	RETURN   	10 2
	52	[243]	RETURN   	0 1

function <./frontend/ui/widget/htmlboxwidget.lua:245,255> (32 instructions, 128 bytes at 0x7fe38f40acc0)
2 params, 11 slots, 0 upvalues, 9 locals, 12 constants, 0 functions
	1	[246]	GETTABLE 	2 0 -1	; "document"
	2	[246]	SELF     	2 2 -2	; "openPage"
	3	[246]	GETTABLE 	4 0 -3	; "page_number"
	4	[246]	CALL     	2 3 2
	5	[247]	SELF     	3 2 -4	; "getPageLinks"
	6	[247]	CALL     	3 2 2
	7	[248]	SELF     	4 2 -5	; "close"
	8	[248]	CALL     	4 2 1
	9	[250]	GETGLOBAL	4 -6	; pairs
	10	[250]	MOVE     	5 3
	11	[250]	CALL     	4 2 4
	12	[250]	JMP      	17	; to 30
	13	[251]	GETTABLE 	9 1 -7	; "x"
	14	[251]	GETTABLE 	10 8 -8	; "x0"
	15	[251]	LE       	0 10 9
	16	[251]	JMP      	13	; to 30
	17	[251]	GETTABLE 	9 1 -7	; "x"
	18	[251]	GETTABLE 	10 8 -9	; "x1"
	19	[251]	LT       	0 9 10
	20	[251]	JMP      	9	; to 30
	21	[251]	GETTABLE 	9 1 -10	; "y"
	22	[251]	GETTABLE 	10 8 -11	; "y0"
	23	[251]	LE       	0 10 9
	24	[251]	JMP      	5	; to 30
	25	[251]	GETTABLE 	9 1 -10	; "y"
	26	[251]	GETTABLE 	10 8 -12	; "y1"
	27	[251]	LT       	0 9 10
	28	[251]	JMP      	1	; to 30
	29	[252]	RETURN   	8 2
	30	[250]	TFORLOOP 	4 2
	31	[253]	JMP      	-19	; to 13
	32	[255]	RETURN   	0 1

function <./frontend/ui/widget/htmlboxwidget.lua:257,272> (26 instructions, 104 bytes at 0x7fe38f40b370)
3 params, 7 slots, 0 upvalues, 5 locals, 7 constants, 0 functions
	1	[258]	GETGLOBAL	3 -1	; G_reader_settings
	2	[258]	SELF     	3 3 -2	; "isFalse"
	3	[258]	LOADK    	5 -3	; "tap_to_follow_links"
	4	[258]	CALL     	3 3 2
	5	[258]	TEST     	3 0 0
	6	[258]	JMP      	1	; to 8
	7	[259]	RETURN   	0 1
	8	[262]	GETTABLE 	3 0 -4	; "html_link_tapped_callback"
	9	[262]	TEST     	3 0 0
	10	[262]	JMP      	15	; to 26
	11	[263]	SELF     	3 0 -5	; "getPosFromAbsPos"
	12	[263]	GETTABLE 	5 2 -6	; "pos"
	13	[263]	CALL     	3 3 2
	14	[264]	TEST     	3 0 0
	15	[264]	JMP      	10	; to 26
	16	[265]	SELF     	4 0 -7	; "getLinkByPosition"
	17	[265]	MOVE     	6 3
	18	[265]	CALL     	4 3 2
	19	[266]	TEST     	4 0 0
	20	[266]	JMP      	5	; to 26
	21	[267]	GETTABLE 	5 0 -4	; "html_link_tapped_callback"
	22	[267]	MOVE     	6 4
	23	[267]	CALL     	5 2 1
	24	[268]	LOADBOOL 	5 1 0
	25	[268]	RETURN   	5 2
	26	[272]	RETURN   	0 1
