-- BYTECODE -- httpclient_spec.lua:6-9
0001    GGET     0   0      ; "require"
0002    KSTR     1   1      ; "commonrequire"
0003    CALL     0   1   2
0004    GGET     0   0      ; "require"
0005    KSTR     1   2      ; "ui/uimanager"
0006    CALL     0   2   2
0007    USETV    0   0      ; UIManager
0008    RET0     0   1

-- BYTECODE -- httpclient_spec.lua:12-17
0001    UGET     1   0      ; requests
0002    SUBVN    1   1   0  ; 1
0003    USETV    0   1      ; requests
0004    UGET     1   0      ; requests
0005    ISNEN    1   1      ; 0
0006    JMP      1 => 0011
0007    UGET     1   1      ; UIManager
0008    MOV      2   1
0009    TGETS    1   1   0  ; "quit"
0010    CALL     1   1   2
0011 => GGET     1   1      ; "assert"
0012    TGETS    2   0   2  ; "error"
0013    NOT      2   2
0014    KSTR     3   3      ; "error occurs"
0015    CALL     1   1   3
0016    GGET     1   1      ; "assert"
0017    TGETS    2   0   4  ; "body"
0018    CALL     1   1   2
0019    RET0     0   1

-- BYTECODE -- httpclient_spec.lua:19-37
0001    GGET     0   0      ; "require"
0002    KSTR     1   1      ; "httpclient"
0003    CALL     0   2   2
0004    MOV      2   0
0005    TGETS    1   0   2  ; "new"
0006    CALL     1   2   2
0007    UGET     2   0      ; UIManager
0008    MOV      3   2
0009    TGETS    2   2   3  ; "quit"
0010    CALL     2   1   2
0011    TDUP     2   4
0012    LEN      3   2
0013    USETV    1   3      ; requests
0014    GGET     3   5      ; "ipairs"
0015    MOV      4   2
0016    CALL     3   4   2
0017    JMP      6 => 0024
0018 => MOV      9   1
0019    TGETS    8   1   6  ; "request"
0020    TDUP    10   7
0021    TSETS    7  10   8  ; "url"
0022    UGET    11   2      ; response_callback
0023    CALL     8   1   4
0024 => ITERC    6   3   3
0025    ITERL    6 => 0018
0026    UGET     3   0      ; UIManager
0027    MOV      4   3
0028    TGETS    3   3   9  ; "runForever"
0029    CALL     3   1   2
0030    RET0     0   1

-- BYTECODE -- httpclient_spec.lua:4-38
0001    KPRI     0   0
0002    GGET     1   0      ; "setup"
0003    FNEW     2   1      ; httpclient_spec.lua:6
0004    CALL     1   1   2
0005    KSHORT   1   0
0006    FNEW     2   2      ; httpclient_spec.lua:12
0007    GGET     3   3      ; "it"
0008    KSTR     4   4      ; "should get response from async GET reque"~
0009    FNEW     5   5      ; httpclient_spec.lua:19
0010    CALL     3   1   3
0011    UCLO     0 => 0012
0012 => RET0     0   1

-- BYTECODE -- httpclient_spec.lua:0-39
0001    KPRI     0   1
0002    GSET     0   0      ; "DUSE_TURBO_LIB"
0003    GGET     0   1      ; "describe"
0004    KSTR     1   2      ; "HTTP client module #notest #nocov"
0005    FNEW     2   3      ; httpclient_spec.lua:4
0006    CALL     0   1   3
0007    RET0     0   1

