
main <./spec/unit/httpclient_spec.lua:0,0> (7 instructions, 28 bytes at 0x7fc0a64068c0)
0+ params, 3 slots, 0 upvalues, 0 locals, 3 constants, 1 function
	1	[2]	LOADBOOL 	0 0 0
	2	[2]	SETGLOBAL	0 -1	; DUSE_TURBO_LIB
	3	[4]	GETGLOBAL	0 -2	; describe
	4	[4]	LOADK    	1 -3	; "HTTP client module #notest #nocov"
	5	[38]	CLOSURE  	2 0	; 0x7fc0a6406cb0
	6	[4]	CALL     	0 3 1
	7	[38]	RETURN   	0 1

function <./spec/unit/httpclient_spec.lua:4,38> (16 instructions, 64 bytes at 0x7fc0a6406cb0)
0 params, 6 slots, 0 upvalues, 3 locals, 4 constants, 3 functions
	1	[6]	GETGLOBAL	1 -1	; setup
	2	[9]	CLOSURE  	2 0	; 0x7fc0a6406ea0
	3	[9]	MOVE     	0 0
	4	[6]	CALL     	1 2 1
	5	[11]	LOADK    	1 -2	; 0
	6	[17]	CLOSURE  	2 1	; 0x7fc0a6406a60
	7	[17]	MOVE     	0 1
	8	[17]	MOVE     	0 0
	9	[19]	GETGLOBAL	3 -3	; it
	10	[19]	LOADK    	4 -4	; "should get response from async GET request"
	11	[37]	CLOSURE  	5 2	; 0x7fc0a6407230
	12	[37]	MOVE     	0 0
	13	[37]	MOVE     	0 1
	14	[37]	MOVE     	0 2
	15	[19]	CALL     	3 3 1
	16	[38]	RETURN   	0 1

function <./spec/unit/httpclient_spec.lua:6,9> (8 instructions, 32 bytes at 0x7fc0a6406ea0)
0 params, 2 slots, 1 upvalue, 0 locals, 3 constants, 0 functions
	1	[7]	GETGLOBAL	0 -1	; require
	2	[7]	LOADK    	1 -2	; "commonrequire"
	3	[7]	CALL     	0 2 1
	4	[8]	GETGLOBAL	0 -1	; require
	5	[8]	LOADK    	1 -3	; "ui/uimanager"
	6	[8]	CALL     	0 2 2
	7	[8]	SETUPVAL 	0 0	; UIManager
	8	[9]	RETURN   	0 1

function <./spec/unit/httpclient_spec.lua:12,17> (18 instructions, 72 bytes at 0x7fc0a6406a60)
1 param, 4 slots, 2 upvalues, 1 local, 7 constants, 0 functions
	1	[13]	GETUPVAL 	1 0	; requests
	2	[13]	SUB      	1 1 -1	; - 1
	3	[13]	SETUPVAL 	1 0	; requests
	4	[14]	GETUPVAL 	1 0	; requests
	5	[14]	EQ       	0 1 -2	; - 0
	6	[14]	JMP      	3	; to 10
	7	[14]	GETUPVAL 	1 1	; UIManager
	8	[14]	SELF     	1 1 -3	; "quit"
	9	[14]	CALL     	1 2 1
	10	[15]	GETGLOBAL	1 -4	; assert
	11	[15]	GETTABLE 	2 0 -5	; "error"
	12	[15]	NOT      	2 2
	13	[15]	LOADK    	3 -6	; "error occurs"
	14	[15]	CALL     	1 3 1
	15	[16]	GETGLOBAL	1 -4	; assert
	16	[16]	GETTABLE 	2 0 -7	; "body"
	17	[16]	CALL     	1 2 1
	18	[17]	RETURN   	0 1

function <./spec/unit/httpclient_spec.lua:19,37> (32 instructions, 128 bytes at 0x7fc0a6407230)
0 params, 12 slots, 3 upvalues, 8 locals, 13 constants, 0 functions
	1	[20]	GETGLOBAL	0 -1	; require
	2	[20]	LOADK    	1 -2	; "httpclient"
	3	[20]	CALL     	0 2 2
	4	[21]	SELF     	1 0 -3	; "new"
	5	[21]	CALL     	1 2 2
	6	[22]	GETUPVAL 	2 0	; UIManager
	7	[22]	SELF     	2 2 -4	; "quit"
	8	[22]	CALL     	2 2 1
	9	[23]	NEWTABLE 	2 5 0
	10	[24]	LOADK    	3 -5	; "http://www.example.com"
	11	[25]	LOADK    	4 -6	; "http://www.example.org"
	12	[26]	LOADK    	5 -7	; "http://www.example.net"
	13	[27]	LOADK    	6 -8	; "https://www.example.com"
	14	[29]	LOADK    	7 -9	; "https://www.example.org"
	15	[29]	SETLIST  	2 5 1	; 1
	16	[30]	LEN      	3 2
	17	[30]	SETUPVAL 	3 1	; requests
	18	[31]	GETGLOBAL	3 -10	; ipairs
	19	[31]	MOVE     	4 2
	20	[31]	CALL     	3 2 4
	21	[31]	JMP      	5	; to 27
	22	[32]	SELF     	8 1 -11	; "request"
	23	[32]	NEWTABLE 	10 0 1
	24	[33]	SETTABLE 	10 -12 7	; "url" -
	25	[34]	GETUPVAL 	11 2	; response_callback
	26	[32]	CALL     	8 4 1
	27	[31]	TFORLOOP 	3 2
	28	[34]	JMP      	-7	; to 22
	29	[36]	GETUPVAL 	3 0	; UIManager
	30	[36]	SELF     	3 3 -13	; "runForever"
	31	[36]	CALL     	3 2 1
	32	[37]	RETURN   	0 1
