-- BYTECODE -- iconbutton.lua:32-54
0001    UGET     1   0      ; ImageWidget
0002    MOV      2   1
0003    TGETS    1   1   1  ; "new"
0004    TDUP     3   3
0005    TGETS    4   0   2  ; "icon_file"
0006    TSETS    4   3   4  ; "file"
0007    TGETS    4   0   5  ; "scale_for_dpi"
0008    TSETS    4   3   5  ; "scale_for_dpi"
0009    TGETS    4   0   6  ; "width"
0010    TSETS    4   3   6  ; "width"
0011    TGETS    4   0   7  ; "height"
0012    TSETS    4   3   7  ; "height"
0013    CALL     1   2   3
0014    TSETS    1   0   0  ; "image"
0015    TGETS    1   0   8  ; "show_parent"
0016    IST          1
0017    JMP      2 => 0019
0018    MOV      1   0
0019 => TSETS    1   0   8  ; "show_parent"
0020    UGET     1   1      ; HorizontalGroup
0021    MOV      2   1
0022    TGETS    1   1   1  ; "new"
0023    TNEW     3   0
0024    CALL     1   2   3
0025    TSETS    1   0   9  ; "horizontal_group"
0026    GGET     1  10      ; "table"
0027    TGETS    1   1  11  ; "insert"
0028    TGETS    2   0   9  ; "horizontal_group"
0029    UGET     3   2      ; HorizontalSpan
0030    MOV      4   3
0031    TGETS    3   3   1  ; "new"
0032    TNEW     5   0
0033    CALL     3   0   3
0034    CALLM    1   1   1
0035    GGET     1  10      ; "table"
0036    TGETS    1   1  11  ; "insert"
0037    TGETS    2   0   9  ; "horizontal_group"
0038    TGETS    3   0   0  ; "image"
0039    CALL     1   1   3
0040    GGET     1  10      ; "table"
0041    TGETS    1   1  11  ; "insert"
0042    TGETS    2   0   9  ; "horizontal_group"
0043    UGET     3   2      ; HorizontalSpan
0044    MOV      4   3
0045    TGETS    3   3   1  ; "new"
0046    TNEW     5   0
0047    CALL     3   0   3
0048    CALLM    1   1   1
0049    UGET     1   3      ; VerticalGroup
0050    MOV      2   1
0051    TGETS    1   1   1  ; "new"
0052    TNEW     3   0
0053    CALL     1   2   3
0054    TSETS    1   0  12  ; "button"
0055    GGET     1  10      ; "table"
0056    TGETS    1   1  11  ; "insert"
0057    TGETS    2   0  12  ; "button"
0058    UGET     3   4      ; VerticalSpan
0059    MOV      4   3
0060    TGETS    3   3   1  ; "new"
0061    TNEW     5   0
0062    CALL     3   0   3
0063    CALLM    1   1   1
0064    GGET     1  10      ; "table"
0065    TGETS    1   1  11  ; "insert"
0066    TGETS    2   0  12  ; "button"
0067    TGETS    3   0   9  ; "horizontal_group"
0068    CALL     1   1   3
0069    GGET     1  10      ; "table"
0070    TGETS    1   1  11  ; "insert"
0071    TGETS    2   0  12  ; "button"
0072    UGET     3   4      ; VerticalSpan
0073    MOV      4   3
0074    TGETS    3   3   1  ; "new"
0075    TNEW     5   0
0076    CALL     3   0   3
0077    CALLM    1   1   1
0078    TGETS    1   0  12  ; "button"
0079    TSETB    1   0   1
0080    MOV      2   0
0081    TGETS    1   0  13  ; "update"
0082    CALL     1   1   2
0083    RET0     0   1

-- BYTECODE -- iconbutton.lua:56-71
0001    TGETS    1   0   0  ; "padding_top"
0002    IST          1
0003    JMP      1 => 0006
0004    TGETS    1   0   1  ; "padding"
0005    TSETS    1   0   0  ; "padding_top"
0006 => TGETS    1   0   2  ; "padding_right"
0007    IST          1
0008    JMP      1 => 0011
0009    TGETS    1   0   1  ; "padding"
0010    TSETS    1   0   2  ; "padding_right"
0011 => TGETS    1   0   3  ; "padding_bottom"
0012    IST          1
0013    JMP      1 => 0016
0014    TGETS    1   0   1  ; "padding"
0015    TSETS    1   0   3  ; "padding_bottom"
0016 => TGETS    1   0   4  ; "padding_left"
0017    IST          1
0018    JMP      1 => 0021
0019    TGETS    1   0   1  ; "padding"
0020    TSETS    1   0   4  ; "padding_left"
0021 => TGETS    1   0   5  ; "horizontal_group"
0022    TGETB    1   1   1
0023    TGETS    2   0   4  ; "padding_left"
0024    TSETS    2   1   6  ; "width"
0025    TGETS    1   0   5  ; "horizontal_group"
0026    TGETB    1   1   3
0027    TGETS    2   0   2  ; "padding_right"
0028    TSETS    2   1   6  ; "width"
0029    TGETS    1   0   8  ; "image"
0030    MOV      2   1
0031    TGETS    1   1   9  ; "getSize"
0032    CALL     1   2   2
0033    TSETS    1   0   7  ; "dimen"
0034    TGETS    1   0   7  ; "dimen"
0035    TGETS    2   0   7  ; "dimen"
0036    TGETS    2   2  10  ; "w"
0037    TGETS    3   0   4  ; "padding_left"
0038    ADDVV    2   2   3
0039    TGETS    3   0   2  ; "padding_right"
0040    ADDVV    2   2   3
0041    TSETS    2   1  10  ; "w"
0042    TGETS    1   0  11  ; "button"
0043    TGETB    1   1   1
0044    TGETS    2   0   0  ; "padding_top"
0045    TSETS    2   1   6  ; "width"
0046    TGETS    1   0  11  ; "button"
0047    TGETB    1   1   3
0048    TGETS    2   0   3  ; "padding_bottom"
0049    TSETS    2   1   6  ; "width"
0050    TGETS    1   0   7  ; "dimen"
0051    TGETS    2   0   7  ; "dimen"
0052    TGETS    2   2  12  ; "h"
0053    TGETS    3   0   0  ; "padding_top"
0054    ADDVV    2   2   3
0055    TGETS    3   0   3  ; "padding_bottom"
0056    ADDVV    2   2   3
0057    TSETS    2   1  12  ; "h"
0058    MOV      2   0
0059    TGETS    1   0  13  ; "initGesListener"
0060    CALL     1   1   2
0061    RET0     0   1

-- BYTECODE -- iconbutton.lua:73-92
0001    UGET     1   0      ; Device
0002    MOV      2   1
0003    TGETS    1   1   0  ; "isTouchDevice"
0004    CALL     1   2   2
0005    ISF          1
0006    JMP      2 => 0029
0007    TDUP     1   7
0008    TDUP     2   6
0009    UGET     3   1      ; GestureRange
0010    MOV      4   3
0011    TGETS    3   3   2  ; "new"
0012    TDUP     5   3
0013    TGETS    6   0   4  ; "dimen"
0014    TSETS    6   5   5  ; "range"
0015    CALL     3   2   3
0016    TSETB    3   2   1
0017    TSETS    2   1   8  ; "TapIconButton"
0018    TDUP     2  10
0019    UGET     3   1      ; GestureRange
0020    MOV      4   3
0021    TGETS    3   3   2  ; "new"
0022    TDUP     5   9
0023    TGETS    6   0   4  ; "dimen"
0024    TSETS    6   5   5  ; "range"
0025    CALL     3   2   3
0026    TSETB    3   2   1
0027    TSETS    2   1  11  ; "HoldIconButton"
0028    TSETS    1   0   1  ; "ges_events"
0029 => RET0     0   1

-- BYTECODE -- iconbutton.lua:102-104
0001    KSTR     0   0      ; "fast"
0002    UGET     1   0      ; self
0003    TGETS    1   1   1  ; "dimen"
0004    RET      0   3

-- BYTECODE -- iconbutton.lua:110-112
0001    KSTR     0   0      ; "fast"
0002    UGET     1   0      ; self
0003    TGETS    1   1   1  ; "dimen"
0004    RET      0   3

-- BYTECODE -- iconbutton.lua:106-113
0001    UGET     0   0      ; self
0002    TGETS    0   0   0  ; "callback"
0003    CALL     0   1   1
0004    UGET     0   0      ; self
0005    TGETS    0   0   1  ; "image"
0006    KPRI     1   1
0007    TSETS    1   0   2  ; "invert"
0008    UGET     0   1      ; UIManager
0009    MOV      1   0
0010    TGETS    0   0   3  ; "widgetRepaint"
0011    UGET     2   0      ; self
0012    TGETS    2   2   1  ; "image"
0013    UGET     3   0      ; self
0014    TGETS    3   3   4  ; "dimen"
0015    TGETS    3   3   5  ; "x"
0016    UGET     4   0      ; self
0017    TGETS    4   4   6  ; "padding_left"
0018    ADDVV    3   3   4
0019    UGET     4   0      ; self
0020    TGETS    4   4   4  ; "dimen"
0021    TGETS    4   4   7  ; "y"
0022    UGET     5   0      ; self
0023    TGETS    5   5   8  ; "padding_top"
0024    ADDVV    4   4   5
0025    CALL     0   1   5
0026    UGET     0   1      ; UIManager
0027    MOV      1   0
0028    TGETS    0   0   9  ; "setDirty"
0029    KPRI     2   0
0030    FNEW     3  10      ; iconbutton.lua:110
0031    CALL     0   1   4
0032    RET0     0   1

-- BYTECODE -- iconbutton.lua:94-116
0001    TGETS    1   0   0  ; "callback"
0002    IST          1
0003    JMP      1 => 0005
0004    UCLO     0 => 0045
0005 => GGET     1   1      ; "G_reader_settings"
0006    MOV      2   1
0007    TGETS    1   1   2  ; "isFalse"
0008    KSTR     3   3      ; "flash_ui"
0009    CALL     1   2   3
0010    ISF          1
0011    JMP      2 => 0015
0012    TGETS    1   0   0  ; "callback"
0013    CALL     1   1   1
0014    JMP      1 => 0042
0015 => TGETS    1   0   4  ; "image"
0016    KPRI     2   2
0017    TSETS    2   1   5  ; "invert"
0018    UGET     1   0      ; UIManager
0019    MOV      2   1
0020    TGETS    1   1   6  ; "widgetRepaint"
0021    TGETS    3   0   4  ; "image"
0022    TGETS    4   0   7  ; "dimen"
0023    TGETS    4   4   8  ; "x"
0024    TGETS    5   0   9  ; "padding_left"
0025    ADDVV    4   4   5
0026    TGETS    5   0   7  ; "dimen"
0027    TGETS    5   5  10  ; "y"
0028    TGETS    6   0  11  ; "padding_top"
0029    ADDVV    5   5   6
0030    CALL     1   1   5
0031    UGET     1   0      ; UIManager
0032    MOV      2   1
0033    TGETS    1   1  12  ; "setDirty"
0034    KPRI     3   0
0035    FNEW     4  13      ; iconbutton.lua:102
0036    CALL     1   1   4
0037    UGET     1   0      ; UIManager
0038    MOV      2   1
0039    TGETS    1   1  14  ; "tickAfterNext"
0040    FNEW     3  15      ; iconbutton.lua:106
0041    CALL     1   1   3
0042 => KPRI     1   2
0043    UCLO     0 => 0044
0044 => RET1     1   2
0045 => RET0     0   1

-- BYTECODE -- iconbutton.lua:118-127
0001    TGETS    1   0   0  ; "enabled"
0002    ISF          1
0003    JMP      2 => 0010
0004    TGETS    1   0   1  ; "hold_callback"
0005    ISF          1
0006    JMP      2 => 0010
0007    TGETS    1   0   1  ; "hold_callback"
0008    CALL     1   1   1
0009    JMP      1 => 0033
0010 => TGETS    1   0   2  ; "hold_input"
0011    ISF          1
0012    JMP      2 => 0018
0013    MOV      2   0
0014    TGETS    1   0   3  ; "onInput"
0015    TGETS    3   0   2  ; "hold_input"
0016    CALL     1   1   3
0017    JMP      1 => 0033
0018 => GGET     1   4      ; "type"
0019    TGETS    2   0   5  ; "hold_input_func"
0020    CALL     1   2   2
0021    ISNES    1   6      ; "function"
0022    JMP      1 => 0029
0023    MOV      2   0
0024    TGETS    1   0   3  ; "onInput"
0025    TGETS    3   0   5  ; "hold_input_func"
0026    CALL     3   0   1
0027    CALLM    1   1   1
0028    JMP      1 => 0033
0029 => TGETS    1   0   1  ; "hold_callback"
0030    ISNEP    1   0
0031    JMP      1 => 0033
0032    RET0     0   1
0033 => KPRI     1   2
0034    RET1     1   2

-- BYTECODE -- iconbutton.lua:129-133
0001    TGETS    1   0   0  ; "image"
0002    KPRI     2   2
0003    TSETS    2   1   1  ; "invert"
0004    KPRI     1   2
0005    RET1     1   2

-- BYTECODE -- iconbutton.lua:135-138
0001    TGETS    1   0   0  ; "image"
0002    KPRI     2   1
0003    TSETS    2   1   1  ; "invert"
0004    KPRI     1   2
0005    RET1     1   2

-- BYTECODE -- iconbutton.lua:140-142
0001    MOV      2   0
0002    TGETS    1   0   0  ; "onTapIconButton"
0003    CALL     1   1   2
0004    RET0     0   1

-- BYTECODE -- iconbutton.lua:0-145
0001    GGET     0   0      ; "require"
0002    KSTR     1   1      ; "device"
0003    CALL     0   2   2
0004    GGET     1   0      ; "require"
0005    KSTR     2   2      ; "ui/widget/horizontalgroup"
0006    CALL     1   2   2
0007    GGET     2   0      ; "require"
0008    KSTR     3   3      ; "ui/widget/horizontalspan"
0009    CALL     2   2   2
0010    GGET     3   0      ; "require"
0011    KSTR     4   4      ; "ui/widget/container/inputcontainer"
0012    CALL     3   2   2
0013    GGET     4   0      ; "require"
0014    KSTR     5   5      ; "ui/widget/imagewidget"
0015    CALL     4   2   2
0016    GGET     5   0      ; "require"
0017    KSTR     6   6      ; "ui/gesturerange"
0018    CALL     5   2   2
0019    GGET     6   0      ; "require"
0020    KSTR     7   7      ; "ui/uimanager"
0021    CALL     6   2   2
0022    GGET     7   0      ; "require"
0023    KSTR     8   8      ; "ui/widget/verticalgroup"
0024    CALL     7   2   2
0025    GGET     8   0      ; "require"
0026    KSTR     9   9      ; "ui/widget/verticalspan"
0027    CALL     8   2   2
0028    MOV     10   3
0029    TGETS    9   3  10  ; "new"
0030    TDUP    11  11
0031    CALL     9   2   3
0032    FNEW    10  13      ; iconbutton.lua:32
0033    TSETS   10   9  12  ; "init"
0034    FNEW    10  15      ; iconbutton.lua:56
0035    TSETS   10   9  14  ; "update"
0036    FNEW    10  17      ; iconbutton.lua:73
0037    TSETS   10   9  16  ; "initGesListener"
0038    FNEW    10  19      ; iconbutton.lua:94
0039    TSETS   10   9  18  ; "onTapIconButton"
0040    FNEW    10  21      ; iconbutton.lua:118
0041    TSETS   10   9  20  ; "onHoldIconButton"
0042    FNEW    10  23      ; iconbutton.lua:129
0043    TSETS   10   9  22  ; "onFocus"
0044    FNEW    10  25      ; iconbutton.lua:135
0045    TSETS   10   9  24  ; "onUnfocus"
0046    FNEW    10  27      ; iconbutton.lua:140
0047    TSETS   10   9  26  ; "onTapSelect"
0048    UCLO     0 => 0049
0049 => RET1     9   2

