
main <./frontend/ui/widget/iconbutton.lua:0,0> (69 instructions, 276 bytes at 0x7fa5bbc068d0)
0+ params, 12 slots, 0 upvalues, 10 locals, 36 constants, 8 functions
	1	[5]	GETGLOBAL	0 -1	; require
	2	[5]	LOADK    	1 -2	; "device"
	3	[5]	CALL     	0 2 2
	4	[6]	GETGLOBAL	1 -1	; require
	5	[6]	LOADK    	2 -3	; "ui/widget/horizontalgroup"
	6	[6]	CALL     	1 2 2
	7	[7]	GETGLOBAL	2 -1	; require
	8	[7]	LOADK    	3 -4	; "ui/widget/horizontalspan"
	9	[7]	CALL     	2 2 2
	10	[8]	GETGLOBAL	3 -1	; require
	11	[8]	LOADK    	4 -5	; "ui/widget/container/inputcontainer"
	12	[8]	CALL     	3 2 2
	13	[9]	GETGLOBAL	4 -1	; require
	14	[9]	LOADK    	5 -6	; "ui/widget/imagewidget"
	15	[9]	CALL     	4 2 2
	16	[10]	GETGLOBAL	5 -1	; require
	17	[10]	LOADK    	6 -7	; "ui/gesturerange"
	18	[10]	CALL     	5 2 2
	19	[11]	GETGLOBAL	6 -1	; require
	20	[11]	LOADK    	7 -8	; "ui/uimanager"
	21	[11]	CALL     	6 2 2
	22	[12]	GETGLOBAL	7 -1	; require
	23	[12]	LOADK    	8 -9	; "ui/widget/verticalgroup"
	24	[12]	CALL     	7 2 2
	25	[13]	GETGLOBAL	8 -1	; require
	26	[13]	LOADK    	9 -10	; "ui/widget/verticalspan"
	27	[13]	CALL     	8 2 2
	28	[15]	SELF     	9 3 -11	; "new"
	29	[15]	NEWTABLE 	11 0 13
	30	[16]	SETTABLE 	11 -12 -13	; "icon_file" "resources/info-confirm.png"
	31	[17]	SETTABLE 	11 -14 -15	; "dimen" nil
	32	[19]	SETTABLE 	11 -16 -15	; "show_parent" nil
	33	[20]	SETTABLE 	11 -17 -15	; "width" nil
	34	[21]	SETTABLE 	11 -18 -15	; "height" nil
	35	[22]	SETTABLE 	11 -19 -20	; "scale_for_dpi" true
	36	[23]	SETTABLE 	11 -21 -22	; "padding" 0
	37	[24]	SETTABLE 	11 -23 -15	; "padding_top" nil
	38	[25]	SETTABLE 	11 -24 -15	; "padding_right" nil
	39	[26]	SETTABLE 	11 -25 -15	; "padding_bottom" nil
	40	[27]	SETTABLE 	11 -26 -15	; "padding_left" nil
	41	[28]	SETTABLE 	11 -27 -20	; "enabled" true
	42	[29]	SETTABLE 	11 -28 -15	; "callback" nil
	43	[15]	CALL     	9 3 2
	44	[54]	CLOSURE  	10 0	; 0x7fa5bbc07130
	45	[54]	MOVE     	0 4
	46	[54]	MOVE     	0 1
	47	[54]	MOVE     	0 2
	48	[54]	MOVE     	0 7
	49	[54]	MOVE     	0 8
	50	[32]	SETTABLE 	9 -29 10	; "init" -
	51	[71]	CLOSURE  	10 1	; 0x7fa5bbc07970
	52	[56]	SETTABLE 	9 -30 10	; "update" -
	53	[92]	CLOSURE  	10 2	; 0x7fa5bbc07530
	54	[92]	MOVE     	0 0
	55	[92]	MOVE     	0 5
	56	[73]	SETTABLE 	9 -31 10	; "initGesListener" -
	57	[116]	CLOSURE  	10 3	; 0x7fa5bbc08430
	58	[116]	MOVE     	0 6
	59	[94]	SETTABLE 	9 -32 10	; "onTapIconButton" -
	60	[127]	CLOSURE  	10 4	; 0x7fa5bbc092e0
	61	[118]	SETTABLE 	9 -33 10	; "onHoldIconButton" -
	62	[133]	CLOSURE  	10 5	; 0x7fa5bbc09150
	63	[129]	SETTABLE 	9 -34 10	; "onFocus" -
	64	[138]	CLOSURE  	10 6	; 0x7fa5bbc08f60
	65	[135]	SETTABLE 	9 -35 10	; "onUnfocus" -
	66	[142]	CLOSURE  	10 7	; 0x7fa5bbc065f0
	67	[140]	SETTABLE 	9 -36 10	; "onTapSelect" -
	68	[144]	RETURN   	9 2
	69	[144]	RETURN   	0 1

function <./frontend/ui/widget/iconbutton.lua:32,54> (75 instructions, 300 bytes at 0x7fa5bbc07130)
1 param, 6 slots, 5 upvalues, 1 local, 14 constants, 0 functions
	1	[33]	GETUPVAL 	1 0	; ImageWidget
	2	[33]	SELF     	1 1 -2	; "new"
	3	[33]	NEWTABLE 	3 0 4
	4	[34]	GETTABLE 	4 0 -4	; "icon_file"
	5	[34]	SETTABLE 	3 -3 4	; "file" -
	6	[35]	GETTABLE 	4 0 -5	; "scale_for_dpi"
	7	[35]	SETTABLE 	3 -5 4	; "scale_for_dpi" -
	8	[36]	GETTABLE 	4 0 -6	; "width"
	9	[36]	SETTABLE 	3 -6 4	; "width" -
	10	[37]	GETTABLE 	4 0 -7	; "height"
	11	[37]	SETTABLE 	3 -7 4	; "height" -
	12	[33]	CALL     	1 3 2
	13	[38]	SETTABLE 	0 -1 1	; "image" -
	14	[40]	GETTABLE 	1 0 -8	; "show_parent"
	15	[40]	TEST     	1 0 1
	16	[40]	JMP      	1	; to 18
	17	[40]	MOVE     	1 0
	18	[40]	SETTABLE 	0 -8 1	; "show_parent" -
	19	[42]	GETUPVAL 	1 1	; HorizontalGroup
	20	[42]	SELF     	1 1 -2	; "new"
	21	[42]	NEWTABLE 	3 0 0
	22	[42]	CALL     	1 3 2
	23	[42]	SETTABLE 	0 -9 1	; "horizontal_group" -
	24	[43]	GETGLOBAL	1 -10	; table
	25	[43]	GETTABLE 	1 1 -11	; "insert"
	26	[43]	GETTABLE 	2 0 -9	; "horizontal_group"
	27	[43]	GETUPVAL 	3 2	; HorizontalSpan
	28	[43]	SELF     	3 3 -2	; "new"
	29	[43]	NEWTABLE 	5 0 0
	30	[43]	CALL     	3 3 0
	31	[43]	CALL     	1 0 1
	32	[44]	GETGLOBAL	1 -10	; table
	33	[44]	GETTABLE 	1 1 -11	; "insert"
	34	[44]	GETTABLE 	2 0 -9	; "horizontal_group"
	35	[44]	GETTABLE 	3 0 -1	; "image"
	36	[44]	CALL     	1 3 1
	37	[45]	GETGLOBAL	1 -10	; table
	38	[45]	GETTABLE 	1 1 -11	; "insert"
	39	[45]	GETTABLE 	2 0 -9	; "horizontal_group"
	40	[45]	GETUPVAL 	3 2	; HorizontalSpan
	41	[45]	SELF     	3 3 -2	; "new"
	42	[45]	NEWTABLE 	5 0 0
	43	[45]	CALL     	3 3 0
	44	[45]	CALL     	1 0 1
	45	[47]	GETUPVAL 	1 3	; VerticalGroup
	46	[47]	SELF     	1 1 -2	; "new"
	47	[47]	NEWTABLE 	3 0 0
	48	[47]	CALL     	1 3 2
	49	[47]	SETTABLE 	0 -12 1	; "button" -
	50	[48]	GETGLOBAL	1 -10	; table
	51	[48]	GETTABLE 	1 1 -11	; "insert"
	52	[48]	GETTABLE 	2 0 -12	; "button"
	53	[48]	GETUPVAL 	3 4	; VerticalSpan
	54	[48]	SELF     	3 3 -2	; "new"
	55	[48]	NEWTABLE 	5 0 0
	56	[48]	CALL     	3 3 0
	57	[48]	CALL     	1 0 1
	58	[49]	GETGLOBAL	1 -10	; table
	59	[49]	GETTABLE 	1 1 -11	; "insert"
	60	[49]	GETTABLE 	2 0 -12	; "button"
	61	[49]	GETTABLE 	3 0 -9	; "horizontal_group"
	62	[49]	CALL     	1 3 1
	63	[50]	GETGLOBAL	1 -10	; table
	64	[50]	GETTABLE 	1 1 -11	; "insert"
	65	[50]	GETTABLE 	2 0 -12	; "button"
	66	[50]	GETUPVAL 	3 4	; VerticalSpan
	67	[50]	SELF     	3 3 -2	; "new"
	68	[50]	NEWTABLE 	5 0 0
	69	[50]	CALL     	3 3 0
	70	[50]	CALL     	1 0 1
	71	[52]	GETTABLE 	1 0 -12	; "button"
	72	[52]	SETTABLE 	0 -13 1	; 1 -
	73	[53]	SELF     	1 0 -14	; "update"
	74	[53]	CALL     	1 2 1
	75	[54]	RETURN   	0 1

function <./frontend/ui/widget/iconbutton.lua:56,71> (59 instructions, 236 bytes at 0x7fa5bbc07970)
1 param, 4 slots, 0 upvalues, 1 local, 16 constants, 0 functions
	1	[57]	GETTABLE 	1 0 -1	; "padding_top"
	2	[57]	TEST     	1 0 1
	3	[57]	JMP      	2	; to 6
	4	[57]	GETTABLE 	1 0 -2	; "padding"
	5	[57]	SETTABLE 	0 -1 1	; "padding_top" -
	6	[58]	GETTABLE 	1 0 -3	; "padding_right"
	7	[58]	TEST     	1 0 1
	8	[58]	JMP      	2	; to 11
	9	[58]	GETTABLE 	1 0 -2	; "padding"
	10	[58]	SETTABLE 	0 -3 1	; "padding_right" -
	11	[59]	GETTABLE 	1 0 -4	; "padding_bottom"
	12	[59]	TEST     	1 0 1
	13	[59]	JMP      	2	; to 16
	14	[59]	GETTABLE 	1 0 -2	; "padding"
	15	[59]	SETTABLE 	0 -4 1	; "padding_bottom" -
	16	[60]	GETTABLE 	1 0 -5	; "padding_left"
	17	[60]	TEST     	1 0 1
	18	[60]	JMP      	2	; to 21
	19	[60]	GETTABLE 	1 0 -2	; "padding"
	20	[60]	SETTABLE 	0 -5 1	; "padding_left" -
	21	[62]	GETTABLE 	1 0 -6	; "horizontal_group"
	22	[62]	GETTABLE 	1 1 -7	; 1
	23	[62]	GETTABLE 	2 0 -5	; "padding_left"
	24	[62]	SETTABLE 	1 -8 2	; "width" -
	25	[63]	GETTABLE 	1 0 -6	; "horizontal_group"
	26	[63]	GETTABLE 	1 1 -9	; 3
	27	[63]	GETTABLE 	2 0 -3	; "padding_right"
	28	[63]	SETTABLE 	1 -8 2	; "width" -
	29	[64]	GETTABLE 	1 0 -11	; "image"
	30	[64]	SELF     	1 1 -12	; "getSize"
	31	[64]	CALL     	1 2 2
	32	[64]	SETTABLE 	0 -10 1	; "dimen" -
	33	[65]	GETTABLE 	1 0 -10	; "dimen"
	34	[65]	GETTABLE 	2 0 -10	; "dimen"
	35	[65]	GETTABLE 	2 2 -13	; "w"
	36	[65]	GETTABLE 	3 0 -5	; "padding_left"
	37	[65]	ADD      	2 2 3
	38	[65]	GETTABLE 	3 0 -3	; "padding_right"
	39	[65]	ADD      	2 2 3
	40	[65]	SETTABLE 	1 -13 2	; "w" -
	41	[67]	GETTABLE 	1 0 -14	; "button"
	42	[67]	GETTABLE 	1 1 -7	; 1
	43	[67]	GETTABLE 	2 0 -1	; "padding_top"
	44	[67]	SETTABLE 	1 -8 2	; "width" -
	45	[68]	GETTABLE 	1 0 -14	; "button"
	46	[68]	GETTABLE 	1 1 -9	; 3
	47	[68]	GETTABLE 	2 0 -4	; "padding_bottom"
	48	[68]	SETTABLE 	1 -8 2	; "width" -
	49	[69]	GETTABLE 	1 0 -10	; "dimen"
	50	[69]	GETTABLE 	2 0 -10	; "dimen"
	51	[69]	GETTABLE 	2 2 -15	; "h"
	52	[69]	GETTABLE 	3 0 -1	; "padding_top"
	53	[69]	ADD      	2 2 3
	54	[69]	GETTABLE 	3 0 -4	; "padding_bottom"
	55	[69]	ADD      	2 2 3
	56	[69]	SETTABLE 	1 -15 2	; "h" -
	57	[70]	SELF     	1 0 -16	; "initGesListener"
	58	[70]	CALL     	1 2 1
	59	[71]	RETURN   	0 1

function <./frontend/ui/widget/iconbutton.lua:73,92> (30 instructions, 120 bytes at 0x7fa5bbc07530)
1 param, 7 slots, 2 upvalues, 1 local, 13 constants, 0 functions
	1	[74]	GETUPVAL 	1 0	; Device
	2	[74]	SELF     	1 1 -1	; "isTouchDevice"
	3	[74]	CALL     	1 2 2
	4	[74]	TEST     	1 0 0
	5	[74]	JMP      	24	; to 30
	6	[75]	NEWTABLE 	1 0 2
	7	[76]	NEWTABLE 	2 1 1
	8	[77]	GETUPVAL 	3 1	; GestureRange
	9	[77]	SELF     	3 3 -4	; "new"
	10	[77]	NEWTABLE 	5 0 2
	11	[78]	SETTABLE 	5 -5 -6	; "ges" "tap"
	12	[79]	GETTABLE 	6 0 -8	; "dimen"
	13	[79]	SETTABLE 	5 -7 6	; "range" -
	14	[77]	CALL     	3 3 2
	15	[81]	SETTABLE 	2 -9 -10	; "doc" "Tap IconButton"
	16	[82]	SETLIST  	2 1 1	; 1
	17	[82]	SETTABLE 	1 -3 2	; "TapIconButton" -
	18	[83]	NEWTABLE 	2 1 1
	19	[84]	GETUPVAL 	3 1	; GestureRange
	20	[84]	SELF     	3 3 -4	; "new"
	21	[84]	NEWTABLE 	5 0 2
	22	[85]	SETTABLE 	5 -5 -12	; "ges" "hold"
	23	[86]	GETTABLE 	6 0 -8	; "dimen"
	24	[86]	SETTABLE 	5 -7 6	; "range" -
	25	[84]	CALL     	3 3 2
	26	[88]	SETTABLE 	2 -9 -13	; "doc" "Hold IconButton"
	27	[89]	SETLIST  	2 1 1	; 1
	28	[89]	SETTABLE 	1 -11 2	; "HoldIconButton" -
	29	[90]	SETTABLE 	0 -2 1	; "ges_events" -
	30	[92]	RETURN   	0 1

function <./frontend/ui/widget/iconbutton.lua:94,116> (42 instructions, 168 bytes at 0x7fa5bbc08430)
1 param, 7 slots, 1 upvalue, 1 local, 15 constants, 2 functions
	1	[95]	GETTABLE 	1 0 -1	; "callback"
	2	[95]	TEST     	1 0 1
	3	[95]	JMP      	1	; to 5
	4	[95]	RETURN   	0 1
	5	[96]	GETGLOBAL	1 -2	; G_reader_settings
	6	[96]	SELF     	1 1 -3	; "isFalse"
	7	[96]	LOADK    	3 -4	; "flash_ui"
	8	[96]	CALL     	1 3 2
	9	[96]	TEST     	1 0 0
	10	[96]	JMP      	3	; to 14
	11	[97]	GETTABLE 	1 0 -1	; "callback"
	12	[97]	CALL     	1 1 1
	13	[97]	JMP      	26	; to 40
	14	[99]	GETTABLE 	1 0 -5	; "image"
	15	[99]	SETTABLE 	1 -6 -7	; "invert" true
	16	[101]	GETUPVAL 	1 0	; UIManager
	17	[101]	SELF     	1 1 -8	; "widgetRepaint"
	18	[101]	GETTABLE 	3 0 -5	; "image"
	19	[101]	GETTABLE 	4 0 -9	; "dimen"
	20	[101]	GETTABLE 	4 4 -10	; "x"
	21	[101]	GETTABLE 	5 0 -11	; "padding_left"
	22	[101]	ADD      	4 4 5
	23	[101]	GETTABLE 	5 0 -9	; "dimen"
	24	[101]	GETTABLE 	5 5 -12	; "y"
	25	[101]	GETTABLE 	6 0 -13	; "padding_top"
	26	[101]	ADD      	5 5 6
	27	[101]	CALL     	1 5 1
	28	[102]	GETUPVAL 	1 0	; UIManager
	29	[102]	SELF     	1 1 -14	; "setDirty"
	30	[102]	LOADNIL  	3 3
	31	[104]	CLOSURE  	4 0	; 0x7fa5bbc067c0
	32	[104]	MOVE     	0 0
	33	[102]	CALL     	1 4 1
	34	[106]	GETUPVAL 	1 0	; UIManager
	35	[106]	SELF     	1 1 -15	; "tickAfterNext"
	36	[113]	CLOSURE  	3 1	; 0x7fa5bbc08610
	37	[113]	MOVE     	0 0
	38	[113]	GETUPVAL 	0 0	; UIManager
	39	[106]	CALL     	1 3 1
	40	[115]	LOADBOOL 	1 1 0
	41	[115]	RETURN   	1 2
	42	[116]	RETURN   	0 1

function <./frontend/ui/widget/iconbutton.lua:102,104> (5 instructions, 20 bytes at 0x7fa5bbc067c0)
0 params, 2 slots, 1 upvalue, 0 locals, 2 constants, 0 functions
	1	[103]	LOADK    	0 -1	; "fast"
	2	[103]	GETUPVAL 	1 0	; self
	3	[103]	GETTABLE 	1 1 -2	; "dimen"
	4	[103]	RETURN   	0 3
	5	[104]	RETURN   	0 1

function <./frontend/ui/widget/iconbutton.lua:106,113> (30 instructions, 120 bytes at 0x7fa5bbc08610)
0 params, 6 slots, 2 upvalues, 0 locals, 11 constants, 1 function
	1	[107]	GETUPVAL 	0 0	; self
	2	[107]	GETTABLE 	0 0 -1	; "callback"
	3	[107]	CALL     	0 1 1
	4	[108]	GETUPVAL 	0 0	; self
	5	[108]	GETTABLE 	0 0 -2	; "image"
	6	[108]	SETTABLE 	0 -3 -4	; "invert" false
	7	[109]	GETUPVAL 	0 1	; UIManager
	8	[109]	SELF     	0 0 -5	; "widgetRepaint"
	9	[109]	GETUPVAL 	2 0	; self
	10	[109]	GETTABLE 	2 2 -2	; "image"
	11	[109]	GETUPVAL 	3 0	; self
	12	[109]	GETTABLE 	3 3 -6	; "dimen"
	13	[109]	GETTABLE 	3 3 -7	; "x"
	14	[109]	GETUPVAL 	4 0	; self
	15	[109]	GETTABLE 	4 4 -8	; "padding_left"
	16	[109]	ADD      	3 3 4
	17	[109]	GETUPVAL 	4 0	; self
	18	[109]	GETTABLE 	4 4 -6	; "dimen"
	19	[109]	GETTABLE 	4 4 -9	; "y"
	20	[109]	GETUPVAL 	5 0	; self
	21	[109]	GETTABLE 	5 5 -10	; "padding_top"
	22	[109]	ADD      	4 4 5
	23	[109]	CALL     	0 5 1
	24	[110]	GETUPVAL 	0 1	; UIManager
	25	[110]	SELF     	0 0 -11	; "setDirty"
	26	[110]	LOADNIL  	2 2
	27	[112]	CLOSURE  	3 0	; 0x7fa5bbc08d40
	28	[112]	GETUPVAL 	0 0	; self
	29	[110]	CALL     	0 4 1
	30	[113]	RETURN   	0 1

function <./frontend/ui/widget/iconbutton.lua:110,112> (5 instructions, 20 bytes at 0x7fa5bbc08d40)
0 params, 2 slots, 1 upvalue, 0 locals, 2 constants, 0 functions
	1	[111]	LOADK    	0 -1	; "fast"
	2	[111]	GETUPVAL 	1 0	; self
	3	[111]	GETTABLE 	1 1 -2	; "dimen"
	4	[111]	RETURN   	0 3
	5	[112]	RETURN   	0 1

function <./frontend/ui/widget/iconbutton.lua:118,127> (33 instructions, 132 bytes at 0x7fa5bbc092e0)
1 param, 4 slots, 0 upvalues, 1 local, 8 constants, 0 functions
	1	[119]	GETTABLE 	1 0 -1	; "enabled"
	2	[119]	TEST     	1 0 0
	3	[119]	JMP      	6	; to 10
	4	[119]	GETTABLE 	1 0 -2	; "hold_callback"
	5	[119]	TEST     	1 0 0
	6	[119]	JMP      	3	; to 10
	7	[120]	GETTABLE 	1 0 -2	; "hold_callback"
	8	[120]	CALL     	1 1 1
	9	[120]	JMP      	21	; to 31
	10	[121]	GETTABLE 	1 0 -3	; "hold_input"
	11	[121]	TEST     	1 0 0
	12	[121]	JMP      	4	; to 17
	13	[122]	SELF     	1 0 -4	; "onInput"
	14	[122]	GETTABLE 	3 0 -3	; "hold_input"
	15	[122]	CALL     	1 3 1
	16	[122]	JMP      	14	; to 31
	17	[123]	GETGLOBAL	1 -5	; type
	18	[123]	GETTABLE 	2 0 -6	; "hold_input_func"
	19	[123]	CALL     	1 2 2
	20	[123]	EQ       	0 1 -7	; - "function"
	21	[123]	JMP      	5	; to 27
	22	[124]	SELF     	1 0 -4	; "onInput"
	23	[124]	GETTABLE 	3 0 -6	; "hold_input_func"
	24	[124]	CALL     	3 1 0
	25	[124]	CALL     	1 0 1
	26	[124]	JMP      	4	; to 31
	27	[125]	GETTABLE 	1 0 -2	; "hold_callback"
	28	[125]	EQ       	0 1 -8	; - nil
	29	[125]	JMP      	1	; to 31
	30	[125]	RETURN   	0 1
	31	[126]	LOADBOOL 	1 1 0
	32	[126]	RETURN   	1 2
	33	[127]	RETURN   	0 1

function <./frontend/ui/widget/iconbutton.lua:129,133> (5 instructions, 20 bytes at 0x7fa5bbc09150)
1 param, 2 slots, 0 upvalues, 1 local, 3 constants, 0 functions
	1	[131]	GETTABLE 	1 0 -1	; "image"
	2	[131]	SETTABLE 	1 -2 -3	; "invert" true
	3	[132]	LOADBOOL 	1 1 0
	4	[132]	RETURN   	1 2
	5	[133]	RETURN   	0 1

function <./frontend/ui/widget/iconbutton.lua:135,138> (5 instructions, 20 bytes at 0x7fa5bbc08f60)
1 param, 2 slots, 0 upvalues, 1 local, 3 constants, 0 functions
	1	[136]	GETTABLE 	1 0 -1	; "image"
	2	[136]	SETTABLE 	1 -2 -3	; "invert" false
	3	[137]	LOADBOOL 	1 1 0
	4	[137]	RETURN   	1 2
	5	[138]	RETURN   	0 1

function <./frontend/ui/widget/iconbutton.lua:140,142> (3 instructions, 12 bytes at 0x7fa5bbc065f0)
1 param, 3 slots, 0 upvalues, 1 local, 1 constant, 0 functions
	1	[141]	SELF     	1 0 -1	; "onTapIconButton"
	2	[141]	CALL     	1 2 1
	3	[142]	RETURN   	0 1
