-- BYTECODE -- imagewidget.lua:35-39
0001    GGET     0   0      ; "math"
0002    TGETS    0   0   1  ; "min"
0003    UGET     1   0      ; Screen
0004    MOV      2   1
0005    TGETS    1   1   2  ; "getWidth"
0006    CALL     1   2   2
0007    UGET     2   0      ; Screen
0008    MOV      3   2
0009    TGETS    2   2   3  ; "getHeight"
0010    CALL     2   0   2
0011    CALLM    0   2   1
0012    DIVVN    0   0   0  ; 600
0013    UGET     1   0      ; Screen
0014    MOV      2   1
0015    TGETS    1   1   4  ; "getDPI"
0016    CALL     1   2   2
0017    DIVVN    1   1   1  ; 167
0018    GGET     2   0      ; "math"
0019    TGETS    2   2   5  ; "pow"
0020    KSHORT   3   2
0021    GGET     4   0      ; "math"
0022    TGETS    4   4   6  ; "max"
0023    KSHORT   5   0
0024    GGET     6   0      ; "math"
0025    TGETS    6   6   7  ; "log"
0026    ADDVV    7   0   1
0027    DIVVN    7   7   2  ; 2
0028    CALL     6   2   2
0029    DIVVN    6   6   3  ; 0.69
0030    CALL     4   0   3
0031    CALLMT   2   1

-- BYTECODE -- imagewidget.lua:52-57
0001    TGETS    1   0   0  ; "bb"
0002    TGETS    1   1   1  ; "free"
0003    ISF          1
0004    JMP      2 => 0014
0005    UGET     1   0      ; logger
0006    TGETS    1   1   2  ; "dbg"
0007    KSTR     2   3      ; "free image blitbuffer"
0008    TGETS    3   0   0  ; "bb"
0009    CALL     1   1   3
0010    TGETS    1   0   0  ; "bb"
0011    MOV      2   1
0012    TGETS    1   1   1  ; "free"
0013    CALL     1   1   2
0014 => RET0     0   1

-- BYTECODE -- imagewidget.lua:124-128
0001    TGETS    1   0   1  ; "image"
0002    TSETS    1   0   0  ; "_bb"
0003    TGETS    1   0   3  ; "image_disposable"
0004    TSETS    1   0   2  ; "_bb_disposable"
0005    RET0     0   1

-- BYTECODE -- imagewidget.lua:130-179
0001    GGET     1   0      ; "string"
0002    TGETS    1   1   1  ; "lower"
0003    GGET     2   0      ; "string"
0004    TGETS    2   2   2  ; "match"
0005    TGETS    3   0   3  ; "file"
0006    KSTR     4   4      ; ".+%.([^.]+)"
0007    CALL     2   2   3
0008    IST          2
0009    JMP      3 => 0011
0010    KSTR     2   5      ; ""
0011 => CALL     1   2   2
0012    ISEQS    1   6      ; "png"
0013    JMP      2 => 0024
0014    ISEQS    1   7      ; "jpg"
0015    JMP      2 => 0024
0016    ISEQS    1   8      ; "jpeg"
0017    JMP      2 => 0024
0018    ISEQS    1   9      ; "tiff"
0019    JMP      2 => 0024
0020    ISEQS    1  10      ; "tif"
0021    JMP      2 => 0024
0022    ISNES    1  11      ; "gif"
0023    JMP      2 => 0143
0024 => KNIL     2   3
0025    TGETS    4   0  12  ; "scale_factor"
0026    ISNEP    4   0
0027    JMP      4 => 0030
0028    TGETS    2   0  13  ; "width"
0029    TGETS    3   0  14  ; "height"
0030 => KSTR     4  15      ; "image|"
0031    TGETS    5   0   3  ; "file"
0032    KSTR     6  16      ; "|"
0033    ISTC     7   2
0034    JMP      7 => 0036
0035    KSTR     7   5      ; ""
0036 => KSTR     8  16      ; "|"
0037    ISTC     9   3
0038    JMP      9 => 0040
0039    KSTR     9   5      ; ""
0040 => CAT      4   4   9
0041    KPRI     5   1
0042    TGETS    6   0  17  ; "scale_for_dpi"
0043    ISF          6
0044    JMP      7 => 0057
0045    UGET     6   0      ; DPI_SCALE
0046    ISEQN    6   0      ; 1
0047    JMP      6 => 0057
0048    TGETS    6   0  12  ; "scale_factor"
0049    IST          6
0050    JMP      6 => 0057
0051    KPRI     5   2
0052    MOV      6   4
0053    KSTR     7  18      ; "|d"
0054    CAT      4   6   7
0055    KPRI     6   2
0056    TSETS    6   0  19  ; "already_scaled_for_dpi"
0057 => UGET     6   1      ; ImageCache
0058    MOV      7   6
0059    TGETS    6   6  20  ; "check"
0060    MOV      8   4
0061    CALL     6   2   3
0062    ISF          6
0063    JMP      7 => 0069
0064    TGETS    7   6  22  ; "bb"
0065    TSETS    7   0  21  ; "_bb"
0066    KPRI     7   1
0067    TSETS    7   0  23  ; "_bb_disposable"
0068    JMP      7 => 0146
0069 => UGET     7   2      ; RenderImage
0070    MOV      8   7
0071    TGETS    7   7  24  ; "renderImageFile"
0072    TGETS    9   0   3  ; "file"
0073    KPRI    10   1
0074    MOV     11   2
0075    MOV     12   3
0076    CALL     7   2   6
0077    TSETS    7   0  21  ; "_bb"
0078    ISF          5
0079    JMP      7 => 0104
0080    TGETS    7   0  21  ; "_bb"
0081    MOV      8   7
0082    TGETS    7   7  25  ; "getWidth"
0083    CALL     7   2   2
0084    TGETS    8   0  21  ; "_bb"
0085    MOV      9   8
0086    TGETS    8   8  26  ; "getHeight"
0087    CALL     8   2   2
0088    UGET     9   2      ; RenderImage
0089    MOV     10   9
0090    TGETS    9   9  27  ; "scaleBlitBuffer"
0091    TGETS   11   0  21  ; "_bb"
0092    GGET    12  28      ; "math"
0093    TGETS   12  12  29  ; "floor"
0094    UGET    13   0      ; DPI_SCALE
0095    MULVV   13   7  13
0096    CALL    12   2   2
0097    GGET    13  28      ; "math"
0098    TGETS   13  13  29  ; "floor"
0099    UGET    14   0      ; DPI_SCALE
0100    MULVV   14   8  14
0101    CALL    13   0   2
0102    CALLM    9   2   3
0103    TSETS    9   0  21  ; "_bb"
0104 => TGETS    7   0  30  ; "file_do_cache"
0105    IST          7
0106    JMP      7 => 0110
0107    KPRI     7   2
0108    TSETS    7   0  23  ; "_bb_disposable"
0109    JMP      7 => 0146
0110 => KPRI     7   1
0111    TSETS    7   0  23  ; "_bb_disposable"
0112    UGET     7   3      ; logger
0113    TGETS    7   7  31  ; "dbg"
0114    KSTR     8  32      ; "cache"
0115    MOV      9   4
0116    CALL     7   1   3
0117    UGET     7   4      ; ImageCacheItem
0118    MOV      8   7
0119    TGETS    7   7  33  ; "new"
0120    TDUP     9  34
0121    TGETS   10   0  21  ; "_bb"
0122    TSETS   10   9  22  ; "bb"
0123    CALL     7   2   3
0124    MOV      6   7
0125    TGETS    7   6  22  ; "bb"
0126    TGETS    7   7  36  ; "pitch"
0127    TGETS    8   6  22  ; "bb"
0128    TGETS    8   8  37  ; "h"
0129    MULVV    7   7   8
0130    TGETS    8   6  22  ; "bb"
0131    MOV      9   8
0132    TGETS    8   8  38  ; "getBytesPerPixel"
0133    CALL     8   2   2
0134    MULVV    7   7   8
0135    TSETS    7   6  35  ; "size"
0136    UGET     7   1      ; ImageCache
0137    MOV      8   7
0138    TGETS    7   7  39  ; "insert"
0139    MOV      9   4
0140    MOV     10   6
0141    CALL     7   1   4
0142    JMP      2 => 0146
0143 => GGET     2  40      ; "error"
0144    KSTR     3  41      ; "Image file type not supported."
0145    CALL     2   1   2
0146 => RET0     0   1

-- BYTECODE -- imagewidget.lua:181-291
0001    TGETS    1   0   0  ; "_bb"
0002    ISF          1
0003    JMP      2 => 0005
0004    RET0     0   1
0005 => UGET     1   0      ; logger
0006    TGETS    1   1   1  ; "dbg"
0007    KSTR     2   2      ; "ImageWidget: _render'ing"
0008    TGETS    3   0   3  ; "file"
0009    ISF          3
0010    JMP      4 => 0014
0011    TGETS    3   0   3  ; "file"
0012    IST          3
0013    JMP      4 => 0015
0014 => KSTR     3   4      ; "data"
0015 => TGETS    4   0   5  ; "width"
0016    TGETS    5   0   6  ; "height"
0017    CALL     1   1   5
0018    TGETS    1   0   7  ; "image"
0019    ISF          1
0020    JMP      2 => 0025
0021    MOV      2   0
0022    TGETS    1   0   8  ; "_loadimage"
0023    CALL     1   1   2
0024    JMP      1 => 0035
0025 => TGETS    1   0   3  ; "file"
0026    ISF          1
0027    JMP      2 => 0032
0028    MOV      2   0
0029    TGETS    1   0   9  ; "_loadfile"
0030    CALL     1   1   2
0031    JMP      1 => 0035
0032 => GGET     1  10      ; "error"
0033    KSTR     2  11      ; "cannot render image"
0034    CALL     1   1   2
0035 => TGETS    1   0  13  ; "scale_factor"
0036    TSETS    1   0  12  ; "_initial_scale_factor"
0037    TGETS    1   0  14  ; "rotation_angle"
0038    ISEQN    1   0      ; 0
0039    JMP      1 => 0074
0040    TGETS    1   0  15  ; "use_legacy_image_scaling"
0041    ISF          1
0042    JMP      2 => 0059
0043    TGETS    1   0  16  ; "_bb_disposable"
0044    IST          1
0045    JMP      1 => 0053
0046    TGETS    1   0   0  ; "_bb"
0047    MOV      2   1
0048    TGETS    1   1  17  ; "copy"
0049    CALL     1   2   2
0050    TSETS    1   0   0  ; "_bb"
0051    KPRI     1   2
0052    TSETS    1   0  16  ; "_bb_disposable"
0053 => TGETS    1   0   0  ; "_bb"
0054    MOV      2   1
0055    TGETS    1   1  18  ; "rotate"
0056    TGETS    3   0  14  ; "rotation_angle"
0057    CALL     1   1   3
0058    JMP      1 => 0074
0059 => TGETS    1   0   0  ; "_bb"
0060    MOV      2   1
0061    TGETS    1   1  19  ; "rotatedCopy"
0062    TGETS    3   0  14  ; "rotation_angle"
0063    CALL     1   2   3
0064    TGETS    2   0  16  ; "_bb_disposable"
0065    ISF          2
0066    JMP      3 => 0071
0067    TGETS    2   0   0  ; "_bb"
0068    MOV      3   2
0069    TGETS    2   2  20  ; "free"
0070    CALL     2   1   2
0071 => TSETS    1   0   0  ; "_bb"
0072    KPRI     2   2
0073    TSETS    2   0  16  ; "_bb_disposable"
0074 => TGETS    1   0   0  ; "_bb"
0075    MOV      2   1
0076    TGETS    1   1  21  ; "getWidth"
0077    CALL     1   2   2
0078    TGETS    2   0   0  ; "_bb"
0079    MOV      3   2
0080    TGETS    2   2  22  ; "getHeight"
0081    CALL     2   2   2
0082    TGETS    3   0  23  ; "scale_for_dpi"
0083    ISF          3
0084    JMP      4 => 0097
0085    TGETS    3   0  24  ; "already_scaled_for_dpi"
0086    IST          3
0087    JMP      3 => 0097
0088    TGETS    3   0  13  ; "scale_factor"
0089    ISNEP    3   0
0090    JMP      3 => 0093
0091    KSHORT   3   1
0092    TSETS    3   0  13  ; "scale_factor"
0093 => TGETS    3   0  13  ; "scale_factor"
0094    UGET     4   1      ; DPI_SCALE
0095    MULVV    3   3   4
0096    TSETS    3   0  13  ; "scale_factor"
0097 => TGETS    3   0  13  ; "scale_factor"
0098    ISNEN    3   0      ; 0
0099    JMP      3 => 0122
0100    TGETS    3   0   5  ; "width"
0101    ISF          3
0102    JMP      4 => 0120
0103    TGETS    3   0   6  ; "height"
0104    ISF          3
0105    JMP      4 => 0120
0106    GGET     3  25      ; "math"
0107    TGETS    3   3  26  ; "min"
0108    TGETS    4   0   5  ; "width"
0109    DIVVV    4   4   1
0110    TGETS    5   0   6  ; "height"
0111    DIVVV    5   5   2
0112    CALL     3   2   3
0113    TSETS    3   0  13  ; "scale_factor"
0114    UGET     3   0      ; logger
0115    TGETS    3   3   1  ; "dbg"
0116    KSTR     4  27      ; "ImageWidget: scale to fit, setting scale"~
0117    TGETS    5   0  13  ; "scale_factor"
0118    CALL     3   1   3
0119    JMP      3 => 0122
0120 => KSHORT   3   1
0121    TSETS    3   0  13  ; "scale_factor"
0122 => TGETS    3   0  13  ; "scale_factor"
0123    ISNEP    3   0
0124    JMP      3 => 0153
0125    TGETS    3   0   5  ; "width"
0126    ISF          3
0127    JMP      4 => 0174
0128    TGETS    3   0   6  ; "height"
0129    ISF          3
0130    JMP      4 => 0174
0131    TGETS    3   0   5  ; "width"
0132    ISNEV    3   1
0133    JMP      3 => 0137
0134    TGETS    3   0   6  ; "height"
0135    ISEQV    3   2
0136    JMP      3 => 0174
0137 => UGET     3   0      ; logger
0138    TGETS    3   3   1  ; "dbg"
0139    KSTR     4  28      ; "ImageWidget: stretching"
0140    CALL     3   1   2
0141    UGET     3   2      ; RenderImage
0142    MOV      4   3
0143    TGETS    3   3  29  ; "scaleBlitBuffer"
0144    TGETS    5   0   0  ; "_bb"
0145    TGETS    6   0   5  ; "width"
0146    TGETS    7   0   6  ; "height"
0147    TGETS    8   0  16  ; "_bb_disposable"
0148    CALL     3   2   6
0149    TSETS    3   0   0  ; "_bb"
0150    KPRI     3   2
0151    TSETS    3   0  16  ; "_bb_disposable"
0152    JMP      3 => 0174
0153 => TGETS    3   0  13  ; "scale_factor"
0154    ISEQN    3   1      ; 1
0155    JMP      3 => 0174
0156    UGET     3   0      ; logger
0157    TGETS    3   3   1  ; "dbg"
0158    KSTR     4  30      ; "ImageWidget: scaling by"
0159    TGETS    5   0  13  ; "scale_factor"
0160    CALL     3   1   3
0161    UGET     3   2      ; RenderImage
0162    MOV      4   3
0163    TGETS    3   3  29  ; "scaleBlitBuffer"
0164    TGETS    5   0   0  ; "_bb"
0165    TGETS    6   0  13  ; "scale_factor"
0166    MULVV    6   1   6
0167    TGETS    7   0  13  ; "scale_factor"
0168    MULVV    7   2   7
0169    TGETS    8   0  16  ; "_bb_disposable"
0170    CALL     3   2   6
0171    TSETS    3   0   0  ; "_bb"
0172    KPRI     3   2
0173    TSETS    3   0  16  ; "_bb_disposable"
0174 => TGETS    3   0   0  ; "_bb"
0175    MOV      4   3
0176    TGETS    3   3  21  ; "getWidth"
0177    CALL     3   2   2
0178    TGETS    4   0   0  ; "_bb"
0179    MOV      5   4
0180    TGETS    4   4  22  ; "getHeight"
0181    CALL     4   2   2
0182    MOV      2   4
0183    MOV      1   3
0184    TGETS    3   0   5  ; "width"
0185    ISF          3
0186    JMP      4 => 0258
0187    TGETS    3   0   6  ; "height"
0188    ISF          3
0189    JMP      4 => 0258
0190    TGETS    3   0   5  ; "width"
0191    ISGE     3   1
0192    JMP      3 => 0198
0193    TGETS    3   0   5  ; "width"
0194    DIVVN    3   3   2  ; 2
0195    DIVVV    3   3   1
0196    SUBNV    3   3   3  ; 0.5
0197    TSETS    3   0  31  ; "_max_off_center_x_ratio"
0198 => TGETS    3   0   6  ; "height"
0199    ISGE     3   2
0200    JMP      3 => 0206
0201    TGETS    3   0   6  ; "height"
0202    DIVVN    3   3   2  ; 2
0203    DIVVV    3   3   2
0204    SUBNV    3   3   3  ; 0.5
0205    TSETS    3   0  32  ; "_max_off_center_y_ratio"
0206 => TGETS    3   0  33  ; "center_x_ratio"
0207    TGETS    4   0  31  ; "_max_off_center_x_ratio"
0208    SUBNV    4   4   3  ; 0.5
0209    ISGE     3   4
0210    JMP      3 => 0215
0211    TGETS    3   0  31  ; "_max_off_center_x_ratio"
0212    SUBNV    3   3   3  ; 0.5
0213    TSETS    3   0  33  ; "center_x_ratio"
0214    JMP      3 => 0223
0215 => TGETS    3   0  33  ; "center_x_ratio"
0216    TGETS    4   0  31  ; "_max_off_center_x_ratio"
0217    ADDNV    4   4   3  ; 0.5
0218    ISGE     4   3
0219    JMP      3 => 0223
0220    TGETS    3   0  31  ; "_max_off_center_x_ratio"
0221    ADDNV    3   3   3  ; 0.5
0222    TSETS    3   0  33  ; "center_x_ratio"
0223 => TGETS    3   0  34  ; "center_y_ratio"
0224    TGETS    4   0  32  ; "_max_off_center_y_ratio"
0225    SUBNV    4   4   3  ; 0.5
0226    ISGE     3   4
0227    JMP      3 => 0232
0228    TGETS    3   0  32  ; "_max_off_center_y_ratio"
0229    SUBNV    3   3   3  ; 0.5
0230    TSETS    3   0  34  ; "center_y_ratio"
0231    JMP      3 => 0240
0232 => TGETS    3   0  34  ; "center_y_ratio"
0233    TGETS    4   0  32  ; "_max_off_center_y_ratio"
0234    ADDNV    4   4   3  ; 0.5
0235    ISGE     4   3
0236    JMP      3 => 0240
0237    TGETS    3   0  32  ; "_max_off_center_y_ratio"
0238    ADDNV    3   3   3  ; 0.5
0239    TSETS    3   0  34  ; "center_y_ratio"
0240 => TGETS    3   0  33  ; "center_x_ratio"
0241    MULVV    3   3   1
0242    TGETS    4   0   5  ; "width"
0243    DIVVN    4   4   2  ; 2
0244    SUBVV    3   3   4
0245    TSETS    3   0  35  ; "_offset_x"
0246    TGETS    3   0  34  ; "center_y_ratio"
0247    MULVV    3   3   2
0248    TGETS    4   0   6  ; "height"
0249    DIVVN    4   4   2  ; 2
0250    SUBVV    3   3   4
0251    TSETS    3   0  36  ; "_offset_y"
0252    UGET     3   0      ; logger
0253    TGETS    3   3   1  ; "dbg"
0254    KSTR     4  37      ; "ImageWidget: initial offsets"
0255    TGETS    5   0  35  ; "_offset_x"
0256    TGETS    6   0  36  ; "_offset_y"
0257    CALL     3   1   4
0258 => TSETS    1   0  38  ; "_bb_w"
0259    TSETS    2   0  39  ; "_bb_h"
0260    RET0     0   1

-- BYTECODE -- imagewidget.lua:293-303
0001    MOV      2   0
0002    TGETS    1   0   0  ; "_render"
0003    CALL     1   1   2
0004    TGETS    1   0   1  ; "width"
0005    ISF          1
0006    JMP      1 => 0010
0007    TGETS    1   0   2  ; "height"
0008    IST          1
0009    JMP      1 => 0025
0010 => UGET     1   0      ; Geom
0011    MOV      2   1
0012    TGETS    1   1   3  ; "new"
0013    TDUP     3   6
0014    TGETS    4   0   4  ; "_bb"
0015    MOV      5   4
0016    TGETS    4   4   5  ; "getWidth"
0017    CALL     4   2   2
0018    TSETS    4   3   7  ; "w"
0019    TGETS    4   0   4  ; "_bb"
0020    MOV      5   4
0021    TGETS    4   4   8  ; "getHeight"
0022    CALL     4   2   2
0023    TSETS    4   3   9  ; "h"
0024    CALLT    1   3
0025 => UGET     1   0      ; Geom
0026    MOV      2   1
0027    TGETS    1   1   3  ; "new"
0028    TDUP     3  10
0029    TGETS    4   0   1  ; "width"
0030    TSETS    4   3   7  ; "w"
0031    TGETS    4   0   2  ; "height"
0032    TSETS    4   3   9  ; "h"
0033    CALLT    1   3

-- BYTECODE -- imagewidget.lua:305-308
0001    TGETS    1   0   0  ; "scale_factor"
0002    RET1     1   2

-- BYTECODE -- imagewidget.lua:310-315
0001    TGETS    3   0   0  ; "_offset_x"
0002    ADDVV    3   1   3
0003    TGETS    4   0   1  ; "width"
0004    DIVVN    4   4   0  ; 2
0005    ADDVV    3   3   4
0006    TGETS    4   0   2  ; "_bb_w"
0007    DIVVV    3   3   4
0008    TGETS    4   0   3  ; "_offset_y"
0009    ADDVV    4   2   4
0010    TGETS    5   0   4  ; "height"
0011    DIVVN    5   5   0  ; 2
0012    ADDVV    4   4   5
0013    TGETS    5   0   5  ; "_bb_h"
0014    DIVVV    4   4   5
0015    MOV      5   3
0016    MOV      6   4
0017    RET      5   3

-- BYTECODE -- imagewidget.lua:340-342
0001    KSTR     0   0      ; "ui"
0002    UGET     1   0      ; self
0003    TGETS    1   1   1  ; "dimen"
0004    KPRI     2   2
0005    RET      0   4

-- BYTECODE -- imagewidget.lua:317-347
0001    TGETS    3   0   1  ; "_offset_x"
0002    ADDVV    3   1   3
0003    TGETS    4   0   2  ; "width"
0004    DIVVN    4   4   0  ; 2
0005    ADDVV    3   3   4
0006    TGETS    4   0   3  ; "_bb_w"
0007    DIVVV    3   3   4
0008    TSETS    3   0   0  ; "center_x_ratio"
0009    TGETS    3   0   5  ; "_offset_y"
0010    ADDVV    3   2   3
0011    TGETS    4   0   6  ; "height"
0012    DIVVN    4   4   0  ; 2
0013    ADDVV    3   3   4
0014    TGETS    4   0   7  ; "_bb_h"
0015    DIVVV    3   3   4
0016    TSETS    3   0   4  ; "center_y_ratio"
0017    TGETS    3   0   0  ; "center_x_ratio"
0018    TGETS    4   0   8  ; "_max_off_center_x_ratio"
0019    SUBNV    4   4   1  ; 0.5
0020    ISGE     3   4
0021    JMP      3 => 0026
0022    TGETS    3   0   8  ; "_max_off_center_x_ratio"
0023    SUBNV    3   3   1  ; 0.5
0024    TSETS    3   0   0  ; "center_x_ratio"
0025    JMP      3 => 0034
0026 => TGETS    3   0   0  ; "center_x_ratio"
0027    TGETS    4   0   8  ; "_max_off_center_x_ratio"
0028    ADDNV    4   4   1  ; 0.5
0029    ISGE     4   3
0030    JMP      3 => 0034
0031    TGETS    3   0   8  ; "_max_off_center_x_ratio"
0032    ADDNV    3   3   1  ; 0.5
0033    TSETS    3   0   0  ; "center_x_ratio"
0034 => TGETS    3   0   4  ; "center_y_ratio"
0035    TGETS    4   0   9  ; "_max_off_center_y_ratio"
0036    SUBNV    4   4   1  ; 0.5
0037    ISGE     3   4
0038    JMP      3 => 0043
0039    TGETS    3   0   9  ; "_max_off_center_y_ratio"
0040    SUBNV    3   3   1  ; 0.5
0041    TSETS    3   0   4  ; "center_y_ratio"
0042    JMP      3 => 0051
0043 => TGETS    3   0   4  ; "center_y_ratio"
0044    TGETS    4   0   9  ; "_max_off_center_y_ratio"
0045    ADDNV    4   4   1  ; 0.5
0046    ISGE     4   3
0047    JMP      3 => 0051
0048    TGETS    3   0   9  ; "_max_off_center_y_ratio"
0049    ADDNV    3   3   1  ; 0.5
0050    TSETS    3   0   4  ; "center_y_ratio"
0051 => TGETS    3   0   0  ; "center_x_ratio"
0052    TGETS    4   0   3  ; "_bb_w"
0053    MULVV    3   3   4
0054    TGETS    4   0   2  ; "width"
0055    DIVVN    4   4   0  ; 2
0056    SUBVV    3   3   4
0057    TGETS    4   0   4  ; "center_y_ratio"
0058    TGETS    5   0   7  ; "_bb_h"
0059    MULVV    4   4   5
0060    TGETS    5   0   6  ; "height"
0061    DIVVN    5   5   0  ; 2
0062    SUBVV    4   4   5
0063    TGETS    5   0   1  ; "_offset_x"
0064    ISNEV    3   5
0065    JMP      5 => 0069
0066    TGETS    5   0   5  ; "_offset_y"
0067    ISEQV    4   5
0068    JMP      5 => 0079
0069 => TSETS    3   0   1  ; "_offset_x"
0070    TSETS    4   0   5  ; "_offset_y"
0071    KPRI     5   2
0072    TSETS    5   0  10  ; "dithered"
0073    UGET     5   0      ; UIManager
0074    MOV      6   5
0075    TGETS    5   5  11  ; "setDirty"
0076    KSTR     7  12      ; "all"
0077    FNEW     8  13      ; imagewidget.lua:340
0078    CALL     5   1   4
0079 => TGETS    5   0   0  ; "center_x_ratio"
0080    TGETS    6   0   4  ; "center_y_ratio"
0081    UCLO     0 => 0082
0082 => RET      5   3

-- BYTECODE -- imagewidget.lua:349-398
0001    TGETS    4   0   0  ; "hide"
0002    ISF          4
0003    JMP      5 => 0005
0004    RET0     0   1
0005 => MOV      5   0
0006    TGETS    4   0   1  ; "getSize"
0007    CALL     4   2   2
0008    UGET     5   0      ; Geom
0009    MOV      6   5
0010    TGETS    5   5   3  ; "new"
0011    TDUP     7   4
0012    TSETS    2   7   5  ; "x"
0013    TSETS    3   7   6  ; "y"
0014    TGETS    8   4   7  ; "w"
0015    TSETS    8   7   7  ; "w"
0016    TGETS    8   4   8  ; "h"
0017    TSETS    8   7   8  ; "h"
0018    CALL     5   2   3
0019    TSETS    5   0   2  ; "dimen"
0020    UGET     5   1      ; logger
0021    TGETS    5   5   9  ; "dbg"
0022    KSTR     6  10      ; "blitFrom"
0023    MOV      7   2
0024    MOV      8   3
0025    TGETS    9   0  11  ; "_offset_x"
0026    TGETS   10   0  12  ; "_offset_y"
0027    TGETS   11   4   7  ; "w"
0028    TGETS   12   4   8  ; "h"
0029    CALL     5   1   8
0030    TGETS    5   0  13  ; "file"
0031    ISF          5
0032    JMP      6 => 0038
0033    UGET     5   2      ; util
0034    TGETS    5   5  14  ; "stringStartsWith"
0035    TGETS    6   0  13  ; "file"
0036    KSTR     7  15      ; "resources/"
0037    CALL     5   2   3
0038 => TGETS    6   0  16  ; "alpha"
0039    ISNEP    6   2
0040    JMP      6 => 0109
0041    TGETS    6   0  17  ; "_bb"
0042    MOV      7   6
0043    TGETS    6   6  18  ; "getType"
0044    CALL     6   2   2
0045    UGET     7   3      ; Blitbuffer
0046    TGETS    7   7  19  ; "TYPE_BB8A"
0047    ISEQV    6   7
0048    JMP      7 => 0053
0049    UGET     7   3      ; Blitbuffer
0050    TGETS    7   7  20  ; "TYPE_BBRGB32"
0051    ISNEV    6   7
0052    JMP      7 => 0081
0053 => UGET     7   4      ; Screen
0054    TGETS    7   7  21  ; "sw_dithering"
0055    ISF          7
0056    JMP      8 => 0070
0057    IST          5
0058    JMP      7 => 0070
0059    MOV      8   1
0060    TGETS    7   1  22  ; "ditherpmulalphablitFrom"
0061    TGETS    9   0  17  ; "_bb"
0062    MOV     10   2
0063    MOV     11   3
0064    TGETS   12   0  11  ; "_offset_x"
0065    TGETS   13   0  12  ; "_offset_y"
0066    TGETS   14   4   7  ; "w"
0067    TGETS   15   4   8  ; "h"
0068    CALL     7   1   9
0069    JMP      7 => 0136
0070 => MOV      8   1
0071    TGETS    7   1  23  ; "pmulalphablitFrom"
0072    TGETS    9   0  17  ; "_bb"
0073    MOV     10   2
0074    MOV     11   3
0075    TGETS   12   0  11  ; "_offset_x"
0076    TGETS   13   0  12  ; "_offset_y"
0077    TGETS   14   4   7  ; "w"
0078    TGETS   15   4   8  ; "h"
0079    CALL     7   1   9
0080    JMP      7 => 0136
0081 => UGET     7   4      ; Screen
0082    TGETS    7   7  21  ; "sw_dithering"
0083    ISF          7
0084    JMP      8 => 0098
0085    IST          5
0086    JMP      7 => 0098
0087    MOV      8   1
0088    TGETS    7   1  24  ; "ditherblitFrom"
0089    TGETS    9   0  17  ; "_bb"
0090    MOV     10   2
0091    MOV     11   3
0092    TGETS   12   0  11  ; "_offset_x"
0093    TGETS   13   0  12  ; "_offset_y"
0094    TGETS   14   4   7  ; "w"
0095    TGETS   15   4   8  ; "h"
0096    CALL     7   1   9
0097    JMP      7 => 0136
0098 => MOV      8   1
0099    TGETS    7   1  10  ; "blitFrom"
0100    TGETS    9   0  17  ; "_bb"
0101    MOV     10   2
0102    MOV     11   3
0103    TGETS   12   0  11  ; "_offset_x"
0104    TGETS   13   0  12  ; "_offset_y"
0105    TGETS   14   4   7  ; "w"
0106    TGETS   15   4   8  ; "h"
0107    CALL     7   1   9
0108    JMP      6 => 0136
0109 => UGET     6   4      ; Screen
0110    TGETS    6   6  21  ; "sw_dithering"
0111    ISF          6
0112    JMP      7 => 0126
0113    IST          5
0114    JMP      6 => 0126
0115    MOV      7   1
0116    TGETS    6   1  24  ; "ditherblitFrom"
0117    TGETS    8   0  17  ; "_bb"
0118    MOV      9   2
0119    MOV     10   3
0120    TGETS   11   0  11  ; "_offset_x"
0121    TGETS   12   0  12  ; "_offset_y"
0122    TGETS   13   4   7  ; "w"
0123    TGETS   14   4   8  ; "h"
0124    CALL     6   1   9
0125    JMP      6 => 0136
0126 => MOV      7   1
0127    TGETS    6   1  10  ; "blitFrom"
0128    TGETS    8   0  17  ; "_bb"
0129    MOV      9   2
0130    MOV     10   3
0131    TGETS   11   0  11  ; "_offset_x"
0132    TGETS   12   0  12  ; "_offset_y"
0133    TGETS   13   4   7  ; "w"
0134    TGETS   14   4   8  ; "h"
0135    CALL     6   1   9
0136 => TGETS    6   0  25  ; "invert"
0137    ISF          6
0138    JMP      7 => 0146
0139    MOV      7   1
0140    TGETS    6   1  26  ; "invertRect"
0141    MOV      8   2
0142    MOV      9   3
0143    TGETS   10   4   7  ; "w"
0144    TGETS   11   4   8  ; "h"
0145    CALL     6   1   6
0146 => TGETS    6   0  27  ; "dim"
0147    ISF          6
0148    JMP      7 => 0156
0149    MOV      7   1
0150    TGETS    6   1  28  ; "dimRect"
0151    MOV      8   2
0152    MOV      9   3
0153    TGETS   10   4   7  ; "w"
0154    TGETS   11   4   8  ; "h"
0155    CALL     6   1   6
0156 => UGET     6   4      ; Screen
0157    TGETS    6   6  29  ; "night_mode"
0158    ISF          6
0159    JMP      7 => 0169
0160    IST          5
0161    JMP      6 => 0169
0162    MOV      7   1
0163    TGETS    6   1  26  ; "invertRect"
0164    MOV      8   2
0165    MOV      9   3
0166    TGETS   10   4   7  ; "w"
0167    TGETS   11   4   8  ; "h"
0168    CALL     6   1   6
0169 => RET0     0   1

-- BYTECODE -- imagewidget.lua:404-413
0001    TGETS    1   0   0  ; "_bb"
0002    ISF          1
0003    JMP      2 => 0017
0004    TGETS    1   0   1  ; "_bb_disposable"
0005    ISF          1
0006    JMP      2 => 0017
0007    TGETS    1   0   0  ; "_bb"
0008    TGETS    1   1   2  ; "free"
0009    ISF          1
0010    JMP      2 => 0017
0011    TGETS    1   0   0  ; "_bb"
0012    MOV      2   1
0013    TGETS    1   1   2  ; "free"
0014    CALL     1   1   2
0015    KPRI     1   0
0016    TSETS    1   0   0  ; "_bb"
0017 => TGETS    1   0   4  ; "_initial_scale_factor"
0018    TSETS    1   0   3  ; "scale_factor"
0019    RET0     0   1

-- BYTECODE -- imagewidget.lua:415-418
0001    MOV      2   0
0002    TGETS    1   0   0  ; "free"
0003    CALL     1   1   2
0004    RET0     0   1

-- BYTECODE -- imagewidget.lua:0-421
0001    GGET     0   0      ; "require"
0002    KSTR     1   1      ; "ffi/blitbuffer"
0003    CALL     0   2   2
0004    GGET     1   0      ; "require"
0005    KSTR     2   2      ; "cache"
0006    CALL     1   2   2
0007    GGET     2   0      ; "require"
0008    KSTR     3   3      ; "cacheitem"
0009    CALL     2   2   2
0010    GGET     3   0      ; "require"
0011    KSTR     4   4      ; "ui/geometry"
0012    CALL     3   2   2
0013    GGET     4   0      ; "require"
0014    KSTR     5   5      ; "ui/renderimage"
0015    CALL     4   2   2
0016    GGET     5   0      ; "require"
0017    KSTR     6   6      ; "device"
0018    CALL     5   2   2
0019    TGETS    5   5   7  ; "screen"
0020    GGET     6   0      ; "require"
0021    KSTR     7   8      ; "ui/uimanager"
0022    CALL     6   2   2
0023    GGET     7   0      ; "require"
0024    KSTR     8   9      ; "ui/widget/widget"
0025    CALL     7   2   2
0026    GGET     8   0      ; "require"
0027    KSTR     9  10      ; "logger"
0028    CALL     8   2   2
0029    GGET     9   0      ; "require"
0030    KSTR    10  11      ; "util"
0031    CALL     9   2   2
0032    FNEW    10  12      ; imagewidget.lua:35
0033    MOV     11  10
0034    CALL    11   2   1
0035    MOV     13   1
0036    TGETS   12   1  13  ; "new"
0037    TDUP    14  14
0038    TNEW    15   0
0039    TSETS   15  14   2  ; "cache"
0040    TNEW    15   0
0041    TSETS   15  14  15  ; "cache_order"
0042    CALL    12   2   3
0043    MOV     14   2
0044    TGETS   13   2  13  ; "new"
0045    TNEW    15   0
0046    CALL    13   2   3
0047    FNEW    14  17      ; imagewidget.lua:52
0048    TSETS   14  13  16  ; "onFree"
0049    MOV     15   7
0050    TGETS   14   7  13  ; "new"
0051    TDUP    16  18
0052    GGET    17  19      ; "G_reader_settings"
0053    MOV     18  17
0054    TGETS   17  17  20  ; "isTrue"
0055    KSTR    19  21      ; "legacy_image_scaling"
0056    CALL    17   2   3
0057    TSETS   17  16  22  ; "use_legacy_image_scaling"
0058    CALL    14   2   3
0059    FNEW    15  24      ; imagewidget.lua:124
0060    TSETS   15  14  23  ; "_loadimage"
0061    FNEW    15  26      ; imagewidget.lua:130
0062    TSETS   15  14  25  ; "_loadfile"
0063    FNEW    15  28      ; imagewidget.lua:181
0064    TSETS   15  14  27  ; "_render"
0065    FNEW    15  30      ; imagewidget.lua:293
0066    TSETS   15  14  29  ; "getSize"
0067    FNEW    15  32      ; imagewidget.lua:305
0068    TSETS   15  14  31  ; "getScaleFactor"
0069    FNEW    15  34      ; imagewidget.lua:310
0070    TSETS   15  14  33  ; "getPanByCenterRatio"
0071    FNEW    15  36      ; imagewidget.lua:317
0072    TSETS   15  14  35  ; "panBy"
0073    FNEW    15  38      ; imagewidget.lua:349
0074    TSETS   15  14  37  ; "paintTo"
0075    FNEW    15  40      ; imagewidget.lua:404
0076    TSETS   15  14  39  ; "free"
0077    FNEW    15  42      ; imagewidget.lua:415
0078    TSETS   15  14  41  ; "onCloseWidget"
0079    UCLO     0 => 0080
0080 => RET1    14   2

