
main <./spec/unit/imagewidget_spec.lua:0,0> (5 instructions, 20 bytes at 0x7f92714068d0)
0+ params, 3 slots, 0 upvalues, 0 locals, 2 constants, 1 function
	1	[1]	GETGLOBAL	0 -1	; describe
	2	[1]	LOADK    	1 -2	; "ImageWidget module"
	3	[23]	CLOSURE  	2 0	; 0x7f9271406b70
	4	[1]	CALL     	0 3 1
	5	[23]	RETURN   	0 1

function <./spec/unit/imagewidget_spec.lua:1,23> (15 instructions, 60 bytes at 0x7f9271406b70)
0 params, 4 slots, 0 upvalues, 1 local, 4 constants, 3 functions
	1	[3]	GETGLOBAL	1 -1	; setup
	2	[6]	CLOSURE  	2 0	; 0x7f9271406da0
	3	[6]	MOVE     	0 0
	4	[3]	CALL     	1 2 1
	5	[8]	GETGLOBAL	1 -2	; it
	6	[8]	LOADK    	2 -3	; "should render without error"
	7	[14]	CLOSURE  	3 1	; 0x7f9271406c80
	8	[14]	MOVE     	0 0
	9	[8]	CALL     	1 3 1
	10	[15]	GETGLOBAL	1 -2	; it
	11	[15]	LOADK    	2 -4	; "should error out on none exist image"
	12	[22]	CLOSURE  	3 2	; 0x7f92714078e0
	13	[22]	MOVE     	0 0
	14	[15]	CALL     	1 3 1
	15	[23]	RETURN   	0 1

function <./spec/unit/imagewidget_spec.lua:3,6> (8 instructions, 32 bytes at 0x7f9271406da0)
0 params, 2 slots, 1 upvalue, 0 locals, 3 constants, 0 functions
	1	[4]	GETGLOBAL	0 -1	; require
	2	[4]	LOADK    	1 -2	; "commonrequire"
	3	[4]	CALL     	0 2 1
	4	[5]	GETGLOBAL	0 -1	; require
	5	[5]	LOADK    	1 -3	; "ui/widget/imagewidget"
	6	[5]	CALL     	0 2 2
	7	[5]	SETUPVAL 	0 0	; ImageWidget
	8	[6]	RETURN   	0 1

function <./spec/unit/imagewidget_spec.lua:8,14> (11 instructions, 44 bytes at 0x7f9271406c80)
0 params, 3 slots, 1 upvalue, 1 local, 6 constants, 0 functions
	1	[9]	GETUPVAL 	0 0	; ImageWidget
	2	[9]	SELF     	0 0 -1	; "new"
	3	[9]	NEWTABLE 	2 0 1
	4	[10]	SETTABLE 	2 -2 -3	; "file" "resources/icons/appbar.chevron.up.png"
	5	[9]	CALL     	0 3 2
	6	[12]	SELF     	1 0 -4	; "_render"
	7	[12]	CALL     	1 2 1
	8	[13]	GETGLOBAL	1 -5	; assert
	9	[13]	GETTABLE 	2 0 -6	; "_bb"
	10	[13]	CALL     	1 2 1
	11	[14]	RETURN   	0 1

function <./spec/unit/imagewidget_spec.lua:15,22> (11 instructions, 44 bytes at 0x7f92714078e0)
0 params, 3 slots, 1 upvalue, 1 local, 5 constants, 1 function
	1	[16]	GETUPVAL 	0 0	; ImageWidget
	2	[16]	SELF     	0 0 -1	; "new"
	3	[16]	NEWTABLE 	2 0 1
	4	[17]	SETTABLE 	2 -2 -3	; "file" "wtf.png"
	5	[16]	CALL     	0 3 2
	6	[19]	GETGLOBAL	1 -4	; assert
	7	[19]	GETTABLE 	1 1 -5	; "has_error"
	8	[21]	CLOSURE  	2 0	; 0x7f9271407ad0
	9	[21]	MOVE     	0 0
	10	[19]	CALL     	1 2 1
	11	[22]	RETURN   	0 1

function <./spec/unit/imagewidget_spec.lua:19,21> (4 instructions, 16 bytes at 0x7f9271407ad0)
0 params, 2 slots, 1 upvalue, 0 locals, 1 constant, 0 functions
	1	[20]	GETUPVAL 	0 0	; imgw
	2	[20]	SELF     	0 0 -1	; "_render"
	3	[20]	CALL     	0 2 1
	4	[21]	RETURN   	0 1
