-- BYTECODE -- imagewidget_spec.lua:3-6
0001    GGET     0   0      ; "require"
0002    KSTR     1   1      ; "commonrequire"
0003    CALL     0   1   2
0004    GGET     0   0      ; "require"
0005    KSTR     1   2      ; "ui/widget/imagewidget"
0006    CALL     0   2   2
0007    USETV    0   0      ; ImageWidget
0008    RET0     0   1

-- BYTECODE -- imagewidget_spec.lua:8-14
0001    UGET     0   0      ; ImageWidget
0002    MOV      1   0
0003    TGETS    0   0   0  ; "new"
0004    TDUP     2   1
0005    CALL     0   2   3
0006    MOV      2   0
0007    TGETS    1   0   2  ; "_render"
0008    CALL     1   1   2
0009    GGET     1   3      ; "assert"
0010    TGETS    2   0   4  ; "_bb"
0011    CALL     1   1   2
0012    RET0     0   1

-- BYTECODE -- imagewidget_spec.lua:19-21
0001    UGET     0   0      ; imgw
0002    MOV      1   0
0003    TGETS    0   0   0  ; "_render"
0004    CALL     0   1   2
0005    RET0     0   1

-- BYTECODE -- imagewidget_spec.lua:15-22
0001    UGET     0   0      ; ImageWidget
0002    MOV      1   0
0003    TGETS    0   0   0  ; "new"
0004    TDUP     2   1
0005    CALL     0   2   3
0006    GGET     1   2      ; "assert"
0007    TGETS    1   1   3  ; "has_error"
0008    FNEW     2   4      ; imagewidget_spec.lua:19
0009    CALL     1   1   2
0010    UCLO     0 => 0011
0011 => RET0     0   1

-- BYTECODE -- imagewidget_spec.lua:1-23
0001    KPRI     0   0
0002    GGET     1   0      ; "setup"
0003    FNEW     2   1      ; imagewidget_spec.lua:3
0004    CALL     1   1   2
0005    GGET     1   2      ; "it"
0006    KSTR     2   3      ; "should render without error"
0007    FNEW     3   4      ; imagewidget_spec.lua:8
0008    CALL     1   1   3
0009    GGET     1   2      ; "it"
0010    KSTR     2   5      ; "should error out on none exist image"
0011    FNEW     3   6      ; imagewidget_spec.lua:15
0012    CALL     1   1   3
0013    UCLO     0 => 0014
0014 => RET0     0   1

-- BYTECODE -- imagewidget_spec.lua:0-24
0001    GGET     0   0      ; "describe"
0002    KSTR     1   1      ; "ImageWidget module"
0003    FNEW     2   2      ; imagewidget_spec.lua:1
0004    CALL     0   1   3
0005    RET0     0   1

