
main <./frontend/ui/widget/imageviewer.lua:0,0> (200 instructions, 800 bytes at 0x7fce86c068d0)
0+ params, 30 slots, 0 upvalues, 25 locals, 92 constants, 19 functions
	1	[5]	GETGLOBAL	0 -1	; require
	2	[5]	LOADK    	1 -2	; "ui/bidi"
	3	[5]	CALL     	0 2 2
	4	[6]	GETGLOBAL	1 -1	; require
	5	[6]	LOADK    	2 -3	; "ffi/blitbuffer"
	6	[6]	CALL     	1 2 2
	7	[7]	GETGLOBAL	2 -1	; require
	8	[7]	LOADK    	3 -4	; "ui/widget/buttontable"
	9	[7]	CALL     	2 2 2
	10	[8]	GETGLOBAL	3 -1	; require
	11	[8]	LOADK    	4 -5	; "ui/widget/container/centercontainer"
	12	[8]	CALL     	3 2 2
	13	[9]	GETGLOBAL	4 -1	; require
	14	[9]	LOADK    	5 -6	; "ui/widget/closebutton"
	15	[9]	CALL     	4 2 2
	16	[10]	GETGLOBAL	5 -1	; require
	17	[10]	LOADK    	6 -7	; "device"
	18	[10]	CALL     	5 2 2
	19	[11]	GETGLOBAL	6 -1	; require
	20	[11]	LOADK    	7 -8	; "ui/geometry"
	21	[11]	CALL     	6 2 2
	22	[12]	GETGLOBAL	7 -1	; require
	23	[12]	LOADK    	8 -9	; "ui/gesturerange"
	24	[12]	CALL     	7 2 2
	25	[13]	GETGLOBAL	8 -1	; require
	26	[13]	LOADK    	9 -10	; "ui/font"
	27	[13]	CALL     	8 2 2
	28	[14]	GETGLOBAL	9 -1	; require
	29	[14]	LOADK    	10 -11	; "ui/widget/container/framecontainer"
	30	[14]	CALL     	9 2 2
	31	[15]	GETGLOBAL	10 -1	; require
	32	[15]	LOADK    	11 -12	; "ui/widget/imagewidget"
	33	[15]	CALL     	10 2 2
	34	[16]	GETGLOBAL	11 -1	; require
	35	[16]	LOADK    	12 -13	; "ui/widget/container/inputcontainer"
	36	[16]	CALL     	11 2 2
	37	[17]	GETGLOBAL	12 -1	; require
	38	[17]	LOADK    	13 -14	; "ui/widget/linewidget"
	39	[17]	CALL     	12 2 2
	40	[18]	GETGLOBAL	13 -1	; require
	41	[18]	LOADK    	14 -15	; "ui/widget/overlapgroup"
	42	[18]	CALL     	13 2 2
	43	[19]	GETGLOBAL	14 -1	; require
	44	[19]	LOADK    	15 -16	; "ui/widget/progresswidget"
	45	[19]	CALL     	14 2 2
	46	[20]	GETGLOBAL	15 -1	; require
	47	[20]	LOADK    	16 -17	; "ui/size"
	48	[20]	CALL     	15 2 2
	49	[21]	GETGLOBAL	16 -1	; require
	50	[21]	LOADK    	17 -18	; "ui/widget/textboxwidget"
	51	[21]	CALL     	16 2 2
	52	[22]	GETGLOBAL	17 -1	; require
	53	[22]	LOADK    	18 -19	; "ui/widget/textwidget"
	54	[22]	CALL     	17 2 2
	55	[23]	GETGLOBAL	18 -1	; require
	56	[23]	LOADK    	19 -20	; "ui/widget/verticalgroup"
	57	[23]	CALL     	18 2 2
	58	[24]	GETGLOBAL	19 -1	; require
	59	[24]	LOADK    	20 -21	; "ui/widget/container/widgetcontainer"
	60	[24]	CALL     	19 2 2
	61	[25]	GETGLOBAL	20 -1	; require
	62	[25]	LOADK    	21 -22	; "ui/uimanager"
	63	[25]	CALL     	20 2 2
	64	[26]	GETGLOBAL	21 -1	; require
	65	[26]	LOADK    	22 -23	; "logger"
	66	[26]	CALL     	21 2 2
	67	[27]	GETGLOBAL	22 -1	; require
	68	[27]	LOADK    	23 -24	; "gettext"
	69	[27]	CALL     	22 2 2
	70	[28]	GETTABLE 	23 5 -25	; "screen"
	71	[30]	SELF     	24 11 -26	; "new"
	72	[30]	NEWTABLE 	26 0 23
	73	[33]	SETTABLE 	26 -27 -28	; "file" nil
	74	[35]	SETTABLE 	26 -29 -28	; "image" nil
	75	[38]	SETTABLE 	26 -30 -31	; "image_disposable" true
	76	[49]	SETTABLE 	26 -32 -31	; "images_keep_pan_and_zoom" true
	77	[51]	SETTABLE 	26 -33 -34	; "fullscreen" false
	78	[52]	SETTABLE 	26 -35 -31	; "with_title_bar" true
	79	[53]	MOVE     	27 22
	80	[53]	LOADK    	28 -37	; "Viewing image"
	81	[53]	CALL     	27 2 2
	82	[53]	SETTABLE 	26 -36 27	; "title_text" -
	83	[55]	SETTABLE 	26 -38 -28	; "caption" nil
	84	[56]	SETTABLE 	26 -39 -31	; "caption_visible" true
	85	[57]	SETTABLE 	26 -40 -28	; "caption_tap_area" nil
	86	[59]	SETTABLE 	26 -41 -34	; "buttons_visible" false
	87	[61]	SETTABLE 	26 -42 -28	; "width" nil
	88	[62]	SETTABLE 	26 -43 -28	; "height" nil
	89	[63]	SETTABLE 	26 -44 -45	; "scale_factor" 0
	90	[64]	SETTABLE 	26 -46 -34	; "rotated" false
	91	[66]	SELF     	27 8 -48	; "getFace"
	92	[66]	LOADK    	29 -49	; "x_smalltfont"
	93	[66]	CALL     	27 3 2
	94	[66]	SETTABLE 	26 -47 27	; "title_face" -
	95	[67]	GETTABLE 	27 15 -51	; "padding"
	96	[67]	GETTABLE 	27 27 -52	; "default"
	97	[67]	SETTABLE 	26 -50 27	; "title_padding" -
	98	[68]	GETTABLE 	27 15 -54	; "margin"
	99	[68]	GETTABLE 	27 27 -55	; "title"
	100	[68]	SETTABLE 	26 -53 27	; "title_margin" -
	101	[69]	SELF     	27 8 -48	; "getFace"
	102	[69]	LOADK    	29 -57	; "xx_smallinfofont"
	103	[69]	CALL     	27 3 2
	104	[69]	SETTABLE 	26 -56 27	; "caption_face" -
	105	[70]	GETTABLE 	27 15 -51	; "padding"
	106	[70]	GETTABLE 	27 27 -59	; "large"
	107	[70]	SETTABLE 	26 -58 27	; "caption_padding" -
	108	[71]	GETTABLE 	27 15 -54	; "margin"
	109	[71]	GETTABLE 	27 27 -61	; "small"
	110	[71]	SETTABLE 	26 -60 27	; "image_padding" -
	111	[72]	GETTABLE 	27 15 -51	; "padding"
	112	[72]	GETTABLE 	27 27 -52	; "default"
	113	[72]	SETTABLE 	26 -62 27	; "button_padding" -
	114	[75]	SELF     	27 23 -64	; "scaleBySize"
	115	[75]	LOADK    	29 -65	; 5
	116	[75]	CALL     	27 3 2
	117	[75]	SETTABLE 	26 -63 27	; "pan_threshold" -
	118	[77]	SETTABLE 	26 -66 -28	; "_scale_to_fit" nil
	119	[78]	SETTABLE 	26 -67 -34	; "_panning" false
	120	[80]	SETTABLE 	26 -68 -69	; "_center_x_ratio" 0.5
	121	[81]	SETTABLE 	26 -70 -69	; "_center_y_ratio" 0.5
	122	[84]	SETTABLE 	26 -71 -28	; "_image_wg" nil
	123	[85]	SETTABLE 	26 -72 -28	; "_images_list" nil
	124	[86]	SETTABLE 	26 -73 -28	; "_images_list_disposable" nil
	125	[30]	CALL     	24 3 2
	126	[140]	CLOSURE  	25 0	; 0x7fce86c07da0
	127	[140]	MOVE     	0 5
	128	[140]	MOVE     	0 6
	129	[140]	MOVE     	0 23
	130	[140]	MOVE     	0 7
	131	[90]	SETTABLE 	24 -74 25	; "init" -
	132	[150]	CLOSURE  	25 1	; 0x7fce86c08400
	133	[150]	MOVE     	0 21
	134	[142]	SETTABLE 	24 -75 25	; "_clean_image_wg" -
	135	[422]	CLOSURE  	25 2	; 0x7fce86c077e0
	136	[422]	MOVE     	0 6
	137	[422]	MOVE     	0 23
	138	[422]	MOVE     	0 22
	139	[422]	MOVE     	0 20
	140	[422]	MOVE     	0 2
	141	[422]	MOVE     	0 3
	142	[422]	MOVE     	0 9
	143	[422]	MOVE     	0 15
	144	[422]	MOVE     	0 17
	145	[422]	MOVE     	0 4
	146	[422]	MOVE     	0 16
	147	[422]	MOVE     	0 13
	148	[422]	MOVE     	0 18
	149	[422]	MOVE     	0 12
	150	[422]	MOVE     	0 14
	151	[422]	MOVE     	0 10
	152	[422]	MOVE     	0 1
	153	[422]	MOVE     	0 19
	154	[422]	MOVE     	0 21
	155	[152]	SETTABLE 	24 -76 25	; "update" -
	156	[430]	CLOSURE  	25 3	; 0x7fce86d04bb0
	157	[430]	MOVE     	0 20
	158	[424]	SETTABLE 	24 -77 25	; "onShow" -
	159	[449]	CLOSURE  	25 4	; 0x7fce86d052a0
	160	[449]	MOVE     	0 21
	161	[432]	SETTABLE 	24 -78 25	; "switchToImageNum" -
	162	[489]	CLOSURE  	25 5	; 0x7fce86d05830
	163	[489]	MOVE     	0 23
	164	[489]	MOVE     	0 0
	165	[451]	SETTABLE 	24 -79 25	; "onTap" -
	166	[497]	CLOSURE  	25 6	; 0x7fce86d05e90
	167	[491]	SETTABLE 	24 -80 25	; "panBy" -
	168	[542]	CLOSURE  	25 7	; 0x7fce86d06650
	169	[542]	MOVE     	0 23
	170	[500]	SETTABLE 	24 -81 25	; "onSwipe" -
	171	[550]	CLOSURE  	25 8	; 0x7fce86d06b90
	172	[544]	SETTABLE 	24 -82 25	; "onHold" -
	173	[567]	CLOSURE  	25 9	; 0x7fce86d078f0
	174	[567]	MOVE     	0 20
	175	[552]	SETTABLE 	24 -83 25	; "onHoldRelease" -
	176	[574]	CLOSURE  	25 10	; 0x7fce86d07c00
	177	[569]	SETTABLE 	24 -84 25	; "onPan" -
	178	[582]	CLOSURE  	25 11	; 0x7fce86d07f60
	179	[576]	SETTABLE 	24 -85 25	; "onPanRelease" -
	180	[596]	CLOSURE  	25 12	; 0x7fce86d083e0
	181	[585]	SETTABLE 	24 -86 25	; "onZoomIn" -
	182	[609]	CLOSURE  	25 13	; 0x7fce86d089a0
	183	[598]	SETTABLE 	24 -87 25	; "onZoomOut" -
	184	[622]	CLOSURE  	25 14	; 0x7fce86d08ed0
	185	[622]	MOVE     	0 23
	186	[611]	SETTABLE 	24 -88 25	; "onSpread" -
	187	[630]	CLOSURE  	25 15	; 0x7fce86d09290
	188	[630]	MOVE     	0 23
	189	[624]	SETTABLE 	24 -89 25	; "onPinch" -
	190	[635]	CLOSURE  	25 16	; 0x7fce86d09620
	191	[635]	MOVE     	0 20
	192	[632]	SETTABLE 	24 -90 25	; "onClose" -
	193	[640]	CLOSURE  	25 17	; 0x7fce86d075b0
	194	[637]	SETTABLE 	24 -91 25	; "onAnyKeyPressed" -
	195	[659]	CLOSURE  	25 18	; 0x7fce86d09eb0
	196	[659]	MOVE     	0 21
	197	[659]	MOVE     	0 20
	198	[642]	SETTABLE 	24 -92 25	; "onCloseWidget" -
	199	[661]	RETURN   	24 2
	200	[661]	RETURN   	0 1

function <./frontend/ui/widget/imageviewer.lua:90,140> (163 instructions, 652 bytes at 0x7fce86c07da0)
1 param, 7 slots, 4 upvalues, 2 locals, 58 constants, 0 functions
	1	[91]	GETUPVAL 	1 0	; Device
	2	[91]	SELF     	1 1 -1	; "hasKeys"
	3	[91]	CALL     	1 2 2
	4	[91]	TEST     	1 0 0
	5	[91]	JMP      	29	; to 35
	6	[92]	NEWTABLE 	1 0 3
	7	[93]	NEWTABLE 	2 1 1
	8	[93]	NEWTABLE 	3 1 0
	9	[93]	LOADK    	4 -4	; "Back"
	10	[93]	SETLIST  	3 1 1	; 1
	11	[93]	SETTABLE 	2 -5 -6	; "doc" "close viewer"
	12	[93]	SETLIST  	2 1 1	; 1
	13	[93]	SETTABLE 	1 -3 2	; "Close" -
	14	[94]	NEWTABLE 	2 1 1
	15	[94]	NEWTABLE 	3 1 0
	16	[94]	GETUPVAL 	4 0	; Device
	17	[94]	GETTABLE 	4 4 -8	; "input"
	18	[94]	GETTABLE 	4 4 -9	; "group"
	19	[94]	GETTABLE 	4 4 -10	; "PgBack"
	20	[94]	SETLIST  	3 1 1	; 1
	21	[94]	SETTABLE 	2 -5 -11	; "doc" "Zoom In"
	22	[94]	SETLIST  	2 1 1	; 1
	23	[94]	SETTABLE 	1 -7 2	; "ZoomIn" -
	24	[95]	NEWTABLE 	2 1 1
	25	[95]	NEWTABLE 	3 1 0
	26	[95]	GETUPVAL 	4 0	; Device
	27	[95]	GETTABLE 	4 4 -8	; "input"
	28	[95]	GETTABLE 	4 4 -9	; "group"
	29	[95]	GETTABLE 	4 4 -13	; "PgFwd"
	30	[95]	SETLIST  	3 1 1	; 1
	31	[95]	SETTABLE 	2 -5 -14	; "doc" "Zoom out"
	32	[95]	SETLIST  	2 1 1	; 1
	33	[95]	SETTABLE 	1 -12 2	; "ZoomOut" -
	34	[96]	SETTABLE 	0 -2 1	; "key_events" -
	35	[98]	GETUPVAL 	1 0	; Device
	36	[98]	SELF     	1 1 -15	; "isTouchDevice"
	37	[98]	CALL     	1 2 2
	38	[98]	TEST     	1 0 0
	39	[98]	JMP      	88	; to 128
	40	[99]	GETUPVAL 	1 1	; Geom
	41	[99]	SELF     	1 1 -16	; "new"
	42	[99]	NEWTABLE 	3 0 4
	43	[100]	SETTABLE 	3 -17 -18	; "x" 0
	44	[100]	SETTABLE 	3 -19 -18	; "y" 0
	45	[101]	GETUPVAL 	4 2	; Screen
	46	[101]	SELF     	4 4 -21	; "getWidth"
	47	[101]	CALL     	4 2 2
	48	[101]	SETTABLE 	3 -20 4	; "w" -
	49	[102]	GETUPVAL 	4 2	; Screen
	50	[102]	SELF     	4 4 -23	; "getHeight"
	51	[102]	CALL     	4 2 2
	52	[102]	SETTABLE 	3 -22 4	; "h" -
	53	[99]	CALL     	1 3 2
	54	[104]	NEWTABLE 	2 0 8
	55	[105]	NEWTABLE 	3 0 0
	56	[105]	GETUPVAL 	4 3	; GestureRange
	57	[105]	SELF     	4 4 -16	; "new"
	58	[105]	NEWTABLE 	6 0 2
	59	[105]	SETTABLE 	6 -26 -27	; "ges" "tap"
	60	[105]	SETTABLE 	6 -28 1	; "range" -
	61	[105]	CALL     	4 3 0
	62	[105]	SETLIST  	3 0 1	; 1
	63	[105]	SETTABLE 	2 -25 3	; "Tap" -
	64	[108]	NEWTABLE 	3 0 0
	65	[108]	GETUPVAL 	4 3	; GestureRange
	66	[108]	SELF     	4 4 -16	; "new"
	67	[108]	NEWTABLE 	6 0 2
	68	[108]	SETTABLE 	6 -26 -30	; "ges" "spread"
	69	[108]	SETTABLE 	6 -28 1	; "range" -
	70	[108]	CALL     	4 3 0
	71	[108]	SETLIST  	3 0 1	; 1
	72	[108]	SETTABLE 	2 -29 3	; "Spread" -
	73	[109]	NEWTABLE 	3 0 0
	74	[109]	GETUPVAL 	4 3	; GestureRange
	75	[109]	SELF     	4 4 -16	; "new"
	76	[109]	NEWTABLE 	6 0 2
	77	[109]	SETTABLE 	6 -26 -32	; "ges" "pinch"
	78	[109]	SETTABLE 	6 -28 1	; "range" -
	79	[109]	CALL     	4 3 0
	80	[109]	SETLIST  	3 0 1	; 1
	81	[109]	SETTABLE 	2 -31 3	; "Pinch" -
	82	[114]	NEWTABLE 	3 0 0
	83	[114]	GETUPVAL 	4 3	; GestureRange
	84	[114]	SELF     	4 4 -16	; "new"
	85	[114]	NEWTABLE 	6 0 2
	86	[114]	SETTABLE 	6 -26 -34	; "ges" "hold"
	87	[114]	SETTABLE 	6 -28 1	; "range" -
	88	[114]	CALL     	4 3 0
	89	[114]	SETLIST  	3 0 1	; 1
	90	[114]	SETTABLE 	2 -33 3	; "Hold" -
	91	[115]	NEWTABLE 	3 0 0
	92	[115]	GETUPVAL 	4 3	; GestureRange
	93	[115]	SELF     	4 4 -16	; "new"
	94	[115]	NEWTABLE 	6 0 2
	95	[115]	SETTABLE 	6 -26 -36	; "ges" "hold_release"
	96	[115]	SETTABLE 	6 -28 1	; "range" -
	97	[115]	CALL     	4 3 0
	98	[115]	SETLIST  	3 0 1	; 1
	99	[115]	SETTABLE 	2 -35 3	; "HoldRelease" -
	100	[116]	NEWTABLE 	3 0 0
	101	[116]	GETUPVAL 	4 3	; GestureRange
	102	[116]	SELF     	4 4 -16	; "new"
	103	[116]	NEWTABLE 	6 0 2
	104	[116]	SETTABLE 	6 -26 -38	; "ges" "pan"
	105	[116]	SETTABLE 	6 -28 1	; "range" -
	106	[116]	CALL     	4 3 0
	107	[116]	SETLIST  	3 0 1	; 1
	108	[116]	SETTABLE 	2 -37 3	; "Pan" -
	109	[117]	NEWTABLE 	3 0 0
	110	[117]	GETUPVAL 	4 3	; GestureRange
	111	[117]	SELF     	4 4 -16	; "new"
	112	[117]	NEWTABLE 	6 0 2
	113	[117]	SETTABLE 	6 -26 -40	; "ges" "pan_release"
	114	[117]	SETTABLE 	6 -28 1	; "range" -
	115	[117]	CALL     	4 3 0
	116	[117]	SETLIST  	3 0 1	; 1
	117	[117]	SETTABLE 	2 -39 3	; "PanRelease" -
	118	[118]	NEWTABLE 	3 0 0
	119	[118]	GETUPVAL 	4 3	; GestureRange
	120	[118]	SELF     	4 4 -16	; "new"
	121	[118]	NEWTABLE 	6 0 2
	122	[118]	SETTABLE 	6 -26 -42	; "ges" "swipe"
	123	[118]	SETTABLE 	6 -28 1	; "range" -
	124	[118]	CALL     	4 3 0
	125	[118]	SETLIST  	3 0 1	; 1
	126	[118]	SETTABLE 	2 -41 3	; "Swipe" -
	127	[119]	SETTABLE 	0 -24 2	; "ges_events" -
	128	[121]	GETTABLE 	1 0 -43	; "fullscreen"
	129	[121]	TEST     	1 0 0
	130	[121]	JMP      	1	; to 132
	131	[122]	SETTABLE 	0 -44 -45	; "covers_fullscreen" true
	132	[126]	GETGLOBAL	1 -46	; type
	133	[126]	GETTABLE 	2 0 -47	; "image"
	134	[126]	CALL     	1 2 2
	135	[126]	EQ       	0 1 -48	; - "table"
	136	[126]	JMP      	24	; to 161
	137	[127]	GETTABLE 	1 0 -47	; "image"
	138	[127]	SETTABLE 	0 -49 1	; "_images_list" -
	139	[128]	GETTABLE 	1 0 -49	; "_images_list"
	140	[128]	GETTABLE 	1 1 -50	; 1
	141	[128]	SETTABLE 	0 -47 1	; "image" -
	142	[129]	GETGLOBAL	1 -46	; type
	143	[129]	GETTABLE 	2 0 -47	; "image"
	144	[129]	CALL     	1 2 2
	145	[129]	EQ       	0 1 -51	; - "function"
	146	[129]	JMP      	3	; to 150
	147	[130]	GETTABLE 	1 0 -47	; "image"
	148	[130]	CALL     	1 1 2
	149	[130]	SETTABLE 	0 -47 1	; "image" -
	150	[132]	SETTABLE 	0 -52 -50	; "_images_list_cur" 1
	151	[133]	GETTABLE 	1 0 -49	; "_images_list"
	152	[133]	LEN      	1 1
	153	[133]	SETTABLE 	0 -53 1	; "_images_list_nb" -
	154	[134]	GETTABLE 	1 0 -55	; "scale_factor"
	155	[134]	SETTABLE 	0 -54 1	; "_images_orig_scale_factor" -
	156	[136]	GETTABLE 	1 0 -57	; "image_disposable"
	157	[136]	SETTABLE 	0 -56 1	; "_images_list_disposable" -
	158	[137]	GETTABLE 	1 0 -49	; "_images_list"
	159	[137]	GETTABLE 	1 1 -57	; "image_disposable"
	160	[137]	SETTABLE 	0 -57 1	; "image_disposable" -
	161	[139]	SELF     	1 0 -58	; "update"
	162	[139]	CALL     	1 2 1
	163	[140]	RETURN   	0 1

function <./frontend/ui/widget/imageviewer.lua:142,150> (12 instructions, 48 bytes at 0x7fce86c08400)
1 param, 3 slots, 1 upvalue, 1 local, 5 constants, 0 functions
	1	[145]	GETTABLE 	1 0 -1	; "_image_wg"
	2	[145]	TEST     	1 0 0
	3	[145]	JMP      	8	; to 12
	4	[146]	GETUPVAL 	1 0	; logger
	5	[146]	GETTABLE 	1 1 -2	; "dbg"
	6	[146]	LOADK    	2 -3	; "ImageViewer:_clean_image_wg()"
	7	[146]	CALL     	1 2 1
	8	[147]	GETTABLE 	1 0 -1	; "_image_wg"
	9	[147]	SELF     	1 1 -4	; "free"
	10	[147]	CALL     	1 2 1
	11	[148]	SETTABLE 	0 -1 -5	; "_image_wg" nil
	12	[150]	RETURN   	0 1

function <./frontend/ui/widget/imageviewer.lua:152,422> (581 instructions, 2324 bytes at 0x7fce86c077e0)
1 param, 20 slots, 19 upvalues, 27 locals, 102 constants, 4 functions
	1	[153]	SELF     	1 0 -1	; "_clean_image_wg"
	2	[153]	CALL     	1 2 1
	3	[154]	GETTABLE 	1 0 -2	; "_scale_to_fit"
	4	[154]	EQ       	0 1 -3	; - nil
	5	[154]	JMP      	8	; to 14
	6	[155]	GETTABLE 	1 0 -4	; "scale_factor"
	7	[155]	EQ       	0 1 -5	; - 0
	8	[155]	JMP      	3	; to 12
	9	[155]	LOADBOOL 	1 1 0
	10	[155]	TEST     	1 0 1
	11	[155]	JMP      	1	; to 13
	12	[155]	LOADBOOL 	1 0 0
	13	[155]	SETTABLE 	0 -2 1	; "_scale_to_fit" -
	14	[157]	GETTABLE 	1 0 -6	; "main_frame"
	15	[157]	TEST     	1 0 0
	16	[157]	JMP      	4	; to 21
	17	[157]	GETTABLE 	1 0 -6	; "main_frame"
	18	[157]	GETTABLE 	1 1 -7	; "dimen"
	19	[157]	TEST     	1 0 1
	20	[157]	JMP      	4	; to 25
	21	[157]	GETUPVAL 	1 0	; Geom
	22	[157]	SELF     	1 1 -8	; "new"
	23	[157]	NEWTABLE 	3 0 0
	24	[157]	CALL     	1 3 2
	25	[158]	SETTABLE 	0 -9 -10	; "align" "center"
	26	[159]	GETUPVAL 	2 0	; Geom
	27	[159]	SELF     	2 2 -8	; "new"
	28	[159]	NEWTABLE 	4 0 4
	29	[160]	SETTABLE 	4 -12 -5	; "x" 0
	30	[160]	SETTABLE 	4 -13 -5	; "y" 0
	31	[161]	GETUPVAL 	5 1	; Screen
	32	[161]	SELF     	5 5 -15	; "getWidth"
	33	[161]	CALL     	5 2 2
	34	[161]	SETTABLE 	4 -14 5	; "w" -
	35	[162]	GETUPVAL 	5 1	; Screen
	36	[162]	SELF     	5 5 -17	; "getHeight"
	37	[162]	CALL     	5 2 2
	38	[162]	SETTABLE 	4 -16 5	; "h" -
	39	[159]	CALL     	2 3 2
	40	[163]	SETTABLE 	0 -11 2	; "region" -
	41	[164]	GETTABLE 	2 0 -18	; "fullscreen"
	42	[164]	TEST     	2 0 0
	43	[164]	JMP      	9	; to 53
	44	[165]	GETUPVAL 	2 1	; Screen
	45	[165]	SELF     	2 2 -17	; "getHeight"
	46	[165]	CALL     	2 2 2
	47	[165]	SETTABLE 	0 -19 2	; "height" -
	48	[166]	GETUPVAL 	2 1	; Screen
	49	[166]	SELF     	2 2 -15	; "getWidth"
	50	[166]	CALL     	2 2 2
	51	[166]	SETTABLE 	0 -20 2	; "width" -
	52	[166]	JMP      	18	; to 71
	53	[168]	GETUPVAL 	2 1	; Screen
	54	[168]	SELF     	2 2 -17	; "getHeight"
	55	[168]	CALL     	2 2 2
	56	[168]	GETUPVAL 	3 1	; Screen
	57	[168]	SELF     	3 3 -21	; "scaleBySize"
	58	[168]	LOADK    	5 -22	; 40
	59	[168]	CALL     	3 3 2
	60	[168]	SUB      	2 2 3
	61	[168]	SETTABLE 	0 -19 2	; "height" -
	62	[169]	GETUPVAL 	2 1	; Screen
	63	[169]	SELF     	2 2 -15	; "getWidth"
	64	[169]	CALL     	2 2 2
	65	[169]	GETUPVAL 	3 1	; Screen
	66	[169]	SELF     	3 3 -21	; "scaleBySize"
	67	[169]	LOADK    	5 -22	; 40
	68	[169]	CALL     	3 3 2
	69	[169]	SUB      	2 2 3
	70	[169]	SETTABLE 	0 -20 2	; "width" -
	71	[172]	LOADK    	2 -5	; 0
	72	[173]	LOADNIL  	3 3
	73	[174]	GETTABLE 	4 0 -23	; "buttons_visible"
	74	[174]	TEST     	4 0 0
	75	[174]	JMP      	80	; to 156
	76	[175]	NEWTABLE 	4 1 0
	77	[175]	NEWTABLE 	5 3 0
	78	[176]	NEWTABLE 	6 0 2
	79	[178]	GETTABLE 	7 0 -2	; "_scale_to_fit"
	80	[178]	TEST     	7 0 0
	81	[178]	JMP      	5	; to 87
	82	[178]	GETUPVAL 	7 2	; _
	83	[178]	LOADK    	8 -25	; "Original size"
	84	[178]	CALL     	7 2 2
	85	[178]	TEST     	7 0 1
	86	[178]	JMP      	3	; to 90
	87	[178]	GETUPVAL 	7 2	; _
	88	[178]	LOADK    	8 -26	; "Scale"
	89	[178]	CALL     	7 2 2
	90	[178]	SETTABLE 	6 -24 7	; "text" -
	91	[186]	CLOSURE  	7 0	; 0x7fce86c08c90
	92	[186]	MOVE     	0 0
	93	[186]	SETTABLE 	6 -27 7	; "callback" -
	94	[187]	NEWTABLE 	7 0 2
	95	[189]	GETTABLE 	8 0 -28	; "rotated"
	96	[189]	TEST     	8 0 0
	97	[189]	JMP      	5	; to 103
	98	[189]	GETUPVAL 	8 2	; _
	99	[189]	LOADK    	9 -29	; "No rotation"
	100	[189]	CALL     	8 2 2
	101	[189]	TEST     	8 0 1
	102	[189]	JMP      	3	; to 106
	103	[189]	GETUPVAL 	8 2	; _
	104	[189]	LOADK    	9 -30	; "Rotate"
	105	[189]	CALL     	8 2 2
	106	[189]	SETTABLE 	7 -24 8	; "text" -
	107	[193]	CLOSURE  	8 1	; 0x7fce86c09390
	108	[193]	MOVE     	0 0
	109	[193]	SETTABLE 	7 -27 8	; "callback" -
	110	[194]	NEWTABLE 	8 0 2
	111	[196]	GETUPVAL 	9 2	; _
	112	[196]	LOADK    	10 -31	; "Close"
	113	[196]	CALL     	9 2 2
	114	[196]	SETTABLE 	8 -24 9	; "text" -
	115	[199]	CLOSURE  	9 2	; 0x7fce86c09770
	116	[199]	GETUPVAL 	0 3	; UIManager
	117	[199]	MOVE     	0 0
	118	[199]	SETTABLE 	8 -27 9	; "callback" -
	119	[201]	SETLIST  	5 3 1	; 1
	120	[202]	SETLIST  	4 1 1	; 1
	121	[203]	GETUPVAL 	5 4	; ButtonTable
	122	[203]	SELF     	5 5 -8	; "new"
	123	[203]	NEWTABLE 	7 0 6
	124	[204]	GETTABLE 	8 0 -20	; "width"
	125	[204]	GETTABLE 	9 0 -32	; "button_padding"
	126	[204]	MUL      	9 -33 9	; 2 -
	127	[204]	SUB      	8 8 9
	128	[204]	SETTABLE 	7 -20 8	; "width" -
	129	[205]	SETTABLE 	7 -34 -35	; "button_font_face" "cfont"
	130	[206]	SETTABLE 	7 -36 -37	; "button_font_size" 20
	131	[207]	SETTABLE 	7 -38 4	; "buttons" -
	132	[208]	SETTABLE 	7 -39 -40	; "zero_sep" true
	133	[209]	SETTABLE 	7 -41 0	; "show_parent" -
	134	[203]	CALL     	5 3 2
	135	[211]	GETUPVAL 	6 5	; CenterContainer
	136	[211]	SELF     	6 6 -8	; "new"
	137	[211]	NEWTABLE 	8 1 1
	138	[212]	GETUPVAL 	9 0	; Geom
	139	[212]	SELF     	9 9 -8	; "new"
	140	[212]	NEWTABLE 	11 0 2
	141	[213]	GETTABLE 	12 0 -20	; "width"
	142	[213]	SETTABLE 	11 -14 12	; "w" -
	143	[214]	SELF     	12 5 -42	; "getSize"
	144	[214]	CALL     	12 2 2
	145	[214]	GETTABLE 	12 12 -16	; "h"
	146	[214]	SETTABLE 	11 -16 12	; "h" -
	147	[212]	CALL     	9 3 2
	148	[215]	SETTABLE 	8 -7 9	; "dimen" -
	149	[217]	MOVE     	9 5
	150	[217]	SETLIST  	8 1 1	; 1
	151	[211]	CALL     	6 3 2
	152	[217]	MOVE     	3 6
	153	[218]	SELF     	6 5 -42	; "getSize"
	154	[218]	CALL     	6 2 2
	155	[218]	GETTABLE 	2 6 -16	; "h"
	156	[222]	GETTABLE 	4 0 -19	; "height"
	157	[222]	SUB      	4 4 2
	158	[224]	LOADNIL  	5 6
	159	[225]	GETTABLE 	7 0 -43	; "with_title_bar"
	160	[225]	TEST     	7 0 0
	161	[225]	JMP      	203	; to 365
	162	[227]	LOADNIL  	7 7
	163	[228]	LOADK    	8 -5	; 0
	164	[229]	GETTABLE 	9 0 -44	; "caption"
	165	[229]	TEST     	9 0 0
	166	[229]	JMP      	33	; to 200
	167	[230]	LOADNIL  	9 9
	168	[231]	GETTABLE 	10 0 -45	; "caption_visible"
	169	[231]	TEST     	10 0 0
	170	[231]	JMP      	2	; to 173
	171	[232]	LOADK    	9 -46	; "\226\150\189 "
	172	[232]	JMP      	1	; to 174
	173	[234]	LOADK    	9 -47	; "\226\150\183 "
	174	[237]	GETUPVAL 	10 6	; FrameContainer
	175	[237]	SELF     	10 10 -8	; "new"
	176	[237]	NEWTABLE 	12 0 4
	177	[238]	SETTABLE 	12 -48 -5	; "bordersize" 0
	178	[239]	GETTABLE 	13 0 -50	; "title_padding"
	179	[239]	SETTABLE 	12 -49 13	; "padding" -
	180	[240]	GETTABLE 	13 0 -50	; "title_padding"
	181	[240]	GETUPVAL 	14 7	; Size
	182	[240]	GETTABLE 	14 14 -49	; "padding"
	183	[240]	GETTABLE 	14 14 -52	; "small"
	184	[240]	ADD      	13 13 14
	185	[240]	SETTABLE 	12 -51 13	; "padding_top" -
	186	[241]	SETTABLE 	12 -53 -5	; "padding_right" 0
	187	[242]	GETUPVAL 	13 8	; TextWidget
	188	[242]	SELF     	13 13 -8	; "new"
	189	[242]	NEWTABLE 	15 0 2
	190	[243]	SETTABLE 	15 -24 9	; "text" -
	191	[244]	GETTABLE 	16 0 -55	; "title_face"
	192	[244]	SETTABLE 	15 -54 16	; "face" -
	193	[242]	CALL     	13 3 0
	194	[246]	SETLIST  	12 0 1	; 1
	195	[237]	CALL     	10 3 2
	196	[246]	MOVE     	7 10
	197	[247]	SELF     	10 7 -42	; "getSize"
	198	[247]	CALL     	10 2 2
	199	[247]	GETTABLE 	8 10 -14	; "w"
	200	[249]	GETUPVAL 	9 9	; CloseButton
	201	[249]	SELF     	9 9 -8	; "new"
	202	[249]	NEWTABLE 	11 0 2
	203	[249]	SETTABLE 	11 -56 0	; "window" -
	204	[249]	GETUPVAL 	12 7	; Size
	205	[249]	GETTABLE 	12 12 -49	; "padding"
	206	[249]	GETTABLE 	12 12 -57	; "tiny"
	207	[249]	SETTABLE 	11 -51 12	; "padding_top" -
	208	[249]	CALL     	9 3 2
	209	[250]	GETUPVAL 	10 10	; TextBoxWidget
	210	[250]	SELF     	10 10 -8	; "new"
	211	[250]	NEWTABLE 	12 0 3
	212	[251]	GETTABLE 	13 0 -58	; "title_text"
	213	[251]	SETTABLE 	12 -24 13	; "text" -
	214	[252]	GETTABLE 	13 0 -55	; "title_face"
	215	[252]	SETTABLE 	12 -54 13	; "face" -
	216	[254]	GETTABLE 	13 0 -20	; "width"
	217	[254]	GETTABLE 	14 0 -50	; "title_padding"
	218	[254]	MUL      	14 -33 14	; 2 -
	219	[254]	SUB      	13 13 14
	220	[254]	GETTABLE 	14 0 -59	; "title_margin"
	221	[254]	MUL      	14 -33 14	; 2 -
	222	[254]	SUB      	13 13 14
	223	[254]	SELF     	14 9 -42	; "getSize"
	224	[254]	CALL     	14 2 2
	225	[254]	GETTABLE 	14 14 -14	; "w"
	226	[254]	SUB      	13 13 14
	227	[254]	SUB      	13 13 8
	228	[254]	SETTABLE 	12 -20 13	; "width" -
	229	[250]	CALL     	10 3 2
	230	[256]	GETTABLE 	11 0 -50	; "title_padding"
	231	[256]	GETUPVAL 	12 7	; Size
	232	[256]	GETTABLE 	12 12 -49	; "padding"
	233	[256]	GETTABLE 	12 12 -52	; "small"
	234	[256]	ADD      	11 11 12
	235	[257]	GETTABLE 	12 0 -44	; "caption"
	236	[257]	TEST     	12 0 0
	237	[257]	JMP      	4	; to 242
	238	[257]	GETTABLE 	12 0 -45	; "caption_visible"
	239	[257]	TEST     	12 0 0
	240	[257]	JMP      	1	; to 242
	241	[258]	LOADK    	11 -5	; 0
	242	[260]	GETUPVAL 	12 6	; FrameContainer
	243	[260]	SELF     	12 12 -8	; "new"
	244	[260]	NEWTABLE 	14 1 6
	245	[261]	GETTABLE 	15 0 -50	; "title_padding"
	246	[261]	SETTABLE 	14 -49 15	; "padding" -
	247	[262]	GETTABLE 	15 0 -50	; "title_padding"
	248	[262]	GETUPVAL 	16 7	; Size
	249	[262]	GETTABLE 	16 16 -49	; "padding"
	250	[262]	GETTABLE 	16 16 -52	; "small"
	251	[262]	ADD      	15 15 16
	252	[262]	SETTABLE 	14 -51 15	; "padding_top" -
	253	[263]	SETTABLE 	14 -60 11	; "padding_bottom" -
	254	[264]	TEST     	7 0 0
	255	[264]	JMP      	2	; to 258
	256	[264]	TESTSET  	15 8 1
	257	[264]	JMP      	1	; to 259
	258	[264]	GETTABLE 	15 0 -50	; "title_padding"
	259	[264]	SETTABLE 	14 -61 15	; "padding_left" -
	260	[265]	GETTABLE 	15 0 -59	; "title_margin"
	261	[265]	SETTABLE 	14 -62 15	; "margin" -
	262	[266]	SETTABLE 	14 -48 -5	; "bordersize" 0
	263	[268]	MOVE     	15 10
	264	[268]	SETLIST  	14 1 1	; 1
	265	[260]	CALL     	12 3 2
	266	[269]	GETTABLE 	13 0 -44	; "caption"
	267	[269]	TEST     	13 0 0
	268	[269]	JMP      	1	; to 270
	269	[270]	SETTABLE 	0 -63 12	; "caption_tap_area" -
	270	[272]	GETUPVAL 	13 11	; OverlapGroup
	271	[272]	SELF     	13 13 -8	; "new"
	272	[272]	NEWTABLE 	15 2 1
	273	[273]	NEWTABLE 	16 0 2
	274	[274]	GETTABLE 	17 0 -20	; "width"
	275	[274]	SETTABLE 	16 -14 17	; "w" -
	276	[275]	SELF     	17 12 -42	; "getSize"
	277	[275]	CALL     	17 2 2
	278	[275]	GETTABLE 	17 17 -16	; "h"
	279	[275]	SETTABLE 	16 -16 17	; "h" -
	280	[276]	SETTABLE 	15 -7 16	; "dimen" -
	281	[277]	MOVE     	16 12
	282	[279]	MOVE     	17 9
	283	[279]	SETLIST  	15 2 1	; 1
	284	[272]	CALL     	13 3 2
	285	[279]	MOVE     	5 13
	286	[280]	TEST     	7 0 0
	287	[280]	JMP      	6	; to 294
	288	[281]	GETGLOBAL	13 -64	; table
	289	[281]	GETTABLE 	13 13 -65	; "insert"
	290	[281]	MOVE     	14 5
	291	[281]	LOADK    	15 -66	; 1
	292	[281]	MOVE     	16 7
	293	[281]	CALL     	13 4 1
	294	[283]	GETTABLE 	13 0 -44	; "caption"
	295	[283]	TEST     	13 0 0
	296	[283]	JMP      	44	; to 341
	297	[283]	GETTABLE 	13 0 -45	; "caption_visible"
	298	[283]	TEST     	13 0 0
	299	[283]	JMP      	41	; to 341
	300	[284]	GETUPVAL 	13 10	; TextBoxWidget
	301	[284]	SELF     	13 13 -8	; "new"
	302	[284]	NEWTABLE 	15 0 3
	303	[285]	GETTABLE 	16 0 -44	; "caption"
	304	[285]	SETTABLE 	15 -24 16	; "text" -
	305	[286]	GETTABLE 	16 0 -67	; "caption_face"
	306	[286]	SETTABLE 	15 -54 16	; "face" -
	307	[287]	GETTABLE 	16 0 -20	; "width"
	308	[287]	GETTABLE 	17 0 -50	; "title_padding"
	309	[287]	MUL      	17 -33 17	; 2 -
	310	[287]	SUB      	16 16 17
	311	[287]	GETTABLE 	17 0 -59	; "title_margin"
	312	[287]	MUL      	17 -33 17	; 2 -
	313	[287]	SUB      	16 16 17
	314	[287]	GETTABLE 	17 0 -68	; "caption_padding"
	315	[287]	MUL      	17 -33 17	; 2 -
	316	[287]	SUB      	16 16 17
	317	[287]	SETTABLE 	15 -20 16	; "width" -
	318	[284]	CALL     	13 3 2
	319	[289]	GETUPVAL 	14 6	; FrameContainer
	320	[289]	SELF     	14 14 -8	; "new"
	321	[289]	NEWTABLE 	16 1 5
	322	[290]	GETTABLE 	17 0 -68	; "caption_padding"
	323	[290]	SETTABLE 	16 -49 17	; "padding" -
	324	[291]	SETTABLE 	16 -51 -5	; "padding_top" 0
	325	[292]	SETTABLE 	16 -60 -5	; "padding_bottom" 0
	326	[293]	GETTABLE 	17 0 -59	; "title_margin"
	327	[293]	SETTABLE 	16 -62 17	; "margin" -
	328	[294]	SETTABLE 	16 -48 -5	; "bordersize" 0
	329	[296]	MOVE     	17 13
	330	[296]	SETLIST  	16 1 1	; 1
	331	[289]	CALL     	14 3 2
	332	[297]	GETUPVAL 	15 12	; VerticalGroup
	333	[297]	SELF     	15 15 -8	; "new"
	334	[297]	NEWTABLE 	17 2 1
	335	[298]	SETTABLE 	17 -9 -69	; "align" "left"
	336	[299]	MOVE     	18 5
	337	[301]	MOVE     	19 14
	338	[301]	SETLIST  	17 2 1	; 1
	339	[297]	CALL     	15 3 2
	340	[301]	MOVE     	5 15
	341	[303]	GETUPVAL 	13 13	; LineWidget
	342	[303]	SELF     	13 13 -8	; "new"
	343	[303]	NEWTABLE 	15 0 1
	344	[304]	GETUPVAL 	16 0	; Geom
	345	[304]	SELF     	16 16 -8	; "new"
	346	[304]	NEWTABLE 	18 0 2
	347	[305]	GETTABLE 	19 0 -20	; "width"
	348	[305]	SETTABLE 	18 -14 19	; "w" -
	349	[306]	GETUPVAL 	19 7	; Size
	350	[306]	GETTABLE 	19 19 -70	; "line"
	351	[306]	GETTABLE 	19 19 -71	; "thick"
	352	[306]	SETTABLE 	18 -16 19	; "h" -
	353	[304]	CALL     	16 3 2
	354	[307]	SETTABLE 	15 -7 16	; "dimen" -
	355	[303]	CALL     	13 3 2
	356	[308]	MOVE     	6 13
	357	[310]	SELF     	13 5 -42	; "getSize"
	358	[310]	CALL     	13 2 2
	359	[310]	GETTABLE 	13 13 -16	; "h"
	360	[310]	SUB      	13 4 13
	361	[310]	SELF     	14 6 -42	; "getSize"
	362	[310]	CALL     	14 2 2
	363	[310]	GETTABLE 	14 14 -16	; "h"
	364	[310]	SUB      	4 13 14
	365	[313]	LOADNIL  	7 7
	366	[314]	GETTABLE 	8 0 -72	; "_images_list"
	367	[314]	TEST     	8 0 0
	368	[314]	JMP      	55	; to 424
	369	[316]	LOADK    	8 -66	; 1
	370	[317]	GETTABLE 	9 0 -73	; "_images_list_nb"
	371	[317]	LT       	0 -66 9	; 1 -
	372	[317]	JMP      	5	; to 378
	373	[318]	GETTABLE 	9 0 -74	; "_images_list_cur"
	374	[318]	SUB      	9 9 -66	; - 1
	375	[318]	GETTABLE 	10 0 -73	; "_images_list_nb"
	376	[318]	SUB      	10 10 -66	; - 1
	377	[318]	DIV      	8 9 10
	378	[320]	GETUPVAL 	9 14	; ProgressWidget
	379	[320]	SELF     	9 9 -8	; "new"
	380	[320]	NEWTABLE 	11 0 8
	381	[321]	GETTABLE 	12 0 -20	; "width"
	382	[321]	GETTABLE 	13 0 -32	; "button_padding"
	383	[321]	MUL      	13 -33 13	; 2 -
	384	[321]	SUB      	12 12 13
	385	[321]	SETTABLE 	11 -20 12	; "width" -
	386	[322]	GETUPVAL 	12 1	; Screen
	387	[322]	SELF     	12 12 -21	; "scaleBySize"
	388	[322]	LOADK    	14 -75	; 5
	389	[322]	CALL     	12 3 2
	390	[322]	SETTABLE 	11 -19 12	; "height" -
	391	[323]	SETTABLE 	11 -76 8	; "percentage" -
	392	[324]	SETTABLE 	11 -77 -5	; "margin_h" 0
	393	[325]	SETTABLE 	11 -78 -5	; "margin_v" 0
	394	[326]	SETTABLE 	11 -79 -5	; "radius" 0
	395	[327]	SETTABLE 	11 -80 -3	; "ticks" nil
	396	[328]	SETTABLE 	11 -81 -3	; "last" nil
	397	[320]	CALL     	9 3 2
	398	[330]	GETUPVAL 	10 5	; CenterContainer
	399	[330]	SELF     	10 10 -8	; "new"
	400	[330]	NEWTABLE 	12 1 1
	401	[331]	GETUPVAL 	13 0	; Geom
	402	[331]	SELF     	13 13 -8	; "new"
	403	[331]	NEWTABLE 	15 0 2
	404	[332]	GETTABLE 	16 0 -20	; "width"
	405	[332]	SETTABLE 	15 -14 16	; "w" -
	406	[333]	SELF     	16 9 -42	; "getSize"
	407	[333]	CALL     	16 2 2
	408	[333]	GETTABLE 	16 16 -16	; "h"
	409	[333]	GETUPVAL 	17 7	; Size
	410	[333]	GETTABLE 	17 17 -49	; "padding"
	411	[333]	GETTABLE 	17 17 -52	; "small"
	412	[333]	ADD      	16 16 17
	413	[333]	SETTABLE 	15 -16 16	; "h" -
	414	[331]	CALL     	13 3 2
	415	[334]	SETTABLE 	12 -7 13	; "dimen" -
	416	[336]	MOVE     	13 9
	417	[336]	SETLIST  	12 1 1	; 1
	418	[330]	CALL     	10 3 2
	419	[336]	MOVE     	7 10
	420	[337]	SELF     	10 7 -42	; "getSize"
	421	[337]	CALL     	10 2 2
	422	[337]	GETTABLE 	10 10 -16	; "h"
	423	[337]	SUB      	4 4 10
	424	[341]	MOVE     	8 4
	425	[342]	GETTABLE 	9 0 -20	; "width"
	426	[344]	GETTABLE 	10 0 -23	; "buttons_visible"
	427	[344]	TEST     	10 0 1
	428	[344]	JMP      	3	; to 432
	429	[344]	GETTABLE 	10 0 -43	; "with_title_bar"
	430	[344]	TEST     	10 0 0
	431	[344]	JMP      	7	; to 439
	432	[345]	GETTABLE 	10 0 -82	; "image_padding"
	433	[345]	MUL      	10 10 -33	; - 2
	434	[345]	SUB      	8 4 10
	435	[346]	GETTABLE 	10 0 -20	; "width"
	436	[346]	GETTABLE 	11 0 -82	; "image_padding"
	437	[346]	MUL      	11 11 -33	; - 2
	438	[346]	SUB      	9 10 11
	439	[349]	LOADK    	10 -5	; 0
	440	[350]	GETTABLE 	11 0 -28	; "rotated"
	441	[350]	TEST     	11 0 0
	442	[350]	JMP      	16	; to 459
	443	[353]	GETGLOBAL	11 -83	; DLANDSCAPE_CLOCKWISE_ROTATION
	444	[354]	GETUPVAL 	12 1	; Screen
	445	[354]	SELF     	12 12 -15	; "getWidth"
	446	[354]	CALL     	12 2 2
	447	[354]	GETUPVAL 	13 1	; Screen
	448	[354]	SELF     	13 13 -17	; "getHeight"
	449	[354]	CALL     	13 2 2
	450	[354]	LT       	0 13 12
	451	[354]	JMP      	1	; to 453
	452	[357]	NOT      	11 11
	453	[359]	TEST     	11 0 0
	454	[359]	JMP      	3	; to 458
	455	[359]	LOADK    	12 -84	; 90
	456	[359]	TESTSET  	10 12 1
	457	[359]	JMP      	1	; to 459
	458	[359]	LOADK    	10 -85	; 270
	459	[362]	GETUPVAL 	11 15	; ImageWidget
	460	[362]	SELF     	11 11 -8	; "new"
	461	[362]	NEWTABLE 	13 0 10
	462	[363]	GETTABLE 	14 0 -87	; "file"
	463	[363]	SETTABLE 	13 -87 14	; "file" -
	464	[364]	GETTABLE 	14 0 -88	; "image"
	465	[364]	SETTABLE 	13 -88 14	; "image" -
	466	[365]	SETTABLE 	13 -89 -90	; "image_disposable" false
	467	[366]	SETTABLE 	13 -91 -40	; "alpha" true
	468	[367]	SETTABLE 	13 -20 9	; "width" -
	469	[368]	SETTABLE 	13 -19 8	; "height" -
	470	[369]	SETTABLE 	13 -92 10	; "rotation_angle" -
	471	[370]	GETTABLE 	14 0 -4	; "scale_factor"
	472	[370]	SETTABLE 	13 -4 14	; "scale_factor" -
	473	[371]	GETTABLE 	14 0 -94	; "_center_x_ratio"
	474	[371]	SETTABLE 	13 -93 14	; "center_x_ratio" -
	475	[372]	GETTABLE 	14 0 -96	; "_center_y_ratio"
	476	[372]	SETTABLE 	13 -95 14	; "center_y_ratio" -
	477	[362]	CALL     	11 3 2
	478	[373]	SETTABLE 	0 -86 11	; "_image_wg" -
	479	[375]	GETUPVAL 	11 5	; CenterContainer
	480	[375]	SELF     	11 11 -8	; "new"
	481	[375]	NEWTABLE 	13 1 1
	482	[376]	GETUPVAL 	14 0	; Geom
	483	[376]	SELF     	14 14 -8	; "new"
	484	[376]	NEWTABLE 	16 0 2
	485	[377]	GETTABLE 	17 0 -20	; "width"
	486	[377]	SETTABLE 	16 -14 17	; "w" -
	487	[378]	SETTABLE 	16 -16 4	; "h" -
	488	[376]	CALL     	14 3 2
	489	[379]	SETTABLE 	13 -7 14	; "dimen" -
	490	[381]	GETTABLE 	14 0 -86	; "_image_wg"
	491	[381]	SETLIST  	13 1 1	; 1
	492	[375]	CALL     	11 3 2
	493	[383]	GETUPVAL 	12 12	; VerticalGroup
	494	[383]	SELF     	12 12 -8	; "new"
	495	[383]	NEWTABLE 	14 0 1
	496	[383]	SETTABLE 	14 -9 -69	; "align" "left"
	497	[383]	CALL     	12 3 2
	498	[384]	GETTABLE 	13 0 -43	; "with_title_bar"
	499	[384]	TEST     	13 0 0
	500	[384]	JMP      	10	; to 511
	501	[385]	GETGLOBAL	13 -64	; table
	502	[385]	GETTABLE 	13 13 -65	; "insert"
	503	[385]	MOVE     	14 12
	504	[385]	MOVE     	15 5
	505	[385]	CALL     	13 3 1
	506	[386]	GETGLOBAL	13 -64	; table
	507	[386]	GETTABLE 	13 13 -65	; "insert"
	508	[386]	MOVE     	14 12
	509	[386]	MOVE     	15 6
	510	[386]	CALL     	13 3 1
	511	[388]	GETGLOBAL	13 -64	; table
	512	[388]	GETTABLE 	13 13 -65	; "insert"
	513	[388]	MOVE     	14 12
	514	[388]	MOVE     	15 11
	515	[388]	CALL     	13 3 1
	516	[389]	TEST     	7 0 0
	517	[389]	JMP      	5	; to 523
	518	[390]	GETGLOBAL	13 -64	; table
	519	[390]	GETTABLE 	13 13 -65	; "insert"
	520	[390]	MOVE     	14 12
	521	[390]	MOVE     	15 7
	522	[390]	CALL     	13 3 1
	523	[392]	GETTABLE 	13 0 -23	; "buttons_visible"
	524	[392]	TEST     	13 0 0
	525	[392]	JMP      	5	; to 531
	526	[393]	GETGLOBAL	13 -64	; table
	527	[393]	GETTABLE 	13 13 -65	; "insert"
	528	[393]	MOVE     	14 12
	529	[393]	MOVE     	15 3
	530	[393]	CALL     	13 3 1
	531	[396]	GETUPVAL 	13 6	; FrameContainer
	532	[396]	SELF     	13 13 -8	; "new"
	533	[396]	NEWTABLE 	15 1 4
	534	[397]	GETTABLE 	16 0 -18	; "fullscreen"
	535	[397]	TEST     	16 0 1
	536	[397]	JMP      	3	; to 540
	537	[397]	LOADK    	16 -97	; 8
	538	[397]	TEST     	16 0 1
	539	[397]	JMP      	1	; to 541
	540	[397]	LOADNIL  	16 16
	541	[397]	SETTABLE 	15 -79 16	; "radius" -
	542	[398]	SETTABLE 	15 -49 -5	; "padding" 0
	543	[399]	SETTABLE 	15 -62 -5	; "margin" 0
	544	[400]	GETUPVAL 	16 16	; Blitbuffer
	545	[400]	GETTABLE 	16 16 -99	; "COLOR_WHITE"
	546	[400]	SETTABLE 	15 -98 16	; "background" -
	547	[402]	MOVE     	16 12
	548	[402]	SETLIST  	15 1 1	; 1
	549	[396]	CALL     	13 3 2
	550	[402]	SETTABLE 	0 -6 13	; "main_frame" -
	551	[403]	GETUPVAL 	13 17	; WidgetContainer
	552	[403]	SELF     	13 13 -8	; "new"
	553	[403]	NEWTABLE 	15 0 2
	554	[404]	GETTABLE 	16 0 -9	; "align"
	555	[404]	SETTABLE 	15 -9 16	; "align" -
	556	[405]	GETTABLE 	16 0 -11	; "region"
	557	[405]	SETTABLE 	15 -7 16	; "dimen" -
	558	[406]	GETUPVAL 	16 6	; FrameContainer
	559	[406]	SELF     	16 16 -8	; "new"
	560	[406]	NEWTABLE 	18 1 2
	561	[407]	SETTABLE 	18 -48 -5	; "bordersize" 0
	562	[408]	GETUPVAL 	19 7	; Size
	563	[408]	GETTABLE 	19 19 -49	; "padding"
	564	[408]	GETTABLE 	19 19 -100	; "default"
	565	[408]	SETTABLE 	18 -49 19	; "padding" -
	566	[410]	GETTABLE 	19 0 -6	; "main_frame"
	567	[410]	SETLIST  	18 1 1	; 1
	568	[406]	CALL     	16 3 0
	569	[411]	SETLIST  	15 0 1	; 1
	570	[403]	CALL     	13 3 2
	571	[411]	SETTABLE 	0 -66 13	; 1 -
	572	[416]	SETTABLE 	0 -101 -40	; "dithered" true
	573	[417]	GETUPVAL 	13 3	; UIManager
	574	[417]	SELF     	13 13 -102	; "setDirty"
	575	[417]	MOVE     	15 0
	576	[421]	CLOSURE  	16 3	; 0x7fce86d04890
	577	[421]	MOVE     	0 0
	578	[421]	MOVE     	0 1
	579	[421]	GETUPVAL 	0 18	; logger
	580	[417]	CALL     	13 4 1
	581	[422]	RETURN   	0 1

function <./frontend/ui/widget/imageviewer.lua:179,186> (23 instructions, 92 bytes at 0x7fce86c08c90)
0 params, 2 slots, 1 upvalue, 0 locals, 8 constants, 0 functions
	1	[180]	GETUPVAL 	0 0	; self
	2	[180]	GETUPVAL 	1 0	; self
	3	[180]	GETTABLE 	1 1 -2	; "_scale_to_fit"
	4	[180]	TEST     	1 0 0
	5	[180]	JMP      	3	; to 9
	6	[180]	LOADK    	1 -3	; 1
	7	[180]	TEST     	1 0 1
	8	[180]	JMP      	1	; to 10
	9	[180]	LOADK    	1 -4	; 0
	10	[180]	SETTABLE 	0 -1 1	; "scale_factor" -
	11	[181]	GETUPVAL 	0 0	; self
	12	[181]	GETUPVAL 	1 0	; self
	13	[181]	GETTABLE 	1 1 -2	; "_scale_to_fit"
	14	[181]	NOT      	1 1
	15	[181]	SETTABLE 	0 -2 1	; "_scale_to_fit" -
	16	[183]	GETUPVAL 	0 0	; self
	17	[183]	SETTABLE 	0 -5 -6	; "_center_x_ratio" 0.5
	18	[184]	GETUPVAL 	0 0	; self
	19	[184]	SETTABLE 	0 -7 -6	; "_center_y_ratio" 0.5
	20	[185]	GETUPVAL 	0 0	; self
	21	[185]	SELF     	0 0 -8	; "update"
	22	[185]	CALL     	0 2 1
	23	[186]	RETURN   	0 1

function <./frontend/ui/widget/imageviewer.lua:190,193> (14 instructions, 56 bytes at 0x7fce86c09390)
0 params, 2 slots, 1 upvalue, 0 locals, 2 constants, 0 functions
	1	[191]	GETUPVAL 	0 0	; self
	2	[191]	GETUPVAL 	1 0	; self
	3	[191]	GETTABLE 	1 1 -1	; "rotated"
	4	[191]	TEST     	1 0 1
	5	[191]	JMP      	3	; to 9
	6	[191]	LOADBOOL 	1 1 0
	7	[191]	TEST     	1 0 1
	8	[191]	JMP      	1	; to 10
	9	[191]	LOADBOOL 	1 0 0
	10	[191]	SETTABLE 	0 -1 1	; "rotated" -
	11	[192]	GETUPVAL 	0 0	; self
	12	[192]	SELF     	0 0 -2	; "update"
	13	[192]	CALL     	0 2 1
	14	[193]	RETURN   	0 1

function <./frontend/ui/widget/imageviewer.lua:197,199> (5 instructions, 20 bytes at 0x7fce86c09770)
0 params, 3 slots, 2 upvalues, 0 locals, 1 constant, 0 functions
	1	[198]	GETUPVAL 	0 0	; UIManager
	2	[198]	SELF     	0 0 -1	; "close"
	3	[198]	GETUPVAL 	2 1	; self
	4	[198]	CALL     	0 3 1
	5	[199]	RETURN   	0 1

function <./frontend/ui/widget/imageviewer.lua:417,421> (16 instructions, 64 bytes at 0x7fce86d04890)
0 params, 4 slots, 3 upvalues, 1 local, 6 constants, 0 functions
	1	[418]	GETUPVAL 	0 0	; self
	2	[418]	GETTABLE 	0 0 -1	; "main_frame"
	3	[418]	GETTABLE 	0 0 -2	; "dimen"
	4	[418]	SELF     	0 0 -3	; "combine"
	5	[418]	GETUPVAL 	2 1	; orig_dimen
	6	[418]	CALL     	0 3 2
	7	[419]	GETUPVAL 	1 2	; logger
	8	[419]	GETTABLE 	1 1 -4	; "dbg"
	9	[419]	LOADK    	2 -5	; "update image region"
	10	[419]	MOVE     	3 0
	11	[419]	CALL     	1 3 1
	12	[420]	LOADK    	1 -6	; "ui"
	13	[420]	MOVE     	2 0
	14	[420]	LOADBOOL 	3 1 0
	15	[420]	RETURN   	1 4
	16	[421]	RETURN   	0 1

function <./frontend/ui/widget/imageviewer.lua:424,430> (10 instructions, 40 bytes at 0x7fce86d04bb0)
1 param, 5 slots, 1 upvalue, 1 local, 3 constants, 1 function
	1	[425]	SETTABLE 	0 -1 -2	; "dithered" true
	2	[426]	GETUPVAL 	1 0	; UIManager
	3	[426]	SELF     	1 1 -3	; "setDirty"
	4	[426]	MOVE     	3 0
	5	[428]	CLOSURE  	4 0	; 0x7fce86d051a0
	6	[428]	MOVE     	0 0
	7	[426]	CALL     	1 4 1
	8	[429]	LOADBOOL 	1 1 0
	9	[429]	RETURN   	1 2
	10	[430]	RETURN   	0 1

function <./frontend/ui/widget/imageviewer.lua:426,428> (7 instructions, 28 bytes at 0x7fce86d051a0)
0 params, 3 slots, 1 upvalue, 0 locals, 3 constants, 0 functions
	1	[427]	LOADK    	0 -1	; "full"
	2	[427]	GETUPVAL 	1 0	; self
	3	[427]	GETTABLE 	1 1 -2	; "main_frame"
	4	[427]	GETTABLE 	1 1 -3	; "dimen"
	5	[427]	LOADBOOL 	2 1 0
	6	[427]	RETURN   	0 4
	7	[428]	RETURN   	0 1

function <./frontend/ui/widget/imageviewer.lua:432,449> (40 instructions, 160 bytes at 0x7fce86d052a0)
2 params, 4 slots, 1 upvalue, 2 locals, 17 constants, 0 functions
	1	[433]	GETTABLE 	2 0 -1	; "image"
	2	[433]	TEST     	2 0 0
	3	[433]	JMP      	15	; to 19
	4	[433]	GETTABLE 	2 0 -2	; "image_disposable"
	5	[433]	TEST     	2 0 0
	6	[433]	JMP      	12	; to 19
	7	[433]	GETTABLE 	2 0 -1	; "image"
	8	[433]	GETTABLE 	2 2 -3	; "free"
	9	[433]	TEST     	2 0 0
	10	[433]	JMP      	8	; to 19
	11	[434]	GETUPVAL 	2 0	; logger
	12	[434]	GETTABLE 	2 2 -4	; "dbg"
	13	[434]	LOADK    	3 -5	; "ImageViewer:free(self.image)"
	14	[434]	CALL     	2 2 1
	15	[435]	GETTABLE 	2 0 -1	; "image"
	16	[435]	SELF     	2 2 -3	; "free"
	17	[435]	CALL     	2 2 1
	18	[436]	SETTABLE 	0 -1 -6	; "image" nil
	19	[438]	GETTABLE 	2 0 -7	; "_images_list"
	20	[438]	GETTABLE 	2 2 1
	21	[438]	SETTABLE 	0 -1 2	; "image" -
	22	[439]	GETGLOBAL	2 -8	; type
	23	[439]	GETTABLE 	3 0 -1	; "image"
	24	[439]	CALL     	2 2 2
	25	[439]	EQ       	0 2 -9	; - "function"
	26	[439]	JMP      	3	; to 30
	27	[440]	GETTABLE 	2 0 -1	; "image"
	28	[440]	CALL     	2 1 2
	29	[440]	SETTABLE 	0 -1 2	; "image" -
	30	[442]	SETTABLE 	0 -10 1	; "_images_list_cur" -
	31	[443]	GETTABLE 	2 0 -11	; "images_keep_pan_and_zoom"
	32	[443]	TEST     	2 0 1
	33	[443]	JMP      	4	; to 38
	34	[444]	SETTABLE 	0 -12 -13	; "_center_x_ratio" 0.5
	35	[445]	SETTABLE 	0 -14 -13	; "_center_y_ratio" 0.5
	36	[446]	GETTABLE 	2 0 -16	; "_images_orig_scale_factor"
	37	[446]	SETTABLE 	0 -15 2	; "scale_factor" -
	38	[448]	SELF     	2 0 -17	; "update"
	39	[448]	CALL     	2 2 1
	40	[449]	RETURN   	0 1

function <./frontend/ui/widget/imageviewer.lua:451,489> (101 instructions, 404 bytes at 0x7fce86d05830)
3 params, 8 slots, 2 upvalues, 5 locals, 20 constants, 0 functions
	1	[452]	GETTABLE 	3 2 -1	; "pos"
	2	[452]	SELF     	3 3 -2	; "notIntersectWith"
	3	[452]	GETTABLE 	5 0 -3	; "main_frame"
	4	[452]	GETTABLE 	5 5 -4	; "dimen"
	5	[452]	CALL     	3 3 2
	6	[452]	TEST     	3 0 0
	7	[452]	JMP      	4	; to 12
	8	[453]	SELF     	3 0 -5	; "onClose"
	9	[453]	CALL     	3 2 1
	10	[454]	LOADBOOL 	3 1 0
	11	[454]	RETURN   	3 2
	12	[456]	GETTABLE 	3 0 -6	; "caption_tap_area"
	13	[456]	TEST     	3 0 0
	14	[456]	JMP      	14	; to 29
	15	[456]	GETTABLE 	3 2 -1	; "pos"
	16	[456]	SELF     	3 3 -7	; "intersectWith"
	17	[456]	GETTABLE 	5 0 -6	; "caption_tap_area"
	18	[456]	GETTABLE 	5 5 -4	; "dimen"
	19	[456]	CALL     	3 3 2
	20	[456]	TEST     	3 0 0
	21	[456]	JMP      	7	; to 29
	22	[457]	GETTABLE 	3 0 -8	; "caption_visible"
	23	[457]	NOT      	3 3
	24	[457]	SETTABLE 	0 -8 3	; "caption_visible" -
	25	[458]	SELF     	3 0 -9	; "update"
	26	[458]	CALL     	3 2 1
	27	[459]	LOADBOOL 	3 1 0
	28	[459]	RETURN   	3 2
	29	[461]	GETTABLE 	3 0 -10	; "_images_list"
	30	[461]	TEST     	3 0 0
	31	[461]	JMP      	62	; to 94
	32	[463]	LOADNIL  	3 4
	33	[464]	GETTABLE 	5 2 -1	; "pos"
	34	[464]	GETTABLE 	5 5 -11	; "x"
	35	[464]	GETUPVAL 	6 0	; Screen
	36	[464]	SELF     	6 6 -12	; "getWidth"
	37	[464]	CALL     	6 2 2
	38	[464]	DIV      	6 6 -13	; - 3
	39	[464]	LT       	0 5 6
	40	[464]	JMP      	9	; to 50
	41	[465]	GETUPVAL 	5 1	; BD
	42	[465]	GETTABLE 	5 5 -14	; "mirroredUILayout"
	43	[465]	CALL     	5 1 2
	44	[465]	NOT      	3 5
	45	[466]	GETUPVAL 	5 1	; BD
	46	[466]	GETTABLE 	5 5 -14	; "mirroredUILayout"
	47	[466]	CALL     	5 1 2
	48	[466]	MOVE     	4 5
	49	[466]	JMP      	17	; to 67
	50	[467]	GETTABLE 	5 2 -1	; "pos"
	51	[467]	GETTABLE 	5 5 -11	; "x"
	52	[467]	GETUPVAL 	6 0	; Screen
	53	[467]	SELF     	6 6 -12	; "getWidth"
	54	[467]	CALL     	6 2 2
	55	[467]	MUL      	6 6 -15	; - 2
	56	[467]	DIV      	6 6 -13	; - 3
	57	[467]	LT       	0 6 5
	58	[467]	JMP      	8	; to 67
	59	[468]	GETUPVAL 	5 1	; BD
	60	[468]	GETTABLE 	5 5 -14	; "mirroredUILayout"
	61	[468]	CALL     	5 1 2
	62	[468]	MOVE     	3 5
	63	[469]	GETUPVAL 	5 1	; BD
	64	[469]	GETTABLE 	5 5 -14	; "mirroredUILayout"
	65	[469]	CALL     	5 1 2
	66	[469]	NOT      	4 5
	67	[471]	TEST     	3 0 0
	68	[471]	JMP      	8	; to 77
	69	[472]	GETTABLE 	5 0 -16	; "_images_list_cur"
	70	[472]	LT       	0 -17 5	; 1 -
	71	[472]	JMP      	27	; to 99
	72	[473]	SELF     	5 0 -18	; "switchToImageNum"
	73	[473]	GETTABLE 	7 0 -16	; "_images_list_cur"
	74	[473]	SUB      	7 7 -17	; - 1
	75	[473]	CALL     	5 3 1
	76	[474]	JMP      	22	; to 99
	77	[475]	TEST     	4 0 0
	78	[475]	JMP      	9	; to 88
	79	[476]	GETTABLE 	5 0 -16	; "_images_list_cur"
	80	[476]	GETTABLE 	6 0 -19	; "_images_list_nb"
	81	[476]	LT       	0 5 6
	82	[476]	JMP      	16	; to 99
	83	[477]	SELF     	5 0 -18	; "switchToImageNum"
	84	[477]	GETTABLE 	7 0 -16	; "_images_list_cur"
	85	[477]	ADD      	7 7 -17	; - 1
	86	[477]	CALL     	5 3 1
	87	[478]	JMP      	11	; to 99
	88	[480]	GETTABLE 	5 0 -20	; "buttons_visible"
	89	[480]	NOT      	5 5
	90	[480]	SETTABLE 	0 -20 5	; "buttons_visible" -
	91	[481]	SELF     	5 0 -9	; "update"
	92	[481]	CALL     	5 2 1
	93	[482]	JMP      	5	; to 99
	94	[485]	GETTABLE 	3 0 -20	; "buttons_visible"
	95	[485]	NOT      	3 3
	96	[485]	SETTABLE 	0 -20 3	; "buttons_visible" -
	97	[486]	SELF     	3 0 -9	; "update"
	98	[486]	CALL     	3 2 1
	99	[488]	LOADBOOL 	3 1 0
	100	[488]	RETURN   	3 2
	101	[489]	RETURN   	0 1

function <./frontend/ui/widget/imageviewer.lua:491,497> (11 instructions, 44 bytes at 0x7fce86d05e90)
3 params, 7 slots, 0 upvalues, 3 locals, 4 constants, 0 functions
	1	[492]	GETTABLE 	3 0 -1	; "_image_wg"
	2	[492]	TEST     	3 0 0
	3	[492]	JMP      	7	; to 11
	4	[495]	GETTABLE 	3 0 -1	; "_image_wg"
	5	[495]	SELF     	3 3 -4	; "panBy"
	6	[495]	MOVE     	5 1
	7	[495]	MOVE     	6 2
	8	[495]	CALL     	3 4 3
	9	[495]	SETTABLE 	0 -3 4	; "_center_y_ratio" -
	10	[495]	SETTABLE 	0 -2 3	; "_center_x_ratio" -
	11	[497]	RETURN   	0 1

function <./frontend/ui/widget/imageviewer.lua:500,542> (125 instructions, 500 bytes at 0x7fce86d06650)
3 params, 10 slots, 1 upvalue, 8 locals, 26 constants, 0 functions
	1	[503]	GETTABLE 	3 2 -1	; "direction"
	2	[504]	GETTABLE 	4 2 -2	; "distance"
	3	[505]	GETGLOBAL	5 -3	; math
	4	[505]	GETTABLE 	5 5 -4	; "sqrt"
	5	[505]	MUL      	6 4 4
	6	[505]	DIV      	6 6 -5	; - 2
	7	[505]	CALL     	5 2 2
	8	[506]	EQ       	0 3 -6	; - "north"
	9	[506]	JMP      	32	; to 42
	10	[507]	GETTABLE 	6 2 -7	; "pos"
	11	[507]	GETTABLE 	6 6 -8	; "x"
	12	[507]	GETUPVAL 	7 0	; Screen
	13	[507]	SELF     	7 7 -9	; "getWidth"
	14	[507]	CALL     	7 2 2
	15	[507]	MUL      	7 7 -10	; - 1
	16	[507]	DIV      	7 7 -11	; - 16
	17	[507]	LT       	1 6 7
	18	[507]	JMP      	9	; to 28
	19	[507]	GETTABLE 	6 2 -7	; "pos"
	20	[507]	GETTABLE 	6 6 -8	; "x"
	21	[507]	GETUPVAL 	7 0	; Screen
	22	[507]	SELF     	7 7 -9	; "getWidth"
	23	[507]	CALL     	7 2 2
	24	[507]	MUL      	7 7 -12	; - 15
	25	[507]	DIV      	7 7 -11	; - 16
	26	[507]	LT       	0 7 6
	27	[507]	JMP      	9	; to 37
	28	[510]	GETTABLE 	6 2 -2	; "distance"
	29	[510]	GETUPVAL 	7 0	; Screen
	30	[510]	SELF     	7 7 -13	; "getHeight"
	31	[510]	CALL     	7 2 2
	32	[510]	DIV      	6 6 7
	33	[511]	SELF     	7 0 -14	; "onZoomIn"
	34	[511]	MOVE     	9 6
	35	[511]	CALL     	7 3 1
	36	[511]	JMP      	86	; to 123
	37	[513]	SELF     	6 0 -15	; "panBy"
	38	[513]	LOADK    	8 -16	; 0
	39	[513]	MOVE     	9 4
	40	[513]	CALL     	6 4 1
	41	[514]	JMP      	81	; to 123
	42	[515]	EQ       	0 3 -17	; - "south"
	43	[515]	JMP      	38	; to 82
	44	[516]	GETTABLE 	6 2 -7	; "pos"
	45	[516]	GETTABLE 	6 6 -8	; "x"
	46	[516]	GETUPVAL 	7 0	; Screen
	47	[516]	SELF     	7 7 -9	; "getWidth"
	48	[516]	CALL     	7 2 2
	49	[516]	MUL      	7 7 -10	; - 1
	50	[516]	DIV      	7 7 -11	; - 16
	51	[516]	LT       	1 6 7
	52	[516]	JMP      	9	; to 62
	53	[516]	GETTABLE 	6 2 -7	; "pos"
	54	[516]	GETTABLE 	6 6 -8	; "x"
	55	[516]	GETUPVAL 	7 0	; Screen
	56	[516]	SELF     	7 7 -9	; "getWidth"
	57	[516]	CALL     	7 2 2
	58	[516]	MUL      	7 7 -12	; - 15
	59	[516]	DIV      	7 7 -11	; - 16
	60	[516]	LT       	0 7 6
	61	[516]	JMP      	9	; to 71
	62	[518]	GETTABLE 	6 2 -2	; "distance"
	63	[518]	GETUPVAL 	7 0	; Screen
	64	[518]	SELF     	7 7 -13	; "getHeight"
	65	[518]	CALL     	7 2 2
	66	[518]	DIV      	6 6 7
	67	[519]	SELF     	7 0 -18	; "onZoomOut"
	68	[519]	MOVE     	9 6
	69	[519]	CALL     	7 3 1
	70	[519]	JMP      	52	; to 123
	71	[520]	GETTABLE 	6 0 -19	; "scale_factor"
	72	[520]	EQ       	0 6 -16	; - 0
	73	[520]	JMP      	3	; to 77
	74	[524]	SELF     	6 0 -20	; "onClose"
	75	[524]	CALL     	6 2 1
	76	[524]	JMP      	46	; to 123
	77	[526]	SELF     	6 0 -15	; "panBy"
	78	[526]	LOADK    	8 -16	; 0
	79	[526]	UNM      	9 4
	80	[526]	CALL     	6 4 1
	81	[527]	JMP      	41	; to 123
	82	[528]	EQ       	0 3 -21	; - "east"
	83	[528]	JMP      	5	; to 89
	84	[529]	SELF     	6 0 -15	; "panBy"
	85	[529]	UNM      	8 4
	86	[529]	LOADK    	9 -16	; 0
	87	[529]	CALL     	6 4 1
	88	[529]	JMP      	34	; to 123
	89	[530]	EQ       	0 3 -22	; - "west"
	90	[530]	JMP      	5	; to 96
	91	[531]	SELF     	6 0 -15	; "panBy"
	92	[531]	MOVE     	8 4
	93	[531]	LOADK    	9 -16	; 0
	94	[531]	CALL     	6 4 1
	95	[531]	JMP      	27	; to 123
	96	[532]	EQ       	0 3 -23	; - "northeast"
	97	[532]	JMP      	5	; to 103
	98	[533]	SELF     	6 0 -15	; "panBy"
	99	[533]	UNM      	8 5
	100	[533]	MOVE     	9 5
	101	[533]	CALL     	6 4 1
	102	[533]	JMP      	20	; to 123
	103	[534]	EQ       	0 3 -24	; - "northwest"
	104	[534]	JMP      	5	; to 110
	105	[535]	SELF     	6 0 -15	; "panBy"
	106	[535]	MOVE     	8 5
	107	[535]	MOVE     	9 5
	108	[535]	CALL     	6 4 1
	109	[535]	JMP      	13	; to 123
	110	[536]	EQ       	0 3 -25	; - "southeast"
	111	[536]	JMP      	5	; to 117
	112	[537]	SELF     	6 0 -15	; "panBy"
	113	[537]	UNM      	8 5
	114	[537]	UNM      	9 5
	115	[537]	CALL     	6 4 1
	116	[537]	JMP      	6	; to 123
	117	[538]	EQ       	0 3 -26	; - "southwest"
	118	[538]	JMP      	4	; to 123
	119	[539]	SELF     	6 0 -15	; "panBy"
	120	[539]	MOVE     	8 5
	121	[539]	UNM      	9 5
	122	[539]	CALL     	6 4 1
	123	[541]	LOADBOOL 	6 1 0
	124	[541]	RETURN   	6 2
	125	[542]	RETURN   	0 1

function <./frontend/ui/widget/imageviewer.lua:544,550> (10 instructions, 40 bytes at 0x7fce86d06b90)
3 params, 4 slots, 0 upvalues, 3 locals, 7 constants, 0 functions
	1	[546]	SETTABLE 	0 -1 -2	; "_panning" true
	2	[547]	GETTABLE 	3 2 -4	; "pos"
	3	[547]	GETTABLE 	3 3 -5	; "x"
	4	[547]	SETTABLE 	0 -3 3	; "_pan_relative_x" -
	5	[548]	GETTABLE 	3 2 -4	; "pos"
	6	[548]	GETTABLE 	3 3 -7	; "y"
	7	[548]	SETTABLE 	0 -6 3	; "_pan_relative_y" -
	8	[549]	LOADBOOL 	3 1 0
	9	[549]	RETURN   	3 2
	10	[550]	RETURN   	0 1

function <./frontend/ui/widget/imageviewer.lua:552,567> (46 instructions, 184 bytes at 0x7fce86d078f0)
3 params, 9 slots, 1 upvalue, 3 locals, 15 constants, 0 functions
	1	[554]	GETTABLE 	3 0 -1	; "_panning"
	2	[554]	TEST     	3 0 0
	3	[554]	JMP      	40	; to 44
	4	[555]	SETTABLE 	0 -1 -2	; "_panning" false
	5	[556]	GETTABLE 	3 2 -4	; "pos"
	6	[556]	GETTABLE 	3 3 -5	; "x"
	7	[556]	GETTABLE 	4 0 -3	; "_pan_relative_x"
	8	[556]	SUB      	3 3 4
	9	[556]	SETTABLE 	0 -3 3	; "_pan_relative_x" -
	10	[557]	GETTABLE 	3 2 -4	; "pos"
	11	[557]	GETTABLE 	3 3 -7	; "y"
	12	[557]	GETTABLE 	4 0 -6	; "_pan_relative_y"
	13	[557]	SUB      	3 3 4
	14	[557]	SETTABLE 	0 -6 3	; "_pan_relative_y" -
	15	[558]	GETGLOBAL	3 -8	; math
	16	[558]	GETTABLE 	3 3 -9	; "abs"
	17	[558]	GETTABLE 	4 0 -3	; "_pan_relative_x"
	18	[558]	CALL     	3 2 2
	19	[558]	GETTABLE 	4 0 -10	; "pan_threshold"
	20	[558]	LT       	0 3 4
	21	[558]	JMP      	16	; to 38
	22	[558]	GETGLOBAL	3 -8	; math
	23	[558]	GETTABLE 	3 3 -9	; "abs"
	24	[558]	GETTABLE 	4 0 -6	; "_pan_relative_y"
	25	[558]	CALL     	3 2 2
	26	[558]	GETTABLE 	4 0 -10	; "pan_threshold"
	27	[558]	LT       	0 3 4
	28	[558]	JMP      	9	; to 38
	29	[560]	SETTABLE 	0 -11 -12	; "dithered" true
	30	[561]	GETUPVAL 	3 0	; UIManager
	31	[561]	SELF     	3 3 -13	; "setDirty"
	32	[561]	LOADNIL  	5 5
	33	[561]	LOADK    	6 -14	; "full"
	34	[561]	LOADNIL  	7 7
	35	[561]	LOADBOOL 	8 1 0
	36	[561]	CALL     	3 6 1
	37	[561]	JMP      	6	; to 44
	38	[563]	SELF     	3 0 -15	; "panBy"
	39	[563]	GETTABLE 	5 0 -3	; "_pan_relative_x"
	40	[563]	UNM      	5 5
	41	[563]	GETTABLE 	6 0 -6	; "_pan_relative_y"
	42	[563]	UNM      	6 6
	43	[563]	CALL     	3 4 1
	44	[566]	LOADBOOL 	3 1 0
	45	[566]	RETURN   	3 2
	46	[567]	RETURN   	0 1

function <./frontend/ui/widget/imageviewer.lua:569,574> (10 instructions, 40 bytes at 0x7fce86d07c00)
3 params, 4 slots, 0 upvalues, 3 locals, 7 constants, 0 functions
	1	[570]	SETTABLE 	0 -1 -2	; "_panning" true
	2	[571]	GETTABLE 	3 2 -4	; "relative"
	3	[571]	GETTABLE 	3 3 -5	; "x"
	4	[571]	SETTABLE 	0 -3 3	; "_pan_relative_x" -
	5	[572]	GETTABLE 	3 2 -4	; "relative"
	6	[572]	GETTABLE 	3 3 -7	; "y"
	7	[572]	SETTABLE 	0 -6 3	; "_pan_relative_y" -
	8	[573]	LOADBOOL 	3 1 0
	9	[573]	RETURN   	3 2
	10	[574]	RETURN   	0 1

function <./frontend/ui/widget/imageviewer.lua:576,582> (13 instructions, 52 bytes at 0x7fce86d07f60)
3 params, 7 slots, 0 upvalues, 3 locals, 5 constants, 0 functions
	1	[577]	GETTABLE 	3 0 -1	; "_panning"
	2	[577]	TEST     	3 0 0
	3	[577]	JMP      	7	; to 11
	4	[578]	SETTABLE 	0 -1 -2	; "_panning" false
	5	[579]	SELF     	3 0 -3	; "panBy"
	6	[579]	GETTABLE 	5 0 -4	; "_pan_relative_x"
	7	[579]	UNM      	5 5
	8	[579]	GETTABLE 	6 0 -5	; "_pan_relative_y"
	9	[579]	UNM      	6 6
	10	[579]	CALL     	3 4 1
	11	[581]	LOADBOOL 	3 1 0
	12	[581]	RETURN   	3 2
	13	[582]	RETURN   	0 1

function <./frontend/ui/widget/imageviewer.lua:585,596> (22 instructions, 88 bytes at 0x7fce86d083e0)
2 params, 4 slots, 0 upvalues, 2 locals, 7 constants, 0 functions
	1	[586]	GETTABLE 	2 0 -1	; "scale_factor"
	2	[586]	EQ       	0 2 -2	; - 0
	3	[586]	JMP      	4	; to 8
	4	[588]	GETTABLE 	2 0 -3	; "_image_wg"
	5	[588]	SELF     	2 2 -4	; "getScaleFactor"
	6	[588]	CALL     	2 2 2
	7	[588]	SETTABLE 	0 -1 2	; "scale_factor" -
	8	[590]	TEST     	1 0 1
	9	[590]	JMP      	1	; to 11
	10	[590]	LOADK    	1 -5	; 0.2
	11	[591]	GETTABLE 	2 0 -1	; "scale_factor"
	12	[591]	ADD      	2 2 1
	13	[591]	LT       	0 2 -6	; - 100
	14	[591]	JMP      	5	; to 20
	15	[592]	GETTABLE 	2 0 -1	; "scale_factor"
	16	[592]	ADD      	2 2 1
	17	[592]	SETTABLE 	0 -1 2	; "scale_factor" -
	18	[593]	SELF     	2 0 -7	; "update"
	19	[593]	CALL     	2 2 1
	20	[595]	LOADBOOL 	2 1 0
	21	[595]	RETURN   	2 2
	22	[596]	RETURN   	0 1

function <./frontend/ui/widget/imageviewer.lua:598,609> (22 instructions, 88 bytes at 0x7fce86d089a0)
2 params, 4 slots, 0 upvalues, 2 locals, 7 constants, 0 functions
	1	[599]	GETTABLE 	2 0 -1	; "scale_factor"
	2	[599]	EQ       	0 2 -2	; - 0
	3	[599]	JMP      	4	; to 8
	4	[601]	GETTABLE 	2 0 -3	; "_image_wg"
	5	[601]	SELF     	2 2 -4	; "getScaleFactor"
	6	[601]	CALL     	2 2 2
	7	[601]	SETTABLE 	0 -1 2	; "scale_factor" -
	8	[603]	TEST     	1 0 1
	9	[603]	JMP      	1	; to 11
	10	[603]	LOADK    	1 -5	; 0.2
	11	[604]	GETTABLE 	2 0 -1	; "scale_factor"
	12	[604]	SUB      	2 2 1
	13	[604]	LT       	0 -6 2	; 0.01 -
	14	[604]	JMP      	5	; to 20
	15	[605]	GETTABLE 	2 0 -1	; "scale_factor"
	16	[605]	SUB      	2 2 1
	17	[605]	SETTABLE 	0 -1 2	; "scale_factor" -
	18	[606]	SELF     	2 0 -7	; "update"
	19	[606]	CALL     	2 2 1
	20	[608]	LOADBOOL 	2 1 0
	21	[608]	RETURN   	2 2
	22	[609]	RETURN   	0 1

function <./frontend/ui/widget/imageviewer.lua:611,622> (33 instructions, 132 bytes at 0x7fce86d08ed0)
3 params, 9 slots, 1 upvalue, 4 locals, 12 constants, 0 functions
	1	[615]	GETTABLE 	3 0 -1	; "_image_wg"
	2	[615]	TEST     	3 0 0
	3	[615]	JMP      	19	; to 23
	4	[616]	GETTABLE 	3 0 -1	; "_image_wg"
	5	[616]	SELF     	3 3 -4	; "getPanByCenterRatio"
	6	[616]	GETTABLE 	5 2 -5	; "pos"
	7	[616]	GETTABLE 	5 5 -6	; "x"
	8	[616]	GETUPVAL 	6 0	; Screen
	9	[616]	SELF     	6 6 -7	; "getWidth"
	10	[616]	CALL     	6 2 2
	11	[616]	DIV      	6 6 -8	; - 2
	12	[616]	SUB      	5 5 6
	13	[616]	GETTABLE 	6 2 -5	; "pos"
	14	[616]	GETTABLE 	6 6 -9	; "y"
	15	[616]	GETUPVAL 	7 0	; Screen
	16	[616]	SELF     	7 7 -10	; "getHeight"
	17	[616]	CALL     	7 2 2
	18	[616]	DIV      	7 7 -8	; - 2
	19	[616]	SUB      	6 6 7
	20	[616]	CALL     	3 4 3
	21	[616]	SETTABLE 	0 -3 4	; "_center_y_ratio" -
	22	[616]	SETTABLE 	0 -2 3	; "_center_x_ratio" -
	23	[619]	GETTABLE 	3 2 -11	; "distance"
	24	[619]	GETUPVAL 	4 0	; Screen
	25	[619]	SELF     	4 4 -7	; "getWidth"
	26	[619]	CALL     	4 2 2
	27	[619]	DIV      	3 3 4
	28	[620]	SELF     	4 0 -12	; "onZoomIn"
	29	[620]	MOVE     	6 3
	30	[620]	CALL     	4 3 1
	31	[621]	LOADBOOL 	4 1 0
	32	[621]	RETURN   	4 2
	33	[622]	RETURN   	0 1

function <./frontend/ui/widget/imageviewer.lua:624,630> (11 instructions, 44 bytes at 0x7fce86d09290)
3 params, 7 slots, 1 upvalue, 4 locals, 3 constants, 0 functions
	1	[627]	GETTABLE 	3 2 -1	; "distance"
	2	[627]	GETUPVAL 	4 0	; Screen
	3	[627]	SELF     	4 4 -2	; "getWidth"
	4	[627]	CALL     	4 2 2
	5	[627]	DIV      	3 3 4
	6	[628]	SELF     	4 0 -3	; "onZoomOut"
	7	[628]	MOVE     	6 3
	8	[628]	CALL     	4 3 1
	9	[629]	LOADBOOL 	4 1 0
	10	[629]	RETURN   	4 2
	11	[630]	RETURN   	0 1

function <./frontend/ui/widget/imageviewer.lua:632,635> (7 instructions, 28 bytes at 0x7fce86d09620)
1 param, 4 slots, 1 upvalue, 1 local, 1 constant, 0 functions
	1	[633]	GETUPVAL 	1 0	; UIManager
	2	[633]	SELF     	1 1 -1	; "close"
	3	[633]	MOVE     	3 0
	4	[633]	CALL     	1 3 1
	5	[634]	LOADBOOL 	1 1 0
	6	[634]	RETURN   	1 2
	7	[635]	RETURN   	0 1

function <./frontend/ui/widget/imageviewer.lua:637,640> (5 instructions, 20 bytes at 0x7fce86d075b0)
1 param, 3 slots, 0 upvalues, 1 local, 1 constant, 0 functions
	1	[638]	SELF     	1 0 -1	; "onClose"
	2	[638]	CALL     	1 2 1
	3	[639]	LOADBOOL 	1 1 0
	4	[639]	RETURN   	1 2
	5	[640]	RETURN   	0 1

function <./frontend/ui/widget/imageviewer.lua:642,659> (42 instructions, 168 bytes at 0x7fce86d09eb0)
1 param, 5 slots, 2 upvalues, 1 local, 10 constants, 1 function
	1	[644]	SELF     	1 0 -1	; "_clean_image_wg"
	2	[644]	CALL     	1 2 1
	3	[645]	GETTABLE 	1 0 -2	; "image"
	4	[645]	TEST     	1 0 0
	5	[645]	JMP      	15	; to 21
	6	[645]	GETTABLE 	1 0 -3	; "image_disposable"
	7	[645]	TEST     	1 0 0
	8	[645]	JMP      	12	; to 21
	9	[645]	GETTABLE 	1 0 -2	; "image"
	10	[645]	GETTABLE 	1 1 -4	; "free"
	11	[645]	TEST     	1 0 0
	12	[645]	JMP      	8	; to 21
	13	[646]	GETUPVAL 	1 0	; logger
	14	[646]	GETTABLE 	1 1 -5	; "dbg"
	15	[646]	LOADK    	2 -6	; "ImageViewer:free(self.image)"
	16	[646]	CALL     	1 2 1
	17	[647]	GETTABLE 	1 0 -2	; "image"
	18	[647]	SELF     	1 1 -4	; "free"
	19	[647]	CALL     	1 2 1
	20	[648]	SETTABLE 	0 -2 -7	; "image" nil
	21	[651]	GETTABLE 	1 0 -8	; "_images_list"
	22	[651]	TEST     	1 0 0
	23	[651]	JMP      	10	; to 34
	24	[651]	GETTABLE 	1 0 -9	; "_images_list_disposable"
	25	[651]	TEST     	1 0 0
	26	[651]	JMP      	7	; to 34
	27	[651]	GETTABLE 	1 0 -8	; "_images_list"
	28	[651]	GETTABLE 	1 1 -4	; "free"
	29	[651]	TEST     	1 0 0
	30	[651]	JMP      	3	; to 34
	31	[652]	GETTABLE 	1 0 -8	; "_images_list"
	32	[652]	GETTABLE 	1 1 -4	; "free"
	33	[652]	CALL     	1 1 1
	34	[655]	GETUPVAL 	1 1	; UIManager
	35	[655]	SELF     	1 1 -10	; "setDirty"
	36	[655]	LOADNIL  	3 3
	37	[657]	CLOSURE  	4 0	; 0x7fce86d0a240
	38	[657]	MOVE     	0 0
	39	[655]	CALL     	1 4 1
	40	[658]	LOADBOOL 	1 1 0
	41	[658]	RETURN   	1 2
	42	[659]	RETURN   	0 1

function <./frontend/ui/widget/imageviewer.lua:655,657> (6 instructions, 24 bytes at 0x7fce86d0a240)
0 params, 2 slots, 1 upvalue, 0 locals, 3 constants, 0 functions
	1	[656]	LOADK    	0 -1	; "flashui"
	2	[656]	GETUPVAL 	1 0	; self
	3	[656]	GETTABLE 	1 1 -2	; "main_frame"
	4	[656]	GETTABLE 	1 1 -3	; "dimen"
	5	[656]	RETURN   	0 3
	6	[657]	RETURN   	0 1
