
main <./frontend/ui/widget/infomessage.lua:0,0> (109 instructions, 436 bytes at 0x7f89d8c068d0)
0+ params, 26 slots, 0 upvalues, 21 locals, 46 constants, 6 functions
	1	[25]	GETGLOBAL	0 -1	; require
	2	[25]	LOADK    	1 -2	; "ffi/blitbuffer"
	3	[25]	CALL     	0 2 2
	4	[26]	GETGLOBAL	1 -1	; require
	5	[26]	LOADK    	2 -3	; "ui/widget/container/centercontainer"
	6	[26]	CALL     	1 2 2
	7	[27]	GETGLOBAL	2 -1	; require
	8	[27]	LOADK    	3 -4	; "device"
	9	[27]	CALL     	2 2 2
	10	[28]	GETGLOBAL	3 -1	; require
	11	[28]	LOADK    	4 -5	; "ui/font"
	12	[28]	CALL     	3 2 2
	13	[29]	GETGLOBAL	4 -1	; require
	14	[29]	LOADK    	5 -6	; "ui/widget/container/framecontainer"
	15	[29]	CALL     	4 2 2
	16	[30]	GETGLOBAL	5 -1	; require
	17	[30]	LOADK    	6 -7	; "ui/geometry"
	18	[30]	CALL     	5 2 2
	19	[31]	GETGLOBAL	6 -1	; require
	20	[31]	LOADK    	7 -8	; "ui/gesturerange"
	21	[31]	CALL     	6 2 2
	22	[32]	GETGLOBAL	7 -1	; require
	23	[32]	LOADK    	8 -9	; "ui/widget/horizontalgroup"
	24	[32]	CALL     	7 2 2
	25	[33]	GETGLOBAL	8 -1	; require
	26	[33]	LOADK    	9 -10	; "ui/widget/horizontalspan"
	27	[33]	CALL     	8 2 2
	28	[34]	GETGLOBAL	9 -1	; require
	29	[34]	LOADK    	10 -11	; "ui/widget/imagewidget"
	30	[34]	CALL     	9 2 2
	31	[35]	GETGLOBAL	10 -1	; require
	32	[35]	LOADK    	11 -12	; "ui/widget/container/inputcontainer"
	33	[35]	CALL     	10 2 2
	34	[36]	GETGLOBAL	11 -1	; require
	35	[36]	LOADK    	12 -13	; "ui/widget/container/movablecontainer"
	36	[36]	CALL     	11 2 2
	37	[37]	GETGLOBAL	12 -1	; require
	38	[37]	LOADK    	13 -14	; "ui/widget/scrolltextwidget"
	39	[37]	CALL     	12 2 2
	40	[38]	GETGLOBAL	13 -1	; require
	41	[38]	LOADK    	14 -15	; "ui/size"
	42	[38]	CALL     	13 2 2
	43	[39]	GETGLOBAL	14 -1	; require
	44	[39]	LOADK    	15 -16	; "ui/widget/textboxwidget"
	45	[39]	CALL     	14 2 2
	46	[40]	GETGLOBAL	15 -1	; require
	47	[40]	LOADK    	16 -17	; "ui/uimanager"
	48	[40]	CALL     	15 2 2
	49	[41]	GETGLOBAL	16 -1	; require
	50	[41]	LOADK    	17 -18	; "ui/widget/container/widgetcontainer"
	51	[41]	CALL     	16 2 2
	52	[42]	GETGLOBAL	17 -1	; require
	53	[42]	LOADK    	18 -19	; "gettext"
	54	[42]	CALL     	17 2 2
	55	[43]	GETTABLE 	18 2 -20	; "input"
	56	[44]	GETTABLE 	19 2 -21	; "screen"
	57	[46]	SELF     	20 10 -22	; "new"
	58	[46]	NEWTABLE 	22 0 13
	59	[47]	SETTABLE 	22 -23 -24	; "modal" true
	60	[48]	SELF     	23 3 -26	; "getFace"
	61	[48]	LOADK    	25 -27	; "infofont"
	62	[48]	CALL     	23 3 2
	63	[48]	SETTABLE 	22 -25 23	; "face" -
	64	[49]	SETTABLE 	22 -28 -29	; "text" ""
	65	[50]	SETTABLE 	22 -30 -31	; "timeout" nil
	66	[51]	SETTABLE 	22 -32 -31	; "width" nil
	67	[52]	SETTABLE 	22 -33 -31	; "height" nil
	68	[55]	SETTABLE 	22 -34 -31	; "image" nil
	69	[56]	SETTABLE 	22 -35 -31	; "image_width" nil
	70	[57]	SETTABLE 	22 -36 -31	; "image_height" nil
	71	[59]	SETTABLE 	22 -37 -24	; "show_icon" true
	72	[60]	SETTABLE 	22 -38 -31	; "icon_file" nil
	73	[61]	SETTABLE 	22 -39 -40	; "alpha" false
	74	[62]	CLOSURE  	23 0	; 0x7f89d8c070a0
	75	[62]	SETTABLE 	22 -41 23	; "dismiss_callback" -
	76	[46]	CALL     	20 3 2
	77	[174]	CLOSURE  	21 1	; 0x7f89d8c072d0
	78	[174]	MOVE     	0 2
	79	[174]	MOVE     	0 18
	80	[174]	MOVE     	0 6
	81	[174]	MOVE     	0 5
	82	[174]	MOVE     	0 19
	83	[174]	MOVE     	0 9
	84	[174]	MOVE     	0 16
	85	[174]	MOVE     	0 12
	86	[174]	MOVE     	0 14
	87	[174]	MOVE     	0 4
	88	[174]	MOVE     	0 0
	89	[174]	MOVE     	0 7
	90	[174]	MOVE     	0 8
	91	[174]	MOVE     	0 13
	92	[174]	MOVE     	0 11
	93	[174]	MOVE     	0 1
	94	[174]	MOVE     	0 3
	95	[65]	SETTABLE 	20 -42 21	; "init" -
	96	[181]	CLOSURE  	21 2	; 0x7f89d8c07f80
	97	[181]	MOVE     	0 15
	98	[176]	SETTABLE 	20 -43 21	; "onCloseWidget" -
	99	[192]	CLOSURE  	21 3	; 0x7f89d8c08850
	100	[192]	MOVE     	0 15
	101	[183]	SETTABLE 	20 -44 21	; "onShow" -
	102	[201]	CLOSURE  	21 4	; 0x7f89d8c09440
	103	[201]	MOVE     	0 15
	104	[194]	SETTABLE 	20 -45 21	; "onAnyKeyPressed" -
	105	[209]	CLOSURE  	21 5	; 0x7f89d8c095c0
	106	[209]	MOVE     	0 15
	107	[203]	SETTABLE 	20 -46 21	; "onTapClose" -
	108	[211]	RETURN   	20 2
	109	[211]	RETURN   	0 1

function <./frontend/ui/widget/infomessage.lua:62,62> (1 instruction, 4 bytes at 0x7f89d8c070a0)
0 params, 2 slots, 0 upvalues, 0 locals, 0 constants, 0 functions
	1	[62]	RETURN   	0 1

function <./frontend/ui/widget/infomessage.lua:65,174> (219 instructions, 876 bytes at 0x7f89d8c072d0)
1 param, 15 slots, 17 upvalues, 9 locals, 59 constants, 0 functions
	1	[66]	GETUPVAL 	1 0	; Device
	2	[66]	SELF     	1 1 -1	; "hasKeys"
	3	[66]	CALL     	1 2 2
	4	[66]	TEST     	1 0 0
	5	[66]	JMP      	12	; to 18
	6	[67]	NEWTABLE 	1 0 1
	7	[68]	NEWTABLE 	2 1 2
	8	[68]	NEWTABLE 	3 1 0
	9	[68]	GETUPVAL 	4 1	; Input
	10	[68]	GETTABLE 	4 4 -4	; "group"
	11	[68]	GETTABLE 	4 4 -5	; "Any"
	12	[68]	SETLIST  	3 1 1	; 1
	13	[69]	SETTABLE 	2 -6 -7	; "seqtext" "any key"
	14	[69]	SETTABLE 	2 -8 -9	; "doc" "close dialog"
	15	[69]	SETLIST  	2 1 1	; 1
	16	[69]	SETTABLE 	1 -3 2	; "AnyKeyPressed" -
	17	[70]	SETTABLE 	0 -2 1	; "key_events" -
	18	[72]	GETUPVAL 	1 0	; Device
	19	[72]	SELF     	1 1 -10	; "isTouchDevice"
	20	[72]	CALL     	1 2 2
	21	[72]	TEST     	1 0 0
	22	[72]	JMP      	24	; to 47
	23	[73]	GETTABLE 	1 0 -11	; "ges_events"
	24	[73]	NEWTABLE 	2 0 0
	25	[74]	GETUPVAL 	3 2	; GestureRange
	26	[74]	SELF     	3 3 -13	; "new"
	27	[74]	NEWTABLE 	5 0 2
	28	[75]	SETTABLE 	5 -14 -15	; "ges" "tap"
	29	[76]	GETUPVAL 	6 3	; Geom
	30	[76]	SELF     	6 6 -13	; "new"
	31	[76]	NEWTABLE 	8 0 4
	32	[77]	SETTABLE 	8 -17 -18	; "x" 0
	33	[77]	SETTABLE 	8 -19 -18	; "y" 0
	34	[78]	GETUPVAL 	9 4	; Screen
	35	[78]	SELF     	9 9 -21	; "getWidth"
	36	[78]	CALL     	9 2 2
	37	[78]	SETTABLE 	8 -20 9	; "w" -
	38	[79]	GETUPVAL 	9 4	; Screen
	39	[79]	SELF     	9 9 -23	; "getHeight"
	40	[79]	CALL     	9 2 2
	41	[79]	SETTABLE 	8 -22 9	; "h" -
	42	[76]	CALL     	6 3 2
	43	[80]	SETTABLE 	5 -16 6	; "range" -
	44	[74]	CALL     	3 3 0
	45	[82]	SETLIST  	2 0 1	; 1
	46	[82]	SETTABLE 	1 -12 2	; "TapClose" -
	47	[85]	LOADNIL  	1 1
	48	[86]	GETTABLE 	2 0 -24	; "show_icon"
	49	[86]	TEST     	2 0 0
	50	[86]	JMP      	31	; to 82
	51	[90]	GETTABLE 	2 0 -25	; "image"
	52	[90]	TEST     	2 0 0
	53	[90]	JMP      	14	; to 68
	54	[91]	GETUPVAL 	2 5	; ImageWidget
	55	[91]	SELF     	2 2 -13	; "new"
	56	[91]	NEWTABLE 	4 0 4
	57	[92]	GETTABLE 	5 0 -25	; "image"
	58	[92]	SETTABLE 	4 -25 5	; "image" -
	59	[93]	GETTABLE 	5 0 -27	; "image_width"
	60	[93]	SETTABLE 	4 -26 5	; "width" -
	61	[94]	GETTABLE 	5 0 -29	; "image_height"
	62	[94]	SETTABLE 	4 -28 5	; "height" -
	63	[95]	GETTABLE 	5 0 -30	; "alpha"
	64	[95]	SETTABLE 	4 -30 5	; "alpha" -
	65	[91]	CALL     	2 3 2
	66	[96]	MOVE     	1 2
	67	[96]	JMP      	18	; to 86
	68	[98]	GETUPVAL 	2 5	; ImageWidget
	69	[98]	SELF     	2 2 -13	; "new"
	70	[98]	NEWTABLE 	4 0 3
	71	[99]	GETTABLE 	5 0 -32	; "icon_file"
	72	[99]	TEST     	5 0 1
	73	[99]	JMP      	1	; to 75
	74	[99]	LOADK    	5 -33	; "resources/info-i.png"
	75	[99]	SETTABLE 	4 -31 5	; "file" -
	76	[100]	SETTABLE 	4 -34 -35	; "scale_for_dpi" true
	77	[101]	GETTABLE 	5 0 -30	; "alpha"
	78	[101]	SETTABLE 	4 -30 5	; "alpha" -
	79	[98]	CALL     	2 3 2
	80	[102]	MOVE     	1 2
	81	[103]	JMP      	4	; to 86
	82	[105]	GETUPVAL 	2 6	; WidgetContainer
	83	[105]	SELF     	2 2 -13	; "new"
	84	[105]	CALL     	2 2 2
	85	[105]	MOVE     	1 2
	86	[108]	LOADNIL  	2 2
	87	[109]	GETTABLE 	3 0 -26	; "width"
	88	[109]	EQ       	0 3 -36	; - nil
	89	[109]	JMP      	6	; to 96
	90	[110]	GETUPVAL 	3 4	; Screen
	91	[110]	SELF     	3 3 -21	; "getWidth"
	92	[110]	CALL     	3 2 2
	93	[110]	MUL      	3 3 -37	; - 2
	94	[110]	DIV      	2 3 -38	; - 3
	95	[110]	JMP      	8	; to 104
	96	[112]	GETTABLE 	3 0 -26	; "width"
	97	[112]	SELF     	4 1 -39	; "getSize"
	98	[112]	CALL     	4 2 2
	99	[112]	GETTABLE 	4 4 -20	; "w"
	100	[112]	SUB      	2 3 4
	101	[113]	LT       	0 2 -18	; - 0
	102	[113]	JMP      	1	; to 104
	103	[114]	LOADK    	2 -18	; 0
	104	[118]	LOADNIL  	3 3
	105	[119]	GETTABLE 	4 0 -28	; "height"
	106	[119]	TEST     	4 0 0
	107	[119]	JMP      	14	; to 122
	108	[120]	GETUPVAL 	4 7	; ScrollTextWidget
	109	[120]	SELF     	4 4 -13	; "new"
	110	[120]	NEWTABLE 	6 0 5
	111	[121]	GETTABLE 	7 0 -40	; "text"
	112	[121]	SETTABLE 	6 -40 7	; "text" -
	113	[122]	GETTABLE 	7 0 -41	; "face"
	114	[122]	SETTABLE 	6 -41 7	; "face" -
	115	[123]	SETTABLE 	6 -26 2	; "width" -
	116	[124]	GETTABLE 	7 0 -28	; "height"
	117	[124]	SETTABLE 	6 -28 7	; "height" -
	118	[125]	SETTABLE 	6 -42 0	; "dialog" -
	119	[120]	CALL     	4 3 2
	120	[126]	MOVE     	3 4
	121	[126]	JMP      	10	; to 132
	122	[128]	GETUPVAL 	4 8	; TextBoxWidget
	123	[128]	SELF     	4 4 -13	; "new"
	124	[128]	NEWTABLE 	6 0 3
	125	[129]	GETTABLE 	7 0 -40	; "text"
	126	[129]	SETTABLE 	6 -40 7	; "text" -
	127	[130]	GETTABLE 	7 0 -41	; "face"
	128	[130]	SETTABLE 	6 -41 7	; "face" -
	129	[131]	SETTABLE 	6 -26 2	; "width" -
	130	[128]	CALL     	4 3 2
	131	[132]	MOVE     	3 4
	132	[134]	GETUPVAL 	4 9	; FrameContainer
	133	[134]	SELF     	4 4 -13	; "new"
	134	[134]	NEWTABLE 	6 0 1
	135	[135]	GETUPVAL 	7 10	; Blitbuffer
	136	[135]	GETTABLE 	7 7 -44	; "COLOR_WHITE"
	137	[135]	SETTABLE 	6 -43 7	; "background" -
	138	[136]	GETUPVAL 	7 11	; HorizontalGroup
	139	[136]	SELF     	7 7 -13	; "new"
	140	[136]	NEWTABLE 	9 3 1
	141	[137]	SETTABLE 	9 -45 -46	; "align" "center"
	142	[138]	MOVE     	10 1
	143	[139]	GETUPVAL 	11 12	; HorizontalSpan
	144	[139]	SELF     	11 11 -13	; "new"
	145	[139]	NEWTABLE 	13 0 1
	146	[139]	GETTABLE 	14 0 -24	; "show_icon"
	147	[139]	TEST     	14 0 0
	148	[139]	JMP      	5	; to 154
	149	[139]	GETUPVAL 	14 13	; Size
	150	[139]	GETTABLE 	14 14 -47	; "span"
	151	[139]	GETTABLE 	14 14 -48	; "horizontal_default"
	152	[139]	TEST     	14 0 1
	153	[139]	JMP      	1	; to 155
	154	[139]	LOADK    	14 -18	; 0
	155	[139]	SETTABLE 	13 -26 14	; "width" -
	156	[139]	CALL     	11 3 2
	157	[141]	MOVE     	12 3
	158	[141]	SETLIST  	9 3 1	; 1
	159	[136]	CALL     	7 3 0
	160	[142]	SETLIST  	6 0 1	; 1
	161	[134]	CALL     	4 3 2
	162	[143]	GETUPVAL 	5 14	; MovableContainer
	163	[143]	SELF     	5 5 -13	; "new"
	164	[143]	NEWTABLE 	7 1 0
	165	[145]	MOVE     	8 4
	166	[145]	SETLIST  	7 1 1	; 1
	167	[143]	CALL     	5 3 2
	168	[145]	SETTABLE 	0 -49 5	; "movable" -
	169	[146]	GETUPVAL 	5 15	; CenterContainer
	170	[146]	SELF     	5 5 -13	; "new"
	171	[146]	NEWTABLE 	7 1 1
	172	[147]	GETUPVAL 	8 4	; Screen
	173	[147]	SELF     	8 8 -39	; "getSize"
	174	[147]	CALL     	8 2 2
	175	[147]	SETTABLE 	7 -51 8	; "dimen" -
	176	[149]	GETTABLE 	8 0 -49	; "movable"
	177	[149]	SETLIST  	7 1 1	; 1
	178	[146]	CALL     	5 3 2
	179	[149]	SETTABLE 	0 -50 5	; 1 -
	180	[150]	GETTABLE 	5 0 -28	; "height"
	181	[150]	TEST     	5 0 1
	182	[150]	JMP      	36	; to 219
	183	[152]	SELF     	5 4 -39	; "getSize"
	184	[152]	CALL     	5 2 2
	185	[153]	TEST     	5 0 0
	186	[153]	JMP      	32	; to 219
	187	[153]	GETTABLE 	6 5 -22	; "h"
	188	[153]	GETUPVAL 	7 4	; Screen
	189	[153]	SELF     	7 7 -23	; "getHeight"
	190	[153]	CALL     	7 2 2
	191	[153]	MUL      	7 -52 7	; 0.95 -
	192	[153]	LT       	0 7 6
	193	[153]	JMP      	25	; to 219
	194	[154]	GETTABLE 	6 3 -41	; "face"
	195	[154]	GETTABLE 	6 6 -53	; "orig_font"
	196	[155]	GETTABLE 	7 3 -41	; "face"
	197	[155]	GETTABLE 	7 7 -54	; "orig_size"
	198	[156]	GETTABLE 	8 3 -41	; "face"
	199	[156]	GETTABLE 	8 8 -55	; "size"
	200	[157]	LT       	0 -56 7	; 10 -
	201	[157]	JMP      	17	; to 219
	202	[159]	SUB      	7 7 -50	; - 1
	203	[160]	GETUPVAL 	9 16	; Font
	204	[160]	SELF     	9 9 -57	; "getFace"
	205	[160]	MOVE     	11 6
	206	[160]	MOVE     	12 7
	207	[160]	CALL     	9 4 2
	208	[160]	SETTABLE 	0 -41 9	; "face" -
	209	[164]	GETTABLE 	9 0 -41	; "face"
	210	[164]	GETTABLE 	9 9 -55	; "size"
	211	[164]	LT       	0 9 8
	212	[164]	JMP      	-11	; to 202
	213	[165]	JMP      	1	; to 215
	214	[166]	JMP      	-13	; to 202
	215	[169]	SELF     	9 0 -58	; "free"
	216	[169]	CALL     	9 2 1
	217	[170]	SELF     	9 0 -59	; "init"
	218	[170]	CALL     	9 2 1
	219	[174]	RETURN   	0 1

function <./frontend/ui/widget/infomessage.lua:176,181> (9 instructions, 36 bytes at 0x7f89d8c07f80)
1 param, 5 slots, 1 upvalue, 1 local, 1 constant, 1 function
	1	[177]	GETUPVAL 	1 0	; UIManager
	2	[177]	SELF     	1 1 -1	; "setDirty"
	3	[177]	LOADNIL  	3 3
	4	[179]	CLOSURE  	4 0	; 0x7f89d8c08570
	5	[179]	MOVE     	0 0
	6	[177]	CALL     	1 4 1
	7	[180]	LOADBOOL 	1 1 0
	8	[180]	RETURN   	1 2
	9	[181]	RETURN   	0 1

function <./frontend/ui/widget/infomessage.lua:177,179> (7 instructions, 28 bytes at 0x7f89d8c08570)
0 params, 2 slots, 1 upvalue, 0 locals, 3 constants, 0 functions
	1	[178]	LOADK    	0 -1	; "ui"
	2	[178]	GETUPVAL 	1 0	; self
	3	[178]	GETTABLE 	1 1 -2	; 1
	4	[178]	GETTABLE 	1 1 -2	; 1
	5	[178]	GETTABLE 	1 1 -3	; "dimen"
	6	[178]	RETURN   	0 3
	7	[179]	RETURN   	0 1

function <./frontend/ui/widget/infomessage.lua:183,192> (19 instructions, 76 bytes at 0x7f89d8c08850)
1 param, 5 slots, 1 upvalue, 1 local, 3 constants, 2 functions
	1	[185]	GETUPVAL 	1 0	; UIManager
	2	[185]	SELF     	1 1 -1	; "setDirty"
	3	[185]	MOVE     	3 0
	4	[187]	CLOSURE  	4 0	; 0x7f89d8c08bd0
	5	[187]	MOVE     	0 0
	6	[185]	CALL     	1 4 1
	7	[188]	GETTABLE 	1 0 -2	; "timeout"
	8	[188]	TEST     	1 0 0
	9	[188]	JMP      	7	; to 17
	10	[189]	GETUPVAL 	1 0	; UIManager
	11	[189]	SELF     	1 1 -3	; "scheduleIn"
	12	[189]	GETTABLE 	3 0 -2	; "timeout"
	13	[189]	CLOSURE  	4 1	; 0x7f89d8c08d50
	14	[189]	GETUPVAL 	0 0	; UIManager
	15	[189]	MOVE     	0 0
	16	[189]	CALL     	1 4 1
	17	[191]	LOADBOOL 	1 1 0
	18	[191]	RETURN   	1 2
	19	[192]	RETURN   	0 1

function <./frontend/ui/widget/infomessage.lua:185,187> (7 instructions, 28 bytes at 0x7f89d8c08bd0)
0 params, 2 slots, 1 upvalue, 0 locals, 3 constants, 0 functions
	1	[186]	LOADK    	0 -1	; "ui"
	2	[186]	GETUPVAL 	1 0	; self
	3	[186]	GETTABLE 	1 1 -2	; 1
	4	[186]	GETTABLE 	1 1 -2	; 1
	5	[186]	GETTABLE 	1 1 -3	; "dimen"
	6	[186]	RETURN   	0 3
	7	[187]	RETURN   	0 1

function <./frontend/ui/widget/infomessage.lua:189,189> (5 instructions, 20 bytes at 0x7f89d8c08d50)
0 params, 3 slots, 2 upvalues, 0 locals, 1 constant, 0 functions
	1	[189]	GETUPVAL 	0 0	; UIManager
	2	[189]	SELF     	0 0 -1	; "close"
	3	[189]	GETUPVAL 	2 1	; self
	4	[189]	CALL     	0 3 1
	5	[189]	RETURN   	0 1

function <./frontend/ui/widget/infomessage.lua:194,201> (12 instructions, 48 bytes at 0x7f89d8c09440)
1 param, 4 slots, 1 upvalue, 1 local, 4 constants, 0 functions
	1	[196]	GETTABLE 	1 0 -1	; "dismiss_callback"
	2	[196]	CALL     	1 1 1
	3	[197]	GETUPVAL 	1 0	; UIManager
	4	[197]	SELF     	1 1 -2	; "close"
	5	[197]	MOVE     	3 0
	6	[197]	CALL     	1 3 1
	7	[198]	GETTABLE 	1 0 -3	; "readonly"
	8	[198]	EQ       	1 1 -4	; - true
	9	[198]	JMP      	2	; to 12
	10	[199]	LOADBOOL 	1 1 0
	11	[199]	RETURN   	1 2
	12	[201]	RETURN   	0 1

function <./frontend/ui/widget/infomessage.lua:203,209> (12 instructions, 48 bytes at 0x7f89d8c095c0)
1 param, 4 slots, 1 upvalue, 1 local, 4 constants, 0 functions
	1	[204]	GETTABLE 	1 0 -1	; "dismiss_callback"
	2	[204]	CALL     	1 1 1
	3	[205]	GETUPVAL 	1 0	; UIManager
	4	[205]	SELF     	1 1 -2	; "close"
	5	[205]	MOVE     	3 0
	6	[205]	CALL     	1 3 1
	7	[206]	GETTABLE 	1 0 -3	; "readonly"
	8	[206]	EQ       	1 1 -4	; - true
	9	[206]	JMP      	2	; to 12
	10	[207]	LOADBOOL 	1 1 0
	11	[207]	RETURN   	1 2
	12	[209]	RETURN   	0 1
