-- BYTECODE -- infomessage.lua:62-62
0001    RET0     0   1

-- BYTECODE -- infomessage.lua:65-174
0001    UGET     1   0      ; Device
0002    MOV      2   1
0003    TGETS    1   1   0  ; "hasKeys"
0004    CALL     1   2   2
0005    ISF          1
0006    JMP      2 => 0017
0007    TDUP     1   5
0008    TDUP     2   4
0009    TNEW     3   3
0010    UGET     4   1      ; Input
0011    TGETS    4   4   2  ; "group"
0012    TGETS    4   4   3  ; "Any"
0013    TSETB    4   3   1
0014    TSETB    3   2   1
0015    TSETS    2   1   6  ; "AnyKeyPressed"
0016    TSETS    1   0   1  ; "key_events"
0017 => UGET     1   0      ; Device
0018    MOV      2   1
0019    TGETS    1   1   7  ; "isTouchDevice"
0020    CALL     1   2   2
0021    ISF          1
0022    JMP      2 => 0048
0023    TGETS    1   0   8  ; "ges_events"
0024    TNEW     2   3
0025    UGET     3   2      ; GestureRange
0026    MOV      4   3
0027    TGETS    3   3  10  ; "new"
0028    TDUP     5  11
0029    UGET     6   3      ; Geom
0030    MOV      7   6
0031    TGETS    6   6  10  ; "new"
0032    TDUP     8  12
0033    UGET     9   4      ; Screen
0034    MOV     10   9
0035    TGETS    9   9  13  ; "getWidth"
0036    CALL     9   2   2
0037    TSETS    9   8  14  ; "w"
0038    UGET     9   4      ; Screen
0039    MOV     10   9
0040    TGETS    9   9  15  ; "getHeight"
0041    CALL     9   2   2
0042    TSETS    9   8  16  ; "h"
0043    CALL     6   2   3
0044    TSETS    6   5  17  ; "range"
0045    CALL     3   0   3
0046    TSETM    3   0      ; 1
0047    TSETS    2   1   9  ; "TapClose"
0048 => KPRI     1   0
0049    TGETS    2   0  18  ; "show_icon"
0050    ISF          2
0051    JMP      3 => 0084
0052    TGETS    2   0  19  ; "image"
0053    ISF          2
0054    JMP      3 => 0070
0055    UGET     2   5      ; ImageWidget
0056    MOV      3   2
0057    TGETS    2   2  10  ; "new"
0058    TDUP     4  20
0059    TGETS    5   0  19  ; "image"
0060    TSETS    5   4  19  ; "image"
0061    TGETS    5   0  21  ; "image_width"
0062    TSETS    5   4  22  ; "width"
0063    TGETS    5   0  23  ; "image_height"
0064    TSETS    5   4  24  ; "height"
0065    TGETS    5   0  25  ; "alpha"
0066    TSETS    5   4  25  ; "alpha"
0067    CALL     2   2   3
0068    MOV      1   2
0069    JMP      2 => 0089
0070 => UGET     2   5      ; ImageWidget
0071    MOV      3   2
0072    TGETS    2   2  10  ; "new"
0073    TDUP     4  27
0074    TGETS    5   0  26  ; "icon_file"
0075    IST          5
0076    JMP      6 => 0078
0077    KSTR     5  28      ; "resources/info-i.png"
0078 => TSETS    5   4  29  ; "file"
0079    TGETS    5   0  25  ; "alpha"
0080    TSETS    5   4  25  ; "alpha"
0081    CALL     2   2   3
0082    MOV      1   2
0083    JMP      2 => 0089
0084 => UGET     2   6      ; WidgetContainer
0085    MOV      3   2
0086    TGETS    2   2  10  ; "new"
0087    CALL     2   2   2
0088    MOV      1   2
0089 => KPRI     2   0
0090    TGETS    3   0  22  ; "width"
0091    ISNEP    3   0
0092    JMP      3 => 0100
0093    UGET     3   4      ; Screen
0094    MOV      4   3
0095    TGETS    3   3  13  ; "getWidth"
0096    CALL     3   2   2
0097    MULVN    3   3   1  ; 2
0098    DIVVN    2   3   2  ; 3
0099    JMP      3 => 0110
0100 => TGETS    3   0  22  ; "width"
0101    MOV      5   1
0102    TGETS    4   1  30  ; "getSize"
0103    CALL     4   2   2
0104    TGETS    4   4  14  ; "w"
0105    SUBVV    2   3   4
0106    KSHORT   3   0
0107    ISGE     2   3
0108    JMP      3 => 0110
0109    KSHORT   2   0
0110 => KPRI     3   0
0111    TGETS    4   0  24  ; "height"
0112    ISF          4
0113    JMP      5 => 0129
0114    UGET     4   7      ; ScrollTextWidget
0115    MOV      5   4
0116    TGETS    4   4  10  ; "new"
0117    TDUP     6  32
0118    TGETS    7   0  31  ; "text"
0119    TSETS    7   6  31  ; "text"
0120    TGETS    7   0  33  ; "face"
0121    TSETS    7   6  33  ; "face"
0122    TSETS    2   6  22  ; "width"
0123    TGETS    7   0  24  ; "height"
0124    TSETS    7   6  24  ; "height"
0125    TSETS    0   6  34  ; "dialog"
0126    CALL     4   2   3
0127    MOV      3   4
0128    JMP      4 => 0140
0129 => UGET     4   8      ; TextBoxWidget
0130    MOV      5   4
0131    TGETS    4   4  10  ; "new"
0132    TDUP     6  35
0133    TGETS    7   0  31  ; "text"
0134    TSETS    7   6  31  ; "text"
0135    TGETS    7   0  33  ; "face"
0136    TSETS    7   6  33  ; "face"
0137    TSETS    2   6  22  ; "width"
0138    CALL     4   2   3
0139    MOV      3   4
0140 => UGET     4   9      ; FrameContainer
0141    MOV      5   4
0142    TGETS    4   4  10  ; "new"
0143    TDUP     6  37
0144    UGET     7  10      ; Blitbuffer
0145    TGETS    7   7  36  ; "COLOR_WHITE"
0146    TSETS    7   6  38  ; "background"
0147    UGET     7  11      ; HorizontalGroup
0148    MOV      8   7
0149    TGETS    7   7  10  ; "new"
0150    TDUP     9  39
0151    TSETB    1   9   1
0152    UGET    10  12      ; HorizontalSpan
0153    MOV     11  10
0154    TGETS   10  10  10  ; "new"
0155    TDUP    12  42
0156    TGETS   13   0  18  ; "show_icon"
0157    ISF         13
0158    JMP     14 => 0164
0159    UGET    13  13      ; Size
0160    TGETS   13  13  40  ; "span"
0161    TGETS   13  13  41  ; "horizontal_default"
0162    IST         13
0163    JMP     14 => 0165
0164 => KSHORT  13   0
0165 => TSETS   13  12  22  ; "width"
0166    CALL    10   2   3
0167    TSETB   10   9   2
0168    TSETB    3   9   3
0169    CALL     7   0   3
0170    TSETM    7   0      ; 1
0171    CALL     4   2   3
0172    UGET     5  14      ; MovableContainer
0173    MOV      6   5
0174    TGETS    5   5  10  ; "new"
0175    TNEW     7   3
0176    TSETB    4   7   1
0177    CALL     5   2   3
0178    TSETS    5   0  43  ; "movable"
0179    UGET     5  15      ; CenterContainer
0180    MOV      6   5
0181    TGETS    5   5  10  ; "new"
0182    TDUP     7  44
0183    UGET     8   4      ; Screen
0184    MOV      9   8
0185    TGETS    8   8  30  ; "getSize"
0186    CALL     8   2   2
0187    TSETS    8   7  45  ; "dimen"
0188    TGETS    8   0  43  ; "movable"
0189    TSETB    8   7   1
0190    CALL     5   2   3
0191    TSETB    5   0   1
0192    TGETS    5   0  24  ; "height"
0193    IST          5
0194    JMP      5 => 0238
0195    MOV      6   4
0196    TGETS    5   4  30  ; "getSize"
0197    CALL     5   2   2
0198    ISF          5
0199    JMP      6 => 0238
0200    TGETS    6   5  16  ; "h"
0201    UGET     7   4      ; Screen
0202    MOV      8   7
0203    TGETS    7   7  15  ; "getHeight"
0204    CALL     7   2   2
0205    MULNV    7   7   3  ; 0.95
0206    ISGE     7   6
0207    JMP      6 => 0238
0208    TGETS    6   3  33  ; "face"
0209    TGETS    6   6  46  ; "orig_font"
0210    TGETS    7   3  33  ; "face"
0211    TGETS    7   7  47  ; "orig_size"
0212    TGETS    8   3  33  ; "face"
0213    TGETS    8   8  48  ; "size"
0214    KSHORT   9  10
0215    ISGE     9   7
0216    JMP      9 => 0238
0217 => LOOP     9 => 0232
0218    SUBVN    7   7   4  ; 1
0219    UGET     9  16      ; Font
0220    MOV     10   9
0221    TGETS    9   9  49  ; "getFace"
0222    MOV     11   6
0223    MOV     12   7
0224    CALL     9   2   4
0225    TSETS    9   0  33  ; "face"
0226    TGETS    9   0  33  ; "face"
0227    TGETS    9   9  48  ; "size"
0228    ISGE     9   8
0229    JMP      9 => 0217
0230    JMP      9 => 0232
0231    JMP      9 => 0217
0232 => MOV     10   0
0233    TGETS    9   0  50  ; "free"
0234    CALL     9   1   2
0235    MOV     10   0
0236    TGETS    9   0  51  ; "init"
0237    CALL     9   1   2
0238 => RET0     0   1

-- BYTECODE -- infomessage.lua:177-179
0001    KSTR     0   0      ; "ui"
0002    UGET     1   0      ; self
0003    TGETB    1   1   1
0004    TGETB    1   1   1
0005    TGETS    1   1   1  ; "dimen"
0006    RET      0   3

-- BYTECODE -- infomessage.lua:176-181
0001    UGET     1   0      ; UIManager
0002    MOV      2   1
0003    TGETS    1   1   0  ; "setDirty"
0004    KPRI     3   0
0005    FNEW     4   1      ; infomessage.lua:177
0006    CALL     1   1   4
0007    KPRI     1   2
0008    UCLO     0 => 0009
0009 => RET1     1   2

-- BYTECODE -- infomessage.lua:185-187
0001    KSTR     0   0      ; "ui"
0002    UGET     1   0      ; self
0003    TGETB    1   1   1
0004    TGETB    1   1   1
0005    TGETS    1   1   1  ; "dimen"
0006    RET      0   3

-- BYTECODE -- infomessage.lua:189-189
0001    UGET     0   0      ; UIManager
0002    MOV      1   0
0003    TGETS    0   0   0  ; "close"
0004    UGET     2   1      ; self
0005    CALL     0   1   3
0006    RET0     0   1

-- BYTECODE -- infomessage.lua:183-192
0001    UGET     1   0      ; UIManager
0002    MOV      2   1
0003    TGETS    1   1   0  ; "setDirty"
0004    MOV      3   0
0005    FNEW     4   1      ; infomessage.lua:185
0006    CALL     1   1   4
0007    TGETS    1   0   2  ; "timeout"
0008    ISF          1
0009    JMP      2 => 0016
0010    UGET     1   0      ; UIManager
0011    MOV      2   1
0012    TGETS    1   1   3  ; "scheduleIn"
0013    TGETS    3   0   2  ; "timeout"
0014    FNEW     4   4      ; infomessage.lua:189
0015    CALL     1   1   4
0016 => KPRI     1   2
0017    UCLO     0 => 0018
0018 => RET1     1   2

-- BYTECODE -- infomessage.lua:194-201
0001    TGETS    1   0   0  ; "dismiss_callback"
0002    CALL     1   1   1
0003    UGET     1   0      ; UIManager
0004    MOV      2   1
0005    TGETS    1   1   1  ; "close"
0006    MOV      3   0
0007    CALL     1   1   3
0008    TGETS    1   0   2  ; "readonly"
0009    ISEQP    1   2
0010    JMP      1 => 0013
0011    KPRI     1   2
0012    RET1     1   2
0013 => RET0     0   1

-- BYTECODE -- infomessage.lua:203-209
0001    TGETS    1   0   0  ; "dismiss_callback"
0002    CALL     1   1   1
0003    UGET     1   0      ; UIManager
0004    MOV      2   1
0005    TGETS    1   1   1  ; "close"
0006    MOV      3   0
0007    CALL     1   1   3
0008    TGETS    1   0   2  ; "readonly"
0009    ISEQP    1   2
0010    JMP      1 => 0013
0011    KPRI     1   2
0012    RET1     1   2
0013 => RET0     0   1

-- BYTECODE -- infomessage.lua:0-212
0001    GGET     0   0      ; "require"
0002    KSTR     1   1      ; "ffi/blitbuffer"
0003    CALL     0   2   2
0004    GGET     1   0      ; "require"
0005    KSTR     2   2      ; "ui/widget/container/centercontainer"
0006    CALL     1   2   2
0007    GGET     2   0      ; "require"
0008    KSTR     3   3      ; "device"
0009    CALL     2   2   2
0010    GGET     3   0      ; "require"
0011    KSTR     4   4      ; "ui/font"
0012    CALL     3   2   2
0013    GGET     4   0      ; "require"
0014    KSTR     5   5      ; "ui/widget/container/framecontainer"
0015    CALL     4   2   2
0016    GGET     5   0      ; "require"
0017    KSTR     6   6      ; "ui/geometry"
0018    CALL     5   2   2
0019    GGET     6   0      ; "require"
0020    KSTR     7   7      ; "ui/gesturerange"
0021    CALL     6   2   2
0022    GGET     7   0      ; "require"
0023    KSTR     8   8      ; "ui/widget/horizontalgroup"
0024    CALL     7   2   2
0025    GGET     8   0      ; "require"
0026    KSTR     9   9      ; "ui/widget/horizontalspan"
0027    CALL     8   2   2
0028    GGET     9   0      ; "require"
0029    KSTR    10  10      ; "ui/widget/imagewidget"
0030    CALL     9   2   2
0031    GGET    10   0      ; "require"
0032    KSTR    11  11      ; "ui/widget/container/inputcontainer"
0033    CALL    10   2   2
0034    GGET    11   0      ; "require"
0035    KSTR    12  12      ; "ui/widget/container/movablecontainer"
0036    CALL    11   2   2
0037    GGET    12   0      ; "require"
0038    KSTR    13  13      ; "ui/widget/scrolltextwidget"
0039    CALL    12   2   2
0040    GGET    13   0      ; "require"
0041    KSTR    14  14      ; "ui/size"
0042    CALL    13   2   2
0043    GGET    14   0      ; "require"
0044    KSTR    15  15      ; "ui/widget/textboxwidget"
0045    CALL    14   2   2
0046    GGET    15   0      ; "require"
0047    KSTR    16  16      ; "ui/uimanager"
0048    CALL    15   2   2
0049    GGET    16   0      ; "require"
0050    KSTR    17  17      ; "ui/widget/container/widgetcontainer"
0051    CALL    16   2   2
0052    GGET    17   0      ; "require"
0053    KSTR    18  18      ; "gettext"
0054    CALL    17   2   2
0055    TGETS   18   2  19  ; "input"
0056    TGETS   19   2  20  ; "screen"
0057    MOV     21  10
0058    TGETS   20  10  21  ; "new"
0059    TDUP    22  22
0060    MOV     24   3
0061    TGETS   23   3  23  ; "getFace"
0062    KSTR    25  24      ; "infofont"
0063    CALL    23   2   3
0064    TSETS   23  22  25  ; "face"
0065    FNEW    23  26      ; infomessage.lua:62
0066    TSETS   23  22  27  ; "dismiss_callback"
0067    CALL    20   2   3
0068    FNEW    21  29      ; infomessage.lua:65
0069    TSETS   21  20  28  ; "init"
0070    FNEW    21  31      ; infomessage.lua:176
0071    TSETS   21  20  30  ; "onCloseWidget"
0072    FNEW    21  33      ; infomessage.lua:183
0073    TSETS   21  20  32  ; "onShow"
0074    FNEW    21  35      ; infomessage.lua:194
0075    TSETS   21  20  34  ; "onAnyKeyPressed"
0076    FNEW    21  37      ; infomessage.lua:203
0077    TSETS   21  20  36  ; "onTapClose"
0078    UCLO     0 => 0079
0079 => RET1    20   2

