-- BYTECODE -- inputcontainer.lua:45-65
0001    TNEW     1   0
0002    TGETS    2   0   0  ; "key_events"
0003    ISF          2
0004    JMP      3 => 0012
0005    GGET     2   1      ; "pairs"
0006    TGETS    3   0   0  ; "key_events"
0007    CALL     2   4   2
0008    ISNEXT   5 => 0010
0009 => TSETV    6   1   5
0010 => ITERN    5   3   3
0011    ITERL    5 => 0009
0012 => TSETS    1   0   0  ; "key_events"
0013    TNEW     2   0
0014    TGETS    3   0   2  ; "ges_events"
0015    ISF          3
0016    JMP      4 => 0024
0017    GGET     3   1      ; "pairs"
0018    TGETS    4   0   2  ; "ges_events"
0019    CALL     3   4   2
0020    ISNEXT   6 => 0022
0021 => TSETV    7   2   6
0022 => ITERN    6   3   3
0023    ITERL    6 => 0021
0024 => TSETS    2   0   2  ; "ges_events"
0025    KPRI     3   0
0026    TSETS    3   0   3  ; "touch_zone_dg"
0027    TNEW     3   0
0028    TSETS    3   0   4  ; "_zones"
0029    TNEW     3   0
0030    TSETS    3   0   5  ; "_ordered_touch_zones"
0031    RET0     0   1

-- BYTECODE -- inputcontainer.lua:67-87
0001    TGETB    4   0   1
0002    ISNEP    4   0
0003    JMP      4 => 0005
0004    RET0     0   1
0005 => TGETS    4   0   0  ; "skip_paint"
0006    ISF          4
0007    JMP      5 => 0009
0008    RET0     0   1
0009 => TGETS    4   0   1  ; "dimen"
0010    IST          4
0011    JMP      4 => 0026
0012    TGETB    4   0   1
0013    MOV      5   4
0014    TGETS    4   4   2  ; "getSize"
0015    CALL     4   2   2
0016    UGET     5   0      ; Geom
0017    MOV      6   5
0018    TGETS    5   5   3  ; "new"
0019    TDUP     7   5
0020    TGETS    8   4   4  ; "w"
0021    TSETS    8   7   4  ; "w"
0022    TGETS    8   4   6  ; "h"
0023    TSETS    8   7   6  ; "h"
0024    CALL     5   2   3
0025    TSETS    5   0   1  ; "dimen"
0026 => TGETS    4   0   1  ; "dimen"
0027    TSETS    2   4   7  ; "x"
0028    TGETS    4   0   1  ; "dimen"
0029    TSETS    3   4   8  ; "y"
0030    TGETS    4   0   9  ; "vertical_align"
0031    ISNES    4  10      ; "center"
0032    JMP      4 => 0053
0033    TGETB    4   0   1
0034    MOV      5   4
0035    TGETS    4   4   2  ; "getSize"
0036    CALL     4   2   2
0037    TGETB    5   0   1
0038    MOV      6   5
0039    TGETS    5   5  11  ; "paintTo"
0040    MOV      7   1
0041    MOV      8   2
0042    GGET     9  12      ; "math"
0043    TGETS    9   9  13  ; "floor"
0044    TGETS   10   0   1  ; "dimen"
0045    TGETS   10  10   6  ; "h"
0046    TGETS   11   4   6  ; "h"
0047    SUBVV   10  10  11
0048    DIVVN   10  10   0  ; 2
0049    CALL     9   2   2
0050    ADDVV    9   3   9
0051    CALL     5   1   5
0052    JMP      4 => 0060
0053 => TGETB    4   0   1
0054    MOV      5   4
0055    TGETS    4   4  11  ; "paintTo"
0056    MOV      6   1
0057    MOV      7   2
0058    MOV      8   3
0059    CALL     4   1   5
0060 => RET0     0   1

-- BYTECODE -- inputcontainer.lua:132-169
0001    UGET     2   0      ; Screen
0002    MOV      3   2
0003    TGETS    2   2   0  ; "getWidth"
0004    CALL     2   2   2
0005    UGET     3   0      ; Screen
0006    MOV      4   3
0007    TGETS    3   3   1  ; "getHeight"
0008    CALL     3   2   2
0009    TGETS    4   0   2  ; "touch_zone_dg"
0010    IST          4
0011    JMP      4 => 0018
0012    UGET     4   1      ; DepGraph
0013    MOV      5   4
0014    TGETS    4   4   3  ; "new"
0015    TNEW     6   0
0016    CALL     4   2   3
0017    TSETS    4   0   2  ; "touch_zone_dg"
0018 => GGET     4   4      ; "ipairs"
0019    MOV      5   1
0020    CALL     4   4   2
0021    JMP      7 => 0091
0022 => TGETS    9   0   5  ; "_zones"
0023    TGETS   10   8   6  ; "id"
0024    TGETV    9   9  10
0025    ISF          9
0026    JMP     10 => 0032
0027    TGETS    9   0   2  ; "touch_zone_dg"
0028    MOV     10   9
0029    TGETS    9   9   7  ; "removeNode"
0030    TGETS   11   8   6  ; "id"
0031    CALL     9   1   3
0032 => TGETS    9   0   5  ; "_zones"
0033    TGETS   10   8   6  ; "id"
0034    TDUP    11   8
0035    TSETS    8  11   9  ; "def"
0036    TGETS   12   8  10  ; "handler"
0037    TSETS   12  11  10  ; "handler"
0038    UGET    12   2      ; GestureRange
0039    MOV     13  12
0040    TGETS   12  12   3  ; "new"
0041    TDUP    14  12
0042    TGETS   15   8  11  ; "ges"
0043    TSETS   15  14  11  ; "ges"
0044    TGETS   15   8  13  ; "rate"
0045    TSETS   15  14  13  ; "rate"
0046    UGET    15   3      ; Geom
0047    MOV     16  15
0048    TGETS   15  15   3  ; "new"
0049    TDUP    17  16
0050    TGETS   18   8  14  ; "screen_zone"
0051    TGETS   18  18  15  ; "ratio_x"
0052    MULVV   18   2  18
0053    TSETS   18  17  17  ; "x"
0054    TGETS   18   8  14  ; "screen_zone"
0055    TGETS   18  18  18  ; "ratio_y"
0056    MULVV   18   3  18
0057    TSETS   18  17  19  ; "y"
0058    TGETS   18   8  14  ; "screen_zone"
0059    TGETS   18  18  20  ; "ratio_w"
0060    MULVV   18   2  18
0061    TSETS   18  17  21  ; "w"
0062    TGETS   18   8  14  ; "screen_zone"
0063    TGETS   18  18  22  ; "ratio_h"
0064    MULVV   18   3  18
0065    TSETS   18  17  23  ; "h"
0066    CALL    15   2   3
0067    TSETS   15  14  24  ; "range"
0068    CALL    12   2   3
0069    TSETS   12  11  25  ; "gs_range"
0070    TSETV   11   9  10
0071    TGETS    9   0   2  ; "touch_zone_dg"
0072    MOV     10   9
0073    TGETS    9   9  26  ; "addNode"
0074    TGETS   11   8   6  ; "id"
0075    CALL     9   1   3
0076    TGETS    9   8  27  ; "overrides"
0077    ISF          9
0078    JMP     10 => 0091
0079    GGET     9   4      ; "ipairs"
0080    TGETS   10   8  27  ; "overrides"
0081    CALL     9   4   2
0082    JMP     12 => 0089
0083 => TGETS   14   0   2  ; "touch_zone_dg"
0084    MOV     15  14
0085    TGETS   14  14  28  ; "addNodeDep"
0086    MOV     16  13
0087    TGETS   17   8   6  ; "id"
0088    CALL    14   1   4
0089 => ITERC   12   3   3
0090    ITERL   12 => 0083
0091 => ITERC    7   3   3
0092    ITERL    7 => 0022
0093    TNEW     4   0
0094    TSETS    4   0  29  ; "_ordered_touch_zones"
0095    GGET     4   4      ; "ipairs"
0096    TGETS    5   0   2  ; "touch_zone_dg"
0097    MOV      6   5
0098    TGETS    5   5  30  ; "serialize"
0099    CALL     5   0   2
0100    CALLM    4   4   0
0101    JMP      7 => 0108
0102 => GGET     9  31      ; "table"
0103    TGETS    9   9  32  ; "insert"
0104    TGETS   10   0  29  ; "_ordered_touch_zones"
0105    TGETS   11   0   5  ; "_zones"
0106    TGETV   11  11   8
0107    CALL     9   1   3
0108 => ITERC    7   3   3
0109    ITERL    7 => 0102
0110    RET0     0   1

-- BYTECODE -- inputcontainer.lua:171-197
0001    TGETS    2   0   0  ; "touch_zone_dg"
0002    ISF          2
0003    JMP      3 => 0072
0004    GGET     2   1      ; "ipairs"
0005    MOV      3   1
0006    CALL     2   4   2
0007    JMP      5 => 0050
0008 => TGETS    7   0   2  ; "_zones"
0009    TGETS    8   6   3  ; "id"
0010    TGETV    7   7   8
0011    ISF          7
0012    JMP      8 => 0050
0013    TGETS    7   0   0  ; "touch_zone_dg"
0014    MOV      8   7
0015    TGETS    7   7   4  ; "removeNode"
0016    TGETS    9   6   3  ; "id"
0017    CALL     7   1   3
0018    TGETS    7   6   5  ; "overrides"
0019    ISF          7
0020    JMP      8 => 0033
0021    GGET     7   1      ; "ipairs"
0022    TGETS    8   6   5  ; "overrides"
0023    CALL     7   4   2
0024    JMP     10 => 0031
0025 => TGETS   12   0   0  ; "touch_zone_dg"
0026    MOV     13  12
0027    TGETS   12  12   6  ; "removeNodeDep"
0028    MOV     14  11
0029    TGETS   15   6   3  ; "id"
0030    CALL    12   1   4
0031 => ITERC   10   3   3
0032    ITERL   10 => 0025
0033 => GGET     7   1      ; "ipairs"
0034    TGETS    8   0   7  ; "_ordered_touch_zones"
0035    CALL     7   4   2
0036    JMP     10 => 0048
0037 => TGETS   12  11   8  ; "def"
0038    TGETS   12  12   3  ; "id"
0039    TGETS   13   6   3  ; "id"
0040    ISNEV   12  13
0041    JMP     12 => 0048
0042    GGET    12   9      ; "table"
0043    TGETS   12  12  10  ; "remove"
0044    TGETS   13   0   7  ; "_ordered_touch_zones"
0045    MOV     14   5
0046    CALL    12   1   3
0047    JMP      7 => 0050
0048 => ITERC   10   3   3
0049    ITERL   10 => 0037
0050 => ITERC    5   3   3
0051    ITERL    5 => 0008
0052    TNEW     2   0
0053    TSETS    2   0   7  ; "_ordered_touch_zones"
0054    TGETS    2   0   0  ; "touch_zone_dg"
0055    ISF          2
0056    JMP      3 => 0072
0057    GGET     2   1      ; "ipairs"
0058    TGETS    3   0   0  ; "touch_zone_dg"
0059    MOV      4   3
0060    TGETS    3   3  11  ; "serialize"
0061    CALL     3   0   2
0062    CALLM    2   4   0
0063    JMP      5 => 0070
0064 => GGET     7   9      ; "table"
0065    TGETS    7   7  12  ; "insert"
0066    TGETS    8   0   7  ; "_ordered_touch_zones"
0067    TGETS    9   0   2  ; "_zones"
0068    TGETV    9   9   6
0069    CALL     7   1   3
0070 => ITERC    5   3   3
0071    ITERL    5 => 0064
0072 => RET0     0   1

-- BYTECODE -- inputcontainer.lua:199-205
0001    TGETS    2   0   0  ; "touch_zone_dg"
0002    ISF          2
0003    JMP      3 => 0010
0004    TGETS    2   0   0  ; "touch_zone_dg"
0005    MOV      3   2
0006    TGETS    2   2   1  ; "checkNode"
0007    MOV      4   1
0008    CALLT    2   3
0009    JMP      2 => 0012
0010 => KPRI     2   1
0011    RET1     2   2
0012 => RET0     0   1

-- BYTECODE -- inputcontainer.lua:212-220
0001    GGET     2   0      ; "ipairs"
0002    TGETS    3   0   1  ; "_ordered_touch_zones"
0003    CALL     2   4   2
0004    JMP      5 => 0031
0005 => TGETS    7   6   2  ; "gs_range"
0006    TGETS    7   7   3  ; "range"
0007    TGETS    8   1   5  ; "w"
0008    TGETS    9   6   6  ; "def"
0009    TGETS    9   9   7  ; "screen_zone"
0010    TGETS    9   9   8  ; "ratio_x"
0011    MULVV    8   8   9
0012    TSETS    8   7   4  ; "x"
0013    TGETS    8   1  10  ; "h"
0014    TGETS    9   6   6  ; "def"
0015    TGETS    9   9   7  ; "screen_zone"
0016    TGETS    9   9  11  ; "ratio_y"
0017    MULVV    8   8   9
0018    TSETS    8   7   9  ; "y"
0019    TGETS    8   1   5  ; "w"
0020    TGETS    9   6   6  ; "def"
0021    TGETS    9   9   7  ; "screen_zone"
0022    TGETS    9   9  12  ; "ratio_w"
0023    MULVV    8   8   9
0024    TSETS    8   7   5  ; "w"
0025    TGETS    8   1  10  ; "h"
0026    TGETS    9   6   6  ; "def"
0027    TGETS    9   9   7  ; "screen_zone"
0028    TGETS    9   9  13  ; "ratio_h"
0029    MULVV    8   8   9
0030    TSETS    8   7  10  ; "h"
0031 => ITERC    5   3   3
0032    ITERL    5 => 0005
0033    RET0     0   1

-- BYTECODE -- inputcontainer.lua:226-237
0001    GGET     2   0      ; "pairs"
0002    TGETS    3   0   1  ; "key_events"
0003    CALL     2   4   2
0004    ISNEXT   5 => 0034
0005 => TGETS    7   6   2  ; "is_inactive"
0006    IST          7
0007    JMP      7 => 0034
0008    GGET     7   3      ; "ipairs"
0009    MOV      8   6
0010    CALL     7   4   2
0011    JMP     10 => 0032
0012 => MOV     13   1
0013    TGETS   12   1   4  ; "match"
0014    MOV     14  11
0015    CALL    12   2   3
0016    ISF         12
0017    JMP     13 => 0032
0018    TGETS   12   6   5  ; "event"
0019    IST         12
0020    JMP     13 => 0022
0021    MOV     12   5
0022 => MOV     14   0
0023    TGETS   13   0   6  ; "handleEvent"
0024    UGET    15   0      ; Event
0025    MOV     16  15
0026    TGETS   15  15   7  ; "new"
0027    MOV     17  12
0028    TGETS   18   6   8  ; "args"
0029    MOV     19   1
0030    CALL    15   0   5
0031    CALLMT  13   1
0032 => ITERC   10   3   3
0033    ITERL   10 => 0012
0034 => ITERN    5   3   3
0035    ITERL    5 => 0005
0036    RET0     0   1

-- BYTECODE -- inputcontainer.lua:240-251
0001    GGET     2   0      ; "pairs"
0002    TGETS    3   0   1  ; "key_events"
0003    CALL     2   4   2
0004    ISNEXT   5 => 0034
0005 => TGETS    7   6   2  ; "is_inactive"
0006    IST          7
0007    JMP      7 => 0034
0008    GGET     7   3      ; "ipairs"
0009    MOV      8   6
0010    CALL     7   4   2
0011    JMP     10 => 0032
0012 => MOV     13   1
0013    TGETS   12   1   4  ; "match"
0014    MOV     14  11
0015    CALL    12   2   3
0016    ISF         12
0017    JMP     13 => 0032
0018    TGETS   12   6   5  ; "event"
0019    IST         12
0020    JMP     13 => 0022
0021    MOV     12   5
0022 => MOV     14   0
0023    TGETS   13   0   6  ; "handleEvent"
0024    UGET    15   0      ; Event
0025    MOV     16  15
0026    TGETS   15  15   7  ; "new"
0027    MOV     17  12
0028    TGETS   18   6   8  ; "args"
0029    MOV     19   1
0030    CALL    15   0   5
0031    CALLMT  13   1
0032 => ITERC   10   3   3
0033    ITERL   10 => 0012
0034 => ITERN    5   3   3
0035    ITERL    5 => 0005
0036    RET0     0   1

-- BYTECODE -- inputcontainer.lua:253-269
0001    GGET     2   0      ; "ipairs"
0002    TGETS    3   0   1  ; "_ordered_touch_zones"
0003    CALL     2   4   2
0004    JMP      5 => 0019
0005 => TGETS    7   6   2  ; "gs_range"
0006    MOV      8   7
0007    TGETS    7   7   3  ; "match"
0008    MOV      9   1
0009    CALL     7   2   3
0010    ISF          7
0011    JMP      8 => 0019
0012    TGETS    7   6   4  ; "handler"
0013    MOV      8   1
0014    CALL     7   2   2
0015    ISF          7
0016    JMP      8 => 0019
0017    KPRI     7   2
0018    RET1     7   2
0019 => ITERC    5   3   3
0020    ITERL    5 => 0005
0021    GGET     2   5      ; "pairs"
0022    TGETS    3   0   6  ; "ges_events"
0023    CALL     2   4   2
0024    ISNEXT   5 => 0055
0025 => GGET     7   0      ; "ipairs"
0026    MOV      8   6
0027    CALL     7   4   2
0028    JMP     10 => 0053
0029 => MOV     13  11
0030    TGETS   12  11   3  ; "match"
0031    MOV     14   1
0032    CALL    12   2   3
0033    ISF         12
0034    JMP     13 => 0053
0035    TGETS   12   6   7  ; "event"
0036    IST         12
0037    JMP     13 => 0039
0038    MOV     12   5
0039 => MOV     14   0
0040    TGETS   13   0   8  ; "handleEvent"
0041    UGET    15   0      ; Event
0042    MOV     16  15
0043    TGETS   15  15   9  ; "new"
0044    MOV     17  12
0045    TGETS   18   6  10  ; "args"
0046    MOV     19   1
0047    CALL    15   0   5
0048    CALLM   13   2   1
0049    ISF         13
0050    JMP     14 => 0053
0051    KPRI    13   2
0052    RET1    13   2
0053 => ITERC   10   3   3
0054    ITERL   10 => 0029
0055 => ITERN    5   3   3
0056    ITERL    5 => 0025
0057    RET0     0   1

-- BYTECODE -- inputcontainer.lua:282-284
0001    UGET     0   0      ; self
0002    MOV      1   0
0003    TGETS    0   0   0  ; "closeInputDialog"
0004    CALL     0   1   2
0005    RET0     0   1

-- BYTECODE -- inputcontainer.lua:289-292
0001    UGET     0   0      ; input
0002    TGETS    0   0   0  ; "callback"
0003    UGET     1   1      ; self
0004    TGETS    1   1   1  ; "input_dialog"
0005    MOV      2   1
0006    TGETS    1   1   2  ; "getInputText"
0007    CALL     1   0   2
0008    CALLM    0   1   0
0009    UGET     0   1      ; self
0010    MOV      1   0
0011    TGETS    0   0   3  ; "closeInputDialog"
0012    CALL     0   1   2
0013    RET0     0   1

-- BYTECODE -- inputcontainer.lua:271-299
0001    GGET     3   0      ; "require"
0002    KSTR     4   1      ; "ui/widget/inputdialog"
0003    CALL     3   2   2
0004    MOV      5   3
0005    TGETS    4   3   3  ; "new"
0006    TDUP     6   5
0007    TGETS    7   1   4  ; "title"
0008    IST          7
0009    JMP      8 => 0011
0010    KSTR     7   6      ; ""
0011 => TSETS    7   6   4  ; "title"
0012    TGETS    7   1   7  ; "input_func"
0013    ISF          7
0014    JMP      8 => 0019
0015    TGETS    7   1   7  ; "input_func"
0016    CALL     7   2   1
0017    IST          7
0018    JMP      8 => 0020
0019 => TGETS    7   1   8  ; "input"
0020 => TSETS    7   6   8  ; "input"
0021    TGETS    7   1   9  ; "hint_func"
0022    ISF          7
0023    JMP      8 => 0028
0024    TGETS    7   1   9  ; "hint_func"
0025    CALL     7   2   1
0026    IST          7
0027    JMP      8 => 0032
0028 => TGETS    7   1  10  ; "hint"
0029    IST          7
0030    JMP      8 => 0032
0031    KSTR     7   6      ; ""
0032 => TSETS    7   6  11  ; "input_hint"
0033    TGETS    7   1  12  ; "type"
0034    IST          7
0035    JMP      8 => 0037
0036    KSTR     7  13      ; "number"
0037 => TSETS    7   6  14  ; "input_type"
0038    TGETS    7   1  15  ; "buttons"
0039    IST          7
0040    JMP      8 => 0066
0041    TNEW     7   3
0042    TNEW     8   3
0043    TDUP     9  18
0044    TGETS   10   1  16  ; "cancel_text"
0045    IST         10
0046    JMP     11 => 0050
0047    UGET    10   0      ; _
0048    KSTR    11  17      ; "Cancel"
0049    CALL    10   2   2
0050 => TSETS   10   9  19  ; "text"
0051    FNEW    10  20      ; inputcontainer.lua:282
0052    TSETS   10   9  21  ; "callback"
0053    TSETB    9   8   1
0054    TDUP     9  24
0055    TGETS   10   1  22  ; "ok_text"
0056    IST         10
0057    JMP     11 => 0061
0058    UGET    10   0      ; _
0059    KSTR    11  23      ; "OK"
0060    CALL    10   2   2
0061 => TSETS   10   9  19  ; "text"
0062    FNEW    10  25      ; inputcontainer.lua:289
0063    TSETS   10   9  21  ; "callback"
0064    TSETB    9   8   2
0065    TSETB    8   7   1
0066 => TSETS    7   6  15  ; "buttons"
0067    CALL     4   2   3
0068    TSETS    4   0   2  ; "input_dialog"
0069    UGET     4   1      ; UIManager
0070    MOV      5   4
0071    TGETS    4   4  26  ; "show"
0072    TGETS    6   0   2  ; "input_dialog"
0073    CALL     4   1   3
0074    TGETS    4   0   2  ; "input_dialog"
0075    MOV      5   4
0076    TGETS    4   4  27  ; "onShowKeyboard"
0077    MOV      6   2
0078    CALL     4   1   3
0079    UCLO     0 => 0080
0080 => RET0     0   1

-- BYTECODE -- inputcontainer.lua:301-303
0001    UGET     1   0      ; UIManager
0002    MOV      2   1
0003    TGETS    1   1   0  ; "close"
0004    TGETS    3   0   1  ; "input_dialog"
0005    CALL     1   1   3
0006    RET0     0   1

-- BYTECODE -- inputcontainer.lua:0-306
0001    GGET     0   0      ; "require"
0002    KSTR     1   1      ; "depgraph"
0003    CALL     0   2   2
0004    GGET     1   0      ; "require"
0005    KSTR     2   2      ; "ui/event"
0006    CALL     1   2   2
0007    GGET     2   0      ; "require"
0008    KSTR     3   3      ; "ui/geometry"
0009    CALL     2   2   2
0010    GGET     3   0      ; "require"
0011    KSTR     4   4      ; "ui/gesturerange"
0012    CALL     3   2   2
0013    GGET     4   0      ; "require"
0014    KSTR     5   5      ; "ui/uimanager"
0015    CALL     4   2   2
0016    GGET     5   0      ; "require"
0017    KSTR     6   6      ; "ui/widget/container/widgetcontainer"
0018    CALL     5   2   2
0019    GGET     6   0      ; "require"
0020    KSTR     7   7      ; "device"
0021    CALL     6   2   2
0022    TGETS    7   6   8  ; "screen"
0023    GGET     8   0      ; "require"
0024    KSTR     9   9      ; "gettext"
0025    CALL     8   2   2
0026    TGETS    9   6  10  ; "should_restrict_JIT"
0027    ISF          9
0028    JMP     10 => 0036
0029    GGET     9   0      ; "require"
0030    KSTR    10  11      ; "jit"
0031    CALL     9   2   2
0032    TGETS    9   9  12  ; "off"
0033    KPRI    10   2
0034    KPRI    11   2
0035    CALL     9   1   3
0036 => MOV     10   5
0037    TGETS    9   5  13  ; "new"
0038    TDUP    11  14
0039    CALL     9   2   3
0040    FNEW    10  16      ; inputcontainer.lua:45
0041    TSETS   10   9  15  ; "_init"
0042    FNEW    10  18      ; inputcontainer.lua:67
0043    TSETS   10   9  17  ; "paintTo"
0044    FNEW    10  20      ; inputcontainer.lua:132
0045    TSETS   10   9  19  ; "registerTouchZones"
0046    FNEW    10  22      ; inputcontainer.lua:171
0047    TSETS   10   9  21  ; "unRegisterTouchZones"
0048    FNEW    10  24      ; inputcontainer.lua:199
0049    TSETS   10   9  23  ; "checkRegisterTouchZone"
0050    FNEW    10  26      ; inputcontainer.lua:212
0051    TSETS   10   9  25  ; "updateTouchZonesOnScreenResize"
0052    FNEW    10  28      ; inputcontainer.lua:226
0053    TSETS   10   9  27  ; "onKeyPress"
0054    FNEW    10  30      ; inputcontainer.lua:240
0055    TSETS   10   9  29  ; "onKeyRepeat"
0056    FNEW    10  32      ; inputcontainer.lua:253
0057    TSETS   10   9  31  ; "onGesture"
0058    FNEW    10  34      ; inputcontainer.lua:271
0059    TSETS   10   9  33  ; "onInput"
0060    FNEW    10  36      ; inputcontainer.lua:301
0061    TSETS   10   9  35  ; "closeInputDialog"
0062    UCLO     0 => 0063
0063 => RET1     9   2

