
main <./frontend/ui/widget/container/inputcontainer.lua:0,0> (74 instructions, 296 bytes at 0x7fe3a2c06900)
0+ params, 12 slots, 0 upvalues, 10 locals, 27 constants, 11 functions
	1	[27]	GETGLOBAL	0 -1	; require
	2	[27]	LOADK    	1 -2	; "depgraph"
	3	[27]	CALL     	0 2 2
	4	[28]	GETGLOBAL	1 -1	; require
	5	[28]	LOADK    	2 -3	; "ui/event"
	6	[28]	CALL     	1 2 2
	7	[29]	GETGLOBAL	2 -1	; require
	8	[29]	LOADK    	3 -4	; "ui/geometry"
	9	[29]	CALL     	2 2 2
	10	[30]	GETGLOBAL	3 -1	; require
	11	[30]	LOADK    	4 -5	; "ui/gesturerange"
	12	[30]	CALL     	3 2 2
	13	[31]	GETGLOBAL	4 -1	; require
	14	[31]	LOADK    	5 -6	; "ui/uimanager"
	15	[31]	CALL     	4 2 2
	16	[32]	GETGLOBAL	5 -1	; require
	17	[32]	LOADK    	6 -7	; "ui/widget/container/widgetcontainer"
	18	[32]	CALL     	5 2 2
	19	[33]	GETGLOBAL	6 -1	; require
	20	[33]	LOADK    	7 -8	; "device"
	21	[33]	CALL     	6 2 2
	22	[34]	GETTABLE 	7 6 -9	; "screen"
	23	[35]	GETGLOBAL	8 -1	; require
	24	[35]	LOADK    	9 -10	; "gettext"
	25	[35]	CALL     	8 2 2
	26	[37]	GETTABLE 	9 6 -11	; "should_restrict_JIT"
	27	[37]	TEST     	9 0 0
	28	[37]	JMP      	7	; to 36
	29	[38]	GETGLOBAL	9 -1	; require
	30	[38]	LOADK    	10 -12	; "jit"
	31	[38]	CALL     	9 2 2
	32	[38]	GETTABLE 	9 9 -13	; "off"
	33	[38]	LOADBOOL 	10 1 0
	34	[38]	LOADBOOL 	11 1 0
	35	[38]	CALL     	9 3 1
	36	[41]	SELF     	9 5 -14	; "new"
	37	[41]	NEWTABLE 	11 0 1
	38	[42]	SETTABLE 	11 -15 -16	; "vertical_align" "top"
	39	[41]	CALL     	9 3 2
	40	[65]	CLOSURE  	10 0	; 0x7fe3a2c070a0
	41	[45]	SETTABLE 	9 -17 10	; "_init" -
	42	[87]	CLOSURE  	10 1	; 0x7fe3a2c077e0
	43	[87]	MOVE     	0 2
	44	[67]	SETTABLE 	9 -18 10	; "paintTo" -
	45	[169]	CLOSURE  	10 2	; 0x7fe3a2c07860
	46	[169]	MOVE     	0 7
	47	[169]	MOVE     	0 0
	48	[169]	MOVE     	0 3
	49	[169]	MOVE     	0 2
	50	[132]	SETTABLE 	9 -19 10	; "registerTouchZones" -
	51	[197]	CLOSURE  	10 3	; 0x7fe3a2c08050
	52	[171]	SETTABLE 	9 -20 10	; "unRegisterTouchZones" -
	53	[205]	CLOSURE  	10 4	; 0x7fe3a2c08d60
	54	[199]	SETTABLE 	9 -21 10	; "checkRegisterTouchZone" -
	55	[220]	CLOSURE  	10 5	; 0x7fe3a2c09080
	56	[212]	SETTABLE 	9 -22 10	; "updateTouchZonesOnScreenResize" -
	57	[237]	CLOSURE  	10 6	; 0x7fe3a2c09b50
	58	[237]	MOVE     	0 1
	59	[226]	SETTABLE 	9 -23 10	; "onKeyPress" -
	60	[251]	CLOSURE  	10 7	; 0x7fe3a2c0a080
	61	[251]	MOVE     	0 1
	62	[240]	SETTABLE 	9 -24 10	; "onKeyRepeat" -
	63	[269]	CLOSURE  	10 8	; 0x7fe3a2c09fd0
	64	[269]	MOVE     	0 1
	65	[253]	SETTABLE 	9 -25 10	; "onGesture" -
	66	[299]	CLOSURE  	10 9	; 0x7fe3a2c0a990
	67	[299]	MOVE     	0 8
	68	[299]	MOVE     	0 4
	69	[271]	SETTABLE 	9 -26 10	; "onInput" -
	70	[303]	CLOSURE  	10 10	; 0x7fe3a2c0b460
	71	[303]	MOVE     	0 4
	72	[301]	SETTABLE 	9 -27 10	; "closeInputDialog" -
	73	[305]	RETURN   	9 2
	74	[305]	RETURN   	0 1

function <./frontend/ui/widget/container/inputcontainer.lua:45,65> (30 instructions, 120 bytes at 0x7fe3a2c070a0)
1 param, 9 slots, 0 upvalues, 13 locals, 7 constants, 0 functions
	1	[47]	NEWTABLE 	1 0 0
	2	[48]	GETTABLE 	2 0 -1	; "key_events"
	3	[48]	TEST     	2 0 0
	4	[48]	JMP      	7	; to 12
	5	[49]	GETGLOBAL	2 -2	; pairs
	6	[49]	GETTABLE 	3 0 -1	; "key_events"
	7	[49]	CALL     	2 2 4
	8	[49]	JMP      	1	; to 10
	9	[50]	SETTABLE 	1 5 6
	10	[49]	TFORLOOP 	2 2
	11	[50]	JMP      	-3	; to 9
	12	[53]	SETTABLE 	0 -1 1	; "key_events" -
	13	[55]	NEWTABLE 	2 0 0
	14	[56]	GETTABLE 	3 0 -3	; "ges_events"
	15	[56]	TEST     	3 0 0
	16	[56]	JMP      	7	; to 24
	17	[57]	GETGLOBAL	3 -2	; pairs
	18	[57]	GETTABLE 	4 0 -3	; "ges_events"
	19	[57]	CALL     	3 2 4
	20	[57]	JMP      	1	; to 22
	21	[58]	SETTABLE 	2 6 7
	22	[57]	TFORLOOP 	3 2
	23	[58]	JMP      	-3	; to 21
	24	[61]	SETTABLE 	0 -3 2	; "ges_events" -
	25	[62]	SETTABLE 	0 -4 -5	; "touch_zone_dg" nil
	26	[63]	NEWTABLE 	3 0 0
	27	[63]	SETTABLE 	0 -6 3	; "_zones" -
	28	[64]	NEWTABLE 	3 0 0
	29	[64]	SETTABLE 	0 -7 3	; "_ordered_touch_zones" -
	30	[65]	RETURN   	0 1

function <./frontend/ui/widget/container/inputcontainer.lua:67,87> (55 instructions, 220 bytes at 0x7fe3a2c077e0)
4 params, 12 slots, 1 upvalue, 6 locals, 16 constants, 0 functions
	1	[68]	GETTABLE 	4 0 -1	; 1
	2	[68]	EQ       	0 4 -2	; - nil
	3	[68]	JMP      	1	; to 5
	4	[69]	RETURN   	0 1
	5	[71]	GETTABLE 	4 0 -3	; "skip_paint"
	6	[71]	TEST     	4 0 0
	7	[71]	JMP      	1	; to 9
	8	[72]	RETURN   	0 1
	9	[75]	GETTABLE 	4 0 -4	; "dimen"
	10	[75]	TEST     	4 0 1
	11	[75]	JMP      	12	; to 24
	12	[76]	GETTABLE 	4 0 -1	; 1
	13	[76]	SELF     	4 4 -5	; "getSize"
	14	[76]	CALL     	4 2 2
	15	[77]	GETUPVAL 	5 0	; Geom
	16	[77]	SELF     	5 5 -6	; "new"
	17	[77]	NEWTABLE 	7 0 2
	18	[77]	GETTABLE 	8 4 -7	; "w"
	19	[77]	SETTABLE 	7 -7 8	; "w" -
	20	[77]	GETTABLE 	8 4 -8	; "h"
	21	[77]	SETTABLE 	7 -8 8	; "h" -
	22	[77]	CALL     	5 3 2
	23	[77]	SETTABLE 	0 -4 5	; "dimen" -
	24	[79]	GETTABLE 	4 0 -4	; "dimen"
	25	[79]	SETTABLE 	4 -9 2	; "x" -
	26	[80]	GETTABLE 	4 0 -4	; "dimen"
	27	[80]	SETTABLE 	4 -10 3	; "y" -
	28	[81]	GETTABLE 	4 0 -11	; "vertical_align"
	29	[81]	EQ       	0 4 -12	; - "center"
	30	[81]	JMP      	18	; to 49
	31	[82]	GETTABLE 	4 0 -1	; 1
	32	[82]	SELF     	4 4 -5	; "getSize"
	33	[82]	CALL     	4 2 2
	34	[83]	GETTABLE 	5 0 -1	; 1
	35	[83]	SELF     	5 5 -13	; "paintTo"
	36	[83]	MOVE     	7 1
	37	[83]	MOVE     	8 2
	38	[83]	GETGLOBAL	9 -14	; math
	39	[83]	GETTABLE 	9 9 -15	; "floor"
	40	[83]	GETTABLE 	10 0 -4	; "dimen"
	41	[83]	GETTABLE 	10 10 -8	; "h"
	42	[83]	GETTABLE 	11 4 -8	; "h"
	43	[83]	SUB      	10 10 11
	44	[83]	DIV      	10 10 -16	; - 2
	45	[83]	CALL     	9 2 2
	46	[83]	ADD      	9 3 9
	47	[83]	CALL     	5 5 1
	48	[83]	JMP      	6	; to 55
	49	[85]	GETTABLE 	4 0 -1	; 1
	50	[85]	SELF     	4 4 -13	; "paintTo"
	51	[85]	MOVE     	6 1
	52	[85]	MOVE     	7 2
	53	[85]	MOVE     	8 3
	54	[85]	CALL     	4 5 1
	55	[87]	RETURN   	0 1

function <./frontend/ui/widget/container/inputcontainer.lua:132,169> (101 instructions, 404 bytes at 0x7fe3a2c07860)
2 params, 19 slots, 4 upvalues, 19 locals, 30 constants, 0 functions
	1	[133]	GETUPVAL 	2 0	; Screen
	2	[133]	SELF     	2 2 -1	; "getWidth"
	3	[133]	CALL     	2 2 2
	4	[133]	GETUPVAL 	3 0	; Screen
	5	[133]	SELF     	3 3 -2	; "getHeight"
	6	[133]	CALL     	3 2 2
	7	[134]	GETTABLE 	4 0 -3	; "touch_zone_dg"
	8	[134]	TEST     	4 0 1
	9	[134]	JMP      	5	; to 15
	10	[134]	GETUPVAL 	4 1	; DepGraph
	11	[134]	SELF     	4 4 -4	; "new"
	12	[134]	NEWTABLE 	6 0 0
	13	[134]	CALL     	4 3 2
	14	[134]	SETTABLE 	0 -3 4	; "touch_zone_dg" -
	15	[135]	GETGLOBAL	4 -5	; ipairs
	16	[135]	MOVE     	5 1
	17	[135]	CALL     	4 2 4
	18	[135]	JMP      	64	; to 83
	19	[137]	GETTABLE 	9 0 -6	; "_zones"
	20	[137]	GETTABLE 	10 8 -7	; "id"
	21	[137]	GETTABLE 	9 9 10
	22	[137]	TEST     	9 0 0
	23	[137]	JMP      	4	; to 28
	24	[138]	GETTABLE 	9 0 -3	; "touch_zone_dg"
	25	[138]	SELF     	9 9 -8	; "removeNode"
	26	[138]	GETTABLE 	11 8 -7	; "id"
	27	[138]	CALL     	9 3 1
	28	[140]	GETTABLE 	9 0 -6	; "_zones"
	29	[140]	GETTABLE 	10 8 -7	; "id"
	30	[140]	NEWTABLE 	11 0 3
	31	[141]	SETTABLE 	11 -9 8	; "def" -
	32	[142]	GETTABLE 	12 8 -10	; "handler"
	33	[142]	SETTABLE 	11 -10 12	; "handler" -
	34	[143]	GETUPVAL 	12 2	; GestureRange
	35	[143]	SELF     	12 12 -4	; "new"
	36	[143]	NEWTABLE 	14 0 3
	37	[144]	GETTABLE 	15 8 -12	; "ges"
	38	[144]	SETTABLE 	14 -12 15	; "ges" -
	39	[145]	GETTABLE 	15 8 -13	; "rate"
	40	[145]	SETTABLE 	14 -13 15	; "rate" -
	41	[146]	GETUPVAL 	15 3	; Geom
	42	[146]	SELF     	15 15 -4	; "new"
	43	[146]	NEWTABLE 	17 0 4
	44	[147]	GETTABLE 	18 8 -16	; "screen_zone"
	45	[147]	GETTABLE 	18 18 -17	; "ratio_x"
	46	[147]	MUL      	18 2 18
	47	[147]	SETTABLE 	17 -15 18	; "x" -
	48	[148]	GETTABLE 	18 8 -16	; "screen_zone"
	49	[148]	GETTABLE 	18 18 -19	; "ratio_y"
	50	[148]	MUL      	18 3 18
	51	[148]	SETTABLE 	17 -18 18	; "y" -
	52	[149]	GETTABLE 	18 8 -16	; "screen_zone"
	53	[149]	GETTABLE 	18 18 -21	; "ratio_w"
	54	[149]	MUL      	18 2 18
	55	[149]	SETTABLE 	17 -20 18	; "w" -
	56	[150]	GETTABLE 	18 8 -16	; "screen_zone"
	57	[150]	GETTABLE 	18 18 -23	; "ratio_h"
	58	[150]	MUL      	18 3 18
	59	[150]	SETTABLE 	17 -22 18	; "h" -
	60	[146]	CALL     	15 3 2
	61	[151]	SETTABLE 	14 -14 15	; "range" -
	62	[143]	CALL     	12 3 2
	63	[152]	SETTABLE 	11 -11 12	; "gs_range" -
	64	[153]	SETTABLE 	9 10 11
	65	[154]	GETTABLE 	9 0 -3	; "touch_zone_dg"
	66	[154]	SELF     	9 9 -24	; "addNode"
	67	[154]	GETTABLE 	11 8 -7	; "id"
	68	[154]	CALL     	9 3 1
	69	[156]	GETTABLE 	9 8 -25	; "overrides"
	70	[156]	TEST     	9 0 0
	71	[156]	JMP      	11	; to 83
	72	[157]	GETGLOBAL	9 -5	; ipairs
	73	[157]	GETTABLE 	10 8 -25	; "overrides"
	74	[157]	CALL     	9 2 4
	75	[157]	JMP      	5	; to 81
	76	[159]	GETTABLE 	14 0 -3	; "touch_zone_dg"
	77	[159]	SELF     	14 14 -26	; "addNodeDep"
	78	[159]	MOVE     	16 13
	79	[159]	GETTABLE 	17 8 -7	; "id"
	80	[159]	CALL     	14 4 1
	81	[157]	TFORLOOP 	9 2
	82	[159]	JMP      	-7	; to 76
	83	[135]	TFORLOOP 	4 2
	84	[161]	JMP      	-66	; to 19
	85	[164]	NEWTABLE 	4 0 0
	86	[164]	SETTABLE 	0 -27 4	; "_ordered_touch_zones" -
	87	[165]	GETGLOBAL	4 -5	; ipairs
	88	[165]	GETTABLE 	5 0 -3	; "touch_zone_dg"
	89	[165]	SELF     	5 5 -28	; "serialize"
	90	[165]	CALL     	5 2 0
	91	[165]	CALL     	4 0 4
	92	[165]	JMP      	6	; to 99
	93	[166]	GETGLOBAL	9 -29	; table
	94	[166]	GETTABLE 	9 9 -30	; "insert"
	95	[166]	GETTABLE 	10 0 -27	; "_ordered_touch_zones"
	96	[166]	GETTABLE 	11 0 -6	; "_zones"
	97	[166]	GETTABLE 	11 11 8
	98	[166]	CALL     	9 3 1
	99	[165]	TFORLOOP 	4 2
	100	[166]	JMP      	-8	; to 93
	101	[169]	RETURN   	0 1

function <./frontend/ui/widget/container/inputcontainer.lua:171,197> (69 instructions, 276 bytes at 0x7fe3a2c08050)
2 params, 16 slots, 0 upvalues, 22 locals, 13 constants, 0 functions
	1	[172]	GETTABLE 	2 0 -1	; "touch_zone_dg"
	2	[172]	TEST     	2 0 0
	3	[172]	JMP      	65	; to 69
	4	[173]	GETGLOBAL	2 -2	; ipairs
	5	[173]	MOVE     	3 1
	6	[173]	CALL     	2 2 4
	7	[173]	JMP      	40	; to 48
	8	[174]	GETTABLE 	7 0 -3	; "_zones"
	9	[174]	GETTABLE 	8 6 -4	; "id"
	10	[174]	GETTABLE 	7 7 8
	11	[174]	TEST     	7 0 0
	12	[174]	JMP      	35	; to 48
	13	[175]	GETTABLE 	7 0 -1	; "touch_zone_dg"
	14	[175]	SELF     	7 7 -5	; "removeNode"
	15	[175]	GETTABLE 	9 6 -4	; "id"
	16	[175]	CALL     	7 3 1
	17	[176]	GETTABLE 	7 6 -6	; "overrides"
	18	[176]	TEST     	7 0 0
	19	[176]	JMP      	11	; to 31
	20	[177]	GETGLOBAL	7 -2	; ipairs
	21	[177]	GETTABLE 	8 6 -6	; "overrides"
	22	[177]	CALL     	7 2 4
	23	[177]	JMP      	5	; to 29
	24	[179]	GETTABLE 	12 0 -1	; "touch_zone_dg"
	25	[179]	SELF     	12 12 -7	; "removeNodeDep"
	26	[179]	MOVE     	14 11
	27	[179]	GETTABLE 	15 6 -4	; "id"
	28	[179]	CALL     	12 4 1
	29	[177]	TFORLOOP 	7 2
	30	[179]	JMP      	-7	; to 24
	31	[182]	GETGLOBAL	7 -2	; ipairs
	32	[182]	GETTABLE 	8 0 -8	; "_ordered_touch_zones"
	33	[182]	CALL     	7 2 4
	34	[182]	JMP      	11	; to 46
	35	[183]	GETTABLE 	12 11 -9	; "def"
	36	[183]	GETTABLE 	12 12 -4	; "id"
	37	[183]	GETTABLE 	13 6 -4	; "id"
	38	[183]	EQ       	0 12 13
	39	[183]	JMP      	6	; to 46
	40	[184]	GETGLOBAL	12 -10	; table
	41	[184]	GETTABLE 	12 12 -11	; "remove"
	42	[184]	GETTABLE 	13 0 -8	; "_ordered_touch_zones"
	43	[184]	MOVE     	14 5
	44	[184]	CALL     	12 3 1
	45	[185]	JMP      	2	; to 48
	46	[182]	TFORLOOP 	7 2
	47	[186]	JMP      	-13	; to 35
	48	[173]	TFORLOOP 	2 2
	49	[188]	JMP      	-42	; to 8
	50	[190]	NEWTABLE 	2 0 0
	51	[190]	SETTABLE 	0 -8 2	; "_ordered_touch_zones" -
	52	[191]	GETTABLE 	2 0 -1	; "touch_zone_dg"
	53	[191]	TEST     	2 0 0
	54	[191]	JMP      	14	; to 69
	55	[192]	GETGLOBAL	2 -2	; ipairs
	56	[192]	GETTABLE 	3 0 -1	; "touch_zone_dg"
	57	[192]	SELF     	3 3 -12	; "serialize"
	58	[192]	CALL     	3 2 0
	59	[192]	CALL     	2 0 4
	60	[192]	JMP      	6	; to 67
	61	[193]	GETGLOBAL	7 -10	; table
	62	[193]	GETTABLE 	7 7 -13	; "insert"
	63	[193]	GETTABLE 	8 0 -8	; "_ordered_touch_zones"
	64	[193]	GETTABLE 	9 0 -3	; "_zones"
	65	[193]	GETTABLE 	9 9 6
	66	[193]	CALL     	7 3 1
	67	[192]	TFORLOOP 	2 2
	68	[193]	JMP      	-8	; to 61
	69	[197]	RETURN   	0 1

function <./frontend/ui/widget/container/inputcontainer.lua:199,205> (12 instructions, 48 bytes at 0x7fe3a2c08d60)
2 params, 5 slots, 0 upvalues, 2 locals, 2 constants, 0 functions
	1	[200]	GETTABLE 	2 0 -1	; "touch_zone_dg"
	2	[200]	TEST     	2 0 0
	3	[200]	JMP      	6	; to 10
	4	[201]	GETTABLE 	2 0 -1	; "touch_zone_dg"
	5	[201]	SELF     	2 2 -2	; "checkNode"
	6	[201]	MOVE     	4 1
	7	[201]	TAILCALL 	2 3 0
	8	[201]	RETURN   	2 0
	9	[201]	JMP      	2	; to 12
	10	[203]	LOADBOOL 	2 0 0
	11	[203]	RETURN   	2 2
	12	[205]	RETURN   	0 1

function <./frontend/ui/widget/container/inputcontainer.lua:212,220> (33 instructions, 132 bytes at 0x7fe3a2c09080)
2 params, 10 slots, 0 upvalues, 8 locals, 14 constants, 0 functions
	1	[213]	GETGLOBAL	2 -1	; ipairs
	2	[213]	GETTABLE 	3 0 -2	; "_ordered_touch_zones"
	3	[213]	CALL     	2 2 4
	4	[213]	JMP      	26	; to 31
	5	[214]	GETTABLE 	7 6 -3	; "gs_range"
	6	[214]	GETTABLE 	7 7 -4	; "range"
	7	[215]	GETTABLE 	8 1 -6	; "w"
	8	[215]	GETTABLE 	9 6 -7	; "def"
	9	[215]	GETTABLE 	9 9 -8	; "screen_zone"
	10	[215]	GETTABLE 	9 9 -9	; "ratio_x"
	11	[215]	MUL      	8 8 9
	12	[215]	SETTABLE 	7 -5 8	; "x" -
	13	[216]	GETTABLE 	8 1 -11	; "h"
	14	[216]	GETTABLE 	9 6 -7	; "def"
	15	[216]	GETTABLE 	9 9 -8	; "screen_zone"
	16	[216]	GETTABLE 	9 9 -12	; "ratio_y"
	17	[216]	MUL      	8 8 9
	18	[216]	SETTABLE 	7 -10 8	; "y" -
	19	[217]	GETTABLE 	8 1 -6	; "w"
	20	[217]	GETTABLE 	9 6 -7	; "def"
	21	[217]	GETTABLE 	9 9 -8	; "screen_zone"
	22	[217]	GETTABLE 	9 9 -13	; "ratio_w"
	23	[217]	MUL      	8 8 9
	24	[217]	SETTABLE 	7 -6 8	; "w" -
	25	[218]	GETTABLE 	8 1 -11	; "h"
	26	[218]	GETTABLE 	9 6 -7	; "def"
	27	[218]	GETTABLE 	9 9 -8	; "screen_zone"
	28	[218]	GETTABLE 	9 9 -14	; "ratio_h"
	29	[218]	MUL      	8 8 9
	30	[218]	SETTABLE 	7 -11 8	; "h" -
	31	[213]	TFORLOOP 	2 2
	32	[218]	JMP      	-28	; to 5
	33	[220]	RETURN   	0 1

function <./frontend/ui/widget/container/inputcontainer.lua:226,237> (34 instructions, 136 bytes at 0x7fe3a2c09b50)
2 params, 20 slots, 1 upvalue, 13 locals, 9 constants, 0 functions
	1	[227]	GETGLOBAL	2 -1	; pairs
	2	[227]	GETTABLE 	3 0 -2	; "key_events"
	3	[227]	CALL     	2 2 4
	4	[227]	JMP      	27	; to 32
	5	[228]	GETTABLE 	7 6 -3	; "is_inactive"
	6	[228]	TEST     	7 0 1
	7	[228]	JMP      	24	; to 32
	8	[229]	GETGLOBAL	7 -4	; ipairs
	9	[229]	MOVE     	8 6
	10	[229]	CALL     	7 2 4
	11	[229]	JMP      	18	; to 30
	12	[230]	SELF     	12 1 -5	; "match"
	13	[230]	MOVE     	14 11
	14	[230]	CALL     	12 3 2
	15	[230]	TEST     	12 0 0
	16	[230]	JMP      	13	; to 30
	17	[231]	GETTABLE 	12 6 -6	; "event"
	18	[231]	TEST     	12 0 1
	19	[231]	JMP      	1	; to 21
	20	[231]	MOVE     	12 5
	21	[232]	SELF     	13 0 -7	; "handleEvent"
	22	[232]	GETUPVAL 	15 0	; Event
	23	[232]	SELF     	15 15 -8	; "new"
	24	[232]	MOVE     	17 12
	25	[232]	GETTABLE 	18 6 -9	; "args"
	26	[232]	MOVE     	19 1
	27	[232]	CALL     	15 5 0
	28	[232]	TAILCALL 	13 0 0
	29	[232]	RETURN   	13 0
	30	[229]	TFORLOOP 	7 2
	31	[233]	JMP      	-20	; to 12
	32	[227]	TFORLOOP 	2 2
	33	[235]	JMP      	-29	; to 5
	34	[237]	RETURN   	0 1

function <./frontend/ui/widget/container/inputcontainer.lua:240,251> (34 instructions, 136 bytes at 0x7fe3a2c0a080)
2 params, 20 slots, 1 upvalue, 13 locals, 9 constants, 0 functions
	1	[241]	GETGLOBAL	2 -1	; pairs
	2	[241]	GETTABLE 	3 0 -2	; "key_events"
	3	[241]	CALL     	2 2 4
	4	[241]	JMP      	27	; to 32
	5	[242]	GETTABLE 	7 6 -3	; "is_inactive"
	6	[242]	TEST     	7 0 1
	7	[242]	JMP      	24	; to 32
	8	[243]	GETGLOBAL	7 -4	; ipairs
	9	[243]	MOVE     	8 6
	10	[243]	CALL     	7 2 4
	11	[243]	JMP      	18	; to 30
	12	[244]	SELF     	12 1 -5	; "match"
	13	[244]	MOVE     	14 11
	14	[244]	CALL     	12 3 2
	15	[244]	TEST     	12 0 0
	16	[244]	JMP      	13	; to 30
	17	[245]	GETTABLE 	12 6 -6	; "event"
	18	[245]	TEST     	12 0 1
	19	[245]	JMP      	1	; to 21
	20	[245]	MOVE     	12 5
	21	[246]	SELF     	13 0 -7	; "handleEvent"
	22	[246]	GETUPVAL 	15 0	; Event
	23	[246]	SELF     	15 15 -8	; "new"
	24	[246]	MOVE     	17 12
	25	[246]	GETTABLE 	18 6 -9	; "args"
	26	[246]	MOVE     	19 1
	27	[246]	CALL     	15 5 0
	28	[246]	TAILCALL 	13 0 0
	29	[246]	RETURN   	13 0
	30	[243]	TFORLOOP 	7 2
	31	[247]	JMP      	-20	; to 12
	32	[241]	TFORLOOP 	2 2
	33	[249]	JMP      	-29	; to 5
	34	[251]	RETURN   	0 1

function <./frontend/ui/widget/container/inputcontainer.lua:253,269> (53 instructions, 212 bytes at 0x7fe3a2c09fd0)
2 params, 20 slots, 1 upvalue, 18 locals, 11 constants, 0 functions
	1	[254]	GETGLOBAL	2 -1	; ipairs
	2	[254]	GETTABLE 	3 0 -2	; "_ordered_touch_zones"
	3	[254]	CALL     	2 2 4
	4	[254]	JMP      	13	; to 18
	5	[255]	GETTABLE 	7 6 -3	; "gs_range"
	6	[255]	SELF     	7 7 -4	; "match"
	7	[255]	MOVE     	9 1
	8	[255]	CALL     	7 3 2
	9	[255]	TEST     	7 0 0
	10	[255]	JMP      	7	; to 18
	11	[255]	GETTABLE 	7 6 -5	; "handler"
	12	[255]	MOVE     	8 1
	13	[255]	CALL     	7 2 2
	14	[255]	TEST     	7 0 0
	15	[255]	JMP      	2	; to 18
	16	[256]	LOADBOOL 	7 1 0
	17	[256]	RETURN   	7 2
	18	[254]	TFORLOOP 	2 2
	19	[257]	JMP      	-15	; to 5
	20	[259]	GETGLOBAL	2 -6	; pairs
	21	[259]	GETTABLE 	3 0 -7	; "ges_events"
	22	[259]	CALL     	2 2 4
	23	[259]	JMP      	27	; to 51
	24	[260]	GETGLOBAL	7 -1	; ipairs
	25	[260]	MOVE     	8 6
	26	[260]	CALL     	7 2 4
	27	[260]	JMP      	21	; to 49
	28	[261]	SELF     	12 11 -4	; "match"
	29	[261]	MOVE     	14 1
	30	[261]	CALL     	12 3 2
	31	[261]	TEST     	12 0 0
	32	[261]	JMP      	16	; to 49
	33	[262]	GETTABLE 	12 6 -8	; "event"
	34	[262]	TEST     	12 0 1
	35	[262]	JMP      	1	; to 37
	36	[262]	MOVE     	12 5
	37	[263]	SELF     	13 0 -9	; "handleEvent"
	38	[263]	GETUPVAL 	15 0	; Event
	39	[263]	SELF     	15 15 -10	; "new"
	40	[263]	MOVE     	17 12
	41	[263]	GETTABLE 	18 6 -11	; "args"
	42	[263]	MOVE     	19 1
	43	[263]	CALL     	15 5 0
	44	[263]	CALL     	13 0 2
	45	[263]	TEST     	13 0 0
	46	[263]	JMP      	2	; to 49
	47	[264]	LOADBOOL 	13 1 0
	48	[264]	RETURN   	13 2
	49	[260]	TFORLOOP 	7 2
	50	[266]	JMP      	-23	; to 28
	51	[259]	TFORLOOP 	2 2
	52	[267]	JMP      	-29	; to 24
	53	[269]	RETURN   	0 1

function <./frontend/ui/widget/container/inputcontainer.lua:271,299> (79 instructions, 316 bytes at 0x7fe3a2c0a990)
3 params, 13 slots, 2 upvalues, 4 locals, 25 constants, 2 functions
	1	[272]	GETGLOBAL	3 -1	; require
	2	[272]	LOADK    	4 -2	; "ui/widget/inputdialog"
	3	[272]	CALL     	3 2 2
	4	[273]	SELF     	4 3 -4	; "new"
	5	[273]	NEWTABLE 	6 0 5
	6	[274]	GETTABLE 	7 1 -5	; "title"
	7	[274]	TEST     	7 0 1
	8	[274]	JMP      	1	; to 10
	9	[274]	LOADK    	7 -6	; ""
	10	[274]	SETTABLE 	6 -5 7	; "title" -
	11	[275]	GETTABLE 	7 1 -8	; "input_func"
	12	[275]	TEST     	7 0 0
	13	[275]	JMP      	4	; to 18
	14	[275]	GETTABLE 	7 1 -8	; "input_func"
	15	[275]	CALL     	7 1 2
	16	[275]	TEST     	7 0 1
	17	[275]	JMP      	1	; to 19
	18	[275]	GETTABLE 	7 1 -7	; "input"
	19	[275]	SETTABLE 	6 -7 7	; "input" -
	20	[276]	GETTABLE 	7 1 -10	; "hint_func"
	21	[276]	TEST     	7 0 0
	22	[276]	JMP      	4	; to 27
	23	[276]	GETTABLE 	7 1 -10	; "hint_func"
	24	[276]	CALL     	7 1 2
	25	[276]	TEST     	7 0 1
	26	[276]	JMP      	4	; to 31
	27	[276]	GETTABLE 	7 1 -11	; "hint"
	28	[276]	TEST     	7 0 1
	29	[276]	JMP      	1	; to 31
	30	[276]	LOADK    	7 -6	; ""
	31	[276]	SETTABLE 	6 -9 7	; "input_hint" -
	32	[277]	GETTABLE 	7 1 -13	; "type"
	33	[277]	TEST     	7 0 1
	34	[277]	JMP      	1	; to 36
	35	[277]	LOADK    	7 -14	; "number"
	36	[277]	SETTABLE 	6 -12 7	; "input_type" -
	37	[278]	GETTABLE 	7 1 -15	; "buttons"
	38	[278]	TEST     	7 0 1
	39	[278]	JMP      	28	; to 68
	40	[278]	NEWTABLE 	7 1 0
	41	[278]	NEWTABLE 	8 2 0
	42	[279]	NEWTABLE 	9 0 2
	43	[281]	GETTABLE 	10 1 -17	; "cancel_text"
	44	[281]	TEST     	10 0 1
	45	[281]	JMP      	3	; to 49
	46	[281]	GETUPVAL 	10 0	; _
	47	[281]	LOADK    	11 -18	; "Cancel"
	48	[281]	CALL     	10 2 2
	49	[281]	SETTABLE 	9 -16 10	; "text" -
	50	[284]	CLOSURE  	10 0	; 0x7fe3a2c0b6b0
	51	[284]	MOVE     	0 0
	52	[284]	SETTABLE 	9 -19 10	; "callback" -
	53	[285]	NEWTABLE 	10 0 3
	54	[287]	GETTABLE 	11 1 -20	; "ok_text"
	55	[287]	TEST     	11 0 1
	56	[287]	JMP      	3	; to 60
	57	[287]	GETUPVAL 	11 0	; _
	58	[287]	LOADK    	12 -21	; "OK"
	59	[287]	CALL     	11 2 2
	60	[287]	SETTABLE 	10 -16 11	; "text" -
	61	[288]	SETTABLE 	10 -22 -23	; "is_enter_default" true
	62	[292]	CLOSURE  	11 1	; 0x7fe3a2c0bb00
	63	[292]	MOVE     	0 1
	64	[292]	MOVE     	0 0
	65	[292]	SETTABLE 	10 -19 11	; "callback" -
	66	[294]	SETLIST  	8 2 1	; 1
	67	[295]	SETLIST  	7 1 1	; 1
	68	[295]	SETTABLE 	6 -15 7	; "buttons" -
	69	[273]	CALL     	4 3 2
	70	[296]	SETTABLE 	0 -3 4	; "input_dialog" -
	71	[297]	GETUPVAL 	4 1	; UIManager
	72	[297]	SELF     	4 4 -24	; "show"
	73	[297]	GETTABLE 	6 0 -3	; "input_dialog"
	74	[297]	CALL     	4 3 1
	75	[298]	GETTABLE 	4 0 -3	; "input_dialog"
	76	[298]	SELF     	4 4 -25	; "onShowKeyboard"
	77	[298]	MOVE     	6 2
	78	[298]	CALL     	4 3 1
	79	[299]	RETURN   	0 1

function <./frontend/ui/widget/container/inputcontainer.lua:282,284> (4 instructions, 16 bytes at 0x7fe3a2c0b6b0)
0 params, 2 slots, 1 upvalue, 0 locals, 1 constant, 0 functions
	1	[283]	GETUPVAL 	0 0	; self
	2	[283]	SELF     	0 0 -1	; "closeInputDialog"
	3	[283]	CALL     	0 2 1
	4	[284]	RETURN   	0 1

function <./frontend/ui/widget/container/inputcontainer.lua:289,292> (11 instructions, 44 bytes at 0x7fe3a2c0bb00)
0 params, 3 slots, 2 upvalues, 0 locals, 4 constants, 0 functions
	1	[290]	GETUPVAL 	0 0	; input
	2	[290]	GETTABLE 	0 0 -1	; "callback"
	3	[290]	GETUPVAL 	1 1	; self
	4	[290]	GETTABLE 	1 1 -2	; "input_dialog"
	5	[290]	SELF     	1 1 -3	; "getInputText"
	6	[290]	CALL     	1 2 0
	7	[290]	CALL     	0 0 1
	8	[291]	GETUPVAL 	0 1	; self
	9	[291]	SELF     	0 0 -4	; "closeInputDialog"
	10	[291]	CALL     	0 2 1
	11	[292]	RETURN   	0 1

function <./frontend/ui/widget/container/inputcontainer.lua:301,303> (5 instructions, 20 bytes at 0x7fe3a2c0b460)
1 param, 4 slots, 1 upvalue, 1 local, 2 constants, 0 functions
	1	[302]	GETUPVAL 	1 0	; UIManager
	2	[302]	SELF     	1 1 -1	; "close"
	3	[302]	GETTABLE 	3 0 -2	; "input_dialog"
	4	[302]	CALL     	1 3 1
	5	[303]	RETURN   	0 1
