
main <./spec/unit/input_spec.lua:0,0> (5 instructions, 20 bytes at 0x7fe17cc068c0)
0+ params, 3 slots, 0 upvalues, 0 locals, 2 constants, 1 function
	1	[1]	GETGLOBAL	0 -1	; describe
	2	[1]	LOADK    	1 -2	; "input module"
	3	[129]	CLOSURE  	2 0	; 0x7fe17cc06b60
	4	[1]	CALL     	0 3 1
	5	[129]	RETURN   	0 1

function <./spec/unit/input_spec.lua:1,129> (10 instructions, 40 bytes at 0x7fe17cc06b60)
0 params, 4 slots, 0 upvalues, 1 local, 3 constants, 2 functions
	1	[3]	GETGLOBAL	1 -1	; setup
	2	[6]	CLOSURE  	2 0	; 0x7fe17cc06d80
	3	[6]	MOVE     	0 0
	4	[3]	CALL     	1 2 1
	5	[8]	GETGLOBAL	1 -2	; describe
	6	[8]	LOADK    	2 -3	; "handleTouchEvPhoenix"
	7	[127]	CLOSURE  	3 1	; 0x7fe17cc06c60
	8	[127]	MOVE     	0 0
	9	[8]	CALL     	1 3 1
	10	[129]	RETURN   	0 1

function <./spec/unit/input_spec.lua:3,6> (8 instructions, 32 bytes at 0x7fe17cc06d80)
0 params, 2 slots, 1 upvalue, 0 locals, 3 constants, 0 functions
	1	[4]	GETGLOBAL	0 -1	; require
	2	[4]	LOADK    	1 -2	; "commonrequire"
	3	[4]	CALL     	0 2 1
	4	[5]	GETGLOBAL	0 -1	; require
	5	[5]	LOADK    	1 -3	; "device/input"
	6	[5]	CALL     	0 2 2
	7	[5]	SETUPVAL 	0 0	; Input
	8	[6]	RETURN   	0 1

function <./spec/unit/input_spec.lua:8,127> (6 instructions, 24 bytes at 0x7fe17cc06c60)
0 params, 3 slots, 1 upvalue, 0 locals, 2 constants, 1 function
	1	[40]	GETGLOBAL	0 -1	; it
	2	[40]	LOADK    	1 -2	; "should set cur_slot correctly"
	3	[126]	CLOSURE  	2 0	; 0x7fe17cc07400
	4	[126]	GETUPVAL 	0 0	; Input
	5	[40]	CALL     	0 3 1
	6	[127]	RETURN   	0 1

function <./spec/unit/input_spec.lua:40,126> (151 instructions, 604 bytes at 0x7fe17cc07400)
0 params, 4 slots, 1 upvalue, 1 local, 17 constants, 0 functions
	1	[42]	NEWTABLE 	1 0 3
	2	[43]	SETTABLE 	1 -1 -2	; "type" 3
	3	[44]	SETTABLE 	1 -3 -4	; "code" 57
	4	[45]	SETTABLE 	1 -5 -6	; "value" 1
	5	[46]	MOVE     	0 1
	6	[47]	GETUPVAL 	1 0	; Input
	7	[47]	SELF     	1 1 -7	; "handleTouchEvPhoenix"
	8	[47]	MOVE     	3 0
	9	[47]	CALL     	1 3 1
	10	[48]	GETGLOBAL	1 -8	; assert
	11	[48]	GETTABLE 	1 1 -9	; "is_equal"
	12	[48]	LOADK    	2 -6	; 1
	13	[48]	GETUPVAL 	3 0	; Input
	14	[48]	GETTABLE 	3 3 -10	; "cur_slot"
	15	[48]	CALL     	1 3 1
	16	[49]	NEWTABLE 	1 0 3
	17	[50]	SETTABLE 	1 -1 -2	; "type" 3
	18	[51]	SETTABLE 	1 -3 -11	; "code" 48
	19	[52]	SETTABLE 	1 -5 -6	; "value" 1
	20	[53]	MOVE     	0 1
	21	[54]	GETUPVAL 	1 0	; Input
	22	[54]	SELF     	1 1 -7	; "handleTouchEvPhoenix"
	23	[54]	MOVE     	3 0
	24	[54]	CALL     	1 3 1
	25	[55]	GETGLOBAL	1 -8	; assert
	26	[55]	GETTABLE 	1 1 -9	; "is_equal"
	27	[55]	LOADK    	2 -6	; 1
	28	[55]	GETUPVAL 	3 0	; Input
	29	[55]	GETTABLE 	3 3 -10	; "cur_slot"
	30	[55]	CALL     	1 3 1
	31	[56]	NEWTABLE 	1 0 3
	32	[57]	SETTABLE 	1 -1 -2	; "type" 3
	33	[58]	SETTABLE 	1 -3 -12	; "code" 50
	34	[59]	SETTABLE 	1 -5 -6	; "value" 1
	35	[60]	MOVE     	0 1
	36	[61]	GETUPVAL 	1 0	; Input
	37	[61]	SELF     	1 1 -7	; "handleTouchEvPhoenix"
	38	[61]	MOVE     	3 0
	39	[61]	CALL     	1 3 1
	40	[62]	GETGLOBAL	1 -8	; assert
	41	[62]	GETTABLE 	1 1 -9	; "is_equal"
	42	[62]	LOADK    	2 -6	; 1
	43	[62]	GETUPVAL 	3 0	; Input
	44	[62]	GETTABLE 	3 3 -10	; "cur_slot"
	45	[62]	CALL     	1 3 1
	46	[63]	NEWTABLE 	1 0 3
	47	[64]	SETTABLE 	1 -1 -2	; "type" 3
	48	[65]	SETTABLE 	1 -3 -13	; "code" 53
	49	[66]	SETTABLE 	1 -5 -14	; "value" 1012
	50	[67]	MOVE     	0 1
	51	[68]	GETUPVAL 	1 0	; Input
	52	[68]	SELF     	1 1 -7	; "handleTouchEvPhoenix"
	53	[68]	MOVE     	3 0
	54	[68]	CALL     	1 3 1
	55	[69]	GETGLOBAL	1 -8	; assert
	56	[69]	GETTABLE 	1 1 -9	; "is_equal"
	57	[69]	LOADK    	2 -6	; 1
	58	[69]	GETUPVAL 	3 0	; Input
	59	[69]	GETTABLE 	3 3 -10	; "cur_slot"
	60	[69]	CALL     	1 3 1
	61	[70]	NEWTABLE 	1 0 3
	62	[71]	SETTABLE 	1 -1 -2	; "type" 3
	63	[72]	SETTABLE 	1 -3 -15	; "code" 54
	64	[73]	SETTABLE 	1 -5 -16	; "value" 914
	65	[74]	MOVE     	0 1
	66	[75]	GETUPVAL 	1 0	; Input
	67	[75]	SELF     	1 1 -7	; "handleTouchEvPhoenix"
	68	[75]	MOVE     	3 0
	69	[75]	CALL     	1 3 1
	70	[76]	GETGLOBAL	1 -8	; assert
	71	[76]	GETTABLE 	1 1 -9	; "is_equal"
	72	[76]	LOADK    	2 -6	; 1
	73	[76]	GETUPVAL 	3 0	; Input
	74	[76]	GETTABLE 	3 3 -10	; "cur_slot"
	75	[76]	CALL     	1 3 1
	76	[91]	NEWTABLE 	1 0 3
	77	[92]	SETTABLE 	1 -1 -2	; "type" 3
	78	[93]	SETTABLE 	1 -3 -4	; "code" 57
	79	[94]	SETTABLE 	1 -5 -17	; "value" 2
	80	[95]	MOVE     	0 1
	81	[96]	GETUPVAL 	1 0	; Input
	82	[96]	SELF     	1 1 -7	; "handleTouchEvPhoenix"
	83	[96]	MOVE     	3 0
	84	[96]	CALL     	1 3 1
	85	[97]	GETGLOBAL	1 -8	; assert
	86	[97]	GETTABLE 	1 1 -9	; "is_equal"
	87	[97]	LOADK    	2 -17	; 2
	88	[97]	GETUPVAL 	3 0	; Input
	89	[97]	GETTABLE 	3 3 -10	; "cur_slot"
	90	[97]	CALL     	1 3 1
	91	[98]	NEWTABLE 	1 0 3
	92	[99]	SETTABLE 	1 -1 -2	; "type" 3
	93	[100]	SETTABLE 	1 -3 -11	; "code" 48
	94	[101]	SETTABLE 	1 -5 -17	; "value" 2
	95	[102]	MOVE     	0 1
	96	[103]	GETUPVAL 	1 0	; Input
	97	[103]	SELF     	1 1 -7	; "handleTouchEvPhoenix"
	98	[103]	MOVE     	3 0
	99	[103]	CALL     	1 3 1
	100	[104]	GETGLOBAL	1 -8	; assert
	101	[104]	GETTABLE 	1 1 -9	; "is_equal"
	102	[104]	LOADK    	2 -17	; 2
	103	[104]	GETUPVAL 	3 0	; Input
	104	[104]	GETTABLE 	3 3 -10	; "cur_slot"
	105	[104]	CALL     	1 3 1
	106	[105]	NEWTABLE 	1 0 3
	107	[106]	SETTABLE 	1 -1 -2	; "type" 3
	108	[107]	SETTABLE 	1 -3 -12	; "code" 50
	109	[108]	SETTABLE 	1 -5 -17	; "value" 2
	110	[109]	MOVE     	0 1
	111	[110]	GETUPVAL 	1 0	; Input
	112	[110]	SELF     	1 1 -7	; "handleTouchEvPhoenix"
	113	[110]	MOVE     	3 0
	114	[110]	CALL     	1 3 1
	115	[111]	GETGLOBAL	1 -8	; assert
	116	[111]	GETTABLE 	1 1 -9	; "is_equal"
	117	[111]	LOADK    	2 -17	; 2
	118	[111]	GETUPVAL 	3 0	; Input
	119	[111]	GETTABLE 	3 3 -10	; "cur_slot"
	120	[111]	CALL     	1 3 1
	121	[112]	NEWTABLE 	1 0 3
	122	[113]	SETTABLE 	1 -1 -2	; "type" 3
	123	[114]	SETTABLE 	1 -3 -13	; "code" 53
	124	[115]	SETTABLE 	1 -5 -14	; "value" 1012
	125	[116]	MOVE     	0 1
	126	[117]	GETUPVAL 	1 0	; Input
	127	[117]	SELF     	1 1 -7	; "handleTouchEvPhoenix"
	128	[117]	MOVE     	3 0
	129	[117]	CALL     	1 3 1
	130	[118]	GETGLOBAL	1 -8	; assert
	131	[118]	GETTABLE 	1 1 -9	; "is_equal"
	132	[118]	LOADK    	2 -17	; 2
	133	[118]	GETUPVAL 	3 0	; Input
	134	[118]	GETTABLE 	3 3 -10	; "cur_slot"
	135	[118]	CALL     	1 3 1
	136	[119]	NEWTABLE 	1 0 3
	137	[120]	SETTABLE 	1 -1 -2	; "type" 3
	138	[121]	SETTABLE 	1 -3 -15	; "code" 54
	139	[122]	SETTABLE 	1 -5 -16	; "value" 914
	140	[123]	MOVE     	0 1
	141	[124]	GETUPVAL 	1 0	; Input
	142	[124]	SELF     	1 1 -7	; "handleTouchEvPhoenix"
	143	[124]	MOVE     	3 0
	144	[124]	CALL     	1 3 1
	145	[125]	GETGLOBAL	1 -8	; assert
	146	[125]	GETTABLE 	1 1 -9	; "is_equal"
	147	[125]	LOADK    	2 -17	; 2
	148	[125]	GETUPVAL 	3 0	; Input
	149	[125]	GETTABLE 	3 3 -10	; "cur_slot"
	150	[125]	CALL     	1 3 1
	151	[126]	RETURN   	0 1
