
main <./plugins/newsdownloader.koplugin/internaldownloadbackend.lua:0,0> (33 instructions, 132 bytes at 0x7f97b8406920)
0+ params, 9 slots, 0 upvalues, 8 locals, 10 constants, 2 functions
	1	[1]	GETGLOBAL	0 -1	; require
	2	[1]	LOADK    	1 -2	; "socket.http"
	3	[1]	CALL     	0 2 2
	4	[2]	GETGLOBAL	1 -1	; require
	5	[2]	LOADK    	2 -3	; "ssl.https"
	6	[2]	CALL     	1 2 2
	7	[3]	GETGLOBAL	2 -1	; require
	8	[3]	LOADK    	3 -4	; "logger"
	9	[3]	CALL     	2 2 2
	10	[4]	GETGLOBAL	3 -1	; require
	11	[4]	LOADK    	4 -5	; "ltn12"
	12	[4]	CALL     	3 2 2
	13	[5]	GETGLOBAL	4 -1	; require
	14	[5]	LOADK    	5 -6	; "socket"
	15	[5]	CALL     	4 2 2
	16	[6]	GETGLOBAL	5 -1	; require
	17	[6]	LOADK    	6 -7	; "socket.url"
	18	[6]	CALL     	5 2 2
	19	[8]	NEWTABLE 	6 0 0
	20	[9]	LOADK    	7 -8	; 5
	21	[37]	CLOSURE  	8 0	; 0x7f97b8406d50
	22	[37]	MOVE     	0 7
	23	[37]	MOVE     	0 2
	24	[37]	MOVE     	0 3
	25	[37]	MOVE     	0 5
	26	[37]	MOVE     	0 0
	27	[37]	MOVE     	0 1
	28	[37]	MOVE     	0 4
	29	[11]	SETTABLE 	6 -9 8	; "getResponseAsString" -
	30	[44]	CLOSURE  	8 1	; 0x7f97b8406640
	31	[39]	SETTABLE 	6 -10 8	; "download" -
	32	[46]	RETURN   	6 2
	33	[46]	RETURN   	0 1

function <./plugins/newsdownloader.koplugin/internaldownloadbackend.lua:11,37> (85 instructions, 340 bytes at 0x7f97b8406d50)
3 params, 15 slots, 7 upvalues, 11 locals, 23 constants, 0 functions
	1	[12]	TEST     	2 0 1
	2	[12]	JMP      	2	; to 5
	3	[13]	LOADK    	2 -1	; 0
	4	[13]	JMP      	7	; to 12
	5	[14]	GETUPVAL 	3 0	; max_redirects
	6	[14]	EQ       	0 2 3
	7	[14]	JMP      	4	; to 12
	8	[15]	GETGLOBAL	3 -2	; error
	9	[15]	LOADK    	4 -3	; "InternalDownloadBackend: reached max redirects: "
	10	[15]	MOVE     	5 2
	11	[15]	CALL     	3 3 1
	12	[17]	GETUPVAL 	3 1	; logger
	13	[17]	GETTABLE 	3 3 -4	; "dbg"
	14	[17]	LOADK    	4 -5	; "InternalDownloadBackend: url :"
	15	[17]	MOVE     	5 1
	16	[17]	CALL     	3 3 1
	17	[18]	NEWTABLE 	3 0 0
	18	[18]	NEWTABLE 	4 0 0
	19	[19]	GETUPVAL 	5 2	; ltn12
	20	[19]	GETTABLE 	5 5 -6	; "sink"
	21	[19]	GETTABLE 	5 5 -7	; "table"
	22	[19]	MOVE     	6 4
	23	[19]	CALL     	5 2 2
	24	[19]	SETTABLE 	3 -6 5	; "sink" -
	25	[20]	SETTABLE 	3 -8 1	; "url" -
	26	[21]	GETUPVAL 	5 3	; socket_url
	27	[21]	GETTABLE 	5 5 -9	; "parse"
	28	[21]	MOVE     	6 1
	29	[21]	CALL     	5 2 2
	30	[23]	GETTABLE 	6 5 -10	; "scheme"
	31	[23]	EQ       	0 6 -11	; - "http"
	32	[23]	JMP      	4	; to 37
	33	[23]	GETUPVAL 	6 4	; http
	34	[23]	GETTABLE 	6 6 -12	; "request"
	35	[23]	TEST     	6 0 1
	36	[23]	JMP      	2	; to 39
	37	[23]	GETUPVAL 	6 5	; https
	38	[23]	GETTABLE 	6 6 -12	; "request"
	39	[24]	GETUPVAL 	7 6	; socket
	40	[24]	GETTABLE 	7 7 -13	; "skip"
	41	[24]	LOADK    	8 -14	; 1
	42	[24]	MOVE     	9 6
	43	[24]	MOVE     	10 3
	44	[24]	CALL     	9 2 0
	45	[24]	CALL     	7 0 4
	46	[26]	EQ       	1 7 -15	; - 200
	47	[26]	JMP      	32	; to 80
	48	[27]	GETUPVAL 	10 1	; logger
	49	[27]	GETTABLE 	10 10 -4	; "dbg"
	50	[27]	LOADK    	11 -16	; "InternalDownloadBackend: HTTP response code <> 200. Response status: "
	51	[27]	MOVE     	12 9
	52	[27]	CALL     	10 3 1
	53	[28]	TEST     	7 0 0
	54	[28]	JMP      	21	; to 76
	55	[28]	LT       	0 -17 7	; 299 -
	56	[28]	JMP      	19	; to 76
	57	[28]	LT       	0 7 -18	; - 400
	58	[28]	JMP      	17	; to 76
	59	[28]	TEST     	8 0 0
	60	[28]	JMP      	15	; to 76
	61	[28]	GETTABLE 	10 8 -19	; "location"
	62	[28]	TEST     	10 0 0
	63	[28]	JMP      	12	; to 76
	64	[29]	GETTABLE 	10 8 -19	; "location"
	65	[30]	GETUPVAL 	11 1	; logger
	66	[30]	GETTABLE 	11 11 -4	; "dbg"
	67	[30]	LOADK    	12 -20	; "InternalDownloadBackend: Redirecting to url: "
	68	[30]	MOVE     	13 10
	69	[30]	CALL     	11 3 1
	70	[31]	SELF     	11 0 -21	; "getResponseAsString"
	71	[31]	MOVE     	13 10
	72	[31]	ADD      	14 2 -14	; - 1
	73	[31]	TAILCALL 	11 4 0
	74	[31]	RETURN   	11 0
	75	[31]	JMP      	4	; to 80
	76	[33]	GETGLOBAL	10 -2	; error
	77	[33]	LOADK    	11 -22	; "InternalDownloadBackend: Don't know how to handle HTTP response status: "
	78	[33]	MOVE     	12 9
	79	[33]	CALL     	10 3 1
	80	[36]	GETGLOBAL	10 -7	; table
	81	[36]	GETTABLE 	10 10 -23	; "concat"
	82	[36]	MOVE     	11 4
	83	[36]	TAILCALL 	10 2 0
	84	[36]	RETURN   	10 0
	85	[37]	RETURN   	0 1

function <./plugins/newsdownloader.koplugin/internaldownloadbackend.lua:39,44> (14 instructions, 56 bytes at 0x7f97b8406640)
3 params, 8 slots, 0 upvalues, 5 locals, 6 constants, 0 functions
	1	[40]	SELF     	3 0 -1	; "getResponseAsString"
	2	[40]	MOVE     	5 1
	3	[40]	CALL     	3 3 2
	4	[41]	GETGLOBAL	4 -2	; io
	5	[41]	GETTABLE 	4 4 -3	; "open"
	6	[41]	MOVE     	5 2
	7	[41]	LOADK    	6 -4	; "w"
	8	[41]	CALL     	4 3 2
	9	[42]	SELF     	5 4 -5	; "write"
	10	[42]	MOVE     	7 3
	11	[42]	CALL     	5 3 1
	12	[43]	SELF     	5 4 -6	; "close"
	13	[43]	CALL     	5 2 1
	14	[44]	RETURN   	0 1
