-- BYTECODE -- key.lua:7-21
0001    TDUP     3   0
0002    TSETS    1   3   1  ; "key"
0003    TSETS    2   3   2  ; "modifiers"
0004    KPRI     4   2
0005    TSETV    4   3   1
0006    GGET     4   3      ; "pairs"
0007    MOV      5   2
0008    CALL     4   4   2
0009    ISNEXT   7 => 0014
0010 => ISF          8
0011    JMP      9 => 0014
0012    KPRI     9   2
0013    TSETV    9   3   7
0014 => ITERN    7   3   3
0015    ITERL    7 => 0010
0016    GGET     4   4      ; "setmetatable"
0017    MOV      5   3
0018    MOV      6   0
0019    CALL     4   1   3
0020    TSETS    0   0   5  ; "__index"
0021    RET1     3   2

-- BYTECODE -- key.lua:23-25
0001    GGET     1   0      ; "table"
0002    TGETS    1   1   1  ; "concat"
0003    MOV      3   0
0004    TGETS    2   0   2  ; "getSequence"
0005    CALL     2   2   2
0006    KSTR     3   3      ; "-"
0007    CALLT    1   3

-- BYTECODE -- key.lua:34-42
0001    TNEW     1   0
0002    GGET     2   0      ; "pairs"
0003    TGETS    3   0   1  ; "modifiers"
0004    CALL     2   4   2
0005    ISNEXT   5 => 0013
0006 => ISF          6
0007    JMP      7 => 0013
0008    GGET     7   2      ; "table"
0009    TGETS    7   7   3  ; "insert"
0010    MOV      8   1
0011    MOV      9   5
0012    CALL     7   1   3
0013 => ITERN    5   3   3
0014    ITERL    5 => 0006
0015    GGET     2   2      ; "table"
0016    TGETS    2   2   3  ; "insert"
0017    MOV      3   1
0018    TGETS    4   0   4  ; "key"
0019    CALL     2   1   3
0020    RET0     0   1

-- BYTECODE -- key.lua:57-89
0001    TNEW     2   0
0002    GGET     3   0      ; "ipairs"
0003    MOV      4   1
0004    CALL     3   4   2
0005    JMP      6 => 0040
0006 => GGET     8   1      ; "type"
0007    MOV      9   7
0008    CALL     8   2   2
0009    ISNES    8   2      ; "table"
0010    JMP      8 => 0028
0011    KPRI     8   1
0012    GGET     9   0      ; "ipairs"
0013    MOV     10   7
0014    CALL     9   4   2
0015    JMP     12 => 0021
0016 => TGETV   14   0  13
0017    ISF         14
0018    JMP     15 => 0021
0019    KPRI     8   2
0020    JMP      9 => 0023
0021 => ITERC   12   3   3
0022    ITERL   12 => 0016
0023 => IST          8
0024    JMP      9 => 0040
0025    KPRI     9   1
0026    RET1     9   2
0027    JMP      8 => 0040
0028 => TGETV    8   0   7
0029    IST          8
0030    JMP      8 => 0034
0031    KPRI     8   1
0032    RET1     8   2
0033    JMP      8 => 0040
0034 => TGETS    8   0   3  ; "modifiers"
0035    TGETV    8   8   7
0036    ISEQP    8   0
0037    JMP      8 => 0040
0038    KPRI     8   2
0039    TSETV    8   2   7
0040 => ITERC    6   3   3
0041    ITERL    6 => 0006
0042    GGET     3   4      ; "pairs"
0043    TGETS    4   0   3  ; "modifiers"
0044    CALL     3   4   2
0045    ISNEXT   6 => 0053
0046 => ISF          7
0047    JMP      8 => 0053
0048    TGETV    8   2   6
0049    IST          8
0050    JMP      8 => 0053
0051    KPRI     8   1
0052    RET1     8   2
0053 => ITERN    6   3   3
0054    ITERL    6 => 0046
0055    KPRI     3   2
0056    RET1     3   2

-- BYTECODE -- key.lua:0-92
0001    TNEW     0   0
0002    FNEW     1   1      ; key.lua:7
0003    TSETS    1   0   0  ; "new"
0004    FNEW     1   3      ; key.lua:23
0005    TSETS    1   0   2  ; "__tostring"
0006    FNEW     1   5      ; key.lua:34
0007    TSETS    1   0   4  ; "getSequence"
0008    FNEW     1   7      ; key.lua:57
0009    TSETS    1   0   6  ; "match"
0010    UCLO     0 => 0011
0011 => RET1     0   2

