
main <./frontend/device/key.lua:0,0> (11 instructions, 44 bytes at 0x7ff402c068c0)
0+ params, 2 slots, 0 upvalues, 1 local, 4 constants, 4 functions
	1	[5]	NEWTABLE 	0 0 0
	2	[21]	CLOSURE  	1 0	; 0x7ff402c06b60
	3	[7]	SETTABLE 	0 -1 1	; "new" -
	4	[25]	CLOSURE  	1 1	; 0x7ff402c07070
	5	[23]	SETTABLE 	0 -2 1	; "__tostring" -
	6	[42]	CLOSURE  	1 2	; 0x7ff402c074f0
	7	[34]	SETTABLE 	0 -3 1	; "getSequence" -
	8	[89]	CLOSURE  	1 3	; 0x7ff402c07640
	9	[57]	SETTABLE 	0 -4 1	; "match" -
	10	[91]	RETURN   	0 2
	11	[91]	RETURN   	0 1

function <./frontend/device/key.lua:7,21> (20 instructions, 80 bytes at 0x7ff402c06b60)
3 params, 10 slots, 0 upvalues, 9 locals, 6 constants, 0 functions
	1	[8]	NEWTABLE 	3 0 2
	2	[8]	SETTABLE 	3 -1 1	; "key" -
	3	[8]	SETTABLE 	3 -2 2	; "modifiers" -
	4	[11]	SETTABLE 	3 1 -3	; - true
	5	[12]	GETGLOBAL	4 -4	; pairs
	6	[12]	MOVE     	5 2
	7	[12]	CALL     	4 2 4
	8	[12]	JMP      	3	; to 12
	9	[13]	TEST     	8 0 0
	10	[13]	JMP      	1	; to 12
	11	[14]	SETTABLE 	3 7 -3	; - true
	12	[12]	TFORLOOP 	4 2
	13	[15]	JMP      	-5	; to 9
	14	[18]	GETGLOBAL	4 -5	; setmetatable
	15	[18]	MOVE     	5 3
	16	[18]	MOVE     	6 0
	17	[18]	CALL     	4 3 1
	18	[19]	SETTABLE 	0 -6 0	; "__index" -
	19	[20]	RETURN   	3 2
	20	[21]	RETURN   	0 1

function <./frontend/device/key.lua:23,25> (8 instructions, 32 bytes at 0x7ff402c07070)
1 param, 4 slots, 0 upvalues, 1 local, 4 constants, 0 functions
	1	[24]	GETGLOBAL	1 -1	; table
	2	[24]	GETTABLE 	1 1 -2	; "concat"
	3	[24]	SELF     	2 0 -3	; "getSequence"
	4	[24]	CALL     	2 2 2
	5	[24]	LOADK    	3 -4	; "-"
	6	[24]	TAILCALL 	1 3 0
	7	[24]	RETURN   	1 0
	8	[25]	RETURN   	0 1

function <./frontend/device/key.lua:34,42> (20 instructions, 80 bytes at 0x7ff402c074f0)
1 param, 10 slots, 0 upvalues, 7 locals, 5 constants, 0 functions
	1	[35]	NEWTABLE 	1 0 0
	2	[36]	GETGLOBAL	2 -1	; pairs
	3	[36]	GETTABLE 	3 0 -2	; "modifiers"
	4	[36]	CALL     	2 2 4
	5	[36]	JMP      	7	; to 13
	6	[37]	TEST     	6 0 0
	7	[37]	JMP      	5	; to 13
	8	[38]	GETGLOBAL	7 -3	; table
	9	[38]	GETTABLE 	7 7 -4	; "insert"
	10	[38]	MOVE     	8 1
	11	[38]	MOVE     	9 5
	12	[38]	CALL     	7 3 1
	13	[36]	TFORLOOP 	2 2
	14	[39]	JMP      	-9	; to 6
	15	[41]	GETGLOBAL	2 -3	; table
	16	[41]	GETTABLE 	2 2 -4	; "insert"
	17	[41]	MOVE     	3 1
	18	[41]	GETTABLE 	4 0 -5	; "key"
	19	[41]	CALL     	2 3 1
	20	[42]	RETURN   	0 1

function <./frontend/device/key.lua:57,89> (56 instructions, 224 bytes at 0x7ff402c07640)
2 params, 15 slots, 0 upvalues, 19 locals, 7 constants, 0 functions
	1	[58]	NEWTABLE 	2 0 0
	2	[59]	GETGLOBAL	3 -1	; ipairs
	3	[59]	MOVE     	4 1
	4	[59]	CALL     	3 2 4
	5	[59]	JMP      	33	; to 39
	6	[60]	GETGLOBAL	8 -2	; type
	7	[60]	MOVE     	9 7
	8	[60]	CALL     	8 2 2
	9	[60]	EQ       	0 8 -3	; - "table"
	10	[60]	JMP      	17	; to 28
	11	[61]	LOADBOOL 	8 0 0
	12	[62]	GETGLOBAL	9 -1	; ipairs
	13	[62]	MOVE     	10 7
	14	[62]	CALL     	9 2 4
	15	[62]	JMP      	5	; to 21
	16	[63]	GETTABLE 	14 0 13
	17	[63]	TEST     	14 0 0
	18	[63]	JMP      	2	; to 21
	19	[64]	LOADBOOL 	8 1 0
	20	[65]	JMP      	2	; to 23
	21	[62]	TFORLOOP 	9 2
	22	[66]	JMP      	-7	; to 16
	23	[68]	TEST     	8 0 1
	24	[68]	JMP      	14	; to 39
	25	[70]	LOADBOOL 	9 0 0
	26	[70]	RETURN   	9 2
	27	[71]	JMP      	11	; to 39
	28	[72]	GETTABLE 	8 0 7
	29	[72]	TEST     	8 0 1
	30	[72]	JMP      	3	; to 34
	31	[74]	LOADBOOL 	8 0 0
	32	[74]	RETURN   	8 2
	33	[74]	JMP      	5	; to 39
	34	[75]	GETTABLE 	8 0 -4	; "modifiers"
	35	[75]	GETTABLE 	8 8 7
	36	[75]	EQ       	1 8 -5	; - nil
	37	[75]	JMP      	1	; to 39
	38	[77]	SETTABLE 	2 7 -6	; - true
	39	[59]	TFORLOOP 	3 2
	40	[78]	JMP      	-35	; to 6
	41	[81]	GETGLOBAL	3 -7	; pairs
	42	[81]	GETTABLE 	4 0 -4	; "modifiers"
	43	[81]	CALL     	3 2 4
	44	[81]	JMP      	7	; to 52
	45	[82]	TEST     	7 0 0
	46	[82]	JMP      	5	; to 52
	47	[82]	GETTABLE 	8 2 6
	48	[82]	TEST     	8 0 1
	49	[82]	JMP      	2	; to 52
	50	[84]	LOADBOOL 	8 0 0
	51	[84]	RETURN   	8 2
	52	[81]	TFORLOOP 	3 2
	53	[85]	JMP      	-9	; to 45
	54	[88]	LOADBOOL 	3 1 0
	55	[88]	RETURN   	3 2
	56	[89]	RETURN   	0 1
