
main <./frontend/ui/widget/keyboardlayoutdialog.lua:0,0> (116 instructions, 464 bytes at 0x7fbb8f4068f0)
0+ params, 25 slots, 0 upvalues, 19 locals, 48 constants, 3 functions
	1	[5]	GETGLOBAL	0 -1	; require
	2	[5]	LOADK    	1 -2	; "ffi/blitbuffer"
	3	[5]	CALL     	0 2 2
	4	[6]	GETGLOBAL	1 -1	; require
	5	[6]	LOADK    	2 -3	; "ui/widget/buttontable"
	6	[6]	CALL     	1 2 2
	7	[7]	GETGLOBAL	2 -1	; require
	8	[7]	LOADK    	3 -4	; "ui/widget/container/centercontainer"
	9	[7]	CALL     	2 2 2
	10	[8]	GETGLOBAL	3 -1	; require
	11	[8]	LOADK    	4 -5	; "ui/font"
	12	[8]	CALL     	3 2 2
	13	[9]	GETGLOBAL	4 -1	; require
	14	[9]	LOADK    	5 -6	; "ui/widget/container/framecontainer"
	15	[9]	CALL     	4 2 2
	16	[10]	GETGLOBAL	5 -1	; require
	17	[10]	LOADK    	6 -7	; "ui/geometry"
	18	[10]	CALL     	5 2 2
	19	[11]	GETGLOBAL	6 -1	; require
	20	[11]	LOADK    	7 -8	; "ui/widget/container/inputcontainer"
	21	[11]	CALL     	6 2 2
	22	[12]	GETGLOBAL	7 -1	; require
	23	[12]	LOADK    	8 -9	; "ui/language"
	24	[12]	CALL     	7 2 2
	25	[13]	GETGLOBAL	8 -1	; require
	26	[13]	LOADK    	9 -10	; "ui/widget/linewidget"
	27	[13]	CALL     	8 2 2
	28	[14]	GETGLOBAL	9 -1	; require
	29	[14]	LOADK    	10 -11	; "ui/widget/radiobuttontable"
	30	[14]	CALL     	9 2 2
	31	[15]	GETGLOBAL	10 -1	; require
	32	[15]	LOADK    	11 -12	; "ui/size"
	33	[15]	CALL     	10 2 2
	34	[16]	GETGLOBAL	11 -1	; require
	35	[16]	LOADK    	12 -13	; "ui/widget/textwidget"
	36	[16]	CALL     	11 2 2
	37	[17]	GETGLOBAL	12 -1	; require
	38	[17]	LOADK    	13 -14	; "ui/uimanager"
	39	[17]	CALL     	12 2 2
	40	[18]	GETGLOBAL	13 -1	; require
	41	[18]	LOADK    	14 -15	; "ui/widget/verticalgroup"
	42	[18]	CALL     	13 2 2
	43	[19]	GETGLOBAL	14 -1	; require
	44	[19]	LOADK    	15 -16	; "ui/widget/verticalspan"
	45	[19]	CALL     	14 2 2
	46	[20]	GETGLOBAL	15 -1	; require
	47	[20]	LOADK    	16 -17	; "gettext"
	48	[20]	CALL     	15 2 2
	49	[21]	GETGLOBAL	16 -1	; require
	50	[21]	LOADK    	17 -18	; "device"
	51	[21]	CALL     	16 2 2
	52	[21]	GETTABLE 	16 16 -19	; "screen"
	53	[22]	GETGLOBAL	17 -1	; require
	54	[22]	LOADK    	18 -20	; "ffi/util"
	55	[22]	CALL     	17 2 2
	56	[22]	GETTABLE 	17 17 -21	; "orderedPairs"
	57	[24]	SELF     	18 6 -22	; "new"
	58	[24]	NEWTABLE 	20 0 10
	59	[25]	SETTABLE 	20 -23 -24	; "is_always_active" true
	60	[26]	MOVE     	21 15
	61	[26]	LOADK    	22 -26	; "Keyboard layout"
	62	[26]	CALL     	21 2 2
	63	[26]	SETTABLE 	20 -25 21	; "title" -
	64	[27]	SETTABLE 	20 -27 -24	; "modal" true
	65	[28]	SELF     	21 16 -29	; "getWidth"
	66	[28]	CALL     	21 2 2
	67	[28]	MUL      	21 21 -30	; - 0.8
	68	[28]	SETTABLE 	20 -28 21	; "width" -
	69	[29]	SELF     	21 3 -32	; "getFace"
	70	[29]	LOADK    	23 -33	; "cfont"
	71	[29]	LOADK    	24 -34	; 22
	72	[29]	CALL     	21 4 2
	73	[29]	SETTABLE 	20 -31 21	; "face" -
	74	[30]	SELF     	21 3 -32	; "getFace"
	75	[30]	LOADK    	23 -36	; "x_smalltfont"
	76	[30]	CALL     	21 3 2
	77	[30]	SETTABLE 	20 -35 21	; "title_face" -
	78	[31]	GETTABLE 	21 10 -38	; "padding"
	79	[31]	GETTABLE 	21 21 -39	; "default"
	80	[31]	SETTABLE 	20 -37 21	; "title_padding" -
	81	[32]	GETTABLE 	21 10 -41	; "margin"
	82	[32]	GETTABLE 	21 21 -25	; "title"
	83	[32]	SETTABLE 	20 -40 21	; "title_margin" -
	84	[33]	GETTABLE 	21 10 -38	; "padding"
	85	[33]	GETTABLE 	21 21 -39	; "default"
	86	[33]	SETTABLE 	20 -42 21	; "button_padding" -
	87	[34]	GETTABLE 	21 10 -44	; "border"
	88	[34]	GETTABLE 	21 21 -45	; "window"
	89	[34]	SETTABLE 	20 -43 21	; "border_size" -
	90	[24]	CALL     	18 3 2
	91	[147]	CLOSURE  	19 0	; 0x7fbb8f407100
	92	[147]	MOVE     	0 4
	93	[147]	MOVE     	0 11
	94	[147]	MOVE     	0 8
	95	[147]	MOVE     	0 5
	96	[147]	MOVE     	0 10
	97	[147]	MOVE     	0 17
	98	[147]	MOVE     	0 7
	99	[147]	MOVE     	0 15
	100	[147]	MOVE     	0 12
	101	[147]	MOVE     	0 9
	102	[147]	MOVE     	0 1
	103	[147]	MOVE     	0 0
	104	[147]	MOVE     	0 13
	105	[147]	MOVE     	0 14
	106	[147]	MOVE     	0 2
	107	[147]	MOVE     	0 16
	108	[38]	SETTABLE 	18 -46 19	; "init" -
	109	[154]	CLOSURE  	19 1	; 0x7fbb8f408300
	110	[154]	MOVE     	0 12
	111	[150]	SETTABLE 	18 -47 19	; "onShow" -
	112	[161]	CLOSURE  	19 2	; 0x7fbb8f4090c0
	113	[161]	MOVE     	0 12
	114	[156]	SETTABLE 	18 -48 19	; "onCloseWidget" -
	115	[163]	RETURN   	18 2
	116	[163]	RETURN   	0 1

function <./frontend/ui/widget/keyboardlayoutdialog.lua:38,147> (231 instructions, 924 bytes at 0x7fbb8f407100)
1 param, 22 slots, 16 upvalues, 8 locals, 64 constants, 2 functions
	1	[40]	GETUPVAL 	1 0	; FrameContainer
	2	[40]	SELF     	1 1 -2	; "new"
	3	[40]	NEWTABLE 	3 0 3
	4	[41]	GETTABLE 	4 0 -4	; "title_padding"
	5	[41]	SETTABLE 	3 -3 4	; "padding" -
	6	[42]	GETTABLE 	4 0 -6	; "title_margin"
	7	[42]	SETTABLE 	3 -5 4	; "margin" -
	8	[43]	SETTABLE 	3 -7 -8	; "bordersize" 0
	9	[44]	GETUPVAL 	4 1	; TextWidget
	10	[44]	SELF     	4 4 -2	; "new"
	11	[44]	NEWTABLE 	6 0 3
	12	[45]	GETTABLE 	7 0 -10	; "title"
	13	[45]	SETTABLE 	6 -9 7	; "text" -
	14	[46]	GETTABLE 	7 0 -12	; "title_face"
	15	[46]	SETTABLE 	6 -11 7	; "face" -
	16	[47]	GETTABLE 	7 0 -14	; "width"
	17	[47]	SETTABLE 	6 -13 7	; "max_width" -
	18	[44]	CALL     	4 3 0
	19	[49]	SETLIST  	3 0 1	; 1
	20	[40]	CALL     	1 3 2
	21	[49]	SETTABLE 	0 -1 1	; "title_widget" -
	22	[50]	GETUPVAL 	1 2	; LineWidget
	23	[50]	SELF     	1 1 -2	; "new"
	24	[50]	NEWTABLE 	3 0 1
	25	[51]	GETUPVAL 	4 3	; Geom
	26	[51]	SELF     	4 4 -2	; "new"
	27	[51]	NEWTABLE 	6 0 2
	28	[52]	GETTABLE 	7 0 -14	; "width"
	29	[52]	SETTABLE 	6 -17 7	; "w" -
	30	[53]	GETUPVAL 	7 4	; Size
	31	[53]	GETTABLE 	7 7 -19	; "line"
	32	[53]	GETTABLE 	7 7 -20	; "thick"
	33	[53]	SETTABLE 	6 -18 7	; "h" -
	34	[51]	CALL     	4 3 2
	35	[54]	SETTABLE 	3 -16 4	; "dimen" -
	36	[50]	CALL     	1 3 2
	37	[55]	SETTABLE 	0 -15 1	; "title_bar" -
	38	[57]	NEWTABLE 	1 0 0
	39	[58]	NEWTABLE 	2 0 0
	40	[59]	GETUPVAL 	3 5	; orderedPairs
	41	[59]	GETTABLE 	4 0 -21	; "parent"
	42	[59]	GETTABLE 	4 4 -22	; "keyboard"
	43	[59]	GETTABLE 	4 4 -23	; "lang_to_keyboard_layout"
	44	[59]	CALL     	3 2 4
	45	[59]	JMP      	22	; to 68
	46	[60]	GETGLOBAL	8 -24	; table
	47	[60]	GETTABLE 	8 8 -25	; "insert"
	48	[60]	MOVE     	9 2
	49	[60]	NEWTABLE 	10 1 0
	50	[60]	NEWTABLE 	11 0 3
	51	[62]	GETUPVAL 	12 6	; Language
	52	[62]	SELF     	12 12 -26	; "getLanguageName"
	53	[62]	MOVE     	14 6
	54	[62]	CALL     	12 3 2
	55	[62]	SETTABLE 	11 -9 12	; "text" -
	56	[63]	GETTABLE 	12 0 -21	; "parent"
	57	[63]	GETTABLE 	12 12 -22	; "keyboard"
	58	[63]	SELF     	12 12 -28	; "getKeyboardLayout"
	59	[63]	CALL     	12 2 2
	60	[63]	EQ       	1 12 6
	61	[63]	JMP      	1	; to 63
	62	[63]	LOADBOOL 	12 0 1
	63	[63]	LOADBOOL 	12 1 0
	64	[63]	SETTABLE 	11 -27 12	; "checked" -
	65	[64]	SETTABLE 	11 -29 6	; "provider" -
	66	[66]	SETLIST  	10 1 1	; 1
	67	[60]	CALL     	8 3 1
	68	[59]	TFORLOOP 	3 2
	69	[66]	JMP      	-24	; to 46
	70	[69]	GETGLOBAL	3 -24	; table
	71	[69]	GETTABLE 	3 3 -25	; "insert"
	72	[69]	MOVE     	4 1
	73	[69]	NEWTABLE 	5 2 0
	74	[69]	NEWTABLE 	6 0 2
	75	[71]	GETUPVAL 	7 7	; _
	76	[71]	LOADK    	8 -30	; "Cancel"
	77	[71]	CALL     	7 2 2
	78	[71]	SETTABLE 	6 -9 7	; "text" -
	79	[74]	CLOSURE  	7 0	; 0x7fbb8f407f60
	80	[74]	GETUPVAL 	0 8	; UIManager
	81	[74]	MOVE     	0 0
	82	[74]	SETTABLE 	6 -31 7	; "callback" -
	83	[75]	NEWTABLE 	7 0 3
	84	[77]	GETUPVAL 	8 7	; _
	85	[77]	LOADK    	9 -32	; "Switch to layout"
	86	[77]	CALL     	8 2 2
	87	[77]	SETTABLE 	7 -9 8	; "text" -
	88	[78]	SETTABLE 	7 -33 -34	; "is_enter_default" true
	89	[83]	CLOSURE  	8 1	; 0x7fbb8f407d10
	90	[83]	MOVE     	0 0
	91	[83]	GETUPVAL 	0 8	; UIManager
	92	[83]	SETTABLE 	7 -31 8	; "callback" -
	93	[85]	SETLIST  	5 2 1	; 1
	94	[69]	CALL     	3 3 1
	95	[87]	GETUPVAL 	3 9	; RadioButtonTable
	96	[87]	SELF     	3 3 -2	; "new"
	97	[87]	NEWTABLE 	5 0 6
	98	[88]	SETTABLE 	5 -36 2	; "radio_buttons" -
	99	[89]	GETTABLE 	6 0 -14	; "width"
	100	[89]	MUL      	6 6 -37	; - 0.9
	101	[89]	SETTABLE 	5 -14 6	; "width" -
	102	[90]	SETTABLE 	5 -38 -34	; "focused" true
	103	[91]	SETTABLE 	5 -39 -40	; "scroll" false
	104	[92]	SETTABLE 	5 -21 0	; "parent" -
	105	[93]	GETTABLE 	6 0 -11	; "face"
	106	[93]	SETTABLE 	5 -11 6	; "face" -
	107	[87]	CALL     	3 3 2
	108	[94]	SETTABLE 	0 -35 3	; "radio_button_table" -
	109	[97]	GETUPVAL 	3 10	; ButtonTable
	110	[97]	SELF     	3 3 -2	; "new"
	111	[97]	NEWTABLE 	5 0 6
	112	[98]	GETTABLE 	6 0 -14	; "width"
	113	[98]	GETTABLE 	7 0 -42	; "button_padding"
	114	[98]	MUL      	7 -43 7	; 2 -
	115	[98]	SUB      	6 6 7
	116	[98]	SETTABLE 	5 -14 6	; "width" -
	117	[99]	SETTABLE 	5 -44 -45	; "button_font_face" "cfont"
	118	[100]	SETTABLE 	5 -46 -47	; "button_font_size" 20
	119	[101]	SETTABLE 	5 -48 1	; "buttons" -
	120	[102]	SETTABLE 	5 -49 -34	; "zero_sep" true
	121	[103]	SETTABLE 	5 -50 0	; "show_parent" -
	122	[97]	CALL     	3 3 2
	123	[104]	SETTABLE 	0 -41 3	; "button_table" -
	124	[106]	GETUPVAL 	3 0	; FrameContainer
	125	[106]	SELF     	3 3 -2	; "new"
	126	[106]	NEWTABLE 	5 0 5
	127	[107]	GETUPVAL 	6 4	; Size
	128	[107]	GETTABLE 	6 6 -52	; "radius"
	129	[107]	GETTABLE 	6 6 -53	; "window"
	130	[107]	SETTABLE 	5 -52 6	; "radius" -
	131	[108]	GETUPVAL 	6 4	; Size
	132	[108]	GETTABLE 	6 6 -54	; "border"
	133	[108]	GETTABLE 	6 6 -53	; "window"
	134	[108]	SETTABLE 	5 -7 6	; "bordersize" -
	135	[109]	SETTABLE 	5 -3 -8	; "padding" 0
	136	[110]	SETTABLE 	5 -5 -8	; "margin" 0
	137	[111]	GETUPVAL 	6 11	; Blitbuffer
	138	[111]	GETTABLE 	6 6 -56	; "COLOR_WHITE"
	139	[111]	SETTABLE 	5 -55 6	; "background" -
	140	[112]	GETUPVAL 	6 12	; VerticalGroup
	141	[112]	SELF     	6 6 -2	; "new"
	142	[112]	NEWTABLE 	8 5 1
	143	[113]	SETTABLE 	8 -57 -58	; "align" "center"
	144	[114]	GETTABLE 	9 0 -1	; "title_widget"
	145	[115]	GETTABLE 	10 0 -15	; "title_bar"
	146	[116]	GETUPVAL 	11 13	; VerticalSpan
	147	[116]	SELF     	11 11 -2	; "new"
	148	[116]	NEWTABLE 	13 0 1
	149	[117]	GETUPVAL 	14 4	; Size
	150	[117]	GETTABLE 	14 14 -59	; "span"
	151	[117]	GETTABLE 	14 14 -60	; "vertical_large"
	152	[117]	MUL      	14 14 -43	; - 2
	153	[117]	SETTABLE 	13 -14 14	; "width" -
	154	[116]	CALL     	11 3 2
	155	[119]	GETUPVAL 	12 14	; CenterContainer
	156	[119]	SELF     	12 12 -2	; "new"
	157	[119]	NEWTABLE 	14 1 1
	158	[120]	GETUPVAL 	15 3	; Geom
	159	[120]	SELF     	15 15 -2	; "new"
	160	[120]	NEWTABLE 	17 0 2
	161	[121]	GETTABLE 	18 0 -15	; "title_bar"
	162	[121]	SELF     	18 18 -61	; "getSize"
	163	[121]	CALL     	18 2 2
	164	[121]	GETTABLE 	18 18 -17	; "w"
	165	[121]	SETTABLE 	17 -17 18	; "w" -
	166	[122]	GETTABLE 	18 0 -35	; "radio_button_table"
	167	[122]	SELF     	18 18 -61	; "getSize"
	168	[122]	CALL     	18 2 2
	169	[122]	GETTABLE 	18 18 -18	; "h"
	170	[122]	SETTABLE 	17 -18 18	; "h" -
	171	[120]	CALL     	15 3 2
	172	[123]	SETTABLE 	14 -16 15	; "dimen" -
	173	[125]	GETTABLE 	15 0 -35	; "radio_button_table"
	174	[125]	SETLIST  	14 1 1	; 1
	175	[119]	CALL     	12 3 2
	176	[126]	GETUPVAL 	13 13	; VerticalSpan
	177	[126]	SELF     	13 13 -2	; "new"
	178	[126]	NEWTABLE 	15 0 1
	179	[127]	GETUPVAL 	16 4	; Size
	180	[127]	GETTABLE 	16 16 -59	; "span"
	181	[127]	GETTABLE 	16 16 -60	; "vertical_large"
	182	[127]	MUL      	16 16 -43	; - 2
	183	[127]	SETTABLE 	15 -14 16	; "width" -
	184	[126]	CALL     	13 3 2
	185	[130]	GETUPVAL 	14 14	; CenterContainer
	186	[130]	SELF     	14 14 -2	; "new"
	187	[130]	NEWTABLE 	16 1 1
	188	[131]	GETUPVAL 	17 3	; Geom
	189	[131]	SELF     	17 17 -2	; "new"
	190	[131]	NEWTABLE 	19 0 2
	191	[132]	GETTABLE 	20 0 -15	; "title_bar"
	192	[132]	SELF     	20 20 -61	; "getSize"
	193	[132]	CALL     	20 2 2
	194	[132]	GETTABLE 	20 20 -17	; "w"
	195	[132]	SETTABLE 	19 -17 20	; "w" -
	196	[133]	GETTABLE 	20 0 -41	; "button_table"
	197	[133]	SELF     	20 20 -61	; "getSize"
	198	[133]	CALL     	20 2 2
	199	[133]	GETTABLE 	20 20 -18	; "h"
	200	[133]	SETTABLE 	19 -18 20	; "h" -
	201	[131]	CALL     	17 3 2
	202	[134]	SETTABLE 	16 -16 17	; "dimen" -
	203	[136]	GETTABLE 	17 0 -41	; "button_table"
	204	[136]	SETLIST  	16 1 1	; 1
	205	[130]	CALL     	14 3 0
	206	[137]	SETLIST  	8 0 1	; 1
	207	[112]	CALL     	6 3 0
	208	[138]	SETLIST  	5 0 1	; 1
	209	[106]	CALL     	3 3 2
	210	[138]	SETTABLE 	0 -51 3	; "dialog_frame" -
	211	[140]	GETUPVAL 	3 14	; CenterContainer
	212	[140]	SELF     	3 3 -2	; "new"
	213	[140]	NEWTABLE 	5 1 1
	214	[141]	GETUPVAL 	6 3	; Geom
	215	[141]	SELF     	6 6 -2	; "new"
	216	[141]	NEWTABLE 	8 0 2
	217	[142]	GETUPVAL 	9 15	; Screen
	218	[142]	SELF     	9 9 -63	; "getWidth"
	219	[142]	CALL     	9 2 2
	220	[142]	SETTABLE 	8 -17 9	; "w" -
	221	[143]	GETUPVAL 	9 15	; Screen
	222	[143]	SELF     	9 9 -64	; "getHeight"
	223	[143]	CALL     	9 2 2
	224	[143]	SETTABLE 	8 -18 9	; "h" -
	225	[141]	CALL     	6 3 2
	226	[144]	SETTABLE 	5 -16 6	; "dimen" -
	227	[146]	GETTABLE 	6 0 -51	; "dialog_frame"
	228	[146]	SETLIST  	5 1 1	; 1
	229	[140]	CALL     	3 3 2
	230	[146]	SETTABLE 	0 -62 3	; 1 -
	231	[147]	RETURN   	0 1

function <./frontend/ui/widget/keyboardlayoutdialog.lua:72,74> (7 instructions, 28 bytes at 0x7fbb8f407f60)
0 params, 3 slots, 2 upvalues, 0 locals, 3 constants, 0 functions
	1	[73]	GETUPVAL 	0 0	; UIManager
	2	[73]	SELF     	0 0 -1	; "close"
	3	[73]	GETUPVAL 	2 1	; self
	4	[73]	GETTABLE 	2 2 -2	; "parent"
	5	[73]	GETTABLE 	2 2 -3	; "keyboard_layout_dialog"
	6	[73]	CALL     	0 3 1
	7	[74]	RETURN   	0 1

function <./frontend/ui/widget/keyboardlayoutdialog.lua:79,83> (19 instructions, 76 bytes at 0x7fbb8f407d10)
0 params, 4 slots, 2 upvalues, 1 local, 8 constants, 0 functions
	1	[80]	GETUPVAL 	0 0	; self
	2	[80]	GETTABLE 	0 0 -1	; "parent"
	3	[80]	GETTABLE 	0 0 -2	; "keyboard_layout_dialog"
	4	[80]	GETTABLE 	0 0 -3	; "radio_button_table"
	5	[80]	GETTABLE 	0 0 -4	; "checked_button"
	6	[80]	GETTABLE 	0 0 -5	; "provider"
	7	[81]	GETUPVAL 	1 0	; self
	8	[81]	GETTABLE 	1 1 -1	; "parent"
	9	[81]	GETTABLE 	1 1 -6	; "keyboard"
	10	[81]	SELF     	1 1 -7	; "setKeyboardLayout"
	11	[81]	MOVE     	3 0
	12	[81]	CALL     	1 3 1
	13	[82]	GETUPVAL 	1 1	; UIManager
	14	[82]	SELF     	1 1 -8	; "close"
	15	[82]	GETUPVAL 	3 0	; self
	16	[82]	GETTABLE 	3 3 -1	; "parent"
	17	[82]	GETTABLE 	3 3 -2	; "keyboard_layout_dialog"
	18	[82]	CALL     	1 3 1
	19	[83]	RETURN   	0 1

function <./frontend/ui/widget/keyboardlayoutdialog.lua:150,154> (7 instructions, 28 bytes at 0x7fbb8f408300)
1 param, 5 slots, 1 upvalue, 1 local, 1 constant, 1 function
	1	[151]	GETUPVAL 	1 0	; UIManager
	2	[151]	SELF     	1 1 -1	; "setDirty"
	3	[151]	MOVE     	3 0
	4	[153]	CLOSURE  	4 0	; 0x7fbb8f408540
	5	[153]	MOVE     	0 0
	6	[151]	CALL     	1 4 1
	7	[154]	RETURN   	0 1

function <./frontend/ui/widget/keyboardlayoutdialog.lua:151,153> (6 instructions, 24 bytes at 0x7fbb8f408540)
0 params, 2 slots, 1 upvalue, 0 locals, 3 constants, 0 functions
	1	[152]	LOADK    	0 -1	; "ui"
	2	[152]	GETUPVAL 	1 0	; self
	3	[152]	GETTABLE 	1 1 -2	; "dialog_frame"
	4	[152]	GETTABLE 	1 1 -3	; "dimen"
	5	[152]	RETURN   	0 3
	6	[153]	RETURN   	0 1

function <./frontend/ui/widget/keyboardlayoutdialog.lua:156,161> (9 instructions, 36 bytes at 0x7fbb8f4090c0)
1 param, 5 slots, 1 upvalue, 1 local, 1 constant, 1 function
	1	[157]	GETUPVAL 	1 0	; UIManager
	2	[157]	SELF     	1 1 -1	; "setDirty"
	3	[157]	LOADNIL  	3 3
	4	[159]	CLOSURE  	4 0	; 0x7fbb8f409350
	5	[159]	MOVE     	0 0
	6	[157]	CALL     	1 4 1
	7	[160]	LOADBOOL 	1 1 0
	8	[160]	RETURN   	1 2
	9	[161]	RETURN   	0 1

function <./frontend/ui/widget/keyboardlayoutdialog.lua:157,159> (7 instructions, 28 bytes at 0x7fbb8f409350)
0 params, 2 slots, 1 upvalue, 0 locals, 3 constants, 0 functions
	1	[158]	LOADK    	0 -1	; "partial"
	2	[158]	GETUPVAL 	1 0	; self
	3	[158]	GETTABLE 	1 1 -2	; 1
	4	[158]	GETTABLE 	1 1 -2	; 1
	5	[158]	GETTABLE 	1 1 -3	; "dimen"
	6	[158]	RETURN   	0 3
	7	[159]	RETURN   	0 1
