
main <./frontend/ui/widget/keyvaluepage.lua:0,0> (201 instructions, 804 bytes at 0x7fac32c068d0)
0+ params, 33 slots, 0 upvalues, 29 locals, 67 constants, 16 functions
	1	[22]	GETGLOBAL	0 -1	; require
	2	[22]	LOADK    	1 -2	; "ui/bidi"
	3	[22]	CALL     	0 2 2
	4	[23]	GETGLOBAL	1 -1	; require
	5	[23]	LOADK    	2 -3	; "ffi/blitbuffer"
	6	[23]	CALL     	1 2 2
	7	[24]	GETGLOBAL	2 -1	; require
	8	[24]	LOADK    	3 -4	; "ui/widget/container/bottomcontainer"
	9	[24]	CALL     	2 2 2
	10	[25]	GETGLOBAL	3 -1	; require
	11	[25]	LOADK    	4 -5	; "ui/widget/button"
	12	[25]	CALL     	3 2 2
	13	[26]	GETGLOBAL	4 -1	; require
	14	[26]	LOADK    	5 -6	; "ui/widget/closebutton"
	15	[26]	CALL     	4 2 2
	16	[27]	GETGLOBAL	5 -1	; require
	17	[27]	LOADK    	6 -7	; "device"
	18	[27]	CALL     	5 2 2
	19	[28]	GETGLOBAL	6 -1	; require
	20	[28]	LOADK    	7 -8	; "ui/font"
	21	[28]	CALL     	6 2 2
	22	[29]	GETGLOBAL	7 -1	; require
	23	[29]	LOADK    	8 -9	; "ui/widget/container/framecontainer"
	24	[29]	CALL     	7 2 2
	25	[30]	GETGLOBAL	8 -1	; require
	26	[30]	LOADK    	9 -10	; "ui/geometry"
	27	[30]	CALL     	8 2 2
	28	[31]	GETGLOBAL	9 -1	; require
	29	[31]	LOADK    	10 -11	; "ui/gesturerange"
	30	[31]	CALL     	9 2 2
	31	[32]	GETGLOBAL	10 -1	; require
	32	[32]	LOADK    	11 -12	; "ui/widget/horizontalgroup"
	33	[32]	CALL     	10 2 2
	34	[33]	GETGLOBAL	11 -1	; require
	35	[33]	LOADK    	12 -13	; "ui/widget/horizontalspan"
	36	[33]	CALL     	11 2 2
	37	[34]	GETGLOBAL	12 -1	; require
	38	[34]	LOADK    	13 -14	; "ui/widget/container/inputcontainer"
	39	[34]	CALL     	12 2 2
	40	[35]	GETGLOBAL	13 -1	; require
	41	[35]	LOADK    	14 -15	; "ui/widget/container/leftcontainer"
	42	[35]	CALL     	13 2 2
	43	[36]	GETGLOBAL	14 -1	; require
	44	[36]	LOADK    	15 -16	; "ui/widget/linewidget"
	45	[36]	CALL     	14 2 2
	46	[37]	GETGLOBAL	15 -1	; require
	47	[37]	LOADK    	16 -17	; "ui/widget/overlapgroup"
	48	[37]	CALL     	15 2 2
	49	[38]	GETGLOBAL	16 -1	; require
	50	[38]	LOADK    	17 -18	; "ui/size"
	51	[38]	CALL     	16 2 2
	52	[39]	GETGLOBAL	17 -1	; require
	53	[39]	LOADK    	18 -19	; "ui/widget/textviewer"
	54	[39]	CALL     	17 2 2
	55	[40]	GETGLOBAL	18 -1	; require
	56	[40]	LOADK    	19 -20	; "ui/widget/textwidget"
	57	[40]	CALL     	18 2 2
	58	[41]	GETGLOBAL	19 -1	; require
	59	[41]	LOADK    	20 -21	; "ui/uimanager"
	60	[41]	CALL     	19 2 2
	61	[42]	GETGLOBAL	20 -1	; require
	62	[42]	LOADK    	21 -22	; "ui/widget/verticalgroup"
	63	[42]	CALL     	20 2 2
	64	[43]	GETGLOBAL	21 -1	; require
	65	[43]	LOADK    	22 -23	; "ui/widget/verticalspan"
	66	[43]	CALL     	21 2 2
	67	[44]	GETTABLE 	22 5 -24	; "input"
	68	[45]	GETTABLE 	23 5 -25	; "screen"
	69	[46]	GETGLOBAL	24 -1	; require
	70	[46]	LOADK    	25 -26	; "ffi/util"
	71	[46]	CALL     	24 2 2
	72	[46]	GETTABLE 	24 24 -27	; "template"
	73	[47]	GETGLOBAL	25 -1	; require
	74	[47]	LOADK    	26 -28	; "gettext"
	75	[47]	CALL     	25 2 2
	76	[49]	SELF     	26 20 -29	; "new"
	77	[49]	NEWTABLE 	28 0 5
	78	[50]	SETTABLE 	28 -30 -31	; "kv_page" nil
	79	[51]	SETTABLE 	28 -32 -33	; "title" ""
	80	[52]	SELF     	29 6 -35	; "getFace"
	81	[52]	LOADK    	31 -36	; "tfont"
	82	[52]	CALL     	29 3 2
	83	[52]	SETTABLE 	28 -34 29	; "tface" -
	84	[53]	SETTABLE 	28 -37 -38	; "align" "left"
	85	[54]	SETTABLE 	28 -39 -40	; "use_top_page_count" false
	86	[49]	CALL     	26 3 2
	87	[97]	CLOSURE  	27 0	; 0x7fac32c07040
	88	[97]	MOVE     	0 4
	89	[97]	MOVE     	0 15
	90	[97]	MOVE     	0 18
	91	[97]	MOVE     	0 16
	92	[97]	MOVE     	0 14
	93	[97]	MOVE     	0 8
	94	[97]	MOVE     	0 1
	95	[97]	MOVE     	0 7
	96	[97]	MOVE     	0 6
	97	[97]	MOVE     	0 21
	98	[57]	SETTABLE 	26 -41 27	; "init" -
	99	[108]	CLOSURE  	27 1	; 0x7fac32c07dd0
	100	[99]	SETTABLE 	26 -42 27	; "setPageCount" -
	101	[113]	CLOSURE  	27 2	; 0x7fac32c08120
	102	[110]	SETTABLE 	26 -43 27	; "onClose" -
	103	[116]	SELF     	27 12 -29	; "new"
	104	[116]	NEWTABLE 	29 0 10
	105	[117]	SETTABLE 	29 -44 -31	; "key" nil
	106	[118]	SETTABLE 	29 -45 -31	; "value" nil
	107	[119]	SETTABLE 	29 -46 -31	; "value_lang" nil
	108	[120]	SELF     	30 6 -35	; "getFace"
	109	[120]	LOADK    	32 -48	; "smallinfofont"
	110	[120]	CALL     	30 3 2
	111	[120]	SETTABLE 	29 -47 30	; "cface" -
	112	[121]	SELF     	30 6 -35	; "getFace"
	113	[121]	LOADK    	32 -49	; "smallinfofontbold"
	114	[121]	CALL     	30 3 2
	115	[121]	SETTABLE 	29 -34 30	; "tface" -
	116	[122]	SETTABLE 	29 -50 -31	; "width" nil
	117	[123]	SETTABLE 	29 -51 -31	; "height" nil
	118	[124]	SETTABLE 	29 -52 -31	; "textviewer_width" nil
	119	[125]	SETTABLE 	29 -53 -31	; "textviewer_height" nil
	120	[126]	SETTABLE 	29 -54 -38	; "value_overflow_align" "left"
	121	[116]	CALL     	27 3 2
	122	[264]	CLOSURE  	28 3	; 0x7fac32c08b90
	123	[264]	MOVE     	0 8
	124	[264]	MOVE     	0 5
	125	[264]	MOVE     	0 9
	126	[264]	MOVE     	0 16
	127	[264]	MOVE     	0 18
	128	[264]	MOVE     	0 7
	129	[264]	MOVE     	0 10
	130	[264]	MOVE     	0 13
	131	[264]	MOVE     	0 11
	132	[129]	SETTABLE 	27 -41 28	; "init" -
	133	[287]	CLOSURE  	28 4	; 0x7fac32c09240
	134	[287]	MOVE     	0 19
	135	[266]	SETTABLE 	27 -55 28	; "onTap" -
	136	[299]	CLOSURE  	28 5	; 0x7fac32c07840
	137	[299]	MOVE     	0 17
	138	[299]	MOVE     	0 19
	139	[289]	SETTABLE 	27 -56 28	; "onHold" -
	140	[302]	SELF     	28 12 -29	; "new"
	141	[302]	NEWTABLE 	30 0 7
	142	[303]	SETTABLE 	30 -32 -33	; "title" ""
	143	[304]	SETTABLE 	30 -50 -31	; "width" nil
	144	[305]	SETTABLE 	30 -51 -31	; "height" nil
	145	[306]	SETTABLE 	30 -57 -31	; "values_lang" nil
	146	[308]	SETTABLE 	30 -58 -59	; "show_page" 1
	147	[309]	SETTABLE 	30 -39 -40	; "use_top_page_count" false
	148	[312]	SETTABLE 	30 -54 -38	; "value_overflow_align" "left"
	149	[302]	CALL     	28 3 2
	150	[479]	CLOSURE  	29 6	; 0x7fac32c095d0
	151	[479]	MOVE     	0 8
	152	[479]	MOVE     	0 23
	153	[479]	MOVE     	0 5
	154	[479]	MOVE     	0 22
	155	[479]	MOVE     	0 9
	156	[479]	MOVE     	0 3
	157	[479]	MOVE     	0 0
	158	[479]	MOVE     	0 11
	159	[479]	MOVE     	0 25
	160	[479]	MOVE     	0 10
	161	[479]	MOVE     	0 2
	162	[479]	MOVE     	0 16
	163	[479]	MOVE     	0 26
	164	[479]	MOVE     	0 20
	165	[479]	MOVE     	0 15
	166	[479]	MOVE     	0 7
	167	[479]	MOVE     	0 1
	168	[315]	SETTABLE 	28 -41 29	; "init" -
	169	[487]	CLOSURE  	29 7	; 0x7fac32c0af30
	170	[481]	SETTABLE 	28 -60 29	; "nextPage" -
	171	[495]	CLOSURE  	29 8	; 0x7fac32c0c100
	172	[489]	SETTABLE 	28 -61 29	; "prevPage" -
	173	[500]	CLOSURE  	29 9	; 0x7fac32c0be50
	174	[497]	SETTABLE 	28 -62 29	; "goToPage" -
	175	[563]	CLOSURE  	29 10	; 0x7fac32c0c9c0
	176	[563]	MOVE     	0 21
	177	[563]	MOVE     	0 27
	178	[563]	MOVE     	0 14
	179	[563]	MOVE     	0 1
	180	[563]	MOVE     	0 8
	181	[563]	MOVE     	0 16
	182	[563]	MOVE     	0 24
	183	[563]	MOVE     	0 25
	184	[563]	MOVE     	0 19
	185	[503]	SETTABLE 	28 -63 29	; "_populateItems" -
	186	[568]	CLOSURE  	29 11	; 0x7fac32c0ce70
	187	[565]	SETTABLE 	28 -64 29	; "onNextPage" -
	188	[573]	CLOSURE  	29 12	; 0x7fac32c0d140
	189	[570]	SETTABLE 	28 -65 29	; "onPrevPage" -
	190	[596]	CLOSURE  	29 13	; 0x7fac32c0d3f0
	191	[596]	MOVE     	0 0
	192	[596]	MOVE     	0 19
	193	[575]	SETTABLE 	28 -66 29	; "onSwipe" -
	194	[601]	CLOSURE  	29 14	; 0x7fac32c0d840
	195	[601]	MOVE     	0 19
	196	[598]	SETTABLE 	28 -43 29	; "onClose" -
	197	[609]	CLOSURE  	29 15	; 0x7fac32c0dcc0
	198	[609]	MOVE     	0 19
	199	[603]	SETTABLE 	28 -67 29	; "onReturn" -
	200	[611]	RETURN   	28 2
	201	[611]	RETURN   	0 1

function <./frontend/ui/widget/keyvaluepage.lua:57,97> (127 instructions, 508 bytes at 0x7fac32c07040)
1 param, 12 slots, 10 upvalues, 2 locals, 38 constants, 0 functions
	1	[58]	GETUPVAL 	1 0	; CloseButton
	2	[58]	SELF     	1 1 -2	; "new"
	3	[58]	NEWTABLE 	3 0 1
	4	[58]	SETTABLE 	3 -3 0	; "window" -
	5	[58]	CALL     	1 3 2
	6	[58]	SETTABLE 	0 -1 1	; "close_button" -
	7	[59]	GETTABLE 	1 0 -1	; "close_button"
	8	[59]	SELF     	1 1 -4	; "getSize"
	9	[59]	CALL     	1 2 2
	10	[59]	GETTABLE 	1 1 -5	; "w"
	11	[61]	GETGLOBAL	2 -6	; table
	12	[61]	GETTABLE 	2 2 -7	; "insert"
	13	[61]	MOVE     	3 0
	14	[61]	GETUPVAL 	4 1	; OverlapGroup
	15	[61]	SELF     	4 4 -2	; "new"
	16	[61]	NEWTABLE 	6 2 1
	17	[62]	NEWTABLE 	7 0 1
	18	[62]	GETTABLE 	8 0 -9	; "width"
	19	[62]	SETTABLE 	7 -5 8	; "w" -
	20	[62]	SETTABLE 	6 -8 7	; "dimen" -
	21	[63]	GETUPVAL 	7 2	; TextWidget
	22	[63]	SELF     	7 7 -2	; "new"
	23	[63]	NEWTABLE 	9 0 3
	24	[64]	GETTABLE 	10 0 -11	; "title"
	25	[64]	SETTABLE 	9 -10 10	; "text" -
	26	[65]	GETTABLE 	10 0 -9	; "width"
	27	[65]	SUB      	10 10 1
	28	[65]	SETTABLE 	9 -12 10	; "max_width" -
	29	[66]	GETTABLE 	10 0 -14	; "tface"
	30	[66]	SETTABLE 	9 -13 10	; "face" -
	31	[63]	CALL     	7 3 2
	32	[69]	GETTABLE 	8 0 -1	; "close_button"
	33	[69]	SETLIST  	6 2 1	; 1
	34	[61]	CALL     	4 3 0
	35	[61]	CALL     	2 0 1
	36	[71]	GETUPVAL 	2 1	; OverlapGroup
	37	[71]	SELF     	2 2 -2	; "new"
	38	[71]	NEWTABLE 	4 0 1
	39	[72]	NEWTABLE 	5 0 2
	40	[72]	GETTABLE 	6 0 -9	; "width"
	41	[72]	SETTABLE 	5 -5 6	; "w" -
	42	[72]	GETUPVAL 	6 3	; Size
	43	[72]	GETTABLE 	6 6 -17	; "line"
	44	[72]	GETTABLE 	6 6 -18	; "thick"
	45	[72]	SETTABLE 	5 -16 6	; "h" -
	46	[72]	SETTABLE 	4 -8 5	; "dimen" -
	47	[73]	GETUPVAL 	5 4	; LineWidget
	48	[73]	SELF     	5 5 -2	; "new"
	49	[73]	NEWTABLE 	7 0 3
	50	[74]	GETUPVAL 	8 5	; Geom
	51	[74]	SELF     	8 8 -2	; "new"
	52	[74]	NEWTABLE 	10 0 2
	53	[74]	GETTABLE 	11 0 -9	; "width"
	54	[74]	SETTABLE 	10 -5 11	; "w" -
	55	[74]	GETUPVAL 	11 3	; Size
	56	[74]	GETTABLE 	11 11 -17	; "line"
	57	[74]	GETTABLE 	11 11 -18	; "thick"
	58	[74]	SETTABLE 	10 -16 11	; "h" -
	59	[74]	CALL     	8 3 2
	60	[74]	SETTABLE 	7 -8 8	; "dimen" -
	61	[75]	GETUPVAL 	8 6	; Blitbuffer
	62	[75]	GETTABLE 	8 8 -20	; "COLOR_DARK_GRAY"
	63	[75]	SETTABLE 	7 -19 8	; "background" -
	64	[76]	SETTABLE 	7 -21 -22	; "style" "solid"
	65	[73]	CALL     	5 3 0
	66	[78]	SETLIST  	4 0 1	; 1
	67	[71]	CALL     	2 3 2
	68	[78]	SETTABLE 	0 -15 2	; "title_bottom" -
	69	[79]	GETTABLE 	2 0 -23	; "use_top_page_count"
	70	[79]	TEST     	2 0 0
	71	[79]	JMP      	38	; to 110
	72	[80]	GETUPVAL 	2 7	; FrameContainer
	73	[80]	SELF     	2 2 -2	; "new"
	74	[80]	NEWTABLE 	4 0 5
	75	[81]	GETUPVAL 	5 3	; Size
	76	[81]	GETTABLE 	5 5 -25	; "padding"
	77	[81]	GETTABLE 	5 5 -26	; "default"
	78	[81]	SETTABLE 	4 -25 5	; "padding" -
	79	[82]	SETTABLE 	4 -27 -28	; "margin" 0
	80	[83]	SETTABLE 	4 -29 -28	; "bordersize" 0
	81	[84]	GETUPVAL 	5 6	; Blitbuffer
	82	[84]	GETTABLE 	5 5 -30	; "COLOR_WHITE"
	83	[84]	SETTABLE 	4 -19 5	; "background" -
	84	[86]	NEWTABLE 	5 2 0
	85	[86]	LOADK    	6 -28	; 0
	86	[86]	LOADK    	7 -32	; -15
	87	[86]	SETLIST  	5 2 1	; 1
	88	[86]	SETTABLE 	4 -31 5	; "overlap_offset" -
	89	[87]	GETUPVAL 	5 2	; TextWidget
	90	[87]	SELF     	5 5 -2	; "new"
	91	[87]	NEWTABLE 	7 0 3
	92	[88]	SETTABLE 	7 -10 -33	; "text" ""
	93	[89]	GETUPVAL 	8 6	; Blitbuffer
	94	[89]	GETTABLE 	8 8 -20	; "COLOR_DARK_GRAY"
	95	[89]	SETTABLE 	7 -34 8	; "fgcolor" -
	96	[90]	GETUPVAL 	8 8	; Font
	97	[90]	SELF     	8 8 -35	; "getFace"
	98	[90]	LOADK    	10 -36	; "smallffont"
	99	[90]	CALL     	8 3 2
	100	[90]	SETTABLE 	7 -13 8	; "face" -
	101	[87]	CALL     	5 3 0
	102	[92]	SETLIST  	4 0 1	; 1
	103	[80]	CALL     	2 3 2
	104	[92]	SETTABLE 	0 -24 2	; "page_cnt" -
	105	[93]	GETGLOBAL	2 -6	; table
	106	[93]	GETTABLE 	2 2 -7	; "insert"
	107	[93]	GETTABLE 	3 0 -15	; "title_bottom"
	108	[93]	GETTABLE 	4 0 -24	; "page_cnt"
	109	[93]	CALL     	2 3 1
	110	[95]	GETGLOBAL	2 -6	; table
	111	[95]	GETTABLE 	2 2 -7	; "insert"
	112	[95]	MOVE     	3 0
	113	[95]	GETTABLE 	4 0 -15	; "title_bottom"
	114	[95]	CALL     	2 3 1
	115	[96]	GETGLOBAL	2 -6	; table
	116	[96]	GETTABLE 	2 2 -7	; "insert"
	117	[96]	MOVE     	3 0
	118	[96]	GETUPVAL 	4 9	; VerticalSpan
	119	[96]	SELF     	4 4 -2	; "new"
	120	[96]	NEWTABLE 	6 0 1
	121	[96]	GETUPVAL 	7 3	; Size
	122	[96]	GETTABLE 	7 7 -37	; "span"
	123	[96]	GETTABLE 	7 7 -38	; "vertical_large"
	124	[96]	SETTABLE 	6 -9 7	; "width" -
	125	[96]	CALL     	4 3 0
	126	[96]	CALL     	2 0 1
	127	[97]	RETURN   	0 1

function <./frontend/ui/widget/keyvaluepage.lua:99,108> (30 instructions, 120 bytes at 0x7fac32c07dd0)
3 params, 8 slots, 0 upvalues, 3 locals, 13 constants, 0 functions
	1	[100]	EQ       	0 2 -1	; - 1
	2	[100]	JMP      	6	; to 9
	3	[102]	GETGLOBAL	3 -2	; table
	4	[102]	GETTABLE 	3 3 -3	; "remove"
	5	[102]	GETTABLE 	4 0 -4	; "title_bottom"
	6	[102]	LOADK    	5 -5	; 2
	7	[102]	CALL     	3 3 1
	8	[103]	RETURN   	0 1
	9	[105]	GETTABLE 	3 0 -6	; "page_cnt"
	10	[105]	GETTABLE 	3 3 -1	; 1
	11	[105]	SELF     	3 3 -7	; "setText"
	12	[105]	MOVE     	5 1
	13	[105]	LOADK    	6 -8	; "/"
	14	[105]	MOVE     	7 2
	15	[105]	CONCAT   	5 5 7
	16	[105]	CALL     	3 3 1
	17	[106]	GETTABLE 	3 0 -6	; "page_cnt"
	18	[106]	GETTABLE 	3 3 -9	; "overlap_offset"
	19	[106]	GETTABLE 	4 0 -10	; "width"
	20	[106]	GETTABLE 	5 0 -6	; "page_cnt"
	21	[106]	SELF     	5 5 -11	; "getSize"
	22	[106]	CALL     	5 2 2
	23	[106]	GETTABLE 	5 5 -12	; "w"
	24	[106]	SUB      	4 4 5
	25	[106]	SUB      	4 4 -13	; - 10
	26	[106]	SETTABLE 	3 -1 4	; 1 -
	27	[107]	GETTABLE 	3 0 -4	; "title_bottom"
	28	[107]	GETTABLE 	4 0 -6	; "page_cnt"
	29	[107]	SETTABLE 	3 -5 4	; 2 -
	30	[108]	RETURN   	0 1

function <./frontend/ui/widget/keyvaluepage.lua:110,113> (6 instructions, 24 bytes at 0x7fac32c08120)
1 param, 3 slots, 0 upvalues, 1 local, 2 constants, 0 functions
	1	[111]	GETTABLE 	1 0 -1	; "kv_page"
	2	[111]	SELF     	1 1 -2	; "onClose"
	3	[111]	CALL     	1 2 1
	4	[112]	LOADBOOL 	1 1 0
	5	[112]	RETURN   	1 2
	6	[113]	RETURN   	0 1

function <./frontend/ui/widget/keyvaluepage.lua:129,264> (192 instructions, 768 bytes at 0x7fac32c08b90)
1 param, 27 slots, 9 upvalues, 14 locals, 40 constants, 0 functions
	1	[130]	GETUPVAL 	1 0	; Geom
	2	[130]	SELF     	1 1 -2	; "new"
	3	[130]	NEWTABLE 	3 0 2
	4	[130]	GETTABLE 	4 0 -4	; "width"
	5	[130]	SETTABLE 	3 -3 4	; "w" -
	6	[130]	GETTABLE 	4 0 -6	; "height"
	7	[130]	SETTABLE 	3 -5 4	; "h" -
	8	[130]	CALL     	1 3 2
	9	[130]	SETTABLE 	0 -1 1	; "dimen" -
	10	[132]	GETTABLE 	1 0 -7	; "callback"
	11	[132]	TEST     	1 0 0
	12	[132]	JMP      	16	; to 29
	13	[132]	GETUPVAL 	1 1	; Device
	14	[132]	SELF     	1 1 -8	; "isTouchDevice"
	15	[132]	CALL     	1 2 2
	16	[132]	TEST     	1 0 0
	17	[132]	JMP      	11	; to 29
	18	[133]	GETTABLE 	1 0 -9	; "ges_events"
	19	[133]	NEWTABLE 	2 0 0
	20	[134]	GETUPVAL 	3 2	; GestureRange
	21	[134]	SELF     	3 3 -2	; "new"
	22	[134]	NEWTABLE 	5 0 2
	23	[135]	SETTABLE 	5 -11 -12	; "ges" "tap"
	24	[136]	GETTABLE 	6 0 -1	; "dimen"
	25	[136]	SETTABLE 	5 -13 6	; "range" -
	26	[134]	CALL     	3 3 0
	27	[138]	SETLIST  	2 0 1	; 1
	28	[138]	SETTABLE 	1 -10 2	; "Tap" -
	29	[145]	GETGLOBAL	1 -14	; tostring
	30	[145]	GETTABLE 	2 0 -15	; "value"
	31	[145]	CALL     	1 2 2
	32	[146]	SELF     	2 1 -16	; "gsub"
	33	[146]	LOADK    	4 -17	; "[\n\t]"
	34	[146]	LOADK    	5 -18	; "|"
	35	[146]	CALL     	2 4 2
	36	[146]	MOVE     	1 2
	37	[148]	GETUPVAL 	2 3	; Size
	38	[148]	GETTABLE 	2 2 -19	; "padding"
	39	[148]	GETTABLE 	2 2 -20	; "default"
	40	[149]	GETTABLE 	3 0 -4	; "width"
	41	[149]	MUL      	4 2 -21	; - 2
	42	[149]	SUB      	3 3 4
	43	[150]	GETUPVAL 	4 3	; Size
	44	[150]	GETTABLE 	4 4 -19	; "padding"
	45	[150]	GETTABLE 	4 4 -20	; "default"
	46	[151]	SUB      	5 3 4
	47	[154]	DIV      	6 3 -21	; - 2
	48	[154]	SUB      	6 6 4
	49	[155]	DIV      	7 3 -21	; - 2
	50	[157]	GETUPVAL 	8 4	; TextWidget
	51	[157]	SELF     	8 8 -2	; "new"
	52	[157]	NEWTABLE 	10 0 3
	53	[158]	GETTABLE 	11 0 -23	; "key"
	54	[158]	SETTABLE 	10 -22 11	; "text" -
	55	[159]	SETTABLE 	10 -24 5	; "max_width" -
	56	[160]	GETTABLE 	11 0 -26	; "tface"
	57	[160]	SETTABLE 	10 -25 11	; "face" -
	58	[157]	CALL     	8 3 2
	59	[162]	GETUPVAL 	9 4	; TextWidget
	60	[162]	SELF     	9 9 -2	; "new"
	61	[162]	NEWTABLE 	11 0 4
	62	[163]	SETTABLE 	11 -22 1	; "text" -
	63	[164]	SETTABLE 	11 -24 5	; "max_width" -
	64	[165]	GETTABLE 	12 0 -27	; "cface"
	65	[165]	SETTABLE 	11 -25 12	; "face" -
	66	[166]	GETTABLE 	12 0 -29	; "value_lang"
	67	[166]	SETTABLE 	11 -28 12	; "lang" -
	68	[162]	CALL     	9 3 2
	69	[168]	SELF     	10 8 -30	; "getWidth"
	70	[168]	CALL     	10 2 2
	71	[169]	SELF     	11 9 -30	; "getWidth"
	72	[169]	CALL     	11 2 2
	73	[174]	LOADBOOL 	12 0 0
	74	[175]	LOADBOOL 	13 1 0
	75	[177]	LT       	1 6 10
	76	[177]	JMP      	2	; to 79
	77	[177]	LT       	0 7 11
	78	[177]	JMP      	45	; to 124
	79	[179]	ADD      	14 10 11
	80	[179]	LT       	0 5 14
	81	[179]	JMP      	30	; to 112
	82	[181]	LE       	0 11 10
	83	[181]	JMP      	2	; to 86
	84	[186]	SUB      	6 5 11
	85	[186]	JMP      	1	; to 87
	86	[190]	MOVE     	6 10
	87	[192]	LOADBOOL 	12 1 0
	88	[193]	GETTABLE 	14 0 -31	; "value_overflow_align"
	89	[193]	EQ       	1 14 -32	; - "right"
	90	[193]	JMP      	4	; to 95
	91	[193]	GETTABLE 	14 0 -33	; "value_align"
	92	[193]	EQ       	1 14 -32	; - "right"
	93	[193]	JMP      	1	; to 95
	94	[196]	LOADBOOL 	13 0 0
	95	[199]	GETUPVAL 	14 1	; Device
	96	[199]	SELF     	14 14 -8	; "isTouchDevice"
	97	[199]	CALL     	14 2 2
	98	[199]	TEST     	14 0 0
	99	[199]	JMP      	22	; to 122
	100	[200]	GETTABLE 	14 0 -9	; "ges_events"
	101	[200]	NEWTABLE 	15 0 0
	102	[201]	GETUPVAL 	16 2	; GestureRange
	103	[201]	SELF     	16 16 -2	; "new"
	104	[201]	NEWTABLE 	18 0 2
	105	[202]	SETTABLE 	18 -11 -35	; "ges" "hold"
	106	[203]	GETTABLE 	19 0 -1	; "dimen"
	107	[203]	SETTABLE 	18 -13 19	; "range" -
	108	[201]	CALL     	16 3 0
	109	[205]	SETLIST  	15 0 1	; 1
	110	[205]	SETTABLE 	14 -34 15	; "Hold" -
	111	[206]	JMP      	10	; to 122
	112	[209]	GETTABLE 	14 0 -31	; "value_overflow_align"
	113	[209]	EQ       	1 14 -32	; - "right"
	114	[209]	JMP      	3	; to 118
	115	[209]	GETTABLE 	14 0 -33	; "value_align"
	116	[209]	EQ       	0 14 -32	; - "right"
	117	[209]	JMP      	3	; to 121
	118	[210]	SUB      	6 5 11
	119	[211]	LOADBOOL 	12 1 0
	120	[211]	JMP      	1	; to 122
	121	[213]	MOVE     	6 10
	122	[218]	SUB      	7 5 6
	123	[218]	JMP      	6	; to 130
	124	[220]	GETTABLE 	14 0 -33	; "value_align"
	125	[220]	EQ       	0 14 -32	; - "right"
	126	[220]	JMP      	3	; to 130
	127	[221]	SUB      	6 5 11
	128	[222]	MOVE     	7 11
	129	[223]	LOADBOOL 	12 1 0
	130	[228]	SELF     	14 9 -36	; "setMaxWidth"
	131	[228]	MOVE     	16 7
	132	[228]	CALL     	14 3 1
	133	[229]	TEST     	13 0 0
	134	[229]	JMP      	10	; to 145
	135	[229]	TEST     	12 0 0
	136	[229]	JMP      	8	; to 145
	137	[229]	SELF     	14 9 -30	; "getWidth"
	138	[229]	CALL     	14 2 2
	139	[229]	LT       	0 14 7
	140	[229]	JMP      	4	; to 145
	141	[233]	SELF     	14 9 -30	; "getWidth"
	142	[233]	CALL     	14 2 2
	143	[233]	SUB      	14 7 14
	144	[233]	ADD      	6 6 14
	145	[235]	SELF     	14 8 -36	; "setMaxWidth"
	146	[235]	MOVE     	16 6
	147	[235]	CALL     	14 3 1
	148	[240]	GETUPVAL 	14 5	; FrameContainer
	149	[240]	SELF     	14 14 -2	; "new"
	150	[240]	NEWTABLE 	16 0 2
	151	[241]	SETTABLE 	16 -19 2	; "padding" -
	152	[242]	SETTABLE 	16 -38 -39	; "bordersize" 0
	153	[243]	GETUPVAL 	17 6	; HorizontalGroup
	154	[243]	SELF     	17 17 -2	; "new"
	155	[243]	NEWTABLE 	19 2 1
	156	[244]	GETTABLE 	20 0 -1	; "dimen"
	157	[244]	SELF     	20 20 -40	; "copy"
	158	[244]	CALL     	20 2 2
	159	[244]	SETTABLE 	19 -1 20	; "dimen" -
	160	[245]	GETUPVAL 	20 7	; LeftContainer
	161	[245]	SELF     	20 20 -2	; "new"
	162	[245]	NEWTABLE 	22 1 1
	163	[246]	NEWTABLE 	23 0 2
	164	[247]	SETTABLE 	23 -3 6	; "w" -
	165	[248]	GETTABLE 	24 0 -6	; "height"
	166	[248]	SETTABLE 	23 -5 24	; "h" -
	167	[249]	SETTABLE 	22 -1 23	; "dimen" -
	168	[251]	MOVE     	23 8
	169	[251]	SETLIST  	22 1 1	; 1
	170	[245]	CALL     	20 3 2
	171	[252]	GETUPVAL 	21 8	; HorizontalSpan
	172	[252]	SELF     	21 21 -2	; "new"
	173	[252]	NEWTABLE 	23 0 1
	174	[253]	SETTABLE 	23 -4 4	; "width" -
	175	[252]	CALL     	21 3 2
	176	[255]	GETUPVAL 	22 7	; LeftContainer
	177	[255]	SELF     	22 22 -2	; "new"
	178	[255]	NEWTABLE 	24 1 1
	179	[256]	NEWTABLE 	25 0 2
	180	[257]	SETTABLE 	25 -3 7	; "w" -
	181	[258]	GETTABLE 	26 0 -6	; "height"
	182	[258]	SETTABLE 	25 -5 26	; "h" -
	183	[259]	SETTABLE 	24 -1 25	; "dimen" -
	184	[261]	MOVE     	25 9
	185	[261]	SETLIST  	24 1 1	; 1
	186	[255]	CALL     	22 3 0
	187	[262]	SETLIST  	19 0 1	; 1
	188	[243]	CALL     	17 3 0
	189	[263]	SETLIST  	16 0 1	; 1
	190	[240]	CALL     	14 3 2
	191	[263]	SETTABLE 	0 -37 14	; 1 -
	192	[264]	RETURN   	0 1

function <./frontend/ui/widget/keyvaluepage.lua:266,287> (39 instructions, 156 bytes at 0x7fac32c09240)
1 param, 6 slots, 1 upvalue, 1 local, 13 constants, 2 functions
	1	[267]	GETTABLE 	1 0 -1	; "callback"
	2	[267]	TEST     	1 0 0
	3	[267]	JMP      	33	; to 37
	4	[268]	GETGLOBAL	1 -2	; G_reader_settings
	5	[268]	SELF     	1 1 -3	; "isFalse"
	6	[268]	LOADK    	3 -4	; "flash_ui"
	7	[268]	CALL     	1 3 2
	8	[268]	TEST     	1 0 0
	9	[268]	JMP      	3	; to 13
	10	[269]	GETTABLE 	1 0 -1	; "callback"
	11	[269]	CALL     	1 1 1
	12	[269]	JMP      	24	; to 37
	13	[271]	GETTABLE 	1 0 -5	; 1
	14	[271]	SETTABLE 	1 -6 -7	; "invert" true
	15	[272]	GETUPVAL 	1 0	; UIManager
	16	[272]	SELF     	1 1 -8	; "widgetRepaint"
	17	[272]	GETTABLE 	3 0 -5	; 1
	18	[272]	GETTABLE 	4 0 -5	; 1
	19	[272]	GETTABLE 	4 4 -9	; "dimen"
	20	[272]	GETTABLE 	4 4 -10	; "x"
	21	[272]	GETTABLE 	5 0 -5	; 1
	22	[272]	GETTABLE 	5 5 -9	; "dimen"
	23	[272]	GETTABLE 	5 5 -11	; "y"
	24	[272]	CALL     	1 5 1
	25	[273]	GETUPVAL 	1 0	; UIManager
	26	[273]	SELF     	1 1 -12	; "setDirty"
	27	[273]	LOADNIL  	3 3
	28	[275]	CLOSURE  	4 0	; 0x7fac32c076c0
	29	[275]	MOVE     	0 0
	30	[273]	CALL     	1 4 1
	31	[276]	GETUPVAL 	1 0	; UIManager
	32	[276]	SELF     	1 1 -13	; "tickAfterNext"
	33	[283]	CLOSURE  	3 1	; 0x7fac32c07950
	34	[283]	MOVE     	0 0
	35	[283]	GETUPVAL 	0 0	; UIManager
	36	[276]	CALL     	1 3 1
	37	[286]	LOADBOOL 	1 1 0
	38	[286]	RETURN   	1 2
	39	[287]	RETURN   	0 1

function <./frontend/ui/widget/keyvaluepage.lua:273,275> (6 instructions, 24 bytes at 0x7fac32c076c0)
0 params, 2 slots, 1 upvalue, 0 locals, 3 constants, 0 functions
	1	[274]	LOADK    	0 -1	; "fast"
	2	[274]	GETUPVAL 	1 0	; self
	3	[274]	GETTABLE 	1 1 -2	; 1
	4	[274]	GETTABLE 	1 1 -3	; "dimen"
	5	[274]	RETURN   	0 3
	6	[275]	RETURN   	0 1

function <./frontend/ui/widget/keyvaluepage.lua:276,283> (26 instructions, 104 bytes at 0x7fac32c07950)
0 params, 5 slots, 2 upvalues, 0 locals, 9 constants, 1 function
	1	[277]	GETUPVAL 	0 0	; self
	2	[277]	GETTABLE 	0 0 -1	; "callback"
	3	[277]	CALL     	0 1 1
	4	[278]	GETUPVAL 	0 0	; self
	5	[278]	GETTABLE 	0 0 -2	; 1
	6	[278]	SETTABLE 	0 -3 -4	; "invert" false
	7	[279]	GETUPVAL 	0 1	; UIManager
	8	[279]	SELF     	0 0 -5	; "widgetRepaint"
	9	[279]	GETUPVAL 	2 0	; self
	10	[279]	GETTABLE 	2 2 -2	; 1
	11	[279]	GETUPVAL 	3 0	; self
	12	[279]	GETTABLE 	3 3 -2	; 1
	13	[279]	GETTABLE 	3 3 -6	; "dimen"
	14	[279]	GETTABLE 	3 3 -7	; "x"
	15	[279]	GETUPVAL 	4 0	; self
	16	[279]	GETTABLE 	4 4 -2	; 1
	17	[279]	GETTABLE 	4 4 -6	; "dimen"
	18	[279]	GETTABLE 	4 4 -8	; "y"
	19	[279]	CALL     	0 5 1
	20	[280]	GETUPVAL 	0 1	; UIManager
	21	[280]	SELF     	0 0 -9	; "setDirty"
	22	[280]	LOADNIL  	2 2
	23	[282]	CLOSURE  	3 0	; 0x7fac32c096e0
	24	[282]	GETUPVAL 	0 0	; self
	25	[280]	CALL     	0 4 1
	26	[283]	RETURN   	0 1

function <./frontend/ui/widget/keyvaluepage.lua:280,282> (6 instructions, 24 bytes at 0x7fac32c096e0)
0 params, 2 slots, 1 upvalue, 0 locals, 3 constants, 0 functions
	1	[281]	LOADK    	0 -1	; "ui"
	2	[281]	GETUPVAL 	1 0	; self
	3	[281]	GETTABLE 	1 1 -2	; 1
	4	[281]	GETTABLE 	1 1 -3	; "dimen"
	5	[281]	RETURN   	0 3
	6	[282]	RETURN   	0 1

function <./frontend/ui/widget/keyvaluepage.lua:289,299> (21 instructions, 84 bytes at 0x7fac32c07840)
1 param, 5 slots, 2 upvalues, 2 locals, 12 constants, 0 functions
	1	[290]	GETUPVAL 	1 0	; TextViewer
	2	[290]	SELF     	1 1 -1	; "new"
	3	[290]	NEWTABLE 	3 0 5
	4	[291]	GETTABLE 	4 0 -3	; "key"
	5	[291]	SETTABLE 	3 -2 4	; "title" -
	6	[292]	GETTABLE 	4 0 -5	; "value"
	7	[292]	SETTABLE 	3 -4 4	; "text" -
	8	[293]	GETTABLE 	4 0 -7	; "value_lang"
	9	[293]	SETTABLE 	3 -6 4	; "lang" -
	10	[294]	GETTABLE 	4 0 -9	; "textviewer_width"
	11	[294]	SETTABLE 	3 -8 4	; "width" -
	12	[295]	GETTABLE 	4 0 -11	; "textviewer_height"
	13	[295]	SETTABLE 	3 -10 4	; "height" -
	14	[290]	CALL     	1 3 2
	15	[297]	GETUPVAL 	2 1	; UIManager
	16	[297]	SELF     	2 2 -12	; "show"
	17	[297]	MOVE     	4 1
	18	[297]	CALL     	2 3 1
	19	[298]	LOADBOOL 	2 1 0
	20	[298]	RETURN   	2 2
	21	[299]	RETURN   	0 1

function <./frontend/ui/widget/keyvaluepage.lua:315,479> (363 instructions, 1452 bytes at 0x7fac32c095d0)
1 param, 17 slots, 17 upvalues, 10 locals, 100 constants, 7 functions
	1	[316]	GETUPVAL 	1 0	; Geom
	2	[316]	SELF     	1 1 -2	; "new"
	3	[316]	NEWTABLE 	3 0 2
	4	[317]	GETTABLE 	4 0 -4	; "width"
	5	[317]	TEST     	4 0 1
	6	[317]	JMP      	3	; to 10
	7	[317]	GETUPVAL 	4 1	; Screen
	8	[317]	SELF     	4 4 -5	; "getWidth"
	9	[317]	CALL     	4 2 2
	10	[317]	SETTABLE 	3 -3 4	; "w" -
	11	[318]	GETTABLE 	4 0 -7	; "height"
	12	[318]	TEST     	4 0 1
	13	[318]	JMP      	3	; to 17
	14	[318]	GETUPVAL 	4 1	; Screen
	15	[318]	SELF     	4 4 -8	; "getHeight"
	16	[318]	CALL     	4 2 2
	17	[318]	SETTABLE 	3 -6 4	; "h" -
	18	[316]	CALL     	1 3 2
	19	[319]	SETTABLE 	0 -1 1	; "dimen" -
	20	[320]	GETTABLE 	1 0 -1	; "dimen"
	21	[320]	GETTABLE 	1 1 -3	; "w"
	22	[320]	GETUPVAL 	2 1	; Screen
	23	[320]	SELF     	2 2 -5	; "getWidth"
	24	[320]	CALL     	2 2 2
	25	[320]	EQ       	0 1 2
	26	[320]	JMP      	8	; to 35
	27	[320]	GETTABLE 	1 0 -1	; "dimen"
	28	[320]	GETTABLE 	1 1 -6	; "h"
	29	[320]	GETUPVAL 	2 1	; Screen
	30	[320]	SELF     	2 2 -8	; "getHeight"
	31	[320]	CALL     	2 2 2
	32	[320]	EQ       	0 1 2
	33	[320]	JMP      	1	; to 35
	34	[321]	SETTABLE 	0 -9 -10	; "covers_fullscreen" true
	35	[324]	GETUPVAL 	1 2	; Device
	36	[324]	SELF     	1 1 -11	; "hasKeys"
	37	[324]	CALL     	1 2 2
	38	[324]	TEST     	1 0 0
	39	[324]	JMP      	27	; to 67
	40	[325]	NEWTABLE 	1 0 3
	41	[326]	NEWTABLE 	2 1 1
	42	[326]	NEWTABLE 	3 1 0
	43	[326]	LOADK    	4 -14	; "Back"
	44	[326]	SETLIST  	3 1 1	; 1
	45	[326]	SETTABLE 	2 -15 -16	; "doc" "close page"
	46	[326]	SETLIST  	2 1 1	; 1
	47	[326]	SETTABLE 	1 -13 2	; "Close" -
	48	[327]	NEWTABLE 	2 1 1
	49	[327]	NEWTABLE 	3 1 0
	50	[327]	GETUPVAL 	4 3	; Input
	51	[327]	GETTABLE 	4 4 -18	; "group"
	52	[327]	GETTABLE 	4 4 -19	; "PgFwd"
	53	[327]	SETLIST  	3 1 1	; 1
	54	[327]	SETTABLE 	2 -15 -20	; "doc" "next page"
	55	[327]	SETLIST  	2 1 1	; 1
	56	[327]	SETTABLE 	1 -17 2	; "NextPage" -
	57	[328]	NEWTABLE 	2 1 1
	58	[328]	NEWTABLE 	3 1 0
	59	[328]	GETUPVAL 	4 3	; Input
	60	[328]	GETTABLE 	4 4 -18	; "group"
	61	[328]	GETTABLE 	4 4 -22	; "PgBack"
	62	[328]	SETLIST  	3 1 1	; 1
	63	[328]	SETTABLE 	2 -15 -23	; "doc" "prev page"
	64	[328]	SETLIST  	2 1 1	; 1
	65	[328]	SETTABLE 	1 -21 2	; "PrevPage" -
	66	[329]	SETTABLE 	0 -12 1	; "key_events" -
	67	[331]	GETUPVAL 	1 2	; Device
	68	[331]	SELF     	1 1 -24	; "isTouchDevice"
	69	[331]	CALL     	1 2 2
	70	[331]	TEST     	1 0 0
	71	[331]	JMP      	11	; to 83
	72	[332]	GETTABLE 	1 0 -25	; "ges_events"
	73	[332]	NEWTABLE 	2 0 0
	74	[333]	GETUPVAL 	3 4	; GestureRange
	75	[333]	SELF     	3 3 -2	; "new"
	76	[333]	NEWTABLE 	5 0 2
	77	[334]	SETTABLE 	5 -27 -28	; "ges" "swipe"
	78	[335]	GETTABLE 	6 0 -1	; "dimen"
	79	[335]	SETTABLE 	5 -29 6	; "range" -
	80	[333]	CALL     	3 3 0
	81	[337]	SETLIST  	2 0 1	; 1
	82	[337]	SETTABLE 	1 -26 2	; "Swipe" -
	83	[342]	GETUPVAL 	1 5	; Button
	84	[342]	SELF     	1 1 -2	; "new"
	85	[342]	NEWTABLE 	3 0 4
	86	[343]	SETTABLE 	3 -31 -32	; "icon" "resources/icons/appbar.arrow.left.up.png"
	87	[344]	CLOSURE  	4 0	; 0x7fac32c08a00
	88	[344]	MOVE     	0 0
	89	[344]	SETTABLE 	3 -33 4	; "callback" -
	90	[345]	SETTABLE 	3 -34 -35	; "bordersize" 0
	91	[346]	SETTABLE 	3 -36 0	; "show_parent" -
	92	[342]	CALL     	1 3 2
	93	[347]	SETTABLE 	0 -30 1	; "page_return_arrow" -
	94	[349]	LOADK    	1 -37	; "resources/icons/appbar.chevron.left.png"
	95	[350]	LOADK    	2 -38	; "resources/icons/appbar.chevron.right.png"
	96	[351]	LOADK    	3 -39	; "resources/icons/appbar.chevron.first.png"
	97	[352]	LOADK    	4 -40	; "resources/icons/appbar.chevron.last.png"
	98	[353]	GETUPVAL 	5 6	; BD
	99	[353]	GETTABLE 	5 5 -41	; "mirroredUILayout"
	100	[353]	CALL     	5 1 2
	101	[353]	TEST     	5 0 0
	102	[353]	JMP      	6	; to 109
	103	[354]	MOVE     	5 2
	104	[354]	MOVE     	2 1
	105	[354]	MOVE     	1 5
	106	[355]	MOVE     	5 4
	107	[355]	MOVE     	4 3
	108	[355]	MOVE     	3 5
	109	[357]	GETUPVAL 	5 5	; Button
	110	[357]	SELF     	5 5 -2	; "new"
	111	[357]	NEWTABLE 	7 0 4
	112	[358]	SETTABLE 	7 -31 1	; "icon" -
	113	[359]	CLOSURE  	8 1	; 0x7fac32c0a940
	114	[359]	MOVE     	0 0
	115	[359]	SETTABLE 	7 -33 8	; "callback" -
	116	[360]	SETTABLE 	7 -34 -35	; "bordersize" 0
	117	[361]	SETTABLE 	7 -36 0	; "show_parent" -
	118	[357]	CALL     	5 3 2
	119	[362]	SETTABLE 	0 -42 5	; "page_info_left_chev" -
	120	[363]	GETUPVAL 	5 5	; Button
	121	[363]	SELF     	5 5 -2	; "new"
	122	[363]	NEWTABLE 	7 0 4
	123	[364]	SETTABLE 	7 -31 2	; "icon" -
	124	[365]	CLOSURE  	8 2	; 0x7fac32c0abb0
	125	[365]	MOVE     	0 0
	126	[365]	SETTABLE 	7 -33 8	; "callback" -
	127	[366]	SETTABLE 	7 -34 -35	; "bordersize" 0
	128	[367]	SETTABLE 	7 -36 0	; "show_parent" -
	129	[363]	CALL     	5 3 2
	130	[368]	SETTABLE 	0 -43 5	; "page_info_right_chev" -
	131	[369]	GETUPVAL 	5 5	; Button
	132	[369]	SELF     	5 5 -2	; "new"
	133	[369]	NEWTABLE 	7 0 4
	134	[370]	SETTABLE 	7 -31 3	; "icon" -
	135	[371]	CLOSURE  	8 3	; 0x7fac32c0a660
	136	[371]	MOVE     	0 0
	137	[371]	SETTABLE 	7 -33 8	; "callback" -
	138	[372]	SETTABLE 	7 -34 -35	; "bordersize" 0
	139	[373]	SETTABLE 	7 -36 0	; "show_parent" -
	140	[369]	CALL     	5 3 2
	141	[374]	SETTABLE 	0 -44 5	; "page_info_first_chev" -
	142	[375]	GETUPVAL 	5 5	; Button
	143	[375]	SELF     	5 5 -2	; "new"
	144	[375]	NEWTABLE 	7 0 4
	145	[376]	SETTABLE 	7 -31 4	; "icon" -
	146	[377]	CLOSURE  	8 4	; 0x7fac32c09b30
	147	[377]	MOVE     	0 0
	148	[377]	SETTABLE 	7 -33 8	; "callback" -
	149	[378]	SETTABLE 	7 -34 -35	; "bordersize" 0
	150	[379]	SETTABLE 	7 -36 0	; "show_parent" -
	151	[375]	CALL     	5 3 2
	152	[380]	SETTABLE 	0 -45 5	; "page_info_last_chev" -
	153	[381]	GETUPVAL 	5 7	; HorizontalSpan
	154	[381]	SELF     	5 5 -2	; "new"
	155	[381]	NEWTABLE 	7 0 1
	156	[382]	GETUPVAL 	8 1	; Screen
	157	[382]	SELF     	8 8 -47	; "scaleBySize"
	158	[382]	LOADK    	10 -48	; 32
	159	[382]	CALL     	8 3 2
	160	[382]	SETTABLE 	7 -4 8	; "width" -
	161	[381]	CALL     	5 3 2
	162	[383]	SETTABLE 	0 -46 5	; "page_info_spacer" -
	163	[384]	GETUPVAL 	5 7	; HorizontalSpan
	164	[384]	SELF     	5 5 -2	; "new"
	165	[384]	NEWTABLE 	7 0 1
	166	[385]	GETTABLE 	8 0 -30	; "page_return_arrow"
	167	[385]	SELF     	8 8 -50	; "getSize"
	168	[385]	CALL     	8 2 2
	169	[385]	GETTABLE 	8 8 -3	; "w"
	170	[385]	SETTABLE 	7 -4 8	; "width" -
	171	[384]	CALL     	5 3 2
	172	[386]	SETTABLE 	0 -49 5	; "page_return_spacer" -
	173	[388]	GETTABLE 	5 0 -51	; "callback_return"
	174	[388]	EQ       	0 5 -52	; - nil
	175	[388]	JMP      	7	; to 183
	176	[388]	GETTABLE 	5 0 -53	; "return_button"
	177	[388]	EQ       	0 5 -52	; - nil
	178	[388]	JMP      	4	; to 183
	179	[389]	GETTABLE 	5 0 -30	; "page_return_arrow"
	180	[389]	SELF     	5 5 -54	; "hide"
	181	[389]	CALL     	5 2 1
	182	[389]	JMP      	6	; to 189
	183	[390]	GETTABLE 	5 0 -51	; "callback_return"
	184	[390]	EQ       	0 5 -52	; - nil
	185	[390]	JMP      	3	; to 189
	186	[391]	GETTABLE 	5 0 -30	; "page_return_arrow"
	187	[391]	SELF     	5 5 -55	; "disable"
	188	[391]	CALL     	5 2 1
	189	[394]	GETTABLE 	5 0 -42	; "page_info_left_chev"
	190	[394]	SELF     	5 5 -54	; "hide"
	191	[394]	CALL     	5 2 1
	192	[395]	GETTABLE 	5 0 -43	; "page_info_right_chev"
	193	[395]	SELF     	5 5 -54	; "hide"
	194	[395]	CALL     	5 2 1
	195	[396]	GETTABLE 	5 0 -44	; "page_info_first_chev"
	196	[396]	SELF     	5 5 -54	; "hide"
	197	[396]	CALL     	5 2 1
	198	[397]	GETTABLE 	5 0 -45	; "page_info_last_chev"
	199	[397]	SELF     	5 5 -54	; "hide"
	200	[397]	CALL     	5 2 1
	201	[399]	GETUPVAL 	5 5	; Button
	202	[399]	SELF     	5 5 -2	; "new"
	203	[399]	NEWTABLE 	7 0 6
	204	[400]	SETTABLE 	7 -57 -58	; "text" ""
	205	[401]	NEWTABLE 	8 0 4
	206	[402]	GETUPVAL 	9 8	; _
	207	[402]	LOADK    	10 -61	; "Enter page number"
	208	[402]	CALL     	9 2 2
	209	[402]	SETTABLE 	8 -60 9	; "title" -
	210	[403]	SETTABLE 	8 -62 -63	; "type" "number"
	211	[406]	CLOSURE  	9 5	; 0x7fac32c0b050
	212	[406]	MOVE     	0 0
	213	[406]	SETTABLE 	8 -64 9	; "hint_func" -
	214	[412]	CLOSURE  	9 6	; 0x7fac32c0b1f0
	215	[412]	MOVE     	0 0
	216	[412]	SETTABLE 	8 -33 9	; "callback" -
	217	[413]	SETTABLE 	7 -59 8	; "hold_input" -
	218	[414]	SETTABLE 	7 -34 -35	; "bordersize" 0
	219	[415]	GETUPVAL 	8 1	; Screen
	220	[415]	SELF     	8 8 -47	; "scaleBySize"
	221	[415]	LOADK    	10 -66	; 20
	222	[415]	CALL     	8 3 2
	223	[415]	SETTABLE 	7 -65 8	; "margin" -
	224	[416]	SETTABLE 	7 -67 -68	; "text_font_face" "pgfont"
	225	[417]	SETTABLE 	7 -69 -70	; "text_font_bold" false
	226	[399]	CALL     	5 3 2
	227	[418]	SETTABLE 	0 -56 5	; "page_info_text" -
	228	[419]	GETUPVAL 	5 9	; HorizontalGroup
	229	[419]	SELF     	5 5 -2	; "new"
	230	[419]	NEWTABLE 	7 9 0
	231	[420]	GETTABLE 	8 0 -30	; "page_return_arrow"
	232	[421]	GETTABLE 	9 0 -44	; "page_info_first_chev"
	233	[422]	GETTABLE 	10 0 -46	; "page_info_spacer"
	234	[423]	GETTABLE 	11 0 -42	; "page_info_left_chev"
	235	[424]	GETTABLE 	12 0 -56	; "page_info_text"
	236	[425]	GETTABLE 	13 0 -43	; "page_info_right_chev"
	237	[426]	GETTABLE 	14 0 -46	; "page_info_spacer"
	238	[427]	GETTABLE 	15 0 -45	; "page_info_last_chev"
	239	[429]	GETTABLE 	16 0 -49	; "page_return_spacer"
	240	[429]	SETLIST  	7 9 1	; 1
	241	[419]	CALL     	5 3 2
	242	[429]	SETTABLE 	0 -71 5	; "page_info" -
	243	[431]	GETUPVAL 	5 10	; BottomContainer
	244	[431]	SELF     	5 5 -2	; "new"
	245	[431]	NEWTABLE 	7 1 1
	246	[432]	GETTABLE 	8 0 -1	; "dimen"
	247	[432]	SELF     	8 8 -72	; "copy"
	248	[432]	CALL     	8 2 2
	249	[432]	SETTABLE 	7 -1 8	; "dimen" -
	250	[434]	GETTABLE 	8 0 -71	; "page_info"
	251	[434]	SETLIST  	7 1 1	; 1
	252	[431]	CALL     	5 3 2
	253	[436]	GETUPVAL 	6 11	; Size
	254	[436]	GETTABLE 	6 6 -73	; "padding"
	255	[436]	GETTABLE 	6 6 -74	; "large"
	256	[437]	GETTABLE 	7 0 -1	; "dimen"
	257	[437]	GETTABLE 	7 7 -3	; "w"
	258	[437]	MUL      	8 -76 6	; 2 -
	259	[437]	SUB      	7 7 8
	260	[437]	SETTABLE 	0 -75 7	; "item_width" -
	261	[438]	GETUPVAL 	7 11	; Size
	262	[438]	GETTABLE 	7 7 -78	; "item"
	263	[438]	GETTABLE 	7 7 -79	; "height_default"
	264	[438]	SETTABLE 	0 -77 7	; "item_height" -
	265	[440]	GETUPVAL 	7 12	; KeyValueTitle
	266	[440]	SELF     	7 7 -2	; "new"
	267	[440]	NEWTABLE 	9 0 5
	268	[441]	GETTABLE 	10 0 -60	; "title"
	269	[441]	SETTABLE 	9 -60 10	; "title" -
	270	[442]	GETTABLE 	10 0 -75	; "item_width"
	271	[442]	SETTABLE 	9 -4 10	; "width" -
	272	[443]	GETTABLE 	10 0 -77	; "item_height"
	273	[443]	SETTABLE 	9 -7 10	; "height" -
	274	[444]	GETTABLE 	10 0 -81	; "use_top_page_count"
	275	[444]	SETTABLE 	9 -81 10	; "use_top_page_count" -
	276	[445]	SETTABLE 	9 -82 0	; "kv_page" -
	277	[440]	CALL     	7 3 2
	278	[446]	SETTABLE 	0 -80 7	; "title_bar" -
	279	[448]	GETTABLE 	7 0 -77	; "item_height"
	280	[448]	DIV      	7 7 -84	; - 4
	281	[448]	SETTABLE 	0 -83 7	; "item_margin" -
	282	[449]	GETTABLE 	7 0 -77	; "item_height"
	283	[449]	GETTABLE 	8 0 -83	; "item_margin"
	284	[449]	MUL      	8 -76 8	; 2 -
	285	[449]	ADD      	7 7 8
	286	[450]	GETTABLE 	8 0 -1	; "dimen"
	287	[450]	GETTABLE 	8 8 -6	; "h"
	288	[450]	GETTABLE 	9 0 -80	; "title_bar"
	289	[450]	SELF     	9 9 -50	; "getSize"
	290	[450]	CALL     	9 2 2
	291	[450]	GETTABLE 	9 9 -6	; "h"
	292	[450]	SUB      	8 8 9
	293	[450]	GETTABLE 	9 0 -71	; "page_info"
	294	[450]	SELF     	9 9 -50	; "getSize"
	295	[450]	CALL     	9 2 2
	296	[450]	GETTABLE 	9 9 -6	; "h"
	297	[450]	SUB      	8 8 9
	298	[451]	GETGLOBAL	9 -86	; math
	299	[451]	GETTABLE 	9 9 -87	; "floor"
	300	[451]	DIV      	10 8 7
	301	[451]	CALL     	9 2 2
	302	[451]	SETTABLE 	0 -85 9	; "items_per_page" -
	303	[452]	GETGLOBAL	9 -86	; math
	304	[452]	GETTABLE 	9 9 -89	; "ceil"
	305	[452]	GETTABLE 	10 0 -90	; "kv_pairs"
	306	[452]	LEN      	10 10
	307	[452]	GETTABLE 	11 0 -85	; "items_per_page"
	308	[452]	DIV      	10 10 11
	309	[452]	CALL     	9 2 2
	310	[452]	SETTABLE 	0 -88 9	; "pages" -
	311	[453]	GETUPVAL 	9 13	; VerticalGroup
	312	[453]	SELF     	9 9 -2	; "new"
	313	[453]	NEWTABLE 	11 0 0
	314	[453]	CALL     	9 3 2
	315	[453]	SETTABLE 	0 -91 9	; "main_content" -
	316	[456]	GETTABLE 	9 0 -75	; "item_width"
	317	[456]	SETTABLE 	0 -92 9	; "textviewer_width" -
	318	[457]	GETTABLE 	9 0 -1	; "dimen"
	319	[457]	GETTABLE 	9 9 -6	; "h"
	320	[457]	GETTABLE 	10 0 -80	; "title_bar"
	321	[457]	SELF     	10 10 -50	; "getSize"
	322	[457]	CALL     	10 2 2
	323	[457]	GETTABLE 	10 10 -6	; "h"
	324	[457]	MUL      	10 -76 10	; 2 -
	325	[457]	SUB      	9 9 10
	326	[457]	SETTABLE 	0 -93 9	; "textviewer_height" -
	327	[459]	SELF     	9 0 -94	; "_populateItems"
	328	[459]	CALL     	9 2 1
	329	[461]	GETUPVAL 	9 14	; OverlapGroup
	330	[461]	SELF     	9 9 -2	; "new"
	331	[461]	NEWTABLE 	11 2 2
	332	[462]	GETTABLE 	12 0 -1	; "dimen"
	333	[462]	SELF     	12 12 -72	; "copy"
	334	[462]	CALL     	12 2 2
	335	[462]	SETTABLE 	11 -1 12	; "dimen" -
	336	[463]	SETTABLE 	11 -95 -70	; "allow_mirroring" false
	337	[464]	GETUPVAL 	12 13	; VerticalGroup
	338	[464]	SELF     	12 12 -2	; "new"
	339	[464]	NEWTABLE 	14 2 1
	340	[465]	SETTABLE 	14 -96 -97	; "align" "left"
	341	[466]	GETTABLE 	15 0 -80	; "title_bar"
	342	[468]	GETTABLE 	16 0 -91	; "main_content"
	343	[468]	SETLIST  	14 2 1	; 1
	344	[464]	CALL     	12 3 2
	345	[470]	MOVE     	13 5
	346	[470]	SETLIST  	11 2 1	; 1
	347	[461]	CALL     	9 3 2
	348	[472]	GETUPVAL 	10 15	; FrameContainer
	349	[472]	SELF     	10 10 -2	; "new"
	350	[472]	NEWTABLE 	12 1 4
	351	[473]	GETTABLE 	13 0 -1	; "dimen"
	352	[473]	GETTABLE 	13 13 -6	; "h"
	353	[473]	SETTABLE 	12 -7 13	; "height" -
	354	[474]	SETTABLE 	12 -73 6	; "padding" -
	355	[475]	SETTABLE 	12 -34 -35	; "bordersize" 0
	356	[476]	GETUPVAL 	13 16	; Blitbuffer
	357	[476]	GETTABLE 	13 13 -100	; "COLOR_WHITE"
	358	[476]	SETTABLE 	12 -99 13	; "background" -
	359	[478]	MOVE     	13 9
	360	[478]	SETLIST  	12 1 1	; 1
	361	[472]	CALL     	10 3 2
	362	[478]	SETTABLE 	0 -98 10	; 1 -
	363	[479]	RETURN   	0 1

function <./frontend/ui/widget/keyvaluepage.lua:344,344> (4 instructions, 16 bytes at 0x7fac32c08a00)
0 params, 2 slots, 1 upvalue, 0 locals, 1 constant, 0 functions
	1	[344]	GETUPVAL 	0 0	; self
	2	[344]	SELF     	0 0 -1	; "onReturn"
	3	[344]	CALL     	0 2 1
	4	[344]	RETURN   	0 1

function <./frontend/ui/widget/keyvaluepage.lua:359,359> (4 instructions, 16 bytes at 0x7fac32c0a940)
0 params, 2 slots, 1 upvalue, 0 locals, 1 constant, 0 functions
	1	[359]	GETUPVAL 	0 0	; self
	2	[359]	SELF     	0 0 -1	; "prevPage"
	3	[359]	CALL     	0 2 1
	4	[359]	RETURN   	0 1

function <./frontend/ui/widget/keyvaluepage.lua:365,365> (4 instructions, 16 bytes at 0x7fac32c0abb0)
0 params, 2 slots, 1 upvalue, 0 locals, 1 constant, 0 functions
	1	[365]	GETUPVAL 	0 0	; self
	2	[365]	SELF     	0 0 -1	; "nextPage"
	3	[365]	CALL     	0 2 1
	4	[365]	RETURN   	0 1

function <./frontend/ui/widget/keyvaluepage.lua:371,371> (5 instructions, 20 bytes at 0x7fac32c0a660)
0 params, 3 slots, 1 upvalue, 0 locals, 2 constants, 0 functions
	1	[371]	GETUPVAL 	0 0	; self
	2	[371]	SELF     	0 0 -1	; "goToPage"
	3	[371]	LOADK    	2 -2	; 1
	4	[371]	CALL     	0 3 1
	5	[371]	RETURN   	0 1

function <./frontend/ui/widget/keyvaluepage.lua:377,377> (6 instructions, 24 bytes at 0x7fac32c09b30)
0 params, 3 slots, 1 upvalue, 0 locals, 2 constants, 0 functions
	1	[377]	GETUPVAL 	0 0	; self
	2	[377]	SELF     	0 0 -1	; "goToPage"
	3	[377]	GETUPVAL 	2 0	; self
	4	[377]	GETTABLE 	2 2 -2	; "pages"
	5	[377]	CALL     	0 3 1
	6	[377]	RETURN   	0 1

function <./frontend/ui/widget/keyvaluepage.lua:404,406> (8 instructions, 32 bytes at 0x7fac32c0b050)
0 params, 4 slots, 1 upvalue, 0 locals, 4 constants, 0 functions
	1	[405]	LOADK    	0 -1	; "("
	2	[405]	LOADK    	1 -2	; "1 - "
	3	[405]	GETUPVAL 	2 0	; self
	4	[405]	GETTABLE 	2 2 -3	; "pages"
	5	[405]	LOADK    	3 -4	; ")"
	6	[405]	CONCAT   	0 0 3
	7	[405]	RETURN   	0 2
	8	[406]	RETURN   	0 1

function <./frontend/ui/widget/keyvaluepage.lua:407,412> (16 instructions, 64 bytes at 0x7fac32c0b1f0)
1 param, 5 slots, 1 upvalue, 2 locals, 4 constants, 0 functions
	1	[408]	GETGLOBAL	1 -1	; tonumber
	2	[408]	MOVE     	2 0
	3	[408]	CALL     	1 2 2
	4	[409]	TEST     	1 0 0
	5	[409]	JMP      	10	; to 16
	6	[409]	LE       	0 -2 1	; 1 -
	7	[409]	JMP      	8	; to 16
	8	[409]	GETUPVAL 	2 0	; self
	9	[409]	GETTABLE 	2 2 -3	; "pages"
	10	[409]	LE       	0 1 2
	11	[409]	JMP      	4	; to 16
	12	[410]	GETUPVAL 	2 0	; self
	13	[410]	SELF     	2 2 -4	; "goToPage"
	14	[410]	MOVE     	4 1
	15	[410]	CALL     	2 3 1
	16	[412]	RETURN   	0 1

function <./frontend/ui/widget/keyvaluepage.lua:481,487> (13 instructions, 52 bytes at 0x7fac32c0af30)
1 param, 4 slots, 0 upvalues, 2 locals, 6 constants, 0 functions
	1	[482]	GETGLOBAL	1 -1	; math
	2	[482]	GETTABLE 	1 1 -2	; "min"
	3	[482]	GETTABLE 	2 0 -3	; "show_page"
	4	[482]	ADD      	2 2 -4	; - 1
	5	[482]	GETTABLE 	3 0 -5	; "pages"
	6	[482]	CALL     	1 3 2
	7	[483]	GETTABLE 	2 0 -3	; "show_page"
	8	[483]	LT       	0 2 1
	9	[483]	JMP      	3	; to 13
	10	[484]	SETTABLE 	0 -3 1	; "show_page" -
	11	[485]	SELF     	2 0 -6	; "_populateItems"
	12	[485]	CALL     	2 2 1
	13	[487]	RETURN   	0 1

function <./frontend/ui/widget/keyvaluepage.lua:489,495> (13 instructions, 52 bytes at 0x7fac32c0c100)
1 param, 4 slots, 0 upvalues, 2 locals, 5 constants, 0 functions
	1	[490]	GETGLOBAL	1 -1	; math
	2	[490]	GETTABLE 	1 1 -2	; "max"
	3	[490]	GETTABLE 	2 0 -3	; "show_page"
	4	[490]	SUB      	2 2 -4	; - 1
	5	[490]	LOADK    	3 -4	; 1
	6	[490]	CALL     	1 3 2
	7	[491]	GETTABLE 	2 0 -3	; "show_page"
	8	[491]	LT       	0 1 2
	9	[491]	JMP      	3	; to 13
	10	[492]	SETTABLE 	0 -3 1	; "show_page" -
	11	[493]	SELF     	2 0 -5	; "_populateItems"
	12	[493]	CALL     	2 2 1
	13	[495]	RETURN   	0 1

function <./frontend/ui/widget/keyvaluepage.lua:497,500> (4 instructions, 16 bytes at 0x7fac32c0be50)
2 params, 4 slots, 0 upvalues, 2 locals, 2 constants, 0 functions
	1	[498]	SETTABLE 	0 -1 1	; "show_page" -
	2	[499]	SELF     	2 0 -2	; "_populateItems"
	3	[499]	CALL     	2 2 1
	4	[500]	RETURN   	0 1

function <./frontend/ui/widget/keyvaluepage.lua:503,563> (207 instructions, 828 bytes at 0x7fac32c0c9c0)
1 param, 17 slots, 9 upvalues, 8 locals, 53 constants, 1 function
	1	[504]	GETTABLE 	1 0 -1	; "page_info"
	2	[504]	SELF     	1 1 -2	; "resetLayout"
	3	[504]	CALL     	1 2 1
	4	[505]	GETTABLE 	1 0 -3	; "main_content"
	5	[505]	SELF     	1 1 -4	; "clear"
	6	[505]	CALL     	1 2 1
	7	[506]	GETTABLE 	1 0 -5	; "show_page"
	8	[506]	SUB      	1 1 -6	; - 1
	9	[506]	GETTABLE 	2 0 -7	; "items_per_page"
	10	[506]	MUL      	1 1 2
	11	[507]	LOADK    	2 -6	; 1
	12	[507]	GETTABLE 	3 0 -7	; "items_per_page"
	13	[507]	LOADK    	4 -6	; 1
	14	[507]	FORPREP  	2 109	; to 124
	15	[508]	GETTABLE 	6 0 -8	; "kv_pairs"
	16	[508]	ADD      	7 1 5
	17	[508]	GETTABLE 	6 6 7
	18	[509]	EQ       	0 6 -9	; - nil
	19	[509]	JMP      	1	; to 21
	20	[509]	JMP      	104	; to 125
	21	[511]	GETGLOBAL	7 -10	; table
	22	[511]	GETTABLE 	7 7 -11	; "insert"
	23	[511]	GETTABLE 	8 0 -3	; "main_content"
	24	[512]	GETUPVAL 	9 0	; VerticalSpan
	25	[512]	SELF     	9 9 -12	; "new"
	26	[512]	NEWTABLE 	11 0 1
	27	[512]	GETTABLE 	12 0 -14	; "item_margin"
	28	[512]	SETTABLE 	11 -13 12	; "width" -
	29	[512]	CALL     	9 3 0
	30	[511]	CALL     	7 0 1
	31	[513]	GETGLOBAL	7 -15	; type
	32	[513]	MOVE     	8 6
	33	[513]	CALL     	7 2 2
	34	[513]	EQ       	0 7 -10	; - "table"
	35	[513]	JMP      	32	; to 68
	36	[514]	GETGLOBAL	7 -10	; table
	37	[514]	GETTABLE 	7 7 -11	; "insert"
	38	[515]	GETTABLE 	8 0 -3	; "main_content"
	39	[516]	GETUPVAL 	9 1	; KeyValueItem
	40	[516]	SELF     	9 9 -12	; "new"
	41	[516]	NEWTABLE 	11 0 12
	42	[517]	GETTABLE 	12 0 -17	; "item_height"
	43	[517]	SETTABLE 	11 -16 12	; "height" -
	44	[518]	GETTABLE 	12 0 -18	; "item_width"
	45	[518]	SETTABLE 	11 -13 12	; "width" -
	46	[519]	GETTABLE 	12 6 -6	; 1
	47	[519]	SETTABLE 	11 -19 12	; "key" -
	48	[520]	GETTABLE 	12 6 -21	; 2
	49	[520]	SETTABLE 	11 -20 12	; "value" -
	50	[521]	GETTABLE 	12 0 -23	; "values_lang"
	51	[521]	SETTABLE 	11 -22 12	; "value_lang" -
	52	[522]	GETTABLE 	12 6 -24	; "callback"
	53	[522]	SETTABLE 	11 -24 12	; "callback" -
	54	[523]	GETTABLE 	12 6 -25	; "callback_back"
	55	[523]	SETTABLE 	11 -25 12	; "callback_back" -
	56	[524]	GETTABLE 	12 0 -26	; "textviewer_width"
	57	[524]	SETTABLE 	11 -26 12	; "textviewer_width" -
	58	[525]	GETTABLE 	12 0 -27	; "textviewer_height"
	59	[525]	SETTABLE 	11 -27 12	; "textviewer_height" -
	60	[526]	GETTABLE 	12 0 -28	; "value_overflow_align"
	61	[526]	SETTABLE 	11 -28 12	; "value_overflow_align" -
	62	[527]	GETTABLE 	12 0 -29	; "value_align"
	63	[527]	SETTABLE 	11 -29 12	; "value_align" -
	64	[528]	SETTABLE 	11 -30 0	; "show_parent" -
	65	[516]	CALL     	9 3 0
	66	[514]	CALL     	7 0 1
	67	[530]	JMP      	46	; to 114
	68	[531]	GETGLOBAL	7 -15	; type
	69	[531]	MOVE     	8 6
	70	[531]	CALL     	7 2 2
	71	[531]	EQ       	0 7 -31	; - "string"
	72	[531]	JMP      	41	; to 114
	73	[532]	GETGLOBAL	7 -31	; string
	74	[532]	GETTABLE 	7 7 -32	; "sub"
	75	[532]	MOVE     	8 6
	76	[532]	LOADK    	9 -6	; 1
	77	[532]	LOADK    	10 -6	; 1
	78	[532]	CALL     	7 4 2
	79	[533]	EQ       	0 7 -33	; - "-"
	80	[533]	JMP      	33	; to 114
	81	[534]	GETGLOBAL	8 -10	; table
	82	[534]	GETTABLE 	8 8 -11	; "insert"
	83	[534]	GETTABLE 	9 0 -3	; "main_content"
	84	[535]	GETUPVAL 	10 0	; VerticalSpan
	85	[535]	SELF     	10 10 -12	; "new"
	86	[535]	NEWTABLE 	12 0 1
	87	[535]	GETTABLE 	13 0 -14	; "item_margin"
	88	[535]	SETTABLE 	12 -13 13	; "width" -
	89	[535]	CALL     	10 3 0
	90	[534]	CALL     	8 0 1
	91	[536]	GETGLOBAL	8 -10	; table
	92	[536]	GETTABLE 	8 8 -11	; "insert"
	93	[536]	GETTABLE 	9 0 -3	; "main_content"
	94	[536]	GETUPVAL 	10 2	; LineWidget
	95	[536]	SELF     	10 10 -12	; "new"
	96	[536]	NEWTABLE 	12 0 3
	97	[537]	GETUPVAL 	13 3	; Blitbuffer
	98	[537]	GETTABLE 	13 13 -35	; "COLOR_LIGHT_GRAY"
	99	[537]	SETTABLE 	12 -34 13	; "background" -
	100	[538]	GETUPVAL 	13 4	; Geom
	101	[538]	SELF     	13 13 -12	; "new"
	102	[538]	NEWTABLE 	15 0 2
	103	[539]	GETTABLE 	16 0 -18	; "item_width"
	104	[539]	SETTABLE 	15 -37 16	; "w" -
	105	[540]	GETUPVAL 	16 5	; Size
	106	[540]	GETTABLE 	16 16 -39	; "line"
	107	[540]	GETTABLE 	16 16 -40	; "thick"
	108	[540]	SETTABLE 	15 -38 16	; "h" -
	109	[538]	CALL     	13 3 2
	110	[541]	SETTABLE 	12 -36 13	; "dimen" -
	111	[542]	SETTABLE 	12 -41 -42	; "style" "solid"
	112	[536]	CALL     	10 3 0
	113	[536]	CALL     	8 0 1
	114	[546]	GETGLOBAL	7 -10	; table
	115	[546]	GETTABLE 	7 7 -11	; "insert"
	116	[546]	GETTABLE 	8 0 -3	; "main_content"
	117	[547]	GETUPVAL 	9 0	; VerticalSpan
	118	[547]	SELF     	9 9 -12	; "new"
	119	[547]	NEWTABLE 	11 0 1
	120	[547]	GETTABLE 	12 0 -14	; "item_margin"
	121	[547]	SETTABLE 	11 -13 12	; "width" -
	122	[547]	CALL     	9 3 0
	123	[546]	CALL     	7 0 1
	124	[507]	FORLOOP  	2 -110	; to 15
	125	[549]	GETTABLE 	2 0 -43	; "page_info_text"
	126	[549]	SELF     	2 2 -44	; "setText"
	127	[549]	GETUPVAL 	4 6	; T
	128	[549]	GETUPVAL 	5 7	; _
	129	[549]	LOADK    	6 -45	; "Page %1 of %2"
	130	[549]	CALL     	5 2 2
	131	[549]	GETTABLE 	6 0 -5	; "show_page"
	132	[549]	GETTABLE 	7 0 -46	; "pages"
	133	[549]	CALL     	4 4 0
	134	[549]	CALL     	2 0 1
	135	[550]	GETTABLE 	2 0 -47	; "page_info_left_chev"
	136	[550]	SELF     	2 2 -48	; "showHide"
	137	[550]	GETTABLE 	4 0 -46	; "pages"
	138	[550]	LT       	1 -6 4	; 1 -
	139	[550]	JMP      	1	; to 141
	140	[550]	LOADBOOL 	4 0 1
	141	[550]	LOADBOOL 	4 1 0
	142	[550]	CALL     	2 3 1
	143	[551]	GETTABLE 	2 0 -49	; "page_info_right_chev"
	144	[551]	SELF     	2 2 -48	; "showHide"
	145	[551]	GETTABLE 	4 0 -46	; "pages"
	146	[551]	LT       	1 -6 4	; 1 -
	147	[551]	JMP      	1	; to 149
	148	[551]	LOADBOOL 	4 0 1
	149	[551]	LOADBOOL 	4 1 0
	150	[551]	CALL     	2 3 1
	151	[552]	GETTABLE 	2 0 -50	; "page_info_first_chev"
	152	[552]	SELF     	2 2 -48	; "showHide"
	153	[552]	GETTABLE 	4 0 -46	; "pages"
	154	[552]	LT       	1 -21 4	; 2 -
	155	[552]	JMP      	1	; to 157
	156	[552]	LOADBOOL 	4 0 1
	157	[552]	LOADBOOL 	4 1 0
	158	[552]	CALL     	2 3 1
	159	[553]	GETTABLE 	2 0 -51	; "page_info_last_chev"
	160	[553]	SELF     	2 2 -48	; "showHide"
	161	[553]	GETTABLE 	4 0 -46	; "pages"
	162	[553]	LT       	1 -21 4	; 2 -
	163	[553]	JMP      	1	; to 165
	164	[553]	LOADBOOL 	4 0 1
	165	[553]	LOADBOOL 	4 1 0
	166	[553]	CALL     	2 3 1
	167	[555]	GETTABLE 	2 0 -47	; "page_info_left_chev"
	168	[555]	SELF     	2 2 -52	; "enableDisable"
	169	[555]	GETTABLE 	4 0 -5	; "show_page"
	170	[555]	LT       	1 -6 4	; 1 -
	171	[555]	JMP      	1	; to 173
	172	[555]	LOADBOOL 	4 0 1
	173	[555]	LOADBOOL 	4 1 0
	174	[555]	CALL     	2 3 1
	175	[556]	GETTABLE 	2 0 -49	; "page_info_right_chev"
	176	[556]	SELF     	2 2 -52	; "enableDisable"
	177	[556]	GETTABLE 	4 0 -5	; "show_page"
	178	[556]	GETTABLE 	5 0 -46	; "pages"
	179	[556]	LT       	1 4 5
	180	[556]	JMP      	1	; to 182
	181	[556]	LOADBOOL 	4 0 1
	182	[556]	LOADBOOL 	4 1 0
	183	[556]	CALL     	2 3 1
	184	[557]	GETTABLE 	2 0 -50	; "page_info_first_chev"
	185	[557]	SELF     	2 2 -52	; "enableDisable"
	186	[557]	GETTABLE 	4 0 -5	; "show_page"
	187	[557]	LT       	1 -6 4	; 1 -
	188	[557]	JMP      	1	; to 190
	189	[557]	LOADBOOL 	4 0 1
	190	[557]	LOADBOOL 	4 1 0
	191	[557]	CALL     	2 3 1
	192	[558]	GETTABLE 	2 0 -51	; "page_info_last_chev"
	193	[558]	SELF     	2 2 -52	; "enableDisable"
	194	[558]	GETTABLE 	4 0 -5	; "show_page"
	195	[558]	GETTABLE 	5 0 -46	; "pages"
	196	[558]	LT       	1 4 5
	197	[558]	JMP      	1	; to 199
	198	[558]	LOADBOOL 	4 0 1
	199	[558]	LOADBOOL 	4 1 0
	200	[558]	CALL     	2 3 1
	201	[560]	GETUPVAL 	2 8	; UIManager
	202	[560]	SELF     	2 2 -53	; "setDirty"
	203	[560]	MOVE     	4 0
	204	[562]	CLOSURE  	5 0	; 0x7fac32c0cd50
	205	[562]	MOVE     	0 0
	206	[560]	CALL     	2 4 1
	207	[563]	RETURN   	0 1

function <./frontend/ui/widget/keyvaluepage.lua:560,562> (5 instructions, 20 bytes at 0x7fac32c0cd50)
0 params, 2 slots, 1 upvalue, 0 locals, 2 constants, 0 functions
	1	[561]	LOADK    	0 -1	; "ui"
	2	[561]	GETUPVAL 	1 0	; self
	3	[561]	GETTABLE 	1 1 -2	; "dimen"
	4	[561]	RETURN   	0 3
	5	[562]	RETURN   	0 1

function <./frontend/ui/widget/keyvaluepage.lua:565,568> (5 instructions, 20 bytes at 0x7fac32c0ce70)
1 param, 3 slots, 0 upvalues, 1 local, 1 constant, 0 functions
	1	[566]	SELF     	1 0 -1	; "nextPage"
	2	[566]	CALL     	1 2 1
	3	[567]	LOADBOOL 	1 1 0
	4	[567]	RETURN   	1 2
	5	[568]	RETURN   	0 1

function <./frontend/ui/widget/keyvaluepage.lua:570,573> (5 instructions, 20 bytes at 0x7fac32c0d140)
1 param, 3 slots, 0 upvalues, 1 local, 1 constant, 0 functions
	1	[571]	SELF     	1 0 -1	; "prevPage"
	2	[571]	CALL     	1 2 1
	3	[572]	LOADBOOL 	1 1 0
	4	[572]	RETURN   	1 2
	5	[573]	RETURN   	0 1

function <./frontend/ui/widget/keyvaluepage.lua:575,596> (34 instructions, 136 bytes at 0x7fac32c0d3f0)
3 params, 8 slots, 2 upvalues, 4 locals, 11 constants, 0 functions
	1	[576]	GETUPVAL 	3 0	; BD
	2	[576]	GETTABLE 	3 3 -1	; "flipDirectionIfMirroredUILayout"
	3	[576]	GETTABLE 	4 2 -2	; "direction"
	4	[576]	CALL     	3 2 2
	5	[577]	EQ       	0 3 -3	; - "west"
	6	[577]	JMP      	5	; to 12
	7	[578]	SELF     	4 0 -4	; "nextPage"
	8	[578]	CALL     	4 2 1
	9	[579]	LOADBOOL 	4 1 0
	10	[579]	RETURN   	4 2
	11	[579]	JMP      	22	; to 34
	12	[580]	EQ       	0 3 -5	; - "east"
	13	[580]	JMP      	5	; to 19
	14	[581]	SELF     	4 0 -6	; "prevPage"
	15	[581]	CALL     	4 2 1
	16	[582]	LOADBOOL 	4 1 0
	17	[582]	RETURN   	4 2
	18	[582]	JMP      	15	; to 34
	19	[583]	EQ       	0 3 -7	; - "south"
	20	[583]	JMP      	3	; to 24
	21	[585]	SELF     	4 0 -8	; "onClose"
	22	[585]	CALL     	4 2 1
	23	[585]	JMP      	10	; to 34
	24	[586]	EQ       	0 3 -9	; - "north"
	25	[586]	JMP      	1	; to 27
	26	[588]	JMP      	7	; to 34
	27	[591]	GETUPVAL 	4 1	; UIManager
	28	[591]	SELF     	4 4 -10	; "setDirty"
	29	[591]	LOADNIL  	6 6
	30	[591]	LOADK    	7 -11	; "full"
	31	[591]	CALL     	4 4 1
	32	[594]	LOADBOOL 	4 0 0
	33	[594]	RETURN   	4 2
	34	[596]	RETURN   	0 1

function <./frontend/ui/widget/keyvaluepage.lua:598,601> (7 instructions, 28 bytes at 0x7fac32c0d840)
1 param, 4 slots, 1 upvalue, 1 local, 1 constant, 0 functions
	1	[599]	GETUPVAL 	1 0	; UIManager
	2	[599]	SELF     	1 1 -1	; "close"
	3	[599]	MOVE     	3 0
	4	[599]	CALL     	1 3 1
	5	[600]	LOADBOOL 	1 1 0
	6	[600]	RETURN   	1 2
	7	[601]	RETURN   	0 1

function <./frontend/ui/widget/keyvaluepage.lua:603,609> (15 instructions, 60 bytes at 0x7fac32c0dcc0)
1 param, 5 slots, 1 upvalue, 1 local, 4 constants, 0 functions
	1	[604]	GETTABLE 	1 0 -1	; "callback_return"
	2	[604]	TEST     	1 0 0
	3	[604]	JMP      	11	; to 15
	4	[605]	SELF     	1 0 -1	; "callback_return"
	5	[605]	CALL     	1 2 1
	6	[606]	GETUPVAL 	1 0	; UIManager
	7	[606]	SELF     	1 1 -2	; "close"
	8	[606]	MOVE     	3 0
	9	[606]	CALL     	1 3 1
	10	[607]	GETUPVAL 	1 0	; UIManager
	11	[607]	SELF     	1 1 -3	; "setDirty"
	12	[607]	LOADNIL  	3 3
	13	[607]	LOADK    	4 -4	; "ui"
	14	[607]	CALL     	1 4 1
	15	[609]	RETURN   	0 1
