-- BYTECODE -- ko_KR_helper.lua:67-73
0001    UGET     1   0      ; HgSylbls
0002    MOV      2   1
0003    TGETS    1   1   0  ; "_create_inverse_tbl_impl"
0004    KSTR     3   1      ; "CHARS"
0005    KSTR     4   2      ; "IDX"
0006    KSTR     5   3      ; "INITIAL"
0007    CALL     1   1   5
0008    UGET     1   0      ; HgSylbls
0009    MOV      2   1
0010    TGETS    1   1   0  ; "_create_inverse_tbl_impl"
0011    KSTR     3   1      ; "CHARS"
0012    KSTR     4   2      ; "IDX"
0013    KSTR     5   4      ; "MEDIAL"
0014    CALL     1   1   5
0015    UGET     1   0      ; HgSylbls
0016    MOV      2   1
0017    TGETS    1   1   0  ; "_create_inverse_tbl_impl"
0018    KSTR     3   1      ; "CHARS"
0019    KSTR     4   2      ; "IDX"
0020    KSTR     5   5      ; "MEDIAL_COMBINABLE"
0021    CALL     1   1   5
0022    UGET     1   0      ; HgSylbls
0023    MOV      2   1
0024    TGETS    1   1   0  ; "_create_inverse_tbl_impl"
0025    KSTR     3   1      ; "CHARS"
0026    KSTR     4   2      ; "IDX"
0027    KSTR     5   6      ; "FINAL"
0028    CALL     1   1   5
0029    UGET     1   0      ; HgSylbls
0030    MOV      2   1
0031    TGETS    1   1   0  ; "_create_inverse_tbl_impl"
0032    KSTR     3   1      ; "CHARS"
0033    KSTR     4   2      ; "IDX"
0034    KSTR     5   7      ; "FINAL_COMBINABLE"
0035    CALL     1   1   5
0036    RET0     0   1

-- BYTECODE -- ko_KR_helper.lua:75-82
0001    UGET     4   0      ; HgSylbls
0002    MOV      5   2
0003    KSTR     6   0      ; "_"
0004    MOV      7   3
0005    CAT      5   5   7
0006    TNEW     6   0
0007    TSETV    6   4   5
0008    GGET     4   1      ; "pairs"
0009    UGET     5   0      ; HgSylbls
0010    MOV      6   1
0011    KSTR     7   0      ; "_"
0012    MOV      8   3
0013    CAT      6   6   8
0014    TGETV    5   5   6
0015    CALL     4   4   2
0016    ISNEXT   7 => 0025
0017 => UGET     9   0      ; HgSylbls
0018    MOV     10   2
0019    KSTR    11   0      ; "_"
0020    MOV     12   3
0021    CAT     10  10  12
0022    TGETV    9   9  10
0023    SUBVN   10   7   0  ; 1
0024    TSETV   10   9   8
0025 => ITERN    7   3   3
0026    ITERL    7 => 0017
0027    RET0     0   1

-- BYTECODE -- ko_KR_helper.lua:85-88
0001    UGET     4   0      ; util
0002    TGETS    4   4   0  ; "unicodeCodepointToUtf8"
0003    UGET     5   1      ; HgSylbls
0004    MOV      6   5
0005    TGETS    5   5   1  ; "_get_combined_charcode"
0006    MOV      7   1
0007    MOV      8   2
0008    MOV      9   3
0009    CALL     5   0   5
0010    CALLMT   4   0

-- BYTECODE -- ko_KR_helper.lua:89-103
0001    UGET     4   0      ; HgSylbls
0002    TGETS    4   4   0  ; "CHARS_MEDIAL"
0003    LEN      4   4
0004    UGET     5   0      ; HgSylbls
0005    TGETS    5   5   1  ; "CHARS_FINAL"
0006    LEN      5   5
0007    UGET     6   0      ; HgSylbls
0008    TGETS    6   6   2  ; "UNI_HG_BASE"
0009    UGET     7   0      ; HgSylbls
0010    MOV      8   7
0011    TGETS    7   7   3  ; "_initial_idx"
0012    MOV      9   1
0013    CALL     7   2   3
0014    MULVV    7   7   4
0015    MULVV    7   7   5
0016    ADDVV    6   6   7
0017    UGET     7   0      ; HgSylbls
0018    MOV      8   7
0019    TGETS    7   7   4  ; "_medial_idx"
0020    MOV      9   2
0021    CALL     7   2   3
0022    MULVV    7   7   5
0023    ADDVV    6   6   7
0024    UGET     7   0      ; HgSylbls
0025    MOV      8   7
0026    TGETS    7   7   5  ; "_final_idx"
0027    MOV      9   3
0028    CALL     7   2   3
0029    ISF          7
0030    JMP      8 => 0032
0031    ADDVV    6   6   7
0032 => RET1     6   2

-- BYTECODE -- ko_KR_helper.lua:105-108
0001    UGET     2   0      ; HgSylbls
0002    TGETS    2   2   0  ; "IDX_INITIAL"
0003    TGETV    2   2   1
0004    RET1     2   2

-- BYTECODE -- ko_KR_helper.lua:109-112
0001    UGET     2   0      ; HgSylbls
0002    MOV      3   2
0003    TGETS    2   2   0  ; "_2elem_tbl_to_str"
0004    MOV      4   1
0005    CALL     2   2   3
0006    MOV      1   2
0007    UGET     2   0      ; HgSylbls
0008    TGETS    2   2   1  ; "IDX_MEDIAL"
0009    TGETV    2   2   1
0010    RET1     2   2

-- BYTECODE -- ko_KR_helper.lua:113-116
0001    UGET     2   0      ; HgSylbls
0002    MOV      3   2
0003    TGETS    2   2   0  ; "_2elem_tbl_to_str"
0004    MOV      4   1
0005    CALL     2   2   3
0006    MOV      1   2
0007    UGET     2   0      ; HgSylbls
0008    TGETS    2   2   1  ; "IDX_FINAL"
0009    TGETV    2   2   1
0010    RET1     2   2

-- BYTECODE -- ko_KR_helper.lua:119-122
0001    UGET     2   0      ; HgSylbls
0002    TGETS    2   2   0  ; "IDX_INITIAL"
0003    TGETV    2   2   1
0004    ISNEP    2   0
0005    JMP      2 => 0008
0006    KPRI     2   1
0007    JMP      3 => 0009
0008 => KPRI     2   2
0009 => RET1     2   2

-- BYTECODE -- ko_KR_helper.lua:123-126
0001    UGET     2   0      ; HgSylbls
0002    MOV      3   2
0003    TGETS    2   2   0  ; "_2elem_tbl_to_str"
0004    MOV      4   1
0005    CALL     2   2   3
0006    MOV      1   2
0007    UGET     2   0      ; HgSylbls
0008    TGETS    2   2   1  ; "IDX_MEDIAL"
0009    TGETV    2   2   1
0010    ISNEP    2   0
0011    JMP      2 => 0014
0012    KPRI     2   1
0013    JMP      3 => 0015
0014 => KPRI     2   2
0015 => RET1     2   2

-- BYTECODE -- ko_KR_helper.lua:127-130
0001    UGET     2   0      ; HgSylbls
0002    MOV      3   2
0003    TGETS    2   2   0  ; "_2elem_tbl_to_str"
0004    MOV      4   1
0005    CALL     2   2   3
0006    MOV      1   2
0007    UGET     2   0      ; HgSylbls
0008    TGETS    2   2   1  ; "IDX_FINAL"
0009    TGETV    2   2   1
0010    ISNEP    2   0
0011    JMP      2 => 0014
0012    KPRI     2   1
0013    JMP      3 => 0015
0014 => KPRI     2   2
0015 => RET1     2   2

-- BYTECODE -- ko_KR_helper.lua:131-133
0001    UGET     2   0      ; HgSylbls
0002    TGETS    2   2   0  ; "IDX_MEDIAL_COMBINABLE"
0003    TGETV    2   2   1
0004    ISNEP    2   0
0005    JMP      2 => 0008
0006    KPRI     2   1
0007    JMP      3 => 0009
0008 => KPRI     2   2
0009 => RET1     2   2

-- BYTECODE -- ko_KR_helper.lua:134-136
0001    UGET     2   0      ; HgSylbls
0002    TGETS    2   2   0  ; "IDX_FINAL_COMBINABLE"
0003    TGETV    2   2   1
0004    ISNEP    2   0
0005    JMP      2 => 0008
0006    KPRI     2   1
0007    JMP      3 => 0009
0008 => KPRI     2   2
0009 => RET1     2   2

-- BYTECODE -- ko_KR_helper.lua:138-142
0001    UGET     2   0      ; HgSylbls
0002    MOV      3   2
0003    TGETS    2   2   0  ; "_in_target_char_group"
0004    MOV      4   1
0005    UGET     5   0      ; HgSylbls
0006    TGETS    5   5   1  ; "UNI_HG_CONSONNANT_BASE"
0007    UGET     6   0      ; HgSylbls
0008    TGETS    6   6   2  ; "UNI_HG_CONSONNANT_UPPER"
0009    UGET     7   0      ; HgSylbls
0010    TGETS    7   7   3  ; "UNI_HG_COMPAT_CONSONNANT_BASE"
0011    UGET     8   0      ; HgSylbls
0012    TGETS    8   8   4  ; "UNI_HG_COMPAT_CONSONNANT_UPPER"
0013    CALLT    2   7

-- BYTECODE -- ko_KR_helper.lua:143-147
0001    UGET     2   0      ; HgSylbls
0002    MOV      3   2
0003    TGETS    2   2   0  ; "_in_target_char_group"
0004    MOV      4   1
0005    UGET     5   0      ; HgSylbls
0006    TGETS    5   5   1  ; "UNI_HG_VOWEL_BASE"
0007    UGET     6   0      ; HgSylbls
0008    TGETS    6   6   2  ; "UNI_HG_VOWEL_UPPER"
0009    UGET     7   0      ; HgSylbls
0010    TGETS    7   7   3  ; "UNI_HG_COMPAT_VOWEL_BASE"
0011    UGET     8   0      ; HgSylbls
0012    TGETS    8   8   4  ; "UNI_HG_COMPAT_VOWEL_UPPER"
0013    CALLT    2   7

-- BYTECODE -- ko_KR_helper.lua:148-163
0001    UGET     6   0      ; BaseUtil
0002    TGETS    6   6   0  ; "utf8charcode"
0003    MOV      7   1
0004    CALL     6   2   2
0005    ISNEP    6   0
0006    JMP      7 => 0009
0007    KPRI     7   1
0008    RET1     7   2
0009 => ISGT     2   6
0010    JMP      7 => 0013
0011    ISLE     6   3
0012    JMP      7 => 0015
0013 => KPRI     7   1
0014    JMP      8 => 0016
0015 => KPRI     7   2
0016 => KPRI     8   1
0017    ISEQP    4   0
0018    JMP      9 => 0026
0019    ISGT     4   6
0020    JMP      9 => 0023
0021    ISLE     6   5
0022    JMP      9 => 0025
0023 => KPRI     8   1
0024    JMP      9 => 0026
0025 => KPRI     8   2
0026 => ISTC     9   7
0027    JMP      9 => 0029
0028    MOV      9   8
0029 => RET1     9   2

-- BYTECODE -- ko_KR_helper.lua:165-174
0001    GGET     2   0      ; "type"
0002    MOV      3   1
0003    CALL     2   2   2
0004    ISNES    2   1      ; "table"
0005    JMP      2 => 0011
0006    MOV      2   1
0007    TGETB    3   2   1
0008    TGETB    4   2   2
0009    CAT      3   3   4
0010    RET1     3   2
0011 => RET1     1   2

-- BYTECODE -- ko_KR_helper.lua:186-188
0001    UGET     2   0      ; logger
0002    TGETS    2   2   0  ; "dbg"
0003    KSTR     3   1      ; "UI:put_char()"
0004    MOV      4   1
0005    CALL     2   1   3
0006    RET0     0   1

-- BYTECODE -- ko_KR_helper.lua:189-191
0001    UGET     1   0      ; logger
0002    TGETS    1   1   0  ; "dbg"
0003    KSTR     2   1      ; "UI:del_char()"
0004    CALL     1   1   2
0005    RET0     0   1

-- BYTECODE -- ko_KR_helper.lua:192-195
0001    UGET     2   0      ; UIHandler
0002    MOV      3   2
0003    TGETS    2   2   0  ; "del_char"
0004    CALL     2   1   2
0005    UGET     2   0      ; UIHandler
0006    MOV      3   2
0007    TGETS    2   2   1  ; "put_char"
0008    MOV      4   1
0009    CALL     2   1   3
0010    RET0     0   1

-- BYTECODE -- ko_KR_helper.lua:223-227
0001    UGET     2   0      ; HgFSM
0002    MOV      3   2
0003    TGETS    2   2   0  ; "clean_state"
0004    CALL     2   1   2
0005    UGET     2   0      ; HgFSM
0006    TSETS    1   2   1  ; "ui_handler"
0007    RET0     0   1

-- BYTECODE -- ko_KR_helper.lua:229-238
0001    UGET     1   0      ; HgFSM
0002    KPRI     2   0
0003    TSETS    2   1   0  ; "initial"
0004    UGET     1   0      ; HgFSM
0005    KPRI     2   0
0006    TSETS    2   1   1  ; "medial"
0007    UGET     1   0      ; HgFSM
0008    KPRI     2   0
0009    TSETS    2   1   2  ; "final"
0010    UGET     1   0      ; HgFSM
0011    TNEW     2   3
0012    UGET     3   0      ; HgFSM
0013    TGETS    3   3   4  ; "STATE"
0014    TGETS    3   3   5  ; "IDLE"
0015    TSETB    3   2   1
0016    TSETS    2   1   3  ; "fsm_prev_states"
0017    UGET     1   0      ; HgFSM
0018    UGET     2   0      ; HgFSM
0019    TGETS    2   2   4  ; "STATE"
0020    TGETS    2   2   5  ; "IDLE"
0021    TSETS    2   1   6  ; "fsm_state"
0022    UGET     1   0      ; HgFSM
0023    KPRI     2   1
0024    TSETS    2   1   7  ; "do_not_del_in_medial"
0025    RET0     0   1

-- BYTECODE -- ko_KR_helper.lua:240-243
0001    UGET     2   0      ; HgFSM
0002    TGETS    2   2   0  ; "fsm_prev_states"
0003    UGET     3   0      ; HgFSM
0004    TGETS    3   3   0  ; "fsm_prev_states"
0005    LEN      3   3
0006    ADDVN    3   3   0  ; 1
0007    TSETV    1   2   3
0008    UGET     2   0      ; HgFSM
0009    TSETS    1   2   1  ; "fsm_state"
0010    RET0     0   1

-- BYTECODE -- ko_KR_helper.lua:244-251
0001    UGET     1   0      ; HgFSM
0002    TGETS    1   1   0  ; "fsm_prev_states"
0003    UGET     2   0      ; HgFSM
0004    TGETS    2   2   0  ; "fsm_prev_states"
0005    LEN      2   2
0006    TGETV    1   1   2
0007    GGET     2   1      ; "table"
0008    TGETS    2   2   2  ; "remove"
0009    UGET     3   0      ; HgFSM
0010    TGETS    3   3   0  ; "fsm_prev_states"
0011    CALL     2   1   2
0012    UGET     2   0      ; HgFSM
0013    UGET     3   0      ; HgFSM
0014    TGETS    3   3   0  ; "fsm_prev_states"
0015    UGET     4   0      ; HgFSM
0016    TGETS    4   4   0  ; "fsm_prev_states"
0017    LEN      4   4
0018    TGETV    3   3   4
0019    TSETS    3   2   3  ; "fsm_state"
0020    RET1     1   2

-- BYTECODE -- ko_KR_helper.lua:253-259
0001    UGET     2   0      ; HgFSM
0002    MOV      3   2
0003    TGETS    2   2   0  ; "_should_handle_as_target_char"
0004    MOV      4   1
0005    CALL     2   2   3
0006    ISF          2
0007    JMP      3 => 0014
0008    UGET     2   0      ; HgFSM
0009    MOV      3   2
0010    TGETS    2   2   1  ; "_process_hg_char"
0011    MOV      4   1
0012    CALL     2   1   3
0013    JMP      2 => 0019
0014 => UGET     2   0      ; HgFSM
0015    MOV      3   2
0016    TGETS    2   2   2  ; "_process_generic_char"
0017    MOV      4   1
0018    CALL     2   1   3
0019 => RET0     0   1

-- BYTECODE -- ko_KR_helper.lua:261-268
0001    UGET     2   0      ; HgFSM
0002    TGETS    2   2   0  ; "fsm_state"
0003    UGET     3   0      ; HgFSM
0004    TGETS    3   3   1  ; "STATE"
0005    TGETS    3   3   2  ; "IDLE"
0006    ISEQV    2   3
0007    JMP      2 => 0015
0008    UGET     2   0      ; HgFSM
0009    TGETS    2   2   0  ; "fsm_state"
0010    UGET     3   0      ; HgFSM
0011    TGETS    3   3   1  ; "STATE"
0012    TGETS    3   3   3  ; "GOT_INITIAL"
0013    ISNEV    2   3
0014    JMP      2 => 0020
0015 => UGET     2   0      ; HgFSM
0016    MOV      3   2
0017    TGETS    2   2   4  ; "_process_generic_bsp"
0018    CALL     2   1   2
0019    JMP      2 => 0029
0020 => UGET     2   0      ; HgFSM
0021    MOV      3   2
0022    TGETS    2   2   5  ; "_process_hg_bsp_except_initial"
0023    CALL     2   1   2
0024    UGET     2   0      ; HgFSM
0025    MOV      3   2
0026    TGETS    2   2   6  ; "_process_hg_char_update_ui"
0027    KPRI     4   2
0028    CALL     2   1   3
0029 => RET0     0   1

-- BYTECODE -- ko_KR_helper.lua:270-278
0001    UGET     2   0      ; HgSylbls
0002    MOV      3   2
0003    TGETS    2   2   0  ; "in_consonnant_char"
0004    MOV      4   1
0005    CALL     2   2   3
0006    ISF          2
0007    JMP      3 => 0011
0008    KPRI     2   2
0009    RET1     2   2
0010    JMP      2 => 0027
0011 => UGET     2   0      ; HgSylbls
0012    MOV      3   2
0013    TGETS    2   2   1  ; "in_vowel_char"
0014    MOV      4   1
0015    CALL     2   2   3
0016    ISF          2
0017    JMP      3 => 0027
0018    UGET     2   1      ; HgFSM
0019    TGETS    2   2   2  ; "fsm_state"
0020    UGET     3   1      ; HgFSM
0021    TGETS    3   3   3  ; "STATE"
0022    TGETS    3   3   4  ; "IDLE"
0023    ISEQV    2   3
0024    JMP      2 => 0027
0025    KPRI     2   2
0026    RET1     2   2
0027 => KPRI     2   1
0028    RET1     2   2

-- BYTECODE -- ko_KR_helper.lua:280-283
0001    UGET     2   0      ; HgFSM
0002    MOV      3   2
0003    TGETS    2   2   0  ; "clean_state"
0004    CALL     2   1   2
0005    UGET     2   0      ; HgFSM
0006    TGETS    2   2   1  ; "ui_handler"
0007    MOV      3   2
0008    TGETS    2   2   2  ; "put_char"
0009    MOV      4   1
0010    CALL     2   1   3
0011    RET0     0   1

-- BYTECODE -- ko_KR_helper.lua:284-287
0001    UGET     2   0      ; HgFSM
0002    MOV      3   2
0003    TGETS    2   2   0  ; "clean_state"
0004    CALL     2   1   2
0005    UGET     2   0      ; HgFSM
0006    TGETS    2   2   1  ; "ui_handler"
0007    MOV      3   2
0008    TGETS    2   2   2  ; "del_char"
0009    CALL     2   1   2
0010    RET0     0   1

-- BYTECODE -- ko_KR_helper.lua:289-297
0001    UGET     2   0      ; HgFSM
0002    MOV      3   2
0003    TGETS    2   2   0  ; "_process_hg_char_impl"
0004    MOV      4   1
0005    CALL     2   2   3
0006    ISF          2
0007    JMP      3 => 0013
0008    UGET     3   0      ; HgFSM
0009    MOV      4   3
0010    TGETS    3   3   1  ; "_process_hg_char_update_ui"
0011    CALL     3   1   2
0012    JMP      3 => 0018
0013 => UGET     3   0      ; HgFSM
0014    MOV      4   3
0015    TGETS    3   3   2  ; "_process_generic_char"
0016    MOV      5   1
0017    CALL     3   1   3
0018 => RET0     0   1

-- BYTECODE -- ko_KR_helper.lua:299-315
0001    UGET     1   0      ; HgFSM
0002    MOV      2   1
0003    TGETS    1   1   0  ; "_pop_state"
0004    CALL     1   2   2
0005    UGET     2   0      ; HgFSM
0006    TGETS    2   2   1  ; "STATE"
0007    TGETS    2   2   2  ; "GOT_MEDIAL"
0008    ISNEV    1   2
0009    JMP      2 => 0014
0010    UGET     2   0      ; HgFSM
0011    KPRI     3   0
0012    TSETS    3   2   3  ; "medial"
0013    JMP      2 => 0044
0014 => UGET     2   0      ; HgFSM
0015    TGETS    2   2   1  ; "STATE"
0016    TGETS    2   2   4  ; "GOT_DOUBLE_MEDIAL"
0017    ISNEV    1   2
0018    JMP      2 => 0025
0019    UGET     2   0      ; HgFSM
0020    UGET     3   0      ; HgFSM
0021    TGETS    3   3   3  ; "medial"
0022    TGETB    3   3   1
0023    TSETS    3   2   3  ; "medial"
0024    JMP      2 => 0044
0025 => UGET     2   0      ; HgFSM
0026    TGETS    2   2   1  ; "STATE"
0027    TGETS    2   2   5  ; "GOT_FINAL"
0028    ISNEV    1   2
0029    JMP      2 => 0034
0030    UGET     2   0      ; HgFSM
0031    KPRI     3   0
0032    TSETS    3   2   6  ; "final"
0033    JMP      2 => 0044
0034 => UGET     2   0      ; HgFSM
0035    TGETS    2   2   1  ; "STATE"
0036    TGETS    2   2   7  ; "GOT_DOUBLE_FINAL"
0037    ISNEV    1   2
0038    JMP      2 => 0044
0039    UGET     2   0      ; HgFSM
0040    UGET     3   0      ; HgFSM
0041    TGETS    3   3   6  ; "final"
0042    TGETB    3   3   1
0043    TSETS    3   2   6  ; "final"
0044 => RET0     0   1

-- BYTECODE -- ko_KR_helper.lua:317-371
0001    UGET     2   0      ; HgFSM
0002    TGETS    2   2   0  ; "fsm_state"
0003    UGET     3   0      ; HgFSM
0004    TGETS    3   3   1  ; "STATE"
0005    TGETS    3   3   2  ; "IDLE"
0006    ISNEV    2   3
0007    JMP      2 => 0014
0008    UGET     2   0      ; HgFSM
0009    MOV      3   2
0010    TGETS    2   2   3  ; "_process_hg_char_new_hg"
0011    MOV      4   1
0012    CALL     2   1   3
0013    JMP      2 => 0200
0014 => UGET     2   0      ; HgFSM
0015    TGETS    2   2   0  ; "fsm_state"
0016    UGET     3   0      ; HgFSM
0017    TGETS    3   3   1  ; "STATE"
0018    TGETS    3   3   4  ; "GOT_INITIAL"
0019    ISNEV    2   3
0020    JMP      2 => 0040
0021    UGET     2   1      ; HgSylbls
0022    MOV      3   2
0023    TGETS    2   2   5  ; "in_consonnant_char"
0024    MOV      4   1
0025    CALL     2   2   3
0026    ISF          2
0027    JMP      3 => 0034
0028    UGET     2   0      ; HgFSM
0029    MOV      3   2
0030    TGETS    2   2   3  ; "_process_hg_char_new_hg"
0031    MOV      4   1
0032    CALL     2   1   3
0033    JMP      2 => 0200
0034 => UGET     2   0      ; HgFSM
0035    MOV      3   2
0036    TGETS    2   2   6  ; "_process_hg_char_push_medial"
0037    MOV      4   1
0038    CALL     2   1   3
0039    JMP      2 => 0200
0040 => UGET     2   0      ; HgFSM
0041    TGETS    2   2   0  ; "fsm_state"
0042    UGET     3   0      ; HgFSM
0043    TGETS    3   3   1  ; "STATE"
0044    TGETS    3   3   7  ; "GOT_MEDIAL"
0045    ISNEV    2   3
0046    JMP      2 => 0090
0047    UGET     2   1      ; HgSylbls
0048    MOV      3   2
0049    TGETS    2   2   8  ; "in_vowel_char"
0050    MOV      4   1
0051    CALL     2   2   3
0052    ISF          2
0053    JMP      3 => 0084
0054    TNEW     2   3
0055    UGET     3   0      ; HgFSM
0056    TGETS    3   3   9  ; "medial"
0057    TSETB    3   2   1
0058    TSETB    1   2   2
0059    UGET     3   1      ; HgSylbls
0060    MOV      4   3
0061    TGETS    3   3  10  ; "is_medial_comb"
0062    UGET     5   0      ; HgFSM
0063    TGETS    5   5   9  ; "medial"
0064    CALL     3   2   3
0065    ISF          3
0066    JMP      4 => 0081
0067    UGET     3   1      ; HgSylbls
0068    MOV      4   3
0069    TGETS    3   3  11  ; "in_medial"
0070    MOV      5   2
0071    CALL     3   2   3
0072    ISF          3
0073    JMP      4 => 0081
0074    UGET     3   0      ; HgFSM
0075    MOV      4   3
0076    TGETS    3   3   6  ; "_process_hg_char_push_medial"
0077    MOV      5   2
0078    KPRI     6   2
0079    CALL     3   1   4
0080    JMP      3 => 0200
0081 => KPRI     3   1
0082    RET1     3   2
0083    JMP      2 => 0200
0084 => UGET     2   0      ; HgFSM
0085    MOV      3   2
0086    TGETS    2   2  12  ; "_process_hg_char_push_final"
0087    MOV      4   1
0088    CALL     2   1   3
0089    JMP      2 => 0200
0090 => UGET     2   0      ; HgFSM
0091    TGETS    2   2   0  ; "fsm_state"
0092    UGET     3   0      ; HgFSM
0093    TGETS    3   3   1  ; "STATE"
0094    TGETS    3   3  13  ; "GOT_DOUBLE_MEDIAL"
0095    ISNEV    2   3
0096    JMP      2 => 0113
0097    UGET     2   1      ; HgSylbls
0098    MOV      3   2
0099    TGETS    2   2   8  ; "in_vowel_char"
0100    MOV      4   1
0101    CALL     2   2   3
0102    ISF          2
0103    JMP      3 => 0107
0104    KPRI     2   1
0105    RET1     2   2
0106    JMP      2 => 0200
0107 => UGET     2   0      ; HgFSM
0108    MOV      3   2
0109    TGETS    2   2  12  ; "_process_hg_char_push_final"
0110    MOV      4   1
0111    CALL     2   1   3
0112    JMP      2 => 0200
0113 => UGET     2   0      ; HgFSM
0114    TGETS    2   2   0  ; "fsm_state"
0115    UGET     3   0      ; HgFSM
0116    TGETS    3   3   1  ; "STATE"
0117    TGETS    3   3  14  ; "GOT_FINAL"
0118    ISNEV    2   3
0119    JMP      2 => 0169
0120    UGET     2   1      ; HgSylbls
0121    MOV      3   2
0122    TGETS    2   2   8  ; "in_vowel_char"
0123    MOV      4   1
0124    CALL     2   2   3
0125    ISF          2
0126    JMP      3 => 0136
0127    UGET     2   0      ; HgFSM
0128    MOV      3   2
0129    TGETS    2   2  15  ; "_process_hg_char_borrow_initial_push_nex"~
0130    KPRI     4   0
0131    UGET     5   0      ; HgFSM
0132    TGETS    5   5  16  ; "final"
0133    MOV      6   1
0134    CALL     2   1   5
0135    JMP      2 => 0200
0136 => TNEW     2   3
0137    UGET     3   0      ; HgFSM
0138    TGETS    3   3  16  ; "final"
0139    TSETB    3   2   1
0140    TSETB    1   2   2
0141    UGET     3   1      ; HgSylbls
0142    MOV      4   3
0143    TGETS    3   3  17  ; "is_final_comb"
0144    UGET     5   0      ; HgFSM
0145    TGETS    5   5  16  ; "final"
0146    CALL     3   2   3
0147    ISF          3
0148    JMP      4 => 0163
0149    UGET     3   1      ; HgSylbls
0150    MOV      4   3
0151    TGETS    3   3  18  ; "in_final"
0152    MOV      5   2
0153    CALL     3   2   3
0154    ISF          3
0155    JMP      4 => 0163
0156    UGET     3   0      ; HgFSM
0157    MOV      4   3
0158    TGETS    3   3  12  ; "_process_hg_char_push_final"
0159    MOV      5   2
0160    KPRI     6   2
0161    CALL     3   1   4
0162    JMP      3 => 0200
0163 => UGET     3   0      ; HgFSM
0164    MOV      4   3
0165    TGETS    3   3   3  ; "_process_hg_char_new_hg"
0166    MOV      5   1
0167    CALL     3   1   3
0168    JMP      2 => 0200
0169 => UGET     2   0      ; HgFSM
0170    TGETS    2   2   0  ; "fsm_state"
0171    UGET     3   0      ; HgFSM
0172    TGETS    3   3   1  ; "STATE"
0173    TGETS    3   3  19  ; "GOT_DOUBLE_FINAL"
0174    ISNEV    2   3
0175    JMP      2 => 0200
0176    UGET     2   1      ; HgSylbls
0177    MOV      3   2
0178    TGETS    2   2   8  ; "in_vowel_char"
0179    MOV      4   1
0180    CALL     2   2   3
0181    ISF          2
0182    JMP      3 => 0195
0183    UGET     2   0      ; HgFSM
0184    MOV      3   2
0185    TGETS    2   2  15  ; "_process_hg_char_borrow_initial_push_nex"~
0186    UGET     4   0      ; HgFSM
0187    TGETS    4   4  16  ; "final"
0188    TGETB    4   4   1
0189    UGET     5   0      ; HgFSM
0190    TGETS    5   5  16  ; "final"
0191    TGETB    5   5   2
0192    MOV      6   1
0193    CALL     2   1   5
0194    JMP      2 => 0200
0195 => UGET     2   0      ; HgFSM
0196    MOV      3   2
0197    TGETS    2   2   3  ; "_process_hg_char_new_hg"
0198    MOV      4   1
0199    CALL     2   1   3
0200 => KPRI     2   2
0201    RET1     2   2

-- BYTECODE -- ko_KR_helper.lua:373-378
0001    UGET     2   0      ; HgFSM
0002    MOV      3   2
0003    TGETS    2   2   0  ; "clean_state"
0004    CALL     2   1   2
0005    UGET     2   0      ; HgFSM
0006    MOV      3   2
0007    TGETS    2   2   1  ; "_push_state"
0008    UGET     4   0      ; HgFSM
0009    TGETS    4   4   2  ; "STATE"
0010    TGETS    4   4   3  ; "GOT_INITIAL"
0011    CALL     2   1   3
0012    UGET     2   0      ; HgFSM
0013    TSETS    1   2   4  ; "initial"
0014    RET0     0   1

-- BYTECODE -- ko_KR_helper.lua:380-387
0001    ISF          2
0002    JMP      3 => 0011
0003    UGET     3   0      ; HgFSM
0004    MOV      4   3
0005    TGETS    3   3   0  ; "_push_state"
0006    UGET     5   0      ; HgFSM
0007    TGETS    5   5   1  ; "STATE"
0008    TGETS    5   5   2  ; "GOT_DOUBLE_MEDIAL"
0009    CALL     3   1   3
0010    JMP      3 => 0018
0011 => UGET     3   0      ; HgFSM
0012    MOV      4   3
0013    TGETS    3   3   0  ; "_push_state"
0014    UGET     5   0      ; HgFSM
0015    TGETS    5   5   1  ; "STATE"
0016    TGETS    5   5   3  ; "GOT_MEDIAL"
0017    CALL     3   1   3
0018 => UGET     3   0      ; HgFSM
0019    TSETS    1   3   4  ; "medial"
0020    RET0     0   1

-- BYTECODE -- ko_KR_helper.lua:389-396
0001    ISF          2
0002    JMP      3 => 0011
0003    UGET     3   0      ; HgFSM
0004    MOV      4   3
0005    TGETS    3   3   0  ; "_push_state"
0006    UGET     5   0      ; HgFSM
0007    TGETS    5   5   1  ; "STATE"
0008    TGETS    5   5   2  ; "GOT_DOUBLE_FINAL"
0009    CALL     3   1   3
0010    JMP      3 => 0018
0011 => UGET     3   0      ; HgFSM
0012    MOV      4   3
0013    TGETS    3   3   0  ; "_push_state"
0014    UGET     5   0      ; HgFSM
0015    TGETS    5   5   1  ; "STATE"
0016    TGETS    5   5   3  ; "GOT_FINAL"
0017    CALL     3   1   3
0018 => UGET     3   0      ; HgFSM
0019    TSETS    1   3   4  ; "final"
0020    RET0     0   1

-- BYTECODE -- ko_KR_helper.lua:398-409
0001    MOV      4   2
0002    UGET     5   0      ; HgFSM
0003    TSETS    1   5   0  ; "final"
0004    UGET     5   0      ; HgFSM
0005    MOV      6   5
0006    TGETS    5   5   1  ; "_pop_state"
0007    CALL     5   1   2
0008    UGET     5   0      ; HgFSM
0009    MOV      6   5
0010    TGETS    5   5   2  ; "_process_hg_char_update_ui"
0011    CALL     5   1   2
0012    UGET     5   0      ; HgFSM
0013    MOV      6   5
0014    TGETS    5   5   3  ; "_process_hg_char_new_hg"
0015    MOV      7   4
0016    CALL     5   1   3
0017    UGET     5   0      ; HgFSM
0018    MOV      6   5
0019    TGETS    5   5   4  ; "_push_state"
0020    UGET     7   0      ; HgFSM
0021    TGETS    7   7   5  ; "STATE"
0022    TGETS    7   7   6  ; "GOT_MEDIAL"
0023    CALL     5   1   3
0024    UGET     5   0      ; HgFSM
0025    TSETS    3   5   7  ; "medial"
0026    UGET     5   0      ; HgFSM
0027    KPRI     6   2
0028    TSETS    6   5   8  ; "do_not_del_in_medial"
0029    RET0     0   1

-- BYTECODE -- ko_KR_helper.lua:412-435
0001    IST          1
0002    JMP      2 => 0004
0003    KPRI     1   1
0004 => UGET     2   0      ; HgFSM
0005    TGETS    2   2   0  ; "fsm_state"
0006    UGET     3   0      ; HgFSM
0007    TGETS    3   3   1  ; "STATE"
0008    TGETS    3   3   2  ; "GOT_INITIAL"
0009    ISNEV    2   3
0010    JMP      2 => 0026
0011    ISF          1
0012    JMP      2 => 0018
0013    UGET     2   0      ; HgFSM
0014    TGETS    2   2   3  ; "ui_handler"
0015    MOV      3   2
0016    TGETS    2   2   4  ; "del_char"
0017    CALL     2   1   2
0018 => UGET     2   0      ; HgFSM
0019    TGETS    2   2   3  ; "ui_handler"
0020    MOV      3   2
0021    TGETS    2   2   5  ; "put_char"
0022    UGET     4   0      ; HgFSM
0023    TGETS    4   4   6  ; "initial"
0024    CALL     2   1   3
0025    JMP      2 => 0100
0026 => UGET     2   0      ; HgFSM
0027    TGETS    2   2   0  ; "fsm_state"
0028    UGET     3   0      ; HgFSM
0029    TGETS    3   3   1  ; "STATE"
0030    TGETS    3   3   7  ; "GOT_MEDIAL"
0031    ISEQV    2   3
0032    JMP      2 => 0040
0033    UGET     2   0      ; HgFSM
0034    TGETS    2   2   0  ; "fsm_state"
0035    UGET     3   0      ; HgFSM
0036    TGETS    3   3   1  ; "STATE"
0037    TGETS    3   3   8  ; "GOT_DOUBLE_MEDIAL"
0038    ISNEV    2   3
0039    JMP      2 => 0070
0040 => UGET     2   1      ; HgSylbls
0041    MOV      3   2
0042    TGETS    2   2   9  ; "get_combined_char"
0043    UGET     4   0      ; HgFSM
0044    TGETS    4   4   6  ; "initial"
0045    UGET     5   0      ; HgFSM
0046    TGETS    5   5  10  ; "medial"
0047    KPRI     6   0
0048    CALL     2   2   5
0049    UGET     3   0      ; HgFSM
0050    TGETS    3   3  11  ; "do_not_del_in_medial"
0051    ISF          3
0052    JMP      4 => 0063
0053    UGET     3   0      ; HgFSM
0054    KPRI     4   1
0055    TSETS    4   3  11  ; "do_not_del_in_medial"
0056    UGET     3   0      ; HgFSM
0057    TGETS    3   3   3  ; "ui_handler"
0058    MOV      4   3
0059    TGETS    3   3   5  ; "put_char"
0060    MOV      5   2
0061    CALL     3   1   3
0062    JMP      3 => 0100
0063 => UGET     3   0      ; HgFSM
0064    TGETS    3   3   3  ; "ui_handler"
0065    MOV      4   3
0066    TGETS    3   3  12  ; "del_put_char"
0067    MOV      5   2
0068    CALL     3   1   3
0069    JMP      2 => 0100
0070 => UGET     2   0      ; HgFSM
0071    TGETS    2   2   0  ; "fsm_state"
0072    UGET     3   0      ; HgFSM
0073    TGETS    3   3   1  ; "STATE"
0074    TGETS    3   3  13  ; "GOT_FINAL"
0075    ISEQV    2   3
0076    JMP      2 => 0084
0077    UGET     2   0      ; HgFSM
0078    TGETS    2   2   0  ; "fsm_state"
0079    UGET     3   0      ; HgFSM
0080    TGETS    3   3   1  ; "STATE"
0081    TGETS    3   3  14  ; "GOT_DOUBLE_FINAL"
0082    ISNEV    2   3
0083    JMP      2 => 0100
0084 => UGET     2   1      ; HgSylbls
0085    MOV      3   2
0086    TGETS    2   2   9  ; "get_combined_char"
0087    UGET     4   0      ; HgFSM
0088    TGETS    4   4   6  ; "initial"
0089    UGET     5   0      ; HgFSM
0090    TGETS    5   5  10  ; "medial"
0091    UGET     6   0      ; HgFSM
0092    TGETS    6   6  15  ; "final"
0093    CALL     2   2   5
0094    UGET     3   0      ; HgFSM
0095    TGETS    3   3   3  ; "ui_handler"
0096    MOV      4   3
0097    TGETS    3   3  12  ; "del_put_char"
0098    MOV      5   2
0099    CALL     3   1   3
0100 => RET0     0   1

-- BYTECODE -- ko_KR_helper.lua:0-442
0001    GGET     0   0      ; "require"
0002    KSTR     1   1      ; "ffi/util"
0003    CALL     0   2   2
0004    GGET     1   0      ; "require"
0005    KSTR     2   2      ; "util"
0006    CALL     1   2   2
0007    GGET     2   0      ; "require"
0008    KSTR     3   3      ; "logger"
0009    CALL     2   2   2
0010    TDUP     3   4
0011    TDUP     4   5
0012    TSETS    4   3   6  ; "CHARS_INITIAL"
0013    TDUP     4   7
0014    TSETS    4   3   8  ; "CHARS_MEDIAL"
0015    TDUP     4   9
0016    TSETS    4   3  10  ; "CHARS_MEDIAL_COMBINABLE"
0017    TDUP     4  11
0018    TSETS    4   3  12  ; "CHARS_FINAL"
0019    TDUP     4  13
0020    TSETS    4   3  14  ; "CHARS_FINAL_COMBINABLE"
0021    FNEW     4  16      ; ko_KR_helper.lua:67
0022    TSETS    4   3  15  ; "create_inverse_tbl"
0023    FNEW     4  18      ; ko_KR_helper.lua:75
0024    TSETS    4   3  17  ; "_create_inverse_tbl_impl"
0025    FNEW     4  20      ; ko_KR_helper.lua:85
0026    TSETS    4   3  19  ; "get_combined_char"
0027    FNEW     4  22      ; ko_KR_helper.lua:89
0028    TSETS    4   3  21  ; "_get_combined_charcode"
0029    FNEW     4  24      ; ko_KR_helper.lua:105
0030    TSETS    4   3  23  ; "_initial_idx"
0031    FNEW     4  26      ; ko_KR_helper.lua:109
0032    TSETS    4   3  25  ; "_medial_idx"
0033    FNEW     4  28      ; ko_KR_helper.lua:113
0034    TSETS    4   3  27  ; "_final_idx"
0035    FNEW     4  30      ; ko_KR_helper.lua:119
0036    TSETS    4   3  29  ; "in_intial"
0037    FNEW     4  32      ; ko_KR_helper.lua:123
0038    TSETS    4   3  31  ; "in_medial"
0039    FNEW     4  34      ; ko_KR_helper.lua:127
0040    TSETS    4   3  33  ; "in_final"
0041    FNEW     4  36      ; ko_KR_helper.lua:131
0042    TSETS    4   3  35  ; "is_medial_comb"
0043    FNEW     4  38      ; ko_KR_helper.lua:134
0044    TSETS    4   3  37  ; "is_final_comb"
0045    FNEW     4  40      ; ko_KR_helper.lua:138
0046    TSETS    4   3  39  ; "in_consonnant_char"
0047    FNEW     4  42      ; ko_KR_helper.lua:143
0048    TSETS    4   3  41  ; "in_vowel_char"
0049    FNEW     4  44      ; ko_KR_helper.lua:148
0050    TSETS    4   3  43  ; "_in_target_char_group"
0051    FNEW     4  46      ; ko_KR_helper.lua:165
0052    TSETS    4   3  45  ; "_2elem_tbl_to_str"
0053    MOV      5   3
0054    TGETS    4   3  15  ; "create_inverse_tbl"
0055    CALL     4   1   2
0056    TNEW     4   0
0057    FNEW     5  48      ; ko_KR_helper.lua:186
0058    TSETS    5   4  47  ; "put_char"
0059    FNEW     5  50      ; ko_KR_helper.lua:189
0060    TSETS    5   4  49  ; "del_char"
0061    FNEW     5  52      ; ko_KR_helper.lua:192
0062    TSETS    5   4  51  ; "del_put_char"
0063    TDUP     5  54
0064    TDUP     6  53
0065    TSETS    6   5  55  ; "STATE"
0066    TNEW     6   0
0067    TSETS    6   5  56  ; "fsm_prev_states"
0068    FNEW     6  58      ; ko_KR_helper.lua:223
0069    TSETS    6   5  57  ; "init"
0070    FNEW     6  60      ; ko_KR_helper.lua:229
0071    TSETS    6   5  59  ; "clean_state"
0072    FNEW     6  62      ; ko_KR_helper.lua:240
0073    TSETS    6   5  61  ; "_push_state"
0074    FNEW     6  64      ; ko_KR_helper.lua:244
0075    TSETS    6   5  63  ; "_pop_state"
0076    FNEW     6  66      ; ko_KR_helper.lua:253
0077    TSETS    6   5  65  ; "process_char"
0078    FNEW     6  68      ; ko_KR_helper.lua:261
0079    TSETS    6   5  67  ; "process_bsp"
0080    FNEW     6  70      ; ko_KR_helper.lua:270
0081    TSETS    6   5  69  ; "_should_handle_as_target_char"
0082    FNEW     6  72      ; ko_KR_helper.lua:280
0083    TSETS    6   5  71  ; "_process_generic_char"
0084    FNEW     6  74      ; ko_KR_helper.lua:284
0085    TSETS    6   5  73  ; "_process_generic_bsp"
0086    FNEW     6  76      ; ko_KR_helper.lua:289
0087    TSETS    6   5  75  ; "_process_hg_char"
0088    FNEW     6  78      ; ko_KR_helper.lua:299
0089    TSETS    6   5  77  ; "_process_hg_bsp_except_initial"
0090    FNEW     6  80      ; ko_KR_helper.lua:317
0091    TSETS    6   5  79  ; "_process_hg_char_impl"
0092    FNEW     6  82      ; ko_KR_helper.lua:373
0093    TSETS    6   5  81  ; "_process_hg_char_new_hg"
0094    FNEW     6  84      ; ko_KR_helper.lua:380
0095    TSETS    6   5  83  ; "_process_hg_char_push_medial"
0096    FNEW     6  86      ; ko_KR_helper.lua:389
0097    TSETS    6   5  85  ; "_process_hg_char_push_final"
0098    FNEW     6  88      ; ko_KR_helper.lua:398
0099    TSETS    6   5  87  ; "_process_hg_char_borrow_initial_push_nex"~
0100    FNEW     6  90      ; ko_KR_helper.lua:412
0101    TSETS    6   5  89  ; "_process_hg_char_update_ui"
0102    TDUP     6  91
0103    TSETS    4   6  92  ; "UIHandler"
0104    TSETS    5   6  93  ; "HgFSM"
0105    UCLO     0 => 0106
0106 => RET1     6   2

