
main <./frontend/ui/data/keyboardlayouts/ko_KR_keyboard.lua:0,0> (260 instructions, 1040 bytes at 0x7fec6c406900)
0+ params, 25 slots, 0 upvalues, 8 locals, 126 constants, 3 functions
	1	[1]	GETGLOBAL	0 -1	; require
	2	[1]	LOADK    	1 -2	; "logger"
	3	[1]	CALL     	0 2 2
	4	[7]	GETGLOBAL	1 -1	; require
	5	[7]	LOADK    	2 -3	; "ui/data/keyboardlayouts/ko_KR_helper"
	6	[7]	CALL     	1 2 2
	7	[12]	GETTABLE 	2 1 -4	; "UIHandler"
	8	[14]	CLOSURE  	3 0	; 0x7fec6c406dd0
	9	[14]	MOVE     	0 1
	10	[12]	SETTABLE 	2 -5 3	; "put_char" -
	11	[15]	GETTABLE 	2 1 -4	; "UIHandler"
	12	[17]	CLOSURE  	3 1	; 0x7fec6c406c10
	13	[17]	MOVE     	0 1
	14	[15]	SETTABLE 	2 -6 3	; "del_char" -
	15	[18]	GETTABLE 	2 1 -7	; "HgFSM"
	16	[18]	SELF     	2 2 -8	; "init"
	17	[18]	GETTABLE 	4 1 -4	; "UIHandler"
	18	[18]	CALL     	2 3 1
	19	[103]	CLOSURE  	2 2	; 0x7fec6c4076f0
	20	[103]	MOVE     	0 1
	21	[103]	MOVE     	0 0
	22	[106]	GETGLOBAL	3 -1	; require
	23	[106]	LOADK    	4 -9	; "ui/data/keyboardlayouts/keypopup/en_popup"
	24	[106]	CALL     	3 2 2
	25	[107]	GETTABLE 	4 3 -10	; "com"
	26	[108]	GETTABLE 	5 3 -11	; "prd"
	27	[109]	GETTABLE 	6 3 -12	; "_at"
	28	[110]	GETTABLE 	7 3 -13	; "_eq"
	29	[112]	NEWTABLE 	8 0 8
	30	[113]	SETTABLE 	8 -14 -15	; "min_layer" 1
	31	[114]	SETTABLE 	8 -16 -17	; "max_layer" 4
	32	[115]	NEWTABLE 	9 0 1
	33	[115]	SETTABLE 	9 -19 -20	; "\238\180\181" true
	34	[115]	SETTABLE 	8 -18 9	; "shiftmode_keys" -
	35	[116]	NEWTABLE 	9 0 2
	36	[116]	SETTABLE 	9 -22 -20	; "Sym" true
	37	[116]	SETTABLE 	9 -23 -20	; "ABC" true
	38	[116]	SETTABLE 	8 -21 9	; "symbolmode_keys" -
	39	[117]	NEWTABLE 	9 0 1
	40	[117]	SETTABLE 	9 -25 -20	; "\240\159\140\144" true
	41	[117]	SETTABLE 	8 -24 9	; "utf8mode_keys" -
	42	[118]	NEWTABLE 	9 0 1
	43	[118]	SETTABLE 	9 -27 -28	; "\195\132\195\169\195\159" false
	44	[118]	SETTABLE 	8 -26 9	; "umlautmode_keys" -
	45	[119]	NEWTABLE 	9 4 0
	46	[119]	NEWTABLE 	10 10 0
	47	[122]	NEWTABLE 	11 4 0
	48	[123]	LOADK    	12 -30	; "\227\133\131"
	49	[123]	LOADK    	13 -31	; "\227\133\130"
	50	[123]	LOADK    	14 -32	; "\239\191\166"
	51	[123]	LOADK    	15 -33	; "0"
	52	[123]	SETLIST  	11 4 1	; 1
	53	[123]	NEWTABLE 	12 4 0
	54	[124]	LOADK    	13 -34	; "\227\133\137"
	55	[124]	LOADK    	14 -35	; "\227\133\136"
	56	[124]	LOADK    	15 -36	; "!"
	57	[124]	LOADK    	16 -37	; "1"
	58	[124]	SETLIST  	12 4 1	; 1
	59	[124]	NEWTABLE 	13 4 0
	60	[125]	LOADK    	14 -38	; "\227\132\184"
	61	[125]	LOADK    	15 -39	; "\227\132\183"
	62	[125]	MOVE     	16 6
	63	[125]	LOADK    	17 -40	; "2"
	64	[125]	SETLIST  	13 4 1	; 1
	65	[125]	NEWTABLE 	14 4 0
	66	[126]	LOADK    	15 -41	; "\227\132\178"
	67	[126]	LOADK    	16 -42	; "\227\132\177"
	68	[126]	LOADK    	17 -43	; "#"
	69	[126]	LOADK    	18 -44	; "3"
	70	[126]	SETLIST  	14 4 1	; 1
	71	[126]	NEWTABLE 	15 4 0
	72	[127]	LOADK    	16 -45	; "\227\133\134"
	73	[127]	LOADK    	17 -46	; "\227\133\133"
	74	[127]	LOADK    	18 -47	; "+"
	75	[127]	MOVE     	19 7
	76	[127]	SETLIST  	15 4 1	; 1
	77	[127]	NEWTABLE 	16 4 0
	78	[128]	LOADK    	17 -48	; "\227\133\155"
	79	[128]	LOADK    	18 -48	; "\227\133\155"
	80	[128]	LOADK    	19 -49	; "\226\152\134"
	81	[128]	LOADK    	20 -50	; "("
	82	[128]	SETLIST  	16 4 1	; 1
	83	[128]	NEWTABLE 	17 4 0
	84	[129]	LOADK    	18 -51	; "\227\133\149"
	85	[129]	LOADK    	19 -51	; "\227\133\149"
	86	[129]	LOADK    	20 -52	; "\226\152\133"
	87	[129]	LOADK    	21 -53	; ")"
	88	[129]	SETLIST  	17 4 1	; 1
	89	[129]	NEWTABLE 	18 4 0
	90	[130]	LOADK    	19 -54	; "\227\133\145"
	91	[130]	LOADK    	20 -54	; "\227\133\145"
	92	[130]	LOADK    	21 -55	; "\226\153\161"
	93	[130]	LOADK    	22 -56	; "\\"
	94	[130]	SETLIST  	18 4 1	; 1
	95	[130]	NEWTABLE 	19 4 0
	96	[131]	LOADK    	20 -57	; "\227\133\146"
	97	[131]	LOADK    	21 -58	; "\227\133\144"
	98	[131]	LOADK    	22 -59	; "\226\153\165"
	99	[131]	LOADK    	23 -60	; "/"
	100	[131]	SETLIST  	19 4 1	; 1
	101	[131]	NEWTABLE 	20 4 0
	102	[132]	LOADK    	21 -61	; "\227\133\150"
	103	[132]	LOADK    	22 -62	; "\227\133\148"
	104	[132]	LOADK    	23 -63	; "\226\128\187"
	105	[132]	LOADK    	24 -64	; "`"
	106	[132]	SETLIST  	20 4 1	; 1
	107	[133]	SETLIST  	10 10 1	; 1
	108	[133]	NEWTABLE 	11 9 0
	109	[135]	NEWTABLE 	12 4 0
	110	[136]	LOADK    	13 -65	; "\227\133\129"
	111	[136]	LOADK    	14 -65	; "\227\133\129"
	112	[136]	LOADK    	15 -66	; "\226\128\166"
	113	[136]	LOADK    	16 -67	; "@"
	114	[136]	SETLIST  	12 4 1	; 1
	115	[136]	NEWTABLE 	13 4 0
	116	[137]	LOADK    	14 -68	; "\227\132\180"
	117	[137]	LOADK    	15 -68	; "\227\132\180"
	118	[137]	LOADK    	16 -69	; "$"
	119	[137]	LOADK    	17 -70	; "4"
	120	[137]	SETLIST  	13 4 1	; 1
	121	[137]	NEWTABLE 	14 4 0
	122	[138]	LOADK    	15 -71	; "\227\133\135"
	123	[138]	LOADK    	16 -71	; "\227\133\135"
	124	[138]	LOADK    	17 -72	; "%"
	125	[138]	LOADK    	18 -73	; "5"
	126	[138]	SETLIST  	14 4 1	; 1
	127	[138]	NEWTABLE 	15 4 0
	128	[139]	LOADK    	16 -74	; "\227\132\185"
	129	[139]	LOADK    	17 -74	; "\227\132\185"
	130	[139]	LOADK    	18 -75	; "^"
	131	[139]	LOADK    	19 -76	; "6"
	132	[139]	SETLIST  	15 4 1	; 1
	133	[139]	NEWTABLE 	16 4 0
	134	[140]	LOADK    	17 -77	; "\227\133\142"
	135	[140]	LOADK    	18 -77	; "\227\133\142"
	136	[140]	LOADK    	19 -78	; ":"
	137	[140]	LOADK    	20 -79	; "'"
	138	[140]	SETLIST  	16 4 1	; 1
	139	[140]	NEWTABLE 	17 4 0
	140	[141]	LOADK    	18 -80	; "\227\133\151"
	141	[141]	LOADK    	19 -80	; "\227\133\151"
	142	[141]	LOADK    	20 -81	; "\226\153\169"
	143	[141]	LOADK    	21 -82	; "\""
	144	[141]	SETLIST  	17 4 1	; 1
	145	[141]	NEWTABLE 	18 4 0
	146	[142]	LOADK    	19 -83	; "\227\133\147"
	147	[142]	LOADK    	20 -83	; "\227\133\147"
	148	[142]	LOADK    	21 -84	; "\226\153\170"
	149	[142]	LOADK    	22 -85	; "["
	150	[142]	SETLIST  	18 4 1	; 1
	151	[142]	NEWTABLE 	19 4 0
	152	[143]	LOADK    	20 -86	; "\227\133\143"
	153	[143]	LOADK    	21 -86	; "\227\133\143"
	154	[143]	LOADK    	22 -87	; "\226\153\172"
	155	[143]	LOADK    	23 -88	; "]"
	156	[143]	SETLIST  	19 4 1	; 1
	157	[143]	NEWTABLE 	20 4 0
	158	[144]	LOADK    	21 -89	; "\227\133\163"
	159	[144]	LOADK    	22 -89	; "\227\133\163"
	160	[144]	LOADK    	23 -90	; "\226\132\162"
	161	[144]	LOADK    	24 -91	; "-"
	162	[144]	SETLIST  	20 4 1	; 1
	163	[145]	SETLIST  	11 9 1	; 1
	164	[145]	NEWTABLE 	12 9 0
	165	[147]	NEWTABLE 	13 0 2
	166	[148]	SETTABLE 	13 -92 -19	; "label" "\238\180\181"
	167	[149]	SETTABLE 	13 -93 -94	; "width" 1.5
	168	[150]	NEWTABLE 	14 4 0
	169	[151]	LOADK    	15 -95	; "\227\133\139"
	170	[151]	LOADK    	16 -95	; "\227\133\139"
	171	[151]	LOADK    	17 -96	; "\227\128\140"
	172	[151]	LOADK    	18 -97	; "7"
	173	[151]	SETLIST  	14 4 1	; 1
	174	[151]	NEWTABLE 	15 4 0
	175	[152]	LOADK    	16 -98	; "\227\133\140"
	176	[152]	LOADK    	17 -98	; "\227\133\140"
	177	[152]	LOADK    	18 -99	; "\227\128\141"
	178	[152]	LOADK    	19 -100	; "8"
	179	[152]	SETLIST  	15 4 1	; 1
	180	[152]	NEWTABLE 	16 4 0
	181	[153]	LOADK    	17 -101	; "\227\133\138"
	182	[153]	LOADK    	18 -101	; "\227\133\138"
	183	[153]	LOADK    	19 -102	; "*"
	184	[153]	LOADK    	20 -103	; "9"
	185	[153]	SETLIST  	16 4 1	; 1
	186	[153]	NEWTABLE 	17 4 0
	187	[154]	LOADK    	18 -104	; "\227\133\141"
	188	[154]	LOADK    	19 -104	; "\227\133\141"
	189	[154]	LOADK    	20 -105	; "\226\157\164"
	190	[154]	MOVE     	21 4
	191	[154]	SETLIST  	17 4 1	; 1
	192	[154]	NEWTABLE 	18 4 0
	193	[155]	LOADK    	19 -106	; "\227\133\160"
	194	[155]	LOADK    	20 -106	; "\227\133\160"
	195	[155]	LOADK    	21 -107	; "&"
	196	[155]	MOVE     	22 5
	197	[155]	SETLIST  	18 4 1	; 1
	198	[155]	NEWTABLE 	19 4 0
	199	[156]	LOADK    	20 -108	; "\227\133\156"
	200	[156]	LOADK    	21 -108	; "\227\133\156"
	201	[156]	LOADK    	22 -109	; "\227\128\142"
	202	[156]	LOADK    	23 -110	; "\226\134\145"
	203	[156]	SETLIST  	19 4 1	; 1
	204	[156]	NEWTABLE 	20 4 0
	205	[157]	LOADK    	21 -111	; "\227\133\161"
	206	[157]	LOADK    	22 -111	; "\227\133\161"
	207	[157]	LOADK    	23 -112	; "\227\128\143"
	208	[157]	LOADK    	24 -113	; "\226\134\147"
	209	[157]	SETLIST  	20 4 1	; 1
	210	[157]	NEWTABLE 	21 0 3
	211	[158]	SETTABLE 	21 -92 -114	; "label" "\238\157\173"
	212	[159]	SETTABLE 	21 -93 -94	; "width" 1.5
	213	[160]	SETTABLE 	21 -115 -28	; "bold" false
	214	[162]	SETLIST  	12 9 1	; 1
	215	[162]	NEWTABLE 	13 6 0
	216	[164]	NEWTABLE 	14 4 1
	217	[165]	LOADK    	15 -22	; "Sym"
	218	[165]	LOADK    	16 -22	; "Sym"
	219	[165]	LOADK    	17 -23	; "ABC"
	220	[165]	LOADK    	18 -23	; "ABC"
	221	[166]	SETTABLE 	14 -93 -94	; "width" 1.5
	222	[166]	SETLIST  	14 4 1	; 1
	223	[166]	NEWTABLE 	15 0 2
	224	[167]	SETTABLE 	15 -92 -25	; "label" "\240\159\140\144"
	225	[168]	SETTABLE 	15 -93 -116	; "width" 2
	226	[169]	NEWTABLE 	16 4 2
	227	[171]	SETTABLE 	16 -92 -117	; "label" "\234\176\132\234\178\169"
	228	[172]	LOADK    	17 -118	; " "
	229	[172]	LOADK    	18 -118	; " "
	230	[172]	LOADK    	19 -118	; " "
	231	[172]	LOADK    	20 -118	; " "
	232	[173]	SETTABLE 	16 -93 -119	; "width" 3
	233	[173]	SETLIST  	16 4 1	; 1
	234	[173]	NEWTABLE 	17 4 0
	235	[174]	MOVE     	18 4
	236	[174]	MOVE     	19 4
	237	[174]	LOADK    	20 -120	; "\226\128\156"
	238	[174]	LOADK    	21 -121	; "\226\134\144"
	239	[174]	SETLIST  	17 4 1	; 1
	240	[174]	NEWTABLE 	18 4 0
	241	[175]	MOVE     	19 5
	242	[175]	MOVE     	20 5
	243	[175]	LOADK    	21 -122	; "\226\128\157"
	244	[175]	LOADK    	22 -123	; "\226\134\146"
	245	[175]	SETLIST  	18 4 1	; 1
	246	[175]	NEWTABLE 	19 4 3
	247	[176]	SETTABLE 	19 -92 -124	; "label" "\226\174\160"
	248	[177]	LOADK    	20 -125	; "\n"
	249	[177]	LOADK    	21 -125	; "\n"
	250	[177]	LOADK    	22 -125	; "\n"
	251	[177]	LOADK    	23 -125	; "\n"
	252	[178]	SETTABLE 	19 -93 -94	; "width" 1.5
	253	[179]	SETTABLE 	19 -115 -20	; "bold" true
	254	[180]	SETLIST  	19 4 1	; 1
	255	[181]	SETLIST  	13 6 1	; 1
	256	[182]	SETLIST  	9 4 1	; 1
	257	[182]	SETTABLE 	8 -29 9	; "keys" -
	258	[185]	SETTABLE 	8 -126 2	; "wrapInputBox" -
	259	[186]	RETURN   	8 2
	260	[186]	RETURN   	0 1

function <./frontend/ui/data/keyboardlayouts/ko_KR_keyboard.lua:12,14> (7 instructions, 28 bytes at 0x7fec6c406dd0)
2 params, 5 slots, 1 upvalue, 2 locals, 3 constants, 0 functions
	1	[13]	GETUPVAL 	2 0	; HgHelper
	2	[13]	GETTABLE 	2 2 -1	; "UIHandler"
	3	[13]	GETTABLE 	2 2 -2	; "inputbox"
	4	[13]	SELF     	2 2 -3	; "_addChars"
	5	[13]	MOVE     	4 1
	6	[13]	CALL     	2 3 1
	7	[14]	RETURN   	0 1

function <./frontend/ui/data/keyboardlayouts/ko_KR_keyboard.lua:15,17> (6 instructions, 24 bytes at 0x7fec6c406c10)
2 params, 4 slots, 1 upvalue, 2 locals, 3 constants, 0 functions
	1	[16]	GETUPVAL 	2 0	; HgHelper
	2	[16]	GETTABLE 	2 2 -1	; "UIHandler"
	3	[16]	GETTABLE 	2 2 -2	; "inputbox"
	4	[16]	SELF     	2 2 -3	; "_delChar"
	5	[16]	CALL     	2 2 1
	6	[17]	RETURN   	0 1

function <./frontend/ui/data/keyboardlayouts/ko_KR_keyboard.lua:23,103> (81 instructions, 324 bytes at 0x7fec6c4076f0)
1 param, 9 slots, 2 upvalues, 6 locals, 17 constants, 7 functions
	1	[24]	GETUPVAL 	1 0	; HgHelper
	2	[24]	GETTABLE 	1 1 -1	; "HgFSM"
	3	[24]	GETTABLE 	1 1 -2	; "clean_state"
	4	[24]	CALL     	1 1 1
	5	[26]	GETTABLE 	1 0 -3	; "_wrapped"
	6	[26]	EQ       	0 1 -4	; - nil
	7	[26]	JMP      	73	; to 81
	8	[27]	SETTABLE 	0 -3 -5	; "_wrapped" true
	9	[30]	NEWTABLE 	1 0 0
	10	[39]	CLOSURE  	2 0	; 0x7fec6c407990
	11	[39]	MOVE     	0 1
	12	[44]	CLOSURE  	3 1	; 0x7fec6c407e30
	13	[44]	MOVE     	0 1
	14	[47]	MOVE     	4 3
	15	[47]	MOVE     	5 0
	16	[47]	LOADK    	6 -6	; "addChars"
	17	[47]	CALL     	4 3 1
	18	[48]	MOVE     	4 3
	19	[48]	MOVE     	5 0
	20	[48]	LOADK    	6 -7	; "delChar"
	21	[48]	CALL     	4 3 1
	22	[54]	CLOSURE  	4 2	; 0x7fec6c407b10
	23	[54]	GETUPVAL 	0 1	; logger
	24	[54]	GETUPVAL 	0 0	; HgHelper
	25	[50]	SETTABLE 	0 -6 4	; "addChars" -
	26	[59]	CLOSURE  	4 3	; 0x7fec6c408270
	27	[59]	GETUPVAL 	0 1	; logger
	28	[59]	GETUPVAL 	0 0	; HgHelper
	29	[55]	SETTABLE 	0 -7 4	; "delChar" -
	30	[69]	CLOSURE  	4 4	; 0x7fec6c408b20
	31	[69]	MOVE     	0 3
	32	[69]	GETUPVAL 	0 0	; HgHelper
	33	[72]	MOVE     	5 4
	34	[72]	MOVE     	6 0
	35	[72]	LOADK    	7 -8	; "delToStartOfLine"
	36	[72]	CALL     	5 3 1
	37	[73]	MOVE     	5 4
	38	[73]	MOVE     	6 0
	39	[73]	LOADK    	7 -9	; "clear"
	40	[73]	CALL     	5 3 1
	41	[76]	MOVE     	5 4
	42	[76]	MOVE     	6 0
	43	[76]	LOADK    	7 -10	; "leftChar"
	44	[76]	CALL     	5 3 1
	45	[77]	MOVE     	5 4
	46	[77]	MOVE     	6 0
	47	[77]	LOADK    	7 -11	; "rightChar"
	48	[77]	CALL     	5 3 1
	49	[78]	MOVE     	5 4
	50	[78]	MOVE     	6 0
	51	[78]	LOADK    	7 -12	; "upLine"
	52	[78]	CALL     	5 3 1
	53	[79]	MOVE     	5 4
	54	[79]	MOVE     	6 0
	55	[79]	LOADK    	7 -13	; "downLine"
	56	[79]	CALL     	5 3 1
	57	[82]	MOVE     	5 4
	58	[82]	MOVE     	6 0
	59	[82]	LOADK    	7 -14	; "unfocus"
	60	[82]	CALL     	5 3 1
	61	[92]	CLOSURE  	5 5	; 0x7fec6c4078a0
	62	[92]	MOVE     	0 3
	63	[92]	GETUPVAL 	0 0	; HgHelper
	64	[94]	MOVE     	6 5
	65	[94]	MOVE     	7 0
	66	[94]	LOADK    	8 -15	; "onTapTextBox"
	67	[94]	CALL     	6 3 1
	68	[95]	MOVE     	6 5
	69	[95]	MOVE     	7 0
	70	[95]	LOADK    	8 -16	; "onHoldTextBox"
	71	[95]	CALL     	6 3 1
	72	[96]	MOVE     	6 5
	73	[96]	MOVE     	7 0
	74	[96]	LOADK    	8 -17	; "onSwipeTextBox"
	75	[96]	CALL     	6 3 1
	76	[101]	CLOSURE  	6 6	; 0x7fec6c409450
	77	[101]	MOVE     	0 2
	78	[101]	MOVE     	0 0
	79	[101]	RETURN   	6 2
	80	[101]	CLOSE    	1
	81	[103]	RETURN   	0 1

function <./frontend/ui/data/keyboardlayouts/ko_KR_keyboard.lua:31,39> (16 instructions, 64 bytes at 0x7fec6c407990)
1 param, 8 slots, 1 upvalue, 7 locals, 3 constants, 0 functions
	1	[32]	GETGLOBAL	1 -1	; ipairs
	2	[32]	GETUPVAL 	2 0	; copied_names
	3	[32]	CALL     	1 2 4
	4	[32]	JMP      	9	; to 14
	5	[33]	LOADK    	6 -2	; "_"
	6	[33]	MOVE     	7 5
	7	[33]	CONCAT   	6 6 7
	8	[34]	GETTABLE 	7 0 6
	9	[34]	TEST     	7 0 0
	10	[34]	JMP      	3	; to 14
	11	[35]	GETTABLE 	7 0 6
	12	[35]	SETTABLE 	0 5 7
	13	[36]	SETTABLE 	0 6 -3	; - nil
	14	[32]	TFORLOOP 	1 2
	15	[37]	JMP      	-11	; to 5
	16	[39]	RETURN   	0 1

function <./frontend/ui/data/keyboardlayouts/ko_KR_keyboard.lua:41,44> (11 instructions, 44 bytes at 0x7fec6c407e30)
2 params, 5 slots, 1 upvalue, 2 locals, 3 constants, 0 functions
	1	[42]	LOADK    	2 -1	; "_"
	2	[42]	MOVE     	3 1
	3	[42]	CONCAT   	2 2 3
	4	[42]	GETTABLE 	3 0 1
	5	[42]	SETTABLE 	0 2 3
	6	[43]	GETGLOBAL	2 -2	; table
	7	[43]	GETTABLE 	2 2 -3	; "insert"
	8	[43]	GETUPVAL 	3 0	; copied_names
	9	[43]	MOVE     	4 1
	10	[43]	CALL     	2 3 1
	11	[44]	RETURN   	0 1

function <./frontend/ui/data/keyboardlayouts/ko_KR_keyboard.lua:50,54> (15 instructions, 60 bytes at 0x7fec6c407b10)
2 params, 6 slots, 2 upvalues, 2 locals, 7 constants, 0 functions
	1	[51]	GETUPVAL 	2 0	; logger
	2	[51]	GETTABLE 	2 2 -1	; "dbg"
	3	[51]	LOADK    	3 -2	; "ko_KR_kbd:addChar("
	4	[51]	MOVE     	4 1
	5	[51]	LOADK    	5 -3	; ")"
	6	[51]	CALL     	2 4 1
	7	[52]	GETUPVAL 	2 1	; HgHelper
	8	[52]	GETTABLE 	2 2 -4	; "UIHandler"
	9	[52]	SETTABLE 	2 -5 0	; "inputbox" -
	10	[53]	GETUPVAL 	2 1	; HgHelper
	11	[53]	GETTABLE 	2 2 -6	; "HgFSM"
	12	[53]	SELF     	2 2 -7	; "process_char"
	13	[53]	MOVE     	4 1
	14	[53]	CALL     	2 3 1
	15	[54]	RETURN   	0 1

function <./frontend/ui/data/keyboardlayouts/ko_KR_keyboard.lua:55,59> (12 instructions, 48 bytes at 0x7fec6c408270)
1 param, 3 slots, 2 upvalues, 1 local, 6 constants, 0 functions
	1	[56]	GETUPVAL 	1 0	; logger
	2	[56]	GETTABLE 	1 1 -1	; "dbg"
	3	[56]	LOADK    	2 -2	; "ko_KR_kbd:delChar()"
	4	[56]	CALL     	1 2 1
	5	[57]	GETUPVAL 	1 1	; HgHelper
	6	[57]	GETTABLE 	1 1 -3	; "UIHandler"
	7	[57]	SETTABLE 	1 -4 0	; "inputbox" -
	8	[58]	GETUPVAL 	1 1	; HgHelper
	9	[58]	GETTABLE 	1 1 -5	; "HgFSM"
	10	[58]	SELF     	1 1 -6	; "process_bsp"
	11	[58]	CALL     	1 2 1
	12	[59]	RETURN   	0 1

function <./frontend/ui/data/keyboardlayouts/ko_KR_keyboard.lua:63,69> (9 instructions, 36 bytes at 0x7fec6c408b20)
2 params, 5 slots, 2 upvalues, 2 locals, 0 constants, 1 function
	1	[64]	GETUPVAL 	2 0	; copy_func_reference
	2	[64]	MOVE     	3 0
	3	[64]	MOVE     	4 1
	4	[64]	CALL     	2 3 1
	5	[68]	CLOSURE  	2 0	; 0x7fec6c408c40
	6	[68]	GETUPVAL 	0 1	; HgHelper
	7	[68]	MOVE     	0 1
	8	[68]	SETTABLE 	0 1 2
	9	[69]	RETURN   	0 1

function <./frontend/ui/data/keyboardlayouts/ko_KR_keyboard.lua:65,68> (11 instructions, 44 bytes at 0x7fec6c408c40)
1 param, 3 slots, 2 upvalues, 1 local, 3 constants, 0 functions
	1	[66]	GETUPVAL 	1 0	; HgHelper
	2	[66]	GETTABLE 	1 1 -1	; "HgFSM"
	3	[66]	GETTABLE 	1 1 -2	; "clean_state"
	4	[66]	CALL     	1 1 1
	5	[67]	LOADK    	1 -3	; "_"
	6	[67]	GETUPVAL 	2 1	; name
	7	[67]	CONCAT   	1 1 2
	8	[67]	GETTABLE 	1 0 1
	9	[67]	MOVE     	2 0
	10	[67]	CALL     	1 2 1
	11	[68]	RETURN   	0 1

function <./frontend/ui/data/keyboardlayouts/ko_KR_keyboard.lua:86,92> (9 instructions, 36 bytes at 0x7fec6c4078a0)
2 params, 5 slots, 2 upvalues, 2 locals, 0 constants, 1 function
	1	[87]	GETUPVAL 	2 0	; copy_func_reference
	2	[87]	MOVE     	3 0
	3	[87]	MOVE     	4 1
	4	[87]	CALL     	2 3 1
	5	[91]	CLOSURE  	2 0	; 0x7fec6c409560
	6	[91]	GETUPVAL 	0 1	; HgHelper
	7	[91]	MOVE     	0 1
	8	[91]	SETTABLE 	0 1 2
	9	[92]	RETURN   	0 1

function <./frontend/ui/data/keyboardlayouts/ko_KR_keyboard.lua:88,91> (14 instructions, 56 bytes at 0x7fec6c409560)
3 params, 7 slots, 2 upvalues, 3 locals, 3 constants, 0 functions
	1	[89]	GETUPVAL 	3 0	; HgHelper
	2	[89]	GETTABLE 	3 3 -1	; "HgFSM"
	3	[89]	GETTABLE 	3 3 -2	; "clean_state"
	4	[89]	CALL     	3 1 1
	5	[90]	LOADK    	3 -3	; "_"
	6	[90]	GETUPVAL 	4 1	; name
	7	[90]	CONCAT   	3 3 4
	8	[90]	GETTABLE 	3 0 3
	9	[90]	MOVE     	4 0
	10	[90]	MOVE     	5 1
	11	[90]	MOVE     	6 2
	12	[90]	TAILCALL 	3 4 0
	13	[90]	RETURN   	3 0
	14	[91]	RETURN   	0 1

function <./frontend/ui/data/keyboardlayouts/ko_KR_keyboard.lua:98,101> (6 instructions, 24 bytes at 0x7fec6c409450)
0 params, 2 slots, 2 upvalues, 0 locals, 2 constants, 0 functions
	1	[99]	GETUPVAL 	0 0	; restore_func_references
	2	[99]	GETUPVAL 	1 1	; inputbox
	3	[99]	CALL     	0 2 1
	4	[100]	GETUPVAL 	0 1	; inputbox
	5	[100]	SETTABLE 	0 -1 -2	; "_wrapped" nil
	6	[101]	RETURN   	0 1
