-- BYTECODE -- ko_KR_keyboard.lua:12-14
0001    UGET     2   0      ; HgHelper
0002    TGETS    2   2   0  ; "UIHandler"
0003    TGETS    2   2   1  ; "inputbox"
0004    MOV      3   2
0005    TGETS    2   2   2  ; "_addChars"
0006    MOV      4   1
0007    CALL     2   1   3
0008    RET0     0   1

-- BYTECODE -- ko_KR_keyboard.lua:15-17
0001    UGET     2   0      ; HgHelper
0002    TGETS    2   2   0  ; "UIHandler"
0003    TGETS    2   2   1  ; "inputbox"
0004    MOV      3   2
0005    TGETS    2   2   2  ; "_delChar"
0006    CALL     2   1   2
0007    RET0     0   1

-- BYTECODE -- ko_KR_keyboard.lua:31-39
0001    GGET     1   0      ; "ipairs"
0002    UGET     2   0      ; copied_names
0003    CALL     1   4   2
0004    JMP      4 => 0015
0005 => KSTR     6   1      ; "_"
0006    MOV      7   5
0007    CAT      6   6   7
0008    TGETV    7   0   6
0009    ISF          7
0010    JMP      8 => 0015
0011    TGETV    7   0   6
0012    TSETV    7   0   5
0013    KPRI     7   0
0014    TSETV    7   0   6
0015 => ITERC    4   3   3
0016    ITERL    4 => 0005
0017    RET0     0   1

-- BYTECODE -- ko_KR_keyboard.lua:41-44
0001    KSTR     2   0      ; "_"
0002    MOV      3   1
0003    CAT      2   2   3
0004    TGETV    3   0   1
0005    TSETV    3   0   2
0006    GGET     2   1      ; "table"
0007    TGETS    2   2   2  ; "insert"
0008    UGET     3   0      ; copied_names
0009    MOV      4   1
0010    CALL     2   1   3
0011    RET0     0   1

-- BYTECODE -- ko_KR_keyboard.lua:50-54
0001    UGET     2   0      ; logger
0002    TGETS    2   2   0  ; "dbg"
0003    KSTR     3   1      ; "ko_KR_kbd:addChar("
0004    MOV      4   1
0005    KSTR     5   2      ; ")"
0006    CALL     2   1   4
0007    UGET     2   1      ; HgHelper
0008    TGETS    2   2   3  ; "UIHandler"
0009    TSETS    0   2   4  ; "inputbox"
0010    UGET     2   1      ; HgHelper
0011    TGETS    2   2   5  ; "HgFSM"
0012    MOV      3   2
0013    TGETS    2   2   6  ; "process_char"
0014    MOV      4   1
0015    CALL     2   1   3
0016    RET0     0   1

-- BYTECODE -- ko_KR_keyboard.lua:55-59
0001    UGET     1   0      ; logger
0002    TGETS    1   1   0  ; "dbg"
0003    KSTR     2   1      ; "ko_KR_kbd:delChar()"
0004    CALL     1   1   2
0005    UGET     1   1      ; HgHelper
0006    TGETS    1   1   2  ; "UIHandler"
0007    TSETS    0   1   3  ; "inputbox"
0008    UGET     1   1      ; HgHelper
0009    TGETS    1   1   4  ; "HgFSM"
0010    MOV      2   1
0011    TGETS    1   1   5  ; "process_bsp"
0012    CALL     1   1   2
0013    RET0     0   1

-- BYTECODE -- ko_KR_keyboard.lua:65-68
0001    UGET     1   0      ; HgHelper
0002    TGETS    1   1   0  ; "HgFSM"
0003    TGETS    1   1   1  ; "clean_state"
0004    CALL     1   1   1
0005    KSTR     1   2      ; "_"
0006    UGET     2   1      ; name
0007    CAT      1   1   2
0008    TGETV    1   0   1
0009    MOV      2   0
0010    CALL     1   1   2
0011    RET0     0   1

-- BYTECODE -- ko_KR_keyboard.lua:63-69
0001    UGET     2   0      ; copy_func_reference
0002    MOV      3   0
0003    MOV      4   1
0004    CALL     2   1   3
0005    FNEW     2   0      ; ko_KR_keyboard.lua:65
0006    TSETV    2   0   1
0007    UCLO     0 => 0008
0008 => RET0     0   1

-- BYTECODE -- ko_KR_keyboard.lua:88-91
0001    UGET     3   0      ; HgHelper
0002    TGETS    3   3   0  ; "HgFSM"
0003    TGETS    3   3   1  ; "clean_state"
0004    CALL     3   1   1
0005    KSTR     3   2      ; "_"
0006    UGET     4   1      ; name
0007    CAT      3   3   4
0008    TGETV    3   0   3
0009    MOV      4   0
0010    MOV      5   1
0011    MOV      6   2
0012    CALLT    3   4

-- BYTECODE -- ko_KR_keyboard.lua:86-92
0001    UGET     2   0      ; copy_func_reference
0002    MOV      3   0
0003    MOV      4   1
0004    CALL     2   1   3
0005    FNEW     2   0      ; ko_KR_keyboard.lua:88
0006    TSETV    2   0   1
0007    UCLO     0 => 0008
0008 => RET0     0   1

-- BYTECODE -- ko_KR_keyboard.lua:98-101
0001    UGET     0   0      ; restore_func_references
0002    UGET     1   1      ; inputbox
0003    CALL     0   1   2
0004    UGET     0   1      ; inputbox
0005    KPRI     1   0
0006    TSETS    1   0   0  ; "_wrapped"
0007    RET0     0   1

-- BYTECODE -- ko_KR_keyboard.lua:23-103
0001    UGET     1   0      ; HgHelper
0002    TGETS    1   1   0  ; "HgFSM"
0003    TGETS    1   1   1  ; "clean_state"
0004    CALL     1   1   1
0005    TGETS    1   0   2  ; "_wrapped"
0006    ISNEP    1   0
0007    JMP      1 => 0071
0008    KPRI     1   2
0009    TSETS    1   0   2  ; "_wrapped"
0010    TNEW     1   0
0011    FNEW     2   3      ; ko_KR_keyboard.lua:31
0012    FNEW     3   4      ; ko_KR_keyboard.lua:41
0013    MOV      4   3
0014    MOV      5   0
0015    KSTR     6   5      ; "addChars"
0016    CALL     4   1   3
0017    MOV      4   3
0018    MOV      5   0
0019    KSTR     6   6      ; "delChar"
0020    CALL     4   1   3
0021    FNEW     4   7      ; ko_KR_keyboard.lua:50
0022    TSETS    4   0   5  ; "addChars"
0023    FNEW     4   8      ; ko_KR_keyboard.lua:55
0024    TSETS    4   0   6  ; "delChar"
0025    FNEW     4   9      ; ko_KR_keyboard.lua:63
0026    MOV      5   4
0027    MOV      6   0
0028    KSTR     7  10      ; "delToStartOfLine"
0029    CALL     5   1   3
0030    MOV      5   4
0031    MOV      6   0
0032    KSTR     7  11      ; "clear"
0033    CALL     5   1   3
0034    MOV      5   4
0035    MOV      6   0
0036    KSTR     7  12      ; "leftChar"
0037    CALL     5   1   3
0038    MOV      5   4
0039    MOV      6   0
0040    KSTR     7  13      ; "rightChar"
0041    CALL     5   1   3
0042    MOV      5   4
0043    MOV      6   0
0044    KSTR     7  14      ; "upLine"
0045    CALL     5   1   3
0046    MOV      5   4
0047    MOV      6   0
0048    KSTR     7  15      ; "downLine"
0049    CALL     5   1   3
0050    MOV      5   4
0051    MOV      6   0
0052    KSTR     7  16      ; "unfocus"
0053    CALL     5   1   3
0054    FNEW     5  17      ; ko_KR_keyboard.lua:86
0055    MOV      6   5
0056    MOV      7   0
0057    KSTR     8  18      ; "onTapTextBox"
0058    CALL     6   1   3
0059    MOV      6   5
0060    MOV      7   0
0061    KSTR     8  19      ; "onHoldTextBox"
0062    CALL     6   1   3
0063    MOV      6   5
0064    MOV      7   0
0065    KSTR     8  20      ; "onSwipeTextBox"
0066    CALL     6   1   3
0067    FNEW     6  21      ; ko_KR_keyboard.lua:98
0068    UCLO     0 => 0069
0069 => RET1     6   2
0070    UCLO     1 => 0071
0071 => UCLO     0 => 0072
0072 => RET0     0   1

-- BYTECODE -- ko_KR_keyboard.lua:0-187
0001    GGET     0   0      ; "require"
0002    KSTR     1   1      ; "logger"
0003    CALL     0   2   2
0004    GGET     1   0      ; "require"
0005    KSTR     2   2      ; "ui/data/keyboardlayouts/ko_KR_helper"
0006    CALL     1   2   2
0007    TGETS    2   1   3  ; "UIHandler"
0008    FNEW     3   5      ; ko_KR_keyboard.lua:12
0009    TSETS    3   2   4  ; "put_char"
0010    TGETS    2   1   3  ; "UIHandler"
0011    FNEW     3   7      ; ko_KR_keyboard.lua:15
0012    TSETS    3   2   6  ; "del_char"
0013    TGETS    2   1   8  ; "HgFSM"
0014    MOV      3   2
0015    TGETS    2   2   9  ; "init"
0016    TGETS    4   1   3  ; "UIHandler"
0017    CALL     2   1   3
0018    FNEW     2  10      ; ko_KR_keyboard.lua:23
0019    GGET     3   0      ; "require"
0020    KSTR     4  11      ; "ui/data/keyboardlayouts/keypopup/en_popu"~
0021    CALL     3   2   2
0022    TGETS    4   3  12  ; "com"
0023    TGETS    5   3  13  ; "prd"
0024    TGETS    6   3  14  ; "_at"
0025    TGETS    7   3  15  ; "_eq"
0026    TDUP     8  16
0027    TDUP     9  17
0028    TSETS    9   8  18  ; "shiftmode_keys"
0029    TDUP     9  19
0030    TSETS    9   8  20  ; "symbolmode_keys"
0031    TDUP     9  21
0032    TSETS    9   8  22  ; "utf8mode_keys"
0033    TDUP     9  23
0034    TSETS    9   8  24  ; "umlautmode_keys"
0035    TNEW     9   5
0036    TNEW    10  11
0037    TDUP    11  25
0038    TSETB   11  10   1
0039    TDUP    11  26
0040    TSETB   11  10   2
0041    TDUP    11  27
0042    TSETB    6  11   3
0043    TSETB   11  10   3
0044    TDUP    11  28
0045    TSETB   11  10   4
0046    TDUP    11  29
0047    TSETB    7  11   4
0048    TSETB   11  10   5
0049    TDUP    11  30
0050    TSETB   11  10   6
0051    TDUP    11  31
0052    TSETB   11  10   7
0053    TDUP    11  32
0054    TSETB   11  10   8
0055    TDUP    11  33
0056    TSETB   11  10   9
0057    TDUP    11  34
0058    TSETB   11  10  10
0059    TSETB   10   9   1
0060    TNEW    10  10
0061    TDUP    11  35
0062    TSETB   11  10   1
0063    TDUP    11  36
0064    TSETB   11  10   2
0065    TDUP    11  37
0066    TSETB   11  10   3
0067    TDUP    11  38
0068    TSETB   11  10   4
0069    TDUP    11  39
0070    TSETB   11  10   5
0071    TDUP    11  40
0072    TSETB   11  10   6
0073    TDUP    11  41
0074    TSETB   11  10   7
0075    TDUP    11  42
0076    TSETB   11  10   8
0077    TDUP    11  43
0078    TSETB   11  10   9
0079    TSETB   10   9   2
0080    TNEW    10  10
0081    TDUP    11  44
0082    TSETB   11  10   1
0083    TDUP    11  45
0084    TSETB   11  10   2
0085    TDUP    11  46
0086    TSETB   11  10   3
0087    TDUP    11  47
0088    TSETB   11  10   4
0089    TDUP    11  48
0090    TSETB    4  11   4
0091    TSETB   11  10   5
0092    TDUP    11  49
0093    TSETB    5  11   4
0094    TSETB   11  10   6
0095    TDUP    11  50
0096    TSETB   11  10   7
0097    TDUP    11  51
0098    TSETB   11  10   8
0099    TDUP    11  52
0100    TSETB   11  10   9
0101    TSETB   10   9   3
0102    TNEW    10   7
0103    TDUP    11  53
0104    TSETB   11  10   1
0105    TDUP    11  54
0106    TSETB   11  10   2
0107    TDUP    11  55
0108    TSETB   11  10   3
0109    TDUP    11  56
0110    TSETB    4  11   1
0111    TSETB    4  11   2
0112    TSETB   11  10   4
0113    TDUP    11  57
0114    TSETB    5  11   1
0115    TSETB    5  11   2
0116    TSETB   11  10   5
0117    TDUP    11  58
0118    TSETB   11  10   6
0119    TSETB   10   9   4
0120    TSETS    9   8  59  ; "keys"
0121    TSETS    2   8  60  ; "wrapInputBox"
0122    UCLO     0 => 0123
0123 => RET1     8   2

