-- BYTECODE -- kobo_touch_probe.lua:45-91
0001    TDUP     1   3
0002    TNEW     2   3
0003    UGET     3   0      ; GestureRange
0004    MOV      4   3
0005    TGETS    3   3   1  ; "new"
0006    TDUP     5   2
0007    CALL     3   0   3
0008    TSETM    3   0      ; 1
0009    TSETS    2   1   4  ; "TapProbe"
0010    TSETS    1   0   0  ; "ges_events"
0011    UGET     1   1      ; ImageWidget
0012    MOV      2   1
0013    TGETS    1   1   1  ; "new"
0014    TDUP     3   6
0015    CALL     1   2   3
0016    TSETS    1   0   5  ; "image_widget"
0017    UGET     1   2      ; Screen
0018    MOV      2   1
0019    TGETS    1   1   7  ; "getWidth"
0020    CALL     1   2   2
0021    UGET     2   2      ; Screen
0022    MOV      3   2
0023    TGETS    2   2   8  ; "getHeight"
0024    CALL     2   2   2
0025    TGETS    3   0   5  ; "image_widget"
0026    MOV      4   3
0027    TGETS    3   3   9  ; "getSize"
0028    CALL     3   2   2
0029    TGETS    3   3  10  ; "w"
0030    TGETS    4   0   5  ; "image_widget"
0031    MOV      5   4
0032    TGETS    4   4   9  ; "getSize"
0033    CALL     4   2   2
0034    TGETS    4   4  11  ; "h"
0035    TNEW     5   3
0036    TDUP     6  14
0037    UGET     7   3      ; _
0038    KSTR     8  13      ; "Tap the lower right corner"
0039    CALL     7   2   2
0040    TSETS    7   6  15  ; "hint_text"
0041    TDUP     7  16
0042    SUBVV    8   1   3
0043    TSETS    8   7  17  ; "x"
0044    SUBVV    8   2   4
0045    TSETS    8   7  18  ; "y"
0046    TSETS    7   6  19  ; "hint_icon_pos"
0047    TSETB    6   5   1
0048    TDUP     6  21
0049    UGET     7   3      ; _
0050    KSTR     8  20      ; "Tap the upper right corner"
0051    CALL     7   2   2
0052    TSETS    7   6  15  ; "hint_text"
0053    TDUP     7  22
0054    SUBVV    8   1   3
0055    TSETS    8   7  17  ; "x"
0056    TSETS    7   6  19  ; "hint_icon_pos"
0057    TSETB    6   5   2
0058    TSETS    5   0  12  ; "probe_steps"
0059    UGET     5   4      ; TextWidget
0060    MOV      6   5
0061    TGETS    5   5   1  ; "new"
0062    TDUP     7  24
0063    UGET     8   5      ; Font
0064    MOV      9   8
0065    TGETS    8   8  25  ; "getFace"
0066    KSTR    10  26      ; "cfont"
0067    KSHORT  11  30
0068    CALL     8   2   4
0069    TSETS    8   7  27  ; "face"
0070    CALL     5   2   3
0071    TSETS    5   0  23  ; "hint_text_widget"
0072    UGET     5   6      ; FrameContainer
0073    MOV      6   5
0074    TGETS    5   5   1  ; "new"
0075    TDUP     7  28
0076    UGET     8   7      ; Blitbuffer
0077    TGETS    8   8  29  ; "COLOR_WHITE"
0078    TSETS    8   7  30  ; "background"
0079    UGET     8   8      ; OverlapGroup
0080    MOV      9   8
0081    TGETS    8   8   1  ; "new"
0082    TDUP    10  31
0083    UGET    11   2      ; Screen
0084    MOV     12  11
0085    TGETS   11  11   9  ; "getSize"
0086    CALL    11   2   2
0087    TSETS   11  10  32  ; "dimen"
0088    UGET    11   9      ; CenterContainer
0089    MOV     12  11
0090    TGETS   11  11   1  ; "new"
0091    TDUP    13  33
0092    UGET    14   2      ; Screen
0093    MOV     15  14
0094    TGETS   14  14   9  ; "getSize"
0095    CALL    14   2   2
0096    TSETS   14  13  32  ; "dimen"
0097    TGETS   14   0  23  ; "hint_text_widget"
0098    TSETB   14  13   1
0099    CALL    11   2   3
0100    TSETB   11  10   1
0101    TGETS   11   0   5  ; "image_widget"
0102    TSETB   11  10   2
0103    CALL     8   0   3
0104    TSETM    8   0      ; 1
0105    CALL     5   2   3
0106    TSETB    5   0   1
0107    MOV      6   0
0108    TGETS    5   0  34  ; "updateProbeInstruction"
0109    CALL     5   1   2
0110    RET0     0   1

-- BYTECODE -- kobo_touch_probe.lua:93-100
0001    TGETS    1   0   0  ; "probe_steps"
0002    TGETS    2   0   1  ; "curr_probe_step"
0003    TGETV    1   1   2
0004    TGETS    2   0   2  ; "image_widget"
0005    TNEW     3   3
0006    TGETS    4   1   4  ; "hint_icon_pos"
0007    TGETS    4   4   5  ; "x"
0008    TSETB    4   3   1
0009    TGETS    4   1   4  ; "hint_icon_pos"
0010    TGETS    4   4   6  ; "y"
0011    TSETB    4   3   2
0012    TSETS    3   2   3  ; "overlap_offset"
0013    TGETS    2   0   7  ; "hint_text_widget"
0014    MOV      3   2
0015    TGETS    2   2   8  ; "setText"
0016    TGETS    4   1   9  ; "hint_text"
0017    CALL     2   1   3
0018    RET0     0   1

-- BYTECODE -- kobo_touch_probe.lua:102-107
0001    GGET     2   0      ; "G_reader_settings"
0002    MOV      3   2
0003    TGETS    2   2   1  ; "saveSetting"
0004    KSTR     4   2      ; "kobo_touch_switch_xy"
0005    MOV      5   1
0006    CALL     2   1   4
0007    GGET     2   0      ; "G_reader_settings"
0008    MOV      3   2
0009    TGETS    2   2   3  ; "flush"
0010    CALL     2   1   2
0011    UGET     2   0      ; UIManager
0012    MOV      3   2
0013    TGETS    2   2   4  ; "quit"
0014    CALL     2   1   2
0015    RET0     0   1

-- BYTECODE -- kobo_touch_probe.lua:109-129
0001    TGETS    3   0   0  ; "curr_probe_step"
0002    ISNEN    3   0      ; 1
0003    JMP      3 => 0050
0004    GGET     3   1      ; "math"
0005    TGETS    3   3   2  ; "min"
0006    UGET     4   0      ; Screen
0007    MOV      5   4
0008    TGETS    4   4   3  ; "getHeight"
0009    CALL     4   2   2
0010    UGET     5   0      ; Screen
0011    MOV      6   5
0012    TGETS    5   5   4  ; "getWidth"
0013    CALL     5   0   2
0014    CALLM    3   2   1
0015    GGET     4   1      ; "math"
0016    TGETS    4   4   2  ; "min"
0017    TGETS    5   2   5  ; "pos"
0018    TGETS    5   5   6  ; "x"
0019    TGETS    6   2   5  ; "pos"
0020    TGETS    6   6   7  ; "y"
0021    CALL     4   2   3
0022    DIVVN    5   3   1  ; 2
0023    ISGE     4   5
0024    JMP      4 => 0039
0025    TGETS    4   2   5  ; "pos"
0026    TGETS    4   4   6  ; "x"
0027    TGETS    5   2   5  ; "pos"
0028    TGETS    5   5   7  ; "y"
0029    ISLT     5   4
0030    JMP      4 => 0033
0031    KPRI     4   1
0032    JMP      5 => 0034
0033 => KPRI     4   2
0034 => MOV      6   0
0035    TGETS    5   0   8  ; "saveSwitchXYSetting"
0036    MOV      7   4
0037    CALL     5   1   3
0038    JMP      4 => 0066
0039 => KSHORT   4   2
0040    TSETS    4   0   0  ; "curr_probe_step"
0041    MOV      5   0
0042    TGETS    4   0   9  ; "updateProbeInstruction"
0043    CALL     4   1   2
0044    UGET     4   1      ; UIManager
0045    MOV      5   4
0046    TGETS    4   4  10  ; "setDirty"
0047    MOV      6   0
0048    CALL     4   1   3
0049    JMP      3 => 0066
0050 => TGETS    3   0   0  ; "curr_probe_step"
0051    ISNEN    3   1      ; 2
0052    JMP      3 => 0066
0053    TGETS    3   2   5  ; "pos"
0054    TGETS    3   3   6  ; "x"
0055    TGETS    4   2   5  ; "pos"
0056    TGETS    4   4   7  ; "y"
0057    ISLT     3   4
0058    JMP      3 => 0061
0059    KPRI     3   1
0060    JMP      4 => 0062
0061 => KPRI     3   2
0062 => MOV      5   0
0063    TGETS    4   0   8  ; "saveSwitchXYSetting"
0064    MOV      6   3
0065    CALL     4   1   3
0066 => RET0     0   1

-- BYTECODE -- kobo_touch_probe.lua:0-132
0001    GGET     0   0      ; "require"
0002    KSTR     1   1      ; "defaults"
0003    CALL     0   1   2
0004    GGET     0   2      ; "package"
0005    KSTR     1   4      ; "common/?.lua;rocks/share/lua/5.1/?.lua;f"~
0006    GGET     2   2      ; "package"
0007    TGETS    2   2   3  ; "path"
0008    CAT      1   1   2
0009    TSETS    1   0   3  ; "path"
0010    GGET     0   2      ; "package"
0011    KSTR     1   6      ; "common/?.so;common/?.dll;/usr/lib/lua/?."~
0012    GGET     2   2      ; "package"
0013    TGETS    2   2   5  ; "cpath"
0014    CAT      1   1   2
0015    TSETS    1   0   5  ; "cpath"
0016    GGET     0   0      ; "require"
0017    KSTR     1   7      ; "datastorage"
0018    CALL     0   2   2
0019    GGET     1   0      ; "require"
0020    KSTR     2   8      ; "gettext"
0021    CALL     1   2   2
0022    GGET     2   9      ; "G_reader_settings"
0023    ISNEP    2   0
0024    JMP      2 => 0037
0025    GGET     2   0      ; "require"
0026    KSTR     3  10      ; "luasettings"
0027    CALL     2   2   2
0028    MOV      3   2
0029    TGETS    2   2  11  ; "open"
0030    MOV      5   0
0031    TGETS    4   0  12  ; "getDataDir"
0032    CALL     4   2   2
0033    KSTR     5  13      ; "/settings.reader.lua"
0034    CAT      4   4   5
0035    CALL     2   2   3
0036    GSET     2   9      ; "G_reader_settings"
0037 => GGET     2   9      ; "G_reader_settings"
0038    MOV      3   2
0039    TGETS    2   2  14  ; "readSetting"
0040    KSTR     4  15      ; "language"
0041    CALL     2   2   3
0042    ISF          2
0043    JMP      3 => 0047
0044    TGETS    3   1  16  ; "changeLang"
0045    MOV      4   2
0046    CALL     3   1   2
0047 => GGET     3   0      ; "require"
0048    KSTR     4  17      ; "ui/widget/container/inputcontainer"
0049    CALL     3   2   2
0050    GGET     4   0      ; "require"
0051    KSTR     5  18      ; "ui/widget/container/centercontainer"
0052    CALL     4   2   2
0053    GGET     5   0      ; "require"
0054    KSTR     6  19      ; "ui/widget/container/framecontainer"
0055    CALL     5   2   2
0056    GGET     6   0      ; "require"
0057    KSTR     7  20      ; "ui/widget/container/rightcontainer"
0058    CALL     6   2   2
0059    GGET     7   0      ; "require"
0060    KSTR     8  21      ; "ui/widget/overlapgroup"
0061    CALL     7   2   2
0062    GGET     8   0      ; "require"
0063    KSTR     9  22      ; "ui/widget/imagewidget"
0064    CALL     8   2   2
0065    GGET     9   0      ; "require"
0066    KSTR    10  23      ; "ui/widget/textwidget"
0067    CALL     9   2   2
0068    GGET    10   0      ; "require"
0069    KSTR    11  24      ; "ui/gesturerange"
0070    CALL    10   2   2
0071    GGET    11   0      ; "require"
0072    KSTR    12  25      ; "ui/uimanager"
0073    CALL    11   2   2
0074    GGET    12   0      ; "require"
0075    KSTR    13  26      ; "ffi/blitbuffer"
0076    CALL    12   2   2
0077    GGET    13   0      ; "require"
0078    KSTR    14  27      ; "ui/geometry"
0079    CALL    13   2   2
0080    GGET    14   0      ; "require"
0081    KSTR    15  28      ; "device"
0082    CALL    14   2   2
0083    TGETS   15  14  29  ; "screen"
0084    TGETS   16  14  30  ; "input"
0085    GGET    17   0      ; "require"
0086    KSTR    18  31      ; "ui/font"
0087    CALL    17   2   2
0088    GGET    18   0      ; "require"
0089    KSTR    19  32      ; "dbg"
0090    CALL    18   2   2
0091    MOV     20   3
0092    TGETS   19   3  33  ; "new"
0093    TDUP    21  34
0094    CALL    19   2   3
0095    FNEW    20  36      ; kobo_touch_probe.lua:45
0096    TSETS   20  19  35  ; "init"
0097    FNEW    20  38      ; kobo_touch_probe.lua:93
0098    TSETS   20  19  37  ; "updateProbeInstruction"
0099    FNEW    20  40      ; kobo_touch_probe.lua:102
0100    TSETS   20  19  39  ; "saveSwitchXYSetting"
0101    FNEW    20  42      ; kobo_touch_probe.lua:109
0102    TSETS   20  19  41  ; "onTapProbe"
0103    UCLO     0 => 0104
0104 => RET1    19   2

