
main <./tools/kobo_touch_probe.lua:0,0> (114 instructions, 456 bytes at 0x7fab964068c0)
0+ params, 22 slots, 0 upvalues, 20 locals, 41 constants, 4 functions
	1	[4]	GETGLOBAL	0 -1	; require
	2	[4]	LOADK    	1 -2	; "defaults"
	3	[4]	CALL     	0 2 1
	4	[5]	GETGLOBAL	0 -3	; package
	5	[5]	LOADK    	1 -5	; "common/?.lua;rocks/share/lua/5.1/?.lua;frontend/?.lua;"
	6	[5]	GETGLOBAL	2 -3	; package
	7	[5]	GETTABLE 	2 2 -4	; "path"
	8	[5]	CONCAT   	1 1 2
	9	[5]	SETTABLE 	0 -4 1	; "path" -
	10	[6]	GETGLOBAL	0 -3	; package
	11	[6]	LOADK    	1 -7	; "common/?.so;common/?.dll;/usr/lib/lua/?.so;rocks/lib/lua/5.1/?.so;"
	12	[6]	GETGLOBAL	2 -3	; package
	13	[6]	GETTABLE 	2 2 -6	; "cpath"
	14	[6]	CONCAT   	1 1 2
	15	[6]	SETTABLE 	0 -6 1	; "cpath" -
	16	[8]	GETGLOBAL	0 -1	; require
	17	[8]	LOADK    	1 -8	; "datastorage"
	18	[8]	CALL     	0 2 2
	19	[9]	GETGLOBAL	1 -1	; require
	20	[9]	LOADK    	2 -9	; "gettext"
	21	[9]	CALL     	1 2 2
	22	[15]	GETGLOBAL	2 -10	; G_reader_settings
	23	[15]	EQ       	0 2 -11	; - nil
	24	[15]	JMP      	10	; to 35
	25	[16]	GETGLOBAL	2 -1	; require
	26	[16]	LOADK    	3 -12	; "luasettings"
	27	[16]	CALL     	2 2 2
	28	[16]	SELF     	2 2 -13	; "open"
	29	[17]	SELF     	4 0 -14	; "getDataDir"
	30	[17]	CALL     	4 2 2
	31	[17]	LOADK    	5 -15	; "/settings.reader.lua"
	32	[17]	CONCAT   	4 4 5
	33	[16]	CALL     	2 3 2
	34	[17]	SETGLOBAL	2 -10	; G_reader_settings
	35	[19]	GETGLOBAL	2 -10	; G_reader_settings
	36	[19]	SELF     	2 2 -16	; "readSetting"
	37	[19]	LOADK    	4 -17	; "language"
	38	[19]	CALL     	2 3 2
	39	[20]	TEST     	2 0 0
	40	[20]	JMP      	3	; to 44
	41	[21]	GETTABLE 	3 1 -18	; "changeLang"
	42	[21]	MOVE     	4 2
	43	[21]	CALL     	3 2 1
	44	[23]	GETGLOBAL	3 -1	; require
	45	[23]	LOADK    	4 -19	; "ui/widget/container/inputcontainer"
	46	[23]	CALL     	3 2 2
	47	[24]	GETGLOBAL	4 -1	; require
	48	[24]	LOADK    	5 -20	; "ui/widget/container/centercontainer"
	49	[24]	CALL     	4 2 2
	50	[25]	GETGLOBAL	5 -1	; require
	51	[25]	LOADK    	6 -21	; "ui/widget/container/framecontainer"
	52	[25]	CALL     	5 2 2
	53	[26]	GETGLOBAL	6 -1	; require
	54	[26]	LOADK    	7 -22	; "ui/widget/container/rightcontainer"
	55	[26]	CALL     	6 2 2
	56	[27]	GETGLOBAL	7 -1	; require
	57	[27]	LOADK    	8 -23	; "ui/widget/overlapgroup"
	58	[27]	CALL     	7 2 2
	59	[28]	GETGLOBAL	8 -1	; require
	60	[28]	LOADK    	9 -24	; "ui/widget/imagewidget"
	61	[28]	CALL     	8 2 2
	62	[29]	GETGLOBAL	9 -1	; require
	63	[29]	LOADK    	10 -25	; "ui/widget/textwidget"
	64	[29]	CALL     	9 2 2
	65	[30]	GETGLOBAL	10 -1	; require
	66	[30]	LOADK    	11 -26	; "ui/gesturerange"
	67	[30]	CALL     	10 2 2
	68	[31]	GETGLOBAL	11 -1	; require
	69	[31]	LOADK    	12 -27	; "ui/uimanager"
	70	[31]	CALL     	11 2 2
	71	[32]	GETGLOBAL	12 -1	; require
	72	[32]	LOADK    	13 -28	; "ffi/blitbuffer"
	73	[32]	CALL     	12 2 2
	74	[33]	GETGLOBAL	13 -1	; require
	75	[33]	LOADK    	14 -29	; "ui/geometry"
	76	[33]	CALL     	13 2 2
	77	[34]	GETGLOBAL	14 -1	; require
	78	[34]	LOADK    	15 -30	; "device"
	79	[34]	CALL     	14 2 2
	80	[35]	GETTABLE 	15 14 -31	; "screen"
	81	[36]	GETTABLE 	16 14 -32	; "input"
	82	[37]	GETGLOBAL	17 -1	; require
	83	[37]	LOADK    	18 -33	; "ui/font"
	84	[37]	CALL     	17 2 2
	85	[38]	GETGLOBAL	18 -1	; require
	86	[38]	LOADK    	19 -34	; "dbg"
	87	[38]	CALL     	18 2 2
	88	[41]	SELF     	19 3 -35	; "new"
	89	[41]	NEWTABLE 	21 0 1
	90	[42]	SETTABLE 	21 -36 -37	; "curr_probe_step" 1
	91	[41]	CALL     	19 3 2
	92	[91]	CLOSURE  	20 0	; 0x7fab96406be0
	93	[91]	MOVE     	0 10
	94	[91]	MOVE     	0 8
	95	[91]	MOVE     	0 15
	96	[91]	MOVE     	0 1
	97	[91]	MOVE     	0 9
	98	[91]	MOVE     	0 17
	99	[91]	MOVE     	0 5
	100	[91]	MOVE     	0 12
	101	[91]	MOVE     	0 7
	102	[91]	MOVE     	0 4
	103	[45]	SETTABLE 	19 -38 20	; "init" -
	104	[100]	CLOSURE  	20 1	; 0x7fab96407f80
	105	[93]	SETTABLE 	19 -39 20	; "updateProbeInstruction" -
	106	[107]	CLOSURE  	20 2	; 0x7fab96408120
	107	[107]	MOVE     	0 11
	108	[102]	SETTABLE 	19 -40 20	; "saveSwitchXYSetting" -
	109	[129]	CLOSURE  	20 3	; 0x7fab96408bd0
	110	[129]	MOVE     	0 15
	111	[129]	MOVE     	0 11
	112	[109]	SETTABLE 	19 -41 20	; "onTapProbe" -
	113	[131]	RETURN   	19 2
	114	[131]	RETURN   	0 1

function <./tools/kobo_touch_probe.lua:45,91> (99 instructions, 396 bytes at 0x7fab96406be0)
1 param, 16 slots, 10 upvalues, 5 locals, 34 constants, 0 functions
	1	[46]	NEWTABLE 	1 0 1
	2	[47]	NEWTABLE 	2 0 0
	3	[48]	GETUPVAL 	3 0	; GestureRange
	4	[48]	SELF     	3 3 -3	; "new"
	5	[48]	NEWTABLE 	5 0 1
	6	[49]	SETTABLE 	5 -4 -5	; "ges" "tap"
	7	[48]	CALL     	3 3 0
	8	[51]	SETLIST  	2 0 1	; 1
	9	[51]	SETTABLE 	1 -2 2	; "TapProbe" -
	10	[52]	SETTABLE 	0 -1 1	; "ges_events" -
	11	[53]	GETUPVAL 	1 1	; ImageWidget
	12	[53]	SELF     	1 1 -3	; "new"
	13	[53]	NEWTABLE 	3 0 1
	14	[54]	SETTABLE 	3 -7 -8	; "file" "resources/kobo-touch-probe.png"
	15	[53]	CALL     	1 3 2
	16	[55]	SETTABLE 	0 -6 1	; "image_widget" -
	17	[56]	GETUPVAL 	1 2	; Screen
	18	[56]	SELF     	1 1 -9	; "getWidth"
	19	[56]	CALL     	1 2 2
	20	[56]	GETUPVAL 	2 2	; Screen
	21	[56]	SELF     	2 2 -10	; "getHeight"
	22	[56]	CALL     	2 2 2
	23	[57]	GETTABLE 	3 0 -6	; "image_widget"
	24	[57]	SELF     	3 3 -11	; "getSize"
	25	[57]	CALL     	3 2 2
	26	[57]	GETTABLE 	3 3 -12	; "w"
	27	[57]	GETTABLE 	4 0 -6	; "image_widget"
	28	[57]	SELF     	4 4 -11	; "getSize"
	29	[57]	CALL     	4 2 2
	30	[57]	GETTABLE 	4 4 -13	; "h"
	31	[58]	NEWTABLE 	5 2 0
	32	[58]	NEWTABLE 	6 0 2
	33	[60]	GETUPVAL 	7 3	; _
	34	[60]	LOADK    	8 -16	; "Tap the lower right corner"
	35	[60]	CALL     	7 2 2
	36	[60]	SETTABLE 	6 -15 7	; "hint_text" -
	37	[61]	NEWTABLE 	7 0 2
	38	[62]	SUB      	8 1 3
	39	[62]	SETTABLE 	7 -18 8	; "x" -
	40	[63]	SUB      	8 2 4
	41	[63]	SETTABLE 	7 -19 8	; "y" -
	42	[64]	SETTABLE 	6 -17 7	; "hint_icon_pos" -
	43	[65]	NEWTABLE 	7 0 2
	44	[67]	GETUPVAL 	8 3	; _
	45	[67]	LOADK    	9 -20	; "Tap the upper right corner"
	46	[67]	CALL     	8 2 2
	47	[67]	SETTABLE 	7 -15 8	; "hint_text" -
	48	[68]	NEWTABLE 	8 0 2
	49	[69]	SUB      	9 1 3
	50	[69]	SETTABLE 	8 -18 9	; "x" -
	51	[70]	SETTABLE 	8 -19 -21	; "y" 0
	52	[71]	SETTABLE 	7 -17 8	; "hint_icon_pos" -
	53	[73]	SETLIST  	5 2 1	; 1
	54	[73]	SETTABLE 	0 -14 5	; "probe_steps" -
	55	[74]	GETUPVAL 	5 4	; TextWidget
	56	[74]	SELF     	5 5 -3	; "new"
	57	[74]	NEWTABLE 	7 0 2
	58	[75]	SETTABLE 	7 -23 -24	; "text" ""
	59	[76]	GETUPVAL 	8 5	; Font
	60	[76]	SELF     	8 8 -26	; "getFace"
	61	[76]	LOADK    	10 -27	; "cfont"
	62	[76]	LOADK    	11 -28	; 30
	63	[76]	CALL     	8 4 2
	64	[76]	SETTABLE 	7 -25 8	; "face" -
	65	[74]	CALL     	5 3 2
	66	[77]	SETTABLE 	0 -22 5	; "hint_text_widget" -
	67	[78]	GETUPVAL 	5 6	; FrameContainer
	68	[78]	SELF     	5 5 -3	; "new"
	69	[78]	NEWTABLE 	7 0 2
	70	[79]	SETTABLE 	7 -30 -21	; "bordersize" 0
	71	[80]	GETUPVAL 	8 7	; Blitbuffer
	72	[80]	GETTABLE 	8 8 -32	; "COLOR_WHITE"
	73	[80]	SETTABLE 	7 -31 8	; "background" -
	74	[81]	GETUPVAL 	8 8	; OverlapGroup
	75	[81]	SELF     	8 8 -3	; "new"
	76	[81]	NEWTABLE 	10 2 1
	77	[82]	GETUPVAL 	11 2	; Screen
	78	[82]	SELF     	11 11 -11	; "getSize"
	79	[82]	CALL     	11 2 2
	80	[82]	SETTABLE 	10 -33 11	; "dimen" -
	81	[83]	GETUPVAL 	11 9	; CenterContainer
	82	[83]	SELF     	11 11 -3	; "new"
	83	[83]	NEWTABLE 	13 1 1
	84	[84]	GETUPVAL 	14 2	; Screen
	85	[84]	SELF     	14 14 -11	; "getSize"
	86	[84]	CALL     	14 2 2
	87	[84]	SETTABLE 	13 -33 14	; "dimen" -
	88	[86]	GETTABLE 	14 0 -22	; "hint_text_widget"
	89	[86]	SETLIST  	13 1 1	; 1
	90	[83]	CALL     	11 3 2
	91	[88]	GETTABLE 	12 0 -6	; "image_widget"
	92	[88]	SETLIST  	10 2 1	; 1
	93	[81]	CALL     	8 3 0
	94	[89]	SETLIST  	7 0 1	; 1
	95	[78]	CALL     	5 3 2
	96	[89]	SETTABLE 	0 -29 5	; 1 -
	97	[90]	SELF     	5 0 -34	; "updateProbeInstruction"
	98	[90]	CALL     	5 2 1
	99	[91]	RETURN   	0 1

function <./tools/kobo_touch_probe.lua:93,100> (16 instructions, 64 bytes at 0x7fab96407f80)
1 param, 6 slots, 0 upvalues, 2 locals, 10 constants, 0 functions
	1	[94]	GETTABLE 	1 0 -1	; "probe_steps"
	2	[94]	GETTABLE 	2 0 -2	; "curr_probe_step"
	3	[94]	GETTABLE 	1 1 2
	4	[95]	GETTABLE 	2 0 -3	; "image_widget"
	5	[95]	NEWTABLE 	3 2 0
	6	[96]	GETTABLE 	4 1 -5	; "hint_icon_pos"
	7	[96]	GETTABLE 	4 4 -6	; "x"
	8	[97]	GETTABLE 	5 1 -5	; "hint_icon_pos"
	9	[98]	GETTABLE 	5 5 -7	; "y"
	10	[98]	SETLIST  	3 2 1	; 1
	11	[98]	SETTABLE 	2 -4 3	; "overlap_offset" -
	12	[99]	GETTABLE 	2 0 -8	; "hint_text_widget"
	13	[99]	SELF     	2 2 -9	; "setText"
	14	[99]	GETTABLE 	4 1 -10	; "hint_text"
	15	[99]	CALL     	2 3 1
	16	[100]	RETURN   	0 1

function <./tools/kobo_touch_probe.lua:102,107> (12 instructions, 48 bytes at 0x7fab96408120)
2 params, 6 slots, 1 upvalue, 2 locals, 5 constants, 0 functions
	1	[104]	GETGLOBAL	2 -1	; G_reader_settings
	2	[104]	SELF     	2 2 -2	; "saveSetting"
	3	[104]	LOADK    	4 -3	; "kobo_touch_switch_xy"
	4	[104]	MOVE     	5 1
	5	[104]	CALL     	2 4 1
	6	[105]	GETGLOBAL	2 -1	; G_reader_settings
	7	[105]	SELF     	2 2 -4	; "flush"
	8	[105]	CALL     	2 2 1
	9	[106]	GETUPVAL 	2 0	; UIManager
	10	[106]	SELF     	2 2 -5	; "quit"
	11	[106]	CALL     	2 2 1
	12	[107]	RETURN   	0 1

function <./tools/kobo_touch_probe.lua:109,129> (57 instructions, 228 bytes at 0x7fab96408bd0)
3 params, 8 slots, 2 upvalues, 6 locals, 13 constants, 0 functions
	1	[110]	GETTABLE 	3 0 -1	; "curr_probe_step"
	2	[110]	EQ       	0 3 -2	; - 1
	3	[110]	JMP      	39	; to 43
	4	[111]	GETGLOBAL	3 -3	; math
	5	[111]	GETTABLE 	3 3 -4	; "min"
	6	[111]	GETUPVAL 	4 0	; Screen
	7	[111]	SELF     	4 4 -5	; "getHeight"
	8	[111]	CALL     	4 2 2
	9	[111]	GETUPVAL 	5 0	; Screen
	10	[111]	SELF     	5 5 -6	; "getWidth"
	11	[111]	CALL     	5 2 0
	12	[111]	CALL     	3 0 2
	13	[112]	GETGLOBAL	4 -3	; math
	14	[112]	GETTABLE 	4 4 -4	; "min"
	15	[112]	GETTABLE 	5 2 -7	; "pos"
	16	[112]	GETTABLE 	5 5 -8	; "x"
	17	[112]	GETTABLE 	6 2 -7	; "pos"
	18	[112]	GETTABLE 	6 6 -9	; "y"
	19	[112]	CALL     	4 3 2
	20	[112]	DIV      	5 3 -10	; - 2
	21	[112]	LT       	0 4 5
	22	[112]	JMP      	12	; to 35
	23	[115]	GETTABLE 	4 2 -7	; "pos"
	24	[115]	GETTABLE 	4 4 -8	; "x"
	25	[115]	GETTABLE 	5 2 -7	; "pos"
	26	[115]	GETTABLE 	5 5 -9	; "y"
	27	[115]	LT       	1 5 4
	28	[115]	JMP      	1	; to 30
	29	[115]	LOADBOOL 	4 0 1
	30	[115]	LOADBOOL 	4 1 0
	31	[116]	SELF     	5 0 -11	; "saveSwitchXYSetting"
	32	[116]	MOVE     	7 4
	33	[116]	CALL     	5 3 1
	34	[116]	JMP      	22	; to 57
	35	[119]	SETTABLE 	0 -1 -10	; "curr_probe_step" 2
	36	[120]	SELF     	4 0 -12	; "updateProbeInstruction"
	37	[120]	CALL     	4 2 1
	38	[121]	GETUPVAL 	4 1	; UIManager
	39	[121]	SELF     	4 4 -13	; "setDirty"
	40	[121]	MOVE     	6 0
	41	[121]	CALL     	4 3 1
	42	[122]	JMP      	14	; to 57
	43	[123]	GETTABLE 	3 0 -1	; "curr_probe_step"
	44	[123]	EQ       	0 3 -10	; - 2
	45	[123]	JMP      	11	; to 57
	46	[126]	GETTABLE 	3 2 -7	; "pos"
	47	[126]	GETTABLE 	3 3 -8	; "x"
	48	[126]	GETTABLE 	4 2 -7	; "pos"
	49	[126]	GETTABLE 	4 4 -9	; "y"
	50	[126]	LT       	1 3 4
	51	[126]	JMP      	1	; to 53
	52	[126]	LOADBOOL 	3 0 1
	53	[126]	LOADBOOL 	3 1 0
	54	[127]	SELF     	4 0 -11	; "saveSwitchXYSetting"
	55	[127]	MOVE     	6 3
	56	[127]	CALL     	4 3 1
	57	[129]	RETURN   	0 1
