
main <./frontend/document/koptinterface.lua:0,0> (247 instructions, 988 bytes at 0x7fef57506870)
0+ params, 21 slots, 0 upvalues, 20 locals, 76 constants, 56 functions
	1	[5]	GETGLOBAL	0 -1	; require
	2	[5]	LOADK    	1 -2	; "cache"
	3	[5]	CALL     	0 2 2
	4	[6]	GETGLOBAL	1 -1	; require
	5	[6]	LOADK    	2 -3	; "cacheitem"
	6	[6]	CALL     	1 2 2
	7	[7]	GETGLOBAL	2 -1	; require
	8	[7]	LOADK    	3 -4	; "document/canvascontext"
	9	[7]	CALL     	2 2 2
	10	[8]	GETGLOBAL	3 -1	; require
	11	[8]	LOADK    	4 -5	; "datastorage"
	12	[8]	CALL     	3 2 2
	13	[9]	GETGLOBAL	4 -1	; require
	14	[9]	LOADK    	5 -6	; "dbg"
	15	[9]	CALL     	4 2 2
	16	[10]	GETGLOBAL	5 -1	; require
	17	[10]	LOADK    	6 -7	; "document/document"
	18	[10]	CALL     	5 2 2
	19	[11]	GETGLOBAL	6 -1	; require
	20	[11]	LOADK    	7 -8	; "ui/geometry"
	21	[11]	CALL     	6 2 2
	22	[12]	GETGLOBAL	7 -1	; require
	23	[12]	LOADK    	8 -9	; "ffi/koptcontext"
	24	[12]	CALL     	7 2 2
	25	[13]	GETGLOBAL	8 -1	; require
	26	[13]	LOADK    	9 -10	; "document/tilecacheitem"
	27	[13]	CALL     	8 2 2
	28	[14]	GETGLOBAL	9 -1	; require
	29	[14]	LOADK    	10 -11	; "logger"
	30	[14]	CALL     	9 2 2
	31	[15]	GETGLOBAL	10 -1	; require
	32	[15]	LOADK    	11 -12	; "serialize"
	33	[15]	CALL     	10 2 2
	34	[16]	GETGLOBAL	11 -1	; require
	35	[16]	LOADK    	12 -13	; "ffi/util"
	36	[16]	CALL     	11 2 2
	37	[18]	NEWTABLE 	12 0 6
	38	[19]	SETTABLE 	12 -14 -14	; "ocrengine" "ocrengine"
	39	[20]	SELF     	13 3 -16	; "getDataDir"
	40	[20]	CALL     	13 2 2
	41	[20]	LOADK    	14 -17	; "/data"
	42	[20]	CONCAT   	13 13 14
	43	[20]	SETTABLE 	12 -15 13	; "tessocr_data" -
	44	[21]	SETTABLE 	12 -18 -19	; "ocr_lang" "eng"
	45	[22]	SETTABLE 	12 -20 -21	; "ocr_type" 3
	46	[23]	SETTABLE 	12 -22 -23	; "last_context_size" nil
	47	[24]	SETTABLE 	12 -24 -25	; "default_context_size" 1048576
	48	[27]	SELF     	13 1 -26	; "new"
	49	[27]	NEWTABLE 	15 0 0
	50	[27]	CALL     	13 3 2
	51	[35]	CLOSURE  	14 0	; 0x7fef57507040
	52	[35]	MOVE     	0 12
	53	[35]	MOVE     	0 9
	54	[29]	SETTABLE 	13 -27 14	; "onFree" -
	55	[42]	CLOSURE  	14 1	; 0x7fef57507930
	56	[42]	MOVE     	0 9
	57	[42]	MOVE     	0 10
	58	[42]	MOVE     	0 7
	59	[37]	SETTABLE 	13 -28 14	; "dump" -
	60	[49]	CLOSURE  	14 2	; 0x7fef57507c50
	61	[49]	MOVE     	0 9
	62	[49]	MOVE     	0 10
	63	[49]	MOVE     	0 7
	64	[44]	SETTABLE 	13 -29 14	; "load" -
	65	[51]	SELF     	14 1 -26	; "new"
	66	[51]	NEWTABLE 	16 0 0
	67	[51]	CALL     	14 3 2
	68	[58]	CLOSURE  	15 3	; 0x7fef57507fc0
	69	[58]	MOVE     	0 9
	70	[53]	SETTABLE 	14 -27 15	; "onFree" -
	71	[76]	CLOSURE  	15 4	; 0x7fef57506560
	72	[60]	SETTABLE 	12 -30 15	; "setDefaultConfigurable" -
	73	[86]	CLOSURE  	15 5	; 0x7fef575076a0
	74	[86]	MOVE     	0 9
	75	[86]	MOVE     	0 11
	76	[78]	SETTABLE 	12 -31 15	; "waitForContext" -
	77	[128]	CLOSURE  	15 6	; 0x7fef57509420
	78	[128]	MOVE     	0 7
	79	[128]	MOVE     	0 2
	80	[128]	MOVE     	0 5
	81	[128]	MOVE     	0 4
	82	[91]	SETTABLE 	12 -32 15	; "createContext" -
	83	[136]	CLOSURE  	15 7	; 0x7fef57509800
	84	[136]	MOVE     	0 2
	85	[130]	SETTABLE 	12 -33 15	; "getContextHash" -
	86	[149]	CLOSURE  	15 8	; 0x7fef5750a1b0
	87	[149]	MOVE     	0 5
	88	[138]	SETTABLE 	12 -34 15	; "getPageBBox" -
	89	[182]	CLOSURE  	15 9	; 0x7fef5750a3d0
	90	[182]	MOVE     	0 5
	91	[182]	MOVE     	0 0
	92	[182]	MOVE     	0 1
	93	[154]	SETTABLE 	12 -35 15	; "getAutoBBox" -
	94	[216]	CLOSURE  	15 10	; 0x7fef5750a940
	95	[216]	MOVE     	0 5
	96	[216]	MOVE     	0 0
	97	[216]	MOVE     	0 9
	98	[216]	MOVE     	0 1
	99	[187]	SETTABLE 	12 -36 15	; "getSemiAutoBBox" -
	100	[257]	CLOSURE  	15 11	; 0x7fef57508990
	101	[257]	MOVE     	0 0
	102	[257]	MOVE     	0 13
	103	[257]	MOVE     	0 9
	104	[224]	SETTABLE 	12 -37 15	; "getCachedContext" -
	105	[268]	CLOSURE  	15 12	; 0x7fef57508a90
	106	[268]	MOVE     	0 5
	107	[262]	SETTABLE 	12 -38 15	; "getPageDimensions" -
	108	[277]	CLOSURE  	15 13	; 0x7fef5750c0a0
	109	[277]	MOVE     	0 6
	110	[273]	SETTABLE 	12 -39 15	; "getRFPageDimensions" -
	111	[290]	CLOSURE  	15 14	; 0x7fef5750c220
	112	[290]	MOVE     	0 5
	113	[290]	MOVE     	0 2
	114	[282]	SETTABLE 	12 -40 15	; "getCoverPageImage" -
	115	[300]	CLOSURE  	15 15	; 0x7fef5750cac0
	116	[300]	MOVE     	0 5
	117	[292]	SETTABLE 	12 -41 15	; "renderPage" -
	118	[334]	CLOSURE  	15 16	; 0x7fef5750ce60
	119	[334]	MOVE     	0 0
	120	[334]	MOVE     	0 8
	121	[334]	MOVE     	0 6
	122	[307]	SETTABLE 	12 -42 15	; "renderReflowedPage" -
	123	[381]	CLOSURE  	15 17	; 0x7fef5750a450
	124	[381]	MOVE     	0 0
	125	[381]	MOVE     	0 8
	126	[381]	MOVE     	0 5
	127	[381]	MOVE     	0 9
	128	[381]	MOVE     	0 6
	129	[341]	SETTABLE 	12 -43 15	; "renderOptimizedPage" -
	130	[391]	CLOSURE  	15 18	; 0x7fef5750d310
	131	[391]	MOVE     	0 5
	132	[383]	SETTABLE 	12 -44 15	; "hintPage" -
	133	[420]	CLOSURE  	15 19	; 0x7fef57508480
	134	[420]	MOVE     	0 0
	135	[420]	MOVE     	0 9
	136	[420]	MOVE     	0 13
	137	[402]	SETTABLE 	12 -45 15	; "hintReflowedPage" -
	138	[430]	CLOSURE  	15 20	; 0x7fef5750dde0
	139	[430]	MOVE     	0 5
	140	[422]	SETTABLE 	12 -46 15	; "drawPage" -
	141	[444]	CLOSURE  	15 21	; 0x7fef5750c400
	142	[437]	SETTABLE 	12 -47 15	; "drawContextPage" -
	143	[464]	CLOSURE  	15 22	; 0x7fef5750eb40
	144	[451]	SETTABLE 	12 -48 15	; "getTextBoxes" -
	145	[488]	CLOSURE  	15 23	; 0x7fef5750ebc0
	146	[488]	MOVE     	0 0
	147	[488]	MOVE     	0 1
	148	[469]	SETTABLE 	12 -49 15	; "getReflowedTextBoxes" -
	149	[512]	CLOSURE  	15 24	; 0x7fef5750f060
	150	[512]	MOVE     	0 0
	151	[512]	MOVE     	0 1
	152	[493]	SETTABLE 	12 -50 15	; "getNativeTextBoxes" -
	153	[540]	CLOSURE  	15 25	; 0x7fef5750f530
	154	[540]	MOVE     	0 0
	155	[540]	MOVE     	0 1
	156	[519]	SETTABLE 	12 -51 15	; "getReflowedTextBoxesFromScratch" -
	157	[569]	CLOSURE  	15 26	; 0x7fef5750f990
	158	[569]	MOVE     	0 0
	159	[569]	MOVE     	0 5
	160	[569]	MOVE     	0 1
	161	[547]	SETTABLE 	12 -52 15	; "getNativeTextBoxesFromScratch" -
	162	[600]	CLOSURE  	15 27	; 0x7fef57510300
	163	[600]	MOVE     	0 0
	164	[600]	MOVE     	0 5
	165	[600]	MOVE     	0 2
	166	[600]	MOVE     	0 1
	167	[574]	SETTABLE 	12 -53 15	; "getPageBlock" -
	168	[614]	CLOSURE  	15 28	; 0x7fef5750fd60
	169	[614]	MOVE     	0 0
	170	[614]	MOVE     	0 14
	171	[614]	MOVE     	0 7
	172	[605]	SETTABLE 	12 -54 15	; "getOCRWord" -
	173	[640]	CLOSURE  	15 29	; 0x7fef57511140
	174	[640]	MOVE     	0 0
	175	[640]	MOVE     	0 1
	176	[619]	SETTABLE 	12 -55 15	; "getReflewOCRWord" -
	177	[675]	CLOSURE  	15 30	; 0x7fef57511730
	178	[675]	MOVE     	0 9
	179	[675]	MOVE     	0 0
	180	[675]	MOVE     	0 1
	181	[645]	SETTABLE 	12 -56 15	; "getNativeOCRWord" -
	182	[685]	CLOSURE  	15 31	; 0x7fef57511670
	183	[685]	MOVE     	0 0
	184	[685]	MOVE     	0 14
	185	[685]	MOVE     	0 7
	186	[685]	MOVE     	0 9
	187	[680]	SETTABLE 	12 -57 15	; "getOCRText" -
	188	[720]	CLOSURE  	15 32	; 0x7fef575122a0
	189	[720]	MOVE     	0 6
	190	[687]	SETTABLE 	12 -58 15	; "getClipPageContext" -
	191	[726]	CLOSURE  	15 33	; 0x7fef57512a00
	192	[722]	SETTABLE 	12 -59 15	; "clipPagePNGFile" -
	193	[746]	CLOSURE  	15 34	; 0x7fef57512840
	194	[746]	MOVE     	0 11
	195	[728]	SETTABLE 	12 -60 15	; "clipPagePNGString" -
	196	[757]	CLOSURE  	15 35	; 0x7fef57512900
	197	[767]	CLOSURE  	16 36	; 0x7fef57506e40
	198	[767]	MOVE     	0 15
	199	[779]	CLOSURE  	17 37	; 0x7fef575147d0
	200	[779]	MOVE     	0 16
	201	[800]	CLOSURE  	18 38	; 0x7fef57514c40
	202	[800]	MOVE     	0 17
	203	[800]	MOVE     	0 6
	204	[784]	SETTABLE 	12 -61 18	; "getWordFromBoxes" -
	205	[869]	CLOSURE  	18 39	; 0x7fef57514e90
	206	[869]	MOVE     	0 17
	207	[869]	MOVE     	0 6
	208	[805]	SETTABLE 	12 -62 18	; "getTextFromBoxes" -
	209	[883]	CLOSURE  	18 40	; 0x7fef57514db0
	210	[874]	SETTABLE 	12 -63 18	; "getWordFromPosition" -
	211	[891]	CLOSURE  	18 41	; 0x7fef575153d0
	212	[918]	CLOSURE  	19 42	; 0x7fef57515690
	213	[918]	MOVE     	0 18
	214	[896]	SETTABLE 	12 -64 19	; "getWordFromReflowPosition" -
	215	[932]	CLOSURE  	19 43	; 0x7fef57515d60
	216	[923]	SETTABLE 	12 -65 19	; "getWordFromNativePosition" -
	217	[971]	CLOSURE  	19 44	; 0x7fef575163f0
	218	[971]	MOVE     	0 2
	219	[971]	MOVE     	0 6
	220	[937]	SETTABLE 	12 -66 19	; "getLinkFromPosition" -
	221	[981]	CLOSURE  	19 45	; 0x7fef57516f30
	222	[976]	SETTABLE 	12 -67 19	; "nativeToReflowPosTransform" -
	223	[991]	CLOSURE  	19 46	; 0x7fef57516fb0
	224	[986]	SETTABLE 	12 -68 19	; "reflowToNativePosTransform" -
	225	[1005]	CLOSURE  	19 47	; 0x7fef575179f0
	226	[996]	SETTABLE 	12 -69 19	; "getTextFromPositions" -
	227	[1039]	CLOSURE  	19 48	; 0x7fef575182d0
	228	[1039]	MOVE     	0 18
	229	[1010]	SETTABLE 	12 -70 19	; "getTextFromReflowPositions" -
	230	[1054]	CLOSURE  	19 49	; 0x7fef575180f0
	231	[1044]	SETTABLE 	12 -71 19	; "getTextFromNativePositions" -
	232	[1081]	CLOSURE  	19 50	; 0x7fef575185f0
	233	[1081]	MOVE     	0 9
	234	[1060]	SETTABLE 	12 -72 19	; "getPageBoxesFromPositions" -
	235	[1107]	CLOSURE  	19 51	; 0x7fef57519280
	236	[1086]	SETTABLE 	12 -73 19	; "nativeToPageRectTransform" -
	237	[1155]	CLOSURE  	19 52	; 0x7fef57519840
	238	[1175]	CLOSURE  	20 53	; 0x7fef57519f50
	239	[1175]	MOVE     	0 19
	240	[1157]	SETTABLE 	12 -74 20	; "findAllMatches" -
	241	[1212]	CLOSURE  	20 54	; 0x7fef5751ae00
	242	[1212]	MOVE     	0 9
	243	[1177]	SETTABLE 	12 -75 20	; "findText" -
	244	[1226]	CLOSURE  	20 55	; 0x7fef5751b2e0
	245	[1217]	SETTABLE 	12 -76 20	; "logReflowDuration" -
	246	[1228]	RETURN   	12 2
	247	[1228]	RETURN   	0 1

function <./frontend/document/koptinterface.lua:29,35> (17 instructions, 68 bytes at 0x7fef57507040)
1 param, 4 slots, 2 upvalues, 1 local, 5 constants, 0 functions
	1	[30]	GETTABLE 	1 0 -1	; "kctx"
	2	[30]	GETTABLE 	1 1 -2	; "free"
	3	[30]	TEST     	1 0 0
	4	[30]	JMP      	12	; to 17
	5	[31]	GETUPVAL 	1 0	; KoptInterface
	6	[31]	SELF     	1 1 -3	; "waitForContext"
	7	[31]	GETTABLE 	3 0 -1	; "kctx"
	8	[31]	CALL     	1 3 1
	9	[32]	GETUPVAL 	1 1	; logger
	10	[32]	GETTABLE 	1 1 -4	; "dbg"
	11	[32]	LOADK    	2 -5	; "free koptcontext"
	12	[32]	GETTABLE 	3 0 -1	; "kctx"
	13	[32]	CALL     	1 3 1
	14	[33]	GETTABLE 	1 0 -1	; "kctx"
	15	[33]	SELF     	1 1 -2	; "free"
	16	[33]	CALL     	1 2 1
	17	[35]	RETURN   	0 1

function <./frontend/document/koptinterface.lua:37,42> (21 instructions, 84 bytes at 0x7fef57507930)
2 params, 6 slots, 3 upvalues, 2 locals, 8 constants, 0 functions
	1	[38]	GETTABLE 	2 0 -1	; "kctx"
	2	[38]	SELF     	2 2 -2	; "isPreCache"
	3	[38]	CALL     	2 2 2
	4	[38]	EQ       	0 2 -3	; - 0
	5	[38]	JMP      	15	; to 21
	6	[39]	GETUPVAL 	2 0	; logger
	7	[39]	GETTABLE 	2 2 -4	; "dbg"
	8	[39]	LOADK    	3 -5	; "dumping koptcontext to"
	9	[39]	MOVE     	4 1
	10	[39]	CALL     	2 3 1
	11	[40]	GETUPVAL 	2 1	; serial
	12	[40]	GETTABLE 	2 2 -6	; "dump"
	13	[40]	GETTABLE 	3 0 -7	; "size"
	14	[40]	GETUPVAL 	4 2	; KOPTContext
	15	[40]	GETTABLE 	4 4 -8	; "totable"
	16	[40]	GETTABLE 	5 0 -1	; "kctx"
	17	[40]	CALL     	4 2 2
	18	[40]	MOVE     	5 1
	19	[40]	TAILCALL 	2 4 0
	20	[40]	RETURN   	2 0
	21	[42]	RETURN   	0 1

function <./frontend/document/koptinterface.lua:44,49> (16 instructions, 64 bytes at 0x7fef57507c50)
2 params, 6 slots, 3 upvalues, 4 locals, 6 constants, 0 functions
	1	[45]	GETUPVAL 	2 0	; logger
	2	[45]	GETTABLE 	2 2 -1	; "dbg"
	3	[45]	LOADK    	3 -2	; "loading koptcontext from"
	4	[45]	MOVE     	4 1
	5	[45]	CALL     	2 3 1
	6	[46]	GETUPVAL 	2 1	; serial
	7	[46]	GETTABLE 	2 2 -3	; "load"
	8	[46]	MOVE     	3 1
	9	[46]	CALL     	2 2 3
	10	[47]	SETTABLE 	0 -4 2	; "size" -
	11	[48]	GETUPVAL 	4 2	; KOPTContext
	12	[48]	GETTABLE 	4 4 -6	; "fromtable"
	13	[48]	MOVE     	5 3
	14	[48]	CALL     	4 2 2
	15	[48]	SETTABLE 	0 -5 4	; "kctx" -
	16	[49]	RETURN   	0 1

function <./frontend/document/koptinterface.lua:53,58> (13 instructions, 52 bytes at 0x7fef57507fc0)
1 param, 4 slots, 1 upvalue, 1 local, 4 constants, 0 functions
	1	[54]	GETTABLE 	1 0 -1	; "ocrengine"
	2	[54]	GETTABLE 	1 1 -2	; "freeOCR"
	3	[54]	TEST     	1 0 0
	4	[54]	JMP      	8	; to 13
	5	[55]	GETUPVAL 	1 0	; logger
	6	[55]	GETTABLE 	1 1 -3	; "dbg"
	7	[55]	LOADK    	2 -4	; "free OCREngine"
	8	[55]	GETTABLE 	3 0 -1	; "ocrengine"
	9	[55]	CALL     	1 3 1
	10	[56]	GETTABLE 	1 0 -1	; "ocrengine"
	11	[56]	SELF     	1 1 -2	; "freeOCR"
	12	[56]	CALL     	1 2 1
	13	[58]	RETURN   	0 1

function <./frontend/document/koptinterface.lua:60,76> (30 instructions, 120 bytes at 0x7fef57506560)
2 params, 3 slots, 0 upvalues, 2 locals, 30 constants, 0 functions
	1	[61]	GETGLOBAL	2 -2	; DKOPTREADER_CONFIG_DOC_DEFAULT_LANG_CODE
	2	[61]	SETTABLE 	1 -1 2	; "doc_language" -
	3	[62]	GETGLOBAL	2 -4	; DKOPTREADER_CONFIG_TRIM_PAGE
	4	[62]	SETTABLE 	1 -3 2	; "trim_page" -
	5	[63]	GETGLOBAL	2 -6	; DKOPTREADER_CONFIG_TEXT_WRAP
	6	[63]	SETTABLE 	1 -5 2	; "text_wrap" -
	7	[64]	GETGLOBAL	2 -8	; DKOPTREADER_CONFIG_DETECT_INDENT
	8	[64]	SETTABLE 	1 -7 2	; "detect_indent" -
	9	[65]	GETGLOBAL	2 -10	; DKOPTREADER_CONFIG_MAX_COLUMNS
	10	[65]	SETTABLE 	1 -9 2	; "max_columns" -
	11	[66]	GETGLOBAL	2 -12	; DKOPTREADER_CONFIG_AUTO_STRAIGHTEN
	12	[66]	SETTABLE 	1 -11 2	; "auto_straighten" -
	13	[67]	GETGLOBAL	2 -14	; DKOPTREADER_CONFIG_JUSTIFICATION
	14	[67]	SETTABLE 	1 -13 2	; "justification" -
	15	[68]	SETTABLE 	1 -15 -16	; "writing_direction" 0
	16	[69]	GETGLOBAL	2 -18	; DKOPTREADER_CONFIG_FONT_SIZE
	17	[69]	SETTABLE 	1 -17 2	; "font_size" -
	18	[70]	GETGLOBAL	2 -20	; DKOPTREADER_CONFIG_PAGE_MARGIN
	19	[70]	SETTABLE 	1 -19 2	; "page_margin" -
	20	[71]	GETGLOBAL	2 -22	; DKOPTREADER_CONFIG_RENDER_QUALITY
	21	[71]	SETTABLE 	1 -21 2	; "quality" -
	22	[72]	GETGLOBAL	2 -24	; DKOPTREADER_CONFIG_CONTRAST
	23	[72]	SETTABLE 	1 -23 2	; "contrast" -
	24	[73]	GETGLOBAL	2 -26	; DKOPTREADER_CONFIG_DEFECT_SIZE
	25	[73]	SETTABLE 	1 -25 2	; "defect_size" -
	26	[74]	GETGLOBAL	2 -28	; DKOPTREADER_CONFIG_LINE_SPACING
	27	[74]	SETTABLE 	1 -27 2	; "line_spacing" -
	28	[75]	GETGLOBAL	2 -30	; DKOPTREADER_CONFIG_DEFAULT_WORD_SPACING
	29	[75]	SETTABLE 	1 -29 2	; "word_spacing" -
	30	[76]	RETURN   	0 1

function <./frontend/document/koptinterface.lua:78,86> (17 instructions, 68 bytes at 0x7fef575076a0)
2 params, 4 slots, 2 upvalues, 2 locals, 6 constants, 0 functions
	1	[81]	TEST     	1 0 0
	2	[81]	JMP      	13	; to 16
	3	[81]	SELF     	2 1 -1	; "isPreCache"
	4	[81]	CALL     	2 2 2
	5	[81]	EQ       	0 2 -2	; - 1
	6	[81]	JMP      	9	; to 16
	7	[82]	GETUPVAL 	2 0	; logger
	8	[82]	GETTABLE 	2 2 -3	; "dbg"
	9	[82]	LOADK    	3 -4	; "waiting for background rendering"
	10	[82]	CALL     	2 2 1
	11	[83]	GETUPVAL 	2 1	; util
	12	[83]	GETTABLE 	2 2 -5	; "usleep"
	13	[83]	LOADK    	3 -6	; 100000
	14	[83]	CALL     	2 2 1
	15	[83]	JMP      	-15	; to 1
	16	[85]	RETURN   	1 2
	17	[86]	RETURN   	0 1

function <./frontend/document/koptinterface.lua:91,128> (122 instructions, 488 bytes at 0x7fef57509420)
4 params, 13 slots, 4 upvalues, 8 locals, 52 constants, 0 functions
	1	[94]	GETUPVAL 	4 0	; KOPTContext
	2	[94]	GETTABLE 	4 4 -1	; "new"
	3	[94]	CALL     	4 1 2
	4	[95]	GETUPVAL 	5 1	; CanvasContext
	5	[95]	SELF     	5 5 -2	; "getSize"
	6	[95]	CALL     	5 2 2
	7	[96]	GETTABLE 	6 1 -3	; "configurable"
	8	[96]	GETTABLE 	6 6 -4	; "doc_language"
	9	[97]	EQ       	1 6 -5	; - "chi_sim"
	10	[97]	JMP      	6	; to 17
	11	[97]	EQ       	1 6 -6	; - "chi_tra"
	12	[97]	JMP      	4	; to 17
	13	[98]	EQ       	1 6 -7	; - "jpn"
	14	[98]	JMP      	2	; to 17
	15	[98]	EQ       	0 6 -8	; - "kor"
	16	[98]	JMP      	2	; to 19
	17	[99]	SELF     	7 4 -9	; "setCJKChar"
	18	[99]	CALL     	7 2 1
	19	[101]	SELF     	7 4 -10	; "setLanguage"
	20	[101]	MOVE     	9 6
	21	[101]	CALL     	7 3 1
	22	[102]	SELF     	7 4 -11	; "setTrim"
	23	[102]	GETTABLE 	9 1 -3	; "configurable"
	24	[102]	GETTABLE 	9 9 -12	; "trim_page"
	25	[102]	CALL     	7 3 1
	26	[103]	SELF     	7 4 -13	; "setWrap"
	27	[103]	GETTABLE 	9 1 -3	; "configurable"
	28	[103]	GETTABLE 	9 9 -14	; "text_wrap"
	29	[103]	CALL     	7 3 1
	30	[104]	SELF     	7 4 -15	; "setIndent"
	31	[104]	GETTABLE 	9 1 -3	; "configurable"
	32	[104]	GETTABLE 	9 9 -16	; "detect_indent"
	33	[104]	CALL     	7 3 1
	34	[105]	SELF     	7 4 -17	; "setColumns"
	35	[105]	GETTABLE 	9 1 -3	; "configurable"
	36	[105]	GETTABLE 	9 9 -18	; "max_columns"
	37	[105]	CALL     	7 3 1
	38	[106]	SELF     	7 4 -19	; "setDeviceDim"
	39	[106]	GETTABLE 	9 5 -20	; "w"
	40	[106]	GETTABLE 	10 5 -21	; "h"
	41	[106]	CALL     	7 4 1
	42	[107]	SELF     	7 4 -22	; "setDeviceDPI"
	43	[107]	GETUPVAL 	9 1	; CanvasContext
	44	[107]	SELF     	9 9 -23	; "getDPI"
	45	[107]	CALL     	9 2 0
	46	[107]	CALL     	7 0 1
	47	[108]	SELF     	7 4 -24	; "setStraighten"
	48	[108]	GETTABLE 	9 1 -3	; "configurable"
	49	[108]	GETTABLE 	9 9 -25	; "auto_straighten"
	50	[108]	CALL     	7 3 1
	51	[109]	SELF     	7 4 -26	; "setJustification"
	52	[109]	GETTABLE 	9 1 -3	; "configurable"
	53	[109]	GETTABLE 	9 9 -27	; "justification"
	54	[109]	CALL     	7 3 1
	55	[110]	SELF     	7 4 -28	; "setWritingDirection"
	56	[110]	GETTABLE 	9 1 -3	; "configurable"
	57	[110]	GETTABLE 	9 9 -29	; "writing_direction"
	58	[110]	CALL     	7 3 1
	59	[111]	SELF     	7 4 -30	; "setZoom"
	60	[111]	GETTABLE 	9 1 -3	; "configurable"
	61	[111]	GETTABLE 	9 9 -31	; "font_size"
	62	[111]	CALL     	7 3 1
	63	[112]	SELF     	7 4 -32	; "setMargin"
	64	[112]	GETTABLE 	9 1 -3	; "configurable"
	65	[112]	GETTABLE 	9 9 -33	; "page_margin"
	66	[112]	CALL     	7 3 1
	67	[113]	SELF     	7 4 -34	; "setQuality"
	68	[113]	GETTABLE 	9 1 -3	; "configurable"
	69	[113]	GETTABLE 	9 9 -35	; "quality"
	70	[113]	CALL     	7 3 1
	71	[114]	SELF     	7 4 -36	; "setContrast"
	72	[114]	GETTABLE 	9 1 -3	; "configurable"
	73	[114]	GETTABLE 	9 9 -37	; "contrast"
	74	[114]	CALL     	7 3 1
	75	[115]	SELF     	7 4 -38	; "setDefectSize"
	76	[115]	GETTABLE 	9 1 -3	; "configurable"
	77	[115]	GETTABLE 	9 9 -39	; "defect_size"
	78	[115]	CALL     	7 3 1
	79	[116]	SELF     	7 4 -40	; "setLineSpacing"
	80	[116]	GETTABLE 	9 1 -3	; "configurable"
	81	[116]	GETTABLE 	9 9 -41	; "line_spacing"
	82	[116]	CALL     	7 3 1
	83	[117]	SELF     	7 4 -42	; "setWordSpacing"
	84	[117]	GETTABLE 	9 1 -3	; "configurable"
	85	[117]	GETTABLE 	9 9 -43	; "word_spacing"
	86	[117]	CALL     	7 3 1
	87	[118]	TEST     	3 0 0
	88	[118]	JMP      	26	; to 115
	89	[119]	GETTABLE 	7 3 -44	; "x0"
	90	[119]	GETTABLE 	8 3 -45	; "x1"
	91	[119]	LE       	1 8 7
	92	[119]	JMP      	4	; to 97
	93	[119]	GETTABLE 	7 3 -46	; "y0"
	94	[119]	GETTABLE 	8 3 -47	; "y1"
	95	[119]	LE       	0 8 7
	96	[119]	JMP      	12	; to 109
	97	[120]	GETUPVAL 	7 2	; Document
	98	[120]	GETTABLE 	7 7 -48	; "getNativePageDimensions"
	99	[120]	MOVE     	8 1
	100	[120]	MOVE     	9 2
	101	[120]	CALL     	7 3 2
	102	[121]	LOADK    	8 -49	; 0
	103	[121]	SETTABLE 	3 -46 -49	; "y0" 0
	104	[121]	SETTABLE 	3 -44 8	; "x0" -
	105	[122]	GETTABLE 	8 7 -20	; "w"
	106	[122]	GETTABLE 	9 7 -21	; "h"
	107	[122]	SETTABLE 	3 -47 9	; "y1" -
	108	[122]	SETTABLE 	3 -45 8	; "x1" -
	109	[124]	SELF     	7 4 -50	; "setBBox"
	110	[124]	GETTABLE 	9 3 -44	; "x0"
	111	[124]	GETTABLE 	10 3 -46	; "y0"
	112	[124]	GETTABLE 	11 3 -45	; "x1"
	113	[124]	GETTABLE 	12 3 -47	; "y1"
	114	[124]	CALL     	7 6 1
	115	[126]	GETUPVAL 	7 3	; DEBUG
	116	[126]	GETTABLE 	7 7 -51	; "is_on"
	117	[126]	TEST     	7 0 0
	118	[126]	JMP      	2	; to 121
	119	[126]	SELF     	7 4 -52	; "setDebug"
	120	[126]	CALL     	7 2 1
	121	[127]	RETURN   	4 2
	122	[128]	RETURN   	0 1

function <./frontend/document/koptinterface.lua:130,136> (32 instructions, 128 bytes at 0x7fef57509800)
4 params, 18 slots, 1 upvalue, 7 locals, 12 constants, 0 functions
	1	[131]	GETUPVAL 	4 0	; CanvasContext
	2	[131]	SELF     	4 4 -1	; "getSize"
	3	[131]	CALL     	4 2 2
	4	[132]	GETTABLE 	5 4 -2	; "w"
	5	[132]	LOADK    	6 -3	; "|"
	6	[132]	GETTABLE 	7 4 -4	; "h"
	7	[132]	CONCAT   	5 5 7
	8	[133]	GETTABLE 	6 3 -5	; "x0"
	9	[133]	LOADK    	7 -3	; "|"
	10	[133]	GETTABLE 	8 3 -6	; "y0"
	11	[133]	LOADK    	9 -3	; "|"
	12	[133]	GETTABLE 	10 3 -7	; "x1"
	13	[133]	LOADK    	11 -3	; "|"
	14	[133]	GETTABLE 	12 3 -8	; "y1"
	15	[133]	CONCAT   	6 6 12
	16	[134]	GETTABLE 	7 1 -9	; "file"
	17	[134]	LOADK    	8 -3	; "|"
	18	[134]	GETTABLE 	9 1 -10	; "mod_time"
	19	[134]	LOADK    	10 -3	; "|"
	20	[134]	MOVE     	11 2
	21	[135]	LOADK    	12 -3	; "|"
	22	[135]	GETTABLE 	13 1 -11	; "configurable"
	23	[135]	SELF     	13 13 -12	; "hash"
	24	[135]	LOADK    	15 -3	; "|"
	25	[135]	CALL     	13 3 2
	26	[135]	LOADK    	14 -3	; "|"
	27	[135]	MOVE     	15 6
	28	[135]	LOADK    	16 -3	; "|"
	29	[135]	MOVE     	17 5
	30	[135]	CONCAT   	7 7 17
	31	[135]	RETURN   	7 2
	32	[136]	RETURN   	0 1

function <./frontend/document/koptinterface.lua:138,149> (35 instructions, 140 bytes at 0x7fef5750a1b0)
3 params, 7 slots, 1 upvalue, 3 locals, 8 constants, 0 functions
	1	[139]	GETTABLE 	3 1 -1	; "configurable"
	2	[139]	GETTABLE 	3 3 -2	; "text_wrap"
	3	[139]	EQ       	1 3 -3	; - 1
	4	[139]	JMP      	10	; to 15
	5	[139]	GETTABLE 	3 1 -1	; "configurable"
	6	[139]	GETTABLE 	3 3 -4	; "trim_page"
	7	[139]	EQ       	0 3 -3	; - 1
	8	[139]	JMP      	6	; to 15
	9	[141]	SELF     	3 0 -5	; "getAutoBBox"
	10	[141]	MOVE     	5 1
	11	[141]	MOVE     	6 2
	12	[141]	TAILCALL 	3 4 0
	13	[141]	RETURN   	3 0
	14	[141]	JMP      	20	; to 35
	15	[142]	GETTABLE 	3 1 -1	; "configurable"
	16	[142]	GETTABLE 	3 3 -2	; "text_wrap"
	17	[142]	EQ       	1 3 -3	; - 1
	18	[142]	JMP      	10	; to 29
	19	[142]	GETTABLE 	3 1 -1	; "configurable"
	20	[142]	GETTABLE 	3 3 -4	; "trim_page"
	21	[142]	EQ       	0 3 -6	; - 2
	22	[142]	JMP      	6	; to 29
	23	[144]	SELF     	3 0 -7	; "getSemiAutoBBox"
	24	[144]	MOVE     	5 1
	25	[144]	MOVE     	6 2
	26	[144]	TAILCALL 	3 4 0
	27	[144]	RETURN   	3 0
	28	[144]	JMP      	6	; to 35
	29	[147]	GETUPVAL 	3 0	; Document
	30	[147]	GETTABLE 	3 3 -8	; "getPageBBox"
	31	[147]	MOVE     	4 1
	32	[147]	MOVE     	5 2
	33	[147]	TAILCALL 	3 3 0
	34	[147]	RETURN   	3 0
	35	[149]	RETURN   	0 1

function <./frontend/document/koptinterface.lua:154,182> (82 instructions, 328 bytes at 0x7fef5750a3d0)
3 params, 22 slots, 3 upvalues, 16 locals, 23 constants, 0 functions
	1	[155]	GETUPVAL 	3 0	; Document
	2	[155]	GETTABLE 	3 3 -1	; "getNativePageDimensions"
	3	[155]	MOVE     	4 1
	4	[155]	MOVE     	5 2
	5	[155]	CALL     	3 3 2
	6	[156]	NEWTABLE 	4 0 4
	7	[157]	SETTABLE 	4 -2 -3	; "x0" 0
	8	[157]	SETTABLE 	4 -4 -3	; "y0" 0
	9	[158]	GETTABLE 	5 3 -6	; "w"
	10	[158]	SETTABLE 	4 -5 5	; "x1" -
	11	[159]	GETTABLE 	5 3 -8	; "h"
	12	[159]	SETTABLE 	4 -7 5	; "y1" -
	13	[161]	SELF     	5 0 -9	; "getContextHash"
	14	[161]	MOVE     	7 1
	15	[161]	MOVE     	8 2
	16	[161]	MOVE     	9 4
	17	[161]	CALL     	5 5 2
	18	[162]	LOADK    	6 -10	; "autobbox|"
	19	[162]	MOVE     	7 5
	20	[162]	CONCAT   	6 6 7
	21	[163]	GETUPVAL 	7 1	; Cache
	22	[163]	SELF     	7 7 -11	; "check"
	23	[163]	MOVE     	9 6
	24	[163]	CALL     	7 3 2
	25	[164]	TEST     	7 0 1
	26	[164]	JMP      	53	; to 80
	27	[165]	GETTABLE 	8 1 -12	; "_document"
	28	[165]	SELF     	8 8 -13	; "openPage"
	29	[165]	MOVE     	10 2
	30	[165]	CALL     	8 3 2
	31	[166]	SELF     	9 0 -14	; "createContext"
	32	[166]	MOVE     	11 1
	33	[166]	MOVE     	12 2
	34	[166]	MOVE     	13 4
	35	[166]	CALL     	9 5 2
	36	[167]	SELF     	10 8 -15	; "getPagePix"
	37	[167]	MOVE     	12 9
	38	[167]	CALL     	10 3 1
	39	[168]	SELF     	10 9 -16	; "getAutoBBox"
	40	[168]	CALL     	10 2 5
	41	[169]	GETTABLE 	14 3 -6	; "w"
	42	[169]	GETTABLE 	15 3 -8	; "h"
	43	[170]	SUB      	16 12 10
	44	[170]	DIV      	16 16 14
	45	[170]	LT       	1 -17 16	; 0.1 -
	46	[170]	JMP      	4	; to 51
	47	[170]	SUB      	16 13 11
	48	[170]	DIV      	16 16 15
	49	[170]	LT       	0 -17 16	; 0.1 -
	50	[170]	JMP      	8	; to 59
	51	[171]	MOVE     	16 10
	52	[171]	MOVE     	17 11
	53	[171]	MOVE     	18 12
	54	[171]	SETTABLE 	4 -7 13	; "y1" -
	55	[171]	SETTABLE 	4 -5 18	; "x1" -
	56	[171]	SETTABLE 	4 -4 17	; "y0" -
	57	[171]	SETTABLE 	4 -2 16	; "x0" -
	58	[171]	JMP      	6	; to 65
	59	[173]	GETUPVAL 	16 0	; Document
	60	[173]	GETTABLE 	16 16 -18	; "getPageBBox"
	61	[173]	MOVE     	17 1
	62	[173]	MOVE     	18 2
	63	[173]	CALL     	16 3 2
	64	[173]	MOVE     	4 16
	65	[175]	GETUPVAL 	16 1	; Cache
	66	[175]	SELF     	16 16 -19	; "insert"
	67	[175]	MOVE     	18 6
	68	[175]	GETUPVAL 	19 2	; CacheItem
	69	[175]	SELF     	19 19 -20	; "new"
	70	[175]	NEWTABLE 	21 0 1
	71	[175]	SETTABLE 	21 -21 4	; "autobbox" -
	72	[175]	CALL     	19 3 0
	73	[175]	CALL     	16 0 1
	74	[176]	SELF     	16 8 -22	; "close"
	75	[176]	CALL     	16 2 1
	76	[177]	SELF     	16 9 -23	; "free"
	77	[177]	CALL     	16 2 1
	78	[178]	RETURN   	4 2
	79	[178]	JMP      	2	; to 82
	80	[180]	GETTABLE 	8 7 -21	; "autobbox"
	81	[180]	RETURN   	8 2
	82	[182]	RETURN   	0 1

function <./frontend/document/koptinterface.lua:187,216> (101 instructions, 404 bytes at 0x7fef5750a940)
3 params, 17 slots, 4 upvalues, 11 locals, 25 constants, 0 functions
	1	[189]	GETUPVAL 	3 0	; Document
	2	[189]	GETTABLE 	3 3 -1	; "getPageBBox"
	3	[189]	MOVE     	4 1
	4	[189]	MOVE     	5 2
	5	[189]	CALL     	3 3 2
	6	[190]	SELF     	4 0 -2	; "getContextHash"
	7	[190]	MOVE     	6 1
	8	[190]	MOVE     	7 2
	9	[190]	MOVE     	8 3
	10	[190]	CALL     	4 5 2
	11	[191]	LOADK    	5 -3	; "semiautobbox|"
	12	[191]	MOVE     	6 4
	13	[191]	CONCAT   	5 5 6
	14	[192]	GETUPVAL 	6 1	; Cache
	15	[192]	SELF     	6 6 -4	; "check"
	16	[192]	MOVE     	8 5
	17	[192]	CALL     	6 3 2
	18	[193]	TEST     	6 0 1
	19	[193]	JMP      	79	; to 99
	20	[194]	GETTABLE 	7 1 -5	; "_document"
	21	[194]	SELF     	7 7 -6	; "openPage"
	22	[194]	MOVE     	9 2
	23	[194]	CALL     	7 3 2
	24	[195]	SELF     	8 0 -7	; "createContext"
	25	[195]	MOVE     	10 1
	26	[195]	MOVE     	11 2
	27	[195]	MOVE     	12 3
	28	[195]	CALL     	8 5 2
	29	[196]	NEWTABLE 	9 0 0
	30	[197]	SELF     	10 7 -8	; "getPagePix"
	31	[197]	MOVE     	12 8
	32	[197]	CALL     	10 3 1
	33	[198]	SELF     	10 8 -13	; "getAutoBBox"
	34	[198]	CALL     	10 2 5
	35	[198]	SETTABLE 	9 -12 13	; "y1" -
	36	[198]	SETTABLE 	9 -11 12	; "x1" -
	37	[198]	SETTABLE 	9 -10 11	; "y0" -
	38	[198]	SETTABLE 	9 -9 10	; "x0" -
	39	[199]	GETTABLE 	10 9 -9	; "x0"
	40	[199]	GETTABLE 	11 3 -9	; "x0"
	41	[199]	ADD      	10 10 11
	42	[199]	SETTABLE 	9 -9 10	; "x0" -
	43	[200]	GETTABLE 	10 9 -10	; "y0"
	44	[200]	GETTABLE 	11 3 -10	; "y0"
	45	[200]	ADD      	10 10 11
	46	[200]	SETTABLE 	9 -10 10	; "y0" -
	47	[201]	GETTABLE 	10 9 -11	; "x1"
	48	[201]	GETTABLE 	11 3 -9	; "x0"
	49	[201]	ADD      	10 10 11
	50	[201]	SETTABLE 	9 -11 10	; "x1" -
	51	[202]	GETTABLE 	10 9 -12	; "y1"
	52	[202]	GETTABLE 	11 3 -10	; "y0"
	53	[202]	ADD      	10 10 11
	54	[202]	SETTABLE 	9 -12 10	; "y1" -
	55	[203]	GETUPVAL 	10 2	; logger
	56	[203]	GETTABLE 	10 10 -14	; "dbg"
	57	[203]	LOADK    	11 -15	; "Semi-auto detected bbox"
	58	[203]	MOVE     	12 9
	59	[203]	CALL     	10 3 1
	60	[204]	GETUPVAL 	10 0	; Document
	61	[204]	GETTABLE 	10 10 -16	; "getNativePageDimensions"
	62	[204]	MOVE     	11 1
	63	[204]	MOVE     	12 2
	64	[204]	CALL     	10 3 2
	65	[205]	GETTABLE 	11 9 -11	; "x1"
	66	[205]	GETTABLE 	12 9 -9	; "x0"
	67	[205]	SUB      	11 11 12
	68	[205]	GETTABLE 	12 10 -17	; "w"
	69	[205]	DIV      	11 11 12
	70	[205]	LT       	0 11 -18	; - 0.1
	71	[205]	JMP      	12	; to 84
	72	[205]	GETTABLE 	11 9 -12	; "y1"
	73	[205]	GETTABLE 	12 9 -10	; "y0"
	74	[205]	SUB      	11 11 12
	75	[205]	GETTABLE 	12 10 -19	; "h"
	76	[205]	DIV      	11 11 12
	77	[205]	LT       	0 11 -18	; - 0.1
	78	[205]	JMP      	5	; to 84
	79	[206]	GETUPVAL 	11 2	; logger
	80	[206]	GETTABLE 	11 11 -14	; "dbg"
	81	[206]	LOADK    	12 -20	; "Semi-auto detected bbox too small, using manual bbox"
	82	[206]	CALL     	11 2 1
	83	[207]	MOVE     	9 3
	84	[209]	SELF     	11 7 -21	; "close"
	85	[209]	CALL     	11 2 1
	86	[210]	GETUPVAL 	11 1	; Cache
	87	[210]	SELF     	11 11 -22	; "insert"
	88	[210]	MOVE     	13 5
	89	[210]	GETUPVAL 	14 3	; CacheItem
	90	[210]	SELF     	14 14 -23	; "new"
	91	[210]	NEWTABLE 	16 0 1
	92	[210]	SETTABLE 	16 -24 9	; "semiautobbox" -
	93	[210]	CALL     	14 3 0
	94	[210]	CALL     	11 0 1
	95	[211]	SELF     	11 8 -25	; "free"
	96	[211]	CALL     	11 2 1
	97	[212]	RETURN   	9 2
	98	[212]	JMP      	2	; to 101
	99	[214]	GETTABLE 	7 6 -24	; "semiautobbox"
	100	[214]	RETURN   	7 2
	101	[216]	RETURN   	0 1

function <./frontend/document/koptinterface.lua:224,257> (77 instructions, 308 bytes at 0x7fef57508990)
3 params, 18 slots, 3 upvalues, 14 locals, 26 constants, 0 functions
	1	[225]	SELF     	3 1 -1	; "getPageBBox"
	2	[225]	MOVE     	5 2
	3	[225]	CALL     	3 3 2
	4	[226]	SELF     	4 0 -2	; "getContextHash"
	5	[226]	MOVE     	6 1
	6	[226]	MOVE     	7 2
	7	[226]	MOVE     	8 3
	8	[226]	CALL     	4 5 2
	9	[227]	LOADK    	5 -3	; "kctx|"
	10	[227]	MOVE     	6 4
	11	[227]	CONCAT   	5 5 6
	12	[228]	GETUPVAL 	6 0	; Cache
	13	[228]	SELF     	6 6 -4	; "check"
	14	[228]	MOVE     	8 5
	15	[228]	GETUPVAL 	9 1	; ContextCacheItem
	16	[228]	CALL     	6 4 2
	17	[229]	TEST     	6 0 1
	18	[229]	JMP      	49	; to 68
	19	[231]	SELF     	7 0 -5	; "createContext"
	20	[231]	MOVE     	9 1
	21	[231]	MOVE     	10 2
	22	[231]	MOVE     	11 3
	23	[231]	CALL     	7 5 2
	24	[232]	GETTABLE 	8 1 -6	; "_document"
	25	[232]	SELF     	8 8 -7	; "openPage"
	26	[232]	MOVE     	10 2
	27	[232]	CALL     	8 3 2
	28	[233]	GETUPVAL 	9 2	; logger
	29	[233]	GETTABLE 	9 9 -8	; "dbg"
	30	[233]	LOADK    	10 -9	; "reflowing page"
	31	[233]	MOVE     	11 2
	32	[233]	LOADK    	12 -10	; "in foreground"
	33	[233]	CALL     	9 4 1
	34	[236]	SELF     	9 8 -11	; "reflow"
	35	[236]	MOVE     	11 7
	36	[236]	LOADK    	12 -12	; 0
	37	[236]	CALL     	9 4 1
	38	[237]	SELF     	9 8 -13	; "close"
	39	[237]	CALL     	9 2 1
	40	[241]	SELF     	9 7 -14	; "getPageDim"
	41	[241]	CALL     	9 2 3
	42	[242]	GETUPVAL 	11 2	; logger
	43	[242]	GETTABLE 	11 11 -8	; "dbg"
	44	[242]	LOADK    	12 -15	; "reflowed page"
	45	[242]	MOVE     	13 2
	46	[242]	LOADK    	14 -16	; "fullwidth:"
	47	[242]	MOVE     	15 9
	48	[242]	LOADK    	16 -17	; "fullheight:"
	49	[242]	MOVE     	17 10
	50	[242]	CALL     	11 7 1
	51	[243]	MUL      	11 9 10
	52	[243]	ADD      	11 11 -19	; - 128
	53	[243]	SETTABLE 	0 -18 11	; "last_context_size" -
	54	[244]	GETUPVAL 	11 0	; Cache
	55	[244]	SELF     	11 11 -20	; "insert"
	56	[244]	MOVE     	13 5
	57	[244]	GETUPVAL 	14 1	; ContextCacheItem
	58	[244]	SELF     	14 14 -21	; "new"
	59	[244]	NEWTABLE 	16 0 3
	60	[245]	SETTABLE 	16 -22 -23	; "persistent" true
	61	[246]	GETTABLE 	17 0 -18	; "last_context_size"
	62	[246]	SETTABLE 	16 -24 17	; "size" -
	63	[247]	SETTABLE 	16 -25 7	; "kctx" -
	64	[244]	CALL     	14 3 0
	65	[244]	CALL     	11 0 1
	66	[249]	RETURN   	7 2
	67	[249]	JMP      	9	; to 77
	68	[252]	SELF     	7 0 -26	; "waitForContext"
	69	[252]	GETTABLE 	9 6 -25	; "kctx"
	70	[252]	CALL     	7 3 2
	71	[253]	SELF     	8 7 -14	; "getPageDim"
	72	[253]	CALL     	8 2 3
	73	[254]	MUL      	10 8 9
	74	[254]	ADD      	10 10 -19	; - 128
	75	[254]	SETTABLE 	0 -18 10	; "last_context_size" -
	76	[255]	RETURN   	7 2
	77	[257]	RETURN   	0 1

function <./frontend/document/koptinterface.lua:262,268> (21 instructions, 84 bytes at 0x7fef57508a90)
5 params, 11 slots, 1 upvalue, 5 locals, 5 constants, 0 functions
	1	[263]	GETTABLE 	5 1 -1	; "configurable"
	2	[263]	GETTABLE 	5 5 -2	; "text_wrap"
	3	[263]	EQ       	0 5 -3	; - 1
	4	[263]	JMP      	8	; to 13
	5	[264]	SELF     	5 0 -4	; "getRFPageDimensions"
	6	[264]	MOVE     	7 1
	7	[264]	MOVE     	8 2
	8	[264]	MOVE     	9 3
	9	[264]	MOVE     	10 4
	10	[264]	TAILCALL 	5 6 0
	11	[264]	RETURN   	5 0
	12	[264]	JMP      	8	; to 21
	13	[266]	GETUPVAL 	5 0	; Document
	14	[266]	GETTABLE 	5 5 -5	; "getPageDimensions"
	15	[266]	MOVE     	6 1
	16	[266]	MOVE     	7 2
	17	[266]	MOVE     	8 3
	18	[266]	MOVE     	9 4
	19	[266]	TAILCALL 	5 5 0
	20	[266]	RETURN   	5 0
	21	[268]	RETURN   	0 1

function <./frontend/document/koptinterface.lua:273,277> (14 instructions, 56 bytes at 0x7fef5750c0a0)
5 params, 11 slots, 1 upvalue, 8 locals, 5 constants, 0 functions
	1	[274]	SELF     	5 0 -1	; "getCachedContext"
	2	[274]	MOVE     	7 1
	3	[274]	MOVE     	8 2
	4	[274]	CALL     	5 4 2
	5	[275]	SELF     	6 5 -2	; "getPageDim"
	6	[275]	CALL     	6 2 3
	7	[276]	GETUPVAL 	8 0	; Geom
	8	[276]	SELF     	8 8 -3	; "new"
	9	[276]	NEWTABLE 	10 0 2
	10	[276]	SETTABLE 	10 -4 6	; "w" -
	11	[276]	SETTABLE 	10 -5 7	; "h" -
	12	[276]	TAILCALL 	8 3 0
	13	[276]	RETURN   	8 0
	14	[277]	RETURN   	0 1

function <./frontend/document/koptinterface.lua:282,290> (34 instructions, 136 bytes at 0x7fef5750c220)
2 params, 13 slots, 2 upvalues, 6 locals, 11 constants, 0 functions
	1	[283]	GETUPVAL 	2 0	; Document
	2	[283]	GETTABLE 	2 2 -1	; "getNativePageDimensions"
	3	[283]	MOVE     	3 1
	4	[283]	LOADK    	4 -2	; 1
	5	[283]	CALL     	2 3 2
	6	[284]	GETUPVAL 	3 1	; CanvasContext
	7	[284]	SELF     	3 3 -3	; "getSize"
	8	[284]	CALL     	3 2 2
	9	[285]	GETGLOBAL	4 -4	; math
	10	[285]	GETTABLE 	4 4 -5	; "min"
	11	[285]	GETTABLE 	5 3 -6	; "w"
	12	[285]	GETTABLE 	6 2 -6	; "w"
	13	[285]	DIV      	5 5 6
	14	[285]	GETTABLE 	6 3 -7	; "h"
	15	[285]	GETTABLE 	7 2 -7	; "h"
	16	[285]	DIV      	6 6 7
	17	[285]	CALL     	4 3 2
	18	[286]	GETUPVAL 	5 0	; Document
	19	[286]	GETTABLE 	5 5 -8	; "renderPage"
	20	[286]	MOVE     	6 1
	21	[286]	LOADK    	7 -2	; 1
	22	[286]	LOADNIL  	8 8
	23	[286]	MOVE     	9 4
	24	[286]	LOADK    	10 -9	; 0
	25	[286]	LOADK    	11 -2	; 1
	26	[286]	LOADK    	12 -9	; 0
	27	[286]	CALL     	5 8 2
	28	[287]	TEST     	5 0 0
	29	[287]	JMP      	4	; to 34
	30	[288]	GETTABLE 	6 5 -10	; "bb"
	31	[288]	SELF     	6 6 -11	; "copy"
	32	[288]	TAILCALL 	6 2 0
	33	[288]	RETURN   	6 0
	34	[290]	RETURN   	0 1

function <./frontend/document/koptinterface.lua:292,300> (40 instructions, 160 bytes at 0x7fef5750cac0)
8 params, 16 slots, 1 upvalue, 8 locals, 7 constants, 0 functions
	1	[293]	GETTABLE 	8 1 -1	; "configurable"
	2	[293]	GETTABLE 	8 8 -2	; "text_wrap"
	3	[293]	EQ       	0 8 -3	; - 1
	4	[293]	JMP      	10	; to 15
	5	[294]	SELF     	8 0 -4	; "renderReflowedPage"
	6	[294]	MOVE     	10 1
	7	[294]	MOVE     	11 2
	8	[294]	MOVE     	12 3
	9	[294]	MOVE     	13 4
	10	[294]	MOVE     	14 5
	11	[294]	MOVE     	15 7
	12	[294]	TAILCALL 	8 8 0
	13	[294]	RETURN   	8 0
	14	[294]	JMP      	25	; to 40
	15	[295]	GETTABLE 	8 1 -1	; "configurable"
	16	[295]	GETTABLE 	8 8 -5	; "page_opt"
	17	[295]	EQ       	0 8 -3	; - 1
	18	[295]	JMP      	10	; to 29
	19	[296]	SELF     	8 0 -6	; "renderOptimizedPage"
	20	[296]	MOVE     	10 1
	21	[296]	MOVE     	11 2
	22	[296]	MOVE     	12 3
	23	[296]	MOVE     	13 4
	24	[296]	MOVE     	14 5
	25	[296]	MOVE     	15 7
	26	[296]	TAILCALL 	8 8 0
	27	[296]	RETURN   	8 0
	28	[296]	JMP      	11	; to 40
	29	[298]	GETUPVAL 	8 0	; Document
	30	[298]	GETTABLE 	8 8 -7	; "renderPage"
	31	[298]	MOVE     	9 1
	32	[298]	MOVE     	10 2
	33	[298]	MOVE     	11 3
	34	[298]	MOVE     	12 4
	35	[298]	MOVE     	13 5
	36	[298]	MOVE     	14 6
	37	[298]	MOVE     	15 7
	38	[298]	TAILCALL 	8 8 0
	39	[298]	RETURN   	8 0
	40	[300]	RETURN   	0 1

function <./frontend/document/koptinterface.lua:307,334> (61 instructions, 244 bytes at 0x7fef5750ce60)
7 params, 20 slots, 3 upvalues, 15 locals, 21 constants, 0 functions
	1	[308]	SETTABLE 	1 -1 6	; "render_mode" -
	2	[309]	SELF     	7 1 -2	; "getPageBBox"
	3	[309]	MOVE     	9 2
	4	[309]	CALL     	7 3 2
	5	[310]	SELF     	8 0 -3	; "getContextHash"
	6	[310]	MOVE     	10 1
	7	[310]	MOVE     	11 2
	8	[310]	MOVE     	12 7
	9	[310]	CALL     	8 5 2
	10	[311]	LOADK    	9 -4	; "renderpg|"
	11	[311]	MOVE     	10 8
	12	[311]	CONCAT   	9 9 10
	13	[313]	GETUPVAL 	10 0	; Cache
	14	[313]	SELF     	10 10 -5	; "check"
	15	[313]	MOVE     	12 9
	16	[313]	CALL     	10 3 2
	17	[314]	TEST     	10 0 1
	18	[314]	JMP      	41	; to 60
	19	[316]	SELF     	11 0 -6	; "getCachedContext"
	20	[316]	MOVE     	13 1
	21	[316]	MOVE     	14 2
	22	[316]	CALL     	11 4 2
	23	[317]	SELF     	12 11 -7	; "getPageDim"
	24	[317]	CALL     	12 2 3
	25	[318]	GETUPVAL 	14 0	; Cache
	26	[318]	SELF     	14 14 -8	; "willAccept"
	27	[318]	MUL      	16 12 13
	28	[318]	DIV      	16 16 -9	; - 2
	29	[318]	CALL     	14 3 2
	30	[318]	TEST     	14 0 1
	31	[318]	JMP      	3	; to 35
	32	[320]	GETGLOBAL	14 -10	; error
	33	[320]	LOADK    	15 -11	; "aborting, since we don't have enough cache for this page"
	34	[320]	CALL     	14 2 1
	35	[323]	GETUPVAL 	14 1	; TileCacheItem
	36	[323]	SELF     	14 14 -12	; "new"
	37	[323]	NEWTABLE 	16 0 3
	38	[324]	MUL      	17 12 13
	39	[324]	ADD      	17 17 -14	; - 64
	40	[324]	SETTABLE 	16 -13 17	; "size" -
	41	[325]	GETUPVAL 	17 2	; Geom
	42	[325]	SELF     	17 17 -12	; "new"
	43	[325]	NEWTABLE 	19 0 2
	44	[325]	SETTABLE 	19 -16 12	; "w" -
	45	[325]	SETTABLE 	19 -17 13	; "h" -
	46	[325]	CALL     	17 3 2
	47	[325]	SETTABLE 	16 -15 17	; "excerpt" -
	48	[326]	SETTABLE 	16 -18 2	; "pageno" -
	49	[323]	CALL     	14 3 2
	50	[328]	SELF     	15 11 -20	; "dstToBlitBuffer"
	51	[328]	CALL     	15 2 2
	52	[328]	SETTABLE 	14 -19 15	; "bb" -
	53	[329]	GETUPVAL 	15 0	; Cache
	54	[329]	SELF     	15 15 -21	; "insert"
	55	[329]	MOVE     	17 9
	56	[329]	MOVE     	18 14
	57	[329]	CALL     	15 4 1
	58	[330]	RETURN   	14 2
	59	[330]	JMP      	1	; to 61
	60	[332]	RETURN   	10 2
	61	[334]	RETURN   	0 1

function <./frontend/document/koptinterface.lua:341,381> (90 instructions, 360 bytes at 0x7fef5750a450)
7 params, 23 slots, 5 upvalues, 18 locals, 36 constants, 0 functions
	1	[342]	SETTABLE 	1 -1 6	; "render_mode" -
	2	[343]	SELF     	7 1 -2	; "getPageBBox"
	3	[343]	MOVE     	9 2
	4	[343]	CALL     	7 3 2
	5	[344]	SELF     	8 0 -3	; "getContextHash"
	6	[344]	MOVE     	10 1
	7	[344]	MOVE     	11 2
	8	[344]	MOVE     	12 7
	9	[344]	CALL     	8 5 2
	10	[345]	LOADK    	9 -4	; "renderoptpg|"
	11	[345]	MOVE     	10 8
	12	[345]	MOVE     	11 4
	13	[345]	CONCAT   	9 9 11
	14	[347]	GETUPVAL 	10 0	; Cache
	15	[347]	SELF     	10 10 -5	; "check"
	16	[347]	MOVE     	12 9
	17	[347]	GETUPVAL 	13 1	; TileCacheItem
	18	[347]	CALL     	10 4 2
	19	[348]	TEST     	10 0 1
	20	[348]	JMP      	68	; to 89
	21	[349]	GETUPVAL 	11 2	; Document
	22	[349]	GETTABLE 	11 11 -6	; "getNativePageDimensions"
	23	[349]	MOVE     	12 1
	24	[349]	MOVE     	13 2
	25	[349]	CALL     	11 3 2
	26	[350]	NEWTABLE 	12 0 4
	27	[351]	SETTABLE 	12 -7 -8	; "x0" 0
	28	[351]	SETTABLE 	12 -9 -8	; "y0" 0
	29	[352]	GETTABLE 	13 11 -11	; "w"
	30	[352]	SETTABLE 	12 -10 13	; "x1" -
	31	[353]	GETTABLE 	13 11 -13	; "h"
	32	[353]	SETTABLE 	12 -12 13	; "y1" -
	33	[355]	SELF     	13 0 -14	; "createContext"
	34	[355]	MOVE     	15 1
	35	[355]	MOVE     	16 2
	36	[355]	MOVE     	17 12
	37	[355]	CALL     	13 5 2
	38	[356]	GETTABLE 	14 1 -15	; "_document"
	39	[356]	SELF     	14 14 -16	; "openPage"
	40	[356]	MOVE     	16 2
	41	[356]	CALL     	14 3 2
	42	[357]	SELF     	15 13 -17	; "setZoom"
	43	[357]	MOVE     	17 4
	44	[357]	CALL     	15 3 1
	45	[358]	SELF     	15 14 -18	; "getPagePix"
	46	[358]	MOVE     	17 13
	47	[358]	CALL     	15 3 1
	48	[359]	SELF     	15 14 -19	; "close"
	49	[359]	CALL     	15 2 1
	50	[360]	GETUPVAL 	15 3	; logger
	51	[360]	GETTABLE 	15 15 -20	; "dbg"
	52	[360]	LOADK    	16 -21	; "optimizing page"
	53	[360]	MOVE     	17 2
	54	[360]	CALL     	15 3 1
	55	[361]	SELF     	15 13 -22	; "optimizePage"
	56	[361]	CALL     	15 2 1
	57	[362]	SELF     	15 13 -23	; "getPageDim"
	58	[362]	CALL     	15 2 3
	59	[364]	GETUPVAL 	17 1	; TileCacheItem
	60	[364]	SELF     	17 17 -24	; "new"
	61	[364]	NEWTABLE 	19 0 4
	62	[365]	SETTABLE 	19 -25 -26	; "persistent" true
	63	[366]	MUL      	20 15 16
	64	[366]	ADD      	20 20 -28	; - 64
	65	[366]	SETTABLE 	19 -27 20	; "size" -
	66	[367]	GETUPVAL 	20 4	; Geom
	67	[367]	SELF     	20 20 -24	; "new"
	68	[367]	NEWTABLE 	22 0 4
	69	[368]	SETTABLE 	22 -30 -8	; "x" 0
	70	[368]	SETTABLE 	22 -31 -8	; "y" 0
	71	[369]	SETTABLE 	22 -11 15	; "w" -
	72	[370]	SETTABLE 	22 -13 16	; "h" -
	73	[367]	CALL     	20 3 2
	74	[371]	SETTABLE 	19 -29 20	; "excerpt" -
	75	[372]	SETTABLE 	19 -32 2	; "pageno" -
	76	[364]	CALL     	17 3 2
	77	[374]	SELF     	18 13 -34	; "dstToBlitBuffer"
	78	[374]	CALL     	18 2 2
	79	[374]	SETTABLE 	17 -33 18	; "bb" -
	80	[375]	SELF     	18 13 -35	; "free"
	81	[375]	CALL     	18 2 1
	82	[376]	GETUPVAL 	18 0	; Cache
	83	[376]	SELF     	18 18 -36	; "insert"
	84	[376]	MOVE     	20 9
	85	[376]	MOVE     	21 17
	86	[376]	CALL     	18 4 1
	87	[377]	RETURN   	17 2
	88	[377]	JMP      	1	; to 90
	89	[379]	RETURN   	10 2
	90	[381]	RETURN   	0 1

function <./frontend/document/koptinterface.lua:383,391> (37 instructions, 148 bytes at 0x7fef5750d310)
7 params, 16 slots, 1 upvalue, 7 locals, 7 constants, 0 functions
	1	[384]	GETTABLE 	7 1 -1	; "configurable"
	2	[384]	GETTABLE 	7 7 -2	; "text_wrap"
	3	[384]	EQ       	0 7 -3	; - 1
	4	[384]	JMP      	9	; to 14
	5	[385]	SELF     	7 0 -4	; "hintReflowedPage"
	6	[385]	MOVE     	9 1
	7	[385]	MOVE     	10 2
	8	[385]	MOVE     	11 3
	9	[385]	MOVE     	12 4
	10	[385]	MOVE     	13 5
	11	[385]	MOVE     	14 6
	12	[385]	CALL     	7 8 1
	13	[385]	JMP      	23	; to 37
	14	[386]	GETTABLE 	7 1 -1	; "configurable"
	15	[386]	GETTABLE 	7 7 -5	; "page_opt"
	16	[386]	EQ       	0 7 -3	; - 1
	17	[386]	JMP      	10	; to 28
	18	[387]	SELF     	7 0 -6	; "renderOptimizedPage"
	19	[387]	MOVE     	9 1
	20	[387]	MOVE     	10 2
	21	[387]	LOADNIL  	11 11
	22	[387]	MOVE     	12 3
	23	[387]	MOVE     	13 4
	24	[387]	MOVE     	14 5
	25	[387]	MOVE     	15 6
	26	[387]	CALL     	7 9 1
	27	[387]	JMP      	9	; to 37
	28	[389]	GETUPVAL 	7 0	; Document
	29	[389]	GETTABLE 	7 7 -7	; "hintPage"
	30	[389]	MOVE     	8 1
	31	[389]	MOVE     	9 2
	32	[389]	MOVE     	10 3
	33	[389]	MOVE     	11 4
	34	[389]	MOVE     	12 5
	35	[389]	MOVE     	13 6
	36	[389]	CALL     	7 7 1
	37	[391]	RETURN   	0 1

function <./frontend/document/koptinterface.lua:402,420> (55 instructions, 220 bytes at 0x7fef57508480)
7 params, 20 slots, 3 upvalues, 13 locals, 20 constants, 0 functions
	1	[403]	SELF     	7 1 -1	; "getPageBBox"
	2	[403]	MOVE     	9 2
	3	[403]	CALL     	7 3 2
	4	[404]	SELF     	8 0 -2	; "getContextHash"
	5	[404]	MOVE     	10 1
	6	[404]	MOVE     	11 2
	7	[404]	MOVE     	12 7
	8	[404]	CALL     	8 5 2
	9	[405]	LOADK    	9 -3	; "kctx|"
	10	[405]	MOVE     	10 8
	11	[405]	CONCAT   	9 9 10
	12	[406]	GETUPVAL 	10 0	; Cache
	13	[406]	SELF     	10 10 -4	; "check"
	14	[406]	MOVE     	12 9
	15	[406]	CALL     	10 3 2
	16	[407]	TEST     	10 0 1
	17	[407]	JMP      	37	; to 55
	18	[408]	SELF     	11 0 -5	; "createContext"
	19	[408]	MOVE     	13 1
	20	[408]	MOVE     	14 2
	21	[408]	MOVE     	15 7
	22	[408]	CALL     	11 5 2
	23	[409]	GETTABLE 	12 1 -6	; "_document"
	24	[409]	SELF     	12 12 -7	; "openPage"
	25	[409]	MOVE     	14 2
	26	[409]	CALL     	12 3 2
	27	[410]	GETUPVAL 	13 1	; logger
	28	[410]	GETTABLE 	13 13 -8	; "dbg"
	29	[410]	LOADK    	14 -9	; "hinting page"
	30	[410]	MOVE     	15 2
	31	[410]	LOADK    	16 -10	; "in background"
	32	[410]	CALL     	13 4 1
	33	[412]	SELF     	13 11 -11	; "setPreCache"
	34	[412]	CALL     	13 2 1
	35	[413]	SELF     	13 12 -12	; "reflow"
	36	[413]	MOVE     	15 11
	37	[413]	LOADK    	16 -13	; 0
	38	[413]	CALL     	13 4 1
	39	[414]	SELF     	13 12 -14	; "close"
	40	[414]	CALL     	13 2 1
	41	[415]	GETUPVAL 	13 0	; Cache
	42	[415]	SELF     	13 13 -15	; "insert"
	43	[415]	MOVE     	15 9
	44	[415]	GETUPVAL 	16 2	; ContextCacheItem
	45	[415]	SELF     	16 16 -16	; "new"
	46	[415]	NEWTABLE 	18 0 2
	47	[416]	GETTABLE 	19 0 -18	; "last_context_size"
	48	[416]	TEST     	19 0 1
	49	[416]	JMP      	1	; to 51
	50	[416]	GETTABLE 	19 0 -19	; "default_context_size"
	51	[416]	SETTABLE 	18 -17 19	; "size" -
	52	[417]	SETTABLE 	18 -20 11	; "kctx" -
	53	[415]	CALL     	16 3 0
	54	[415]	CALL     	13 0 1
	55	[420]	RETURN   	0 1

function <./frontend/document/koptinterface.lua:422,430> (46 instructions, 184 bytes at 0x7fef5750dde0)
11 params, 22 slots, 1 upvalue, 11 locals, 6 constants, 0 functions
	1	[423]	GETTABLE 	11 1 -1	; "configurable"
	2	[423]	GETTABLE 	11 11 -2	; "text_wrap"
	3	[423]	EQ       	0 11 -3	; - 1
	4	[423]	JMP      	12	; to 17
	5	[424]	SELF     	11 0 -4	; "drawContextPage"
	6	[424]	MOVE     	13 1
	7	[424]	MOVE     	14 2
	8	[424]	MOVE     	15 3
	9	[424]	MOVE     	16 4
	10	[424]	MOVE     	17 5
	11	[424]	MOVE     	18 6
	12	[424]	MOVE     	19 7
	13	[424]	MOVE     	20 8
	14	[424]	MOVE     	21 10
	15	[424]	CALL     	11 11 1
	16	[424]	JMP      	29	; to 46
	17	[425]	GETTABLE 	11 1 -1	; "configurable"
	18	[425]	GETTABLE 	11 11 -5	; "page_opt"
	19	[425]	EQ       	0 11 -3	; - 1
	20	[425]	JMP      	12	; to 33
	21	[426]	SELF     	11 0 -4	; "drawContextPage"
	22	[426]	MOVE     	13 1
	23	[426]	MOVE     	14 2
	24	[426]	MOVE     	15 3
	25	[426]	MOVE     	16 4
	26	[426]	MOVE     	17 5
	27	[426]	MOVE     	18 6
	28	[426]	MOVE     	19 7
	29	[426]	MOVE     	20 8
	30	[426]	MOVE     	21 10
	31	[426]	CALL     	11 11 1
	32	[426]	JMP      	13	; to 46
	33	[428]	GETUPVAL 	11 0	; Document
	34	[428]	GETTABLE 	11 11 -6	; "drawPage"
	35	[428]	MOVE     	12 1
	36	[428]	MOVE     	13 2
	37	[428]	MOVE     	14 3
	38	[428]	MOVE     	15 4
	39	[428]	MOVE     	16 5
	40	[428]	MOVE     	17 6
	41	[428]	MOVE     	18 7
	42	[428]	MOVE     	19 8
	43	[428]	MOVE     	20 9
	44	[428]	MOVE     	21 10
	45	[428]	CALL     	11 11 1
	46	[430]	RETURN   	0 1

function <./frontend/document/koptinterface.lua:437,444> (24 instructions, 96 bytes at 0x7fef5750c400)
10 params, 20 slots, 0 upvalues, 11 locals, 8 constants, 0 functions
	1	[438]	SELF     	10 0 -1	; "renderPage"
	2	[438]	MOVE     	12 1
	3	[438]	MOVE     	13 6
	4	[438]	MOVE     	14 5
	5	[438]	MOVE     	15 7
	6	[438]	MOVE     	16 8
	7	[438]	MOVE     	17 9
	8	[438]	CALL     	10 8 2
	9	[439]	SELF     	11 2 -2	; "blitFrom"
	10	[439]	GETTABLE 	13 10 -3	; "bb"
	11	[440]	MOVE     	14 3
	12	[440]	MOVE     	15 4
	13	[441]	GETTABLE 	16 5 -4	; "x"
	14	[441]	GETTABLE 	17 10 -5	; "excerpt"
	15	[441]	GETTABLE 	17 17 -4	; "x"
	16	[441]	SUB      	16 16 17
	17	[442]	GETTABLE 	17 5 -6	; "y"
	18	[442]	GETTABLE 	18 10 -5	; "excerpt"
	19	[442]	GETTABLE 	18 18 -6	; "y"
	20	[442]	SUB      	17 17 18
	21	[443]	GETTABLE 	18 5 -7	; "w"
	22	[443]	GETTABLE 	19 5 -8	; "h"
	23	[439]	CALL     	11 9 1
	24	[444]	RETURN   	0 1

function <./frontend/document/koptinterface.lua:451,464> (30 instructions, 120 bytes at 0x7fef5750eb40)
3 params, 8 slots, 0 upvalues, 4 locals, 7 constants, 0 functions
	1	[452]	SELF     	3 1 -1	; "getPageTextBoxes"
	2	[452]	MOVE     	5 2
	3	[452]	CALL     	3 3 2
	4	[453]	TEST     	3 0 0
	5	[453]	JMP      	9	; to 15
	6	[453]	LEN      	4 3
	7	[453]	LT       	0 -2 4	; 1 -
	8	[453]	JMP      	6	; to 15
	9	[453]	GETTABLE 	4 1 -3	; "configurable"
	10	[453]	GETTABLE 	4 4 -4	; "forced_ocr"
	11	[453]	EQ       	1 4 -2	; - 1
	12	[453]	JMP      	2	; to 15
	13	[454]	RETURN   	3 2
	14	[454]	JMP      	15	; to 30
	15	[458]	GETTABLE 	4 1 -3	; "configurable"
	16	[458]	GETTABLE 	4 4 -5	; "text_wrap"
	17	[458]	EQ       	0 4 -2	; - 1
	18	[458]	JMP      	6	; to 25
	19	[459]	SELF     	4 0 -6	; "getNativeTextBoxes"
	20	[459]	MOVE     	6 1
	21	[459]	MOVE     	7 2
	22	[459]	TAILCALL 	4 4 0
	23	[459]	RETURN   	4 0
	24	[459]	JMP      	5	; to 30
	25	[461]	SELF     	4 0 -7	; "getNativeTextBoxesFromScratch"
	26	[461]	MOVE     	6 1
	27	[461]	MOVE     	7 2
	28	[461]	TAILCALL 	4 4 0
	29	[461]	RETURN   	4 0
	30	[464]	RETURN   	0 1

function <./frontend/document/koptinterface.lua:469,488> (53 instructions, 212 bytes at 0x7fef5750ebc0)
3 params, 18 slots, 2 upvalues, 12 locals, 14 constants, 0 functions
	1	[470]	SELF     	3 1 -1	; "getPageBBox"
	2	[470]	MOVE     	5 2
	3	[470]	CALL     	3 3 2
	4	[471]	SELF     	4 0 -2	; "getContextHash"
	5	[471]	MOVE     	6 1
	6	[471]	MOVE     	7 2
	7	[471]	MOVE     	8 3
	8	[471]	CALL     	4 5 2
	9	[472]	LOADK    	5 -3	; "rfpgboxes|"
	10	[472]	MOVE     	6 4
	11	[472]	CONCAT   	5 5 6
	12	[473]	GETUPVAL 	6 0	; Cache
	13	[473]	SELF     	6 6 -4	; "check"
	14	[473]	MOVE     	8 5
	15	[473]	CALL     	6 3 2
	16	[474]	TEST     	6 0 1
	17	[474]	JMP      	33	; to 51
	18	[475]	LOADK    	7 -5	; "kctx|"
	19	[475]	MOVE     	8 4
	20	[475]	CONCAT   	7 7 8
	21	[476]	GETUPVAL 	8 0	; Cache
	22	[476]	SELF     	8 8 -4	; "check"
	23	[476]	MOVE     	10 7
	24	[476]	CALL     	8 3 2
	25	[476]	MOVE     	6 8
	26	[477]	TEST     	6 0 0
	27	[477]	JMP      	25	; to 53
	28	[478]	SELF     	8 0 -6	; "waitForContext"
	29	[478]	GETTABLE 	10 6 -7	; "kctx"
	30	[478]	CALL     	8 3 2
	31	[480]	SELF     	9 8 -8	; "getPageDim"
	32	[480]	CALL     	9 2 3
	33	[481]	SELF     	11 8 -9	; "getReflowedWordBoxes"
	34	[481]	LOADK    	13 -10	; "dst"
	35	[481]	LOADK    	14 -11	; 0
	36	[481]	LOADK    	15 -11	; 0
	37	[481]	MOVE     	16 9
	38	[481]	MOVE     	17 10
	39	[481]	CALL     	11 7 2
	40	[482]	GETUPVAL 	12 0	; Cache
	41	[482]	SELF     	12 12 -12	; "insert"
	42	[482]	MOVE     	14 5
	43	[482]	GETUPVAL 	15 1	; CacheItem
	44	[482]	SELF     	15 15 -13	; "new"
	45	[482]	NEWTABLE 	17 0 1
	46	[482]	SETTABLE 	17 -14 11	; "rfpgboxes" -
	47	[482]	CALL     	15 3 0
	48	[482]	CALL     	12 0 1
	49	[483]	RETURN   	11 2
	50	[484]	JMP      	2	; to 53
	51	[486]	GETTABLE 	7 6 -14	; "rfpgboxes"
	52	[486]	RETURN   	7 2
	53	[488]	RETURN   	0 1

function <./frontend/document/koptinterface.lua:493,512> (53 instructions, 212 bytes at 0x7fef5750f060)
3 params, 18 slots, 2 upvalues, 12 locals, 14 constants, 0 functions
	1	[494]	SELF     	3 1 -1	; "getPageBBox"
	2	[494]	MOVE     	5 2
	3	[494]	CALL     	3 3 2
	4	[495]	SELF     	4 0 -2	; "getContextHash"
	5	[495]	MOVE     	6 1
	6	[495]	MOVE     	7 2
	7	[495]	MOVE     	8 3
	8	[495]	CALL     	4 5 2
	9	[496]	LOADK    	5 -3	; "nativepgboxes|"
	10	[496]	MOVE     	6 4
	11	[496]	CONCAT   	5 5 6
	12	[497]	GETUPVAL 	6 0	; Cache
	13	[497]	SELF     	6 6 -4	; "check"
	14	[497]	MOVE     	8 5
	15	[497]	CALL     	6 3 2
	16	[498]	TEST     	6 0 1
	17	[498]	JMP      	33	; to 51
	18	[499]	LOADK    	7 -5	; "kctx|"
	19	[499]	MOVE     	8 4
	20	[499]	CONCAT   	7 7 8
	21	[500]	GETUPVAL 	8 0	; Cache
	22	[500]	SELF     	8 8 -4	; "check"
	23	[500]	MOVE     	10 7
	24	[500]	CALL     	8 3 2
	25	[500]	MOVE     	6 8
	26	[501]	TEST     	6 0 0
	27	[501]	JMP      	25	; to 53
	28	[502]	SELF     	8 0 -6	; "waitForContext"
	29	[502]	GETTABLE 	10 6 -7	; "kctx"
	30	[502]	CALL     	8 3 2
	31	[504]	SELF     	9 8 -8	; "getPageDim"
	32	[504]	CALL     	9 2 3
	33	[505]	SELF     	11 8 -9	; "getNativeWordBoxes"
	34	[505]	LOADK    	13 -10	; "dst"
	35	[505]	LOADK    	14 -11	; 0
	36	[505]	LOADK    	15 -11	; 0
	37	[505]	MOVE     	16 9
	38	[505]	MOVE     	17 10
	39	[505]	CALL     	11 7 2
	40	[506]	GETUPVAL 	12 0	; Cache
	41	[506]	SELF     	12 12 -12	; "insert"
	42	[506]	MOVE     	14 5
	43	[506]	GETUPVAL 	15 1	; CacheItem
	44	[506]	SELF     	15 15 -13	; "new"
	45	[506]	NEWTABLE 	17 0 1
	46	[506]	SETTABLE 	17 -14 11	; "nativepgboxes" -
	47	[506]	CALL     	15 3 0
	48	[506]	CALL     	12 0 1
	49	[507]	RETURN   	11 2
	50	[508]	JMP      	2	; to 53
	51	[510]	GETTABLE 	7 6 -14	; "nativepgboxes"
	52	[510]	RETURN   	7 2
	53	[512]	RETURN   	0 1

function <./frontend/document/koptinterface.lua:519,540> (62 instructions, 248 bytes at 0x7fef5750f530)
3 params, 19 slots, 2 upvalues, 13 locals, 17 constants, 0 functions
	1	[520]	SELF     	3 1 -1	; "getPageBBox"
	2	[520]	MOVE     	5 2
	3	[520]	CALL     	3 3 2
	4	[521]	SELF     	4 0 -2	; "getContextHash"
	5	[521]	MOVE     	6 1
	6	[521]	MOVE     	7 2
	7	[521]	MOVE     	8 3
	8	[521]	CALL     	4 5 2
	9	[522]	LOADK    	5 -3	; "scratchrfpgboxes|"
	10	[522]	MOVE     	6 4
	11	[522]	CONCAT   	5 5 6
	12	[523]	GETUPVAL 	6 0	; Cache
	13	[523]	SELF     	6 6 -4	; "check"
	14	[523]	MOVE     	8 5
	15	[523]	CALL     	6 3 2
	16	[524]	TEST     	6 0 1
	17	[524]	JMP      	42	; to 60
	18	[525]	LOADK    	7 -5	; "kctx|"
	19	[525]	MOVE     	8 4
	20	[525]	CONCAT   	7 7 8
	21	[526]	GETUPVAL 	8 0	; Cache
	22	[526]	SELF     	8 8 -4	; "check"
	23	[526]	MOVE     	10 7
	24	[526]	CALL     	8 3 2
	25	[526]	MOVE     	6 8
	26	[527]	TEST     	6 0 0
	27	[527]	JMP      	34	; to 62
	28	[528]	SELF     	8 0 -6	; "waitForContext"
	29	[528]	GETTABLE 	10 6 -7	; "kctx"
	30	[528]	CALL     	8 3 2
	31	[529]	SELF     	9 8 -8	; "getPageDim"
	32	[529]	CALL     	9 2 3
	33	[530]	SELF     	11 0 -9	; "createContext"
	34	[530]	MOVE     	13 1
	35	[530]	MOVE     	14 2
	36	[530]	CALL     	11 4 2
	37	[531]	SELF     	12 11 -10	; "copyDestBMP"
	38	[531]	MOVE     	14 8
	39	[531]	CALL     	12 3 1
	40	[532]	SELF     	12 11 -11	; "getNativeWordBoxes"
	41	[532]	LOADK    	14 -12	; "dst"
	42	[532]	LOADK    	15 -13	; 0
	43	[532]	LOADK    	16 -13	; 0
	44	[532]	MOVE     	17 9
	45	[532]	MOVE     	18 10
	46	[532]	CALL     	12 7 2
	47	[533]	GETUPVAL 	13 0	; Cache
	48	[533]	SELF     	13 13 -14	; "insert"
	49	[533]	MOVE     	15 5
	50	[533]	GETUPVAL 	16 1	; CacheItem
	51	[533]	SELF     	16 16 -15	; "new"
	52	[533]	NEWTABLE 	18 0 1
	53	[533]	SETTABLE 	18 -16 12	; "scratchrfpgboxes" -
	54	[533]	CALL     	16 3 0
	55	[533]	CALL     	13 0 1
	56	[534]	SELF     	13 11 -17	; "free"
	57	[534]	CALL     	13 2 1
	58	[535]	RETURN   	12 2
	59	[536]	JMP      	2	; to 62
	60	[538]	GETTABLE 	7 6 -16	; "scratchrfpgboxes"
	61	[538]	RETURN   	7 2
	62	[540]	RETURN   	0 1

function <./frontend/document/koptinterface.lua:547,569> (63 instructions, 252 bytes at 0x7fef5750f990)
3 params, 16 slots, 3 upvalues, 10 locals, 25 constants, 0 functions
	1	[548]	LOADK    	3 -1	; "scratchnativepgboxes|"
	2	[548]	GETTABLE 	4 1 -2	; "file"
	3	[548]	LOADK    	5 -3	; "|"
	4	[548]	MOVE     	6 2
	5	[548]	CONCAT   	3 3 6
	6	[549]	GETUPVAL 	4 0	; Cache
	7	[549]	SELF     	4 4 -4	; "check"
	8	[549]	MOVE     	6 3
	9	[549]	CALL     	4 3 2
	10	[550]	TEST     	4 0 1
	11	[550]	JMP      	49	; to 61
	12	[551]	GETUPVAL 	5 1	; Document
	13	[551]	GETTABLE 	5 5 -5	; "getNativePageDimensions"
	14	[551]	MOVE     	6 1
	15	[551]	MOVE     	7 2
	16	[551]	CALL     	5 3 2
	17	[552]	NEWTABLE 	6 0 4
	18	[553]	SETTABLE 	6 -6 -7	; "x0" 0
	19	[553]	SETTABLE 	6 -8 -7	; "y0" 0
	20	[554]	GETTABLE 	7 5 -10	; "w"
	21	[554]	SETTABLE 	6 -9 7	; "x1" -
	22	[555]	GETTABLE 	7 5 -12	; "h"
	23	[555]	SETTABLE 	6 -11 7	; "y1" -
	24	[557]	SELF     	7 0 -13	; "createContext"
	25	[557]	MOVE     	9 1
	26	[557]	MOVE     	10 2
	27	[557]	MOVE     	11 6
	28	[557]	CALL     	7 5 2
	29	[558]	SELF     	8 7 -14	; "setZoom"
	30	[558]	LOADK    	10 -15	; 1
	31	[558]	CALL     	8 3 1
	32	[559]	GETTABLE 	8 1 -16	; "_document"
	33	[559]	SELF     	8 8 -17	; "openPage"
	34	[559]	MOVE     	10 2
	35	[559]	CALL     	8 3 2
	36	[560]	SELF     	9 8 -18	; "getPagePix"
	37	[560]	MOVE     	11 7
	38	[560]	CALL     	9 3 1
	39	[561]	SELF     	9 7 -19	; "getNativeWordBoxes"
	40	[561]	LOADK    	11 -20	; "src"
	41	[561]	LOADK    	12 -7	; 0
	42	[561]	LOADK    	13 -7	; 0
	43	[561]	GETTABLE 	14 5 -10	; "w"
	44	[561]	GETTABLE 	15 5 -12	; "h"
	45	[561]	CALL     	9 7 2
	46	[562]	GETUPVAL 	10 0	; Cache
	47	[562]	SELF     	10 10 -21	; "insert"
	48	[562]	MOVE     	12 3
	49	[562]	GETUPVAL 	13 2	; CacheItem
	50	[562]	SELF     	13 13 -22	; "new"
	51	[562]	NEWTABLE 	15 0 1
	52	[562]	SETTABLE 	15 -23 9	; "scratchnativepgboxes" -
	53	[562]	CALL     	13 3 0
	54	[562]	CALL     	10 0 1
	55	[563]	SELF     	10 8 -24	; "close"
	56	[563]	CALL     	10 2 1
	57	[564]	SELF     	10 7 -25	; "free"
	58	[564]	CALL     	10 2 1
	59	[565]	RETURN   	9 2
	60	[565]	JMP      	2	; to 63
	61	[567]	GETTABLE 	5 4 -23	; "scratchnativepgboxes"
	62	[567]	RETURN   	5 2
	63	[569]	RETURN   	0 1

function <./frontend/document/koptinterface.lua:574,600> (75 instructions, 300 bytes at 0x7fef57510300)
5 params, 20 slots, 4 upvalues, 14 locals, 26 constants, 0 functions
	1	[576]	SELF     	6 1 -1	; "getPageBBox"
	2	[576]	MOVE     	8 2
	3	[576]	CALL     	6 3 2
	4	[577]	SELF     	7 0 -2	; "getContextHash"
	5	[577]	MOVE     	9 1
	6	[577]	MOVE     	10 2
	7	[577]	MOVE     	11 6
	8	[577]	CALL     	7 5 2
	9	[578]	LOADK    	8 -3	; "pageblocks|"
	10	[578]	MOVE     	9 7
	11	[578]	CONCAT   	8 8 9
	12	[579]	GETUPVAL 	9 0	; Cache
	13	[579]	SELF     	9 9 -4	; "check"
	14	[579]	MOVE     	11 8
	15	[579]	CALL     	9 3 2
	16	[580]	TEST     	9 0 1
	17	[580]	JMP      	51	; to 69
	18	[581]	GETUPVAL 	10 1	; Document
	19	[581]	GETTABLE 	10 10 -5	; "getNativePageDimensions"
	20	[581]	MOVE     	11 1
	21	[581]	MOVE     	12 2
	22	[581]	CALL     	10 3 2
	23	[582]	NEWTABLE 	11 0 4
	24	[583]	SETTABLE 	11 -6 -7	; "x0" 0
	25	[583]	SETTABLE 	11 -8 -7	; "y0" 0
	26	[584]	GETTABLE 	12 10 -10	; "w"
	27	[584]	SETTABLE 	11 -9 12	; "x1" -
	28	[585]	GETTABLE 	12 10 -12	; "h"
	29	[585]	SETTABLE 	11 -11 12	; "y1" -
	30	[587]	SELF     	12 0 -13	; "createContext"
	31	[587]	MOVE     	14 1
	32	[587]	MOVE     	15 2
	33	[587]	MOVE     	16 11
	34	[587]	CALL     	12 5 2
	35	[589]	SELF     	13 12 -14	; "setZoom"
	36	[589]	GETUPVAL 	15 2	; CanvasContext
	37	[589]	SELF     	15 15 -15	; "getWidth"
	38	[589]	CALL     	15 2 2
	39	[589]	GETTABLE 	16 10 -10	; "w"
	40	[589]	DIV      	15 15 16
	41	[589]	MUL      	15 15 -16	; - 300
	42	[589]	GETUPVAL 	16 2	; CanvasContext
	43	[589]	SELF     	16 16 -17	; "getDPI"
	44	[589]	CALL     	16 2 2
	45	[589]	DIV      	15 15 16
	46	[589]	CALL     	13 3 1
	47	[590]	GETTABLE 	13 1 -18	; "_document"
	48	[590]	SELF     	13 13 -19	; "openPage"
	49	[590]	MOVE     	15 2
	50	[590]	CALL     	13 3 2
	51	[591]	SELF     	14 13 -20	; "getPagePix"
	52	[591]	MOVE     	16 12
	53	[591]	CALL     	14 3 1
	54	[592]	SELF     	14 12 -21	; "findPageBlocks"
	55	[592]	CALL     	14 2 1
	56	[593]	GETUPVAL 	14 0	; Cache
	57	[593]	SELF     	14 14 -22	; "insert"
	58	[593]	MOVE     	16 8
	59	[593]	GETUPVAL 	17 3	; CacheItem
	60	[593]	SELF     	17 17 -23	; "new"
	61	[593]	NEWTABLE 	19 0 1
	62	[593]	SETTABLE 	19 -24 12	; "kctx" -
	63	[593]	CALL     	17 3 0
	64	[593]	CALL     	14 0 1
	65	[594]	SELF     	14 13 -25	; "close"
	66	[594]	CALL     	14 2 1
	67	[595]	MOVE     	5 12
	68	[595]	JMP      	1	; to 70
	69	[597]	GETTABLE 	5 9 -24	; "kctx"
	70	[599]	SELF     	10 5 -26	; "getPageBlock"
	71	[599]	MOVE     	12 3
	72	[599]	MOVE     	13 4
	73	[599]	TAILCALL 	10 4 0
	74	[599]	RETURN   	10 0
	75	[600]	RETURN   	0 1

function <./frontend/document/koptinterface.lua:605,614> (36 instructions, 144 bytes at 0x7fef5750fd60)
4 params, 11 slots, 3 upvalues, 4 locals, 10 constants, 0 functions
	1	[606]	GETUPVAL 	4 0	; Cache
	2	[606]	SELF     	4 4 -1	; "check"
	3	[606]	GETTABLE 	6 0 -2	; "ocrengine"
	4	[606]	CALL     	4 3 2
	5	[606]	TEST     	4 0 1
	6	[606]	JMP      	12	; to 19
	7	[607]	GETUPVAL 	4 0	; Cache
	8	[607]	SELF     	4 4 -3	; "insert"
	9	[607]	GETTABLE 	6 0 -2	; "ocrengine"
	10	[607]	GETUPVAL 	7 1	; OCREngine
	11	[607]	SELF     	7 7 -4	; "new"
	12	[607]	NEWTABLE 	9 0 1
	13	[607]	GETUPVAL 	10 2	; KOPTContext
	14	[607]	GETTABLE 	10 10 -4	; "new"
	15	[607]	CALL     	10 1 2
	16	[607]	SETTABLE 	9 -2 10	; "ocrengine" -
	17	[607]	CALL     	7 3 0
	18	[607]	CALL     	4 0 1
	19	[609]	GETTABLE 	4 1 -5	; "configurable"
	20	[609]	GETTABLE 	4 4 -6	; "text_wrap"
	21	[609]	EQ       	0 4 -7	; - 1
	22	[609]	JMP      	7	; to 30
	23	[610]	SELF     	4 0 -8	; "getReflewOCRWord"
	24	[610]	MOVE     	6 1
	25	[610]	MOVE     	7 2
	26	[610]	GETTABLE 	8 3 -9	; "sbox"
	27	[610]	TAILCALL 	4 5 0
	28	[610]	RETURN   	4 0
	29	[610]	JMP      	6	; to 36
	30	[612]	SELF     	4 0 -10	; "getNativeOCRWord"
	31	[612]	MOVE     	6 1
	32	[612]	MOVE     	7 2
	33	[612]	GETTABLE 	8 3 -9	; "sbox"
	34	[612]	TAILCALL 	4 5 0
	35	[612]	RETURN   	4 0
	36	[614]	RETURN   	0 1

function <./frontend/document/koptinterface.lua:619,640> (65 instructions, 260 bytes at 0x7fef57511140)
4 params, 23 slots, 2 upvalues, 12 locals, 24 constants, 0 functions
	1	[620]	GETTABLE 	4 1 -2	; "configurable"
	2	[620]	GETTABLE 	4 4 -3	; "doc_language"
	3	[620]	SETTABLE 	0 -1 4	; "ocr_lang" -
	4	[621]	SELF     	4 1 -4	; "getPageBBox"
	5	[621]	MOVE     	6 2
	6	[621]	CALL     	4 3 2
	7	[622]	SELF     	5 0 -5	; "getContextHash"
	8	[622]	MOVE     	7 1
	9	[622]	MOVE     	8 2
	10	[622]	MOVE     	9 4
	11	[622]	CALL     	5 5 2
	12	[623]	LOADK    	6 -6	; "rfocrword|"
	13	[623]	MOVE     	7 5
	14	[623]	GETTABLE 	8 3 -7	; "x"
	15	[623]	GETTABLE 	9 3 -8	; "y"
	16	[623]	GETTABLE 	10 3 -9	; "w"
	17	[623]	GETTABLE 	11 3 -10	; "h"
	18	[623]	CONCAT   	6 6 11
	19	[624]	GETUPVAL 	7 0	; Cache
	20	[624]	SELF     	7 7 -11	; "check"
	21	[624]	MOVE     	9 6
	22	[624]	CALL     	7 3 2
	23	[625]	TEST     	7 0 1
	24	[625]	JMP      	38	; to 63
	25	[626]	LOADK    	8 -12	; "kctx|"
	26	[626]	MOVE     	9 5
	27	[626]	CONCAT   	8 8 9
	28	[627]	GETUPVAL 	9 0	; Cache
	29	[627]	SELF     	9 9 -11	; "check"
	30	[627]	MOVE     	11 8
	31	[627]	CALL     	9 3 2
	32	[627]	MOVE     	7 9
	33	[628]	TEST     	7 0 0
	34	[628]	JMP      	30	; to 65
	35	[629]	SELF     	9 0 -13	; "waitForContext"
	36	[629]	GETTABLE 	11 7 -14	; "kctx"
	37	[629]	CALL     	9 3 2
	38	[630]	GETGLOBAL	10 -15	; pcall
	39	[631]	GETTABLE 	11 9 -16	; "getTOCRWord"
	40	[631]	MOVE     	12 9
	41	[631]	LOADK    	13 -17	; "dst"
	42	[632]	GETTABLE 	14 3 -7	; "x"
	43	[632]	GETTABLE 	15 3 -8	; "y"
	44	[632]	GETTABLE 	16 3 -9	; "w"
	45	[632]	GETTABLE 	17 3 -10	; "h"
	46	[633]	GETTABLE 	18 0 -18	; "tessocr_data"
	47	[633]	GETTABLE 	19 0 -1	; "ocr_lang"
	48	[633]	GETTABLE 	20 0 -19	; "ocr_type"
	49	[633]	LOADK    	21 -20	; 0
	50	[633]	LOADK    	22 -21	; 1
	51	[630]	CALL     	10 13 3
	52	[634]	GETUPVAL 	12 0	; Cache
	53	[634]	SELF     	12 12 -22	; "insert"
	54	[634]	MOVE     	14 6
	55	[634]	GETUPVAL 	15 1	; CacheItem
	56	[634]	SELF     	15 15 -23	; "new"
	57	[634]	NEWTABLE 	17 0 1
	58	[634]	SETTABLE 	17 -24 11	; "rfocrword" -
	59	[634]	CALL     	15 3 0
	60	[634]	CALL     	12 0 1
	61	[635]	RETURN   	11 2
	62	[636]	JMP      	2	; to 65
	63	[638]	GETTABLE 	8 7 -24	; "rfocrword"
	64	[638]	RETURN   	8 2
	65	[640]	RETURN   	0 1

function <./frontend/document/koptinterface.lua:645,675> (115 instructions, 460 bytes at 0x7fef57511730)
4 params, 24 slots, 3 upvalues, 13 locals, 40 constants, 0 functions
	1	[646]	GETTABLE 	4 1 -2	; "configurable"
	2	[646]	GETTABLE 	4 4 -3	; "doc_language"
	3	[646]	SETTABLE 	0 -1 4	; "ocr_lang" -
	4	[647]	LOADK    	4 -4	; "ocrword|"
	5	[647]	GETTABLE 	5 1 -5	; "file"
	6	[647]	LOADK    	6 -6	; "|"
	7	[647]	MOVE     	7 2
	8	[647]	GETTABLE 	8 3 -7	; "x"
	9	[647]	GETTABLE 	9 3 -8	; "y"
	10	[647]	GETTABLE 	10 3 -9	; "w"
	11	[647]	GETTABLE 	11 3 -10	; "h"
	12	[647]	CONCAT   	4 4 11
	13	[648]	GETUPVAL 	5 0	; logger
	14	[648]	GETTABLE 	5 5 -11	; "dbg"
	15	[648]	LOADK    	6 -12	; "hash"
	16	[648]	MOVE     	7 4
	17	[648]	CALL     	5 3 1
	18	[649]	GETUPVAL 	5 1	; Cache
	19	[649]	SELF     	5 5 -13	; "check"
	20	[649]	MOVE     	7 4
	21	[649]	CALL     	5 3 2
	22	[650]	TEST     	5 0 1
	23	[650]	JMP      	89	; to 113
	24	[651]	NEWTABLE 	6 0 4
	25	[652]	GETTABLE 	7 3 -7	; "x"
	26	[652]	GETGLOBAL	8 -15	; math
	27	[652]	GETTABLE 	8 8 -16	; "floor"
	28	[652]	GETTABLE 	9 3 -10	; "h"
	29	[652]	MUL      	9 9 -17	; - 0.3
	30	[652]	CALL     	8 2 2
	31	[652]	SUB      	7 7 8
	32	[652]	SETTABLE 	6 -14 7	; "x0" -
	33	[653]	GETTABLE 	7 3 -8	; "y"
	34	[653]	GETGLOBAL	8 -15	; math
	35	[653]	GETTABLE 	8 8 -16	; "floor"
	36	[653]	GETTABLE 	9 3 -10	; "h"
	37	[653]	MUL      	9 9 -17	; - 0.3
	38	[653]	CALL     	8 2 2
	39	[653]	SUB      	7 7 8
	40	[653]	SETTABLE 	6 -18 7	; "y0" -
	41	[654]	GETTABLE 	7 3 -7	; "x"
	42	[654]	GETTABLE 	8 3 -9	; "w"
	43	[654]	ADD      	7 7 8
	44	[654]	GETGLOBAL	8 -15	; math
	45	[654]	GETTABLE 	8 8 -16	; "floor"
	46	[654]	GETTABLE 	9 3 -10	; "h"
	47	[654]	MUL      	9 9 -17	; - 0.3
	48	[654]	CALL     	8 2 2
	49	[654]	ADD      	7 7 8
	50	[654]	SETTABLE 	6 -19 7	; "x1" -
	51	[655]	GETTABLE 	7 3 -8	; "y"
	52	[655]	GETTABLE 	8 3 -10	; "h"
	53	[655]	ADD      	7 7 8
	54	[655]	GETGLOBAL	8 -15	; math
	55	[655]	GETTABLE 	8 8 -16	; "floor"
	56	[655]	GETTABLE 	9 3 -10	; "h"
	57	[655]	MUL      	9 9 -17	; - 0.3
	58	[655]	CALL     	8 2 2
	59	[655]	ADD      	7 7 8
	60	[655]	SETTABLE 	6 -20 7	; "y1" -
	61	[657]	SELF     	7 0 -21	; "createContext"
	62	[657]	MOVE     	9 1
	63	[657]	MOVE     	10 2
	64	[657]	MOVE     	11 6
	65	[657]	CALL     	7 5 2
	66	[658]	SELF     	8 7 -22	; "setZoom"
	67	[658]	GETTABLE 	10 3 -10	; "h"
	68	[658]	DIV      	10 -23 10	; 30 -
	69	[658]	CALL     	8 3 1
	70	[659]	GETTABLE 	8 1 -24	; "_document"
	71	[659]	SELF     	8 8 -25	; "openPage"
	72	[659]	MOVE     	10 2
	73	[659]	CALL     	8 3 2
	74	[660]	SELF     	9 8 -26	; "getPagePix"
	75	[660]	MOVE     	11 7
	76	[660]	CALL     	9 3 1
	77	[662]	SELF     	9 7 -27	; "getPageDim"
	78	[662]	CALL     	9 2 3
	79	[663]	GETGLOBAL	11 -28	; pcall
	80	[664]	GETTABLE 	12 7 -29	; "getTOCRWord"
	81	[664]	MOVE     	13 7
	82	[664]	LOADK    	14 -30	; "src"
	83	[665]	LOADK    	15 -31	; 0
	84	[665]	LOADK    	16 -31	; 0
	85	[665]	MOVE     	17 9
	86	[665]	MOVE     	18 10
	87	[666]	GETTABLE 	19 0 -32	; "tessocr_data"
	88	[666]	GETTABLE 	20 0 -1	; "ocr_lang"
	89	[666]	GETTABLE 	21 0 -33	; "ocr_type"
	90	[666]	LOADK    	22 -31	; 0
	91	[666]	LOADK    	23 -34	; 1
	92	[663]	CALL     	11 13 3
	93	[667]	GETUPVAL 	13 1	; Cache
	94	[667]	SELF     	13 13 -35	; "insert"
	95	[667]	MOVE     	15 4
	96	[667]	GETUPVAL 	16 2	; CacheItem
	97	[667]	SELF     	16 16 -36	; "new"
	98	[667]	NEWTABLE 	18 0 1
	99	[667]	SETTABLE 	18 -37 12	; "ocrword" -
	100	[667]	CALL     	16 3 0
	101	[667]	CALL     	13 0 1
	102	[668]	GETUPVAL 	13 0	; logger
	103	[668]	GETTABLE 	13 13 -11	; "dbg"
	104	[668]	LOADK    	14 -38	; "word"
	105	[668]	MOVE     	15 12
	106	[668]	CALL     	13 3 1
	107	[669]	SELF     	13 8 -39	; "close"
	108	[669]	CALL     	13 2 1
	109	[670]	SELF     	13 7 -40	; "free"
	110	[670]	CALL     	13 2 1
	111	[671]	RETURN   	12 2
	112	[671]	JMP      	2	; to 115
	113	[673]	GETTABLE 	6 5 -37	; "ocrword"
	114	[673]	RETURN   	6 2
	115	[675]	RETURN   	0 1

function <./frontend/document/koptinterface.lua:680,685> (23 instructions, 92 bytes at 0x7fef57511670)
4 params, 11 slots, 4 upvalues, 4 locals, 6 constants, 0 functions
	1	[681]	GETUPVAL 	4 0	; Cache
	2	[681]	SELF     	4 4 -1	; "check"
	3	[681]	GETTABLE 	6 0 -2	; "ocrengine"
	4	[681]	CALL     	4 3 2
	5	[681]	TEST     	4 0 1
	6	[681]	JMP      	12	; to 19
	7	[682]	GETUPVAL 	4 0	; Cache
	8	[682]	SELF     	4 4 -3	; "insert"
	9	[682]	GETTABLE 	6 0 -2	; "ocrengine"
	10	[682]	GETUPVAL 	7 1	; OCREngine
	11	[682]	SELF     	7 7 -4	; "new"
	12	[682]	NEWTABLE 	9 0 1
	13	[682]	GETUPVAL 	10 2	; KOPTContext
	14	[682]	GETTABLE 	10 10 -4	; "new"
	15	[682]	CALL     	10 1 2
	16	[682]	SETTABLE 	9 -2 10	; "ocrengine" -
	17	[682]	CALL     	7 3 0
	18	[682]	CALL     	4 0 1
	19	[684]	GETUPVAL 	4 3	; logger
	20	[684]	GETTABLE 	4 4 -5	; "info"
	21	[684]	LOADK    	5 -6	; "Not implemented yet"
	22	[684]	CALL     	4 2 1
	23	[685]	RETURN   	0 1

function <./frontend/document/koptinterface.lua:687,720> (117 instructions, 468 bytes at 0x7fef575122a0)
6 params, 18 slots, 1 upvalue, 17 locals, 24 constants, 0 functions
	1	[688]	GETGLOBAL	6 -1	; assert
	2	[688]	GETTABLE 	7 2 -2	; "page"
	3	[688]	GETTABLE 	8 3 -2	; "page"
	4	[688]	EQ       	1 7 8
	5	[688]	JMP      	1	; to 7
	6	[688]	LOADBOOL 	7 0 1
	7	[688]	LOADBOOL 	7 1 0
	8	[688]	CALL     	6 2 1
	9	[689]	GETGLOBAL	6 -1	; assert
	10	[689]	GETTABLE 	7 2 -3	; "zoom"
	11	[689]	GETTABLE 	8 3 -3	; "zoom"
	12	[689]	EQ       	1 7 8
	13	[689]	JMP      	1	; to 15
	14	[689]	LOADBOOL 	7 0 1
	15	[689]	LOADBOOL 	7 1 0
	16	[689]	CALL     	6 2 1
	17	[690]	LOADNIL  	6 6
	18	[691]	TEST     	4 0 0
	19	[691]	JMP      	31	; to 51
	20	[691]	LEN      	7 4
	21	[691]	LT       	0 -4 7	; 0 -
	22	[691]	JMP      	28	; to 51
	23	[692]	GETTABLE 	7 4 -5	; 1
	24	[693]	GETUPVAL 	8 0	; Geom
	25	[693]	SELF     	8 8 -6	; "new"
	26	[693]	NEWTABLE 	10 0 4
	27	[694]	GETTABLE 	11 7 -7	; "x"
	28	[694]	SETTABLE 	10 -7 11	; "x" -
	29	[694]	GETTABLE 	11 7 -8	; "y"
	30	[694]	SETTABLE 	10 -8 11	; "y" -
	31	[695]	GETTABLE 	11 7 -9	; "w"
	32	[695]	SETTABLE 	10 -9 11	; "w" -
	33	[695]	GETTABLE 	11 7 -10	; "h"
	34	[695]	SETTABLE 	10 -10 11	; "h" -
	35	[693]	CALL     	8 3 2
	36	[696]	MOVE     	6 8
	37	[697]	GETGLOBAL	8 -11	; ipairs
	38	[697]	MOVE     	9 4
	39	[697]	CALL     	8 2 4
	40	[697]	JMP      	7	; to 48
	41	[698]	SELF     	13 6 -12	; "combine"
	42	[698]	GETUPVAL 	15 0	; Geom
	43	[698]	SELF     	15 15 -6	; "new"
	44	[698]	MOVE     	17 12
	45	[698]	CALL     	15 3 0
	46	[698]	CALL     	13 0 2
	47	[698]	MOVE     	6 13
	48	[697]	TFORLOOP 	8 2
	49	[698]	JMP      	-9	; to 41
	50	[699]	JMP      	36	; to 87
	51	[701]	GETTABLE 	7 2 -3	; "zoom"
	52	[701]	TEST     	7 0 1
	53	[701]	JMP      	1	; to 55
	54	[701]	LOADK    	7 -5	; 1
	55	[702]	NEWTABLE 	8 0 4
	56	[703]	GETGLOBAL	9 -13	; math
	57	[703]	GETTABLE 	9 9 -14	; "min"
	58	[703]	GETTABLE 	10 2 -7	; "x"
	59	[703]	GETTABLE 	11 3 -7	; "x"
	60	[703]	CALL     	9 3 2
	61	[703]	DIV      	9 9 7
	62	[703]	SETTABLE 	8 -7 9	; "x" -
	63	[704]	GETGLOBAL	9 -13	; math
	64	[704]	GETTABLE 	9 9 -14	; "min"
	65	[704]	GETTABLE 	10 2 -8	; "y"
	66	[704]	GETTABLE 	11 3 -8	; "y"
	67	[704]	CALL     	9 3 2
	68	[704]	DIV      	9 9 7
	69	[704]	SETTABLE 	8 -8 9	; "y" -
	70	[705]	GETGLOBAL	9 -13	; math
	71	[705]	GETTABLE 	9 9 -15	; "abs"
	72	[705]	GETTABLE 	10 2 -7	; "x"
	73	[705]	GETTABLE 	11 3 -7	; "x"
	74	[705]	SUB      	10 10 11
	75	[705]	CALL     	9 2 2
	76	[705]	DIV      	9 9 7
	77	[705]	SETTABLE 	8 -9 9	; "w" -
	78	[706]	GETGLOBAL	9 -13	; math
	79	[706]	GETTABLE 	9 9 -15	; "abs"
	80	[706]	GETTABLE 	10 2 -8	; "y"
	81	[706]	GETTABLE 	11 3 -8	; "y"
	82	[706]	SUB      	10 10 11
	83	[706]	CALL     	9 2 2
	84	[706]	DIV      	9 9 7
	85	[706]	SETTABLE 	8 -10 9	; "h" -
	86	[707]	MOVE     	6 8
	87	[710]	NEWTABLE 	7 0 4
	88	[711]	GETTABLE 	8 6 -7	; "x"
	89	[711]	SETTABLE 	7 -16 8	; "x0" -
	90	[711]	GETTABLE 	8 6 -8	; "y"
	91	[711]	SETTABLE 	7 -17 8	; "y0" -
	92	[712]	GETTABLE 	8 6 -7	; "x"
	93	[712]	GETTABLE 	9 6 -9	; "w"
	94	[712]	ADD      	8 8 9
	95	[712]	SETTABLE 	7 -18 8	; "x1" -
	96	[713]	GETTABLE 	8 6 -8	; "y"
	97	[713]	GETTABLE 	9 6 -10	; "h"
	98	[713]	ADD      	8 8 9
	99	[713]	SETTABLE 	7 -19 8	; "y1" -
	100	[715]	SELF     	8 0 -20	; "createContext"
	101	[715]	MOVE     	10 1
	102	[715]	GETTABLE 	11 2 -2	; "page"
	103	[715]	MOVE     	12 7
	104	[715]	CALL     	8 5 2
	105	[716]	GETTABLE 	9 1 -21	; "_document"
	106	[716]	SELF     	9 9 -22	; "openPage"
	107	[716]	GETTABLE 	11 2 -2	; "page"
	108	[716]	CALL     	9 3 2
	109	[717]	SELF     	10 9 -23	; "getPagePix"
	110	[717]	MOVE     	12 8
	111	[717]	CALL     	10 3 1
	112	[718]	SELF     	10 9 -24	; "close"
	113	[718]	CALL     	10 2 1
	114	[719]	MOVE     	10 8
	115	[719]	MOVE     	11 6
	116	[719]	RETURN   	10 3
	117	[720]	RETURN   	0 1

function <./frontend/document/koptinterface.lua:722,726> (15 instructions, 60 bytes at 0x7fef57512a00)
7 params, 14 slots, 0 upvalues, 8 locals, 3 constants, 0 functions
	1	[723]	SELF     	7 0 -1	; "getClipPageContext"
	2	[723]	MOVE     	9 1
	3	[723]	MOVE     	10 2
	4	[723]	MOVE     	11 3
	5	[723]	MOVE     	12 4
	6	[723]	MOVE     	13 5
	7	[723]	CALL     	7 7 2
	8	[724]	SELF     	8 7 -2	; "exportSrcPNGFile"
	9	[724]	MOVE     	10 4
	10	[724]	MOVE     	11 5
	11	[724]	MOVE     	12 6
	12	[724]	CALL     	8 5 1
	13	[725]	SELF     	8 7 -3	; "free"
	14	[725]	CALL     	8 2 1
	15	[726]	RETURN   	0 1

function <./frontend/document/koptinterface.lua:728,746> (42 instructions, 168 bytes at 0x7fef57512840)
6 params, 14 slots, 1 upvalue, 10 locals, 12 constants, 0 functions
	1	[729]	SELF     	6 0 -1	; "getClipPageContext"
	2	[729]	MOVE     	8 1
	3	[729]	MOVE     	9 2
	4	[729]	MOVE     	10 3
	5	[729]	MOVE     	11 4
	6	[729]	MOVE     	12 5
	7	[729]	CALL     	6 7 2
	8	[732]	LOADNIL  	7 7
	9	[733]	GETUPVAL 	8 0	; util
	10	[733]	GETTABLE 	8 8 -2	; "isAndroid"
	11	[733]	CALL     	8 1 2
	12	[733]	TEST     	8 0 0
	13	[733]	JMP      	20	; to 34
	14	[734]	LOADK    	8 -3	; "cache/tmpclippng.png"
	15	[735]	SELF     	9 6 -4	; "exportSrcPNGFile"
	16	[735]	MOVE     	11 4
	17	[735]	MOVE     	12 5
	18	[735]	MOVE     	13 8
	19	[735]	CALL     	9 5 1
	20	[736]	GETGLOBAL	9 -5	; io
	21	[736]	GETTABLE 	9 9 -6	; "open"
	22	[736]	MOVE     	10 8
	23	[736]	LOADK    	11 -7	; "rb"
	24	[736]	CALL     	9 3 2
	25	[737]	TEST     	9 0 0
	26	[737]	JMP      	12	; to 39
	27	[738]	SELF     	10 9 -8	; "read"
	28	[738]	LOADK    	12 -9	; "*all"
	29	[738]	CALL     	10 3 2
	30	[738]	MOVE     	7 10
	31	[739]	SELF     	10 9 -10	; "close"
	32	[739]	CALL     	10 2 1
	33	[740]	JMP      	5	; to 39
	34	[742]	SELF     	8 6 -11	; "exportSrcPNGString"
	35	[742]	MOVE     	10 4
	36	[742]	MOVE     	11 5
	37	[742]	CALL     	8 4 2
	38	[742]	MOVE     	7 8
	39	[744]	SELF     	8 6 -12	; "free"
	40	[744]	CALL     	8 2 1
	41	[745]	RETURN   	7 2
	42	[746]	RETURN   	0 1

function <./frontend/document/koptinterface.lua:751,757> (19 instructions, 76 bytes at 0x7fef57512900)
2 params, 5 slots, 0 upvalues, 4 locals, 6 constants, 0 functions
	1	[752]	GETTABLE 	2 1 -1	; "x"
	2	[752]	GETTABLE 	3 1 -2	; "y"
	3	[753]	GETTABLE 	4 0 -3	; "x0"
	4	[753]	LE       	0 4 2
	5	[753]	JMP      	11	; to 17
	6	[753]	GETTABLE 	4 0 -4	; "y0"
	7	[753]	LE       	0 4 3
	8	[753]	JMP      	8	; to 17
	9	[753]	GETTABLE 	4 0 -5	; "x1"
	10	[753]	LE       	0 2 4
	11	[753]	JMP      	5	; to 17
	12	[753]	GETTABLE 	4 0 -6	; "y1"
	13	[753]	LE       	0 3 4
	14	[753]	JMP      	2	; to 17
	15	[754]	LOADBOOL 	4 1 0
	16	[754]	RETURN   	4 2
	17	[756]	LOADBOOL 	4 0 0
	18	[756]	RETURN   	4 2
	19	[757]	RETURN   	0 1

function <./frontend/document/koptinterface.lua:759,767> (28 instructions, 112 bytes at 0x7fef57506e40)
2 params, 9 slots, 1 upvalue, 6 locals, 8 constants, 0 functions
	1	[760]	GETUPVAL 	2 0	; inside_box
	2	[760]	MOVE     	3 0
	3	[760]	MOVE     	4 1
	4	[760]	CALL     	2 3 2
	5	[760]	TEST     	2 0 0
	6	[760]	JMP      	3	; to 10
	7	[761]	LOADK    	2 -1	; 0
	8	[761]	RETURN   	2 2
	9	[761]	JMP      	18	; to 28
	10	[763]	GETTABLE 	2 1 -2	; "x"
	11	[763]	GETTABLE 	3 1 -3	; "y"
	12	[764]	GETTABLE 	4 0 -4	; "x0"
	13	[764]	GETTABLE 	5 0 -5	; "x1"
	14	[764]	ADD      	4 4 5
	15	[764]	DIV      	4 4 -6	; - 2
	16	[764]	GETTABLE 	5 0 -7	; "y0"
	17	[764]	GETTABLE 	6 0 -8	; "y1"
	18	[764]	ADD      	5 5 6
	19	[764]	DIV      	5 5 -6	; - 2
	20	[765]	SUB      	6 2 4
	21	[765]	SUB      	7 2 4
	22	[765]	MUL      	6 6 7
	23	[765]	SUB      	7 3 5
	24	[765]	SUB      	8 3 5
	25	[765]	MUL      	7 7 8
	26	[765]	ADD      	6 6 7
	27	[765]	RETURN   	6 2
	28	[767]	RETURN   	0 1

function <./frontend/document/koptinterface.lua:769,779> (32 instructions, 128 bytes at 0x7fef575147d0)
2 params, 16 slots, 1 upvalue, 12 locals, 1 constant, 0 functions
	1	[770]	LOADK    	2 -1	; 1
	2	[770]	LOADK    	3 -1	; 1
	3	[771]	LOADK    	4 -1	; 1
	4	[771]	LEN      	5 0
	5	[771]	LOADK    	6 -1	; 1
	6	[771]	FORPREP  	4 21	; to 28
	7	[772]	LOADK    	8 -1	; 1
	8	[772]	GETTABLE 	9 0 7
	9	[772]	LEN      	9 9
	10	[772]	LOADK    	10 -1	; 1
	11	[772]	FORPREP  	8 15	; to 27
	12	[773]	GETUPVAL 	12 0	; box_distance
	13	[773]	GETTABLE 	13 0 7
	14	[773]	GETTABLE 	13 13 11
	15	[773]	MOVE     	14 1
	16	[773]	CALL     	12 3 2
	17	[773]	GETUPVAL 	13 0	; box_distance
	18	[773]	GETTABLE 	14 0 2
	19	[773]	GETTABLE 	14 14 3
	20	[773]	MOVE     	15 1
	21	[773]	CALL     	13 3 2
	22	[773]	LT       	0 12 13
	23	[773]	JMP      	3	; to 27
	24	[774]	MOVE     	12 7
	25	[774]	MOVE     	3 11
	26	[774]	MOVE     	2 12
	27	[772]	FORLOOP  	8 -16	; to 12
	28	[771]	FORLOOP  	4 -22	; to 7
	29	[778]	MOVE     	4 2
	30	[778]	MOVE     	5 3
	31	[778]	RETURN   	4 3
	32	[779]	RETURN   	0 1

function <./frontend/document/koptinterface.lua:784,800> (40 instructions, 160 bytes at 0x7fef57514c40)
3 params, 12 slots, 2 upvalues, 8 locals, 12 constants, 0 functions
	1	[785]	TEST     	2 0 0
	2	[785]	JMP      	3	; to 6
	3	[785]	LEN      	3 1
	4	[785]	EQ       	0 3 -1	; - 0
	5	[785]	JMP      	2	; to 8
	6	[785]	NEWTABLE 	3 0 0
	7	[785]	RETURN   	3 2
	8	[786]	GETUPVAL 	3 0	; getWordBoxIndices
	9	[786]	MOVE     	4 1
	10	[786]	MOVE     	5 2
	11	[786]	CALL     	3 3 3
	12	[787]	GETTABLE 	5 1 3
	13	[788]	GETTABLE 	6 1 3
	14	[788]	GETTABLE 	6 6 4
	15	[789]	TEST     	5 0 0
	16	[789]	JMP      	23	; to 40
	17	[789]	TEST     	6 0 0
	18	[789]	JMP      	21	; to 40
	19	[790]	GETUPVAL 	7 1	; Geom
	20	[790]	SELF     	7 7 -2	; "new"
	21	[790]	NEWTABLE 	9 0 4
	22	[791]	GETTABLE 	10 6 -4	; "x0"
	23	[791]	SETTABLE 	9 -3 10	; "x" -
	24	[791]	GETTABLE 	10 5 -6	; "y0"
	25	[791]	SETTABLE 	9 -5 10	; "y" -
	26	[792]	GETTABLE 	10 6 -8	; "x1"
	27	[792]	GETTABLE 	11 6 -4	; "x0"
	28	[792]	SUB      	10 10 11
	29	[792]	SETTABLE 	9 -7 10	; "w" -
	30	[793]	GETTABLE 	10 5 -10	; "y1"
	31	[793]	GETTABLE 	11 5 -6	; "y0"
	32	[793]	SUB      	10 10 11
	33	[793]	SETTABLE 	9 -9 10	; "h" -
	34	[790]	CALL     	7 3 2
	35	[795]	NEWTABLE 	8 0 2
	36	[796]	GETTABLE 	9 6 -11	; "word"
	37	[796]	SETTABLE 	8 -11 9	; "word" -
	38	[797]	SETTABLE 	8 -12 7	; "box" -
	39	[798]	RETURN   	8 2
	40	[800]	RETURN   	0 1

function <./frontend/document/koptinterface.lua:805,869> (198 instructions, 792 bytes at 0x7fef57514e90)
4 params, 25 slots, 2 upvalues, 31 locals, 20 constants, 0 functions
	1	[806]	TEST     	2 0 0
	2	[806]	JMP      	5	; to 8
	3	[806]	TEST     	3 0 0
	4	[806]	JMP      	3	; to 8
	5	[806]	LEN      	4 1
	6	[806]	EQ       	0 4 -1	; - 0
	7	[806]	JMP      	2	; to 10
	8	[806]	NEWTABLE 	4 0 0
	9	[806]	RETURN   	4 2
	10	[807]	LOADK    	4 -2	; ""
	11	[808]	NEWTABLE 	5 0 0
	12	[809]	GETUPVAL 	6 0	; getWordBoxIndices
	13	[809]	MOVE     	7 1
	14	[809]	MOVE     	8 2
	15	[809]	CALL     	6 3 3
	16	[810]	GETUPVAL 	8 0	; getWordBoxIndices
	17	[810]	MOVE     	9 1
	18	[810]	MOVE     	10 3
	19	[810]	CALL     	8 3 3
	20	[811]	EQ       	0 6 8
	21	[811]	JMP      	2	; to 24
	22	[811]	LT       	1 9 7
	23	[811]	JMP      	2	; to 26
	24	[811]	LT       	0 8 6
	25	[811]	JMP      	6	; to 32
	26	[812]	MOVE     	10 8
	27	[812]	MOVE     	8 6
	28	[812]	MOVE     	6 10
	29	[813]	MOVE     	10 9
	30	[813]	MOVE     	9 7
	31	[813]	MOVE     	7 10
	32	[815]	MOVE     	10 6
	33	[815]	MOVE     	11 8
	34	[815]	LOADK    	12 -3	; 1
	35	[815]	FORPREP  	10 157	; to 193
	36	[816]	EQ       	0 6 8
	37	[816]	JMP      	5	; to 43
	38	[816]	GETTABLE 	14 1 13
	39	[816]	LEN      	14 14
	40	[816]	EQ       	0 14 -1	; - 0
	41	[816]	JMP      	1	; to 43
	42	[816]	JMP      	151	; to 194
	43	[818]	LT       	0 6 13
	44	[818]	JMP      	3	; to 48
	45	[818]	LOADK    	14 -3	; 1
	46	[818]	TEST     	14 0 1
	47	[818]	JMP      	1	; to 49
	48	[818]	MOVE     	14 7
	49	[819]	LT       	0 13 8
	50	[819]	JMP      	4	; to 55
	51	[819]	GETTABLE 	15 1 13
	52	[819]	LEN      	15 15
	53	[819]	TEST     	15 0 1
	54	[819]	JMP      	1	; to 56
	55	[819]	MOVE     	15 9
	56	[820]	MOVE     	16 14
	57	[820]	MOVE     	17 15
	58	[820]	LOADK    	18 -3	; 1
	59	[820]	FORPREP  	16 20	; to 80
	60	[821]	GETTABLE 	20 1 13
	61	[821]	GETTABLE 	20 20 19
	62	[821]	GETTABLE 	20 20 -4	; "word"
	63	[822]	TEST     	20 0 0
	64	[822]	JMP      	15	; to 80
	65	[824]	SELF     	21 20 -5	; "match"
	66	[824]	LOADK    	23 -6	; "[%z\194-\244][\128-\191]*$"
	67	[824]	CALL     	21 3 2
	68	[824]	TEST     	21 0 1
	69	[824]	JMP      	2	; to 72
	70	[824]	EQ       	0 19 15
	71	[824]	JMP      	3	; to 75
	72	[825]	LOADK    	21 -2	; ""
	73	[825]	TEST     	21 0 1
	74	[825]	JMP      	1	; to 76
	75	[825]	LOADK    	21 -7	; " "
	76	[826]	MOVE     	22 4
	77	[826]	MOVE     	23 20
	78	[826]	MOVE     	24 21
	79	[826]	CONCAT   	4 22 24
	80	[820]	FORLOOP  	16 -21	; to 60
	81	[830]	GETTABLE 	16 1 13
	82	[831]	LT       	0 6 13
	83	[831]	JMP      	24	; to 108
	84	[831]	LT       	0 13 8
	85	[831]	JMP      	22	; to 108
	86	[832]	GETUPVAL 	17 1	; Geom
	87	[832]	SELF     	17 17 -8	; "new"
	88	[832]	NEWTABLE 	19 0 4
	89	[833]	GETTABLE 	20 16 -10	; "x0"
	90	[833]	SETTABLE 	19 -9 20	; "x" -
	91	[833]	GETTABLE 	20 16 -12	; "y0"
	92	[833]	SETTABLE 	19 -11 20	; "y" -
	93	[834]	GETTABLE 	20 16 -14	; "x1"
	94	[834]	GETTABLE 	21 16 -10	; "x0"
	95	[834]	SUB      	20 20 21
	96	[834]	SETTABLE 	19 -13 20	; "w" -
	97	[835]	GETTABLE 	20 16 -16	; "y1"
	98	[835]	GETTABLE 	21 16 -12	; "y0"
	99	[835]	SUB      	20 20 21
	100	[835]	SETTABLE 	19 -15 20	; "h" -
	101	[832]	CALL     	17 3 2
	102	[837]	GETGLOBAL	18 -17	; table
	103	[837]	GETTABLE 	18 18 -18	; "insert"
	104	[837]	MOVE     	19 5
	105	[837]	MOVE     	20 17
	106	[837]	CALL     	18 3 1
	107	[837]	JMP      	85	; to 193
	108	[838]	EQ       	0 13 6
	109	[838]	JMP      	26	; to 136
	110	[838]	LT       	0 13 8
	111	[838]	JMP      	24	; to 136
	112	[839]	GETTABLE 	17 1 13
	113	[839]	GETTABLE 	17 17 7
	114	[840]	GETUPVAL 	18 1	; Geom
	115	[840]	SELF     	18 18 -8	; "new"
	116	[840]	NEWTABLE 	20 0 4
	117	[841]	GETTABLE 	21 17 -10	; "x0"
	118	[841]	SETTABLE 	20 -9 21	; "x" -
	119	[841]	GETTABLE 	21 16 -12	; "y0"
	120	[841]	SETTABLE 	20 -11 21	; "y" -
	121	[842]	GETTABLE 	21 16 -14	; "x1"
	122	[842]	GETTABLE 	22 17 -10	; "x0"
	123	[842]	SUB      	21 21 22
	124	[842]	SETTABLE 	20 -13 21	; "w" -
	125	[843]	GETTABLE 	21 16 -16	; "y1"
	126	[843]	GETTABLE 	22 16 -12	; "y0"
	127	[843]	SUB      	21 21 22
	128	[843]	SETTABLE 	20 -15 21	; "h" -
	129	[840]	CALL     	18 3 2
	130	[845]	GETGLOBAL	19 -17	; table
	131	[845]	GETTABLE 	19 19 -18	; "insert"
	132	[845]	MOVE     	20 5
	133	[845]	MOVE     	21 18
	134	[845]	CALL     	19 3 1
	135	[845]	JMP      	57	; to 193
	136	[846]	LT       	0 6 13
	137	[846]	JMP      	26	; to 164
	138	[846]	EQ       	0 13 8
	139	[846]	JMP      	24	; to 164
	140	[847]	GETTABLE 	17 1 13
	141	[847]	GETTABLE 	17 17 9
	142	[848]	GETUPVAL 	18 1	; Geom
	143	[848]	SELF     	18 18 -8	; "new"
	144	[848]	NEWTABLE 	20 0 4
	145	[849]	GETTABLE 	21 16 -10	; "x0"
	146	[849]	SETTABLE 	20 -9 21	; "x" -
	147	[849]	GETTABLE 	21 16 -12	; "y0"
	148	[849]	SETTABLE 	20 -11 21	; "y" -
	149	[850]	GETTABLE 	21 17 -14	; "x1"
	150	[850]	GETTABLE 	22 16 -10	; "x0"
	151	[850]	SUB      	21 21 22
	152	[850]	SETTABLE 	20 -13 21	; "w" -
	153	[851]	GETTABLE 	21 16 -16	; "y1"
	154	[851]	GETTABLE 	22 16 -12	; "y0"
	155	[851]	SUB      	21 21 22
	156	[851]	SETTABLE 	20 -15 21	; "h" -
	157	[848]	CALL     	18 3 2
	158	[853]	GETGLOBAL	19 -17	; table
	159	[853]	GETTABLE 	19 19 -18	; "insert"
	160	[853]	MOVE     	20 5
	161	[853]	MOVE     	21 18
	162	[853]	CALL     	19 3 1
	163	[853]	JMP      	29	; to 193
	164	[854]	EQ       	0 13 6
	165	[854]	JMP      	27	; to 193
	166	[854]	EQ       	0 13 8
	167	[854]	JMP      	25	; to 193
	168	[855]	GETTABLE 	17 1 13
	169	[855]	GETTABLE 	17 17 7
	170	[856]	GETTABLE 	18 1 13
	171	[856]	GETTABLE 	18 18 9
	172	[857]	GETUPVAL 	19 1	; Geom
	173	[857]	SELF     	19 19 -8	; "new"
	174	[857]	NEWTABLE 	21 0 4
	175	[858]	GETTABLE 	22 17 -10	; "x0"
	176	[858]	SETTABLE 	21 -9 22	; "x" -
	177	[858]	GETTABLE 	22 16 -12	; "y0"
	178	[858]	SETTABLE 	21 -11 22	; "y" -
	179	[859]	GETTABLE 	22 18 -14	; "x1"
	180	[859]	GETTABLE 	23 17 -10	; "x0"
	181	[859]	SUB      	22 22 23
	182	[859]	SETTABLE 	21 -13 22	; "w" -
	183	[860]	GETTABLE 	22 16 -16	; "y1"
	184	[860]	GETTABLE 	23 16 -12	; "y0"
	185	[860]	SUB      	22 22 23
	186	[860]	SETTABLE 	21 -15 22	; "h" -
	187	[857]	CALL     	19 3 2
	188	[862]	GETGLOBAL	20 -17	; table
	189	[862]	GETTABLE 	20 20 -18	; "insert"
	190	[862]	MOVE     	21 5
	191	[862]	MOVE     	22 19
	192	[862]	CALL     	20 3 1
	193	[815]	FORLOOP  	10 -158	; to 36
	194	[865]	NEWTABLE 	10 0 2
	195	[866]	SETTABLE 	10 -19 4	; "text" -
	196	[867]	SETTABLE 	10 -20 5	; "boxes" -
	197	[868]	RETURN   	10 2
	198	[869]	RETURN   	0 1

function <./frontend/document/koptinterface.lua:874,883> (24 instructions, 96 bytes at 0x7fef57514db0)
3 params, 9 slots, 0 upvalues, 4 locals, 7 constants, 0 functions
	1	[875]	SELF     	3 0 -1	; "getTextBoxes"
	2	[875]	MOVE     	5 1
	3	[875]	GETTABLE 	6 2 -2	; "page"
	4	[875]	CALL     	3 4 2
	5	[876]	TEST     	3 0 0
	6	[876]	JMP      	17	; to 24
	7	[877]	GETTABLE 	4 1 -3	; "configurable"
	8	[877]	GETTABLE 	4 4 -4	; "text_wrap"
	9	[877]	EQ       	0 4 -5	; - 1
	10	[877]	JMP      	7	; to 18
	11	[878]	SELF     	4 0 -6	; "getWordFromReflowPosition"
	12	[878]	MOVE     	6 1
	13	[878]	MOVE     	7 3
	14	[878]	MOVE     	8 2
	15	[878]	TAILCALL 	4 5 0
	16	[878]	RETURN   	4 0
	17	[878]	JMP      	6	; to 24
	18	[880]	SELF     	4 0 -7	; "getWordFromNativePosition"
	19	[880]	MOVE     	6 1
	20	[880]	MOVE     	7 3
	21	[880]	MOVE     	8 2
	22	[880]	TAILCALL 	4 5 0
	23	[880]	RETURN   	4 0
	24	[883]	RETURN   	0 1

function <./frontend/document/koptinterface.lua:885,891> (17 instructions, 68 bytes at 0x7fef575153d0)
2 params, 6 slots, 0 upvalues, 4 locals, 5 constants, 0 functions
	1	[886]	NEWTABLE 	2 0 0
	2	[887]	SELF     	3 0 -1	; "center"
	3	[887]	CALL     	3 2 2
	4	[888]	GETTABLE 	4 3 -2	; "x"
	5	[888]	GETTABLE 	5 1 -2	; "x"
	6	[888]	SUB      	4 4 5
	7	[888]	GETTABLE 	5 1 -3	; "w"
	8	[888]	DIV      	4 4 5
	9	[888]	SETTABLE 	2 -2 4	; "x" -
	10	[889]	GETTABLE 	4 3 -4	; "y"
	11	[889]	GETTABLE 	5 1 -4	; "y"
	12	[889]	SUB      	4 4 5
	13	[889]	GETTABLE 	5 1 -5	; "h"
	14	[889]	DIV      	4 4 5
	15	[889]	SETTABLE 	2 -4 4	; "y" -
	16	[890]	RETURN   	2 2
	17	[891]	RETURN   	0 1

function <./frontend/document/koptinterface.lua:896,918> (44 instructions, 176 bytes at 0x7fef57515690)
4 params, 17 slots, 1 upvalue, 14 locals, 11 constants, 0 functions
	1	[897]	GETTABLE 	4 3 -1	; "page"
	2	[899]	SELF     	5 0 -2	; "getReflowedTextBoxesFromScratch"
	3	[899]	MOVE     	7 1
	4	[899]	MOVE     	8 4
	5	[899]	CALL     	5 4 2
	6	[900]	SELF     	6 0 -3	; "getWordFromBoxes"
	7	[900]	MOVE     	8 5
	8	[900]	MOVE     	9 3
	9	[900]	CALL     	6 4 2
	10	[902]	SELF     	7 0 -4	; "getReflowedTextBoxes"
	11	[902]	MOVE     	9 1
	12	[902]	MOVE     	10 4
	13	[902]	CALL     	7 4 2
	14	[903]	SELF     	8 0 -3	; "getWordFromBoxes"
	15	[903]	MOVE     	10 7
	16	[903]	MOVE     	11 3
	17	[903]	CALL     	8 4 2
	18	[905]	GETTABLE 	9 6 -5	; "box"
	19	[905]	SELF     	9 9 -6	; "center"
	20	[905]	CALL     	9 2 2
	21	[906]	GETUPVAL 	10 0	; getBoxRelativePosition
	22	[906]	GETTABLE 	11 6 -5	; "box"
	23	[906]	GETTABLE 	12 8 -5	; "box"
	24	[906]	CALL     	10 3 2
	25	[908]	SELF     	11 0 -7	; "reflowToNativePosTransform"
	26	[908]	MOVE     	13 1
	27	[908]	MOVE     	14 4
	28	[908]	MOVE     	15 9
	29	[908]	MOVE     	16 10
	30	[908]	CALL     	11 6 2
	31	[909]	SELF     	12 0 -3	; "getWordFromBoxes"
	32	[909]	MOVE     	14 2
	33	[909]	MOVE     	15 11
	34	[909]	CALL     	12 4 2
	35	[911]	NEWTABLE 	13 0 4
	36	[912]	GETTABLE 	14 12 -8	; "word"
	37	[912]	SETTABLE 	13 -8 14	; "word" -
	38	[913]	GETTABLE 	14 12 -5	; "box"
	39	[913]	SETTABLE 	13 -9 14	; "pbox" -
	40	[914]	GETTABLE 	14 6 -5	; "box"
	41	[914]	SETTABLE 	13 -10 14	; "sbox" -
	42	[915]	SETTABLE 	13 -11 11	; "pos" -
	43	[917]	RETURN   	13 2
	44	[918]	RETURN   	0 1

function <./frontend/document/koptinterface.lua:923,932> (14 instructions, 56 bytes at 0x7fef57515d60)
4 params, 8 slots, 0 upvalues, 6 locals, 6 constants, 0 functions
	1	[924]	SELF     	4 0 -1	; "getWordFromBoxes"
	2	[924]	MOVE     	6 2
	3	[924]	MOVE     	7 3
	4	[924]	CALL     	4 4 2
	5	[925]	NEWTABLE 	5 0 4
	6	[926]	GETTABLE 	6 4 -2	; "word"
	7	[926]	SETTABLE 	5 -2 6	; "word" -
	8	[927]	GETTABLE 	6 4 -4	; "box"
	9	[927]	SETTABLE 	5 -3 6	; "pbox" -
	10	[928]	GETTABLE 	6 4 -4	; "box"
	11	[928]	SETTABLE 	5 -5 6	; "sbox" -
	12	[929]	SETTABLE 	5 -6 3	; "pos" -
	13	[931]	RETURN   	5 2
	14	[932]	RETURN   	0 1

function <./frontend/document/koptinterface.lua:937,971> (63 instructions, 252 bytes at 0x7fef575163f0)
4 params, 18 slots, 2 upvalues, 14 locals, 18 constants, 1 function
	1	[947]	CLOSURE  	4 0	; 0x7fef57516990
	2	[948]	SELF     	5 1 -1	; "getPageLinks"
	3	[948]	MOVE     	7 2
	4	[948]	CALL     	5 3 2
	5	[949]	TEST     	5 0 0
	6	[949]	JMP      	56	; to 63
	7	[950]	GETTABLE 	6 1 -2	; "configurable"
	8	[950]	GETTABLE 	6 6 -3	; "text_wrap"
	9	[950]	EQ       	0 6 -4	; - 1
	10	[950]	JMP      	9	; to 20
	11	[951]	SELF     	6 0 -5	; "reflowToNativePosTransform"
	12	[951]	MOVE     	8 1
	13	[951]	MOVE     	9 2
	14	[951]	MOVE     	10 3
	15	[951]	NEWTABLE 	11 0 2
	16	[951]	SETTABLE 	11 -6 -7	; "x" 0.5
	17	[951]	SETTABLE 	11 -8 -7	; "y" 0.5
	18	[951]	CALL     	6 6 2
	19	[951]	MOVE     	3 6
	20	[954]	GETUPVAL 	6 0	; CanvasContext
	21	[954]	SELF     	6 6 -9	; "scaleBySize"
	22	[954]	LOADK    	8 -10	; 5
	23	[954]	CALL     	6 3 2
	24	[955]	GETUPVAL 	7 0	; CanvasContext
	25	[955]	SELF     	7 7 -9	; "scaleBySize"
	26	[955]	LOADK    	9 -11	; 10
	27	[955]	CALL     	7 3 2
	28	[956]	LOADK    	8 -4	; 1
	29	[956]	LEN      	9 5
	30	[956]	LOADK    	10 -4	; 1
	31	[956]	FORPREP  	8 30	; to 62
	32	[957]	GETTABLE 	12 5 11
	33	[959]	GETUPVAL 	13 1	; Geom
	34	[959]	SELF     	13 13 -12	; "new"
	35	[959]	NEWTABLE 	15 0 4
	36	[960]	GETTABLE 	16 12 -13	; "x0"
	37	[960]	SUB      	16 16 6
	38	[960]	SETTABLE 	15 -6 16	; "x" -
	39	[961]	GETTABLE 	16 12 -14	; "y0"
	40	[961]	SUB      	16 16 6
	41	[961]	SETTABLE 	15 -8 16	; "y" -
	42	[962]	GETTABLE 	16 12 -16	; "x1"
	43	[962]	GETTABLE 	17 12 -13	; "x0"
	44	[962]	SUB      	16 16 17
	45	[962]	ADD      	16 16 7
	46	[962]	SETTABLE 	15 -15 16	; "w" -
	47	[963]	GETTABLE 	16 12 -18	; "y1"
	48	[963]	GETTABLE 	17 12 -14	; "y0"
	49	[963]	SUB      	16 16 17
	50	[963]	ADD      	16 16 7
	51	[963]	SETTABLE 	15 -17 16	; "h" -
	52	[959]	CALL     	13 3 2
	53	[966]	MOVE     	14 4
	54	[966]	MOVE     	15 3
	55	[966]	MOVE     	16 13
	56	[966]	CALL     	14 3 2
	57	[966]	TEST     	14 0 0
	58	[966]	JMP      	3	; to 62
	59	[967]	MOVE     	14 12
	60	[967]	MOVE     	15 13
	61	[967]	RETURN   	14 3
	62	[956]	FORLOOP  	8 -31	; to 32
	63	[971]	RETURN   	0 1

function <./frontend/document/koptinterface.lua:938,947> (23 instructions, 92 bytes at 0x7fef57516990)
2 params, 6 slots, 0 upvalues, 4 locals, 4 constants, 0 functions
	1	[939]	TEST     	0 0 0
	2	[939]	JMP      	20	; to 23
	3	[940]	GETTABLE 	2 0 -1	; "x"
	4	[940]	GETTABLE 	3 0 -2	; "y"
	5	[941]	GETTABLE 	4 1 -1	; "x"
	6	[941]	LE       	0 4 2
	7	[941]	JMP      	15	; to 23
	8	[941]	GETTABLE 	4 1 -2	; "y"
	9	[941]	LE       	0 4 3
	10	[941]	JMP      	12	; to 23
	11	[942]	GETTABLE 	4 1 -1	; "x"
	12	[942]	GETTABLE 	5 1 -3	; "w"
	13	[942]	ADD      	4 4 5
	14	[942]	LE       	0 2 4
	15	[942]	JMP      	7	; to 23
	16	[943]	GETTABLE 	4 1 -2	; "y"
	17	[943]	GETTABLE 	5 1 -4	; "h"
	18	[943]	ADD      	4 4 5
	19	[943]	LE       	0 3 4
	20	[943]	JMP      	2	; to 23
	21	[944]	LOADBOOL 	4 1 0
	22	[944]	RETURN   	4 2
	23	[947]	RETURN   	0 1

function <./frontend/document/koptinterface.lua:976,981> (13 instructions, 52 bytes at 0x7fef57516f30)
4 params, 10 slots, 0 upvalues, 6 locals, 4 constants, 0 functions
	1	[977]	SELF     	4 0 -1	; "getCachedContext"
	2	[977]	MOVE     	6 1
	3	[977]	MOVE     	7 2
	4	[977]	CALL     	4 4 2
	5	[978]	NEWTABLE 	5 0 0
	6	[979]	SELF     	6 4 -4	; "nativeToReflowPosTransform"
	7	[979]	GETTABLE 	8 3 -2	; "x"
	8	[979]	GETTABLE 	9 3 -3	; "y"
	9	[979]	CALL     	6 4 3
	10	[979]	SETTABLE 	5 -3 7	; "y" -
	11	[979]	SETTABLE 	5 -2 6	; "x" -
	12	[980]	RETURN   	5 2
	13	[981]	RETURN   	0 1

function <./frontend/document/koptinterface.lua:986,991> (15 instructions, 60 bytes at 0x7fef57516fb0)
5 params, 13 slots, 0 upvalues, 7 locals, 4 constants, 0 functions
	1	[987]	SELF     	5 0 -1	; "getCachedContext"
	2	[987]	MOVE     	7 1
	3	[987]	MOVE     	8 2
	4	[987]	CALL     	5 4 2
	5	[988]	NEWTABLE 	6 0 0
	6	[989]	SELF     	7 5 -4	; "reflowToNativePosTransform"
	7	[989]	GETTABLE 	9 3 -2	; "x"
	8	[989]	GETTABLE 	10 3 -3	; "y"
	9	[989]	GETTABLE 	11 4 -2	; "x"
	10	[989]	GETTABLE 	12 4 -3	; "y"
	11	[989]	CALL     	7 6 3
	12	[989]	SETTABLE 	6 -3 8	; "y" -
	13	[989]	SETTABLE 	6 -2 7	; "x" -
	14	[990]	RETURN   	6 2
	15	[991]	RETURN   	0 1

function <./frontend/document/koptinterface.lua:996,1005> (26 instructions, 104 bytes at 0x7fef575179f0)
4 params, 11 slots, 0 upvalues, 5 locals, 7 constants, 0 functions
	1	[997]	SELF     	4 0 -1	; "getTextBoxes"
	2	[997]	MOVE     	6 1
	3	[997]	GETTABLE 	7 2 -2	; "page"
	4	[997]	CALL     	4 4 2
	5	[998]	TEST     	4 0 0
	6	[998]	JMP      	19	; to 26
	7	[999]	GETTABLE 	5 1 -3	; "configurable"
	8	[999]	GETTABLE 	5 5 -4	; "text_wrap"
	9	[999]	EQ       	0 5 -5	; - 1
	10	[999]	JMP      	8	; to 19
	11	[1000]	SELF     	5 0 -6	; "getTextFromReflowPositions"
	12	[1000]	MOVE     	7 1
	13	[1000]	MOVE     	8 4
	14	[1000]	MOVE     	9 2
	15	[1000]	MOVE     	10 3
	16	[1000]	TAILCALL 	5 6 0
	17	[1000]	RETURN   	5 0
	18	[1000]	JMP      	7	; to 26
	19	[1002]	SELF     	5 0 -7	; "getTextFromNativePositions"
	20	[1002]	MOVE     	7 1
	21	[1002]	MOVE     	8 4
	22	[1002]	MOVE     	9 2
	23	[1002]	MOVE     	10 3
	24	[1002]	TAILCALL 	5 6 0
	25	[1002]	RETURN   	5 0
	26	[1005]	RETURN   	0 1

function <./frontend/document/koptinterface.lua:1010,1039> (72 instructions, 288 bytes at 0x7fef575182d0)
5 params, 24 slots, 1 upvalue, 21 locals, 14 constants, 0 functions
	1	[1011]	GETTABLE 	5 3 -1	; "page"
	2	[1013]	SELF     	6 0 -2	; "getReflowedTextBoxesFromScratch"
	3	[1013]	MOVE     	8 1
	4	[1013]	MOVE     	9 5
	5	[1013]	CALL     	6 4 2
	6	[1014]	SELF     	7 0 -3	; "getReflowedTextBoxes"
	7	[1014]	MOVE     	9 1
	8	[1014]	MOVE     	10 5
	9	[1014]	CALL     	7 4 2
	10	[1016]	SELF     	8 0 -4	; "getWordFromBoxes"
	11	[1016]	MOVE     	10 6
	12	[1016]	MOVE     	11 3
	13	[1016]	CALL     	8 4 2
	14	[1017]	SELF     	9 0 -4	; "getWordFromBoxes"
	15	[1017]	MOVE     	11 7
	16	[1017]	MOVE     	12 3
	17	[1017]	CALL     	9 4 2
	18	[1018]	SELF     	10 0 -4	; "getWordFromBoxes"
	19	[1018]	MOVE     	12 6
	20	[1018]	MOVE     	13 4
	21	[1018]	CALL     	10 4 2
	22	[1019]	SELF     	11 0 -4	; "getWordFromBoxes"
	23	[1019]	MOVE     	13 7
	24	[1019]	MOVE     	14 4
	25	[1019]	CALL     	11 4 2
	26	[1021]	GETTABLE 	12 8 -5	; "box"
	27	[1021]	SELF     	12 12 -6	; "center"
	28	[1021]	CALL     	12 2 2
	29	[1022]	GETUPVAL 	13 0	; getBoxRelativePosition
	30	[1022]	GETTABLE 	14 8 -5	; "box"
	31	[1022]	GETTABLE 	15 9 -5	; "box"
	32	[1022]	CALL     	13 3 2
	33	[1023]	GETTABLE 	14 10 -5	; "box"
	34	[1023]	SELF     	14 14 -6	; "center"
	35	[1023]	CALL     	14 2 2
	36	[1024]	GETUPVAL 	15 0	; getBoxRelativePosition
	37	[1024]	GETTABLE 	16 10 -5	; "box"
	38	[1024]	GETTABLE 	17 11 -5	; "box"
	39	[1024]	CALL     	15 3 2
	40	[1026]	SELF     	16 0 -7	; "reflowToNativePosTransform"
	41	[1026]	MOVE     	18 1
	42	[1026]	MOVE     	19 5
	43	[1026]	MOVE     	20 12
	44	[1026]	MOVE     	21 13
	45	[1026]	CALL     	16 6 2
	46	[1027]	SELF     	17 0 -7	; "reflowToNativePosTransform"
	47	[1027]	MOVE     	19 1
	48	[1027]	MOVE     	20 5
	49	[1027]	MOVE     	21 14
	50	[1027]	MOVE     	22 15
	51	[1027]	CALL     	17 6 2
	52	[1029]	SELF     	18 0 -8	; "getTextFromBoxes"
	53	[1029]	MOVE     	20 7
	54	[1029]	MOVE     	21 3
	55	[1029]	MOVE     	22 4
	56	[1029]	CALL     	18 5 2
	57	[1030]	SELF     	19 0 -8	; "getTextFromBoxes"
	58	[1030]	MOVE     	21 2
	59	[1030]	MOVE     	22 16
	60	[1030]	MOVE     	23 17
	61	[1030]	CALL     	19 5 2
	62	[1031]	NEWTABLE 	20 0 5
	63	[1032]	GETTABLE 	21 19 -9	; "text"
	64	[1032]	SETTABLE 	20 -9 21	; "text" -
	65	[1033]	GETTABLE 	21 19 -11	; "boxes"
	66	[1033]	SETTABLE 	20 -10 21	; "pboxes" -
	67	[1034]	GETTABLE 	21 18 -11	; "boxes"
	68	[1034]	SETTABLE 	20 -12 21	; "sboxes" -
	69	[1035]	SETTABLE 	20 -13 16	; "pos0" -
	70	[1036]	SETTABLE 	20 -14 17	; "pos1" -
	71	[1038]	RETURN   	20 2
	72	[1039]	RETURN   	0 1

function <./frontend/document/koptinterface.lua:1044,1054> (16 instructions, 64 bytes at 0x7fef575180f0)
5 params, 10 slots, 0 upvalues, 7 locals, 7 constants, 0 functions
	1	[1045]	SELF     	5 0 -1	; "getTextFromBoxes"
	2	[1045]	MOVE     	7 2
	3	[1045]	MOVE     	8 3
	4	[1045]	MOVE     	9 4
	5	[1045]	CALL     	5 5 2
	6	[1046]	NEWTABLE 	6 0 5
	7	[1047]	GETTABLE 	7 5 -2	; "text"
	8	[1047]	SETTABLE 	6 -2 7	; "text" -
	9	[1048]	GETTABLE 	7 5 -4	; "boxes"
	10	[1048]	SETTABLE 	6 -3 7	; "pboxes" -
	11	[1049]	GETTABLE 	7 5 -4	; "boxes"
	12	[1049]	SETTABLE 	6 -5 7	; "sboxes" -
	13	[1050]	SETTABLE 	6 -6 3	; "pos0" -
	14	[1051]	SETTABLE 	6 -7 4	; "pos1" -
	15	[1053]	RETURN   	6 2
	16	[1054]	RETURN   	0 1

function <./frontend/document/koptinterface.lua:1060,1081> (57 instructions, 228 bytes at 0x7fef575185f0)
5 params, 13 slots, 1 upvalue, 11 locals, 10 constants, 0 functions
	1	[1061]	TEST     	3 0 0
	2	[1061]	JMP      	2	; to 5
	3	[1061]	TEST     	4 0 1
	4	[1061]	JMP      	1	; to 6
	5	[1061]	RETURN   	0 1
	6	[1062]	GETTABLE 	5 1 -1	; "configurable"
	7	[1062]	GETTABLE 	5 5 -2	; "text_wrap"
	8	[1062]	EQ       	0 5 -3	; - 1
	9	[1062]	JMP      	29	; to 39
	10	[1063]	SELF     	5 0 -4	; "nativeToReflowPosTransform"
	11	[1063]	MOVE     	7 1
	12	[1063]	MOVE     	8 2
	13	[1063]	MOVE     	9 3
	14	[1063]	CALL     	5 5 2
	15	[1064]	SELF     	6 0 -4	; "nativeToReflowPosTransform"
	16	[1064]	MOVE     	8 1
	17	[1064]	MOVE     	9 2
	18	[1064]	MOVE     	10 4
	19	[1064]	CALL     	6 5 2
	20	[1065]	SELF     	7 0 -5	; "getReflowedTextBoxes"
	21	[1065]	MOVE     	9 1
	22	[1065]	MOVE     	10 2
	23	[1065]	CALL     	7 4 2
	24	[1066]	TEST     	7 0 1
	25	[1066]	JMP      	5	; to 31
	26	[1067]	GETUPVAL 	8 0	; logger
	27	[1067]	GETTABLE 	8 8 -6	; "warn"
	28	[1067]	LOADK    	9 -7	; "KoptInterface: missing page_boxes"
	29	[1067]	CALL     	8 2 1
	30	[1068]	RETURN   	0 1
	31	[1070]	SELF     	8 0 -8	; "getTextFromBoxes"
	32	[1070]	MOVE     	10 7
	33	[1070]	MOVE     	11 5
	34	[1070]	MOVE     	12 6
	35	[1070]	CALL     	8 5 2
	36	[1071]	GETTABLE 	9 8 -9	; "boxes"
	37	[1071]	RETURN   	9 2
	38	[1071]	JMP      	18	; to 57
	39	[1073]	SELF     	5 0 -10	; "getTextBoxes"
	40	[1073]	MOVE     	7 1
	41	[1073]	MOVE     	8 2
	42	[1073]	CALL     	5 4 2
	43	[1074]	TEST     	5 0 1
	44	[1074]	JMP      	5	; to 50
	45	[1075]	GETUPVAL 	6 0	; logger
	46	[1075]	GETTABLE 	6 6 -6	; "warn"
	47	[1075]	LOADK    	7 -7	; "KoptInterface: missing page_boxes"
	48	[1075]	CALL     	6 2 1
	49	[1076]	RETURN   	0 1
	50	[1078]	SELF     	6 0 -8	; "getTextFromBoxes"
	51	[1078]	MOVE     	8 5
	52	[1078]	MOVE     	9 3
	53	[1078]	MOVE     	10 4
	54	[1078]	CALL     	6 5 2
	55	[1079]	GETTABLE 	7 6 -9	; "boxes"
	56	[1079]	RETURN   	7 2
	57	[1081]	RETURN   	0 1

function <./frontend/document/koptinterface.lua:1086,1107> (47 instructions, 188 bytes at 0x7fef57519280)
4 params, 16 slots, 0 upvalues, 13 locals, 12 constants, 0 functions
	1	[1087]	GETTABLE 	4 1 -1	; "configurable"
	2	[1087]	GETTABLE 	4 4 -2	; "text_wrap"
	3	[1087]	EQ       	0 4 -3	; - 1
	4	[1087]	JMP      	41	; to 46
	5	[1088]	NEWTABLE 	4 0 2
	6	[1089]	GETTABLE 	5 3 -4	; "x"
	7	[1089]	ADD      	5 5 -5	; - 5
	8	[1089]	SETTABLE 	4 -4 5	; "x" -
	9	[1089]	GETTABLE 	5 3 -6	; "y"
	10	[1089]	ADD      	5 5 -5	; - 5
	11	[1089]	SETTABLE 	4 -6 5	; "y" -
	12	[1091]	NEWTABLE 	5 0 2
	13	[1092]	GETTABLE 	6 3 -4	; "x"
	14	[1092]	GETTABLE 	7 3 -7	; "w"
	15	[1092]	ADD      	6 6 7
	16	[1092]	SUB      	6 6 -5	; - 5
	17	[1092]	SETTABLE 	5 -4 6	; "x" -
	18	[1093]	GETTABLE 	6 3 -6	; "y"
	19	[1093]	GETTABLE 	7 3 -8	; "h"
	20	[1093]	ADD      	6 6 7
	21	[1093]	SUB      	6 6 -5	; - 5
	22	[1093]	SETTABLE 	5 -6 6	; "y" -
	23	[1095]	SELF     	6 0 -9	; "getPageBoxesFromPositions"
	24	[1095]	MOVE     	8 1
	25	[1095]	MOVE     	9 2
	26	[1095]	MOVE     	10 4
	27	[1095]	MOVE     	11 5
	28	[1095]	CALL     	6 6 2
	29	[1096]	LOADNIL  	7 7
	30	[1097]	LEN      	8 6
	31	[1097]	LT       	0 -10 8	; 0 -
	32	[1097]	JMP      	11	; to 44
	33	[1098]	GETTABLE 	7 6 -3	; 1
	34	[1099]	GETGLOBAL	8 -11	; pairs
	35	[1099]	MOVE     	9 6
	36	[1099]	CALL     	8 2 4
	37	[1099]	JMP      	4	; to 42
	38	[1100]	SELF     	13 7 -12	; "combine"
	39	[1100]	MOVE     	15 12
	40	[1100]	CALL     	13 3 2
	41	[1100]	MOVE     	7 13
	42	[1099]	TFORLOOP 	8 2
	43	[1100]	JMP      	-6	; to 38
	44	[1103]	RETURN   	7 2
	45	[1103]	JMP      	1	; to 47
	46	[1105]	RETURN   	3 2
	47	[1107]	RETURN   	0 1

function <./frontend/document/koptinterface.lua:1109,1155> (36 instructions, 144 bytes at 0x7fef57519840)
3 params, 16 slots, 0 upvalues, 13 locals, 8 constants, 2 functions
	1	[1111]	NEWTABLE 	3 0 0
	2	[1113]	SELF     	4 1 -1	; "gmatch"
	3	[1113]	LOADK    	6 -2	; "[ -\127\192-\255]+[\128-\191]*"
	4	[1113]	CALL     	4 3 4
	5	[1113]	JMP      	17	; to 23
	6	[1115]	SELF     	8 7 -1	; "gmatch"
	7	[1115]	LOADK    	10 -3	; "[^%s]+"
	8	[1115]	CALL     	8 3 4
	9	[1115]	JMP      	11	; to 21
	10	[1116]	GETGLOBAL	12 -4	; table
	11	[1116]	GETTABLE 	12 12 -5	; "insert"
	12	[1116]	MOVE     	13 3
	13	[1116]	TEST     	2 0 0
	14	[1116]	JMP      	4	; to 19
	15	[1116]	SELF     	14 11 -6	; "lower"
	16	[1116]	CALL     	14 2 2
	17	[1116]	TEST     	14 0 1
	18	[1116]	JMP      	1	; to 20
	19	[1116]	MOVE     	14 11
	20	[1116]	CALL     	12 3 1
	21	[1115]	TFORLOOP 	8 1
	22	[1116]	JMP      	-13	; to 10
	23	[1113]	TFORLOOP 	4 1
	24	[1117]	JMP      	-19	; to 6
	25	[1144]	CLOSURE  	4 0	; 0x7fef57519fd0
	26	[1144]	MOVE     	0 3
	27	[1144]	MOVE     	0 0
	28	[1144]	MOVE     	0 2
	29	[1145]	GETGLOBAL	5 -7	; coroutine
	30	[1145]	GETTABLE 	5 5 -8	; "wrap"
	31	[1154]	CLOSURE  	6 1	; 0x7fef5751a150
	32	[1154]	MOVE     	0 0
	33	[1154]	MOVE     	0 4
	34	[1145]	TAILCALL 	5 2 0
	35	[1154]	RETURN   	5 0
	36	[1155]	RETURN   	0 1

function <./frontend/document/koptinterface.lua:1120,1144> (60 instructions, 240 bytes at 0x7fef57519fd0)
2 params, 11 slots, 3 upvalues, 6 locals, 7 constants, 0 functions
	1	[1121]	LOADK    	2 -1	; 1
	2	[1122]	NEWTABLE 	3 0 0
	3	[1123]	GETUPVAL 	4 0	; plist
	4	[1123]	LEN      	4 4
	5	[1123]	EQ       	0 4 -2	; - 0
	6	[1123]	JMP      	1	; to 8
	7	[1123]	RETURN   	0 1
	8	[1125]	GETUPVAL 	4 1	; boxes
	9	[1125]	GETTABLE 	4 4 0
	10	[1125]	LEN      	4 4
	11	[1125]	LT       	0 4 1
	12	[1125]	JMP      	5	; to 18
	13	[1126]	GETUPVAL 	4 1	; boxes
	14	[1126]	GETTABLE 	4 4 0
	15	[1126]	LEN      	4 4
	16	[1126]	SUB      	1 1 4
	17	[1127]	ADD      	0 0 -1	; - 1
	18	[1129]	GETUPVAL 	4 1	; boxes
	19	[1129]	LEN      	4 4
	20	[1129]	LT       	0 4 0
	21	[1129]	JMP      	1	; to 23
	22	[1129]	JMP      	37	; to 60
	23	[1130]	GETUPVAL 	4 1	; boxes
	24	[1130]	GETTABLE 	4 4 0
	25	[1130]	GETTABLE 	4 4 1
	26	[1131]	GETUPVAL 	5 2	; caseInsensitive
	27	[1131]	TEST     	5 0 0
	28	[1131]	JMP      	5	; to 34
	29	[1131]	GETTABLE 	5 4 -3	; "word"
	30	[1131]	SELF     	5 5 -4	; "lower"
	31	[1131]	CALL     	5 2 2
	32	[1131]	TEST     	5 0 1
	33	[1131]	JMP      	1	; to 35
	34	[1131]	GETTABLE 	5 4 -3	; "word"
	35	[1132]	SELF     	6 5 -5	; "match"
	36	[1132]	GETUPVAL 	8 0	; plist
	37	[1132]	GETTABLE 	8 8 2
	38	[1132]	CALL     	6 3 2
	39	[1132]	TEST     	6 0 0
	40	[1132]	JMP      	19	; to 60
	41	[1133]	GETGLOBAL	6 -6	; table
	42	[1133]	GETTABLE 	6 6 -7	; "insert"
	43	[1133]	MOVE     	7 3
	44	[1133]	NEWTABLE 	8 2 0
	45	[1133]	MOVE     	9 0
	46	[1133]	MOVE     	10 1
	47	[1133]	SETLIST  	8 2 1	; 1
	48	[1133]	CALL     	6 3 1
	49	[1134]	GETUPVAL 	6 0	; plist
	50	[1134]	LEN      	6 6
	51	[1134]	EQ       	0 2 6
	52	[1134]	JMP      	2	; to 55
	53	[1135]	RETURN   	3 2
	54	[1135]	JMP      	-47	; to 8
	55	[1137]	ADD      	1 1 -1	; - 1
	56	[1138]	ADD      	2 2 -1	; - 1
	57	[1139]	JMP      	-50	; to 8
	58	[1141]	JMP      	1	; to 60
	59	[1142]	JMP      	-52	; to 8
	60	[1144]	RETURN   	0 1

function <./frontend/document/koptinterface.lua:1145,1154> (23 instructions, 92 bytes at 0x7fef5751a150)
0 params, 13 slots, 2 upvalues, 11 locals, 3 constants, 0 functions
	1	[1146]	GETGLOBAL	0 -1	; ipairs
	2	[1146]	GETUPVAL 	1 0	; boxes
	3	[1146]	CALL     	0 2 4
	4	[1146]	JMP      	16	; to 21
	5	[1147]	GETGLOBAL	5 -1	; ipairs
	6	[1147]	MOVE     	6 4
	7	[1147]	CALL     	5 2 4
	8	[1147]	JMP      	10	; to 19
	9	[1148]	GETUPVAL 	10 1	; match
	10	[1148]	MOVE     	11 3
	11	[1148]	MOVE     	12 8
	12	[1148]	CALL     	10 3 2
	13	[1149]	TEST     	10 0 0
	14	[1149]	JMP      	4	; to 19
	15	[1150]	GETGLOBAL	11 -2	; coroutine
	16	[1150]	GETTABLE 	11 11 -3	; "yield"
	17	[1150]	MOVE     	12 10
	18	[1150]	CALL     	11 2 1
	19	[1147]	TFORLOOP 	5 2
	20	[1151]	JMP      	-12	; to 9
	21	[1146]	TFORLOOP 	0 2
	22	[1152]	JMP      	-18	; to 5
	23	[1154]	RETURN   	0 1

function <./frontend/document/koptinterface.lua:1157,1175> (52 instructions, 208 bytes at 0x7fef57519f50)
5 params, 27 slots, 1 upvalue, 20 locals, 14 constants, 0 functions
	1	[1158]	SELF     	5 1 -1	; "getPageTextBoxes"
	2	[1158]	MOVE     	7 4
	3	[1158]	CALL     	5 3 2
	4	[1159]	TEST     	5 0 1
	5	[1159]	JMP      	1	; to 7
	6	[1159]	RETURN   	0 1
	7	[1160]	NEWTABLE 	6 0 0
	8	[1161]	GETUPVAL 	7 0	; all_matches
	9	[1161]	TESTSET  	8 5 1
	10	[1161]	JMP      	1	; to 12
	11	[1161]	NEWTABLE 	8 0 0
	12	[1161]	MOVE     	9 2
	13	[1161]	MOVE     	10 3
	14	[1161]	CALL     	7 4 4
	15	[1161]	JMP      	33	; to 49
	16	[1162]	GETGLOBAL	11 -2	; ipairs
	17	[1162]	MOVE     	12 10
	18	[1162]	CALL     	11 2 4
	19	[1162]	JMP      	27	; to 47
	20	[1163]	GETGLOBAL	16 -3	; unpack
	21	[1163]	MOVE     	17 15
	22	[1163]	CALL     	16 2 3
	23	[1164]	GETTABLE 	18 5 16
	24	[1164]	GETTABLE 	18 18 17
	25	[1165]	NEWTABLE 	19 0 4
	26	[1166]	GETTABLE 	20 18 -5	; "x0"
	27	[1166]	SETTABLE 	19 -4 20	; "x" -
	28	[1166]	GETTABLE 	20 18 -7	; "y0"
	29	[1166]	SETTABLE 	19 -6 20	; "y" -
	30	[1167]	GETTABLE 	20 18 -9	; "x1"
	31	[1167]	GETTABLE 	21 18 -5	; "x0"
	32	[1167]	SUB      	20 20 21
	33	[1167]	SETTABLE 	19 -8 20	; "w" -
	34	[1168]	GETTABLE 	20 18 -11	; "y1"
	35	[1168]	GETTABLE 	21 18 -7	; "y0"
	36	[1168]	SUB      	20 20 21
	37	[1168]	SETTABLE 	19 -10 20	; "h" -
	38	[1171]	GETGLOBAL	20 -12	; table
	39	[1171]	GETTABLE 	20 20 -13	; "insert"
	40	[1171]	MOVE     	21 6
	41	[1171]	SELF     	22 0 -14	; "nativeToPageRectTransform"
	42	[1171]	MOVE     	24 1
	43	[1171]	MOVE     	25 4
	44	[1171]	MOVE     	26 19
	45	[1171]	CALL     	22 5 0
	46	[1171]	CALL     	20 0 1
	47	[1162]	TFORLOOP 	11 2
	48	[1171]	JMP      	-29	; to 20
	49	[1161]	TFORLOOP 	7 1
	50	[1172]	JMP      	-35	; to 16
	51	[1174]	RETURN   	6 2
	52	[1175]	RETURN   	0 1

function <./frontend/document/koptinterface.lua:1177,1212> (71 instructions, 284 bytes at 0x7fef5751ae00)
7 params, 20 slots, 1 upvalue, 15 locals, 8 constants, 0 functions
	1	[1178]	GETUPVAL 	7 0	; logger
	2	[1178]	GETTABLE 	7 7 -1	; "dbg"
	3	[1178]	LOADK    	8 -2	; "Koptinterface: find text"
	4	[1178]	MOVE     	9 2
	5	[1178]	MOVE     	10 3
	6	[1178]	MOVE     	11 4
	7	[1178]	MOVE     	12 5
	8	[1178]	MOVE     	13 6
	9	[1178]	CALL     	7 7 1
	10	[1179]	SELF     	7 1 -3	; "getPageCount"
	11	[1179]	CALL     	7 2 2
	12	[1180]	LOADNIL  	8 9
	13	[1181]	EQ       	0 4 -4	; - 1
	14	[1181]	JMP      	18	; to 33
	15	[1183]	EQ       	0 3 -5	; - 0
	16	[1183]	JMP      	4	; to 21
	17	[1185]	MOVE     	10 6
	18	[1185]	LOADK    	9 -4	; 1
	19	[1185]	MOVE     	8 10
	20	[1185]	JMP      	29	; to 50
	21	[1186]	EQ       	0 3 -6	; - -1
	22	[1186]	JMP      	4	; to 27
	23	[1188]	MOVE     	10 7
	24	[1188]	ADD      	9 6 -4	; - 1
	25	[1188]	MOVE     	8 10
	26	[1188]	JMP      	23	; to 50
	27	[1189]	EQ       	0 3 -4	; - 1
	28	[1189]	JMP      	21	; to 50
	29	[1190]	SUB      	10 6 -4	; - 1
	30	[1190]	LOADK    	9 -4	; 1
	31	[1190]	MOVE     	8 10
	32	[1191]	JMP      	17	; to 50
	33	[1194]	EQ       	0 3 -5	; - 0
	34	[1194]	JMP      	4	; to 39
	35	[1196]	MOVE     	10 6
	36	[1196]	MOVE     	9 7
	37	[1196]	MOVE     	8 10
	38	[1196]	JMP      	11	; to 50
	39	[1197]	EQ       	0 3 -6	; - -1
	40	[1197]	JMP      	4	; to 45
	41	[1199]	LOADK    	10 -4	; 1
	42	[1199]	SUB      	9 6 -4	; - 1
	43	[1199]	MOVE     	8 10
	44	[1199]	JMP      	5	; to 50
	45	[1200]	EQ       	0 3 -4	; - 1
	46	[1200]	JMP      	3	; to 50
	47	[1202]	ADD      	10 6 -4	; - 1
	48	[1202]	MOVE     	9 7
	49	[1202]	MOVE     	8 10
	50	[1205]	MOVE     	10 8
	51	[1205]	MOVE     	11 9
	52	[1205]	EQ       	0 4 -4	; - 1
	53	[1205]	JMP      	3	; to 57
	54	[1205]	LOADK    	12 -6	; -1
	55	[1205]	TEST     	12 0 1
	56	[1205]	JMP      	1	; to 58
	57	[1205]	LOADK    	12 -4	; 1
	58	[1205]	FORPREP  	10 11	; to 70
	59	[1206]	SELF     	14 0 -7	; "findAllMatches"
	60	[1206]	MOVE     	16 1
	61	[1206]	MOVE     	17 2
	62	[1206]	MOVE     	18 5
	63	[1206]	MOVE     	19 13
	64	[1206]	CALL     	14 6 2
	65	[1207]	LEN      	15 14
	66	[1207]	LT       	0 -5 15	; 0 -
	67	[1207]	JMP      	2	; to 70
	68	[1208]	SETTABLE 	14 -8 13	; "page" -
	69	[1209]	RETURN   	14 2
	70	[1205]	FORLOOP  	10 -12	; to 59
	71	[1212]	RETURN   	0 1

function <./frontend/document/koptinterface.lua:1217,1226> (26 instructions, 104 bytes at 0x7fef5751b2e0)
3 params, 10 slots, 0 upvalues, 4 locals, 13 constants, 0 functions
	1	[1218]	GETGLOBAL	3 -1	; io
	2	[1218]	GETTABLE 	3 3 -2	; "open"
	3	[1218]	LOADK    	4 -3	; "reflow_dur_log.txt"
	4	[1218]	LOADK    	5 -4	; "a+"
	5	[1218]	CALL     	3 3 2
	6	[1219]	TEST     	3 0 0
	7	[1219]	JMP      	18	; to 26
	8	[1220]	SELF     	4 3 -5	; "seek"
	9	[1220]	LOADK    	6 -6	; "end"
	10	[1220]	CALL     	4 3 2
	11	[1220]	EQ       	0 4 -7	; - 0
	12	[1220]	JMP      	3	; to 16
	13	[1221]	SELF     	4 3 -8	; "write"
	14	[1221]	LOADK    	6 -9	; "PAGE\tDUR\n"
	15	[1221]	CALL     	4 3 1
	16	[1223]	SELF     	4 3 -8	; "write"
	17	[1223]	GETGLOBAL	6 -10	; string
	18	[1223]	GETTABLE 	6 6 -11	; "format"
	19	[1223]	LOADK    	7 -12	; "%s\t%s\n"
	20	[1223]	MOVE     	8 1
	21	[1223]	MOVE     	9 2
	22	[1223]	CALL     	6 4 0
	23	[1223]	CALL     	4 0 1
	24	[1224]	SELF     	4 3 -13	; "close"
	25	[1224]	CALL     	4 2 1
	26	[1226]	RETURN   	0 1
