
main <./spec/unit/koptinterface_spec.lua:0,0> (5 instructions, 20 bytes at 0x7faae44068d0)
0+ params, 3 slots, 0 upvalues, 0 locals, 2 constants, 1 function
	1	[1]	GETGLOBAL	0 -1	; describe
	2	[1]	LOADK    	1 -2	; "Koptinterface module"
	3	[150]	CLOSURE  	2 0	; 0x7faae4406b70
	4	[1]	CALL     	0 3 1
	5	[150]	RETURN   	0 1

function <./spec/unit/koptinterface_spec.lua:1,150> (112 instructions, 448 bytes at 0x7faae4406b70)
0 params, 12 slots, 0 upvalues, 9 locals, 21 constants, 17 functions
	1	[3]	GETGLOBAL	3 -1	; setup
	2	[8]	CLOSURE  	4 0	; 0x7faae4406ed0
	3	[8]	MOVE     	0 0
	4	[8]	MOVE     	0 1
	5	[8]	MOVE     	0 2
	6	[3]	CALL     	3 2 1
	7	[10]	LOADK    	3 -2	; "spec/front/unit/data/tall.pdf"
	8	[11]	LOADK    	4 -3	; "spec/front/unit/data/sample.pdf"
	9	[12]	LOADK    	5 -4	; "spec/front/unit/data/paper.pdf"
	10	[13]	LOADNIL  	6 8
	11	[15]	GETGLOBAL	9 -5	; before_each
	12	[23]	CLOSURE  	10 1	; 0x7faae4407900
	13	[23]	MOVE     	0 6
	14	[23]	MOVE     	0 0
	15	[23]	MOVE     	0 3
	16	[23]	MOVE     	0 7
	17	[23]	MOVE     	0 4
	18	[23]	MOVE     	0 8
	19	[23]	MOVE     	0 5
	20	[23]	MOVE     	0 2
	21	[15]	CALL     	9 2 1
	22	[25]	GETGLOBAL	9 -6	; after_each
	23	[29]	CLOSURE  	10 2	; 0x7faae4407580
	24	[29]	MOVE     	0 6
	25	[29]	MOVE     	0 7
	26	[29]	MOVE     	0 8
	27	[25]	CALL     	9 2 1
	28	[31]	GETGLOBAL	9 -7	; it
	29	[31]	LOADK    	10 -8	; "should get auto bbox"
	30	[37]	CLOSURE  	11 3	; 0x7faae4407680
	31	[37]	MOVE     	0 1
	32	[37]	MOVE     	0 6
	33	[31]	CALL     	9 3 1
	34	[39]	GETGLOBAL	9 -7	; it
	35	[39]	LOADK    	10 -9	; "should get semi auto bbox"
	36	[54]	CLOSURE  	11 4	; 0x7faae4407170
	37	[54]	MOVE     	0 1
	38	[54]	MOVE     	0 6
	39	[39]	CALL     	9 3 1
	40	[56]	GETGLOBAL	9 -7	; it
	41	[56]	LOADK    	10 -10	; "should render optimized page to de-watermark"
	42	[62]	CLOSURE  	11 5	; 0x7faae44087a0
	43	[62]	MOVE     	0 6
	44	[62]	MOVE     	0 1
	45	[56]	CALL     	9 3 1
	46	[64]	GETGLOBAL	9 -7	; it
	47	[64]	LOADK    	10 -11	; "should reflow page in foreground"
	48	[68]	CLOSURE  	11 6	; 0x7faae4408c90
	49	[68]	MOVE     	0 6
	50	[68]	MOVE     	0 1
	51	[64]	CALL     	9 3 1
	52	[70]	GETGLOBAL	9 -7	; it
	53	[70]	LOADK    	10 -12	; "should hint reflowed page in background"
	54	[76]	CLOSURE  	11 7	; 0x7faae44093e0
	55	[76]	MOVE     	0 6
	56	[76]	MOVE     	0 1
	57	[70]	CALL     	9 3 1
	58	[78]	GETGLOBAL	9 -7	; it
	59	[78]	LOADK    	10 -13	; "should get native text boxes"
	60	[83]	CLOSURE  	11 8	; 0x7faae4409930
	61	[83]	MOVE     	0 1
	62	[83]	MOVE     	0 6
	63	[78]	CALL     	9 3 1
	64	[85]	GETGLOBAL	9 -7	; it
	65	[85]	LOADK    	10 -14	; "should get native text boxes from scratch"
	66	[90]	CLOSURE  	11 9	; 0x7faae44084a0
	67	[90]	MOVE     	0 1
	68	[90]	MOVE     	0 6
	69	[85]	CALL     	9 3 1
	70	[92]	GETGLOBAL	9 -7	; it
	71	[92]	LOADK    	10 -15	; "should get reflow text boxes"
	72	[98]	CLOSURE  	11 10	; 0x7faae440a010
	73	[98]	MOVE     	0 6
	74	[98]	MOVE     	0 1
	75	[92]	CALL     	9 3 1
	76	[100]	GETGLOBAL	9 -7	; it
	77	[100]	LOADK    	10 -16	; "should get reflow text boxes from scratch"
	78	[106]	CLOSURE  	11 11	; 0x7faae440a5d0
	79	[106]	MOVE     	0 6
	80	[106]	MOVE     	0 1
	81	[100]	CALL     	9 3 1
	82	[108]	GETGLOBAL	9 -7	; it
	83	[108]	LOADK    	10 -17	; "should get page block of a two-column page"
	84	[115]	CLOSURE  	11 12	; 0x7faae4408690
	85	[115]	MOVE     	0 1
	86	[115]	MOVE     	0 7
	87	[108]	CALL     	9 3 1
	88	[117]	GETGLOBAL	9 -7	; it
	89	[117]	LOADK    	10 -18	; "should get word from native position"
	90	[122]	CLOSURE  	11 13	; 0x7faae440b050
	91	[122]	MOVE     	0 1
	92	[122]	MOVE     	0 7
	93	[117]	CALL     	9 3 1
	94	[124]	GETGLOBAL	9 -7	; it
	95	[124]	LOADK    	10 -19	; "should get word from reflow position"
	96	[131]	CLOSURE  	11 14	; 0x7faae440b310
	97	[131]	MOVE     	0 7
	98	[131]	MOVE     	0 1
	99	[124]	CALL     	9 3 1
	100	[133]	GETGLOBAL	9 -7	; it
	101	[133]	LOADK    	10 -20	; "should get link from native position"
	102	[140]	CLOSURE  	11 15	; 0x7faae440b860
	103	[140]	MOVE     	0 1
	104	[140]	MOVE     	0 8
	105	[133]	CALL     	9 3 1
	106	[142]	GETGLOBAL	9 -7	; it
	107	[142]	LOADK    	10 -21	; "should get link from reflow position"
	108	[149]	CLOSURE  	11 16	; 0x7faae440bc60
	109	[149]	MOVE     	0 8
	110	[149]	MOVE     	0 1
	111	[142]	CALL     	9 3 1
	112	[150]	RETURN   	0 1

function <./spec/unit/koptinterface_spec.lua:3,8> (16 instructions, 64 bytes at 0x7faae4406ed0)
0 params, 2 slots, 3 upvalues, 0 locals, 5 constants, 0 functions
	1	[4]	GETGLOBAL	0 -1	; require
	2	[4]	LOADK    	1 -2	; "commonrequire"
	3	[4]	CALL     	0 2 1
	4	[5]	GETGLOBAL	0 -1	; require
	5	[5]	LOADK    	1 -3	; "document/documentregistry"
	6	[5]	CALL     	0 2 2
	7	[5]	SETUPVAL 	0 0	; DocumentRegistry
	8	[6]	GETGLOBAL	0 -1	; require
	9	[6]	LOADK    	1 -4	; "document/koptinterface"
	10	[6]	CALL     	0 2 2
	11	[6]	SETUPVAL 	0 1	; Koptinterface
	12	[7]	GETGLOBAL	0 -1	; require
	13	[7]	LOADK    	1 -5	; "cache"
	14	[7]	CALL     	0 2 2
	15	[7]	SETUPVAL 	0 2	; Cache
	16	[8]	RETURN   	0 1

function <./spec/unit/koptinterface_spec.lua:15,23> (28 instructions, 112 bytes at 0x7faae4407900)
0 params, 3 slots, 8 upvalues, 0 locals, 5 constants, 0 functions
	1	[16]	GETUPVAL 	0 1	; DocumentRegistry
	2	[16]	SELF     	0 0 -1	; "openDocument"
	3	[16]	GETUPVAL 	2 2	; tall_pdf
	4	[16]	CALL     	0 3 2
	5	[16]	SETUPVAL 	0 0	; doc
	6	[17]	GETUPVAL 	0 1	; DocumentRegistry
	7	[17]	SELF     	0 0 -1	; "openDocument"
	8	[17]	GETUPVAL 	2 4	; complex_pdf
	9	[17]	CALL     	0 3 2
	10	[17]	SETUPVAL 	0 3	; complex_doc
	11	[18]	GETUPVAL 	0 1	; DocumentRegistry
	12	[18]	SELF     	0 0 -1	; "openDocument"
	13	[18]	GETUPVAL 	2 6	; paper_pdf
	14	[18]	CALL     	0 3 2
	15	[18]	SETUPVAL 	0 5	; paper_doc
	16	[19]	GETUPVAL 	0 0	; doc
	17	[19]	GETTABLE 	0 0 -2	; "configurable"
	18	[19]	SETTABLE 	0 -3 -4	; "text_wrap" 0
	19	[20]	GETUPVAL 	0 3	; complex_doc
	20	[20]	GETTABLE 	0 0 -2	; "configurable"
	21	[20]	SETTABLE 	0 -3 -4	; "text_wrap" 0
	22	[21]	GETUPVAL 	0 5	; paper_doc
	23	[21]	GETTABLE 	0 0 -2	; "configurable"
	24	[21]	SETTABLE 	0 -3 -4	; "text_wrap" 0
	25	[22]	GETUPVAL 	0 7	; Cache
	26	[22]	SELF     	0 0 -5	; "clear"
	27	[22]	CALL     	0 2 1
	28	[23]	RETURN   	0 1

function <./spec/unit/koptinterface_spec.lua:25,29> (10 instructions, 40 bytes at 0x7faae4407580)
0 params, 2 slots, 3 upvalues, 0 locals, 1 constant, 0 functions
	1	[26]	GETUPVAL 	0 0	; doc
	2	[26]	SELF     	0 0 -1	; "close"
	3	[26]	CALL     	0 2 1
	4	[27]	GETUPVAL 	0 1	; complex_doc
	5	[27]	SELF     	0 0 -1	; "close"
	6	[27]	CALL     	0 2 1
	7	[28]	GETUPVAL 	0 2	; paper_doc
	8	[28]	SELF     	0 0 -1	; "close"
	9	[28]	CALL     	0 2 1
	10	[29]	RETURN   	0 1

function <./spec/unit/koptinterface_spec.lua:31,37> (34 instructions, 136 bytes at 0x7faae4407680)
0 params, 5 slots, 2 upvalues, 1 local, 14 constants, 0 functions
	1	[32]	GETUPVAL 	0 0	; Koptinterface
	2	[32]	SELF     	0 0 -1	; "getAutoBBox"
	3	[32]	GETUPVAL 	2 1	; doc
	4	[32]	LOADK    	3 -2	; 1
	5	[32]	CALL     	0 4 2
	6	[33]	GETGLOBAL	1 -3	; assert
	7	[33]	GETTABLE 	1 1 -4	; "is"
	8	[33]	GETTABLE 	1 1 -5	; "near"
	9	[33]	LOADK    	2 -6	; 22
	10	[33]	GETTABLE 	3 0 -7	; "x0"
	11	[33]	LOADK    	4 -8	; 0.5
	12	[33]	CALL     	1 4 1
	13	[34]	GETGLOBAL	1 -3	; assert
	14	[34]	GETTABLE 	1 1 -4	; "is"
	15	[34]	GETTABLE 	1 1 -5	; "near"
	16	[34]	LOADK    	2 -9	; 38
	17	[34]	GETTABLE 	3 0 -10	; "y0"
	18	[34]	LOADK    	4 -8	; 0.5
	19	[34]	CALL     	1 4 1
	20	[35]	GETGLOBAL	1 -3	; assert
	21	[35]	GETTABLE 	1 1 -4	; "is"
	22	[35]	GETTABLE 	1 1 -5	; "near"
	23	[35]	LOADK    	2 -11	; 548
	24	[35]	GETTABLE 	3 0 -12	; "x1"
	25	[35]	LOADK    	4 -8	; 0.5
	26	[35]	CALL     	1 4 1
	27	[36]	GETGLOBAL	1 -3	; assert
	28	[36]	GETTABLE 	1 1 -4	; "is"
	29	[36]	GETTABLE 	1 1 -5	; "near"
	30	[36]	LOADK    	2 -13	; 1387
	31	[36]	GETTABLE 	3 0 -14	; "y1"
	32	[36]	LOADK    	4 -8	; 0.5
	33	[36]	CALL     	1 4 1
	34	[37]	RETURN   	0 1

function <./spec/unit/koptinterface_spec.lua:39,54> (59 instructions, 236 bytes at 0x7faae4407170)
0 params, 7 slots, 2 upvalues, 3 locals, 13 constants, 0 functions
	1	[40]	GETUPVAL 	0 0	; Koptinterface
	2	[40]	SELF     	0 0 -1	; "getSemiAutoBBox"
	3	[40]	GETUPVAL 	2 1	; doc
	4	[40]	LOADK    	3 -2	; 1
	5	[40]	CALL     	0 4 2
	6	[41]	GETUPVAL 	1 1	; doc
	7	[41]	SELF     	1 1 -3	; "getPageBBox"
	8	[41]	LOADK    	3 -2	; 1
	9	[41]	CALL     	1 3 2
	10	[42]	GETUPVAL 	2 1	; doc
	11	[42]	GETTABLE 	2 2 -4	; "bbox"
	12	[42]	NEWTABLE 	3 0 4
	13	[43]	GETTABLE 	4 1 -5	; "x0"
	14	[43]	ADD      	4 4 -6	; - 10
	15	[43]	SETTABLE 	3 -5 4	; "x0" -
	16	[44]	GETTABLE 	4 1 -7	; "y0"
	17	[44]	ADD      	4 4 -6	; - 10
	18	[44]	SETTABLE 	3 -7 4	; "y0" -
	19	[45]	GETTABLE 	4 1 -8	; "x1"
	20	[45]	SUB      	4 4 -6	; - 10
	21	[45]	SETTABLE 	3 -8 4	; "x1" -
	22	[46]	GETTABLE 	4 1 -9	; "y1"
	23	[46]	SUB      	4 4 -6	; - 10
	24	[46]	SETTABLE 	3 -9 4	; "y1" -
	25	[47]	SETTABLE 	2 -2 3	; 1 -
	26	[49]	GETUPVAL 	2 0	; Koptinterface
	27	[49]	SELF     	2 2 -1	; "getSemiAutoBBox"
	28	[49]	GETUPVAL 	4 1	; doc
	29	[49]	LOADK    	5 -2	; 1
	30	[49]	CALL     	2 4 2
	31	[50]	GETGLOBAL	3 -10	; assert
	32	[50]	GETTABLE 	3 3 -11	; "is_not"
	33	[50]	GETTABLE 	3 3 -12	; "near"
	34	[50]	GETTABLE 	4 0 -5	; "x0"
	35	[50]	GETTABLE 	5 2 -5	; "x0"
	36	[50]	LOADK    	6 -13	; 0.5
	37	[50]	CALL     	3 4 1
	38	[51]	GETGLOBAL	3 -10	; assert
	39	[51]	GETTABLE 	3 3 -11	; "is_not"
	40	[51]	GETTABLE 	3 3 -12	; "near"
	41	[51]	GETTABLE 	4 0 -7	; "y0"
	42	[51]	GETTABLE 	5 2 -7	; "y0"
	43	[51]	LOADK    	6 -13	; 0.5
	44	[51]	CALL     	3 4 1
	45	[52]	GETGLOBAL	3 -10	; assert
	46	[52]	GETTABLE 	3 3 -11	; "is_not"
	47	[52]	GETTABLE 	3 3 -12	; "near"
	48	[52]	GETTABLE 	4 0 -8	; "x1"
	49	[52]	GETTABLE 	5 2 -8	; "x1"
	50	[52]	LOADK    	6 -13	; 0.5
	51	[52]	CALL     	3 4 1
	52	[53]	GETGLOBAL	3 -10	; assert
	53	[53]	GETTABLE 	3 3 -11	; "is_not"
	54	[53]	GETTABLE 	3 3 -12	; "near"
	55	[53]	GETTABLE 	4 0 -9	; "y1"
	56	[53]	GETTABLE 	5 2 -9	; "y1"
	57	[53]	LOADK    	6 -13	; 0.5
	58	[53]	CALL     	3 4 1
	59	[54]	RETURN   	0 1

function <./spec/unit/koptinterface_spec.lua:56,62> (26 instructions, 104 bytes at 0x7faae44087a0)
0 params, 9 slots, 2 upvalues, 2 locals, 9 constants, 0 functions
	1	[57]	GETUPVAL 	0 0	; doc
	2	[57]	SELF     	0 0 -1	; "getPageDimensions"
	3	[57]	LOADK    	2 -2	; 1
	4	[57]	LOADK    	3 -2	; 1
	5	[57]	LOADK    	4 -3	; 0
	6	[57]	CALL     	0 5 2
	7	[58]	GETUPVAL 	1 1	; Koptinterface
	8	[58]	SELF     	1 1 -4	; "renderOptimizedPage"
	9	[58]	GETUPVAL 	3 0	; doc
	10	[58]	LOADK    	4 -2	; 1
	11	[58]	LOADNIL  	5 5
	12	[59]	LOADK    	6 -2	; 1
	13	[59]	LOADK    	7 -3	; 0
	14	[59]	LOADK    	8 -3	; 0
	15	[58]	CALL     	1 8 2
	16	[60]	GETGLOBAL	2 -5	; assert
	17	[60]	GETTABLE 	2 2 -6	; "truthy"
	18	[60]	MOVE     	3 1
	19	[60]	CALL     	2 2 1
	20	[61]	GETGLOBAL	2 -5	; assert
	21	[61]	GETTABLE 	2 2 -7	; "are"
	22	[61]	GETTABLE 	2 2 -8	; "same"
	23	[61]	MOVE     	3 0
	24	[61]	GETTABLE 	4 1 -9	; "excerpt"
	25	[61]	CALL     	2 3 1
	26	[62]	RETURN   	0 1

function <./spec/unit/koptinterface_spec.lua:64,68> (13 instructions, 52 bytes at 0x7faae4408c90)
0 params, 4 slots, 2 upvalues, 1 local, 6 constants, 0 functions
	1	[65]	GETUPVAL 	0 0	; doc
	2	[65]	GETTABLE 	0 0 -1	; "configurable"
	3	[65]	SETTABLE 	0 -2 -3	; "text_wrap" 1
	4	[66]	GETUPVAL 	0 1	; Koptinterface
	5	[66]	SELF     	0 0 -4	; "getCachedContext"
	6	[66]	GETUPVAL 	2 0	; doc
	7	[66]	LOADK    	3 -3	; 1
	8	[66]	CALL     	0 4 2
	9	[67]	GETGLOBAL	1 -5	; assert
	10	[67]	GETTABLE 	1 1 -6	; "truthy"
	11	[67]	MOVE     	2 0
	12	[67]	CALL     	1 2 1
	13	[68]	RETURN   	0 1

function <./spec/unit/koptinterface_spec.lua:70,76> (22 instructions, 88 bytes at 0x7faae44093e0)
0 params, 8 slots, 2 upvalues, 1 local, 8 constants, 0 functions
	1	[71]	GETUPVAL 	0 0	; doc
	2	[71]	GETTABLE 	0 0 -1	; "configurable"
	3	[71]	SETTABLE 	0 -2 -3	; "text_wrap" 1
	4	[72]	GETUPVAL 	0 1	; Koptinterface
	5	[72]	SELF     	0 0 -4	; "hintReflowedPage"
	6	[72]	GETUPVAL 	2 0	; doc
	7	[72]	LOADK    	3 -3	; 1
	8	[72]	LOADK    	4 -3	; 1
	9	[72]	LOADK    	5 -5	; 0
	10	[72]	LOADK    	6 -3	; 1
	11	[72]	LOADK    	7 -5	; 0
	12	[72]	CALL     	0 8 1
	13	[74]	GETUPVAL 	0 1	; Koptinterface
	14	[74]	SELF     	0 0 -6	; "getCachedContext"
	15	[74]	GETUPVAL 	2 0	; doc
	16	[74]	LOADK    	3 -3	; 1
	17	[74]	CALL     	0 4 2
	18	[75]	GETGLOBAL	1 -7	; assert
	19	[75]	GETTABLE 	1 1 -8	; "truthy"
	20	[75]	MOVE     	2 0
	21	[75]	CALL     	1 2 1
	22	[76]	RETURN   	0 1

function <./spec/unit/koptinterface_spec.lua:78,83> (19 instructions, 76 bytes at 0x7faae4409930)
0 params, 4 slots, 2 upvalues, 2 locals, 6 constants, 0 functions
	1	[79]	GETUPVAL 	0 0	; Koptinterface
	2	[79]	SELF     	0 0 -1	; "getCachedContext"
	3	[79]	GETUPVAL 	2 1	; doc
	4	[79]	LOADK    	3 -2	; 1
	5	[79]	CALL     	0 4 1
	6	[80]	GETUPVAL 	0 0	; Koptinterface
	7	[80]	SELF     	0 0 -3	; "getNativeTextBoxes"
	8	[80]	GETUPVAL 	2 1	; doc
	9	[80]	LOADK    	3 -2	; 1
	10	[80]	CALL     	0 4 2
	11	[81]	LEN      	1 0
	12	[82]	GETGLOBAL	2 -4	; assert
	13	[82]	GETTABLE 	2 2 -5	; "truthy"
	14	[82]	EQ       	1 1 -6	; - 60
	15	[82]	JMP      	1	; to 17
	16	[82]	LOADBOOL 	3 0 1
	17	[82]	LOADBOOL 	3 1 0
	18	[82]	CALL     	2 2 1
	19	[83]	RETURN   	0 1

function <./spec/unit/koptinterface_spec.lua:85,90> (19 instructions, 76 bytes at 0x7faae44084a0)
0 params, 4 slots, 2 upvalues, 2 locals, 6 constants, 0 functions
	1	[86]	GETUPVAL 	0 0	; Koptinterface
	2	[86]	SELF     	0 0 -1	; "getCachedContext"
	3	[86]	GETUPVAL 	2 1	; doc
	4	[86]	LOADK    	3 -2	; 1
	5	[86]	CALL     	0 4 1
	6	[87]	GETUPVAL 	0 0	; Koptinterface
	7	[87]	SELF     	0 0 -3	; "getNativeTextBoxesFromScratch"
	8	[87]	GETUPVAL 	2 1	; doc
	9	[87]	LOADK    	3 -2	; 1
	10	[87]	CALL     	0 4 2
	11	[88]	LEN      	1 0
	12	[89]	GETGLOBAL	2 -4	; assert
	13	[89]	GETTABLE 	2 2 -5	; "truthy"
	14	[89]	EQ       	1 1 -6	; - 60
	15	[89]	JMP      	1	; to 17
	16	[89]	LOADBOOL 	3 0 1
	17	[89]	LOADBOOL 	3 1 0
	18	[89]	CALL     	2 2 1
	19	[90]	RETURN   	0 1

function <./spec/unit/koptinterface_spec.lua:92,98> (22 instructions, 88 bytes at 0x7faae440a010)
0 params, 4 slots, 2 upvalues, 2 locals, 8 constants, 0 functions
	1	[93]	GETUPVAL 	0 0	; doc
	2	[93]	GETTABLE 	0 0 -1	; "configurable"
	3	[93]	SETTABLE 	0 -2 -3	; "text_wrap" 1
	4	[94]	GETUPVAL 	0 1	; Koptinterface
	5	[94]	SELF     	0 0 -4	; "getCachedContext"
	6	[94]	GETUPVAL 	2 0	; doc
	7	[94]	LOADK    	3 -3	; 1
	8	[94]	CALL     	0 4 1
	9	[95]	GETUPVAL 	0 1	; Koptinterface
	10	[95]	SELF     	0 0 -5	; "getReflowedTextBoxes"
	11	[95]	GETUPVAL 	2 0	; doc
	12	[95]	LOADK    	3 -3	; 1
	13	[95]	CALL     	0 4 2
	14	[96]	LEN      	1 0
	15	[97]	GETGLOBAL	2 -6	; assert
	16	[97]	GETTABLE 	2 2 -7	; "truthy"
	17	[97]	LT       	1 -8 1	; 60 -
	18	[97]	JMP      	1	; to 20
	19	[97]	LOADBOOL 	3 0 1
	20	[97]	LOADBOOL 	3 1 0
	21	[97]	CALL     	2 2 1
	22	[98]	RETURN   	0 1

function <./spec/unit/koptinterface_spec.lua:100,106> (22 instructions, 88 bytes at 0x7faae440a5d0)
0 params, 4 slots, 2 upvalues, 2 locals, 8 constants, 0 functions
	1	[101]	GETUPVAL 	0 0	; doc
	2	[101]	GETTABLE 	0 0 -1	; "configurable"
	3	[101]	SETTABLE 	0 -2 -3	; "text_wrap" 1
	4	[102]	GETUPVAL 	0 1	; Koptinterface
	5	[102]	SELF     	0 0 -4	; "getCachedContext"
	6	[102]	GETUPVAL 	2 0	; doc
	7	[102]	LOADK    	3 -3	; 1
	8	[102]	CALL     	0 4 1
	9	[103]	GETUPVAL 	0 1	; Koptinterface
	10	[103]	SELF     	0 0 -5	; "getReflowedTextBoxesFromScratch"
	11	[103]	GETUPVAL 	2 0	; doc
	12	[103]	LOADK    	3 -3	; 1
	13	[103]	CALL     	0 4 2
	14	[104]	LEN      	1 0
	15	[105]	GETGLOBAL	2 -6	; assert
	16	[105]	GETTABLE 	2 2 -7	; "truthy"
	17	[105]	LT       	1 -8 1	; 60 -
	18	[105]	JMP      	1	; to 20
	19	[105]	LOADBOOL 	3 0 1
	20	[105]	LOADBOOL 	3 1 0
	21	[105]	CALL     	2 2 1
	22	[106]	RETURN   	0 1

function <./spec/unit/koptinterface_spec.lua:108,115> (28 instructions, 112 bytes at 0x7faae4408690)
0 params, 14 slots, 2 upvalues, 9 locals, 9 constants, 0 functions
	1	[109]	LOADK    	0 -1	; 0.3
	2	[109]	LOADK    	1 -2	; 0.6
	3	[109]	LOADK    	2 -1	; 0.3
	4	[109]	FORPREP  	0 22	; to 27
	5	[110]	LOADK    	4 -1	; 0.3
	6	[110]	LOADK    	5 -2	; 0.6
	7	[110]	LOADK    	6 -1	; 0.3
	8	[110]	FORPREP  	4 17	; to 26
	9	[111]	GETUPVAL 	8 0	; Koptinterface
	10	[111]	SELF     	8 8 -3	; "getPageBlock"
	11	[111]	GETUPVAL 	10 1	; complex_doc
	12	[111]	LOADK    	11 -4	; 34
	13	[111]	MOVE     	12 3
	14	[111]	MOVE     	13 7
	15	[111]	CALL     	8 6 2
	16	[112]	GETGLOBAL	9 -5	; assert
	17	[112]	GETTABLE 	9 9 -6	; "truthy"
	18	[112]	GETTABLE 	10 8 -7	; "x1"
	19	[112]	GETTABLE 	11 8 -8	; "x0"
	20	[112]	SUB      	10 10 11
	21	[112]	LT       	1 10 -9	; - 0.5
	22	[112]	JMP      	1	; to 24
	23	[112]	LOADBOOL 	10 0 1
	24	[112]	LOADBOOL 	10 1 0
	25	[112]	CALL     	9 2 1
	26	[110]	FORLOOP  	4 -18	; to 9
	27	[109]	FORLOOP  	0 -23	; to 5
	28	[115]	RETURN   	0 1

function <./spec/unit/koptinterface_spec.lua:117,122> (15 instructions, 60 bytes at 0x7faae440b050)
0 params, 4 slots, 2 upvalues, 1 local, 12 constants, 0 functions
	1	[118]	GETUPVAL 	0 0	; Koptinterface
	2	[118]	SELF     	0 0 -1	; "getWordFromPosition"
	3	[118]	GETUPVAL 	2 1	; complex_doc
	4	[118]	NEWTABLE 	3 0 3
	5	[119]	SETTABLE 	3 -2 -3	; "page" 19
	6	[119]	SETTABLE 	3 -4 -5	; "x" 400
	7	[119]	SETTABLE 	3 -6 -7	; "y" 530
	8	[118]	CALL     	0 4 2
	9	[121]	GETGLOBAL	1 -8	; assert
	10	[121]	GETTABLE 	1 1 -9	; "is"
	11	[121]	GETTABLE 	1 1 -10	; "same"
	12	[121]	LOADK    	2 -11	; "previous"
	13	[121]	GETTABLE 	3 0 -12	; "word"
	14	[121]	CALL     	1 3 1
	15	[122]	RETURN   	0 1

function <./spec/unit/koptinterface_spec.lua:124,131> (23 instructions, 92 bytes at 0x7faae440b310)
0 params, 4 slots, 2 upvalues, 1 local, 16 constants, 0 functions
	1	[125]	GETUPVAL 	0 0	; complex_doc
	2	[125]	GETTABLE 	0 0 -1	; "configurable"
	3	[125]	SETTABLE 	0 -2 -3	; "text_wrap" 1
	4	[126]	GETUPVAL 	0 1	; Koptinterface
	5	[126]	SELF     	0 0 -4	; "getCachedContext"
	6	[126]	GETUPVAL 	2 0	; complex_doc
	7	[126]	LOADK    	3 -5	; 19
	8	[126]	CALL     	0 4 1
	9	[127]	GETUPVAL 	0 1	; Koptinterface
	10	[127]	SELF     	0 0 -6	; "getWordFromPosition"
	11	[127]	GETUPVAL 	2 0	; complex_doc
	12	[127]	NEWTABLE 	3 0 3
	13	[128]	SETTABLE 	3 -7 -5	; "page" 19
	14	[128]	SETTABLE 	3 -8 -9	; "x" 320
	15	[128]	SETTABLE 	3 -10 -11	; "y" 730
	16	[127]	CALL     	0 4 2
	17	[130]	GETGLOBAL	1 -12	; assert
	18	[130]	GETTABLE 	1 1 -13	; "is"
	19	[130]	GETTABLE 	1 1 -14	; "same"
	20	[130]	LOADK    	2 -15	; "examples"
	21	[130]	GETTABLE 	3 0 -16	; "word"
	22	[130]	CALL     	1 3 1
	23	[131]	RETURN   	0 1

function <./spec/unit/koptinterface_spec.lua:133,140> (26 instructions, 104 bytes at 0x7faae440b860)
0 params, 5 slots, 2 upvalues, 1 local, 16 constants, 0 functions
	1	[134]	GETUPVAL 	0 0	; Koptinterface
	2	[134]	SELF     	0 0 -1	; "getLinkFromPosition"
	3	[134]	GETUPVAL 	2 1	; paper_doc
	4	[134]	LOADK    	3 -2	; 1
	5	[134]	NEWTABLE 	4 0 2
	6	[135]	SETTABLE 	4 -3 -4	; "x" 140
	7	[135]	SETTABLE 	4 -5 -6	; "y" 560
	8	[134]	CALL     	0 5 2
	9	[137]	GETGLOBAL	1 -7	; assert
	10	[137]	GETTABLE 	1 1 -8	; "truthy"
	11	[137]	MOVE     	2 0
	12	[137]	CALL     	1 2 1
	13	[138]	GETGLOBAL	1 -7	; assert
	14	[138]	GETTABLE 	1 1 -9	; "is"
	15	[138]	GETTABLE 	1 1 -10	; "same"
	16	[138]	LOADK    	2 -11	; 20
	17	[138]	GETTABLE 	3 0 -12	; "page"
	18	[138]	CALL     	1 3 1
	19	[139]	GETGLOBAL	1 -13	; require
	20	[139]	LOADK    	2 -14	; "dbg"
	21	[139]	CALL     	1 2 2
	22	[139]	SELF     	1 1 -15	; "v"
	23	[139]	LOADK    	3 -16	; "link"
	24	[139]	MOVE     	4 0
	25	[139]	CALL     	1 4 1
	26	[140]	RETURN   	0 1

function <./spec/unit/koptinterface_spec.lua:142,149> (22 instructions, 88 bytes at 0x7faae440bc60)
0 params, 5 slots, 2 upvalues, 1 local, 14 constants, 0 functions
	1	[143]	GETUPVAL 	0 0	; paper_doc
	2	[143]	GETTABLE 	0 0 -1	; "configurable"
	3	[143]	SETTABLE 	0 -2 -3	; "text_wrap" 1
	4	[144]	GETUPVAL 	0 1	; Koptinterface
	5	[144]	SELF     	0 0 -4	; "getLinkFromPosition"
	6	[144]	GETUPVAL 	2 0	; paper_doc
	7	[144]	LOADK    	3 -3	; 1
	8	[144]	NEWTABLE 	4 0 2
	9	[145]	SETTABLE 	4 -5 -6	; "x" 500
	10	[145]	SETTABLE 	4 -7 -8	; "y" 480
	11	[144]	CALL     	0 5 2
	12	[147]	GETGLOBAL	1 -9	; assert
	13	[147]	GETTABLE 	1 1 -10	; "truthy"
	14	[147]	MOVE     	2 0
	15	[147]	CALL     	1 2 1
	16	[148]	GETGLOBAL	1 -9	; assert
	17	[148]	GETTABLE 	1 1 -11	; "is"
	18	[148]	GETTABLE 	1 1 -12	; "same"
	19	[148]	LOADK    	2 -13	; 20
	20	[148]	GETTABLE 	3 0 -14	; "page"
	21	[148]	CALL     	1 3 1
	22	[149]	RETURN   	0 1
