-- BYTECODE -- language.lua:69-71
0001    TGETS    2   0   0  ; "language_names"
0002    TGETV    2   2   1
0003    IST          2
0004    JMP      3 => 0006
0005    MOV      2   1
0006 => RET1     2   2

-- BYTECODE -- language.lua:73-83
0001    IST          1
0002    JMP      2 => 0005
0003    KPRI     2   1
0004    RET1     2   2
0005 => MOV      2   1
0006    MOV      4   2
0007    TGETS    3   2   0  ; "find"
0008    KSTR     5   1      ; "_"
0009    CALL     3   2   3
0010    ISF          3
0011    JMP      4 => 0018
0012    MOV      5   2
0013    TGETS    4   2   2  ; "sub"
0014    KSHORT   6   1
0015    SUBVN    7   3   0  ; 1
0016    CALL     4   2   4
0017    MOV      2   4
0018 => TGETS    4   0   3  ; "languages_rtl"
0019    TGETV    4   4   2
0020    IST          4
0021    JMP      5 => 0023
0022    KPRI     4   1
0023 => RET1     4   2

-- BYTECODE -- language.lua:85-94
0001    GGET     2   0      ; "require"
0002    KSTR     3   1      ; "ui/widget/infomessage"
0003    CALL     2   2   2
0004    GGET     3   0      ; "require"
0005    KSTR     4   2      ; "ui/uimanager"
0006    CALL     3   2   2
0007    UGET     4   0      ; _
0008    TGETS    4   4   3  ; "changeLang"
0009    MOV      5   1
0010    CALL     4   1   2
0011    GGET     4   4      ; "G_reader_settings"
0012    MOV      5   4
0013    TGETS    4   4   5  ; "saveSetting"
0014    KSTR     6   6      ; "language"
0015    MOV      7   1
0016    CALL     4   1   4
0017    MOV      5   3
0018    TGETS    4   3   7  ; "show"
0019    MOV      7   2
0020    TGETS    6   2   8  ; "new"
0021    TDUP     8  10
0022    UGET     9   0      ; _
0023    KSTR    10   9      ; "Please restart KOReader for the new lang"~
0024    CALL     9   2   2
0025    TSETS    9   8  11  ; "text"
0026    CALL     6   0   3
0027    CALLM    4   1   1
0028    RET0     0   1

-- BYTECODE -- language.lua:99-101
0001    GGET     0   0      ; "G_reader_settings"
0002    MOV      1   0
0003    TGETS    0   0   1  ; "readSetting"
0004    KSTR     2   2      ; "language"
0005    CALL     0   2   3
0006    UGET     1   0      ; lang_locale
0007    ISEQV    0   1
0008    JMP      0 => 0011
0009    KPRI     0   1
0010    JMP      1 => 0012
0011 => KPRI     0   2
0012 => RET1     0   2

-- BYTECODE -- language.lua:102-104
0001    UGET     0   0      ; self
0002    MOV      1   0
0003    TGETS    0   0   0  ; "changeLanguage"
0004    UGET     2   1      ; lang_locale
0005    CALL     0   1   3
0006    RET0     0   1

-- BYTECODE -- language.lua:96-106
0001    TDUP     2   1
0002    MOV      4   0
0003    TGETS    3   0   0  ; "getLanguageName"
0004    MOV      5   1
0005    CALL     3   2   3
0006    TSETS    3   2   2  ; "text"
0007    FNEW     3   3      ; language.lua:99
0008    TSETS    3   2   4  ; "checked_func"
0009    FNEW     3   5      ; language.lua:102
0010    TSETS    3   2   6  ; "callback"
0011    UCLO     0 => 0012
0012 => RET1     2   2

-- BYTECODE -- language.lua:108-157
0001    TGETS    1   0   0  ; "LangMenuTable"
0002    IST          1
0003    JMP      1 => 0167
0004    TDUP     1   2
0005    UGET     2   0      ; _
0006    KSTR     3   1      ; "Language"
0007    CALL     2   2   2
0008    TSETS    2   1   3  ; "text"
0009    TNEW     2  32
0010    MOV      4   0
0011    TGETS    3   0   4  ; "genLanguageSubItem"
0012    KSTR     5   5      ; "C"
0013    CALL     3   2   3
0014    TSETB    3   2   1
0015    MOV      4   0
0016    TGETS    3   0   4  ; "genLanguageSubItem"
0017    KSTR     5   6      ; "ca"
0018    CALL     3   2   3
0019    TSETB    3   2   2
0020    MOV      4   0
0021    TGETS    3   0   4  ; "genLanguageSubItem"
0022    KSTR     5   7      ; "cs_CZ"
0023    CALL     3   2   3
0024    TSETB    3   2   3
0025    MOV      4   0
0026    TGETS    3   0   4  ; "genLanguageSubItem"
0027    KSTR     5   8      ; "de"
0028    CALL     3   2   3
0029    TSETB    3   2   4
0030    MOV      4   0
0031    TGETS    3   0   4  ; "genLanguageSubItem"
0032    KSTR     5   9      ; "eo"
0033    CALL     3   2   3
0034    TSETB    3   2   5
0035    MOV      4   0
0036    TGETS    3   0   4  ; "genLanguageSubItem"
0037    KSTR     5  10      ; "es"
0038    CALL     3   2   3
0039    TSETB    3   2   6
0040    MOV      4   0
0041    TGETS    3   0   4  ; "genLanguageSubItem"
0042    KSTR     5  11      ; "eu"
0043    CALL     3   2   3
0044    TSETB    3   2   7
0045    MOV      4   0
0046    TGETS    3   0   4  ; "genLanguageSubItem"
0047    KSTR     5  12      ; "fr"
0048    CALL     3   2   3
0049    TSETB    3   2   8
0050    MOV      4   0
0051    TGETS    3   0   4  ; "genLanguageSubItem"
0052    KSTR     5  13      ; "gl"
0053    CALL     3   2   3
0054    TSETB    3   2   9
0055    MOV      4   0
0056    TGETS    3   0   4  ; "genLanguageSubItem"
0057    KSTR     5  14      ; "it_IT"
0058    CALL     3   2   3
0059    TSETB    3   2  10
0060    MOV      4   0
0061    TGETS    3   0   4  ; "genLanguageSubItem"
0062    KSTR     5  15      ; "hu"
0063    CALL     3   2   3
0064    TSETB    3   2  11
0065    MOV      4   0
0066    TGETS    3   0   4  ; "genLanguageSubItem"
0067    KSTR     5  16      ; "nl_NL"
0068    CALL     3   2   3
0069    TSETB    3   2  12
0070    MOV      4   0
0071    TGETS    3   0   4  ; "genLanguageSubItem"
0072    KSTR     5  17      ; "nb_NO"
0073    CALL     3   2   3
0074    TSETB    3   2  13
0075    MOV      4   0
0076    TGETS    3   0   4  ; "genLanguageSubItem"
0077    KSTR     5  18      ; "pl"
0078    CALL     3   2   3
0079    TSETB    3   2  14
0080    MOV      4   0
0081    TGETS    3   0   4  ; "genLanguageSubItem"
0082    KSTR     5  19      ; "pt_PT"
0083    CALL     3   2   3
0084    TSETB    3   2  15
0085    MOV      4   0
0086    TGETS    3   0   4  ; "genLanguageSubItem"
0087    KSTR     5  20      ; "pt_BR"
0088    CALL     3   2   3
0089    TSETB    3   2  16
0090    MOV      4   0
0091    TGETS    3   0   4  ; "genLanguageSubItem"
0092    KSTR     5  21      ; "ro_MD"
0093    CALL     3   2   3
0094    TSETB    3   2  17
0095    MOV      4   0
0096    TGETS    3   0   4  ; "genLanguageSubItem"
0097    KSTR     5  22      ; "sk"
0098    CALL     3   2   3
0099    TSETB    3   2  18
0100    MOV      4   0
0101    TGETS    3   0   4  ; "genLanguageSubItem"
0102    KSTR     5  23      ; "sv"
0103    CALL     3   2   3
0104    TSETB    3   2  19
0105    MOV      4   0
0106    TGETS    3   0   4  ; "genLanguageSubItem"
0107    KSTR     5  24      ; "vi"
0108    CALL     3   2   3
0109    TSETB    3   2  20
0110    MOV      4   0
0111    TGETS    3   0   4  ; "genLanguageSubItem"
0112    KSTR     5  25      ; "tr"
0113    CALL     3   2   3
0114    TSETB    3   2  21
0115    MOV      4   0
0116    TGETS    3   0   4  ; "genLanguageSubItem"
0117    KSTR     5  26      ; "vi_VN"
0118    CALL     3   2   3
0119    TSETB    3   2  22
0120    MOV      4   0
0121    TGETS    3   0   4  ; "genLanguageSubItem"
0122    KSTR     5  27      ; "ar_AA"
0123    CALL     3   2   3
0124    TSETB    3   2  23
0125    MOV      4   0
0126    TGETS    3   0   4  ; "genLanguageSubItem"
0127    KSTR     5  28      ; "bg_BG"
0128    CALL     3   2   3
0129    TSETB    3   2  24
0130    MOV      4   0
0131    TGETS    3   0   4  ; "genLanguageSubItem"
0132    KSTR     5  29      ; "el"
0133    CALL     3   2   3
0134    TSETB    3   2  25
0135    MOV      4   0
0136    TGETS    3   0   4  ; "genLanguageSubItem"
0137    KSTR     5  30      ; "ja"
0138    CALL     3   2   3
0139    TSETB    3   2  26
0140    MOV      4   0
0141    TGETS    3   0   4  ; "genLanguageSubItem"
0142    KSTR     5  31      ; "ko_KR"
0143    CALL     3   2   3
0144    TSETB    3   2  27
0145    MOV      4   0
0146    TGETS    3   0   4  ; "genLanguageSubItem"
0147    KSTR     5  32      ; "ru"
0148    CALL     3   2   3
0149    TSETB    3   2  28
0150    MOV      4   0
0151    TGETS    3   0   4  ; "genLanguageSubItem"
0152    KSTR     5  33      ; "uk"
0153    CALL     3   2   3
0154    TSETB    3   2  29
0155    MOV      4   0
0156    TGETS    3   0   4  ; "genLanguageSubItem"
0157    KSTR     5  34      ; "zh_CN"
0158    CALL     3   2   3
0159    TSETB    3   2  30
0160    MOV      4   0
0161    TGETS    3   0   4  ; "genLanguageSubItem"
0162    KSTR     5  35      ; "zh_TW"
0163    CALL     3   0   3
0164    TSETM    3   0      ; 31
0165    TSETS    2   1  36  ; "sub_item_table"
0166    TSETS    1   0   0  ; "LangMenuTable"
0167 => TGETS    1   0   0  ; "LangMenuTable"
0168    RET1     1   2

-- BYTECODE -- language.lua:0-160
0001    GGET     0   0      ; "require"
0002    KSTR     1   1      ; "gettext"
0003    CALL     0   2   2
0004    TDUP     1   3
0005    TDUP     2   2
0006    TSETS    2   1   4  ; "language_names"
0007    TDUP     2   5
0008    TSETS    2   1   6  ; "languages_rtl"
0009    FNEW     2   8      ; language.lua:69
0010    TSETS    2   1   7  ; "getLanguageName"
0011    FNEW     2  10      ; language.lua:73
0012    TSETS    2   1   9  ; "isLanguageRTL"
0013    FNEW     2  12      ; language.lua:85
0014    TSETS    2   1  11  ; "changeLanguage"
0015    FNEW     2  14      ; language.lua:96
0016    TSETS    2   1  13  ; "genLanguageSubItem"
0017    FNEW     2  16      ; language.lua:108
0018    TSETS    2   1  15  ; "getLangMenuTable"
0019    UCLO     0 => 0020
0020 => RET1     1   2

