-- BYTECODE -- leftcontainer.lua:13-24
0001    TGETB    4   0   1
0002    MOV      5   4
0003    TGETS    4   4   0  ; "getSize"
0004    CALL     4   2   2
0005    TGETS    5   0   1  ; "_mirroredUI"
0006    ISF          5
0007    JMP      6 => 0016
0008    TGETS    5   0   2  ; "allow_mirroring"
0009    ISF          5
0010    JMP      6 => 0016
0011    TGETS    5   0   3  ; "dimen"
0012    TGETS    5   5   4  ; "w"
0013    TGETS    6   4   4  ; "w"
0014    SUBVV    5   5   6
0015    ADDVV    2   2   5
0016 => TGETB    5   0   1
0017    MOV      6   5
0018    TGETS    5   5   5  ; "paintTo"
0019    MOV      7   1
0020    MOV      8   2
0021    GGET     9   6      ; "math"
0022    TGETS    9   9   7  ; "floor"
0023    TGETS   10   0   3  ; "dimen"
0024    TGETS   10  10   8  ; "h"
0025    TGETS   11   4   8  ; "h"
0026    SUBVV   10  10  11
0027    DIVVN   10  10   0  ; 2
0028    CALL     9   2   2
0029    ADDVV    9   3   9
0030    CALL     5   1   5
0031    RET0     0   1

-- BYTECODE -- leftcontainer.lua:0-27
0001    GGET     0   0      ; "require"
0002    KSTR     1   1      ; "ui/bidi"
0003    CALL     0   2   2
0004    GGET     1   0      ; "require"
0005    KSTR     2   2      ; "ui/widget/container/widgetcontainer"
0006    CALL     1   2   2
0007    MOV      3   1
0008    TGETS    2   1   3  ; "new"
0009    TDUP     4   4
0010    TGETS    5   0   5  ; "mirroredUILayout"
0011    CALL     5   2   1
0012    TSETS    5   4   6  ; "_mirroredUI"
0013    CALL     2   2   3
0014    FNEW     3   8      ; leftcontainer.lua:13
0015    TSETS    3   2   7  ; "paintTo"
0016    UCLO     0 => 0017
0017 => RET1     2   2

