
main <./frontend/ui/widget/linewidget.lua:0,0> (18 instructions, 72 bytes at 0x7fcb9a4068d0)
0+ params, 6 slots, 0 upvalues, 3 locals, 12 constants, 1 function
	1	[5]	GETGLOBAL	0 -1	; require
	2	[5]	LOADK    	1 -2	; "ffi/blitbuffer"
	3	[5]	CALL     	0 2 2
	4	[6]	GETGLOBAL	1 -1	; require
	5	[6]	LOADK    	2 -3	; "ui/widget/widget"
	6	[6]	CALL     	1 2 2
	7	[8]	SELF     	2 1 -4	; "new"
	8	[8]	NEWTABLE 	4 0 4
	9	[9]	SETTABLE 	4 -5 -6	; "style" "solid"
	10	[10]	GETTABLE 	5 0 -8	; "COLOR_BLACK"
	11	[10]	SETTABLE 	4 -7 5	; "background" -
	12	[11]	SETTABLE 	4 -9 -10	; "dimen" nil
	13	[13]	SETTABLE 	4 -11 -10	; "empty_segments" nil
	14	[8]	CALL     	2 3 2
	15	[37]	CLOSURE  	3 0	; 0x7fcb9a406bd0
	16	[16]	SETTABLE 	2 -12 3	; "paintTo" -
	17	[39]	RETURN   	2 2
	18	[39]	RETURN   	0 1

function <./frontend/ui/widget/linewidget.lua:16,37> (64 instructions, 256 bytes at 0x7fcb9a406bd0)
4 params, 15 slots, 0 upvalues, 8 locals, 15 constants, 0 functions
	1	[17]	GETTABLE 	4 0 -1	; "style"
	2	[17]	EQ       	0 4 -2	; - "none"
	3	[17]	JMP      	1	; to 5
	4	[17]	RETURN   	0 1
	5	[18]	GETTABLE 	4 0 -1	; "style"
	6	[18]	EQ       	0 4 -3	; - "dashed"
	7	[18]	JMP      	16	; to 24
	8	[19]	LOADK    	4 -4	; 0
	9	[19]	GETTABLE 	5 0 -5	; "dimen"
	10	[19]	GETTABLE 	5 5 -6	; "w"
	11	[19]	SUB      	5 5 -7	; - 20
	12	[19]	LOADK    	6 -7	; 20
	13	[19]	FORPREP  	4 8	; to 22
	14	[20]	SELF     	8 1 -8	; "paintRect"
	15	[20]	ADD      	10 2 7
	16	[20]	MOVE     	11 3
	17	[21]	LOADK    	12 -9	; 16
	18	[21]	GETTABLE 	13 0 -5	; "dimen"
	19	[21]	GETTABLE 	13 13 -10	; "h"
	20	[21]	GETTABLE 	14 0 -11	; "background"
	21	[20]	CALL     	8 7 1
	22	[19]	FORLOOP  	4 -9	; to 14
	23	[22]	JMP      	40	; to 64
	24	[24]	GETTABLE 	4 0 -12	; "empty_segments"
	25	[24]	TEST     	4 0 0
	26	[24]	JMP      	28	; to 55
	27	[25]	SELF     	4 1 -8	; "paintRect"
	28	[25]	MOVE     	6 2
	29	[25]	MOVE     	7 3
	30	[26]	GETTABLE 	8 0 -12	; "empty_segments"
	31	[26]	GETTABLE 	8 8 -13	; 1
	32	[26]	GETTABLE 	8 8 -14	; "s"
	33	[27]	GETTABLE 	9 0 -5	; "dimen"
	34	[27]	GETTABLE 	9 9 -10	; "h"
	35	[28]	GETTABLE 	10 0 -11	; "background"
	36	[25]	CALL     	4 7 1
	37	[29]	SELF     	4 1 -8	; "paintRect"
	38	[29]	GETTABLE 	6 0 -12	; "empty_segments"
	39	[29]	GETTABLE 	6 6 -13	; 1
	40	[29]	GETTABLE 	6 6 -15	; "e"
	41	[29]	ADD      	6 2 6
	42	[29]	MOVE     	7 3
	43	[30]	GETTABLE 	8 0 -5	; "dimen"
	44	[30]	GETTABLE 	8 8 -6	; "w"
	45	[30]	SUB      	8 8 2
	46	[30]	GETTABLE 	9 0 -12	; "empty_segments"
	47	[30]	GETTABLE 	9 9 -13	; 1
	48	[30]	GETTABLE 	9 9 -15	; "e"
	49	[30]	SUB      	8 8 9
	50	[31]	GETTABLE 	9 0 -5	; "dimen"
	51	[31]	GETTABLE 	9 9 -10	; "h"
	52	[32]	GETTABLE 	10 0 -11	; "background"
	53	[29]	CALL     	4 7 1
	54	[32]	JMP      	9	; to 64
	55	[34]	SELF     	4 1 -8	; "paintRect"
	56	[34]	MOVE     	6 2
	57	[34]	MOVE     	7 3
	58	[34]	GETTABLE 	8 0 -5	; "dimen"
	59	[34]	GETTABLE 	8 8 -6	; "w"
	60	[34]	GETTABLE 	9 0 -5	; "dimen"
	61	[34]	GETTABLE 	9 9 -10	; "h"
	62	[34]	GETTABLE 	10 0 -11	; "background"
	63	[34]	CALL     	4 7 1
	64	[37]	RETURN   	0 1
