
main <./plugins/coverbrowser.koplugin/listmenu.lua:0,0> (242 instructions, 968 bytes at 0x7fdc3ec068f0)
0+ params, 49 slots, 0 upvalues, 43 locals, 82 constants, 11 functions
	1	[1]	GETGLOBAL	0 -1	; require
	2	[1]	LOADK    	1 -2	; "ui/bidi"
	3	[1]	CALL     	0 2 2
	4	[2]	GETGLOBAL	1 -1	; require
	5	[2]	LOADK    	2 -3	; "ffi/blitbuffer"
	6	[2]	CALL     	1 2 2
	7	[3]	GETGLOBAL	2 -1	; require
	8	[3]	LOADK    	3 -4	; "ui/widget/container/centercontainer"
	9	[3]	CALL     	2 2 2
	10	[4]	GETGLOBAL	3 -1	; require
	11	[4]	LOADK    	4 -5	; "device"
	12	[4]	CALL     	3 2 2
	13	[5]	GETGLOBAL	4 -1	; require
	14	[5]	LOADK    	5 -6	; "docsettings"
	15	[5]	CALL     	4 2 2
	16	[6]	GETGLOBAL	5 -1	; require
	17	[6]	LOADK    	6 -7	; "ui/font"
	18	[6]	CALL     	5 2 2
	19	[7]	GETGLOBAL	6 -1	; require
	20	[7]	LOADK    	7 -8	; "ui/widget/container/framecontainer"
	21	[7]	CALL     	6 2 2
	22	[8]	GETGLOBAL	7 -1	; require
	23	[8]	LOADK    	8 -9	; "ui/geometry"
	24	[8]	CALL     	7 2 2
	25	[9]	GETGLOBAL	8 -1	; require
	26	[9]	LOADK    	9 -10	; "ui/gesturerange"
	27	[9]	CALL     	8 2 2
	28	[10]	GETGLOBAL	9 -1	; require
	29	[10]	LOADK    	10 -11	; "ui/widget/horizontalgroup"
	30	[10]	CALL     	9 2 2
	31	[11]	GETGLOBAL	10 -1	; require
	32	[11]	LOADK    	11 -12	; "ui/widget/horizontalspan"
	33	[11]	CALL     	10 2 2
	34	[12]	GETGLOBAL	11 -1	; require
	35	[12]	LOADK    	12 -13	; "ui/widget/imagewidget"
	36	[12]	CALL     	11 2 2
	37	[13]	GETGLOBAL	12 -1	; require
	38	[13]	LOADK    	13 -14	; "ui/widget/infomessage"
	39	[13]	CALL     	12 2 2
	40	[14]	GETGLOBAL	13 -1	; require
	41	[14]	LOADK    	14 -15	; "ui/widget/container/inputcontainer"
	42	[14]	CALL     	13 2 2
	43	[15]	GETGLOBAL	14 -1	; require
	44	[15]	LOADK    	15 -16	; "ui/widget/container/leftcontainer"
	45	[15]	CALL     	14 2 2
	46	[16]	GETGLOBAL	15 -1	; require
	47	[16]	LOADK    	16 -17	; "ui/widget/linewidget"
	48	[16]	CALL     	15 2 2
	49	[17]	GETGLOBAL	16 -1	; require
	50	[17]	LOADK    	17 -18	; "optmath"
	51	[17]	CALL     	16 2 2
	52	[18]	GETGLOBAL	17 -1	; require
	53	[18]	LOADK    	18 -19	; "ui/widget/overlapgroup"
	54	[18]	CALL     	17 2 2
	55	[19]	GETGLOBAL	18 -1	; require
	56	[19]	LOADK    	19 -20	; "ui/widget/container/rightcontainer"
	57	[19]	CALL     	18 2 2
	58	[20]	GETGLOBAL	19 -1	; require
	59	[20]	LOADK    	20 -21	; "ui/size"
	60	[20]	CALL     	19 2 2
	61	[21]	GETGLOBAL	20 -1	; require
	62	[21]	LOADK    	21 -22	; "ui/widget/textboxwidget"
	63	[21]	CALL     	20 2 2
	64	[22]	GETGLOBAL	21 -1	; require
	65	[22]	LOADK    	22 -23	; "ui/widget/textwidget"
	66	[22]	CALL     	21 2 2
	67	[23]	GETGLOBAL	22 -1	; require
	68	[23]	LOADK    	23 -24	; "ui/uimanager"
	69	[23]	CALL     	22 2 2
	70	[24]	GETGLOBAL	23 -1	; require
	71	[24]	LOADK    	24 -25	; "ui/widget/container/underlinecontainer"
	72	[24]	CALL     	23 2 2
	73	[25]	GETGLOBAL	24 -1	; require
	74	[25]	LOADK    	25 -26	; "ui/widget/verticalgroup"
	75	[25]	CALL     	24 2 2
	76	[26]	GETGLOBAL	25 -1	; require
	77	[26]	LOADK    	26 -27	; "ui/widget/verticalspan"
	78	[26]	CALL     	25 2 2
	79	[27]	GETGLOBAL	26 -1	; require
	80	[27]	LOADK    	27 -28	; "ui/widget/container/widgetcontainer"
	81	[27]	CALL     	26 2 2
	82	[28]	GETGLOBAL	27 -1	; require
	83	[28]	LOADK    	28 -29	; "libs/libkoreader-lfs"
	84	[28]	CALL     	27 2 2
	85	[29]	GETGLOBAL	28 -1	; require
	86	[29]	LOADK    	29 -30	; "logger"
	87	[29]	CALL     	28 2 2
	88	[30]	GETGLOBAL	29 -1	; require
	89	[30]	LOADK    	30 -31	; "util"
	90	[30]	CALL     	29 2 2
	91	[31]	GETGLOBAL	30 -1	; require
	92	[31]	LOADK    	31 -32	; "gettext"
	93	[31]	CALL     	30 2 2
	94	[32]	GETTABLE 	31 30 -33	; "ngettext"
	95	[33]	GETTABLE 	32 3 -34	; "screen"
	96	[34]	GETGLOBAL	33 -1	; require
	97	[34]	LOADK    	34 -35	; "ffi/util"
	98	[34]	CALL     	33 2 2
	99	[34]	GETTABLE 	33 33 -36	; "template"
	100	[35]	GETGLOBAL	34 -1	; require
	101	[35]	LOADK    	35 -37	; "ui/widget/menu"
	102	[35]	CALL     	34 2 2
	103	[35]	GETTABLE 	34 34 -38	; "getMenuText"
	104	[37]	GETGLOBAL	35 -1	; require
	105	[37]	LOADK    	36 -39	; "bookinfomanager"
	106	[37]	CALL     	35 2 2
	107	[46]	LOADK    	36 -40	; -1
	108	[47]	LOADNIL  	37 37
	109	[49]	SELF     	38 32 -41	; "scaleBySize"
	110	[49]	LOADK    	40 -42	; 1000000
	111	[49]	CALL     	38 3 2
	112	[49]	DIV      	38 38 -42	; - 1000000
	113	[50]	LOADNIL  	39 39
	114	[54]	SELF     	40 26 -43	; "new"
	115	[54]	NEWTABLE 	42 0 5
	116	[55]	SELF     	43 7 -43	; "new"
	117	[55]	NEWTABLE 	45 0 2
	118	[55]	SELF     	46 32 -41	; "scaleBySize"
	119	[55]	LOADK    	48 -46	; 22
	120	[55]	CALL     	46 3 2
	121	[55]	SETTABLE 	45 -45 46	; "w" -
	122	[55]	SELF     	46 32 -41	; "scaleBySize"
	123	[55]	LOADK    	48 -46	; 22
	124	[55]	CALL     	46 3 2
	125	[55]	SETTABLE 	45 -47 46	; "h" -
	126	[55]	CALL     	43 3 2
	127	[55]	SETTABLE 	42 -44 43	; "dimen" -
	128	[56]	SETTABLE 	42 -48 -49	; "key" nil
	129	[57]	GETTABLE 	43 19 -51	; "border"
	130	[57]	GETTABLE 	43 43 -52	; "default"
	131	[57]	SETTABLE 	42 -50 43	; "bordersize" -
	132	[58]	SETTABLE 	42 -53 -54	; "radius" 0
	133	[59]	SETTABLE 	42 -55 -56	; "style" "square"
	134	[54]	CALL     	40 3 2
	135	[93]	CLOSURE  	41 0	; 0x7fdc3ec07670
	136	[93]	MOVE     	0 1
	137	[93]	MOVE     	0 5
	138	[93]	MOVE     	0 6
	139	[93]	MOVE     	0 2
	140	[93]	MOVE     	0 21
	141	[62]	SETTABLE 	40 -57 41	; "init" -
	142	[97]	SELF     	41 13 -43	; "new"
	143	[97]	NEWTABLE 	43 0 16
	144	[98]	NEWTABLE 	44 0 0
	145	[98]	SETTABLE 	43 -58 44	; "entry" -
	146	[99]	SETTABLE 	43 -59 -49	; "text" nil
	147	[100]	SETTABLE 	43 -60 -49	; "show_parent" nil
	148	[101]	SETTABLE 	43 -61 -49	; "detail" nil
	149	[102]	SETTABLE 	43 -44 -49	; "dimen" nil
	150	[103]	SETTABLE 	43 -62 -49	; "shortcut" nil
	151	[104]	SETTABLE 	43 -63 -56	; "shortcut_style" "square"
	152	[105]	SETTABLE 	43 -64 -49	; "_underline_container" nil
	153	[106]	SETTABLE 	43 -65 -66	; "do_cover_image" false
	154	[107]	SETTABLE 	43 -67 -66	; "do_filename_only" false
	155	[108]	SETTABLE 	43 -68 -66	; "do_hint_opened" false
	156	[109]	SETTABLE 	43 -69 -66	; "been_opened" false
	157	[110]	SETTABLE 	43 -70 -66	; "init_done" false
	158	[111]	SETTABLE 	43 -71 -66	; "bookinfo_found" false
	159	[112]	SETTABLE 	43 -72 -49	; "cover_specs" nil
	160	[113]	SETTABLE 	43 -73 -66	; "has_description" false
	161	[97]	CALL     	41 3 2
	162	[180]	CLOSURE  	42 1	; 0x7fdc3ec07dc0
	163	[180]	MOVE     	0 7
	164	[180]	MOVE     	0 40
	165	[180]	MOVE     	0 3
	166	[180]	MOVE     	0 8
	167	[180]	MOVE     	0 23
	168	[116]	SETTABLE 	41 -57 42	; "init" -
	169	[702]	CLOSURE  	42 2	; 0x7fdc3ec08790
	170	[702]	MOVE     	0 7
	171	[702]	MOVE     	0 38
	172	[702]	MOVE     	0 27
	173	[702]	MOVE     	0 21
	174	[702]	MOVE     	0 5
	175	[702]	MOVE     	0 39
	176	[702]	MOVE     	0 32
	177	[702]	MOVE     	0 20
	178	[702]	MOVE     	0 0
	179	[702]	MOVE     	0 17
	180	[702]	MOVE     	0 14
	181	[702]	MOVE     	0 9
	182	[702]	MOVE     	0 10
	183	[702]	MOVE     	0 18
	184	[702]	MOVE     	0 35
	185	[702]	MOVE     	0 11
	186	[702]	MOVE     	0 2
	187	[702]	MOVE     	0 6
	188	[702]	MOVE     	0 29
	189	[702]	MOVE     	0 4
	190	[702]	MOVE     	0 33
	191	[702]	MOVE     	0 30
	192	[702]	MOVE     	0 16
	193	[702]	MOVE     	0 31
	194	[702]	MOVE     	0 1
	195	[702]	MOVE     	0 24
	196	[702]	MOVE     	0 25
	197	[702]	MOVE     	0 36
	198	[702]	MOVE     	0 37
	199	[702]	MOVE     	0 28
	200	[182]	SETTABLE 	41 -74 42	; "update" -
	201	[769]	CLOSURE  	42 3	; 0x7fdc3ec0a9b0
	202	[769]	MOVE     	0 28
	203	[769]	MOVE     	0 13
	204	[769]	MOVE     	0 0
	205	[769]	MOVE     	0 37
	206	[769]	MOVE     	0 35
	207	[769]	MOVE     	0 32
	208	[704]	SETTABLE 	41 -75 42	; "paintTo" -
	209	[775]	CLOSURE  	42 4	; 0x7fdc3ec0afc0
	210	[775]	MOVE     	0 1
	211	[772]	SETTABLE 	41 -76 42	; "onFocus" -
	212	[780]	CLOSURE  	42 5	; 0x7fdc3ec0b280
	213	[780]	MOVE     	0 1
	214	[777]	SETTABLE 	41 -77 42	; "onUnfocus" -
	215	[785]	CLOSURE  	42 6	; 0x7fdc3ec0b340
	216	[785]	MOVE     	0 22
	217	[785]	MOVE     	0 12
	218	[782]	SETTABLE 	41 -78 42	; "onShowItemDetail" -
	219	[794]	CLOSURE  	42 7	; 0x7fdc3ec0b400
	220	[791]	SETTABLE 	41 -79 42	; "onTapSelect" -
	221	[799]	CLOSURE  	42 8	; 0x7fdc3ec0bf50
	222	[796]	SETTABLE 	41 -80 42	; "onHoldSelect" -
	223	[804]	NEWTABLE 	42 0 0
	224	[901]	CLOSURE  	43 9	; 0x7fdc3ec0c460
	225	[901]	MOVE     	0 32
	226	[901]	MOVE     	0 19
	227	[901]	MOVE     	0 35
	228	[901]	MOVE     	0 38
	229	[901]	MOVE     	0 16
	230	[901]	MOVE     	0 7
	231	[901]	MOVE     	0 39
	232	[806]	SETTABLE 	42 -81 43	; "_recalculateDimen" -
	233	[958]	CLOSURE  	43 10	; 0x7fdc3ec0ca40
	234	[958]	MOVE     	0 15
	235	[958]	MOVE     	0 7
	236	[958]	MOVE     	0 19
	237	[958]	MOVE     	0 1
	238	[958]	MOVE     	0 41
	239	[958]	MOVE     	0 34
	240	[903]	SETTABLE 	42 -82 43	; "_updateItemsBuildUI" -
	241	[960]	RETURN   	42 2
	242	[960]	RETURN   	0 1

function <./plugins/coverbrowser.koplugin/listmenu.lua:62,93> (69 instructions, 276 bytes at 0x7fdc3ec07670)
1 param, 14 slots, 5 upvalues, 4 locals, 26 constants, 0 functions
	1	[63]	GETTABLE 	1 0 -1	; "key"
	2	[63]	TEST     	1 0 1
	3	[63]	JMP      	1	; to 5
	4	[64]	RETURN   	0 1
	5	[66]	LOADK    	1 -2	; 0
	6	[67]	GETUPVAL 	2 0	; Blitbuffer
	7	[67]	GETTABLE 	2 2 -3	; "COLOR_WHITE"
	8	[68]	GETTABLE 	3 0 -4	; "style"
	9	[68]	EQ       	0 3 -5	; - "rounded_corner"
	10	[68]	JMP      	7	; to 18
	11	[69]	GETGLOBAL	3 -6	; math
	12	[69]	GETTABLE 	3 3 -7	; "floor"
	13	[69]	GETTABLE 	4 0 -8	; "width"
	14	[69]	DIV      	4 4 -9	; - 2
	15	[69]	CALL     	3 2 2
	16	[69]	MOVE     	1 3
	17	[69]	JMP      	5	; to 23
	18	[70]	GETTABLE 	3 0 -4	; "style"
	19	[70]	EQ       	0 3 -10	; - "grey_square"
	20	[70]	JMP      	2	; to 23
	21	[71]	GETUPVAL 	3 0	; Blitbuffer
	22	[71]	GETTABLE 	2 3 -11	; "COLOR_LIGHT_GRAY"
	23	[73]	LOADNIL  	3 3
	24	[74]	GETTABLE 	4 0 -1	; "key"
	25	[74]	SELF     	4 4 -12	; "len"
	26	[74]	CALL     	4 2 2
	27	[74]	LT       	0 -13 4	; 1 -
	28	[74]	JMP      	7	; to 36
	29	[75]	GETUPVAL 	4 1	; Font
	30	[75]	SELF     	4 4 -14	; "getFace"
	31	[75]	LOADK    	6 -15	; "ffont"
	32	[75]	LOADK    	7 -16	; 14
	33	[75]	CALL     	4 4 2
	34	[75]	MOVE     	3 4
	35	[75]	JMP      	6	; to 42
	36	[77]	GETUPVAL 	4 1	; Font
	37	[77]	SELF     	4 4 -14	; "getFace"
	38	[77]	LOADK    	6 -17	; "scfont"
	39	[77]	LOADK    	7 -18	; 22
	40	[77]	CALL     	4 4 2
	41	[77]	MOVE     	3 4
	42	[79]	GETUPVAL 	4 2	; FrameContainer
	43	[79]	SELF     	4 4 -19	; "new"
	44	[79]	NEWTABLE 	6 0 5
	45	[80]	SETTABLE 	6 -20 -2	; "padding" 0
	46	[81]	GETTABLE 	7 0 -21	; "bordersize"
	47	[81]	SETTABLE 	6 -21 7	; "bordersize" -
	48	[82]	SETTABLE 	6 -22 1	; "radius" -
	49	[83]	SETTABLE 	6 -23 2	; "background" -
	50	[84]	GETTABLE 	7 0 -24	; "dimen"
	51	[84]	SETTABLE 	6 -24 7	; "dimen" -
	52	[85]	GETUPVAL 	7 3	; CenterContainer
	53	[85]	SELF     	7 7 -19	; "new"
	54	[85]	NEWTABLE 	9 0 1
	55	[86]	GETTABLE 	10 0 -24	; "dimen"
	56	[86]	SETTABLE 	9 -24 10	; "dimen" -
	57	[87]	GETUPVAL 	10 4	; TextWidget
	58	[87]	SELF     	10 10 -19	; "new"
	59	[87]	NEWTABLE 	12 0 2
	60	[88]	GETTABLE 	13 0 -1	; "key"
	61	[88]	SETTABLE 	12 -25 13	; "text" -
	62	[89]	SETTABLE 	12 -26 3	; "face" -
	63	[87]	CALL     	10 3 0
	64	[91]	SETLIST  	9 0 1	; 1
	65	[85]	CALL     	7 3 0
	66	[92]	SETLIST  	6 0 1	; 1
	67	[79]	CALL     	4 3 2
	68	[92]	SETTABLE 	0 -13 4	; 1 -
	69	[93]	RETURN   	0 1

function <./plugins/coverbrowser.koplugin/listmenu.lua:116,180> (89 instructions, 356 bytes at 0x7fdc3ec07dc0)
1 param, 8 slots, 5 upvalues, 2 locals, 43 constants, 0 functions
	1	[119]	GETTABLE 	1 0 -2	; "entry"
	2	[119]	GETTABLE 	1 1 -3	; "file"
	3	[119]	TEST     	1 0 1
	4	[119]	JMP      	2	; to 7
	5	[119]	GETTABLE 	1 0 -2	; "entry"
	6	[119]	GETTABLE 	1 1 -4	; "path"
	7	[119]	SETTABLE 	0 -1 1	; "filepath" -
	8	[123]	GETTABLE 	1 0 -5	; "shortcut"
	9	[123]	TEST     	1 0 0
	10	[123]	JMP      	23	; to 34
	11	[124]	GETUPVAL 	1 0	; Geom
	12	[124]	SELF     	1 1 -6	; "new"
	13	[124]	CALL     	1 2 2
	14	[125]	GETGLOBAL	2 -8	; math
	15	[125]	GETTABLE 	2 2 -9	; "floor"
	16	[125]	GETTABLE 	3 0 -10	; "dimen"
	17	[125]	GETTABLE 	3 3 -11	; "h"
	18	[125]	MUL      	3 3 -12	; - 2
	19	[125]	DIV      	3 3 -13	; - 5
	20	[125]	CALL     	2 2 2
	21	[125]	SETTABLE 	1 -7 2	; "w" -
	22	[126]	GETTABLE 	2 1 -7	; "w"
	23	[126]	SETTABLE 	1 -11 2	; "h" -
	24	[129]	GETUPVAL 	2 1	; ItemShortCutIcon
	25	[129]	SELF     	2 2 -6	; "new"
	26	[129]	NEWTABLE 	4 0 3
	27	[130]	SETTABLE 	4 -10 1	; "dimen" -
	28	[131]	GETTABLE 	5 0 -5	; "shortcut"
	29	[131]	SETTABLE 	4 -15 5	; "key" -
	30	[132]	GETTABLE 	5 0 -17	; "shortcut_style"
	31	[132]	SETTABLE 	4 -16 5	; "style" -
	32	[129]	CALL     	2 3 2
	33	[133]	SETTABLE 	0 -14 2	; "shortcut_icon" -
	34	[135]	GETTABLE 	1 0 -19	; "text"
	35	[135]	SETTABLE 	0 -18 1	; "detail" -
	36	[138]	GETUPVAL 	1 2	; Device
	37	[138]	SELF     	1 1 -20	; "isTouchDevice"
	38	[138]	CALL     	1 2 2
	39	[138]	TEST     	1 0 0
	40	[138]	JMP      	24	; to 65
	41	[139]	NEWTABLE 	1 0 2
	42	[140]	NEWTABLE 	2 1 1
	43	[141]	GETUPVAL 	3 3	; GestureRange
	44	[141]	SELF     	3 3 -6	; "new"
	45	[141]	NEWTABLE 	5 0 2
	46	[142]	SETTABLE 	5 -23 -24	; "ges" "tap"
	47	[143]	GETTABLE 	6 0 -10	; "dimen"
	48	[143]	SETTABLE 	5 -25 6	; "range" -
	49	[141]	CALL     	3 3 2
	50	[145]	SETTABLE 	2 -26 -27	; "doc" "Select Menu Item"
	51	[146]	SETLIST  	2 1 1	; 1
	52	[146]	SETTABLE 	1 -22 2	; "TapSelect" -
	53	[147]	NEWTABLE 	2 1 1
	54	[148]	GETUPVAL 	3 3	; GestureRange
	55	[148]	SELF     	3 3 -6	; "new"
	56	[148]	NEWTABLE 	5 0 2
	57	[149]	SETTABLE 	5 -23 -29	; "ges" "hold"
	58	[150]	GETTABLE 	6 0 -10	; "dimen"
	59	[150]	SETTABLE 	5 -25 6	; "range" -
	60	[148]	CALL     	3 3 2
	61	[152]	SETTABLE 	2 -26 -30	; "doc" "Hold Menu Item"
	62	[153]	SETLIST  	2 1 1	; 1
	63	[153]	SETTABLE 	1 -28 2	; "HoldSelect" -
	64	[154]	SETTABLE 	0 -21 1	; "ges_events" -
	65	[163]	SETTABLE 	0 -31 -32	; "underline_h" 1
	66	[164]	GETUPVAL 	1 4	; UnderlineContainer
	67	[164]	SELF     	1 1 -6	; "new"
	68	[164]	NEWTABLE 	3 0 4
	69	[165]	SETTABLE 	3 -34 -35	; "vertical_align" "top"
	70	[166]	SETTABLE 	3 -36 -37	; "padding" 0
	71	[167]	GETUPVAL 	4 0	; Geom
	72	[167]	SELF     	4 4 -6	; "new"
	73	[167]	NEWTABLE 	6 0 2
	74	[168]	GETTABLE 	7 0 -38	; "width"
	75	[168]	SETTABLE 	6 -7 7	; "w" -
	76	[169]	GETTABLE 	7 0 -39	; "height"
	77	[169]	SETTABLE 	6 -11 7	; "h" -
	78	[167]	CALL     	4 3 2
	79	[170]	SETTABLE 	3 -10 4	; "dimen" -
	80	[171]	GETTABLE 	4 0 -31	; "underline_h"
	81	[171]	SETTABLE 	3 -40 4	; "linesize" -
	82	[164]	CALL     	1 3 2
	83	[173]	SETTABLE 	0 -33 1	; "_underline_container" -
	84	[174]	GETTABLE 	1 0 -33	; "_underline_container"
	85	[174]	SETTABLE 	0 -32 1	; 1 -
	86	[178]	SELF     	1 0 -41	; "update"
	87	[178]	CALL     	1 2 1
	88	[179]	SETTABLE 	0 -42 -43	; "init_done" true
	89	[180]	RETURN   	0 1

function <./plugins/coverbrowser.koplugin/listmenu.lua:182,702> (1128 instructions, 4512 bytes at 0x7fdc3ec08790)
1 param, 56 slots, 30 upvalues, 62 locals, 153 constants, 1 function
	1	[188]	GETUPVAL 	2 0	; Geom
	2	[188]	SELF     	2 2 -1	; "new"
	3	[188]	NEWTABLE 	4 0 2
	4	[189]	GETTABLE 	5 0 -3	; "width"
	5	[189]	SETTABLE 	4 -2 5	; "w" -
	6	[190]	GETTABLE 	5 0 -5	; "height"
	7	[190]	GETTABLE 	6 0 -6	; "underline_h"
	8	[190]	MUL      	6 -7 6	; 2 -
	9	[190]	SUB      	5 5 6
	10	[190]	SETTABLE 	4 -4 5	; "h" -
	11	[188]	CALL     	2 3 2
	12	[198]	CLOSURE  	3 0	; 0x7fdc3ec08aa0
	13	[198]	MOVE     	0 2
	14	[198]	GETUPVAL 	0 1	; scale_by_size
	15	[201]	GETGLOBAL	4 -8	; math
	16	[201]	GETTABLE 	4 4 -9	; "ceil"
	17	[201]	MOVE     	5 3
	18	[201]	LOADK    	6 -10	; 100
	19	[201]	CALL     	5 2 2
	20	[201]	DIV      	5 5 -10	; - 100
	21	[201]	CALL     	4 2 2
	22	[206]	LOADK    	5 -11	; 1
	23	[207]	GETTABLE 	6 2 -4	; "h"
	24	[207]	MUL      	7 -7 5	; 2 -
	25	[207]	SUB      	6 6 7
	26	[208]	GETTABLE 	7 2 -4	; "h"
	27	[208]	MUL      	8 -7 5	; 2 -
	28	[208]	SUB      	7 7 8
	29	[209]	NEWTABLE 	8 0 3
	30	[210]	GETTABLE 	9 0 -13	; "menu"
	31	[210]	GETTABLE 	9 9 -14	; "cover_sizetag"
	32	[210]	SETTABLE 	8 -12 9	; "sizetag" -
	33	[211]	SETTABLE 	8 -15 6	; "max_cover_w" -
	34	[212]	SETTABLE 	8 -16 7	; "max_cover_h" -
	35	[216]	GETTABLE 	9 0 -17	; "do_cover_image"
	36	[216]	TEST     	9 0 0
	37	[216]	JMP      	3	; to 41
	38	[217]	GETTABLE 	9 0 -13	; "menu"
	39	[217]	SETTABLE 	9 -18 8	; "cover_specs" -
	40	[217]	JMP      	2	; to 43
	41	[219]	GETTABLE 	9 0 -13	; "menu"
	42	[219]	SETTABLE 	9 -18 -19	; "cover_specs" false
	43	[222]	GETUPVAL 	9 2	; lfs
	44	[222]	GETTABLE 	9 9 -20	; "attributes"
	45	[222]	GETTABLE 	10 0 -21	; "filepath"
	46	[222]	LOADK    	11 -22	; "mode"
	47	[222]	CALL     	9 3 2
	48	[223]	EQ       	0 9 -23	; - "directory"
	49	[223]	JMP      	91	; to 141
	50	[224]	SETTABLE 	0 -24 -25	; "is_directory" true
	51	[226]	GETUPVAL 	10 3	; TextWidget
	52	[226]	SELF     	10 10 -1	; "new"
	53	[226]	NEWTABLE 	12 0 2
	54	[227]	GETTABLE 	13 0 -27	; "mandatory"
	55	[227]	SETTABLE 	12 -26 13	; "text" -
	56	[228]	GETUPVAL 	13 4	; Font
	57	[228]	SELF     	13 13 -29	; "getFace"
	58	[228]	LOADK    	15 -30	; "infont"
	59	[228]	GETGLOBAL	16 -8	; math
	60	[228]	GETTABLE 	16 16 -31	; "min"
	61	[228]	GETUPVAL 	17 5	; max_fontsize_fileinfo
	62	[228]	MOVE     	18 3
	63	[228]	LOADK    	19 -32	; 15
	64	[228]	CALL     	18 2 0
	65	[228]	CALL     	16 0 0
	66	[228]	CALL     	13 0 2
	67	[228]	SETTABLE 	12 -28 13	; "face" -
	68	[226]	CALL     	10 3 2
	69	[230]	GETUPVAL 	11 6	; Screen
	70	[230]	SELF     	11 11 -33	; "scaleBySize"
	71	[230]	LOADK    	13 -34	; 10
	72	[230]	CALL     	11 3 2
	73	[231]	GETTABLE 	12 2 -2	; "w"
	74	[231]	SELF     	13 10 -35	; "getWidth"
	75	[231]	CALL     	13 2 2
	76	[231]	SUB      	12 12 13
	77	[231]	MUL      	13 -36 11	; 3 -
	78	[231]	SUB      	12 12 13
	79	[232]	GETUPVAL 	13 7	; TextBoxWidget
	80	[232]	SELF     	13 13 -1	; "new"
	81	[232]	NEWTABLE 	15 0 5
	82	[233]	GETUPVAL 	16 8	; BD
	83	[233]	GETTABLE 	16 16 -23	; "directory"
	84	[233]	GETTABLE 	17 0 -26	; "text"
	85	[233]	CALL     	16 2 2
	86	[233]	SETTABLE 	15 -26 16	; "text" -
	87	[234]	GETUPVAL 	16 4	; Font
	88	[234]	SELF     	16 16 -29	; "getFace"
	89	[234]	LOADK    	18 -37	; "cfont"
	90	[234]	MOVE     	19 3
	91	[234]	LOADK    	20 -38	; 20
	92	[234]	CALL     	19 2 0
	93	[234]	CALL     	16 0 2
	94	[234]	SETTABLE 	15 -28 16	; "face" -
	95	[235]	SETTABLE 	15 -3 12	; "width" -
	96	[236]	SETTABLE 	15 -39 -40	; "alignment" "left"
	97	[237]	SETTABLE 	15 -41 -25	; "bold" true
	98	[232]	CALL     	13 3 2
	99	[239]	GETUPVAL 	14 9	; OverlapGroup
	100	[239]	SELF     	14 14 -1	; "new"
	101	[239]	NEWTABLE 	16 1 1
	102	[240]	SETTABLE 	16 -42 2	; "dimen" -
	103	[241]	GETUPVAL 	17 10	; LeftContainer
	104	[241]	SELF     	17 17 -1	; "new"
	105	[241]	NEWTABLE 	19 0 1
	106	[242]	SETTABLE 	19 -42 2	; "dimen" -
	107	[243]	GETUPVAL 	20 11	; HorizontalGroup
	108	[243]	SELF     	20 20 -1	; "new"
	109	[243]	NEWTABLE 	22 2 0
	110	[244]	GETUPVAL 	23 12	; HorizontalSpan
	111	[244]	SELF     	23 23 -1	; "new"
	112	[244]	NEWTABLE 	25 0 1
	113	[244]	SETTABLE 	25 -3 11	; "width" -
	114	[244]	CALL     	23 3 2
	115	[246]	MOVE     	24 13
	116	[246]	SETLIST  	22 2 1	; 1
	117	[243]	CALL     	20 3 0
	118	[247]	SETLIST  	19 0 1	; 1
	119	[241]	CALL     	17 3 2
	120	[248]	GETUPVAL 	18 13	; RightContainer
	121	[248]	SELF     	18 18 -1	; "new"
	122	[248]	NEWTABLE 	20 0 1
	123	[249]	SETTABLE 	20 -42 2	; "dimen" -
	124	[250]	GETUPVAL 	21 11	; HorizontalGroup
	125	[250]	SELF     	21 21 -1	; "new"
	126	[250]	NEWTABLE 	23 1 0
	127	[251]	MOVE     	24 10
	128	[252]	GETUPVAL 	25 12	; HorizontalSpan
	129	[252]	SELF     	25 25 -1	; "new"
	130	[252]	NEWTABLE 	27 0 1
	131	[252]	SETTABLE 	27 -3 11	; "width" -
	132	[252]	CALL     	25 3 0
	133	[253]	SETLIST  	23 0 1	; 1
	134	[250]	CALL     	21 3 0
	135	[254]	SETLIST  	20 0 1	; 1
	136	[248]	CALL     	18 3 0
	137	[255]	SETLIST  	16 0 1	; 1
	138	[239]	CALL     	14 3 2
	139	[255]	MOVE     	1 14
	140	[255]	JMP      	965	; to 1106
	141	[257]	EQ       	1 9 -43	; - "file"
	142	[257]	JMP      	1	; to 144
	143	[258]	SETTABLE 	0 -44 -25	; "file_deleted" true
	144	[262]	GETUPVAL 	10 14	; BookInfoManager
	145	[262]	SELF     	10 10 -45	; "getBookInfo"
	146	[262]	GETTABLE 	12 0 -21	; "filepath"
	147	[262]	GETTABLE 	13 0 -17	; "do_cover_image"
	148	[262]	CALL     	10 4 2
	149	[263]	TEST     	10 0 0
	150	[263]	JMP      	28	; to 179
	151	[263]	GETTABLE 	11 0 -17	; "do_cover_image"
	152	[263]	TEST     	11 0 0
	153	[263]	JMP      	25	; to 179
	154	[263]	GETTABLE 	11 10 -46	; "ignore_cover"
	155	[263]	TEST     	11 0 1
	156	[263]	JMP      	22	; to 179
	157	[264]	GETTABLE 	11 10 -47	; "cover_fetched"
	158	[264]	TEST     	11 0 0
	159	[264]	JMP      	18	; to 178
	160	[266]	GETTABLE 	11 10 -48	; "has_cover"
	161	[266]	TEST     	11 0 0
	162	[266]	JMP      	16	; to 179
	163	[266]	GETTABLE 	11 10 -14	; "cover_sizetag"
	164	[266]	EQ       	1 11 -49	; - "M"
	165	[266]	JMP      	13	; to 179
	166	[266]	GETTABLE 	11 10 -14	; "cover_sizetag"
	167	[266]	GETTABLE 	12 8 -12	; "sizetag"
	168	[266]	EQ       	1 11 12
	169	[266]	JMP      	9	; to 179
	170	[267]	GETTABLE 	11 10 -50	; "cover_bb"
	171	[267]	TEST     	11 0 0
	172	[267]	JMP      	3	; to 176
	173	[268]	GETTABLE 	11 10 -50	; "cover_bb"
	174	[268]	SELF     	11 11 -51	; "free"
	175	[268]	CALL     	11 2 1
	176	[270]	LOADNIL  	10 10
	177	[271]	JMP      	1	; to 179
	178	[275]	LOADNIL  	10 10
	179	[283]	TEST     	10 0 0
	180	[283]	JMP      	824	; to 1005
	181	[284]	SETTABLE 	0 -52 -25	; "bookinfo_found" true
	182	[285]	LOADBOOL 	11 0 0
	183	[288]	LOADNIL  	12 12
	184	[289]	LOADK    	13 -53	; 0
	185	[290]	LOADNIL  	14 14
	186	[291]	GETTABLE 	15 0 -17	; "do_cover_image"
	187	[291]	TEST     	15 0 0
	188	[291]	JMP      	81	; to 270
	189	[292]	GETTABLE 	14 2 -4	; "h"
	190	[293]	MOVE     	13 14
	191	[294]	GETTABLE 	15 10 -48	; "has_cover"
	192	[294]	TEST     	15 0 0
	193	[294]	JMP      	58	; to 252
	194	[294]	GETTABLE 	15 10 -46	; "ignore_cover"
	195	[294]	TEST     	15 0 1
	196	[294]	JMP      	55	; to 252
	197	[295]	LOADBOOL 	11 1 0
	198	[297]	GETGLOBAL	15 -8	; math
	199	[297]	GETTABLE 	15 15 -31	; "min"
	200	[297]	GETTABLE 	16 10 -54	; "cover_w"
	201	[297]	DIV      	16 6 16
	202	[297]	GETTABLE 	17 10 -55	; "cover_h"
	203	[297]	DIV      	17 7 17
	204	[297]	CALL     	15 3 2
	205	[298]	GETUPVAL 	16 15	; ImageWidget
	206	[298]	SELF     	16 16 -1	; "new"
	207	[298]	NEWTABLE 	18 0 2
	208	[299]	GETTABLE 	19 10 -50	; "cover_bb"
	209	[299]	SETTABLE 	18 -56 19	; "image" -
	210	[300]	SETTABLE 	18 -57 15	; "scale_factor" -
	211	[298]	CALL     	16 3 2
	212	[302]	SELF     	17 16 -58	; "_render"
	213	[302]	CALL     	17 2 1
	214	[303]	SELF     	17 16 -59	; "getSize"
	215	[303]	CALL     	17 2 2
	216	[304]	GETUPVAL 	18 16	; CenterContainer
	217	[304]	SELF     	18 18 -1	; "new"
	218	[304]	NEWTABLE 	20 0 1
	219	[305]	GETUPVAL 	21 0	; Geom
	220	[305]	SELF     	21 21 -1	; "new"
	221	[305]	NEWTABLE 	23 0 2
	222	[305]	SETTABLE 	23 -2 13	; "w" -
	223	[305]	SETTABLE 	23 -4 14	; "h" -
	224	[305]	CALL     	21 3 2
	225	[305]	SETTABLE 	20 -42 21	; "dimen" -
	226	[306]	GETUPVAL 	21 17	; FrameContainer
	227	[306]	SELF     	21 21 -1	; "new"
	228	[306]	NEWTABLE 	23 1 6
	229	[307]	GETTABLE 	24 17 -2	; "w"
	230	[307]	MUL      	25 -7 5	; 2 -
	231	[307]	ADD      	24 24 25
	232	[307]	SETTABLE 	23 -3 24	; "width" -
	233	[308]	GETTABLE 	24 17 -4	; "h"
	234	[308]	MUL      	25 -7 5	; 2 -
	235	[308]	ADD      	24 24 25
	236	[308]	SETTABLE 	23 -5 24	; "height" -
	237	[309]	SETTABLE 	23 -60 -53	; "margin" 0
	238	[310]	SETTABLE 	23 -61 -53	; "padding" 0
	239	[311]	SETTABLE 	23 -62 5	; "bordersize" -
	240	[312]	GETTABLE 	24 0 -44	; "file_deleted"
	241	[312]	SETTABLE 	23 -63 24	; "dim" -
	242	[314]	MOVE     	24 16
	243	[314]	SETLIST  	23 1 1	; 1
	244	[306]	CALL     	21 3 0
	245	[315]	SETLIST  	20 0 1	; 1
	246	[304]	CALL     	18 3 2
	247	[315]	MOVE     	12 18
	248	[317]	GETTABLE 	18 0 -13	; "menu"
	249	[317]	SETTABLE 	18 -64 -25	; "_has_cover_images" true
	250	[318]	SETTABLE 	0 -65 -25	; "_has_cover_image" true
	251	[318]	JMP      	18	; to 270
	252	[321]	GETUPVAL 	15 16	; CenterContainer
	253	[321]	SELF     	15 15 -1	; "new"
	254	[321]	NEWTABLE 	17 0 1
	255	[322]	GETUPVAL 	18 0	; Geom
	256	[322]	SELF     	18 18 -1	; "new"
	257	[322]	NEWTABLE 	20 0 2
	258	[322]	SETTABLE 	20 -2 13	; "w" -
	259	[322]	SETTABLE 	20 -4 14	; "h" -
	260	[322]	CALL     	18 3 2
	261	[322]	SETTABLE 	17 -42 18	; "dimen" -
	262	[323]	GETUPVAL 	18 12	; HorizontalSpan
	263	[323]	SELF     	18 18 -1	; "new"
	264	[323]	NEWTABLE 	20 0 1
	265	[323]	SETTABLE 	20 -3 13	; "width" -
	266	[323]	CALL     	18 3 0
	267	[324]	SETLIST  	17 0 1	; 1
	268	[321]	CALL     	15 3 2
	269	[324]	MOVE     	12 15
	270	[328]	GETTABLE 	15 10 -50	; "cover_bb"
	271	[328]	TEST     	15 0 0
	272	[328]	JMP      	5	; to 278
	273	[328]	TEST     	11 0 1
	274	[328]	JMP      	3	; to 278
	275	[329]	GETTABLE 	15 10 -50	; "cover_bb"
	276	[329]	SELF     	15 15 -51	; "free"
	277	[329]	CALL     	15 2 1
	278	[332]	GETTABLE 	15 10 -66	; "description"
	279	[332]	TEST     	15 0 0
	280	[332]	JMP      	1	; to 282
	281	[333]	SETTABLE 	0 -67 -25	; "has_description" true
	282	[340]	GETUPVAL 	15 18	; util
	283	[340]	GETTABLE 	15 15 -68	; "splitFilePathName"
	284	[340]	GETTABLE 	16 0 -21	; "filepath"
	285	[340]	CALL     	15 2 3
	286	[341]	GETUPVAL 	17 18	; util
	287	[341]	GETTABLE 	17 17 -69	; "splitFileNameSuffix"
	288	[341]	MOVE     	18 16
	289	[341]	CALL     	17 2 3
	290	[342]	MOVE     	19 18
	291	[343]	GETTABLE 	20 0 -27	; "mandatory"
	292	[343]	TEST     	20 0 0
	293	[343]	JMP      	7	; to 301
	294	[344]	GETTABLE 	20 0 -27	; "mandatory"
	295	[344]	LOADK    	21 -70	; "  "
	296	[344]	GETUPVAL 	22 8	; BD
	297	[344]	GETTABLE 	22 22 -71	; "wrap"
	298	[344]	MOVE     	23 19
	299	[344]	CALL     	22 2 2
	300	[344]	CONCAT   	19 20 22
	301	[346]	GETTABLE 	20 10 -72	; "_no_provider"
	302	[346]	TEST     	20 0 0
	303	[346]	JMP      	2	; to 306
	304	[349]	MOVE     	17 16
	305	[350]	GETTABLE 	19 0 -27	; "mandatory"
	306	[356]	GETTABLE 	20 0 -13	; "menu"
	307	[356]	GETTABLE 	20 20 -73	; "cover_info_cache"
	308	[356]	TEST     	20 0 1
	309	[356]	JMP      	3	; to 313
	310	[357]	GETTABLE 	20 0 -13	; "menu"
	311	[357]	NEWTABLE 	21 0 0
	312	[357]	SETTABLE 	20 -73 21	; "cover_info_cache" -
	313	[359]	LOADK    	20 -74	; ""
	314	[360]	LOADNIL  	21 22
	315	[361]	GETTABLE 	23 10 -75	; "pages"
	316	[362]	GETUPVAL 	24 19	; DocSettings
	317	[362]	SELF     	24 24 -76	; "hasSidecarFile"
	318	[362]	GETTABLE 	26 0 -21	; "filepath"
	319	[362]	CALL     	24 3 2
	320	[362]	TEST     	24 0 0
	321	[362]	JMP      	68	; to 390
	322	[363]	SETTABLE 	0 -77 -25	; "been_opened" true
	323	[364]	GETTABLE 	24 0 -13	; "menu"
	324	[364]	GETTABLE 	24 24 -73	; "cover_info_cache"
	325	[364]	GETTABLE 	25 0 -21	; "filepath"
	326	[364]	GETTABLE 	24 24 25
	327	[364]	TEST     	24 0 0
	328	[364]	JMP      	10	; to 339
	329	[365]	GETGLOBAL	24 -78	; unpack
	330	[365]	GETTABLE 	25 0 -13	; "menu"
	331	[365]	GETTABLE 	25 25 -73	; "cover_info_cache"
	332	[365]	GETTABLE 	26 0 -21	; "filepath"
	333	[365]	GETTABLE 	25 25 26
	334	[365]	CALL     	24 2 4
	335	[365]	MOVE     	22 26
	336	[365]	MOVE     	21 25
	337	[365]	MOVE     	23 24
	338	[365]	JMP      	51	; to 390
	339	[367]	GETUPVAL 	24 19	; DocSettings
	340	[367]	SELF     	24 24 -79	; "open"
	341	[367]	GETTABLE 	26 0 -21	; "filepath"
	342	[367]	CALL     	24 3 2
	343	[369]	GETTABLE 	25 24 -80	; "data"
	344	[369]	GETTABLE 	25 25 -81	; "doc_pages"
	345	[369]	TEST     	25 0 0
	346	[369]	JMP      	3	; to 350
	347	[370]	GETTABLE 	25 24 -80	; "data"
	348	[370]	GETTABLE 	23 25 -81	; "doc_pages"
	349	[370]	JMP      	17	; to 367
	350	[371]	GETTABLE 	25 24 -80	; "data"
	351	[371]	GETTABLE 	25 25 -82	; "stats"
	352	[371]	TEST     	25 0 0
	353	[371]	JMP      	13	; to 367
	354	[371]	GETTABLE 	25 24 -80	; "data"
	355	[371]	GETTABLE 	25 25 -82	; "stats"
	356	[371]	GETTABLE 	25 25 -75	; "pages"
	357	[371]	TEST     	25 0 0
	358	[371]	JMP      	8	; to 367
	359	[372]	GETTABLE 	25 24 -80	; "data"
	360	[372]	GETTABLE 	25 25 -82	; "stats"
	361	[372]	GETTABLE 	25 25 -75	; "pages"
	362	[372]	EQ       	1 25 -53	; - 0
	363	[372]	JMP      	3	; to 367
	364	[373]	GETTABLE 	25 24 -80	; "data"
	365	[373]	GETTABLE 	25 25 -82	; "stats"
	366	[373]	GETTABLE 	23 25 -75	; "pages"
	367	[376]	GETTABLE 	25 24 -80	; "data"
	368	[376]	GETTABLE 	25 25 -83	; "summary"
	369	[376]	TEST     	25 0 0
	370	[376]	JMP      	8	; to 379
	371	[376]	GETTABLE 	25 24 -80	; "data"
	372	[376]	GETTABLE 	25 25 -83	; "summary"
	373	[376]	GETTABLE 	25 25 -84	; "status"
	374	[376]	TEST     	25 0 0
	375	[376]	JMP      	3	; to 379
	376	[377]	GETTABLE 	25 24 -80	; "data"
	377	[377]	GETTABLE 	25 25 -83	; "summary"
	378	[377]	GETTABLE 	22 25 -84	; "status"
	379	[379]	GETTABLE 	25 24 -80	; "data"
	380	[379]	GETTABLE 	21 25 -85	; "percent_finished"
	381	[380]	GETTABLE 	25 0 -13	; "menu"
	382	[380]	GETTABLE 	25 25 -73	; "cover_info_cache"
	383	[380]	GETTABLE 	26 0 -21	; "filepath"
	384	[380]	NEWTABLE 	27 3 0
	385	[380]	MOVE     	28 23
	386	[380]	MOVE     	29 21
	387	[380]	MOVE     	30 22
	388	[380]	SETLIST  	27 3 1	; 1
	389	[380]	SETTABLE 	25 26 27
	390	[383]	EQ       	1 22 -86	; - "complete"
	391	[383]	JMP      	2	; to 394
	392	[383]	EQ       	0 22 -87	; - "abandoned"
	393	[383]	JMP      	32	; to 426
	394	[385]	TEST     	23 0 0
	395	[385]	JMP      	18	; to 414
	396	[386]	EQ       	0 22 -86	; - "complete"
	397	[386]	JMP      	8	; to 406
	398	[387]	GETUPVAL 	24 20	; T
	399	[387]	GETUPVAL 	25 21	; _
	400	[387]	LOADK    	26 -88	; "Finished - %1 pages"
	401	[387]	CALL     	25 2 2
	402	[387]	MOVE     	26 23
	403	[387]	CALL     	24 3 2
	404	[387]	MOVE     	20 24
	405	[387]	JMP      	94	; to 500
	406	[389]	GETUPVAL 	24 20	; T
	407	[389]	GETUPVAL 	25 21	; _
	408	[389]	LOADK    	26 -89	; "On hold - %1 pages"
	409	[389]	CALL     	25 2 2
	410	[389]	MOVE     	26 23
	411	[389]	CALL     	24 3 2
	412	[389]	MOVE     	20 24
	413	[390]	JMP      	86	; to 500
	414	[392]	EQ       	0 22 -86	; - "complete"
	415	[392]	JMP      	5	; to 421
	416	[392]	GETUPVAL 	24 21	; _
	417	[392]	LOADK    	25 -90	; "Finished"
	418	[392]	CALL     	24 2 2
	419	[392]	TESTSET  	20 24 1
	420	[392]	JMP      	4	; to 425
	421	[392]	GETUPVAL 	24 21	; _
	422	[392]	LOADK    	25 -91	; "On hold"
	423	[392]	CALL     	24 2 2
	424	[392]	MOVE     	20 24
	425	[393]	JMP      	74	; to 500
	426	[394]	TEST     	21 0 0
	427	[394]	JMP      	61	; to 489
	428	[395]	TEST     	23 0 0
	429	[395]	JMP      	49	; to 479
	430	[396]	GETUPVAL 	24 14	; BookInfoManager
	431	[396]	SELF     	24 24 -92	; "getSetting"
	432	[396]	LOADK    	26 -93	; "show_pages_read_as_progress"
	433	[396]	CALL     	24 3 2
	434	[396]	TEST     	24 0 0
	435	[396]	JMP      	12	; to 448
	436	[397]	GETUPVAL 	24 20	; T
	437	[397]	GETUPVAL 	25 21	; _
	438	[397]	LOADK    	26 -94	; "Page %1 of %2"
	439	[397]	CALL     	25 2 2
	440	[397]	GETUPVAL 	26 22	; Math
	441	[397]	GETTABLE 	26 26 -95	; "round"
	442	[397]	MUL      	27 21 23
	443	[397]	CALL     	26 2 2
	444	[397]	MOVE     	27 23
	445	[397]	CALL     	24 4 2
	446	[397]	MOVE     	20 24
	447	[397]	JMP      	11	; to 459
	448	[399]	GETUPVAL 	24 20	; T
	449	[399]	GETUPVAL 	25 21	; _
	450	[399]	LOADK    	26 -96	; "%1 % of %2 pages"
	451	[399]	CALL     	25 2 2
	452	[399]	GETGLOBAL	26 -8	; math
	453	[399]	GETTABLE 	26 26 -97	; "floor"
	454	[399]	MUL      	27 -10 21	; 100 -
	455	[399]	CALL     	26 2 2
	456	[399]	MOVE     	27 23
	457	[399]	CALL     	24 4 2
	458	[399]	MOVE     	20 24
	459	[401]	GETUPVAL 	24 14	; BookInfoManager
	460	[401]	SELF     	24 24 -92	; "getSetting"
	461	[401]	LOADK    	26 -98	; "show_pages_left_in_progress"
	462	[401]	CALL     	24 3 2
	463	[401]	TEST     	24 0 0
	464	[401]	JMP      	35	; to 500
	465	[402]	GETUPVAL 	24 20	; T
	466	[402]	GETUPVAL 	25 21	; _
	467	[402]	LOADK    	26 -99	; "%1, %2 to read"
	468	[402]	CALL     	25 2 2
	469	[402]	MOVE     	26 20
	470	[402]	GETUPVAL 	27 22	; Math
	471	[402]	GETTABLE 	27 27 -95	; "round"
	472	[402]	MUL      	28 21 23
	473	[402]	SUB      	28 23 28
	474	[402]	CALL     	27 2 2
	475	[402]	MOVE     	28 23
	476	[402]	CALL     	24 5 2
	477	[402]	MOVE     	20 24
	478	[403]	JMP      	21	; to 500
	479	[405]	GETGLOBAL	24 -100	; string
	480	[405]	GETTABLE 	24 24 -101	; "format"
	481	[405]	LOADK    	25 -102	; "%d %%"
	482	[405]	GETGLOBAL	26 -8	; math
	483	[405]	GETTABLE 	26 26 -97	; "floor"
	484	[405]	MUL      	27 -10 21	; 100 -
	485	[405]	CALL     	26 2 0
	486	[405]	CALL     	24 0 2
	487	[405]	MOVE     	20 24
	488	[406]	JMP      	11	; to 500
	489	[408]	TEST     	23 0 0
	490	[408]	JMP      	9	; to 500
	491	[409]	GETUPVAL 	24 20	; T
	492	[409]	GETUPVAL 	25 23	; N_
	493	[409]	LOADK    	26 -103	; "1 page"
	494	[409]	LOADK    	27 -104	; "%1 pages"
	495	[409]	MOVE     	28 23
	496	[409]	CALL     	25 4 2
	497	[409]	MOVE     	26 23
	498	[409]	CALL     	24 3 2
	499	[409]	MOVE     	20 24
	500	[415]	GETGLOBAL	24 -8	; math
	501	[415]	GETTABLE 	24 24 -31	; "min"
	502	[415]	GETUPVAL 	25 5	; max_fontsize_fileinfo
	503	[415]	MOVE     	26 3
	504	[415]	LOADK    	27 -105	; 14
	505	[415]	CALL     	26 2 0
	506	[415]	CALL     	24 0 2
	507	[417]	GETUPVAL 	25 3	; TextWidget
	508	[417]	SELF     	25 25 -1	; "new"
	509	[417]	NEWTABLE 	27 0 3
	510	[418]	SETTABLE 	27 -26 19	; "text" -
	511	[419]	GETUPVAL 	28 4	; Font
	512	[419]	SELF     	28 28 -29	; "getFace"
	513	[419]	LOADK    	30 -37	; "cfont"
	514	[419]	MOVE     	31 24
	515	[419]	CALL     	28 4 2
	516	[419]	SETTABLE 	27 -28 28	; "face" -
	517	[420]	GETTABLE 	28 0 -44	; "file_deleted"
	518	[420]	TEST     	28 0 0
	519	[420]	JMP      	4	; to 524
	520	[420]	GETUPVAL 	28 24	; Blitbuffer
	521	[420]	GETTABLE 	28 28 -107	; "COLOR_DARK_GRAY"
	522	[420]	TEST     	28 0 1
	523	[420]	JMP      	1	; to 525
	524	[420]	LOADNIL  	28 28
	525	[420]	SETTABLE 	27 -106 28	; "fgcolor" -
	526	[417]	CALL     	25 3 2
	527	[422]	GETUPVAL 	26 3	; TextWidget
	528	[422]	SELF     	26 26 -1	; "new"
	529	[422]	NEWTABLE 	28 0 3
	530	[423]	SETTABLE 	28 -26 20	; "text" -
	531	[424]	GETUPVAL 	29 4	; Font
	532	[424]	SELF     	29 29 -29	; "getFace"
	533	[424]	LOADK    	31 -37	; "cfont"
	534	[424]	MOVE     	32 24
	535	[424]	CALL     	29 4 2
	536	[424]	SETTABLE 	28 -28 29	; "face" -
	537	[425]	GETTABLE 	29 0 -44	; "file_deleted"
	538	[425]	TEST     	29 0 0
	539	[425]	JMP      	4	; to 544
	540	[425]	GETUPVAL 	29 24	; Blitbuffer
	541	[425]	GETTABLE 	29 29 -107	; "COLOR_DARK_GRAY"
	542	[425]	TEST     	29 0 1
	543	[425]	JMP      	1	; to 545
	544	[425]	LOADNIL  	29 29
	545	[425]	SETTABLE 	28 -106 29	; "fgcolor" -
	546	[422]	CALL     	26 3 2
	547	[428]	GETGLOBAL	27 -8	; math
	548	[428]	GETTABLE 	27 27 -108	; "max"
	549	[428]	SELF     	28 25 -59	; "getSize"
	550	[428]	CALL     	28 2 2
	551	[428]	GETTABLE 	28 28 -2	; "w"
	552	[428]	SELF     	29 26 -59	; "getSize"
	553	[428]	CALL     	29 2 2
	554	[428]	GETTABLE 	29 29 -2	; "w"
	555	[428]	CALL     	27 3 2
	556	[429]	GETUPVAL 	28 6	; Screen
	557	[429]	SELF     	28 28 -33	; "scaleBySize"
	558	[429]	LOADK    	30 -34	; 10
	559	[429]	CALL     	28 3 2
	560	[437]	GETUPVAL 	29 16	; CenterContainer
	561	[437]	SELF     	29 29 -1	; "new"
	562	[437]	NEWTABLE 	31 0 1
	563	[438]	GETUPVAL 	32 0	; Geom
	564	[438]	SELF     	32 32 -1	; "new"
	565	[438]	NEWTABLE 	34 0 2
	566	[438]	SETTABLE 	34 -2 27	; "w" -
	567	[438]	GETTABLE 	35 2 -4	; "h"
	568	[438]	SETTABLE 	34 -4 35	; "h" -
	569	[438]	CALL     	32 3 2
	570	[438]	SETTABLE 	31 -42 32	; "dimen" -
	571	[439]	GETUPVAL 	32 25	; VerticalGroup
	572	[439]	SELF     	32 32 -1	; "new"
	573	[439]	NEWTABLE 	34 3 1
	574	[440]	SETTABLE 	34 -109 -110	; "align" "right"
	575	[441]	GETUPVAL 	35 26	; VerticalSpan
	576	[441]	SELF     	35 35 -1	; "new"
	577	[441]	NEWTABLE 	37 0 1
	578	[441]	GETUPVAL 	38 6	; Screen
	579	[441]	SELF     	38 38 -33	; "scaleBySize"
	580	[441]	LOADK    	40 -7	; 2
	581	[441]	CALL     	38 3 2
	582	[441]	SETTABLE 	37 -3 38	; "width" -
	583	[441]	CALL     	35 3 2
	584	[442]	MOVE     	36 25
	585	[444]	MOVE     	37 26
	586	[444]	SETLIST  	34 3 1	; 1
	587	[439]	CALL     	32 3 0
	588	[445]	SETLIST  	31 0 1	; 1
	589	[437]	CALL     	29 3 2
	590	[448]	GETGLOBAL	30 -8	; math
	591	[448]	GETTABLE 	30 30 -97	; "floor"
	592	[448]	GETTABLE 	31 2 -4	; "h"
	593	[448]	DIV      	31 31 -111	; - 6
	594	[448]	CALL     	30 2 2
	595	[450]	GETUPVAL 	31 27	; corner_mark_size
	596	[450]	EQ       	1 30 31
	597	[450]	JMP      	27	; to 625
	598	[451]	SETUPVAL 	30 27	; corner_mark_size
	599	[452]	GETUPVAL 	31 28	; corner_mark
	600	[452]	TEST     	31 0 0
	601	[452]	JMP      	3	; to 605
	602	[453]	GETUPVAL 	31 28	; corner_mark
	603	[453]	SELF     	31 31 -51	; "free"
	604	[453]	CALL     	31 2 1
	605	[455]	GETUPVAL 	31 15	; ImageWidget
	606	[455]	SELF     	31 31 -1	; "new"
	607	[455]	NEWTABLE 	33 0 4
	608	[456]	SETTABLE 	33 -43 -112	; "file" "resources/icons/dogear.png"
	609	[457]	GETUPVAL 	34 8	; BD
	610	[457]	GETTABLE 	34 34 -114	; "mirroredUILayout"
	611	[457]	CALL     	34 1 2
	612	[457]	TEST     	34 0 0
	613	[457]	JMP      	3	; to 617
	614	[457]	LOADK    	34 -115	; 180
	615	[457]	TEST     	34 0 1
	616	[457]	JMP      	1	; to 618
	617	[457]	LOADK    	34 -116	; 270
	618	[457]	SETTABLE 	33 -113 34	; "rotation_angle" -
	619	[458]	GETUPVAL 	34 27	; corner_mark_size
	620	[458]	SETTABLE 	33 -3 34	; "width" -
	621	[459]	GETUPVAL 	34 27	; corner_mark_size
	622	[459]	SETTABLE 	33 -5 34	; "height" -
	623	[455]	CALL     	31 3 2
	624	[460]	SETUPVAL 	31 28	; corner_mark
	625	[464]	GETUPVAL 	31 6	; Screen
	626	[464]	SELF     	31 31 -33	; "scaleBySize"
	627	[464]	LOADK    	33 -34	; 10
	628	[464]	CALL     	31 3 2
	629	[465]	GETTABLE 	32 0 -17	; "do_cover_image"
	630	[465]	TEST     	32 0 0
	631	[465]	JMP      	5	; to 637
	632	[468]	GETUPVAL 	32 6	; Screen
	633	[468]	SELF     	32 32 -33	; "scaleBySize"
	634	[468]	LOADK    	34 -117	; 5
	635	[468]	CALL     	32 3 2
	636	[468]	MOVE     	31 32
	637	[470]	GETUPVAL 	32 6	; Screen
	638	[470]	SELF     	32 32 -33	; "scaleBySize"
	639	[470]	LOADK    	34 -34	; 10
	640	[470]	CALL     	32 3 2
	641	[471]	GETTABLE 	33 2 -2	; "w"
	642	[471]	SUB      	33 33 13
	643	[471]	SUB      	33 33 31
	644	[471]	SUB      	33 33 32
	645	[471]	SUB      	33 33 27
	646	[471]	SUB      	33 33 28
	647	[473]	LOADK    	34 -37	; "cfont"
	648	[474]	LOADK    	35 -37	; "cfont"
	649	[475]	MOVE     	36 3
	650	[475]	LOADK    	37 -38	; 20
	651	[475]	CALL     	36 2 2
	652	[476]	MOVE     	37 3
	653	[476]	LOADK    	38 -118	; 18
	654	[476]	CALL     	37 2 2
	655	[477]	LOADNIL  	38 41
	656	[479]	GETUPVAL 	42 14	; BookInfoManager
	657	[479]	SELF     	42 42 -92	; "getSetting"
	658	[479]	LOADK    	44 -119	; "series_mode"
	659	[479]	CALL     	42 3 2
	660	[486]	GETTABLE 	43 0 -120	; "do_filename_only"
	661	[486]	TEST     	43 0 1
	662	[486]	JMP      	3	; to 666
	663	[486]	GETTABLE 	43 10 -121	; "ignore_meta"
	664	[486]	TEST     	43 0 0
	665	[486]	JMP      	8	; to 674
	666	[487]	MOVE     	40 17
	667	[488]	GETUPVAL 	43 8	; BD
	668	[488]	GETTABLE 	43 43 -122	; "auto"
	669	[488]	MOVE     	44 40
	670	[488]	CALL     	43 2 2
	671	[488]	MOVE     	40 43
	672	[489]	LOADNIL  	41 41
	673	[489]	JMP      	89	; to 763
	674	[491]	GETTABLE 	43 10 -123	; "title"
	675	[491]	TEST     	43 0 0
	676	[491]	JMP      	3	; to 680
	677	[491]	GETTABLE 	43 10 -123	; "title"
	678	[491]	TESTSET  	40 43 1
	679	[491]	JMP      	1	; to 681
	680	[491]	MOVE     	40 17
	681	[492]	GETUPVAL 	43 8	; BD
	682	[492]	GETTABLE 	43 43 -122	; "auto"
	683	[492]	MOVE     	44 40
	684	[492]	CALL     	43 2 2
	685	[492]	MOVE     	40 43
	686	[493]	GETTABLE 	41 10 -124	; "authors"
	687	[497]	TEST     	41 0 0
	688	[497]	JMP      	67	; to 756
	689	[497]	SELF     	43 41 -125	; "find"
	690	[497]	LOADK    	45 -126	; "\n"
	691	[497]	CALL     	43 3 2
	692	[497]	TEST     	43 0 0
	693	[497]	JMP      	62	; to 756
	694	[498]	GETUPVAL 	43 18	; util
	695	[498]	GETTABLE 	43 43 -127	; "splitToArray"
	696	[498]	MOVE     	44 41
	697	[498]	LOADK    	45 -126	; "\n"
	698	[498]	CALL     	43 3 2
	699	[498]	MOVE     	41 43
	700	[499]	LOADK    	43 -11	; 1
	701	[499]	LEN      	44 41
	702	[499]	LOADK    	45 -11	; 1
	703	[499]	FORPREP  	43 5	; to 709
	704	[500]	GETUPVAL 	47 8	; BD
	705	[500]	GETTABLE 	47 47 -122	; "auto"
	706	[500]	GETTABLE 	48 41 46
	707	[500]	CALL     	47 2 2
	708	[500]	SETTABLE 	41 46 47
	709	[499]	FORLOOP  	43 -6	; to 704
	710	[502]	LEN      	43 41
	711	[502]	LT       	0 -11 43	; 1 -
	712	[502]	JMP      	15	; to 728
	713	[502]	GETTABLE 	43 10 -128	; "series"
	714	[502]	TEST     	43 0 0
	715	[502]	JMP      	12	; to 728
	716	[502]	EQ       	0 42 -129	; - "series_in_separate_line"
	717	[502]	JMP      	10	; to 728
	718	[503]	NEWTABLE 	43 0 0
	719	[503]	GETUPVAL 	44 20	; T
	720	[503]	GETUPVAL 	45 21	; _
	721	[503]	LOADK    	46 -130	; "%1 et al."
	722	[503]	CALL     	45 2 2
	723	[503]	GETTABLE 	46 41 -11	; 1
	724	[503]	CALL     	44 3 0
	725	[503]	SETLIST  	43 0 1	; 1
	726	[503]	MOVE     	41 43
	727	[503]	JMP      	13	; to 741
	728	[504]	LEN      	43 41
	729	[504]	LT       	0 -7 43	; 2 -
	730	[504]	JMP      	10	; to 741
	731	[505]	NEWTABLE 	43 1 0
	732	[505]	GETTABLE 	44 41 -11	; 1
	733	[505]	GETUPVAL 	45 20	; T
	734	[505]	GETUPVAL 	46 21	; _
	735	[505]	LOADK    	47 -130	; "%1 et al."
	736	[505]	CALL     	46 2 2
	737	[505]	GETTABLE 	47 41 -7	; 2
	738	[505]	CALL     	45 3 0
	739	[505]	SETLIST  	43 0 1	; 1
	740	[505]	MOVE     	41 43
	741	[507]	GETGLOBAL	43 -131	; table
	742	[507]	GETTABLE 	43 43 -132	; "concat"
	743	[507]	MOVE     	44 41
	744	[507]	LOADK    	45 -126	; "\n"
	745	[507]	CALL     	43 3 2
	746	[507]	MOVE     	41 43
	747	[509]	MOVE     	43 3
	748	[509]	LOADK    	44 -133	; 17
	749	[509]	CALL     	43 2 2
	750	[509]	MOVE     	36 43
	751	[510]	MOVE     	43 3
	752	[510]	LOADK    	44 -32	; 15
	753	[510]	CALL     	43 2 2
	754	[510]	MOVE     	37 43
	755	[510]	JMP      	7	; to 763
	756	[511]	TEST     	41 0 0
	757	[511]	JMP      	5	; to 763
	758	[512]	GETUPVAL 	43 8	; BD
	759	[512]	GETTABLE 	43 43 -122	; "auto"
	760	[512]	MOVE     	44 41
	761	[512]	CALL     	43 2 2
	762	[512]	MOVE     	41 43
	763	[516]	GETTABLE 	43 10 -128	; "series"
	764	[516]	TEST     	43 0 0
	765	[516]	JMP      	50	; to 816
	766	[518]	GETTABLE 	43 10 -128	; "series"
	767	[518]	SELF     	43 43 -134	; "gsub"
	768	[518]	LOADK    	45 -135	; "(#%d+)%.0$"
	769	[518]	LOADK    	46 -136	; "%1"
	770	[518]	CALL     	43 4 2
	771	[518]	SETTABLE 	10 -128 43	; "series" -
	772	[519]	GETUPVAL 	43 8	; BD
	773	[519]	GETTABLE 	43 43 -122	; "auto"
	774	[519]	GETTABLE 	44 10 -128	; "series"
	775	[519]	CALL     	43 2 2
	776	[519]	SETTABLE 	10 -128 43	; "series" -
	777	[520]	EQ       	0 42 -137	; - "append_series_to_title"
	778	[520]	JMP      	8	; to 787
	779	[521]	TEST     	40 0 0
	780	[521]	JMP      	5	; to 786
	781	[522]	MOVE     	43 40
	782	[522]	LOADK    	44 -138	; " - "
	783	[522]	GETTABLE 	45 10 -128	; "series"
	784	[522]	CONCAT   	40 43 45
	785	[522]	JMP      	1	; to 787
	786	[524]	GETTABLE 	40 10 -128	; "series"
	787	[527]	TEST     	41 0 1
	788	[527]	JMP      	6	; to 795
	789	[528]	EQ       	1 42 -139	; - "append_series_to_authors"
	790	[528]	JMP      	2	; to 793
	791	[528]	EQ       	0 42 -129	; - "series_in_separate_line"
	792	[528]	JMP      	23	; to 816
	793	[529]	GETTABLE 	41 10 -128	; "series"
	794	[530]	JMP      	21	; to 816
	795	[532]	EQ       	0 42 -139	; - "append_series_to_authors"
	796	[532]	JMP      	5	; to 802
	797	[533]	MOVE     	43 41
	798	[533]	LOADK    	44 -138	; " - "
	799	[533]	GETTABLE 	45 10 -128	; "series"
	800	[533]	CONCAT   	41 43 45
	801	[533]	JMP      	14	; to 816
	802	[534]	EQ       	0 42 -129	; - "series_in_separate_line"
	803	[534]	JMP      	12	; to 816
	804	[535]	GETTABLE 	43 10 -128	; "series"
	805	[535]	LOADK    	44 -126	; "\n"
	806	[535]	MOVE     	45 41
	807	[535]	CONCAT   	41 43 45
	808	[537]	MOVE     	43 3
	809	[537]	LOADK    	44 -133	; 17
	810	[537]	CALL     	43 2 2
	811	[537]	MOVE     	36 43
	812	[538]	MOVE     	43 3
	813	[538]	LOADK    	44 -32	; 15
	814	[538]	CALL     	43 2 2
	815	[538]	MOVE     	37 43
	816	[542]	GETTABLE 	43 10 -140	; "unsupported"
	817	[542]	TEST     	43 0 0
	818	[542]	JMP      	7	; to 826
	819	[544]	GETUPVAL 	43 20	; T
	820	[544]	GETUPVAL 	44 21	; _
	821	[544]	LOADK    	45 -141	; "(no book information: %1)"
	822	[544]	CALL     	44 2 2
	823	[544]	GETTABLE 	45 10 -140	; "unsupported"
	824	[544]	CALL     	43 3 2
	825	[544]	MOVE     	41 43
	826	[550]	TEST     	38 0 0
	827	[550]	JMP      	2	; to 830
	828	[551]	SELF     	43 38 -51	; "free"
	829	[551]	CALL     	43 2 1
	830	[553]	TEST     	39 0 0
	831	[553]	JMP      	3	; to 835
	832	[554]	SELF     	43 39 -51	; "free"
	833	[554]	CALL     	43 2 1
	834	[555]	LOADNIL  	39 39
	835	[561]	GETUPVAL 	43 7	; TextBoxWidget
	836	[561]	SELF     	43 43 -1	; "new"
	837	[561]	NEWTABLE 	45 0 7
	838	[562]	SETTABLE 	45 -26 40	; "text" -
	839	[563]	GETTABLE 	46 10 -143	; "language"
	840	[563]	SETTABLE 	45 -142 46	; "lang" -
	841	[564]	GETUPVAL 	46 4	; Font
	842	[564]	SELF     	46 46 -29	; "getFace"
	843	[564]	MOVE     	48 34
	844	[564]	MOVE     	49 36
	845	[564]	CALL     	46 4 2
	846	[564]	SETTABLE 	45 -28 46	; "face" -
	847	[565]	SETTABLE 	45 -3 33	; "width" -
	848	[566]	SETTABLE 	45 -39 -40	; "alignment" "left"
	849	[567]	SETTABLE 	45 -41 -25	; "bold" true
	850	[568]	GETTABLE 	46 0 -44	; "file_deleted"
	851	[568]	TEST     	46 0 0
	852	[568]	JMP      	4	; to 857
	853	[568]	GETUPVAL 	46 24	; Blitbuffer
	854	[568]	GETTABLE 	46 46 -107	; "COLOR_DARK_GRAY"
	855	[568]	TEST     	46 0 1
	856	[568]	JMP      	1	; to 858
	857	[568]	LOADNIL  	46 46
	858	[568]	SETTABLE 	45 -106 46	; "fgcolor" -
	859	[561]	CALL     	43 3 2
	860	[569]	MOVE     	38 43
	861	[570]	SELF     	43 38 -59	; "getSize"
	862	[570]	CALL     	43 2 2
	863	[570]	GETTABLE 	43 43 -4	; "h"
	864	[571]	TEST     	41 0 0
	865	[571]	JMP      	29	; to 895
	866	[572]	GETUPVAL 	44 7	; TextBoxWidget
	867	[572]	SELF     	44 44 -1	; "new"
	868	[572]	NEWTABLE 	46 0 6
	869	[573]	SETTABLE 	46 -26 41	; "text" -
	870	[574]	GETTABLE 	47 10 -143	; "language"
	871	[574]	SETTABLE 	46 -142 47	; "lang" -
	872	[575]	GETUPVAL 	47 4	; Font
	873	[575]	SELF     	47 47 -29	; "getFace"
	874	[575]	MOVE     	49 35
	875	[575]	MOVE     	50 37
	876	[575]	CALL     	47 4 2
	877	[575]	SETTABLE 	46 -28 47	; "face" -
	878	[576]	SETTABLE 	46 -3 33	; "width" -
	879	[577]	SETTABLE 	46 -39 -40	; "alignment" "left"
	880	[578]	GETTABLE 	47 0 -44	; "file_deleted"
	881	[578]	TEST     	47 0 0
	882	[578]	JMP      	4	; to 887
	883	[578]	GETUPVAL 	47 24	; Blitbuffer
	884	[578]	GETTABLE 	47 47 -107	; "COLOR_DARK_GRAY"
	885	[578]	TEST     	47 0 1
	886	[578]	JMP      	1	; to 888
	887	[578]	LOADNIL  	47 47
	888	[578]	SETTABLE 	46 -106 47	; "fgcolor" -
	889	[572]	CALL     	44 3 2
	890	[579]	MOVE     	39 44
	891	[580]	SELF     	44 39 -59	; "getSize"
	892	[580]	CALL     	44 2 2
	893	[580]	GETTABLE 	44 44 -4	; "h"
	894	[580]	ADD      	43 43 44
	895	[582]	GETTABLE 	44 2 -4	; "h"
	896	[582]	LT       	0 43 44
	897	[582]	JMP      	1	; to 899
	898	[583]	JMP      	14	; to 913
	899	[586]	SUB      	36 36 4
	900	[587]	SUB      	37 37 4
	901	[588]	GETUPVAL 	44 29	; logger
	902	[588]	GETTABLE 	44 44 -144	; "dbg"
	903	[588]	MOVE     	45 40
	904	[588]	LOADK    	46 -145	; "recalculate title/author with"
	905	[588]	MOVE     	47 36
	906	[588]	CALL     	44 4 1
	907	[590]	LT       	1 36 -36	; - 3
	908	[590]	JMP      	4	; to 913
	909	[590]	LT       	0 37 -36	; - 3
	910	[590]	JMP      	-85	; to 826
	911	[591]	JMP      	1	; to 913
	912	[592]	JMP      	-87	; to 826
	913	[595]	GETUPVAL 	43 10	; LeftContainer
	914	[595]	SELF     	43 43 -1	; "new"
	915	[595]	NEWTABLE 	45 0 1
	916	[596]	SETTABLE 	45 -42 2	; "dimen" -
	917	[597]	GETUPVAL 	46 25	; VerticalGroup
	918	[597]	SELF     	46 46 -1	; "new"
	919	[597]	NEWTABLE 	48 2 0
	920	[598]	MOVE     	49 38
	921	[600]	MOVE     	50 39
	922	[600]	SETLIST  	48 2 1	; 1
	923	[597]	CALL     	46 3 0
	924	[601]	SETLIST  	45 0 1	; 1
	925	[595]	CALL     	43 3 2
	926	[604]	GETUPVAL 	44 9	; OverlapGroup
	927	[604]	SELF     	44 44 -1	; "new"
	928	[604]	NEWTABLE 	46 0 1
	929	[605]	SETTABLE 	46 -42 2	; "dimen" -
	930	[604]	CALL     	44 3 2
	931	[606]	MOVE     	1 44
	932	[607]	GETTABLE 	44 0 -17	; "do_cover_image"
	933	[607]	TEST     	44 0 0
	934	[607]	JMP      	25	; to 960
	935	[609]	TEST     	12 0 0
	936	[609]	JMP      	5	; to 942
	937	[613]	GETGLOBAL	44 -131	; table
	938	[613]	GETTABLE 	44 44 -146	; "insert"
	939	[613]	MOVE     	45 1
	940	[613]	MOVE     	46 12
	941	[613]	CALL     	44 3 1
	942	[616]	GETUPVAL 	44 11	; HorizontalGroup
	943	[616]	SELF     	44 44 -1	; "new"
	944	[616]	NEWTABLE 	46 3 0
	945	[617]	GETUPVAL 	47 12	; HorizontalSpan
	946	[617]	SELF     	47 47 -1	; "new"
	947	[617]	NEWTABLE 	49 0 1
	948	[617]	SETTABLE 	49 -3 13	; "width" -
	949	[617]	CALL     	47 3 2
	950	[618]	GETUPVAL 	48 12	; HorizontalSpan
	951	[618]	SELF     	48 48 -1	; "new"
	952	[618]	NEWTABLE 	50 0 1
	953	[618]	SETTABLE 	50 -3 31	; "width" -
	954	[618]	CALL     	48 3 2
	955	[620]	MOVE     	49 43
	956	[620]	SETLIST  	46 3 1	; 1
	957	[616]	CALL     	44 3 2
	958	[620]	MOVE     	43 44
	959	[620]	JMP      	12	; to 972
	960	[623]	GETUPVAL 	44 11	; HorizontalGroup
	961	[623]	SELF     	44 44 -1	; "new"
	962	[623]	NEWTABLE 	46 2 0
	963	[624]	GETUPVAL 	47 12	; HorizontalSpan
	964	[624]	SELF     	47 47 -1	; "new"
	965	[624]	NEWTABLE 	49 0 1
	966	[624]	SETTABLE 	49 -3 31	; "width" -
	967	[624]	CALL     	47 3 2
	968	[626]	MOVE     	48 43
	969	[626]	SETLIST  	46 2 1	; 1
	970	[623]	CALL     	44 3 2
	971	[626]	MOVE     	43 44
	972	[629]	GETGLOBAL	44 -131	; table
	973	[629]	GETTABLE 	44 44 -146	; "insert"
	974	[629]	MOVE     	45 1
	975	[629]	GETUPVAL 	46 10	; LeftContainer
	976	[629]	SELF     	46 46 -1	; "new"
	977	[629]	NEWTABLE 	48 1 1
	978	[630]	SETTABLE 	48 -42 2	; "dimen" -
	979	[632]	MOVE     	49 43
	980	[632]	SETLIST  	48 1 1	; 1
	981	[629]	CALL     	46 3 0
	982	[629]	CALL     	44 0 1
	983	[634]	GETGLOBAL	44 -131	; table
	984	[634]	GETTABLE 	44 44 -146	; "insert"
	985	[634]	MOVE     	45 1
	986	[634]	GETUPVAL 	46 13	; RightContainer
	987	[634]	SELF     	46 46 -1	; "new"
	988	[634]	NEWTABLE 	48 0 1
	989	[635]	SETTABLE 	48 -42 2	; "dimen" -
	990	[636]	GETUPVAL 	49 11	; HorizontalGroup
	991	[636]	SELF     	49 49 -1	; "new"
	992	[636]	NEWTABLE 	51 1 0
	993	[637]	MOVE     	52 29
	994	[638]	GETUPVAL 	53 12	; HorizontalSpan
	995	[638]	SELF     	53 53 -1	; "new"
	996	[638]	NEWTABLE 	55 0 1
	997	[638]	SETTABLE 	55 -3 28	; "width" -
	998	[638]	CALL     	53 3 0
	999	[639]	SETLIST  	51 0 1	; 1
	1000	[636]	CALL     	49 3 0
	1001	[640]	SETLIST  	48 0 1	; 1
	1002	[634]	CALL     	46 3 0
	1003	[634]	CALL     	44 0 1
	1004	[640]	JMP      	101	; to 1106
	1005	[643]	GETTABLE 	11 0 -147	; "init_done"
	1006	[643]	TEST     	11 0 0
	1007	[643]	JMP      	1	; to 1009
	1008	[646]	RETURN   	0 1
	1009	[651]	GETTABLE 	11 0 -17	; "do_cover_image"
	1010	[651]	TEST     	11 0 0
	1011	[651]	JMP      	1	; to 1013
	1012	[653]	SETTABLE 	0 -18 8	; "cover_specs" -
	1013	[656]	GETTABLE 	11 0 -148	; "do_hint_opened"
	1014	[656]	TEST     	11 0 0
	1015	[656]	JMP      	7	; to 1023
	1016	[656]	GETUPVAL 	11 19	; DocSettings
	1017	[656]	SELF     	11 11 -76	; "hasSidecarFile"
	1018	[656]	GETTABLE 	13 0 -21	; "filepath"
	1019	[656]	CALL     	11 3 2
	1020	[656]	TEST     	11 0 0
	1021	[656]	JMP      	1	; to 1023
	1022	[657]	SETTABLE 	0 -77 -25	; "been_opened" true
	1023	[660]	LOADK    	11 -149	; "\226\128\166"
	1024	[661]	GETTABLE 	12 0 -44	; "file_deleted"
	1025	[661]	TEST     	12 0 0
	1026	[661]	JMP      	5	; to 1032
	1027	[662]	LOADK    	12 -150	; " "
	1028	[662]	GETUPVAL 	13 21	; _
	1029	[662]	LOADK    	14 -151	; "(deleted)"
	1030	[662]	CALL     	13 2 2
	1031	[662]	CONCAT   	11 12 13
	1032	[664]	GETUPVAL 	12 8	; BD
	1033	[664]	GETTABLE 	12 12 -152	; "filename"
	1034	[664]	GETTABLE 	13 0 -26	; "text"
	1035	[664]	CALL     	12 2 2
	1036	[665]	LOADNIL  	13 13
	1037	[666]	MOVE     	14 3
	1038	[666]	LOADK    	15 -118	; 18
	1039	[666]	CALL     	14 2 2
	1040	[668]	TEST     	13 0 0
	1041	[668]	JMP      	2	; to 1044
	1042	[669]	SELF     	15 13 -51	; "free"
	1043	[669]	CALL     	15 2 1
	1044	[671]	GETUPVAL 	15 7	; TextBoxWidget
	1045	[671]	SELF     	15 15 -1	; "new"
	1046	[671]	NEWTABLE 	17 0 5
	1047	[672]	MOVE     	18 12
	1048	[672]	MOVE     	19 11
	1049	[672]	CONCAT   	18 18 19
	1050	[672]	SETTABLE 	17 -26 18	; "text" -
	1051	[673]	GETUPVAL 	18 4	; Font
	1052	[673]	SELF     	18 18 -29	; "getFace"
	1053	[673]	LOADK    	20 -37	; "cfont"
	1054	[673]	MOVE     	21 14
	1055	[673]	CALL     	18 4 2
	1056	[673]	SETTABLE 	17 -28 18	; "face" -
	1057	[674]	GETTABLE 	18 2 -2	; "w"
	1058	[674]	GETUPVAL 	19 6	; Screen
	1059	[674]	SELF     	19 19 -33	; "scaleBySize"
	1060	[674]	LOADK    	21 -34	; 10
	1061	[674]	CALL     	19 3 2
	1062	[674]	MUL      	19 -7 19	; 2 -
	1063	[674]	SUB      	18 18 19
	1064	[674]	SETTABLE 	17 -3 18	; "width" -
	1065	[675]	SETTABLE 	17 -39 -40	; "alignment" "left"
	1066	[676]	GETTABLE 	18 0 -44	; "file_deleted"
	1067	[676]	TEST     	18 0 0
	1068	[676]	JMP      	4	; to 1073
	1069	[676]	GETUPVAL 	18 24	; Blitbuffer
	1070	[676]	GETTABLE 	18 18 -107	; "COLOR_DARK_GRAY"
	1071	[676]	TEST     	18 0 1
	1072	[676]	JMP      	1	; to 1074
	1073	[676]	LOADNIL  	18 18
	1074	[676]	SETTABLE 	17 -106 18	; "fgcolor" -
	1075	[671]	CALL     	15 3 2
	1076	[677]	MOVE     	13 15
	1077	[679]	SUB      	14 14 4
	1078	[680]	SELF     	15 13 -59	; "getSize"
	1079	[680]	CALL     	15 2 2
	1080	[680]	GETTABLE 	15 15 -4	; "h"
	1081	[680]	GETTABLE 	16 2 -4	; "h"
	1082	[680]	LE       	0 15 16
	1083	[680]	JMP      	-44	; to 1040
	1084	[681]	GETUPVAL 	15 10	; LeftContainer
	1085	[681]	SELF     	15 15 -1	; "new"
	1086	[681]	NEWTABLE 	17 0 1
	1087	[682]	SETTABLE 	17 -42 2	; "dimen" -
	1088	[683]	GETUPVAL 	18 11	; HorizontalGroup
	1089	[683]	SELF     	18 18 -1	; "new"
	1090	[683]	NEWTABLE 	20 2 0
	1091	[684]	GETUPVAL 	21 12	; HorizontalSpan
	1092	[684]	SELF     	21 21 -1	; "new"
	1093	[684]	NEWTABLE 	23 0 1
	1094	[684]	GETUPVAL 	24 6	; Screen
	1095	[684]	SELF     	24 24 -33	; "scaleBySize"
	1096	[684]	LOADK    	26 -34	; 10
	1097	[684]	CALL     	24 3 2
	1098	[684]	SETTABLE 	23 -3 24	; "width" -
	1099	[684]	CALL     	21 3 2
	1100	[686]	MOVE     	22 13
	1101	[686]	SETLIST  	20 2 1	; 1
	1102	[683]	CALL     	18 3 0
	1103	[687]	SETLIST  	17 0 1	; 1
	1104	[681]	CALL     	15 3 2
	1105	[687]	MOVE     	1 15
	1106	[692]	GETTABLE 	10 0 -153	; "_underline_container"
	1107	[692]	GETTABLE 	10 10 -11	; 1
	1108	[692]	TEST     	10 0 0
	1109	[692]	JMP      	4	; to 1114
	1110	[694]	GETTABLE 	10 0 -153	; "_underline_container"
	1111	[694]	GETTABLE 	10 10 -11	; 1
	1112	[695]	SELF     	11 10 -51	; "free"
	1113	[695]	CALL     	11 2 1
	1114	[698]	GETTABLE 	10 0 -153	; "_underline_container"
	1115	[698]	GETUPVAL 	11 25	; VerticalGroup
	1116	[698]	SELF     	11 11 -1	; "new"
	1117	[698]	NEWTABLE 	13 2 0
	1118	[699]	GETUPVAL 	14 26	; VerticalSpan
	1119	[699]	SELF     	14 14 -1	; "new"
	1120	[699]	NEWTABLE 	16 0 1
	1121	[699]	GETTABLE 	17 0 -6	; "underline_h"
	1122	[699]	SETTABLE 	16 -3 17	; "width" -
	1123	[699]	CALL     	14 3 2
	1124	[701]	MOVE     	15 1
	1125	[701]	SETLIST  	13 2 1	; 1
	1126	[698]	CALL     	11 3 2
	1127	[701]	SETTABLE 	10 -11 11	; 1 -
	1128	[702]	RETURN   	0 1

function <./plugins/coverbrowser.koplugin/listmenu.lua:193,198> (12 instructions, 48 bytes at 0x7fdc3ec08aa0)
1 param, 4 slots, 2 upvalues, 2 locals, 4 constants, 0 functions
	1	[196]	GETUPVAL 	1 0	; dimen
	2	[196]	GETTABLE 	1 1 -1	; "h"
	3	[196]	MUL      	1 0 1
	4	[196]	DIV      	1 1 -2	; - 64
	5	[196]	GETUPVAL 	2 1	; scale_by_size
	6	[196]	DIV      	1 1 2
	7	[197]	GETGLOBAL	2 -3	; math
	8	[197]	GETTABLE 	2 2 -4	; "floor"
	9	[197]	MOVE     	3 1
	10	[197]	TAILCALL 	2 2 0
	11	[197]	RETURN   	2 0
	12	[198]	RETURN   	0 1

function <./plugins/coverbrowser.koplugin/listmenu.lua:704,769> (172 instructions, 688 bytes at 0x7fdc3ec0a9b0)
4 params, 15 slots, 6 upvalues, 14 locals, 29 constants, 0 functions
	1	[709]	GETGLOBAL	4 -1	; math
	2	[709]	GETTABLE 	4 4 -2	; "floor"
	3	[709]	MOVE     	5 2
	4	[709]	CALL     	4 2 2
	5	[709]	EQ       	0 2 4
	6	[709]	JMP      	6	; to 13
	7	[709]	GETGLOBAL	4 -1	; math
	8	[709]	GETTABLE 	4 4 -2	; "floor"
	9	[709]	MOVE     	5 3
	10	[709]	CALL     	4 2 2
	11	[709]	EQ       	1 3 4
	12	[709]	JMP      	6	; to 19
	13	[710]	GETUPVAL 	4 0	; logger
	14	[710]	GETTABLE 	4 4 -3	; "err"
	15	[710]	LOADK    	5 -4	; "ListMenuItem:paintTo() got non-integer x/y :"
	16	[710]	MOVE     	6 2
	17	[710]	MOVE     	7 3
	18	[710]	CALL     	4 4 1
	19	[714]	GETUPVAL 	4 1	; InputContainer
	20	[714]	GETTABLE 	4 4 -5	; "paintTo"
	21	[714]	MOVE     	5 0
	22	[714]	MOVE     	6 1
	23	[714]	MOVE     	7 2
	24	[714]	MOVE     	8 3
	25	[714]	CALL     	4 5 1
	26	[717]	GETTABLE 	4 0 -6	; "shortcut_icon"
	27	[717]	TEST     	4 0 0
	28	[717]	JMP      	29	; to 58
	29	[719]	GETTABLE 	4 0 -7	; 1
	30	[719]	GETTABLE 	4 4 -7	; 1
	31	[719]	GETTABLE 	4 4 -8	; 2
	32	[720]	LOADNIL  	5 5
	33	[721]	GETUPVAL 	6 2	; BD
	34	[721]	GETTABLE 	6 6 -9	; "mirroredUILayout"
	35	[721]	CALL     	6 1 2
	36	[721]	TEST     	6 0 0
	37	[721]	JMP      	7	; to 45
	38	[722]	GETTABLE 	6 4 -10	; "dimen"
	39	[722]	GETTABLE 	6 6 -11	; "w"
	40	[722]	GETTABLE 	7 0 -6	; "shortcut_icon"
	41	[722]	GETTABLE 	7 7 -10	; "dimen"
	42	[722]	GETTABLE 	7 7 -11	; "w"
	43	[722]	SUB      	5 6 7
	44	[722]	JMP      	1	; to 46
	45	[724]	LOADK    	5 -12	; 0
	46	[726]	GETTABLE 	6 4 -10	; "dimen"
	47	[726]	GETTABLE 	6 6 -13	; "h"
	48	[726]	GETTABLE 	7 0 -6	; "shortcut_icon"
	49	[726]	GETTABLE 	7 7 -10	; "dimen"
	50	[726]	GETTABLE 	7 7 -13	; "h"
	51	[726]	SUB      	6 6 7
	52	[727]	GETTABLE 	7 0 -6	; "shortcut_icon"
	53	[727]	SELF     	7 7 -5	; "paintTo"
	54	[727]	MOVE     	9 1
	55	[727]	ADD      	10 2 5
	56	[727]	ADD      	11 3 6
	57	[727]	CALL     	7 5 1
	58	[731]	GETUPVAL 	4 3	; corner_mark
	59	[731]	TEST     	4 0 0
	60	[731]	JMP      	32	; to 93
	61	[731]	GETTABLE 	4 0 -14	; "do_hint_opened"
	62	[731]	TEST     	4 0 0
	63	[731]	JMP      	29	; to 93
	64	[731]	GETTABLE 	4 0 -15	; "been_opened"
	65	[731]	TEST     	4 0 0
	66	[731]	JMP      	26	; to 93
	67	[733]	LOADNIL  	4 4
	68	[734]	GETUPVAL 	5 2	; BD
	69	[734]	GETTABLE 	5 5 -9	; "mirroredUILayout"
	70	[734]	CALL     	5 1 2
	71	[734]	TEST     	5 0 0
	72	[734]	JMP      	2	; to 75
	73	[735]	LOADK    	4 -12	; 0
	74	[735]	JMP      	6	; to 81
	75	[737]	GETTABLE 	5 0 -16	; "width"
	76	[737]	GETUPVAL 	6 3	; corner_mark
	77	[737]	SELF     	6 6 -17	; "getSize"
	78	[737]	CALL     	6 2 2
	79	[737]	GETTABLE 	6 6 -11	; "w"
	80	[737]	SUB      	4 5 6
	81	[739]	GETTABLE 	5 0 -18	; "height"
	82	[739]	GETUPVAL 	6 3	; corner_mark
	83	[739]	SELF     	6 6 -17	; "getSize"
	84	[739]	CALL     	6 2 2
	85	[739]	GETTABLE 	6 6 -13	; "h"
	86	[739]	SUB      	5 5 6
	87	[740]	GETUPVAL 	6 3	; corner_mark
	88	[740]	SELF     	6 6 -5	; "paintTo"
	89	[740]	MOVE     	8 1
	90	[740]	ADD      	9 2 4
	91	[740]	ADD      	10 3 5
	92	[740]	CALL     	6 5 1
	93	[744]	GETTABLE 	4 0 -19	; "has_description"
	94	[744]	TEST     	4 0 0
	95	[744]	JMP      	76	; to 172
	96	[744]	GETUPVAL 	4 4	; BookInfoManager
	97	[744]	SELF     	4 4 -20	; "getSetting"
	98	[744]	LOADK    	6 -21	; "no_hint_description"
	99	[744]	CALL     	4 3 2
	100	[744]	TEST     	4 0 1
	101	[744]	JMP      	70	; to 172
	102	[745]	GETTABLE 	4 0 -7	; 1
	103	[745]	GETTABLE 	4 4 -7	; 1
	104	[745]	GETTABLE 	4 4 -8	; 2
	105	[746]	GETUPVAL 	5 5	; Screen
	106	[746]	SELF     	5 5 -22	; "scaleBySize"
	107	[746]	LOADK    	7 -23	; 3
	108	[746]	CALL     	5 3 2
	109	[747]	GETGLOBAL	6 -1	; math
	110	[747]	GETTABLE 	6 6 -24	; "ceil"
	111	[747]	GETTABLE 	7 4 -10	; "dimen"
	112	[747]	GETTABLE 	7 7 -13	; "h"
	113	[747]	DIV      	7 7 -25	; - 4
	114	[747]	CALL     	6 2 2
	115	[748]	GETTABLE 	7 0 -26	; "do_cover_image"
	116	[748]	TEST     	7 0 0
	117	[748]	JMP      	33	; to 151
	118	[748]	GETTABLE 	7 4 -7	; 1
	119	[748]	GETTABLE 	7 7 -7	; 1
	120	[748]	GETTABLE 	7 7 -7	; 1
	121	[748]	TEST     	7 0 0
	122	[748]	JMP      	28	; to 151
	123	[750]	GETTABLE 	7 4 -7	; 1
	124	[750]	GETTABLE 	4 7 -7	; 1
	125	[751]	LOADNIL  	7 7
	126	[752]	GETUPVAL 	8 2	; BD
	127	[752]	GETTABLE 	8 8 -9	; "mirroredUILayout"
	128	[752]	CALL     	8 1 2
	129	[752]	TEST     	8 0 0
	130	[752]	JMP      	5	; to 136
	131	[753]	GETTABLE 	8 4 -10	; "dimen"
	132	[753]	GETTABLE 	8 8 -27	; "x"
	133	[753]	SUB      	8 8 5
	134	[753]	ADD      	7 8 -7	; - 1
	135	[753]	JMP      	6	; to 142
	136	[755]	GETTABLE 	8 4 -10	; "dimen"
	137	[755]	GETTABLE 	8 8 -27	; "x"
	138	[755]	GETTABLE 	9 4 -10	; "dimen"
	139	[755]	GETTABLE 	9 9 -11	; "w"
	140	[755]	ADD      	8 8 9
	141	[755]	SUB      	7 8 -7	; - 1
	142	[757]	SELF     	8 1 -28	; "paintBorder"
	143	[757]	MOVE     	10 7
	144	[757]	GETTABLE 	11 4 -10	; "dimen"
	145	[757]	GETTABLE 	11 11 -29	; "y"
	146	[757]	MOVE     	12 5
	147	[757]	MOVE     	13 6
	148	[757]	LOADK    	14 -7	; 1
	149	[757]	CALL     	8 7 1
	150	[757]	JMP      	21	; to 172
	151	[760]	LOADNIL  	7 7
	152	[761]	GETUPVAL 	8 2	; BD
	153	[761]	GETTABLE 	8 8 -9	; "mirroredUILayout"
	154	[761]	CALL     	8 1 2
	155	[761]	TEST     	8 0 0
	156	[761]	JMP      	7	; to 164
	157	[762]	GETTABLE 	8 4 -10	; "dimen"
	158	[762]	GETTABLE 	8 8 -27	; "x"
	159	[762]	GETTABLE 	9 4 -10	; "dimen"
	160	[762]	GETTABLE 	9 9 -11	; "w"
	161	[762]	ADD      	8 8 9
	162	[762]	SUB      	7 8 5
	163	[762]	JMP      	1	; to 165
	164	[764]	MOVE     	7 2
	165	[766]	SELF     	8 1 -28	; "paintBorder"
	166	[766]	MOVE     	10 7
	167	[766]	MOVE     	11 3
	168	[766]	MOVE     	12 5
	169	[766]	MOVE     	13 6
	170	[766]	LOADK    	14 -7	; 1
	171	[766]	CALL     	8 7 1
	172	[769]	RETURN   	0 1

function <./plugins/coverbrowser.koplugin/listmenu.lua:772,775> (7 instructions, 28 bytes at 0x7fdc3ec0afc0)
1 param, 3 slots, 1 upvalue, 1 local, 3 constants, 0 functions
	1	[773]	GETTABLE 	1 0 -1	; "_underline_container"
	2	[773]	GETUPVAL 	2 0	; Blitbuffer
	3	[773]	GETTABLE 	2 2 -3	; "COLOR_BLACK"
	4	[773]	SETTABLE 	1 -2 2	; "color" -
	5	[774]	LOADBOOL 	1 1 0
	6	[774]	RETURN   	1 2
	7	[775]	RETURN   	0 1

function <./plugins/coverbrowser.koplugin/listmenu.lua:777,780> (7 instructions, 28 bytes at 0x7fdc3ec0b280)
1 param, 3 slots, 1 upvalue, 1 local, 3 constants, 0 functions
	1	[778]	GETTABLE 	1 0 -1	; "_underline_container"
	2	[778]	GETUPVAL 	2 0	; Blitbuffer
	3	[778]	GETTABLE 	2 2 -3	; "COLOR_WHITE"
	4	[778]	SETTABLE 	1 -2 2	; "color" -
	5	[779]	LOADBOOL 	1 1 0
	6	[779]	RETURN   	1 2
	7	[780]	RETURN   	0 1

function <./plugins/coverbrowser.koplugin/listmenu.lua:782,785> (12 instructions, 48 bytes at 0x7fdc3ec0b340)
1 param, 7 slots, 2 upvalues, 1 local, 4 constants, 0 functions
	1	[783]	GETUPVAL 	1 0	; UIManager
	2	[783]	SELF     	1 1 -1	; "show"
	3	[783]	GETUPVAL 	3 1	; InfoMessage
	4	[783]	SELF     	3 3 -2	; "new"
	5	[783]	NEWTABLE 	5 0 1
	6	[783]	GETTABLE 	6 0 -4	; "detail"
	7	[783]	SETTABLE 	5 -3 6	; "text" -
	8	[783]	CALL     	3 3 0
	9	[783]	CALL     	1 0 1
	10	[784]	LOADBOOL 	1 1 0
	11	[784]	RETURN   	1 2
	12	[785]	RETURN   	0 1

function <./plugins/coverbrowser.koplugin/listmenu.lua:791,794> (7 instructions, 28 bytes at 0x7fdc3ec0b400)
2 params, 5 slots, 0 upvalues, 2 locals, 3 constants, 0 functions
	1	[792]	GETTABLE 	2 0 -1	; "menu"
	2	[792]	SELF     	2 2 -2	; "onMenuSelect"
	3	[792]	GETTABLE 	4 0 -3	; "entry"
	4	[792]	CALL     	2 3 1
	5	[793]	LOADBOOL 	2 1 0
	6	[793]	RETURN   	2 2
	7	[794]	RETURN   	0 1

function <./plugins/coverbrowser.koplugin/listmenu.lua:796,799> (7 instructions, 28 bytes at 0x7fdc3ec0bf50)
3 params, 6 slots, 0 upvalues, 3 locals, 3 constants, 0 functions
	1	[797]	GETTABLE 	3 0 -1	; "menu"
	2	[797]	SELF     	3 3 -2	; "onMenuHold"
	3	[797]	GETTABLE 	5 0 -3	; "entry"
	4	[797]	CALL     	3 3 1
	5	[798]	LOADBOOL 	3 1 0
	6	[798]	RETURN   	3 2
	7	[799]	RETURN   	0 1

function <./plugins/coverbrowser.koplugin/listmenu.lua:806,901> (220 instructions, 880 bytes at 0x7fdc3ec0c460)
1 param, 11 slots, 7 upvalues, 10 locals, 50 constants, 0 functions
	1	[807]	GETTABLE 	1 0 -1	; "dimen"
	2	[807]	GETTABLE 	2 0 -3	; "width"
	3	[807]	SETTABLE 	1 -2 2	; "w" -
	4	[808]	GETTABLE 	1 0 -1	; "dimen"
	5	[808]	GETTABLE 	2 0 -5	; "height"
	6	[808]	TEST     	2 0 1
	7	[808]	JMP      	3	; to 11
	8	[808]	GETUPVAL 	2 0	; Screen
	9	[808]	SELF     	2 2 -6	; "getHeight"
	10	[808]	CALL     	2 2 2
	11	[808]	SETTABLE 	1 -4 2	; "h" -
	12	[811]	SETTABLE 	0 -7 -8	; "others_height" 0
	13	[812]	GETTABLE 	1 0 -9	; "title_bar"
	14	[812]	TEST     	1 0 0
	15	[812]	JMP      	30	; to 46
	16	[813]	GETTABLE 	1 0 -10	; "is_borderless"
	17	[813]	TEST     	1 0 1
	18	[813]	JMP      	3	; to 22
	19	[814]	GETTABLE 	1 0 -7	; "others_height"
	20	[814]	ADD      	1 1 -11	; - 2
	21	[814]	SETTABLE 	0 -7 1	; "others_height" -
	22	[816]	GETTABLE 	1 0 -12	; "no_title"
	23	[816]	TEST     	1 0 1
	24	[816]	JMP      	10	; to 35
	25	[817]	GETTABLE 	1 0 -7	; "others_height"
	26	[817]	GETTABLE 	2 0 -13	; "header_padding"
	27	[817]	ADD      	1 1 2
	28	[817]	SETTABLE 	0 -7 1	; "others_height" -
	29	[818]	GETTABLE 	1 0 -7	; "others_height"
	30	[818]	GETTABLE 	2 0 -9	; "title_bar"
	31	[818]	GETTABLE 	2 2 -1	; "dimen"
	32	[818]	GETTABLE 	2 2 -4	; "h"
	33	[818]	ADD      	1 1 2
	34	[818]	SETTABLE 	0 -7 1	; "others_height" -
	35	[820]	GETTABLE 	1 0 -14	; "page_info"
	36	[820]	TEST     	1 0 0
	37	[820]	JMP      	15	; to 53
	38	[821]	GETTABLE 	1 0 -7	; "others_height"
	39	[821]	GETTABLE 	2 0 -14	; "page_info"
	40	[821]	SELF     	2 2 -15	; "getSize"
	41	[821]	CALL     	2 2 2
	42	[821]	GETTABLE 	2 2 -4	; "h"
	43	[821]	ADD      	1 1 2
	44	[821]	SETTABLE 	0 -7 1	; "others_height" -
	45	[822]	JMP      	7	; to 53
	46	[828]	SETTABLE 	0 -16 -17	; "page_recalc_needed_next_time" true
	47	[831]	GETTABLE 	1 0 -19	; "path_items"
	48	[831]	GETTABLE 	2 0 -20	; "path"
	49	[831]	GETTABLE 	1 1 2
	50	[831]	SETTABLE 	0 -18 1	; "itemnum_orig" -
	51	[832]	GETTABLE 	1 0 -22	; "focused_path"
	52	[832]	SETTABLE 	0 -21 1	; "focused_path_orig" -
	53	[834]	GETTABLE 	1 0 -1	; "dimen"
	54	[834]	GETTABLE 	1 1 -4	; "h"
	55	[834]	GETTABLE 	2 0 -7	; "others_height"
	56	[834]	SUB      	1 1 2
	57	[834]	GETUPVAL 	2 1	; Size
	58	[834]	GETTABLE 	2 2 -23	; "line"
	59	[834]	GETTABLE 	2 2 -24	; "thin"
	60	[834]	SUB      	1 1 2
	61	[839]	GETUPVAL 	2 2	; BookInfoManager
	62	[839]	SELF     	2 2 -25	; "getSetting"
	63	[839]	LOADK    	4 -26	; "files_per_page"
	64	[839]	CALL     	2 3 2
	65	[840]	TEST     	2 0 0
	66	[840]	JMP      	5	; to 72
	67	[841]	GETGLOBAL	3 -28	; tonumber
	68	[841]	MOVE     	4 2
	69	[841]	CALL     	3 2 2
	70	[841]	SETTABLE 	0 -27 3	; "perpage" -
	71	[841]	JMP      	14	; to 86
	72	[847]	GETGLOBAL	3 -29	; math
	73	[847]	GETTABLE 	3 3 -30	; "floor"
	74	[847]	GETUPVAL 	4 3	; scale_by_size
	75	[847]	DIV      	4 1 4
	76	[847]	DIV      	4 4 -31	; - 64
	77	[847]	CALL     	3 2 2
	78	[847]	SETTABLE 	0 -27 3	; "perpage" -
	79	[848]	GETUPVAL 	3 2	; BookInfoManager
	80	[848]	SELF     	3 3 -32	; "saveSetting"
	81	[848]	LOADK    	5 -26	; "files_per_page"
	82	[848]	GETGLOBAL	6 -33	; tostring
	83	[848]	GETTABLE 	7 0 -27	; "perpage"
	84	[848]	CALL     	6 2 0
	85	[848]	CALL     	3 0 1
	86	[850]	LOADK    	3 -35	; "s"
	87	[850]	GETTABLE 	4 0 -27	; "perpage"
	88	[850]	CONCAT   	3 3 4
	89	[850]	SETTABLE 	0 -34 3	; "cover_sizetag" -
	90	[851]	GETUPVAL 	3 0	; Screen
	91	[851]	SELF     	3 3 -36	; "getWidth"
	92	[851]	CALL     	3 2 2
	93	[851]	GETUPVAL 	4 0	; Screen
	94	[851]	SELF     	4 4 -6	; "getHeight"
	95	[851]	CALL     	4 2 2
	96	[851]	LT       	0 4 3
	97	[851]	JMP      	23	; to 121
	98	[857]	GETUPVAL 	3 0	; Screen
	99	[857]	SELF     	3 3 -36	; "getWidth"
	100	[857]	CALL     	3 2 2
	101	[857]	GETTABLE 	4 0 -7	; "others_height"
	102	[857]	SUB      	3 3 4
	103	[857]	GETUPVAL 	4 1	; Size
	104	[857]	GETTABLE 	4 4 -23	; "line"
	105	[857]	GETTABLE 	4 4 -24	; "thin"
	106	[857]	SUB      	3 3 4
	107	[858]	GETGLOBAL	4 -29	; math
	108	[858]	GETTABLE 	4 4 -30	; "floor"
	109	[858]	GETTABLE 	5 0 -27	; "perpage"
	110	[858]	DIV      	5 3 5
	111	[858]	CALL     	4 2 2
	112	[858]	GETUPVAL 	5 1	; Size
	113	[858]	GETTABLE 	5 5 -23	; "line"
	114	[858]	GETTABLE 	5 5 -24	; "thin"
	115	[858]	SUB      	4 4 5
	116	[859]	GETUPVAL 	5 4	; Math
	117	[859]	GETTABLE 	5 5 -37	; "round"
	118	[859]	DIV      	6 1 4
	119	[859]	CALL     	5 2 2
	120	[859]	SETTABLE 	0 -27 5	; "perpage" -
	121	[862]	GETGLOBAL	3 -29	; math
	122	[862]	GETTABLE 	3 3 -39	; "ceil"
	123	[862]	GETTABLE 	4 0 -40	; "item_table"
	124	[862]	LEN      	4 4
	125	[862]	GETTABLE 	5 0 -27	; "perpage"
	126	[862]	DIV      	4 4 5
	127	[862]	CALL     	3 2 2
	128	[862]	SETTABLE 	0 -38 3	; "page_num" -
	129	[864]	GETTABLE 	3 0 -38	; "page_num"
	130	[864]	LT       	0 -8 3	; 0 -
	131	[864]	JMP      	6	; to 138
	132	[864]	GETTABLE 	3 0 -41	; "page"
	133	[864]	GETTABLE 	4 0 -38	; "page_num"
	134	[864]	LT       	0 4 3
	135	[864]	JMP      	2	; to 138
	136	[864]	GETTABLE 	3 0 -38	; "page_num"
	137	[864]	SETTABLE 	0 -41 3	; "page" -
	138	[868]	GETGLOBAL	3 -29	; math
	139	[868]	GETTABLE 	3 3 -30	; "floor"
	140	[868]	GETTABLE 	4 0 -27	; "perpage"
	141	[868]	DIV      	4 1 4
	142	[868]	CALL     	3 2 2
	143	[868]	GETUPVAL 	4 1	; Size
	144	[868]	GETTABLE 	4 4 -23	; "line"
	145	[868]	GETTABLE 	4 4 -24	; "thin"
	146	[868]	SUB      	3 3 4
	147	[868]	SETTABLE 	0 -42 3	; "item_height" -
	148	[869]	GETTABLE 	3 0 -1	; "dimen"
	149	[869]	GETTABLE 	3 3 -2	; "w"
	150	[869]	SETTABLE 	0 -43 3	; "item_width" -
	151	[870]	GETUPVAL 	3 5	; Geom
	152	[870]	SELF     	3 3 -45	; "new"
	153	[870]	NEWTABLE 	5 0 2
	154	[871]	GETTABLE 	6 0 -43	; "item_width"
	155	[871]	SETTABLE 	5 -2 6	; "w" -
	156	[872]	GETTABLE 	6 0 -42	; "item_height"
	157	[872]	SETTABLE 	5 -4 6	; "h" -
	158	[870]	CALL     	3 3 2
	159	[873]	SETTABLE 	0 -44 3	; "item_dimen" -
	160	[876]	GETUPVAL 	3 3	; scale_by_size
	161	[876]	DIV      	3 1 3
	162	[876]	DIV      	3 3 -46	; - 32
	163	[876]	SETUPVAL 	3 6	; max_fontsize_fileinfo
	164	[878]	GETTABLE 	3 0 -47	; "page_recalc_needed"
	165	[878]	TEST     	3 0 0
	166	[878]	JMP      	48	; to 215
	167	[881]	GETTABLE 	3 0 -40	; "item_table"
	168	[881]	LEN      	3 3
	169	[881]	LT       	0 -8 3	; 0 -
	170	[881]	JMP      	10	; to 181
	171	[882]	GETGLOBAL	3 -29	; math
	172	[882]	GETTABLE 	3 3 -39	; "ceil"
	173	[882]	GETTABLE 	4 0 -18	; "itemnum_orig"
	174	[882]	TEST     	4 0 1
	175	[882]	JMP      	1	; to 177
	176	[882]	LOADK    	4 -48	; 1
	177	[882]	GETTABLE 	5 0 -27	; "perpage"
	178	[882]	DIV      	4 4 5
	179	[882]	CALL     	3 2 2
	180	[882]	SETTABLE 	0 -41 3	; "page" -
	181	[884]	GETTABLE 	3 0 -21	; "focused_path_orig"
	182	[884]	TEST     	3 0 0
	183	[884]	JMP      	19	; to 203
	184	[885]	GETGLOBAL	3 -49	; ipairs
	185	[885]	GETTABLE 	4 0 -40	; "item_table"
	186	[885]	CALL     	3 2 4
	187	[885]	JMP      	13	; to 201
	188	[886]	GETTABLE 	8 7 -20	; "path"
	189	[886]	GETTABLE 	9 0 -21	; "focused_path_orig"
	190	[886]	EQ       	0 8 9
	191	[886]	JMP      	9	; to 201
	192	[887]	GETGLOBAL	8 -29	; math
	193	[887]	GETTABLE 	8 8 -30	; "floor"
	194	[887]	SUB      	9 6 -48	; - 1
	195	[887]	GETTABLE 	10 0 -27	; "perpage"
	196	[887]	DIV      	9 9 10
	197	[887]	CALL     	8 2 2
	198	[887]	ADD      	8 8 -48	; - 1
	199	[887]	SETTABLE 	0 -41 8	; "page" -
	200	[888]	JMP      	2	; to 203
	201	[885]	TFORLOOP 	3 2
	202	[889]	JMP      	-15	; to 188
	203	[892]	GETTABLE 	3 0 -38	; "page_num"
	204	[892]	LT       	0 -8 3	; 0 -
	205	[892]	JMP      	6	; to 212
	206	[892]	GETTABLE 	3 0 -41	; "page"
	207	[892]	GETTABLE 	4 0 -38	; "page_num"
	208	[892]	LT       	0 4 3
	209	[892]	JMP      	2	; to 212
	210	[892]	GETTABLE 	3 0 -38	; "page_num"
	211	[892]	SETTABLE 	0 -41 3	; "page" -
	212	[893]	SETTABLE 	0 -47 -50	; "page_recalc_needed" nil
	213	[894]	SETTABLE 	0 -18 -50	; "itemnum_orig" nil
	214	[895]	SETTABLE 	0 -21 -50	; "focused_path_orig" nil
	215	[897]	GETTABLE 	3 0 -16	; "page_recalc_needed_next_time"
	216	[897]	TEST     	3 0 0
	217	[897]	JMP      	2	; to 220
	218	[898]	SETTABLE 	0 -47 -17	; "page_recalc_needed" true
	219	[899]	SETTABLE 	0 -16 -50	; "page_recalc_needed_next_time" nil
	220	[901]	RETURN   	0 1

function <./plugins/coverbrowser.koplugin/listmenu.lua:903,958> (130 instructions, 520 bytes at 0x7fdc3ec0ca40)
1 param, 19 slots, 6 upvalues, 10 locals, 47 constants, 0 functions
	1	[905]	GETGLOBAL	1 -1	; table
	2	[905]	GETTABLE 	1 1 -2	; "insert"
	3	[905]	GETTABLE 	2 0 -3	; "item_group"
	4	[905]	GETUPVAL 	3 0	; LineWidget
	5	[905]	SELF     	3 3 -4	; "new"
	6	[905]	NEWTABLE 	5 0 3
	7	[906]	GETUPVAL 	6 1	; Geom
	8	[906]	SELF     	6 6 -4	; "new"
	9	[906]	NEWTABLE 	8 0 2
	10	[906]	GETTABLE 	9 0 -7	; "width"
	11	[906]	SETTABLE 	8 -6 9	; "w" -
	12	[906]	GETUPVAL 	9 2	; Size
	13	[906]	GETTABLE 	9 9 -9	; "line"
	14	[906]	GETTABLE 	9 9 -10	; "thin"
	15	[906]	SETTABLE 	8 -8 9	; "h" -
	16	[906]	CALL     	6 3 2
	17	[906]	SETTABLE 	5 -5 6	; "dimen" -
	18	[907]	GETUPVAL 	6 3	; Blitbuffer
	19	[907]	GETTABLE 	6 6 -12	; "COLOR_DARK_GRAY"
	20	[907]	SETTABLE 	5 -11 6	; "background" -
	21	[908]	SETTABLE 	5 -13 -14	; "style" "solid"
	22	[905]	CALL     	3 3 0
	23	[905]	CALL     	1 0 1
	24	[910]	GETTABLE 	1 0 -15	; "page"
	25	[910]	SUB      	1 1 -16	; - 1
	26	[910]	GETTABLE 	2 0 -17	; "perpage"
	27	[910]	MUL      	1 1 2
	28	[911]	LOADK    	2 -16	; 1
	29	[911]	GETTABLE 	3 0 -17	; "perpage"
	30	[911]	LOADK    	4 -16	; 1
	31	[911]	FORPREP  	2 97	; to 129
	32	[912]	GETTABLE 	6 0 -18	; "item_table"
	33	[912]	ADD      	7 1 5
	34	[912]	GETTABLE 	6 6 7
	35	[913]	EQ       	0 6 -19	; - nil
	36	[913]	JMP      	1	; to 38
	37	[913]	JMP      	92	; to 130
	38	[916]	LOADNIL  	7 7
	39	[917]	LOADK    	8 -20	; "square"
	40	[918]	GETTABLE 	9 0 -21	; "is_enable_shortcut"
	41	[918]	TEST     	9 0 0
	42	[918]	JMP      	7	; to 50
	43	[921]	LE       	0 -22 5	; 11 -
	44	[921]	JMP      	3	; to 48
	45	[921]	LE       	0 5 -23	; - 20
	46	[921]	JMP      	1	; to 48
	47	[922]	LOADK    	8 -24	; "grey_square"
	48	[924]	GETTABLE 	9 0 -25	; "item_shortcuts"
	49	[924]	GETTABLE 	7 9 5
	50	[927]	GETUPVAL 	9 4	; ListMenuItem
	51	[927]	SELF     	9 9 -4	; "new"
	52	[927]	NEWTABLE 	11 0 13
	53	[928]	GETTABLE 	12 0 -27	; "item_height"
	54	[928]	SETTABLE 	11 -26 12	; "height" -
	55	[929]	GETTABLE 	12 0 -28	; "item_width"
	56	[929]	SETTABLE 	11 -7 12	; "width" -
	57	[930]	SETTABLE 	11 -29 6	; "entry" -
	58	[931]	GETUPVAL 	12 5	; getMenuText
	59	[931]	MOVE     	13 6
	60	[931]	CALL     	12 2 2
	61	[931]	SETTABLE 	11 -30 12	; "text" -
	62	[932]	GETTABLE 	12 0 -31	; "show_parent"
	63	[932]	SETTABLE 	11 -31 12	; "show_parent" -
	64	[933]	GETTABLE 	12 6 -32	; "mandatory"
	65	[933]	SETTABLE 	11 -32 12	; "mandatory" -
	66	[934]	GETTABLE 	12 0 -33	; "item_dimen"
	67	[934]	SELF     	12 12 -4	; "new"
	68	[934]	CALL     	12 2 2
	69	[934]	SETTABLE 	11 -5 12	; "dimen" -
	70	[935]	SETTABLE 	11 -34 7	; "shortcut" -
	71	[936]	SETTABLE 	11 -35 8	; "shortcut_style" -
	72	[937]	SETTABLE 	11 -36 0	; "menu" -
	73	[938]	GETTABLE 	12 0 -38	; "_do_cover_images"
	74	[938]	SETTABLE 	11 -37 12	; "do_cover_image" -
	75	[939]	GETTABLE 	12 0 -40	; "_do_hint_opened"
	76	[939]	SETTABLE 	11 -39 12	; "do_hint_opened" -
	77	[940]	GETTABLE 	12 0 -42	; "_do_filename_only"
	78	[940]	SETTABLE 	11 -41 12	; "do_filename_only" -
	79	[927]	CALL     	9 3 2
	80	[942]	GETGLOBAL	10 -1	; table
	81	[942]	GETTABLE 	10 10 -2	; "insert"
	82	[942]	GETTABLE 	11 0 -3	; "item_group"
	83	[942]	MOVE     	12 9
	84	[942]	CALL     	10 3 1
	85	[943]	GETGLOBAL	10 -1	; table
	86	[943]	GETTABLE 	10 10 -2	; "insert"
	87	[943]	GETTABLE 	11 0 -3	; "item_group"
	88	[943]	GETUPVAL 	12 0	; LineWidget
	89	[943]	SELF     	12 12 -4	; "new"
	90	[943]	NEWTABLE 	14 0 3
	91	[944]	GETUPVAL 	15 1	; Geom
	92	[944]	SELF     	15 15 -4	; "new"
	93	[944]	NEWTABLE 	17 0 2
	94	[944]	GETTABLE 	18 0 -7	; "width"
	95	[944]	SETTABLE 	17 -6 18	; "w" -
	96	[944]	GETUPVAL 	18 2	; Size
	97	[944]	GETTABLE 	18 18 -9	; "line"
	98	[944]	GETTABLE 	18 18 -10	; "thin"
	99	[944]	SETTABLE 	17 -8 18	; "h" -
	100	[944]	CALL     	15 3 2
	101	[944]	SETTABLE 	14 -5 15	; "dimen" -
	102	[945]	GETUPVAL 	15 3	; Blitbuffer
	103	[945]	GETTABLE 	15 15 -12	; "COLOR_DARK_GRAY"
	104	[945]	SETTABLE 	14 -11 15	; "background" -
	105	[946]	SETTABLE 	14 -13 -14	; "style" "solid"
	106	[943]	CALL     	12 3 0
	107	[943]	CALL     	10 0 1
	108	[950]	GETGLOBAL	10 -1	; table
	109	[950]	GETTABLE 	10 10 -2	; "insert"
	110	[950]	GETTABLE 	11 0 -43	; "layout"
	111	[950]	NEWTABLE 	12 1 0
	112	[950]	MOVE     	13 9
	113	[950]	SETLIST  	12 1 1	; 1
	114	[950]	CALL     	10 3 1
	115	[952]	GETTABLE 	10 9 -44	; "bookinfo_found"
	116	[952]	TEST     	10 0 1
	117	[952]	JMP      	11	; to 129
	118	[952]	GETTABLE 	10 9 -45	; "is_directory"
	119	[952]	TEST     	10 0 1
	120	[952]	JMP      	8	; to 129
	121	[952]	GETTABLE 	10 9 -46	; "file_deleted"
	122	[952]	TEST     	10 0 1
	123	[952]	JMP      	5	; to 129
	124	[954]	GETGLOBAL	10 -1	; table
	125	[954]	GETTABLE 	10 10 -2	; "insert"
	126	[954]	GETTABLE 	11 0 -47	; "items_to_update"
	127	[954]	MOVE     	12 9
	128	[954]	CALL     	10 3 1
	129	[911]	FORLOOP  	2 -98	; to 32
	130	[958]	RETURN   	0 1
