
main <./platform/android/llapp_main.lua:0,0> (76 instructions, 304 bytes at 0x7fe4bb4068d0)
0+ params, 10 slots, 0 upvalues, 6 locals, 31 constants, 0 functions
	1	[1]	GETGLOBAL	0 -1	; require
	2	[1]	LOADK    	1 -2	; "android"
	3	[1]	CALL     	0 2 2
	4	[2]	GETTABLE 	1 0 -3	; "dl"
	5	[2]	GETTABLE 	2 0 -3	; "dl"
	6	[2]	GETTABLE 	2 2 -4	; "library_path"
	7	[2]	LOADK    	3 -5	; ":"
	8	[2]	GETTABLE 	4 0 -6	; "dir"
	9	[2]	LOADK    	5 -7	; "/libs"
	10	[2]	CONCAT   	2 2 5
	11	[2]	SETTABLE 	1 -4 2	; "library_path" -
	12	[4]	GETGLOBAL	1 -1	; require
	13	[4]	LOADK    	2 -8	; "ffi"
	14	[4]	CALL     	1 2 2
	15	[5]	GETGLOBAL	2 -1	; require
	16	[5]	LOADK    	3 -9	; "ffi/posix_h"
	17	[5]	CALL     	2 2 2
	18	[6]	GETTABLE 	3 1 -10	; "C"
	19	[9]	GETTABLE 	4 0 -11	; "getIntent"
	20	[9]	CALL     	4 1 2
	21	[11]	EQ       	1 4 -12	; - nil
	22	[11]	JMP      	5	; to 28
	23	[12]	GETTABLE 	5 0 -13	; "LOGI"
	24	[12]	LOADK    	6 -14	; "intent file path "
	25	[12]	MOVE     	7 4
	26	[12]	CONCAT   	6 6 7
	27	[12]	CALL     	5 2 1
	28	[16]	GETTABLE 	5 0 -15	; "getExternalStoragePath"
	29	[16]	CALL     	5 1 2
	30	[19]	GETGLOBAL	6 -16	; pcall
	31	[19]	GETGLOBAL	7 -17	; dofile
	32	[19]	MOVE     	8 5
	33	[19]	LOADK    	9 -18	; "/koreader/patch.lua"
	34	[19]	CONCAT   	8 8 9
	35	[19]	CALL     	6 3 1
	36	[24]	GETTABLE 	6 0 -19	; "execute"
	37	[24]	LOADK    	7 -20	; "chmod"
	38	[24]	LOADK    	8 -21	; "755"
	39	[24]	LOADK    	9 -22	; "./sdcv"
	40	[24]	CALL     	6 4 1
	41	[25]	GETTABLE 	6 0 -19	; "execute"
	42	[25]	LOADK    	7 -20	; "chmod"
	43	[25]	LOADK    	8 -21	; "755"
	44	[25]	LOADK    	9 -23	; "./tar"
	45	[25]	CALL     	6 4 1
	46	[28]	GETTABLE 	6 3 -24	; "setenv"
	47	[28]	LOADK    	7 -25	; "TESSDATA_PREFIX"
	48	[28]	MOVE     	8 5
	49	[28]	LOADK    	9 -26	; "/koreader/data"
	50	[28]	CONCAT   	8 8 9
	51	[28]	LOADK    	9 -27	; 1
	52	[28]	CALL     	6 4 1
	53	[32]	GETTABLE 	6 0 -28	; "isDebuggable"
	54	[32]	CALL     	6 1 2
	55	[32]	TEST     	6 0 0
	56	[32]	JMP      	8	; to 65
	57	[33]	NEWTABLE 	6 2 0
	58	[33]	LOADK    	7 -30	; "-d"
	59	[33]	TESTSET  	8 4 1
	60	[33]	JMP      	1	; to 62
	61	[33]	MOVE     	8 5
	62	[33]	SETLIST  	6 2 1	; 1
	63	[33]	SETGLOBAL	6 -29	; arg
	64	[33]	JMP      	6	; to 71
	65	[35]	NEWTABLE 	6 1 0
	66	[35]	TESTSET  	7 4 1
	67	[35]	JMP      	1	; to 69
	68	[35]	MOVE     	7 5
	69	[35]	SETLIST  	6 1 1	; 1
	70	[35]	SETGLOBAL	6 -29	; arg
	71	[38]	GETGLOBAL	6 -17	; dofile
	72	[38]	GETTABLE 	7 0 -6	; "dir"
	73	[38]	LOADK    	8 -31	; "/reader.lua"
	74	[38]	CONCAT   	7 7 8
	75	[38]	CALL     	6 2 1
	76	[38]	RETURN   	0 1
