-- BYTECODE -- llapp_main.lua:0-39
0001    GGET     0   0      ; "require"
0002    KSTR     1   1      ; "android"
0003    CALL     0   2   2
0004    TGETS    1   0   2  ; "dl"
0005    TGETS    2   0   2  ; "dl"
0006    TGETS    2   2   3  ; "library_path"
0007    KSTR     3   4      ; ":"
0008    TGETS    4   0   5  ; "dir"
0009    KSTR     5   6      ; "/libs"
0010    CAT      2   2   5
0011    TSETS    2   1   3  ; "library_path"
0012    GGET     1   0      ; "require"
0013    KSTR     2   7      ; "ffi"
0014    CALL     1   2   2
0015    GGET     2   0      ; "require"
0016    KSTR     3   8      ; "ffi/posix_h"
0017    CALL     2   2   2
0018    TGETS    3   1   9  ; "C"
0019    TGETS    4   0  10  ; "getIntent"
0020    CALL     4   2   1
0021    ISEQP    4   0
0022    JMP      5 => 0028
0023    TGETS    5   0  11  ; "LOGI"
0024    KSTR     6  12      ; "intent file path "
0025    MOV      7   4
0026    CAT      6   6   7
0027    CALL     5   1   2
0028 => TGETS    5   0  13  ; "getExternalStoragePath"
0029    CALL     5   2   1
0030    GGET     6  14      ; "pcall"
0031    GGET     7  15      ; "dofile"
0032    MOV      8   5
0033    KSTR     9  16      ; "/koreader/patch.lua"
0034    CAT      8   8   9
0035    CALL     6   1   3
0036    TGETS    6   0  17  ; "execute"
0037    KSTR     7  18      ; "chmod"
0038    KSTR     8  19      ; "755"
0039    KSTR     9  20      ; "./sdcv"
0040    CALL     6   1   4
0041    TGETS    6   0  17  ; "execute"
0042    KSTR     7  18      ; "chmod"
0043    KSTR     8  19      ; "755"
0044    KSTR     9  21      ; "./tar"
0045    CALL     6   1   4
0046    TGETS    6   3  22  ; "setenv"
0047    KSTR     7  23      ; "TESSDATA_PREFIX"
0048    MOV      8   5
0049    KSTR     9  24      ; "/koreader/data"
0050    CAT      8   8   9
0051    KSHORT   9   1
0052    CALL     6   1   4
0053    TGETS    6   0  25  ; "isDebuggable"
0054    CALL     6   2   1
0055    ISF          6
0056    JMP      7 => 0064
0057    TDUP     6  26
0058    ISTC     7   4
0059    JMP      7 => 0061
0060    MOV      7   5
0061 => TSETB    7   6   2
0062    GSET     6  27      ; "arg"
0063    JMP      6 => 0070
0064 => TNEW     6   3
0065    ISTC     7   4
0066    JMP      7 => 0068
0067    MOV      7   5
0068 => TSETB    7   6   1
0069    GSET     6  27      ; "arg"
0070 => GGET     6  15      ; "dofile"
0071    TGETS    7   0   5  ; "dir"
0072    KSTR     8  28      ; "/reader.lua"
0073    CAT      7   7   8
0074    CALL     6   1   2
0075    RET0     0   1

