
main <./frontend/ui/widget/logindialog.lua:0,0> (59 instructions, 236 bytes at 0x7ff6b44068d0)
0+ params, 14 slots, 0 upvalues, 12 locals, 22 constants, 3 functions
	1	[5]	GETGLOBAL	0 -1	; require
	2	[5]	LOADK    	1 -2	; "ffi/blitbuffer"
	3	[5]	CALL     	0 2 2
	4	[6]	GETGLOBAL	1 -1	; require
	5	[6]	LOADK    	2 -3	; "ui/widget/container/centercontainer"
	6	[6]	CALL     	1 2 2
	7	[7]	GETGLOBAL	2 -1	; require
	8	[7]	LOADK    	3 -4	; "ui/widget/container/framecontainer"
	9	[7]	CALL     	2 2 2
	10	[8]	GETGLOBAL	3 -1	; require
	11	[8]	LOADK    	4 -5	; "ui/geometry"
	12	[8]	CALL     	3 2 2
	13	[9]	GETGLOBAL	4 -1	; require
	14	[9]	LOADK    	5 -6	; "ui/widget/inputdialog"
	15	[9]	CALL     	4 2 2
	16	[10]	GETGLOBAL	5 -1	; require
	17	[10]	LOADK    	6 -7	; "ui/widget/inputtext"
	18	[10]	CALL     	5 2 2
	19	[11]	GETGLOBAL	6 -1	; require
	20	[11]	LOADK    	7 -8	; "ui/size"
	21	[11]	CALL     	6 2 2
	22	[12]	GETGLOBAL	7 -1	; require
	23	[12]	LOADK    	8 -9	; "ui/uimanager"
	24	[12]	CALL     	7 2 2
	25	[13]	GETGLOBAL	8 -1	; require
	26	[13]	LOADK    	9 -10	; "ui/widget/verticalgroup"
	27	[13]	CALL     	8 2 2
	28	[14]	GETGLOBAL	9 -1	; require
	29	[14]	LOADK    	10 -11	; "gettext"
	30	[14]	CALL     	9 2 2
	31	[15]	GETGLOBAL	10 -1	; require
	32	[15]	LOADK    	11 -12	; "device"
	33	[15]	CALL     	10 2 2
	34	[15]	GETTABLE 	10 10 -13	; "screen"
	35	[17]	SELF     	11 4 -14	; "extend"
	36	[17]	NEWTABLE 	13 0 4
	37	[18]	SETTABLE 	13 -15 -16	; "username" ""
	38	[19]	SETTABLE 	13 -17 -15	; "username_hint" "username"
	39	[20]	SETTABLE 	13 -18 -16	; "password" ""
	40	[21]	SETTABLE 	13 -19 -18	; "password_hint" "password"
	41	[17]	CALL     	11 3 2
	42	[93]	CLOSURE  	12 0	; 0x7ff6b44070c0
	43	[93]	MOVE     	0 4
	44	[93]	MOVE     	0 5
	45	[93]	MOVE     	0 2
	46	[93]	MOVE     	0 6
	47	[93]	MOVE     	0 0
	48	[93]	MOVE     	0 8
	49	[93]	MOVE     	0 1
	50	[93]	MOVE     	0 3
	51	[93]	MOVE     	0 10
	52	[24]	SETTABLE 	11 -20 12	; "init" -
	53	[99]	CLOSURE  	12 1	; 0x7ff6b4407980
	54	[95]	SETTABLE 	11 -21 12	; "getCredential" -
	55	[110]	CLOSURE  	12 2	; 0x7ff6b4407b80
	56	[110]	MOVE     	0 7
	57	[101]	SETTABLE 	11 -22 12	; "onSwitchFocus" -
	58	[112]	RETURN   	11 2
	59	[112]	RETURN   	0 1

function <./frontend/ui/widget/logindialog.lua:24,93> (153 instructions, 612 bytes at 0x7ff6b44070c0)
1 param, 19 slots, 9 upvalues, 1 local, 42 constants, 0 functions
	1	[26]	GETUPVAL 	1 0	; InputDialog
	2	[26]	GETTABLE 	1 1 -1	; "init"
	3	[26]	MOVE     	2 0
	4	[26]	CALL     	1 2 1
	5	[27]	GETUPVAL 	1 1	; InputText
	6	[27]	SELF     	1 1 -3	; "new"
	7	[27]	NEWTABLE 	3 0 7
	8	[28]	GETTABLE 	4 0 -5	; "username"
	9	[28]	SETTABLE 	3 -4 4	; "text" -
	10	[29]	GETTABLE 	4 0 -7	; "username_hint"
	11	[29]	SETTABLE 	3 -6 4	; "hint" -
	12	[30]	GETTABLE 	4 0 -9	; "input_face"
	13	[30]	SETTABLE 	3 -8 4	; "face" -
	14	[31]	GETTABLE 	4 0 -10	; "width"
	15	[31]	MUL      	4 4 -11	; - 0.9
	16	[31]	SETTABLE 	3 -10 4	; "width" -
	17	[32]	SETTABLE 	3 -12 -13	; "focused" true
	18	[33]	SETTABLE 	3 -14 -15	; "scroll" false
	19	[34]	SETTABLE 	3 -16 0	; "parent" -
	20	[27]	CALL     	1 3 2
	21	[35]	SETTABLE 	0 -2 1	; "input_username" -
	22	[37]	GETUPVAL 	1 1	; InputText
	23	[37]	SELF     	1 1 -3	; "new"
	24	[37]	NEWTABLE 	3 0 8
	25	[38]	GETTABLE 	4 0 -18	; "password"
	26	[38]	SETTABLE 	3 -4 4	; "text" -
	27	[39]	GETTABLE 	4 0 -19	; "password_hint"
	28	[39]	SETTABLE 	3 -6 4	; "hint" -
	29	[40]	GETTABLE 	4 0 -9	; "input_face"
	30	[40]	SETTABLE 	3 -8 4	; "face" -
	31	[41]	GETTABLE 	4 0 -10	; "width"
	32	[41]	MUL      	4 4 -11	; - 0.9
	33	[41]	SETTABLE 	3 -10 4	; "width" -
	34	[42]	SETTABLE 	3 -20 -18	; "text_type" "password"
	35	[43]	SETTABLE 	3 -12 -15	; "focused" false
	36	[44]	SETTABLE 	3 -14 -15	; "scroll" false
	37	[45]	SETTABLE 	3 -16 0	; "parent" -
	38	[37]	CALL     	1 3 2
	39	[46]	SETTABLE 	0 -17 1	; "input_password" -
	40	[48]	GETUPVAL 	1 2	; FrameContainer
	41	[48]	SELF     	1 1 -3	; "new"
	42	[48]	NEWTABLE 	3 0 4
	43	[49]	GETUPVAL 	4 3	; Size
	44	[49]	GETTABLE 	4 4 -22	; "radius"
	45	[49]	GETTABLE 	4 4 -23	; "window"
	46	[49]	SETTABLE 	3 -22 4	; "radius" -
	47	[50]	SETTABLE 	3 -24 -25	; "padding" 0
	48	[51]	SETTABLE 	3 -26 -25	; "margin" 0
	49	[52]	GETUPVAL 	4 4	; Blitbuffer
	50	[52]	GETTABLE 	4 4 -28	; "COLOR_WHITE"
	51	[52]	SETTABLE 	3 -27 4	; "background" -
	52	[53]	GETUPVAL 	4 5	; VerticalGroup
	53	[53]	SELF     	4 4 -3	; "new"
	54	[53]	NEWTABLE 	6 4 1
	55	[54]	SETTABLE 	6 -29 -30	; "align" "left"
	56	[55]	GETTABLE 	7 0 -31	; "title_widget"
	57	[56]	GETTABLE 	8 0 -32	; "title_bar"
	58	[58]	GETUPVAL 	9 6	; CenterContainer
	59	[58]	SELF     	9 9 -3	; "new"
	60	[58]	NEWTABLE 	11 1 1
	61	[59]	GETUPVAL 	12 7	; Geom
	62	[59]	SELF     	12 12 -3	; "new"
	63	[59]	NEWTABLE 	14 0 2
	64	[60]	GETTABLE 	15 0 -32	; "title_bar"
	65	[60]	SELF     	15 15 -35	; "getSize"
	66	[60]	CALL     	15 2 2
	67	[60]	GETTABLE 	15 15 -34	; "w"
	68	[60]	SETTABLE 	14 -34 15	; "w" -
	69	[61]	GETTABLE 	15 0 -2	; "input_username"
	70	[61]	SELF     	15 15 -35	; "getSize"
	71	[61]	CALL     	15 2 2
	72	[61]	GETTABLE 	15 15 -36	; "h"
	73	[61]	SETTABLE 	14 -36 15	; "h" -
	74	[59]	CALL     	12 3 2
	75	[62]	SETTABLE 	11 -33 12	; "dimen" -
	76	[64]	GETTABLE 	12 0 -2	; "input_username"
	77	[64]	SETLIST  	11 1 1	; 1
	78	[58]	CALL     	9 3 2
	79	[66]	GETUPVAL 	10 6	; CenterContainer
	80	[66]	SELF     	10 10 -3	; "new"
	81	[66]	NEWTABLE 	12 1 1
	82	[67]	GETUPVAL 	13 7	; Geom
	83	[67]	SELF     	13 13 -3	; "new"
	84	[67]	NEWTABLE 	15 0 2
	85	[68]	GETTABLE 	16 0 -32	; "title_bar"
	86	[68]	SELF     	16 16 -35	; "getSize"
	87	[68]	CALL     	16 2 2
	88	[68]	GETTABLE 	16 16 -34	; "w"
	89	[68]	SETTABLE 	15 -34 16	; "w" -
	90	[69]	GETTABLE 	16 0 -17	; "input_password"
	91	[69]	SELF     	16 16 -35	; "getSize"
	92	[69]	CALL     	16 2 2
	93	[69]	GETTABLE 	16 16 -36	; "h"
	94	[69]	SETTABLE 	15 -36 16	; "h" -
	95	[67]	CALL     	13 3 2
	96	[70]	SETTABLE 	12 -33 13	; "dimen" -
	97	[72]	GETTABLE 	13 0 -17	; "input_password"
	98	[72]	SETLIST  	12 1 1	; 1
	99	[66]	CALL     	10 3 2
	100	[74]	GETUPVAL 	11 6	; CenterContainer
	101	[74]	SELF     	11 11 -3	; "new"
	102	[74]	NEWTABLE 	13 1 1
	103	[75]	GETUPVAL 	14 7	; Geom
	104	[75]	SELF     	14 14 -3	; "new"
	105	[75]	NEWTABLE 	16 0 2
	106	[76]	GETTABLE 	17 0 -32	; "title_bar"
	107	[76]	SELF     	17 17 -35	; "getSize"
	108	[76]	CALL     	17 2 2
	109	[76]	GETTABLE 	17 17 -34	; "w"
	110	[76]	SETTABLE 	16 -34 17	; "w" -
	111	[77]	GETTABLE 	17 0 -37	; "button_table"
	112	[77]	SELF     	17 17 -35	; "getSize"
	113	[77]	CALL     	17 2 2
	114	[77]	GETTABLE 	17 17 -36	; "h"
	115	[77]	SETTABLE 	16 -36 17	; "h" -
	116	[75]	CALL     	14 3 2
	117	[78]	SETTABLE 	13 -33 14	; "dimen" -
	118	[80]	GETTABLE 	14 0 -37	; "button_table"
	119	[80]	SETLIST  	13 1 1	; 1
	120	[74]	CALL     	11 3 0
	121	[81]	SETLIST  	6 0 1	; 1
	122	[53]	CALL     	4 3 0
	123	[82]	SETLIST  	3 0 1	; 1
	124	[48]	CALL     	1 3 2
	125	[82]	SETTABLE 	0 -21 1	; "dialog_frame" -
	126	[84]	GETTABLE 	1 0 -2	; "input_username"
	127	[84]	SETTABLE 	0 -38 1	; "_input_widget" -
	128	[86]	GETUPVAL 	1 6	; CenterContainer
	129	[86]	SELF     	1 1 -3	; "new"
	130	[86]	NEWTABLE 	3 1 1
	131	[87]	GETUPVAL 	4 7	; Geom
	132	[87]	SELF     	4 4 -3	; "new"
	133	[87]	NEWTABLE 	6 0 2
	134	[88]	GETUPVAL 	7 8	; Screen
	135	[88]	SELF     	7 7 -40	; "getWidth"
	136	[88]	CALL     	7 2 2
	137	[88]	SETTABLE 	6 -34 7	; "w" -
	138	[89]	GETUPVAL 	7 8	; Screen
	139	[89]	SELF     	7 7 -41	; "getHeight"
	140	[89]	CALL     	7 2 2
	141	[89]	GETTABLE 	8 0 -38	; "_input_widget"
	142	[89]	SELF     	8 8 -42	; "getKeyboardDimen"
	143	[89]	CALL     	8 2 2
	144	[89]	GETTABLE 	8 8 -36	; "h"
	145	[89]	SUB      	7 7 8
	146	[89]	SETTABLE 	6 -36 7	; "h" -
	147	[87]	CALL     	4 3 2
	148	[90]	SETTABLE 	3 -33 4	; "dimen" -
	149	[92]	GETTABLE 	4 0 -21	; "dialog_frame"
	150	[92]	SETLIST  	3 1 1	; 1
	151	[86]	CALL     	1 3 2
	152	[92]	SETTABLE 	0 -39 1	; 1 -
	153	[93]	RETURN   	0 1

function <./frontend/ui/widget/logindialog.lua:95,99> (10 instructions, 40 bytes at 0x7ff6b4407980)
1 param, 5 slots, 0 upvalues, 3 locals, 3 constants, 0 functions
	1	[96]	GETTABLE 	1 0 -1	; "input_username"
	2	[96]	SELF     	1 1 -2	; "getText"
	3	[96]	CALL     	1 2 2
	4	[97]	GETTABLE 	2 0 -3	; "input_password"
	5	[97]	SELF     	2 2 -2	; "getText"
	6	[97]	CALL     	2 2 2
	7	[98]	MOVE     	3 1
	8	[98]	MOVE     	4 2
	9	[98]	RETURN   	3 3
	10	[99]	RETURN   	0 1

function <./frontend/ui/widget/logindialog.lua:101,110> (19 instructions, 76 bytes at 0x7ff6b4407b80)
2 params, 6 slots, 1 upvalue, 2 locals, 7 constants, 0 functions
	1	[103]	GETTABLE 	2 0 -1	; "_input_widget"
	2	[103]	SELF     	2 2 -2	; "unfocus"
	3	[103]	CALL     	2 2 1
	4	[104]	GETTABLE 	2 0 -1	; "_input_widget"
	5	[104]	SELF     	2 2 -3	; "onCloseKeyboard"
	6	[104]	CALL     	2 2 1
	7	[106]	SETTABLE 	0 -1 1	; "_input_widget" -
	8	[107]	GETTABLE 	2 0 -1	; "_input_widget"
	9	[107]	SELF     	2 2 -4	; "focus"
	10	[107]	CALL     	2 2 1
	11	[108]	GETTABLE 	2 0 -1	; "_input_widget"
	12	[108]	SELF     	2 2 -5	; "onShowKeyboard"
	13	[108]	CALL     	2 2 1
	14	[109]	GETUPVAL 	2 0	; UIManager
	15	[109]	SELF     	2 2 -6	; "setDirty"
	16	[109]	MOVE     	4 0
	17	[109]	LOADK    	5 -7	; "ui"
	18	[109]	CALL     	2 4 1
	19	[110]	RETURN   	0 1
