-- BYTECODE -- logindialog.lua:24-93
0001    UGET     1   0      ; InputDialog
0002    TGETS    1   1   0  ; "init"
0003    MOV      2   0
0004    CALL     1   1   2
0005    UGET     1   1      ; InputText
0006    MOV      2   1
0007    TGETS    1   1   2  ; "new"
0008    TDUP     3   4
0009    TGETS    4   0   3  ; "username"
0010    TSETS    4   3   5  ; "text"
0011    TGETS    4   0   6  ; "username_hint"
0012    TSETS    4   3   7  ; "hint"
0013    TGETS    4   0   8  ; "input_face"
0014    TSETS    4   3   9  ; "face"
0015    TGETS    4   0  10  ; "width"
0016    MULVN    4   4   0  ; 0.9
0017    TSETS    4   3  10  ; "width"
0018    TSETS    0   3  11  ; "parent"
0019    CALL     1   2   3
0020    TSETS    1   0   1  ; "input_username"
0021    UGET     1   1      ; InputText
0022    MOV      2   1
0023    TGETS    1   1   2  ; "new"
0024    TDUP     3  14
0025    TGETS    4   0  13  ; "password"
0026    TSETS    4   3   5  ; "text"
0027    TGETS    4   0  15  ; "password_hint"
0028    TSETS    4   3   7  ; "hint"
0029    TGETS    4   0   8  ; "input_face"
0030    TSETS    4   3   9  ; "face"
0031    TGETS    4   0  10  ; "width"
0032    MULVN    4   4   0  ; 0.9
0033    TSETS    4   3  10  ; "width"
0034    TSETS    0   3  11  ; "parent"
0035    CALL     1   2   3
0036    TSETS    1   0  12  ; "input_password"
0037    UGET     1   2      ; FrameContainer
0038    MOV      2   1
0039    TGETS    1   1   2  ; "new"
0040    TDUP     3  19
0041    UGET     4   3      ; Size
0042    TGETS    4   4  17  ; "radius"
0043    TGETS    4   4  18  ; "window"
0044    TSETS    4   3  17  ; "radius"
0045    UGET     4   4      ; Blitbuffer
0046    TGETS    4   4  20  ; "COLOR_WHITE"
0047    TSETS    4   3  21  ; "background"
0048    UGET     4   5      ; VerticalGroup
0049    MOV      5   4
0050    TGETS    4   4   2  ; "new"
0051    TDUP     6  22
0052    TGETS    7   0  23  ; "title_widget"
0053    TSETB    7   6   1
0054    TGETS    7   0  24  ; "title_bar"
0055    TSETB    7   6   2
0056    UGET     7   6      ; CenterContainer
0057    MOV      8   7
0058    TGETS    7   7   2  ; "new"
0059    TDUP     9  29
0060    UGET    10   7      ; Geom
0061    MOV     11  10
0062    TGETS   10  10   2  ; "new"
0063    TDUP    12  27
0064    TGETS   13   0  24  ; "title_bar"
0065    MOV     14  13
0066    TGETS   13  13  25  ; "getSize"
0067    CALL    13   2   2
0068    TGETS   13  13  26  ; "w"
0069    TSETS   13  12  26  ; "w"
0070    TGETS   13   0   1  ; "input_username"
0071    MOV     14  13
0072    TGETS   13  13  25  ; "getSize"
0073    CALL    13   2   2
0074    TGETS   13  13  28  ; "h"
0075    TSETS   13  12  28  ; "h"
0076    CALL    10   2   3
0077    TSETS   10   9  30  ; "dimen"
0078    TGETS   10   0   1  ; "input_username"
0079    TSETB   10   9   1
0080    CALL     7   2   3
0081    TSETB    7   6   3
0082    UGET     7   6      ; CenterContainer
0083    MOV      8   7
0084    TGETS    7   7   2  ; "new"
0085    TDUP     9  32
0086    UGET    10   7      ; Geom
0087    MOV     11  10
0088    TGETS   10  10   2  ; "new"
0089    TDUP    12  31
0090    TGETS   13   0  24  ; "title_bar"
0091    MOV     14  13
0092    TGETS   13  13  25  ; "getSize"
0093    CALL    13   2   2
0094    TGETS   13  13  26  ; "w"
0095    TSETS   13  12  26  ; "w"
0096    TGETS   13   0  12  ; "input_password"
0097    MOV     14  13
0098    TGETS   13  13  25  ; "getSize"
0099    CALL    13   2   2
0100    TGETS   13  13  28  ; "h"
0101    TSETS   13  12  28  ; "h"
0102    CALL    10   2   3
0103    TSETS   10   9  30  ; "dimen"
0104    TGETS   10   0  12  ; "input_password"
0105    TSETB   10   9   1
0106    CALL     7   2   3
0107    TSETB    7   6   4
0108    UGET     7   6      ; CenterContainer
0109    MOV      8   7
0110    TGETS    7   7   2  ; "new"
0111    TDUP     9  35
0112    UGET    10   7      ; Geom
0113    MOV     11  10
0114    TGETS   10  10   2  ; "new"
0115    TDUP    12  33
0116    TGETS   13   0  24  ; "title_bar"
0117    MOV     14  13
0118    TGETS   13  13  25  ; "getSize"
0119    CALL    13   2   2
0120    TGETS   13  13  26  ; "w"
0121    TSETS   13  12  26  ; "w"
0122    TGETS   13   0  34  ; "button_table"
0123    MOV     14  13
0124    TGETS   13  13  25  ; "getSize"
0125    CALL    13   2   2
0126    TGETS   13  13  28  ; "h"
0127    TSETS   13  12  28  ; "h"
0128    CALL    10   2   3
0129    TSETS   10   9  30  ; "dimen"
0130    TGETS   10   0  34  ; "button_table"
0131    TSETB   10   9   1
0132    CALL     7   0   3
0133    TSETM    7   1      ; 5
0134    CALL     4   0   3
0135    TSETM    4   2      ; 1
0136    CALL     1   2   3
0137    TSETS    1   0  16  ; "dialog_frame"
0138    TGETS    1   0   1  ; "input_username"
0139    TSETS    1   0  36  ; "_input_widget"
0140    UGET     1   6      ; CenterContainer
0141    MOV      2   1
0142    TGETS    1   1   2  ; "new"
0143    TDUP     3  41
0144    UGET     4   7      ; Geom
0145    MOV      5   4
0146    TGETS    4   4   2  ; "new"
0147    TDUP     6  38
0148    UGET     7   8      ; Screen
0149    MOV      8   7
0150    TGETS    7   7  37  ; "getWidth"
0151    CALL     7   2   2
0152    TSETS    7   6  26  ; "w"
0153    UGET     7   8      ; Screen
0154    MOV      8   7
0155    TGETS    7   7  39  ; "getHeight"
0156    CALL     7   2   2
0157    TGETS    8   0  36  ; "_input_widget"
0158    MOV      9   8
0159    TGETS    8   8  40  ; "getKeyboardDimen"
0160    CALL     8   2   2
0161    TGETS    8   8  28  ; "h"
0162    SUBVV    7   7   8
0163    TSETS    7   6  28  ; "h"
0164    CALL     4   2   3
0165    TSETS    4   3  30  ; "dimen"
0166    TGETS    4   0  16  ; "dialog_frame"
0167    TSETB    4   3   1
0168    CALL     1   2   3
0169    TSETB    1   0   1
0170    RET0     0   1

-- BYTECODE -- logindialog.lua:95-99
0001    TGETS    1   0   0  ; "input_username"
0002    MOV      2   1
0003    TGETS    1   1   1  ; "getText"
0004    CALL     1   2   2
0005    TGETS    2   0   2  ; "input_password"
0006    MOV      3   2
0007    TGETS    2   2   1  ; "getText"
0008    CALL     2   2   2
0009    MOV      3   1
0010    MOV      4   2
0011    RET      3   3

-- BYTECODE -- logindialog.lua:101-110
0001    TGETS    2   0   0  ; "_input_widget"
0002    MOV      3   2
0003    TGETS    2   2   1  ; "unfocus"
0004    CALL     2   1   2
0005    TGETS    2   0   0  ; "_input_widget"
0006    MOV      3   2
0007    TGETS    2   2   2  ; "onCloseKeyboard"
0008    CALL     2   1   2
0009    TSETS    1   0   0  ; "_input_widget"
0010    TGETS    2   0   0  ; "_input_widget"
0011    MOV      3   2
0012    TGETS    2   2   3  ; "focus"
0013    CALL     2   1   2
0014    TGETS    2   0   0  ; "_input_widget"
0015    MOV      3   2
0016    TGETS    2   2   4  ; "onShowKeyboard"
0017    CALL     2   1   2
0018    UGET     2   0      ; UIManager
0019    MOV      3   2
0020    TGETS    2   2   5  ; "setDirty"
0021    MOV      4   0
0022    KSTR     5   6      ; "ui"
0023    CALL     2   1   4
0024    RET0     0   1

-- BYTECODE -- logindialog.lua:0-114
0001    GGET     0   0      ; "require"
0002    KSTR     1   1      ; "ffi/blitbuffer"
0003    CALL     0   2   2
0004    GGET     1   0      ; "require"
0005    KSTR     2   2      ; "ui/widget/container/centercontainer"
0006    CALL     1   2   2
0007    GGET     2   0      ; "require"
0008    KSTR     3   3      ; "ui/widget/container/framecontainer"
0009    CALL     2   2   2
0010    GGET     3   0      ; "require"
0011    KSTR     4   4      ; "ui/geometry"
0012    CALL     3   2   2
0013    GGET     4   0      ; "require"
0014    KSTR     5   5      ; "ui/widget/inputdialog"
0015    CALL     4   2   2
0016    GGET     5   0      ; "require"
0017    KSTR     6   6      ; "ui/widget/inputtext"
0018    CALL     5   2   2
0019    GGET     6   0      ; "require"
0020    KSTR     7   7      ; "ui/size"
0021    CALL     6   2   2
0022    GGET     7   0      ; "require"
0023    KSTR     8   8      ; "ui/uimanager"
0024    CALL     7   2   2
0025    GGET     8   0      ; "require"
0026    KSTR     9   9      ; "ui/widget/verticalgroup"
0027    CALL     8   2   2
0028    GGET     9   0      ; "require"
0029    KSTR    10  10      ; "gettext"
0030    CALL     9   2   2
0031    GGET    10   0      ; "require"
0032    KSTR    11  11      ; "device"
0033    CALL    10   2   2
0034    TGETS   10  10  12  ; "screen"
0035    MOV     12   4
0036    TGETS   11   4  13  ; "extend"
0037    TDUP    13  14
0038    CALL    11   2   3
0039    FNEW    12  16      ; logindialog.lua:24
0040    TSETS   12  11  15  ; "init"
0041    FNEW    12  18      ; logindialog.lua:95
0042    TSETS   12  11  17  ; "getCredential"
0043    FNEW    12  20      ; logindialog.lua:101
0044    TSETS   12  11  19  ; "onSwitchFocus"
0045    UCLO     0 => 0046
0046 => RET1    11   2

