
main <./frontend/luadata.lua:0,0> (47 instructions, 188 bytes at 0x7fce544068a0)
0+ params, 8 slots, 0 upvalues, 7 locals, 19 constants, 8 functions
	1	[5]	GETGLOBAL	0 -1	; require
	2	[5]	LOADK    	1 -2	; "luasettings"
	3	[5]	CALL     	0 2 2
	4	[6]	GETGLOBAL	1 -1	; require
	5	[6]	LOADK    	2 -3	; "dbg"
	6	[6]	CALL     	1 2 2
	7	[7]	GETGLOBAL	2 -1	; require
	8	[7]	LOADK    	3 -4	; "dump"
	9	[7]	CALL     	2 2 2
	10	[8]	GETGLOBAL	3 -1	; require
	11	[8]	LOADK    	4 -5	; "logger"
	12	[8]	CALL     	3 2 2
	13	[9]	GETGLOBAL	4 -1	; require
	14	[9]	LOADK    	5 -6	; "util"
	15	[9]	CALL     	4 2 2
	16	[11]	SELF     	5 0 -7	; "new"
	17	[11]	NEWTABLE 	7 0 2
	18	[12]	SETTABLE 	7 -8 -9	; "name" ""
	19	[13]	SETTABLE 	7 -10 -11	; "max_backups" 9
	20	[11]	CALL     	5 3 2
	21	[80]	CLOSURE  	6 0	; 0x7fce54406ce0
	22	[80]	MOVE     	0 1
	23	[80]	MOVE     	0 5
	24	[80]	MOVE     	0 4
	25	[80]	MOVE     	0 3
	26	[17]	SETTABLE 	5 -12 6	; "open" -
	27	[90]	CLOSURE  	6 1	; 0x7fce54407360
	28	[83]	SETTABLE 	5 -13 6	; "saveSetting" -
	29	[99]	CLOSURE  	6 2	; 0x7fce54406f60
	30	[93]	SETTABLE 	5 -14 6	; "delSetting" -
	31	[110]	CLOSURE  	6 3	; 0x7fce54408170
	32	[102]	SETTABLE 	5 -15 6	; "addTableItem" -
	33	[112]	GETTABLE 	6 0 -16	; "removeTableItem"
	34	[118]	CLOSURE  	7 4	; 0x7fce54406c20
	35	[118]	MOVE     	0 6
	36	[114]	SETTABLE 	5 -16 7	; "removeTableItem" -
	37	[132]	CLOSURE  	7 5	; 0x7fce54408cd0
	38	[132]	MOVE     	0 2
	39	[121]	SETTABLE 	5 -17 7	; "append" -
	40	[139]	CLOSURE  	7 6	; 0x7fce54409290
	41	[135]	SETTABLE 	5 -18 7	; "reset" -
	42	[169]	CLOSURE  	7 7	; 0x7fce54409530
	43	[169]	MOVE     	0 3
	44	[169]	MOVE     	0 2
	45	[142]	SETTABLE 	5 -19 7	; "flush" -
	46	[171]	RETURN   	5 2
	47	[171]	RETURN   	0 1

function <./frontend/luadata.lua:17,80> (121 instructions, 484 bytes at 0x7fce54406ce0)
3 params, 14 slots, 4 upvalues, 11 locals, 27 constants, 1 function
	1	[18]	TEST     	2 0 0
	2	[18]	JMP      	20	; to 23
	3	[18]	GETGLOBAL	3 -1	; type
	4	[18]	MOVE     	4 2
	5	[18]	CALL     	3 2 2
	6	[18]	EQ       	1 3 -2	; - "table"
	7	[18]	JMP      	15	; to 23
	8	[19]	GETUPVAL 	3 0	; dbg
	9	[19]	GETTABLE 	3 3 -3	; "is_on"
	10	[19]	TEST     	3 0 0
	11	[19]	JMP      	9	; to 21
	12	[20]	GETGLOBAL	3 -4	; error
	13	[20]	LOADK    	4 -5	; "LuaData: got "
	14	[20]	GETGLOBAL	5 -1	; type
	15	[20]	MOVE     	6 2
	16	[20]	CALL     	5 2 2
	17	[20]	LOADK    	6 -6	; ", table expected"
	18	[20]	CONCAT   	4 4 6
	19	[20]	CALL     	3 2 1
	20	[20]	JMP      	2	; to 23
	21	[22]	NEWTABLE 	3 0 0
	22	[22]	MOVE     	2 3
	23	[27]	GETUPVAL 	3 1	; LuaData
	24	[27]	SELF     	3 3 -7	; "new"
	25	[27]	MOVE     	5 2
	26	[27]	CALL     	3 3 2
	27	[27]	MOVE     	0 3
	28	[29]	NEWTABLE 	3 0 2
	29	[29]	SETTABLE 	3 -8 1	; "file" -
	30	[29]	NEWTABLE 	4 0 0
	31	[29]	SETTABLE 	3 -9 4	; "data" -
	32	[32]	NEWTABLE 	4 0 0
	33	[33]	SETTABLE 	4 -10 4	; "__index" -
	34	[34]	GETGLOBAL	5 -11	; setmetatable
	35	[34]	GETGLOBAL	6 -12	; _G
	36	[34]	MOVE     	7 4
	37	[34]	CALL     	5 3 1
	38	[35]	GETTABLE 	5 0 -13	; "name"
	39	[35]	LOADK    	6 -14	; "Entry"
	40	[35]	CONCAT   	5 5 6
	41	[52]	CLOSURE  	6 0	; 0x7fce54407690
	42	[52]	MOVE     	0 3
	43	[52]	GETUPVAL 	0 2	; util
	44	[52]	SETTABLE 	4 5 6
	45	[54]	LOADBOOL 	5 0 0
	46	[55]	GETGLOBAL	6 -15	; lfs
	47	[55]	GETTABLE 	6 6 -16	; "attributes"
	48	[55]	GETTABLE 	7 3 -8	; "file"
	49	[55]	LOADK    	8 -17	; "mode"
	50	[55]	CALL     	6 3 2
	51	[55]	EQ       	0 6 -8	; - "file"
	52	[55]	JMP      	22	; to 75
	53	[56]	GETGLOBAL	6 -18	; pcall
	54	[56]	GETGLOBAL	7 -19	; dofile
	55	[56]	GETTABLE 	8 3 -8	; "file"
	56	[56]	CALL     	6 3 2
	57	[56]	MOVE     	5 6
	58	[57]	TEST     	5 0 0
	59	[57]	JMP      	6	; to 66
	60	[58]	GETUPVAL 	6 3	; logger
	61	[58]	GETTABLE 	6 6 -20	; "dbg"
	62	[58]	LOADK    	7 -21	; "data is read from "
	63	[58]	GETTABLE 	8 3 -8	; "file"
	64	[58]	CALL     	6 3 1
	65	[58]	JMP      	9	; to 75
	66	[60]	GETUPVAL 	6 3	; logger
	67	[60]	GETTABLE 	6 6 -20	; "dbg"
	68	[60]	GETTABLE 	7 3 -8	; "file"
	69	[60]	LOADK    	8 -22	; " is invalid, remove."
	70	[60]	CALL     	6 3 1
	71	[61]	GETGLOBAL	6 -23	; os
	72	[61]	GETTABLE 	6 6 -24	; "remove"
	73	[61]	GETTABLE 	7 3 -8	; "file"
	74	[61]	CALL     	6 2 1
	75	[64]	TEST     	5 0 1
	76	[64]	JMP      	38	; to 115
	77	[65]	LOADK    	6 -25	; 1
	78	[65]	GETTABLE 	7 0 -26	; "max_backups"
	79	[65]	LOADK    	8 -25	; 1
	80	[65]	FORPREP  	6 33	; to 114
	81	[66]	GETTABLE 	10 3 -8	; "file"
	82	[66]	LOADK    	11 -27	; ".old."
	83	[66]	MOVE     	12 9
	84	[66]	CONCAT   	10 10 12
	85	[67]	GETGLOBAL	11 -15	; lfs
	86	[67]	GETTABLE 	11 11 -16	; "attributes"
	87	[67]	MOVE     	12 10
	88	[67]	LOADK    	13 -17	; "mode"
	89	[67]	CALL     	11 3 2
	90	[67]	EQ       	0 11 -8	; - "file"
	91	[67]	JMP      	22	; to 114
	92	[68]	GETGLOBAL	11 -18	; pcall
	93	[68]	GETGLOBAL	12 -19	; dofile
	94	[68]	MOVE     	13 10
	95	[68]	CALL     	11 3 2
	96	[68]	TEST     	11 0 0
	97	[68]	JMP      	7	; to 105
	98	[69]	GETUPVAL 	11 3	; logger
	99	[69]	GETTABLE 	11 11 -20	; "dbg"
	100	[69]	LOADK    	12 -21	; "data is read from "
	101	[69]	MOVE     	13 10
	102	[69]	CALL     	11 3 1
	103	[70]	JMP      	11	; to 115
	104	[70]	JMP      	9	; to 114
	105	[72]	GETUPVAL 	11 3	; logger
	106	[72]	GETTABLE 	11 11 -20	; "dbg"
	107	[72]	MOVE     	12 10
	108	[72]	LOADK    	13 -22	; " is invalid, remove."
	109	[72]	CALL     	11 3 1
	110	[73]	GETGLOBAL	11 -23	; os
	111	[73]	GETTABLE 	11 11 -24	; "remove"
	112	[73]	MOVE     	12 10
	113	[73]	CALL     	11 2 1
	114	[65]	FORLOOP  	6 -34	; to 81
	115	[79]	GETGLOBAL	6 -11	; setmetatable
	116	[79]	MOVE     	7 3
	117	[79]	NEWTABLE 	8 0 1
	118	[79]	SETTABLE 	8 -10 0	; "__index" -
	119	[79]	TAILCALL 	6 3 0
	120	[79]	RETURN   	6 0
	121	[80]	RETURN   	0 1

function <./frontend/luadata.lua:35,52> (48 instructions, 192 bytes at 0x7fce54407690)
1 param, 9 slots, 2 upvalues, 7 locals, 6 constants, 0 functions
	1	[36]	GETTABLE 	1 0 -1	; "index"
	2	[36]	TEST     	1 0 0
	3	[36]	JMP      	42	; to 46
	4	[38]	GETTABLE 	1 0 -2	; "data"
	5	[38]	TEST     	1 0 1
	6	[38]	JMP      	4	; to 11
	7	[38]	GETUPVAL 	1 0	; new
	8	[38]	GETTABLE 	1 1 -2	; "data"
	9	[38]	GETTABLE 	2 0 -1	; "index"
	10	[38]	SETTABLE 	1 2 -3	; - nil
	11	[39]	GETUPVAL 	1 0	; new
	12	[39]	GETTABLE 	1 1 -2	; "data"
	13	[39]	GETTABLE 	2 0 -1	; "index"
	14	[39]	GETUPVAL 	3 0	; new
	15	[39]	GETTABLE 	3 3 -2	; "data"
	16	[39]	GETTABLE 	4 0 -1	; "index"
	17	[39]	GETTABLE 	3 3 4
	18	[39]	TEST     	3 0 1
	19	[39]	JMP      	1	; to 21
	20	[39]	NEWTABLE 	3 0 0
	21	[39]	SETTABLE 	1 2 3
	22	[40]	GETUPVAL 	1 1	; util
	23	[40]	GETTABLE 	1 1 -4	; "tableSize"
	24	[40]	GETTABLE 	2 0 -2	; "data"
	25	[40]	CALL     	1 2 2
	26	[41]	EQ       	0 1 -5	; - 1
	27	[41]	JMP      	12	; to 40
	28	[42]	GETGLOBAL	2 -6	; pairs
	29	[42]	GETTABLE 	3 0 -2	; "data"
	30	[42]	CALL     	2 2 4
	31	[42]	JMP      	5	; to 37
	32	[43]	GETUPVAL 	7 0	; new
	33	[43]	GETTABLE 	7 7 -2	; "data"
	34	[43]	GETTABLE 	8 0 -1	; "index"
	35	[43]	GETTABLE 	7 7 8
	36	[43]	SETTABLE 	7 5 6
	37	[42]	TFORLOOP 	2 2
	38	[43]	JMP      	-7	; to 32
	39	[44]	JMP      	8	; to 48
	40	[46]	GETUPVAL 	2 0	; new
	41	[46]	GETTABLE 	2 2 -2	; "data"
	42	[46]	GETTABLE 	3 0 -1	; "index"
	43	[46]	GETTABLE 	4 0 -2	; "data"
	44	[46]	SETTABLE 	2 3 4
	45	[47]	JMP      	2	; to 48
	46	[50]	GETUPVAL 	1 0	; new
	47	[50]	SETTABLE 	1 -2 0	; "data" -
	48	[52]	RETURN   	0 1

function <./frontend/luadata.lua:83,90> (9 instructions, 36 bytes at 0x7fce54407360)
3 params, 6 slots, 0 upvalues, 3 locals, 3 constants, 0 functions
	1	[84]	GETTABLE 	3 0 -1	; "data"
	2	[84]	SETTABLE 	3 1 2
	3	[85]	SELF     	3 0 -2	; "append"
	4	[85]	NEWTABLE 	5 0 2
	5	[86]	SETTABLE 	5 -3 1	; "index" -
	6	[87]	SETTABLE 	5 -1 2	; "data" -
	7	[85]	CALL     	3 3 1
	8	[89]	RETURN   	0 2
	9	[90]	RETURN   	0 1

function <./frontend/luadata.lua:93,99> (8 instructions, 32 bytes at 0x7fce54406f60)
2 params, 5 slots, 0 upvalues, 2 locals, 4 constants, 0 functions
	1	[94]	GETTABLE 	2 0 -1	; "data"
	2	[94]	SETTABLE 	2 1 -2	; - nil
	3	[95]	SELF     	2 0 -3	; "append"
	4	[95]	NEWTABLE 	4 0 1
	5	[96]	SETTABLE 	4 -4 1	; "index" -
	6	[95]	CALL     	2 3 1
	7	[98]	RETURN   	0 2
	8	[99]	RETURN   	0 1

function <./frontend/luadata.lua:102,110> (27 instructions, 108 bytes at 0x7fce54408170)
3 params, 9 slots, 0 upvalues, 4 locals, 7 constants, 0 functions
	1	[103]	SELF     	3 0 -1	; "has"
	2	[103]	MOVE     	5 1
	3	[103]	CALL     	3 3 2
	4	[103]	TEST     	3 0 0
	5	[103]	JMP      	5	; to 11
	6	[103]	SELF     	3 0 -2	; "readSetting"
	7	[103]	MOVE     	5 1
	8	[103]	CALL     	3 3 2
	9	[103]	TEST     	3 0 1
	10	[103]	JMP      	1	; to 12
	11	[103]	NEWTABLE 	3 0 0
	12	[104]	GETGLOBAL	4 -3	; table
	13	[104]	GETTABLE 	4 4 -4	; "insert"
	14	[104]	MOVE     	5 3
	15	[104]	MOVE     	6 2
	16	[104]	CALL     	4 3 1
	17	[105]	GETTABLE 	4 0 -5	; "data"
	18	[105]	SETTABLE 	4 1 3
	19	[106]	SELF     	4 0 -6	; "append"
	20	[106]	NEWTABLE 	6 0 2
	21	[107]	SETTABLE 	6 -7 1	; "index" -
	22	[108]	NEWTABLE 	7 0 1
	23	[108]	LEN      	8 3
	24	[108]	SETTABLE 	7 8 2
	25	[108]	SETTABLE 	6 -5 7	; "data" -
	26	[106]	CALL     	4 3 1
	27	[110]	RETURN   	0 1

function <./frontend/luadata.lua:114,118> (9 instructions, 36 bytes at 0x7fce54406c20)
3 params, 7 slots, 1 upvalue, 3 locals, 1 constant, 0 functions
	1	[115]	GETUPVAL 	3 0	; _orig_removeTableItem
	2	[115]	MOVE     	4 0
	3	[115]	MOVE     	5 1
	4	[115]	MOVE     	6 2
	5	[115]	CALL     	3 4 1
	6	[116]	SELF     	3 0 -1	; "flush"
	7	[116]	CALL     	3 2 1
	8	[117]	RETURN   	0 2
	9	[118]	RETURN   	0 1

function <./frontend/luadata.lua:121,132> (33 instructions, 132 bytes at 0x7fce54408cd0)
2 params, 7 slots, 1 upvalue, 3 locals, 14 constants, 0 functions
	1	[122]	GETTABLE 	2 0 -1	; "file"
	2	[122]	TEST     	2 0 1
	3	[122]	JMP      	1	; to 5
	4	[122]	RETURN   	0 1
	5	[123]	GETGLOBAL	2 -2	; io
	6	[123]	GETTABLE 	2 2 -3	; "open"
	7	[123]	GETTABLE 	3 0 -1	; "file"
	8	[123]	LOADK    	4 -4	; "a"
	9	[123]	CALL     	2 3 2
	10	[124]	EQ       	1 2 -5	; - nil
	11	[124]	JMP      	20	; to 32
	12	[125]	GETGLOBAL	3 -6	; os
	13	[125]	GETTABLE 	3 3 -7	; "setlocale"
	14	[125]	LOADK    	4 -8	; "C"
	15	[125]	LOADK    	5 -9	; "numeric"
	16	[125]	CALL     	3 3 1
	17	[126]	SELF     	3 2 -10	; "write"
	18	[126]	GETTABLE 	5 0 -11	; "name"
	19	[126]	LOADK    	6 -12	; "Entry"
	20	[126]	CONCAT   	5 5 6
	21	[126]	CALL     	3 3 1
	22	[127]	SELF     	3 2 -10	; "write"
	23	[127]	GETUPVAL 	5 0	; dump
	24	[127]	MOVE     	6 1
	25	[127]	CALL     	5 2 0
	26	[127]	CALL     	3 0 1
	27	[128]	SELF     	3 2 -10	; "write"
	28	[128]	LOADK    	5 -13	; "\n"
	29	[128]	CALL     	3 3 1
	30	[129]	SELF     	3 2 -14	; "close"
	31	[129]	CALL     	3 2 1
	32	[131]	RETURN   	0 2
	33	[132]	RETURN   	0 1

function <./frontend/luadata.lua:135,139> (5 instructions, 20 bytes at 0x7fce54409290)
2 params, 4 slots, 0 upvalues, 2 locals, 2 constants, 0 functions
	1	[136]	SETTABLE 	0 -1 1	; "data" -
	2	[137]	SELF     	2 0 -2	; "flush"
	3	[137]	CALL     	2 2 1
	4	[138]	RETURN   	0 2
	5	[139]	RETURN   	0 1

function <./frontend/luadata.lua:142,169> (102 instructions, 408 bytes at 0x7fce54409530)
1 param, 12 slots, 2 upvalues, 6 locals, 28 constants, 0 functions
	1	[143]	GETTABLE 	1 0 -1	; "file"
	2	[143]	TEST     	1 0 1
	3	[143]	JMP      	1	; to 5
	4	[143]	RETURN   	0 1
	5	[145]	GETGLOBAL	1 -2	; lfs
	6	[145]	GETTABLE 	1 1 -3	; "attributes"
	7	[145]	GETTABLE 	2 0 -1	; "file"
	8	[145]	LOADK    	3 -4	; "mode"
	9	[145]	CALL     	1 3 2
	10	[145]	EQ       	0 1 -1	; - "file"
	11	[145]	JMP      	54	; to 66
	12	[146]	LOADK    	1 -5	; 1
	13	[146]	GETTABLE 	2 0 -6	; "max_backups"
	14	[146]	LOADK    	3 -5	; 1
	15	[146]	FORPREP  	1 33	; to 49
	16	[147]	GETGLOBAL	5 -2	; lfs
	17	[147]	GETTABLE 	5 5 -3	; "attributes"
	18	[147]	GETTABLE 	6 0 -1	; "file"
	19	[147]	LOADK    	7 -7	; ".old."
	20	[147]	MOVE     	8 4
	21	[147]	CONCAT   	6 6 8
	22	[147]	LOADK    	7 -4	; "mode"
	23	[147]	CALL     	5 3 2
	24	[147]	EQ       	0 5 -1	; - "file"
	25	[147]	JMP      	24	; to 50
	26	[148]	GETUPVAL 	5 0	; logger
	27	[148]	GETTABLE 	5 5 -8	; "dbg"
	28	[148]	LOADK    	6 -9	; "LuaData: Rename "
	29	[148]	GETTABLE 	7 0 -1	; "file"
	30	[148]	LOADK    	8 -7	; ".old."
	31	[148]	MOVE     	9 4
	32	[148]	CONCAT   	7 7 9
	33	[148]	LOADK    	8 -10	; " to "
	34	[148]	GETTABLE 	9 0 -1	; "file"
	35	[148]	LOADK    	10 -7	; ".old."
	36	[148]	ADD      	11 4 -5	; - 1
	37	[148]	CONCAT   	9 9 11
	38	[148]	CALL     	5 5 1
	39	[149]	GETGLOBAL	5 -11	; os
	40	[149]	GETTABLE 	5 5 -12	; "rename"
	41	[149]	GETTABLE 	6 0 -1	; "file"
	42	[149]	GETTABLE 	7 0 -1	; "file"
	43	[149]	LOADK    	8 -7	; ".old."
	44	[149]	ADD      	9 4 -5	; - 1
	45	[149]	CONCAT   	7 7 9
	46	[149]	CALL     	5 3 1
	47	[149]	JMP      	1	; to 49
	48	[151]	JMP      	1	; to 50
	49	[146]	FORLOOP  	1 -34	; to 16
	50	[154]	GETUPVAL 	1 0	; logger
	51	[154]	GETTABLE 	1 1 -8	; "dbg"
	52	[154]	LOADK    	2 -9	; "LuaData: Rename "
	53	[154]	GETTABLE 	3 0 -1	; "file"
	54	[154]	LOADK    	4 -10	; " to "
	55	[154]	GETTABLE 	5 0 -1	; "file"
	56	[154]	LOADK    	6 -13	; ".old.1"
	57	[154]	CONCAT   	5 5 6
	58	[154]	CALL     	1 5 1
	59	[155]	GETGLOBAL	1 -11	; os
	60	[155]	GETTABLE 	1 1 -12	; "rename"
	61	[155]	GETTABLE 	2 0 -1	; "file"
	62	[155]	GETTABLE 	3 0 -1	; "file"
	63	[155]	LOADK    	4 -13	; ".old.1"
	64	[155]	CONCAT   	3 3 4
	65	[155]	CALL     	1 3 1
	66	[158]	GETUPVAL 	1 0	; logger
	67	[158]	GETTABLE 	1 1 -8	; "dbg"
	68	[158]	LOADK    	2 -14	; "LuaData: Write to "
	69	[158]	GETTABLE 	3 0 -1	; "file"
	70	[158]	CALL     	1 3 1
	71	[159]	GETGLOBAL	1 -15	; io
	72	[159]	GETTABLE 	1 1 -16	; "open"
	73	[159]	GETTABLE 	2 0 -1	; "file"
	74	[159]	LOADK    	3 -17	; "w"
	75	[159]	CALL     	1 3 2
	76	[160]	EQ       	1 1 -18	; - nil
	77	[160]	JMP      	23	; to 101
	78	[161]	GETGLOBAL	2 -11	; os
	79	[161]	GETTABLE 	2 2 -19	; "setlocale"
	80	[161]	LOADK    	3 -20	; "C"
	81	[161]	LOADK    	4 -21	; "numeric"
	82	[161]	CALL     	2 3 1
	83	[162]	SELF     	2 1 -22	; "write"
	84	[162]	LOADK    	4 -23	; "-- we can read Lua syntax here!\n"
	85	[162]	CALL     	2 3 1
	86	[163]	SELF     	2 1 -22	; "write"
	87	[163]	GETTABLE 	4 0 -24	; "name"
	88	[163]	LOADK    	5 -25	; "Entry"
	89	[163]	CONCAT   	4 4 5
	90	[163]	CALL     	2 3 1
	91	[164]	SELF     	2 1 -22	; "write"
	92	[164]	GETUPVAL 	4 1	; dump
	93	[164]	GETTABLE 	5 0 -26	; "data"
	94	[164]	CALL     	4 2 0
	95	[164]	CALL     	2 0 1
	96	[165]	SELF     	2 1 -22	; "write"
	97	[165]	LOADK    	4 -27	; "\n"
	98	[165]	CALL     	2 3 1
	99	[166]	SELF     	2 1 -28	; "close"
	100	[166]	CALL     	2 2 1
	101	[168]	RETURN   	0 2
	102	[169]	RETURN   	0 1
