-- BYTECODE -- luadata_spec.lua:3-6
0001    GGET     0   0      ; "require"
0002    KSTR     1   1      ; "commonrequire"
0003    CALL     0   1   2
0004    GGET     0   0      ; "require"
0005    KSTR     1   2      ; "frontend/luadata"
0006    CALL     0   2   2
0007    MOV      1   0
0008    TGETS    0   0   3  ; "open"
0009    KSTR     2   4      ; "this-is-not-a-valid-file"
0010    CALL     0   2   3
0011    USETV    0   0      ; Settings
0012    RET0     0   1

-- BYTECODE -- luadata_spec.lua:8-18
0001    UGET     0   0      ; Settings
0002    MOV      1   0
0003    TGETS    0   0   0  ; "delSetting"
0004    KSTR     2   1      ; "abc"
0005    CALL     0   1   3
0006    GGET     0   2      ; "assert"
0007    TGETS    0   0   3  ; "True"
0008    UGET     1   0      ; Settings
0009    MOV      2   1
0010    TGETS    1   1   4  ; "hasNot"
0011    KSTR     3   1      ; "abc"
0012    CALL     1   0   3
0013    CALLM    0   1   0
0014    GGET     0   2      ; "assert"
0015    TGETS    0   0   3  ; "True"
0016    UGET     1   0      ; Settings
0017    MOV      2   1
0018    TGETS    1   1   5  ; "nilOrTrue"
0019    KSTR     3   1      ; "abc"
0020    CALL     1   0   3
0021    CALLM    0   1   0
0022    GGET     0   2      ; "assert"
0023    TGETS    0   0   6  ; "False"
0024    UGET     1   0      ; Settings
0025    MOV      2   1
0026    TGETS    1   1   7  ; "isTrue"
0027    KSTR     3   1      ; "abc"
0028    CALL     1   0   3
0029    CALLM    0   1   0
0030    UGET     0   0      ; Settings
0031    MOV      1   0
0032    TGETS    0   0   8  ; "saveSetting"
0033    KSTR     2   1      ; "abc"
0034    KPRI     3   2
0035    CALL     0   1   4
0036    GGET     0   2      ; "assert"
0037    TGETS    0   0   3  ; "True"
0038    UGET     1   0      ; Settings
0039    MOV      2   1
0040    TGETS    1   1   9  ; "has"
0041    KSTR     3   1      ; "abc"
0042    CALL     1   0   3
0043    CALLM    0   1   0
0044    GGET     0   2      ; "assert"
0045    TGETS    0   0   3  ; "True"
0046    UGET     1   0      ; Settings
0047    MOV      2   1
0048    TGETS    1   1   5  ; "nilOrTrue"
0049    KSTR     3   1      ; "abc"
0050    CALL     1   0   3
0051    CALLM    0   1   0
0052    GGET     0   2      ; "assert"
0053    TGETS    0   0   3  ; "True"
0054    UGET     1   0      ; Settings
0055    MOV      2   1
0056    TGETS    1   1   7  ; "isTrue"
0057    KSTR     3   1      ; "abc"
0058    CALL     1   0   3
0059    CALLM    0   1   0
0060    RET0     0   1

-- BYTECODE -- luadata_spec.lua:20-41
0001    UGET     0   0      ; Settings
0002    MOV      1   0
0003    TGETS    0   0   0  ; "delSetting"
0004    KSTR     2   1      ; "abc"
0005    CALL     0   1   3
0006    GGET     0   2      ; "assert"
0007    TGETS    0   0   3  ; "True"
0008    UGET     1   0      ; Settings
0009    MOV      2   1
0010    TGETS    1   1   4  ; "hasNot"
0011    KSTR     3   1      ; "abc"
0012    CALL     1   0   3
0013    CALLM    0   1   0
0014    UGET     0   0      ; Settings
0015    MOV      1   0
0016    TGETS    0   0   5  ; "flipNilOrTrue"
0017    KSTR     2   1      ; "abc"
0018    CALL     0   1   3
0019    GGET     0   2      ; "assert"
0020    TGETS    0   0   6  ; "False"
0021    UGET     1   0      ; Settings
0022    MOV      2   1
0023    TGETS    1   1   7  ; "nilOrTrue"
0024    KSTR     3   1      ; "abc"
0025    CALL     1   0   3
0026    CALLM    0   1   0
0027    GGET     0   2      ; "assert"
0028    TGETS    0   0   3  ; "True"
0029    UGET     1   0      ; Settings
0030    MOV      2   1
0031    TGETS    1   1   8  ; "has"
0032    KSTR     3   1      ; "abc"
0033    CALL     1   0   3
0034    CALLM    0   1   0
0035    GGET     0   2      ; "assert"
0036    TGETS    0   0   6  ; "False"
0037    UGET     1   0      ; Settings
0038    MOV      2   1
0039    TGETS    1   1   9  ; "isTrue"
0040    KSTR     3   1      ; "abc"
0041    CALL     1   0   3
0042    CALLM    0   1   0
0043    UGET     0   0      ; Settings
0044    MOV      1   0
0045    TGETS    0   0   5  ; "flipNilOrTrue"
0046    KSTR     2   1      ; "abc"
0047    CALL     0   1   3
0048    GGET     0   2      ; "assert"
0049    TGETS    0   0   3  ; "True"
0050    UGET     1   0      ; Settings
0051    MOV      2   1
0052    TGETS    1   1   7  ; "nilOrTrue"
0053    KSTR     3   1      ; "abc"
0054    CALL     1   0   3
0055    CALLM    0   1   0
0056    GGET     0   2      ; "assert"
0057    TGETS    0   0   3  ; "True"
0058    UGET     1   0      ; Settings
0059    MOV      2   1
0060    TGETS    1   1   4  ; "hasNot"
0061    KSTR     3   1      ; "abc"
0062    CALL     1   0   3
0063    CALLM    0   1   0
0064    GGET     0   2      ; "assert"
0065    TGETS    0   0   6  ; "False"
0066    UGET     1   0      ; Settings
0067    MOV      2   1
0068    TGETS    1   1   9  ; "isTrue"
0069    KSTR     3   1      ; "abc"
0070    CALL     1   0   3
0071    CALLM    0   1   0
0072    UGET     0   0      ; Settings
0073    MOV      1   0
0074    TGETS    0   0  10  ; "flipTrue"
0075    KSTR     2   1      ; "abc"
0076    CALL     0   1   3
0077    GGET     0   2      ; "assert"
0078    TGETS    0   0   3  ; "True"
0079    UGET     1   0      ; Settings
0080    MOV      2   1
0081    TGETS    1   1   8  ; "has"
0082    KSTR     3   1      ; "abc"
0083    CALL     1   0   3
0084    CALLM    0   1   0
0085    GGET     0   2      ; "assert"
0086    TGETS    0   0   3  ; "True"
0087    UGET     1   0      ; Settings
0088    MOV      2   1
0089    TGETS    1   1   9  ; "isTrue"
0090    KSTR     3   1      ; "abc"
0091    CALL     1   0   3
0092    CALLM    0   1   0
0093    GGET     0   2      ; "assert"
0094    TGETS    0   0   3  ; "True"
0095    UGET     1   0      ; Settings
0096    MOV      2   1
0097    TGETS    1   1   7  ; "nilOrTrue"
0098    KSTR     3   1      ; "abc"
0099    CALL     1   0   3
0100    CALLM    0   1   0
0101    UGET     0   0      ; Settings
0102    MOV      1   0
0103    TGETS    0   0  10  ; "flipTrue"
0104    KSTR     2   1      ; "abc"
0105    CALL     0   1   3
0106    GGET     0   2      ; "assert"
0107    TGETS    0   0   6  ; "False"
0108    UGET     1   0      ; Settings
0109    MOV      2   1
0110    TGETS    1   1   8  ; "has"
0111    KSTR     3   1      ; "abc"
0112    CALL     1   0   3
0113    CALLM    0   1   0
0114    GGET     0   2      ; "assert"
0115    TGETS    0   0   6  ; "False"
0116    UGET     1   0      ; Settings
0117    MOV      2   1
0118    TGETS    1   1   9  ; "isTrue"
0119    KSTR     3   1      ; "abc"
0120    CALL     1   0   3
0121    CALLM    0   1   0
0122    GGET     0   2      ; "assert"
0123    TGETS    0   0   3  ; "True"
0124    UGET     1   0      ; Settings
0125    MOV      2   1
0126    TGETS    1   1   7  ; "nilOrTrue"
0127    KSTR     3   1      ; "abc"
0128    CALL     1   0   3
0129    CALLM    0   1   0
0130    RET0     0   1

-- BYTECODE -- luadata_spec.lua:43-67
0001    UGET     0   0      ; Settings
0002    MOV      1   0
0003    TGETS    0   0   0  ; "delSetting"
0004    KSTR     2   1      ; "key"
0005    CALL     0   1   3
0006    UGET     0   0      ; Settings
0007    MOV      1   0
0008    TGETS    0   0   2  ; "saveSetting"
0009    KSTR     2   1      ; "key"
0010    TDUP     3   3
0011    CALL     0   1   4
0012    UGET     0   0      ; Settings
0013    MOV      1   0
0014    TGETS    0   0   4  ; "child"
0015    KSTR     2   1      ; "key"
0016    CALL     0   2   3
0017    GGET     1   5      ; "assert"
0018    TGETS    1   1   6  ; "is_not_nil"
0019    MOV      2   0
0020    CALL     1   1   2
0021    GGET     1   5      ; "assert"
0022    TGETS    1   1   7  ; "True"
0023    MOV      3   0
0024    TGETS    2   0   8  ; "has"
0025    KSTR     4   9      ; "a"
0026    CALL     2   0   3
0027    CALLM    1   1   0
0028    GGET     1   5      ; "assert"
0029    TGETS    1   1  10  ; "are"
0030    TGETS    1   1  11  ; "equal"
0031    MOV      3   0
0032    TGETS    2   0  12  ; "readSetting"
0033    KSTR     4   9      ; "a"
0034    CALL     2   2   3
0035    KSTR     3  13      ; "b"
0036    CALL     1   1   3
0037    GGET     1   5      ; "assert"
0038    TGETS    1   1   7  ; "True"
0039    MOV      3   0
0040    TGETS    2   0   8  ; "has"
0041    KSTR     4  14      ; "c"
0042    CALL     2   0   3
0043    CALLM    1   1   0
0044    GGET     1   5      ; "assert"
0045    TGETS    1   1   7  ; "True"
0046    MOV      3   0
0047    TGETS    2   0  15  ; "isTrue"
0048    KSTR     4  14      ; "c"
0049    CALL     2   0   3
0050    CALLM    1   1   0
0051    GGET     1   5      ; "assert"
0052    TGETS    1   1   7  ; "True"
0053    MOV      3   0
0054    TGETS    2   0   8  ; "has"
0055    KSTR     4  16      ; "d"
0056    CALL     2   0   3
0057    CALLM    1   1   0
0058    GGET     1   5      ; "assert"
0059    TGETS    1   1   7  ; "True"
0060    MOV      3   0
0061    TGETS    2   0  17  ; "isFalse"
0062    KSTR     4  16      ; "d"
0063    CALL     2   0   3
0064    CALLM    1   1   0
0065    GGET     1   5      ; "assert"
0066    TGETS    1   1  18  ; "False"
0067    MOV      3   0
0068    TGETS    2   0  15  ; "isTrue"
0069    KSTR     4  19      ; "e"
0070    CALL     2   0   3
0071    CALLM    1   1   0
0072    MOV      2   0
0073    TGETS    1   0  20  ; "flipTrue"
0074    KSTR     3  19      ; "e"
0075    CALL     1   1   3
0076    MOV      2   0
0077    TGETS    1   0  21  ; "close"
0078    CALL     1   1   2
0079    UGET     1   0      ; Settings
0080    MOV      2   1
0081    TGETS    1   1   4  ; "child"
0082    KSTR     3   1      ; "key"
0083    CALL     1   2   3
0084    MOV      0   1
0085    GGET     1   5      ; "assert"
0086    TGETS    1   1   7  ; "True"
0087    MOV      3   0
0088    TGETS    2   0  15  ; "isTrue"
0089    KSTR     4  19      ; "e"
0090    CALL     2   0   3
0091    CALLM    1   1   0
0092    RET0     0   1

-- BYTECODE -- luadata_spec.lua:72-80
0001    UGET     0   0      ; Settings
0002    MOV      1   0
0003    TGETS    0   0   0  ; "addTableItem"
0004    KSTR     2   1      ; "key"
0005    KSHORT   3   1
0006    CALL     0   1   4
0007    UGET     0   0      ; Settings
0008    MOV      1   0
0009    TGETS    0   0   0  ; "addTableItem"
0010    KSTR     2   1      ; "key"
0011    KSHORT   3   2
0012    CALL     0   1   4
0013    UGET     0   0      ; Settings
0014    MOV      1   0
0015    TGETS    0   0   0  ; "addTableItem"
0016    KSTR     2   1      ; "key"
0017    KSHORT   3   3
0018    CALL     0   1   4
0019    GGET     0   2      ; "assert"
0020    TGETS    0   0   3  ; "are"
0021    TGETS    0   0   4  ; "equal"
0022    KSHORT   1   1
0023    UGET     2   0      ; Settings
0024    MOV      3   2
0025    TGETS    2   2   5  ; "readSetting"
0026    KSTR     4   1      ; "key"
0027    CALL     2   2   3
0028    TGETB    2   2   1
0029    CALL     0   1   3
0030    GGET     0   2      ; "assert"
0031    TGETS    0   0   3  ; "are"
0032    TGETS    0   0   4  ; "equal"
0033    KSHORT   1   2
0034    UGET     2   0      ; Settings
0035    MOV      3   2
0036    TGETS    2   2   5  ; "readSetting"
0037    KSTR     4   1      ; "key"
0038    CALL     2   2   3
0039    TGETB    2   2   2
0040    CALL     0   1   3
0041    GGET     0   2      ; "assert"
0042    TGETS    0   0   3  ; "are"
0043    TGETS    0   0   4  ; "equal"
0044    KSHORT   1   3
0045    UGET     2   0      ; Settings
0046    MOV      3   2
0047    TGETS    2   2   5  ; "readSetting"
0048    KSTR     4   1      ; "key"
0049    CALL     2   2   3
0050    TGETB    2   2   3
0051    CALL     0   1   3
0052    RET0     0   1

-- BYTECODE -- luadata_spec.lua:82-87
0001    UGET     0   0      ; Settings
0002    MOV      1   0
0003    TGETS    0   0   0  ; "removeTableItem"
0004    KSTR     2   1      ; "key"
0005    KSHORT   3   1
0006    CALL     0   1   4
0007    GGET     0   2      ; "assert"
0008    TGETS    0   0   3  ; "are"
0009    TGETS    0   0   4  ; "equal"
0010    KSHORT   1   2
0011    UGET     2   0      ; Settings
0012    MOV      3   2
0013    TGETS    2   2   5  ; "readSetting"
0014    KSTR     4   1      ; "key"
0015    CALL     2   2   3
0016    TGETB    2   2   1
0017    CALL     0   1   3
0018    GGET     0   2      ; "assert"
0019    TGETS    0   0   3  ; "are"
0020    TGETS    0   0   4  ; "equal"
0021    KSHORT   1   3
0022    UGET     2   0      ; Settings
0023    MOV      3   2
0024    TGETS    2   2   5  ; "readSetting"
0025    KSTR     4   1      ; "key"
0026    CALL     2   2   3
0027    TGETB    2   2   2
0028    CALL     0   1   3
0029    RET0     0   1

-- BYTECODE -- luadata_spec.lua:69-88
0001    UGET     0   0      ; Settings
0002    MOV      1   0
0003    TGETS    0   0   0  ; "delSetting"
0004    KSTR     2   1      ; "key"
0005    CALL     0   1   3
0006    GGET     0   2      ; "it"
0007    KSTR     1   3      ; "should add item to table"
0008    FNEW     2   4      ; luadata_spec.lua:72
0009    CALL     0   1   3
0010    GGET     0   2      ; "it"
0011    KSTR     1   5      ; "should remove item from table"
0012    FNEW     2   6      ; luadata_spec.lua:82
0013    CALL     0   1   3
0014    RET0     0   1

-- BYTECODE -- luadata_spec.lua:93-96
0001    UGET     0   0      ; d
0002    MOV      1   0
0003    TGETS    0   0   0  ; "saveSetting"
0004    KSTR     2   1      ; "a"
0005    KSTR     3   1      ; "a"
0006    CALL     0   1   4
0007    GGET     0   2      ; "assert"
0008    TGETS    0   0   3  ; "Equals"
0009    KSTR     1   4      ; "file"
0010    GGET     2   5      ; "lfs"
0011    TGETS    2   2   6  ; "attributes"
0012    UGET     3   0      ; d
0013    TGETS    3   3   4  ; "file"
0014    KSTR     4   7      ; "mode"
0015    CALL     2   0   3
0016    CALLM    0   1   1
0017    RET0     0   1

-- BYTECODE -- luadata_spec.lua:97-103
0001    UGET     0   0      ; d
0002    MOV      1   0
0003    TGETS    0   0   0  ; "flush"
0004    CALL     0   1   2
0005    GGET     0   1      ; "assert"
0006    TGETS    0   0   2  ; "Equals"
0007    KSTR     1   3      ; "file"
0008    GGET     2   4      ; "lfs"
0009    TGETS    2   2   5  ; "attributes"
0010    UGET     3   0      ; d
0011    TGETS    3   3   3  ; "file"
0012    KSTR     4   6      ; "mode"
0013    CALL     2   0   3
0014    CALLM    0   1   1
0015    GGET     0   1      ; "assert"
0016    TGETS    0   0   2  ; "Equals"
0017    KSTR     1   3      ; "file"
0018    GGET     2   4      ; "lfs"
0019    TGETS    2   2   5  ; "attributes"
0020    UGET     3   0      ; d
0021    TGETS    3   3   3  ; "file"
0022    KSTR     4   7      ; ".old.1"
0023    CAT      3   3   4
0024    KSTR     4   6      ; "mode"
0025    CALL     2   0   3
0026    CALLM    0   1   1
0027    UGET     0   0      ; d
0028    MOV      1   0
0029    TGETS    0   0   8  ; "close"
0030    CALL     0   1   2
0031    RET0     0   1

-- BYTECODE -- luadata_spec.lua:104-122
0001    GGET     0   0      ; "io"
0002    TGETS    0   0   1  ; "open"
0003    UGET     1   0      ; d
0004    TGETS    1   1   2  ; "file"
0005    KSTR     2   3      ; "w"
0006    CALL     0   2   3
0007    MOV      2   0
0008    TGETS    1   0   4  ; "write"
0009    KSTR     3   5      ; "bla bla bla"
0010    CALL     1   1   3
0011    MOV      2   0
0012    TGETS    1   0   6  ; "close"
0013    CALL     1   1   2
0014    UGET     1   1      ; Settings
0015    MOV      2   1
0016    TGETS    1   1   1  ; "open"
0017    UGET     3   2      ; file
0018    CALL     1   2   3
0019    USETV    0   1      ; d
0020    GGET     1   7      ; "assert"
0021    TGETS    1   1   8  ; "are"
0022    TGETS    1   1   9  ; "not_equal"
0023    KSTR     2   2      ; "file"
0024    GGET     3  10      ; "lfs"
0025    TGETS    3   3  11  ; "attributes"
0026    UGET     4   0      ; d
0027    TGETS    4   4   2  ; "file"
0028    KSTR     5  12      ; "mode"
0029    CALL     3   0   3
0030    CALLM    1   1   1
0031    GGET     1   7      ; "assert"
0032    TGETS    1   1  13  ; "Equals"
0033    KSTR     2   2      ; "file"
0034    GGET     3  10      ; "lfs"
0035    TGETS    3   3  11  ; "attributes"
0036    UGET     4   0      ; d
0037    TGETS    4   4   2  ; "file"
0038    KSTR     5  14      ; ".old.2"
0039    CAT      4   4   5
0040    KSTR     5  12      ; "mode"
0041    CALL     3   0   3
0042    CALLM    1   1   1
0043    GGET     1   7      ; "assert"
0044    TGETS    1   1  13  ; "Equals"
0045    KSTR     2  15      ; "a"
0046    UGET     3   0      ; d
0047    MOV      4   3
0048    TGETS    3   3  16  ; "readSetting"
0049    KSTR     5  15      ; "a"
0050    CALL     3   0   3
0051    CALLM    1   1   1
0052    UGET     1   0      ; d
0053    MOV      2   1
0054    TGETS    1   1  17  ; "saveSetting"
0055    KSTR     3  15      ; "a"
0056    KSTR     4  18      ; "b"
0057    CALL     1   1   4
0058    UGET     1   0      ; d
0059    MOV      2   1
0060    TGETS    1   1   6  ; "close"
0061    CALL     1   1   2
0062    GGET     1   7      ; "assert"
0063    TGETS    1   1  13  ; "Equals"
0064    KSTR     2   2      ; "file"
0065    GGET     3  10      ; "lfs"
0066    TGETS    3   3  11  ; "attributes"
0067    UGET     4   0      ; d
0068    TGETS    4   4   2  ; "file"
0069    KSTR     5  12      ; "mode"
0070    CALL     3   0   3
0071    CALLM    1   1   1
0072    GGET     1   7      ; "assert"
0073    TGETS    1   1  13  ; "Equals"
0074    KSTR     2   2      ; "file"
0075    GGET     3  10      ; "lfs"
0076    TGETS    3   3  11  ; "attributes"
0077    UGET     4   0      ; d
0078    TGETS    4   4   2  ; "file"
0079    KSTR     5  19      ; ".old.1"
0080    CAT      4   4   5
0081    KSTR     5  12      ; "mode"
0082    CALL     3   0   3
0083    CALLM    1   1   1
0084    RET0     0   1

-- BYTECODE -- luadata_spec.lua:123-143
0001    UGET     0   1      ; Settings
0002    MOV      1   0
0003    TGETS    0   0   0  ; "open"
0004    UGET     2   2      ; file
0005    CALL     0   2   3
0006    USETV    0   0      ; d
0007    GGET     0   1      ; "assert"
0008    TGETS    0   0   2  ; "Equals"
0009    KSTR     1   3      ; "b"
0010    UGET     2   0      ; d
0011    MOV      3   2
0012    TGETS    2   2   4  ; "readSetting"
0013    KSTR     4   5      ; "a"
0014    CALL     2   0   3
0015    CALLM    0   1   1
0016    GGET     0   6      ; "io"
0017    TGETS    0   0   0  ; "open"
0018    UGET     1   0      ; d
0019    TGETS    1   1   7  ; "file"
0020    KSTR     2   8      ; "w"
0021    CALL     0   2   3
0022    MOV      2   0
0023    TGETS    1   0   9  ; "write"
0024    KSTR     3  10      ; "bla bla bla"
0025    CALL     1   1   3
0026    MOV      2   0
0027    TGETS    1   0  11  ; "close"
0028    CALL     1   1   2
0029    UGET     1   1      ; Settings
0030    MOV      2   1
0031    TGETS    1   1   0  ; "open"
0032    UGET     3   2      ; file
0033    CALL     1   2   3
0034    USETV    0   1      ; d
0035    GGET     1   1      ; "assert"
0036    TGETS    1   1  12  ; "are"
0037    TGETS    1   1  13  ; "not_equal"
0038    KSTR     2   7      ; "file"
0039    GGET     3  14      ; "lfs"
0040    TGETS    3   3  15  ; "attributes"
0041    UGET     4   0      ; d
0042    TGETS    4   4   7  ; "file"
0043    KSTR     5  16      ; "mode"
0044    CALL     3   0   3
0045    CALLM    1   1   1
0046    GGET     1   1      ; "assert"
0047    TGETS    1   1   2  ; "Equals"
0048    KSTR     2   7      ; "file"
0049    GGET     3  14      ; "lfs"
0050    TGETS    3   3  15  ; "attributes"
0051    UGET     4   0      ; d
0052    TGETS    4   4   7  ; "file"
0053    KSTR     5  17      ; ".old.2"
0054    CAT      4   4   5
0055    KSTR     5  16      ; "mode"
0056    CALL     3   0   3
0057    CALLM    1   1   1
0058    GGET     1   1      ; "assert"
0059    TGETS    1   1   2  ; "Equals"
0060    KSTR     2   5      ; "a"
0061    UGET     3   0      ; d
0062    MOV      4   3
0063    TGETS    3   3   4  ; "readSetting"
0064    KSTR     5   5      ; "a"
0065    CALL     3   0   3
0066    CALLM    1   1   1
0067    UGET     1   0      ; d
0068    MOV      2   1
0069    TGETS    1   1  11  ; "close"
0070    CALL     1   1   2
0071    GGET     1   1      ; "assert"
0072    TGETS    1   1   2  ; "Equals"
0073    KSTR     2   7      ; "file"
0074    GGET     3  14      ; "lfs"
0075    TGETS    3   3  15  ; "attributes"
0076    UGET     4   0      ; d
0077    TGETS    4   4   7  ; "file"
0078    KSTR     5  16      ; "mode"
0079    CALL     3   0   3
0080    CALLM    1   1   1
0081    GGET     1   1      ; "assert"
0082    TGETS    1   1   2  ; "Equals"
0083    KSTR     2   7      ; "file"
0084    GGET     3  14      ; "lfs"
0085    TGETS    3   3  15  ; "attributes"
0086    UGET     4   0      ; d
0087    TGETS    4   4   7  ; "file"
0088    KSTR     5  17      ; ".old.2"
0089    CAT      4   4   5
0090    KSTR     5  16      ; "mode"
0091    CALL     3   0   3
0092    CALLM    1   1   1
0093    RET0     0   1

-- BYTECODE -- luadata_spec.lua:90-144
0001    KSTR     0   0      ; "dummy-test-file"
0002    UGET     1   0      ; Settings
0003    MOV      2   1
0004    TGETS    1   1   1  ; "open"
0005    MOV      3   0
0006    CALL     1   2   3
0007    GGET     2   2      ; "it"
0008    KSTR     3   3      ; "should generate data file"
0009    FNEW     4   4      ; luadata_spec.lua:93
0010    CALL     2   1   3
0011    GGET     2   2      ; "it"
0012    KSTR     3   5      ; "should generate backup data file on flus"~
0013    FNEW     4   6      ; luadata_spec.lua:97
0014    CALL     2   1   3
0015    GGET     2   2      ; "it"
0016    KSTR     3   7      ; "should remove garbage data file"
0017    FNEW     4   8      ; luadata_spec.lua:104
0018    CALL     2   1   3
0019    GGET     2   2      ; "it"
0020    KSTR     3   9      ; "should open backup data file after garba"~
0021    FNEW     4  10      ; luadata_spec.lua:123
0022    CALL     2   1   3
0023    UCLO     0 => 0024
0024 => RET0     0   1

-- BYTECODE -- luadata_spec.lua:1-145
0001    KPRI     0   0
0002    GGET     1   0      ; "setup"
0003    FNEW     2   1      ; luadata_spec.lua:3
0004    CALL     1   1   2
0005    GGET     1   2      ; "it"
0006    KSTR     2   3      ; "should handle undefined keys"
0007    FNEW     3   4      ; luadata_spec.lua:8
0008    CALL     1   1   3
0009    GGET     1   2      ; "it"
0010    KSTR     2   5      ; "should flip bool values"
0011    FNEW     3   6      ; luadata_spec.lua:20
0012    CALL     1   1   3
0013    GGET     1   2      ; "it"
0014    KSTR     2   7      ; "should create child settings"
0015    FNEW     3   8      ; luadata_spec.lua:43
0016    CALL     1   1   3
0017    GGET     1   9      ; "describe"
0018    KSTR     2  10      ; "table wrapper"
0019    FNEW     3  11      ; luadata_spec.lua:69
0020    CALL     1   1   3
0021    GGET     1   9      ; "describe"
0022    KSTR     2  12      ; "backup data file"
0023    FNEW     3  13      ; luadata_spec.lua:90
0024    CALL     1   1   3
0025    UCLO     0 => 0026
0026 => RET0     0   1

-- BYTECODE -- luadata_spec.lua:0-146
0001    GGET     0   0      ; "describe"
0002    KSTR     1   1      ; "luadata module"
0003    FNEW     2   2      ; luadata_spec.lua:1
0004    CALL     0   1   3
0005    RET0     0   1

