
main <./plugins/newsdownloader.koplugin/luahttpdownloadbackend.lua:0,0> (16 instructions, 64 bytes at 0x7fdcf2406920)
0+ params, 4 slots, 0 upvalues, 3 locals, 5 constants, 2 functions
	1	[1]	GETGLOBAL	0 -1	; require
	2	[1]	LOADK    	1 -2	; "logger"
	3	[1]	CALL     	0 2 2
	4	[2]	GETGLOBAL	1 -1	; require
	5	[2]	LOADK    	2 -3	; "http.request"
	6	[2]	CALL     	1 2 2
	7	[5]	NEWTABLE 	2 0 0
	8	[12]	CLOSURE  	3 0	; 0x7fdcf2406d60
	9	[12]	MOVE     	0 1
	10	[12]	MOVE     	0 0
	11	[7]	SETTABLE 	2 -4 3	; "getResponseAsString" -
	12	[18]	CLOSURE  	3 1	; 0x7fdcf2406ca0
	13	[18]	MOVE     	0 1
	14	[14]	SETTABLE 	2 -5 3	; "download" -
	15	[20]	RETURN   	2 2
	16	[20]	RETURN   	0 1

function <./plugins/newsdownloader.koplugin/luahttpdownloadbackend.lua:7,12> (19 instructions, 76 bytes at 0x7fdcf2406d60)
2 params, 8 slots, 2 upvalues, 5 locals, 6 constants, 0 functions
	1	[8]	GETGLOBAL	2 -1	; assert
	2	[8]	GETUPVAL 	3 0	; http_request
	3	[8]	GETTABLE 	3 3 -2	; "new_from_uri"
	4	[8]	MOVE     	4 1
	5	[8]	CALL     	3 2 2
	6	[8]	SELF     	3 3 -3	; "go"
	7	[8]	CALL     	3 2 0
	8	[8]	CALL     	2 0 3
	9	[9]	GETGLOBAL	4 -1	; assert
	10	[9]	SELF     	5 3 -4	; "get_body_as_string"
	11	[9]	CALL     	5 2 0
	12	[9]	CALL     	4 0 2
	13	[10]	GETUPVAL 	5 1	; logger
	14	[10]	GETTABLE 	5 5 -5	; "dbg"
	15	[10]	LOADK    	6 -6	; "Response body :"
	16	[10]	MOVE     	7 4
	17	[10]	CALL     	5 3 1
	18	[11]	RETURN   	4 2
	19	[12]	RETURN   	0 1

function <./plugins/newsdownloader.koplugin/luahttpdownloadbackend.lua:14,18> (14 instructions, 56 bytes at 0x7fdcf2406ca0)
3 params, 8 slots, 1 upvalue, 5 locals, 5 constants, 0 functions
	1	[15]	GETGLOBAL	3 -1	; assert
	2	[15]	GETUPVAL 	4 0	; http_request
	3	[15]	GETTABLE 	4 4 -2	; "new_from_uri"
	4	[15]	MOVE     	5 1
	5	[15]	CALL     	4 2 2
	6	[15]	SELF     	4 4 -3	; "go"
	7	[15]	CALL     	4 2 0
	8	[15]	CALL     	3 0 3
	9	[16]	SELF     	5 4 -4	; "save_body_to_file"
	10	[16]	MOVE     	7 2
	11	[16]	CALL     	5 3 1
	12	[17]	SELF     	5 4 -5	; "shutdown"
	13	[17]	CALL     	5 2 1
	14	[18]	RETURN   	0 1
