
main <./plugins/statistics.koplugin/main.lua:0,0> (496 instructions, 1984 bytes at 0x7fcdebc068d0)
0+ params, 40 slots, 0 upvalues, 39 locals, 147 constants, 53 functions
	1	[1]	GETGLOBAL	0 -1	; require
	2	[1]	LOADK    	1 -2	; "ui/bidi"
	3	[1]	CALL     	0 2 2
	4	[2]	GETGLOBAL	1 -1	; require
	5	[2]	LOADK    	2 -3	; "ui/widget/bookstatuswidget"
	6	[2]	CALL     	1 2 2
	7	[3]	GETGLOBAL	2 -1	; require
	8	[3]	LOADK    	3 -4	; "ui/widget/confirmbox"
	9	[3]	CALL     	2 2 2
	10	[4]	GETGLOBAL	3 -1	; require
	11	[4]	LOADK    	4 -5	; "datastorage"
	12	[4]	CALL     	3 2 2
	13	[5]	GETGLOBAL	4 -1	; require
	14	[5]	LOADK    	5 -6	; "device"
	15	[5]	CALL     	4 2 2
	16	[6]	GETGLOBAL	5 -1	; require
	17	[6]	LOADK    	6 -7	; "docsettings"
	18	[6]	CALL     	5 2 2
	19	[7]	GETGLOBAL	6 -1	; require
	20	[7]	LOADK    	7 -8	; "ui/widget/infomessage"
	21	[7]	CALL     	6 2 2
	22	[8]	GETGLOBAL	7 -1	; require
	23	[8]	LOADK    	8 -9	; "ui/widget/keyvaluepage"
	24	[8]	CALL     	7 2 2
	25	[9]	GETGLOBAL	8 -1	; require
	26	[9]	LOADK    	9 -10	; "apps/reader/modules/readerfooter"
	27	[9]	CALL     	8 2 2
	28	[10]	GETGLOBAL	9 -1	; require
	29	[10]	LOADK    	10 -11	; "readerprogress"
	30	[10]	CALL     	9 2 2
	31	[11]	GETGLOBAL	10 -1	; require
	32	[11]	LOADK    	11 -12	; "readhistory"
	33	[11]	CALL     	10 2 2
	34	[12]	GETGLOBAL	11 -1	; require
	35	[12]	LOADK    	12 -13	; "ui/screensaver"
	36	[12]	CALL     	11 2 2
	37	[13]	GETGLOBAL	12 -1	; require
	38	[13]	LOADK    	13 -14	; "lua-ljsqlite3/init"
	39	[13]	CALL     	12 2 2
	40	[14]	GETGLOBAL	13 -1	; require
	41	[14]	LOADK    	14 -15	; "ui/timeval"
	42	[14]	CALL     	13 2 2
	43	[15]	GETGLOBAL	14 -1	; require
	44	[15]	LOADK    	15 -16	; "ui/uimanager"
	45	[15]	CALL     	14 2 2
	46	[16]	GETGLOBAL	15 -1	; require
	47	[16]	LOADK    	16 -17	; "ui/widget/widget"
	48	[16]	CALL     	15 2 2
	49	[17]	GETGLOBAL	16 -1	; require
	50	[17]	LOADK    	17 -18	; "libs/libkoreader-lfs"
	51	[17]	CALL     	16 2 2
	52	[18]	GETGLOBAL	17 -1	; require
	53	[18]	LOADK    	18 -19	; "logger"
	54	[18]	CALL     	17 2 2
	55	[19]	GETGLOBAL	18 -1	; require
	56	[19]	LOADK    	19 -20	; "util"
	57	[19]	CALL     	18 2 2
	58	[20]	GETGLOBAL	19 -1	; require
	59	[20]	LOADK    	20 -21	; "gettext"
	60	[20]	CALL     	19 2 2
	61	[21]	GETGLOBAL	20 -1	; require
	62	[21]	LOADK    	21 -22	; "ffi/util"
	63	[21]	CALL     	20 2 2
	64	[21]	GETTABLE 	20 20 -23	; "joinPath"
	65	[22]	GETGLOBAL	21 -1	; require
	66	[22]	LOADK    	22 -6	; "device"
	67	[22]	CALL     	21 2 2
	68	[22]	GETTABLE 	21 21 -24	; "screen"
	69	[23]	GETTABLE 	22 19 -25	; "ngettext"
	70	[24]	GETGLOBAL	23 -1	; require
	71	[24]	LOADK    	24 -22	; "ffi/util"
	72	[24]	CALL     	23 2 2
	73	[24]	GETTABLE 	23 23 -26	; "template"
	74	[26]	SELF     	24 3 -27	; "getDataDir"
	75	[26]	CALL     	24 2 2
	76	[26]	LOADK    	25 -28	; "/statistics/"
	77	[26]	CONCAT   	24 24 25
	78	[27]	SELF     	25 3 -29	; "getSettingsDir"
	79	[27]	CALL     	25 2 2
	80	[27]	LOADK    	26 -30	; "/statistics.sqlite3"
	81	[27]	CONCAT   	25 25 26
	82	[28]	LOADK    	26 -31	; 50
	83	[29]	LOADK    	27 -32	; 5
	84	[30]	LOADK    	28 -33	; 120
	85	[31]	LOADK    	29 -34	; 2
	86	[32]	LOADK    	30 -35	; 3
	87	[34]	SELF     	31 15 -36	; "extend"
	88	[34]	NEWTABLE 	33 0 18
	89	[35]	SETTABLE 	33 -37 -38	; "name" "statistics"
	90	[36]	SETTABLE 	33 -39 27	; "page_min_read_sec" -
	91	[37]	SETTABLE 	33 -40 28	; "page_max_read_sec" -
	92	[38]	SETTABLE 	33 -41 29	; "calendar_start_day_of_week" -
	93	[39]	SETTABLE 	33 -42 30	; "calendar_nb_book_spans" -
	94	[40]	SETTABLE 	33 -43 -44	; "calendar_show_histogram" true
	95	[41]	SETTABLE 	33 -45 -46	; "calendar_browse_future_months" false
	96	[42]	SETTABLE 	33 -47 -48	; "start_current_period" 0
	97	[43]	SETTABLE 	33 -49 -48	; "curr_page" 0
	98	[44]	SETTABLE 	33 -50 -51	; "id_curr_book" nil
	99	[45]	SETTABLE 	33 -52 -48	; "curr_total_time" 0
	100	[46]	SETTABLE 	33 -53 -48	; "curr_total_pages" 0
	101	[47]	SETTABLE 	33 -54 -51	; "is_enabled" nil
	102	[48]	SETTABLE 	33 -55 -51	; "convert_to_db" nil
	103	[49]	SETTABLE 	33 -56 -48	; "total_read_pages" 0
	104	[50]	SETTABLE 	33 -57 -48	; "total_read_time" 0
	105	[51]	SETTABLE 	33 -58 -51	; "avg_time" nil
	106	[52]	NEWTABLE 	34 0 0
	107	[52]	SETTABLE 	33 -59 34	; "pages_stats" -
	108	[53]	NEWTABLE 	34 0 10
	109	[54]	SETTABLE 	34 -61 -62	; "title" ""
	110	[55]	SETTABLE 	34 -63 -62	; "authors" ""
	111	[56]	SETTABLE 	34 -64 -62	; "language" ""
	112	[57]	SETTABLE 	34 -65 -62	; "series" ""
	113	[58]	NEWTABLE 	35 0 0
	114	[58]	SETTABLE 	34 -66 35	; "performance_in_pages" -
	115	[59]	SETTABLE 	34 -67 -48	; "total_time_in_sec" 0
	116	[60]	SETTABLE 	34 -68 -48	; "highlights" 0
	117	[61]	SETTABLE 	34 -69 -48	; "notes" 0
	118	[62]	SETTABLE 	34 -70 -48	; "pages" 0
	119	[63]	SETTABLE 	34 -71 -51	; "md5" nil
	120	[64]	SETTABLE 	33 -60 34	; "data" -
	121	[34]	CALL     	31 3 2
	122	[67]	NEWTABLE 	32 7 0
	123	[67]	LOADK    	33 -72	; "Sun"
	124	[67]	LOADK    	34 -73	; "Mon"
	125	[67]	LOADK    	35 -74	; "Tue"
	126	[67]	LOADK    	36 -75	; "Wed"
	127	[67]	LOADK    	37 -76	; "Thu"
	128	[67]	LOADK    	38 -77	; "Fri"
	129	[67]	LOADK    	39 -78	; "Sat"
	130	[67]	SETLIST  	32 7 1	; 1
	131	[69]	NEWTABLE 	33 0 7
	132	[70]	MOVE     	34 19
	133	[70]	LOADK    	35 -73	; "Mon"
	134	[70]	CALL     	34 2 2
	135	[70]	SETTABLE 	33 -73 34	; "Mon" -
	136	[71]	MOVE     	34 19
	137	[71]	LOADK    	35 -74	; "Tue"
	138	[71]	CALL     	34 2 2
	139	[71]	SETTABLE 	33 -74 34	; "Tue" -
	140	[72]	MOVE     	34 19
	141	[72]	LOADK    	35 -75	; "Wed"
	142	[72]	CALL     	34 2 2
	143	[72]	SETTABLE 	33 -75 34	; "Wed" -
	144	[73]	MOVE     	34 19
	145	[73]	LOADK    	35 -76	; "Thu"
	146	[73]	CALL     	34 2 2
	147	[73]	SETTABLE 	33 -76 34	; "Thu" -
	148	[74]	MOVE     	34 19
	149	[74]	LOADK    	35 -77	; "Fri"
	150	[74]	CALL     	34 2 2
	151	[74]	SETTABLE 	33 -77 34	; "Fri" -
	152	[75]	MOVE     	34 19
	153	[75]	LOADK    	35 -78	; "Sat"
	154	[75]	CALL     	34 2 2
	155	[75]	SETTABLE 	33 -78 34	; "Sat" -
	156	[76]	MOVE     	34 19
	157	[76]	LOADK    	35 -72	; "Sun"
	158	[76]	CALL     	34 2 2
	159	[76]	SETTABLE 	33 -72 34	; "Sun" -
	160	[79]	NEWTABLE 	34 0 7
	161	[80]	MOVE     	35 19
	162	[80]	LOADK    	36 -79	; "Monday"
	163	[80]	CALL     	35 2 2
	164	[80]	SETTABLE 	34 -73 35	; "Mon" -
	165	[81]	MOVE     	35 19
	166	[81]	LOADK    	36 -80	; "Tuesday"
	167	[81]	CALL     	35 2 2
	168	[81]	SETTABLE 	34 -74 35	; "Tue" -
	169	[82]	MOVE     	35 19
	170	[82]	LOADK    	36 -81	; "Wednesday"
	171	[82]	CALL     	35 2 2
	172	[82]	SETTABLE 	34 -75 35	; "Wed" -
	173	[83]	MOVE     	35 19
	174	[83]	LOADK    	36 -82	; "Thursday"
	175	[83]	CALL     	35 2 2
	176	[83]	SETTABLE 	34 -76 35	; "Thu" -
	177	[84]	MOVE     	35 19
	178	[84]	LOADK    	36 -83	; "Friday"
	179	[84]	CALL     	35 2 2
	180	[84]	SETTABLE 	34 -77 35	; "Fri" -
	181	[85]	MOVE     	35 19
	182	[85]	LOADK    	36 -84	; "Saturday"
	183	[85]	CALL     	35 2 2
	184	[85]	SETTABLE 	34 -78 35	; "Sat" -
	185	[86]	MOVE     	35 19
	186	[86]	LOADK    	36 -85	; "Sunday"
	187	[86]	CALL     	35 2 2
	188	[86]	SETTABLE 	34 -72 35	; "Sun" -
	189	[89]	NEWTABLE 	35 0 12
	190	[90]	MOVE     	36 19
	191	[90]	LOADK    	37 -86	; "January"
	192	[90]	CALL     	36 2 2
	193	[90]	SETTABLE 	35 -86 36	; "January" -
	194	[91]	MOVE     	36 19
	195	[91]	LOADK    	37 -87	; "February"
	196	[91]	CALL     	36 2 2
	197	[91]	SETTABLE 	35 -87 36	; "February" -
	198	[92]	MOVE     	36 19
	199	[92]	LOADK    	37 -88	; "March"
	200	[92]	CALL     	36 2 2
	201	[92]	SETTABLE 	35 -88 36	; "March" -
	202	[93]	MOVE     	36 19
	203	[93]	LOADK    	37 -89	; "April"
	204	[93]	CALL     	36 2 2
	205	[93]	SETTABLE 	35 -89 36	; "April" -
	206	[94]	MOVE     	36 19
	207	[94]	LOADK    	37 -90	; "May"
	208	[94]	CALL     	36 2 2
	209	[94]	SETTABLE 	35 -90 36	; "May" -
	210	[95]	MOVE     	36 19
	211	[95]	LOADK    	37 -91	; "June"
	212	[95]	CALL     	36 2 2
	213	[95]	SETTABLE 	35 -91 36	; "June" -
	214	[96]	MOVE     	36 19
	215	[96]	LOADK    	37 -92	; "July"
	216	[96]	CALL     	36 2 2
	217	[96]	SETTABLE 	35 -92 36	; "July" -
	218	[97]	MOVE     	36 19
	219	[97]	LOADK    	37 -93	; "August"
	220	[97]	CALL     	36 2 2
	221	[97]	SETTABLE 	35 -93 36	; "August" -
	222	[98]	MOVE     	36 19
	223	[98]	LOADK    	37 -94	; "September"
	224	[98]	CALL     	36 2 2
	225	[98]	SETTABLE 	35 -94 36	; "September" -
	226	[99]	MOVE     	36 19
	227	[99]	LOADK    	37 -95	; "October"
	228	[99]	CALL     	36 2 2
	229	[99]	SETTABLE 	35 -95 36	; "October" -
	230	[100]	MOVE     	36 19
	231	[100]	LOADK    	37 -96	; "November"
	232	[100]	CALL     	36 2 2
	233	[100]	SETTABLE 	35 -96 36	; "November" -
	234	[101]	MOVE     	36 19
	235	[101]	LOADK    	37 -97	; "December"
	236	[101]	CALL     	36 2 2
	237	[101]	SETTABLE 	35 -97 36	; "December" -
	238	[106]	CLOSURE  	36 0	; 0x7fcdebc078c0
	239	[104]	SETTABLE 	31 -98 36	; "isDocless" -
	240	[183]	CLOSURE  	36 1	; 0x7fcdebc07ea0
	241	[183]	MOVE     	0 13
	242	[183]	MOVE     	0 1
	243	[183]	MOVE     	0 8
	244	[183]	MOVE     	0 11
	245	[183]	MOVE     	0 9
	246	[183]	MOVE     	0 7
	247	[183]	MOVE     	0 19
	248	[108]	SETTABLE 	31 -99 36	; "init" -
	249	[215]	CLOSURE  	36 2	; 0x7fcdebc09dd0
	250	[185]	SETTABLE 	31 -100 36	; "initData" -
	251	[254]	CLOSURE  	36 3	; 0x7fcdebc09f70
	252	[254]	MOVE     	0 12
	253	[254]	MOVE     	0 25
	254	[217]	SETTABLE 	31 -101 36	; "getStatsBookStatus" -
	255	[312]	CLOSURE  	36 4	; 0x7fcdebc0a120
	256	[312]	MOVE     	0 12
	257	[312]	MOVE     	0 25
	258	[312]	MOVE     	0 14
	259	[312]	MOVE     	0 2
	260	[312]	MOVE     	0 23
	261	[312]	MOVE     	0 19
	262	[312]	MOVE     	0 0
	263	[312]	MOVE     	0 6
	264	[312]	MOVE     	0 10
	265	[312]	MOVE     	0 18
	266	[256]	SETTABLE 	31 -102 36	; "checkInitDatabase" -
	267	[334]	CLOSURE  	36 5	; 0x7fcdebc0b0a0
	268	[314]	SETTABLE 	31 -103 36	; "partialMd5" -
	269	[380]	CLOSURE  	36 6	; 0x7fcdebc0c0c0
	270	[380]	MOVE     	0 4
	271	[336]	SETTABLE 	31 -104 36	; "createDB" -
	272	[481]	CLOSURE  	36 7	; 0x7fcdebc0a750
	273	[481]	MOVE     	0 18
	274	[481]	MOVE     	0 17
	275	[382]	SETTABLE 	31 -105 36	; "addBookStatToDB" -
	276	[534]	CLOSURE  	36 8	; 0x7fcdebc0c780
	277	[534]	MOVE     	0 10
	278	[534]	MOVE     	0 5
	279	[534]	MOVE     	0 17
	280	[534]	MOVE     	0 16
	281	[534]	MOVE     	0 24
	282	[483]	SETTABLE 	31 -106 36	; "migrateToDB" -
	283	[572]	CLOSURE  	36 9	; 0x7fcdebc0cec0
	284	[572]	MOVE     	0 12
	285	[572]	MOVE     	0 25
	286	[572]	MOVE     	0 13
	287	[536]	SETTABLE 	31 -107 36	; "getIdBookDB" -
	288	[632]	CLOSURE  	36 10	; 0x7fcdebc0d4b0
	289	[632]	MOVE     	0 13
	290	[632]	MOVE     	0 18
	291	[632]	MOVE     	0 12
	292	[632]	MOVE     	0 25
	293	[574]	SETTABLE 	31 -108 36	; "insertDB" -
	294	[658]	CLOSURE  	36 11	; 0x7fcdebc0d5e0
	295	[658]	MOVE     	0 12
	296	[658]	MOVE     	0 25
	297	[634]	SETTABLE 	31 -109 36	; "getPageTimeTotalStats" -
	298	[667]	CLOSURE  	36 12	; 0x7fcdebc0e210
	299	[660]	SETTABLE 	31 -110 36	; "getBookProperties" -
	300	[695]	CLOSURE  	36 13	; 0x7fcdebc0e690
	301	[695]	MOVE     	0 19
	302	[695]	MOVE     	0 13
	303	[669]	SETTABLE 	31 -111 36	; "getStatisticEnabledMenuItem" -
	304	[878]	CLOSURE  	36 14	; 0x7fcdebc0f200
	305	[878]	MOVE     	0 19
	306	[878]	MOVE     	0 23
	307	[878]	MOVE     	0 27
	308	[878]	MOVE     	0 28
	309	[878]	MOVE     	0 14
	310	[878]	MOVE     	0 34
	311	[878]	MOVE     	0 32
	312	[878]	MOVE     	0 21
	313	[878]	MOVE     	0 30
	314	[878]	MOVE     	0 7
	315	[878]	MOVE     	0 9
	316	[878]	MOVE     	0 6
	317	[697]	SETTABLE 	31 -112 36	; "addToMainMenu" -
	318	[1019]	CLOSURE  	36 15	; 0x7fcdebc14e60
	319	[1019]	MOVE     	0 7
	320	[1019]	MOVE     	0 19
	321	[1019]	MOVE     	0 14
	322	[880]	SETTABLE 	31 -113 36	; "statMenu" -
	323	[1048]	CLOSURE  	36 16	; 0x7fcdebc18c10
	324	[1048]	MOVE     	0 12
	325	[1048]	MOVE     	0 25
	326	[1021]	SETTABLE 	31 -114 36	; "getTodayBookStats" -
	327	[1072]	CLOSURE  	36 17	; 0x7fcdebc08820
	328	[1072]	MOVE     	0 12
	329	[1072]	MOVE     	0 25
	330	[1050]	SETTABLE 	31 -115 36	; "getCurrentBookStats" -
	331	[1134]	CLOSURE  	36 18	; 0x7fcdebc14470
	332	[1134]	MOVE     	0 12
	333	[1134]	MOVE     	0 25
	334	[1134]	MOVE     	0 19
	335	[1134]	MOVE     	0 18
	336	[1134]	MOVE     	0 23
	337	[1134]	MOVE     	0 22
	338	[1074]	SETTABLE 	31 -116 36	; "getCurrentStat" -
	339	[1219]	CLOSURE  	36 19	; 0x7fcdebc11ba0
	340	[1219]	MOVE     	0 12
	341	[1219]	MOVE     	0 25
	342	[1219]	MOVE     	0 19
	343	[1219]	MOVE     	0 18
	344	[1219]	MOVE     	0 14
	345	[1219]	MOVE     	0 7
	346	[1136]	SETTABLE 	31 -117 36	; "getBookStat" -
	347	[1239]	CLOSURE  	36 20	; 0x7fcdebc13900
	348	[1259]	CLOSURE  	37 21	; 0x7fcdebc14ae0
	349	[1279]	CLOSURE  	38 22	; 0x7fcdebc117d0
	350	[1306]	CLOSURE  	39 23	; 0x7fcdebc17ad0
	351	[1306]	MOVE     	0 14
	352	[1306]	MOVE     	0 7
	353	[1306]	MOVE     	0 23
	354	[1306]	MOVE     	0 19
	355	[1281]	SETTABLE 	31 -118 39	; "callbackMonthly" -
	356	[1333]	CLOSURE  	39 24	; 0x7fcdebc184e0
	357	[1333]	MOVE     	0 14
	358	[1333]	MOVE     	0 7
	359	[1333]	MOVE     	0 23
	360	[1333]	MOVE     	0 19
	361	[1308]	SETTABLE 	31 -119 39	; "callbackWeekly" -
	362	[1348]	CLOSURE  	39 25	; 0x7fcdebc0fff0
	363	[1348]	MOVE     	0 14
	364	[1348]	MOVE     	0 7
	365	[1335]	SETTABLE 	31 -120 39	; "callbackDaily" -
	366	[1446]	CLOSURE  	39 26	; 0x7fcdebc1a640
	367	[1446]	MOVE     	0 36
	368	[1446]	MOVE     	0 37
	369	[1446]	MOVE     	0 38
	370	[1446]	MOVE     	0 12
	371	[1446]	MOVE     	0 25
	372	[1446]	MOVE     	0 33
	373	[1446]	MOVE     	0 23
	374	[1446]	MOVE     	0 19
	375	[1446]	MOVE     	0 35
	376	[1446]	MOVE     	0 18
	377	[1356]	SETTABLE 	31 -121 39	; "getDatesFromAll" -
	378	[1495]	CLOSURE  	39 27	; 0x7fcdebc1b730
	379	[1495]	MOVE     	0 12
	380	[1495]	MOVE     	0 25
	381	[1495]	MOVE     	0 23
	382	[1495]	MOVE     	0 19
	383	[1495]	MOVE     	0 18
	384	[1495]	MOVE     	0 14
	385	[1495]	MOVE     	0 7
	386	[1448]	SETTABLE 	31 -122 39	; "getDaysFromPeriod" -
	387	[1536]	CLOSURE  	39 28	; 0x7fcdebc1c770
	388	[1536]	MOVE     	0 12
	389	[1536]	MOVE     	0 25
	390	[1536]	MOVE     	0 23
	391	[1536]	MOVE     	0 19
	392	[1536]	MOVE     	0 18
	393	[1536]	MOVE     	0 14
	394	[1536]	MOVE     	0 7
	395	[1497]	SETTABLE 	31 -123 39	; "getBooksFromPeriod" -
	396	[1579]	CLOSURE  	39 29	; 0x7fcdebc1cfe0
	397	[1579]	MOVE     	0 12
	398	[1579]	MOVE     	0 25
	399	[1538]	SETTABLE 	31 -124 39	; "getReadingProgressStats" -
	400	[1605]	CLOSURE  	39 30	; 0x7fcdebc1cf60
	401	[1605]	MOVE     	0 12
	402	[1605]	MOVE     	0 25
	403	[1605]	MOVE     	0 23
	404	[1605]	MOVE     	0 19
	405	[1605]	MOVE     	0 18
	406	[1581]	SETTABLE 	31 -125 39	; "getDatesForBook" -
	407	[1672]	CLOSURE  	39 31	; 0x7fcdebc1e7a0
	408	[1672]	MOVE     	0 12
	409	[1672]	MOVE     	0 25
	410	[1672]	MOVE     	0 18
	411	[1672]	MOVE     	0 14
	412	[1672]	MOVE     	0 7
	413	[1672]	MOVE     	0 23
	414	[1672]	MOVE     	0 19
	415	[1607]	SETTABLE 	31 -126 39	; "getTotalStats" -
	416	[1698]	CLOSURE  	39 32	; 0x7fcdebc1f820
	417	[1698]	MOVE     	0 19
	418	[1698]	MOVE     	0 23
	419	[1698]	MOVE     	0 22
	420	[1674]	SETTABLE 	31 -127 39	; "genResetBookSubItemTable" -
	421	[1774]	CLOSURE  	39 33	; 0x7fcdebc20050
	422	[1774]	MOVE     	0 12
	423	[1774]	MOVE     	0 25
	424	[1774]	MOVE     	0 18
	425	[1774]	MOVE     	0 14
	426	[1774]	MOVE     	0 2
	427	[1774]	MOVE     	0 23
	428	[1774]	MOVE     	0 19
	429	[1774]	MOVE     	0 7
	430	[1700]	SETTABLE 	31 -128 39	; "resetBook" -
	431	[1793]	CLOSURE  	39 34	; 0x7fcdebc207e0
	432	[1793]	MOVE     	0 12
	433	[1793]	MOVE     	0 25
	434	[1776]	SETTABLE 	31 -129 39	; "deleteBook" -
	435	[1845]	CLOSURE  	39 35	; 0x7fcdebc21a40
	436	[1845]	MOVE     	0 14
	437	[1845]	MOVE     	0 2
	438	[1845]	MOVE     	0 23
	439	[1845]	MOVE     	0 22
	440	[1845]	MOVE     	0 19
	441	[1845]	MOVE     	0 12
	442	[1845]	MOVE     	0 25
	443	[1845]	MOVE     	0 17
	444	[1845]	MOVE     	0 6
	445	[1795]	SETTABLE 	31 -130 39	; "deleteBooksByTotalDuration" -
	446	[1852]	CLOSURE  	39 36	; 0x7fcdebc21c00
	447	[1848]	SETTABLE 	31 -131 39	; "onPosUpdate" -
	448	[1888]	CLOSURE  	39 37	; 0x7fcdebc22dd0
	449	[1888]	MOVE     	0 13
	450	[1888]	MOVE     	0 18
	451	[1888]	MOVE     	0 26
	452	[1854]	SETTABLE 	31 -132 39	; "onPageUpdate" -
	453	[1903]	CLOSURE  	39 38	; 0x7fcdebc233d0
	454	[1903]	MOVE     	0 20
	455	[1903]	MOVE     	0 16
	456	[1891]	SETTABLE 	31 -133 39	; "importFromFile" -
	457	[1910]	CLOSURE  	39 39	; 0x7fcdebc22ed0
	458	[1905]	SETTABLE 	31 -134 39	; "onCloseDocument" -
	459	[1915]	CLOSURE  	39 40	; 0x7fcdebc24410
	460	[1912]	SETTABLE 	31 -135 39	; "onAddHighlight" -
	461	[1922]	CLOSURE  	39 41	; 0x7fcdebc244a0
	462	[1917]	SETTABLE 	31 -136 39	; "onDelHighlight" -
	463	[1926]	CLOSURE  	39 42	; 0x7fcdebc24620
	464	[1924]	SETTABLE 	31 -137 39	; "onAddNote" -
	465	[1933]	CLOSURE  	39 43	; 0x7fcdebc248c0
	466	[1928]	SETTABLE 	31 -138 39	; "onSaveSettings" -
	467	[1941]	CLOSURE  	39 44	; 0x7fcdebc24f70
	468	[1936]	SETTABLE 	31 -139 39	; "onSuspend" -
	469	[1948]	CLOSURE  	39 45	; 0x7fcdebc25420
	470	[1948]	MOVE     	0 13
	471	[1944]	SETTABLE 	31 -140 39	; "onResume" -
	472	[1962]	CLOSURE  	39 46	; 0x7fcdebc25880
	473	[1950]	SETTABLE 	31 -141 39	; "saveSettings" -
	474	[1966]	CLOSURE  	39 47	; 0x7fcdebc25ee0
	475	[1964]	SETTABLE 	31 -142 39	; "onReadSettings" -
	476	[1972]	CLOSURE  	39 48	; 0x7fcdebc25f80
	477	[1968]	SETTABLE 	31 -143 39	; "onReaderReady" -
	478	[1987]	CLOSURE  	39 49	; 0x7fcdebc260f0
	479	[1987]	MOVE     	0 35
	480	[1987]	MOVE     	0 33
	481	[1987]	MOVE     	0 34
	482	[1974]	SETTABLE 	31 -144 39	; "getCalendarView" -
	483	[1999]	CLOSURE  	39 50	; 0x7fcdebc265f0
	484	[1999]	MOVE     	0 12
	485	[1999]	MOVE     	0 25
	486	[1990]	SETTABLE 	31 -145 39	; "getFirstTimestamp" -
	487	[2029]	CLOSURE  	39 51	; 0x7fcdebc26c90
	488	[2029]	MOVE     	0 12
	489	[2029]	MOVE     	0 25
	490	[2001]	SETTABLE 	31 -146 39	; "getReadingRatioPerHourByDay" -
	491	[2063]	CLOSURE  	39 52	; 0x7fcdebc271d0
	492	[2063]	MOVE     	0 12
	493	[2063]	MOVE     	0 25
	494	[2031]	SETTABLE 	31 -147 39	; "getReadBookByDay" -
	495	[2065]	RETURN   	31 2
	496	[2065]	RETURN   	0 1

function <./plugins/statistics.koplugin/main.lua:104,106> (11 instructions, 44 bytes at 0x7fcdebc078c0)
1 param, 2 slots, 0 upvalues, 1 local, 3 constants, 0 functions
	1	[105]	GETTABLE 	1 0 -1	; "ui"
	2	[105]	EQ       	1 1 -2	; - nil
	3	[105]	JMP      	5	; to 9
	4	[105]	GETTABLE 	1 0 -1	; "ui"
	5	[105]	GETTABLE 	1 1 -3	; "document"
	6	[105]	EQ       	1 1 -2	; - nil
	7	[105]	JMP      	1	; to 9
	8	[105]	LOADBOOL 	1 0 1
	9	[105]	LOADBOOL 	1 1 0
	10	[105]	RETURN   	1 2
	11	[106]	RETURN   	0 1

function <./plugins/statistics.koplugin/main.lua:108,183> (84 instructions, 336 bytes at 0x7fcdebc07ea0)
1 param, 5 slots, 7 upvalues, 3 locals, 33 constants, 6 functions
	1	[109]	SELF     	1 0 -1	; "isDocless"
	2	[109]	CALL     	1 2 2
	3	[109]	TEST     	1 0 1
	4	[109]	JMP      	6	; to 11
	5	[109]	GETTABLE 	1 0 -2	; "ui"
	6	[109]	GETTABLE 	1 1 -3	; "document"
	7	[109]	GETTABLE 	1 1 -4	; "is_pic"
	8	[109]	TEST     	1 0 0
	9	[109]	JMP      	1	; to 11
	10	[110]	RETURN   	0 1
	11	[112]	GETUPVAL 	1 0	; TimeVal
	12	[112]	SELF     	1 1 -6	; "now"
	13	[112]	CALL     	1 2 2
	14	[112]	GETTABLE 	1 1 -7	; "sec"
	15	[112]	SETTABLE 	0 -5 1	; "start_current_period" -
	16	[113]	NEWTABLE 	1 0 0
	17	[113]	SETTABLE 	0 -8 1	; "pages_stats" -
	18	[114]	GETGLOBAL	1 -9	; G_reader_settings
	19	[114]	SELF     	1 1 -10	; "readSetting"
	20	[114]	LOADK    	3 -11	; "statistics"
	21	[114]	CALL     	1 3 2
	22	[114]	TEST     	1 0 1
	23	[114]	JMP      	1	; to 25
	24	[114]	NEWTABLE 	1 0 0
	25	[115]	GETGLOBAL	2 -13	; tonumber
	26	[115]	GETTABLE 	3 1 -14	; "min_sec"
	27	[115]	CALL     	2 2 2
	28	[115]	SETTABLE 	0 -12 2	; "page_min_read_sec" -
	29	[116]	GETGLOBAL	2 -13	; tonumber
	30	[116]	GETTABLE 	3 1 -16	; "max_sec"
	31	[116]	CALL     	2 2 2
	32	[116]	SETTABLE 	0 -15 2	; "page_max_read_sec" -
	33	[117]	GETTABLE 	2 1 -17	; "calendar_start_day_of_week"
	34	[117]	SETTABLE 	0 -17 2	; "calendar_start_day_of_week" -
	35	[118]	GETTABLE 	2 1 -18	; "calendar_nb_book_spans"
	36	[118]	SETTABLE 	0 -18 2	; "calendar_nb_book_spans" -
	37	[119]	GETTABLE 	2 1 -19	; "calendar_show_histogram"
	38	[119]	SETTABLE 	0 -19 2	; "calendar_show_histogram" -
	39	[120]	GETTABLE 	2 1 -20	; "calendar_browse_future_months"
	40	[120]	SETTABLE 	0 -20 2	; "calendar_browse_future_months" -
	41	[121]	GETTABLE 	2 1 -21	; "is_enabled"
	42	[121]	EQ       	0 2 -22	; - false
	43	[121]	JMP      	1	; to 45
	44	[121]	LOADBOOL 	2 0 1
	45	[121]	LOADBOOL 	2 1 0
	46	[121]	SETTABLE 	0 -21 2	; "is_enabled" -
	47	[122]	GETTABLE 	2 1 -23	; "convert_to_db"
	48	[122]	SETTABLE 	0 -23 2	; "convert_to_db" -
	49	[123]	GETTABLE 	2 0 -2	; "ui"
	50	[123]	GETTABLE 	2 2 -24	; "menu"
	51	[123]	SELF     	2 2 -25	; "registerToMainMenu"
	52	[123]	MOVE     	4 0
	53	[123]	CALL     	2 3 1
	54	[124]	SELF     	2 0 -26	; "checkInitDatabase"
	55	[124]	CALL     	2 2 1
	56	[125]	GETUPVAL 	2 1	; BookStatusWidget
	57	[127]	CLOSURE  	3 0	; 0x7fcdebc08400
	58	[127]	MOVE     	0 0
	59	[127]	SETTABLE 	2 -27 3	; "getStats" -
	60	[128]	GETUPVAL 	2 2	; ReaderFooter
	61	[132]	CLOSURE  	3 1	; 0x7fcdebc08990
	62	[132]	MOVE     	0 0
	63	[132]	SETTABLE 	2 -28 3	; "getAvgTimePerPage" -
	64	[133]	GETUPVAL 	2 3	; Screensaver
	65	[150]	CLOSURE  	3 2	; 0x7fcdebc08cc0
	66	[150]	MOVE     	0 0
	67	[150]	GETUPVAL 	0 4	; ReaderProgress
	68	[150]	SETTABLE 	2 -29 3	; "getReaderProgress" -
	69	[151]	GETGLOBAL	2 -30	; require
	70	[151]	LOADK    	3 -31	; "apps/reader/modules/readergesture"
	71	[151]	CALL     	2 2 2
	72	[169]	CLOSURE  	3 3	; 0x7fcdebc09520
	73	[169]	MOVE     	0 0
	74	[169]	GETUPVAL 	0 4	; ReaderProgress
	75	[169]	SETTABLE 	2 -29 3	; "getReaderProgress" -
	76	[178]	CLOSURE  	3 4	; 0x7fcdebc09340
	77	[178]	MOVE     	0 0
	78	[178]	GETUPVAL 	0 5	; KeyValuePage
	79	[178]	GETUPVAL 	0 6	; _
	80	[178]	SETTABLE 	2 -32 3	; "getBookStats" -
	81	[182]	CLOSURE  	3 5	; 0x7fcdebc086f0
	82	[182]	MOVE     	0 0
	83	[182]	SETTABLE 	2 -33 3	; "getCalendarView" -
	84	[183]	RETURN   	0 1

function <./plugins/statistics.koplugin/main.lua:125,127> (9 instructions, 36 bytes at 0x7fcdebc08400)
0 params, 4 slots, 1 upvalue, 0 locals, 3 constants, 0 functions
	1	[126]	GETUPVAL 	0 0	; self
	2	[126]	SELF     	0 0 -1	; "getStatsBookStatus"
	3	[126]	GETUPVAL 	2 0	; self
	4	[126]	GETTABLE 	2 2 -2	; "id_curr_book"
	5	[126]	GETUPVAL 	3 0	; self
	6	[126]	GETTABLE 	3 3 -3	; "is_enabled"
	7	[126]	TAILCALL 	0 4 0
	8	[126]	RETURN   	0 0
	9	[127]	RETURN   	0 1

function <./plugins/statistics.koplugin/main.lua:128,132> (8 instructions, 32 bytes at 0x7fcdebc08990)
0 params, 2 slots, 1 upvalue, 0 locals, 2 constants, 0 functions
	1	[129]	GETUPVAL 	0 0	; self
	2	[129]	GETTABLE 	0 0 -1	; "is_enabled"
	3	[129]	TEST     	0 0 0
	4	[129]	JMP      	3	; to 8
	5	[130]	GETUPVAL 	0 0	; self
	6	[130]	GETTABLE 	0 0 -2	; "avg_time"
	7	[130]	RETURN   	0 2
	8	[132]	RETURN   	0 1

function <./plugins/statistics.koplugin/main.lua:133,150> (30 instructions, 120 bytes at 0x7fcdebc08cc0)
0 params, 9 slots, 2 upvalues, 6 locals, 14 constants, 0 functions
	1	[135]	GETUPVAL 	1 0	; self
	2	[135]	SELF     	1 1 -1	; "insertDB"
	3	[135]	GETUPVAL 	3 0	; self
	4	[135]	GETTABLE 	3 3 -2	; "id_curr_book"
	5	[135]	CALL     	1 3 1
	6	[136]	GETUPVAL 	1 0	; self
	7	[136]	SELF     	1 1 -3	; "getCurrentBookStats"
	8	[136]	CALL     	1 2 3
	9	[137]	GETUPVAL 	3 0	; self
	10	[137]	SELF     	3 3 -4	; "getTodayBookStats"
	11	[137]	CALL     	3 2 3
	12	[138]	GETUPVAL 	5 0	; self
	13	[138]	SELF     	5 5 -5	; "getReadingProgressStats"
	14	[138]	LOADK    	7 -6	; 7
	15	[138]	CALL     	5 3 2
	16	[139]	TEST     	5 0 0
	17	[139]	JMP      	11	; to 29
	18	[140]	GETUPVAL 	6 1	; ReaderProgress
	19	[140]	SELF     	6 6 -7	; "new"
	20	[140]	NEWTABLE 	8 0 6
	21	[141]	SETTABLE 	8 -8 5	; "dates" -
	22	[142]	SETTABLE 	8 -9 1	; "current_period" -
	23	[143]	SETTABLE 	8 -10 2	; "current_pages" -
	24	[144]	SETTABLE 	8 -11 3	; "today_period" -
	25	[145]	SETTABLE 	8 -12 4	; "today_pages" -
	26	[146]	SETTABLE 	8 -13 -14	; "readonly" true
	27	[140]	CALL     	6 3 2
	28	[147]	MOVE     	0 6
	29	[149]	RETURN   	0 2
	30	[150]	RETURN   	0 1

function <./plugins/statistics.koplugin/main.lua:152,169> (29 instructions, 116 bytes at 0x7fcdebc09520)
0 params, 9 slots, 2 upvalues, 6 locals, 12 constants, 0 functions
	1	[154]	GETUPVAL 	1 0	; self
	2	[154]	SELF     	1 1 -1	; "insertDB"
	3	[154]	GETUPVAL 	3 0	; self
	4	[154]	GETTABLE 	3 3 -2	; "id_curr_book"
	5	[154]	CALL     	1 3 1
	6	[155]	GETUPVAL 	1 0	; self
	7	[155]	SELF     	1 1 -3	; "getCurrentBookStats"
	8	[155]	CALL     	1 2 3
	9	[156]	GETUPVAL 	3 0	; self
	10	[156]	SELF     	3 3 -4	; "getTodayBookStats"
	11	[156]	CALL     	3 2 3
	12	[157]	GETUPVAL 	5 0	; self
	13	[157]	SELF     	5 5 -5	; "getReadingProgressStats"
	14	[157]	LOADK    	7 -6	; 7
	15	[157]	CALL     	5 3 2
	16	[158]	TEST     	5 0 0
	17	[158]	JMP      	10	; to 28
	18	[159]	GETUPVAL 	6 1	; ReaderProgress
	19	[159]	SELF     	6 6 -7	; "new"
	20	[159]	NEWTABLE 	8 0 5
	21	[160]	SETTABLE 	8 -8 5	; "dates" -
	22	[161]	SETTABLE 	8 -9 1	; "current_period" -
	23	[162]	SETTABLE 	8 -10 2	; "current_pages" -
	24	[163]	SETTABLE 	8 -11 3	; "today_period" -
	25	[164]	SETTABLE 	8 -12 4	; "today_pages" -
	26	[159]	CALL     	6 3 2
	27	[166]	MOVE     	0 6
	28	[168]	RETURN   	0 2
	29	[169]	RETURN   	0 1

function <./plugins/statistics.koplugin/main.lua:171,178> (26 instructions, 104 bytes at 0x7fcdebc09340)
0 params, 6 slots, 3 upvalues, 1 local, 8 constants, 0 functions
	1	[172]	GETUPVAL 	0 0	; self
	2	[172]	SELF     	0 0 -1	; "isDocless"
	3	[172]	CALL     	0 2 2
	4	[172]	TEST     	0 0 1
	5	[172]	JMP      	4	; to 10
	6	[172]	GETUPVAL 	0 0	; self
	7	[172]	GETTABLE 	0 0 -2	; "is_enabled"
	8	[172]	TEST     	0 0 1
	9	[172]	JMP      	1	; to 11
	10	[172]	RETURN   	0 1
	11	[173]	GETUPVAL 	0 1	; KeyValuePage
	12	[173]	SELF     	0 0 -3	; "new"
	13	[173]	NEWTABLE 	2 0 2
	14	[174]	GETUPVAL 	3 2	; _
	15	[174]	LOADK    	4 -5	; "Statistics"
	16	[174]	CALL     	3 2 2
	17	[174]	SETTABLE 	2 -4 3	; "title" -
	18	[175]	GETUPVAL 	3 0	; self
	19	[175]	SELF     	3 3 -7	; "getCurrentStat"
	20	[175]	GETUPVAL 	5 0	; self
	21	[175]	GETTABLE 	5 5 -8	; "id_curr_book"
	22	[175]	CALL     	3 3 2
	23	[175]	SETTABLE 	2 -6 3	; "kv_pairs" -
	24	[173]	CALL     	0 3 2
	25	[177]	RETURN   	0 2
	26	[178]	RETURN   	0 1

function <./plugins/statistics.koplugin/main.lua:180,182> (5 instructions, 20 bytes at 0x7fcdebc086f0)
0 params, 2 slots, 1 upvalue, 0 locals, 1 constant, 0 functions
	1	[181]	GETUPVAL 	0 0	; self
	2	[181]	SELF     	0 0 -1	; "getCalendarView"
	3	[181]	TAILCALL 	0 2 0
	4	[181]	RETURN   	0 0
	5	[182]	RETURN   	0 1

function <./plugins/statistics.koplugin/main.lua:185,215> (80 instructions, 320 bytes at 0x7fcdebc09dd0)
1 param, 6 slots, 0 upvalues, 2 locals, 29 constants, 0 functions
	1	[186]	SELF     	1 0 -1	; "isDocless"
	2	[186]	CALL     	1 2 2
	3	[186]	TEST     	1 0 1
	4	[186]	JMP      	3	; to 8
	5	[186]	GETTABLE 	1 0 -2	; "is_enabled"
	6	[186]	TEST     	1 0 1
	7	[186]	JMP      	1	; to 9
	8	[187]	RETURN   	0 1
	9	[190]	GETTABLE 	1 0 -3	; "data"
	10	[190]	TEST     	1 0 1
	11	[190]	JMP      	4	; to 16
	12	[191]	NEWTABLE 	1 0 1
	13	[191]	NEWTABLE 	2 0 0
	14	[191]	SETTABLE 	1 -4 2	; "performance_in_pages" -
	15	[191]	SETTABLE 	0 -3 1	; "data" -
	16	[193]	SELF     	1 0 -5	; "getBookProperties"
	17	[193]	CALL     	1 2 2
	18	[194]	GETTABLE 	2 0 -3	; "data"
	19	[194]	GETTABLE 	3 1 -6	; "title"
	20	[194]	SETTABLE 	2 -6 3	; "title" -
	21	[195]	GETTABLE 	2 0 -3	; "data"
	22	[195]	GETTABLE 	2 2 -6	; "title"
	23	[195]	EQ       	1 2 -7	; - nil
	24	[195]	JMP      	4	; to 29
	25	[195]	GETTABLE 	2 0 -3	; "data"
	26	[195]	GETTABLE 	2 2 -6	; "title"
	27	[195]	EQ       	0 2 -8	; - ""
	28	[195]	JMP      	7	; to 36
	29	[196]	GETTABLE 	2 0 -3	; "data"
	30	[196]	GETTABLE 	3 0 -9	; "document"
	31	[196]	GETTABLE 	3 3 -10	; "file"
	32	[196]	SELF     	3 3 -11	; "match"
	33	[196]	LOADK    	5 -12	; "^.+/(.+)$"
	34	[196]	CALL     	3 3 2
	35	[196]	SETTABLE 	2 -6 3	; "title" -
	36	[198]	GETTABLE 	2 0 -3	; "data"
	37	[198]	GETTABLE 	3 1 -13	; "authors"
	38	[198]	SETTABLE 	2 -13 3	; "authors" -
	39	[199]	GETTABLE 	2 0 -3	; "data"
	40	[199]	GETTABLE 	3 1 -14	; "language"
	41	[199]	SETTABLE 	2 -14 3	; "language" -
	42	[200]	GETTABLE 	2 0 -3	; "data"
	43	[200]	GETTABLE 	3 1 -15	; "series"
	44	[200]	SETTABLE 	2 -15 3	; "series" -
	45	[202]	GETTABLE 	2 0 -3	; "data"
	46	[202]	GETTABLE 	3 0 -17	; "view"
	47	[202]	GETTABLE 	3 3 -9	; "document"
	48	[202]	SELF     	3 3 -18	; "getPageCount"
	49	[202]	CALL     	3 2 2
	50	[202]	SETTABLE 	2 -16 3	; "pages" -
	51	[203]	GETTABLE 	2 0 -3	; "data"
	52	[203]	GETTABLE 	2 2 -19	; "md5"
	53	[203]	TEST     	2 0 1
	54	[203]	JMP      	6	; to 61
	55	[204]	GETTABLE 	2 0 -3	; "data"
	56	[204]	SELF     	3 0 -20	; "partialMd5"
	57	[204]	GETTABLE 	5 0 -9	; "document"
	58	[204]	GETTABLE 	5 5 -10	; "file"
	59	[204]	CALL     	3 3 2
	60	[204]	SETTABLE 	2 -19 3	; "md5" -
	61	[206]	SETTABLE 	0 -21 -22	; "curr_total_time" 0
	62	[207]	SETTABLE 	0 -23 -22	; "curr_total_pages" 0
	63	[208]	SELF     	2 0 -25	; "getIdBookDB"
	64	[208]	CALL     	2 2 2
	65	[208]	SETTABLE 	0 -24 2	; "id_curr_book" -
	66	[209]	SELF     	2 0 -28	; "getPageTimeTotalStats"
	67	[209]	GETTABLE 	4 0 -24	; "id_curr_book"
	68	[209]	CALL     	2 3 3
	69	[209]	SETTABLE 	0 -27 3	; "total_read_time" -
	70	[209]	SETTABLE 	0 -26 2	; "total_read_pages" -
	71	[210]	GETTABLE 	2 0 -26	; "total_read_pages"
	72	[210]	LT       	0 -22 2	; 0 -
	73	[210]	JMP      	5	; to 79
	74	[211]	GETTABLE 	2 0 -27	; "total_read_time"
	75	[211]	GETTABLE 	3 0 -26	; "total_read_pages"
	76	[211]	DIV      	2 2 3
	77	[211]	SETTABLE 	0 -29 2	; "avg_time" -
	78	[211]	JMP      	1	; to 80
	79	[213]	SETTABLE 	0 -29 -22	; "avg_time" 0
	80	[215]	RETURN   	0 1

function <./plugins/statistics.koplugin/main.lua:217,254> (52 instructions, 208 bytes at 0x7fcdebc09f70)
3 params, 11 slots, 2 upvalues, 8 locals, 15 constants, 0 functions
	1	[218]	TEST     	2 0 0
	2	[218]	JMP      	2	; to 5
	3	[218]	EQ       	0 1 -1	; - nil
	4	[218]	JMP      	2	; to 7
	5	[219]	NEWTABLE 	3 0 0
	6	[219]	RETURN   	3 2
	7	[222]	SELF     	3 0 -2	; "insertDB"
	8	[222]	GETTABLE 	5 0 -3	; "id_curr_book"
	9	[222]	CALL     	3 3 1
	10	[223]	GETUPVAL 	3 0	; SQ3
	11	[223]	GETTABLE 	3 3 -4	; "open"
	12	[223]	GETUPVAL 	4 1	; db_location
	13	[223]	CALL     	3 2 2
	14	[232]	LOADK    	4 -5	; "        SELECT count(*)\n        FROM   (\n                    SELECT strftime('%%Y-%%m-%%d', start_time, 'unixepoch', 'localtime') AS dates\n                    FROM   page_stat\n                    WHERE  id_book = '%s'\n                    GROUP  BY dates\n               )\n    "
	15	[233]	SELF     	5 3 -6	; "rowexec"
	16	[233]	GETGLOBAL	7 -7	; string
	17	[233]	GETTABLE 	7 7 -8	; "format"
	18	[233]	MOVE     	8 4
	19	[233]	MOVE     	9 1
	20	[233]	CALL     	7 3 0
	21	[233]	CALL     	5 0 2
	22	[239]	LOADK    	4 -9	; "        SELECT sum(period),\n               count(DISTINCT page)\n        FROM   page_stat\n        WHERE  id_book = '%s'\n    "
	23	[240]	SELF     	6 3 -6	; "rowexec"
	24	[240]	GETGLOBAL	8 -7	; string
	25	[240]	GETTABLE 	8 8 -8	; "format"
	26	[240]	MOVE     	9 4
	27	[240]	MOVE     	10 1
	28	[240]	CALL     	8 3 0
	29	[240]	CALL     	6 0 3
	30	[241]	SELF     	8 3 -10	; "close"
	31	[241]	CALL     	8 2 1
	32	[243]	EQ       	0 6 -1	; - nil
	33	[243]	JMP      	1	; to 35
	34	[244]	LOADK    	6 -11	; 0
	35	[246]	EQ       	0 7 -1	; - nil
	36	[246]	JMP      	1	; to 38
	37	[247]	LOADK    	7 -11	; 0
	38	[249]	NEWTABLE 	8 0 3
	39	[250]	GETGLOBAL	9 -13	; tonumber
	40	[250]	MOVE     	10 5
	41	[250]	CALL     	9 2 2
	42	[250]	SETTABLE 	8 -12 9	; "days" -
	43	[251]	GETGLOBAL	9 -13	; tonumber
	44	[251]	MOVE     	10 6
	45	[251]	CALL     	9 2 2
	46	[251]	SETTABLE 	8 -14 9	; "time" -
	47	[252]	GETGLOBAL	9 -13	; tonumber
	48	[252]	MOVE     	10 7
	49	[252]	CALL     	9 2 2
	50	[252]	SETTABLE 	8 -15 9	; "pages" -
	51	[253]	RETURN   	8 2
	52	[254]	RETURN   	0 1

function <./plugins/statistics.koplugin/main.lua:256,312> (134 instructions, 536 bytes at 0x7fcdebc0a120)
1 param, 15 slots, 10 upvalues, 8 locals, 29 constants, 2 functions
	1	[257]	GETUPVAL 	1 0	; SQ3
	2	[257]	GETTABLE 	1 1 -1	; "open"
	3	[257]	GETUPVAL 	2 1	; db_location
	4	[257]	CALL     	1 2 2
	5	[258]	GETTABLE 	2 0 -2	; "convert_to_db"
	6	[258]	TEST     	2 0 0
	7	[258]	JMP      	41	; to 49
	8	[259]	SELF     	2 1 -3	; "exec"
	9	[259]	LOADK    	4 -4	; "pragma table_info('book');"
	10	[259]	CALL     	2 3 2
	11	[259]	TEST     	2 0 1
	12	[259]	JMP      	119	; to 132
	13	[260]	GETUPVAL 	2 2	; UIManager
	14	[260]	SELF     	2 2 -5	; "show"
	15	[260]	GETUPVAL 	4 3	; ConfirmBox
	16	[260]	SELF     	4 4 -6	; "new"
	17	[260]	NEWTABLE 	6 0 5
	18	[261]	GETUPVAL 	7 4	; T
	19	[261]	GETUPVAL 	8 5	; _
	20	[265]	LOADK    	9 -8	; "Cannot open database in %1.\nThe database may have been moved or deleted.\nDo you want to create an empty database?\n"
	21	[261]	CALL     	8 2 2
	22	[266]	GETUPVAL 	9 6	; BD
	23	[266]	GETTABLE 	9 9 -9	; "filepath"
	24	[266]	GETUPVAL 	10 1	; db_location
	25	[266]	CALL     	9 2 0
	26	[261]	CALL     	7 0 2
	27	[266]	SETTABLE 	6 -7 7	; "text" -
	28	[267]	GETUPVAL 	7 5	; _
	29	[267]	LOADK    	8 -11	; "Close"
	30	[267]	CALL     	7 2 2
	31	[267]	SETTABLE 	6 -10 7	; "cancel_text" -
	32	[270]	CLOSURE  	7 0	; 0x7fcdebc0ac40
	33	[270]	SETTABLE 	6 -12 7	; "cancel_callback" -
	34	[271]	GETUPVAL 	7 5	; _
	35	[271]	LOADK    	8 -14	; "Create"
	36	[271]	CALL     	7 2 2
	37	[271]	SETTABLE 	6 -13 7	; "ok_text" -
	38	[278]	CLOSURE  	7 1	; 0x7fcdebc0b020
	39	[278]	GETUPVAL 	0 0	; SQ3
	40	[278]	GETUPVAL 	0 1	; db_location
	41	[278]	MOVE     	0 0
	42	[278]	GETUPVAL 	0 2	; UIManager
	43	[278]	GETUPVAL 	0 7	; InfoMessage
	44	[278]	GETUPVAL 	0 5	; _
	45	[278]	SETTABLE 	6 -15 7	; "ok_callback" -
	46	[260]	CALL     	4 3 0
	47	[260]	CALL     	2 0 1
	48	[280]	JMP      	83	; to 132
	49	[282]	SETTABLE 	0 -2 -16	; "convert_to_db" true
	50	[283]	SELF     	2 1 -3	; "exec"
	51	[283]	LOADK    	4 -4	; "pragma table_info('book');"
	52	[283]	CALL     	2 3 2
	53	[283]	TEST     	2 0 1
	54	[283]	JMP      	75	; to 130
	55	[284]	LOADNIL  	2 4
	56	[285]	GETUPVAL 	5 8	; ReadHistory
	57	[285]	GETTABLE 	5 5 -17	; "hist"
	58	[285]	LEN      	5 5
	59	[285]	EQ       	0 5 -18	; - 1
	60	[285]	JMP      	14	; to 75
	61	[286]	GETUPVAL 	5 8	; ReadHistory
	62	[286]	GETTABLE 	5 5 -17	; "hist"
	63	[286]	GETTABLE 	5 5 -18	; 1
	64	[286]	GETTABLE 	2 5 -7	; "text"
	65	[287]	GETGLOBAL	5 -19	; require
	66	[287]	LOADK    	6 -20	; "ui/quickstart"
	67	[287]	CALL     	5 2 2
	68	[287]	GETTABLE 	5 5 -21	; "quickstart_filename"
	69	[288]	GETUPVAL 	6 9	; util
	70	[288]	GETTABLE 	6 6 -22	; "splitFilePathName"
	71	[288]	MOVE     	7 5
	72	[288]	CALL     	6 2 3
	73	[288]	MOVE     	3 7
	74	[288]	MOVE     	4 6
	75	[290]	GETUPVAL 	5 8	; ReadHistory
	76	[290]	GETTABLE 	5 5 -17	; "hist"
	77	[290]	LEN      	5 5
	78	[290]	LT       	1 -18 5	; 1 -
	79	[290]	JMP      	7	; to 87
	80	[290]	GETUPVAL 	5 8	; ReadHistory
	81	[290]	GETTABLE 	5 5 -17	; "hist"
	82	[290]	LEN      	5 5
	83	[290]	EQ       	0 5 -18	; - 1
	84	[290]	JMP      	42	; to 127
	85	[290]	EQ       	1 2 3
	86	[290]	JMP      	40	; to 127
	87	[291]	GETUPVAL 	5 7	; InfoMessage
	88	[291]	SELF     	5 5 -6	; "new"
	89	[291]	NEWTABLE 	7 0 1
	90	[292]	GETUPVAL 	8 5	; _
	91	[297]	LOADK    	9 -23	; "New version of statistics plugin detected.\nStatistics data needs to be converted into the new database format.\nThis may take a few minutes.\nPlease wait\226\128\166\n"
	92	[292]	CALL     	8 2 2
	93	[297]	SETTABLE 	7 -7 8	; "text" -
	94	[291]	CALL     	5 3 2
	95	[298]	GETUPVAL 	6 2	; UIManager
	96	[298]	SELF     	6 6 -5	; "show"
	97	[298]	MOVE     	8 5
	98	[298]	CALL     	6 3 1
	99	[299]	GETUPVAL 	6 2	; UIManager
	100	[299]	SELF     	6 6 -24	; "forceRePaint"
	101	[299]	CALL     	6 2 1
	102	[300]	SELF     	6 0 -25	; "migrateToDB"
	103	[300]	MOVE     	8 1
	104	[300]	CALL     	6 3 2
	105	[301]	GETUPVAL 	7 2	; UIManager
	106	[301]	SELF     	7 7 -26	; "close"
	107	[301]	MOVE     	9 5
	108	[301]	CALL     	7 3 1
	109	[302]	GETUPVAL 	7 2	; UIManager
	110	[302]	SELF     	7 7 -24	; "forceRePaint"
	111	[302]	CALL     	7 2 1
	112	[303]	GETUPVAL 	7 2	; UIManager
	113	[303]	SELF     	7 7 -5	; "show"
	114	[303]	GETUPVAL 	9 7	; InfoMessage
	115	[303]	SELF     	9 9 -6	; "new"
	116	[303]	NEWTABLE 	11 0 1
	117	[304]	GETUPVAL 	12 4	; T
	118	[304]	GETUPVAL 	13 5	; _
	119	[304]	LOADK    	14 -27	; "Conversion completed.\nImported %1 books to database.\nTap to continue."
	120	[304]	CALL     	13 2 2
	121	[304]	MOVE     	14 6
	122	[304]	CALL     	12 3 2
	123	[304]	SETTABLE 	11 -7 12	; "text" -
	124	[303]	CALL     	9 3 0
	125	[303]	CALL     	7 0 1
	126	[304]	JMP      	3	; to 130
	127	[306]	SELF     	5 0 -28	; "createDB"
	128	[306]	MOVE     	7 1
	129	[306]	CALL     	5 3 1
	130	[309]	SELF     	2 0 -29	; "saveSettings"
	131	[309]	CALL     	2 2 1
	132	[311]	SELF     	2 1 -26	; "close"
	133	[311]	CALL     	2 2 1
	134	[312]	RETURN   	0 1

function <./plugins/statistics.koplugin/main.lua:268,270> (2 instructions, 8 bytes at 0x7fcdebc0ac40)
0 params, 2 slots, 0 upvalues, 0 locals, 0 constants, 0 functions
	1	[269]	RETURN   	0 1
	2	[270]	RETURN   	0 1

function <./plugins/statistics.koplugin/main.lua:272,278> (26 instructions, 104 bytes at 0x7fcdebc0b020)
0 params, 8 slots, 6 upvalues, 1 local, 10 constants, 0 functions
	1	[273]	GETUPVAL 	0 0	; SQ3
	2	[273]	GETTABLE 	0 0 -1	; "open"
	3	[273]	GETUPVAL 	1 1	; db_location
	4	[273]	CALL     	0 2 2
	5	[274]	GETUPVAL 	1 2	; self
	6	[274]	SELF     	1 1 -2	; "createDB"
	7	[274]	MOVE     	3 0
	8	[274]	CALL     	1 3 1
	9	[275]	SELF     	1 0 -3	; "close"
	10	[275]	CALL     	1 2 1
	11	[276]	GETUPVAL 	1 3	; UIManager
	12	[276]	SELF     	1 1 -4	; "show"
	13	[276]	GETUPVAL 	3 4	; InfoMessage
	14	[276]	SELF     	3 3 -5	; "new"
	15	[276]	NEWTABLE 	5 0 2
	16	[276]	GETUPVAL 	6 5	; _
	17	[276]	LOADK    	7 -7	; "A new empty database has been created."
	18	[276]	CALL     	6 2 2
	19	[276]	SETTABLE 	5 -6 6	; "text" -
	20	[276]	SETTABLE 	5 -8 -9	; "timeout" 3
	21	[276]	CALL     	3 3 0
	22	[276]	CALL     	1 0 1
	23	[277]	GETUPVAL 	1 2	; self
	24	[277]	SELF     	1 1 -10	; "initData"
	25	[277]	CALL     	1 2 1
	26	[278]	RETURN   	0 1

function <./plugins/statistics.koplugin/main.lua:314,334> (46 instructions, 184 bytes at 0x7fcdebc0b0a0)
2 params, 19 slots, 0 upvalues, 14 locals, 19 constants, 0 functions
	1	[315]	EQ       	0 1 -1	; - nil
	2	[315]	JMP      	2	; to 5
	3	[316]	LOADNIL  	2 2
	4	[316]	RETURN   	2 2
	5	[318]	GETGLOBAL	2 -2	; require
	6	[318]	LOADK    	3 -3	; "bit"
	7	[318]	CALL     	2 2 2
	8	[319]	GETGLOBAL	3 -2	; require
	9	[319]	LOADK    	4 -4	; "ffi/MD5"
	10	[319]	CALL     	3 2 2
	11	[320]	GETTABLE 	4 2 -5	; "lshift"
	12	[321]	LOADK    	5 -6	; 1024
	13	[321]	LOADK    	6 -6	; 1024
	14	[322]	GETTABLE 	7 3 -7	; "new"
	15	[322]	CALL     	7 1 2
	16	[323]	GETGLOBAL	8 -8	; io
	17	[323]	GETTABLE 	8 8 -9	; "open"
	18	[323]	MOVE     	9 1
	19	[323]	LOADK    	10 -10	; "rb"
	20	[323]	CALL     	8 3 2
	21	[324]	LOADK    	9 -11	; -1
	22	[324]	LOADK    	10 -12	; 10
	23	[324]	LOADK    	11 -13	; 1
	24	[324]	FORPREP  	9 17	; to 42
	25	[325]	SELF     	13 8 -14	; "seek"
	26	[325]	LOADK    	15 -15	; "set"
	27	[325]	MOVE     	16 4
	28	[325]	MOVE     	17 5
	29	[325]	MUL      	18 -16 12	; 2 -
	30	[325]	CALL     	16 3 0
	31	[325]	CALL     	13 0 1
	32	[326]	SELF     	13 8 -17	; "read"
	33	[326]	MOVE     	15 6
	34	[326]	CALL     	13 3 2
	35	[327]	TEST     	13 0 0
	36	[327]	JMP      	6	; to 43
	37	[328]	SELF     	14 7 -18	; "update"
	38	[328]	MOVE     	16 13
	39	[328]	CALL     	14 3 1
	40	[328]	JMP      	1	; to 42
	41	[330]	JMP      	1	; to 43
	42	[324]	FORLOOP  	9 -18	; to 25
	43	[333]	SELF     	9 7 -19	; "sum"
	44	[333]	TAILCALL 	9 2 0
	45	[333]	RETURN   	9 0
	46	[334]	RETURN   	0 1

function <./plugins/statistics.koplugin/main.lua:336,380> (29 instructions, 116 bytes at 0x7fcdebc0c0c0)
2 params, 7 slots, 1 upvalue, 4 locals, 12 constants, 0 functions
	1	[338]	GETUPVAL 	2 0	; Device
	2	[338]	SELF     	2 2 -1	; "canUseWAL"
	3	[338]	CALL     	2 2 2
	4	[338]	TEST     	2 0 0
	5	[338]	JMP      	4	; to 10
	6	[339]	SELF     	2 1 -2	; "exec"
	7	[339]	LOADK    	4 -3	; "PRAGMA journal_mode=WAL;"
	8	[339]	CALL     	2 3 1
	9	[339]	JMP      	3	; to 13
	10	[341]	SELF     	2 1 -2	; "exec"
	11	[341]	LOADK    	4 -4	; "PRAGMA journal_mode=TRUNCATE;"
	12	[341]	CALL     	2 3 1
	13	[374]	LOADK    	2 -5	; "        CREATE TABLE IF NOT EXISTS book\n            (\n                id integer PRIMARY KEY autoincrement,\n                title text,\n                authors text,\n                notes      integer,\n                last_open  integer,\n                highlights integer,\n                pages      integer,\n                series text,\n                language text,\n                md5 text,\n                total_read_time  integer,\n                total_read_pages integer\n            );\n        CREATE TABLE IF NOT EXISTS page_stat\n            (\n                id_book    integer,\n                page       integer NOT NULL,\n                start_time integer NOT NULL,\n                period     integer NOT NULL,\n                UNIQUE (page, start_time),\n                FOREIGN KEY(id_book) REFERENCES book(id)\n             );\n        CREATE TABLE IF NOT EXISTS info\n             (\n                 version integer\n             );\n        CREATE INDEX IF NOT EXISTS page_stat_id_book ON page_stat(id_book);\n        CREATE INDEX IF NOT EXISTS book_title_authors_md5 ON book(title, authors, md5);\n    "
	14	[375]	SELF     	3 1 -2	; "exec"
	15	[375]	MOVE     	5 2
	16	[375]	CALL     	3 3 1
	17	[377]	SELF     	3 1 -6	; "prepare"
	18	[377]	LOADK    	5 -7	; "INSERT INTO info values (?)"
	19	[377]	CALL     	3 3 2
	20	[378]	SELF     	4 3 -8	; "reset"
	21	[378]	CALL     	4 2 2
	22	[378]	SELF     	4 4 -9	; "bind"
	23	[378]	LOADK    	6 -10	; "1"
	24	[378]	CALL     	4 3 2
	25	[378]	SELF     	4 4 -11	; "step"
	26	[378]	CALL     	4 2 1
	27	[379]	SELF     	4 3 -12	; "close"
	28	[379]	CALL     	4 2 1
	29	[380]	RETURN   	0 1

function <./plugins/statistics.koplugin/main.lua:382,481> (241 instructions, 964 bytes at 0x7fcdebc0a750)
3 params, 27 slots, 2 upvalues, 26 locals, 45 constants, 0 functions
	1	[384]	LOADK    	4 -1	; 0
	2	[385]	LOADNIL  	5 6
	3	[387]	LOADK    	7 -1	; 0
	4	[388]	LOADK    	8 -1	; 0
	5	[389]	LOADNIL  	9 9
	6	[390]	GETTABLE 	10 1 -2	; "total_time_in_sec"
	7	[390]	TEST     	10 0 0
	8	[390]	JMP      	232	; to 241
	9	[390]	GETTABLE 	10 1 -2	; "total_time_in_sec"
	10	[390]	LT       	0 -1 10	; 0 -
	11	[390]	JMP      	229	; to 241
	12	[391]	GETUPVAL 	10 0	; util
	13	[391]	GETTABLE 	10 10 -3	; "tableSize"
	14	[391]	GETTABLE 	11 1 -4	; "performance_in_pages"
	15	[391]	CALL     	10 2 2
	16	[391]	LT       	0 -1 10	; 0 -
	17	[391]	JMP      	223	; to 241
	18	[392]	GETUPVAL 	10 0	; util
	19	[392]	GETTABLE 	10 10 -3	; "tableSize"
	20	[392]	GETTABLE 	11 1 -4	; "performance_in_pages"
	21	[392]	CALL     	10 2 2
	22	[393]	GETUPVAL 	11 1	; logger
	23	[393]	GETTABLE 	11 11 -5	; "dbg"
	24	[393]	LOADK    	12 -6	; "Insert to database: "
	25	[393]	GETTABLE 	13 1 -7	; "title"
	26	[393]	CONCAT   	12 12 13
	27	[393]	CALL     	11 2 1
	28	[400]	LOADK    	9 -8	; "            SELECT count(id)\n            FROM   book\n            WHERE  title = ?\n                AND    authors = ?\n                AND    md5 = ?\n        "
	29	[401]	SELF     	11 2 -9	; "prepare"
	30	[401]	MOVE     	13 9
	31	[401]	CALL     	11 3 2
	32	[402]	SELF     	12 11 -10	; "reset"
	33	[402]	CALL     	12 2 2
	34	[402]	SELF     	12 12 -11	; "bind"
	35	[402]	GETTABLE 	14 0 -12	; "data"
	36	[402]	GETTABLE 	14 14 -7	; "title"
	37	[402]	GETTABLE 	15 0 -12	; "data"
	38	[402]	GETTABLE 	15 15 -13	; "authors"
	39	[402]	GETTABLE 	16 0 -12	; "data"
	40	[402]	GETTABLE 	16 16 -14	; "md5"
	41	[402]	CALL     	12 5 2
	42	[402]	SELF     	12 12 -15	; "step"
	43	[402]	CALL     	12 2 2
	44	[403]	GETGLOBAL	13 -16	; tonumber
	45	[403]	GETTABLE 	14 12 -17	; 1
	46	[403]	CALL     	13 2 2
	47	[404]	EQ       	0 13 -1	; - 0
	48	[404]	JMP      	29	; to 78
	49	[405]	SELF     	14 2 -9	; "prepare"
	50	[405]	LOADK    	16 -18	; "INSERT INTO book VALUES(NULL, ?, ?, ?, ?, ?, ?, ?, ?, ?, ?, ?)"
	51	[405]	CALL     	14 3 2
	52	[405]	MOVE     	11 14
	53	[406]	SELF     	14 11 -10	; "reset"
	54	[406]	CALL     	14 2 2
	55	[406]	SELF     	14 14 -11	; "bind"
	56	[406]	GETTABLE 	16 1 -7	; "title"
	57	[406]	GETTABLE 	17 1 -13	; "authors"
	58	[406]	GETTABLE 	18 1 -19	; "notes"
	59	[407]	MOVE     	19 4
	60	[407]	GETTABLE 	20 1 -20	; "highlights"
	61	[407]	GETTABLE 	21 1 -21	; "pages"
	62	[408]	GETTABLE 	22 1 -22	; "series"
	63	[408]	GETTABLE 	23 1 -23	; "language"
	64	[408]	SELF     	24 0 -24	; "partialMd5"
	65	[408]	GETTABLE 	26 1 -25	; "file"
	66	[408]	CALL     	24 3 2
	67	[408]	MOVE     	25 8
	68	[408]	MOVE     	26 7
	69	[406]	CALL     	14 13 2
	70	[408]	SELF     	14 14 -15	; "step"
	71	[408]	CALL     	14 2 1
	72	[411]	LOADK    	9 -26	; "                SELECT last_insert_rowid() AS num;\n            "
	73	[412]	SELF     	14 2 -27	; "rowexec"
	74	[412]	MOVE     	16 9
	75	[412]	CALL     	14 3 2
	76	[412]	MOVE     	3 14
	77	[412]	JMP      	19	; to 97
	78	[420]	LOADK    	9 -28	; "                SELECT id\n                FROM   book\n                WHERE  title = ?\n                    AND authors = ?\n                    AND md5 = ?\n            "
	79	[421]	SELF     	14 2 -9	; "prepare"
	80	[421]	MOVE     	16 9
	81	[421]	CALL     	14 3 2
	82	[421]	MOVE     	11 14
	83	[422]	SELF     	14 11 -10	; "reset"
	84	[422]	CALL     	14 2 2
	85	[422]	SELF     	14 14 -11	; "bind"
	86	[422]	GETTABLE 	16 0 -12	; "data"
	87	[422]	GETTABLE 	16 16 -7	; "title"
	88	[422]	GETTABLE 	17 0 -12	; "data"
	89	[422]	GETTABLE 	17 17 -13	; "authors"
	90	[422]	GETTABLE 	18 0 -12	; "data"
	91	[422]	GETTABLE 	18 18 -14	; "md5"
	92	[422]	CALL     	14 5 2
	93	[422]	SELF     	14 14 -15	; "step"
	94	[422]	CALL     	14 2 2
	95	[422]	MOVE     	12 14
	96	[423]	GETTABLE 	3 12 -17	; 1
	97	[426]	NEWTABLE 	14 0 0
	98	[427]	GETGLOBAL	15 -29	; pairs
	99	[427]	GETTABLE 	16 1 -4	; "performance_in_pages"
	100	[427]	CALL     	15 2 4
	101	[427]	JMP      	5	; to 107
	102	[428]	GETGLOBAL	20 -30	; table
	103	[428]	GETTABLE 	20 20 -31	; "insert"
	104	[428]	MOVE     	21 14
	105	[428]	MOVE     	22 18
	106	[428]	CALL     	20 3 1
	107	[427]	TFORLOOP 	15 2
	108	[428]	JMP      	-7	; to 102
	109	[430]	GETGLOBAL	15 -30	; table
	110	[430]	GETTABLE 	15 15 -32	; "sort"
	111	[430]	MOVE     	16 14
	112	[430]	CALL     	15 2 1
	113	[432]	SELF     	15 2 -33	; "exec"
	114	[432]	LOADK    	17 -34	; "BEGIN"
	115	[432]	CALL     	15 3 1
	116	[433]	SELF     	15 2 -9	; "prepare"
	117	[433]	LOADK    	17 -35	; "INSERT OR IGNORE INTO page_stat VALUES(?, ?, ?, ?)"
	118	[433]	CALL     	15 3 2
	119	[433]	MOVE     	11 15
	120	[434]	GETGLOBAL	15 -36	; math
	121	[434]	GETTABLE 	15 15 -37	; "ceil"
	122	[434]	GETTABLE 	16 1 -2	; "total_time_in_sec"
	123	[434]	DIV      	16 16 10
	124	[434]	CALL     	15 2 2
	125	[435]	GETTABLE 	16 0 -38	; "page_max_read_sec"
	126	[435]	LT       	0 16 15
	127	[435]	JMP      	1	; to 129
	128	[436]	GETTABLE 	15 0 -38	; "page_max_read_sec"
	129	[438]	GETTABLE 	16 1 -4	; "performance_in_pages"
	130	[438]	GETTABLE 	17 14 -17	; 1
	131	[438]	GETTABLE 	16 16 17
	132	[439]	LT       	0 -17 16	; 1 -
	133	[439]	JMP      	1	; to 135
	134	[440]	SUB      	16 16 -17	; - 1
	135	[442]	GETTABLE 	5 14 -17	; 1
	136	[444]	SELF     	17 11 -10	; "reset"
	137	[444]	CALL     	17 2 2
	138	[444]	SELF     	17 17 -11	; "bind"
	139	[444]	MOVE     	19 3
	140	[444]	MOVE     	20 16
	141	[444]	SUB      	21 5 15
	142	[444]	MOVE     	22 15
	143	[444]	CALL     	17 6 2
	144	[444]	SELF     	17 17 -15	; "step"
	145	[444]	CALL     	17 2 1
	146	[445]	LOADK    	17 -39	; 2
	147	[445]	LEN      	18 14
	148	[445]	LOADK    	19 -17	; 1
	149	[445]	FORPREP  	17 39	; to 189
	150	[446]	SUB      	21 20 -17	; - 1
	151	[446]	GETTABLE 	5 14 21
	152	[447]	GETTABLE 	21 14 20
	153	[447]	SUB      	22 20 -17	; - 1
	154	[447]	GETTABLE 	22 14 22
	155	[447]	SUB      	6 21 22
	156	[448]	GETTABLE 	21 0 -38	; "page_max_read_sec"
	157	[448]	LE       	0 6 21
	158	[448]	JMP      	14	; to 173
	159	[449]	SELF     	21 11 -10	; "reset"
	160	[449]	CALL     	21 2 2
	161	[449]	SELF     	21 21 -11	; "bind"
	162	[449]	MOVE     	23 3
	163	[449]	GETTABLE 	24 1 -4	; "performance_in_pages"
	164	[449]	SUB      	25 20 -17	; - 1
	165	[449]	GETTABLE 	25 14 25
	166	[449]	GETTABLE 	24 24 25
	167	[450]	MOVE     	25 5
	168	[450]	MOVE     	26 6
	169	[449]	CALL     	21 6 2
	170	[450]	SELF     	21 21 -15	; "step"
	171	[450]	CALL     	21 2 1
	172	[450]	JMP      	16	; to 189
	173	[451]	GETTABLE 	21 0 -38	; "page_max_read_sec"
	174	[451]	LT       	0 21 6
	175	[451]	JMP      	13	; to 189
	176	[452]	SELF     	21 11 -10	; "reset"
	177	[452]	CALL     	21 2 2
	178	[452]	SELF     	21 21 -11	; "bind"
	179	[452]	MOVE     	23 3
	180	[452]	GETTABLE 	24 1 -4	; "performance_in_pages"
	181	[452]	SUB      	25 20 -17	; - 1
	182	[452]	GETTABLE 	25 14 25
	183	[452]	GETTABLE 	24 24 25
	184	[453]	MOVE     	25 5
	185	[453]	MOVE     	26 15
	186	[452]	CALL     	21 6 2
	187	[453]	SELF     	21 21 -15	; "step"
	188	[453]	CALL     	21 2 1
	189	[445]	FORLOOP  	17 -40	; to 150
	190	[457]	SELF     	17 11 -10	; "reset"
	191	[457]	CALL     	17 2 2
	192	[457]	SELF     	17 17 -11	; "bind"
	193	[457]	MOVE     	19 3
	194	[457]	GETTABLE 	20 1 -4	; "performance_in_pages"
	195	[457]	LEN      	21 14
	196	[457]	GETTABLE 	21 14 21
	197	[457]	GETTABLE 	20 20 21
	198	[458]	LEN      	21 14
	199	[458]	GETTABLE 	21 14 21
	200	[458]	MOVE     	22 15
	201	[457]	CALL     	17 6 2
	202	[458]	SELF     	17 17 -15	; "step"
	203	[458]	CALL     	17 2 1
	204	[460]	LEN      	17 14
	205	[460]	GETTABLE 	17 14 17
	206	[460]	ADD      	4 17 15
	207	[461]	SELF     	17 2 -33	; "exec"
	208	[461]	LOADK    	19 -40	; "COMMIT"
	209	[461]	CALL     	17 3 1
	210	[467]	LOADK    	9 -41	; "            SELECT count(DISTINCT page),\n                   sum(period)\n            FROM   page_stat\n            WHERE  id_book = %s;\n        "
	211	[468]	SELF     	17 2 -27	; "rowexec"
	212	[468]	GETGLOBAL	19 -42	; string
	213	[468]	GETTABLE 	19 19 -43	; "format"
	214	[468]	MOVE     	20 9
	215	[468]	GETGLOBAL	21 -16	; tonumber
	216	[468]	MOVE     	22 3
	217	[468]	CALL     	21 2 0
	218	[468]	CALL     	19 0 0
	219	[468]	CALL     	17 0 3
	220	[468]	MOVE     	8 18
	221	[468]	MOVE     	7 17
	222	[475]	LOADK    	9 -44	; "            UPDATE book\n            SET    last_open = ?,\n                   total_read_time = ?,\n                   total_read_pages = ?\n            WHERE  id = ?\n        "
	223	[476]	SELF     	17 2 -9	; "prepare"
	224	[476]	MOVE     	19 9
	225	[476]	CALL     	17 3 2
	226	[476]	MOVE     	11 17
	227	[477]	SELF     	17 11 -10	; "reset"
	228	[477]	CALL     	17 2 2
	229	[477]	SELF     	17 17 -11	; "bind"
	230	[477]	MOVE     	19 4
	231	[477]	MOVE     	20 8
	232	[477]	MOVE     	21 7
	233	[477]	MOVE     	22 3
	234	[477]	CALL     	17 6 2
	235	[477]	SELF     	17 17 -15	; "step"
	236	[477]	CALL     	17 2 1
	237	[478]	SELF     	17 11 -45	; "close"
	238	[478]	CALL     	17 2 1
	239	[479]	LOADBOOL 	17 1 0
	240	[479]	RETURN   	17 2
	241	[481]	RETURN   	0 1

function <./plugins/statistics.koplugin/main.lua:483,534> (138 instructions, 552 bytes at 0x7fcdebc0c780)
2 params, 19 slots, 5 upvalues, 22 locals, 37 constants, 0 functions
	1	[484]	SELF     	2 0 -1	; "createDB"
	2	[484]	MOVE     	4 1
	3	[484]	CALL     	2 3 1
	4	[485]	LOADK    	2 -2	; 0
	5	[486]	NEWTABLE 	3 0 0
	6	[487]	GETGLOBAL	4 -3	; pairs
	7	[487]	GETUPVAL 	5 0	; ReadHistory
	8	[487]	GETTABLE 	5 5 -4	; "hist"
	9	[487]	CALL     	4 2 4
	10	[487]	JMP      	43	; to 54
	11	[488]	GETUPVAL 	9 1	; DocSettings
	12	[488]	SELF     	9 9 -5	; "open"
	13	[488]	GETTABLE 	11 8 -6	; "file"
	14	[488]	CALL     	9 3 2
	15	[488]	SELF     	9 9 -7	; "readSetting"
	16	[488]	LOADK    	11 -8	; "stats"
	17	[488]	CALL     	9 3 2
	18	[489]	TEST     	9 0 0
	19	[489]	JMP      	8	; to 28
	20	[489]	GETTABLE 	10 9 -9	; "title"
	21	[489]	EQ       	0 10 -10	; - ""
	22	[489]	JMP      	5	; to 28
	23	[490]	GETTABLE 	10 8 -6	; "file"
	24	[490]	SELF     	10 10 -11	; "match"
	25	[490]	LOADK    	12 -12	; "^.+/(.+)$"
	26	[490]	CALL     	10 3 2
	27	[490]	SETTABLE 	9 -9 10	; "title" -
	28	[492]	TEST     	9 0 0
	29	[492]	JMP      	19	; to 49
	30	[493]	GETTABLE 	10 8 -6	; "file"
	31	[493]	SETTABLE 	9 -6 10	; "file" -
	32	[494]	SELF     	10 0 -13	; "addBookStatToDB"
	33	[494]	MOVE     	12 9
	34	[494]	MOVE     	13 1
	35	[494]	CALL     	10 4 2
	36	[494]	TEST     	10 0 0
	37	[494]	JMP      	4	; to 42
	38	[495]	ADD      	2 2 -14	; - 1
	39	[496]	GETTABLE 	10 9 -9	; "title"
	40	[496]	SETTABLE 	3 10 -15	; - true
	41	[496]	JMP      	12	; to 54
	42	[498]	GETUPVAL 	10 2	; logger
	43	[498]	GETTABLE 	10 10 -16	; "dbg"
	44	[498]	LOADK    	11 -17	; "Book not converted: "
	45	[498]	GETTABLE 	12 9 -9	; "title"
	46	[498]	CONCAT   	11 11 12
	47	[498]	CALL     	10 2 1
	48	[499]	JMP      	5	; to 54
	49	[501]	GETUPVAL 	10 2	; logger
	50	[501]	GETTABLE 	10 10 -16	; "dbg"
	51	[501]	LOADK    	11 -18	; "Empty stats for file: "
	52	[501]	GETTABLE 	12 8 -6	; "file"
	53	[501]	CALL     	10 3 1
	54	[487]	TFORLOOP 	4 2
	55	[502]	JMP      	-45	; to 11
	56	[505]	GETUPVAL 	4 3	; lfs
	57	[505]	GETTABLE 	4 4 -19	; "attributes"
	58	[505]	GETUPVAL 	5 4	; statistics_dir
	59	[505]	LOADK    	6 -20	; "mode"
	60	[505]	CALL     	4 3 2
	61	[505]	EQ       	0 4 -21	; - "directory"
	62	[505]	JMP      	74	; to 137
	63	[506]	GETUPVAL 	4 3	; lfs
	64	[506]	GETTABLE 	4 4 -22	; "dir"
	65	[506]	GETUPVAL 	5 4	; statistics_dir
	66	[506]	CALL     	4 2 4
	67	[506]	JMP      	67	; to 135
	68	[507]	GETUPVAL 	8 4	; statistics_dir
	69	[507]	MOVE     	9 7
	70	[507]	CONCAT   	8 8 9
	71	[508]	GETUPVAL 	9 3	; lfs
	72	[508]	GETTABLE 	9 9 -19	; "attributes"
	73	[508]	MOVE     	10 8
	74	[508]	LOADK    	11 -20	; "mode"
	75	[508]	CALL     	9 3 2
	76	[508]	EQ       	0 9 -6	; - "file"
	77	[508]	JMP      	57	; to 135
	78	[509]	SELF     	9 0 -23	; "importFromFile"
	79	[509]	GETUPVAL 	11 4	; statistics_dir
	80	[509]	MOVE     	12 7
	81	[509]	CALL     	9 4 2
	82	[510]	TEST     	9 0 0
	83	[510]	JMP      	51	; to 135
	84	[510]	GETTABLE 	10 9 -24	; "total_time"
	85	[510]	LT       	0 -2 10	; 0 -
	86	[510]	JMP      	48	; to 135
	87	[510]	GETTABLE 	10 9 -9	; "title"
	88	[510]	GETTABLE 	10 3 10
	89	[510]	TEST     	10 0 1
	90	[510]	JMP      	44	; to 135
	91	[511]	NEWTABLE 	10 0 1
	92	[511]	NEWTABLE 	11 0 0
	93	[511]	SETTABLE 	10 -25 11	; "performance_in_pages" -
	94	[512]	GETGLOBAL	11 -3	; pairs
	95	[512]	GETTABLE 	12 9 -26	; "details"
	96	[512]	CALL     	11 2 4
	97	[512]	JMP      	4	; to 102
	98	[513]	GETTABLE 	16 10 -25	; "performance_in_pages"
	99	[513]	GETTABLE 	17 15 -27	; "time"
	100	[513]	GETTABLE 	18 15 -28	; "page"
	101	[513]	SETTABLE 	16 17 18
	102	[512]	TFORLOOP 	11 2
	103	[513]	JMP      	-6	; to 98
	104	[515]	GETTABLE 	11 9 -9	; "title"
	105	[515]	SETTABLE 	10 -9 11	; "title" -
	106	[516]	GETTABLE 	11 9 -29	; "authors"
	107	[516]	SETTABLE 	10 -29 11	; "authors" -
	108	[517]	GETTABLE 	11 9 -30	; "notes"
	109	[517]	SETTABLE 	10 -30 11	; "notes" -
	110	[518]	GETTABLE 	11 9 -31	; "highlights"
	111	[518]	SETTABLE 	10 -31 11	; "highlights" -
	112	[519]	GETTABLE 	11 9 -32	; "pages"
	113	[519]	SETTABLE 	10 -32 11	; "pages" -
	114	[520]	GETTABLE 	11 9 -33	; "series"
	115	[520]	SETTABLE 	10 -33 11	; "series" -
	116	[521]	GETTABLE 	11 9 -34	; "language"
	117	[521]	SETTABLE 	10 -34 11	; "language" -
	118	[522]	GETTABLE 	11 9 -24	; "total_time"
	119	[522]	SETTABLE 	10 -35 11	; "total_time_in_sec" -
	120	[523]	SETTABLE 	10 -6 -36	; "file" nil
	121	[524]	SELF     	11 0 -13	; "addBookStatToDB"
	122	[524]	MOVE     	13 10
	123	[524]	MOVE     	14 1
	124	[524]	CALL     	11 4 2
	125	[524]	TEST     	11 0 0
	126	[524]	JMP      	2	; to 129
	127	[525]	ADD      	2 2 -14	; - 1
	128	[525]	JMP      	6	; to 135
	129	[527]	GETUPVAL 	11 2	; logger
	130	[527]	GETTABLE 	11 11 -16	; "dbg"
	131	[527]	LOADK    	12 -37	; "Book not converted (old stats): "
	132	[527]	GETTABLE 	13 10 -9	; "title"
	133	[527]	CONCAT   	12 12 13
	134	[527]	CALL     	11 2 1
	135	[506]	TFORLOOP 	4 1
	136	[530]	JMP      	-69	; to 68
	137	[533]	RETURN   	2 2
	138	[534]	RETURN   	0 1

function <./plugins/statistics.koplugin/main.lua:536,572> (90 instructions, 360 bytes at 0x7fcdebc0cec0)
1 param, 20 slots, 3 upvalues, 7 locals, 27 constants, 0 functions
	1	[537]	GETUPVAL 	1 0	; SQ3
	2	[537]	GETTABLE 	1 1 -1	; "open"
	3	[537]	GETUPVAL 	2 1	; db_location
	4	[537]	CALL     	1 2 2
	5	[538]	LOADNIL  	2 2
	6	[545]	LOADK    	3 -2	; "        SELECT count(id)\n        FROM   book\n        WHERE  title = ?\n            AND authors = ?\n            AND md5 = ?\n    "
	7	[546]	SELF     	4 1 -3	; "prepare"
	8	[546]	MOVE     	6 3
	9	[546]	CALL     	4 3 2
	10	[547]	SELF     	5 4 -4	; "reset"
	11	[547]	CALL     	5 2 2
	12	[547]	SELF     	5 5 -5	; "bind"
	13	[547]	GETTABLE 	7 0 -6	; "data"
	14	[547]	GETTABLE 	7 7 -7	; "title"
	15	[547]	GETTABLE 	8 0 -6	; "data"
	16	[547]	GETTABLE 	8 8 -8	; "authors"
	17	[547]	GETTABLE 	9 0 -6	; "data"
	18	[547]	GETTABLE 	9 9 -9	; "md5"
	19	[547]	CALL     	5 5 2
	20	[547]	SELF     	5 5 -10	; "step"
	21	[547]	CALL     	5 2 2
	22	[548]	GETGLOBAL	6 -11	; tonumber
	23	[548]	GETTABLE 	7 5 -12	; 1
	24	[548]	CALL     	6 2 2
	25	[549]	EQ       	0 6 -13	; - 0
	26	[549]	JMP      	38	; to 65
	27	[550]	SELF     	7 1 -3	; "prepare"
	28	[550]	LOADK    	9 -14	; "INSERT INTO book VALUES(NULL, ?, ?, ?, ?, ?, ?, ?, ?, ?, ?, ?)"
	29	[550]	CALL     	7 3 2
	30	[550]	MOVE     	4 7
	31	[551]	SELF     	7 4 -4	; "reset"
	32	[551]	CALL     	7 2 2
	33	[551]	SELF     	7 7 -5	; "bind"
	34	[551]	GETTABLE 	9 0 -6	; "data"
	35	[551]	GETTABLE 	9 9 -7	; "title"
	36	[551]	GETTABLE 	10 0 -6	; "data"
	37	[551]	GETTABLE 	10 10 -8	; "authors"
	38	[551]	GETTABLE 	11 0 -6	; "data"
	39	[551]	GETTABLE 	11 11 -15	; "notes"
	40	[552]	GETUPVAL 	12 2	; TimeVal
	41	[552]	SELF     	12 12 -16	; "now"
	42	[552]	CALL     	12 2 2
	43	[552]	GETTABLE 	12 12 -17	; "sec"
	44	[552]	GETTABLE 	13 0 -6	; "data"
	45	[552]	GETTABLE 	13 13 -18	; "highlights"
	46	[552]	GETTABLE 	14 0 -6	; "data"
	47	[552]	GETTABLE 	14 14 -19	; "pages"
	48	[553]	GETTABLE 	15 0 -6	; "data"
	49	[553]	GETTABLE 	15 15 -20	; "series"
	50	[553]	GETTABLE 	16 0 -6	; "data"
	51	[553]	GETTABLE 	16 16 -21	; "language"
	52	[553]	GETTABLE 	17 0 -6	; "data"
	53	[553]	GETTABLE 	17 17 -9	; "md5"
	54	[553]	GETTABLE 	18 0 -22	; "curr_total_time"
	55	[553]	GETTABLE 	19 0 -23	; "curr_total_pages"
	56	[551]	CALL     	7 13 2
	57	[553]	SELF     	7 7 -10	; "step"
	58	[553]	CALL     	7 2 1
	59	[556]	LOADK    	3 -24	; "            SELECT last_insert_rowid() AS num;\n        "
	60	[557]	SELF     	7 1 -25	; "rowexec"
	61	[557]	MOVE     	9 3
	62	[557]	CALL     	7 3 2
	63	[557]	MOVE     	2 7
	64	[557]	JMP      	19	; to 84
	65	[565]	LOADK    	3 -26	; "            SELECT id\n            FROM   book\n            WHERE  title = ?\n                AND    authors = ?\n                AND    md5 = ?\n        "
	66	[566]	SELF     	7 1 -3	; "prepare"
	67	[566]	MOVE     	9 3
	68	[566]	CALL     	7 3 2
	69	[566]	MOVE     	4 7
	70	[567]	SELF     	7 4 -4	; "reset"
	71	[567]	CALL     	7 2 2
	72	[567]	SELF     	7 7 -5	; "bind"
	73	[567]	GETTABLE 	9 0 -6	; "data"
	74	[567]	GETTABLE 	9 9 -7	; "title"
	75	[567]	GETTABLE 	10 0 -6	; "data"
	76	[567]	GETTABLE 	10 10 -8	; "authors"
	77	[567]	GETTABLE 	11 0 -6	; "data"
	78	[567]	GETTABLE 	11 11 -9	; "md5"
	79	[567]	CALL     	7 5 2
	80	[567]	SELF     	7 7 -10	; "step"
	81	[567]	CALL     	7 2 2
	82	[567]	MOVE     	5 7
	83	[568]	GETTABLE 	2 5 -12	; 1
	84	[570]	SELF     	7 1 -27	; "close"
	85	[570]	CALL     	7 2 1
	86	[571]	GETGLOBAL	7 -11	; tonumber
	87	[571]	MOVE     	8 2
	88	[571]	TAILCALL 	7 2 0
	89	[571]	RETURN   	7 0
	90	[572]	RETURN   	0 1

function <./plugins/statistics.koplugin/main.lua:574,632> (135 instructions, 540 bytes at 0x7fcdebc0d4b0)
2 params, 18 slots, 4 upvalues, 18 locals, 39 constants, 0 functions
	1	[575]	GETTABLE 	2 0 -1	; "pages_stats"
	2	[575]	GETUPVAL 	3 0	; TimeVal
	3	[575]	SELF     	3 3 -2	; "now"
	4	[575]	CALL     	3 2 2
	5	[575]	GETTABLE 	3 3 -3	; "sec"
	6	[575]	GETTABLE 	4 0 -4	; "curr_page"
	7	[575]	SETTABLE 	2 3 4
	8	[576]	EQ       	1 1 -5	; - nil
	9	[576]	JMP      	6	; to 16
	10	[576]	GETUPVAL 	2 1	; util
	11	[576]	GETTABLE 	2 2 -6	; "tableSize"
	12	[576]	GETTABLE 	3 0 -1	; "pages_stats"
	13	[576]	CALL     	2 2 2
	14	[576]	LT       	0 2 -7	; - 2
	15	[576]	JMP      	1	; to 17
	16	[577]	RETURN   	0 1
	17	[579]	LOADNIL  	2 2
	18	[580]	GETUPVAL 	3 2	; SQ3
	19	[580]	GETTABLE 	3 3 -8	; "open"
	20	[580]	GETUPVAL 	4 3	; db_location
	21	[580]	CALL     	3 2 2
	22	[581]	NEWTABLE 	4 0 0
	23	[582]	GETGLOBAL	5 -9	; pairs
	24	[582]	GETTABLE 	6 0 -1	; "pages_stats"
	25	[582]	CALL     	5 2 4
	26	[582]	JMP      	5	; to 32
	27	[583]	GETGLOBAL	10 -10	; table
	28	[583]	GETTABLE 	10 10 -11	; "insert"
	29	[583]	MOVE     	11 4
	30	[583]	MOVE     	12 8
	31	[583]	CALL     	10 3 1
	32	[582]	TFORLOOP 	5 2
	33	[583]	JMP      	-7	; to 27
	34	[585]	GETGLOBAL	5 -10	; table
	35	[585]	GETTABLE 	5 5 -12	; "sort"
	36	[585]	MOVE     	6 4
	37	[585]	CALL     	5 2 1
	38	[586]	SELF     	5 3 -13	; "exec"
	39	[586]	LOADK    	7 -14	; "BEGIN"
	40	[586]	CALL     	5 3 1
	41	[587]	SELF     	5 3 -15	; "prepare"
	42	[587]	LOADK    	7 -16	; "INSERT OR IGNORE INTO page_stat VALUES(?, ?, ?, ?)"
	43	[587]	CALL     	5 3 2
	44	[588]	LOADK    	6 -17	; 1
	45	[588]	LEN      	7 4
	46	[588]	SUB      	7 7 -17	; - 1
	47	[588]	LOADK    	8 -17	; 1
	48	[588]	FORPREP  	6 23	; to 72
	49	[589]	ADD      	10 9 -17	; - 1
	50	[589]	GETTABLE 	10 4 10
	51	[589]	GETTABLE 	11 4 9
	52	[589]	SUB      	2 10 11
	53	[590]	GETTABLE 	10 0 -18	; "page_min_read_sec"
	54	[590]	LE       	0 10 2
	55	[590]	JMP      	16	; to 72
	56	[591]	SELF     	10 5 -19	; "reset"
	57	[591]	CALL     	10 2 2
	58	[591]	SELF     	10 10 -20	; "bind"
	59	[591]	MOVE     	12 1
	60	[592]	GETTABLE 	13 0 -1	; "pages_stats"
	61	[592]	GETTABLE 	14 4 9
	62	[592]	GETTABLE 	13 13 14
	63	[593]	GETTABLE 	14 4 9
	64	[594]	GETGLOBAL	15 -21	; math
	65	[594]	GETTABLE 	15 15 -22	; "min"
	66	[594]	MOVE     	16 2
	67	[594]	GETTABLE 	17 0 -23	; "page_max_read_sec"
	68	[594]	CALL     	15 3 0
	69	[591]	CALL     	10 0 2
	70	[594]	SELF     	10 10 -24	; "step"
	71	[594]	CALL     	10 2 1
	72	[588]	FORLOOP  	6 -24	; to 49
	73	[597]	SELF     	6 3 -13	; "exec"
	74	[597]	LOADK    	8 -25	; "COMMIT"
	75	[597]	CALL     	6 3 1
	76	[603]	LOADK    	6 -26	; "        SELECT count(DISTINCT page),\n               sum(period)\n        FROM   page_stat\n        WHERE  id_book = '%s'\n    "
	77	[604]	SELF     	7 3 -27	; "rowexec"
	78	[604]	GETGLOBAL	9 -28	; string
	79	[604]	GETTABLE 	9 9 -29	; "format"
	80	[604]	MOVE     	10 6
	81	[604]	MOVE     	11 1
	82	[604]	CALL     	9 3 0
	83	[604]	CALL     	7 0 3
	84	[614]	LOADK    	6 -30	; "        UPDATE book\n        SET    last_open = ?,\n               notes = ?,\n               highlights = ?,\n               total_read_time = ?,\n               total_read_pages = ?,\n               pages = ?\n        WHERE  id = ?\n    "
	85	[615]	SELF     	9 3 -15	; "prepare"
	86	[615]	MOVE     	11 6
	87	[615]	CALL     	9 3 2
	88	[615]	MOVE     	5 9
	89	[616]	SELF     	9 5 -19	; "reset"
	90	[616]	CALL     	9 2 2
	91	[616]	SELF     	9 9 -20	; "bind"
	92	[616]	GETUPVAL 	11 0	; TimeVal
	93	[616]	SELF     	11 11 -2	; "now"
	94	[616]	CALL     	11 2 2
	95	[616]	GETTABLE 	11 11 -3	; "sec"
	96	[616]	GETTABLE 	12 0 -31	; "data"
	97	[616]	GETTABLE 	12 12 -32	; "notes"
	98	[616]	GETTABLE 	13 0 -31	; "data"
	99	[616]	GETTABLE 	13 13 -33	; "highlights"
	100	[616]	MOVE     	14 8
	101	[616]	MOVE     	15 7
	102	[617]	GETTABLE 	16 0 -31	; "data"
	103	[617]	GETTABLE 	16 16 -34	; "pages"
	104	[617]	MOVE     	17 1
	105	[616]	CALL     	9 9 2
	106	[617]	SELF     	9 9 -24	; "step"
	107	[617]	CALL     	9 2 1
	108	[618]	TEST     	7 0 0
	109	[618]	JMP      	5	; to 115
	110	[619]	GETGLOBAL	9 -36	; tonumber
	111	[619]	MOVE     	10 7
	112	[619]	CALL     	9 2 2
	113	[619]	SETTABLE 	0 -35 9	; "total_read_pages" -
	114	[619]	JMP      	1	; to 116
	115	[621]	SETTABLE 	0 -35 -37	; "total_read_pages" 0
	116	[623]	TEST     	8 0 0
	117	[623]	JMP      	5	; to 123
	118	[624]	GETGLOBAL	9 -36	; tonumber
	119	[624]	MOVE     	10 8
	120	[624]	CALL     	9 2 2
	121	[624]	SETTABLE 	0 -38 9	; "total_read_time" -
	122	[624]	JMP      	1	; to 124
	123	[626]	SETTABLE 	0 -38 -37	; "total_read_time" 0
	124	[628]	NEWTABLE 	9 0 0
	125	[628]	SETTABLE 	0 -1 9	; "pages_stats" -
	126	[630]	GETTABLE 	9 0 -1	; "pages_stats"
	127	[630]	GETUPVAL 	10 0	; TimeVal
	128	[630]	SELF     	10 10 -2	; "now"
	129	[630]	CALL     	10 2 2
	130	[630]	GETTABLE 	10 10 -3	; "sec"
	131	[630]	GETTABLE 	11 0 -4	; "curr_page"
	132	[630]	SETTABLE 	9 10 11
	133	[631]	SELF     	9 3 -39	; "close"
	134	[631]	CALL     	9 2 1
	135	[632]	RETURN   	0 1

function <./plugins/statistics.koplugin/main.lua:634,658> (37 instructions, 148 bytes at 0x7fcdebc0d5e0)
2 params, 9 slots, 2 upvalues, 6 locals, 9 constants, 0 functions
	1	[635]	EQ       	0 1 -1	; - nil
	2	[635]	JMP      	1	; to 4
	3	[636]	RETURN   	0 1
	4	[638]	GETUPVAL 	2 0	; SQ3
	5	[638]	GETTABLE 	2 2 -2	; "open"
	6	[638]	GETUPVAL 	3 1	; db_location
	7	[638]	CALL     	2 2 2
	8	[644]	LOADK    	3 -3	; "        SELECT total_read_pages,\n               total_read_time\n        FROM   book\n        WHERE  id = '%s'\n    "
	9	[645]	SELF     	4 2 -4	; "rowexec"
	10	[645]	GETGLOBAL	6 -5	; string
	11	[645]	GETTABLE 	6 6 -6	; "format"
	12	[645]	MOVE     	7 3
	13	[645]	MOVE     	8 1
	14	[645]	CALL     	6 3 0
	15	[645]	CALL     	4 0 3
	16	[646]	TEST     	4 0 0
	17	[646]	JMP      	5	; to 23
	18	[647]	GETGLOBAL	6 -7	; tonumber
	19	[647]	MOVE     	7 4
	20	[647]	CALL     	6 2 2
	21	[647]	MOVE     	4 6
	22	[647]	JMP      	1	; to 24
	23	[649]	LOADK    	4 -8	; 0
	24	[651]	TEST     	5 0 0
	25	[651]	JMP      	5	; to 31
	26	[652]	GETGLOBAL	6 -7	; tonumber
	27	[652]	MOVE     	7 5
	28	[652]	CALL     	6 2 2
	29	[652]	MOVE     	5 6
	30	[652]	JMP      	1	; to 32
	31	[654]	LOADK    	5 -8	; 0
	32	[656]	SELF     	6 2 -9	; "close"
	33	[656]	CALL     	6 2 1
	34	[657]	MOVE     	6 4
	35	[657]	MOVE     	7 5
	36	[657]	RETURN   	6 3
	37	[658]	RETURN   	0 1

function <./plugins/statistics.koplugin/main.lua:660,667> (17 instructions, 68 bytes at 0x7fcdebc0e210)
1 param, 4 slots, 0 upvalues, 2 locals, 6 constants, 0 functions
	1	[661]	GETTABLE 	1 0 -1	; "view"
	2	[661]	GETTABLE 	1 1 -2	; "document"
	3	[661]	SELF     	1 1 -3	; "getProps"
	4	[661]	CALL     	1 2 2
	5	[662]	GETTABLE 	2 1 -4	; "title"
	6	[662]	EQ       	1 2 -5	; - "No document"
	7	[662]	JMP      	3	; to 11
	8	[662]	GETTABLE 	2 1 -4	; "title"
	9	[662]	EQ       	0 2 -6	; - ""
	10	[662]	JMP      	5	; to 16
	11	[664]	GETTABLE 	2 0 -1	; "view"
	12	[664]	GETTABLE 	2 2 -2	; "document"
	13	[664]	SELF     	2 2 -3	; "getProps"
	14	[664]	CALL     	2 2 2
	15	[664]	MOVE     	1 2
	16	[666]	RETURN   	1 2
	17	[667]	RETURN   	0 1

function <./plugins/statistics.koplugin/main.lua:669,695> (14 instructions, 56 bytes at 0x7fcdebc0e690)
1 param, 4 slots, 2 upvalues, 1 local, 4 constants, 2 functions
	1	[670]	NEWTABLE 	1 0 3
	2	[671]	GETUPVAL 	2 0	; _
	3	[671]	LOADK    	3 -2	; "Enabled"
	4	[671]	CALL     	2 2 2
	5	[671]	SETTABLE 	1 -1 2	; "text" -
	6	[672]	CLOSURE  	2 0	; 0x7fcdebc0ec90
	7	[672]	MOVE     	0 0
	8	[672]	SETTABLE 	1 -3 2	; "checked_func" -
	9	[693]	CLOSURE  	2 1	; 0x7fcdebc0efd0
	10	[693]	MOVE     	0 0
	11	[693]	GETUPVAL 	0 1	; TimeVal
	12	[693]	SETTABLE 	1 -4 2	; "callback" -
	13	[694]	RETURN   	1 2
	14	[695]	RETURN   	0 1

function <./plugins/statistics.koplugin/main.lua:672,672> (4 instructions, 16 bytes at 0x7fcdebc0ec90)
0 params, 2 slots, 1 upvalue, 0 locals, 1 constant, 0 functions
	1	[672]	GETUPVAL 	0 0	; self
	2	[672]	GETTABLE 	0 0 -1	; "is_enabled"
	3	[672]	RETURN   	0 2
	4	[672]	RETURN   	0 1

function <./plugins/statistics.koplugin/main.lua:673,693> (75 instructions, 300 bytes at 0x7fcdebc0efd0)
0 params, 4 slots, 2 upvalues, 0 locals, 20 constants, 0 functions
	1	[675]	GETUPVAL 	0 0	; self
	2	[675]	GETTABLE 	0 0 -1	; "is_enabled"
	3	[675]	TEST     	0 0 0
	4	[675]	JMP      	18	; to 23
	5	[675]	GETUPVAL 	0 0	; self
	6	[675]	SELF     	0 0 -2	; "isDocless"
	7	[675]	CALL     	0 2 2
	8	[675]	TEST     	0 0 1
	9	[675]	JMP      	13	; to 23
	10	[676]	GETUPVAL 	0 0	; self
	11	[676]	SELF     	0 0 -3	; "insertDB"
	12	[676]	GETUPVAL 	2 0	; self
	13	[676]	GETTABLE 	2 2 -4	; "id_curr_book"
	14	[676]	CALL     	0 3 1
	15	[677]	GETUPVAL 	0 0	; self
	16	[677]	GETTABLE 	0 0 -5	; "ui"
	17	[677]	GETTABLE 	0 0 -6	; "doc_settings"
	18	[677]	SELF     	0 0 -7	; "saveSetting"
	19	[677]	LOADK    	2 -8	; "stats"
	20	[677]	GETUPVAL 	3 0	; self
	21	[677]	GETTABLE 	3 3 -9	; "data"
	22	[677]	CALL     	0 4 1
	23	[680]	GETUPVAL 	0 0	; self
	24	[680]	GETUPVAL 	1 0	; self
	25	[680]	GETTABLE 	1 1 -1	; "is_enabled"
	26	[680]	NOT      	1 1
	27	[680]	SETTABLE 	0 -1 1	; "is_enabled" -
	28	[682]	GETUPVAL 	0 0	; self
	29	[682]	GETTABLE 	0 0 -1	; "is_enabled"
	30	[682]	TEST     	0 0 0
	31	[682]	JMP      	30	; to 62
	32	[682]	GETUPVAL 	0 0	; self
	33	[682]	SELF     	0 0 -2	; "isDocless"
	34	[682]	CALL     	0 2 2
	35	[682]	TEST     	0 0 1
	36	[682]	JMP      	25	; to 62
	37	[683]	GETUPVAL 	0 0	; self
	38	[683]	SELF     	0 0 -10	; "initData"
	39	[683]	CALL     	0 2 1
	40	[684]	GETUPVAL 	0 0	; self
	41	[684]	NEWTABLE 	1 0 0
	42	[684]	SETTABLE 	0 -11 1	; "pages_stats" -
	43	[685]	GETUPVAL 	0 0	; self
	44	[685]	GETUPVAL 	1 1	; TimeVal
	45	[685]	SELF     	1 1 -13	; "now"
	46	[685]	CALL     	1 2 2
	47	[685]	GETTABLE 	1 1 -14	; "sec"
	48	[685]	SETTABLE 	0 -12 1	; "start_current_period" -
	49	[686]	GETUPVAL 	0 0	; self
	50	[686]	GETUPVAL 	1 0	; self
	51	[686]	GETTABLE 	1 1 -5	; "ui"
	52	[686]	SELF     	1 1 -16	; "getCurrentPage"
	53	[686]	CALL     	1 2 2
	54	[686]	SETTABLE 	0 -15 1	; "curr_page" -
	55	[687]	GETUPVAL 	0 0	; self
	56	[687]	GETTABLE 	0 0 -11	; "pages_stats"
	57	[687]	GETUPVAL 	1 0	; self
	58	[687]	GETTABLE 	1 1 -12	; "start_current_period"
	59	[687]	GETUPVAL 	2 0	; self
	60	[687]	GETTABLE 	2 2 -15	; "curr_page"
	61	[687]	SETTABLE 	0 1 2
	62	[689]	GETUPVAL 	0 0	; self
	63	[689]	SELF     	0 0 -17	; "saveSettings"
	64	[689]	CALL     	0 2 1
	65	[690]	GETUPVAL 	0 0	; self
	66	[690]	SELF     	0 0 -2	; "isDocless"
	67	[690]	CALL     	0 2 2
	68	[690]	TEST     	0 0 1
	69	[690]	JMP      	5	; to 75
	70	[691]	GETUPVAL 	0 0	; self
	71	[691]	GETTABLE 	0 0 -18	; "view"
	72	[691]	GETTABLE 	0 0 -19	; "footer"
	73	[691]	SELF     	0 0 -20	; "updateFooter"
	74	[691]	CALL     	0 2 1
	75	[693]	RETURN   	0 1

function <./plugins/statistics.koplugin/main.lua:697,878> (187 instructions, 748 bytes at 0x7fcdebc0f200)
2 params, 16 slots, 12 upvalues, 2 locals, 25 constants, 22 functions
	1	[698]	NEWTABLE 	2 0 2
	2	[699]	GETUPVAL 	3 0	; _
	3	[699]	LOADK    	4 -3	; "Reading statistics"
	4	[699]	CALL     	3 2 2
	5	[699]	SETTABLE 	2 -2 3	; "text" -
	6	[700]	NEWTABLE 	3 7 0
	7	[701]	SELF     	4 0 -5	; "getStatisticEnabledMenuItem"
	8	[701]	CALL     	4 2 2
	9	[701]	NEWTABLE 	5 0 2
	10	[703]	GETUPVAL 	6 0	; _
	11	[703]	LOADK    	7 -6	; "Settings"
	12	[703]	CALL     	6 2 2
	13	[703]	SETTABLE 	5 -2 6	; "text" -
	14	[704]	NEWTABLE 	6 5 0
	15	[704]	NEWTABLE 	7 0 4
	16	[709]	CLOSURE  	8 0	; 0x7fcdebc0f7e0
	17	[709]	GETUPVAL 	0 1	; T
	18	[709]	GETUPVAL 	0 0	; _
	19	[709]	MOVE     	0 0
	20	[709]	SETTABLE 	7 -7 8	; "text_func" -
	21	[749]	CLOSURE  	8 1	; 0x7fcdebc10320
	22	[749]	GETUPVAL 	0 0	; _
	23	[749]	MOVE     	0 0
	24	[749]	GETUPVAL 	0 2	; DEFAULT_MIN_READ_SEC
	25	[749]	GETUPVAL 	0 3	; DEFAULT_MAX_READ_SEC
	26	[749]	GETUPVAL 	0 4	; UIManager
	27	[749]	SETTABLE 	7 -8 8	; "callback" -
	28	[750]	SETTABLE 	7 -9 -10	; "keep_menu_open" true
	29	[751]	SETTABLE 	7 -11 -10	; "separator" true
	30	[752]	NEWTABLE 	8 0 2
	31	[757]	CLOSURE  	9 2	; 0x7fcdebc0f700
	32	[757]	GETUPVAL 	0 1	; T
	33	[757]	GETUPVAL 	0 0	; _
	34	[757]	GETUPVAL 	0 5	; longDayOfWeekTranslation
	35	[757]	GETUPVAL 	0 6	; weekDays
	36	[757]	MOVE     	0 0
	37	[757]	SETTABLE 	8 -7 9	; "text_func" -
	38	[758]	NEWTABLE 	9 4 0
	39	[758]	NEWTABLE 	10 0 3
	40	[760]	GETUPVAL 	11 5	; longDayOfWeekTranslation
	41	[760]	GETUPVAL 	12 6	; weekDays
	42	[760]	GETTABLE 	12 12 -12	; 6
	43	[760]	GETTABLE 	11 11 12
	44	[760]	SETTABLE 	10 -2 11	; "text" -
	45	[761]	CLOSURE  	11 3	; 0x7fcdebc102a0
	46	[761]	MOVE     	0 0
	47	[761]	SETTABLE 	10 -13 11	; "checked_func" -
	48	[762]	CLOSURE  	11 4	; 0x7fcdebc10070
	49	[762]	MOVE     	0 0
	50	[762]	SETTABLE 	10 -8 11	; "callback" -
	51	[763]	NEWTABLE 	11 0 3
	52	[765]	GETUPVAL 	12 5	; longDayOfWeekTranslation
	53	[765]	GETUPVAL 	13 6	; weekDays
	54	[765]	GETTABLE 	13 13 -14	; 7
	55	[765]	GETTABLE 	12 12 13
	56	[765]	SETTABLE 	11 -2 12	; "text" -
	57	[766]	CLOSURE  	12 5	; 0x7fcdebc11870
	58	[766]	MOVE     	0 0
	59	[766]	SETTABLE 	11 -13 12	; "checked_func" -
	60	[767]	CLOSURE  	12 6	; 0x7fcdebc118f0
	61	[767]	MOVE     	0 0
	62	[767]	SETTABLE 	11 -8 12	; "callback" -
	63	[768]	NEWTABLE 	12 0 3
	64	[770]	GETUPVAL 	13 5	; longDayOfWeekTranslation
	65	[770]	GETUPVAL 	14 6	; weekDays
	66	[770]	GETTABLE 	14 14 -15	; 1
	67	[770]	GETTABLE 	13 13 14
	68	[770]	SETTABLE 	12 -2 13	; "text" -
	69	[771]	CLOSURE  	13 7	; 0x7fcdebc116d0
	70	[771]	MOVE     	0 0
	71	[771]	SETTABLE 	12 -13 13	; "checked_func" -
	72	[772]	CLOSURE  	13 8	; 0x7fcdebc112f0
	73	[772]	MOVE     	0 0
	74	[772]	SETTABLE 	12 -8 13	; "callback" -
	75	[773]	NEWTABLE 	13 0 3
	76	[775]	GETUPVAL 	14 5	; longDayOfWeekTranslation
	77	[775]	GETUPVAL 	15 6	; weekDays
	78	[775]	GETTABLE 	15 15 -16	; 2
	79	[775]	GETTABLE 	14 14 15
	80	[775]	SETTABLE 	13 -2 14	; "text" -
	81	[776]	CLOSURE  	14 9	; 0x7fcdebc11370
	82	[776]	MOVE     	0 0
	83	[776]	SETTABLE 	13 -13 14	; "checked_func" -
	84	[777]	CLOSURE  	14 10	; 0x7fcdebc12240
	85	[777]	MOVE     	0 0
	86	[777]	SETTABLE 	13 -8 14	; "callback" -
	87	[779]	SETLIST  	9 4 1	; 1
	88	[779]	SETTABLE 	8 -4 9	; "sub_item_table" -
	89	[780]	NEWTABLE 	9 0 3
	90	[784]	CLOSURE  	10 11	; 0x7fcdebc125e0
	91	[784]	GETUPVAL 	0 1	; T
	92	[784]	GETUPVAL 	0 0	; _
	93	[784]	MOVE     	0 0
	94	[784]	SETTABLE 	9 -7 10	; "text_func" -
	95	[805]	CLOSURE  	10 12	; 0x7fcdebc12900
	96	[805]	GETUPVAL 	0 4	; UIManager
	97	[805]	GETUPVAL 	0 7	; Screen
	98	[805]	MOVE     	0 0
	99	[805]	GETUPVAL 	0 0	; _
	100	[805]	GETUPVAL 	0 8	; DEFAULT_CALENDAR_NB_BOOK_SPANS
	101	[805]	SETTABLE 	9 -8 10	; "callback" -
	102	[806]	SETTABLE 	9 -9 -10	; "keep_menu_open" true
	103	[807]	NEWTABLE 	10 0 3
	104	[809]	GETUPVAL 	11 0	; _
	105	[809]	LOADK    	12 -17	; "Show hourly histogram in calendar days"
	106	[809]	CALL     	11 2 2
	107	[809]	SETTABLE 	10 -2 11	; "text" -
	108	[810]	CLOSURE  	11 13	; 0x7fcdebc134a0
	109	[810]	MOVE     	0 0
	110	[810]	SETTABLE 	10 -13 11	; "checked_func" -
	111	[813]	CLOSURE  	11 14	; 0x7fcdebc139a0
	112	[813]	MOVE     	0 0
	113	[813]	SETTABLE 	10 -8 11	; "callback" -
	114	[814]	NEWTABLE 	11 0 3
	115	[816]	GETUPVAL 	12 0	; _
	116	[816]	LOADK    	13 -18	; "Allow browsing coming months"
	117	[816]	CALL     	12 2 2
	118	[816]	SETTABLE 	11 -2 12	; "text" -
	119	[817]	CLOSURE  	12 15	; 0x7fcdebc13b40
	120	[817]	MOVE     	0 0
	121	[817]	SETTABLE 	11 -13 12	; "checked_func" -
	122	[820]	CLOSURE  	12 16	; 0x7fcdebc13cf0
	123	[820]	MOVE     	0 0
	124	[820]	SETTABLE 	11 -8 12	; "callback" -
	125	[822]	SETLIST  	6 5 1	; 1
	126	[822]	SETTABLE 	5 -4 6	; "sub_item_table" -
	127	[823]	NEWTABLE 	6 0 3
	128	[825]	GETUPVAL 	7 0	; _
	129	[825]	LOADK    	8 -19	; "Reset statistics"
	130	[825]	CALL     	7 2 2
	131	[825]	SETTABLE 	6 -2 7	; "text" -
	132	[826]	SELF     	7 0 -20	; "genResetBookSubItemTable"
	133	[826]	CALL     	7 2 2
	134	[826]	SETTABLE 	6 -4 7	; "sub_item_table" -
	135	[827]	SETTABLE 	6 -11 -10	; "separator" true
	136	[828]	NEWTABLE 	7 0 4
	137	[830]	GETUPVAL 	8 0	; _
	138	[830]	LOADK    	9 -21	; "Current book"
	139	[830]	CALL     	8 2 2
	140	[830]	SETTABLE 	7 -2 8	; "text" -
	141	[831]	SETTABLE 	7 -9 -10	; "keep_menu_open" true
	142	[837]	CLOSURE  	8 17	; 0x7fcdebc121c0
	143	[837]	GETUPVAL 	0 4	; UIManager
	144	[837]	GETUPVAL 	0 9	; KeyValuePage
	145	[837]	GETUPVAL 	0 0	; _
	146	[837]	MOVE     	0 0
	147	[837]	SETTABLE 	7 -8 8	; "callback" -
	148	[838]	CLOSURE  	8 18	; 0x7fcdebc11df0
	149	[838]	MOVE     	0 0
	150	[838]	SETTABLE 	7 -22 8	; "enabled_func" -
	151	[839]	NEWTABLE 	8 0 3
	152	[841]	GETUPVAL 	9 0	; _
	153	[841]	LOADK    	10 -23	; "Reading progress"
	154	[841]	CALL     	9 2 2
	155	[841]	SETTABLE 	8 -2 9	; "text" -
	156	[842]	SETTABLE 	8 -9 -10	; "keep_menu_open" true
	157	[860]	CLOSURE  	9 19	; 0x7fcdebc143f0
	158	[860]	MOVE     	0 0
	159	[860]	GETUPVAL 	0 4	; UIManager
	160	[860]	GETUPVAL 	0 10	; ReaderProgress
	161	[860]	GETUPVAL 	0 11	; InfoMessage
	162	[860]	GETUPVAL 	0 1	; T
	163	[860]	GETUPVAL 	0 0	; _
	164	[860]	SETTABLE 	8 -8 9	; "callback" -
	165	[861]	NEWTABLE 	9 0 3
	166	[863]	GETUPVAL 	10 0	; _
	167	[863]	LOADK    	11 -24	; "Time range"
	168	[863]	CALL     	10 2 2
	169	[863]	SETTABLE 	9 -2 10	; "text" -
	170	[864]	SETTABLE 	9 -9 -10	; "keep_menu_open" true
	171	[867]	CLOSURE  	10 20	; 0x7fcdebc14900
	172	[867]	MOVE     	0 0
	173	[867]	SETTABLE 	9 -8 10	; "callback" -
	174	[868]	NEWTABLE 	10 0 3
	175	[870]	GETUPVAL 	11 0	; _
	176	[870]	LOADK    	12 -25	; "Calendar view"
	177	[870]	CALL     	11 2 2
	178	[870]	SETTABLE 	10 -2 11	; "text" -
	179	[871]	SETTABLE 	10 -9 -10	; "keep_menu_open" true
	180	[874]	CLOSURE  	11 21	; 0x7fcdebc14b80
	181	[874]	GETUPVAL 	0 4	; UIManager
	182	[874]	MOVE     	0 0
	183	[874]	SETTABLE 	10 -8 11	; "callback" -
	184	[876]	SETLIST  	3 7 1	; 1
	185	[876]	SETTABLE 	2 -4 3	; "sub_item_table" -
	186	[877]	SETTABLE 	1 -1 2	; "statistics" -
	187	[878]	RETURN   	0 1

function <./plugins/statistics.koplugin/main.lua:706,709> (11 instructions, 44 bytes at 0x7fcdebc0f7e0)
0 params, 4 slots, 3 upvalues, 0 locals, 3 constants, 0 functions
	1	[707]	GETUPVAL 	0 0	; T
	2	[707]	GETUPVAL 	1 1	; _
	3	[707]	LOADK    	2 -1	; "Read page duration limits: %1 s / %2 s"
	4	[707]	CALL     	1 2 2
	5	[708]	GETUPVAL 	2 2	; self
	6	[708]	GETTABLE 	2 2 -2	; "page_min_read_sec"
	7	[708]	GETUPVAL 	3 2	; self
	8	[708]	GETTABLE 	3 3 -3	; "page_max_read_sec"
	9	[707]	TAILCALL 	0 4 0
	10	[708]	RETURN   	0 0
	11	[709]	RETURN   	0 1

function <./plugins/statistics.koplugin/main.lua:710,749> (60 instructions, 240 bytes at 0x7fcdebc10320)
1 param, 8 slots, 5 upvalues, 3 locals, 37 constants, 1 function
	1	[711]	GETGLOBAL	1 -1	; require
	2	[711]	LOADK    	2 -2	; "/ui/widget/doublespinwidget"
	3	[711]	CALL     	1 2 2
	4	[712]	LOADNIL  	2 2
	5	[713]	SELF     	3 1 -3	; "new"
	6	[713]	NEWTABLE 	5 0 18
	7	[714]	GETUPVAL 	6 0	; _
	8	[714]	LOADK    	7 -5	; "Min"
	9	[714]	CALL     	6 2 2
	10	[714]	SETTABLE 	5 -4 6	; "left_text" -
	11	[715]	GETUPVAL 	6 1	; self
	12	[715]	GETTABLE 	6 6 -7	; "page_min_read_sec"
	13	[715]	SETTABLE 	5 -6 6	; "left_value" -
	14	[716]	GETUPVAL 	6 2	; DEFAULT_MIN_READ_SEC
	15	[716]	SETTABLE 	5 -8 6	; "left_default" -
	16	[717]	SETTABLE 	5 -9 -10	; "left_min" 3
	17	[718]	SETTABLE 	5 -11 -12	; "left_max" 120
	18	[719]	SETTABLE 	5 -13 -14	; "left_step" 1
	19	[720]	SETTABLE 	5 -15 -16	; "left_hold_step" 10
	20	[721]	GETUPVAL 	6 0	; _
	21	[721]	LOADK    	7 -18	; "Max"
	22	[721]	CALL     	6 2 2
	23	[721]	SETTABLE 	5 -17 6	; "right_text" -
	24	[722]	GETUPVAL 	6 1	; self
	25	[722]	GETTABLE 	6 6 -20	; "page_max_read_sec"
	26	[722]	SETTABLE 	5 -19 6	; "right_value" -
	27	[723]	GETUPVAL 	6 3	; DEFAULT_MAX_READ_SEC
	28	[723]	SETTABLE 	5 -21 6	; "right_default" -
	29	[724]	SETTABLE 	5 -22 -16	; "right_min" 10
	30	[725]	SETTABLE 	5 -23 -24	; "right_max" 7200
	31	[726]	SETTABLE 	5 -25 -16	; "right_step" 10
	32	[727]	SETTABLE 	5 -26 -27	; "right_hold_step" 60
	33	[728]	SETTABLE 	5 -28 -29	; "default_values" true
	34	[729]	GETUPVAL 	6 0	; _
	35	[729]	LOADK    	7 -31	; "Use defaults"
	36	[729]	CALL     	6 2 2
	37	[729]	SETTABLE 	5 -30 6	; "default_text" -
	38	[730]	GETUPVAL 	6 0	; _
	39	[730]	LOADK    	7 -33	; "Read page duration limits"
	40	[730]	CALL     	6 2 2
	41	[730]	SETTABLE 	5 -32 6	; "title_text" -
	42	[731]	GETUPVAL 	6 0	; _
	43	[734]	LOADK    	7 -35	; "Set min and max time spent (in seconds) on a page for it to be counted as read in statistics.\nThe min value ensures pages you quickly browse and skip are not included.\nThe max value ensures a page you stay on for a long time (because you fell asleep or went away) will be included, but with a duration capped to this specified max value."
	44	[731]	CALL     	6 2 2
	45	[734]	SETTABLE 	5 -34 6	; "info_text" -
	46	[746]	CLOSURE  	6 0	; 0x7fcdebc10690
	47	[746]	GETUPVAL 	0 2	; DEFAULT_MIN_READ_SEC
	48	[746]	GETUPVAL 	0 3	; DEFAULT_MAX_READ_SEC
	49	[746]	GETUPVAL 	0 1	; self
	50	[746]	GETUPVAL 	0 4	; UIManager
	51	[746]	MOVE     	0 2
	52	[746]	MOVE     	0 0
	53	[746]	SETTABLE 	5 -36 6	; "callback" -
	54	[713]	CALL     	3 3 2
	55	[747]	MOVE     	2 3
	56	[748]	GETUPVAL 	3 4	; UIManager
	57	[748]	SELF     	3 3 -37	; "show"
	58	[748]	MOVE     	5 2
	59	[748]	CALL     	3 3 1
	60	[749]	RETURN   	0 1

function <./plugins/statistics.koplugin/main.lua:735,746> (26 instructions, 104 bytes at 0x7fcdebc10690)
2 params, 5 slots, 6 upvalues, 2 locals, 5 constants, 0 functions
	1	[736]	TEST     	0 0 1
	2	[736]	JMP      	1	; to 4
	3	[736]	GETUPVAL 	0 0	; DEFAULT_MIN_READ_SEC
	4	[737]	TEST     	1 0 1
	5	[737]	JMP      	1	; to 7
	6	[737]	GETUPVAL 	1 1	; DEFAULT_MAX_READ_SEC
	7	[738]	LT       	0 1 0
	8	[738]	JMP      	3	; to 12
	9	[739]	MOVE     	2 1
	10	[739]	MOVE     	1 0
	11	[739]	MOVE     	0 2
	12	[741]	GETUPVAL 	2 2	; self
	13	[741]	SETTABLE 	2 -1 0	; "page_min_read_sec" -
	14	[742]	GETUPVAL 	2 2	; self
	15	[742]	SETTABLE 	2 -2 1	; "page_max_read_sec" -
	16	[743]	GETUPVAL 	2 2	; self
	17	[743]	SELF     	2 2 -3	; "saveSettings"
	18	[743]	CALL     	2 2 1
	19	[744]	GETUPVAL 	2 3	; UIManager
	20	[744]	SELF     	2 2 -4	; "close"
	21	[744]	GETUPVAL 	4 4	; durations_widget
	22	[744]	CALL     	2 3 1
	23	[745]	GETUPVAL 	2 5	; touchmenu_instance
	24	[745]	SELF     	2 2 -5	; "updateItems"
	25	[745]	CALL     	2 2 1
	26	[746]	RETURN   	0 1

function <./plugins/statistics.koplugin/main.lua:754,757> (13 instructions, 52 bytes at 0x7fcdebc0f700)
0 params, 5 slots, 5 upvalues, 0 locals, 2 constants, 0 functions
	1	[755]	GETUPVAL 	0 0	; T
	2	[755]	GETUPVAL 	1 1	; _
	3	[755]	LOADK    	2 -1	; "Calendar weeks start on %1"
	4	[755]	CALL     	1 2 2
	5	[756]	GETUPVAL 	2 2	; longDayOfWeekTranslation
	6	[756]	GETUPVAL 	3 3	; weekDays
	7	[756]	GETUPVAL 	4 4	; self
	8	[756]	GETTABLE 	4 4 -2	; "calendar_start_day_of_week"
	9	[756]	GETTABLE 	3 3 4
	10	[756]	GETTABLE 	2 2 3
	11	[755]	TAILCALL 	0 3 0
	12	[756]	RETURN   	0 0
	13	[757]	RETURN   	0 1

function <./plugins/statistics.koplugin/main.lua:761,761> (8 instructions, 32 bytes at 0x7fcdebc102a0)
0 params, 2 slots, 1 upvalue, 0 locals, 2 constants, 0 functions
	1	[761]	GETUPVAL 	0 0	; self
	2	[761]	GETTABLE 	0 0 -1	; "calendar_start_day_of_week"
	3	[761]	EQ       	1 0 -2	; - 6
	4	[761]	JMP      	1	; to 6
	5	[761]	LOADBOOL 	0 0 1
	6	[761]	LOADBOOL 	0 1 0
	7	[761]	RETURN   	0 2
	8	[761]	RETURN   	0 1

function <./plugins/statistics.koplugin/main.lua:762,762> (3 instructions, 12 bytes at 0x7fcdebc10070)
0 params, 2 slots, 1 upvalue, 0 locals, 2 constants, 0 functions
	1	[762]	GETUPVAL 	0 0	; self
	2	[762]	SETTABLE 	0 -1 -2	; "calendar_start_day_of_week" 6
	3	[762]	RETURN   	0 1

function <./plugins/statistics.koplugin/main.lua:766,766> (8 instructions, 32 bytes at 0x7fcdebc11870)
0 params, 2 slots, 1 upvalue, 0 locals, 2 constants, 0 functions
	1	[766]	GETUPVAL 	0 0	; self
	2	[766]	GETTABLE 	0 0 -1	; "calendar_start_day_of_week"
	3	[766]	EQ       	1 0 -2	; - 7
	4	[766]	JMP      	1	; to 6
	5	[766]	LOADBOOL 	0 0 1
	6	[766]	LOADBOOL 	0 1 0
	7	[766]	RETURN   	0 2
	8	[766]	RETURN   	0 1

function <./plugins/statistics.koplugin/main.lua:767,767> (3 instructions, 12 bytes at 0x7fcdebc118f0)
0 params, 2 slots, 1 upvalue, 0 locals, 2 constants, 0 functions
	1	[767]	GETUPVAL 	0 0	; self
	2	[767]	SETTABLE 	0 -1 -2	; "calendar_start_day_of_week" 7
	3	[767]	RETURN   	0 1

function <./plugins/statistics.koplugin/main.lua:771,771> (8 instructions, 32 bytes at 0x7fcdebc116d0)
0 params, 2 slots, 1 upvalue, 0 locals, 2 constants, 0 functions
	1	[771]	GETUPVAL 	0 0	; self
	2	[771]	GETTABLE 	0 0 -1	; "calendar_start_day_of_week"
	3	[771]	EQ       	1 0 -2	; - 1
	4	[771]	JMP      	1	; to 6
	5	[771]	LOADBOOL 	0 0 1
	6	[771]	LOADBOOL 	0 1 0
	7	[771]	RETURN   	0 2
	8	[771]	RETURN   	0 1

function <./plugins/statistics.koplugin/main.lua:772,772> (3 instructions, 12 bytes at 0x7fcdebc112f0)
0 params, 2 slots, 1 upvalue, 0 locals, 2 constants, 0 functions
	1	[772]	GETUPVAL 	0 0	; self
	2	[772]	SETTABLE 	0 -1 -2	; "calendar_start_day_of_week" 1
	3	[772]	RETURN   	0 1

function <./plugins/statistics.koplugin/main.lua:776,776> (8 instructions, 32 bytes at 0x7fcdebc11370)
0 params, 2 slots, 1 upvalue, 0 locals, 2 constants, 0 functions
	1	[776]	GETUPVAL 	0 0	; self
	2	[776]	GETTABLE 	0 0 -1	; "calendar_start_day_of_week"
	3	[776]	EQ       	1 0 -2	; - 2
	4	[776]	JMP      	1	; to 6
	5	[776]	LOADBOOL 	0 0 1
	6	[776]	LOADBOOL 	0 1 0
	7	[776]	RETURN   	0 2
	8	[776]	RETURN   	0 1

function <./plugins/statistics.koplugin/main.lua:777,777> (3 instructions, 12 bytes at 0x7fcdebc12240)
0 params, 2 slots, 1 upvalue, 0 locals, 2 constants, 0 functions
	1	[777]	GETUPVAL 	0 0	; self
	2	[777]	SETTABLE 	0 -1 -2	; "calendar_start_day_of_week" 2
	3	[777]	RETURN   	0 1

function <./plugins/statistics.koplugin/main.lua:782,784> (9 instructions, 36 bytes at 0x7fcdebc125e0)
0 params, 3 slots, 3 upvalues, 0 locals, 2 constants, 0 functions
	1	[783]	GETUPVAL 	0 0	; T
	2	[783]	GETUPVAL 	1 1	; _
	3	[783]	LOADK    	2 -1	; "Books per calendar day: %1"
	4	[783]	CALL     	1 2 2
	5	[783]	GETUPVAL 	2 2	; self
	6	[783]	GETTABLE 	2 2 -2	; "calendar_nb_book_spans"
	7	[783]	TAILCALL 	0 3 0
	8	[783]	RETURN   	0 0
	9	[784]	RETURN   	0 1

function <./plugins/statistics.koplugin/main.lua:785,805> (45 instructions, 180 bytes at 0x7fcdebc12900)
1 param, 9 slots, 5 upvalues, 2 locals, 23 constants, 2 functions
	1	[786]	GETGLOBAL	1 -1	; require
	2	[786]	LOADK    	2 -2	; "ui/widget/spinwidget"
	3	[786]	CALL     	1 2 2
	4	[787]	GETUPVAL 	2 0	; UIManager
	5	[787]	SELF     	2 2 -3	; "show"
	6	[787]	SELF     	4 1 -4	; "new"
	7	[787]	NEWTABLE 	6 0 10
	8	[788]	GETUPVAL 	7 1	; Screen
	9	[788]	SELF     	7 7 -6	; "getWidth"
	10	[788]	CALL     	7 2 2
	11	[788]	MUL      	7 7 -7	; - 0.6
	12	[788]	SETTABLE 	6 -5 7	; "width" -
	13	[789]	GETUPVAL 	7 2	; self
	14	[789]	GETTABLE 	7 7 -9	; "calendar_nb_book_spans"
	15	[789]	SETTABLE 	6 -8 7	; "value" -
	16	[790]	SETTABLE 	6 -10 -11	; "value_min" 1
	17	[791]	SETTABLE 	6 -12 -13	; "value_max" 5
	18	[792]	GETUPVAL 	7 3	; _
	19	[792]	LOADK    	8 -15	; "Set"
	20	[792]	CALL     	7 2 2
	21	[792]	SETTABLE 	6 -14 7	; "ok_text" -
	22	[793]	GETUPVAL 	7 3	; _
	23	[793]	LOADK    	8 -17	; "Books per calendar day"
	24	[793]	CALL     	7 2 2
	25	[793]	SETTABLE 	6 -16 7	; "title_text" -
	26	[794]	GETUPVAL 	7 3	; _
	27	[794]	LOADK    	8 -19	; "Set the max number of book spans to show for a day"
	28	[794]	CALL     	7 2 2
	29	[794]	SETTABLE 	6 -18 7	; "info_text" -
	30	[798]	CLOSURE  	7 0	; 0x7fcdebc12b30
	31	[798]	GETUPVAL 	0 2	; self
	32	[798]	MOVE     	0 0
	33	[798]	SETTABLE 	6 -20 7	; "callback" -
	34	[799]	GETUPVAL 	7 3	; _
	35	[799]	LOADK    	8 -22	; "Use default"
	36	[799]	CALL     	7 2 2
	37	[799]	SETTABLE 	6 -21 7	; "extra_text" -
	38	[803]	CLOSURE  	7 1	; 0x7fcdebc12cc0
	39	[803]	GETUPVAL 	0 2	; self
	40	[803]	GETUPVAL 	0 4	; DEFAULT_CALENDAR_NB_BOOK_SPANS
	41	[803]	MOVE     	0 0
	42	[803]	SETTABLE 	6 -23 7	; "extra_callback" -
	43	[787]	CALL     	4 3 0
	44	[787]	CALL     	2 0 1
	45	[805]	RETURN   	0 1

function <./plugins/statistics.koplugin/main.lua:795,798> (7 instructions, 28 bytes at 0x7fcdebc12b30)
1 param, 3 slots, 2 upvalues, 1 local, 3 constants, 0 functions
	1	[796]	GETUPVAL 	1 0	; self
	2	[796]	GETTABLE 	2 0 -2	; "value"
	3	[796]	SETTABLE 	1 -1 2	; "calendar_nb_book_spans" -
	4	[797]	GETUPVAL 	1 1	; touchmenu_instance
	5	[797]	SELF     	1 1 -3	; "updateItems"
	6	[797]	CALL     	1 2 1
	7	[798]	RETURN   	0 1

function <./plugins/statistics.koplugin/main.lua:800,803> (7 instructions, 28 bytes at 0x7fcdebc12cc0)
0 params, 2 slots, 3 upvalues, 0 locals, 2 constants, 0 functions
	1	[801]	GETUPVAL 	0 0	; self
	2	[801]	GETUPVAL 	1 1	; DEFAULT_CALENDAR_NB_BOOK_SPANS
	3	[801]	SETTABLE 	0 -1 1	; "calendar_nb_book_spans" -
	4	[802]	GETUPVAL 	0 2	; touchmenu_instance
	5	[802]	SELF     	0 0 -2	; "updateItems"
	6	[802]	CALL     	0 2 1
	7	[803]	RETURN   	0 1

function <./plugins/statistics.koplugin/main.lua:810,810> (4 instructions, 16 bytes at 0x7fcdebc134a0)
0 params, 2 slots, 1 upvalue, 0 locals, 1 constant, 0 functions
	1	[810]	GETUPVAL 	0 0	; self
	2	[810]	GETTABLE 	0 0 -1	; "calendar_show_histogram"
	3	[810]	RETURN   	0 2
	4	[810]	RETURN   	0 1

function <./plugins/statistics.koplugin/main.lua:811,813> (6 instructions, 24 bytes at 0x7fcdebc139a0)
0 params, 2 slots, 1 upvalue, 0 locals, 1 constant, 0 functions
	1	[812]	GETUPVAL 	0 0	; self
	2	[812]	GETUPVAL 	1 0	; self
	3	[812]	GETTABLE 	1 1 -1	; "calendar_show_histogram"
	4	[812]	NOT      	1 1
	5	[812]	SETTABLE 	0 -1 1	; "calendar_show_histogram" -
	6	[813]	RETURN   	0 1

function <./plugins/statistics.koplugin/main.lua:817,817> (4 instructions, 16 bytes at 0x7fcdebc13b40)
0 params, 2 slots, 1 upvalue, 0 locals, 1 constant, 0 functions
	1	[817]	GETUPVAL 	0 0	; self
	2	[817]	GETTABLE 	0 0 -1	; "calendar_browse_future_months"
	3	[817]	RETURN   	0 2
	4	[817]	RETURN   	0 1

function <./plugins/statistics.koplugin/main.lua:818,820> (6 instructions, 24 bytes at 0x7fcdebc13cf0)
0 params, 2 slots, 1 upvalue, 0 locals, 1 constant, 0 functions
	1	[819]	GETUPVAL 	0 0	; self
	2	[819]	GETUPVAL 	1 0	; self
	3	[819]	GETTABLE 	1 1 -1	; "calendar_browse_future_months"
	4	[819]	NOT      	1 1
	5	[819]	SETTABLE 	0 -1 1	; "calendar_browse_future_months" -
	6	[820]	RETURN   	0 1

function <./plugins/statistics.koplugin/main.lua:832,837> (18 instructions, 72 bytes at 0x7fcdebc121c0)
0 params, 8 slots, 4 upvalues, 0 locals, 7 constants, 0 functions
	1	[833]	GETUPVAL 	0 0	; UIManager
	2	[833]	SELF     	0 0 -1	; "show"
	3	[833]	GETUPVAL 	2 1	; KeyValuePage
	4	[833]	SELF     	2 2 -2	; "new"
	5	[833]	NEWTABLE 	4 0 2
	6	[834]	GETUPVAL 	5 2	; _
	7	[834]	LOADK    	6 -4	; "Statistics"
	8	[834]	CALL     	5 2 2
	9	[834]	SETTABLE 	4 -3 5	; "title" -
	10	[835]	GETUPVAL 	5 3	; self
	11	[835]	SELF     	5 5 -6	; "getCurrentStat"
	12	[835]	GETUPVAL 	7 3	; self
	13	[835]	GETTABLE 	7 7 -7	; "id_curr_book"
	14	[835]	CALL     	5 3 2
	15	[835]	SETTABLE 	4 -5 5	; "kv_pairs" -
	16	[833]	CALL     	2 3 0
	17	[833]	CALL     	0 0 1
	18	[837]	RETURN   	0 1

function <./plugins/statistics.koplugin/main.lua:838,838> (12 instructions, 48 bytes at 0x7fcdebc11df0)
0 params, 2 slots, 1 upvalue, 0 locals, 2 constants, 0 functions
	1	[838]	GETUPVAL 	0 0	; self
	2	[838]	SELF     	0 0 -1	; "isDocless"
	3	[838]	CALL     	0 2 2
	4	[838]	TEST     	0 0 1
	5	[838]	JMP      	3	; to 9
	6	[838]	GETUPVAL 	0 0	; self
	7	[838]	GETTABLE 	0 0 -2	; "is_enabled"
	8	[838]	JMP      	2	; to 11
	9	[838]	LOADBOOL 	0 0 1
	10	[838]	LOADBOOL 	0 1 0
	11	[838]	RETURN   	0 2
	12	[838]	RETURN   	0 1

function <./plugins/statistics.koplugin/main.lua:843,860> (45 instructions, 180 bytes at 0x7fcdebc143f0)
0 params, 13 slots, 6 upvalues, 5 locals, 15 constants, 0 functions
	1	[844]	GETUPVAL 	0 0	; self
	2	[844]	SELF     	0 0 -1	; "insertDB"
	3	[844]	GETUPVAL 	2 0	; self
	4	[844]	GETTABLE 	2 2 -2	; "id_curr_book"
	5	[844]	CALL     	0 3 1
	6	[845]	GETUPVAL 	0 0	; self
	7	[845]	SELF     	0 0 -3	; "getCurrentBookStats"
	8	[845]	CALL     	0 2 3
	9	[846]	GETUPVAL 	2 0	; self
	10	[846]	SELF     	2 2 -4	; "getTodayBookStats"
	11	[846]	CALL     	2 2 3
	12	[847]	GETUPVAL 	4 0	; self
	13	[847]	SELF     	4 4 -5	; "getReadingProgressStats"
	14	[847]	LOADK    	6 -6	; 7
	15	[847]	CALL     	4 3 2
	16	[848]	TEST     	4 0 0
	17	[848]	JMP      	13	; to 31
	18	[849]	GETUPVAL 	5 1	; UIManager
	19	[849]	SELF     	5 5 -7	; "show"
	20	[849]	GETUPVAL 	7 2	; ReaderProgress
	21	[849]	SELF     	7 7 -8	; "new"
	22	[849]	NEWTABLE 	9 0 5
	23	[850]	SETTABLE 	9 -9 4	; "dates" -
	24	[851]	SETTABLE 	9 -10 0	; "current_period" -
	25	[852]	SETTABLE 	9 -11 1	; "current_pages" -
	26	[853]	SETTABLE 	9 -12 2	; "today_period" -
	27	[854]	SETTABLE 	9 -13 3	; "today_pages" -
	28	[849]	CALL     	7 3 0
	29	[849]	CALL     	5 0 1
	30	[855]	JMP      	14	; to 45
	31	[857]	GETUPVAL 	5 1	; UIManager
	32	[857]	SELF     	5 5 -7	; "show"
	33	[857]	GETUPVAL 	7 3	; InfoMessage
	34	[857]	SELF     	7 7 -8	; "new"
	35	[857]	NEWTABLE 	9 0 1
	36	[858]	GETUPVAL 	10 4	; T
	37	[858]	GETUPVAL 	11 5	; _
	38	[858]	LOADK    	12 -15	; "Reading progress unavailable.\nNo data from last %1 days."
	39	[858]	CALL     	11 2 2
	40	[858]	LOADK    	12 -6	; 7
	41	[858]	CALL     	10 3 2
	42	[858]	SETTABLE 	9 -14 10	; "text" -
	43	[857]	CALL     	7 3 0
	44	[857]	CALL     	5 0 1
	45	[860]	RETURN   	0 1

function <./plugins/statistics.koplugin/main.lua:865,867> (4 instructions, 16 bytes at 0x7fcdebc14900)
0 params, 2 slots, 1 upvalue, 0 locals, 1 constant, 0 functions
	1	[866]	GETUPVAL 	0 0	; self
	2	[866]	SELF     	0 0 -1	; "statMenu"
	3	[866]	CALL     	0 2 1
	4	[867]	RETURN   	0 1

function <./plugins/statistics.koplugin/main.lua:872,874> (7 instructions, 28 bytes at 0x7fcdebc14b80)
0 params, 4 slots, 2 upvalues, 0 locals, 2 constants, 0 functions
	1	[873]	GETUPVAL 	0 0	; UIManager
	2	[873]	SELF     	0 0 -1	; "show"
	3	[873]	GETUPVAL 	2 1	; self
	4	[873]	SELF     	2 2 -2	; "getCalendarView"
	5	[873]	CALL     	2 2 0
	6	[873]	CALL     	0 0 1
	7	[874]	RETURN   	0 1

function <./plugins/statistics.koplugin/main.lua:880,1019> (115 instructions, 460 bytes at 0x7fcdebc14e60)
1 param, 18 slots, 3 upvalues, 1 local, 19 constants, 8 functions
	1	[881]	GETUPVAL 	1 0	; KeyValuePage
	2	[881]	SELF     	1 1 -2	; "new"
	3	[881]	NEWTABLE 	3 0 3
	4	[882]	GETUPVAL 	4 1	; _
	5	[882]	LOADK    	5 -4	; "Time range statistics"
	6	[882]	CALL     	4 2 2
	7	[882]	SETTABLE 	3 -3 4	; "title" -
	8	[883]	SETTABLE 	3 -5 -6	; "return_button" true
	9	[884]	NEWTABLE 	4 10 0
	10	[884]	NEWTABLE 	5 2 1
	11	[885]	GETUPVAL 	6 1	; _
	12	[885]	LOADK    	7 -8	; "All books"
	13	[885]	CALL     	6 2 2
	14	[885]	LOADK    	7 -9	; ""
	15	[900]	CLOSURE  	8 0	; 0x7fcdebc14f20
	16	[900]	MOVE     	0 0
	17	[900]	GETUPVAL 	0 2	; UIManager
	18	[900]	GETUPVAL 	0 0	; KeyValuePage
	19	[900]	SETTABLE 	5 -10 8	; "callback" -
	20	[901]	SETLIST  	5 2 1	; 1
	21	[902]	LOADK    	6 -11	; "----"
	22	[902]	NEWTABLE 	7 2 1
	23	[903]	GETUPVAL 	8 1	; _
	24	[903]	LOADK    	9 -12	; "Last week"
	25	[903]	CALL     	8 2 2
	26	[903]	LOADK    	9 -9	; ""
	27	[917]	CLOSURE  	10 1	; 0x7fcdebc156f0
	28	[917]	MOVE     	0 0
	29	[917]	GETUPVAL 	0 2	; UIManager
	30	[917]	GETUPVAL 	0 0	; KeyValuePage
	31	[917]	GETUPVAL 	0 1	; _
	32	[917]	SETTABLE 	7 -10 10	; "callback" -
	33	[918]	SETLIST  	7 2 1	; 1
	34	[918]	NEWTABLE 	8 2 1
	35	[919]	GETUPVAL 	9 1	; _
	36	[919]	LOADK    	10 -13	; "Last month by day"
	37	[919]	CALL     	9 2 2
	38	[919]	LOADK    	10 -9	; ""
	39	[933]	CLOSURE  	11 2	; 0x7fcdebc15aa0
	40	[933]	MOVE     	0 0
	41	[933]	GETUPVAL 	0 2	; UIManager
	42	[933]	GETUPVAL 	0 0	; KeyValuePage
	43	[933]	GETUPVAL 	0 1	; _
	44	[933]	SETTABLE 	8 -10 11	; "callback" -
	45	[934]	SETLIST  	8 2 1	; 1
	46	[934]	NEWTABLE 	9 2 1
	47	[935]	GETUPVAL 	10 1	; _
	48	[935]	LOADK    	11 -14	; "Last year by day"
	49	[935]	CALL     	10 2 2
	50	[935]	LOADK    	11 -9	; ""
	51	[949]	CLOSURE  	12 3	; 0x7fcdebc16690
	52	[949]	MOVE     	0 0
	53	[949]	GETUPVAL 	0 2	; UIManager
	54	[949]	GETUPVAL 	0 0	; KeyValuePage
	55	[949]	GETUPVAL 	0 1	; _
	56	[949]	SETTABLE 	9 -10 12	; "callback" -
	57	[950]	SETLIST  	9 2 1	; 1
	58	[950]	NEWTABLE 	10 2 1
	59	[951]	GETUPVAL 	11 1	; _
	60	[951]	LOADK    	12 -15	; "Last year by week"
	61	[951]	CALL     	11 2 2
	62	[951]	LOADK    	12 -9	; ""
	63	[965]	CLOSURE  	13 4	; 0x7fcdebc16d70
	64	[965]	MOVE     	0 0
	65	[965]	GETUPVAL 	0 2	; UIManager
	66	[965]	GETUPVAL 	0 0	; KeyValuePage
	67	[965]	GETUPVAL 	0 1	; _
	68	[965]	SETTABLE 	10 -10 13	; "callback" -
	69	[966]	SETLIST  	10 2 1	; 1
	70	[966]	NEWTABLE 	11 2 1
	71	[967]	GETUPVAL 	12 1	; _
	72	[967]	LOADK    	13 -16	; "All stats by month"
	73	[967]	CALL     	12 2 2
	74	[967]	LOADK    	13 -9	; ""
	75	[981]	CLOSURE  	14 5	; 0x7fcdebc16a50
	76	[981]	MOVE     	0 0
	77	[981]	GETUPVAL 	0 2	; UIManager
	78	[981]	GETUPVAL 	0 0	; KeyValuePage
	79	[981]	GETUPVAL 	0 1	; _
	80	[981]	SETTABLE 	11 -10 14	; "callback" -
	81	[982]	SETLIST  	11 2 1	; 1
	82	[983]	LOADK    	12 -11	; "----"
	83	[983]	NEWTABLE 	13 2 1
	84	[984]	GETUPVAL 	14 1	; _
	85	[984]	LOADK    	15 -17	; "Books by week"
	86	[984]	CALL     	14 2 2
	87	[984]	LOADK    	15 -9	; ""
	88	[998]	CLOSURE  	16 6	; 0x7fcdebc15250
	89	[998]	MOVE     	0 0
	90	[998]	GETUPVAL 	0 2	; UIManager
	91	[998]	GETUPVAL 	0 0	; KeyValuePage
	92	[998]	GETUPVAL 	0 1	; _
	93	[998]	SETTABLE 	13 -10 16	; "callback" -
	94	[999]	SETLIST  	13 2 1	; 1
	95	[999]	NEWTABLE 	14 2 1
	96	[1000]	GETUPVAL 	15 1	; _
	97	[1000]	LOADK    	16 -18	; "Books by month"
	98	[1000]	CALL     	15 2 2
	99	[1000]	LOADK    	16 -9	; ""
	100	[1014]	CLOSURE  	17 7	; 0x7fcdebc17dc0
	101	[1014]	MOVE     	0 0
	102	[1014]	GETUPVAL 	0 2	; UIManager
	103	[1014]	GETUPVAL 	0 0	; KeyValuePage
	104	[1014]	GETUPVAL 	0 1	; _
	105	[1014]	SETTABLE 	14 -10 17	; "callback" -
	106	[1015]	SETLIST  	14 2 1	; 1
	107	[1016]	SETLIST  	4 10 1	; 1
	108	[1016]	SETTABLE 	3 -7 4	; "kv_pairs" -
	109	[881]	CALL     	1 3 2
	110	[1017]	SETTABLE 	0 -1 1	; "kv" -
	111	[1018]	GETUPVAL 	1 2	; UIManager
	112	[1018]	SELF     	1 1 -19	; "show"
	113	[1018]	GETTABLE 	3 0 -1	; "kv"
	114	[1018]	CALL     	1 3 1
	115	[1019]	RETURN   	0 1

function <./plugins/statistics.koplugin/main.lua:886,900> (30 instructions, 120 bytes at 0x7fcdebc14f20)
0 params, 8 slots, 3 upvalues, 3 locals, 10 constants, 1 function
	1	[887]	GETUPVAL 	0 0	; self
	2	[887]	GETTABLE 	0 0 -1	; "kv"
	3	[888]	GETUPVAL 	1 1	; UIManager
	4	[888]	SELF     	1 1 -2	; "close"
	5	[888]	GETUPVAL 	3 0	; self
	6	[888]	GETTABLE 	3 3 -1	; "kv"
	7	[888]	CALL     	1 3 1
	8	[889]	GETUPVAL 	1 0	; self
	9	[889]	SELF     	1 1 -3	; "getTotalStats"
	10	[889]	CALL     	1 2 3
	11	[890]	GETUPVAL 	3 0	; self
	12	[890]	GETUPVAL 	4 2	; KeyValuePage
	13	[890]	SELF     	4 4 -4	; "new"
	14	[890]	NEWTABLE 	6 0 4
	15	[891]	SETTABLE 	6 -5 1	; "title" -
	16	[892]	SETTABLE 	6 -6 -7	; "value_align" "right"
	17	[893]	SETTABLE 	6 -8 2	; "kv_pairs" -
	18	[897]	CLOSURE  	7 0	; 0x7fcdebc15500
	19	[897]	GETUPVAL 	0 1	; UIManager
	20	[897]	MOVE     	0 0
	21	[897]	GETUPVAL 	0 0	; self
	22	[897]	SETTABLE 	6 -9 7	; "callback_return" -
	23	[890]	CALL     	4 3 2
	24	[898]	SETTABLE 	3 -1 4	; "kv" -
	25	[899]	GETUPVAL 	3 1	; UIManager
	26	[899]	SELF     	3 3 -10	; "show"
	27	[899]	GETUPVAL 	5 0	; self
	28	[899]	GETTABLE 	5 5 -1	; "kv"
	29	[899]	CALL     	3 3 1
	30	[900]	RETURN   	0 1

function <./plugins/statistics.koplugin/main.lua:894,897> (8 instructions, 32 bytes at 0x7fcdebc15500)
0 params, 3 slots, 3 upvalues, 0 locals, 2 constants, 0 functions
	1	[895]	GETUPVAL 	0 0	; UIManager
	2	[895]	SELF     	0 0 -1	; "show"
	3	[895]	GETUPVAL 	2 1	; kv
	4	[895]	CALL     	0 3 1
	5	[896]	GETUPVAL 	0 2	; self
	6	[896]	GETUPVAL 	1 1	; kv
	7	[896]	SETTABLE 	0 -2 1	; "kv" -
	8	[897]	RETURN   	0 1

function <./plugins/statistics.koplugin/main.lua:904,917> (35 instructions, 140 bytes at 0x7fcdebc156f0)
0 params, 9 slots, 4 upvalues, 1 local, 13 constants, 1 function
	1	[905]	GETUPVAL 	0 0	; self
	2	[905]	GETTABLE 	0 0 -1	; "kv"
	3	[906]	GETUPVAL 	1 1	; UIManager
	4	[906]	SELF     	1 1 -2	; "close"
	5	[906]	GETUPVAL 	3 0	; self
	6	[906]	GETTABLE 	3 3 -1	; "kv"
	7	[906]	CALL     	1 3 1
	8	[907]	GETUPVAL 	1 0	; self
	9	[907]	GETUPVAL 	2 2	; KeyValuePage
	10	[907]	SELF     	2 2 -3	; "new"
	11	[907]	NEWTABLE 	4 0 4
	12	[908]	GETUPVAL 	5 3	; _
	13	[908]	LOADK    	6 -5	; "Last week"
	14	[908]	CALL     	5 2 2
	15	[908]	SETTABLE 	4 -4 5	; "title" -
	16	[909]	SETTABLE 	4 -6 -7	; "value_overflow_align" "right"
	17	[910]	GETUPVAL 	5 0	; self
	18	[910]	SELF     	5 5 -9	; "getDatesFromAll"
	19	[910]	LOADK    	7 -10	; 7
	20	[910]	LOADK    	8 -11	; "daily_weekday"
	21	[910]	CALL     	5 4 2
	22	[910]	SETTABLE 	4 -8 5	; "kv_pairs" -
	23	[914]	CLOSURE  	5 0	; 0x7fcdebc15770
	24	[914]	GETUPVAL 	0 1	; UIManager
	25	[914]	MOVE     	0 0
	26	[914]	GETUPVAL 	0 0	; self
	27	[914]	SETTABLE 	4 -12 5	; "callback_return" -
	28	[907]	CALL     	2 3 2
	29	[915]	SETTABLE 	1 -1 2	; "kv" -
	30	[916]	GETUPVAL 	1 1	; UIManager
	31	[916]	SELF     	1 1 -13	; "show"
	32	[916]	GETUPVAL 	3 0	; self
	33	[916]	GETTABLE 	3 3 -1	; "kv"
	34	[916]	CALL     	1 3 1
	35	[917]	RETURN   	0 1

function <./plugins/statistics.koplugin/main.lua:911,914> (8 instructions, 32 bytes at 0x7fcdebc15770)
0 params, 3 slots, 3 upvalues, 0 locals, 2 constants, 0 functions
	1	[912]	GETUPVAL 	0 0	; UIManager
	2	[912]	SELF     	0 0 -1	; "show"
	3	[912]	GETUPVAL 	2 1	; kv
	4	[912]	CALL     	0 3 1
	5	[913]	GETUPVAL 	0 2	; self
	6	[913]	GETUPVAL 	1 1	; kv
	7	[913]	SETTABLE 	0 -2 1	; "kv" -
	8	[914]	RETURN   	0 1

function <./plugins/statistics.koplugin/main.lua:920,933> (35 instructions, 140 bytes at 0x7fcdebc15aa0)
0 params, 9 slots, 4 upvalues, 1 local, 13 constants, 1 function
	1	[921]	GETUPVAL 	0 0	; self
	2	[921]	GETTABLE 	0 0 -1	; "kv"
	3	[922]	GETUPVAL 	1 1	; UIManager
	4	[922]	SELF     	1 1 -2	; "close"
	5	[922]	GETUPVAL 	3 0	; self
	6	[922]	GETTABLE 	3 3 -1	; "kv"
	7	[922]	CALL     	1 3 1
	8	[923]	GETUPVAL 	1 0	; self
	9	[923]	GETUPVAL 	2 2	; KeyValuePage
	10	[923]	SELF     	2 2 -3	; "new"
	11	[923]	NEWTABLE 	4 0 4
	12	[924]	GETUPVAL 	5 3	; _
	13	[924]	LOADK    	6 -5	; "Last month by day"
	14	[924]	CALL     	5 2 2
	15	[924]	SETTABLE 	4 -4 5	; "title" -
	16	[925]	SETTABLE 	4 -6 -7	; "value_overflow_align" "right"
	17	[926]	GETUPVAL 	5 0	; self
	18	[926]	SELF     	5 5 -9	; "getDatesFromAll"
	19	[926]	LOADK    	7 -10	; 30
	20	[926]	LOADK    	8 -11	; "daily_weekday"
	21	[926]	CALL     	5 4 2
	22	[926]	SETTABLE 	4 -8 5	; "kv_pairs" -
	23	[930]	CLOSURE  	5 0	; 0x7fcdebc163b0
	24	[930]	GETUPVAL 	0 1	; UIManager
	25	[930]	MOVE     	0 0
	26	[930]	GETUPVAL 	0 0	; self
	27	[930]	SETTABLE 	4 -12 5	; "callback_return" -
	28	[923]	CALL     	2 3 2
	29	[931]	SETTABLE 	1 -1 2	; "kv" -
	30	[932]	GETUPVAL 	1 1	; UIManager
	31	[932]	SELF     	1 1 -13	; "show"
	32	[932]	GETUPVAL 	3 0	; self
	33	[932]	GETTABLE 	3 3 -1	; "kv"
	34	[932]	CALL     	1 3 1
	35	[933]	RETURN   	0 1

function <./plugins/statistics.koplugin/main.lua:927,930> (8 instructions, 32 bytes at 0x7fcdebc163b0)
0 params, 3 slots, 3 upvalues, 0 locals, 2 constants, 0 functions
	1	[928]	GETUPVAL 	0 0	; UIManager
	2	[928]	SELF     	0 0 -1	; "show"
	3	[928]	GETUPVAL 	2 1	; kv
	4	[928]	CALL     	0 3 1
	5	[929]	GETUPVAL 	0 2	; self
	6	[929]	GETUPVAL 	1 1	; kv
	7	[929]	SETTABLE 	0 -2 1	; "kv" -
	8	[930]	RETURN   	0 1

function <./plugins/statistics.koplugin/main.lua:936,949> (35 instructions, 140 bytes at 0x7fcdebc16690)
0 params, 9 slots, 4 upvalues, 1 local, 13 constants, 1 function
	1	[937]	GETUPVAL 	0 0	; self
	2	[937]	GETTABLE 	0 0 -1	; "kv"
	3	[938]	GETUPVAL 	1 1	; UIManager
	4	[938]	SELF     	1 1 -2	; "close"
	5	[938]	GETUPVAL 	3 0	; self
	6	[938]	GETTABLE 	3 3 -1	; "kv"
	7	[938]	CALL     	1 3 1
	8	[939]	GETUPVAL 	1 0	; self
	9	[939]	GETUPVAL 	2 2	; KeyValuePage
	10	[939]	SELF     	2 2 -3	; "new"
	11	[939]	NEWTABLE 	4 0 4
	12	[940]	GETUPVAL 	5 3	; _
	13	[940]	LOADK    	6 -5	; "Last year by day"
	14	[940]	CALL     	5 2 2
	15	[940]	SETTABLE 	4 -4 5	; "title" -
	16	[941]	SETTABLE 	4 -6 -7	; "value_overflow_align" "right"
	17	[942]	GETUPVAL 	5 0	; self
	18	[942]	SELF     	5 5 -9	; "getDatesFromAll"
	19	[942]	LOADK    	7 -10	; 365
	20	[942]	LOADK    	8 -11	; "daily"
	21	[942]	CALL     	5 4 2
	22	[942]	SETTABLE 	4 -8 5	; "kv_pairs" -
	23	[946]	CLOSURE  	5 0	; 0x7fcdebc16af0
	24	[946]	GETUPVAL 	0 1	; UIManager
	25	[946]	MOVE     	0 0
	26	[946]	GETUPVAL 	0 0	; self
	27	[946]	SETTABLE 	4 -12 5	; "callback_return" -
	28	[939]	CALL     	2 3 2
	29	[947]	SETTABLE 	1 -1 2	; "kv" -
	30	[948]	GETUPVAL 	1 1	; UIManager
	31	[948]	SELF     	1 1 -13	; "show"
	32	[948]	GETUPVAL 	3 0	; self
	33	[948]	GETTABLE 	3 3 -1	; "kv"
	34	[948]	CALL     	1 3 1
	35	[949]	RETURN   	0 1

function <./plugins/statistics.koplugin/main.lua:943,946> (8 instructions, 32 bytes at 0x7fcdebc16af0)
0 params, 3 slots, 3 upvalues, 0 locals, 2 constants, 0 functions
	1	[944]	GETUPVAL 	0 0	; UIManager
	2	[944]	SELF     	0 0 -1	; "show"
	3	[944]	GETUPVAL 	2 1	; kv
	4	[944]	CALL     	0 3 1
	5	[945]	GETUPVAL 	0 2	; self
	6	[945]	GETUPVAL 	1 1	; kv
	7	[945]	SETTABLE 	0 -2 1	; "kv" -
	8	[946]	RETURN   	0 1

function <./plugins/statistics.koplugin/main.lua:952,965> (35 instructions, 140 bytes at 0x7fcdebc16d70)
0 params, 9 slots, 4 upvalues, 1 local, 13 constants, 1 function
	1	[953]	GETUPVAL 	0 0	; self
	2	[953]	GETTABLE 	0 0 -1	; "kv"
	3	[954]	GETUPVAL 	1 1	; UIManager
	4	[954]	SELF     	1 1 -2	; "close"
	5	[954]	GETUPVAL 	3 0	; self
	6	[954]	GETTABLE 	3 3 -1	; "kv"
	7	[954]	CALL     	1 3 1
	8	[955]	GETUPVAL 	1 0	; self
	9	[955]	GETUPVAL 	2 2	; KeyValuePage
	10	[955]	SELF     	2 2 -3	; "new"
	11	[955]	NEWTABLE 	4 0 4
	12	[956]	GETUPVAL 	5 3	; _
	13	[956]	LOADK    	6 -5	; "Last year by week"
	14	[956]	CALL     	5 2 2
	15	[956]	SETTABLE 	4 -4 5	; "title" -
	16	[957]	SETTABLE 	4 -6 -7	; "value_overflow_align" "right"
	17	[958]	GETUPVAL 	5 0	; self
	18	[958]	SELF     	5 5 -9	; "getDatesFromAll"
	19	[958]	LOADK    	7 -10	; 365
	20	[958]	LOADK    	8 -11	; "weekly"
	21	[958]	CALL     	5 4 2
	22	[958]	SETTABLE 	4 -8 5	; "kv_pairs" -
	23	[962]	CLOSURE  	5 0	; 0x7fcdebc171b0
	24	[962]	GETUPVAL 	0 1	; UIManager
	25	[962]	MOVE     	0 0
	26	[962]	GETUPVAL 	0 0	; self
	27	[962]	SETTABLE 	4 -12 5	; "callback_return" -
	28	[955]	CALL     	2 3 2
	29	[963]	SETTABLE 	1 -1 2	; "kv" -
	30	[964]	GETUPVAL 	1 1	; UIManager
	31	[964]	SELF     	1 1 -13	; "show"
	32	[964]	GETUPVAL 	3 0	; self
	33	[964]	GETTABLE 	3 3 -1	; "kv"
	34	[964]	CALL     	1 3 1
	35	[965]	RETURN   	0 1

function <./plugins/statistics.koplugin/main.lua:959,962> (8 instructions, 32 bytes at 0x7fcdebc171b0)
0 params, 3 slots, 3 upvalues, 0 locals, 2 constants, 0 functions
	1	[960]	GETUPVAL 	0 0	; UIManager
	2	[960]	SELF     	0 0 -1	; "show"
	3	[960]	GETUPVAL 	2 1	; kv
	4	[960]	CALL     	0 3 1
	5	[961]	GETUPVAL 	0 2	; self
	6	[961]	GETUPVAL 	1 1	; kv
	7	[961]	SETTABLE 	0 -2 1	; "kv" -
	8	[962]	RETURN   	0 1

function <./plugins/statistics.koplugin/main.lua:968,981> (35 instructions, 140 bytes at 0x7fcdebc16a50)
0 params, 9 slots, 4 upvalues, 1 local, 13 constants, 1 function
	1	[969]	GETUPVAL 	0 0	; self
	2	[969]	GETTABLE 	0 0 -1	; "kv"
	3	[970]	GETUPVAL 	1 1	; UIManager
	4	[970]	SELF     	1 1 -2	; "close"
	5	[970]	GETUPVAL 	3 0	; self
	6	[970]	GETTABLE 	3 3 -1	; "kv"
	7	[970]	CALL     	1 3 1
	8	[971]	GETUPVAL 	1 0	; self
	9	[971]	GETUPVAL 	2 2	; KeyValuePage
	10	[971]	SELF     	2 2 -3	; "new"
	11	[971]	NEWTABLE 	4 0 4
	12	[972]	GETUPVAL 	5 3	; _
	13	[972]	LOADK    	6 -5	; "All stats by month"
	14	[972]	CALL     	5 2 2
	15	[972]	SETTABLE 	4 -4 5	; "title" -
	16	[973]	SETTABLE 	4 -6 -7	; "value_overflow_align" "right"
	17	[974]	GETUPVAL 	5 0	; self
	18	[974]	SELF     	5 5 -9	; "getDatesFromAll"
	19	[974]	LOADK    	7 -10	; 0
	20	[974]	LOADK    	8 -11	; "monthly"
	21	[974]	CALL     	5 4 2
	22	[974]	SETTABLE 	4 -8 5	; "kv_pairs" -
	23	[978]	CLOSURE  	5 0	; 0x7fcdebc152d0
	24	[978]	GETUPVAL 	0 1	; UIManager
	25	[978]	MOVE     	0 0
	26	[978]	GETUPVAL 	0 0	; self
	27	[978]	SETTABLE 	4 -12 5	; "callback_return" -
	28	[971]	CALL     	2 3 2
	29	[979]	SETTABLE 	1 -1 2	; "kv" -
	30	[980]	GETUPVAL 	1 1	; UIManager
	31	[980]	SELF     	1 1 -13	; "show"
	32	[980]	GETUPVAL 	3 0	; self
	33	[980]	GETTABLE 	3 3 -1	; "kv"
	34	[980]	CALL     	1 3 1
	35	[981]	RETURN   	0 1

function <./plugins/statistics.koplugin/main.lua:975,978> (8 instructions, 32 bytes at 0x7fcdebc152d0)
0 params, 3 slots, 3 upvalues, 0 locals, 2 constants, 0 functions
	1	[976]	GETUPVAL 	0 0	; UIManager
	2	[976]	SELF     	0 0 -1	; "show"
	3	[976]	GETUPVAL 	2 1	; kv
	4	[976]	CALL     	0 3 1
	5	[977]	GETUPVAL 	0 2	; self
	6	[977]	GETUPVAL 	1 1	; kv
	7	[977]	SETTABLE 	0 -2 1	; "kv" -
	8	[978]	RETURN   	0 1

function <./plugins/statistics.koplugin/main.lua:985,998> (36 instructions, 144 bytes at 0x7fcdebc15250)
0 params, 10 slots, 4 upvalues, 1 local, 13 constants, 1 function
	1	[986]	GETUPVAL 	0 0	; self
	2	[986]	GETTABLE 	0 0 -1	; "kv"
	3	[987]	GETUPVAL 	1 1	; UIManager
	4	[987]	SELF     	1 1 -2	; "close"
	5	[987]	GETUPVAL 	3 0	; self
	6	[987]	GETTABLE 	3 3 -1	; "kv"
	7	[987]	CALL     	1 3 1
	8	[988]	GETUPVAL 	1 0	; self
	9	[988]	GETUPVAL 	2 2	; KeyValuePage
	10	[988]	SELF     	2 2 -3	; "new"
	11	[988]	NEWTABLE 	4 0 4
	12	[989]	GETUPVAL 	5 3	; _
	13	[989]	LOADK    	6 -5	; "Books by week"
	14	[989]	CALL     	5 2 2
	15	[989]	SETTABLE 	4 -4 5	; "title" -
	16	[990]	SETTABLE 	4 -6 -7	; "value_overflow_align" "right"
	17	[991]	GETUPVAL 	5 0	; self
	18	[991]	SELF     	5 5 -9	; "getDatesFromAll"
	19	[991]	LOADK    	7 -10	; 0
	20	[991]	LOADK    	8 -11	; "weekly"
	21	[991]	LOADBOOL 	9 1 0
	22	[991]	CALL     	5 5 2
	23	[991]	SETTABLE 	4 -8 5	; "kv_pairs" -
	24	[995]	CLOSURE  	5 0	; 0x7fcdebc18290
	25	[995]	GETUPVAL 	0 1	; UIManager
	26	[995]	MOVE     	0 0
	27	[995]	GETUPVAL 	0 0	; self
	28	[995]	SETTABLE 	4 -12 5	; "callback_return" -
	29	[988]	CALL     	2 3 2
	30	[996]	SETTABLE 	1 -1 2	; "kv" -
	31	[997]	GETUPVAL 	1 1	; UIManager
	32	[997]	SELF     	1 1 -13	; "show"
	33	[997]	GETUPVAL 	3 0	; self
	34	[997]	GETTABLE 	3 3 -1	; "kv"
	35	[997]	CALL     	1 3 1
	36	[998]	RETURN   	0 1

function <./plugins/statistics.koplugin/main.lua:992,995> (8 instructions, 32 bytes at 0x7fcdebc18290)
0 params, 3 slots, 3 upvalues, 0 locals, 2 constants, 0 functions
	1	[993]	GETUPVAL 	0 0	; UIManager
	2	[993]	SELF     	0 0 -1	; "show"
	3	[993]	GETUPVAL 	2 1	; kv
	4	[993]	CALL     	0 3 1
	5	[994]	GETUPVAL 	0 2	; self
	6	[994]	GETUPVAL 	1 1	; kv
	7	[994]	SETTABLE 	0 -2 1	; "kv" -
	8	[995]	RETURN   	0 1

function <./plugins/statistics.koplugin/main.lua:1001,1014> (36 instructions, 144 bytes at 0x7fcdebc17dc0)
0 params, 10 slots, 4 upvalues, 1 local, 13 constants, 1 function
	1	[1002]	GETUPVAL 	0 0	; self
	2	[1002]	GETTABLE 	0 0 -1	; "kv"
	3	[1003]	GETUPVAL 	1 1	; UIManager
	4	[1003]	SELF     	1 1 -2	; "close"
	5	[1003]	GETUPVAL 	3 0	; self
	6	[1003]	GETTABLE 	3 3 -1	; "kv"
	7	[1003]	CALL     	1 3 1
	8	[1004]	GETUPVAL 	1 0	; self
	9	[1004]	GETUPVAL 	2 2	; KeyValuePage
	10	[1004]	SELF     	2 2 -3	; "new"
	11	[1004]	NEWTABLE 	4 0 4
	12	[1005]	GETUPVAL 	5 3	; _
	13	[1005]	LOADK    	6 -5	; "Books by month"
	14	[1005]	CALL     	5 2 2
	15	[1005]	SETTABLE 	4 -4 5	; "title" -
	16	[1006]	SETTABLE 	4 -6 -7	; "value_overflow_align" "right"
	17	[1007]	GETUPVAL 	5 0	; self
	18	[1007]	SELF     	5 5 -9	; "getDatesFromAll"
	19	[1007]	LOADK    	7 -10	; 0
	20	[1007]	LOADK    	8 -11	; "monthly"
	21	[1007]	LOADBOOL 	9 1 0
	22	[1007]	CALL     	5 5 2
	23	[1007]	SETTABLE 	4 -8 5	; "kv_pairs" -
	24	[1011]	CLOSURE  	5 0	; 0x7fcdebc18950
	25	[1011]	GETUPVAL 	0 1	; UIManager
	26	[1011]	MOVE     	0 0
	27	[1011]	GETUPVAL 	0 0	; self
	28	[1011]	SETTABLE 	4 -12 5	; "callback_return" -
	29	[1004]	CALL     	2 3 2
	30	[1012]	SETTABLE 	1 -1 2	; "kv" -
	31	[1013]	GETUPVAL 	1 1	; UIManager
	32	[1013]	SELF     	1 1 -13	; "show"
	33	[1013]	GETUPVAL 	3 0	; self
	34	[1013]	GETTABLE 	3 3 -1	; "kv"
	35	[1013]	CALL     	1 3 1
	36	[1014]	RETURN   	0 1

function <./plugins/statistics.koplugin/main.lua:1008,1011> (8 instructions, 32 bytes at 0x7fcdebc18950)
0 params, 3 slots, 3 upvalues, 0 locals, 2 constants, 0 functions
	1	[1009]	GETUPVAL 	0 0	; UIManager
	2	[1009]	SELF     	0 0 -1	; "show"
	3	[1009]	GETUPVAL 	2 1	; kv
	4	[1009]	CALL     	0 3 1
	5	[1010]	GETUPVAL 	0 2	; self
	6	[1010]	GETUPVAL 	1 1	; kv
	7	[1010]	SETTABLE 	0 -2 1	; "kv" -
	8	[1011]	RETURN   	0 1

function <./plugins/statistics.koplugin/main.lua:1021,1048> (47 instructions, 188 bytes at 0x7fcdebc18c10)
1 param, 12 slots, 2 upvalues, 9 locals, 18 constants, 0 functions
	1	[1022]	GETGLOBAL	1 -1	; os
	2	[1022]	GETTABLE 	1 1 -2	; "time"
	3	[1022]	CALL     	1 1 2
	4	[1023]	GETGLOBAL	2 -1	; os
	5	[1023]	GETTABLE 	2 2 -3	; "date"
	6	[1023]	LOADK    	3 -4	; "*t"
	7	[1023]	CALL     	2 2 2
	8	[1024]	GETTABLE 	3 2 -5	; "hour"
	9	[1024]	MUL      	3 3 -6	; - 3600
	10	[1024]	GETTABLE 	4 2 -7	; "min"
	11	[1024]	MUL      	4 4 -8	; - 60
	12	[1024]	ADD      	3 3 4
	13	[1024]	GETTABLE 	4 2 -9	; "sec"
	14	[1024]	ADD      	3 3 4
	15	[1025]	SUB      	4 1 3
	16	[1026]	GETUPVAL 	5 0	; SQ3
	17	[1026]	GETTABLE 	5 5 -10	; "open"
	18	[1026]	GETUPVAL 	6 1	; db_location
	19	[1026]	CALL     	5 2 2
	20	[1036]	LOADK    	6 -11	; "        SELECT count(*),\n               sum(sum_period)\n        FROM    (\n                     SELECT sum(period)      AS sum_period\n                     FROM   page_stat\n                     WHERE  start_time >= '%s'\n                     GROUP  BY id_book, page\n                )\n    "
	21	[1037]	SELF     	7 5 -12	; "rowexec"
	22	[1037]	GETGLOBAL	9 -13	; string
	23	[1037]	GETTABLE 	9 9 -14	; "format"
	24	[1037]	MOVE     	10 6
	25	[1037]	MOVE     	11 4
	26	[1037]	CALL     	9 3 0
	27	[1037]	CALL     	7 0 3
	28	[1038]	EQ       	0 7 -15	; - nil
	29	[1038]	JMP      	1	; to 31
	30	[1039]	LOADK    	7 -16	; 0
	31	[1041]	EQ       	0 8 -15	; - nil
	32	[1041]	JMP      	1	; to 34
	33	[1042]	LOADK    	8 -16	; 0
	34	[1044]	GETGLOBAL	9 -17	; tonumber
	35	[1044]	MOVE     	10 8
	36	[1044]	CALL     	9 2 2
	37	[1044]	MOVE     	8 9
	38	[1045]	GETGLOBAL	9 -17	; tonumber
	39	[1045]	MOVE     	10 7
	40	[1045]	CALL     	9 2 2
	41	[1045]	MOVE     	7 9
	42	[1046]	SELF     	9 5 -18	; "close"
	43	[1046]	CALL     	9 2 1
	44	[1047]	MOVE     	9 8
	45	[1047]	MOVE     	10 7
	46	[1047]	RETURN   	9 3
	47	[1048]	RETURN   	0 1

function <./plugins/statistics.koplugin/main.lua:1050,1072> (30 instructions, 120 bytes at 0x7fcdebc08820)
1 param, 8 slots, 2 upvalues, 5 locals, 9 constants, 0 functions
	1	[1051]	GETUPVAL 	1 0	; SQ3
	2	[1051]	GETTABLE 	1 1 -1	; "open"
	3	[1051]	GETUPVAL 	2 1	; db_location
	4	[1051]	CALL     	1 2 2
	5	[1061]	LOADK    	2 -2	; "        SELECT count(*),\n               sum(sum_period)\n        FROM   (\n                    SELECT sum(period)      AS sum_period\n                    FROM   page_stat\n                    WHERE  start_time >= '%s'\n                    GROUP  BY id_book, page\n               )\n    "
	6	[1062]	SELF     	3 1 -3	; "rowexec"
	7	[1062]	GETGLOBAL	5 -4	; string
	8	[1062]	GETTABLE 	5 5 -5	; "format"
	9	[1062]	MOVE     	6 2
	10	[1062]	GETTABLE 	7 0 -6	; "start_current_period"
	11	[1062]	CALL     	5 3 0
	12	[1062]	CALL     	3 0 3
	13	[1063]	EQ       	0 3 -7	; - nil
	14	[1063]	JMP      	1	; to 16
	15	[1064]	LOADK    	3 -8	; 0
	16	[1066]	EQ       	0 4 -7	; - nil
	17	[1066]	JMP      	1	; to 19
	18	[1067]	LOADK    	4 -8	; 0
	19	[1069]	GETGLOBAL	5 -9	; tonumber
	20	[1069]	MOVE     	6 4
	21	[1069]	CALL     	5 2 2
	22	[1069]	MOVE     	4 5
	23	[1070]	GETGLOBAL	5 -9	; tonumber
	24	[1070]	MOVE     	6 3
	25	[1070]	CALL     	5 2 2
	26	[1070]	MOVE     	3 5
	27	[1071]	MOVE     	5 4
	28	[1071]	MOVE     	6 3
	29	[1071]	RETURN   	5 3
	30	[1072]	RETURN   	0 1

function <./plugins/statistics.koplugin/main.lua:1074,1134> (238 instructions, 952 bytes at 0x7fcdebc14470)
2 params, 39 slots, 6 upvalues, 17 locals, 51 constants, 0 functions
	1	[1075]	EQ       	0 1 -1	; - nil
	2	[1075]	JMP      	1	; to 4
	3	[1076]	RETURN   	0 1
	4	[1078]	SELF     	2 0 -2	; "insertDB"
	5	[1078]	MOVE     	4 1
	6	[1078]	CALL     	2 3 1
	7	[1079]	SELF     	2 0 -3	; "getTodayBookStats"
	8	[1079]	CALL     	2 2 3
	9	[1080]	SELF     	4 0 -4	; "getCurrentBookStats"
	10	[1080]	CALL     	4 2 3
	11	[1082]	GETUPVAL 	6 0	; SQ3
	12	[1082]	GETTABLE 	6 6 -5	; "open"
	13	[1082]	GETUPVAL 	7 1	; db_location
	14	[1082]	CALL     	6 2 2
	15	[1083]	SELF     	7 6 -6	; "rowexec"
	16	[1083]	GETGLOBAL	9 -7	; string
	17	[1083]	GETTABLE 	9 9 -8	; "format"
	18	[1083]	LOADK    	10 -9	; "SELECT notes, highlights  FROM book WHERE id = '%s';)"
	19	[1083]	MOVE     	11 1
	20	[1083]	CALL     	9 3 0
	21	[1083]	CALL     	7 0 3
	22	[1092]	LOADK    	9 -10	; "        SELECT count(*)\n        FROM   (\n                    SELECT strftime('%%Y-%%m-%%d', start_time, 'unixepoch', 'localtime') AS dates\n                    FROM   page_stat\n                    WHERE  id_book = '%s'\n                    GROUP  BY dates\n               )\n    "
	23	[1093]	SELF     	10 6 -6	; "rowexec"
	24	[1093]	GETGLOBAL	12 -7	; string
	25	[1093]	GETTABLE 	12 12 -8	; "format"
	26	[1093]	MOVE     	13 9
	27	[1093]	MOVE     	14 1
	28	[1093]	CALL     	12 3 0
	29	[1093]	CALL     	10 0 2
	30	[1099]	LOADK    	9 -11	; "        SELECT sum(period),\n               count(DISTINCT page)\n        FROM   page_stat\n        WHERE  id_book = '%s'\n    "
	31	[1100]	SELF     	11 6 -6	; "rowexec"
	32	[1100]	GETGLOBAL	13 -7	; string
	33	[1100]	GETTABLE 	13 13 -8	; "format"
	34	[1100]	MOVE     	14 9
	35	[1100]	MOVE     	15 1
	36	[1100]	CALL     	13 3 0
	37	[1100]	CALL     	11 0 3
	38	[1101]	SELF     	13 6 -12	; "close"
	39	[1101]	CALL     	13 2 1
	40	[1103]	EQ       	0 11 -1	; - nil
	41	[1103]	JMP      	1	; to 43
	42	[1104]	LOADK    	11 -13	; 0
	43	[1106]	EQ       	0 12 -1	; - nil
	44	[1106]	JMP      	1	; to 46
	45	[1107]	LOADK    	12 -13	; 0
	46	[1109]	GETTABLE 	13 0 -14	; "data"
	47	[1109]	GETTABLE 	14 0 -16	; "view"
	48	[1109]	GETTABLE 	14 14 -17	; "document"
	49	[1109]	SELF     	14 14 -18	; "getPageCount"
	50	[1109]	CALL     	14 2 2
	51	[1109]	SETTABLE 	13 -15 14	; "pages" -
	52	[1110]	GETGLOBAL	13 -19	; tonumber
	53	[1110]	MOVE     	14 11
	54	[1110]	CALL     	13 2 2
	55	[1110]	MOVE     	11 13
	56	[1111]	GETGLOBAL	13 -19	; tonumber
	57	[1111]	MOVE     	14 12
	58	[1111]	CALL     	13 2 2
	59	[1111]	MOVE     	12 13
	60	[1112]	GETTABLE 	13 0 -14	; "data"
	61	[1112]	GETTABLE 	13 13 -15	; "pages"
	62	[1112]	GETTABLE 	14 0 -16	; "view"
	63	[1112]	GETTABLE 	14 14 -20	; "state"
	64	[1112]	GETTABLE 	14 14 -21	; "page"
	65	[1112]	SUB      	13 13 14
	66	[1112]	GETTABLE 	14 0 -22	; "avg_time"
	67	[1112]	MUL      	13 13 14
	68	[1113]	GETGLOBAL	14 -23	; math
	69	[1113]	GETTABLE 	14 14 -24	; "ceil"
	70	[1113]	GETGLOBAL	15 -19	; tonumber
	71	[1113]	MOVE     	16 10
	72	[1113]	CALL     	15 2 2
	73	[1113]	DIV      	15 11 15
	74	[1113]	DIV      	15 13 15
	75	[1113]	CALL     	14 2 2
	76	[1114]	GETGLOBAL	15 -25	; os
	77	[1114]	GETTABLE 	15 15 -26	; "date"
	78	[1114]	LOADK    	16 -27	; "%Y-%m-%d"
	79	[1114]	GETGLOBAL	17 -19	; tonumber
	80	[1114]	GETGLOBAL	18 -25	; os
	81	[1114]	GETTABLE 	18 18 -28	; "time"
	82	[1114]	CALL     	18 1 2
	83	[1114]	MUL      	19 14 -29	; - 86400
	84	[1114]	ADD      	18 18 19
	85	[1114]	CALL     	17 2 0
	86	[1114]	CALL     	15 0 2
	87	[1115]	LOADK    	16 -30	; "%.0f%%"
	88	[1116]	NEWTABLE 	17 15 0
	89	[1116]	NEWTABLE 	18 1 0
	90	[1117]	GETUPVAL 	19 2	; _
	91	[1117]	LOADK    	20 -31	; "Time spent reading this session"
	92	[1117]	CALL     	19 2 2
	93	[1117]	GETUPVAL 	20 3	; util
	94	[1117]	GETTABLE 	20 20 -32	; "secondsToClock"
	95	[1117]	MOVE     	21 4
	96	[1117]	LOADBOOL 	22 0 0
	97	[1117]	CALL     	20 3 0
	98	[1117]	SETLIST  	18 0 1	; 1
	99	[1117]	NEWTABLE 	19 1 0
	100	[1118]	GETUPVAL 	20 2	; _
	101	[1118]	LOADK    	21 -33	; "Pages read this session"
	102	[1118]	CALL     	20 2 2
	103	[1118]	GETGLOBAL	21 -19	; tonumber
	104	[1118]	MOVE     	22 5
	105	[1118]	CALL     	21 2 0
	106	[1118]	SETLIST  	19 0 1	; 1
	107	[1118]	NEWTABLE 	20 1 0
	108	[1119]	GETUPVAL 	21 2	; _
	109	[1119]	LOADK    	22 -34	; "Time spent reading today"
	110	[1119]	CALL     	21 2 2
	111	[1119]	GETUPVAL 	22 3	; util
	112	[1119]	GETTABLE 	22 22 -32	; "secondsToClock"
	113	[1119]	MOVE     	23 2
	114	[1119]	LOADBOOL 	24 0 0
	115	[1119]	CALL     	22 3 0
	116	[1119]	SETLIST  	20 0 1	; 1
	117	[1119]	NEWTABLE 	21 1 0
	118	[1120]	GETUPVAL 	22 2	; _
	119	[1120]	LOADK    	23 -35	; "Pages read today"
	120	[1120]	CALL     	22 2 2
	121	[1120]	GETGLOBAL	23 -19	; tonumber
	122	[1120]	MOVE     	24 3
	123	[1120]	CALL     	23 2 0
	124	[1120]	SETLIST  	21 0 1	; 1
	125	[1120]	NEWTABLE 	22 3 0
	126	[1121]	GETUPVAL 	23 2	; _
	127	[1121]	LOADK    	24 -36	; "Time to read"
	128	[1121]	CALL     	23 2 2
	129	[1121]	GETUPVAL 	24 3	; util
	130	[1121]	GETTABLE 	24 24 -32	; "secondsToClock"
	131	[1121]	MOVE     	25 13
	132	[1121]	CALL     	24 2 2
	133	[1121]	LOADBOOL 	25 0 0
	134	[1121]	SETLIST  	22 3 1	; 1
	135	[1121]	NEWTABLE 	23 1 0
	136	[1122]	GETUPVAL 	24 2	; _
	137	[1122]	LOADK    	25 -37	; "Total time"
	138	[1122]	CALL     	24 2 2
	139	[1122]	GETUPVAL 	25 3	; util
	140	[1122]	GETTABLE 	25 25 -32	; "secondsToClock"
	141	[1122]	MOVE     	26 11
	142	[1122]	LOADBOOL 	27 0 0
	143	[1122]	CALL     	25 3 0
	144	[1122]	SETLIST  	23 0 1	; 1
	145	[1122]	NEWTABLE 	24 1 0
	146	[1123]	GETUPVAL 	25 2	; _
	147	[1123]	LOADK    	26 -38	; "Total highlights"
	148	[1123]	CALL     	25 2 2
	149	[1123]	GETGLOBAL	26 -19	; tonumber
	150	[1123]	MOVE     	27 8
	151	[1123]	CALL     	26 2 0
	152	[1123]	SETLIST  	24 0 1	; 1
	153	[1123]	NEWTABLE 	25 1 0
	154	[1124]	GETUPVAL 	26 2	; _
	155	[1124]	LOADK    	27 -39	; "Total notes"
	156	[1124]	CALL     	26 2 2
	157	[1124]	GETGLOBAL	27 -19	; tonumber
	158	[1124]	MOVE     	28 7
	159	[1124]	CALL     	27 2 0
	160	[1124]	SETLIST  	25 0 1	; 1
	161	[1124]	NEWTABLE 	26 1 0
	162	[1125]	GETUPVAL 	27 2	; _
	163	[1125]	LOADK    	28 -40	; "Total pages read"
	164	[1125]	CALL     	27 2 2
	165	[1125]	GETGLOBAL	28 -19	; tonumber
	166	[1125]	MOVE     	29 12
	167	[1125]	CALL     	28 2 0
	168	[1125]	SETLIST  	26 0 1	; 1
	169	[1125]	NEWTABLE 	27 1 0
	170	[1126]	GETUPVAL 	28 2	; _
	171	[1126]	LOADK    	29 -41	; "Total days"
	172	[1126]	CALL     	28 2 2
	173	[1126]	GETGLOBAL	29 -19	; tonumber
	174	[1126]	MOVE     	30 10
	175	[1126]	CALL     	29 2 0
	176	[1126]	SETLIST  	27 0 1	; 1
	177	[1126]	NEWTABLE 	28 1 0
	178	[1127]	GETUPVAL 	29 2	; _
	179	[1127]	LOADK    	30 -42	; "Average time per page"
	180	[1127]	CALL     	29 2 2
	181	[1127]	GETUPVAL 	30 3	; util
	182	[1127]	GETTABLE 	30 30 -32	; "secondsToClock"
	183	[1127]	GETTABLE 	31 0 -22	; "avg_time"
	184	[1127]	LOADBOOL 	32 0 0
	185	[1127]	CALL     	30 3 0
	186	[1127]	SETLIST  	28 0 1	; 1
	187	[1127]	NEWTABLE 	29 2 0
	188	[1128]	GETUPVAL 	30 2	; _
	189	[1128]	LOADK    	31 -43	; "Current pages read/Total pages"
	190	[1128]	CALL     	30 2 2
	191	[1128]	GETTABLE 	31 0 -44	; "curr_page"
	192	[1128]	LOADK    	32 -45	; "/"
	193	[1128]	GETTABLE 	33 0 -14	; "data"
	194	[1128]	GETTABLE 	33 33 -15	; "pages"
	195	[1128]	CONCAT   	31 31 33
	196	[1128]	SETLIST  	29 2 1	; 1
	197	[1128]	NEWTABLE 	30 1 0
	198	[1129]	GETUPVAL 	31 2	; _
	199	[1129]	LOADK    	32 -46	; "Percentage completed"
	200	[1129]	CALL     	31 2 2
	201	[1129]	SELF     	32 16 -8	; "format"
	202	[1129]	GETTABLE 	34 0 -44	; "curr_page"
	203	[1129]	GETTABLE 	35 0 -14	; "data"
	204	[1129]	GETTABLE 	35 35 -15	; "pages"
	205	[1129]	DIV      	34 34 35
	206	[1129]	MUL      	34 34 -47	; - 100
	207	[1129]	CALL     	32 3 0
	208	[1129]	SETLIST  	30 0 1	; 1
	209	[1129]	NEWTABLE 	31 3 0
	210	[1130]	GETUPVAL 	32 2	; _
	211	[1130]	LOADK    	33 -48	; "Average time per day"
	212	[1130]	CALL     	32 2 2
	213	[1130]	GETUPVAL 	33 3	; util
	214	[1130]	GETTABLE 	33 33 -32	; "secondsToClock"
	215	[1130]	GETGLOBAL	34 -19	; tonumber
	216	[1130]	MOVE     	35 10
	217	[1130]	CALL     	34 2 2
	218	[1130]	DIV      	34 11 34
	219	[1130]	CALL     	33 2 2
	220	[1130]	LOADBOOL 	34 0 0
	221	[1130]	SETLIST  	31 3 1	; 1
	222	[1130]	NEWTABLE 	32 1 0
	223	[1131]	GETUPVAL 	33 2	; _
	224	[1131]	LOADK    	34 -49	; "Estimated reading finished"
	225	[1131]	CALL     	33 2 2
	226	[1132]	GETUPVAL 	34 4	; T
	227	[1132]	GETUPVAL 	35 5	; N_
	228	[1132]	LOADK    	36 -50	; "%1 (1 day)"
	229	[1132]	LOADK    	37 -51	; "%1 (%2 days)"
	230	[1132]	MOVE     	38 14
	231	[1132]	CALL     	35 4 2
	232	[1132]	MOVE     	36 15
	233	[1132]	MOVE     	37 14
	234	[1132]	CALL     	34 4 0
	235	[1132]	SETLIST  	32 0 1	; 1
	236	[1133]	SETLIST  	17 15 1	; 1
	237	[1133]	RETURN   	17 2
	238	[1134]	RETURN   	0 1

function <./plugins/statistics.koplugin/main.lua:1136,1219> (187 instructions, 748 bytes at 0x7fcdebc11ba0)
2 params, 32 slots, 6 upvalues, 15 locals, 38 constants, 1 function
	1	[1137]	EQ       	0 1 -1	; - nil
	2	[1137]	JMP      	1	; to 4
	3	[1138]	RETURN   	0 1
	4	[1140]	GETUPVAL 	2 0	; SQ3
	5	[1140]	GETTABLE 	2 2 -2	; "open"
	6	[1140]	GETUPVAL 	3 1	; db_location
	7	[1140]	CALL     	2 2 2
	8	[1145]	LOADK    	3 -3	; "        SELECT title, authors, notes, highlights, pages, last_open\n        FROM book\n        WHERE id = '%s'\n    "
	9	[1146]	SELF     	4 2 -4	; "rowexec"
	10	[1146]	GETGLOBAL	6 -5	; string
	11	[1146]	GETTABLE 	6 6 -6	; "format"
	12	[1146]	MOVE     	7 3
	13	[1146]	MOVE     	8 1
	14	[1146]	CALL     	6 3 0
	15	[1146]	CALL     	4 0 7
	16	[1156]	LOADK    	3 -7	; "        SELECT count(*)\n        FROM   (\n                    SELECT strftime('%%Y-%%m-%%d', start_time, 'unixepoch', 'localtime') AS dates\n                    FROM   page_stat\n                    WHERE  id_book = '%s'\n                    GROUP  BY dates\n               )\n    "
	17	[1157]	SELF     	10 2 -4	; "rowexec"
	18	[1157]	GETGLOBAL	12 -5	; string
	19	[1157]	GETTABLE 	12 12 -6	; "format"
	20	[1157]	MOVE     	13 3
	21	[1157]	MOVE     	14 1
	22	[1157]	CALL     	12 3 0
	23	[1157]	CALL     	10 0 2
	24	[1164]	LOADK    	3 -8	; "        SELECT sum(period),\n               count(DISTINCT page)\n        FROM   page_stat\n        WHERE  id_book = '%s'\n    "
	25	[1165]	SELF     	11 2 -4	; "rowexec"
	26	[1165]	GETGLOBAL	13 -5	; string
	27	[1165]	GETTABLE 	13 13 -6	; "format"
	28	[1165]	MOVE     	14 3
	29	[1165]	MOVE     	15 1
	30	[1165]	CALL     	13 3 0
	31	[1165]	CALL     	11 0 3
	32	[1171]	LOADK    	3 -9	; "        SELECT min(start_time)\n        FROM   page_stat\n        WHERE  id_book = '%s'\n    "
	33	[1172]	SELF     	13 2 -4	; "rowexec"
	34	[1172]	GETGLOBAL	15 -5	; string
	35	[1172]	GETTABLE 	15 15 -6	; "format"
	36	[1172]	MOVE     	16 3
	37	[1172]	MOVE     	17 1
	38	[1172]	CALL     	15 3 0
	39	[1172]	CALL     	13 0 2
	40	[1173]	SELF     	14 2 -10	; "close"
	41	[1173]	CALL     	14 2 1
	42	[1175]	EQ       	0 11 -1	; - nil
	43	[1175]	JMP      	1	; to 45
	44	[1176]	LOADK    	11 -11	; 0
	45	[1178]	EQ       	0 12 -1	; - nil
	46	[1178]	JMP      	1	; to 48
	47	[1179]	LOADK    	12 -11	; 0
	48	[1181]	GETGLOBAL	14 -12	; tonumber
	49	[1181]	MOVE     	15 11
	50	[1181]	CALL     	14 2 2
	51	[1181]	MOVE     	11 14
	52	[1182]	GETGLOBAL	14 -12	; tonumber
	53	[1182]	MOVE     	15 12
	54	[1182]	CALL     	14 2 2
	55	[1182]	MOVE     	12 14
	56	[1183]	GETGLOBAL	14 -12	; tonumber
	57	[1183]	MOVE     	15 8
	58	[1183]	CALL     	14 2 2
	59	[1183]	MOVE     	8 14
	60	[1184]	EQ       	1 8 -1	; - nil
	61	[1184]	JMP      	2	; to 64
	62	[1184]	EQ       	0 8 -11	; - 0
	63	[1184]	JMP      	1	; to 65
	64	[1185]	LOADK    	8 -13	; 1
	65	[1187]	DIV      	14 11 12
	66	[1188]	NEWTABLE 	15 13 0
	67	[1188]	NEWTABLE 	16 2 0
	68	[1189]	GETUPVAL 	17 2	; _
	69	[1189]	LOADK    	18 -14	; "Title"
	70	[1189]	CALL     	17 2 2
	71	[1189]	MOVE     	18 4
	72	[1189]	SETLIST  	16 2 1	; 1
	73	[1189]	NEWTABLE 	17 2 0
	74	[1190]	GETUPVAL 	18 2	; _
	75	[1190]	LOADK    	19 -15	; "Authors"
	76	[1190]	CALL     	18 2 2
	77	[1190]	MOVE     	19 5
	78	[1190]	SETLIST  	17 2 1	; 1
	79	[1190]	NEWTABLE 	18 1 0
	80	[1191]	GETUPVAL 	19 2	; _
	81	[1191]	LOADK    	20 -16	; "First opened"
	82	[1191]	CALL     	19 2 2
	83	[1191]	GETGLOBAL	20 -17	; os
	84	[1191]	GETTABLE 	20 20 -18	; "date"
	85	[1191]	LOADK    	21 -19	; "%Y-%m-%d (%H:%M)"
	86	[1191]	GETGLOBAL	22 -12	; tonumber
	87	[1191]	MOVE     	23 13
	88	[1191]	CALL     	22 2 0
	89	[1191]	CALL     	20 0 0
	90	[1191]	SETLIST  	18 0 1	; 1
	91	[1191]	NEWTABLE 	19 1 0
	92	[1192]	GETUPVAL 	20 2	; _
	93	[1192]	LOADK    	21 -20	; "Last opened"
	94	[1192]	CALL     	20 2 2
	95	[1192]	GETGLOBAL	21 -17	; os
	96	[1192]	GETTABLE 	21 21 -18	; "date"
	97	[1192]	LOADK    	22 -19	; "%Y-%m-%d (%H:%M)"
	98	[1192]	GETGLOBAL	23 -12	; tonumber
	99	[1192]	MOVE     	24 9
	100	[1192]	CALL     	23 2 0
	101	[1192]	CALL     	21 0 0
	102	[1192]	SETLIST  	19 0 1	; 1
	103	[1192]	NEWTABLE 	20 1 0
	104	[1193]	GETUPVAL 	21 2	; _
	105	[1193]	LOADK    	22 -21	; "Total time"
	106	[1193]	CALL     	21 2 2
	107	[1193]	GETUPVAL 	22 3	; util
	108	[1193]	GETTABLE 	22 22 -22	; "secondsToClock"
	109	[1193]	MOVE     	23 11
	110	[1193]	LOADBOOL 	24 0 0
	111	[1193]	CALL     	22 3 0
	112	[1193]	SETLIST  	20 0 1	; 1
	113	[1193]	NEWTABLE 	21 1 0
	114	[1194]	GETUPVAL 	22 2	; _
	115	[1194]	LOADK    	23 -23	; "Total highlights"
	116	[1194]	CALL     	22 2 2
	117	[1194]	GETGLOBAL	23 -12	; tonumber
	118	[1194]	MOVE     	24 7
	119	[1194]	CALL     	23 2 0
	120	[1194]	SETLIST  	21 0 1	; 1
	121	[1194]	NEWTABLE 	22 1 0
	122	[1195]	GETUPVAL 	23 2	; _
	123	[1195]	LOADK    	24 -24	; "Total notes"
	124	[1195]	CALL     	23 2 2
	125	[1195]	GETGLOBAL	24 -12	; tonumber
	126	[1195]	MOVE     	25 6
	127	[1195]	CALL     	24 2 0
	128	[1195]	SETLIST  	22 0 1	; 1
	129	[1195]	NEWTABLE 	23 1 0
	130	[1196]	GETUPVAL 	24 2	; _
	131	[1196]	LOADK    	25 -25	; "Total days"
	132	[1196]	CALL     	24 2 2
	133	[1196]	GETGLOBAL	25 -12	; tonumber
	134	[1196]	MOVE     	26 10
	135	[1196]	CALL     	25 2 0
	136	[1196]	SETLIST  	23 0 1	; 1
	137	[1196]	NEWTABLE 	24 1 0
	138	[1197]	GETUPVAL 	25 2	; _
	139	[1197]	LOADK    	26 -26	; "Average time per page"
	140	[1197]	CALL     	25 2 2
	141	[1197]	GETUPVAL 	26 3	; util
	142	[1197]	GETTABLE 	26 26 -22	; "secondsToClock"
	143	[1197]	MOVE     	27 14
	144	[1197]	LOADBOOL 	28 0 0
	145	[1197]	CALL     	26 3 0
	146	[1197]	SETLIST  	24 0 1	; 1
	147	[1197]	NEWTABLE 	25 2 0
	148	[1198]	GETUPVAL 	26 2	; _
	149	[1198]	LOADK    	27 -27	; "Read pages/Total pages"
	150	[1198]	CALL     	26 2 2
	151	[1198]	MOVE     	27 12
	152	[1198]	LOADK    	28 -28	; "/"
	153	[1198]	MOVE     	29 8
	154	[1198]	CONCAT   	27 27 29
	155	[1198]	SETLIST  	25 2 1	; 1
	156	[1198]	NEWTABLE 	26 2 0
	157	[1200]	GETUPVAL 	27 2	; _
	158	[1200]	LOADK    	28 -29	; "Percentage completed"
	159	[1200]	CALL     	27 2 2
	160	[1200]	GETGLOBAL	28 -30	; math
	161	[1200]	GETTABLE 	28 28 -31	; "floor"
	162	[1200]	DIV      	29 12 8
	163	[1200]	MUL      	29 29 -32	; - 100
	164	[1200]	ADD      	29 29 -33	; - 0.5
	165	[1200]	CALL     	28 2 2
	166	[1200]	LOADK    	29 -34	; "%"
	167	[1200]	CONCAT   	28 28 29
	168	[1200]	SETLIST  	26 2 1	; 1
	169	[1201]	LOADK    	27 -35	; "----"
	170	[1201]	NEWTABLE 	28 2 1
	171	[1202]	GETUPVAL 	29 2	; _
	172	[1202]	LOADK    	30 -36	; "Show days"
	173	[1202]	CALL     	29 2 2
	174	[1202]	GETUPVAL 	30 2	; _
	175	[1202]	LOADK    	31 -37	; "Tap to display"
	176	[1202]	CALL     	30 2 2
	177	[1216]	CLOSURE  	31 0	; 0x7fcdebc12120
	178	[1216]	MOVE     	0 0
	179	[1216]	GETUPVAL 	0 4	; UIManager
	180	[1216]	GETUPVAL 	0 5	; KeyValuePage
	181	[1216]	GETUPVAL 	0 2	; _
	182	[1216]	MOVE     	0 1
	183	[1216]	SETTABLE 	28 -38 31	; "callback" -
	184	[1217]	SETLIST  	28 2 1	; 1
	185	[1218]	SETLIST  	15 13 1	; 1
	186	[1218]	RETURN   	15 2
	187	[1219]	RETURN   	0 1

function <./plugins/statistics.koplugin/main.lua:1203,1216> (34 instructions, 136 bytes at 0x7fcdebc12120)
0 params, 8 slots, 5 upvalues, 1 local, 11 constants, 1 function
	1	[1204]	GETUPVAL 	0 0	; self
	2	[1204]	GETTABLE 	0 0 -1	; "kv"
	3	[1205]	GETUPVAL 	1 1	; UIManager
	4	[1205]	SELF     	1 1 -2	; "close"
	5	[1205]	GETUPVAL 	3 0	; self
	6	[1205]	GETTABLE 	3 3 -1	; "kv"
	7	[1205]	CALL     	1 3 1
	8	[1206]	GETUPVAL 	1 0	; self
	9	[1206]	GETUPVAL 	2 2	; KeyValuePage
	10	[1206]	SELF     	2 2 -3	; "new"
	11	[1206]	NEWTABLE 	4 0 4
	12	[1207]	GETUPVAL 	5 3	; _
	13	[1207]	LOADK    	6 -5	; "Read in days"
	14	[1207]	CALL     	5 2 2
	15	[1207]	SETTABLE 	4 -4 5	; "title" -
	16	[1208]	SETTABLE 	4 -6 -7	; "value_overflow_align" "right"
	17	[1209]	GETUPVAL 	5 0	; self
	18	[1209]	SELF     	5 5 -9	; "getDatesForBook"
	19	[1209]	GETUPVAL 	7 4	; id_book
	20	[1209]	CALL     	5 3 2
	21	[1209]	SETTABLE 	4 -8 5	; "kv_pairs" -
	22	[1213]	CLOSURE  	5 0	; 0x7fcdebc13aa0
	23	[1213]	GETUPVAL 	0 1	; UIManager
	24	[1213]	MOVE     	0 0
	25	[1213]	GETUPVAL 	0 0	; self
	26	[1213]	SETTABLE 	4 -10 5	; "callback_return" -
	27	[1206]	CALL     	2 3 2
	28	[1214]	SETTABLE 	1 -1 2	; "kv" -
	29	[1215]	GETUPVAL 	1 1	; UIManager
	30	[1215]	SELF     	1 1 -11	; "show"
	31	[1215]	GETUPVAL 	3 0	; self
	32	[1215]	GETTABLE 	3 3 -1	; "kv"
	33	[1215]	CALL     	1 3 1
	34	[1216]	RETURN   	0 1

function <./plugins/statistics.koplugin/main.lua:1210,1213> (8 instructions, 32 bytes at 0x7fcdebc13aa0)
0 params, 3 slots, 3 upvalues, 0 locals, 2 constants, 0 functions
	1	[1211]	GETUPVAL 	0 0	; UIManager
	2	[1211]	SELF     	0 0 -1	; "show"
	3	[1211]	GETUPVAL 	2 1	; kv
	4	[1211]	CALL     	0 3 1
	5	[1212]	GETUPVAL 	0 2	; self
	6	[1212]	GETUPVAL 	1 1	; kv
	7	[1212]	SETTABLE 	0 -2 1	; "kv" -
	8	[1213]	RETURN   	0 1

function <./plugins/statistics.koplugin/main.lua:1221,1239> (3 instructions, 12 bytes at 0x7fcdebc13900)
0 params, 2 slots, 0 upvalues, 0 locals, 1 constant, 0 functions
	1	[1238]	LOADK    	0 -1	; "            SELECT dates,\n                   count(*)             AS pages,\n                   sum(sum_period)      AS periods,\n                   start_time\n            FROM   (\n                        SELECT strftime('%%Y-%%m-%%d', start_time, 'unixepoch', 'localtime') AS dates,\n                               sum(period)                                                   AS sum_period,\n                               start_time\n                        FROM   page_stat\n                        WHERE  start_time >= '%s'\n                        GROUP  BY id_book, page, dates\n                   )\n            GROUP  BY dates\n            ORDER  BY dates DESC\n    "
	2	[1238]	RETURN   	0 2
	3	[1239]	RETURN   	0 1

function <./plugins/statistics.koplugin/main.lua:1241,1259> (3 instructions, 12 bytes at 0x7fcdebc14ae0)
0 params, 2 slots, 0 upvalues, 0 locals, 1 constant, 0 functions
	1	[1258]	LOADK    	0 -1	; "            SELECT dates,\n                   count(*)             AS pages,\n                   sum(sum_period)      AS periods,\n                   start_time\n            FROM   (\n                        SELECT strftime('%%Y-%%W', start_time, 'unixepoch', 'localtime')     AS dates,\n                               sum(period)                                                   AS sum_period,\n                               start_time\n                        FROM   page_stat\n                        WHERE  start_time >= '%s'\n                        GROUP  BY id_book, page, dates\n                   )\n            GROUP  BY dates\n            ORDER  BY dates DESC\n    "
	2	[1258]	RETURN   	0 2
	3	[1259]	RETURN   	0 1

function <./plugins/statistics.koplugin/main.lua:1261,1279> (3 instructions, 12 bytes at 0x7fcdebc117d0)
0 params, 2 slots, 0 upvalues, 0 locals, 1 constant, 0 functions
	1	[1278]	LOADK    	0 -1	; "            SELECT dates,\n                   count(*)             AS pages,\n                   sum(sum_period)      AS periods,\n                   start_time\n            FROM   (\n                        SELECT strftime('%%Y-%%m', start_time, 'unixepoch', 'localtime')     AS dates,\n                               sum(period)                                                   AS sum_period,\n                               start_time\n                        FROM   page_stat\n                        WHERE  start_time >= '%s'\n                        GROUP  BY id_book, page, dates\n                   )\n            GROUP  BY dates\n            ORDER  BY dates DESC\n    "
	2	[1278]	RETURN   	0 2
	3	[1279]	RETURN   	0 1

function <./plugins/statistics.koplugin/main.lua:1281,1306> (53 instructions, 212 bytes at 0x7fcdebc17ad0)
5 params, 13 slots, 4 upvalues, 6 locals, 12 constants, 2 functions
	1	[1282]	GETTABLE 	5 0 -1	; "kv"
	2	[1283]	GETUPVAL 	6 0	; UIManager
	3	[1283]	SELF     	6 6 -2	; "close"
	4	[1283]	MOVE     	8 5
	5	[1283]	CALL     	6 3 1
	6	[1284]	TEST     	4 0 0
	7	[1284]	JMP      	24	; to 32
	8	[1285]	GETUPVAL 	6 1	; KeyValuePage
	9	[1285]	SELF     	6 6 -3	; "new"
	10	[1285]	NEWTABLE 	8 0 4
	11	[1286]	GETUPVAL 	9 2	; T
	12	[1286]	GETUPVAL 	10 3	; _
	13	[1286]	LOADK    	11 -5	; "Books from: %1"
	14	[1286]	CALL     	10 2 2
	15	[1286]	MOVE     	11 3
	16	[1286]	CALL     	9 3 2
	17	[1286]	SETTABLE 	8 -4 9	; "title" -
	18	[1287]	SETTABLE 	8 -6 -7	; "value_align" "right"
	19	[1288]	SELF     	9 0 -9	; "getBooksFromPeriod"
	20	[1288]	MOVE     	11 1
	21	[1288]	MOVE     	12 2
	22	[1288]	CALL     	9 4 2
	23	[1288]	SETTABLE 	8 -8 9	; "kv_pairs" -
	24	[1292]	CLOSURE  	9 0	; 0x7fcdebc14dc0
	25	[1292]	GETUPVAL 	0 0	; UIManager
	26	[1292]	MOVE     	0 5
	27	[1292]	MOVE     	0 0
	28	[1292]	SETTABLE 	8 -10 9	; "callback_return" -
	29	[1285]	CALL     	6 3 2
	30	[1293]	SETTABLE 	0 -1 6	; "kv" -
	31	[1293]	JMP      	17	; to 49
	32	[1295]	GETUPVAL 	6 1	; KeyValuePage
	33	[1295]	SELF     	6 6 -3	; "new"
	34	[1295]	NEWTABLE 	8 0 4
	35	[1296]	SETTABLE 	8 -4 3	; "title" -
	36	[1297]	SETTABLE 	8 -6 -7	; "value_align" "right"
	37	[1298]	SELF     	9 0 -11	; "getDaysFromPeriod"
	38	[1298]	MOVE     	11 1
	39	[1298]	MOVE     	12 2
	40	[1298]	CALL     	9 4 2
	41	[1298]	SETTABLE 	8 -8 9	; "kv_pairs" -
	42	[1302]	CLOSURE  	9 1	; 0x7fcdebc15bf0
	43	[1302]	GETUPVAL 	0 0	; UIManager
	44	[1302]	MOVE     	0 5
	45	[1302]	MOVE     	0 0
	46	[1302]	SETTABLE 	8 -10 9	; "callback_return" -
	47	[1295]	CALL     	6 3 2
	48	[1303]	SETTABLE 	0 -1 6	; "kv" -
	49	[1305]	GETUPVAL 	6 0	; UIManager
	50	[1305]	SELF     	6 6 -12	; "show"
	51	[1305]	GETTABLE 	8 0 -1	; "kv"
	52	[1305]	CALL     	6 3 1
	53	[1306]	RETURN   	0 1

function <./plugins/statistics.koplugin/main.lua:1289,1292> (8 instructions, 32 bytes at 0x7fcdebc14dc0)
0 params, 3 slots, 3 upvalues, 0 locals, 2 constants, 0 functions
	1	[1290]	GETUPVAL 	0 0	; UIManager
	2	[1290]	SELF     	0 0 -1	; "show"
	3	[1290]	GETUPVAL 	2 1	; kv
	4	[1290]	CALL     	0 3 1
	5	[1291]	GETUPVAL 	0 2	; self
	6	[1291]	GETUPVAL 	1 1	; kv
	7	[1291]	SETTABLE 	0 -2 1	; "kv" -
	8	[1292]	RETURN   	0 1

function <./plugins/statistics.koplugin/main.lua:1299,1302> (8 instructions, 32 bytes at 0x7fcdebc15bf0)
0 params, 3 slots, 3 upvalues, 0 locals, 2 constants, 0 functions
	1	[1300]	GETUPVAL 	0 0	; UIManager
	2	[1300]	SELF     	0 0 -1	; "show"
	3	[1300]	GETUPVAL 	2 1	; kv
	4	[1300]	CALL     	0 3 1
	5	[1301]	GETUPVAL 	0 2	; self
	6	[1301]	GETUPVAL 	1 1	; kv
	7	[1301]	SETTABLE 	0 -2 1	; "kv" -
	8	[1302]	RETURN   	0 1

function <./plugins/statistics.koplugin/main.lua:1308,1333> (53 instructions, 212 bytes at 0x7fcdebc184e0)
5 params, 13 slots, 4 upvalues, 6 locals, 12 constants, 2 functions
	1	[1309]	GETTABLE 	5 0 -1	; "kv"
	2	[1310]	GETUPVAL 	6 0	; UIManager
	3	[1310]	SELF     	6 6 -2	; "close"
	4	[1310]	MOVE     	8 5
	5	[1310]	CALL     	6 3 1
	6	[1311]	TEST     	4 0 0
	7	[1311]	JMP      	24	; to 32
	8	[1312]	GETUPVAL 	6 1	; KeyValuePage
	9	[1312]	SELF     	6 6 -3	; "new"
	10	[1312]	NEWTABLE 	8 0 4
	11	[1313]	GETUPVAL 	9 2	; T
	12	[1313]	GETUPVAL 	10 3	; _
	13	[1313]	LOADK    	11 -5	; "Books from: %1"
	14	[1313]	CALL     	10 2 2
	15	[1313]	MOVE     	11 3
	16	[1313]	CALL     	9 3 2
	17	[1313]	SETTABLE 	8 -4 9	; "title" -
	18	[1314]	SETTABLE 	8 -6 -7	; "value_align" "right"
	19	[1315]	SELF     	9 0 -9	; "getBooksFromPeriod"
	20	[1315]	MOVE     	11 1
	21	[1315]	MOVE     	12 2
	22	[1315]	CALL     	9 4 2
	23	[1315]	SETTABLE 	8 -8 9	; "kv_pairs" -
	24	[1319]	CLOSURE  	9 0	; 0x7fcdebc17480
	25	[1319]	GETUPVAL 	0 0	; UIManager
	26	[1319]	MOVE     	0 5
	27	[1319]	MOVE     	0 0
	28	[1319]	SETTABLE 	8 -10 9	; "callback_return" -
	29	[1312]	CALL     	6 3 2
	30	[1320]	SETTABLE 	0 -1 6	; "kv" -
	31	[1320]	JMP      	17	; to 49
	32	[1322]	GETUPVAL 	6 1	; KeyValuePage
	33	[1322]	SELF     	6 6 -3	; "new"
	34	[1322]	NEWTABLE 	8 0 4
	35	[1323]	SETTABLE 	8 -4 3	; "title" -
	36	[1324]	SETTABLE 	8 -6 -7	; "value_align" "right"
	37	[1325]	SELF     	9 0 -11	; "getDaysFromPeriod"
	38	[1325]	MOVE     	11 1
	39	[1325]	MOVE     	12 2
	40	[1325]	CALL     	9 4 2
	41	[1325]	SETTABLE 	8 -8 9	; "kv_pairs" -
	42	[1329]	CLOSURE  	9 1	; 0x7fcdebc18440
	43	[1329]	GETUPVAL 	0 0	; UIManager
	44	[1329]	MOVE     	0 5
	45	[1329]	MOVE     	0 0
	46	[1329]	SETTABLE 	8 -10 9	; "callback_return" -
	47	[1322]	CALL     	6 3 2
	48	[1330]	SETTABLE 	0 -1 6	; "kv" -
	49	[1332]	GETUPVAL 	6 0	; UIManager
	50	[1332]	SELF     	6 6 -12	; "show"
	51	[1332]	GETTABLE 	8 0 -1	; "kv"
	52	[1332]	CALL     	6 3 1
	53	[1333]	RETURN   	0 1

function <./plugins/statistics.koplugin/main.lua:1316,1319> (8 instructions, 32 bytes at 0x7fcdebc17480)
0 params, 3 slots, 3 upvalues, 0 locals, 2 constants, 0 functions
	1	[1317]	GETUPVAL 	0 0	; UIManager
	2	[1317]	SELF     	0 0 -1	; "show"
	3	[1317]	GETUPVAL 	2 1	; kv
	4	[1317]	CALL     	0 3 1
	5	[1318]	GETUPVAL 	0 2	; self
	6	[1318]	GETUPVAL 	1 1	; kv
	7	[1318]	SETTABLE 	0 -2 1	; "kv" -
	8	[1319]	RETURN   	0 1

function <./plugins/statistics.koplugin/main.lua:1326,1329> (8 instructions, 32 bytes at 0x7fcdebc18440)
0 params, 3 slots, 3 upvalues, 0 locals, 2 constants, 0 functions
	1	[1327]	GETUPVAL 	0 0	; UIManager
	2	[1327]	SELF     	0 0 -1	; "show"
	3	[1327]	GETUPVAL 	2 1	; kv
	4	[1327]	CALL     	0 3 1
	5	[1328]	GETUPVAL 	0 2	; self
	6	[1328]	GETUPVAL 	1 1	; kv
	7	[1328]	SETTABLE 	0 -2 1	; "kv" -
	8	[1329]	RETURN   	0 1

function <./plugins/statistics.koplugin/main.lua:1335,1348> (27 instructions, 108 bytes at 0x7fcdebc0fff0)
4 params, 12 slots, 2 upvalues, 5 locals, 10 constants, 1 function
	1	[1336]	GETTABLE 	4 0 -1	; "kv"
	2	[1337]	GETUPVAL 	5 0	; UIManager
	3	[1337]	SELF     	5 5 -2	; "close"
	4	[1337]	MOVE     	7 4
	5	[1337]	CALL     	5 3 1
	6	[1338]	GETUPVAL 	5 1	; KeyValuePage
	7	[1338]	SELF     	5 5 -3	; "new"
	8	[1338]	NEWTABLE 	7 0 4
	9	[1339]	SETTABLE 	7 -4 3	; "title" -
	10	[1340]	SETTABLE 	7 -5 -6	; "value_align" "right"
	11	[1341]	SELF     	8 0 -8	; "getBooksFromPeriod"
	12	[1341]	MOVE     	10 1
	13	[1341]	MOVE     	11 2
	14	[1341]	CALL     	8 4 2
	15	[1341]	SETTABLE 	7 -7 8	; "kv_pairs" -
	16	[1345]	CLOSURE  	8 0	; 0x7fcdebc11650
	17	[1345]	GETUPVAL 	0 0	; UIManager
	18	[1345]	MOVE     	0 4
	19	[1345]	MOVE     	0 0
	20	[1345]	SETTABLE 	7 -9 8	; "callback_return" -
	21	[1338]	CALL     	5 3 2
	22	[1346]	SETTABLE 	0 -1 5	; "kv" -
	23	[1347]	GETUPVAL 	5 0	; UIManager
	24	[1347]	SELF     	5 5 -10	; "show"
	25	[1347]	GETTABLE 	7 0 -1	; "kv"
	26	[1347]	CALL     	5 3 1
	27	[1348]	RETURN   	0 1

function <./plugins/statistics.koplugin/main.lua:1342,1345> (8 instructions, 32 bytes at 0x7fcdebc11650)
0 params, 3 slots, 3 upvalues, 0 locals, 2 constants, 0 functions
	1	[1343]	GETUPVAL 	0 0	; UIManager
	2	[1343]	SELF     	0 0 -1	; "show"
	3	[1343]	GETUPVAL 	2 1	; kv
	4	[1343]	CALL     	0 3 1
	5	[1344]	GETUPVAL 	0 2	; self
	6	[1344]	GETUPVAL 	1 1	; kv
	7	[1344]	SETTABLE 	0 -2 1	; "kv" -
	8	[1345]	RETURN   	0 1

function <./plugins/statistics.koplugin/main.lua:1356,1446> (372 instructions, 1488 bytes at 0x7fcdebc1a640)
4 params, 36 slots, 10 upvalues, 30 locals, 54 constants, 3 functions
	1	[1357]	NEWTABLE 	4 0 0
	2	[1358]	LOADNIL  	5 9
	3	[1360]	GETGLOBAL	10 -1	; os
	4	[1360]	GETTABLE 	10 10 -2	; "date"
	5	[1360]	LOADK    	11 -3	; "*t"
	6	[1360]	CALL     	10 2 2
	7	[1361]	GETTABLE 	11 10 -4	; "hour"
	8	[1361]	MUL      	11 11 -5	; - 3600
	9	[1361]	GETTABLE 	12 10 -6	; "min"
	10	[1361]	MUL      	12 12 -7	; - 60
	11	[1361]	ADD      	11 11 12
	12	[1361]	GETTABLE 	12 10 -8	; "sec"
	13	[1361]	ADD      	11 11 12
	14	[1362]	GETGLOBAL	12 -1	; os
	15	[1362]	GETTABLE 	12 12 -9	; "time"
	16	[1362]	CALL     	12 1 2
	17	[1363]	LOADK    	13 -10	; 86400
	18	[1364]	LOADNIL  	14 14
	19	[1365]	LOADK    	15 -11	; 0
	20	[1366]	LT       	0 -11 1	; 0 -
	21	[1366]	JMP      	4	; to 26
	22	[1367]	SUB      	16 1 -12	; - 1
	23	[1367]	MUL      	16 16 13
	24	[1367]	SUB      	16 12 16
	25	[1367]	SUB      	15 16 11
	26	[1369]	EQ       	1 2 -13	; - "daily"
	27	[1369]	JMP      	2	; to 30
	28	[1369]	EQ       	0 2 -14	; - "daily_weekday"
	29	[1369]	JMP      	4	; to 34
	30	[1370]	GETUPVAL 	16 0	; sqlDaily
	31	[1370]	CALL     	16 1 2
	32	[1370]	MOVE     	14 16
	33	[1370]	JMP      	11	; to 45
	34	[1371]	EQ       	0 2 -15	; - "weekly"
	35	[1371]	JMP      	4	; to 40
	36	[1372]	GETUPVAL 	16 1	; sqlWeekly
	37	[1372]	CALL     	16 1 2
	38	[1372]	MOVE     	14 16
	39	[1372]	JMP      	5	; to 45
	40	[1373]	EQ       	0 2 -16	; - "monthly"
	41	[1373]	JMP      	3	; to 45
	42	[1374]	GETUPVAL 	16 2	; sqlMonthly
	43	[1374]	CALL     	16 1 2
	44	[1374]	MOVE     	14 16
	45	[1376]	SELF     	16 0 -17	; "insertDB"
	46	[1376]	GETTABLE 	18 0 -18	; "id_curr_book"
	47	[1376]	CALL     	16 3 1
	48	[1377]	GETUPVAL 	16 3	; SQ3
	49	[1377]	GETTABLE 	16 16 -19	; "open"
	50	[1377]	GETUPVAL 	17 4	; db_location
	51	[1377]	CALL     	16 2 2
	52	[1378]	SELF     	17 16 -20	; "exec"
	53	[1378]	GETGLOBAL	19 -21	; string
	54	[1378]	GETTABLE 	19 19 -22	; "format"
	55	[1378]	MOVE     	20 14
	56	[1378]	MOVE     	21 15
	57	[1378]	CALL     	19 3 0
	58	[1378]	CALL     	17 0 2
	59	[1379]	SELF     	18 16 -23	; "close"
	60	[1379]	CALL     	18 2 1
	61	[1380]	EQ       	0 17 -24	; - nil
	62	[1380]	JMP      	2	; to 65
	63	[1381]	NEWTABLE 	18 0 0
	64	[1381]	RETURN   	18 2
	65	[1383]	LOADK    	18 -12	; 1
	66	[1383]	GETTABLE 	19 17 -25	; "dates"
	67	[1383]	LEN      	19 19
	68	[1383]	LOADK    	20 -12	; 1
	69	[1383]	FORPREP  	18 300	; to 370
	70	[1384]	LOADNIL  	22 22
	71	[1385]	GETGLOBAL	23 -26	; tonumber
	72	[1385]	GETTABLE 	24 17 -27	; 4
	73	[1385]	GETTABLE 	24 24 21
	74	[1385]	CALL     	23 2 2
	75	[1385]	MOVE     	9 23
	76	[1386]	EQ       	0 2 -14	; - "daily_weekday"
	77	[1386]	JMP      	18	; to 96
	78	[1387]	GETGLOBAL	23 -21	; string
	79	[1387]	GETTABLE 	23 23 -22	; "format"
	80	[1387]	LOADK    	24 -28	; "%s (%s)"
	81	[1388]	GETGLOBAL	25 -1	; os
	82	[1388]	GETTABLE 	25 25 -2	; "date"
	83	[1388]	LOADK    	26 -29	; "%Y-%m-%d"
	84	[1388]	MOVE     	27 9
	85	[1388]	CALL     	25 3 2
	86	[1389]	GETUPVAL 	26 5	; shortDayOfWeekTranslation
	87	[1389]	GETGLOBAL	27 -1	; os
	88	[1389]	GETTABLE 	27 27 -2	; "date"
	89	[1389]	LOADK    	28 -30	; "%a"
	90	[1389]	MOVE     	29 9
	91	[1389]	CALL     	27 3 2
	92	[1389]	GETTABLE 	26 26 27
	93	[1387]	CALL     	23 4 2
	94	[1389]	MOVE     	22 23
	95	[1389]	JMP      	42	; to 138
	96	[1390]	EQ       	0 2 -13	; - "daily"
	97	[1390]	JMP      	3	; to 101
	98	[1391]	GETTABLE 	23 17 -12	; 1
	99	[1391]	GETTABLE 	22 23 21
	100	[1391]	JMP      	37	; to 138
	101	[1392]	EQ       	0 2 -15	; - "weekly"
	102	[1392]	JMP      	17	; to 120
	103	[1393]	GETUPVAL 	23 6	; T
	104	[1393]	GETUPVAL 	24 7	; _
	105	[1393]	LOADK    	25 -31	; "%1 Week %2"
	106	[1393]	CALL     	24 2 2
	107	[1393]	GETGLOBAL	25 -1	; os
	108	[1393]	GETTABLE 	25 25 -2	; "date"
	109	[1393]	LOADK    	26 -32	; "%Y"
	110	[1393]	MOVE     	27 9
	111	[1393]	CALL     	25 3 2
	112	[1393]	GETGLOBAL	26 -1	; os
	113	[1393]	GETTABLE 	26 26 -2	; "date"
	114	[1393]	LOADK    	27 -33	; " %W"
	115	[1393]	MOVE     	28 9
	116	[1393]	CALL     	26 3 0
	117	[1393]	CALL     	23 0 2
	118	[1393]	MOVE     	22 23
	119	[1393]	JMP      	18	; to 138
	120	[1394]	EQ       	0 2 -16	; - "monthly"
	121	[1394]	JMP      	14	; to 136
	122	[1395]	GETUPVAL 	23 8	; monthTranslation
	123	[1395]	GETGLOBAL	24 -1	; os
	124	[1395]	GETTABLE 	24 24 -2	; "date"
	125	[1395]	LOADK    	25 -34	; "%B"
	126	[1395]	MOVE     	26 9
	127	[1395]	CALL     	24 3 2
	128	[1395]	GETTABLE 	23 23 24
	129	[1395]	GETGLOBAL	24 -1	; os
	130	[1395]	GETTABLE 	24 24 -2	; "date"
	131	[1395]	LOADK    	25 -35	; " %Y"
	132	[1395]	MOVE     	26 9
	133	[1395]	CALL     	24 3 2
	134	[1395]	CONCAT   	22 23 24
	135	[1395]	JMP      	2	; to 138
	136	[1397]	GETTABLE 	23 17 -12	; 1
	137	[1397]	GETTABLE 	22 23 21
	138	[1399]	EQ       	0 2 -16	; - "monthly"
	139	[1399]	JMP      	74	; to 214
	140	[1400]	GETGLOBAL	23 -26	; tonumber
	141	[1400]	GETGLOBAL	24 -1	; os
	142	[1400]	GETTABLE 	24 24 -2	; "date"
	143	[1400]	LOADK    	25 -32	; "%Y"
	144	[1400]	MOVE     	26 9
	145	[1400]	CALL     	24 3 0
	146	[1400]	CALL     	23 0 2
	147	[1400]	MOVE     	5 23
	148	[1401]	GETGLOBAL	23 -26	; tonumber
	149	[1401]	GETGLOBAL	24 -1	; os
	150	[1401]	GETTABLE 	24 24 -2	; "date"
	151	[1401]	LOADK    	25 -36	; "%m"
	152	[1401]	MOVE     	26 9
	153	[1401]	CALL     	24 3 0
	154	[1401]	CALL     	23 0 2
	155	[1401]	MOVE     	7 23
	156	[1402]	EQ       	0 7 -37	; - 12
	157	[1402]	JMP      	3	; to 161
	158	[1403]	ADD      	6 5 -12	; - 1
	159	[1404]	LOADK    	8 -12	; 1
	160	[1404]	JMP      	2	; to 163
	161	[1406]	MOVE     	6 5
	162	[1407]	ADD      	8 7 -12	; - 1
	163	[1409]	GETGLOBAL	23 -1	; os
	164	[1409]	GETTABLE 	23 23 -9	; "time"
	165	[1409]	NEWTABLE 	24 0 5
	166	[1409]	SETTABLE 	24 -38 5	; "year" -
	167	[1409]	SETTABLE 	24 -39 7	; "month" -
	168	[1409]	SETTABLE 	24 -40 -12	; "day" 1
	169	[1409]	SETTABLE 	24 -4 -11	; "hour" 0
	170	[1409]	SETTABLE 	24 -6 -11	; "min" 0
	171	[1409]	CALL     	23 2 2
	172	[1410]	GETGLOBAL	24 -1	; os
	173	[1410]	GETTABLE 	24 24 -9	; "time"
	174	[1410]	NEWTABLE 	25 0 5
	175	[1410]	SETTABLE 	25 -38 6	; "year" -
	176	[1410]	SETTABLE 	25 -39 8	; "month" -
	177	[1410]	SETTABLE 	25 -40 -12	; "day" 1
	178	[1410]	SETTABLE 	25 -4 -11	; "hour" 0
	179	[1410]	SETTABLE 	25 -6 -11	; "min" 0
	180	[1410]	CALL     	24 2 2
	181	[1411]	GETGLOBAL	25 -41	; table
	182	[1411]	GETTABLE 	25 25 -42	; "insert"
	183	[1411]	MOVE     	26 4
	184	[1411]	NEWTABLE 	27 2 1
	185	[1412]	MOVE     	28 22
	186	[1413]	GETUPVAL 	29 6	; T
	187	[1413]	GETUPVAL 	30 7	; _
	188	[1413]	LOADK    	31 -43	; "Pages: (%1) Time: %2"
	189	[1413]	CALL     	30 2 2
	190	[1413]	GETGLOBAL	31 -26	; tonumber
	191	[1413]	GETTABLE 	32 17 -44	; 2
	192	[1413]	GETTABLE 	32 32 21
	193	[1413]	CALL     	31 2 2
	194	[1413]	GETUPVAL 	32 9	; util
	195	[1413]	GETTABLE 	32 32 -45	; "secondsToClock"
	196	[1413]	GETGLOBAL	33 -26	; tonumber
	197	[1413]	GETTABLE 	34 17 -46	; 3
	198	[1413]	GETTABLE 	34 34 21
	199	[1413]	CALL     	33 2 2
	200	[1413]	LOADBOOL 	34 0 0
	201	[1413]	CALL     	32 3 0
	202	[1413]	CALL     	29 0 2
	203	[1416]	CLOSURE  	30 0	; 0x7fcdebc1aa20
	204	[1416]	MOVE     	0 0
	205	[1416]	MOVE     	0 23
	206	[1416]	MOVE     	0 24
	207	[1416]	MOVE     	0 22
	208	[1416]	MOVE     	0 3
	209	[1416]	SETTABLE 	27 -47 30	; "callback" -
	210	[1417]	SETLIST  	27 2 1	; 1
	211	[1411]	CALL     	25 3 1
	212	[1417]	CLOSE    	23
	213	[1417]	JMP      	155	; to 369
	214	[1418]	EQ       	0 2 -15	; - "weekly"
	215	[1418]	JMP      	85	; to 301
	216	[1419]	GETGLOBAL	23 -1	; os
	217	[1419]	GETTABLE 	23 23 -2	; "date"
	218	[1419]	LOADK    	24 -48	; "%H%M%S%w"
	219	[1419]	MOVE     	25 9
	220	[1419]	CALL     	23 3 2
	221	[1420]	GETGLOBAL	24 -26	; tonumber
	222	[1420]	GETTABLE 	25 17 -27	; 4
	223	[1420]	GETTABLE 	25 25 21
	224	[1420]	CALL     	24 2 2
	225	[1420]	GETGLOBAL	25 -26	; tonumber
	226	[1420]	GETGLOBAL	26 -21	; string
	227	[1420]	GETTABLE 	26 26 -49	; "sub"
	228	[1420]	MOVE     	27 23
	229	[1420]	LOADK    	28 -12	; 1
	230	[1420]	LOADK    	29 -44	; 2
	231	[1420]	CALL     	26 4 0
	232	[1420]	CALL     	25 0 2
	233	[1420]	MUL      	25 -5 25	; 3600 -
	234	[1420]	SUB      	24 24 25
	235	[1421]	GETGLOBAL	25 -26	; tonumber
	236	[1421]	GETGLOBAL	26 -21	; string
	237	[1421]	GETTABLE 	26 26 -49	; "sub"
	238	[1421]	MOVE     	27 23
	239	[1421]	LOADK    	28 -46	; 3
	240	[1421]	LOADK    	29 -27	; 4
	241	[1421]	CALL     	26 4 0
	242	[1421]	CALL     	25 0 2
	243	[1421]	MUL      	25 -7 25	; 60 -
	244	[1421]	SUB      	24 24 25
	245	[1421]	GETGLOBAL	25 -26	; tonumber
	246	[1421]	GETGLOBAL	26 -21	; string
	247	[1421]	GETTABLE 	26 26 -49	; "sub"
	248	[1421]	MOVE     	27 23
	249	[1421]	LOADK    	28 -50	; 5
	250	[1421]	LOADK    	29 -51	; 6
	251	[1421]	CALL     	26 4 0
	252	[1421]	CALL     	25 0 2
	253	[1421]	SUB      	24 24 25
	254	[1422]	GETGLOBAL	25 -26	; tonumber
	255	[1422]	GETGLOBAL	26 -21	; string
	256	[1422]	GETTABLE 	26 26 -49	; "sub"
	257	[1422]	MOVE     	27 23
	258	[1422]	LOADK    	28 -52	; 7
	259	[1422]	LOADK    	29 -53	; 8
	260	[1422]	CALL     	26 4 0
	261	[1422]	CALL     	25 0 2
	262	[1423]	EQ       	0 25 -11	; - 0
	263	[1423]	JMP      	2	; to 266
	264	[1423]	LOADK    	25 -51	; 6
	265	[1423]	JMP      	1	; to 267
	266	[1423]	SUB      	25 25 -12	; - 1
	267	[1424]	MUL      	26 25 -10	; - 86400
	268	[1424]	SUB      	24 24 26
	269	[1425]	GETGLOBAL	26 -41	; table
	270	[1425]	GETTABLE 	26 26 -42	; "insert"
	271	[1425]	MOVE     	27 4
	272	[1425]	NEWTABLE 	28 2 1
	273	[1426]	MOVE     	29 22
	274	[1427]	GETUPVAL 	30 6	; T
	275	[1427]	GETUPVAL 	31 7	; _
	276	[1427]	LOADK    	32 -43	; "Pages: (%1) Time: %2"
	277	[1427]	CALL     	31 2 2
	278	[1427]	GETGLOBAL	32 -26	; tonumber
	279	[1427]	GETTABLE 	33 17 -44	; 2
	280	[1427]	GETTABLE 	33 33 21
	281	[1427]	CALL     	32 2 2
	282	[1427]	GETUPVAL 	33 9	; util
	283	[1427]	GETTABLE 	33 33 -45	; "secondsToClock"
	284	[1427]	GETGLOBAL	34 -26	; tonumber
	285	[1427]	GETTABLE 	35 17 -46	; 3
	286	[1427]	GETTABLE 	35 35 21
	287	[1427]	CALL     	34 2 2
	288	[1427]	LOADBOOL 	35 0 0
	289	[1427]	CALL     	33 3 0
	290	[1427]	CALL     	30 0 2
	291	[1430]	CLOSURE  	31 1	; 0x7fcdebc1b450
	292	[1430]	MOVE     	0 0
	293	[1430]	MOVE     	0 24
	294	[1430]	MOVE     	0 22
	295	[1430]	MOVE     	0 3
	296	[1430]	SETTABLE 	28 -47 31	; "callback" -
	297	[1431]	SETLIST  	28 2 1	; 1
	298	[1425]	CALL     	26 3 1
	299	[1431]	CLOSE    	23
	300	[1431]	JMP      	68	; to 369
	301	[1433]	GETGLOBAL	23 -1	; os
	302	[1433]	GETTABLE 	23 23 -2	; "date"
	303	[1433]	LOADK    	24 -54	; "%H%M%S"
	304	[1433]	MOVE     	25 9
	305	[1433]	CALL     	23 3 2
	306	[1434]	GETGLOBAL	24 -26	; tonumber
	307	[1434]	GETTABLE 	25 17 -27	; 4
	308	[1434]	GETTABLE 	25 25 21
	309	[1434]	CALL     	24 2 2
	310	[1434]	GETGLOBAL	25 -26	; tonumber
	311	[1434]	GETGLOBAL	26 -21	; string
	312	[1434]	GETTABLE 	26 26 -49	; "sub"
	313	[1434]	MOVE     	27 23
	314	[1434]	LOADK    	28 -12	; 1
	315	[1434]	LOADK    	29 -44	; 2
	316	[1434]	CALL     	26 4 0
	317	[1434]	CALL     	25 0 2
	318	[1434]	MUL      	25 -5 25	; 3600 -
	319	[1434]	SUB      	24 24 25
	320	[1435]	GETGLOBAL	25 -26	; tonumber
	321	[1435]	GETGLOBAL	26 -21	; string
	322	[1435]	GETTABLE 	26 26 -49	; "sub"
	323	[1435]	MOVE     	27 23
	324	[1435]	LOADK    	28 -46	; 3
	325	[1435]	LOADK    	29 -27	; 4
	326	[1435]	CALL     	26 4 0
	327	[1435]	CALL     	25 0 2
	328	[1435]	MUL      	25 -7 25	; 60 -
	329	[1435]	SUB      	24 24 25
	330	[1435]	GETGLOBAL	25 -26	; tonumber
	331	[1435]	GETGLOBAL	26 -21	; string
	332	[1435]	GETTABLE 	26 26 -49	; "sub"
	333	[1435]	MOVE     	27 23
	334	[1435]	LOADK    	28 -50	; 5
	335	[1435]	LOADK    	29 -51	; 6
	336	[1435]	CALL     	26 4 0
	337	[1435]	CALL     	25 0 2
	338	[1435]	SUB      	24 24 25
	339	[1436]	GETGLOBAL	25 -41	; table
	340	[1436]	GETTABLE 	25 25 -42	; "insert"
	341	[1436]	MOVE     	26 4
	342	[1436]	NEWTABLE 	27 2 1
	343	[1437]	MOVE     	28 22
	344	[1438]	GETUPVAL 	29 6	; T
	345	[1438]	GETUPVAL 	30 7	; _
	346	[1438]	LOADK    	31 -43	; "Pages: (%1) Time: %2"
	347	[1438]	CALL     	30 2 2
	348	[1438]	GETGLOBAL	31 -26	; tonumber
	349	[1438]	GETTABLE 	32 17 -44	; 2
	350	[1438]	GETTABLE 	32 32 21
	351	[1438]	CALL     	31 2 2
	352	[1438]	GETUPVAL 	32 9	; util
	353	[1438]	GETTABLE 	32 32 -45	; "secondsToClock"
	354	[1438]	GETGLOBAL	33 -26	; tonumber
	355	[1438]	GETTABLE 	34 17 -46	; 3
	356	[1438]	GETTABLE 	34 34 21
	357	[1438]	CALL     	33 2 2
	358	[1438]	LOADBOOL 	34 0 0
	359	[1438]	CALL     	32 3 0
	360	[1438]	CALL     	29 0 2
	361	[1441]	CLOSURE  	30 2	; 0x7fcdebc1abe0
	362	[1441]	MOVE     	0 0
	363	[1441]	MOVE     	0 24
	364	[1441]	MOVE     	0 22
	365	[1441]	SETTABLE 	27 -47 30	; "callback" -
	366	[1442]	SETLIST  	27 2 1	; 1
	367	[1436]	CALL     	25 3 1
	368	[1442]	CLOSE    	23
	369	[1443]	CLOSE    	22
	370	[1383]	FORLOOP  	18 -301	; to 70
	371	[1445]	RETURN   	4 2
	372	[1446]	RETURN   	0 1

function <./plugins/statistics.koplugin/main.lua:1414,1416> (8 instructions, 32 bytes at 0x7fcdebc1aa20)
0 params, 6 slots, 5 upvalues, 0 locals, 1 constant, 0 functions
	1	[1415]	GETUPVAL 	0 0	; self
	2	[1415]	SELF     	0 0 -1	; "callbackMonthly"
	3	[1415]	GETUPVAL 	2 1	; start_month
	4	[1415]	GETUPVAL 	3 2	; stop_month
	5	[1415]	GETUPVAL 	4 3	; date_text
	6	[1415]	GETUPVAL 	5 4	; book_mode
	7	[1415]	CALL     	0 6 1
	8	[1416]	RETURN   	0 1

function <./plugins/statistics.koplugin/main.lua:1428,1430> (9 instructions, 36 bytes at 0x7fcdebc1b450)
0 params, 6 slots, 4 upvalues, 0 locals, 2 constants, 0 functions
	1	[1429]	GETUPVAL 	0 0	; self
	2	[1429]	SELF     	0 0 -1	; "callbackWeekly"
	3	[1429]	GETUPVAL 	2 1	; begin_week
	4	[1429]	GETUPVAL 	3 1	; begin_week
	5	[1429]	ADD      	3 3 -2	; - 604800
	6	[1429]	GETUPVAL 	4 2	; date_text
	7	[1429]	GETUPVAL 	5 3	; book_mode
	8	[1429]	CALL     	0 6 1
	9	[1430]	RETURN   	0 1

function <./plugins/statistics.koplugin/main.lua:1439,1441> (8 instructions, 32 bytes at 0x7fcdebc1abe0)
0 params, 5 slots, 3 upvalues, 0 locals, 2 constants, 0 functions
	1	[1440]	GETUPVAL 	0 0	; self
	2	[1440]	SELF     	0 0 -1	; "callbackDaily"
	3	[1440]	GETUPVAL 	2 1	; begin_day
	4	[1440]	GETUPVAL 	3 1	; begin_day
	5	[1440]	ADD      	3 3 -2	; - 86400
	6	[1440]	GETUPVAL 	4 2	; date_text
	7	[1440]	CALL     	0 5 1
	8	[1441]	RETURN   	0 1

function <./plugins/statistics.koplugin/main.lua:1448,1495> (96 instructions, 384 bytes at 0x7fcdebc1b730)
3 params, 22 slots, 7 upvalues, 12 locals, 32 constants, 1 function
	1	[1449]	NEWTABLE 	3 0 0
	2	[1465]	LOADK    	4 -1	; "        SELECT dates,\n               count(*)             AS pages,\n               sum(sum_period)      AS periods,\n               start_time\n        FROM   (\n                    SELECT strftime('%%Y-%%m-%%d', start_time, 'unixepoch', 'localtime') AS dates,\n                           sum(period)                                                   AS sum_period,\n                           start_time\n                    FROM   page_stat\n                    WHERE  start_time >= '%s' AND start_time < '%s'\n                    GROUP  BY id_book, page, dates\n               )\n        GROUP  BY dates\n        ORDER  BY dates DESC\n    "
	3	[1466]	GETUPVAL 	5 0	; SQ3
	4	[1466]	GETTABLE 	5 5 -2	; "open"
	5	[1466]	GETUPVAL 	6 1	; db_location
	6	[1466]	CALL     	5 2 2
	7	[1467]	SELF     	6 5 -3	; "exec"
	8	[1467]	GETGLOBAL	8 -4	; string
	9	[1467]	GETTABLE 	8 8 -5	; "format"
	10	[1467]	MOVE     	9 4
	11	[1467]	MOVE     	10 1
	12	[1467]	MOVE     	11 2
	13	[1467]	CALL     	8 4 0
	14	[1467]	CALL     	6 0 2
	15	[1468]	SELF     	7 5 -6	; "close"
	16	[1468]	CALL     	7 2 1
	17	[1469]	EQ       	0 6 -7	; - nil
	18	[1469]	JMP      	2	; to 21
	19	[1470]	NEWTABLE 	7 0 0
	20	[1470]	RETURN   	7 2
	21	[1472]	LOADK    	7 -8	; 1
	22	[1472]	GETTABLE 	8 6 -9	; "dates"
	23	[1472]	LEN      	8 8
	24	[1472]	LOADK    	9 -8	; 1
	25	[1472]	FORPREP  	7 68	; to 94
	26	[1473]	GETGLOBAL	11 -10	; os
	27	[1473]	GETTABLE 	11 11 -11	; "time"
	28	[1473]	NEWTABLE 	12 0 6
	29	[1473]	GETGLOBAL	13 -4	; string
	30	[1473]	GETTABLE 	13 13 -13	; "sub"
	31	[1473]	GETTABLE 	14 6 -8	; 1
	32	[1473]	GETTABLE 	14 14 10
	33	[1473]	LOADK    	15 -8	; 1
	34	[1473]	LOADK    	16 -14	; 4
	35	[1473]	CALL     	13 4 2
	36	[1473]	SETTABLE 	12 -12 13	; "year" -
	37	[1473]	GETGLOBAL	13 -4	; string
	38	[1473]	GETTABLE 	13 13 -13	; "sub"
	39	[1473]	GETTABLE 	14 6 -8	; 1
	40	[1473]	GETTABLE 	14 14 10
	41	[1473]	LOADK    	15 -16	; 6
	42	[1473]	LOADK    	16 -17	; 7
	43	[1473]	CALL     	13 4 2
	44	[1473]	SETTABLE 	12 -15 13	; "month" -
	45	[1474]	GETGLOBAL	13 -4	; string
	46	[1474]	GETTABLE 	13 13 -13	; "sub"
	47	[1474]	GETTABLE 	14 6 -8	; 1
	48	[1474]	GETTABLE 	14 14 10
	49	[1474]	LOADK    	15 -19	; 9
	50	[1474]	LOADK    	16 -20	; 10
	51	[1474]	CALL     	13 4 2
	52	[1474]	SETTABLE 	12 -18 13	; "day" -
	53	[1474]	SETTABLE 	12 -21 -22	; "hour" 0
	54	[1474]	SETTABLE 	12 -23 -22	; "min" 0
	55	[1474]	SETTABLE 	12 -24 -22	; "sec" 0
	56	[1473]	CALL     	11 2 2
	57	[1475]	GETGLOBAL	12 -25	; table
	58	[1475]	GETTABLE 	12 12 -26	; "insert"
	59	[1475]	MOVE     	13 3
	60	[1475]	NEWTABLE 	14 2 1
	61	[1476]	GETTABLE 	15 6 -8	; 1
	62	[1476]	GETTABLE 	15 15 10
	63	[1477]	GETUPVAL 	16 2	; T
	64	[1477]	GETUPVAL 	17 3	; _
	65	[1477]	LOADK    	18 -27	; "Pages: (%1) Time: %2"
	66	[1477]	CALL     	17 2 2
	67	[1477]	GETGLOBAL	18 -28	; tonumber
	68	[1477]	GETTABLE 	19 6 -29	; 2
	69	[1477]	GETTABLE 	19 19 10
	70	[1477]	CALL     	18 2 2
	71	[1477]	GETUPVAL 	19 4	; util
	72	[1477]	GETTABLE 	19 19 -30	; "secondsToClock"
	73	[1477]	GETGLOBAL	20 -28	; tonumber
	74	[1477]	GETTABLE 	21 6 -31	; 3
	75	[1477]	GETTABLE 	21 21 10
	76	[1477]	CALL     	20 2 2
	77	[1477]	LOADBOOL 	21 0 0
	78	[1477]	CALL     	19 3 0
	79	[1477]	CALL     	16 0 2
	80	[1491]	CLOSURE  	17 0	; 0x7fcdebc1b950
	81	[1491]	MOVE     	0 0
	82	[1491]	GETUPVAL 	0 5	; UIManager
	83	[1491]	GETUPVAL 	0 6	; KeyValuePage
	84	[1491]	GETUPVAL 	0 2	; T
	85	[1491]	GETUPVAL 	0 3	; _
	86	[1491]	MOVE     	0 6
	87	[1491]	MOVE     	0 10
	88	[1491]	MOVE     	0 11
	89	[1491]	SETTABLE 	14 -32 17	; "callback" -
	90	[1492]	SETLIST  	14 2 1	; 1
	91	[1475]	CALL     	12 3 1
	92	[1492]	CLOSE    	11
	93	[1492]	CLOSE    	10
	94	[1472]	FORLOOP  	7 -69	; to 26
	95	[1494]	RETURN   	3 2
	96	[1495]	RETURN   	0 1

function <./plugins/statistics.koplugin/main.lua:1478,1491> (41 instructions, 164 bytes at 0x7fcdebc1b950)
0 params, 9 slots, 8 upvalues, 1 local, 13 constants, 1 function
	1	[1479]	GETUPVAL 	0 0	; self
	2	[1479]	GETTABLE 	0 0 -1	; "kv"
	3	[1480]	GETUPVAL 	1 1	; UIManager
	4	[1480]	SELF     	1 1 -2	; "close"
	5	[1480]	MOVE     	3 0
	6	[1480]	CALL     	1 3 1
	7	[1481]	GETUPVAL 	1 0	; self
	8	[1481]	GETUPVAL 	2 2	; KeyValuePage
	9	[1481]	SELF     	2 2 -3	; "new"
	10	[1481]	NEWTABLE 	4 0 4
	11	[1482]	GETUPVAL 	5 3	; T
	12	[1482]	GETUPVAL 	6 4	; _
	13	[1482]	LOADK    	7 -5	; "Books in %1"
	14	[1482]	CALL     	6 2 2
	15	[1482]	GETUPVAL 	7 5	; result_book
	16	[1482]	GETTABLE 	7 7 -6	; 1
	17	[1482]	GETUPVAL 	8 6	; i
	18	[1482]	GETTABLE 	7 7 8
	19	[1482]	CALL     	5 3 2
	20	[1482]	SETTABLE 	4 -4 5	; "title" -
	21	[1483]	SETTABLE 	4 -7 -8	; "value_overflow_align" "right"
	22	[1484]	GETUPVAL 	5 0	; self
	23	[1484]	SELF     	5 5 -10	; "getBooksFromPeriod"
	24	[1484]	GETUPVAL 	7 7	; time_begin
	25	[1484]	GETUPVAL 	8 7	; time_begin
	26	[1484]	ADD      	8 8 -11	; - 86400
	27	[1484]	CALL     	5 4 2
	28	[1484]	SETTABLE 	4 -9 5	; "kv_pairs" -
	29	[1488]	CLOSURE  	5 0	; 0x7fcdebc1bfa0
	30	[1488]	GETUPVAL 	0 1	; UIManager
	31	[1488]	MOVE     	0 0
	32	[1488]	GETUPVAL 	0 0	; self
	33	[1488]	SETTABLE 	4 -12 5	; "callback_return" -
	34	[1481]	CALL     	2 3 2
	35	[1489]	SETTABLE 	1 -1 2	; "kv" -
	36	[1490]	GETUPVAL 	1 1	; UIManager
	37	[1490]	SELF     	1 1 -13	; "show"
	38	[1490]	GETUPVAL 	3 0	; self
	39	[1490]	GETTABLE 	3 3 -1	; "kv"
	40	[1490]	CALL     	1 3 1
	41	[1491]	RETURN   	0 1

function <./plugins/statistics.koplugin/main.lua:1485,1488> (8 instructions, 32 bytes at 0x7fcdebc1bfa0)
0 params, 3 slots, 3 upvalues, 0 locals, 2 constants, 0 functions
	1	[1486]	GETUPVAL 	0 0	; UIManager
	2	[1486]	SELF     	0 0 -1	; "show"
	3	[1486]	GETUPVAL 	2 1	; kv
	4	[1486]	CALL     	0 3 1
	5	[1487]	GETUPVAL 	0 2	; self
	6	[1487]	GETUPVAL 	1 1	; kv
	7	[1487]	SETTABLE 	0 -2 1	; "kv" -
	8	[1488]	RETURN   	0 1

function <./plugins/statistics.koplugin/main.lua:1497,1536> (62 instructions, 248 bytes at 0x7fcdebc1c770)
3 params, 20 slots, 7 upvalues, 11 locals, 17 constants, 1 function
	1	[1498]	NEWTABLE 	3 0 0
	2	[1508]	LOADK    	4 -1	; "        SELECT  book_tbl.title AS title,\n                sum(page_stat_tbl.period),\n                count(distinct page_stat_tbl.page),\n                book_tbl.id\n        FROM    page_stat AS page_stat_tbl, book AS book_tbl\n        WHERE   page_stat_tbl.id_book=book_tbl.id AND page_stat_tbl.start_time > '%s' AND page_stat_tbl.start_time <= '%s'\n        GROUP   BY book_tbl.id\n        ORDER   BY book_tbl.last_open DESC\n    "
	3	[1509]	GETUPVAL 	5 0	; SQ3
	4	[1509]	GETTABLE 	5 5 -2	; "open"
	5	[1509]	GETUPVAL 	6 1	; db_location
	6	[1509]	CALL     	5 2 2
	7	[1510]	SELF     	6 5 -3	; "exec"
	8	[1510]	GETGLOBAL	8 -4	; string
	9	[1510]	GETTABLE 	8 8 -5	; "format"
	10	[1510]	MOVE     	9 4
	11	[1510]	MOVE     	10 1
	12	[1510]	MOVE     	11 2
	13	[1510]	CALL     	8 4 0
	14	[1510]	CALL     	6 0 2
	15	[1511]	SELF     	7 5 -6	; "close"
	16	[1511]	CALL     	7 2 1
	17	[1512]	EQ       	0 6 -7	; - nil
	18	[1512]	JMP      	2	; to 21
	19	[1513]	NEWTABLE 	7 0 0
	20	[1513]	RETURN   	7 2
	21	[1515]	LOADK    	7 -8	; 1
	22	[1515]	GETTABLE 	8 6 -9	; "title"
	23	[1515]	LEN      	8 8
	24	[1515]	LOADK    	9 -8	; 1
	25	[1515]	FORPREP  	7 34	; to 60
	26	[1516]	GETGLOBAL	11 -10	; table
	27	[1516]	GETTABLE 	11 11 -11	; "insert"
	28	[1516]	MOVE     	12 3
	29	[1516]	NEWTABLE 	13 2 1
	30	[1517]	GETTABLE 	14 6 -8	; 1
	31	[1517]	GETTABLE 	14 14 10
	32	[1518]	GETUPVAL 	15 2	; T
	33	[1518]	GETUPVAL 	16 3	; _
	34	[1518]	LOADK    	17 -12	; "%1 (%2)"
	35	[1518]	CALL     	16 2 2
	36	[1518]	GETUPVAL 	17 4	; util
	37	[1518]	GETTABLE 	17 17 -13	; "secondsToClock"
	38	[1518]	GETGLOBAL	18 -14	; tonumber
	39	[1518]	GETTABLE 	19 6 -15	; 2
	40	[1518]	GETTABLE 	19 19 10
	41	[1518]	CALL     	18 2 2
	42	[1518]	LOADBOOL 	19 0 0
	43	[1518]	CALL     	17 3 2
	44	[1518]	GETGLOBAL	18 -14	; tonumber
	45	[1518]	GETTABLE 	19 6 -16	; 3
	46	[1518]	GETTABLE 	19 19 10
	47	[1518]	CALL     	18 2 0
	48	[1518]	CALL     	15 0 2
	49	[1532]	CLOSURE  	16 0	; 0x7fcdebc1c020
	50	[1532]	MOVE     	0 0
	51	[1532]	GETUPVAL 	0 5	; UIManager
	52	[1532]	GETUPVAL 	0 6	; KeyValuePage
	53	[1532]	GETUPVAL 	0 3	; _
	54	[1532]	MOVE     	0 6
	55	[1532]	MOVE     	0 10
	56	[1532]	SETTABLE 	13 -17 16	; "callback" -
	57	[1533]	SETLIST  	13 2 1	; 1
	58	[1516]	CALL     	11 3 1
	59	[1533]	CLOSE    	10
	60	[1515]	FORLOOP  	7 -35	; to 26
	61	[1535]	RETURN   	3 2
	62	[1536]	RETURN   	0 1

function <./plugins/statistics.koplugin/main.lua:1519,1532> (39 instructions, 156 bytes at 0x7fcdebc1c020)
0 params, 10 slots, 6 upvalues, 1 local, 13 constants, 1 function
	1	[1520]	GETUPVAL 	0 0	; self
	2	[1520]	GETTABLE 	0 0 -1	; "kv"
	3	[1521]	GETUPVAL 	1 1	; UIManager
	4	[1521]	SELF     	1 1 -2	; "close"
	5	[1521]	GETUPVAL 	3 0	; self
	6	[1521]	GETTABLE 	3 3 -1	; "kv"
	7	[1521]	CALL     	1 3 1
	8	[1522]	GETUPVAL 	1 0	; self
	9	[1522]	GETUPVAL 	2 2	; KeyValuePage
	10	[1522]	SELF     	2 2 -3	; "new"
	11	[1522]	NEWTABLE 	4 0 4
	12	[1523]	GETUPVAL 	5 3	; _
	13	[1523]	LOADK    	6 -5	; "Read in days"
	14	[1523]	CALL     	5 2 2
	15	[1523]	SETTABLE 	4 -4 5	; "title" -
	16	[1524]	SETTABLE 	4 -6 -7	; "value_overflow_align" "right"
	17	[1525]	GETUPVAL 	5 0	; self
	18	[1525]	SELF     	5 5 -9	; "getDatesForBook"
	19	[1525]	GETGLOBAL	7 -10	; tonumber
	20	[1525]	GETUPVAL 	8 4	; result_book
	21	[1525]	GETTABLE 	8 8 -11	; 4
	22	[1525]	GETUPVAL 	9 5	; i
	23	[1525]	GETTABLE 	8 8 9
	24	[1525]	CALL     	7 2 0
	25	[1525]	CALL     	5 0 2
	26	[1525]	SETTABLE 	4 -8 5	; "kv_pairs" -
	27	[1529]	CLOSURE  	5 0	; 0x7fcdebc1d4a0
	28	[1529]	GETUPVAL 	0 1	; UIManager
	29	[1529]	MOVE     	0 0
	30	[1529]	GETUPVAL 	0 0	; self
	31	[1529]	SETTABLE 	4 -12 5	; "callback_return" -
	32	[1522]	CALL     	2 3 2
	33	[1530]	SETTABLE 	1 -1 2	; "kv" -
	34	[1531]	GETUPVAL 	1 1	; UIManager
	35	[1531]	SELF     	1 1 -13	; "show"
	36	[1531]	GETUPVAL 	3 0	; self
	37	[1531]	GETTABLE 	3 3 -1	; "kv"
	38	[1531]	CALL     	1 3 1
	39	[1532]	RETURN   	0 1

function <./plugins/statistics.koplugin/main.lua:1526,1529> (8 instructions, 32 bytes at 0x7fcdebc1d4a0)
0 params, 3 slots, 3 upvalues, 0 locals, 2 constants, 0 functions
	1	[1527]	GETUPVAL 	0 0	; UIManager
	2	[1527]	SELF     	0 0 -1	; "show"
	3	[1527]	GETUPVAL 	2 1	; kv
	4	[1527]	CALL     	0 3 1
	5	[1528]	GETUPVAL 	0 2	; self
	6	[1528]	GETUPVAL 	1 1	; kv
	7	[1528]	SETTABLE 	0 -2 1	; "kv" -
	8	[1529]	RETURN   	0 1

function <./plugins/statistics.koplugin/main.lua:1538,1579> (72 instructions, 288 bytes at 0x7fcdebc1cfe0)
2 params, 24 slots, 2 upvalues, 18 locals, 24 constants, 0 functions
	1	[1539]	NEWTABLE 	2 0 0
	2	[1540]	LOADNIL  	3 5
	3	[1541]	GETGLOBAL	6 -1	; os
	4	[1541]	GETTABLE 	6 6 -2	; "date"
	5	[1541]	LOADK    	7 -3	; "*t"
	6	[1541]	CALL     	6 2 2
	7	[1542]	GETTABLE 	7 6 -4	; "hour"
	8	[1542]	MUL      	7 7 -5	; - 3600
	9	[1542]	GETTABLE 	8 6 -6	; "min"
	10	[1542]	MUL      	8 8 -7	; - 60
	11	[1542]	ADD      	7 7 8
	12	[1542]	GETTABLE 	8 6 -8	; "sec"
	13	[1542]	ADD      	7 7 8
	14	[1543]	GETGLOBAL	8 -1	; os
	15	[1543]	GETTABLE 	8 8 -9	; "time"
	16	[1543]	CALL     	8 1 2
	17	[1544]	LOADK    	9 -10	; 86400
	18	[1545]	SUB      	10 1 -11	; - 1
	19	[1545]	MUL      	10 10 9
	20	[1545]	SUB      	10 8 10
	21	[1545]	SUB      	10 10 7
	22	[1546]	GETUPVAL 	11 0	; SQ3
	23	[1546]	GETTABLE 	11 11 -12	; "open"
	24	[1546]	GETUPVAL 	12 1	; db_location
	25	[1546]	CALL     	11 2 2
	26	[1562]	LOADK    	12 -13	; "        SELECT dates,\n               count(*)             AS pages,\n               sum(sum_period)      AS periods,\n               start_time\n        FROM   (\n                    SELECT strftime('%%Y-%%m-%%d', start_time, 'unixepoch', 'localtime') AS dates,\n                           sum(period)                                                   AS sum_period,\n                           start_time\n                    FROM   page_stat\n                    WHERE  start_time >= '%s'\n                    GROUP  BY id_book, page, dates\n               )\n        GROUP  BY dates\n        ORDER  BY dates DESC\n    "
	27	[1563]	SELF     	13 11 -14	; "exec"
	28	[1563]	GETGLOBAL	15 -15	; string
	29	[1563]	GETTABLE 	15 15 -16	; "format"
	30	[1563]	MOVE     	16 12
	31	[1563]	MOVE     	17 10
	32	[1563]	CALL     	15 3 0
	33	[1563]	CALL     	13 0 2
	34	[1564]	TEST     	13 0 1
	35	[1564]	JMP      	1	; to 37
	36	[1564]	RETURN   	0 1
	37	[1565]	LOADK    	14 -11	; 1
	38	[1565]	MOVE     	15 1
	39	[1565]	LOADK    	16 -11	; 1
	40	[1565]	FORPREP  	14 27	; to 68
	41	[1566]	GETGLOBAL	18 -17	; tonumber
	42	[1566]	GETTABLE 	19 13 -18	; 2
	43	[1566]	GETTABLE 	19 19 17
	44	[1566]	CALL     	18 2 2
	45	[1566]	MOVE     	3 18
	46	[1567]	GETGLOBAL	18 -17	; tonumber
	47	[1567]	GETTABLE 	19 13 -19	; 3
	48	[1567]	GETTABLE 	19 19 17
	49	[1567]	CALL     	18 2 2
	50	[1567]	MOVE     	4 18
	51	[1568]	GETTABLE 	18 13 -11	; 1
	52	[1568]	GETTABLE 	5 18 17
	53	[1569]	EQ       	0 3 -20	; - nil
	54	[1569]	JMP      	1	; to 56
	55	[1569]	LOADK    	3 -21	; 0
	56	[1570]	EQ       	0 4 -20	; - nil
	57	[1570]	JMP      	1	; to 59
	58	[1570]	LOADK    	4 -21	; 0
	59	[1571]	GETGLOBAL	18 -22	; table
	60	[1571]	GETTABLE 	18 18 -23	; "insert"
	61	[1571]	MOVE     	19 2
	62	[1571]	NEWTABLE 	20 3 0
	63	[1572]	MOVE     	21 3
	64	[1573]	MOVE     	22 4
	65	[1575]	MOVE     	23 5
	66	[1575]	SETLIST  	20 3 1	; 1
	67	[1571]	CALL     	18 3 1
	68	[1565]	FORLOOP  	14 -28	; to 41
	69	[1577]	SELF     	14 11 -24	; "close"
	70	[1577]	CALL     	14 2 1
	71	[1578]	RETURN   	2 2
	72	[1579]	RETURN   	0 1

function <./plugins/statistics.koplugin/main.lua:1581,1605> (52 instructions, 208 bytes at 0x7fcdebc1cf60)
2 params, 20 slots, 5 upvalues, 10 locals, 16 constants, 0 functions
	1	[1582]	NEWTABLE 	2 0 0
	2	[1583]	GETUPVAL 	3 0	; SQ3
	3	[1583]	GETTABLE 	3 3 -1	; "open"
	4	[1583]	GETUPVAL 	4 1	; db_location
	5	[1583]	CALL     	3 2 2
	6	[1592]	LOADK    	4 -2	; "        SELECT date(start_time, 'unixepoch', 'localtime') AS dates,\n               count(DISTINCT page)                       AS pages,\n               sum(period)                                AS periods\n        FROM   page_stat\n        WHERE  id_book = '%s'\n        GROUP  BY Date(start_time, 'unixepoch', 'localtime')\n        ORDER  BY dates DESC\n    "
	7	[1593]	SELF     	5 3 -3	; "exec"
	8	[1593]	GETGLOBAL	7 -4	; string
	9	[1593]	GETTABLE 	7 7 -5	; "format"
	10	[1593]	MOVE     	8 4
	11	[1593]	MOVE     	9 1
	12	[1593]	CALL     	7 3 0
	13	[1593]	CALL     	5 0 2
	14	[1594]	SELF     	6 3 -6	; "close"
	15	[1594]	CALL     	6 2 1
	16	[1595]	EQ       	0 5 -7	; - nil
	17	[1595]	JMP      	2	; to 20
	18	[1596]	NEWTABLE 	6 0 0
	19	[1596]	RETURN   	6 2
	20	[1598]	LOADK    	6 -8	; 1
	21	[1598]	GETTABLE 	7 5 -9	; "dates"
	22	[1598]	LEN      	7 7
	23	[1598]	LOADK    	8 -8	; 1
	24	[1598]	FORPREP  	6 25	; to 50
	25	[1599]	GETGLOBAL	10 -10	; table
	26	[1599]	GETTABLE 	10 10 -11	; "insert"
	27	[1599]	MOVE     	11 2
	28	[1599]	NEWTABLE 	12 1 0
	29	[1600]	GETTABLE 	13 5 -8	; 1
	30	[1600]	GETTABLE 	13 13 9
	31	[1601]	GETUPVAL 	14 2	; T
	32	[1601]	GETUPVAL 	15 3	; _
	33	[1601]	LOADK    	16 -12	; "Pages: (%1) Time: %2"
	34	[1601]	CALL     	15 2 2
	35	[1601]	GETGLOBAL	16 -13	; tonumber
	36	[1601]	GETTABLE 	17 5 -14	; 2
	37	[1601]	GETTABLE 	17 17 9
	38	[1601]	CALL     	16 2 2
	39	[1601]	GETUPVAL 	17 4	; util
	40	[1601]	GETTABLE 	17 17 -15	; "secondsToClock"
	41	[1601]	GETGLOBAL	18 -13	; tonumber
	42	[1601]	GETTABLE 	19 5 -16	; 3
	43	[1601]	GETTABLE 	19 19 9
	44	[1601]	CALL     	18 2 2
	45	[1601]	LOADBOOL 	19 0 0
	46	[1601]	CALL     	17 3 0
	47	[1601]	CALL     	14 0 0
	48	[1602]	SETLIST  	12 0 1	; 1
	49	[1599]	CALL     	10 3 1
	50	[1598]	FORLOOP  	6 -26	; to 25
	51	[1604]	RETURN   	2 2
	52	[1605]	RETURN   	0 1

function <./plugins/statistics.koplugin/main.lua:1607,1672> (91 instructions, 364 bytes at 0x7fcdebc1e7a0)
1 param, 21 slots, 7 upvalues, 14 locals, 22 constants, 1 function
	1	[1608]	SELF     	1 0 -1	; "insertDB"
	2	[1608]	GETTABLE 	3 0 -2	; "id_curr_book"
	3	[1608]	CALL     	1 3 1
	4	[1609]	GETUPVAL 	1 0	; SQ3
	5	[1609]	GETTABLE 	1 1 -3	; "open"
	6	[1609]	GETUPVAL 	2 1	; db_location
	7	[1609]	CALL     	1 2 2
	8	[1613]	LOADK    	2 -4	; "        SELECT sum(period)\n        FROM   page_stat\n    "
	9	[1614]	SELF     	3 1 -5	; "rowexec"
	10	[1614]	MOVE     	5 2
	11	[1614]	CALL     	3 3 2
	12	[1615]	EQ       	0 3 -6	; - nil
	13	[1615]	JMP      	1	; to 15
	14	[1616]	LOADK    	3 -7	; 0
	15	[1618]	NEWTABLE 	4 0 0
	16	[1623]	LOADK    	2 -8	; "        SELECT id\n        FROM   book\n        ORDER  BY last_open DESC\n    "
	17	[1624]	SELF     	5 1 -9	; "exec"
	18	[1624]	MOVE     	7 2
	19	[1624]	CALL     	5 3 2
	20	[1625]	LOADNIL  	6 6
	21	[1626]	EQ       	1 5 -6	; - nil
	22	[1626]	JMP      	3	; to 26
	23	[1627]	GETTABLE 	7 5 -10	; "id"
	24	[1627]	LEN      	6 7
	25	[1627]	JMP      	1	; to 27
	26	[1629]	LOADK    	6 -7	; 0
	27	[1632]	LOADNIL  	7 7
	28	[1633]	LOADK    	8 -11	; 1
	29	[1633]	MOVE     	9 6
	30	[1633]	LOADK    	10 -11	; 1
	31	[1633]	FORPREP  	8 44	; to 76
	32	[1634]	GETGLOBAL	12 -12	; tonumber
	33	[1634]	GETTABLE 	13 5 -11	; 1
	34	[1634]	GETTABLE 	13 13 11
	35	[1634]	CALL     	12 2 2
	36	[1639]	LOADK    	2 -13	; "            SELECT title\n            FROM   book\n            WHERE  id = '%s'\n        "
	37	[1640]	SELF     	13 1 -5	; "rowexec"
	38	[1640]	GETGLOBAL	15 -14	; string
	39	[1640]	GETTABLE 	15 15 -15	; "format"
	40	[1640]	MOVE     	16 2
	41	[1640]	MOVE     	17 12
	42	[1640]	CALL     	15 3 0
	43	[1640]	CALL     	13 0 2
	44	[1645]	LOADK    	2 -16	; "            SELECT sum(period)\n            FROM   page_stat\n            WHERE  id_book = '%s'\n        "
	45	[1646]	SELF     	14 1 -5	; "rowexec"
	46	[1646]	GETGLOBAL	16 -14	; string
	47	[1646]	GETTABLE 	16 16 -15	; "format"
	48	[1646]	MOVE     	17 2
	49	[1646]	MOVE     	18 12
	50	[1646]	CALL     	16 3 0
	51	[1646]	CALL     	14 0 2
	52	[1646]	MOVE     	7 14
	53	[1647]	EQ       	0 7 -6	; - nil
	54	[1647]	JMP      	1	; to 56
	55	[1648]	LOADK    	7 -7	; 0
	56	[1650]	GETGLOBAL	14 -17	; table
	57	[1650]	GETTABLE 	14 14 -18	; "insert"
	58	[1650]	MOVE     	15 4
	59	[1650]	NEWTABLE 	16 2 1
	60	[1651]	MOVE     	17 13
	61	[1652]	GETUPVAL 	18 2	; util
	62	[1652]	GETTABLE 	18 18 -19	; "secondsToClock"
	63	[1652]	MOVE     	19 7
	64	[1652]	LOADBOOL 	20 0 0
	65	[1652]	CALL     	18 3 2
	66	[1667]	CLOSURE  	19 0	; 0x7fcdebc1ec90
	67	[1667]	MOVE     	0 0
	68	[1667]	GETUPVAL 	0 3	; UIManager
	69	[1667]	GETUPVAL 	0 4	; KeyValuePage
	70	[1667]	MOVE     	0 13
	71	[1667]	MOVE     	0 12
	72	[1667]	SETTABLE 	16 -20 19	; "callback" -
	73	[1668]	SETLIST  	16 2 1	; 1
	74	[1650]	CALL     	14 3 1
	75	[1668]	CLOSE    	12
	76	[1633]	FORLOOP  	8 -45	; to 32
	77	[1670]	SELF     	8 1 -21	; "close"
	78	[1670]	CALL     	8 2 1
	79	[1671]	GETUPVAL 	8 5	; T
	80	[1671]	GETUPVAL 	9 6	; _
	81	[1671]	LOADK    	10 -22	; "Total hours read %1"
	82	[1671]	CALL     	9 2 2
	83	[1671]	GETUPVAL 	10 2	; util
	84	[1671]	GETTABLE 	10 10 -19	; "secondsToClock"
	85	[1671]	MOVE     	11 3
	86	[1671]	LOADBOOL 	12 0 0
	87	[1671]	CALL     	10 3 0
	88	[1671]	CALL     	8 0 2
	89	[1671]	MOVE     	9 4
	90	[1671]	RETURN   	8 3
	91	[1672]	RETURN   	0 1

function <./plugins/statistics.koplugin/main.lua:1653,1667> (32 instructions, 128 bytes at 0x7fcdebc1ec90)
0 params, 8 slots, 5 upvalues, 1 local, 10 constants, 1 function
	1	[1654]	GETUPVAL 	0 0	; self
	2	[1654]	GETTABLE 	0 0 -1	; "kv"
	3	[1655]	GETUPVAL 	1 1	; UIManager
	4	[1655]	SELF     	1 1 -2	; "close"
	5	[1655]	GETUPVAL 	3 0	; self
	6	[1655]	GETTABLE 	3 3 -1	; "kv"
	7	[1655]	CALL     	1 3 1
	8	[1657]	GETUPVAL 	1 0	; self
	9	[1657]	GETUPVAL 	2 2	; KeyValuePage
	10	[1657]	SELF     	2 2 -3	; "new"
	11	[1657]	NEWTABLE 	4 0 4
	12	[1658]	GETUPVAL 	5 3	; book_title
	13	[1658]	SETTABLE 	4 -4 5	; "title" -
	14	[1659]	SETTABLE 	4 -5 -6	; "value_overflow_align" "right"
	15	[1660]	GETUPVAL 	5 0	; self
	16	[1660]	SELF     	5 5 -8	; "getBookStat"
	17	[1660]	GETUPVAL 	7 4	; id_book
	18	[1660]	CALL     	5 3 2
	19	[1660]	SETTABLE 	4 -7 5	; "kv_pairs" -
	20	[1664]	CLOSURE  	5 0	; 0x7fcdebc1f040
	21	[1664]	GETUPVAL 	0 1	; UIManager
	22	[1664]	MOVE     	0 0
	23	[1664]	GETUPVAL 	0 0	; self
	24	[1664]	SETTABLE 	4 -9 5	; "callback_return" -
	25	[1657]	CALL     	2 3 2
	26	[1665]	SETTABLE 	1 -1 2	; "kv" -
	27	[1666]	GETUPVAL 	1 1	; UIManager
	28	[1666]	SELF     	1 1 -10	; "show"
	29	[1666]	GETUPVAL 	3 0	; self
	30	[1666]	GETTABLE 	3 3 -1	; "kv"
	31	[1666]	CALL     	1 3 1
	32	[1667]	RETURN   	0 1

function <./plugins/statistics.koplugin/main.lua:1661,1664> (8 instructions, 32 bytes at 0x7fcdebc1f040)
0 params, 3 slots, 3 upvalues, 0 locals, 2 constants, 0 functions
	1	[1662]	GETUPVAL 	0 0	; UIManager
	2	[1662]	SELF     	0 0 -1	; "show"
	3	[1662]	GETUPVAL 	2 1	; kv
	4	[1662]	CALL     	0 3 1
	5	[1663]	GETUPVAL 	0 2	; self
	6	[1663]	GETUPVAL 	1 1	; kv
	7	[1663]	SETTABLE 	0 -2 1	; "kv" -
	8	[1664]	RETURN   	0 1

function <./plugins/statistics.koplugin/main.lua:1674,1698> (50 instructions, 200 bytes at 0x7fcdebc1f820)
1 param, 13 slots, 3 upvalues, 9 locals, 16 constants, 2 functions
	1	[1675]	NEWTABLE 	1 0 0
	2	[1676]	GETGLOBAL	2 -1	; table
	3	[1676]	GETTABLE 	2 2 -2	; "insert"
	4	[1676]	MOVE     	3 1
	5	[1676]	NEWTABLE 	4 0 4
	6	[1677]	GETUPVAL 	5 0	; _
	7	[1677]	LOADK    	6 -4	; "Reset statistics per book"
	8	[1677]	CALL     	5 2 2
	9	[1677]	SETTABLE 	4 -3 5	; "text" -
	10	[1678]	SETTABLE 	4 -5 -6	; "keep_menu_open" true
	11	[1681]	CLOSURE  	5 0	; 0x7fcdebc1fd80
	12	[1681]	MOVE     	0 0
	13	[1681]	SETTABLE 	4 -7 5	; "callback" -
	14	[1682]	SETTABLE 	4 -8 -6	; "separator" true
	15	[1676]	CALL     	2 3 1
	16	[1684]	NEWTABLE 	2 5 0
	17	[1684]	LOADK    	3 -9	; 1
	18	[1684]	LOADK    	4 -10	; 5
	19	[1684]	LOADK    	5 -11	; 15
	20	[1684]	LOADK    	6 -12	; 30
	21	[1684]	LOADK    	7 -13	; 60
	22	[1684]	SETLIST  	2 5 1	; 1
	23	[1685]	GETGLOBAL	3 -14	; ipairs
	24	[1685]	MOVE     	4 2
	25	[1685]	CALL     	3 2 4
	26	[1685]	JMP      	20	; to 47
	27	[1686]	GETUPVAL 	8 1	; T
	28	[1686]	GETUPVAL 	9 2	; N_
	29	[1686]	LOADK    	10 -15	; "Reset stats for books read for < 1 m"
	30	[1687]	LOADK    	11 -16	; "Reset stats for books read for < %1 m"
	31	[1688]	MOVE     	12 7
	32	[1686]	CALL     	9 4 2
	33	[1688]	MOVE     	10 7
	34	[1686]	CALL     	8 3 2
	35	[1689]	GETGLOBAL	9 -1	; table
	36	[1689]	GETTABLE 	9 9 -2	; "insert"
	37	[1689]	MOVE     	10 1
	38	[1689]	NEWTABLE 	11 0 3
	39	[1690]	SETTABLE 	11 -3 8	; "text" -
	40	[1691]	SETTABLE 	11 -5 -6	; "keep_menu_open" true
	41	[1694]	CLOSURE  	12 1	; 0x7fcdebc202e0
	42	[1694]	MOVE     	0 0
	43	[1694]	MOVE     	0 7
	44	[1694]	SETTABLE 	11 -7 12	; "callback" -
	45	[1689]	CALL     	9 3 1
	46	[1695]	CLOSE    	6
	47	[1685]	TFORLOOP 	3 2
	48	[1695]	JMP      	-22	; to 27
	49	[1697]	RETURN   	1 2
	50	[1698]	RETURN   	0 1

function <./plugins/statistics.koplugin/main.lua:1679,1681> (4 instructions, 16 bytes at 0x7fcdebc1fd80)
0 params, 2 slots, 1 upvalue, 0 locals, 1 constant, 0 functions
	1	[1680]	GETUPVAL 	0 0	; self
	2	[1680]	SELF     	0 0 -1	; "resetBook"
	3	[1680]	CALL     	0 2 1
	4	[1681]	RETURN   	0 1

function <./plugins/statistics.koplugin/main.lua:1692,1694> (5 instructions, 20 bytes at 0x7fcdebc202e0)
0 params, 3 slots, 2 upvalues, 0 locals, 1 constant, 0 functions
	1	[1693]	GETUPVAL 	0 0	; self
	2	[1693]	SELF     	0 0 -1	; "deleteBooksByTotalDuration"
	3	[1693]	GETUPVAL 	2 1	; minutes
	4	[1693]	CALL     	0 3 1
	5	[1694]	RETURN   	0 1

function <./plugins/statistics.koplugin/main.lua:1700,1774> (96 instructions, 384 bytes at 0x7fcdebc20050)
1 param, 21 slots, 8 upvalues, 14 locals, 27 constants, 1 function
	1	[1701]	NEWTABLE 	1 0 0
	2	[1702]	LOADNIL  	2 2
	3	[1704]	SELF     	3 0 -1	; "insertDB"
	4	[1704]	GETTABLE 	5 0 -2	; "id_curr_book"
	5	[1704]	CALL     	3 3 1
	6	[1705]	GETUPVAL 	3 0	; SQ3
	7	[1705]	GETTABLE 	3 3 -3	; "open"
	8	[1705]	GETUPVAL 	4 1	; db_location
	9	[1705]	CALL     	3 2 2
	10	[1710]	LOADK    	4 -4	; "        SELECT id\n        FROM   book\n        ORDER  BY last_open DESC\n    "
	11	[1711]	SELF     	5 3 -5	; "exec"
	12	[1711]	MOVE     	7 4
	13	[1711]	CALL     	5 3 2
	14	[1712]	LOADNIL  	6 6
	15	[1713]	EQ       	1 5 -6	; - nil
	16	[1713]	JMP      	3	; to 20
	17	[1714]	GETTABLE 	7 5 -7	; "id"
	18	[1714]	LEN      	6 7
	19	[1714]	JMP      	1	; to 21
	20	[1716]	LOADK    	6 -8	; 0
	21	[1719]	LOADNIL  	7 7
	22	[1720]	LOADK    	8 -9	; 1
	23	[1720]	MOVE     	9 6
	24	[1720]	LOADK    	10 -9	; 1
	25	[1720]	FORPREP  	8 52	; to 78
	26	[1721]	GETGLOBAL	12 -10	; tonumber
	27	[1721]	GETTABLE 	13 5 -9	; 1
	28	[1721]	GETTABLE 	13 13 11
	29	[1721]	CALL     	12 2 2
	30	[1726]	LOADK    	4 -11	; "            SELECT title\n            FROM   book\n            WHERE  id = '%s'\n        "
	31	[1727]	SELF     	13 3 -12	; "rowexec"
	32	[1727]	GETGLOBAL	15 -13	; string
	33	[1727]	GETTABLE 	15 15 -14	; "format"
	34	[1727]	MOVE     	16 4
	35	[1727]	MOVE     	17 12
	36	[1727]	CALL     	15 3 0
	37	[1727]	CALL     	13 0 2
	38	[1732]	LOADK    	4 -15	; "            SELECT sum(period)\n            FROM   page_stat\n            WHERE  id_book = '%s'\n        "
	39	[1733]	SELF     	14 3 -12	; "rowexec"
	40	[1733]	GETGLOBAL	16 -13	; string
	41	[1733]	GETTABLE 	16 16 -14	; "format"
	42	[1733]	MOVE     	17 4
	43	[1733]	MOVE     	18 12
	44	[1733]	CALL     	16 3 0
	45	[1733]	CALL     	14 0 2
	46	[1733]	MOVE     	7 14
	47	[1734]	EQ       	0 7 -6	; - nil
	48	[1734]	JMP      	1	; to 50
	49	[1735]	LOADK    	7 -8	; 0
	50	[1738]	GETTABLE 	14 0 -2	; "id_curr_book"
	51	[1738]	EQ       	1 12 14
	52	[1738]	JMP      	24	; to 77
	53	[1739]	GETGLOBAL	14 -16	; table
	54	[1739]	GETTABLE 	14 14 -17	; "insert"
	55	[1739]	MOVE     	15 1
	56	[1739]	NEWTABLE 	16 3 1
	57	[1740]	MOVE     	17 13
	58	[1741]	GETUPVAL 	18 2	; util
	59	[1741]	GETTABLE 	18 18 -18	; "secondsToClock"
	60	[1741]	MOVE     	19 7
	61	[1741]	LOADBOOL 	20 0 0
	62	[1741]	CALL     	18 3 2
	63	[1742]	MOVE     	19 12
	64	[1763]	CLOSURE  	20 0	; 0x7fcdebc20960
	65	[1763]	GETUPVAL 	0 3	; UIManager
	66	[1763]	GETUPVAL 	0 4	; ConfirmBox
	67	[1763]	GETUPVAL 	0 5	; T
	68	[1763]	GETUPVAL 	0 6	; _
	69	[1763]	MOVE     	0 13
	70	[1763]	MOVE     	0 1
	71	[1763]	MOVE     	0 12
	72	[1763]	MOVE     	0 0
	73	[1763]	MOVE     	0 2
	74	[1763]	SETTABLE 	16 -19 20	; "callback" -
	75	[1764]	SETLIST  	16 3 1	; 1
	76	[1739]	CALL     	14 3 1
	77	[1765]	CLOSE    	12
	78	[1720]	FORLOOP  	8 -53	; to 26
	79	[1767]	GETUPVAL 	8 7	; KeyValuePage
	80	[1767]	SELF     	8 8 -20	; "new"
	81	[1767]	NEWTABLE 	10 0 3
	82	[1768]	GETUPVAL 	11 6	; _
	83	[1768]	LOADK    	12 -22	; "Reset book statistics"
	84	[1768]	CALL     	11 2 2
	85	[1768]	SETTABLE 	10 -21 11	; "title" -
	86	[1769]	SETTABLE 	10 -23 -24	; "value_align" "right"
	87	[1770]	SETTABLE 	10 -25 1	; "kv_pairs" -
	88	[1767]	CALL     	8 3 2
	89	[1771]	MOVE     	2 8
	90	[1772]	GETUPVAL 	8 3	; UIManager
	91	[1772]	SELF     	8 8 -26	; "show"
	92	[1772]	MOVE     	10 2
	93	[1772]	CALL     	8 3 1
	94	[1773]	SELF     	8 3 -27	; "close"
	95	[1773]	CALL     	8 2 1
	96	[1774]	RETURN   	0 1

function <./plugins/statistics.koplugin/main.lua:1743,1763> (31 instructions, 124 bytes at 0x7fcdebc20960)
0 params, 8 slots, 9 upvalues, 0 locals, 10 constants, 2 functions
	1	[1744]	GETUPVAL 	0 0	; UIManager
	2	[1744]	SELF     	0 0 -1	; "show"
	3	[1744]	GETUPVAL 	2 1	; ConfirmBox
	4	[1744]	SELF     	2 2 -2	; "new"
	5	[1744]	NEWTABLE 	4 0 5
	6	[1745]	GETUPVAL 	5 2	; T
	7	[1745]	GETUPVAL 	6 3	; _
	8	[1745]	LOADK    	7 -4	; "Do you want to reset statistics for book:\n%1"
	9	[1745]	CALL     	6 2 2
	10	[1745]	GETUPVAL 	7 4	; book_title
	11	[1745]	CALL     	5 3 2
	12	[1745]	SETTABLE 	4 -3 5	; "text" -
	13	[1746]	GETUPVAL 	5 3	; _
	14	[1746]	LOADK    	6 -6	; "Cancel"
	15	[1746]	CALL     	5 2 2
	16	[1746]	SETTABLE 	4 -5 5	; "cancel_text" -
	17	[1749]	CLOSURE  	5 0	; 0x7fcdebc21060
	18	[1749]	SETTABLE 	4 -7 5	; "cancel_callback" -
	19	[1750]	GETUPVAL 	5 3	; _
	20	[1750]	LOADK    	6 -9	; "Reset"
	21	[1750]	CALL     	5 2 2
	22	[1750]	SETTABLE 	4 -8 5	; "ok_text" -
	23	[1761]	CLOSURE  	5 1	; 0x7fcdebc20fe0
	24	[1761]	GETUPVAL 	0 5	; total_stats
	25	[1761]	GETUPVAL 	0 6	; id_book
	26	[1761]	GETUPVAL 	0 7	; self
	27	[1761]	GETUPVAL 	0 8	; kv_reset_book
	28	[1761]	SETTABLE 	4 -10 5	; "ok_callback" -
	29	[1744]	CALL     	2 3 0
	30	[1744]	CALL     	0 0 1
	31	[1763]	RETURN   	0 1

function <./plugins/statistics.koplugin/main.lua:1747,1749> (2 instructions, 8 bytes at 0x7fcdebc21060)
0 params, 2 slots, 0 upvalues, 0 locals, 0 constants, 0 functions
	1	[1748]	RETURN   	0 1
	2	[1749]	RETURN   	0 1

function <./plugins/statistics.koplugin/main.lua:1751,1761> (26 instructions, 104 bytes at 0x7fcdebc20fe0)
0 params, 7 slots, 4 upvalues, 4 locals, 6 constants, 0 functions
	1	[1752]	LOADK    	0 -1	; 1
	2	[1752]	GETUPVAL 	1 0	; total_stats
	3	[1752]	LEN      	1 1
	4	[1752]	LOADK    	2 -1	; 1
	5	[1752]	FORPREP  	0 16	; to 22
	6	[1753]	GETUPVAL 	4 0	; total_stats
	7	[1753]	GETTABLE 	4 4 3
	8	[1753]	GETTABLE 	4 4 -2	; 3
	9	[1753]	GETUPVAL 	5 1	; id_book
	10	[1753]	EQ       	0 4 5
	11	[1753]	JMP      	10	; to 22
	12	[1754]	GETUPVAL 	4 2	; self
	13	[1754]	SELF     	4 4 -3	; "deleteBook"
	14	[1754]	GETUPVAL 	6 1	; id_book
	15	[1754]	CALL     	4 3 1
	16	[1755]	GETGLOBAL	4 -4	; table
	17	[1755]	GETTABLE 	4 4 -5	; "remove"
	18	[1755]	GETUPVAL 	5 0	; total_stats
	19	[1755]	MOVE     	6 3
	20	[1755]	CALL     	4 3 1
	21	[1756]	JMP      	1	; to 23
	22	[1752]	FORLOOP  	0 -17	; to 6
	23	[1760]	GETUPVAL 	0 3	; kv_reset_book
	24	[1760]	SELF     	0 0 -6	; "_populateItems"
	25	[1760]	CALL     	0 2 1
	26	[1761]	RETURN   	0 1

function <./plugins/statistics.koplugin/main.lua:1776,1793> (32 instructions, 128 bytes at 0x7fcdebc207e0)
2 params, 8 slots, 2 upvalues, 5 locals, 8 constants, 0 functions
	1	[1777]	GETUPVAL 	2 0	; SQ3
	2	[1777]	GETTABLE 	2 2 -1	; "open"
	3	[1777]	GETUPVAL 	3 1	; db_location
	4	[1777]	CALL     	2 2 2
	5	[1781]	LOADK    	3 -2	; "            DELETE from book\n            WHERE  id = ?\n        "
	6	[1782]	SELF     	4 2 -3	; "prepare"
	7	[1782]	MOVE     	6 3
	8	[1782]	CALL     	4 3 2
	9	[1783]	SELF     	5 4 -4	; "reset"
	10	[1783]	CALL     	5 2 2
	11	[1783]	SELF     	5 5 -5	; "bind"
	12	[1783]	MOVE     	7 1
	13	[1783]	CALL     	5 3 2
	14	[1783]	SELF     	5 5 -6	; "step"
	15	[1783]	CALL     	5 2 1
	16	[1788]	LOADK    	3 -7	; "            DELETE from page_stat\n            WHERE  id_book = ?\n        "
	17	[1789]	SELF     	5 2 -3	; "prepare"
	18	[1789]	MOVE     	7 3
	19	[1789]	CALL     	5 3 2
	20	[1789]	MOVE     	4 5
	21	[1790]	SELF     	5 4 -4	; "reset"
	22	[1790]	CALL     	5 2 2
	23	[1790]	SELF     	5 5 -5	; "bind"
	24	[1790]	MOVE     	7 1
	25	[1790]	CALL     	5 3 2
	26	[1790]	SELF     	5 5 -6	; "step"
	27	[1790]	CALL     	5 2 1
	28	[1791]	SELF     	5 4 -8	; "close"
	29	[1791]	CALL     	5 2 1
	30	[1792]	SELF     	5 2 -8	; "close"
	31	[1792]	CALL     	5 2 1
	32	[1793]	RETURN   	0 1

function <./plugins/statistics.koplugin/main.lua:1795,1845> (35 instructions, 140 bytes at 0x7fcdebc21a40)
2 params, 13 slots, 9 upvalues, 3 locals, 9 constants, 1 function
	1	[1796]	MUL      	2 1 -1	; - 60
	2	[1797]	GETUPVAL 	3 0	; UIManager
	3	[1797]	SELF     	3 3 -2	; "show"
	4	[1797]	GETUPVAL 	5 1	; ConfirmBox
	5	[1797]	SELF     	5 5 -3	; "new"
	6	[1797]	NEWTABLE 	7 0 3
	7	[1798]	GETUPVAL 	8 2	; T
	8	[1798]	GETUPVAL 	9 3	; N_
	9	[1798]	LOADK    	10 -5	; "Permanently remove statistics for books read for less than 1 minute?"
	10	[1799]	LOADK    	11 -6	; "Permanently remove statistics for books read for less than %1 minutes?"
	11	[1800]	MOVE     	12 1
	12	[1798]	CALL     	9 4 2
	13	[1800]	MOVE     	10 1
	14	[1798]	CALL     	8 3 2
	15	[1800]	SETTABLE 	7 -4 8	; "text" -
	16	[1801]	GETUPVAL 	8 4	; _
	17	[1801]	LOADK    	9 -8	; "Remove"
	18	[1801]	CALL     	8 2 2
	19	[1801]	SETTABLE 	7 -7 8	; "ok_text" -
	20	[1843]	CLOSURE  	8 0	; 0x7fcdebc21e30
	21	[1843]	MOVE     	0 0
	22	[1843]	GETUPVAL 	0 5	; SQ3
	23	[1843]	GETUPVAL 	0 6	; db_location
	24	[1843]	MOVE     	0 2
	25	[1843]	MOVE     	0 1
	26	[1843]	GETUPVAL 	0 7	; logger
	27	[1843]	GETUPVAL 	0 0	; UIManager
	28	[1843]	GETUPVAL 	0 8	; InfoMessage
	29	[1843]	GETUPVAL 	0 2	; T
	30	[1843]	GETUPVAL 	0 3	; N_
	31	[1843]	GETUPVAL 	0 4	; _
	32	[1843]	SETTABLE 	7 -9 8	; "ok_callback" -
	33	[1797]	CALL     	5 3 0
	34	[1797]	CALL     	3 0 1
	35	[1845]	RETURN   	0 1

function <./plugins/statistics.koplugin/main.lua:1802,1843> (96 instructions, 384 bytes at 0x7fcdebc21e30)
0 params, 15 slots, 11 upvalues, 7 locals, 28 constants, 0 functions
	1	[1805]	GETUPVAL 	0 0	; self
	2	[1805]	GETTABLE 	0 0 -1	; "id_curr_book"
	3	[1805]	TEST     	0 0 1
	4	[1805]	JMP      	1	; to 6
	5	[1805]	LOADK    	0 -2	; -1
	6	[1806]	GETUPVAL 	1 1	; SQ3
	7	[1806]	GETTABLE 	1 1 -3	; "open"
	8	[1806]	GETUPVAL 	2 2	; db_location
	9	[1806]	CALL     	1 2 2
	10	[1812]	LOADK    	2 -4	; "                    DELETE from page_stat\n                    WHERE  id_book in (\n                      select id from book where id != ? and (total_read_time is NULL or total_read_time < ?)\n                    )\n                "
	11	[1813]	SELF     	3 1 -5	; "prepare"
	12	[1813]	MOVE     	5 2
	13	[1813]	CALL     	3 3 2
	14	[1814]	SELF     	4 3 -6	; "reset"
	15	[1814]	CALL     	4 2 2
	16	[1814]	SELF     	4 4 -7	; "bind"
	17	[1814]	MOVE     	6 0
	18	[1814]	GETUPVAL 	7 3	; max_total_duration_sec
	19	[1814]	CALL     	4 4 2
	20	[1814]	SELF     	4 4 -8	; "step"
	21	[1814]	CALL     	4 2 1
	22	[1818]	LOADK    	2 -9	; "                    DELETE from book\n                    WHERE  id != ? and (total_read_time is NULL or total_read_time < ?)\n                "
	23	[1819]	SELF     	4 1 -5	; "prepare"
	24	[1819]	MOVE     	6 2
	25	[1819]	CALL     	4 3 2
	26	[1819]	MOVE     	3 4
	27	[1820]	SELF     	4 3 -6	; "reset"
	28	[1820]	CALL     	4 2 2
	29	[1820]	SELF     	4 4 -7	; "bind"
	30	[1820]	MOVE     	6 0
	31	[1820]	GETUPVAL 	7 3	; max_total_duration_sec
	32	[1820]	CALL     	4 4 2
	33	[1820]	SELF     	4 4 -8	; "step"
	34	[1820]	CALL     	4 2 1
	35	[1821]	SELF     	4 3 -10	; "close"
	36	[1821]	CALL     	4 2 1
	37	[1825]	LOADK    	2 -11	; "                SELECT changes()\n            "
	38	[1826]	SELF     	4 1 -12	; "rowexec"
	39	[1826]	MOVE     	6 2
	40	[1826]	CALL     	4 3 2
	41	[1827]	TEST     	4 0 0
	42	[1827]	JMP      	5	; to 48
	43	[1827]	GETGLOBAL	5 -13	; tonumber
	44	[1827]	MOVE     	6 4
	45	[1827]	CALL     	5 2 2
	46	[1827]	TESTSET  	4 5 1
	47	[1827]	JMP      	1	; to 49
	48	[1827]	LOADK    	4 -14	; 0
	49	[1828]	GETUPVAL 	5 4	; max_total_duration_mn
	50	[1828]	LE       	0 -15 5	; 30 -
	51	[1828]	JMP      	17	; to 69
	52	[1828]	LE       	0 -16 4	; 10 -
	53	[1828]	JMP      	15	; to 69
	54	[1830]	SELF     	5 1 -17	; "exec"
	55	[1830]	LOADK    	7 -18	; "PRAGMA temp_store = 2"
	56	[1830]	CALL     	5 3 1
	57	[1831]	GETGLOBAL	5 -19	; pcall
	58	[1831]	GETTABLE 	6 1 -17	; "exec"
	59	[1831]	MOVE     	7 1
	60	[1831]	LOADK    	8 -20	; "VACUUM"
	61	[1831]	CALL     	5 4 3
	62	[1832]	TEST     	5 0 1
	63	[1832]	JMP      	5	; to 69
	64	[1833]	GETUPVAL 	7 5	; logger
	65	[1833]	GETTABLE 	7 7 -21	; "warn"
	66	[1833]	LOADK    	8 -22	; "Failed compacting statistics database:"
	67	[1833]	MOVE     	9 6
	68	[1833]	CALL     	7 3 1
	69	[1836]	SELF     	5 1 -10	; "close"
	70	[1836]	CALL     	5 2 1
	71	[1837]	GETUPVAL 	5 6	; UIManager
	72	[1837]	SELF     	5 5 -23	; "show"
	73	[1837]	GETUPVAL 	7 7	; InfoMessage
	74	[1837]	SELF     	7 7 -24	; "new"
	75	[1837]	NEWTABLE 	9 0 1
	76	[1838]	LT       	0 -14 4	; 0 -
	77	[1838]	JMP      	10	; to 88
	78	[1838]	GETUPVAL 	10 8	; T
	79	[1838]	GETUPVAL 	11 9	; N_
	80	[1838]	LOADK    	12 -26	; "Statistics for 1 book removed."
	81	[1839]	LOADK    	13 -27	; "Statistics for %1 books removed."
	82	[1840]	MOVE     	14 4
	83	[1838]	CALL     	11 4 2
	84	[1840]	MOVE     	12 4
	85	[1838]	CALL     	10 3 2
	86	[1841]	TEST     	10 0 1
	87	[1841]	JMP      	5	; to 93
	88	[1841]	GETUPVAL 	10 8	; T
	89	[1841]	GETUPVAL 	11 10	; _
	90	[1841]	LOADK    	12 -28	; "No statistics removed."
	91	[1841]	CALL     	11 2 0
	92	[1841]	CALL     	10 0 2
	93	[1841]	SETTABLE 	9 -25 10	; "text" -
	94	[1837]	CALL     	7 3 0
	95	[1837]	CALL     	5 0 1
	96	[1843]	RETURN   	0 1

function <./plugins/statistics.koplugin/main.lua:1848,1852> (7 instructions, 28 bytes at 0x7fcdebc21c00)
3 params, 6 slots, 0 upvalues, 3 locals, 2 constants, 0 functions
	1	[1849]	GETTABLE 	3 0 -1	; "curr_page"
	2	[1849]	EQ       	1 3 2
	3	[1849]	JMP      	3	; to 7
	4	[1850]	SELF     	3 0 -2	; "onPageUpdate"
	5	[1850]	MOVE     	5 2
	6	[1850]	CALL     	3 3 1
	7	[1852]	RETURN   	0 1

function <./plugins/statistics.koplugin/main.lua:1854,1888> (93 instructions, 372 bytes at 0x7fcdebc22dd0)
2 params, 13 slots, 3 upvalues, 15 locals, 20 constants, 0 functions
	1	[1855]	SELF     	2 0 -1	; "isDocless"
	2	[1855]	CALL     	2 2 2
	3	[1855]	TEST     	2 0 1
	4	[1855]	JMP      	3	; to 8
	5	[1855]	GETTABLE 	2 0 -2	; "is_enabled"
	6	[1855]	TEST     	2 0 1
	7	[1855]	JMP      	1	; to 9
	8	[1856]	RETURN   	0 1
	9	[1858]	SETTABLE 	0 -3 1	; "curr_page" -
	10	[1859]	GETTABLE 	2 0 -4	; "pages_stats"
	11	[1859]	GETUPVAL 	3 0	; TimeVal
	12	[1859]	SELF     	3 3 -5	; "now"
	13	[1859]	CALL     	3 2 2
	14	[1859]	GETTABLE 	3 3 -6	; "sec"
	15	[1859]	SETTABLE 	2 3 1
	16	[1860]	LOADK    	2 -7	; 0
	17	[1861]	LOADK    	3 -7	; 0
	18	[1862]	GETUPVAL 	4 1	; util
	19	[1862]	GETTABLE 	4 4 -8	; "tableSize"
	20	[1862]	GETTABLE 	5 0 -4	; "pages_stats"
	21	[1862]	CALL     	4 2 2
	22	[1862]	LT       	0 -9 4	; 1 -
	23	[1862]	JMP      	45	; to 69
	24	[1863]	GETUPVAL 	4 1	; util
	25	[1863]	GETTABLE 	4 4 -8	; "tableSize"
	26	[1863]	GETTABLE 	5 0 -4	; "pages_stats"
	27	[1863]	CALL     	4 2 2
	28	[1863]	SUB      	2 4 -9	; - 1
	29	[1864]	NEWTABLE 	4 0 0
	30	[1865]	GETGLOBAL	5 -10	; pairs
	31	[1865]	GETTABLE 	6 0 -4	; "pages_stats"
	32	[1865]	CALL     	5 2 4
	33	[1865]	JMP      	5	; to 39
	34	[1866]	GETGLOBAL	10 -11	; table
	35	[1866]	GETTABLE 	10 10 -12	; "insert"
	36	[1866]	MOVE     	11 4
	37	[1866]	MOVE     	12 8
	38	[1866]	CALL     	10 3 1
	39	[1865]	TFORLOOP 	5 2
	40	[1866]	JMP      	-7	; to 34
	41	[1868]	GETGLOBAL	5 -11	; table
	42	[1868]	GETTABLE 	5 5 -13	; "sort"
	43	[1868]	MOVE     	6 4
	44	[1868]	CALL     	5 2 1
	45	[1869]	LOADNIL  	5 5
	46	[1870]	LOADK    	6 -9	; 1
	47	[1870]	LEN      	7 4
	48	[1870]	SUB      	7 7 -9	; - 1
	49	[1870]	LOADK    	8 -9	; 1
	50	[1870]	FORPREP  	6 17	; to 68
	51	[1871]	ADD      	10 9 -9	; - 1
	52	[1871]	GETTABLE 	10 4 10
	53	[1871]	GETTABLE 	11 4 9
	54	[1871]	SUB      	5 10 11
	55	[1872]	GETTABLE 	10 0 -14	; "page_max_read_sec"
	56	[1872]	LE       	0 5 10
	57	[1872]	JMP      	5	; to 63
	58	[1872]	GETTABLE 	10 0 -15	; "page_min_read_sec"
	59	[1872]	LE       	0 10 5
	60	[1872]	JMP      	2	; to 63
	61	[1873]	ADD      	3 3 5
	62	[1873]	JMP      	5	; to 68
	63	[1874]	GETTABLE 	10 0 -14	; "page_max_read_sec"
	64	[1874]	LT       	0 10 5
	65	[1874]	JMP      	2	; to 68
	66	[1875]	GETTABLE 	10 0 -14	; "page_max_read_sec"
	67	[1875]	ADD      	3 3 10
	68	[1870]	FORLOOP  	6 -18	; to 51
	69	[1880]	GETUPVAL 	4 1	; util
	70	[1880]	GETTABLE 	4 4 -8	; "tableSize"
	71	[1880]	GETTABLE 	5 0 -4	; "pages_stats"
	72	[1880]	CALL     	4 2 2
	73	[1880]	GETUPVAL 	5 2	; PAGE_INSERT
	74	[1880]	MOD      	4 4 5
	75	[1880]	EQ       	0 4 -7	; - 0
	76	[1880]	JMP      	5	; to 82
	77	[1881]	SELF     	4 0 -16	; "insertDB"
	78	[1881]	GETTABLE 	6 0 -17	; "id_curr_book"
	79	[1881]	CALL     	4 3 1
	80	[1882]	LOADK    	2 -7	; 0
	81	[1883]	LOADK    	3 -7	; 0
	82	[1885]	GETTABLE 	4 0 -18	; "total_read_pages"
	83	[1885]	LT       	1 -7 4	; 0 -
	84	[1885]	JMP      	2	; to 87
	85	[1885]	LT       	0 -7 2	; 0 -
	86	[1885]	JMP      	6	; to 93
	87	[1886]	GETTABLE 	4 0 -20	; "total_read_time"
	88	[1886]	ADD      	4 4 3
	89	[1886]	GETTABLE 	5 0 -18	; "total_read_pages"
	90	[1886]	ADD      	5 5 2
	91	[1886]	DIV      	4 4 5
	92	[1886]	SETTABLE 	0 -19 4	; "avg_time" -
	93	[1888]	RETURN   	0 1

function <./plugins/statistics.koplugin/main.lua:1891,1903> (29 instructions, 116 bytes at 0x7fcdebc233d0)
3 params, 7 slots, 2 upvalues, 6 locals, 10 constants, 0 functions
	1	[1892]	GETGLOBAL	3 -1	; string
	2	[1892]	GETTABLE 	3 3 -2	; "gsub"
	3	[1892]	MOVE     	4 2
	4	[1892]	LOADK    	5 -3	; "^%s*(.-)%s*$"
	5	[1892]	LOADK    	6 -4	; "%1"
	6	[1892]	CALL     	3 4 2
	7	[1892]	MOVE     	2 3
	8	[1893]	EQ       	1 2 -5	; - ".stat"
	9	[1893]	JMP      	19	; to 29
	10	[1894]	GETUPVAL 	3 0	; joinPath
	11	[1894]	MOVE     	4 1
	12	[1894]	MOVE     	5 2
	13	[1894]	CALL     	3 3 2
	14	[1895]	GETUPVAL 	4 1	; lfs
	15	[1895]	GETTABLE 	4 4 -6	; "attributes"
	16	[1895]	MOVE     	5 3
	17	[1895]	LOADK    	6 -7	; "mode"
	18	[1895]	CALL     	4 3 2
	19	[1895]	EQ       	0 4 -8	; - "directory"
	20	[1895]	JMP      	1	; to 22
	21	[1896]	RETURN   	0 1
	22	[1898]	GETGLOBAL	4 -9	; pcall
	23	[1898]	GETGLOBAL	5 -10	; dofile
	24	[1898]	MOVE     	6 3
	25	[1898]	CALL     	4 3 3
	26	[1899]	TEST     	4 0 0
	27	[1899]	JMP      	1	; to 29
	28	[1900]	RETURN   	5 2
	29	[1903]	RETURN   	0 1

function <./plugins/statistics.koplugin/main.lua:1905,1910> (17 instructions, 68 bytes at 0x7fcdebc22ed0)
1 param, 5 slots, 0 upvalues, 1 local, 9 constants, 0 functions
	1	[1906]	SELF     	1 0 -1	; "isDocless"
	2	[1906]	CALL     	1 2 2
	3	[1906]	TEST     	1 0 1
	4	[1906]	JMP      	12	; to 17
	5	[1906]	GETTABLE 	1 0 -2	; "is_enabled"
	6	[1906]	TEST     	1 0 0
	7	[1906]	JMP      	9	; to 17
	8	[1907]	GETTABLE 	1 0 -3	; "ui"
	9	[1907]	GETTABLE 	1 1 -4	; "doc_settings"
	10	[1907]	SELF     	1 1 -5	; "saveSetting"
	11	[1907]	LOADK    	3 -6	; "stats"
	12	[1907]	GETTABLE 	4 0 -7	; "data"
	13	[1907]	CALL     	1 4 1
	14	[1908]	SELF     	1 0 -8	; "insertDB"
	15	[1908]	GETTABLE 	3 0 -9	; "id_curr_book"
	16	[1908]	CALL     	1 3 1
	17	[1910]	RETURN   	0 1

function <./plugins/statistics.koplugin/main.lua:1912,1915> (8 instructions, 32 bytes at 0x7fcdebc24410)
1 param, 3 slots, 0 upvalues, 1 local, 3 constants, 0 functions
	1	[1913]	GETTABLE 	1 0 -1	; "data"
	2	[1913]	GETTABLE 	2 0 -1	; "data"
	3	[1913]	GETTABLE 	2 2 -2	; "highlights"
	4	[1913]	ADD      	2 2 -3	; - 1
	5	[1913]	SETTABLE 	1 -2 2	; "highlights" -
	6	[1914]	LOADBOOL 	1 1 0
	7	[1914]	RETURN   	1 2
	8	[1915]	RETURN   	0 1

function <./plugins/statistics.koplugin/main.lua:1917,1922> (12 instructions, 48 bytes at 0x7fcdebc244a0)
1 param, 3 slots, 0 upvalues, 1 local, 4 constants, 0 functions
	1	[1918]	GETTABLE 	1 0 -1	; "data"
	2	[1918]	GETTABLE 	1 1 -2	; "highlights"
	3	[1918]	LT       	0 -3 1	; 0 -
	4	[1918]	JMP      	5	; to 10
	5	[1919]	GETTABLE 	1 0 -1	; "data"
	6	[1919]	GETTABLE 	2 0 -1	; "data"
	7	[1919]	GETTABLE 	2 2 -2	; "highlights"
	8	[1919]	SUB      	2 2 -4	; - 1
	9	[1919]	SETTABLE 	1 -2 2	; "highlights" -
	10	[1921]	LOADBOOL 	1 1 0
	11	[1921]	RETURN   	1 2
	12	[1922]	RETURN   	0 1

function <./plugins/statistics.koplugin/main.lua:1924,1926> (6 instructions, 24 bytes at 0x7fcdebc24620)
1 param, 3 slots, 0 upvalues, 1 local, 3 constants, 0 functions
	1	[1925]	GETTABLE 	1 0 -1	; "data"
	2	[1925]	GETTABLE 	2 0 -1	; "data"
	3	[1925]	GETTABLE 	2 2 -2	; "notes"
	4	[1925]	ADD      	2 2 -3	; - 1
	5	[1925]	SETTABLE 	1 -2 2	; "notes" -
	6	[1926]	RETURN   	0 1

function <./plugins/statistics.koplugin/main.lua:1928,1933> (13 instructions, 52 bytes at 0x7fcdebc248c0)
1 param, 5 slots, 0 upvalues, 1 local, 7 constants, 0 functions
	1	[1929]	SELF     	1 0 -1	; "saveSettings"
	2	[1929]	CALL     	1 2 1
	3	[1930]	SELF     	1 0 -2	; "isDocless"
	4	[1930]	CALL     	1 2 2
	5	[1930]	TEST     	1 0 1
	6	[1930]	JMP      	6	; to 13
	7	[1931]	GETTABLE 	1 0 -3	; "ui"
	8	[1931]	GETTABLE 	1 1 -4	; "doc_settings"
	9	[1931]	SELF     	1 1 -5	; "saveSetting"
	10	[1931]	LOADK    	3 -6	; "stats"
	11	[1931]	GETTABLE 	4 0 -7	; "data"
	12	[1931]	CALL     	1 4 1
	13	[1933]	RETURN   	0 1

function <./plugins/statistics.koplugin/main.lua:1936,1941> (14 instructions, 56 bytes at 0x7fcdebc24f70)
1 param, 5 slots, 0 upvalues, 1 local, 8 constants, 0 functions
	1	[1937]	SELF     	1 0 -1	; "isDocless"
	2	[1937]	CALL     	1 2 2
	3	[1937]	TEST     	1 0 1
	4	[1937]	JMP      	9	; to 14
	5	[1938]	GETTABLE 	1 0 -2	; "ui"
	6	[1938]	GETTABLE 	1 1 -3	; "doc_settings"
	7	[1938]	SELF     	1 1 -4	; "saveSetting"
	8	[1938]	LOADK    	3 -5	; "stats"
	9	[1938]	GETTABLE 	4 0 -6	; "data"
	10	[1938]	CALL     	1 4 1
	11	[1939]	SELF     	1 0 -7	; "insertDB"
	12	[1939]	GETTABLE 	3 0 -8	; "id_curr_book"
	13	[1939]	CALL     	1 3 1
	14	[1941]	RETURN   	0 1

function <./plugins/statistics.koplugin/main.lua:1944,1948> (12 instructions, 48 bytes at 0x7fcdebc25420)
1 param, 4 slots, 1 upvalue, 1 local, 5 constants, 0 functions
	1	[1945]	GETUPVAL 	1 0	; TimeVal
	2	[1945]	SELF     	1 1 -2	; "now"
	3	[1945]	CALL     	1 2 2
	4	[1945]	GETTABLE 	1 1 -3	; "sec"
	5	[1945]	SETTABLE 	0 -1 1	; "start_current_period" -
	6	[1946]	NEWTABLE 	1 0 0
	7	[1946]	SETTABLE 	0 -4 1	; "pages_stats" -
	8	[1947]	GETTABLE 	1 0 -4	; "pages_stats"
	9	[1947]	GETTABLE 	2 0 -1	; "start_current_period"
	10	[1947]	GETTABLE 	3 0 -5	; "curr_page"
	11	[1947]	SETTABLE 	1 2 3
	12	[1948]	RETURN   	0 1

function <./plugins/statistics.koplugin/main.lua:1950,1962> (23 instructions, 92 bytes at 0x7fcdebc25880)
1 param, 6 slots, 0 upvalues, 2 locals, 13 constants, 0 functions
	1	[1951]	NEWTABLE 	1 0 8
	2	[1952]	GETTABLE 	2 0 -2	; "page_min_read_sec"
	3	[1952]	SETTABLE 	1 -1 2	; "min_sec" -
	4	[1953]	GETTABLE 	2 0 -4	; "page_max_read_sec"
	5	[1953]	SETTABLE 	1 -3 2	; "max_sec" -
	6	[1954]	GETTABLE 	2 0 -5	; "is_enabled"
	7	[1954]	SETTABLE 	1 -5 2	; "is_enabled" -
	8	[1955]	GETTABLE 	2 0 -6	; "convert_to_db"
	9	[1955]	SETTABLE 	1 -6 2	; "convert_to_db" -
	10	[1956]	GETTABLE 	2 0 -7	; "calendar_start_day_of_week"
	11	[1956]	SETTABLE 	1 -7 2	; "calendar_start_day_of_week" -
	12	[1957]	GETTABLE 	2 0 -8	; "calendar_nb_book_spans"
	13	[1957]	SETTABLE 	1 -8 2	; "calendar_nb_book_spans" -
	14	[1958]	GETTABLE 	2 0 -9	; "calendar_show_histogram"
	15	[1958]	SETTABLE 	1 -9 2	; "calendar_show_histogram" -
	16	[1959]	GETTABLE 	2 0 -10	; "calendar_browse_future_months"
	17	[1959]	SETTABLE 	1 -10 2	; "calendar_browse_future_months" -
	18	[1961]	GETGLOBAL	2 -11	; G_reader_settings
	19	[1961]	SELF     	2 2 -12	; "saveSetting"
	20	[1961]	LOADK    	4 -13	; "statistics"
	21	[1961]	MOVE     	5 1
	22	[1961]	CALL     	2 4 1
	23	[1962]	RETURN   	0 1

function <./plugins/statistics.koplugin/main.lua:1964,1966> (7 instructions, 28 bytes at 0x7fcdebc25ee0)
2 params, 3 slots, 0 upvalues, 2 locals, 2 constants, 0 functions
	1	[1965]	GETTABLE 	2 1 -1	; "data"
	2	[1965]	GETTABLE 	2 2 -2	; "stats"
	3	[1965]	TEST     	2 0 1
	4	[1965]	JMP      	1	; to 6
	5	[1965]	NEWTABLE 	2 0 0
	6	[1965]	SETTABLE 	0 -1 2	; "data" -
	7	[1966]	RETURN   	0 1

function <./plugins/statistics.koplugin/main.lua:1968,1972> (7 instructions, 28 bytes at 0x7fcdebc25f80)
1 param, 3 slots, 0 upvalues, 1 local, 4 constants, 0 functions
	1	[1970]	SELF     	1 0 -1	; "initData"
	2	[1970]	CALL     	1 2 1
	3	[1971]	GETTABLE 	1 0 -2	; "view"
	4	[1971]	GETTABLE 	1 1 -3	; "footer"
	5	[1971]	SELF     	1 1 -4	; "updateFooter"
	6	[1971]	CALL     	1 2 1
	7	[1972]	RETURN   	0 1

function <./plugins/statistics.koplugin/main.lua:1974,1987> (26 instructions, 104 bytes at 0x7fcdebc260f0)
1 param, 6 slots, 3 upvalues, 2 locals, 17 constants, 0 functions
	1	[1975]	SELF     	1 0 -1	; "insertDB"
	2	[1975]	GETTABLE 	3 0 -2	; "id_curr_book"
	3	[1975]	CALL     	1 3 1
	4	[1976]	GETGLOBAL	1 -3	; require
	5	[1976]	LOADK    	2 -4	; "calendarview"
	6	[1976]	CALL     	1 2 2
	7	[1977]	SELF     	2 1 -5	; "new"
	8	[1977]	NEWTABLE 	4 0 8
	9	[1978]	SETTABLE 	4 -6 0	; "reader_statistics" -
	10	[1979]	GETUPVAL 	5 0	; monthTranslation
	11	[1979]	SETTABLE 	4 -7 5	; "monthTranslation" -
	12	[1980]	GETUPVAL 	5 1	; shortDayOfWeekTranslation
	13	[1980]	SETTABLE 	4 -8 5	; "shortDayOfWeekTranslation" -
	14	[1981]	GETUPVAL 	5 2	; longDayOfWeekTranslation
	15	[1981]	SETTABLE 	4 -9 5	; "longDayOfWeekTranslation" -
	16	[1982]	GETTABLE 	5 0 -11	; "calendar_start_day_of_week"
	17	[1982]	SETTABLE 	4 -10 5	; "start_day_of_week" -
	18	[1983]	GETTABLE 	5 0 -13	; "calendar_nb_book_spans"
	19	[1983]	SETTABLE 	4 -12 5	; "nb_book_spans" -
	20	[1984]	GETTABLE 	5 0 -15	; "calendar_show_histogram"
	21	[1984]	SETTABLE 	4 -14 5	; "show_hourly_histogram" -
	22	[1985]	GETTABLE 	5 0 -17	; "calendar_browse_future_months"
	23	[1985]	SETTABLE 	4 -16 5	; "browse_future_months" -
	24	[1977]	TAILCALL 	2 3 0
	25	[1986]	RETURN   	2 0
	26	[1987]	RETURN   	0 1

function <./plugins/statistics.koplugin/main.lua:1990,1999> (20 instructions, 80 bytes at 0x7fcdebc265f0)
1 param, 6 slots, 2 upvalues, 4 locals, 5 constants, 0 functions
	1	[1994]	LOADK    	1 -1	; "        SELECT min(start_time)\n        FROM   page_stat\n    "
	2	[1995]	GETUPVAL 	2 0	; SQ3
	3	[1995]	GETTABLE 	2 2 -2	; "open"
	4	[1995]	GETUPVAL 	3 1	; db_location
	5	[1995]	CALL     	2 2 2
	6	[1996]	SELF     	3 2 -3	; "rowexec"
	7	[1996]	MOVE     	5 1
	8	[1996]	CALL     	3 3 2
	9	[1997]	SELF     	4 2 -4	; "close"
	10	[1997]	CALL     	4 2 1
	11	[1998]	TEST     	3 0 0
	12	[1998]	JMP      	5	; to 18
	13	[1998]	GETGLOBAL	4 -5	; tonumber
	14	[1998]	MOVE     	5 3
	15	[1998]	CALL     	4 2 2
	16	[1998]	TEST     	4 0 1
	17	[1998]	JMP      	1	; to 19
	18	[1998]	LOADNIL  	4 4
	19	[1998]	RETURN   	4 2
	20	[1999]	RETURN   	0 1

function <./plugins/statistics.koplugin/main.lua:2001,2029> (45 instructions, 180 bytes at 0x7fcdebc26c90)
2 params, 18 slots, 2 upvalues, 15 locals, 12 constants, 0 functions
	1	[2013]	LOADK    	2 -1	; "        SELECT\n            strftime('%Y-%m-%d', start_time, 'unixepoch', 'localtime') day,\n            strftime('%H', start_time, 'unixepoch', 'localtime') hour,\n            sum(period)/3600.0 ratio\n        FROM   page_stat\n        WHERE  strftime('%Y-%m', start_time, 'unixepoch', 'localtime') = ?\n        GROUP  BY\n            strftime('%Y-%m-%d', start_time, 'unixepoch', 'localtime'),\n            strftime('%H', start_time, 'unixepoch', 'localtime')\n        ORDER BY day, hour\n    "
	2	[2014]	GETUPVAL 	3 0	; SQ3
	3	[2014]	GETTABLE 	3 3 -2	; "open"
	4	[2014]	GETUPVAL 	4 1	; db_location
	5	[2014]	CALL     	3 2 2
	6	[2015]	SELF     	4 3 -3	; "prepare"
	7	[2015]	MOVE     	6 2
	8	[2015]	CALL     	4 3 2
	9	[2016]	SELF     	5 4 -4	; "reset"
	10	[2016]	CALL     	5 2 2
	11	[2016]	SELF     	5 5 -5	; "bind"
	12	[2016]	MOVE     	7 1
	13	[2016]	CALL     	5 3 2
	14	[2016]	SELF     	5 5 -6	; "resultset"
	15	[2016]	LOADK    	7 -7	; "i"
	16	[2016]	CALL     	5 3 3
	17	[2017]	SELF     	7 4 -8	; "close"
	18	[2017]	CALL     	7 2 1
	19	[2018]	SELF     	7 3 -8	; "close"
	20	[2018]	CALL     	7 2 1
	21	[2019]	NEWTABLE 	7 0 0
	22	[2020]	LOADK    	8 -9	; 1
	23	[2020]	MOVE     	9 6
	24	[2020]	LOADK    	10 -9	; 1
	25	[2020]	FORPREP  	8 17	; to 43
	26	[2021]	GETTABLE 	12 5 -9	; 1
	27	[2021]	GETTABLE 	12 12 11
	28	[2021]	GETTABLE 	13 5 -10	; 2
	29	[2021]	GETTABLE 	13 13 11
	30	[2021]	GETTABLE 	14 5 -11	; 3
	31	[2021]	GETTABLE 	14 14 11
	32	[2022]	GETTABLE 	15 7 12
	33	[2022]	TEST     	15 0 1
	34	[2022]	JMP      	2	; to 37
	35	[2023]	NEWTABLE 	15 0 0
	36	[2023]	SETTABLE 	7 12 15
	37	[2026]	GETTABLE 	15 7 12
	38	[2026]	GETGLOBAL	16 -12	; tonumber
	39	[2026]	MOVE     	17 13
	40	[2026]	CALL     	16 2 2
	41	[2026]	ADD      	16 16 -9	; - 1
	42	[2026]	SETTABLE 	15 16 14
	43	[2020]	FORLOOP  	8 -18	; to 26
	44	[2028]	RETURN   	7 2
	45	[2029]	RETURN   	0 1

function <./plugins/statistics.koplugin/main.lua:2031,2063> (54 instructions, 216 bytes at 0x7fcdebc271d0)
2 params, 21 slots, 2 upvalues, 16 locals, 18 constants, 0 functions
	1	[2046]	LOADK    	2 -1	; "        SELECT\n            strftime('%Y-%m-%d', start_time, 'unixepoch', 'localtime') day,\n            sum(period) duration,\n            id_book book_id,\n            book.title book_title\n        FROM   page_stat\n        JOIN   book on book.id = page_stat.id_book\n        WHERE  strftime('%Y-%m', start_time, 'unixepoch', 'localtime') = ?\n        GROUP  BY\n            strftime('%Y-%m-%d', start_time, 'unixepoch', 'localtime'),\n            id_book,\n            title\n        ORDER BY day, duration desc, book_id, book_title\n    "
	2	[2047]	GETUPVAL 	3 0	; SQ3
	3	[2047]	GETTABLE 	3 3 -2	; "open"
	4	[2047]	GETUPVAL 	4 1	; db_location
	5	[2047]	CALL     	3 2 2
	6	[2048]	SELF     	4 3 -3	; "prepare"
	7	[2048]	MOVE     	6 2
	8	[2048]	CALL     	4 3 2
	9	[2049]	SELF     	5 4 -4	; "reset"
	10	[2049]	CALL     	5 2 2
	11	[2049]	SELF     	5 5 -5	; "bind"
	12	[2049]	MOVE     	7 1
	13	[2049]	CALL     	5 3 2
	14	[2049]	SELF     	5 5 -6	; "resultset"
	15	[2049]	LOADK    	7 -7	; "i"
	16	[2049]	CALL     	5 3 3
	17	[2050]	SELF     	7 4 -8	; "close"
	18	[2050]	CALL     	7 2 1
	19	[2051]	SELF     	7 3 -8	; "close"
	20	[2051]	CALL     	7 2 1
	21	[2052]	NEWTABLE 	7 0 0
	22	[2053]	LOADK    	8 -9	; 1
	23	[2053]	MOVE     	9 6
	24	[2053]	LOADK    	10 -9	; 1
	25	[2053]	FORPREP  	8 26	; to 52
	26	[2056]	GETTABLE 	12 5 -9	; 1
	27	[2056]	GETTABLE 	12 12 11
	28	[2056]	GETTABLE 	13 5 -10	; 2
	29	[2056]	GETTABLE 	13 13 11
	30	[2056]	GETTABLE 	14 5 -11	; 3
	31	[2056]	GETTABLE 	14 14 11
	32	[2056]	GETTABLE 	15 5 -12	; 4
	33	[2056]	GETTABLE 	15 15 11
	34	[2057]	GETTABLE 	16 7 12
	35	[2057]	TEST     	16 0 1
	36	[2057]	JMP      	2	; to 39
	37	[2058]	NEWTABLE 	16 0 0
	38	[2058]	SETTABLE 	7 12 16
	39	[2060]	GETGLOBAL	16 -13	; table
	40	[2060]	GETTABLE 	16 16 -14	; "insert"
	41	[2060]	GETTABLE 	17 7 12
	42	[2060]	NEWTABLE 	18 0 2
	43	[2060]	GETGLOBAL	19 -16	; tonumber
	44	[2060]	MOVE     	20 14
	45	[2060]	CALL     	19 2 2
	46	[2060]	SETTABLE 	18 -15 19	; "id" -
	47	[2060]	GETGLOBAL	19 -18	; tostring
	48	[2060]	MOVE     	20 15
	49	[2060]	CALL     	19 2 2
	50	[2060]	SETTABLE 	18 -17 19	; "title" -
	51	[2060]	CALL     	16 3 1
	52	[2053]	FORLOOP  	8 -27	; to 26
	53	[2062]	RETURN   	7 2
	54	[2063]	RETURN   	0 1
