
main <./frontend/ui/elements/mass_storage.lua:0,0> (21 instructions, 84 bytes at 0x7fe75bc068e0)
0+ params, 4 slots, 0 upvalues, 3 locals, 7 constants, 4 functions
	1	[1]	GETGLOBAL	0 -1	; require
	2	[1]	LOADK    	1 -2	; "ui/uimanager"
	3	[1]	CALL     	0 2 2
	4	[2]	GETGLOBAL	1 -1	; require
	5	[2]	LOADK    	2 -3	; "gettext"
	6	[2]	CALL     	1 2 2
	7	[4]	NEWTABLE 	2 0 0
	8	[9]	CLOSURE  	3 0	; 0x7fe75bc06be0
	9	[7]	SETTABLE 	2 -4 3	; "requireConfirmation" -
	10	[22]	CLOSURE  	3 1	; 0x7fe75bc072d0
	11	[22]	MOVE     	0 1
	12	[12]	SETTABLE 	2 -5 3	; "getSettingsMenuTable" -
	13	[34]	CLOSURE  	3 2	; 0x7fe75bc07aa0
	14	[34]	MOVE     	0 1
	15	[25]	SETTABLE 	2 -6 3	; "getActionsMenuTable" -
	16	[52]	CLOSURE  	3 3	; 0x7fe75bc08270
	17	[52]	MOVE     	0 0
	18	[52]	MOVE     	0 1
	19	[37]	SETTABLE 	2 -7 3	; "start" -
	20	[54]	RETURN   	2 2
	21	[54]	RETURN   	0 1

function <./frontend/ui/elements/mass_storage.lua:7,9> (7 instructions, 28 bytes at 0x7fe75bc06be0)
1 param, 4 slots, 0 upvalues, 1 local, 3 constants, 0 functions
	1	[8]	GETGLOBAL	1 -1	; G_reader_settings
	2	[8]	SELF     	1 1 -2	; "isTrue"
	3	[8]	LOADK    	3 -3	; "mass_storage_confirmation_disabled"
	4	[8]	CALL     	1 3 2
	5	[8]	NOT      	1 1
	6	[8]	RETURN   	1 2
	7	[9]	RETURN   	0 1

function <./frontend/ui/elements/mass_storage.lua:12,22> (15 instructions, 60 bytes at 0x7fe75bc072d0)
1 param, 5 slots, 1 upvalue, 1 local, 4 constants, 2 functions
	1	[13]	NEWTABLE 	1 1 0
	2	[13]	NEWTABLE 	2 0 3
	3	[15]	GETUPVAL 	3 0	; _
	4	[15]	LOADK    	4 -2	; "Disable confirmation popup"
	5	[15]	CALL     	3 2 2
	6	[15]	SETTABLE 	2 -1 3	; "text" -
	7	[16]	CLOSURE  	3 0	; 0x7fe75bc07660
	8	[16]	MOVE     	0 0
	9	[16]	SETTABLE 	2 -3 3	; "checked_func" -
	10	[19]	CLOSURE  	3 1	; 0x7fe75bc07950
	11	[19]	MOVE     	0 0
	12	[19]	SETTABLE 	2 -4 3	; "callback" -
	13	[21]	SETLIST  	1 1 1	; 1
	14	[21]	RETURN   	1 2
	15	[22]	RETURN   	0 1

function <./frontend/ui/elements/mass_storage.lua:16,16> (6 instructions, 24 bytes at 0x7fe75bc07660)
0 params, 2 slots, 1 upvalue, 0 locals, 1 constant, 0 functions
	1	[16]	GETUPVAL 	0 0	; self
	2	[16]	SELF     	0 0 -1	; "requireConfirmation"
	3	[16]	CALL     	0 2 2
	4	[16]	NOT      	0 0
	5	[16]	RETURN   	0 2
	6	[16]	RETURN   	0 1

function <./frontend/ui/elements/mass_storage.lua:17,19> (8 instructions, 32 bytes at 0x7fe75bc07950)
0 params, 5 slots, 1 upvalue, 0 locals, 4 constants, 0 functions
	1	[18]	GETGLOBAL	0 -1	; G_reader_settings
	2	[18]	SELF     	0 0 -2	; "saveSetting"
	3	[18]	LOADK    	2 -3	; "mass_storage_confirmation_disabled"
	4	[18]	GETUPVAL 	3 0	; self
	5	[18]	SELF     	3 3 -4	; "requireConfirmation"
	6	[18]	CALL     	3 2 0
	7	[18]	CALL     	0 0 1
	8	[19]	RETURN   	0 1

function <./frontend/ui/elements/mass_storage.lua:25,34> (12 instructions, 48 bytes at 0x7fe75bc07aa0)
1 param, 5 slots, 1 upvalue, 1 local, 3 constants, 1 function
	1	[26]	NEWTABLE 	1 1 0
	2	[26]	NEWTABLE 	2 0 2
	3	[28]	GETUPVAL 	3 0	; _
	4	[28]	LOADK    	4 -2	; "Start USB storage"
	5	[28]	CALL     	3 2 2
	6	[28]	SETTABLE 	2 -1 3	; "text" -
	7	[31]	CLOSURE  	3 0	; 0x7fe75bc07580
	8	[31]	MOVE     	0 0
	9	[31]	SETTABLE 	2 -3 3	; "callback" -
	10	[33]	SETLIST  	1 1 1	; 1
	11	[33]	RETURN   	1 2
	12	[34]	RETURN   	0 1

function <./frontend/ui/elements/mass_storage.lua:29,31> (4 instructions, 16 bytes at 0x7fe75bc07580)
0 params, 2 slots, 1 upvalue, 0 locals, 1 constant, 0 functions
	1	[30]	GETUPVAL 	0 0	; self
	2	[30]	SELF     	0 0 -1	; "start"
	3	[30]	CALL     	0 2 1
	4	[31]	RETURN   	0 1

function <./frontend/ui/elements/mass_storage.lua:37,52> (31 instructions, 124 bytes at 0x7fe75bc08270)
1 param, 9 slots, 2 upvalues, 2 locals, 13 constants, 1 function
	1	[38]	SELF     	1 0 -1	; "requireConfirmation"
	2	[38]	CALL     	1 2 2
	3	[38]	TEST     	1 0 0
	4	[38]	JMP      	21	; to 26
	5	[39]	GETGLOBAL	1 -2	; require
	6	[39]	LOADK    	2 -3	; "ui/widget/confirmbox"
	7	[39]	CALL     	1 2 2
	8	[40]	GETUPVAL 	2 0	; UIManager
	9	[40]	SELF     	2 2 -4	; "show"
	10	[40]	SELF     	4 1 -5	; "new"
	11	[40]	NEWTABLE 	6 0 3
	12	[41]	GETUPVAL 	7 1	; _
	13	[41]	LOADK    	8 -7	; "Share storage via USB?\n"
	14	[41]	CALL     	7 2 2
	15	[41]	SETTABLE 	6 -6 7	; "text" -
	16	[42]	GETUPVAL 	7 1	; _
	17	[42]	LOADK    	8 -9	; "Share"
	18	[42]	CALL     	7 2 2
	19	[42]	SETTABLE 	6 -8 7	; "ok_text" -
	20	[46]	CLOSURE  	7 0	; 0x7fe75bc06740
	21	[46]	GETUPVAL 	0 0	; UIManager
	22	[46]	SETTABLE 	6 -10 7	; "ok_callback" -
	23	[40]	CALL     	4 3 0
	24	[40]	CALL     	2 0 1
	25	[47]	JMP      	5	; to 31
	26	[49]	GETUPVAL 	1 0	; UIManager
	27	[49]	SELF     	1 1 -11	; "quit"
	28	[49]	CALL     	1 2 1
	29	[50]	GETUPVAL 	1 0	; UIManager
	30	[50]	SETTABLE 	1 -12 -13	; "_exit_code" 86
	31	[52]	RETURN   	0 1

function <./frontend/ui/elements/mass_storage.lua:43,46> (6 instructions, 24 bytes at 0x7fe75bc06740)
0 params, 2 slots, 1 upvalue, 0 locals, 3 constants, 0 functions
	1	[44]	GETUPVAL 	0 0	; UIManager
	2	[44]	SELF     	0 0 -1	; "quit"
	3	[44]	CALL     	0 2 1
	4	[45]	GETUPVAL 	0 0	; UIManager
	5	[45]	SETTABLE 	0 -2 -3	; "_exit_code" 86
	6	[46]	RETURN   	0 1
