-- BYTECODE -- mass_storage.lua:7-9
0001    GGET     1   0      ; "G_reader_settings"
0002    MOV      2   1
0003    TGETS    1   1   1  ; "isTrue"
0004    KSTR     3   2      ; "mass_storage_confirmation_disabled"
0005    CALL     1   2   3
0006    NOT      1   1
0007    RET1     1   2

-- BYTECODE -- mass_storage.lua:16-16
0001    UGET     0   0      ; self
0002    MOV      1   0
0003    TGETS    0   0   0  ; "requireConfirmation"
0004    CALL     0   2   2
0005    NOT      0   0
0006    RET1     0   2

-- BYTECODE -- mass_storage.lua:17-19
0001    GGET     0   0      ; "G_reader_settings"
0002    MOV      1   0
0003    TGETS    0   0   1  ; "saveSetting"
0004    KSTR     2   2      ; "mass_storage_confirmation_disabled"
0005    UGET     3   0      ; self
0006    MOV      4   3
0007    TGETS    3   3   3  ; "requireConfirmation"
0008    CALL     3   0   2
0009    CALLM    0   1   2
0010    RET0     0   1

-- BYTECODE -- mass_storage.lua:12-22
0001    TNEW     1   3
0002    TDUP     2   1
0003    UGET     3   0      ; _
0004    KSTR     4   0      ; "Disable confirmation popup"
0005    CALL     3   2   2
0006    TSETS    3   2   2  ; "text"
0007    FNEW     3   3      ; mass_storage.lua:16
0008    TSETS    3   2   4  ; "checked_func"
0009    FNEW     3   5      ; mass_storage.lua:17
0010    TSETS    3   2   6  ; "callback"
0011    TSETB    2   1   1
0012    UCLO     0 => 0013
0013 => RET1     1   2

-- BYTECODE -- mass_storage.lua:29-31
0001    UGET     0   0      ; self
0002    MOV      1   0
0003    TGETS    0   0   0  ; "start"
0004    CALL     0   1   2
0005    RET0     0   1

-- BYTECODE -- mass_storage.lua:25-34
0001    TNEW     1   3
0002    TDUP     2   1
0003    UGET     3   0      ; _
0004    KSTR     4   0      ; "Start USB storage"
0005    CALL     3   2   2
0006    TSETS    3   2   2  ; "text"
0007    FNEW     3   3      ; mass_storage.lua:29
0008    TSETS    3   2   4  ; "callback"
0009    TSETB    2   1   1
0010    UCLO     0 => 0011
0011 => RET1     1   2

-- BYTECODE -- mass_storage.lua:43-46
0001    UGET     0   0      ; UIManager
0002    MOV      1   0
0003    TGETS    0   0   0  ; "quit"
0004    CALL     0   1   2
0005    UGET     0   0      ; UIManager
0006    KSHORT   1  86
0007    TSETS    1   0   1  ; "_exit_code"
0008    RET0     0   1

-- BYTECODE -- mass_storage.lua:37-52
0001    MOV      2   0
0002    TGETS    1   0   0  ; "requireConfirmation"
0003    CALL     1   2   2
0004    ISF          1
0005    JMP      2 => 0028
0006    GGET     1   1      ; "require"
0007    KSTR     2   2      ; "ui/widget/confirmbox"
0008    CALL     1   2   2
0009    UGET     2   0      ; UIManager
0010    MOV      3   2
0011    TGETS    2   2   3  ; "show"
0012    MOV      5   1
0013    TGETS    4   1   4  ; "new"
0014    TDUP     6   6
0015    UGET     7   1      ; _
0016    KSTR     8   5      ; "Share storage via USB?\n"
0017    CALL     7   2   2
0018    TSETS    7   6   7  ; "text"
0019    UGET     7   1      ; _
0020    KSTR     8   8      ; "Share"
0021    CALL     7   2   2
0022    TSETS    7   6   9  ; "ok_text"
0023    FNEW     7  10      ; mass_storage.lua:43
0024    TSETS    7   6  11  ; "ok_callback"
0025    CALL     4   0   3
0026    CALLM    2   1   1
0027    JMP      1 => 0035
0028 => UGET     1   0      ; UIManager
0029    MOV      2   1
0030    TGETS    1   1  12  ; "quit"
0031    CALL     1   1   2
0032    UGET     1   0      ; UIManager
0033    KSHORT   2  86
0034    TSETS    2   1  13  ; "_exit_code"
0035 => RET0     0   1

-- BYTECODE -- mass_storage.lua:0-55
0001    GGET     0   0      ; "require"
0002    KSTR     1   1      ; "ui/uimanager"
0003    CALL     0   2   2
0004    GGET     1   0      ; "require"
0005    KSTR     2   2      ; "gettext"
0006    CALL     1   2   2
0007    TNEW     2   0
0008    FNEW     3   4      ; mass_storage.lua:7
0009    TSETS    3   2   3  ; "requireConfirmation"
0010    FNEW     3   6      ; mass_storage.lua:12
0011    TSETS    3   2   5  ; "getSettingsMenuTable"
0012    FNEW     3   8      ; mass_storage.lua:25
0013    TSETS    3   2   7  ; "getActionsMenuTable"
0014    FNEW     3  10      ; mass_storage.lua:37
0015    TSETS    3   2   9  ; "start"
0016    UCLO     0 => 0017
0017 => RET1     2   2

