
main <./frontend/apps/filemanager/lib/md.lua:0,0> (183 instructions, 732 bytes at 0x7fe7f9c068d0)
0+ params, 55 slots, 0 upvalues, 51 locals, 40 constants, 25 functions
	1	[24]	GETGLOBAL	0 -1	; table
	2	[24]	GETTABLE 	0 0 -2	; "concat"
	3	[25]	GETGLOBAL	1 -3	; string
	4	[25]	GETTABLE 	1 1 -4	; "sub"
	5	[26]	GETGLOBAL	2 -3	; string
	6	[26]	GETTABLE 	2 2 -5	; "match"
	7	[27]	GETGLOBAL	3 -3	; string
	8	[27]	GETTABLE 	3 3 -6	; "format"
	9	[28]	GETGLOBAL	4 -3	; string
	10	[28]	GETTABLE 	4 4 -7	; "gmatch"
	11	[29]	GETGLOBAL	5 -3	; string
	12	[29]	GETTABLE 	5 5 -8	; "byte"
	13	[30]	GETGLOBAL	6 -3	; string
	14	[30]	GETTABLE 	6 6 -9	; "find"
	15	[31]	GETGLOBAL	7 -3	; string
	16	[31]	GETTABLE 	7 7 -10	; "lower"
	17	[32]	GETGLOBAL	8 -11	; tonumber
	18	[33]	GETGLOBAL	9 -12	; type
	19	[34]	GETGLOBAL	10 -13	; pcall
	20	[42]	CLOSURE  	11 0	; 0x7fe7f9c07140
	21	[42]	MOVE     	0 4
	22	[50]	CLOSURE  	12 1	; 0x7fe7f9c07290
	23	[60]	CLOSURE  	13 2	; 0x7fe7f9c07720
	24	[66]	NEWTABLE 	14 5 0
	25	[66]	LOADK    	15 -14	; "`"
	26	[66]	LOADK    	16 -15	; "__"
	27	[66]	LOADK    	17 -16	; "**"
	28	[66]	LOADK    	18 -17	; "_"
	29	[66]	LOADK    	19 -18	; "*"
	30	[66]	SETLIST  	14 5 1	; 1
	31	[81]	CLOSURE  	15 3	; 0x7fe7f9c06c00
	32	[81]	MOVE     	0 14
	33	[81]	MOVE     	0 6
	34	[95]	CLOSURE  	16 4	; 0x7fe7f9c06a90
	35	[95]	MOVE     	0 4
	36	[95]	MOVE     	0 2
	37	[95]	MOVE     	0 5
	38	[112]	CLOSURE  	17 5	; 0x7fe7f9c08c40
	39	[112]	MOVE     	0 4
	40	[112]	MOVE     	0 16
	41	[112]	MOVE     	0 2
	42	[112]	MOVE     	0 5
	43	[114]	NEWTABLE 	18 0 5
	44	[114]	SETTABLE 	18 -14 -19	; "`" "code"
	45	[114]	SETTABLE 	18 -15 -20	; "__" "strong"
	46	[114]	SETTABLE 	18 -16 -20	; "**" "strong"
	47	[114]	SETTABLE 	18 -17 -21	; "_" "em"
	48	[114]	SETTABLE 	18 -18 -21	; "*" "em"
	49	[149]	CLOSURE  	19 6	; 0x7fe7f9c07680
	50	[149]	MOVE     	0 15
	51	[149]	MOVE     	0 17
	52	[149]	MOVE     	0 1
	53	[149]	MOVE     	0 6
	54	[149]	MOVE     	0 19
	55	[149]	MOVE     	0 18
	56	[164]	CLOSURE  	20 7	; 0x7fe7f9c07ac0
	57	[164]	MOVE     	0 5
	58	[184]	CLOSURE  	21 8	; 0x7fe7f9c09740
	59	[184]	MOVE     	0 5
	60	[184]	MOVE     	0 1
	61	[189]	LOADK    	22 -22	; "\n"
	62	[195]	LOADK    	23 -23	; "^%s*$"
	63	[196]	LOADK    	24 -24	; "^%s*<>"
	64	[197]	LOADK    	25 -25	; "^%s*(%#+)%s*(.*)%#*$"
	65	[198]	LOADK    	26 -26	; "^%s?%s?%s?(-%s*-%s*-[%s-]*)$"
	66	[199]	LOADK    	27 -27	; "^%s?%s?%s?(*%s**%s**[%s*]*)$"
	67	[200]	LOADK    	28 -28	; "^%s?%s?%s?(_%s*_%s*_[%s_]*)$"
	68	[201]	LOADK    	29 -29	; "^%s*%`%`%`(.*)"
	69	[202]	LOADK    	30 -30	; "^%s*> (.*)$"
	70	[203]	LOADK    	31 -31	; "^%s*[%*%-] (.+)$"
	71	[204]	LOADK    	32 -32	; "^%s*%d+%. (.+)$"
	72	[205]	LOADK    	33 -33	; "^%s*%[(.*)%]%s*%:%s*(.*)"
	73	[208]	NEWTABLE 	34 11 0
	74	[209]	MOVE     	35 23
	75	[210]	MOVE     	36 24
	76	[211]	MOVE     	37 25
	77	[212]	MOVE     	38 26
	78	[213]	MOVE     	39 27
	79	[214]	MOVE     	40 28
	80	[215]	MOVE     	41 29
	81	[216]	MOVE     	42 30
	82	[217]	MOVE     	43 31
	83	[218]	MOVE     	44 32
	84	[220]	MOVE     	45 33
	85	[220]	SETLIST  	34 11 1	; 1
	86	[226]	CLOSURE  	35 9	; 0x7fe7f9c07c50
	87	[226]	MOVE     	0 34
	88	[226]	MOVE     	0 2
	89	[318]	CLOSURE  	36 10	; 0x7fe7f9c0a6a0
	90	[318]	MOVE     	0 2
	91	[318]	MOVE     	0 23
	92	[318]	MOVE     	0 24
	93	[318]	MOVE     	0 25
	94	[318]	MOVE     	0 19
	95	[318]	MOVE     	0 22
	96	[318]	MOVE     	0 26
	97	[318]	MOVE     	0 27
	98	[318]	MOVE     	0 28
	99	[318]	MOVE     	0 29
	100	[318]	MOVE     	0 20
	101	[318]	MOVE     	0 3
	102	[318]	MOVE     	0 7
	103	[318]	MOVE     	0 33
	104	[318]	MOVE     	0 35
	105	[324]	LOADNIL  	37 37
	106	[339]	CLOSURE  	38 11	; 0x7fe7f9c0aae0
	107	[339]	MOVE     	0 20
	108	[339]	MOVE     	0 21
	109	[339]	MOVE     	0 37
	110	[339]	MOVE     	0 12
	111	[352]	CLOSURE  	39 12	; 0x7fe7f9c0aec0
	112	[352]	MOVE     	0 2
	113	[352]	MOVE     	0 30
	114	[352]	MOVE     	0 38
	115	[352]	MOVE     	0 35
	116	[396]	CLOSURE  	40 13	; 0x7fe7f9c0baa0
	117	[396]	MOVE     	0 20
	118	[396]	MOVE     	0 2
	119	[396]	MOVE     	0 31
	120	[396]	MOVE     	0 32
	121	[396]	MOVE     	0 22
	122	[396]	MOVE     	0 19
	123	[396]	MOVE     	0 35
	124	[396]	MOVE     	0 23
	125	[396]	MOVE     	0 38
	126	[410]	CLOSURE  	37 14	; 0x7fe7f9c0c420
	127	[410]	MOVE     	0 13
	128	[410]	MOVE     	0 39
	129	[410]	MOVE     	0 40
	130	[398]	MOVE     	0 36
	131	[414]	CLOSURE  	41 15	; 0x7fe7f9c0b690
	132	[414]	MOVE     	0 37
	133	[414]	MOVE     	0 11
	134	[426]	CLOSURE  	42 16	; 0x7fe7f9c0c0c0
	135	[426]	MOVE     	0 3
	136	[426]	MOVE     	0 0
	137	[453]	CLOSURE  	43 17	; 0x7fe7f9c09c20
	138	[453]	MOVE     	0 7
	139	[453]	MOVE     	0 42
	140	[453]	MOVE     	0 3
	141	[453]	MOVE     	0 9
	142	[453]	MOVE     	0 43
	143	[483]	CLOSURE  	44 18	; 0x7fe7f9c0cc20
	144	[483]	MOVE     	0 37
	145	[483]	MOVE     	0 9
	146	[483]	MOVE     	0 3
	147	[483]	MOVE     	0 42
	148	[483]	MOVE     	0 43
	149	[483]	MOVE     	0 22
	150	[483]	MOVE     	0 0
	151	[496]	CLOSURE  	45 19	; 0x7fe7f9c0d4a0
	152	[496]	MOVE     	0 10
	153	[500]	CLOSURE  	46 20	; 0x7fe7f9c0d3e0
	154	[500]	MOVE     	0 45
	155	[500]	MOVE     	0 44
	156	[504]	CLOSURE  	47 21	; 0x7fe7f9c0d570
	157	[504]	MOVE     	0 45
	158	[504]	MOVE     	0 44
	159	[504]	MOVE     	0 12
	160	[508]	CLOSURE  	48 22	; 0x7fe7f9c0ddf0
	161	[508]	MOVE     	0 45
	162	[508]	MOVE     	0 44
	163	[508]	MOVE     	0 11
	164	[510]	NEWTABLE 	49 0 3
	165	[511]	SETTABLE 	49 -3 48	; "string" -
	166	[512]	SETTABLE 	49 -1 47	; "table" -
	167	[513]	SETTABLE 	49 -34 46	; "function" -
	168	[520]	CLOSURE  	50 23	; 0x7fe7f9c0e6d0
	169	[520]	MOVE     	0 49
	170	[520]	MOVE     	0 9
	171	[522]	GETGLOBAL	51 -35	; setmetatable
	172	[522]	NEWTABLE 	52 0 4
	173	[523]	SETTABLE 	52 -36 50	; "render" -
	174	[524]	SETTABLE 	52 -37 48	; "renderString" -
	175	[525]	SETTABLE 	52 -38 46	; "renderLineIterator" -
	176	[526]	SETTABLE 	52 -39 47	; "renderTable" -
	177	[527]	NEWTABLE 	53 0 1
	178	[530]	CLOSURE  	54 24	; 0x7fe7f9c0e930
	179	[530]	MOVE     	0 50
	180	[530]	SETTABLE 	53 -40 54	; "__call" -
	181	[522]	TAILCALL 	51 3 0
	182	[531]	RETURN   	51 0
	183	[531]	RETURN   	0 1

function <./frontend/apps/filemanager/lib/md.lua:40,42> (6 instructions, 24 bytes at 0x7fe7f9c07140)
1 param, 4 slots, 1 upvalue, 1 local, 1 constant, 0 functions
	1	[41]	GETUPVAL 	1 0	; gmatch
	2	[41]	MOVE     	2 0
	3	[41]	LOADK    	3 -1	; "([^\n\r]*)\r?\n?"
	4	[41]	TAILCALL 	1 3 0
	5	[41]	RETURN   	1 0
	6	[42]	RETURN   	0 1

function <./frontend/apps/filemanager/lib/md.lua:44,50> (6 instructions, 24 bytes at 0x7fe7f9c07290)
1 param, 3 slots, 0 upvalues, 2 locals, 1 constant, 1 function
	1	[45]	LOADK    	1 -1	; 0
	2	[49]	CLOSURE  	2 0	; 0x7fe7f9c06f20
	3	[49]	MOVE     	0 1
	4	[49]	MOVE     	0 0
	5	[49]	RETURN   	2 2
	6	[50]	RETURN   	0 1

function <./frontend/apps/filemanager/lib/md.lua:46,49> (8 instructions, 32 bytes at 0x7fe7f9c06f20)
0 params, 2 slots, 2 upvalues, 0 locals, 1 constant, 0 functions
	1	[47]	GETUPVAL 	0 0	; index
	2	[47]	ADD      	0 0 -1	; - 1
	3	[47]	SETUPVAL 	0 0	; index
	4	[48]	GETUPVAL 	0 1	; t
	5	[48]	GETUPVAL 	1 0	; index
	6	[48]	GETTABLE 	0 0 1
	7	[48]	RETURN   	0 2
	8	[49]	RETURN   	0 1

function <./frontend/apps/filemanager/lib/md.lua:52,60> (9 instructions, 36 bytes at 0x7fe7f9c07720)
1 param, 4 slots, 0 upvalues, 2 locals, 0 constants, 2 functions
	1	[53]	MOVE     	1 0
	2	[53]	CALL     	1 1 2
	3	[57]	CLOSURE  	2 0	; 0x7fe7f9c07890
	4	[57]	MOVE     	0 1
	5	[57]	MOVE     	0 0
	6	[59]	CLOSURE  	3 1	; 0x7fe7f9c07990
	7	[59]	MOVE     	0 1
	8	[59]	RETURN   	2 3
	9	[60]	RETURN   	0 1

function <./frontend/apps/filemanager/lib/md.lua:54,57> (6 instructions, 24 bytes at 0x7fe7f9c07890)
0 params, 2 slots, 2 upvalues, 0 locals, 0 constants, 0 functions
	1	[55]	GETUPVAL 	0 1	; linestream
	2	[55]	CALL     	0 1 2
	3	[55]	SETUPVAL 	0 0	; bufferedLine
	4	[56]	GETUPVAL 	0 0	; bufferedLine
	5	[56]	RETURN   	0 2
	6	[57]	RETURN   	0 1

function <./frontend/apps/filemanager/lib/md.lua:57,59> (3 instructions, 12 bytes at 0x7fe7f9c07990)
0 params, 2 slots, 1 upvalue, 0 locals, 0 constants, 0 functions
	1	[58]	GETUPVAL 	0 0	; bufferedLine
	2	[58]	RETURN   	0 2
	3	[59]	RETURN   	0 1

function <./frontend/apps/filemanager/lib/md.lua:67,81> (33 instructions, 132 bytes at 0x7fe7f9c06c00)
3 params, 15 slots, 2 upvalues, 12 locals, 2 constants, 0 functions
	1	[69]	DIV      	4 -2 -1	; 1 0
	2	[70]	DIV      	5 -2 -1	; 1 0
	3	[71]	TEST     	2 0 1
	4	[71]	JMP      	1	; to 6
	5	[71]	LEN      	2 0
	6	[72]	LOADK    	6 -2	; 1
	7	[72]	GETUPVAL 	7 0	; lineDelimiters
	8	[72]	LEN      	7 7
	9	[72]	LOADK    	8 -2	; 1
	10	[72]	FORPREP  	6 17	; to 28
	11	[73]	GETUPVAL 	10 1	; find
	12	[73]	MOVE     	11 0
	13	[73]	GETUPVAL 	12 0	; lineDelimiters
	14	[73]	GETTABLE 	12 12 9
	15	[73]	MOVE     	13 1
	16	[73]	LOADBOOL 	14 1 0
	17	[73]	CALL     	10 5 3
	18	[74]	TEST     	10 0 0
	19	[74]	JMP      	8	; to 28
	20	[74]	LT       	0 10 4
	21	[74]	JMP      	6	; to 28
	22	[74]	LE       	0 10 2
	23	[74]	JMP      	4	; to 28
	24	[75]	MOVE     	4 10
	25	[76]	MOVE     	5 11
	26	[77]	GETUPVAL 	12 0	; lineDelimiters
	27	[77]	GETTABLE 	3 12 9
	28	[72]	FORLOOP  	6 -18	; to 11
	29	[80]	MOVE     	6 3
	30	[80]	MOVE     	7 4
	31	[80]	MOVE     	8 5
	32	[80]	RETURN   	6 4
	33	[81]	RETURN   	0 1

function <./frontend/apps/filemanager/lib/md.lua:83,95> (52 instructions, 208 bytes at 0x7fe7f9c06a90)
2 params, 13 slots, 3 upvalues, 9 locals, 9 constants, 0 functions
	1	[84]	LOADBOOL 	2 1 0
	2	[85]	GETUPVAL 	3 0	; gmatch
	3	[85]	MOVE     	4 0
	4	[85]	LOADK    	5 -1	; "(.*)%[(.*)%](.*)"
	5	[85]	CALL     	3 3 4
	6	[85]	JMP      	38	; to 45
	7	[86]	TEST     	2 0 0
	8	[86]	JMP      	8	; to 17
	9	[86]	LEN      	9 1
	10	[86]	ADD      	9 9 -2	; - 1
	11	[86]	GETUPVAL 	10 1	; match
	12	[86]	MOVE     	11 6
	13	[86]	LOADK    	12 -3	; "^(.-)!?$"
	14	[86]	CALL     	10 3 2
	15	[86]	SETTABLE 	1 9 10
	16	[86]	LOADBOOL 	2 0 0
	17	[87]	GETUPVAL 	9 2	; byte
	18	[87]	MOVE     	10 6
	19	[87]	LEN      	11 6
	20	[87]	CALL     	9 3 2
	21	[87]	GETUPVAL 	10 2	; byte
	22	[87]	LOADK    	11 -4	; "!"
	23	[87]	CALL     	10 2 2
	24	[87]	EQ       	0 9 10
	25	[87]	JMP      	9	; to 35
	26	[88]	LEN      	9 1
	27	[88]	ADD      	9 9 -2	; - 1
	28	[88]	NEWTABLE 	10 0 2
	29	[88]	SETTABLE 	10 -5 -6	; "type" "img"
	30	[88]	NEWTABLE 	11 0 1
	31	[88]	SETTABLE 	11 -8 7	; "alt" -
	32	[88]	SETTABLE 	10 -7 11	; "attributes" -
	33	[88]	SETTABLE 	1 9 10
	34	[88]	JMP      	7	; to 42
	35	[90]	LEN      	9 1
	36	[90]	ADD      	9 9 -2	; - 1
	37	[90]	NEWTABLE 	10 1 1
	38	[90]	MOVE     	11 7
	39	[90]	SETTABLE 	10 -5 -9	; "type" "a"
	40	[90]	SETLIST  	10 1 1	; 1
	41	[90]	SETTABLE 	1 9 10
	42	[92]	LEN      	9 1
	43	[92]	ADD      	9 9 -2	; - 1
	44	[92]	SETTABLE 	1 9 8
	45	[85]	TFORLOOP 	3 3
	46	[92]	JMP      	-40	; to 7
	47	[94]	TEST     	2 0 0
	48	[94]	JMP      	3	; to 52
	49	[94]	LEN      	3 1
	50	[94]	ADD      	3 3 -2	; - 1
	51	[94]	SETTABLE 	1 3 0
	52	[95]	RETURN   	0 1

function <./frontend/apps/filemanager/lib/md.lua:97,112> (59 instructions, 236 bytes at 0x7fe7f9c08c40)
2 params, 14 slots, 4 upvalues, 10 locals, 13 constants, 0 functions
	1	[98]	LOADBOOL 	2 1 0
	2	[99]	GETUPVAL 	3 0	; gmatch
	3	[99]	MOVE     	4 0
	4	[99]	LOADK    	5 -1	; "(.*)%[(.*)%]%((.*)%)(.*)"
	5	[99]	CALL     	3 3 4
	6	[99]	JMP      	44	; to 51
	7	[100]	TEST     	2 0 0
	8	[100]	JMP      	8	; to 17
	9	[100]	GETUPVAL 	10 1	; externalLinkEscape
	10	[100]	GETUPVAL 	11 2	; match
	11	[100]	MOVE     	12 6
	12	[100]	LOADK    	13 -2	; "^(.-)!?$"
	13	[100]	CALL     	11 3 2
	14	[100]	MOVE     	12 1
	15	[100]	CALL     	10 3 1
	16	[100]	LOADBOOL 	2 0 0
	17	[101]	GETUPVAL 	10 3	; byte
	18	[101]	MOVE     	11 6
	19	[101]	LEN      	12 6
	20	[101]	CALL     	10 3 2
	21	[101]	GETUPVAL 	11 3	; byte
	22	[101]	LOADK    	12 -3	; "!"
	23	[101]	CALL     	11 2 2
	24	[101]	EQ       	0 10 11
	25	[101]	JMP      	11	; to 37
	26	[102]	LEN      	10 1
	27	[102]	ADD      	10 10 -4	; - 1
	28	[102]	NEWTABLE 	11 0 3
	29	[102]	SETTABLE 	11 -5 -6	; "type" "img"
	30	[102]	NEWTABLE 	12 0 2
	31	[103]	SETTABLE 	12 -8 8	; "src" -
	32	[104]	SETTABLE 	12 -9 7	; "alt" -
	33	[105]	SETTABLE 	11 -7 12	; "attributes" -
	34	[105]	SETTABLE 	11 -10 -11	; "noclose" true
	35	[105]	SETTABLE 	1 10 11
	36	[105]	JMP      	10	; to 47
	37	[107]	LEN      	10 1
	38	[107]	ADD      	10 10 -4	; - 1
	39	[107]	NEWTABLE 	11 1 2
	40	[107]	MOVE     	12 7
	41	[107]	SETTABLE 	11 -5 -12	; "type" "a"
	42	[107]	NEWTABLE 	13 0 1
	43	[107]	SETTABLE 	13 -13 8	; "href" -
	44	[107]	SETTABLE 	11 -7 13	; "attributes" -
	45	[107]	SETLIST  	11 1 1	; 1
	46	[107]	SETTABLE 	1 10 11
	47	[109]	GETUPVAL 	10 1	; externalLinkEscape
	48	[109]	MOVE     	11 9
	49	[109]	MOVE     	12 1
	50	[109]	CALL     	10 3 1
	51	[99]	TFORLOOP 	3 4
	52	[109]	JMP      	-46	; to 7
	53	[111]	TEST     	2 0 0
	54	[111]	JMP      	4	; to 59
	55	[111]	GETUPVAL 	3 1	; externalLinkEscape
	56	[111]	MOVE     	4 0
	57	[111]	MOVE     	5 1
	58	[111]	CALL     	3 3 1
	59	[112]	RETURN   	0 1

function <./frontend/apps/filemanager/lib/md.lua:115,149> (80 instructions, 320 bytes at 0x7fe7f9c07680)
3 params, 16 slots, 6 upvalues, 11 locals, 4 constants, 0 functions
	1	[116]	TESTSET  	3 1 1
	2	[116]	JMP      	1	; to 4
	3	[116]	LOADK    	3 -1	; 1
	4	[116]	TEST     	2 0 1
	5	[116]	JMP      	1	; to 7
	6	[116]	LEN      	2 0
	7	[116]	MOVE     	1 3
	8	[117]	MOVE     	3 1
	9	[118]	NEWTABLE 	4 0 0
	10	[120]	GETUPVAL 	5 0	; findDelim
	11	[120]	MOVE     	6 0
	12	[120]	MOVE     	7 3
	13	[120]	MOVE     	8 2
	14	[120]	CALL     	5 4 4
	15	[121]	TEST     	5 0 1
	16	[121]	JMP      	9	; to 26
	17	[122]	GETUPVAL 	8 1	; linkEscape
	18	[122]	GETUPVAL 	9 2	; sub
	19	[122]	MOVE     	10 0
	20	[122]	MOVE     	11 3
	21	[122]	MOVE     	12 2
	22	[122]	CALL     	9 4 2
	23	[122]	MOVE     	10 4
	24	[122]	CALL     	8 3 1
	25	[123]	JMP      	53	; to 79
	26	[125]	LT       	0 3 6
	27	[125]	JMP      	8	; to 36
	28	[126]	GETUPVAL 	8 1	; linkEscape
	29	[126]	GETUPVAL 	9 2	; sub
	30	[126]	MOVE     	10 0
	31	[126]	MOVE     	11 3
	32	[126]	SUB      	12 6 -1	; - 1
	33	[126]	CALL     	9 4 2
	34	[126]	MOVE     	10 4
	35	[126]	CALL     	8 3 1
	36	[128]	GETUPVAL 	8 3	; find
	37	[128]	MOVE     	9 0
	38	[128]	MOVE     	10 5
	39	[128]	ADD      	11 7 -1	; - 1
	40	[128]	LOADBOOL 	12 1 0
	41	[128]	CALL     	8 5 3
	42	[129]	TEST     	8 0 0
	43	[129]	JMP      	27	; to 71
	44	[130]	EQ       	0 5 -2	; - "`"
	45	[130]	JMP      	12	; to 58
	46	[131]	LEN      	10 4
	47	[131]	ADD      	10 10 -1	; - 1
	48	[131]	NEWTABLE 	11 1 1
	49	[132]	GETUPVAL 	12 2	; sub
	50	[132]	MOVE     	13 0
	51	[132]	ADD      	14 7 -1	; - 1
	52	[132]	SUB      	15 8 -1	; - 1
	53	[132]	CALL     	12 4 2
	54	[133]	SETTABLE 	11 -3 -4	; "type" "code"
	55	[134]	SETLIST  	11 1 1	; 1
	56	[134]	SETTABLE 	4 10 11
	57	[134]	JMP      	11	; to 69
	58	[136]	GETUPVAL 	10 4	; lineRead
	59	[136]	MOVE     	11 0
	60	[136]	ADD      	12 7 -1	; - 1
	61	[136]	SUB      	13 8 -1	; - 1
	62	[136]	CALL     	10 4 2
	63	[137]	GETUPVAL 	11 5	; lineDeimiterNames
	64	[137]	GETTABLE 	11 11 5
	65	[137]	SETTABLE 	10 -3 11	; "type" -
	66	[138]	LEN      	11 4
	67	[138]	ADD      	11 11 -1	; - 1
	68	[138]	SETTABLE 	4 11 10
	69	[140]	ADD      	3 9 -1	; - 1
	70	[140]	JMP      	-61	; to 10
	71	[142]	LEN      	10 4
	72	[142]	ADD      	10 10 -1	; - 1
	73	[142]	NEWTABLE 	11 1 0
	74	[144]	MOVE     	12 5
	75	[144]	SETLIST  	11 1 1	; 1
	76	[144]	SETTABLE 	4 10 11
	77	[145]	ADD      	3 7 -1	; - 1
	78	[146]	JMP      	-69	; to 10
	79	[148]	RETURN   	4 2
	80	[149]	RETURN   	0 1

function <./frontend/apps/filemanager/lib/md.lua:151,164> (32 instructions, 128 bytes at 0x7fe7f9c07ac0)
1 param, 9 slots, 1 upvalue, 7 locals, 6 constants, 0 functions
	1	[152]	LOADK    	1 -1	; 0
	2	[153]	LOADK    	2 -2	; 1
	3	[153]	LEN      	3 0
	4	[153]	LOADK    	4 -2	; 1
	5	[153]	FORPREP  	2 24	; to 30
	6	[154]	GETUPVAL 	6 0	; byte
	7	[154]	MOVE     	7 0
	8	[154]	MOVE     	8 5
	9	[154]	CALL     	6 3 2
	10	[155]	GETUPVAL 	7 0	; byte
	11	[155]	LOADK    	8 -3	; " "
	12	[155]	CALL     	7 2 2
	13	[155]	EQ       	1 6 7
	14	[155]	JMP      	5	; to 20
	15	[155]	GETUPVAL 	7 0	; byte
	16	[155]	LOADK    	8 -4	; ">"
	17	[155]	CALL     	7 2 2
	18	[155]	EQ       	0 6 7
	19	[155]	JMP      	2	; to 22
	20	[156]	ADD      	1 1 -2	; - 1
	21	[156]	JMP      	8	; to 30
	22	[157]	GETUPVAL 	7 0	; byte
	23	[157]	LOADK    	8 -5	; "\t"
	24	[157]	CALL     	7 2 2
	25	[157]	EQ       	0 6 7
	26	[157]	JMP      	4	; to 31
	27	[158]	ADD      	1 1 -6	; - 4
	28	[158]	JMP      	1	; to 30
	29	[160]	JMP      	1	; to 31
	30	[153]	FORLOOP  	2 -25	; to 6
	31	[163]	RETURN   	1 2
	32	[164]	RETURN   	0 1

function <./frontend/apps/filemanager/lib/md.lua:166,184> (72 instructions, 288 bytes at 0x7fe7f9c09740)
3 params, 15 slots, 2 upvalues, 13 locals, 7 constants, 0 functions
	1	[167]	LOADK    	3 -1	; -1
	2	[168]	LOADK    	4 -2	; 1
	3	[168]	LEN      	5 0
	4	[168]	LOADK    	6 -2	; 1
	5	[168]	FORPREP  	4 65	; to 71
	6	[169]	GETUPVAL 	8 0	; byte
	7	[169]	MOVE     	9 0
	8	[169]	MOVE     	10 7
	9	[169]	CALL     	8 3 2
	10	[169]	GETUPVAL 	9 0	; byte
	11	[169]	LOADK    	10 -3	; "\t"
	12	[169]	CALL     	9 2 2
	13	[169]	EQ       	0 8 9
	14	[169]	JMP      	2	; to 17
	15	[170]	ADD      	3 3 -4	; - 4
	16	[170]	JMP      	26	; to 43
	17	[171]	GETUPVAL 	8 0	; byte
	18	[171]	MOVE     	9 0
	19	[171]	MOVE     	10 7
	20	[171]	CALL     	8 3 2
	21	[171]	GETUPVAL 	9 0	; byte
	22	[171]	LOADK    	10 -5	; " "
	23	[171]	CALL     	9 2 2
	24	[171]	EQ       	1 8 9
	25	[171]	JMP      	9	; to 35
	26	[171]	GETUPVAL 	8 0	; byte
	27	[171]	MOVE     	9 0
	28	[171]	MOVE     	10 7
	29	[171]	CALL     	8 3 2
	30	[171]	GETUPVAL 	9 0	; byte
	31	[171]	LOADK    	10 -6	; ">"
	32	[171]	CALL     	9 2 2
	33	[171]	EQ       	0 8 9
	34	[171]	JMP      	2	; to 37
	35	[172]	ADD      	3 3 -2	; - 1
	36	[172]	JMP      	6	; to 43
	37	[174]	GETUPVAL 	8 1	; sub
	38	[174]	MOVE     	9 0
	39	[174]	MOVE     	10 7
	40	[174]	LOADK    	11 -1	; -1
	41	[174]	TAILCALL 	8 4 0
	42	[174]	RETURN   	8 0
	43	[176]	EQ       	0 3 1
	44	[176]	JMP      	7	; to 52
	45	[177]	GETUPVAL 	8 1	; sub
	46	[177]	MOVE     	9 0
	47	[177]	MOVE     	10 7
	48	[177]	LOADK    	11 -1	; -1
	49	[177]	TAILCALL 	8 4 0
	50	[177]	RETURN   	8 0
	51	[177]	JMP      	19	; to 71
	52	[178]	LT       	0 1 3
	53	[178]	JMP      	17	; to 71
	54	[179]	LOADK    	8 -7	; ""
	55	[180]	LOADK    	9 -2	; 1
	56	[180]	SUB      	10 3 1
	57	[180]	LOADK    	11 -2	; 1
	58	[180]	FORPREP  	9 3	; to 62
	59	[180]	MOVE     	13 8
	60	[180]	LOADK    	14 -5	; " "
	61	[180]	CONCAT   	8 13 14
	62	[180]	FORLOOP  	9 -4	; to 59
	63	[181]	MOVE     	9 8
	64	[181]	GETUPVAL 	10 1	; sub
	65	[181]	MOVE     	11 0
	66	[181]	MOVE     	12 7
	67	[181]	LOADK    	13 -1	; -1
	68	[181]	CALL     	10 4 2
	69	[181]	CONCAT   	9 9 10
	70	[181]	RETURN   	9 2
	71	[168]	FORLOOP  	4 -66	; to 6
	72	[184]	RETURN   	0 1

function <./frontend/apps/filemanager/lib/md.lua:222,226> (17 instructions, 68 bytes at 0x7fe7f9c07c50)
1 param, 8 slots, 2 upvalues, 5 locals, 1 constant, 0 functions
	1	[223]	LOADK    	1 -1	; 1
	2	[223]	GETUPVAL 	2 0	; PATTERNS
	3	[223]	LEN      	2 2
	4	[223]	LOADK    	3 -1	; 1
	5	[223]	FORPREP  	1 10	; to 16
	6	[224]	GETUPVAL 	5 1	; match
	7	[224]	MOVE     	6 0
	8	[224]	GETUPVAL 	7 0	; PATTERNS
	9	[224]	GETTABLE 	7 7 4
	10	[224]	CALL     	5 3 2
	11	[224]	TEST     	5 0 0
	12	[224]	JMP      	3	; to 16
	13	[224]	GETUPVAL 	5 0	; PATTERNS
	14	[224]	GETTABLE 	5 5 4
	15	[224]	RETURN   	5 2
	16	[223]	FORLOOP  	1 -11	; to 6
	17	[226]	RETURN   	0 1

function <./frontend/apps/filemanager/lib/md.lua:232,318> (227 instructions, 908 bytes at 0x7fe7f9c0a6a0)
4 params, 15 slots, 15 upvalues, 15 locals, 19 constants, 0 functions
	1	[234]	MOVE     	4 1
	2	[234]	CALL     	4 1 2
	3	[235]	TEST     	4 0 1
	4	[235]	JMP      	1	; to 6
	5	[235]	RETURN   	0 1
	6	[238]	GETUPVAL 	5 0	; match
	7	[238]	MOVE     	6 4
	8	[238]	GETUPVAL 	7 1	; PATTERN_EMPTY
	9	[238]	CALL     	5 3 2
	10	[238]	TEST     	5 0 1
	11	[238]	JMP      	6	; to 18
	12	[238]	GETUPVAL 	5 0	; match
	13	[238]	MOVE     	6 4
	14	[238]	GETUPVAL 	7 2	; PATTERN_COMMENT
	15	[238]	CALL     	5 3 2
	16	[238]	TEST     	5 0 0
	17	[238]	JMP      	3	; to 21
	18	[239]	MOVE     	5 0
	19	[239]	TAILCALL 	5 1 0
	20	[239]	RETURN   	5 0
	21	[243]	GETUPVAL 	5 0	; match
	22	[243]	MOVE     	6 4
	23	[243]	GETUPVAL 	7 3	; PATTERN_HEADER
	24	[243]	CALL     	5 3 3
	25	[244]	TEST     	5 0 0
	26	[244]	JMP      	19	; to 46
	27	[245]	LEN      	7 2
	28	[245]	ADD      	7 7 -1	; - 1
	29	[245]	NEWTABLE 	8 1 1
	30	[246]	GETUPVAL 	9 4	; lineRead
	31	[246]	MOVE     	10 6
	32	[246]	CALL     	9 2 2
	33	[247]	LOADK    	10 -3	; "h"
	34	[247]	LEN      	11 5
	35	[247]	CONCAT   	10 10 11
	36	[247]	SETTABLE 	8 -2 10	; "type" -
	37	[248]	SETLIST  	8 1 1	; 1
	38	[248]	SETTABLE 	2 7 8
	39	[249]	LEN      	7 2
	40	[249]	ADD      	7 7 -1	; - 1
	41	[249]	GETUPVAL 	8 5	; NEWLINE
	42	[249]	SETTABLE 	2 7 8
	43	[250]	MOVE     	7 0
	44	[250]	TAILCALL 	7 1 0
	45	[250]	RETURN   	7 0
	46	[254]	GETUPVAL 	7 0	; match
	47	[254]	MOVE     	8 4
	48	[254]	GETUPVAL 	9 6	; PATTERN_RULE1
	49	[254]	CALL     	7 3 2
	50	[254]	TEST     	7 0 1
	51	[254]	JMP      	12	; to 64
	52	[255]	GETUPVAL 	7 0	; match
	53	[255]	MOVE     	8 4
	54	[255]	GETUPVAL 	9 7	; PATTERN_RULE2
	55	[255]	CALL     	7 3 2
	56	[255]	TEST     	7 0 1
	57	[255]	JMP      	6	; to 64
	58	[256]	GETUPVAL 	7 0	; match
	59	[256]	MOVE     	8 4
	60	[256]	GETUPVAL 	9 8	; PATTERN_RULE3
	61	[256]	CALL     	7 3 2
	62	[256]	TEST     	7 0 0
	63	[256]	JMP      	13	; to 77
	64	[257]	LEN      	7 2
	65	[257]	ADD      	7 7 -1	; - 1
	66	[257]	NEWTABLE 	8 0 2
	67	[257]	SETTABLE 	8 -2 -4	; "type" "hr"
	68	[257]	SETTABLE 	8 -5 -6	; "noclose" true
	69	[257]	SETTABLE 	2 7 8
	70	[258]	LEN      	7 2
	71	[258]	ADD      	7 7 -1	; - 1
	72	[258]	GETUPVAL 	8 5	; NEWLINE
	73	[258]	SETTABLE 	2 7 8
	74	[259]	MOVE     	7 0
	75	[259]	TAILCALL 	7 1 0
	76	[259]	RETURN   	7 0
	77	[263]	GETUPVAL 	7 0	; match
	78	[263]	MOVE     	8 4
	79	[263]	GETUPVAL 	9 9	; PATTERN_CODEBLOCK
	80	[263]	CALL     	7 3 2
	81	[264]	TEST     	7 0 0
	82	[264]	JMP      	48	; to 131
	83	[265]	GETUPVAL 	8 10	; getIndentLevel
	84	[265]	MOVE     	9 4
	85	[265]	CALL     	8 2 2
	86	[266]	NEWTABLE 	9 0 1
	87	[267]	SETTABLE 	9 -2 -7	; "type" "code"
	88	[269]	LEN      	10 7
	89	[269]	LT       	0 -8 10	; 0 -
	90	[269]	JMP      	9	; to 100
	91	[270]	NEWTABLE 	10 0 1
	92	[271]	GETUPVAL 	11 11	; format
	93	[271]	LOADK    	12 -11	; "language-%s"
	94	[271]	GETUPVAL 	13 12	; lower
	95	[271]	MOVE     	14 7
	96	[271]	CALL     	13 2 0
	97	[271]	CALL     	11 0 2
	98	[271]	SETTABLE 	10 -10 11	; "class" -
	99	[272]	SETTABLE 	9 -9 10	; "attributes" -
	100	[274]	NEWTABLE 	10 0 2
	101	[275]	SETTABLE 	10 -2 -12	; "type" "pre"
	102	[276]	SETTABLE 	10 -1 9	; 1 -
	103	[278]	LEN      	11 2
	104	[278]	ADD      	11 11 -1	; - 1
	105	[278]	SETTABLE 	2 11 10
	106	[279]	GETUPVAL 	11 0	; match
	107	[279]	MOVE     	12 0
	108	[279]	CALL     	12 1 2
	109	[279]	GETUPVAL 	13 9	; PATTERN_CODEBLOCK
	110	[279]	CALL     	11 3 2
	111	[279]	TEST     	11 0 0
	112	[279]	JMP      	6	; to 119
	113	[279]	GETUPVAL 	11 10	; getIndentLevel
	114	[279]	MOVE     	12 1
	115	[279]	CALL     	12 1 0
	116	[279]	CALL     	11 0 2
	117	[279]	EQ       	1 11 8
	118	[279]	JMP      	9	; to 128
	119	[280]	LEN      	11 9
	120	[280]	ADD      	11 11 -1	; - 1
	121	[280]	MOVE     	12 1
	122	[280]	CALL     	12 1 2
	123	[280]	SETTABLE 	9 11 12
	124	[281]	LEN      	11 9
	125	[281]	ADD      	11 11 -1	; - 1
	126	[281]	SETTABLE 	9 11 -13	; - "\r\n"
	127	[281]	JMP      	-22	; to 106
	128	[283]	MOVE     	11 0
	129	[283]	TAILCALL 	11 1 0
	130	[283]	RETURN   	11 0
	131	[287]	GETUPVAL 	8 0	; match
	132	[287]	MOVE     	9 4
	133	[287]	GETUPVAL 	10 13	; PATTERN_LINKDEF
	134	[287]	CALL     	8 3 3
	135	[288]	TEST     	8 0 0
	136	[288]	JMP      	7	; to 144
	137	[289]	GETUPVAL 	10 12	; lower
	138	[289]	MOVE     	11 8
	139	[289]	CALL     	10 2 2
	140	[289]	SETTABLE 	3 10 9
	141	[290]	MOVE     	10 0
	142	[290]	TAILCALL 	10 1 0
	143	[290]	RETURN   	10 0
	144	[294]	MOVE     	10 0
	145	[294]	CALL     	10 1 2
	146	[295]	TEST     	10 0 0
	147	[295]	JMP      	19	; to 167
	148	[295]	GETUPVAL 	11 0	; match
	149	[295]	MOVE     	12 10
	150	[295]	LOADK    	13 -14	; "^%s*%=+$"
	151	[295]	CALL     	11 3 2
	152	[295]	TEST     	11 0 0
	153	[295]	JMP      	13	; to 167
	154	[296]	LEN      	11 2
	155	[296]	ADD      	11 11 -1	; - 1
	156	[296]	NEWTABLE 	12 1 1
	157	[296]	GETUPVAL 	13 4	; lineRead
	158	[296]	MOVE     	14 4
	159	[296]	CALL     	13 2 2
	160	[296]	SETTABLE 	12 -2 -15	; "type" "h1"
	161	[296]	SETLIST  	12 1 1	; 1
	162	[296]	SETTABLE 	2 11 12
	163	[297]	MOVE     	11 0
	164	[297]	TAILCALL 	11 1 0
	165	[297]	RETURN   	11 0
	166	[297]	JMP      	20	; to 187
	167	[298]	TEST     	10 0 0
	168	[298]	JMP      	18	; to 187
	169	[298]	GETUPVAL 	11 0	; match
	170	[298]	MOVE     	12 10
	171	[298]	LOADK    	13 -16	; "^%s*%-+$"
	172	[298]	CALL     	11 3 2
	173	[298]	TEST     	11 0 0
	174	[298]	JMP      	12	; to 187
	175	[299]	LEN      	11 2
	176	[299]	ADD      	11 11 -1	; - 1
	177	[299]	NEWTABLE 	12 1 1
	178	[299]	GETUPVAL 	13 4	; lineRead
	179	[299]	MOVE     	14 4
	180	[299]	CALL     	13 2 2
	181	[299]	SETTABLE 	12 -2 -17	; "type" "h2"
	182	[299]	SETLIST  	12 1 1	; 1
	183	[299]	SETTABLE 	2 11 12
	184	[300]	MOVE     	11 0
	185	[300]	TAILCALL 	11 1 0
	186	[300]	RETURN   	11 0
	187	[304]	NEWTABLE 	11 2 1
	188	[305]	GETUPVAL 	12 4	; lineRead
	189	[305]	MOVE     	13 4
	190	[305]	CALL     	12 2 2
	191	[305]	GETUPVAL 	13 5	; NEWLINE
	192	[306]	SETTABLE 	11 -2 -18	; "type" "p"
	193	[307]	SETLIST  	11 2 1	; 1
	194	[308]	LEN      	12 2
	195	[308]	ADD      	12 12 -1	; - 1
	196	[308]	SETTABLE 	2 12 11
	197	[309]	TEST     	10 0 0
	198	[309]	JMP      	19	; to 218
	199	[309]	GETUPVAL 	12 14	; isSpecialLine
	200	[309]	MOVE     	13 10
	201	[309]	CALL     	12 2 2
	202	[309]	TEST     	12 0 1
	203	[309]	JMP      	14	; to 218
	204	[310]	LEN      	12 11
	205	[310]	ADD      	12 12 -1	; - 1
	206	[310]	GETUPVAL 	13 4	; lineRead
	207	[310]	MOVE     	14 10
	208	[310]	CALL     	13 2 2
	209	[310]	SETTABLE 	11 12 13
	210	[311]	LEN      	12 11
	211	[311]	ADD      	12 12 -1	; - 1
	212	[311]	GETUPVAL 	13 5	; NEWLINE
	213	[311]	SETTABLE 	11 12 13
	214	[312]	MOVE     	12 0
	215	[312]	CALL     	12 1 2
	216	[312]	MOVE     	10 12
	217	[312]	JMP      	-21	; to 197
	218	[314]	LEN      	12 11
	219	[314]	SETTABLE 	11 12 -19	; - nil
	220	[315]	LEN      	12 2
	221	[315]	ADD      	12 12 -1	; - 1
	222	[315]	GETUPVAL 	13 5	; NEWLINE
	223	[315]	SETTABLE 	2 12 13
	224	[316]	MOVE     	12 1
	225	[316]	TAILCALL 	12 1 0
	226	[316]	RETURN   	12 0
	227	[318]	RETURN   	0 1

function <./frontend/apps/filemanager/lib/md.lua:326,339> (37 instructions, 148 bytes at 0x7fe7f9c0aae0)
4+ params, 13 slots, 4 upvalues, 9 locals, 1 constant, 0 functions
	1	[327]	NEWTABLE 	5 0 0
	2	[328]	MOVE     	6 1
	3	[328]	CALL     	6 1 2
	4	[329]	GETUPVAL 	7 0	; getIndentLevel
	5	[329]	MOVE     	8 6
	6	[329]	CALL     	7 2 2
	7	[331]	LEN      	8 5
	8	[331]	ADD      	8 8 -1	; - 1
	9	[331]	GETUPVAL 	9 1	; stripIndent
	10	[331]	MOVE     	10 6
	11	[331]	MOVE     	11 7
	12	[331]	CALL     	9 3 2
	13	[331]	SETTABLE 	5 8 9
	14	[332]	MOVE     	8 0
	15	[332]	CALL     	8 1 2
	16	[332]	MOVE     	6 8
	17	[333]	TEST     	6 0 1
	18	[333]	JMP      	1	; to 20
	19	[333]	JMP      	8	; to 28
	20	[334]	MOVE     	8 3
	21	[334]	MOVE     	9 6
	22	[334]	VARARG   	10 0
	23	[334]	CALL     	8 0 2
	24	[334]	TEST     	8 0 0
	25	[334]	JMP      	-19	; to 7
	26	[334]	JMP      	1	; to 28
	27	[334]	JMP      	-21	; to 7
	28	[336]	NEWTABLE 	8 0 0
	29	[337]	GETUPVAL 	9 2	; readLineStream
	30	[337]	GETUPVAL 	10 3	; tableLineStream
	31	[337]	MOVE     	11 5
	32	[337]	CALL     	10 2 2
	33	[337]	MOVE     	11 8
	34	[337]	MOVE     	12 2
	35	[337]	CALL     	9 4 1
	36	[338]	RETURN   	8 2
	37	[339]	RETURN   	0 1

function <./frontend/apps/filemanager/lib/md.lua:341,352> (24 instructions, 96 bytes at 0x7fe7f9c0aec0)
4 params, 10 slots, 4 upvalues, 6 locals, 3 constants, 1 function
	1	[342]	MOVE     	4 1
	2	[342]	CALL     	4 1 2
	3	[343]	GETUPVAL 	5 0	; match
	4	[343]	MOVE     	6 4
	5	[343]	GETUPVAL 	7 1	; PATTERN_BLOCKQUOTE
	6	[343]	CALL     	5 3 2
	7	[343]	TEST     	5 0 0
	8	[343]	JMP      	15	; to 24
	9	[344]	GETUPVAL 	5 2	; readFragment
	10	[344]	MOVE     	6 0
	11	[344]	MOVE     	7 1
	12	[344]	MOVE     	8 3
	13	[347]	CLOSURE  	9 0	; 0x7fe7f9c0b2e0
	14	[347]	GETUPVAL 	0 3	; isSpecialLine
	15	[347]	GETUPVAL 	0 1	; PATTERN_BLOCKQUOTE
	16	[344]	CALL     	5 5 2
	17	[348]	SETTABLE 	5 -1 -2	; "type" "blockquote"
	18	[349]	LEN      	6 2
	19	[349]	ADD      	6 6 -3	; - 1
	20	[349]	SETTABLE 	2 6 5
	21	[350]	MOVE     	6 1
	22	[350]	TAILCALL 	6 1 0
	23	[350]	RETURN   	6 0
	24	[352]	RETURN   	0 1

function <./frontend/apps/filemanager/lib/md.lua:344,347> (12 instructions, 48 bytes at 0x7fe7f9c0b2e0)
1 param, 3 slots, 2 upvalues, 2 locals, 0 constants, 0 functions
	1	[345]	GETUPVAL 	1 0	; isSpecialLine
	2	[345]	MOVE     	2 0
	3	[345]	CALL     	1 2 2
	4	[346]	TESTSET  	2 1 0
	5	[346]	JMP      	5	; to 11
	6	[346]	GETUPVAL 	2 1	; PATTERN_BLOCKQUOTE
	7	[346]	EQ       	0 1 2
	8	[346]	JMP      	1	; to 10
	9	[346]	LOADBOOL 	2 0 1
	10	[346]	LOADBOOL 	2 1 0
	11	[346]	RETURN   	2 2
	12	[347]	RETURN   	0 1

function <./frontend/apps/filemanager/lib/md.lua:354,396> (132 instructions, 528 bytes at 0x7fe7f9c0baa0)
5 params, 16 slots, 9 upvalues, 12 locals, 5 constants, 1 function
	1	[355]	MOVE     	5 1
	2	[355]	CALL     	5 1 2
	3	[355]	TEST     	5 0 1
	4	[355]	JMP      	1	; to 6
	5	[355]	RETURN   	0 1
	6	[356]	TEST     	4 0 0
	7	[356]	JMP      	7	; to 15
	8	[356]	GETUPVAL 	5 0	; getIndentLevel
	9	[356]	MOVE     	6 1
	10	[356]	CALL     	6 1 0
	11	[356]	CALL     	5 0 2
	12	[356]	EQ       	1 5 4
	13	[356]	JMP      	1	; to 15
	14	[356]	RETURN   	0 1
	15	[357]	GETUPVAL 	5 1	; match
	16	[357]	MOVE     	6 1
	17	[357]	CALL     	6 1 2
	18	[357]	GETUPVAL 	7 2	; PATTERN_ULIST
	19	[357]	CALL     	5 3 2
	20	[357]	TEST     	5 0 0
	21	[357]	JMP      	3	; to 25
	22	[357]	GETUPVAL 	5 2	; PATTERN_ULIST
	23	[357]	TEST     	5 0 1
	24	[357]	JMP      	8	; to 33
	25	[358]	GETUPVAL 	5 1	; match
	26	[358]	MOVE     	6 1
	27	[358]	CALL     	6 1 2
	28	[358]	GETUPVAL 	7 3	; PATTERN_OLIST
	29	[358]	CALL     	5 3 2
	30	[358]	TEST     	5 0 0
	31	[358]	JMP      	1	; to 33
	32	[358]	GETUPVAL 	5 3	; PATTERN_OLIST
	33	[359]	TEST     	5 0 1
	34	[359]	JMP      	1	; to 36
	35	[359]	RETURN   	0 1
	36	[360]	MOVE     	6 5
	37	[361]	MOVE     	7 1
	38	[361]	CALL     	7 1 2
	39	[362]	GETUPVAL 	8 0	; getIndentLevel
	40	[362]	MOVE     	9 7
	41	[362]	CALL     	8 2 2
	42	[363]	NEWTABLE 	9 0 1
	43	[364]	GETUPVAL 	10 2	; PATTERN_ULIST
	44	[364]	EQ       	0 5 10
	45	[364]	JMP      	3	; to 49
	46	[364]	LOADK    	10 -2	; "ul"
	47	[364]	TEST     	10 0 1
	48	[364]	JMP      	1	; to 50
	49	[364]	LOADK    	10 -3	; "ol"
	50	[364]	SETTABLE 	9 -1 10	; "type" -
	51	[366]	LEN      	10 2
	52	[366]	ADD      	10 10 -4	; - 1
	53	[366]	SETTABLE 	2 10 9
	54	[367]	GETUPVAL 	10 4	; NEWLINE
	55	[367]	SETTABLE 	9 -4 10	; 1 -
	56	[368]	EQ       	0 6 5
	57	[368]	JMP      	63	; to 121
	58	[369]	LEN      	10 9
	59	[369]	ADD      	10 10 -4	; - 1
	60	[369]	NEWTABLE 	11 1 1
	61	[370]	GETUPVAL 	12 5	; lineRead
	62	[370]	GETUPVAL 	13 1	; match
	63	[370]	MOVE     	14 7
	64	[370]	MOVE     	15 6
	65	[370]	CALL     	13 3 0
	66	[370]	CALL     	12 0 2
	67	[371]	SETTABLE 	11 -1 -5	; "type" "li"
	68	[372]	SETLIST  	11 1 1	; 1
	69	[372]	SETTABLE 	9 10 11
	70	[373]	MOVE     	10 0
	71	[373]	CALL     	10 1 2
	72	[373]	MOVE     	7 10
	73	[374]	TEST     	7 0 1
	74	[374]	JMP      	1	; to 76
	75	[374]	JMP      	45	; to 121
	76	[375]	GETUPVAL 	10 6	; isSpecialLine
	77	[375]	MOVE     	11 7
	78	[375]	CALL     	10 2 2
	79	[375]	MOVE     	6 10
	80	[376]	GETUPVAL 	10 7	; PATTERN_EMPTY
	81	[376]	EQ       	1 6 10
	82	[376]	JMP      	-27	; to 56
	83	[377]	LEN      	10 9
	84	[377]	ADD      	10 10 -4	; - 1
	85	[377]	GETUPVAL 	11 4	; NEWLINE
	86	[377]	SETTABLE 	9 10 11
	87	[378]	GETUPVAL 	10 0	; getIndentLevel
	88	[378]	MOVE     	11 7
	89	[378]	CALL     	10 2 2
	90	[379]	LT       	0 10 8
	91	[379]	JMP      	1	; to 93
	92	[379]	JMP      	28	; to 121
	93	[380]	LT       	0 8 10
	94	[380]	JMP      	24	; to 119
	95	[381]	GETUPVAL 	11 8	; readFragment
	96	[381]	MOVE     	12 0
	97	[381]	MOVE     	13 1
	98	[381]	MOVE     	14 3
	99	[385]	CLOSURE  	15 0	; 0x7fe7f9c0bec0
	100	[385]	GETUPVAL 	0 6	; isSpecialLine
	101	[385]	GETUPVAL 	0 7	; PATTERN_EMPTY
	102	[385]	GETUPVAL 	0 0	; getIndentLevel
	103	[385]	MOVE     	0 10
	104	[381]	CALL     	11 5 2
	105	[386]	LEN      	12 9
	106	[386]	ADD      	12 12 -4	; - 1
	107	[386]	SETTABLE 	9 12 11
	108	[387]	MOVE     	12 1
	109	[387]	CALL     	12 1 2
	110	[387]	MOVE     	7 12
	111	[388]	TEST     	7 0 1
	112	[388]	JMP      	2	; to 115
	113	[388]	CLOSE    	10
	114	[388]	JMP      	6	; to 121
	115	[389]	GETUPVAL 	12 6	; isSpecialLine
	116	[389]	MOVE     	13 7
	117	[389]	CALL     	12 2 2
	118	[389]	MOVE     	6 12
	119	[390]	CLOSE    	10
	120	[391]	JMP      	-65	; to 56
	121	[393]	LEN      	10 9
	122	[393]	ADD      	10 10 -4	; - 1
	123	[393]	GETUPVAL 	11 4	; NEWLINE
	124	[393]	SETTABLE 	9 10 11
	125	[394]	LEN      	10 2
	126	[394]	ADD      	10 10 -4	; - 1
	127	[394]	GETUPVAL 	11 4	; NEWLINE
	128	[394]	SETTABLE 	2 10 11
	129	[395]	MOVE     	10 1
	130	[395]	TAILCALL 	10 1 0
	131	[395]	RETURN   	10 0
	132	[396]	RETURN   	0 1

function <./frontend/apps/filemanager/lib/md.lua:381,385> (20 instructions, 80 bytes at 0x7fe7f9c0bec0)
1 param, 4 slots, 4 upvalues, 2 locals, 0 constants, 0 functions
	1	[382]	TEST     	0 0 1
	2	[382]	JMP      	2	; to 5
	3	[382]	LOADBOOL 	1 1 0
	4	[382]	RETURN   	1 2
	5	[383]	GETUPVAL 	1 0	; isSpecialLine
	6	[383]	MOVE     	2 0
	7	[383]	CALL     	1 2 2
	8	[384]	GETUPVAL 	2 1	; PATTERN_EMPTY
	9	[384]	EQ       	1 1 2
	10	[384]	JMP      	6	; to 17
	11	[384]	GETUPVAL 	2 2	; getIndentLevel
	12	[384]	MOVE     	3 0
	13	[384]	CALL     	2 2 2
	14	[384]	GETUPVAL 	3 3	; i
	15	[384]	LT       	1 2 3
	16	[384]	JMP      	1	; to 18
	17	[384]	LOADBOOL 	2 0 1
	18	[384]	LOADBOOL 	2 1 0
	19	[384]	RETURN   	2 2
	20	[385]	RETURN   	0 1

function <./frontend/apps/filemanager/lib/md.lua:398,410> (42 instructions, 168 bytes at 0x7fe7f9c0c420)
3 params, 10 slots, 4 upvalues, 5 locals, 0 constants, 0 functions
	1	[399]	GETUPVAL 	3 0	; bufferStream
	2	[399]	MOVE     	4 0
	3	[399]	CALL     	3 2 3
	4	[400]	TEST     	1 0 1
	5	[400]	JMP      	2	; to 8
	6	[400]	NEWTABLE 	5 0 0
	7	[400]	MOVE     	1 5
	8	[401]	TEST     	2 0 1
	9	[401]	JMP      	2	; to 12
	10	[401]	NEWTABLE 	5 0 0
	11	[401]	MOVE     	2 5
	12	[402]	MOVE     	5 4
	13	[402]	CALL     	5 1 2
	14	[402]	TEST     	5 0 0
	15	[402]	JMP      	23	; to 39
	16	[403]	GETUPVAL 	5 1	; readBlockQuote
	17	[403]	MOVE     	6 3
	18	[403]	MOVE     	7 4
	19	[403]	MOVE     	8 1
	20	[403]	MOVE     	9 2
	21	[403]	CALL     	5 5 2
	22	[403]	TEST     	5 0 1
	23	[403]	JMP      	-12	; to 12
	24	[404]	GETUPVAL 	5 2	; readList
	25	[404]	MOVE     	6 3
	26	[404]	MOVE     	7 4
	27	[404]	MOVE     	8 1
	28	[404]	MOVE     	9 2
	29	[404]	CALL     	5 5 2
	30	[404]	TEST     	5 0 1
	31	[404]	JMP      	-20	; to 12
	32	[405]	GETUPVAL 	5 3	; readSimple
	33	[405]	MOVE     	6 3
	34	[405]	MOVE     	7 4
	35	[405]	MOVE     	8 1
	36	[405]	MOVE     	9 2
	37	[405]	CALL     	5 5 1
	38	[407]	JMP      	-27	; to 12
	39	[409]	MOVE     	5 1
	40	[409]	MOVE     	6 2
	41	[409]	RETURN   	5 3
	42	[410]	RETURN   	0 1

function <./frontend/apps/filemanager/lib/md.lua:412,414> (7 instructions, 28 bytes at 0x7fe7f9c0b690)
1 param, 4 slots, 2 upvalues, 1 local, 0 constants, 0 functions
	1	[413]	GETUPVAL 	1 0	; readLineStream
	2	[413]	GETUPVAL 	2 1	; stringLineStream
	3	[413]	MOVE     	3 0
	4	[413]	CALL     	2 2 0
	5	[413]	TAILCALL 	1 0 0
	6	[413]	RETURN   	1 0
	7	[414]	RETURN   	0 1

function <./frontend/apps/filemanager/lib/md.lua:420,426> (21 instructions, 84 bytes at 0x7fe7f9c0c0c0)
1 param, 12 slots, 2 upvalues, 7 locals, 4 constants, 0 functions
	1	[421]	NEWTABLE 	1 0 0
	2	[422]	GETGLOBAL	2 -1	; pairs
	3	[422]	MOVE     	3 0
	4	[422]	CALL     	2 2 4
	5	[422]	JMP      	8	; to 14
	6	[423]	LEN      	7 1
	7	[423]	ADD      	7 7 -2	; - 1
	8	[423]	GETUPVAL 	8 0	; format
	9	[423]	LOADK    	9 -3	; "%s=\"%s\""
	10	[423]	MOVE     	10 5
	11	[423]	MOVE     	11 6
	12	[423]	CALL     	8 4 2
	13	[423]	SETTABLE 	1 7 8
	14	[422]	TFORLOOP 	2 2
	15	[423]	JMP      	-10	; to 6
	16	[425]	GETUPVAL 	2 1	; concat
	17	[425]	MOVE     	3 1
	18	[425]	LOADK    	4 -4	; " "
	19	[425]	TAILCALL 	2 3 0
	20	[425]	RETURN   	2 0
	21	[426]	RETURN   	0 1

function <./frontend/apps/filemanager/lib/md.lua:428,453> (106 instructions, 424 bytes at 0x7fe7f9c09c20)
3 params, 12 slots, 5 upvalues, 10 locals, 18 constants, 0 functions
	1	[429]	GETTABLE 	3 0 -1	; "type"
	2	[429]	TEST     	3 0 0
	3	[429]	JMP      	60	; to 64
	4	[430]	GETTABLE 	3 0 -2	; "attributes"
	5	[430]	TEST     	3 0 1
	6	[430]	JMP      	1	; to 8
	7	[430]	NEWTABLE 	3 0 0
	8	[431]	GETTABLE 	4 0 -1	; "type"
	9	[431]	EQ       	0 4 -3	; - "a"
	10	[431]	JMP      	14	; to 25
	11	[431]	GETTABLE 	4 3 -4	; "href"
	12	[431]	TEST     	4 0 1
	13	[431]	JMP      	11	; to 25
	14	[431]	GETUPVAL 	4 0	; lower
	15	[431]	GETTABLE 	5 0 -5	; 1
	16	[431]	TEST     	5 0 1
	17	[431]	JMP      	1	; to 19
	18	[431]	LOADK    	5 -6	; ""
	19	[431]	CALL     	4 2 2
	20	[431]	GETTABLE 	4 1 4
	21	[431]	TEST     	4 0 1
	22	[431]	JMP      	1	; to 24
	23	[431]	LOADK    	4 -6	; ""
	24	[431]	SETTABLE 	3 -4 4	; "href" -
	25	[432]	GETTABLE 	4 0 -1	; "type"
	26	[432]	EQ       	0 4 -7	; - "img"
	27	[432]	JMP      	14	; to 42
	28	[432]	GETTABLE 	4 3 -8	; "src"
	29	[432]	TEST     	4 0 1
	30	[432]	JMP      	11	; to 42
	31	[432]	GETUPVAL 	4 0	; lower
	32	[432]	GETTABLE 	5 3 -9	; "alt"
	33	[432]	TEST     	5 0 1
	34	[432]	JMP      	1	; to 36
	35	[432]	LOADK    	5 -6	; ""
	36	[432]	CALL     	4 2 2
	37	[432]	GETTABLE 	4 1 4
	38	[432]	TEST     	4 0 1
	39	[432]	JMP      	1	; to 41
	40	[432]	LOADK    	4 -6	; ""
	41	[432]	SETTABLE 	3 -8 4	; "src" -
	42	[433]	GETUPVAL 	4 1	; renderAttributes
	43	[433]	MOVE     	5 3
	44	[433]	CALL     	4 2 2
	45	[434]	LEN      	5 4
	46	[434]	LT       	0 -10 5	; 0 -
	47	[434]	JMP      	9	; to 57
	48	[435]	LEN      	5 2
	49	[435]	ADD      	5 5 -5	; - 1
	50	[435]	GETUPVAL 	6 2	; format
	51	[435]	LOADK    	7 -11	; "<%s %s>"
	52	[435]	GETTABLE 	8 0 -1	; "type"
	53	[435]	MOVE     	9 4
	54	[435]	CALL     	6 4 2
	55	[435]	SETTABLE 	2 5 6
	56	[435]	JMP      	7	; to 64
	57	[437]	LEN      	5 2
	58	[437]	ADD      	5 5 -5	; - 1
	59	[437]	GETUPVAL 	6 2	; format
	60	[437]	LOADK    	7 -12	; "<%s>"
	61	[437]	GETTABLE 	8 0 -1	; "type"
	62	[437]	CALL     	6 3 2
	63	[437]	SETTABLE 	2 5 6
	64	[440]	LOADK    	3 -5	; 1
	65	[440]	LEN      	4 0
	66	[440]	LOADK    	5 -5	; 1
	67	[440]	FORPREP  	3 24	; to 92
	68	[441]	GETTABLE 	7 0 6
	69	[442]	GETUPVAL 	8 3	; type
	70	[442]	MOVE     	9 7
	71	[442]	CALL     	8 2 2
	72	[442]	EQ       	0 8 -13	; - "string"
	73	[442]	JMP      	4	; to 78
	74	[443]	LEN      	8 2
	75	[443]	ADD      	8 8 -5	; - 1
	76	[443]	SETTABLE 	2 8 7
	77	[443]	JMP      	14	; to 92
	78	[444]	GETUPVAL 	8 3	; type
	79	[444]	MOVE     	9 7
	80	[444]	CALL     	8 2 2
	81	[444]	EQ       	0 8 -14	; - "table"
	82	[444]	JMP      	6	; to 89
	83	[445]	GETUPVAL 	8 4	; renderTree
	84	[445]	MOVE     	9 7
	85	[445]	MOVE     	10 1
	86	[445]	MOVE     	11 2
	87	[445]	CALL     	8 4 1
	88	[445]	JMP      	3	; to 92
	89	[447]	GETGLOBAL	8 -15	; error
	90	[447]	LOADK    	9 -16	; "Unexpected node while rendering tree."
	91	[447]	CALL     	8 2 1
	92	[440]	FORLOOP  	3 -25	; to 68
	93	[450]	GETTABLE 	3 0 -17	; "noclose"
	94	[450]	TEST     	3 0 1
	95	[450]	JMP      	10	; to 106
	96	[450]	GETTABLE 	3 0 -1	; "type"
	97	[450]	TEST     	3 0 0
	98	[450]	JMP      	7	; to 106
	99	[451]	LEN      	3 2
	100	[451]	ADD      	3 3 -5	; - 1
	101	[451]	GETUPVAL 	4 2	; format
	102	[451]	LOADK    	5 -18	; "</%s>"
	103	[451]	GETTABLE 	6 0 -1	; "type"
	104	[451]	CALL     	4 3 2
	105	[451]	SETTABLE 	2 3 4
	106	[453]	RETURN   	0 1

function <./frontend/apps/filemanager/lib/md.lua:455,483> (81 instructions, 324 bytes at 0x7fe7f9c0cc20)
2 params, 16 slots, 7 upvalues, 11 locals, 14 constants, 0 functions
	1	[456]	GETUPVAL 	2 0	; readLineStream
	2	[456]	MOVE     	3 0
	3	[456]	CALL     	2 2 3
	4	[457]	NEWTABLE 	4 0 0
	5	[458]	LOADNIL  	5 10
	6	[459]	TEST     	1 0 0
	7	[459]	JMP      	39	; to 47
	8	[460]	GETGLOBAL	11 -1	; assert
	9	[460]	GETUPVAL 	12 1	; type
	10	[460]	MOVE     	13 1
	11	[460]	CALL     	12 2 2
	12	[460]	EQ       	1 12 -2	; - "table"
	13	[460]	JMP      	1	; to 15
	14	[460]	LOADBOOL 	12 0 1
	15	[460]	LOADBOOL 	12 1 0
	16	[460]	LOADK    	13 -3	; "Options argument should be a table."
	17	[460]	CALL     	11 3 1
	18	[461]	GETTABLE 	11 1 -4	; "tag"
	19	[461]	TEST     	11 0 0
	20	[461]	JMP      	22	; to 43
	21	[462]	GETUPVAL 	11 2	; format
	22	[462]	LOADK    	12 -5	; "</%s>"
	23	[462]	GETTABLE 	13 1 -4	; "tag"
	24	[462]	CALL     	11 3 2
	25	[462]	MOVE     	6 11
	26	[463]	GETTABLE 	11 1 -6	; "attributes"
	27	[463]	TEST     	11 0 0
	28	[463]	JMP      	9	; to 38
	29	[464]	GETUPVAL 	11 2	; format
	30	[464]	LOADK    	12 -7	; "<%s %s>"
	31	[464]	GETTABLE 	13 1 -4	; "tag"
	32	[464]	GETUPVAL 	14 3	; renderAttributes
	33	[464]	GETTABLE 	15 1 -6	; "attributes"
	34	[464]	CALL     	14 2 0
	35	[464]	CALL     	11 0 2
	36	[464]	MOVE     	5 11
	37	[464]	JMP      	5	; to 43
	38	[466]	GETUPVAL 	11 2	; format
	39	[466]	LOADK    	12 -8	; "<%s>"
	40	[466]	GETTABLE 	13 1 -4	; "tag"
	41	[466]	CALL     	11 3 2
	42	[466]	MOVE     	5 11
	43	[469]	GETTABLE 	7 1 -9	; "insertHead"
	44	[470]	GETTABLE 	8 1 -10	; "insertTail"
	45	[471]	GETTABLE 	9 1 -11	; "prependHead"
	46	[472]	GETTABLE 	10 1 -12	; "appendTail"
	47	[474]	LEN      	11 4
	48	[474]	ADD      	11 11 -13	; - 1
	49	[474]	SETTABLE 	4 11 9
	50	[475]	LEN      	11 4
	51	[475]	ADD      	11 11 -13	; - 1
	52	[475]	SETTABLE 	4 11 5
	53	[476]	LEN      	11 4
	54	[476]	ADD      	11 11 -13	; - 1
	55	[476]	SETTABLE 	4 11 7
	56	[477]	GETUPVAL 	11 4	; renderTree
	57	[477]	MOVE     	12 2
	58	[477]	MOVE     	13 3
	59	[477]	MOVE     	14 4
	60	[477]	CALL     	11 4 1
	61	[478]	LEN      	11 4
	62	[478]	GETTABLE 	11 4 11
	63	[478]	GETUPVAL 	12 5	; NEWLINE
	64	[478]	EQ       	0 11 12
	65	[478]	JMP      	2	; to 68
	66	[478]	LEN      	11 4
	67	[478]	SETTABLE 	4 11 -14	; - nil
	68	[479]	LEN      	11 4
	69	[479]	ADD      	11 11 -13	; - 1
	70	[479]	SETTABLE 	4 11 8
	71	[480]	LEN      	11 4
	72	[480]	ADD      	11 11 -13	; - 1
	73	[480]	SETTABLE 	4 11 6
	74	[481]	LEN      	11 4
	75	[481]	ADD      	11 11 -13	; - 1
	76	[481]	SETTABLE 	4 11 10
	77	[482]	GETUPVAL 	11 6	; concat
	78	[482]	MOVE     	12 4
	79	[482]	TAILCALL 	11 2 0
	80	[482]	RETURN   	11 0
	81	[483]	RETURN   	0 1

function <./frontend/apps/filemanager/lib/md.lua:489,496> (11 instructions, 44 bytes at 0x7fe7f9c0d4a0)
0+ params, 5 slots, 1 upvalue, 3 locals, 0 constants, 0 functions
	1	[490]	GETUPVAL 	1 0	; pcall
	2	[490]	VARARG   	2 0
	3	[490]	CALL     	1 0 3
	4	[491]	TEST     	1 0 0
	5	[491]	JMP      	2	; to 8
	6	[492]	RETURN   	2 2
	7	[492]	JMP      	3	; to 11
	8	[494]	LOADNIL  	3 3
	9	[494]	MOVE     	4 2
	10	[494]	RETURN   	3 3
	11	[496]	RETURN   	0 1

function <./frontend/apps/filemanager/lib/md.lua:498,500> (7 instructions, 28 bytes at 0x7fe7f9c0d3e0)
2 params, 6 slots, 2 upvalues, 2 locals, 0 constants, 0 functions
	1	[499]	GETUPVAL 	2 0	; pwrap
	2	[499]	GETUPVAL 	3 1	; renderLinesRaw
	3	[499]	MOVE     	4 0
	4	[499]	MOVE     	5 1
	5	[499]	TAILCALL 	2 4 0
	6	[499]	RETURN   	2 0
	7	[500]	RETURN   	0 1

function <./frontend/apps/filemanager/lib/md.lua:502,504> (9 instructions, 36 bytes at 0x7fe7f9c0d570)
2 params, 6 slots, 3 upvalues, 2 locals, 0 constants, 0 functions
	1	[503]	GETUPVAL 	2 0	; pwrap
	2	[503]	GETUPVAL 	3 1	; renderLinesRaw
	3	[503]	GETUPVAL 	4 2	; tableLineStream
	4	[503]	MOVE     	5 0
	5	[503]	CALL     	4 2 2
	6	[503]	MOVE     	5 1
	7	[503]	TAILCALL 	2 4 0
	8	[503]	RETURN   	2 0
	9	[504]	RETURN   	0 1

function <./frontend/apps/filemanager/lib/md.lua:506,508> (9 instructions, 36 bytes at 0x7fe7f9c0ddf0)
2 params, 6 slots, 3 upvalues, 2 locals, 0 constants, 0 functions
	1	[507]	GETUPVAL 	2 0	; pwrap
	2	[507]	GETUPVAL 	3 1	; renderLinesRaw
	3	[507]	GETUPVAL 	4 2	; stringLineStream
	4	[507]	MOVE     	5 0
	5	[507]	CALL     	4 2 2
	6	[507]	MOVE     	5 1
	7	[507]	TAILCALL 	2 4 0
	8	[507]	RETURN   	2 0
	9	[508]	RETURN   	0 1

function <./frontend/apps/filemanager/lib/md.lua:516,520> (16 instructions, 64 bytes at 0x7fe7f9c0e6d0)
2 params, 6 slots, 2 upvalues, 3 locals, 1 constant, 0 functions
	1	[517]	GETUPVAL 	2 0	; renderers
	2	[517]	GETUPVAL 	3 1	; type
	3	[517]	MOVE     	4 0
	4	[517]	CALL     	3 2 2
	5	[517]	GETTABLE 	2 2 3
	6	[518]	TEST     	2 0 1
	7	[518]	JMP      	3	; to 11
	8	[518]	LOADNIL  	3 3
	9	[518]	LOADK    	4 -1	; "Source must be a string, table, or function."
	10	[518]	RETURN   	3 3
	11	[519]	MOVE     	3 2
	12	[519]	MOVE     	4 0
	13	[519]	MOVE     	5 1
	14	[519]	TAILCALL 	3 3 0
	15	[519]	RETURN   	3 0
	16	[520]	RETURN   	0 1

function <./frontend/apps/filemanager/lib/md.lua:528,530> (5 instructions, 20 bytes at 0x7fe7f9c0e930)
1+ param, 4 slots, 1 upvalue, 2 locals, 0 constants, 0 functions
	1	[529]	GETUPVAL 	2 0	; render
	2	[529]	VARARG   	3 0
	3	[529]	TAILCALL 	2 0 0
	4	[529]	RETURN   	2 0
	5	[530]	RETURN   	0 1
