
main <./frontend/ui/elements/menu_activate.lua:0,0> (69 instructions, 276 bytes at 0x7fc6944068f0)
0+ params, 12 slots, 0 upvalues, 4 locals, 15 constants, 9 functions
	1	[1]	GETGLOBAL	0 -1	; require
	2	[1]	LOADK    	1 -2	; "ui/widget/infomessage"
	3	[1]	CALL     	0 2 2
	4	[2]	GETGLOBAL	1 -1	; require
	5	[2]	LOADK    	2 -3	; "ui/uimanager"
	6	[2]	CALL     	1 2 2
	7	[3]	GETGLOBAL	2 -1	; require
	8	[3]	LOADK    	3 -4	; "gettext"
	9	[3]	CALL     	2 2 2
	10	[5]	CLOSURE  	3 0	; 0x7fc694406c30
	11	[7]	NEWTABLE 	4 0 2
	12	[8]	MOVE     	5 2
	13	[8]	LOADK    	6 -6	; "Activate menu"
	14	[8]	CALL     	5 2 2
	15	[8]	SETTABLE 	4 -5 5	; "text" -
	16	[9]	NEWTABLE 	5 4 0
	17	[9]	NEWTABLE 	6 0 3
	18	[11]	MOVE     	7 2
	19	[11]	LOADK    	8 -8	; "Swipe and tap"
	20	[11]	CALL     	7 2 2
	21	[11]	SETTABLE 	6 -5 7	; "text" -
	22	[19]	CLOSURE  	7 1	; 0x7fc6944070c0
	23	[19]	MOVE     	0 3
	24	[19]	SETTABLE 	6 -9 7	; "checked_func" -
	25	[25]	CLOSURE  	7 2	; 0x7fc694407660
	26	[25]	MOVE     	0 1
	27	[25]	MOVE     	0 0
	28	[25]	MOVE     	0 2
	29	[25]	SETTABLE 	6 -10 7	; "callback" -
	30	[26]	NEWTABLE 	7 0 3
	31	[28]	MOVE     	8 2
	32	[28]	LOADK    	9 -11	; "Only swipe"
	33	[28]	CALL     	8 2 2
	34	[28]	SETTABLE 	7 -5 8	; "text" -
	35	[35]	CLOSURE  	8 3	; 0x7fc694407380
	36	[35]	MOVE     	0 3
	37	[35]	SETTABLE 	7 -9 8	; "checked_func" -
	38	[41]	CLOSURE  	8 4	; 0x7fc694406740
	39	[41]	MOVE     	0 1
	40	[41]	MOVE     	0 0
	41	[41]	MOVE     	0 2
	42	[41]	SETTABLE 	7 -10 8	; "callback" -
	43	[42]	NEWTABLE 	8 0 4
	44	[44]	MOVE     	9 2
	45	[44]	LOADK    	10 -12	; "Only tap"
	46	[44]	CALL     	9 2 2
	47	[44]	SETTABLE 	8 -5 9	; "text" -
	48	[51]	CLOSURE  	9 5	; 0x7fc694406e70
	49	[51]	MOVE     	0 3
	50	[51]	SETTABLE 	8 -9 9	; "checked_func" -
	51	[57]	CLOSURE  	9 6	; 0x7fc694408680
	52	[57]	MOVE     	0 1
	53	[57]	MOVE     	0 0
	54	[57]	MOVE     	0 2
	55	[57]	SETTABLE 	8 -10 9	; "callback" -
	56	[58]	SETTABLE 	8 -13 -14	; "separator" true
	57	[59]	NEWTABLE 	9 0 3
	58	[61]	MOVE     	10 2
	59	[61]	LOADK    	11 -15	; "Auto-show bottom menu"
	60	[61]	CALL     	10 2 2
	61	[61]	SETTABLE 	9 -5 10	; "text" -
	62	[64]	CLOSURE  	10 7	; 0x7fc694408b90
	63	[64]	SETTABLE 	9 -9 10	; "checked_func" -
	64	[67]	CLOSURE  	10 8	; 0x7fc694408f60
	65	[67]	SETTABLE 	9 -10 10	; "callback" -
	66	[69]	SETLIST  	5 4 1	; 1
	67	[69]	SETTABLE 	4 -7 5	; "sub_item_table" -
	68	[70]	RETURN   	4 2
	69	[70]	RETURN   	0 1

function <./frontend/ui/elements/menu_activate.lua:5,5> (6 instructions, 24 bytes at 0x7fc694406c30)
0 params, 3 slots, 0 upvalues, 0 locals, 3 constants, 0 functions
	1	[5]	GETGLOBAL	0 -1	; G_reader_settings
	2	[5]	SELF     	0 0 -2	; "readSetting"
	3	[5]	LOADK    	2 -3	; "activate_menu"
	4	[5]	TAILCALL 	0 3 0
	5	[5]	RETURN   	0 0
	6	[5]	RETURN   	0 1

function <./frontend/ui/elements/menu_activate.lua:12,19> (12 instructions, 48 bytes at 0x7fc6944070c0)
0 params, 2 slots, 1 upvalue, 1 local, 2 constants, 0 functions
	1	[13]	GETUPVAL 	0 0	; activateMenu
	2	[13]	CALL     	0 1 2
	3	[14]	EQ       	1 0 -1	; - nil
	4	[14]	JMP      	2	; to 7
	5	[14]	EQ       	0 0 -2	; - "swipe_tap"
	6	[14]	JMP      	3	; to 10
	7	[15]	LOADBOOL 	1 1 0
	8	[15]	RETURN   	1 2
	9	[15]	JMP      	2	; to 12
	10	[17]	LOADBOOL 	1 0 0
	11	[17]	RETURN   	1 2
	12	[19]	RETURN   	0 1

function <./frontend/ui/elements/menu_activate.lua:20,25> (17 instructions, 68 bytes at 0x7fc694407660)
0 params, 7 slots, 3 upvalues, 0 locals, 8 constants, 0 functions
	1	[21]	GETGLOBAL	0 -1	; G_reader_settings
	2	[21]	SELF     	0 0 -2	; "saveSetting"
	3	[21]	LOADK    	2 -3	; "activate_menu"
	4	[21]	LOADK    	3 -4	; "swipe_tap"
	5	[21]	CALL     	0 4 1
	6	[22]	GETUPVAL 	0 0	; UIManager
	7	[22]	SELF     	0 0 -5	; "show"
	8	[22]	GETUPVAL 	2 1	; InfoMessage
	9	[22]	SELF     	2 2 -6	; "new"
	10	[22]	NEWTABLE 	4 0 1
	11	[23]	GETUPVAL 	5 2	; _
	12	[23]	LOADK    	6 -8	; "This will take effect on next restart."
	13	[23]	CALL     	5 2 2
	14	[23]	SETTABLE 	4 -7 5	; "text" -
	15	[22]	CALL     	2 3 0
	16	[22]	CALL     	0 0 1
	17	[25]	RETURN   	0 1

function <./frontend/ui/elements/menu_activate.lua:29,35> (10 instructions, 40 bytes at 0x7fc694407380)
0 params, 2 slots, 1 upvalue, 0 locals, 1 constant, 0 functions
	1	[30]	GETUPVAL 	0 0	; activateMenu
	2	[30]	CALL     	0 1 2
	3	[30]	EQ       	0 0 -1	; - "swipe"
	4	[30]	JMP      	3	; to 8
	5	[31]	LOADBOOL 	0 1 0
	6	[31]	RETURN   	0 2
	7	[31]	JMP      	2	; to 10
	8	[33]	LOADBOOL 	0 0 0
	9	[33]	RETURN   	0 2
	10	[35]	RETURN   	0 1

function <./frontend/ui/elements/menu_activate.lua:36,41> (17 instructions, 68 bytes at 0x7fc694406740)
0 params, 7 slots, 3 upvalues, 0 locals, 8 constants, 0 functions
	1	[37]	GETGLOBAL	0 -1	; G_reader_settings
	2	[37]	SELF     	0 0 -2	; "saveSetting"
	3	[37]	LOADK    	2 -3	; "activate_menu"
	4	[37]	LOADK    	3 -4	; "swipe"
	5	[37]	CALL     	0 4 1
	6	[38]	GETUPVAL 	0 0	; UIManager
	7	[38]	SELF     	0 0 -5	; "show"
	8	[38]	GETUPVAL 	2 1	; InfoMessage
	9	[38]	SELF     	2 2 -6	; "new"
	10	[38]	NEWTABLE 	4 0 1
	11	[39]	GETUPVAL 	5 2	; _
	12	[39]	LOADK    	6 -8	; "This will take effect on next restart."
	13	[39]	CALL     	5 2 2
	14	[39]	SETTABLE 	4 -7 5	; "text" -
	15	[38]	CALL     	2 3 0
	16	[38]	CALL     	0 0 1
	17	[41]	RETURN   	0 1

function <./frontend/ui/elements/menu_activate.lua:45,51> (10 instructions, 40 bytes at 0x7fc694406e70)
0 params, 2 slots, 1 upvalue, 0 locals, 1 constant, 0 functions
	1	[46]	GETUPVAL 	0 0	; activateMenu
	2	[46]	CALL     	0 1 2
	3	[46]	EQ       	0 0 -1	; - "tap"
	4	[46]	JMP      	3	; to 8
	5	[47]	LOADBOOL 	0 1 0
	6	[47]	RETURN   	0 2
	7	[47]	JMP      	2	; to 10
	8	[49]	LOADBOOL 	0 0 0
	9	[49]	RETURN   	0 2
	10	[51]	RETURN   	0 1

function <./frontend/ui/elements/menu_activate.lua:52,57> (17 instructions, 68 bytes at 0x7fc694408680)
0 params, 7 slots, 3 upvalues, 0 locals, 8 constants, 0 functions
	1	[53]	GETGLOBAL	0 -1	; G_reader_settings
	2	[53]	SELF     	0 0 -2	; "saveSetting"
	3	[53]	LOADK    	2 -3	; "activate_menu"
	4	[53]	LOADK    	3 -4	; "tap"
	5	[53]	CALL     	0 4 1
	6	[54]	GETUPVAL 	0 0	; UIManager
	7	[54]	SELF     	0 0 -5	; "show"
	8	[54]	GETUPVAL 	2 1	; InfoMessage
	9	[54]	SELF     	2 2 -6	; "new"
	10	[54]	NEWTABLE 	4 0 1
	11	[55]	GETUPVAL 	5 2	; _
	12	[55]	LOADK    	6 -8	; "This will take effect on next restart."
	13	[55]	CALL     	5 2 2
	14	[55]	SETTABLE 	4 -7 5	; "text" -
	15	[54]	CALL     	2 3 0
	16	[54]	CALL     	0 0 1
	17	[57]	RETURN   	0 1

function <./frontend/ui/elements/menu_activate.lua:62,64> (6 instructions, 24 bytes at 0x7fc694408b90)
0 params, 3 slots, 0 upvalues, 0 locals, 3 constants, 0 functions
	1	[63]	GETGLOBAL	0 -1	; G_reader_settings
	2	[63]	SELF     	0 0 -2	; "nilOrTrue"
	3	[63]	LOADK    	2 -3	; "show_bottom_menu"
	4	[63]	TAILCALL 	0 3 0
	5	[63]	RETURN   	0 0
	6	[64]	RETURN   	0 1

function <./frontend/ui/elements/menu_activate.lua:65,67> (5 instructions, 20 bytes at 0x7fc694408f60)
0 params, 3 slots, 0 upvalues, 0 locals, 3 constants, 0 functions
	1	[66]	GETGLOBAL	0 -1	; G_reader_settings
	2	[66]	SELF     	0 0 -2	; "flipNilOrTrue"
	3	[66]	LOADK    	2 -3	; "show_bottom_menu"
	4	[66]	CALL     	0 3 1
	5	[67]	RETURN   	0 1
