-- BYTECODE -- menu_activate.lua:5-5
0001    GGET     0   0      ; "G_reader_settings"
0002    MOV      1   0
0003    TGETS    0   0   1  ; "readSetting"
0004    KSTR     2   2      ; "activate_menu"
0005    CALLT    0   3

-- BYTECODE -- menu_activate.lua:12-19
0001    UGET     0   0      ; activateMenu
0002    CALL     0   2   1
0003    ISEQP    0   0
0004    JMP      1 => 0007
0005    ISNES    0   0      ; "swipe_tap"
0006    JMP      1 => 0010
0007 => KPRI     1   2
0008    RET1     1   2
0009    JMP      1 => 0012
0010 => KPRI     1   1
0011    RET1     1   2
0012 => RET0     0   1

-- BYTECODE -- menu_activate.lua:20-25
0001    GGET     0   0      ; "G_reader_settings"
0002    MOV      1   0
0003    TGETS    0   0   1  ; "saveSetting"
0004    KSTR     2   2      ; "activate_menu"
0005    KSTR     3   3      ; "swipe_tap"
0006    CALL     0   1   4
0007    UGET     0   0      ; UIManager
0008    MOV      1   0
0009    TGETS    0   0   4  ; "show"
0010    UGET     2   1      ; InfoMessage
0011    MOV      3   2
0012    TGETS    2   2   5  ; "new"
0013    TDUP     4   7
0014    UGET     5   2      ; _
0015    KSTR     6   6      ; "This will take effect on next restart."
0016    CALL     5   2   2
0017    TSETS    5   4   8  ; "text"
0018    CALL     2   0   3
0019    CALLM    0   1   1
0020    RET0     0   1

-- BYTECODE -- menu_activate.lua:29-35
0001    UGET     0   0      ; activateMenu
0002    CALL     0   2   1
0003    ISNES    0   0      ; "swipe"
0004    JMP      0 => 0008
0005    KPRI     0   2
0006    RET1     0   2
0007    JMP      0 => 0010
0008 => KPRI     0   1
0009    RET1     0   2
0010 => RET0     0   1

-- BYTECODE -- menu_activate.lua:36-41
0001    GGET     0   0      ; "G_reader_settings"
0002    MOV      1   0
0003    TGETS    0   0   1  ; "saveSetting"
0004    KSTR     2   2      ; "activate_menu"
0005    KSTR     3   3      ; "swipe"
0006    CALL     0   1   4
0007    UGET     0   0      ; UIManager
0008    MOV      1   0
0009    TGETS    0   0   4  ; "show"
0010    UGET     2   1      ; InfoMessage
0011    MOV      3   2
0012    TGETS    2   2   5  ; "new"
0013    TDUP     4   7
0014    UGET     5   2      ; _
0015    KSTR     6   6      ; "This will take effect on next restart."
0016    CALL     5   2   2
0017    TSETS    5   4   8  ; "text"
0018    CALL     2   0   3
0019    CALLM    0   1   1
0020    RET0     0   1

-- BYTECODE -- menu_activate.lua:45-51
0001    UGET     0   0      ; activateMenu
0002    CALL     0   2   1
0003    ISNES    0   0      ; "tap"
0004    JMP      0 => 0008
0005    KPRI     0   2
0006    RET1     0   2
0007    JMP      0 => 0010
0008 => KPRI     0   1
0009    RET1     0   2
0010 => RET0     0   1

-- BYTECODE -- menu_activate.lua:52-57
0001    GGET     0   0      ; "G_reader_settings"
0002    MOV      1   0
0003    TGETS    0   0   1  ; "saveSetting"
0004    KSTR     2   2      ; "activate_menu"
0005    KSTR     3   3      ; "tap"
0006    CALL     0   1   4
0007    UGET     0   0      ; UIManager
0008    MOV      1   0
0009    TGETS    0   0   4  ; "show"
0010    UGET     2   1      ; InfoMessage
0011    MOV      3   2
0012    TGETS    2   2   5  ; "new"
0013    TDUP     4   7
0014    UGET     5   2      ; _
0015    KSTR     6   6      ; "This will take effect on next restart."
0016    CALL     5   2   2
0017    TSETS    5   4   8  ; "text"
0018    CALL     2   0   3
0019    CALLM    0   1   1
0020    RET0     0   1

-- BYTECODE -- menu_activate.lua:62-64
0001    GGET     0   0      ; "G_reader_settings"
0002    MOV      1   0
0003    TGETS    0   0   1  ; "nilOrTrue"
0004    KSTR     2   2      ; "show_bottom_menu"
0005    CALLT    0   3

-- BYTECODE -- menu_activate.lua:65-67
0001    GGET     0   0      ; "G_reader_settings"
0002    MOV      1   0
0003    TGETS    0   0   1  ; "flipNilOrTrue"
0004    KSTR     2   2      ; "show_bottom_menu"
0005    CALL     0   1   3
0006    RET0     0   1

-- BYTECODE -- menu_activate.lua:0-71
0001    GGET     0   0      ; "require"
0002    KSTR     1   1      ; "ui/widget/infomessage"
0003    CALL     0   2   2
0004    GGET     1   0      ; "require"
0005    KSTR     2   2      ; "ui/uimanager"
0006    CALL     1   2   2
0007    GGET     2   0      ; "require"
0008    KSTR     3   3      ; "gettext"
0009    CALL     2   2   2
0010    FNEW     3   4      ; menu_activate.lua:5
0011    TDUP     4   6
0012    MOV      5   2
0013    KSTR     6   5      ; "Activate menu"
0014    CALL     5   2   2
0015    TSETS    5   4   7  ; "text"
0016    TNEW     5   5
0017    TDUP     6   9
0018    MOV      7   2
0019    KSTR     8   8      ; "Swipe and tap"
0020    CALL     7   2   2
0021    TSETS    7   6   7  ; "text"
0022    FNEW     7  10      ; menu_activate.lua:12
0023    TSETS    7   6  11  ; "checked_func"
0024    FNEW     7  12      ; menu_activate.lua:20
0025    TSETS    7   6  13  ; "callback"
0026    TSETB    6   5   1
0027    TDUP     6  15
0028    MOV      7   2
0029    KSTR     8  14      ; "Only swipe"
0030    CALL     7   2   2
0031    TSETS    7   6   7  ; "text"
0032    FNEW     7  16      ; menu_activate.lua:29
0033    TSETS    7   6  11  ; "checked_func"
0034    FNEW     7  17      ; menu_activate.lua:36
0035    TSETS    7   6  13  ; "callback"
0036    TSETB    6   5   2
0037    TDUP     6  19
0038    MOV      7   2
0039    KSTR     8  18      ; "Only tap"
0040    CALL     7   2   2
0041    TSETS    7   6   7  ; "text"
0042    FNEW     7  20      ; menu_activate.lua:45
0043    TSETS    7   6  11  ; "checked_func"
0044    FNEW     7  21      ; menu_activate.lua:52
0045    TSETS    7   6  13  ; "callback"
0046    TSETB    6   5   3
0047    TDUP     6  23
0048    MOV      7   2
0049    KSTR     8  22      ; "Auto-show bottom menu"
0050    CALL     7   2   2
0051    TSETS    7   6   7  ; "text"
0052    FNEW     7  24      ; menu_activate.lua:62
0053    TSETS    7   6  11  ; "checked_func"
0054    FNEW     7  25      ; menu_activate.lua:65
0055    TSETS    7   6  13  ; "callback"
0056    TSETB    6   5   4
0057    TSETS    5   4  26  ; "sub_item_table"
0058    UCLO     0 => 0059
0059 => RET1     4   2

