
main <./spec/unit/menu_table_screen_color_spec.lua:0,0> (5 instructions, 20 bytes at 0x7f8e265056a0)
0+ params, 3 slots, 0 upvalues, 0 locals, 2 constants, 1 function
	1	[1]	GETGLOBAL	0 -1	; describe
	2	[1]	LOADK    	1 -2	; "menu table screen color module"
	3	[20]	CLOSURE  	2 0	; 0x7f8e26505950
	4	[1]	CALL     	0 3 1
	5	[20]	RETURN   	0 1

function <./spec/unit/menu_table_screen_color_spec.lua:1,20> (14 instructions, 56 bytes at 0x7f8e26505950)
0 params, 6 slots, 0 upvalues, 3 locals, 3 constants, 2 functions
	1	[3]	GETGLOBAL	3 -1	; setup
	2	[8]	CLOSURE  	4 0	; 0x7f8e26505ca0
	3	[8]	MOVE     	0 0
	4	[8]	MOVE     	0 1
	5	[8]	MOVE     	0 2
	6	[3]	CALL     	3 2 1
	7	[10]	GETGLOBAL	3 -2	; it
	8	[10]	LOADK    	4 -3	; "should toggle color rendering"
	9	[19]	CLOSURE  	5 1	; 0x7f8e26506380
	10	[19]	MOVE     	0 1
	11	[19]	MOVE     	0 2
	12	[19]	MOVE     	0 0
	13	[10]	CALL     	3 3 1
	14	[20]	RETURN   	0 1

function <./spec/unit/menu_table_screen_color_spec.lua:3,8> (17 instructions, 68 bytes at 0x7f8e26505ca0)
0 params, 2 slots, 3 upvalues, 0 locals, 6 constants, 0 functions
	1	[4]	GETGLOBAL	0 -1	; require
	2	[4]	LOADK    	1 -2	; "commonrequire"
	3	[4]	CALL     	0 2 1
	4	[5]	GETGLOBAL	0 -1	; require
	5	[5]	LOADK    	1 -3	; "ui/elements/screen_color_menu_table"
	6	[5]	CALL     	0 2 2
	7	[5]	SETUPVAL 	0 0	; menu
	8	[6]	GETGLOBAL	0 -1	; require
	9	[6]	LOADK    	1 -4	; "device"
	10	[6]	CALL     	0 2 2
	11	[6]	GETTABLE 	0 0 -5	; "screen"
	12	[6]	SETUPVAL 	0 1	; Screen
	13	[7]	GETGLOBAL	0 -1	; require
	14	[7]	LOADK    	1 -6	; "document/canvascontext"
	15	[7]	CALL     	0 2 2
	16	[7]	SETUPVAL 	0 2	; CanvasContext
	17	[8]	RETURN   	0 1

function <./spec/unit/menu_table_screen_color_spec.lua:10,19> (46 instructions, 184 bytes at 0x7f8e26506380)
0 params, 2 slots, 3 upvalues, 0 locals, 7 constants, 0 functions
	1	[11]	GETGLOBAL	0 -1	; assert
	2	[11]	GETTABLE 	0 0 -2	; "is"
	3	[11]	GETTABLE 	0 0 -3	; "truthy"
	4	[11]	GETUPVAL 	1 0	; Screen
	5	[11]	GETTABLE 	1 1 -4	; "isColorEnabled"
	6	[11]	CALL     	1 1 0
	7	[11]	CALL     	0 0 1
	8	[12]	GETGLOBAL	0 -1	; assert
	9	[12]	GETTABLE 	0 0 -2	; "is"
	10	[12]	GETTABLE 	0 0 -3	; "truthy"
	11	[12]	GETUPVAL 	1 1	; CanvasContext
	12	[12]	GETTABLE 	1 1 -5	; "is_color_rendering_enabled"
	13	[12]	CALL     	0 2 1
	14	[13]	GETUPVAL 	0 2	; menu
	15	[13]	GETTABLE 	0 0 -6	; "callback"
	16	[13]	CALL     	0 1 1
	17	[14]	GETGLOBAL	0 -1	; assert
	18	[14]	GETTABLE 	0 0 -2	; "is"
	19	[14]	GETTABLE 	0 0 -7	; "falsy"
	20	[14]	GETUPVAL 	1 0	; Screen
	21	[14]	GETTABLE 	1 1 -4	; "isColorEnabled"
	22	[14]	CALL     	1 1 0
	23	[14]	CALL     	0 0 1
	24	[15]	GETGLOBAL	0 -1	; assert
	25	[15]	GETTABLE 	0 0 -2	; "is"
	26	[15]	GETTABLE 	0 0 -7	; "falsy"
	27	[15]	GETUPVAL 	1 1	; CanvasContext
	28	[15]	GETTABLE 	1 1 -5	; "is_color_rendering_enabled"
	29	[15]	CALL     	0 2 1
	30	[16]	GETUPVAL 	0 2	; menu
	31	[16]	GETTABLE 	0 0 -6	; "callback"
	32	[16]	CALL     	0 1 1
	33	[17]	GETGLOBAL	0 -1	; assert
	34	[17]	GETTABLE 	0 0 -2	; "is"
	35	[17]	GETTABLE 	0 0 -3	; "truthy"
	36	[17]	GETUPVAL 	1 0	; Screen
	37	[17]	GETTABLE 	1 1 -4	; "isColorEnabled"
	38	[17]	CALL     	1 1 0
	39	[17]	CALL     	0 0 1
	40	[18]	GETGLOBAL	0 -1	; assert
	41	[18]	GETTABLE 	0 0 -2	; "is"
	42	[18]	GETTABLE 	0 0 -3	; "truthy"
	43	[18]	GETUPVAL 	1 1	; CanvasContext
	44	[18]	GETTABLE 	1 1 -5	; "is_color_rendering_enabled"
	45	[18]	CALL     	0 2 1
	46	[19]	RETURN   	0 1
