-- BYTECODE -- menusorter_spec.lua:4-8
0001    GGET     0   0      ; "require"
0002    KSTR     1   1      ; "commonrequire"
0003    CALL     0   1   2
0004    GGET     0   0      ; "require"
0005    KSTR     1   2      ; "ui/menusorter"
0006    CALL     0   2   2
0007    USETV    0   0      ; MenuSorter
0008    GGET     0   0      ; "require"
0009    KSTR     1   3      ; "util"
0010    CALL     0   2   2
0011    TGETS    0   0   4  ; "tableEquals"
0012    USETV    1   0      ; equals
0013    RET0     0   1

-- BYTECODE -- menusorter_spec.lua:10-37
0001    TDUP     0   0
0002    TNEW     1   0
0003    TSETS    1   0   1  ; "KOMenu:menu_buttons"
0004    TNEW     1   0
0005    TSETS    1   0   2  ; "main"
0006    TNEW     1   0
0007    TSETS    1   0   3  ; "search"
0008    TNEW     1   0
0009    TSETS    1   0   4  ; "tools"
0010    TNEW     1   0
0011    TSETS    1   0   5  ; "setting"
0012    TDUP     1   7
0013    TDUP     2   6
0014    TSETS    2   1   1  ; "KOMenu:menu_buttons"
0015    TNEW     2   0
0016    TSETS    2   1   2  ; "main"
0017    TNEW     2   0
0018    TSETS    2   1   3  ; "search"
0019    TNEW     2   0
0020    TSETS    2   1   4  ; "tools"
0021    TNEW     2   0
0022    TSETS    2   1   5  ; "setting"
0023    UGET     2   0      ; MenuSorter
0024    MOV      3   2
0025    TGETS    2   2   8  ; "sort"
0026    MOV      4   0
0027    MOV      5   1
0028    CALL     2   2   4
0029    GGET     3   9      ; "assert"
0030    TGETS    3   3  10  ; "is_true"
0031    TGETB    4   2   1
0032    TGETS    4   4  11  ; "id"
0033    ISEQS    4   5      ; "setting"
0034    JMP      4 => 0037
0035    KPRI     4   1
0036    JMP      5 => 0038
0037 => KPRI     4   2
0038 => CALL     3   1   2
0039    GGET     3   9      ; "assert"
0040    TGETS    3   3  10  ; "is_true"
0041    TGETB    4   2   2
0042    TGETS    4   4  11  ; "id"
0043    ISEQS    4   4      ; "tools"
0044    JMP      4 => 0047
0045    KPRI     4   1
0046    JMP      5 => 0048
0047 => KPRI     4   2
0048 => CALL     3   1   2
0049    GGET     3   9      ; "assert"
0050    TGETS    3   3  10  ; "is_true"
0051    TGETB    4   2   3
0052    TGETS    4   4  11  ; "id"
0053    ISEQS    4   3      ; "search"
0054    JMP      4 => 0057
0055    KPRI     4   1
0056    JMP      5 => 0058
0057 => KPRI     4   2
0058 => CALL     3   1   2
0059    GGET     3   9      ; "assert"
0060    TGETS    3   3  10  ; "is_true"
0061    TGETB    4   2   4
0062    TGETS    4   4  11  ; "id"
0063    ISEQS    4   2      ; "main"
0064    JMP      4 => 0067
0065    KPRI     4   1
0066    JMP      5 => 0068
0067 => KPRI     4   2
0068 => CALL     3   1   2
0069    RET0     0   1

-- BYTECODE -- menusorter_spec.lua:38-58
0001    TDUP     0   0
0002    TNEW     1   0
0003    TSETS    1   0   1  ; "KOMenu:menu_buttons"
0004    TNEW     1   0
0005    TSETS    1   0   2  ; "first"
0006    TNEW     1   0
0007    TSETS    1   0   3  ; "second"
0008    TNEW     1   0
0009    TSETS    1   0   4  ; "third1"
0010    TNEW     1   0
0011    TSETS    1   0   5  ; "third2"
0012    TDUP     1   7
0013    TDUP     2   6
0014    TSETS    2   1   1  ; "KOMenu:menu_buttons"
0015    TDUP     2   8
0016    TSETS    2   1   2  ; "first"
0017    TDUP     2   9
0018    TSETS    2   1   3  ; "second"
0019    UGET     2   0      ; MenuSorter
0020    MOV      3   2
0021    TGETS    2   2  10  ; "sort"
0022    MOV      4   0
0023    MOV      5   1
0024    CALL     2   2   4
0025    GGET     3  11      ; "assert"
0026    TGETS    3   3  12  ; "is_true"
0027    TGETB    4   2   1
0028    TGETS    4   4  13  ; "id"
0029    ISEQS    4   2      ; "first"
0030    JMP      4 => 0033
0031    KPRI     4   1
0032    JMP      5 => 0034
0033 => KPRI     4   2
0034 => CALL     3   1   2
0035    GGET     3  11      ; "assert"
0036    TGETS    3   3  12  ; "is_true"
0037    TGETB    4   2   1
0038    TGETB    4   4   1
0039    TGETS    4   4  13  ; "id"
0040    ISEQS    4   3      ; "second"
0041    JMP      4 => 0044
0042    KPRI     4   1
0043    JMP      5 => 0045
0044 => KPRI     4   2
0045 => CALL     3   1   2
0046    GGET     3  11      ; "assert"
0047    TGETS    3   3  12  ; "is_true"
0048    TGETB    4   2   1
0049    TGETB    4   4   1
0050    TGETS    4   4  14  ; "sub_item_table"
0051    TGETB    4   4   1
0052    TGETS    4   4  13  ; "id"
0053    ISEQS    4   4      ; "third1"
0054    JMP      4 => 0057
0055    KPRI     4   1
0056    JMP      5 => 0058
0057 => KPRI     4   2
0058 => CALL     3   1   2
0059    GGET     3  11      ; "assert"
0060    TGETS    3   3  12  ; "is_true"
0061    TGETB    4   2   1
0062    TGETB    4   4   1
0063    TGETS    4   4  14  ; "sub_item_table"
0064    TGETB    4   4   2
0065    TGETS    4   4  13  ; "id"
0066    ISEQS    4   5      ; "third2"
0067    JMP      4 => 0070
0068    KPRI     4   1
0069    JMP      5 => 0071
0070 => KPRI     4   2
0071 => CALL     3   1   2
0072    RET0     0   1

-- BYTECODE -- menusorter_spec.lua:59-84
0001    TDUP     0   0
0002    TNEW     1   0
0003    TSETS    1   0   1  ; "KOMenu:menu_buttons"
0004    TDUP     1   2
0005    TSETS    1   0   3  ; "main"
0006    TDUP     1   4
0007    TSETS    1   0   5  ; "search"
0008    TDUP     1   6
0009    TSETS    1   0   7  ; "tools"
0010    TDUP     1   8
0011    TSETS    1   0   9  ; "setting"
0012    TDUP     1  11
0013    TDUP     2  10
0014    TSETS    2   1   1  ; "KOMenu:menu_buttons"
0015    TNEW     2   0
0016    TSETS    2   1   9  ; "setting"
0017    UGET     2   0      ; MenuSorter
0018    MOV      3   2
0019    TGETS    2   2  12  ; "sort"
0020    MOV      4   0
0021    MOV      5   1
0022    CALL     2   2   4
0023    GGET     3  13      ; "assert"
0024    TGETS    3   3  14  ; "is_true"
0025    TGETB    4   2   1
0026    LEN      4   4
0027    ISEQN    4   0      ; 3
0028    JMP      4 => 0031
0029    KPRI     4   1
0030    JMP      5 => 0032
0031 => KPRI     4   2
0032 => CALL     3   1   2
0033    GGET     3  15      ; "ipairs"
0034    TGETB    4   2   1
0035    CALL     3   4   2
0036    JMP      6 => 0068
0037 => GGET     8  13      ; "assert"
0038    TGETS    8   8  14  ; "is_true"
0039    GGET     9  16      ; "type"
0040    TGETS   10   7  17  ; "id"
0041    CALL     9   2   2
0042    ISEQS    9  18      ; "string"
0043    JMP      9 => 0046
0044    KPRI     9   1
0045    JMP     10 => 0047
0046 => KPRI     9   2
0047 => CALL     8   1   2
0048    GGET     8  13      ; "assert"
0049    TGETS    8   8  14  ; "is_true"
0050    GGET     9  18      ; "string"
0051    TGETS    9   9  19  ; "sub"
0052    TGETS   10   7  20  ; "text"
0053    KSHORT  11   1
0054    GGET    12  18      ; "string"
0055    TGETS   12  12  21  ; "len"
0056    UGET    13   0      ; MenuSorter
0057    TGETS   13  13  22  ; "orphaned_prefix"
0058    CALL    12   0   2
0059    CALLM    9   2   2
0060    UGET    10   0      ; MenuSorter
0061    TGETS   10  10  22  ; "orphaned_prefix"
0062    ISEQV    9  10
0063    JMP      9 => 0066
0064    KPRI     9   1
0065    JMP     10 => 0067
0066 => KPRI     9   2
0067 => CALL     8   1   2
0068 => ITERC    6   3   3
0069    ITERL    6 => 0037
0070    RET0     0   1

-- BYTECODE -- menusorter_spec.lua:85-157
0001    TDUP     0   0
0002    TNEW     1   0
0003    TSETS    1   0   1  ; "KOMenu:menu_buttons"
0004    TDUP     1   2
0005    TSETS    1   0   3  ; "main"
0006    TDUP     1   4
0007    TSETS    1   0   5  ; "search"
0008    TDUP     1   6
0009    TSETS    1   0   7  ; "tools"
0010    TDUP     1   8
0011    TSETS    1   0   9  ; "setting"
0012    TDUP     1  10
0013    TSETS    1   0  11  ; "submenu"
0014    TDUP     1  12
0015    TSETS    1   0  13  ; "submenu_item1"
0016    TDUP     1  14
0017    TSETS    1   0  15  ; "submenu_item2"
0018    TDUP     1  17
0019    TDUP     2  16
0020    TSETS    2   1   1  ; "KOMenu:menu_buttons"
0021    TNEW     2   0
0022    TSETS    2   1   7  ; "tools"
0023    TDUP     2  18
0024    TSETS    2   1   9  ; "setting"
0025    TDUP     2  19
0026    TSETS    2   1  11  ; "submenu"
0027    UGET     2   0      ; MenuSorter
0028    MOV      3   2
0029    TGETS    2   2  20  ; "sort"
0030    MOV      4   0
0031    MOV      5   1
0032    CALL     2   2   4
0033    TDUP     3  31
0034    TDUP     4  30
0035    TDUP     5  21
0036    TDUP     6  23
0037    TDUP     7  22
0038    TSETB    7   6   1
0039    TSETS    6   5  24  ; "sub_item_table"
0040    TSETB    5   4   1
0041    TDUP     5  25
0042    TDUP     6  28
0043    TDUP     7  26
0044    TSETB    7   6   1
0045    TDUP     7  27
0046    TSETB    7   6   2
0047    TSETS    6   5  24  ; "sub_item_table"
0048    TSETB    5   4   2
0049    TDUP     5  29
0050    TSETB    5   4   3
0051    TSETB    4   3   1
0052    GGET     4  32      ; "assert"
0053    TGETS    4   4  33  ; "is_true"
0054    UGET     5   1      ; equals
0055    MOV      6   3
0056    MOV      7   2
0057    CALL     5   0   3
0058    CALLM    4   1   0
0059    RET0     0   1

-- BYTECODE -- menusorter_spec.lua:158-187
0001    TDUP     0   0
0002    TNEW     1   0
0003    TSETS    1   0   1  ; "KOMenu:menu_buttons"
0004    TDUP     1   2
0005    TSETS    1   0   3  ; "main"
0006    TDUP     1   4
0007    TSETS    1   0   5  ; "search"
0008    TDUP     1   6
0009    TSETS    1   0   7  ; "tools"
0010    TDUP     1   8
0011    TSETS    1   0   9  ; "setting"
0012    TDUP     1  10
0013    TSETS    1   0  11  ; "submenu"
0014    TDUP     1  12
0015    TSETS    1   0  13  ; "submenu_item1"
0016    TDUP     1  14
0017    TSETS    1   0  15  ; "submenu_item2"
0018    TDUP     1  17
0019    TDUP     2  16
0020    TSETS    2   1   1  ; "KOMenu:menu_buttons"
0021    TNEW     2   0
0022    TSETS    2   1   9  ; "setting"
0023    TDUP     2  18
0024    TSETS    2   1  11  ; "submenu"
0025    UGET     2   0      ; MenuSorter
0026    MOV      3   2
0027    TGETS    2   2  19  ; "sort"
0028    MOV      4   0
0029    MOV      5   1
0030    CALL     2   2   4
0031    GGET     3  20      ; "assert"
0032    TGETS    3   3  21  ; "is_true"
0033    TGETB    4   2   1
0034    LEN      4   4
0035    ISEQN    4   0      ; 4
0036    JMP      4 => 0039
0037    KPRI     4   1
0038    JMP      5 => 0040
0039 => KPRI     4   2
0040 => CALL     3   1   2
0041    GGET     3  20      ; "assert"
0042    TGETS    3   3  22  ; "is_truthy"
0043    TGETB    4   2   1
0044    TGETB    4   4   3
0045    TGETS    4   4  23  ; "sub_item_table"
0046    CALL     3   1   2
0047    GGET     3  20      ; "assert"
0048    TGETS    3   3  24  ; "equals"
0049    TGETB    4   2   1
0050    TGETB    4   4   3
0051    TGETS    4   4  23  ; "sub_item_table"
0052    TGETB    4   4   1
0053    TGETS    4   4  25  ; "id"
0054    KSTR     5  15      ; "submenu_item2"
0055    CALL     3   1   3
0056    GGET     3  20      ; "assert"
0057    TGETS    3   3  24  ; "equals"
0058    TGETB    4   2   1
0059    TGETB    4   4   3
0060    TGETS    4   4  23  ; "sub_item_table"
0061    TGETB    4   4   2
0062    TGETS    4   4  25  ; "id"
0063    KSTR     5  13      ; "submenu_item1"
0064    CALL     3   1   3
0065    RET0     0   1

-- BYTECODE -- menusorter_spec.lua:188-209
0001    TDUP     0   0
0002    TNEW     1   0
0003    TSETS    1   0   1  ; "KOMenu:menu_buttons"
0004    TDUP     1   2
0005    TSETS    1   0   3  ; "main"
0006    TDUP     1   4
0007    TSETS    1   0   5  ; "search"
0008    TDUP     1   6
0009    TSETS    1   0   7  ; "tools"
0010    TDUP     1   8
0011    TSETS    1   0   9  ; "setting"
0012    TDUP     1  11
0013    TDUP     2  10
0014    TSETS    2   1   1  ; "KOMenu:menu_buttons"
0015    TNEW     2   0
0016    TSETS    2   1   9  ; "setting"
0017    TDUP     2  12
0018    TSETS    2   1  13  ; "KOMenu:disabled"
0019    UGET     2   0      ; MenuSorter
0020    MOV      3   2
0021    TGETS    2   2  14  ; "sort"
0022    MOV      4   0
0023    MOV      5   1
0024    CALL     2   2   4
0025    GGET     3  15      ; "assert"
0026    TGETS    3   3  16  ; "is_true"
0027    TGETB    4   2   1
0028    LEN      4   4
0029    ISEQN    4   0      ; 1
0030    JMP      4 => 0033
0031    KPRI     4   1
0032    JMP      5 => 0034
0033 => KPRI     4   2
0034 => CALL     3   1   2
0035    GGET     3  15      ; "assert"
0036    TGETS    3   3  16  ; "is_true"
0037    TGETB    4   2   1
0038    TGETB    4   4   1
0039    TGETS    4   4  17  ; "id"
0040    ISEQS    4   7      ; "tools"
0041    JMP      4 => 0044
0042    KPRI     4   1
0043    JMP      5 => 0045
0044 => KPRI     4   2
0045 => CALL     3   1   2
0046    RET0     0   1

-- BYTECODE -- menusorter_spec.lua:210-231
0001    TDUP     0   0
0002    TNEW     1   0
0003    TSETS    1   0   1  ; "KOMenu:menu_buttons"
0004    TNEW     1   0
0005    TSETS    1   0   2  ; "first"
0006    TNEW     1   0
0007    TSETS    1   0   3  ; "second"
0008    TNEW     1   0
0009    TSETS    1   0   4  ; "third1"
0010    TNEW     1   0
0011    TSETS    1   0   5  ; "third2"
0012    TDUP     1   7
0013    TDUP     2   6
0014    TSETS    2   1   1  ; "KOMenu:menu_buttons"
0015    TDUP     2   8
0016    TSETS    2   1   2  ; "first"
0017    UGET     2   0      ; MenuSorter
0018    MOV      3   2
0019    TGETS    2   2   9  ; "sort"
0020    MOV      4   0
0021    MOV      5   1
0022    CALL     2   2   4
0023    GGET     3  10      ; "assert"
0024    TGETS    3   3  11  ; "is_true"
0025    TGETB    4   2   1
0026    TGETS    4   4  12  ; "id"
0027    ISEQS    4   2      ; "first"
0028    JMP      4 => 0031
0029    KPRI     4   1
0030    JMP      5 => 0032
0031 => KPRI     4   2
0032 => CALL     3   1   2
0033    GGET     3  10      ; "assert"
0034    TGETS    3   3  11  ; "is_true"
0035    TGETB    4   2   1
0036    TGETB    4   4   1
0037    TGETS    4   4  12  ; "id"
0038    ISEQS    4   3      ; "second"
0039    JMP      4 => 0042
0040    KPRI     4   1
0041    JMP      5 => 0043
0042 => KPRI     4   2
0043 => CALL     3   1   2
0044    GGET     3  10      ; "assert"
0045    TGETS    3   3  11  ; "is_true"
0046    TGETB    4   2   1
0047    TGETB    4   4   1
0048    TGETS    4   4  13  ; "separator"
0049    ISEQP    4   2
0050    JMP      4 => 0053
0051    KPRI     4   1
0052    JMP      5 => 0054
0053 => KPRI     4   2
0054 => CALL     3   1   2
0055    GGET     3  10      ; "assert"
0056    TGETS    3   3  11  ; "is_true"
0057    TGETB    4   2   1
0058    TGETB    4   4   2
0059    TGETS    4   4  12  ; "id"
0060    ISEQS    4   4      ; "third1"
0061    JMP      4 => 0064
0062    KPRI     4   1
0063    JMP      5 => 0065
0064 => KPRI     4   2
0065 => CALL     3   1   2
0066    GGET     3  10      ; "assert"
0067    TGETS    3   3  11  ; "is_true"
0068    TGETB    4   2   1
0069    TGETB    4   4   2
0070    TGETS    4   4  13  ; "separator"
0071    ISEQP    4   2
0072    JMP      4 => 0075
0073    KPRI     4   1
0074    JMP      5 => 0076
0075 => KPRI     4   2
0076 => CALL     3   1   2
0077    GGET     3  10      ; "assert"
0078    TGETS    3   3  11  ; "is_true"
0079    TGETB    4   2   1
0080    TGETB    4   4   3
0081    TGETS    4   4  12  ; "id"
0082    ISEQS    4   5      ; "third2"
0083    JMP      4 => 0086
0084    KPRI     4   1
0085    JMP      5 => 0087
0086 => KPRI     4   2
0087 => CALL     3   1   2
0088    RET0     0   1

-- BYTECODE -- menusorter_spec.lua:232-253
0001    TDUP     0   0
0002    TNEW     1   0
0003    TSETS    1   0   1  ; "KOMenu:menu_buttons"
0004    TNEW     1   0
0005    TSETS    1   0   2  ; "first"
0006    TNEW     1   0
0007    TSETS    1   0   3  ; "second"
0008    TNEW     1   0
0009    TSETS    1   0   4  ; "third1"
0010    TNEW     1   0
0011    TSETS    1   0   5  ; "third2"
0012    TDUP     1   7
0013    TDUP     2   6
0014    TSETS    2   1   1  ; "KOMenu:menu_buttons"
0015    TDUP     2   8
0016    TSETS    2   1   2  ; "first"
0017    UGET     2   0      ; MenuSorter
0018    MOV      3   2
0019    TGETS    2   2   9  ; "sort"
0020    MOV      4   0
0021    MOV      5   1
0022    CALL     2   2   4
0023    GGET     3  10      ; "assert"
0024    TGETS    3   3  11  ; "is_true"
0025    TGETB    4   2   1
0026    TGETS    4   4  12  ; "id"
0027    ISEQS    4   2      ; "first"
0028    JMP      4 => 0031
0029    KPRI     4   1
0030    JMP      5 => 0032
0031 => KPRI     4   2
0032 => CALL     3   1   2
0033    GGET     3  10      ; "assert"
0034    TGETS    3   3  11  ; "is_true"
0035    TGETB    4   2   1
0036    TGETB    4   4   1
0037    TGETS    4   4  12  ; "id"
0038    ISEQS    4   3      ; "second"
0039    JMP      4 => 0042
0040    KPRI     4   1
0041    JMP      5 => 0043
0042 => KPRI     4   2
0043 => CALL     3   1   2
0044    GGET     3  10      ; "assert"
0045    TGETS    3   3  13  ; "is_nil"
0046    TGETB    4   2   1
0047    TGETB    4   4   1
0048    TGETS    4   4  14  ; "separator"
0049    CALL     3   1   2
0050    GGET     3  10      ; "assert"
0051    TGETS    3   3  11  ; "is_true"
0052    TGETB    4   2   1
0053    TGETB    4   4   2
0054    TGETS    4   4  12  ; "id"
0055    ISEQS    4   4      ; "third1"
0056    JMP      4 => 0059
0057    KPRI     4   1
0058    JMP      5 => 0060
0059 => KPRI     4   2
0060 => CALL     3   1   2
0061    GGET     3  10      ; "assert"
0062    TGETS    3   3  11  ; "is_true"
0063    TGETB    4   2   1
0064    TGETB    4   4   2
0065    TGETS    4   4  14  ; "separator"
0066    ISEQP    4   2
0067    JMP      4 => 0070
0068    KPRI     4   1
0069    JMP      5 => 0071
0070 => KPRI     4   2
0071 => CALL     3   1   2
0072    GGET     3  10      ; "assert"
0073    TGETS    3   3  11  ; "is_true"
0074    TGETB    4   2   1
0075    TGETB    4   4   3
0076    TGETS    4   4  12  ; "id"
0077    ISEQS    4   5      ; "third2"
0078    JMP      4 => 0081
0079    KPRI     4   1
0080    JMP      5 => 0082
0081 => KPRI     4   2
0082 => CALL     3   1   2
0083    RET0     0   1

-- BYTECODE -- menusorter_spec.lua:254-273
0001    TDUP     0   0
0002    TNEW     1   0
0003    TSETS    1   0   1  ; "KOMenu:menu_buttons"
0004    TNEW     1   0
0005    TSETS    1   0   2  ; "first"
0006    TNEW     1   0
0007    TSETS    1   0   3  ; "second"
0008    TNEW     1   0
0009    TSETS    1   0   4  ; "third2"
0010    TNEW     1   0
0011    TSETS    1   0   5  ; "third4"
0012    TDUP     1   7
0013    TDUP     2   6
0014    TSETS    2   1   1  ; "KOMenu:menu_buttons"
0015    TDUP     2   8
0016    TSETS    2   1   2  ; "first"
0017    UGET     2   0      ; MenuSorter
0018    MOV      3   2
0019    TGETS    2   2   9  ; "sort"
0020    MOV      4   0
0021    MOV      5   1
0022    CALL     2   2   4
0023    GGET     3  10      ; "assert"
0024    TGETS    3   3  11  ; "is_true"
0025    TGETB    4   2   1
0026    TGETS    4   4  12  ; "id"
0027    ISEQS    4   2      ; "first"
0028    JMP      4 => 0031
0029    KPRI     4   1
0030    JMP      5 => 0032
0031 => KPRI     4   2
0032 => CALL     3   1   2
0033    GGET     3  10      ; "assert"
0034    TGETS    3   3  11  ; "is_true"
0035    TGETB    4   2   1
0036    TGETB    4   4   1
0037    TGETS    4   4  12  ; "id"
0038    ISEQS    4   3      ; "second"
0039    JMP      4 => 0042
0040    KPRI     4   1
0041    JMP      5 => 0043
0042 => KPRI     4   2
0043 => CALL     3   1   2
0044    GGET     3  10      ; "assert"
0045    TGETS    3   3  11  ; "is_true"
0046    TGETB    4   2   1
0047    TGETB    4   4   2
0048    TGETS    4   4  12  ; "id"
0049    ISEQS    4   4      ; "third2"
0050    JMP      4 => 0053
0051    KPRI     4   1
0052    JMP      5 => 0054
0053 => KPRI     4   2
0054 => CALL     3   1   2
0055    GGET     3  10      ; "assert"
0056    TGETS    3   3  11  ; "is_true"
0057    TGETB    4   2   1
0058    TGETB    4   4   3
0059    TGETS    4   4  12  ; "id"
0060    ISEQS    4   5      ; "third4"
0061    JMP      4 => 0064
0062    KPRI     4   1
0063    JMP      5 => 0065
0064 => KPRI     4   2
0065 => CALL     3   1   2
0066    RET0     0   1

-- BYTECODE -- menusorter_spec.lua:1-274
0001    KNIL     0   1
0002    GGET     2   0      ; "setup"
0003    FNEW     3   1      ; menusorter_spec.lua:4
0004    CALL     2   1   2
0005    GGET     2   2      ; "it"
0006    KSTR     3   3      ; "should put menu items in the defined ord"~
0007    FNEW     4   4      ; menusorter_spec.lua:10
0008    CALL     2   1   3
0009    GGET     2   2      ; "it"
0010    KSTR     3   5      ; "should attach submenus correctly"
0011    FNEW     4   6      ; menusorter_spec.lua:38
0012    CALL     2   1   3
0013    GGET     2   2      ; "it"
0014    KSTR     3   7      ; "should put orphans in the first menu"
0015    FNEW     4   8      ; menusorter_spec.lua:59
0016    CALL     2   1   3
0017    GGET     2   2      ; "it"
0018    KSTR     3   9      ; "should put orphans with sorting_hint in "~
0019    FNEW     4  10      ; menusorter_spec.lua:85
0020    CALL     2   1   3
0021    GGET     2   2      ; "it"
0022    KSTR     3  11      ; "should display submenu of orphaned subme"~
0023    FNEW     4  12      ; menusorter_spec.lua:158
0024    CALL     2   1   3
0025    GGET     2   2      ; "it"
0026    KSTR     3  13      ; "should not treat disabled as orphans"
0027    FNEW     4  14      ; menusorter_spec.lua:188
0028    CALL     2   1   3
0029    GGET     2   2      ; "it"
0030    KSTR     3  15      ; "should attach separator=true to previous"~
0031    FNEW     4  16      ; menusorter_spec.lua:210
0032    CALL     2   1   3
0033    GGET     2   2      ; "it"
0034    KSTR     3  17      ; "should ignore separator as first item"
0035    FNEW     4  18      ; menusorter_spec.lua:232
0036    CALL     2   1   3
0037    GGET     2   2      ; "it"
0038    KSTR     3  19      ; "should compress menus when items from or"~
0039    FNEW     4  20      ; menusorter_spec.lua:254
0040    CALL     2   1   3
0041    UCLO     0 => 0042
0042 => RET0     0   1

-- BYTECODE -- menusorter_spec.lua:0-275
0001    GGET     0   0      ; "describe"
0002    KSTR     1   1      ; "MenuSorter module"
0003    FNEW     2   2      ; menusorter_spec.lua:1
0004    CALL     0   1   3
0005    RET0     0   1

