-- BYTECODE -- menu.lua:46-81
0001    TGETS    1   0   0  ; "key"
0002    IST          1
0003    JMP      1 => 0005
0004    RET0     0   1
0005 => KSHORT   1   0
0006    UGET     2   0      ; Blitbuffer
0007    TGETS    2   2   1  ; "COLOR_WHITE"
0008    TGETS    3   0   2  ; "style"
0009    ISNES    3   3      ; "rounded_corner"
0010    JMP      3 => 0018
0011    GGET     3   4      ; "math"
0012    TGETS    3   3   5  ; "floor"
0013    TGETS    4   0   6  ; "width"
0014    DIVVN    4   4   0  ; 2
0015    CALL     3   2   2
0016    MOV      1   3
0017    JMP      3 => 0023
0018 => TGETS    3   0   2  ; "style"
0019    ISNES    3   7      ; "grey_square"
0020    JMP      3 => 0023
0021    UGET     3   0      ; Blitbuffer
0022    TGETS    2   3   8  ; "COLOR_LIGHT_GRAY"
0023 => KPRI     3   0
0024    TGETS    4   0   0  ; "key"
0025    MOV      5   4
0026    TGETS    4   4   9  ; "len"
0027    CALL     4   2   2
0028    KSHORT   5   1
0029    ISGE     5   4
0030    JMP      4 => 0039
0031    UGET     4   1      ; Font
0032    MOV      5   4
0033    TGETS    4   4  10  ; "getFace"
0034    KSTR     6  11      ; "ffont"
0035    KSHORT   7  14
0036    CALL     4   2   4
0037    MOV      3   4
0038    JMP      4 => 0046
0039 => UGET     4   1      ; Font
0040    MOV      5   4
0041    TGETS    4   4  10  ; "getFace"
0042    KSTR     6  12      ; "scfont"
0043    KSHORT   7  22
0044    CALL     4   2   4
0045    MOV      3   4
0046 => UGET     4   2      ; FrameContainer
0047    MOV      5   4
0048    TGETS    4   4  13  ; "new"
0049    TDUP     6  14
0050    TGETS    7   0  15  ; "bordersize"
0051    TSETS    7   6  15  ; "bordersize"
0052    TSETS    1   6  16  ; "radius"
0053    TSETS    2   6  17  ; "background"
0054    TGETS    7   0  18  ; "dimen"
0055    TSETS    7   6  18  ; "dimen"
0056    UGET     7   3      ; CenterContainer
0057    MOV      8   7
0058    TGETS    7   7  13  ; "new"
0059    TDUP     9  19
0060    TGETS   10   0  18  ; "dimen"
0061    TSETS   10   9  18  ; "dimen"
0062    UGET    10   4      ; TextWidget
0063    MOV     11  10
0064    TGETS   10  10  13  ; "new"
0065    TDUP    12  20
0066    TGETS   13   0   0  ; "key"
0067    TSETS   13  12  21  ; "text"
0068    TSETS    3  12  22  ; "face"
0069    CALL    10   0   3
0070    TSETM   10   1      ; 1
0071    CALL     7   0   3
0072    TSETM    7   1      ; 1
0073    CALL     4   2   3
0074    TSETB    4   0   1
0075    RET0     0   1

-- BYTECODE -- menu.lua:94-126
0001    UGET     1   0      ; TextWidget
0002    MOV      2   1
0003    TGETS    1   1   0  ; "new"
0004    TDUP     3   1
0005    UGET     4   1      ; Font
0006    MOV      5   4
0007    TGETS    4   4   2  ; "getFace"
0008    KSTR     6   3      ; "cfont"
0009    KSHORT   7  30
0010    CALL     4   2   4
0011    TSETS    4   3   4  ; "face"
0012    CALL     1   2   3
0013    MOV      3   1
0014    TGETS    2   1   5  ; "getSize"
0015    CALL     2   2   2
0016    TGETS    3   2   6  ; "h"
0017    TGETS    4   2   7  ; "w"
0018    SUBVV    3   3   4
0019    DIVVN    3   3   0  ; 2
0020    UGET     4   2      ; FrameContainer
0021    MOV      5   4
0022    TGETS    4   4   0  ; "new"
0023    TDUP     6   8
0024    TGETS    7   0   9  ; "padding_top"
0025    TSETS    7   6   9  ; "padding_top"
0026    TGETS    7   0  10  ; "padding_bottom"
0027    TSETS    7   6  10  ; "padding_bottom"
0028    TGETS    7   0  11  ; "padding_left"
0029    TSETS    7   6  11  ; "padding_left"
0030    TGETS    7   0  12  ; "padding_right"
0031    ADDVV    7   7   3
0032    TSETS    7   6  12  ; "padding_right"
0033    TSETB    1   6   1
0034    CALL     4   2   3
0035    TSETB    4   0   1
0036    UGET     4   3      ; Geom
0037    MOV      5   4
0038    TGETS    4   4   0  ; "new"
0039    TDUP     6  14
0040    TGETS    7   2   7  ; "w"
0041    ADDVV    7   7   3
0042    TGETS    8   0  12  ; "padding_right"
0043    ADDVV    7   7   8
0044    TSETS    7   6   7  ; "w"
0045    TGETS    7   2   6  ; "h"
0046    TSETS    7   6   6  ; "h"
0047    CALL     4   2   3
0048    TSETS    4   0  13  ; "dimen"
0049    TGETS    4   0  15  ; "ges_events"
0050    TDUP     5  19
0051    UGET     6   4      ; GestureRange
0052    MOV      7   6
0053    TGETS    6   6   0  ; "new"
0054    TDUP     8  17
0055    TGETS    9   0  13  ; "dimen"
0056    TSETS    9   8  18  ; "range"
0057    CALL     6   2   3
0058    TSETB    6   5   1
0059    TSETS    5   4  16  ; "Close"
0060    RET0     0   1

-- BYTECODE -- menu.lua:128-131
0001    TGETS    1   0   0  ; "menu"
0002    MOV      2   1
0003    TGETS    1   1   1  ; "onClose"
0004    CALL     1   1   2
0005    KPRI     1   2
0006    RET1     1   2

-- BYTECODE -- menu.lua:305-320
0001    UGET     1   0      ; item_name
0002    ISF          1
0003    JMP      2 => 0008
0004    UGET     1   0      ; item_name
0005    MOV      2   1
0006    TGETS    1   1   0  ; "free"
0007    CALL     1   1   2
0008 => UGET     1   1      ; logger
0009    TGETS    1   1   1  ; "dbg"
0010    KSTR     2   2      ; "multilines_show_more_text trying font si"~
0011    MOV      3   0
0012    CALL     1   1   3
0013    UGET     1   2      ; TextBoxWidget
0014    MOV      2   1
0015    TGETS    1   1   3  ; "new"
0016    TDUP     3   4
0017    UGET     4   3      ; text
0018    TSETS    4   3   5  ; "text"
0019    UGET     4   4      ; Font
0020    MOV      5   4
0021    TGETS    4   4   6  ; "getFace"
0022    UGET     6   5      ; self
0023    TGETS    6   6   7  ; "font"
0024    MOV      7   0
0025    CALL     4   2   4
0026    TSETS    4   3   8  ; "face"
0027    UGET     4   6      ; available_width
0028    TSETS    4   3   9  ; "width"
0029    UGET     4   5      ; self
0030    TGETS    4   4  10  ; "bold"
0031    TSETS    4   3  10  ; "bold"
0032    UGET     4   5      ; self
0033    TGETS    4   4  11  ; "dim"
0034    ISF          4
0035    JMP      5 => 0040
0036    UGET     4   7      ; Blitbuffer
0037    TGETS    4   4  12  ; "COLOR_DARK_GRAY"
0038    IST          4
0039    JMP      5 => 0041
0040 => KPRI     4   0
0041 => TSETS    4   3  13  ; "fgcolor"
0042    CALL     1   2   3
0043    USETV    0   1      ; item_name
0044    UGET     1   0      ; item_name
0045    MOV      2   1
0046    TGETS    1   1  14  ; "getSize"
0047    CALL     1   2   2
0048    TGETS    1   1  15  ; "h"
0049    UGET     2   8      ; max_item_height
0050    ISLE     1   2
0051    JMP      1 => 0054
0052    KPRI     1   1
0053    JMP      2 => 0055
0054 => KPRI     1   2
0055 => RET1     1   2

-- BYTECODE -- menu.lua:155-427
0001    TGETS    1   0   1  ; "dimen"
0002    TGETS    1   1   2  ; "w"
0003    UGET     2   0      ; Size
0004    TGETS    2   2   3  ; "padding"
0005    TGETS    2   2   4  ; "fullscreen"
0006    MULNV    2   2   0  ; 2
0007    SUBVV    1   1   2
0008    TSETS    1   0   0  ; "content_width"
0009    UGET     1   1      ; Geom
0010    MOV      2   1
0011    TGETS    1   1   5  ; "new"
0012    CALL     1   2   2
0013    TGETS    2   0   6  ; "shortcut"
0014    ISF          2
0015    JMP      3 => 0034
0016    GGET     2   7      ; "math"
0017    TGETS    2   2   8  ; "floor"
0018    TGETS    3   0   1  ; "dimen"
0019    TGETS    3   3   9  ; "h"
0020    MULVN    3   3   1  ; 4
0021    DIVVN    3   3   2  ; 5
0022    CALL     2   2   2
0023    TSETS    2   1   2  ; "w"
0024    TGETS    2   1   2  ; "w"
0025    TSETS    2   1   9  ; "h"
0026    TGETS    2   0   0  ; "content_width"
0027    TGETS    3   1   2  ; "w"
0028    SUBVV    2   2   3
0029    UGET     3   0      ; Size
0030    TGETS    3   3  10  ; "span"
0031    TGETS    3   3  11  ; "horizontal_default"
0032    SUBVV    2   2   3
0033    TSETS    2   0   0  ; "content_width"
0034 => TGETS    2   0  13  ; "text"
0035    TSETS    2   0  12  ; "detail"
0036    UGET     2   2      ; Device
0037    MOV      3   2
0038    TGETS    2   2  14  ; "isTouchDevice"
0039    CALL     2   2   2
0040    ISF          2
0041    JMP      3 => 0064
0042    TDUP     2  19
0043    TDUP     3  18
0044    UGET     4   3      ; GestureRange
0045    MOV      5   4
0046    TGETS    4   4   5  ; "new"
0047    TDUP     6  16
0048    TGETS    7   0   1  ; "dimen"
0049    TSETS    7   6  17  ; "range"
0050    CALL     4   2   3
0051    TSETB    4   3   1
0052    TSETS    3   2  20  ; "TapSelect"
0053    TDUP     3  22
0054    UGET     4   3      ; GestureRange
0055    MOV      5   4
0056    TGETS    4   4   5  ; "new"
0057    TDUP     6  21
0058    TGETS    7   0   1  ; "dimen"
0059    TSETS    7   6  17  ; "range"
0060    CALL     4   2   3
0061    TSETB    4   3   1
0062    TSETS    3   2  23  ; "HoldSelect"
0063    TSETS    2   0  15  ; "ges_events"
0064 => TGETS    2   0   1  ; "dimen"
0065    TGETS    2   2   9  ; "h"
0066    TGETS    3   0  24  ; "linesize"
0067    MULNV    3   3   0  ; 2
0068    SUBVV    2   2   3
0069    UGET     3   4      ; TextBoxWidget
0070    MOV      4   3
0071    TGETS    3   3  25  ; "getFontSizeToFitHeight"
0072    MOV      5   2
0073    KSHORT   6   1
0074    CALL     3   2   4
0075    TGETS    4   0  26  ; "font_size"
0076    ISGE     3   4
0077    JMP      4 => 0079
0078    TSETS    3   0  26  ; "font_size"
0079 => TGETS    4   0  27  ; "infont_size"
0080    ISGE     3   4
0081    JMP      4 => 0083
0082    TSETS    3   0  27  ; "infont_size"
0083 => GGET     4  28      ; "G_reader_settings"
0084    MOV      5   4
0085    TGETS    4   4  29  ; "isTrue"
0086    KSTR     6  30      ; "items_multilines_show_more_text"
0087    CALL     4   2   3
0088    TGETS    5   0  31  ; "single_line"
0089    IST          5
0090    JMP      5 => 0104
0091    IST          4
0092    JMP      5 => 0104
0093    UGET     5   4      ; TextBoxWidget
0094    MOV      6   5
0095    TGETS    5   5  25  ; "getFontSizeToFitHeight"
0096    MOV      7   2
0097    KSHORT   8   2
0098    CALL     5   2   4
0099    TGETS    6   0  26  ; "font_size"
0100    ISGE     5   6
0101    JMP      6 => 0104
0102    KPRI     6   2
0103    TSETS    6   0  31  ; "single_line"
0104 => TGETS    5   0  32  ; "state_size"
0105    TGETS    5   5   2  ; "w"
0106    IST          5
0107    JMP      6 => 0109
0108    KSHORT   5   0
0109 => TGETS    6   0  33  ; "state"
0110    IST          6
0111    JMP      7 => 0118
0112    UGET     6   5      ; HorizontalSpan
0113    MOV      7   6
0114    TGETS    6   6   5  ; "new"
0115    TDUP     8  34
0116    TSETS    5   8  35  ; "width"
0117    CALL     6   2   3
0118 => TGETS    7   0  33  ; "state"
0119    ISF          7
0120    JMP      8 => 0125
0121    TGETS    7   0  33  ; "state"
0122    TGETS    7   7  36  ; "indent"
0123    IST          7
0124    JMP      8 => 0126
0125 => KSTR     7  37      ; ""
0126 => UGET     8   6      ; LeftContainer
0127    MOV      9   8
0128    TGETS    8   8   5  ; "new"
0129    TDUP    10  39
0130    UGET    11   1      ; Geom
0131    MOV     12  11
0132    TGETS   11  11   5  ; "new"
0133    TDUP    13  38
0134    TGETS   14   0   0  ; "content_width"
0135    DIVVN   14  14   0  ; 2
0136    TSETS   14  13   2  ; "w"
0137    TGETS   14   0   1  ; "dimen"
0138    TGETS   14  14   9  ; "h"
0139    TSETS   14  13   9  ; "h"
0140    CALL    11   2   3
0141    TSETS   11  10   1  ; "dimen"
0142    UGET    11   7      ; HorizontalGroup
0143    MOV     12  11
0144    TGETS   11  11   5  ; "new"
0145    TNEW    13   3
0146    UGET    14   8      ; TextWidget
0147    MOV     15  14
0148    TGETS   14  14   5  ; "new"
0149    TDUP    16  40
0150    TSETS    7  16  13  ; "text"
0151    UGET    17   9      ; Font
0152    MOV     18  17
0153    TGETS   17  17  41  ; "getFace"
0154    TGETS   19   0  42  ; "font"
0155    TGETS   20   0  26  ; "font_size"
0156    CALL    17   2   4
0157    TSETS   17  16  43  ; "face"
0158    CALL    14   2   3
0159    TSETB   14  13   1
0160    TSETB    6  13   2
0161    CALL    11   0   3
0162    TSETM   11   3      ; 1
0163    CALL     8   2   3
0164    UGET     9   9      ; Font
0165    MOV     10   9
0166    TGETS    9   9  41  ; "getFace"
0167    TGETS   11   0  42  ; "font"
0168    TGETS   12   0  26  ; "font_size"
0169    CALL     9   2   4
0170    TSETS    9   0  43  ; "face"
0171    UGET     9   9      ; Font
0172    MOV     10   9
0173    TGETS    9   9  41  ; "getFace"
0174    TGETS   11   0  45  ; "infont"
0175    TGETS   12   0  27  ; "infont_size"
0176    CALL     9   2   4
0177    TSETS    9   0  44  ; "info_face"
0178    KSHORT   9   0
0179    KSHORT  10   0
0180    TGETS   11   0  46  ; "mandatory"
0181    ISF         11
0182    JMP     12 => 0189
0183    UGET    11   0      ; Size
0184    TGETS   11  11  10  ; "span"
0185    TGETS    9  11  11  ; "horizontal_default"
0186    UGET    11   0      ; Size
0187    TGETS   11  11  10  ; "span"
0188    TGETS   10  11  47  ; "horizontal_small"
0189 => TGETS   11   0  46  ; "mandatory"
0190    ISF         11
0191    JMP     12 => 0197
0192    KSTR    11  37      ; ""
0193    TGETS   12   0  46  ; "mandatory"
0194    CAT     11  11  12
0195    IST         11
0196    JMP     12 => 0198
0197 => KSTR    11  37      ; ""
0198 => UGET    12   8      ; TextWidget
0199    MOV     13  12
0200    TGETS   12  12   5  ; "new"
0201    TDUP    14  48
0202    TSETS   11  14  13  ; "text"
0203    TGETS   15   0  44  ; "info_face"
0204    TSETS   15  14  43  ; "face"
0205    TGETS   15   0  49  ; "bold"
0206    TSETS   15  14  49  ; "bold"
0207    TGETS   15   0  50  ; "dim"
0208    ISF         15
0209    JMP     16 => 0214
0210    UGET    15  10      ; Blitbuffer
0211    TGETS   15  15  51  ; "COLOR_DARK_GRAY"
0212    IST         15
0213    JMP     16 => 0215
0214 => KPRI    15   0
0215 => TSETS   15  14  52  ; "fgcolor"
0216    CALL    12   2   3
0217    MOV     14  12
0218    TGETS   13  12  53  ; "getWidth"
0219    CALL    13   2   2
0220    TGETS   14   0   0  ; "content_width"
0221    SUBVV   14  14   5
0222    SUBVV   14  14   9
0223    SUBVV   14  14  13
0224    KPRI    15   0
0225    TGETS   16   0  13  ; "text"
0226    MOV     17  16
0227    TGETS   16  16  54  ; "gsub"
0228    KSTR    18  55      ; "\n"
0229    KSTR    19  56      ; " "
0230    CALL    16   2   4
0231    TGETS   17   0  57  ; "bidi_wrap_func"
0232    ISF         17
0233    JMP     18 => 0238
0234    TGETS   17   0  57  ; "bidi_wrap_func"
0235    MOV     18  16
0236    CALL    17   2   2
0237    MOV     16  17
0238 => TGETS   17   0  31  ; "single_line"
0239    ISF         17
0240    JMP     18 => 0322
0241    UGET    17   8      ; TextWidget
0242    MOV     18  17
0243    TGETS   17  17   5  ; "new"
0244    TDUP    19  58
0245    TSETS   16  19  13  ; "text"
0246    TGETS   20   0  43  ; "face"
0247    TSETS   20  19  43  ; "face"
0248    TGETS   20   0  49  ; "bold"
0249    TSETS   20  19  49  ; "bold"
0250    TGETS   20   0  50  ; "dim"
0251    ISF         20
0252    JMP     21 => 0257
0253    UGET    20  10      ; Blitbuffer
0254    TGETS   20  20  51  ; "COLOR_DARK_GRAY"
0255    IST         20
0256    JMP     21 => 0258
0257 => KPRI    20   0
0258 => TSETS   20  19  52  ; "fgcolor"
0259    CALL    17   2   3
0260    MOV     15  17
0261    MOV     18  15
0262    TGETS   17  15  53  ; "getWidth"
0263    CALL    17   2   2
0264    ISGE    14  17
0265    JMP     18 => 0272
0266    ADDVV   18  14   9
0267    SUBVV   18  18  10
0268    MOV     20  15
0269    TGETS   19  15  59  ; "setMaxWidth"
0270    MOV     21  18
0271    CALL    19   1   3
0272 => TGETS   18   0  60  ; "align_baselines"
0273    ISF         18
0274    JMP     19 => 0403
0275    MOV     19  15
0276    TGETS   18  15  61  ; "getBaseline"
0277    CALL    18   2   2
0278    MOV     20  12
0279    TGETS   19  12  61  ; "getBaseline"
0280    CALL    19   2   2
0281    UGET    20  11      ; Math
0282    TGETS   20  20  62  ; "round"
0283    SUBVV   21  18  19
0284    CALL    20   2   2
0285    KSHORT  21   0
0286    ISGE    21  20
0287    JMP     21 => 0303
0288    UGET    21  12      ; VerticalGroup
0289    MOV     22  21
0290    TGETS   21  21   5  ; "new"
0291    TNEW    23   3
0292    UGET    24  13      ; VerticalSpan
0293    MOV     25  24
0294    TGETS   24  24   5  ; "new"
0295    TDUP    26  63
0296    TSETS   20  26  35  ; "width"
0297    CALL    24   2   3
0298    TSETB   24  23   1
0299    TSETB   12  23   2
0300    CALL    21   2   3
0301    MOV     12  21
0302    JMP     21 => 0403
0303 => KSHORT  21   0
0304    ISGE    20  21
0305    JMP     21 => 0403
0306    UGET    21  12      ; VerticalGroup
0307    MOV     22  21
0308    TGETS   21  21   5  ; "new"
0309    TNEW    23   3
0310    UGET    24  13      ; VerticalSpan
0311    MOV     25  24
0312    TGETS   24  24   5  ; "new"
0313    TDUP    26  64
0314    UNM     27  20
0315    TSETS   27  26  35  ; "width"
0316    CALL    24   2   3
0317    TSETB   24  23   1
0318    TSETB   15  23   2
0319    CALL    21   2   3
0320    MOV     15  21
0321    JMP     17 => 0403
0322 => ISF          4
0323    JMP     17 => 0381
0324    UGET    17  14      ; logger
0325    TGETS   17  17  65  ; "dbg"
0326    KSTR    18  66      ; "multilines_show_more_text menu item font"~
0327    CALL    17   1   2
0328    FNEW    17  67      ; menu.lua:305
0329    KSHORT  18  12
0330    MOV     19  17
0331    TGETS   20   0  26  ; "font_size"
0332    CALL    19   2   2
0333    IST         19
0334    JMP     19 => 0403
0335    MOV     19  17
0336    MOV     20  18
0337    CALL    19   2   2
0338    IST         19
0339    JMP     19 => 0352
0340    MOV     20  15
0341    TGETS   19  15  68  ; "free"
0342    CALL    19   1   2
0343    TSETS    2  15  69  ; "height"
0344    KPRI    19   2
0345    TSETS   19  15  70  ; "height_adjust"
0346    KPRI    19   2
0347    TSETS   19  15  71  ; "height_overflow_show_ellipsis"
0348    MOV     20  15
0349    TGETS   19  15  72  ; "init"
0350    CALL    19   1   2
0351    JMP     19 => 0403
0352 => TGETS   19   0  26  ; "font_size"
0353    MOV     20  18
0354    KPRI    21   2
0355 => LOOP    22 => 0380
0356    GGET    22   7      ; "math"
0357    TGETS   22  22   8  ; "floor"
0358    ADDVV   23  20  19
0359    DIVVN   23  23   0  ; 2
0360    CALL    22   2   2
0361    ISNEV   22  20
0362    JMP     23 => 0369
0363    IST         21
0364    JMP     23 => 0403
0365    MOV     23  17
0366    MOV     24  20
0367    CALL    23   1   2
0368    JMP     22 => 0403
0369 => MOV     23  17
0370    MOV     24  22
0371    CALL    23   2   2
0372    ISF         23
0373    JMP     24 => 0377
0374    MOV     20  22
0375    KPRI    21   2
0376    JMP     23 => 0355
0377 => MOV     19  22
0378    KPRI    21   1
0379    JMP     22 => 0355
0380 => JMP     17 => 0403
0381 => UGET    17   4      ; TextBoxWidget
0382    MOV     18  17
0383    TGETS   17  17   5  ; "new"
0384    TDUP    19  73
0385    TSETS   16  19  13  ; "text"
0386    TGETS   20   0  43  ; "face"
0387    TSETS   20  19  43  ; "face"
0388    TSETS   14  19  35  ; "width"
0389    TSETS    2  19  69  ; "height"
0390    TGETS   20   0  49  ; "bold"
0391    TSETS   20  19  49  ; "bold"
0392    TGETS   20   0  50  ; "dim"
0393    ISF         20
0394    JMP     21 => 0399
0395    UGET    20  10      ; Blitbuffer
0396    TGETS   20  20  51  ; "COLOR_DARK_GRAY"
0397    IST         20
0398    JMP     21 => 0400
0399 => KPRI    20   0
0400 => TSETS   20  19  52  ; "fgcolor"
0401    CALL    17   2   3
0402    MOV     15  17
0403 => UGET    17   6      ; LeftContainer
0404    MOV     18  17
0405    TGETS   17  17   5  ; "new"
0406    TDUP    19  75
0407    UGET    20   1      ; Geom
0408    MOV     21  20
0409    TGETS   20  20   5  ; "new"
0410    TDUP    22  74
0411    TGETS   23   0   0  ; "content_width"
0412    TSETS   23  22   2  ; "w"
0413    TGETS   23   0   1  ; "dimen"
0414    TGETS   23  23   9  ; "h"
0415    TSETS   23  22   9  ; "h"
0416    CALL    20   2   3
0417    TSETS   20  19   1  ; "dimen"
0418    UGET    20   7      ; HorizontalGroup
0419    MOV     21  20
0420    TGETS   20  20   5  ; "new"
0421    TNEW    22   3
0422    UGET    23   5      ; HorizontalSpan
0423    MOV     24  23
0424    TGETS   23  23   5  ; "new"
0425    TDUP    25  76
0426    TGETS   26   0  32  ; "state_size"
0427    TGETS   26  26   2  ; "w"
0428    TSETS   26  25  35  ; "width"
0429    CALL    23   2   3
0430    TSETB   23  22   1
0431    TSETB   15  22   2
0432    CALL    20   0   3
0433    TSETM   20   3      ; 1
0434    CALL    17   2   3
0435    UGET    18  15      ; RightContainer
0436    MOV     19  18
0437    TGETS   18  18   5  ; "new"
0438    TDUP    20  78
0439    UGET    21   1      ; Geom
0440    MOV     22  21
0441    TGETS   21  21   5  ; "new"
0442    TDUP    23  77
0443    TGETS   24   0   0  ; "content_width"
0444    TSETS   24  23   2  ; "w"
0445    TGETS   24   0   1  ; "dimen"
0446    TGETS   24  24   9  ; "h"
0447    TSETS   24  23   9  ; "h"
0448    CALL    21   2   3
0449    TSETS   21  20   1  ; "dimen"
0450    TSETB   12  20   1
0451    CALL    18   2   3
0452    UGET    19  16      ; UnderlineContainer
0453    MOV     20  19
0454    TGETS   19  19   5  ; "new"
0455    TDUP    21  81
0456    TGETS   22   0  80  ; "line_color"
0457    TSETS   22  21  82  ; "color"
0458    TGETS   22   0  24  ; "linesize"
0459    TSETS   22  21  24  ; "linesize"
0460    UGET    22   1      ; Geom
0461    MOV     23  22
0462    TGETS   22  22   5  ; "new"
0463    TDUP    24  83
0464    TGETS   25   0   0  ; "content_width"
0465    TSETS   25  24   2  ; "w"
0466    TGETS   25   0   1  ; "dimen"
0467    TGETS   25  25   9  ; "h"
0468    TSETS   25  24   9  ; "h"
0469    CALL    22   2   3
0470    TSETS   22  21   1  ; "dimen"
0471    UGET    22   7      ; HorizontalGroup
0472    MOV     23  22
0473    TGETS   22  22   5  ; "new"
0474    TDUP    24  84
0475    UGET    25  17      ; OverlapGroup
0476    MOV     26  25
0477    TGETS   25  25   5  ; "new"
0478    TDUP    27  86
0479    UGET    28   1      ; Geom
0480    MOV     29  28
0481    TGETS   28  28   5  ; "new"
0482    TDUP    30  85
0483    TGETS   31   0   0  ; "content_width"
0484    TSETS   31  30   2  ; "w"
0485    TGETS   31   0   1  ; "dimen"
0486    TGETS   31  31   9  ; "h"
0487    TSETS   31  30   9  ; "h"
0488    CALL    28   2   3
0489    TSETS   28  27   1  ; "dimen"
0490    TSETB    8  27   1
0491    TSETB   17  27   2
0492    TSETB   18  27   3
0493    CALL    25   0   3
0494    TSETM   25   3      ; 1
0495    CALL    22   0   3
0496    TSETM   22   3      ; 1
0497    CALL    19   2   3
0498    TSETS   19   0  79  ; "_underline_container"
0499    UGET    19   7      ; HorizontalGroup
0500    MOV     20  19
0501    TGETS   19  19   5  ; "new"
0502    TDUP    21  87
0503    UGET    22   5      ; HorizontalSpan
0504    MOV     23  22
0505    TGETS   22  22   5  ; "new"
0506    TDUP    24  88
0507    UGET    25   0      ; Size
0508    TGETS   25  25   3  ; "padding"
0509    TGETS   25  25   4  ; "fullscreen"
0510    TSETS   25  24  35  ; "width"
0511    CALL    22   0   3
0512    TSETM   22   3      ; 1
0513    CALL    19   2   3
0514    TGETS   20   0   6  ; "shortcut"
0515    ISF         20
0516    JMP     21 => 0544
0517    GGET    20  89      ; "table"
0518    TGETS   20  20  90  ; "insert"
0519    MOV     21  19
0520    UGET    22  18      ; ItemShortCutIcon
0521    MOV     23  22
0522    TGETS   22  22   5  ; "new"
0523    TDUP    24  91
0524    TSETS    1  24   1  ; "dimen"
0525    TGETS   25   0   6  ; "shortcut"
0526    TSETS   25  24  92  ; "key"
0527    TGETS   25   0  93  ; "shortcut_style"
0528    TSETS   25  24  94  ; "style"
0529    CALL    22   0   3
0530    CALLM   20   1   1
0531    GGET    20  89      ; "table"
0532    TGETS   20  20  90  ; "insert"
0533    MOV     21  19
0534    UGET    22   5      ; HorizontalSpan
0535    MOV     23  22
0536    TGETS   22  22   5  ; "new"
0537    TDUP    24  95
0538    UGET    25   0      ; Size
0539    TGETS   25  25  10  ; "span"
0540    TGETS   25  25  11  ; "horizontal_default"
0541    TSETS   25  24  35  ; "width"
0542    CALL    22   0   3
0543    CALLM   20   1   1
0544 => GGET    20  89      ; "table"
0545    TGETS   20  20  90  ; "insert"
0546    MOV     21  19
0547    TGETS   22   0  79  ; "_underline_container"
0548    CALL    20   1   3
0549    GGET    20  89      ; "table"
0550    TGETS   20  20  90  ; "insert"
0551    MOV     21  19
0552    UGET    22   5      ; HorizontalSpan
0553    MOV     23  22
0554    TGETS   22  22   5  ; "new"
0555    TDUP    24  96
0556    UGET    25   0      ; Size
0557    TGETS   25  25   3  ; "padding"
0558    TGETS   25  25   4  ; "fullscreen"
0559    TSETS   25  24  35  ; "width"
0560    CALL    22   0   3
0561    CALLM   20   1   1
0562    UGET    20  19      ; FrameContainer
0563    MOV     21  20
0564    TGETS   20  20   5  ; "new"
0565    TDUP    22  97
0566    TSETB   19  22   1
0567    CALL    20   2   3
0568    TSETB   20   0   1
0569    UCLO     0 => 0570
0570 => RET0     0   1

-- BYTECODE -- menu.lua:429-444
0001    UGET     2   0      ; Device
0002    MOV      3   2
0003    TGETS    2   2   0  ; "isTouchDevice"
0004    CALL     2   2   2
0005    ISF          2
0006    JMP      3 => 0021
0007    ISF          1
0008    JMP      2 => 0013
0009    TGETS    2   0   1  ; "menu"
0010    TGETS    2   2   2  ; "did_focus_with_keys"
0011    ISF          2
0012    JMP      3 => 0025
0013 => TGETS    2   0   3  ; "_underline_container"
0014    UGET     3   1      ; Blitbuffer
0015    TGETS    3   3   5  ; "COLOR_BLACK"
0016    TSETS    3   2   4  ; "color"
0017    TGETS    2   0   1  ; "menu"
0018    KPRI     3   2
0019    TSETS    3   2   2  ; "did_focus_with_keys"
0020    JMP      2 => 0025
0021 => TGETS    2   0   3  ; "_underline_container"
0022    UGET     3   1      ; Blitbuffer
0023    TGETS    3   3   5  ; "COLOR_BLACK"
0024    TSETS    3   2   4  ; "color"
0025 => KPRI     2   2
0026    RET1     2   2

-- BYTECODE -- menu.lua:446-449
0001    TGETS    1   0   0  ; "_underline_container"
0002    TGETS    2   0   2  ; "line_color"
0003    TSETS    2   1   1  ; "color"
0004    KPRI     1   2
0005    RET1     1   2

-- BYTECODE -- menu.lua:451-454
0001    UGET     1   0      ; UIManager
0002    MOV      2   1
0003    TGETS    1   1   0  ; "show"
0004    UGET     3   1      ; InfoMessage
0005    MOV      4   3
0006    TGETS    3   3   1  ; "new"
0007    TDUP     5   3
0008    TGETS    6   0   2  ; "detail"
0009    TSETS    6   5   4  ; "text"
0010    CALL     3   0   3
0011    CALLM    1   1   1
0012    KPRI     1   2
0013    RET1     1   2

-- BYTECODE -- menu.lua:456-462
0001    TGETB    2   0   1
0002    TGETS    2   2   0  ; "dimen"
0003    TDUP     3   4
0004    TGETS    4   1   1  ; "pos"
0005    TGETS    4   4   2  ; "x"
0006    TGETS    5   2   2  ; "x"
0007    SUBVV    4   4   5
0008    TGETS    5   2   3  ; "w"
0009    DIVVV    4   4   5
0010    TSETS    4   3   2  ; "x"
0011    TGETS    4   1   1  ; "pos"
0012    TGETS    4   4   5  ; "y"
0013    TGETS    5   2   5  ; "y"
0014    SUBVV    4   4   5
0015    TGETS    5   2   6  ; "h"
0016    DIVVV    4   4   5
0017    TSETS    4   3   5  ; "y"
0018    RET1     3   2

-- BYTECODE -- menu.lua:468-470
0001    UGET     0   0      ; self
0002    TGETS    0   0   0  ; "menu"
0003    MOV      1   0
0004    TGETS    0   0   1  ; "onMenuSelect"
0005    UGET     2   0      ; self
0006    TGETS    2   2   2  ; "table"
0007    UGET     3   1      ; pos
0008    CALL     0   1   4
0009    RET0     0   1

-- BYTECODE -- menu.lua:475-477
0001    KSTR     0   0      ; "fast"
0002    UGET     1   0      ; self
0003    TGETB    1   1   1
0004    TGETS    1   1   1  ; "dimen"
0005    RET      0   3

-- BYTECODE -- menu.lua:480-482
0001    UGET     0   0      ; self
0002    TGETS    0   0   0  ; "menu"
0003    MOV      1   0
0004    TGETS    0   0   1  ; "onMenuSelect"
0005    UGET     2   0      ; self
0006    TGETS    2   2   2  ; "table"
0007    UGET     3   1      ; pos
0008    CALL     0   1   4
0009    RET0     0   1

-- BYTECODE -- menu.lua:486-488
0001    KSTR     0   0      ; "ui"
0002    UGET     1   0      ; self
0003    TGETB    1   1   1
0004    TGETS    1   1   1  ; "dimen"
0005    RET      0   3

-- BYTECODE -- menu.lua:478-489
0001    UGET     0   0      ; logger
0002    TGETS    0   0   0  ; "dbg"
0003    KSTR     1   1      ; "creating coroutine for menu select"
0004    CALL     0   1   2
0005    GGET     0   2      ; "coroutine"
0006    TGETS    0   0   3  ; "create"
0007    FNEW     1   4      ; menu.lua:480
0008    CALL     0   2   2
0009    GGET     1   2      ; "coroutine"
0010    TGETS    1   1   5  ; "resume"
0011    MOV      2   0
0012    CALL     1   1   2
0013    UGET     1   1      ; self
0014    TGETB    1   1   1
0015    KPRI     2   1
0016    TSETS    2   1   6  ; "invert"
0017    UGET     1   3      ; UIManager
0018    MOV      2   1
0019    TGETS    1   1   7  ; "setDirty"
0020    UGET     3   1      ; self
0021    TGETS    3   3   8  ; "show_parent"
0022    FNEW     4   9      ; menu.lua:486
0023    CALL     1   1   4
0024    RET0     0   1

-- BYTECODE -- menu.lua:464-492
0001    MOV      4   0
0002    TGETS    3   0   0  ; "getGesPosition"
0003    MOV      5   2
0004    CALL     3   2   3
0005    GGET     4   1      ; "G_reader_settings"
0006    MOV      5   4
0007    TGETS    4   4   2  ; "isFalse"
0008    KSTR     6   3      ; "flash_ui"
0009    CALL     4   2   3
0010    ISF          4
0011    JMP      5 => 0025
0012    UGET     4   0      ; logger
0013    TGETS    4   4   4  ; "dbg"
0014    KSTR     5   5      ; "creating coroutine for menu select"
0015    CALL     4   1   2
0016    GGET     4   6      ; "coroutine"
0017    TGETS    4   4   7  ; "create"
0018    FNEW     5   8      ; menu.lua:468
0019    CALL     4   2   2
0020    GGET     5   6      ; "coroutine"
0021    TGETS    5   5   9  ; "resume"
0022    MOV      6   4
0023    CALL     5   1   2
0024    JMP      4 => 0050
0025 => TGETB    4   0   1
0026    KPRI     5   2
0027    TSETS    5   4  10  ; "invert"
0028    UGET     4   1      ; UIManager
0029    MOV      5   4
0030    TGETS    4   4  11  ; "widgetRepaint"
0031    TGETB    6   0   1
0032    TGETB    7   0   1
0033    TGETS    7   7  12  ; "dimen"
0034    TGETS    7   7  13  ; "x"
0035    TGETB    8   0   1
0036    TGETS    8   8  12  ; "dimen"
0037    TGETS    8   8  14  ; "y"
0038    CALL     4   1   5
0039    UGET     4   1      ; UIManager
0040    MOV      5   4
0041    TGETS    4   4  15  ; "setDirty"
0042    KPRI     6   0
0043    FNEW     7  16      ; menu.lua:475
0044    CALL     4   1   4
0045    UGET     4   1      ; UIManager
0046    MOV      5   4
0047    TGETS    4   4  17  ; "tickAfterNext"
0048    FNEW     6  18      ; menu.lua:478
0049    CALL     4   1   3
0050 => KPRI     4   2
0051    UCLO     0 => 0052
0052 => RET1     4   2

-- BYTECODE -- menu.lua:501-503
0001    KSTR     0   0      ; "fast"
0002    UGET     1   0      ; self
0003    TGETB    1   1   1
0004    TGETS    1   1   1  ; "dimen"
0005    RET      0   3

-- BYTECODE -- menu.lua:508-510
0001    KSTR     0   0      ; "ui"
0002    UGET     1   0      ; self
0003    TGETB    1   1   1
0004    TGETS    1   1   1  ; "dimen"
0005    RET      0   3

-- BYTECODE -- menu.lua:504-511
0001    UGET     0   0      ; self
0002    TGETS    0   0   0  ; "menu"
0003    MOV      1   0
0004    TGETS    0   0   1  ; "onMenuHold"
0005    UGET     2   0      ; self
0006    TGETS    2   2   2  ; "table"
0007    UGET     3   1      ; pos
0008    CALL     0   1   4
0009    UGET     0   0      ; self
0010    TGETB    0   0   1
0011    KPRI     1   1
0012    TSETS    1   0   3  ; "invert"
0013    UGET     0   2      ; UIManager
0014    MOV      1   0
0015    TGETS    0   0   4  ; "setDirty"
0016    UGET     2   0      ; self
0017    TGETS    2   2   5  ; "show_parent"
0018    FNEW     3   6      ; menu.lua:508
0019    CALL     0   1   4
0020    RET0     0   1

-- BYTECODE -- menu.lua:494-514
0001    MOV      4   0
0002    TGETS    3   0   0  ; "getGesPosition"
0003    MOV      5   2
0004    CALL     3   2   3
0005    GGET     4   1      ; "G_reader_settings"
0006    MOV      5   4
0007    TGETS    4   4   2  ; "isFalse"
0008    KSTR     6   3      ; "flash_ui"
0009    CALL     4   2   3
0010    ISF          4
0011    JMP      5 => 0019
0012    TGETS    4   0   4  ; "menu"
0013    MOV      5   4
0014    TGETS    4   4   5  ; "onMenuHold"
0015    TGETS    6   0   6  ; "table"
0016    MOV      7   3
0017    CALL     4   1   4
0018    JMP      4 => 0044
0019 => TGETB    4   0   1
0020    KPRI     5   2
0021    TSETS    5   4   7  ; "invert"
0022    UGET     4   0      ; UIManager
0023    MOV      5   4
0024    TGETS    4   4   8  ; "widgetRepaint"
0025    TGETB    6   0   1
0026    TGETB    7   0   1
0027    TGETS    7   7   9  ; "dimen"
0028    TGETS    7   7  10  ; "x"
0029    TGETB    8   0   1
0030    TGETS    8   8   9  ; "dimen"
0031    TGETS    8   8  11  ; "y"
0032    CALL     4   1   5
0033    UGET     4   0      ; UIManager
0034    MOV      5   4
0035    TGETS    4   4  12  ; "setDirty"
0036    KPRI     6   0
0037    FNEW     7  13      ; menu.lua:501
0038    CALL     4   1   4
0039    UGET     4   0      ; UIManager
0040    MOV      5   4
0041    TGETS    4   4  14  ; "tickAfterNext"
0042    FNEW     6  15      ; menu.lua:504
0043    CALL     4   1   3
0044 => KPRI     4   2
0045    UCLO     0 => 0046
0046 => RET1     4   2

-- BYTECODE -- menu.lua:570-598
0001    TGETS    1   0   1  ; "perpage_custom"
0002    IST          1
0003    JMP      2 => 0012
0004    GGET     1   2      ; "G_reader_settings"
0005    MOV      2   1
0006    TGETS    1   1   3  ; "readSetting"
0007    KSTR     3   4      ; "items_per_page"
0008    CALL     1   2   3
0009    IST          1
0010    JMP      2 => 0012
0011    KSHORT   1  14
0012 => TSETS    1   0   0  ; "perpage"
0013    KSHORT   1   0
0014    TSETS    1   0   5  ; "span_width"
0015    TGETS    1   0   6  ; "dimen"
0016    TGETS    2   0   8  ; "width"
0017    TSETS    2   1   7  ; "w"
0018    TGETS    1   0   6  ; "dimen"
0019    TGETS    2   0  10  ; "height"
0020    IST          2
0021    JMP      3 => 0026
0022    UGET     2   0      ; Screen
0023    MOV      3   2
0024    TGETS    2   2  11  ; "getHeight"
0025    CALL     2   2   2
0026 => TSETS    2   1   9  ; "h"
0027    TGETS    1   0   6  ; "dimen"
0028    TGETS    1   1   9  ; "h"
0029    UGET     2   0      ; Screen
0030    MOV      3   2
0031    TGETS    2   2  11  ; "getHeight"
0032    CALL     2   2   2
0033    ISLT     2   1
0034    JMP      1 => 0039
0035    TGETS    1   0   6  ; "dimen"
0036    TGETS    1   1   9  ; "h"
0037    ISNEP    1   0
0038    JMP      1 => 0045
0039 => TGETS    1   0   6  ; "dimen"
0040    UGET     2   0      ; Screen
0041    MOV      3   2
0042    TGETS    2   2  11  ; "getHeight"
0043    CALL     2   2   2
0044    TSETS    2   1   9  ; "h"
0045 => UGET     1   1      ; Geom
0046    MOV      2   1
0047    TGETS    1   1  13  ; "new"
0048    TDUP     3  14
0049    TGETS    4   0   6  ; "dimen"
0050    TGETS    4   4   7  ; "w"
0051    TSETS    4   3   7  ; "w"
0052    UGET     4   0      ; Screen
0053    MOV      5   4
0054    TGETS    4   4  15  ; "scaleBySize"
0055    KSHORT   6  46
0056    CALL     4   2   3
0057    TSETS    4   3   9  ; "h"
0058    CALL     1   2   3
0059    TSETS    1   0  12  ; "item_dimen"
0060    KPRI     1   0
0061    KSHORT   2   0
0062    KSHORT   3   0
0063    TGETS    4   0  16  ; "page_return_arrow"
0064    ISF          4
0065    JMP      5 => 0087
0066    TGETS    4   0  17  ; "page_info_text"
0067    ISF          4
0068    JMP      5 => 0087
0069    GGET     4  18      ; "math"
0070    TGETS    4   4  19  ; "max"
0071    TGETS    5   0  16  ; "page_return_arrow"
0072    MOV      6   5
0073    TGETS    5   5  20  ; "getSize"
0074    CALL     5   2   2
0075    TGETS    5   5   9  ; "h"
0076    TGETS    6   0  17  ; "page_info_text"
0077    MOV      7   6
0078    TGETS    6   6  20  ; "getSize"
0079    CALL     6   2   2
0080    TGETS    6   6   9  ; "h"
0081    CALL     4   2   3
0082    UGET     5   2      ; Size
0083    TGETS    5   5  21  ; "padding"
0084    TGETS    5   5  22  ; "button"
0085    MULNV    5   5   0  ; 2
0086    ADDVV    2   4   5
0087 => TGETS    4   0  23  ; "menu_title"
0088    ISF          4
0089    JMP      5 => 0103
0090    TGETS    4   0  24  ; "no_title"
0091    IST          4
0092    JMP      4 => 0103
0093    TGETS    4   0  25  ; "menu_title_group"
0094    MOV      5   4
0095    TGETS    4   4  20  ; "getSize"
0096    CALL     4   2   2
0097    TGETS    4   4   9  ; "h"
0098    UGET     5   2      ; Size
0099    TGETS    5   5  21  ; "padding"
0100    TGETS    5   5  26  ; "small"
0101    MULNV    5   5   0  ; 2
0102    ADDVV    3   4   5
0103 => TGETS    4   0   6  ; "dimen"
0104    TGETS    4   4   9  ; "h"
0105    SUBVV    4   4   2
0106    SUBVV    1   4   3
0107    TGETS    4   0  12  ; "item_dimen"
0108    GGET     5  18      ; "math"
0109    TGETS    5   5  27  ; "floor"
0110    TGETS    6   0   0  ; "perpage"
0111    DIVVV    6   1   6
0112    CALL     5   2   2
0113    TSETS    5   4   9  ; "h"
0114    GGET     4  18      ; "math"
0115    TGETS    4   4  27  ; "floor"
0116    TGETS    5   0   0  ; "perpage"
0117    TGETS    6   0  12  ; "item_dimen"
0118    TGETS    6   6   9  ; "h"
0119    MULVV    5   5   6
0120    SUBVV    5   1   5
0121    DIVVN    5   5   0  ; 2
0122    SUBVN    5   5   1  ; 1
0123    CALL     4   2   2
0124    TSETS    4   0   5  ; "span_width"
0125    GGET     4  18      ; "math"
0126    TGETS    4   4  29  ; "ceil"
0127    TGETS    5   0  30  ; "item_table"
0128    LEN      5   5
0129    TGETS    6   0   0  ; "perpage"
0130    DIVVV    5   5   6
0131    CALL     4   2   2
0132    TSETS    4   0  28  ; "page_num"
0133    TGETS    4   0  28  ; "page_num"
0134    KSHORT   5   0
0135    ISGE     5   4
0136    JMP      4 => 0143
0137    TGETS    4   0  31  ; "page"
0138    TGETS    5   0  28  ; "page_num"
0139    ISGE     5   4
0140    JMP      4 => 0143
0141    TGETS    4   0  28  ; "page_num"
0142    TSETS    4   0  31  ; "page"
0143 => RET0     0   1

-- BYTECODE -- menu.lua:670-670
0001    UGET     0   0      ; self
0002    MOV      1   0
0003    TGETS    0   0   0  ; "onPrevPage"
0004    CALL     0   1   2
0005    RET0     0   1

-- BYTECODE -- menu.lua:676-676
0001    UGET     0   0      ; self
0002    MOV      1   0
0003    TGETS    0   0   0  ; "onNextPage"
0004    CALL     0   1   2
0005    RET0     0   1

-- BYTECODE -- menu.lua:682-682
0001    UGET     0   0      ; self
0002    MOV      1   0
0003    TGETS    0   0   0  ; "onFirstPage"
0004    CALL     0   1   2
0005    RET0     0   1

-- BYTECODE -- menu.lua:688-688
0001    UGET     0   0      ; self
0002    MOV      1   0
0003    TGETS    0   0   0  ; "onLastPage"
0004    CALL     0   1   2
0005    RET0     0   1

-- BYTECODE -- menu.lua:705-707
0001    UGET     0   0      ; self
0002    TGETS    0   0   0  ; "page_info_text"
0003    MOV      1   0
0004    TGETS    0   0   1  ; "closeInputDialog"
0005    CALL     0   1   2
0006    RET0     0   1

-- BYTECODE -- menu.lua:712-718
0001    GGET     0   0      ; "tonumber"
0002    UGET     1   0      ; self
0003    TGETS    1   1   1  ; "page_info_text"
0004    TGETS    1   1   2  ; "input_dialog"
0005    MOV      2   1
0006    TGETS    1   1   3  ; "getInputText"
0007    CALL     1   0   2
0008    CALLM    0   2   0
0009    ISF          0
0010    JMP      1 => 0023
0011    KSHORT   1   1
0012    ISGT     1   0
0013    JMP      1 => 0023
0014    UGET     1   0      ; self
0015    TGETS    1   1   4  ; "page_num"
0016    ISGT     0   1
0017    JMP      1 => 0023
0018    UGET     1   0      ; self
0019    MOV      2   1
0020    TGETS    1   1   5  ; "onGotoPage"
0021    MOV      3   0
0022    CALL     1   1   3
0023 => UGET     1   0      ; self
0024    TGETS    1   1   1  ; "page_info_text"
0025    MOV      2   1
0026    TGETS    1   1   6  ; "closeInputDialog"
0027    CALL     1   1   2
0028    RET0     0   1

-- BYTECODE -- menu.lua:726-728
0001    GGET     0   0      ; "string"
0002    TGETS    0   0   1  ; "format"
0003    KSTR     1   2      ; "(1 - %s) or (a - z)"
0004    UGET     2   0      ; self
0005    TGETS    2   2   3  ; "page_num"
0006    CALLT    0   3

-- BYTECODE -- menu.lua:732-744
0001    GGET     0   0      ; "ipairs"
0002    UGET     1   0      ; self
0003    TGETS    1   1   1  ; "item_table"
0004    CALL     0   4   2
0005    JMP      3 => 0042
0006 => UGET     5   1      ; util
0007    TGETS    5   5   2  ; "basename"
0008    TGETS    6   4   3  ; "path"
0009    CALL     5   2   2
0010    MOV      6   5
0011    TGETS    5   5   4  ; "lower"
0012    CALL     5   2   2
0013    UGET     6   0      ; self
0014    TGETS    6   6   5  ; "page_info_text"
0015    TGETS    6   6   6  ; "input_dialog"
0016    MOV      7   6
0017    TGETS    6   6   7  ; "getInputText"
0018    CALL     6   2   2
0019    MOV      7   6
0020    TGETS    6   6   4  ; "lower"
0021    CALL     6   2   2
0022    MOV      8   5
0023    TGETS    7   5   8  ; "find"
0024    MOV      9   6
0025    CALL     7   3   3
0026    ISNEN    7   0      ; 1
0027    JMP      9 => 0042
0028    TGETS    9   4   9  ; "is_go_up"
0029    IST          9
0030    JMP      9 => 0042
0031    UGET     9   0      ; self
0032    MOV     10   9
0033    TGETS    9   9  10  ; "onGotoPage"
0034    GGET    11  11      ; "math"
0035    TGETS   11  11  12  ; "ceil"
0036    UGET    12   0      ; self
0037    TGETS   12  12  13  ; "perpage"
0038    DIVVV   12   3  12
0039    CALL    11   0   2
0040    CALLM    9   1   1
0041    JMP      0 => 0044
0042 => ITERC    3   3   3
0043    ITERL    3 => 0006
0044 => UGET     0   0      ; self
0045    TGETS    0   0   5  ; "page_info_text"
0046    MOV      1   0
0047    TGETS    0   0  14  ; "closeInputDialog"
0048    CALL     0   1   2
0049    RET0     0   1

-- BYTECODE -- menu.lua:749-751
0001    GGET     0   0      ; "string"
0002    TGETS    0   0   1  ; "format"
0003    KSTR     1   2      ; "(1 - %s)"
0004    UGET     2   0      ; self
0005    TGETS    2   2   3  ; "page_num"
0006    CALLT    0   3

-- BYTECODE -- menu.lua:780-782
0001    UGET     0   0      ; self
0002    TGETS    0   0   0  ; "onReturn"
0003    ISF          0
0004    JMP      1 => 0009
0005    UGET     0   0      ; self
0006    MOV      1   0
0007    TGETS    0   0   0  ; "onReturn"
0008    CALL     0   1   2
0009 => RET0     0   1

-- BYTECODE -- menu.lua:600-928
0001    TGETS    1   0   0  ; "show_parent"
0002    IST          1
0003    JMP      2 => 0005
0004    MOV      1   0
0005 => TSETS    1   0   0  ; "show_parent"
0006    TNEW     1   0
0007    TSETS    1   0   1  ; "item_table_stack"
0008    TGETS    1   0   2  ; "dimen"
0009    TGETS    2   0   4  ; "width"
0010    TSETS    2   1   3  ; "w"
0011    TGETS    1   0   2  ; "dimen"
0012    TGETS    2   0   6  ; "height"
0013    IST          2
0014    JMP      3 => 0019
0015    UGET     2   0      ; Screen
0016    MOV      3   2
0017    TGETS    2   2   7  ; "getHeight"
0018    CALL     2   2   2
0019 => TSETS    2   1   5  ; "h"
0020    TGETS    1   0   2  ; "dimen"
0021    TGETS    1   1   5  ; "h"
0022    UGET     2   0      ; Screen
0023    MOV      3   2
0024    TGETS    2   2   7  ; "getHeight"
0025    CALL     2   2   2
0026    ISLT     2   1
0027    JMP      1 => 0032
0028    TGETS    1   0   2  ; "dimen"
0029    TGETS    1   1   5  ; "h"
0030    ISNEP    1   0
0031    JMP      1 => 0038
0032 => TGETS    1   0   2  ; "dimen"
0033    UGET     2   0      ; Screen
0034    MOV      3   2
0035    TGETS    2   2   7  ; "getHeight"
0036    CALL     2   2   2
0037    TSETS    2   1   5  ; "h"
0038 => KSHORT   1   1
0039    TSETS    1   0   8  ; "page"
0040    UGET     1   1      ; TextWidget
0041    MOV      2   1
0042    TGETS    1   1  10  ; "new"
0043    TDUP     3  11
0044    TGETS    4   0  12  ; "title"
0045    TSETS    4   3  13  ; "text"
0046    TGETS    4   0  14  ; "tface"
0047    TSETS    4   3  15  ; "face"
0048    CALL     1   2   3
0049    TSETS    1   0   9  ; "menu_title"
0050    UGET     1   2      ; CenterContainer
0051    MOV      2   1
0052    TGETS    1   1  10  ; "new"
0053    TDUP     3  18
0054    UGET     4   3      ; Geom
0055    MOV      5   4
0056    TGETS    4   4  10  ; "new"
0057    TDUP     6  16
0058    TGETS    7   0   2  ; "dimen"
0059    TGETS    7   7   3  ; "w"
0060    TSETS    7   6   3  ; "w"
0061    TGETS    7   0   9  ; "menu_title"
0062    MOV      8   7
0063    TGETS    7   7  17  ; "getSize"
0064    CALL     7   2   2
0065    TGETS    7   7   5  ; "h"
0066    TSETS    7   6   5  ; "h"
0067    CALL     4   2   3
0068    TSETS    4   3   2  ; "dimen"
0069    TGETS    4   0   9  ; "menu_title"
0070    TSETB    4   3   1
0071    CALL     1   2   3
0072    KPRI     2   0
0073    TGETS    3   0  19  ; "show_path"
0074    ISF          3
0075    JMP      4 => 0133
0076    UGET     3   1      ; TextWidget
0077    MOV      4   3
0078    TGETS    3   3  10  ; "new"
0079    TDUP     5  23
0080    UGET     6   4      ; Font
0081    MOV      7   6
0082    TGETS    6   6  21  ; "getFace"
0083    KSTR     8  22      ; "xx_smallinfofont"
0084    CALL     6   2   3
0085    TSETS    6   5  15  ; "face"
0086    UGET     6   5      ; BD
0087    TGETS    6   6  24  ; "directory"
0088    TGETS    7   0  25  ; "path"
0089    CALL     6   2   2
0090    TSETS    6   5  13  ; "text"
0091    TGETS    6   0   2  ; "dimen"
0092    TGETS    6   6   3  ; "w"
0093    UGET     7   6      ; Size
0094    TGETS    7   7  26  ; "padding"
0095    TGETS    7   7  27  ; "small"
0096    MULNV    7   7   0  ; 2
0097    SUBVV    6   6   7
0098    TSETS    6   5  28  ; "max_width"
0099    CALL     3   2   3
0100    TSETS    3   0  20  ; "path_text"
0101    UGET     3   2      ; CenterContainer
0102    MOV      4   3
0103    TGETS    3   3  10  ; "new"
0104    TDUP     5  30
0105    UGET     6   3      ; Geom
0106    MOV      7   6
0107    TGETS    6   6  10  ; "new"
0108    TDUP     8  29
0109    TGETS    9   0   2  ; "dimen"
0110    TGETS    9   9   3  ; "w"
0111    TSETS    9   8   3  ; "w"
0112    TGETS    9   0  20  ; "path_text"
0113    MOV     10   9
0114    TGETS    9   9  17  ; "getSize"
0115    CALL     9   2   2
0116    TGETS    9   9   5  ; "h"
0117    TSETS    9   8   5  ; "h"
0118    CALL     6   2   3
0119    TSETS    6   5   2  ; "dimen"
0120    TGETS    6   0  20  ; "path_text"
0121    TSETB    6   5   1
0122    CALL     3   2   3
0123    MOV      2   3
0124    UGET     3   7      ; VerticalGroup
0125    MOV      4   3
0126    TGETS    3   3  10  ; "new"
0127    TDUP     5  32
0128    TSETB    1   5   1
0129    TSETB    2   5   2
0130    CALL     3   2   3
0131    TSETS    3   0  31  ; "menu_title_group"
0132    JMP      3 => 0140
0133 => UGET     3   7      ; VerticalGroup
0134    MOV      4   3
0135    TGETS    3   3  10  ; "new"
0136    TDUP     5  33
0137    TSETB    1   5   1
0138    CALL     3   2   3
0139    TSETS    3   0  31  ; "menu_title_group"
0140 => UGET     3   8      ; OverlapGroup
0141    MOV      4   3
0142    TGETS    3   3  10  ; "new"
0143    TDUP     5  36
0144    TDUP     6  35
0145    TGETS    7   0   2  ; "dimen"
0146    TGETS    7   7   3  ; "w"
0147    TSETS    7   6   3  ; "w"
0148    TGETS    7   0  31  ; "menu_title_group"
0149    MOV      8   7
0150    TGETS    7   7  17  ; "getSize"
0151    CALL     7   2   2
0152    TGETS    7   7   5  ; "h"
0153    TSETS    7   6   5  ; "h"
0154    TSETS    6   5   2  ; "dimen"
0155    TGETS    6   0  31  ; "menu_title_group"
0156    TSETB    6   5   1
0157    CALL     3   2   3
0158    TSETS    3   0  34  ; "title_bar"
0159    UGET     3   7      ; VerticalGroup
0160    MOV      4   3
0161    TGETS    3   3  10  ; "new"
0162    TNEW     5   0
0163    CALL     3   2   3
0164    TSETS    3   0  37  ; "item_group"
0165    KSTR     3  38      ; "resources/icons/appbar.chevron.left.png"
0166    KSTR     4  39      ; "resources/icons/appbar.chevron.right.png"
0167    KSTR     5  40      ; "resources/icons/appbar.chevron.first.png"
0168    KSTR     6  41      ; "resources/icons/appbar.chevron.last.png"
0169    UGET     7   5      ; BD
0170    TGETS    7   7  42  ; "mirroredUILayout"
0171    CALL     7   2   1
0172    ISF          7
0173    JMP      8 => 0180
0174    MOV      7   4
0175    MOV      4   3
0176    MOV      3   7
0177    MOV      7   6
0178    MOV      6   5
0179    MOV      5   7
0180 => UGET     7   9      ; Button
0181    MOV      8   7
0182    TGETS    7   7  10  ; "new"
0183    TDUP     9  44
0184    TSETS    3   9  45  ; "icon"
0185    FNEW    10  46      ; menu.lua:670
0186    TSETS   10   9  47  ; "callback"
0187    TGETS   10   0   0  ; "show_parent"
0188    TSETS   10   9   0  ; "show_parent"
0189    CALL     7   2   3
0190    TSETS    7   0  43  ; "page_info_left_chev"
0191    UGET     7   9      ; Button
0192    MOV      8   7
0193    TGETS    7   7  10  ; "new"
0194    TDUP     9  49
0195    TSETS    4   9  45  ; "icon"
0196    FNEW    10  50      ; menu.lua:676
0197    TSETS   10   9  47  ; "callback"
0198    TGETS   10   0   0  ; "show_parent"
0199    TSETS   10   9   0  ; "show_parent"
0200    CALL     7   2   3
0201    TSETS    7   0  48  ; "page_info_right_chev"
0202    UGET     7   9      ; Button
0203    MOV      8   7
0204    TGETS    7   7  10  ; "new"
0205    TDUP     9  52
0206    TSETS    5   9  45  ; "icon"
0207    FNEW    10  53      ; menu.lua:682
0208    TSETS   10   9  47  ; "callback"
0209    TGETS   10   0   0  ; "show_parent"
0210    TSETS   10   9   0  ; "show_parent"
0211    CALL     7   2   3
0212    TSETS    7   0  51  ; "page_info_first_chev"
0213    UGET     7   9      ; Button
0214    MOV      8   7
0215    TGETS    7   7  10  ; "new"
0216    TDUP     9  55
0217    TSETS    6   9  45  ; "icon"
0218    FNEW    10  56      ; menu.lua:688
0219    TSETS   10   9  47  ; "callback"
0220    TGETS   10   0   0  ; "show_parent"
0221    TSETS   10   9   0  ; "show_parent"
0222    CALL     7   2   3
0223    TSETS    7   0  54  ; "page_info_last_chev"
0224    UGET     7  10      ; HorizontalSpan
0225    MOV      8   7
0226    TGETS    7   7  10  ; "new"
0227    TDUP     9  59
0228    UGET    10   0      ; Screen
0229    MOV     11  10
0230    TGETS   10  10  58  ; "scaleBySize"
0231    KSHORT  12  32
0232    CALL    10   2   3
0233    TSETS   10   9   4  ; "width"
0234    CALL     7   2   3
0235    TSETS    7   0  57  ; "page_info_spacer"
0236    TGETS    7   0  43  ; "page_info_left_chev"
0237    MOV      8   7
0238    TGETS    7   7  60  ; "hide"
0239    CALL     7   1   2
0240    TGETS    7   0  48  ; "page_info_right_chev"
0241    MOV      8   7
0242    TGETS    7   7  60  ; "hide"
0243    CALL     7   1   2
0244    TGETS    7   0  51  ; "page_info_first_chev"
0245    MOV      8   7
0246    TGETS    7   7  60  ; "hide"
0247    CALL     7   1   2
0248    TGETS    7   0  54  ; "page_info_last_chev"
0249    MOV      8   7
0250    TGETS    7   7  60  ; "hide"
0251    CALL     7   1   2
0252    KNIL     7   9
0253    TNEW    10   3
0254    TNEW    11   3
0255    TDUP    12  62
0256    UGET    13  11      ; _
0257    KSTR    14  61      ; "Cancel"
0258    CALL    13   2   2
0259    TSETS   13  12  13  ; "text"
0260    FNEW    13  63      ; menu.lua:705
0261    TSETS   13  12  47  ; "callback"
0262    TSETB   12  11   1
0263    TDUP    12  65
0264    UGET    13  11      ; _
0265    KSTR    14  64      ; "Go to page"
0266    CALL    13   2   2
0267    TSETS   13  12  13  ; "text"
0268    FNEW    13  66      ; menu.lua:712
0269    TSETS   13  12  47  ; "callback"
0270    TSETB   12  11   2
0271    TSETB   11  10   1
0272    TGETS   11   0  67  ; "goto_letter"
0273    ISF         11
0274    JMP     12 => 0293
0275    UGET    11  11      ; _
0276    KSTR    12  68      ; "Enter page number or letter"
0277    CALL    11   2   2
0278    MOV      7  11
0279    KSTR     8  69      ; "string"
0280    FNEW     9  70      ; menu.lua:726
0281    GGET    11  71      ; "table"
0282    TGETS   11  11  72  ; "insert"
0283    TGETB   12  10   1
0284    TDUP    13  74
0285    UGET    14  11      ; _
0286    KSTR    15  73      ; "Go to letter"
0287    CALL    14   2   2
0288    TSETS   14  13  13  ; "text"
0289    FNEW    14  75      ; menu.lua:732
0290    TSETS   14  13  47  ; "callback"
0291    CALL    11   1   3
0292    JMP     11 => 0299
0293 => UGET    11  11      ; _
0294    KSTR    12  76      ; "Enter page number"
0295    CALL    11   2   2
0296    MOV      7  11
0297    KSTR     8  77      ; "number"
0298    FNEW     9  78      ; menu.lua:749
0299 => UGET    11   9      ; Button
0300    MOV     12  11
0301    TGETS   11  11  10  ; "new"
0302    TDUP    13  80
0303    TDUP    14  81
0304    TSETS    7  14  12  ; "title"
0305    TSETS    8  14  82  ; "type"
0306    TSETS    9  14  83  ; "hint_func"
0307    TSETS   10  14  84  ; "buttons"
0308    TSETS   14  13  85  ; "hold_input"
0309    CALL    11   2   3
0310    TSETS   11   0  79  ; "page_info_text"
0311    UGET    11  13      ; HorizontalGroup
0312    MOV     12  11
0313    TGETS   11  11  10  ; "new"
0314    TNEW    13   8
0315    TGETS   14   0  51  ; "page_info_first_chev"
0316    TSETB   14  13   1
0317    TGETS   14   0  57  ; "page_info_spacer"
0318    TSETB   14  13   2
0319    TGETS   14   0  43  ; "page_info_left_chev"
0320    TSETB   14  13   3
0321    TGETS   14   0  79  ; "page_info_text"
0322    TSETB   14  13   4
0323    TGETS   14   0  48  ; "page_info_right_chev"
0324    TSETB   14  13   5
0325    TGETS   14   0  57  ; "page_info_spacer"
0326    TSETB   14  13   6
0327    TGETS   14   0  54  ; "page_info_last_chev"
0328    TSETB   14  13   7
0329    CALL    11   2   3
0330    TSETS   11   0  86  ; "page_info"
0331    UGET    11   9      ; Button
0332    MOV     12  11
0333    TGETS   11  11  10  ; "new"
0334    TDUP    13  88
0335    FNEW    14  89      ; menu.lua:780
0336    TSETS   14  13  47  ; "callback"
0337    TGETS   14   0   0  ; "show_parent"
0338    TSETS   14  13   0  ; "show_parent"
0339    TGETS   14   0  90  ; "return_arrow_propagation"
0340    TSETS   14  13  91  ; "readonly"
0341    CALL    11   2   3
0342    TSETS   11   0  87  ; "page_return_arrow"
0343    TGETS   11   0  87  ; "page_return_arrow"
0344    MOV     12  11
0345    TGETS   11  11  60  ; "hide"
0346    CALL    11   1   2
0347    UGET    11  13      ; HorizontalGroup
0348    MOV     12  11
0349    TGETS   11  11  10  ; "new"
0350    TNEW    13   3
0351    UGET    14  10      ; HorizontalSpan
0352    MOV     15  14
0353    TGETS   14  14  10  ; "new"
0354    TDUP    16  95
0355    UGET    17   6      ; Size
0356    TGETS   17  17  93  ; "span"
0357    TGETS   17  17  94  ; "horizontal_small"
0358    TSETS   17  16   4  ; "width"
0359    CALL    14   2   3
0360    TSETB   14  13   1
0361    TGETS   14   0  87  ; "page_return_arrow"
0362    TSETB   14  13   2
0363    CALL    11   2   3
0364    TSETS   11   0  92  ; "return_button"
0365    UGET    11   7      ; VerticalGroup
0366    MOV     12  11
0367    TGETS   11  11  10  ; "new"
0368    TNEW    13   3
0369    UGET    14  14      ; VerticalSpan
0370    MOV     15  14
0371    TGETS   14  14  10  ; "new"
0372    TDUP    16  97
0373    TGETS   17   0  96  ; "header_padding"
0374    TSETS   17  16   4  ; "width"
0375    CALL    14   2   3
0376    TSETB   14  13   1
0377    TGETS   14   0  34  ; "title_bar"
0378    TSETB   14  13   2
0379    CALL    11   2   3
0380    TGETS   12   0  37  ; "item_group"
0381    UGET    13  15      ; BottomContainer
0382    MOV     14  13
0383    TGETS   13  13  10  ; "new"
0384    TDUP    15  99
0385    TGETS   16   0   2  ; "dimen"
0386    MOV     17  16
0387    TGETS   16  16  98  ; "copy"
0388    CALL    16   2   2
0389    TSETS   16  15   2  ; "dimen"
0390    TGETS   16   0  86  ; "page_info"
0391    TSETB   16  15   1
0392    CALL    13   2   3
0393    UGET    14  15      ; BottomContainer
0394    MOV     15  14
0395    TGETS   14  14  10  ; "new"
0396    TDUP    16 100
0397    TGETS   17   0   2  ; "dimen"
0398    MOV     18  17
0399    TGETS   17  17  98  ; "copy"
0400    CALL    17   2   2
0401    TSETS   17  16   2  ; "dimen"
0402    UGET    17  16      ; WidgetContainer
0403    MOV     18  17
0404    TGETS   17  17  10  ; "new"
0405    TDUP    19 103
0406    UGET    20   3      ; Geom
0407    MOV     21  20
0408    TGETS   20  20  10  ; "new"
0409    TDUP    22 102
0410    UGET    23   0      ; Screen
0411    MOV     24  23
0412    TGETS   23  23 101  ; "getWidth"
0413    CALL    23   2   2
0414    TSETS   23  22   3  ; "w"
0415    TGETS   23   0  87  ; "page_return_arrow"
0416    MOV     24  23
0417    TGETS   23  23  17  ; "getSize"
0418    CALL    23   2   2
0419    TGETS   23  23   5  ; "h"
0420    TSETS   23  22   5  ; "h"
0421    CALL    20   2   3
0422    TSETS   20  19   2  ; "dimen"
0423    TGETS   20   0  92  ; "return_button"
0424    TSETB   20  19   1
0425    CALL    17   0   3
0426    TSETM   17   1      ; 1
0427    CALL    14   2   3
0428    MOV     16   0
0429    TGETS   15   0 104  ; "_recalculateDimen"
0430    CALL    15   1   2
0431    UGET    15  13      ; HorizontalGroup
0432    MOV     16  15
0433    TGETS   15  15  10  ; "new"
0434    TNEW    17   3
0435    UGET    18  14      ; VerticalSpan
0436    MOV     19  18
0437    TGETS   18  18  10  ; "new"
0438    TDUP    20 107
0439    TGETS   21   0 106  ; "span_width"
0440    TSETS   21  20   4  ; "width"
0441    CALL    18   0   3
0442    TSETM   18   1      ; 1
0443    CALL    15   2   3
0444    TSETS   15   0 105  ; "vertical_span"
0445    TGETS   15   0 108  ; "no_title"
0446    ISF         15
0447    JMP     16 => 0458
0448    UGET    15   7      ; VerticalGroup
0449    MOV     16  15
0450    TGETS   15  15  10  ; "new"
0451    TDUP    17 110
0452    TGETS   18   0 105  ; "vertical_span"
0453    TSETB   18  17   1
0454    TSETB   12  17   2
0455    CALL    15   2   3
0456    TSETS   15   0 109  ; "content_group"
0457    JMP     15 => 0468
0458 => UGET    15   7      ; VerticalGroup
0459    MOV     16  15
0460    TGETS   15  15  10  ; "new"
0461    TDUP    17 111
0462    TSETB   11  17   1
0463    TGETS   18   0 105  ; "vertical_span"
0464    TSETB   18  17   2
0465    TSETB   12  17   3
0466    CALL    15   2   3
0467    TSETS   15   0 109  ; "content_group"
0468 => UGET    15   8      ; OverlapGroup
0469    MOV     16  15
0470    TGETS   15  15  10  ; "new"
0471    TDUP    17 112
0472    TGETS   18   0   2  ; "dimen"
0473    MOV     19  18
0474    TGETS   18  18  98  ; "copy"
0475    CALL    18   2   2
0476    TSETS   18  17   2  ; "dimen"
0477    TGETS   18   0 109  ; "content_group"
0478    TSETB   18  17   1
0479    TSETB   14  17   2
0480    TSETB   13  17   3
0481    CALL    15   2   3
0482    UGET    16  17      ; FrameContainer
0483    MOV     17  16
0484    TGETS   16  16  10  ; "new"
0485    TDUP    18 114
0486    UGET    19  18      ; Blitbuffer
0487    TGETS   19  19 113  ; "COLOR_WHITE"
0488    TSETS   19  18 115  ; "background"
0489    TGETS   19   0 116  ; "is_borderless"
0490    ISF         19
0491    JMP     20 => 0494
0492    KSHORT  19   0
0493    JMP     20 => 0495
0494 => KSHORT  19   2
0495 => TSETS   19  18 117  ; "bordersize"
0496    TGETS   19   0 118  ; "is_popout"
0497    ISF         19
0498    JMP     20 => 0507
0499    GGET    19 119      ; "math"
0500    TGETS   19  19 120  ; "floor"
0501    TGETS   20   0   2  ; "dimen"
0502    TGETS   20  20   3  ; "w"
0503    DIVVN   20  20   2  ; 20
0504    CALL    19   2   2
0505    IST         19
0506    JMP     20 => 0508
0507 => KSHORT  19   0
0508 => TSETS   19  18 121  ; "radius"
0509    TSETB   15  18   1
0510    CALL    16   2   3
0511    TSETB   16   0   1
0512    UGET    16  19      ; Device
0513    MOV     17  16
0514    TGETS   16  16 122  ; "isTouchDevice"
0515    CALL    16   2   2
0516    ISF         16
0517    JMP     17 => 0578
0518    TGETS   16   0 123  ; "has_close_button"
0519    ISF         16
0520    JMP     17 => 0533
0521    GGET    16  71      ; "table"
0522    TGETS   16  16  72  ; "insert"
0523    TGETS   17   0  34  ; "title_bar"
0524    UGET    18  20      ; MenuCloseButton
0525    MOV     19  18
0526    TGETS   18  18  10  ; "new"
0527    TDUP    20 124
0528    TSETS    0  20 125  ; "menu"
0529    TGETS   21   0  96  ; "header_padding"
0530    TSETS   21  20 126  ; "padding_right"
0531    CALL    18   0   3
0532    CALLM   16   1   1
0533 => TGETS   16   0 118  ; "is_popout"
0534    ISF         16
0535    JMP     17 => 0561
0536    TGETS   16   0 127  ; "ges_events"
0537    TNEW    17   3
0538    UGET    18  21      ; GestureRange
0539    MOV     19  18
0540    TGETS   18  18  10  ; "new"
0541    TDUP    20 129
0542    UGET    21   3      ; Geom
0543    MOV     22  21
0544    TGETS   21  21  10  ; "new"
0545    TDUP    23 130
0546    UGET    24   0      ; Screen
0547    MOV     25  24
0548    TGETS   24  24 101  ; "getWidth"
0549    CALL    24   2   2
0550    TSETS   24  23   3  ; "w"
0551    UGET    24   0      ; Screen
0552    MOV     25  24
0553    TGETS   24  24   7  ; "getHeight"
0554    CALL    24   2   2
0555    TSETS   24  23   5  ; "h"
0556    CALL    21   2   3
0557    TSETS   21  20 131  ; "range"
0558    CALL    18   0   3
0559    TSETM   18   1      ; 1
0560    TSETS   17  16 128  ; "TapCloseAllMenus"
0561 => TGETS   16   0 132  ; "is_file_manager"
0562    ISEQP   16   2
0563    JMP     16 => 0575
0564    TGETS   16   0 127  ; "ges_events"
0565    TNEW    17   3
0566    UGET    18  21      ; GestureRange
0567    MOV     19  18
0568    TGETS   18  18  10  ; "new"
0569    TDUP    20 134
0570    TGETS   21   0   2  ; "dimen"
0571    TSETS   21  20 131  ; "range"
0572    CALL    18   0   3
0573    TSETM   18   1      ; 1
0574    TSETS   17  16 133  ; "Swipe"
0575 => TGETS   16   0 127  ; "ges_events"
0576    TGETS   17   0 136  ; "on_close_ges"
0577    TSETS   17  16 135  ; "Close"
0578 => UGET    16  19      ; Device
0579    MOV     17  16
0580    TGETS   16  16 137  ; "hasKeyboard"
0581    CALL    16   2   2
0582    IST         16
0583    JMP     16 => 0586
0584    KPRI    16   1
0585    TSETS   16   0 138  ; "is_enable_shortcut"
0586 => UGET    16  19      ; Device
0587    MOV     17  16
0588    TGETS   16  16 139  ; "hasKeys"
0589    CALL    16   2   2
0590    ISF         16
0591    JMP     17 => 0615
0592    TGETS   16   0 140  ; "key_events"
0593    TDUP    17 142
0594    TDUP    18 141
0595    TSETB   18  17   1
0596    TSETS   17  16 135  ; "Close"
0597    TGETS   16   0 140  ; "key_events"
0598    TDUP    17 146
0599    TNEW    18   3
0600    UGET    19  22      ; Input
0601    TGETS   19  19 144  ; "group"
0602    TGETS   19  19 145  ; "PgFwd"
0603    TSETB   19  18   1
0604    TSETB   18  17   1
0605    TSETS   17  16 143  ; "NextPage"
0606    TGETS   16   0 140  ; "key_events"
0607    TDUP    17 149
0608    TNEW    18   3
0609    UGET    19  22      ; Input
0610    TGETS   19  19 144  ; "group"
0611    TGETS   19  19 148  ; "PgBack"
0612    TSETB   19  18   1
0613    TSETB   18  17   1
0614    TSETS   17  16 147  ; "PrevPage"
0615 => UGET    16  19      ; Device
0616    MOV     17  16
0617    TGETS   16  16 150  ; "hasDPad"
0618    CALL    16   2   2
0619    ISF         16
0620    JMP     17 => 0644
0621    TGETS   16   0 140  ; "key_events"
0622    KPRI    17   0
0623    TSETS   17  16 151  ; "FocusRight"
0624    TGETS   16   0 138  ; "is_enable_shortcut"
0625    ISF         16
0626    JMP     17 => 0634
0627    TGETS   16   0 140  ; "key_events"
0628    TNEW    17   3
0629    TNEW    18   3
0630    TGETS   19   0 153  ; "item_shortcuts"
0631    TSETB   19  18   1
0632    TSETB   18  17   1
0633    TSETS   17  16 152  ; "SelectByShortCut"
0634 => TGETS   16   0 140  ; "key_events"
0635    TDUP    17 156
0636    TDUP    18 155
0637    TSETB   18  17   1
0638    TSETS   17  16 154  ; "Select"
0639    TGETS   16   0 140  ; "key_events"
0640    TDUP    17 159
0641    TDUP    18 158
0642    TSETB   18  17   1
0643    TSETS   17  16 157  ; "Right"
0644 => TGETS   16   0 160  ; "item_table"
0645    LEN     16  16
0646    KSHORT  17   0
0647    ISGE    17  16
0648    JMP     16 => 0660
0649    GGET    16 119      ; "math"
0650    TGETS   16  16 161  ; "ceil"
0651    TGETS   17   0 160  ; "item_table"
0652    TGETS   17  17 162  ; "current"
0653    IST         17
0654    JMP     18 => 0656
0655    KSHORT  17   1
0656 => TGETS   18   0 163  ; "perpage"
0657    DIVVV   17  17  18
0658    CALL    16   2   2
0659    TSETS   16   0   8  ; "page"
0660 => TGETS   16   0 164  ; "path_items"
0661    ISF         16
0662    JMP     17 => 0667
0663    MOV     17   0
0664    TGETS   16   0 165  ; "refreshPath"
0665    CALL    16   1   2
0666    JMP     16 => 0670
0667 => MOV     17   0
0668    TGETS   16   0 166  ; "updateItems"
0669    CALL    16   1   2
0670 => UCLO     0 => 0671
0671 => RET0     0   1

-- BYTECODE -- menu.lua:930-941
0001    UGET     1   0      ; UIManager
0002    MOV      2   1
0003    TGETS    1   1   0  ; "setDirty"
0004    KPRI     3   0
0005    KSTR     4   1      ; "partial"
0006    CALL     1   1   4
0007    RET0     0   1

-- BYTECODE -- menu.lua:943-969
0001    TGETS    2   0   0  ; "item_group"
0002    TGETB    2   2   1
0003    ISF          2
0004    JMP      3 => 0147
0005    UGET     2   0      ; Device
0006    MOV      3   2
0007    TGETS    2   2   1  ; "hasDPad"
0008    CALL     2   2   2
0009    ISF          2
0010    JMP      3 => 0014
0011    TDUP     2   3
0012    TSETS    1   2   4  ; "y"
0013    TSETS    2   0   2  ; "selected"
0014 => TGETS    2   0   5  ; "page_num"
0015    KSHORT   3   1
0016    ISGE     3   2
0017    JMP      2 => 0031
0018    TGETS    2   0   6  ; "page_info_text"
0019    MOV      3   2
0020    TGETS    2   2   7  ; "setText"
0021    UGET     4   1      ; util
0022    TGETS    4   4   8  ; "template"
0023    UGET     5   2      ; _
0024    KSTR     6   9      ; "Page %1 of %2"
0025    CALL     5   2   2
0026    TGETS    6   0  10  ; "page"
0027    TGETS    7   0   5  ; "page_num"
0028    CALL     4   0   4
0029    CALLM    2   1   1
0030    JMP      2 => 0036
0031 => TGETS    2   0   6  ; "page_info_text"
0032    MOV      3   2
0033    TGETS    2   2   7  ; "setText"
0034    KSTR     4  11      ; ""
0035    CALL     2   1   3
0036 => TGETS    2   0  12  ; "page_info_left_chev"
0037    MOV      3   2
0038    TGETS    2   2  13  ; "showHide"
0039    TGETS    4   0   5  ; "page_num"
0040    KSHORT   5   1
0041    ISLT     5   4
0042    JMP      4 => 0045
0043    KPRI     4   1
0044    JMP      5 => 0046
0045 => KPRI     4   2
0046 => CALL     2   1   3
0047    TGETS    2   0  14  ; "page_info_right_chev"
0048    MOV      3   2
0049    TGETS    2   2  13  ; "showHide"
0050    TGETS    4   0   5  ; "page_num"
0051    KSHORT   5   1
0052    ISLT     5   4
0053    JMP      4 => 0056
0054    KPRI     4   1
0055    JMP      5 => 0057
0056 => KPRI     4   2
0057 => CALL     2   1   3
0058    TGETS    2   0  15  ; "page_info_first_chev"
0059    MOV      3   2
0060    TGETS    2   2  13  ; "showHide"
0061    TGETS    4   0   5  ; "page_num"
0062    KSHORT   5   2
0063    ISLT     5   4
0064    JMP      4 => 0067
0065    KPRI     4   1
0066    JMP      5 => 0068
0067 => KPRI     4   2
0068 => CALL     2   1   3
0069    TGETS    2   0  16  ; "page_info_last_chev"
0070    MOV      3   2
0071    TGETS    2   2  13  ; "showHide"
0072    TGETS    4   0   5  ; "page_num"
0073    KSHORT   5   2
0074    ISLT     5   4
0075    JMP      4 => 0078
0076    KPRI     4   1
0077    JMP      5 => 0079
0078 => KPRI     4   2
0079 => CALL     2   1   3
0080    TGETS    2   0  17  ; "page_return_arrow"
0081    MOV      3   2
0082    TGETS    2   2  13  ; "showHide"
0083    TGETS    4   0  18  ; "onReturn"
0084    ISNEP    4   0
0085    JMP      4 => 0088
0086    KPRI     4   1
0087    JMP      5 => 0089
0088 => KPRI     4   2
0089 => CALL     2   1   3
0090    TGETS    2   0  12  ; "page_info_left_chev"
0091    MOV      3   2
0092    TGETS    2   2  19  ; "enableDisable"
0093    TGETS    4   0  10  ; "page"
0094    KSHORT   5   1
0095    ISLT     5   4
0096    JMP      4 => 0099
0097    KPRI     4   1
0098    JMP      5 => 0100
0099 => KPRI     4   2
0100 => CALL     2   1   3
0101    TGETS    2   0  14  ; "page_info_right_chev"
0102    MOV      3   2
0103    TGETS    2   2  19  ; "enableDisable"
0104    TGETS    4   0  10  ; "page"
0105    TGETS    5   0   5  ; "page_num"
0106    ISLT     4   5
0107    JMP      4 => 0110
0108    KPRI     4   1
0109    JMP      5 => 0111
0110 => KPRI     4   2
0111 => CALL     2   1   3
0112    TGETS    2   0  15  ; "page_info_first_chev"
0113    MOV      3   2
0114    TGETS    2   2  19  ; "enableDisable"
0115    TGETS    4   0  10  ; "page"
0116    KSHORT   5   1
0117    ISLT     5   4
0118    JMP      4 => 0121
0119    KPRI     4   1
0120    JMP      5 => 0122
0121 => KPRI     4   2
0122 => CALL     2   1   3
0123    TGETS    2   0  16  ; "page_info_last_chev"
0124    MOV      3   2
0125    TGETS    2   2  19  ; "enableDisable"
0126    TGETS    4   0  10  ; "page"
0127    TGETS    5   0   5  ; "page_num"
0128    ISLT     4   5
0129    JMP      4 => 0132
0130    KPRI     4   1
0131    JMP      5 => 0133
0132 => KPRI     4   2
0133 => CALL     2   1   3
0134    TGETS    2   0  17  ; "page_return_arrow"
0135    MOV      3   2
0136    TGETS    2   2  19  ; "enableDisable"
0137    TGETS    4   0  20  ; "paths"
0138    LEN      4   4
0139    KSHORT   5   0
0140    ISLT     5   4
0141    JMP      4 => 0144
0142    KPRI     4   1
0143    JMP      5 => 0145
0144 => KPRI     4   2
0145 => CALL     2   1   3
0146    JMP      2 => 0154
0147 => TGETS    2   0   6  ; "page_info_text"
0148    MOV      3   2
0149    TGETS    2   2   7  ; "setText"
0150    UGET     4   2      ; _
0151    KSTR     5  21      ; "No choices available"
0152    CALL     4   0   2
0153    CALLM    2   1   1
0154 => RET0     0   1

-- BYTECODE -- menu.lua:1040-1045
0001    UGET     0   0      ; old_dimen
0002    ISF          0
0003    JMP      1 => 0012
0004    UGET     0   0      ; old_dimen
0005    MOV      1   0
0006    TGETS    0   0   0  ; "combine"
0007    UGET     2   1      ; self
0008    TGETS    2   2   1  ; "dimen"
0009    CALL     0   2   3
0010    IST          0
0011    JMP      1 => 0014
0012 => UGET     0   1      ; self
0013    TGETS    0   0   1  ; "dimen"
0014 => KSTR     1   2      ; "ui"
0015    MOV      2   0
0016    RET      1   3

-- BYTECODE -- menu.lua:971-1046
0001    TGETS    2   0   0  ; "dimen"
0002    ISF          2
0003    JMP      3 => 0008
0004    TGETS    2   0   0  ; "dimen"
0005    MOV      3   2
0006    TGETS    2   2   1  ; "copy"
0007    CALL     2   2   2
0008 => TNEW     3   0
0009    TSETS    3   0   2  ; "layout"
0010    TGETS    3   0   3  ; "item_group"
0011    MOV      4   3
0012    TGETS    3   3   4  ; "clear"
0013    CALL     3   1   2
0014    TGETS    3   0   5  ; "page_info"
0015    MOV      4   3
0016    TGETS    3   3   6  ; "resetLayout"
0017    CALL     3   1   2
0018    TGETS    3   0   7  ; "return_button"
0019    MOV      4   3
0020    TGETS    3   3   6  ; "resetLayout"
0021    CALL     3   1   2
0022    TGETS    3   0   8  ; "vertical_span"
0023    MOV      4   3
0024    TGETS    3   3   4  ; "clear"
0025    CALL     3   1   2
0026    TGETS    3   0   9  ; "content_group"
0027    MOV      4   3
0028    TGETS    3   3   6  ; "resetLayout"
0029    CALL     3   1   2
0030    MOV      4   0
0031    TGETS    3   0  10  ; "_recalculateDimen"
0032    CALL     3   1   2
0033    IST          1
0034    JMP      3 => 0036
0035    KSHORT   1   1
0036 => GGET     3  11      ; "math"
0037    TGETS    3   3  12  ; "floor"
0038    TGETS    4   0  13  ; "perpage"
0039    SUBVN    4   4   0  ; 6
0040    DIVVN    4   4   1  ; 3
0041    SUBNV    4   4   2  ; 18
0042    CALL     3   2   2
0043    GGET     4  14      ; "G_reader_settings"
0044    MOV      5   4
0045    TGETS    4   4  15  ; "readSetting"
0046    KSTR     6  16      ; "items_font_size"
0047    CALL     4   2   3
0048    IST          4
0049    JMP      5 => 0058
0050    GGET     4  11      ; "math"
0051    TGETS    4   4  12  ; "floor"
0052    TGETS    5   0  13  ; "perpage"
0053    SUBVN    5   5   0  ; 6
0054    DIVVN    5   5   2  ; 18
0055    MULVN    5   5   3  ; 10
0056    SUBNV    5   5   4  ; 24
0057    CALL     4   2   2
0058 => KSHORT   5   1
0059    GGET     6  11      ; "math"
0060    TGETS    6   6  17  ; "min"
0061    TGETS    7   0  13  ; "perpage"
0062    TGETS    8   0  18  ; "item_table"
0063    LEN      8   8
0064    CALL     6   2   3
0065    KSHORT   7   1
0066    FORI     5 => 0170
0067 => TGETS    9   0  19  ; "page"
0068    SUBVN    9   9   5  ; 1
0069    TGETS   10   0  13  ; "perpage"
0070    MULVV    9   9  10
0071    ADDVV    9   9   8
0072    TGETS   10   0  18  ; "item_table"
0073    LEN     10  10
0074    ISGT     9  10
0075    JMP     10 => 0169
0076    KPRI    10   0
0077    KSTR    11  20      ; "square"
0078    TGETS   12   0  21  ; "is_enable_shortcut"
0079    ISF         12
0080    JMP     13 => 0090
0081    KSHORT  12  11
0082    ISGT    12   8
0083    JMP     12 => 0088
0084    KSHORT  12  20
0085    ISGT     8  12
0086    JMP     12 => 0088
0087    KSTR    11  22      ; "grey_square"
0088 => TGETS   12   0  23  ; "item_shortcuts"
0089    TGETV   10  12   8
0090 => UGET    12   0      ; MenuItem
0091    MOV     13  12
0092    TGETS   12  12  24  ; "new"
0093    TDUP    14  26
0094    TGETS   15   0  25  ; "show_parent"
0095    TSETS   15  14  25  ; "show_parent"
0096    TGETS   15   0  18  ; "item_table"
0097    TGETV   15  15   9
0098    TGETS   15  15  27  ; "state"
0099    TSETS   15  14  27  ; "state"
0100    TGETS   15   0  28  ; "state_size"
0101    IST         15
0102    JMP     16 => 0104
0103    TNEW    15   0
0104 => TSETS   15  14  28  ; "state_size"
0105    UGET    15   1      ; Menu
0106    TGETS   15  15  29  ; "getMenuText"
0107    TGETS   16   0  18  ; "item_table"
0108    TGETV   16  16   9
0109    CALL    15   2   2
0110    TSETS   15  14  30  ; "text"
0111    TGETS   15   0  18  ; "item_table"
0112    TGETV   15  15   9
0113    TGETS   15  15  31  ; "bidi_wrap_func"
0114    TSETS   15  14  31  ; "bidi_wrap_func"
0115    TGETS   15   0  18  ; "item_table"
0116    TGETV   15  15   9
0117    TGETS   15  15  32  ; "mandatory"
0118    TSETS   15  14  32  ; "mandatory"
0119    TGETS   15   0  18  ; "item_table"
0120    TGETS   15  15  33  ; "current"
0121    ISEQV   15   9
0122    JMP     15 => 0130
0123    TGETS   15   0  18  ; "item_table"
0124    TGETV   15  15   9
0125    TGETS   15  15  34  ; "bold"
0126    ISEQP   15   2
0127    JMP     15 => 0130
0128    KPRI    15   1
0129    JMP     16 => 0131
0130 => KPRI    15   2
0131 => TSETS   15  14  34  ; "bold"
0132    TGETS   15   0  18  ; "item_table"
0133    TGETV   15  15   9
0134    TGETS   15  15  35  ; "dim"
0135    TSETS   15  14  35  ; "dim"
0136    TSETS    4  14  36  ; "font_size"
0137    TSETS    3  14  37  ; "infont_size"
0138    TGETS   15   0  38  ; "item_dimen"
0139    MOV     16  15
0140    TGETS   15  15  24  ; "new"
0141    CALL    15   2   2
0142    TSETS   15  14   0  ; "dimen"
0143    TSETS   10  14  39  ; "shortcut"
0144    TSETS   11  14  40  ; "shortcut_style"
0145    TGETS   15   0  18  ; "item_table"
0146    TGETV   15  15   9
0147    TSETS   15  14  41  ; "table"
0148    TSETS    0  14  42  ; "menu"
0149    TGETS   15   0  43  ; "linesize"
0150    TSETS   15  14  43  ; "linesize"
0151    TGETS   15   0  44  ; "single_line"
0152    TSETS   15  14  44  ; "single_line"
0153    TGETS   15   0  45  ; "align_baselines"
0154    TSETS   15  14  45  ; "align_baselines"
0155    TGETS   15   0  46  ; "line_color"
0156    TSETS   15  14  46  ; "line_color"
0157    CALL    12   2   3
0158    GGET    13  41      ; "table"
0159    TGETS   13  13  47  ; "insert"
0160    TGETS   14   0   3  ; "item_group"
0161    MOV     15  12
0162    CALL    13   1   3
0163    GGET    13  41      ; "table"
0164    TGETS   13  13  47  ; "insert"
0165    TGETS   14   0   2  ; "layout"
0166    TNEW    15   3
0167    TSETB   12  15   1
0168    CALL    13   1   3
0169 => FORL     5 => 0067
0170 => MOV      6   0
0171    TGETS    5   0  48  ; "updatePageInfo"
0172    MOV      7   1
0173    CALL     5   1   3
0174    TGETS    5   0  49  ; "show_path"
0175    ISF          5
0176    JMP      6 => 0185
0177    TGETS    5   0  50  ; "path_text"
0178    MOV      6   5
0179    TGETS    5   5  51  ; "setText"
0180    UGET     7   2      ; BD
0181    TGETS    7   7  52  ; "directory"
0182    TGETS    8   0  53  ; "path"
0183    CALL     7   0   2
0184    CALLM    5   1   1
0185 => UGET     5   3      ; UIManager
0186    MOV      6   5
0187    TGETS    5   5  54  ; "setDirty"
0188    TGETS    7   0  25  ; "show_parent"
0189    FNEW     8  55      ; menu.lua:1040
0190    CALL     5   1   4
0191    UCLO     0 => 0192
0192 => RET0     0   1

-- BYTECODE -- menu.lua:1062-1091
0001    TGETS    5   0   0  ; "menu_title"
0002    ISF          5
0003    JMP      6 => 0011
0004    ISF          1
0005    JMP      5 => 0011
0006    TGETS    5   0   0  ; "menu_title"
0007    MOV      6   5
0008    TGETS    5   5   1  ; "setText"
0009    MOV      7   1
0010    CALL     5   1   3
0011 => ISNEP    3   0
0012    JMP      5 => 0016
0013    KSHORT   5   1
0014    TSETS    5   0   2  ; "page"
0015    JMP      5 => 0025
0016 => KSHORT   5   0
0017    ISGT     5   3
0018    JMP      5 => 0025
0019    GGET     5   3      ; "math"
0020    TGETS    5   5   4  ; "ceil"
0021    TGETS    6   0   5  ; "perpage"
0022    DIVVV    6   3   6
0023    CALL     5   2   2
0024    TSETS    5   0   2  ; "page"
0025 => GGET     5   6      ; "type"
0026    MOV      6   4
0027    CALL     5   2   2
0028    ISNES    5   7      ; "table"
0029    JMP      5 => 0051
0030    GGET     5   8      ; "next"
0031    MOV      6   4
0032    CALL     5   3   2
0033    GGET     7   9      ; "ipairs"
0034    MOV      8   2
0035    CALL     7   4   2
0036    JMP     10 => 0049
0037 => TGETV   12  11   5
0038    ISNEV   12   6
0039    JMP     12 => 0049
0040    GGET    12   3      ; "math"
0041    TGETS   12  12  10  ; "floor"
0042    SUBVN   13  10   0  ; 1
0043    TGETS   14   0   5  ; "perpage"
0044    DIVVV   13  13  14
0045    CALL    12   2   2
0046    ADDVN   12  12   0  ; 1
0047    TSETS   12   0   2  ; "page"
0048    JMP      7 => 0051
0049 => ITERC   10   3   3
0050    ITERL   10 => 0037
0051 => GGET     5   3      ; "math"
0052    TGETS    5   5   4  ; "ceil"
0053    LEN      6   2
0054    TGETS    7   0   5  ; "perpage"
0055    DIVVV    6   6   7
0056    CALL     5   2   2
0057    TGETS    6   0   2  ; "page"
0058    ISGE     5   6
0059    JMP      6 => 0061
0060    TSETS    5   0   2  ; "page"
0061 => TSETS    2   0  11  ; "item_table"
0062    MOV      7   0
0063    TGETS    6   0  12  ; "updateItems"
0064    CALL     6   1   2
0065    RET0     0   1

-- BYTECODE -- menu.lua:1093-1097
0001    MOV      3   0
0002    TGETS    2   0   0  ; "init"
0003    CALL     2   1   2
0004    KPRI     2   1
0005    RET1     2   2

-- BYTECODE -- menu.lua:1099-1111
0001    GGET     3   0      ; "ipairs"
0002    TGETS    4   0   1  ; "item_shortcuts"
0003    CALL     3   4   2
0004    JMP      6 => 0033
0005 => TGETS    8   0   2  ; "perpage"
0006    ISGE     8   6
0007    JMP      8 => 0010
0008    JMP      3 => 0035
0009    JMP      8 => 0033
0010 => TGETS    8   2   3  ; "key"
0011    ISNEV    7   8
0012    JMP      8 => 0033
0013    TGETS    8   0   4  ; "item_table"
0014    TGETS    9   0   5  ; "page"
0015    SUBVN    9   9   0  ; 1
0016    TGETS   10   0   2  ; "perpage"
0017    MULVV    9   9  10
0018    ADDVV    9   9   6
0019    TGETV    8   8   9
0020    ISF          8
0021    JMP      9 => 0035
0022    MOV      9   0
0023    TGETS    8   0   6  ; "onMenuSelect"
0024    TGETS   10   0   4  ; "item_table"
0025    TGETS   11   0   5  ; "page"
0026    SUBVN   11  11   0  ; 1
0027    TGETS   12   0   2  ; "perpage"
0028    MULVV   11  11  12
0029    ADDVV   11  11   6
0030    TGETV   10  10  11
0031    CALL     8   1   3
0032    JMP      3 => 0035
0033 => ITERC    6   3   3
0034    ITERL    6 => 0005
0035 => KPRI     3   2
0036    RET1     3   2

-- BYTECODE -- menu.lua:1113-1118
0001    TGETS    1   0   0  ; "page_info_text"
0002    ISF          1
0003    JMP      2 => 0014
0004    TGETS    1   0   0  ; "page_info_text"
0005    TGETS    1   1   1  ; "hold_input"
0006    ISF          1
0007    JMP      2 => 0014
0008    TGETS    1   0   0  ; "page_info_text"
0009    MOV      2   1
0010    TGETS    1   1   2  ; "onInput"
0011    TGETS    3   0   0  ; "page_info_text"
0012    TGETS    3   3   1  ; "hold_input"
0013    CALL     1   1   3
0014 => KPRI     1   2
0015    RET1     1   2

-- BYTECODE -- menu.lua:1120-1130
0001    TGETS    1   0   0  ; "page"
0002    KSHORT   2   1
0003    ISGE     2   1
0004    JMP      1 => 0021
0005    TGETS    1   0   0  ; "page"
0006    SUBVN    1   1   0  ; 1
0007    TSETS    1   0   0  ; "page"
0008    TGETS    1   0   1  ; "perpage"
0009    TGETS    2   0   0  ; "page"
0010    TGETS    3   0   2  ; "page_num"
0011    ISNEV    2   3
0012    JMP      2 => 0017
0013    TGETS    2   0   3  ; "item_table"
0014    LEN      2   2
0015    TGETS    3   0   1  ; "perpage"
0016    MODVV    1   2   3
0017 => MOV      3   0
0018    TGETS    2   0   4  ; "updateItems"
0019    MOV      4   1
0020    CALL     2   1   3
0021 => KPRI     1   1
0022    RET1     1   2

-- BYTECODE -- menu.lua:1132-1137
0001    TGETS    1   0   0  ; "page"
0002    TGETS    2   0   1  ; "page_num"
0003    ISGE     1   2
0004    JMP      1 => 0008
0005    MOV      2   0
0006    TGETS    1   0   2  ; "onNextPage"
0007    CALL     1   1   2
0008 => KPRI     1   1
0009    RET1     1   2

-- BYTECODE -- menu.lua:1142-1155
0001    TGETS    2   1   0  ; "sub_item_table"
0002    ISNEP    2   0
0003    JMP      2 => 0014
0004    TGETS    2   0   1  ; "close_callback"
0005    ISF          2
0006    JMP      3 => 0009
0007    TGETS    2   0   1  ; "close_callback"
0008    CALL     2   1   1
0009 => MOV      3   0
0010    TGETS    2   0   2  ; "onMenuChoice"
0011    MOV      4   1
0012    CALL     2   1   3
0013    JMP      2 => 0027
0014 => TGETS    2   0   3  ; "item_table"
0015    TGETS    3   0   4  ; "title"
0016    TSETS    3   2   4  ; "title"
0017    GGET     2   5      ; "table"
0018    TGETS    2   2   6  ; "insert"
0019    TGETS    3   0   7  ; "item_table_stack"
0020    TGETS    4   0   3  ; "item_table"
0021    CALL     2   1   3
0022    MOV      3   0
0023    TGETS    2   0   8  ; "switchItemTable"
0024    TGETS    4   1   9  ; "text"
0025    TGETS    5   1   0  ; "sub_item_table"
0026    CALL     2   1   4
0027 => KPRI     2   2
0028    RET1     2   2

-- BYTECODE -- menu.lua:1161-1166
0001    TGETS    2   1   0  ; "callback"
0002    ISF          2
0003    JMP      3 => 0006
0004    TGETS    2   1   0  ; "callback"
0005    CALL     2   1   1
0006 => KPRI     2   2
0007    RET1     2   2

-- BYTECODE -- menu.lua:1171-1173
0001    KPRI     2   2
0002    RET1     2   2

-- BYTECODE -- menu.lua:1175-1195
0001    TGETS    1   0   0  ; "onNext"
0002    ISF          1
0003    JMP      2 => 0012
0004    TGETS    1   0   1  ; "page"
0005    TGETS    2   0   2  ; "page_num"
0006    SUBVN    2   2   0  ; 1
0007    ISNEV    1   2
0008    JMP      1 => 0012
0009    MOV      2   0
0010    TGETS    1   0   0  ; "onNext"
0011    CALL     1   1   2
0012 => TGETS    1   0   1  ; "page"
0013    TGETS    2   0   2  ; "page_num"
0014    ISGE     1   2
0015    JMP      1 => 0023
0016    TGETS    1   0   1  ; "page"
0017    ADDVN    1   1   0  ; 1
0018    TSETS    1   0   1  ; "page"
0019    MOV      2   0
0020    TGETS    1   0   3  ; "updateItems"
0021    CALL     1   1   2
0022    JMP      1 => 0047
0023 => TGETS    1   0   1  ; "page"
0024    TGETS    2   0   2  ; "page_num"
0025    ISNEV    1   2
0026    JMP      1 => 0047
0027    TGETS    1   0   4  ; "item_table"
0028    LEN      1   1
0029    TGETS    2   0   5  ; "perpage"
0030    MODVV    1   1   2
0031    ISNEN    1   1      ; 0
0032    JMP      2 => 0034
0033    TGETS    1   0   5  ; "perpage"
0034 => TGETS    2   0   6  ; "selected"
0035    TGETS    2   2   7  ; "y"
0036    ISEQV    1   2
0037    JMP      2 => 0042
0038    MOV      3   0
0039    TGETS    2   0   3  ; "updateItems"
0040    MOV      4   1
0041    CALL     2   1   3
0042 => KSHORT   2   1
0043    TSETS    2   0   1  ; "page"
0044    MOV      3   0
0045    TGETS    2   0   3  ; "updateItems"
0046    CALL     2   1   2
0047 => KPRI     1   2
0048    RET1     1   2

-- BYTECODE -- menu.lua:1197-1205
0001    TGETS    1   0   0  ; "page"
0002    KSHORT   2   1
0003    ISGE     2   1
0004    JMP      1 => 0009
0005    TGETS    1   0   0  ; "page"
0006    SUBVN    1   1   0  ; 1
0007    TSETS    1   0   0  ; "page"
0008    JMP      1 => 0014
0009 => TGETS    1   0   0  ; "page"
0010    ISNEN    1   0      ; 1
0011    JMP      1 => 0014
0012    TGETS    1   0   1  ; "page_num"
0013    TSETS    1   0   0  ; "page"
0014 => MOV      2   0
0015    TGETS    1   0   2  ; "updateItems"
0016    CALL     1   1   2
0017    KPRI     1   2
0018    RET1     1   2

-- BYTECODE -- menu.lua:1207-1211
0001    KSHORT   1   1
0002    TSETS    1   0   0  ; "page"
0003    MOV      2   0
0004    TGETS    1   0   1  ; "updateItems"
0005    CALL     1   1   2
0006    KPRI     1   2
0007    RET1     1   2

-- BYTECODE -- menu.lua:1213-1217
0001    TGETS    1   0   1  ; "page_num"
0002    TSETS    1   0   0  ; "page"
0003    MOV      2   0
0004    TGETS    1   0   2  ; "updateItems"
0005    CALL     1   1   2
0006    KPRI     1   2
0007    RET1     1   2

-- BYTECODE -- menu.lua:1219-1223
0001    TSETS    1   0   0  ; "page"
0002    MOV      3   0
0003    TGETS    2   0   1  ; "updateItems"
0004    CALL     2   1   2
0005    KPRI     2   2
0006    RET1     2   2

-- BYTECODE -- menu.lua:1225-1231
0001    TGETS    1   0   0  ; "item_table"
0002    TGETS    2   0   1  ; "page"
0003    SUBVN    2   2   0  ; 1
0004    TGETS    3   0   2  ; "perpage"
0005    MULVV    2   2   3
0006    TGETS    3   0   3  ; "selected"
0007    TGETS    3   3   4  ; "y"
0008    ADDVV    2   2   3
0009    TGETV    1   1   2
0010    ISF          1
0011    JMP      2 => 0016
0012    MOV      3   0
0013    TGETS    2   0   5  ; "onMenuSelect"
0014    MOV      4   1
0015    CALL     2   1   3
0016 => KPRI     2   2
0017    RET1     2   2

-- BYTECODE -- menu.lua:1233-1239
0001    TGETS    1   0   0  ; "item_table"
0002    TGETS    2   0   1  ; "page"
0003    SUBVN    2   2   0  ; 1
0004    TGETS    3   0   2  ; "perpage"
0005    MULVV    2   2   3
0006    TGETS    3   0   3  ; "selected"
0007    TGETS    3   3   4  ; "y"
0008    ADDVV    2   2   3
0009    TGETV    1   1   2
0010    ISF          1
0011    JMP      2 => 0016
0012    MOV      3   0
0013    TGETS    2   0   5  ; "onMenuHold"
0014    MOV      4   1
0015    CALL     2   1   3
0016 => KPRI     2   2
0017    RET1     2   2

-- BYTECODE -- menu.lua:1241-1251
0001    TGETS    1   0   0  ; "item_table_stack"
0002    LEN      1   1
0003    ISNEN    1   0      ; 0
0004    JMP      2 => 0009
0005    MOV      3   0
0006    TGETS    2   0   1  ; "onCloseAllMenus"
0007    CALL     2   1   2
0008    JMP      2 => 0019
0009 => GGET     2   2      ; "table"
0010    TGETS    2   2   3  ; "remove"
0011    TGETS    3   0   0  ; "item_table_stack"
0012    MOV      4   1
0013    CALL     2   2   3
0014    MOV      4   0
0015    TGETS    3   0   4  ; "switchItemTable"
0016    TGETS    5   2   5  ; "title"
0017    MOV      6   2
0018    CALL     3   1   4
0019 => KPRI     2   2
0020    RET1     2   2

-- BYTECODE -- menu.lua:1253-1259
0001    UGET     1   0      ; UIManager
0002    MOV      2   1
0003    TGETS    1   1   0  ; "close"
0004    MOV      3   0
0005    CALL     1   1   3
0006    TGETS    1   0   1  ; "close_callback"
0007    ISF          1
0008    JMP      2 => 0011
0009    TGETS    1   0   1  ; "close_callback"
0010    CALL     1   1   1
0011 => KPRI     1   2
0012    RET1     1   2

-- BYTECODE -- menu.lua:1261-1266
0001    TGETS    3   2   0  ; "pos"
0002    MOV      4   3
0003    TGETS    3   3   1  ; "notIntersectWith"
0004    TGETS    5   0   2  ; "dimen"
0005    CALL     3   2   3
0006    ISF          3
0007    JMP      4 => 0013
0008    MOV      4   0
0009    TGETS    3   0   3  ; "onCloseAllMenus"
0010    CALL     3   1   2
0011    KPRI     3   2
0012    RET1     3   2
0013 => RET0     0   1

-- BYTECODE -- menu.lua:1268-1289
0001    UGET     3   0      ; BD
0002    TGETS    3   3   0  ; "flipDirectionIfMirroredUILayout"
0003    TGETS    4   2   1  ; "direction"
0004    CALL     3   2   2
0005    ISNES    3   2      ; "west"
0006    JMP      4 => 0011
0007    MOV      5   0
0008    TGETS    4   0   3  ; "onNextPage"
0009    CALL     4   1   2
0010    JMP      4 => 0038
0011 => ISNES    3   4      ; "east"
0012    JMP      4 => 0017
0013    MOV      5   0
0014    TGETS    4   0   5  ; "onPrevPage"
0015    CALL     4   1   2
0016    JMP      4 => 0038
0017 => ISNES    3   6      ; "south"
0018    JMP      4 => 0029
0019    TGETS    4   0   7  ; "has_close_button"
0020    ISF          4
0021    JMP      5 => 0038
0022    TGETS    4   0   8  ; "no_title"
0023    IST          4
0024    JMP      4 => 0038
0025    MOV      5   0
0026    TGETS    4   0   9  ; "onClose"
0027    CALL     4   1   2
0028    JMP      4 => 0038
0029 => ISNES    3  10      ; "north"
0030    JMP      4 => 0032
0031    JMP      4 => 0038
0032 => UGET     4   1      ; UIManager
0033    MOV      5   4
0034    TGETS    4   4  11  ; "setDirty"
0035    KPRI     6   0
0036    KSTR     7  12      ; "full"
0037    CALL     4   1   4
0038 => RET0     0   1

-- BYTECODE -- menu.lua:1311-1322
0001    KPRI     1   0
0002    TGETS    2   0   0  ; "text_func"
0003    ISF          2
0004    JMP      3 => 0009
0005    TGETS    2   0   0  ; "text_func"
0006    CALL     2   2   1
0007    MOV      1   2
0008    JMP      2 => 0010
0009 => TGETS    1   0   1  ; "text"
0010 => TGETS    2   0   2  ; "sub_item_table"
0011    ISNEP    2   0
0012    JMP      2 => 0016
0013    TGETS    2   0   3  ; "sub_item_table_func"
0014    ISF          2
0015    JMP      3 => 0022
0016 => GGET     2   4      ; "string"
0017    TGETS    2   2   5  ; "format"
0018    UGET     3   0      ; sub_item_format
0019    MOV      4   1
0020    CALL     2   2   3
0021    MOV      1   2
0022 => RET1     1   2

-- BYTECODE -- menu.lua:1324-1336
0001    TNEW     1   0
0002    GGET     2   0      ; "pairs"
0003    MOV      3   0
0004    CALL     2   4   2
0005    ISNEXT   5 => 0020
0006 => TDUP     7   1
0007    TSETS    5   7   2  ; "text"
0008    TGETS    8   6   3  ; "callback"
0009    ISF          8
0010    JMP      9 => 0014
0011    TGETS    8   6   3  ; "callback"
0012    TSETS    8   7   3  ; "callback"
0013    JMP      8 => 0015
0014 => TSETS    6   7   4  ; "sub_item_table"
0015 => GGET     8   5      ; "table"
0016    TGETS    8   8   6  ; "insert"
0017    MOV      9   1
0018    MOV     10   7
0019    CALL     8   1   3
0020 => ITERN    5   3   3
0021    ITERL    5 => 0006
0022    RET1     1   2

-- BYTECODE -- menu.lua:0-1339
0001    GGET     0   0      ; "require"
0002    KSTR     1   1      ; "ui/bidi"
0003    CALL     0   2   2
0004    GGET     1   0      ; "require"
0005    KSTR     2   2      ; "ffi/blitbuffer"
0006    CALL     1   2   2
0007    GGET     2   0      ; "require"
0008    KSTR     3   3      ; "ui/widget/container/bottomcontainer"
0009    CALL     2   2   2
0010    GGET     3   0      ; "require"
0011    KSTR     4   4      ; "ui/widget/button"
0012    CALL     3   2   2
0013    GGET     4   0      ; "require"
0014    KSTR     5   5      ; "ui/widget/container/centercontainer"
0015    CALL     4   2   2
0016    GGET     5   0      ; "require"
0017    KSTR     6   6      ; "device"
0018    CALL     5   2   2
0019    GGET     6   0      ; "require"
0020    KSTR     7   7      ; "ui/widget/focusmanager"
0021    CALL     6   2   2
0022    GGET     7   0      ; "require"
0023    KSTR     8   8      ; "ui/font"
0024    CALL     7   2   2
0025    GGET     8   0      ; "require"
0026    KSTR     9   9      ; "ui/widget/container/framecontainer"
0027    CALL     8   2   2
0028    GGET     9   0      ; "require"
0029    KSTR    10  10      ; "ui/geometry"
0030    CALL     9   2   2
0031    GGET    10   0      ; "require"
0032    KSTR    11  11      ; "ui/gesturerange"
0033    CALL    10   2   2
0034    GGET    11   0      ; "require"
0035    KSTR    12  12      ; "ui/widget/horizontalgroup"
0036    CALL    11   2   2
0037    GGET    12   0      ; "require"
0038    KSTR    13  13      ; "ui/widget/horizontalspan"
0039    CALL    12   2   2
0040    GGET    13   0      ; "require"
0041    KSTR    14  14      ; "ui/widget/infomessage"
0042    CALL    13   2   2
0043    GGET    14   0      ; "require"
0044    KSTR    15  15      ; "ui/widget/container/inputcontainer"
0045    CALL    14   2   2
0046    GGET    15   0      ; "require"
0047    KSTR    16  16      ; "ui/widget/container/leftcontainer"
0048    CALL    15   2   2
0049    GGET    16   0      ; "require"
0050    KSTR    17  17      ; "optmath"
0051    CALL    16   2   2
0052    GGET    17   0      ; "require"
0053    KSTR    18  18      ; "ui/widget/overlapgroup"
0054    CALL    17   2   2
0055    GGET    18   0      ; "require"
0056    KSTR    19  19      ; "ui/widget/container/rightcontainer"
0057    CALL    18   2   2
0058    GGET    19   0      ; "require"
0059    KSTR    20  20      ; "ui/size"
0060    CALL    19   2   2
0061    GGET    20   0      ; "require"
0062    KSTR    21  21      ; "ui/widget/textboxwidget"
0063    CALL    20   2   2
0064    GGET    21   0      ; "require"
0065    KSTR    22  22      ; "ui/widget/textwidget"
0066    CALL    21   2   2
0067    GGET    22   0      ; "require"
0068    KSTR    23  23      ; "ui/uimanager"
0069    CALL    22   2   2
0070    GGET    23   0      ; "require"
0071    KSTR    24  24      ; "ui/widget/container/underlinecontainer"
0072    CALL    23   2   2
0073    GGET    24   0      ; "require"
0074    KSTR    25  25      ; "ui/widget/verticalgroup"
0075    CALL    24   2   2
0076    GGET    25   0      ; "require"
0077    KSTR    26  26      ; "ui/widget/verticalspan"
0078    CALL    25   2   2
0079    GGET    26   0      ; "require"
0080    KSTR    27  27      ; "ui/widget/container/widgetcontainer"
0081    CALL    26   2   2
0082    GGET    27   0      ; "require"
0083    KSTR    28  28      ; "logger"
0084    CALL    27   2   2
0085    GGET    28   0      ; "require"
0086    KSTR    29  29      ; "ffi/util"
0087    CALL    28   2   2
0088    GGET    29   0      ; "require"
0089    KSTR    30  30      ; "gettext"
0090    CALL    29   2   2
0091    TGETS   30   5  31  ; "input"
0092    TGETS   31   5  32  ; "screen"
0093    MOV     33  26
0094    TGETS   32  26  33  ; "new"
0095    TDUP    34  38
0096    MOV     36   9
0097    TGETS   35   9  33  ; "new"
0098    TDUP    37  35
0099    MOV     39  31
0100    TGETS   38  31  34  ; "scaleBySize"
0101    KSHORT  40  22
0102    CALL    38   2   3
0103    TSETS   38  37  36  ; "w"
0104    MOV     39  31
0105    TGETS   38  31  34  ; "scaleBySize"
0106    KSHORT  40  22
0107    CALL    38   2   3
0108    TSETS   38  37  37  ; "h"
0109    CALL    35   2   3
0110    TSETS   35  34  39  ; "dimen"
0111    TGETS   35  19  40  ; "border"
0112    TGETS   35  35  41  ; "default"
0113    TSETS   35  34  42  ; "bordersize"
0114    CALL    32   2   3
0115    FNEW    33  44      ; menu.lua:46
0116    TSETS   33  32  43  ; "init"
0117    MOV     34  14
0118    TGETS   33  14  33  ; "new"
0119    TDUP    35  45
0120    MOV     37   9
0121    TGETS   36   9  33  ; "new"
0122    TNEW    38   0
0123    CALL    36   2   3
0124    TSETS   36  35  39  ; "dimen"
0125    CALL    33   2   3
0126    FNEW    34  46      ; menu.lua:94
0127    TSETS   34  33  43  ; "init"
0128    FNEW    34  48      ; menu.lua:128
0129    TSETS   34  33  47  ; "onClose"
0130    MOV     35  14
0131    TGETS   34  14  33  ; "new"
0132    TDUP    36  49
0133    TGETS   37  19  50  ; "line"
0134    TGETS   37  37  51  ; "medium"
0135    TSETS   37  36  52  ; "linesize"
0136    CALL    34   2   3
0137    FNEW    35  53      ; menu.lua:155
0138    TSETS   35  34  43  ; "init"
0139    FNEW    35  55      ; menu.lua:429
0140    TSETS   35  34  54  ; "onFocus"
0141    FNEW    35  57      ; menu.lua:446
0142    TSETS   35  34  56  ; "onUnfocus"
0143    FNEW    35  59      ; menu.lua:451
0144    TSETS   35  34  58  ; "onShowItemDetail"
0145    FNEW    35  61      ; menu.lua:456
0146    TSETS   35  34  60  ; "getGesPosition"
0147    FNEW    35  63      ; menu.lua:464
0148    TSETS   35  34  62  ; "onTapSelect"
0149    FNEW    35  65      ; menu.lua:494
0150    TSETS   35  34  64  ; "onHoldSelect"
0151    MOV     36   6
0152    TGETS   35   6  33  ; "new"
0153    TDUP    37  66
0154    MOV     39   7
0155    TGETS   38   7  67  ; "getFace"
0156    KSTR    40  68      ; "cfont"
0157    CALL    38   2   3
0158    TSETS   38  37  69  ; "cface"
0159    MOV     39   7
0160    TGETS   38   7  67  ; "getFace"
0161    KSTR    40  70      ; "tfont"
0162    CALL    38   2   3
0163    TSETS   38  37  71  ; "tface"
0164    MOV     39   7
0165    TGETS   38   7  67  ; "getFace"
0166    KSTR    40  72      ; "ffont"
0167    CALL    38   2   3
0168    TSETS   38  37  73  ; "fface"
0169    MOV     39   7
0170    TGETS   38   7  67  ; "getFace"
0171    KSTR    40  74      ; "scfont"
0172    CALL    38   2   3
0173    TSETS   38  37  75  ; "sface"
0174    TGETS   38  19  76  ; "padding"
0175    TGETS   38  38  77  ; "large"
0176    TSETS   38  37  78  ; "header_padding"
0177    MOV     39   9
0178    TGETS   38   9  33  ; "new"
0179    TNEW    40   0
0180    CALL    38   2   3
0181    TSETS   38  37  39  ; "dimen"
0182    TNEW    38   0
0183    TSETS   38  37  79  ; "item_table"
0184    TDUP    38  80
0185    TSETS   38  37  81  ; "item_shortcuts"
0186    TNEW    38   0
0187    TSETS   38  37  82  ; "paths"
0188    TGETS   38  19  50  ; "line"
0189    TGETS   38  38  51  ; "medium"
0190    TSETS   38  37  52  ; "linesize"
0191    GGET    38  83      ; "G_reader_settings"
0192    MOV     39  38
0193    TGETS   38  38  84  ; "readSetting"
0194    KSTR    40  85      ; "items_per_page"
0195    CALL    38   2   3
0196    IST         38
0197    JMP     39 => 0199
0198    KSHORT  38  14
0199 => TSETS   38  37  86  ; "perpage"
0200    TGETS   38   1  87  ; "COLOR_DARK_GRAY"
0201    TSETS   38  37  88  ; "line_color"
0202    CALL    35   2   3
0203    FNEW    36  90      ; menu.lua:570
0204    TSETS   36  35  89  ; "_recalculateDimen"
0205    FNEW    36  91      ; menu.lua:600
0206    TSETS   36  35  43  ; "init"
0207    FNEW    36  93      ; menu.lua:930
0208    TSETS   36  35  92  ; "onCloseWidget"
0209    FNEW    36  95      ; menu.lua:943
0210    TSETS   36  35  94  ; "updatePageInfo"
0211    FNEW    36  97      ; menu.lua:971
0212    TSETS   36  35  96  ; "updateItems"
0213    FNEW    36  99      ; menu.lua:1062
0214    TSETS   36  35  98  ; "switchItemTable"
0215    FNEW    36 101      ; menu.lua:1093
0216    TSETS   36  35 100  ; "onScreenResize"
0217    FNEW    36 103      ; menu.lua:1099
0218    TSETS   36  35 102  ; "onSelectByShortCut"
0219    FNEW    36 105      ; menu.lua:1113
0220    TSETS   36  35 104  ; "onShowGotoDialog"
0221    FNEW    36 107      ; menu.lua:1120
0222    TSETS   36  35 106  ; "onWrapFirst"
0223    FNEW    36 109      ; menu.lua:1132
0224    TSETS   36  35 108  ; "onWrapLast"
0225    FNEW    36 111      ; menu.lua:1142
0226    TSETS   36  35 110  ; "onMenuSelect"
0227    FNEW    36 113      ; menu.lua:1161
0228    TSETS   36  35 112  ; "onMenuChoice"
0229    FNEW    36 115      ; menu.lua:1171
0230    TSETS   36  35 114  ; "onMenuHold"
0231    FNEW    36 117      ; menu.lua:1175
0232    TSETS   36  35 116  ; "onNextPage"
0233    FNEW    36 119      ; menu.lua:1197
0234    TSETS   36  35 118  ; "onPrevPage"
0235    FNEW    36 121      ; menu.lua:1207
0236    TSETS   36  35 120  ; "onFirstPage"
0237    FNEW    36 123      ; menu.lua:1213
0238    TSETS   36  35 122  ; "onLastPage"
0239    FNEW    36 125      ; menu.lua:1219
0240    TSETS   36  35 124  ; "onGotoPage"
0241    FNEW    36 127      ; menu.lua:1225
0242    TSETS   36  35 126  ; "onSelect"
0243    FNEW    36 129      ; menu.lua:1233
0244    TSETS   36  35 128  ; "onRight"
0245    FNEW    36 130      ; menu.lua:1241
0246    TSETS   36  35  47  ; "onClose"
0247    FNEW    36 132      ; menu.lua:1253
0248    TSETS   36  35 131  ; "onCloseAllMenus"
0249    FNEW    36 134      ; menu.lua:1261
0250    TSETS   36  35 133  ; "onTapCloseAllMenus"
0251    FNEW    36 136      ; menu.lua:1268
0252    TSETS   36  35 135  ; "onSwipe"
0253    KSTR    36 137      ; ""
0254    KSTR    37 138      ; ""
0255    KPRI    38   0
0256    TGETS   39   0 139  ; "mirroredUILayout"
0257    CALL    39   2   1
0258    ISF         39
0259    JMP     40 => 0276
0260    TGETS   39   0 140  ; "rtlUIText"
0261    CALL    39   2   1
0262    ISF         39
0263    JMP     40 => 0270
0264    KSTR    39 141      ; "%s "
0265    TGETS   40   0 142  ; "rtl"
0266    MOV     41  36
0267    CALL    40   2   2
0268    CAT     38  39  40
0269    JMP     39 => 0291
0270 => TGETS   39   0 143  ; "ltr"
0271    MOV     40  36
0272    CALL    39   2   2
0273    KSTR    40 144      ; " %s"
0274    CAT     38  39  40
0275    JMP     39 => 0291
0276 => TGETS   39   0 140  ; "rtlUIText"
0277    CALL    39   2   1
0278    ISF         39
0279    JMP     40 => 0286
0280    TGETS   39   0 142  ; "rtl"
0281    MOV     40  37
0282    CALL    39   2   2
0283    KSTR    40 144      ; " %s"
0284    CAT     38  39  40
0285    JMP     39 => 0291
0286 => KSTR    39 141      ; "%s "
0287    TGETS   40   0 143  ; "ltr"
0288    MOV     41  37
0289    CALL    40   2   2
0290    CAT     38  39  40
0291 => FNEW    39 146      ; menu.lua:1311
0292    TSETS   39  35 145  ; "getMenuText"
0293    FNEW    39 148      ; menu.lua:1324
0294    TSETS   39  35 147  ; "itemTableFromTouchMenu"
0295    UCLO     0 => 0296
0296 => RET1    35   2

