
main <./frontend/ui/widget/menu.lua:0,0> (422 instructions, 1688 bytes at 0x7ffad5c068c0)
0+ params, 68 slots, 0 upvalues, 39 locals, 180 constants, 37 functions
	1	[5]	GETGLOBAL	0 -1	; require
	2	[5]	LOADK    	1 -2	; "ui/bidi"
	3	[5]	CALL     	0 2 2
	4	[6]	GETGLOBAL	1 -1	; require
	5	[6]	LOADK    	2 -3	; "ffi/blitbuffer"
	6	[6]	CALL     	1 2 2
	7	[7]	GETGLOBAL	2 -1	; require
	8	[7]	LOADK    	3 -4	; "ui/widget/container/bottomcontainer"
	9	[7]	CALL     	2 2 2
	10	[8]	GETGLOBAL	3 -1	; require
	11	[8]	LOADK    	4 -5	; "ui/widget/button"
	12	[8]	CALL     	3 2 2
	13	[9]	GETGLOBAL	4 -1	; require
	14	[9]	LOADK    	5 -6	; "ui/widget/container/centercontainer"
	15	[9]	CALL     	4 2 2
	16	[10]	GETGLOBAL	5 -1	; require
	17	[10]	LOADK    	6 -7	; "device"
	18	[10]	CALL     	5 2 2
	19	[11]	GETGLOBAL	6 -1	; require
	20	[11]	LOADK    	7 -8	; "ui/widget/focusmanager"
	21	[11]	CALL     	6 2 2
	22	[12]	GETGLOBAL	7 -1	; require
	23	[12]	LOADK    	8 -9	; "ui/font"
	24	[12]	CALL     	7 2 2
	25	[13]	GETGLOBAL	8 -1	; require
	26	[13]	LOADK    	9 -10	; "ui/widget/container/framecontainer"
	27	[13]	CALL     	8 2 2
	28	[14]	GETGLOBAL	9 -1	; require
	29	[14]	LOADK    	10 -11	; "ui/geometry"
	30	[14]	CALL     	9 2 2
	31	[15]	GETGLOBAL	10 -1	; require
	32	[15]	LOADK    	11 -12	; "ui/gesturerange"
	33	[15]	CALL     	10 2 2
	34	[16]	GETGLOBAL	11 -1	; require
	35	[16]	LOADK    	12 -13	; "ui/widget/horizontalgroup"
	36	[16]	CALL     	11 2 2
	37	[17]	GETGLOBAL	12 -1	; require
	38	[17]	LOADK    	13 -14	; "ui/widget/horizontalspan"
	39	[17]	CALL     	12 2 2
	40	[18]	GETGLOBAL	13 -1	; require
	41	[18]	LOADK    	14 -15	; "ui/widget/infomessage"
	42	[18]	CALL     	13 2 2
	43	[19]	GETGLOBAL	14 -1	; require
	44	[19]	LOADK    	15 -16	; "ui/widget/container/inputcontainer"
	45	[19]	CALL     	14 2 2
	46	[20]	GETGLOBAL	15 -1	; require
	47	[20]	LOADK    	16 -17	; "ui/widget/container/leftcontainer"
	48	[20]	CALL     	15 2 2
	49	[21]	GETGLOBAL	16 -1	; require
	50	[21]	LOADK    	17 -18	; "optmath"
	51	[21]	CALL     	16 2 2
	52	[22]	GETGLOBAL	17 -1	; require
	53	[22]	LOADK    	18 -19	; "ui/widget/overlapgroup"
	54	[22]	CALL     	17 2 2
	55	[23]	GETGLOBAL	18 -1	; require
	56	[23]	LOADK    	19 -20	; "ui/widget/container/rightcontainer"
	57	[23]	CALL     	18 2 2
	58	[24]	GETGLOBAL	19 -1	; require
	59	[24]	LOADK    	20 -21	; "ui/size"
	60	[24]	CALL     	19 2 2
	61	[25]	GETGLOBAL	20 -1	; require
	62	[25]	LOADK    	21 -22	; "ui/widget/textboxwidget"
	63	[25]	CALL     	20 2 2
	64	[26]	GETGLOBAL	21 -1	; require
	65	[26]	LOADK    	22 -23	; "ui/widget/textwidget"
	66	[26]	CALL     	21 2 2
	67	[27]	GETGLOBAL	22 -1	; require
	68	[27]	LOADK    	23 -24	; "ui/uimanager"
	69	[27]	CALL     	22 2 2
	70	[28]	GETGLOBAL	23 -1	; require
	71	[28]	LOADK    	24 -25	; "ui/widget/container/underlinecontainer"
	72	[28]	CALL     	23 2 2
	73	[29]	GETGLOBAL	24 -1	; require
	74	[29]	LOADK    	25 -26	; "ui/widget/verticalgroup"
	75	[29]	CALL     	24 2 2
	76	[30]	GETGLOBAL	25 -1	; require
	77	[30]	LOADK    	26 -27	; "ui/widget/verticalspan"
	78	[30]	CALL     	25 2 2
	79	[31]	GETGLOBAL	26 -1	; require
	80	[31]	LOADK    	27 -28	; "ui/widget/container/widgetcontainer"
	81	[31]	CALL     	26 2 2
	82	[32]	GETGLOBAL	27 -1	; require
	83	[32]	LOADK    	28 -29	; "logger"
	84	[32]	CALL     	27 2 2
	85	[33]	GETGLOBAL	28 -1	; require
	86	[33]	LOADK    	29 -30	; "ffi/util"
	87	[33]	CALL     	28 2 2
	88	[34]	GETGLOBAL	29 -1	; require
	89	[34]	LOADK    	30 -31	; "gettext"
	90	[34]	CALL     	29 2 2
	91	[35]	GETTABLE 	30 5 -32	; "input"
	92	[36]	GETTABLE 	31 5 -33	; "screen"
	93	[38]	SELF     	32 26 -34	; "new"
	94	[38]	NEWTABLE 	34 0 5
	95	[39]	SELF     	35 9 -34	; "new"
	96	[39]	NEWTABLE 	37 0 2
	97	[39]	SELF     	38 31 -37	; "scaleBySize"
	98	[39]	LOADK    	40 -38	; 22
	99	[39]	CALL     	38 3 2
	100	[39]	SETTABLE 	37 -36 38	; "w" -
	101	[39]	SELF     	38 31 -37	; "scaleBySize"
	102	[39]	LOADK    	40 -38	; 22
	103	[39]	CALL     	38 3 2
	104	[39]	SETTABLE 	37 -39 38	; "h" -
	105	[39]	CALL     	35 3 2
	106	[39]	SETTABLE 	34 -35 35	; "dimen" -
	107	[40]	SETTABLE 	34 -40 -41	; "key" nil
	108	[41]	GETTABLE 	35 19 -43	; "border"
	109	[41]	GETTABLE 	35 35 -44	; "default"
	110	[41]	SETTABLE 	34 -42 35	; "bordersize" -
	111	[42]	SETTABLE 	34 -45 -46	; "radius" 0
	112	[43]	SETTABLE 	34 -47 -48	; "style" "square"
	113	[38]	CALL     	32 3 2
	114	[81]	CLOSURE  	33 0	; 0x7ffad5d04380
	115	[81]	MOVE     	0 1
	116	[81]	MOVE     	0 7
	117	[81]	MOVE     	0 8
	118	[81]	MOVE     	0 4
	119	[81]	MOVE     	0 21
	120	[46]	SETTABLE 	32 -49 33	; "init" -
	121	[87]	SELF     	33 14 -34	; "new"
	122	[87]	NEWTABLE 	35 0 4
	123	[88]	SETTABLE 	35 -50 -51	; "overlap_align" "right"
	124	[89]	SETTABLE 	35 -52 -46	; "padding_right" 0
	125	[90]	SETTABLE 	35 -53 -41	; "menu" nil
	126	[91]	SELF     	36 9 -34	; "new"
	127	[91]	NEWTABLE 	38 0 0
	128	[91]	CALL     	36 3 2
	129	[91]	SETTABLE 	35 -35 36	; "dimen" -
	130	[87]	CALL     	33 3 2
	131	[126]	CLOSURE  	34 1	; 0x7ffad5d046e0
	132	[126]	MOVE     	0 21
	133	[126]	MOVE     	0 7
	134	[126]	MOVE     	0 8
	135	[126]	MOVE     	0 9
	136	[126]	MOVE     	0 10
	137	[94]	SETTABLE 	33 -49 34	; "init" -
	138	[131]	CLOSURE  	34 2	; 0x7ffad5d05670
	139	[128]	SETTABLE 	33 -54 34	; "onClose" -
	140	[136]	SELF     	34 14 -34	; "new"
	141	[136]	NEWTABLE 	36 0 15
	142	[137]	SETTABLE 	36 -55 -41	; "text" nil
	143	[138]	SETTABLE 	36 -56 -41	; "bidi_wrap_func" nil
	144	[139]	SETTABLE 	36 -57 -41	; "show_parent" nil
	145	[140]	SETTABLE 	36 -58 -41	; "detail" nil
	146	[141]	SETTABLE 	36 -59 -60	; "font" "cfont"
	147	[142]	SETTABLE 	36 -61 -62	; "font_size" 24
	148	[143]	SETTABLE 	36 -63 -63	; "infont" "infont"
	149	[144]	SETTABLE 	36 -64 -65	; "infont_size" 18
	150	[145]	SETTABLE 	36 -35 -41	; "dimen" nil
	151	[146]	SETTABLE 	36 -66 -41	; "shortcut" nil
	152	[147]	SETTABLE 	36 -67 -48	; "shortcut_style" "square"
	153	[148]	SETTABLE 	36 -68 -41	; "_underline_container" nil
	154	[149]	GETTABLE 	37 19 -70	; "line"
	155	[149]	GETTABLE 	37 37 -71	; "medium"
	156	[149]	SETTABLE 	36 -69 37	; "linesize" -
	157	[150]	SETTABLE 	36 -72 -73	; "single_line" false
	158	[152]	SETTABLE 	36 -74 -73	; "align_baselines" false
	159	[136]	CALL     	34 3 2
	160	[427]	CLOSURE  	35 3	; 0x7ffad5d05ba0
	161	[427]	MOVE     	0 19
	162	[427]	MOVE     	0 9
	163	[427]	MOVE     	0 5
	164	[427]	MOVE     	0 10
	165	[427]	MOVE     	0 20
	166	[427]	MOVE     	0 12
	167	[427]	MOVE     	0 15
	168	[427]	MOVE     	0 11
	169	[427]	MOVE     	0 21
	170	[427]	MOVE     	0 7
	171	[427]	MOVE     	0 1
	172	[427]	MOVE     	0 16
	173	[427]	MOVE     	0 24
	174	[427]	MOVE     	0 25
	175	[427]	MOVE     	0 27
	176	[427]	MOVE     	0 18
	177	[427]	MOVE     	0 23
	178	[427]	MOVE     	0 17
	179	[427]	MOVE     	0 32
	180	[427]	MOVE     	0 8
	181	[155]	SETTABLE 	34 -49 35	; "init" -
	182	[444]	CLOSURE  	35 4	; 0x7ffad5d05f10
	183	[444]	MOVE     	0 5
	184	[444]	MOVE     	0 1
	185	[429]	SETTABLE 	34 -75 35	; "onFocus" -
	186	[449]	CLOSURE  	35 5	; 0x7ffad5d074b0
	187	[446]	SETTABLE 	34 -76 35	; "onUnfocus" -
	188	[454]	CLOSURE  	35 6	; 0x7ffad5d075c0
	189	[454]	MOVE     	0 22
	190	[454]	MOVE     	0 13
	191	[451]	SETTABLE 	34 -77 35	; "onShowItemDetail" -
	192	[462]	CLOSURE  	35 7	; 0x7ffad5d07960
	193	[456]	SETTABLE 	34 -78 35	; "getGesPosition" -
	194	[492]	CLOSURE  	35 8	; 0x7ffad5d07ee0
	195	[492]	MOVE     	0 27
	196	[492]	MOVE     	0 22
	197	[464]	SETTABLE 	34 -79 35	; "onTapSelect" -
	198	[514]	CLOSURE  	35 9	; 0x7ffad5d09570
	199	[514]	MOVE     	0 22
	200	[494]	SETTABLE 	34 -80 35	; "onHoldSelect" -
	201	[519]	SELF     	35 6 -34	; "new"
	202	[519]	NEWTABLE 	37 0 22
	203	[520]	SETTABLE 	37 -57 -41	; "show_parent" nil
	204	[522]	SELF     	38 7 -82	; "getFace"
	205	[522]	LOADK    	40 -60	; "cfont"
	206	[522]	CALL     	38 3 2
	207	[522]	SETTABLE 	37 -81 38	; "cface" -
	208	[524]	SELF     	38 7 -82	; "getFace"
	209	[524]	LOADK    	40 -84	; "tfont"
	210	[524]	CALL     	38 3 2
	211	[524]	SETTABLE 	37 -83 38	; "tface" -
	212	[526]	SELF     	38 7 -82	; "getFace"
	213	[526]	LOADK    	40 -86	; "ffont"
	214	[526]	CALL     	38 3 2
	215	[526]	SETTABLE 	37 -85 38	; "fface" -
	216	[528]	SELF     	38 7 -82	; "getFace"
	217	[528]	LOADK    	40 -88	; "scfont"
	218	[528]	CALL     	38 3 2
	219	[528]	SETTABLE 	37 -87 38	; "sface" -
	220	[530]	SETTABLE 	37 -89 -90	; "title" "No Title"
	221	[532]	SETTABLE 	37 -91 -41	; "width" nil
	222	[534]	SETTABLE 	37 -92 -41	; "height" nil
	223	[535]	GETTABLE 	38 19 -94	; "padding"
	224	[535]	GETTABLE 	38 38 -95	; "large"
	225	[535]	SETTABLE 	37 -93 38	; "header_padding" -
	226	[536]	SELF     	38 9 -34	; "new"
	227	[536]	NEWTABLE 	40 0 0
	228	[536]	CALL     	38 3 2
	229	[536]	SETTABLE 	37 -35 38	; "dimen" -
	230	[537]	NEWTABLE 	38 0 0
	231	[537]	SETTABLE 	37 -96 38	; "item_table" -
	232	[538]	NEWTABLE 	38 23 0
	233	[539]	LOADK    	39 -98	; "Q"
	234	[539]	LOADK    	40 -99	; "W"
	235	[539]	LOADK    	41 -100	; "E"
	236	[539]	LOADK    	42 -101	; "R"
	237	[539]	LOADK    	43 -102	; "T"
	238	[539]	LOADK    	44 -103	; "Y"
	239	[539]	LOADK    	45 -104	; "U"
	240	[539]	LOADK    	46 -105	; "I"
	241	[539]	LOADK    	47 -106	; "O"
	242	[539]	LOADK    	48 -107	; "P"
	243	[540]	LOADK    	49 -108	; "A"
	244	[540]	LOADK    	50 -109	; "S"
	245	[540]	LOADK    	51 -110	; "D"
	246	[540]	LOADK    	52 -111	; "F"
	247	[540]	LOADK    	53 -112	; "G"
	248	[540]	LOADK    	54 -113	; "H"
	249	[540]	LOADK    	55 -114	; "J"
	250	[540]	LOADK    	56 -115	; "K"
	251	[540]	LOADK    	57 -116	; "L"
	252	[540]	LOADK    	58 -117	; "Del"
	253	[541]	LOADK    	59 -118	; "Z"
	254	[541]	LOADK    	60 -119	; "X"
	255	[541]	LOADK    	61 -120	; "C"
	256	[541]	LOADK    	62 -121	; "V"
	257	[541]	LOADK    	63 -122	; "B"
	258	[541]	LOADK    	64 -123	; "N"
	259	[541]	LOADK    	65 -124	; "M"
	260	[541]	LOADK    	66 -125	; "."
	261	[542]	LOADK    	67 -126	; "Sym"
	262	[542]	SETLIST  	38 29 1	; 1
	263	[542]	SETTABLE 	37 -97 38	; "item_shortcuts" -
	264	[543]	SETTABLE 	37 -127 -41	; "item_table_stack" nil
	265	[544]	SETTABLE 	37 -128 -129	; "is_enable_shortcut" true
	266	[546]	SETTABLE 	37 -130 -41	; "item_dimen" nil
	267	[547]	SETTABLE 	37 -131 -132	; "page" 1
	268	[549]	SETTABLE 	37 -133 -41	; "item_group" nil
	269	[550]	SETTABLE 	37 -134 -41	; "page_info" nil
	270	[551]	SETTABLE 	37 -135 -41	; "page_return" nil
	271	[553]	NEWTABLE 	38 0 0
	272	[553]	SETTABLE 	37 -136 38	; "paths" -
	273	[556]	SETTABLE 	37 -137 -73	; "is_borderless" false
	274	[559]	SETTABLE 	37 -138 -129	; "is_popout" true
	275	[561]	SETTABLE 	37 -139 -129	; "has_close_button" true
	276	[564]	SETTABLE 	37 -140 -41	; "close_callback" nil
	277	[565]	GETTABLE 	38 19 -70	; "line"
	278	[565]	GETTABLE 	38 38 -71	; "medium"
	279	[565]	SETTABLE 	37 -69 38	; "linesize" -
	280	[566]	GETGLOBAL	38 -142	; G_reader_settings
	281	[566]	SELF     	38 38 -143	; "readSetting"
	282	[566]	LOADK    	40 -144	; "items_per_page"
	283	[566]	CALL     	38 3 2
	284	[566]	TEST     	38 0 1
	285	[566]	JMP      	1	; to 287
	286	[566]	LOADK    	38 -145	; 14
	287	[566]	SETTABLE 	37 -141 38	; "perpage" -
	288	[567]	GETTABLE 	38 1 -147	; "COLOR_DARK_GRAY"
	289	[567]	SETTABLE 	37 -146 38	; "line_color" -
	290	[519]	CALL     	35 3 2
	291	[598]	CLOSURE  	36 10	; 0x7ffad5d091b0
	292	[598]	MOVE     	0 31
	293	[598]	MOVE     	0 9
	294	[598]	MOVE     	0 19
	295	[570]	SETTABLE 	35 -148 36	; "_recalculateDimen" -
	296	[928]	CLOSURE  	36 11	; 0x7ffad5d087b0
	297	[928]	MOVE     	0 31
	298	[928]	MOVE     	0 21
	299	[928]	MOVE     	0 4
	300	[928]	MOVE     	0 9
	301	[928]	MOVE     	0 7
	302	[928]	MOVE     	0 0
	303	[928]	MOVE     	0 19
	304	[928]	MOVE     	0 24
	305	[928]	MOVE     	0 17
	306	[928]	MOVE     	0 3
	307	[928]	MOVE     	0 12
	308	[928]	MOVE     	0 29
	309	[928]	MOVE     	0 28
	310	[928]	MOVE     	0 11
	311	[928]	MOVE     	0 25
	312	[928]	MOVE     	0 2
	313	[928]	MOVE     	0 26
	314	[928]	MOVE     	0 8
	315	[928]	MOVE     	0 1
	316	[928]	MOVE     	0 5
	317	[928]	MOVE     	0 33
	318	[928]	MOVE     	0 10
	319	[928]	MOVE     	0 30
	320	[600]	SETTABLE 	35 -49 36	; "init" -
	321	[941]	CLOSURE  	36 12	; 0x7ffad5d09e50
	322	[941]	MOVE     	0 22
	323	[930]	SETTABLE 	35 -149 36	; "onCloseWidget" -
	324	[969]	CLOSURE  	36 13	; 0x7ffad5d0d0f0
	325	[969]	MOVE     	0 5
	326	[969]	MOVE     	0 28
	327	[969]	MOVE     	0 29
	328	[943]	SETTABLE 	35 -150 36	; "updatePageInfo" -
	329	[1046]	CLOSURE  	36 14	; 0x7ffad5d0d720
	330	[1046]	MOVE     	0 34
	331	[1046]	MOVE     	0 35
	332	[1046]	MOVE     	0 0
	333	[1046]	MOVE     	0 22
	334	[971]	SETTABLE 	35 -151 36	; "updateItems" -
	335	[1091]	CLOSURE  	36 15	; 0x7ffad5d0e030
	336	[1062]	SETTABLE 	35 -152 36	; "switchItemTable" -
	337	[1097]	CLOSURE  	36 16	; 0x7ffad5d0e160
	338	[1093]	SETTABLE 	35 -153 36	; "onScreenResize" -
	339	[1111]	CLOSURE  	36 17	; 0x7ffad5d094f0
	340	[1099]	SETTABLE 	35 -154 36	; "onSelectByShortCut" -
	341	[1118]	CLOSURE  	36 18	; 0x7ffad5d0f140
	342	[1113]	SETTABLE 	35 -155 36	; "onShowGotoDialog" -
	343	[1130]	CLOSURE  	36 19	; 0x7ffad5d0efc0
	344	[1120]	SETTABLE 	35 -156 36	; "onWrapFirst" -
	345	[1137]	CLOSURE  	36 20	; 0x7ffad5d0f510
	346	[1132]	SETTABLE 	35 -157 36	; "onWrapLast" -
	347	[1155]	CLOSURE  	36 21	; 0x7ffad5d0fd80
	348	[1142]	SETTABLE 	35 -158 36	; "onMenuSelect" -
	349	[1166]	CLOSURE  	36 22	; 0x7ffad5d07bf0
	350	[1161]	SETTABLE 	35 -159 36	; "onMenuChoice" -
	351	[1173]	CLOSURE  	36 23	; 0x7ffad5d0a500
	352	[1171]	SETTABLE 	35 -160 36	; "onMenuHold" -
	353	[1195]	CLOSURE  	36 24	; 0x7ffad5d0af50
	354	[1175]	SETTABLE 	35 -161 36	; "onNextPage" -
	355	[1205]	CLOSURE  	36 25	; 0x7ffad5d10220
	356	[1197]	SETTABLE 	35 -162 36	; "onPrevPage" -
	357	[1211]	CLOSURE  	36 26	; 0x7ffad5d0a390
	358	[1207]	SETTABLE 	35 -163 36	; "onFirstPage" -
	359	[1217]	CLOSURE  	36 27	; 0x7ffad5d0f730
	360	[1213]	SETTABLE 	35 -164 36	; "onLastPage" -
	361	[1223]	CLOSURE  	36 28	; 0x7ffad5d0f7b0
	362	[1219]	SETTABLE 	35 -165 36	; "onGotoPage" -
	363	[1231]	CLOSURE  	36 29	; 0x7ffad5d103e0
	364	[1225]	SETTABLE 	35 -166 36	; "onSelect" -
	365	[1239]	CLOSURE  	36 30	; 0x7ffad5d0e5c0
	366	[1233]	SETTABLE 	35 -167 36	; "onRight" -
	367	[1251]	CLOSURE  	36 31	; 0x7ffad5d10a80
	368	[1241]	SETTABLE 	35 -54 36	; "onClose" -
	369	[1259]	CLOSURE  	36 32	; 0x7ffad5d10c00
	370	[1259]	MOVE     	0 22
	371	[1253]	SETTABLE 	35 -168 36	; "onCloseAllMenus" -
	372	[1266]	CLOSURE  	36 33	; 0x7ffad5d10f80
	373	[1261]	SETTABLE 	35 -169 36	; "onTapCloseAllMenus" -
	374	[1289]	CLOSURE  	36 34	; 0x7ffad5d11090
	375	[1289]	MOVE     	0 0
	376	[1289]	MOVE     	0 22
	377	[1268]	SETTABLE 	35 -170 36	; "onSwipe" -
	378	[1292]	LOADK    	36 -171	; "\226\151\130"
	379	[1293]	LOADK    	37 -172	; "\226\150\184"
	380	[1294]	LOADNIL  	38 38
	381	[1297]	GETTABLE 	39 0 -173	; "mirroredUILayout"
	382	[1297]	CALL     	39 1 2
	383	[1297]	TEST     	39 0 0
	384	[1297]	JMP      	16	; to 401
	385	[1298]	GETTABLE 	39 0 -174	; "rtlUIText"
	386	[1298]	CALL     	39 1 2
	387	[1298]	TEST     	39 0 0
	388	[1298]	JMP      	6	; to 395
	389	[1299]	LOADK    	39 -175	; "%s "
	390	[1299]	GETTABLE 	40 0 -176	; "rtl"
	391	[1299]	MOVE     	41 36
	392	[1299]	CALL     	40 2 2
	393	[1299]	CONCAT   	38 39 40
	394	[1299]	JMP      	21	; to 416
	395	[1301]	GETTABLE 	39 0 -177	; "ltr"
	396	[1301]	MOVE     	40 36
	397	[1301]	CALL     	39 2 2
	398	[1301]	LOADK    	40 -178	; " %s"
	399	[1301]	CONCAT   	38 39 40
	400	[1302]	JMP      	15	; to 416
	401	[1304]	GETTABLE 	39 0 -174	; "rtlUIText"
	402	[1304]	CALL     	39 1 2
	403	[1304]	TEST     	39 0 0
	404	[1304]	JMP      	6	; to 411
	405	[1305]	GETTABLE 	39 0 -176	; "rtl"
	406	[1305]	MOVE     	40 37
	407	[1305]	CALL     	39 2 2
	408	[1305]	LOADK    	40 -178	; " %s"
	409	[1305]	CONCAT   	38 39 40
	410	[1305]	JMP      	5	; to 416
	411	[1307]	LOADK    	39 -175	; "%s "
	412	[1307]	GETTABLE 	40 0 -177	; "ltr"
	413	[1307]	MOVE     	41 37
	414	[1307]	CALL     	40 2 2
	415	[1307]	CONCAT   	38 39 40
	416	[1322]	CLOSURE  	39 35	; 0x7ffad5d11bc0
	417	[1322]	MOVE     	0 38
	418	[1311]	SETTABLE 	35 -179 39	; "getMenuText" -
	419	[1336]	CLOSURE  	39 36	; 0x7ffad5d121c0
	420	[1324]	SETTABLE 	35 -180 39	; "itemTableFromTouchMenu" -
	421	[1338]	RETURN   	35 2
	422	[1338]	RETURN   	0 1

function <./frontend/ui/widget/menu.lua:46,81> (69 instructions, 276 bytes at 0x7ffad5d04380)
1 param, 14 slots, 5 upvalues, 4 locals, 26 constants, 0 functions
	1	[47]	GETTABLE 	1 0 -1	; "key"
	2	[47]	TEST     	1 0 1
	3	[47]	JMP      	1	; to 5
	4	[48]	RETURN   	0 1
	5	[51]	LOADK    	1 -2	; 0
	6	[52]	GETUPVAL 	2 0	; Blitbuffer
	7	[52]	GETTABLE 	2 2 -3	; "COLOR_WHITE"
	8	[53]	GETTABLE 	3 0 -4	; "style"
	9	[53]	EQ       	0 3 -5	; - "rounded_corner"
	10	[53]	JMP      	7	; to 18
	11	[54]	GETGLOBAL	3 -6	; math
	12	[54]	GETTABLE 	3 3 -7	; "floor"
	13	[54]	GETTABLE 	4 0 -8	; "width"
	14	[54]	DIV      	4 4 -9	; - 2
	15	[54]	CALL     	3 2 2
	16	[54]	MOVE     	1 3
	17	[54]	JMP      	5	; to 23
	18	[55]	GETTABLE 	3 0 -4	; "style"
	19	[55]	EQ       	0 3 -10	; - "grey_square"
	20	[55]	JMP      	2	; to 23
	21	[56]	GETUPVAL 	3 0	; Blitbuffer
	22	[56]	GETTABLE 	2 3 -11	; "COLOR_LIGHT_GRAY"
	23	[60]	LOADNIL  	3 3
	24	[61]	GETTABLE 	4 0 -1	; "key"
	25	[61]	SELF     	4 4 -12	; "len"
	26	[61]	CALL     	4 2 2
	27	[61]	LT       	0 -13 4	; 1 -
	28	[61]	JMP      	7	; to 36
	29	[62]	GETUPVAL 	4 1	; Font
	30	[62]	SELF     	4 4 -14	; "getFace"
	31	[62]	LOADK    	6 -15	; "ffont"
	32	[62]	LOADK    	7 -16	; 14
	33	[62]	CALL     	4 4 2
	34	[62]	MOVE     	3 4
	35	[62]	JMP      	6	; to 42
	36	[64]	GETUPVAL 	4 1	; Font
	37	[64]	SELF     	4 4 -14	; "getFace"
	38	[64]	LOADK    	6 -17	; "scfont"
	39	[64]	LOADK    	7 -18	; 22
	40	[64]	CALL     	4 4 2
	41	[64]	MOVE     	3 4
	42	[67]	GETUPVAL 	4 2	; FrameContainer
	43	[67]	SELF     	4 4 -19	; "new"
	44	[67]	NEWTABLE 	6 0 5
	45	[68]	SETTABLE 	6 -20 -2	; "padding" 0
	46	[69]	GETTABLE 	7 0 -21	; "bordersize"
	47	[69]	SETTABLE 	6 -21 7	; "bordersize" -
	48	[70]	SETTABLE 	6 -22 1	; "radius" -
	49	[71]	SETTABLE 	6 -23 2	; "background" -
	50	[72]	GETTABLE 	7 0 -24	; "dimen"
	51	[72]	SETTABLE 	6 -24 7	; "dimen" -
	52	[73]	GETUPVAL 	7 3	; CenterContainer
	53	[73]	SELF     	7 7 -19	; "new"
	54	[73]	NEWTABLE 	9 0 1
	55	[74]	GETTABLE 	10 0 -24	; "dimen"
	56	[74]	SETTABLE 	9 -24 10	; "dimen" -
	57	[75]	GETUPVAL 	10 4	; TextWidget
	58	[75]	SELF     	10 10 -19	; "new"
	59	[75]	NEWTABLE 	12 0 2
	60	[76]	GETTABLE 	13 0 -1	; "key"
	61	[76]	SETTABLE 	12 -25 13	; "text" -
	62	[77]	SETTABLE 	12 -26 3	; "face" -
	63	[75]	CALL     	10 3 0
	64	[79]	SETLIST  	9 0 1	; 1
	65	[73]	CALL     	7 3 0
	66	[80]	SETLIST  	6 0 1	; 1
	67	[67]	CALL     	4 3 2
	68	[80]	SETTABLE 	0 -13 4	; 1 -
	69	[81]	RETURN   	0 1

function <./frontend/ui/widget/menu.lua:94,126> (60 instructions, 240 bytes at 0x7ffad5d046e0)
1 param, 10 slots, 5 upvalues, 4 locals, 27 constants, 0 functions
	1	[95]	GETUPVAL 	1 0	; TextWidget
	2	[95]	SELF     	1 1 -1	; "new"
	3	[95]	NEWTABLE 	3 0 2
	4	[96]	SETTABLE 	3 -2 -3	; "text" "\195\151"
	5	[97]	GETUPVAL 	4 1	; Font
	6	[97]	SELF     	4 4 -5	; "getFace"
	7	[97]	LOADK    	6 -6	; "cfont"
	8	[97]	LOADK    	7 -7	; 30
	9	[97]	CALL     	4 4 2
	10	[97]	SETTABLE 	3 -4 4	; "face" -
	11	[95]	CALL     	1 3 2
	12	[102]	SELF     	2 1 -8	; "getSize"
	13	[102]	CALL     	2 2 2
	14	[103]	GETTABLE 	3 2 -9	; "h"
	15	[103]	GETTABLE 	4 2 -10	; "w"
	16	[103]	SUB      	3 3 4
	17	[103]	DIV      	3 3 -11	; - 2
	18	[105]	GETUPVAL 	4 2	; FrameContainer
	19	[105]	SELF     	4 4 -1	; "new"
	20	[105]	NEWTABLE 	6 1 6
	21	[106]	SETTABLE 	6 -13 -14	; "bordersize" 0
	22	[107]	SETTABLE 	6 -15 -14	; "padding" 0
	23	[108]	GETTABLE 	7 0 -16	; "padding_top"
	24	[108]	SETTABLE 	6 -16 7	; "padding_top" -
	25	[109]	GETTABLE 	7 0 -17	; "padding_bottom"
	26	[109]	SETTABLE 	6 -17 7	; "padding_bottom" -
	27	[110]	GETTABLE 	7 0 -18	; "padding_left"
	28	[110]	SETTABLE 	6 -18 7	; "padding_left" -
	29	[111]	GETTABLE 	7 0 -19	; "padding_right"
	30	[111]	ADD      	7 7 3
	31	[111]	SETTABLE 	6 -19 7	; "padding_right" -
	32	[113]	MOVE     	7 1
	33	[113]	SETLIST  	6 1 1	; 1
	34	[105]	CALL     	4 3 2
	35	[113]	SETTABLE 	0 -12 4	; 1 -
	36	[115]	GETUPVAL 	4 3	; Geom
	37	[115]	SELF     	4 4 -1	; "new"
	38	[115]	NEWTABLE 	6 0 2
	39	[116]	GETTABLE 	7 2 -10	; "w"
	40	[116]	ADD      	7 7 3
	41	[116]	GETTABLE 	8 0 -19	; "padding_right"
	42	[116]	ADD      	7 7 8
	43	[116]	SETTABLE 	6 -10 7	; "w" -
	44	[117]	GETTABLE 	7 2 -9	; "h"
	45	[117]	SETTABLE 	6 -9 7	; "h" -
	46	[115]	CALL     	4 3 2
	47	[118]	SETTABLE 	0 -20 4	; "dimen" -
	48	[119]	GETTABLE 	4 0 -21	; "ges_events"
	49	[119]	NEWTABLE 	5 1 1
	50	[120]	GETUPVAL 	6 4	; GestureRange
	51	[120]	SELF     	6 6 -1	; "new"
	52	[120]	NEWTABLE 	8 0 2
	53	[121]	SETTABLE 	8 -23 -24	; "ges" "tap"
	54	[122]	GETTABLE 	9 0 -20	; "dimen"
	55	[122]	SETTABLE 	8 -25 9	; "range" -
	56	[120]	CALL     	6 3 2
	57	[124]	SETTABLE 	5 -26 -27	; "doc" "Close menu"
	58	[125]	SETLIST  	5 1 1	; 1
	59	[125]	SETTABLE 	4 -22 5	; "Close" -
	60	[126]	RETURN   	0 1

function <./frontend/ui/widget/menu.lua:128,131> (6 instructions, 24 bytes at 0x7ffad5d05670)
1 param, 3 slots, 0 upvalues, 1 local, 2 constants, 0 functions
	1	[129]	GETTABLE 	1 0 -1	; "menu"
	2	[129]	SELF     	1 1 -2	; "onClose"
	3	[129]	CALL     	1 2 1
	4	[130]	LOADBOOL 	1 1 0
	5	[130]	RETURN   	1 2
	6	[131]	RETURN   	0 1

function <./frontend/ui/widget/menu.lua:155,427> (541 instructions, 2164 bytes at 0x7ffad5d05ba0)
1 param, 32 slots, 20 upvalues, 32 locals, 86 constants, 1 function
	1	[156]	GETTABLE 	1 0 -2	; "dimen"
	2	[156]	GETTABLE 	1 1 -3	; "w"
	3	[156]	GETUPVAL 	2 0	; Size
	4	[156]	GETTABLE 	2 2 -4	; "padding"
	5	[156]	GETTABLE 	2 2 -5	; "fullscreen"
	6	[156]	MUL      	2 -6 2	; 2 -
	7	[156]	SUB      	1 1 2
	8	[156]	SETTABLE 	0 -1 1	; "content_width" -
	9	[157]	GETUPVAL 	1 1	; Geom
	10	[157]	SELF     	1 1 -7	; "new"
	11	[157]	CALL     	1 2 2
	12	[158]	GETTABLE 	2 0 -8	; "shortcut"
	13	[158]	TEST     	2 0 0
	14	[158]	JMP      	18	; to 33
	15	[159]	GETGLOBAL	2 -9	; math
	16	[159]	GETTABLE 	2 2 -10	; "floor"
	17	[159]	GETTABLE 	3 0 -2	; "dimen"
	18	[159]	GETTABLE 	3 3 -11	; "h"
	19	[159]	MUL      	3 3 -12	; - 4
	20	[159]	DIV      	3 3 -13	; - 5
	21	[159]	CALL     	2 2 2
	22	[159]	SETTABLE 	1 -3 2	; "w" -
	23	[160]	GETTABLE 	2 1 -3	; "w"
	24	[160]	SETTABLE 	1 -11 2	; "h" -
	25	[161]	GETTABLE 	2 0 -1	; "content_width"
	26	[161]	GETTABLE 	3 1 -3	; "w"
	27	[161]	SUB      	2 2 3
	28	[161]	GETUPVAL 	3 0	; Size
	29	[161]	GETTABLE 	3 3 -14	; "span"
	30	[161]	GETTABLE 	3 3 -15	; "horizontal_default"
	31	[161]	SUB      	2 2 3
	32	[161]	SETTABLE 	0 -1 2	; "content_width" -
	33	[164]	GETTABLE 	2 0 -17	; "text"
	34	[164]	SETTABLE 	0 -16 2	; "detail" -
	35	[167]	GETUPVAL 	2 2	; Device
	36	[167]	SELF     	2 2 -18	; "isTouchDevice"
	37	[167]	CALL     	2 2 2
	38	[167]	TEST     	2 0 0
	39	[167]	JMP      	24	; to 64
	40	[168]	NEWTABLE 	2 0 2
	41	[169]	NEWTABLE 	3 1 1
	42	[170]	GETUPVAL 	4 3	; GestureRange
	43	[170]	SELF     	4 4 -7	; "new"
	44	[170]	NEWTABLE 	6 0 2
	45	[171]	SETTABLE 	6 -21 -22	; "ges" "tap"
	46	[172]	GETTABLE 	7 0 -2	; "dimen"
	47	[172]	SETTABLE 	6 -23 7	; "range" -
	48	[170]	CALL     	4 3 2
	49	[174]	SETTABLE 	3 -24 -25	; "doc" "Select Menu Item"
	50	[175]	SETLIST  	3 1 1	; 1
	51	[175]	SETTABLE 	2 -20 3	; "TapSelect" -
	52	[176]	NEWTABLE 	3 1 1
	53	[177]	GETUPVAL 	4 3	; GestureRange
	54	[177]	SELF     	4 4 -7	; "new"
	55	[177]	NEWTABLE 	6 0 2
	56	[178]	SETTABLE 	6 -21 -27	; "ges" "hold"
	57	[179]	GETTABLE 	7 0 -2	; "dimen"
	58	[179]	SETTABLE 	6 -23 7	; "range" -
	59	[177]	CALL     	4 3 2
	60	[181]	SETTABLE 	3 -24 -28	; "doc" "Hold Menu Item"
	61	[182]	SETLIST  	3 1 1	; 1
	62	[182]	SETTABLE 	2 -26 3	; "HoldSelect" -
	63	[183]	SETTABLE 	0 -19 2	; "ges_events" -
	64	[186]	GETTABLE 	2 0 -2	; "dimen"
	65	[186]	GETTABLE 	2 2 -11	; "h"
	66	[186]	GETTABLE 	3 0 -29	; "linesize"
	67	[186]	MUL      	3 -6 3	; 2 -
	68	[186]	SUB      	2 2 3
	69	[189]	GETUPVAL 	3 4	; TextBoxWidget
	70	[189]	SELF     	3 3 -30	; "getFontSizeToFitHeight"
	71	[189]	MOVE     	5 2
	72	[189]	LOADK    	6 -31	; 1
	73	[189]	CALL     	3 4 2
	74	[190]	GETTABLE 	4 0 -32	; "font_size"
	75	[190]	LT       	0 3 4
	76	[190]	JMP      	1	; to 78
	77	[191]	SETTABLE 	0 -32 3	; "font_size" -
	78	[193]	GETTABLE 	4 0 -33	; "infont_size"
	79	[193]	LT       	0 3 4
	80	[193]	JMP      	1	; to 82
	81	[194]	SETTABLE 	0 -33 3	; "infont_size" -
	82	[196]	GETGLOBAL	4 -34	; G_reader_settings
	83	[196]	SELF     	4 4 -35	; "isTrue"
	84	[196]	LOADK    	6 -36	; "items_multilines_show_more_text"
	85	[196]	CALL     	4 3 2
	86	[197]	GETTABLE 	5 0 -37	; "single_line"
	87	[197]	TEST     	5 0 1
	88	[197]	JMP      	11	; to 100
	89	[197]	TEST     	4 0 1
	90	[197]	JMP      	9	; to 100
	91	[206]	GETUPVAL 	5 4	; TextBoxWidget
	92	[206]	SELF     	5 5 -30	; "getFontSizeToFitHeight"
	93	[206]	MOVE     	7 2
	94	[206]	LOADK    	8 -6	; 2
	95	[206]	CALL     	5 4 2
	96	[207]	GETTABLE 	6 0 -32	; "font_size"
	97	[207]	LT       	0 5 6
	98	[207]	JMP      	1	; to 100
	99	[208]	SETTABLE 	0 -37 -38	; "single_line" true
	100	[213]	GETTABLE 	5 0 -39	; "state_size"
	101	[213]	GETTABLE 	5 5 -3	; "w"
	102	[213]	TEST     	5 0 1
	103	[213]	JMP      	1	; to 105
	104	[213]	LOADK    	5 -40	; 0
	105	[214]	GETTABLE 	6 0 -41	; "state"
	106	[214]	TEST     	6 0 1
	107	[214]	JMP      	5	; to 113
	108	[214]	GETUPVAL 	6 5	; HorizontalSpan
	109	[214]	SELF     	6 6 -7	; "new"
	110	[214]	NEWTABLE 	8 0 1
	111	[215]	SETTABLE 	8 -42 5	; "width" -
	112	[214]	CALL     	6 3 2
	113	[217]	GETTABLE 	7 0 -41	; "state"
	114	[217]	TEST     	7 0 0
	115	[217]	JMP      	4	; to 120
	116	[217]	GETTABLE 	7 0 -41	; "state"
	117	[217]	GETTABLE 	7 7 -43	; "indent"
	118	[217]	TEST     	7 0 1
	119	[217]	JMP      	1	; to 121
	120	[217]	LOADK    	7 -44	; ""
	121	[218]	GETUPVAL 	8 6	; LeftContainer
	122	[218]	SELF     	8 8 -7	; "new"
	123	[218]	NEWTABLE 	10 0 1
	124	[219]	GETUPVAL 	11 1	; Geom
	125	[219]	SELF     	11 11 -7	; "new"
	126	[219]	NEWTABLE 	13 0 2
	127	[219]	GETTABLE 	14 0 -1	; "content_width"
	128	[219]	DIV      	14 14 -6	; - 2
	129	[219]	SETTABLE 	13 -3 14	; "w" -
	130	[219]	GETTABLE 	14 0 -2	; "dimen"
	131	[219]	GETTABLE 	14 14 -11	; "h"
	132	[219]	SETTABLE 	13 -11 14	; "h" -
	133	[219]	CALL     	11 3 2
	134	[219]	SETTABLE 	10 -2 11	; "dimen" -
	135	[220]	GETUPVAL 	11 7	; HorizontalGroup
	136	[220]	SELF     	11 11 -7	; "new"
	137	[220]	NEWTABLE 	13 2 0
	138	[221]	GETUPVAL 	14 8	; TextWidget
	139	[221]	SELF     	14 14 -7	; "new"
	140	[221]	NEWTABLE 	16 0 2
	141	[222]	SETTABLE 	16 -17 7	; "text" -
	142	[223]	GETUPVAL 	17 9	; Font
	143	[223]	SELF     	17 17 -46	; "getFace"
	144	[223]	GETTABLE 	19 0 -47	; "font"
	145	[223]	GETTABLE 	20 0 -32	; "font_size"
	146	[223]	CALL     	17 4 2
	147	[223]	SETTABLE 	16 -45 17	; "face" -
	148	[221]	CALL     	14 3 2
	149	[226]	MOVE     	15 6
	150	[226]	SETLIST  	13 2 1	; 1
	151	[220]	CALL     	11 3 0
	152	[227]	SETLIST  	10 0 1	; 1
	153	[218]	CALL     	8 3 2
	154	[230]	GETUPVAL 	9 9	; Font
	155	[230]	SELF     	9 9 -46	; "getFace"
	156	[230]	GETTABLE 	11 0 -47	; "font"
	157	[230]	GETTABLE 	12 0 -32	; "font_size"
	158	[230]	CALL     	9 4 2
	159	[230]	SETTABLE 	0 -45 9	; "face" -
	160	[232]	GETUPVAL 	9 9	; Font
	161	[232]	SELF     	9 9 -46	; "getFace"
	162	[232]	GETTABLE 	11 0 -49	; "infont"
	163	[232]	GETTABLE 	12 0 -33	; "infont_size"
	164	[232]	CALL     	9 4 2
	165	[232]	SETTABLE 	0 -48 9	; "info_face" -
	166	[236]	LOADK    	9 -40	; 0
	167	[237]	LOADK    	10 -40	; 0
	168	[238]	GETTABLE 	11 0 -50	; "mandatory"
	169	[238]	TEST     	11 0 0
	170	[238]	JMP      	6	; to 177
	171	[239]	GETUPVAL 	11 0	; Size
	172	[239]	GETTABLE 	11 11 -14	; "span"
	173	[239]	GETTABLE 	9 11 -15	; "horizontal_default"
	174	[241]	GETUPVAL 	11 0	; Size
	175	[241]	GETTABLE 	11 11 -14	; "span"
	176	[241]	GETTABLE 	10 11 -51	; "horizontal_small"
	177	[243]	GETTABLE 	11 0 -50	; "mandatory"
	178	[243]	TEST     	11 0 0
	179	[243]	JMP      	5	; to 185
	180	[243]	LOADK    	11 -44	; ""
	181	[243]	GETTABLE 	12 0 -50	; "mandatory"
	182	[243]	CONCAT   	11 11 12
	183	[243]	TEST     	11 0 1
	184	[243]	JMP      	1	; to 186
	185	[243]	LOADK    	11 -44	; ""
	186	[244]	GETUPVAL 	12 8	; TextWidget
	187	[244]	SELF     	12 12 -7	; "new"
	188	[244]	NEWTABLE 	14 0 4
	189	[245]	SETTABLE 	14 -17 11	; "text" -
	190	[246]	GETTABLE 	15 0 -48	; "info_face"
	191	[246]	SETTABLE 	14 -45 15	; "face" -
	192	[247]	GETTABLE 	15 0 -52	; "bold"
	193	[247]	SETTABLE 	14 -52 15	; "bold" -
	194	[248]	GETTABLE 	15 0 -54	; "dim"
	195	[248]	TEST     	15 0 0
	196	[248]	JMP      	4	; to 201
	197	[248]	GETUPVAL 	15 10	; Blitbuffer
	198	[248]	GETTABLE 	15 15 -55	; "COLOR_DARK_GRAY"
	199	[248]	TEST     	15 0 1
	200	[248]	JMP      	1	; to 202
	201	[248]	LOADNIL  	15 15
	202	[248]	SETTABLE 	14 -53 15	; "fgcolor" -
	203	[244]	CALL     	12 3 2
	204	[250]	SELF     	13 12 -56	; "getWidth"
	205	[250]	CALL     	13 2 2
	206	[252]	GETTABLE 	14 0 -1	; "content_width"
	207	[252]	SUB      	14 14 5
	208	[252]	SUB      	14 14 9
	209	[252]	SUB      	14 14 13
	210	[253]	LOADNIL  	15 15
	211	[259]	GETTABLE 	16 0 -17	; "text"
	212	[259]	SELF     	16 16 -57	; "gsub"
	213	[259]	LOADK    	18 -58	; "\n"
	214	[259]	LOADK    	19 -59	; " "
	215	[259]	CALL     	16 4 2
	216	[263]	GETTABLE 	17 0 -60	; "bidi_wrap_func"
	217	[263]	TEST     	17 0 0
	218	[263]	JMP      	4	; to 223
	219	[264]	GETTABLE 	17 0 -60	; "bidi_wrap_func"
	220	[264]	MOVE     	18 16
	221	[264]	CALL     	17 2 2
	222	[264]	MOVE     	16 17
	223	[267]	GETTABLE 	17 0 -37	; "single_line"
	224	[267]	TEST     	17 0 0
	225	[267]	JMP      	70	; to 296
	226	[269]	GETUPVAL 	17 8	; TextWidget
	227	[269]	SELF     	17 17 -7	; "new"
	228	[269]	NEWTABLE 	19 0 4
	229	[270]	SETTABLE 	19 -17 16	; "text" -
	230	[271]	GETTABLE 	20 0 -45	; "face"
	231	[271]	SETTABLE 	19 -45 20	; "face" -
	232	[272]	GETTABLE 	20 0 -52	; "bold"
	233	[272]	SETTABLE 	19 -52 20	; "bold" -
	234	[273]	GETTABLE 	20 0 -54	; "dim"
	235	[273]	TEST     	20 0 0
	236	[273]	JMP      	4	; to 241
	237	[273]	GETUPVAL 	20 10	; Blitbuffer
	238	[273]	GETTABLE 	20 20 -55	; "COLOR_DARK_GRAY"
	239	[273]	TEST     	20 0 1
	240	[273]	JMP      	1	; to 242
	241	[273]	LOADNIL  	20 20
	242	[273]	SETTABLE 	19 -53 20	; "fgcolor" -
	243	[269]	CALL     	17 3 2
	244	[274]	MOVE     	15 17
	245	[275]	SELF     	17 15 -56	; "getWidth"
	246	[275]	CALL     	17 2 2
	247	[276]	LT       	0 14 17
	248	[276]	JMP      	5	; to 254
	249	[279]	ADD      	18 14 9
	250	[279]	SUB      	18 18 10
	251	[280]	SELF     	19 15 -61	; "setMaxWidth"
	252	[280]	MOVE     	21 18
	253	[280]	CALL     	19 3 1
	254	[282]	GETTABLE 	18 0 -62	; "align_baselines"
	255	[282]	TEST     	18 0 0
	256	[282]	JMP      	126	; to 383
	257	[283]	SELF     	18 15 -63	; "getBaseline"
	258	[283]	CALL     	18 2 2
	259	[284]	SELF     	19 12 -63	; "getBaseline"
	260	[284]	CALL     	19 2 2
	261	[285]	GETUPVAL 	20 11	; Math
	262	[285]	GETTABLE 	20 20 -64	; "round"
	263	[285]	SUB      	21 18 19
	264	[285]	CALL     	20 2 2
	265	[286]	LT       	0 -40 20	; 0 -
	266	[286]	JMP      	13	; to 280
	267	[287]	GETUPVAL 	21 12	; VerticalGroup
	268	[287]	SELF     	21 21 -7	; "new"
	269	[287]	NEWTABLE 	23 2 0
	270	[288]	GETUPVAL 	24 13	; VerticalSpan
	271	[288]	SELF     	24 24 -7	; "new"
	272	[288]	NEWTABLE 	26 0 1
	273	[288]	SETTABLE 	26 -42 20	; "width" -
	274	[288]	CALL     	24 3 2
	275	[290]	MOVE     	25 12
	276	[290]	SETLIST  	23 2 1	; 1
	277	[287]	CALL     	21 3 2
	278	[290]	MOVE     	12 21
	279	[290]	JMP      	103	; to 383
	280	[291]	LT       	0 20 -40	; - 0
	281	[291]	JMP      	101	; to 383
	282	[292]	GETUPVAL 	21 12	; VerticalGroup
	283	[292]	SELF     	21 21 -7	; "new"
	284	[292]	NEWTABLE 	23 2 0
	285	[293]	GETUPVAL 	24 13	; VerticalSpan
	286	[293]	SELF     	24 24 -7	; "new"
	287	[293]	NEWTABLE 	26 0 1
	288	[293]	UNM      	27 20
	289	[293]	SETTABLE 	26 -42 27	; "width" -
	290	[293]	CALL     	24 3 2
	291	[295]	MOVE     	25 15
	292	[295]	SETLIST  	23 2 1	; 1
	293	[292]	CALL     	21 3 2
	294	[295]	MOVE     	15 21
	295	[297]	JMP      	87	; to 383
	296	[299]	TEST     	4 0 0
	297	[299]	JMP      	61	; to 359
	298	[304]	GETUPVAL 	17 14	; logger
	299	[304]	GETTABLE 	17 17 -65	; "dbg"
	300	[304]	LOADK    	18 -66	; "multilines_show_more_text menu item font sizing start"
	301	[304]	CALL     	17 2 1
	302	[320]	CLOSURE  	17 0	; 0x7ffad5d05920
	303	[320]	MOVE     	0 15
	304	[320]	GETUPVAL 	0 14	; logger
	305	[320]	GETUPVAL 	0 4	; TextBoxWidget
	306	[320]	MOVE     	0 16
	307	[320]	GETUPVAL 	0 9	; Font
	308	[320]	MOVE     	0 0
	309	[320]	MOVE     	0 14
	310	[320]	GETUPVAL 	0 10	; Blitbuffer
	311	[320]	MOVE     	0 2
	312	[321]	LOADK    	18 -67	; 12
	313	[323]	MOVE     	19 17
	314	[323]	GETTABLE 	20 0 -32	; "font_size"
	315	[323]	CALL     	19 2 2
	316	[323]	TEST     	19 0 1
	317	[323]	JMP      	65	; to 383
	318	[325]	MOVE     	19 17
	319	[325]	MOVE     	20 18
	320	[325]	CALL     	19 2 2
	321	[325]	TEST     	19 0 1
	322	[325]	JMP      	8	; to 331
	323	[328]	SELF     	19 15 -68	; "free"
	324	[328]	CALL     	19 2 1
	325	[329]	SETTABLE 	15 -69 2	; "height" -
	326	[330]	SETTABLE 	15 -70 -38	; "height_adjust" true
	327	[331]	SETTABLE 	15 -71 -38	; "height_overflow_show_ellipsis" true
	328	[332]	SELF     	19 15 -72	; "init"
	329	[332]	CALL     	19 2 1
	330	[332]	JMP      	52	; to 383
	331	[337]	GETTABLE 	19 0 -32	; "font_size"
	332	[338]	MOVE     	20 18
	333	[339]	LOADBOOL 	21 1 0
	334	[341]	GETGLOBAL	22 -9	; math
	335	[341]	GETTABLE 	22 22 -10	; "floor"
	336	[341]	ADD      	23 20 19
	337	[341]	DIV      	23 23 -6	; - 2
	338	[341]	CALL     	22 2 2
	339	[342]	EQ       	0 22 20
	340	[342]	JMP      	6	; to 347
	341	[343]	TEST     	21 0 1
	342	[343]	JMP      	40	; to 383
	343	[344]	MOVE     	23 17
	344	[344]	MOVE     	24 20
	345	[344]	CALL     	23 2 1
	346	[346]	JMP      	36	; to 383
	347	[348]	MOVE     	23 17
	348	[348]	MOVE     	24 22
	349	[348]	CALL     	23 2 2
	350	[348]	TEST     	23 0 0
	351	[348]	JMP      	3	; to 355
	352	[349]	MOVE     	20 22
	353	[350]	LOADBOOL 	21 1 0
	354	[350]	JMP      	-21	; to 334
	355	[352]	MOVE     	19 22
	356	[353]	LOADBOOL 	21 0 0
	357	[354]	JMP      	-24	; to 334
	358	[357]	JMP      	24	; to 383
	359	[360]	GETUPVAL 	17 4	; TextBoxWidget
	360	[360]	SELF     	17 17 -7	; "new"
	361	[360]	NEWTABLE 	19 0 9
	362	[361]	SETTABLE 	19 -17 16	; "text" -
	363	[362]	GETTABLE 	20 0 -45	; "face"
	364	[362]	SETTABLE 	19 -45 20	; "face" -
	365	[363]	SETTABLE 	19 -42 14	; "width" -
	366	[364]	SETTABLE 	19 -69 2	; "height" -
	367	[365]	SETTABLE 	19 -70 -38	; "height_adjust" true
	368	[366]	SETTABLE 	19 -71 -38	; "height_overflow_show_ellipsis" true
	369	[367]	SETTABLE 	19 -73 -74	; "alignment" "left"
	370	[368]	GETTABLE 	20 0 -52	; "bold"
	371	[368]	SETTABLE 	19 -52 20	; "bold" -
	372	[369]	GETTABLE 	20 0 -54	; "dim"
	373	[369]	TEST     	20 0 0
	374	[369]	JMP      	4	; to 379
	375	[369]	GETUPVAL 	20 10	; Blitbuffer
	376	[369]	GETTABLE 	20 20 -55	; "COLOR_DARK_GRAY"
	377	[369]	TEST     	20 0 1
	378	[369]	JMP      	1	; to 380
	379	[369]	LOADNIL  	20 20
	380	[369]	SETTABLE 	19 -53 20	; "fgcolor" -
	381	[360]	CALL     	17 3 2
	382	[370]	MOVE     	15 17
	383	[373]	GETUPVAL 	17 6	; LeftContainer
	384	[373]	SELF     	17 17 -7	; "new"
	385	[373]	NEWTABLE 	19 0 1
	386	[374]	GETUPVAL 	20 1	; Geom
	387	[374]	SELF     	20 20 -7	; "new"
	388	[374]	NEWTABLE 	22 0 2
	389	[374]	GETTABLE 	23 0 -1	; "content_width"
	390	[374]	SETTABLE 	22 -3 23	; "w" -
	391	[374]	GETTABLE 	23 0 -2	; "dimen"
	392	[374]	GETTABLE 	23 23 -11	; "h"
	393	[374]	SETTABLE 	22 -11 23	; "h" -
	394	[374]	CALL     	20 3 2
	395	[374]	SETTABLE 	19 -2 20	; "dimen" -
	396	[375]	GETUPVAL 	20 7	; HorizontalGroup
	397	[375]	SELF     	20 20 -7	; "new"
	398	[375]	NEWTABLE 	22 2 0
	399	[376]	GETUPVAL 	23 5	; HorizontalSpan
	400	[376]	SELF     	23 23 -7	; "new"
	401	[376]	NEWTABLE 	25 0 1
	402	[377]	GETTABLE 	26 0 -39	; "state_size"
	403	[377]	GETTABLE 	26 26 -3	; "w"
	404	[377]	SETTABLE 	25 -42 26	; "width" -
	405	[376]	CALL     	23 3 2
	406	[380]	MOVE     	24 15
	407	[380]	SETLIST  	22 2 1	; 1
	408	[375]	CALL     	20 3 0
	409	[381]	SETLIST  	19 0 1	; 1
	410	[373]	CALL     	17 3 2
	411	[383]	GETUPVAL 	18 15	; RightContainer
	412	[383]	SELF     	18 18 -7	; "new"
	413	[383]	NEWTABLE 	20 1 1
	414	[384]	GETUPVAL 	21 1	; Geom
	415	[384]	SELF     	21 21 -7	; "new"
	416	[384]	NEWTABLE 	23 0 2
	417	[384]	GETTABLE 	24 0 -1	; "content_width"
	418	[384]	SETTABLE 	23 -3 24	; "w" -
	419	[384]	GETTABLE 	24 0 -2	; "dimen"
	420	[384]	GETTABLE 	24 24 -11	; "h"
	421	[384]	SETTABLE 	23 -11 24	; "h" -
	422	[384]	CALL     	21 3 2
	423	[384]	SETTABLE 	20 -2 21	; "dimen" -
	424	[386]	MOVE     	21 12
	425	[386]	SETLIST  	20 1 1	; 1
	426	[383]	CALL     	18 3 2
	427	[388]	GETUPVAL 	19 16	; UnderlineContainer
	428	[388]	SELF     	19 19 -7	; "new"
	429	[388]	NEWTABLE 	21 0 5
	430	[389]	GETTABLE 	22 0 -77	; "line_color"
	431	[389]	SETTABLE 	21 -76 22	; "color" -
	432	[390]	GETTABLE 	22 0 -29	; "linesize"
	433	[390]	SETTABLE 	21 -29 22	; "linesize" -
	434	[391]	SETTABLE 	21 -78 -79	; "vertical_align" "center"
	435	[392]	SETTABLE 	21 -4 -40	; "padding" 0
	436	[393]	GETUPVAL 	22 1	; Geom
	437	[393]	SELF     	22 22 -7	; "new"
	438	[393]	NEWTABLE 	24 0 2
	439	[394]	GETTABLE 	25 0 -1	; "content_width"
	440	[394]	SETTABLE 	24 -3 25	; "w" -
	441	[395]	GETTABLE 	25 0 -2	; "dimen"
	442	[395]	GETTABLE 	25 25 -11	; "h"
	443	[395]	SETTABLE 	24 -11 25	; "h" -
	444	[393]	CALL     	22 3 2
	445	[396]	SETTABLE 	21 -2 22	; "dimen" -
	446	[397]	GETUPVAL 	22 7	; HorizontalGroup
	447	[397]	SELF     	22 22 -7	; "new"
	448	[397]	NEWTABLE 	24 0 1
	449	[398]	SETTABLE 	24 -80 -79	; "align" "center"
	450	[399]	GETUPVAL 	25 17	; OverlapGroup
	451	[399]	SELF     	25 25 -7	; "new"
	452	[399]	NEWTABLE 	27 3 1
	453	[400]	GETUPVAL 	28 1	; Geom
	454	[400]	SELF     	28 28 -7	; "new"
	455	[400]	NEWTABLE 	30 0 2
	456	[400]	GETTABLE 	31 0 -1	; "content_width"
	457	[400]	SETTABLE 	30 -3 31	; "w" -
	458	[400]	GETTABLE 	31 0 -2	; "dimen"
	459	[400]	GETTABLE 	31 31 -11	; "h"
	460	[400]	SETTABLE 	30 -11 31	; "h" -
	461	[400]	CALL     	28 3 2
	462	[400]	SETTABLE 	27 -2 28	; "dimen" -
	463	[401]	MOVE     	28 8
	464	[402]	MOVE     	29 17
	465	[404]	MOVE     	30 18
	466	[404]	SETLIST  	27 3 1	; 1
	467	[399]	CALL     	25 3 0
	468	[405]	SETLIST  	24 0 1	; 1
	469	[397]	CALL     	22 3 0
	470	[406]	SETLIST  	21 0 1	; 1
	471	[388]	CALL     	19 3 2
	472	[406]	SETTABLE 	0 -75 19	; "_underline_container" -
	473	[407]	GETUPVAL 	19 7	; HorizontalGroup
	474	[407]	SELF     	19 19 -7	; "new"
	475	[407]	NEWTABLE 	21 0 1
	476	[408]	SETTABLE 	21 -80 -79	; "align" "center"
	477	[409]	GETUPVAL 	22 5	; HorizontalSpan
	478	[409]	SELF     	22 22 -7	; "new"
	479	[409]	NEWTABLE 	24 0 1
	480	[409]	GETUPVAL 	25 0	; Size
	481	[409]	GETTABLE 	25 25 -4	; "padding"
	482	[409]	GETTABLE 	25 25 -5	; "fullscreen"
	483	[409]	SETTABLE 	24 -42 25	; "width" -
	484	[409]	CALL     	22 3 0
	485	[410]	SETLIST  	21 0 1	; 1
	486	[407]	CALL     	19 3 2
	487	[411]	GETTABLE 	20 0 -8	; "shortcut"
	488	[411]	TEST     	20 0 0
	489	[411]	JMP      	25	; to 515
	490	[412]	GETGLOBAL	20 -81	; table
	491	[412]	GETTABLE 	20 20 -82	; "insert"
	492	[412]	MOVE     	21 19
	493	[412]	GETUPVAL 	22 18	; ItemShortCutIcon
	494	[412]	SELF     	22 22 -7	; "new"
	495	[412]	NEWTABLE 	24 0 3
	496	[413]	SETTABLE 	24 -2 1	; "dimen" -
	497	[414]	GETTABLE 	25 0 -8	; "shortcut"
	498	[414]	SETTABLE 	24 -83 25	; "key" -
	499	[415]	GETTABLE 	25 0 -85	; "shortcut_style"
	500	[415]	SETTABLE 	24 -84 25	; "style" -
	501	[412]	CALL     	22 3 0
	502	[412]	CALL     	20 0 1
	503	[417]	GETGLOBAL	20 -81	; table
	504	[417]	GETTABLE 	20 20 -82	; "insert"
	505	[417]	MOVE     	21 19
	506	[417]	GETUPVAL 	22 5	; HorizontalSpan
	507	[417]	SELF     	22 22 -7	; "new"
	508	[417]	NEWTABLE 	24 0 1
	509	[417]	GETUPVAL 	25 0	; Size
	510	[417]	GETTABLE 	25 25 -14	; "span"
	511	[417]	GETTABLE 	25 25 -15	; "horizontal_default"
	512	[417]	SETTABLE 	24 -42 25	; "width" -
	513	[417]	CALL     	22 3 0
	514	[417]	CALL     	20 0 1
	515	[419]	GETGLOBAL	20 -81	; table
	516	[419]	GETTABLE 	20 20 -82	; "insert"
	517	[419]	MOVE     	21 19
	518	[419]	GETTABLE 	22 0 -75	; "_underline_container"
	519	[419]	CALL     	20 3 1
	520	[420]	GETGLOBAL	20 -81	; table
	521	[420]	GETTABLE 	20 20 -82	; "insert"
	522	[420]	MOVE     	21 19
	523	[420]	GETUPVAL 	22 5	; HorizontalSpan
	524	[420]	SELF     	22 22 -7	; "new"
	525	[420]	NEWTABLE 	24 0 1
	526	[420]	GETUPVAL 	25 0	; Size
	527	[420]	GETTABLE 	25 25 -4	; "padding"
	528	[420]	GETTABLE 	25 25 -5	; "fullscreen"
	529	[420]	SETTABLE 	24 -42 25	; "width" -
	530	[420]	CALL     	22 3 0
	531	[420]	CALL     	20 0 1
	532	[422]	GETUPVAL 	20 19	; FrameContainer
	533	[422]	SELF     	20 20 -7	; "new"
	534	[422]	NEWTABLE 	22 1 2
	535	[423]	SETTABLE 	22 -86 -40	; "bordersize" 0
	536	[424]	SETTABLE 	22 -4 -40	; "padding" 0
	537	[426]	MOVE     	23 19
	538	[426]	SETLIST  	22 1 1	; 1
	539	[422]	CALL     	20 3 2
	540	[426]	SETTABLE 	0 -31 20	; 1 -
	541	[427]	RETURN   	0 1

function <./frontend/ui/widget/menu.lua:305,320> (52 instructions, 208 bytes at 0x7ffad5d05920)
1 param, 8 slots, 9 upvalues, 1 local, 17 constants, 0 functions
	1	[306]	GETUPVAL 	1 0	; item_name
	2	[306]	TEST     	1 0 0
	3	[306]	JMP      	3	; to 7
	4	[307]	GETUPVAL 	1 0	; item_name
	5	[307]	SELF     	1 1 -1	; "free"
	6	[307]	CALL     	1 2 1
	7	[309]	GETUPVAL 	1 1	; logger
	8	[309]	GETTABLE 	1 1 -2	; "dbg"
	9	[309]	LOADK    	2 -3	; "multilines_show_more_text trying font size"
	10	[309]	MOVE     	3 0
	11	[309]	CALL     	1 3 1
	12	[310]	GETUPVAL 	1 2	; TextBoxWidget
	13	[310]	SELF     	1 1 -4	; "new"
	14	[310]	NEWTABLE 	3 0 6
	15	[311]	GETUPVAL 	4 3	; text
	16	[311]	SETTABLE 	3 -5 4	; "text" -
	17	[312]	GETUPVAL 	4 4	; Font
	18	[312]	SELF     	4 4 -7	; "getFace"
	19	[312]	GETUPVAL 	6 5	; self
	20	[312]	GETTABLE 	6 6 -8	; "font"
	21	[312]	MOVE     	7 0
	22	[312]	CALL     	4 4 2
	23	[312]	SETTABLE 	3 -6 4	; "face" -
	24	[313]	GETUPVAL 	4 6	; available_width
	25	[313]	SETTABLE 	3 -9 4	; "width" -
	26	[314]	SETTABLE 	3 -10 -11	; "alignment" "left"
	27	[315]	GETUPVAL 	4 5	; self
	28	[315]	GETTABLE 	4 4 -12	; "bold"
	29	[315]	SETTABLE 	3 -12 4	; "bold" -
	30	[316]	GETUPVAL 	4 5	; self
	31	[316]	GETTABLE 	4 4 -14	; "dim"
	32	[316]	TEST     	4 0 0
	33	[316]	JMP      	4	; to 38
	34	[316]	GETUPVAL 	4 7	; Blitbuffer
	35	[316]	GETTABLE 	4 4 -15	; "COLOR_DARK_GRAY"
	36	[316]	TEST     	4 0 1
	37	[316]	JMP      	1	; to 39
	38	[316]	LOADNIL  	4 4
	39	[316]	SETTABLE 	3 -13 4	; "fgcolor" -
	40	[310]	CALL     	1 3 2
	41	[317]	SETUPVAL 	1 0	; item_name
	42	[319]	GETUPVAL 	1 0	; item_name
	43	[319]	SELF     	1 1 -16	; "getSize"
	44	[319]	CALL     	1 2 2
	45	[319]	GETTABLE 	1 1 -17	; "h"
	46	[319]	GETUPVAL 	2 8	; max_item_height
	47	[319]	LE       	1 1 2
	48	[319]	JMP      	1	; to 50
	49	[319]	LOADBOOL 	1 0 1
	50	[319]	LOADBOOL 	1 1 0
	51	[319]	RETURN   	1 2
	52	[320]	RETURN   	0 1

function <./frontend/ui/widget/menu.lua:429,444> (25 instructions, 100 bytes at 0x7ffad5d05f10)
2 params, 4 slots, 2 upvalues, 2 locals, 7 constants, 0 functions
	1	[430]	GETUPVAL 	2 0	; Device
	2	[430]	SELF     	2 2 -1	; "isTouchDevice"
	3	[430]	CALL     	2 2 2
	4	[430]	TEST     	2 0 0
	5	[430]	JMP      	13	; to 19
	6	[436]	TEST     	1 0 0
	7	[436]	JMP      	4	; to 12
	8	[436]	GETTABLE 	2 0 -2	; "menu"
	9	[436]	GETTABLE 	2 2 -3	; "did_focus_with_keys"
	10	[436]	TEST     	2 0 0
	11	[436]	JMP      	11	; to 23
	12	[437]	GETTABLE 	2 0 -4	; "_underline_container"
	13	[437]	GETUPVAL 	3 1	; Blitbuffer
	14	[437]	GETTABLE 	3 3 -6	; "COLOR_BLACK"
	15	[437]	SETTABLE 	2 -5 3	; "color" -
	16	[438]	GETTABLE 	2 0 -2	; "menu"
	17	[438]	SETTABLE 	2 -3 -7	; "did_focus_with_keys" true
	18	[439]	JMP      	4	; to 23
	19	[441]	GETTABLE 	2 0 -4	; "_underline_container"
	20	[441]	GETUPVAL 	3 1	; Blitbuffer
	21	[441]	GETTABLE 	3 3 -6	; "COLOR_BLACK"
	22	[441]	SETTABLE 	2 -5 3	; "color" -
	23	[443]	LOADBOOL 	2 1 0
	24	[443]	RETURN   	2 2
	25	[444]	RETURN   	0 1

function <./frontend/ui/widget/menu.lua:446,449> (6 instructions, 24 bytes at 0x7ffad5d074b0)
1 param, 3 slots, 0 upvalues, 1 local, 3 constants, 0 functions
	1	[447]	GETTABLE 	1 0 -1	; "_underline_container"
	2	[447]	GETTABLE 	2 0 -3	; "line_color"
	3	[447]	SETTABLE 	1 -2 2	; "color" -
	4	[448]	LOADBOOL 	1 1 0
	5	[448]	RETURN   	1 2
	6	[449]	RETURN   	0 1

function <./frontend/ui/widget/menu.lua:451,454> (12 instructions, 48 bytes at 0x7ffad5d075c0)
1 param, 7 slots, 2 upvalues, 1 local, 4 constants, 0 functions
	1	[452]	GETUPVAL 	1 0	; UIManager
	2	[452]	SELF     	1 1 -1	; "show"
	3	[452]	GETUPVAL 	3 1	; InfoMessage
	4	[452]	SELF     	3 3 -2	; "new"
	5	[452]	NEWTABLE 	5 0 1
	6	[452]	GETTABLE 	6 0 -4	; "detail"
	7	[452]	SETTABLE 	5 -3 6	; "text" -
	8	[452]	CALL     	3 3 0
	9	[452]	CALL     	1 0 1
	10	[453]	LOADBOOL 	1 1 0
	11	[453]	RETURN   	1 2
	12	[454]	RETURN   	0 1

function <./frontend/ui/widget/menu.lua:456,462> (19 instructions, 76 bytes at 0x7ffad5d07960)
2 params, 6 slots, 0 upvalues, 3 locals, 7 constants, 0 functions
	1	[457]	GETTABLE 	2 0 -1	; 1
	2	[457]	GETTABLE 	2 2 -2	; "dimen"
	3	[458]	NEWTABLE 	3 0 2
	4	[459]	GETTABLE 	4 1 -4	; "pos"
	5	[459]	GETTABLE 	4 4 -3	; "x"
	6	[459]	GETTABLE 	5 2 -3	; "x"
	7	[459]	SUB      	4 4 5
	8	[459]	GETTABLE 	5 2 -5	; "w"
	9	[459]	DIV      	4 4 5
	10	[459]	SETTABLE 	3 -3 4	; "x" -
	11	[460]	GETTABLE 	4 1 -4	; "pos"
	12	[460]	GETTABLE 	4 4 -6	; "y"
	13	[460]	GETTABLE 	5 2 -6	; "y"
	14	[460]	SUB      	4 4 5
	15	[460]	GETTABLE 	5 2 -7	; "h"
	16	[460]	DIV      	4 4 5
	17	[460]	SETTABLE 	3 -6 4	; "y" -
	18	[461]	RETURN   	3 2
	19	[462]	RETURN   	0 1

function <./frontend/ui/widget/menu.lua:464,492> (53 instructions, 212 bytes at 0x7ffad5d07ee0)
3 params, 9 slots, 2 upvalues, 5 locals, 18 constants, 3 functions
	1	[465]	SELF     	3 0 -1	; "getGesPosition"
	2	[465]	MOVE     	5 2
	3	[465]	CALL     	3 3 2
	4	[466]	GETGLOBAL	4 -2	; G_reader_settings
	5	[466]	SELF     	4 4 -3	; "isFalse"
	6	[466]	LOADK    	6 -4	; "flash_ui"
	7	[466]	CALL     	4 3 2
	8	[466]	TEST     	4 0 0
	9	[466]	JMP      	15	; to 25
	10	[467]	GETUPVAL 	4 0	; logger
	11	[467]	GETTABLE 	4 4 -5	; "dbg"
	12	[467]	LOADK    	5 -6	; "creating coroutine for menu select"
	13	[467]	CALL     	4 2 1
	14	[468]	GETGLOBAL	4 -7	; coroutine
	15	[468]	GETTABLE 	4 4 -8	; "create"
	16	[470]	CLOSURE  	5 0	; 0x7ffad5d08480
	17	[470]	MOVE     	0 0
	18	[470]	MOVE     	0 3
	19	[468]	CALL     	4 2 2
	20	[471]	GETGLOBAL	5 -7	; coroutine
	21	[471]	GETTABLE 	5 5 -9	; "resume"
	22	[471]	MOVE     	6 4
	23	[471]	CALL     	5 2 1
	24	[471]	JMP      	26	; to 51
	25	[473]	GETTABLE 	4 0 -10	; 1
	26	[473]	SETTABLE 	4 -11 -12	; "invert" true
	27	[474]	GETUPVAL 	4 1	; UIManager
	28	[474]	SELF     	4 4 -13	; "widgetRepaint"
	29	[474]	GETTABLE 	6 0 -10	; 1
	30	[474]	GETTABLE 	7 0 -10	; 1
	31	[474]	GETTABLE 	7 7 -14	; "dimen"
	32	[474]	GETTABLE 	7 7 -15	; "x"
	33	[474]	GETTABLE 	8 0 -10	; 1
	34	[474]	GETTABLE 	8 8 -14	; "dimen"
	35	[474]	GETTABLE 	8 8 -16	; "y"
	36	[474]	CALL     	4 5 1
	37	[475]	GETUPVAL 	4 1	; UIManager
	38	[475]	SELF     	4 4 -17	; "setDirty"
	39	[475]	LOADNIL  	6 6
	40	[477]	CLOSURE  	7 1	; 0x7ffad5d08680
	41	[477]	MOVE     	0 0
	42	[475]	CALL     	4 4 1
	43	[478]	GETUPVAL 	4 1	; UIManager
	44	[478]	SELF     	4 4 -18	; "tickAfterNext"
	45	[489]	CLOSURE  	6 2	; 0x7ffad5d088c0
	46	[489]	GETUPVAL 	0 0	; logger
	47	[489]	MOVE     	0 0
	48	[489]	MOVE     	0 3
	49	[489]	GETUPVAL 	0 1	; UIManager
	50	[478]	CALL     	4 3 1
	51	[491]	LOADBOOL 	4 1 0
	52	[491]	RETURN   	4 2
	53	[492]	RETURN   	0 1

function <./frontend/ui/widget/menu.lua:468,470> (8 instructions, 32 bytes at 0x7ffad5d08480)
0 params, 4 slots, 2 upvalues, 0 locals, 3 constants, 0 functions
	1	[469]	GETUPVAL 	0 0	; self
	2	[469]	GETTABLE 	0 0 -1	; "menu"
	3	[469]	SELF     	0 0 -2	; "onMenuSelect"
	4	[469]	GETUPVAL 	2 0	; self
	5	[469]	GETTABLE 	2 2 -3	; "table"
	6	[469]	GETUPVAL 	3 1	; pos
	7	[469]	CALL     	0 4 1
	8	[470]	RETURN   	0 1

function <./frontend/ui/widget/menu.lua:475,477> (6 instructions, 24 bytes at 0x7ffad5d08680)
0 params, 2 slots, 1 upvalue, 0 locals, 3 constants, 0 functions
	1	[476]	LOADK    	0 -1	; "fast"
	2	[476]	GETUPVAL 	1 0	; self
	3	[476]	GETTABLE 	1 1 -2	; 1
	4	[476]	GETTABLE 	1 1 -3	; "dimen"
	5	[476]	RETURN   	0 3
	6	[477]	RETURN   	0 1

function <./frontend/ui/widget/menu.lua:478,489> (25 instructions, 100 bytes at 0x7ffad5d088c0)
0 params, 5 slots, 4 upvalues, 1 local, 10 constants, 2 functions
	1	[479]	GETUPVAL 	0 0	; logger
	2	[479]	GETTABLE 	0 0 -1	; "dbg"
	3	[479]	LOADK    	1 -2	; "creating coroutine for menu select"
	4	[479]	CALL     	0 2 1
	5	[480]	GETGLOBAL	0 -3	; coroutine
	6	[480]	GETTABLE 	0 0 -4	; "create"
	7	[482]	CLOSURE  	1 0	; 0x7ffad5d09030
	8	[482]	GETUPVAL 	0 1	; self
	9	[482]	GETUPVAL 	0 2	; pos
	10	[480]	CALL     	0 2 2
	11	[483]	GETGLOBAL	1 -3	; coroutine
	12	[483]	GETTABLE 	1 1 -5	; "resume"
	13	[483]	MOVE     	2 0
	14	[483]	CALL     	1 2 1
	15	[484]	GETUPVAL 	1 1	; self
	16	[484]	GETTABLE 	1 1 -6	; 1
	17	[484]	SETTABLE 	1 -7 -8	; "invert" false
	18	[486]	GETUPVAL 	1 3	; UIManager
	19	[486]	SELF     	1 1 -9	; "setDirty"
	20	[486]	GETUPVAL 	3 1	; self
	21	[486]	GETTABLE 	3 3 -10	; "show_parent"
	22	[488]	CLOSURE  	4 1	; 0x7ffad5d090b0
	23	[488]	GETUPVAL 	0 1	; self
	24	[486]	CALL     	1 4 1
	25	[489]	RETURN   	0 1

function <./frontend/ui/widget/menu.lua:480,482> (8 instructions, 32 bytes at 0x7ffad5d09030)
0 params, 4 slots, 2 upvalues, 0 locals, 3 constants, 0 functions
	1	[481]	GETUPVAL 	0 0	; self
	2	[481]	GETTABLE 	0 0 -1	; "menu"
	3	[481]	SELF     	0 0 -2	; "onMenuSelect"
	4	[481]	GETUPVAL 	2 0	; self
	5	[481]	GETTABLE 	2 2 -3	; "table"
	6	[481]	GETUPVAL 	3 1	; pos
	7	[481]	CALL     	0 4 1
	8	[482]	RETURN   	0 1

function <./frontend/ui/widget/menu.lua:486,488> (6 instructions, 24 bytes at 0x7ffad5d090b0)
0 params, 2 slots, 1 upvalue, 0 locals, 3 constants, 0 functions
	1	[487]	LOADK    	0 -1	; "ui"
	2	[487]	GETUPVAL 	1 0	; self
	3	[487]	GETTABLE 	1 1 -2	; 1
	4	[487]	GETTABLE 	1 1 -3	; "dimen"
	5	[487]	RETURN   	0 3
	6	[488]	RETURN   	0 1

function <./frontend/ui/widget/menu.lua:494,514> (43 instructions, 172 bytes at 0x7ffad5d09570)
3 params, 9 slots, 1 upvalue, 4 locals, 16 constants, 2 functions
	1	[495]	SELF     	3 0 -1	; "getGesPosition"
	2	[495]	MOVE     	5 2
	3	[495]	CALL     	3 3 2
	4	[496]	GETGLOBAL	4 -2	; G_reader_settings
	5	[496]	SELF     	4 4 -3	; "isFalse"
	6	[496]	LOADK    	6 -4	; "flash_ui"
	7	[496]	CALL     	4 3 2
	8	[496]	TEST     	4 0 0
	9	[496]	JMP      	6	; to 16
	10	[497]	GETTABLE 	4 0 -5	; "menu"
	11	[497]	SELF     	4 4 -6	; "onMenuHold"
	12	[497]	GETTABLE 	6 0 -7	; "table"
	13	[497]	MOVE     	7 3
	14	[497]	CALL     	4 4 1
	15	[497]	JMP      	25	; to 41
	16	[499]	GETTABLE 	4 0 -8	; 1
	17	[499]	SETTABLE 	4 -9 -10	; "invert" true
	18	[500]	GETUPVAL 	4 0	; UIManager
	19	[500]	SELF     	4 4 -11	; "widgetRepaint"
	20	[500]	GETTABLE 	6 0 -8	; 1
	21	[500]	GETTABLE 	7 0 -8	; 1
	22	[500]	GETTABLE 	7 7 -12	; "dimen"
	23	[500]	GETTABLE 	7 7 -13	; "x"
	24	[500]	GETTABLE 	8 0 -8	; 1
	25	[500]	GETTABLE 	8 8 -12	; "dimen"
	26	[500]	GETTABLE 	8 8 -14	; "y"
	27	[500]	CALL     	4 5 1
	28	[501]	GETUPVAL 	4 0	; UIManager
	29	[501]	SELF     	4 4 -15	; "setDirty"
	30	[501]	LOADNIL  	6 6
	31	[503]	CLOSURE  	7 0	; 0x7ffad5d09ba0
	32	[503]	MOVE     	0 0
	33	[501]	CALL     	4 4 1
	34	[504]	GETUPVAL 	4 0	; UIManager
	35	[504]	SELF     	4 4 -16	; "tickAfterNext"
	36	[511]	CLOSURE  	6 1	; 0x7ffad5d09b20
	37	[511]	MOVE     	0 0
	38	[511]	MOVE     	0 3
	39	[511]	GETUPVAL 	0 0	; UIManager
	40	[504]	CALL     	4 3 1
	41	[513]	LOADBOOL 	4 1 0
	42	[513]	RETURN   	4 2
	43	[514]	RETURN   	0 1

function <./frontend/ui/widget/menu.lua:501,503> (6 instructions, 24 bytes at 0x7ffad5d09ba0)
0 params, 2 slots, 1 upvalue, 0 locals, 3 constants, 0 functions
	1	[502]	LOADK    	0 -1	; "fast"
	2	[502]	GETUPVAL 	1 0	; self
	3	[502]	GETTABLE 	1 1 -2	; 1
	4	[502]	GETTABLE 	1 1 -3	; "dimen"
	5	[502]	RETURN   	0 3
	6	[503]	RETURN   	0 1

function <./frontend/ui/widget/menu.lua:504,511> (18 instructions, 72 bytes at 0x7ffad5d09b20)
0 params, 4 slots, 3 upvalues, 0 locals, 8 constants, 1 function
	1	[505]	GETUPVAL 	0 0	; self
	2	[505]	GETTABLE 	0 0 -1	; "menu"
	3	[505]	SELF     	0 0 -2	; "onMenuHold"
	4	[505]	GETUPVAL 	2 0	; self
	5	[505]	GETTABLE 	2 2 -3	; "table"
	6	[505]	GETUPVAL 	3 1	; pos
	7	[505]	CALL     	0 4 1
	8	[506]	GETUPVAL 	0 0	; self
	9	[506]	GETTABLE 	0 0 -4	; 1
	10	[506]	SETTABLE 	0 -5 -6	; "invert" false
	11	[508]	GETUPVAL 	0 2	; UIManager
	12	[508]	SELF     	0 0 -7	; "setDirty"
	13	[508]	GETUPVAL 	2 0	; self
	14	[508]	GETTABLE 	2 2 -8	; "show_parent"
	15	[510]	CLOSURE  	3 0	; 0x7ffad5d0a0e0
	16	[510]	GETUPVAL 	0 0	; self
	17	[508]	CALL     	0 4 1
	18	[511]	RETURN   	0 1

function <./frontend/ui/widget/menu.lua:508,510> (6 instructions, 24 bytes at 0x7ffad5d0a0e0)
0 params, 2 slots, 1 upvalue, 0 locals, 3 constants, 0 functions
	1	[509]	LOADK    	0 -1	; "ui"
	2	[509]	GETUPVAL 	1 0	; self
	3	[509]	GETTABLE 	1 1 -2	; 1
	4	[509]	GETTABLE 	1 1 -3	; "dimen"
	5	[509]	RETURN   	0 3
	6	[510]	RETURN   	0 1

function <./frontend/ui/widget/menu.lua:570,598> (132 instructions, 528 bytes at 0x7ffad5d091b0)
1 param, 8 slots, 3 upvalues, 4 locals, 37 constants, 0 functions
	1	[571]	GETTABLE 	1 0 -2	; "perpage_custom"
	2	[571]	TEST     	1 0 1
	3	[571]	JMP      	7	; to 11
	4	[571]	GETGLOBAL	1 -3	; G_reader_settings
	5	[571]	SELF     	1 1 -4	; "readSetting"
	6	[571]	LOADK    	3 -5	; "items_per_page"
	7	[571]	CALL     	1 3 2
	8	[571]	TEST     	1 0 1
	9	[571]	JMP      	1	; to 11
	10	[571]	LOADK    	1 -6	; 14
	11	[571]	SETTABLE 	0 -1 1	; "perpage" -
	12	[572]	SETTABLE 	0 -7 -8	; "span_width" 0
	13	[573]	GETTABLE 	1 0 -9	; "dimen"
	14	[573]	GETTABLE 	2 0 -11	; "width"
	15	[573]	SETTABLE 	1 -10 2	; "w" -
	16	[574]	GETTABLE 	1 0 -9	; "dimen"
	17	[574]	GETTABLE 	2 0 -13	; "height"
	18	[574]	TEST     	2 0 1
	19	[574]	JMP      	3	; to 23
	20	[574]	GETUPVAL 	2 0	; Screen
	21	[574]	SELF     	2 2 -14	; "getHeight"
	22	[574]	CALL     	2 2 2
	23	[574]	SETTABLE 	1 -12 2	; "h" -
	24	[575]	GETTABLE 	1 0 -9	; "dimen"
	25	[575]	GETTABLE 	1 1 -12	; "h"
	26	[575]	GETUPVAL 	2 0	; Screen
	27	[575]	SELF     	2 2 -14	; "getHeight"
	28	[575]	CALL     	2 2 2
	29	[575]	LT       	1 2 1
	30	[575]	JMP      	4	; to 35
	31	[575]	GETTABLE 	1 0 -9	; "dimen"
	32	[575]	GETTABLE 	1 1 -12	; "h"
	33	[575]	EQ       	0 1 -15	; - nil
	34	[575]	JMP      	5	; to 40
	35	[576]	GETTABLE 	1 0 -9	; "dimen"
	36	[576]	GETUPVAL 	2 0	; Screen
	37	[576]	SELF     	2 2 -14	; "getHeight"
	38	[576]	CALL     	2 2 2
	39	[576]	SETTABLE 	1 -12 2	; "h" -
	40	[578]	GETUPVAL 	1 1	; Geom
	41	[578]	SELF     	1 1 -17	; "new"
	42	[578]	NEWTABLE 	3 0 2
	43	[579]	GETTABLE 	4 0 -9	; "dimen"
	44	[579]	GETTABLE 	4 4 -10	; "w"
	45	[579]	SETTABLE 	3 -10 4	; "w" -
	46	[580]	GETUPVAL 	4 0	; Screen
	47	[580]	SELF     	4 4 -18	; "scaleBySize"
	48	[580]	LOADK    	6 -19	; 46
	49	[580]	CALL     	4 3 2
	50	[580]	SETTABLE 	3 -12 4	; "h" -
	51	[578]	CALL     	1 3 2
	52	[581]	SETTABLE 	0 -16 1	; "item_dimen" -
	53	[582]	LOADNIL  	1 1
	54	[583]	LOADK    	2 -8	; 0
	55	[584]	LOADK    	3 -8	; 0
	56	[585]	GETTABLE 	4 0 -20	; "page_return_arrow"
	57	[585]	TEST     	4 0 0
	58	[585]	JMP      	19	; to 78
	59	[585]	GETTABLE 	4 0 -21	; "page_info_text"
	60	[585]	TEST     	4 0 0
	61	[585]	JMP      	16	; to 78
	62	[586]	GETGLOBAL	4 -22	; math
	63	[586]	GETTABLE 	4 4 -23	; "max"
	64	[586]	GETTABLE 	5 0 -20	; "page_return_arrow"
	65	[586]	SELF     	5 5 -24	; "getSize"
	66	[586]	CALL     	5 2 2
	67	[586]	GETTABLE 	5 5 -12	; "h"
	68	[586]	GETTABLE 	6 0 -21	; "page_info_text"
	69	[586]	SELF     	6 6 -24	; "getSize"
	70	[586]	CALL     	6 2 2
	71	[586]	GETTABLE 	6 6 -12	; "h"
	72	[586]	CALL     	4 3 2
	73	[587]	GETUPVAL 	5 2	; Size
	74	[587]	GETTABLE 	5 5 -25	; "padding"
	75	[587]	GETTABLE 	5 5 -26	; "button"
	76	[587]	MUL      	5 -27 5	; 2 -
	77	[587]	ADD      	2 4 5
	78	[589]	GETTABLE 	4 0 -28	; "menu_title"
	79	[589]	TEST     	4 0 0
	80	[589]	JMP      	12	; to 93
	81	[589]	GETTABLE 	4 0 -29	; "no_title"
	82	[589]	TEST     	4 0 1
	83	[589]	JMP      	9	; to 93
	84	[590]	GETTABLE 	4 0 -30	; "menu_title_group"
	85	[590]	SELF     	4 4 -24	; "getSize"
	86	[590]	CALL     	4 2 2
	87	[590]	GETTABLE 	4 4 -12	; "h"
	88	[590]	GETUPVAL 	5 2	; Size
	89	[590]	GETTABLE 	5 5 -25	; "padding"
	90	[590]	GETTABLE 	5 5 -31	; "small"
	91	[590]	MUL      	5 -27 5	; 2 -
	92	[590]	ADD      	3 4 5
	93	[592]	GETTABLE 	4 0 -9	; "dimen"
	94	[592]	GETTABLE 	4 4 -12	; "h"
	95	[592]	SUB      	4 4 2
	96	[592]	SUB      	1 4 3
	97	[593]	GETTABLE 	4 0 -16	; "item_dimen"
	98	[593]	GETGLOBAL	5 -22	; math
	99	[593]	GETTABLE 	5 5 -32	; "floor"
	100	[593]	GETTABLE 	6 0 -1	; "perpage"
	101	[593]	DIV      	6 1 6
	102	[593]	CALL     	5 2 2
	103	[593]	SETTABLE 	4 -12 5	; "h" -
	104	[594]	GETGLOBAL	4 -22	; math
	105	[594]	GETTABLE 	4 4 -32	; "floor"
	106	[594]	GETTABLE 	5 0 -1	; "perpage"
	107	[594]	GETTABLE 	6 0 -16	; "item_dimen"
	108	[594]	GETTABLE 	6 6 -12	; "h"
	109	[594]	MUL      	5 5 6
	110	[594]	SUB      	5 1 5
	111	[594]	DIV      	5 5 -27	; - 2
	112	[594]	SUB      	5 5 -33	; - 1
	113	[594]	CALL     	4 2 2
	114	[594]	SETTABLE 	0 -7 4	; "span_width" -
	115	[595]	GETGLOBAL	4 -22	; math
	116	[595]	GETTABLE 	4 4 -35	; "ceil"
	117	[595]	GETTABLE 	5 0 -36	; "item_table"
	118	[595]	LEN      	5 5
	119	[595]	GETTABLE 	6 0 -1	; "perpage"
	120	[595]	DIV      	5 5 6
	121	[595]	CALL     	4 2 2
	122	[595]	SETTABLE 	0 -34 4	; "page_num" -
	123	[597]	GETTABLE 	4 0 -34	; "page_num"
	124	[597]	LT       	0 -8 4	; 0 -
	125	[597]	JMP      	6	; to 132
	126	[597]	GETTABLE 	4 0 -37	; "page"
	127	[597]	GETTABLE 	5 0 -34	; "page_num"
	128	[597]	LT       	0 5 4
	129	[597]	JMP      	2	; to 132
	130	[597]	GETTABLE 	4 0 -34	; "page_num"
	131	[597]	SETTABLE 	0 -37 4	; "page" -
	132	[598]	RETURN   	0 1

function <./frontend/ui/widget/menu.lua:600,928> (646 instructions, 2584 bytes at 0x7ffad5d087b0)
1 param, 26 slots, 23 upvalues, 16 locals, 148 constants, 10 functions
	1	[601]	GETTABLE 	1 0 -1	; "show_parent"
	2	[601]	TEST     	1 0 1
	3	[601]	JMP      	1	; to 5
	4	[601]	MOVE     	1 0
	5	[601]	SETTABLE 	0 -1 1	; "show_parent" -
	6	[602]	NEWTABLE 	1 0 0
	7	[602]	SETTABLE 	0 -2 1	; "item_table_stack" -
	8	[603]	GETTABLE 	1 0 -3	; "dimen"
	9	[603]	GETTABLE 	2 0 -5	; "width"
	10	[603]	SETTABLE 	1 -4 2	; "w" -
	11	[604]	GETTABLE 	1 0 -3	; "dimen"
	12	[604]	GETTABLE 	2 0 -7	; "height"
	13	[604]	TEST     	2 0 1
	14	[604]	JMP      	3	; to 18
	15	[604]	GETUPVAL 	2 0	; Screen
	16	[604]	SELF     	2 2 -8	; "getHeight"
	17	[604]	CALL     	2 2 2
	18	[604]	SETTABLE 	1 -6 2	; "h" -
	19	[605]	GETTABLE 	1 0 -3	; "dimen"
	20	[605]	GETTABLE 	1 1 -6	; "h"
	21	[605]	GETUPVAL 	2 0	; Screen
	22	[605]	SELF     	2 2 -8	; "getHeight"
	23	[605]	CALL     	2 2 2
	24	[605]	LT       	1 2 1
	25	[605]	JMP      	4	; to 30
	26	[605]	GETTABLE 	1 0 -3	; "dimen"
	27	[605]	GETTABLE 	1 1 -6	; "h"
	28	[605]	EQ       	0 1 -9	; - nil
	29	[605]	JMP      	5	; to 35
	30	[606]	GETTABLE 	1 0 -3	; "dimen"
	31	[606]	GETUPVAL 	2 0	; Screen
	32	[606]	SELF     	2 2 -8	; "getHeight"
	33	[606]	CALL     	2 2 2
	34	[606]	SETTABLE 	1 -6 2	; "h" -
	35	[608]	SETTABLE 	0 -10 -11	; "page" 1
	36	[613]	GETUPVAL 	1 1	; TextWidget
	37	[613]	SELF     	1 1 -13	; "new"
	38	[613]	NEWTABLE 	3 0 3
	39	[614]	SETTABLE 	3 -14 -15	; "overlap_align" "center"
	40	[615]	GETTABLE 	4 0 -17	; "title"
	41	[615]	SETTABLE 	3 -16 4	; "text" -
	42	[616]	GETTABLE 	4 0 -19	; "tface"
	43	[616]	SETTABLE 	3 -18 4	; "face" -
	44	[613]	CALL     	1 3 2
	45	[617]	SETTABLE 	0 -12 1	; "menu_title" -
	46	[618]	GETUPVAL 	1 2	; CenterContainer
	47	[618]	SELF     	1 1 -13	; "new"
	48	[618]	NEWTABLE 	3 1 1
	49	[619]	GETUPVAL 	4 3	; Geom
	50	[619]	SELF     	4 4 -13	; "new"
	51	[619]	NEWTABLE 	6 0 2
	52	[620]	GETTABLE 	7 0 -3	; "dimen"
	53	[620]	GETTABLE 	7 7 -4	; "w"
	54	[620]	SETTABLE 	6 -4 7	; "w" -
	55	[621]	GETTABLE 	7 0 -12	; "menu_title"
	56	[621]	SELF     	7 7 -20	; "getSize"
	57	[621]	CALL     	7 2 2
	58	[621]	GETTABLE 	7 7 -6	; "h"
	59	[621]	SETTABLE 	6 -6 7	; "h" -
	60	[619]	CALL     	4 3 2
	61	[622]	SETTABLE 	3 -3 4	; "dimen" -
	62	[624]	GETTABLE 	4 0 -12	; "menu_title"
	63	[624]	SETLIST  	3 1 1	; 1
	64	[618]	CALL     	1 3 2
	65	[625]	LOADNIL  	2 2
	66	[627]	GETTABLE 	3 0 -21	; "show_path"
	67	[627]	TEST     	3 0 0
	68	[627]	JMP      	54	; to 123
	69	[628]	GETUPVAL 	3 1	; TextWidget
	70	[628]	SELF     	3 3 -13	; "new"
	71	[628]	NEWTABLE 	5 0 4
	72	[629]	GETUPVAL 	6 4	; Font
	73	[629]	SELF     	6 6 -23	; "getFace"
	74	[629]	LOADK    	8 -24	; "xx_smallinfofont"
	75	[629]	CALL     	6 3 2
	76	[629]	SETTABLE 	5 -18 6	; "face" -
	77	[630]	GETUPVAL 	6 5	; BD
	78	[630]	GETTABLE 	6 6 -25	; "directory"
	79	[630]	GETTABLE 	7 0 -26	; "path"
	80	[630]	CALL     	6 2 2
	81	[630]	SETTABLE 	5 -16 6	; "text" -
	82	[631]	GETTABLE 	6 0 -3	; "dimen"
	83	[631]	GETTABLE 	6 6 -4	; "w"
	84	[631]	GETUPVAL 	7 6	; Size
	85	[631]	GETTABLE 	7 7 -28	; "padding"
	86	[631]	GETTABLE 	7 7 -29	; "small"
	87	[631]	MUL      	7 -30 7	; 2 -
	88	[631]	SUB      	6 6 7
	89	[631]	SETTABLE 	5 -27 6	; "max_width" -
	90	[632]	SETTABLE 	5 -31 -32	; "truncate_left" true
	91	[628]	CALL     	3 3 2
	92	[633]	SETTABLE 	0 -22 3	; "path_text" -
	93	[634]	GETUPVAL 	3 2	; CenterContainer
	94	[634]	SELF     	3 3 -13	; "new"
	95	[634]	NEWTABLE 	5 1 1
	96	[635]	GETUPVAL 	6 3	; Geom
	97	[635]	SELF     	6 6 -13	; "new"
	98	[635]	NEWTABLE 	8 0 2
	99	[636]	GETTABLE 	9 0 -3	; "dimen"
	100	[636]	GETTABLE 	9 9 -4	; "w"
	101	[636]	SETTABLE 	8 -4 9	; "w" -
	102	[637]	GETTABLE 	9 0 -22	; "path_text"
	103	[637]	SELF     	9 9 -20	; "getSize"
	104	[637]	CALL     	9 2 2
	105	[637]	GETTABLE 	9 9 -6	; "h"
	106	[637]	SETTABLE 	8 -6 9	; "h" -
	107	[635]	CALL     	6 3 2
	108	[638]	SETTABLE 	5 -3 6	; "dimen" -
	109	[640]	GETTABLE 	6 0 -22	; "path_text"
	110	[640]	SETLIST  	5 1 1	; 1
	111	[634]	CALL     	3 3 2
	112	[640]	MOVE     	2 3
	113	[641]	GETUPVAL 	3 7	; VerticalGroup
	114	[641]	SELF     	3 3 -13	; "new"
	115	[641]	NEWTABLE 	5 2 1
	116	[642]	SETTABLE 	5 -34 -15	; "align" "center"
	117	[643]	MOVE     	6 1
	118	[645]	MOVE     	7 2
	119	[645]	SETLIST  	5 2 1	; 1
	120	[641]	CALL     	3 3 2
	121	[645]	SETTABLE 	0 -33 3	; "menu_title_group" -
	122	[645]	JMP      	8	; to 131
	123	[647]	GETUPVAL 	3 7	; VerticalGroup
	124	[647]	SELF     	3 3 -13	; "new"
	125	[647]	NEWTABLE 	5 1 1
	126	[648]	SETTABLE 	5 -34 -15	; "align" "center"
	127	[650]	MOVE     	6 1
	128	[650]	SETLIST  	5 1 1	; 1
	129	[647]	CALL     	3 3 2
	130	[650]	SETTABLE 	0 -33 3	; "menu_title_group" -
	131	[653]	GETUPVAL 	3 8	; OverlapGroup
	132	[653]	SELF     	3 3 -13	; "new"
	133	[653]	NEWTABLE 	5 1 1
	134	[654]	NEWTABLE 	6 0 2
	135	[654]	GETTABLE 	7 0 -3	; "dimen"
	136	[654]	GETTABLE 	7 7 -4	; "w"
	137	[654]	SETTABLE 	6 -4 7	; "w" -
	138	[654]	GETTABLE 	7 0 -33	; "menu_title_group"
	139	[654]	SELF     	7 7 -20	; "getSize"
	140	[654]	CALL     	7 2 2
	141	[654]	GETTABLE 	7 7 -6	; "h"
	142	[654]	SETTABLE 	6 -6 7	; "h" -
	143	[654]	SETTABLE 	5 -3 6	; "dimen" -
	144	[656]	GETTABLE 	6 0 -33	; "menu_title_group"
	145	[656]	SETLIST  	5 1 1	; 1
	146	[653]	CALL     	3 3 2
	147	[656]	SETTABLE 	0 -35 3	; "title_bar" -
	148	[658]	GETUPVAL 	3 7	; VerticalGroup
	149	[658]	SELF     	3 3 -13	; "new"
	150	[658]	NEWTABLE 	5 0 0
	151	[658]	CALL     	3 3 2
	152	[658]	SETTABLE 	0 -36 3	; "item_group" -
	153	[660]	LOADK    	3 -37	; "resources/icons/appbar.chevron.left.png"
	154	[661]	LOADK    	4 -38	; "resources/icons/appbar.chevron.right.png"
	155	[662]	LOADK    	5 -39	; "resources/icons/appbar.chevron.first.png"
	156	[663]	LOADK    	6 -40	; "resources/icons/appbar.chevron.last.png"
	157	[664]	GETUPVAL 	7 5	; BD
	158	[664]	GETTABLE 	7 7 -41	; "mirroredUILayout"
	159	[664]	CALL     	7 1 2
	160	[664]	TEST     	7 0 0
	161	[664]	JMP      	6	; to 168
	162	[665]	MOVE     	7 4
	163	[665]	MOVE     	4 3
	164	[665]	MOVE     	3 7
	165	[666]	MOVE     	7 6
	166	[666]	MOVE     	6 5
	167	[666]	MOVE     	5 7
	168	[668]	GETUPVAL 	7 9	; Button
	169	[668]	SELF     	7 7 -13	; "new"
	170	[668]	NEWTABLE 	9 0 4
	171	[669]	SETTABLE 	9 -43 3	; "icon" -
	172	[670]	CLOSURE  	10 0	; 0x7ffad5d07740
	173	[670]	MOVE     	0 0
	174	[670]	SETTABLE 	9 -44 10	; "callback" -
	175	[671]	SETTABLE 	9 -45 -46	; "bordersize" 0
	176	[672]	GETTABLE 	10 0 -1	; "show_parent"
	177	[672]	SETTABLE 	9 -1 10	; "show_parent" -
	178	[668]	CALL     	7 3 2
	179	[673]	SETTABLE 	0 -42 7	; "page_info_left_chev" -
	180	[674]	GETUPVAL 	7 9	; Button
	181	[674]	SELF     	7 7 -13	; "new"
	182	[674]	NEWTABLE 	9 0 4
	183	[675]	SETTABLE 	9 -43 4	; "icon" -
	184	[676]	CLOSURE  	10 1	; 0x7ffad5d07fa0
	185	[676]	MOVE     	0 0
	186	[676]	SETTABLE 	9 -44 10	; "callback" -
	187	[677]	SETTABLE 	9 -45 -46	; "bordersize" 0
	188	[678]	GETTABLE 	10 0 -1	; "show_parent"
	189	[678]	SETTABLE 	9 -1 10	; "show_parent" -
	190	[674]	CALL     	7 3 2
	191	[679]	SETTABLE 	0 -47 7	; "page_info_right_chev" -
	192	[680]	GETUPVAL 	7 9	; Button
	193	[680]	SELF     	7 7 -13	; "new"
	194	[680]	NEWTABLE 	9 0 4
	195	[681]	SETTABLE 	9 -43 5	; "icon" -
	196	[682]	CLOSURE  	10 2	; 0x7ffad5d080f0
	197	[682]	MOVE     	0 0
	198	[682]	SETTABLE 	9 -44 10	; "callback" -
	199	[683]	SETTABLE 	9 -45 -46	; "bordersize" 0
	200	[684]	GETTABLE 	10 0 -1	; "show_parent"
	201	[684]	SETTABLE 	9 -1 10	; "show_parent" -
	202	[680]	CALL     	7 3 2
	203	[685]	SETTABLE 	0 -48 7	; "page_info_first_chev" -
	204	[686]	GETUPVAL 	7 9	; Button
	205	[686]	SELF     	7 7 -13	; "new"
	206	[686]	NEWTABLE 	9 0 4
	207	[687]	SETTABLE 	9 -43 6	; "icon" -
	208	[688]	CLOSURE  	10 3	; 0x7ffad5d0a5a0
	209	[688]	MOVE     	0 0
	210	[688]	SETTABLE 	9 -44 10	; "callback" -
	211	[689]	SETTABLE 	9 -45 -46	; "bordersize" 0
	212	[690]	GETTABLE 	10 0 -1	; "show_parent"
	213	[690]	SETTABLE 	9 -1 10	; "show_parent" -
	214	[686]	CALL     	7 3 2
	215	[691]	SETTABLE 	0 -49 7	; "page_info_last_chev" -
	216	[692]	GETUPVAL 	7 10	; HorizontalSpan
	217	[692]	SELF     	7 7 -13	; "new"
	218	[692]	NEWTABLE 	9 0 1
	219	[693]	GETUPVAL 	10 0	; Screen
	220	[693]	SELF     	10 10 -51	; "scaleBySize"
	221	[693]	LOADK    	12 -52	; 32
	222	[693]	CALL     	10 3 2
	223	[693]	SETTABLE 	9 -5 10	; "width" -
	224	[692]	CALL     	7 3 2
	225	[694]	SETTABLE 	0 -50 7	; "page_info_spacer" -
	226	[695]	GETTABLE 	7 0 -42	; "page_info_left_chev"
	227	[695]	SELF     	7 7 -53	; "hide"
	228	[695]	CALL     	7 2 1
	229	[696]	GETTABLE 	7 0 -47	; "page_info_right_chev"
	230	[696]	SELF     	7 7 -53	; "hide"
	231	[696]	CALL     	7 2 1
	232	[697]	GETTABLE 	7 0 -48	; "page_info_first_chev"
	233	[697]	SELF     	7 7 -53	; "hide"
	234	[697]	CALL     	7 2 1
	235	[698]	GETTABLE 	7 0 -49	; "page_info_last_chev"
	236	[698]	SELF     	7 7 -53	; "hide"
	237	[698]	CALL     	7 2 1
	238	[700]	LOADNIL  	7 9
	239	[701]	NEWTABLE 	10 1 0
	240	[701]	NEWTABLE 	11 2 0
	241	[702]	NEWTABLE 	12 0 2
	242	[704]	GETUPVAL 	13 11	; _
	243	[704]	LOADK    	14 -54	; "Cancel"
	244	[704]	CALL     	13 2 2
	245	[704]	SETTABLE 	12 -16 13	; "text" -
	246	[707]	CLOSURE  	13 4	; 0x7ffad5d08e50
	247	[707]	MOVE     	0 0
	248	[707]	SETTABLE 	12 -44 13	; "callback" -
	249	[708]	NEWTABLE 	13 0 3
	250	[710]	GETUPVAL 	14 11	; _
	251	[710]	LOADK    	15 -55	; "Go to page"
	252	[710]	CALL     	14 2 2
	253	[710]	SETTABLE 	13 -16 14	; "text" -
	254	[711]	SETTABLE 	13 -56 -32	; "is_enter_default" true
	255	[718]	CLOSURE  	14 5	; 0x7ffad5d0b080
	256	[718]	MOVE     	0 0
	257	[718]	SETTABLE 	13 -44 14	; "callback" -
	258	[720]	SETLIST  	11 2 1	; 1
	259	[721]	SETLIST  	10 1 1	; 1
	260	[723]	GETTABLE 	11 0 -57	; "goto_letter"
	261	[723]	TEST     	11 0 0
	262	[723]	JMP      	22	; to 285
	263	[724]	GETUPVAL 	11 11	; _
	264	[724]	LOADK    	12 -58	; "Enter page number or letter"
	265	[724]	CALL     	11 2 2
	266	[724]	MOVE     	7 11
	267	[725]	LOADK    	8 -59	; "string"
	268	[728]	CLOSURE  	9 6	; 0x7ffad5d0b750
	269	[728]	MOVE     	0 0
	270	[729]	GETGLOBAL	11 -60	; table
	271	[729]	GETTABLE 	11 11 -61	; "insert"
	272	[729]	GETTABLE 	12 10 -11	; 1
	273	[729]	NEWTABLE 	13 0 3
	274	[730]	GETUPVAL 	14 11	; _
	275	[730]	LOADK    	15 -62	; "Go to letter"
	276	[730]	CALL     	14 2 2
	277	[730]	SETTABLE 	13 -16 14	; "text" -
	278	[731]	SETTABLE 	13 -56 -32	; "is_enter_default" true
	279	[744]	CLOSURE  	14 7	; 0x7ffad5d0b860
	280	[744]	MOVE     	0 0
	281	[744]	GETUPVAL 	0 12	; util
	282	[744]	SETTABLE 	13 -44 14	; "callback" -
	283	[729]	CALL     	11 3 1
	284	[745]	JMP      	7	; to 292
	285	[747]	GETUPVAL 	11 11	; _
	286	[747]	LOADK    	12 -63	; "Enter page number"
	287	[747]	CALL     	11 2 2
	288	[747]	MOVE     	7 11
	289	[748]	LOADK    	8 -64	; "number"
	290	[751]	CLOSURE  	9 8	; 0x7ffad5d0beb0
	291	[751]	MOVE     	0 0
	292	[754]	GETUPVAL 	11 9	; Button
	293	[754]	SELF     	11 11 -13	; "new"
	294	[754]	NEWTABLE 	13 0 6
	295	[755]	SETTABLE 	13 -16 -66	; "text" ""
	296	[756]	NEWTABLE 	14 0 4
	297	[757]	SETTABLE 	14 -17 7	; "title" -
	298	[758]	SETTABLE 	14 -68 8	; "type" -
	299	[759]	SETTABLE 	14 -69 9	; "hint_func" -
	300	[760]	SETTABLE 	14 -70 10	; "buttons" -
	301	[761]	SETTABLE 	13 -67 14	; "hold_input" -
	302	[762]	SETTABLE 	13 -45 -46	; "bordersize" 0
	303	[763]	SETTABLE 	13 -71 -72	; "text_font_face" "cfont"
	304	[764]	SETTABLE 	13 -73 -74	; "text_font_size" 20
	305	[765]	SETTABLE 	13 -75 -76	; "text_font_bold" false
	306	[754]	CALL     	11 3 2
	307	[766]	SETTABLE 	0 -65 11	; "page_info_text" -
	308	[767]	GETUPVAL 	11 13	; HorizontalGroup
	309	[767]	SELF     	11 11 -13	; "new"
	310	[767]	NEWTABLE 	13 7 0
	311	[768]	GETTABLE 	14 0 -48	; "page_info_first_chev"
	312	[769]	GETTABLE 	15 0 -50	; "page_info_spacer"
	313	[770]	GETTABLE 	16 0 -42	; "page_info_left_chev"
	314	[771]	GETTABLE 	17 0 -65	; "page_info_text"
	315	[772]	GETTABLE 	18 0 -47	; "page_info_right_chev"
	316	[773]	GETTABLE 	19 0 -50	; "page_info_spacer"
	317	[775]	GETTABLE 	20 0 -49	; "page_info_last_chev"
	318	[775]	SETLIST  	13 7 1	; 1
	319	[767]	CALL     	11 3 2
	320	[775]	SETTABLE 	0 -77 11	; "page_info" -
	321	[778]	GETUPVAL 	11 9	; Button
	322	[778]	SELF     	11 11 -13	; "new"
	323	[778]	NEWTABLE 	13 0 5
	324	[779]	SETTABLE 	13 -43 -79	; "icon" "resources/icons/appbar.arrow.left.up.png"
	325	[782]	CLOSURE  	14 9	; 0x7ffad5d0c590
	326	[782]	MOVE     	0 0
	327	[782]	SETTABLE 	13 -44 14	; "callback" -
	328	[783]	SETTABLE 	13 -45 -46	; "bordersize" 0
	329	[784]	GETTABLE 	14 0 -1	; "show_parent"
	330	[784]	SETTABLE 	13 -1 14	; "show_parent" -
	331	[785]	GETTABLE 	14 0 -81	; "return_arrow_propagation"
	332	[785]	SETTABLE 	13 -80 14	; "readonly" -
	333	[778]	CALL     	11 3 2
	334	[786]	SETTABLE 	0 -78 11	; "page_return_arrow" -
	335	[787]	GETTABLE 	11 0 -78	; "page_return_arrow"
	336	[787]	SELF     	11 11 -53	; "hide"
	337	[787]	CALL     	11 2 1
	338	[788]	GETUPVAL 	11 13	; HorizontalGroup
	339	[788]	SELF     	11 11 -13	; "new"
	340	[788]	NEWTABLE 	13 2 0
	341	[789]	GETUPVAL 	14 10	; HorizontalSpan
	342	[789]	SELF     	14 14 -13	; "new"
	343	[789]	NEWTABLE 	16 0 1
	344	[790]	GETUPVAL 	17 6	; Size
	345	[790]	GETTABLE 	17 17 -83	; "span"
	346	[790]	GETTABLE 	17 17 -84	; "horizontal_small"
	347	[790]	SETTABLE 	16 -5 17	; "width" -
	348	[789]	CALL     	14 3 2
	349	[793]	GETTABLE 	15 0 -78	; "page_return_arrow"
	350	[793]	SETLIST  	13 2 1	; 1
	351	[788]	CALL     	11 3 2
	352	[793]	SETTABLE 	0 -82 11	; "return_button" -
	353	[795]	GETUPVAL 	11 7	; VerticalGroup
	354	[795]	SELF     	11 11 -13	; "new"
	355	[795]	NEWTABLE 	13 2 0
	356	[796]	GETUPVAL 	14 14	; VerticalSpan
	357	[796]	SELF     	14 14 -13	; "new"
	358	[796]	NEWTABLE 	16 0 1
	359	[796]	GETTABLE 	17 0 -85	; "header_padding"
	360	[796]	SETTABLE 	16 -5 17	; "width" -
	361	[796]	CALL     	14 3 2
	362	[798]	GETTABLE 	15 0 -35	; "title_bar"
	363	[798]	SETLIST  	13 2 1	; 1
	364	[795]	CALL     	11 3 2
	365	[799]	GETTABLE 	12 0 -36	; "item_group"
	366	[800]	GETUPVAL 	13 15	; BottomContainer
	367	[800]	SELF     	13 13 -13	; "new"
	368	[800]	NEWTABLE 	15 1 1
	369	[801]	GETTABLE 	16 0 -3	; "dimen"
	370	[801]	SELF     	16 16 -86	; "copy"
	371	[801]	CALL     	16 2 2
	372	[801]	SETTABLE 	15 -3 16	; "dimen" -
	373	[803]	GETTABLE 	16 0 -77	; "page_info"
	374	[803]	SETLIST  	15 1 1	; 1
	375	[800]	CALL     	13 3 2
	376	[804]	GETUPVAL 	14 15	; BottomContainer
	377	[804]	SELF     	14 14 -13	; "new"
	378	[804]	NEWTABLE 	16 0 1
	379	[805]	GETTABLE 	17 0 -3	; "dimen"
	380	[805]	SELF     	17 17 -86	; "copy"
	381	[805]	CALL     	17 2 2
	382	[805]	SETTABLE 	16 -3 17	; "dimen" -
	383	[806]	GETUPVAL 	17 16	; WidgetContainer
	384	[806]	SELF     	17 17 -13	; "new"
	385	[806]	NEWTABLE 	19 1 1
	386	[807]	GETUPVAL 	20 3	; Geom
	387	[807]	SELF     	20 20 -13	; "new"
	388	[807]	NEWTABLE 	22 0 2
	389	[808]	GETUPVAL 	23 0	; Screen
	390	[808]	SELF     	23 23 -87	; "getWidth"
	391	[808]	CALL     	23 2 2
	392	[808]	SETTABLE 	22 -4 23	; "w" -
	393	[809]	GETTABLE 	23 0 -78	; "page_return_arrow"
	394	[809]	SELF     	23 23 -20	; "getSize"
	395	[809]	CALL     	23 2 2
	396	[809]	GETTABLE 	23 23 -6	; "h"
	397	[809]	SETTABLE 	22 -6 23	; "h" -
	398	[807]	CALL     	20 3 2
	399	[810]	SETTABLE 	19 -3 20	; "dimen" -
	400	[812]	GETTABLE 	20 0 -82	; "return_button"
	401	[812]	SETLIST  	19 1 1	; 1
	402	[806]	CALL     	17 3 0
	403	[813]	SETLIST  	16 0 1	; 1
	404	[804]	CALL     	14 3 2
	405	[815]	SELF     	15 0 -88	; "_recalculateDimen"
	406	[815]	CALL     	15 2 1
	407	[816]	GETUPVAL 	15 13	; HorizontalGroup
	408	[816]	SELF     	15 15 -13	; "new"
	409	[816]	NEWTABLE 	17 0 0
	410	[817]	GETUPVAL 	18 14	; VerticalSpan
	411	[817]	SELF     	18 18 -13	; "new"
	412	[817]	NEWTABLE 	20 0 1
	413	[817]	GETTABLE 	21 0 -90	; "span_width"
	414	[817]	SETTABLE 	20 -5 21	; "width" -
	415	[817]	CALL     	18 3 0
	416	[818]	SETLIST  	17 0 1	; 1
	417	[816]	CALL     	15 3 2
	418	[818]	SETTABLE 	0 -89 15	; "vertical_span" -
	419	[819]	GETTABLE 	15 0 -91	; "no_title"
	420	[819]	TEST     	15 0 0
	421	[819]	JMP      	10	; to 432
	422	[820]	GETUPVAL 	15 7	; VerticalGroup
	423	[820]	SELF     	15 15 -13	; "new"
	424	[820]	NEWTABLE 	17 2 1
	425	[821]	SETTABLE 	17 -34 -93	; "align" "left"
	426	[822]	GETTABLE 	18 0 -89	; "vertical_span"
	427	[824]	MOVE     	19 12
	428	[824]	SETLIST  	17 2 1	; 1
	429	[820]	CALL     	15 3 2
	430	[824]	SETTABLE 	0 -92 15	; "content_group" -
	431	[824]	JMP      	10	; to 442
	432	[826]	GETUPVAL 	15 7	; VerticalGroup
	433	[826]	SELF     	15 15 -13	; "new"
	434	[826]	NEWTABLE 	17 3 1
	435	[827]	SETTABLE 	17 -34 -93	; "align" "left"
	436	[828]	MOVE     	18 11
	437	[829]	GETTABLE 	19 0 -89	; "vertical_span"
	438	[831]	MOVE     	20 12
	439	[831]	SETLIST  	17 3 1	; 1
	440	[826]	CALL     	15 3 2
	441	[831]	SETTABLE 	0 -92 15	; "content_group" -
	442	[833]	GETUPVAL 	15 8	; OverlapGroup
	443	[833]	SELF     	15 15 -13	; "new"
	444	[833]	NEWTABLE 	17 3 2
	445	[837]	SETTABLE 	17 -94 -76	; "allow_mirroring" false
	446	[838]	GETTABLE 	18 0 -3	; "dimen"
	447	[838]	SELF     	18 18 -86	; "copy"
	448	[838]	CALL     	18 2 2
	449	[838]	SETTABLE 	17 -3 18	; "dimen" -
	450	[839]	GETTABLE 	18 0 -92	; "content_group"
	451	[840]	MOVE     	19 14
	452	[842]	MOVE     	20 13
	453	[842]	SETLIST  	17 3 1	; 1
	454	[833]	CALL     	15 3 2
	455	[844]	GETUPVAL 	16 17	; FrameContainer
	456	[844]	SELF     	16 16 -13	; "new"
	457	[844]	NEWTABLE 	18 1 5
	458	[845]	GETUPVAL 	19 18	; Blitbuffer
	459	[845]	GETTABLE 	19 19 -96	; "COLOR_WHITE"
	460	[845]	SETTABLE 	18 -95 19	; "background" -
	461	[846]	GETTABLE 	19 0 -97	; "is_borderless"
	462	[846]	TEST     	19 0 0
	463	[846]	JMP      	3	; to 467
	464	[846]	LOADK    	19 -46	; 0
	465	[846]	TEST     	19 0 1
	466	[846]	JMP      	1	; to 468
	467	[846]	LOADK    	19 -30	; 2
	468	[846]	SETTABLE 	18 -45 19	; "bordersize" -
	469	[847]	SETTABLE 	18 -28 -46	; "padding" 0
	470	[848]	SETTABLE 	18 -98 -46	; "margin" 0
	471	[849]	GETTABLE 	19 0 -100	; "is_popout"
	472	[849]	TEST     	19 0 0
	473	[849]	JMP      	8	; to 482
	474	[849]	GETGLOBAL	19 -101	; math
	475	[849]	GETTABLE 	19 19 -102	; "floor"
	476	[849]	GETTABLE 	20 0 -3	; "dimen"
	477	[849]	GETTABLE 	20 20 -4	; "w"
	478	[849]	DIV      	20 20 -74	; - 20
	479	[849]	CALL     	19 2 2
	480	[849]	TEST     	19 0 1
	481	[849]	JMP      	1	; to 483
	482	[849]	LOADK    	19 -46	; 0
	483	[849]	SETTABLE 	18 -99 19	; "radius" -
	484	[851]	MOVE     	19 15
	485	[851]	SETLIST  	18 1 1	; 1
	486	[844]	CALL     	16 3 2
	487	[851]	SETTABLE 	0 -11 16	; 1 -
	488	[855]	GETUPVAL 	16 19	; Device
	489	[855]	SELF     	16 16 -103	; "isTouchDevice"
	490	[855]	CALL     	16 2 2
	491	[855]	TEST     	16 0 0
	492	[855]	JMP      	58	; to 551
	493	[856]	GETTABLE 	16 0 -104	; "has_close_button"
	494	[856]	TEST     	16 0 0
	495	[856]	JMP      	11	; to 507
	496	[857]	GETGLOBAL	16 -60	; table
	497	[857]	GETTABLE 	16 16 -61	; "insert"
	498	[857]	GETTABLE 	17 0 -35	; "title_bar"
	499	[857]	GETUPVAL 	18 20	; MenuCloseButton
	500	[857]	SELF     	18 18 -13	; "new"
	501	[857]	NEWTABLE 	20 0 2
	502	[858]	SETTABLE 	20 -105 0	; "menu" -
	503	[859]	GETTABLE 	21 0 -85	; "header_padding"
	504	[859]	SETTABLE 	20 -106 21	; "padding_right" -
	505	[857]	CALL     	18 3 0
	506	[857]	CALL     	16 0 1
	507	[863]	GETTABLE 	16 0 -100	; "is_popout"
	508	[863]	TEST     	16 0 0
	509	[863]	JMP      	24	; to 534
	510	[864]	GETTABLE 	16 0 -107	; "ges_events"
	511	[864]	NEWTABLE 	17 0 0
	512	[865]	GETUPVAL 	18 21	; GestureRange
	513	[865]	SELF     	18 18 -13	; "new"
	514	[865]	NEWTABLE 	20 0 2
	515	[866]	SETTABLE 	20 -109 -110	; "ges" "tap"
	516	[867]	GETUPVAL 	21 3	; Geom
	517	[867]	SELF     	21 21 -13	; "new"
	518	[867]	NEWTABLE 	23 0 4
	519	[868]	SETTABLE 	23 -112 -46	; "x" 0
	520	[868]	SETTABLE 	23 -113 -46	; "y" 0
	521	[869]	GETUPVAL 	24 0	; Screen
	522	[869]	SELF     	24 24 -87	; "getWidth"
	523	[869]	CALL     	24 2 2
	524	[869]	SETTABLE 	23 -4 24	; "w" -
	525	[870]	GETUPVAL 	24 0	; Screen
	526	[870]	SELF     	24 24 -8	; "getHeight"
	527	[870]	CALL     	24 2 2
	528	[870]	SETTABLE 	23 -6 24	; "h" -
	529	[867]	CALL     	21 3 2
	530	[871]	SETTABLE 	20 -111 21	; "range" -
	531	[865]	CALL     	18 3 0
	532	[873]	SETLIST  	17 0 1	; 1
	533	[873]	SETTABLE 	16 -108 17	; "TapCloseAllMenus" -
	534	[876]	GETTABLE 	16 0 -114	; "is_file_manager"
	535	[876]	EQ       	1 16 -32	; - true
	536	[876]	JMP      	11	; to 548
	537	[877]	GETTABLE 	16 0 -107	; "ges_events"
	538	[877]	NEWTABLE 	17 0 0
	539	[878]	GETUPVAL 	18 21	; GestureRange
	540	[878]	SELF     	18 18 -13	; "new"
	541	[878]	NEWTABLE 	20 0 2
	542	[879]	SETTABLE 	20 -109 -116	; "ges" "swipe"
	543	[880]	GETTABLE 	21 0 -3	; "dimen"
	544	[880]	SETTABLE 	20 -111 21	; "range" -
	545	[878]	CALL     	18 3 0
	546	[882]	SETLIST  	17 0 1	; 1
	547	[882]	SETTABLE 	16 -115 17	; "Swipe" -
	548	[884]	GETTABLE 	16 0 -107	; "ges_events"
	549	[884]	GETTABLE 	17 0 -118	; "on_close_ges"
	550	[884]	SETTABLE 	16 -117 17	; "Close" -
	551	[887]	GETUPVAL 	16 19	; Device
	552	[887]	SELF     	16 16 -119	; "hasKeyboard"
	553	[887]	CALL     	16 2 2
	554	[887]	TEST     	16 0 1
	555	[887]	JMP      	1	; to 557
	556	[889]	SETTABLE 	0 -120 -76	; "is_enable_shortcut" false
	557	[892]	GETUPVAL 	16 19	; Device
	558	[892]	SELF     	16 16 -121	; "hasKeys"
	559	[892]	CALL     	16 2 2
	560	[892]	TEST     	16 0 0
	561	[892]	JMP      	28	; to 590
	562	[894]	GETTABLE 	16 0 -122	; "key_events"
	563	[894]	NEWTABLE 	17 1 1
	564	[894]	NEWTABLE 	18 1 0
	565	[894]	LOADK    	19 -123	; "Back"
	566	[894]	SETLIST  	18 1 1	; 1
	567	[894]	SETTABLE 	17 -124 -125	; "doc" "close menu"
	568	[894]	SETLIST  	17 1 1	; 1
	569	[894]	SETTABLE 	16 -117 17	; "Close" -
	570	[895]	GETTABLE 	16 0 -122	; "key_events"
	571	[895]	NEWTABLE 	17 1 1
	572	[895]	NEWTABLE 	18 1 0
	573	[896]	GETUPVAL 	19 22	; Input
	574	[896]	GETTABLE 	19 19 -127	; "group"
	575	[896]	GETTABLE 	19 19 -128	; "PgFwd"
	576	[896]	SETLIST  	18 1 1	; 1
	577	[896]	SETTABLE 	17 -124 -129	; "doc" "goto next page of the menu"
	578	[897]	SETLIST  	17 1 1	; 1
	579	[897]	SETTABLE 	16 -126 17	; "NextPage" -
	580	[898]	GETTABLE 	16 0 -122	; "key_events"
	581	[898]	NEWTABLE 	17 1 1
	582	[898]	NEWTABLE 	18 1 0
	583	[899]	GETUPVAL 	19 22	; Input
	584	[899]	GETTABLE 	19 19 -127	; "group"
	585	[899]	GETTABLE 	19 19 -131	; "PgBack"
	586	[899]	SETLIST  	18 1 1	; 1
	587	[899]	SETTABLE 	17 -124 -132	; "doc" "goto previous page of the menu"
	588	[900]	SETLIST  	17 1 1	; 1
	589	[900]	SETTABLE 	16 -130 17	; "PrevPage" -
	590	[903]	GETUPVAL 	16 19	; Device
	591	[903]	SELF     	16 16 -133	; "hasDPad"
	592	[903]	CALL     	16 2 2
	593	[903]	TEST     	16 0 0
	594	[903]	JMP      	28	; to 623
	595	[905]	GETTABLE 	16 0 -122	; "key_events"
	596	[905]	SETTABLE 	16 -134 -9	; "FocusRight" nil
	597	[907]	GETTABLE 	16 0 -120	; "is_enable_shortcut"
	598	[907]	TEST     	16 0 0
	599	[907]	JMP      	7	; to 607
	600	[908]	GETTABLE 	16 0 -122	; "key_events"
	601	[908]	NEWTABLE 	17 1 0
	602	[908]	NEWTABLE 	18 1 0
	603	[908]	GETTABLE 	19 0 -136	; "item_shortcuts"
	604	[908]	SETLIST  	18 1 1	; 1
	605	[908]	SETLIST  	17 1 1	; 1
	606	[908]	SETTABLE 	16 -135 17	; "SelectByShortCut" -
	607	[910]	GETTABLE 	16 0 -122	; "key_events"
	608	[910]	NEWTABLE 	17 1 1
	609	[910]	NEWTABLE 	18 1 0
	610	[911]	LOADK    	19 -138	; "Press"
	611	[911]	SETLIST  	18 1 1	; 1
	612	[911]	SETTABLE 	17 -124 -139	; "doc" "select current menu item"
	613	[912]	SETLIST  	17 1 1	; 1
	614	[912]	SETTABLE 	16 -137 17	; "Select" -
	615	[913]	GETTABLE 	16 0 -122	; "key_events"
	616	[913]	NEWTABLE 	17 1 1
	617	[913]	NEWTABLE 	18 1 0
	618	[914]	LOADK    	19 -140	; "Right"
	619	[914]	SETLIST  	18 1 1	; 1
	620	[914]	SETTABLE 	17 -124 -141	; "doc" "hold  menu item"
	621	[915]	SETLIST  	17 1 1	; 1
	622	[915]	SETTABLE 	16 -140 17	; "Right" -
	623	[918]	GETTABLE 	16 0 -142	; "item_table"
	624	[918]	LEN      	16 16
	625	[918]	LT       	0 -46 16	; 0 -
	626	[918]	JMP      	11	; to 638
	627	[921]	GETGLOBAL	16 -101	; math
	628	[921]	GETTABLE 	16 16 -143	; "ceil"
	629	[921]	GETTABLE 	17 0 -142	; "item_table"
	630	[921]	GETTABLE 	17 17 -144	; "current"
	631	[921]	TEST     	17 0 1
	632	[921]	JMP      	1	; to 634
	633	[921]	LOADK    	17 -11	; 1
	634	[921]	GETTABLE 	18 0 -145	; "perpage"
	635	[921]	DIV      	17 17 18
	636	[921]	CALL     	16 2 2
	637	[921]	SETTABLE 	0 -10 16	; "page" -
	638	[923]	GETTABLE 	16 0 -146	; "path_items"
	639	[923]	TEST     	16 0 0
	640	[923]	JMP      	3	; to 644
	641	[924]	SELF     	16 0 -147	; "refreshPath"
	642	[924]	CALL     	16 2 1
	643	[924]	JMP      	2	; to 646
	644	[926]	SELF     	16 0 -148	; "updateItems"
	645	[926]	CALL     	16 2 1
	646	[928]	RETURN   	0 1

function <./frontend/ui/widget/menu.lua:670,670> (4 instructions, 16 bytes at 0x7ffad5d07740)
0 params, 2 slots, 1 upvalue, 0 locals, 1 constant, 0 functions
	1	[670]	GETUPVAL 	0 0	; self
	2	[670]	SELF     	0 0 -1	; "onPrevPage"
	3	[670]	CALL     	0 2 1
	4	[670]	RETURN   	0 1

function <./frontend/ui/widget/menu.lua:676,676> (4 instructions, 16 bytes at 0x7ffad5d07fa0)
0 params, 2 slots, 1 upvalue, 0 locals, 1 constant, 0 functions
	1	[676]	GETUPVAL 	0 0	; self
	2	[676]	SELF     	0 0 -1	; "onNextPage"
	3	[676]	CALL     	0 2 1
	4	[676]	RETURN   	0 1

function <./frontend/ui/widget/menu.lua:682,682> (4 instructions, 16 bytes at 0x7ffad5d080f0)
0 params, 2 slots, 1 upvalue, 0 locals, 1 constant, 0 functions
	1	[682]	GETUPVAL 	0 0	; self
	2	[682]	SELF     	0 0 -1	; "onFirstPage"
	3	[682]	CALL     	0 2 1
	4	[682]	RETURN   	0 1

function <./frontend/ui/widget/menu.lua:688,688> (4 instructions, 16 bytes at 0x7ffad5d0a5a0)
0 params, 2 slots, 1 upvalue, 0 locals, 1 constant, 0 functions
	1	[688]	GETUPVAL 	0 0	; self
	2	[688]	SELF     	0 0 -1	; "onLastPage"
	3	[688]	CALL     	0 2 1
	4	[688]	RETURN   	0 1

function <./frontend/ui/widget/menu.lua:705,707> (5 instructions, 20 bytes at 0x7ffad5d08e50)
0 params, 2 slots, 1 upvalue, 0 locals, 2 constants, 0 functions
	1	[706]	GETUPVAL 	0 0	; self
	2	[706]	GETTABLE 	0 0 -1	; "page_info_text"
	3	[706]	SELF     	0 0 -2	; "closeInputDialog"
	4	[706]	CALL     	0 2 1
	5	[707]	RETURN   	0 1

function <./frontend/ui/widget/menu.lua:712,718> (24 instructions, 96 bytes at 0x7ffad5d0b080)
0 params, 4 slots, 1 upvalue, 1 local, 8 constants, 0 functions
	1	[713]	GETGLOBAL	0 -1	; tonumber
	2	[713]	GETUPVAL 	1 0	; self
	3	[713]	GETTABLE 	1 1 -2	; "page_info_text"
	4	[713]	GETTABLE 	1 1 -3	; "input_dialog"
	5	[713]	SELF     	1 1 -4	; "getInputText"
	6	[713]	CALL     	1 2 0
	7	[713]	CALL     	0 0 2
	8	[714]	TEST     	0 0 0
	9	[714]	JMP      	10	; to 20
	10	[714]	LE       	0 -5 0	; 1 -
	11	[714]	JMP      	8	; to 20
	12	[714]	GETUPVAL 	1 0	; self
	13	[714]	GETTABLE 	1 1 -6	; "page_num"
	14	[714]	LE       	0 0 1
	15	[714]	JMP      	4	; to 20
	16	[715]	GETUPVAL 	1 0	; self
	17	[715]	SELF     	1 1 -7	; "onGotoPage"
	18	[715]	MOVE     	3 0
	19	[715]	CALL     	1 3 1
	20	[717]	GETUPVAL 	1 0	; self
	21	[717]	GETTABLE 	1 1 -2	; "page_info_text"
	22	[717]	SELF     	1 1 -8	; "closeInputDialog"
	23	[717]	CALL     	1 2 1
	24	[718]	RETURN   	0 1

function <./frontend/ui/widget/menu.lua:726,728> (8 instructions, 32 bytes at 0x7ffad5d0b750)
0 params, 3 slots, 1 upvalue, 0 locals, 4 constants, 0 functions
	1	[727]	GETGLOBAL	0 -1	; string
	2	[727]	GETTABLE 	0 0 -2	; "format"
	3	[727]	LOADK    	1 -3	; "(1 - %s) or (a - z)"
	4	[727]	GETUPVAL 	2 0	; self
	5	[727]	GETTABLE 	2 2 -4	; "page_num"
	6	[727]	TAILCALL 	0 3 0
	7	[727]	RETURN   	0 0
	8	[728]	RETURN   	0 1

function <./frontend/ui/widget/menu.lua:732,744> (43 instructions, 172 bytes at 0x7ffad5d0b860)
0 params, 13 slots, 2 upvalues, 9 locals, 16 constants, 0 functions
	1	[733]	GETGLOBAL	0 -1	; ipairs
	2	[733]	GETUPVAL 	1 0	; self
	3	[733]	GETTABLE 	1 1 -2	; "item_table"
	4	[733]	CALL     	0 2 4
	5	[733]	JMP      	31	; to 37
	6	[735]	GETUPVAL 	5 1	; util
	7	[735]	GETTABLE 	5 5 -3	; "basename"
	8	[735]	GETTABLE 	6 4 -4	; "path"
	9	[735]	CALL     	5 2 2
	10	[735]	SELF     	5 5 -5	; "lower"
	11	[735]	CALL     	5 2 2
	12	[736]	GETUPVAL 	6 0	; self
	13	[736]	GETTABLE 	6 6 -6	; "page_info_text"
	14	[736]	GETTABLE 	6 6 -7	; "input_dialog"
	15	[736]	SELF     	6 6 -8	; "getInputText"
	16	[736]	CALL     	6 2 2
	17	[736]	SELF     	6 6 -5	; "lower"
	18	[736]	CALL     	6 2 2
	19	[737]	SELF     	7 5 -9	; "find"
	20	[737]	MOVE     	9 6
	21	[737]	CALL     	7 3 3
	22	[738]	EQ       	0 7 -10	; - 1
	23	[738]	JMP      	13	; to 37
	24	[738]	GETTABLE 	9 4 -11	; "is_go_up"
	25	[738]	TEST     	9 0 1
	26	[738]	JMP      	10	; to 37
	27	[739]	GETUPVAL 	9 0	; self
	28	[739]	SELF     	9 9 -12	; "onGotoPage"
	29	[739]	GETGLOBAL	11 -13	; math
	30	[739]	GETTABLE 	11 11 -14	; "ceil"
	31	[739]	GETUPVAL 	12 0	; self
	32	[739]	GETTABLE 	12 12 -15	; "perpage"
	33	[739]	DIV      	12 3 12
	34	[739]	CALL     	11 2 0
	35	[739]	CALL     	9 0 1
	36	[740]	JMP      	2	; to 39
	37	[733]	TFORLOOP 	0 2
	38	[741]	JMP      	-33	; to 6
	39	[743]	GETUPVAL 	0 0	; self
	40	[743]	GETTABLE 	0 0 -6	; "page_info_text"
	41	[743]	SELF     	0 0 -16	; "closeInputDialog"
	42	[743]	CALL     	0 2 1
	43	[744]	RETURN   	0 1

function <./frontend/ui/widget/menu.lua:749,751> (8 instructions, 32 bytes at 0x7ffad5d0beb0)
0 params, 3 slots, 1 upvalue, 0 locals, 4 constants, 0 functions
	1	[750]	GETGLOBAL	0 -1	; string
	2	[750]	GETTABLE 	0 0 -2	; "format"
	3	[750]	LOADK    	1 -3	; "(1 - %s)"
	4	[750]	GETUPVAL 	2 0	; self
	5	[750]	GETTABLE 	2 2 -4	; "page_num"
	6	[750]	TAILCALL 	0 3 0
	7	[750]	RETURN   	0 0
	8	[751]	RETURN   	0 1

function <./frontend/ui/widget/menu.lua:780,782> (8 instructions, 32 bytes at 0x7ffad5d0c590)
0 params, 2 slots, 1 upvalue, 0 locals, 1 constant, 0 functions
	1	[781]	GETUPVAL 	0 0	; self
	2	[781]	GETTABLE 	0 0 -1	; "onReturn"
	3	[781]	TEST     	0 0 0
	4	[781]	JMP      	3	; to 8
	5	[781]	GETUPVAL 	0 0	; self
	6	[781]	SELF     	0 0 -1	; "onReturn"
	7	[781]	CALL     	0 2 1
	8	[782]	RETURN   	0 1

function <./frontend/ui/widget/menu.lua:930,941> (6 instructions, 24 bytes at 0x7ffad5d09e50)
1 param, 5 slots, 1 upvalue, 1 local, 2 constants, 0 functions
	1	[940]	GETUPVAL 	1 0	; UIManager
	2	[940]	SELF     	1 1 -1	; "setDirty"
	3	[940]	LOADNIL  	3 3
	4	[940]	LOADK    	4 -2	; "partial"
	5	[940]	CALL     	1 4 1
	6	[941]	RETURN   	0 1

function <./frontend/ui/widget/menu.lua:943,969> (123 instructions, 492 bytes at 0x7ffad5d0d0f0)
2 params, 8 slots, 3 upvalues, 2 locals, 26 constants, 0 functions
	1	[944]	GETTABLE 	2 0 -1	; "item_group"
	2	[944]	GETTABLE 	2 2 -2	; 1
	3	[944]	TEST     	2 0 0
	4	[944]	JMP      	112	; to 117
	5	[945]	GETUPVAL 	2 0	; Device
	6	[945]	SELF     	2 2 -3	; "hasDPad"
	7	[945]	CALL     	2 2 2
	8	[945]	TEST     	2 0 0
	9	[945]	JMP      	4	; to 14
	10	[947]	NEWTABLE 	2 0 2
	11	[947]	SETTABLE 	2 -5 -2	; "x" 1
	12	[947]	SETTABLE 	2 -6 1	; "y" -
	13	[947]	SETTABLE 	0 -4 2	; "selected" -
	14	[950]	GETTABLE 	2 0 -7	; "page_num"
	15	[950]	LT       	0 -2 2	; 1 -
	16	[950]	JMP      	12	; to 29
	17	[951]	GETTABLE 	2 0 -8	; "page_info_text"
	18	[951]	SELF     	2 2 -9	; "setText"
	19	[951]	GETUPVAL 	4 1	; util
	20	[951]	GETTABLE 	4 4 -10	; "template"
	21	[951]	GETUPVAL 	5 2	; _
	22	[951]	LOADK    	6 -11	; "Page %1 of %2"
	23	[951]	CALL     	5 2 2
	24	[951]	GETTABLE 	6 0 -12	; "page"
	25	[951]	GETTABLE 	7 0 -7	; "page_num"
	26	[951]	CALL     	4 4 0
	27	[951]	CALL     	2 0 1
	28	[951]	JMP      	4	; to 33
	29	[953]	GETTABLE 	2 0 -8	; "page_info_text"
	30	[953]	SELF     	2 2 -9	; "setText"
	31	[953]	LOADK    	4 -13	; ""
	32	[953]	CALL     	2 3 1
	33	[955]	GETTABLE 	2 0 -14	; "page_info_left_chev"
	34	[955]	SELF     	2 2 -15	; "showHide"
	35	[955]	GETTABLE 	4 0 -7	; "page_num"
	36	[955]	LT       	1 -2 4	; 1 -
	37	[955]	JMP      	1	; to 39
	38	[955]	LOADBOOL 	4 0 1
	39	[955]	LOADBOOL 	4 1 0
	40	[955]	CALL     	2 3 1
	41	[956]	GETTABLE 	2 0 -16	; "page_info_right_chev"
	42	[956]	SELF     	2 2 -15	; "showHide"
	43	[956]	GETTABLE 	4 0 -7	; "page_num"
	44	[956]	LT       	1 -2 4	; 1 -
	45	[956]	JMP      	1	; to 47
	46	[956]	LOADBOOL 	4 0 1
	47	[956]	LOADBOOL 	4 1 0
	48	[956]	CALL     	2 3 1
	49	[957]	GETTABLE 	2 0 -17	; "page_info_first_chev"
	50	[957]	SELF     	2 2 -15	; "showHide"
	51	[957]	GETTABLE 	4 0 -7	; "page_num"
	52	[957]	LT       	1 -18 4	; 2 -
	53	[957]	JMP      	1	; to 55
	54	[957]	LOADBOOL 	4 0 1
	55	[957]	LOADBOOL 	4 1 0
	56	[957]	CALL     	2 3 1
	57	[958]	GETTABLE 	2 0 -19	; "page_info_last_chev"
	58	[958]	SELF     	2 2 -15	; "showHide"
	59	[958]	GETTABLE 	4 0 -7	; "page_num"
	60	[958]	LT       	1 -18 4	; 2 -
	61	[958]	JMP      	1	; to 63
	62	[958]	LOADBOOL 	4 0 1
	63	[958]	LOADBOOL 	4 1 0
	64	[958]	CALL     	2 3 1
	65	[959]	GETTABLE 	2 0 -20	; "page_return_arrow"
	66	[959]	SELF     	2 2 -15	; "showHide"
	67	[959]	GETTABLE 	4 0 -21	; "onReturn"
	68	[959]	EQ       	0 4 -22	; - nil
	69	[959]	JMP      	1	; to 71
	70	[959]	LOADBOOL 	4 0 1
	71	[959]	LOADBOOL 	4 1 0
	72	[959]	CALL     	2 3 1
	73	[961]	GETTABLE 	2 0 -14	; "page_info_left_chev"
	74	[961]	SELF     	2 2 -23	; "enableDisable"
	75	[961]	GETTABLE 	4 0 -12	; "page"
	76	[961]	LT       	1 -2 4	; 1 -
	77	[961]	JMP      	1	; to 79
	78	[961]	LOADBOOL 	4 0 1
	79	[961]	LOADBOOL 	4 1 0
	80	[961]	CALL     	2 3 1
	81	[962]	GETTABLE 	2 0 -16	; "page_info_right_chev"
	82	[962]	SELF     	2 2 -23	; "enableDisable"
	83	[962]	GETTABLE 	4 0 -12	; "page"
	84	[962]	GETTABLE 	5 0 -7	; "page_num"
	85	[962]	LT       	1 4 5
	86	[962]	JMP      	1	; to 88
	87	[962]	LOADBOOL 	4 0 1
	88	[962]	LOADBOOL 	4 1 0
	89	[962]	CALL     	2 3 1
	90	[963]	GETTABLE 	2 0 -17	; "page_info_first_chev"
	91	[963]	SELF     	2 2 -23	; "enableDisable"
	92	[963]	GETTABLE 	4 0 -12	; "page"
	93	[963]	LT       	1 -2 4	; 1 -
	94	[963]	JMP      	1	; to 96
	95	[963]	LOADBOOL 	4 0 1
	96	[963]	LOADBOOL 	4 1 0
	97	[963]	CALL     	2 3 1
	98	[964]	GETTABLE 	2 0 -19	; "page_info_last_chev"
	99	[964]	SELF     	2 2 -23	; "enableDisable"
	100	[964]	GETTABLE 	4 0 -12	; "page"
	101	[964]	GETTABLE 	5 0 -7	; "page_num"
	102	[964]	LT       	1 4 5
	103	[964]	JMP      	1	; to 105
	104	[964]	LOADBOOL 	4 0 1
	105	[964]	LOADBOOL 	4 1 0
	106	[964]	CALL     	2 3 1
	107	[965]	GETTABLE 	2 0 -20	; "page_return_arrow"
	108	[965]	SELF     	2 2 -23	; "enableDisable"
	109	[965]	GETTABLE 	4 0 -24	; "paths"
	110	[965]	LEN      	4 4
	111	[965]	LT       	1 -25 4	; 0 -
	112	[965]	JMP      	1	; to 114
	113	[965]	LOADBOOL 	4 0 1
	114	[965]	LOADBOOL 	4 1 0
	115	[965]	CALL     	2 3 1
	116	[965]	JMP      	6	; to 123
	117	[967]	GETTABLE 	2 0 -8	; "page_info_text"
	118	[967]	SELF     	2 2 -9	; "setText"
	119	[967]	GETUPVAL 	4 2	; _
	120	[967]	LOADK    	5 -26	; "No choices available"
	121	[967]	CALL     	4 2 0
	122	[967]	CALL     	2 0 1
	123	[969]	RETURN   	0 1

function <./frontend/ui/widget/menu.lua:971,1046> (180 instructions, 720 bytes at 0x7ffad5d0d720)
2 params, 17 slots, 4 upvalues, 13 locals, 66 constants, 1 function
	1	[972]	GETTABLE 	2 0 -1	; "dimen"
	2	[972]	TEST     	2 0 0
	3	[972]	JMP      	3	; to 7
	4	[972]	GETTABLE 	2 0 -1	; "dimen"
	5	[972]	SELF     	2 2 -2	; "copy"
	6	[972]	CALL     	2 2 2
	7	[974]	NEWTABLE 	3 0 0
	8	[974]	SETTABLE 	0 -3 3	; "layout" -
	9	[975]	GETTABLE 	3 0 -4	; "item_group"
	10	[975]	SELF     	3 3 -5	; "clear"
	11	[975]	CALL     	3 2 1
	12	[976]	GETTABLE 	3 0 -6	; "page_info"
	13	[976]	SELF     	3 3 -7	; "resetLayout"
	14	[976]	CALL     	3 2 1
	15	[977]	GETTABLE 	3 0 -8	; "return_button"
	16	[977]	SELF     	3 3 -7	; "resetLayout"
	17	[977]	CALL     	3 2 1
	18	[978]	GETTABLE 	3 0 -9	; "vertical_span"
	19	[978]	SELF     	3 3 -5	; "clear"
	20	[978]	CALL     	3 2 1
	21	[979]	GETTABLE 	3 0 -10	; "content_group"
	22	[979]	SELF     	3 3 -7	; "resetLayout"
	23	[979]	CALL     	3 2 1
	24	[980]	SELF     	3 0 -11	; "_recalculateDimen"
	25	[980]	CALL     	3 2 1
	26	[983]	TEST     	1 0 1
	27	[983]	JMP      	1	; to 29
	28	[984]	LOADK    	1 -12	; 1
	29	[987]	GETGLOBAL	3 -13	; math
	30	[987]	GETTABLE 	3 3 -14	; "floor"
	31	[987]	GETTABLE 	4 0 -15	; "perpage"
	32	[987]	SUB      	4 4 -16	; - 6
	33	[987]	DIV      	4 4 -17	; - 3
	34	[987]	SUB      	4 -18 4	; 18 -
	35	[987]	CALL     	3 2 2
	36	[989]	GETGLOBAL	4 -19	; G_reader_settings
	37	[989]	SELF     	4 4 -20	; "readSetting"
	38	[989]	LOADK    	6 -21	; "items_font_size"
	39	[989]	CALL     	4 3 2
	40	[989]	TEST     	4 0 1
	41	[989]	JMP      	8	; to 50
	42	[989]	GETGLOBAL	4 -13	; math
	43	[989]	GETTABLE 	4 4 -14	; "floor"
	44	[989]	GETTABLE 	5 0 -15	; "perpage"
	45	[989]	SUB      	5 5 -16	; - 6
	46	[989]	DIV      	5 5 -18	; - 18
	47	[989]	MUL      	5 5 -22	; - 10
	48	[989]	SUB      	5 -23 5	; 24 -
	49	[989]	CALL     	4 2 2
	50	[991]	LOADK    	5 -12	; 1
	51	[991]	GETGLOBAL	6 -13	; math
	52	[991]	GETTABLE 	6 6 -24	; "min"
	53	[991]	GETTABLE 	7 0 -15	; "perpage"
	54	[991]	GETTABLE 	8 0 -25	; "item_table"
	55	[991]	LEN      	8 8
	56	[991]	CALL     	6 3 2
	57	[991]	LOADK    	7 -12	; 1
	58	[991]	FORPREP  	5 100	; to 159
	59	[993]	GETTABLE 	9 0 -26	; "page"
	60	[993]	SUB      	9 9 -12	; - 1
	61	[993]	GETTABLE 	10 0 -15	; "perpage"
	62	[993]	MUL      	9 9 10
	63	[993]	ADD      	9 9 8
	64	[994]	GETTABLE 	10 0 -25	; "item_table"
	65	[994]	LEN      	10 10
	66	[994]	LE       	0 9 10
	67	[994]	JMP      	91	; to 159
	68	[995]	LOADNIL  	10 10
	69	[996]	LOADK    	11 -27	; "square"
	70	[997]	GETTABLE 	12 0 -28	; "is_enable_shortcut"
	71	[997]	TEST     	12 0 0
	72	[997]	JMP      	7	; to 80
	73	[1000]	LE       	0 -29 8	; 11 -
	74	[1000]	JMP      	3	; to 78
	75	[1000]	LE       	0 8 -30	; - 20
	76	[1000]	JMP      	1	; to 78
	77	[1002]	LOADK    	11 -31	; "grey_square"
	78	[1004]	GETTABLE 	12 0 -32	; "item_shortcuts"
	79	[1004]	GETTABLE 	10 12 8
	80	[1006]	GETUPVAL 	12 0	; MenuItem
	81	[1006]	SELF     	12 12 -33	; "new"
	82	[1006]	NEWTABLE 	14 0 19
	83	[1007]	GETTABLE 	15 0 -34	; "show_parent"
	84	[1007]	SETTABLE 	14 -34 15	; "show_parent" -
	85	[1008]	GETTABLE 	15 0 -25	; "item_table"
	86	[1008]	GETTABLE 	15 15 9
	87	[1008]	GETTABLE 	15 15 -35	; "state"
	88	[1008]	SETTABLE 	14 -35 15	; "state" -
	89	[1009]	GETTABLE 	15 0 -36	; "state_size"
	90	[1009]	TEST     	15 0 1
	91	[1009]	JMP      	1	; to 93
	92	[1009]	NEWTABLE 	15 0 0
	93	[1009]	SETTABLE 	14 -36 15	; "state_size" -
	94	[1010]	GETUPVAL 	15 1	; Menu
	95	[1010]	GETTABLE 	15 15 -38	; "getMenuText"
	96	[1010]	GETTABLE 	16 0 -25	; "item_table"
	97	[1010]	GETTABLE 	16 16 9
	98	[1010]	CALL     	15 2 2
	99	[1010]	SETTABLE 	14 -37 15	; "text" -
	100	[1011]	GETTABLE 	15 0 -25	; "item_table"
	101	[1011]	GETTABLE 	15 15 9
	102	[1011]	GETTABLE 	15 15 -39	; "bidi_wrap_func"
	103	[1011]	SETTABLE 	14 -39 15	; "bidi_wrap_func" -
	104	[1012]	GETTABLE 	15 0 -25	; "item_table"
	105	[1012]	GETTABLE 	15 15 9
	106	[1012]	GETTABLE 	15 15 -40	; "mandatory"
	107	[1012]	SETTABLE 	14 -40 15	; "mandatory" -
	108	[1013]	GETTABLE 	15 0 -25	; "item_table"
	109	[1013]	GETTABLE 	15 15 -42	; "current"
	110	[1013]	EQ       	1 15 9
	111	[1013]	JMP      	6	; to 118
	112	[1013]	GETTABLE 	15 0 -25	; "item_table"
	113	[1013]	GETTABLE 	15 15 9
	114	[1013]	GETTABLE 	15 15 -41	; "bold"
	115	[1013]	EQ       	1 15 -43	; - true
	116	[1013]	JMP      	1	; to 118
	117	[1013]	LOADBOOL 	15 0 1
	118	[1013]	LOADBOOL 	15 1 0
	119	[1013]	SETTABLE 	14 -41 15	; "bold" -
	120	[1014]	GETTABLE 	15 0 -25	; "item_table"
	121	[1014]	GETTABLE 	15 15 9
	122	[1014]	GETTABLE 	15 15 -44	; "dim"
	123	[1014]	SETTABLE 	14 -44 15	; "dim" -
	124	[1015]	SETTABLE 	14 -45 -46	; "font" "smallinfofont"
	125	[1016]	SETTABLE 	14 -47 4	; "font_size" -
	126	[1017]	SETTABLE 	14 -48 -48	; "infont" "infont"
	127	[1018]	SETTABLE 	14 -49 3	; "infont_size" -
	128	[1019]	GETTABLE 	15 0 -50	; "item_dimen"
	129	[1019]	SELF     	15 15 -33	; "new"
	130	[1019]	CALL     	15 2 2
	131	[1019]	SETTABLE 	14 -1 15	; "dimen" -
	132	[1020]	SETTABLE 	14 -51 10	; "shortcut" -
	133	[1021]	SETTABLE 	14 -52 11	; "shortcut_style" -
	134	[1022]	GETTABLE 	15 0 -25	; "item_table"
	135	[1022]	GETTABLE 	15 15 9
	136	[1022]	SETTABLE 	14 -53 15	; "table" -
	137	[1023]	SETTABLE 	14 -54 0	; "menu" -
	138	[1024]	GETTABLE 	15 0 -55	; "linesize"
	139	[1024]	SETTABLE 	14 -55 15	; "linesize" -
	140	[1025]	GETTABLE 	15 0 -56	; "single_line"
	141	[1025]	SETTABLE 	14 -56 15	; "single_line" -
	142	[1026]	GETTABLE 	15 0 -57	; "align_baselines"
	143	[1026]	SETTABLE 	14 -57 15	; "align_baselines" -
	144	[1027]	GETTABLE 	15 0 -58	; "line_color"
	145	[1027]	SETTABLE 	14 -58 15	; "line_color" -
	146	[1006]	CALL     	12 3 2
	147	[1029]	GETGLOBAL	13 -53	; table
	148	[1029]	GETTABLE 	13 13 -59	; "insert"
	149	[1029]	GETTABLE 	14 0 -4	; "item_group"
	150	[1029]	MOVE     	15 12
	151	[1029]	CALL     	13 3 1
	152	[1031]	GETGLOBAL	13 -53	; table
	153	[1031]	GETTABLE 	13 13 -59	; "insert"
	154	[1031]	GETTABLE 	14 0 -3	; "layout"
	155	[1031]	NEWTABLE 	15 1 0
	156	[1031]	MOVE     	16 12
	157	[1031]	SETLIST  	15 1 1	; 1
	158	[1031]	CALL     	13 3 1
	159	[991]	FORLOOP  	5 -101	; to 59
	160	[1035]	SELF     	5 0 -60	; "updatePageInfo"
	161	[1035]	MOVE     	7 1
	162	[1035]	CALL     	5 3 1
	163	[1036]	GETTABLE 	5 0 -61	; "show_path"
	164	[1036]	TEST     	5 0 0
	165	[1036]	JMP      	7	; to 173
	166	[1037]	GETTABLE 	5 0 -62	; "path_text"
	167	[1037]	SELF     	5 5 -63	; "setText"
	168	[1037]	GETUPVAL 	7 2	; BD
	169	[1037]	GETTABLE 	7 7 -64	; "directory"
	170	[1037]	GETTABLE 	8 0 -65	; "path"
	171	[1037]	CALL     	7 2 0
	172	[1037]	CALL     	5 0 1
	173	[1040]	GETUPVAL 	5 3	; UIManager
	174	[1040]	SELF     	5 5 -66	; "setDirty"
	175	[1040]	GETTABLE 	7 0 -34	; "show_parent"
	176	[1045]	CLOSURE  	8 0	; 0x7ffad5d0deb0
	177	[1045]	MOVE     	0 2
	178	[1045]	MOVE     	0 0
	179	[1040]	CALL     	5 4 1
	180	[1046]	RETURN   	0 1

function <./frontend/ui/widget/menu.lua:1040,1045> (16 instructions, 64 bytes at 0x7ffad5d0deb0)
0 params, 3 slots, 2 upvalues, 1 local, 3 constants, 0 functions
	1	[1042]	GETUPVAL 	0 0	; old_dimen
	2	[1042]	TEST     	0 0 0
	3	[1042]	JMP      	7	; to 11
	4	[1042]	GETUPVAL 	0 0	; old_dimen
	5	[1042]	SELF     	0 0 -1	; "combine"
	6	[1042]	GETUPVAL 	2 1	; self
	7	[1042]	GETTABLE 	2 2 -2	; "dimen"
	8	[1042]	CALL     	0 3 2
	9	[1043]	TEST     	0 0 1
	10	[1043]	JMP      	2	; to 13
	11	[1043]	GETUPVAL 	0 1	; self
	12	[1043]	GETTABLE 	0 0 -2	; "dimen"
	13	[1044]	LOADK    	1 -3	; "ui"
	14	[1044]	MOVE     	2 0
	15	[1044]	RETURN   	1 3
	16	[1045]	RETURN   	0 1

function <./frontend/ui/widget/menu.lua:1062,1091> (61 instructions, 244 bytes at 0x7ffad5d0e030)
5 params, 15 slots, 0 upvalues, 13 locals, 16 constants, 0 functions
	1	[1063]	GETTABLE 	5 0 -1	; "menu_title"
	2	[1063]	TEST     	5 0 0
	3	[1063]	JMP      	6	; to 10
	4	[1063]	TEST     	1 0 0
	5	[1063]	JMP      	4	; to 10
	6	[1064]	GETTABLE 	5 0 -1	; "menu_title"
	7	[1064]	SELF     	5 5 -2	; "setText"
	8	[1064]	MOVE     	7 1
	9	[1064]	CALL     	5 3 1
	10	[1067]	EQ       	0 3 -3	; - nil
	11	[1067]	JMP      	2	; to 14
	12	[1068]	SETTABLE 	0 -4 -5	; "page" 1
	13	[1068]	JMP      	8	; to 22
	14	[1069]	LE       	0 -6 3	; 0 -
	15	[1069]	JMP      	6	; to 22
	16	[1070]	GETGLOBAL	5 -7	; math
	17	[1070]	GETTABLE 	5 5 -8	; "ceil"
	18	[1070]	GETTABLE 	6 0 -9	; "perpage"
	19	[1070]	DIV      	6 3 6
	20	[1070]	CALL     	5 2 2
	21	[1070]	SETTABLE 	0 -4 5	; "page" -
	22	[1073]	GETGLOBAL	5 -10	; type
	23	[1073]	MOVE     	6 4
	24	[1073]	CALL     	5 2 2
	25	[1073]	EQ       	0 5 -11	; - "table"
	26	[1073]	JMP      	21	; to 48
	27	[1074]	GETGLOBAL	5 -12	; next
	28	[1074]	MOVE     	6 4
	29	[1074]	CALL     	5 2 3
	30	[1075]	GETGLOBAL	7 -13	; ipairs
	31	[1075]	MOVE     	8 2
	32	[1075]	CALL     	7 2 4
	33	[1075]	JMP      	12	; to 46
	34	[1076]	GETTABLE 	12 11 5
	35	[1076]	EQ       	0 12 6
	36	[1076]	JMP      	9	; to 46
	37	[1077]	GETGLOBAL	12 -7	; math
	38	[1077]	GETTABLE 	12 12 -14	; "floor"
	39	[1077]	SUB      	13 10 -5	; - 1
	40	[1077]	GETTABLE 	14 0 -9	; "perpage"
	41	[1077]	DIV      	13 13 14
	42	[1077]	CALL     	12 2 2
	43	[1077]	ADD      	12 12 -5	; - 1
	44	[1077]	SETTABLE 	0 -4 12	; "page" -
	45	[1078]	JMP      	2	; to 48
	46	[1075]	TFORLOOP 	7 2
	47	[1079]	JMP      	-14	; to 34
	48	[1084]	GETGLOBAL	5 -7	; math
	49	[1084]	GETTABLE 	5 5 -8	; "ceil"
	50	[1084]	LEN      	6 2
	51	[1084]	GETTABLE 	7 0 -9	; "perpage"
	52	[1084]	DIV      	6 6 7
	53	[1084]	CALL     	5 2 2
	54	[1085]	GETTABLE 	6 0 -4	; "page"
	55	[1085]	LT       	0 5 6
	56	[1085]	JMP      	1	; to 58
	57	[1086]	SETTABLE 	0 -4 5	; "page" -
	58	[1089]	SETTABLE 	0 -15 2	; "item_table" -
	59	[1090]	SELF     	6 0 -16	; "updateItems"
	60	[1090]	CALL     	6 2 1
	61	[1091]	RETURN   	0 1

function <./frontend/ui/widget/menu.lua:1093,1097> (5 instructions, 20 bytes at 0x7ffad5d0e160)
2 params, 4 slots, 0 upvalues, 2 locals, 1 constant, 0 functions
	1	[1095]	SELF     	2 0 -1	; "init"
	2	[1095]	CALL     	2 2 1
	3	[1096]	LOADBOOL 	2 0 0
	4	[1096]	RETURN   	2 2
	5	[1097]	RETURN   	0 1

function <./frontend/ui/widget/menu.lua:1099,1111> (36 instructions, 144 bytes at 0x7ffad5d094f0)
3 params, 13 slots, 0 upvalues, 8 locals, 8 constants, 0 functions
	1	[1100]	GETGLOBAL	3 -1	; ipairs
	2	[1100]	GETTABLE 	4 0 -2	; "item_shortcuts"
	3	[1100]	CALL     	3 2 4
	4	[1100]	JMP      	27	; to 32
	5	[1101]	GETTABLE 	8 0 -3	; "perpage"
	6	[1101]	LT       	0 8 6
	7	[1101]	JMP      	2	; to 10
	8	[1102]	JMP      	25	; to 34
	9	[1102]	JMP      	22	; to 32
	10	[1103]	GETTABLE 	8 2 -4	; "key"
	11	[1103]	EQ       	0 7 8
	12	[1103]	JMP      	19	; to 32
	13	[1104]	GETTABLE 	8 0 -5	; "item_table"
	14	[1104]	GETTABLE 	9 0 -6	; "page"
	15	[1104]	SUB      	9 9 -7	; - 1
	16	[1104]	GETTABLE 	10 0 -3	; "perpage"
	17	[1104]	MUL      	9 9 10
	18	[1104]	ADD      	9 9 6
	19	[1104]	GETTABLE 	8 8 9
	20	[1104]	TEST     	8 0 0
	21	[1104]	JMP      	12	; to 34
	22	[1105]	SELF     	8 0 -8	; "onMenuSelect"
	23	[1105]	GETTABLE 	10 0 -5	; "item_table"
	24	[1105]	GETTABLE 	11 0 -6	; "page"
	25	[1105]	SUB      	11 11 -7	; - 1
	26	[1105]	GETTABLE 	12 0 -3	; "perpage"
	27	[1105]	MUL      	11 11 12
	28	[1105]	ADD      	11 11 6
	29	[1105]	GETTABLE 	10 10 11
	30	[1105]	CALL     	8 3 1
	31	[1107]	JMP      	2	; to 34
	32	[1100]	TFORLOOP 	3 2
	33	[1108]	JMP      	-29	; to 5
	34	[1110]	LOADBOOL 	3 1 0
	35	[1110]	RETURN   	3 2
	36	[1111]	RETURN   	0 1

function <./frontend/ui/widget/menu.lua:1113,1118> (15 instructions, 60 bytes at 0x7ffad5d0f140)
1 param, 4 slots, 0 upvalues, 1 local, 3 constants, 0 functions
	1	[1114]	GETTABLE 	1 0 -1	; "page_info_text"
	2	[1114]	TEST     	1 0 0
	3	[1114]	JMP      	9	; to 13
	4	[1114]	GETTABLE 	1 0 -1	; "page_info_text"
	5	[1114]	GETTABLE 	1 1 -2	; "hold_input"
	6	[1114]	TEST     	1 0 0
	7	[1114]	JMP      	5	; to 13
	8	[1115]	GETTABLE 	1 0 -1	; "page_info_text"
	9	[1115]	SELF     	1 1 -3	; "onInput"
	10	[1115]	GETTABLE 	3 0 -1	; "page_info_text"
	11	[1115]	GETTABLE 	3 3 -2	; "hold_input"
	12	[1115]	CALL     	1 3 1
	13	[1117]	LOADBOOL 	1 1 0
	14	[1117]	RETURN   	1 2
	15	[1118]	RETURN   	0 1

function <./frontend/ui/widget/menu.lua:1120,1130> (21 instructions, 84 bytes at 0x7ffad5d0efc0)
1 param, 5 slots, 0 upvalues, 2 locals, 6 constants, 0 functions
	1	[1121]	GETTABLE 	1 0 -1	; "page"
	2	[1121]	LT       	0 -2 1	; 1 -
	3	[1121]	JMP      	15	; to 19
	4	[1122]	GETTABLE 	1 0 -1	; "page"
	5	[1122]	SUB      	1 1 -2	; - 1
	6	[1122]	SETTABLE 	0 -1 1	; "page" -
	7	[1123]	GETTABLE 	1 0 -3	; "perpage"
	8	[1124]	GETTABLE 	2 0 -1	; "page"
	9	[1124]	GETTABLE 	3 0 -4	; "page_num"
	10	[1124]	EQ       	0 2 3
	11	[1124]	JMP      	4	; to 16
	12	[1125]	GETTABLE 	2 0 -5	; "item_table"
	13	[1125]	LEN      	2 2
	14	[1125]	GETTABLE 	3 0 -3	; "perpage"
	15	[1125]	MOD      	1 2 3
	16	[1127]	SELF     	2 0 -6	; "updateItems"
	17	[1127]	MOVE     	4 1
	18	[1127]	CALL     	2 3 1
	19	[1129]	LOADBOOL 	1 0 0
	20	[1129]	RETURN   	1 2
	21	[1130]	RETURN   	0 1

function <./frontend/ui/widget/menu.lua:1132,1137> (9 instructions, 36 bytes at 0x7ffad5d0f510)
1 param, 3 slots, 0 upvalues, 1 local, 3 constants, 0 functions
	1	[1133]	GETTABLE 	1 0 -1	; "page"
	2	[1133]	GETTABLE 	2 0 -2	; "page_num"
	3	[1133]	LT       	0 1 2
	4	[1133]	JMP      	2	; to 7
	5	[1134]	SELF     	1 0 -3	; "onNextPage"
	6	[1134]	CALL     	1 2 1
	7	[1136]	LOADBOOL 	1 0 0
	8	[1136]	RETURN   	1 2
	9	[1137]	RETURN   	0 1

function <./frontend/ui/widget/menu.lua:1142,1155> (27 instructions, 108 bytes at 0x7ffad5d0fd80)
2 params, 6 slots, 0 upvalues, 2 locals, 11 constants, 0 functions
	1	[1143]	GETTABLE 	2 1 -1	; "sub_item_table"
	2	[1143]	EQ       	0 2 -2	; - nil
	3	[1143]	JMP      	9	; to 13
	4	[1144]	GETTABLE 	2 0 -3	; "close_callback"
	5	[1144]	TEST     	2 0 0
	6	[1144]	JMP      	2	; to 9
	7	[1145]	GETTABLE 	2 0 -3	; "close_callback"
	8	[1145]	CALL     	2 1 1
	9	[1147]	SELF     	2 0 -4	; "onMenuChoice"
	10	[1147]	MOVE     	4 1
	11	[1147]	CALL     	2 3 1
	12	[1147]	JMP      	12	; to 25
	13	[1150]	GETTABLE 	2 0 -5	; "item_table"
	14	[1150]	GETTABLE 	3 0 -6	; "title"
	15	[1150]	SETTABLE 	2 -6 3	; "title" -
	16	[1151]	GETGLOBAL	2 -7	; table
	17	[1151]	GETTABLE 	2 2 -8	; "insert"
	18	[1151]	GETTABLE 	3 0 -9	; "item_table_stack"
	19	[1151]	GETTABLE 	4 0 -5	; "item_table"
	20	[1151]	CALL     	2 3 1
	21	[1152]	SELF     	2 0 -10	; "switchItemTable"
	22	[1152]	GETTABLE 	4 1 -11	; "text"
	23	[1152]	GETTABLE 	5 1 -1	; "sub_item_table"
	24	[1152]	CALL     	2 4 1
	25	[1154]	LOADBOOL 	2 1 0
	26	[1154]	RETURN   	2 2
	27	[1155]	RETURN   	0 1

function <./frontend/ui/widget/menu.lua:1161,1166> (8 instructions, 32 bytes at 0x7ffad5d07bf0)
2 params, 3 slots, 0 upvalues, 2 locals, 1 constant, 0 functions
	1	[1162]	GETTABLE 	2 1 -1	; "callback"
	2	[1162]	TEST     	2 0 0
	3	[1162]	JMP      	2	; to 6
	4	[1163]	GETTABLE 	2 1 -1	; "callback"
	5	[1163]	CALL     	2 1 1
	6	[1165]	LOADBOOL 	2 1 0
	7	[1165]	RETURN   	2 2
	8	[1166]	RETURN   	0 1

function <./frontend/ui/widget/menu.lua:1171,1173> (3 instructions, 12 bytes at 0x7ffad5d0a500)
2 params, 3 slots, 0 upvalues, 2 locals, 0 constants, 0 functions
	1	[1172]	LOADBOOL 	2 1 0
	2	[1172]	RETURN   	2 2
	3	[1173]	RETURN   	0 1

function <./frontend/ui/widget/menu.lua:1175,1195> (44 instructions, 176 bytes at 0x7ffad5d0af50)
1 param, 5 slots, 0 upvalues, 2 locals, 10 constants, 0 functions
	1	[1176]	GETTABLE 	1 0 -1	; "onNext"
	2	[1176]	TEST     	1 0 0
	3	[1176]	JMP      	7	; to 11
	4	[1176]	GETTABLE 	1 0 -2	; "page"
	5	[1176]	GETTABLE 	2 0 -3	; "page_num"
	6	[1176]	SUB      	2 2 -4	; - 1
	7	[1176]	EQ       	0 1 2
	8	[1176]	JMP      	2	; to 11
	9	[1177]	SELF     	1 0 -1	; "onNext"
	10	[1177]	CALL     	1 2 1
	11	[1179]	GETTABLE 	1 0 -2	; "page"
	12	[1179]	GETTABLE 	2 0 -3	; "page_num"
	13	[1179]	LT       	0 1 2
	14	[1179]	JMP      	6	; to 21
	15	[1180]	GETTABLE 	1 0 -2	; "page"
	16	[1180]	ADD      	1 1 -4	; - 1
	17	[1180]	SETTABLE 	0 -2 1	; "page" -
	18	[1181]	SELF     	1 0 -5	; "updateItems"
	19	[1181]	CALL     	1 2 1
	20	[1181]	JMP      	21	; to 42
	21	[1182]	GETTABLE 	1 0 -2	; "page"
	22	[1182]	GETTABLE 	2 0 -3	; "page_num"
	23	[1182]	EQ       	0 1 2
	24	[1182]	JMP      	17	; to 42
	25	[1184]	GETTABLE 	1 0 -6	; "item_table"
	26	[1184]	LEN      	1 1
	27	[1184]	GETTABLE 	2 0 -7	; "perpage"
	28	[1184]	MOD      	1 1 2
	29	[1185]	EQ       	0 1 -8	; - 0
	30	[1185]	JMP      	1	; to 32
	31	[1186]	GETTABLE 	1 0 -7	; "perpage"
	32	[1188]	GETTABLE 	2 0 -9	; "selected"
	33	[1188]	GETTABLE 	2 2 -10	; "y"
	34	[1188]	EQ       	1 1 2
	35	[1188]	JMP      	3	; to 39
	36	[1189]	SELF     	2 0 -5	; "updateItems"
	37	[1189]	MOVE     	4 1
	38	[1189]	CALL     	2 3 1
	39	[1191]	SETTABLE 	0 -2 -4	; "page" 1
	40	[1192]	SELF     	2 0 -5	; "updateItems"
	41	[1192]	CALL     	2 2 1
	42	[1194]	LOADBOOL 	1 1 0
	43	[1194]	RETURN   	1 2
	44	[1195]	RETURN   	0 1

function <./frontend/ui/widget/menu.lua:1197,1205> (17 instructions, 68 bytes at 0x7ffad5d10220)
1 param, 3 slots, 0 upvalues, 1 local, 4 constants, 0 functions
	1	[1198]	GETTABLE 	1 0 -1	; "page"
	2	[1198]	LT       	0 -2 1	; 1 -
	3	[1198]	JMP      	4	; to 8
	4	[1199]	GETTABLE 	1 0 -1	; "page"
	5	[1199]	SUB      	1 1 -2	; - 1
	6	[1199]	SETTABLE 	0 -1 1	; "page" -
	7	[1199]	JMP      	5	; to 13
	8	[1200]	GETTABLE 	1 0 -1	; "page"
	9	[1200]	EQ       	0 1 -2	; - 1
	10	[1200]	JMP      	2	; to 13
	11	[1201]	GETTABLE 	1 0 -3	; "page_num"
	12	[1201]	SETTABLE 	0 -1 1	; "page" -
	13	[1203]	SELF     	1 0 -4	; "updateItems"
	14	[1203]	CALL     	1 2 1
	15	[1204]	LOADBOOL 	1 1 0
	16	[1204]	RETURN   	1 2
	17	[1205]	RETURN   	0 1

function <./frontend/ui/widget/menu.lua:1207,1211> (6 instructions, 24 bytes at 0x7ffad5d0a390)
1 param, 3 slots, 0 upvalues, 1 local, 3 constants, 0 functions
	1	[1208]	SETTABLE 	0 -1 -2	; "page" 1
	2	[1209]	SELF     	1 0 -3	; "updateItems"
	3	[1209]	CALL     	1 2 1
	4	[1210]	LOADBOOL 	1 1 0
	5	[1210]	RETURN   	1 2
	6	[1211]	RETURN   	0 1

function <./frontend/ui/widget/menu.lua:1213,1217> (7 instructions, 28 bytes at 0x7ffad5d0f730)
1 param, 3 slots, 0 upvalues, 1 local, 3 constants, 0 functions
	1	[1214]	GETTABLE 	1 0 -2	; "page_num"
	2	[1214]	SETTABLE 	0 -1 1	; "page" -
	3	[1215]	SELF     	1 0 -3	; "updateItems"
	4	[1215]	CALL     	1 2 1
	5	[1216]	LOADBOOL 	1 1 0
	6	[1216]	RETURN   	1 2
	7	[1217]	RETURN   	0 1

function <./frontend/ui/widget/menu.lua:1219,1223> (6 instructions, 24 bytes at 0x7ffad5d0f7b0)
2 params, 4 slots, 0 upvalues, 2 locals, 2 constants, 0 functions
	1	[1220]	SETTABLE 	0 -1 1	; "page" -
	2	[1221]	SELF     	2 0 -2	; "updateItems"
	3	[1221]	CALL     	2 2 1
	4	[1222]	LOADBOOL 	2 1 0
	5	[1222]	RETURN   	2 2
	6	[1223]	RETURN   	0 1

function <./frontend/ui/widget/menu.lua:1225,1231> (17 instructions, 68 bytes at 0x7ffad5d103e0)
1 param, 5 slots, 0 upvalues, 2 locals, 7 constants, 0 functions
	1	[1226]	GETTABLE 	1 0 -1	; "item_table"
	2	[1226]	GETTABLE 	2 0 -2	; "page"
	3	[1226]	SUB      	2 2 -3	; - 1
	4	[1226]	GETTABLE 	3 0 -4	; "perpage"
	5	[1226]	MUL      	2 2 3
	6	[1226]	GETTABLE 	3 0 -5	; "selected"
	7	[1226]	GETTABLE 	3 3 -6	; "y"
	8	[1226]	ADD      	2 2 3
	9	[1226]	GETTABLE 	1 1 2
	10	[1227]	TEST     	1 0 0
	11	[1227]	JMP      	3	; to 15
	12	[1228]	SELF     	2 0 -7	; "onMenuSelect"
	13	[1228]	MOVE     	4 1
	14	[1228]	CALL     	2 3 1
	15	[1230]	LOADBOOL 	2 1 0
	16	[1230]	RETURN   	2 2
	17	[1231]	RETURN   	0 1

function <./frontend/ui/widget/menu.lua:1233,1239> (17 instructions, 68 bytes at 0x7ffad5d0e5c0)
1 param, 5 slots, 0 upvalues, 2 locals, 7 constants, 0 functions
	1	[1234]	GETTABLE 	1 0 -1	; "item_table"
	2	[1234]	GETTABLE 	2 0 -2	; "page"
	3	[1234]	SUB      	2 2 -3	; - 1
	4	[1234]	GETTABLE 	3 0 -4	; "perpage"
	5	[1234]	MUL      	2 2 3
	6	[1234]	GETTABLE 	3 0 -5	; "selected"
	7	[1234]	GETTABLE 	3 3 -6	; "y"
	8	[1234]	ADD      	2 2 3
	9	[1234]	GETTABLE 	1 1 2
	10	[1235]	TEST     	1 0 0
	11	[1235]	JMP      	3	; to 15
	12	[1236]	SELF     	2 0 -7	; "onMenuHold"
	13	[1236]	MOVE     	4 1
	14	[1236]	CALL     	2 3 1
	15	[1238]	LOADBOOL 	2 1 0
	16	[1238]	RETURN   	2 2
	17	[1239]	RETURN   	0 1

function <./frontend/ui/widget/menu.lua:1241,1251> (19 instructions, 76 bytes at 0x7ffad5d10a80)
1 param, 7 slots, 0 upvalues, 3 locals, 7 constants, 0 functions
	1	[1242]	GETTABLE 	1 0 -1	; "item_table_stack"
	2	[1242]	LEN      	1 1
	3	[1243]	EQ       	0 1 -2	; - 0
	4	[1243]	JMP      	3	; to 8
	5	[1244]	SELF     	2 0 -3	; "onCloseAllMenus"
	6	[1244]	CALL     	2 2 1
	7	[1244]	JMP      	9	; to 17
	8	[1247]	GETGLOBAL	2 -4	; table
	9	[1247]	GETTABLE 	2 2 -5	; "remove"
	10	[1247]	GETTABLE 	3 0 -1	; "item_table_stack"
	11	[1247]	MOVE     	4 1
	12	[1247]	CALL     	2 3 2
	13	[1248]	SELF     	3 0 -6	; "switchItemTable"
	14	[1248]	GETTABLE 	5 2 -7	; "title"
	15	[1248]	MOVE     	6 2
	16	[1248]	CALL     	3 4 1
	17	[1250]	LOADBOOL 	2 1 0
	18	[1250]	RETURN   	2 2
	19	[1251]	RETURN   	0 1

function <./frontend/ui/widget/menu.lua:1253,1259> (12 instructions, 48 bytes at 0x7ffad5d10c00)
1 param, 4 slots, 1 upvalue, 1 local, 2 constants, 0 functions
	1	[1254]	GETUPVAL 	1 0	; UIManager
	2	[1254]	SELF     	1 1 -1	; "close"
	3	[1254]	MOVE     	3 0
	4	[1254]	CALL     	1 3 1
	5	[1255]	GETTABLE 	1 0 -2	; "close_callback"
	6	[1255]	TEST     	1 0 0
	7	[1255]	JMP      	2	; to 10
	8	[1256]	GETTABLE 	1 0 -2	; "close_callback"
	9	[1256]	CALL     	1 1 1
	10	[1258]	LOADBOOL 	1 1 0
	11	[1258]	RETURN   	1 2
	12	[1259]	RETURN   	0 1

function <./frontend/ui/widget/menu.lua:1261,1266> (11 instructions, 44 bytes at 0x7ffad5d10f80)
3 params, 6 slots, 0 upvalues, 3 locals, 4 constants, 0 functions
	1	[1262]	GETTABLE 	3 2 -1	; "pos"
	2	[1262]	SELF     	3 3 -2	; "notIntersectWith"
	3	[1262]	GETTABLE 	5 0 -3	; "dimen"
	4	[1262]	CALL     	3 3 2
	5	[1262]	TEST     	3 0 0
	6	[1262]	JMP      	4	; to 11
	7	[1263]	SELF     	3 0 -4	; "onCloseAllMenus"
	8	[1263]	CALL     	3 2 1
	9	[1264]	LOADBOOL 	3 1 0
	10	[1264]	RETURN   	3 2
	11	[1266]	RETURN   	0 1

function <./frontend/ui/widget/menu.lua:1268,1289> (34 instructions, 136 bytes at 0x7ffad5d11090)
3 params, 8 slots, 2 upvalues, 4 locals, 13 constants, 0 functions
	1	[1269]	GETUPVAL 	3 0	; BD
	2	[1269]	GETTABLE 	3 3 -1	; "flipDirectionIfMirroredUILayout"
	3	[1269]	GETTABLE 	4 2 -2	; "direction"
	4	[1269]	CALL     	3 2 2
	5	[1270]	EQ       	0 3 -3	; - "west"
	6	[1270]	JMP      	3	; to 10
	7	[1271]	SELF     	4 0 -4	; "onNextPage"
	8	[1271]	CALL     	4 2 1
	9	[1271]	JMP      	24	; to 34
	10	[1272]	EQ       	0 3 -5	; - "east"
	11	[1272]	JMP      	3	; to 15
	12	[1273]	SELF     	4 0 -6	; "onPrevPage"
	13	[1273]	CALL     	4 2 1
	14	[1273]	JMP      	19	; to 34
	15	[1274]	EQ       	0 3 -7	; - "south"
	16	[1274]	JMP      	9	; to 26
	17	[1275]	GETTABLE 	4 0 -8	; "has_close_button"
	18	[1275]	TEST     	4 0 0
	19	[1275]	JMP      	14	; to 34
	20	[1275]	GETTABLE 	4 0 -9	; "no_title"
	21	[1275]	TEST     	4 0 1
	22	[1275]	JMP      	11	; to 34
	23	[1278]	SELF     	4 0 -10	; "onClose"
	24	[1278]	CALL     	4 2 1
	25	[1279]	JMP      	8	; to 34
	26	[1282]	EQ       	0 3 -11	; - "north"
	27	[1282]	JMP      	1	; to 29
	28	[1284]	JMP      	5	; to 34
	29	[1287]	GETUPVAL 	4 1	; UIManager
	30	[1287]	SELF     	4 4 -12	; "setDirty"
	31	[1287]	LOADNIL  	6 6
	32	[1287]	LOADK    	7 -13	; "full"
	33	[1287]	CALL     	4 4 1
	34	[1289]	RETURN   	0 1

function <./frontend/ui/widget/menu.lua:1311,1322> (22 instructions, 88 bytes at 0x7ffad5d11bc0)
1 param, 5 slots, 1 upvalue, 2 locals, 7 constants, 0 functions
	1	[1313]	GETTABLE 	2 0 -1	; "text_func"
	2	[1313]	TEST     	2 0 0
	3	[1313]	JMP      	4	; to 8
	4	[1314]	GETTABLE 	2 0 -1	; "text_func"
	5	[1314]	CALL     	2 1 2
	6	[1314]	MOVE     	1 2
	7	[1314]	JMP      	1	; to 9
	8	[1316]	GETTABLE 	1 0 -2	; "text"
	9	[1318]	GETTABLE 	2 0 -3	; "sub_item_table"
	10	[1318]	EQ       	0 2 -4	; - nil
	11	[1318]	JMP      	3	; to 15
	12	[1318]	GETTABLE 	2 0 -5	; "sub_item_table_func"
	13	[1318]	TEST     	2 0 0
	14	[1318]	JMP      	6	; to 21
	15	[1319]	GETGLOBAL	2 -6	; string
	16	[1319]	GETTABLE 	2 2 -7	; "format"
	17	[1319]	GETUPVAL 	3 0	; sub_item_format
	18	[1319]	MOVE     	4 1
	19	[1319]	CALL     	2 3 2
	20	[1319]	MOVE     	1 2
	21	[1321]	RETURN   	1 2
	22	[1322]	RETURN   	0 1

function <./frontend/ui/widget/menu.lua:1324,1336> (23 instructions, 92 bytes at 0x7ffad5d121c0)
1 param, 11 slots, 0 upvalues, 8 locals, 6 constants, 0 functions
	1	[1325]	NEWTABLE 	1 0 0
	2	[1326]	GETGLOBAL	2 -1	; pairs
	3	[1326]	MOVE     	3 0
	4	[1326]	CALL     	2 2 4
	5	[1326]	JMP      	14	; to 20
	6	[1327]	NEWTABLE 	7 0 1
	7	[1327]	SETTABLE 	7 -2 5	; "text" -
	8	[1328]	GETTABLE 	8 6 -3	; "callback"
	9	[1328]	TEST     	8 0 0
	10	[1328]	JMP      	3	; to 14
	11	[1329]	GETTABLE 	8 6 -3	; "callback"
	12	[1329]	SETTABLE 	7 -3 8	; "callback" -
	13	[1329]	JMP      	1	; to 15
	14	[1331]	SETTABLE 	7 -4 6	; "sub_item_table" -
	15	[1333]	GETGLOBAL	8 -5	; table
	16	[1333]	GETTABLE 	8 8 -6	; "insert"
	17	[1333]	MOVE     	9 1
	18	[1333]	MOVE     	10 7
	19	[1333]	CALL     	8 3 1
	20	[1326]	TFORLOOP 	2 2
	21	[1333]	JMP      	-16	; to 6
	22	[1335]	RETURN   	1 2
	23	[1336]	RETURN   	0 1
