-- BYTECODE -- mock_time_spec.lua:2-4
0001    GGET     0   0      ; "require"
0002    KSTR     1   1      ; "mock_time"
0003    CALL     0   2   2
0004    MOV      1   0
0005    TGETS    0   0   2  ; "uninstall"
0006    CALL     0   1   2
0007    RET0     0   1

-- BYTECODE -- mock_time_spec.lua:6-20
0001    GGET     0   0      ; "require"
0002    KSTR     1   1      ; "mock_time"
0003    CALL     0   2   2
0004    GGET     1   0      ; "require"
0005    KSTR     2   2      ; "ffi/util"
0006    CALL     1   2   2
0007    GGET     2   3      ; "os"
0008    TGETS    2   2   4  ; "time"
0009    CALL     2   2   1
0010    TGETS    3   1   5  ; "gettime"
0011    CALL     3   2   1
0012    MOV      5   0
0013    TGETS    4   0   6  ; "install"
0014    CALL     4   1   2
0015    GGET     4   7      ; "assert"
0016    TGETS    4   4   8  ; "is"
0017    TGETS    4   4   9  ; "truthy"
0018    MOV      6   0
0019    TGETS    5   0  10  ; "set"
0020    KSHORT   7  10
0021    CALL     5   0   3
0022    CALLM    4   1   0
0023    GGET     4   7      ; "assert"
0024    TGETS    4   4  11  ; "are"
0025    TGETS    4   4  12  ; "equal"
0026    GGET     5   3      ; "os"
0027    TGETS    5   5   4  ; "time"
0028    CALL     5   2   1
0029    KSHORT   6  10
0030    CALL     4   1   3
0031    TGETS    4   1   5  ; "gettime"
0032    CALL     4   3   1
0033    GGET     6   7      ; "assert"
0034    TGETS    6   6  11  ; "are"
0035    TGETS    6   6  12  ; "equal"
0036    MOV      7   4
0037    KSHORT   8  10
0038    CALL     6   1   3
0039    GGET     6   7      ; "assert"
0040    TGETS    6   6  11  ; "are"
0041    TGETS    6   6  12  ; "equal"
0042    MOV      7   5
0043    KSHORT   8   0
0044    CALL     6   1   3
0045    MOV      7   0
0046    TGETS    6   0  13  ; "uninstall"
0047    CALL     6   1   2
0048    GGET     6   7      ; "assert"
0049    TGETS    6   6   8  ; "is"
0050    TGETS    6   6   9  ; "truthy"
0051    GGET     7   3      ; "os"
0052    TGETS    7   7   4  ; "time"
0053    CALL     7   2   1
0054    ISLE     2   7
0055    JMP      7 => 0058
0056    KPRI     7   1
0057    JMP      8 => 0059
0058 => KPRI     7   2
0059 => CALL     6   1   2
0060    GGET     6   7      ; "assert"
0061    TGETS    6   6   8  ; "is"
0062    TGETS    6   6   9  ; "truthy"
0063    TGETS    7   1   5  ; "gettime"
0064    CALL     7   2   1
0065    ISLE     3   7
0066    JMP      7 => 0069
0067    KPRI     7   1
0068    JMP      8 => 0070
0069 => KPRI     7   2
0070 => CALL     6   1   2
0071    RET0     0   1

-- BYTECODE -- mock_time_spec.lua:22-32
0001    GGET     0   0      ; "require"
0002    KSTR     1   1      ; "mock_time"
0003    CALL     0   2   2
0004    GGET     1   0      ; "require"
0005    KSTR     2   2      ; "ffi/util"
0006    CALL     1   2   2
0007    GGET     2   3      ; "os"
0008    TGETS    2   2   4  ; "time"
0009    CALL     2   2   1
0010    TGETS    3   1   5  ; "gettime"
0011    CALL     3   2   1
0012    MOV      5   0
0013    TGETS    4   0   6  ; "install"
0014    CALL     4   1   2
0015    MOV      5   0
0016    TGETS    4   0   6  ; "install"
0017    CALL     4   1   2
0018    MOV      5   0
0019    TGETS    4   0   7  ; "uninstall"
0020    CALL     4   1   2
0021    GGET     4   8      ; "assert"
0022    TGETS    4   4   9  ; "is"
0023    TGETS    4   4  10  ; "truthy"
0024    GGET     5   3      ; "os"
0025    TGETS    5   5   4  ; "time"
0026    CALL     5   2   1
0027    ISLE     2   5
0028    JMP      5 => 0031
0029    KPRI     5   1
0030    JMP      6 => 0032
0031 => KPRI     5   2
0032 => CALL     4   1   2
0033    GGET     4   8      ; "assert"
0034    TGETS    4   4   9  ; "is"
0035    TGETS    4   4  10  ; "truthy"
0036    TGETS    5   1   5  ; "gettime"
0037    CALL     5   2   1
0038    ISLE     3   5
0039    JMP      5 => 0042
0040    KPRI     5   1
0041    JMP      6 => 0043
0042 => KPRI     5   2
0043 => CALL     4   1   2
0044    RET0     0   1

-- BYTECODE -- mock_time_spec.lua:39-39
0001    RET0     0   1

-- BYTECODE -- mock_time_spec.lua:34-40
0001    GGET     0   0      ; "require"
0002    KSTR     1   1      ; "mock_time"
0003    CALL     0   2   2
0004    GGET     1   2      ; "assert"
0005    TGETS    1   1   3  ; "is"
0006    TGETS    1   1   4  ; "falsy"
0007    MOV      3   0
0008    TGETS    2   0   5  ; "set"
0009    KSTR     4   6      ; "100"
0010    CALL     2   0   3
0011    CALLM    1   1   0
0012    GGET     1   2      ; "assert"
0013    TGETS    1   1   3  ; "is"
0014    TGETS    1   1   4  ; "falsy"
0015    MOV      3   0
0016    TGETS    2   0   5  ; "set"
0017    KPRI     4   2
0018    CALL     2   0   3
0019    CALLM    1   1   0
0020    GGET     1   2      ; "assert"
0021    TGETS    1   1   3  ; "is"
0022    TGETS    1   1   4  ; "falsy"
0023    MOV      3   0
0024    TGETS    2   0   5  ; "set"
0025    KPRI     4   0
0026    CALL     2   0   3
0027    CALLM    1   1   0
0028    GGET     1   2      ; "assert"
0029    TGETS    1   1   3  ; "is"
0030    TGETS    1   1   4  ; "falsy"
0031    MOV      3   0
0032    TGETS    2   0   5  ; "set"
0033    FNEW     4   7      ; mock_time_spec.lua:39
0034    CALL     2   0   3
0035    CALLM    1   1   0
0036    RET0     0   1

-- BYTECODE -- mock_time_spec.lua:42-50
0001    GGET     0   0      ; "require"
0002    KSTR     1   1      ; "mock_time"
0003    CALL     0   2   2
0004    MOV      2   0
0005    TGETS    1   0   2  ; "install"
0006    CALL     1   1   2
0007    GGET     1   3      ; "assert"
0008    TGETS    1   1   4  ; "is"
0009    TGETS    1   1   5  ; "truthy"
0010    MOV      3   0
0011    TGETS    2   0   6  ; "set"
0012    KNUM     4   0      ; 10.1
0013    CALL     2   0   3
0014    CALLM    1   1   0
0015    GGET     1   3      ; "assert"
0016    TGETS    1   1   7  ; "are"
0017    TGETS    1   1   8  ; "equal"
0018    GGET     2   9      ; "os"
0019    TGETS    2   2  10  ; "time"
0020    CALL     2   2   1
0021    KSHORT   3  10
0022    CALL     1   1   3
0023    MOV      2   0
0024    TGETS    1   0  11  ; "increase"
0025    KSHORT   3   1
0026    CALL     1   1   3
0027    GGET     1   3      ; "assert"
0028    TGETS    1   1   7  ; "are"
0029    TGETS    1   1   8  ; "equal"
0030    GGET     2   9      ; "os"
0031    TGETS    2   2  10  ; "time"
0032    CALL     2   2   1
0033    KSHORT   3  11
0034    CALL     1   1   3
0035    MOV      2   0
0036    TGETS    1   0  12  ; "uninstall"
0037    CALL     1   1   2
0038    RET0     0   1

-- BYTECODE -- mock_time_spec.lua:1-51
0001    GGET     0   0      ; "teardown"
0002    FNEW     1   1      ; mock_time_spec.lua:2
0003    CALL     0   1   2
0004    GGET     0   2      ; "it"
0005    KSTR     1   3      ; "should be able to install and uninstall"
0006    FNEW     2   4      ; mock_time_spec.lua:6
0007    CALL     0   1   3
0008    GGET     0   2      ; "it"
0009    KSTR     1   5      ; "should be able to install several times"
0010    FNEW     2   6      ; mock_time_spec.lua:22
0011    CALL     0   1   3
0012    GGET     0   2      ; "it"
0013    KSTR     1   7      ; "should reject invalid value"
0014    FNEW     2   8      ; mock_time_spec.lua:34
0015    CALL     0   1   3
0016    GGET     0   2      ; "it"
0017    KSTR     1   9      ; "should increase time"
0018    FNEW     2  10      ; mock_time_spec.lua:42
0019    CALL     0   1   3
0020    RET0     0   1

-- BYTECODE -- mock_time_spec.lua:0-52
0001    GGET     0   0      ; "describe"
0002    KSTR     1   1      ; "MockTime tests"
0003    FNEW     2   2      ; mock_time_spec.lua:1
0004    CALL     0   1   3
0005    RET0     0   1

