
main <./frontend/ui/widget/container/movablecontainer.lua:0,0> (86 instructions, 344 bytes at 0x7fd421406900)
0+ params, 15 slots, 0 upvalues, 10 locals, 39 constants, 12 functions
	1	[16]	GETGLOBAL	0 -1	; require
	2	[16]	LOADK    	1 -2	; "ffi/blitbuffer"
	3	[16]	CALL     	0 2 2
	4	[17]	GETGLOBAL	1 -1	; require
	5	[17]	LOADK    	2 -3	; "device"
	6	[17]	CALL     	1 2 2
	7	[18]	GETGLOBAL	2 -1	; require
	8	[18]	LOADK    	3 -4	; "ui/geometry"
	9	[18]	CALL     	2 2 2
	10	[19]	GETGLOBAL	3 -1	; require
	11	[19]	LOADK    	4 -5	; "ui/gesturerange"
	12	[19]	CALL     	3 2 2
	13	[20]	GETGLOBAL	4 -1	; require
	14	[20]	LOADK    	5 -6	; "ui/widget/container/inputcontainer"
	15	[20]	CALL     	4 2 2
	16	[21]	GETGLOBAL	5 -1	; require
	17	[21]	LOADK    	6 -7	; "optmath"
	18	[21]	CALL     	5 2 2
	19	[22]	GETGLOBAL	6 -1	; require
	20	[22]	LOADK    	7 -8	; "ui/uimanager"
	21	[22]	CALL     	6 2 2
	22	[23]	GETTABLE 	7 1 -9	; "screen"
	23	[24]	GETGLOBAL	8 -1	; require
	24	[24]	LOADK    	9 -10	; "logger"
	25	[24]	CALL     	8 2 2
	26	[26]	SELF     	9 4 -11	; "new"
	27	[26]	NEWTABLE 	11 0 11
	28	[29]	SETTABLE 	11 -12 -13	; "alpha" nil
	29	[33]	SELF     	12 7 -15	; "scaleBySize"
	30	[33]	LOADK    	14 -16	; 5
	31	[33]	CALL     	12 3 2
	32	[33]	SETTABLE 	11 -14 12	; "move_threshold" -
	33	[36]	SETTABLE 	11 -17 -13	; "ignore_events" nil
	34	[39]	SETTABLE 	11 -18 -19	; "_moved_offset_x" 0
	35	[40]	SETTABLE 	11 -20 -19	; "_moved_offset_y" 0
	36	[42]	SETTABLE 	11 -21 -22	; "_touch_pre_pan_was_inside" false
	37	[43]	SETTABLE 	11 -23 -22	; "_moving" false
	38	[44]	SETTABLE 	11 -24 -13	; "_move_relative_x" nil
	39	[45]	SETTABLE 	11 -25 -13	; "_move_relative_y" nil
	40	[47]	SETTABLE 	11 -26 -13	; "_orig_x" nil
	41	[48]	SETTABLE 	11 -27 -13	; "_orig_y" nil
	42	[26]	CALL     	9 3 2
	43	[83]	CLOSURE  	10 0	; 0x7fd4214070a0
	44	[83]	MOVE     	0 1
	45	[83]	MOVE     	0 2
	46	[83]	MOVE     	0 7
	47	[83]	MOVE     	0 3
	48	[51]	SETTABLE 	9 -28 10	; "init" -
	49	[90]	CLOSURE  	10 1	; 0x7fd421407720
	50	[90]	MOVE     	0 2
	51	[85]	SETTABLE 	9 -29 10	; "getMovedOffset" -
	52	[97]	CLOSURE  	10 2	; 0x7fd421407db0
	53	[92]	SETTABLE 	9 -30 10	; "setMovedOffset" -
	54	[128]	CLOSURE  	10 3	; 0x7fd421407fa0
	55	[128]	MOVE     	0 2
	56	[128]	MOVE     	0 0
	57	[99]	SETTABLE 	9 -31 10	; "paintTo" -
	58	[188]	CLOSURE  	10 4	; 0x7fd421408110
	59	[188]	MOVE     	0 8
	60	[188]	MOVE     	0 5
	61	[188]	MOVE     	0 7
	62	[188]	MOVE     	0 6
	63	[130]	SETTABLE 	9 -32 10	; "_moveBy" -
	64	[213]	CLOSURE  	10 5	; 0x7fd421409490
	65	[213]	MOVE     	0 8
	66	[190]	SETTABLE 	9 -33 10	; "onMovableSwipe" -
	67	[227]	CLOSURE  	10 6	; 0x7fd421407200
	68	[227]	MOVE     	0 8
	69	[215]	SETTABLE 	9 -34 10	; "onMovableTouch" -
	70	[238]	CLOSURE  	10 7	; 0x7fd421409930
	71	[238]	MOVE     	0 8
	72	[229]	SETTABLE 	9 -35 10	; "onMovableHold" -
	73	[249]	CLOSURE  	10 8	; 0x7fd42140a760
	74	[249]	MOVE     	0 8
	75	[240]	SETTABLE 	9 -36 10	; "onMovableHoldPan" -
	76	[272]	CLOSURE  	10 9	; 0x7fd42140acb0
	77	[272]	MOVE     	0 8
	78	[251]	SETTABLE 	9 -37 10	; "onMovableHoldRelease" -
	79	[284]	CLOSURE  	10 10	; 0x7fd42140af80
	80	[284]	MOVE     	0 8
	81	[274]	SETTABLE 	9 -38 10	; "onMovablePan" -
	82	[296]	CLOSURE  	10 11	; 0x7fd42140b2b0
	83	[296]	MOVE     	0 8
	84	[286]	SETTABLE 	9 -39 10	; "onMovablePanRelease" -
	85	[298]	RETURN   	9 2
	86	[298]	RETURN   	0 1

function <./frontend/ui/widget/container/movablecontainer.lua:51,83> (145 instructions, 580 bytes at 0x7fd4214070a0)
1 param, 9 slots, 4 upvalues, 8 locals, 29 constants, 0 functions
	1	[52]	GETUPVAL 	1 0	; Device
	2	[52]	SELF     	1 1 -1	; "isTouchDevice"
	3	[52]	CALL     	1 2 2
	4	[52]	TEST     	1 0 0
	5	[52]	JMP      	139	; to 145
	6	[53]	GETUPVAL 	1 1	; Geom
	7	[53]	SELF     	1 1 -2	; "new"
	8	[53]	NEWTABLE 	3 0 4
	9	[54]	SETTABLE 	3 -3 -4	; "x" 0
	10	[54]	SETTABLE 	3 -5 -4	; "y" 0
	11	[55]	GETUPVAL 	4 2	; Screen
	12	[55]	SELF     	4 4 -7	; "getWidth"
	13	[55]	CALL     	4 2 2
	14	[55]	SETTABLE 	3 -6 4	; "w" -
	15	[56]	GETUPVAL 	4 2	; Screen
	16	[56]	SELF     	4 4 -9	; "getHeight"
	17	[56]	CALL     	4 2 2
	18	[56]	SETTABLE 	3 -8 4	; "h" -
	19	[53]	CALL     	1 3 2
	20	[59]	NEWTABLE 	2 0 0
	21	[60]	GETTABLE 	3 0 -10	; "ignore_events"
	22	[60]	TEST     	3 0 0
	23	[60]	JMP      	7	; to 31
	24	[61]	GETGLOBAL	3 -11	; pairs
	25	[61]	GETTABLE 	4 0 -10	; "ignore_events"
	26	[61]	CALL     	3 2 4
	27	[61]	JMP      	1	; to 29
	28	[62]	SETTABLE 	2 7 -12	; - true
	29	[61]	TFORLOOP 	3 2
	30	[62]	JMP      	-3	; to 28
	31	[74]	NEWTABLE 	3 0 0
	32	[74]	SETTABLE 	0 -13 3	; "ges_events" -
	33	[75]	GETTABLE 	3 0 -13	; "ges_events"
	34	[75]	GETTABLE 	4 2 -15	; "touch"
	35	[75]	TEST     	4 0 1
	36	[75]	JMP      	10	; to 47
	37	[75]	NEWTABLE 	4 0 0
	38	[75]	GETUPVAL 	5 3	; GestureRange
	39	[75]	SELF     	5 5 -2	; "new"
	40	[75]	NEWTABLE 	7 0 2
	41	[75]	SETTABLE 	7 -16 -15	; "ges" "touch"
	42	[75]	SETTABLE 	7 -17 1	; "range" -
	43	[75]	CALL     	5 3 0
	44	[75]	SETLIST  	4 0 1	; 1
	45	[75]	TEST     	4 0 1
	46	[75]	JMP      	1	; to 48
	47	[75]	LOADNIL  	4 4
	48	[75]	SETTABLE 	3 -14 4	; "MovableTouch" -
	49	[76]	GETTABLE 	3 0 -13	; "ges_events"
	50	[76]	GETTABLE 	4 2 -19	; "swipe"
	51	[76]	TEST     	4 0 1
	52	[76]	JMP      	10	; to 63
	53	[76]	NEWTABLE 	4 0 0
	54	[76]	GETUPVAL 	5 3	; GestureRange
	55	[76]	SELF     	5 5 -2	; "new"
	56	[76]	NEWTABLE 	7 0 2
	57	[76]	SETTABLE 	7 -16 -19	; "ges" "swipe"
	58	[76]	SETTABLE 	7 -17 1	; "range" -
	59	[76]	CALL     	5 3 0
	60	[76]	SETLIST  	4 0 1	; 1
	61	[76]	TEST     	4 0 1
	62	[76]	JMP      	1	; to 64
	63	[76]	LOADNIL  	4 4
	64	[76]	SETTABLE 	3 -18 4	; "MovableSwipe" -
	65	[77]	GETTABLE 	3 0 -13	; "ges_events"
	66	[77]	GETTABLE 	4 2 -21	; "hold"
	67	[77]	TEST     	4 0 1
	68	[77]	JMP      	10	; to 79
	69	[77]	NEWTABLE 	4 0 0
	70	[77]	GETUPVAL 	5 3	; GestureRange
	71	[77]	SELF     	5 5 -2	; "new"
	72	[77]	NEWTABLE 	7 0 2
	73	[77]	SETTABLE 	7 -16 -21	; "ges" "hold"
	74	[77]	SETTABLE 	7 -17 1	; "range" -
	75	[77]	CALL     	5 3 0
	76	[77]	SETLIST  	4 0 1	; 1
	77	[77]	TEST     	4 0 1
	78	[77]	JMP      	1	; to 80
	79	[77]	LOADNIL  	4 4
	80	[77]	SETTABLE 	3 -20 4	; "MovableHold" -
	81	[78]	GETTABLE 	3 0 -13	; "ges_events"
	82	[78]	GETTABLE 	4 2 -23	; "hold_pan"
	83	[78]	TEST     	4 0 1
	84	[78]	JMP      	10	; to 95
	85	[78]	NEWTABLE 	4 0 0
	86	[78]	GETUPVAL 	5 3	; GestureRange
	87	[78]	SELF     	5 5 -2	; "new"
	88	[78]	NEWTABLE 	7 0 2
	89	[78]	SETTABLE 	7 -16 -23	; "ges" "hold_pan"
	90	[78]	SETTABLE 	7 -17 1	; "range" -
	91	[78]	CALL     	5 3 0
	92	[78]	SETLIST  	4 0 1	; 1
	93	[78]	TEST     	4 0 1
	94	[78]	JMP      	1	; to 96
	95	[78]	LOADNIL  	4 4
	96	[78]	SETTABLE 	3 -22 4	; "MovableHoldPan" -
	97	[79]	GETTABLE 	3 0 -13	; "ges_events"
	98	[79]	GETTABLE 	4 2 -25	; "hold_release"
	99	[79]	TEST     	4 0 1
	100	[79]	JMP      	10	; to 111
	101	[79]	NEWTABLE 	4 0 0
	102	[79]	GETUPVAL 	5 3	; GestureRange
	103	[79]	SELF     	5 5 -2	; "new"
	104	[79]	NEWTABLE 	7 0 2
	105	[79]	SETTABLE 	7 -16 -25	; "ges" "hold_release"
	106	[79]	SETTABLE 	7 -17 1	; "range" -
	107	[79]	CALL     	5 3 0
	108	[79]	SETLIST  	4 0 1	; 1
	109	[79]	TEST     	4 0 1
	110	[79]	JMP      	1	; to 112
	111	[79]	LOADNIL  	4 4
	112	[79]	SETTABLE 	3 -24 4	; "MovableHoldRelease" -
	113	[80]	GETTABLE 	3 0 -13	; "ges_events"
	114	[80]	GETTABLE 	4 2 -27	; "pan"
	115	[80]	TEST     	4 0 1
	116	[80]	JMP      	10	; to 127
	117	[80]	NEWTABLE 	4 0 0
	118	[80]	GETUPVAL 	5 3	; GestureRange
	119	[80]	SELF     	5 5 -2	; "new"
	120	[80]	NEWTABLE 	7 0 2
	121	[80]	SETTABLE 	7 -16 -27	; "ges" "pan"
	122	[80]	SETTABLE 	7 -17 1	; "range" -
	123	[80]	CALL     	5 3 0
	124	[80]	SETLIST  	4 0 1	; 1
	125	[80]	TEST     	4 0 1
	126	[80]	JMP      	1	; to 128
	127	[80]	LOADNIL  	4 4
	128	[80]	SETTABLE 	3 -26 4	; "MovablePan" -
	129	[81]	GETTABLE 	3 0 -13	; "ges_events"
	130	[81]	GETTABLE 	4 2 -29	; "pan_release"
	131	[81]	TEST     	4 0 1
	132	[81]	JMP      	10	; to 143
	133	[81]	NEWTABLE 	4 0 0
	134	[81]	GETUPVAL 	5 3	; GestureRange
	135	[81]	SELF     	5 5 -2	; "new"
	136	[81]	NEWTABLE 	7 0 2
	137	[81]	SETTABLE 	7 -16 -29	; "ges" "pan_release"
	138	[81]	SETTABLE 	7 -17 1	; "range" -
	139	[81]	CALL     	5 3 0
	140	[81]	SETLIST  	4 0 1	; 1
	141	[81]	TEST     	4 0 1
	142	[81]	JMP      	1	; to 144
	143	[81]	LOADNIL  	4 4
	144	[81]	SETTABLE 	3 -28 4	; "MovablePanRelease" -
	145	[83]	RETURN   	0 1

function <./frontend/ui/widget/container/movablecontainer.lua:85,90> (10 instructions, 40 bytes at 0x7fd421407720)
1 param, 5 slots, 1 upvalue, 1 local, 5 constants, 0 functions
	1	[86]	GETUPVAL 	1 0	; Geom
	2	[86]	SELF     	1 1 -1	; "new"
	3	[86]	NEWTABLE 	3 0 2
	4	[87]	GETTABLE 	4 0 -3	; "_moved_offset_x"
	5	[87]	SETTABLE 	3 -2 4	; "x" -
	6	[88]	GETTABLE 	4 0 -5	; "_moved_offset_y"
	7	[88]	SETTABLE 	3 -4 4	; "y" -
	8	[86]	TAILCALL 	1 3 0
	9	[89]	RETURN   	1 0
	10	[90]	RETURN   	0 1

function <./frontend/ui/widget/container/movablecontainer.lua:92,97> (13 instructions, 52 bytes at 0x7fd421407db0)
2 params, 3 slots, 0 upvalues, 2 locals, 4 constants, 0 functions
	1	[93]	TEST     	1 0 0
	2	[93]	JMP      	10	; to 13
	3	[93]	GETTABLE 	2 1 -1	; "x"
	4	[93]	TEST     	2 0 0
	5	[93]	JMP      	7	; to 13
	6	[93]	GETTABLE 	2 1 -2	; "y"
	7	[93]	TEST     	2 0 0
	8	[93]	JMP      	4	; to 13
	9	[94]	GETTABLE 	2 1 -1	; "x"
	10	[94]	SETTABLE 	0 -3 2	; "_moved_offset_x" -
	11	[95]	GETTABLE 	2 1 -2	; "y"
	12	[95]	SETTABLE 	0 -4 2	; "_moved_offset_y" -
	13	[97]	RETURN   	0 1

function <./frontend/ui/widget/container/movablecontainer.lua:99,128> (81 instructions, 324 bytes at 0x7fd421407fa0)
4 params, 16 slots, 2 upvalues, 6 locals, 22 constants, 0 functions
	1	[100]	GETTABLE 	4 0 -1	; 1
	2	[100]	EQ       	0 4 -2	; - nil
	3	[100]	JMP      	1	; to 5
	4	[101]	RETURN   	0 1
	5	[104]	GETTABLE 	4 0 -1	; 1
	6	[104]	SELF     	4 4 -3	; "getSize"
	7	[104]	CALL     	4 2 2
	8	[105]	GETTABLE 	5 0 -4	; "dimen"
	9	[105]	TEST     	5 0 1
	10	[105]	JMP      	9	; to 20
	11	[106]	GETUPVAL 	5 0	; Geom
	12	[106]	SELF     	5 5 -5	; "new"
	13	[106]	NEWTABLE 	7 0 2
	14	[106]	GETTABLE 	8 4 -6	; "w"
	15	[106]	SETTABLE 	7 -6 8	; "w" -
	16	[106]	GETTABLE 	8 4 -7	; "h"
	17	[106]	SETTABLE 	7 -7 8	; "h" -
	18	[106]	CALL     	5 3 2
	19	[106]	SETTABLE 	0 -4 5	; "dimen" -
	20	[109]	SETTABLE 	0 -8 2	; "_orig_x" -
	21	[110]	SETTABLE 	0 -9 3	; "_orig_y" -
	22	[112]	GETTABLE 	5 0 -4	; "dimen"
	23	[112]	GETTABLE 	6 0 -11	; "_moved_offset_x"
	24	[112]	ADD      	6 2 6
	25	[112]	SETTABLE 	5 -10 6	; "x" -
	26	[113]	GETTABLE 	5 0 -4	; "dimen"
	27	[113]	GETTABLE 	6 0 -13	; "_moved_offset_y"
	28	[113]	ADD      	6 3 6
	29	[113]	SETTABLE 	5 -12 6	; "y" -
	30	[115]	GETTABLE 	5 0 -14	; "alpha"
	31	[115]	TEST     	5 0 0
	32	[115]	JMP      	40	; to 73
	33	[117]	GETUPVAL 	5 1	; BlitBuffer
	34	[117]	GETTABLE 	5 5 -5	; "new"
	35	[117]	SELF     	6 1 -15	; "getWidth"
	36	[117]	CALL     	6 2 2
	37	[117]	SELF     	7 1 -16	; "getHeight"
	38	[117]	CALL     	7 2 2
	39	[117]	SELF     	8 1 -17	; "getType"
	40	[117]	CALL     	8 2 0
	41	[117]	CALL     	5 0 2
	42	[118]	SELF     	6 5 -18	; "fill"
	43	[118]	GETUPVAL 	8 1	; BlitBuffer
	44	[118]	GETTABLE 	8 8 -19	; "COLOR_WHITE"
	45	[118]	CALL     	6 3 1
	46	[119]	GETTABLE 	6 0 -1	; 1
	47	[119]	SELF     	6 6 -20	; "paintTo"
	48	[119]	MOVE     	8 5
	49	[119]	GETTABLE 	9 0 -4	; "dimen"
	50	[119]	GETTABLE 	9 9 -10	; "x"
	51	[119]	GETTABLE 	10 0 -4	; "dimen"
	52	[119]	GETTABLE 	10 10 -12	; "y"
	53	[119]	CALL     	6 5 1
	54	[121]	SELF     	6 1 -21	; "addblitFrom"
	55	[121]	MOVE     	8 5
	56	[121]	GETTABLE 	9 0 -4	; "dimen"
	57	[121]	GETTABLE 	9 9 -10	; "x"
	58	[121]	GETTABLE 	10 0 -4	; "dimen"
	59	[121]	GETTABLE 	10 10 -12	; "y"
	60	[121]	GETTABLE 	11 0 -4	; "dimen"
	61	[121]	GETTABLE 	11 11 -10	; "x"
	62	[121]	GETTABLE 	12 0 -4	; "dimen"
	63	[121]	GETTABLE 	12 12 -12	; "y"
	64	[122]	GETTABLE 	13 0 -4	; "dimen"
	65	[122]	GETTABLE 	13 13 -6	; "w"
	66	[122]	GETTABLE 	14 0 -4	; "dimen"
	67	[122]	GETTABLE 	14 14 -7	; "h"
	68	[122]	GETTABLE 	15 0 -14	; "alpha"
	69	[121]	CALL     	6 10 1
	70	[123]	SELF     	6 5 -22	; "free"
	71	[123]	CALL     	6 2 1
	72	[123]	JMP      	8	; to 81
	73	[126]	GETTABLE 	5 0 -1	; 1
	74	[126]	SELF     	5 5 -20	; "paintTo"
	75	[126]	MOVE     	7 1
	76	[126]	GETTABLE 	8 0 -4	; "dimen"
	77	[126]	GETTABLE 	8 8 -10	; "x"
	78	[126]	GETTABLE 	9 0 -4	; "dimen"
	79	[126]	GETTABLE 	9 9 -12	; "y"
	80	[126]	CALL     	5 5 1
	81	[128]	RETURN   	0 1

function <./frontend/ui/widget/container/movablecontainer.lua:130,188> (119 instructions, 476 bytes at 0x7fd421408110)
4 params, 9 slots, 4 upvalues, 7 locals, 20 constants, 1 function
	1	[131]	GETUPVAL 	4 0	; logger
	2	[131]	GETTABLE 	4 4 -1	; "dbg"
	3	[131]	LOADK    	5 -2	; "MovableContainer:_moveBy:"
	4	[131]	MOVE     	6 1
	5	[131]	MOVE     	7 2
	6	[131]	CALL     	4 4 1
	7	[132]	TEST     	1 0 0
	8	[132]	JMP      	79	; to 88
	9	[132]	TEST     	2 0 0
	10	[132]	JMP      	77	; to 88
	11	[133]	GETTABLE 	4 0 -3	; "_moved_offset_x"
	12	[133]	GETUPVAL 	5 1	; Math
	13	[133]	GETTABLE 	5 5 -4	; "round"
	14	[133]	MOVE     	6 1
	15	[133]	CALL     	5 2 2
	16	[133]	ADD      	4 4 5
	17	[133]	SETTABLE 	0 -3 4	; "_moved_offset_x" -
	18	[134]	GETTABLE 	4 0 -5	; "_moved_offset_y"
	19	[134]	GETUPVAL 	5 1	; Math
	20	[134]	GETTABLE 	5 5 -4	; "round"
	21	[134]	MOVE     	6 2
	22	[134]	CALL     	5 2 2
	23	[134]	ADD      	4 4 5
	24	[134]	SETTABLE 	0 -5 4	; "_moved_offset_y" -
	25	[135]	TEST     	3 0 0
	26	[135]	JMP      	50	; to 77
	27	[136]	GETUPVAL 	4 2	; Screen
	28	[136]	SELF     	4 4 -6	; "getWidth"
	29	[136]	CALL     	4 2 2
	30	[136]	GETUPVAL 	5 2	; Screen
	31	[136]	SELF     	5 5 -7	; "getHeight"
	32	[136]	CALL     	5 2 2
	33	[137]	GETTABLE 	6 0 -8	; "_orig_x"
	34	[137]	GETTABLE 	7 0 -3	; "_moved_offset_x"
	35	[137]	ADD      	6 6 7
	36	[137]	LT       	0 6 -9	; - 0
	37	[137]	JMP      	3	; to 41
	38	[138]	GETTABLE 	6 0 -8	; "_orig_x"
	39	[138]	UNM      	6 6
	40	[138]	SETTABLE 	0 -3 6	; "_moved_offset_x" -
	41	[140]	GETTABLE 	6 0 -10	; "_orig_y"
	42	[140]	GETTABLE 	7 0 -5	; "_moved_offset_y"
	43	[140]	ADD      	6 6 7
	44	[140]	LT       	0 6 -9	; - 0
	45	[140]	JMP      	3	; to 49
	46	[141]	GETTABLE 	6 0 -10	; "_orig_y"
	47	[141]	UNM      	6 6
	48	[141]	SETTABLE 	0 -5 6	; "_moved_offset_y" -
	49	[143]	GETTABLE 	6 0 -8	; "_orig_x"
	50	[143]	GETTABLE 	7 0 -3	; "_moved_offset_x"
	51	[143]	ADD      	6 6 7
	52	[143]	GETTABLE 	7 0 -11	; "dimen"
	53	[143]	GETTABLE 	7 7 -12	; "w"
	54	[143]	ADD      	6 6 7
	55	[143]	LT       	0 4 6
	56	[143]	JMP      	6	; to 63
	57	[144]	GETTABLE 	6 0 -8	; "_orig_x"
	58	[144]	SUB      	6 4 6
	59	[144]	GETTABLE 	7 0 -11	; "dimen"
	60	[144]	GETTABLE 	7 7 -12	; "w"
	61	[144]	SUB      	6 6 7
	62	[144]	SETTABLE 	0 -3 6	; "_moved_offset_x" -
	63	[146]	GETTABLE 	6 0 -10	; "_orig_y"
	64	[146]	GETTABLE 	7 0 -5	; "_moved_offset_y"
	65	[146]	ADD      	6 6 7
	66	[146]	GETTABLE 	7 0 -11	; "dimen"
	67	[146]	GETTABLE 	7 7 -13	; "h"
	68	[146]	ADD      	6 6 7
	69	[146]	LT       	0 5 6
	70	[146]	JMP      	6	; to 77
	71	[147]	GETTABLE 	6 0 -10	; "_orig_y"
	72	[147]	SUB      	6 5 6
	73	[147]	GETTABLE 	7 0 -11	; "dimen"
	74	[147]	GETTABLE 	7 7 -13	; "h"
	75	[147]	SUB      	6 6 7
	76	[147]	SETTABLE 	0 -5 6	; "_moved_offset_y" -
	77	[151]	GETUPVAL 	4 1	; Math
	78	[151]	GETTABLE 	4 4 -4	; "round"
	79	[151]	GETTABLE 	5 0 -3	; "_moved_offset_x"
	80	[151]	CALL     	4 2 2
	81	[151]	SETTABLE 	0 -3 4	; "_moved_offset_x" -
	82	[152]	GETUPVAL 	4 1	; Math
	83	[152]	GETTABLE 	4 4 -4	; "round"
	84	[152]	GETTABLE 	5 0 -5	; "_moved_offset_y"
	85	[152]	CALL     	4 2 2
	86	[152]	SETTABLE 	0 -5 4	; "_moved_offset_y" -
	87	[152]	JMP      	20	; to 108
	88	[159]	GETTABLE 	4 0 -3	; "_moved_offset_x"
	89	[159]	EQ       	0 4 -9	; - 0
	90	[159]	JMP      	15	; to 106
	91	[159]	GETTABLE 	4 0 -5	; "_moved_offset_y"
	92	[159]	EQ       	0 4 -9	; - 0
	93	[159]	JMP      	12	; to 106
	94	[162]	GETTABLE 	4 0 -14	; "alpha"
	95	[162]	TEST     	4 0 0
	96	[162]	JMP      	4	; to 101
	97	[163]	GETTABLE 	4 0 -14	; "alpha"
	98	[163]	SETTABLE 	0 -15 4	; "orig_alpha" -
	99	[164]	SETTABLE 	0 -14 -16	; "alpha" nil
	100	[164]	JMP      	5	; to 106
	101	[166]	GETTABLE 	4 0 -15	; "orig_alpha"
	102	[166]	TEST     	4 0 1
	103	[166]	JMP      	1	; to 105
	104	[166]	LOADK    	4 -17	; 0.7
	105	[166]	SETTABLE 	0 -14 4	; "alpha" -
	106	[177]	SETTABLE 	0 -3 -9	; "_moved_offset_x" 0
	107	[178]	SETTABLE 	0 -5 -9	; "_moved_offset_y" 0
	108	[182]	GETTABLE 	4 0 -11	; "dimen"
	109	[182]	SELF     	4 4 -18	; "copy"
	110	[182]	CALL     	4 2 2
	111	[183]	GETUPVAL 	5 3	; UIManager
	112	[183]	SELF     	5 5 -19	; "setDirty"
	113	[183]	LOADK    	7 -20	; "all"
	114	[187]	CLOSURE  	8 0	; 0x7fd421408a60
	115	[187]	MOVE     	0 4
	116	[187]	MOVE     	0 0
	117	[187]	GETUPVAL 	0 0	; logger
	118	[183]	CALL     	5 4 1
	119	[188]	RETURN   	0 1

function <./frontend/ui/widget/container/movablecontainer.lua:183,187> (14 instructions, 56 bytes at 0x7fd421408a60)
0 params, 4 slots, 3 upvalues, 1 local, 5 constants, 0 functions
	1	[184]	GETUPVAL 	0 0	; orig_dimen
	2	[184]	SELF     	0 0 -1	; "combine"
	3	[184]	GETUPVAL 	2 1	; self
	4	[184]	GETTABLE 	2 2 -2	; "dimen"
	5	[184]	CALL     	0 3 2
	6	[185]	GETUPVAL 	1 2	; logger
	7	[185]	GETTABLE 	1 1 -3	; "dbg"
	8	[185]	LOADK    	2 -4	; "MovableContainer refresh region"
	9	[185]	MOVE     	3 0
	10	[185]	CALL     	1 3 1
	11	[186]	LOADK    	1 -5	; "ui"
	12	[186]	MOVE     	2 0
	13	[186]	RETURN   	1 3
	14	[187]	RETURN   	0 1

function <./frontend/ui/widget/container/movablecontainer.lua:190,213> (90 instructions, 360 bytes at 0x7fd421409490)
3 params, 11 slots, 1 upvalue, 6 locals, 23 constants, 0 functions
	1	[191]	GETUPVAL 	3 0	; logger
	2	[191]	GETTABLE 	3 3 -1	; "dbg"
	3	[191]	LOADK    	4 -2	; "MovableContainer:onMovableSwipe"
	4	[191]	MOVE     	5 2
	5	[191]	CALL     	3 3 1
	6	[192]	GETTABLE 	3 2 -3	; "pos"
	7	[192]	SELF     	3 3 -4	; "intersectWith"
	8	[192]	GETTABLE 	5 0 -5	; "dimen"
	9	[192]	CALL     	3 3 2
	10	[192]	TEST     	3 0 1
	11	[192]	JMP      	2	; to 14
	12	[195]	LOADBOOL 	3 0 0
	13	[195]	RETURN   	3 2
	14	[197]	SETTABLE 	0 -6 -7	; "_moving" false
	15	[198]	GETTABLE 	3 2 -8	; "direction"
	16	[199]	GETTABLE 	4 2 -9	; "distance"
	17	[200]	GETGLOBAL	5 -10	; math
	18	[200]	GETTABLE 	5 5 -11	; "floor"
	19	[200]	GETGLOBAL	6 -10	; math
	20	[200]	GETTABLE 	6 6 -12	; "sqrt"
	21	[200]	MUL      	7 4 4
	22	[200]	DIV      	7 7 -13	; - 2
	23	[200]	CALL     	6 2 0
	24	[200]	CALL     	5 0 2
	25	[203]	EQ       	0 3 -14	; - "north"
	26	[203]	JMP      	6	; to 33
	27	[203]	SELF     	6 0 -15	; "_moveBy"
	28	[203]	LOADK    	8 -16	; 0
	29	[203]	UNM      	9 4
	30	[203]	LOADBOOL 	10 1 0
	31	[203]	CALL     	6 5 1
	32	[203]	JMP      	55	; to 88
	33	[204]	EQ       	0 3 -17	; - "south"
	34	[204]	JMP      	6	; to 41
	35	[204]	SELF     	6 0 -15	; "_moveBy"
	36	[204]	LOADK    	8 -16	; 0
	37	[204]	MOVE     	9 4
	38	[204]	LOADBOOL 	10 1 0
	39	[204]	CALL     	6 5 1
	40	[204]	JMP      	47	; to 88
	41	[205]	EQ       	0 3 -18	; - "east"
	42	[205]	JMP      	6	; to 49
	43	[205]	SELF     	6 0 -15	; "_moveBy"
	44	[205]	MOVE     	8 4
	45	[205]	LOADK    	9 -16	; 0
	46	[205]	LOADBOOL 	10 1 0
	47	[205]	CALL     	6 5 1
	48	[205]	JMP      	39	; to 88
	49	[206]	EQ       	0 3 -19	; - "west"
	50	[206]	JMP      	6	; to 57
	51	[206]	SELF     	6 0 -15	; "_moveBy"
	52	[206]	UNM      	8 4
	53	[206]	LOADK    	9 -16	; 0
	54	[206]	LOADBOOL 	10 1 0
	55	[206]	CALL     	6 5 1
	56	[206]	JMP      	31	; to 88
	57	[207]	EQ       	0 3 -20	; - "northeast"
	58	[207]	JMP      	6	; to 65
	59	[207]	SELF     	6 0 -15	; "_moveBy"
	60	[207]	MOVE     	8 5
	61	[207]	UNM      	9 5
	62	[207]	LOADBOOL 	10 1 0
	63	[207]	CALL     	6 5 1
	64	[207]	JMP      	23	; to 88
	65	[208]	EQ       	0 3 -21	; - "northwest"
	66	[208]	JMP      	6	; to 73
	67	[208]	SELF     	6 0 -15	; "_moveBy"
	68	[208]	UNM      	8 5
	69	[208]	UNM      	9 5
	70	[208]	LOADBOOL 	10 1 0
	71	[208]	CALL     	6 5 1
	72	[208]	JMP      	15	; to 88
	73	[209]	EQ       	0 3 -22	; - "southeast"
	74	[209]	JMP      	6	; to 81
	75	[209]	SELF     	6 0 -15	; "_moveBy"
	76	[209]	MOVE     	8 5
	77	[209]	MOVE     	9 5
	78	[209]	LOADBOOL 	10 1 0
	79	[209]	CALL     	6 5 1
	80	[209]	JMP      	7	; to 88
	81	[210]	EQ       	0 3 -23	; - "southwest"
	82	[210]	JMP      	5	; to 88
	83	[210]	SELF     	6 0 -15	; "_moveBy"
	84	[210]	UNM      	8 5
	85	[210]	MOVE     	9 5
	86	[210]	LOADBOOL 	10 1 0
	87	[210]	CALL     	6 5 1
	88	[212]	LOADBOOL 	6 1 0
	89	[212]	RETURN   	6 2
	90	[213]	RETURN   	0 1

function <./frontend/ui/widget/container/movablecontainer.lua:215,227> (23 instructions, 92 bytes at 0x7fd421407200)
3 params, 6 slots, 1 upvalue, 3 locals, 12 constants, 0 functions
	1	[218]	GETUPVAL 	3 0	; logger
	2	[218]	GETTABLE 	3 3 -1	; "dbg"
	3	[218]	LOADK    	4 -2	; "MovableContainer:onMovableTouch"
	4	[218]	MOVE     	5 2
	5	[218]	CALL     	3 3 1
	6	[219]	GETTABLE 	3 2 -3	; "pos"
	7	[219]	SELF     	3 3 -4	; "intersectWith"
	8	[219]	GETTABLE 	5 0 -5	; "dimen"
	9	[219]	CALL     	3 3 2
	10	[219]	TEST     	3 0 0
	11	[219]	JMP      	8	; to 20
	12	[220]	SETTABLE 	0 -6 -7	; "_touch_pre_pan_was_inside" true
	13	[221]	GETTABLE 	3 2 -3	; "pos"
	14	[221]	GETTABLE 	3 3 -9	; "x"
	15	[221]	SETTABLE 	0 -8 3	; "_move_relative_x" -
	16	[222]	GETTABLE 	3 2 -3	; "pos"
	17	[222]	GETTABLE 	3 3 -11	; "y"
	18	[222]	SETTABLE 	0 -10 3	; "_move_relative_y" -
	19	[222]	JMP      	1	; to 21
	20	[224]	SETTABLE 	0 -6 -12	; "_touch_pre_pan_was_inside" false
	21	[226]	LOADBOOL 	3 0 0
	22	[226]	RETURN   	3 2
	23	[227]	RETURN   	0 1

function <./frontend/ui/widget/container/movablecontainer.lua:229,238> (23 instructions, 92 bytes at 0x7fd421409930)
3 params, 6 slots, 1 upvalue, 3 locals, 11 constants, 0 functions
	1	[230]	GETUPVAL 	3 0	; logger
	2	[230]	GETTABLE 	3 3 -1	; "dbg"
	3	[230]	LOADK    	4 -2	; "MovableContainer:onMovableHold"
	4	[230]	MOVE     	5 2
	5	[230]	CALL     	3 3 1
	6	[231]	GETTABLE 	3 2 -3	; "pos"
	7	[231]	SELF     	3 3 -4	; "intersectWith"
	8	[231]	GETTABLE 	5 0 -5	; "dimen"
	9	[231]	CALL     	3 3 2
	10	[231]	TEST     	3 0 0
	11	[231]	JMP      	9	; to 21
	12	[232]	SETTABLE 	0 -6 -7	; "_moving" true
	13	[233]	GETTABLE 	3 2 -3	; "pos"
	14	[233]	GETTABLE 	3 3 -9	; "x"
	15	[233]	SETTABLE 	0 -8 3	; "_move_relative_x" -
	16	[234]	GETTABLE 	3 2 -3	; "pos"
	17	[234]	GETTABLE 	3 3 -11	; "y"
	18	[234]	SETTABLE 	0 -10 3	; "_move_relative_y" -
	19	[235]	LOADBOOL 	3 1 0
	20	[235]	RETURN   	3 2
	21	[237]	LOADBOOL 	3 0 0
	22	[237]	RETURN   	3 2
	23	[238]	RETURN   	0 1

function <./frontend/ui/widget/container/movablecontainer.lua:240,249> (24 instructions, 96 bytes at 0x7fd42140a760)
3 params, 6 slots, 1 upvalue, 3 locals, 9 constants, 0 functions
	1	[241]	GETUPVAL 	3 0	; logger
	2	[241]	GETTABLE 	3 3 -1	; "dbg"
	3	[241]	LOADK    	4 -2	; "MovableContainer:onMovableHoldPan"
	4	[241]	MOVE     	5 2
	5	[241]	CALL     	3 3 1
	6	[243]	GETTABLE 	3 2 -3	; "pos"
	7	[243]	SELF     	3 3 -4	; "intersectWith"
	8	[243]	GETTABLE 	5 0 -5	; "dimen"
	9	[243]	CALL     	3 3 2
	10	[243]	TEST     	3 0 1
	11	[243]	JMP      	6	; to 18
	12	[243]	GETTABLE 	3 0 -6	; "_moving"
	13	[243]	TEST     	3 0 1
	14	[243]	JMP      	3	; to 18
	15	[243]	GETTABLE 	3 0 -7	; "_touch_pre_pan_was_inside"
	16	[243]	TEST     	3 0 0
	17	[243]	JMP      	4	; to 22
	18	[244]	SETTABLE 	0 -7 -8	; "_touch_pre_pan_was_inside" false
	19	[245]	SETTABLE 	0 -6 -9	; "_moving" true
	20	[246]	LOADBOOL 	3 1 0
	21	[246]	RETURN   	3 2
	22	[248]	LOADBOOL 	3 0 0
	23	[248]	RETURN   	3 2
	24	[249]	RETURN   	0 1

function <./frontend/ui/widget/container/movablecontainer.lua:251,272> (58 instructions, 232 bytes at 0x7fd42140acb0)
3 params, 7 slots, 1 upvalue, 3 locals, 15 constants, 0 functions
	1	[252]	GETUPVAL 	3 0	; logger
	2	[252]	GETTABLE 	3 3 -1	; "dbg"
	3	[252]	LOADK    	4 -2	; "MovableContainer:onMovableHoldRelease"
	4	[252]	MOVE     	5 2
	5	[252]	CALL     	3 3 1
	6	[253]	GETTABLE 	3 0 -3	; "_moving"
	7	[253]	TEST     	3 0 1
	8	[253]	JMP      	3	; to 12
	9	[253]	GETTABLE 	3 0 -4	; "_touch_pre_pan_was_inside"
	10	[253]	TEST     	3 0 0
	11	[253]	JMP      	44	; to 56
	12	[254]	SETTABLE 	0 -3 -5	; "_moving" false
	13	[255]	GETTABLE 	3 0 -6	; "_move_relative_x"
	14	[255]	TEST     	3 0 0
	15	[255]	JMP      	3	; to 19
	16	[255]	GETTABLE 	3 0 -7	; "_move_relative_y"
	17	[255]	TEST     	3 0 1
	18	[255]	JMP      	2	; to 21
	19	[257]	LOADBOOL 	3 0 0
	20	[257]	RETURN   	3 2
	21	[259]	GETTABLE 	3 2 -8	; "pos"
	22	[259]	GETTABLE 	3 3 -9	; "x"
	23	[259]	GETTABLE 	4 0 -6	; "_move_relative_x"
	24	[259]	SUB      	3 3 4
	25	[259]	SETTABLE 	0 -6 3	; "_move_relative_x" -
	26	[260]	GETTABLE 	3 2 -8	; "pos"
	27	[260]	GETTABLE 	3 3 -10	; "y"
	28	[260]	GETTABLE 	4 0 -7	; "_move_relative_y"
	29	[260]	SUB      	3 3 4
	30	[260]	SETTABLE 	0 -7 3	; "_move_relative_y" -
	31	[261]	GETGLOBAL	3 -11	; math
	32	[261]	GETTABLE 	3 3 -12	; "abs"
	33	[261]	GETTABLE 	4 0 -6	; "_move_relative_x"
	34	[261]	CALL     	3 2 2
	35	[261]	GETTABLE 	4 0 -13	; "move_threshold"
	36	[261]	LT       	0 3 4
	37	[261]	JMP      	10	; to 48
	38	[261]	GETGLOBAL	3 -11	; math
	39	[261]	GETTABLE 	3 3 -12	; "abs"
	40	[261]	GETTABLE 	4 0 -7	; "_move_relative_y"
	41	[261]	CALL     	3 2 2
	42	[261]	GETTABLE 	4 0 -13	; "move_threshold"
	43	[261]	LT       	0 3 4
	44	[261]	JMP      	3	; to 48
	45	[263]	SELF     	3 0 -14	; "_moveBy"
	46	[263]	CALL     	3 2 1
	47	[263]	JMP      	6	; to 54
	48	[265]	SELF     	3 0 -14	; "_moveBy"
	49	[265]	GETTABLE 	5 0 -6	; "_move_relative_x"
	50	[265]	GETTABLE 	6 0 -7	; "_move_relative_y"
	51	[265]	CALL     	3 4 1
	52	[266]	SETTABLE 	0 -6 -15	; "_move_relative_x" nil
	53	[267]	SETTABLE 	0 -7 -15	; "_move_relative_y" nil
	54	[269]	LOADBOOL 	3 1 0
	55	[269]	RETURN   	3 2
	56	[271]	LOADBOOL 	3 0 0
	57	[271]	RETURN   	3 2
	58	[272]	RETURN   	0 1

function <./frontend/ui/widget/container/movablecontainer.lua:274,284> (30 instructions, 120 bytes at 0x7fd42140af80)
3 params, 6 slots, 1 upvalue, 3 locals, 14 constants, 0 functions
	1	[275]	GETUPVAL 	3 0	; logger
	2	[275]	GETTABLE 	3 3 -1	; "dbg"
	3	[275]	LOADK    	4 -2	; "MovableContainer:onMovablePan"
	4	[275]	MOVE     	5 2
	5	[275]	CALL     	3 3 1
	6	[276]	GETTABLE 	3 2 -3	; "pos"
	7	[276]	SELF     	3 3 -4	; "intersectWith"
	8	[276]	GETTABLE 	5 0 -5	; "dimen"
	9	[276]	CALL     	3 3 2
	10	[276]	TEST     	3 0 1
	11	[276]	JMP      	6	; to 18
	12	[276]	GETTABLE 	3 0 -6	; "_moving"
	13	[276]	TEST     	3 0 1
	14	[276]	JMP      	3	; to 18
	15	[276]	GETTABLE 	3 0 -7	; "_touch_pre_pan_was_inside"
	16	[276]	TEST     	3 0 0
	17	[276]	JMP      	10	; to 28
	18	[277]	SETTABLE 	0 -7 -8	; "_touch_pre_pan_was_inside" false
	19	[278]	SETTABLE 	0 -6 -9	; "_moving" true
	20	[279]	GETTABLE 	3 2 -11	; "relative"
	21	[279]	GETTABLE 	3 3 -12	; "x"
	22	[279]	SETTABLE 	0 -10 3	; "_move_relative_x" -
	23	[280]	GETTABLE 	3 2 -11	; "relative"
	24	[280]	GETTABLE 	3 3 -14	; "y"
	25	[280]	SETTABLE 	0 -13 3	; "_move_relative_y" -
	26	[281]	LOADBOOL 	3 1 0
	27	[281]	RETURN   	3 2
	28	[283]	LOADBOOL 	3 0 0
	29	[283]	RETURN   	3 2
	30	[284]	RETURN   	0 1

function <./frontend/ui/widget/container/movablecontainer.lua:286,296> (20 instructions, 80 bytes at 0x7fd42140b2b0)
3 params, 7 slots, 1 upvalue, 3 locals, 8 constants, 0 functions
	1	[287]	GETUPVAL 	3 0	; logger
	2	[287]	GETTABLE 	3 3 -1	; "dbg"
	3	[287]	LOADK    	4 -2	; "MovableContainer:onMovablePanRelease"
	4	[287]	MOVE     	5 2
	5	[287]	CALL     	3 3 1
	6	[288]	GETTABLE 	3 0 -3	; "_moving"
	7	[288]	TEST     	3 0 0
	8	[288]	JMP      	9	; to 18
	9	[289]	SELF     	3 0 -4	; "_moveBy"
	10	[289]	GETTABLE 	5 0 -5	; "_move_relative_x"
	11	[289]	GETTABLE 	6 0 -6	; "_move_relative_y"
	12	[289]	CALL     	3 4 1
	13	[290]	SETTABLE 	0 -3 -7	; "_moving" false
	14	[291]	SETTABLE 	0 -5 -8	; "_move_relative_x" nil
	15	[292]	SETTABLE 	0 -6 -8	; "_move_relative_y" nil
	16	[293]	LOADBOOL 	3 1 0
	17	[293]	RETURN   	3 2
	18	[295]	LOADBOOL 	3 0 0
	19	[295]	RETURN   	3 2
	20	[296]	RETURN   	0 1
