-- BYTECODE -- multiinputdialog.lua:25-131
0001    UGET     1   0      ; InputDialog
0002    TGETS    1   1   0  ; "init"
0003    MOV      2   0
0004    CALL     1   1   2
0005    UGET     1   1      ; VerticalGroup
0006    MOV      2   1
0007    TGETS    1   1   1  ; "new"
0008    TDUP     3   2
0009    TGETS    4   0   3  ; "title_widget"
0010    TSETB    4   3   1
0011    TGETS    4   0   4  ; "title_bar"
0012    TSETB    4   3   2
0013    CALL     1   2   3
0014    TNEW     2   0
0015    USETV    2   2      ; input_field
0016    TNEW     2   0
0017    USETV    3   2      ; input_description
0018    KSHORT   2   0
0019    GGET     3   5      ; "ipairs"
0020    TGETS    4   0   6  ; "fields"
0021    CALL     3   4   2
0022    JMP      6 => 0211
0023 => ADDVN    2   2   0  ; 1
0024    UGET     8   2      ; input_field
0025    UGET     9   4      ; InputText
0026    MOV     10   9
0027    TGETS    9   9   1  ; "new"
0028    TDUP    11   8
0029    TGETS   12   7   7  ; "text"
0030    IST         12
0031    JMP     13 => 0033
0032    KSTR    12   9      ; ""
0033 => TSETS   12  11   7  ; "text"
0034    TGETS   12   7  10  ; "hint"
0035    IST         12
0036    JMP     13 => 0038
0037    KSTR    12   9      ; ""
0038 => TSETS   12  11  10  ; "hint"
0039    TGETS   12   7  11  ; "input_type"
0040    IST         12
0041    JMP     13 => 0043
0042    KSTR    12  12      ; "string"
0043 => TSETS   12  11  11  ; "input_type"
0044    TGETS   12   7  13  ; "text_type"
0045    TSETS   12  11  13  ; "text_type"
0046    TGETS   12   0  14  ; "input_face"
0047    TSETS   12  11  15  ; "face"
0048    TGETS   12   0  16  ; "width"
0049    MULVN   12  12   1  ; 0.9
0050    TSETS   12  11  16  ; "width"
0051    ISNEN    2   0      ; 1
0052    JMP     12 => 0055
0053    KPRI    12   2
0054    JMP     13 => 0056
0055 => KPRI    12   1
0056 => TSETS   12  11  17  ; "focused"
0057    TSETS    0  11  18  ; "parent"
0058    TGETS   12   7  19  ; "padding"
0059    IST         12
0060    JMP     13 => 0062
0061    KPRI    12   0
0062 => TSETS   12  11  19  ; "padding"
0063    TGETS   12   7  20  ; "margin"
0064    IST         12
0065    JMP     13 => 0067
0066    KPRI    12   0
0067 => TSETS   12  11  20  ; "margin"
0068    TGETS   12   7  21  ; "alignment"
0069    IST         12
0070    JMP     13 => 0072
0071    TGETS   12   0  21  ; "alignment"
0072 => TSETS   12  11  21  ; "alignment"
0073    TGETS   12   7  22  ; "justified"
0074    IST         12
0075    JMP     13 => 0077
0076    TGETS   12   0  22  ; "justified"
0077 => TSETS   12  11  22  ; "justified"
0078    TGETS   12   7  23  ; "lang"
0079    IST         12
0080    JMP     13 => 0082
0081    TGETS   12   0  23  ; "lang"
0082 => TSETS   12  11  23  ; "lang"
0083    TGETS   12   7  24  ; "para_direction_rtl"
0084    IST         12
0085    JMP     13 => 0087
0086    TGETS   12   0  24  ; "para_direction_rtl"
0087 => TSETS   12  11  24  ; "para_direction_rtl"
0088    TGETS   12   7  25  ; "auto_para_direction"
0089    IST         12
0090    JMP     13 => 0092
0091    TGETS   12   0  25  ; "auto_para_direction"
0092 => TSETS   12  11  25  ; "auto_para_direction"
0093    TGETS   12   7  26  ; "alignment_strict"
0094    IST         12
0095    JMP     13 => 0097
0096    TGETS   12   0  26  ; "alignment_strict"
0097 => TSETS   12  11  26  ; "alignment_strict"
0098    CALL     9   2   3
0099    TSETV    9   8   2
0100    UGET     8   5      ; Device
0101    MOV      9   8
0102    TGETS    8   8  27  ; "hasDPad"
0103    CALL     8   2   2
0104    ISF          8
0105    JMP      9 => 0118
0106    GGET     8  28      ; "table"
0107    TGETS    8   8  29  ; "insert"
0108    TGETS    9   0  30  ; "button_table"
0109    TGETS    9   9  31  ; "layout"
0110    TGETS   10   0  30  ; "button_table"
0111    TGETS   10  10  31  ; "layout"
0112    LEN     10  10
0113    TNEW    11   3
0114    UGET    12   2      ; input_field
0115    TGETV   12  12   2
0116    TSETB   12  11   1
0117    CALL     8   1   4
0118 => TGETS    8   7  32  ; "description"
0119    ISF          8
0120    JMP      9 => 0180
0121    UGET     8   3      ; input_description
0122    UGET     9   6      ; FrameContainer
0123    MOV     10   9
0124    TGETS    9   9   1  ; "new"
0125    TDUP    11  34
0126    TGETS   12   0  33  ; "description_padding"
0127    TSETS   12  11  19  ; "padding"
0128    TGETS   12   0  35  ; "description_margin"
0129    TSETS   12  11  20  ; "margin"
0130    UGET    12   7      ; TextBoxWidget
0131    MOV     13  12
0132    TGETS   12  12   1  ; "new"
0133    TDUP    14  36
0134    TGETS   15   7  32  ; "description"
0135    TSETS   15  14   7  ; "text"
0136    UGET    15   8      ; Font
0137    MOV     16  15
0138    TGETS   15  15  37  ; "getFace"
0139    KSTR    17  38      ; "x_smallinfofont"
0140    CALL    15   2   3
0141    TSETS   15  14  15  ; "face"
0142    TGETS   15   0  16  ; "width"
0143    MULVN   15  15   1  ; 0.9
0144    TSETS   15  14  16  ; "width"
0145    CALL    12   0   3
0146    TSETM   12   2      ; 1
0147    CALL     9   2   3
0148    TSETV    9   8   2
0149    GGET     8  28      ; "table"
0150    TGETS    8   8  29  ; "insert"
0151    MOV      9   1
0152    UGET    10   9      ; CenterContainer
0153    MOV     11  10
0154    TGETS   10  10   1  ; "new"
0155    TDUP    12  43
0156    UGET    13  10      ; Geom
0157    MOV     14  13
0158    TGETS   13  13   1  ; "new"
0159    TDUP    15  41
0160    TGETS   16   0   4  ; "title_bar"
0161    MOV     17  16
0162    TGETS   16  16  39  ; "getSize"
0163    CALL    16   2   2
0164    TGETS   16  16  40  ; "w"
0165    TSETS   16  15  40  ; "w"
0166    UGET    16   3      ; input_description
0167    TGETV   16  16   2
0168    MOV     17  16
0169    TGETS   16  16  39  ; "getSize"
0170    CALL    16   2   2
0171    TGETS   16  16  42  ; "h"
0172    TSETS   16  15  42  ; "h"
0173    CALL    13   2   3
0174    TSETS   13  12  44  ; "dimen"
0175    UGET    13   3      ; input_description
0176    TGETV   13  13   2
0177    TSETB   13  12   1
0178    CALL    10   0   3
0179    CALLM    8   1   1
0180 => GGET     8  28      ; "table"
0181    TGETS    8   8  29  ; "insert"
0182    MOV      9   1
0183    UGET    10   9      ; CenterContainer
0184    MOV     11  10
0185    TGETS   10  10   1  ; "new"
0186    TDUP    12  46
0187    UGET    13  10      ; Geom
0188    MOV     14  13
0189    TGETS   13  13   1  ; "new"
0190    TDUP    15  45
0191    TGETS   16   0   4  ; "title_bar"
0192    MOV     17  16
0193    TGETS   16  16  39  ; "getSize"
0194    CALL    16   2   2
0195    TGETS   16  16  40  ; "w"
0196    TSETS   16  15  40  ; "w"
0197    UGET    16   2      ; input_field
0198    TGETV   16  16   2
0199    MOV     17  16
0200    TGETS   16  16  39  ; "getSize"
0201    CALL    16   2   2
0202    TGETS   16  16  42  ; "h"
0203    TSETS   16  15  42  ; "h"
0204    CALL    13   2   3
0205    TSETS   13  12  44  ; "dimen"
0206    UGET    13   2      ; input_field
0207    TGETV   13  13   2
0208    TSETB   13  12   1
0209    CALL    10   0   3
0210    CALLM    8   1   1
0211 => ITERC    6   3   3
0212    ITERL    6 => 0023
0213    UGET     3   5      ; Device
0214    MOV      4   3
0215    TGETS    3   3  27  ; "hasDPad"
0216    CALL     3   2   2
0217    ISF          3
0218    JMP      4 => 0225
0219    GGET     3  28      ; "table"
0220    TGETS    3   3  47  ; "remove"
0221    TGETS    4   0  30  ; "button_table"
0222    TGETS    4   4  31  ; "layout"
0223    KSHORT   5   1
0224    CALL     3   1   3
0225 => GGET     3  28      ; "table"
0226    TGETS    3   3  29  ; "insert"
0227    MOV      4   1
0228    UGET     5   9      ; CenterContainer
0229    MOV      6   5
0230    TGETS    5   5   1  ; "new"
0231    TDUP     7  49
0232    UGET     8  10      ; Geom
0233    MOV      9   8
0234    TGETS    8   8   1  ; "new"
0235    TDUP    10  48
0236    TGETS   11   0   4  ; "title_bar"
0237    MOV     12  11
0238    TGETS   11  11  39  ; "getSize"
0239    CALL    11   2   2
0240    TGETS   11  11  40  ; "w"
0241    TSETS   11  10  40  ; "w"
0242    TGETS   11   0  33  ; "description_padding"
0243    TGETS   12   0  35  ; "description_margin"
0244    ADDVV   11  11  12
0245    TSETS   11  10  42  ; "h"
0246    CALL     8   2   3
0247    TSETS    8   7  44  ; "dimen"
0248    UGET     8  11      ; VerticalSpan
0249    MOV      9   8
0250    TGETS    8   8   1  ; "new"
0251    TDUP    10  50
0252    TGETS   11   0  33  ; "description_padding"
0253    TGETS   12   0  35  ; "description_margin"
0254    ADDVV   11  11  12
0255    TSETS   11  10  16  ; "width"
0256    CALL     8   0   3
0257    TSETM    8   2      ; 1
0258    CALL     5   0   3
0259    CALLM    3   1   1
0260    GGET     3  28      ; "table"
0261    TGETS    3   3  29  ; "insert"
0262    MOV      4   1
0263    UGET     5   9      ; CenterContainer
0264    MOV      6   5
0265    TGETS    5   5   1  ; "new"
0266    TDUP     7  52
0267    UGET     8  10      ; Geom
0268    MOV      9   8
0269    TGETS    8   8   1  ; "new"
0270    TDUP    10  51
0271    TGETS   11   0   4  ; "title_bar"
0272    MOV     12  11
0273    TGETS   11  11  39  ; "getSize"
0274    CALL    11   2   2
0275    TGETS   11  11  40  ; "w"
0276    TSETS   11  10  40  ; "w"
0277    TGETS   11   0  30  ; "button_table"
0278    MOV     12  11
0279    TGETS   11  11  39  ; "getSize"
0280    CALL    11   2   2
0281    TGETS   11  11  42  ; "h"
0282    TSETS   11  10  42  ; "h"
0283    CALL     8   2   3
0284    TSETS    8   7  44  ; "dimen"
0285    TGETS    8   0  30  ; "button_table"
0286    TSETB    8   7   1
0287    CALL     5   0   3
0288    CALLM    3   1   1
0289    UGET     3   6      ; FrameContainer
0290    MOV      4   3
0291    TGETS    3   3   1  ; "new"
0292    TDUP     5  56
0293    UGET     6  12      ; Size
0294    TGETS    6   6  54  ; "radius"
0295    TGETS    6   6  55  ; "window"
0296    TSETS    6   5  54  ; "radius"
0297    UGET     6  12      ; Size
0298    TGETS    6   6  57  ; "border"
0299    TGETS    6   6  55  ; "window"
0300    TSETS    6   5  58  ; "bordersize"
0301    UGET     6  13      ; Blitbuffer
0302    TGETS    6   6  59  ; "COLOR_WHITE"
0303    TSETS    6   5  60  ; "background"
0304    TSETB    1   5   1
0305    CALL     3   2   3
0306    TSETS    3   0  53  ; "dialog_frame"
0307    UGET     3   2      ; input_field
0308    TGETB    3   3   1
0309    TSETS    3   0  61  ; "_input_widget"
0310    UGET     3   9      ; CenterContainer
0311    MOV      4   3
0312    TGETS    3   3   1  ; "new"
0313    TDUP     5  66
0314    UGET     6  10      ; Geom
0315    MOV      7   6
0316    TGETS    6   6   1  ; "new"
0317    TDUP     8  63
0318    UGET     9  14      ; Screen
0319    MOV     10   9
0320    TGETS    9   9  62  ; "getWidth"
0321    CALL     9   2   2
0322    TSETS    9   8  40  ; "w"
0323    UGET     9  14      ; Screen
0324    MOV     10   9
0325    TGETS    9   9  64  ; "getHeight"
0326    CALL     9   2   2
0327    TGETS   10   0  61  ; "_input_widget"
0328    MOV     11  10
0329    TGETS   10  10  65  ; "getKeyboardDimen"
0330    CALL    10   2   2
0331    TGETS   10  10  42  ; "h"
0332    SUBVV    9   9  10
0333    TSETS    9   8  42  ; "h"
0334    CALL     6   2   3
0335    TSETS    6   5  44  ; "dimen"
0336    TGETS    6   0  53  ; "dialog_frame"
0337    TSETB    6   5   1
0338    CALL     3   2   3
0339    TSETB    3   0   1
0340    UGET     3  15      ; UIManager
0341    MOV      4   3
0342    TGETS    3   3  67  ; "setDirty"
0343    MOV      5   0
0344    KSTR     6  68      ; "ui"
0345    CALL     3   1   4
0346    RET0     0   1

-- BYTECODE -- multiinputdialog.lua:133-139
0001    TNEW     1   0
0002    KSHORT   2   1
0003    UGET     3   0      ; input_field
0004    LEN      3   3
0005    KSHORT   4   1
0006    FORI     2 => 0015
0007 => GGET     6   0      ; "table"
0008    TGETS    6   6   1  ; "insert"
0009    MOV      7   1
0010    UGET     8   0      ; input_field
0011    TGETV    8   8   5
0012    TGETS    8   8   2  ; "text"
0013    CALL     6   1   3
0014    FORL     2 => 0007
0015 => RET1     1   2

-- BYTECODE -- multiinputdialog.lua:145-147
0001    KSTR     0   0      ; "ui"
0002    UGET     1   0      ; self
0003    TGETS    1   1   1  ; "dialog_frame"
0004    TGETS    1   1   2  ; "dimen"
0005    RET      0   3

-- BYTECODE -- multiinputdialog.lua:141-153
0001    TGETS    2   0   0  ; "_input_widget"
0002    MOV      3   2
0003    TGETS    2   2   1  ; "unfocus"
0004    CALL     2   1   2
0005    TGETS    2   0   0  ; "_input_widget"
0006    MOV      3   2
0007    TGETS    2   2   2  ; "onCloseKeyboard"
0008    CALL     2   1   2
0009    UGET     2   0      ; UIManager
0010    MOV      3   2
0011    TGETS    2   2   3  ; "setDirty"
0012    KPRI     4   0
0013    FNEW     5   4      ; multiinputdialog.lua:145
0014    CALL     2   1   4
0015    TSETS    1   0   0  ; "_input_widget"
0016    TGETS    2   0   0  ; "_input_widget"
0017    MOV      3   2
0018    TGETS    2   2   5  ; "focus"
0019    CALL     2   1   2
0020    TGETS    2   0   0  ; "_input_widget"
0021    MOV      3   2
0022    TGETS    2   2   6  ; "onShowKeyboard"
0023    CALL     2   1   2
0024    UCLO     0 => 0025
0025 => RET0     0   1

-- BYTECODE -- multiinputdialog.lua:0-157
0001    GGET     0   0      ; "require"
0002    KSTR     1   1      ; "ffi/blitbuffer"
0003    CALL     0   2   2
0004    GGET     1   0      ; "require"
0005    KSTR     2   2      ; "ui/widget/container/centercontainer"
0006    CALL     1   2   2
0007    GGET     2   0      ; "require"
0008    KSTR     3   3      ; "device"
0009    CALL     2   2   2
0010    GGET     3   0      ; "require"
0011    KSTR     4   4      ; "ui/font"
0012    CALL     3   2   2
0013    GGET     4   0      ; "require"
0014    KSTR     5   5      ; "ui/widget/container/framecontainer"
0015    CALL     4   2   2
0016    GGET     5   0      ; "require"
0017    KSTR     6   6      ; "ui/geometry"
0018    CALL     5   2   2
0019    GGET     6   0      ; "require"
0020    KSTR     7   7      ; "ui/widget/inputdialog"
0021    CALL     6   2   2
0022    GGET     7   0      ; "require"
0023    KSTR     8   8      ; "ui/widget/inputtext"
0024    CALL     7   2   2
0025    GGET     8   0      ; "require"
0026    KSTR     9   9      ; "ui/size"
0027    CALL     8   2   2
0028    GGET     9   0      ; "require"
0029    KSTR    10  10      ; "ui/widget/textboxwidget"
0030    CALL     9   2   2
0031    GGET    10   0      ; "require"
0032    KSTR    11  11      ; "ui/uimanager"
0033    CALL    10   2   2
0034    GGET    11   0      ; "require"
0035    KSTR    12  12      ; "ui/widget/verticalgroup"
0036    CALL    11   2   2
0037    GGET    12   0      ; "require"
0038    KSTR    13  13      ; "ui/widget/verticalspan"
0039    CALL    12   2   2
0040    GGET    13   0      ; "require"
0041    KSTR    14  14      ; "gettext"
0042    CALL    13   2   2
0043    TGETS   14   2  15  ; "screen"
0044    KNIL    15  16
0045    MOV     18   6
0046    TGETS   17   6  16  ; "extend"
0047    TDUP    19  17
0048    TNEW    20   0
0049    TSETS   20  19  18  ; "fields"
0050    TGETS   20   8  19  ; "padding"
0051    TGETS   20  20  20  ; "default"
0052    TSETS   20  19  21  ; "description_padding"
0053    TGETS   20   8  22  ; "margin"
0054    TGETS   20  20  23  ; "small"
0055    TSETS   20  19  24  ; "description_margin"
0056    CALL    17   2   3
0057    FNEW    18  26      ; multiinputdialog.lua:25
0058    TSETS   18  17  25  ; "init"
0059    FNEW    18  28      ; multiinputdialog.lua:133
0060    TSETS   18  17  27  ; "getFields"
0061    FNEW    18  30      ; multiinputdialog.lua:141
0062    TSETS   18  17  29  ; "onSwitchFocus"
0063    UCLO     0 => 0064
0064 => RET1    17   2

