
main <./frontend/ui/widget/multiinputdialog.lua:0,0> (81 instructions, 324 bytes at 0x7ff5e74068f0)
0+ params, 21 slots, 0 upvalues, 18 locals, 27 constants, 3 functions
	1	[1]	GETGLOBAL	0 -1	; require
	2	[1]	LOADK    	1 -2	; "ffi/blitbuffer"
	3	[1]	CALL     	0 2 2
	4	[2]	GETGLOBAL	1 -1	; require
	5	[2]	LOADK    	2 -3	; "ui/widget/container/centercontainer"
	6	[2]	CALL     	1 2 2
	7	[3]	GETGLOBAL	2 -1	; require
	8	[3]	LOADK    	3 -4	; "device"
	9	[3]	CALL     	2 2 2
	10	[4]	GETGLOBAL	3 -1	; require
	11	[4]	LOADK    	4 -5	; "ui/font"
	12	[4]	CALL     	3 2 2
	13	[5]	GETGLOBAL	4 -1	; require
	14	[5]	LOADK    	5 -6	; "ui/widget/container/framecontainer"
	15	[5]	CALL     	4 2 2
	16	[6]	GETGLOBAL	5 -1	; require
	17	[6]	LOADK    	6 -7	; "ui/geometry"
	18	[6]	CALL     	5 2 2
	19	[7]	GETGLOBAL	6 -1	; require
	20	[7]	LOADK    	7 -8	; "ui/widget/inputdialog"
	21	[7]	CALL     	6 2 2
	22	[8]	GETGLOBAL	7 -1	; require
	23	[8]	LOADK    	8 -9	; "ui/widget/inputtext"
	24	[8]	CALL     	7 2 2
	25	[9]	GETGLOBAL	8 -1	; require
	26	[9]	LOADK    	9 -10	; "ui/size"
	27	[9]	CALL     	8 2 2
	28	[10]	GETGLOBAL	9 -1	; require
	29	[10]	LOADK    	10 -11	; "ui/widget/textboxwidget"
	30	[10]	CALL     	9 2 2
	31	[11]	GETGLOBAL	10 -1	; require
	32	[11]	LOADK    	11 -12	; "ui/uimanager"
	33	[11]	CALL     	10 2 2
	34	[12]	GETGLOBAL	11 -1	; require
	35	[12]	LOADK    	12 -13	; "ui/widget/verticalgroup"
	36	[12]	CALL     	11 2 2
	37	[13]	GETGLOBAL	12 -1	; require
	38	[13]	LOADK    	13 -14	; "ui/widget/verticalspan"
	39	[13]	CALL     	12 2 2
	40	[14]	GETGLOBAL	13 -1	; require
	41	[14]	LOADK    	14 -15	; "gettext"
	42	[14]	CALL     	13 2 2
	43	[15]	GETTABLE 	14 2 -16	; "screen"
	44	[17]	LOADNIL  	15 16
	45	[19]	SELF     	17 6 -17	; "extend"
	46	[19]	NEWTABLE 	19 0 3
	47	[20]	NEWTABLE 	20 0 0
	48	[20]	SETTABLE 	19 -18 20	; "fields" -
	49	[21]	GETTABLE 	20 8 -20	; "padding"
	50	[21]	GETTABLE 	20 20 -21	; "default"
	51	[21]	SETTABLE 	19 -19 20	; "description_padding" -
	52	[22]	GETTABLE 	20 8 -23	; "margin"
	53	[22]	GETTABLE 	20 20 -24	; "small"
	54	[22]	SETTABLE 	19 -22 20	; "description_margin" -
	55	[19]	CALL     	17 3 2
	56	[131]	CLOSURE  	18 0	; 0x7ff5e74070c0
	57	[131]	MOVE     	0 6
	58	[131]	MOVE     	0 11
	59	[131]	MOVE     	0 15
	60	[131]	MOVE     	0 16
	61	[131]	MOVE     	0 7
	62	[131]	MOVE     	0 2
	63	[131]	MOVE     	0 4
	64	[131]	MOVE     	0 9
	65	[131]	MOVE     	0 3
	66	[131]	MOVE     	0 1
	67	[131]	MOVE     	0 5
	68	[131]	MOVE     	0 12
	69	[131]	MOVE     	0 8
	70	[131]	MOVE     	0 0
	71	[131]	MOVE     	0 14
	72	[131]	MOVE     	0 10
	73	[25]	SETTABLE 	17 -25 18	; "init" -
	74	[139]	CLOSURE  	18 1	; 0x7ff5e74071a0
	75	[139]	MOVE     	0 15
	76	[133]	SETTABLE 	17 -26 18	; "getFields" -
	77	[153]	CLOSURE  	18 2	; 0x7ff5e7408610
	78	[153]	MOVE     	0 10
	79	[141]	SETTABLE 	17 -27 18	; "onSwitchFocus" -
	80	[155]	RETURN   	17 2
	81	[155]	RETURN   	0 1

function <./frontend/ui/widget/multiinputdialog.lua:25,131> (322 instructions, 1288 bytes at 0x7ff5e74070c0)
1 param, 18 slots, 16 upvalues, 8 locals, 60 constants, 0 functions
	1	[27]	GETUPVAL 	1 0	; InputDialog
	2	[27]	GETTABLE 	1 1 -1	; "init"
	3	[27]	MOVE     	2 0
	4	[27]	CALL     	1 2 1
	5	[28]	GETUPVAL 	1 1	; VerticalGroup
	6	[28]	SELF     	1 1 -2	; "new"
	7	[28]	NEWTABLE 	3 2 1
	8	[29]	SETTABLE 	3 -3 -4	; "align" "left"
	9	[30]	GETTABLE 	4 0 -5	; "title_widget"
	10	[32]	GETTABLE 	5 0 -6	; "title_bar"
	11	[32]	SETLIST  	3 2 1	; 1
	12	[28]	CALL     	1 3 2
	13	[34]	NEWTABLE 	2 0 0
	14	[34]	SETUPVAL 	2 2	; input_field
	15	[35]	NEWTABLE 	2 0 0
	16	[35]	SETUPVAL 	2 3	; input_description
	17	[36]	LOADK    	2 -7	; 0
	18	[37]	GETGLOBAL	3 -8	; ipairs
	19	[37]	GETTABLE 	4 0 -9	; "fields"
	20	[37]	CALL     	3 2 4
	21	[37]	JMP      	178	; to 200
	22	[38]	ADD      	2 2 -10	; - 1
	23	[39]	GETUPVAL 	8 2	; input_field
	24	[39]	GETUPVAL 	9 4	; InputText
	25	[39]	SELF     	9 9 -2	; "new"
	26	[39]	NEWTABLE 	11 0 17
	27	[40]	GETTABLE 	12 7 -11	; "text"
	28	[40]	TEST     	12 0 1
	29	[40]	JMP      	1	; to 31
	30	[40]	LOADK    	12 -12	; ""
	31	[40]	SETTABLE 	11 -11 12	; "text" -
	32	[41]	GETTABLE 	12 7 -13	; "hint"
	33	[41]	TEST     	12 0 1
	34	[41]	JMP      	1	; to 36
	35	[41]	LOADK    	12 -12	; ""
	36	[41]	SETTABLE 	11 -13 12	; "hint" -
	37	[42]	GETTABLE 	12 7 -14	; "input_type"
	38	[42]	TEST     	12 0 1
	39	[42]	JMP      	1	; to 41
	40	[42]	LOADK    	12 -15	; "string"
	41	[42]	SETTABLE 	11 -14 12	; "input_type" -
	42	[43]	GETTABLE 	12 7 -16	; "text_type"
	43	[43]	SETTABLE 	11 -16 12	; "text_type" -
	44	[44]	GETTABLE 	12 0 -18	; "input_face"
	45	[44]	SETTABLE 	11 -17 12	; "face" -
	46	[45]	GETTABLE 	12 0 -19	; "width"
	47	[45]	MUL      	12 12 -20	; - 0.9
	48	[45]	SETTABLE 	11 -19 12	; "width" -
	49	[46]	EQ       	0 2 -10	; - 1
	50	[46]	JMP      	3	; to 54
	51	[46]	LOADBOOL 	12 1 0
	52	[46]	TEST     	12 0 1
	53	[46]	JMP      	1	; to 55
	54	[46]	LOADBOOL 	12 0 0
	55	[46]	SETTABLE 	11 -21 12	; "focused" -
	56	[47]	SETTABLE 	11 -22 -23	; "scroll" false
	57	[48]	SETTABLE 	11 -24 0	; "parent" -
	58	[49]	GETTABLE 	12 7 -25	; "padding"
	59	[49]	TEST     	12 0 1
	60	[49]	JMP      	1	; to 62
	61	[49]	LOADNIL  	12 12
	62	[49]	SETTABLE 	11 -25 12	; "padding" -
	63	[50]	GETTABLE 	12 7 -26	; "margin"
	64	[50]	TEST     	12 0 1
	65	[50]	JMP      	1	; to 67
	66	[50]	LOADNIL  	12 12
	67	[50]	SETTABLE 	11 -26 12	; "margin" -
	68	[52]	GETTABLE 	12 7 -27	; "alignment"
	69	[52]	TEST     	12 0 1
	70	[52]	JMP      	1	; to 72
	71	[52]	GETTABLE 	12 0 -27	; "alignment"
	72	[52]	SETTABLE 	11 -27 12	; "alignment" -
	73	[53]	GETTABLE 	12 7 -28	; "justified"
	74	[53]	TEST     	12 0 1
	75	[53]	JMP      	1	; to 77
	76	[53]	GETTABLE 	12 0 -28	; "justified"
	77	[53]	SETTABLE 	11 -28 12	; "justified" -
	78	[54]	GETTABLE 	12 7 -29	; "lang"
	79	[54]	TEST     	12 0 1
	80	[54]	JMP      	1	; to 82
	81	[54]	GETTABLE 	12 0 -29	; "lang"
	82	[54]	SETTABLE 	11 -29 12	; "lang" -
	83	[55]	GETTABLE 	12 7 -30	; "para_direction_rtl"
	84	[55]	TEST     	12 0 1
	85	[55]	JMP      	1	; to 87
	86	[55]	GETTABLE 	12 0 -30	; "para_direction_rtl"
	87	[55]	SETTABLE 	11 -30 12	; "para_direction_rtl" -
	88	[56]	GETTABLE 	12 7 -31	; "auto_para_direction"
	89	[56]	TEST     	12 0 1
	90	[56]	JMP      	1	; to 92
	91	[56]	GETTABLE 	12 0 -31	; "auto_para_direction"
	92	[56]	SETTABLE 	11 -31 12	; "auto_para_direction" -
	93	[57]	GETTABLE 	12 7 -32	; "alignment_strict"
	94	[57]	TEST     	12 0 1
	95	[57]	JMP      	1	; to 97
	96	[57]	GETTABLE 	12 0 -32	; "alignment_strict"
	97	[57]	SETTABLE 	11 -32 12	; "alignment_strict" -
	98	[39]	CALL     	9 3 2
	99	[58]	SETTABLE 	8 2 9
	100	[59]	GETUPVAL 	8 5	; Device
	101	[59]	SELF     	8 8 -33	; "hasDPad"
	102	[59]	CALL     	8 2 2
	103	[59]	TEST     	8 0 0
	104	[59]	JMP      	12	; to 117
	105	[61]	GETGLOBAL	8 -34	; table
	106	[61]	GETTABLE 	8 8 -35	; "insert"
	107	[61]	GETTABLE 	9 0 -36	; "button_table"
	108	[61]	GETTABLE 	9 9 -37	; "layout"
	109	[61]	GETTABLE 	10 0 -36	; "button_table"
	110	[61]	GETTABLE 	10 10 -37	; "layout"
	111	[61]	LEN      	10 10
	112	[61]	NEWTABLE 	11 1 0
	113	[61]	GETUPVAL 	12 2	; input_field
	114	[61]	GETTABLE 	12 12 2
	115	[61]	SETLIST  	11 1 1	; 1
	116	[61]	CALL     	8 4 1
	117	[63]	GETTABLE 	8 7 -38	; "description"
	118	[63]	TEST     	8 0 0
	119	[63]	JMP      	53	; to 173
	120	[64]	GETUPVAL 	8 3	; input_description
	121	[64]	GETUPVAL 	9 6	; FrameContainer
	122	[64]	SELF     	9 9 -2	; "new"
	123	[64]	NEWTABLE 	11 0 3
	124	[65]	GETTABLE 	12 0 -39	; "description_padding"
	125	[65]	SETTABLE 	11 -25 12	; "padding" -
	126	[66]	GETTABLE 	12 0 -40	; "description_margin"
	127	[66]	SETTABLE 	11 -26 12	; "margin" -
	128	[67]	SETTABLE 	11 -41 -7	; "bordersize" 0
	129	[68]	GETUPVAL 	12 7	; TextBoxWidget
	130	[68]	SELF     	12 12 -2	; "new"
	131	[68]	NEWTABLE 	14 0 3
	132	[69]	GETTABLE 	15 7 -38	; "description"
	133	[69]	SETTABLE 	14 -11 15	; "text" -
	134	[70]	GETUPVAL 	15 8	; Font
	135	[70]	SELF     	15 15 -42	; "getFace"
	136	[70]	LOADK    	17 -43	; "x_smallinfofont"
	137	[70]	CALL     	15 3 2
	138	[70]	SETTABLE 	14 -17 15	; "face" -
	139	[71]	GETTABLE 	15 0 -19	; "width"
	140	[71]	MUL      	15 15 -20	; - 0.9
	141	[71]	SETTABLE 	14 -19 15	; "width" -
	142	[68]	CALL     	12 3 0
	143	[73]	SETLIST  	11 0 1	; 1
	144	[64]	CALL     	9 3 2
	145	[73]	SETTABLE 	8 2 9
	146	[74]	GETGLOBAL	8 -34	; table
	147	[74]	GETTABLE 	8 8 -35	; "insert"
	148	[74]	MOVE     	9 1
	149	[74]	GETUPVAL 	10 9	; CenterContainer
	150	[74]	SELF     	10 10 -2	; "new"
	151	[74]	NEWTABLE 	12 1 1
	152	[75]	GETUPVAL 	13 10	; Geom
	153	[75]	SELF     	13 13 -2	; "new"
	154	[75]	NEWTABLE 	15 0 2
	155	[76]	GETTABLE 	16 0 -6	; "title_bar"
	156	[76]	SELF     	16 16 -46	; "getSize"
	157	[76]	CALL     	16 2 2
	158	[76]	GETTABLE 	16 16 -45	; "w"
	159	[76]	SETTABLE 	15 -45 16	; "w" -
	160	[77]	GETUPVAL 	16 3	; input_description
	161	[77]	GETTABLE 	16 16 2
	162	[77]	SELF     	16 16 -46	; "getSize"
	163	[77]	CALL     	16 2 2
	164	[77]	GETTABLE 	16 16 -47	; "h"
	165	[77]	SETTABLE 	15 -47 16	; "h" -
	166	[75]	CALL     	13 3 2
	167	[78]	SETTABLE 	12 -44 13	; "dimen" -
	168	[79]	GETUPVAL 	13 3	; input_description
	169	[80]	GETTABLE 	13 13 2
	170	[80]	SETLIST  	12 1 1	; 1
	171	[74]	CALL     	10 3 0
	172	[74]	CALL     	8 0 1
	173	[82]	GETGLOBAL	8 -34	; table
	174	[82]	GETTABLE 	8 8 -35	; "insert"
	175	[82]	MOVE     	9 1
	176	[82]	GETUPVAL 	10 9	; CenterContainer
	177	[82]	SELF     	10 10 -2	; "new"
	178	[82]	NEWTABLE 	12 1 1
	179	[83]	GETUPVAL 	13 10	; Geom
	180	[83]	SELF     	13 13 -2	; "new"
	181	[83]	NEWTABLE 	15 0 2
	182	[84]	GETTABLE 	16 0 -6	; "title_bar"
	183	[84]	SELF     	16 16 -46	; "getSize"
	184	[84]	CALL     	16 2 2
	185	[84]	GETTABLE 	16 16 -45	; "w"
	186	[84]	SETTABLE 	15 -45 16	; "w" -
	187	[85]	GETUPVAL 	16 2	; input_field
	188	[85]	GETTABLE 	16 16 2
	189	[85]	SELF     	16 16 -46	; "getSize"
	190	[85]	CALL     	16 2 2
	191	[85]	GETTABLE 	16 16 -47	; "h"
	192	[85]	SETTABLE 	15 -47 16	; "h" -
	193	[83]	CALL     	13 3 2
	194	[86]	SETTABLE 	12 -44 13	; "dimen" -
	195	[87]	GETUPVAL 	13 2	; input_field
	196	[88]	GETTABLE 	13 13 2
	197	[88]	SETLIST  	12 1 1	; 1
	198	[82]	CALL     	10 3 0
	199	[82]	CALL     	8 0 1
	200	[37]	TFORLOOP 	3 2
	201	[88]	JMP      	-180	; to 22
	202	[91]	GETUPVAL 	3 5	; Device
	203	[91]	SELF     	3 3 -33	; "hasDPad"
	204	[91]	CALL     	3 2 2
	205	[91]	TEST     	3 0 0
	206	[91]	JMP      	6	; to 213
	207	[93]	GETGLOBAL	3 -34	; table
	208	[93]	GETTABLE 	3 3 -48	; "remove"
	209	[93]	GETTABLE 	4 0 -36	; "button_table"
	210	[93]	GETTABLE 	4 4 -37	; "layout"
	211	[93]	LOADK    	5 -10	; 1
	212	[93]	CALL     	3 3 1
	213	[96]	GETGLOBAL	3 -34	; table
	214	[96]	GETTABLE 	3 3 -35	; "insert"
	215	[96]	MOVE     	4 1
	216	[96]	GETUPVAL 	5 9	; CenterContainer
	217	[96]	SELF     	5 5 -2	; "new"
	218	[96]	NEWTABLE 	7 0 1
	219	[97]	GETUPVAL 	8 10	; Geom
	220	[97]	SELF     	8 8 -2	; "new"
	221	[97]	NEWTABLE 	10 0 2
	222	[98]	GETTABLE 	11 0 -6	; "title_bar"
	223	[98]	SELF     	11 11 -46	; "getSize"
	224	[98]	CALL     	11 2 2
	225	[98]	GETTABLE 	11 11 -45	; "w"
	226	[98]	SETTABLE 	10 -45 11	; "w" -
	227	[99]	GETTABLE 	11 0 -39	; "description_padding"
	228	[99]	GETTABLE 	12 0 -40	; "description_margin"
	229	[99]	ADD      	11 11 12
	230	[99]	SETTABLE 	10 -47 11	; "h" -
	231	[97]	CALL     	8 3 2
	232	[100]	SETTABLE 	7 -44 8	; "dimen" -
	233	[101]	GETUPVAL 	8 11	; VerticalSpan
	234	[101]	SELF     	8 8 -2	; "new"
	235	[101]	NEWTABLE 	10 0 1
	236	[101]	GETTABLE 	11 0 -39	; "description_padding"
	237	[101]	GETTABLE 	12 0 -40	; "description_margin"
	238	[101]	ADD      	11 11 12
	239	[101]	SETTABLE 	10 -19 11	; "width" -
	240	[101]	CALL     	8 3 0
	241	[102]	SETLIST  	7 0 1	; 1
	242	[96]	CALL     	5 3 0
	243	[96]	CALL     	3 0 1
	244	[104]	GETGLOBAL	3 -34	; table
	245	[104]	GETTABLE 	3 3 -35	; "insert"
	246	[104]	MOVE     	4 1
	247	[104]	GETUPVAL 	5 9	; CenterContainer
	248	[104]	SELF     	5 5 -2	; "new"
	249	[104]	NEWTABLE 	7 1 1
	250	[105]	GETUPVAL 	8 10	; Geom
	251	[105]	SELF     	8 8 -2	; "new"
	252	[105]	NEWTABLE 	10 0 2
	253	[106]	GETTABLE 	11 0 -6	; "title_bar"
	254	[106]	SELF     	11 11 -46	; "getSize"
	255	[106]	CALL     	11 2 2
	256	[106]	GETTABLE 	11 11 -45	; "w"
	257	[106]	SETTABLE 	10 -45 11	; "w" -
	258	[107]	GETTABLE 	11 0 -36	; "button_table"
	259	[107]	SELF     	11 11 -46	; "getSize"
	260	[107]	CALL     	11 2 2
	261	[107]	GETTABLE 	11 11 -47	; "h"
	262	[107]	SETTABLE 	10 -47 11	; "h" -
	263	[105]	CALL     	8 3 2
	264	[108]	SETTABLE 	7 -44 8	; "dimen" -
	265	[110]	GETTABLE 	8 0 -36	; "button_table"
	266	[110]	SETLIST  	7 1 1	; 1
	267	[104]	CALL     	5 3 0
	268	[104]	CALL     	3 0 1
	269	[112]	GETUPVAL 	3 6	; FrameContainer
	270	[112]	SELF     	3 3 -2	; "new"
	271	[112]	NEWTABLE 	5 1 5
	272	[113]	GETUPVAL 	6 12	; Size
	273	[113]	GETTABLE 	6 6 -50	; "radius"
	274	[113]	GETTABLE 	6 6 -51	; "window"
	275	[113]	SETTABLE 	5 -50 6	; "radius" -
	276	[114]	GETUPVAL 	6 12	; Size
	277	[114]	GETTABLE 	6 6 -52	; "border"
	278	[114]	GETTABLE 	6 6 -51	; "window"
	279	[114]	SETTABLE 	5 -41 6	; "bordersize" -
	280	[115]	SETTABLE 	5 -25 -7	; "padding" 0
	281	[116]	SETTABLE 	5 -26 -7	; "margin" 0
	282	[117]	GETUPVAL 	6 13	; Blitbuffer
	283	[117]	GETTABLE 	6 6 -54	; "COLOR_WHITE"
	284	[117]	SETTABLE 	5 -53 6	; "background" -
	285	[119]	MOVE     	6 1
	286	[119]	SETLIST  	5 1 1	; 1
	287	[112]	CALL     	3 3 2
	288	[119]	SETTABLE 	0 -49 3	; "dialog_frame" -
	289	[121]	GETUPVAL 	3 2	; input_field
	290	[121]	GETTABLE 	3 3 -10	; 1
	291	[121]	SETTABLE 	0 -55 3	; "_input_widget" -
	292	[123]	GETUPVAL 	3 9	; CenterContainer
	293	[123]	SELF     	3 3 -2	; "new"
	294	[123]	NEWTABLE 	5 1 1
	295	[124]	GETUPVAL 	6 10	; Geom
	296	[124]	SELF     	6 6 -2	; "new"
	297	[124]	NEWTABLE 	8 0 2
	298	[125]	GETUPVAL 	9 14	; Screen
	299	[125]	SELF     	9 9 -56	; "getWidth"
	300	[125]	CALL     	9 2 2
	301	[125]	SETTABLE 	8 -45 9	; "w" -
	302	[126]	GETUPVAL 	9 14	; Screen
	303	[126]	SELF     	9 9 -57	; "getHeight"
	304	[126]	CALL     	9 2 2
	305	[126]	GETTABLE 	10 0 -55	; "_input_widget"
	306	[126]	SELF     	10 10 -58	; "getKeyboardDimen"
	307	[126]	CALL     	10 2 2
	308	[126]	GETTABLE 	10 10 -47	; "h"
	309	[126]	SUB      	9 9 10
	310	[126]	SETTABLE 	8 -47 9	; "h" -
	311	[124]	CALL     	6 3 2
	312	[127]	SETTABLE 	5 -44 6	; "dimen" -
	313	[129]	GETTABLE 	6 0 -49	; "dialog_frame"
	314	[129]	SETLIST  	5 1 1	; 1
	315	[123]	CALL     	3 3 2
	316	[129]	SETTABLE 	0 -10 3	; 1 -
	317	[130]	GETUPVAL 	3 15	; UIManager
	318	[130]	SELF     	3 3 -59	; "setDirty"
	319	[130]	MOVE     	5 0
	320	[130]	LOADK    	6 -60	; "ui"
	321	[130]	CALL     	3 4 1
	322	[131]	RETURN   	0 1

function <./frontend/ui/widget/multiinputdialog.lua:133,139> (16 instructions, 64 bytes at 0x7ff5e74071a0)
1 param, 9 slots, 1 upvalue, 6 locals, 4 constants, 0 functions
	1	[134]	NEWTABLE 	1 0 0
	2	[135]	LOADK    	2 -1	; 1
	3	[135]	GETUPVAL 	3 0	; input_field
	4	[135]	LEN      	3 3
	5	[135]	LOADK    	4 -1	; 1
	6	[135]	FORPREP  	2 7	; to 14
	7	[136]	GETGLOBAL	6 -2	; table
	8	[136]	GETTABLE 	6 6 -3	; "insert"
	9	[136]	MOVE     	7 1
	10	[136]	GETUPVAL 	8 0	; input_field
	11	[136]	GETTABLE 	8 8 5
	12	[136]	GETTABLE 	8 8 -4	; "text"
	13	[136]	CALL     	6 3 1
	14	[135]	FORLOOP  	2 -8	; to 7
	15	[138]	RETURN   	1 2
	16	[139]	RETURN   	0 1

function <./frontend/ui/widget/multiinputdialog.lua:141,153> (20 instructions, 80 bytes at 0x7ff5e7408610)
2 params, 6 slots, 1 upvalue, 2 locals, 6 constants, 1 function
	1	[143]	GETTABLE 	2 0 -1	; "_input_widget"
	2	[143]	SELF     	2 2 -2	; "unfocus"
	3	[143]	CALL     	2 2 1
	4	[144]	GETTABLE 	2 0 -1	; "_input_widget"
	5	[144]	SELF     	2 2 -3	; "onCloseKeyboard"
	6	[144]	CALL     	2 2 1
	7	[145]	GETUPVAL 	2 0	; UIManager
	8	[145]	SELF     	2 2 -4	; "setDirty"
	9	[145]	LOADNIL  	4 4
	10	[147]	CLOSURE  	5 0	; 0x7ff5e74089c0
	11	[147]	MOVE     	0 0
	12	[145]	CALL     	2 4 1
	13	[150]	SETTABLE 	0 -1 1	; "_input_widget" -
	14	[151]	GETTABLE 	2 0 -1	; "_input_widget"
	15	[151]	SELF     	2 2 -5	; "focus"
	16	[151]	CALL     	2 2 1
	17	[152]	GETTABLE 	2 0 -1	; "_input_widget"
	18	[152]	SELF     	2 2 -6	; "onShowKeyboard"
	19	[152]	CALL     	2 2 1
	20	[153]	RETURN   	0 1

function <./frontend/ui/widget/multiinputdialog.lua:145,147> (6 instructions, 24 bytes at 0x7ff5e74089c0)
0 params, 2 slots, 1 upvalue, 0 locals, 3 constants, 0 functions
	1	[146]	LOADK    	0 -1	; "ui"
	2	[146]	GETUPVAL 	1 0	; self
	3	[146]	GETTABLE 	1 1 -2	; "dialog_frame"
	4	[146]	GETTABLE 	1 1 -3	; "dimen"
	5	[146]	RETURN   	0 3
	6	[147]	RETURN   	0 1
