
main <./spec/unit/network_manager_spec.lua:0,0> (5 instructions, 20 bytes at 0x7fc4504068d0)
0+ params, 3 slots, 0 upvalues, 0 locals, 2 constants, 1 function
	1	[1]	GETGLOBAL	0 -1	; describe
	2	[1]	LOADK    	1 -2	; "network_manager module"
	3	[77]	CLOSURE  	2 0	; 0x7fc450406b70
	4	[1]	CALL     	0 3 1
	5	[77]	RETURN   	0 1

function <./spec/unit/network_manager_spec.lua:1,77> (36 instructions, 144 bytes at 0x7fc450406b70)
0 params, 9 slots, 0 upvalues, 6 locals, 5 constants, 5 functions
	1	[14]	CLOSURE  	5 0	; 0x7fc450406f00
	2	[14]	MOVE     	0 1
	3	[14]	MOVE     	0 2
	4	[14]	MOVE     	0 3
	5	[14]	MOVE     	0 4
	6	[16]	GETGLOBAL	6 -1	; setup
	7	[49]	CLOSURE  	7 1	; 0x7fc450406e10
	8	[49]	MOVE     	0 0
	9	[49]	MOVE     	0 1
	10	[49]	MOVE     	0 2
	11	[49]	MOVE     	0 3
	12	[49]	MOVE     	0 4
	13	[16]	CALL     	6 2 1
	14	[51]	GETGLOBAL	6 -2	; it
	15	[51]	LOADK    	7 -3	; "should restore wifi in init if wifi was on"
	16	[60]	CLOSURE  	8 2	; 0x7fc450408b60
	17	[60]	MOVE     	0 5
	18	[60]	MOVE     	0 1
	19	[60]	MOVE     	0 2
	20	[60]	MOVE     	0 3
	21	[60]	MOVE     	0 4
	22	[51]	CALL     	6 3 1
	23	[62]	GETGLOBAL	6 -2	; it
	24	[62]	LOADK    	7 -4	; "should not restore wifi in init if wifi was off"
	25	[71]	CLOSURE  	8 3	; 0x7fc450409090
	26	[71]	MOVE     	0 5
	27	[71]	MOVE     	0 1
	28	[71]	MOVE     	0 2
	29	[71]	MOVE     	0 3
	30	[71]	MOVE     	0 4
	31	[62]	CALL     	6 3 1
	32	[73]	GETGLOBAL	6 -5	; teardown
	33	[76]	CLOSURE  	7 4	; 0x7fc4504093d0
	34	[76]	MOVE     	0 0
	35	[73]	CALL     	6 2 1
	36	[77]	RETURN   	0 1

function <./spec/unit/network_manager_spec.lua:8,14> (14 instructions, 56 bytes at 0x7fc450406f00)
0 params, 4 slots, 4 upvalues, 0 locals, 4 constants, 0 functions
	1	[9]	GETGLOBAL	0 -1	; G_reader_settings
	2	[9]	SELF     	0 0 -2	; "saveSetting"
	3	[9]	LOADK    	2 -3	; "auto_restore_wifi"
	4	[9]	LOADBOOL 	3 1 0
	5	[9]	CALL     	0 4 1
	6	[10]	LOADK    	0 -4	; 0
	7	[10]	SETUPVAL 	0 0	; turn_on_wifi_called
	8	[11]	LOADK    	0 -4	; 0
	9	[11]	SETUPVAL 	0 1	; turn_off_wifi_called
	10	[12]	LOADK    	0 -4	; 0
	11	[12]	SETUPVAL 	0 2	; obtain_ip_called
	12	[13]	LOADK    	0 -4	; 0
	13	[13]	SETUPVAL 	0 3	; release_ip_called
	14	[14]	RETURN   	0 1

function <./spec/unit/network_manager_spec.lua:16,49> (15 instructions, 60 bytes at 0x7fc450406e10)
0 params, 2 slots, 5 upvalues, 0 locals, 4 constants, 1 function
	1	[17]	GETGLOBAL	0 -1	; require
	2	[17]	LOADK    	1 -2	; "commonrequire"
	3	[17]	CALL     	0 2 1
	4	[18]	GETGLOBAL	0 -1	; require
	5	[18]	LOADK    	1 -3	; "device"
	6	[18]	CALL     	0 2 2
	7	[18]	SETUPVAL 	0 0	; Device
	8	[19]	GETUPVAL 	0 0	; Device
	9	[48]	CLOSURE  	1 0	; 0x7fc450407220
	10	[48]	GETUPVAL 	0 1	; turn_on_wifi_called
	11	[48]	GETUPVAL 	0 2	; turn_off_wifi_called
	12	[48]	GETUPVAL 	0 3	; obtain_ip_called
	13	[48]	GETUPVAL 	0 4	; release_ip_called
	14	[19]	SETTABLE 	0 -4 1	; "initNetworkManager" -
	15	[49]	RETURN   	0 1

function <./spec/unit/network_manager_spec.lua:19,48> (15 instructions, 60 bytes at 0x7fc450407220)
2 params, 3 slots, 4 upvalues, 2 locals, 5 constants, 5 functions
	1	[25]	CLOSURE  	2 0	; 0x7fc450407b30
	2	[25]	GETUPVAL 	0 0	; turn_on_wifi_called
	3	[20]	SETTABLE 	1 -1 2	; "turnOnWifi" -
	4	[31]	CLOSURE  	2 1	; 0x7fc450407d60
	5	[31]	GETUPVAL 	0 1	; turn_off_wifi_called
	6	[26]	SETTABLE 	1 -2 2	; "turnOffWifi" -
	7	[37]	CLOSURE  	2 2	; 0x7fc4504080d0
	8	[37]	GETUPVAL 	0 2	; obtain_ip_called
	9	[32]	SETTABLE 	1 -3 2	; "obtainIP" -
	10	[43]	CLOSURE  	2 3	; 0x7fc450406660
	11	[43]	GETUPVAL 	0 3	; release_ip_called
	12	[38]	SETTABLE 	1 -4 2	; "releaseIP" -
	13	[47]	CLOSURE  	2 4	; 0x7fc4504084e0
	14	[44]	SETTABLE 	1 -5 2	; "restoreWifiAsync" -
	15	[48]	RETURN   	0 1

function <./spec/unit/network_manager_spec.lua:20,25> (8 instructions, 32 bytes at 0x7fc450407b30)
2 params, 3 slots, 1 upvalue, 2 locals, 1 constant, 0 functions
	1	[21]	GETUPVAL 	2 0	; turn_on_wifi_called
	2	[21]	ADD      	2 2 -1	; - 1
	3	[21]	SETUPVAL 	2 0	; turn_on_wifi_called
	4	[22]	TEST     	1 0 0
	5	[22]	JMP      	2	; to 8
	6	[23]	MOVE     	2 1
	7	[23]	CALL     	2 1 1
	8	[25]	RETURN   	0 1

function <./spec/unit/network_manager_spec.lua:26,31> (8 instructions, 32 bytes at 0x7fc450407d60)
2 params, 3 slots, 1 upvalue, 2 locals, 1 constant, 0 functions
	1	[27]	GETUPVAL 	2 0	; turn_off_wifi_called
	2	[27]	ADD      	2 2 -1	; - 1
	3	[27]	SETUPVAL 	2 0	; turn_off_wifi_called
	4	[28]	TEST     	1 0 0
	5	[28]	JMP      	2	; to 8
	6	[29]	MOVE     	2 1
	7	[29]	CALL     	2 1 1
	8	[31]	RETURN   	0 1

function <./spec/unit/network_manager_spec.lua:32,37> (8 instructions, 32 bytes at 0x7fc4504080d0)
2 params, 3 slots, 1 upvalue, 2 locals, 1 constant, 0 functions
	1	[33]	GETUPVAL 	2 0	; obtain_ip_called
	2	[33]	ADD      	2 2 -1	; - 1
	3	[33]	SETUPVAL 	2 0	; obtain_ip_called
	4	[34]	TEST     	1 0 0
	5	[34]	JMP      	2	; to 8
	6	[35]	MOVE     	2 1
	7	[35]	CALL     	2 1 1
	8	[37]	RETURN   	0 1

function <./spec/unit/network_manager_spec.lua:38,43> (8 instructions, 32 bytes at 0x7fc450406660)
2 params, 3 slots, 1 upvalue, 2 locals, 1 constant, 0 functions
	1	[39]	GETUPVAL 	2 0	; release_ip_called
	2	[39]	ADD      	2 2 -1	; - 1
	3	[39]	SETUPVAL 	2 0	; release_ip_called
	4	[40]	TEST     	1 0 0
	5	[40]	JMP      	2	; to 8
	6	[41]	MOVE     	2 1
	7	[41]	CALL     	2 1 1
	8	[43]	RETURN   	0 1

function <./spec/unit/network_manager_spec.lua:44,47> (5 instructions, 20 bytes at 0x7fc4504084e0)
1 param, 3 slots, 0 upvalues, 1 local, 2 constants, 0 functions
	1	[45]	SELF     	1 0 -1	; "turnOnWifi"
	2	[45]	CALL     	1 2 1
	3	[46]	SELF     	1 0 -2	; "obtainIP"
	4	[46]	CALL     	1 2 1
	5	[47]	RETURN   	0 1

function <./spec/unit/network_manager_spec.lua:51,60> (38 instructions, 152 bytes at 0x7fc450408b60)
0 params, 4 slots, 5 upvalues, 1 local, 13 constants, 0 functions
	1	[52]	GETGLOBAL	0 -1	; package
	2	[52]	GETTABLE 	0 0 -2	; "loaded"
	3	[52]	SETTABLE 	0 -3 -4	; "ui/network/manager" nil
	4	[53]	GETUPVAL 	0 0	; clearState
	5	[53]	CALL     	0 1 1
	6	[54]	GETGLOBAL	0 -5	; G_reader_settings
	7	[54]	SELF     	0 0 -6	; "saveSetting"
	8	[54]	LOADK    	2 -7	; "wifi_was_on"
	9	[54]	LOADBOOL 	3 1 0
	10	[54]	CALL     	0 4 1
	11	[55]	GETGLOBAL	0 -8	; require
	12	[55]	LOADK    	1 -3	; "ui/network/manager"
	13	[55]	CALL     	0 2 2
	14	[56]	GETGLOBAL	1 -9	; assert
	15	[56]	GETTABLE 	1 1 -10	; "is"
	16	[56]	GETTABLE 	1 1 -11	; "same"
	17	[56]	GETUPVAL 	2 1	; turn_on_wifi_called
	18	[56]	LOADK    	3 -12	; 1
	19	[56]	CALL     	1 3 1
	20	[57]	GETGLOBAL	1 -9	; assert
	21	[57]	GETTABLE 	1 1 -10	; "is"
	22	[57]	GETTABLE 	1 1 -11	; "same"
	23	[57]	GETUPVAL 	2 2	; turn_off_wifi_called
	24	[57]	LOADK    	3 -13	; 0
	25	[57]	CALL     	1 3 1
	26	[58]	GETGLOBAL	1 -9	; assert
	27	[58]	GETTABLE 	1 1 -10	; "is"
	28	[58]	GETTABLE 	1 1 -11	; "same"
	29	[58]	GETUPVAL 	2 3	; obtain_ip_called
	30	[58]	LOADK    	3 -12	; 1
	31	[58]	CALL     	1 3 1
	32	[59]	GETGLOBAL	1 -9	; assert
	33	[59]	GETTABLE 	1 1 -10	; "is"
	34	[59]	GETTABLE 	1 1 -11	; "same"
	35	[59]	GETUPVAL 	2 4	; release_ip_called
	36	[59]	LOADK    	3 -13	; 0
	37	[59]	CALL     	1 3 1
	38	[60]	RETURN   	0 1

function <./spec/unit/network_manager_spec.lua:62,71> (38 instructions, 152 bytes at 0x7fc450409090)
0 params, 4 slots, 5 upvalues, 1 local, 12 constants, 0 functions
	1	[63]	GETGLOBAL	0 -1	; package
	2	[63]	GETTABLE 	0 0 -2	; "loaded"
	3	[63]	SETTABLE 	0 -3 -4	; "ui/network/manager" nil
	4	[64]	GETUPVAL 	0 0	; clearState
	5	[64]	CALL     	0 1 1
	6	[65]	GETGLOBAL	0 -5	; G_reader_settings
	7	[65]	SELF     	0 0 -6	; "saveSetting"
	8	[65]	LOADK    	2 -7	; "wifi_was_on"
	9	[65]	LOADBOOL 	3 0 0
	10	[65]	CALL     	0 4 1
	11	[66]	GETGLOBAL	0 -8	; require
	12	[66]	LOADK    	1 -3	; "ui/network/manager"
	13	[66]	CALL     	0 2 2
	14	[67]	GETGLOBAL	1 -9	; assert
	15	[67]	GETTABLE 	1 1 -10	; "is"
	16	[67]	GETTABLE 	1 1 -11	; "same"
	17	[67]	GETUPVAL 	2 1	; turn_on_wifi_called
	18	[67]	LOADK    	3 -12	; 0
	19	[67]	CALL     	1 3 1
	20	[68]	GETGLOBAL	1 -9	; assert
	21	[68]	GETTABLE 	1 1 -10	; "is"
	22	[68]	GETTABLE 	1 1 -11	; "same"
	23	[68]	GETUPVAL 	2 2	; turn_off_wifi_called
	24	[68]	LOADK    	3 -12	; 0
	25	[68]	CALL     	1 3 1
	26	[69]	GETGLOBAL	1 -9	; assert
	27	[69]	GETTABLE 	1 1 -10	; "is"
	28	[69]	GETTABLE 	1 1 -11	; "same"
	29	[69]	GETUPVAL 	2 3	; obtain_ip_called
	30	[69]	LOADK    	3 -12	; 0
	31	[69]	CALL     	1 3 1
	32	[70]	GETGLOBAL	1 -9	; assert
	33	[70]	GETTABLE 	1 1 -10	; "is"
	34	[70]	GETTABLE 	1 1 -11	; "same"
	35	[70]	GETUPVAL 	2 4	; release_ip_called
	36	[70]	LOADK    	3 -12	; 0
	37	[70]	CALL     	1 3 1
	38	[71]	RETURN   	0 1

function <./spec/unit/network_manager_spec.lua:73,76> (7 instructions, 28 bytes at 0x7fc4504093d0)
0 params, 2 slots, 1 upvalue, 0 locals, 5 constants, 1 function
	1	[74]	GETUPVAL 	0 0	; Device
	2	[74]	CLOSURE  	1 0	; 0x7fc450409210
	3	[74]	SETTABLE 	0 -1 1	; "initNetworkManager" -
	4	[75]	GETGLOBAL	0 -2	; package
	5	[75]	GETTABLE 	0 0 -3	; "loaded"
	6	[75]	SETTABLE 	0 -4 -5	; "ui/network/manager" nil
	7	[76]	RETURN   	0 1

function <./spec/unit/network_manager_spec.lua:74,74> (1 instruction, 4 bytes at 0x7fc450409210)
1 param, 2 slots, 0 upvalues, 1 local, 0 constants, 0 functions
	1	[74]	RETURN   	0 1
