
main <./frontend/ui/widget/networksetting.lua:0,0> (208 instructions, 832 bytes at 0x7ff7ba4068e0)
0+ params, 37 slots, 0 upvalues, 33 locals, 58 constants, 16 functions
	1	[33]	GETGLOBAL	0 -1	; require
	2	[33]	LOADK    	1 -2	; "ui/bidi"
	3	[33]	CALL     	0 2 2
	4	[34]	GETGLOBAL	1 -1	; require
	5	[34]	LOADK    	2 -3	; "bit"
	6	[34]	CALL     	1 2 2
	7	[35]	GETGLOBAL	2 -1	; require
	8	[35]	LOADK    	3 -4	; "ffi/blitbuffer"
	9	[35]	CALL     	2 2 2
	10	[36]	GETGLOBAL	3 -1	; require
	11	[36]	LOADK    	4 -5	; "ui/widget/container/centercontainer"
	12	[36]	CALL     	3 2 2
	13	[37]	GETGLOBAL	4 -1	; require
	14	[37]	LOADK    	5 -6	; "device"
	15	[37]	CALL     	4 2 2
	16	[38]	GETGLOBAL	5 -1	; require
	17	[38]	LOADK    	6 -7	; "ui/font"
	18	[38]	CALL     	5 2 2
	19	[39]	GETGLOBAL	6 -1	; require
	20	[39]	LOADK    	7 -8	; "ui/geometry"
	21	[39]	CALL     	6 2 2
	22	[40]	GETGLOBAL	7 -1	; require
	23	[40]	LOADK    	8 -9	; "ui/widget/container/framecontainer"
	24	[40]	CALL     	7 2 2
	25	[41]	GETGLOBAL	8 -1	; require
	26	[41]	LOADK    	9 -10	; "ui/gesturerange"
	27	[41]	CALL     	8 2 2
	28	[42]	GETGLOBAL	9 -1	; require
	29	[42]	LOADK    	10 -11	; "ui/widget/horizontalgroup"
	30	[42]	CALL     	9 2 2
	31	[43]	GETGLOBAL	10 -1	; require
	32	[43]	LOADK    	11 -12	; "ui/widget/horizontalspan"
	33	[43]	CALL     	10 2 2
	34	[44]	GETGLOBAL	11 -1	; require
	35	[44]	LOADK    	12 -13	; "ui/widget/imagewidget"
	36	[44]	CALL     	11 2 2
	37	[45]	GETGLOBAL	12 -1	; require
	38	[45]	LOADK    	13 -14	; "ui/widget/infomessage"
	39	[45]	CALL     	12 2 2
	40	[46]	GETGLOBAL	13 -1	; require
	41	[46]	LOADK    	14 -15	; "ui/widget/container/inputcontainer"
	42	[46]	CALL     	13 2 2
	43	[47]	GETGLOBAL	14 -1	; require
	44	[47]	LOADK    	15 -16	; "ui/widget/inputdialog"
	45	[47]	CALL     	14 2 2
	46	[48]	GETGLOBAL	15 -1	; require
	47	[48]	LOADK    	16 -17	; "ui/widget/container/leftcontainer"
	48	[48]	CALL     	15 2 2
	49	[49]	GETGLOBAL	16 -1	; require
	50	[49]	LOADK    	17 -18	; "ui/widget/listview"
	51	[49]	CALL     	16 2 2
	52	[50]	GETGLOBAL	17 -1	; require
	53	[50]	LOADK    	18 -19	; "ui/widget/container/rightcontainer"
	54	[50]	CALL     	17 2 2
	55	[51]	GETGLOBAL	18 -1	; require
	56	[51]	LOADK    	19 -20	; "ui/network/manager"
	57	[51]	CALL     	18 2 2
	58	[52]	GETGLOBAL	19 -1	; require
	59	[52]	LOADK    	20 -21	; "ui/widget/overlapgroup"
	60	[52]	CALL     	19 2 2
	61	[53]	GETGLOBAL	20 -1	; require
	62	[53]	LOADK    	21 -22	; "ui/size"
	63	[53]	CALL     	20 2 2
	64	[54]	GETGLOBAL	21 -1	; require
	65	[54]	LOADK    	22 -23	; "ui/widget/textwidget"
	66	[54]	CALL     	21 2 2
	67	[55]	GETGLOBAL	22 -1	; require
	68	[55]	LOADK    	23 -24	; "ui/uimanager"
	69	[55]	CALL     	22 2 2
	70	[56]	GETGLOBAL	23 -1	; require
	71	[56]	LOADK    	24 -25	; "ui/widget/verticalgroup"
	72	[56]	CALL     	23 2 2
	73	[57]	GETGLOBAL	24 -1	; require
	74	[57]	LOADK    	25 -26	; "ui/widget/widget"
	75	[57]	CALL     	24 2 2
	76	[58]	GETGLOBAL	25 -1	; require
	77	[58]	LOADK    	26 -27	; "gettext"
	78	[58]	CALL     	25 2 2
	79	[59]	GETGLOBAL	26 -1	; require
	80	[59]	LOADK    	27 -28	; "ffi/util"
	81	[59]	CALL     	26 2 2
	82	[59]	GETTABLE 	26 26 -29	; "template"
	83	[60]	GETTABLE 	27 4 -30	; "screen"
	84	[62]	GETTABLE 	28 1 -31	; "band"
	85	[71]	CLOSURE  	29 0	; 0x7ff7ba4070c0
	86	[71]	MOVE     	0 12
	87	[71]	MOVE     	0 25
	88	[71]	MOVE     	0 22
	89	[71]	MOVE     	0 18
	90	[74]	SELF     	30 24 -32	; "new"
	91	[74]	NEWTABLE 	32 0 3
	92	[75]	SETTABLE 	32 -33 -34	; "width" nil
	93	[76]	SETTABLE 	32 -35 -34	; "height" nil
	94	[77]	SETTABLE 	32 -36 -34	; "progress" nil
	95	[74]	CALL     	30 3 2
	96	[82]	CLOSURE  	31 1	; 0x7ff7ba407250
	97	[82]	MOVE     	0 6
	98	[80]	SETTABLE 	30 -37 31	; "getSize" -
	99	[95]	CLOSURE  	31 2	; 0x7ff7ba4067b0
	100	[95]	MOVE     	0 2
	101	[84]	SETTABLE 	30 -38 31	; "paintTo" -
	102	[97]	CLOSURE  	31 3	; 0x7ff7ba407f50
	103	[97]	SETTABLE 	30 -39 31	; "setProgress" -
	104	[100]	SELF     	31 13 -32	; "new"
	105	[100]	NEWTABLE 	33 0 5
	106	[101]	SETTABLE 	33 -40 -34	; "dimen" nil
	107	[102]	SELF     	34 27 -41	; "scaleBySize"
	108	[102]	LOADK    	36 -42	; 44
	109	[102]	CALL     	34 3 2
	110	[102]	SETTABLE 	33 -35 34	; "height" -
	111	[103]	SETTABLE 	33 -33 -34	; "width" nil
	112	[104]	SETTABLE 	33 -43 -34	; "info" nil
	113	[105]	GETTABLE 	34 2 -45	; "COLOR_WHITE"
	114	[105]	SETTABLE 	33 -44 34	; "background" -
	115	[100]	CALL     	31 3 2
	116	[204]	CLOSURE  	32 4	; 0x7ff7ba408a00
	117	[204]	MOVE     	0 6
	118	[204]	MOVE     	0 10
	119	[204]	MOVE     	0 20
	120	[204]	MOVE     	0 19
	121	[204]	MOVE     	0 15
	122	[204]	MOVE     	0 9
	123	[204]	MOVE     	0 11
	124	[204]	MOVE     	0 21
	125	[204]	MOVE     	0 5
	126	[204]	MOVE     	0 7
	127	[204]	MOVE     	0 25
	128	[204]	MOVE     	0 17
	129	[204]	MOVE     	0 4
	130	[204]	MOVE     	0 8
	131	[108]	SETTABLE 	31 -46 32	; "init" -
	132	[209]	CLOSURE  	32 5	; 0x7ff7ba407680
	133	[209]	MOVE     	0 22
	134	[206]	SETTABLE 	31 -47 32	; "refresh" -
	135	[233]	CLOSURE  	32 6	; 0x7ff7ba409470
	136	[233]	MOVE     	0 18
	137	[233]	MOVE     	0 29
	138	[233]	MOVE     	0 25
	139	[233]	MOVE     	0 22
	140	[233]	MOVE     	0 12
	141	[211]	SETTABLE 	31 -48 32	; "connect" -
	142	[250]	CLOSURE  	32 7	; 0x7ff7ba409a60
	143	[250]	MOVE     	0 12
	144	[250]	MOVE     	0 25
	145	[250]	MOVE     	0 22
	146	[250]	MOVE     	0 18
	147	[235]	SETTABLE 	31 -49 32	; "disconnect" -
	148	[268]	CLOSURE  	32 8	; 0x7ff7ba409d20
	149	[268]	MOVE     	0 22
	150	[268]	MOVE     	0 12
	151	[268]	MOVE     	0 25
	152	[268]	MOVE     	0 18
	153	[252]	SETTABLE 	31 -50 32	; "saveAndConnectToNetwork" -
	154	[310]	CLOSURE  	32 9	; 0x7ff7ba408930
	155	[310]	MOVE     	0 14
	156	[310]	MOVE     	0 25
	157	[310]	MOVE     	0 22
	158	[310]	MOVE     	0 18
	159	[270]	SETTABLE 	31 -51 32	; "onEditNetwork" -
	160	[341]	CLOSURE  	32 10	; 0x7ff7ba40a590
	161	[341]	MOVE     	0 14
	162	[341]	MOVE     	0 25
	163	[341]	MOVE     	0 22
	164	[312]	SETTABLE 	31 -52 32	; "onAddNetwork" -
	165	[365]	CLOSURE  	32 11	; 0x7ff7ba40b120
	166	[365]	MOVE     	0 22
	167	[365]	MOVE     	0 12
	168	[365]	MOVE     	0 25
	169	[343]	SETTABLE 	31 -53 32	; "onTapSelect" -
	170	[368]	SELF     	32 13 -32	; "new"
	171	[368]	NEWTABLE 	34 0 4
	172	[369]	SETTABLE 	34 -33 -34	; "width" nil
	173	[370]	SETTABLE 	34 -35 -34	; "height" nil
	174	[379]	SETTABLE 	34 -54 -34	; "network_list" nil
	175	[380]	SETTABLE 	34 -55 -34	; "connect_callback" nil
	176	[368]	CALL     	32 3 2
	177	[481]	CLOSURE  	33 12	; 0x7ff7ba40bae0
	178	[481]	MOVE     	0 27
	179	[481]	MOVE     	0 2
	180	[481]	MOVE     	0 28
	181	[481]	MOVE     	0 31
	182	[481]	MOVE     	0 21
	183	[481]	MOVE     	0 5
	184	[481]	MOVE     	0 30
	185	[481]	MOVE     	0 7
	186	[481]	MOVE     	0 20
	187	[481]	MOVE     	0 23
	188	[481]	MOVE     	0 16
	189	[481]	MOVE     	0 22
	190	[481]	MOVE     	0 3
	191	[481]	MOVE     	0 4
	192	[481]	MOVE     	0 8
	193	[481]	MOVE     	0 6
	194	[481]	MOVE     	0 29
	195	[481]	MOVE     	0 12
	196	[481]	MOVE     	0 26
	197	[481]	MOVE     	0 25
	198	[481]	MOVE     	0 0
	199	[383]	SETTABLE 	32 -46 33	; "init" -
	200	[485]	CLOSURE  	33 13	; 0x7ff7ba40d330
	201	[483]	SETTABLE 	32 -56 33	; "setConnectedItem" -
	202	[489]	CLOSURE  	33 14	; 0x7ff7ba40d220
	203	[487]	SETTABLE 	32 -57 33	; "getConnectedItem" -
	204	[496]	CLOSURE  	33 15	; 0x7ff7ba40d2b0
	205	[496]	MOVE     	0 22
	206	[491]	SETTABLE 	32 -58 33	; "onTapClose" -
	207	[498]	RETURN   	32 2
	208	[498]	RETURN   	0 1

function <./frontend/ui/widget/networksetting.lua:64,71> (23 instructions, 92 bytes at 0x7ff7ba4070c0)
0 params, 5 slots, 4 upvalues, 1 local, 7 constants, 0 functions
	1	[66]	GETUPVAL 	0 0	; InfoMessage
	2	[66]	SELF     	0 0 -1	; "new"
	3	[66]	NEWTABLE 	2 0 1
	4	[66]	GETUPVAL 	3 1	; _
	5	[66]	LOADK    	4 -3	; "Obtaining IP address\226\128\166"
	6	[66]	CALL     	3 2 2
	7	[66]	SETTABLE 	2 -2 3	; "text" -
	8	[66]	CALL     	0 3 2
	9	[67]	GETUPVAL 	1 2	; UIManager
	10	[67]	SELF     	1 1 -4	; "show"
	11	[67]	MOVE     	3 0
	12	[67]	CALL     	1 3 1
	13	[68]	GETUPVAL 	1 2	; UIManager
	14	[68]	SELF     	1 1 -5	; "forceRePaint"
	15	[68]	CALL     	1 2 1
	16	[69]	GETUPVAL 	1 3	; NetworkMgr
	17	[69]	SELF     	1 1 -6	; "obtainIP"
	18	[69]	CALL     	1 2 1
	19	[70]	GETUPVAL 	1 2	; UIManager
	20	[70]	SELF     	1 1 -7	; "close"
	21	[70]	MOVE     	3 0
	22	[70]	CALL     	1 3 1
	23	[71]	RETURN   	0 1

function <./frontend/ui/widget/networksetting.lua:80,82> (10 instructions, 40 bytes at 0x7ff7ba407250)
1 param, 5 slots, 1 upvalue, 1 local, 5 constants, 0 functions
	1	[81]	GETUPVAL 	1 0	; Geom
	2	[81]	SELF     	1 1 -1	; "new"
	3	[81]	NEWTABLE 	3 0 2
	4	[81]	GETTABLE 	4 0 -3	; "width"
	5	[81]	SETTABLE 	3 -2 4	; "w" -
	6	[81]	GETTABLE 	4 0 -5	; "height"
	7	[81]	SETTABLE 	3 -4 4	; "h" -
	8	[81]	TAILCALL 	1 3 0
	9	[81]	RETURN   	1 0
	10	[82]	RETURN   	0 1

function <./frontend/ui/widget/networksetting.lua:84,95> (34 instructions, 136 bytes at 0x7ff7ba4067b0)
4 params, 11 slots, 1 upvalue, 4 locals, 13 constants, 0 functions
	1	[85]	SELF     	4 0 -2	; "getSize"
	2	[85]	CALL     	4 2 2
	3	[85]	SETTABLE 	0 -1 4	; "dimen" -
	4	[86]	GETTABLE 	4 0 -1	; "dimen"
	5	[86]	GETTABLE 	5 0 -1	; "dimen"
	6	[86]	MOVE     	6 2
	7	[86]	SETTABLE 	5 -4 3	; "y" -
	8	[86]	SETTABLE 	4 -3 6	; "x" -
	9	[88]	SELF     	4 1 -5	; "paintRoundedRect"
	10	[88]	MOVE     	6 2
	11	[88]	MOVE     	7 3
	12	[89]	GETTABLE 	8 0 -1	; "dimen"
	13	[89]	GETTABLE 	8 8 -6	; "w"
	14	[89]	GETTABLE 	9 0 -1	; "dimen"
	15	[89]	GETTABLE 	9 9 -7	; "h"
	16	[90]	GETUPVAL 	10 0	; Blitbuffer
	17	[90]	GETTABLE 	10 10 -8	; "COLOR_LIGHT_GRAY"
	18	[88]	CALL     	4 7 1
	19	[92]	SELF     	4 1 -9	; "paintRect"
	20	[92]	MOVE     	6 2
	21	[92]	MOVE     	7 3
	22	[93]	GETGLOBAL	8 -10	; math
	23	[93]	GETTABLE 	8 8 -11	; "ceil"
	24	[93]	GETTABLE 	9 0 -1	; "dimen"
	25	[93]	GETTABLE 	9 9 -6	; "w"
	26	[93]	GETTABLE 	10 0 -12	; "progress"
	27	[93]	MUL      	9 9 10
	28	[93]	CALL     	8 2 2
	29	[93]	GETTABLE 	9 0 -1	; "dimen"
	30	[93]	GETTABLE 	9 9 -7	; "h"
	31	[94]	GETUPVAL 	10 0	; Blitbuffer
	32	[94]	GETTABLE 	10 10 -13	; "COLOR_DARK_GRAY"
	33	[92]	CALL     	4 7 1
	34	[95]	RETURN   	0 1

function <./frontend/ui/widget/networksetting.lua:97,97> (2 instructions, 8 bytes at 0x7ff7ba407f50)
2 params, 2 slots, 0 upvalues, 2 locals, 1 constant, 0 functions
	1	[97]	SETTABLE 	0 -1 1	; "progress" -
	2	[97]	RETURN   	0 1

function <./frontend/ui/widget/networksetting.lua:108,204> (236 instructions, 944 bytes at 0x7ff7ba408a00)
1 param, 21 slots, 14 upvalues, 3 locals, 53 constants, 0 functions
	1	[109]	GETUPVAL 	1 0	; Geom
	2	[109]	SELF     	1 1 -2	; "new"
	3	[109]	NEWTABLE 	3 0 2
	4	[109]	GETTABLE 	4 0 -4	; "width"
	5	[109]	SETTABLE 	3 -3 4	; "w" -
	6	[109]	GETTABLE 	4 0 -6	; "height"
	7	[109]	SETTABLE 	3 -5 4	; "h" -
	8	[109]	CALL     	1 3 2
	9	[109]	SETTABLE 	0 -1 1	; "dimen" -
	10	[110]	GETTABLE 	1 0 -7	; "info"
	11	[110]	GETTABLE 	1 1 -8	; "ssid"
	12	[110]	TEST     	1 0 1
	13	[110]	JMP      	2	; to 16
	14	[111]	GETTABLE 	1 0 -7	; "info"
	15	[111]	SETTABLE 	1 -8 -9	; "ssid" "[hidden]"
	16	[114]	LOADNIL  	1 1
	17	[115]	GETGLOBAL	2 -10	; string
	18	[115]	GETTABLE 	2 2 -11	; "find"
	19	[115]	GETTABLE 	3 0 -7	; "info"
	20	[115]	GETTABLE 	3 3 -12	; "flags"
	21	[115]	LOADK    	4 -13	; "WPA"
	22	[115]	CALL     	2 3 2
	23	[115]	TEST     	2 0 0
	24	[115]	JMP      	2	; to 27
	25	[116]	LOADK    	1 -14	; "resources/icons/koicon.wifi.secure.%d.medium.png"
	26	[116]	JMP      	1	; to 28
	27	[118]	LOADK    	1 -15	; "resources/icons/koicon.wifi.open.%d.medium.png"
	28	[120]	GETTABLE 	2 0 -7	; "info"
	29	[120]	GETTABLE 	2 2 -16	; "signal_quality"
	30	[120]	EQ       	1 2 -17	; - 0
	31	[120]	JMP      	4	; to 36
	32	[120]	GETTABLE 	2 0 -7	; "info"
	33	[120]	GETTABLE 	2 2 -16	; "signal_quality"
	34	[120]	EQ       	0 2 -18	; - 100
	35	[120]	JMP      	8	; to 44
	36	[121]	GETGLOBAL	2 -10	; string
	37	[121]	GETTABLE 	2 2 -19	; "format"
	38	[121]	MOVE     	3 1
	39	[121]	GETTABLE 	4 0 -7	; "info"
	40	[121]	GETTABLE 	4 4 -16	; "signal_quality"
	41	[121]	CALL     	2 3 2
	42	[121]	MOVE     	1 2
	43	[121]	JMP      	12	; to 56
	44	[123]	GETGLOBAL	2 -10	; string
	45	[123]	GETTABLE 	2 2 -19	; "format"
	46	[124]	MOVE     	3 1
	47	[125]	GETTABLE 	4 0 -7	; "info"
	48	[125]	GETTABLE 	4 4 -16	; "signal_quality"
	49	[125]	ADD      	4 4 -20	; - 25
	50	[125]	GETTABLE 	5 0 -7	; "info"
	51	[125]	GETTABLE 	5 5 -16	; "signal_quality"
	52	[125]	MOD      	5 5 -20
	53	[125]	SUB      	4 4 5
	54	[123]	CALL     	2 3 2
	55	[125]	MOVE     	1 2
	56	[127]	GETUPVAL 	2 1	; HorizontalSpan
	57	[127]	SELF     	2 2 -2	; "new"
	58	[127]	NEWTABLE 	4 0 1
	59	[127]	GETUPVAL 	5 2	; Size
	60	[127]	GETTABLE 	5 5 -21	; "span"
	61	[127]	GETTABLE 	5 5 -22	; "horizontal_default"
	62	[127]	SETTABLE 	4 -4 5	; "width" -
	63	[127]	CALL     	2 3 2
	64	[128]	GETUPVAL 	3 3	; OverlapGroup
	65	[128]	SELF     	3 3 -2	; "new"
	66	[128]	NEWTABLE 	5 0 1
	67	[129]	GETTABLE 	6 0 -1	; "dimen"
	68	[129]	SELF     	6 6 -24	; "copy"
	69	[129]	CALL     	6 2 2
	70	[129]	SETTABLE 	5 -1 6	; "dimen" -
	71	[130]	GETUPVAL 	6 4	; LeftContainer
	72	[130]	SELF     	6 6 -2	; "new"
	73	[130]	NEWTABLE 	8 0 1
	74	[131]	GETTABLE 	9 0 -1	; "dimen"
	75	[131]	SELF     	9 9 -24	; "copy"
	76	[131]	CALL     	9 2 2
	77	[131]	SETTABLE 	8 -1 9	; "dimen" -
	78	[132]	GETUPVAL 	9 5	; HorizontalGroup
	79	[132]	SELF     	9 9 -2	; "new"
	80	[132]	NEWTABLE 	11 3 0
	81	[133]	MOVE     	12 2
	82	[134]	GETUPVAL 	13 6	; ImageWidget
	83	[134]	SELF     	13 13 -2	; "new"
	84	[134]	NEWTABLE 	15 0 2
	85	[135]	SETTABLE 	15 -25 -26	; "alpha" true
	86	[136]	SETTABLE 	15 -27 1	; "file" -
	87	[134]	CALL     	13 3 2
	88	[138]	MOVE     	14 2
	89	[139]	GETUPVAL 	15 7	; TextWidget
	90	[139]	SELF     	15 15 -2	; "new"
	91	[139]	NEWTABLE 	17 0 2
	92	[140]	GETTABLE 	18 0 -7	; "info"
	93	[140]	GETTABLE 	18 18 -8	; "ssid"
	94	[140]	SETTABLE 	17 -28 18	; "text" -
	95	[141]	GETUPVAL 	18 8	; Font
	96	[141]	SELF     	18 18 -30	; "getFace"
	97	[141]	LOADK    	20 -31	; "cfont"
	98	[141]	CALL     	18 3 2
	99	[141]	SETTABLE 	17 -29 18	; "face" -
	100	[139]	CALL     	15 3 0
	101	[143]	SETLIST  	11 0 1	; 1
	102	[132]	CALL     	9 3 0
	103	[144]	SETLIST  	8 0 1	; 1
	104	[130]	CALL     	6 3 0
	105	[145]	SETLIST  	5 0 1	; 1
	106	[128]	CALL     	3 3 2
	107	[145]	SETTABLE 	0 -23 3	; "content_container" -
	108	[146]	SETTABLE 	0 -32 -33	; "btn_disconnect" nil
	109	[147]	SETTABLE 	0 -34 -33	; "btn_edit_nw" nil
	110	[148]	GETTABLE 	3 0 -7	; "info"
	111	[148]	GETTABLE 	3 3 -35	; "connected"
	112	[148]	TEST     	3 0 0
	113	[148]	JMP      	46	; to 160
	114	[149]	GETUPVAL 	3 9	; FrameContainer
	115	[149]	SELF     	3 3 -2	; "new"
	116	[149]	NEWTABLE 	5 0 2
	117	[150]	SETTABLE 	5 -36 -17	; "bordersize" 0
	118	[151]	SETTABLE 	5 -37 -17	; "padding" 0
	119	[152]	GETUPVAL 	6 7	; TextWidget
	120	[152]	SELF     	6 6 -2	; "new"
	121	[152]	NEWTABLE 	8 0 2
	122	[153]	GETUPVAL 	9 10	; _
	123	[153]	LOADK    	10 -38	; "disconnect"
	124	[153]	CALL     	9 2 2
	125	[153]	SETTABLE 	8 -28 9	; "text" -
	126	[154]	GETUPVAL 	9 8	; Font
	127	[154]	SELF     	9 9 -30	; "getFace"
	128	[154]	LOADK    	11 -31	; "cfont"
	129	[154]	CALL     	9 3 2
	130	[154]	SETTABLE 	8 -29 9	; "face" -
	131	[152]	CALL     	6 3 0
	132	[156]	SETLIST  	5 0 1	; 1
	133	[149]	CALL     	3 3 2
	134	[156]	SETTABLE 	0 -32 3	; "btn_disconnect" -
	135	[158]	GETGLOBAL	3 -39	; table
	136	[158]	GETTABLE 	3 3 -40	; "insert"
	137	[158]	GETTABLE 	4 0 -23	; "content_container"
	138	[158]	GETUPVAL 	5 11	; RightContainer
	139	[158]	SELF     	5 5 -2	; "new"
	140	[158]	NEWTABLE 	7 0 1
	141	[159]	GETTABLE 	8 0 -1	; "dimen"
	142	[159]	SELF     	8 8 -24	; "copy"
	143	[159]	CALL     	8 2 2
	144	[159]	SETTABLE 	7 -1 8	; "dimen" -
	145	[160]	GETUPVAL 	8 5	; HorizontalGroup
	146	[160]	SELF     	8 8 -2	; "new"
	147	[160]	NEWTABLE 	10 2 0
	148	[161]	GETTABLE 	11 0 -32	; "btn_disconnect"
	149	[163]	MOVE     	12 2
	150	[163]	SETLIST  	10 2 1	; 1
	151	[160]	CALL     	8 3 0
	152	[164]	SETLIST  	7 0 1	; 1
	153	[158]	CALL     	5 3 0
	154	[158]	CALL     	3 0 1
	155	[165]	GETTABLE 	3 0 -41	; "setting_ui"
	156	[165]	SELF     	3 3 -42	; "setConnectedItem"
	157	[165]	MOVE     	5 0
	158	[165]	CALL     	3 3 1
	159	[165]	JMP      	45	; to 205
	160	[166]	GETTABLE 	3 0 -7	; "info"
	161	[166]	GETTABLE 	3 3 -43	; "password"
	162	[166]	TEST     	3 0 0
	163	[166]	JMP      	41	; to 205
	164	[167]	GETUPVAL 	3 9	; FrameContainer
	165	[167]	SELF     	3 3 -2	; "new"
	166	[167]	NEWTABLE 	5 0 2
	167	[168]	SETTABLE 	5 -36 -17	; "bordersize" 0
	168	[169]	SETTABLE 	5 -37 -17	; "padding" 0
	169	[170]	GETUPVAL 	6 7	; TextWidget
	170	[170]	SELF     	6 6 -2	; "new"
	171	[170]	NEWTABLE 	8 0 2
	172	[171]	GETUPVAL 	9 10	; _
	173	[171]	LOADK    	10 -44	; "edit"
	174	[171]	CALL     	9 2 2
	175	[171]	SETTABLE 	8 -28 9	; "text" -
	176	[172]	GETUPVAL 	9 8	; Font
	177	[172]	SELF     	9 9 -30	; "getFace"
	178	[172]	LOADK    	11 -31	; "cfont"
	179	[172]	CALL     	9 3 2
	180	[172]	SETTABLE 	8 -29 9	; "face" -
	181	[170]	CALL     	6 3 0
	182	[174]	SETLIST  	5 0 1	; 1
	183	[167]	CALL     	3 3 2
	184	[174]	SETTABLE 	0 -34 3	; "btn_edit_nw" -
	185	[176]	GETGLOBAL	3 -39	; table
	186	[176]	GETTABLE 	3 3 -40	; "insert"
	187	[176]	GETTABLE 	4 0 -23	; "content_container"
	188	[176]	GETUPVAL 	5 11	; RightContainer
	189	[176]	SELF     	5 5 -2	; "new"
	190	[176]	NEWTABLE 	7 0 1
	191	[177]	GETTABLE 	8 0 -1	; "dimen"
	192	[177]	SELF     	8 8 -24	; "copy"
	193	[177]	CALL     	8 2 2
	194	[177]	SETTABLE 	7 -1 8	; "dimen" -
	195	[178]	GETUPVAL 	8 5	; HorizontalGroup
	196	[178]	SELF     	8 8 -2	; "new"
	197	[178]	NEWTABLE 	10 2 0
	198	[179]	GETTABLE 	11 0 -34	; "btn_edit_nw"
	199	[181]	MOVE     	12 2
	200	[181]	SETLIST  	10 2 1	; 1
	201	[178]	CALL     	8 3 0
	202	[182]	SETLIST  	7 0 1	; 1
	203	[176]	CALL     	5 3 0
	204	[176]	CALL     	3 0 1
	205	[185]	GETUPVAL 	3 9	; FrameContainer
	206	[185]	SELF     	3 3 -2	; "new"
	207	[185]	NEWTABLE 	5 1 5
	208	[186]	SETTABLE 	5 -37 -17	; "padding" 0
	209	[187]	SETTABLE 	5 -46 -17	; "margin" 0
	210	[188]	GETTABLE 	6 0 -47	; "background"
	211	[188]	SETTABLE 	5 -47 6	; "background" -
	212	[189]	SETTABLE 	5 -36 -17	; "bordersize" 0
	213	[190]	GETTABLE 	6 0 -4	; "width"
	214	[190]	SETTABLE 	5 -4 6	; "width" -
	215	[192]	GETTABLE 	6 0 -23	; "content_container"
	216	[192]	SETLIST  	5 1 1	; 1
	217	[185]	CALL     	3 3 2
	218	[192]	SETTABLE 	0 -45 3	; 1 -
	219	[194]	GETUPVAL 	3 12	; Device
	220	[194]	SELF     	3 3 -48	; "isTouchDevice"
	221	[194]	CALL     	3 2 2
	222	[194]	TEST     	3 0 0
	223	[194]	JMP      	12	; to 236
	224	[195]	NEWTABLE 	3 0 1
	225	[196]	NEWTABLE 	4 0 0
	226	[197]	GETUPVAL 	5 13	; GestureRange
	227	[197]	SELF     	5 5 -2	; "new"
	228	[197]	NEWTABLE 	7 0 2
	229	[198]	SETTABLE 	7 -51 -52	; "ges" "tap"
	230	[199]	GETTABLE 	8 0 -1	; "dimen"
	231	[199]	SETTABLE 	7 -53 8	; "range" -
	232	[197]	CALL     	5 3 0
	233	[201]	SETLIST  	4 0 1	; 1
	234	[201]	SETTABLE 	3 -50 4	; "TapSelect" -
	235	[202]	SETTABLE 	0 -49 3	; "ges_events" -
	236	[204]	RETURN   	0 1

function <./frontend/ui/widget/networksetting.lua:206,209> (9 instructions, 36 bytes at 0x7ff7ba407680)
1 param, 5 slots, 1 upvalue, 1 local, 3 constants, 1 function
	1	[207]	SELF     	1 0 -1	; "init"
	2	[207]	CALL     	1 2 1
	3	[208]	GETUPVAL 	1 0	; UIManager
	4	[208]	SELF     	1 1 -2	; "setDirty"
	5	[208]	GETTABLE 	3 0 -3	; "setting_ui"
	6	[208]	CLOSURE  	4 0	; 0x7ff7ba407800
	7	[208]	MOVE     	0 0
	8	[208]	CALL     	1 4 1
	9	[209]	RETURN   	0 1

function <./frontend/ui/widget/networksetting.lua:208,208> (5 instructions, 20 bytes at 0x7ff7ba407800)
0 params, 2 slots, 1 upvalue, 0 locals, 2 constants, 0 functions
	1	[208]	LOADK    	0 -1	; "ui"
	2	[208]	GETUPVAL 	1 0	; self
	3	[208]	GETTABLE 	1 1 -2	; "dimen"
	4	[208]	RETURN   	0 3
	5	[208]	RETURN   	0 1

function <./frontend/ui/widget/networksetting.lua:211,233> (47 instructions, 188 bytes at 0x7ff7ba409470)
1 param, 10 slots, 5 upvalues, 5 locals, 16 constants, 0 functions
	1	[212]	GETTABLE 	1 0 -1	; "setting_ui"
	2	[212]	SELF     	1 1 -2	; "getConnectedItem"
	3	[212]	CALL     	1 2 2
	4	[213]	TEST     	1 0 0
	5	[213]	JMP      	2	; to 8
	6	[213]	SELF     	2 1 -3	; "disconnect"
	7	[213]	CALL     	2 2 1
	8	[215]	GETUPVAL 	2 0	; NetworkMgr
	9	[215]	SELF     	2 2 -4	; "authenticateNetwork"
	10	[215]	GETTABLE 	4 0 -5	; "info"
	11	[215]	CALL     	2 3 3
	12	[217]	LOADNIL  	4 4
	13	[218]	TEST     	2 0 0
	14	[218]	JMP      	13	; to 28
	15	[219]	GETUPVAL 	5 1	; obtainIP
	16	[219]	CALL     	5 1 1
	17	[220]	GETTABLE 	5 0 -5	; "info"
	18	[220]	SETTABLE 	5 -6 -7	; "connected" true
	19	[221]	GETTABLE 	5 0 -1	; "setting_ui"
	20	[221]	SELF     	5 5 -8	; "setConnectedItem"
	21	[221]	MOVE     	7 0
	22	[221]	CALL     	5 3 1
	23	[222]	GETUPVAL 	5 2	; _
	24	[222]	LOADK    	6 -9	; "Connected."
	25	[222]	CALL     	5 2 2
	26	[222]	MOVE     	4 5
	27	[222]	JMP      	1	; to 29
	28	[224]	MOVE     	4 3
	29	[227]	GETTABLE 	5 0 -1	; "setting_ui"
	30	[227]	GETTABLE 	5 5 -10	; "connect_callback"
	31	[227]	TEST     	5 0 0
	32	[227]	JMP      	3	; to 36
	33	[228]	GETTABLE 	5 0 -1	; "setting_ui"
	34	[228]	GETTABLE 	5 5 -10	; "connect_callback"
	35	[228]	CALL     	5 1 1
	36	[231]	SELF     	5 0 -11	; "refresh"
	37	[231]	CALL     	5 2 1
	38	[232]	GETUPVAL 	5 3	; UIManager
	39	[232]	SELF     	5 5 -12	; "show"
	40	[232]	GETUPVAL 	7 4	; InfoMessage
	41	[232]	SELF     	7 7 -13	; "new"
	42	[232]	NEWTABLE 	9 0 2
	43	[232]	SETTABLE 	9 -14 4	; "text" -
	44	[232]	SETTABLE 	9 -15 -16	; "timeout" 3
	45	[232]	CALL     	7 3 0
	46	[232]	CALL     	5 0 1
	47	[233]	RETURN   	0 1

function <./frontend/ui/widget/networksetting.lua:235,250> (42 instructions, 168 bytes at 0x7ff7ba409a60)
1 param, 6 slots, 4 upvalues, 2 locals, 15 constants, 0 functions
	1	[236]	GETUPVAL 	1 0	; InfoMessage
	2	[236]	SELF     	1 1 -1	; "new"
	3	[236]	NEWTABLE 	3 0 1
	4	[236]	GETUPVAL 	4 1	; _
	5	[236]	LOADK    	5 -3	; "Disconnecting\226\128\166"
	6	[236]	CALL     	4 2 2
	7	[236]	SETTABLE 	3 -2 4	; "text" -
	8	[236]	CALL     	1 3 2
	9	[237]	GETUPVAL 	2 2	; UIManager
	10	[237]	SELF     	2 2 -4	; "show"
	11	[237]	MOVE     	4 1
	12	[237]	CALL     	2 3 1
	13	[238]	GETUPVAL 	2 2	; UIManager
	14	[238]	SELF     	2 2 -5	; "forceRePaint"
	15	[238]	CALL     	2 2 1
	16	[240]	GETUPVAL 	2 3	; NetworkMgr
	17	[240]	SELF     	2 2 -6	; "disconnectNetwork"
	18	[240]	GETTABLE 	4 0 -7	; "info"
	19	[240]	CALL     	2 3 1
	20	[241]	GETUPVAL 	2 3	; NetworkMgr
	21	[241]	SELF     	2 2 -8	; "releaseIP"
	22	[241]	CALL     	2 2 1
	23	[243]	GETUPVAL 	2 2	; UIManager
	24	[243]	SELF     	2 2 -9	; "close"
	25	[243]	MOVE     	4 1
	26	[243]	CALL     	2 3 1
	27	[244]	GETTABLE 	2 0 -7	; "info"
	28	[244]	SETTABLE 	2 -10 -11	; "connected" nil
	29	[245]	SELF     	2 0 -12	; "refresh"
	30	[245]	CALL     	2 2 1
	31	[246]	GETTABLE 	2 0 -13	; "setting_ui"
	32	[246]	SELF     	2 2 -14	; "setConnectedItem"
	33	[246]	LOADNIL  	4 4
	34	[246]	CALL     	2 3 1
	35	[247]	GETTABLE 	2 0 -13	; "setting_ui"
	36	[247]	GETTABLE 	2 2 -15	; "connect_callback"
	37	[247]	TEST     	2 0 0
	38	[247]	JMP      	3	; to 42
	39	[248]	GETTABLE 	2 0 -13	; "setting_ui"
	40	[248]	GETTABLE 	2 2 -15	; "connect_callback"
	41	[248]	CALL     	2 1 1
	42	[250]	RETURN   	0 1

function <./frontend/ui/widget/networksetting.lua:252,268> (41 instructions, 164 bytes at 0x7ff7ba409d20)
2 params, 10 slots, 4 upvalues, 3 locals, 15 constants, 0 functions
	1	[253]	SELF     	2 1 -1	; "getInputText"
	2	[253]	CALL     	2 2 2
	3	[254]	EQ       	1 2 -2	; - nil
	4	[254]	JMP      	6	; to 11
	5	[254]	GETGLOBAL	3 -3	; string
	6	[254]	GETTABLE 	3 3 -4	; "len"
	7	[254]	MOVE     	4 2
	8	[254]	CALL     	3 2 2
	9	[254]	EQ       	0 3 -5	; - 0
	10	[254]	JMP      	12	; to 23
	11	[255]	GETUPVAL 	3 0	; UIManager
	12	[255]	SELF     	3 3 -6	; "show"
	13	[255]	GETUPVAL 	5 1	; InfoMessage
	14	[255]	SELF     	5 5 -7	; "new"
	15	[255]	NEWTABLE 	7 0 1
	16	[256]	GETUPVAL 	8 2	; _
	17	[256]	LOADK    	9 -9	; "Password cannot be empty."
	18	[256]	CALL     	8 2 2
	19	[256]	SETTABLE 	7 -8 8	; "text" -
	20	[255]	CALL     	5 3 0
	21	[255]	CALL     	3 0 1
	22	[257]	JMP      	14	; to 37
	23	[259]	GETTABLE 	3 0 -10	; "info"
	24	[259]	GETTABLE 	3 3 -11	; "password"
	25	[259]	EQ       	1 2 3
	26	[259]	JMP      	8	; to 35
	27	[260]	GETTABLE 	3 0 -10	; "info"
	28	[260]	SETTABLE 	3 -11 2	; "password" -
	29	[261]	GETTABLE 	3 0 -10	; "info"
	30	[261]	SETTABLE 	3 -12 -2	; "psk" nil
	31	[262]	GETUPVAL 	3 3	; NetworkMgr
	32	[262]	SELF     	3 3 -13	; "saveNetwork"
	33	[262]	GETTABLE 	5 0 -10	; "info"
	34	[262]	CALL     	3 3 1
	35	[264]	SELF     	3 0 -14	; "connect"
	36	[264]	CALL     	3 2 1
	37	[267]	GETUPVAL 	3 0	; UIManager
	38	[267]	SELF     	3 3 -15	; "close"
	39	[267]	MOVE     	5 1
	40	[267]	CALL     	3 3 1
	41	[268]	RETURN   	0 1

function <./frontend/ui/widget/networksetting.lua:270,310> (58 instructions, 232 bytes at 0x7ff7ba408930)
1 param, 12 slots, 4 upvalues, 2 locals, 19 constants, 3 functions
	1	[272]	GETUPVAL 	2 0	; InputDialog
	2	[272]	SELF     	2 2 -1	; "new"
	3	[272]	NEWTABLE 	4 0 6
	4	[273]	GETTABLE 	5 0 -3	; "info"
	5	[273]	GETTABLE 	5 5 -4	; "ssid"
	6	[273]	SETTABLE 	4 -2 5	; "title" -
	7	[274]	GETTABLE 	5 0 -3	; "info"
	8	[274]	GETTABLE 	5 5 -6	; "password"
	9	[274]	SETTABLE 	4 -5 5	; "input" -
	10	[275]	SETTABLE 	4 -7 -6	; "input_hint" "password"
	11	[276]	SETTABLE 	4 -8 -9	; "input_type" "text"
	12	[277]	SETTABLE 	4 -10 -6	; "text_type" "password"
	13	[278]	NEWTABLE 	5 1 0
	14	[278]	NEWTABLE 	6 3 0
	15	[279]	NEWTABLE 	7 0 2
	16	[281]	GETUPVAL 	8 1	; _
	17	[281]	LOADK    	9 -12	; "Cancel"
	18	[281]	CALL     	8 2 2
	19	[281]	SETTABLE 	7 -9 8	; "text" -
	20	[284]	CLOSURE  	8 0	; 0x7ff7ba40a460
	21	[284]	GETUPVAL 	0 2	; UIManager
	22	[284]	MOVE     	0 1
	23	[284]	SETTABLE 	7 -13 8	; "callback" -
	24	[285]	NEWTABLE 	8 0 2
	25	[287]	GETUPVAL 	9 1	; _
	26	[287]	LOADK    	10 -14	; "Forget"
	27	[287]	CALL     	9 2 2
	28	[287]	SETTABLE 	8 -9 9	; "text" -
	29	[295]	CLOSURE  	9 1	; 0x7ff7ba40a2a0
	30	[295]	GETUPVAL 	0 3	; NetworkMgr
	31	[295]	MOVE     	0 0
	32	[295]	GETUPVAL 	0 2	; UIManager
	33	[295]	MOVE     	0 1
	34	[295]	SETTABLE 	8 -13 9	; "callback" -
	35	[296]	NEWTABLE 	9 0 3
	36	[298]	GETUPVAL 	10 1	; _
	37	[298]	LOADK    	11 -15	; "Connect"
	38	[298]	CALL     	10 2 2
	39	[298]	SETTABLE 	9 -9 10	; "text" -
	40	[299]	SETTABLE 	9 -16 -17	; "is_enter_default" true
	41	[302]	CLOSURE  	10 2	; 0x7ff7ba40a3e0
	42	[302]	MOVE     	0 0
	43	[302]	MOVE     	0 1
	44	[302]	SETTABLE 	9 -13 10	; "callback" -
	45	[304]	SETLIST  	6 3 1	; 1
	46	[305]	SETLIST  	5 1 1	; 1
	47	[305]	SETTABLE 	4 -11 5	; "buttons" -
	48	[272]	CALL     	2 3 2
	49	[306]	MOVE     	1 2
	50	[307]	GETUPVAL 	2 2	; UIManager
	51	[307]	SELF     	2 2 -18	; "show"
	52	[307]	MOVE     	4 1
	53	[307]	CALL     	2 3 1
	54	[308]	SELF     	2 1 -19	; "onShowKeyboard"
	55	[308]	CALL     	2 2 1
	56	[309]	LOADBOOL 	2 1 0
	57	[309]	RETURN   	2 2
	58	[310]	RETURN   	0 1

function <./frontend/ui/widget/networksetting.lua:282,284> (5 instructions, 20 bytes at 0x7ff7ba40a460)
0 params, 3 slots, 2 upvalues, 0 locals, 1 constant, 0 functions
	1	[283]	GETUPVAL 	0 0	; UIManager
	2	[283]	SELF     	0 0 -1	; "close"
	3	[283]	GETUPVAL 	2 1	; password_input
	4	[283]	CALL     	0 3 1
	5	[284]	RETURN   	0 1

function <./frontend/ui/widget/networksetting.lua:288,295> (22 instructions, 88 bytes at 0x7ff7ba40a2a0)
0 params, 3 slots, 4 upvalues, 0 locals, 10 constants, 0 functions
	1	[289]	GETUPVAL 	0 0	; NetworkMgr
	2	[289]	SELF     	0 0 -1	; "deleteNetwork"
	3	[289]	GETUPVAL 	2 1	; self
	4	[289]	GETTABLE 	2 2 -2	; "info"
	5	[289]	CALL     	0 3 1
	6	[290]	GETUPVAL 	0 1	; self
	7	[290]	GETTABLE 	0 0 -2	; "info"
	8	[290]	SETTABLE 	0 -3 -4	; "password" nil
	9	[292]	GETGLOBAL	0 -5	; table
	10	[292]	GETTABLE 	0 0 -6	; "remove"
	11	[292]	GETUPVAL 	1 1	; self
	12	[292]	GETTABLE 	1 1 -7	; "content_container"
	13	[292]	LOADK    	2 -8	; 2
	14	[292]	CALL     	0 3 1
	15	[293]	GETUPVAL 	0 2	; UIManager
	16	[293]	SELF     	0 0 -9	; "close"
	17	[293]	GETUPVAL 	2 3	; password_input
	18	[293]	CALL     	0 3 1
	19	[294]	GETUPVAL 	0 1	; self
	20	[294]	SELF     	0 0 -10	; "refresh"
	21	[294]	CALL     	0 2 1
	22	[295]	RETURN   	0 1

function <./frontend/ui/widget/networksetting.lua:300,302> (5 instructions, 20 bytes at 0x7ff7ba40a3e0)
0 params, 3 slots, 2 upvalues, 0 locals, 1 constant, 0 functions
	1	[301]	GETUPVAL 	0 0	; self
	2	[301]	SELF     	0 0 -1	; "saveAndConnectToNetwork"
	3	[301]	GETUPVAL 	2 1	; password_input
	4	[301]	CALL     	0 3 1
	5	[302]	RETURN   	0 1

function <./frontend/ui/widget/networksetting.lua:312,341> (45 instructions, 180 bytes at 0x7ff7ba40a590)
1 param, 11 slots, 3 upvalues, 2 locals, 19 constants, 2 functions
	1	[314]	GETUPVAL 	2 0	; InputDialog
	2	[314]	SELF     	2 2 -1	; "new"
	3	[314]	NEWTABLE 	4 0 6
	4	[315]	GETTABLE 	5 0 -3	; "info"
	5	[315]	GETTABLE 	5 5 -4	; "ssid"
	6	[315]	SETTABLE 	4 -2 5	; "title" -
	7	[316]	SETTABLE 	4 -5 -6	; "input" ""
	8	[317]	SETTABLE 	4 -7 -8	; "input_hint" "password"
	9	[318]	SETTABLE 	4 -9 -10	; "input_type" "text"
	10	[319]	SETTABLE 	4 -11 -8	; "text_type" "password"
	11	[320]	NEWTABLE 	5 1 0
	12	[320]	NEWTABLE 	6 2 0
	13	[321]	NEWTABLE 	7 0 2
	14	[323]	GETUPVAL 	8 1	; _
	15	[323]	LOADK    	9 -13	; "Cancel"
	16	[323]	CALL     	8 2 2
	17	[323]	SETTABLE 	7 -10 8	; "text" -
	18	[326]	CLOSURE  	8 0	; 0x7ff7ba40b1a0
	19	[326]	GETUPVAL 	0 2	; UIManager
	20	[326]	MOVE     	0 1
	21	[326]	SETTABLE 	7 -14 8	; "callback" -
	22	[327]	NEWTABLE 	8 0 3
	23	[329]	GETUPVAL 	9 1	; _
	24	[329]	LOADK    	10 -15	; "Connect"
	25	[329]	CALL     	9 2 2
	26	[329]	SETTABLE 	8 -10 9	; "text" -
	27	[330]	SETTABLE 	8 -16 -17	; "is_enter_default" true
	28	[333]	CLOSURE  	9 1	; 0x7ff7ba40b350
	29	[333]	MOVE     	0 0
	30	[333]	MOVE     	0 1
	31	[333]	SETTABLE 	8 -14 9	; "callback" -
	32	[335]	SETLIST  	6 2 1	; 1
	33	[336]	SETLIST  	5 1 1	; 1
	34	[336]	SETTABLE 	4 -12 5	; "buttons" -
	35	[314]	CALL     	2 3 2
	36	[337]	MOVE     	1 2
	37	[338]	GETUPVAL 	2 2	; UIManager
	38	[338]	SELF     	2 2 -18	; "show"
	39	[338]	MOVE     	4 1
	40	[338]	CALL     	2 3 1
	41	[339]	SELF     	2 1 -19	; "onShowKeyboard"
	42	[339]	CALL     	2 2 1
	43	[340]	LOADBOOL 	2 1 0
	44	[340]	RETURN   	2 2
	45	[341]	RETURN   	0 1

function <./frontend/ui/widget/networksetting.lua:324,326> (5 instructions, 20 bytes at 0x7ff7ba40b1a0)
0 params, 3 slots, 2 upvalues, 0 locals, 1 constant, 0 functions
	1	[325]	GETUPVAL 	0 0	; UIManager
	2	[325]	SELF     	0 0 -1	; "close"
	3	[325]	GETUPVAL 	2 1	; password_input
	4	[325]	CALL     	0 3 1
	5	[326]	RETURN   	0 1

function <./frontend/ui/widget/networksetting.lua:331,333> (5 instructions, 20 bytes at 0x7ff7ba40b350)
0 params, 3 slots, 2 upvalues, 0 locals, 1 constant, 0 functions
	1	[332]	GETUPVAL 	0 0	; self
	2	[332]	SELF     	0 0 -1	; "saveAndConnectToNetwork"
	3	[332]	GETUPVAL 	2 1	; password_input
	4	[332]	CALL     	0 3 1
	5	[333]	RETURN   	0 1

function <./frontend/ui/widget/networksetting.lua:343,365> (58 instructions, 232 bytes at 0x7ff7ba40b120)
3 params, 10 slots, 3 upvalues, 3 locals, 19 constants, 0 functions
	1	[344]	GETGLOBAL	3 -1	; string
	2	[344]	GETTABLE 	3 3 -2	; "find"
	3	[344]	GETTABLE 	4 0 -3	; "info"
	4	[344]	GETTABLE 	4 4 -4	; "flags"
	5	[344]	LOADK    	5 -5	; "WPA"
	6	[344]	CALL     	3 3 2
	7	[344]	TEST     	3 0 1
	8	[344]	JMP      	12	; to 21
	9	[345]	GETUPVAL 	3 0	; UIManager
	10	[345]	SELF     	3 3 -6	; "show"
	11	[345]	GETUPVAL 	5 1	; InfoMessage
	12	[345]	SELF     	5 5 -7	; "new"
	13	[345]	NEWTABLE 	7 0 1
	14	[346]	GETUPVAL 	8 2	; _
	15	[346]	LOADK    	9 -9	; "Networks without WPA/WPA2 encryption are not supported."
	16	[346]	CALL     	8 2 2
	17	[346]	SETTABLE 	7 -8 8	; "text" -
	18	[345]	CALL     	5 3 0
	19	[345]	CALL     	3 0 1
	20	[348]	RETURN   	0 1
	21	[350]	GETTABLE 	3 0 -10	; "btn_disconnect"
	22	[350]	TEST     	3 0 0
	23	[350]	JMP      	10	; to 34
	24	[352]	GETTABLE 	3 2 -11	; "pos"
	25	[352]	SELF     	3 3 -12	; "intersectWith"
	26	[352]	GETTABLE 	5 0 -10	; "btn_disconnect"
	27	[352]	GETTABLE 	5 5 -13	; "dimen"
	28	[352]	CALL     	3 3 2
	29	[352]	TEST     	3 0 0
	30	[352]	JMP      	25	; to 56
	31	[353]	SELF     	3 0 -14	; "disconnect"
	32	[353]	CALL     	3 2 1
	33	[354]	JMP      	22	; to 56
	34	[355]	GETTABLE 	3 0 -3	; "info"
	35	[355]	GETTABLE 	3 3 -15	; "password"
	36	[355]	TEST     	3 0 0
	37	[355]	JMP      	16	; to 54
	38	[356]	GETTABLE 	3 0 -16	; "btn_edit_nw"
	39	[356]	TEST     	3 0 0
	40	[356]	JMP      	10	; to 51
	41	[356]	GETTABLE 	3 2 -11	; "pos"
	42	[356]	SELF     	3 3 -12	; "intersectWith"
	43	[356]	GETTABLE 	5 0 -16	; "btn_edit_nw"
	44	[356]	GETTABLE 	5 5 -13	; "dimen"
	45	[356]	CALL     	3 3 2
	46	[356]	TEST     	3 0 0
	47	[356]	JMP      	3	; to 51
	48	[357]	SELF     	3 0 -17	; "onEditNetwork"
	49	[357]	CALL     	3 2 1
	50	[357]	JMP      	5	; to 56
	51	[359]	SELF     	3 0 -18	; "connect"
	52	[359]	CALL     	3 2 1
	53	[360]	JMP      	2	; to 56
	54	[362]	SELF     	3 0 -19	; "onAddNetwork"
	55	[362]	CALL     	3 2 1
	56	[364]	LOADBOOL 	3 1 0
	57	[364]	RETURN   	3 2
	58	[365]	RETURN   	0 1

function <./frontend/ui/widget/networksetting.lua:383,481> (209 instructions, 836 bytes at 0x7ff7ba40bae0)
1 param, 16 slots, 21 upvalues, 9 locals, 58 constants, 3 functions
	1	[384]	GETTABLE 	1 0 -1	; "width"
	2	[384]	TEST     	1 0 1
	3	[384]	JMP      	8	; to 12
	4	[384]	GETUPVAL 	1 0	; Screen
	5	[384]	SELF     	1 1 -2	; "getWidth"
	6	[384]	CALL     	1 2 2
	7	[384]	GETUPVAL 	2 0	; Screen
	8	[384]	SELF     	2 2 -3	; "scaleBySize"
	9	[384]	LOADK    	4 -4	; 50
	10	[384]	CALL     	2 3 2
	11	[384]	SUB      	1 1 2
	12	[384]	SETTABLE 	0 -1 1	; "width" -
	13	[385]	GETGLOBAL	1 -5	; math
	14	[385]	GETTABLE 	1 1 -6	; "min"
	15	[385]	GETTABLE 	2 0 -1	; "width"
	16	[385]	GETUPVAL 	3 0	; Screen
	17	[385]	SELF     	3 3 -3	; "scaleBySize"
	18	[385]	LOADK    	5 -7	; 600
	19	[385]	CALL     	3 3 0
	20	[385]	CALL     	1 0 2
	21	[385]	SETTABLE 	0 -1 1	; "width" -
	22	[387]	GETUPVAL 	1 1	; Blitbuffer
	23	[387]	GETTABLE 	1 1 -8	; "COLOR_GRAY_E"
	24	[388]	NEWTABLE 	2 0 0
	25	[389]	GETGLOBAL	3 -9	; table
	26	[389]	GETTABLE 	3 3 -10	; "sort"
	27	[389]	GETTABLE 	4 0 -11	; "network_list"
	28	[390]	CLOSURE  	5 0	; 0x7ff7ba407590
	29	[389]	CALL     	3 3 1
	30	[391]	GETGLOBAL	3 -12	; ipairs
	31	[391]	GETTABLE 	4 0 -11	; "network_list"
	32	[391]	CALL     	3 2 4
	33	[391]	JMP      	24	; to 58
	34	[392]	LOADNIL  	8 8
	35	[393]	GETUPVAL 	9 2	; band
	36	[393]	MOVE     	10 6
	37	[393]	LOADK    	11 -13	; 1
	38	[393]	CALL     	9 3 2
	39	[393]	EQ       	0 9 -14	; - 0
	40	[393]	JMP      	2	; to 43
	41	[394]	MOVE     	8 1
	42	[394]	JMP      	2	; to 45
	43	[396]	GETUPVAL 	9 1	; Blitbuffer
	44	[396]	GETTABLE 	8 9 -15	; "COLOR_WHITE"
	45	[398]	GETGLOBAL	9 -9	; table
	46	[398]	GETTABLE 	9 9 -16	; "insert"
	47	[398]	MOVE     	10 2
	48	[398]	GETUPVAL 	11 3	; NetworkItem
	49	[398]	SELF     	11 11 -17	; "new"
	50	[398]	NEWTABLE 	13 0 4
	51	[399]	GETTABLE 	14 0 -1	; "width"
	52	[399]	SETTABLE 	13 -1 14	; "width" -
	53	[400]	SETTABLE 	13 -18 7	; "info" -
	54	[401]	SETTABLE 	13 -19 8	; "background" -
	55	[402]	SETTABLE 	13 -20 0	; "setting_ui" -
	56	[398]	CALL     	11 3 0
	57	[398]	CALL     	9 0 1
	58	[391]	TFORLOOP 	3 2
	59	[403]	JMP      	-26	; to 34
	60	[406]	GETUPVAL 	3 4	; TextWidget
	61	[406]	SELF     	3 3 -17	; "new"
	62	[406]	NEWTABLE 	5 0 2
	63	[407]	SETTABLE 	5 -22 -23	; "text" ""
	64	[408]	GETUPVAL 	6 5	; Font
	65	[408]	SELF     	6 6 -25	; "getFace"
	66	[408]	LOADK    	8 -26	; "ffont"
	67	[408]	CALL     	6 3 2
	68	[408]	SETTABLE 	5 -24 6	; "face" -
	69	[406]	CALL     	3 3 2
	70	[409]	SETTABLE 	0 -21 3	; "status_text" -
	71	[410]	GETUPVAL 	3 4	; TextWidget
	72	[410]	SELF     	3 3 -17	; "new"
	73	[410]	NEWTABLE 	5 0 2
	74	[411]	SETTABLE 	5 -22 -23	; "text" ""
	75	[412]	GETUPVAL 	6 5	; Font
	76	[412]	SELF     	6 6 -25	; "getFace"
	77	[412]	LOADK    	8 -26	; "ffont"
	78	[412]	CALL     	6 3 2
	79	[412]	SETTABLE 	5 -24 6	; "face" -
	80	[410]	CALL     	3 3 2
	81	[413]	SETTABLE 	0 -27 3	; "page_text" -
	82	[415]	GETUPVAL 	3 6	; MinimalPaginator
	83	[415]	SELF     	3 3 -17	; "new"
	84	[415]	NEWTABLE 	5 0 4
	85	[416]	GETTABLE 	6 0 -1	; "width"
	86	[416]	SETTABLE 	5 -1 6	; "width" -
	87	[417]	GETUPVAL 	6 0	; Screen
	88	[417]	SELF     	6 6 -3	; "scaleBySize"
	89	[417]	LOADK    	8 -30	; 8
	90	[417]	CALL     	6 3 2
	91	[417]	SETTABLE 	5 -29 6	; "height" -
	92	[418]	SETTABLE 	5 -31 -14	; "percentage" 0
	93	[419]	SETTABLE 	5 -32 -14	; "progress" 0
	94	[415]	CALL     	3 3 2
	95	[420]	SETTABLE 	0 -28 3	; "pagination" -
	96	[422]	GETTABLE 	3 0 -29	; "height"
	97	[422]	TEST     	3 0 1
	98	[422]	JMP      	12	; to 111
	99	[422]	GETGLOBAL	3 -5	; math
	100	[422]	GETTABLE 	3 3 -6	; "min"
	101	[422]	GETUPVAL 	4 0	; Screen
	102	[422]	SELF     	4 4 -33	; "getHeight"
	103	[422]	CALL     	4 2 2
	104	[422]	MUL      	4 4 -34	; - 3
	105	[422]	DIV      	4 4 -35	; - 4
	106	[423]	GETUPVAL 	5 0	; Screen
	107	[423]	SELF     	5 5 -3	; "scaleBySize"
	108	[423]	LOADK    	7 -36	; 800
	109	[423]	CALL     	5 3 0
	110	[422]	CALL     	3 0 2
	111	[423]	SETTABLE 	0 -29 3	; "height" -
	112	[424]	GETUPVAL 	3 7	; FrameContainer
	113	[424]	SELF     	3 3 -17	; "new"
	114	[424]	NEWTABLE 	5 0 3
	115	[425]	GETUPVAL 	6 1	; Blitbuffer
	116	[425]	GETTABLE 	6 6 -15	; "COLOR_WHITE"
	117	[425]	SETTABLE 	5 -19 6	; "background" -
	118	[426]	SETTABLE 	5 -38 -14	; "padding" 0
	119	[427]	GETUPVAL 	6 8	; Size
	120	[427]	GETTABLE 	6 6 -40	; "border"
	121	[427]	GETTABLE 	6 6 -41	; "window"
	122	[427]	SETTABLE 	5 -39 6	; "bordersize" -
	123	[428]	GETUPVAL 	6 9	; VerticalGroup
	124	[428]	SELF     	6 6 -17	; "new"
	125	[428]	NEWTABLE 	8 1 1
	126	[429]	SETTABLE 	8 -42 -43	; "align" "left"
	127	[430]	GETTABLE 	9 0 -28	; "pagination"
	128	[431]	GETUPVAL 	10 10	; ListView
	129	[431]	SELF     	10 10 -17	; "new"
	130	[431]	NEWTABLE 	12 0 5
	131	[432]	SETTABLE 	12 -38 -14	; "padding" 0
	132	[433]	SETTABLE 	12 -44 2	; "items" -
	133	[434]	GETTABLE 	13 0 -1	; "width"
	134	[434]	SETTABLE 	12 -1 13	; "width" -
	135	[435]	GETTABLE 	13 0 -29	; "height"
	136	[435]	GETTABLE 	14 0 -28	; "pagination"
	137	[435]	SELF     	14 14 -45	; "getSize"
	138	[435]	CALL     	14 2 2
	139	[435]	GETTABLE 	14 14 -46	; "h"
	140	[435]	SUB      	13 13 14
	141	[435]	SETTABLE 	12 -29 13	; "height" -
	142	[442]	CLOSURE  	13 1	; 0x7ff7ba40c2b0
	143	[442]	MOVE     	0 0
	144	[442]	GETUPVAL 	0 11	; UIManager
	145	[442]	SETTABLE 	12 -47 13	; "page_update_cb" -
	146	[431]	CALL     	10 3 0
	147	[444]	SETLIST  	8 0 1	; 1
	148	[428]	CALL     	6 3 0
	149	[445]	SETLIST  	5 0 1	; 1
	150	[424]	CALL     	3 3 2
	151	[445]	SETTABLE 	0 -37 3	; "popup" -
	152	[447]	GETUPVAL 	3 12	; CenterContainer
	153	[447]	SELF     	3 3 -17	; "new"
	154	[447]	NEWTABLE 	5 1 1
	155	[448]	NEWTABLE 	6 0 2
	156	[448]	GETUPVAL 	7 0	; Screen
	157	[448]	SELF     	7 7 -2	; "getWidth"
	158	[448]	CALL     	7 2 2
	159	[448]	SETTABLE 	6 -49 7	; "w" -
	160	[448]	GETUPVAL 	7 0	; Screen
	161	[448]	SELF     	7 7 -33	; "getHeight"
	162	[448]	CALL     	7 2 2
	163	[448]	SETTABLE 	6 -46 7	; "h" -
	164	[448]	SETTABLE 	5 -48 6	; "dimen" -
	165	[450]	GETTABLE 	6 0 -37	; "popup"
	166	[450]	SETLIST  	5 1 1	; 1
	167	[447]	CALL     	3 3 2
	168	[450]	SETTABLE 	0 -13 3	; 1 -
	169	[452]	GETUPVAL 	3 13	; Device
	170	[452]	SELF     	3 3 -50	; "isTouchDevice"
	171	[452]	CALL     	3 2 2
	172	[452]	TEST     	3 0 0
	173	[452]	JMP      	24	; to 198
	174	[453]	GETTABLE 	3 0 -51	; "ges_events"
	175	[453]	NEWTABLE 	4 0 0
	176	[454]	GETUPVAL 	5 14	; GestureRange
	177	[454]	SELF     	5 5 -17	; "new"
	178	[454]	NEWTABLE 	7 0 2
	179	[455]	SETTABLE 	7 -53 -54	; "ges" "tap"
	180	[456]	GETUPVAL 	8 15	; Geom
	181	[456]	SELF     	8 8 -17	; "new"
	182	[456]	NEWTABLE 	10 0 4
	183	[457]	SETTABLE 	10 -56 -14	; "x" 0
	184	[457]	SETTABLE 	10 -57 -14	; "y" 0
	185	[458]	GETUPVAL 	11 0	; Screen
	186	[458]	SELF     	11 11 -2	; "getWidth"
	187	[458]	CALL     	11 2 2
	188	[458]	SETTABLE 	10 -49 11	; "w" -
	189	[459]	GETUPVAL 	11 0	; Screen
	190	[459]	SELF     	11 11 -33	; "getHeight"
	191	[459]	CALL     	11 2 2
	192	[459]	SETTABLE 	10 -46 11	; "h" -
	193	[456]	CALL     	8 3 2
	194	[460]	SETTABLE 	7 -55 8	; "range" -
	195	[454]	CALL     	5 3 0
	196	[462]	SETLIST  	4 0 1	; 1
	197	[462]	SETTABLE 	3 -52 4	; "TapClose" -
	198	[465]	GETUPVAL 	3 11	; UIManager
	199	[465]	SELF     	3 3 -58	; "nextTick"
	200	[480]	CLOSURE  	5 2	; 0x7ff7ba40ca40
	201	[480]	MOVE     	0 0
	202	[480]	GETUPVAL 	0 16	; obtainIP
	203	[480]	GETUPVAL 	0 11	; UIManager
	204	[480]	GETUPVAL 	0 17	; InfoMessage
	205	[480]	GETUPVAL 	0 18	; T
	206	[480]	GETUPVAL 	0 19	; _
	207	[480]	GETUPVAL 	0 20	; BD
	208	[465]	CALL     	3 3 1
	209	[481]	RETURN   	0 1

function <./frontend/ui/widget/networksetting.lua:390,390> (8 instructions, 32 bytes at 0x7ff7ba407590)
2 params, 4 slots, 0 upvalues, 2 locals, 1 constant, 0 functions
	1	[390]	GETTABLE 	2 0 -1	; "signal_quality"
	2	[390]	GETTABLE 	3 1 -1	; "signal_quality"
	3	[390]	LT       	1 3 2
	4	[390]	JMP      	1	; to 6
	5	[390]	LOADBOOL 	2 0 1
	6	[390]	LOADBOOL 	2 1 0
	7	[390]	RETURN   	2 2
	8	[390]	RETURN   	0 1

function <./frontend/ui/widget/networksetting.lua:436,442> (12 instructions, 48 bytes at 0x7ff7ba40c2b0)
2 params, 6 slots, 2 upvalues, 2 locals, 3 constants, 1 function
	1	[437]	GETUPVAL 	2 0	; self
	2	[437]	GETTABLE 	2 2 -1	; "pagination"
	3	[437]	SELF     	2 2 -2	; "setProgress"
	4	[437]	DIV      	4 0 1
	5	[437]	CALL     	2 3 1
	6	[439]	GETUPVAL 	2 1	; UIManager
	7	[439]	SELF     	2 2 -3	; "setDirty"
	8	[439]	GETUPVAL 	4 0	; self
	9	[441]	CLOSURE  	5 0	; 0x7ff7ba40c710
	10	[441]	GETUPVAL 	0 0	; self
	11	[439]	CALL     	2 4 1
	12	[442]	RETURN   	0 1

function <./frontend/ui/widget/networksetting.lua:439,441> (5 instructions, 20 bytes at 0x7ff7ba40c710)
0 params, 2 slots, 1 upvalue, 0 locals, 2 constants, 0 functions
	1	[440]	LOADK    	0 -1	; "ui"
	2	[440]	GETUPVAL 	1 0	; self
	3	[440]	GETTABLE 	1 1 -2	; "dimen"
	4	[440]	RETURN   	0 3
	5	[441]	RETURN   	0 1

function <./frontend/ui/widget/networksetting.lua:465,480> (47 instructions, 188 bytes at 0x7ff7ba40ca40)
0 params, 10 slots, 7 upvalues, 1 local, 18 constants, 0 functions
	1	[466]	GETUPVAL 	0 0	; self
	2	[466]	SELF     	0 0 -1	; "getConnectedItem"
	3	[466]	CALL     	0 2 2
	4	[467]	EQ       	1 0 -2	; - nil
	5	[467]	JMP      	41	; to 47
	6	[468]	GETUPVAL 	1 1	; obtainIP
	7	[468]	CALL     	1 1 1
	8	[469]	GETGLOBAL	1 -3	; G_reader_settings
	9	[469]	SELF     	1 1 -4	; "nilOrTrue"
	10	[469]	LOADK    	3 -5	; "auto_dismiss_wifi_scan"
	11	[469]	CALL     	1 3 2
	12	[469]	TEST     	1 0 0
	13	[469]	JMP      	7	; to 21
	14	[470]	GETUPVAL 	1 2	; UIManager
	15	[470]	SELF     	1 1 -6	; "close"
	16	[470]	GETUPVAL 	3 0	; self
	17	[470]	LOADK    	4 -7	; "ui"
	18	[470]	GETUPVAL 	5 0	; self
	19	[470]	GETTABLE 	5 5 -8	; "dimen"
	20	[470]	CALL     	1 5 1
	21	[472]	GETUPVAL 	1 2	; UIManager
	22	[472]	SELF     	1 1 -9	; "show"
	23	[472]	GETUPVAL 	3 3	; InfoMessage
	24	[472]	SELF     	3 3 -10	; "new"
	25	[472]	NEWTABLE 	5 0 2
	26	[473]	GETUPVAL 	6 4	; T
	27	[473]	GETUPVAL 	7 5	; _
	28	[473]	LOADK    	8 -12	; "Connected to network %1"
	29	[473]	CALL     	7 2 2
	30	[473]	GETUPVAL 	8 6	; BD
	31	[473]	GETTABLE 	8 8 -13	; "wrap"
	32	[473]	GETTABLE 	9 0 -14	; "info"
	33	[473]	GETTABLE 	9 9 -15	; "ssid"
	34	[473]	CALL     	8 2 0
	35	[473]	CALL     	6 0 2
	36	[473]	SETTABLE 	5 -11 6	; "text" -
	37	[474]	SETTABLE 	5 -16 -17	; "timeout" 3
	38	[472]	CALL     	3 3 0
	39	[472]	CALL     	1 0 1
	40	[476]	GETUPVAL 	1 0	; self
	41	[476]	GETTABLE 	1 1 -18	; "connect_callback"
	42	[476]	TEST     	1 0 0
	43	[476]	JMP      	3	; to 47
	44	[477]	GETUPVAL 	1 0	; self
	45	[477]	GETTABLE 	1 1 -18	; "connect_callback"
	46	[477]	CALL     	1 1 1
	47	[480]	RETURN   	0 1

function <./frontend/ui/widget/networksetting.lua:483,485> (2 instructions, 8 bytes at 0x7ff7ba40d330)
2 params, 2 slots, 0 upvalues, 2 locals, 1 constant, 0 functions
	1	[484]	SETTABLE 	0 -1 1	; "connected_item" -
	2	[485]	RETURN   	0 1

function <./frontend/ui/widget/networksetting.lua:487,489> (3 instructions, 12 bytes at 0x7ff7ba40d220)
1 param, 2 slots, 0 upvalues, 1 local, 1 constant, 0 functions
	1	[488]	GETTABLE 	1 0 -1	; "connected_item"
	2	[488]	RETURN   	1 2
	3	[489]	RETURN   	0 1

function <./frontend/ui/widget/networksetting.lua:491,496> (14 instructions, 56 bytes at 0x7ff7ba40d2b0)
3 params, 6 slots, 1 upvalue, 3 locals, 5 constants, 0 functions
	1	[492]	GETTABLE 	3 2 -1	; "pos"
	2	[492]	SELF     	3 3 -2	; "notIntersectWith"
	3	[492]	GETTABLE 	5 0 -3	; "popup"
	4	[492]	GETTABLE 	5 5 -4	; "dimen"
	5	[492]	CALL     	3 3 2
	6	[492]	TEST     	3 0 0
	7	[492]	JMP      	6	; to 14
	8	[493]	GETUPVAL 	3 0	; UIManager
	9	[493]	SELF     	3 3 -5	; "close"
	10	[493]	MOVE     	5 0
	11	[493]	CALL     	3 3 1
	12	[494]	LOADBOOL 	3 1 0
	13	[494]	RETURN   	3 2
	14	[496]	RETURN   	0 1
