
main <./spec/unit/networksetting_spec.lua:0,0> (5 instructions, 20 bytes at 0x7fcde4c068d0)
0+ params, 3 slots, 0 upvalues, 0 locals, 2 constants, 1 function
	1	[1]	GETGLOBAL	0 -1	; describe
	2	[1]	LOADK    	1 -2	; "NetworkSetting module"
	3	[71]	CLOSURE  	2 0	; 0x7fcde4c06b70
	4	[1]	CALL     	0 3 1
	5	[71]	RETURN   	0 1

function <./spec/unit/networksetting_spec.lua:1,71> (26 instructions, 104 bytes at 0x7fcde4c06b70)
0 params, 6 slots, 0 upvalues, 3 locals, 5 constants, 4 functions
	1	[3]	GETGLOBAL	3 -1	; setup
	2	[8]	CLOSURE  	4 0	; 0x7fcde4c06ee0
	3	[8]	MOVE     	0 2
	4	[8]	MOVE     	0 0
	5	[8]	MOVE     	0 1
	6	[3]	CALL     	3 2 1
	7	[10]	GETGLOBAL	3 -2	; it
	8	[10]	LOADK    	4 -3	; "should initilize properly with empty network list"
	9	[13]	CLOSURE  	5 1	; 0x7fcde4c07150
	10	[13]	MOVE     	0 0
	11	[10]	CALL     	3 3 1
	12	[15]	GETGLOBAL	3 -2	; it
	13	[15]	LOADK    	4 -4	; "should call connect_callback after disconnect"
	14	[40]	CLOSURE  	5 2	; 0x7fcde4c07800
	15	[40]	MOVE     	0 1
	16	[40]	MOVE     	0 2
	17	[40]	MOVE     	0 0
	18	[15]	CALL     	3 3 1
	19	[42]	GETGLOBAL	3 -2	; it
	20	[42]	LOADK    	4 -5	; "should set connected_item to nil after disconnect"
	21	[70]	CLOSURE  	5 3	; 0x7fcde4c085b0
	22	[70]	MOVE     	0 1
	23	[70]	MOVE     	0 2
	24	[70]	MOVE     	0 0
	25	[42]	CALL     	3 3 1
	26	[71]	RETURN   	0 1

function <./spec/unit/networksetting_spec.lua:3,8> (16 instructions, 64 bytes at 0x7fcde4c06ee0)
0 params, 2 slots, 3 upvalues, 0 locals, 5 constants, 0 functions
	1	[4]	GETGLOBAL	0 -1	; require
	2	[4]	LOADK    	1 -2	; "commonrequire"
	3	[4]	CALL     	0 2 1
	4	[5]	GETGLOBAL	0 -1	; require
	5	[5]	LOADK    	1 -3	; "ui/uimanager"
	6	[5]	CALL     	0 2 2
	7	[5]	SETUPVAL 	0 0	; UIManager
	8	[6]	GETGLOBAL	0 -1	; require
	9	[6]	LOADK    	1 -4	; "ui/widget/networksetting"
	10	[6]	CALL     	0 2 2
	11	[6]	SETUPVAL 	0 1	; NetworkSetting
	12	[7]	GETGLOBAL	0 -1	; require
	13	[7]	LOADK    	1 -5	; "ui/network/manager"
	14	[7]	CALL     	0 2 2
	15	[7]	SETUPVAL 	0 2	; NetworkMgr
	16	[8]	RETURN   	0 1

function <./spec/unit/networksetting_spec.lua:10,13> (12 instructions, 48 bytes at 0x7fcde4c07150)
0 params, 4 slots, 1 upvalue, 1 local, 6 constants, 0 functions
	1	[11]	GETUPVAL 	0 0	; NetworkSetting
	2	[11]	SELF     	0 0 -1	; "new"
	3	[11]	NEWTABLE 	2 0 1
	4	[11]	NEWTABLE 	3 0 0
	5	[11]	SETTABLE 	2 -2 3	; "network_list" -
	6	[11]	CALL     	0 3 2
	7	[12]	GETGLOBAL	1 -3	; assert
	8	[12]	GETTABLE 	1 1 -4	; "is"
	9	[12]	GETTABLE 	1 1 -5	; "falsy"
	10	[12]	GETTABLE 	2 0 -6	; "connected_item"
	11	[12]	CALL     	1 2 1
	12	[13]	RETURN   	0 1

function <./spec/unit/networksetting_spec.lua:15,40> (45 instructions, 180 bytes at 0x7fcde4c07800)
0 params, 6 slots, 3 upvalues, 3 locals, 24 constants, 1 function
	1	[16]	GETGLOBAL	0 -1	; stub
	2	[16]	GETUPVAL 	1 0	; NetworkMgr
	3	[16]	LOADK    	2 -2	; "disconnectNetwork"
	4	[16]	CALL     	0 3 1
	5	[17]	GETGLOBAL	0 -1	; stub
	6	[17]	GETUPVAL 	1 0	; NetworkMgr
	7	[17]	LOADK    	2 -3	; "releaseIP"
	8	[17]	CALL     	0 3 1
	9	[19]	GETUPVAL 	0 1	; UIManager
	10	[19]	SELF     	0 0 -4	; "quit"
	11	[19]	CALL     	0 2 1
	12	[20]	LOADBOOL 	0 0 0
	13	[21]	NEWTABLE 	1 1 0
	14	[21]	NEWTABLE 	2 0 6
	15	[23]	SETTABLE 	2 -5 -6	; "ssid" "foo"
	16	[24]	SETTABLE 	2 -7 -8	; "signal_level" -58
	17	[25]	SETTABLE 	2 -9 -10	; "flags" "[WPA2-PSK-CCMP][ESS]"
	18	[26]	SETTABLE 	2 -11 -12	; "signal_quality" 84
	19	[27]	SETTABLE 	2 -13 -14	; "password" "123abc"
	20	[28]	SETTABLE 	2 -15 -16	; "connected" true
	21	[30]	SETLIST  	1 1 1	; 1
	22	[31]	GETUPVAL 	2 2	; NetworkSetting
	23	[31]	SELF     	2 2 -17	; "new"
	24	[31]	NEWTABLE 	4 0 2
	25	[32]	SETTABLE 	4 -18 1	; "network_list" -
	26	[33]	CLOSURE  	5 0	; 0x7fcde4c07ec0
	27	[33]	MOVE     	0 0
	28	[33]	SETTABLE 	4 -19 5	; "connect_callback" -
	29	[31]	CALL     	2 3 2
	30	[35]	GETTABLE 	3 2 -20	; "connected_item"
	31	[35]	SELF     	3 3 -21	; "disconnect"
	32	[35]	CALL     	3 2 1
	33	[36]	GETGLOBAL	3 -22	; assert
	34	[36]	GETTABLE 	3 3 -23	; "truthy"
	35	[36]	MOVE     	4 0
	36	[36]	CALL     	3 2 1
	37	[38]	GETUPVAL 	3 0	; NetworkMgr
	38	[38]	GETTABLE 	3 3 -2	; "disconnectNetwork"
	39	[38]	SELF     	3 3 -24	; "revert"
	40	[38]	CALL     	3 2 1
	41	[39]	GETUPVAL 	3 0	; NetworkMgr
	42	[39]	GETTABLE 	3 3 -3	; "releaseIP"
	43	[39]	SELF     	3 3 -24	; "revert"
	44	[39]	CALL     	3 2 1
	45	[40]	RETURN   	0 1

function <./spec/unit/networksetting_spec.lua:33,33> (3 instructions, 12 bytes at 0x7fcde4c07ec0)
0 params, 2 slots, 1 upvalue, 0 locals, 0 constants, 0 functions
	1	[33]	LOADBOOL 	0 1 0
	2	[33]	SETUPVAL 	0 0	; called
	3	[33]	RETURN   	0 1

function <./spec/unit/networksetting_spec.lua:42,70> (55 instructions, 220 bytes at 0x7fcde4c085b0)
0 params, 5 slots, 3 upvalues, 2 locals, 30 constants, 0 functions
	1	[43]	GETGLOBAL	0 -1	; stub
	2	[43]	GETUPVAL 	1 0	; NetworkMgr
	3	[43]	LOADK    	2 -2	; "disconnectNetwork"
	4	[43]	CALL     	0 3 1
	5	[44]	GETGLOBAL	0 -1	; stub
	6	[44]	GETUPVAL 	1 0	; NetworkMgr
	7	[44]	LOADK    	2 -3	; "releaseIP"
	8	[44]	CALL     	0 3 1
	9	[46]	GETUPVAL 	0 1	; UIManager
	10	[46]	SELF     	0 0 -4	; "quit"
	11	[46]	CALL     	0 2 1
	12	[47]	NEWTABLE 	0 2 0
	13	[47]	NEWTABLE 	1 0 6
	14	[49]	SETTABLE 	1 -5 -6	; "ssid" "foo"
	15	[50]	SETTABLE 	1 -7 -8	; "signal_level" -58
	16	[51]	SETTABLE 	1 -9 -10	; "flags" "[WPA2-PSK-CCMP][ESS]"
	17	[52]	SETTABLE 	1 -11 -12	; "signal_quality" 84
	18	[53]	SETTABLE 	1 -13 -14	; "password" "123abc"
	19	[54]	SETTABLE 	1 -15 -16	; "connected" true
	20	[55]	NEWTABLE 	2 0 4
	21	[57]	SETTABLE 	2 -5 -17	; "ssid" "bar"
	22	[58]	SETTABLE 	2 -7 -18	; "signal_level" -258
	23	[59]	SETTABLE 	2 -11 -19	; "signal_quality" 44
	24	[60]	SETTABLE 	2 -9 -20	; "flags" "[WEP][ESS]"
	25	[62]	SETLIST  	0 2 1	; 1
	26	[63]	GETUPVAL 	1 2	; NetworkSetting
	27	[63]	SELF     	1 1 -21	; "new"
	28	[63]	NEWTABLE 	3 0 1
	29	[63]	SETTABLE 	3 -22 0	; "network_list" -
	30	[63]	CALL     	1 3 2
	31	[64]	GETGLOBAL	2 -23	; assert
	32	[64]	GETTABLE 	2 2 -24	; "is"
	33	[64]	GETTABLE 	2 2 -25	; "same"
	34	[64]	LOADK    	3 -6	; "foo"
	35	[64]	GETTABLE 	4 1 -26	; "connected_item"
	36	[64]	GETTABLE 	4 4 -27	; "info"
	37	[64]	GETTABLE 	4 4 -5	; "ssid"
	38	[64]	CALL     	2 3 1
	39	[65]	GETTABLE 	2 1 -26	; "connected_item"
	40	[65]	SELF     	2 2 -28	; "disconnect"
	41	[65]	CALL     	2 2 1
	42	[66]	GETGLOBAL	2 -23	; assert
	43	[66]	GETTABLE 	2 2 -24	; "is"
	44	[66]	GETTABLE 	2 2 -29	; "falsy"
	45	[66]	GETTABLE 	3 1 -26	; "connected_item"
	46	[66]	CALL     	2 2 1
	47	[68]	GETUPVAL 	2 0	; NetworkMgr
	48	[68]	GETTABLE 	2 2 -2	; "disconnectNetwork"
	49	[68]	SELF     	2 2 -30	; "revert"
	50	[68]	CALL     	2 2 1
	51	[69]	GETUPVAL 	2 0	; NetworkMgr
	52	[69]	GETTABLE 	2 2 -3	; "releaseIP"
	53	[69]	SELF     	2 2 -30	; "revert"
	54	[69]	CALL     	2 2 1
	55	[70]	RETURN   	0 1
