-- BYTECODE -- networksetting_spec.lua:3-8
0001    GGET     0   0      ; "require"
0002    KSTR     1   1      ; "commonrequire"
0003    CALL     0   1   2
0004    GGET     0   0      ; "require"
0005    KSTR     1   2      ; "ui/uimanager"
0006    CALL     0   2   2
0007    USETV    0   0      ; UIManager
0008    GGET     0   0      ; "require"
0009    KSTR     1   3      ; "ui/widget/networksetting"
0010    CALL     0   2   2
0011    USETV    1   0      ; NetworkSetting
0012    GGET     0   0      ; "require"
0013    KSTR     1   4      ; "ui/network/manager"
0014    CALL     0   2   2
0015    USETV    2   0      ; NetworkMgr
0016    RET0     0   1

-- BYTECODE -- networksetting_spec.lua:10-13
0001    UGET     0   0      ; NetworkSetting
0002    MOV      1   0
0003    TGETS    0   0   0  ; "new"
0004    TDUP     2   1
0005    TNEW     3   0
0006    TSETS    3   2   2  ; "network_list"
0007    CALL     0   2   3
0008    GGET     1   3      ; "assert"
0009    TGETS    1   1   4  ; "is"
0010    TGETS    1   1   5  ; "falsy"
0011    TGETS    2   0   6  ; "connected_item"
0012    CALL     1   1   2
0013    RET0     0   1

-- BYTECODE -- networksetting_spec.lua:33-33
0001    USETP    0   2      ; called
0002    RET0     0   1

-- BYTECODE -- networksetting_spec.lua:15-40
0001    GGET     0   0      ; "stub"
0002    UGET     1   0      ; NetworkMgr
0003    KSTR     2   1      ; "disconnectNetwork"
0004    CALL     0   1   3
0005    GGET     0   0      ; "stub"
0006    UGET     1   0      ; NetworkMgr
0007    KSTR     2   2      ; "releaseIP"
0008    CALL     0   1   3
0009    UGET     0   1      ; UIManager
0010    MOV      1   0
0011    TGETS    0   0   3  ; "quit"
0012    CALL     0   1   2
0013    KPRI     0   1
0014    TNEW     1   3
0015    TDUP     2   4
0016    TSETB    2   1   1
0017    UGET     2   2      ; NetworkSetting
0018    MOV      3   2
0019    TGETS    2   2   5  ; "new"
0020    TDUP     4   6
0021    TSETS    1   4   7  ; "network_list"
0022    FNEW     5   8      ; networksetting_spec.lua:33
0023    TSETS    5   4   9  ; "connect_callback"
0024    CALL     2   2   3
0025    TGETS    3   2  10  ; "connected_item"
0026    MOV      4   3
0027    TGETS    3   3  11  ; "disconnect"
0028    CALL     3   1   2
0029    GGET     3  12      ; "assert"
0030    TGETS    3   3  13  ; "truthy"
0031    MOV      4   0
0032    CALL     3   1   2
0033    UGET     3   0      ; NetworkMgr
0034    TGETS    3   3   1  ; "disconnectNetwork"
0035    MOV      4   3
0036    TGETS    3   3  14  ; "revert"
0037    CALL     3   1   2
0038    UGET     3   0      ; NetworkMgr
0039    TGETS    3   3   2  ; "releaseIP"
0040    MOV      4   3
0041    TGETS    3   3  14  ; "revert"
0042    CALL     3   1   2
0043    UCLO     0 => 0044
0044 => RET0     0   1

-- BYTECODE -- networksetting_spec.lua:42-70
0001    GGET     0   0      ; "stub"
0002    UGET     1   0      ; NetworkMgr
0003    KSTR     2   1      ; "disconnectNetwork"
0004    CALL     0   1   3
0005    GGET     0   0      ; "stub"
0006    UGET     1   0      ; NetworkMgr
0007    KSTR     2   2      ; "releaseIP"
0008    CALL     0   1   3
0009    UGET     0   1      ; UIManager
0010    MOV      1   0
0011    TGETS    0   0   3  ; "quit"
0012    CALL     0   1   2
0013    TNEW     0   3
0014    TDUP     1   4
0015    TSETB    1   0   1
0016    TDUP     1   5
0017    TSETB    1   0   2
0018    UGET     1   2      ; NetworkSetting
0019    MOV      2   1
0020    TGETS    1   1   6  ; "new"
0021    TDUP     3   7
0022    TSETS    0   3   8  ; "network_list"
0023    CALL     1   2   3
0024    GGET     2   9      ; "assert"
0025    TGETS    2   2  10  ; "is"
0026    TGETS    2   2  11  ; "same"
0027    KSTR     3  12      ; "foo"
0028    TGETS    4   1  13  ; "connected_item"
0029    TGETS    4   4  14  ; "info"
0030    TGETS    4   4  15  ; "ssid"
0031    CALL     2   1   3
0032    TGETS    2   1  13  ; "connected_item"
0033    MOV      3   2
0034    TGETS    2   2  16  ; "disconnect"
0035    CALL     2   1   2
0036    GGET     2   9      ; "assert"
0037    TGETS    2   2  10  ; "is"
0038    TGETS    2   2  17  ; "falsy"
0039    TGETS    3   1  13  ; "connected_item"
0040    CALL     2   1   2
0041    UGET     2   0      ; NetworkMgr
0042    TGETS    2   2   1  ; "disconnectNetwork"
0043    MOV      3   2
0044    TGETS    2   2  18  ; "revert"
0045    CALL     2   1   2
0046    UGET     2   0      ; NetworkMgr
0047    TGETS    2   2   2  ; "releaseIP"
0048    MOV      3   2
0049    TGETS    2   2  18  ; "revert"
0050    CALL     2   1   2
0051    RET0     0   1

-- BYTECODE -- networksetting_spec.lua:1-71
0001    KNIL     0   2
0002    GGET     3   0      ; "setup"
0003    FNEW     4   1      ; networksetting_spec.lua:3
0004    CALL     3   1   2
0005    GGET     3   2      ; "it"
0006    KSTR     4   3      ; "should initilize properly with empty net"~
0007    FNEW     5   4      ; networksetting_spec.lua:10
0008    CALL     3   1   3
0009    GGET     3   2      ; "it"
0010    KSTR     4   5      ; "should call connect_callback after disco"~
0011    FNEW     5   6      ; networksetting_spec.lua:15
0012    CALL     3   1   3
0013    GGET     3   2      ; "it"
0014    KSTR     4   7      ; "should set connected_item to nil after d"~
0015    FNEW     5   8      ; networksetting_spec.lua:42
0016    CALL     3   1   3
0017    UCLO     0 => 0018
0018 => RET0     0   1

-- BYTECODE -- networksetting_spec.lua:0-72
0001    GGET     0   0      ; "describe"
0002    KSTR     1   1      ; "NetworkSetting module"
0003    FNEW     2   2      ; networksetting_spec.lua:1
0004    CALL     0   1   3
0005    RET0     0   1

