-- BYTECODE -- nickel_conf_spec.lua:3-7
0001    GGET     0   0      ; "require"
0002    KSTR     1   1      ; "commonrequire"
0003    CALL     0   1   2
0004    GGET     0   0      ; "require"
0005    KSTR     1   2      ; "libs/libkoreader-lfs"
0006    CALL     0   2   2
0007    USETV    0   0      ; lfs
0008    GGET     0   0      ; "require"
0009    KSTR     1   3      ; "device/kobo/nickel_conf"
0010    CALL     0   2   2
0011    USETV    1   0      ; NickelConf
0012    RET0     0   1

-- BYTECODE -- nickel_conf_spec.lua:10-29
0001    GGET     0   0      ; "os"
0002    TGETS    0   0   1  ; "tmpname"
0003    CALL     0   2   1
0004    GGET     1   2      ; "io"
0005    TGETS    1   1   3  ; "open"
0006    MOV      2   0
0007    KSTR     3   4      ; "w"
0008    CALL     1   2   3
0009    MOV      3   1
0010    TGETS    2   1   5  ; "write"
0011    KSTR     4   6      ; "[OtherThing]\nfoo=bar\n[PowerOptions]\nF"~
0012    CALL     2   1   3
0013    MOV      3   1
0014    TGETS    2   1   7  ; "close"
0015    CALL     2   1   2
0016    UGET     2   0      ; NickelConf
0017    TGETS    2   2   8  ; "_set_kobo_conf_path"
0018    MOV      3   0
0019    CALL     2   1   2
0020    GGET     2   9      ; "assert"
0021    TGETS    2   2  10  ; "Equals"
0022    UGET     3   0      ; NickelConf
0023    TGETS    3   3  11  ; "frontLightLevel"
0024    TGETS    3   3  12  ; "get"
0025    CALL     3   2   1
0026    KSHORT   4  55
0027    CALL     2   1   3
0028    GGET     2   9      ; "assert"
0029    TGETS    2   2  10  ; "Equals"
0030    UGET     3   0      ; NickelConf
0031    TGETS    3   3  13  ; "frontLightState"
0032    TGETS    3   3  12  ; "get"
0033    CALL     3   2   1
0034    KPRI     4   2
0035    CALL     2   1   3
0036    GGET     2   0      ; "os"
0037    TGETS    2   2  14  ; "remove"
0038    MOV      3   0
0039    CALL     2   1   2
0040    RET0     0   1

-- BYTECODE -- nickel_conf_spec.lua:31-50
0001    GGET     0   0      ; "os"
0002    TGETS    0   0   1  ; "tmpname"
0003    CALL     0   2   1
0004    GGET     1   2      ; "io"
0005    TGETS    1   1   3  ; "open"
0006    MOV      2   0
0007    KSTR     3   4      ; "w"
0008    CALL     1   2   3
0009    MOV      3   1
0010    TGETS    2   1   5  ; "write"
0011    KSTR     4   6      ; "[OtherThing]\nfoo=bar\n[PowerOptions]\nF"~
0012    CALL     2   1   3
0013    MOV      3   1
0014    TGETS    2   1   7  ; "close"
0015    CALL     2   1   2
0016    UGET     2   0      ; NickelConf
0017    TGETS    2   2   8  ; "_set_kobo_conf_path"
0018    MOV      3   0
0019    CALL     2   1   2
0020    GGET     2   9      ; "assert"
0021    TGETS    2   2  10  ; "Equals"
0022    UGET     3   0      ; NickelConf
0023    TGETS    3   3  11  ; "frontLightLevel"
0024    TGETS    3   3  12  ; "get"
0025    CALL     3   2   1
0026    KSHORT   4  30
0027    CALL     2   1   3
0028    GGET     2   9      ; "assert"
0029    TGETS    2   2  10  ; "Equals"
0030    UGET     3   0      ; NickelConf
0031    TGETS    3   3  13  ; "frontLightState"
0032    TGETS    3   3  12  ; "get"
0033    CALL     3   2   1
0034    KPRI     4   1
0035    CALL     2   1   3
0036    GGET     2   0      ; "os"
0037    TGETS    2   2  14  ; "remove"
0038    MOV      3   0
0039    CALL     2   1   2
0040    RET0     0   1

-- BYTECODE -- nickel_conf_spec.lua:52-68
0001    GGET     0   0      ; "os"
0002    TGETS    0   0   1  ; "tmpname"
0003    CALL     0   2   1
0004    GGET     1   2      ; "io"
0005    TGETS    1   1   3  ; "open"
0006    MOV      2   0
0007    KSTR     3   4      ; "w"
0008    CALL     1   2   3
0009    MOV      3   1
0010    TGETS    2   1   5  ; "write"
0011    KSTR     4   6      ; "[OtherThing]\nfoo=bar\n[YetAnotherThing]"~
0012    CALL     2   1   3
0013    MOV      3   1
0014    TGETS    2   1   7  ; "close"
0015    CALL     2   1   2
0016    UGET     2   0      ; NickelConf
0017    TGETS    2   2   8  ; "_set_kobo_conf_path"
0018    MOV      3   0
0019    CALL     2   1   2
0020    GGET     2   9      ; "assert"
0021    TGETS    2   2  10  ; "Equals"
0022    UGET     3   0      ; NickelConf
0023    TGETS    3   3  11  ; "frontLightLevel"
0024    TGETS    3   3  12  ; "get"
0025    CALL     3   2   1
0026    KSHORT   4   1
0027    CALL     2   1   3
0028    GGET     2   9      ; "assert"
0029    TGETS    2   2  10  ; "Equals"
0030    UGET     3   0      ; NickelConf
0031    TGETS    3   3  13  ; "frontLightState"
0032    TGETS    3   3  12  ; "get"
0033    CALL     3   2   1
0034    KPRI     4   0
0035    CALL     2   1   3
0036    GGET     2   0      ; "os"
0037    TGETS    2   2  14  ; "remove"
0038    MOV      3   0
0039    CALL     2   1   2
0040    RET0     0   1

-- BYTECODE -- nickel_conf_spec.lua:70-107
0001    GGET     0   0      ; "os"
0002    TGETS    0   0   1  ; "tmpname"
0003    CALL     0   2   1
0004    GGET     1   2      ; "io"
0005    TGETS    1   1   3  ; "open"
0006    MOV      2   0
0007    KSTR     3   4      ; "w"
0008    CALL     1   2   3
0009    MOV      3   1
0010    TGETS    2   1   5  ; "write"
0011    KSTR     4   6      ; "[OtherThing]\nFrontLightLevel=6\n"
0012    CALL     2   1   3
0013    MOV      3   1
0014    TGETS    2   1   7  ; "close"
0015    CALL     2   1   2
0016    UGET     2   0      ; NickelConf
0017    TGETS    2   2   8  ; "_set_kobo_conf_path"
0018    MOV      3   0
0019    CALL     2   1   2
0020    UGET     2   0      ; NickelConf
0021    TGETS    2   2   9  ; "frontLightLevel"
0022    TGETS    2   2  10  ; "set"
0023    KSHORT   3 100
0024    CALL     2   1   2
0025    UGET     2   0      ; NickelConf
0026    TGETS    2   2  11  ; "frontLightState"
0027    TGETS    2   2  10  ; "set"
0028    KPRI     3   2
0029    CALL     2   1   2
0030    GGET     2   2      ; "io"
0031    TGETS    2   2   3  ; "open"
0032    MOV      3   0
0033    KSTR     4  12      ; "r"
0034    CALL     2   2   3
0035    MOV      1   2
0036    GGET     2  13      ; "assert"
0037    TGETS    2   2  14  ; "Equals"
0038    MOV      4   1
0039    TGETS    3   1  15  ; "read"
0040    KSTR     5  16      ; "*a"
0041    CALL     3   2   3
0042    KSTR     4  17      ; "[OtherThing]\nFrontLightLevel=6\n[PowerO"~
0043    CALL     2   1   3
0044    MOV      3   1
0045    TGETS    2   1   7  ; "close"
0046    CALL     2   1   2
0047    GGET     2   0      ; "os"
0048    TGETS    2   2  18  ; "remove"
0049    MOV      3   0
0050    CALL     2   1   2
0051    GGET     2   2      ; "io"
0052    TGETS    2   2   3  ; "open"
0053    MOV      3   0
0054    KSTR     4   4      ; "w"
0055    CALL     2   2   3
0056    MOV      1   2
0057    MOV      3   1
0058    TGETS    2   1   5  ; "write"
0059    KSTR     4  19      ; ""
0060    CALL     2   1   3
0061    MOV      3   1
0062    TGETS    2   1   7  ; "close"
0063    CALL     2   1   2
0064    UGET     2   0      ; NickelConf
0065    TGETS    2   2   9  ; "frontLightLevel"
0066    TGETS    2   2  10  ; "set"
0067    KSHORT   3  20
0068    CALL     2   1   2
0069    UGET     2   0      ; NickelConf
0070    TGETS    2   2  11  ; "frontLightState"
0071    TGETS    2   2  10  ; "set"
0072    KPRI     3   1
0073    CALL     2   1   2
0074    GGET     2   2      ; "io"
0075    TGETS    2   2   3  ; "open"
0076    MOV      3   0
0077    KSTR     4  12      ; "r"
0078    CALL     2   2   3
0079    MOV      1   2
0080    GGET     2  13      ; "assert"
0081    TGETS    2   2  14  ; "Equals"
0082    MOV      4   1
0083    TGETS    3   1  15  ; "read"
0084    KSTR     5  16      ; "*a"
0085    CALL     3   2   3
0086    KSTR     4  20      ; "[PowerOptions]\nFrontLightLevel=20\n"
0087    CALL     2   1   3
0088    MOV      3   1
0089    TGETS    2   1   7  ; "close"
0090    CALL     2   1   2
0091    GGET     2   0      ; "os"
0092    TGETS    2   2  18  ; "remove"
0093    MOV      3   0
0094    CALL     2   1   2
0095    RET0     0   1

-- BYTECODE -- nickel_conf_spec.lua:109-139
0001    GGET     0   0      ; "os"
0002    TGETS    0   0   1  ; "tmpname"
0003    CALL     0   2   1
0004    GGET     1   2      ; "io"
0005    TGETS    1   1   3  ; "open"
0006    MOV      2   0
0007    KSTR     3   4      ; "w"
0008    CALL     1   2   3
0009    MOV      3   1
0010    TGETS    2   1   5  ; "write"
0011    KSTR     4   6      ; "[OtherThing]\nfoo=bar\n[PowerOptions]\nF"~
0012    CALL     2   1   3
0013    MOV      3   1
0014    TGETS    2   1   7  ; "close"
0015    CALL     2   1   2
0016    UGET     2   0      ; NickelConf
0017    TGETS    2   2   8  ; "_set_kobo_conf_path"
0018    MOV      3   0
0019    CALL     2   1   2
0020    UGET     2   0      ; NickelConf
0021    TGETS    2   2   9  ; "frontLightLevel"
0022    TGETS    2   2  10  ; "set"
0023    KSHORT   3 100
0024    CALL     2   1   2
0025    UGET     2   0      ; NickelConf
0026    TGETS    2   2  11  ; "frontLightState"
0027    TGETS    2   2  10  ; "set"
0028    KPRI     3   2
0029    CALL     2   1   2
0030    GGET     2   2      ; "io"
0031    TGETS    2   2   3  ; "open"
0032    MOV      3   0
0033    KSTR     4  12      ; "r"
0034    CALL     2   2   3
0035    MOV      1   2
0036    GGET     2  13      ; "assert"
0037    TGETS    2   2  14  ; "Equals"
0038    MOV      4   1
0039    TGETS    3   1  15  ; "read"
0040    KSTR     5  16      ; "*a"
0041    CALL     3   2   3
0042    KSTR     4  17      ; "[OtherThing]\nfoo=bar\n[PowerOptions]\nF"~
0043    CALL     2   1   3
0044    MOV      3   1
0045    TGETS    2   1   7  ; "close"
0046    CALL     2   1   2
0047    GGET     2   0      ; "os"
0048    TGETS    2   2  18  ; "remove"
0049    MOV      3   0
0050    CALL     2   1   2
0051    RET0     0   1

-- BYTECODE -- nickel_conf_spec.lua:141-166
0001    GGET     0   0      ; "os"
0002    TGETS    0   0   1  ; "tmpname"
0003    CALL     0   2   1
0004    GGET     1   2      ; "io"
0005    TGETS    1   1   3  ; "open"
0006    MOV      2   0
0007    KSTR     3   4      ; "w"
0008    CALL     1   2   3
0009    MOV      3   1
0010    TGETS    2   1   5  ; "write"
0011    KSTR     4   6      ; "[PowerOptions]\nfoo=bar\n[OtherThing]\nb"~
0012    CALL     2   1   3
0013    MOV      3   1
0014    TGETS    2   1   7  ; "close"
0015    CALL     2   1   2
0016    UGET     2   0      ; NickelConf
0017    TGETS    2   2   8  ; "_set_kobo_conf_path"
0018    MOV      3   0
0019    CALL     2   1   2
0020    UGET     2   0      ; NickelConf
0021    TGETS    2   2   9  ; "frontLightLevel"
0022    TGETS    2   2  10  ; "set"
0023    KSHORT   3   1
0024    CALL     2   1   2
0025    UGET     2   0      ; NickelConf
0026    TGETS    2   2  11  ; "frontLightState"
0027    TGETS    2   2  10  ; "set"
0028    KPRI     3   2
0029    CALL     2   1   2
0030    GGET     2   2      ; "io"
0031    TGETS    2   2   3  ; "open"
0032    MOV      3   0
0033    KSTR     4  12      ; "r"
0034    CALL     2   2   3
0035    MOV      1   2
0036    GGET     2  13      ; "assert"
0037    TGETS    2   2  14  ; "Equals"
0038    KSTR     3  15      ; "[PowerOptions]\nfoo=bar\nFrontLightLevel"~
0039    MOV      5   1
0040    TGETS    4   1  16  ; "read"
0041    KSTR     6  17      ; "*a"
0042    CALL     4   0   3
0043    CALLM    2   1   1
0044    MOV      3   1
0045    TGETS    2   1   7  ; "close"
0046    CALL     2   1   2
0047    GGET     2   0      ; "os"
0048    TGETS    2   2  18  ; "remove"
0049    MOV      3   0
0050    CALL     2   1   2
0051    RET0     0   1

-- BYTECODE -- nickel_conf_spec.lua:172-172
0001    GGET     0   0      ; "os"
0002    TGETS    0   0   1  ; "remove"
0003    UGET     1   0      ; fn
0004    CALL     0   1   2
0005    RET0     0   1

-- BYTECODE -- nickel_conf_spec.lua:168-185
0001    KPRI     0   0
0002    KSTR     1   0      ; "/tmp/abcfoobarbaz449"
0003    GGET     2   1      ; "assert"
0004    TGETS    2   2   2  ; "is_not"
0005    TGETS    2   2   3  ; "Equals"
0006    UGET     3   0      ; lfs
0007    TGETS    3   3   4  ; "attributes"
0008    MOV      4   1
0009    KSTR     5   5      ; "mode"
0010    CALL     3   2   3
0011    KSTR     4   6      ; "file"
0012    CALL     2   1   3
0013    GGET     2   7      ; "finally"
0014    FNEW     3   8      ; nickel_conf_spec.lua:172
0015    CALL     2   1   2
0016    UGET     2   1      ; NickelConf
0017    TGETS    2   2   9  ; "_set_kobo_conf_path"
0018    MOV      3   1
0019    CALL     2   1   2
0020    UGET     2   1      ; NickelConf
0021    TGETS    2   2  10  ; "frontLightLevel"
0022    TGETS    2   2  11  ; "set"
0023    KSHORT   3  15
0024    CALL     2   1   2
0025    UGET     2   1      ; NickelConf
0026    TGETS    2   2  12  ; "frontLightState"
0027    TGETS    2   2  11  ; "set"
0028    KPRI     3   1
0029    CALL     2   1   2
0030    GGET     2  13      ; "io"
0031    TGETS    2   2  14  ; "open"
0032    MOV      3   1
0033    KSTR     4  15      ; "r"
0034    CALL     2   2   3
0035    MOV      0   2
0036    GGET     2   1      ; "assert"
0037    TGETS    2   2   3  ; "Equals"
0038    KSTR     3  16      ; "[PowerOptions]\nFrontLightLevel=15\n"
0039    MOV      5   0
0040    TGETS    4   0  17  ; "read"
0041    KSTR     6  18      ; "*a"
0042    CALL     4   0   3
0043    CALLM    2   1   1
0044    MOV      3   0
0045    TGETS    2   0  19  ; "close"
0046    CALL     2   1   2
0047    UCLO     0 => 0048
0048 => RET0     0   1

-- BYTECODE -- nickel_conf_spec.lua:187-211
0001    GGET     0   0      ; "os"
0002    TGETS    0   0   1  ; "tmpname"
0003    CALL     0   2   1
0004    GGET     1   2      ; "io"
0005    TGETS    1   1   3  ; "open"
0006    MOV      2   0
0007    KSTR     3   4      ; "w"
0008    CALL     1   2   3
0009    MOV      3   1
0010    TGETS    2   1   5  ; "write"
0011    KSTR     4   6      ; "[PowerOptions]\nfoo=bar\n[OtherThing]\nb"~
0012    CALL     2   1   3
0013    MOV      3   1
0014    TGETS    2   1   7  ; "close"
0015    CALL     2   1   2
0016    UGET     2   0      ; NickelConf
0017    TGETS    2   2   8  ; "_set_kobo_conf_path"
0018    MOV      3   0
0019    CALL     2   1   2
0020    UGET     2   0      ; NickelConf
0021    TGETS    2   2   9  ; "frontLightLevel"
0022    TGETS    2   2  10  ; "set"
0023    CALL     2   1   1
0024    UGET     2   0      ; NickelConf
0025    TGETS    2   2  11  ; "frontLightState"
0026    TGETS    2   2  10  ; "set"
0027    CALL     2   1   1
0028    GGET     2   2      ; "io"
0029    TGETS    2   2   3  ; "open"
0030    MOV      3   0
0031    KSTR     4  12      ; "r"
0032    CALL     2   2   3
0033    MOV      1   2
0034    GGET     2  13      ; "assert"
0035    TGETS    2   2  14  ; "Equals"
0036    KSTR     3   6      ; "[PowerOptions]\nfoo=bar\n[OtherThing]\nb"~
0037    MOV      5   1
0038    TGETS    4   1  15  ; "read"
0039    KSTR     6  16      ; "*a"
0040    CALL     4   0   3
0041    CALLM    2   1   1
0042    MOV      3   1
0043    TGETS    2   1   7  ; "close"
0044    CALL     2   1   2
0045    GGET     2   0      ; "os"
0046    TGETS    2   2  17  ; "remove"
0047    MOV      3   0
0048    CALL     2   1   2
0049    RET0     0   1

-- BYTECODE -- nickel_conf_spec.lua:228-228
0001    UGET     0   0      ; NickelConf
0002    TGETS    0   0   0  ; "frontLightLevel"
0003    TGETS    0   0   1  ; "set"
0004    CALL     0   1   1
0005    RET0     0   1

-- BYTECODE -- nickel_conf_spec.lua:229-229
0001    UGET     0   0      ; NickelConf
0002    TGETS    0   0   0  ; "frontLightState"
0003    TGETS    0   0   1  ; "set"
0004    CALL     0   1   1
0005    RET0     0   1

-- BYTECODE -- nickel_conf_spec.lua:213-240
0001    GGET     0   0      ; "require"
0002    KSTR     1   1      ; "dbg"
0003    CALL     0   2   2
0004    MOV      2   0
0005    TGETS    1   0   2  ; "turnOn"
0006    CALL     1   1   2
0007    GGET     1   3      ; "package"
0008    TGETS    1   1   4  ; "reload"
0009    KSTR     2   5      ; "device/kobo/nickel_conf"
0010    CALL     1   2   2
0011    USETV    0   1      ; NickelConf
0012    GGET     1   6      ; "os"
0013    TGETS    1   1   7  ; "tmpname"
0014    CALL     1   2   1
0015    GGET     2   8      ; "io"
0016    TGETS    2   2   9  ; "open"
0017    MOV      3   1
0018    KSTR     4  10      ; "w"
0019    CALL     2   2   3
0020    MOV      4   2
0021    TGETS    3   2  11  ; "write"
0022    KSTR     5  12      ; "[PowerOptions]\nfoo=bar\n[OtherThing]\nb"~
0023    CALL     3   1   3
0024    MOV      4   2
0025    TGETS    3   2  13  ; "close"
0026    CALL     3   1   2
0027    UGET     3   0      ; NickelConf
0028    TGETS    3   3  14  ; "_set_kobo_conf_path"
0029    MOV      4   1
0030    CALL     3   1   2
0031    GGET     3  15      ; "assert"
0032    TGETS    3   3  16  ; "has_error"
0033    FNEW     4  17      ; nickel_conf_spec.lua:228
0034    CALL     3   1   2
0035    GGET     3  15      ; "assert"
0036    TGETS    3   3  16  ; "has_error"
0037    FNEW     4  18      ; nickel_conf_spec.lua:229
0038    CALL     3   1   2
0039    GGET     3   8      ; "io"
0040    TGETS    3   3   9  ; "open"
0041    MOV      4   1
0042    KSTR     5  19      ; "r"
0043    CALL     3   2   3
0044    MOV      2   3
0045    GGET     3  15      ; "assert"
0046    TGETS    3   3  20  ; "Equals"
0047    KSTR     4  12      ; "[PowerOptions]\nfoo=bar\n[OtherThing]\nb"~
0048    MOV      6   2
0049    TGETS    5   2  21  ; "read"
0050    KSTR     7  22      ; "*a"
0051    CALL     5   0   3
0052    CALLM    3   1   1
0053    MOV      4   2
0054    TGETS    3   2  13  ; "close"
0055    CALL     3   1   2
0056    GGET     3   6      ; "os"
0057    TGETS    3   3  23  ; "remove"
0058    MOV      4   1
0059    CALL     3   1   2
0060    RET0     0   1

-- BYTECODE -- nickel_conf_spec.lua:9-241
0001    GGET     0   0      ; "it"
0002    KSTR     1   1      ; "should read value"
0003    FNEW     2   2      ; nickel_conf_spec.lua:10
0004    CALL     0   1   3
0005    GGET     0   0      ; "it"
0006    KSTR     1   3      ; "should also read value"
0007    FNEW     2   4      ; nickel_conf_spec.lua:31
0008    CALL     0   1   3
0009    GGET     0   0      ; "it"
0010    KSTR     1   5      ; "should have default value"
0011    FNEW     2   6      ; nickel_conf_spec.lua:52
0012    CALL     0   1   3
0013    GGET     0   0      ; "it"
0014    KSTR     1   7      ; "should create section"
0015    FNEW     2   8      ; nickel_conf_spec.lua:70
0016    CALL     0   1   3
0017    GGET     0   0      ; "it"
0018    KSTR     1   9      ; "should replace value"
0019    FNEW     2  10      ; nickel_conf_spec.lua:109
0020    CALL     0   1   3
0021    GGET     0   0      ; "it"
0022    KSTR     1  11      ; "should insert entry"
0023    FNEW     2  12      ; nickel_conf_spec.lua:141
0024    CALL     0   1   3
0025    GGET     0   0      ; "it"
0026    KSTR     1  13      ; "should create config file"
0027    FNEW     2  14      ; nickel_conf_spec.lua:168
0028    CALL     0   1   3
0029    GGET     0   0      ; "it"
0030    KSTR     1  15      ; "should not crash on nil values for regul"~
0031    FNEW     2  16      ; nickel_conf_spec.lua:187
0032    CALL     0   1   3
0033    GGET     0   0      ; "it"
0034    KSTR     1  17      ; "should crash on nil values in debug mode"
0035    FNEW     2  18      ; nickel_conf_spec.lua:213
0036    CALL     0   1   3
0037    RET0     0   1

-- BYTECODE -- nickel_conf_spec.lua:1-242
0001    KNIL     0   1
0002    GGET     2   0      ; "setup"
0003    FNEW     3   1      ; nickel_conf_spec.lua:3
0004    CALL     2   1   2
0005    GGET     2   2      ; "describe"
0006    KSTR     3   3      ; "Frontlight module"
0007    FNEW     4   4      ; nickel_conf_spec.lua:9
0008    CALL     2   1   3
0009    UCLO     0 => 0010
0010 => RET0     0   1

-- BYTECODE -- nickel_conf_spec.lua:0-243
0001    GGET     0   0      ; "describe"
0002    KSTR     1   1      ; "Nickel configuation module"
0003    FNEW     2   2      ; nickel_conf_spec.lua:1
0004    CALL     0   1   3
0005    RET0     0   1

