
main <./frontend/ui/widget/notification.lua:0,0> (75 instructions, 300 bytes at 0x7fda9a4068d0)
0+ params, 19 slots, 0 upvalues, 14 locals, 30 constants, 5 functions
	1	[5]	GETGLOBAL	0 -1	; require
	2	[5]	LOADK    	1 -2	; "ffi/blitbuffer"
	3	[5]	CALL     	0 2 2
	4	[6]	GETGLOBAL	1 -1	; require
	5	[6]	LOADK    	2 -3	; "ui/widget/container/centercontainer"
	6	[6]	CALL     	1 2 2
	7	[7]	GETGLOBAL	2 -1	; require
	8	[7]	LOADK    	3 -4	; "device"
	9	[7]	CALL     	2 2 2
	10	[8]	GETGLOBAL	3 -1	; require
	11	[8]	LOADK    	4 -5	; "ui/font"
	12	[8]	CALL     	3 2 2
	13	[9]	GETGLOBAL	4 -1	; require
	14	[9]	LOADK    	5 -6	; "ui/widget/container/framecontainer"
	15	[9]	CALL     	4 2 2
	16	[10]	GETGLOBAL	5 -1	; require
	17	[10]	LOADK    	6 -7	; "ui/geometry"
	18	[10]	CALL     	5 2 2
	19	[11]	GETGLOBAL	6 -1	; require
	20	[11]	LOADK    	7 -8	; "ui/gesturerange"
	21	[11]	CALL     	6 2 2
	22	[12]	GETGLOBAL	7 -1	; require
	23	[12]	LOADK    	8 -9	; "ui/widget/container/inputcontainer"
	24	[12]	CALL     	7 2 2
	25	[13]	GETGLOBAL	8 -1	; require
	26	[13]	LOADK    	9 -10	; "ui/size"
	27	[13]	CALL     	8 2 2
	28	[14]	GETGLOBAL	9 -1	; require
	29	[14]	LOADK    	10 -11	; "ui/widget/textwidget"
	30	[14]	CALL     	9 2 2
	31	[15]	GETGLOBAL	10 -1	; require
	32	[15]	LOADK    	11 -12	; "ui/uimanager"
	33	[15]	CALL     	10 2 2
	34	[16]	GETTABLE 	11 2 -13	; "input"
	35	[17]	GETTABLE 	12 2 -14	; "screen"
	36	[19]	SELF     	13 7 -15	; "new"
	37	[19]	NEWTABLE 	15 0 5
	38	[20]	SELF     	16 3 -17	; "getFace"
	39	[20]	LOADK    	18 -18	; "x_smallinfofont"
	40	[20]	CALL     	16 3 2
	41	[20]	SETTABLE 	15 -16 16	; "face" -
	42	[21]	SETTABLE 	15 -19 -20	; "text" "Null Message"
	43	[22]	SETTABLE 	15 -21 -22	; "timeout" nil
	44	[23]	GETTABLE 	16 8 -23	; "margin"
	45	[23]	GETTABLE 	16 16 -24	; "default"
	46	[23]	SETTABLE 	15 -23 16	; "margin" -
	47	[24]	GETTABLE 	16 8 -25	; "padding"
	48	[24]	GETTABLE 	16 16 -24	; "default"
	49	[24]	SETTABLE 	15 -25 16	; "padding" -
	50	[19]	CALL     	13 3 2
	51	[72]	CLOSURE  	14 0	; 0x7fda9a4070a0
	52	[72]	MOVE     	0 2
	53	[72]	MOVE     	0 11
	54	[72]	MOVE     	0 6
	55	[72]	MOVE     	0 5
	56	[72]	MOVE     	0 12
	57	[72]	MOVE     	0 9
	58	[72]	MOVE     	0 1
	59	[72]	MOVE     	0 4
	60	[72]	MOVE     	0 0
	61	[27]	SETTABLE 	13 -26 14	; "init" -
	62	[79]	CLOSURE  	14 1	; 0x7fda9a407b10
	63	[79]	MOVE     	0 10
	64	[74]	SETTABLE 	13 -27 14	; "onCloseWidget" -
	65	[90]	CLOSURE  	14 2	; 0x7fda9a4082b0
	66	[90]	MOVE     	0 10
	67	[81]	SETTABLE 	13 -28 14	; "onShow" -
	68	[98]	CLOSURE  	14 3	; 0x7fda9a4089f0
	69	[98]	MOVE     	0 10
	70	[92]	SETTABLE 	13 -29 14	; "onAnyKeyPressed" -
	71	[109]	CLOSURE  	14 4	; 0x7fda9a4083c0
	72	[109]	MOVE     	0 10
	73	[100]	SETTABLE 	13 -30 14	; "onTapClose" -
	74	[111]	RETURN   	13 2
	75	[111]	RETURN   	0 1

function <./frontend/ui/widget/notification.lua:27,72> (105 instructions, 420 bytes at 0x7fda9a4070a0)
1 param, 16 slots, 9 upvalues, 3 locals, 34 constants, 0 functions
	1	[28]	GETUPVAL 	1 0	; Device
	2	[28]	SELF     	1 1 -1	; "hasKeys"
	3	[28]	CALL     	1 2 2
	4	[28]	TEST     	1 0 0
	5	[28]	JMP      	12	; to 18
	6	[29]	NEWTABLE 	1 0 1
	7	[30]	NEWTABLE 	2 1 2
	8	[30]	NEWTABLE 	3 1 0
	9	[30]	GETUPVAL 	4 1	; Input
	10	[30]	GETTABLE 	4 4 -4	; "group"
	11	[30]	GETTABLE 	4 4 -5	; "Any"
	12	[30]	SETLIST  	3 1 1	; 1
	13	[31]	SETTABLE 	2 -6 -7	; "seqtext" "any key"
	14	[31]	SETTABLE 	2 -8 -9	; "doc" "close dialog"
	15	[31]	SETLIST  	2 1 1	; 1
	16	[31]	SETTABLE 	1 -3 2	; "AnyKeyPressed" -
	17	[32]	SETTABLE 	0 -2 1	; "key_events" -
	18	[34]	GETUPVAL 	1 0	; Device
	19	[34]	SELF     	1 1 -10	; "isTouchDevice"
	20	[34]	CALL     	1 2 2
	21	[34]	TEST     	1 0 0
	22	[34]	JMP      	24	; to 47
	23	[35]	GETTABLE 	1 0 -11	; "ges_events"
	24	[35]	NEWTABLE 	2 0 0
	25	[36]	GETUPVAL 	3 2	; GestureRange
	26	[36]	SELF     	3 3 -13	; "new"
	27	[36]	NEWTABLE 	5 0 2
	28	[37]	SETTABLE 	5 -14 -15	; "ges" "tap"
	29	[38]	GETUPVAL 	6 3	; Geom
	30	[38]	SELF     	6 6 -13	; "new"
	31	[38]	NEWTABLE 	8 0 4
	32	[39]	SETTABLE 	8 -17 -18	; "x" 0
	33	[39]	SETTABLE 	8 -19 -18	; "y" 0
	34	[40]	GETUPVAL 	9 4	; Screen
	35	[40]	SELF     	9 9 -21	; "getWidth"
	36	[40]	CALL     	9 2 2
	37	[40]	SETTABLE 	8 -20 9	; "w" -
	38	[41]	GETUPVAL 	9 4	; Screen
	39	[41]	SELF     	9 9 -23	; "getHeight"
	40	[41]	CALL     	9 2 2
	41	[41]	SETTABLE 	8 -22 9	; "h" -
	42	[38]	CALL     	6 3 2
	43	[42]	SETTABLE 	5 -16 6	; "range" -
	44	[36]	CALL     	3 3 0
	45	[44]	SETLIST  	2 0 1	; 1
	46	[44]	SETTABLE 	1 -12 2	; "TapClose" -
	47	[48]	GETUPVAL 	1 5	; TextWidget
	48	[48]	SELF     	1 1 -13	; "new"
	49	[48]	NEWTABLE 	3 0 2
	50	[49]	GETTABLE 	4 0 -24	; "text"
	51	[49]	SETTABLE 	3 -24 4	; "text" -
	52	[50]	GETTABLE 	4 0 -25	; "face"
	53	[50]	SETTABLE 	3 -25 4	; "face" -
	54	[48]	CALL     	1 3 2
	55	[52]	SELF     	2 1 -26	; "getSize"
	56	[52]	CALL     	2 2 2
	57	[53]	GETUPVAL 	3 6	; CenterContainer
	58	[53]	SELF     	3 3 -13	; "new"
	59	[53]	NEWTABLE 	5 0 1
	60	[54]	GETUPVAL 	6 3	; Geom
	61	[54]	SELF     	6 6 -13	; "new"
	62	[54]	NEWTABLE 	8 0 2
	63	[55]	GETUPVAL 	9 4	; Screen
	64	[55]	SELF     	9 9 -21	; "getWidth"
	65	[55]	CALL     	9 2 2
	66	[55]	SETTABLE 	8 -20 9	; "w" -
	67	[56]	GETUPVAL 	9 4	; Screen
	68	[56]	SELF     	9 9 -23	; "getHeight"
	69	[56]	CALL     	9 2 2
	70	[56]	DIV      	9 9 -29	; - 10
	71	[56]	SETTABLE 	8 -22 9	; "h" -
	72	[54]	CALL     	6 3 2
	73	[57]	SETTABLE 	5 -28 6	; "dimen" -
	74	[58]	GETUPVAL 	6 7	; FrameContainer
	75	[58]	SELF     	6 6 -13	; "new"
	76	[58]	NEWTABLE 	8 0 4
	77	[59]	GETUPVAL 	9 8	; Blitbuffer
	78	[59]	GETTABLE 	9 9 -31	; "COLOR_WHITE"
	79	[59]	SETTABLE 	8 -30 9	; "background" -
	80	[60]	SETTABLE 	8 -32 -18	; "radius" 0
	81	[61]	GETTABLE 	9 0 -33	; "margin"
	82	[61]	SETTABLE 	8 -33 9	; "margin" -
	83	[62]	GETTABLE 	9 0 -34	; "padding"
	84	[62]	SETTABLE 	8 -34 9	; "padding" -
	85	[63]	GETUPVAL 	9 6	; CenterContainer
	86	[63]	SELF     	9 9 -13	; "new"
	87	[63]	NEWTABLE 	11 1 1
	88	[64]	GETUPVAL 	12 3	; Geom
	89	[64]	SELF     	12 12 -13	; "new"
	90	[64]	NEWTABLE 	14 0 2
	91	[65]	GETTABLE 	15 2 -20	; "w"
	92	[65]	SETTABLE 	14 -20 15	; "w" -
	93	[66]	GETTABLE 	15 2 -22	; "h"
	94	[66]	SETTABLE 	14 -22 15	; "h" -
	95	[64]	CALL     	12 3 2
	96	[67]	SETTABLE 	11 -28 12	; "dimen" -
	97	[69]	MOVE     	12 1
	98	[69]	SETLIST  	11 1 1	; 1
	99	[63]	CALL     	9 3 0
	100	[70]	SETLIST  	8 0 1	; 1
	101	[58]	CALL     	6 3 0
	102	[71]	SETLIST  	5 0 1	; 1
	103	[53]	CALL     	3 3 2
	104	[71]	SETTABLE 	0 -27 3	; 1 -
	105	[72]	RETURN   	0 1

function <./frontend/ui/widget/notification.lua:74,79> (9 instructions, 36 bytes at 0x7fda9a407b10)
1 param, 5 slots, 1 upvalue, 1 local, 1 constant, 1 function
	1	[75]	GETUPVAL 	1 0	; UIManager
	2	[75]	SELF     	1 1 -1	; "setDirty"
	3	[75]	LOADNIL  	3 3
	4	[77]	CLOSURE  	4 0	; 0x7fda9a408190
	5	[77]	MOVE     	0 0
	6	[75]	CALL     	1 4 1
	7	[78]	LOADBOOL 	1 1 0
	8	[78]	RETURN   	1 2
	9	[79]	RETURN   	0 1

function <./frontend/ui/widget/notification.lua:75,77> (7 instructions, 28 bytes at 0x7fda9a408190)
0 params, 2 slots, 1 upvalue, 0 locals, 3 constants, 0 functions
	1	[76]	LOADK    	0 -1	; "ui"
	2	[76]	GETUPVAL 	1 0	; self
	3	[76]	GETTABLE 	1 1 -2	; 1
	4	[76]	GETTABLE 	1 1 -2	; 1
	5	[76]	GETTABLE 	1 1 -3	; "dimen"
	6	[76]	RETURN   	0 3
	7	[77]	RETURN   	0 1

function <./frontend/ui/widget/notification.lua:81,90> (19 instructions, 76 bytes at 0x7fda9a4082b0)
1 param, 5 slots, 1 upvalue, 1 local, 3 constants, 2 functions
	1	[83]	GETUPVAL 	1 0	; UIManager
	2	[83]	SELF     	1 1 -1	; "setDirty"
	3	[83]	MOVE     	3 0
	4	[85]	CLOSURE  	4 0	; 0x7fda9a408650
	5	[85]	MOVE     	0 0
	6	[83]	CALL     	1 4 1
	7	[86]	GETTABLE 	1 0 -2	; "timeout"
	8	[86]	TEST     	1 0 0
	9	[86]	JMP      	7	; to 17
	10	[87]	GETUPVAL 	1 0	; UIManager
	11	[87]	SELF     	1 1 -3	; "scheduleIn"
	12	[87]	GETTABLE 	3 0 -2	; "timeout"
	13	[87]	CLOSURE  	4 1	; 0x7fda9a4067c0
	14	[87]	GETUPVAL 	0 0	; UIManager
	15	[87]	MOVE     	0 0
	16	[87]	CALL     	1 4 1
	17	[89]	LOADBOOL 	1 1 0
	18	[89]	RETURN   	1 2
	19	[90]	RETURN   	0 1

function <./frontend/ui/widget/notification.lua:83,85> (7 instructions, 28 bytes at 0x7fda9a408650)
0 params, 2 slots, 1 upvalue, 0 locals, 3 constants, 0 functions
	1	[84]	LOADK    	0 -1	; "ui"
	2	[84]	GETUPVAL 	1 0	; self
	3	[84]	GETTABLE 	1 1 -2	; 1
	4	[84]	GETTABLE 	1 1 -2	; 1
	5	[84]	GETTABLE 	1 1 -3	; "dimen"
	6	[84]	RETURN   	0 3
	7	[85]	RETURN   	0 1

function <./frontend/ui/widget/notification.lua:87,87> (5 instructions, 20 bytes at 0x7fda9a4067c0)
0 params, 3 slots, 2 upvalues, 0 locals, 1 constant, 0 functions
	1	[87]	GETUPVAL 	0 0	; UIManager
	2	[87]	SELF     	0 0 -1	; "close"
	3	[87]	GETUPVAL 	2 1	; self
	4	[87]	CALL     	0 3 1
	5	[87]	RETURN   	0 1

function <./frontend/ui/widget/notification.lua:92,98> (10 instructions, 40 bytes at 0x7fda9a4089f0)
1 param, 4 slots, 1 upvalue, 1 local, 2 constants, 0 functions
	1	[94]	GETUPVAL 	1 0	; UIManager
	2	[94]	SELF     	1 1 -1	; "close"
	3	[94]	MOVE     	3 0
	4	[94]	CALL     	1 3 1
	5	[95]	GETTABLE 	1 0 -2	; "timeout"
	6	[95]	TEST     	1 0 1
	7	[95]	JMP      	2	; to 10
	8	[96]	LOADBOOL 	1 1 0
	9	[96]	RETURN   	1 2
	10	[98]	RETURN   	0 1

function <./frontend/ui/widget/notification.lua:100,109> (10 instructions, 40 bytes at 0x7fda9a4083c0)
1 param, 4 slots, 1 upvalue, 1 local, 2 constants, 0 functions
	1	[101]	GETUPVAL 	1 0	; UIManager
	2	[101]	SELF     	1 1 -1	; "close"
	3	[101]	MOVE     	3 0
	4	[101]	CALL     	1 3 1
	5	[106]	GETTABLE 	1 0 -2	; "timeout"
	6	[106]	TEST     	1 0 1
	7	[106]	JMP      	2	; to 10
	8	[107]	LOADBOOL 	1 1 0
	9	[107]	RETURN   	1 2
	10	[109]	RETURN   	0 1
