-- BYTECODE -- opds_spec.lua:232-236
0001    GGET     0   0      ; "require"
0002    KSTR     1   1      ; "commonrequire"
0003    CALL     0   1   2
0004    GGET     0   0      ; "require"
0005    KSTR     1   2      ; "ui/opdsparser"
0006    CALL     0   2   2
0007    USETV    0   0      ; OPDSParser
0008    GGET     0   0      ; "require"
0009    KSTR     1   3      ; "ui/widget/opdsbrowser"
0010    CALL     0   2   2
0011    USETV    1   0      ; OPDSBrowser
0012    RET0     0   1

-- BYTECODE -- opds_spec.lua:239-253
0001    UGET     0   0      ; OPDSParser
0002    MOV      1   0
0003    TGETS    0   0   0  ; "parse"
0004    UGET     2   1      ; navigation_sample
0005    CALL     0   2   3
0006    TGETS    1   0   1  ; "feed"
0007    GGET     2   2      ; "assert"
0008    TGETS    2   2   3  ; "truthy"
0009    MOV      3   1
0010    CALL     2   1   2
0011    GGET     2   2      ; "assert"
0012    TGETS    2   2   4  ; "are"
0013    TGETS    2   2   5  ; "same"
0014    TGETS    3   1   6  ; "title"
0015    KSTR     4   7      ; "Project Gutenberg"
0016    CALL     2   1   3
0017    TGETS    2   1   8  ; "entry"
0018    GGET     3   2      ; "assert"
0019    TGETS    3   3   3  ; "truthy"
0020    MOV      4   2
0021    CALL     3   1   2
0022    GGET     3   2      ; "assert"
0023    TGETS    3   3   4  ; "are"
0024    TGETS    3   3   5  ; "same"
0025    LEN      4   2
0026    KSHORT   5   3
0027    CALL     3   1   3
0028    TGETB    3   2   3
0029    GGET     4   2      ; "assert"
0030    TGETS    4   4   4  ; "are"
0031    TGETS    4   4   5  ; "same"
0032    TGETS    5   3   6  ; "title"
0033    KSTR     6   9      ; "Random"
0034    CALL     4   1   3
0035    GGET     4   2      ; "assert"
0036    TGETS    4   4   4  ; "are"
0037    TGETS    4   4   5  ; "same"
0038    TGETS    5   3  10  ; "id"
0039    KSTR     6  11      ; "http://m.gutenberg.org/ebooks/search.opd"~
0040    CALL     4   1   3
0041    GGET     4   2      ; "assert"
0042    TGETS    4   4   4  ; "are"
0043    TGETS    4   4   5  ; "same"
0044    KSTR     5  12      ; "/ebooks/search.opds/?sort_order=random&l"~
0045    TGETS    6   3  13  ; "link"
0046    TGETB    6   6   1
0047    TGETS    6   6  14  ; "href"
0048    CALL     4   1   3
0049    RET0     0   1

-- BYTECODE -- opds_spec.lua:254-264
0001    UGET     0   0      ; OPDSParser
0002    MOV      1   0
0003    TGETS    0   0   0  ; "parse"
0004    UGET     2   1      ; acquisition_sample
0005    CALL     0   2   3
0006    TGETS    1   0   1  ; "feed"
0007    GGET     2   2      ; "assert"
0008    TGETS    2   2   3  ; "truthy"
0009    MOV      3   1
0010    CALL     2   1   2
0011    TGETS    2   1   4  ; "entry"
0012    GGET     3   2      ; "assert"
0013    TGETS    3   3   3  ; "truthy"
0014    MOV      4   2
0015    CALL     3   1   2
0016    GGET     3   2      ; "assert"
0017    TGETS    3   3   5  ; "are"
0018    TGETS    3   3   6  ; "same"
0019    LEN      4   2
0020    KSHORT   5   2
0021    CALL     3   1   3
0022    TGETB    3   2   2
0023    GGET     4   2      ; "assert"
0024    TGETS    4   4   5  ; "are"
0025    TGETS    4   4   6  ; "same"
0026    TGETS    5   3   7  ; "title"
0027    KSTR     6   8      ; "1000 Mythological Characters Briefly Des"~
0028    CALL     4   1   3
0029    GGET     4   2      ; "assert"
0030    TGETS    4   4   5  ; "are"
0031    TGETS    4   4   6  ; "same"
0032    TGETS    5   3   9  ; "link"
0033    TGETB    5   5   1
0034    TGETS    5   5  10  ; "href"
0035    KSTR     6  11      ; "//www.gutenberg.org/ebooks/42474.epub.im"~
0036    CALL     4   1   3
0037    RET0     0   1

-- BYTECODE -- opds_spec.lua:238-265
0001    GGET     0   0      ; "it"
0002    KSTR     1   1      ; "should parse OPDS navigation catalog"
0003    FNEW     2   2      ; opds_spec.lua:239
0004    CALL     0   1   3
0005    GGET     0   0      ; "it"
0006    KSTR     1   3      ; "should parse OPDS acquisition catalog"
0007    FNEW     2   4      ; opds_spec.lua:254
0008    CALL     0   1   3
0009    RET0     0   1

-- BYTECODE -- opds_spec.lua:269-276
0001    UGET     0   0      ; OPDSParser
0002    MOV      1   0
0003    TGETS    0   0   0  ; "parse"
0004    UGET     2   1      ; navigation_sample
0005    CALL     0   2   3
0006    UGET     1   2      ; OPDSBrowser
0007    MOV      2   1
0008    TGETS    1   1   1  ; "genItemTableFromCatalog"
0009    MOV      3   0
0010    KSTR     4   2      ; "http://m.gutenberg.org/ebooks.opds/?form"~
0011    CALL     1   2   4
0012    GGET     2   3      ; "assert"
0013    TGETS    2   2   4  ; "truthy"
0014    MOV      3   1
0015    CALL     2   1   2
0016    GGET     2   3      ; "assert"
0017    TGETS    2   2   5  ; "are"
0018    TGETS    2   2   6  ; "same"
0019    TGETB    3   1   1
0020    TGETS    3   3   7  ; "title"
0021    KSTR     4   8      ; "Popular"
0022    CALL     2   1   3
0023    GGET     2   3      ; "assert"
0024    TGETS    2   2   5  ; "are"
0025    TGETS    2   2   6  ; "same"
0026    TGETB    3   1   1
0027    TGETS    3   3   9  ; "url"
0028    KSTR     4  10      ; "http://m.gutenberg.org/ebooks/search.opd"~
0029    CALL     2   1   3
0030    RET0     0   1

-- BYTECODE -- opds_spec.lua:277-286
0001    UGET     0   0      ; OPDSParser
0002    MOV      1   0
0003    TGETS    0   0   0  ; "parse"
0004    UGET     2   1      ; popular_new_sample
0005    CALL     0   2   3
0006    UGET     1   2      ; OPDSBrowser
0007    MOV      2   1
0008    TGETS    1   1   1  ; "genItemTableFromCatalog"
0009    MOV      3   0
0010    KSTR     4   2      ; "http://www.feedbooks.com/publicdomain/ca"~
0011    CALL     1   2   4
0012    GGET     2   3      ; "assert"
0013    TGETS    2   2   4  ; "truthy"
0014    MOV      3   1
0015    CALL     2   1   2
0016    GGET     2   3      ; "assert"
0017    TGETS    2   2   5  ; "are"
0018    TGETS    2   2   6  ; "same"
0019    TGETB    3   1   1
0020    TGETS    3   3   7  ; "title"
0021    KSTR     4   8      ; "Most Popular"
0022    CALL     2   1   3
0023    GGET     2   3      ; "assert"
0024    TGETS    2   2   5  ; "are"
0025    TGETS    2   2   6  ; "same"
0026    TGETB    3   1   1
0027    TGETS    3   3   9  ; "url"
0028    KSTR     4  10      ; "http://www.feedbooks.com/books/top.atom"
0029    CALL     2   1   3
0030    GGET     2   3      ; "assert"
0031    TGETS    2   2   5  ; "are"
0032    TGETS    2   2   6  ; "same"
0033    TGETB    3   1   2
0034    TGETS    3   3   7  ; "title"
0035    KSTR     4  11      ; "Recently Added"
0036    CALL     2   1   3
0037    GGET     2   3      ; "assert"
0038    TGETS    2   2   5  ; "are"
0039    TGETS    2   2   6  ; "same"
0040    TGETB    3   1   2
0041    TGETS    3   3   9  ; "url"
0042    KSTR     4  12      ; "http://www.feedbooks.com/books/recent.at"~
0043    CALL     2   1   3
0044    RET0     0   1

-- BYTECODE -- opds_spec.lua:287-293
0001    UGET     0   0      ; OPDSParser
0002    MOV      1   0
0003    TGETS    0   0   0  ; "parse"
0004    UGET     2   1      ; facet_sample
0005    CALL     0   2   3
0006    UGET     1   2      ; OPDSBrowser
0007    MOV      2   1
0008    TGETS    1   1   1  ; "genItemTableFromCatalog"
0009    MOV      3   0
0010    KSTR     4   2      ; "http://flibusta.net/opds"
0011    CALL     1   2   4
0012    GGET     2   3      ; "assert"
0013    TGETS    2   2   4  ; "truthy"
0014    MOV      3   1
0015    CALL     2   1   2
0016    GGET     2   3      ; "assert"
0017    TGETS    2   2   5  ; "are"
0018    TGETS    2   2   6  ; "same"
0019    TGETB    3   1   1
0020    TGETS    3   3   7  ; "url"
0021    KSTR     4   8      ; "http://flibusta.net/opds/author/75357"
0022    CALL     2   1   3
0023    RET0     0   1

-- BYTECODE -- opds_spec.lua:268-294
0001    GGET     0   0      ; "it"
0002    KSTR     1   1      ; "should generate URL on rel=subsection"
0003    FNEW     2   2      ; opds_spec.lua:269
0004    CALL     0   1   3
0005    GGET     0   0      ; "it"
0006    KSTR     1   3      ; "should generate URL on rel=popular and r"~
0007    FNEW     2   4      ; opds_spec.lua:277
0008    CALL     0   1   3
0009    GGET     0   0      ; "it"
0010    KSTR     1   5      ; "should use the main URL for faceted link"~
0011    FNEW     2   6      ; opds_spec.lua:287
0012    CALL     0   1   3
0013    RET0     0   1

-- BYTECODE -- opds_spec.lua:296-302
0001    UGET     0   0      ; OPDSParser
0002    MOV      1   0
0003    TGETS    0   0   0  ; "parse"
0004    UGET     2   1      ; facet_sample
0005    CALL     0   2   3
0006    UGET     1   2      ; OPDSBrowser
0007    MOV      2   1
0008    TGETS    1   1   1  ; "genItemTableFromCatalog"
0009    MOV      3   0
0010    KSTR     4   2      ; "http://flibusta.net/opds"
0011    CALL     1   2   4
0012    GGET     2   3      ; "assert"
0013    TGETS    2   2   4  ; "truthy"
0014    MOV      3   1
0015    CALL     2   1   2
0016    GGET     2   3      ; "assert"
0017    TGETS    2   2   5  ; "are_not"
0018    TGETS    2   2   6  ; "same"
0019    TGETB    3   1   1
0020    TGETS    3   3   7  ; "image"
0021    KSTR     4   8      ; "http://flibusta.net/opds/author/75357"
0022    CALL     2   1   3
0023    RET0     0   1

-- BYTECODE -- opds_spec.lua:267-303
0001    GGET     0   0      ; "describe"
0002    KSTR     1   1      ; "URL generation"
0003    FNEW     2   2      ; opds_spec.lua:268
0004    CALL     0   1   3
0005    GGET     0   3      ; "it"
0006    KSTR     1   4      ; "should not fill item table incorrectly w"~
0007    FNEW     2   5      ; opds_spec.lua:296
0008    CALL     0   1   3
0009    RET0     0   1

-- BYTECODE -- opds_spec.lua:229-304
0001    KNIL     0   1
0002    GGET     2   0      ; "setup"
0003    FNEW     3   1      ; opds_spec.lua:232
0004    CALL     2   1   2
0005    GGET     2   2      ; "describe"
0006    KSTR     3   3      ; "OPDS parser module"
0007    FNEW     4   4      ; opds_spec.lua:238
0008    CALL     2   1   3
0009    GGET     2   2      ; "describe"
0010    KSTR     3   5      ; "OPDS browser module"
0011    FNEW     4   6      ; opds_spec.lua:267
0012    CALL     2   1   3
0013    UCLO     0 => 0014
0014 => RET0     0   1

-- BYTECODE -- opds_spec.lua:0-305
0001    KSTR     0   0      ; "<?xml version="1.0" encoding="utf-8"?>\n"~
0002    KSTR     1   1      ; "<?xml version="1.0" encoding="utf-8"?>\n"~
0003    KSTR     2   2      ; "<?xml version="1.0" encoding="UTF-8"?>\n"~
0004    KSTR     3   3      ; "<?xml version="1.0" encoding="utf-8"?>\n"~
0005    GGET     4   4      ; "describe"
0006    KSTR     5   5      ; "OPDS module #nocov"
0007    FNEW     6   6      ; opds_spec.lua:229
0008    CALL     4   1   3
0009    UCLO     0 => 0010
0010 => RET0     0   1

