-- BYTECODE -- opdscatalog.lua:16-16
0001    RET0     0   1

-- BYTECODE -- opdscatalog.lua:26-26
0001    UGET     0   0      ; self
0002    MOV      1   0
0003    TGETS    0   0   0  ; "onClose"
0004    CALLT    0   2

-- BYTECODE -- opdscatalog.lua:33-36
0001    UGET     0   0      ; self
0002    MOV      1   0
0003    TGETS    0   0   0  ; "onClose"
0004    CALL     0   1   2
0005    UGET     0   1      ; ReaderUI
0006    MOV      1   0
0007    TGETS    0   0   1  ; "showReader"
0008    UGET     2   2      ; downloaded_file
0009    CALL     0   1   3
0010    RET0     0   1

-- BYTECODE -- opdscatalog.lua:27-38
0001    UGET     1   0      ; UIManager
0002    MOV      2   1
0003    TGETS    1   1   0  ; "show"
0004    UGET     3   1      ; ConfirmBox
0005    MOV      4   3
0006    TGETS    3   3   1  ; "new"
0007    TDUP     5   4
0008    UGET     6   2      ; T
0009    UGET     7   3      ; _
0010    KSTR     8   2      ; "File saved to:\n%1\nWould you like to re"~
0011    CALL     7   2   2
0012    UGET     8   4      ; BD
0013    TGETS    8   8   3  ; "filepath"
0014    MOV      9   0
0015    CALL     8   0   2
0016    CALLM    6   2   1
0017    TSETS    6   5   5  ; "text"
0018    UGET     6   3      ; _
0019    KSTR     7   6      ; "Read now"
0020    CALL     6   2   2
0021    TSETS    6   5   7  ; "ok_text"
0022    UGET     6   3      ; _
0023    KSTR     7   8      ; "Read later"
0024    CALL     6   2   2
0025    TSETS    6   5   9  ; "cancel_text"
0026    FNEW     6  10      ; opdscatalog.lua:33
0027    TSETS    6   5  11  ; "ok_callback"
0028    CALL     3   0   3
0029    CALLM    1   1   1
0030    UCLO     0 => 0031
0031 => RET0     0   1

-- BYTECODE -- opdscatalog.lua:19-47
0001    UGET     1   0      ; OPDSBrowser
0002    MOV      2   1
0003    TGETS    1   1   0  ; "new"
0004    TDUP     3   2
0005    TGETS    4   0   1  ; "title"
0006    TSETS    4   3   1  ; "title"
0007    TSETS    0   3   3  ; "show_parent"
0008    FNEW     4   4      ; opdscatalog.lua:26
0009    TSETS    4   3   5  ; "close_callback"
0010    FNEW     4   6      ; opdscatalog.lua:27
0011    TSETS    4   3   7  ; "file_downloaded_callback"
0012    CALL     1   2   3
0013    UGET     2   7      ; FrameContainer
0014    MOV      3   2
0015    TGETS    2   2   0  ; "new"
0016    TDUP     4   8
0017    UGET     5   8      ; Blitbuffer
0018    TGETS    5   5   9  ; "COLOR_WHITE"
0019    TSETS    5   4  10  ; "background"
0020    TSETB    1   4   1
0021    CALL     2   2   3
0022    TSETB    2   0   1
0023    UCLO     0 => 0024
0024 => RET0     0   1

-- BYTECODE -- opdscatalog.lua:50-52
0001    KSTR     0   0      ; "ui"
0002    UGET     1   0      ; self
0003    TGETB    1   1   1
0004    TGETS    1   1   1  ; "dimen"
0005    RET      0   3

-- BYTECODE -- opdscatalog.lua:49-53
0001    UGET     1   0      ; UIManager
0002    MOV      2   1
0003    TGETS    1   1   0  ; "setDirty"
0004    MOV      3   0
0005    FNEW     4   1      ; opdscatalog.lua:50
0006    CALL     1   1   4
0007    UCLO     0 => 0008
0008 => RET0     0   1

-- BYTECODE -- opdscatalog.lua:56-58
0001    KSTR     0   0      ; "partial"
0002    UGET     1   0      ; self
0003    TGETB    1   1   1
0004    TGETS    1   1   1  ; "dimen"
0005    RET      0   3

-- BYTECODE -- opdscatalog.lua:55-59
0001    UGET     1   0      ; UIManager
0002    MOV      2   1
0003    TGETS    1   1   0  ; "setDirty"
0004    KPRI     3   0
0005    FNEW     4   1      ; opdscatalog.lua:56
0006    CALL     1   1   4
0007    UCLO     0 => 0008
0008 => RET0     0   1

-- BYTECODE -- opdscatalog.lua:66-68
0001    RET0     0   1

-- BYTECODE -- opdscatalog.lua:61-70
0001    UGET     1   0      ; logger
0002    TGETS    1   1   0  ; "dbg"
0003    KSTR     2   1      ; "show OPDS catalog"
0004    CALL     1   1   2
0005    UGET     1   1      ; UIManager
0006    MOV      2   1
0007    TGETS    1   1   2  ; "show"
0008    UGET     3   2      ; OPDSCatalog
0009    MOV      4   3
0010    TGETS    3   3   3  ; "new"
0011    TDUP     5   5
0012    UGET     6   3      ; Screen
0013    MOV      7   6
0014    TGETS    6   6   4  ; "getSize"
0015    CALL     6   2   2
0016    TSETS    6   5   6  ; "dimen"
0017    FNEW     6   7      ; opdscatalog.lua:66
0018    TSETS    6   5   8  ; "onExit"
0019    CALL     3   0   3
0020    CALLM    1   1   1
0021    RET0     0   1

-- BYTECODE -- opdscatalog.lua:72-79
0001    UGET     1   0      ; logger
0002    TGETS    1   1   0  ; "dbg"
0003    KSTR     2   1      ; "close OPDS catalog"
0004    CALL     1   1   2
0005    UGET     1   1      ; UIManager
0006    MOV      2   1
0007    TGETS    1   1   2  ; "close"
0008    MOV      3   0
0009    CALL     1   1   3
0010    TGETS    1   0   3  ; "onExit"
0011    ISF          1
0012    JMP      2 => 0016
0013    MOV      2   0
0014    TGETS    1   0   3  ; "onExit"
0015    CALL     1   1   2
0016 => KPRI     1   2
0017    RET1     1   2

-- BYTECODE -- opdscatalog.lua:0-82
0001    GGET     0   0      ; "require"
0002    KSTR     1   1      ; "ui/bidi"
0003    CALL     0   2   2
0004    GGET     1   0      ; "require"
0005    KSTR     2   2      ; "ffi/blitbuffer"
0006    CALL     1   2   2
0007    GGET     2   0      ; "require"
0008    KSTR     3   3      ; "ui/widget/confirmbox"
0009    CALL     2   2   2
0010    GGET     3   0      ; "require"
0011    KSTR     4   4      ; "ui/widget/container/framecontainer"
0012    CALL     3   2   2
0013    GGET     4   0      ; "require"
0014    KSTR     5   5      ; "ui/widget/container/inputcontainer"
0015    CALL     4   2   2
0016    GGET     5   0      ; "require"
0017    KSTR     6   6      ; "ui/widget/opdsbrowser"
0018    CALL     5   2   2
0019    GGET     6   0      ; "require"
0020    KSTR     7   7      ; "apps/reader/readerui"
0021    CALL     6   2   2
0022    GGET     7   0      ; "require"
0023    KSTR     8   8      ; "ui/uimanager"
0024    CALL     7   2   2
0025    GGET     8   0      ; "require"
0026    KSTR     9   9      ; "logger"
0027    CALL     8   2   2
0028    GGET     9   0      ; "require"
0029    KSTR    10  10      ; "gettext"
0030    CALL     9   2   2
0031    GGET    10   0      ; "require"
0032    KSTR    11  11      ; "device"
0033    CALL    10   2   2
0034    TGETS   10  10  12  ; "screen"
0035    GGET    11   0      ; "require"
0036    KSTR    12  13      ; "ffi/util"
0037    CALL    11   2   2
0038    TGETS   11  11  14  ; "template"
0039    MOV     13   4
0040    TGETS   12   4  15  ; "extend"
0041    TDUP    14  17
0042    MOV     15   9
0043    KSTR    16  16      ; "OPDS Catalog"
0044    CALL    15   2   2
0045    TSETS   15  14  18  ; "title"
0046    FNEW    15  19      ; opdscatalog.lua:16
0047    TSETS   15  14  20  ; "onExit"
0048    CALL    12   2   3
0049    FNEW    13  22      ; opdscatalog.lua:19
0050    TSETS   13  12  21  ; "init"
0051    FNEW    13  24      ; opdscatalog.lua:49
0052    TSETS   13  12  23  ; "onShow"
0053    FNEW    13  26      ; opdscatalog.lua:55
0054    TSETS   13  12  25  ; "onCloseWidget"
0055    FNEW    13  28      ; opdscatalog.lua:61
0056    TSETS   13  12  27  ; "showCatalog"
0057    FNEW    13  30      ; opdscatalog.lua:72
0058    TSETS   13  12  29  ; "onClose"
0059    UCLO     0 => 0060
0060 => RET1    12   2

