
main <./frontend/ui/widget/opdsbrowser.lua:0,0> (253 instructions, 1012 bytes at 0x7fefd04068d0)
0+ params, 32 slots, 0 upvalues, 28 locals, 103 constants, 26 functions
	1	[1]	GETGLOBAL	0 -1	; require
	2	[1]	LOADK    	1 -2	; "ui/bidi"
	3	[1]	CALL     	0 2 2
	4	[2]	GETGLOBAL	1 -1	; require
	5	[2]	LOADK    	2 -3	; "ui/widget/buttondialog"
	6	[2]	CALL     	1 2 2
	7	[3]	GETGLOBAL	2 -1	; require
	8	[3]	LOADK    	3 -4	; "ui/widget/buttondialogtitle"
	9	[3]	CALL     	2 2 2
	10	[4]	GETGLOBAL	3 -1	; require
	11	[4]	LOADK    	4 -5	; "cache"
	12	[4]	CALL     	3 2 2
	13	[5]	GETGLOBAL	4 -1	; require
	14	[5]	LOADK    	5 -6	; "cacheitem"
	15	[5]	CALL     	4 2 2
	16	[6]	GETGLOBAL	5 -1	; require
	17	[6]	LOADK    	6 -7	; "ui/widget/confirmbox"
	18	[6]	CALL     	5 2 2
	19	[7]	GETGLOBAL	6 -1	; require
	20	[7]	LOADK    	7 -8	; "ui/widget/infomessage"
	21	[7]	CALL     	6 2 2
	22	[8]	GETGLOBAL	7 -1	; require
	23	[8]	LOADK    	8 -9	; "ui/widget/menu"
	24	[8]	CALL     	7 2 2
	25	[9]	GETGLOBAL	8 -1	; require
	26	[9]	LOADK    	9 -10	; "ui/widget/multiinputdialog"
	27	[9]	CALL     	8 2 2
	28	[10]	GETGLOBAL	9 -1	; require
	29	[10]	LOADK    	10 -11	; "ui/widget/inputdialog"
	30	[10]	CALL     	9 2 2
	31	[11]	GETGLOBAL	10 -1	; require
	32	[11]	LOADK    	11 -12	; "ui/network/manager"
	33	[11]	CALL     	10 2 2
	34	[12]	GETGLOBAL	11 -1	; require
	35	[12]	LOADK    	12 -13	; "ui/opdsparser"
	36	[12]	CALL     	11 2 2
	37	[13]	GETGLOBAL	12 -1	; require
	38	[13]	LOADK    	13 -14	; "device"
	39	[13]	CALL     	12 2 2
	40	[13]	GETTABLE 	12 12 -15	; "screen"
	41	[14]	GETGLOBAL	13 -1	; require
	42	[14]	LOADK    	14 -16	; "ui/uimanager"
	43	[14]	CALL     	13 2 2
	44	[15]	GETGLOBAL	14 -1	; require
	45	[15]	LOADK    	15 -17	; "socket.http"
	46	[15]	CALL     	14 2 2
	47	[16]	GETGLOBAL	15 -1	; require
	48	[16]	LOADK    	16 -18	; "ssl.https"
	49	[16]	CALL     	15 2 2
	50	[17]	GETGLOBAL	16 -1	; require
	51	[17]	LOADK    	17 -19	; "libs/libkoreader-lfs"
	52	[17]	CALL     	16 2 2
	53	[18]	GETGLOBAL	17 -1	; require
	54	[18]	LOADK    	18 -20	; "logger"
	55	[18]	CALL     	17 2 2
	56	[19]	GETGLOBAL	18 -1	; require
	57	[19]	LOADK    	19 -21	; "ltn12"
	58	[19]	CALL     	18 2 2
	59	[20]	GETGLOBAL	19 -1	; require
	60	[20]	LOADK    	20 -22	; "mime"
	61	[20]	CALL     	19 2 2
	62	[21]	GETGLOBAL	20 -1	; require
	63	[21]	LOADK    	21 -23	; "socket"
	64	[21]	CALL     	20 2 2
	65	[22]	GETGLOBAL	21 -1	; require
	66	[22]	LOADK    	22 -24	; "socket.url"
	67	[22]	CALL     	21 2 2
	68	[23]	GETGLOBAL	22 -1	; require
	69	[23]	LOADK    	23 -25	; "util"
	70	[23]	CALL     	22 2 2
	71	[24]	GETGLOBAL	23 -1	; require
	72	[24]	LOADK    	24 -26	; "gettext"
	73	[24]	CALL     	23 2 2
	74	[25]	GETGLOBAL	24 -1	; require
	75	[25]	LOADK    	25 -27	; "ffi/util"
	76	[25]	CALL     	24 2 2
	77	[25]	GETTABLE 	24 24 -28	; "template"
	78	[27]	SELF     	25 4 -29	; "new"
	79	[27]	NEWTABLE 	27 0 1
	80	[28]	SETTABLE 	27 -30 -31	; "size" 1024
	81	[27]	CALL     	25 3 2
	82	[32]	SELF     	26 3 -29	; "new"
	83	[32]	NEWTABLE 	28 0 4
	84	[33]	SETTABLE 	28 -32 -33	; "max_memsize" 20480
	85	[34]	SETTABLE 	28 -34 -35	; "current_memsize" 0
	86	[35]	NEWTABLE 	29 0 0
	87	[35]	SETTABLE 	28 -5 29	; "cache" -
	88	[36]	NEWTABLE 	29 0 0
	89	[36]	SETTABLE 	28 -36 29	; "cache_order" -
	90	[32]	CALL     	26 3 2
	91	[39]	SELF     	27 7 -37	; "extend"
	92	[39]	NEWTABLE 	29 0 12
	93	[40]	NEWTABLE 	30 0 0
	94	[40]	SETTABLE 	29 -38 30	; "opds_servers" -
	95	[41]	MOVE     	30 23
	96	[41]	LOADK    	31 -40	; "Local calibre library"
	97	[41]	CALL     	30 2 2
	98	[41]	SETTABLE 	29 -39 30	; "calibre_name" -
	99	[43]	SETTABLE 	29 -41 -42	; "catalog_type" "application/atom%+xml"
	100	[44]	SETTABLE 	29 -43 -44	; "search_type" "application/opensearchdescription%+xml"
	101	[45]	SETTABLE 	29 -45 -46	; "acquisition_rel" "^http://opds%-spec%.org/acquisition"
	102	[46]	SETTABLE 	29 -47 -48	; "image_rel" "http://opds-spec.org/image"
	103	[47]	SETTABLE 	29 -49 -50	; "thumbnail_rel" "http://opds-spec.org/image/thumbnail"
	104	[49]	NEWTABLE 	30 0 9
	105	[50]	SETTABLE 	30 -52 -53	; "application/epub+zip" "EPUB"
	106	[51]	SETTABLE 	30 -54 -55	; "application/fb2+zip" "FB2"
	107	[52]	SETTABLE 	30 -56 -57	; "application/pdf" "PDF"
	108	[53]	SETTABLE 	30 -58 -59	; "text/plain" "TXT"
	109	[54]	SETTABLE 	30 -60 -61	; "application/x-mobipocket-ebook" "MOBI"
	110	[55]	SETTABLE 	30 -62 -63	; "application/x-mobi8-ebook" "AZW3"
	111	[56]	SETTABLE 	30 -64 -65	; "application/x-cbz" "CBZ"
	112	[57]	SETTABLE 	30 -66 -67	; "application/x-cbr" "CBR"
	113	[58]	SETTABLE 	30 -68 -69	; "application/djvu" "DJVU"
	114	[59]	SETTABLE 	29 -51 30	; "formats" -
	115	[61]	SELF     	30 12 -71	; "getWidth"
	116	[61]	CALL     	30 2 2
	117	[61]	SETTABLE 	29 -70 30	; "width" -
	118	[62]	SELF     	30 12 -73	; "getHeight"
	119	[62]	CALL     	30 2 2
	120	[62]	SETTABLE 	29 -72 30	; "height" -
	121	[63]	SETTABLE 	29 -74 -75	; "no_title" false
	122	[64]	SETTABLE 	29 -76 -77	; "parent" nil
	123	[39]	CALL     	27 3 2
	124	[121]	CLOSURE  	28 0	; 0x7fefd0407e10
	125	[121]	MOVE     	0 7
	126	[67]	SETTABLE 	27 -78 28	; "init" -
	127	[136]	CLOSURE  	28 1	; 0x7fefd0408770
	128	[136]	MOVE     	0 17
	129	[123]	SETTABLE 	27 -79 28	; "addServerFromInput" -
	130	[155]	CLOSURE  	28 2	; 0x7fefd0408eb0
	131	[155]	MOVE     	0 17
	132	[138]	SETTABLE 	27 -80 28	; "editCalibreFromInput" -
	133	[203]	CLOSURE  	28 3	; 0x7fefd0407830
	134	[203]	MOVE     	0 8
	135	[203]	MOVE     	0 23
	136	[203]	MOVE     	0 13
	137	[203]	MOVE     	0 12
	138	[157]	SETTABLE 	27 -81 28	; "addNewCatalog" -
	139	[253]	CLOSURE  	28 4	; 0x7fefd040a080
	140	[253]	MOVE     	0 8
	141	[253]	MOVE     	0 23
	142	[253]	MOVE     	0 13
	143	[253]	MOVE     	0 12
	144	[205]	SETTABLE 	27 -82 28	; "editCalibreServer" -
	145	[298]	CLOSURE  	28 5	; 0x7fefd0409d40
	146	[298]	MOVE     	0 23
	147	[255]	SETTABLE 	27 -83 28	; "genItemTableFromRoot" -
	148	[353]	CLOSURE  	28 6	; 0x7fefd040b680
	149	[353]	MOVE     	0 21
	150	[353]	MOVE     	0 18
	151	[353]	MOVE     	0 19
	152	[353]	MOVE     	0 17
	153	[353]	MOVE     	0 14
	154	[353]	MOVE     	0 15
	155	[353]	MOVE     	0 20
	156	[353]	MOVE     	0 13
	157	[353]	MOVE     	0 6
	158	[353]	MOVE     	0 24
	159	[353]	MOVE     	0 23
	160	[353]	MOVE     	0 0
	161	[300]	SETTABLE 	27 -84 28	; "fetchFeed" -
	162	[376]	CLOSURE  	28 7	; 0x7fefd040c070
	163	[376]	MOVE     	0 26
	164	[376]	MOVE     	0 17
	165	[376]	MOVE     	0 25
	166	[376]	MOVE     	0 11
	167	[355]	SETTABLE 	27 -85 28	; "parseFeed" -
	168	[394]	CLOSURE  	28 8	; 0x7fefd040c550
	169	[394]	MOVE     	0 10
	170	[394]	MOVE     	0 17
	171	[394]	MOVE     	0 13
	172	[394]	MOVE     	0 6
	173	[394]	MOVE     	0 24
	174	[394]	MOVE     	0 23
	175	[394]	MOVE     	0 0
	176	[378]	SETTABLE 	27 -86 28	; "getCatalog" -
	177	[399]	CLOSURE  	28 9	; 0x7fefd040cfe0
	178	[396]	SETTABLE 	27 -87 28	; "genItemTableFromURL" -
	179	[511]	CLOSURE  	28 10	; 0x7fefd040d1b0
	180	[511]	MOVE     	0 21
	181	[511]	MOVE     	0 13
	182	[511]	MOVE     	0 6
	183	[511]	MOVE     	0 23
	184	[511]	MOVE     	0 17
	185	[401]	SETTABLE 	27 -88 28	; "genItemTableFromCatalog" -
	186	[522]	CLOSURE  	28 11	; 0x7fefd040d8f0
	187	[513]	SETTABLE 	27 -89 28	; "updateCatalog" -
	188	[534]	CLOSURE  	28 12	; 0x7fefd040e510
	189	[524]	SETTABLE 	27 -90 28	; "appendCatalog" -
	190	[539]	CLOSURE  	28 13	; 0x7fefd040e0b0
	191	[536]	SETTABLE 	27 -91 28	; "getCurrentDownloadDir" -
	192	[609]	CLOSURE  	28 14	; 0x7fefd040e830
	193	[609]	MOVE     	0 22
	194	[609]	MOVE     	0 13
	195	[609]	MOVE     	0 17
	196	[609]	MOVE     	0 21
	197	[609]	MOVE     	0 14
	198	[609]	MOVE     	0 15
	199	[609]	MOVE     	0 18
	200	[609]	MOVE     	0 19
	201	[609]	MOVE     	0 6
	202	[609]	MOVE     	0 24
	203	[609]	MOVE     	0 23
	204	[609]	MOVE     	0 0
	205	[609]	MOVE     	0 16
	206	[609]	MOVE     	0 5
	207	[541]	SETTABLE 	27 -92 28	; "downloadFile" -
	208	[616]	CLOSURE  	28 15	; 0x7fefd040d4d0
	209	[616]	MOVE     	0 2
	210	[616]	MOVE     	0 24
	211	[616]	MOVE     	0 23
	212	[616]	MOVE     	0 0
	213	[611]	SETTABLE 	27 -93 28	; "createNewDownloadDialog" -
	214	[669]	CLOSURE  	28 16	; 0x7fefd040edf0
	215	[669]	MOVE     	0 13
	216	[669]	MOVE     	0 23
	217	[669]	MOVE     	0 17
	218	[618]	SETTABLE 	27 -94 28	; "showDownloads" -
	219	[681]	CLOSURE  	28 17	; 0x7fefd040cbc0
	220	[681]	MOVE     	0 17
	221	[671]	SETTABLE 	27 -95 28	; "browse" -
	222	[715]	CLOSURE  	28 18	; 0x7fefd0411a70
	223	[715]	MOVE     	0 9
	224	[715]	MOVE     	0 23
	225	[715]	MOVE     	0 13
	226	[683]	SETTABLE 	27 -96 28	; "browseSearchable" -
	227	[734]	CLOSURE  	28 19	; 0x7fefd04127d0
	228	[734]	MOVE     	0 17
	229	[717]	SETTABLE 	27 -97 28	; "onMenuSelect" -
	230	[751]	CLOSURE  	28 20	; 0x7fefd0412990
	231	[751]	MOVE     	0 17
	232	[736]	SETTABLE 	27 -98 28	; "editServerFromInput" -
	233	[800]	CLOSURE  	28 21	; 0x7fefd0413040
	234	[800]	MOVE     	0 17
	235	[800]	MOVE     	0 8
	236	[800]	MOVE     	0 23
	237	[800]	MOVE     	0 13
	238	[800]	MOVE     	0 12
	239	[753]	SETTABLE 	27 -99 28	; "editOPDSServer" -
	240	[812]	CLOSURE  	28 22	; 0x7fefd0413ad0
	241	[812]	MOVE     	0 17
	242	[802]	SETTABLE 	27 -100 28	; "deleteOPDSServer" -
	243	[845]	CLOSURE  	28 23	; 0x7fefd0413b50
	244	[845]	MOVE     	0 1
	245	[845]	MOVE     	0 23
	246	[845]	MOVE     	0 13
	247	[814]	SETTABLE 	27 -101 28	; "onMenuHold" -
	248	[860]	CLOSURE  	28 24	; 0x7fefd0414cf0
	249	[847]	SETTABLE 	27 -102 28	; "onReturn" -
	250	[878]	CLOSURE  	28 25	; 0x7fefd0415830
	251	[862]	SETTABLE 	27 -103 28	; "onNext" -
	252	[880]	RETURN   	27 2
	253	[880]	RETURN   	0 1

function <./frontend/ui/widget/opdsbrowser.lua:67,121> (69 instructions, 276 bytes at 0x7fefd0407e10)
1 param, 13 slots, 1 upvalue, 2 locals, 34 constants, 0 functions
	1	[68]	GETGLOBAL	1 -1	; G_reader_settings
	2	[68]	SELF     	1 1 -2	; "readSetting"
	3	[68]	LOADK    	3 -3	; "opds_servers"
	4	[68]	CALL     	1 3 2
	5	[69]	TEST     	1 0 1
	6	[69]	JMP      	42	; to 49
	7	[70]	NEWTABLE 	2 10 0
	8	[70]	NEWTABLE 	3 0 2
	9	[72]	SETTABLE 	3 -4 -5	; "title" "Project Gutenberg"
	10	[73]	SETTABLE 	3 -6 -7	; "url" "http://m.gutenberg.org/ebooks.opds/?format=opds"
	11	[74]	NEWTABLE 	4 0 3
	12	[76]	SETTABLE 	4 -4 -8	; "title" "Project Gutenberg [Searchable]"
	13	[77]	SETTABLE 	4 -6 -9	; "url" "https://m.gutenberg.org/ebooks/search.mobile/?format=opds&query=%s"
	14	[78]	SETTABLE 	4 -10 -11	; "searchable" true
	15	[79]	NEWTABLE 	5 0 2
	16	[81]	SETTABLE 	5 -4 -12	; "title" "Feedbooks"
	17	[82]	SETTABLE 	5 -6 -13	; "url" "http://www.feedbooks.com/publicdomain/catalog.atom"
	18	[83]	NEWTABLE 	6 0 2
	19	[85]	SETTABLE 	6 -4 -14	; "title" "ManyBooks"
	20	[86]	SETTABLE 	6 -6 -15	; "url" "http://manybooks.net/opds/index.php"
	21	[87]	NEWTABLE 	7 0 2
	22	[89]	SETTABLE 	7 -4 -16	; "title" "Internet Archive"
	23	[90]	SETTABLE 	7 -6 -17	; "url" "https://bookserver.archive.org/"
	24	[91]	NEWTABLE 	8 0 2
	25	[93]	SETTABLE 	8 -4 -18	; "title" "Flibusta (Russian)"
	26	[94]	SETTABLE 	8 -6 -19	; "url" "http://www.flibusta.is/opds"
	27	[95]	NEWTABLE 	9 0 3
	28	[97]	SETTABLE 	9 -4 -20	; "title" "Flibusta [Ru] [Searchable]"
	29	[98]	SETTABLE 	9 -6 -21	; "url" "http://www.flibusta.is/opds/search?searchTerm=%s"
	30	[99]	SETTABLE 	9 -10 -11	; "searchable" true
	31	[100]	NEWTABLE 	10 0 2
	32	[102]	SETTABLE 	10 -4 -22	; "title" "textos.info (Spanish)"
	33	[103]	SETTABLE 	10 -6 -23	; "url" "https://www.textos.info/catalogo.atom"
	34	[104]	NEWTABLE 	11 0 2
	35	[106]	SETTABLE 	11 -4 -24	; "title" "Gallica (French)"
	36	[107]	SETTABLE 	11 -6 -25	; "url" "https://gallica.bnf.fr/opds"
	37	[108]	NEWTABLE 	12 0 3
	38	[110]	SETTABLE 	12 -4 -26	; "title" "Gallica [Fr] [Searchable]"
	39	[111]	SETTABLE 	12 -6 -27	; "url" "https://gallica.bnf.fr/services/engine/search/opds?operation=searchRetrieve&query=(gallica all \"%s\")"
	40	[112]	SETTABLE 	12 -10 -11	; "searchable" true
	41	[114]	SETLIST  	2 10 1	; 1
	42	[114]	MOVE     	1 2
	43	[115]	GETGLOBAL	2 -1	; G_reader_settings
	44	[115]	SELF     	2 2 -28	; "saveSetting"
	45	[115]	LOADK    	4 -3	; "opds_servers"
	46	[115]	MOVE     	5 1
	47	[115]	CALL     	2 4 1
	48	[115]	JMP      	13	; to 62
	49	[116]	GETTABLE 	2 1 -29	; 4
	50	[116]	TEST     	2 0 0
	51	[116]	JMP      	10	; to 62
	52	[116]	GETTABLE 	2 1 -29	; 4
	53	[116]	GETTABLE 	2 2 -4	; "title"
	54	[116]	EQ       	0 2 -16	; - "Internet Archive"
	55	[116]	JMP      	6	; to 62
	56	[116]	GETTABLE 	2 1 -29	; 4
	57	[116]	GETTABLE 	2 2 -6	; "url"
	58	[116]	EQ       	0 2 -30	; - "http://bookserver.archive.org/catalog/"
	59	[116]	JMP      	2	; to 62
	60	[117]	GETTABLE 	2 1 -29	; 4
	61	[117]	SETTABLE 	2 -6 -31	; "url" "https://bookserver.archive.org"
	62	[119]	SELF     	2 0 -33	; "genItemTableFromRoot"
	63	[119]	CALL     	2 2 2
	64	[119]	SETTABLE 	0 -32 2	; "item_table" -
	65	[120]	GETUPVAL 	2 0	; Menu
	66	[120]	GETTABLE 	2 2 -34	; "init"
	67	[120]	MOVE     	3 0
	68	[120]	CALL     	2 2 1
	69	[121]	RETURN   	0 1

function <./frontend/ui/widget/opdsbrowser.lua:123,136> (56 instructions, 224 bytes at 0x7fefd0408770)
2 params, 8 slots, 1 upvalue, 4 locals, 22 constants, 0 functions
	1	[124]	GETUPVAL 	2 0	; logger
	2	[124]	GETTABLE 	2 2 -1	; "info"
	3	[124]	LOADK    	3 -2	; "input catalog"
	4	[124]	MOVE     	4 1
	5	[124]	CALL     	2 3 1
	6	[125]	GETGLOBAL	2 -3	; G_reader_settings
	7	[125]	SELF     	2 2 -4	; "readSetting"
	8	[125]	LOADK    	4 -5	; "opds_servers"
	9	[125]	CALL     	2 3 2
	10	[125]	TEST     	2 0 1
	11	[125]	JMP      	1	; to 13
	12	[125]	NEWTABLE 	2 0 0
	13	[126]	NEWTABLE 	3 0 5
	14	[127]	GETTABLE 	4 1 -7	; 1
	15	[127]	SETTABLE 	3 -6 4	; "title" -
	16	[128]	GETTABLE 	4 1 -9	; 2
	17	[128]	SELF     	4 4 -10	; "match"
	18	[128]	LOADK    	6 -11	; "^%a+://"
	19	[128]	CALL     	4 3 2
	20	[128]	TEST     	4 0 0
	21	[128]	JMP      	3	; to 25
	22	[128]	GETTABLE 	4 1 -9	; 2
	23	[128]	TEST     	4 0 1
	24	[128]	JMP      	3	; to 28
	25	[128]	LOADK    	4 -12	; "http://"
	26	[128]	GETTABLE 	5 1 -9	; 2
	27	[128]	CONCAT   	4 4 5
	28	[128]	SETTABLE 	3 -8 4	; "url" -
	29	[129]	GETTABLE 	4 1 -9	; 2
	30	[129]	SELF     	4 4 -10	; "match"
	31	[129]	LOADK    	6 -14	; "%%s"
	32	[129]	CALL     	4 3 2
	33	[129]	TEST     	4 0 0
	34	[129]	JMP      	3	; to 38
	35	[129]	LOADBOOL 	4 1 0
	36	[129]	TEST     	4 0 1
	37	[129]	JMP      	1	; to 39
	38	[129]	LOADBOOL 	4 0 0
	39	[129]	SETTABLE 	3 -13 4	; "searchable" -
	40	[130]	GETTABLE 	4 1 -16	; 3
	41	[130]	SETTABLE 	3 -15 4	; "username" -
	42	[131]	GETTABLE 	4 1 -18	; 4
	43	[131]	SETTABLE 	3 -17 4	; "password" -
	44	[133]	GETGLOBAL	4 -19	; table
	45	[133]	GETTABLE 	4 4 -20	; "insert"
	46	[133]	MOVE     	5 2
	47	[133]	MOVE     	6 3
	48	[133]	CALL     	4 3 1
	49	[134]	GETGLOBAL	4 -3	; G_reader_settings
	50	[134]	SELF     	4 4 -21	; "saveSetting"
	51	[134]	LOADK    	6 -5	; "opds_servers"
	52	[134]	MOVE     	7 2
	53	[134]	CALL     	4 4 1
	54	[135]	SELF     	4 0 -22	; "init"
	55	[135]	CALL     	4 2 1
	56	[136]	RETURN   	0 1

function <./frontend/ui/widget/opdsbrowser.lua:138,155> (42 instructions, 168 bytes at 0x7fefd0408eb0)
2 params, 7 slots, 1 upvalue, 3 locals, 16 constants, 0 functions
	1	[139]	GETUPVAL 	2 0	; logger
	2	[139]	GETTABLE 	2 2 -1	; "dbg"
	3	[139]	LOADK    	3 -2	; "input calibre server"
	4	[139]	MOVE     	4 1
	5	[139]	CALL     	2 3 1
	6	[140]	GETGLOBAL	2 -3	; G_reader_settings
	7	[140]	SELF     	2 2 -4	; "readSetting"
	8	[140]	LOADK    	4 -5	; "calibre_opds"
	9	[140]	CALL     	2 3 2
	10	[140]	TEST     	2 0 1
	11	[140]	JMP      	1	; to 13
	12	[140]	NEWTABLE 	2 0 0
	13	[141]	GETTABLE 	3 1 -6	; 1
	14	[141]	TEST     	3 0 0
	15	[141]	JMP      	2	; to 18
	16	[142]	GETTABLE 	3 1 -6	; 1
	17	[142]	SETTABLE 	2 -7 3	; "host" -
	18	[144]	GETGLOBAL	3 -8	; tonumber
	19	[144]	GETTABLE 	4 1 -9	; 2
	20	[144]	CALL     	3 2 2
	21	[144]	TEST     	3 0 0
	22	[144]	JMP      	2	; to 25
	23	[145]	GETTABLE 	3 1 -9	; 2
	24	[145]	SETTABLE 	2 -10 3	; "port" -
	25	[147]	GETTABLE 	3 1 -11	; 3
	26	[147]	TEST     	3 0 0
	27	[147]	JMP      	2	; to 30
	28	[148]	GETTABLE 	3 1 -11	; 3
	29	[148]	SETTABLE 	2 -12 3	; "username" -
	30	[150]	GETTABLE 	3 1 -13	; 4
	31	[150]	TEST     	3 0 0
	32	[150]	JMP      	2	; to 35
	33	[151]	GETTABLE 	3 1 -13	; 4
	34	[151]	SETTABLE 	2 -14 3	; "password" -
	35	[153]	GETGLOBAL	3 -3	; G_reader_settings
	36	[153]	SELF     	3 3 -15	; "saveSetting"
	37	[153]	LOADK    	5 -5	; "calibre_opds"
	38	[153]	MOVE     	6 2
	39	[153]	CALL     	3 4 1
	40	[154]	SELF     	3 0 -16	; "init"
	41	[154]	CALL     	3 2 1
	42	[155]	RETURN   	0 1

function <./frontend/ui/widget/opdsbrowser.lua:157,203> (79 instructions, 316 bytes at 0x7fefd0407830)
1 param, 11 slots, 4 upvalues, 1 local, 26 constants, 2 functions
	1	[158]	GETUPVAL 	1 0	; MultiInputDialog
	2	[158]	SELF     	1 1 -2	; "new"
	3	[158]	NEWTABLE 	3 0 5
	4	[159]	GETUPVAL 	4 1	; _
	5	[159]	LOADK    	5 -4	; "Add OPDS catalog"
	6	[159]	CALL     	4 2 2
	7	[159]	SETTABLE 	3 -3 4	; "title" -
	8	[160]	NEWTABLE 	4 4 0
	9	[160]	NEWTABLE 	5 0 2
	10	[162]	SETTABLE 	5 -6 -7	; "text" ""
	11	[163]	GETUPVAL 	6 1	; _
	12	[163]	LOADK    	7 -9	; "Catalog name"
	13	[163]	CALL     	6 2 2
	14	[163]	SETTABLE 	5 -8 6	; "hint" -
	15	[164]	NEWTABLE 	6 0 2
	16	[166]	SETTABLE 	6 -6 -7	; "text" ""
	17	[167]	GETUPVAL 	7 1	; _
	18	[167]	LOADK    	8 -10	; "Catalog URL"
	19	[167]	CALL     	7 2 2
	20	[167]	SETTABLE 	6 -8 7	; "hint" -
	21	[168]	NEWTABLE 	7 0 2
	22	[170]	SETTABLE 	7 -6 -7	; "text" ""
	23	[171]	GETUPVAL 	8 1	; _
	24	[171]	LOADK    	9 -11	; "Username (optional)"
	25	[171]	CALL     	8 2 2
	26	[171]	SETTABLE 	7 -8 8	; "hint" -
	27	[172]	NEWTABLE 	8 0 3
	28	[174]	SETTABLE 	8 -6 -7	; "text" ""
	29	[175]	GETUPVAL 	9 1	; _
	30	[175]	LOADK    	10 -12	; "Password (optional)"
	31	[175]	CALL     	9 2 2
	32	[175]	SETTABLE 	8 -8 9	; "hint" -
	33	[176]	SETTABLE 	8 -13 -14	; "text_type" "password"
	34	[178]	SETLIST  	4 4 1	; 1
	35	[178]	SETTABLE 	3 -5 4	; "fields" -
	36	[179]	NEWTABLE 	4 1 0
	37	[179]	NEWTABLE 	5 2 0
	38	[180]	NEWTABLE 	6 0 2
	39	[182]	GETUPVAL 	7 1	; _
	40	[182]	LOADK    	8 -16	; "Cancel"
	41	[182]	CALL     	7 2 2
	42	[182]	SETTABLE 	6 -6 7	; "text" -
	43	[186]	CLOSURE  	7 0	; 0x7fefd04096a0
	44	[186]	MOVE     	0 0
	45	[186]	GETUPVAL 	0 2	; UIManager
	46	[186]	SETTABLE 	6 -17 7	; "callback" -
	47	[187]	NEWTABLE 	7 0 2
	48	[189]	GETUPVAL 	8 1	; _
	49	[189]	LOADK    	9 -18	; "Add"
	50	[189]	CALL     	8 2 2
	51	[189]	SETTABLE 	7 -6 8	; "text" -
	52	[194]	CLOSURE  	8 1	; 0x7fefd0409e80
	53	[194]	MOVE     	0 0
	54	[194]	GETUPVAL 	0 2	; UIManager
	55	[194]	GETUPVAL 	0 0	; MultiInputDialog
	56	[194]	SETTABLE 	7 -17 8	; "callback" -
	57	[196]	SETLIST  	5 2 1	; 1
	58	[197]	SETLIST  	4 1 1	; 1
	59	[197]	SETTABLE 	3 -15 4	; "buttons" -
	60	[198]	GETUPVAL 	4 3	; Screen
	61	[198]	SELF     	4 4 -20	; "getWidth"
	62	[198]	CALL     	4 2 2
	63	[198]	MUL      	4 4 -21	; - 0.95
	64	[198]	SETTABLE 	3 -19 4	; "width" -
	65	[199]	GETUPVAL 	4 3	; Screen
	66	[199]	SELF     	4 4 -23	; "getHeight"
	67	[199]	CALL     	4 2 2
	68	[199]	MUL      	4 4 -24	; - 0.2
	69	[199]	SETTABLE 	3 -22 4	; "height" -
	70	[158]	CALL     	1 3 2
	71	[200]	SETTABLE 	0 -1 1	; "add_server_dialog" -
	72	[201]	GETUPVAL 	1 2	; UIManager
	73	[201]	SELF     	1 1 -25	; "show"
	74	[201]	GETTABLE 	3 0 -1	; "add_server_dialog"
	75	[201]	CALL     	1 3 1
	76	[202]	GETTABLE 	1 0 -1	; "add_server_dialog"
	77	[202]	SELF     	1 1 -26	; "onShowKeyboard"
	78	[202]	CALL     	1 2 1
	79	[203]	RETURN   	0 1

function <./frontend/ui/widget/opdsbrowser.lua:183,186> (10 instructions, 40 bytes at 0x7fefd04096a0)
0 params, 3 slots, 2 upvalues, 0 locals, 3 constants, 0 functions
	1	[184]	GETUPVAL 	0 0	; self
	2	[184]	GETTABLE 	0 0 -1	; "add_server_dialog"
	3	[184]	SELF     	0 0 -2	; "onClose"
	4	[184]	CALL     	0 2 1
	5	[185]	GETUPVAL 	0 1	; UIManager
	6	[185]	SELF     	0 0 -3	; "close"
	7	[185]	GETUPVAL 	2 0	; self
	8	[185]	GETTABLE 	2 2 -1	; "add_server_dialog"
	9	[185]	CALL     	0 3 1
	10	[186]	RETURN   	0 1

function <./frontend/ui/widget/opdsbrowser.lua:190,194> (16 instructions, 64 bytes at 0x7fefd0409e80)
0 params, 4 slots, 3 upvalues, 0 locals, 5 constants, 0 functions
	1	[191]	GETUPVAL 	0 0	; self
	2	[191]	GETTABLE 	0 0 -1	; "add_server_dialog"
	3	[191]	SELF     	0 0 -2	; "onClose"
	4	[191]	CALL     	0 2 1
	5	[192]	GETUPVAL 	0 1	; UIManager
	6	[192]	SELF     	0 0 -3	; "close"
	7	[192]	GETUPVAL 	2 0	; self
	8	[192]	GETTABLE 	2 2 -1	; "add_server_dialog"
	9	[192]	CALL     	0 3 1
	10	[193]	GETUPVAL 	0 0	; self
	11	[193]	SELF     	0 0 -4	; "addServerFromInput"
	12	[193]	GETUPVAL 	2 2	; MultiInputDialog
	13	[193]	SELF     	2 2 -5	; "getFields"
	14	[193]	CALL     	2 2 0
	15	[193]	CALL     	0 0 1
	16	[194]	RETURN   	0 1

function <./frontend/ui/widget/opdsbrowser.lua:205,253> (107 instructions, 428 bytes at 0x7fefd040a080)
1 param, 12 slots, 4 upvalues, 2 locals, 35 constants, 2 functions
	1	[206]	GETGLOBAL	1 -1	; G_reader_settings
	2	[206]	SELF     	1 1 -2	; "readSetting"
	3	[206]	LOADK    	3 -3	; "calibre_opds"
	4	[206]	CALL     	1 3 2
	5	[206]	TEST     	1 0 1
	6	[206]	JMP      	1	; to 8
	7	[206]	NEWTABLE 	1 0 0
	8	[207]	GETUPVAL 	2 0	; MultiInputDialog
	9	[207]	SELF     	2 2 -5	; "new"
	10	[207]	NEWTABLE 	4 0 5
	11	[208]	GETUPVAL 	5 1	; _
	12	[208]	LOADK    	6 -7	; "Edit local calibre host and port"
	13	[208]	CALL     	5 2 2
	14	[208]	SETTABLE 	4 -6 5	; "title" -
	15	[209]	NEWTABLE 	5 4 0
	16	[209]	NEWTABLE 	6 0 2
	17	[212]	GETTABLE 	7 1 -10	; "host"
	18	[212]	TEST     	7 0 1
	19	[212]	JMP      	1	; to 21
	20	[212]	LOADK    	7 -11	; "192.168.1.1"
	21	[212]	SETTABLE 	6 -9 7	; "text" -
	22	[213]	GETUPVAL 	7 1	; _
	23	[213]	LOADK    	8 -13	; "calibre host"
	24	[213]	CALL     	7 2 2
	25	[213]	SETTABLE 	6 -12 7	; "hint" -
	26	[214]	NEWTABLE 	7 0 2
	27	[216]	GETTABLE 	8 1 -14	; "port"
	28	[216]	TEST     	8 0 0
	29	[216]	JMP      	5	; to 35
	30	[216]	GETGLOBAL	8 -15	; tostring
	31	[216]	GETTABLE 	9 1 -14	; "port"
	32	[216]	CALL     	8 2 2
	33	[216]	TEST     	8 0 1
	34	[216]	JMP      	1	; to 36
	35	[216]	LOADK    	8 -16	; "8080"
	36	[216]	SETTABLE 	7 -9 8	; "text" -
	37	[217]	GETUPVAL 	8 1	; _
	38	[217]	LOADK    	9 -17	; "calibre port"
	39	[217]	CALL     	8 2 2
	40	[217]	SETTABLE 	7 -12 8	; "hint" -
	41	[218]	NEWTABLE 	8 0 2
	42	[220]	GETTABLE 	9 1 -18	; "username"
	43	[220]	TEST     	9 0 1
	44	[220]	JMP      	1	; to 46
	45	[220]	LOADK    	9 -19	; ""
	46	[220]	SETTABLE 	8 -9 9	; "text" -
	47	[221]	GETUPVAL 	9 1	; _
	48	[221]	LOADK    	10 -20	; "Username (optional)"
	49	[221]	CALL     	9 2 2
	50	[221]	SETTABLE 	8 -12 9	; "hint" -
	51	[222]	NEWTABLE 	9 0 3
	52	[224]	GETTABLE 	10 1 -21	; "password"
	53	[224]	TEST     	10 0 1
	54	[224]	JMP      	1	; to 56
	55	[224]	LOADK    	10 -19	; ""
	56	[224]	SETTABLE 	9 -9 10	; "text" -
	57	[225]	GETUPVAL 	10 1	; _
	58	[225]	LOADK    	11 -22	; "Password (optional)"
	59	[225]	CALL     	10 2 2
	60	[225]	SETTABLE 	9 -12 10	; "hint" -
	61	[226]	SETTABLE 	9 -23 -21	; "text_type" "password"
	62	[228]	SETLIST  	5 4 1	; 1
	63	[228]	SETTABLE 	4 -8 5	; "fields" -
	64	[229]	NEWTABLE 	5 1 0
	65	[229]	NEWTABLE 	6 2 0
	66	[230]	NEWTABLE 	7 0 2
	67	[232]	GETUPVAL 	8 1	; _
	68	[232]	LOADK    	9 -25	; "Cancel"
	69	[232]	CALL     	8 2 2
	70	[232]	SETTABLE 	7 -9 8	; "text" -
	71	[236]	CLOSURE  	8 0	; 0x7fefd0409a20
	72	[236]	MOVE     	0 0
	73	[236]	GETUPVAL 	0 2	; UIManager
	74	[236]	SETTABLE 	7 -26 8	; "callback" -
	75	[237]	NEWTABLE 	8 0 2
	76	[239]	GETUPVAL 	9 1	; _
	77	[239]	LOADK    	10 -27	; "Apply"
	78	[239]	CALL     	9 2 2
	79	[239]	SETTABLE 	8 -9 9	; "text" -
	80	[244]	CLOSURE  	9 1	; 0x7fefd040ab30
	81	[244]	MOVE     	0 0
	82	[244]	GETUPVAL 	0 2	; UIManager
	83	[244]	GETUPVAL 	0 0	; MultiInputDialog
	84	[244]	SETTABLE 	8 -26 9	; "callback" -
	85	[246]	SETLIST  	6 2 1	; 1
	86	[247]	SETLIST  	5 1 1	; 1
	87	[247]	SETTABLE 	4 -24 5	; "buttons" -
	88	[248]	GETUPVAL 	5 3	; Screen
	89	[248]	SELF     	5 5 -29	; "getWidth"
	90	[248]	CALL     	5 2 2
	91	[248]	MUL      	5 5 -30	; - 0.95
	92	[248]	SETTABLE 	4 -28 5	; "width" -
	93	[249]	GETUPVAL 	5 3	; Screen
	94	[249]	SELF     	5 5 -32	; "getHeight"
	95	[249]	CALL     	5 2 2
	96	[249]	MUL      	5 5 -33	; - 0.2
	97	[249]	SETTABLE 	4 -31 5	; "height" -
	98	[207]	CALL     	2 3 2
	99	[250]	SETTABLE 	0 -4 2	; "add_server_dialog" -
	100	[251]	GETUPVAL 	2 2	; UIManager
	101	[251]	SELF     	2 2 -34	; "show"
	102	[251]	GETTABLE 	4 0 -4	; "add_server_dialog"
	103	[251]	CALL     	2 3 1
	104	[252]	GETTABLE 	2 0 -4	; "add_server_dialog"
	105	[252]	SELF     	2 2 -35	; "onShowKeyboard"
	106	[252]	CALL     	2 2 1
	107	[253]	RETURN   	0 1

function <./frontend/ui/widget/opdsbrowser.lua:233,236> (10 instructions, 40 bytes at 0x7fefd0409a20)
0 params, 3 slots, 2 upvalues, 0 locals, 3 constants, 0 functions
	1	[234]	GETUPVAL 	0 0	; self
	2	[234]	GETTABLE 	0 0 -1	; "add_server_dialog"
	3	[234]	SELF     	0 0 -2	; "onClose"
	4	[234]	CALL     	0 2 1
	5	[235]	GETUPVAL 	0 1	; UIManager
	6	[235]	SELF     	0 0 -3	; "close"
	7	[235]	GETUPVAL 	2 0	; self
	8	[235]	GETTABLE 	2 2 -1	; "add_server_dialog"
	9	[235]	CALL     	0 3 1
	10	[236]	RETURN   	0 1

function <./frontend/ui/widget/opdsbrowser.lua:240,244> (16 instructions, 64 bytes at 0x7fefd040ab30)
0 params, 4 slots, 3 upvalues, 0 locals, 5 constants, 0 functions
	1	[241]	GETUPVAL 	0 0	; self
	2	[241]	GETTABLE 	0 0 -1	; "add_server_dialog"
	3	[241]	SELF     	0 0 -2	; "onClose"
	4	[241]	CALL     	0 2 1
	5	[242]	GETUPVAL 	0 1	; UIManager
	6	[242]	SELF     	0 0 -3	; "close"
	7	[242]	GETUPVAL 	2 0	; self
	8	[242]	GETTABLE 	2 2 -1	; "add_server_dialog"
	9	[242]	CALL     	0 3 1
	10	[243]	GETUPVAL 	0 0	; self
	11	[243]	SELF     	0 0 -4	; "editCalibreFromInput"
	12	[243]	GETUPVAL 	2 2	; MultiInputDialog
	13	[243]	SELF     	2 2 -5	; "getFields"
	14	[243]	CALL     	2 2 0
	15	[243]	CALL     	0 0 1
	16	[244]	RETURN   	0 1

function <./frontend/ui/widget/opdsbrowser.lua:255,298> (93 instructions, 372 bytes at 0x7fefd0409d40)
1 param, 12 slots, 1 upvalue, 9 locals, 27 constants, 2 functions
	1	[256]	NEWTABLE 	1 0 0
	2	[257]	GETGLOBAL	2 -1	; G_reader_settings
	3	[257]	SELF     	2 2 -2	; "readSetting"
	4	[257]	LOADK    	4 -3	; "opds_servers"
	5	[257]	CALL     	2 3 2
	6	[257]	TEST     	2 0 1
	7	[257]	JMP      	1	; to 9
	8	[257]	NEWTABLE 	2 0 0
	9	[258]	GETGLOBAL	3 -4	; ipairs
	10	[258]	MOVE     	4 2
	11	[258]	CALL     	3 2 4
	12	[258]	JMP      	19	; to 32
	13	[259]	GETGLOBAL	8 -5	; table
	14	[259]	GETTABLE 	8 8 -6	; "insert"
	15	[259]	MOVE     	9 1
	16	[259]	NEWTABLE 	10 0 8
	17	[260]	GETTABLE 	11 7 -8	; "title"
	18	[260]	SETTABLE 	10 -7 11	; "text" -
	19	[261]	GETTABLE 	11 7 -10	; "subtitle"
	20	[261]	SETTABLE 	10 -9 11	; "content" -
	21	[262]	GETTABLE 	11 7 -11	; "url"
	22	[262]	SETTABLE 	10 -11 11	; "url" -
	23	[263]	GETTABLE 	11 7 -12	; "username"
	24	[263]	SETTABLE 	10 -12 11	; "username" -
	25	[264]	GETTABLE 	11 7 -13	; "password"
	26	[264]	SETTABLE 	10 -13 11	; "password" -
	27	[265]	SETTABLE 	10 -14 -15	; "deletable" true
	28	[266]	SETTABLE 	10 -16 -15	; "editable" true
	29	[267]	GETTABLE 	11 7 -17	; "searchable"
	30	[267]	SETTABLE 	10 -17 11	; "searchable" -
	31	[259]	CALL     	8 3 1
	32	[258]	TFORLOOP 	3 2
	33	[268]	JMP      	-21	; to 13
	34	[270]	GETGLOBAL	3 -1	; G_reader_settings
	35	[270]	SELF     	3 3 -2	; "readSetting"
	36	[270]	LOADK    	5 -18	; "calibre_opds"
	37	[270]	CALL     	3 3 2
	38	[270]	TEST     	3 0 1
	39	[270]	JMP      	1	; to 41
	40	[270]	NEWTABLE 	3 0 0
	41	[271]	GETTABLE 	4 3 -19	; "host"
	42	[271]	TEST     	4 0 0
	43	[271]	JMP      	3	; to 47
	44	[271]	GETTABLE 	4 3 -20	; "port"
	45	[271]	TEST     	4 0 1
	46	[271]	JMP      	12	; to 59
	47	[272]	GETGLOBAL	4 -5	; table
	48	[272]	GETTABLE 	4 4 -6	; "insert"
	49	[272]	MOVE     	5 1
	50	[272]	NEWTABLE 	6 0 3
	51	[273]	GETTABLE 	7 0 -21	; "calibre_name"
	52	[273]	SETTABLE 	6 -7 7	; "text" -
	53	[276]	CLOSURE  	7 0	; 0x7fefd0409e00
	54	[276]	MOVE     	0 0
	55	[276]	SETTABLE 	6 -22 7	; "callback" -
	56	[277]	SETTABLE 	6 -14 -23	; "deletable" false
	57	[272]	CALL     	4 3 1
	58	[278]	JMP      	21	; to 80
	59	[280]	GETGLOBAL	4 -5	; table
	60	[280]	GETTABLE 	4 4 -6	; "insert"
	61	[280]	MOVE     	5 1
	62	[280]	NEWTABLE 	6 0 7
	63	[281]	GETTABLE 	7 0 -21	; "calibre_name"
	64	[281]	SETTABLE 	6 -7 7	; "text" -
	65	[282]	GETGLOBAL	7 -24	; string
	66	[282]	GETTABLE 	7 7 -25	; "format"
	67	[282]	LOADK    	8 -26	; "http://%s:%d/opds"
	68	[283]	GETTABLE 	9 3 -19	; "host"
	69	[283]	GETTABLE 	10 3 -20	; "port"
	70	[282]	CALL     	7 4 2
	71	[283]	SETTABLE 	6 -11 7	; "url" -
	72	[284]	GETTABLE 	7 3 -12	; "username"
	73	[284]	SETTABLE 	6 -12 7	; "username" -
	74	[285]	GETTABLE 	7 3 -13	; "password"
	75	[285]	SETTABLE 	6 -13 7	; "password" -
	76	[286]	SETTABLE 	6 -16 -15	; "editable" true
	77	[287]	SETTABLE 	6 -14 -23	; "deletable" false
	78	[288]	SETTABLE 	6 -17 -23	; "searchable" false
	79	[280]	CALL     	4 3 1
	80	[291]	GETGLOBAL	4 -5	; table
	81	[291]	GETTABLE 	4 4 -6	; "insert"
	82	[291]	MOVE     	5 1
	83	[291]	NEWTABLE 	6 0 2
	84	[292]	GETUPVAL 	7 0	; _
	85	[292]	LOADK    	8 -27	; "Add new OPDS catalog"
	86	[292]	CALL     	7 2 2
	87	[292]	SETTABLE 	6 -7 7	; "text" -
	88	[295]	CLOSURE  	7 1	; 0x7fefd040b560
	89	[295]	MOVE     	0 0
	90	[295]	SETTABLE 	6 -22 7	; "callback" -
	91	[291]	CALL     	4 3 1
	92	[297]	RETURN   	1 2
	93	[298]	RETURN   	0 1

function <./frontend/ui/widget/opdsbrowser.lua:274,276> (4 instructions, 16 bytes at 0x7fefd0409e00)
0 params, 2 slots, 1 upvalue, 0 locals, 1 constant, 0 functions
	1	[275]	GETUPVAL 	0 0	; self
	2	[275]	SELF     	0 0 -1	; "editCalibreServer"
	3	[275]	CALL     	0 2 1
	4	[276]	RETURN   	0 1

function <./frontend/ui/widget/opdsbrowser.lua:293,295> (4 instructions, 16 bytes at 0x7fefd040b560)
0 params, 2 slots, 1 upvalue, 0 locals, 1 constant, 0 functions
	1	[294]	GETUPVAL 	0 0	; self
	2	[294]	SELF     	0 0 -1	; "addNewCatalog"
	3	[294]	CALL     	0 2 1
	4	[295]	RETURN   	0 1

function <./frontend/ui/widget/opdsbrowser.lua:300,353> (179 instructions, 716 bytes at 0x7fefd040b680)
5 params, 22 slots, 12 upvalues, 14 locals, 43 constants, 0 functions
	1	[301]	NEWTABLE 	5 0 0
	2	[301]	NEWTABLE 	6 0 0
	3	[302]	GETUPVAL 	7 0	; url
	4	[302]	GETTABLE 	7 7 -1	; "parse"
	5	[302]	MOVE     	8 1
	6	[302]	CALL     	7 2 2
	7	[303]	GETTABLE 	8 7 -2	; "host"
	8	[304]	GETGLOBAL	9 -3	; string
	9	[304]	GETTABLE 	9 9 -4	; "format"
	10	[304]	LOADK    	10 -5	; "%s:%s"
	11	[304]	MOVE     	11 2
	12	[304]	MOVE     	12 3
	13	[304]	CALL     	9 4 2
	14	[305]	SETTABLE 	5 -6 1	; "url" -
	15	[306]	TEST     	4 0 0
	16	[306]	JMP      	2	; to 19
	17	[306]	TESTSET  	10 4 1
	18	[306]	JMP      	1	; to 20
	19	[306]	LOADK    	10 -8	; "GET"
	20	[306]	SETTABLE 	5 -7 10	; "method" -
	21	[307]	GETUPVAL 	10 1	; ltn12
	22	[307]	GETTABLE 	10 10 -9	; "sink"
	23	[307]	GETTABLE 	10 10 -10	; "table"
	24	[307]	MOVE     	11 6
	25	[307]	CALL     	10 2 2
	26	[307]	SETTABLE 	5 -9 10	; "sink" -
	27	[308]	TEST     	2 0 0
	28	[308]	JMP      	11	; to 40
	29	[308]	NEWTABLE 	10 0 2
	30	[308]	LOADK    	11 -13	; "Basic "
	31	[308]	GETUPVAL 	12 2	; mime
	32	[308]	GETTABLE 	12 12 -14	; "b64"
	33	[308]	MOVE     	13 9
	34	[308]	CALL     	12 2 2
	35	[308]	CONCAT   	11 11 12
	36	[308]	SETTABLE 	10 -12 11	; "Authorization" -
	37	[308]	SETTABLE 	10 -15 8	; "Host" -
	38	[308]	TEST     	10 0 1
	39	[308]	JMP      	2	; to 42
	40	[308]	NEWTABLE 	10 0 1
	41	[308]	SETTABLE 	10 -15 8	; "Host" -
	42	[308]	SETTABLE 	5 -11 10	; "headers" -
	43	[309]	GETUPVAL 	10 3	; logger
	44	[309]	GETTABLE 	10 10 -16	; "info"
	45	[309]	LOADK    	11 -17	; "request"
	46	[309]	MOVE     	12 5
	47	[309]	CALL     	10 3 1
	48	[310]	GETUPVAL 	10 4	; http
	49	[310]	GETUPVAL 	11 5	; https
	50	[310]	LOADK    	12 -19	; 10
	51	[310]	SETTABLE 	11 -18 -19	; "TIMEOUT" 10
	52	[310]	SETTABLE 	10 -18 12	; "TIMEOUT" -
	53	[311]	GETTABLE 	10 7 -20	; "scheme"
	54	[311]	EQ       	0 10 -21	; - "http"
	55	[311]	JMP      	4	; to 60
	56	[311]	GETUPVAL 	10 4	; http
	57	[311]	GETTABLE 	10 10 -17	; "request"
	58	[311]	TEST     	10 0 1
	59	[311]	JMP      	2	; to 62
	60	[311]	GETUPVAL 	10 5	; https
	61	[311]	GETTABLE 	10 10 -17	; "request"
	62	[312]	GETUPVAL 	11 6	; socket
	63	[312]	GETTABLE 	11 11 -22	; "skip"
	64	[312]	LOADK    	12 -23	; 1
	65	[312]	MOVE     	13 10
	66	[312]	MOVE     	14 5
	67	[312]	CALL     	13 2 0
	68	[312]	CALL     	11 0 3
	69	[314]	EQ       	0 12 -24	; - nil
	70	[314]	JMP      	3	; to 74
	71	[315]	GETGLOBAL	13 -25	; error
	72	[315]	MOVE     	14 11
	73	[315]	CALL     	13 2 1
	74	[317]	EQ       	0 11 -26	; - 200
	75	[317]	JMP      	17	; to 93
	76	[318]	EQ       	0 4 -27	; - "HEAD"
	77	[318]	JMP      	7	; to 85
	78	[319]	GETTABLE 	13 12 -28	; "last-modified"
	79	[319]	TEST     	13 0 0
	80	[319]	JMP      	3	; to 84
	81	[320]	GETTABLE 	13 12 -28	; "last-modified"
	82	[320]	RETURN   	13 2
	83	[320]	JMP      	1	; to 85
	84	[322]	RETURN   	0 1
	85	[325]	GETGLOBAL	13 -10	; table
	86	[325]	GETTABLE 	13 13 -29	; "concat"
	87	[325]	MOVE     	14 6
	88	[325]	CALL     	13 2 2
	89	[326]	EQ       	1 13 -30	; - ""
	90	[326]	JMP      	88	; to 179
	91	[327]	RETURN   	13 2
	92	[328]	JMP      	86	; to 179
	93	[329]	EQ       	0 4 -27	; - "HEAD"
	94	[329]	JMP      	2	; to 97
	95	[331]	RETURN   	0 1
	96	[331]	JMP      	82	; to 179
	97	[332]	EQ       	0 11 -31	; - 301
	98	[332]	JMP      	18	; to 117
	99	[333]	GETUPVAL 	13 7	; UIManager
	100	[333]	SELF     	13 13 -32	; "show"
	101	[333]	GETUPVAL 	15 8	; InfoMessage
	102	[333]	SELF     	15 15 -33	; "new"
	103	[333]	NEWTABLE 	17 0 1
	104	[334]	GETUPVAL 	18 9	; T
	105	[334]	GETUPVAL 	19 10	; _
	106	[334]	LOADK    	20 -35	; "The catalog has been permanently moved. Please update catalog URL to '%1'."
	107	[334]	CALL     	19 2 2
	108	[334]	GETUPVAL 	20 11	; BD
	109	[334]	GETTABLE 	20 20 -6	; "url"
	110	[334]	GETTABLE 	21 12 -36	; "Location"
	111	[334]	CALL     	20 2 0
	112	[334]	CALL     	18 0 2
	113	[334]	SETTABLE 	17 -34 18	; "text" -
	114	[333]	CALL     	15 3 0
	115	[333]	CALL     	13 0 1
	116	[335]	JMP      	62	; to 179
	117	[336]	EQ       	0 11 -37	; - 401
	118	[336]	JMP      	14	; to 133
	119	[337]	GETUPVAL 	13 7	; UIManager
	120	[337]	SELF     	13 13 -32	; "show"
	121	[337]	GETUPVAL 	15 8	; InfoMessage
	122	[337]	SELF     	15 15 -33	; "new"
	123	[337]	NEWTABLE 	17 0 1
	124	[338]	GETUPVAL 	18 9	; T
	125	[338]	GETUPVAL 	19 10	; _
	126	[338]	LOADK    	20 -38	; "Authentication required for catalog. Please add a username and password."
	127	[338]	CALL     	19 2 0
	128	[338]	CALL     	18 0 2
	129	[338]	SETTABLE 	17 -34 18	; "text" -
	130	[337]	CALL     	15 3 0
	131	[337]	CALL     	13 0 1
	132	[339]	JMP      	46	; to 179
	133	[340]	EQ       	0 11 -39	; - 403
	134	[340]	JMP      	14	; to 149
	135	[341]	GETUPVAL 	13 7	; UIManager
	136	[341]	SELF     	13 13 -32	; "show"
	137	[341]	GETUPVAL 	15 8	; InfoMessage
	138	[341]	SELF     	15 15 -33	; "new"
	139	[341]	NEWTABLE 	17 0 1
	140	[342]	GETUPVAL 	18 9	; T
	141	[342]	GETUPVAL 	19 10	; _
	142	[342]	LOADK    	20 -40	; "Failed to authenticate. Please check your username and password."
	143	[342]	CALL     	19 2 0
	144	[342]	CALL     	18 0 2
	145	[342]	SETTABLE 	17 -34 18	; "text" -
	146	[341]	CALL     	15 3 0
	147	[341]	CALL     	13 0 1
	148	[343]	JMP      	30	; to 179
	149	[344]	EQ       	0 11 -41	; - 404
	150	[344]	JMP      	14	; to 165
	151	[345]	GETUPVAL 	13 7	; UIManager
	152	[345]	SELF     	13 13 -32	; "show"
	153	[345]	GETUPVAL 	15 8	; InfoMessage
	154	[345]	SELF     	15 15 -33	; "new"
	155	[345]	NEWTABLE 	17 0 1
	156	[346]	GETUPVAL 	18 9	; T
	157	[346]	GETUPVAL 	19 10	; _
	158	[346]	LOADK    	20 -42	; "Catalog not found."
	159	[346]	CALL     	19 2 0
	160	[346]	CALL     	18 0 2
	161	[346]	SETTABLE 	17 -34 18	; "text" -
	162	[345]	CALL     	15 3 0
	163	[345]	CALL     	13 0 1
	164	[347]	JMP      	14	; to 179
	165	[349]	GETUPVAL 	13 7	; UIManager
	166	[349]	SELF     	13 13 -32	; "show"
	167	[349]	GETUPVAL 	15 8	; InfoMessage
	168	[349]	SELF     	15 15 -33	; "new"
	169	[349]	NEWTABLE 	17 0 1
	170	[350]	GETUPVAL 	18 9	; T
	171	[350]	GETUPVAL 	19 10	; _
	172	[350]	LOADK    	20 -43	; "Cannot get catalog. Server response code %1."
	173	[350]	CALL     	19 2 2
	174	[350]	MOVE     	20 11
	175	[350]	CALL     	18 3 2
	176	[350]	SETTABLE 	17 -34 18	; "text" -
	177	[349]	CALL     	15 3 0
	178	[349]	CALL     	13 0 1
	179	[353]	RETURN   	0 1

function <./frontend/ui/widget/opdsbrowser.lua:355,376> (52 instructions, 208 bytes at 0x7fefd040c070)
4 params, 14 slots, 4 upvalues, 8 locals, 10 constants, 0 functions
	1	[357]	SELF     	5 0 -1	; "fetchFeed"
	2	[357]	MOVE     	7 1
	3	[357]	MOVE     	8 2
	4	[357]	MOVE     	9 3
	5	[357]	LOADK    	10 -2	; "HEAD"
	6	[357]	CALL     	5 6 2
	7	[358]	LOADK    	6 -3	; "opds|catalog|"
	8	[358]	MOVE     	7 1
	9	[358]	CONCAT   	6 6 7
	10	[359]	TEST     	5 0 0
	11	[359]	JMP      	3	; to 15
	12	[360]	MOVE     	7 6
	13	[360]	MOVE     	8 5
	14	[360]	CONCAT   	6 7 8
	15	[363]	GETUPVAL 	7 0	; CatalogCache
	16	[363]	SELF     	7 7 -4	; "check"
	17	[363]	MOVE     	9 6
	18	[363]	CALL     	7 3 2
	19	[364]	TEST     	7 0 0
	20	[364]	JMP      	2	; to 23
	21	[365]	GETTABLE 	4 7 -5	; "feed"
	22	[365]	JMP      	22	; to 45
	23	[367]	GETUPVAL 	8 1	; logger
	24	[367]	GETTABLE 	8 8 -6	; "dbg"
	25	[367]	LOADK    	9 -7	; "cache"
	26	[367]	MOVE     	10 6
	27	[367]	CALL     	8 3 1
	28	[368]	SELF     	8 0 -1	; "fetchFeed"
	29	[368]	MOVE     	10 1
	30	[368]	MOVE     	11 2
	31	[368]	MOVE     	12 3
	32	[368]	CALL     	8 5 2
	33	[368]	MOVE     	4 8
	34	[369]	TEST     	4 0 0
	35	[369]	JMP      	9	; to 45
	36	[370]	GETUPVAL 	8 0	; CatalogCache
	37	[370]	SELF     	8 8 -8	; "insert"
	38	[370]	MOVE     	10 6
	39	[370]	GETUPVAL 	11 2	; CatalogCacheItem
	40	[370]	SELF     	11 11 -9	; "new"
	41	[370]	NEWTABLE 	13 0 1
	42	[370]	SETTABLE 	13 -5 4	; "feed" -
	43	[370]	CALL     	11 3 0
	44	[370]	CALL     	8 0 1
	45	[373]	TEST     	4 0 0
	46	[373]	JMP      	5	; to 52
	47	[374]	GETUPVAL 	8 3	; OPDSParser
	48	[374]	SELF     	8 8 -10	; "parse"
	49	[374]	MOVE     	10 4
	50	[374]	TAILCALL 	8 3 0
	51	[374]	RETURN   	8 0
	52	[376]	RETURN   	0 1

function <./frontend/ui/widget/opdsbrowser.lua:378,394> (58 instructions, 232 bytes at 0x7fefd040c550)
4 params, 15 slots, 7 upvalues, 6 locals, 12 constants, 0 functions
	1	[379]	GETGLOBAL	4 -1	; pcall
	2	[379]	GETTABLE 	5 0 -2	; "parseFeed"
	3	[379]	MOVE     	6 0
	4	[379]	MOVE     	7 1
	5	[379]	MOVE     	8 2
	6	[379]	MOVE     	9 3
	7	[379]	CALL     	4 6 3
	8	[380]	TEST     	4 0 1
	9	[380]	JMP      	12	; to 22
	10	[380]	TEST     	5 0 0
	11	[380]	JMP      	10	; to 22
	12	[380]	GETUPVAL 	6 0	; NetworkMgr
	13	[380]	SELF     	6 6 -3	; "isOnline"
	14	[380]	CALL     	6 2 2
	15	[380]	TEST     	6 0 1
	16	[380]	JMP      	5	; to 22
	17	[381]	GETUPVAL 	6 0	; NetworkMgr
	18	[381]	SELF     	6 6 -4	; "promptWifiOn"
	19	[381]	CALL     	6 2 1
	20	[382]	RETURN   	0 1
	21	[382]	JMP      	31	; to 53
	22	[383]	TEST     	4 0 1
	23	[383]	JMP      	29	; to 53
	24	[383]	TEST     	5 0 0
	25	[383]	JMP      	27	; to 53
	26	[384]	GETUPVAL 	6 1	; logger
	27	[384]	GETTABLE 	6 6 -5	; "info"
	28	[384]	LOADK    	7 -6	; "cannot get catalog info from"
	29	[384]	MOVE     	8 1
	30	[384]	MOVE     	9 5
	31	[384]	CALL     	6 4 1
	32	[385]	GETUPVAL 	6 2	; UIManager
	33	[385]	SELF     	6 6 -7	; "show"
	34	[385]	GETUPVAL 	8 3	; InfoMessage
	35	[385]	SELF     	8 8 -8	; "new"
	36	[385]	NEWTABLE 	10 0 1
	37	[386]	GETUPVAL 	11 4	; T
	38	[386]	GETUPVAL 	12 5	; _
	39	[386]	LOADK    	13 -10	; "Cannot get catalog info from %1"
	40	[386]	CALL     	12 2 2
	41	[386]	GETUPVAL 	13 6	; BD
	42	[386]	GETTABLE 	13 13 -11	; "url"
	43	[386]	MOVE     	14 1
	44	[386]	CALL     	13 2 2
	45	[386]	TEST     	13 0 1
	46	[386]	JMP      	1	; to 48
	47	[386]	LOADK    	13 -12	; ""
	48	[386]	CALL     	11 3 2
	49	[386]	SETTABLE 	10 -9 11	; "text" -
	50	[385]	CALL     	8 3 0
	51	[385]	CALL     	6 0 1
	52	[388]	RETURN   	0 1
	53	[391]	TEST     	4 0 0
	54	[391]	JMP      	3	; to 58
	55	[391]	TEST     	5 0 0
	56	[391]	JMP      	1	; to 58
	57	[392]	RETURN   	5 2
	58	[394]	RETURN   	0 1

function <./frontend/ui/widget/opdsbrowser.lua:396,399> (13 instructions, 52 bytes at 0x7fefd040cfe0)
4 params, 11 slots, 0 upvalues, 5 locals, 2 constants, 0 functions
	1	[397]	SELF     	4 0 -1	; "getCatalog"
	2	[397]	MOVE     	6 1
	3	[397]	MOVE     	7 2
	4	[397]	MOVE     	8 3
	5	[397]	CALL     	4 5 2
	6	[398]	SELF     	5 0 -2	; "genItemTableFromCatalog"
	7	[398]	MOVE     	7 4
	8	[398]	MOVE     	8 1
	9	[398]	MOVE     	9 2
	10	[398]	MOVE     	10 3
	11	[398]	TAILCALL 	5 6 0
	12	[398]	RETURN   	5 0
	13	[399]	RETURN   	0 1

function <./frontend/ui/widget/opdsbrowser.lua:401,511> (242 instructions, 968 bytes at 0x7fefd040d1b0)
5 params, 25 slots, 5 upvalues, 27 locals, 49 constants, 1 function
	1	[402]	NEWTABLE 	5 0 0
	2	[403]	TEST     	1 0 1
	3	[403]	JMP      	1	; to 5
	4	[404]	RETURN   	5 2
	5	[407]	GETTABLE 	6 1 -1	; "feed"
	6	[407]	TEST     	6 0 1
	7	[407]	JMP      	1	; to 9
	8	[407]	MOVE     	6 1
	9	[411]	CLOSURE  	7 0	; 0x7fefd040d5d0
	10	[411]	GETUPVAL 	0 0	; url
	11	[411]	MOVE     	0 2
	12	[413]	NEWTABLE 	8 0 0
	13	[414]	GETTABLE 	9 6 -2	; "link"
	14	[414]	TEST     	9 0 0
	15	[414]	JMP      	32	; to 48
	16	[415]	GETGLOBAL	9 -3	; ipairs
	17	[415]	GETTABLE 	10 6 -2	; "link"
	18	[415]	CALL     	9 2 4
	19	[415]	JMP      	26	; to 46
	20	[416]	GETTABLE 	14 13 -4	; "type"
	21	[416]	EQ       	1 14 -5	; - nil
	22	[416]	JMP      	23	; to 46
	23	[417]	GETTABLE 	14 13 -4	; "type"
	24	[417]	SELF     	14 14 -6	; "find"
	25	[417]	GETTABLE 	16 0 -7	; "catalog_type"
	26	[417]	CALL     	14 3 2
	27	[417]	TEST     	14 0 1
	28	[417]	JMP      	6	; to 35
	29	[418]	GETTABLE 	14 13 -4	; "type"
	30	[418]	SELF     	14 14 -6	; "find"
	31	[418]	GETTABLE 	16 0 -8	; "search_type"
	32	[418]	CALL     	14 3 2
	33	[418]	TEST     	14 0 0
	34	[418]	JMP      	11	; to 46
	35	[419]	GETTABLE 	14 13 -9	; "rel"
	36	[419]	TEST     	14 0 0
	37	[419]	JMP      	8	; to 46
	38	[419]	GETTABLE 	14 13 -10	; "href"
	39	[419]	TEST     	14 0 0
	40	[419]	JMP      	5	; to 46
	41	[420]	GETTABLE 	14 13 -9	; "rel"
	42	[420]	MOVE     	15 7
	43	[420]	GETTABLE 	16 13 -10	; "href"
	44	[420]	CALL     	15 2 2
	45	[420]	SETTABLE 	8 14 15
	46	[415]	TFORLOOP 	9 2
	47	[423]	JMP      	-28	; to 20
	48	[426]	SETTABLE 	5 -11 8	; "hrefs" -
	49	[427]	TEST     	3 0 0
	50	[427]	JMP      	1	; to 52
	51	[428]	SETTABLE 	5 -12 3	; "username" -
	52	[430]	TEST     	4 0 0
	53	[430]	JMP      	1	; to 55
	54	[431]	SETTABLE 	5 -13 4	; "password" -
	55	[434]	GETTABLE 	9 6 -14	; "entry"
	56	[434]	TEST     	9 0 1
	57	[434]	JMP      	15	; to 73
	58	[435]	LEN      	9 8
	59	[435]	EQ       	0 9 -15	; - 0
	60	[435]	JMP      	11	; to 72
	61	[436]	GETUPVAL 	9 1	; UIManager
	62	[436]	SELF     	9 9 -16	; "show"
	63	[436]	GETUPVAL 	11 2	; InfoMessage
	64	[436]	SELF     	11 11 -17	; "new"
	65	[436]	NEWTABLE 	13 0 1
	66	[437]	GETUPVAL 	14 3	; _
	67	[437]	LOADK    	15 -19	; "Catalog not found."
	68	[437]	CALL     	14 2 2
	69	[437]	SETTABLE 	13 -18 14	; "text" -
	70	[436]	CALL     	11 3 0
	71	[436]	CALL     	9 0 1
	72	[440]	RETURN   	5 2
	73	[443]	GETGLOBAL	9 -3	; ipairs
	74	[443]	GETTABLE 	10 6 -14	; "entry"
	75	[443]	CALL     	9 2 4
	76	[443]	JMP      	162	; to 239
	77	[444]	NEWTABLE 	14 0 0
	78	[445]	NEWTABLE 	15 0 0
	79	[445]	SETTABLE 	14 -20 15	; "acquisitions" -
	80	[446]	GETTABLE 	15 13 -2	; "link"
	81	[446]	TEST     	15 0 0
	82	[446]	JMP      	69	; to 152
	83	[447]	GETGLOBAL	15 -3	; ipairs
	84	[447]	GETTABLE 	16 13 -2	; "link"
	85	[447]	CALL     	15 2 4
	86	[447]	JMP      	63	; to 150
	87	[448]	GETTABLE 	20 19 -4	; "type"
	88	[448]	SELF     	20 20 -6	; "find"
	89	[448]	GETTABLE 	22 0 -7	; "catalog_type"
	90	[448]	CALL     	20 3 2
	91	[449]	TEST     	20 0 0
	92	[449]	JMP      	19	; to 112
	93	[449]	GETTABLE 	20 19 -9	; "rel"
	94	[450]	TEST     	20 0 0
	95	[450]	JMP      	12	; to 108
	96	[450]	GETTABLE 	20 19 -9	; "rel"
	97	[450]	EQ       	1 20 -21	; - "subsection"
	98	[450]	JMP      	9	; to 108
	99	[451]	GETTABLE 	20 19 -9	; "rel"
	100	[451]	EQ       	1 20 -22	; - "http://opds-spec.org/subsection"
	101	[451]	JMP      	6	; to 108
	102	[452]	GETTABLE 	20 19 -9	; "rel"
	103	[452]	EQ       	1 20 -23	; - "http://opds-spec.org/sort/popular"
	104	[452]	JMP      	3	; to 108
	105	[453]	GETTABLE 	20 19 -9	; "rel"
	106	[453]	EQ       	0 20 -24	; - "http://opds-spec.org/sort/new"
	107	[453]	JMP      	4	; to 112
	108	[454]	MOVE     	20 7
	109	[454]	GETTABLE 	21 19 -10	; "href"
	110	[454]	CALL     	20 2 2
	111	[454]	SETTABLE 	14 -25 20	; "url" -
	112	[456]	GETTABLE 	20 19 -9	; "rel"
	113	[456]	TEST     	20 0 0
	114	[456]	JMP      	35	; to 150
	115	[457]	GETTABLE 	20 19 -9	; "rel"
	116	[457]	SELF     	20 20 -26	; "match"
	117	[457]	GETTABLE 	22 0 -27	; "acquisition_rel"
	118	[457]	CALL     	20 3 2
	119	[457]	TEST     	20 0 0
	120	[457]	JMP      	12	; to 133
	121	[458]	GETGLOBAL	20 -28	; table
	122	[458]	GETTABLE 	20 20 -29	; "insert"
	123	[458]	GETTABLE 	21 14 -20	; "acquisitions"
	124	[458]	NEWTABLE 	22 0 2
	125	[459]	GETTABLE 	23 19 -4	; "type"
	126	[459]	SETTABLE 	22 -4 23	; "type" -
	127	[460]	MOVE     	23 7
	128	[460]	GETTABLE 	24 19 -10	; "href"
	129	[460]	CALL     	23 2 2
	130	[460]	SETTABLE 	22 -10 23	; "href" -
	131	[458]	CALL     	20 3 1
	132	[461]	JMP      	17	; to 150
	133	[462]	GETTABLE 	20 19 -9	; "rel"
	134	[462]	GETTABLE 	21 0 -30	; "thumbnail_rel"
	135	[462]	EQ       	0 20 21
	136	[462]	JMP      	5	; to 142
	137	[463]	MOVE     	20 7
	138	[463]	GETTABLE 	21 19 -10	; "href"
	139	[463]	CALL     	20 2 2
	140	[463]	SETTABLE 	14 -31 20	; "thumbnail" -
	141	[463]	JMP      	8	; to 150
	142	[464]	GETTABLE 	20 19 -9	; "rel"
	143	[464]	GETTABLE 	21 0 -32	; "image_rel"
	144	[464]	EQ       	0 20 21
	145	[464]	JMP      	4	; to 150
	146	[465]	MOVE     	20 7
	147	[465]	GETTABLE 	21 19 -10	; "href"
	148	[465]	CALL     	20 2 2
	149	[465]	SETTABLE 	14 -33 20	; "image" -
	150	[447]	TFORLOOP 	15 2
	151	[467]	JMP      	-65	; to 87
	152	[470]	LOADK    	15 -34	; "Unknown"
	153	[471]	GETGLOBAL	16 -4	; type
	154	[471]	GETTABLE 	17 13 -35	; "title"
	155	[471]	CALL     	16 2 2
	156	[471]	EQ       	0 16 -36	; - "string"
	157	[471]	JMP      	2	; to 160
	158	[472]	GETTABLE 	15 13 -35	; "title"
	159	[472]	JMP      	17	; to 177
	160	[473]	GETGLOBAL	16 -4	; type
	161	[473]	GETTABLE 	17 13 -35	; "title"
	162	[473]	CALL     	16 2 2
	163	[473]	EQ       	0 16 -28	; - "table"
	164	[473]	JMP      	12	; to 177
	165	[474]	GETGLOBAL	16 -4	; type
	166	[474]	GETTABLE 	17 13 -35	; "title"
	167	[474]	GETTABLE 	17 17 -4	; "type"
	168	[474]	CALL     	16 2 2
	169	[474]	EQ       	0 16 -36	; - "string"
	170	[474]	JMP      	6	; to 177
	171	[474]	GETTABLE 	16 13 -35	; "title"
	172	[474]	GETTABLE 	16 16 -37	; "div"
	173	[474]	EQ       	1 16 -38	; - ""
	174	[474]	JMP      	2	; to 177
	175	[475]	GETTABLE 	16 13 -35	; "title"
	176	[475]	GETTABLE 	15 16 -37	; "div"
	177	[478]	EQ       	0 15 -34	; - "Unknown"
	178	[478]	JMP      	5	; to 184
	179	[479]	GETUPVAL 	16 4	; logger
	180	[479]	GETTABLE 	16 16 -39	; "info"
	181	[479]	LOADK    	17 -40	; "Cannot handle title"
	182	[479]	GETTABLE 	18 13 -35	; "title"
	183	[479]	CALL     	16 3 1
	184	[481]	SETTABLE 	14 -18 15	; "text" -
	185	[482]	LOADK    	16 -41	; "Unknown Author"
	186	[483]	GETGLOBAL	17 -4	; type
	187	[483]	GETTABLE 	18 13 -42	; "author"
	188	[483]	CALL     	17 2 2
	189	[483]	EQ       	0 17 -28	; - "table"
	190	[483]	JMP      	29	; to 220
	191	[483]	GETTABLE 	17 13 -42	; "author"
	192	[483]	GETTABLE 	17 17 -43	; "name"
	193	[483]	TEST     	17 0 0
	194	[483]	JMP      	25	; to 220
	195	[484]	GETTABLE 	17 13 -42	; "author"
	196	[484]	GETTABLE 	16 17 -43	; "name"
	197	[485]	GETGLOBAL	17 -4	; type
	198	[485]	MOVE     	18 16
	199	[485]	CALL     	17 2 2
	200	[485]	EQ       	0 17 -28	; - "table"
	201	[485]	JMP      	11	; to 213
	202	[486]	LEN      	17 16
	203	[486]	LT       	0 -15 17	; 0 -
	204	[486]	JMP      	7	; to 212
	205	[487]	GETGLOBAL	17 -28	; table
	206	[487]	GETTABLE 	17 17 -44	; "concat"
	207	[487]	MOVE     	18 16
	208	[487]	LOADK    	19 -45	; ", "
	209	[487]	CALL     	17 3 2
	210	[487]	MOVE     	16 17
	211	[487]	JMP      	1	; to 213
	212	[490]	LOADNIL  	16 16
	213	[493]	TEST     	16 0 0
	214	[493]	JMP      	5	; to 220
	215	[494]	MOVE     	17 15
	216	[494]	LOADK    	18 -46	; "\n"
	217	[494]	MOVE     	19 16
	218	[494]	CONCAT   	17 17 19
	219	[494]	SETTABLE 	14 -18 17	; "text" -
	220	[497]	SETTABLE 	14 -35 15	; "title" -
	221	[498]	SETTABLE 	14 -42 16	; "author" -
	222	[499]	GETTABLE 	17 13 -47	; "id"
	223	[499]	SETTABLE 	14 -47 17	; "id" -
	224	[500]	GETTABLE 	17 13 -48	; "content"
	225	[500]	SETTABLE 	14 -48 17	; "content" -
	226	[501]	GETTABLE 	17 13 -49	; "updated"
	227	[501]	SETTABLE 	14 -49 17	; "updated" -
	228	[502]	TEST     	3 0 0
	229	[502]	JMP      	1	; to 231
	230	[503]	SETTABLE 	14 -12 3	; "username" -
	231	[505]	TEST     	4 0 0
	232	[505]	JMP      	1	; to 234
	233	[506]	SETTABLE 	14 -13 4	; "password" -
	234	[508]	GETGLOBAL	17 -28	; table
	235	[508]	GETTABLE 	17 17 -29	; "insert"
	236	[508]	MOVE     	18 5
	237	[508]	MOVE     	19 14
	238	[508]	CALL     	17 3 1
	239	[443]	TFORLOOP 	9 2
	240	[508]	JMP      	-164	; to 77
	241	[510]	RETURN   	5 2
	242	[511]	RETURN   	0 1

function <./frontend/ui/widget/opdsbrowser.lua:409,411> (7 instructions, 28 bytes at 0x7fefd040d5d0)
1 param, 4 slots, 2 upvalues, 1 local, 1 constant, 0 functions
	1	[410]	GETUPVAL 	1 0	; url
	2	[410]	GETTABLE 	1 1 -1	; "absolute"
	3	[410]	GETUPVAL 	2 1	; item_url
	4	[410]	MOVE     	3 0
	5	[410]	TAILCALL 	1 3 0
	6	[410]	RETURN   	1 0
	7	[411]	RETURN   	0 1

function <./frontend/ui/widget/opdsbrowser.lua:513,522> (20 instructions, 80 bytes at 0x7fefd040d8f0)
4 params, 9 slots, 0 upvalues, 5 locals, 6 constants, 0 functions
	1	[514]	SELF     	4 0 -1	; "genItemTableFromURL"
	2	[514]	MOVE     	6 1
	3	[514]	MOVE     	7 2
	4	[514]	MOVE     	8 3
	5	[514]	CALL     	4 5 2
	6	[515]	LEN      	5 4
	7	[515]	LT       	0 -2 5	; 0 -
	8	[515]	JMP      	11	; to 20
	9	[516]	SELF     	5 0 -3	; "switchItemTable"
	10	[516]	LOADNIL  	7 7
	11	[516]	MOVE     	8 4
	12	[516]	CALL     	5 4 1
	13	[517]	GETTABLE 	5 0 -4	; "page_num"
	14	[517]	LE       	0 5 -5	; - 1
	15	[517]	JMP      	2	; to 18
	16	[518]	SELF     	5 0 -6	; "onNext"
	17	[518]	CALL     	5 2 1
	18	[520]	LOADBOOL 	5 1 0
	19	[520]	RETURN   	5 2
	20	[522]	RETURN   	0 1

function <./frontend/ui/widget/opdsbrowser.lua:524,534> (32 instructions, 128 bytes at 0x7fefd040e510)
4 params, 13 slots, 0 upvalues, 10 locals, 9 constants, 0 functions
	1	[525]	SELF     	4 0 -1	; "genItemTableFromURL"
	2	[525]	MOVE     	6 1
	3	[525]	MOVE     	7 2
	4	[525]	MOVE     	8 3
	5	[525]	CALL     	4 5 2
	6	[526]	LEN      	5 4
	7	[526]	EQ       	0 5 -2	; - 0
	8	[526]	JMP      	2	; to 11
	9	[526]	LOADBOOL 	5 0 0
	10	[526]	RETURN   	5 2
	11	[528]	GETGLOBAL	5 -3	; ipairs
	12	[528]	MOVE     	6 4
	13	[528]	CALL     	5 2 4
	14	[528]	JMP      	5	; to 20
	15	[529]	GETGLOBAL	10 -4	; table
	16	[529]	GETTABLE 	10 10 -5	; "insert"
	17	[529]	GETTABLE 	11 0 -6	; "item_table"
	18	[529]	MOVE     	12 9
	19	[529]	CALL     	10 3 1
	20	[528]	TFORLOOP 	5 2
	21	[529]	JMP      	-7	; to 15
	22	[531]	GETTABLE 	5 0 -6	; "item_table"
	23	[531]	GETTABLE 	6 4 -7	; "hrefs"
	24	[531]	SETTABLE 	5 -7 6	; "hrefs" -
	25	[532]	SELF     	5 0 -8	; "switchItemTable"
	26	[532]	LOADNIL  	7 7
	27	[532]	GETTABLE 	8 0 -6	; "item_table"
	28	[532]	LOADK    	9 -9	; -1
	29	[532]	CALL     	5 5 1
	30	[533]	LOADBOOL 	5 1 0
	31	[533]	RETURN   	5 2
	32	[534]	RETURN   	0 1

function <./frontend/ui/widget/opdsbrowser.lua:536,539> (13 instructions, 52 bytes at 0x7fefd040e0b0)
0 params, 4 slots, 0 upvalues, 1 local, 4 constants, 0 functions
	1	[537]	GETGLOBAL	0 -1	; G_reader_settings
	2	[537]	SELF     	0 0 -2	; "readSetting"
	3	[537]	LOADK    	2 -3	; "lastdir"
	4	[537]	CALL     	0 3 2
	5	[538]	GETGLOBAL	1 -1	; G_reader_settings
	6	[538]	SELF     	1 1 -2	; "readSetting"
	7	[538]	LOADK    	3 -4	; "download_dir"
	8	[538]	CALL     	1 3 2
	9	[538]	TEST     	1 0 1
	10	[538]	JMP      	1	; to 12
	11	[538]	MOVE     	1 0
	12	[538]	RETURN   	1 2
	13	[539]	RETURN   	0 1

function <./frontend/ui/widget/opdsbrowser.lua:541,609> (76 instructions, 304 bytes at 0x7fefd040e830)
4 params, 17 slots, 14 upvalues, 8 locals, 22 constants, 2 functions
	1	[543]	GETTABLE 	4 0 -1	; "getCurrentDownloadDir"
	2	[543]	CALL     	4 1 2
	3	[544]	GETUPVAL 	5 0	; util
	4	[544]	GETTABLE 	5 5 -2	; "getSafeFilename"
	5	[544]	GETTABLE 	6 1 -3	; "author"
	6	[544]	LOADK    	7 -4	; " - "
	7	[544]	GETTABLE 	8 1 -5	; "title"
	8	[544]	LOADK    	9 -6	; "."
	9	[544]	GETGLOBAL	10 -7	; string
	10	[544]	GETTABLE 	10 10 -8	; "lower"
	11	[544]	MOVE     	11 2
	12	[544]	CALL     	10 2 2
	13	[544]	CONCAT   	6 6 10
	14	[544]	MOVE     	7 4
	15	[544]	CALL     	5 3 2
	16	[545]	MOVE     	6 4
	17	[545]	LOADK    	7 -9	; "/"
	18	[545]	MOVE     	8 5
	19	[545]	CONCAT   	6 6 8
	20	[546]	GETUPVAL 	7 0	; util
	21	[546]	GETTABLE 	7 7 -10	; "fixUtf8"
	22	[546]	MOVE     	8 6
	23	[546]	LOADK    	9 -11	; "_"
	24	[546]	CALL     	7 3 2
	25	[546]	MOVE     	6 7
	26	[596]	CLOSURE  	7 0	; 0x7fefd040ef70
	27	[596]	GETUPVAL 	0 1	; UIManager
	28	[596]	GETUPVAL 	0 2	; logger
	29	[596]	MOVE     	0 6
	30	[596]	MOVE     	0 3
	31	[596]	GETUPVAL 	0 3	; url
	32	[596]	GETUPVAL 	0 4	; http
	33	[596]	GETUPVAL 	0 5	; https
	34	[596]	GETUPVAL 	0 6	; ltn12
	35	[596]	MOVE     	0 1
	36	[596]	GETUPVAL 	0 7	; mime
	37	[596]	GETUPVAL 	0 8	; InfoMessage
	38	[596]	GETUPVAL 	0 9	; T
	39	[596]	GETUPVAL 	0 10	; _
	40	[596]	MOVE     	0 0
	41	[596]	GETUPVAL 	0 11	; BD
	42	[598]	GETUPVAL 	8 12	; lfs
	43	[598]	GETTABLE 	8 8 -12	; "attributes"
	44	[598]	MOVE     	9 6
	45	[598]	LOADK    	10 -13	; "mode"
	46	[598]	CALL     	8 3 2
	47	[598]	EQ       	0 8 -14	; - "file"
	48	[598]	JMP      	25	; to 74
	49	[599]	GETUPVAL 	8 1	; UIManager
	50	[599]	SELF     	8 8 -15	; "show"
	51	[599]	GETUPVAL 	10 13	; ConfirmBox
	52	[599]	SELF     	10 10 -16	; "new"
	53	[599]	NEWTABLE 	12 0 3
	54	[600]	GETUPVAL 	13 9	; T
	55	[600]	GETUPVAL 	14 10	; _
	56	[600]	LOADK    	15 -18	; "The file %1 already exists. Do you want to overwrite it?"
	57	[600]	CALL     	14 2 2
	58	[600]	GETUPVAL 	15 11	; BD
	59	[600]	GETTABLE 	15 15 -19	; "filepath"
	60	[600]	MOVE     	16 6
	61	[600]	CALL     	15 2 0
	62	[600]	CALL     	13 0 2
	63	[600]	SETTABLE 	12 -17 13	; "text" -
	64	[601]	GETUPVAL 	13 10	; _
	65	[601]	LOADK    	14 -21	; "Overwrite"
	66	[601]	CALL     	13 2 2
	67	[601]	SETTABLE 	12 -20 13	; "ok_text" -
	68	[604]	CLOSURE  	13 1	; 0x7fefd040eef0
	69	[604]	MOVE     	0 7
	70	[604]	SETTABLE 	12 -22 13	; "ok_callback" -
	71	[599]	CALL     	10 3 0
	72	[599]	CALL     	8 0 1
	73	[605]	JMP      	2	; to 76
	74	[607]	MOVE     	8 7
	75	[607]	CALL     	8 1 1
	76	[609]	RETURN   	0 1

function <./frontend/ui/widget/opdsbrowser.lua:548,596> (33 instructions, 132 bytes at 0x7fefd040ef70)
0 params, 7 slots, 15 upvalues, 0 locals, 7 constants, 1 function
	1	[549]	GETUPVAL 	0 0	; UIManager
	2	[549]	SELF     	0 0 -1	; "scheduleIn"
	3	[549]	LOADK    	2 -2	; 1
	4	[590]	CLOSURE  	3 0	; 0x7fefd040f1d0
	5	[590]	GETUPVAL 	0 1	; logger
	6	[590]	GETUPVAL 	0 2	; local_path
	7	[590]	GETUPVAL 	0 3	; remote_url
	8	[590]	GETUPVAL 	0 4	; url
	9	[590]	GETUPVAL 	0 5	; http
	10	[590]	GETUPVAL 	0 6	; https
	11	[590]	GETUPVAL 	0 7	; ltn12
	12	[590]	GETUPVAL 	0 8	; item
	13	[590]	GETUPVAL 	0 9	; mime
	14	[590]	GETUPVAL 	0 0	; UIManager
	15	[590]	GETUPVAL 	0 10	; InfoMessage
	16	[590]	GETUPVAL 	0 11	; T
	17	[590]	GETUPVAL 	0 12	; _
	18	[590]	GETUPVAL 	0 13	; self
	19	[590]	GETUPVAL 	0 14	; BD
	20	[549]	CALL     	0 4 1
	21	[592]	GETUPVAL 	0 0	; UIManager
	22	[592]	SELF     	0 0 -3	; "show"
	23	[592]	GETUPVAL 	2 10	; InfoMessage
	24	[592]	SELF     	2 2 -4	; "new"
	25	[592]	NEWTABLE 	4 0 2
	26	[593]	GETUPVAL 	5 12	; _
	27	[593]	LOADK    	6 -6	; "Downloading may take several minutes\226\128\166"
	28	[593]	CALL     	5 2 2
	29	[593]	SETTABLE 	4 -5 5	; "text" -
	30	[594]	SETTABLE 	4 -7 -2	; "timeout" 1
	31	[592]	CALL     	2 3 0
	32	[592]	CALL     	0 0 1
	33	[596]	RETURN   	0 1

function <./frontend/ui/widget/opdsbrowser.lua:549,590> (135 instructions, 540 bytes at 0x7fefd040f1d0)
0 params, 11 slots, 15 upvalues, 5 locals, 39 constants, 0 functions
	1	[550]	GETUPVAL 	0 0	; logger
	2	[550]	GETTABLE 	0 0 -1	; "dbg"
	3	[550]	LOADK    	1 -2	; "downloading file"
	4	[550]	GETUPVAL 	2 1	; local_path
	5	[550]	LOADK    	3 -3	; "from"
	6	[550]	GETUPVAL 	4 2	; remote_url
	7	[550]	CALL     	0 5 1
	8	[551]	GETUPVAL 	0 3	; url
	9	[551]	GETTABLE 	0 0 -4	; "parse"
	10	[551]	GETUPVAL 	1 2	; remote_url
	11	[551]	CALL     	0 2 2
	12	[552]	GETUPVAL 	1 4	; http
	13	[552]	GETUPVAL 	2 5	; https
	14	[552]	LOADK    	3 -6	; 20
	15	[552]	SETTABLE 	2 -5 -6	; "TIMEOUT" 20
	16	[552]	SETTABLE 	1 -5 3	; "TIMEOUT" -
	17	[554]	LOADNIL  	1 2
	18	[556]	GETTABLE 	3 0 -7	; "scheme"
	19	[556]	EQ       	0 3 -8	; - "http"
	20	[556]	JMP      	25	; to 46
	21	[557]	GETUPVAL 	3 4	; http
	22	[557]	GETTABLE 	3 3 -9	; "request"
	23	[557]	NEWTABLE 	4 0 4
	24	[558]	GETUPVAL 	5 2	; remote_url
	25	[558]	SETTABLE 	4 -10 5	; "url" -
	26	[559]	GETUPVAL 	5 6	; ltn12
	27	[559]	GETTABLE 	5 5 -11	; "sink"
	28	[559]	GETTABLE 	5 5 -12	; "file"
	29	[559]	GETGLOBAL	6 -13	; io
	30	[559]	GETTABLE 	6 6 -14	; "open"
	31	[559]	GETUPVAL 	7 1	; local_path
	32	[559]	LOADK    	8 -15	; "w"
	33	[559]	CALL     	6 3 0
	34	[559]	CALL     	5 0 2
	35	[559]	SETTABLE 	4 -11 5	; "sink" -
	36	[560]	GETUPVAL 	5 7	; item
	37	[560]	GETTABLE 	5 5 -17	; "username"
	38	[560]	SETTABLE 	4 -16 5	; "user" -
	39	[561]	GETUPVAL 	5 7	; item
	40	[561]	GETTABLE 	5 5 -18	; "password"
	41	[561]	SETTABLE 	4 -18 5	; "password" -
	42	[557]	CALL     	3 2 3
	43	[562]	MOVE     	2 4
	44	[562]	MOVE     	1 3
	45	[562]	JMP      	56	; to 102
	46	[563]	GETTABLE 	3 0 -7	; "scheme"
	47	[563]	EQ       	0 3 -19	; - "https"
	48	[563]	JMP      	38	; to 87
	49	[564]	GETGLOBAL	3 -20	; string
	50	[564]	GETTABLE 	3 3 -21	; "format"
	51	[564]	LOADK    	4 -22	; "%s:%s"
	52	[564]	GETUPVAL 	5 7	; item
	53	[564]	GETTABLE 	5 5 -17	; "username"
	54	[564]	GETUPVAL 	6 7	; item
	55	[564]	GETTABLE 	6 6 -18	; "password"
	56	[564]	CALL     	3 4 2
	57	[565]	GETTABLE 	4 0 -23	; "host"
	58	[567]	GETUPVAL 	5 5	; https
	59	[567]	GETTABLE 	5 5 -9	; "request"
	60	[567]	NEWTABLE 	6 0 3
	61	[568]	GETUPVAL 	7 2	; remote_url
	62	[568]	SETTABLE 	6 -10 7	; "url" -
	63	[569]	NEWTABLE 	7 0 2
	64	[569]	LOADK    	8 -26	; "Basic "
	65	[569]	GETUPVAL 	9 8	; mime
	66	[569]	GETTABLE 	9 9 -27	; "b64"
	67	[569]	MOVE     	10 3
	68	[569]	CALL     	9 2 2
	69	[569]	CONCAT   	8 8 9
	70	[569]	SETTABLE 	7 -25 8	; "Authorization" -
	71	[569]	SETTABLE 	7 -28 4	; "Host" -
	72	[569]	SETTABLE 	6 -24 7	; "headers" -
	73	[570]	GETUPVAL 	7 6	; ltn12
	74	[570]	GETTABLE 	7 7 -11	; "sink"
	75	[570]	GETTABLE 	7 7 -12	; "file"
	76	[570]	GETGLOBAL	8 -13	; io
	77	[570]	GETTABLE 	8 8 -14	; "open"
	78	[570]	GETUPVAL 	9 1	; local_path
	79	[570]	LOADK    	10 -15	; "w"
	80	[570]	CALL     	8 3 0
	81	[570]	CALL     	7 0 2
	82	[570]	SETTABLE 	6 -11 7	; "sink" -
	83	[567]	CALL     	5 2 3
	84	[571]	MOVE     	2 6
	85	[571]	MOVE     	1 5
	86	[571]	JMP      	15	; to 102
	87	[573]	GETUPVAL 	3 9	; UIManager
	88	[573]	SELF     	3 3 -29	; "show"
	89	[573]	GETUPVAL 	5 10	; InfoMessage
	90	[573]	SELF     	5 5 -30	; "new"
	91	[573]	NEWTABLE 	7 0 2
	92	[574]	GETUPVAL 	8 11	; T
	93	[574]	GETUPVAL 	9 12	; _
	94	[574]	LOADK    	10 -32	; "Invalid protocol:\n%1"
	95	[574]	CALL     	9 2 2
	96	[574]	GETTABLE 	10 0 -7	; "scheme"
	97	[574]	CALL     	8 3 2
	98	[574]	SETTABLE 	7 -31 8	; "text" -
	99	[575]	SETTABLE 	7 -33 -34	; "timeout" 3
	100	[573]	CALL     	5 3 0
	101	[573]	CALL     	3 0 1
	102	[579]	EQ       	0 2 -35	; - 200
	103	[579]	JMP      	14	; to 118
	104	[580]	GETUPVAL 	3 0	; logger
	105	[580]	GETTABLE 	3 3 -1	; "dbg"
	106	[580]	LOADK    	4 -36	; "file downloaded to"
	107	[580]	GETUPVAL 	5 1	; local_path
	108	[580]	CALL     	3 3 1
	109	[581]	GETUPVAL 	3 13	; self
	110	[581]	GETTABLE 	3 3 -37	; "file_downloaded_callback"
	111	[581]	TEST     	3 0 0
	112	[581]	JMP      	22	; to 135
	113	[582]	GETUPVAL 	3 13	; self
	114	[582]	GETTABLE 	3 3 -37	; "file_downloaded_callback"
	115	[582]	GETUPVAL 	4 1	; local_path
	116	[582]	CALL     	3 2 1
	117	[583]	JMP      	17	; to 135
	118	[585]	GETUPVAL 	3 9	; UIManager
	119	[585]	SELF     	3 3 -29	; "show"
	120	[585]	GETUPVAL 	5 10	; InfoMessage
	121	[585]	SELF     	5 5 -30	; "new"
	122	[585]	NEWTABLE 	7 0 2
	123	[586]	GETUPVAL 	8 12	; _
	124	[586]	LOADK    	9 -38	; "Could not save file to:\n"
	125	[586]	CALL     	8 2 2
	126	[586]	GETUPVAL 	9 14	; BD
	127	[586]	GETTABLE 	9 9 -39	; "filepath"
	128	[586]	GETUPVAL 	10 1	; local_path
	129	[586]	CALL     	9 2 2
	130	[586]	CONCAT   	8 8 9
	131	[586]	SETTABLE 	7 -31 8	; "text" -
	132	[587]	SETTABLE 	7 -33 -34	; "timeout" 3
	133	[585]	CALL     	5 3 0
	134	[585]	CALL     	3 0 1
	135	[590]	RETURN   	0 1

function <./frontend/ui/widget/opdsbrowser.lua:602,604> (3 instructions, 12 bytes at 0x7fefd040eef0)
0 params, 2 slots, 1 upvalue, 0 locals, 0 constants, 0 functions
	1	[603]	GETUPVAL 	0 0	; download
	2	[603]	CALL     	0 1 1
	3	[604]	RETURN   	0 1

function <./frontend/ui/widget/opdsbrowser.lua:611,616> (17 instructions, 68 bytes at 0x7fefd040d4d0)
3 params, 10 slots, 4 upvalues, 3 locals, 6 constants, 0 functions
	1	[612]	GETUPVAL 	3 0	; ButtonDialogTitle
	2	[612]	SELF     	3 3 -2	; "new"
	3	[612]	NEWTABLE 	5 0 2
	4	[613]	GETUPVAL 	6 1	; T
	5	[613]	GETUPVAL 	7 2	; _
	6	[613]	LOADK    	8 -4	; "Download directory:\n%1\n\nDownload file type:"
	7	[613]	CALL     	7 2 2
	8	[613]	GETUPVAL 	8 3	; BD
	9	[613]	GETTABLE 	8 8 -5	; "dirpath"
	10	[613]	MOVE     	9 1
	11	[613]	CALL     	8 2 0
	12	[613]	CALL     	6 0 2
	13	[613]	SETTABLE 	5 -3 6	; "title" -
	14	[614]	SETTABLE 	5 -6 2	; "buttons" -
	15	[612]	CALL     	3 3 2
	16	[615]	SETTABLE 	0 -1 3	; "download_dialog" -
	17	[616]	RETURN   	0 1

function <./frontend/ui/widget/opdsbrowser.lua:618,669> (96 instructions, 384 bytes at 0x7fefd040edf0)
2 params, 22 slots, 3 upvalues, 19 locals, 18 constants, 2 functions
	1	[619]	GETTABLE 	2 1 -1	; "acquisitions"
	2	[620]	LOADK    	3 -2	; 2
	3	[621]	GETGLOBAL	4 -3	; math
	4	[621]	GETTABLE 	4 4 -4	; "ceil"
	5	[621]	LEN      	5 2
	6	[621]	DIV      	5 5 3
	7	[621]	CALL     	4 2 2
	8	[622]	NEWTABLE 	5 0 0
	9	[623]	LOADK    	6 -5	; 1
	10	[623]	MOVE     	7 4
	11	[623]	LOADK    	8 -5	; 1
	12	[623]	FORPREP  	6 51	; to 64
	13	[624]	NEWTABLE 	10 0 0
	14	[625]	LOADK    	11 -5	; 1
	15	[625]	MOVE     	12 3
	16	[625]	LOADK    	13 -5	; 1
	17	[625]	FORPREP  	11 40	; to 58
	18	[626]	NEWTABLE 	15 0 0
	19	[627]	SUB      	16 9 -5	; - 1
	20	[627]	MUL      	16 16 3
	21	[627]	ADD      	16 16 14
	22	[628]	GETTABLE 	17 2 16
	23	[629]	TEST     	17 0 0
	24	[629]	JMP      	23	; to 48
	25	[630]	GETTABLE 	18 0 -6	; "formats"
	26	[630]	GETTABLE 	19 17 -7	; "type"
	27	[630]	GETTABLE 	18 18 19
	28	[631]	TEST     	18 0 0
	29	[631]	JMP      	16	; to 46
	30	[633]	MOVE     	19 18
	31	[633]	LOADK    	20 -9	; "xE2xACx87"
	32	[633]	CONCAT   	19 19 20
	33	[633]	SETTABLE 	15 -8 19	; "text" -
	34	[637]	CLOSURE  	19 0	; 0x7fefd040fd90
	35	[637]	MOVE     	0 0
	36	[637]	MOVE     	0 1
	37	[637]	MOVE     	0 18
	38	[637]	MOVE     	0 17
	39	[637]	GETUPVAL 	0 0	; UIManager
	40	[637]	SETTABLE 	15 -10 19	; "callback" -
	41	[638]	GETGLOBAL	19 -11	; table
	42	[638]	GETTABLE 	19 19 -12	; "insert"
	43	[638]	MOVE     	20 10
	44	[638]	MOVE     	21 15
	45	[638]	CALL     	19 3 1
	46	[639]	CLOSE    	18
	47	[639]	JMP      	9	; to 57
	48	[640]	LEN      	18 2
	49	[640]	LT       	0 3 18
	50	[640]	JMP      	6	; to 57
	51	[641]	GETGLOBAL	18 -11	; table
	52	[641]	GETTABLE 	18 18 -12	; "insert"
	53	[641]	MOVE     	19 10
	54	[641]	NEWTABLE 	20 0 1
	55	[641]	SETTABLE 	20 -8 -13	; "text" ""
	56	[641]	CALL     	18 3 1
	57	[642]	CLOSE    	15
	58	[625]	FORLOOP  	11 -41	; to 18
	59	[644]	GETGLOBAL	11 -11	; table
	60	[644]	GETTABLE 	11 11 -12	; "insert"
	61	[644]	MOVE     	12 5
	62	[644]	MOVE     	13 10
	63	[644]	CALL     	11 3 1
	64	[623]	FORLOOP  	6 -52	; to 13
	65	[646]	GETGLOBAL	6 -11	; table
	66	[646]	GETTABLE 	6 6 -12	; "insert"
	67	[646]	MOVE     	7 5
	68	[646]	NEWTABLE 	8 0 0
	69	[646]	CALL     	6 3 1
	70	[648]	GETGLOBAL	6 -11	; table
	71	[648]	GETTABLE 	6 6 -12	; "insert"
	72	[648]	MOVE     	7 5
	73	[648]	NEWTABLE 	8 1 0
	74	[648]	NEWTABLE 	9 0 2
	75	[650]	GETUPVAL 	10 1	; _
	76	[650]	LOADK    	11 -14	; "Select another directory"
	77	[650]	CALL     	10 2 2
	78	[650]	SETTABLE 	9 -8 10	; "text" -
	79	[663]	CLOSURE  	10 1	; 0x7fefd0410110
	80	[663]	GETUPVAL 	0 2	; logger
	81	[663]	GETUPVAL 	0 0	; UIManager
	82	[663]	MOVE     	0 0
	83	[663]	MOVE     	0 5
	84	[663]	SETTABLE 	9 -10 10	; "callback" -
	85	[665]	SETLIST  	8 1 1	; 1
	86	[648]	CALL     	6 3 1
	87	[667]	SELF     	6 0 -15	; "createNewDownloadDialog"
	88	[667]	GETTABLE 	8 0 -16	; "getCurrentDownloadDir"
	89	[667]	CALL     	8 1 2
	90	[667]	MOVE     	9 5
	91	[667]	CALL     	6 4 1
	92	[668]	GETUPVAL 	6 0	; UIManager
	93	[668]	SELF     	6 6 -17	; "show"
	94	[668]	GETTABLE 	8 0 -18	; "download_dialog"
	95	[668]	CALL     	6 3 1
	96	[669]	RETURN   	0 1

function <./frontend/ui/widget/opdsbrowser.lua:634,637> (13 instructions, 52 bytes at 0x7fefd040fd90)
0 params, 5 slots, 5 upvalues, 0 locals, 4 constants, 0 functions
	1	[635]	GETUPVAL 	0 0	; self
	2	[635]	SELF     	0 0 -1	; "downloadFile"
	3	[635]	GETUPVAL 	2 1	; item
	4	[635]	GETUPVAL 	3 2	; format
	5	[635]	GETUPVAL 	4 3	; acquisition
	6	[635]	GETTABLE 	4 4 -2	; "href"
	7	[635]	CALL     	0 5 1
	8	[636]	GETUPVAL 	0 4	; UIManager
	9	[636]	SELF     	0 0 -3	; "close"
	10	[636]	GETUPVAL 	2 0	; self
	11	[636]	GETTABLE 	2 2 -4	; "download_dialog"
	12	[636]	CALL     	0 3 1
	13	[637]	RETURN   	0 1

function <./frontend/ui/widget/opdsbrowser.lua:651,663> (15 instructions, 60 bytes at 0x7fefd0410110)
0 params, 4 slots, 4 upvalues, 0 locals, 5 constants, 1 function
	1	[652]	GETGLOBAL	0 -1	; require
	2	[652]	LOADK    	1 -2	; "ui/downloadmgr"
	3	[652]	CALL     	0 2 2
	4	[652]	SELF     	0 0 -3	; "new"
	5	[652]	NEWTABLE 	2 0 1
	6	[661]	CLOSURE  	3 0	; 0x7fefd0410b30
	7	[661]	GETUPVAL 	0 0	; logger
	8	[661]	GETUPVAL 	0 1	; UIManager
	9	[661]	GETUPVAL 	0 2	; self
	10	[661]	GETUPVAL 	0 3	; buttons
	11	[661]	SETTABLE 	2 -4 3	; "onConfirm" -
	12	[652]	CALL     	0 3 2
	13	[662]	SELF     	0 0 -5	; "chooseDir"
	14	[662]	CALL     	0 2 1
	15	[663]	RETURN   	0 1

function <./frontend/ui/widget/opdsbrowser.lua:653,661> (19 instructions, 76 bytes at 0x7fefd0410b30)
1 param, 5 slots, 4 upvalues, 1 local, 6 constants, 1 function
	1	[654]	GETUPVAL 	1 0	; logger
	2	[654]	GETTABLE 	1 1 -1	; "info"
	3	[654]	LOADK    	2 -2	; "set download directory to"
	4	[654]	MOVE     	3 0
	5	[654]	CALL     	1 3 1
	6	[655]	GETGLOBAL	1 -3	; G_reader_settings
	7	[655]	SELF     	1 1 -4	; "saveSetting"
	8	[655]	LOADK    	3 -5	; "download_dir"
	9	[655]	MOVE     	4 0
	10	[655]	CALL     	1 4 1
	11	[656]	GETUPVAL 	1 1	; UIManager
	12	[656]	SELF     	1 1 -6	; "nextTick"
	13	[660]	CLOSURE  	3 0	; 0x7fefd0410d40
	14	[660]	GETUPVAL 	0 1	; UIManager
	15	[660]	GETUPVAL 	0 2	; self
	16	[660]	MOVE     	0 0
	17	[660]	GETUPVAL 	0 3	; buttons
	18	[656]	CALL     	1 3 1
	19	[661]	RETURN   	0 1

function <./frontend/ui/widget/opdsbrowser.lua:656,660> (16 instructions, 64 bytes at 0x7fefd0410d40)
0 params, 4 slots, 4 upvalues, 0 locals, 4 constants, 0 functions
	1	[657]	GETUPVAL 	0 0	; UIManager
	2	[657]	SELF     	0 0 -1	; "close"
	3	[657]	GETUPVAL 	2 1	; self
	4	[657]	GETTABLE 	2 2 -2	; "download_dialog"
	5	[657]	CALL     	0 3 1
	6	[658]	GETUPVAL 	0 1	; self
	7	[658]	SELF     	0 0 -3	; "createNewDownloadDialog"
	8	[658]	GETUPVAL 	2 2	; path
	9	[658]	GETUPVAL 	3 3	; buttons
	10	[658]	CALL     	0 4 1
	11	[659]	GETUPVAL 	0 0	; UIManager
	12	[659]	SELF     	0 0 -4	; "show"
	13	[659]	GETUPVAL 	2 1	; self
	14	[659]	GETTABLE 	2 2 -2	; "download_dialog"
	15	[659]	CALL     	0 3 1
	16	[660]	RETURN   	0 1

function <./frontend/ui/widget/opdsbrowser.lua:671,681> (25 instructions, 100 bytes at 0x7fefd040cbc0)
4 params, 9 slots, 1 upvalue, 4 locals, 10 constants, 0 functions
	1	[672]	GETUPVAL 	4 0	; logger
	2	[672]	GETTABLE 	4 4 -1	; "dbg"
	3	[672]	LOADK    	5 -2	; "Browse opds url"
	4	[672]	MOVE     	6 1
	5	[672]	CALL     	4 3 1
	6	[673]	GETGLOBAL	4 -3	; table
	7	[673]	GETTABLE 	4 4 -4	; "insert"
	8	[673]	GETTABLE 	5 0 -5	; "paths"
	9	[673]	NEWTABLE 	6 0 3
	10	[674]	SETTABLE 	6 -6 1	; "url" -
	11	[675]	SETTABLE 	6 -7 2	; "username" -
	12	[676]	SETTABLE 	6 -8 3	; "password" -
	13	[673]	CALL     	4 3 1
	14	[678]	SELF     	4 0 -9	; "updateCatalog"
	15	[678]	MOVE     	6 1
	16	[678]	MOVE     	7 2
	17	[678]	MOVE     	8 3
	18	[678]	CALL     	4 5 2
	19	[678]	TEST     	4 0 1
	20	[678]	JMP      	4	; to 25
	21	[679]	GETGLOBAL	4 -3	; table
	22	[679]	GETTABLE 	4 4 -10	; "remove"
	23	[679]	GETTABLE 	5 0 -5	; "paths"
	24	[679]	CALL     	4 2 1
	25	[681]	RETURN   	0 1

function <./frontend/ui/widget/opdsbrowser.lua:683,715> (58 instructions, 232 bytes at 0x7fefd0411a70)
4 params, 13 slots, 3 upvalues, 4 locals, 23 constants, 2 functions
	1	[684]	GETUPVAL 	4 0	; InputDialog
	2	[684]	SELF     	4 4 -2	; "new"
	3	[684]	NEWTABLE 	6 0 7
	4	[685]	GETUPVAL 	7 1	; _
	5	[685]	LOADK    	8 -4	; "Search OPDS catalog"
	6	[685]	CALL     	7 2 2
	7	[685]	SETTABLE 	6 -3 7	; "title" -
	8	[686]	SETTABLE 	6 -5 -6	; "input" ""
	9	[687]	GETUPVAL 	7 1	; _
	10	[687]	LOADK    	8 -8	; "Search string"
	11	[687]	CALL     	7 2 2
	12	[687]	SETTABLE 	6 -7 7	; "hint" -
	13	[689]	GETUPVAL 	7 1	; _
	14	[689]	LOADK    	8 -10	; "Alexandre Dumas"
	15	[689]	CALL     	7 2 2
	16	[689]	SETTABLE 	6 -9 7	; "input_hint" -
	17	[690]	SETTABLE 	6 -11 -12	; "input_type" "string"
	18	[691]	GETUPVAL 	7 1	; _
	19	[691]	LOADK    	8 -14	; "%s in url will be replaced by your input"
	20	[691]	CALL     	7 2 2
	21	[691]	SETTABLE 	6 -13 7	; "description" -
	22	[692]	NEWTABLE 	7 1 0
	23	[692]	NEWTABLE 	8 2 0
	24	[693]	NEWTABLE 	9 0 2
	25	[695]	GETUPVAL 	10 1	; _
	26	[695]	LOADK    	11 -17	; "Cancel"
	27	[695]	CALL     	10 2 2
	28	[695]	SETTABLE 	9 -16 10	; "text" -
	29	[698]	CLOSURE  	10 0	; 0x7fefd0411f10
	30	[698]	GETUPVAL 	0 2	; UIManager
	31	[698]	MOVE     	0 0
	32	[698]	SETTABLE 	9 -18 10	; "callback" -
	33	[699]	NEWTABLE 	10 0 3
	34	[701]	GETUPVAL 	11 1	; _
	35	[701]	LOADK    	12 -19	; "Search"
	36	[701]	CALL     	11 2 2
	37	[701]	SETTABLE 	10 -16 11	; "text" -
	38	[702]	SETTABLE 	10 -20 -21	; "is_enter_default" true
	39	[708]	CLOSURE  	11 1	; 0x7fefd0411e40
	40	[708]	GETUPVAL 	0 2	; UIManager
	41	[708]	MOVE     	0 0
	42	[708]	MOVE     	0 1
	43	[708]	MOVE     	0 2
	44	[708]	MOVE     	0 3
	45	[708]	SETTABLE 	10 -18 11	; "callback" -
	46	[710]	SETLIST  	8 2 1	; 1
	47	[711]	SETLIST  	7 1 1	; 1
	48	[711]	SETTABLE 	6 -15 7	; "buttons" -
	49	[684]	CALL     	4 3 2
	50	[712]	SETTABLE 	0 -1 4	; "search_server_dialog" -
	51	[713]	GETUPVAL 	4 2	; UIManager
	52	[713]	SELF     	4 4 -22	; "show"
	53	[713]	GETTABLE 	6 0 -1	; "search_server_dialog"
	54	[713]	CALL     	4 3 1
	55	[714]	GETTABLE 	4 0 -1	; "search_server_dialog"
	56	[714]	SELF     	4 4 -23	; "onShowKeyboard"
	57	[714]	CALL     	4 2 1
	58	[715]	RETURN   	0 1

function <./frontend/ui/widget/opdsbrowser.lua:696,698> (6 instructions, 24 bytes at 0x7fefd0411f10)
0 params, 3 slots, 2 upvalues, 0 locals, 2 constants, 0 functions
	1	[697]	GETUPVAL 	0 0	; UIManager
	2	[697]	SELF     	0 0 -1	; "close"
	3	[697]	GETUPVAL 	2 1	; self
	4	[697]	GETTABLE 	2 2 -2	; "search_server_dialog"
	5	[697]	CALL     	0 3 1
	6	[698]	RETURN   	0 1

function <./frontend/ui/widget/opdsbrowser.lua:703,708> (25 instructions, 100 bytes at 0x7fefd0411e40)
0 params, 7 slots, 5 upvalues, 2 locals, 8 constants, 0 functions
	1	[704]	GETUPVAL 	0 0	; UIManager
	2	[704]	SELF     	0 0 -1	; "close"
	3	[704]	GETUPVAL 	2 1	; self
	4	[704]	GETTABLE 	2 2 -2	; "search_server_dialog"
	5	[704]	CALL     	0 3 1
	6	[705]	GETUPVAL 	0 1	; self
	7	[705]	GETTABLE 	0 0 -2	; "search_server_dialog"
	8	[705]	SELF     	0 0 -3	; "getInputText"
	9	[705]	CALL     	0 2 2
	10	[705]	SELF     	0 0 -4	; "gsub"
	11	[705]	LOADK    	2 -5	; " "
	12	[705]	LOADK    	3 -6	; "+"
	13	[705]	CALL     	0 4 2
	14	[706]	GETUPVAL 	1 2	; browse_url
	15	[706]	SELF     	1 1 -4	; "gsub"
	16	[706]	LOADK    	3 -7	; "%%s"
	17	[706]	MOVE     	4 0
	18	[706]	CALL     	1 4 2
	19	[707]	GETUPVAL 	2 1	; self
	20	[707]	SELF     	2 2 -8	; "browse"
	21	[707]	MOVE     	4 1
	22	[707]	GETUPVAL 	5 3	; username
	23	[707]	GETUPVAL 	6 4	; password
	24	[707]	CALL     	2 5 1
	25	[708]	RETURN   	0 1

function <./frontend/ui/widget/opdsbrowser.lua:717,734> (39 instructions, 156 bytes at 0x7fefd04127d0)
2 params, 7 slots, 1 upvalue, 2 locals, 12 constants, 0 functions
	1	[719]	GETTABLE 	2 1 -1	; "callback"
	2	[719]	TEST     	2 0 0
	3	[719]	JMP      	3	; to 7
	4	[720]	GETTABLE 	2 1 -1	; "callback"
	5	[720]	CALL     	2 1 1
	6	[720]	JMP      	30	; to 37
	7	[722]	GETTABLE 	2 1 -2	; "acquisitions"
	8	[722]	TEST     	2 0 0
	9	[722]	JMP      	13	; to 23
	10	[722]	GETTABLE 	2 1 -2	; "acquisitions"
	11	[722]	LEN      	2 2
	12	[722]	LT       	0 -3 2	; 0 -
	13	[722]	JMP      	9	; to 23
	14	[723]	GETUPVAL 	2 0	; logger
	15	[723]	GETTABLE 	2 2 -4	; "dbg"
	16	[723]	LOADK    	3 -5	; "downloads available"
	17	[723]	MOVE     	4 1
	18	[723]	CALL     	2 3 1
	19	[724]	SELF     	2 0 -6	; "showDownloads"
	20	[724]	MOVE     	4 1
	21	[724]	CALL     	2 3 1
	22	[724]	JMP      	14	; to 37
	23	[727]	GETTABLE 	2 1 -7	; "searchable"
	24	[727]	TEST     	2 0 0
	25	[727]	JMP      	6	; to 32
	26	[728]	SELF     	2 0 -8	; "browseSearchable"
	27	[728]	GETTABLE 	4 1 -9	; "url"
	28	[728]	GETTABLE 	5 1 -10	; "username"
	29	[728]	GETTABLE 	6 1 -11	; "password"
	30	[728]	CALL     	2 5 1
	31	[728]	JMP      	5	; to 37
	32	[730]	SELF     	2 0 -12	; "browse"
	33	[730]	GETTABLE 	4 1 -9	; "url"
	34	[730]	GETTABLE 	5 1 -10	; "username"
	35	[730]	GETTABLE 	6 1 -11	; "password"
	36	[730]	CALL     	2 5 1
	37	[733]	LOADBOOL 	2 1 0
	38	[733]	RETURN   	2 2
	39	[734]	RETURN   	0 1

function <./frontend/ui/widget/opdsbrowser.lua:736,751> (69 instructions, 276 bytes at 0x7fefd0412990)
3 params, 12 slots, 1 upvalue, 9 locals, 24 constants, 0 functions
	1	[737]	GETUPVAL 	3 0	; logger
	2	[737]	GETTABLE 	3 3 -1	; "info"
	3	[737]	LOADK    	4 -2	; "input catalog"
	4	[737]	MOVE     	5 2
	5	[737]	CALL     	3 3 1
	6	[738]	NEWTABLE 	3 0 0
	7	[739]	GETGLOBAL	4 -3	; ipairs
	8	[739]	GETGLOBAL	5 -4	; G_reader_settings
	9	[739]	SELF     	5 5 -5	; "readSetting"
	10	[739]	LOADK    	7 -6	; "opds_servers"
	11	[739]	CALL     	5 3 2
	12	[739]	TEST     	5 0 1
	13	[739]	JMP      	1	; to 15
	14	[739]	NEWTABLE 	5 0 0
	15	[739]	CALL     	4 2 4
	16	[739]	JMP      	43	; to 60
	17	[740]	GETTABLE 	9 8 -7	; "title"
	18	[740]	GETTABLE 	10 1 -8	; "text"
	19	[740]	EQ       	1 9 10
	20	[740]	JMP      	4	; to 25
	21	[740]	GETTABLE 	9 8 -9	; "url"
	22	[740]	GETTABLE 	10 1 -9	; "url"
	23	[740]	EQ       	0 9 10
	24	[740]	JMP      	30	; to 55
	25	[741]	GETTABLE 	9 2 -10	; 1
	26	[741]	SETTABLE 	8 -7 9	; "title" -
	27	[742]	GETTABLE 	9 2 -11	; 2
	28	[742]	SELF     	9 9 -12	; "match"
	29	[742]	LOADK    	11 -13	; "^%a+://"
	30	[742]	CALL     	9 3 2
	31	[742]	TEST     	9 0 0
	32	[742]	JMP      	3	; to 36
	33	[742]	GETTABLE 	9 2 -11	; 2
	34	[742]	TEST     	9 0 1
	35	[742]	JMP      	3	; to 39
	36	[742]	LOADK    	9 -14	; "http://"
	37	[742]	GETTABLE 	10 2 -11	; 2
	38	[742]	CONCAT   	9 9 10
	39	[742]	SETTABLE 	8 -9 9	; "url" -
	40	[743]	GETTABLE 	9 2 -11	; 2
	41	[743]	SELF     	9 9 -12	; "match"
	42	[743]	LOADK    	11 -16	; "%%s"
	43	[743]	CALL     	9 3 2
	44	[743]	TEST     	9 0 0
	45	[743]	JMP      	3	; to 49
	46	[743]	LOADBOOL 	9 1 0
	47	[743]	TEST     	9 0 1
	48	[743]	JMP      	1	; to 50
	49	[743]	LOADBOOL 	9 0 0
	50	[743]	SETTABLE 	8 -15 9	; "searchable" -
	51	[744]	GETTABLE 	9 2 -18	; 3
	52	[744]	SETTABLE 	8 -17 9	; "username" -
	53	[745]	GETTABLE 	9 2 -20	; 4
	54	[745]	SETTABLE 	8 -19 9	; "password" -
	55	[747]	GETGLOBAL	9 -21	; table
	56	[747]	GETTABLE 	9 9 -22	; "insert"
	57	[747]	MOVE     	10 3
	58	[747]	MOVE     	11 8
	59	[747]	CALL     	9 3 1
	60	[739]	TFORLOOP 	4 2
	61	[747]	JMP      	-45	; to 17
	62	[749]	GETGLOBAL	4 -4	; G_reader_settings
	63	[749]	SELF     	4 4 -23	; "saveSetting"
	64	[749]	LOADK    	6 -6	; "opds_servers"
	65	[749]	MOVE     	7 3
	66	[749]	CALL     	4 4 1
	67	[750]	SELF     	4 0 -24	; "init"
	68	[750]	CALL     	4 2 1
	69	[751]	RETURN   	0 1

function <./frontend/ui/widget/opdsbrowser.lua:753,800> (101 instructions, 404 bytes at 0x7fefd0413040)
2 params, 12 slots, 5 upvalues, 2 locals, 30 constants, 2 functions
	1	[754]	GETUPVAL 	2 0	; logger
	2	[754]	GETTABLE 	2 2 -1	; "info"
	3	[754]	LOADK    	3 -2	; "edit"
	4	[754]	MOVE     	4 1
	5	[754]	CALL     	2 3 1
	6	[755]	GETUPVAL 	2 1	; MultiInputDialog
	7	[755]	SELF     	2 2 -4	; "new"
	8	[755]	NEWTABLE 	4 0 5
	9	[756]	GETUPVAL 	5 2	; _
	10	[756]	LOADK    	6 -6	; "Edit OPDS catalog"
	11	[756]	CALL     	5 2 2
	12	[756]	SETTABLE 	4 -5 5	; "title" -
	13	[757]	NEWTABLE 	5 4 0
	14	[757]	NEWTABLE 	6 0 2
	15	[759]	GETTABLE 	7 1 -8	; "text"
	16	[759]	TEST     	7 0 1
	17	[759]	JMP      	1	; to 19
	18	[759]	LOADK    	7 -9	; ""
	19	[759]	SETTABLE 	6 -8 7	; "text" -
	20	[760]	GETUPVAL 	7 2	; _
	21	[760]	LOADK    	8 -11	; "Catalog Name"
	22	[760]	CALL     	7 2 2
	23	[760]	SETTABLE 	6 -10 7	; "hint" -
	24	[761]	NEWTABLE 	7 0 2
	25	[763]	GETTABLE 	8 1 -12	; "url"
	26	[763]	TEST     	8 0 1
	27	[763]	JMP      	1	; to 29
	28	[763]	LOADK    	8 -9	; ""
	29	[763]	SETTABLE 	7 -8 8	; "text" -
	30	[764]	GETUPVAL 	8 2	; _
	31	[764]	LOADK    	9 -13	; "Catalog URL"
	32	[764]	CALL     	8 2 2
	33	[764]	SETTABLE 	7 -10 8	; "hint" -
	34	[765]	NEWTABLE 	8 0 2
	35	[767]	GETTABLE 	9 1 -14	; "username"
	36	[767]	TEST     	9 0 1
	37	[767]	JMP      	1	; to 39
	38	[767]	LOADK    	9 -9	; ""
	39	[767]	SETTABLE 	8 -8 9	; "text" -
	40	[768]	GETUPVAL 	9 2	; _
	41	[768]	LOADK    	10 -15	; "Username (optional)"
	42	[768]	CALL     	9 2 2
	43	[768]	SETTABLE 	8 -10 9	; "hint" -
	44	[769]	NEWTABLE 	9 0 3
	45	[771]	GETTABLE 	10 1 -16	; "password"
	46	[771]	TEST     	10 0 1
	47	[771]	JMP      	1	; to 49
	48	[771]	LOADK    	10 -9	; ""
	49	[771]	SETTABLE 	9 -8 10	; "text" -
	50	[772]	GETUPVAL 	10 2	; _
	51	[772]	LOADK    	11 -17	; "Password (optional)"
	52	[772]	CALL     	10 2 2
	53	[772]	SETTABLE 	9 -10 10	; "hint" -
	54	[773]	SETTABLE 	9 -18 -16	; "text_type" "password"
	55	[775]	SETLIST  	5 4 1	; 1
	56	[775]	SETTABLE 	4 -7 5	; "fields" -
	57	[776]	NEWTABLE 	5 1 0
	58	[776]	NEWTABLE 	6 2 0
	59	[777]	NEWTABLE 	7 0 2
	60	[779]	GETUPVAL 	8 2	; _
	61	[779]	LOADK    	9 -20	; "Cancel"
	62	[779]	CALL     	8 2 2
	63	[779]	SETTABLE 	7 -8 8	; "text" -
	64	[783]	CLOSURE  	8 0	; 0x7fefd0413890
	65	[783]	MOVE     	0 0
	66	[783]	GETUPVAL 	0 3	; UIManager
	67	[783]	SETTABLE 	7 -21 8	; "callback" -
	68	[784]	NEWTABLE 	8 0 2
	69	[786]	GETUPVAL 	9 2	; _
	70	[786]	LOADK    	10 -22	; "Apply"
	71	[786]	CALL     	9 2 2
	72	[786]	SETTABLE 	8 -8 9	; "text" -
	73	[791]	CLOSURE  	9 1	; 0x7fefd0413910
	74	[791]	MOVE     	0 0
	75	[791]	GETUPVAL 	0 3	; UIManager
	76	[791]	MOVE     	0 1
	77	[791]	GETUPVAL 	0 1	; MultiInputDialog
	78	[791]	SETTABLE 	8 -21 9	; "callback" -
	79	[793]	SETLIST  	6 2 1	; 1
	80	[794]	SETLIST  	5 1 1	; 1
	81	[794]	SETTABLE 	4 -19 5	; "buttons" -
	82	[795]	GETUPVAL 	5 4	; Screen
	83	[795]	SELF     	5 5 -24	; "getWidth"
	84	[795]	CALL     	5 2 2
	85	[795]	MUL      	5 5 -25	; - 0.95
	86	[795]	SETTABLE 	4 -23 5	; "width" -
	87	[796]	GETUPVAL 	5 4	; Screen
	88	[796]	SELF     	5 5 -27	; "getHeight"
	89	[796]	CALL     	5 2 2
	90	[796]	MUL      	5 5 -28	; - 0.2
	91	[796]	SETTABLE 	4 -26 5	; "height" -
	92	[755]	CALL     	2 3 2
	93	[797]	SETTABLE 	0 -3 2	; "edit_server_dialog" -
	94	[798]	GETUPVAL 	2 3	; UIManager
	95	[798]	SELF     	2 2 -29	; "show"
	96	[798]	GETTABLE 	4 0 -3	; "edit_server_dialog"
	97	[798]	CALL     	2 3 1
	98	[799]	GETTABLE 	2 0 -3	; "edit_server_dialog"
	99	[799]	SELF     	2 2 -30	; "onShowKeyboard"
	100	[799]	CALL     	2 2 1
	101	[800]	RETURN   	0 1

function <./frontend/ui/widget/opdsbrowser.lua:780,783> (10 instructions, 40 bytes at 0x7fefd0413890)
0 params, 3 slots, 2 upvalues, 0 locals, 3 constants, 0 functions
	1	[781]	GETUPVAL 	0 0	; self
	2	[781]	GETTABLE 	0 0 -1	; "edit_server_dialog"
	3	[781]	SELF     	0 0 -2	; "onClose"
	4	[781]	CALL     	0 2 1
	5	[782]	GETUPVAL 	0 1	; UIManager
	6	[782]	SELF     	0 0 -3	; "close"
	7	[782]	GETUPVAL 	2 0	; self
	8	[782]	GETTABLE 	2 2 -1	; "edit_server_dialog"
	9	[782]	CALL     	0 3 1
	10	[783]	RETURN   	0 1

function <./frontend/ui/widget/opdsbrowser.lua:787,791> (17 instructions, 68 bytes at 0x7fefd0413910)
0 params, 5 slots, 4 upvalues, 0 locals, 5 constants, 0 functions
	1	[788]	GETUPVAL 	0 0	; self
	2	[788]	GETTABLE 	0 0 -1	; "edit_server_dialog"
	3	[788]	SELF     	0 0 -2	; "onClose"
	4	[788]	CALL     	0 2 1
	5	[789]	GETUPVAL 	0 1	; UIManager
	6	[789]	SELF     	0 0 -3	; "close"
	7	[789]	GETUPVAL 	2 0	; self
	8	[789]	GETTABLE 	2 2 -1	; "edit_server_dialog"
	9	[789]	CALL     	0 3 1
	10	[790]	GETUPVAL 	0 0	; self
	11	[790]	SELF     	0 0 -4	; "editServerFromInput"
	12	[790]	GETUPVAL 	2 2	; item
	13	[790]	GETUPVAL 	3 3	; MultiInputDialog
	14	[790]	SELF     	3 3 -5	; "getFields"
	15	[790]	CALL     	3 2 0
	16	[790]	CALL     	0 0 1
	17	[791]	RETURN   	0 1

function <./frontend/ui/widget/opdsbrowser.lua:802,812> (39 instructions, 156 bytes at 0x7fefd0413ad0)
2 params, 11 slots, 1 upvalue, 8 locals, 13 constants, 0 functions
	1	[803]	GETUPVAL 	2 0	; logger
	2	[803]	GETTABLE 	2 2 -1	; "info"
	3	[803]	LOADK    	3 -2	; "delete"
	4	[803]	MOVE     	4 1
	5	[803]	CALL     	2 3 1
	6	[804]	NEWTABLE 	2 0 0
	7	[805]	GETGLOBAL	3 -3	; ipairs
	8	[805]	GETGLOBAL	4 -4	; G_reader_settings
	9	[805]	SELF     	4 4 -5	; "readSetting"
	10	[805]	LOADK    	6 -6	; "opds_servers"
	11	[805]	CALL     	4 3 2
	12	[805]	TEST     	4 0 1
	13	[805]	JMP      	1	; to 15
	14	[805]	NEWTABLE 	4 0 0
	15	[805]	CALL     	3 2 4
	16	[805]	JMP      	13	; to 30
	17	[806]	GETTABLE 	8 7 -7	; "title"
	18	[806]	GETTABLE 	9 1 -8	; "text"
	19	[806]	EQ       	0 8 9
	20	[806]	JMP      	4	; to 25
	21	[806]	GETTABLE 	8 7 -9	; "url"
	22	[806]	GETTABLE 	9 1 -9	; "url"
	23	[806]	EQ       	1 8 9
	24	[806]	JMP      	5	; to 30
	25	[807]	GETGLOBAL	8 -10	; table
	26	[807]	GETTABLE 	8 8 -11	; "insert"
	27	[807]	MOVE     	9 2
	28	[807]	MOVE     	10 7
	29	[807]	CALL     	8 3 1
	30	[805]	TFORLOOP 	3 2
	31	[808]	JMP      	-15	; to 17
	32	[810]	GETGLOBAL	3 -4	; G_reader_settings
	33	[810]	SELF     	3 3 -12	; "saveSetting"
	34	[810]	LOADK    	5 -6	; "opds_servers"
	35	[810]	MOVE     	6 2
	36	[810]	CALL     	3 4 1
	37	[811]	SELF     	3 0 -13	; "init"
	38	[811]	CALL     	3 2 1
	39	[812]	RETURN   	0 1

function <./frontend/ui/widget/opdsbrowser.lua:814,845> (47 instructions, 188 bytes at 0x7fefd0413b50)
2 params, 11 slots, 3 upvalues, 2 locals, 11 constants, 2 functions
	1	[815]	GETTABLE 	2 1 -1	; "deletable"
	2	[815]	TEST     	2 0 1
	3	[815]	JMP      	3	; to 7
	4	[815]	GETTABLE 	2 1 -2	; "editable"
	5	[815]	TEST     	2 0 0
	6	[815]	JMP      	40	; to 47
	7	[816]	GETUPVAL 	2 0	; ButtonDialog
	8	[816]	SELF     	2 2 -4	; "new"
	9	[816]	NEWTABLE 	4 0 1
	10	[817]	NEWTABLE 	5 1 0
	11	[817]	NEWTABLE 	6 2 0
	12	[818]	NEWTABLE 	7 0 3
	13	[820]	GETUPVAL 	8 1	; _
	14	[820]	LOADK    	9 -7	; "Edit"
	15	[820]	CALL     	8 2 2
	16	[820]	SETTABLE 	7 -6 8	; "text" -
	17	[821]	GETTABLE 	8 1 -2	; "editable"
	18	[821]	SETTABLE 	7 -8 8	; "enabled" -
	19	[829]	CLOSURE  	8 0	; 0x7fefd0414bf0
	20	[829]	GETUPVAL 	0 2	; UIManager
	21	[829]	MOVE     	0 0
	22	[829]	MOVE     	0 1
	23	[829]	SETTABLE 	7 -9 8	; "callback" -
	24	[830]	NEWTABLE 	8 0 3
	25	[832]	GETUPVAL 	9 1	; _
	26	[832]	LOADK    	10 -10	; "Delete"
	27	[832]	CALL     	9 2 2
	28	[832]	SETTABLE 	8 -6 9	; "text" -
	29	[833]	GETTABLE 	9 1 -1	; "deletable"
	30	[833]	SETTABLE 	8 -8 9	; "enabled" -
	31	[837]	CLOSURE  	9 1	; 0x7fefd04147c0
	32	[837]	GETUPVAL 	0 2	; UIManager
	33	[837]	MOVE     	0 0
	34	[837]	MOVE     	0 1
	35	[837]	SETTABLE 	8 -9 9	; "callback" -
	36	[839]	SETLIST  	6 2 1	; 1
	37	[840]	SETLIST  	5 1 1	; 1
	38	[840]	SETTABLE 	4 -5 5	; "buttons" -
	39	[816]	CALL     	2 3 2
	40	[841]	SETTABLE 	0 -3 2	; "opds_server_dialog" -
	41	[842]	GETUPVAL 	2 2	; UIManager
	42	[842]	SELF     	2 2 -11	; "show"
	43	[842]	GETTABLE 	4 0 -3	; "opds_server_dialog"
	44	[842]	CALL     	2 3 1
	45	[843]	LOADBOOL 	2 1 0
	46	[843]	RETURN   	2 2
	47	[845]	RETURN   	0 1

function <./frontend/ui/widget/opdsbrowser.lua:822,829> (21 instructions, 84 bytes at 0x7fefd0414bf0)
0 params, 3 slots, 3 upvalues, 0 locals, 6 constants, 0 functions
	1	[823]	GETUPVAL 	0 0	; UIManager
	2	[823]	SELF     	0 0 -1	; "close"
	3	[823]	GETUPVAL 	2 1	; self
	4	[823]	GETTABLE 	2 2 -2	; "opds_server_dialog"
	5	[823]	CALL     	0 3 1
	6	[824]	GETUPVAL 	0 2	; item
	7	[824]	GETTABLE 	0 0 -3	; "text"
	8	[824]	GETUPVAL 	1 1	; self
	9	[824]	GETTABLE 	1 1 -4	; "calibre_name"
	10	[824]	EQ       	1 0 1
	11	[824]	JMP      	5	; to 17
	12	[825]	GETUPVAL 	0 1	; self
	13	[825]	SELF     	0 0 -5	; "editOPDSServer"
	14	[825]	GETUPVAL 	2 2	; item
	15	[825]	CALL     	0 3 1
	16	[825]	JMP      	4	; to 21
	17	[827]	GETUPVAL 	0 1	; self
	18	[827]	SELF     	0 0 -6	; "editCalibreServer"
	19	[827]	GETUPVAL 	2 2	; item
	20	[827]	CALL     	0 3 1
	21	[829]	RETURN   	0 1

function <./frontend/ui/widget/opdsbrowser.lua:834,837> (10 instructions, 40 bytes at 0x7fefd04147c0)
0 params, 3 slots, 3 upvalues, 0 locals, 3 constants, 0 functions
	1	[835]	GETUPVAL 	0 0	; UIManager
	2	[835]	SELF     	0 0 -1	; "close"
	3	[835]	GETUPVAL 	2 1	; self
	4	[835]	GETTABLE 	2 2 -2	; "opds_server_dialog"
	5	[835]	CALL     	0 3 1
	6	[836]	GETUPVAL 	0 1	; self
	7	[836]	SELF     	0 0 -3	; "deleteOPDSServer"
	8	[836]	GETUPVAL 	2 2	; item
	9	[836]	CALL     	0 3 1
	10	[837]	RETURN   	0 1

function <./frontend/ui/widget/opdsbrowser.lua:847,860> (25 instructions, 100 bytes at 0x7fefd0414cf0)
1 param, 7 slots, 0 upvalues, 2 locals, 9 constants, 0 functions
	1	[848]	GETTABLE 	1 0 -1	; "paths"
	2	[848]	LEN      	1 1
	3	[848]	LT       	0 -2 1	; 0 -
	4	[848]	JMP      	18	; to 23
	5	[849]	GETGLOBAL	1 -3	; table
	6	[849]	GETTABLE 	1 1 -4	; "remove"
	7	[849]	GETTABLE 	2 0 -1	; "paths"
	8	[849]	CALL     	1 2 1
	9	[850]	GETTABLE 	1 0 -1	; "paths"
	10	[850]	GETTABLE 	2 0 -1	; "paths"
	11	[850]	LEN      	2 2
	12	[850]	GETTABLE 	1 1 2
	13	[851]	TEST     	1 0 0
	14	[851]	JMP      	6	; to 21
	15	[853]	SELF     	2 0 -5	; "updateCatalog"
	16	[853]	GETTABLE 	4 1 -6	; "url"
	17	[853]	GETTABLE 	5 1 -7	; "username"
	18	[853]	GETTABLE 	6 1 -8	; "password"
	19	[853]	CALL     	2 5 1
	20	[853]	JMP      	2	; to 23
	21	[856]	SELF     	2 0 -9	; "init"
	22	[856]	CALL     	2 2 1
	23	[859]	LOADBOOL 	1 1 0
	24	[859]	RETURN   	1 2
	25	[860]	RETURN   	0 1

function <./frontend/ui/widget/opdsbrowser.lua:862,878> (27 instructions, 108 bytes at 0x7fefd0415830)
1 param, 8 slots, 0 upvalues, 3 locals, 7 constants, 0 functions
	1	[864]	GETTABLE 	1 0 -1	; "page_num"
	2	[866]	GETTABLE 	2 0 -1	; "page_num"
	3	[866]	EQ       	0 1 2
	4	[866]	JMP      	20	; to 25
	5	[867]	GETTABLE 	2 0 -2	; "item_table"
	6	[867]	GETTABLE 	2 2 -3	; "hrefs"
	7	[868]	TEST     	2 0 0
	8	[868]	JMP      	16	; to 25
	9	[868]	GETTABLE 	3 2 -4	; "next"
	10	[868]	TEST     	3 0 0
	11	[868]	JMP      	13	; to 25
	12	[869]	SELF     	3 0 -5	; "appendCatalog"
	13	[869]	GETTABLE 	5 2 -4	; "next"
	14	[869]	GETTABLE 	6 0 -2	; "item_table"
	15	[869]	GETTABLE 	6 6 -6	; "username"
	16	[869]	GETTABLE 	7 0 -2	; "item_table"
	17	[869]	GETTABLE 	7 7 -7	; "password"
	18	[869]	CALL     	3 5 2
	19	[869]	TEST     	3 0 1
	20	[869]	JMP      	-19	; to 2
	21	[870]	JMP      	3	; to 25
	22	[871]	JMP      	-21	; to 2
	23	[873]	JMP      	1	; to 25
	24	[874]	JMP      	-23	; to 2
	25	[877]	LOADBOOL 	2 1 0
	26	[877]	RETURN   	2 2
	27	[878]	RETURN   	0 1
