
main <./frontend/apps/opdscatalog/opdscatalog.lua:0,0> (76 instructions, 304 bytes at 0x7f95b5c068f0)
0+ params, 17 slots, 0 upvalues, 13 locals, 24 constants, 6 functions
	1	[1]	GETGLOBAL	0 -1	; require
	2	[1]	LOADK    	1 -2	; "ui/bidi"
	3	[1]	CALL     	0 2 2
	4	[2]	GETGLOBAL	1 -1	; require
	5	[2]	LOADK    	2 -3	; "ffi/blitbuffer"
	6	[2]	CALL     	1 2 2
	7	[3]	GETGLOBAL	2 -1	; require
	8	[3]	LOADK    	3 -4	; "ui/widget/confirmbox"
	9	[3]	CALL     	2 2 2
	10	[4]	GETGLOBAL	3 -1	; require
	11	[4]	LOADK    	4 -5	; "ui/widget/container/framecontainer"
	12	[4]	CALL     	3 2 2
	13	[5]	GETGLOBAL	4 -1	; require
	14	[5]	LOADK    	5 -6	; "ui/widget/container/inputcontainer"
	15	[5]	CALL     	4 2 2
	16	[6]	GETGLOBAL	5 -1	; require
	17	[6]	LOADK    	6 -7	; "ui/widget/opdsbrowser"
	18	[6]	CALL     	5 2 2
	19	[7]	GETGLOBAL	6 -1	; require
	20	[7]	LOADK    	7 -8	; "apps/reader/readerui"
	21	[7]	CALL     	6 2 2
	22	[8]	GETGLOBAL	7 -1	; require
	23	[8]	LOADK    	8 -9	; "ui/uimanager"
	24	[8]	CALL     	7 2 2
	25	[9]	GETGLOBAL	8 -1	; require
	26	[9]	LOADK    	9 -10	; "logger"
	27	[9]	CALL     	8 2 2
	28	[10]	GETGLOBAL	9 -1	; require
	29	[10]	LOADK    	10 -11	; "gettext"
	30	[10]	CALL     	9 2 2
	31	[11]	GETGLOBAL	10 -1	; require
	32	[11]	LOADK    	11 -12	; "device"
	33	[11]	CALL     	10 2 2
	34	[11]	GETTABLE 	10 10 -13	; "screen"
	35	[12]	GETGLOBAL	11 -1	; require
	36	[12]	LOADK    	12 -14	; "ffi/util"
	37	[12]	CALL     	11 2 2
	38	[12]	GETTABLE 	11 11 -15	; "template"
	39	[14]	SELF     	12 4 -16	; "extend"
	40	[14]	NEWTABLE 	14 0 2
	41	[15]	MOVE     	15 9
	42	[15]	LOADK    	16 -18	; "OPDS Catalog"
	43	[15]	CALL     	15 2 2
	44	[15]	SETTABLE 	14 -17 15	; "title" -
	45	[16]	CLOSURE  	15 0	; 0x7f95b5c07110
	46	[16]	SETTABLE 	14 -19 15	; "onExit" -
	47	[14]	CALL     	12 3 2
	48	[47]	CLOSURE  	13 1	; 0x7f95b5c06e30
	49	[47]	MOVE     	0 5
	50	[47]	MOVE     	0 7
	51	[47]	MOVE     	0 2
	52	[47]	MOVE     	0 11
	53	[47]	MOVE     	0 9
	54	[47]	MOVE     	0 0
	55	[47]	MOVE     	0 6
	56	[47]	MOVE     	0 3
	57	[47]	MOVE     	0 1
	58	[19]	SETTABLE 	12 -20 13	; "init" -
	59	[53]	CLOSURE  	13 2	; 0x7f95b5c08070
	60	[53]	MOVE     	0 7
	61	[49]	SETTABLE 	12 -21 13	; "onShow" -
	62	[59]	CLOSURE  	13 3	; 0x7f95b5c08840
	63	[59]	MOVE     	0 7
	64	[55]	SETTABLE 	12 -22 13	; "onCloseWidget" -
	65	[70]	CLOSURE  	13 4	; 0x7f95b5c08f10
	66	[70]	MOVE     	0 8
	67	[70]	MOVE     	0 7
	68	[70]	MOVE     	0 12
	69	[70]	MOVE     	0 10
	70	[61]	SETTABLE 	12 -23 13	; "showCatalog" -
	71	[79]	CLOSURE  	13 5	; 0x7f95b5c08b60
	72	[79]	MOVE     	0 8
	73	[79]	MOVE     	0 7
	74	[72]	SETTABLE 	12 -24 13	; "onClose" -
	75	[81]	RETURN   	12 2
	76	[81]	RETURN   	0 1

function <./frontend/apps/opdscatalog/opdscatalog.lua:16,16> (1 instruction, 4 bytes at 0x7f95b5c07110)
0 params, 2 slots, 0 upvalues, 0 locals, 0 constants, 0 functions
	1	[16]	RETURN   	0 1

function <./frontend/apps/opdscatalog/opdscatalog.lua:19,47> (35 instructions, 140 bytes at 0x7f95b5c06e30)
1 param, 6 slots, 9 upvalues, 2 locals, 16 constants, 2 functions
	1	[20]	GETUPVAL 	1 0	; OPDSBrowser
	2	[20]	SELF     	1 1 -1	; "new"
	3	[20]	NEWTABLE 	3 0 7
	4	[21]	GETTABLE 	4 0 -2	; "title"
	5	[21]	SETTABLE 	3 -2 4	; "title" -
	6	[22]	SETTABLE 	3 -3 0	; "show_parent" -
	7	[23]	SETTABLE 	3 -4 -5	; "is_popout" false
	8	[24]	SETTABLE 	3 -6 -7	; "is_borderless" true
	9	[25]	SETTABLE 	3 -8 -7	; "has_close_button" true
	10	[26]	CLOSURE  	4 0	; 0x7f95b5c075f0
	11	[26]	MOVE     	0 0
	12	[26]	SETTABLE 	3 -9 4	; "close_callback" -
	13	[38]	CLOSURE  	4 1	; 0x7f95b5c07750
	14	[38]	GETUPVAL 	0 1	; UIManager
	15	[38]	GETUPVAL 	0 2	; ConfirmBox
	16	[38]	GETUPVAL 	0 3	; T
	17	[38]	GETUPVAL 	0 4	; _
	18	[38]	GETUPVAL 	0 5	; BD
	19	[38]	MOVE     	0 0
	20	[38]	GETUPVAL 	0 6	; ReaderUI
	21	[38]	SETTABLE 	3 -10 4	; "file_downloaded_callback" -
	22	[20]	CALL     	1 3 2
	23	[41]	GETUPVAL 	2 7	; FrameContainer
	24	[41]	SELF     	2 2 -1	; "new"
	25	[41]	NEWTABLE 	4 1 3
	26	[42]	SETTABLE 	4 -12 -13	; "padding" 0
	27	[43]	SETTABLE 	4 -14 -13	; "bordersize" 0
	28	[44]	GETUPVAL 	5 8	; Blitbuffer
	29	[44]	GETTABLE 	5 5 -16	; "COLOR_WHITE"
	30	[44]	SETTABLE 	4 -15 5	; "background" -
	31	[46]	MOVE     	5 1
	32	[46]	SETLIST  	4 1 1	; 1
	33	[41]	CALL     	2 3 2
	34	[46]	SETTABLE 	0 -11 2	; 1 -
	35	[47]	RETURN   	0 1

function <./frontend/apps/opdscatalog/opdscatalog.lua:26,26> (5 instructions, 20 bytes at 0x7f95b5c075f0)
0 params, 2 slots, 1 upvalue, 0 locals, 1 constant, 0 functions
	1	[26]	GETUPVAL 	0 0	; self
	2	[26]	SELF     	0 0 -1	; "onClose"
	3	[26]	TAILCALL 	0 2 0
	4	[26]	RETURN   	0 0
	5	[26]	RETURN   	0 1

function <./frontend/apps/opdscatalog/opdscatalog.lua:27,38> (31 instructions, 124 bytes at 0x7f95b5c07750)
1 param, 10 slots, 7 upvalues, 1 local, 10 constants, 1 function
	1	[28]	GETUPVAL 	1 0	; UIManager
	2	[28]	SELF     	1 1 -1	; "show"
	3	[28]	GETUPVAL 	3 1	; ConfirmBox
	4	[28]	SELF     	3 3 -2	; "new"
	5	[28]	NEWTABLE 	5 0 4
	6	[29]	GETUPVAL 	6 2	; T
	7	[29]	GETUPVAL 	7 3	; _
	8	[29]	LOADK    	8 -4	; "File saved to:\n%1\nWould you like to read the downloaded book now?"
	9	[29]	CALL     	7 2 2
	10	[30]	GETUPVAL 	8 4	; BD
	11	[30]	GETTABLE 	8 8 -5	; "filepath"
	12	[30]	MOVE     	9 0
	13	[30]	CALL     	8 2 0
	14	[29]	CALL     	6 0 2
	15	[30]	SETTABLE 	5 -3 6	; "text" -
	16	[31]	GETUPVAL 	6 3	; _
	17	[31]	LOADK    	7 -7	; "Read now"
	18	[31]	CALL     	6 2 2
	19	[31]	SETTABLE 	5 -6 6	; "ok_text" -
	20	[32]	GETUPVAL 	6 3	; _
	21	[32]	LOADK    	7 -9	; "Read later"
	22	[32]	CALL     	6 2 2
	23	[32]	SETTABLE 	5 -8 6	; "cancel_text" -
	24	[36]	CLOSURE  	6 0	; 0x7f95b5c07d60
	25	[36]	GETUPVAL 	0 5	; self
	26	[36]	GETUPVAL 	0 6	; ReaderUI
	27	[36]	MOVE     	0 0
	28	[36]	SETTABLE 	5 -10 6	; "ok_callback" -
	29	[28]	CALL     	3 3 0
	30	[28]	CALL     	1 0 1
	31	[38]	RETURN   	0 1

function <./frontend/apps/opdscatalog/opdscatalog.lua:33,36> (8 instructions, 32 bytes at 0x7f95b5c07d60)
0 params, 3 slots, 3 upvalues, 0 locals, 2 constants, 0 functions
	1	[34]	GETUPVAL 	0 0	; self
	2	[34]	SELF     	0 0 -1	; "onClose"
	3	[34]	CALL     	0 2 1
	4	[35]	GETUPVAL 	0 1	; ReaderUI
	5	[35]	SELF     	0 0 -2	; "showReader"
	6	[35]	GETUPVAL 	2 2	; downloaded_file
	7	[35]	CALL     	0 3 1
	8	[36]	RETURN   	0 1

function <./frontend/apps/opdscatalog/opdscatalog.lua:49,53> (7 instructions, 28 bytes at 0x7f95b5c08070)
1 param, 5 slots, 1 upvalue, 1 local, 1 constant, 1 function
	1	[50]	GETUPVAL 	1 0	; UIManager
	2	[50]	SELF     	1 1 -1	; "setDirty"
	3	[50]	MOVE     	3 0
	4	[52]	CLOSURE  	4 0	; 0x7f95b5c08740
	5	[52]	MOVE     	0 0
	6	[50]	CALL     	1 4 1
	7	[53]	RETURN   	0 1

function <./frontend/apps/opdscatalog/opdscatalog.lua:50,52> (6 instructions, 24 bytes at 0x7f95b5c08740)
0 params, 2 slots, 1 upvalue, 0 locals, 3 constants, 0 functions
	1	[51]	LOADK    	0 -1	; "ui"
	2	[51]	GETUPVAL 	1 0	; self
	3	[51]	GETTABLE 	1 1 -2	; 1
	4	[51]	GETTABLE 	1 1 -3	; "dimen"
	5	[51]	RETURN   	0 3
	6	[52]	RETURN   	0 1

function <./frontend/apps/opdscatalog/opdscatalog.lua:55,59> (7 instructions, 28 bytes at 0x7f95b5c08840)
1 param, 5 slots, 1 upvalue, 1 local, 1 constant, 1 function
	1	[56]	GETUPVAL 	1 0	; UIManager
	2	[56]	SELF     	1 1 -1	; "setDirty"
	3	[56]	LOADNIL  	3 3
	4	[58]	CLOSURE  	4 0	; 0x7f95b5c08e30
	5	[58]	MOVE     	0 0
	6	[56]	CALL     	1 4 1
	7	[59]	RETURN   	0 1

function <./frontend/apps/opdscatalog/opdscatalog.lua:56,58> (6 instructions, 24 bytes at 0x7f95b5c08e30)
0 params, 2 slots, 1 upvalue, 0 locals, 3 constants, 0 functions
	1	[57]	LOADK    	0 -1	; "partial"
	2	[57]	GETUPVAL 	1 0	; self
	3	[57]	GETTABLE 	1 1 -2	; 1
	4	[57]	GETTABLE 	1 1 -3	; "dimen"
	5	[57]	RETURN   	0 3
	6	[58]	RETURN   	0 1

function <./frontend/apps/opdscatalog/opdscatalog.lua:61,70> (19 instructions, 76 bytes at 0x7f95b5c08f10)
1 param, 8 slots, 4 upvalues, 1 local, 9 constants, 1 function
	1	[62]	GETUPVAL 	1 0	; logger
	2	[62]	GETTABLE 	1 1 -1	; "dbg"
	3	[62]	LOADK    	2 -2	; "show OPDS catalog"
	4	[62]	CALL     	1 2 1
	5	[63]	GETUPVAL 	1 1	; UIManager
	6	[63]	SELF     	1 1 -3	; "show"
	7	[63]	GETUPVAL 	3 2	; OPDSCatalog
	8	[63]	SELF     	3 3 -4	; "new"
	9	[63]	NEWTABLE 	5 0 3
	10	[64]	GETUPVAL 	6 3	; Screen
	11	[64]	SELF     	6 6 -6	; "getSize"
	12	[64]	CALL     	6 2 2
	13	[64]	SETTABLE 	5 -5 6	; "dimen" -
	14	[65]	SETTABLE 	5 -7 -8	; "covers_fullscreen" true
	15	[68]	CLOSURE  	6 0	; 0x7f95b5c067c0
	16	[68]	SETTABLE 	5 -9 6	; "onExit" -
	17	[63]	CALL     	3 3 0
	18	[63]	CALL     	1 0 1
	19	[70]	RETURN   	0 1

function <./frontend/apps/opdscatalog/opdscatalog.lua:66,68> (1 instruction, 4 bytes at 0x7f95b5c067c0)
0 params, 2 slots, 0 upvalues, 0 locals, 0 constants, 0 functions
	1	[68]	RETURN   	0 1

function <./frontend/apps/opdscatalog/opdscatalog.lua:72,79> (16 instructions, 64 bytes at 0x7f95b5c08b60)
1 param, 4 slots, 2 upvalues, 1 local, 4 constants, 0 functions
	1	[73]	GETUPVAL 	1 0	; logger
	2	[73]	GETTABLE 	1 1 -1	; "dbg"
	3	[73]	LOADK    	2 -2	; "close OPDS catalog"
	4	[73]	CALL     	1 2 1
	5	[74]	GETUPVAL 	1 1	; UIManager
	6	[74]	SELF     	1 1 -3	; "close"
	7	[74]	MOVE     	3 0
	8	[74]	CALL     	1 3 1
	9	[75]	GETTABLE 	1 0 -4	; "onExit"
	10	[75]	TEST     	1 0 0
	11	[75]	JMP      	2	; to 14
	12	[76]	SELF     	1 0 -4	; "onExit"
	13	[76]	CALL     	1 2 1
	14	[78]	LOADBOOL 	1 1 0
	15	[78]	RETURN   	1 2
	16	[79]	RETURN   	0 1
