
main <./frontend/ui/data/optionsutil.lua:0,0> (35 instructions, 140 bytes at 0x7ff9c6c068d0)
0+ params, 8 slots, 0 upvalues, 7 locals, 11 constants, 3 functions
	1	[5]	GETGLOBAL	0 -1	; require
	2	[5]	LOADK    	1 -2	; "device"
	3	[5]	CALL     	0 2 2
	4	[6]	GETGLOBAL	1 -1	; require
	5	[6]	LOADK    	2 -3	; "ui/widget/infomessage"
	6	[6]	CALL     	1 2 2
	7	[7]	GETGLOBAL	2 -1	; require
	8	[7]	LOADK    	3 -4	; "ui/uimanager"
	9	[7]	CALL     	2 2 2
	10	[8]	GETGLOBAL	3 -1	; require
	11	[8]	LOADK    	4 -5	; "gettext"
	12	[8]	CALL     	3 2 2
	13	[9]	GETTABLE 	4 0 -6	; "screen"
	14	[10]	GETGLOBAL	5 -1	; require
	15	[10]	LOADK    	6 -7	; "ffi/util"
	16	[10]	CALL     	5 2 2
	17	[10]	GETTABLE 	5 5 -8	; "template"
	18	[12]	NEWTABLE 	6 0 0
	19	[16]	CLOSURE  	7 0	; 0x7ff9c6c06bc0
	20	[14]	SETTABLE 	6 -9 7	; "enableIfEquals" -
	21	[119]	CLOSURE  	7 1	; 0x7ff9c6c07120
	22	[119]	MOVE     	0 4
	23	[119]	MOVE     	0 3
	24	[119]	MOVE     	0 5
	25	[119]	MOVE     	0 2
	26	[119]	MOVE     	0 1
	27	[18]	SETTABLE 	6 -10 7	; "showValues" -
	28	[146]	CLOSURE  	7 2	; 0x7ff9c6c071c0
	29	[146]	MOVE     	0 2
	30	[146]	MOVE     	0 1
	31	[146]	MOVE     	0 5
	32	[146]	MOVE     	0 3
	33	[121]	SETTABLE 	6 -11 7	; "showValuesHMargins" -
	34	[148]	RETURN   	6 2
	35	[148]	RETURN   	0 1

function <./frontend/ui/data/optionsutil.lua:14,16> (7 instructions, 28 bytes at 0x7ff9c6c06bc0)
3 params, 4 slots, 0 upvalues, 3 locals, 0 constants, 0 functions
	1	[15]	GETTABLE 	3 0 1
	2	[15]	EQ       	1 3 2
	3	[15]	JMP      	1	; to 5
	4	[15]	LOADBOOL 	3 0 1
	5	[15]	LOADBOOL 	3 1 0
	6	[15]	RETURN   	3 2
	7	[16]	RETURN   	0 1

function <./frontend/ui/data/optionsutil.lua:18,119> (279 instructions, 1116 bytes at 0x7ff9c6c07120)
3 params, 17 slots, 5 upvalues, 33 locals, 32 constants, 0 functions
	1	[19]	GETGLOBAL	3 -1	; G_reader_settings
	2	[19]	SELF     	3 3 -2	; "readSetting"
	3	[19]	MOVE     	5 2
	4	[19]	LOADK    	6 -3	; "_"
	5	[19]	GETTABLE 	7 1 -4	; "name"
	6	[19]	CONCAT   	5 5 7
	7	[19]	CALL     	3 3 2
	8	[20]	GETTABLE 	4 1 -4	; "name"
	9	[20]	GETTABLE 	4 0 4
	10	[21]	LOADNIL  	5 6
	11	[22]	GETTABLE 	7 1 -4	; "name"
	12	[22]	EQ       	0 7 -5	; - "screen_mode"
	13	[22]	JMP      	4	; to 18
	14	[23]	GETUPVAL 	7 0	; Screen
	15	[23]	SELF     	7 7 -6	; "getScreenMode"
	16	[23]	CALL     	7 2 2
	17	[23]	MOVE     	4 7
	18	[25]	GETTABLE 	7 1 -7	; "toggle"
	19	[25]	TEST     	7 0 0
	20	[25]	JMP      	91	; to 112
	21	[25]	GETTABLE 	7 1 -8	; "values"
	22	[25]	TEST     	7 0 0
	23	[25]	JMP      	88	; to 112
	24	[28]	NEWTABLE 	7 0 0
	25	[29]	LOADK    	8 -9	; 1
	26	[29]	GETTABLE 	9 1 -8	; "values"
	27	[29]	LEN      	9 9
	28	[29]	LOADK    	10 -9	; 1
	29	[29]	FORPREP  	8 16	; to 46
	30	[30]	GETTABLE 	12 1 -8	; "values"
	31	[30]	GETTABLE 	12 12 11
	32	[32]	GETGLOBAL	13 -10	; type
	33	[32]	MOVE     	14 12
	34	[32]	CALL     	13 2 2
	35	[32]	EQ       	0 13 -11	; - "table"
	36	[32]	JMP      	6	; to 43
	37	[32]	GETGLOBAL	13 -11	; table
	38	[32]	GETTABLE 	13 13 -12	; "concat"
	39	[32]	MOVE     	14 12
	40	[32]	LOADK    	15 -13	; ","
	41	[32]	CALL     	13 3 2
	42	[32]	MOVE     	12 13
	43	[33]	GETTABLE 	13 1 -7	; "toggle"
	44	[33]	GETTABLE 	13 13 11
	45	[33]	SETTABLE 	7 12 13
	46	[29]	FORLOOP  	8 -17	; to 30
	47	[35]	MOVE     	6 4
	48	[36]	GETGLOBAL	8 -10	; type
	49	[36]	MOVE     	9 4
	50	[36]	CALL     	8 2 2
	51	[36]	EQ       	0 8 -11	; - "table"
	52	[36]	JMP      	6	; to 59
	53	[36]	GETGLOBAL	8 -11	; table
	54	[36]	GETTABLE 	8 8 -12	; "concat"
	55	[36]	MOVE     	9 4
	56	[36]	LOADK    	10 -13	; ","
	57	[36]	CALL     	8 3 2
	58	[36]	MOVE     	4 8
	59	[37]	GETTABLE 	4 7 4
	60	[38]	TEST     	4 0 1
	61	[38]	JMP      	9	; to 71
	62	[39]	GETTABLE 	8 1 -14	; "name_text_true_values"
	63	[39]	TEST     	8 0 0
	64	[39]	JMP      	5	; to 70
	65	[39]	GETUPVAL 	8 1	; _
	66	[39]	LOADK    	9 -15	; "custom"
	67	[39]	CALL     	8 2 2
	68	[39]	TESTSET  	4 8 1
	69	[39]	JMP      	1	; to 71
	70	[39]	MOVE     	4 6
	71	[41]	GETTABLE 	8 1 -16	; "show_true_value_func"
	72	[41]	TEST     	8 0 0
	73	[41]	JMP      	4	; to 78
	74	[42]	GETTABLE 	8 1 -16	; "show_true_value_func"
	75	[42]	MOVE     	9 6
	76	[42]	CALL     	8 2 2
	77	[42]	MOVE     	6 8
	78	[44]	TEST     	3 0 0
	79	[44]	JMP      	129	; to 209
	80	[45]	MOVE     	5 3
	81	[46]	GETGLOBAL	8 -10	; type
	82	[46]	MOVE     	9 3
	83	[46]	CALL     	8 2 2
	84	[46]	EQ       	0 8 -11	; - "table"
	85	[46]	JMP      	6	; to 92
	86	[46]	GETGLOBAL	8 -11	; table
	87	[46]	GETTABLE 	8 8 -12	; "concat"
	88	[46]	MOVE     	9 3
	89	[46]	LOADK    	10 -13	; ","
	90	[46]	CALL     	8 3 2
	91	[46]	MOVE     	3 8
	92	[47]	GETTABLE 	3 7 3
	93	[48]	TEST     	3 0 1
	94	[48]	JMP      	9	; to 104
	95	[49]	GETTABLE 	8 1 -14	; "name_text_true_values"
	96	[49]	TEST     	8 0 0
	97	[49]	JMP      	5	; to 103
	98	[49]	GETUPVAL 	8 1	; _
	99	[49]	LOADK    	9 -15	; "custom"
	100	[49]	CALL     	8 2 2
	101	[49]	TESTSET  	3 8 1
	102	[49]	JMP      	1	; to 104
	103	[49]	MOVE     	3 5
	104	[51]	GETTABLE 	8 1 -16	; "show_true_value_func"
	105	[51]	TEST     	8 0 0
	106	[51]	JMP      	102	; to 209
	107	[52]	GETTABLE 	8 1 -16	; "show_true_value_func"
	108	[52]	MOVE     	9 5
	109	[52]	CALL     	8 2 2
	110	[52]	MOVE     	5 8
	111	[54]	JMP      	97	; to 209
	112	[55]	GETTABLE 	7 1 -17	; "labels"
	113	[55]	TEST     	7 0 0
	114	[55]	JMP      	78	; to 193
	115	[55]	GETTABLE 	7 1 -8	; "values"
	116	[55]	TEST     	7 0 0
	117	[55]	JMP      	75	; to 193
	118	[56]	GETTABLE 	7 1 -18	; "more_options_param"
	119	[56]	TEST     	7 0 0
	120	[56]	JMP      	43	; to 164
	121	[56]	GETTABLE 	7 1 -18	; "more_options_param"
	122	[56]	GETTABLE 	7 7 -19	; "value_table"
	123	[56]	TEST     	7 0 0
	124	[56]	JMP      	39	; to 164
	125	[57]	GETTABLE 	7 1 -18	; "more_options_param"
	126	[57]	GETTABLE 	7 7 -20	; "args_table"
	127	[57]	TEST     	7 0 0
	128	[57]	JMP      	11	; to 140
	129	[58]	GETGLOBAL	7 -21	; pairs
	130	[58]	GETTABLE 	8 1 -18	; "more_options_param"
	131	[58]	GETTABLE 	8 8 -20	; "args_table"
	132	[58]	CALL     	7 2 4
	133	[58]	JMP      	4	; to 138
	134	[59]	EQ       	0 11 4
	135	[59]	JMP      	2	; to 138
	136	[60]	MOVE     	4 10
	137	[61]	JMP      	2	; to 140
	138	[58]	TFORLOOP 	7 2
	139	[62]	JMP      	-6	; to 134
	140	[65]	GETTABLE 	7 1 -18	; "more_options_param"
	141	[65]	GETTABLE 	7 7 -19	; "value_table"
	142	[65]	GETTABLE 	4 7 4
	143	[66]	TEST     	3 0 0
	144	[66]	JMP      	64	; to 209
	145	[67]	GETTABLE 	7 1 -18	; "more_options_param"
	146	[67]	GETTABLE 	7 7 -20	; "args_table"
	147	[67]	TEST     	7 0 0
	148	[67]	JMP      	11	; to 160
	149	[68]	GETGLOBAL	7 -21	; pairs
	150	[68]	GETTABLE 	8 1 -18	; "more_options_param"
	151	[68]	GETTABLE 	8 8 -20	; "args_table"
	152	[68]	CALL     	7 2 4
	153	[68]	JMP      	4	; to 158
	154	[69]	EQ       	0 11 3
	155	[69]	JMP      	2	; to 158
	156	[70]	MOVE     	3 10
	157	[71]	JMP      	2	; to 160
	158	[68]	TFORLOOP 	7 2
	159	[72]	JMP      	-6	; to 154
	160	[75]	GETTABLE 	7 1 -18	; "more_options_param"
	161	[75]	GETTABLE 	7 7 -19	; "value_table"
	162	[75]	GETTABLE 	3 7 3
	163	[76]	JMP      	45	; to 209
	164	[78]	TEST     	3 0 0
	165	[78]	JMP      	13	; to 179
	166	[79]	LOADK    	7 -9	; 1
	167	[79]	GETTABLE 	8 1 -17	; "labels"
	168	[79]	LEN      	8 8
	169	[79]	LOADK    	9 -9	; 1
	170	[79]	FORPREP  	7 7	; to 178
	171	[80]	GETTABLE 	11 1 -8	; "values"
	172	[80]	GETTABLE 	11 11 10
	173	[80]	EQ       	0 3 11
	174	[80]	JMP      	3	; to 178
	175	[81]	GETTABLE 	11 1 -17	; "labels"
	176	[81]	GETTABLE 	3 11 10
	177	[82]	JMP      	1	; to 179
	178	[79]	FORLOOP  	7 -8	; to 171
	179	[86]	LOADK    	7 -9	; 1
	180	[86]	GETTABLE 	8 1 -17	; "labels"
	181	[86]	LEN      	8 8
	182	[86]	LOADK    	9 -9	; 1
	183	[86]	FORPREP  	7 7	; to 191
	184	[87]	GETTABLE 	11 1 -8	; "values"
	185	[87]	GETTABLE 	11 11 10
	186	[87]	EQ       	0 4 11
	187	[87]	JMP      	3	; to 191
	188	[88]	GETTABLE 	11 1 -17	; "labels"
	189	[88]	GETTABLE 	4 11 10
	190	[89]	JMP      	18	; to 209
	191	[86]	FORLOOP  	7 -8	; to 184
	192	[92]	JMP      	16	; to 209
	193	[93]	GETTABLE 	7 1 -16	; "show_true_value_func"
	194	[93]	TEST     	7 0 0
	195	[93]	JMP      	13	; to 209
	196	[93]	GETTABLE 	7 1 -8	; "values"
	197	[93]	TEST     	7 0 0
	198	[93]	JMP      	10	; to 209
	199	[94]	GETTABLE 	7 1 -16	; "show_true_value_func"
	200	[94]	MOVE     	8 4
	201	[94]	CALL     	7 2 2
	202	[94]	MOVE     	4 7
	203	[95]	TEST     	3 0 0
	204	[95]	JMP      	4	; to 209
	205	[96]	GETTABLE 	7 1 -16	; "show_true_value_func"
	206	[96]	MOVE     	8 3
	207	[96]	CALL     	7 2 2
	208	[96]	MOVE     	3 7
	209	[99]	TEST     	3 0 1
	210	[99]	JMP      	4	; to 215
	211	[100]	GETUPVAL 	7 1	; _
	212	[100]	LOADK    	8 -22	; "not set"
	213	[100]	CALL     	7 2 2
	214	[100]	MOVE     	3 7
	215	[102]	LOADK    	7 -23	; ""
	216	[103]	GETTABLE 	8 1 -24	; "help_text"
	217	[103]	TEST     	8 0 0
	218	[103]	JMP      	5	; to 224
	219	[104]	GETUPVAL 	8 2	; T
	220	[104]	LOADK    	9 -25	; "\n%1\n"
	221	[104]	GETTABLE 	10 1 -24	; "help_text"
	222	[104]	CALL     	8 3 2
	223	[104]	MOVE     	7 8
	224	[106]	LOADNIL  	8 8
	225	[107]	GETTABLE 	9 1 -14	; "name_text_true_values"
	226	[107]	TEST     	9 0 0
	227	[107]	JMP      	33	; to 261
	228	[107]	GETTABLE 	9 1 -7	; "toggle"
	229	[107]	TEST     	9 0 0
	230	[107]	JMP      	30	; to 261
	231	[107]	GETTABLE 	9 1 -8	; "values"
	232	[107]	TEST     	9 0 0
	233	[107]	JMP      	27	; to 261
	234	[108]	TEST     	5 0 0
	235	[108]	JMP      	13	; to 249
	236	[109]	GETUPVAL 	9 2	; T
	237	[109]	GETUPVAL 	10 1	; _
	238	[109]	LOADK    	11 -26	; "%1\n%2\nCurrent value: %3 (%4)\nDefault value: %5 (%6)"
	239	[109]	CALL     	10 2 2
	240	[109]	GETTABLE 	11 1 -27	; "name_text"
	241	[109]	MOVE     	12 7
	242	[110]	MOVE     	13 4
	243	[110]	MOVE     	14 6
	244	[110]	MOVE     	15 3
	245	[110]	MOVE     	16 5
	246	[109]	CALL     	9 8 2
	247	[110]	MOVE     	8 9
	248	[110]	JMP      	22	; to 271
	249	[112]	GETUPVAL 	9 2	; T
	250	[112]	GETUPVAL 	10 1	; _
	251	[112]	LOADK    	11 -28	; "%1\n%2\nCurrent value: %3 (%4)\nDefault value: %5"
	252	[112]	CALL     	10 2 2
	253	[112]	GETTABLE 	11 1 -27	; "name_text"
	254	[112]	MOVE     	12 7
	255	[113]	MOVE     	13 4
	256	[113]	MOVE     	14 6
	257	[113]	MOVE     	15 3
	258	[112]	CALL     	9 7 2
	259	[113]	MOVE     	8 9
	260	[114]	JMP      	10	; to 271
	261	[116]	GETUPVAL 	9 2	; T
	262	[116]	GETUPVAL 	10 1	; _
	263	[116]	LOADK    	11 -29	; "%1\n%2\nCurrent value: %3\nDefault value: %4"
	264	[116]	CALL     	10 2 2
	265	[116]	GETTABLE 	11 1 -27	; "name_text"
	266	[116]	MOVE     	12 7
	267	[116]	MOVE     	13 4
	268	[116]	MOVE     	14 3
	269	[116]	CALL     	9 6 2
	270	[116]	MOVE     	8 9
	271	[118]	GETUPVAL 	9 3	; UIManager
	272	[118]	SELF     	9 9 -30	; "show"
	273	[118]	GETUPVAL 	11 4	; InfoMessage
	274	[118]	SELF     	11 11 -31	; "new"
	275	[118]	NEWTABLE 	13 0 1
	276	[118]	SETTABLE 	13 -32 8	; "text" -
	277	[118]	CALL     	11 3 0
	278	[118]	CALL     	9 0 1
	279	[119]	RETURN   	0 1

function <./frontend/ui/data/optionsutil.lua:121,146> (44 instructions, 176 bytes at 0x7ff9c6c071c0)
2 params, 15 slots, 4 upvalues, 4 locals, 11 constants, 0 functions
	1	[122]	GETGLOBAL	2 -1	; G_reader_settings
	2	[122]	SELF     	2 2 -2	; "readSetting"
	3	[122]	LOADK    	4 -3	; "copt_"
	4	[122]	GETTABLE 	5 1 -4	; "name"
	5	[122]	CONCAT   	4 4 5
	6	[122]	CALL     	2 3 2
	7	[123]	GETTABLE 	3 1 -4	; "name"
	8	[123]	GETTABLE 	3 0 3
	9	[124]	TEST     	2 0 1
	10	[124]	JMP      	16	; to 27
	11	[125]	GETUPVAL 	4 0	; UIManager
	12	[125]	SELF     	4 4 -5	; "show"
	13	[125]	GETUPVAL 	6 1	; InfoMessage
	14	[125]	SELF     	6 6 -6	; "new"
	15	[125]	NEWTABLE 	8 0 1
	16	[126]	GETUPVAL 	9 2	; T
	17	[126]	GETUPVAL 	10 3	; _
	18	[130]	LOADK    	11 -8	; "Current margins:\n  left:  %1\n  right: %2\nDefault margins: not set"
	19	[126]	CALL     	10 2 2
	20	[131]	GETTABLE 	11 3 -9	; 1
	21	[131]	GETTABLE 	12 3 -10	; 2
	22	[126]	CALL     	9 4 2
	23	[131]	SETTABLE 	8 -7 9	; "text" -
	24	[125]	CALL     	6 3 0
	25	[125]	CALL     	4 0 1
	26	[132]	JMP      	17	; to 44
	27	[134]	GETUPVAL 	4 0	; UIManager
	28	[134]	SELF     	4 4 -5	; "show"
	29	[134]	GETUPVAL 	6 1	; InfoMessage
	30	[134]	SELF     	6 6 -6	; "new"
	31	[134]	NEWTABLE 	8 0 1
	32	[135]	GETUPVAL 	9 2	; T
	33	[135]	GETUPVAL 	10 3	; _
	34	[141]	LOADK    	11 -11	; "Current margins:\n  left:  %1\n  right: %2\nDefault margins:\n  left:  %3\n  right: %4"
	35	[135]	CALL     	10 2 2
	36	[142]	GETTABLE 	11 3 -9	; 1
	37	[142]	GETTABLE 	12 3 -10	; 2
	38	[143]	GETTABLE 	13 2 -9	; 1
	39	[143]	GETTABLE 	14 2 -10	; 2
	40	[135]	CALL     	9 6 2
	41	[143]	SETTABLE 	8 -7 9	; "text" -
	42	[134]	CALL     	6 3 0
	43	[134]	CALL     	4 0 1
	44	[146]	RETURN   	0 1
