
main <./spec/unit/optmath_spec.lua:0,0> (5 instructions, 20 bytes at 0x7fd0e34068c0)
0+ params, 3 slots, 0 upvalues, 0 locals, 2 constants, 1 function
	1	[1]	GETGLOBAL	0 -1	; describe
	2	[1]	LOADK    	1 -2	; "Math module"
	3	[61]	CLOSURE  	2 0	; 0x7fd0e3406b60
	4	[1]	CALL     	0 3 1
	5	[61]	RETURN   	0 1

function <./spec/unit/optmath_spec.lua:1,61> (30 instructions, 120 bytes at 0x7fd0e3406b60)
0 params, 4 slots, 0 upvalues, 1 local, 8 constants, 6 functions
	1	[4]	GETGLOBAL	1 -1	; setup
	2	[7]	CLOSURE  	2 0	; 0x7fd0e3406d80
	3	[7]	MOVE     	0 0
	4	[4]	CALL     	1 2 1
	5	[9]	GETGLOBAL	1 -2	; describe
	6	[9]	LOADK    	2 -3	; "tmin"
	7	[22]	CLOSURE  	3 1	; 0x7fd0e3406c60
	8	[22]	MOVE     	0 0
	9	[9]	CALL     	1 3 1
	10	[23]	GETGLOBAL	1 -2	; describe
	11	[23]	LOADK    	2 -4	; "tmax"
	12	[36]	CLOSURE  	3 2	; 0x7fd0e34086c0
	13	[36]	MOVE     	0 0
	14	[23]	CALL     	1 3 1
	15	[37]	GETGLOBAL	1 -5	; it
	16	[37]	LOADK    	2 -6	; "should round away from zero"
	17	[43]	CLOSURE  	3 3	; 0x7fd0e3408760
	18	[43]	MOVE     	0 0
	19	[37]	CALL     	1 3 1
	20	[44]	GETGLOBAL	1 -5	; it
	21	[44]	LOADK    	2 -7	; "should round"
	22	[50]	CLOSURE  	3 4	; 0x7fd0e3407160
	23	[50]	MOVE     	0 0
	24	[44]	CALL     	1 3 1
	25	[51]	GETGLOBAL	1 -5	; it
	26	[51]	LOADK    	2 -8	; "should determine odd or even"
	27	[59]	CLOSURE  	3 5	; 0x7fd0e340a730
	28	[59]	MOVE     	0 0
	29	[51]	CALL     	1 3 1
	30	[61]	RETURN   	0 1

function <./spec/unit/optmath_spec.lua:4,7> (8 instructions, 32 bytes at 0x7fd0e3406d80)
0 params, 2 slots, 1 upvalue, 0 locals, 3 constants, 0 functions
	1	[5]	GETGLOBAL	0 -1	; require
	2	[5]	LOADK    	1 -2	; "commonrequire"
	3	[5]	CALL     	0 2 1
	4	[6]	GETGLOBAL	0 -1	; require
	5	[6]	LOADK    	1 -3	; "optmath"
	6	[6]	CALL     	0 2 2
	7	[6]	SETUPVAL 	0 0	; Math
	8	[7]	RETURN   	0 1

function <./spec/unit/optmath_spec.lua:9,22> (16 instructions, 64 bytes at 0x7fd0e3406c60)
0 params, 3 slots, 1 upvalue, 0 locals, 4 constants, 3 functions
	1	[10]	GETGLOBAL	0 -1	; it
	2	[10]	LOADK    	1 -2	; "should return nil on empty table"
	3	[12]	CLOSURE  	2 0	; 0x7fd0e3407430
	4	[12]	GETUPVAL 	0 0	; Math
	5	[10]	CALL     	0 3 1
	6	[13]	GETGLOBAL	0 -1	; it
	7	[13]	LOADK    	1 -3	; "should get minimum element in table"
	8	[15]	CLOSURE  	2 1	; 0x7fd0e3407770
	9	[15]	GETUPVAL 	0 0	; Math
	10	[13]	CALL     	0 3 1
	11	[16]	GETGLOBAL	0 -1	; it
	12	[16]	LOADK    	1 -4	; "should get minimum element in table using custom function"
	13	[21]	CLOSURE  	2 2	; 0x7fd0e3407f50
	14	[21]	GETUPVAL 	0 0	; Math
	15	[16]	CALL     	0 3 1
	16	[22]	RETURN   	0 1

function <./spec/unit/optmath_spec.lua:10,12> (8 instructions, 32 bytes at 0x7fd0e3407430)
0 params, 3 slots, 1 upvalue, 0 locals, 3 constants, 0 functions
	1	[11]	GETGLOBAL	0 -1	; assert
	2	[11]	GETTABLE 	0 0 -2	; "is_nil"
	3	[11]	GETUPVAL 	1 0	; Math
	4	[11]	GETTABLE 	1 1 -3	; "tmin"
	5	[11]	NEWTABLE 	2 0 0
	6	[11]	CALL     	1 2 0
	7	[11]	CALL     	0 0 1
	8	[12]	RETURN   	0 1

function <./spec/unit/optmath_spec.lua:13,15> (17 instructions, 68 bytes at 0x7fd0e3407770)
0 params, 10 slots, 1 upvalue, 0 locals, 9 constants, 0 functions
	1	[14]	GETGLOBAL	0 -1	; assert
	2	[14]	GETTABLE 	0 0 -2	; "are"
	3	[14]	GETTABLE 	0 0 -3	; "same"
	4	[14]	LOADK    	1 -4	; 5
	5	[14]	GETUPVAL 	2 0	; Math
	6	[14]	GETTABLE 	2 2 -5	; "tmin"
	7	[14]	NEWTABLE 	3 6 0
	8	[14]	LOADK    	4 -6	; 9
	9	[14]	LOADK    	5 -7	; 7
	10	[14]	LOADK    	6 -8	; 10
	11	[14]	LOADK    	7 -9	; 11
	12	[14]	LOADK    	8 -4	; 5
	13	[14]	LOADK    	9 -7	; 7
	14	[14]	SETLIST  	3 6 1	; 1
	15	[14]	CALL     	2 2 0
	16	[14]	CALL     	0 0 1
	17	[15]	RETURN   	0 1

function <./spec/unit/optmath_spec.lua:16,21> (18 instructions, 72 bytes at 0x7fd0e3407f50)
0 params, 10 slots, 1 upvalue, 0 locals, 10 constants, 1 function
	1	[17]	GETGLOBAL	0 -1	; assert
	2	[17]	GETTABLE 	0 0 -2	; "are"
	3	[17]	GETTABLE 	0 0 -3	; "same"
	4	[17]	LOADK    	1 -4	; 5
	5	[18]	GETUPVAL 	2 0	; Math
	6	[18]	GETTABLE 	2 2 -5	; "tmin"
	7	[18]	NEWTABLE 	3 6 0
	8	[18]	LOADK    	4 -6	; "9"
	9	[18]	LOADK    	5 -7	; "7"
	10	[18]	LOADK    	6 -8	; "10"
	11	[18]	LOADK    	7 -9	; "11"
	12	[18]	LOADK    	8 -10	; "5"
	13	[18]	LOADK    	9 -7	; "7"
	14	[18]	SETLIST  	3 6 1	; 1
	15	[20]	CLOSURE  	4 0	; 0x7fd0e3407360
	16	[18]	CALL     	2 3 0
	17	[17]	CALL     	0 0 1
	18	[21]	RETURN   	0 1

function <./spec/unit/optmath_spec.lua:18,20> (12 instructions, 48 bytes at 0x7fd0e3407360)
2 params, 5 slots, 0 upvalues, 2 locals, 1 constant, 0 functions
	1	[19]	GETGLOBAL	2 -1	; tonumber
	2	[19]	MOVE     	3 0
	3	[19]	CALL     	2 2 2
	4	[19]	GETGLOBAL	3 -1	; tonumber
	5	[19]	MOVE     	4 1
	6	[19]	CALL     	3 2 2
	7	[19]	LT       	1 3 2
	8	[19]	JMP      	1	; to 10
	9	[19]	LOADBOOL 	2 0 1
	10	[19]	LOADBOOL 	2 1 0
	11	[19]	RETURN   	2 2
	12	[20]	RETURN   	0 1

function <./spec/unit/optmath_spec.lua:23,36> (16 instructions, 64 bytes at 0x7fd0e34086c0)
0 params, 3 slots, 1 upvalue, 0 locals, 4 constants, 3 functions
	1	[24]	GETGLOBAL	0 -1	; it
	2	[24]	LOADK    	1 -2	; "should return nil on empty table"
	3	[26]	CLOSURE  	2 0	; 0x7fd0e3408830
	4	[26]	GETUPVAL 	0 0	; Math
	5	[24]	CALL     	0 3 1
	6	[27]	GETGLOBAL	0 -1	; it
	7	[27]	LOADK    	1 -3	; "should get maximum element in table"
	8	[29]	CLOSURE  	2 1	; 0x7fd0e3408b10
	9	[29]	GETUPVAL 	0 0	; Math
	10	[27]	CALL     	0 3 1
	11	[30]	GETGLOBAL	0 -1	; it
	12	[30]	LOADK    	1 -4	; "should get maximum element in table using custom function"
	13	[35]	CLOSURE  	2 2	; 0x7fd0e34092b0
	14	[35]	GETUPVAL 	0 0	; Math
	15	[30]	CALL     	0 3 1
	16	[36]	RETURN   	0 1

function <./spec/unit/optmath_spec.lua:24,26> (8 instructions, 32 bytes at 0x7fd0e3408830)
0 params, 3 slots, 1 upvalue, 0 locals, 3 constants, 0 functions
	1	[25]	GETGLOBAL	0 -1	; assert
	2	[25]	GETTABLE 	0 0 -2	; "is_nil"
	3	[25]	GETUPVAL 	1 0	; Math
	4	[25]	GETTABLE 	1 1 -3	; "tmin"
	5	[25]	NEWTABLE 	2 0 0
	6	[25]	CALL     	1 2 0
	7	[25]	CALL     	0 0 1
	8	[26]	RETURN   	0 1

function <./spec/unit/optmath_spec.lua:27,29> (17 instructions, 68 bytes at 0x7fd0e3408b10)
0 params, 10 slots, 1 upvalue, 0 locals, 10 constants, 0 functions
	1	[28]	GETGLOBAL	0 -1	; assert
	2	[28]	GETTABLE 	0 0 -2	; "are"
	3	[28]	GETTABLE 	0 0 -3	; "same"
	4	[28]	LOADK    	1 -4	; 4
	5	[28]	GETUPVAL 	2 0	; Math
	6	[28]	GETTABLE 	2 2 -5	; "tmax"
	7	[28]	NEWTABLE 	3 6 0
	8	[28]	LOADK    	4 -6	; 9
	9	[28]	LOADK    	5 -7	; 7
	10	[28]	LOADK    	6 -8	; 10
	11	[28]	LOADK    	7 -9	; 11
	12	[28]	LOADK    	8 -10	; 5
	13	[28]	LOADK    	9 -7	; 7
	14	[28]	SETLIST  	3 6 1	; 1
	15	[28]	CALL     	2 2 0
	16	[28]	CALL     	0 0 1
	17	[29]	RETURN   	0 1

function <./spec/unit/optmath_spec.lua:30,35> (18 instructions, 72 bytes at 0x7fd0e34092b0)
0 params, 10 slots, 1 upvalue, 0 locals, 10 constants, 1 function
	1	[31]	GETGLOBAL	0 -1	; assert
	2	[31]	GETTABLE 	0 0 -2	; "are"
	3	[31]	GETTABLE 	0 0 -3	; "same"
	4	[31]	LOADK    	1 -4	; 4
	5	[32]	GETUPVAL 	2 0	; Math
	6	[32]	GETTABLE 	2 2 -5	; "tmax"
	7	[32]	NEWTABLE 	3 6 0
	8	[32]	LOADK    	4 -6	; "9"
	9	[32]	LOADK    	5 -7	; "7"
	10	[32]	LOADK    	6 -8	; "10"
	11	[32]	LOADK    	7 -9	; "11"
	12	[32]	LOADK    	8 -10	; "5"
	13	[32]	LOADK    	9 -7	; "7"
	14	[32]	SETLIST  	3 6 1	; 1
	15	[34]	CLOSURE  	4 0	; 0x7fd0e3409430
	16	[32]	CALL     	2 3 0
	17	[31]	CALL     	0 0 1
	18	[35]	RETURN   	0 1

function <./spec/unit/optmath_spec.lua:32,34> (12 instructions, 48 bytes at 0x7fd0e3409430)
2 params, 5 slots, 0 upvalues, 2 locals, 1 constant, 0 functions
	1	[33]	GETGLOBAL	2 -1	; tonumber
	2	[33]	MOVE     	3 0
	3	[33]	CALL     	2 2 2
	4	[33]	GETGLOBAL	3 -1	; tonumber
	5	[33]	MOVE     	4 1
	6	[33]	CALL     	3 2 2
	7	[33]	LT       	1 2 3
	8	[33]	JMP      	1	; to 10
	9	[33]	LOADBOOL 	2 0 1
	10	[33]	LOADBOOL 	2 1 0
	11	[33]	RETURN   	2 2
	12	[34]	RETURN   	0 1

function <./spec/unit/optmath_spec.lua:37,43> (46 instructions, 184 bytes at 0x7fd0e3408760)
0 params, 4 slots, 1 upvalue, 0 locals, 13 constants, 0 functions
	1	[38]	GETGLOBAL	0 -1	; assert
	2	[38]	GETTABLE 	0 0 -2	; "are"
	3	[38]	GETTABLE 	0 0 -3	; "same"
	4	[38]	LOADK    	1 -4	; 2
	5	[38]	GETUPVAL 	2 0	; Math
	6	[38]	GETTABLE 	2 2 -5	; "roundAwayFromZero"
	7	[38]	LOADK    	3 -6	; 1.5
	8	[38]	CALL     	2 2 0
	9	[38]	CALL     	0 0 1
	10	[39]	GETGLOBAL	0 -1	; assert
	11	[39]	GETTABLE 	0 0 -2	; "are"
	12	[39]	GETTABLE 	0 0 -3	; "same"
	13	[39]	LOADK    	1 -4	; 2
	14	[39]	GETUPVAL 	2 0	; Math
	15	[39]	GETTABLE 	2 2 -5	; "roundAwayFromZero"
	16	[39]	LOADK    	3 -7	; 1.4
	17	[39]	CALL     	2 2 0
	18	[39]	CALL     	0 0 1
	19	[40]	GETGLOBAL	0 -1	; assert
	20	[40]	GETTABLE 	0 0 -2	; "are"
	21	[40]	GETTABLE 	0 0 -3	; "same"
	22	[40]	LOADK    	1 -8	; -2
	23	[40]	GETUPVAL 	2 0	; Math
	24	[40]	GETTABLE 	2 2 -5	; "roundAwayFromZero"
	25	[40]	LOADK    	3 -9	; -1.4
	26	[40]	CALL     	2 2 0
	27	[40]	CALL     	0 0 1
	28	[41]	GETGLOBAL	0 -1	; assert
	29	[41]	GETTABLE 	0 0 -2	; "are"
	30	[41]	GETTABLE 	0 0 -3	; "same"
	31	[41]	LOADK    	1 -10	; 1
	32	[41]	GETUPVAL 	2 0	; Math
	33	[41]	GETTABLE 	2 2 -5	; "roundAwayFromZero"
	34	[41]	LOADK    	3 -11	; 0.2
	35	[41]	CALL     	2 2 0
	36	[41]	CALL     	0 0 1
	37	[42]	GETGLOBAL	0 -1	; assert
	38	[42]	GETTABLE 	0 0 -2	; "are"
	39	[42]	GETTABLE 	0 0 -3	; "same"
	40	[42]	LOADK    	1 -12	; -1
	41	[42]	GETUPVAL 	2 0	; Math
	42	[42]	GETTABLE 	2 2 -5	; "roundAwayFromZero"
	43	[42]	LOADK    	3 -13	; -0.2
	44	[42]	CALL     	2 2 0
	45	[42]	CALL     	0 0 1
	46	[43]	RETURN   	0 1

function <./spec/unit/optmath_spec.lua:44,50> (46 instructions, 184 bytes at 0x7fd0e3407160)
0 params, 4 slots, 1 upvalue, 0 locals, 13 constants, 0 functions
	1	[45]	GETGLOBAL	0 -1	; assert
	2	[45]	GETTABLE 	0 0 -2	; "are"
	3	[45]	GETTABLE 	0 0 -3	; "same"
	4	[45]	LOADK    	1 -4	; 2
	5	[45]	GETUPVAL 	2 0	; Math
	6	[45]	GETTABLE 	2 2 -5	; "round"
	7	[45]	LOADK    	3 -6	; 1.5
	8	[45]	CALL     	2 2 0
	9	[45]	CALL     	0 0 1
	10	[46]	GETGLOBAL	0 -1	; assert
	11	[46]	GETTABLE 	0 0 -2	; "are"
	12	[46]	GETTABLE 	0 0 -3	; "same"
	13	[46]	LOADK    	1 -7	; 1
	14	[46]	GETUPVAL 	2 0	; Math
	15	[46]	GETTABLE 	2 2 -5	; "round"
	16	[46]	LOADK    	3 -8	; 1.4
	17	[46]	CALL     	2 2 0
	18	[46]	CALL     	0 0 1
	19	[47]	GETGLOBAL	0 -1	; assert
	20	[47]	GETTABLE 	0 0 -2	; "are"
	21	[47]	GETTABLE 	0 0 -3	; "same"
	22	[47]	LOADK    	1 -9	; -1
	23	[47]	GETUPVAL 	2 0	; Math
	24	[47]	GETTABLE 	2 2 -5	; "round"
	25	[47]	LOADK    	3 -10	; -1.4
	26	[47]	CALL     	2 2 0
	27	[47]	CALL     	0 0 1
	28	[48]	GETGLOBAL	0 -1	; assert
	29	[48]	GETTABLE 	0 0 -2	; "are"
	30	[48]	GETTABLE 	0 0 -3	; "same"
	31	[48]	LOADK    	1 -11	; 0
	32	[48]	GETUPVAL 	2 0	; Math
	33	[48]	GETTABLE 	2 2 -5	; "round"
	34	[48]	LOADK    	3 -12	; 0.2
	35	[48]	CALL     	2 2 0
	36	[48]	CALL     	0 0 1
	37	[49]	GETGLOBAL	0 -1	; assert
	38	[49]	GETTABLE 	0 0 -2	; "are"
	39	[49]	GETTABLE 	0 0 -3	; "same"
	40	[49]	LOADK    	1 -11	; 0
	41	[49]	GETUPVAL 	2 0	; Math
	42	[49]	GETTABLE 	2 2 -5	; "round"
	43	[49]	LOADK    	3 -13	; -0.2
	44	[49]	CALL     	2 2 0
	45	[49]	CALL     	0 0 1
	46	[50]	RETURN   	0 1

function <./spec/unit/optmath_spec.lua:51,59> (64 instructions, 256 bytes at 0x7fd0e340a730)
0 params, 4 slots, 1 upvalue, 0 locals, 13 constants, 0 functions
	1	[52]	GETGLOBAL	0 -1	; assert
	2	[52]	GETTABLE 	0 0 -2	; "are"
	3	[52]	GETTABLE 	0 0 -3	; "same"
	4	[52]	LOADK    	1 -4	; "odd"
	5	[52]	GETUPVAL 	2 0	; Math
	6	[52]	GETTABLE 	2 2 -5	; "oddEven"
	7	[52]	LOADK    	3 -6	; 1
	8	[52]	CALL     	2 2 0
	9	[52]	CALL     	0 0 1
	10	[53]	GETGLOBAL	0 -1	; assert
	11	[53]	GETTABLE 	0 0 -2	; "are"
	12	[53]	GETTABLE 	0 0 -3	; "same"
	13	[53]	LOADK    	1 -7	; "even"
	14	[53]	GETUPVAL 	2 0	; Math
	15	[53]	GETTABLE 	2 2 -5	; "oddEven"
	16	[53]	LOADK    	3 -8	; 2
	17	[53]	CALL     	2 2 0
	18	[53]	CALL     	0 0 1
	19	[54]	GETGLOBAL	0 -1	; assert
	20	[54]	GETTABLE 	0 0 -2	; "are"
	21	[54]	GETTABLE 	0 0 -3	; "same"
	22	[54]	LOADK    	1 -4	; "odd"
	23	[54]	GETUPVAL 	2 0	; Math
	24	[54]	GETTABLE 	2 2 -5	; "oddEven"
	25	[54]	LOADK    	3 -9	; 3
	26	[54]	CALL     	2 2 0
	27	[54]	CALL     	0 0 1
	28	[55]	GETGLOBAL	0 -1	; assert
	29	[55]	GETTABLE 	0 0 -2	; "are"
	30	[55]	GETTABLE 	0 0 -3	; "same"
	31	[55]	LOADK    	1 -7	; "even"
	32	[55]	GETUPVAL 	2 0	; Math
	33	[55]	GETTABLE 	2 2 -5	; "oddEven"
	34	[55]	LOADK    	3 -10	; 4
	35	[55]	CALL     	2 2 0
	36	[55]	CALL     	0 0 1
	37	[56]	GETGLOBAL	0 -1	; assert
	38	[56]	GETTABLE 	0 0 -2	; "are"
	39	[56]	GETTABLE 	0 0 -3	; "same"
	40	[56]	LOADK    	1 -7	; "even"
	41	[56]	GETUPVAL 	2 0	; Math
	42	[56]	GETTABLE 	2 2 -5	; "oddEven"
	43	[56]	LOADK    	3 -11	; -4
	44	[56]	CALL     	2 2 0
	45	[56]	CALL     	0 0 1
	46	[57]	GETGLOBAL	0 -1	; assert
	47	[57]	GETTABLE 	0 0 -2	; "are"
	48	[57]	GETTABLE 	0 0 -3	; "same"
	49	[57]	LOADK    	1 -4	; "odd"
	50	[57]	GETUPVAL 	2 0	; Math
	51	[57]	GETTABLE 	2 2 -5	; "oddEven"
	52	[57]	LOADK    	3 -12	; -3
	53	[57]	CALL     	2 2 0
	54	[57]	CALL     	0 0 1
	55	[58]	GETGLOBAL	0 -1	; assert
	56	[58]	GETTABLE 	0 0 -2	; "are"
	57	[58]	GETTABLE 	0 0 -3	; "same"
	58	[58]	LOADK    	1 -7	; "even"
	59	[58]	GETUPVAL 	2 0	; Math
	60	[58]	GETTABLE 	2 2 -5	; "oddEven"
	61	[58]	LOADK    	3 -13	; 0
	62	[58]	CALL     	2 2 0
	63	[58]	CALL     	0 0 1
	64	[59]	RETURN   	0 1
