
main <./frontend/ui/otamanager.lua:0,0> (158 instructions, 632 bytes at 0x7f8a35c068c0)
0+ params, 21 slots, 0 upvalues, 18 locals, 61 constants, 17 functions
	1	[5]	GETGLOBAL	0 -1	; require
	2	[5]	LOADK    	1 -2	; "ui/bidi"
	3	[5]	CALL     	0 2 2
	4	[6]	GETGLOBAL	1 -1	; require
	5	[6]	LOADK    	2 -3	; "ui/widget/confirmbox"
	6	[6]	CALL     	1 2 2
	7	[7]	GETGLOBAL	2 -1	; require
	8	[7]	LOADK    	3 -4	; "datastorage"
	9	[7]	CALL     	2 2 2
	10	[8]	GETGLOBAL	3 -1	; require
	11	[8]	LOADK    	4 -5	; "device"
	12	[8]	CALL     	3 2 2
	13	[9]	GETGLOBAL	4 -1	; require
	14	[9]	LOADK    	5 -6	; "ui/widget/infomessage"
	15	[9]	CALL     	4 2 2
	16	[10]	GETGLOBAL	5 -1	; require
	17	[10]	LOADK    	6 -7	; "ui/widget/multiconfirmbox"
	18	[10]	CALL     	5 2 2
	19	[11]	GETGLOBAL	6 -1	; require
	20	[11]	LOADK    	7 -8	; "ui/network/manager"
	21	[11]	CALL     	6 2 2
	22	[12]	GETGLOBAL	7 -1	; require
	23	[12]	LOADK    	8 -9	; "ui/uimanager"
	24	[12]	CALL     	7 2 2
	25	[13]	GETGLOBAL	8 -1	; require
	26	[13]	LOADK    	9 -10	; "version"
	27	[13]	CALL     	8 2 2
	28	[14]	GETGLOBAL	9 -1	; require
	29	[14]	LOADK    	10 -11	; "libs/libkoreader-lfs"
	30	[14]	CALL     	9 2 2
	31	[15]	GETGLOBAL	10 -1	; require
	32	[15]	LOADK    	11 -12	; "logger"
	33	[15]	CALL     	10 2 2
	34	[16]	GETGLOBAL	11 -1	; require
	35	[16]	LOADK    	12 -13	; "gettext"
	36	[16]	CALL     	11 2 2
	37	[17]	GETGLOBAL	12 -1	; require
	38	[17]	LOADK    	13 -14	; "ffi/util"
	39	[17]	CALL     	12 2 2
	40	[17]	GETTABLE 	12 12 -15	; "template"
	41	[19]	SELF     	13 2 -16	; "getDataDir"
	42	[19]	CALL     	13 2 2
	43	[19]	LOADK    	14 -17	; "/ota/"
	44	[19]	CONCAT   	13 13 14
	45	[21]	NEWTABLE 	14 0 8
	46	[23]	NEWTABLE 	15 5 0
	47	[24]	LOADK    	16 -19	; "http://ota.koreader.rocks/"
	48	[29]	LOADK    	17 -20	; "http://koreader-fr.ak-team.com/"
	49	[30]	LOADK    	18 -21	; "http://koreader-pl.ak-team.com/"
	50	[31]	LOADK    	19 -22	; "http://koreader-na.ak-team.com/"
	51	[33]	LOADK    	20 -23	; "http://koreader.ak-team.com/"
	52	[33]	SETLIST  	15 5 1	; 1
	53	[33]	SETTABLE 	14 -18 15	; "ota_servers" -
	54	[34]	NEWTABLE 	15 2 0
	55	[35]	LOADK    	16 -25	; "stable"
	56	[37]	LOADK    	17 -26	; "nightly"
	57	[37]	SETLIST  	15 2 1	; 1
	58	[37]	SETTABLE 	14 -24 15	; "ota_channels" -
	59	[38]	SETTABLE 	14 -27 -28	; "link_template" "koreader-%s-latest-%s"
	60	[39]	SETTABLE 	14 -29 -30	; "zsync_template" "koreader-%s-latest-%s.zsync"
	61	[40]	MOVE     	15 13
	62	[40]	LOADK    	16 -32	; "koreader.installed.tar"
	63	[40]	CONCAT   	15 15 16
	64	[40]	SETTABLE 	14 -31 15	; "installed_package" -
	65	[41]	SETTABLE 	14 -33 -34	; "package_indexfile" "ota/package.index"
	66	[42]	MOVE     	15 13
	67	[42]	LOADK    	16 -36	; "koreader.updated.tar"
	68	[42]	CONCAT   	15 15 16
	69	[42]	SETTABLE 	14 -35 15	; "updated_package" -
	70	[43]	GETTABLE 	15 9 -38	; "attributes"
	71	[43]	LOADK    	16 -39	; "./fbink"
	72	[43]	LOADK    	17 -40	; "mode"
	73	[43]	CALL     	15 3 2
	74	[43]	EQ       	0 15 -41	; - "file"
	75	[43]	JMP      	3	; to 79
	76	[43]	LOADBOOL 	15 1 0
	77	[43]	TEST     	15 0 1
	78	[43]	JMP      	1	; to 80
	79	[43]	LOADBOOL 	15 0 0
	80	[43]	SETTABLE 	14 -37 15	; "can_pretty_print" -
	81	[46]	NEWTABLE 	15 0 2
	82	[47]	MOVE     	16 11
	83	[47]	LOADK    	17 -42	; "Stable"
	84	[47]	CALL     	16 2 2
	85	[47]	SETTABLE 	15 -25 16	; "stable" -
	86	[48]	MOVE     	16 11
	87	[48]	LOADK    	17 -43	; "Development"
	88	[48]	CALL     	16 2 2
	89	[48]	SETTABLE 	15 -26 16	; "nightly" -
	90	[76]	CLOSURE  	16 0	; 0x7f8a35c06e50
	91	[76]	MOVE     	0 7
	92	[76]	MOVE     	0 1
	93	[76]	MOVE     	0 11
	94	[76]	MOVE     	0 3
	95	[101]	CLOSURE  	17 1	; 0x7f8a35c086c0
	96	[79]	SETTABLE 	14 -44 17	; "_isKindleWarioOrMore" -
	97	[104]	GETGLOBAL	17 -45	; jit
	98	[104]	GETTABLE 	17 17 -46	; "arch"
	99	[137]	CLOSURE  	18 2	; 0x7f8a35c08d00
	100	[137]	MOVE     	0 3
	101	[137]	MOVE     	0 17
	102	[106]	SETTABLE 	14 -47 18	; "getOTAModel" -
	103	[149]	CLOSURE  	18 3	; 0x7f8a35c09310
	104	[139]	SETTABLE 	14 -48 18	; "getOTAType" -
	105	[153]	CLOSURE  	18 4	; 0x7f8a35c09e20
	106	[151]	SETTABLE 	14 -49 18	; "getOTAServer" -
	107	[158]	CLOSURE  	18 5	; 0x7f8a35c0a0b0
	108	[158]	MOVE     	0 10
	109	[155]	SETTABLE 	14 -50 18	; "setOTAServer" -
	110	[162]	CLOSURE  	18 6	; 0x7f8a35c0a570
	111	[160]	SETTABLE 	14 -51 18	; "getOTAChannel" -
	112	[167]	CLOSURE  	18 7	; 0x7f8a35c0aa90
	113	[167]	MOVE     	0 10
	114	[164]	SETTABLE 	14 -52 18	; "setOTAChannel" -
	115	[171]	CLOSURE  	18 8	; 0x7f8a35c0afd0
	116	[169]	SETTABLE 	14 -53 18	; "getLinkFilename" -
	117	[175]	CLOSURE  	18 9	; 0x7f8a35c0b650
	118	[173]	SETTABLE 	14 -54 18	; "getZsyncFilename" -
	119	[230]	CLOSURE  	18 10	; 0x7f8a35c0b940
	120	[230]	MOVE     	0 13
	121	[230]	MOVE     	0 10
	122	[230]	MOVE     	0 14
	123	[230]	MOVE     	0 8
	124	[177]	SETTABLE 	14 -55 18	; "checkUpdate" -
	125	[350]	CLOSURE  	18 11	; 0x7f8a35c0c870
	126	[350]	MOVE     	0 14
	127	[350]	MOVE     	0 7
	128	[350]	MOVE     	0 4
	129	[350]	MOVE     	0 11
	130	[350]	MOVE     	0 15
	131	[350]	MOVE     	0 12
	132	[350]	MOVE     	0 0
	133	[350]	MOVE     	0 1
	134	[350]	MOVE     	0 3
	135	[350]	MOVE     	0 16
	136	[350]	MOVE     	0 5
	137	[350]	MOVE     	0 13
	138	[232]	SETTABLE 	14 -56 18	; "fetchAndProcessUpdate" -
	139	[397]	CLOSURE  	18 12	; 0x7f8a35c0e0e0
	140	[397]	MOVE     	0 9
	141	[397]	MOVE     	0 10
	142	[397]	MOVE     	0 13
	143	[353]	SETTABLE 	14 -57 18	; "_buildLocalPackage" -
	144	[437]	CLOSURE  	18 13	; 0x7f8a35c076a0
	145	[437]	MOVE     	0 13
	146	[399]	SETTABLE 	14 -58 18	; "zsync" -
	147	[450]	CLOSURE  	18 14	; 0x7f8a35c0ee50
	148	[439]	SETTABLE 	14 -59 18	; "genServerList" -
	149	[463]	CLOSURE  	18 15	; 0x7f8a35c0f980
	150	[463]	MOVE     	0 15
	151	[452]	SETTABLE 	14 -60 18	; "genChannelList" -
	152	[501]	CLOSURE  	18 16	; 0x7f8a35c10240
	153	[501]	MOVE     	0 11
	154	[501]	MOVE     	0 6
	155	[501]	MOVE     	0 14
	156	[465]	SETTABLE 	14 -61 18	; "getOTAMenuTable" -
	157	[503]	RETURN   	14 2
	158	[503]	RETURN   	0 1

function <./frontend/ui/otamanager.lua:51,76> (20 instructions, 80 bytes at 0x7f8a35c06e50)
0 params, 7 slots, 4 upvalues, 0 locals, 7 constants, 1 function
	1	[52]	GETUPVAL 	0 0	; UIManager
	2	[52]	SELF     	0 0 -1	; "show"
	3	[52]	GETUPVAL 	2 1	; ConfirmBox
	4	[52]	SELF     	2 2 -2	; "new"
	5	[52]	NEWTABLE 	4 0 3
	6	[53]	GETUPVAL 	5 2	; _
	7	[53]	LOADK    	6 -4	; "KOReader will be updated on next restart.\nWould you like to restart now?"
	8	[53]	CALL     	5 2 2
	9	[53]	SETTABLE 	4 -3 5	; "text" -
	10	[54]	GETUPVAL 	5 2	; _
	11	[54]	LOADK    	6 -6	; "Restart"
	12	[54]	CALL     	5 2 2
	13	[54]	SETTABLE 	4 -5 5	; "ok_text" -
	14	[74]	CLOSURE  	5 0	; 0x7f8a35c07a80
	15	[74]	GETUPVAL 	0 3	; Device
	16	[74]	GETUPVAL 	0 0	; UIManager
	17	[74]	SETTABLE 	4 -7 5	; "ok_callback" -
	18	[52]	CALL     	2 3 0
	19	[52]	CALL     	0 0 1
	20	[76]	RETURN   	0 1

function <./frontend/ui/otamanager.lua:55,74> (23 instructions, 92 bytes at 0x7f8a35c07a80)
0 params, 8 slots, 2 upvalues, 5 locals, 7 constants, 1 function
	1	[61]	CLOSURE  	1 0	; 0x7f8a35c08060
	2	[61]	GETUPVAL 	0 0	; Device
	3	[61]	GETUPVAL 	0 1	; UIManager
	4	[63]	GETGLOBAL	2 -1	; require
	5	[63]	LOADK    	3 -2	; "apps/filemanager/filemanager"
	6	[63]	CALL     	2 2 2
	7	[64]	GETTABLE 	3 2 -3	; "instance"
	8	[64]	TEST     	3 0 0
	9	[64]	JMP      	2	; to 12
	10	[65]	GETTABLE 	3 2 -3	; "instance"
	11	[65]	GETTABLE 	0 3 -4	; "menu"
	12	[68]	GETGLOBAL	3 -1	; require
	13	[68]	LOADK    	4 -5	; "apps/reader/readerui"
	14	[68]	CALL     	3 2 2
	15	[69]	SELF     	4 3 -6	; "_getRunningInstance"
	16	[69]	CALL     	4 2 2
	17	[70]	TEST     	4 0 0
	18	[70]	JMP      	1	; to 20
	19	[71]	GETTABLE 	0 4 -4	; "menu"
	20	[73]	SELF     	5 0 -7	; "exitOrRestart"
	21	[73]	MOVE     	7 1
	22	[73]	CALL     	5 3 1
	23	[74]	RETURN   	0 1

function <./frontend/ui/otamanager.lua:57,61> (9 instructions, 36 bytes at 0x7f8a35c08060)
0 params, 2 slots, 2 upvalues, 0 locals, 4 constants, 0 functions
	1	[58]	GETUPVAL 	0 0	; Device
	2	[58]	SELF     	0 0 -1	; "saveSettings"
	3	[58]	CALL     	0 2 1
	4	[59]	GETUPVAL 	0 1	; UIManager
	5	[59]	SELF     	0 0 -2	; "quit"
	6	[59]	CALL     	0 2 1
	7	[60]	GETUPVAL 	0 1	; UIManager
	8	[60]	SETTABLE 	0 -3 -4	; "_exit_code" 85
	9	[61]	RETURN   	0 1

function <./frontend/ui/otamanager.lua:79,101> (32 instructions, 128 bytes at 0x7f8a35c086c0)
1 param, 9 slots, 0 upvalues, 6 locals, 8 constants, 0 functions
	1	[82]	GETGLOBAL	2 -1	; io
	2	[82]	GETTABLE 	2 2 -2	; "lines"
	3	[82]	LOADK    	3 -3	; "/proc/cpuinfo"
	4	[82]	CALL     	2 2 4
	5	[82]	JMP      	9	; to 15
	6	[83]	SELF     	6 5 -4	; "find"
	7	[83]	LOADK    	8 -5	; "^Hardware"
	8	[83]	CALL     	6 3 2
	9	[83]	TEST     	6 0 0
	10	[83]	JMP      	4	; to 15
	11	[84]	SELF     	6 5 -6	; "match"
	12	[84]	LOADK    	8 -7	; "^Hardware%s*:%s([%g%s]*)$"
	13	[84]	CALL     	6 3 2
	14	[84]	MOVE     	1 6
	15	[82]	TFORLOOP 	2 1
	16	[85]	JMP      	-11	; to 6
	17	[92]	TEST     	1 0 0
	18	[92]	JMP      	11	; to 30
	19	[93]	SELF     	2 1 -4	; "find"
	20	[93]	LOADK    	4 -8	; "i.MX%s?[6-7]"
	21	[93]	CALL     	2 3 2
	22	[93]	TEST     	2 0 0
	23	[93]	JMP      	3	; to 27
	24	[94]	LOADBOOL 	2 1 0
	25	[94]	RETURN   	2 2
	26	[94]	JMP      	5	; to 32
	27	[96]	LOADBOOL 	2 0 0
	28	[96]	RETURN   	2 2
	29	[97]	JMP      	2	; to 32
	30	[99]	LOADBOOL 	2 0 0
	31	[99]	RETURN   	2 2
	32	[101]	RETURN   	0 1

function <./frontend/ui/otamanager.lua:106,137> (91 instructions, 364 bytes at 0x7f8a35c08d00)
1 param, 3 slots, 2 upvalues, 1 local, 25 constants, 0 functions
	1	[107]	GETUPVAL 	1 0	; Device
	2	[107]	SELF     	1 1 -1	; "isAndroid"
	3	[107]	CALL     	1 2 2
	4	[107]	TEST     	1 0 0
	5	[107]	JMP      	8	; to 14
	6	[108]	GETUPVAL 	1 1	; arch
	7	[108]	EQ       	0 1 -2	; - "x86"
	8	[108]	JMP      	2	; to 11
	9	[109]	LOADK    	1 -3	; "android-x86"
	10	[109]	RETURN   	1 2
	11	[111]	LOADK    	1 -4	; "android"
	12	[111]	RETURN   	1 2
	13	[111]	JMP      	77	; to 91
	14	[112]	GETUPVAL 	1 0	; Device
	15	[112]	SELF     	1 1 -5	; "isSDL"
	16	[112]	CALL     	1 2 2
	17	[112]	TEST     	1 0 0
	18	[112]	JMP      	3	; to 22
	19	[113]	LOADK    	1 -6	; "appimage"
	20	[113]	RETURN   	1 2
	21	[113]	JMP      	69	; to 91
	22	[114]	GETUPVAL 	1 0	; Device
	23	[114]	SELF     	1 1 -7	; "isCervantes"
	24	[114]	CALL     	1 2 2
	25	[114]	TEST     	1 0 0
	26	[114]	JMP      	3	; to 30
	27	[115]	LOADK    	1 -8	; "cervantes"
	28	[115]	RETURN   	1 2
	29	[115]	JMP      	61	; to 91
	30	[116]	GETUPVAL 	1 0	; Device
	31	[116]	SELF     	1 1 -9	; "isKindle"
	32	[116]	CALL     	1 2 2
	33	[116]	TEST     	1 0 0
	34	[116]	JMP      	22	; to 57
	35	[117]	GETUPVAL 	1 0	; Device
	36	[117]	SELF     	1 1 -10	; "isTouchDevice"
	37	[117]	CALL     	1 2 2
	38	[117]	TEST     	1 0 1
	39	[117]	JMP      	4	; to 44
	40	[117]	GETUPVAL 	1 0	; Device
	41	[117]	GETTABLE 	1 1 -11	; "model"
	42	[117]	EQ       	0 1 -12	; - "Kindle4"
	43	[117]	JMP      	10	; to 54
	44	[118]	SELF     	1 0 -13	; "_isKindleWarioOrMore"
	45	[118]	CALL     	1 2 2
	46	[118]	TEST     	1 0 0
	47	[118]	JMP      	3	; to 51
	48	[119]	LOADK    	1 -14	; "kindlepw2"
	49	[119]	RETURN   	1 2
	50	[119]	JMP      	40	; to 91
	51	[121]	LOADK    	1 -15	; "kindle"
	52	[121]	RETURN   	1 2
	53	[122]	JMP      	37	; to 91
	54	[124]	LOADK    	1 -16	; "kindle-legacy"
	55	[124]	RETURN   	1 2
	56	[125]	JMP      	34	; to 91
	57	[126]	GETUPVAL 	1 0	; Device
	58	[126]	SELF     	1 1 -17	; "isKobo"
	59	[126]	CALL     	1 2 2
	60	[126]	TEST     	1 0 0
	61	[126]	JMP      	3	; to 65
	62	[127]	LOADK    	1 -18	; "kobo"
	63	[127]	RETURN   	1 2
	64	[127]	JMP      	26	; to 91
	65	[128]	GETUPVAL 	1 0	; Device
	66	[128]	SELF     	1 1 -19	; "isPocketBook"
	67	[128]	CALL     	1 2 2
	68	[128]	TEST     	1 0 0
	69	[128]	JMP      	3	; to 73
	70	[129]	LOADK    	1 -20	; "pocketbook"
	71	[129]	RETURN   	1 2
	72	[129]	JMP      	18	; to 91
	73	[130]	GETUPVAL 	1 0	; Device
	74	[130]	SELF     	1 1 -21	; "isRemarkable"
	75	[130]	CALL     	1 2 2
	76	[130]	TEST     	1 0 0
	77	[130]	JMP      	3	; to 81
	78	[131]	LOADK    	1 -22	; "remarkable"
	79	[131]	RETURN   	1 2
	80	[131]	JMP      	10	; to 91
	81	[132]	GETUPVAL 	1 0	; Device
	82	[132]	SELF     	1 1 -23	; "isSonyPRSTUX"
	83	[132]	CALL     	1 2 2
	84	[132]	TEST     	1 0 0
	85	[132]	JMP      	3	; to 89
	86	[133]	LOADK    	1 -24	; "sony-prstux"
	87	[133]	RETURN   	1 2
	88	[133]	JMP      	2	; to 91
	89	[135]	LOADK    	1 -25	; ""
	90	[135]	RETURN   	1 2
	91	[137]	RETURN   	0 1

function <./frontend/ui/otamanager.lua:139,149> (20 instructions, 80 bytes at 0x7f8a35c09310)
1 param, 5 slots, 0 upvalues, 2 locals, 7 constants, 0 functions
	1	[140]	SELF     	1 0 -1	; "getOTAModel"
	2	[140]	CALL     	1 2 2
	3	[142]	EQ       	0 1 -2	; - ""
	4	[142]	JMP      	1	; to 6
	5	[142]	RETURN   	0 1
	6	[144]	SELF     	2 1 -3	; "find"
	7	[144]	LOADK    	4 -4	; "android"
	8	[144]	CALL     	2 3 2
	9	[144]	TEST     	2 0 1
	10	[144]	JMP      	5	; to 16
	11	[144]	SELF     	2 1 -3	; "find"
	12	[144]	LOADK    	4 -5	; "appimage"
	13	[144]	CALL     	2 3 2
	14	[144]	TEST     	2 0 0
	15	[144]	JMP      	2	; to 18
	16	[145]	LOADK    	2 -6	; "link"
	17	[145]	RETURN   	2 2
	18	[148]	LOADK    	2 -7	; "ota"
	19	[148]	RETURN   	2 2
	20	[149]	RETURN   	0 1

function <./frontend/ui/otamanager.lua:151,153> (10 instructions, 40 bytes at 0x7f8a35c09e20)
1 param, 4 slots, 0 upvalues, 1 local, 5 constants, 0 functions
	1	[152]	GETGLOBAL	1 -1	; G_reader_settings
	2	[152]	SELF     	1 1 -2	; "readSetting"
	3	[152]	LOADK    	3 -3	; "ota_server"
	4	[152]	CALL     	1 3 2
	5	[152]	TEST     	1 0 1
	6	[152]	JMP      	2	; to 9
	7	[152]	GETTABLE 	1 0 -4	; "ota_servers"
	8	[152]	GETTABLE 	1 1 -5	; 1
	9	[152]	RETURN   	1 2
	10	[153]	RETURN   	0 1

function <./frontend/ui/otamanager.lua:155,158> (11 instructions, 44 bytes at 0x7f8a35c0a0b0)
2 params, 6 slots, 1 upvalue, 2 locals, 5 constants, 0 functions
	1	[156]	GETUPVAL 	2 0	; logger
	2	[156]	GETTABLE 	2 2 -1	; "dbg"
	3	[156]	LOADK    	3 -2	; "Set OTA server:"
	4	[156]	MOVE     	4 1
	5	[156]	CALL     	2 3 1
	6	[157]	GETGLOBAL	2 -3	; G_reader_settings
	7	[157]	SELF     	2 2 -4	; "saveSetting"
	8	[157]	LOADK    	4 -5	; "ota_server"
	9	[157]	MOVE     	5 1
	10	[157]	CALL     	2 4 1
	11	[158]	RETURN   	0 1

function <./frontend/ui/otamanager.lua:160,162> (10 instructions, 40 bytes at 0x7f8a35c0a570)
1 param, 4 slots, 0 upvalues, 1 local, 5 constants, 0 functions
	1	[161]	GETGLOBAL	1 -1	; G_reader_settings
	2	[161]	SELF     	1 1 -2	; "readSetting"
	3	[161]	LOADK    	3 -3	; "ota_channel"
	4	[161]	CALL     	1 3 2
	5	[161]	TEST     	1 0 1
	6	[161]	JMP      	2	; to 9
	7	[161]	GETTABLE 	1 0 -4	; "ota_channels"
	8	[161]	GETTABLE 	1 1 -5	; 1
	9	[161]	RETURN   	1 2
	10	[162]	RETURN   	0 1

function <./frontend/ui/otamanager.lua:164,167> (11 instructions, 44 bytes at 0x7f8a35c0aa90)
2 params, 6 slots, 1 upvalue, 2 locals, 5 constants, 0 functions
	1	[165]	GETUPVAL 	2 0	; logger
	2	[165]	GETTABLE 	2 2 -1	; "dbg"
	3	[165]	LOADK    	3 -2	; "Set OTA channel:"
	4	[165]	MOVE     	4 1
	5	[165]	CALL     	2 3 1
	6	[166]	GETGLOBAL	2 -3	; G_reader_settings
	7	[166]	SELF     	2 2 -4	; "saveSetting"
	8	[166]	LOADK    	4 -5	; "ota_channel"
	9	[166]	MOVE     	5 1
	10	[166]	CALL     	2 4 1
	11	[167]	RETURN   	0 1

function <./frontend/ui/otamanager.lua:169,171> (9 instructions, 36 bytes at 0x7f8a35c0afd0)
1 param, 6 slots, 0 upvalues, 1 local, 4 constants, 0 functions
	1	[170]	GETTABLE 	1 0 -1	; "link_template"
	2	[170]	SELF     	1 1 -2	; "format"
	3	[170]	SELF     	3 0 -3	; "getOTAModel"
	4	[170]	CALL     	3 2 2
	5	[170]	SELF     	4 0 -4	; "getOTAChannel"
	6	[170]	CALL     	4 2 0
	7	[170]	TAILCALL 	1 0 0
	8	[170]	RETURN   	1 0
	9	[171]	RETURN   	0 1

function <./frontend/ui/otamanager.lua:173,175> (9 instructions, 36 bytes at 0x7f8a35c0b650)
1 param, 6 slots, 0 upvalues, 1 local, 4 constants, 0 functions
	1	[174]	GETTABLE 	1 0 -1	; "zsync_template"
	2	[174]	SELF     	1 1 -2	; "format"
	3	[174]	SELF     	3 0 -3	; "getOTAModel"
	4	[174]	CALL     	3 2 2
	5	[174]	SELF     	4 0 -4	; "getOTAChannel"
	6	[174]	CALL     	4 2 0
	7	[174]	TAILCALL 	1 0 0
	8	[174]	RETURN   	1 0
	9	[175]	RETURN   	0 1

function <./frontend/ui/otamanager.lua:177,230> (123 instructions, 492 bytes at 0x7f8a35c0b940)
1 param, 20 slots, 4 upvalues, 25 locals, 28 constants, 2 functions
	1	[178]	GETGLOBAL	1 -1	; require
	2	[178]	LOADK    	2 -2	; "socket.http"
	3	[178]	CALL     	1 2 2
	4	[179]	GETGLOBAL	2 -1	; require
	5	[179]	LOADK    	3 -3	; "ltn12"
	6	[179]	CALL     	2 2 2
	7	[181]	SELF     	3 0 -4	; "getOTAType"
	8	[181]	CALL     	3 2 2
	9	[181]	EQ       	0 3 -5	; - "link"
	10	[181]	JMP      	4	; to 15
	11	[181]	SELF     	3 0 -6	; "getLinkFilename"
	12	[181]	CALL     	3 2 2
	13	[181]	TEST     	3 0 1
	14	[181]	JMP      	2	; to 17
	15	[181]	SELF     	3 0 -7	; "getZsyncFilename"
	16	[181]	CALL     	3 2 2
	17	[183]	SELF     	4 0 -8	; "getOTAServer"
	18	[183]	CALL     	4 2 2
	19	[183]	MOVE     	5 3
	20	[183]	CONCAT   	4 4 5
	21	[184]	GETUPVAL 	5 0	; ota_dir
	22	[184]	MOVE     	6 3
	23	[184]	CONCAT   	5 5 6
	24	[186]	GETUPVAL 	6 1	; logger
	25	[186]	GETTABLE 	6 6 -9	; "dbg"
	26	[186]	LOADK    	7 -10	; "downloading update file"
	27	[186]	MOVE     	8 4
	28	[186]	CALL     	6 3 1
	29	[187]	GETTABLE 	6 1 -11	; "request"
	30	[187]	NEWTABLE 	7 0 2
	31	[188]	SETTABLE 	7 -12 4	; "url" -
	32	[189]	GETTABLE 	8 2 -13	; "sink"
	33	[189]	GETTABLE 	8 8 -14	; "file"
	34	[189]	GETGLOBAL	9 -15	; io
	35	[189]	GETTABLE 	9 9 -16	; "open"
	36	[189]	MOVE     	10 5
	37	[189]	LOADK    	11 -17	; "w"
	38	[189]	CALL     	9 3 0
	39	[189]	CALL     	8 0 2
	40	[189]	SETTABLE 	7 -13 8	; "sink" -
	41	[187]	CALL     	6 2 4
	42	[190]	EQ       	1 7 -18	; - 200
	43	[190]	JMP      	6	; to 50
	44	[191]	GETUPVAL 	9 1	; logger
	45	[191]	GETTABLE 	9 9 -19	; "warn"
	46	[191]	LOADK    	10 -20	; "cannot find update file"
	47	[191]	MOVE     	11 7
	48	[191]	CALL     	9 3 1
	49	[192]	RETURN   	0 1
	50	[195]	LOADNIL  	9 10
	51	[196]	GETGLOBAL	11 -15	; io
	52	[196]	GETTABLE 	11 11 -16	; "open"
	53	[196]	MOVE     	12 5
	54	[196]	LOADK    	13 -21	; "r"
	55	[196]	CALL     	11 3 2
	56	[197]	TEST     	11 0 0
	57	[197]	JMP      	34	; to 92
	58	[198]	GETUPVAL 	12 2	; OTAManager
	59	[198]	SELF     	12 12 -4	; "getOTAType"
	60	[198]	CALL     	12 2 2
	61	[198]	EQ       	0 12 -5	; - "link"
	62	[198]	JMP      	15	; to 78
	63	[199]	LOADK    	12 -22	; 0
	64	[200]	SELF     	13 11 -23	; "lines"
	65	[200]	CALL     	13 2 4
	66	[200]	JMP      	8	; to 75
	67	[201]	ADD      	12 12 -24	; - 1
	68	[202]	EQ       	0 12 -24	; - 1
	69	[202]	JMP      	5	; to 75
	70	[203]	MOVE     	10 16
	71	[204]	SELF     	17 0 -8	; "getOTAServer"
	72	[204]	CALL     	17 2 2
	73	[204]	MOVE     	18 10
	74	[204]	CONCAT   	9 17 18
	75	[200]	TFORLOOP 	13 1
	76	[205]	JMP      	-10	; to 67
	77	[206]	JMP      	12	; to 90
	78	[208]	SELF     	12 11 -23	; "lines"
	79	[208]	CALL     	12 2 4
	80	[208]	JMP      	7	; to 88
	81	[209]	SELF     	16 15 -25	; "match"
	82	[209]	LOADK    	18 -26	; "^Filename:%s*(.-)%s*$"
	83	[209]	CALL     	16 3 2
	84	[209]	MOVE     	10 16
	85	[210]	TEST     	10 0 0
	86	[210]	JMP      	1	; to 88
	87	[210]	JMP      	2	; to 90
	88	[208]	TFORLOOP 	12 1
	89	[210]	JMP      	-9	; to 81
	90	[213]	SELF     	12 11 -27	; "close"
	91	[213]	CALL     	12 2 1
	92	[215]	GETGLOBAL	12 -28	; pcall
	93	[218]	CLOSURE  	13 0	; 0x7f8a35c0bef0
	94	[218]	GETUPVAL 	0 3	; Version
	95	[215]	CALL     	12 2 3
	96	[219]	GETGLOBAL	14 -28	; pcall
	97	[221]	CLOSURE  	15 1	; 0x7f8a35c0bde0
	98	[221]	GETUPVAL 	0 3	; Version
	99	[221]	MOVE     	0 10
	100	[219]	CALL     	14 2 3
	101	[224]	TEST     	12 0 0
	102	[224]	JMP      	14	; to 117
	103	[224]	TEST     	14 0 0
	104	[224]	JMP      	12	; to 117
	105	[224]	TEST     	15 0 0
	106	[224]	JMP      	10	; to 117
	107	[224]	TEST     	13 0 0
	108	[224]	JMP      	8	; to 117
	109	[225]	EQ       	1 15 13
	110	[225]	JMP      	6	; to 117
	111	[226]	MOVE     	16 15
	112	[226]	MOVE     	17 13
	113	[226]	MOVE     	18 9
	114	[226]	MOVE     	19 10
	115	[226]	RETURN   	16 5
	116	[226]	JMP      	6	; to 123
	117	[227]	TEST     	15 0 0
	118	[227]	JMP      	4	; to 123
	119	[227]	EQ       	0 15 13
	120	[227]	JMP      	2	; to 123
	121	[228]	LOADK    	16 -22	; 0
	122	[228]	RETURN   	16 2
	123	[230]	RETURN   	0 1

function <./frontend/ui/otamanager.lua:215,218> (11 instructions, 44 bytes at 0x7f8a35c0bef0)
0 params, 4 slots, 1 upvalue, 1 local, 2 constants, 0 functions
	1	[216]	GETUPVAL 	0 0	; Version
	2	[216]	SELF     	0 0 -1	; "getCurrentRevision"
	3	[216]	CALL     	0 2 2
	4	[217]	TEST     	0 0 0
	5	[217]	JMP      	5	; to 11
	6	[217]	GETUPVAL 	1 0	; Version
	7	[217]	SELF     	1 1 -2	; "getNormalizedVersion"
	8	[217]	MOVE     	3 0
	9	[217]	TAILCALL 	1 3 0
	10	[217]	RETURN   	1 0
	11	[218]	RETURN   	0 1

function <./frontend/ui/otamanager.lua:219,221> (6 instructions, 24 bytes at 0x7f8a35c0bde0)
0 params, 3 slots, 2 upvalues, 0 locals, 1 constant, 0 functions
	1	[220]	GETUPVAL 	0 0	; Version
	2	[220]	SELF     	0 0 -1	; "getNormalizedVersion"
	3	[220]	GETUPVAL 	2 1	; ota_package
	4	[220]	TAILCALL 	0 3 0
	5	[220]	RETURN   	0 0
	6	[221]	RETURN   	0 1

function <./frontend/ui/otamanager.lua:232,350> (122 instructions, 488 bytes at 0x7f8a35c0c870)
1 param, 14 slots, 12 upvalues, 8 locals, 18 constants, 2 functions
	1	[233]	GETUPVAL 	1 0	; OTAManager
	2	[233]	SELF     	1 1 -1	; "checkUpdate"
	3	[233]	CALL     	1 2 5
	4	[235]	EQ       	0 1 -2	; - 0
	5	[235]	JMP      	12	; to 18
	6	[236]	GETUPVAL 	5 1	; UIManager
	7	[236]	SELF     	5 5 -3	; "show"
	8	[236]	GETUPVAL 	7 2	; InfoMessage
	9	[236]	SELF     	7 7 -4	; "new"
	10	[236]	NEWTABLE 	9 0 1
	11	[237]	GETUPVAL 	10 3	; _
	12	[237]	LOADK    	11 -6	; "KOReader is up to date."
	13	[237]	CALL     	10 2 2
	14	[237]	SETTABLE 	9 -5 10	; "text" -
	15	[236]	CALL     	7 3 0
	16	[236]	CALL     	5 0 1
	17	[238]	JMP      	104	; to 122
	18	[239]	EQ       	0 1 -7	; - nil
	19	[239]	JMP      	20	; to 40
	20	[240]	GETUPVAL 	5 4	; ota_channels
	21	[240]	GETUPVAL 	6 0	; OTAManager
	22	[240]	SELF     	6 6 -8	; "getOTAChannel"
	23	[240]	CALL     	6 2 2
	24	[240]	GETTABLE 	5 5 6
	25	[241]	GETUPVAL 	6 1	; UIManager
	26	[241]	SELF     	6 6 -3	; "show"
	27	[241]	GETUPVAL 	8 2	; InfoMessage
	28	[241]	SELF     	8 8 -4	; "new"
	29	[241]	NEWTABLE 	10 0 1
	30	[242]	GETUPVAL 	11 5	; T
	31	[242]	GETUPVAL 	12 3	; _
	32	[242]	LOADK    	13 -9	; "Update information not available on %1 channel."
	33	[242]	CALL     	12 2 2
	34	[242]	MOVE     	13 5
	35	[242]	CALL     	11 3 2
	36	[242]	SETTABLE 	10 -5 11	; "text" -
	37	[241]	CALL     	8 3 0
	38	[241]	CALL     	6 0 1
	39	[243]	JMP      	82	; to 122
	40	[244]	TEST     	1 0 0
	41	[244]	JMP      	80	; to 122
	42	[245]	GETUPVAL 	5 5	; T
	43	[245]	GETUPVAL 	6 3	; _
	44	[245]	LOADK    	7 -10	; "Do you want to update?\nInstalled version: %1\nAvailable version: %2"
	45	[245]	CALL     	6 2 2
	46	[246]	GETUPVAL 	7 6	; BD
	47	[246]	GETTABLE 	7 7 -11	; "ltr"
	48	[246]	MOVE     	8 2
	49	[246]	CALL     	7 2 2
	50	[247]	GETUPVAL 	8 6	; BD
	51	[247]	GETTABLE 	8 8 -11	; "ltr"
	52	[247]	MOVE     	9 1
	53	[247]	CALL     	8 2 0
	54	[245]	CALL     	5 0 2
	55	[248]	GETUPVAL 	6 3	; _
	56	[248]	LOADK    	7 -12	; "Update"
	57	[248]	CALL     	6 2 2
	58	[249]	LT       	0 1 2
	59	[249]	JMP      	18	; to 78
	60	[250]	GETUPVAL 	7 5	; T
	61	[250]	GETUPVAL 	8 3	; _
	62	[250]	LOADK    	9 -13	; "The currently installed version is newer than the available version.\nWould you still like to continue and downgrade?\nInstalled version: %1\nAvailable version: %2"
	63	[250]	CALL     	8 2 2
	64	[251]	GETUPVAL 	9 6	; BD
	65	[251]	GETTABLE 	9 9 -11	; "ltr"
	66	[251]	MOVE     	10 2
	67	[251]	CALL     	9 2 2
	68	[252]	GETUPVAL 	10 6	; BD
	69	[252]	GETTABLE 	10 10 -11	; "ltr"
	70	[252]	MOVE     	11 1
	71	[252]	CALL     	10 2 0
	72	[250]	CALL     	7 0 2
	73	[252]	MOVE     	5 7
	74	[253]	GETUPVAL 	7 3	; _
	75	[253]	LOADK    	8 -14	; "Downgrade"
	76	[253]	CALL     	7 2 2
	77	[253]	MOVE     	6 7
	78	[256]	GETUPVAL 	7 0	; OTAManager
	79	[256]	SELF     	7 7 -15	; "getOTAType"
	80	[256]	CALL     	7 2 2
	81	[256]	EQ       	0 7 -16	; - "link"
	82	[256]	JMP      	19	; to 102
	83	[257]	GETUPVAL 	7 1	; UIManager
	84	[257]	SELF     	7 7 -3	; "show"
	85	[257]	GETUPVAL 	9 7	; ConfirmBox
	86	[257]	SELF     	9 9 -4	; "new"
	87	[257]	NEWTABLE 	11 0 3
	88	[258]	SETTABLE 	11 -5 5	; "text" -
	89	[259]	SETTABLE 	11 -17 6	; "ok_text" -
	90	[279]	CLOSURE  	12 0	; 0x7f8a35c0ceb0
	91	[279]	MOVE     	0 3
	92	[279]	MOVE     	0 4
	93	[279]	GETUPVAL 	0 5	; T
	94	[279]	GETUPVAL 	0 3	; _
	95	[279]	GETUPVAL 	0 1	; UIManager
	96	[279]	GETUPVAL 	0 7	; ConfirmBox
	97	[279]	GETUPVAL 	0 8	; Device
	98	[279]	SETTABLE 	11 -18 12	; "ok_callback" -
	99	[257]	CALL     	9 3 0
	100	[257]	CALL     	7 0 1
	101	[280]	JMP      	20	; to 122
	102	[282]	GETUPVAL 	7 1	; UIManager
	103	[282]	SELF     	7 7 -3	; "show"
	104	[282]	GETUPVAL 	9 7	; ConfirmBox
	105	[282]	SELF     	9 9 -4	; "new"
	106	[282]	NEWTABLE 	11 0 3
	107	[283]	SETTABLE 	11 -5 5	; "text" -
	108	[284]	SETTABLE 	11 -17 6	; "ok_text" -
	109	[346]	CLOSURE  	12 1	; 0x7f8a35c09da0
	110	[346]	GETUPVAL 	0 1	; UIManager
	111	[346]	GETUPVAL 	0 2	; InfoMessage
	112	[346]	GETUPVAL 	0 3	; _
	113	[346]	GETUPVAL 	0 0	; OTAManager
	114	[346]	GETUPVAL 	0 9	; showRestartMessage
	115	[346]	MOVE     	0 0
	116	[346]	GETUPVAL 	0 10	; MultiConfirmBox
	117	[346]	GETUPVAL 	0 7	; ConfirmBox
	118	[346]	GETUPVAL 	0 11	; ota_dir
	119	[346]	SETTABLE 	11 -18 12	; "ok_callback" -
	120	[282]	CALL     	9 3 0
	121	[282]	CALL     	7 0 1
	122	[350]	RETURN   	0 1

function <./frontend/ui/otamanager.lua:260,279> (62 instructions, 248 bytes at 0x7f8a35c0ceb0)
0 params, 10 slots, 7 upvalues, 3 locals, 18 constants, 1 function
	1	[261]	GETGLOBAL	0 -1	; pcall
	2	[261]	GETGLOBAL	1 -2	; require
	3	[261]	LOADK    	2 -3	; "android"
	4	[261]	CALL     	0 3 3
	5	[262]	TEST     	0 0 0
	6	[262]	JMP      	46	; to 53
	7	[264]	GETTABLE 	2 1 -4	; "download"
	8	[264]	GETUPVAL 	3 0	; link
	9	[264]	GETUPVAL 	4 1	; ota_package
	10	[264]	CALL     	2 3 2
	11	[265]	EQ       	0 2 -5	; - 1
	12	[265]	JMP      	9	; to 22
	13	[266]	GETTABLE 	3 1 -6	; "notification"
	14	[266]	GETUPVAL 	4 2	; T
	15	[266]	GETUPVAL 	5 3	; _
	16	[266]	LOADK    	6 -7	; "The file %1 already exists."
	17	[266]	CALL     	5 2 2
	18	[266]	GETUPVAL 	6 1	; ota_package
	19	[266]	CALL     	4 3 0
	20	[266]	CALL     	3 0 1
	21	[266]	JMP      	40	; to 62
	22	[267]	EQ       	0 2 -8	; - 0
	23	[267]	JMP      	9	; to 33
	24	[268]	GETTABLE 	3 1 -6	; "notification"
	25	[268]	GETUPVAL 	4 2	; T
	26	[268]	GETUPVAL 	5 3	; _
	27	[268]	LOADK    	6 -9	; "Downloading %1"
	28	[268]	CALL     	5 2 2
	29	[268]	GETUPVAL 	6 1	; ota_package
	30	[268]	CALL     	4 3 0
	31	[268]	CALL     	3 0 1
	32	[268]	JMP      	29	; to 62
	33	[270]	GETUPVAL 	3 4	; UIManager
	34	[270]	SELF     	3 3 -10	; "show"
	35	[270]	GETUPVAL 	5 5	; ConfirmBox
	36	[270]	SELF     	5 5 -11	; "new"
	37	[270]	NEWTABLE 	7 0 3
	38	[271]	GETUPVAL 	8 3	; _
	39	[271]	LOADK    	9 -13	; "Your device seems to be unable to download packages.\nRetry using the browser?"
	40	[271]	CALL     	8 2 2
	41	[271]	SETTABLE 	7 -12 8	; "text" -
	42	[272]	GETUPVAL 	8 3	; _
	43	[272]	LOADK    	9 -15	; "Retry"
	44	[272]	CALL     	8 2 2
	45	[272]	SETTABLE 	7 -14 8	; "ok_text" -
	46	[273]	CLOSURE  	8 0	; 0x7f8a35c0d310
	47	[273]	GETUPVAL 	0 6	; Device
	48	[273]	GETUPVAL 	0 0	; link
	49	[273]	SETTABLE 	7 -16 8	; "ok_callback" -
	50	[270]	CALL     	5 3 0
	51	[270]	CALL     	3 0 1
	52	[275]	JMP      	9	; to 62
	53	[276]	GETUPVAL 	2 6	; Device
	54	[276]	SELF     	2 2 -17	; "isSDL"
	55	[276]	CALL     	2 2 2
	56	[276]	TEST     	2 0 0
	57	[276]	JMP      	4	; to 62
	58	[277]	GETUPVAL 	2 6	; Device
	59	[277]	SELF     	2 2 -18	; "openLink"
	60	[277]	GETUPVAL 	4 0	; link
	61	[277]	CALL     	2 3 1
	62	[279]	RETURN   	0 1

function <./frontend/ui/otamanager.lua:273,273> (5 instructions, 20 bytes at 0x7f8a35c0d310)
0 params, 3 slots, 2 upvalues, 0 locals, 1 constant, 0 functions
	1	[273]	GETUPVAL 	0 0	; Device
	2	[273]	SELF     	0 0 -1	; "openLink"
	3	[273]	GETUPVAL 	2 1	; link
	4	[273]	CALL     	0 3 1
	5	[273]	RETURN   	0 1

function <./frontend/ui/otamanager.lua:285,346> (27 instructions, 108 bytes at 0x7f8a35c09da0)
0 params, 7 slots, 9 upvalues, 0 locals, 8 constants, 1 function
	1	[286]	GETUPVAL 	0 0	; UIManager
	2	[286]	SELF     	0 0 -1	; "show"
	3	[286]	GETUPVAL 	2 1	; InfoMessage
	4	[286]	SELF     	2 2 -2	; "new"
	5	[286]	NEWTABLE 	4 0 2
	6	[287]	GETUPVAL 	5 2	; _
	7	[287]	LOADK    	6 -4	; "Downloading may take several minutes\226\128\166"
	8	[287]	CALL     	5 2 2
	9	[287]	SETTABLE 	4 -3 5	; "text" -
	10	[288]	SETTABLE 	4 -5 -6	; "timeout" 3
	11	[286]	CALL     	2 3 0
	12	[286]	CALL     	0 0 1
	13	[290]	GETUPVAL 	0 0	; UIManager
	14	[290]	SELF     	0 0 -7	; "scheduleIn"
	15	[290]	LOADK    	2 -8	; 1
	16	[345]	CLOSURE  	3 0	; 0x7f8a35c0b490
	17	[345]	GETUPVAL 	0 3	; OTAManager
	18	[345]	GETUPVAL 	0 4	; showRestartMessage
	19	[345]	GETUPVAL 	0 5	; self
	20	[345]	GETUPVAL 	0 0	; UIManager
	21	[345]	GETUPVAL 	0 6	; MultiConfirmBox
	22	[345]	GETUPVAL 	0 2	; _
	23	[345]	GETUPVAL 	0 1	; InfoMessage
	24	[345]	GETUPVAL 	0 7	; ConfirmBox
	25	[345]	GETUPVAL 	0 8	; ota_dir
	26	[290]	CALL     	0 4 1
	27	[346]	RETURN   	0 1

function <./frontend/ui/otamanager.lua:290,345> (58 instructions, 232 bytes at 0x7f8a35c0b490)
0 params, 7 slots, 9 upvalues, 0 locals, 16 constants, 2 functions
	1	[291]	GETUPVAL 	0 0	; OTAManager
	2	[291]	SELF     	0 0 -1	; "zsync"
	3	[291]	CALL     	0 2 2
	4	[291]	EQ       	0 0 -2	; - 0
	5	[291]	JMP      	11	; to 17
	6	[292]	GETUPVAL 	0 1	; showRestartMessage
	7	[292]	CALL     	0 1 1
	8	[294]	GETUPVAL 	0 2	; self
	9	[294]	GETTABLE 	0 0 -3	; "can_pretty_print"
	10	[294]	TEST     	0 0 0
	11	[294]	JMP      	46	; to 58
	12	[295]	GETGLOBAL	0 -4	; os
	13	[295]	GETTABLE 	0 0 -5	; "execute"
	14	[295]	LOADK    	1 -6	; "./fbink -q -y -7 -pm ' '  ' '"
	15	[295]	CALL     	0 2 1
	16	[296]	JMP      	41	; to 58
	17	[299]	GETUPVAL 	0 2	; self
	18	[299]	GETTABLE 	0 0 -3	; "can_pretty_print"
	19	[299]	TEST     	0 0 0
	20	[299]	JMP      	4	; to 25
	21	[300]	GETGLOBAL	0 -4	; os
	22	[300]	GETTABLE 	0 0 -5	; "execute"
	23	[300]	LOADK    	1 -6	; "./fbink -q -y -7 -pm ' '  ' '"
	24	[300]	CALL     	0 2 1
	25	[302]	GETUPVAL 	0 3	; UIManager
	26	[302]	SELF     	0 0 -7	; "show"
	27	[302]	GETUPVAL 	2 4	; MultiConfirmBox
	28	[302]	SELF     	2 2 -8	; "new"
	29	[302]	NEWTABLE 	4 0 5
	30	[303]	GETUPVAL 	5 5	; _
	31	[303]	LOADK    	6 -10	; "Failed to update KOReader.\n\nYou can:\nCancel, keeping temporary files.\nRetry the update process with a full download.\nAbort and cleanup all temporary files."
	32	[303]	CALL     	5 2 2
	33	[303]	SETTABLE 	4 -9 5	; "text" -
	34	[304]	GETUPVAL 	5 5	; _
	35	[304]	LOADK    	6 -12	; "Retry"
	36	[304]	CALL     	5 2 2
	37	[304]	SETTABLE 	4 -11 5	; "choice1_text" -
	38	[336]	CLOSURE  	5 0	; 0x7f8a35c07ec0
	39	[336]	GETUPVAL 	0 3	; UIManager
	40	[336]	GETUPVAL 	0 6	; InfoMessage
	41	[336]	GETUPVAL 	0 5	; _
	42	[336]	GETUPVAL 	0 2	; self
	43	[336]	GETUPVAL 	0 0	; OTAManager
	44	[336]	GETUPVAL 	0 1	; showRestartMessage
	45	[336]	GETUPVAL 	0 7	; ConfirmBox
	46	[336]	GETUPVAL 	0 8	; ota_dir
	47	[336]	SETTABLE 	4 -13 5	; "choice1_callback" -
	48	[337]	GETUPVAL 	5 5	; _
	49	[337]	LOADK    	6 -15	; "Abort"
	50	[337]	CALL     	5 2 2
	51	[337]	SETTABLE 	4 -14 5	; "choice2_text" -
	52	[342]	CLOSURE  	5 1	; 0x7f8a35c0dc30
	53	[342]	GETUPVAL 	0 8	; ota_dir
	54	[342]	GETUPVAL 	0 2	; self
	55	[342]	SETTABLE 	4 -16 5	; "choice2_callback" -
	56	[302]	CALL     	2 3 0
	57	[302]	CALL     	0 0 1
	58	[345]	RETURN   	0 1

function <./frontend/ui/otamanager.lua:305,336> (44 instructions, 176 bytes at 0x7f8a35c07ec0)
0 params, 7 slots, 8 upvalues, 0 locals, 15 constants, 1 function
	1	[306]	GETUPVAL 	0 0	; UIManager
	2	[306]	SELF     	0 0 -1	; "show"
	3	[306]	GETUPVAL 	2 1	; InfoMessage
	4	[306]	SELF     	2 2 -2	; "new"
	5	[306]	NEWTABLE 	4 0 2
	6	[307]	GETUPVAL 	5 2	; _
	7	[307]	LOADK    	6 -4	; "Downloading may take several minutes\226\128\166"
	8	[307]	CALL     	5 2 2
	9	[307]	SETTABLE 	4 -3 5	; "text" -
	10	[308]	SETTABLE 	4 -5 -6	; "timeout" 3
	11	[306]	CALL     	2 3 0
	12	[306]	CALL     	0 0 1
	13	[311]	GETGLOBAL	0 -7	; os
	14	[311]	GETTABLE 	0 0 -8	; "execute"
	15	[311]	LOADK    	1 -9	; "rm -f "
	16	[311]	GETUPVAL 	2 3	; self
	17	[311]	GETTABLE 	2 2 -10	; "installed_package"
	18	[311]	CONCAT   	1 1 2
	19	[311]	CALL     	0 2 1
	20	[312]	GETGLOBAL	0 -7	; os
	21	[312]	GETTABLE 	0 0 -8	; "execute"
	22	[312]	LOADK    	1 -9	; "rm -f "
	23	[312]	GETUPVAL 	2 3	; self
	24	[312]	GETTABLE 	2 2 -11	; "updated_package"
	25	[312]	LOADK    	3 -12	; "*"
	26	[312]	CONCAT   	1 1 3
	27	[312]	CALL     	0 2 1
	28	[314]	GETGLOBAL	0 -7	; os
	29	[314]	GETTABLE 	0 0 -8	; "execute"
	30	[314]	LOADK    	1 -13	; "rm -f ./rcksum-*"
	31	[314]	CALL     	0 2 1
	32	[316]	GETUPVAL 	0 0	; UIManager
	33	[316]	SELF     	0 0 -14	; "scheduleIn"
	34	[316]	LOADK    	2 -15	; 1
	35	[335]	CLOSURE  	3 0	; 0x7f8a35c0af00
	36	[335]	GETUPVAL 	0 4	; OTAManager
	37	[335]	GETUPVAL 	0 5	; showRestartMessage
	38	[335]	GETUPVAL 	0 3	; self
	39	[335]	GETUPVAL 	0 0	; UIManager
	40	[335]	GETUPVAL 	0 6	; ConfirmBox
	41	[335]	GETUPVAL 	0 2	; _
	42	[335]	GETUPVAL 	0 7	; ota_dir
	43	[316]	CALL     	0 4 1
	44	[336]	RETURN   	0 1

function <./frontend/ui/otamanager.lua:316,335> (40 instructions, 160 bytes at 0x7f8a35c0af00)
0 params, 7 slots, 7 upvalues, 0 locals, 11 constants, 1 function
	1	[317]	GETUPVAL 	0 0	; OTAManager
	2	[317]	SELF     	0 0 -1	; "zsync"
	3	[317]	LOADBOOL 	2 1 0
	4	[317]	CALL     	0 3 2
	5	[317]	EQ       	0 0 -2	; - 0
	6	[317]	JMP      	11	; to 18
	7	[318]	GETUPVAL 	0 1	; showRestartMessage
	8	[318]	CALL     	0 1 1
	9	[320]	GETUPVAL 	0 2	; self
	10	[320]	GETTABLE 	0 0 -3	; "can_pretty_print"
	11	[320]	TEST     	0 0 0
	12	[320]	JMP      	27	; to 40
	13	[321]	GETGLOBAL	0 -4	; os
	14	[321]	GETTABLE 	0 0 -5	; "execute"
	15	[321]	LOADK    	1 -6	; "./fbink -q -y -7 -pm ' '  ' '"
	16	[321]	CALL     	0 2 1
	17	[322]	JMP      	22	; to 40
	18	[325]	GETUPVAL 	0 2	; self
	19	[325]	GETTABLE 	0 0 -3	; "can_pretty_print"
	20	[325]	TEST     	0 0 0
	21	[325]	JMP      	4	; to 26
	22	[326]	GETGLOBAL	0 -4	; os
	23	[326]	GETTABLE 	0 0 -5	; "execute"
	24	[326]	LOADK    	1 -6	; "./fbink -q -y -7 -pm ' '  ' '"
	25	[326]	CALL     	0 2 1
	26	[328]	GETUPVAL 	0 3	; UIManager
	27	[328]	SELF     	0 0 -7	; "show"
	28	[328]	GETUPVAL 	2 4	; ConfirmBox
	29	[328]	SELF     	2 2 -8	; "new"
	30	[328]	NEWTABLE 	4 0 2
	31	[329]	GETUPVAL 	5 5	; _
	32	[329]	LOADK    	6 -10	; "Error updating KOReader. Would you like to delete temporary files?"
	33	[329]	CALL     	5 2 2
	34	[329]	SETTABLE 	4 -9 5	; "text" -
	35	[332]	CLOSURE  	5 0	; 0x7f8a35c07e30
	36	[332]	GETUPVAL 	0 6	; ota_dir
	37	[332]	SETTABLE 	4 -11 5	; "ok_callback" -
	38	[328]	CALL     	2 3 0
	39	[328]	CALL     	0 0 1
	40	[335]	RETURN   	0 1

function <./frontend/ui/otamanager.lua:330,332> (8 instructions, 32 bytes at 0x7f8a35c07e30)
0 params, 4 slots, 1 upvalue, 0 locals, 4 constants, 0 functions
	1	[331]	GETGLOBAL	0 -1	; os
	2	[331]	GETTABLE 	0 0 -2	; "execute"
	3	[331]	LOADK    	1 -3	; "rm -f "
	4	[331]	GETUPVAL 	2 0	; ota_dir
	5	[331]	LOADK    	3 -4	; "ko*"
	6	[331]	CONCAT   	1 1 3
	7	[331]	CALL     	0 2 1
	8	[332]	RETURN   	0 1

function <./frontend/ui/otamanager.lua:338,342> (20 instructions, 80 bytes at 0x7f8a35c0dc30)
0 params, 4 slots, 2 upvalues, 0 locals, 7 constants, 0 functions
	1	[339]	GETGLOBAL	0 -1	; os
	2	[339]	GETTABLE 	0 0 -2	; "execute"
	3	[339]	LOADK    	1 -3	; "rm -f "
	4	[339]	GETUPVAL 	2 0	; ota_dir
	5	[339]	LOADK    	3 -4	; "ko*"
	6	[339]	CONCAT   	1 1 3
	7	[339]	CALL     	0 2 1
	8	[340]	GETGLOBAL	0 -1	; os
	9	[340]	GETTABLE 	0 0 -2	; "execute"
	10	[340]	LOADK    	1 -3	; "rm -f "
	11	[340]	GETUPVAL 	2 1	; self
	12	[340]	GETTABLE 	2 2 -5	; "updated_package"
	13	[340]	LOADK    	3 -6	; "*"
	14	[340]	CONCAT   	1 1 3
	15	[340]	CALL     	0 2 1
	16	[341]	GETGLOBAL	0 -1	; os
	17	[341]	GETTABLE 	0 0 -2	; "execute"
	18	[341]	LOADK    	1 -7	; "rm -f ./rcksum-*"
	19	[341]	CALL     	0 2 1
	20	[342]	RETURN   	0 1

function <./frontend/ui/otamanager.lua:353,397> (87 instructions, 348 bytes at 0x7f8a35c0e0e0)
1 param, 15 slots, 3 upvalues, 12 locals, 27 constants, 0 functions
	1	[355]	GETTABLE 	1 0 -1	; "installed_package"
	2	[356]	GETUPVAL 	2 0	; lfs
	3	[356]	GETTABLE 	2 2 -2	; "attributes"
	4	[356]	MOVE     	3 1
	5	[356]	LOADK    	4 -3	; "mode"
	6	[356]	CALL     	2 3 2
	7	[356]	EQ       	0 2 -4	; - "file"
	8	[356]	JMP      	2	; to 11
	9	[357]	LOADK    	2 -5	; 0
	10	[357]	RETURN   	2 2
	11	[359]	GETUPVAL 	2 0	; lfs
	12	[359]	GETTABLE 	2 2 -2	; "attributes"
	13	[359]	GETTABLE 	3 0 -6	; "package_indexfile"
	14	[359]	LOADK    	4 -3	; "mode"
	15	[359]	CALL     	2 3 2
	16	[359]	EQ       	1 2 -4	; - "file"
	17	[359]	JMP      	7	; to 25
	18	[360]	GETUPVAL 	2 1	; logger
	19	[360]	GETTABLE 	2 2 -7	; "err"
	20	[360]	LOADK    	3 -8	; "Missing ota metadata:"
	21	[360]	GETTABLE 	4 0 -6	; "package_indexfile"
	22	[360]	CALL     	2 3 1
	23	[361]	LOADNIL  	2 2
	24	[361]	RETURN   	2 2
	25	[365]	GETTABLE 	2 0 -9	; "can_pretty_print"
	26	[365]	TEST     	2 0 0
	27	[365]	JMP      	49	; to 77
	28	[366]	GETGLOBAL	2 -10	; os
	29	[366]	GETTABLE 	2 2 -11	; "execute"
	30	[366]	LOADK    	3 -12	; "./fbink -q -y -7 -pmh 'Preparing local OTA package'"
	31	[366]	CALL     	2 2 1
	32	[369]	SELF     	2 0 -13	; "getZsyncFilename"
	33	[369]	CALL     	2 2 2
	34	[370]	GETUPVAL 	3 2	; ota_dir
	35	[370]	MOVE     	4 2
	36	[370]	CONCAT   	3 3 4
	37	[371]	LOADNIL  	4 4
	38	[372]	GETGLOBAL	5 -14	; io
	39	[372]	GETTABLE 	5 5 -15	; "open"
	40	[372]	MOVE     	6 3
	41	[372]	LOADK    	7 -16	; "r"
	42	[372]	CALL     	5 3 2
	43	[373]	TEST     	5 0 0
	44	[373]	JMP      	14	; to 59
	45	[374]	SELF     	6 5 -17	; "lines"
	46	[374]	CALL     	6 2 4
	47	[374]	JMP      	7	; to 55
	48	[375]	SELF     	10 9 -18	; "match"
	49	[375]	LOADK    	12 -19	; "^Length: (%d*)$"
	50	[375]	CALL     	10 3 2
	51	[375]	MOVE     	4 10
	52	[376]	TEST     	4 0 0
	53	[376]	JMP      	1	; to 55
	54	[376]	JMP      	2	; to 57
	55	[374]	TFORLOOP 	6 1
	56	[376]	JMP      	-9	; to 48
	57	[378]	SELF     	6 5 -20	; "close"
	58	[378]	CALL     	6 2 1
	59	[383]	LOADK    	6 -21	; 6405
	60	[384]	TEST     	4 0 0
	61	[384]	JMP      	1	; to 63
	62	[385]	DIV      	6 4 -22	; - 10240
	63	[388]	DIV      	7 6 -23	; - 100
	64	[389]	GETGLOBAL	8 -10	; os
	65	[389]	GETTABLE 	8 8 -11	; "execute"
	66	[389]	GETGLOBAL	9 -24	; string
	67	[389]	GETTABLE 	9 9 -25	; "format"
	68	[390]	LOADK    	10 -26	; "./tar --no-recursion -cf %s -C .. -T %s --checkpoint=%d --checkpoint-action=exec='./fbink -q -y -6 -P $(($TAR_CHECKPOINT/%d))'"
	69	[391]	GETTABLE 	11 0 -1	; "installed_package"
	70	[391]	GETTABLE 	12 0 -6	; "package_indexfile"
	71	[391]	MOVE     	13 7
	72	[391]	MOVE     	14 7
	73	[389]	CALL     	9 6 0
	74	[389]	TAILCALL 	8 0 0
	75	[391]	RETURN   	8 0
	76	[391]	JMP      	10	; to 87
	77	[393]	GETGLOBAL	2 -10	; os
	78	[393]	GETTABLE 	2 2 -11	; "execute"
	79	[393]	GETGLOBAL	3 -24	; string
	80	[393]	GETTABLE 	3 3 -25	; "format"
	81	[394]	LOADK    	4 -27	; "./tar --no-recursion -cf %s -C .. -T %s"
	82	[395]	GETTABLE 	5 0 -1	; "installed_package"
	83	[395]	GETTABLE 	6 0 -6	; "package_indexfile"
	84	[393]	CALL     	3 4 0
	85	[393]	TAILCALL 	2 0 0
	86	[395]	RETURN   	2 0
	87	[397]	RETURN   	0 1

function <./frontend/ui/otamanager.lua:399,437> (55 instructions, 220 bytes at 0x7f8a35c076a0)
2 params, 15 slots, 1 upvalue, 4 locals, 15 constants, 0 functions
	1	[400]	TEST     	1 0 1
	2	[400]	JMP      	4	; to 7
	3	[400]	SELF     	2 0 -1	; "_buildLocalPackage"
	4	[400]	CALL     	2 2 2
	5	[400]	EQ       	0 2 -2	; - 0
	6	[400]	JMP      	48	; to 55
	7	[401]	LOADK    	2 -3	; "zsync2"
	8	[402]	LOADBOOL 	3 1 0
	9	[404]	GETTABLE 	4 0 -4	; "can_pretty_print"
	10	[404]	TEST     	4 0 0
	11	[404]	JMP      	9	; to 21
	12	[405]	LOADK    	2 -5	; "spinning_zsync"
	13	[411]	GETGLOBAL	4 -6	; os
	14	[411]	GETTABLE 	4 4 -7	; "execute"
	15	[411]	LOADK    	5 -8	; "set -o pipefail 2>/dev/null"
	16	[411]	CALL     	4 2 2
	17	[411]	EQ       	1 4 -2	; - 0
	18	[411]	JMP      	1	; to 20
	19	[411]	LOADBOOL 	3 0 1
	20	[411]	LOADBOOL 	3 1 0
	21	[414]	TEST     	1 0 0
	22	[414]	JMP      	16	; to 39
	23	[415]	GETGLOBAL	4 -6	; os
	24	[415]	GETTABLE 	4 4 -7	; "execute"
	25	[416]	LOADK    	5 -9	; "env WITH_PIPEFAIL='%s' ./%s -o '%s' -u '%s' '%s%s'"
	26	[416]	SELF     	5 5 -10	; "format"
	27	[417]	MOVE     	7 3
	28	[418]	MOVE     	8 2
	29	[419]	GETTABLE 	9 0 -11	; "updated_package"
	30	[420]	SELF     	10 0 -12	; "getOTAServer"
	31	[420]	CALL     	10 2 2
	32	[421]	GETUPVAL 	11 0	; ota_dir
	33	[422]	SELF     	12 0 -13	; "getZsyncFilename"
	34	[422]	CALL     	12 2 0
	35	[416]	CALL     	5 0 0
	36	[415]	TAILCALL 	4 0 0
	37	[423]	RETURN   	4 0
	38	[423]	JMP      	16	; to 55
	39	[425]	GETGLOBAL	4 -6	; os
	40	[425]	GETTABLE 	4 4 -7	; "execute"
	41	[426]	LOADK    	5 -14	; "env WITH_PIPEFAIL='%s' ./%s -i '%s' -o '%s' -u '%s' '%s%s'"
	42	[426]	SELF     	5 5 -10	; "format"
	43	[427]	MOVE     	7 3
	44	[428]	MOVE     	8 2
	45	[429]	GETTABLE 	9 0 -15	; "installed_package"
	46	[430]	GETTABLE 	10 0 -11	; "updated_package"
	47	[431]	SELF     	11 0 -12	; "getOTAServer"
	48	[431]	CALL     	11 2 2
	49	[432]	GETUPVAL 	12 0	; ota_dir
	50	[433]	SELF     	13 0 -13	; "getZsyncFilename"
	51	[433]	CALL     	13 2 0
	52	[426]	CALL     	5 0 0
	53	[425]	TAILCALL 	4 0 0
	54	[434]	RETURN   	4 0
	55	[437]	RETURN   	0 1

function <./frontend/ui/otamanager.lua:439,450> (25 instructions, 100 bytes at 0x7f8a35c0ee50)
1 param, 11 slots, 0 upvalues, 8 locals, 7 constants, 2 functions
	1	[440]	NEWTABLE 	1 0 0
	2	[441]	GETGLOBAL	2 -1	; ipairs
	3	[441]	GETTABLE 	3 0 -2	; "ota_servers"
	4	[441]	CALL     	2 2 4
	5	[441]	JMP      	16	; to 22
	6	[442]	NEWTABLE 	7 0 3
	7	[443]	SETTABLE 	7 -3 6	; "text" -
	8	[444]	CLOSURE  	8 0	; 0x7f8a35c0f2f0
	9	[444]	MOVE     	0 0
	10	[444]	MOVE     	0 6
	11	[444]	SETTABLE 	7 -4 8	; "checked_func" -
	12	[445]	CLOSURE  	8 1	; 0x7f8a35c0f770
	13	[445]	MOVE     	0 0
	14	[445]	MOVE     	0 6
	15	[445]	SETTABLE 	7 -5 8	; "callback" -
	16	[447]	GETGLOBAL	8 -6	; table
	17	[447]	GETTABLE 	8 8 -7	; "insert"
	18	[447]	MOVE     	9 1
	19	[447]	MOVE     	10 7
	20	[447]	CALL     	8 3 1
	21	[447]	CLOSE    	5
	22	[441]	TFORLOOP 	2 2
	23	[447]	JMP      	-18	; to 6
	24	[449]	RETURN   	1 2
	25	[450]	RETURN   	0 1

function <./frontend/ui/otamanager.lua:444,444> (10 instructions, 40 bytes at 0x7f8a35c0f2f0)
0 params, 2 slots, 2 upvalues, 0 locals, 1 constant, 0 functions
	1	[444]	GETUPVAL 	0 0	; self
	2	[444]	SELF     	0 0 -1	; "getOTAServer"
	3	[444]	CALL     	0 2 2
	4	[444]	GETUPVAL 	1 1	; server
	5	[444]	EQ       	1 0 1
	6	[444]	JMP      	1	; to 8
	7	[444]	LOADBOOL 	0 0 1
	8	[444]	LOADBOOL 	0 1 0
	9	[444]	RETURN   	0 2
	10	[444]	RETURN   	0 1

function <./frontend/ui/otamanager.lua:445,445> (5 instructions, 20 bytes at 0x7f8a35c0f770)
0 params, 3 slots, 2 upvalues, 0 locals, 1 constant, 0 functions
	1	[445]	GETUPVAL 	0 0	; self
	2	[445]	SELF     	0 0 -1	; "setOTAServer"
	3	[445]	GETUPVAL 	2 1	; server
	4	[445]	CALL     	0 3 1
	5	[445]	RETURN   	0 1

function <./frontend/ui/otamanager.lua:452,463> (27 instructions, 108 bytes at 0x7f8a35c0f980)
1 param, 11 slots, 1 upvalue, 8 locals, 7 constants, 2 functions
	1	[453]	NEWTABLE 	1 0 0
	2	[454]	GETGLOBAL	2 -1	; ipairs
	3	[454]	GETTABLE 	3 0 -2	; "ota_channels"
	4	[454]	CALL     	2 2 4
	5	[454]	JMP      	18	; to 24
	6	[455]	NEWTABLE 	7 0 3
	7	[456]	GETUPVAL 	8 0	; ota_channels
	8	[456]	GETTABLE 	8 8 6
	9	[456]	SETTABLE 	7 -3 8	; "text" -
	10	[457]	CLOSURE  	8 0	; 0x7f8a35c0fbe0
	11	[457]	MOVE     	0 0
	12	[457]	MOVE     	0 6
	13	[457]	SETTABLE 	7 -4 8	; "checked_func" -
	14	[458]	CLOSURE  	8 1	; 0x7f8a35c0fe50
	15	[458]	MOVE     	0 0
	16	[458]	MOVE     	0 6
	17	[458]	SETTABLE 	7 -5 8	; "callback" -
	18	[460]	GETGLOBAL	8 -6	; table
	19	[460]	GETTABLE 	8 8 -7	; "insert"
	20	[460]	MOVE     	9 1
	21	[460]	MOVE     	10 7
	22	[460]	CALL     	8 3 1
	23	[460]	CLOSE    	5
	24	[454]	TFORLOOP 	2 2
	25	[460]	JMP      	-20	; to 6
	26	[462]	RETURN   	1 2
	27	[463]	RETURN   	0 1

function <./frontend/ui/otamanager.lua:457,457> (10 instructions, 40 bytes at 0x7f8a35c0fbe0)
0 params, 2 slots, 2 upvalues, 0 locals, 1 constant, 0 functions
	1	[457]	GETUPVAL 	0 0	; self
	2	[457]	SELF     	0 0 -1	; "getOTAChannel"
	3	[457]	CALL     	0 2 2
	4	[457]	GETUPVAL 	1 1	; channel
	5	[457]	EQ       	1 0 1
	6	[457]	JMP      	1	; to 8
	7	[457]	LOADBOOL 	0 0 1
	8	[457]	LOADBOOL 	0 1 0
	9	[457]	RETURN   	0 2
	10	[457]	RETURN   	0 1

function <./frontend/ui/otamanager.lua:458,458> (5 instructions, 20 bytes at 0x7f8a35c0fe50)
0 params, 3 slots, 2 upvalues, 0 locals, 1 constant, 0 functions
	1	[458]	GETUPVAL 	0 0	; self
	2	[458]	SELF     	0 0 -1	; "setOTAChannel"
	3	[458]	GETUPVAL 	2 1	; channel
	4	[458]	CALL     	0 3 1
	5	[458]	RETURN   	0 1

function <./frontend/ui/otamanager.lua:465,501> (47 instructions, 188 bytes at 0x7f8a35c10240)
1 param, 10 slots, 3 upvalues, 1 local, 11 constants, 2 functions
	1	[466]	NEWTABLE 	1 0 3
	2	[467]	GETUPVAL 	2 0	; _
	3	[467]	LOADK    	3 -2	; "Update"
	4	[467]	CALL     	2 2 2
	5	[467]	SETTABLE 	1 -1 2	; "text" -
	6	[474]	CLOSURE  	2 0	; 0x7f8a35c10310
	7	[474]	GETUPVAL 	0 1	; NetworkMgr
	8	[474]	GETUPVAL 	0 2	; OTAManager
	9	[474]	SETTABLE 	1 -3 2	; "hold_callback" -
	10	[475]	NEWTABLE 	2 2 0
	11	[475]	NEWTABLE 	3 0 2
	12	[477]	GETUPVAL 	4 0	; _
	13	[477]	LOADK    	5 -5	; "Check for update"
	14	[477]	CALL     	4 2 2
	15	[477]	SETTABLE 	3 -1 4	; "text" -
	16	[484]	CLOSURE  	4 1	; 0x7f8a35c10770
	17	[484]	GETUPVAL 	0 1	; NetworkMgr
	18	[484]	GETUPVAL 	0 2	; OTAManager
	19	[484]	SETTABLE 	3 -6 4	; "callback" -
	20	[485]	NEWTABLE 	4 0 2
	21	[487]	GETUPVAL 	5 0	; _
	22	[487]	LOADK    	6 -7	; "Settings"
	23	[487]	CALL     	5 2 2
	24	[487]	SETTABLE 	4 -1 5	; "text" -
	25	[488]	NEWTABLE 	5 2 0
	26	[488]	NEWTABLE 	6 0 2
	27	[490]	GETUPVAL 	7 0	; _
	28	[490]	LOADK    	8 -8	; "Update server"
	29	[490]	CALL     	7 2 2
	30	[490]	SETTABLE 	6 -1 7	; "text" -
	31	[491]	SELF     	7 0 -9	; "genServerList"
	32	[491]	CALL     	7 2 2
	33	[491]	SETTABLE 	6 -4 7	; "sub_item_table" -
	34	[492]	NEWTABLE 	7 0 2
	35	[494]	GETUPVAL 	8 0	; _
	36	[494]	LOADK    	9 -10	; "Update channel"
	37	[494]	CALL     	8 2 2
	38	[494]	SETTABLE 	7 -1 8	; "text" -
	39	[495]	SELF     	8 0 -11	; "genChannelList"
	40	[495]	CALL     	8 2 2
	41	[495]	SETTABLE 	7 -4 8	; "sub_item_table" -
	42	[497]	SETLIST  	5 2 1	; 1
	43	[497]	SETTABLE 	4 -4 5	; "sub_item_table" -
	44	[499]	SETLIST  	2 2 1	; 1
	45	[499]	SETTABLE 	1 -4 2	; "sub_item_table" -
	46	[500]	RETURN   	1 2
	47	[501]	RETURN   	0 1

function <./frontend/ui/otamanager.lua:468,474> (13 instructions, 52 bytes at 0x7f8a35c10310)
0 params, 2 slots, 2 upvalues, 0 locals, 3 constants, 0 functions
	1	[469]	GETUPVAL 	0 0	; NetworkMgr
	2	[469]	SELF     	0 0 -1	; "isOnline"
	3	[469]	CALL     	0 2 2
	4	[469]	TEST     	0 0 1
	5	[469]	JMP      	4	; to 10
	6	[470]	GETUPVAL 	0 0	; NetworkMgr
	7	[470]	SELF     	0 0 -2	; "promptWifiOn"
	8	[470]	CALL     	0 2 1
	9	[470]	JMP      	3	; to 13
	10	[472]	GETUPVAL 	0 1	; OTAManager
	11	[472]	SELF     	0 0 -3	; "fetchAndProcessUpdate"
	12	[472]	CALL     	0 2 1
	13	[474]	RETURN   	0 1

function <./frontend/ui/otamanager.lua:478,484> (13 instructions, 52 bytes at 0x7f8a35c10770)
0 params, 2 slots, 2 upvalues, 0 locals, 3 constants, 0 functions
	1	[479]	GETUPVAL 	0 0	; NetworkMgr
	2	[479]	SELF     	0 0 -1	; "isOnline"
	3	[479]	CALL     	0 2 2
	4	[479]	TEST     	0 0 1
	5	[479]	JMP      	4	; to 10
	6	[480]	GETUPVAL 	0 0	; NetworkMgr
	7	[480]	SELF     	0 0 -2	; "promptWifiOn"
	8	[480]	CALL     	0 2 1
	9	[480]	JMP      	3	; to 13
	10	[482]	GETUPVAL 	0 1	; OTAManager
	11	[482]	SELF     	0 0 -3	; "fetchAndProcessUpdate"
	12	[482]	CALL     	0 2 1
	13	[484]	RETURN   	0 1
