
main <./frontend/ui/widget/pathchooser.lua:0,0> (65 instructions, 260 bytes at 0x7fbcf2c068d0)
0+ params, 16 slots, 0 upvalues, 11 locals, 30 constants, 3 functions
	1	[1]	GETGLOBAL	0 -1	; require
	2	[1]	LOADK    	1 -2	; "ui/bidi"
	3	[1]	CALL     	0 2 2
	4	[2]	GETGLOBAL	1 -1	; require
	5	[2]	LOADK    	2 -3	; "ui/widget/buttondialogtitle"
	6	[2]	CALL     	1 2 2
	7	[3]	GETGLOBAL	2 -1	; require
	8	[3]	LOADK    	3 -4	; "ui/widget/filechooser"
	9	[3]	CALL     	2 2 2
	10	[4]	GETGLOBAL	3 -1	; require
	11	[4]	LOADK    	4 -5	; "ui/font"
	12	[4]	CALL     	3 2 2
	13	[5]	GETGLOBAL	4 -1	; require
	14	[5]	LOADK    	5 -6	; "ui/uimanager"
	15	[5]	CALL     	4 2 2
	16	[6]	GETGLOBAL	5 -1	; require
	17	[6]	LOADK    	6 -7	; "ffi/util"
	18	[6]	CALL     	5 2 2
	19	[7]	GETGLOBAL	6 -1	; require
	20	[7]	LOADK    	7 -8	; "libs/libkoreader-lfs"
	21	[7]	CALL     	6 2 2
	22	[8]	GETGLOBAL	7 -1	; require
	23	[8]	LOADK    	8 -9	; "util"
	24	[8]	CALL     	7 2 2
	25	[9]	GETGLOBAL	8 -1	; require
	26	[9]	LOADK    	9 -10	; "gettext"
	27	[9]	CALL     	8 2 2
	28	[10]	GETTABLE 	9 5 -11	; "template"
	29	[12]	SELF     	10 2 -12	; "extend"
	30	[12]	NEWTABLE 	12 0 11
	31	[13]	SETTABLE 	12 -13 -14	; "title" true
	32	[15]	SETTABLE 	12 -15 -16	; "no_title" false
	33	[16]	SETTABLE 	12 -17 -14	; "show_path" true
	34	[17]	SETTABLE 	12 -18 -16	; "is_popout" false
	35	[18]	SETTABLE 	12 -19 -14	; "covers_fullscreen" true
	36	[19]	SETTABLE 	12 -20 -14	; "is_borderless" true
	37	[21]	SELF     	13 3 -22	; "getFace"
	38	[21]	LOADK    	15 -23	; "smalltfont"
	39	[21]	CALL     	13 3 2
	40	[21]	SETTABLE 	12 -21 13	; "tface" -
	41	[23]	SETTABLE 	12 -24 -14	; "select_directory" true
	42	[24]	SETTABLE 	12 -25 -14	; "select_file" true
	43	[25]	SETTABLE 	12 -26 -14	; "show_files" true
	44	[27]	SETTABLE 	12 -27 -16	; "detailed_file_info" false
	45	[12]	CALL     	10 3 2
	46	[49]	CLOSURE  	11 0	; 0x7fbcf2c07040
	47	[49]	MOVE     	0 8
	48	[49]	MOVE     	0 2
	49	[30]	SETTABLE 	10 -28 11	; "init" -
	50	[81]	CLOSURE  	11 1	; 0x7fbcf2c07ab0
	51	[81]	MOVE     	0 5
	52	[81]	MOVE     	0 6
	53	[51]	SETTABLE 	10 -29 11	; "onMenuSelect" -
	54	[143]	CLOSURE  	11 2	; 0x7fbcf2c07fa0
	55	[143]	MOVE     	0 5
	56	[143]	MOVE     	0 6
	57	[143]	MOVE     	0 7
	58	[143]	MOVE     	0 9
	59	[143]	MOVE     	0 8
	60	[143]	MOVE     	0 0
	61	[143]	MOVE     	0 1
	62	[143]	MOVE     	0 4
	63	[83]	SETTABLE 	10 -30 11	; "onMenuHold" -
	64	[145]	RETURN   	10 2
	65	[145]	RETURN   	0 1

function <./frontend/ui/widget/pathchooser.lua:30,49> (48 instructions, 192 bytes at 0x7fbcf2c07040)
1 param, 4 slots, 2 upvalues, 1 local, 14 constants, 1 function
	1	[31]	GETTABLE 	1 0 -1	; "title"
	2	[31]	EQ       	0 1 -2	; - true
	3	[31]	JMP      	26	; to 30
	4	[32]	GETTABLE 	1 0 -3	; "select_directory"
	5	[32]	TEST     	1 0 0
	6	[32]	JMP      	8	; to 15
	7	[32]	GETTABLE 	1 0 -4	; "select_file"
	8	[32]	TEST     	1 0 1
	9	[32]	JMP      	5	; to 15
	10	[33]	GETUPVAL 	1 0	; _
	11	[33]	LOADK    	2 -5	; "Long-press to select directory"
	12	[33]	CALL     	1 2 2
	13	[33]	SETTABLE 	0 -1 1	; "title" -
	14	[33]	JMP      	15	; to 30
	15	[34]	GETTABLE 	1 0 -3	; "select_directory"
	16	[34]	TEST     	1 0 1
	17	[34]	JMP      	8	; to 26
	18	[34]	GETTABLE 	1 0 -4	; "select_file"
	19	[34]	TEST     	1 0 0
	20	[34]	JMP      	5	; to 26
	21	[35]	GETUPVAL 	1 0	; _
	22	[35]	LOADK    	2 -6	; "Long-press to select file"
	23	[35]	CALL     	1 2 2
	24	[35]	SETTABLE 	0 -1 1	; "title" -
	25	[35]	JMP      	4	; to 30
	26	[37]	GETUPVAL 	1 0	; _
	27	[37]	LOADK    	2 -7	; "Long-press to select"
	28	[37]	CALL     	1 2 2
	29	[37]	SETTABLE 	0 -1 1	; "title" -
	30	[40]	GETGLOBAL	1 -9	; G_reader_settings
	31	[40]	SELF     	1 1 -10	; "readSetting"
	32	[40]	LOADK    	3 -8	; "show_hidden"
	33	[40]	CALL     	1 3 2
	34	[40]	SETTABLE 	0 -8 1	; "show_hidden" -
	35	[41]	GETTABLE 	1 0 -11	; "show_files"
	36	[41]	TEST     	1 0 1
	37	[41]	JMP      	2	; to 40
	38	[42]	CLOSURE  	1 0	; 0x7fbcf2c075d0
	39	[42]	SETTABLE 	0 -12 1	; "file_filter" -
	40	[44]	GETTABLE 	1 0 -3	; "select_directory"
	41	[44]	TEST     	1 0 0
	42	[44]	JMP      	1	; to 44
	43	[46]	SETTABLE 	0 -13 -2	; "show_current_dir_for_hold" true
	44	[48]	GETUPVAL 	1 1	; FileChooser
	45	[48]	GETTABLE 	1 1 -14	; "init"
	46	[48]	MOVE     	2 0
	47	[48]	CALL     	1 2 1
	48	[49]	RETURN   	0 1

function <./frontend/ui/widget/pathchooser.lua:42,42> (3 instructions, 12 bytes at 0x7fbcf2c075d0)
0 params, 2 slots, 0 upvalues, 0 locals, 0 constants, 0 functions
	1	[42]	LOADBOOL 	0 0 0
	2	[42]	RETURN   	0 2
	3	[42]	RETURN   	0 1

function <./frontend/ui/widget/pathchooser.lua:51,81> (49 instructions, 196 bytes at 0x7fbcf2c07ab0)
2 params, 8 slots, 2 upvalues, 5 locals, 13 constants, 0 functions
	1	[52]	GETTABLE 	2 1 -1	; "path"
	2	[53]	SELF     	3 2 -2	; "sub"
	3	[53]	LOADK    	5 -3	; -2
	4	[53]	LOADK    	6 -4	; -1
	5	[53]	CALL     	3 4 2
	6	[53]	EQ       	0 3 -5	; - "/."
	7	[53]	JMP      	2	; to 10
	8	[55]	LOADBOOL 	3 1 0
	9	[55]	RETURN   	3 2
	10	[57]	GETUPVAL 	3 0	; ffiutil
	11	[57]	GETTABLE 	3 3 -6	; "realpath"
	12	[57]	MOVE     	4 2
	13	[57]	CALL     	3 2 2
	14	[57]	MOVE     	2 3
	15	[58]	TEST     	2 0 1
	16	[58]	JMP      	5	; to 22
	17	[61]	SELF     	3 0 -7	; "changeToPath"
	18	[61]	LOADK    	5 -8	; "/"
	19	[61]	CALL     	3 3 1
	20	[62]	LOADBOOL 	3 1 0
	21	[62]	RETURN   	3 2
	22	[64]	GETUPVAL 	3 1	; lfs
	23	[64]	GETTABLE 	3 3 -9	; "attributes"
	24	[64]	MOVE     	4 2
	25	[64]	CALL     	3 2 2
	26	[65]	TEST     	3 0 1
	27	[65]	JMP      	5	; to 33
	28	[67]	SELF     	4 0 -7	; "changeToPath"
	29	[67]	LOADK    	6 -8	; "/"
	30	[67]	CALL     	4 3 1
	31	[68]	LOADBOOL 	4 1 0
	32	[68]	RETURN   	4 2
	33	[70]	GETTABLE 	4 3 -10	; "mode"
	34	[70]	EQ       	1 4 -11	; - "directory"
	35	[70]	JMP      	2	; to 38
	36	[72]	LOADBOOL 	4 1 0
	37	[72]	RETURN   	4 2
	38	[76]	SELF     	4 0 -12	; "genItemTableFromPath"
	39	[76]	MOVE     	6 2
	40	[76]	CALL     	4 3 2
	41	[77]	LEN      	5 4
	42	[77]	LT       	0 -13 5	; 0 -
	43	[77]	JMP      	3	; to 47
	44	[78]	SELF     	5 0 -7	; "changeToPath"
	45	[78]	MOVE     	7 2
	46	[78]	CALL     	5 3 1
	47	[80]	LOADBOOL 	5 1 0
	48	[80]	RETURN   	5 2
	49	[81]	RETURN   	0 1

function <./frontend/ui/widget/pathchooser.lua:83,143> (148 instructions, 592 bytes at 0x7fbcf2c07fa0)
2 params, 15 slots, 8 upvalues, 8 locals, 37 constants, 2 functions
	1	[84]	GETTABLE 	2 1 -1	; "path"
	2	[85]	SELF     	3 2 -2	; "sub"
	3	[85]	LOADK    	5 -3	; -2
	4	[85]	LOADK    	6 -4	; -1
	5	[85]	CALL     	3 4 2
	6	[85]	EQ       	0 3 -5	; - "/."
	7	[85]	JMP      	5	; to 13
	8	[86]	SELF     	3 2 -2	; "sub"
	9	[86]	LOADK    	5 -6	; 1
	10	[86]	LOADK    	6 -7	; -3
	11	[86]	CALL     	3 4 2
	12	[86]	MOVE     	2 3
	13	[88]	GETUPVAL 	3 0	; ffiutil
	14	[88]	GETTABLE 	3 3 -8	; "realpath"
	15	[88]	MOVE     	4 2
	16	[88]	CALL     	3 2 2
	17	[88]	MOVE     	2 3
	18	[89]	TEST     	2 0 1
	19	[89]	JMP      	2	; to 22
	20	[90]	LOADBOOL 	3 1 0
	21	[90]	RETURN   	3 2
	22	[92]	GETUPVAL 	3 1	; lfs
	23	[92]	GETTABLE 	3 3 -9	; "attributes"
	24	[92]	MOVE     	4 2
	25	[92]	CALL     	3 2 2
	26	[93]	TEST     	3 0 1
	27	[93]	JMP      	2	; to 30
	28	[94]	LOADBOOL 	4 1 0
	29	[94]	RETURN   	4 2
	30	[96]	GETTABLE 	4 3 -10	; "mode"
	31	[96]	EQ       	0 4 -11	; - "file"
	32	[96]	JMP      	5	; to 38
	33	[96]	GETTABLE 	4 0 -12	; "select_file"
	34	[96]	TEST     	4 0 1
	35	[96]	JMP      	2	; to 38
	36	[97]	LOADBOOL 	4 1 0
	37	[97]	RETURN   	4 2
	38	[99]	GETTABLE 	4 3 -10	; "mode"
	39	[99]	EQ       	0 4 -13	; - "directory"
	40	[99]	JMP      	5	; to 46
	41	[99]	GETTABLE 	4 0 -14	; "select_directory"
	42	[99]	TEST     	4 0 1
	43	[99]	JMP      	2	; to 46
	44	[100]	LOADBOOL 	4 1 0
	45	[100]	RETURN   	4 2
	46	[102]	LOADNIL  	4 4
	47	[103]	GETTABLE 	5 3 -10	; "mode"
	48	[103]	EQ       	0 5 -11	; - "file"
	49	[103]	JMP      	36	; to 86
	50	[104]	GETTABLE 	5 0 -15	; "detailed_file_info"
	51	[104]	TEST     	5 0 0
	52	[104]	JMP      	22	; to 75
	53	[105]	GETUPVAL 	5 2	; util
	54	[105]	GETTABLE 	5 5 -16	; "getFormattedSize"
	55	[105]	GETTABLE 	6 3 -17	; "size"
	56	[105]	CALL     	5 2 2
	57	[106]	GETGLOBAL	6 -18	; os
	58	[106]	GETTABLE 	6 6 -19	; "date"
	59	[106]	LOADK    	7 -20	; "%Y-%m-%d %H:%M"
	60	[106]	GETTABLE 	8 3 -21	; "modification"
	61	[106]	CALL     	6 3 2
	62	[107]	GETUPVAL 	7 3	; T
	63	[107]	GETUPVAL 	8 4	; _
	64	[107]	LOADK    	9 -22	; "Select this file?\n\n%1\n\nFile size: %2 bytes\nLast modified: %3"
	65	[107]	CALL     	8 2 2
	66	[108]	GETUPVAL 	9 5	; BD
	67	[108]	GETTABLE 	9 9 -23	; "filepath"
	68	[108]	MOVE     	10 2
	69	[108]	CALL     	9 2 2
	70	[108]	MOVE     	10 5
	71	[108]	MOVE     	11 6
	72	[107]	CALL     	7 5 2
	73	[108]	MOVE     	4 7
	74	[108]	JMP      	35	; to 110
	75	[110]	GETUPVAL 	5 3	; T
	76	[110]	GETUPVAL 	6 4	; _
	77	[110]	LOADK    	7 -24	; "Select this file?\n\n%1"
	78	[110]	CALL     	6 2 2
	79	[110]	GETUPVAL 	7 5	; BD
	80	[110]	GETTABLE 	7 7 -23	; "filepath"
	81	[110]	MOVE     	8 2
	82	[110]	CALL     	7 2 0
	83	[110]	CALL     	5 0 2
	84	[110]	MOVE     	4 5
	85	[111]	JMP      	24	; to 110
	86	[112]	GETTABLE 	5 3 -10	; "mode"
	87	[112]	EQ       	0 5 -13	; - "directory"
	88	[112]	JMP      	11	; to 100
	89	[113]	GETUPVAL 	5 3	; T
	90	[113]	GETUPVAL 	6 4	; _
	91	[113]	LOADK    	7 -25	; "Select this directory?\n\n%1"
	92	[113]	CALL     	6 2 2
	93	[113]	GETUPVAL 	7 5	; BD
	94	[113]	GETTABLE 	7 7 -26	; "dirpath"
	95	[113]	MOVE     	8 2
	96	[113]	CALL     	7 2 0
	97	[113]	CALL     	5 0 2
	98	[113]	MOVE     	4 5
	99	[113]	JMP      	10	; to 110
	100	[115]	GETUPVAL 	5 3	; T
	101	[115]	GETUPVAL 	6 4	; _
	102	[115]	LOADK    	7 -27	; "Select this path?\n\n%1"
	103	[115]	CALL     	6 2 2
	104	[115]	GETUPVAL 	7 5	; BD
	105	[115]	GETTABLE 	7 7 -1	; "path"
	106	[115]	MOVE     	8 2
	107	[115]	CALL     	7 2 0
	108	[115]	CALL     	5 0 2
	109	[115]	MOVE     	4 5
	110	[117]	GETTABLE 	5 0 -28	; "onConfirm"
	111	[118]	GETUPVAL 	6 6	; ButtonDialogTitle
	112	[118]	SELF     	6 6 -30	; "new"
	113	[118]	NEWTABLE 	8 0 2
	114	[119]	SETTABLE 	8 -31 4	; "title" -
	115	[120]	NEWTABLE 	9 1 0
	116	[120]	NEWTABLE 	10 2 0
	117	[121]	NEWTABLE 	11 0 2
	118	[123]	GETUPVAL 	12 4	; _
	119	[123]	LOADK    	13 -34	; "Cancel"
	120	[123]	CALL     	12 2 2
	121	[123]	SETTABLE 	11 -33 12	; "text" -
	122	[126]	CLOSURE  	12 0	; 0x7fbcf2c08690
	123	[126]	GETUPVAL 	0 7	; UIManager
	124	[126]	MOVE     	0 0
	125	[126]	SETTABLE 	11 -35 12	; "callback" -
	126	[127]	NEWTABLE 	12 0 2
	127	[129]	GETUPVAL 	13 4	; _
	128	[129]	LOADK    	14 -36	; "Select"
	129	[129]	CALL     	13 2 2
	130	[129]	SETTABLE 	12 -33 13	; "text" -
	131	[136]	CLOSURE  	13 1	; 0x7fbcf2c08850
	132	[136]	MOVE     	0 5
	133	[136]	MOVE     	0 2
	134	[136]	GETUPVAL 	0 7	; UIManager
	135	[136]	MOVE     	0 0
	136	[136]	SETTABLE 	12 -35 13	; "callback" -
	137	[138]	SETLIST  	10 2 1	; 1
	138	[139]	SETLIST  	9 1 1	; 1
	139	[139]	SETTABLE 	8 -32 9	; "buttons" -
	140	[118]	CALL     	6 3 2
	141	[140]	SETTABLE 	0 -29 6	; "button_dialog" -
	142	[141]	GETUPVAL 	6 7	; UIManager
	143	[141]	SELF     	6 6 -37	; "show"
	144	[141]	GETTABLE 	8 0 -29	; "button_dialog"
	145	[141]	CALL     	6 3 1
	146	[142]	LOADBOOL 	6 1 0
	147	[142]	RETURN   	6 2
	148	[143]	RETURN   	0 1

function <./frontend/ui/widget/pathchooser.lua:124,126> (6 instructions, 24 bytes at 0x7fbcf2c08690)
0 params, 3 slots, 2 upvalues, 0 locals, 2 constants, 0 functions
	1	[125]	GETUPVAL 	0 0	; UIManager
	2	[125]	SELF     	0 0 -1	; "close"
	3	[125]	GETUPVAL 	2 1	; self
	4	[125]	GETTABLE 	2 2 -2	; "button_dialog"
	5	[125]	CALL     	0 3 1
	6	[126]	RETURN   	0 1

function <./frontend/ui/widget/pathchooser.lua:130,136> (16 instructions, 64 bytes at 0x7fbcf2c08850)
0 params, 3 slots, 4 upvalues, 0 locals, 2 constants, 0 functions
	1	[131]	GETUPVAL 	0 0	; onConfirm
	2	[131]	TEST     	0 0 0
	3	[131]	JMP      	3	; to 7
	4	[132]	GETUPVAL 	0 0	; onConfirm
	5	[132]	GETUPVAL 	1 1	; path
	6	[132]	CALL     	0 2 1
	7	[134]	GETUPVAL 	0 2	; UIManager
	8	[134]	SELF     	0 0 -1	; "close"
	9	[134]	GETUPVAL 	2 3	; self
	10	[134]	GETTABLE 	2 2 -2	; "button_dialog"
	11	[134]	CALL     	0 3 1
	12	[135]	GETUPVAL 	0 2	; UIManager
	13	[135]	SELF     	0 0 -1	; "close"
	14	[135]	GETUPVAL 	2 3	; self
	15	[135]	CALL     	0 3 1
	16	[136]	RETURN   	0 1
