
main <./frontend/ui/widget/physicalkeyboard.lua:0,0> (133 instructions, 532 bytes at 0x7fc171c068f0)
0+ params, 26 slots, 0 upvalues, 20 locals, 52 constants, 5 functions
	1	[1]	GETGLOBAL	0 -1	; require
	2	[1]	LOADK    	1 -2	; "ffi/blitbuffer"
	3	[1]	CALL     	0 2 2
	4	[2]	GETGLOBAL	1 -1	; require
	5	[2]	LOADK    	2 -3	; "ui/widget/container/bottomcontainer"
	6	[2]	CALL     	1 2 2
	7	[3]	GETGLOBAL	2 -1	; require
	8	[3]	LOADK    	3 -4	; "ui/widget/container/centercontainer"
	9	[3]	CALL     	2 2 2
	10	[4]	GETGLOBAL	3 -1	; require
	11	[4]	LOADK    	4 -5	; "device"
	12	[4]	CALL     	3 2 2
	13	[5]	GETGLOBAL	4 -1	; require
	14	[5]	LOADK    	5 -6	; "ui/font"
	15	[5]	CALL     	4 2 2
	16	[6]	GETGLOBAL	5 -1	; require
	17	[6]	LOADK    	6 -7	; "ui/widget/container/framecontainer"
	18	[6]	CALL     	5 2 2
	19	[7]	GETGLOBAL	6 -1	; require
	20	[7]	LOADK    	7 -8	; "ui/geometry"
	21	[7]	CALL     	6 2 2
	22	[8]	GETGLOBAL	7 -1	; require
	23	[8]	LOADK    	8 -9	; "ui/widget/horizontalgroup"
	24	[8]	CALL     	7 2 2
	25	[9]	GETGLOBAL	8 -1	; require
	26	[9]	LOADK    	9 -10	; "ui/widget/horizontalspan"
	27	[9]	CALL     	8 2 2
	28	[10]	GETGLOBAL	9 -1	; require
	29	[10]	LOADK    	10 -11	; "ui/widget/container/inputcontainer"
	30	[10]	CALL     	9 2 2
	31	[11]	GETGLOBAL	10 -1	; require
	32	[11]	LOADK    	11 -12	; "ui/size"
	33	[11]	CALL     	10 2 2
	34	[12]	GETGLOBAL	11 -1	; require
	35	[12]	LOADK    	12 -13	; "ui/widget/textwidget"
	36	[12]	CALL     	11 2 2
	37	[13]	GETGLOBAL	12 -1	; require
	38	[13]	LOADK    	13 -14	; "ui/widget/container/topcontainer"
	39	[13]	CALL     	12 2 2
	40	[14]	GETGLOBAL	13 -1	; require
	41	[14]	LOADK    	14 -15	; "ui/widget/verticalgroup"
	42	[14]	CALL     	13 2 2
	43	[15]	GETGLOBAL	14 -1	; require
	44	[15]	LOADK    	15 -16	; "ui/widget/container/widgetcontainer"
	45	[15]	CALL     	14 2 2
	46	[16]	GETGLOBAL	15 -1	; require
	47	[16]	LOADK    	16 -17	; "logger"
	48	[16]	CALL     	15 2 2
	49	[17]	GETGLOBAL	16 -1	; require
	50	[17]	LOADK    	17 -18	; "util"
	51	[17]	CALL     	16 2 2
	52	[18]	GETTABLE 	17 3 -19	; "screen"
	53	[20]	SELF     	18 14 -20	; "new"
	54	[20]	NEWTABLE 	20 0 11
	55	[21]	SETTABLE 	20 -21 -22	; "key" nil
	56	[22]	SETTABLE 	20 -23 -22	; "label" nil
	57	[23]	SETTABLE 	20 -24 -22	; "physical_key_label" nil
	58	[25]	SETTABLE 	20 -25 -22	; "keyboard" nil
	59	[26]	SETTABLE 	20 -26 -22	; "callback" nil
	60	[27]	SETTABLE 	20 -27 -22	; "mapping" nil
	61	[29]	SETTABLE 	20 -28 -22	; "width" nil
	62	[30]	SETTABLE 	20 -29 -22	; "height" nil
	63	[31]	GETTABLE 	21 10 -31	; "border"
	64	[31]	GETTABLE 	21 21 -32	; "button"
	65	[31]	SETTABLE 	20 -30 21	; "bordersize" -
	66	[32]	SELF     	21 4 -34	; "getFace"
	67	[32]	LOADK    	23 -35	; "infont"
	68	[32]	CALL     	21 3 2
	69	[32]	SETTABLE 	20 -33 21	; "face" -
	70	[33]	SELF     	21 4 -34	; "getFace"
	71	[33]	LOADK    	23 -35	; "infont"
	72	[33]	LOADK    	24 -37	; 14
	73	[33]	CALL     	21 4 2
	74	[33]	SETTABLE 	20 -36 21	; "pkey_face" -
	75	[20]	CALL     	18 3 2
	76	[66]	CLOSURE  	19 0	; 0x7fc171c07100
	77	[66]	MOVE     	0 11
	78	[66]	MOVE     	0 5
	79	[66]	MOVE     	0 0
	80	[66]	MOVE     	0 10
	81	[66]	MOVE     	0 2
	82	[66]	MOVE     	0 6
	83	[66]	MOVE     	0 13
	84	[36]	SETTABLE 	18 -38 19	; "init" -
	85	[70]	SELF     	19 9 -20	; "new"
	86	[70]	NEWTABLE 	21 0 6
	87	[71]	SETTABLE 	21 -39 -40	; "is_always_active" true
	88	[72]	SETTABLE 	21 -41 -22	; "inputbox" nil
	89	[73]	GETTABLE 	22 10 -31	; "border"
	90	[73]	GETTABLE 	22 22 -32	; "button"
	91	[73]	SETTABLE 	21 -30 22	; "bordersize" -
	92	[74]	GETTABLE 	22 10 -42	; "padding"
	93	[74]	GETTABLE 	22 22 -32	; "button"
	94	[74]	SETTABLE 	21 -42 22	; "padding" -
	95	[75]	GETGLOBAL	22 -43	; math
	96	[75]	GETTABLE 	22 22 -44	; "max"
	97	[75]	SELF     	23 17 -45	; "getWidth"
	98	[75]	CALL     	23 2 2
	99	[75]	SELF     	24 17 -46	; "getHeight"
	100	[75]	CALL     	24 2 0
	101	[75]	CALL     	22 0 2
	102	[75]	MUL      	22 22 -47	; - 0.33
	103	[75]	SETTABLE 	21 -29 22	; "height" -
	104	[76]	GETTABLE 	22 10 -42	; "padding"
	105	[76]	GETTABLE 	22 22 -49	; "default"
	106	[76]	SETTABLE 	21 -48 22	; "key_padding" -
	107	[70]	CALL     	19 3 2
	108	[91]	CLOSURE  	20 1	; 0x7fc171c07e00
	109	[91]	MOVE     	0 3
	110	[91]	MOVE     	0 16
	111	[91]	MOVE     	0 6
	112	[79]	SETTABLE 	19 -38 20	; "init" -
	113	[110]	CLOSURE  	20 2	; 0x7fc171c086c0
	114	[110]	MOVE     	0 3
	115	[93]	SETTABLE 	19 -50 20	; "setType" -
	116	[124]	CLOSURE  	20 3	; 0x7fc171c08840
	117	[124]	MOVE     	0 15
	118	[112]	SETTABLE 	19 -51 20	; "onKeyPress" -
	119	[170]	CLOSURE  	20 4	; 0x7fc171c091c0
	120	[170]	MOVE     	0 13
	121	[170]	MOVE     	0 10
	122	[170]	MOVE     	0 7
	123	[170]	MOVE     	0 8
	124	[170]	MOVE     	0 18
	125	[170]	MOVE     	0 3
	126	[170]	MOVE     	0 5
	127	[170]	MOVE     	0 12
	128	[170]	MOVE     	0 6
	129	[170]	MOVE     	0 1
	130	[170]	MOVE     	0 17
	131	[126]	SETTABLE 	19 -52 20	; "setupNumericMappingUI" -
	132	[172]	RETURN   	19 2
	133	[172]	RETURN   	0 1

function <./frontend/ui/widget/physicalkeyboard.lua:36,66> (72 instructions, 288 bytes at 0x7fc171c07100)
1 param, 16 slots, 7 upvalues, 2 locals, 23 constants, 0 functions
	1	[37]	GETUPVAL 	1 0	; TextWidget
	2	[37]	SELF     	1 1 -1	; "new"
	3	[37]	NEWTABLE 	3 0 2
	4	[38]	GETTABLE 	4 0 -3	; "label"
	5	[38]	SETTABLE 	3 -2 4	; "text" -
	6	[39]	GETTABLE 	4 0 -4	; "face"
	7	[39]	SETTABLE 	3 -4 4	; "face" -
	8	[37]	CALL     	1 3 2
	9	[41]	GETUPVAL 	2 1	; FrameContainer
	10	[41]	SELF     	2 2 -1	; "new"
	11	[41]	NEWTABLE 	4 0 5
	12	[42]	SETTABLE 	4 -6 -7	; "margin" 0
	13	[43]	GETTABLE 	5 0 -8	; "bordersize"
	14	[43]	SETTABLE 	4 -8 5	; "bordersize" -
	15	[44]	GETUPVAL 	5 2	; Blitbuffer
	16	[44]	GETTABLE 	5 5 -10	; "COLOR_WHITE"
	17	[44]	SETTABLE 	4 -9 5	; "background" -
	18	[45]	GETUPVAL 	5 3	; Size
	19	[45]	GETTABLE 	5 5 -11	; "radius"
	20	[45]	GETTABLE 	5 5 -12	; "default"
	21	[45]	SETTABLE 	4 -11 5	; "radius" -
	22	[46]	SETTABLE 	4 -13 -7	; "padding" 0
	23	[47]	GETUPVAL 	5 4	; CenterContainer
	24	[47]	SELF     	5 5 -1	; "new"
	25	[47]	NEWTABLE 	7 0 1
	26	[48]	GETUPVAL 	8 5	; Geom
	27	[48]	SELF     	8 8 -1	; "new"
	28	[48]	NEWTABLE 	10 0 2
	29	[49]	GETTABLE 	11 0 -16	; "width"
	30	[49]	GETTABLE 	12 0 -8	; "bordersize"
	31	[49]	MUL      	12 -17 12	; 2 -
	32	[49]	SUB      	11 11 12
	33	[49]	SETTABLE 	10 -15 11	; "w" -
	34	[50]	GETTABLE 	11 0 -19	; "height"
	35	[50]	GETTABLE 	12 0 -8	; "bordersize"
	36	[50]	MUL      	12 -17 12	; 2 -
	37	[50]	SUB      	11 11 12
	38	[50]	SETTABLE 	10 -18 11	; "h" -
	39	[48]	CALL     	8 3 2
	40	[51]	SETTABLE 	7 -14 8	; "dimen" -
	41	[52]	GETUPVAL 	8 6	; VerticalGroup
	42	[52]	SELF     	8 8 -1	; "new"
	43	[52]	NEWTABLE 	10 1 0
	44	[53]	MOVE     	11 1
	45	[54]	GETUPVAL 	12 0	; TextWidget
	46	[54]	SELF     	12 12 -1	; "new"
	47	[54]	NEWTABLE 	14 0 3
	48	[55]	GETUPVAL 	15 2	; Blitbuffer
	49	[55]	GETTABLE 	15 15 -21	; "COLOR_DARK_GRAY"
	50	[55]	SETTABLE 	14 -20 15	; "fgcolor" -
	51	[56]	GETTABLE 	15 0 -22	; "physical_key_label"
	52	[56]	SETTABLE 	14 -2 15	; "text" -
	53	[57]	GETTABLE 	15 0 -23	; "pkey_face"
	54	[57]	SETTABLE 	14 -4 15	; "face" -
	55	[54]	CALL     	12 3 0
	56	[59]	SETLIST  	10 0 1	; 1
	57	[52]	CALL     	8 3 0
	58	[60]	SETLIST  	7 0 1	; 1
	59	[47]	CALL     	5 3 0
	60	[61]	SETLIST  	4 0 1	; 1
	61	[41]	CALL     	2 3 2
	62	[61]	SETTABLE 	0 -5 2	; 1 -
	63	[62]	GETUPVAL 	2 5	; Geom
	64	[62]	SELF     	2 2 -1	; "new"
	65	[62]	NEWTABLE 	4 0 2
	66	[63]	GETTABLE 	5 0 -16	; "width"
	67	[63]	SETTABLE 	4 -15 5	; "w" -
	68	[64]	GETTABLE 	5 0 -19	; "height"
	69	[64]	SETTABLE 	4 -18 5	; "h" -
	70	[62]	CALL     	2 3 2
	71	[65]	SETTABLE 	0 -14 2	; "dimen" -
	72	[66]	RETURN   	0 1

function <./frontend/ui/widget/physicalkeyboard.lua:79,91> (33 instructions, 132 bytes at 0x7fc171c07e00)
1 param, 10 slots, 3 upvalues, 7 locals, 13 constants, 0 functions
	1	[80]	NEWTABLE 	1 0 0
	2	[81]	GETGLOBAL	2 -1	; ipairs
	3	[81]	GETUPVAL 	3 0	; Device
	4	[81]	GETTABLE 	3 3 -2	; "keyboard_layout"
	5	[81]	CALL     	2 2 4
	6	[81]	JMP      	5	; to 12
	7	[82]	GETUPVAL 	7 1	; util
	8	[82]	GETTABLE 	7 7 -3	; "arrayAppend"
	9	[82]	MOVE     	8 1
	10	[82]	MOVE     	9 6
	11	[82]	CALL     	7 3 1
	12	[81]	TFORLOOP 	2 2
	13	[82]	JMP      	-7	; to 7
	14	[84]	NEWTABLE 	2 0 1
	15	[85]	NEWTABLE 	3 1 0
	16	[85]	NEWTABLE 	4 1 0
	17	[85]	MOVE     	5 1
	18	[85]	SETLIST  	4 1 1	; 1
	19	[85]	SETLIST  	3 1 1	; 1
	20	[85]	SETTABLE 	2 -5 3	; "KeyPress" -
	21	[86]	SETTABLE 	0 -4 2	; "key_events" -
	22	[88]	GETUPVAL 	2 2	; Geom
	23	[88]	SELF     	2 2 -7	; "new"
	24	[88]	NEWTABLE 	4 0 2
	25	[88]	SETTABLE 	4 -8 -9	; "w" 0
	26	[88]	SETTABLE 	4 -10 -9	; "h" 0
	27	[88]	CALL     	2 3 2
	28	[88]	SETTABLE 	0 -6 2	; "dimen" -
	29	[90]	SELF     	2 0 -11	; "setType"
	30	[90]	GETTABLE 	4 0 -12	; "inputbox"
	31	[90]	GETTABLE 	4 4 -13	; "input_type"
	32	[90]	CALL     	2 3 1
	33	[91]	RETURN   	0 1

function <./frontend/ui/widget/physicalkeyboard.lua:93,110> (47 instructions, 188 bytes at 0x7fc171c086c0)
2 params, 15 slots, 1 upvalue, 13 locals, 16 constants, 0 functions
	1	[94]	EQ       	0 1 -1	; - "number"
	2	[94]	JMP      	41	; to 44
	3	[95]	NEWTABLE 	2 1 0
	4	[95]	NEWTABLE 	3 10 0
	5	[96]	LOADK    	4 -3	; "1"
	6	[96]	LOADK    	5 -4	; "2"
	7	[96]	LOADK    	6 -5	; "3"
	8	[96]	LOADK    	7 -6	; "4"
	9	[96]	LOADK    	8 -7	; "5"
	10	[96]	LOADK    	9 -8	; "6"
	11	[96]	LOADK    	10 -9	; "7"
	12	[96]	LOADK    	11 -10	; "8"
	13	[96]	LOADK    	12 -11	; "9"
	14	[96]	LOADK    	13 -12	; "0"
	15	[96]	SETLIST  	3 10 1	; 1
	16	[97]	SETLIST  	2 1 1	; 1
	17	[97]	SETTABLE 	0 -2 2	; "mapping" -
	18	[98]	NEWTABLE 	2 0 0
	19	[98]	SETTABLE 	0 -13 2	; "key_transformer" -
	20	[99]	GETGLOBAL	2 -14	; ipairs
	21	[99]	GETTABLE 	3 0 -2	; "mapping"
	22	[99]	CALL     	2 2 4
	23	[99]	JMP      	15	; to 39
	24	[100]	GETGLOBAL	7 -14	; ipairs
	25	[100]	MOVE     	8 6
	26	[100]	CALL     	7 2 4
	27	[100]	JMP      	9	; to 37
	28	[101]	GETUPVAL 	12 0	; Device
	29	[101]	GETTABLE 	12 12 -15	; "keyboard_layout"
	30	[101]	GETTABLE 	12 12 5
	31	[101]	GETTABLE 	12 12 10
	32	[102]	GETTABLE 	13 0 -13	; "key_transformer"
	33	[102]	GETTABLE 	14 0 -2	; "mapping"
	34	[102]	GETTABLE 	14 14 5
	35	[102]	GETTABLE 	14 14 10
	36	[102]	SETTABLE 	13 12 14
	37	[100]	TFORLOOP 	7 2
	38	[102]	JMP      	-11	; to 28
	39	[99]	TFORLOOP 	2 2
	40	[103]	JMP      	-17	; to 24
	41	[105]	SELF     	2 0 -16	; "setupNumericMappingUI"
	42	[105]	CALL     	2 2 1
	43	[105]	JMP      	3	; to 47
	44	[108]	GETUPVAL 	2 0	; Device
	45	[108]	GETTABLE 	2 2 -15	; "keyboard_layout"
	46	[108]	SETTABLE 	0 -2 2	; "mapping" -
	47	[110]	RETURN   	0 1

function <./frontend/ui/widget/physicalkeyboard.lua:112,124> (24 instructions, 96 bytes at 0x7fc171c08840)
2 params, 6 slots, 1 upvalue, 3 locals, 9 constants, 0 functions
	1	[113]	GETTABLE 	2 1 -1	; "key"
	2	[114]	EQ       	0 2 -2	; - "Back"
	3	[114]	JMP      	5	; to 9
	4	[115]	GETUPVAL 	3 0	; logger
	5	[115]	GETTABLE 	3 3 -3	; "warn"
	6	[115]	LOADK    	4 -4	; "TODO: exit keyboard"
	7	[115]	CALL     	3 2 1
	8	[115]	JMP      	15	; to 24
	9	[116]	EQ       	0 2 -5	; - "Del"
	10	[116]	JMP      	4	; to 15
	11	[117]	GETTABLE 	3 0 -6	; "inputbox"
	12	[117]	SELF     	3 3 -7	; "delChar"
	13	[117]	CALL     	3 2 1
	14	[117]	JMP      	9	; to 24
	15	[119]	GETTABLE 	3 0 -8	; "key_transformer"
	16	[119]	TEST     	3 0 0
	17	[119]	JMP      	2	; to 20
	18	[120]	GETTABLE 	3 0 -8	; "key_transformer"
	19	[120]	GETTABLE 	2 3 2
	20	[122]	GETTABLE 	3 0 -6	; "inputbox"
	21	[122]	SELF     	3 3 -9	; "addChars"
	22	[122]	MOVE     	5 2
	23	[122]	CALL     	3 3 1
	24	[124]	RETURN   	0 1

function <./frontend/ui/widget/physicalkeyboard.lua:126,170> (139 instructions, 556 bytes at 0x7fc171c091c0)
1 param, 24 slots, 11 upvalues, 19 locals, 27 constants, 0 functions
	1	[127]	GETUPVAL 	1 0	; VerticalGroup
	2	[127]	SELF     	1 1 -1	; "new"
	3	[127]	NEWTABLE 	3 0 0
	4	[127]	CALL     	1 3 2
	5	[128]	GETUPVAL 	2 1	; Size
	6	[128]	GETTABLE 	2 2 -2	; "margin"
	7	[128]	GETTABLE 	2 2 -3	; "tiny"
	8	[129]	GETTABLE 	3 0 -4	; "mapping"
	9	[129]	GETTABLE 	3 3 -5	; 1
	10	[129]	LEN      	3 3
	11	[130]	GETGLOBAL	4 -6	; math
	12	[130]	GETTABLE 	4 4 -7	; "floor"
	13	[130]	GETTABLE 	5 0 -8	; "width"
	14	[130]	GETTABLE 	6 0 -9	; "key_padding"
	15	[130]	MUL      	7 -10 2	; 2 -
	16	[130]	ADD      	6 6 7
	17	[130]	MUL      	6 3 6
	18	[130]	SUB      	5 5 6
	19	[130]	GETTABLE 	6 0 -11	; "padding"
	20	[130]	MUL      	6 -10 6	; 2 -
	21	[130]	SUB      	5 5 6
	22	[130]	DIV      	5 5 -12	; - 10
	23	[130]	CALL     	4 2 2
	24	[131]	GETGLOBAL	5 -6	; math
	25	[131]	GETTABLE 	5 5 -7	; "floor"
	26	[131]	GETTABLE 	6 0 -13	; "height"
	27	[131]	GETTABLE 	7 0 -9	; "key_padding"
	28	[131]	SUB      	6 6 7
	29	[131]	GETTABLE 	7 0 -11	; "padding"
	30	[131]	MUL      	7 -10 7	; 2 -
	31	[131]	SUB      	6 6 7
	32	[131]	DIV      	6 6 -14	; - 4
	33	[131]	CALL     	5 2 2
	34	[132]	GETGLOBAL	6 -6	; math
	35	[132]	GETTABLE 	6 6 -7	; "floor"
	36	[132]	GETTABLE 	7 0 -9	; "key_padding"
	37	[132]	ADD      	7 4 7
	38	[132]	CALL     	6 2 2
	39	[134]	GETGLOBAL	7 -15	; ipairs
	40	[134]	GETTABLE 	8 0 -4	; "mapping"
	41	[134]	CALL     	7 2 4
	42	[134]	JMP      	43	; to 86
	43	[135]	GETUPVAL 	12 2	; HorizontalGroup
	44	[135]	SELF     	12 12 -1	; "new"
	45	[135]	NEWTABLE 	14 0 0
	46	[135]	CALL     	12 3 2
	47	[136]	GETGLOBAL	13 -15	; ipairs
	48	[136]	MOVE     	14 11
	49	[136]	CALL     	13 2 4
	50	[136]	JMP      	28	; to 79
	51	[137]	LT       	0 -5 16	; 1 -
	52	[137]	JMP      	10	; to 63
	53	[138]	GETGLOBAL	18 -16	; table
	54	[138]	GETTABLE 	18 18 -17	; "insert"
	55	[138]	MOVE     	19 12
	56	[138]	GETUPVAL 	20 3	; HorizontalSpan
	57	[138]	SELF     	20 20 -1	; "new"
	58	[138]	NEWTABLE 	22 0 1
	59	[138]	MUL      	23 2 -10	; - 2
	60	[138]	SETTABLE 	22 -8 23	; "width" -
	61	[138]	CALL     	20 3 0
	62	[138]	CALL     	18 0 1
	63	[140]	GETGLOBAL	18 -16	; table
	64	[140]	GETTABLE 	18 18 -17	; "insert"
	65	[140]	MOVE     	19 12
	66	[140]	GETUPVAL 	20 4	; PhysicalNumericKey
	67	[140]	SELF     	20 20 -1	; "new"
	68	[140]	NEWTABLE 	22 0 4
	69	[141]	SETTABLE 	22 -18 17	; "label" -
	70	[142]	GETUPVAL 	23 5	; Device
	71	[142]	GETTABLE 	23 23 -20	; "keyboard_layout"
	72	[142]	GETTABLE 	23 23 10
	73	[142]	GETTABLE 	23 23 16
	74	[142]	SETTABLE 	22 -19 23	; "physical_key_label" -
	75	[143]	SETTABLE 	22 -8 6	; "width" -
	76	[144]	SETTABLE 	22 -13 5	; "height" -
	77	[140]	CALL     	20 3 0
	78	[140]	CALL     	18 0 1
	79	[136]	TFORLOOP 	13 2
	80	[145]	JMP      	-30	; to 51
	81	[147]	GETGLOBAL	13 -16	; table
	82	[147]	GETTABLE 	13 13 -17	; "insert"
	83	[147]	MOVE     	14 1
	84	[147]	MOVE     	15 12
	85	[147]	CALL     	13 3 1
	86	[134]	TFORLOOP 	7 2
	87	[147]	JMP      	-45	; to 43
	88	[150]	GETUPVAL 	7 6	; FrameContainer
	89	[150]	SELF     	7 7 -1	; "new"
	90	[150]	NEWTABLE 	9 0 4
	91	[151]	SETTABLE 	9 -2 -21	; "margin" 0
	92	[152]	SETTABLE 	9 -22 -21	; "bordersize" 0
	93	[153]	SETTABLE 	9 -23 -21	; "radius" 0
	94	[154]	GETTABLE 	10 0 -11	; "padding"
	95	[154]	SETTABLE 	9 -11 10	; "padding" -
	96	[155]	GETUPVAL 	10 7	; TopContainer
	97	[155]	SELF     	10 10 -1	; "new"
	98	[155]	NEWTABLE 	12 1 1
	99	[156]	GETUPVAL 	13 8	; Geom
	100	[156]	SELF     	13 13 -1	; "new"
	101	[156]	NEWTABLE 	15 0 2
	102	[157]	GETTABLE 	16 0 -8	; "width"
	103	[157]	GETTABLE 	17 0 -22	; "bordersize"
	104	[157]	MUL      	17 -10 17	; 2 -
	105	[157]	SUB      	16 16 17
	106	[157]	GETTABLE 	17 0 -11	; "padding"
	107	[157]	MUL      	17 -10 17	; 2 -
	108	[157]	SUB      	16 16 17
	109	[157]	SETTABLE 	15 -25 16	; "w" -
	110	[158]	GETTABLE 	16 0 -13	; "height"
	111	[158]	GETTABLE 	17 0 -22	; "bordersize"
	112	[158]	MUL      	17 -10 17	; 2 -
	113	[158]	SUB      	16 16 17
	114	[158]	GETTABLE 	17 0 -11	; "padding"
	115	[158]	MUL      	17 -10 17	; 2 -
	116	[158]	SUB      	16 16 17
	117	[158]	SETTABLE 	15 -26 16	; "h" -
	118	[156]	CALL     	13 3 2
	119	[159]	SETTABLE 	12 -24 13	; "dimen" -
	120	[161]	MOVE     	13 1
	121	[161]	SETLIST  	12 1 1	; 1
	122	[155]	CALL     	10 3 0
	123	[162]	SETLIST  	9 0 1	; 1
	124	[150]	CALL     	7 3 2
	125	[164]	GETUPVAL 	8 9	; BottomContainer
	126	[164]	SELF     	8 8 -1	; "new"
	127	[164]	NEWTABLE 	10 1 1
	128	[165]	GETUPVAL 	11 10	; Screen
	129	[165]	SELF     	11 11 -27	; "getSize"
	130	[165]	CALL     	11 2 2
	131	[165]	SETTABLE 	10 -24 11	; "dimen" -
	132	[167]	MOVE     	11 7
	133	[167]	SETLIST  	10 1 1	; 1
	134	[164]	CALL     	8 3 2
	135	[167]	SETTABLE 	0 -5 8	; 1 -
	136	[169]	SELF     	8 7 -27	; "getSize"
	137	[169]	CALL     	8 2 2
	138	[169]	SETTABLE 	0 -24 8	; "dimen" -
	139	[170]	RETURN   	0 1
