
main <./frontend/document/picdocument.lua:0,0> (34 instructions, 136 bytes at 0x7ffb544068d0)
0+ params, 8 slots, 0 upvalues, 5 locals, 19 constants, 5 functions
	1	[1]	GETGLOBAL	0 -1	; require
	2	[1]	LOADK    	1 -2	; "document/document"
	3	[1]	CALL     	0 2 2
	4	[2]	GETGLOBAL	1 -1	; require
	5	[2]	LOADK    	2 -3	; "ffi/drawcontext"
	6	[2]	CALL     	1 2 2
	7	[3]	GETGLOBAL	2 -1	; require
	8	[3]	LOADK    	3 -4	; "document/canvascontext"
	9	[3]	CALL     	2 2 2
	10	[4]	LOADNIL  	3 3
	11	[6]	SELF     	4 0 -5	; "new"
	12	[6]	NEWTABLE 	6 0 5
	13	[7]	SETTABLE 	6 -6 -7	; "_document" false
	14	[8]	SETTABLE 	6 -8 -9	; "is_pic" true
	15	[9]	GETTABLE 	7 1 -5	; "new"
	16	[9]	CALL     	7 1 2
	17	[9]	SETTABLE 	6 -10 7	; "dc_null" -
	18	[10]	SETTABLE 	6 -11 -12	; "provider" "picdocument"
	19	[11]	SETTABLE 	6 -13 -14	; "provider_name" "Picture Document"
	20	[6]	CALL     	4 3 2
	21	[29]	CLOSURE  	5 0	; 0x7ffb54407000
	22	[29]	MOVE     	0 3
	23	[29]	MOVE     	0 2
	24	[14]	SETTABLE 	4 -15 5	; "init" -
	25	[33]	CLOSURE  	5 1	; 0x7ffb54406640
	26	[31]	SETTABLE 	4 -16 5	; "getUsedBBox" -
	27	[41]	CLOSURE  	5 2	; 0x7ffb54406d60
	28	[35]	SETTABLE 	4 -17 5	; "getProps" -
	29	[49]	CLOSURE  	5 3	; 0x7ffb54407ef0
	30	[43]	SETTABLE 	4 -18 5	; "getCoverPageImage" -
	31	[56]	CLOSURE  	5 4	; 0x7ffb54408470
	32	[51]	SETTABLE 	4 -19 5	; "register" -
	33	[58]	RETURN   	4 2
	34	[58]	RETURN   	0 1

function <./frontend/document/picdocument.lua:14,29> (35 instructions, 140 bytes at 0x7ffb54407000)
1 param, 5 slots, 2 upvalues, 2 locals, 17 constants, 0 functions
	1	[15]	SELF     	1 0 -1	; "updateColorRendering"
	2	[15]	CALL     	1 2 1
	3	[16]	GETUPVAL 	1 0	; pic
	4	[16]	TEST     	1 0 1
	5	[16]	JMP      	4	; to 10
	6	[16]	GETGLOBAL	1 -2	; require
	7	[16]	LOADK    	2 -3	; "ffi/pic"
	8	[16]	CALL     	1 2 2
	9	[16]	SETUPVAL 	1 0	; pic
	10	[18]	GETUPVAL 	1 0	; pic
	11	[18]	GETUPVAL 	2 1	; CanvasContext
	12	[18]	GETTABLE 	2 2 -5	; "is_color_rendering_enabled"
	13	[18]	SETTABLE 	1 -4 2	; "color" -
	14	[19]	LOADNIL  	1 1
	15	[20]	GETGLOBAL	2 -7	; pcall
	16	[20]	GETUPVAL 	3 0	; pic
	17	[20]	GETTABLE 	3 3 -8	; "openDocument"
	18	[20]	GETTABLE 	4 0 -9	; "file"
	19	[20]	CALL     	2 3 3
	20	[20]	SETTABLE 	0 -6 3	; "_document" -
	21	[20]	MOVE     	1 2
	22	[21]	TEST     	1 0 1
	23	[21]	JMP      	5	; to 29
	24	[22]	GETGLOBAL	2 -10	; error
	25	[22]	LOADK    	3 -11	; "Failed to open image:"
	26	[22]	GETTABLE 	4 0 -6	; "_document"
	27	[22]	CONCAT   	3 3 4
	28	[22]	CALL     	2 2 1
	29	[25]	GETTABLE 	2 0 -12	; "info"
	30	[25]	SETTABLE 	2 -13 -14	; "has_pages" true
	31	[26]	GETTABLE 	2 0 -12	; "info"
	32	[26]	SETTABLE 	2 -15 -16	; "configurable" false
	33	[28]	SELF     	2 0 -17	; "_readMetadata"
	34	[28]	CALL     	2 2 1
	35	[29]	RETURN   	0 1

function <./frontend/document/picdocument.lua:31,33> (11 instructions, 44 bytes at 0x7ffb54406640)
2 params, 4 slots, 0 upvalues, 2 locals, 8 constants, 0 functions
	1	[32]	NEWTABLE 	2 0 4
	2	[32]	SETTABLE 	2 -1 -2	; "x0" 0
	3	[32]	SETTABLE 	2 -3 -2	; "y0" 0
	4	[32]	GETTABLE 	3 0 -5	; "_document"
	5	[32]	GETTABLE 	3 3 -6	; "width"
	6	[32]	SETTABLE 	2 -4 3	; "x1" -
	7	[32]	GETTABLE 	3 0 -5	; "_document"
	8	[32]	GETTABLE 	3 3 -8	; "height"
	9	[32]	SETTABLE 	2 -7 3	; "y1" -
	10	[32]	RETURN   	2 2
	11	[33]	RETURN   	0 1

function <./frontend/document/picdocument.lua:35,41> (14 instructions, 56 bytes at 0x7ffb54406d60)
1 param, 8 slots, 0 upvalues, 4 locals, 6 constants, 0 functions
	1	[36]	GETTABLE 	1 0 -1	; "file"
	2	[36]	SELF     	1 1 -2	; "find"
	3	[36]	LOADK    	3 -3	; ".*/(.*)"
	4	[36]	CALL     	1 3 4
	5	[37]	TEST     	3 0 1
	6	[37]	JMP      	1	; to 8
	7	[37]	GETTABLE 	3 0 -1	; "file"
	8	[38]	NEWTABLE 	4 0 1
	9	[39]	SELF     	5 3 -5	; "match"
	10	[39]	LOADK    	7 -6	; "(.*)%."
	11	[39]	CALL     	5 3 2
	12	[39]	SETTABLE 	4 -4 5	; "title" -
	13	[40]	RETURN   	4 2
	14	[41]	RETURN   	0 1

function <./frontend/document/picdocument.lua:43,49> (14 instructions, 56 bytes at 0x7ffb54407ef0)
1 param, 4 slots, 0 upvalues, 2 locals, 5 constants, 0 functions
	1	[44]	GETTABLE 	1 0 -1	; "_document"
	2	[44]	SELF     	1 1 -2	; "openPage"
	3	[44]	LOADK    	3 -3	; 1
	4	[44]	CALL     	1 3 2
	5	[45]	GETTABLE 	2 1 -4	; "image_bb"
	6	[45]	TEST     	2 0 0
	7	[45]	JMP      	4	; to 12
	8	[46]	GETTABLE 	2 1 -4	; "image_bb"
	9	[46]	SELF     	2 2 -5	; "copy"
	10	[46]	TAILCALL 	2 2 0
	11	[46]	RETURN   	2 0
	12	[48]	LOADNIL  	2 2
	13	[48]	RETURN   	2 2
	14	[49]	RETURN   	0 1

function <./frontend/document/picdocument.lua:51,56> (25 instructions, 100 bytes at 0x7ffb54408470)
2 params, 8 slots, 0 upvalues, 2 locals, 9 constants, 0 functions
	1	[52]	SELF     	2 1 -1	; "addProvider"
	2	[52]	LOADK    	4 -2	; "gif"
	3	[52]	LOADK    	5 -3	; "image/gif"
	4	[52]	MOVE     	6 0
	5	[52]	LOADK    	7 -4	; 100
	6	[52]	CALL     	2 6 1
	7	[53]	SELF     	2 1 -1	; "addProvider"
	8	[53]	LOADK    	4 -5	; "jpg"
	9	[53]	LOADK    	5 -6	; "image/jpeg"
	10	[53]	MOVE     	6 0
	11	[53]	LOADK    	7 -4	; 100
	12	[53]	CALL     	2 6 1
	13	[54]	SELF     	2 1 -1	; "addProvider"
	14	[54]	LOADK    	4 -7	; "jpeg"
	15	[54]	LOADK    	5 -6	; "image/jpeg"
	16	[54]	MOVE     	6 0
	17	[54]	LOADK    	7 -4	; 100
	18	[54]	CALL     	2 6 1
	19	[55]	SELF     	2 1 -1	; "addProvider"
	20	[55]	LOADK    	4 -8	; "png"
	21	[55]	LOADK    	5 -9	; "image/png"
	22	[55]	MOVE     	6 0
	23	[55]	LOADK    	7 -4	; 100
	24	[55]	CALL     	2 6 1
	25	[56]	RETURN   	0 1
