-- BYTECODE -- picdocument.lua:14-29
0001    MOV      2   0
0002    TGETS    1   0   0  ; "updateColorRendering"
0003    CALL     1   1   2
0004    UGET     1   0      ; pic
0005    IST          1
0006    JMP      1 => 0011
0007    GGET     1   1      ; "require"
0008    KSTR     2   2      ; "ffi/pic"
0009    CALL     1   2   2
0010    USETV    0   1      ; pic
0011 => UGET     1   0      ; pic
0012    UGET     2   1      ; CanvasContext
0013    TGETS    2   2   4  ; "is_color_rendering_enabled"
0014    TSETS    2   1   3  ; "color"
0015    KPRI     1   0
0016    GGET     2   6      ; "pcall"
0017    UGET     3   0      ; pic
0018    TGETS    3   3   7  ; "openDocument"
0019    TGETS    4   0   8  ; "file"
0020    CALL     2   3   3
0021    TSETS    3   0   5  ; "_document"
0022    MOV      1   2
0023    IST          1
0024    JMP      2 => 0030
0025    GGET     2   9      ; "error"
0026    KSTR     3  10      ; "Failed to open image:"
0027    TGETS    4   0   5  ; "_document"
0028    CAT      3   3   4
0029    CALL     2   1   2
0030 => TGETS    2   0  11  ; "info"
0031    KPRI     3   2
0032    TSETS    3   2  12  ; "has_pages"
0033    TGETS    2   0  11  ; "info"
0034    KPRI     3   1
0035    TSETS    3   2  13  ; "configurable"
0036    MOV      3   0
0037    TGETS    2   0  14  ; "_readMetadata"
0038    CALL     2   1   2
0039    RET0     0   1

-- BYTECODE -- picdocument.lua:31-33
0001    TDUP     2   0
0002    TGETS    3   0   1  ; "_document"
0003    TGETS    3   3   2  ; "width"
0004    TSETS    3   2   3  ; "x1"
0005    TGETS    3   0   1  ; "_document"
0006    TGETS    3   3   4  ; "height"
0007    TSETS    3   2   5  ; "y1"
0008    RET1     2   2

-- BYTECODE -- picdocument.lua:35-41
0001    TGETS    1   0   0  ; "file"
0002    MOV      2   1
0003    TGETS    1   1   1  ; "find"
0004    KSTR     3   2      ; ".*/(.*)"
0005    CALL     1   4   3
0006    IST          3
0007    JMP      4 => 0009
0008    TGETS    3   0   0  ; "file"
0009 => TDUP     4   5
0010    MOV      6   3
0011    TGETS    5   3   3  ; "match"
0012    KSTR     7   4      ; "(.*)%."
0013    CALL     5   2   3
0014    TSETS    5   4   6  ; "title"
0015    RET1     4   2

-- BYTECODE -- picdocument.lua:43-49
0001    TGETS    1   0   0  ; "_document"
0002    MOV      2   1
0003    TGETS    1   1   1  ; "openPage"
0004    KSHORT   3   1
0005    CALL     1   2   3
0006    TGETS    2   1   2  ; "image_bb"
0007    ISF          2
0008    JMP      3 => 0013
0009    TGETS    2   1   2  ; "image_bb"
0010    MOV      3   2
0011    TGETS    2   2   3  ; "copy"
0012    CALLT    2   2
0013 => KPRI     2   0
0014    RET1     2   2

-- BYTECODE -- picdocument.lua:51-56
0001    MOV      3   1
0002    TGETS    2   1   0  ; "addProvider"
0003    KSTR     4   1      ; "gif"
0004    KSTR     5   2      ; "image/gif"
0005    MOV      6   0
0006    KSHORT   7 100
0007    CALL     2   1   6
0008    MOV      3   1
0009    TGETS    2   1   0  ; "addProvider"
0010    KSTR     4   3      ; "jpg"
0011    KSTR     5   4      ; "image/jpeg"
0012    MOV      6   0
0013    KSHORT   7 100
0014    CALL     2   1   6
0015    MOV      3   1
0016    TGETS    2   1   0  ; "addProvider"
0017    KSTR     4   5      ; "jpeg"
0018    KSTR     5   4      ; "image/jpeg"
0019    MOV      6   0
0020    KSHORT   7 100
0021    CALL     2   1   6
0022    MOV      3   1
0023    TGETS    2   1   0  ; "addProvider"
0024    KSTR     4   6      ; "png"
0025    KSTR     5   7      ; "image/png"
0026    MOV      6   0
0027    KSHORT   7 100
0028    CALL     2   1   6
0029    RET0     0   1

-- BYTECODE -- picdocument.lua:0-59
0001    GGET     0   0      ; "require"
0002    KSTR     1   1      ; "document/document"
0003    CALL     0   2   2
0004    GGET     1   0      ; "require"
0005    KSTR     2   2      ; "ffi/drawcontext"
0006    CALL     1   2   2
0007    GGET     2   0      ; "require"
0008    KSTR     3   3      ; "document/canvascontext"
0009    CALL     2   2   2
0010    KPRI     3   0
0011    MOV      5   0
0012    TGETS    4   0   4  ; "new"
0013    TDUP     6   5
0014    TGETS    7   1   4  ; "new"
0015    CALL     7   2   1
0016    TSETS    7   6   6  ; "dc_null"
0017    CALL     4   2   3
0018    FNEW     5   8      ; picdocument.lua:14
0019    TSETS    5   4   7  ; "init"
0020    FNEW     5  10      ; picdocument.lua:31
0021    TSETS    5   4   9  ; "getUsedBBox"
0022    FNEW     5  12      ; picdocument.lua:35
0023    TSETS    5   4  11  ; "getProps"
0024    FNEW     5  14      ; picdocument.lua:43
0025    TSETS    5   4  13  ; "getCoverPageImage"
0026    FNEW     5  16      ; picdocument.lua:51
0027    TSETS    5   4  15  ; "register"
0028    UCLO     0 => 0029
0029 => RET1     4   2

