-- BYTECODE -- powerd.lua:28-106
0001    KNIL     1   4
0002    GGET     5   0      ; "tonumber"
0003    GGET     6   1      ; "KOBO_LIGHT_ON_START"
0004    CALL     5   2   2
0005    ISF          5
0006    JMP      6 => 0102
0007    KSHORT   6   0
0008    ISGE     6   5
0009    JMP      6 => 0018
0010    GGET     6   2      ; "math"
0011    TGETS    6   6   3  ; "min"
0012    MOV      7   5
0013    KSHORT   8 100
0014    CALL     6   2   3
0015    MOV      1   6
0016    KPRI     2   2
0017    JMP      6 => 0102
0018 => ISNEN    5   0      ; 0
0019    JMP      6 => 0023
0020    KSHORT   1   0
0021    KPRI     2   1
0022    JMP      6 => 0102
0023 => ISNEN    5   1      ; -2
0024    JMP      6 => 0075
0025    UGET     6   0      ; NickelConf
0026    TGETS    6   6   4  ; "frontLightLevel"
0027    TGETS    6   6   5  ; "get"
0028    CALL     6   2   1
0029    MOV      1   6
0030    UGET     6   0      ; NickelConf
0031    TGETS    6   6   6  ; "frontLightState"
0032    MOV      7   6
0033    TGETS    6   6   5  ; "get"
0034    CALL     6   2   2
0035    MOV      2   6
0036    TGETS    6   0   7  ; "fl_warmth"
0037    ISEQP    6   0
0038    JMP      6 => 0056
0039    UGET     6   0      ; NickelConf
0040    TGETS    6   6   8  ; "colorSetting"
0041    TGETS    6   6   5  ; "get"
0042    CALL     6   2   1
0043    ISEQP    6   0
0044    JMP      7 => 0051
0045    GGET     7   2      ; "math"
0046    TGETS    7   7   9  ; "floor"
0047    SUBVN    8   6   2  ; 1500
0048    DIVVN    8   8   3  ; 49
0049    CALL     7   2   2
0050    SUBNV    3   7   4  ; 100
0051 => UGET     7   0      ; NickelConf
0052    TGETS    7   7  10  ; "autoColorEnabled"
0053    TGETS    7   7   5  ; "get"
0054    CALL     7   2   1
0055    MOV      4   7
0056 => ISNEP    2   0
0057    JMP      6 => 0064
0058    KSHORT   6   0
0059    ISGE     6   1
0060    JMP      6 => 0063
0061    KPRI     2   2
0062    JMP      6 => 0064
0063 => KPRI     2   1
0064 => ISNEP    2   1
0065    JMP      6 => 0102
0066    ISNEN    1   0      ; 0
0067    JMP      6 => 0102
0068    GGET     6  11      ; "G_reader_settings"
0069    MOV      7   6
0070    TGETS    6   6  12  ; "readSetting"
0071    KSTR     8  13      ; "frontlight_intensity"
0072    CALL     6   2   3
0073    MOV      1   6
0074    JMP      6 => 0102
0075 => GGET     6  11      ; "G_reader_settings"
0076    MOV      7   6
0077    TGETS    6   6  12  ; "readSetting"
0078    KSTR     8  13      ; "frontlight_intensity"
0079    CALL     6   2   3
0080    MOV      1   6
0081    GGET     6  11      ; "G_reader_settings"
0082    MOV      7   6
0083    TGETS    6   6  12  ; "readSetting"
0084    KSTR     8  14      ; "is_frontlight_on"
0085    CALL     6   2   3
0086    MOV      2   6
0087    TGETS    6   0   7  ; "fl_warmth"
0088    ISEQP    6   0
0089    JMP      6 => 0102
0090    GGET     6  11      ; "G_reader_settings"
0091    MOV      7   6
0092    TGETS    6   6  12  ; "readSetting"
0093    KSTR     8  15      ; "frontlight_warmth"
0094    CALL     6   2   3
0095    MOV      3   6
0096    GGET     6  11      ; "G_reader_settings"
0097    MOV      7   6
0098    TGETS    6   6  12  ; "readSetting"
0099    KSTR     8  16      ; "frontlight_auto_warmth"
0100    CALL     6   2   3
0101    MOV      4   6
0102 => ISEQP    1   0
0103    JMP      6 => 0105
0104    TSETS    1   0  17  ; "hw_intensity"
0105 => ISEQP    2   0
0106    JMP      6 => 0108
0107    TSETS    2   0  18  ; "initial_is_fl_on"
0108 => GGET     6  11      ; "G_reader_settings"
0109    MOV      7   6
0110    TGETS    6   6  12  ; "readSetting"
0111    KSTR     8  19      ; "frontlight_max_warmth_hour"
0112    CALL     6   2   3
0113    ISF          6
0114    JMP      7 => 0116
0115    TSETS    6   0  20  ; "max_warmth_hour"
0116 => ISF          4
0117    JMP      7 => 0124
0118    KPRI     7   2
0119    TSETS    7   0  21  ; "auto_warmth"
0120    MOV      8   0
0121    TGETS    7   0  22  ; "calculateAutoWarmth"
0122    CALL     7   1   2
0123    JMP      7 => 0127
0124 => ISEQP    3   0
0125    JMP      7 => 0127
0126    TSETS    3   0   7  ; "fl_warmth"
0127 => TGETS    7   0  18  ; "initial_is_fl_on"
0128    ISNEP    7   1
0129    JMP      7 => 0135
0130    TGETS    7   0  17  ; "hw_intensity"
0131    ISNEN    7   0      ; 0
0132    JMP      7 => 0135
0133    KSHORT   7   1
0134    TSETS    7   0  17  ; "hw_intensity"
0135 => RET0     0   1

-- BYTECODE -- powerd.lua:108-169
0001    KSHORT   1  20
0002    TSETS    1   0   0  ; "hw_intensity"
0003    KPRI     1   2
0004    TSETS    1   0   1  ; "initial_is_fl_on"
0005    KPRI     1   1
0006    TSETS    1   0   2  ; "autowarmth_job_running"
0007    TGETS    1   0   3  ; "device"
0008    MOV      2   1
0009    TGETS    1   1   4  ; "hasFrontlight"
0010    CALL     1   2   2
0011    ISF          1
0012    JMP      2 => 0120
0013    TGETS    1   0   3  ; "device"
0014    MOV      2   1
0015    TGETS    1   1   5  ; "hasNaturalLight"
0016    CALL     1   2   2
0017    ISF          1
0018    JMP      2 => 0079
0019    GGET     1   6      ; "G_reader_settings"
0020    MOV      2   1
0021    TGETS    1   1   7  ; "readSetting"
0022    KSTR     3   8      ; "natural_light_config"
0023    CALL     1   2   3
0024    ISF          1
0025    JMP      2 => 0035
0026    GGET     2   9      ; "pairs"
0027    MOV      3   1
0028    CALL     2   4   2
0029    ISNEXT   5 => 0033
0030 => TGETS    7   0   3  ; "device"
0031    TGETS    7   7  10  ; "frontlight_settings"
0032    TSETV    6   7   5
0033 => ITERN    5   3   3
0034    ITERL    5 => 0030
0035 => TGETS    2   0   3  ; "device"
0036    TGETS    2   2  10  ; "frontlight_settings"
0037    TGETS    2   2  12  ; "nl_min"
0038    IST          2
0039    JMP      3 => 0041
0040    TGETS    2   0  11  ; "fl_warmth_min"
0041 => TSETS    2   0  11  ; "fl_warmth_min"
0042    TGETS    2   0   3  ; "device"
0043    TGETS    2   2  10  ; "frontlight_settings"
0044    TGETS    2   2  14  ; "nl_max"
0045    IST          2
0046    JMP      3 => 0048
0047    TGETS    2   0  13  ; "fl_warmth_max"
0048 => TSETS    2   0  13  ; "fl_warmth_max"
0049    TGETS    2   0   3  ; "device"
0050    MOV      3   2
0051    TGETS    2   2  15  ; "hasNaturalLightMixer"
0052    CALL     2   2   2
0053    ISF          2
0054    JMP      3 => 0066
0055    GGET     2  16      ; "require"
0056    KSTR     3  17      ; "ffi/kobolight"
0057    CALL     2   2   2
0058    GGET     3  18      ; "pcall"
0059    TGETS    4   2  19  ; "open"
0060    CALL     3   3   2
0061    ISF          3
0062    JMP      5 => 0066
0063    TGETS    5   0   3  ; "device"
0064    TGETS    5   5  10  ; "frontlight_settings"
0065    TSETS    4   5  20  ; "frontlight_ioctl"
0066 => UGET     2   0      ; SysfsLight
0067    MOV      3   2
0068    TGETS    2   2  22  ; "new"
0069    TGETS    4   0   3  ; "device"
0070    TGETS    4   4  10  ; "frontlight_settings"
0071    CALL     2   2   3
0072    TSETS    2   0  21  ; "fl"
0073    KSHORT   2   0
0074    TSETS    2   0  23  ; "fl_warmth"
0075    MOV      3   0
0076    TGETS    2   0  24  ; "_syncKoboLightOnStart"
0077    CALL     2   1   2
0078    JMP      1 => 0091
0079 => GGET     1  16      ; "require"
0080    KSTR     2  17      ; "ffi/kobolight"
0081    CALL     1   2   2
0082    GGET     2  18      ; "pcall"
0083    TGETS    3   1  19  ; "open"
0084    CALL     2   3   2
0085    ISF          2
0086    JMP      4 => 0091
0087    TSETS    3   0  21  ; "fl"
0088    MOV      5   0
0089    TGETS    4   0  24  ; "_syncKoboLightOnStart"
0090    CALL     4   1   2
0091 => MOV      2   0
0092    TGETS    1   0  25  ; "isFrontlightOnHW"
0093    CALL     1   2   2
0094    ISF          1
0095    JMP      2 => 0113
0096    TGETS    1   0   3  ; "device"
0097    MOV      2   1
0098    TGETS    1   1  15  ; "hasNaturalLightMixer"
0099    CALL     1   2   2
0100    ISF          1
0101    JMP      2 => 0106
0102    MOV      2   0
0103    TGETS    1   0  26  ; "setWarmth"
0104    TGETS    3   0  23  ; "fl_warmth"
0105    CALL     1   1   3
0106 => MOV      2   0
0107    TGETS    1   0  27  ; "setIntensity"
0108    MOV      4   0
0109    TGETS    3   0  28  ; "frontlightIntensityHW"
0110    CALL     3   0   2
0111    CALLM    1   1   1
0112    JMP      1 => 0120
0113 => TGETS    1   0  21  ; "fl"
0114    MOV      2   1
0115    TGETS    1   1  29  ; "setBrightness"
0116    KSHORT   3   0
0117    CALL     1   1   3
0118    KPRI     1   1
0119    TSETS    1   0   1  ; "initial_is_fl_on"
0120 => RET0     0   1

-- BYTECODE -- powerd.lua:171-216
0001    TGETS    1   0   0  ; "device"
0002    MOV      2   1
0003    TGETS    1   1   1  ; "hasFrontlight"
0004    CALL     1   2   2
0005    ISF          1
0006    JMP      2 => 0112
0007    TGETS    1   0   2  ; "fl_intensity"
0008    TGETS    2   0   3  ; "is_fl_on"
0009    IST          2
0010    JMP      3 => 0015
0011    TGETS    2   0   4  ; "fl_was_on"
0012    IST          2
0013    JMP      3 => 0015
0014    KPRI     2   1
0015 => TGETS    3   0   5  ; "fl_warmth"
0016    TGETS    4   0   6  ; "auto_warmth"
0017    TGETS    5   0   7  ; "max_warmth_hour"
0018    GGET     6   8      ; "G_reader_settings"
0019    MOV      7   6
0020    TGETS    6   6   9  ; "saveSetting"
0021    KSTR     8  10      ; "frontlight_intensity"
0022    MOV      9   1
0023    CALL     6   1   4
0024    GGET     6   8      ; "G_reader_settings"
0025    MOV      7   6
0026    TGETS    6   6   9  ; "saveSetting"
0027    KSTR     8  11      ; "is_frontlight_on"
0028    MOV      9   2
0029    CALL     6   1   4
0030    ISEQP    3   0
0031    JMP      6 => 0050
0032    GGET     6   8      ; "G_reader_settings"
0033    MOV      7   6
0034    TGETS    6   6   9  ; "saveSetting"
0035    KSTR     8  12      ; "frontlight_warmth"
0036    MOV      9   3
0037    CALL     6   1   4
0038    GGET     6   8      ; "G_reader_settings"
0039    MOV      7   6
0040    TGETS    6   6   9  ; "saveSetting"
0041    KSTR     8  13      ; "frontlight_auto_warmth"
0042    MOV      9   4
0043    CALL     6   1   4
0044    GGET     6   8      ; "G_reader_settings"
0045    MOV      7   6
0046    TGETS    6   6   9  ; "saveSetting"
0047    KSTR     8  14      ; "frontlight_max_warmth_hour"
0048    MOV      9   5
0049    CALL     6   1   4
0050 => GGET     6  15      ; "KOBO_SYNC_BRIGHTNESS_WITH_NICKEL"
0051    ISF          6
0052    JMP      7 => 0112
0053    UGET     6   0      ; NickelConf
0054    TGETS    6   6  16  ; "frontLightState"
0055    TGETS    6   6  17  ; "get"
0056    CALL     6   2   1
0057    ISEQP    6   0
0058    JMP      6 => 0071
0059    UGET     6   0      ; NickelConf
0060    TGETS    6   6  16  ; "frontLightState"
0061    TGETS    6   6  17  ; "get"
0062    CALL     6   2   1
0063    ISEQV    6   2
0064    JMP      6 => 0074
0065    UGET     6   0      ; NickelConf
0066    TGETS    6   6  16  ; "frontLightState"
0067    TGETS    6   6  18  ; "set"
0068    MOV      7   2
0069    CALL     6   1   2
0070    JMP      6 => 0074
0071 => IST          2
0072    JMP      6 => 0074
0073    TGETS    1   0  19  ; "fl_min"
0074 => UGET     6   0      ; NickelConf
0075    TGETS    6   6  20  ; "frontLightLevel"
0076    TGETS    6   6  17  ; "get"
0077    CALL     6   2   1
0078    ISEQV    6   1
0079    JMP      6 => 0085
0080    UGET     6   0      ; NickelConf
0081    TGETS    6   6  20  ; "frontLightLevel"
0082    TGETS    6   6  18  ; "set"
0083    MOV      7   1
0084    CALL     6   1   2
0085 => ISEQP    3   0
0086    JMP      6 => 0112
0087    SUBNV    6   3   0  ; 100
0088    MULVN    6   6   1  ; 49
0089    ADDVN    6   6   2  ; 1500
0090    UGET     7   0      ; NickelConf
0091    TGETS    7   7  21  ; "colorSetting"
0092    TGETS    7   7  17  ; "get"
0093    CALL     7   2   1
0094    ISEQV    7   6
0095    JMP      7 => 0101
0096    UGET     7   0      ; NickelConf
0097    TGETS    7   7  21  ; "colorSetting"
0098    TGETS    7   7  18  ; "set"
0099    MOV      8   6
0100    CALL     7   1   2
0101 => UGET     7   0      ; NickelConf
0102    TGETS    7   7  22  ; "autoColorEnabled"
0103    TGETS    7   7  17  ; "get"
0104    CALL     7   2   1
0105    ISEQV    7   4
0106    JMP      7 => 0112
0107    UGET     7   0      ; NickelConf
0108    TGETS    7   7  22  ; "autoColorEnabled"
0109    TGETS    7   7  18  ; "set"
0110    MOV      8   4
0111    CALL     7   1   2
0112 => RET0     0   1

-- BYTECODE -- powerd.lua:218-220
0001    TGETS    1   0   0  ; "hw_intensity"
0002    RET1     1   2

-- BYTECODE -- powerd.lua:222-231
0001    TGETS    1   0   0  ; "initial_is_fl_on"
0002    ISEQP    1   0
0003    JMP      1 => 0008
0004    TGETS    1   0   0  ; "initial_is_fl_on"
0005    KPRI     2   0
0006    TSETS    2   0   0  ; "initial_is_fl_on"
0007    RET1     1   2
0008 => TGETS    1   0   1  ; "hw_intensity"
0009    KSHORT   2   0
0010    ISLT     2   1
0011    JMP      1 => 0014
0012    KPRI     1   1
0013    JMP      2 => 0015
0014 => KPRI     1   2
0015 => RET1     1   2

-- BYTECODE -- powerd.lua:233-247
0001    TGETS    2   0   0  ; "fl"
0002    ISNEP    2   0
0003    JMP      2 => 0005
0004    RET0     0   1
0005 => TGETS    2   0   1  ; "fl_warmth"
0006    ISEQP    2   0
0007    JMP      2 => 0014
0008    TGETS    2   0   2  ; "device"
0009    MOV      3   2
0010    TGETS    2   2   3  ; "hasNaturalLightMixer"
0011    CALL     2   2   2
0012    ISF          2
0013    JMP      3 => 0020
0014 => TGETS    2   0   0  ; "fl"
0015    MOV      3   2
0016    TGETS    2   2   4  ; "setBrightness"
0017    MOV      4   1
0018    CALL     2   1   3
0019    JMP      2 => 0026
0020 => TGETS    2   0   0  ; "fl"
0021    MOV      3   2
0022    TGETS    2   2   5  ; "setNaturalBrightness"
0023    MOV      4   1
0024    TGETS    5   0   1  ; "fl_warmth"
0025    CALL     2   1   4
0026 => TSETS    1   0   6  ; "hw_intensity"
0027    MOV      3   0
0028    TGETS    2   0   7  ; "_decideFrontlightState"
0029    CALL     2   1   2
0030    RET0     0   1

-- BYTECODE -- powerd.lua:249-261
0001    TGETS    2   0   0  ; "fl"
0002    ISNEP    2   0
0003    JMP      2 => 0005
0004    RET0     0   1
0005 => IST          1
0006    JMP      2 => 0013
0007    TGETS    2   0   1  ; "auto_warmth"
0008    ISF          2
0009    JMP      3 => 0013
0010    MOV      3   0
0011    TGETS    2   0   2  ; "calculateAutoWarmth"
0012    CALL     2   1   2
0013 => ISTC     2   1
0014    JMP      2 => 0016
0015    TGETS    2   0   3  ; "fl_warmth"
0016 => TSETS    2   0   3  ; "fl_warmth"
0017    TGETS    2   0   4  ; "device"
0018    MOV      3   2
0019    TGETS    2   2   5  ; "hasNaturalLightMixer"
0020    CALL     2   2   2
0021    IST          2
0022    JMP      3 => 0028
0023    MOV      3   0
0024    TGETS    2   0   6  ; "isFrontlightOnHW"
0025    CALL     2   2   2
0026    ISF          2
0027    JMP      3 => 0033
0028 => TGETS    2   0   0  ; "fl"
0029    MOV      3   2
0030    TGETS    2   2   7  ; "setWarmth"
0031    TGETS    4   0   3  ; "fl_warmth"
0032    CALL     2   1   3
0033 => RET0     0   1

-- BYTECODE -- powerd.lua:300-304
0001    UGET     0   0      ; self
0002    TGETS    0   0   0  ; "auto_warmth"
0003    ISF          0
0004    JMP      1 => 0009
0005    UGET     0   0      ; self
0006    MOV      1   0
0007    TGETS    0   0   1  ; "setWarmth"
0008    CALL     0   1   2
0009 => RET0     0   1

-- BYTECODE -- powerd.lua:265-308
0001    GGET     1   0      ; "os"
0002    TGETS    1   1   1  ; "date"
0003    KSTR     2   2      ; "%H"
0004    CALL     1   2   2
0005    GGET     2   0      ; "os"
0006    TGETS    2   2   1  ; "date"
0007    KSTR     3   3      ; "%M"
0008    CALL     2   2   2
0009    DIVVN    2   2   0  ; 60
0010    ADDVV    1   1   2
0011    TGETS    2   0   4  ; "max_warmth_hour"
0012    SUBVV    3   2   1
0013    KSHORT   4   0
0014    ISGE     3   4
0015    JMP      4 => 0017
0016    ADDVN    3   3   1  ; 24
0017 => KSHORT   4  12
0018    ISGE     3   4
0019    JMP      4 => 0028
0020    GGET     4   6      ; "math"
0021    TGETS    4   4   7  ; "max"
0022    SUBNV    5   3   2  ; 5
0023    MULNV    5   5   3  ; 20
0024    KSHORT   6   0
0025    CALL     4   2   3
0026    TSETS    4   0   5  ; "fl_warmth"
0027    JMP      4 => 0042
0028 => KSHORT   4  22
0029    ISGE     4   3
0030    JMP      4 => 0034
0031    KSHORT   4 100
0032    TSETS    4   0   5  ; "fl_warmth"
0033    JMP      4 => 0042
0034 => GGET     4   6      ; "math"
0035    TGETS    4   4   7  ; "max"
0036    SUBNV    5   3   4  ; 22
0037    MULNV    5   5   5  ; 50
0038    SUBNV    5   5   6  ; 100
0039    KSHORT   6   0
0040    CALL     4   2   3
0041    TSETS    4   0   5  ; "fl_warmth"
0042 => GGET     4   6      ; "math"
0043    TGETS    4   4   8  ; "floor"
0044    TGETS    5   0   5  ; "fl_warmth"
0045    ADDVN    5   5   7  ; 0.5
0046    CALL     4   2   2
0047    TSETS    4   0   5  ; "fl_warmth"
0048    TGETS    4   0   9  ; "fl"
0049    ISF          4
0050    JMP      5 => 0054
0051    TGETS    4   0   9  ; "fl"
0052    TGETS    5   0   5  ; "fl_warmth"
0053    TSETS    5   4  10  ; "current_warmth"
0054 => TGETS    4   0  11  ; "autowarmth_job_running"
0055    IST          4
0056    JMP      4 => 0067
0057    GGET     4  12      ; "table"
0058    TGETS    4   4  13  ; "insert"
0059    UGET     5   0      ; PluginShare
0060    TGETS    5   5  14  ; "backgroundJobs"
0061    TDUP     6  15
0062    FNEW     7  16      ; powerd.lua:300
0063    TSETS    7   6  17  ; "executable"
0064    CALL     4   1   3
0065    KPRI     4   2
0066    TSETS    4   0  11  ; "autowarmth_job_running"
0067 => UCLO     0 => 0068
0068 => RET0     0   1

-- BYTECODE -- powerd.lua:310-312
0001    MOV      2   0
0002    TGETS    1   0   0  ; "read_int_file"
0003    TGETS    3   0   1  ; "batt_capacity_file"
0004    CALLT    1   3

-- BYTECODE -- powerd.lua:314-316
0001    MOV      2   0
0002    TGETS    1   0   0  ; "read_str_file"
0003    TGETS    3   0   1  ; "is_charging_file"
0004    CALL     1   2   3
0005    ISEQS    1   2      ; "Charging\n"
0006    JMP      1 => 0009
0007    KPRI     1   1
0008    JMP      2 => 0010
0009 => KPRI     1   2
0010 => RET1     1   2

-- BYTECODE -- powerd.lua:323-334
0001    KSHORT   0   1
0002    KSHORT   1   5
0003    KSHORT   2   1
0004    FORI     0 => 0034
0005 => UGET     4   0      ; self
0006    MOV      5   4
0007    TGETS    4   4   0  ; "_setIntensity"
0008    GGET     6   1      ; "math"
0009    TGETS    6   6   2  ; "floor"
0010    UGET     7   0      ; self
0011    TGETS    7   7   3  ; "fl_intensity"
0012    UGET     8   0      ; self
0013    TGETS    8   8   3  ; "fl_intensity"
0014    DIVVN    8   8   0  ; 5
0015    MULVV    8   8   3
0016    SUBVV    7   7   8
0017    CALL     6   0   2
0018    CALLM    4   1   1
0019    UGET     4   0      ; self
0020    TGETS    4   4   4  ; "device"
0021    MOV      5   4
0022    TGETS    4   4   5  ; "hasNaturalLight"
0023    CALL     4   2   2
0024    IST          4
0025    JMP      4 => 0033
0026    KSHORT   4   5
0027    ISGE     3   4
0028    JMP      4 => 0033
0029    UGET     4   1      ; util
0030    TGETS    4   4   6  ; "usleep"
0031    KNUM     5   1      ; 35000
0032    CALL     4   1   2
0033 => FORL     0 => 0005
0034 => RET0     0   1

-- BYTECODE -- powerd.lua:318-350
0001    MOV      2   0
0002    TGETS    1   0   0  ; "isFrontlightOnHW"
0003    CALL     1   2   2
0004    IST          1
0005    JMP      1 => 0007
0006    UCLO     0 => 0046
0007 => GGET     1   1      ; "require"
0008    KSTR     2   2      ; "ffi/util"
0009    CALL     1   2   2
0010    TGETS    2   1   3  ; "runInSubProcess"
0011    FNEW     3   4      ; powerd.lua:323
0012    KPRI     4   1
0013    KPRI     5   2
0014    CALL     2   1   4
0015    TGETS    2   0   6  ; "fl_min"
0016    TSETS    2   0   5  ; "hw_intensity"
0017    TGETS    2   0   7  ; "fl"
0018    ISF          2
0019    JMP      3 => 0023
0020    TGETS    2   0   7  ; "fl"
0021    TGETS    3   0   6  ; "fl_min"
0022    TSETS    3   2   8  ; "current_brightness"
0023 => MOV      3   0
0024    TGETS    2   0   9  ; "_decideFrontlightState"
0025    CALL     2   1   2
0026    GGET     2  10      ; "package"
0027    TGETS    2   2  11  ; "loaded"
0028    TGETS    2   2  12  ; "ui/uimanager"
0029    ISEQP    2   0
0030    JMP      2 => 0044
0031    GGET     2   1      ; "require"
0032    KSTR     3  13      ; "ui/event"
0033    CALL     2   2   2
0034    GGET     3   1      ; "require"
0035    KSTR     4  12      ; "ui/uimanager"
0036    CALL     3   2   2
0037    MOV      5   3
0038    TGETS    4   3  14  ; "broadcastEvent"
0039    MOV      7   2
0040    TGETS    6   2  15  ; "new"
0041    KSTR     8  16      ; "FrontlightStateChanged"
0042    CALL     6   0   3
0043    CALLM    4   1   1
0044 => UCLO     0 => 0045
0045 => RET0     0   1
0046 => RET0     0   1

-- BYTECODE -- powerd.lua:362-373
0001    KSHORT   0   1
0002    KSHORT   1   5
0003    KSHORT   2   1
0004    FORI     0 => 0034
0005 => UGET     4   0      ; self
0006    MOV      5   4
0007    TGETS    4   4   0  ; "_setIntensity"
0008    GGET     6   1      ; "math"
0009    TGETS    6   6   2  ; "ceil"
0010    UGET     7   0      ; self
0011    TGETS    7   7   3  ; "fl_min"
0012    UGET     8   0      ; self
0013    TGETS    8   8   4  ; "fl_intensity"
0014    DIVVN    8   8   0  ; 5
0015    MULVV    8   8   3
0016    ADDVV    7   7   8
0017    CALL     6   0   2
0018    CALLM    4   1   1
0019    UGET     4   0      ; self
0020    TGETS    4   4   5  ; "device"
0021    MOV      5   4
0022    TGETS    4   4   6  ; "hasNaturalLight"
0023    CALL     4   2   2
0024    IST          4
0025    JMP      4 => 0033
0026    KSHORT   4   5
0027    ISGE     3   4
0028    JMP      4 => 0033
0029    UGET     4   1      ; util
0030    TGETS    4   4   7  ; "usleep"
0031    KNUM     5   1      ; 35000
0032    CALL     4   1   2
0033 => FORL     0 => 0005
0034 => RET0     0   1

-- BYTECODE -- powerd.lua:351-389
0001    TGETS    1   0   0  ; "is_fl_on"
0002    ISNEP    1   1
0003    JMP      1 => 0014
0004    TGETS    1   0   1  ; "hw_intensity"
0005    TGETS    2   0   2  ; "fl_min"
0006    ISGE     2   1
0007    JMP      1 => 0014
0008    TGETS    1   0   1  ; "hw_intensity"
0009    TGETS    2   0   3  ; "fl_intensity"
0010    ISNEV    1   2
0011    JMP      1 => 0014
0012    TGETS    1   0   2  ; "fl_min"
0013    TSETS    1   0   1  ; "hw_intensity"
0014 => MOV      2   0
0015    TGETS    1   0   4  ; "isFrontlightOnHW"
0016    CALL     1   2   2
0017    ISF          1
0018    JMP      2 => 0020
0019    UCLO     0 => 0059
0020 => GGET     1   5      ; "require"
0021    KSTR     2   6      ; "ffi/util"
0022    CALL     1   2   2
0023    TGETS    2   1   7  ; "runInSubProcess"
0024    FNEW     3   8      ; powerd.lua:362
0025    KPRI     4   1
0026    KPRI     5   2
0027    CALL     2   1   4
0028    TGETS    2   0   3  ; "fl_intensity"
0029    TSETS    2   0   1  ; "hw_intensity"
0030    TGETS    2   0   9  ; "fl"
0031    ISF          2
0032    JMP      3 => 0036
0033    TGETS    2   0   9  ; "fl"
0034    TGETS    3   0   3  ; "fl_intensity"
0035    TSETS    3   2  10  ; "current_brightness"
0036 => MOV      3   0
0037    TGETS    2   0  11  ; "_decideFrontlightState"
0038    CALL     2   1   2
0039    GGET     2  12      ; "package"
0040    TGETS    2   2  13  ; "loaded"
0041    TGETS    2   2  14  ; "ui/uimanager"
0042    ISEQP    2   0
0043    JMP      2 => 0057
0044    GGET     2   5      ; "require"
0045    KSTR     3  15      ; "ui/event"
0046    CALL     2   2   2
0047    GGET     3   5      ; "require"
0048    KSTR     4  14      ; "ui/uimanager"
0049    CALL     3   2   2
0050    MOV      5   3
0051    TGETS    4   3  16  ; "broadcastEvent"
0052    MOV      7   2
0053    TGETS    6   2  17  ; "new"
0054    KSTR     8  18      ; "FrontlightStateChanged"
0055    CALL     6   0   3
0056    CALLM    4   1   1
0057 => UCLO     0 => 0058
0058 => RET0     0   1
0059 => RET0     0   1

-- BYTECODE -- powerd.lua:392-398
0001    TGETS    1   0   0  ; "fl"
0002    ISNEP    1   0
0003    JMP      1 => 0005
0004    RET0     0   1
0005 => TGETS    1   0   2  ; "is_fl_on"
0006    TSETS    1   0   1  ; "fl_was_on"
0007    MOV      2   0
0008    TGETS    1   0   3  ; "turnOffFrontlight"
0009    CALL     1   1   2
0010    RET0     0   1

-- BYTECODE -- powerd.lua:401-415
0001    TGETS    1   0   0  ; "fl"
0002    ISNEP    1   0
0003    JMP      1 => 0005
0004    RET0     0   1
0005 => TGETS    1   0   1  ; "fl_was_on"
0006    IST          1
0007    JMP      1 => 0009
0008    RET0     0   1
0009 => TGETS    1   0   2  ; "fl_warmth"
0010    ISEQP    1   0
0011    JMP      1 => 0028
0012    TGETS    1   0   3  ; "auto_warmth"
0013    ISF          1
0014    JMP      2 => 0028
0015    MOV      2   0
0016    TGETS    1   0   4  ; "calculateAutoWarmth"
0017    CALL     1   1   2
0018    TGETS    1   0   5  ; "device"
0019    MOV      2   1
0020    TGETS    1   1   6  ; "hasNaturalLightMixer"
0021    CALL     1   2   2
0022    ISF          1
0023    JMP      2 => 0028
0024    MOV      2   0
0025    TGETS    1   0   7  ; "setWarmth"
0026    TGETS    3   0   2  ; "fl_warmth"
0027    CALL     1   1   3
0028 => MOV      2   0
0029    TGETS    1   0   8  ; "turnOnFrontlight"
0030    CALL     1   1   2
0031    RET0     0   1

-- BYTECODE -- powerd.lua:0-418
0001    GGET     0   0      ; "require"
0002    KSTR     1   1      ; "device/generic/powerd"
0003    CALL     0   2   2
0004    GGET     1   0      ; "require"
0005    KSTR     2   2      ; "device/kobo/nickel_conf"
0006    CALL     1   2   2
0007    GGET     2   0      ; "require"
0008    KSTR     3   3      ; "pluginshare"
0009    CALL     2   2   2
0010    GGET     3   0      ; "require"
0011    KSTR     4   4      ; "device/sysfs_light"
0012    CALL     3   2   2
0013    KSTR     4   5      ; "/sys/devices/platform/pmic_battery.1/pow"~
0014    MOV      6   0
0015    TGETS    5   0   6  ; "new"
0016    TDUP     7   7
0017    MOV      8   4
0018    KSTR     9   8      ; "capacity"
0019    CAT      8   8   9
0020    TSETS    8   7   9  ; "batt_capacity_file"
0021    MOV      8   4
0022    KSTR     9  10      ; "status"
0023    CAT      8   8   9
0024    TSETS    8   7  11  ; "is_charging_file"
0025    CALL     5   2   3
0026    FNEW     6  13      ; powerd.lua:28
0027    TSETS    6   5  12  ; "_syncKoboLightOnStart"
0028    FNEW     6  15      ; powerd.lua:108
0029    TSETS    6   5  14  ; "init"
0030    FNEW     6  17      ; powerd.lua:171
0031    TSETS    6   5  16  ; "saveSettings"
0032    FNEW     6  19      ; powerd.lua:218
0033    TSETS    6   5  18  ; "frontlightIntensityHW"
0034    FNEW     6  21      ; powerd.lua:222
0035    TSETS    6   5  20  ; "isFrontlightOnHW"
0036    FNEW     6  23      ; powerd.lua:233
0037    TSETS    6   5  22  ; "setIntensityHW"
0038    FNEW     6  25      ; powerd.lua:249
0039    TSETS    6   5  24  ; "setWarmth"
0040    FNEW     6  27      ; powerd.lua:265
0041    TSETS    6   5  26  ; "calculateAutoWarmth"
0042    FNEW     6  29      ; powerd.lua:310
0043    TSETS    6   5  28  ; "getCapacityHW"
0044    FNEW     6  31      ; powerd.lua:314
0045    TSETS    6   5  30  ; "isChargingHW"
0046    FNEW     6  33      ; powerd.lua:318
0047    TSETS    6   5  32  ; "turnOffFrontlightHW"
0048    FNEW     6  35      ; powerd.lua:351
0049    TSETS    6   5  34  ; "turnOnFrontlightHW"
0050    FNEW     6  37      ; powerd.lua:392
0051    TSETS    6   5  36  ; "beforeSuspend"
0052    FNEW     6  39      ; powerd.lua:401
0053    TSETS    6   5  38  ; "afterResume"
0054    UCLO     0 => 0055
0055 => RET1     5   2

