
main <./frontend/ui/widget/progresswidget.lua:0,0> (71 instructions, 284 bytes at 0x7fb95ac068e0)
0+ params, 11 slots, 0 upvalues, 6 locals, 40 constants, 5 functions
	1	[30]	GETGLOBAL	0 -1	; require
	2	[30]	LOADK    	1 -2	; "ui/bidi"
	3	[30]	CALL     	0 2 2
	4	[31]	GETGLOBAL	1 -1	; require
	5	[31]	LOADK    	2 -3	; "ffi/blitbuffer"
	6	[31]	CALL     	1 2 2
	7	[32]	GETGLOBAL	2 -1	; require
	8	[32]	LOADK    	3 -4	; "ui/geometry"
	9	[32]	CALL     	2 2 2
	10	[33]	GETGLOBAL	3 -1	; require
	11	[33]	LOADK    	4 -5	; "ui/widget/widget"
	12	[33]	CALL     	3 2 2
	13	[34]	GETGLOBAL	4 -1	; require
	14	[34]	LOADK    	5 -6	; "device"
	15	[34]	CALL     	4 2 2
	16	[34]	GETTABLE 	4 4 -7	; "screen"
	17	[36]	SELF     	5 3 -8	; "new"
	18	[36]	NEWTABLE 	7 0 16
	19	[37]	SETTABLE 	7 -9 -10	; "width" nil
	20	[38]	SETTABLE 	7 -11 -10	; "height" nil
	21	[39]	SELF     	8 4 -13	; "scaleBySize"
	22	[39]	LOADK    	10 -14	; 3
	23	[39]	CALL     	8 3 2
	24	[39]	SETTABLE 	7 -12 8	; "margin_h" -
	25	[40]	SELF     	8 4 -13	; "scaleBySize"
	26	[40]	LOADK    	10 -16	; 1
	27	[40]	CALL     	8 3 2
	28	[40]	SETTABLE 	7 -15 8	; "margin_v" -
	29	[41]	SELF     	8 4 -13	; "scaleBySize"
	30	[41]	LOADK    	10 -18	; 2
	31	[41]	CALL     	8 3 2
	32	[41]	SETTABLE 	7 -17 8	; "radius" -
	33	[42]	SELF     	8 4 -13	; "scaleBySize"
	34	[42]	LOADK    	10 -16	; 1
	35	[42]	CALL     	8 3 2
	36	[42]	SETTABLE 	7 -19 8	; "bordersize" -
	37	[43]	GETTABLE 	8 1 -21	; "COLOR_BLACK"
	38	[43]	SETTABLE 	7 -20 8	; "bordercolor" -
	39	[44]	GETTABLE 	8 1 -23	; "COLOR_WHITE"
	40	[44]	SETTABLE 	7 -22 8	; "bgcolor" -
	41	[45]	GETTABLE 	8 1 -25	; "COLOR_DIM_GRAY"
	42	[45]	SETTABLE 	7 -24 8	; "rectcolor" -
	43	[46]	SETTABLE 	7 -26 -10	; "percentage" nil
	44	[47]	SETTABLE 	7 -27 -10	; "ticks" nil
	45	[48]	SELF     	8 4 -13	; "scaleBySize"
	46	[48]	LOADK    	10 -14	; 3
	47	[48]	CALL     	8 3 2
	48	[48]	SETTABLE 	7 -28 8	; "tick_width" -
	49	[49]	SETTABLE 	7 -29 -10	; "last" nil
	50	[50]	SETTABLE 	7 -30 -31	; "fill_from_right" false
	51	[51]	SETTABLE 	7 -32 -33	; "allow_mirroring" true
	52	[52]	GETTABLE 	8 0 -35	; "mirroredUILayout"
	53	[52]	CALL     	8 1 2
	54	[52]	SETTABLE 	7 -34 8	; "_mirroredUI" -
	55	[36]	CALL     	5 3 2
	56	[57]	CLOSURE  	6 0	; 0x7fb95ac070a0
	57	[55]	SETTABLE 	5 -36 6	; "getSize" -
	58	[106]	CLOSURE  	6 1	; 0x7fb95ac07220
	59	[106]	MOVE     	0 2
	60	[59]	SETTABLE 	5 -37 6	; "paintTo" -
	61	[110]	CLOSURE  	6 2	; 0x7fb95ac07680
	62	[108]	SETTABLE 	5 -38 6	; "setPercentage" -
	63	[125]	CLOSURE  	6 3	; 0x7fb95ac07d60
	64	[125]	MOVE     	0 0
	65	[112]	SETTABLE 	5 -39 6	; "getPercentageFromPosition" -
	66	[148]	CLOSURE  	6 4	; 0x7fb95ac07e60
	67	[148]	MOVE     	0 4
	68	[148]	MOVE     	0 1
	69	[127]	SETTABLE 	5 -40 6	; "updateStyle" -
	70	[150]	RETURN   	5 2
	71	[150]	RETURN   	0 1

function <./frontend/ui/widget/progresswidget.lua:55,57> (7 instructions, 28 bytes at 0x7fb95ac070a0)
1 param, 3 slots, 0 upvalues, 1 local, 4 constants, 0 functions
	1	[56]	NEWTABLE 	1 0 2
	2	[56]	GETTABLE 	2 0 -2	; "width"
	3	[56]	SETTABLE 	1 -1 2	; "w" -
	4	[56]	GETTABLE 	2 0 -4	; "height"
	5	[56]	SETTABLE 	1 -3 2	; "h" -
	6	[56]	RETURN   	1 2
	7	[57]	RETURN   	0 1

function <./frontend/ui/widget/progresswidget.lua:59,106> (168 instructions, 672 bytes at 0x7fb95ac07220)
4 params, 20 slots, 1 upvalue, 13 locals, 28 constants, 0 functions
	1	[60]	SELF     	4 0 -1	; "getSize"
	2	[60]	CALL     	4 2 2
	3	[61]	GETUPVAL 	5 0	; Geom
	4	[61]	SELF     	5 5 -3	; "new"
	5	[61]	NEWTABLE 	7 0 4
	6	[62]	SETTABLE 	7 -4 2	; "x" -
	7	[62]	SETTABLE 	7 -5 3	; "y" -
	8	[63]	GETTABLE 	8 4 -6	; "w"
	9	[63]	SETTABLE 	7 -6 8	; "w" -
	10	[64]	GETTABLE 	8 4 -7	; "h"
	11	[64]	SETTABLE 	7 -7 8	; "h" -
	12	[61]	CALL     	5 3 2
	13	[65]	SETTABLE 	0 -2 5	; "dimen" -
	14	[66]	GETTABLE 	5 0 -2	; "dimen"
	15	[66]	GETTABLE 	5 5 -6	; "w"
	16	[66]	EQ       	1 5 -8	; - 0
	17	[66]	JMP      	4	; to 22
	18	[66]	GETTABLE 	5 0 -2	; "dimen"
	19	[66]	GETTABLE 	5 5 -7	; "h"
	20	[66]	EQ       	0 5 -8	; - 0
	21	[66]	JMP      	1	; to 23
	22	[66]	RETURN   	0 1
	23	[69]	SELF     	5 1 -9	; "paintRoundedRect"
	24	[69]	MOVE     	7 2
	25	[69]	MOVE     	8 3
	26	[69]	GETTABLE 	9 4 -6	; "w"
	27	[69]	GETTABLE 	10 4 -7	; "h"
	28	[69]	GETTABLE 	11 0 -10	; "bgcolor"
	29	[69]	GETTABLE 	12 0 -11	; "radius"
	30	[69]	CALL     	5 8 1
	31	[71]	SELF     	5 1 -12	; "paintBorder"
	32	[71]	MOVE     	7 2
	33	[71]	MOVE     	8 3
	34	[72]	GETTABLE 	9 4 -6	; "w"
	35	[72]	GETTABLE 	10 4 -7	; "h"
	36	[73]	GETTABLE 	11 0 -13	; "bordersize"
	37	[73]	GETTABLE 	12 0 -14	; "bordercolor"
	38	[73]	GETTABLE 	13 0 -11	; "radius"
	39	[71]	CALL     	5 9 1
	40	[75]	GETTABLE 	5 0 -15	; "percentage"
	41	[75]	LE       	0 -8 5	; 0 -
	42	[75]	JMP      	78	; to 121
	43	[75]	GETTABLE 	5 0 -15	; "percentage"
	44	[75]	LE       	0 5 -16	; - 1
	45	[75]	JMP      	75	; to 121
	46	[76]	GETTABLE 	5 0 -17	; "fill_from_right"
	47	[76]	TEST     	5 0 1
	48	[76]	JMP      	6	; to 55
	49	[76]	GETTABLE 	5 0 -18	; "_mirroredUI"
	50	[76]	TEST     	5 0 0
	51	[76]	JMP      	42	; to 94
	52	[76]	GETTABLE 	5 0 -17	; "fill_from_right"
	53	[76]	TEST     	5 0 1
	54	[76]	JMP      	39	; to 94
	55	[77]	SELF     	5 1 -19	; "paintRect"
	56	[77]	GETTABLE 	7 0 -20	; "margin_h"
	57	[77]	ADD      	7 2 7
	58	[77]	GETGLOBAL	8 -21	; math
	59	[77]	GETTABLE 	8 8 -22	; "ceil"
	60	[77]	GETTABLE 	9 4 -6	; "w"
	61	[77]	GETTABLE 	10 0 -20	; "margin_h"
	62	[77]	MUL      	10 -23 10	; 2 -
	63	[77]	SUB      	9 9 10
	64	[77]	GETTABLE 	10 0 -15	; "percentage"
	65	[77]	SUB      	10 -16 10	; 1 -
	66	[77]	MUL      	9 9 10
	67	[77]	CALL     	8 2 2
	68	[77]	ADD      	7 7 8
	69	[78]	GETGLOBAL	8 -21	; math
	70	[78]	GETTABLE 	8 8 -22	; "ceil"
	71	[78]	GETTABLE 	9 0 -24	; "margin_v"
	72	[78]	ADD      	9 3 9
	73	[78]	GETTABLE 	10 0 -13	; "bordersize"
	74	[78]	ADD      	9 9 10
	75	[78]	CALL     	8 2 2
	76	[79]	GETGLOBAL	9 -21	; math
	77	[79]	GETTABLE 	9 9 -22	; "ceil"
	78	[79]	GETTABLE 	10 4 -6	; "w"
	79	[79]	GETTABLE 	11 0 -20	; "margin_h"
	80	[79]	MUL      	11 -23 11	; 2 -
	81	[79]	SUB      	10 10 11
	82	[79]	GETTABLE 	11 0 -15	; "percentage"
	83	[79]	MUL      	10 10 11
	84	[79]	CALL     	9 2 2
	85	[80]	GETTABLE 	10 4 -7	; "h"
	86	[80]	GETTABLE 	11 0 -24	; "margin_v"
	87	[80]	GETTABLE 	12 0 -13	; "bordersize"
	88	[80]	ADD      	11 11 12
	89	[80]	MUL      	11 -23 11	; 2 -
	90	[80]	SUB      	10 10 11
	91	[81]	GETTABLE 	11 0 -25	; "rectcolor"
	92	[77]	CALL     	5 7 1
	93	[81]	JMP      	27	; to 121
	94	[83]	SELF     	5 1 -19	; "paintRect"
	95	[83]	GETTABLE 	7 0 -20	; "margin_h"
	96	[83]	ADD      	7 2 7
	97	[84]	GETGLOBAL	8 -21	; math
	98	[84]	GETTABLE 	8 8 -22	; "ceil"
	99	[84]	GETTABLE 	9 0 -24	; "margin_v"
	100	[84]	ADD      	9 3 9
	101	[84]	GETTABLE 	10 0 -13	; "bordersize"
	102	[84]	ADD      	9 9 10
	103	[84]	CALL     	8 2 2
	104	[85]	GETGLOBAL	9 -21	; math
	105	[85]	GETTABLE 	9 9 -22	; "ceil"
	106	[85]	GETTABLE 	10 4 -6	; "w"
	107	[85]	GETTABLE 	11 0 -20	; "margin_h"
	108	[85]	MUL      	11 -23 11	; 2 -
	109	[85]	SUB      	10 10 11
	110	[85]	GETTABLE 	11 0 -15	; "percentage"
	111	[85]	MUL      	10 10 11
	112	[85]	CALL     	9 2 2
	113	[86]	GETTABLE 	10 4 -7	; "h"
	114	[86]	GETTABLE 	11 0 -24	; "margin_v"
	115	[86]	GETTABLE 	12 0 -13	; "bordersize"
	116	[86]	ADD      	11 11 12
	117	[86]	MUL      	11 -23 11	; 2 -
	118	[86]	SUB      	10 10 11
	119	[86]	GETTABLE 	11 0 -25	; "rectcolor"
	120	[83]	CALL     	5 7 1
	121	[89]	GETTABLE 	5 0 -26	; "ticks"
	122	[89]	TEST     	5 0 0
	123	[89]	JMP      	44	; to 168
	124	[89]	GETTABLE 	5 0 -27	; "last"
	125	[89]	TEST     	5 0 0
	126	[89]	JMP      	41	; to 168
	127	[89]	GETTABLE 	5 0 -27	; "last"
	128	[89]	LT       	0 -8 5	; 0 -
	129	[89]	JMP      	38	; to 168
	130	[90]	GETTABLE 	5 4 -6	; "w"
	131	[90]	GETTABLE 	6 0 -20	; "margin_h"
	132	[90]	MUL      	6 -23 6	; 2 -
	133	[90]	SUB      	5 5 6
	134	[91]	GETTABLE 	6 0 -24	; "margin_v"
	135	[91]	ADD      	6 3 6
	136	[91]	GETTABLE 	7 0 -13	; "bordersize"
	137	[91]	ADD      	6 6 7
	138	[92]	GETTABLE 	7 4 -7	; "h"
	139	[92]	GETTABLE 	8 0 -24	; "margin_v"
	140	[92]	GETTABLE 	9 0 -13	; "bordersize"
	141	[92]	ADD      	8 8 9
	142	[92]	MUL      	8 -23 8	; 2 -
	143	[92]	SUB      	7 7 8
	144	[93]	LOADK    	8 -16	; 1
	145	[93]	GETTABLE 	9 0 -26	; "ticks"
	146	[93]	LEN      	9 9
	147	[93]	LOADK    	10 -16	; 1
	148	[93]	FORPREP  	8 18	; to 167
	149	[94]	GETTABLE 	12 0 -26	; "ticks"
	150	[94]	GETTABLE 	12 12 11
	151	[94]	GETTABLE 	13 0 -27	; "last"
	152	[94]	DIV      	12 12 13
	153	[94]	MUL      	12 5 12
	154	[95]	GETTABLE 	13 0 -18	; "_mirroredUI"
	155	[95]	TEST     	13 0 0
	156	[95]	JMP      	1	; to 158
	157	[96]	SUB      	12 5 12
	158	[98]	SELF     	13 1 -19	; "paintRect"
	159	[99]	GETTABLE 	15 0 -20	; "margin_h"
	160	[99]	ADD      	15 2 15
	161	[99]	ADD      	15 15 12
	162	[100]	MOVE     	16 6
	163	[101]	GETTABLE 	17 0 -28	; "tick_width"
	164	[102]	MOVE     	18 7
	165	[103]	GETTABLE 	19 0 -14	; "bordercolor"
	166	[98]	CALL     	13 7 1
	167	[93]	FORLOOP  	8 -19	; to 149
	168	[106]	RETURN   	0 1

function <./frontend/ui/widget/progresswidget.lua:108,110> (2 instructions, 8 bytes at 0x7fb95ac07680)
2 params, 2 slots, 0 upvalues, 2 locals, 1 constant, 0 functions
	1	[109]	SETTABLE 	0 -1 1	; "percentage" -
	2	[110]	RETURN   	0 1

function <./frontend/ui/widget/progresswidget.lua:112,125> (33 instructions, 132 bytes at 0x7fb95ac07d60)
2 params, 5 slots, 1 upvalue, 4 locals, 7 constants, 0 functions
	1	[113]	TEST     	1 0 0
	2	[113]	JMP      	3	; to 6
	3	[113]	GETTABLE 	2 1 -1	; "x"
	4	[113]	TEST     	2 0 1
	5	[113]	JMP      	2	; to 8
	6	[114]	LOADNIL  	2 2
	7	[114]	RETURN   	2 2
	8	[116]	GETTABLE 	2 0 -2	; "dimen"
	9	[116]	GETTABLE 	2 2 -3	; "w"
	10	[116]	GETTABLE 	3 0 -4	; "margin_h"
	11	[116]	MUL      	3 -5 3	; 2 -
	12	[116]	SUB      	2 2 3
	13	[117]	GETTABLE 	3 1 -1	; "x"
	14	[117]	GETTABLE 	4 0 -2	; "dimen"
	15	[117]	GETTABLE 	4 4 -1	; "x"
	16	[117]	SUB      	3 3 4
	17	[117]	GETTABLE 	4 0 -4	; "margin_h"
	18	[117]	SUB      	3 3 4
	19	[118]	LT       	1 3 -6	; - 0
	20	[118]	JMP      	2	; to 23
	21	[118]	LT       	0 2 3
	22	[118]	JMP      	2	; to 25
	23	[119]	LOADNIL  	4 4
	24	[119]	RETURN   	4 2
	25	[121]	GETUPVAL 	4 0	; BD
	26	[121]	GETTABLE 	4 4 -7	; "mirroredUILayout"
	27	[121]	CALL     	4 1 2
	28	[121]	TEST     	4 0 0
	29	[121]	JMP      	1	; to 31
	30	[122]	SUB      	3 2 3
	31	[124]	DIV      	4 3 2
	32	[124]	RETURN   	4 2
	33	[125]	RETURN   	0 1

function <./frontend/ui/widget/progresswidget.lua:127,148> (49 instructions, 196 bytes at 0x7fb95ac07e60)
3 params, 6 slots, 2 upvalues, 3 locals, 15 constants, 0 functions
	1	[128]	TEST     	1 0 0
	2	[128]	JMP      	31	; to 34
	3	[129]	TEST     	2 0 0
	4	[129]	JMP      	5	; to 10
	5	[130]	GETUPVAL 	3 0	; Screen
	6	[130]	SELF     	3 3 -2	; "scaleBySize"
	7	[130]	MOVE     	5 2
	8	[130]	CALL     	3 3 2
	9	[130]	SETTABLE 	0 -1 3	; "height" -
	10	[132]	GETUPVAL 	3 0	; Screen
	11	[132]	SELF     	3 3 -2	; "scaleBySize"
	12	[132]	LOADK    	5 -4	; 3
	13	[132]	CALL     	3 3 2
	14	[132]	SETTABLE 	0 -3 3	; "margin_h" -
	15	[133]	GETUPVAL 	3 0	; Screen
	16	[133]	SELF     	3 3 -2	; "scaleBySize"
	17	[133]	LOADK    	5 -6	; 1
	18	[133]	CALL     	3 3 2
	19	[133]	SETTABLE 	0 -5 3	; "margin_v" -
	20	[134]	GETUPVAL 	3 0	; Screen
	21	[134]	SELF     	3 3 -2	; "scaleBySize"
	22	[134]	LOADK    	5 -6	; 1
	23	[134]	CALL     	3 3 2
	24	[134]	SETTABLE 	0 -7 3	; "bordersize" -
	25	[135]	GETUPVAL 	3 0	; Screen
	26	[135]	SELF     	3 3 -2	; "scaleBySize"
	27	[135]	LOADK    	5 -9	; 2
	28	[135]	CALL     	3 3 2
	29	[135]	SETTABLE 	0 -8 3	; "radius" -
	30	[136]	GETUPVAL 	3 1	; Blitbuffer
	31	[136]	GETTABLE 	3 3 -11	; "COLOR_WHITE"
	32	[136]	SETTABLE 	0 -10 3	; "bgcolor" -
	33	[136]	JMP      	15	; to 49
	34	[138]	TEST     	2 0 0
	35	[138]	JMP      	5	; to 41
	36	[139]	GETUPVAL 	3 0	; Screen
	37	[139]	SELF     	3 3 -2	; "scaleBySize"
	38	[139]	MOVE     	5 2
	39	[139]	CALL     	3 3 2
	40	[139]	SETTABLE 	0 -1 3	; "height" -
	41	[141]	SETTABLE 	0 -3 -12	; "margin_h" 0
	42	[142]	SETTABLE 	0 -5 -12	; "margin_v" 0
	43	[143]	SETTABLE 	0 -7 -12	; "bordersize" 0
	44	[144]	SETTABLE 	0 -8 -12	; "radius" 0
	45	[145]	GETUPVAL 	3 1	; Blitbuffer
	46	[145]	GETTABLE 	3 3 -13	; "COLOR_GRAY"
	47	[145]	SETTABLE 	0 -10 3	; "bgcolor" -
	48	[146]	SETTABLE 	0 -14 -15	; "ticks" nil
	49	[148]	RETURN   	0 1
