
main <./spec/unit/quickstart_spec.lua:0,0> (5 instructions, 20 bytes at 0x7fccff4068c0)
0+ params, 3 slots, 0 upvalues, 0 locals, 2 constants, 1 function
	1	[1]	GETGLOBAL	0 -1	; describe
	2	[1]	LOADK    	1 -2	; "QuickStart module"
	3	[36]	CLOSURE  	2 0	; 0x7fccff406b60
	4	[1]	CALL     	0 3 1
	5	[36]	RETURN   	0 1

function <./spec/unit/quickstart_spec.lua:1,36> (20 instructions, 80 bytes at 0x7fccff406b60)
0 params, 3 slots, 0 upvalues, 0 locals, 6 constants, 5 functions
	1	[2]	GETGLOBAL	0 -1	; setup
	2	[4]	CLOSURE  	1 0	; 0x7fccff406ca0
	3	[2]	CALL     	0 2 1
	4	[5]	GETGLOBAL	0 -2	; it
	5	[5]	LOADK    	1 -3	; "should return false shown_version lower than force_show_version"
	6	[11]	CLOSURE  	2 1	; 0x7fccff407080
	7	[5]	CALL     	0 3 1
	8	[12]	GETGLOBAL	0 -2	; it
	9	[12]	LOADK    	1 -4	; "should return true when shown_version equal to force_show_version"
	10	[18]	CLOSURE  	2 2	; 0x7fccff407970
	11	[12]	CALL     	0 3 1
	12	[19]	GETGLOBAL	0 -2	; it
	13	[19]	LOADK    	1 -5	; "should return true when shown_version higher than force_show_version"
	14	[25]	CLOSURE  	2 3	; 0x7fccff408030
	15	[19]	CALL     	0 3 1
	16	[26]	GETGLOBAL	0 -2	; it
	17	[26]	LOADK    	1 -6	; "should return a proper quickstart filename"
	18	[35]	CLOSURE  	2 4	; 0x7fccff408690
	19	[26]	CALL     	0 3 1
	20	[36]	RETURN   	0 1

function <./spec/unit/quickstart_spec.lua:2,4> (4 instructions, 16 bytes at 0x7fccff406ca0)
0 params, 2 slots, 0 upvalues, 0 locals, 2 constants, 0 functions
	1	[3]	GETGLOBAL	0 -1	; require
	2	[3]	LOADK    	1 -2	; "commonrequire"
	3	[3]	CALL     	0 2 1
	4	[4]	RETURN   	0 1

function <./spec/unit/quickstart_spec.lua:5,11> (18 instructions, 72 bytes at 0x7fccff407080)
0 params, 4 slots, 0 upvalues, 1 local, 12 constants, 0 functions
	1	[6]	GETGLOBAL	0 -1	; G_reader_settings
	2	[6]	SELF     	0 0 -2	; "saveSetting"
	3	[6]	LOADK    	2 -3	; "quickstart_shown_version"
	4	[6]	LOADK    	3 -4	; 1
	5	[6]	CALL     	0 4 1
	6	[7]	GETGLOBAL	0 -1	; G_reader_settings
	7	[7]	SELF     	0 0 -5	; "flush"
	8	[7]	CALL     	0 2 1
	9	[8]	GETGLOBAL	0 -6	; require
	10	[8]	LOADK    	1 -7	; "ui/quickstart"
	11	[8]	CALL     	0 2 2
	12	[9]	SETTABLE 	0 -8 -9	; "quickstart_force_show_version" 2
	13	[10]	GETGLOBAL	1 -10	; assert
	14	[10]	GETTABLE 	1 1 -11	; "is_false"
	15	[10]	SELF     	2 0 -12	; "isShown"
	16	[10]	CALL     	2 2 0
	17	[10]	CALL     	1 0 1
	18	[11]	RETURN   	0 1

function <./spec/unit/quickstart_spec.lua:12,18> (18 instructions, 72 bytes at 0x7fccff407970)
0 params, 4 slots, 0 upvalues, 1 local, 11 constants, 0 functions
	1	[13]	GETGLOBAL	0 -1	; G_reader_settings
	2	[13]	SELF     	0 0 -2	; "saveSetting"
	3	[13]	LOADK    	2 -3	; "quickstart_shown_version"
	4	[13]	LOADK    	3 -4	; 1
	5	[13]	CALL     	0 4 1
	6	[14]	GETGLOBAL	0 -1	; G_reader_settings
	7	[14]	SELF     	0 0 -5	; "flush"
	8	[14]	CALL     	0 2 1
	9	[15]	GETGLOBAL	0 -6	; require
	10	[15]	LOADK    	1 -7	; "ui/quickstart"
	11	[15]	CALL     	0 2 2
	12	[16]	SETTABLE 	0 -8 -4	; "quickstart_force_show_version" 1
	13	[17]	GETGLOBAL	1 -9	; assert
	14	[17]	GETTABLE 	1 1 -10	; "is_true"
	15	[17]	SELF     	2 0 -11	; "isShown"
	16	[17]	CALL     	2 2 0
	17	[17]	CALL     	1 0 1
	18	[18]	RETURN   	0 1

function <./spec/unit/quickstart_spec.lua:19,25> (18 instructions, 72 bytes at 0x7fccff408030)
0 params, 4 slots, 0 upvalues, 1 local, 12 constants, 0 functions
	1	[20]	GETGLOBAL	0 -1	; G_reader_settings
	2	[20]	SELF     	0 0 -2	; "saveSetting"
	3	[20]	LOADK    	2 -3	; "quickstart_shown_version"
	4	[20]	LOADK    	3 -4	; 2
	5	[20]	CALL     	0 4 1
	6	[21]	GETGLOBAL	0 -1	; G_reader_settings
	7	[21]	SELF     	0 0 -5	; "flush"
	8	[21]	CALL     	0 2 1
	9	[22]	GETGLOBAL	0 -6	; require
	10	[22]	LOADK    	1 -7	; "ui/quickstart"
	11	[22]	CALL     	0 2 2
	12	[23]	SETTABLE 	0 -8 -9	; "quickstart_force_show_version" 1
	13	[24]	GETGLOBAL	1 -10	; assert
	14	[24]	GETTABLE 	1 1 -11	; "is_true"
	15	[24]	SELF     	2 0 -12	; "isShown"
	16	[24]	CALL     	2 2 0
	17	[24]	CALL     	1 0 1
	18	[25]	RETURN   	0 1

function <./spec/unit/quickstart_spec.lua:26,35> (33 instructions, 132 bytes at 0x7fccff408690)
0 params, 11 slots, 0 upvalues, 7 locals, 16 constants, 0 functions
	1	[27]	GETGLOBAL	0 -1	; require
	2	[27]	LOADK    	1 -2	; "datastorage"
	3	[27]	CALL     	0 2 2
	4	[28]	GETGLOBAL	1 -1	; require
	5	[28]	LOADK    	2 -3	; "ui/quickstart"
	6	[28]	CALL     	1 2 2
	7	[29]	GETGLOBAL	2 -1	; require
	8	[29]	LOADK    	3 -4	; "version"
	9	[29]	CALL     	2 2 2
	10	[30]	LOADK    	3 -5	; "en"
	11	[31]	SELF     	4 2 -6	; "getCurrentRevision"
	12	[31]	CALL     	4 2 2
	13	[32]	GETGLOBAL	5 -7	; string
	14	[32]	GETTABLE 	5 5 -8	; "format"
	15	[32]	LOADK    	6 -9	; "%s%s"
	16	[32]	SELF     	7 0 -10	; "getDataDir"
	17	[32]	CALL     	7 2 2
	18	[32]	LOADK    	8 -11	; "/help"
	19	[32]	CALL     	5 4 2
	20	[33]	LOADK    	6 -12	; "%s/quickstart-%s-%s.html"
	21	[33]	SELF     	6 6 -8	; "format"
	22	[33]	MOVE     	8 5
	23	[33]	MOVE     	9 3
	24	[33]	MOVE     	10 4
	25	[33]	CALL     	6 5 2
	26	[34]	GETGLOBAL	7 -13	; assert
	27	[34]	GETTABLE 	7 7 -14	; "is"
	28	[34]	GETTABLE 	7 7 -15	; "same"
	29	[34]	MOVE     	8 6
	30	[34]	SELF     	9 1 -16	; "getQuickStart"
	31	[34]	CALL     	9 2 0
	32	[34]	CALL     	7 0 1
	33	[35]	RETURN   	0 1
