-- BYTECODE -- quickstart_spec.lua:2-4
0001    GGET     0   0      ; "require"
0002    KSTR     1   1      ; "commonrequire"
0003    CALL     0   1   2
0004    RET0     0   1

-- BYTECODE -- quickstart_spec.lua:5-11
0001    GGET     0   0      ; "G_reader_settings"
0002    MOV      1   0
0003    TGETS    0   0   1  ; "saveSetting"
0004    KSTR     2   2      ; "quickstart_shown_version"
0005    KSHORT   3   1
0006    CALL     0   1   4
0007    GGET     0   0      ; "G_reader_settings"
0008    MOV      1   0
0009    TGETS    0   0   3  ; "flush"
0010    CALL     0   1   2
0011    GGET     0   4      ; "require"
0012    KSTR     1   5      ; "ui/quickstart"
0013    CALL     0   2   2
0014    KSHORT   1   2
0015    TSETS    1   0   6  ; "quickstart_force_show_version"
0016    GGET     1   7      ; "assert"
0017    TGETS    1   1   8  ; "is_false"
0018    MOV      3   0
0019    TGETS    2   0   9  ; "isShown"
0020    CALL     2   0   2
0021    CALLM    1   1   0
0022    RET0     0   1

-- BYTECODE -- quickstart_spec.lua:12-18
0001    GGET     0   0      ; "G_reader_settings"
0002    MOV      1   0
0003    TGETS    0   0   1  ; "saveSetting"
0004    KSTR     2   2      ; "quickstart_shown_version"
0005    KSHORT   3   1
0006    CALL     0   1   4
0007    GGET     0   0      ; "G_reader_settings"
0008    MOV      1   0
0009    TGETS    0   0   3  ; "flush"
0010    CALL     0   1   2
0011    GGET     0   4      ; "require"
0012    KSTR     1   5      ; "ui/quickstart"
0013    CALL     0   2   2
0014    KSHORT   1   1
0015    TSETS    1   0   6  ; "quickstart_force_show_version"
0016    GGET     1   7      ; "assert"
0017    TGETS    1   1   8  ; "is_true"
0018    MOV      3   0
0019    TGETS    2   0   9  ; "isShown"
0020    CALL     2   0   2
0021    CALLM    1   1   0
0022    RET0     0   1

-- BYTECODE -- quickstart_spec.lua:19-25
0001    GGET     0   0      ; "G_reader_settings"
0002    MOV      1   0
0003    TGETS    0   0   1  ; "saveSetting"
0004    KSTR     2   2      ; "quickstart_shown_version"
0005    KSHORT   3   2
0006    CALL     0   1   4
0007    GGET     0   0      ; "G_reader_settings"
0008    MOV      1   0
0009    TGETS    0   0   3  ; "flush"
0010    CALL     0   1   2
0011    GGET     0   4      ; "require"
0012    KSTR     1   5      ; "ui/quickstart"
0013    CALL     0   2   2
0014    KSHORT   1   1
0015    TSETS    1   0   6  ; "quickstart_force_show_version"
0016    GGET     1   7      ; "assert"
0017    TGETS    1   1   8  ; "is_true"
0018    MOV      3   0
0019    TGETS    2   0   9  ; "isShown"
0020    CALL     2   0   2
0021    CALLM    1   1   0
0022    RET0     0   1

-- BYTECODE -- quickstart_spec.lua:26-35
0001    GGET     0   0      ; "require"
0002    KSTR     1   1      ; "datastorage"
0003    CALL     0   2   2
0004    GGET     1   0      ; "require"
0005    KSTR     2   2      ; "ui/quickstart"
0006    CALL     1   2   2
0007    GGET     2   0      ; "require"
0008    KSTR     3   3      ; "version"
0009    CALL     2   2   2
0010    KSTR     3   4      ; "en"
0011    MOV      5   2
0012    TGETS    4   2   5  ; "getCurrentRevision"
0013    CALL     4   2   2
0014    GGET     5   6      ; "string"
0015    TGETS    5   5   7  ; "format"
0016    KSTR     6   8      ; "%s%s"
0017    MOV      8   0
0018    TGETS    7   0   9  ; "getDataDir"
0019    CALL     7   2   2
0020    KSTR     8  10      ; "/help"
0021    CALL     5   2   4
0022    KSTR     6  11      ; "%s/quickstart-%s-%s.html"
0023    MOV      7   6
0024    TGETS    6   6   7  ; "format"
0025    MOV      8   5
0026    MOV      9   3
0027    MOV     10   4
0028    CALL     6   2   5
0029    GGET     7  12      ; "assert"
0030    TGETS    7   7  13  ; "is"
0031    TGETS    7   7  14  ; "same"
0032    MOV      8   6
0033    MOV     10   1
0034    TGETS    9   1  15  ; "getQuickStart"
0035    CALL     9   0   2
0036    CALLM    7   1   1
0037    RET0     0   1

-- BYTECODE -- quickstart_spec.lua:1-36
0001    GGET     0   0      ; "setup"
0002    FNEW     1   1      ; quickstart_spec.lua:2
0003    CALL     0   1   2
0004    GGET     0   2      ; "it"
0005    KSTR     1   3      ; "should return false shown_version lower "~
0006    FNEW     2   4      ; quickstart_spec.lua:5
0007    CALL     0   1   3
0008    GGET     0   2      ; "it"
0009    KSTR     1   5      ; "should return true when shown_version eq"~
0010    FNEW     2   6      ; quickstart_spec.lua:12
0011    CALL     0   1   3
0012    GGET     0   2      ; "it"
0013    KSTR     1   7      ; "should return true when shown_version hi"~
0014    FNEW     2   8      ; quickstart_spec.lua:19
0015    CALL     0   1   3
0016    GGET     0   2      ; "it"
0017    KSTR     1   9      ; "should return a proper quickstart filena"~
0018    FNEW     2  10      ; quickstart_spec.lua:26
0019    CALL     0   1   3
0020    RET0     0   1

-- BYTECODE -- quickstart_spec.lua:0-37
0001    GGET     0   0      ; "describe"
0002    KSTR     1   1      ; "QuickStart module"
0003    FNEW     2   2      ; quickstart_spec.lua:1
0004    CALL     0   1   3
0005    RET0     0   1

