
main <./frontend/ui/widget/radiobutton.lua:0,0> (71 instructions, 284 bytes at 0x7fa9494068d0)
0+ params, 16 slots, 0 upvalues, 11 locals, 33 constants, 8 functions
	1	[17]	GETGLOBAL	0 -1	; require
	2	[17]	LOADK    	1 -2	; "ffi/blitbuffer"
	3	[17]	CALL     	0 2 2
	4	[18]	GETGLOBAL	1 -1	; require
	5	[18]	LOADK    	2 -3	; "device"
	6	[18]	CALL     	1 2 2
	7	[19]	GETGLOBAL	2 -1	; require
	8	[19]	LOADK    	3 -4	; "ui/font"
	9	[19]	CALL     	2 2 2
	10	[20]	GETGLOBAL	3 -1	; require
	11	[20]	LOADK    	4 -5	; "ui/widget/container/framecontainer"
	12	[20]	CALL     	3 2 2
	13	[21]	GETGLOBAL	4 -1	; require
	14	[21]	LOADK    	5 -6	; "ui/geometry"
	15	[21]	CALL     	4 2 2
	16	[22]	GETGLOBAL	5 -1	; require
	17	[22]	LOADK    	6 -7	; "ui/gesturerange"
	18	[22]	CALL     	5 2 2
	19	[23]	GETGLOBAL	6 -1	; require
	20	[23]	LOADK    	7 -8	; "ui/widget/container/inputcontainer"
	21	[23]	CALL     	6 2 2
	22	[24]	GETGLOBAL	7 -1	; require
	23	[24]	LOADK    	8 -9	; "ui/widget/container/leftcontainer"
	24	[24]	CALL     	7 2 2
	25	[25]	GETGLOBAL	8 -1	; require
	26	[25]	LOADK    	9 -10	; "ui/widget/textwidget"
	27	[25]	CALL     	8 2 2
	28	[26]	GETGLOBAL	9 -1	; require
	29	[26]	LOADK    	10 -11	; "ui/uimanager"
	30	[26]	CALL     	9 2 2
	31	[28]	SELF     	10 6 -12	; "new"
	32	[28]	NEWTABLE 	12 0 7
	33	[29]	SETTABLE 	12 -13 -14	; "checkable" true
	34	[30]	SETTABLE 	12 -15 -16	; "checked" false
	35	[31]	SETTABLE 	12 -17 -14	; "enabled" true
	36	[32]	SELF     	13 2 -19	; "getFace"
	37	[32]	LOADK    	15 -20	; "smallinfofont"
	38	[32]	CALL     	13 3 2
	39	[32]	SETTABLE 	12 -18 13	; "face" -
	40	[33]	GETTABLE 	13 0 -22	; "COLOR_WHITE"
	41	[33]	SETTABLE 	12 -21 13	; "background" -
	42	[34]	SETTABLE 	12 -23 -24	; "width" 0
	43	[35]	SETTABLE 	12 -25 -24	; "height" 0
	44	[28]	CALL     	10 3 2
	45	[81]	CLOSURE  	11 0	; 0x7fa9494070d0
	46	[81]	MOVE     	0 8
	47	[81]	MOVE     	0 1
	48	[81]	MOVE     	0 5
	49	[38]	SETTABLE 	10 -26 11	; "init" -
	50	[99]	CLOSURE  	11 1	; 0x7fa949407560
	51	[99]	MOVE     	0 3
	52	[99]	MOVE     	0 7
	53	[99]	MOVE     	0 4
	54	[83]	SETTABLE 	10 -27 11	; "update" -
	55	[104]	CLOSURE  	11 2	; 0x7fa9494080e0
	56	[101]	SETTABLE 	10 -28 11	; "onFocus" -
	57	[109]	CLOSURE  	11 3	; 0x7fa949408180
	58	[106]	SETTABLE 	10 -29 11	; "onUnfocus" -
	59	[137]	CLOSURE  	11 4	; 0x7fa949408720
	60	[137]	MOVE     	0 9
	61	[111]	SETTABLE 	10 -30 11	; "onTapCheckButton" -
	62	[148]	CLOSURE  	11 5	; 0x7fa949408880
	63	[139]	SETTABLE 	10 -31 11	; "onHoldCheckButton" -
	64	[157]	CLOSURE  	11 6	; 0x7fa949409b10
	65	[157]	MOVE     	0 9
	66	[150]	SETTABLE 	10 -32 11	; "check" -
	67	[166]	CLOSURE  	11 7	; 0x7fa94940a260
	68	[166]	MOVE     	0 9
	69	[159]	SETTABLE 	10 -33 11	; "unCheck" -
	70	[168]	RETURN   	10 2
	71	[168]	RETURN   	0 1

function <./frontend/ui/widget/radiobutton.lua:38,81> (99 instructions, 396 bytes at 0x7fa9494070d0)
1 param, 7 slots, 3 upvalues, 1 local, 32 constants, 0 functions
	1	[39]	GETUPVAL 	1 0	; TextWidget
	2	[39]	SELF     	1 1 -2	; "new"
	3	[39]	NEWTABLE 	3 0 3
	4	[40]	LOADK    	4 -4	; "\226\151\137 "
	5	[40]	GETTABLE 	5 0 -3	; "text"
	6	[40]	CONCAT   	4 4 5
	7	[40]	SETTABLE 	3 -3 4	; "text" -
	8	[41]	GETTABLE 	4 0 -5	; "face"
	9	[41]	SETTABLE 	3 -5 4	; "face" -
	10	[42]	GETTABLE 	4 0 -6	; "max_width"
	11	[42]	SETTABLE 	3 -6 4	; "max_width" -
	12	[39]	CALL     	1 3 2
	13	[43]	SETTABLE 	0 -1 1	; "_checked_widget" -
	14	[44]	GETUPVAL 	1 0	; TextWidget
	15	[44]	SELF     	1 1 -2	; "new"
	16	[44]	NEWTABLE 	3 0 3
	17	[45]	LOADK    	4 -8	; "\226\151\175 "
	18	[45]	GETTABLE 	5 0 -3	; "text"
	19	[45]	CONCAT   	4 4 5
	20	[45]	SETTABLE 	3 -3 4	; "text" -
	21	[46]	GETTABLE 	4 0 -5	; "face"
	22	[46]	SETTABLE 	3 -5 4	; "face" -
	23	[47]	GETTABLE 	4 0 -6	; "max_width"
	24	[47]	SETTABLE 	3 -6 4	; "max_width" -
	25	[44]	CALL     	1 3 2
	26	[48]	SETTABLE 	0 -7 1	; "_unchecked_widget" -
	27	[49]	GETUPVAL 	1 0	; TextWidget
	28	[49]	SELF     	1 1 -2	; "new"
	29	[49]	NEWTABLE 	3 0 3
	30	[50]	LOADK    	4 -10	; ""
	31	[50]	GETTABLE 	5 0 -3	; "text"
	32	[50]	CONCAT   	4 4 5
	33	[50]	SETTABLE 	3 -3 4	; "text" -
	34	[51]	GETTABLE 	4 0 -5	; "face"
	35	[51]	SETTABLE 	3 -5 4	; "face" -
	36	[52]	GETTABLE 	4 0 -6	; "max_width"
	37	[52]	SETTABLE 	3 -6 4	; "max_width" -
	38	[49]	CALL     	1 3 2
	39	[53]	SETTABLE 	0 -9 1	; "_empty_widget" -
	40	[54]	GETTABLE 	1 0 -7	; "_unchecked_widget"
	41	[54]	SELF     	1 1 -12	; "getSize"
	42	[54]	CALL     	1 2 2
	43	[54]	SETTABLE 	0 -11 1	; "_widget_size" -
	44	[55]	GETTABLE 	1 0 -13	; "width"
	45	[55]	EQ       	0 1 -14	; - nil
	46	[55]	JMP      	3	; to 50
	47	[56]	GETTABLE 	1 0 -11	; "_widget_size"
	48	[56]	GETTABLE 	1 1 -15	; "w"
	49	[56]	SETTABLE 	0 -13 1	; "width" -
	50	[59]	GETTABLE 	1 0 -17	; "checkable"
	51	[59]	TEST     	1 0 0
	52	[59]	JMP      	9	; to 62
	53	[59]	GETTABLE 	1 0 -18	; "checked"
	54	[59]	TEST     	1 0 0
	55	[59]	JMP      	3	; to 59
	56	[59]	GETTABLE 	1 0 -1	; "_checked_widget"
	57	[59]	TEST     	1 0 1
	58	[59]	JMP      	4	; to 63
	59	[59]	GETTABLE 	1 0 -7	; "_unchecked_widget"
	60	[60]	TEST     	1 0 1
	61	[60]	JMP      	1	; to 63
	62	[60]	GETTABLE 	1 0 -9	; "_empty_widget"
	63	[60]	SETTABLE 	0 -16 1	; "_radio_button" -
	64	[61]	SELF     	1 0 -19	; "update"
	65	[61]	CALL     	1 2 1
	66	[62]	GETTABLE 	1 0 -21	; "frame"
	67	[62]	SELF     	1 1 -12	; "getSize"
	68	[62]	CALL     	1 2 2
	69	[62]	SETTABLE 	0 -20 1	; "dimen" -
	70	[63]	GETUPVAL 	1 1	; Device
	71	[63]	SELF     	1 1 -22	; "isTouchDevice"
	72	[63]	CALL     	1 2 2
	73	[63]	TEST     	1 0 0
	74	[63]	JMP      	24	; to 99
	75	[64]	NEWTABLE 	1 0 2
	76	[65]	NEWTABLE 	2 1 1
	77	[66]	GETUPVAL 	3 2	; GestureRange
	78	[66]	SELF     	3 3 -2	; "new"
	79	[66]	NEWTABLE 	5 0 2
	80	[67]	SETTABLE 	5 -25 -26	; "ges" "tap"
	81	[68]	GETTABLE 	6 0 -20	; "dimen"
	82	[68]	SETTABLE 	5 -27 6	; "range" -
	83	[66]	CALL     	3 3 2
	84	[70]	SETTABLE 	2 -28 -29	; "doc" "Tap Button"
	85	[71]	SETLIST  	2 1 1	; 1
	86	[71]	SETTABLE 	1 -24 2	; "TapCheckButton" -
	87	[72]	NEWTABLE 	2 1 1
	88	[73]	GETUPVAL 	3 2	; GestureRange
	89	[73]	SELF     	3 3 -2	; "new"
	90	[73]	NEWTABLE 	5 0 2
	91	[74]	SETTABLE 	5 -25 -31	; "ges" "hold"
	92	[75]	GETTABLE 	6 0 -20	; "dimen"
	93	[75]	SETTABLE 	5 -27 6	; "range" -
	94	[73]	CALL     	3 3 2
	95	[77]	SETTABLE 	2 -28 -32	; "doc" "Hold Button"
	96	[78]	SETLIST  	2 1 1	; 1
	97	[78]	SETTABLE 	1 -30 2	; "HoldCheckButton" -
	98	[79]	SETTABLE 	0 -23 1	; "ges_events" -
	99	[81]	RETURN   	0 1

function <./frontend/ui/widget/radiobutton.lua:83,99> (35 instructions, 140 bytes at 0x7fa949407560)
1 param, 11 slots, 3 upvalues, 1 local, 14 constants, 0 functions
	1	[84]	GETUPVAL 	1 0	; FrameContainer
	2	[84]	SELF     	1 1 -2	; "new"
	3	[84]	NEWTABLE 	3 0 5
	4	[85]	GETTABLE 	4 0 -3	; "margin"
	5	[85]	SETTABLE 	3 -3 4	; "margin" -
	6	[86]	GETTABLE 	4 0 -4	; "bordersize"
	7	[86]	SETTABLE 	3 -4 4	; "bordersize" -
	8	[87]	GETTABLE 	4 0 -5	; "background"
	9	[87]	SETTABLE 	3 -5 4	; "background" -
	10	[88]	GETTABLE 	4 0 -6	; "radius"
	11	[88]	SETTABLE 	3 -6 4	; "radius" -
	12	[89]	GETTABLE 	4 0 -7	; "padding"
	13	[89]	SETTABLE 	3 -7 4	; "padding" -
	14	[90]	GETUPVAL 	4 1	; LeftContainer
	15	[90]	SELF     	4 4 -2	; "new"
	16	[90]	NEWTABLE 	6 1 1
	17	[91]	GETUPVAL 	7 2	; Geom
	18	[91]	SELF     	7 7 -2	; "new"
	19	[91]	NEWTABLE 	9 0 2
	20	[92]	GETTABLE 	10 0 -10	; "width"
	21	[92]	SETTABLE 	9 -9 10	; "w" -
	22	[93]	GETTABLE 	10 0 -12	; "_widget_size"
	23	[93]	GETTABLE 	10 10 -11	; "h"
	24	[93]	SETTABLE 	9 -11 10	; "h" -
	25	[91]	CALL     	7 3 2
	26	[94]	SETTABLE 	6 -8 7	; "dimen" -
	27	[96]	GETTABLE 	7 0 -13	; "_radio_button"
	28	[96]	SETLIST  	6 1 1	; 1
	29	[90]	CALL     	4 3 0
	30	[97]	SETLIST  	3 0 1	; 1
	31	[84]	CALL     	1 3 2
	32	[97]	SETTABLE 	0 -1 1	; "frame" -
	33	[98]	GETTABLE 	1 0 -1	; "frame"
	34	[98]	SETTABLE 	0 -14 1	; 1 -
	35	[99]	RETURN   	0 1

function <./frontend/ui/widget/radiobutton.lua:101,104> (5 instructions, 20 bytes at 0x7fa9494080e0)
1 param, 2 slots, 0 upvalues, 1 local, 3 constants, 0 functions
	1	[102]	GETTABLE 	1 0 -1	; "frame"
	2	[102]	SETTABLE 	1 -2 -3	; "invert" true
	3	[103]	LOADBOOL 	1 1 0
	4	[103]	RETURN   	1 2
	5	[104]	RETURN   	0 1

function <./frontend/ui/widget/radiobutton.lua:106,109> (5 instructions, 20 bytes at 0x7fa949408180)
1 param, 2 slots, 0 upvalues, 1 local, 3 constants, 0 functions
	1	[107]	GETTABLE 	1 0 -1	; "frame"
	2	[107]	SETTABLE 	1 -2 -3	; "invert" false
	3	[108]	LOADBOOL 	1 1 0
	4	[108]	RETURN   	1 2
	5	[109]	RETURN   	0 1

function <./frontend/ui/widget/radiobutton.lua:111,137> (57 instructions, 228 bytes at 0x7fa949408720)
1 param, 6 slots, 1 upvalue, 1 local, 19 constants, 2 functions
	1	[112]	GETTABLE 	1 0 -1	; "enabled"
	2	[112]	TEST     	1 0 0
	3	[112]	JMP      	35	; to 39
	4	[112]	GETTABLE 	1 0 -2	; "callback"
	5	[112]	TEST     	1 0 0
	6	[112]	JMP      	32	; to 39
	7	[113]	GETGLOBAL	1 -3	; G_reader_settings
	8	[113]	SELF     	1 1 -4	; "isFalse"
	9	[113]	LOADK    	3 -5	; "flash_ui"
	10	[113]	CALL     	1 3 2
	11	[113]	TEST     	1 0 0
	12	[113]	JMP      	3	; to 16
	13	[114]	GETTABLE 	1 0 -2	; "callback"
	14	[114]	CALL     	1 1 1
	15	[114]	JMP      	39	; to 55
	16	[117]	GETTABLE 	1 0 -6	; "frame"
	17	[117]	SETTABLE 	1 -7 -8	; "invert" true
	18	[118]	GETUPVAL 	1 0	; UIManager
	19	[118]	SELF     	1 1 -9	; "widgetRepaint"
	20	[118]	GETTABLE 	3 0 -6	; "frame"
	21	[118]	GETTABLE 	4 0 -10	; "dimen"
	22	[118]	GETTABLE 	4 4 -11	; "x"
	23	[118]	GETTABLE 	5 0 -10	; "dimen"
	24	[118]	GETTABLE 	5 5 -12	; "y"
	25	[118]	CALL     	1 5 1
	26	[119]	GETUPVAL 	1 0	; UIManager
	27	[119]	SELF     	1 1 -13	; "setDirty"
	28	[119]	LOADNIL  	3 3
	29	[121]	CLOSURE  	4 0	; 0x7fa9494085d0
	30	[121]	MOVE     	0 0
	31	[119]	CALL     	1 4 1
	32	[122]	GETUPVAL 	1 0	; UIManager
	33	[122]	SELF     	1 1 -14	; "tickAfterNext"
	34	[129]	CLOSURE  	3 1	; 0x7fa949408cc0
	35	[129]	MOVE     	0 0
	36	[129]	GETUPVAL 	0 0	; UIManager
	37	[122]	CALL     	1 3 1
	38	[130]	JMP      	16	; to 55
	39	[131]	GETTABLE 	1 0 -15	; "tap_input"
	40	[131]	TEST     	1 0 0
	41	[131]	JMP      	4	; to 46
	42	[132]	SELF     	1 0 -16	; "onInput"
	43	[132]	GETTABLE 	3 0 -15	; "tap_input"
	44	[132]	CALL     	1 3 1
	45	[132]	JMP      	9	; to 55
	46	[133]	GETGLOBAL	1 -17	; type
	47	[133]	GETTABLE 	2 0 -18	; "tap_input_func"
	48	[133]	CALL     	1 2 2
	49	[133]	EQ       	0 1 -19	; - "function"
	50	[133]	JMP      	4	; to 55
	51	[134]	SELF     	1 0 -16	; "onInput"
	52	[134]	GETTABLE 	3 0 -18	; "tap_input_func"
	53	[134]	CALL     	3 1 0
	54	[134]	CALL     	1 0 1
	55	[136]	LOADBOOL 	1 1 0
	56	[136]	RETURN   	1 2
	57	[137]	RETURN   	0 1

function <./frontend/ui/widget/radiobutton.lua:119,121> (5 instructions, 20 bytes at 0x7fa9494085d0)
0 params, 2 slots, 1 upvalue, 0 locals, 2 constants, 0 functions
	1	[120]	LOADK    	0 -1	; "fast"
	2	[120]	GETUPVAL 	1 0	; self
	3	[120]	GETTABLE 	1 1 -2	; "dimen"
	4	[120]	RETURN   	0 3
	5	[121]	RETURN   	0 1

function <./frontend/ui/widget/radiobutton.lua:122,129> (24 instructions, 96 bytes at 0x7fa949408cc0)
0 params, 5 slots, 2 upvalues, 0 locals, 9 constants, 1 function
	1	[123]	GETUPVAL 	0 0	; self
	2	[123]	GETTABLE 	0 0 -1	; "callback"
	3	[123]	CALL     	0 1 1
	4	[124]	GETUPVAL 	0 0	; self
	5	[124]	GETTABLE 	0 0 -2	; "frame"
	6	[124]	SETTABLE 	0 -3 -4	; "invert" false
	7	[125]	GETUPVAL 	0 1	; UIManager
	8	[125]	SELF     	0 0 -5	; "widgetRepaint"
	9	[125]	GETUPVAL 	2 0	; self
	10	[125]	GETTABLE 	2 2 -2	; "frame"
	11	[125]	GETUPVAL 	3 0	; self
	12	[125]	GETTABLE 	3 3 -6	; "dimen"
	13	[125]	GETTABLE 	3 3 -7	; "x"
	14	[125]	GETUPVAL 	4 0	; self
	15	[125]	GETTABLE 	4 4 -6	; "dimen"
	16	[125]	GETTABLE 	4 4 -8	; "y"
	17	[125]	CALL     	0 5 1
	18	[126]	GETUPVAL 	0 1	; UIManager
	19	[126]	SELF     	0 0 -9	; "setDirty"
	20	[126]	LOADNIL  	2 2
	21	[128]	CLOSURE  	3 0	; 0x7fa9494093e0
	22	[128]	GETUPVAL 	0 0	; self
	23	[126]	CALL     	0 4 1
	24	[129]	RETURN   	0 1

function <./frontend/ui/widget/radiobutton.lua:126,128> (5 instructions, 20 bytes at 0x7fa9494093e0)
0 params, 2 slots, 1 upvalue, 0 locals, 2 constants, 0 functions
	1	[127]	LOADK    	0 -1	; "fast"
	2	[127]	GETUPVAL 	1 0	; self
	3	[127]	GETTABLE 	1 1 -2	; "dimen"
	4	[127]	RETURN   	0 3
	5	[128]	RETURN   	0 1

function <./frontend/ui/widget/radiobutton.lua:139,148> (28 instructions, 112 bytes at 0x7fa949408880)
1 param, 4 slots, 0 upvalues, 1 local, 7 constants, 0 functions
	1	[140]	GETTABLE 	1 0 -1	; "enabled"
	2	[140]	TEST     	1 0 0
	3	[140]	JMP      	6	; to 10
	4	[140]	GETTABLE 	1 0 -2	; "hold_callback"
	5	[140]	TEST     	1 0 0
	6	[140]	JMP      	3	; to 10
	7	[141]	GETTABLE 	1 0 -2	; "hold_callback"
	8	[141]	CALL     	1 1 1
	9	[141]	JMP      	16	; to 26
	10	[142]	GETTABLE 	1 0 -3	; "hold_input"
	11	[142]	TEST     	1 0 0
	12	[142]	JMP      	4	; to 17
	13	[143]	SELF     	1 0 -4	; "onInput"
	14	[143]	GETTABLE 	3 0 -3	; "hold_input"
	15	[143]	CALL     	1 3 1
	16	[143]	JMP      	9	; to 26
	17	[144]	GETGLOBAL	1 -5	; type
	18	[144]	GETTABLE 	2 0 -6	; "hold_input_func"
	19	[144]	CALL     	1 2 2
	20	[144]	EQ       	0 1 -7	; - "function"
	21	[144]	JMP      	4	; to 26
	22	[145]	SELF     	1 0 -4	; "onInput"
	23	[145]	GETTABLE 	3 0 -6	; "hold_input_func"
	24	[145]	CALL     	3 1 0
	25	[145]	CALL     	1 0 1
	26	[147]	LOADBOOL 	1 1 0
	27	[147]	RETURN   	1 2
	28	[148]	RETURN   	0 1

function <./frontend/ui/widget/radiobutton.lua:150,157> (12 instructions, 48 bytes at 0x7fa949409b10)
2 params, 6 slots, 1 upvalue, 2 locals, 7 constants, 1 function
	1	[151]	GETTABLE 	2 0 -2	; "_checked_widget"
	2	[151]	SETTABLE 	0 -1 2	; "_radio_button" -
	3	[152]	SETTABLE 	0 -3 -4	; "checked" true
	4	[153]	SELF     	2 0 -5	; "update"
	5	[153]	CALL     	2 2 1
	6	[154]	GETUPVAL 	2 0	; UIManager
	7	[154]	SELF     	2 2 -6	; "setDirty"
	8	[154]	GETTABLE 	4 0 -7	; "parent"
	9	[156]	CLOSURE  	5 0	; 0x7fa94940a130
	10	[156]	MOVE     	0 0
	11	[154]	CALL     	2 4 1
	12	[157]	RETURN   	0 1

function <./frontend/ui/widget/radiobutton.lua:154,156> (5 instructions, 20 bytes at 0x7fa94940a130)
0 params, 2 slots, 1 upvalue, 0 locals, 2 constants, 0 functions
	1	[155]	LOADK    	0 -1	; "fast"
	2	[155]	GETUPVAL 	1 0	; self
	3	[155]	GETTABLE 	1 1 -2	; "dimen"
	4	[155]	RETURN   	0 3
	5	[156]	RETURN   	0 1

function <./frontend/ui/widget/radiobutton.lua:159,166> (12 instructions, 48 bytes at 0x7fa94940a260)
1 param, 5 slots, 1 upvalue, 1 local, 7 constants, 1 function
	1	[160]	GETTABLE 	1 0 -2	; "_unchecked_widget"
	2	[160]	SETTABLE 	0 -1 1	; "_radio_button" -
	3	[161]	SETTABLE 	0 -3 -4	; "checked" false
	4	[162]	SELF     	1 0 -5	; "update"
	5	[162]	CALL     	1 2 1
	6	[163]	GETUPVAL 	1 0	; UIManager
	7	[163]	SELF     	1 1 -6	; "setDirty"
	8	[163]	GETTABLE 	3 0 -7	; "parent"
	9	[165]	CLOSURE  	4 0	; 0x7fa949406670
	10	[165]	MOVE     	0 0
	11	[163]	CALL     	1 4 1
	12	[166]	RETURN   	0 1

function <./frontend/ui/widget/radiobutton.lua:163,165> (5 instructions, 20 bytes at 0x7fa949406670)
0 params, 2 slots, 1 upvalue, 0 locals, 2 constants, 0 functions
	1	[164]	LOADK    	0 -1	; "fast"
	2	[164]	GETUPVAL 	1 0	; self
	3	[164]	GETTABLE 	1 1 -2	; "dimen"
	4	[164]	RETURN   	0 3
	5	[165]	RETURN   	0 1
