
main <./frontend/ui/widget/radiobuttontable.lua:0,0> (93 instructions, 372 bytes at 0x7fd0c24068f0)
0+ params, 20 slots, 0 upvalues, 14 locals, 42 constants, 4 functions
	1	[1]	GETGLOBAL	0 -1	; require
	2	[1]	LOADK    	1 -2	; "ffi/blitbuffer"
	3	[1]	CALL     	0 2 2
	4	[2]	GETGLOBAL	1 -1	; require
	5	[2]	LOADK    	2 -3	; "device"
	6	[2]	CALL     	1 2 2
	7	[3]	GETGLOBAL	2 -1	; require
	8	[3]	LOADK    	3 -4	; "ui/widget/focusmanager"
	9	[3]	CALL     	2 2 2
	10	[4]	GETGLOBAL	3 -1	; require
	11	[4]	LOADK    	4 -5	; "ui/font"
	12	[4]	CALL     	3 2 2
	13	[5]	GETGLOBAL	4 -1	; require
	14	[5]	LOADK    	5 -6	; "ui/geometry"
	15	[5]	CALL     	4 2 2
	16	[6]	GETGLOBAL	5 -1	; require
	17	[6]	LOADK    	6 -7	; "ui/widget/horizontalgroup"
	18	[6]	CALL     	5 2 2
	19	[7]	GETGLOBAL	6 -1	; require
	20	[7]	LOADK    	7 -8	; "ui/widget/linewidget"
	21	[7]	CALL     	6 2 2
	22	[8]	GETGLOBAL	7 -1	; require
	23	[8]	LOADK    	8 -9	; "ui/widget/radiobutton"
	24	[8]	CALL     	7 2 2
	25	[9]	GETGLOBAL	8 -1	; require
	26	[9]	LOADK    	9 -10	; "ui/size"
	27	[9]	CALL     	8 2 2
	28	[10]	GETGLOBAL	9 -1	; require
	29	[10]	LOADK    	10 -11	; "ui/widget/verticalgroup"
	30	[10]	CALL     	9 2 2
	31	[11]	GETGLOBAL	10 -1	; require
	32	[11]	LOADK    	11 -12	; "ui/widget/verticalspan"
	33	[11]	CALL     	10 2 2
	34	[12]	GETGLOBAL	11 -1	; require
	35	[12]	LOADK    	12 -13	; "dbg"
	36	[12]	CALL     	11 2 2
	37	[13]	GETTABLE 	12 1 -14	; "screen"
	38	[15]	SELF     	13 2 -15	; "new"
	39	[15]	NEWTABLE 	15 0 8
	40	[16]	SELF     	16 12 -17	; "getWidth"
	41	[16]	CALL     	16 2 2
	42	[16]	SETTABLE 	15 -16 16	; "width" -
	43	[17]	NEWTABLE 	16 1 0
	44	[17]	NEWTABLE 	17 2 0
	45	[18]	NEWTABLE 	18 0 3
	46	[19]	SETTABLE 	18 -19 -20	; "text" "Cancel"
	47	[19]	SETTABLE 	18 -21 -22	; "enabled" false
	48	[19]	SETTABLE 	18 -23 -24	; "callback" nil
	49	[19]	NEWTABLE 	19 0 3
	50	[20]	SETTABLE 	19 -19 -25	; "text" "OK"
	51	[20]	SETTABLE 	19 -21 -26	; "enabled" true
	52	[20]	SETTABLE 	19 -23 -24	; "callback" nil
	53	[21]	SETLIST  	17 2 1	; 1
	54	[22]	SETLIST  	16 1 1	; 1
	55	[22]	SETTABLE 	15 -18 16	; "radio_buttons" -
	56	[23]	GETTABLE 	16 8 -28	; "line"
	57	[23]	GETTABLE 	16 16 -29	; "medium"
	58	[23]	SETTABLE 	15 -27 16	; "sep_width" -
	59	[24]	GETTABLE 	16 8 -30	; "padding"
	60	[24]	GETTABLE 	16 16 -31	; "button"
	61	[24]	SETTABLE 	15 -30 16	; "padding" -
	62	[26]	SETTABLE 	15 -32 -22	; "zero_sep" false
	63	[27]	SELF     	16 3 -34	; "getFace"
	64	[27]	LOADK    	18 -35	; "cfont"
	65	[27]	LOADK    	19 -36	; 22
	66	[27]	CALL     	16 4 2
	67	[27]	SETTABLE 	15 -33 16	; "face" -
	68	[28]	SETTABLE 	15 -37 -24	; "_first_button" nil
	69	[29]	SETTABLE 	15 -38 -24	; "checked_button" nil
	70	[15]	CALL     	13 3 2
	71	[123]	CLOSURE  	14 0	; 0x7fd0c24070a0
	72	[123]	MOVE     	0 9
	73	[123]	MOVE     	0 5
	74	[123]	MOVE     	0 7
	75	[123]	MOVE     	0 11
	76	[123]	MOVE     	0 6
	77	[123]	MOVE     	0 0
	78	[123]	MOVE     	0 4
	79	[123]	MOVE     	0 1
	80	[32]	SETTABLE 	13 -39 14	; "init" -
	81	[143]	CLOSURE  	14 1	; 0x7fd0c2407e80
	82	[143]	MOVE     	0 10
	83	[143]	MOVE     	0 8
	84	[143]	MOVE     	0 6
	85	[143]	MOVE     	0 0
	86	[143]	MOVE     	0 4
	87	[125]	SETTABLE 	13 -40 14	; "addHorizontalSep" -
	88	[147]	CLOSURE  	14 2	; 0x7fd0c24082c0
	89	[145]	SETTABLE 	13 -41 14	; "onSelectByKeyPress" -
	90	[156]	CLOSURE  	14 3	; 0x7fd0c24088f0
	91	[149]	SETTABLE 	13 -42 14	; "_checkButton" -
	92	[158]	RETURN   	13 2
	93	[158]	RETURN   	0 1

function <./frontend/ui/widget/radiobuttontable.lua:32,123> (212 instructions, 848 bytes at 0x7fd0c24070a0)
1 param, 25 slots, 8 upvalues, 19 locals, 47 constants, 1 function
	1	[33]	NEWTABLE 	1 0 2
	2	[33]	SETTABLE 	1 -2 -3	; "x" 1
	3	[33]	SETTABLE 	1 -4 -3	; "y" 1
	4	[33]	SETTABLE 	0 -1 1	; "selected" -
	5	[34]	NEWTABLE 	1 0 0
	6	[34]	SETTABLE 	0 -5 1	; "radio_buttons_layout" -
	7	[35]	GETUPVAL 	1 0	; VerticalGroup
	8	[35]	SELF     	1 1 -7	; "new"
	9	[35]	NEWTABLE 	3 0 1
	10	[35]	GETTABLE 	4 0 -8	; "width"
	11	[35]	SETTABLE 	3 -8 4	; "width" -
	12	[35]	CALL     	1 3 2
	13	[35]	SETTABLE 	0 -6 1	; "container" -
	14	[36]	GETGLOBAL	1 -9	; table
	15	[36]	GETTABLE 	1 1 -10	; "insert"
	16	[36]	MOVE     	2 0
	17	[36]	GETTABLE 	3 0 -6	; "container"
	18	[36]	CALL     	1 3 1
	19	[38]	GETTABLE 	1 0 -11	; "zero_sep"
	20	[38]	TEST     	1 0 0
	21	[38]	JMP      	6	; to 28
	22	[42]	SELF     	1 0 -12	; "addHorizontalSep"
	23	[42]	LOADBOOL 	3 0 0
	24	[42]	LOADBOOL 	4 1 0
	25	[42]	LOADBOOL 	5 1 0
	26	[42]	CALL     	1 5 1
	27	[42]	JMP      	5	; to 33
	28	[44]	SELF     	1 0 -12	; "addHorizontalSep"
	29	[44]	LOADBOOL 	3 0 0
	30	[44]	LOADBOOL 	4 0 0
	31	[44]	LOADBOOL 	5 1 0
	32	[44]	CALL     	1 5 1
	33	[47]	GETTABLE 	1 0 -13	; "radio_buttons"
	34	[47]	LEN      	1 1
	35	[49]	LOADK    	2 -3	; 1
	36	[49]	MOVE     	3 1
	37	[49]	LOADK    	4 -3	; 1
	38	[49]	FORPREP  	2 130	; to 169
	39	[50]	GETTABLE 	6 0 -5	; "radio_buttons_layout"
	40	[50]	NEWTABLE 	7 0 0
	41	[50]	SETTABLE 	6 5 7
	42	[51]	GETUPVAL 	6 1	; HorizontalGroup
	43	[51]	SELF     	6 6 -7	; "new"
	44	[51]	NEWTABLE 	8 0 0
	45	[51]	CALL     	6 3 2
	46	[52]	GETTABLE 	7 0 -13	; "radio_buttons"
	47	[52]	GETTABLE 	7 7 5
	48	[53]	LEN      	8 7
	49	[54]	GETTABLE 	9 0 -14	; "sep_width"
	50	[54]	SUB      	10 8 -3	; - 1
	51	[54]	MUL      	9 9 10
	52	[54]	ADD      	9 9 -15	; - 2
	53	[55]	LOADK    	10 -3	; 1
	54	[55]	MOVE     	11 8
	55	[55]	LOADK    	12 -3	; 1
	56	[55]	FORPREP  	10 106	; to 163
	57	[56]	GETTABLE 	14 7 13
	58	[57]	GETUPVAL 	15 2	; RadioButton
	59	[57]	SELF     	15 15 -7	; "new"
	60	[57]	NEWTABLE 	17 0 12
	61	[58]	GETTABLE 	18 14 -16	; "text"
	62	[58]	SETTABLE 	17 -16 18	; "text" -
	63	[59]	GETTABLE 	18 14 -17	; "enabled"
	64	[59]	SETTABLE 	17 -17 18	; "enabled" -
	65	[60]	GETTABLE 	18 14 -18	; "checked"
	66	[60]	SETTABLE 	17 -18 18	; "checked" -
	67	[61]	GETTABLE 	18 14 -19	; "provider"
	68	[61]	SETTABLE 	17 -19 18	; "provider" -
	69	[63]	GETTABLE 	18 0 -8	; "width"
	70	[63]	SUB      	18 18 9
	71	[63]	DIV      	18 18 8
	72	[63]	SETTABLE 	17 -8 18	; "width" -
	73	[64]	GETTABLE 	18 0 -8	; "width"
	74	[64]	SUB      	18 18 9
	75	[64]	DIV      	18 18 8
	76	[64]	GETTABLE 	19 0 -14	; "sep_width"
	77	[64]	MUL      	19 -15 19	; 2 -
	78	[64]	SUB      	18 18 19
	79	[64]	GETTABLE 	19 0 -21	; "padding"
	80	[64]	MUL      	19 -15 19	; 2 -
	81	[64]	SUB      	18 18 19
	82	[64]	SETTABLE 	17 -20 18	; "max_width" -
	83	[65]	SETTABLE 	17 -22 -23	; "bordersize" 0
	84	[66]	SETTABLE 	17 -24 -23	; "margin" 0
	85	[67]	SETTABLE 	17 -21 -23	; "padding" 0
	86	[68]	GETTABLE 	18 0 -25	; "face"
	87	[68]	SETTABLE 	17 -25 18	; "face" -
	88	[70]	GETTABLE 	18 0 -26	; "show_parent"
	89	[70]	TEST     	18 0 1
	90	[70]	JMP      	1	; to 92
	91	[70]	MOVE     	18 0
	92	[70]	SETTABLE 	17 -26 18	; "show_parent" -
	93	[71]	GETTABLE 	18 0 -27	; "parent"
	94	[71]	TEST     	18 0 1
	95	[71]	JMP      	1	; to 97
	96	[71]	MOVE     	18 0
	97	[71]	SETTABLE 	17 -27 18	; "parent" -
	98	[57]	CALL     	15 3 2
	99	[75]	CLOSURE  	16 0	; 0x7fd0c24073d0
	100	[75]	MOVE     	0 0
	101	[75]	MOVE     	0 15
	102	[76]	SETTABLE 	15 -28 16	; "callback" -
	103	[78]	EQ       	0 5 -3	; - 1
	104	[78]	JMP      	3	; to 108
	105	[78]	EQ       	0 13 -3	; - 1
	106	[78]	JMP      	1	; to 108
	107	[79]	SETTABLE 	0 -29 15	; "_first_button" -
	108	[82]	GETTABLE 	17 15 -18	; "checked"
	109	[82]	TEST     	17 0 0
	110	[82]	JMP      	5	; to 116
	111	[82]	GETTABLE 	17 0 -30	; "checked_button"
	112	[82]	TEST     	17 0 1
	113	[82]	JMP      	2	; to 116
	114	[83]	SETTABLE 	0 -30 15	; "checked_button" -
	115	[83]	JMP      	13	; to 129
	116	[84]	GETUPVAL 	17 3	; dbg
	117	[84]	GETTABLE 	17 17 -31	; "is_on"
	118	[84]	TEST     	17 0 0
	119	[84]	JMP      	9	; to 129
	120	[85]	GETTABLE 	17 15 -18	; "checked"
	121	[85]	TEST     	17 0 0
	122	[85]	JMP      	6	; to 129
	123	[85]	GETTABLE 	17 0 -30	; "checked_button"
	124	[85]	TEST     	17 0 0
	125	[85]	JMP      	3	; to 129
	126	[86]	GETGLOBAL	17 -32	; error
	127	[86]	LOADK    	18 -33	; "RadioButtonGroup: multiple checked RadioButtons"
	128	[86]	CALL     	17 2 1
	129	[89]	SELF     	17 15 -34	; "getSize"
	130	[89]	CALL     	17 2 2
	131	[90]	GETUPVAL 	18 4	; LineWidget
	132	[90]	SELF     	18 18 -7	; "new"
	133	[90]	NEWTABLE 	20 0 2
	134	[91]	GETUPVAL 	21 5	; Blitbuffer
	135	[91]	GETTABLE 	21 21 -36	; "COLOR_DARK_GRAY"
	136	[91]	SETTABLE 	20 -35 21	; "background" -
	137	[92]	GETUPVAL 	21 6	; Geom
	138	[92]	SELF     	21 21 -7	; "new"
	139	[92]	NEWTABLE 	23 0 2
	140	[93]	GETTABLE 	24 0 -14	; "sep_width"
	141	[93]	SETTABLE 	23 -38 24	; "w" -
	142	[94]	GETTABLE 	24 17 -39	; "h"
	143	[94]	SETTABLE 	23 -39 24	; "h" -
	144	[92]	CALL     	21 3 2
	145	[95]	SETTABLE 	20 -37 21	; "dimen" -
	146	[90]	CALL     	18 3 2
	147	[97]	GETTABLE 	19 0 -5	; "radio_buttons_layout"
	148	[97]	GETTABLE 	19 19 5
	149	[97]	SETTABLE 	19 13 15
	150	[98]	GETGLOBAL	19 -9	; table
	151	[98]	GETTABLE 	19 19 -10	; "insert"
	152	[98]	MOVE     	20 6
	153	[98]	MOVE     	21 15
	154	[98]	CALL     	19 3 1
	155	[99]	LT       	0 13 8
	156	[99]	JMP      	5	; to 162
	157	[100]	GETGLOBAL	19 -9	; table
	158	[100]	GETTABLE 	19 19 -10	; "insert"
	159	[100]	MOVE     	20 6
	160	[100]	MOVE     	21 18
	161	[100]	CALL     	19 3 1
	162	[101]	CLOSE    	14
	163	[55]	FORLOOP  	10 -107	; to 57
	164	[103]	GETGLOBAL	10 -9	; table
	165	[103]	GETTABLE 	10 10 -10	; "insert"
	166	[103]	GETTABLE 	11 0 -6	; "container"
	167	[103]	MOVE     	12 6
	168	[103]	CALL     	10 3 1
	169	[49]	FORLOOP  	2 -131	; to 39
	170	[108]	SELF     	2 0 -12	; "addHorizontalSep"
	171	[108]	LOADBOOL 	4 1 0
	172	[108]	LOADBOOL 	5 0 0
	173	[108]	LOADBOOL 	6 0 0
	174	[108]	CALL     	2 5 1
	175	[111]	GETTABLE 	2 0 -30	; "checked_button"
	176	[111]	TEST     	2 0 1
	177	[111]	JMP      	5	; to 183
	178	[112]	GETTABLE 	2 0 -29	; "_first_button"
	179	[112]	SELF     	2 2 -40	; "check"
	180	[112]	CALL     	2 2 1
	181	[113]	GETTABLE 	2 0 -29	; "_first_button"
	182	[113]	SETTABLE 	0 -30 2	; "checked_button" -
	183	[116]	GETUPVAL 	2 7	; Device
	184	[116]	SELF     	2 2 -41	; "hasDPad"
	185	[116]	CALL     	2 2 2
	186	[116]	TEST     	2 0 1
	187	[116]	JMP      	5	; to 193
	188	[116]	GETUPVAL 	2 7	; Device
	189	[116]	SELF     	2 2 -42	; "hasKeyboard"
	190	[116]	CALL     	2 2 2
	191	[116]	TEST     	2 0 0
	192	[116]	JMP      	17	; to 210
	193	[117]	GETTABLE 	2 0 -5	; "radio_buttons_layout"
	194	[117]	SETTABLE 	0 -43 2	; "layout" -
	195	[118]	GETTABLE 	2 0 -43	; "layout"
	196	[118]	GETTABLE 	2 2 -3	; 1
	197	[118]	GETTABLE 	2 2 -3	; 1
	198	[118]	SELF     	2 2 -44	; "onFocus"
	199	[118]	CALL     	2 2 1
	200	[119]	GETTABLE 	2 0 -45	; "key_events"
	201	[119]	NEWTABLE 	3 1 0
	202	[119]	NEWTABLE 	4 1 0
	203	[119]	NEWTABLE 	5 1 0
	204	[119]	LOADK    	6 -47	; "Press"
	205	[119]	SETLIST  	5 1 1	; 1
	206	[119]	SETLIST  	4 1 1	; 1
	207	[119]	SETLIST  	3 1 1	; 1
	208	[119]	SETTABLE 	2 -46 3	; "SelectByKeyPress" -
	209	[119]	JMP      	2	; to 212
	210	[121]	NEWTABLE 	2 0 0
	211	[121]	SETTABLE 	0 -45 2	; "key_events" -
	212	[123]	RETURN   	0 1

function <./frontend/ui/widget/radiobuttontable.lua:73,75> (5 instructions, 20 bytes at 0x7fd0c24073d0)
0 params, 3 slots, 2 upvalues, 0 locals, 1 constant, 0 functions
	1	[74]	GETUPVAL 	0 0	; self
	2	[74]	SELF     	0 0 -1	; "_checkButton"
	3	[74]	GETUPVAL 	2 1	; button
	4	[74]	CALL     	0 3 1
	5	[75]	RETURN   	0 1

function <./frontend/ui/widget/radiobuttontable.lua:125,143> (57 instructions, 228 bytes at 0x7fd0c2407e80)
5 params, 14 slots, 5 upvalues, 5 locals, 14 constants, 0 functions
	1	[126]	TEST     	1 0 0
	2	[126]	JMP      	12	; to 15
	3	[127]	GETGLOBAL	5 -1	; table
	4	[127]	GETTABLE 	5 5 -2	; "insert"
	5	[127]	GETTABLE 	6 0 -3	; "container"
	6	[128]	GETUPVAL 	7 0	; VerticalSpan
	7	[128]	SELF     	7 7 -4	; "new"
	8	[128]	NEWTABLE 	9 0 1
	9	[128]	GETUPVAL 	10 1	; Size
	10	[128]	GETTABLE 	10 10 -6	; "span"
	11	[128]	GETTABLE 	10 10 -7	; "vertical_default"
	12	[128]	SETTABLE 	9 -5 10	; "width" -
	13	[128]	CALL     	7 3 0
	14	[127]	CALL     	5 0 1
	15	[130]	TEST     	2 0 0
	16	[130]	JMP      	26	; to 43
	17	[131]	GETGLOBAL	5 -1	; table
	18	[131]	GETTABLE 	5 5 -2	; "insert"
	19	[131]	GETTABLE 	6 0 -3	; "container"
	20	[131]	GETUPVAL 	7 2	; LineWidget
	21	[131]	SELF     	7 7 -4	; "new"
	22	[131]	NEWTABLE 	9 0 2
	23	[132]	TEST     	4 0 0
	24	[132]	JMP      	4	; to 29
	25	[132]	GETUPVAL 	10 3	; Blitbuffer
	26	[132]	GETTABLE 	10 10 -9	; "COLOR_BLACK"
	27	[132]	TEST     	10 0 1
	28	[132]	JMP      	2	; to 31
	29	[132]	GETUPVAL 	10 3	; Blitbuffer
	30	[132]	GETTABLE 	10 10 -10	; "COLOR_DARK_GRAY"
	31	[132]	SETTABLE 	9 -8 10	; "background" -
	32	[133]	GETUPVAL 	10 4	; Geom
	33	[133]	SELF     	10 10 -4	; "new"
	34	[133]	NEWTABLE 	12 0 2
	35	[134]	GETTABLE 	13 0 -5	; "width"
	36	[134]	SETTABLE 	12 -12 13	; "w" -
	37	[135]	GETTABLE 	13 0 -14	; "sep_width"
	38	[135]	SETTABLE 	12 -13 13	; "h" -
	39	[133]	CALL     	10 3 2
	40	[136]	SETTABLE 	9 -11 10	; "dimen" -
	41	[131]	CALL     	7 3 0
	42	[131]	CALL     	5 0 1
	43	[139]	TEST     	3 0 0
	44	[139]	JMP      	12	; to 57
	45	[140]	GETGLOBAL	5 -1	; table
	46	[140]	GETTABLE 	5 5 -2	; "insert"
	47	[140]	GETTABLE 	6 0 -3	; "container"
	48	[141]	GETUPVAL 	7 0	; VerticalSpan
	49	[141]	SELF     	7 7 -4	; "new"
	50	[141]	NEWTABLE 	9 0 1
	51	[141]	GETUPVAL 	10 1	; Size
	52	[141]	GETTABLE 	10 10 -6	; "span"
	53	[141]	GETTABLE 	10 10 -7	; "vertical_default"
	54	[141]	SETTABLE 	9 -5 10	; "width" -
	55	[141]	CALL     	7 3 0
	56	[140]	CALL     	5 0 1
	57	[143]	RETURN   	0 1

function <./frontend/ui/widget/radiobuttontable.lua:145,147> (5 instructions, 20 bytes at 0x7fd0c24082c0)
1 param, 3 slots, 0 upvalues, 1 local, 2 constants, 0 functions
	1	[146]	SELF     	1 0 -1	; "getFocusItem"
	2	[146]	CALL     	1 2 2
	3	[146]	GETTABLE 	1 1 -2	; "callback"
	4	[146]	CALL     	1 1 1
	5	[147]	RETURN   	0 1

function <./frontend/ui/widget/radiobuttontable.lua:149,156> (11 instructions, 44 bytes at 0x7fd0c24088f0)
2 params, 4 slots, 0 upvalues, 2 locals, 4 constants, 0 functions
	1	[151]	GETTABLE 	2 1 -1	; "checked"
	2	[151]	TEST     	2 0 0
	3	[151]	JMP      	1	; to 5
	4	[151]	RETURN   	0 1
	5	[153]	GETTABLE 	2 0 -2	; "checked_button"
	6	[153]	SELF     	2 2 -3	; "unCheck"
	7	[153]	CALL     	2 2 1
	8	[154]	SELF     	2 1 -4	; "check"
	9	[154]	CALL     	2 2 1
	10	[155]	SETTABLE 	0 -2 1	; "checked_button" -
	11	[156]	RETURN   	0 1
