
main <./spec/unit/random_spec.lua:0,0> (5 instructions, 20 bytes at 0x7ff75a4068c0)
0+ params, 3 slots, 0 upvalues, 0 locals, 2 constants, 1 function
	1	[1]	GETGLOBAL	0 -1	; describe
	2	[1]	LOADK    	1 -2	; "random package tests"
	3	[33]	CLOSURE  	2 0	; 0x7ff75a406b60
	4	[1]	CALL     	0 3 1
	5	[33]	RETURN   	0 1

function <./spec/unit/random_spec.lua:1,33> (18 instructions, 72 bytes at 0x7ff75a406b60)
0 params, 5 slots, 0 upvalues, 2 locals, 4 constants, 4 functions
	1	[6]	CLOSURE  	1 0	; 0x7ff75a406d20
	2	[8]	GETGLOBAL	2 -1	; setup
	3	[10]	CLOSURE  	3 1	; 0x7ff75a407390
	4	[10]	MOVE     	0 0
	5	[8]	CALL     	2 2 1
	6	[12]	GETGLOBAL	2 -2	; it
	7	[12]	LOADK    	3 -3	; "should generate uuid without dash"
	8	[19]	CLOSURE  	4 2	; 0x7ff75a407600
	9	[19]	MOVE     	0 0
	10	[19]	MOVE     	0 1
	11	[12]	CALL     	2 3 1
	12	[21]	GETGLOBAL	2 -2	; it
	13	[21]	LOADK    	3 -4	; "should generate uuid with dash"
	14	[32]	CLOSURE  	4 3	; 0x7ff75a4066c0
	15	[32]	MOVE     	0 0
	16	[32]	MOVE     	0 1
	17	[21]	CALL     	2 3 1
	18	[33]	RETURN   	0 1

function <./spec/unit/random_spec.lua:4,6> (12 instructions, 48 bytes at 0x7ff75a406d20)
1 param, 2 slots, 0 upvalues, 1 local, 4 constants, 0 functions
	1	[5]	EQ       	1 0 -1	; - "8"
	2	[5]	JMP      	7	; to 10
	3	[5]	EQ       	1 0 -2	; - "9"
	4	[5]	JMP      	5	; to 10
	5	[5]	EQ       	1 0 -3	; - "A"
	6	[5]	JMP      	3	; to 10
	7	[5]	EQ       	1 0 -4	; - "B"
	8	[5]	JMP      	1	; to 10
	9	[5]	LOADBOOL 	1 0 1
	10	[5]	LOADBOOL 	1 1 0
	11	[5]	RETURN   	1 2
	12	[6]	RETURN   	0 1

function <./spec/unit/random_spec.lua:8,10> (5 instructions, 20 bytes at 0x7ff75a407390)
0 params, 2 slots, 1 upvalue, 0 locals, 2 constants, 0 functions
	1	[9]	GETGLOBAL	0 -1	; require
	2	[9]	LOADK    	1 -2	; "frontend/random"
	3	[9]	CALL     	0 2 2
	4	[9]	SETUPVAL 	0 0	; random
	5	[10]	RETURN   	0 1

function <./spec/unit/random_spec.lua:12,19> (32 instructions, 128 bytes at 0x7ff75a407600)
0 params, 11 slots, 2 upvalues, 5 locals, 12 constants, 0 functions
	1	[13]	LOADK    	0 -1	; 1
	2	[13]	LOADK    	1 -2	; 10000
	3	[13]	LOADK    	2 -1	; 1
	4	[13]	FORPREP  	0 26	; to 31
	5	[14]	GETUPVAL 	4 0	; random
	6	[14]	GETTABLE 	4 4 -3	; "uuid"
	7	[14]	CALL     	4 1 2
	8	[15]	GETGLOBAL	5 -4	; assert
	9	[15]	GETTABLE 	5 5 -5	; "Equals"
	10	[15]	SELF     	6 4 -6	; "len"
	11	[15]	CALL     	6 2 2
	12	[15]	LOADK    	7 -7	; 32
	13	[15]	CALL     	5 3 1
	14	[16]	GETGLOBAL	5 -4	; assert
	15	[16]	GETTABLE 	5 5 -5	; "Equals"
	16	[16]	SELF     	6 4 -8	; "sub"
	17	[16]	LOADK    	8 -9	; 13
	18	[16]	LOADK    	9 -9	; 13
	19	[16]	CALL     	6 4 2
	20	[16]	LOADK    	7 -10	; "4"
	21	[16]	CALL     	5 3 1
	22	[17]	GETGLOBAL	5 -4	; assert
	23	[17]	GETTABLE 	5 5 -11	; "is_true"
	24	[17]	GETUPVAL 	6 1	; is_magic_char
	25	[17]	SELF     	7 4 -8	; "sub"
	26	[17]	LOADK    	9 -12	; 17
	27	[17]	LOADK    	10 -12	; 17
	28	[17]	CALL     	7 4 0
	29	[17]	CALL     	6 0 0
	30	[17]	CALL     	5 0 1
	31	[13]	FORLOOP  	0 -27	; to 5
	32	[19]	RETURN   	0 1

function <./spec/unit/random_spec.lua:21,32> (65 instructions, 260 bytes at 0x7ff75a4066c0)
0 params, 11 slots, 2 upvalues, 5 locals, 17 constants, 0 functions
	1	[22]	LOADK    	0 -1	; 1
	2	[22]	LOADK    	1 -2	; 10000
	3	[22]	LOADK    	2 -1	; 1
	4	[22]	FORPREP  	0 59	; to 64
	5	[23]	GETUPVAL 	4 0	; random
	6	[23]	GETTABLE 	4 4 -3	; "uuid"
	7	[23]	LOADBOOL 	5 1 0
	8	[23]	CALL     	4 2 2
	9	[24]	GETGLOBAL	5 -4	; assert
	10	[24]	GETTABLE 	5 5 -5	; "Equals"
	11	[24]	SELF     	6 4 -6	; "len"
	12	[24]	CALL     	6 2 2
	13	[24]	LOADK    	7 -7	; 36
	14	[24]	CALL     	5 3 1
	15	[25]	GETGLOBAL	5 -4	; assert
	16	[25]	GETTABLE 	5 5 -5	; "Equals"
	17	[25]	SELF     	6 4 -8	; "sub"
	18	[25]	LOADK    	8 -9	; 9
	19	[25]	LOADK    	9 -9	; 9
	20	[25]	CALL     	6 4 2
	21	[25]	LOADK    	7 -10	; "-"
	22	[25]	CALL     	5 3 1
	23	[26]	GETGLOBAL	5 -4	; assert
	24	[26]	GETTABLE 	5 5 -5	; "Equals"
	25	[26]	SELF     	6 4 -8	; "sub"
	26	[26]	LOADK    	8 -11	; 14
	27	[26]	LOADK    	9 -11	; 14
	28	[26]	CALL     	6 4 2
	29	[26]	LOADK    	7 -10	; "-"
	30	[26]	CALL     	5 3 1
	31	[27]	GETGLOBAL	5 -4	; assert
	32	[27]	GETTABLE 	5 5 -5	; "Equals"
	33	[27]	SELF     	6 4 -8	; "sub"
	34	[27]	LOADK    	8 -12	; 19
	35	[27]	LOADK    	9 -12	; 19
	36	[27]	CALL     	6 4 2
	37	[27]	LOADK    	7 -10	; "-"
	38	[27]	CALL     	5 3 1
	39	[28]	GETGLOBAL	5 -4	; assert
	40	[28]	GETTABLE 	5 5 -5	; "Equals"
	41	[28]	SELF     	6 4 -8	; "sub"
	42	[28]	LOADK    	8 -13	; 24
	43	[28]	LOADK    	9 -13	; 24
	44	[28]	CALL     	6 4 2
	45	[28]	LOADK    	7 -10	; "-"
	46	[28]	CALL     	5 3 1
	47	[29]	GETGLOBAL	5 -4	; assert
	48	[29]	GETTABLE 	5 5 -5	; "Equals"
	49	[29]	SELF     	6 4 -8	; "sub"
	50	[29]	LOADK    	8 -14	; 15
	51	[29]	LOADK    	9 -14	; 15
	52	[29]	CALL     	6 4 2
	53	[29]	LOADK    	7 -15	; "4"
	54	[29]	CALL     	5 3 1
	55	[30]	GETGLOBAL	5 -4	; assert
	56	[30]	GETTABLE 	5 5 -16	; "is_true"
	57	[30]	GETUPVAL 	6 1	; is_magic_char
	58	[30]	SELF     	7 4 -8	; "sub"
	59	[30]	LOADK    	9 -17	; 20
	60	[30]	LOADK    	10 -17	; 20
	61	[30]	CALL     	7 4 0
	62	[30]	CALL     	6 0 0
	63	[30]	CALL     	5 0 1
	64	[22]	FORLOOP  	0 -60	; to 5
	65	[32]	RETURN   	0 1
