
main <./frontend/random.lua:0,0> (13 instructions, 52 bytes at 0x7f9cad4068a0)
0+ params, 3 slots, 0 upvalues, 2 locals, 4 constants, 2 functions
	1	[3]	GETGLOBAL	0 -1	; require
	2	[3]	LOADK    	1 -2	; "bit"
	3	[3]	CALL     	0 2 2
	4	[4]	NEWTABLE 	1 0 0
	5	[9]	CLOSURE  	2 0	; 0x7f9cad406ca0
	6	[7]	SETTABLE 	1 -3 2	; "seed" -
	7	[11]	GETTABLE 	2 1 -3	; "seed"
	8	[11]	CALL     	2 1 1
	9	[32]	CLOSURE  	2 1	; 0x7f9cad406e40
	10	[32]	MOVE     	0 0
	11	[14]	SETTABLE 	1 -4 2	; "uuid" -
	12	[34]	RETURN   	1 2
	13	[34]	RETURN   	0 1

function <./frontend/random.lua:7,9> (7 instructions, 28 bytes at 0x7f9cad406ca0)
0 params, 2 slots, 0 upvalues, 0 locals, 4 constants, 0 functions
	1	[8]	GETGLOBAL	0 -1	; math
	2	[8]	GETTABLE 	0 0 -2	; "randomseed"
	3	[8]	GETGLOBAL	1 -3	; os
	4	[8]	GETTABLE 	1 1 -4	; "time"
	5	[8]	CALL     	1 1 0
	6	[8]	CALL     	0 0 1
	7	[9]	RETURN   	0 1

function <./frontend/random.lua:14,32> (59 instructions, 236 bytes at 0x7f9cad406e40)
1 param, 10 slots, 1 upvalue, 6 locals, 20 constants, 0 functions
	1	[15]	NEWTABLE 	1 0 0
	2	[16]	LOADK    	2 -1	; 1
	3	[16]	LOADK    	3 -2	; 16
	4	[16]	LOADK    	4 -1	; 1
	5	[16]	FORPREP  	2 9	; to 15
	6	[17]	GETGLOBAL	6 -3	; table
	7	[17]	GETTABLE 	6 6 -4	; "insert"
	8	[17]	MOVE     	7 1
	9	[17]	GETGLOBAL	8 -5	; math
	10	[17]	GETTABLE 	8 8 -6	; "random"
	11	[17]	LOADK    	9 -7	; 256
	12	[17]	CALL     	8 2 2
	13	[17]	SUB      	8 8 -1	; - 1
	14	[17]	CALL     	6 3 1
	15	[16]	FORLOOP  	2 -10	; to 6
	16	[20]	GETUPVAL 	2 0	; bit
	17	[20]	GETTABLE 	2 2 -9	; "band"
	18	[20]	GETTABLE 	3 1 -8	; 7
	19	[20]	LOADK    	4 -10	; 79
	20	[20]	CALL     	2 3 2
	21	[20]	SETTABLE 	1 -8 2	; 7 -
	22	[21]	GETUPVAL 	2 0	; bit
	23	[21]	GETTABLE 	2 2 -11	; "bor"
	24	[21]	GETTABLE 	3 1 -8	; 7
	25	[21]	LOADK    	4 -12	; 64
	26	[21]	CALL     	2 3 2
	27	[21]	SETTABLE 	1 -8 2	; 7 -
	28	[23]	GETUPVAL 	2 0	; bit
	29	[23]	GETTABLE 	2 2 -9	; "band"
	30	[23]	GETTABLE 	3 1 -13	; 9
	31	[23]	LOADK    	4 -14	; 191
	32	[23]	CALL     	2 3 2
	33	[23]	SETTABLE 	1 -13 2	; 9 -
	34	[24]	GETUPVAL 	2 0	; bit
	35	[24]	GETTABLE 	2 2 -11	; "bor"
	36	[24]	GETTABLE 	3 1 -13	; 9
	37	[24]	LOADK    	4 -15	; 128
	38	[24]	CALL     	2 3 2
	39	[24]	SETTABLE 	1 -13 2	; 9 -
	40	[25]	TEST     	0 0 0
	41	[25]	JMP      	9	; to 51
	42	[26]	GETGLOBAL	2 -16	; string
	43	[26]	GETTABLE 	2 2 -17	; "format"
	44	[26]	LOADK    	3 -18	; "%02X%02X%02X%02X-%02X%02X-%02X%02X-%02X%02X-%02X%02X%02X%02X%02X%02X"
	45	[27]	GETGLOBAL	4 -19	; unpack
	46	[27]	MOVE     	5 1
	47	[27]	CALL     	4 2 0
	48	[26]	TAILCALL 	2 0 0
	49	[27]	RETURN   	2 0
	50	[27]	JMP      	8	; to 59
	51	[29]	GETGLOBAL	2 -16	; string
	52	[29]	GETTABLE 	2 2 -17	; "format"
	53	[29]	LOADK    	3 -20	; "%02X%02X%02X%02X%02X%02X%02X%02X%02X%02X%02X%02X%02X%02X%02X%02X"
	54	[30]	GETGLOBAL	4 -19	; unpack
	55	[30]	MOVE     	5 1
	56	[30]	CALL     	4 2 0
	57	[29]	TAILCALL 	2 0 0
	58	[30]	RETURN   	2 0
	59	[32]	RETURN   	0 1
