-- BYTECODE -- random_spec.lua:4-6
0001    ISEQS    0   0      ; "8"
0002    JMP      1 => 0011
0003    ISEQS    0   1      ; "9"
0004    JMP      1 => 0011
0005    ISEQS    0   2      ; "A"
0006    JMP      1 => 0011
0007    ISEQS    0   3      ; "B"
0008    JMP      1 => 0011
0009    KPRI     1   1
0010    JMP      2 => 0012
0011 => KPRI     1   2
0012 => RET1     1   2

-- BYTECODE -- random_spec.lua:8-10
0001    GGET     0   0      ; "require"
0002    KSTR     1   1      ; "frontend/random"
0003    CALL     0   2   2
0004    USETV    0   0      ; random
0005    RET0     0   1

-- BYTECODE -- random_spec.lua:12-19
0001    KSHORT   0   1
0002    KSHORT   1 10000
0003    KSHORT   2   1
0004    FORI     0 => 0035
0005 => UGET     4   0      ; random
0006    TGETS    4   4   0  ; "uuid"
0007    CALL     4   2   1
0008    GGET     5   1      ; "assert"
0009    TGETS    5   5   2  ; "Equals"
0010    MOV      7   4
0011    TGETS    6   4   3  ; "len"
0012    CALL     6   2   2
0013    KSHORT   7  32
0014    CALL     5   1   3
0015    GGET     5   1      ; "assert"
0016    TGETS    5   5   2  ; "Equals"
0017    MOV      7   4
0018    TGETS    6   4   4  ; "sub"
0019    KSHORT   8  13
0020    KSHORT   9  13
0021    CALL     6   2   4
0022    KSTR     7   5      ; "4"
0023    CALL     5   1   3
0024    GGET     5   1      ; "assert"
0025    TGETS    5   5   6  ; "is_true"
0026    UGET     6   1      ; is_magic_char
0027    MOV      8   4
0028    TGETS    7   4   4  ; "sub"
0029    KSHORT   9  17
0030    KSHORT  10  17
0031    CALL     7   0   4
0032    CALLM    6   0   0
0033    CALLM    5   1   0
0034    FORL     0 => 0005
0035 => RET0     0   1

-- BYTECODE -- random_spec.lua:21-32
0001    KSHORT   0   1
0002    KSHORT   1 10000
0003    KSHORT   2   1
0004    FORI     0 => 0072
0005 => UGET     4   0      ; random
0006    TGETS    4   4   0  ; "uuid"
0007    KPRI     5   2
0008    CALL     4   2   2
0009    GGET     5   1      ; "assert"
0010    TGETS    5   5   2  ; "Equals"
0011    MOV      7   4
0012    TGETS    6   4   3  ; "len"
0013    CALL     6   2   2
0014    KSHORT   7  36
0015    CALL     5   1   3
0016    GGET     5   1      ; "assert"
0017    TGETS    5   5   2  ; "Equals"
0018    MOV      7   4
0019    TGETS    6   4   4  ; "sub"
0020    KSHORT   8   9
0021    KSHORT   9   9
0022    CALL     6   2   4
0023    KSTR     7   5      ; "-"
0024    CALL     5   1   3
0025    GGET     5   1      ; "assert"
0026    TGETS    5   5   2  ; "Equals"
0027    MOV      7   4
0028    TGETS    6   4   4  ; "sub"
0029    KSHORT   8  14
0030    KSHORT   9  14
0031    CALL     6   2   4
0032    KSTR     7   5      ; "-"
0033    CALL     5   1   3
0034    GGET     5   1      ; "assert"
0035    TGETS    5   5   2  ; "Equals"
0036    MOV      7   4
0037    TGETS    6   4   4  ; "sub"
0038    KSHORT   8  19
0039    KSHORT   9  19
0040    CALL     6   2   4
0041    KSTR     7   5      ; "-"
0042    CALL     5   1   3
0043    GGET     5   1      ; "assert"
0044    TGETS    5   5   2  ; "Equals"
0045    MOV      7   4
0046    TGETS    6   4   4  ; "sub"
0047    KSHORT   8  24
0048    KSHORT   9  24
0049    CALL     6   2   4
0050    KSTR     7   5      ; "-"
0051    CALL     5   1   3
0052    GGET     5   1      ; "assert"
0053    TGETS    5   5   2  ; "Equals"
0054    MOV      7   4
0055    TGETS    6   4   4  ; "sub"
0056    KSHORT   8  15
0057    KSHORT   9  15
0058    CALL     6   2   4
0059    KSTR     7   6      ; "4"
0060    CALL     5   1   3
0061    GGET     5   1      ; "assert"
0062    TGETS    5   5   7  ; "is_true"
0063    UGET     6   1      ; is_magic_char
0064    MOV      8   4
0065    TGETS    7   4   4  ; "sub"
0066    KSHORT   9  20
0067    KSHORT  10  20
0068    CALL     7   0   4
0069    CALLM    6   0   0
0070    CALLM    5   1   0
0071    FORL     0 => 0005
0072 => RET0     0   1

-- BYTECODE -- random_spec.lua:1-33
0001    KPRI     0   0
0002    FNEW     1   0      ; random_spec.lua:4
0003    GGET     2   1      ; "setup"
0004    FNEW     3   2      ; random_spec.lua:8
0005    CALL     2   1   2
0006    GGET     2   3      ; "it"
0007    KSTR     3   4      ; "should generate uuid without dash"
0008    FNEW     4   5      ; random_spec.lua:12
0009    CALL     2   1   3
0010    GGET     2   3      ; "it"
0011    KSTR     3   6      ; "should generate uuid with dash"
0012    FNEW     4   7      ; random_spec.lua:21
0013    CALL     2   1   3
0014    UCLO     0 => 0015
0015 => RET0     0   1

-- BYTECODE -- random_spec.lua:0-34
0001    GGET     0   0      ; "describe"
0002    KSTR     1   1      ; "random package tests"
0003    FNEW     2   2      ; random_spec.lua:1
0004    CALL     0   1   3
0005    RET0     0   1

