
main <./frontend/apps/reader/modules/readerstyletweak.lua:0,0> (165 instructions, 660 bytes at 0x7fa6fec06900)
0+ params, 31 slots, 0 upvalues, 29 locals, 58 constants, 16 functions
	1	[1]	GETGLOBAL	0 -1	; require
	2	[1]	LOADK    	1 -2	; "ui/bidi"
	3	[1]	CALL     	0 2 2
	4	[2]	GETGLOBAL	1 -1	; require
	5	[2]	LOADK    	2 -3	; "ffi/blitbuffer"
	6	[2]	CALL     	1 2 2
	7	[3]	GETGLOBAL	2 -1	; require
	8	[3]	LOADK    	3 -4	; "ui/widget/buttontable"
	9	[3]	CALL     	2 2 2
	10	[4]	GETGLOBAL	3 -1	; require
	11	[4]	LOADK    	4 -5	; "ui/widget/container/centercontainer"
	12	[4]	CALL     	3 2 2
	13	[5]	GETGLOBAL	4 -1	; require
	14	[5]	LOADK    	5 -6	; "ui/data/css_tweaks"
	15	[5]	CALL     	4 2 2
	16	[6]	GETGLOBAL	5 -1	; require
	17	[6]	LOADK    	6 -7	; "datastorage"
	18	[6]	CALL     	5 2 2
	19	[7]	GETGLOBAL	6 -1	; require
	20	[7]	LOADK    	7 -8	; "device"
	21	[7]	CALL     	6 2 2
	22	[8]	GETGLOBAL	7 -1	; require
	23	[8]	LOADK    	8 -9	; "ui/event"
	24	[8]	CALL     	7 2 2
	25	[9]	GETGLOBAL	8 -1	; require
	26	[9]	LOADK    	9 -10	; "ui/font"
	27	[9]	CALL     	8 2 2
	28	[10]	GETGLOBAL	9 -1	; require
	29	[10]	LOADK    	10 -11	; "ui/widget/container/framecontainer"
	30	[10]	CALL     	9 2 2
	31	[11]	GETGLOBAL	10 -1	; require
	32	[11]	LOADK    	11 -12	; "ui/geometry"
	33	[11]	CALL     	10 2 2
	34	[12]	GETGLOBAL	11 -1	; require
	35	[12]	LOADK    	12 -13	; "ui/gesturerange"
	36	[12]	CALL     	11 2 2
	37	[13]	GETGLOBAL	12 -1	; require
	38	[13]	LOADK    	13 -14	; "ui/widget/infomessage"
	39	[13]	CALL     	12 2 2
	40	[14]	GETGLOBAL	13 -1	; require
	41	[14]	LOADK    	14 -15	; "ui/widget/container/inputcontainer"
	42	[14]	CALL     	13 2 2
	43	[15]	GETGLOBAL	14 -1	; require
	44	[15]	LOADK    	15 -16	; "ui/widget/container/movablecontainer"
	45	[15]	CALL     	14 2 2
	46	[16]	GETGLOBAL	15 -1	; require
	47	[16]	LOADK    	16 -17	; "ui/size"
	48	[16]	CALL     	15 2 2
	49	[17]	GETGLOBAL	16 -1	; require
	50	[17]	LOADK    	17 -18	; "ui/widget/textboxwidget"
	51	[17]	CALL     	16 2 2
	52	[18]	GETGLOBAL	17 -1	; require
	53	[18]	LOADK    	18 -19	; "ui/uimanager"
	54	[18]	CALL     	17 2 2
	55	[19]	GETGLOBAL	18 -1	; require
	56	[19]	LOADK    	19 -20	; "ui/widget/verticalgroup"
	57	[19]	CALL     	18 2 2
	58	[20]	GETGLOBAL	19 -1	; require
	59	[20]	LOADK    	20 -21	; "ui/widget/verticalspan"
	60	[20]	CALL     	19 2 2
	61	[21]	GETGLOBAL	20 -1	; require
	62	[21]	LOADK    	21 -22	; "libs/libkoreader-lfs"
	63	[21]	CALL     	20 2 2
	64	[22]	GETGLOBAL	21 -1	; require
	65	[22]	LOADK    	22 -23	; "logger"
	66	[22]	CALL     	21 2 2
	67	[23]	GETGLOBAL	22 -1	; require
	68	[23]	LOADK    	23 -24	; "util"
	69	[23]	CALL     	22 2 2
	70	[24]	GETGLOBAL	23 -1	; require
	71	[24]	LOADK    	24 -25	; "gettext"
	72	[24]	CALL     	23 2 2
	73	[25]	GETTABLE 	24 6 -26	; "screen"
	74	[26]	GETGLOBAL	25 -1	; require
	75	[26]	LOADK    	26 -27	; "ffi/util"
	76	[26]	CALL     	25 2 2
	77	[26]	GETTABLE 	25 25 -28	; "template"
	78	[29]	SELF     	26 13 -29	; "new"
	79	[29]	NEWTABLE 	28 0 5
	80	[30]	SETTABLE 	28 -30 -31	; "tweak" nil
	81	[31]	SETTABLE 	28 -32 -31	; "is_global_default" nil
	82	[32]	CLOSURE  	29 0	; 0x7fa6fec070d0
	83	[32]	SETTABLE 	28 -33 29	; "toggle_global_default_callback" -
	84	[33]	SETTABLE 	28 -34 -35	; "modal" true
	85	[34]	SELF     	29 24 -37	; "getWidth"
	86	[34]	CALL     	29 2 2
	87	[34]	MUL      	29 29 -38	; - 3
	88	[34]	DIV      	29 29 -39	; - 4
	89	[34]	SETTABLE 	28 -36 29	; "width" -
	90	[29]	CALL     	26 3 2
	91	[167]	CLOSURE  	27 1	; 0x7fa6fec07330
	92	[167]	MOVE     	0 6
	93	[167]	MOVE     	0 11
	94	[167]	MOVE     	0 10
	95	[167]	MOVE     	0 24
	96	[167]	MOVE     	0 18
	97	[167]	MOVE     	0 16
	98	[167]	MOVE     	0 8
	99	[167]	MOVE     	0 19
	100	[167]	MOVE     	0 15
	101	[167]	MOVE     	0 9
	102	[167]	MOVE     	0 23
	103	[167]	MOVE     	0 17
	104	[167]	MOVE     	0 2
	105	[167]	MOVE     	0 14
	106	[167]	MOVE     	0 1
	107	[167]	MOVE     	0 3
	108	[37]	SETTABLE 	26 -40 27	; "init" -
	109	[173]	CLOSURE  	27 2	; 0x7fa6fec08a60
	110	[173]	MOVE     	0 17
	111	[169]	SETTABLE 	26 -41 27	; "onShow" -
	112	[179]	CLOSURE  	27 3	; 0x7fa6fec090b0
	113	[179]	MOVE     	0 17
	114	[175]	SETTABLE 	26 -42 27	; "onCloseWidget" -
	115	[184]	CLOSURE  	27 4	; 0x7fa6fec093e0
	116	[184]	MOVE     	0 17
	117	[181]	SETTABLE 	26 -43 27	; "onClose" -
	118	[192]	CLOSURE  	27 5	; 0x7fa6fec098c0
	119	[186]	SETTABLE 	26 -44 27	; "onTapClose" -
	120	[200]	CLOSURE  	27 6	; 0x7fa6fec09ab0
	121	[200]	MOVE     	0 17
	122	[194]	SETTABLE 	26 -45 27	; "onSelect" -
	123	[212]	CLOSURE  	27 7	; 0x7fa6fec09fe0
	124	[216]	SELF     	28 13 -29	; "new"
	125	[216]	NEWTABLE 	30 0 5
	126	[217]	SETTABLE 	30 -46 -31	; "tweaks_by_id" nil
	127	[218]	SETTABLE 	30 -47 -31	; "tweaks_table" nil
	128	[219]	SETTABLE 	30 -48 -49	; "nb_enabled_tweaks" 0
	129	[220]	SETTABLE 	30 -50 -31	; "css_text" nil
	130	[221]	SETTABLE 	30 -51 -35	; "enabled" true
	131	[216]	CALL     	28 3 2
	132	[237]	CLOSURE  	29 8	; 0x7fa6fec07650
	133	[224]	SETTABLE 	28 -52 29	; "isTweakEnabled" -
	134	[255]	CLOSURE  	29 9	; 0x7fa6fec0a8e0
	135	[239]	SETTABLE 	28 -53 29	; "nbTweaksEnabled" -
	136	[260]	CLOSURE  	29 10	; 0x7fa6fec09270
	137	[258]	SETTABLE 	28 -54 29	; "getCssText" -
	138	[310]	CLOSURE  	29 11	; 0x7fa6fec08750
	139	[310]	MOVE     	0 27
	140	[310]	MOVE     	0 21
	141	[310]	MOVE     	0 7
	142	[263]	SETTABLE 	28 -55 29	; "updateCssText" -
	143	[319]	CLOSURE  	29 12	; 0x7fa6fec0a760
	144	[319]	MOVE     	0 4
	145	[312]	SETTABLE 	28 -56 29	; "onReadSettings" -
	146	[329]	CLOSURE  	29 13	; 0x7fa6fec086d0
	147	[329]	MOVE     	0 22
	148	[321]	SETTABLE 	28 -57 29	; "onSaveSettings" -
	149	[521]	CLOSURE  	29 14	; 0x7fa6fec0af50
	150	[521]	MOVE     	0 23
	151	[521]	MOVE     	0 17
	152	[521]	MOVE     	0 12
	153	[521]	MOVE     	0 26
	154	[521]	MOVE     	0 4
	155	[521]	MOVE     	0 5
	156	[521]	MOVE     	0 20
	157	[521]	MOVE     	0 25
	158	[521]	MOVE     	0 0
	159	[331]	SETTABLE 	28 -40 29	; "init" -
	160	[535]	CLOSURE  	29 15	; 0x7fa6fec0de40
	161	[535]	MOVE     	0 25
	162	[535]	MOVE     	0 23
	163	[523]	SETTABLE 	28 -58 29	; "addToMainMenu" -
	164	[537]	RETURN   	28 2
	165	[537]	RETURN   	0 1

function <./frontend/apps/reader/modules/readerstyletweak.lua:32,32> (1 instruction, 4 bytes at 0x7fa6fec070d0)
0 params, 2 slots, 0 upvalues, 0 locals, 0 constants, 0 functions
	1	[32]	RETURN   	0 1

function <./frontend/apps/reader/modules/readerstyletweak.lua:37,167> (309 instructions, 1236 bytes at 0x7fa6fec07330)
1 param, 17 slots, 16 upvalues, 7 locals, 81 constants, 2 functions
	1	[38]	GETTABLE 	1 0 -1	; "tweak"
	2	[39]	GETUPVAL 	2 0	; Device
	3	[39]	SELF     	2 2 -2	; "isTouchDevice"
	4	[39]	CALL     	2 2 2
	5	[39]	TEST     	2 0 0
	6	[39]	JMP      	24	; to 31
	7	[40]	GETTABLE 	2 0 -3	; "ges_events"
	8	[40]	NEWTABLE 	3 0 0
	9	[41]	GETUPVAL 	4 1	; GestureRange
	10	[41]	SELF     	4 4 -5	; "new"
	11	[41]	NEWTABLE 	6 0 2
	12	[42]	SETTABLE 	6 -6 -7	; "ges" "tap"
	13	[43]	GETUPVAL 	7 2	; Geom
	14	[43]	SELF     	7 7 -5	; "new"
	15	[43]	NEWTABLE 	9 0 4
	16	[44]	SETTABLE 	9 -9 -10	; "x" 0
	17	[44]	SETTABLE 	9 -11 -10	; "y" 0
	18	[45]	GETUPVAL 	10 3	; Screen
	19	[45]	SELF     	10 10 -13	; "getWidth"
	20	[45]	CALL     	10 2 2
	21	[45]	SETTABLE 	9 -12 10	; "w" -
	22	[46]	GETUPVAL 	10 3	; Screen
	23	[46]	SELF     	10 10 -15	; "getHeight"
	24	[46]	CALL     	10 2 2
	25	[46]	SETTABLE 	9 -14 10	; "h" -
	26	[43]	CALL     	7 3 2
	27	[47]	SETTABLE 	6 -8 7	; "range" -
	28	[41]	CALL     	4 3 0
	29	[49]	SETLIST  	3 0 1	; 1
	30	[49]	SETTABLE 	2 -4 3	; "TapClose" -
	31	[51]	GETUPVAL 	2 0	; Device
	32	[51]	SELF     	2 2 -16	; "hasKeys"
	33	[51]	CALL     	2 2 2
	34	[51]	TEST     	2 0 0
	35	[51]	JMP      	9	; to 45
	36	[52]	NEWTABLE 	2 0 1
	37	[53]	NEWTABLE 	3 1 1
	38	[53]	NEWTABLE 	4 1 0
	39	[53]	LOADK    	5 -19	; "Back"
	40	[53]	SETLIST  	4 1 1	; 1
	41	[53]	SETTABLE 	3 -20 -21	; "doc" "cancel"
	42	[53]	SETLIST  	3 1 1	; 1
	43	[53]	SETTABLE 	2 -18 3	; "Close" -
	44	[54]	SETTABLE 	0 -17 2	; "key_events" -
	45	[57]	GETUPVAL 	2 4	; VerticalGroup
	46	[57]	SELF     	2 2 -5	; "new"
	47	[57]	NEWTABLE 	4 1 0
	48	[58]	GETUPVAL 	5 5	; TextBoxWidget
	49	[58]	SELF     	5 5 -5	; "new"
	50	[58]	NEWTABLE 	7 0 4
	51	[59]	GETTABLE 	8 1 -23	; "title"
	52	[59]	SETTABLE 	7 -22 8	; "text" -
	53	[60]	SETTABLE 	7 -24 -25	; "bold" true
	54	[61]	GETUPVAL 	8 6	; Font
	55	[61]	SELF     	8 8 -27	; "getFace"
	56	[61]	LOADK    	10 -28	; "infofont"
	57	[61]	CALL     	8 3 2
	58	[61]	SETTABLE 	7 -26 8	; "face" -
	59	[62]	GETTABLE 	8 0 -29	; "width"
	60	[62]	SETTABLE 	7 -29 8	; "width" -
	61	[58]	CALL     	5 3 2
	62	[64]	GETUPVAL 	6 7	; VerticalSpan
	63	[64]	SELF     	6 6 -5	; "new"
	64	[64]	NEWTABLE 	8 0 1
	65	[65]	GETUPVAL 	9 8	; Size
	66	[65]	GETTABLE 	9 9 -30	; "padding"
	67	[65]	GETTABLE 	9 9 -31	; "large"
	68	[65]	SETTABLE 	8 -29 9	; "width" -
	69	[64]	CALL     	6 3 0
	70	[67]	SETLIST  	4 0 1	; 1
	71	[57]	CALL     	2 3 2
	72	[68]	GETTABLE 	3 1 -32	; "description"
	73	[68]	TEST     	3 0 0
	74	[68]	JMP      	29	; to 104
	75	[69]	GETGLOBAL	3 -33	; table
	76	[69]	GETTABLE 	3 3 -34	; "insert"
	77	[69]	MOVE     	4 2
	78	[70]	GETUPVAL 	5 5	; TextBoxWidget
	79	[70]	SELF     	5 5 -5	; "new"
	80	[70]	NEWTABLE 	7 0 3
	81	[71]	GETTABLE 	8 1 -32	; "description"
	82	[71]	SETTABLE 	7 -22 8	; "text" -
	83	[72]	GETUPVAL 	8 6	; Font
	84	[72]	SELF     	8 8 -27	; "getFace"
	85	[72]	LOADK    	10 -35	; "smallinfofont"
	86	[72]	CALL     	8 3 2
	87	[72]	SETTABLE 	7 -26 8	; "face" -
	88	[73]	GETTABLE 	8 0 -29	; "width"
	89	[73]	SETTABLE 	7 -29 8	; "width" -
	90	[70]	CALL     	5 3 0
	91	[69]	CALL     	3 0 1
	92	[76]	GETGLOBAL	3 -33	; table
	93	[76]	GETTABLE 	3 3 -34	; "insert"
	94	[76]	MOVE     	4 2
	95	[76]	GETUPVAL 	5 7	; VerticalSpan
	96	[76]	SELF     	5 5 -5	; "new"
	97	[76]	NEWTABLE 	7 0 1
	98	[77]	GETUPVAL 	8 8	; Size
	99	[77]	GETTABLE 	8 8 -30	; "padding"
	100	[77]	GETTABLE 	8 8 -31	; "large"
	101	[77]	SETTABLE 	7 -29 8	; "width" -
	102	[76]	CALL     	5 3 0
	103	[76]	CALL     	3 0 1
	104	[84]	GETTABLE 	3 1 -36	; "css"
	105	[85]	TEST     	3 0 1
	106	[85]	JMP      	17	; to 124
	107	[85]	GETTABLE 	4 1 -37	; "css_path"
	108	[85]	TEST     	4 0 0
	109	[85]	JMP      	14	; to 124
	110	[86]	LOADK    	3 -38	; ""
	111	[87]	GETGLOBAL	4 -39	; io
	112	[87]	GETTABLE 	4 4 -40	; "open"
	113	[87]	GETTABLE 	5 1 -37	; "css_path"
	114	[87]	LOADK    	6 -41	; "r"
	115	[87]	CALL     	4 3 2
	116	[88]	TEST     	4 0 0
	117	[88]	JMP      	6	; to 124
	118	[89]	SELF     	5 4 -42	; "read"
	119	[89]	LOADK    	7 -43	; "*all"
	120	[89]	CALL     	5 3 2
	121	[89]	MOVE     	3 5
	122	[90]	SELF     	5 4 -44	; "close"
	123	[90]	CALL     	5 2 1
	124	[93]	SELF     	4 3 -45	; "gsub"
	125	[93]	LOADK    	6 -46	; "^%s+"
	126	[93]	LOADK    	7 -38	; ""
	127	[93]	CALL     	4 4 2
	128	[93]	SELF     	4 4 -45	; "gsub"
	129	[93]	LOADK    	6 -47	; "%s+$"
	130	[93]	LOADK    	7 -38	; ""
	131	[93]	CALL     	4 4 2
	132	[93]	MOVE     	3 4
	133	[94]	GETGLOBAL	4 -33	; table
	134	[94]	GETTABLE 	4 4 -34	; "insert"
	135	[94]	MOVE     	5 2
	136	[94]	GETUPVAL 	6 9	; FrameContainer
	137	[94]	SELF     	6 6 -5	; "new"
	138	[94]	NEWTABLE 	8 0 2
	139	[95]	GETUPVAL 	9 8	; Size
	140	[95]	GETTABLE 	9 9 -49	; "border"
	141	[95]	GETTABLE 	9 9 -50	; "thin"
	142	[95]	SETTABLE 	8 -48 9	; "bordersize" -
	143	[96]	GETUPVAL 	9 8	; Size
	144	[96]	GETTABLE 	9 9 -30	; "padding"
	145	[96]	GETTABLE 	9 9 -31	; "large"
	146	[96]	SETTABLE 	8 -30 9	; "padding" -
	147	[97]	GETUPVAL 	9 5	; TextBoxWidget
	148	[97]	SELF     	9 9 -5	; "new"
	149	[97]	NEWTABLE 	11 0 4
	150	[98]	SETTABLE 	11 -22 3	; "text" -
	151	[99]	GETUPVAL 	12 6	; Font
	152	[99]	SELF     	12 12 -27	; "getFace"
	153	[99]	LOADK    	14 -51	; "infont"
	154	[99]	LOADK    	15 -52	; 16
	155	[99]	CALL     	12 4 2
	156	[99]	SETTABLE 	11 -26 12	; "face" -
	157	[100]	GETTABLE 	12 0 -29	; "width"
	158	[100]	GETUPVAL 	13 8	; Size
	159	[100]	GETTABLE 	13 13 -30	; "padding"
	160	[100]	GETTABLE 	13 13 -31	; "large"
	161	[100]	MUL      	13 -53 13	; 2 -
	162	[100]	SUB      	12 12 13
	163	[100]	SETTABLE 	11 -29 12	; "width" -
	164	[101]	SETTABLE 	11 -54 -55	; "para_direction_rtl" false
	165	[97]	CALL     	9 3 0
	166	[103]	SETLIST  	8 0 1	; 1
	167	[94]	CALL     	6 3 0
	168	[94]	CALL     	4 0 1
	169	[104]	GETTABLE 	4 0 -56	; "is_global_default"
	170	[104]	TEST     	4 0 0
	171	[104]	JMP      	31	; to 203
	172	[105]	GETGLOBAL	4 -33	; table
	173	[105]	GETTABLE 	4 4 -34	; "insert"
	174	[105]	MOVE     	5 2
	175	[105]	GETUPVAL 	6 7	; VerticalSpan
	176	[105]	SELF     	6 6 -5	; "new"
	177	[105]	NEWTABLE 	8 0 1
	178	[106]	GETUPVAL 	9 8	; Size
	179	[106]	GETTABLE 	9 9 -30	; "padding"
	180	[106]	GETTABLE 	9 9 -31	; "large"
	181	[106]	SETTABLE 	8 -29 9	; "width" -
	182	[105]	CALL     	6 3 0
	183	[105]	CALL     	4 0 1
	184	[108]	GETGLOBAL	4 -33	; table
	185	[108]	GETTABLE 	4 4 -34	; "insert"
	186	[108]	MOVE     	5 2
	187	[109]	GETUPVAL 	6 5	; TextBoxWidget
	188	[109]	SELF     	6 6 -5	; "new"
	189	[109]	NEWTABLE 	8 0 3
	190	[110]	GETUPVAL 	9 10	; _
	191	[110]	LOADK    	10 -57	; "This tweak is applied on all books."
	192	[110]	CALL     	9 2 2
	193	[110]	SETTABLE 	8 -22 9	; "text" -
	194	[111]	GETUPVAL 	9 6	; Font
	195	[111]	SELF     	9 9 -27	; "getFace"
	196	[111]	LOADK    	11 -35	; "smallinfofont"
	197	[111]	CALL     	9 3 2
	198	[111]	SETTABLE 	8 -26 9	; "face" -
	199	[112]	GETTABLE 	9 0 -29	; "width"
	200	[112]	SETTABLE 	8 -29 9	; "width" -
	201	[109]	CALL     	6 3 0
	202	[108]	CALL     	4 0 1
	203	[117]	GETUPVAL 	4 9	; FrameContainer
	204	[117]	SELF     	4 4 -5	; "new"
	205	[117]	NEWTABLE 	6 1 3
	206	[118]	SETTABLE 	6 -48 -10	; "bordersize" 0
	207	[119]	GETUPVAL 	7 8	; Size
	208	[119]	GETTABLE 	7 7 -30	; "padding"
	209	[119]	GETTABLE 	7 7 -31	; "large"
	210	[119]	SETTABLE 	6 -30 7	; "padding" -
	211	[120]	GETUPVAL 	7 8	; Size
	212	[120]	GETTABLE 	7 7 -30	; "padding"
	213	[120]	GETTABLE 	7 7 -59	; "default"
	214	[120]	SETTABLE 	6 -58 7	; "padding_top" -
	215	[122]	MOVE     	7 2
	216	[122]	SETLIST  	6 1 1	; 1
	217	[117]	CALL     	4 3 2
	218	[122]	MOVE     	2 4
	219	[124]	NEWTABLE 	4 2 0
	220	[124]	NEWTABLE 	5 0 2
	221	[126]	GETUPVAL 	6 10	; _
	222	[126]	LOADK    	7 -18	; "Close"
	223	[126]	CALL     	6 2 2
	224	[126]	SETTABLE 	5 -22 6	; "text" -
	225	[129]	CLOSURE  	6 0	; 0x7fa6fec08220
	226	[129]	GETUPVAL 	0 11	; UIManager
	227	[129]	MOVE     	0 0
	228	[129]	SETTABLE 	5 -60 6	; "callback" -
	229	[130]	NEWTABLE 	6 0 2
	230	[132]	GETTABLE 	7 0 -56	; "is_global_default"
	231	[132]	TEST     	7 0 0
	232	[132]	JMP      	5	; to 238
	233	[132]	GETUPVAL 	7 10	; _
	234	[132]	LOADK    	8 -61	; "Don't use on all books"
	235	[132]	CALL     	7 2 2
	236	[132]	TEST     	7 0 1
	237	[132]	JMP      	3	; to 241
	238	[132]	GETUPVAL 	7 10	; _
	239	[132]	LOADK    	8 -62	; "Use on all books"
	240	[132]	CALL     	7 2 2
	241	[132]	SETTABLE 	6 -22 7	; "text" -
	242	[136]	CLOSURE  	7 1	; 0x7fa6fec08490
	243	[136]	MOVE     	0 0
	244	[136]	GETUPVAL 	0 11	; UIManager
	245	[136]	SETTABLE 	6 -60 7	; "callback" -
	246	[138]	SETLIST  	4 2 1	; 1
	247	[140]	GETUPVAL 	5 12	; ButtonTable
	248	[140]	SELF     	5 5 -5	; "new"
	249	[140]	NEWTABLE 	7 0 6
	250	[141]	SELF     	8 2 -63	; "getSize"
	251	[141]	CALL     	8 2 2
	252	[141]	GETTABLE 	8 8 -12	; "w"
	253	[141]	SETTABLE 	7 -29 8	; "width" -
	254	[142]	SETTABLE 	7 -64 -65	; "button_font_face" "cfont"
	255	[143]	SETTABLE 	7 -66 -67	; "button_font_size" 20
	256	[144]	NEWTABLE 	8 1 0
	257	[144]	MOVE     	9 4
	258	[144]	SETLIST  	8 1 1	; 1
	259	[144]	SETTABLE 	7 -68 8	; "buttons" -
	260	[145]	SETTABLE 	7 -69 -25	; "zero_sep" true
	261	[146]	SETTABLE 	7 -70 0	; "show_parent" -
	262	[140]	CALL     	5 3 2
	263	[149]	GETUPVAL 	6 13	; MovableContainer
	264	[149]	SELF     	6 6 -5	; "new"
	265	[149]	NEWTABLE 	8 0 0
	266	[150]	GETUPVAL 	9 9	; FrameContainer
	267	[150]	SELF     	9 9 -5	; "new"
	268	[150]	NEWTABLE 	11 0 5
	269	[151]	GETUPVAL 	12 14	; Blitbuffer
	270	[151]	GETTABLE 	12 12 -73	; "COLOR_WHITE"
	271	[151]	SETTABLE 	11 -72 12	; "background" -
	272	[152]	GETUPVAL 	12 8	; Size
	273	[152]	GETTABLE 	12 12 -74	; "radius"
	274	[152]	GETTABLE 	12 12 -75	; "window"
	275	[152]	SETTABLE 	11 -74 12	; "radius" -
	276	[153]	GETUPVAL 	12 8	; Size
	277	[153]	GETTABLE 	12 12 -76	; "margin"
	278	[153]	GETTABLE 	12 12 -59	; "default"
	279	[153]	SETTABLE 	11 -76 12	; "margin" -
	280	[154]	GETUPVAL 	12 8	; Size
	281	[154]	GETTABLE 	12 12 -30	; "padding"
	282	[154]	GETTABLE 	12 12 -59	; "default"
	283	[154]	SETTABLE 	11 -30 12	; "padding" -
	284	[155]	SETTABLE 	11 -77 -10	; "padding_bottom" 0
	285	[156]	GETUPVAL 	12 4	; VerticalGroup
	286	[156]	SELF     	12 12 -5	; "new"
	287	[156]	NEWTABLE 	14 2 1
	288	[157]	SETTABLE 	14 -78 -79	; "align" "left"
	289	[158]	MOVE     	15 2
	290	[160]	MOVE     	16 5
	291	[160]	SETLIST  	14 2 1	; 1
	292	[156]	CALL     	12 3 0
	293	[161]	SETLIST  	11 0 1	; 1
	294	[150]	CALL     	9 3 0
	295	[162]	SETLIST  	8 0 1	; 1
	296	[149]	CALL     	6 3 2
	297	[162]	SETTABLE 	0 -71 6	; "movable" -
	298	[163]	GETUPVAL 	6 15	; CenterContainer
	299	[163]	SELF     	6 6 -5	; "new"
	300	[163]	NEWTABLE 	8 1 1
	301	[164]	GETUPVAL 	9 3	; Screen
	302	[164]	SELF     	9 9 -63	; "getSize"
	303	[164]	CALL     	9 2 2
	304	[164]	SETTABLE 	8 -81 9	; "dimen" -
	305	[166]	GETTABLE 	9 0 -71	; "movable"
	306	[166]	SETLIST  	8 1 1	; 1
	307	[163]	CALL     	6 3 2
	308	[166]	SETTABLE 	0 -80 6	; 1 -
	309	[167]	RETURN   	0 1

function <./frontend/apps/reader/modules/readerstyletweak.lua:127,129> (5 instructions, 20 bytes at 0x7fa6fec08220)
0 params, 3 slots, 2 upvalues, 0 locals, 1 constant, 0 functions
	1	[128]	GETUPVAL 	0 0	; UIManager
	2	[128]	SELF     	0 0 -1	; "close"
	3	[128]	GETUPVAL 	2 1	; self
	4	[128]	CALL     	0 3 1
	5	[129]	RETURN   	0 1

function <./frontend/apps/reader/modules/readerstyletweak.lua:133,136> (8 instructions, 32 bytes at 0x7fa6fec08490)
0 params, 3 slots, 2 upvalues, 0 locals, 2 constants, 0 functions
	1	[134]	GETUPVAL 	0 0	; self
	2	[134]	GETTABLE 	0 0 -1	; "toggle_global_default_callback"
	3	[134]	CALL     	0 1 1
	4	[135]	GETUPVAL 	0 1	; UIManager
	5	[135]	SELF     	0 0 -2	; "close"
	6	[135]	GETUPVAL 	2 0	; self
	7	[135]	CALL     	0 3 1
	8	[136]	RETURN   	0 1

function <./frontend/apps/reader/modules/readerstyletweak.lua:169,173> (7 instructions, 28 bytes at 0x7fa6fec08a60)
1 param, 5 slots, 1 upvalue, 1 local, 1 constant, 1 function
	1	[170]	GETUPVAL 	1 0	; UIManager
	2	[170]	SELF     	1 1 -1	; "setDirty"
	3	[170]	MOVE     	3 0
	4	[172]	CLOSURE  	4 0	; 0x7fa6fec08c80
	5	[172]	MOVE     	0 0
	6	[170]	CALL     	1 4 1
	7	[173]	RETURN   	0 1

function <./frontend/apps/reader/modules/readerstyletweak.lua:170,172> (6 instructions, 24 bytes at 0x7fa6fec08c80)
0 params, 2 slots, 1 upvalue, 0 locals, 3 constants, 0 functions
	1	[171]	LOADK    	0 -1	; "ui"
	2	[171]	GETUPVAL 	1 0	; self
	3	[171]	GETTABLE 	1 1 -2	; "movable"
	4	[171]	GETTABLE 	1 1 -3	; "dimen"
	5	[171]	RETURN   	0 3
	6	[172]	RETURN   	0 1

function <./frontend/apps/reader/modules/readerstyletweak.lua:175,179> (7 instructions, 28 bytes at 0x7fa6fec090b0)
1 param, 5 slots, 1 upvalue, 1 local, 1 constant, 1 function
	1	[176]	GETUPVAL 	1 0	; UIManager
	2	[176]	SELF     	1 1 -1	; "setDirty"
	3	[176]	LOADNIL  	3 3
	4	[178]	CLOSURE  	4 0	; 0x7fa6fec09340
	5	[178]	MOVE     	0 0
	6	[176]	CALL     	1 4 1
	7	[179]	RETURN   	0 1

function <./frontend/apps/reader/modules/readerstyletweak.lua:176,178> (6 instructions, 24 bytes at 0x7fa6fec09340)
0 params, 2 slots, 1 upvalue, 0 locals, 3 constants, 0 functions
	1	[177]	LOADK    	0 -1	; "ui"
	2	[177]	GETUPVAL 	1 0	; self
	3	[177]	GETTABLE 	1 1 -2	; "movable"
	4	[177]	GETTABLE 	1 1 -3	; "dimen"
	5	[177]	RETURN   	0 3
	6	[178]	RETURN   	0 1

function <./frontend/apps/reader/modules/readerstyletweak.lua:181,184> (7 instructions, 28 bytes at 0x7fa6fec093e0)
1 param, 4 slots, 1 upvalue, 1 local, 1 constant, 0 functions
	1	[182]	GETUPVAL 	1 0	; UIManager
	2	[182]	SELF     	1 1 -1	; "close"
	3	[182]	MOVE     	3 0
	4	[182]	CALL     	1 3 1
	5	[183]	LOADBOOL 	1 1 0
	6	[183]	RETURN   	1 2
	7	[184]	RETURN   	0 1

function <./frontend/apps/reader/modules/readerstyletweak.lua:186,192> (14 instructions, 56 bytes at 0x7fa6fec098c0)
3 params, 6 slots, 0 upvalues, 3 locals, 5 constants, 0 functions
	1	[187]	GETTABLE 	3 2 -1	; "pos"
	2	[187]	SELF     	3 3 -2	; "notIntersectWith"
	3	[187]	GETTABLE 	5 0 -3	; "movable"
	4	[187]	GETTABLE 	5 5 -4	; "dimen"
	5	[187]	CALL     	3 3 2
	6	[187]	TEST     	3 0 0
	7	[187]	JMP      	4	; to 12
	8	[188]	SELF     	3 0 -5	; "onClose"
	9	[188]	CALL     	3 2 1
	10	[189]	LOADBOOL 	3 1 0
	11	[189]	RETURN   	3 2
	12	[191]	LOADBOOL 	3 0 0
	13	[191]	RETURN   	3 2
	14	[192]	RETURN   	0 1

function <./frontend/apps/reader/modules/readerstyletweak.lua:194,200> (13 instructions, 52 bytes at 0x7fa6fec09ab0)
1 param, 4 slots, 1 upvalue, 1 local, 5 constants, 0 functions
	1	[195]	GETTABLE 	1 0 -1	; "selected"
	2	[195]	GETTABLE 	1 1 -2	; "x"
	3	[195]	EQ       	0 1 -3	; - 1
	4	[195]	JMP      	2	; to 7
	5	[196]	SELF     	1 0 -4	; "toggle_global_default_callback"
	6	[196]	CALL     	1 2 1
	7	[198]	GETUPVAL 	1 0	; UIManager
	8	[198]	SELF     	1 1 -5	; "close"
	9	[198]	MOVE     	3 0
	10	[198]	CALL     	1 3 1
	11	[199]	LOADBOOL 	1 1 0
	12	[199]	RETURN   	1 2
	13	[200]	RETURN   	0 1

function <./frontend/apps/reader/modules/readerstyletweak.lua:205,212> (19 instructions, 76 bytes at 0x7fa6fec09fe0)
2 params, 4 slots, 0 upvalues, 2 locals, 2 constants, 0 functions
	1	[206]	GETTABLE 	2 0 -1	; "priority"
	2	[206]	GETTABLE 	3 1 -1	; "priority"
	3	[206]	EQ       	1 2 3
	4	[206]	JMP      	7	; to 12
	5	[208]	GETTABLE 	2 0 -1	; "priority"
	6	[208]	GETTABLE 	3 1 -1	; "priority"
	7	[208]	LT       	1 2 3
	8	[208]	JMP      	1	; to 10
	9	[208]	LOADBOOL 	2 0 1
	10	[208]	LOADBOOL 	2 1 0
	11	[208]	RETURN   	2 2
	12	[211]	GETTABLE 	2 0 -2	; "id"
	13	[211]	GETTABLE 	3 1 -2	; "id"
	14	[211]	LT       	1 2 3
	15	[211]	JMP      	1	; to 17
	16	[211]	LOADBOOL 	2 0 1
	17	[211]	LOADBOOL 	2 1 0
	18	[211]	RETURN   	2 2
	19	[212]	RETURN   	0 1

function <./frontend/apps/reader/modules/readerstyletweak.lua:224,237> (23 instructions, 92 bytes at 0x7fa6fec07650)
2 params, 6 slots, 0 upvalues, 4 locals, 4 constants, 0 functions
	1	[225]	LOADBOOL 	2 0 0
	2	[226]	LOADBOOL 	3 0 0
	3	[227]	GETTABLE 	4 0 -1	; "global_tweaks"
	4	[227]	GETTABLE 	4 4 1
	5	[227]	TEST     	4 0 0
	6	[227]	JMP      	2	; to 9
	7	[228]	LOADBOOL 	3 1 0
	8	[229]	LOADBOOL 	2 1 0
	9	[231]	GETTABLE 	4 0 -2	; "doc_tweaks"
	10	[231]	GETTABLE 	4 4 1
	11	[231]	EQ       	0 4 -3	; - true
	12	[231]	JMP      	2	; to 15
	13	[232]	LOADBOOL 	3 1 0
	14	[232]	JMP      	5	; to 20
	15	[233]	GETTABLE 	4 0 -2	; "doc_tweaks"
	16	[233]	GETTABLE 	4 4 1
	17	[233]	EQ       	0 4 -4	; - false
	18	[233]	JMP      	1	; to 20
	19	[234]	LOADBOOL 	3 0 0
	20	[236]	MOVE     	4 3
	21	[236]	MOVE     	5 2
	22	[236]	RETURN   	4 3
	23	[237]	RETURN   	0 1

function <./frontend/apps/reader/modules/readerstyletweak.lua:239,255> (31 instructions, 124 bytes at 0x7fa6fec0a8e0)
2 params, 12 slots, 0 upvalues, 11 locals, 7 constants, 0 functions
	1	[240]	LOADK    	2 -1	; 0
	2	[241]	LOADK    	3 -1	; 0
	3	[242]	GETGLOBAL	4 -2	; ipairs
	4	[242]	MOVE     	5 1
	5	[242]	CALL     	4 2 4
	6	[242]	JMP      	19	; to 26
	7	[243]	GETTABLE 	9 8 -3	; "sub_item_table"
	8	[243]	TEST     	9 0 0
	9	[243]	JMP      	6	; to 16
	10	[244]	SELF     	9 0 -4	; "nbTweaksEnabled"
	11	[244]	GETTABLE 	11 8 -3	; "sub_item_table"
	12	[244]	CALL     	9 3 3
	13	[245]	ADD      	2 2 9
	14	[246]	ADD      	3 3 10
	15	[246]	JMP      	10	; to 26
	16	[247]	GETTABLE 	9 8 -5	; "tweak_id"
	17	[247]	TEST     	9 0 0
	18	[247]	JMP      	7	; to 26
	19	[248]	SELF     	9 0 -6	; "isTweakEnabled"
	20	[248]	GETTABLE 	11 8 -5	; "tweak_id"
	21	[248]	CALL     	9 3 2
	22	[248]	TEST     	9 0 0
	23	[248]	JMP      	1	; to 25
	24	[249]	ADD      	2 2 -7	; - 1
	25	[251]	ADD      	3 3 -7	; - 1
	26	[242]	TFORLOOP 	4 2
	27	[252]	JMP      	-21	; to 7
	28	[254]	MOVE     	4 2
	29	[254]	MOVE     	5 3
	30	[254]	RETURN   	4 3
	31	[255]	RETURN   	0 1

function <./frontend/apps/reader/modules/readerstyletweak.lua:258,260> (3 instructions, 12 bytes at 0x7fa6fec09270)
1 param, 2 slots, 0 upvalues, 1 local, 1 constant, 0 functions
	1	[259]	GETTABLE 	1 0 -1	; "css_text"
	2	[259]	RETURN   	1 2
	3	[260]	RETURN   	0 1

function <./frontend/apps/reader/modules/readerstyletweak.lua:263,310> (115 instructions, 460 bytes at 0x7fa6fec08750)
2 params, 14 slots, 3 upvalues, 21 locals, 37 constants, 0 functions
	1	[264]	GETTABLE 	2 0 -1	; "enabled"
	2	[264]	TEST     	2 0 0
	3	[264]	JMP      	97	; to 101
	4	[265]	NEWTABLE 	2 0 0
	5	[266]	GETGLOBAL	3 -2	; pairs
	6	[266]	GETTABLE 	4 0 -3	; "global_tweaks"
	7	[266]	CALL     	3 2 4
	8	[266]	JMP      	10	; to 19
	9	[271]	GETTABLE 	8 0 -4	; "doc_tweaks"
	10	[271]	GETTABLE 	8 8 6
	11	[271]	EQ       	0 8 -5	; - nil
	12	[271]	JMP      	6	; to 19
	13	[272]	GETGLOBAL	8 -6	; table
	14	[272]	GETTABLE 	8 8 -7	; "insert"
	15	[272]	MOVE     	9 2
	16	[272]	GETTABLE 	10 0 -8	; "tweaks_by_id"
	17	[272]	GETTABLE 	10 10 6
	18	[272]	CALL     	8 3 1
	19	[266]	TFORLOOP 	3 2
	20	[273]	JMP      	-12	; to 9
	21	[275]	GETGLOBAL	3 -2	; pairs
	22	[275]	GETTABLE 	4 0 -4	; "doc_tweaks"
	23	[275]	CALL     	3 2 4
	24	[275]	JMP      	10	; to 35
	25	[277]	GETTABLE 	8 0 -4	; "doc_tweaks"
	26	[277]	GETTABLE 	8 8 6
	27	[277]	EQ       	0 8 -9	; - true
	28	[277]	JMP      	6	; to 35
	29	[278]	GETGLOBAL	8 -6	; table
	30	[278]	GETTABLE 	8 8 -7	; "insert"
	31	[278]	MOVE     	9 2
	32	[278]	GETTABLE 	10 0 -8	; "tweaks_by_id"
	33	[278]	GETTABLE 	10 10 6
	34	[278]	CALL     	8 3 1
	35	[275]	TFORLOOP 	3 2
	36	[279]	JMP      	-12	; to 25
	37	[281]	GETGLOBAL	3 -6	; table
	38	[281]	GETTABLE 	3 3 -10	; "sort"
	39	[281]	MOVE     	4 2
	40	[281]	GETUPVAL 	5 0	; tweakOrdering
	41	[281]	CALL     	3 3 1
	42	[282]	SETTABLE 	0 -11 -12	; "nb_enabled_tweaks" 0
	43	[283]	NEWTABLE 	3 0 0
	44	[284]	GETGLOBAL	4 -13	; ipairs
	45	[284]	MOVE     	5 2
	46	[284]	CALL     	4 2 4
	47	[284]	JMP      	37	; to 85
	48	[285]	GETTABLE 	9 0 -11	; "nb_enabled_tweaks"
	49	[285]	ADD      	9 9 -14	; - 1
	50	[285]	SETTABLE 	0 -11 9	; "nb_enabled_tweaks" -
	51	[286]	GETTABLE 	9 8 -15	; "css"
	52	[287]	TEST     	9 0 1
	53	[287]	JMP      	17	; to 71
	54	[287]	GETTABLE 	10 8 -16	; "css_path"
	55	[287]	TEST     	10 0 0
	56	[287]	JMP      	14	; to 71
	57	[288]	LOADK    	9 -17	; ""
	58	[289]	GETGLOBAL	10 -18	; io
	59	[289]	GETTABLE 	10 10 -19	; "open"
	60	[289]	GETTABLE 	11 8 -16	; "css_path"
	61	[289]	LOADK    	12 -20	; "r"
	62	[289]	CALL     	10 3 2
	63	[290]	TEST     	10 0 0
	64	[290]	JMP      	6	; to 71
	65	[291]	SELF     	11 10 -21	; "read"
	66	[291]	LOADK    	13 -22	; "*all"
	67	[291]	CALL     	11 3 2
	68	[291]	MOVE     	9 11
	69	[292]	SELF     	11 10 -23	; "close"
	70	[292]	CALL     	11 2 1
	71	[298]	SELF     	10 9 -24	; "gsub"
	72	[298]	LOADK    	12 -25	; "^%s+"
	73	[298]	LOADK    	13 -17	; ""
	74	[298]	CALL     	10 4 2
	75	[298]	SELF     	10 10 -24	; "gsub"
	76	[298]	LOADK    	12 -26	; "%s+$"
	77	[298]	LOADK    	13 -17	; ""
	78	[298]	CALL     	10 4 2
	79	[298]	MOVE     	9 10
	80	[299]	GETGLOBAL	10 -6	; table
	81	[299]	GETTABLE 	10 10 -7	; "insert"
	82	[299]	MOVE     	11 3
	83	[299]	MOVE     	12 9
	84	[299]	CALL     	10 3 1
	85	[284]	TFORLOOP 	4 2
	86	[299]	JMP      	-39	; to 48
	87	[301]	GETGLOBAL	4 -6	; table
	88	[301]	GETTABLE 	4 4 -28	; "concat"
	89	[301]	MOVE     	5 3
	90	[301]	LOADK    	6 -29	; "\n"
	91	[301]	CALL     	4 3 2
	92	[301]	SETTABLE 	0 -27 4	; "css_text" -
	93	[302]	GETUPVAL 	4 1	; logger
	94	[302]	GETTABLE 	4 4 -30	; "dbg"
	95	[302]	LOADK    	5 -31	; "made tweak css:\n"
	96	[302]	GETTABLE 	6 0 -27	; "css_text"
	97	[302]	LOADK    	7 -32	; "[END]"
	98	[302]	CONCAT   	5 5 7
	99	[302]	CALL     	4 2 1
	100	[302]	JMP      	5	; to 106
	101	[304]	SETTABLE 	0 -27 -5	; "css_text" nil
	102	[305]	GETUPVAL 	2 1	; logger
	103	[305]	GETTABLE 	2 2 -30	; "dbg"
	104	[305]	LOADK    	3 -33	; "made no tweak css (Style tweaks disabled)"
	105	[305]	CALL     	2 2 1
	106	[307]	TEST     	1 0 0
	107	[307]	JMP      	7	; to 115
	108	[308]	GETTABLE 	2 0 -34	; "ui"
	109	[308]	SELF     	2 2 -35	; "handleEvent"
	110	[308]	GETUPVAL 	4 2	; Event
	111	[308]	SELF     	4 4 -36	; "new"
	112	[308]	LOADK    	6 -37	; "ApplyStyleSheet"
	113	[308]	CALL     	4 3 0
	114	[308]	CALL     	2 0 1
	115	[310]	RETURN   	0 1

function <./frontend/apps/reader/modules/readerstyletweak.lua:312,319> (27 instructions, 108 bytes at 0x7fa6fec0a760)
2 params, 5 slots, 1 upvalue, 2 locals, 10 constants, 0 functions
	1	[313]	SELF     	2 1 -2	; "readSetting"
	2	[313]	LOADK    	4 -3	; "style_tweaks_enabled"
	3	[313]	CALL     	2 3 2
	4	[313]	EQ       	0 2 -4	; - false
	5	[313]	JMP      	1	; to 7
	6	[313]	LOADBOOL 	2 0 1
	7	[313]	LOADBOOL 	2 1 0
	8	[313]	SETTABLE 	0 -1 2	; "enabled" -
	9	[314]	SELF     	2 1 -2	; "readSetting"
	10	[314]	LOADK    	4 -6	; "style_tweaks"
	11	[314]	CALL     	2 3 2
	12	[314]	TEST     	2 0 1
	13	[314]	JMP      	1	; to 15
	14	[314]	NEWTABLE 	2 0 0
	15	[314]	SETTABLE 	0 -5 2	; "doc_tweaks" -
	16	[317]	GETGLOBAL	2 -8	; G_reader_settings
	17	[317]	SELF     	2 2 -2	; "readSetting"
	18	[317]	LOADK    	4 -6	; "style_tweaks"
	19	[317]	CALL     	2 3 2
	20	[317]	TEST     	2 0 1
	21	[317]	JMP      	2	; to 24
	22	[317]	GETUPVAL 	2 0	; CssTweaks
	23	[317]	GETTABLE 	2 2 -9	; "DEFAULT_GLOBAL_STYLE_TWEAKS"
	24	[317]	SETTABLE 	0 -7 2	; "global_tweaks" -
	25	[318]	SELF     	2 0 -10	; "updateCssText"
	26	[318]	CALL     	2 2 1
	27	[319]	RETURN   	0 1

function <./frontend/apps/reader/modules/readerstyletweak.lua:321,329> (36 instructions, 144 bytes at 0x7fa6fec086d0)
1 param, 6 slots, 1 upvalue, 1 local, 12 constants, 0 functions
	1	[322]	GETTABLE 	1 0 -1	; "enabled"
	2	[322]	TEST     	1 0 0
	3	[322]	JMP      	6	; to 10
	4	[323]	GETTABLE 	1 0 -2	; "ui"
	5	[323]	GETTABLE 	1 1 -3	; "doc_settings"
	6	[323]	SELF     	1 1 -4	; "delSetting"
	7	[323]	LOADK    	3 -5	; "style_tweaks_enabled"
	8	[323]	CALL     	1 3 1
	9	[323]	JMP      	6	; to 16
	10	[325]	GETTABLE 	1 0 -2	; "ui"
	11	[325]	GETTABLE 	1 1 -3	; "doc_settings"
	12	[325]	SELF     	1 1 -6	; "saveSetting"
	13	[325]	LOADK    	3 -5	; "style_tweaks_enabled"
	14	[325]	LOADBOOL 	4 0 0
	15	[325]	CALL     	1 4 1
	16	[327]	GETTABLE 	1 0 -2	; "ui"
	17	[327]	GETTABLE 	1 1 -3	; "doc_settings"
	18	[327]	SELF     	1 1 -6	; "saveSetting"
	19	[327]	LOADK    	3 -7	; "style_tweaks"
	20	[327]	GETUPVAL 	4 0	; util
	21	[327]	GETTABLE 	4 4 -8	; "tableSize"
	22	[327]	GETTABLE 	5 0 -9	; "doc_tweaks"
	23	[327]	CALL     	4 2 2
	24	[327]	LT       	0 -10 4	; 0 -
	25	[327]	JMP      	3	; to 29
	26	[327]	GETTABLE 	4 0 -9	; "doc_tweaks"
	27	[327]	TEST     	4 0 1
	28	[327]	JMP      	1	; to 30
	29	[327]	LOADNIL  	4 4
	30	[327]	CALL     	1 4 1
	31	[328]	GETGLOBAL	1 -11	; G_reader_settings
	32	[328]	SELF     	1 1 -6	; "saveSetting"
	33	[328]	LOADK    	3 -7	; "style_tweaks"
	34	[328]	GETTABLE 	4 0 -12	; "global_tweaks"
	35	[328]	CALL     	1 4 1
	36	[329]	RETURN   	0 1

function <./frontend/apps/reader/modules/readerstyletweak.lua:331,521> (86 instructions, 344 bytes at 0x7fa6fec0af50)
1 param, 11 slots, 9 upvalues, 12 locals, 20 constants, 6 functions
	1	[332]	NEWTABLE 	1 0 0
	2	[332]	SETTABLE 	0 -1 1	; "tweaks_by_id" -
	3	[333]	NEWTABLE 	1 0 0
	4	[333]	SETTABLE 	0 -2 1	; "tweaks_table" -
	5	[338]	GETGLOBAL	1 -3	; table
	6	[338]	GETTABLE 	1 1 -4	; "insert"
	7	[338]	GETTABLE 	2 0 -2	; "tweaks_table"
	8	[338]	NEWTABLE 	3 0 5
	9	[339]	GETUPVAL 	4 0	; _
	10	[339]	LOADK    	5 -6	; "Enable style tweaks (hold for info)"
	11	[339]	CALL     	4 2 2
	12	[339]	SETTABLE 	3 -5 4	; "text" -
	13	[340]	CLOSURE  	4 0	; 0x7fa6fec0b460
	14	[340]	MOVE     	0 0
	15	[340]	SETTABLE 	3 -7 4	; "checked_func" -
	16	[344]	CLOSURE  	4 1	; 0x7fa6fec0b650
	17	[344]	MOVE     	0 0
	18	[344]	SETTABLE 	3 -8 4	; "callback" -
	19	[354]	CLOSURE  	4 2	; 0x7fa6fec0adc0
	20	[354]	GETUPVAL 	0 1	; UIManager
	21	[354]	GETUPVAL 	0 2	; InfoMessage
	22	[354]	GETUPVAL 	0 0	; _
	23	[354]	SETTABLE 	3 -9 4	; "hold_callback" -
	24	[355]	SETTABLE 	3 -10 -11	; "separator" true
	25	[338]	CALL     	1 3 1
	26	[359]	CLOSURE  	1 3	; 0x7fa6fec0b6d0
	27	[359]	MOVE     	0 0
	28	[365]	LOADNIL  	2 2
	29	[461]	CLOSURE  	2 4	; 0x7fa6fec0b850
	30	[461]	MOVE     	0 2
	31	[461]	MOVE     	0 0
	32	[461]	MOVE     	0 1
	33	[461]	GETUPVAL 	0 1	; UIManager
	34	[461]	GETUPVAL 	0 3	; TweakInfoWidget
	35	[461]	GETUPVAL 	0 2	; InfoMessage
	36	[461]	GETUPVAL 	0 0	; _
	37	[464]	GETGLOBAL	3 -12	; ipairs
	38	[464]	GETUPVAL 	4 4	; CssTweaks
	39	[464]	CALL     	3 2 4
	40	[464]	JMP      	4	; to 45
	41	[465]	MOVE     	8 2
	42	[465]	GETTABLE 	9 0 -2	; "tweaks_table"
	43	[465]	MOVE     	10 7
	44	[465]	CALL     	8 3 1
	45	[464]	TFORLOOP 	3 2
	46	[465]	JMP      	-6	; to 41
	47	[471]	GETUPVAL 	3 5	; DataStorage
	48	[471]	SELF     	3 3 -13	; "getDataDir"
	49	[471]	CALL     	3 2 2
	50	[471]	LOADK    	4 -14	; "/styletweaks"
	51	[471]	CONCAT   	3 3 4
	52	[472]	NEWTABLE 	4 0 1
	53	[472]	GETUPVAL 	5 0	; _
	54	[472]	LOADK    	6 -16	; "User style tweaks"
	55	[472]	CALL     	5 2 2
	56	[472]	SETTABLE 	4 -15 5	; "title" -
	57	[475]	LOADNIL  	5 5
	58	[514]	CLOSURE  	5 5	; 0x7fa6fec0bc40
	59	[514]	GETUPVAL 	0 6	; lfs
	60	[514]	MOVE     	0 5
	61	[514]	GETUPVAL 	0 7	; T
	62	[514]	GETUPVAL 	0 0	; _
	63	[514]	GETUPVAL 	0 8	; BD
	64	[515]	GETUPVAL 	6 0	; _
	65	[515]	LOADK    	7 -17	; "Add your own tweaks in koreader/styletweaks/"
	66	[515]	CALL     	6 2 2
	67	[516]	MOVE     	7 5
	68	[516]	MOVE     	8 3
	69	[516]	MOVE     	9 4
	70	[516]	MOVE     	10 6
	71	[516]	CALL     	7 4 1
	72	[517]	GETTABLE 	7 0 -2	; "tweaks_table"
	73	[517]	GETTABLE 	8 0 -2	; "tweaks_table"
	74	[517]	LEN      	8 8
	75	[517]	GETTABLE 	7 7 8
	76	[517]	SETTABLE 	7 -10 -11	; "separator" true
	77	[518]	MOVE     	7 2
	78	[518]	GETTABLE 	8 0 -2	; "tweaks_table"
	79	[518]	MOVE     	9 4
	80	[518]	CALL     	7 3 1
	81	[520]	GETTABLE 	7 0 -18	; "ui"
	82	[520]	GETTABLE 	7 7 -19	; "menu"
	83	[520]	SELF     	7 7 -20	; "registerToMainMenu"
	84	[520]	MOVE     	9 0
	85	[520]	CALL     	7 3 1
	86	[521]	RETURN   	0 1

function <./frontend/apps/reader/modules/readerstyletweak.lua:340,340> (4 instructions, 16 bytes at 0x7fa6fec0b460)
0 params, 2 slots, 1 upvalue, 0 locals, 1 constant, 0 functions
	1	[340]	GETUPVAL 	0 0	; self
	2	[340]	GETTABLE 	0 0 -1	; "enabled"
	3	[340]	RETURN   	0 2
	4	[340]	RETURN   	0 1

function <./frontend/apps/reader/modules/readerstyletweak.lua:341,344> (10 instructions, 40 bytes at 0x7fa6fec0b650)
0 params, 3 slots, 1 upvalue, 0 locals, 2 constants, 0 functions
	1	[342]	GETUPVAL 	0 0	; self
	2	[342]	GETUPVAL 	1 0	; self
	3	[342]	GETTABLE 	1 1 -1	; "enabled"
	4	[342]	NOT      	1 1
	5	[342]	SETTABLE 	0 -1 1	; "enabled" -
	6	[343]	GETUPVAL 	0 0	; self
	7	[343]	SELF     	0 0 -2	; "updateCssText"
	8	[343]	LOADBOOL 	2 1 0
	9	[343]	CALL     	0 3 1
	10	[344]	RETURN   	0 1

function <./frontend/apps/reader/modules/readerstyletweak.lua:345,354> (12 instructions, 48 bytes at 0x7fa6fec0adc0)
0 params, 7 slots, 3 upvalues, 0 locals, 4 constants, 0 functions
	1	[346]	GETUPVAL 	0 0	; UIManager
	2	[346]	SELF     	0 0 -1	; "show"
	3	[346]	GETUPVAL 	2 1	; InfoMessage
	4	[346]	SELF     	2 2 -2	; "new"
	5	[346]	NEWTABLE 	4 0 1
	6	[347]	GETUPVAL 	5 2	; _
	7	[352]	LOADK    	6 -4	; "Style tweaks allow changing small parts of book styles (including the publisher/embedded styles) to make visual adjustments or disable unwanted publisher layout choices.\n\nSome tweaks may be useful with some books, while resulting in undesirable effects with others.\n\nYou can enable individual tweaks on this book with a tap, or view more details about a tweak and enable it on all books with hold."
	8	[347]	CALL     	5 2 2
	9	[352]	SETTABLE 	4 -3 5	; "text" -
	10	[346]	CALL     	2 3 0
	11	[346]	CALL     	0 0 1
	12	[354]	RETURN   	0 1

function <./frontend/apps/reader/modules/readerstyletweak.lua:359,359> (4 instructions, 16 bytes at 0x7fa6fec0b6d0)
0 params, 2 slots, 1 upvalue, 0 locals, 1 constant, 0 functions
	1	[359]	GETUPVAL 	0 0	; self
	2	[359]	GETTABLE 	0 0 -1	; "enabled"
	3	[359]	RETURN   	0 2
	4	[359]	RETURN   	0 1

function <./frontend/apps/reader/modules/readerstyletweak.lua:366,461> (118 instructions, 472 bytes at 0x7fa6fec0b850)
2 params, 11 slots, 7 upvalues, 8 locals, 26 constants, 7 functions
	1	[367]	GETGLOBAL	2 -1	; type
	2	[367]	MOVE     	3 1
	3	[367]	CALL     	2 2 2
	4	[367]	EQ       	0 2 -2	; - "table"
	5	[367]	JMP      	31	; to 37
	6	[367]	LEN      	2 1
	7	[367]	LT       	0 -3 2	; 0 -
	8	[367]	JMP      	28	; to 37
	9	[368]	NEWTABLE 	2 0 0
	10	[369]	GETGLOBAL	3 -4	; ipairs
	11	[369]	MOVE     	4 1
	12	[369]	CALL     	3 2 4
	13	[369]	JMP      	4	; to 18
	14	[370]	GETUPVAL 	8 0	; addTweakMenuItem
	15	[370]	MOVE     	9 2
	16	[370]	MOVE     	10 7
	17	[370]	CALL     	8 3 1
	18	[369]	TFORLOOP 	3 2
	19	[370]	JMP      	-6	; to 14
	20	[372]	GETGLOBAL	3 -2	; table
	21	[372]	GETTABLE 	3 3 -5	; "insert"
	22	[372]	MOVE     	4 0
	23	[372]	NEWTABLE 	5 0 4
	24	[383]	CLOSURE  	6 0	; 0x7fa6fec0b790
	25	[383]	MOVE     	0 1
	26	[383]	GETUPVAL 	0 1	; self
	27	[383]	MOVE     	0 2
	28	[383]	SETTABLE 	5 -6 6	; "text_func" -
	29	[384]	GETUPVAL 	6 2	; is_enabled
	30	[384]	SETTABLE 	5 -7 6	; "enabled_func" -
	31	[385]	SETTABLE 	5 -8 2	; "sub_item_table" -
	32	[386]	GETTABLE 	6 1 -9	; "separator"
	33	[386]	SETTABLE 	5 -9 6	; "separator" -
	34	[372]	CALL     	3 3 1
	35	[387]	CLOSE    	2
	36	[387]	JMP      	81	; to 118
	37	[388]	GETTABLE 	2 1 -10	; "id"
	38	[388]	TEST     	2 0 0
	39	[388]	JMP      	38	; to 78
	40	[390]	GETTABLE 	2 1 -11	; "priority"
	41	[390]	TEST     	2 0 1
	42	[390]	JMP      	1	; to 44
	43	[390]	SETTABLE 	1 -11 -3	; "priority" 0
	44	[391]	GETUPVAL 	2 1	; self
	45	[391]	GETTABLE 	2 2 -12	; "tweaks_by_id"
	46	[391]	GETTABLE 	3 1 -10	; "id"
	47	[391]	SETTABLE 	2 3 1
	48	[392]	GETGLOBAL	2 -2	; table
	49	[392]	GETTABLE 	2 2 -5	; "insert"
	50	[392]	MOVE     	3 0
	51	[392]	NEWTABLE 	4 0 7
	52	[393]	GETTABLE 	5 1 -10	; "id"
	53	[393]	SETTABLE 	4 -13 5	; "tweak_id" -
	54	[394]	GETUPVAL 	5 2	; is_enabled
	55	[394]	SETTABLE 	4 -7 5	; "enabled_func" -
	56	[395]	CLOSURE  	5 1	; 0x7fa6fec0c5f0
	57	[395]	GETUPVAL 	0 1	; self
	58	[395]	MOVE     	0 1
	59	[395]	SETTABLE 	4 -14 5	; "checked_func" -
	60	[403]	CLOSURE  	5 2	; 0x7fa6fec0ccc0
	61	[403]	MOVE     	0 1
	62	[403]	GETUPVAL 	0 1	; self
	63	[403]	SETTABLE 	4 -6 5	; "text_func" -
	64	[418]	CLOSURE  	5 3	; 0x7fa6fec0d4b0
	65	[418]	GETUPVAL 	0 3	; UIManager
	66	[418]	GETUPVAL 	0 4	; TweakInfoWidget
	67	[418]	MOVE     	0 1
	68	[418]	GETUPVAL 	0 1	; self
	69	[418]	SETTABLE 	4 -15 5	; "hold_callback" -
	70	[434]	CLOSURE  	5 4	; 0x7fa6fec0c670
	71	[434]	GETUPVAL 	0 1	; self
	72	[434]	MOVE     	0 1
	73	[434]	SETTABLE 	4 -16 5	; "callback" -
	74	[435]	GETTABLE 	5 1 -9	; "separator"
	75	[435]	SETTABLE 	4 -9 5	; "separator" -
	76	[392]	CALL     	2 3 1
	77	[436]	JMP      	40	; to 118
	78	[437]	GETTABLE 	2 1 -17	; "info_text"
	79	[437]	TEST     	2 0 0
	80	[437]	JMP      	24	; to 105
	81	[438]	GETGLOBAL	2 -2	; table
	82	[438]	GETTABLE 	2 2 -5	; "insert"
	83	[438]	MOVE     	3 0
	84	[438]	NEWTABLE 	4 0 5
	85	[439]	GETTABLE 	5 1 -19	; "title"
	86	[439]	TEST     	5 0 1
	87	[439]	JMP      	1	; to 89
	88	[439]	LOADK    	5 -20	; "### undefined menu title ###"
	89	[439]	SETTABLE 	4 -18 5	; "text" -
	90	[442]	SETTABLE 	4 -21 -22	; "keep_menu_open" true
	91	[447]	CLOSURE  	5 5	; 0x7fa6fec0cad0
	92	[447]	GETUPVAL 	0 3	; UIManager
	93	[447]	GETUPVAL 	0 5	; InfoMessage
	94	[447]	MOVE     	0 1
	95	[447]	SETTABLE 	4 -16 5	; "callback" -
	96	[452]	CLOSURE  	5 6	; 0x7fa6fec0e600
	97	[452]	GETUPVAL 	0 3	; UIManager
	98	[452]	GETUPVAL 	0 5	; InfoMessage
	99	[452]	MOVE     	0 1
	100	[452]	SETTABLE 	4 -15 5	; "hold_callback" -
	101	[453]	GETTABLE 	5 1 -9	; "separator"
	102	[453]	SETTABLE 	4 -9 5	; "separator" -
	103	[438]	CALL     	2 3 1
	104	[454]	JMP      	13	; to 118
	105	[456]	GETGLOBAL	2 -2	; table
	106	[456]	GETTABLE 	2 2 -5	; "insert"
	107	[456]	MOVE     	3 0
	108	[456]	NEWTABLE 	4 0 2
	109	[457]	GETTABLE 	5 1 -23	; "if_empty_menu_title"
	110	[457]	TEST     	5 0 1
	111	[457]	JMP      	3	; to 115
	112	[457]	GETUPVAL 	5 6	; _
	113	[457]	LOADK    	6 -24	; "This section is empty"
	114	[457]	CALL     	5 2 2
	115	[457]	SETTABLE 	4 -18 5	; "text" -
	116	[458]	SETTABLE 	4 -25 -26	; "enabled" false
	117	[456]	CALL     	2 3 1
	118	[461]	RETURN   	0 1

function <./frontend/apps/reader/modules/readerstyletweak.lua:373,383> (20 instructions, 80 bytes at 0x7fa6fec0b790)
0 params, 7 slots, 3 upvalues, 3 locals, 7 constants, 0 functions
	1	[374]	GETUPVAL 	0 0	; item
	2	[374]	GETTABLE 	0 0 -1	; "title"
	3	[374]	TEST     	0 0 1
	4	[374]	JMP      	1	; to 6
	5	[374]	LOADK    	0 -2	; "### undefined submenu title ###"
	6	[375]	GETUPVAL 	1 1	; self
	7	[375]	SELF     	1 1 -3	; "nbTweaksEnabled"
	8	[375]	GETUPVAL 	3 2	; sub_item_table
	9	[375]	CALL     	1 3 3
	10	[379]	LT       	0 -4 1	; 0 -
	11	[379]	JMP      	7	; to 19
	12	[380]	GETGLOBAL	3 -5	; string
	13	[380]	GETTABLE 	3 3 -6	; "format"
	14	[380]	LOADK    	4 -7	; "%s (%d)"
	15	[380]	MOVE     	5 0
	16	[380]	MOVE     	6 1
	17	[380]	CALL     	3 4 2
	18	[380]	MOVE     	0 3
	19	[382]	RETURN   	0 2
	20	[383]	RETURN   	0 1

function <./frontend/apps/reader/modules/readerstyletweak.lua:395,395> (7 instructions, 28 bytes at 0x7fa6fec0c5f0)
0 params, 3 slots, 2 upvalues, 0 locals, 2 constants, 0 functions
	1	[395]	GETUPVAL 	0 0	; self
	2	[395]	SELF     	0 0 -1	; "isTweakEnabled"
	3	[395]	GETUPVAL 	2 1	; item
	4	[395]	GETTABLE 	2 2 -2	; "id"
	5	[395]	TAILCALL 	0 3 0
	6	[395]	RETURN   	0 0
	7	[395]	RETURN   	0 1

function <./frontend/apps/reader/modules/readerstyletweak.lua:397,403> (17 instructions, 68 bytes at 0x7fa6fec0ccc0)
0 params, 3 slots, 2 upvalues, 1 local, 5 constants, 0 functions
	1	[398]	GETUPVAL 	0 0	; item
	2	[398]	GETTABLE 	0 0 -1	; "title"
	3	[398]	TEST     	0 0 1
	4	[398]	JMP      	1	; to 6
	5	[398]	LOADK    	0 -2	; "### undefined tweak title ###"
	6	[399]	GETUPVAL 	1 1	; self
	7	[399]	GETTABLE 	1 1 -3	; "global_tweaks"
	8	[399]	GETUPVAL 	2 0	; item
	9	[399]	GETTABLE 	2 2 -4	; "id"
	10	[399]	GETTABLE 	1 1 2
	11	[399]	TEST     	1 0 0
	12	[399]	JMP      	3	; to 16
	13	[400]	MOVE     	1 0
	14	[400]	LOADK    	2 -5	; "   \226\152\133"
	15	[400]	CONCAT   	0 1 2
	16	[402]	RETURN   	0 2
	17	[403]	RETURN   	0 1

function <./frontend/apps/reader/modules/readerstyletweak.lua:404,418> (21 instructions, 84 bytes at 0x7fa6fec0d4b0)
1 param, 8 slots, 4 upvalues, 1 local, 7 constants, 1 function
	1	[405]	GETUPVAL 	1 0	; UIManager
	2	[405]	SELF     	1 1 -1	; "show"
	3	[405]	GETUPVAL 	3 1	; TweakInfoWidget
	4	[405]	SELF     	3 3 -2	; "new"
	5	[405]	NEWTABLE 	5 0 3
	6	[406]	GETUPVAL 	6 2	; item
	7	[406]	SETTABLE 	5 -3 6	; "tweak" -
	8	[407]	GETUPVAL 	6 3	; self
	9	[407]	GETTABLE 	6 6 -5	; "global_tweaks"
	10	[407]	GETUPVAL 	7 2	; item
	11	[407]	GETTABLE 	7 7 -6	; "id"
	12	[407]	GETTABLE 	6 6 7
	13	[407]	SETTABLE 	5 -4 6	; "is_global_default" -
	14	[416]	CLOSURE  	6 0	; 0x7fa6fec0d660
	15	[416]	GETUPVAL 	0 3	; self
	16	[416]	GETUPVAL 	0 2	; item
	17	[416]	MOVE     	0 0
	18	[416]	SETTABLE 	5 -7 6	; "toggle_global_default_callback" -
	19	[405]	CALL     	3 3 0
	20	[405]	CALL     	1 0 1
	21	[418]	RETURN   	0 1

function <./frontend/apps/reader/modules/readerstyletweak.lua:408,416> (26 instructions, 104 bytes at 0x7fa6fec0d660)
0 params, 3 slots, 3 upvalues, 0 locals, 6 constants, 0 functions
	1	[409]	GETUPVAL 	0 0	; self
	2	[409]	GETTABLE 	0 0 -1	; "global_tweaks"
	3	[409]	GETUPVAL 	1 1	; item
	4	[409]	GETTABLE 	1 1 -2	; "id"
	5	[409]	GETTABLE 	0 0 1
	6	[409]	TEST     	0 0 0
	7	[409]	JMP      	6	; to 14
	8	[410]	GETUPVAL 	0 0	; self
	9	[410]	GETTABLE 	0 0 -1	; "global_tweaks"
	10	[410]	GETUPVAL 	1 1	; item
	11	[410]	GETTABLE 	1 1 -2	; "id"
	12	[410]	SETTABLE 	0 1 -3	; - nil
	13	[410]	JMP      	5	; to 19
	14	[412]	GETUPVAL 	0 0	; self
	15	[412]	GETTABLE 	0 0 -1	; "global_tweaks"
	16	[412]	GETUPVAL 	1 1	; item
	17	[412]	GETTABLE 	1 1 -2	; "id"
	18	[412]	SETTABLE 	0 1 -4	; - true
	19	[414]	GETUPVAL 	0 2	; touchmenu_instance
	20	[414]	SELF     	0 0 -5	; "updateItems"
	21	[414]	CALL     	0 2 1
	22	[415]	GETUPVAL 	0 0	; self
	23	[415]	SELF     	0 0 -6	; "updateCssText"
	24	[415]	LOADBOOL 	2 1 0
	25	[415]	CALL     	0 3 1
	26	[416]	RETURN   	0 1

function <./frontend/apps/reader/modules/readerstyletweak.lua:419,434> (31 instructions, 124 bytes at 0x7fa6fec0c670)
0 params, 5 slots, 2 upvalues, 2 locals, 7 constants, 0 functions
	1	[421]	GETUPVAL 	0 0	; self
	2	[421]	SELF     	0 0 -1	; "isTweakEnabled"
	3	[421]	GETUPVAL 	2 1	; item
	4	[421]	GETTABLE 	2 2 -2	; "id"
	5	[421]	CALL     	0 3 3
	6	[422]	TEST     	0 0 0
	7	[422]	JMP      	14	; to 22
	8	[423]	TEST     	1 0 0
	9	[423]	JMP      	6	; to 16
	10	[426]	GETUPVAL 	2 0	; self
	11	[426]	GETTABLE 	2 2 -3	; "doc_tweaks"
	12	[426]	GETUPVAL 	3 1	; item
	13	[426]	GETTABLE 	3 3 -2	; "id"
	14	[426]	SETTABLE 	2 3 -4	; - false
	15	[426]	JMP      	11	; to 27
	16	[428]	GETUPVAL 	2 0	; self
	17	[428]	GETTABLE 	2 2 -3	; "doc_tweaks"
	18	[428]	GETUPVAL 	3 1	; item
	19	[428]	GETTABLE 	3 3 -2	; "id"
	20	[428]	SETTABLE 	2 3 -5	; - nil
	21	[429]	JMP      	5	; to 27
	22	[431]	GETUPVAL 	2 0	; self
	23	[431]	GETTABLE 	2 2 -3	; "doc_tweaks"
	24	[431]	GETUPVAL 	3 1	; item
	25	[431]	GETTABLE 	3 3 -2	; "id"
	26	[431]	SETTABLE 	2 3 -6	; - true
	27	[433]	GETUPVAL 	2 0	; self
	28	[433]	SELF     	2 2 -7	; "updateCssText"
	29	[433]	LOADBOOL 	4 1 0
	30	[433]	CALL     	2 3 1
	31	[434]	RETURN   	0 1

function <./frontend/apps/reader/modules/readerstyletweak.lua:443,447> (11 instructions, 44 bytes at 0x7fa6fec0cad0)
0 params, 6 slots, 3 upvalues, 0 locals, 4 constants, 0 functions
	1	[444]	GETUPVAL 	0 0	; UIManager
	2	[444]	SELF     	0 0 -1	; "show"
	3	[444]	GETUPVAL 	2 1	; InfoMessage
	4	[444]	SELF     	2 2 -2	; "new"
	5	[444]	NEWTABLE 	4 0 1
	6	[445]	GETUPVAL 	5 2	; item
	7	[445]	GETTABLE 	5 5 -4	; "info_text"
	8	[445]	SETTABLE 	4 -3 5	; "text" -
	9	[444]	CALL     	2 3 0
	10	[444]	CALL     	0 0 1
	11	[447]	RETURN   	0 1

function <./frontend/apps/reader/modules/readerstyletweak.lua:448,452> (11 instructions, 44 bytes at 0x7fa6fec0e600)
0 params, 6 slots, 3 upvalues, 0 locals, 4 constants, 0 functions
	1	[449]	GETUPVAL 	0 0	; UIManager
	2	[449]	SELF     	0 0 -1	; "show"
	3	[449]	GETUPVAL 	2 1	; InfoMessage
	4	[449]	SELF     	2 2 -2	; "new"
	5	[449]	NEWTABLE 	4 0 1
	6	[450]	GETUPVAL 	5 2	; item
	7	[450]	GETTABLE 	5 5 -4	; "info_text"
	8	[450]	SETTABLE 	4 -3 5	; "text" -
	9	[449]	CALL     	2 3 0
	10	[449]	CALL     	0 0 1
	11	[452]	RETURN   	0 1

function <./frontend/apps/reader/modules/readerstyletweak.lua:476,514> (134 instructions, 536 bytes at 0x7fa6fec0bc40)
3 params, 19 slots, 5 upvalues, 23 locals, 30 constants, 0 functions
	1	[477]	NEWTABLE 	3 0 0
	2	[478]	NEWTABLE 	4 0 0
	3	[479]	GETUPVAL 	5 0	; lfs
	4	[479]	GETTABLE 	5 5 -1	; "attributes"
	5	[479]	MOVE     	6 0
	6	[479]	LOADK    	7 -2	; "mode"
	7	[479]	CALL     	5 3 2
	8	[479]	EQ       	0 5 -3	; - "directory"
	9	[479]	JMP      	41	; to 51
	10	[480]	GETUPVAL 	5 0	; lfs
	11	[480]	GETTABLE 	5 5 -4	; "dir"
	12	[480]	MOVE     	6 0
	13	[480]	CALL     	5 2 4
	14	[480]	JMP      	34	; to 49
	15	[481]	EQ       	1 8 -5	; - "."
	16	[481]	JMP      	32	; to 49
	17	[481]	EQ       	1 8 -6	; - ".."
	18	[481]	JMP      	30	; to 49
	19	[482]	GETUPVAL 	9 0	; lfs
	20	[482]	GETTABLE 	9 9 -1	; "attributes"
	21	[482]	MOVE     	10 0
	22	[482]	LOADK    	11 -7	; "/"
	23	[482]	MOVE     	12 8
	24	[482]	CONCAT   	10 10 12
	25	[482]	LOADK    	11 -2	; "mode"
	26	[482]	CALL     	9 3 2
	27	[483]	EQ       	0 9 -3	; - "directory"
	28	[483]	JMP      	6	; to 35
	29	[484]	GETGLOBAL	10 -8	; table
	30	[484]	GETTABLE 	10 10 -9	; "insert"
	31	[484]	MOVE     	11 4
	32	[484]	MOVE     	12 8
	33	[484]	CALL     	10 3 1
	34	[484]	JMP      	14	; to 49
	35	[485]	EQ       	0 9 -10	; - "file"
	36	[485]	JMP      	12	; to 49
	37	[485]	GETGLOBAL	10 -11	; string
	38	[485]	GETTABLE 	10 10 -12	; "match"
	39	[485]	MOVE     	11 8
	40	[485]	LOADK    	12 -13	; "%.css$"
	41	[485]	CALL     	10 3 2
	42	[485]	TEST     	10 0 0
	43	[485]	JMP      	5	; to 49
	44	[486]	GETGLOBAL	10 -8	; table
	45	[486]	GETTABLE 	10 10 -9	; "insert"
	46	[486]	MOVE     	11 3
	47	[486]	MOVE     	12 8
	48	[486]	CALL     	10 3 1
	49	[480]	TFORLOOP 	5 1
	50	[488]	JMP      	-36	; to 15
	51	[491]	GETGLOBAL	5 -8	; table
	52	[491]	GETTABLE 	5 5 -14	; "sort"
	53	[491]	MOVE     	6 4
	54	[491]	CALL     	5 2 1
	55	[492]	GETGLOBAL	5 -8	; table
	56	[492]	GETTABLE 	5 5 -14	; "sort"
	57	[492]	MOVE     	6 3
	58	[492]	CALL     	5 2 1
	59	[493]	GETGLOBAL	5 -15	; ipairs
	60	[493]	MOVE     	6 4
	61	[493]	CALL     	5 2 4
	62	[493]	JMP      	18	; to 81
	63	[494]	NEWTABLE 	10 0 1
	64	[494]	SELF     	11 9 -17	; "gsub"
	65	[494]	LOADK    	13 -18	; "_"
	66	[494]	LOADK    	14 -19	; " "
	67	[494]	CALL     	11 4 2
	68	[494]	SETTABLE 	10 -16 11	; "title" -
	69	[495]	GETUPVAL 	11 1	; process_tweaks_dir
	70	[495]	MOVE     	12 0
	71	[495]	LOADK    	13 -7	; "/"
	72	[495]	MOVE     	14 9
	73	[495]	CONCAT   	12 12 14
	74	[495]	MOVE     	13 10
	75	[495]	CALL     	11 3 1
	76	[496]	GETGLOBAL	11 -8	; table
	77	[496]	GETTABLE 	11 11 -9	; "insert"
	78	[496]	MOVE     	12 1
	79	[496]	MOVE     	13 10
	80	[496]	CALL     	11 3 1
	81	[493]	TFORLOOP 	5 2
	82	[496]	JMP      	-20	; to 63
	83	[498]	GETGLOBAL	5 -15	; ipairs
	84	[498]	MOVE     	6 3
	85	[498]	CALL     	5 2 4
	86	[498]	JMP      	31	; to 118
	87	[499]	SELF     	10 9 -17	; "gsub"
	88	[499]	LOADK    	12 -13	; "%.css$"
	89	[499]	LOADK    	13 -20	; ""
	90	[499]	CALL     	10 4 2
	91	[499]	SELF     	10 10 -17	; "gsub"
	92	[499]	LOADK    	12 -18	; "_"
	93	[499]	LOADK    	13 -19	; " "
	94	[499]	CALL     	10 4 2
	95	[500]	MOVE     	11 0
	96	[500]	LOADK    	12 -7	; "/"
	97	[500]	MOVE     	13 9
	98	[500]	CONCAT   	11 11 13
	99	[501]	GETGLOBAL	12 -8	; table
	100	[501]	GETTABLE 	12 12 -9	; "insert"
	101	[501]	MOVE     	13 1
	102	[501]	NEWTABLE 	14 0 5
	103	[502]	SETTABLE 	14 -16 10	; "title" -
	104	[503]	SETTABLE 	14 -21 9	; "id" -
	105	[504]	GETUPVAL 	15 2	; T
	106	[504]	GETUPVAL 	16 3	; _
	107	[504]	LOADK    	17 -23	; "User style tweak at %1"
	108	[504]	CALL     	16 2 2
	109	[504]	GETUPVAL 	17 4	; BD
	110	[504]	GETTABLE 	17 17 -24	; "filepath"
	111	[504]	MOVE     	18 11
	112	[504]	CALL     	17 2 0
	113	[504]	CALL     	15 0 2
	114	[504]	SETTABLE 	14 -22 15	; "description" -
	115	[505]	SETTABLE 	14 -25 -26	; "priority" 10
	116	[506]	SETTABLE 	14 -27 11	; "css_path" -
	117	[501]	CALL     	12 3 1
	118	[498]	TFORLOOP 	5 2
	119	[507]	JMP      	-33	; to 87
	120	[509]	LEN      	5 1
	121	[509]	EQ       	0 5 -28	; - 0
	122	[509]	JMP      	11	; to 134
	123	[510]	GETGLOBAL	5 -8	; table
	124	[510]	GETTABLE 	5 5 -9	; "insert"
	125	[510]	MOVE     	6 1
	126	[510]	NEWTABLE 	7 0 1
	127	[511]	TESTSET  	8 2 1
	128	[511]	JMP      	3	; to 132
	129	[511]	GETUPVAL 	8 3	; _
	130	[511]	LOADK    	9 -30	; "No CSS tweak found in this directory"
	131	[511]	CALL     	8 2 2
	132	[511]	SETTABLE 	7 -29 8	; "if_empty_menu_title" -
	133	[510]	CALL     	5 3 1
	134	[514]	RETURN   	0 1

function <./frontend/apps/reader/modules/readerstyletweak.lua:523,535> (10 instructions, 40 bytes at 0x7fa6fec0de40)
2 params, 4 slots, 2 upvalues, 2 locals, 4 constants, 1 function
	1	[525]	NEWTABLE 	2 0 2
	2	[532]	CLOSURE  	3 0	; 0x7fa6fec0a420
	3	[532]	MOVE     	0 0
	4	[532]	GETUPVAL 	0 0	; T
	5	[532]	GETUPVAL 	0 1	; _
	6	[532]	SETTABLE 	2 -2 3	; "text_func" -
	7	[533]	GETTABLE 	3 0 -4	; "tweaks_table"
	8	[533]	SETTABLE 	2 -3 3	; "sub_item_table" -
	9	[534]	SETTABLE 	1 -1 2	; "style_tweaks" -
	10	[535]	RETURN   	0 1

function <./frontend/apps/reader/modules/readerstyletweak.lua:526,532> (22 instructions, 88 bytes at 0x7fa6fec0a420)
0 params, 3 slots, 3 upvalues, 0 locals, 5 constants, 0 functions
	1	[527]	GETUPVAL 	0 0	; self
	2	[527]	GETTABLE 	0 0 -1	; "enabled"
	3	[527]	TEST     	0 0 0
	4	[527]	JMP      	13	; to 18
	5	[527]	GETUPVAL 	0 0	; self
	6	[527]	GETTABLE 	0 0 -2	; "nb_enabled_tweaks"
	7	[527]	LT       	0 -3 0	; 0 -
	8	[527]	JMP      	9	; to 18
	9	[528]	GETUPVAL 	0 1	; T
	10	[528]	GETUPVAL 	1 2	; _
	11	[528]	LOADK    	2 -4	; "Style tweaks (%1)"
	12	[528]	CALL     	1 2 2
	13	[528]	GETUPVAL 	2 0	; self
	14	[528]	GETTABLE 	2 2 -2	; "nb_enabled_tweaks"
	15	[528]	TAILCALL 	0 3 0
	16	[528]	RETURN   	0 0
	17	[528]	JMP      	4	; to 22
	18	[530]	GETUPVAL 	0 2	; _
	19	[530]	LOADK    	1 -5	; "Style tweaks"
	20	[530]	TAILCALL 	0 2 0
	21	[530]	RETURN   	0 0
	22	[532]	RETURN   	0 1
