
main <./frontend/apps/reader/modules/readerflipping.lua:0,0> (31 instructions, 124 bytes at 0x7fdc6fc06900)
0+ params, 8 slots, 0 upvalues, 6 locals, 12 constants, 2 functions
	1	[1]	GETGLOBAL	0 -1	; require
	2	[1]	LOADK    	1 -2	; "ui/geometry"
	3	[1]	CALL     	0 2 2
	4	[2]	GETGLOBAL	1 -1	; require
	5	[2]	LOADK    	2 -3	; "ui/widget/imagewidget"
	6	[2]	CALL     	1 2 2
	7	[3]	GETGLOBAL	2 -1	; require
	8	[3]	LOADK    	3 -4	; "ui/widget/container/inputcontainer"
	9	[3]	CALL     	2 2 2
	10	[4]	GETGLOBAL	3 -1	; require
	11	[4]	LOADK    	4 -5	; "ui/widget/container/leftcontainer"
	12	[4]	CALL     	3 2 2
	13	[5]	GETGLOBAL	4 -1	; require
	14	[5]	LOADK    	5 -6	; "device"
	15	[5]	CALL     	4 2 2
	16	[5]	GETTABLE 	4 4 -7	; "screen"
	17	[7]	SELF     	5 2 -8	; "new"
	18	[7]	NEWTABLE 	7 0 1
	19	[8]	SETTABLE 	7 -9 -10	; "orig_reflow_mode" 0
	20	[7]	CALL     	5 3 2
	21	[20]	CLOSURE  	6 0	; 0x7fdc6fc06c40
	22	[20]	MOVE     	0 1
	23	[20]	MOVE     	0 3
	24	[20]	MOVE     	0 0
	25	[20]	MOVE     	0 4
	26	[11]	SETTABLE 	5 -11 6	; "init" -
	27	[28]	CLOSURE  	6 1	; 0x7fdc6fc072a0
	28	[28]	MOVE     	0 4
	29	[22]	SETTABLE 	5 -12 6	; "resetLayout" -
	30	[30]	RETURN   	5 2
	31	[30]	RETURN   	0 1

function <./frontend/apps/reader/modules/readerflipping.lua:11,20> (28 instructions, 112 bytes at 0x7fdc6fc06c40)
1 param, 10 slots, 4 upvalues, 2 locals, 10 constants, 0 functions
	1	[12]	GETUPVAL 	1 0	; ImageWidget
	2	[12]	SELF     	1 1 -1	; "new"
	3	[12]	NEWTABLE 	3 0 1
	4	[13]	SETTABLE 	3 -2 -3	; "file" "resources/icons/appbar.book.open.png"
	5	[12]	CALL     	1 3 2
	6	[15]	GETUPVAL 	2 1	; LeftContainer
	7	[15]	SELF     	2 2 -1	; "new"
	8	[15]	NEWTABLE 	4 1 1
	9	[16]	GETUPVAL 	5 2	; Geom
	10	[16]	SELF     	5 5 -1	; "new"
	11	[16]	NEWTABLE 	7 0 2
	12	[16]	GETUPVAL 	8 3	; Screen
	13	[16]	SELF     	8 8 -7	; "getWidth"
	14	[16]	CALL     	8 2 2
	15	[16]	SETTABLE 	7 -6 8	; "w" -
	16	[16]	SELF     	8 1 -9	; "getSize"
	17	[16]	CALL     	8 2 2
	18	[16]	GETTABLE 	8 8 -8	; "h"
	19	[16]	SETTABLE 	7 -8 8	; "h" -
	20	[16]	CALL     	5 3 2
	21	[16]	SETTABLE 	4 -5 5	; "dimen" -
	22	[18]	MOVE     	5 1
	23	[18]	SETLIST  	4 1 1	; 1
	24	[15]	CALL     	2 3 2
	25	[18]	SETTABLE 	0 -4 2	; 1 -
	26	[19]	SELF     	2 0 -10	; "resetLayout"
	27	[19]	CALL     	2 2 1
	28	[20]	RETURN   	0 1

function <./frontend/apps/reader/modules/readerflipping.lua:22,28> (12 instructions, 48 bytes at 0x7fdc6fc072a0)
1 param, 3 slots, 1 upvalue, 2 locals, 5 constants, 0 functions
	1	[23]	GETUPVAL 	1 0	; Screen
	2	[23]	SELF     	1 1 -1	; "getWidth"
	3	[23]	CALL     	1 2 2
	4	[24]	GETTABLE 	2 0 -2	; "_last_screen_width"
	5	[24]	EQ       	0 1 2
	6	[24]	JMP      	1	; to 8
	7	[24]	RETURN   	0 1
	8	[25]	SETTABLE 	0 -2 1	; "_last_screen_width" -
	9	[27]	GETTABLE 	2 0 -3	; 1
	10	[27]	GETTABLE 	2 2 -4	; "dimen"
	11	[27]	SETTABLE 	2 -5 1	; "w" -
	12	[28]	RETURN   	0 1
