-- BYTECODE -- readerconfig.lua:15-36
0001    TGETS    1   0   0  ; "document"
0002    TGETS    1   1   1  ; "koptinterface"
0003    ISEQP    1   0
0004    JMP      1 => 0008
0005    UGET     1   0      ; KoptOptions
0006    TSETS    1   0   2  ; "options"
0007    JMP      1 => 0010
0008 => UGET     1   1      ; CreOptions
0009    TSETS    1   0   2  ; "options"
0010 => TGETS    1   0   3  ; "configurable"
0011    MOV      2   1
0012    TGETS    1   1   4  ; "loadDefaults"
0013    TGETS    3   0   2  ; "options"
0014    CALL     1   1   3
0015    TGETS    1   0   5  ; "dimen"
0016    IST          1
0017    JMP      1 => 0024
0018    UGET     1   2      ; Geom
0019    MOV      2   1
0020    TGETS    1   1   6  ; "new"
0021    TNEW     3   0
0022    CALL     1   2   3
0023    TSETS    1   0   5  ; "dimen"
0024 => UGET     1   3      ; Device
0025    MOV      2   1
0026    TGETS    1   1   7  ; "hasKeys"
0027    CALL     1   2   2
0028    ISF          1
0029    JMP      2 => 0038
0030    TDUP     1  11
0031    TDUP     2  10
0032    TNEW     3   3
0033    TDUP     4   9
0034    TSETB    4   3   1
0035    TSETB    3   2   1
0036    TSETS    2   1  12  ; "ShowConfigMenu"
0037    TSETS    1   0   8  ; "key_events"
0038 => UGET     1   3      ; Device
0039    MOV      2   1
0040    TGETS    1   1  13  ; "isTouchDevice"
0041    CALL     1   2   2
0042    ISF          1
0043    JMP      2 => 0047
0044    MOV      2   0
0045    TGETS    1   0  14  ; "initGesListener"
0046    CALL     1   1   2
0047 => GGET     1  16      ; "G_reader_settings"
0048    MOV      2   1
0049    TGETS    1   1  17  ; "readSetting"
0050    KSTR     3  18      ; "activate_menu"
0051    CALL     1   2   3
0052    TSETS    1   0  15  ; "activation_menu"
0053    TGETS    1   0  15  ; "activation_menu"
0054    ISNEP    1   0
0055    JMP      1 => 0058
0056    KSTR     1  19      ; "swipe_tap"
0057    TSETS    1   0  15  ; "activation_menu"
0058 => RET0     0   1

-- BYTECODE -- readerconfig.lua:51-51
0001    UGET     0   0      ; self
0002    MOV      1   0
0003    TGETS    0   0   0  ; "onTapShowConfigMenu"
0004    CALLT    0   2

-- BYTECODE -- readerconfig.lua:64-64
0001    UGET     1   0      ; self
0002    MOV      2   1
0003    TGETS    1   1   0  ; "onSwipeShowConfigMenu"
0004    MOV      3   0
0005    CALLT    1   3

-- BYTECODE -- readerconfig.lua:77-77
0001    UGET     1   0      ; self
0002    MOV      2   1
0003    TGETS    1   1   0  ; "onSwipeShowConfigMenu"
0004    MOV      3   0
0005    CALLT    1   3

-- BYTECODE -- readerconfig.lua:38-80
0001    TGETS    1   0   0  ; "ui"
0002    MOV      2   1
0003    TGETS    1   1   1  ; "registerTouchZones"
0004    TNEW     3   4
0005    TDUP     4   2
0006    TDUP     5   5
0007    GGET     6   3      ; "DTAP_ZONE_CONFIG"
0008    TGETS    6   6   4  ; "x"
0009    TSETS    6   5   6  ; "ratio_x"
0010    GGET     6   3      ; "DTAP_ZONE_CONFIG"
0011    TGETS    6   6   7  ; "y"
0012    TSETS    6   5   8  ; "ratio_y"
0013    GGET     6   3      ; "DTAP_ZONE_CONFIG"
0014    TGETS    6   6   9  ; "w"
0015    TSETS    6   5  10  ; "ratio_w"
0016    GGET     6   3      ; "DTAP_ZONE_CONFIG"
0017    TGETS    6   6  11  ; "h"
0018    TSETS    6   5  12  ; "ratio_h"
0019    TSETS    5   4  13  ; "screen_zone"
0020    TDUP     5  14
0021    TSETS    5   4  15  ; "overrides"
0022    FNEW     5  16      ; readerconfig.lua:51
0023    TSETS    5   4  17  ; "handler"
0024    TSETB    4   3   1
0025    TDUP     4  18
0026    TDUP     5  19
0027    GGET     6   3      ; "DTAP_ZONE_CONFIG"
0028    TGETS    6   6   4  ; "x"
0029    TSETS    6   5   6  ; "ratio_x"
0030    GGET     6   3      ; "DTAP_ZONE_CONFIG"
0031    TGETS    6   6   7  ; "y"
0032    TSETS    6   5   8  ; "ratio_y"
0033    GGET     6   3      ; "DTAP_ZONE_CONFIG"
0034    TGETS    6   6   9  ; "w"
0035    TSETS    6   5  10  ; "ratio_w"
0036    GGET     6   3      ; "DTAP_ZONE_CONFIG"
0037    TGETS    6   6  11  ; "h"
0038    TSETS    6   5  12  ; "ratio_h"
0039    TSETS    5   4  13  ; "screen_zone"
0040    TDUP     5  20
0041    TSETS    5   4  15  ; "overrides"
0042    FNEW     5  21      ; readerconfig.lua:64
0043    TSETS    5   4  17  ; "handler"
0044    TSETB    4   3   2
0045    TDUP     4  22
0046    TDUP     5  23
0047    GGET     6   3      ; "DTAP_ZONE_CONFIG"
0048    TGETS    6   6   4  ; "x"
0049    TSETS    6   5   6  ; "ratio_x"
0050    GGET     6   3      ; "DTAP_ZONE_CONFIG"
0051    TGETS    6   6   7  ; "y"
0052    TSETS    6   5   8  ; "ratio_y"
0053    GGET     6   3      ; "DTAP_ZONE_CONFIG"
0054    TGETS    6   6   9  ; "w"
0055    TSETS    6   5  10  ; "ratio_w"
0056    GGET     6   3      ; "DTAP_ZONE_CONFIG"
0057    TGETS    6   6  11  ; "h"
0058    TSETS    6   5  12  ; "ratio_h"
0059    TSETS    5   4  13  ; "screen_zone"
0060    TDUP     5  24
0061    TSETS    5   4  15  ; "overrides"
0062    FNEW     5  25      ; readerconfig.lua:77
0063    TSETS    5   4  17  ; "handler"
0064    TSETB    4   3   3
0065    CALL     1   1   3
0066    UCLO     0 => 0067
0067 => RET0     0   1

-- BYTECODE -- readerconfig.lua:90-90
0001    UGET     0   0      ; self
0002    MOV      1   0
0003    TGETS    0   0   0  ; "onCloseCallback"
0004    CALL     0   1   2
0005    RET0     0   1

-- BYTECODE -- readerconfig.lua:82-98
0001    UGET     1   0      ; ConfigDialog
0002    MOV      2   1
0003    TGETS    1   1   1  ; "new"
0004    TDUP     3   4
0005    TGETS    4   0   2  ; "dimen"
0006    MOV      5   4
0007    TGETS    4   4   3  ; "copy"
0008    CALL     4   2   2
0009    TSETS    4   3   2  ; "dimen"
0010    TGETS    4   0   5  ; "document"
0011    TSETS    4   3   5  ; "document"
0012    TGETS    4   0   6  ; "ui"
0013    TSETS    4   3   6  ; "ui"
0014    TGETS    4   0   7  ; "configurable"
0015    TSETS    4   3   7  ; "configurable"
0016    TGETS    4   0   8  ; "options"
0017    TSETS    4   3   9  ; "config_options"
0018    FNEW     4  10      ; readerconfig.lua:90
0019    TSETS    4   3  11  ; "close_callback"
0020    CALL     1   2   3
0021    TSETS    1   0   0  ; "config_dialog"
0022    TGETS    1   0   6  ; "ui"
0023    MOV      2   1
0024    TGETS    1   1  12  ; "handleEvent"
0025    UGET     3   1      ; Event
0026    MOV      4   3
0027    TGETS    3   3   1  ; "new"
0028    KSTR     5  13      ; "DisableHinting"
0029    CALL     3   0   3
0030    CALLM    1   1   1
0031    TGETS    1   0   0  ; "config_dialog"
0032    MOV      2   1
0033    TGETS    1   1  14  ; "onShowConfigPanel"
0034    TGETS    3   0  15  ; "last_panel_index"
0035    CALL     1   1   3
0036    UGET     1   2      ; UIManager
0037    MOV      2   1
0038    TGETS    1   1  16  ; "show"
0039    TGETS    3   0   0  ; "config_dialog"
0040    CALL     1   1   3
0041    KPRI     1   2
0042    UCLO     0 => 0043
0043 => RET1     1   2

-- BYTECODE -- readerconfig.lua:100-105
0001    TGETS    1   0   0  ; "activation_menu"
0002    ISEQS    1   1      ; "swipe"
0003    JMP      1 => 0009
0004    MOV      2   0
0005    TGETS    1   0   2  ; "onShowConfigMenu"
0006    CALL     1   1   2
0007    KPRI     1   2
0008    RET1     1   2
0009 => RET0     0   1

-- BYTECODE -- readerconfig.lua:107-112
0001    TGETS    2   0   0  ; "activation_menu"
0002    ISEQS    2   1      ; "tap"
0003    JMP      2 => 0012
0004    TGETS    2   1   2  ; "direction"
0005    ISNES    2   3      ; "north"
0006    JMP      2 => 0012
0007    MOV      3   0
0008    TGETS    2   0   4  ; "onShowConfigMenu"
0009    CALL     2   1   2
0010    KPRI     2   2
0011    RET1     2   2
0012 => RET0     0   1

-- BYTECODE -- readerconfig.lua:114-120
0001    TGETS    2   0   0  ; "config_dialog"
0002    ISF          2
0003    JMP      3 => 0008
0004    TGETS    2   0   0  ; "config_dialog"
0005    MOV      3   2
0006    TGETS    2   2   1  ; "closeDialog"
0007    CALL     2   1   2
0008 => RET0     0   1

-- BYTECODE -- readerconfig.lua:122-126
0001    TGETS    1   0   1  ; "config_dialog"
0002    TGETS    1   1   2  ; "panel_index"
0003    TSETS    1   0   0  ; "last_panel_index"
0004    KPRI     1   0
0005    TSETS    1   0   1  ; "config_dialog"
0006    TGETS    1   0   3  ; "ui"
0007    MOV      2   1
0008    TGETS    1   1   4  ; "handleEvent"
0009    UGET     3   0      ; Event
0010    MOV      4   3
0011    TGETS    3   3   5  ; "new"
0012    KSTR     5   6      ; "RestoreHinting"
0013    CALL     3   0   3
0014    CALLM    1   1   1
0015    RET0     0   1

-- BYTECODE -- readerconfig.lua:129-133
0001    TGETS    1   0   0  ; "config_dialog"
0002    ISF          1
0003    JMP      2 => 0008
0004    TGETS    1   0   0  ; "config_dialog"
0005    MOV      2   1
0006    TGETS    1   1   1  ; "closeDialog"
0007    CALL     1   1   2
0008 => RET0     0   1

-- BYTECODE -- readerconfig.lua:135-142
0001    TGETS    2   0   0  ; "configurable"
0002    MOV      3   2
0003    TGETS    2   2   1  ; "loadSettings"
0004    MOV      4   1
0005    TGETS    5   0   2  ; "options"
0006    TGETS    5   5   3  ; "prefix"
0007    KSTR     6   4      ; "_"
0008    CAT      5   5   6
0009    CALL     2   1   4
0010    MOV      3   1
0011    TGETS    2   1   5  ; "readSetting"
0012    KSTR     4   6      ; "config_panel_index"
0013    CALL     2   2   3
0014    ISF          2
0015    JMP      3 => 0023
0016    GGET     3   7      ; "math"
0017    TGETS    3   3   8  ; "min"
0018    MOV      4   2
0019    TGETS    5   0   2  ; "options"
0020    LEN      5   5
0021    CALL     3   2   3
0022    MOV      2   3
0023 => ISTC     3   2
0024    JMP      3 => 0026
0025    KSHORT   3   1
0026 => TSETS    3   0   9  ; "last_panel_index"
0027    RET0     0   1

-- BYTECODE -- readerconfig.lua:144-147
0001    TGETS    1   0   0  ; "configurable"
0002    MOV      2   1
0003    TGETS    1   1   1  ; "saveSettings"
0004    TGETS    3   0   2  ; "ui"
0005    TGETS    3   3   3  ; "doc_settings"
0006    TGETS    4   0   4  ; "options"
0007    TGETS    4   4   5  ; "prefix"
0008    KSTR     5   6      ; "_"
0009    CAT      4   4   5
0010    CALL     1   1   4
0011    TGETS    1   0   2  ; "ui"
0012    TGETS    1   1   3  ; "doc_settings"
0013    MOV      2   1
0014    TGETS    1   1   7  ; "saveSetting"
0015    KSTR     3   8      ; "config_panel_index"
0016    TGETS    4   0   9  ; "last_panel_index"
0017    CALL     1   1   4
0018    RET0     0   1

-- BYTECODE -- readerconfig.lua:0-150
0001    GGET     0   0      ; "require"
0002    KSTR     1   1      ; "ui/widget/configdialog"
0003    CALL     0   2   2
0004    GGET     1   0      ; "require"
0005    KSTR     2   2      ; "device"
0006    CALL     1   2   2
0007    GGET     2   0      ; "require"
0008    KSTR     3   3      ; "ui/event"
0009    CALL     2   2   2
0010    GGET     3   0      ; "require"
0011    KSTR     4   4      ; "ui/geometry"
0012    CALL     3   2   2
0013    GGET     4   0      ; "require"
0014    KSTR     5   5      ; "ui/widget/container/inputcontainer"
0015    CALL     4   2   2
0016    GGET     5   0      ; "require"
0017    KSTR     6   6      ; "ui/uimanager"
0018    CALL     5   2   2
0019    GGET     6   0      ; "require"
0020    KSTR     7   7      ; "ui/data/creoptions"
0021    CALL     6   2   2
0022    GGET     7   0      ; "require"
0023    KSTR     8   8      ; "ui/data/koptoptions"
0024    CALL     7   2   2
0025    GGET     8   0      ; "require"
0026    KSTR     9   9      ; "gettext"
0027    CALL     8   2   2
0028    MOV     10   4
0029    TGETS    9   4  10  ; "new"
0030    TDUP    11  11
0031    CALL     9   2   3
0032    FNEW    10  13      ; readerconfig.lua:15
0033    TSETS   10   9  12  ; "init"
0034    FNEW    10  15      ; readerconfig.lua:38
0035    TSETS   10   9  14  ; "initGesListener"
0036    FNEW    10  17      ; readerconfig.lua:82
0037    TSETS   10   9  16  ; "onShowConfigMenu"
0038    FNEW    10  19      ; readerconfig.lua:100
0039    TSETS   10   9  18  ; "onTapShowConfigMenu"
0040    FNEW    10  21      ; readerconfig.lua:107
0041    TSETS   10   9  20  ; "onSwipeShowConfigMenu"
0042    FNEW    10  23      ; readerconfig.lua:114
0043    TSETS   10   9  22  ; "onSetDimensions"
0044    FNEW    10  25      ; readerconfig.lua:122
0045    TSETS   10   9  24  ; "onCloseCallback"
0046    FNEW    10  27      ; readerconfig.lua:129
0047    TSETS   10   9  26  ; "onCloseConfigMenu"
0048    FNEW    10  29      ; readerconfig.lua:135
0049    TSETS   10   9  28  ; "onReadSettings"
0050    FNEW    10  31      ; readerconfig.lua:144
0051    TSETS   10   9  30  ; "onSaveSettings"
0052    UCLO     0 => 0053
0053 => RET1     9   2

