
main <./frontend/apps/reader/modules/readerpanning.lua:0,0> (27 instructions, 108 bytes at 0x7f822c406900)
0+ params, 7 slots, 0 upvalues, 4 locals, 17 constants, 3 functions
	1	[1]	GETGLOBAL	0 -1	; require
	2	[1]	LOADK    	1 -2	; "ui/widget/container/inputcontainer"
	3	[1]	CALL     	0 2 2
	4	[2]	GETGLOBAL	1 -1	; require
	5	[2]	LOADK    	2 -3	; "device"
	6	[2]	CALL     	1 2 2
	7	[3]	GETGLOBAL	2 -1	; require
	8	[3]	LOADK    	3 -4	; "gettext"
	9	[3]	CALL     	2 2 2
	10	[5]	SELF     	3 0 -5	; "new"
	11	[5]	NEWTABLE 	5 0 1
	12	[7]	NEWTABLE 	6 0 4
	13	[8]	SETTABLE 	6 -7 -8	; "normal" 50
	14	[9]	SETTABLE 	6 -9 -10	; "alt" 25
	15	[10]	SETTABLE 	6 -11 -12	; "shift" 10
	16	[11]	SETTABLE 	6 -13 -14	; "altshift" 5
	17	[12]	SETTABLE 	5 -6 6	; "panning_steps" -
	18	[5]	CALL     	3 3 2
	19	[33]	CLOSURE  	4 0	; 0x7f822c406e40
	20	[33]	MOVE     	0 1
	21	[15]	SETTABLE 	3 -15 4	; "init" -
	22	[37]	CLOSURE  	4 1	; 0x7f822c407140
	23	[35]	SETTABLE 	3 -16 4	; "onSetDimensions" -
	24	[46]	CLOSURE  	4 2	; 0x7f822c407040
	25	[39]	SETTABLE 	3 -17 4	; "onPanning" -
	26	[48]	RETURN   	3 2
	27	[48]	RETURN   	0 1

function <./frontend/apps/reader/modules/readerpanning.lua:15,33> (60 instructions, 240 bytes at 0x7f822c406e40)
1 param, 7 slots, 1 upvalue, 1 local, 21 constants, 0 functions
	1	[16]	GETUPVAL 	1 0	; Device
	2	[16]	SELF     	1 1 -1	; "hasKeyboard"
	3	[16]	CALL     	1 2 2
	4	[16]	TEST     	1 0 0
	5	[16]	JMP      	54	; to 60
	6	[17]	NEWTABLE 	1 0 4
	7	[19]	NEWTABLE 	2 1 3
	8	[19]	NEWTABLE 	3 1 0
	9	[20]	LOADK    	4 -4	; "Up"
	10	[20]	SETLIST  	3 1 1	; 1
	11	[20]	SETTABLE 	2 -5 -6	; "doc" "move visible area up"
	12	[21]	SETTABLE 	2 -7 -8	; "event" "Panning"
	13	[21]	NEWTABLE 	4 2 0
	14	[21]	LOADK    	5 -10	; 0
	15	[21]	LOADK    	6 -11	; -1
	16	[21]	SETLIST  	4 2 1	; 1
	17	[21]	SETTABLE 	2 -9 4	; "args" -
	18	[21]	SETLIST  	2 1 1	; 1
	19	[21]	SETTABLE 	1 -3 2	; "MoveUp" -
	20	[22]	NEWTABLE 	2 1 3
	21	[22]	NEWTABLE 	3 1 0
	22	[23]	LOADK    	4 -13	; "Down"
	23	[23]	SETLIST  	3 1 1	; 1
	24	[23]	SETTABLE 	2 -5 -14	; "doc" "move visible area down"
	25	[24]	SETTABLE 	2 -7 -8	; "event" "Panning"
	26	[24]	NEWTABLE 	4 2 0
	27	[24]	LOADK    	5 -10	; 0
	28	[24]	LOADK    	6 -15	; 1
	29	[24]	SETLIST  	4 2 1	; 1
	30	[24]	SETTABLE 	2 -9 4	; "args" -
	31	[24]	SETLIST  	2 1 1	; 1
	32	[24]	SETTABLE 	1 -12 2	; "MoveDown" -
	33	[25]	NEWTABLE 	2 1 3
	34	[25]	NEWTABLE 	3 1 0
	35	[26]	LOADK    	4 -17	; "Left"
	36	[26]	SETLIST  	3 1 1	; 1
	37	[26]	SETTABLE 	2 -5 -18	; "doc" "move visible area left"
	38	[27]	SETTABLE 	2 -7 -8	; "event" "Panning"
	39	[27]	NEWTABLE 	4 2 0
	40	[27]	LOADK    	5 -11	; -1
	41	[27]	LOADK    	6 -10	; 0
	42	[27]	SETLIST  	4 2 1	; 1
	43	[27]	SETTABLE 	2 -9 4	; "args" -
	44	[27]	SETLIST  	2 1 1	; 1
	45	[27]	SETTABLE 	1 -16 2	; "MoveLeft" -
	46	[28]	NEWTABLE 	2 1 3
	47	[28]	NEWTABLE 	3 1 0
	48	[29]	LOADK    	4 -20	; "Right"
	49	[29]	SETLIST  	3 1 1	; 1
	50	[29]	SETTABLE 	2 -5 -21	; "doc" "move visible area right"
	51	[30]	SETTABLE 	2 -7 -8	; "event" "Panning"
	52	[30]	NEWTABLE 	4 2 0
	53	[30]	LOADK    	5 -15	; 1
	54	[30]	LOADK    	6 -10	; 0
	55	[30]	SETLIST  	4 2 1	; 1
	56	[30]	SETTABLE 	2 -9 4	; "args" -
	57	[30]	SETLIST  	2 1 1	; 1
	58	[30]	SETTABLE 	1 -19 2	; "MoveRight" -
	59	[31]	SETTABLE 	0 -2 1	; "key_events" -
	60	[33]	RETURN   	0 1

function <./frontend/apps/reader/modules/readerpanning.lua:35,37> (2 instructions, 8 bytes at 0x7f822c407140)
2 params, 2 slots, 0 upvalues, 2 locals, 1 constant, 0 functions
	1	[36]	SETTABLE 	0 -1 1	; "dimen" -
	2	[37]	RETURN   	0 1

function <./frontend/apps/reader/modules/readerpanning.lua:39,46> (23 instructions, 92 bytes at 0x7f822c407040)
3 params, 10 slots, 0 upvalues, 5 locals, 9 constants, 0 functions
	1	[40]	GETGLOBAL	3 -1	; unpack
	2	[40]	MOVE     	4 1
	3	[40]	CALL     	3 2 3
	4	[42]	GETTABLE 	5 0 -2	; "view"
	5	[42]	SELF     	5 5 -3	; "PanningUpdate"
	6	[43]	GETTABLE 	7 0 -4	; "panning_steps"
	7	[43]	GETTABLE 	7 7 -5	; "normal"
	8	[43]	MUL      	7 3 7
	9	[43]	GETTABLE 	8 0 -6	; "dimen"
	10	[43]	GETTABLE 	8 8 -7	; "w"
	11	[43]	MUL      	7 7 8
	12	[43]	DIV      	7 7 -8	; - 100
	13	[44]	GETTABLE 	8 0 -4	; "panning_steps"
	14	[44]	GETTABLE 	8 8 -5	; "normal"
	15	[44]	MUL      	8 4 8
	16	[44]	GETTABLE 	9 0 -6	; "dimen"
	17	[44]	GETTABLE 	9 9 -9	; "h"
	18	[44]	MUL      	8 8 9
	19	[44]	DIV      	8 8 -8	; - 100
	20	[42]	CALL     	5 4 1
	21	[45]	LOADBOOL 	5 1 0
	22	[45]	RETURN   	5 2
	23	[46]	RETURN   	0 1
