
main <./frontend/apps/reader/modules/readergoto.lua:0,0> (62 instructions, 248 bytes at 0x7f97dcc068f0)
0+ params, 12 slots, 0 upvalues, 8 locals, 22 constants, 8 functions
	1	[1]	GETGLOBAL	0 -1	; require
	2	[1]	LOADK    	1 -2	; "ui/event"
	3	[1]	CALL     	0 2 2
	4	[2]	GETGLOBAL	1 -1	; require
	5	[2]	LOADK    	2 -3	; "ui/widget/container/inputcontainer"
	6	[2]	CALL     	1 2 2
	7	[3]	GETGLOBAL	2 -1	; require
	8	[3]	LOADK    	3 -4	; "ui/widget/inputdialog"
	9	[3]	CALL     	2 2 2
	10	[4]	GETGLOBAL	3 -1	; require
	11	[4]	LOADK    	4 -5	; "apps/reader/skimtowidget"
	12	[4]	CALL     	3 2 2
	13	[5]	GETGLOBAL	4 -1	; require
	14	[5]	LOADK    	5 -6	; "ui/uimanager"
	15	[5]	CALL     	4 2 2
	16	[6]	GETGLOBAL	5 -1	; require
	17	[6]	LOADK    	6 -7	; "gettext"
	18	[6]	CALL     	5 2 2
	19	[7]	GETGLOBAL	6 -1	; require
	20	[7]	LOADK    	7 -8	; "ffi/util"
	21	[7]	CALL     	6 2 2
	22	[7]	GETTABLE 	6 6 -9	; "template"
	23	[9]	SELF     	7 1 -10	; "new"
	24	[9]	NEWTABLE 	9 0 2
	25	[10]	MOVE     	10 5
	26	[10]	LOADK    	11 -12	; "Go to"
	27	[10]	CALL     	10 2 2
	28	[10]	SETTABLE 	9 -11 10	; "goto_menu_title" -
	29	[11]	MOVE     	10 5
	30	[11]	LOADK    	11 -14	; "Skim document"
	31	[11]	CALL     	10 2 2
	32	[11]	SETTABLE 	9 -13 10	; "skim_menu_title" -
	33	[9]	CALL     	7 3 2
	34	[16]	CLOSURE  	8 0	; 0x7f97dcc07100
	35	[14]	SETTABLE 	7 -15 8	; "init" -
	36	[32]	CLOSURE  	8 1	; 0x7f97dcc071b0
	37	[18]	SETTABLE 	7 -16 8	; "addToMainMenu" -
	38	[98]	CLOSURE  	8 2	; 0x7f97dcc06de0
	39	[98]	MOVE     	0 5
	40	[98]	MOVE     	0 6
	41	[98]	MOVE     	0 2
	42	[98]	MOVE     	0 3
	43	[98]	MOVE     	0 4
	44	[34]	SETTABLE 	7 -17 8	; "onShowGotoDialog" -
	45	[110]	CLOSURE  	8 3	; 0x7f97dcc067d0
	46	[110]	MOVE     	0 3
	47	[110]	MOVE     	0 4
	48	[100]	SETTABLE 	7 -18 8	; "onShowSkimtoDialog" -
	49	[114]	CLOSURE  	8 4	; 0x7f97dcc07250
	50	[114]	MOVE     	0 4
	51	[112]	SETTABLE 	7 -19 8	; "close" -
	52	[138]	CLOSURE  	8 5	; 0x7f97dcc07310
	53	[138]	MOVE     	0 0
	54	[116]	SETTABLE 	7 -20 8	; "gotoPage" -
	55	[144]	CLOSURE  	8 6	; 0x7f97dcc09c70
	56	[144]	MOVE     	0 0
	57	[140]	SETTABLE 	7 -21 8	; "onGoToBeginning" -
	58	[153]	CLOSURE  	8 7	; 0x7f97dcc0a5b0
	59	[153]	MOVE     	0 0
	60	[146]	SETTABLE 	7 -22 8	; "onGoToEnd" -
	61	[155]	RETURN   	7 2
	62	[155]	RETURN   	0 1

function <./frontend/apps/reader/modules/readergoto.lua:14,16> (6 instructions, 24 bytes at 0x7f97dcc07100)
1 param, 4 slots, 0 upvalues, 1 local, 3 constants, 0 functions
	1	[15]	GETTABLE 	1 0 -1	; "ui"
	2	[15]	GETTABLE 	1 1 -2	; "menu"
	3	[15]	SELF     	1 1 -3	; "registerToMainMenu"
	4	[15]	MOVE     	3 0
	5	[15]	CALL     	1 3 1
	6	[16]	RETURN   	0 1

function <./frontend/apps/reader/modules/readergoto.lua:18,32> (15 instructions, 60 bytes at 0x7f97dcc071b0)
2 params, 4 slots, 0 upvalues, 2 locals, 6 constants, 2 functions
	1	[20]	NEWTABLE 	2 0 2
	2	[21]	GETTABLE 	3 0 -3	; "goto_menu_title"
	3	[21]	SETTABLE 	2 -2 3	; "text" -
	4	[24]	CLOSURE  	3 0	; 0x7f97dcc076e0
	5	[24]	MOVE     	0 0
	6	[24]	SETTABLE 	2 -4 3	; "callback" -
	7	[25]	SETTABLE 	1 -1 2	; "go_to" -
	8	[26]	NEWTABLE 	2 0 2
	9	[27]	GETTABLE 	3 0 -6	; "skim_menu_title"
	10	[27]	SETTABLE 	2 -2 3	; "text" -
	11	[30]	CLOSURE  	3 1	; 0x7f97dcc075a0
	12	[30]	MOVE     	0 0
	13	[30]	SETTABLE 	2 -4 3	; "callback" -
	14	[31]	SETTABLE 	1 -5 2	; "skim_to" -
	15	[32]	RETURN   	0 1

function <./frontend/apps/reader/modules/readergoto.lua:22,24> (4 instructions, 16 bytes at 0x7f97dcc076e0)
0 params, 2 slots, 1 upvalue, 0 locals, 1 constant, 0 functions
	1	[23]	GETUPVAL 	0 0	; self
	2	[23]	SELF     	0 0 -1	; "onShowGotoDialog"
	3	[23]	CALL     	0 2 1
	4	[24]	RETURN   	0 1

function <./frontend/apps/reader/modules/readergoto.lua:28,30> (4 instructions, 16 bytes at 0x7f97dcc075a0)
0 params, 2 slots, 1 upvalue, 0 locals, 1 constant, 0 functions
	1	[29]	GETUPVAL 	0 0	; self
	2	[29]	SELF     	0 0 -1	; "onShowSkimtoDialog"
	3	[29]	CALL     	0 2 1
	4	[30]	RETURN   	0 1

function <./frontend/apps/reader/modules/readergoto.lua:34,98> (122 instructions, 488 bytes at 0x7f97dcc06de0)
1 param, 14 slots, 5 upvalues, 5 locals, 35 constants, 4 functions
	1	[36]	GETTABLE 	4 0 -1	; "document"
	2	[36]	GETTABLE 	4 4 -2	; "info"
	3	[36]	GETTABLE 	4 4 -3	; "has_pages"
	4	[36]	TEST     	4 0 0
	5	[36]	JMP      	18	; to 24
	6	[37]	GETUPVAL 	4 0	; _
	7	[37]	LOADK    	5 -4	; "Go to Page"
	8	[37]	CALL     	4 2 2
	9	[37]	MOVE     	1 4
	10	[38]	NEWTABLE 	4 0 3
	11	[39]	SETTABLE 	4 -5 -6	; "is_enter_default" true
	12	[40]	GETUPVAL 	5 0	; _
	13	[40]	LOADK    	6 -8	; "Page"
	14	[40]	CALL     	5 2 2
	15	[40]	SETTABLE 	4 -7 5	; "text" -
	16	[41]	CLOSURE  	5 0	; 0x7f97dcc08000
	17	[41]	MOVE     	0 0
	18	[41]	SETTABLE 	4 -9 5	; "callback" -
	19	[42]	MOVE     	2 4
	20	[43]	GETTABLE 	4 0 -10	; "ui"
	21	[43]	GETTABLE 	4 4 -11	; "paging"
	22	[43]	GETTABLE 	3 4 -12	; "current_page"
	23	[43]	JMP      	18	; to 42
	24	[45]	GETUPVAL 	4 0	; _
	25	[45]	LOADK    	5 -13	; "Go to Location"
	26	[45]	CALL     	4 2 2
	27	[45]	MOVE     	1 4
	28	[46]	NEWTABLE 	4 0 3
	29	[47]	SETTABLE 	4 -5 -6	; "is_enter_default" true
	30	[48]	GETUPVAL 	5 0	; _
	31	[48]	LOADK    	6 -14	; "Location"
	32	[48]	CALL     	5 2 2
	33	[48]	SETTABLE 	4 -7 5	; "text" -
	34	[49]	CLOSURE  	5 1	; 0x7f97dcc08440
	35	[49]	MOVE     	0 0
	36	[49]	SETTABLE 	4 -9 5	; "callback" -
	37	[50]	MOVE     	2 4
	38	[52]	GETTABLE 	4 0 -1	; "document"
	39	[52]	SELF     	4 4 -15	; "getCurrentPage"
	40	[52]	CALL     	4 2 2
	41	[52]	MOVE     	3 4
	42	[54]	LOADNIL  	4 4
	43	[55]	GETTABLE 	5 0 -10	; "ui"
	44	[55]	GETTABLE 	5 5 -16	; "pagemap"
	45	[55]	TEST     	5 0 0
	46	[55]	JMP      	26	; to 73
	47	[55]	GETTABLE 	5 0 -10	; "ui"
	48	[55]	GETTABLE 	5 5 -16	; "pagemap"
	49	[55]	SELF     	5 5 -17	; "wantsPageLabels"
	50	[55]	CALL     	5 2 2
	51	[55]	TEST     	5 0 0
	52	[55]	JMP      	20	; to 73
	53	[56]	GETUPVAL 	5 1	; T
	54	[56]	LOADK    	6 -18	; "@%1 (%2 - %3)"
	55	[56]	GETTABLE 	7 0 -10	; "ui"
	56	[56]	GETTABLE 	7 7 -16	; "pagemap"
	57	[56]	SELF     	7 7 -19	; "getCurrentPageLabel"
	58	[56]	LOADBOOL 	9 1 0
	59	[56]	CALL     	7 3 2
	60	[57]	GETTABLE 	8 0 -10	; "ui"
	61	[57]	GETTABLE 	8 8 -16	; "pagemap"
	62	[57]	SELF     	8 8 -20	; "getFirstPageLabel"
	63	[57]	LOADBOOL 	10 1 0
	64	[57]	CALL     	8 3 2
	65	[58]	GETTABLE 	9 0 -10	; "ui"
	66	[58]	GETTABLE 	9 9 -16	; "pagemap"
	67	[58]	SELF     	9 9 -21	; "getLastPageLabel"
	68	[58]	LOADBOOL 	11 1 0
	69	[58]	CALL     	9 3 0
	70	[56]	CALL     	5 0 2
	71	[58]	MOVE     	4 5
	72	[58]	JMP      	8	; to 81
	73	[60]	GETUPVAL 	5 1	; T
	74	[60]	LOADK    	6 -22	; "@%1 (1 - %2)"
	75	[60]	MOVE     	7 3
	76	[60]	GETTABLE 	8 0 -1	; "document"
	77	[60]	SELF     	8 8 -23	; "getPageCount"
	78	[60]	CALL     	8 2 0
	79	[60]	CALL     	5 0 2
	80	[60]	MOVE     	4 5
	81	[62]	GETUPVAL 	5 2	; InputDialog
	82	[62]	SELF     	5 5 -25	; "new"
	83	[62]	NEWTABLE 	7 0 4
	84	[63]	SETTABLE 	7 -26 1	; "title" -
	85	[64]	SETTABLE 	7 -27 4	; "input_hint" -
	86	[65]	NEWTABLE 	8 1 0
	87	[65]	NEWTABLE 	9 3 0
	88	[66]	NEWTABLE 	10 0 3
	89	[68]	GETUPVAL 	11 0	; _
	90	[68]	LOADK    	12 -29	; "Cancel"
	91	[68]	CALL     	11 2 2
	92	[68]	SETTABLE 	10 -7 11	; "text" -
	93	[69]	SETTABLE 	10 -30 -6	; "enabled" true
	94	[72]	CLOSURE  	11 2	; 0x7f97dcc08570
	95	[72]	MOVE     	0 0
	96	[72]	SETTABLE 	10 -9 11	; "callback" -
	97	[73]	NEWTABLE 	11 0 3
	98	[75]	GETUPVAL 	12 0	; _
	99	[75]	LOADK    	13 -31	; "Skim mode"
	100	[75]	CALL     	12 2 2
	101	[75]	SETTABLE 	11 -7 12	; "text" -
	102	[76]	SETTABLE 	11 -30 -6	; "enabled" true
	103	[89]	CLOSURE  	12 3	; 0x7f97dcc08f00
	104	[89]	MOVE     	0 0
	105	[89]	GETUPVAL 	0 3	; SkimToWidget
	106	[89]	GETUPVAL 	0 4	; UIManager
	107	[89]	SETTABLE 	11 -9 12	; "callback" -
	108	[92]	MOVE     	12 2
	109	[92]	SETLIST  	9 3 1	; 1
	110	[93]	SETLIST  	8 1 1	; 1
	111	[93]	SETTABLE 	7 -28 8	; "buttons" -
	112	[94]	SETTABLE 	7 -32 -33	; "input_type" "number"
	113	[62]	CALL     	5 3 2
	114	[95]	SETTABLE 	0 -24 5	; "goto_dialog" -
	115	[96]	GETUPVAL 	5 4	; UIManager
	116	[96]	SELF     	5 5 -34	; "show"
	117	[96]	GETTABLE 	7 0 -24	; "goto_dialog"
	118	[96]	CALL     	5 3 1
	119	[97]	GETTABLE 	5 0 -24	; "goto_dialog"
	120	[97]	SELF     	5 5 -35	; "onShowKeyboard"
	121	[97]	CALL     	5 2 1
	122	[98]	RETURN   	0 1

function <./frontend/apps/reader/modules/readergoto.lua:41,41> (4 instructions, 16 bytes at 0x7f97dcc08000)
0 params, 2 slots, 1 upvalue, 0 locals, 1 constant, 0 functions
	1	[41]	GETUPVAL 	0 0	; self
	2	[41]	SELF     	0 0 -1	; "gotoPage"
	3	[41]	CALL     	0 2 1
	4	[41]	RETURN   	0 1

function <./frontend/apps/reader/modules/readergoto.lua:49,49> (4 instructions, 16 bytes at 0x7f97dcc08440)
0 params, 2 slots, 1 upvalue, 0 locals, 1 constant, 0 functions
	1	[49]	GETUPVAL 	0 0	; self
	2	[49]	SELF     	0 0 -1	; "gotoPage"
	3	[49]	CALL     	0 2 1
	4	[49]	RETURN   	0 1

function <./frontend/apps/reader/modules/readergoto.lua:70,72> (4 instructions, 16 bytes at 0x7f97dcc08570)
0 params, 2 slots, 1 upvalue, 0 locals, 1 constant, 0 functions
	1	[71]	GETUPVAL 	0 0	; self
	2	[71]	SELF     	0 0 -1	; "close"
	3	[71]	CALL     	0 2 1
	4	[72]	RETURN   	0 1

function <./frontend/apps/reader/modules/readergoto.lua:77,89> (25 instructions, 100 bytes at 0x7f97dcc08f00)
0 params, 5 slots, 3 upvalues, 0 locals, 7 constants, 1 function
	1	[78]	GETUPVAL 	0 0	; self
	2	[78]	SELF     	0 0 -1	; "close"
	3	[78]	CALL     	0 2 1
	4	[79]	GETUPVAL 	0 0	; self
	5	[79]	GETUPVAL 	1 1	; SkimToWidget
	6	[79]	SELF     	1 1 -3	; "new"
	7	[79]	NEWTABLE 	3 0 3
	8	[80]	GETUPVAL 	4 0	; self
	9	[80]	GETTABLE 	4 4 -4	; "document"
	10	[80]	SETTABLE 	3 -4 4	; "document" -
	11	[81]	GETUPVAL 	4 0	; self
	12	[81]	GETTABLE 	4 4 -5	; "ui"
	13	[81]	SETTABLE 	3 -5 4	; "ui" -
	14	[85]	CLOSURE  	4 0	; 0x7f97dcc09080
	15	[85]	GETUPVAL 	0 2	; UIManager
	16	[85]	GETUPVAL 	0 0	; self
	17	[85]	SETTABLE 	3 -6 4	; "callback_switch_to_goto" -
	18	[79]	CALL     	1 3 2
	19	[86]	SETTABLE 	0 -2 1	; "skimto" -
	20	[87]	GETUPVAL 	0 2	; UIManager
	21	[87]	SELF     	0 0 -7	; "show"
	22	[87]	GETUPVAL 	2 0	; self
	23	[87]	GETTABLE 	2 2 -2	; "skimto"
	24	[87]	CALL     	0 3 1
	25	[89]	RETURN   	0 1

function <./frontend/apps/reader/modules/readergoto.lua:82,85> (9 instructions, 36 bytes at 0x7f97dcc09080)
0 params, 3 slots, 2 upvalues, 0 locals, 3 constants, 0 functions
	1	[83]	GETUPVAL 	0 0	; UIManager
	2	[83]	SELF     	0 0 -1	; "close"
	3	[83]	GETUPVAL 	2 1	; self
	4	[83]	GETTABLE 	2 2 -2	; "skimto"
	5	[83]	CALL     	0 3 1
	6	[84]	GETUPVAL 	0 1	; self
	7	[84]	SELF     	0 0 -3	; "onShowGotoDialog"
	8	[84]	CALL     	0 2 1
	9	[85]	RETURN   	0 1

function <./frontend/apps/reader/modules/readergoto.lua:100,110> (18 instructions, 72 bytes at 0x7f97dcc067d0)
1 param, 5 slots, 2 upvalues, 1 local, 6 constants, 1 function
	1	[101]	GETUPVAL 	1 0	; SkimToWidget
	2	[101]	SELF     	1 1 -2	; "new"
	3	[101]	NEWTABLE 	3 0 3
	4	[102]	GETTABLE 	4 0 -3	; "document"
	5	[102]	SETTABLE 	3 -3 4	; "document" -
	6	[103]	GETTABLE 	4 0 -4	; "ui"
	7	[103]	SETTABLE 	3 -4 4	; "ui" -
	8	[107]	CLOSURE  	4 0	; 0x7f97dcc08300
	9	[107]	GETUPVAL 	0 1	; UIManager
	10	[107]	MOVE     	0 0
	11	[107]	SETTABLE 	3 -5 4	; "callback_switch_to_goto" -
	12	[101]	CALL     	1 3 2
	13	[108]	SETTABLE 	0 -1 1	; "skimto" -
	14	[109]	GETUPVAL 	1 1	; UIManager
	15	[109]	SELF     	1 1 -6	; "show"
	16	[109]	GETTABLE 	3 0 -1	; "skimto"
	17	[109]	CALL     	1 3 1
	18	[110]	RETURN   	0 1

function <./frontend/apps/reader/modules/readergoto.lua:104,107> (9 instructions, 36 bytes at 0x7f97dcc08300)
0 params, 3 slots, 2 upvalues, 0 locals, 3 constants, 0 functions
	1	[105]	GETUPVAL 	0 0	; UIManager
	2	[105]	SELF     	0 0 -1	; "close"
	3	[105]	GETUPVAL 	2 1	; self
	4	[105]	GETTABLE 	2 2 -2	; "skimto"
	5	[105]	CALL     	0 3 1
	6	[106]	GETUPVAL 	0 1	; self
	7	[106]	SELF     	0 0 -3	; "onShowGotoDialog"
	8	[106]	CALL     	0 2 1
	9	[107]	RETURN   	0 1

function <./frontend/apps/reader/modules/readergoto.lua:112,114> (5 instructions, 20 bytes at 0x7f97dcc07250)
1 param, 4 slots, 1 upvalue, 1 local, 2 constants, 0 functions
	1	[113]	GETUPVAL 	1 0	; UIManager
	2	[113]	SELF     	1 1 -1	; "close"
	3	[113]	GETTABLE 	3 0 -2	; "goto_dialog"
	4	[113]	CALL     	1 3 1
	5	[114]	RETURN   	0 1

function <./frontend/apps/reader/modules/readergoto.lua:116,138> (70 instructions, 280 bytes at 0x7f97dcc07310)
1 param, 10 slots, 1 upvalue, 4 locals, 18 constants, 0 functions
	1	[117]	GETTABLE 	1 0 -1	; "goto_dialog"
	2	[117]	SELF     	1 1 -2	; "getInputText"
	3	[117]	CALL     	1 2 2
	4	[118]	SELF     	2 1 -3	; "sub"
	5	[118]	LOADK    	4 -4	; 1
	6	[118]	LOADK    	5 -4	; 1
	7	[118]	CALL     	2 4 2
	8	[119]	GETGLOBAL	3 -5	; tonumber
	9	[119]	MOVE     	4 1
	10	[119]	CALL     	3 2 2
	11	[120]	TEST     	3 0 0
	12	[120]	JMP      	57	; to 70
	13	[121]	GETTABLE 	4 0 -6	; "ui"
	14	[121]	GETTABLE 	4 4 -7	; "link"
	15	[121]	SELF     	4 4 -8	; "addCurrentLocationToStack"
	16	[121]	CALL     	4 2 1
	17	[122]	EQ       	1 2 -9	; - "+"
	18	[122]	JMP      	2	; to 21
	19	[122]	EQ       	0 2 -10	; - "-"
	20	[122]	JMP      	9	; to 30
	21	[123]	GETTABLE 	4 0 -6	; "ui"
	22	[123]	SELF     	4 4 -11	; "handleEvent"
	23	[123]	GETUPVAL 	6 0	; Event
	24	[123]	SELF     	6 6 -12	; "new"
	25	[123]	LOADK    	8 -13	; "GotoRelativePage"
	26	[123]	MOVE     	9 3
	27	[123]	CALL     	6 4 0
	28	[123]	CALL     	4 0 1
	29	[123]	JMP      	38	; to 68
	30	[125]	GETTABLE 	4 0 -6	; "ui"
	31	[125]	GETTABLE 	4 4 -14	; "pagemap"
	32	[125]	TEST     	4 0 0
	33	[125]	JMP      	26	; to 60
	34	[125]	GETTABLE 	4 0 -6	; "ui"
	35	[125]	GETTABLE 	4 4 -14	; "pagemap"
	36	[125]	SELF     	4 4 -15	; "wantsPageLabels"
	37	[125]	CALL     	4 2 2
	38	[125]	TEST     	4 0 0
	39	[125]	JMP      	20	; to 60
	40	[126]	GETTABLE 	4 0 -6	; "ui"
	41	[126]	GETTABLE 	4 4 -14	; "pagemap"
	42	[126]	SELF     	4 4 -16	; "getRenderedPageNumber"
	43	[126]	MOVE     	6 1
	44	[126]	LOADBOOL 	7 1 0
	45	[126]	CALL     	4 4 2
	46	[126]	MOVE     	3 4
	47	[127]	TEST     	3 0 0
	48	[127]	JMP      	9	; to 58
	49	[128]	GETTABLE 	4 0 -6	; "ui"
	50	[128]	SELF     	4 4 -11	; "handleEvent"
	51	[128]	GETUPVAL 	6 0	; Event
	52	[128]	SELF     	6 6 -12	; "new"
	53	[128]	LOADK    	8 -17	; "GotoPage"
	54	[128]	MOVE     	9 3
	55	[128]	CALL     	6 4 0
	56	[128]	CALL     	4 0 1
	57	[128]	JMP      	10	; to 68
	58	[130]	RETURN   	0 1
	59	[131]	JMP      	8	; to 68
	60	[133]	GETTABLE 	4 0 -6	; "ui"
	61	[133]	SELF     	4 4 -11	; "handleEvent"
	62	[133]	GETUPVAL 	6 0	; Event
	63	[133]	SELF     	6 6 -12	; "new"
	64	[133]	LOADK    	8 -17	; "GotoPage"
	65	[133]	MOVE     	9 3
	66	[133]	CALL     	6 4 0
	67	[133]	CALL     	4 0 1
	68	[136]	SELF     	4 0 -18	; "close"
	69	[136]	CALL     	4 2 1
	70	[138]	RETURN   	0 1

function <./frontend/apps/reader/modules/readergoto.lua:140,144> (15 instructions, 60 bytes at 0x7f97dcc09c70)
1 param, 7 slots, 1 upvalue, 1 local, 7 constants, 0 functions
	1	[141]	GETTABLE 	1 0 -1	; "ui"
	2	[141]	GETTABLE 	1 1 -2	; "link"
	3	[141]	SELF     	1 1 -3	; "addCurrentLocationToStack"
	4	[141]	CALL     	1 2 1
	5	[142]	GETTABLE 	1 0 -1	; "ui"
	6	[142]	SELF     	1 1 -4	; "handleEvent"
	7	[142]	GETUPVAL 	3 0	; Event
	8	[142]	SELF     	3 3 -5	; "new"
	9	[142]	LOADK    	5 -6	; "GotoPage"
	10	[142]	LOADK    	6 -7	; 1
	11	[142]	CALL     	3 4 0
	12	[142]	CALL     	1 0 1
	13	[143]	LOADBOOL 	1 1 0
	14	[143]	RETURN   	1 2
	15	[144]	RETURN   	0 1

function <./frontend/apps/reader/modules/readergoto.lua:146,153> (20 instructions, 80 bytes at 0x7f97dcc0a5b0)
1 param, 8 slots, 1 upvalue, 2 locals, 8 constants, 0 functions
	1	[147]	GETTABLE 	1 0 -1	; "document"
	2	[147]	SELF     	1 1 -2	; "getPageCount"
	3	[147]	CALL     	1 2 2
	4	[148]	TEST     	1 0 0
	5	[148]	JMP      	12	; to 18
	6	[149]	GETTABLE 	2 0 -3	; "ui"
	7	[149]	GETTABLE 	2 2 -4	; "link"
	8	[149]	SELF     	2 2 -5	; "addCurrentLocationToStack"
	9	[149]	CALL     	2 2 1
	10	[150]	GETTABLE 	2 0 -3	; "ui"
	11	[150]	SELF     	2 2 -6	; "handleEvent"
	12	[150]	GETUPVAL 	4 0	; Event
	13	[150]	SELF     	4 4 -7	; "new"
	14	[150]	LOADK    	6 -8	; "GotoPage"
	15	[150]	MOVE     	7 1
	16	[150]	CALL     	4 4 0
	17	[150]	CALL     	2 0 1
	18	[152]	LOADBOOL 	2 1 0
	19	[152]	RETURN   	2 2
	20	[153]	RETURN   	0 1
