
main <./frontend/apps/reader/modules/readerrotation.lua:0,0> (24 instructions, 96 bytes at 0x7f86dec06900)
0+ params, 7 slots, 0 upvalues, 5 locals, 10 constants, 2 functions
	1	[1]	GETGLOBAL	0 -1	; require
	2	[1]	LOADK    	1 -2	; "ui/widget/container/inputcontainer"
	3	[1]	CALL     	0 2 2
	4	[2]	GETGLOBAL	1 -1	; require
	5	[2]	LOADK    	2 -3	; "device"
	6	[2]	CALL     	1 2 2
	7	[3]	GETGLOBAL	2 -1	; require
	8	[3]	LOADK    	3 -4	; "ui/event"
	9	[3]	CALL     	2 2 2
	10	[4]	GETGLOBAL	3 -1	; require
	11	[4]	LOADK    	4 -5	; "gettext"
	12	[4]	CALL     	3 2 2
	13	[6]	SELF     	4 0 -6	; "new"
	14	[6]	NEWTABLE 	6 0 1
	15	[7]	SETTABLE 	6 -7 -8	; "current_rotation" 0
	16	[6]	CALL     	4 3 2
	17	[24]	CLOSURE  	5 0	; 0x7f86dec06c10
	18	[24]	MOVE     	0 1
	19	[10]	SETTABLE 	4 -9 5	; "init" -
	20	[32]	CLOSURE  	5 1	; 0x7f86dec07570
	21	[32]	MOVE     	0 2
	22	[28]	SETTABLE 	4 -10 5	; "onRotate" -
	23	[34]	RETURN   	4 2
	24	[34]	RETURN   	0 1

function <./frontend/apps/reader/modules/readerrotation.lua:10,24> (26 instructions, 104 bytes at 0x7f86dec06c10)
1 param, 5 slots, 1 upvalue, 1 local, 14 constants, 0 functions
	1	[11]	GETUPVAL 	1 0	; Device
	2	[11]	SELF     	1 1 -1	; "hasKeyboard"
	3	[11]	CALL     	1 2 2
	4	[11]	TEST     	1 0 0
	5	[11]	JMP      	20	; to 26
	6	[12]	NEWTABLE 	1 0 2
	7	[14]	NEWTABLE 	2 1 3
	8	[14]	NEWTABLE 	3 1 0
	9	[15]	LOADK    	4 -4	; "J"
	10	[15]	SETLIST  	3 1 1	; 1
	11	[16]	SETTABLE 	2 -5 -6	; "doc" "rotate left by 90 degrees"
	12	[17]	SETTABLE 	2 -7 -8	; "event" "Rotate"
	13	[17]	SETTABLE 	2 -9 -10	; "args" -90
	14	[17]	SETLIST  	2 1 1	; 1
	15	[17]	SETTABLE 	1 -3 2	; "RotateLeft" -
	16	[18]	NEWTABLE 	2 1 3
	17	[18]	NEWTABLE 	3 1 0
	18	[19]	LOADK    	4 -12	; "K"
	19	[19]	SETLIST  	3 1 1	; 1
	20	[20]	SETTABLE 	2 -5 -13	; "doc" "rotate right by 90 degrees"
	21	[21]	SETTABLE 	2 -7 -8	; "event" "Rotate"
	22	[21]	SETTABLE 	2 -9 -14	; "args" 90
	23	[21]	SETLIST  	2 1 1	; 1
	24	[21]	SETTABLE 	1 -11 2	; "RotateRight" -
	25	[22]	SETTABLE 	0 -2 1	; "key_events" -
	26	[24]	RETURN   	0 1

function <./frontend/apps/reader/modules/readerrotation.lua:28,32> (15 instructions, 60 bytes at 0x7f86dec07570)
2 params, 8 slots, 1 upvalue, 2 locals, 6 constants, 0 functions
	1	[29]	GETTABLE 	2 0 -1	; "current_rotation"
	2	[29]	ADD      	2 2 1
	3	[29]	MOD      	2 2 -2
	4	[29]	SETTABLE 	0 -1 2	; "current_rotation" -
	5	[30]	GETTABLE 	2 0 -3	; "ui"
	6	[30]	SELF     	2 2 -4	; "handleEvent"
	7	[30]	GETUPVAL 	4 0	; Event
	8	[30]	SELF     	4 4 -5	; "new"
	9	[30]	LOADK    	6 -6	; "RotationUpdate"
	10	[30]	GETTABLE 	7 0 -1	; "current_rotation"
	11	[30]	CALL     	4 4 0
	12	[30]	CALL     	2 0 1
	13	[31]	LOADBOOL 	2 1 0
	14	[31]	RETURN   	2 2
	15	[32]	RETURN   	0 1
