
main <./frontend/apps/reader/modules/readerfont.lua:0,0> (188 instructions, 752 bytes at 0x7fd49fc068f0)
0+ params, 34 slots, 0 upvalues, 19 locals, 61 constants, 20 functions
	1	[1]	GETGLOBAL	0 -1	; require
	2	[1]	LOADK    	1 -2	; "ui/bidi"
	3	[1]	CALL     	0 2 2
	4	[2]	GETGLOBAL	1 -1	; require
	5	[2]	LOADK    	2 -3	; "ui/widget/container/centercontainer"
	6	[2]	CALL     	1 2 2
	7	[3]	GETGLOBAL	2 -1	; require
	8	[3]	LOADK    	3 -4	; "ui/widget/confirmbox"
	9	[3]	CALL     	2 2 2
	10	[4]	GETGLOBAL	3 -1	; require
	11	[4]	LOADK    	4 -5	; "device"
	12	[4]	CALL     	3 2 2
	13	[5]	GETGLOBAL	4 -1	; require
	14	[5]	LOADK    	5 -6	; "ui/event"
	15	[5]	CALL     	4 2 2
	16	[6]	GETTABLE 	5 3 -7	; "input"
	17	[7]	GETGLOBAL	6 -1	; require
	18	[7]	LOADK    	7 -8	; "ui/widget/container/inputcontainer"
	19	[7]	CALL     	6 2 2
	20	[8]	GETGLOBAL	7 -1	; require
	21	[8]	LOADK    	8 -9	; "ui/widget/menu"
	22	[8]	CALL     	7 2 2
	23	[9]	GETGLOBAL	8 -1	; require
	24	[9]	LOADK    	9 -10	; "ui/widget/multiconfirmbox"
	25	[9]	CALL     	8 2 2
	26	[10]	GETGLOBAL	9 -1	; require
	27	[10]	LOADK    	10 -11	; "ui/widget/notification"
	28	[10]	CALL     	9 2 2
	29	[11]	GETGLOBAL	10 -1	; require
	30	[11]	LOADK    	11 -5	; "device"
	31	[11]	CALL     	10 2 2
	32	[11]	GETTABLE 	10 10 -12	; "screen"
	33	[12]	GETGLOBAL	11 -1	; require
	34	[12]	LOADK    	12 -13	; "ui/uimanager"
	35	[12]	CALL     	11 2 2
	36	[13]	GETGLOBAL	12 -1	; require
	37	[13]	LOADK    	13 -14	; "ffi/util"
	38	[13]	CALL     	12 2 2
	39	[13]	GETTABLE 	12 12 -15	; "template"
	40	[14]	GETGLOBAL	13 -1	; require
	41	[14]	LOADK    	14 -16	; "gettext"
	42	[14]	CALL     	13 2 2
	43	[15]	GETTABLE 	14 13 -17	; "pgettext"
	44	[17]	SELF     	15 6 -18	; "new"
	45	[17]	NEWTABLE 	17 0 8
	46	[18]	SETTABLE 	17 -19 -20	; "font_face" nil
	47	[19]	SETTABLE 	17 -21 -20	; "font_size" nil
	48	[20]	SETTABLE 	17 -22 -20	; "line_space_percent" nil
	49	[21]	MOVE     	18 13
	50	[21]	LOADK    	19 -24	; "Font"
	51	[21]	CALL     	18 2 2
	52	[21]	SETTABLE 	17 -23 18	; "font_menu_title" -
	53	[22]	SETTABLE 	17 -25 -20	; "face_table" nil
	54	[24]	SETTABLE 	17 -26 -20	; "gamma_index" nil
	55	[25]	NEWTABLE 	18 15 0
	56	[25]	LOADK    	19 -28	; 0
	57	[25]	LOADK    	20 -29	; 1
	58	[25]	LOADK    	21 -29	; 1
	59	[25]	LOADK    	22 -29	; 1
	60	[25]	LOADK    	23 -29	; 1
	61	[25]	LOADK    	24 -29	; 1
	62	[25]	LOADK    	25 -30	; 2
	63	[25]	LOADK    	26 -30	; 2
	64	[25]	LOADK    	27 -30	; 2
	65	[25]	LOADK    	28 -31	; 3
	66	[25]	LOADK    	29 -31	; 3
	67	[25]	LOADK    	30 -31	; 3
	68	[25]	LOADK    	31 -32	; 4
	69	[25]	LOADK    	32 -32	; 4
	70	[25]	LOADK    	33 -33	; 5
	71	[25]	SETLIST  	18 15 1	; 1
	72	[25]	SETTABLE 	17 -27 18	; "steps" -
	73	[26]	SELF     	18 10 -35	; "getWidth"
	74	[26]	CALL     	18 2 2
	75	[26]	GETGLOBAL	19 -36	; FRONTLIGHT_SENSITIVITY_DECREASE
	76	[26]	MUL      	18 18 19
	77	[26]	SETTABLE 	17 -34 18	; "gestureScale" -
	78	[17]	CALL     	15 3 2
	79	[90]	CLOSURE  	16 0	; 0x7fd49fc07070
	80	[90]	MOVE     	0 3
	81	[90]	MOVE     	0 5
	82	[90]	MOVE     	0 13
	83	[29]	SETTABLE 	15 -37 16	; "init" -
	84	[94]	CLOSURE  	16 1	; 0x7fd49fc08f70
	85	[92]	SETTABLE 	15 -38 16	; "onSetDimensions" -
	86	[149]	CLOSURE  	16 2	; 0x7fd49fc091d0
	87	[149]	MOVE     	0 10
	88	[149]	MOVE     	0 4
	89	[96]	SETTABLE 	15 -39 16	; "onReadSettings" -
	90	[176]	CLOSURE  	16 3	; 0x7fd49fc09c40
	91	[176]	MOVE     	0 7
	92	[176]	MOVE     	0 10
	93	[176]	MOVE     	0 1
	94	[176]	MOVE     	0 11
	95	[151]	SETTABLE 	15 -40 16	; "onShowFontMenu" -
	96	[190]	CLOSURE  	16 4	; 0x7fd49fc0a280
	97	[190]	MOVE     	0 4
	98	[181]	SETTABLE 	15 -41 16	; "onChangeSize" -
	99	[205]	CLOSURE  	16 5	; 0x7fd49fc0aa20
	100	[205]	MOVE     	0 10
	101	[205]	MOVE     	0 4
	102	[205]	MOVE     	0 11
	103	[205]	MOVE     	0 9
	104	[205]	MOVE     	0 12
	105	[205]	MOVE     	0 13
	106	[192]	SETTABLE 	15 -42 16	; "onSetFontSize" -
	107	[216]	CLOSURE  	16 6	; 0x7fd49fc0aba0
	108	[216]	MOVE     	0 11
	109	[216]	MOVE     	0 9
	110	[216]	MOVE     	0 12
	111	[216]	MOVE     	0 13
	112	[216]	MOVE     	0 4
	113	[207]	SETTABLE 	15 -43 16	; "onSetLineSpace" -
	114	[223]	CLOSURE  	16 7	; 0x7fd49fc0b220
	115	[223]	MOVE     	0 4
	116	[218]	SETTABLE 	15 -44 16	; "onToggleFontBolder" -
	117	[230]	CLOSURE  	16 8	; 0x7fd49fc0b780
	118	[230]	MOVE     	0 4
	119	[225]	SETTABLE 	15 -45 16	; "onSetFontHinting" -
	120	[237]	CLOSURE  	16 9	; 0x7fd49fc0bfe0
	121	[237]	MOVE     	0 4
	122	[232]	SETTABLE 	15 -46 16	; "onSetFontKerning" -
	123	[244]	CLOSURE  	16 10	; 0x7fd49fc0c1b0
	124	[244]	MOVE     	0 4
	125	[239]	SETTABLE 	15 -47 16	; "onSetWordSpacing" -
	126	[251]	CLOSURE  	16 11	; 0x7fd49fc0c6a0
	127	[251]	MOVE     	0 4
	128	[246]	SETTABLE 	15 -48 16	; "onSetWordExpansion" -
	129	[263]	CLOSURE  	16 12	; 0x7fd49fc09130
	130	[263]	MOVE     	0 11
	131	[263]	MOVE     	0 9
	132	[263]	MOVE     	0 12
	133	[263]	MOVE     	0 13
	134	[263]	MOVE     	0 4
	135	[253]	SETTABLE 	15 -49 16	; "onSetFontGamma" -
	136	[276]	CLOSURE  	16 13	; 0x7fd49fc08c30
	137	[265]	SETTABLE 	15 -50 16	; "onSaveSettings" -
	138	[290]	CLOSURE  	16 14	; 0x7fd49fc08bb0
	139	[290]	MOVE     	0 11
	140	[290]	MOVE     	0 9
	141	[290]	MOVE     	0 12
	142	[290]	MOVE     	0 13
	143	[290]	MOVE     	0 4
	144	[278]	SETTABLE 	15 -51 16	; "setFont" -
	145	[310]	CLOSURE  	16 15	; 0x7fd49fc076f0
	146	[310]	MOVE     	0 11
	147	[310]	MOVE     	0 8
	148	[310]	MOVE     	0 12
	149	[310]	MOVE     	0 13
	150	[310]	MOVE     	0 14
	151	[310]	MOVE     	0 4
	152	[292]	SETTABLE 	15 -52 16	; "makeDefault" -
	153	[321]	CLOSURE  	16 16	; 0x7fd49fc0c430
	154	[312]	SETTABLE 	15 -53 16	; "addToMainMenu" -
	155	[349]	CLOSURE  	16 17	; 0x7fd49fc0bc20
	156	[349]	MOVE     	0 9
	157	[349]	MOVE     	0 13
	158	[349]	MOVE     	0 11
	159	[325]	SETTABLE 	15 -54 16	; "onAdjustFontSize" -
	160	[395]	CLOSURE  	16 18	; 0x7fd49fc0e130
	161	[395]	MOVE     	0 3
	162	[395]	MOVE     	0 13
	163	[395]	MOVE     	0 4
	164	[395]	MOVE     	0 12
	165	[395]	MOVE     	0 11
	166	[395]	MOVE     	0 2
	167	[351]	SETTABLE 	15 -55 16	; "getFontSettingsTable" -
	168	[398]	LOADK    	16 -56	; "frontend/ui/elements/font-test-sample-default.html"
	169	[400]	GETGLOBAL	17 -1	; require
	170	[400]	LOADK    	18 -57	; "datastorage"
	171	[400]	CALL     	17 2 2
	172	[400]	SELF     	17 17 -58	; "getSettingsDir"
	173	[400]	CALL     	17 2 2
	174	[400]	LOADK    	18 -59	; "/font-test-sample.html"
	175	[400]	CONCAT   	17 17 18
	176	[402]	LOADK    	18 -60	; "font-test.html"
	177	[467]	CLOSURE  	19 19	; 0x7fd49fc10540
	178	[467]	MOVE     	0 17
	179	[467]	MOVE     	0 16
	180	[467]	MOVE     	0 18
	181	[467]	MOVE     	0 13
	182	[467]	MOVE     	0 11
	183	[467]	MOVE     	0 2
	184	[467]	MOVE     	0 12
	185	[467]	MOVE     	0 0
	186	[404]	SETTABLE 	15 -61 19	; "buildFontsTestDocument" -
	187	[469]	RETURN   	15 2
	188	[469]	RETURN   	0 1

function <./frontend/apps/reader/modules/readerfont.lua:29,90> (117 instructions, 468 bytes at 0x7fd49fc07070)
1 param, 11 slots, 3 upvalues, 7 locals, 44 constants, 4 functions
	1	[30]	GETUPVAL 	1 0	; Device
	2	[30]	SELF     	1 1 -1	; "hasKeyboard"
	3	[30]	CALL     	1 2 2
	4	[30]	TEST     	1 0 0
	5	[30]	JMP      	57	; to 63
	6	[32]	NEWTABLE 	1 0 5
	7	[33]	NEWTABLE 	2 1 1
	8	[33]	NEWTABLE 	3 1 0
	9	[33]	LOADK    	4 -4	; "F"
	10	[33]	SETLIST  	3 1 1	; 1
	11	[33]	SETTABLE 	2 -5 -6	; "doc" "show font menu"
	12	[33]	SETLIST  	2 1 1	; 1
	13	[33]	SETTABLE 	1 -3 2	; "ShowFontMenu" -
	14	[34]	NEWTABLE 	2 1 3
	15	[34]	NEWTABLE 	3 2 0
	16	[35]	LOADK    	4 -8	; "Shift"
	17	[35]	GETUPVAL 	5 1	; Input
	18	[35]	GETTABLE 	5 5 -9	; "group"
	19	[35]	GETTABLE 	5 5 -10	; "PgFwd"
	20	[35]	SETLIST  	3 2 1	; 1
	21	[36]	SETTABLE 	2 -5 -11	; "doc" "increase font size"
	22	[37]	SETTABLE 	2 -12 -13	; "event" "ChangeSize"
	23	[37]	SETTABLE 	2 -14 -15	; "args" "increase"
	24	[37]	SETLIST  	2 1 1	; 1
	25	[37]	SETTABLE 	1 -7 2	; "IncreaseSize" -
	26	[38]	NEWTABLE 	2 1 3
	27	[38]	NEWTABLE 	3 2 0
	28	[39]	LOADK    	4 -8	; "Shift"
	29	[39]	GETUPVAL 	5 1	; Input
	30	[39]	GETTABLE 	5 5 -9	; "group"
	31	[39]	GETTABLE 	5 5 -17	; "PgBack"
	32	[39]	SETLIST  	3 2 1	; 1
	33	[40]	SETTABLE 	2 -5 -18	; "doc" "decrease font size"
	34	[41]	SETTABLE 	2 -12 -13	; "event" "ChangeSize"
	35	[41]	SETTABLE 	2 -14 -19	; "args" "decrease"
	36	[41]	SETLIST  	2 1 1	; 1
	37	[41]	SETTABLE 	1 -16 2	; "DecreaseSize" -
	38	[42]	NEWTABLE 	2 1 3
	39	[42]	NEWTABLE 	3 2 0
	40	[43]	LOADK    	4 -21	; "Alt"
	41	[43]	GETUPVAL 	5 1	; Input
	42	[43]	GETTABLE 	5 5 -9	; "group"
	43	[43]	GETTABLE 	5 5 -10	; "PgFwd"
	44	[43]	SETLIST  	3 2 1	; 1
	45	[44]	SETTABLE 	2 -5 -22	; "doc" "increase line space"
	46	[45]	SETTABLE 	2 -12 -23	; "event" "ChangeLineSpace"
	47	[45]	SETTABLE 	2 -14 -15	; "args" "increase"
	48	[45]	SETLIST  	2 1 1	; 1
	49	[45]	SETTABLE 	1 -20 2	; "IncreaseLineSpace" -
	50	[46]	NEWTABLE 	2 1 3
	51	[46]	NEWTABLE 	3 2 0
	52	[47]	LOADK    	4 -21	; "Alt"
	53	[47]	GETUPVAL 	5 1	; Input
	54	[47]	GETTABLE 	5 5 -9	; "group"
	55	[47]	GETTABLE 	5 5 -17	; "PgBack"
	56	[47]	SETLIST  	3 2 1	; 1
	57	[48]	SETTABLE 	2 -5 -25	; "doc" "decrease line space"
	58	[49]	SETTABLE 	2 -12 -23	; "event" "ChangeLineSpace"
	59	[49]	SETTABLE 	2 -14 -19	; "args" "decrease"
	60	[49]	SETLIST  	2 1 1	; 1
	61	[49]	SETTABLE 	1 -24 2	; "DecreaseLineSpace" -
	62	[50]	SETTABLE 	0 -2 1	; "key_events" -
	63	[53]	NEWTABLE 	1 0 0
	64	[53]	SETTABLE 	0 -26 1	; "face_table" -
	65	[55]	GETGLOBAL	1 -27	; table
	66	[55]	GETTABLE 	1 1 -28	; "insert"
	67	[55]	GETTABLE 	2 0 -26	; "face_table"
	68	[55]	NEWTABLE 	3 0 3
	69	[56]	GETUPVAL 	4 2	; _
	70	[56]	LOADK    	5 -30	; "Font settings"
	71	[56]	CALL     	4 2 2
	72	[56]	SETTABLE 	3 -29 4	; "text" -
	73	[57]	SELF     	4 0 -32	; "getFontSettingsTable"
	74	[57]	CALL     	4 2 2
	75	[57]	SETTABLE 	3 -31 4	; "sub_item_table" -
	76	[58]	SETTABLE 	3 -33 -34	; "separator" true
	77	[55]	CALL     	1 3 1
	78	[61]	GETGLOBAL	1 -35	; cre
	79	[61]	GETTABLE 	1 1 -36	; "getFontFaces"
	80	[61]	CALL     	1 1 2
	81	[62]	GETGLOBAL	2 -37	; ipairs
	82	[62]	MOVE     	3 1
	83	[62]	CALL     	2 2 4
	84	[62]	JMP      	25	; to 110
	85	[63]	GETGLOBAL	7 -27	; table
	86	[63]	GETTABLE 	7 7 -28	; "insert"
	87	[63]	GETTABLE 	8 0 -26	; "face_table"
	88	[63]	NEWTABLE 	9 0 4
	89	[76]	CLOSURE  	10 0	; 0x7fd49fc07c60
	90	[76]	MOVE     	0 0
	91	[76]	MOVE     	0 6
	92	[76]	SETTABLE 	9 -38 10	; "text_func" -
	93	[79]	CLOSURE  	10 1	; 0x7fd49fc084e0
	94	[79]	MOVE     	0 0
	95	[79]	MOVE     	0 6
	96	[79]	SETTABLE 	9 -39 10	; "callback" -
	97	[82]	CLOSURE  	10 2	; 0x7fd49fc08af0
	98	[82]	MOVE     	0 0
	99	[82]	MOVE     	0 6
	100	[82]	SETTABLE 	9 -40 10	; "hold_callback" -
	101	[85]	CLOSURE  	10 3	; 0x7fd49fc08730
	102	[85]	MOVE     	0 6
	103	[85]	MOVE     	0 0
	104	[85]	SETTABLE 	9 -41 10	; "checked_func" -
	105	[63]	CALL     	7 3 1
	106	[87]	NEWTABLE 	7 0 1
	107	[87]	SETTABLE 	7 -29 6	; "text" -
	108	[87]	SETTABLE 	1 5 7
	109	[87]	CLOSE    	5
	110	[62]	TFORLOOP 	2 2
	111	[87]	JMP      	-27	; to 85
	112	[89]	GETTABLE 	2 0 -42	; "ui"
	113	[89]	GETTABLE 	2 2 -43	; "menu"
	114	[89]	SELF     	2 2 -44	; "registerToMainMenu"
	115	[89]	MOVE     	4 0
	116	[89]	CALL     	2 3 1
	117	[90]	RETURN   	0 1

function <./frontend/apps/reader/modules/readerfont.lua:64,76> (36 instructions, 144 bytes at 0x7fd49fc07c60)
0 params, 5 slots, 2 upvalues, 3 locals, 11 constants, 0 functions
	1	[66]	GETGLOBAL	0 -1	; G_reader_settings
	2	[66]	SELF     	0 0 -2	; "readSetting"
	3	[66]	LOADK    	2 -3	; "cre_font"
	4	[66]	CALL     	0 3 2
	5	[66]	TEST     	0 0 1
	6	[66]	JMP      	4	; to 11
	7	[66]	GETUPVAL 	0 0	; self
	8	[66]	GETTABLE 	0 0 -4	; "ui"
	9	[66]	GETTABLE 	0 0 -5	; "document"
	10	[66]	GETTABLE 	0 0 -6	; "default_font"
	11	[67]	GETGLOBAL	1 -1	; G_reader_settings
	12	[67]	SELF     	1 1 -2	; "readSetting"
	13	[67]	LOADK    	3 -7	; "fallback_font"
	14	[67]	CALL     	1 3 2
	15	[67]	TEST     	1 0 1
	16	[67]	JMP      	5	; to 22
	17	[67]	GETUPVAL 	1 0	; self
	18	[67]	GETTABLE 	1 1 -4	; "ui"
	19	[67]	GETTABLE 	1 1 -5	; "document"
	20	[67]	GETTABLE 	1 1 -8	; "fallback_fonts"
	21	[67]	GETTABLE 	1 1 -9	; 1
	22	[68]	GETUPVAL 	2 1	; v
	23	[69]	GETUPVAL 	3 1	; v
	24	[69]	EQ       	0 3 0
	25	[69]	JMP      	3	; to 29
	26	[70]	MOVE     	3 2
	27	[70]	LOADK    	4 -10	; "   \226\152\133"
	28	[70]	CONCAT   	2 3 4
	29	[72]	GETUPVAL 	3 1	; v
	30	[72]	EQ       	0 3 1
	31	[72]	JMP      	3	; to 35
	32	[73]	MOVE     	3 2
	33	[73]	LOADK    	4 -11	; "   \239\191\189"
	34	[73]	CONCAT   	2 3 4
	35	[75]	RETURN   	2 2
	36	[76]	RETURN   	0 1

function <./frontend/apps/reader/modules/readerfont.lua:77,79> (5 instructions, 20 bytes at 0x7fd49fc084e0)
0 params, 3 slots, 2 upvalues, 0 locals, 1 constant, 0 functions
	1	[78]	GETUPVAL 	0 0	; self
	2	[78]	SELF     	0 0 -1	; "setFont"
	3	[78]	GETUPVAL 	2 1	; v
	4	[78]	CALL     	0 3 1
	5	[79]	RETURN   	0 1

function <./frontend/apps/reader/modules/readerfont.lua:80,82> (6 instructions, 24 bytes at 0x7fd49fc08af0)
1 param, 5 slots, 2 upvalues, 1 local, 1 constant, 0 functions
	1	[81]	GETUPVAL 	1 0	; self
	2	[81]	SELF     	1 1 -1	; "makeDefault"
	3	[81]	GETUPVAL 	3 1	; v
	4	[81]	MOVE     	4 0
	5	[81]	CALL     	1 4 1
	6	[82]	RETURN   	0 1

function <./frontend/apps/reader/modules/readerfont.lua:83,85> (9 instructions, 36 bytes at 0x7fd49fc08730)
0 params, 2 slots, 2 upvalues, 0 locals, 1 constant, 0 functions
	1	[84]	GETUPVAL 	0 0	; v
	2	[84]	GETUPVAL 	1 1	; self
	3	[84]	GETTABLE 	1 1 -1	; "font_face"
	4	[84]	EQ       	1 0 1
	5	[84]	JMP      	1	; to 7
	6	[84]	LOADBOOL 	0 0 1
	7	[84]	LOADBOOL 	0 1 0
	8	[84]	RETURN   	0 2
	9	[85]	RETURN   	0 1

function <./frontend/apps/reader/modules/readerfont.lua:92,94> (2 instructions, 8 bytes at 0x7fd49fc08f70)
2 params, 2 slots, 0 upvalues, 2 locals, 1 constant, 0 functions
	1	[93]	SETTABLE 	0 -1 1	; "dimen" -
	2	[94]	RETURN   	0 1

function <./frontend/apps/reader/modules/readerfont.lua:96,149> (205 instructions, 820 bytes at 0x7fd49fc091d0)
2 params, 7 slots, 2 upvalues, 2 locals, 49 constants, 1 function
	1	[97]	SELF     	2 1 -2	; "readSetting"
	2	[97]	LOADK    	4 -1	; "font_face"
	3	[97]	CALL     	2 3 2
	4	[98]	TEST     	2 0 1
	5	[98]	JMP      	9	; to 15
	6	[98]	GETGLOBAL	2 -3	; G_reader_settings
	7	[98]	SELF     	2 2 -2	; "readSetting"
	8	[98]	LOADK    	4 -4	; "cre_font"
	9	[98]	CALL     	2 3 2
	10	[99]	TEST     	2 0 1
	11	[99]	JMP      	3	; to 15
	12	[99]	GETTABLE 	2 0 -5	; "ui"
	13	[99]	GETTABLE 	2 2 -6	; "document"
	14	[99]	GETTABLE 	2 2 -7	; "default_font"
	15	[99]	SETTABLE 	0 -1 2	; "font_face" -
	16	[100]	GETTABLE 	2 0 -5	; "ui"
	17	[100]	GETTABLE 	2 2 -6	; "document"
	18	[100]	SELF     	2 2 -8	; "setFontFace"
	19	[100]	GETTABLE 	4 0 -1	; "font_face"
	20	[100]	CALL     	2 3 1
	21	[102]	SELF     	2 1 -2	; "readSetting"
	22	[102]	LOADK    	4 -9	; "header_font_face"
	23	[102]	CALL     	2 3 2
	24	[103]	TEST     	2 0 1
	25	[103]	JMP      	9	; to 35
	26	[103]	GETGLOBAL	2 -3	; G_reader_settings
	27	[103]	SELF     	2 2 -2	; "readSetting"
	28	[103]	LOADK    	4 -10	; "header_font"
	29	[103]	CALL     	2 3 2
	30	[104]	TEST     	2 0 1
	31	[104]	JMP      	3	; to 35
	32	[104]	GETTABLE 	2 0 -5	; "ui"
	33	[104]	GETTABLE 	2 2 -6	; "document"
	34	[104]	GETTABLE 	2 2 -10	; "header_font"
	35	[104]	SETTABLE 	0 -9 2	; "header_font_face" -
	36	[105]	GETTABLE 	2 0 -5	; "ui"
	37	[105]	GETTABLE 	2 2 -6	; "document"
	38	[105]	SELF     	2 2 -11	; "setHeaderFont"
	39	[105]	GETTABLE 	4 0 -9	; "header_font_face"
	40	[105]	CALL     	2 3 1
	41	[107]	SELF     	2 1 -2	; "readSetting"
	42	[107]	LOADK    	4 -12	; "font_size"
	43	[107]	CALL     	2 3 2
	44	[108]	TEST     	2 0 1
	45	[108]	JMP      	10	; to 56
	46	[108]	GETGLOBAL	2 -3	; G_reader_settings
	47	[108]	SELF     	2 2 -2	; "readSetting"
	48	[108]	LOADK    	4 -13	; "copt_font_size"
	49	[108]	CALL     	2 3 2
	50	[109]	TEST     	2 0 1
	51	[109]	JMP      	4	; to 56
	52	[109]	GETGLOBAL	2 -14	; DCREREADER_CONFIG_DEFAULT_FONT_SIZE
	53	[109]	TEST     	2 0 1
	54	[109]	JMP      	1	; to 56
	55	[109]	LOADK    	2 -15	; 22
	56	[109]	SETTABLE 	0 -12 2	; "font_size" -
	57	[110]	GETTABLE 	2 0 -5	; "ui"
	58	[110]	GETTABLE 	2 2 -6	; "document"
	59	[110]	SELF     	2 2 -16	; "setFontSize"
	60	[110]	GETUPVAL 	4 0	; Screen
	61	[110]	SELF     	4 4 -17	; "scaleBySize"
	62	[110]	GETTABLE 	6 0 -12	; "font_size"
	63	[110]	CALL     	4 3 0
	64	[110]	CALL     	2 0 1
	65	[112]	SELF     	2 1 -2	; "readSetting"
	66	[112]	LOADK    	4 -18	; "font_embolden"
	67	[112]	CALL     	2 3 2
	68	[113]	TEST     	2 0 1
	69	[113]	JMP      	7	; to 77
	70	[113]	GETGLOBAL	2 -3	; G_reader_settings
	71	[113]	SELF     	2 2 -2	; "readSetting"
	72	[113]	LOADK    	4 -19	; "copt_font_weight"
	73	[113]	CALL     	2 3 2
	74	[113]	TEST     	2 0 1
	75	[113]	JMP      	1	; to 77
	76	[113]	LOADK    	2 -20	; 0
	77	[113]	SETTABLE 	0 -18 2	; "font_embolden" -
	78	[114]	GETTABLE 	2 0 -5	; "ui"
	79	[114]	GETTABLE 	2 2 -6	; "document"
	80	[114]	SELF     	2 2 -21	; "toggleFontBolder"
	81	[114]	GETTABLE 	4 0 -18	; "font_embolden"
	82	[114]	CALL     	2 3 1
	83	[116]	SELF     	2 1 -2	; "readSetting"
	84	[116]	LOADK    	4 -22	; "font_hinting"
	85	[116]	CALL     	2 3 2
	86	[117]	TEST     	2 0 1
	87	[117]	JMP      	7	; to 95
	88	[117]	GETGLOBAL	2 -3	; G_reader_settings
	89	[117]	SELF     	2 2 -2	; "readSetting"
	90	[117]	LOADK    	4 -23	; "copt_font_hinting"
	91	[117]	CALL     	2 3 2
	92	[117]	TEST     	2 0 1
	93	[117]	JMP      	1	; to 95
	94	[117]	LOADK    	2 -24	; 2
	95	[117]	SETTABLE 	0 -22 2	; "font_hinting" -
	96	[118]	GETTABLE 	2 0 -5	; "ui"
	97	[118]	GETTABLE 	2 2 -6	; "document"
	98	[118]	SELF     	2 2 -25	; "setFontHinting"
	99	[118]	GETTABLE 	4 0 -22	; "font_hinting"
	100	[118]	CALL     	2 3 1
	101	[120]	SELF     	2 1 -2	; "readSetting"
	102	[120]	LOADK    	4 -26	; "font_kerning"
	103	[120]	CALL     	2 3 2
	104	[121]	TEST     	2 0 1
	105	[121]	JMP      	7	; to 113
	106	[121]	GETGLOBAL	2 -3	; G_reader_settings
	107	[121]	SELF     	2 2 -2	; "readSetting"
	108	[121]	LOADK    	4 -27	; "copt_font_kerning"
	109	[121]	CALL     	2 3 2
	110	[121]	TEST     	2 0 1
	111	[121]	JMP      	1	; to 113
	112	[121]	LOADK    	2 -28	; 3
	113	[121]	SETTABLE 	0 -26 2	; "font_kerning" -
	114	[122]	GETTABLE 	2 0 -5	; "ui"
	115	[122]	GETTABLE 	2 2 -6	; "document"
	116	[122]	SELF     	2 2 -29	; "setFontKerning"
	117	[122]	GETTABLE 	4 0 -26	; "font_kerning"
	118	[122]	CALL     	2 3 1
	119	[124]	SELF     	2 1 -2	; "readSetting"
	120	[124]	LOADK    	4 -30	; "word_spacing"
	121	[124]	CALL     	2 3 2
	122	[125]	TEST     	2 0 1
	123	[125]	JMP      	10	; to 134
	124	[125]	GETGLOBAL	2 -3	; G_reader_settings
	125	[125]	SELF     	2 2 -2	; "readSetting"
	126	[125]	LOADK    	4 -31	; "copt_word_spacing"
	127	[125]	CALL     	2 3 2
	128	[125]	TEST     	2 0 1
	129	[125]	JMP      	4	; to 134
	130	[125]	NEWTABLE 	2 2 0
	131	[125]	LOADK    	3 -32	; 95
	132	[125]	LOADK    	4 -33	; 75
	133	[125]	SETLIST  	2 2 1	; 1
	134	[125]	SETTABLE 	0 -30 2	; "word_spacing" -
	135	[126]	GETTABLE 	2 0 -5	; "ui"
	136	[126]	GETTABLE 	2 2 -6	; "document"
	137	[126]	SELF     	2 2 -34	; "setWordSpacing"
	138	[126]	GETTABLE 	4 0 -30	; "word_spacing"
	139	[126]	CALL     	2 3 1
	140	[128]	SELF     	2 1 -2	; "readSetting"
	141	[128]	LOADK    	4 -35	; "word_expansion"
	142	[128]	CALL     	2 3 2
	143	[129]	TEST     	2 0 1
	144	[129]	JMP      	7	; to 152
	145	[129]	GETGLOBAL	2 -3	; G_reader_settings
	146	[129]	SELF     	2 2 -2	; "readSetting"
	147	[129]	LOADK    	4 -36	; "copt_word_expansion"
	148	[129]	CALL     	2 3 2
	149	[129]	TEST     	2 0 1
	150	[129]	JMP      	1	; to 152
	151	[129]	LOADK    	2 -20	; 0
	152	[129]	SETTABLE 	0 -35 2	; "word_expansion" -
	153	[130]	GETTABLE 	2 0 -5	; "ui"
	154	[130]	GETTABLE 	2 2 -6	; "document"
	155	[130]	SELF     	2 2 -37	; "setWordExpansion"
	156	[130]	GETTABLE 	4 0 -35	; "word_expansion"
	157	[130]	CALL     	2 3 1
	158	[132]	SELF     	2 1 -2	; "readSetting"
	159	[132]	LOADK    	4 -38	; "line_space_percent"
	160	[132]	CALL     	2 3 2
	161	[133]	TEST     	2 0 1
	162	[133]	JMP      	7	; to 170
	163	[133]	GETGLOBAL	2 -3	; G_reader_settings
	164	[133]	SELF     	2 2 -2	; "readSetting"
	165	[133]	LOADK    	4 -39	; "copt_line_spacing"
	166	[133]	CALL     	2 3 2
	167	[134]	TEST     	2 0 1
	168	[134]	JMP      	1	; to 170
	169	[134]	GETGLOBAL	2 -40	; DCREREADER_CONFIG_LINE_SPACE_PERCENT_MEDIUM
	170	[134]	SETTABLE 	0 -38 2	; "line_space_percent" -
	171	[135]	GETTABLE 	2 0 -5	; "ui"
	172	[135]	GETTABLE 	2 2 -6	; "document"
	173	[135]	SELF     	2 2 -41	; "setInterlineSpacePercent"
	174	[135]	GETTABLE 	4 0 -38	; "line_space_percent"
	175	[135]	CALL     	2 3 1
	176	[137]	SELF     	2 1 -2	; "readSetting"
	177	[137]	LOADK    	4 -42	; "gamma_index"
	178	[137]	CALL     	2 3 2
	179	[138]	TEST     	2 0 1
	180	[138]	JMP      	10	; to 191
	181	[138]	GETGLOBAL	2 -3	; G_reader_settings
	182	[138]	SELF     	2 2 -2	; "readSetting"
	183	[138]	LOADK    	4 -43	; "copt_font_gamma"
	184	[138]	CALL     	2 3 2
	185	[139]	TEST     	2 0 1
	186	[139]	JMP      	4	; to 191
	187	[139]	GETGLOBAL	2 -44	; DCREREADER_CONFIG_DEFAULT_FONT_GAMMA
	188	[139]	TEST     	2 0 1
	189	[139]	JMP      	1	; to 191
	190	[139]	LOADK    	2 -45	; 15
	191	[139]	SETTABLE 	0 -42 2	; "gamma_index" -
	192	[140]	GETTABLE 	2 0 -5	; "ui"
	193	[140]	GETTABLE 	2 2 -6	; "document"
	194	[140]	SELF     	2 2 -46	; "setGammaIndex"
	195	[140]	GETTABLE 	4 0 -42	; "gamma_index"
	196	[140]	CALL     	2 3 1
	197	[146]	GETGLOBAL	2 -47	; table
	198	[146]	GETTABLE 	2 2 -48	; "insert"
	199	[146]	GETTABLE 	3 0 -5	; "ui"
	200	[146]	GETTABLE 	3 3 -49	; "postInitCallback"
	201	[148]	CLOSURE  	4 0	; 0x7fd49fc092d0
	202	[148]	MOVE     	0 0
	203	[148]	GETUPVAL 	0 1	; Event
	204	[146]	CALL     	2 3 1
	205	[149]	RETURN   	0 1

function <./frontend/apps/reader/modules/readerfont.lua:146,148> (9 instructions, 36 bytes at 0x7fd49fc092d0)
0 params, 5 slots, 2 upvalues, 0 locals, 4 constants, 0 functions
	1	[147]	GETUPVAL 	0 0	; self
	2	[147]	GETTABLE 	0 0 -1	; "ui"
	3	[147]	SELF     	0 0 -2	; "handleEvent"
	4	[147]	GETUPVAL 	2 1	; Event
	5	[147]	SELF     	2 2 -3	; "new"
	6	[147]	LOADK    	4 -4	; "UpdatePos"
	7	[147]	CALL     	2 3 0
	8	[147]	CALL     	0 0 1
	9	[148]	RETURN   	0 1

function <./frontend/apps/reader/modules/readerfont.lua:151,176> (42 instructions, 168 bytes at 0x7fd49fc09c40)
1 param, 8 slots, 4 upvalues, 3 locals, 20 constants, 1 function
	1	[153]	GETUPVAL 	1 0	; Menu
	2	[153]	SELF     	1 1 -1	; "new"
	3	[153]	NEWTABLE 	3 0 6
	4	[154]	GETTABLE 	4 0 -3	; "font_menu_title"
	5	[154]	SETTABLE 	3 -2 4	; "title" -
	6	[155]	GETTABLE 	4 0 -5	; "face_table"
	7	[155]	SETTABLE 	3 -4 4	; "item_table" -
	8	[156]	GETUPVAL 	4 1	; Screen
	9	[156]	SELF     	4 4 -7	; "getWidth"
	10	[156]	CALL     	4 2 2
	11	[156]	SUB      	4 4 -8	; - 100
	12	[156]	SETTABLE 	3 -6 4	; "width" -
	13	[157]	GETUPVAL 	4 1	; Screen
	14	[157]	SELF     	4 4 -10	; "getHeight"
	15	[157]	CALL     	4 2 2
	16	[157]	DIV      	4 4 -11	; - 2
	17	[157]	SETTABLE 	3 -9 4	; "height" -
	18	[158]	SETTABLE 	3 -12 -13	; "single_line" true
	19	[159]	SETTABLE 	3 -14 -15	; "perpage_custom" 8
	20	[153]	CALL     	1 3 2
	21	[162]	GETUPVAL 	2 2	; CenterContainer
	22	[162]	SELF     	2 2 -1	; "new"
	23	[162]	NEWTABLE 	4 1 1
	24	[163]	MOVE     	5 1
	25	[164]	GETUPVAL 	6 1	; Screen
	26	[164]	SELF     	6 6 -17	; "getSize"
	27	[164]	CALL     	6 2 2
	28	[164]	SETTABLE 	4 -16 6	; "dimen" -
	29	[165]	SETLIST  	4 1 1	; 1
	30	[162]	CALL     	2 3 2
	31	[168]	CLOSURE  	3 0	; 0x7fd49fc09ed0
	32	[168]	GETUPVAL 	0 3	; UIManager
	33	[168]	MOVE     	0 2
	34	[168]	SETTABLE 	1 -18 3	; "close_callback" -
	35	[171]	SETTABLE 	1 -19 2	; "show_parent" -
	36	[173]	GETUPVAL 	3 3	; UIManager
	37	[173]	SELF     	3 3 -20	; "show"
	38	[173]	MOVE     	5 2
	39	[173]	CALL     	3 3 1
	40	[175]	LOADBOOL 	3 1 0
	41	[175]	RETURN   	3 2
	42	[176]	RETURN   	0 1

function <./frontend/apps/reader/modules/readerfont.lua:166,168> (5 instructions, 20 bytes at 0x7fd49fc09ed0)
0 params, 3 slots, 2 upvalues, 0 locals, 1 constant, 0 functions
	1	[167]	GETUPVAL 	0 0	; UIManager
	2	[167]	SELF     	0 0 -1	; "close"
	3	[167]	GETUPVAL 	2 1	; menu_container
	4	[167]	CALL     	0 3 1
	5	[168]	RETURN   	0 1

function <./frontend/apps/reader/modules/readerfont.lua:181,190> (27 instructions, 108 bytes at 0x7fd49fc0a280)
3 params, 10 slots, 1 upvalue, 4 locals, 8 constants, 0 functions
	1	[182]	EQ       	0 1 -1	; - "decrease"
	2	[182]	JMP      	3	; to 6
	3	[182]	LOADK    	3 -2	; -0.5
	4	[182]	TEST     	3 0 1
	5	[182]	JMP      	1	; to 7
	6	[182]	LOADK    	3 -3	; 0.5
	7	[183]	TEST     	2 0 0
	8	[183]	JMP      	5	; to 14
	9	[184]	GETTABLE 	4 0 -4	; "font_size"
	10	[184]	MUL      	5 2 3
	11	[184]	ADD      	4 4 5
	12	[184]	SETTABLE 	0 -4 4	; "font_size" -
	13	[184]	JMP      	3	; to 17
	14	[186]	GETTABLE 	4 0 -4	; "font_size"
	15	[186]	ADD      	4 4 3
	16	[186]	SETTABLE 	0 -4 4	; "font_size" -
	17	[188]	GETTABLE 	4 0 -5	; "ui"
	18	[188]	SELF     	4 4 -6	; "handleEvent"
	19	[188]	GETUPVAL 	6 0	; Event
	20	[188]	SELF     	6 6 -7	; "new"
	21	[188]	LOADK    	8 -8	; "SetFontSize"
	22	[188]	GETTABLE 	9 0 -4	; "font_size"
	23	[188]	CALL     	6 4 0
	24	[188]	CALL     	4 0 1
	25	[189]	LOADBOOL 	4 1 0
	26	[189]	RETURN   	4 2
	27	[190]	RETURN   	0 1

function <./frontend/apps/reader/modules/readerfont.lua:192,205> (40 instructions, 160 bytes at 0x7fd49fc0aa20)
2 params, 10 slots, 6 upvalues, 2 locals, 15 constants, 0 functions
	1	[193]	LT       	0 -1 1	; 255 -
	2	[193]	JMP      	1	; to 4
	3	[193]	LOADK    	1 -1	; 255
	4	[194]	LT       	0 1 -2	; - 12
	5	[194]	JMP      	1	; to 7
	6	[194]	LOADK    	1 -2	; 12
	7	[196]	SETTABLE 	0 -3 1	; "font_size" -
	8	[197]	GETTABLE 	2 0 -4	; "ui"
	9	[197]	GETTABLE 	2 2 -5	; "document"
	10	[197]	SELF     	2 2 -6	; "setFontSize"
	11	[197]	GETUPVAL 	4 0	; Screen
	12	[197]	SELF     	4 4 -7	; "scaleBySize"
	13	[197]	MOVE     	6 1
	14	[197]	CALL     	4 3 0
	15	[197]	CALL     	2 0 1
	16	[198]	GETTABLE 	2 0 -4	; "ui"
	17	[198]	SELF     	2 2 -8	; "handleEvent"
	18	[198]	GETUPVAL 	4 1	; Event
	19	[198]	SELF     	4 4 -9	; "new"
	20	[198]	LOADK    	6 -10	; "UpdatePos"
	21	[198]	CALL     	4 3 0
	22	[198]	CALL     	2 0 1
	23	[199]	GETUPVAL 	2 2	; UIManager
	24	[199]	SELF     	2 2 -11	; "show"
	25	[199]	GETUPVAL 	4 3	; Notification
	26	[199]	SELF     	4 4 -9	; "new"
	27	[199]	NEWTABLE 	6 0 2
	28	[200]	GETUPVAL 	7 4	; T
	29	[200]	GETUPVAL 	8 5	; _
	30	[200]	LOADK    	9 -13	; "Font size set to %1."
	31	[200]	CALL     	8 2 2
	32	[200]	GETTABLE 	9 0 -3	; "font_size"
	33	[200]	CALL     	7 3 2
	34	[200]	SETTABLE 	6 -12 7	; "text" -
	35	[201]	SETTABLE 	6 -14 -15	; "timeout" 2
	36	[199]	CALL     	4 3 0
	37	[199]	CALL     	2 0 1
	38	[204]	LOADBOOL 	2 1 0
	39	[204]	RETURN   	2 2
	40	[205]	RETURN   	0 1

function <./frontend/apps/reader/modules/readerfont.lua:207,216> (40 instructions, 160 bytes at 0x7fd49fc0aba0)
2 params, 10 slots, 5 upvalues, 2 locals, 17 constants, 0 functions
	1	[208]	GETGLOBAL	2 -2	; math
	2	[208]	GETTABLE 	2 2 -3	; "min"
	3	[208]	LOADK    	3 -4	; 200
	4	[208]	GETGLOBAL	4 -2	; math
	5	[208]	GETTABLE 	4 4 -5	; "max"
	6	[208]	LOADK    	5 -6	; 50
	7	[208]	MOVE     	6 1
	8	[208]	CALL     	4 3 0
	9	[208]	CALL     	2 0 2
	10	[208]	SETTABLE 	0 -1 2	; "line_space_percent" -
	11	[209]	GETUPVAL 	2 0	; UIManager
	12	[209]	SELF     	2 2 -7	; "show"
	13	[209]	GETUPVAL 	4 1	; Notification
	14	[209]	SELF     	4 4 -8	; "new"
	15	[209]	NEWTABLE 	6 0 2
	16	[210]	GETUPVAL 	7 2	; T
	17	[210]	GETUPVAL 	8 3	; _
	18	[210]	LOADK    	9 -10	; "Line spacing set to %1%."
	19	[210]	CALL     	8 2 2
	20	[210]	GETTABLE 	9 0 -1	; "line_space_percent"
	21	[210]	CALL     	7 3 2
	22	[210]	SETTABLE 	6 -9 7	; "text" -
	23	[211]	SETTABLE 	6 -11 -12	; "timeout" 2
	24	[209]	CALL     	4 3 0
	25	[209]	CALL     	2 0 1
	26	[213]	GETTABLE 	2 0 -13	; "ui"
	27	[213]	GETTABLE 	2 2 -14	; "document"
	28	[213]	SELF     	2 2 -15	; "setInterlineSpacePercent"
	29	[213]	GETTABLE 	4 0 -1	; "line_space_percent"
	30	[213]	CALL     	2 3 1
	31	[214]	GETTABLE 	2 0 -13	; "ui"
	32	[214]	SELF     	2 2 -16	; "handleEvent"
	33	[214]	GETUPVAL 	4 4	; Event
	34	[214]	SELF     	4 4 -8	; "new"
	35	[214]	LOADK    	6 -17	; "UpdatePos"
	36	[214]	CALL     	4 3 0
	37	[214]	CALL     	2 0 1
	38	[215]	LOADBOOL 	2 1 0
	39	[215]	RETURN   	2 2
	40	[216]	RETURN   	0 1

function <./frontend/apps/reader/modules/readerfont.lua:218,223> (16 instructions, 64 bytes at 0x7fd49fc0b220)
2 params, 7 slots, 1 upvalue, 2 locals, 7 constants, 0 functions
	1	[219]	SETTABLE 	0 -1 1	; "font_embolden" -
	2	[220]	GETTABLE 	2 0 -2	; "ui"
	3	[220]	GETTABLE 	2 2 -3	; "document"
	4	[220]	SELF     	2 2 -4	; "toggleFontBolder"
	5	[220]	MOVE     	4 1
	6	[220]	CALL     	2 3 1
	7	[221]	GETTABLE 	2 0 -2	; "ui"
	8	[221]	SELF     	2 2 -5	; "handleEvent"
	9	[221]	GETUPVAL 	4 0	; Event
	10	[221]	SELF     	4 4 -6	; "new"
	11	[221]	LOADK    	6 -7	; "UpdatePos"
	12	[221]	CALL     	4 3 0
	13	[221]	CALL     	2 0 1
	14	[222]	LOADBOOL 	2 1 0
	15	[222]	RETURN   	2 2
	16	[223]	RETURN   	0 1

function <./frontend/apps/reader/modules/readerfont.lua:225,230> (16 instructions, 64 bytes at 0x7fd49fc0b780)
2 params, 7 slots, 1 upvalue, 2 locals, 7 constants, 0 functions
	1	[226]	SETTABLE 	0 -1 1	; "font_hinting" -
	2	[227]	GETTABLE 	2 0 -2	; "ui"
	3	[227]	GETTABLE 	2 2 -3	; "document"
	4	[227]	SELF     	2 2 -4	; "setFontHinting"
	5	[227]	MOVE     	4 1
	6	[227]	CALL     	2 3 1
	7	[228]	GETTABLE 	2 0 -2	; "ui"
	8	[228]	SELF     	2 2 -5	; "handleEvent"
	9	[228]	GETUPVAL 	4 0	; Event
	10	[228]	SELF     	4 4 -6	; "new"
	11	[228]	LOADK    	6 -7	; "UpdatePos"
	12	[228]	CALL     	4 3 0
	13	[228]	CALL     	2 0 1
	14	[229]	LOADBOOL 	2 1 0
	15	[229]	RETURN   	2 2
	16	[230]	RETURN   	0 1

function <./frontend/apps/reader/modules/readerfont.lua:232,237> (16 instructions, 64 bytes at 0x7fd49fc0bfe0)
2 params, 7 slots, 1 upvalue, 2 locals, 7 constants, 0 functions
	1	[233]	SETTABLE 	0 -1 1	; "font_kerning" -
	2	[234]	GETTABLE 	2 0 -2	; "ui"
	3	[234]	GETTABLE 	2 2 -3	; "document"
	4	[234]	SELF     	2 2 -4	; "setFontKerning"
	5	[234]	MOVE     	4 1
	6	[234]	CALL     	2 3 1
	7	[235]	GETTABLE 	2 0 -2	; "ui"
	8	[235]	SELF     	2 2 -5	; "handleEvent"
	9	[235]	GETUPVAL 	4 0	; Event
	10	[235]	SELF     	4 4 -6	; "new"
	11	[235]	LOADK    	6 -7	; "UpdatePos"
	12	[235]	CALL     	4 3 0
	13	[235]	CALL     	2 0 1
	14	[236]	LOADBOOL 	2 1 0
	15	[236]	RETURN   	2 2
	16	[237]	RETURN   	0 1

function <./frontend/apps/reader/modules/readerfont.lua:239,244> (16 instructions, 64 bytes at 0x7fd49fc0c1b0)
2 params, 7 slots, 1 upvalue, 2 locals, 7 constants, 0 functions
	1	[240]	SETTABLE 	0 -1 1	; "word_spacing" -
	2	[241]	GETTABLE 	2 0 -2	; "ui"
	3	[241]	GETTABLE 	2 2 -3	; "document"
	4	[241]	SELF     	2 2 -4	; "setWordSpacing"
	5	[241]	MOVE     	4 1
	6	[241]	CALL     	2 3 1
	7	[242]	GETTABLE 	2 0 -2	; "ui"
	8	[242]	SELF     	2 2 -5	; "handleEvent"
	9	[242]	GETUPVAL 	4 0	; Event
	10	[242]	SELF     	4 4 -6	; "new"
	11	[242]	LOADK    	6 -7	; "UpdatePos"
	12	[242]	CALL     	4 3 0
	13	[242]	CALL     	2 0 1
	14	[243]	LOADBOOL 	2 1 0
	15	[243]	RETURN   	2 2
	16	[244]	RETURN   	0 1

function <./frontend/apps/reader/modules/readerfont.lua:246,251> (16 instructions, 64 bytes at 0x7fd49fc0c6a0)
2 params, 7 slots, 1 upvalue, 2 locals, 7 constants, 0 functions
	1	[247]	SETTABLE 	0 -1 1	; "word_expansion" -
	2	[248]	GETTABLE 	2 0 -2	; "ui"
	3	[248]	GETTABLE 	2 2 -3	; "document"
	4	[248]	SELF     	2 2 -4	; "setWordExpansion"
	5	[248]	MOVE     	4 1
	6	[248]	CALL     	2 3 1
	7	[249]	GETTABLE 	2 0 -2	; "ui"
	8	[249]	SELF     	2 2 -5	; "handleEvent"
	9	[249]	GETUPVAL 	4 0	; Event
	10	[249]	SELF     	4 4 -6	; "new"
	11	[249]	LOADK    	6 -7	; "UpdatePos"
	12	[249]	CALL     	4 3 0
	13	[249]	CALL     	2 0 1
	14	[250]	LOADBOOL 	2 1 0
	15	[250]	RETURN   	2 2
	16	[251]	RETURN   	0 1

function <./frontend/apps/reader/modules/readerfont.lua:253,263> (35 instructions, 140 bytes at 0x7fd49fc09130)
2 params, 11 slots, 5 upvalues, 3 locals, 13 constants, 0 functions
	1	[254]	SETTABLE 	0 -1 1	; "gamma_index" -
	2	[255]	GETTABLE 	2 0 -2	; "ui"
	3	[255]	GETTABLE 	2 2 -3	; "document"
	4	[255]	SELF     	2 2 -4	; "setGammaIndex"
	5	[255]	GETTABLE 	4 0 -1	; "gamma_index"
	6	[255]	CALL     	2 3 1
	7	[256]	GETTABLE 	2 0 -2	; "ui"
	8	[256]	GETTABLE 	2 2 -3	; "document"
	9	[256]	SELF     	2 2 -5	; "getGammaLevel"
	10	[256]	CALL     	2 2 2
	11	[257]	GETUPVAL 	3 0	; UIManager
	12	[257]	SELF     	3 3 -6	; "show"
	13	[257]	GETUPVAL 	5 1	; Notification
	14	[257]	SELF     	5 5 -7	; "new"
	15	[257]	NEWTABLE 	7 0 2
	16	[258]	GETUPVAL 	8 2	; T
	17	[258]	GETUPVAL 	9 3	; _
	18	[258]	LOADK    	10 -9	; "Font gamma set to %1."
	19	[258]	CALL     	9 2 2
	20	[258]	MOVE     	10 2
	21	[258]	CALL     	8 3 2
	22	[258]	SETTABLE 	7 -8 8	; "text" -
	23	[259]	SETTABLE 	7 -10 -11	; "timeout" 2
	24	[257]	CALL     	5 3 0
	25	[257]	CALL     	3 0 1
	26	[261]	GETTABLE 	3 0 -2	; "ui"
	27	[261]	SELF     	3 3 -12	; "handleEvent"
	28	[261]	GETUPVAL 	5 4	; Event
	29	[261]	SELF     	5 5 -7	; "new"
	30	[261]	LOADK    	7 -13	; "RedrawCurrentView"
	31	[261]	CALL     	5 3 0
	32	[261]	CALL     	3 0 1
	33	[262]	LOADBOOL 	3 1 0
	34	[262]	RETURN   	3 2
	35	[263]	RETURN   	0 1

function <./frontend/apps/reader/modules/readerfont.lua:265,276> (61 instructions, 244 bytes at 0x7fd49fc08c30)
1 param, 5 slots, 0 upvalues, 1 local, 13 constants, 0 functions
	1	[266]	GETTABLE 	1 0 -1	; "ui"
	2	[266]	GETTABLE 	1 1 -2	; "doc_settings"
	3	[266]	SELF     	1 1 -3	; "saveSetting"
	4	[266]	LOADK    	3 -4	; "font_face"
	5	[266]	GETTABLE 	4 0 -4	; "font_face"
	6	[266]	CALL     	1 4 1
	7	[267]	GETTABLE 	1 0 -1	; "ui"
	8	[267]	GETTABLE 	1 1 -2	; "doc_settings"
	9	[267]	SELF     	1 1 -3	; "saveSetting"
	10	[267]	LOADK    	3 -5	; "header_font_face"
	11	[267]	GETTABLE 	4 0 -5	; "header_font_face"
	12	[267]	CALL     	1 4 1
	13	[268]	GETTABLE 	1 0 -1	; "ui"
	14	[268]	GETTABLE 	1 1 -2	; "doc_settings"
	15	[268]	SELF     	1 1 -3	; "saveSetting"
	16	[268]	LOADK    	3 -6	; "font_size"
	17	[268]	GETTABLE 	4 0 -6	; "font_size"
	18	[268]	CALL     	1 4 1
	19	[269]	GETTABLE 	1 0 -1	; "ui"
	20	[269]	GETTABLE 	1 1 -2	; "doc_settings"
	21	[269]	SELF     	1 1 -3	; "saveSetting"
	22	[269]	LOADK    	3 -7	; "font_embolden"
	23	[269]	GETTABLE 	4 0 -7	; "font_embolden"
	24	[269]	CALL     	1 4 1
	25	[270]	GETTABLE 	1 0 -1	; "ui"
	26	[270]	GETTABLE 	1 1 -2	; "doc_settings"
	27	[270]	SELF     	1 1 -3	; "saveSetting"
	28	[270]	LOADK    	3 -8	; "font_hinting"
	29	[270]	GETTABLE 	4 0 -8	; "font_hinting"
	30	[270]	CALL     	1 4 1
	31	[271]	GETTABLE 	1 0 -1	; "ui"
	32	[271]	GETTABLE 	1 1 -2	; "doc_settings"
	33	[271]	SELF     	1 1 -3	; "saveSetting"
	34	[271]	LOADK    	3 -9	; "font_kerning"
	35	[271]	GETTABLE 	4 0 -9	; "font_kerning"
	36	[271]	CALL     	1 4 1
	37	[272]	GETTABLE 	1 0 -1	; "ui"
	38	[272]	GETTABLE 	1 1 -2	; "doc_settings"
	39	[272]	SELF     	1 1 -3	; "saveSetting"
	40	[272]	LOADK    	3 -10	; "word_spacing"
	41	[272]	GETTABLE 	4 0 -10	; "word_spacing"
	42	[272]	CALL     	1 4 1
	43	[273]	GETTABLE 	1 0 -1	; "ui"
	44	[273]	GETTABLE 	1 1 -2	; "doc_settings"
	45	[273]	SELF     	1 1 -3	; "saveSetting"
	46	[273]	LOADK    	3 -11	; "word_expansion"
	47	[273]	GETTABLE 	4 0 -11	; "word_expansion"
	48	[273]	CALL     	1 4 1
	49	[274]	GETTABLE 	1 0 -1	; "ui"
	50	[274]	GETTABLE 	1 1 -2	; "doc_settings"
	51	[274]	SELF     	1 1 -3	; "saveSetting"
	52	[274]	LOADK    	3 -12	; "line_space_percent"
	53	[274]	GETTABLE 	4 0 -12	; "line_space_percent"
	54	[274]	CALL     	1 4 1
	55	[275]	GETTABLE 	1 0 -1	; "ui"
	56	[275]	GETTABLE 	1 1 -2	; "doc_settings"
	57	[275]	SELF     	1 1 -3	; "saveSetting"
	58	[275]	LOADK    	3 -13	; "gamma_index"
	59	[275]	GETTABLE 	4 0 -13	; "gamma_index"
	60	[275]	CALL     	1 4 1
	61	[276]	RETURN   	0 1

function <./frontend/apps/reader/modules/readerfont.lua:278,290> (34 instructions, 136 bytes at 0x7fd49fc08bb0)
2 params, 10 slots, 5 upvalues, 2 locals, 12 constants, 0 functions
	1	[279]	TEST     	1 0 0
	2	[279]	JMP      	31	; to 34
	3	[279]	GETTABLE 	2 0 -1	; "font_face"
	4	[279]	EQ       	1 2 1
	5	[279]	JMP      	28	; to 34
	6	[280]	SETTABLE 	0 -1 1	; "font_face" -
	7	[281]	GETUPVAL 	2 0	; UIManager
	8	[281]	SELF     	2 2 -2	; "show"
	9	[281]	GETUPVAL 	4 1	; Notification
	10	[281]	SELF     	4 4 -3	; "new"
	11	[281]	NEWTABLE 	6 0 2
	12	[282]	GETUPVAL 	7 2	; T
	13	[282]	GETUPVAL 	8 3	; _
	14	[282]	LOADK    	9 -5	; "Redrawing with font %1."
	15	[282]	CALL     	8 2 2
	16	[282]	MOVE     	9 1
	17	[282]	CALL     	7 3 2
	18	[282]	SETTABLE 	6 -4 7	; "text" -
	19	[283]	SETTABLE 	6 -6 -7	; "timeout" 2
	20	[281]	CALL     	4 3 0
	21	[281]	CALL     	2 0 1
	22	[286]	GETTABLE 	2 0 -8	; "ui"
	23	[286]	GETTABLE 	2 2 -9	; "document"
	24	[286]	SELF     	2 2 -10	; "setFontFace"
	25	[286]	MOVE     	4 1
	26	[286]	CALL     	2 3 1
	27	[288]	GETTABLE 	2 0 -8	; "ui"
	28	[288]	SELF     	2 2 -11	; "handleEvent"
	29	[288]	GETUPVAL 	4 4	; Event
	30	[288]	SELF     	4 4 -3	; "new"
	31	[288]	LOADK    	6 -12	; "UpdatePos"
	32	[288]	CALL     	4 3 0
	33	[288]	CALL     	2 0 1
	34	[290]	RETURN   	0 1

function <./frontend/apps/reader/modules/readerfont.lua:292,310> (36 instructions, 144 bytes at 0x7fd49fc076f0)
3 params, 11 slots, 6 upvalues, 3 locals, 11 constants, 2 functions
	1	[293]	TEST     	1 0 0
	2	[293]	JMP      	33	; to 36
	3	[294]	GETUPVAL 	3 0	; UIManager
	4	[294]	SELF     	3 3 -1	; "show"
	5	[294]	GETUPVAL 	5 1	; MultiConfirmBox
	6	[294]	SELF     	5 5 -2	; "new"
	7	[294]	NEWTABLE 	7 0 5
	8	[295]	GETUPVAL 	8 2	; T
	9	[295]	GETUPVAL 	9 3	; _
	10	[295]	LOADK    	10 -4	; "Would you like %1 to be used as the default font\194\160(\226\152\133), or the fallback font\194\160(\239\191\189)?\n\nCharacters not found in the active font are shown in the fallback font instead."
	11	[295]	CALL     	9 2 2
	12	[295]	MOVE     	10 1
	13	[295]	CALL     	8 3 2
	14	[295]	SETTABLE 	7 -3 8	; "text" -
	15	[296]	GETUPVAL 	8 3	; _
	16	[296]	LOADK    	9 -6	; "Default"
	17	[296]	CALL     	8 2 2
	18	[296]	SETTABLE 	7 -5 8	; "choice1_text" -
	19	[300]	CLOSURE  	8 0	; 0x7fd49fc0c4b0
	20	[300]	MOVE     	0 1
	21	[300]	MOVE     	0 2
	22	[300]	SETTABLE 	7 -7 8	; "choice1_callback" -
	23	[301]	GETUPVAL 	8 4	; C_
	24	[301]	LOADK    	9 -9	; "Font"
	25	[301]	LOADK    	10 -10	; "Fallback"
	26	[301]	CALL     	8 3 2
	27	[301]	SETTABLE 	7 -8 8	; "choice2_text" -
	28	[307]	CLOSURE  	8 1	; 0x7fd49fc0bac0
	29	[307]	MOVE     	0 1
	30	[307]	MOVE     	0 0
	31	[307]	GETUPVAL 	0 5	; Event
	32	[307]	MOVE     	0 2
	33	[307]	SETTABLE 	7 -11 8	; "choice2_callback" -
	34	[294]	CALL     	5 3 0
	35	[294]	CALL     	3 0 1
	36	[310]	RETURN   	0 1

function <./frontend/apps/reader/modules/readerfont.lua:297,300> (12 instructions, 48 bytes at 0x7fd49fc0c4b0)
0 params, 4 slots, 2 upvalues, 0 locals, 4 constants, 0 functions
	1	[298]	GETGLOBAL	0 -1	; G_reader_settings
	2	[298]	SELF     	0 0 -2	; "saveSetting"
	3	[298]	LOADK    	2 -3	; "cre_font"
	4	[298]	GETUPVAL 	3 0	; face
	5	[298]	CALL     	0 4 1
	6	[299]	GETUPVAL 	0 1	; touchmenu_instance
	7	[299]	TEST     	0 0 0
	8	[299]	JMP      	3	; to 12
	9	[299]	GETUPVAL 	0 1	; touchmenu_instance
	10	[299]	SELF     	0 0 -4	; "updateItems"
	11	[299]	CALL     	0 2 1
	12	[300]	RETURN   	0 1

function <./frontend/apps/reader/modules/readerfont.lua:302,307> (25 instructions, 100 bytes at 0x7fd49fc0bac0)
0 params, 5 slots, 4 upvalues, 0 locals, 10 constants, 0 functions
	1	[303]	GETGLOBAL	0 -1	; G_reader_settings
	2	[303]	SELF     	0 0 -2	; "saveSetting"
	3	[303]	LOADK    	2 -3	; "fallback_font"
	4	[303]	GETUPVAL 	3 0	; face
	5	[303]	CALL     	0 4 1
	6	[304]	GETUPVAL 	0 1	; self
	7	[304]	GETTABLE 	0 0 -4	; "ui"
	8	[304]	GETTABLE 	0 0 -5	; "document"
	9	[304]	SELF     	0 0 -6	; "setupFallbackFontFaces"
	10	[304]	CALL     	0 2 1
	11	[305]	GETUPVAL 	0 1	; self
	12	[305]	GETTABLE 	0 0 -4	; "ui"
	13	[305]	SELF     	0 0 -7	; "handleEvent"
	14	[305]	GETUPVAL 	2 2	; Event
	15	[305]	SELF     	2 2 -8	; "new"
	16	[305]	LOADK    	4 -9	; "UpdatePos"
	17	[305]	CALL     	2 3 0
	18	[305]	CALL     	0 0 1
	19	[306]	GETUPVAL 	0 3	; touchmenu_instance
	20	[306]	TEST     	0 0 0
	21	[306]	JMP      	3	; to 25
	22	[306]	GETUPVAL 	0 3	; touchmenu_instance
	23	[306]	SELF     	0 0 -10	; "updateItems"
	24	[306]	CALL     	0 2 1
	25	[307]	RETURN   	0 1

function <./frontend/apps/reader/modules/readerfont.lua:312,321> (9 instructions, 36 bytes at 0x7fd49fc0c430)
2 params, 4 slots, 0 upvalues, 2 locals, 7 constants, 0 functions
	1	[315]	GETTABLE 	2 0 -1	; "face_table"
	2	[315]	SETTABLE 	2 -2 -3	; "max_per_page" 5
	3	[317]	NEWTABLE 	2 0 2
	4	[318]	GETTABLE 	3 0 -6	; "font_menu_title"
	5	[318]	SETTABLE 	2 -5 3	; "text" -
	6	[319]	GETTABLE 	3 0 -1	; "face_table"
	7	[319]	SETTABLE 	2 -7 3	; "sub_item_table" -
	8	[320]	SETTABLE 	1 -4 2	; "change_font" -
	9	[321]	RETURN   	0 1

function <./frontend/apps/reader/modules/readerfont.lua:325,349> (79 instructions, 316 bytes at 0x7fd49fc0bc20)
3 params, 10 slots, 3 upvalues, 7 locals, 19 constants, 0 functions
	1	[326]	GETTABLE 	3 1 -1	; "distance"
	2	[326]	EQ       	0 3 -2	; - nil
	3	[326]	JMP      	1	; to 5
	4	[327]	SETTABLE 	1 -1 -3	; "distance" 1
	5	[329]	EQ       	1 2 -4	; - -1
	6	[329]	JMP      	3	; to 10
	7	[329]	EQ       	1 2 -3	; - 1
	8	[329]	JMP      	1	; to 10
	9	[331]	LOADK    	2 -3	; 1
	10	[333]	GETGLOBAL	3 -5	; math
	11	[333]	GETTABLE 	3 3 -6	; "ceil"
	12	[333]	GETTABLE 	4 0 -7	; "steps"
	13	[333]	LEN      	4 4
	14	[333]	MUL      	4 -8 4	; 2 -
	15	[333]	GETTABLE 	5 1 -1	; "distance"
	16	[333]	MUL      	4 4 5
	17	[333]	GETTABLE 	5 0 -9	; "gestureScale"
	18	[333]	DIV      	4 4 5
	19	[333]	CALL     	3 2 2
	20	[334]	GETTABLE 	4 0 -7	; "steps"
	21	[334]	GETTABLE 	4 4 3
	22	[334]	TEST     	4 0 1
	23	[334]	JMP      	4	; to 28
	24	[334]	GETTABLE 	4 0 -7	; "steps"
	25	[334]	GETTABLE 	5 0 -7	; "steps"
	26	[334]	LEN      	5 5
	27	[334]	GETTABLE 	4 4 5
	28	[335]	EQ       	0 2 -3	; - 1
	29	[335]	JMP      	24	; to 54
	30	[336]	GETUPVAL 	5 0	; Notification
	31	[336]	SELF     	5 5 -10	; "new"
	32	[336]	NEWTABLE 	7 0 1
	33	[336]	GETUPVAL 	8 1	; _
	34	[336]	LOADK    	9 -12	; "Increasing font size\226\128\166"
	35	[336]	CALL     	8 2 2
	36	[336]	SETTABLE 	7 -11 8	; "text" -
	37	[336]	CALL     	5 3 2
	38	[337]	GETUPVAL 	6 2	; UIManager
	39	[337]	SELF     	6 6 -13	; "show"
	40	[337]	MOVE     	8 5
	41	[337]	CALL     	6 3 1
	42	[338]	GETUPVAL 	6 2	; UIManager
	43	[338]	SELF     	6 6 -14	; "forceRePaint"
	44	[338]	CALL     	6 2 1
	45	[339]	SELF     	6 0 -15	; "onChangeSize"
	46	[339]	LOADK    	8 -16	; "increase"
	47	[339]	MOVE     	9 4
	48	[339]	CALL     	6 4 1
	49	[340]	GETUPVAL 	6 2	; UIManager
	50	[340]	SELF     	6 6 -17	; "close"
	51	[340]	MOVE     	8 5
	52	[340]	CALL     	6 3 1
	53	[340]	JMP      	23	; to 77
	54	[342]	GETUPVAL 	5 0	; Notification
	55	[342]	SELF     	5 5 -10	; "new"
	56	[342]	NEWTABLE 	7 0 1
	57	[342]	GETUPVAL 	8 1	; _
	58	[342]	LOADK    	9 -18	; "Decreasing font size\226\128\166"
	59	[342]	CALL     	8 2 2
	60	[342]	SETTABLE 	7 -11 8	; "text" -
	61	[342]	CALL     	5 3 2
	62	[343]	GETUPVAL 	6 2	; UIManager
	63	[343]	SELF     	6 6 -13	; "show"
	64	[343]	MOVE     	8 5
	65	[343]	CALL     	6 3 1
	66	[344]	GETUPVAL 	6 2	; UIManager
	67	[344]	SELF     	6 6 -14	; "forceRePaint"
	68	[344]	CALL     	6 2 1
	69	[345]	SELF     	6 0 -15	; "onChangeSize"
	70	[345]	LOADK    	8 -19	; "decrease"
	71	[345]	MOVE     	9 4
	72	[345]	CALL     	6 4 1
	73	[346]	GETUPVAL 	6 2	; UIManager
	74	[346]	SELF     	6 6 -17	; "close"
	75	[346]	MOVE     	8 5
	76	[346]	CALL     	6 3 1
	77	[348]	LOADBOOL 	5 1 0
	78	[348]	RETURN   	5 2
	79	[349]	RETURN   	0 1

function <./frontend/apps/reader/modules/readerfont.lua:351,395> (80 instructions, 320 bytes at 0x7fd49fc0e130)
1 param, 10 slots, 6 upvalues, 7 locals, 23 constants, 3 functions
	1	[352]	NEWTABLE 	1 0 0
	2	[354]	GETUPVAL 	2 0	; Device
	3	[354]	SELF     	2 2 -1	; "isAndroid"
	4	[354]	CALL     	2 2 2
	5	[354]	TEST     	2 0 1
	6	[354]	JMP      	10	; to 17
	7	[354]	GETUPVAL 	2 0	; Device
	8	[354]	SELF     	2 2 -2	; "isDesktop"
	9	[354]	CALL     	2 2 2
	10	[354]	TEST     	2 0 1
	11	[354]	JMP      	5	; to 17
	12	[354]	GETUPVAL 	2 0	; Device
	13	[354]	SELF     	2 2 -3	; "isEmulator"
	14	[354]	CALL     	2 2 2
	15	[354]	TEST     	2 0 0
	16	[354]	JMP      	18	; to 35
	17	[355]	GETGLOBAL	2 -4	; ipairs
	18	[355]	GETGLOBAL	3 -5	; require
	19	[355]	LOADK    	4 -6	; "ui/elements/font_settings"
	20	[355]	CALL     	3 2 2
	21	[355]	SELF     	3 3 -7	; "getSystemFontMenuItems"
	22	[355]	CALL     	3 2 0
	23	[355]	CALL     	2 0 4
	24	[355]	JMP      	5	; to 30
	25	[356]	GETGLOBAL	7 -8	; table
	26	[356]	GETTABLE 	7 7 -9	; "insert"
	27	[356]	MOVE     	8 1
	28	[356]	MOVE     	9 6
	29	[356]	CALL     	7 3 1
	30	[355]	TFORLOOP 	2 2
	31	[356]	JMP      	-7	; to 25
	32	[358]	LEN      	2 1
	33	[358]	GETTABLE 	2 1 2
	34	[358]	SETTABLE 	2 -10 -11	; "separator" true
	35	[361]	GETGLOBAL	2 -8	; table
	36	[361]	GETTABLE 	2 2 -9	; "insert"
	37	[361]	MOVE     	3 1
	38	[361]	NEWTABLE 	4 0 5
	39	[362]	GETUPVAL 	5 1	; _
	40	[362]	LOADK    	6 -13	; "Use additional fallback fonts"
	41	[362]	CALL     	5 2 2
	42	[362]	SETTABLE 	4 -12 5	; "text" -
	43	[365]	CLOSURE  	5 0	; 0x7fd49fc0e040
	44	[365]	SETTABLE 	4 -14 5	; "checked_func" -
	45	[370]	CLOSURE  	5 1	; 0x7fd49fc0ee20
	46	[370]	MOVE     	0 0
	47	[370]	GETUPVAL 	0 2	; Event
	48	[370]	SETTABLE 	4 -15 5	; "callback" -
	49	[371]	GETUPVAL 	5 3	; T
	50	[371]	GETUPVAL 	6 1	; _
	51	[378]	LOADK    	7 -17	; "Enable additional fallback fonts, for the most complete script and language coverage.\nThese fonts will be used in this order:\n\n%1\n\nYou can set a preferred fallback font with a long-press on a font name, and it will be used before these.\nIf that font happens to be part of this list already, it will be used first."
	52	[371]	CALL     	6 2 2
	53	[379]	GETGLOBAL	7 -8	; table
	54	[379]	GETTABLE 	7 7 -18	; "concat"
	55	[379]	GETTABLE 	8 0 -19	; "ui"
	56	[379]	GETTABLE 	8 8 -20	; "document"
	57	[379]	GETTABLE 	8 8 -21	; "fallback_fonts"
	58	[379]	LOADK    	9 -22	; "\n"
	59	[379]	CALL     	7 3 0
	60	[371]	CALL     	5 0 2
	61	[379]	SETTABLE 	4 -16 5	; "help_text" -
	62	[380]	SETTABLE 	4 -10 -11	; "separator" true
	63	[361]	CALL     	2 3 1
	64	[383]	GETGLOBAL	2 -8	; table
	65	[383]	GETTABLE 	2 2 -9	; "insert"
	66	[383]	MOVE     	3 1
	67	[383]	NEWTABLE 	4 0 2
	68	[384]	GETUPVAL 	5 1	; _
	69	[384]	LOADK    	6 -23	; "Generate font test document"
	70	[384]	CALL     	5 2 2
	71	[384]	SETTABLE 	4 -12 5	; "text" -
	72	[392]	CLOSURE  	5 2	; 0x7fd49fc0ece0
	73	[392]	GETUPVAL 	0 4	; UIManager
	74	[392]	GETUPVAL 	0 5	; ConfirmBox
	75	[392]	GETUPVAL 	0 1	; _
	76	[392]	MOVE     	0 0
	77	[392]	SETTABLE 	4 -15 5	; "callback" -
	78	[383]	CALL     	2 3 1
	79	[394]	RETURN   	1 2
	80	[395]	RETURN   	0 1

function <./frontend/apps/reader/modules/readerfont.lua:363,365> (6 instructions, 24 bytes at 0x7fd49fc0e040)
0 params, 3 slots, 0 upvalues, 0 locals, 3 constants, 0 functions
	1	[364]	GETGLOBAL	0 -1	; G_reader_settings
	2	[364]	SELF     	0 0 -2	; "nilOrTrue"
	3	[364]	LOADK    	2 -3	; "additional_fallback_fonts"
	4	[364]	TAILCALL 	0 3 0
	5	[364]	RETURN   	0 0
	6	[365]	RETURN   	0 1

function <./frontend/apps/reader/modules/readerfont.lua:366,370> (18 instructions, 72 bytes at 0x7fd49fc0ee20)
0 params, 5 slots, 2 upvalues, 0 locals, 9 constants, 0 functions
	1	[367]	GETGLOBAL	0 -1	; G_reader_settings
	2	[367]	SELF     	0 0 -2	; "flipNilOrTrue"
	3	[367]	LOADK    	2 -3	; "additional_fallback_fonts"
	4	[367]	CALL     	0 3 1
	5	[368]	GETUPVAL 	0 0	; self
	6	[368]	GETTABLE 	0 0 -4	; "ui"
	7	[368]	GETTABLE 	0 0 -5	; "document"
	8	[368]	SELF     	0 0 -6	; "setupFallbackFontFaces"
	9	[368]	CALL     	0 2 1
	10	[369]	GETUPVAL 	0 0	; self
	11	[369]	GETTABLE 	0 0 -4	; "ui"
	12	[369]	SELF     	0 0 -7	; "handleEvent"
	13	[369]	GETUPVAL 	2 1	; Event
	14	[369]	SELF     	2 2 -8	; "new"
	15	[369]	LOADK    	4 -9	; "UpdatePos"
	16	[369]	CALL     	2 3 0
	17	[369]	CALL     	0 0 1
	18	[370]	RETURN   	0 1

function <./frontend/apps/reader/modules/readerfont.lua:385,392> (15 instructions, 60 bytes at 0x7fd49fc0ece0)
0 params, 7 slots, 4 upvalues, 0 locals, 5 constants, 1 function
	1	[386]	GETUPVAL 	0 0	; UIManager
	2	[386]	SELF     	0 0 -1	; "show"
	3	[386]	GETUPVAL 	2 1	; ConfirmBox
	4	[386]	SELF     	2 2 -2	; "new"
	5	[386]	NEWTABLE 	4 0 2
	6	[387]	GETUPVAL 	5 2	; _
	7	[387]	LOADK    	6 -4	; "Would you like to generate an HTML document showing some sample text rendered with each available font?"
	8	[387]	CALL     	5 2 2
	9	[387]	SETTABLE 	4 -3 5	; "text" -
	10	[390]	CLOSURE  	5 0	; 0x7fd49fc0fdb0
	11	[390]	GETUPVAL 	0 3	; self
	12	[390]	SETTABLE 	4 -5 5	; "ok_callback" -
	13	[386]	CALL     	2 3 0
	14	[386]	CALL     	0 0 1
	15	[392]	RETURN   	0 1

function <./frontend/apps/reader/modules/readerfont.lua:388,390> (4 instructions, 16 bytes at 0x7fd49fc0fdb0)
0 params, 2 slots, 1 upvalue, 0 locals, 1 constant, 0 functions
	1	[389]	GETUPVAL 	0 0	; self
	2	[389]	SELF     	0 0 -1	; "buildFontsTestDocument"
	3	[389]	CALL     	0 2 1
	4	[390]	RETURN   	0 1

function <./frontend/apps/reader/modules/readerfont.lua:404,467> (165 instructions, 660 bytes at 0x7fd49fc10540)
1 param, 18 slots, 8 upvalues, 18 locals, 41 constants, 1 function
	1	[406]	GETGLOBAL	2 -1	; io
	2	[406]	GETTABLE 	2 2 -2	; "open"
	3	[406]	GETUPVAL 	3 0	; FONT_TEST_USER_SAMPLE_PATH
	4	[406]	LOADK    	4 -3	; "r"
	5	[406]	CALL     	2 3 2
	6	[407]	TEST     	2 0 0
	7	[407]	JMP      	6	; to 14
	8	[408]	SELF     	3 2 -4	; "read"
	9	[408]	LOADK    	5 -5	; "*all"
	10	[408]	CALL     	3 3 2
	11	[408]	MOVE     	1 3
	12	[409]	SELF     	3 2 -6	; "close"
	13	[409]	CALL     	3 2 1
	14	[411]	TEST     	1 0 1
	15	[411]	JMP      	16	; to 32
	16	[412]	GETGLOBAL	3 -1	; io
	17	[412]	GETTABLE 	3 3 -2	; "open"
	18	[412]	GETUPVAL 	4 1	; FONT_TEST_DEFAULT_SAMPLE_PATH
	19	[412]	LOADK    	5 -3	; "r"
	20	[412]	CALL     	3 3 2
	21	[412]	MOVE     	2 3
	22	[413]	TEST     	2 0 1
	23	[413]	JMP      	2	; to 26
	24	[413]	LOADNIL  	3 3
	25	[413]	RETURN   	3 2
	26	[414]	SELF     	3 2 -4	; "read"
	27	[414]	LOADK    	5 -5	; "*all"
	28	[414]	CALL     	3 3 2
	29	[414]	MOVE     	1 3
	30	[415]	SELF     	3 2 -6	; "close"
	31	[415]	CALL     	3 2 1
	32	[417]	GETGLOBAL	3 -7	; G_reader_settings
	33	[417]	SELF     	3 3 -8	; "readSetting"
	34	[417]	LOADK    	5 -9	; "home_dir"
	35	[417]	CALL     	3 3 2
	36	[418]	TEST     	3 0 1
	37	[418]	JMP      	6	; to 44
	38	[418]	GETGLOBAL	4 -10	; require
	39	[418]	LOADK    	5 -11	; "apps/filemanager/filemanagerutil"
	40	[418]	CALL     	4 2 2
	41	[418]	GETTABLE 	4 4 -12	; "getDefaultDir"
	42	[418]	CALL     	4 1 2
	43	[418]	MOVE     	3 4
	44	[419]	TEST     	3 0 1
	45	[419]	JMP      	1	; to 47
	46	[419]	LOADK    	3 -13	; "."
	47	[420]	MOVE     	4 3
	48	[420]	LOADK    	5 -14	; "/"
	49	[420]	GETUPVAL 	6 2	; FONT_TEST_FINAL_FILENAME
	50	[420]	CONCAT   	4 4 6
	51	[421]	GETGLOBAL	5 -1	; io
	52	[421]	GETTABLE 	5 5 -2	; "open"
	53	[421]	MOVE     	6 4
	54	[421]	LOADK    	7 -15	; "w"
	55	[421]	CALL     	5 3 2
	56	[421]	MOVE     	2 5
	57	[422]	TEST     	2 0 1
	58	[422]	JMP      	1	; to 60
	59	[422]	RETURN   	0 1
	60	[424]	SELF     	5 2 -16	; "write"
	61	[424]	GETGLOBAL	7 -17	; string
	62	[424]	GETTABLE 	7 7 -18	; "format"
	63	[442]	LOADK    	8 -19	; "<?xml version=\"1.0\" encoding=\"UTF-8\"?>\n<html>\n<head>\n<title>%s</title>\n<style>\nsection > title {\n  font-size: large;\n  font-weight: bold;\n  text-align: center;\n  page-break-before: always;\n  margin-bottom: 0.5em;\n}\na { color: black; }\n</style>\n</head>\n<body>\n<section id=\"list\"><title>%s</title></section>\n"
	64	[442]	GETUPVAL 	9 3	; _
	65	[442]	LOADK    	10 -20	; "Available fonts test document"
	66	[442]	CALL     	9 2 2
	67	[442]	GETUPVAL 	10 3	; _
	68	[442]	LOADK    	11 -21	; "AVAILABLE FONTS"
	69	[442]	CALL     	10 2 0
	70	[424]	CALL     	7 0 0
	71	[424]	CALL     	5 0 1
	72	[443]	GETGLOBAL	5 -22	; cre
	73	[443]	GETTABLE 	5 5 -23	; "getFontFaces"
	74	[443]	CALL     	5 1 2
	75	[444]	SELF     	6 2 -16	; "write"
	76	[444]	LOADK    	8 -24	; "<div style='margin: 2em'>\n"
	77	[444]	CALL     	6 3 1
	78	[445]	GETGLOBAL	6 -25	; ipairs
	79	[445]	MOVE     	7 5
	80	[445]	CALL     	6 2 4
	81	[445]	JMP      	16	; to 98
	82	[446]	SELF     	11 10 -26	; "gsub"
	83	[446]	LOADK    	13 -27	; " "
	84	[446]	LOADK    	14 -28	; "_"
	85	[446]	CALL     	11 4 2
	86	[446]	SELF     	11 11 -26	; "gsub"
	87	[446]	LOADK    	13 -29	; "'"
	88	[446]	LOADK    	14 -28	; "_"
	89	[446]	CALL     	11 4 2
	90	[447]	SELF     	12 2 -16	; "write"
	91	[447]	GETGLOBAL	14 -17	; string
	92	[447]	GETTABLE 	14 14 -18	; "format"
	93	[447]	LOADK    	15 -30	; "  <div><a href='#%s'>%s</a></div>\n"
	94	[447]	MOVE     	16 11
	95	[447]	MOVE     	17 10
	96	[447]	CALL     	14 4 0
	97	[447]	CALL     	12 0 1
	98	[445]	TFORLOOP 	6 2
	99	[447]	JMP      	-18	; to 82
	100	[449]	SELF     	6 2 -16	; "write"
	101	[449]	LOADK    	8 -31	; "</div>\n\n"
	102	[449]	CALL     	6 3 1
	103	[450]	GETGLOBAL	6 -25	; ipairs
	104	[450]	MOVE     	7 5
	105	[450]	CALL     	6 2 4
	106	[450]	JMP      	29	; to 136
	107	[451]	SELF     	11 10 -26	; "gsub"
	108	[451]	LOADK    	13 -27	; " "
	109	[451]	LOADK    	14 -28	; "_"
	110	[451]	CALL     	11 4 2
	111	[451]	SELF     	11 11 -26	; "gsub"
	112	[451]	LOADK    	13 -29	; "'"
	113	[451]	LOADK    	14 -28	; "_"
	114	[451]	CALL     	11 4 2
	115	[452]	SELF     	12 2 -16	; "write"
	116	[452]	GETGLOBAL	14 -17	; string
	117	[452]	GETTABLE 	14 14 -18	; "format"
	118	[452]	LOADK    	15 -32	; "<section id='%s'><title>%s</title></section>\n"
	119	[452]	MOVE     	16 11
	120	[452]	MOVE     	17 10
	121	[452]	CALL     	14 4 0
	122	[452]	CALL     	12 0 1
	123	[453]	SELF     	12 2 -16	; "write"
	124	[453]	GETGLOBAL	14 -17	; string
	125	[453]	GETTABLE 	14 14 -18	; "format"
	126	[453]	LOADK    	15 -33	; "<div style='font-family: %s'>\n"
	127	[453]	MOVE     	16 10
	128	[453]	CALL     	14 3 0
	129	[453]	CALL     	12 0 1
	130	[454]	SELF     	12 2 -16	; "write"
	131	[454]	MOVE     	14 1
	132	[454]	CALL     	12 3 1
	133	[455]	SELF     	12 2 -16	; "write"
	134	[455]	LOADK    	14 -34	; "\n</div>\n\n"
	135	[455]	CALL     	12 3 1
	136	[450]	TFORLOOP 	6 2
	137	[455]	JMP      	-31	; to 107
	138	[457]	SELF     	6 2 -16	; "write"
	139	[457]	LOADK    	8 -35	; "</body></html>\n"
	140	[457]	CALL     	6 3 1
	141	[458]	SELF     	6 2 -6	; "close"
	142	[458]	CALL     	6 2 1
	143	[459]	GETUPVAL 	6 4	; UIManager
	144	[459]	SELF     	6 6 -36	; "show"
	145	[459]	GETUPVAL 	8 5	; ConfirmBox
	146	[459]	SELF     	8 8 -37	; "new"
	147	[459]	NEWTABLE 	10 0 2
	148	[460]	GETUPVAL 	11 6	; T
	149	[460]	GETUPVAL 	12 3	; _
	150	[460]	LOADK    	13 -39	; "Document created as:\n%1\n\nWould you like to read it now?"
	151	[460]	CALL     	12 2 2
	152	[460]	GETUPVAL 	13 7	; BD
	153	[460]	GETTABLE 	13 13 -40	; "filepath"
	154	[460]	MOVE     	14 4
	155	[460]	CALL     	13 2 0
	156	[460]	CALL     	11 0 2
	157	[460]	SETTABLE 	10 -38 11	; "text" -
	158	[465]	CLOSURE  	11 0	; 0x7fd49fc0c720
	159	[465]	GETUPVAL 	0 4	; UIManager
	160	[465]	MOVE     	0 0
	161	[465]	MOVE     	0 4
	162	[465]	SETTABLE 	10 -41 11	; "ok_callback" -
	163	[459]	CALL     	8 3 0
	164	[459]	CALL     	6 0 1
	165	[467]	RETURN   	0 1

function <./frontend/apps/reader/modules/readerfont.lua:461,465> (8 instructions, 32 bytes at 0x7fd49fc0c720)
0 params, 4 slots, 3 upvalues, 0 locals, 2 constants, 1 function
	1	[462]	GETUPVAL 	0 0	; UIManager
	2	[462]	SELF     	0 0 -1	; "scheduleIn"
	3	[462]	LOADK    	2 -2	; 1
	4	[464]	CLOSURE  	3 0	; 0x7fd49fc10a30
	5	[464]	GETUPVAL 	0 1	; self
	6	[464]	GETUPVAL 	0 2	; font_test_final_path
	7	[462]	CALL     	0 4 1
	8	[465]	RETURN   	0 1

function <./frontend/apps/reader/modules/readerfont.lua:462,464> (6 instructions, 24 bytes at 0x7fd49fc10a30)
0 params, 3 slots, 2 upvalues, 0 locals, 2 constants, 0 functions
	1	[463]	GETUPVAL 	0 0	; self
	2	[463]	GETTABLE 	0 0 -1	; "ui"
	3	[463]	SELF     	0 0 -2	; "switchDocument"
	4	[463]	GETUPVAL 	2 1	; font_test_final_path
	5	[463]	CALL     	0 3 1
	6	[464]	RETURN   	0 1
