-- BYTECODE -- readerpanning.lua:15-33
0001    UGET     1   0      ; Device
0002    MOV      2   1
0003    TGETS    1   1   0  ; "hasKeyboard"
0004    CALL     1   2   2
0005    ISF          1
0006    JMP      2 => 0033
0007    TDUP     1   6
0008    TDUP     2   3
0009    TDUP     3   2
0010    TSETB    3   2   1
0011    TDUP     3   4
0012    TSETS    3   2   5  ; "args"
0013    TSETS    2   1   7  ; "MoveUp"
0014    TDUP     2   9
0015    TDUP     3   8
0016    TSETB    3   2   1
0017    TDUP     3  10
0018    TSETS    3   2   5  ; "args"
0019    TSETS    2   1  11  ; "MoveDown"
0020    TDUP     2  13
0021    TDUP     3  12
0022    TSETB    3   2   1
0023    TDUP     3  14
0024    TSETS    3   2   5  ; "args"
0025    TSETS    2   1  15  ; "MoveLeft"
0026    TDUP     2  17
0027    TDUP     3  16
0028    TSETB    3   2   1
0029    TDUP     3  18
0030    TSETS    3   2   5  ; "args"
0031    TSETS    2   1  19  ; "MoveRight"
0032    TSETS    1   0   1  ; "key_events"
0033 => RET0     0   1

-- BYTECODE -- readerpanning.lua:35-37
0001    TSETS    1   0   0  ; "dimen"
0002    RET0     0   1

-- BYTECODE -- readerpanning.lua:39-46
0001    GGET     3   0      ; "unpack"
0002    MOV      4   1
0003    CALL     3   3   2
0004    TGETS    5   0   1  ; "view"
0005    MOV      6   5
0006    TGETS    5   5   2  ; "PanningUpdate"
0007    TGETS    7   0   3  ; "panning_steps"
0008    TGETS    7   7   4  ; "normal"
0009    MULVV    7   3   7
0010    TGETS    8   0   5  ; "dimen"
0011    TGETS    8   8   6  ; "w"
0012    MULVV    7   7   8
0013    DIVVN    7   7   0  ; 100
0014    TGETS    8   0   3  ; "panning_steps"
0015    TGETS    8   8   4  ; "normal"
0016    MULVV    8   4   8
0017    TGETS    9   0   5  ; "dimen"
0018    TGETS    9   9   7  ; "h"
0019    MULVV    8   8   9
0020    DIVVN    8   8   0  ; 100
0021    CALL     5   1   4
0022    KPRI     5   2
0023    RET1     5   2

-- BYTECODE -- readerpanning.lua:0-49
0001    GGET     0   0      ; "require"
0002    KSTR     1   1      ; "ui/widget/container/inputcontainer"
0003    CALL     0   2   2
0004    GGET     1   0      ; "require"
0005    KSTR     2   2      ; "device"
0006    CALL     1   2   2
0007    GGET     2   0      ; "require"
0008    KSTR     3   3      ; "gettext"
0009    CALL     2   2   2
0010    MOV      4   0
0011    TGETS    3   0   4  ; "new"
0012    TDUP     5   6
0013    TDUP     6   5
0014    TSETS    6   5   7  ; "panning_steps"
0015    CALL     3   2   3
0016    FNEW     4   9      ; readerpanning.lua:15
0017    TSETS    4   3   8  ; "init"
0018    FNEW     4  11      ; readerpanning.lua:35
0019    TSETS    4   3  10  ; "onSetDimensions"
0020    FNEW     4  13      ; readerpanning.lua:39
0021    TSETS    4   3  12  ; "onPanning"
0022    UCLO     0 => 0023
0023 => RET1     3   2

