
main <./frontend/apps/reader/modules/readerrolling.lua:0,0> (223 instructions, 892 bytes at 0x7fc0a2406900)
0+ params, 23 slots, 0 upvalues, 21 locals, 86 constants, 44 functions
	1	[1]	GETGLOBAL	0 -1	; require
	2	[1]	LOADK    	1 -2	; "ui/bidi"
	3	[1]	CALL     	0 2 2
	4	[2]	GETGLOBAL	1 -1	; require
	5	[2]	LOADK    	2 -3	; "ffi/blitbuffer"
	6	[2]	CALL     	1 2 2
	7	[3]	GETGLOBAL	2 -1	; require
	8	[3]	LOADK    	3 -4	; "ui/widget/confirmbox"
	9	[3]	CALL     	2 2 2
	10	[4]	GETGLOBAL	3 -1	; require
	11	[4]	LOADK    	4 -5	; "device"
	12	[4]	CALL     	3 2 2
	13	[5]	GETGLOBAL	4 -1	; require
	14	[5]	LOADK    	5 -6	; "ui/event"
	15	[5]	CALL     	4 2 2
	16	[6]	GETGLOBAL	5 -1	; require
	17	[6]	LOADK    	6 -7	; "ui/widget/container/inputcontainer"
	18	[6]	CALL     	5 2 2
	19	[7]	GETGLOBAL	6 -1	; require
	20	[7]	LOADK    	7 -8	; "ui/widget/multiconfirmbox"
	21	[7]	CALL     	6 2 2
	22	[8]	GETGLOBAL	7 -1	; require
	23	[8]	LOADK    	8 -9	; "ui/widget/progresswidget"
	24	[8]	CALL     	7 2 2
	25	[9]	GETGLOBAL	8 -1	; require
	26	[9]	LOADK    	9 -10	; "apps/reader/modules/readerpanning"
	27	[9]	CALL     	8 2 2
	28	[10]	GETGLOBAL	9 -1	; require
	29	[10]	LOADK    	10 -11	; "ui/size"
	30	[10]	CALL     	9 2 2
	31	[11]	GETGLOBAL	10 -1	; require
	32	[11]	LOADK    	11 -12	; "ui/timeval"
	33	[11]	CALL     	10 2 2
	34	[12]	GETGLOBAL	11 -1	; require
	35	[12]	LOADK    	12 -13	; "ui/uimanager"
	36	[12]	CALL     	11 2 2
	37	[13]	GETGLOBAL	12 -1	; require
	38	[13]	LOADK    	13 -14	; "bit"
	39	[13]	CALL     	12 2 2
	40	[14]	GETGLOBAL	13 -1	; require
	41	[14]	LOADK    	14 -15	; "logger"
	42	[14]	CALL     	13 2 2
	43	[15]	GETGLOBAL	14 -1	; require
	44	[15]	LOADK    	15 -16	; "gettext"
	45	[15]	CALL     	14 2 2
	46	[16]	GETTABLE 	15 3 -17	; "screen"
	47	[17]	GETGLOBAL	16 -1	; require
	48	[17]	LOADK    	17 -18	; "ffi/util"
	49	[17]	CALL     	16 2 2
	50	[17]	GETTABLE 	16 16 -19	; "template"
	51	[19]	GETTABLE 	17 12 -20	; "band"
	52	[41]	SELF     	18 5 -21	; "new"
	53	[41]	NEWTABLE 	20 0 12
	54	[42]	SETTABLE 	20 -22 -23	; "pan_rate" 30
	55	[43]	SETTABLE 	20 -24 -25	; "old_doc_height" nil
	56	[44]	SETTABLE 	20 -26 -25	; "old_page" nil
	57	[45]	SETTABLE 	20 -27 -28	; "current_pos" 0
	58	[46]	SETTABLE 	20 -29 -25	; "inverse_reading_order" nil
	59	[48]	SETTABLE 	20 -30 -25	; "current_page" nil
	60	[49]	SETTABLE 	20 -31 -25	; "xpointer" nil
	61	[50]	GETTABLE 	21 8 -32	; "panning_steps"
	62	[50]	SETTABLE 	20 -32 21	; "panning_steps" -
	63	[51]	SETTABLE 	20 -33 -25	; "show_overlap_enable" nil
	64	[52]	SETTABLE 	20 -34 -35	; "cre_top_bar_enabled" false
	65	[53]	SETTABLE 	20 -36 -37	; "visible_pages" 1
	66	[57]	SETTABLE 	20 -38 -37	; "odd_or_even_first_page" 1
	67	[41]	CALL     	18 3 2
	68	[131]	CLOSURE  	19 0	; 0x7fc0a24070e0
	69	[131]	MOVE     	0 3
	70	[60]	SETTABLE 	18 -39 19	; "init" -
	71	[244]	CLOSURE  	19 1	; 0x7fc0a2408b00
	72	[244]	MOVE     	0 4
	73	[244]	MOVE     	0 13
	74	[133]	SETTABLE 	18 -40 19	; "onReadSettings" -
	75	[261]	CLOSURE  	19 2	; 0x7fc0a240adf0
	76	[261]	MOVE     	0 13
	77	[248]	SETTABLE 	18 -41 19	; "onCloseDocument" -
	78	[284]	CLOSURE  	19 3	; 0x7fc0a240b3d0
	79	[284]	MOVE     	0 14
	80	[284]	MOVE     	0 11
	81	[284]	MOVE     	0 2
	82	[284]	MOVE     	0 16
	83	[263]	SETTABLE 	18 -42 19	; "onCheckDomStyleCoherence" -
	84	[299]	CLOSURE  	19 4	; 0x7fc0a240c2f0
	85	[286]	SETTABLE 	18 -43 19	; "onSaveSettings" -
	86	[304]	CLOSURE  	19 5	; 0x7fc0a240be20
	87	[301]	SETTABLE 	18 -44 19	; "onReaderReady" -
	88	[386]	CLOSURE  	19 6	; 0x7fc0a24094a0
	89	[386]	MOVE     	0 3
	90	[386]	MOVE     	0 0
	91	[306]	SETTABLE 	18 -45 19	; "setupTouchZones" -
	92	[390]	CLOSURE  	19 7	; 0x7fc0a240c9b0
	93	[388]	SETTABLE 	18 -46 19	; "getLastProgress" -
	94	[480]	CLOSURE  	19 8	; 0x7fc0a240d350
	95	[480]	MOVE     	0 14
	96	[480]	MOVE     	0 4
	97	[480]	MOVE     	0 11
	98	[480]	MOVE     	0 6
	99	[480]	MOVE     	0 16
	100	[480]	MOVE     	0 15
	101	[392]	SETTABLE 	18 -47 19	; "addToMainMenu" -
	102	[490]	CLOSURE  	19 9	; 0x7fc0a2411820
	103	[482]	SETTABLE 	18 -48 19	; "getLastPercent" -
	104	[512]	CLOSURE  	19 10	; 0x7fc0a2411b10
	105	[512]	MOVE     	0 0
	106	[512]	MOVE     	0 11
	107	[492]	SETTABLE 	18 -49 19	; "onSwipe" -
	108	[530]	CLOSURE  	19 11	; 0x7fc0a2411c20
	109	[530]	MOVE     	0 11
	110	[530]	MOVE     	0 4
	111	[514]	SETTABLE 	18 -50 19	; "onPan" -
	112	[535]	CLOSURE  	19 12	; 0x7fc0a240ced0
	113	[532]	SETTABLE 	18 -51 19	; "onPosUpdate" -
	114	[540]	CLOSURE  	19 13	; 0x7fc0a240e5a0
	115	[537]	SETTABLE 	18 -52 19	; "onPageUpdate" -
	116	[544]	CLOSURE  	19 14	; 0x7fc0a24125c0
	117	[542]	SETTABLE 	18 -53 19	; "onResume" -
	118	[555]	CLOSURE  	19 15	; 0x7fc0a240f760
	119	[546]	SETTABLE 	18 -54 19	; "onGotoNextChapter" -
	120	[565]	CLOSURE  	19 16	; 0x7fc0a24121c0
	121	[557]	SETTABLE 	18 -55 19	; "onGotoPrevChapter" -
	122	[569]	CLOSURE  	19 17	; 0x7fc0a24117a0
	123	[567]	SETTABLE 	18 -56 19	; "onNotCharging" -
	124	[576]	CLOSURE  	19 18	; 0x7fc0a240a5c0
	125	[576]	MOVE     	0 13
	126	[571]	SETTABLE 	18 -57 19	; "onGotoPercent" -
	127	[584]	CLOSURE  	19 19	; 0x7fc0a240cd50
	128	[578]	SETTABLE 	18 -58 19	; "onGotoPage" -
	129	[592]	CLOSURE  	19 20	; 0x7fc0a240ee70
	130	[586]	SETTABLE 	18 -59 19	; "onGotoRelativePage" -
	131	[703]	CLOSURE  	19 21	; 0x7fc0a2410060
	132	[703]	MOVE     	0 11
	133	[703]	MOVE     	0 15
	134	[703]	MOVE     	0 0
	135	[703]	MOVE     	0 1
	136	[594]	SETTABLE 	18 -60 19	; "onGotoXPointer" -
	137	[707]	CLOSURE  	19 22	; 0x7fc0a2412fc0
	138	[705]	SETTABLE 	18 -61 19	; "getBookLocation" -
	139	[711]	CLOSURE  	19 23	; 0x7fc0a2413520
	140	[709]	SETTABLE 	18 -62 19	; "onRestoreBookLocation" -
	141	[753]	CLOSURE  	19 24	; 0x7fc0a24132c0
	142	[753]	MOVE     	0 13
	143	[753]	MOVE     	0 15
	144	[753]	MOVE     	0 4
	145	[713]	SETTABLE 	18 -63 19	; "onGotoViewRel" -
	146	[764]	CLOSURE  	19 25	; 0x7fc0a2413890
	147	[764]	MOVE     	0 11
	148	[764]	MOVE     	0 4
	149	[755]	SETTABLE 	18 -64 19	; "onPanning" -
	150	[769]	CLOSURE  	19 26	; 0x7fc0a2413d70
	151	[766]	SETTABLE 	18 -65 19	; "onZoom" -
	152	[793]	CLOSURE  	19 27	; 0x7fc0a2414200
	153	[793]	MOVE     	0 11
	154	[776]	SETTABLE 	18 -66 19	; "onUpdatePos" -
	155	[819]	CLOSURE  	19 28	; 0x7fc0a2414990
	156	[819]	MOVE     	0 4
	157	[819]	MOVE     	0 11
	158	[795]	SETTABLE 	18 -67 19	; "updatePos" -
	159	[839]	CLOSURE  	19 29	; 0x7fc0a2414a40
	160	[839]	MOVE     	0 4
	161	[839]	MOVE     	0 11
	162	[824]	SETTABLE 	18 -68 19	; "onChangeViewMode" -
	163	[848]	CLOSURE  	19 30	; 0x7fc0a24157b0
	164	[848]	MOVE     	0 4
	165	[841]	SETTABLE 	18 -69 19	; "onRedrawCurrentView" -
	166	[871]	CLOSURE  	19 31	; 0x7fc0a2415a60
	167	[871]	MOVE     	0 15
	168	[850]	SETTABLE 	18 -70 19	; "onSetDimensions" -
	169	[879]	CLOSURE  	19 32	; 0x7fc0a24159b0
	170	[879]	MOVE     	0 4
	171	[873]	SETTABLE 	18 -71 19	; "onChangeScreenMode" -
	172	[884]	CLOSURE  	19 33	; 0x7fc0a2411610
	173	[884]	MOVE     	0 11
	174	[881]	SETTABLE 	18 -72 19	; "onColorRenderingUpdate" -
	175	[922]	CLOSURE  	19 34	; 0x7fc0a2416780
	176	[922]	MOVE     	0 4
	177	[889]	SETTABLE 	18 -73 19	; "_gotoPos" -
	178	[926]	CLOSURE  	19 35	; 0x7fc0a2416d60
	179	[924]	SETTABLE 	18 -74 19	; "_gotoPercent" -
	180	[949]	CLOSURE  	19 36	; 0x7fc0a2416e20
	181	[949]	MOVE     	0 17
	182	[949]	MOVE     	0 4
	183	[928]	SETTABLE 	18 -75 19	; "_gotoPage" -
	184	[957]	CLOSURE  	19 37	; 0x7fc0a2416f60
	185	[951]	SETTABLE 	18 -76 19	; "_gotoXPointer" -
	186	[987]	CLOSURE  	19 38	; 0x7fc0a2418460
	187	[987]	MOVE     	0 4
	188	[969]	SETTABLE 	18 -77 19	; "onSetVisiblePages" -
	189	[1001]	CLOSURE  	19 39	; 0x7fc0a24187f0
	190	[1001]	MOVE     	0 4
	191	[989]	SETTABLE 	18 -78 19	; "onSetStatusLine" -
	192	[1013]	CLOSURE  	19 40	; 0x7fc0a2418eb0
	193	[1013]	MOVE     	0 13
	194	[1013]	MOVE     	0 3
	195	[1003]	SETTABLE 	18 -79 19	; "updateBatteryState" -
	196	[1046]	CLOSURE  	19 41	; 0x7fc0a2418f70
	197	[1046]	MOVE     	0 13
	198	[1015]	SETTABLE 	18 -80 19	; "handleEngineCallback" -
	199	[1048]	SELF     	19 10 -21	; "new"
	200	[1048]	NEWTABLE 	21 0 1
	201	[1048]	SETTABLE 	21 -81 -82	; "sec" 2
	202	[1048]	CALL     	19 3 2
	203	[1049]	SELF     	20 10 -21	; "new"
	204	[1049]	NEWTABLE 	22 0 1
	205	[1049]	SETTABLE 	22 -83 -84	; "usec" 500000
	206	[1049]	CALL     	20 3 2
	207	[1106]	CLOSURE  	21 42	; 0x7fc0a24192e0
	208	[1106]	MOVE     	0 10
	209	[1106]	MOVE     	0 19
	210	[1106]	MOVE     	0 9
	211	[1106]	MOVE     	0 15
	212	[1106]	MOVE     	0 7
	213	[1106]	MOVE     	0 20
	214	[1051]	SETTABLE 	18 -85 21	; "showEngineProgress" -
	215	[1318]	CLOSURE  	21 43	; 0x7fc0a240c240
	216	[1318]	MOVE     	0 13
	217	[1318]	MOVE     	0 16
	218	[1318]	MOVE     	0 14
	219	[1318]	MOVE     	0 11
	220	[1318]	MOVE     	0 2
	221	[1108]	SETTABLE 	18 -86 21	; "checkXPointersAndProposeDOMVersionUpgrade" -
	222	[1320]	RETURN   	18 2
	223	[1320]	RETURN   	0 1

function <./frontend/apps/reader/modules/readerrolling.lua:60,131> (193 instructions, 772 bytes at 0x7fc0a24070e0)
1 param, 8 slots, 1 upvalue, 1 local, 75 constants, 2 functions
	1	[61]	NEWTABLE 	1 0 0
	2	[61]	SETTABLE 	0 -1 1	; "key_events" -
	3	[62]	GETUPVAL 	1 0	; Device
	4	[62]	SELF     	1 1 -2	; "hasKeys"
	5	[62]	CALL     	1 2 2
	6	[62]	TEST     	1 0 0
	7	[62]	JMP      	28	; to 36
	8	[63]	GETTABLE 	1 0 -1	; "key_events"
	9	[63]	NEWTABLE 	2 1 3
	10	[63]	NEWTABLE 	3 1 0
	11	[64]	NEWTABLE 	4 3 0
	12	[64]	LOADK    	5 -4	; "RPgFwd"
	13	[64]	LOADK    	6 -5	; "LPgFwd"
	14	[64]	LOADK    	7 -6	; "Right"
	15	[64]	SETLIST  	4 3 1	; 1
	16	[64]	SETLIST  	3 1 1	; 1
	17	[65]	SETTABLE 	2 -7 -8	; "doc" "go to next view"
	18	[66]	SETTABLE 	2 -9 -10	; "event" "GotoViewRel"
	19	[66]	SETTABLE 	2 -11 -12	; "args" 1
	20	[67]	SETLIST  	2 1 1	; 1
	21	[67]	SETTABLE 	1 -3 2	; "GotoNextView" -
	22	[68]	GETTABLE 	1 0 -1	; "key_events"
	23	[68]	NEWTABLE 	2 1 3
	24	[68]	NEWTABLE 	3 1 0
	25	[69]	NEWTABLE 	4 3 0
	26	[69]	LOADK    	5 -14	; "RPgBack"
	27	[69]	LOADK    	6 -15	; "LPgBack"
	28	[69]	LOADK    	7 -16	; "Left"
	29	[69]	SETLIST  	4 3 1	; 1
	30	[69]	SETLIST  	3 1 1	; 1
	31	[70]	SETTABLE 	2 -7 -17	; "doc" "go to previous view"
	32	[71]	SETTABLE 	2 -9 -10	; "event" "GotoViewRel"
	33	[71]	SETTABLE 	2 -11 -18	; "args" -1
	34	[72]	SETLIST  	2 1 1	; 1
	35	[72]	SETTABLE 	1 -13 2	; "GotoPrevView" -
	36	[74]	GETUPVAL 	1 0	; Device
	37	[74]	SELF     	1 1 -19	; "hasDPad"
	38	[74]	CALL     	1 2 2
	39	[74]	TEST     	1 0 0
	40	[74]	JMP      	28	; to 69
	41	[75]	GETTABLE 	1 0 -1	; "key_events"
	42	[75]	NEWTABLE 	2 1 3
	43	[75]	NEWTABLE 	3 1 0
	44	[76]	LOADK    	4 -21	; "Up"
	45	[76]	SETLIST  	3 1 1	; 1
	46	[77]	SETTABLE 	2 -7 -22	; "doc" "move view up"
	47	[78]	SETTABLE 	2 -9 -23	; "event" "Panning"
	48	[78]	NEWTABLE 	4 2 0
	49	[78]	LOADK    	5 -24	; 0
	50	[78]	LOADK    	6 -18	; -1
	51	[78]	SETLIST  	4 2 1	; 1
	52	[78]	SETTABLE 	2 -11 4	; "args" -
	53	[79]	SETLIST  	2 1 1	; 1
	54	[79]	SETTABLE 	1 -20 2	; "MoveUp" -
	55	[80]	GETTABLE 	1 0 -1	; "key_events"
	56	[80]	NEWTABLE 	2 1 3
	57	[80]	NEWTABLE 	3 1 0
	58	[81]	LOADK    	4 -26	; "Down"
	59	[81]	SETLIST  	3 1 1	; 1
	60	[82]	SETTABLE 	2 -7 -27	; "doc" "move view down"
	61	[83]	SETTABLE 	2 -9 -23	; "event" "Panning"
	62	[83]	NEWTABLE 	4 2 0
	63	[83]	LOADK    	5 -24	; 0
	64	[83]	LOADK    	6 -12	; 1
	65	[83]	SETLIST  	4 2 1	; 1
	66	[83]	SETTABLE 	2 -11 4	; "args" -
	67	[84]	SETLIST  	2 1 1	; 1
	68	[84]	SETTABLE 	1 -25 2	; "MoveDown" -
	69	[86]	GETUPVAL 	1 0	; Device
	70	[86]	SELF     	1 1 -28	; "hasKeyboard"
	71	[86]	CALL     	1 2 2
	72	[86]	TEST     	1 0 0
	73	[86]	JMP      	100	; to 174
	74	[87]	GETTABLE 	1 0 -1	; "key_events"
	75	[87]	NEWTABLE 	2 1 3
	76	[87]	NEWTABLE 	3 1 0
	77	[88]	LOADK    	4 -30	; "1"
	78	[88]	SETLIST  	3 1 1	; 1
	79	[88]	SETTABLE 	2 -7 -31	; "doc" "go to start"
	80	[88]	SETTABLE 	2 -9 -32	; "event" "GotoPercent"
	81	[88]	SETTABLE 	2 -11 -24	; "args" 0
	82	[89]	SETLIST  	2 1 1	; 1
	83	[89]	SETTABLE 	1 -29 2	; "GotoFirst" -
	84	[90]	GETTABLE 	1 0 -1	; "key_events"
	85	[90]	NEWTABLE 	2 1 3
	86	[90]	NEWTABLE 	3 1 0
	87	[91]	LOADK    	4 -34	; "2"
	88	[91]	SETLIST  	3 1 1	; 1
	89	[91]	SETTABLE 	2 -7 -35	; "doc" "go to 11%"
	90	[91]	SETTABLE 	2 -9 -32	; "event" "GotoPercent"
	91	[91]	SETTABLE 	2 -11 -36	; "args" 11
	92	[92]	SETLIST  	2 1 1	; 1
	93	[92]	SETTABLE 	1 -33 2	; "Goto11" -
	94	[93]	GETTABLE 	1 0 -1	; "key_events"
	95	[93]	NEWTABLE 	2 1 3
	96	[93]	NEWTABLE 	3 1 0
	97	[94]	LOADK    	4 -38	; "3"
	98	[94]	SETLIST  	3 1 1	; 1
	99	[94]	SETTABLE 	2 -7 -39	; "doc" "go to 22%"
	100	[94]	SETTABLE 	2 -9 -32	; "event" "GotoPercent"
	101	[94]	SETTABLE 	2 -11 -40	; "args" 22
	102	[95]	SETLIST  	2 1 1	; 1
	103	[95]	SETTABLE 	1 -37 2	; "Goto22" -
	104	[96]	GETTABLE 	1 0 -1	; "key_events"
	105	[96]	NEWTABLE 	2 1 3
	106	[96]	NEWTABLE 	3 1 0
	107	[97]	LOADK    	4 -42	; "4"
	108	[97]	SETLIST  	3 1 1	; 1
	109	[97]	SETTABLE 	2 -7 -43	; "doc" "go to 33%"
	110	[97]	SETTABLE 	2 -9 -32	; "event" "GotoPercent"
	111	[97]	SETTABLE 	2 -11 -44	; "args" 33
	112	[98]	SETLIST  	2 1 1	; 1
	113	[98]	SETTABLE 	1 -41 2	; "Goto33" -
	114	[99]	GETTABLE 	1 0 -1	; "key_events"
	115	[99]	NEWTABLE 	2 1 3
	116	[99]	NEWTABLE 	3 1 0
	117	[100]	LOADK    	4 -46	; "5"
	118	[100]	SETLIST  	3 1 1	; 1
	119	[100]	SETTABLE 	2 -7 -47	; "doc" "go to 44%"
	120	[100]	SETTABLE 	2 -9 -32	; "event" "GotoPercent"
	121	[100]	SETTABLE 	2 -11 -48	; "args" 44
	122	[101]	SETLIST  	2 1 1	; 1
	123	[101]	SETTABLE 	1 -45 2	; "Goto44" -
	124	[102]	GETTABLE 	1 0 -1	; "key_events"
	125	[102]	NEWTABLE 	2 1 3
	126	[102]	NEWTABLE 	3 1 0
	127	[103]	LOADK    	4 -50	; "6"
	128	[103]	SETLIST  	3 1 1	; 1
	129	[103]	SETTABLE 	2 -7 -51	; "doc" "go to 55%"
	130	[103]	SETTABLE 	2 -9 -32	; "event" "GotoPercent"
	131	[103]	SETTABLE 	2 -11 -52	; "args" 55
	132	[104]	SETLIST  	2 1 1	; 1
	133	[104]	SETTABLE 	1 -49 2	; "Goto55" -
	134	[105]	GETTABLE 	1 0 -1	; "key_events"
	135	[105]	NEWTABLE 	2 1 3
	136	[105]	NEWTABLE 	3 1 0
	137	[106]	LOADK    	4 -54	; "7"
	138	[106]	SETLIST  	3 1 1	; 1
	139	[106]	SETTABLE 	2 -7 -55	; "doc" "go to 66%"
	140	[106]	SETTABLE 	2 -9 -32	; "event" "GotoPercent"
	141	[106]	SETTABLE 	2 -11 -56	; "args" 66
	142	[107]	SETLIST  	2 1 1	; 1
	143	[107]	SETTABLE 	1 -53 2	; "Goto66" -
	144	[108]	GETTABLE 	1 0 -1	; "key_events"
	145	[108]	NEWTABLE 	2 1 3
	146	[108]	NEWTABLE 	3 1 0
	147	[109]	LOADK    	4 -58	; "8"
	148	[109]	SETLIST  	3 1 1	; 1
	149	[109]	SETTABLE 	2 -7 -59	; "doc" "go to 77%"
	150	[109]	SETTABLE 	2 -9 -32	; "event" "GotoPercent"
	151	[109]	SETTABLE 	2 -11 -60	; "args" 77
	152	[110]	SETLIST  	2 1 1	; 1
	153	[110]	SETTABLE 	1 -57 2	; "Goto77" -
	154	[111]	GETTABLE 	1 0 -1	; "key_events"
	155	[111]	NEWTABLE 	2 1 3
	156	[111]	NEWTABLE 	3 1 0
	157	[112]	LOADK    	4 -62	; "9"
	158	[112]	SETLIST  	3 1 1	; 1
	159	[112]	SETTABLE 	2 -7 -63	; "doc" "go to 88%"
	160	[112]	SETTABLE 	2 -9 -32	; "event" "GotoPercent"
	161	[112]	SETTABLE 	2 -11 -64	; "args" 88
	162	[113]	SETLIST  	2 1 1	; 1
	163	[113]	SETTABLE 	1 -61 2	; "Goto88" -
	164	[114]	GETTABLE 	1 0 -1	; "key_events"
	165	[114]	NEWTABLE 	2 1 3
	166	[114]	NEWTABLE 	3 1 0
	167	[115]	LOADK    	4 -66	; "0"
	168	[115]	SETLIST  	3 1 1	; 1
	169	[115]	SETTABLE 	2 -7 -67	; "doc" "go to end"
	170	[115]	SETTABLE 	2 -9 -32	; "event" "GotoPercent"
	171	[115]	SETTABLE 	2 -11 -68	; "args" 100
	172	[116]	SETLIST  	2 1 1	; 1
	173	[116]	SETTABLE 	1 -65 2	; "GotoLast" -
	174	[119]	GETGLOBAL	1 -69	; table
	175	[119]	GETTABLE 	1 1 -70	; "insert"
	176	[119]	GETTABLE 	2 0 -71	; "ui"
	177	[119]	GETTABLE 	2 2 -72	; "postInitCallback"
	178	[123]	CLOSURE  	3 0	; 0x7fc0a2407c60
	179	[123]	MOVE     	0 0
	180	[119]	CALL     	1 3 1
	181	[124]	GETGLOBAL	1 -69	; table
	182	[124]	GETTABLE 	1 1 -70	; "insert"
	183	[124]	GETTABLE 	2 0 -71	; "ui"
	184	[124]	GETTABLE 	2 2 -73	; "postReaderCallback"
	185	[129]	CLOSURE  	3 1	; 0x7fc0a24083d0
	186	[129]	MOVE     	0 0
	187	[124]	CALL     	1 3 1
	188	[130]	GETTABLE 	1 0 -71	; "ui"
	189	[130]	GETTABLE 	1 1 -74	; "menu"
	190	[130]	SELF     	1 1 -75	; "registerToMainMenu"
	191	[130]	MOVE     	3 0
	192	[130]	CALL     	1 3 1
	193	[131]	RETURN   	0 1

function <./frontend/apps/reader/modules/readerrolling.lua:119,123> (20 instructions, 80 bytes at 0x7fc0a2407c60)
0 params, 2 slots, 1 upvalue, 0 locals, 8 constants, 0 functions
	1	[120]	GETUPVAL 	0 0	; self
	2	[120]	GETTABLE 	0 0 -1	; "ui"
	3	[120]	GETTABLE 	0 0 -2	; "document"
	4	[120]	SELF     	0 0 -3	; "_readMetadata"
	5	[120]	CALL     	0 2 1
	6	[121]	GETUPVAL 	0 0	; self
	7	[121]	GETUPVAL 	1 0	; self
	8	[121]	GETTABLE 	1 1 -1	; "ui"
	9	[121]	GETTABLE 	1 1 -2	; "document"
	10	[121]	GETTABLE 	1 1 -5	; "info"
	11	[121]	GETTABLE 	1 1 -6	; "doc_height"
	12	[121]	SETTABLE 	0 -4 1	; "old_doc_height" -
	13	[122]	GETUPVAL 	0 0	; self
	14	[122]	GETUPVAL 	1 0	; self
	15	[122]	GETTABLE 	1 1 -1	; "ui"
	16	[122]	GETTABLE 	1 1 -2	; "document"
	17	[122]	GETTABLE 	1 1 -5	; "info"
	18	[122]	GETTABLE 	1 1 -8	; "number_of_pages"
	19	[122]	SETTABLE 	0 -7 1	; "old_page" -
	20	[123]	RETURN   	0 1

function <./frontend/apps/reader/modules/readerrolling.lua:124,129> (13 instructions, 52 bytes at 0x7fc0a24083d0)
0 params, 3 slots, 1 upvalue, 0 locals, 5 constants, 0 functions
	1	[125]	GETUPVAL 	0 0	; self
	2	[125]	SELF     	0 0 -1	; "updatePos"
	3	[125]	CALL     	0 2 1
	4	[127]	GETUPVAL 	0 0	; self
	5	[127]	GETTABLE 	0 0 -2	; "ui"
	6	[127]	GETTABLE 	0 0 -3	; "document"
	7	[127]	SELF     	0 0 -4	; "enableInternalHistory"
	8	[127]	LOADBOOL 	2 0 0
	9	[127]	CALL     	0 3 1
	10	[128]	GETUPVAL 	0 0	; self
	11	[128]	SELF     	0 0 -5	; "onRedrawCurrentView"
	12	[128]	CALL     	0 2 1
	13	[129]	RETURN   	0 1

function <./frontend/apps/reader/modules/readerrolling.lua:133,244> (127 instructions, 508 bytes at 0x7fc0a2408b00)
2 params, 7 slots, 2 upvalues, 4 locals, 31 constants, 5 functions
	1	[142]	SELF     	2 1 -1	; "readSetting"
	2	[142]	LOADK    	4 -2	; "cre_dom_version"
	3	[142]	CALL     	2 3 2
	4	[142]	TEST     	2 0 1
	5	[142]	JMP      	20	; to 26
	6	[144]	SELF     	2 1 -1	; "readSetting"
	7	[144]	LOADK    	4 -3	; "last_xpointer"
	8	[144]	CALL     	2 3 2
	9	[144]	TEST     	2 0 0
	10	[144]	JMP      	8	; to 19
	11	[147]	SELF     	2 1 -4	; "saveSetting"
	12	[147]	LOADK    	4 -2	; "cre_dom_version"
	13	[147]	GETTABLE 	5 0 -5	; "ui"
	14	[147]	GETTABLE 	5 5 -6	; "document"
	15	[147]	SELF     	5 5 -7	; "getOldestDomVersion"
	16	[147]	CALL     	5 2 0
	17	[147]	CALL     	2 0 1
	18	[147]	JMP      	7	; to 26
	19	[151]	SELF     	2 1 -4	; "saveSetting"
	20	[151]	LOADK    	4 -2	; "cre_dom_version"
	21	[151]	GETTABLE 	5 0 -5	; "ui"
	22	[151]	GETTABLE 	5 5 -6	; "document"
	23	[151]	SELF     	5 5 -8	; "getLatestDomVersion"
	24	[151]	CALL     	5 2 0
	25	[151]	CALL     	2 0 1
	26	[154]	GETTABLE 	2 0 -5	; "ui"
	27	[154]	GETTABLE 	2 2 -6	; "document"
	28	[154]	SELF     	2 2 -9	; "requestDomVersion"
	29	[154]	SELF     	4 1 -1	; "readSetting"
	30	[154]	LOADK    	6 -2	; "cre_dom_version"
	31	[154]	CALL     	4 3 0
	32	[154]	CALL     	2 0 1
	33	[157]	SELF     	2 1 -1	; "readSetting"
	34	[157]	LOADK    	4 -2	; "cre_dom_version"
	35	[157]	CALL     	2 3 2
	36	[157]	GETGLOBAL	3 -10	; cre
	37	[157]	GETTABLE 	3 3 -11	; "getDomVersionWithNormalizedXPointers"
	38	[157]	CALL     	3 1 2
	39	[157]	LT       	0 2 3
	40	[157]	JMP      	15	; to 56
	41	[160]	SETTABLE 	0 -12 -13	; "using_non_normalized_xpointers" true
	42	[166]	GETTABLE 	2 0 -5	; "ui"
	43	[166]	GETTABLE 	2 2 -14	; "typeset"
	44	[166]	SELF     	2 2 -15	; "ensureSanerBlockRenderingFlags"
	45	[166]	CALL     	2 2 1
	46	[169]	SELF     	2 1 -1	; "readSetting"
	47	[169]	LOADK    	4 -16	; "cre_keep_old_dom_version"
	48	[169]	CALL     	2 3 2
	49	[169]	TEST     	2 0 1
	50	[169]	JMP      	5	; to 56
	51	[170]	GETTABLE 	2 0 -5	; "ui"
	52	[170]	SELF     	2 2 -17	; "registerPostReadyCallback"
	53	[172]	CLOSURE  	4 0	; 0x7fc0a2409160
	54	[172]	MOVE     	0 0
	55	[170]	CALL     	2 3 1
	56	[176]	SELF     	2 1 -1	; "readSetting"
	57	[176]	LOADK    	4 -3	; "last_xpointer"
	58	[176]	CALL     	2 3 2
	59	[177]	SELF     	3 1 -1	; "readSetting"
	60	[177]	LOADK    	5 -18	; "last_percent"
	61	[177]	CALL     	3 3 2
	62	[178]	TEST     	2 0 0
	63	[178]	JMP      	5	; to 69
	64	[179]	SETTABLE 	0 -19 2	; "xpointer" -
	65	[185]	CLOSURE  	4 1	; 0x7fc0a24095e0
	66	[185]	MOVE     	0 0
	67	[185]	SETTABLE 	0 -20 4	; "setupXpointer" -
	68	[185]	JMP      	12	; to 81
	69	[188]	TEST     	3 0 0
	70	[188]	JMP      	6	; to 77
	71	[203]	CLOSURE  	4 2	; 0x7fc0a24092e0
	72	[203]	MOVE     	0 0
	73	[203]	MOVE     	0 3
	74	[203]	GETUPVAL 	0 0	; Event
	75	[203]	SETTABLE 	0 -20 4	; "setupXpointer" -
	76	[203]	JMP      	4	; to 81
	77	[210]	CLOSURE  	4 3	; 0x7fc0a2409ea0
	78	[210]	MOVE     	0 0
	79	[210]	GETUPVAL 	0 0	; Event
	80	[210]	SETTABLE 	0 -20 4	; "setupXpointer" -
	81	[212]	SELF     	4 1 -1	; "readSetting"
	82	[212]	LOADK    	6 -21	; "show_overlap_enable"
	83	[212]	CALL     	4 3 2
	84	[212]	SETTABLE 	0 -21 4	; "show_overlap_enable" -
	85	[213]	GETTABLE 	4 0 -21	; "show_overlap_enable"
	86	[213]	EQ       	0 4 -22	; - nil
	87	[213]	JMP      	2	; to 90
	88	[214]	GETGLOBAL	4 -23	; DSHOWOVERLAP
	89	[214]	SETTABLE 	0 -21 4	; "show_overlap_enable" -
	90	[217]	SELF     	4 1 -1	; "readSetting"
	91	[217]	LOADK    	6 -24	; "inverse_reading_order"
	92	[217]	CALL     	4 3 2
	93	[217]	SETTABLE 	0 -24 4	; "inverse_reading_order" -
	94	[218]	GETTABLE 	4 0 -24	; "inverse_reading_order"
	95	[218]	EQ       	0 4 -22	; - nil
	96	[218]	JMP      	5	; to 102
	97	[219]	GETGLOBAL	4 -25	; G_reader_settings
	98	[219]	SELF     	4 4 -26	; "isTrue"
	99	[219]	LOADK    	6 -24	; "inverse_reading_order"
	100	[219]	CALL     	4 3 2
	101	[219]	SETTABLE 	0 -24 4	; "inverse_reading_order" -
	102	[228]	SELF     	4 1 -1	; "readSetting"
	103	[228]	LOADK    	6 -27	; "visible_pages"
	104	[228]	CALL     	4 3 2
	105	[228]	TEST     	4 0 1
	106	[228]	JMP      	7	; to 114
	107	[229]	GETGLOBAL	4 -25	; G_reader_settings
	108	[229]	SELF     	4 4 -1	; "readSetting"
	109	[229]	LOADK    	6 -28	; "copt_visible_pages"
	110	[229]	CALL     	4 3 2
	111	[229]	TEST     	4 0 1
	112	[229]	JMP      	1	; to 114
	113	[229]	LOADK    	4 -29	; 1
	114	[229]	SETTABLE 	0 -27 4	; "visible_pages" -
	115	[230]	GETTABLE 	4 0 -5	; "ui"
	116	[230]	GETTABLE 	4 4 -6	; "document"
	117	[230]	SELF     	4 4 -30	; "setVisiblePageCount"
	118	[230]	GETTABLE 	6 0 -27	; "visible_pages"
	119	[230]	CALL     	4 3 1
	120	[235]	GETTABLE 	4 0 -5	; "ui"
	121	[235]	GETTABLE 	4 4 -6	; "document"
	122	[235]	SELF     	4 4 -31	; "setCallback"
	123	[243]	CLOSURE  	6 4	; 0x7fc0a240a770
	124	[243]	MOVE     	0 0
	125	[243]	GETUPVAL 	0 1	; logger
	126	[235]	CALL     	4 3 1
	127	[244]	RETURN   	0 1

function <./frontend/apps/reader/modules/readerrolling.lua:170,172> (4 instructions, 16 bytes at 0x7fc0a2409160)
0 params, 2 slots, 1 upvalue, 0 locals, 1 constant, 0 functions
	1	[171]	GETUPVAL 	0 0	; self
	2	[171]	SELF     	0 0 -1	; "checkXPointersAndProposeDOMVersionUpgrade"
	3	[171]	CALL     	0 2 1
	4	[172]	RETURN   	0 1

function <./frontend/apps/reader/modules/readerrolling.lua:180,185> (13 instructions, 52 bytes at 0x7fc0a24095e0)
0 params, 3 slots, 1 upvalue, 0 locals, 5 constants, 0 functions
	1	[181]	GETUPVAL 	0 0	; self
	2	[181]	SELF     	0 0 -1	; "_gotoXPointer"
	3	[181]	GETUPVAL 	2 0	; self
	4	[181]	GETTABLE 	2 2 -2	; "xpointer"
	5	[181]	CALL     	0 3 1
	6	[184]	GETUPVAL 	0 0	; self
	7	[184]	GETTABLE 	0 0 -3	; "ui"
	8	[184]	GETTABLE 	0 0 -4	; "document"
	9	[184]	SELF     	0 0 -5	; "gotoXPointer"
	10	[184]	GETUPVAL 	2 0	; self
	11	[184]	GETTABLE 	2 2 -2	; "xpointer"
	12	[184]	CALL     	0 3 1
	13	[185]	RETURN   	0 1

function <./frontend/apps/reader/modules/readerrolling.lua:189,203> (37 instructions, 148 bytes at 0x7fc0a24092e0)
0 params, 7 slots, 3 upvalues, 0 locals, 14 constants, 0 functions
	1	[190]	GETUPVAL 	0 0	; self
	2	[190]	SELF     	0 0 -1	; "_gotoPercent"
	3	[190]	GETUPVAL 	2 1	; last_per
	4	[190]	CALL     	0 3 1
	5	[195]	GETUPVAL 	0 0	; self
	6	[195]	GETTABLE 	0 0 -2	; "ui"
	7	[195]	GETTABLE 	0 0 -3	; "document"
	8	[195]	SELF     	0 0 -4	; "gotoPos"
	9	[195]	GETUPVAL 	2 0	; self
	10	[195]	GETTABLE 	2 2 -5	; "current_pos"
	11	[195]	CALL     	0 3 1
	12	[198]	GETUPVAL 	0 0	; self
	13	[198]	GETTABLE 	0 0 -6	; "view"
	14	[198]	GETTABLE 	0 0 -7	; "view_mode"
	15	[198]	EQ       	0 0 -8	; - "page"
	16	[198]	JMP      	13	; to 30
	17	[199]	GETUPVAL 	0 0	; self
	18	[199]	GETTABLE 	0 0 -2	; "ui"
	19	[199]	SELF     	0 0 -9	; "handleEvent"
	20	[200]	GETUPVAL 	2 2	; Event
	21	[200]	SELF     	2 2 -10	; "new"
	22	[200]	LOADK    	4 -11	; "PageUpdate"
	23	[200]	GETUPVAL 	5 0	; self
	24	[200]	GETTABLE 	5 5 -2	; "ui"
	25	[200]	GETTABLE 	5 5 -3	; "document"
	26	[200]	SELF     	5 5 -12	; "getCurrentPage"
	27	[200]	CALL     	5 2 0
	28	[200]	CALL     	2 0 0
	29	[199]	CALL     	0 0 1
	30	[202]	GETUPVAL 	0 0	; self
	31	[202]	GETUPVAL 	1 0	; self
	32	[202]	GETTABLE 	1 1 -2	; "ui"
	33	[202]	GETTABLE 	1 1 -3	; "document"
	34	[202]	SELF     	1 1 -14	; "getXPointer"
	35	[202]	CALL     	1 2 2
	36	[202]	SETTABLE 	0 -13 1	; "xpointer" -
	37	[203]	RETURN   	0 1

function <./frontend/apps/reader/modules/readerrolling.lua:205,210> (22 instructions, 88 bytes at 0x7fc0a2409ea0)
0 params, 6 slots, 2 upvalues, 0 locals, 11 constants, 0 functions
	1	[206]	GETUPVAL 	0 0	; self
	2	[206]	GETUPVAL 	1 0	; self
	3	[206]	GETTABLE 	1 1 -2	; "ui"
	4	[206]	GETTABLE 	1 1 -3	; "document"
	5	[206]	SELF     	1 1 -4	; "getXPointer"
	6	[206]	CALL     	1 2 2
	7	[206]	SETTABLE 	0 -1 1	; "xpointer" -
	8	[207]	GETUPVAL 	0 0	; self
	9	[207]	GETTABLE 	0 0 -5	; "view"
	10	[207]	GETTABLE 	0 0 -6	; "view_mode"
	11	[207]	EQ       	0 0 -7	; - "page"
	12	[207]	JMP      	9	; to 22
	13	[208]	GETUPVAL 	0 0	; self
	14	[208]	GETTABLE 	0 0 -2	; "ui"
	15	[208]	SELF     	0 0 -8	; "handleEvent"
	16	[208]	GETUPVAL 	2 1	; Event
	17	[208]	SELF     	2 2 -9	; "new"
	18	[208]	LOADK    	4 -10	; "PageUpdate"
	19	[208]	LOADK    	5 -11	; 1
	20	[208]	CALL     	2 4 0
	21	[208]	CALL     	0 0 1
	22	[210]	RETURN   	0 1

function <./frontend/apps/reader/modules/readerrolling.lua:235,243> (16 instructions, 64 bytes at 0x7fc0a240a770)
0+ params, 6 slots, 2 upvalues, 3 locals, 6 constants, 0 functions
	1	[239]	GETGLOBAL	1 -1	; xpcall
	2	[239]	GETUPVAL 	2 0	; self
	3	[239]	GETTABLE 	2 2 -2	; "handleEngineCallback"
	4	[239]	GETGLOBAL	3 -3	; debug
	5	[239]	GETTABLE 	3 3 -4	; "traceback"
	6	[239]	GETUPVAL 	4 0	; self
	7	[239]	VARARG   	5 0
	8	[239]	CALL     	1 0 3
	9	[240]	TEST     	1 0 1
	10	[240]	JMP      	5	; to 16
	11	[241]	GETUPVAL 	3 1	; logger
	12	[241]	GETTABLE 	3 3 -5	; "warn"
	13	[241]	LOADK    	4 -6	; "cre callback() error:"
	14	[241]	MOVE     	5 2
	15	[241]	CALL     	3 3 1
	16	[243]	RETURN   	0 1

function <./frontend/apps/reader/modules/readerrolling.lua:248,261> (45 instructions, 180 bytes at 0x7fc0a240adf0)
1 param, 6 slots, 1 upvalue, 2 locals, 15 constants, 0 functions
	1	[249]	GETTABLE 	1 0 -1	; "ui"
	2	[249]	GETTABLE 	1 1 -2	; "doc_settings"
	3	[249]	SELF     	1 1 -3	; "saveSetting"
	4	[249]	LOADK    	3 -4	; "percent_finished"
	5	[249]	SELF     	4 0 -5	; "getLastPercent"
	6	[249]	CALL     	4 2 0
	7	[249]	CALL     	1 0 1
	8	[250]	GETTABLE 	1 0 -1	; "ui"
	9	[250]	GETTABLE 	1 1 -6	; "document"
	10	[250]	SELF     	1 1 -7	; "getCacheFilePath"
	11	[250]	CALL     	1 2 2
	12	[251]	GETTABLE 	2 0 -1	; "ui"
	13	[251]	GETTABLE 	2 2 -2	; "doc_settings"
	14	[251]	SELF     	2 2 -3	; "saveSetting"
	15	[251]	LOADK    	4 -8	; "cache_file_path"
	16	[251]	MOVE     	5 1
	17	[251]	CALL     	2 4 1
	18	[252]	GETTABLE 	2 0 -1	; "ui"
	19	[252]	GETTABLE 	2 2 -6	; "document"
	20	[252]	SELF     	2 2 -9	; "hasCacheFile"
	21	[252]	CALL     	2 2 2
	22	[252]	TEST     	2 0 0
	23	[252]	JMP      	14	; to 38
	24	[255]	GETTABLE 	2 0 -1	; "ui"
	25	[255]	GETTABLE 	2 2 -6	; "document"
	26	[255]	SELF     	2 2 -10	; "isBuiltDomStale"
	27	[255]	CALL     	2 2 2
	28	[255]	TEST     	2 0 0
	29	[255]	JMP      	8	; to 38
	30	[256]	GETUPVAL 	2 0	; logger
	31	[256]	GETTABLE 	2 2 -11	; "dbg"
	32	[256]	LOADK    	3 -12	; "cre DOM may not be in sync with styles, invalidating cache file for a full reload at next opening"
	33	[256]	CALL     	2 2 1
	34	[257]	GETTABLE 	2 0 -1	; "ui"
	35	[257]	GETTABLE 	2 2 -6	; "document"
	36	[257]	SELF     	2 2 -13	; "invalidateCacheFile"
	37	[257]	CALL     	2 2 1
	38	[260]	GETUPVAL 	2 0	; logger
	39	[260]	GETTABLE 	2 2 -11	; "dbg"
	40	[260]	LOADK    	3 -14	; "cre cache used:"
	41	[260]	TESTSET  	4 1 1
	42	[260]	JMP      	1	; to 44
	43	[260]	LOADK    	4 -15	; "none"
	44	[260]	CALL     	2 3 1
	45	[261]	RETURN   	0 1

function <./frontend/apps/reader/modules/readerrolling.lua:263,284> (43 instructions, 172 bytes at 0x7fc0a240b3d0)
1 param, 10 slots, 4 upvalues, 2 locals, 13 constants, 1 function
	1	[264]	GETTABLE 	1 0 -1	; "ui"
	2	[264]	GETTABLE 	1 1 -2	; "document"
	3	[264]	TEST     	1 0 0
	4	[264]	JMP      	38	; to 43
	5	[264]	GETTABLE 	1 0 -1	; "ui"
	6	[264]	GETTABLE 	1 1 -2	; "document"
	7	[264]	SELF     	1 1 -3	; "isBuiltDomStale"
	8	[264]	CALL     	1 2 2
	9	[264]	TEST     	1 0 0
	10	[264]	JMP      	32	; to 43
	11	[265]	LOADK    	1 -4	; ""
	12	[267]	GETTABLE 	2 0 -5	; "using_non_normalized_xpointers"
	13	[267]	TEST     	2 0 0
	14	[267]	JMP      	10	; to 25
	15	[267]	GETTABLE 	2 0 -1	; "ui"
	16	[267]	GETTABLE 	2 2 -6	; "bookmark"
	17	[267]	SELF     	2 2 -7	; "hasBookmarks"
	18	[267]	CALL     	2 2 2
	19	[267]	TEST     	2 0 0
	20	[267]	JMP      	4	; to 25
	21	[268]	GETUPVAL 	2 0	; _
	22	[268]	LOADK    	3 -8	; "\nNote that this change in styles may render your bookmarks or highlights no more valid.\nIf some of them do not show anymore, you can just revert the change you just made to have them shown again.\n\n"
	23	[268]	CALL     	2 2 2
	24	[268]	MOVE     	1 2
	25	[270]	GETUPVAL 	2 1	; UIManager
	26	[270]	SELF     	2 2 -9	; "show"
	27	[270]	GETUPVAL 	4 2	; ConfirmBox
	28	[270]	SELF     	4 4 -10	; "new"
	29	[270]	NEWTABLE 	6 0 2
	30	[271]	GETUPVAL 	7 3	; T
	31	[271]	GETUPVAL 	8 0	; _
	32	[271]	LOADK    	9 -12	; "Styles have changed in such a way that fully reloading the document may be needed for a correct rendering.\n%1Do you want to reload the document?"
	33	[271]	CALL     	8 2 2
	34	[271]	MOVE     	9 1
	35	[271]	CALL     	7 3 2
	36	[271]	SETTABLE 	6 -11 7	; "text" -
	37	[281]	CLOSURE  	7 0	; 0x7fc0a240bac0
	38	[281]	GETUPVAL 	0 1	; UIManager
	39	[281]	MOVE     	0 0
	40	[281]	SETTABLE 	6 -13 7	; "ok_callback" -
	41	[270]	CALL     	4 3 0
	42	[270]	CALL     	2 0 1
	43	[284]	RETURN   	0 1

function <./frontend/apps/reader/modules/readerrolling.lua:272,281> (7 instructions, 28 bytes at 0x7fc0a240bac0)
0 params, 4 slots, 2 upvalues, 0 locals, 2 constants, 1 function
	1	[275]	GETUPVAL 	0 0	; UIManager
	2	[275]	SELF     	0 0 -1	; "scheduleIn"
	3	[275]	LOADK    	2 -2	; 0.5
	4	[280]	CLOSURE  	3 0	; 0x7fc0a240bec0
	5	[280]	GETUPVAL 	0 1	; self
	6	[275]	CALL     	0 4 1
	7	[281]	RETURN   	0 1

function <./frontend/apps/reader/modules/readerrolling.lua:275,280> (10 instructions, 40 bytes at 0x7fc0a240bec0)
0 params, 2 slots, 1 upvalue, 0 locals, 3 constants, 0 functions
	1	[277]	GETUPVAL 	0 0	; self
	2	[277]	GETTABLE 	0 0 -1	; "ui"
	3	[277]	GETTABLE 	0 0 -2	; "document"
	4	[277]	TEST     	0 0 0
	5	[277]	JMP      	4	; to 10
	6	[278]	GETUPVAL 	0 0	; self
	7	[278]	GETTABLE 	0 0 -1	; "ui"
	8	[278]	SELF     	0 0 -3	; "reloadDocument"
	9	[278]	CALL     	0 2 1
	10	[280]	RETURN   	0 1

function <./frontend/apps/reader/modules/readerrolling.lua:286,299> (42 instructions, 168 bytes at 0x7fc0a240c2f0)
1 param, 6 slots, 0 upvalues, 1 local, 12 constants, 0 functions
	1	[288]	GETTABLE 	1 0 -1	; "ui"
	2	[288]	GETTABLE 	1 1 -2	; "doc_settings"
	3	[288]	SELF     	1 1 -3	; "saveSetting"
	4	[288]	LOADK    	3 -4	; "last_percent"
	5	[288]	LOADNIL  	4 4
	6	[288]	CALL     	1 4 1
	7	[289]	GETTABLE 	1 0 -1	; "ui"
	8	[289]	GETTABLE 	1 1 -2	; "doc_settings"
	9	[289]	SELF     	1 1 -3	; "saveSetting"
	10	[289]	LOADK    	3 -5	; "last_xpointer"
	11	[289]	GETTABLE 	4 0 -6	; "xpointer"
	12	[289]	CALL     	1 4 1
	13	[293]	GETTABLE 	1 0 -1	; "ui"
	14	[293]	GETTABLE 	1 1 -7	; "document"
	15	[293]	TEST     	1 0 0
	16	[293]	JMP      	7	; to 24
	17	[294]	GETTABLE 	1 0 -1	; "ui"
	18	[294]	GETTABLE 	1 1 -2	; "doc_settings"
	19	[294]	SELF     	1 1 -3	; "saveSetting"
	20	[294]	LOADK    	3 -8	; "percent_finished"
	21	[294]	SELF     	4 0 -9	; "getLastPercent"
	22	[294]	CALL     	4 2 0
	23	[294]	CALL     	1 0 1
	24	[296]	GETTABLE 	1 0 -1	; "ui"
	25	[296]	GETTABLE 	1 1 -2	; "doc_settings"
	26	[296]	SELF     	1 1 -3	; "saveSetting"
	27	[296]	LOADK    	3 -10	; "show_overlap_enable"
	28	[296]	GETTABLE 	4 0 -10	; "show_overlap_enable"
	29	[296]	CALL     	1 4 1
	30	[297]	GETTABLE 	1 0 -1	; "ui"
	31	[297]	GETTABLE 	1 1 -2	; "doc_settings"
	32	[297]	SELF     	1 1 -3	; "saveSetting"
	33	[297]	LOADK    	3 -11	; "inverse_reading_order"
	34	[297]	GETTABLE 	4 0 -11	; "inverse_reading_order"
	35	[297]	CALL     	1 4 1
	36	[298]	GETTABLE 	1 0 -1	; "ui"
	37	[298]	GETTABLE 	1 1 -2	; "doc_settings"
	38	[298]	SELF     	1 1 -3	; "saveSetting"
	39	[298]	LOADK    	3 -12	; "visible_pages"
	40	[298]	GETTABLE 	4 0 -12	; "visible_pages"
	41	[298]	CALL     	1 4 1
	42	[299]	RETURN   	0 1

function <./frontend/apps/reader/modules/readerrolling.lua:301,304> (5 instructions, 20 bytes at 0x7fc0a240be20)
1 param, 3 slots, 0 upvalues, 1 local, 2 constants, 0 functions
	1	[302]	SELF     	1 0 -1	; "setupTouchZones"
	2	[302]	CALL     	1 2 1
	3	[303]	GETTABLE 	1 0 -2	; "setupXpointer"
	4	[303]	CALL     	1 1 1
	5	[304]	RETURN   	0 1

function <./frontend/apps/reader/modules/readerrolling.lua:306,386> (150 instructions, 600 bytes at 0x7fc0a24094a0)
1 param, 16 slots, 2 upvalues, 6 locals, 38 constants, 6 functions
	1	[307]	NEWTABLE 	1 0 0
	2	[307]	SETTABLE 	0 -1 1	; "ges_events" -
	3	[308]	SETTABLE 	0 -2 -3	; "onGesture" nil
	4	[309]	GETUPVAL 	1 0	; Device
	5	[309]	SELF     	1 1 -4	; "isTouchDevice"
	6	[309]	CALL     	1 2 2
	7	[309]	TEST     	1 0 1
	8	[309]	JMP      	1	; to 10
	9	[309]	RETURN   	0 1
	10	[311]	NEWTABLE 	1 0 4
	11	[312]	GETGLOBAL	2 -6	; DTAP_ZONE_FORWARD
	12	[312]	GETTABLE 	2 2 -7	; "x"
	13	[312]	SETTABLE 	1 -5 2	; "ratio_x" -
	14	[312]	GETGLOBAL	2 -6	; DTAP_ZONE_FORWARD
	15	[312]	GETTABLE 	2 2 -9	; "y"
	16	[312]	SETTABLE 	1 -8 2	; "ratio_y" -
	17	[313]	GETGLOBAL	2 -6	; DTAP_ZONE_FORWARD
	18	[313]	GETTABLE 	2 2 -11	; "w"
	19	[313]	SETTABLE 	1 -10 2	; "ratio_w" -
	20	[313]	GETGLOBAL	2 -6	; DTAP_ZONE_FORWARD
	21	[313]	GETTABLE 	2 2 -13	; "h"
	22	[313]	SETTABLE 	1 -12 2	; "ratio_h" -
	23	[315]	NEWTABLE 	2 0 4
	24	[316]	GETGLOBAL	3 -14	; DTAP_ZONE_BACKWARD
	25	[316]	GETTABLE 	3 3 -7	; "x"
	26	[316]	SETTABLE 	2 -5 3	; "ratio_x" -
	27	[316]	GETGLOBAL	3 -14	; DTAP_ZONE_BACKWARD
	28	[316]	GETTABLE 	3 3 -9	; "y"
	29	[316]	SETTABLE 	2 -8 3	; "ratio_y" -
	30	[317]	GETGLOBAL	3 -14	; DTAP_ZONE_BACKWARD
	31	[317]	GETTABLE 	3 3 -11	; "w"
	32	[317]	SETTABLE 	2 -10 3	; "ratio_w" -
	33	[317]	GETGLOBAL	3 -14	; DTAP_ZONE_BACKWARD
	34	[317]	GETTABLE 	3 3 -13	; "h"
	35	[317]	SETTABLE 	2 -12 3	; "ratio_h" -
	36	[320]	NEWTABLE 	3 0 4
	37	[321]	GETGLOBAL	4 -15	; DDOUBLE_TAP_ZONE_NEXT_CHAPTER
	38	[321]	GETTABLE 	4 4 -7	; "x"
	39	[321]	SETTABLE 	3 -5 4	; "ratio_x" -
	40	[321]	GETGLOBAL	4 -15	; DDOUBLE_TAP_ZONE_NEXT_CHAPTER
	41	[321]	GETTABLE 	4 4 -9	; "y"
	42	[321]	SETTABLE 	3 -8 4	; "ratio_y" -
	43	[322]	GETGLOBAL	4 -15	; DDOUBLE_TAP_ZONE_NEXT_CHAPTER
	44	[322]	GETTABLE 	4 4 -11	; "w"
	45	[322]	SETTABLE 	3 -10 4	; "ratio_w" -
	46	[322]	GETGLOBAL	4 -15	; DDOUBLE_TAP_ZONE_NEXT_CHAPTER
	47	[322]	GETTABLE 	4 4 -13	; "h"
	48	[322]	SETTABLE 	3 -12 4	; "ratio_h" -
	49	[324]	NEWTABLE 	4 0 4
	50	[325]	GETGLOBAL	5 -16	; DDOUBLE_TAP_ZONE_PREV_CHAPTER
	51	[325]	GETTABLE 	5 5 -7	; "x"
	52	[325]	SETTABLE 	4 -5 5	; "ratio_x" -
	53	[325]	GETGLOBAL	5 -16	; DDOUBLE_TAP_ZONE_PREV_CHAPTER
	54	[325]	GETTABLE 	5 5 -9	; "y"
	55	[325]	SETTABLE 	4 -8 5	; "ratio_y" -
	56	[326]	GETGLOBAL	5 -16	; DDOUBLE_TAP_ZONE_PREV_CHAPTER
	57	[326]	GETTABLE 	5 5 -11	; "w"
	58	[326]	SETTABLE 	4 -10 5	; "ratio_w" -
	59	[326]	GETGLOBAL	5 -16	; DDOUBLE_TAP_ZONE_PREV_CHAPTER
	60	[326]	GETTABLE 	5 5 -13	; "h"
	61	[326]	SETTABLE 	4 -12 5	; "ratio_h" -
	62	[329]	GETUPVAL 	5 1	; BD
	63	[329]	GETTABLE 	5 5 -17	; "mirroredUILayout"
	64	[329]	CALL     	5 1 2
	65	[330]	GETTABLE 	6 0 -18	; "inverse_reading_order"
	66	[330]	TEST     	6 0 0
	67	[330]	JMP      	1	; to 69
	68	[331]	NOT      	5 5
	69	[333]	TEST     	5 0 0
	70	[333]	JMP      	20	; to 91
	71	[334]	GETTABLE 	6 1 -5	; "ratio_x"
	72	[334]	SUB      	6 -19 6	; 1 -
	73	[334]	GETTABLE 	7 1 -10	; "ratio_w"
	74	[334]	SUB      	6 6 7
	75	[334]	SETTABLE 	1 -5 6	; "ratio_x" -
	76	[335]	GETTABLE 	6 2 -5	; "ratio_x"
	77	[335]	SUB      	6 -19 6	; 1 -
	78	[335]	GETTABLE 	7 2 -10	; "ratio_w"
	79	[335]	SUB      	6 6 7
	80	[335]	SETTABLE 	2 -5 6	; "ratio_x" -
	81	[338]	GETTABLE 	6 3 -5	; "ratio_x"
	82	[338]	SUB      	6 -19 6	; 1 -
	83	[338]	GETTABLE 	7 3 -10	; "ratio_w"
	84	[338]	SUB      	6 6 7
	85	[338]	SETTABLE 	3 -5 6	; "ratio_x" -
	86	[340]	GETTABLE 	6 4 -5	; "ratio_x"
	87	[340]	SUB      	6 -19 6	; 1 -
	88	[340]	GETTABLE 	7 4 -10	; "ratio_w"
	89	[340]	SUB      	6 6 7
	90	[340]	SETTABLE 	4 -5 6	; "ratio_x" -
	91	[343]	GETTABLE 	6 0 -20	; "ui"
	92	[343]	SELF     	6 6 -21	; "registerTouchZones"
	93	[343]	NEWTABLE 	8 6 0
	94	[343]	NEWTABLE 	9 0 4
	95	[345]	SETTABLE 	9 -22 -23	; "id" "tap_forward"
	96	[346]	SETTABLE 	9 -24 -25	; "ges" "tap"
	97	[347]	SETTABLE 	9 -26 1	; "screen_zone" -
	98	[348]	CLOSURE  	10 0	; 0x7fc0a240ab70
	99	[348]	MOVE     	0 0
	100	[348]	SETTABLE 	9 -27 10	; "handler" -
	101	[349]	NEWTABLE 	10 0 4
	102	[351]	SETTABLE 	10 -22 -28	; "id" "tap_backward"
	103	[352]	SETTABLE 	10 -24 -25	; "ges" "tap"
	104	[353]	SETTABLE 	10 -26 2	; "screen_zone" -
	105	[354]	CLOSURE  	11 1	; 0x7fc0a2408620
	106	[354]	MOVE     	0 0
	107	[354]	SETTABLE 	10 -27 11	; "handler" -
	108	[355]	NEWTABLE 	11 0 4
	109	[357]	SETTABLE 	11 -22 -29	; "id" "double_tap_forward"
	110	[358]	SETTABLE 	11 -24 -30	; "ges" "double_tap"
	111	[359]	SETTABLE 	11 -26 3	; "screen_zone" -
	112	[360]	CLOSURE  	12 2	; 0x7fc0a240cc10
	113	[360]	MOVE     	0 0
	114	[360]	SETTABLE 	11 -27 12	; "handler" -
	115	[361]	NEWTABLE 	12 0 4
	116	[363]	SETTABLE 	12 -22 -31	; "id" "double_tap_backward"
	117	[364]	SETTABLE 	12 -24 -30	; "ges" "double_tap"
	118	[365]	SETTABLE 	12 -26 4	; "screen_zone" -
	119	[366]	CLOSURE  	13 3	; 0x7fc0a240cfd0
	120	[366]	MOVE     	0 0
	121	[366]	SETTABLE 	12 -27 13	; "handler" -
	122	[367]	NEWTABLE 	13 0 4
	123	[369]	SETTABLE 	13 -22 -32	; "id" "rolling_swipe"
	124	[370]	SETTABLE 	13 -24 -33	; "ges" "swipe"
	125	[371]	NEWTABLE 	14 0 4
	126	[372]	SETTABLE 	14 -5 -34	; "ratio_x" 0
	127	[372]	SETTABLE 	14 -8 -34	; "ratio_y" 0
	128	[372]	SETTABLE 	14 -10 -19	; "ratio_w" 1
	129	[372]	SETTABLE 	14 -12 -19	; "ratio_h" 1
	130	[373]	SETTABLE 	13 -26 14	; "screen_zone" -
	131	[374]	CLOSURE  	14 4	; 0x7fc0a240c510
	132	[374]	MOVE     	0 0
	133	[374]	SETTABLE 	13 -27 14	; "handler" -
	134	[375]	NEWTABLE 	14 0 5
	135	[377]	SETTABLE 	14 -22 -35	; "id" "rolling_pan"
	136	[378]	SETTABLE 	14 -24 -36	; "ges" "pan"
	137	[379]	GETTABLE 	15 0 -38	; "pan_rate"
	138	[379]	SETTABLE 	14 -37 15	; "rate" -
	139	[380]	NEWTABLE 	15 0 4
	140	[381]	SETTABLE 	15 -5 -34	; "ratio_x" 0
	141	[381]	SETTABLE 	15 -8 -34	; "ratio_y" 0
	142	[381]	SETTABLE 	15 -10 -19	; "ratio_w" 1
	143	[381]	SETTABLE 	15 -12 -19	; "ratio_h" 1
	144	[382]	SETTABLE 	14 -26 15	; "screen_zone" -
	145	[383]	CLOSURE  	15 5	; 0x7fc0a240c8d0
	146	[383]	MOVE     	0 0
	147	[383]	SETTABLE 	14 -27 15	; "handler" -
	148	[385]	SETLIST  	8 6 1	; 1
	149	[343]	CALL     	6 3 1
	150	[386]	RETURN   	0 1

function <./frontend/apps/reader/modules/readerrolling.lua:348,348> (6 instructions, 24 bytes at 0x7fc0a240ab70)
0 params, 3 slots, 1 upvalue, 0 locals, 2 constants, 0 functions
	1	[348]	GETUPVAL 	0 0	; self
	2	[348]	SELF     	0 0 -1	; "onGotoViewRel"
	3	[348]	LOADK    	2 -2	; 1
	4	[348]	TAILCALL 	0 3 0
	5	[348]	RETURN   	0 0
	6	[348]	RETURN   	0 1

function <./frontend/apps/reader/modules/readerrolling.lua:354,354> (6 instructions, 24 bytes at 0x7fc0a2408620)
0 params, 3 slots, 1 upvalue, 0 locals, 2 constants, 0 functions
	1	[354]	GETUPVAL 	0 0	; self
	2	[354]	SELF     	0 0 -1	; "onGotoViewRel"
	3	[354]	LOADK    	2 -2	; -1
	4	[354]	TAILCALL 	0 3 0
	5	[354]	RETURN   	0 0
	6	[354]	RETURN   	0 1

function <./frontend/apps/reader/modules/readerrolling.lua:360,360> (5 instructions, 20 bytes at 0x7fc0a240cc10)
0 params, 2 slots, 1 upvalue, 0 locals, 1 constant, 0 functions
	1	[360]	GETUPVAL 	0 0	; self
	2	[360]	SELF     	0 0 -1	; "onGotoNextChapter"
	3	[360]	TAILCALL 	0 2 0
	4	[360]	RETURN   	0 0
	5	[360]	RETURN   	0 1

function <./frontend/apps/reader/modules/readerrolling.lua:366,366> (5 instructions, 20 bytes at 0x7fc0a240cfd0)
0 params, 2 slots, 1 upvalue, 0 locals, 1 constant, 0 functions
	1	[366]	GETUPVAL 	0 0	; self
	2	[366]	SELF     	0 0 -1	; "onGotoPrevChapter"
	3	[366]	TAILCALL 	0 2 0
	4	[366]	RETURN   	0 0
	5	[366]	RETURN   	0 1

function <./frontend/apps/reader/modules/readerrolling.lua:374,374> (7 instructions, 28 bytes at 0x7fc0a240c510)
1 param, 5 slots, 1 upvalue, 1 local, 1 constant, 0 functions
	1	[374]	GETUPVAL 	1 0	; self
	2	[374]	SELF     	1 1 -1	; "onSwipe"
	3	[374]	LOADNIL  	3 3
	4	[374]	MOVE     	4 0
	5	[374]	TAILCALL 	1 4 0
	6	[374]	RETURN   	1 0
	7	[374]	RETURN   	0 1

function <./frontend/apps/reader/modules/readerrolling.lua:383,383> (7 instructions, 28 bytes at 0x7fc0a240c8d0)
1 param, 5 slots, 1 upvalue, 1 local, 1 constant, 0 functions
	1	[383]	GETUPVAL 	1 0	; self
	2	[383]	SELF     	1 1 -1	; "onPan"
	3	[383]	LOADNIL  	3 3
	4	[383]	MOVE     	4 0
	5	[383]	TAILCALL 	1 4 0
	6	[383]	RETURN   	1 0
	7	[383]	RETURN   	0 1

function <./frontend/apps/reader/modules/readerrolling.lua:388,390> (3 instructions, 12 bytes at 0x7fc0a240c9b0)
1 param, 2 slots, 0 upvalues, 1 local, 1 constant, 0 functions
	1	[389]	GETTABLE 	1 0 -1	; "xpointer"
	2	[389]	RETURN   	1 2
	3	[390]	RETURN   	0 1

function <./frontend/apps/reader/modules/readerrolling.lua:392,480> (82 instructions, 328 bytes at 0x7fc0a240d350)
2 params, 13 slots, 6 upvalues, 10 locals, 22 constants, 10 functions
	1	[394]	NEWTABLE 	2 0 4
	2	[395]	GETUPVAL 	3 0	; _
	3	[395]	LOADK    	4 -3	; "Invert page turn taps and swipes"
	4	[395]	CALL     	3 2 2
	5	[395]	SETTABLE 	2 -2 3	; "text" -
	6	[396]	CLOSURE  	3 0	; 0x7fc0a240d6a0
	7	[396]	MOVE     	0 0
	8	[396]	SETTABLE 	2 -4 3	; "checked_func" -
	9	[399]	CLOSURE  	3 1	; 0x7fc0a240d7a0
	10	[399]	MOVE     	0 0
	11	[399]	GETUPVAL 	0 1	; Event
	12	[399]	SETTABLE 	2 -5 3	; "callback" -
	13	[420]	CLOSURE  	3 2	; 0x7fc0a240df90
	14	[420]	GETUPVAL 	0 2	; UIManager
	15	[420]	GETUPVAL 	0 3	; MultiConfirmBox
	16	[420]	GETUPVAL 	0 0	; _
	17	[420]	SETTABLE 	2 -6 3	; "hold_callback" -
	18	[421]	SETTABLE 	1 -1 2	; "invert_page_turn_gestures" -
	19	[425]	GETUPVAL 	2 0	; _
	20	[427]	LOADK    	3 -7	; "When page overlap is enabled, some lines from the previous page will be displayed on the next page.\nYou can set how many lines are shown."
	21	[425]	CALL     	2 2 2
	22	[428]	NEWTABLE 	3 2 0
	23	[428]	NEWTABLE 	4 0 3
	24	[430]	GETUPVAL 	5 0	; _
	25	[430]	LOADK    	6 -8	; "Page overlap"
	26	[430]	CALL     	5 2 2
	27	[430]	SETTABLE 	4 -2 5	; "text" -
	28	[433]	CLOSURE  	5 3	; 0x7fc0a240f690
	29	[433]	MOVE     	0 0
	30	[433]	SETTABLE 	4 -4 5	; "checked_func" -
	31	[439]	CLOSURE  	5 4	; 0x7fc0a240f800
	32	[439]	MOVE     	0 0
	33	[439]	SETTABLE 	4 -5 5	; "callback" -
	34	[440]	NEWTABLE 	5 0 6
	35	[444]	CLOSURE  	6 5	; 0x7fc0a240d720
	36	[444]	GETUPVAL 	0 4	; T
	37	[444]	GETUPVAL 	0 0	; _
	38	[444]	SETTABLE 	5 -9 6	; "text_func" -
	39	[447]	CLOSURE  	6 6	; 0x7fc0a240ff30
	40	[447]	MOVE     	0 0
	41	[447]	SETTABLE 	5 -10 6	; "enabled_func" -
	42	[464]	CLOSURE  	6 7	; 0x7fc0a240db50
	43	[464]	GETUPVAL 	0 2	; UIManager
	44	[464]	GETUPVAL 	0 5	; Screen
	45	[464]	GETUPVAL 	0 0	; _
	46	[464]	MOVE     	0 2
	47	[464]	SETTABLE 	5 -5 6	; "callback" -
	48	[465]	SETTABLE 	5 -11 -12	; "keep_menu_open" true
	49	[466]	SETTABLE 	5 -13 2	; "help_text" -
	50	[467]	SETTABLE 	5 -14 -12	; "separator" true
	51	[469]	SETLIST  	3 2 1	; 1
	52	[470]	CLOSURE  	4 8	; 0x7fc0a2410ce0
	53	[470]	MOVE     	0 0
	54	[471]	GETGLOBAL	5 -15	; ipairs
	55	[471]	GETTABLE 	6 0 -16	; "view"
	56	[471]	SELF     	6 6 -17	; "genOverlapStyleMenu"
	57	[471]	MOVE     	8 4
	58	[471]	CALL     	6 3 0
	59	[471]	CALL     	5 0 4
	60	[471]	JMP      	5	; to 66
	61	[472]	GETGLOBAL	10 -18	; table
	62	[472]	GETTABLE 	10 10 -19	; "insert"
	63	[472]	MOVE     	11 3
	64	[472]	MOVE     	12 9
	65	[472]	CALL     	10 3 1
	66	[471]	TFORLOOP 	5 2
	67	[472]	JMP      	-7	; to 61
	68	[474]	NEWTABLE 	5 0 4
	69	[475]	GETUPVAL 	6 0	; _
	70	[475]	LOADK    	7 -8	; "Page overlap"
	71	[475]	CALL     	6 2 2
	72	[475]	SETTABLE 	5 -2 6	; "text" -
	73	[476]	CLOSURE  	6 9	; 0x7fc0a2410c60
	74	[476]	MOVE     	0 0
	75	[476]	SETTABLE 	5 -10 6	; "enabled_func" -
	76	[477]	GETUPVAL 	6 0	; _
	77	[477]	LOADK    	7 -21	; "When page overlap is enabled, some lines from the previous pages are shown on the next page."
	78	[477]	CALL     	6 2 2
	79	[477]	SETTABLE 	5 -13 6	; "help_text" -
	80	[478]	SETTABLE 	5 -22 3	; "sub_item_table" -
	81	[479]	SETTABLE 	1 -20 5	; "page_overlap" -
	82	[480]	RETURN   	0 1

function <./frontend/apps/reader/modules/readerrolling.lua:396,396> (4 instructions, 16 bytes at 0x7fc0a240d6a0)
0 params, 2 slots, 1 upvalue, 0 locals, 1 constant, 0 functions
	1	[396]	GETUPVAL 	0 0	; self
	2	[396]	GETTABLE 	0 0 -1	; "inverse_reading_order"
	3	[396]	RETURN   	0 2
	4	[396]	RETURN   	0 1

function <./frontend/apps/reader/modules/readerrolling.lua:397,399> (9 instructions, 36 bytes at 0x7fc0a240d7a0)
0 params, 5 slots, 2 upvalues, 0 locals, 4 constants, 0 functions
	1	[398]	GETUPVAL 	0 0	; self
	2	[398]	GETTABLE 	0 0 -1	; "ui"
	3	[398]	SELF     	0 0 -2	; "handleEvent"
	4	[398]	GETUPVAL 	2 1	; Event
	5	[398]	SELF     	2 2 -3	; "new"
	6	[398]	LOADK    	4 -4	; "ToggleReadingOrder"
	7	[398]	CALL     	2 3 0
	8	[398]	CALL     	0 0 1
	9	[399]	RETURN   	0 1

function <./frontend/apps/reader/modules/readerrolling.lua:400,420> (37 instructions, 148 bytes at 0x7fc0a240df90)
1 param, 9 slots, 3 upvalues, 2 locals, 12 constants, 4 functions
	1	[401]	GETGLOBAL	1 -1	; G_reader_settings
	2	[401]	SELF     	1 1 -2	; "isTrue"
	3	[401]	LOADK    	3 -3	; "inverse_reading_order"
	4	[401]	CALL     	1 3 2
	5	[402]	GETUPVAL 	2 0	; UIManager
	6	[402]	SELF     	2 2 -4	; "show"
	7	[402]	GETUPVAL 	4 1	; MultiConfirmBox
	8	[402]	SELF     	4 4 -5	; "new"
	9	[402]	NEWTABLE 	6 0 5
	10	[403]	TEST     	1 0 0
	11	[403]	JMP      	5	; to 17
	12	[403]	GETUPVAL 	7 2	; _
	13	[403]	LOADK    	8 -7	; "The default (\226\152\133) for newly opened books is right-to-left (RTL) page turning.\n\nWould you like to change it?"
	14	[403]	CALL     	7 2 2
	15	[404]	TEST     	7 0 1
	16	[404]	JMP      	3	; to 20
	17	[404]	GETUPVAL 	7 2	; _
	18	[404]	LOADK    	8 -8	; "The default (\226\152\133) for newly opened books is left-to-right (LTR) page turning.\n\nWould you like to change it?"
	19	[404]	CALL     	7 2 2
	20	[404]	SETTABLE 	6 -6 7	; "text" -
	21	[407]	CLOSURE  	7 0	; 0x7fc0a240e1e0
	22	[407]	MOVE     	0 1
	23	[407]	GETUPVAL 	0 2	; _
	24	[407]	SETTABLE 	6 -9 7	; "choice1_text_func" -
	25	[411]	CLOSURE  	7 1	; 0x7fc0a240e520
	26	[411]	MOVE     	0 0
	27	[411]	SETTABLE 	6 -10 7	; "choice1_callback" -
	28	[414]	CLOSURE  	7 2	; 0x7fc0a240e960
	29	[414]	MOVE     	0 1
	30	[414]	GETUPVAL 	0 2	; _
	31	[414]	SETTABLE 	6 -11 7	; "choice2_text_func" -
	32	[418]	CLOSURE  	7 3	; 0x7fc0a240ef40
	33	[418]	MOVE     	0 0
	34	[418]	SETTABLE 	6 -12 7	; "choice2_callback" -
	35	[402]	CALL     	4 3 0
	36	[402]	CALL     	2 0 1
	37	[420]	RETURN   	0 1

function <./frontend/apps/reader/modules/readerrolling.lua:405,407> (13 instructions, 52 bytes at 0x7fc0a240e1e0)
0 params, 2 slots, 2 upvalues, 0 locals, 2 constants, 0 functions
	1	[406]	GETUPVAL 	0 0	; inverse_reading_order
	2	[406]	TEST     	0 0 0
	3	[406]	JMP      	5	; to 9
	4	[406]	GETUPVAL 	0 1	; _
	5	[406]	LOADK    	1 -1	; "LTR"
	6	[406]	CALL     	0 2 2
	7	[406]	TEST     	0 0 1
	8	[406]	JMP      	3	; to 12
	9	[406]	GETUPVAL 	0 1	; _
	10	[406]	LOADK    	1 -2	; "LTR (\226\152\133)"
	11	[406]	CALL     	0 2 2
	12	[406]	RETURN   	0 2
	13	[407]	RETURN   	0 1

function <./frontend/apps/reader/modules/readerrolling.lua:408,411> (12 instructions, 48 bytes at 0x7fc0a240e520)
0 params, 4 slots, 1 upvalue, 0 locals, 4 constants, 0 functions
	1	[409]	GETGLOBAL	0 -1	; G_reader_settings
	2	[409]	SELF     	0 0 -2	; "saveSetting"
	3	[409]	LOADK    	2 -3	; "inverse_reading_order"
	4	[409]	LOADBOOL 	3 0 0
	5	[409]	CALL     	0 4 1
	6	[410]	GETUPVAL 	0 0	; touchmenu_instance
	7	[410]	TEST     	0 0 0
	8	[410]	JMP      	3	; to 12
	9	[410]	GETUPVAL 	0 0	; touchmenu_instance
	10	[410]	SELF     	0 0 -4	; "updateItems"
	11	[410]	CALL     	0 2 1
	12	[411]	RETURN   	0 1

function <./frontend/apps/reader/modules/readerrolling.lua:412,414> (13 instructions, 52 bytes at 0x7fc0a240e960)
0 params, 2 slots, 2 upvalues, 0 locals, 2 constants, 0 functions
	1	[413]	GETUPVAL 	0 0	; inverse_reading_order
	2	[413]	TEST     	0 0 0
	3	[413]	JMP      	5	; to 9
	4	[413]	GETUPVAL 	0 1	; _
	5	[413]	LOADK    	1 -1	; "RTL (\226\152\133)"
	6	[413]	CALL     	0 2 2
	7	[413]	TEST     	0 0 1
	8	[413]	JMP      	3	; to 12
	9	[413]	GETUPVAL 	0 1	; _
	10	[413]	LOADK    	1 -2	; "RTL"
	11	[413]	CALL     	0 2 2
	12	[413]	RETURN   	0 2
	13	[414]	RETURN   	0 1

function <./frontend/apps/reader/modules/readerrolling.lua:415,418> (12 instructions, 48 bytes at 0x7fc0a240ef40)
0 params, 4 slots, 1 upvalue, 0 locals, 4 constants, 0 functions
	1	[416]	GETGLOBAL	0 -1	; G_reader_settings
	2	[416]	SELF     	0 0 -2	; "saveSetting"
	3	[416]	LOADK    	2 -3	; "inverse_reading_order"
	4	[416]	LOADBOOL 	3 1 0
	5	[416]	CALL     	0 4 1
	6	[417]	GETUPVAL 	0 0	; touchmenu_instance
	7	[417]	TEST     	0 0 0
	8	[417]	JMP      	3	; to 12
	9	[417]	GETUPVAL 	0 0	; touchmenu_instance
	10	[417]	SELF     	0 0 -4	; "updateItems"
	11	[417]	CALL     	0 2 1
	12	[418]	RETURN   	0 1

function <./frontend/apps/reader/modules/readerrolling.lua:431,433> (4 instructions, 16 bytes at 0x7fc0a240f690)
0 params, 2 slots, 1 upvalue, 0 locals, 1 constant, 0 functions
	1	[432]	GETUPVAL 	0 0	; self
	2	[432]	GETTABLE 	0 0 -1	; "show_overlap_enable"
	3	[432]	RETURN   	0 2
	4	[433]	RETURN   	0 1

function <./frontend/apps/reader/modules/readerrolling.lua:434,439> (14 instructions, 56 bytes at 0x7fc0a240f800)
0 params, 2 slots, 1 upvalue, 0 locals, 3 constants, 0 functions
	1	[435]	GETUPVAL 	0 0	; self
	2	[435]	GETUPVAL 	1 0	; self
	3	[435]	GETTABLE 	1 1 -1	; "show_overlap_enable"
	4	[435]	NOT      	1 1
	5	[435]	SETTABLE 	0 -1 1	; "show_overlap_enable" -
	6	[436]	GETUPVAL 	0 0	; self
	7	[436]	GETTABLE 	0 0 -1	; "show_overlap_enable"
	8	[436]	TEST     	0 0 1
	9	[436]	JMP      	4	; to 14
	10	[437]	GETUPVAL 	0 0	; self
	11	[437]	GETTABLE 	0 0 -2	; "view"
	12	[437]	SELF     	0 0 -3	; "resetDimArea"
	13	[437]	CALL     	0 2 1
	14	[439]	RETURN   	0 1

function <./frontend/apps/reader/modules/readerrolling.lua:442,444> (14 instructions, 56 bytes at 0x7fc0a240d720)
0 params, 5 slots, 2 upvalues, 0 locals, 5 constants, 0 functions
	1	[443]	GETUPVAL 	0 0	; T
	2	[443]	GETUPVAL 	1 1	; _
	3	[443]	LOADK    	2 -1	; "Number of lines: %1"
	4	[443]	CALL     	1 2 2
	5	[443]	GETGLOBAL	2 -2	; G_reader_settings
	6	[443]	SELF     	2 2 -3	; "readSetting"
	7	[443]	LOADK    	4 -4	; "copt_overlap_lines"
	8	[443]	CALL     	2 3 2
	9	[443]	TEST     	2 0 1
	10	[443]	JMP      	1	; to 12
	11	[443]	LOADK    	2 -5	; 1
	12	[443]	TAILCALL 	0 3 0
	13	[443]	RETURN   	0 0
	14	[444]	RETURN   	0 1

function <./frontend/apps/reader/modules/readerrolling.lua:445,447> (4 instructions, 16 bytes at 0x7fc0a240ff30)
0 params, 2 slots, 1 upvalue, 0 locals, 1 constant, 0 functions
	1	[446]	GETUPVAL 	0 0	; self
	2	[446]	GETTABLE 	0 0 -1	; "show_overlap_enable"
	3	[446]	RETURN   	0 2
	4	[447]	RETURN   	0 1

function <./frontend/apps/reader/modules/readerrolling.lua:448,464> (39 instructions, 156 bytes at 0x7fc0a240db50)
1 param, 10 slots, 4 upvalues, 2 locals, 23 constants, 1 function
	1	[449]	GETGLOBAL	1 -1	; require
	2	[449]	LOADK    	2 -2	; "ui/widget/spinwidget"
	3	[449]	CALL     	1 2 2
	4	[450]	GETUPVAL 	2 0	; UIManager
	5	[450]	SELF     	2 2 -3	; "show"
	6	[450]	SELF     	4 1 -4	; "new"
	7	[450]	NEWTABLE 	6 0 9
	8	[451]	GETUPVAL 	7 1	; Screen
	9	[451]	SELF     	7 7 -6	; "getWidth"
	10	[451]	CALL     	7 2 2
	11	[451]	MUL      	7 7 -7	; - 0.75
	12	[451]	SETTABLE 	6 -5 7	; "width" -
	13	[452]	GETGLOBAL	7 -9	; G_reader_settings
	14	[452]	SELF     	7 7 -10	; "readSetting"
	15	[452]	LOADK    	9 -11	; "copt_overlap_lines"
	16	[452]	CALL     	7 3 2
	17	[452]	TEST     	7 0 1
	18	[452]	JMP      	1	; to 20
	19	[452]	LOADK    	7 -12	; 1
	20	[452]	SETTABLE 	6 -8 7	; "value" -
	21	[453]	SETTABLE 	6 -13 -12	; "value_min" 1
	22	[454]	SETTABLE 	6 -14 -15	; "value_max" 10
	23	[455]	SETTABLE 	6 -16 -17	; "precision" "%d"
	24	[456]	GETUPVAL 	7 2	; _
	25	[456]	LOADK    	8 -19	; "Set"
	26	[456]	CALL     	7 2 2
	27	[456]	SETTABLE 	6 -18 7	; "ok_text" -
	28	[457]	GETUPVAL 	7 2	; _
	29	[457]	LOADK    	8 -21	; "Set overlapped lines"
	30	[457]	CALL     	7 2 2
	31	[457]	SETTABLE 	6 -20 7	; "title_text" -
	32	[458]	GETUPVAL 	7 3	; overlap_lines_help_text
	33	[458]	SETTABLE 	6 -22 7	; "info_text" -
	34	[462]	CLOSURE  	7 0	; 0x7fc0a2410470
	35	[462]	MOVE     	0 0
	36	[462]	SETTABLE 	6 -23 7	; "callback" -
	37	[450]	CALL     	4 3 0
	38	[450]	CALL     	2 0 1
	39	[464]	RETURN   	0 1

function <./frontend/apps/reader/modules/readerrolling.lua:459,462> (9 instructions, 36 bytes at 0x7fc0a2410470)
1 param, 5 slots, 1 upvalue, 1 local, 5 constants, 0 functions
	1	[460]	GETGLOBAL	1 -1	; G_reader_settings
	2	[460]	SELF     	1 1 -2	; "saveSetting"
	3	[460]	LOADK    	3 -3	; "copt_overlap_lines"
	4	[460]	GETTABLE 	4 0 -4	; "value"
	5	[460]	CALL     	1 4 1
	6	[461]	GETUPVAL 	1 0	; touchmenu_instance
	7	[461]	SELF     	1 1 -5	; "updateItems"
	8	[461]	CALL     	1 2 1
	9	[462]	RETURN   	0 1

function <./frontend/apps/reader/modules/readerrolling.lua:470,470> (4 instructions, 16 bytes at 0x7fc0a2410ce0)
0 params, 2 slots, 1 upvalue, 0 locals, 1 constant, 0 functions
	1	[470]	GETUPVAL 	0 0	; self
	2	[470]	GETTABLE 	0 0 -1	; "show_overlap_enable"
	3	[470]	RETURN   	0 2
	4	[470]	RETURN   	0 1

function <./frontend/apps/reader/modules/readerrolling.lua:476,476> (9 instructions, 36 bytes at 0x7fc0a2410c60)
0 params, 2 slots, 1 upvalue, 0 locals, 3 constants, 0 functions
	1	[476]	GETUPVAL 	0 0	; self
	2	[476]	GETTABLE 	0 0 -1	; "view"
	3	[476]	GETTABLE 	0 0 -2	; "view_mode"
	4	[476]	EQ       	0 0 -3	; - "page"
	5	[476]	JMP      	1	; to 7
	6	[476]	LOADBOOL 	0 0 1
	7	[476]	LOADBOOL 	0 1 0
	8	[476]	RETURN   	0 2
	9	[476]	RETURN   	0 1

function <./frontend/apps/reader/modules/readerrolling.lua:482,490> (24 instructions, 96 bytes at 0x7fc0a2411820)
1 param, 5 slots, 0 upvalues, 1 local, 11 constants, 0 functions
	1	[483]	GETTABLE 	1 0 -1	; "view"
	2	[483]	GETTABLE 	1 1 -2	; "view_mode"
	3	[483]	EQ       	0 1 -3	; - "page"
	4	[483]	JMP      	5	; to 10
	5	[484]	GETTABLE 	1 0 -4	; "current_page"
	6	[484]	GETTABLE 	2 0 -5	; "old_page"
	7	[484]	DIV      	1 1 2
	8	[484]	RETURN   	1 2
	9	[484]	JMP      	14	; to 24
	10	[487]	GETTABLE 	1 0 -6	; "ui"
	11	[487]	GETTABLE 	1 1 -7	; "document"
	12	[487]	SELF     	1 1 -8	; "getPosFromXPointer"
	13	[488]	GETTABLE 	3 0 -6	; "ui"
	14	[488]	GETTABLE 	3 3 -7	; "document"
	15	[488]	SELF     	3 3 -9	; "getXPointer"
	16	[488]	CALL     	3 2 0
	17	[487]	CALL     	1 0 2
	18	[488]	GETTABLE 	2 0 -6	; "ui"
	19	[488]	GETTABLE 	2 2 -7	; "document"
	20	[488]	GETTABLE 	2 2 -10	; "info"
	21	[488]	GETTABLE 	2 2 -11	; "doc_height"
	22	[488]	DIV      	1 1 2
	23	[488]	RETURN   	1 2
	24	[490]	RETURN   	0 1

function <./frontend/apps/reader/modules/readerrolling.lua:492,512> (40 instructions, 160 bytes at 0x7fc0a2411b10)
3 params, 8 slots, 2 upvalues, 4 locals, 13 constants, 0 functions
	1	[493]	GETUPVAL 	3 0	; BD
	2	[493]	GETTABLE 	3 3 -1	; "flipDirectionIfMirroredUILayout"
	3	[493]	GETTABLE 	4 2 -2	; "direction"
	4	[493]	CALL     	3 2 2
	5	[494]	EQ       	0 3 -3	; - "west"
	6	[494]	JMP      	11	; to 18
	7	[495]	GETTABLE 	4 0 -4	; "inverse_reading_order"
	8	[495]	TEST     	4 0 0
	9	[495]	JMP      	4	; to 14
	10	[496]	SELF     	4 0 -5	; "onGotoViewRel"
	11	[496]	LOADK    	6 -6	; -1
	12	[496]	CALL     	4 3 1
	13	[496]	JMP      	26	; to 40
	14	[498]	SELF     	4 0 -5	; "onGotoViewRel"
	15	[498]	LOADK    	6 -7	; 1
	16	[498]	CALL     	4 3 1
	17	[499]	JMP      	22	; to 40
	18	[500]	EQ       	0 3 -8	; - "east"
	19	[500]	JMP      	11	; to 31
	20	[501]	GETTABLE 	4 0 -4	; "inverse_reading_order"
	21	[501]	TEST     	4 0 0
	22	[501]	JMP      	4	; to 27
	23	[502]	SELF     	4 0 -5	; "onGotoViewRel"
	24	[502]	LOADK    	6 -7	; 1
	25	[502]	CALL     	4 3 1
	26	[502]	JMP      	13	; to 40
	27	[504]	SELF     	4 0 -5	; "onGotoViewRel"
	28	[504]	LOADK    	6 -6	; -1
	29	[504]	CALL     	4 3 1
	30	[505]	JMP      	9	; to 40
	31	[508]	GETTABLE 	4 0 -9	; "view"
	32	[508]	GETTABLE 	4 4 -10	; "footer"
	33	[508]	SELF     	4 4 -11	; "updateFooter"
	34	[508]	CALL     	4 2 1
	35	[510]	GETUPVAL 	4 1	; UIManager
	36	[510]	SELF     	4 4 -12	; "setDirty"
	37	[510]	LOADNIL  	6 6
	38	[510]	LOADK    	7 -13	; "full"
	39	[510]	CALL     	4 4 1
	40	[512]	RETURN   	0 1

function <./frontend/apps/reader/modules/readerrolling.lua:514,530> (52 instructions, 208 bytes at 0x7fc0a2411c20)
3 params, 9 slots, 2 upvalues, 4 locals, 19 constants, 0 functions
	1	[515]	GETTABLE 	3 0 -1	; "view"
	2	[515]	GETTABLE 	3 3 -2	; "view_mode"
	3	[515]	EQ       	0 3 -3	; - "scroll"
	4	[515]	JMP      	29	; to 34
	5	[516]	LOADK    	3 -4	; "distance"
	6	[517]	GETTABLE 	4 0 -5	; "ui"
	7	[517]	GETTABLE 	4 4 -6	; "gesture"
	8	[517]	TEST     	4 0 0
	9	[517]	JMP      	6	; to 16
	10	[517]	GETTABLE 	4 0 -5	; "ui"
	11	[517]	GETTABLE 	4 4 -6	; "gesture"
	12	[517]	GETTABLE 	4 4 -7	; "multiswipes_enabled"
	13	[517]	TEST     	4 0 0
	14	[517]	JMP      	1	; to 16
	15	[518]	LOADK    	3 -8	; "distance_delayed"
	16	[520]	GETTABLE 	4 2 -9	; "direction"
	17	[520]	EQ       	0 4 -10	; - "north"
	18	[520]	JMP      	6	; to 25
	19	[521]	SELF     	4 0 -11	; "_gotoPos"
	20	[521]	GETTABLE 	6 0 -12	; "current_pos"
	21	[521]	GETTABLE 	7 2 3
	22	[521]	ADD      	6 6 7
	23	[521]	CALL     	4 3 1
	24	[521]	JMP      	25	; to 50
	25	[522]	GETTABLE 	4 2 -9	; "direction"
	26	[522]	EQ       	0 4 -13	; - "south"
	27	[522]	JMP      	22	; to 50
	28	[523]	SELF     	4 0 -11	; "_gotoPos"
	29	[523]	GETTABLE 	6 0 -12	; "current_pos"
	30	[523]	GETTABLE 	7 2 3
	31	[523]	SUB      	6 6 7
	32	[523]	CALL     	4 3 1
	33	[524]	JMP      	16	; to 50
	34	[526]	GETTABLE 	3 2 -14	; "mousewheel_direction"
	35	[526]	TEST     	3 0 0
	36	[526]	JMP      	13	; to 50
	37	[526]	GETTABLE 	3 0 -1	; "view"
	38	[526]	GETTABLE 	3 3 -2	; "view_mode"
	39	[526]	EQ       	0 3 -15	; - "page"
	40	[526]	JMP      	9	; to 50
	41	[527]	GETUPVAL 	3 0	; UIManager
	42	[527]	SELF     	3 3 -16	; "broadcastEvent"
	43	[527]	GETUPVAL 	5 1	; Event
	44	[527]	SELF     	5 5 -17	; "new"
	45	[527]	LOADK    	7 -18	; "GotoViewRel"
	46	[527]	GETTABLE 	8 2 -14	; "mousewheel_direction"
	47	[527]	MUL      	8 -19 8	; -1 -
	48	[527]	CALL     	5 4 0
	49	[527]	CALL     	3 0 1
	50	[529]	LOADBOOL 	3 1 0
	51	[529]	RETURN   	3 2
	52	[530]	RETURN   	0 1

function <./frontend/apps/reader/modules/readerrolling.lua:532,535> (4 instructions, 16 bytes at 0x7fc0a240ced0)
2 params, 4 slots, 0 upvalues, 2 locals, 2 constants, 0 functions
	1	[533]	SETTABLE 	0 -1 1	; "current_pos" -
	2	[534]	SELF     	2 0 -2	; "updateBatteryState"
	3	[534]	CALL     	2 2 1
	4	[535]	RETURN   	0 1

function <./frontend/apps/reader/modules/readerrolling.lua:537,540> (4 instructions, 16 bytes at 0x7fc0a240e5a0)
2 params, 4 slots, 0 upvalues, 2 locals, 2 constants, 0 functions
	1	[538]	SETTABLE 	0 -1 1	; "current_page" -
	2	[539]	SELF     	2 0 -2	; "updateBatteryState"
	3	[539]	CALL     	2 2 1
	4	[540]	RETURN   	0 1

function <./frontend/apps/reader/modules/readerrolling.lua:542,544> (3 instructions, 12 bytes at 0x7fc0a24125c0)
1 param, 3 slots, 0 upvalues, 1 local, 1 constant, 0 functions
	1	[543]	SELF     	1 0 -1	; "updateBatteryState"
	2	[543]	CALL     	1 2 1
	3	[544]	RETURN   	0 1

function <./frontend/apps/reader/modules/readerrolling.lua:546,555> (30 instructions, 120 bytes at 0x7fc0a240f760)
1 param, 7 slots, 0 upvalues, 4 locals, 11 constants, 0 functions
	1	[547]	GETTABLE 	1 0 -1	; "ui"
	2	[547]	GETTABLE 	1 1 -2	; "document"
	3	[547]	SELF     	1 1 -3	; "getVisiblePageCount"
	4	[547]	CALL     	1 2 2
	5	[548]	GETTABLE 	2 0 -4	; "current_page"
	6	[548]	LT       	0 -5 1	; 1 -
	7	[548]	JMP      	3	; to 11
	8	[548]	LOADK    	3 -5	; 1
	9	[548]	TEST     	3 0 1
	10	[548]	JMP      	1	; to 12
	11	[548]	LOADK    	3 -6	; 0
	12	[548]	ADD      	2 2 3
	13	[549]	GETTABLE 	3 0 -1	; "ui"
	14	[549]	GETTABLE 	3 3 -7	; "toc"
	15	[549]	SELF     	3 3 -8	; "getNextChapter"
	16	[549]	MOVE     	5 2
	17	[549]	LOADK    	6 -6	; 0
	18	[549]	CALL     	3 4 2
	19	[550]	TEST     	3 0 0
	20	[550]	JMP      	7	; to 28
	21	[551]	GETTABLE 	4 0 -1	; "ui"
	22	[551]	GETTABLE 	4 4 -9	; "link"
	23	[551]	SELF     	4 4 -10	; "addCurrentLocationToStack"
	24	[551]	CALL     	4 2 1
	25	[552]	SELF     	4 0 -11	; "onGotoPage"
	26	[552]	MOVE     	6 3
	27	[552]	CALL     	4 3 1
	28	[554]	LOADBOOL 	4 1 0
	29	[554]	RETURN   	4 2
	30	[555]	RETURN   	0 1

function <./frontend/apps/reader/modules/readerrolling.lua:557,565> (19 instructions, 76 bytes at 0x7fc0a24121c0)
1 param, 6 slots, 0 upvalues, 3 locals, 8 constants, 0 functions
	1	[558]	GETTABLE 	1 0 -1	; "current_page"
	2	[559]	GETTABLE 	2 0 -2	; "ui"
	3	[559]	GETTABLE 	2 2 -3	; "toc"
	4	[559]	SELF     	2 2 -4	; "getPreviousChapter"
	5	[559]	MOVE     	4 1
	6	[559]	LOADK    	5 -5	; 0
	7	[559]	CALL     	2 4 2
	8	[560]	TEST     	2 0 0
	9	[560]	JMP      	7	; to 17
	10	[561]	GETTABLE 	3 0 -2	; "ui"
	11	[561]	GETTABLE 	3 3 -6	; "link"
	12	[561]	SELF     	3 3 -7	; "addCurrentLocationToStack"
	13	[561]	CALL     	3 2 1
	14	[562]	SELF     	3 0 -8	; "onGotoPage"
	15	[562]	MOVE     	5 2
	16	[562]	CALL     	3 3 1
	17	[564]	LOADBOOL 	3 1 0
	18	[564]	RETURN   	3 2
	19	[565]	RETURN   	0 1

function <./frontend/apps/reader/modules/readerrolling.lua:567,569> (3 instructions, 12 bytes at 0x7fc0a24117a0)
1 param, 3 slots, 0 upvalues, 1 local, 1 constant, 0 functions
	1	[568]	SELF     	1 0 -1	; "updateBatteryState"
	2	[568]	CALL     	1 2 1
	3	[569]	RETURN   	0 1

function <./frontend/apps/reader/modules/readerrolling.lua:571,576> (16 instructions, 64 bytes at 0x7fc0a240a5c0)
2 params, 5 slots, 1 upvalue, 2 locals, 7 constants, 0 functions
	1	[572]	GETUPVAL 	2 0	; logger
	2	[572]	GETTABLE 	2 2 -1	; "dbg"
	3	[572]	LOADK    	3 -2	; "goto document offset in percent:"
	4	[572]	MOVE     	4 1
	5	[572]	CALL     	2 3 1
	6	[573]	SELF     	2 0 -3	; "_gotoPercent"
	7	[573]	MOVE     	4 1
	8	[573]	CALL     	2 3 1
	9	[574]	GETTABLE 	2 0 -5	; "ui"
	10	[574]	GETTABLE 	2 2 -6	; "document"
	11	[574]	SELF     	2 2 -7	; "getXPointer"
	12	[574]	CALL     	2 2 2
	13	[574]	SETTABLE 	0 -4 2	; "xpointer" -
	14	[575]	LOADBOOL 	2 1 0
	15	[575]	RETURN   	2 2
	16	[576]	RETURN   	0 1

function <./frontend/apps/reader/modules/readerrolling.lua:578,584> (13 instructions, 52 bytes at 0x7fc0a240cd50)
2 params, 5 slots, 0 upvalues, 2 locals, 5 constants, 0 functions
	1	[579]	TEST     	1 0 0
	2	[579]	JMP      	3	; to 6
	3	[580]	SELF     	2 0 -1	; "_gotoPage"
	4	[580]	MOVE     	4 1
	5	[580]	CALL     	2 3 1
	6	[582]	GETTABLE 	2 0 -3	; "ui"
	7	[582]	GETTABLE 	2 2 -4	; "document"
	8	[582]	SELF     	2 2 -5	; "getXPointer"
	9	[582]	CALL     	2 2 2
	10	[582]	SETTABLE 	0 -2 2	; "xpointer" -
	11	[583]	LOADBOOL 	2 1 0
	12	[583]	RETURN   	2 2
	13	[584]	RETURN   	0 1

function <./frontend/apps/reader/modules/readerrolling.lua:586,592> (14 instructions, 56 bytes at 0x7fc0a240ee70)
2 params, 5 slots, 0 upvalues, 2 locals, 6 constants, 0 functions
	1	[587]	TEST     	1 0 0
	2	[587]	JMP      	4	; to 7
	3	[588]	SELF     	2 0 -1	; "_gotoPage"
	4	[588]	GETTABLE 	4 0 -2	; "current_page"
	5	[588]	ADD      	4 4 1
	6	[588]	CALL     	2 3 1
	7	[590]	GETTABLE 	2 0 -4	; "ui"
	8	[590]	GETTABLE 	2 2 -5	; "document"
	9	[590]	SELF     	2 2 -6	; "getXPointer"
	10	[590]	CALL     	2 2 2
	11	[590]	SETTABLE 	0 -3 2	; "xpointer" -
	12	[591]	LOADBOOL 	2 1 0
	13	[591]	RETURN   	2 2
	14	[592]	RETURN   	0 1

function <./frontend/apps/reader/modules/readerrolling.lua:594,703> (158 instructions, 632 bytes at 0x7fc0a2410060)
3 params, 14 slots, 4 upvalues, 11 locals, 35 constants, 1 function
	1	[595]	GETTABLE 	3 0 -1	; "mark_func"
	2	[595]	TEST     	3 0 0
	3	[595]	JMP      	5	; to 9
	4	[597]	GETUPVAL 	3 0	; UIManager
	5	[597]	SELF     	3 3 -2	; "unschedule"
	6	[597]	GETTABLE 	5 0 -1	; "mark_func"
	7	[597]	CALL     	3 3 1
	8	[598]	SETTABLE 	0 -1 -3	; "mark_func" nil
	9	[600]	GETTABLE 	3 0 -4	; "unmark_func"
	10	[600]	TEST     	3 0 0
	11	[600]	JMP      	3	; to 15
	12	[602]	GETTABLE 	3 0 -4	; "unmark_func"
	13	[602]	CALL     	3 1 1
	14	[603]	SETTABLE 	0 -4 -3	; "unmark_func" nil
	15	[605]	SELF     	3 0 -5	; "_gotoXPointer"
	16	[605]	MOVE     	5 1
	17	[605]	CALL     	3 3 1
	18	[606]	SETTABLE 	0 -6 1	; "xpointer" -
	19	[613]	GETGLOBAL	3 -7	; G_reader_settings
	20	[613]	SELF     	3 3 -8	; "readSetting"
	21	[613]	LOADK    	5 -9	; "followed_link_marker"
	22	[613]	CALL     	3 3 2
	23	[614]	EQ       	0 3 -3	; - nil
	24	[614]	JMP      	1	; to 26
	25	[615]	LOADK    	3 -10	; 1
	26	[618]	TEST     	2 0 0
	27	[618]	JMP      	128	; to 156
	28	[618]	TEST     	3 0 0
	29	[618]	JMP      	126	; to 156
	30	[621]	GETTABLE 	4 0 -11	; "ui"
	31	[621]	GETTABLE 	4 4 -12	; "document"
	32	[621]	SELF     	4 4 -13	; "getScreenPositionFromXPointer"
	33	[621]	MOVE     	6 2
	34	[621]	CALL     	4 3 3
	35	[622]	GETTABLE 	6 0 -11	; "ui"
	36	[622]	GETTABLE 	6 6 -12	; "document"
	37	[622]	SELF     	6 6 -14	; "getPageMargins"
	38	[622]	CALL     	6 2 2
	39	[623]	GETUPVAL 	7 1	; Screen
	40	[623]	SELF     	7 7 -15	; "scaleBySize"
	41	[623]	GETTABLE 	9 0 -11	; "ui"
	42	[623]	GETTABLE 	9 9 -16	; "font"
	43	[623]	GETTABLE 	9 9 -17	; "font_size"
	44	[623]	MUL      	9 9 -18	; - 1.1
	45	[623]	GETTABLE 	10 0 -11	; "ui"
	46	[623]	GETTABLE 	10 10 -16	; "font"
	47	[623]	GETTABLE 	10 10 -19	; "line_space_percent"
	48	[623]	MUL      	9 9 10
	49	[623]	DIV      	9 9 -20	; - 100
	50	[623]	CALL     	7 3 2
	51	[625]	GETGLOBAL	8 -21	; math
	52	[625]	GETTABLE 	8 8 -22	; "floor"
	53	[625]	GETGLOBAL	9 -21	; math
	54	[625]	GETTABLE 	9 9 -23	; "max"
	55	[625]	GETTABLE 	10 6 -24	; "left"
	56	[625]	GETUPVAL 	11 1	; Screen
	57	[625]	SELF     	11 11 -15	; "scaleBySize"
	58	[625]	LOADK    	13 -25	; 5
	59	[625]	CALL     	11 3 2
	60	[625]	SUB      	10 10 11
	61	[625]	GETTABLE 	11 6 -24	; "left"
	62	[625]	MUL      	11 11 -26	; - 4
	63	[625]	DIV      	11 11 -25	; - 5
	64	[625]	CALL     	9 3 0
	65	[625]	CALL     	8 0 2
	66	[627]	GETTABLE 	9 0 -11	; "ui"
	67	[627]	GETTABLE 	9 9 -12	; "document"
	68	[627]	SELF     	9 9 -27	; "getVisiblePageCount"
	69	[627]	CALL     	9 2 2
	70	[627]	LT       	0 -10 9	; 1 -
	71	[627]	JMP      	56	; to 128
	72	[628]	GETUPVAL 	9 1	; Screen
	73	[628]	SELF     	9 9 -28	; "getWidth"
	74	[628]	CALL     	9 2 2
	75	[628]	DIV      	9 9 -29	; - 2
	76	[628]	LT       	0 5 9
	77	[628]	JMP      	24	; to 102
	78	[629]	GETUPVAL 	9 2	; BD
	79	[629]	GETTABLE 	9 9 -30	; "mirroredUILayout"
	80	[629]	CALL     	9 1 2
	81	[629]	TEST     	9 0 0
	82	[629]	JMP      	17	; to 100
	83	[632]	GETUPVAL 	9 1	; Screen
	84	[632]	SELF     	9 9 -28	; "getWidth"
	85	[632]	CALL     	9 2 2
	86	[632]	DIV      	5 9 -29	; - 2
	87	[633]	GETTABLE 	9 0 -11	; "ui"
	88	[633]	GETTABLE 	9 9 -12	; "document"
	89	[633]	SELF     	9 9 -31	; "getPageOffsetX"
	90	[633]	GETTABLE 	11 0 -11	; "ui"
	91	[633]	GETTABLE 	11 11 -12	; "document"
	92	[633]	SELF     	11 11 -32	; "getCurrentPage"
	93	[633]	CALL     	11 2 2
	94	[633]	ADD      	11 11 -10	; - 1
	95	[633]	CALL     	9 3 2
	96	[634]	ADD      	10 9 8
	97	[634]	SUB      	8 10 5
	98	[635]	SUB      	5 5 8
	99	[635]	JMP      	39	; to 139
	100	[637]	LOADK    	5 -33	; 0
	101	[638]	JMP      	37	; to 139
	102	[640]	GETUPVAL 	9 2	; BD
	103	[640]	GETTABLE 	9 9 -30	; "mirroredUILayout"
	104	[640]	CALL     	9 1 2
	105	[640]	TEST     	9 0 0
	106	[640]	JMP      	5	; to 112
	107	[641]	GETUPVAL 	9 1	; Screen
	108	[641]	SELF     	9 9 -28	; "getWidth"
	109	[641]	CALL     	9 2 2
	110	[641]	SUB      	5 9 8
	111	[641]	JMP      	27	; to 139
	112	[646]	GETUPVAL 	9 1	; Screen
	113	[646]	SELF     	9 9 -28	; "getWidth"
	114	[646]	CALL     	9 2 2
	115	[646]	DIV      	5 9 -29	; - 2
	116	[647]	GETTABLE 	9 0 -11	; "ui"
	117	[647]	GETTABLE 	9 9 -12	; "document"
	118	[647]	SELF     	9 9 -31	; "getPageOffsetX"
	119	[647]	GETTABLE 	11 0 -11	; "ui"
	120	[647]	GETTABLE 	11 11 -12	; "document"
	121	[647]	SELF     	11 11 -32	; "getCurrentPage"
	122	[647]	CALL     	11 2 2
	123	[647]	ADD      	11 11 -10	; - 1
	124	[647]	CALL     	9 3 2
	125	[648]	ADD      	10 9 8
	126	[648]	SUB      	8 10 5
	127	[650]	JMP      	11	; to 139
	128	[652]	GETUPVAL 	9 2	; BD
	129	[652]	GETTABLE 	9 9 -30	; "mirroredUILayout"
	130	[652]	CALL     	9 1 2
	131	[652]	TEST     	9 0 0
	132	[652]	JMP      	5	; to 138
	133	[653]	GETUPVAL 	9 1	; Screen
	134	[653]	SELF     	9 9 -28	; "getWidth"
	135	[653]	CALL     	9 2 2
	136	[653]	SUB      	5 9 8
	137	[653]	JMP      	1	; to 139
	138	[655]	LOADK    	5 -33	; 0
	139	[699]	CLOSURE  	9 0	; 0x7fc0a2412680
	140	[699]	MOVE     	0 0
	141	[699]	MOVE     	0 3
	142	[699]	GETUPVAL 	0 3	; Blitbuffer
	143	[699]	MOVE     	0 8
	144	[699]	MOVE     	0 7
	145	[699]	GETUPVAL 	0 1	; Screen
	146	[699]	MOVE     	0 5
	147	[699]	MOVE     	0 4
	148	[699]	GETUPVAL 	0 0	; UIManager
	149	[699]	SETTABLE 	0 -1 9	; "mark_func" -
	150	[700]	GETUPVAL 	9 0	; UIManager
	151	[700]	SELF     	9 9 -34	; "scheduleIn"
	152	[700]	LOADK    	11 -35	; 0.5
	153	[700]	GETTABLE 	12 0 -1	; "mark_func"
	154	[700]	CALL     	9 4 1
	155	[700]	CLOSE    	4
	156	[702]	LOADBOOL 	4 1 0
	157	[702]	RETURN   	4 2
	158	[703]	RETURN   	0 1

function <./frontend/apps/reader/modules/readerrolling.lua:659,699> (80 instructions, 320 bytes at 0x7fc0a2412680)
0 params, 10 slots, 9 upvalues, 1 local, 16 constants, 1 function
	1	[660]	GETUPVAL 	0 0	; self
	2	[660]	SETTABLE 	0 -1 -2	; "mark_func" nil
	3	[661]	GETGLOBAL	0 -3	; type
	4	[661]	GETUPVAL 	1 1	; marker_setting
	5	[661]	CALL     	0 2 2
	6	[661]	EQ       	1 0 -4	; - "number"
	7	[661]	JMP      	1	; to 9
	8	[661]	LOADBOOL 	0 0 1
	9	[661]	LOADBOOL 	0 1 0
	10	[662]	TEST     	0 0 0
	11	[662]	JMP      	33	; to 45
	12	[670]	GETUPVAL 	1 0	; self
	13	[670]	GETTABLE 	1 1 -5	; "mark_orig_content_bb"
	14	[670]	TEST     	1 0 0
	15	[670]	JMP      	6	; to 22
	16	[673]	GETUPVAL 	1 0	; self
	17	[673]	GETTABLE 	1 1 -5	; "mark_orig_content_bb"
	18	[673]	SELF     	1 1 -6	; "free"
	19	[673]	CALL     	1 2 1
	20	[674]	GETUPVAL 	1 0	; self
	21	[674]	SETTABLE 	1 -5 -2	; "mark_orig_content_bb" nil
	22	[676]	GETUPVAL 	1 0	; self
	23	[676]	GETUPVAL 	2 2	; Blitbuffer
	24	[676]	GETTABLE 	2 2 -7	; "new"
	25	[676]	GETUPVAL 	3 3	; marker_w
	26	[676]	GETUPVAL 	4 4	; marker_h
	27	[676]	GETUPVAL 	5 5	; Screen
	28	[676]	GETTABLE 	5 5 -8	; "bb"
	29	[676]	SELF     	5 5 -9	; "getType"
	30	[676]	CALL     	5 2 0
	31	[676]	CALL     	2 0 2
	32	[676]	SETTABLE 	1 -5 2	; "mark_orig_content_bb" -
	33	[677]	GETUPVAL 	1 0	; self
	34	[677]	GETTABLE 	1 1 -5	; "mark_orig_content_bb"
	35	[677]	SELF     	1 1 -10	; "blitFrom"
	36	[677]	GETUPVAL 	3 5	; Screen
	37	[677]	GETTABLE 	3 3 -8	; "bb"
	38	[677]	LOADK    	4 -11	; 0
	39	[677]	LOADK    	5 -11	; 0
	40	[677]	GETUPVAL 	6 6	; screen_x
	41	[677]	GETUPVAL 	7 7	; screen_y
	42	[677]	GETUPVAL 	8 3	; marker_w
	43	[677]	GETUPVAL 	9 4	; marker_h
	44	[677]	CALL     	1 9 1
	45	[680]	GETUPVAL 	1 5	; Screen
	46	[680]	GETTABLE 	1 1 -8	; "bb"
	47	[680]	SELF     	1 1 -12	; "paintRect"
	48	[680]	GETUPVAL 	3 6	; screen_x
	49	[680]	GETUPVAL 	4 7	; screen_y
	50	[680]	GETUPVAL 	5 3	; marker_w
	51	[680]	GETUPVAL 	6 4	; marker_h
	52	[680]	GETUPVAL 	7 2	; Blitbuffer
	53	[680]	GETTABLE 	7 7 -13	; "COLOR_BLACK"
	54	[680]	CALL     	1 7 1
	55	[681]	GETUPVAL 	1 5	; Screen
	56	[681]	GETTABLE 	1 1 -14	; "refreshFast"
	57	[681]	GETUPVAL 	2 5	; Screen
	58	[681]	GETUPVAL 	3 6	; screen_x
	59	[681]	GETUPVAL 	4 7	; screen_y
	60	[681]	GETUPVAL 	5 3	; marker_w
	61	[681]	GETUPVAL 	6 4	; marker_h
	62	[681]	CALL     	1 6 1
	63	[682]	TEST     	0 0 0
	64	[682]	JMP      	15	; to 80
	65	[683]	GETUPVAL 	1 0	; self
	66	[696]	CLOSURE  	2 0	; 0x7fc0a2412b60
	67	[696]	GETUPVAL 	0 0	; self
	68	[696]	GETUPVAL 	0 5	; Screen
	69	[696]	GETUPVAL 	0 6	; screen_x
	70	[696]	GETUPVAL 	0 7	; screen_y
	71	[696]	GETUPVAL 	0 3	; marker_w
	72	[696]	GETUPVAL 	0 4	; marker_h
	73	[696]	SETTABLE 	1 -15 2	; "unmark_func" -
	74	[697]	GETUPVAL 	1 8	; UIManager
	75	[697]	SELF     	1 1 -16	; "scheduleIn"
	76	[697]	GETUPVAL 	3 1	; marker_setting
	77	[697]	GETUPVAL 	4 0	; self
	78	[697]	GETTABLE 	4 4 -15	; "unmark_func"
	79	[697]	CALL     	1 4 1
	80	[699]	RETURN   	0 1

function <./frontend/apps/reader/modules/readerrolling.lua:683,696> (33 instructions, 132 bytes at 0x7fc0a2412b60)
0 params, 9 slots, 6 upvalues, 0 locals, 8 constants, 0 functions
	1	[684]	GETUPVAL 	0 0	; self
	2	[684]	SETTABLE 	0 -1 -2	; "unmark_func" nil
	3	[690]	GETUPVAL 	0 0	; self
	4	[690]	GETTABLE 	0 0 -3	; "mark_orig_content_bb"
	5	[690]	TEST     	0 0 0
	6	[690]	JMP      	26	; to 33
	7	[691]	GETUPVAL 	0 1	; Screen
	8	[691]	GETTABLE 	0 0 -4	; "bb"
	9	[691]	SELF     	0 0 -5	; "blitFrom"
	10	[691]	GETUPVAL 	2 0	; self
	11	[691]	GETTABLE 	2 2 -3	; "mark_orig_content_bb"
	12	[691]	GETUPVAL 	3 2	; screen_x
	13	[691]	GETUPVAL 	4 3	; screen_y
	14	[691]	LOADK    	5 -6	; 0
	15	[691]	LOADK    	6 -6	; 0
	16	[691]	GETUPVAL 	7 4	; marker_w
	17	[691]	GETUPVAL 	8 5	; marker_h
	18	[691]	CALL     	0 9 1
	19	[692]	GETUPVAL 	0 1	; Screen
	20	[692]	GETTABLE 	0 0 -7	; "refreshUI"
	21	[692]	GETUPVAL 	1 1	; Screen
	22	[692]	GETUPVAL 	2 2	; screen_x
	23	[692]	GETUPVAL 	3 3	; screen_y
	24	[692]	GETUPVAL 	4 4	; marker_w
	25	[692]	GETUPVAL 	5 5	; marker_h
	26	[692]	CALL     	0 6 1
	27	[693]	GETUPVAL 	0 0	; self
	28	[693]	GETTABLE 	0 0 -3	; "mark_orig_content_bb"
	29	[693]	SELF     	0 0 -8	; "free"
	30	[693]	CALL     	0 2 1
	31	[694]	GETUPVAL 	0 0	; self
	32	[694]	SETTABLE 	0 -3 -2	; "mark_orig_content_bb" nil
	33	[696]	RETURN   	0 1

function <./frontend/apps/reader/modules/readerrolling.lua:705,707> (3 instructions, 12 bytes at 0x7fc0a2412fc0)
1 param, 2 slots, 0 upvalues, 1 local, 1 constant, 0 functions
	1	[706]	GETTABLE 	1 0 -1	; "xpointer"
	2	[706]	RETURN   	1 2
	3	[707]	RETURN   	0 1

function <./frontend/apps/reader/modules/readerrolling.lua:709,711> (6 instructions, 24 bytes at 0x7fc0a2413520)
2 params, 6 slots, 0 upvalues, 2 locals, 3 constants, 0 functions
	1	[710]	SELF     	2 0 -1	; "onGotoXPointer"
	2	[710]	GETTABLE 	4 1 -2	; "xpointer"
	3	[710]	GETTABLE 	5 1 -3	; "marker_xpointer"
	4	[710]	TAILCALL 	2 4 0
	5	[710]	RETURN   	2 0
	6	[711]	RETURN   	0 1

function <./frontend/apps/reader/modules/readerrolling.lua:713,753> (139 instructions, 556 bytes at 0x7fc0a24132c0)
2 params, 12 slots, 3 upvalues, 11 locals, 41 constants, 0 functions
	1	[714]	GETUPVAL 	2 0	; logger
	2	[714]	GETTABLE 	2 2 -1	; "dbg"
	3	[714]	LOADK    	3 -2	; "goto relative screen:"
	4	[714]	MOVE     	4 1
	5	[714]	LOADK    	5 -3	; ", in mode: "
	6	[714]	GETTABLE 	6 0 -4	; "view"
	7	[714]	GETTABLE 	6 6 -5	; "view_mode"
	8	[714]	CALL     	2 5 1
	9	[715]	GETTABLE 	2 0 -4	; "view"
	10	[715]	GETTABLE 	2 2 -5	; "view_mode"
	11	[715]	EQ       	0 2 -6	; - "scroll"
	12	[715]	JMP      	76	; to 89
	13	[716]	GETTABLE 	2 0 -4	; "view"
	14	[716]	GETTABLE 	2 2 -7	; "footer_visible"
	15	[716]	TEST     	2 0 0
	16	[716]	JMP      	3	; to 20
	17	[716]	LOADK    	2 -8	; 1
	18	[716]	TEST     	2 0 1
	19	[716]	JMP      	1	; to 21
	20	[716]	LOADK    	2 -9	; 0
	21	[716]	GETTABLE 	3 0 -4	; "view"
	22	[716]	GETTABLE 	3 3 -10	; "footer"
	23	[716]	SELF     	3 3 -11	; "getHeight"
	24	[716]	CALL     	3 2 2
	25	[716]	MUL      	2 2 3
	26	[717]	GETTABLE 	3 0 -12	; "ui"
	27	[717]	GETTABLE 	3 3 -13	; "dimen"
	28	[717]	GETTABLE 	3 3 -14	; "h"
	29	[717]	SUB      	3 3 2
	30	[718]	MUL      	4 1 3
	31	[719]	GETTABLE 	5 0 -15	; "show_overlap_enable"
	32	[719]	TEST     	5 0 0
	33	[719]	JMP      	28	; to 62
	34	[720]	GETGLOBAL	5 -16	; G_reader_settings
	35	[720]	SELF     	5 5 -17	; "readSetting"
	36	[720]	LOADK    	7 -18	; "copt_overlap_lines"
	37	[720]	CALL     	5 3 2
	38	[720]	TEST     	5 0 1
	39	[720]	JMP      	1	; to 41
	40	[720]	LOADK    	5 -8	; 1
	41	[721]	GETUPVAL 	6 1	; Screen
	42	[721]	SELF     	6 6 -19	; "scaleBySize"
	43	[721]	GETTABLE 	8 0 -12	; "ui"
	44	[721]	GETTABLE 	8 8 -20	; "font"
	45	[721]	GETTABLE 	8 8 -21	; "font_size"
	46	[721]	MUL      	8 8 -22	; - 1.1
	47	[721]	GETTABLE 	9 0 -12	; "ui"
	48	[721]	GETTABLE 	9 9 -20	; "font"
	49	[721]	GETTABLE 	9 9 -23	; "line_space_percent"
	50	[721]	MUL      	8 8 9
	51	[721]	DIV      	8 8 -24	; - 100
	52	[721]	CALL     	6 3 2
	53	[721]	MUL      	6 6 5
	54	[722]	LT       	0 6 4
	55	[722]	JMP      	2	; to 58
	56	[723]	SUB      	4 4 6
	57	[723]	JMP      	4	; to 62
	58	[724]	UNM      	7 6
	59	[724]	LT       	0 4 7
	60	[724]	JMP      	1	; to 62
	61	[725]	ADD      	4 4 6
	62	[728]	GETTABLE 	5 0 -25	; "current_pos"
	63	[730]	GETGLOBAL	6 -26	; math
	64	[730]	GETTABLE 	6 6 -27	; "abs"
	65	[730]	MOVE     	7 1
	66	[730]	CALL     	6 2 2
	67	[730]	EQ       	1 6 -8	; - 1
	68	[730]	JMP      	1	; to 70
	69	[730]	LOADBOOL 	6 0 1
	70	[730]	LOADBOOL 	6 1 0
	71	[731]	SELF     	7 0 -28	; "_gotoPos"
	72	[731]	GETTABLE 	9 0 -25	; "current_pos"
	73	[731]	ADD      	9 9 4
	74	[731]	MOVE     	10 6
	75	[731]	CALL     	7 4 1
	76	[732]	LT       	0 -9 1	; 0 -
	77	[732]	JMP      	50	; to 128
	78	[732]	GETTABLE 	7 0 -25	; "current_pos"
	79	[732]	EQ       	0 5 7
	80	[732]	JMP      	47	; to 128
	81	[733]	GETTABLE 	7 0 -12	; "ui"
	82	[733]	SELF     	7 7 -29	; "handleEvent"
	83	[733]	GETUPVAL 	9 2	; Event
	84	[733]	SELF     	9 9 -30	; "new"
	85	[733]	LOADK    	11 -31	; "EndOfBook"
	86	[733]	CALL     	9 3 0
	87	[733]	CALL     	7 0 1
	88	[734]	JMP      	39	; to 128
	89	[735]	GETTABLE 	2 0 -4	; "view"
	90	[735]	GETTABLE 	2 2 -5	; "view_mode"
	91	[735]	EQ       	0 2 -32	; - "page"
	92	[735]	JMP      	35	; to 128
	93	[736]	GETTABLE 	2 0 -12	; "ui"
	94	[736]	GETTABLE 	2 2 -33	; "document"
	95	[736]	SELF     	2 2 -34	; "getVisiblePageCount"
	96	[736]	CALL     	2 2 2
	97	[737]	GETTABLE 	3 0 -35	; "current_page"
	98	[739]	LT       	0 -9 1	; 0 -
	99	[739]	JMP      	6	; to 106
	100	[740]	GETGLOBAL	4 -26	; math
	101	[740]	GETTABLE 	4 4 -36	; "ceil"
	102	[740]	MOVE     	5 1
	103	[740]	CALL     	4 2 2
	104	[740]	MOVE     	1 4
	105	[740]	JMP      	5	; to 111
	106	[742]	GETGLOBAL	4 -26	; math
	107	[742]	GETTABLE 	4 4 -37	; "floor"
	108	[742]	MOVE     	5 1
	109	[742]	CALL     	4 2 2
	110	[742]	MOVE     	1 4
	111	[744]	SELF     	4 0 -38	; "_gotoPage"
	112	[744]	GETTABLE 	6 0 -35	; "current_page"
	113	[744]	MUL      	7 1 2
	114	[744]	ADD      	6 6 7
	115	[744]	CALL     	4 3 1
	116	[745]	LT       	0 -9 1	; 0 -
	117	[745]	JMP      	10	; to 128
	118	[745]	GETTABLE 	4 0 -35	; "current_page"
	119	[745]	EQ       	0 3 4
	120	[745]	JMP      	7	; to 128
	121	[746]	GETTABLE 	4 0 -12	; "ui"
	122	[746]	SELF     	4 4 -29	; "handleEvent"
	123	[746]	GETUPVAL 	6 2	; Event
	124	[746]	SELF     	6 6 -30	; "new"
	125	[746]	LOADK    	8 -31	; "EndOfBook"
	126	[746]	CALL     	6 3 0
	127	[746]	CALL     	4 0 1
	128	[749]	GETTABLE 	2 0 -12	; "ui"
	129	[749]	GETTABLE 	2 2 -33	; "document"
	130	[749]	EQ       	1 2 -39	; - nil
	131	[749]	JMP      	5	; to 137
	132	[750]	GETTABLE 	2 0 -12	; "ui"
	133	[750]	GETTABLE 	2 2 -33	; "document"
	134	[750]	SELF     	2 2 -41	; "getXPointer"
	135	[750]	CALL     	2 2 2
	136	[750]	SETTABLE 	0 -40 2	; "xpointer" -
	137	[752]	LOADBOOL 	2 1 0
	138	[752]	RETURN   	2 2
	139	[753]	RETURN   	0 1

function <./frontend/apps/reader/modules/readerrolling.lua:755,764> (31 instructions, 124 bytes at 0x7fc0a2413890)
3 params, 11 slots, 2 upvalues, 5 locals, 15 constants, 0 functions
	1	[756]	GETGLOBAL	3 -1	; unpack
	2	[756]	MOVE     	4 1
	3	[756]	CALL     	3 2 3
	4	[757]	GETTABLE 	5 0 -2	; "view"
	5	[757]	GETTABLE 	5 5 -3	; "view_mode"
	6	[757]	EQ       	1 5 -4	; - "scroll"
	7	[757]	JMP      	9	; to 17
	8	[758]	GETUPVAL 	5 0	; UIManager
	9	[758]	SELF     	5 5 -5	; "broadcastEvent"
	10	[758]	GETUPVAL 	7 1	; Event
	11	[758]	SELF     	7 7 -6	; "new"
	12	[758]	LOADK    	9 -7	; "GotoViewRel"
	13	[758]	MOVE     	10 4
	14	[758]	CALL     	7 4 0
	15	[758]	CALL     	5 0 1
	16	[759]	RETURN   	0 1
	17	[761]	SELF     	5 0 -8	; "_gotoPos"
	18	[761]	GETTABLE 	7 0 -9	; "current_pos"
	19	[761]	GETTABLE 	8 0 -10	; "panning_steps"
	20	[761]	GETTABLE 	8 8 -11	; "normal"
	21	[761]	MUL      	8 4 8
	22	[761]	ADD      	7 7 8
	23	[761]	CALL     	5 3 1
	24	[762]	GETTABLE 	5 0 -13	; "ui"
	25	[762]	GETTABLE 	5 5 -14	; "document"
	26	[762]	SELF     	5 5 -15	; "getXPointer"
	27	[762]	CALL     	5 2 2
	28	[762]	SETTABLE 	0 -12 5	; "xpointer" -
	29	[763]	LOADBOOL 	5 1 0
	30	[763]	RETURN   	5 2
	31	[764]	RETURN   	0 1

function <./frontend/apps/reader/modules/readerrolling.lua:766,769> (3 instructions, 12 bytes at 0x7fc0a2413d70)
1 param, 3 slots, 0 upvalues, 1 local, 1 constant, 0 functions
	1	[768]	SELF     	1 0 -1	; "updatePos"
	2	[768]	CALL     	1 2 1
	3	[769]	RETURN   	0 1

function <./frontend/apps/reader/modules/readerrolling.lua:776,793> (17 instructions, 68 bytes at 0x7fc0a2414200)
1 param, 5 slots, 1 upvalue, 1 local, 7 constants, 1 function
	1	[777]	GETTABLE 	1 0 -1	; "ui"
	2	[777]	GETTABLE 	1 1 -2	; "postReaderCallback"
	3	[777]	EQ       	1 1 -3	; - nil
	4	[777]	JMP      	2	; to 7
	5	[781]	LOADBOOL 	1 1 0
	6	[781]	RETURN   	1 2
	7	[786]	GETTABLE 	1 0 -1	; "ui"
	8	[786]	GETTABLE 	1 1 -4	; "document"
	9	[786]	SELF     	1 1 -5	; "getCurrentPos"
	10	[786]	CALL     	1 2 1
	11	[792]	GETUPVAL 	1 0	; UIManager
	12	[792]	SELF     	1 1 -6	; "scheduleIn"
	13	[792]	LOADK    	3 -7	; 0.1
	14	[792]	CLOSURE  	4 0	; 0x7fc0a2414400
	15	[792]	MOVE     	0 0
	16	[792]	CALL     	1 4 1
	17	[793]	RETURN   	0 1

function <./frontend/apps/reader/modules/readerrolling.lua:792,792> (4 instructions, 16 bytes at 0x7fc0a2414400)
0 params, 2 slots, 1 upvalue, 0 locals, 1 constant, 0 functions
	1	[792]	GETUPVAL 	0 0	; self
	2	[792]	SELF     	0 0 -1	; "updatePos"
	3	[792]	CALL     	0 2 1
	4	[792]	RETURN   	0 1

function <./frontend/apps/reader/modules/readerrolling.lua:795,819> (52 instructions, 208 bytes at 0x7fc0a2414990)
1 param, 8 slots, 2 upvalues, 3 locals, 21 constants, 1 function
	1	[796]	GETTABLE 	1 0 -1	; "ui"
	2	[796]	GETTABLE 	1 1 -2	; "document"
	3	[796]	TEST     	1 0 1
	4	[796]	JMP      	1	; to 6
	5	[798]	RETURN   	0 1
	6	[801]	GETTABLE 	1 0 -1	; "ui"
	7	[801]	GETTABLE 	1 1 -2	; "document"
	8	[801]	SELF     	1 1 -3	; "_readMetadata"
	9	[801]	CALL     	1 2 1
	10	[803]	GETTABLE 	1 0 -1	; "ui"
	11	[803]	GETTABLE 	1 1 -2	; "document"
	12	[803]	GETTABLE 	1 1 -4	; "info"
	13	[803]	GETTABLE 	1 1 -5	; "doc_height"
	14	[804]	GETTABLE 	2 0 -1	; "ui"
	15	[804]	GETTABLE 	2 2 -2	; "document"
	16	[804]	GETTABLE 	2 2 -4	; "info"
	17	[804]	GETTABLE 	2 2 -6	; "number_of_pages"
	18	[805]	GETTABLE 	3 0 -7	; "old_doc_height"
	19	[805]	EQ       	0 3 1
	20	[805]	JMP      	3	; to 24
	21	[805]	GETTABLE 	3 0 -8	; "old_page"
	22	[805]	EQ       	1 3 2
	23	[805]	JMP      	16	; to 40
	24	[806]	SELF     	3 0 -9	; "_gotoXPointer"
	25	[806]	GETTABLE 	5 0 -10	; "xpointer"
	26	[806]	CALL     	3 3 1
	27	[807]	SETTABLE 	0 -7 1	; "old_doc_height" -
	28	[808]	SETTABLE 	0 -8 2	; "old_page" -
	29	[809]	GETTABLE 	3 0 -1	; "ui"
	30	[809]	SELF     	3 3 -11	; "handleEvent"
	31	[809]	GETUPVAL 	5 0	; Event
	32	[809]	SELF     	5 5 -12	; "new"
	33	[809]	LOADK    	7 -13	; "UpdateToc"
	34	[809]	CALL     	5 3 0
	35	[809]	CALL     	3 0 1
	36	[810]	GETTABLE 	3 0 -14	; "view"
	37	[810]	GETTABLE 	3 3 -15	; "footer"
	38	[810]	SELF     	3 3 -16	; "updateFooter"
	39	[810]	CALL     	3 2 1
	40	[812]	GETUPVAL 	3 1	; UIManager
	41	[812]	SELF     	3 3 -17	; "setDirty"
	42	[812]	GETTABLE 	5 0 -14	; "view"
	43	[812]	GETTABLE 	5 5 -18	; "dialog"
	44	[812]	LOADK    	6 -19	; "partial"
	45	[812]	CALL     	3 4 1
	46	[816]	GETUPVAL 	3 1	; UIManager
	47	[816]	SELF     	3 3 -20	; "scheduleIn"
	48	[816]	LOADK    	5 -21	; 0.1
	49	[818]	CLOSURE  	6 0	; 0x7fc0a2414b50
	50	[818]	MOVE     	0 0
	51	[816]	CALL     	3 4 1
	52	[819]	RETURN   	0 1

function <./frontend/apps/reader/modules/readerrolling.lua:816,818> (4 instructions, 16 bytes at 0x7fc0a2414b50)
0 params, 2 slots, 1 upvalue, 0 locals, 1 constant, 0 functions
	1	[817]	GETUPVAL 	0 0	; self
	2	[817]	SELF     	0 0 -1	; "onCheckDomStyleCoherence"
	3	[817]	CALL     	0 2 1
	4	[818]	RETURN   	0 1

function <./frontend/apps/reader/modules/readerrolling.lua:824,839> (47 instructions, 188 bytes at 0x7fc0a2414a40)
1 param, 6 slots, 2 upvalues, 1 local, 22 constants, 1 function
	1	[825]	GETTABLE 	1 0 -1	; "ui"
	2	[825]	GETTABLE 	1 1 -2	; "document"
	3	[825]	SELF     	1 1 -3	; "_readMetadata"
	4	[825]	CALL     	1 2 1
	5	[826]	GETTABLE 	1 0 -1	; "ui"
	6	[826]	GETTABLE 	1 1 -2	; "document"
	7	[826]	GETTABLE 	1 1 -5	; "info"
	8	[826]	GETTABLE 	1 1 -6	; "doc_height"
	9	[826]	SETTABLE 	0 -4 1	; "old_doc_height" -
	10	[827]	GETTABLE 	1 0 -1	; "ui"
	11	[827]	GETTABLE 	1 1 -2	; "document"
	12	[827]	GETTABLE 	1 1 -5	; "info"
	13	[827]	GETTABLE 	1 1 -8	; "number_of_pages"
	14	[827]	SETTABLE 	0 -7 1	; "old_page" -
	15	[828]	GETTABLE 	1 0 -1	; "ui"
	16	[828]	SELF     	1 1 -9	; "handleEvent"
	17	[828]	GETUPVAL 	3 0	; Event
	18	[828]	SELF     	3 3 -10	; "new"
	19	[828]	LOADK    	5 -11	; "UpdateToc"
	20	[828]	CALL     	3 3 0
	21	[828]	CALL     	1 0 1
	22	[829]	GETTABLE 	1 0 -12	; "view"
	23	[829]	GETTABLE 	1 1 -13	; "footer"
	24	[829]	SELF     	1 1 -14	; "setTocMarkers"
	25	[829]	LOADBOOL 	3 1 0
	26	[829]	CALL     	1 3 1
	27	[830]	GETTABLE 	1 0 -15	; "xpointer"
	28	[830]	TEST     	1 0 0
	29	[830]	JMP      	10	; to 40
	30	[831]	SELF     	1 0 -16	; "_gotoXPointer"
	31	[831]	GETTABLE 	3 0 -15	; "xpointer"
	32	[831]	CALL     	1 3 1
	33	[833]	GETUPVAL 	1 1	; UIManager
	34	[833]	SELF     	1 1 -17	; "setDirty"
	35	[833]	GETTABLE 	3 0 -12	; "view"
	36	[833]	GETTABLE 	3 3 -18	; "dialog"
	37	[833]	LOADK    	4 -19	; "partial"
	38	[833]	CALL     	1 4 1
	39	[833]	JMP      	7	; to 47
	40	[835]	GETGLOBAL	1 -20	; table
	41	[835]	GETTABLE 	1 1 -21	; "insert"
	42	[835]	GETTABLE 	2 0 -1	; "ui"
	43	[835]	GETTABLE 	2 2 -22	; "postInitCallback"
	44	[837]	CLOSURE  	3 0	; 0x7fc0a2414de0
	45	[837]	MOVE     	0 0
	46	[835]	CALL     	1 3 1
	47	[839]	RETURN   	0 1

function <./frontend/apps/reader/modules/readerrolling.lua:835,837> (6 instructions, 24 bytes at 0x7fc0a2414de0)
0 params, 3 slots, 1 upvalue, 0 locals, 2 constants, 0 functions
	1	[836]	GETUPVAL 	0 0	; self
	2	[836]	SELF     	0 0 -1	; "_gotoXPointer"
	3	[836]	GETUPVAL 	2 0	; self
	4	[836]	GETTABLE 	2 2 -2	; "xpointer"
	5	[836]	CALL     	0 3 1
	6	[837]	RETURN   	0 1

function <./frontend/apps/reader/modules/readerrolling.lua:841,848> (24 instructions, 96 bytes at 0x7fc0a24157b0)
1 param, 7 slots, 1 upvalue, 1 local, 10 constants, 0 functions
	1	[842]	GETTABLE 	1 0 -1	; "view"
	2	[842]	GETTABLE 	1 1 -2	; "view_mode"
	3	[842]	EQ       	0 1 -3	; - "page"
	4	[842]	JMP      	9	; to 14
	5	[843]	GETTABLE 	1 0 -4	; "ui"
	6	[843]	SELF     	1 1 -5	; "handleEvent"
	7	[843]	GETUPVAL 	3 0	; Event
	8	[843]	SELF     	3 3 -6	; "new"
	9	[843]	LOADK    	5 -7	; "PageUpdate"
	10	[843]	GETTABLE 	6 0 -8	; "current_page"
	11	[843]	CALL     	3 4 0
	12	[843]	CALL     	1 0 1
	13	[843]	JMP      	8	; to 22
	14	[845]	GETTABLE 	1 0 -4	; "ui"
	15	[845]	SELF     	1 1 -5	; "handleEvent"
	16	[845]	GETUPVAL 	3 0	; Event
	17	[845]	SELF     	3 3 -6	; "new"
	18	[845]	LOADK    	5 -9	; "PosUpdate"
	19	[845]	GETTABLE 	6 0 -10	; "current_pos"
	20	[845]	CALL     	3 4 0
	21	[845]	CALL     	1 0 1
	22	[847]	LOADBOOL 	1 1 0
	23	[847]	RETURN   	1 2
	24	[848]	RETURN   	0 1

function <./frontend/apps/reader/modules/readerrolling.lua:850,871> (36 instructions, 144 bytes at 0x7fc0a2415a60)
2 params, 6 slots, 1 upvalue, 2 locals, 10 constants, 0 functions
	1	[851]	GETTABLE 	2 0 -1	; "ui"
	2	[851]	GETTABLE 	2 2 -2	; "postReaderCallback"
	3	[851]	EQ       	1 2 -3	; - nil
	4	[851]	JMP      	8	; to 13
	5	[853]	GETTABLE 	2 0 -1	; "ui"
	6	[853]	GETTABLE 	2 2 -4	; "document"
	7	[853]	SELF     	2 2 -5	; "setViewDimen"
	8	[853]	GETUPVAL 	4 0	; Screen
	9	[853]	SELF     	4 4 -6	; "getSize"
	10	[853]	CALL     	4 2 0
	11	[853]	CALL     	2 0 1
	12	[853]	JMP      	23	; to 36
	13	[861]	GETTABLE 	2 0 -1	; "ui"
	14	[861]	GETTABLE 	2 2 -4	; "document"
	15	[861]	SELF     	2 2 -7	; "enableInternalHistory"
	16	[861]	LOADBOOL 	4 1 0
	17	[861]	CALL     	2 3 1
	18	[863]	GETTABLE 	2 0 -1	; "ui"
	19	[863]	GETTABLE 	2 2 -4	; "document"
	20	[863]	SELF     	2 2 -5	; "setViewDimen"
	21	[863]	GETUPVAL 	4 0	; Screen
	22	[863]	SELF     	4 4 -6	; "getSize"
	23	[863]	CALL     	4 2 0
	24	[863]	CALL     	2 0 1
	25	[865]	SELF     	2 0 -8	; "onChangeViewMode"
	26	[865]	CALL     	2 2 1
	27	[866]	SELF     	2 0 -9	; "onUpdatePos"
	28	[866]	CALL     	2 2 1
	29	[868]	GETTABLE 	2 0 -1	; "ui"
	30	[868]	GETTABLE 	2 2 -4	; "document"
	31	[868]	SELF     	2 2 -7	; "enableInternalHistory"
	32	[868]	LOADBOOL 	4 0 0
	33	[868]	CALL     	2 3 1
	34	[869]	SELF     	2 0 -10	; "onRedrawCurrentView"
	35	[869]	CALL     	2 2 1
	36	[871]	RETURN   	0 1

function <./frontend/apps/reader/modules/readerrolling.lua:873,879> (12 instructions, 48 bytes at 0x7fc0a24159b0)
3 params, 10 slots, 1 upvalue, 3 locals, 4 constants, 0 functions
	1	[876]	GETTABLE 	3 0 -1	; "ui"
	2	[876]	SELF     	3 3 -2	; "handleEvent"
	3	[876]	GETUPVAL 	5 0	; Event
	4	[876]	SELF     	5 5 -3	; "new"
	5	[876]	LOADK    	7 -4	; "SetScreenMode"
	6	[876]	MOVE     	8 1
	7	[876]	TESTSET  	9 2 1
	8	[876]	JMP      	1	; to 10
	9	[876]	LOADBOOL 	9 1 0
	10	[876]	CALL     	5 5 0
	11	[876]	CALL     	3 0 1
	12	[879]	RETURN   	0 1

function <./frontend/apps/reader/modules/readerrolling.lua:881,884> (11 instructions, 44 bytes at 0x7fc0a2411610)
1 param, 5 slots, 1 upvalue, 1 local, 7 constants, 0 functions
	1	[882]	GETTABLE 	1 0 -1	; "ui"
	2	[882]	GETTABLE 	1 1 -2	; "document"
	3	[882]	SELF     	1 1 -3	; "updateColorRendering"
	4	[882]	CALL     	1 2 1
	5	[883]	GETUPVAL 	1 0	; UIManager
	6	[883]	SELF     	1 1 -4	; "setDirty"
	7	[883]	GETTABLE 	3 0 -5	; "view"
	8	[883]	GETTABLE 	3 3 -6	; "dialog"
	9	[883]	LOADK    	4 -7	; "partial"
	10	[883]	CALL     	1 4 1
	11	[884]	RETURN   	0 1

function <./frontend/apps/reader/modules/readerrolling.lua:889,922> (116 instructions, 464 bytes at 0x7fc0a2416780)
3 params, 12 slots, 1 upvalue, 7 locals, 29 constants, 0 functions
	1	[890]	GETTABLE 	3 0 -1	; "current_pos"
	2	[890]	EQ       	0 1 3
	3	[890]	JMP      	1	; to 5
	4	[890]	RETURN   	0 1
	5	[891]	LT       	0 1 -2	; - 0
	6	[891]	JMP      	1	; to 8
	7	[891]	LOADK    	1 -2	; 0
	8	[894]	GETTABLE 	3 0 -3	; "ui"
	9	[894]	GETTABLE 	3 3 -4	; "document"
	10	[894]	GETTABLE 	3 3 -5	; "info"
	11	[894]	GETTABLE 	3 3 -6	; "doc_height"
	12	[894]	GETTABLE 	4 0 -3	; "ui"
	13	[894]	GETTABLE 	4 4 -7	; "dimen"
	14	[894]	GETTABLE 	4 4 -8	; "h"
	15	[894]	SUB      	3 3 4
	16	[894]	GETTABLE 	4 0 -9	; "view"
	17	[894]	GETTABLE 	4 4 -10	; "footer"
	18	[894]	SELF     	4 4 -11	; "getHeight"
	19	[894]	CALL     	4 2 2
	20	[894]	ADD      	3 3 4
	21	[895]	LT       	0 3 1
	22	[895]	JMP      	1	; to 24
	23	[895]	MOVE     	1 3
	24	[897]	GETTABLE 	4 0 -9	; "view"
	25	[897]	GETTABLE 	4 4 -12	; "view_mode"
	26	[897]	EQ       	1 4 -13	; - "page"
	27	[897]	JMP      	68	; to 96
	28	[897]	GETTABLE 	4 0 -14	; "show_overlap_enable"
	29	[897]	TEST     	4 0 0
	30	[897]	JMP      	65	; to 96
	31	[897]	TEST     	2 0 0
	32	[897]	JMP      	63	; to 96
	33	[898]	GETTABLE 	4 0 -9	; "view"
	34	[898]	GETTABLE 	4 4 -15	; "footer_visible"
	35	[898]	TEST     	4 0 0
	36	[898]	JMP      	3	; to 40
	37	[898]	LOADK    	4 -16	; 1
	38	[898]	TEST     	4 0 1
	39	[898]	JMP      	1	; to 41
	40	[898]	LOADK    	4 -2	; 0
	41	[898]	GETTABLE 	5 0 -9	; "view"
	42	[898]	GETTABLE 	5 5 -10	; "footer"
	43	[898]	SELF     	5 5 -11	; "getHeight"
	44	[898]	CALL     	5 2 2
	45	[898]	MUL      	4 4 5
	46	[899]	GETTABLE 	5 0 -3	; "ui"
	47	[899]	GETTABLE 	5 5 -7	; "dimen"
	48	[899]	GETTABLE 	5 5 -8	; "h"
	49	[899]	SUB      	5 5 4
	50	[900]	GETTABLE 	6 0 -1	; "current_pos"
	51	[900]	SUB      	6 1 6
	52	[901]	GETTABLE 	7 0 -9	; "view"
	53	[901]	GETTABLE 	7 7 -17	; "dim_area"
	54	[901]	SETTABLE 	7 -18 -2	; "x" 0
	55	[902]	GETTABLE 	7 0 -9	; "view"
	56	[902]	GETTABLE 	7 7 -17	; "dim_area"
	57	[902]	GETGLOBAL	8 -19	; math
	58	[902]	GETTABLE 	8 8 -20	; "abs"
	59	[902]	MOVE     	9 6
	60	[902]	CALL     	8 2 2
	61	[902]	SUB      	8 5 8
	62	[902]	SETTABLE 	7 -8 8	; "h" -
	63	[903]	GETTABLE 	7 0 -9	; "view"
	64	[903]	GETTABLE 	7 7 -17	; "dim_area"
	65	[903]	GETTABLE 	8 0 -3	; "ui"
	66	[903]	GETTABLE 	8 8 -7	; "dimen"
	67	[903]	GETTABLE 	8 8 -21	; "w"
	68	[903]	SETTABLE 	7 -21 8	; "w" -
	69	[904]	LT       	0 6 -2	; - 0
	70	[904]	JMP      	8	; to 79
	71	[905]	GETTABLE 	7 0 -9	; "view"
	72	[905]	GETTABLE 	7 7 -17	; "dim_area"
	73	[905]	GETTABLE 	8 0 -9	; "view"
	74	[905]	GETTABLE 	8 8 -17	; "dim_area"
	75	[905]	GETTABLE 	8 8 -8	; "h"
	76	[905]	SUB      	8 5 8
	77	[905]	SETTABLE 	7 -22 8	; "y" -
	78	[905]	JMP      	5	; to 84
	79	[906]	LT       	0 -2 6	; 0 -
	80	[906]	JMP      	3	; to 84
	81	[907]	GETTABLE 	7 0 -9	; "view"
	82	[907]	GETTABLE 	7 7 -17	; "dim_area"
	83	[907]	SETTABLE 	7 -22 -2	; "y" 0
	84	[909]	GETTABLE 	7 0 -1	; "current_pos"
	85	[909]	GETTABLE 	8 0 -3	; "ui"
	86	[909]	GETTABLE 	8 8 -7	; "dimen"
	87	[909]	GETTABLE 	8 8 -8	; "h"
	88	[909]	DIV      	8 8 -23	; - 2
	89	[909]	SUB      	8 3 8
	90	[909]	LT       	0 8 7
	91	[909]	JMP      	7	; to 99
	92	[912]	GETTABLE 	7 0 -9	; "view"
	93	[912]	SELF     	7 7 -24	; "resetDimArea"
	94	[912]	CALL     	7 2 1
	95	[913]	JMP      	3	; to 99
	96	[915]	GETTABLE 	4 0 -9	; "view"
	97	[915]	SELF     	4 4 -24	; "resetDimArea"
	98	[915]	CALL     	4 2 1
	99	[917]	GETTABLE 	4 0 -3	; "ui"
	100	[917]	GETTABLE 	4 4 -4	; "document"
	101	[917]	SELF     	4 4 -25	; "gotoPos"
	102	[917]	MOVE     	6 1
	103	[917]	CALL     	4 3 1
	104	[921]	GETTABLE 	4 0 -3	; "ui"
	105	[921]	SELF     	4 4 -26	; "handleEvent"
	106	[921]	GETUPVAL 	6 0	; Event
	107	[921]	SELF     	6 6 -27	; "new"
	108	[921]	LOADK    	8 -28	; "PosUpdate"
	109	[921]	MOVE     	9 1
	110	[921]	GETTABLE 	10 0 -3	; "ui"
	111	[921]	GETTABLE 	10 10 -4	; "document"
	112	[921]	SELF     	10 10 -29	; "getCurrentPage"
	113	[921]	CALL     	10 2 0
	114	[921]	CALL     	6 0 0
	115	[921]	CALL     	4 0 1
	116	[922]	RETURN   	0 1

function <./frontend/apps/reader/modules/readerrolling.lua:924,926> (9 instructions, 36 bytes at 0x7fc0a2416d60)
2 params, 5 slots, 0 upvalues, 2 locals, 6 constants, 0 functions
	1	[925]	SELF     	2 0 -1	; "_gotoPos"
	2	[925]	GETTABLE 	4 0 -2	; "ui"
	3	[925]	GETTABLE 	4 4 -3	; "document"
	4	[925]	GETTABLE 	4 4 -4	; "info"
	5	[925]	GETTABLE 	4 4 -5	; "doc_height"
	6	[925]	MUL      	4 1 4
	7	[925]	DIV      	4 4 -6	; - 10000
	8	[925]	CALL     	2 3 1
	9	[926]	RETURN   	0 1

function <./frontend/apps/reader/modules/readerrolling.lua:928,949> (66 instructions, 264 bytes at 0x7fc0a2416e20)
3 params, 11 slots, 2 upvalues, 3 locals, 17 constants, 0 functions
	1	[929]	GETTABLE 	3 0 -1	; "ui"
	2	[929]	GETTABLE 	3 3 -2	; "document"
	3	[929]	SELF     	3 3 -3	; "getVisiblePageCount"
	4	[929]	CALL     	3 2 2
	5	[929]	LT       	0 -4 3	; 1 -
	6	[929]	JMP      	23	; to 30
	7	[929]	TEST     	2 0 1
	8	[929]	JMP      	21	; to 30
	9	[931]	GETTABLE 	3 0 -5	; "odd_or_even_first_page"
	10	[931]	EQ       	0 3 -4	; - 1
	11	[931]	JMP      	8	; to 20
	12	[932]	GETUPVAL 	3 0	; band
	13	[932]	MOVE     	4 1
	14	[932]	LOADK    	5 -4	; 1
	15	[932]	CALL     	3 3 2
	16	[932]	EQ       	0 3 -6	; - 0
	17	[932]	JMP      	12	; to 30
	18	[934]	SUB      	1 1 -4	; - 1
	19	[935]	JMP      	10	; to 30
	20	[936]	GETTABLE 	3 0 -5	; "odd_or_even_first_page"
	21	[936]	EQ       	0 3 -7	; - 2
	22	[936]	JMP      	7	; to 30
	23	[937]	GETUPVAL 	3 0	; band
	24	[937]	MOVE     	4 1
	25	[937]	LOADK    	5 -4	; 1
	26	[937]	CALL     	3 3 2
	27	[937]	EQ       	0 3 -4	; - 1
	28	[937]	JMP      	1	; to 30
	29	[939]	SUB      	1 1 -4	; - 1
	30	[943]	GETTABLE 	3 0 -1	; "ui"
	31	[943]	GETTABLE 	3 3 -2	; "document"
	32	[943]	SELF     	3 3 -8	; "gotoPage"
	33	[943]	MOVE     	5 1
	34	[943]	CALL     	3 3 1
	35	[944]	GETTABLE 	3 0 -9	; "view"
	36	[944]	GETTABLE 	3 3 -10	; "view_mode"
	37	[944]	EQ       	0 3 -11	; - "page"
	38	[944]	JMP      	12	; to 51
	39	[945]	GETTABLE 	3 0 -1	; "ui"
	40	[945]	SELF     	3 3 -12	; "handleEvent"
	41	[945]	GETUPVAL 	5 1	; Event
	42	[945]	SELF     	5 5 -13	; "new"
	43	[945]	LOADK    	7 -14	; "PageUpdate"
	44	[945]	GETTABLE 	8 0 -1	; "ui"
	45	[945]	GETTABLE 	8 8 -2	; "document"
	46	[945]	SELF     	8 8 -15	; "getCurrentPage"
	47	[945]	CALL     	8 2 0
	48	[945]	CALL     	5 0 0
	49	[945]	CALL     	3 0 1
	50	[945]	JMP      	15	; to 66
	51	[947]	GETTABLE 	3 0 -1	; "ui"
	52	[947]	SELF     	3 3 -12	; "handleEvent"
	53	[947]	GETUPVAL 	5 1	; Event
	54	[947]	SELF     	5 5 -13	; "new"
	55	[947]	LOADK    	7 -16	; "PosUpdate"
	56	[947]	GETTABLE 	8 0 -1	; "ui"
	57	[947]	GETTABLE 	8 8 -2	; "document"
	58	[947]	SELF     	8 8 -17	; "getCurrentPos"
	59	[947]	CALL     	8 2 2
	60	[947]	GETTABLE 	9 0 -1	; "ui"
	61	[947]	GETTABLE 	9 9 -2	; "document"
	62	[947]	SELF     	9 9 -15	; "getCurrentPage"
	63	[947]	CALL     	9 2 0
	64	[947]	CALL     	5 0 0
	65	[947]	CALL     	3 0 1
	66	[949]	RETURN   	0 1

function <./frontend/apps/reader/modules/readerrolling.lua:951,957> (20 instructions, 80 bytes at 0x7fc0a2416f60)
2 params, 7 slots, 0 upvalues, 2 locals, 9 constants, 0 functions
	1	[952]	GETTABLE 	2 0 -1	; "view"
	2	[952]	GETTABLE 	2 2 -2	; "view_mode"
	3	[952]	EQ       	0 2 -3	; - "page"
	4	[952]	JMP      	8	; to 13
	5	[953]	SELF     	2 0 -4	; "_gotoPage"
	6	[953]	GETTABLE 	4 0 -5	; "ui"
	7	[953]	GETTABLE 	4 4 -6	; "document"
	8	[953]	SELF     	4 4 -7	; "getPageFromXPointer"
	9	[953]	MOVE     	6 1
	10	[953]	CALL     	4 3 0
	11	[953]	CALL     	2 0 1
	12	[953]	JMP      	7	; to 20
	13	[955]	SELF     	2 0 -8	; "_gotoPos"
	14	[955]	GETTABLE 	4 0 -5	; "ui"
	15	[955]	GETTABLE 	4 4 -6	; "document"
	16	[955]	SELF     	4 4 -9	; "getPosFromXPointer"
	17	[955]	MOVE     	6 1
	18	[955]	CALL     	4 3 0
	19	[955]	CALL     	2 0 1
	20	[957]	RETURN   	0 1

function <./frontend/apps/reader/modules/readerrolling.lua:969,987> (24 instructions, 96 bytes at 0x7fc0a2418460)
2 params, 9 slots, 1 upvalue, 4 locals, 8 constants, 0 functions
	1	[980]	SETTABLE 	0 -1 1	; "visible_pages" -
	2	[981]	GETTABLE 	2 0 -2	; "ui"
	3	[981]	GETTABLE 	2 2 -3	; "document"
	4	[981]	SELF     	2 2 -4	; "getVisiblePageCount"
	5	[981]	CALL     	2 2 2
	6	[982]	GETTABLE 	3 0 -2	; "ui"
	7	[982]	GETTABLE 	3 3 -3	; "document"
	8	[982]	SELF     	3 3 -5	; "setVisiblePageCount"
	9	[982]	MOVE     	5 1
	10	[982]	CALL     	3 3 1
	11	[983]	GETTABLE 	3 0 -2	; "ui"
	12	[983]	GETTABLE 	3 3 -3	; "document"
	13	[983]	SELF     	3 3 -4	; "getVisiblePageCount"
	14	[983]	CALL     	3 2 2
	15	[984]	EQ       	1 3 2
	16	[984]	JMP      	7	; to 24
	17	[985]	GETTABLE 	4 0 -2	; "ui"
	18	[985]	SELF     	4 4 -6	; "handleEvent"
	19	[985]	GETUPVAL 	6 0	; Event
	20	[985]	SELF     	6 6 -7	; "new"
	21	[985]	LOADK    	8 -8	; "UpdatePos"
	22	[985]	CALL     	6 3 0
	23	[985]	CALL     	4 0 1
	24	[987]	RETURN   	0 1

function <./frontend/apps/reader/modules/readerrolling.lua:989,1001> (28 instructions, 112 bytes at 0x7fc0a24187f0)
3 params, 8 slots, 1 upvalue, 3 locals, 12 constants, 0 functions
	1	[993]	GETTABLE 	3 0 -1	; "ui"
	2	[993]	GETTABLE 	3 3 -2	; "document"
	3	[993]	SELF     	3 3 -3	; "setStatusLineProp"
	4	[993]	MOVE     	5 1
	5	[993]	CALL     	3 3 1
	6	[994]	EQ       	1 1 -5	; - 0
	7	[994]	JMP      	1	; to 9
	8	[994]	LOADBOOL 	3 0 1
	9	[994]	LOADBOOL 	3 1 0
	10	[994]	SETTABLE 	0 -4 3	; "cre_top_bar_enabled" -
	11	[995]	TEST     	2 0 1
	12	[995]	JMP      	8	; to 21
	13	[998]	GETTABLE 	3 0 -6	; "view"
	14	[998]	GETTABLE 	3 3 -7	; "footer"
	15	[998]	SELF     	3 3 -8	; "setVisible"
	16	[998]	EQ       	1 1 -9	; - 1
	17	[998]	JMP      	1	; to 19
	18	[998]	LOADBOOL 	5 0 1
	19	[998]	LOADBOOL 	5 1 0
	20	[998]	CALL     	3 3 1
	21	[1000]	GETTABLE 	3 0 -1	; "ui"
	22	[1000]	SELF     	3 3 -10	; "handleEvent"
	23	[1000]	GETUPVAL 	5 0	; Event
	24	[1000]	SELF     	5 5 -11	; "new"
	25	[1000]	LOADK    	7 -12	; "UpdatePos"
	26	[1000]	CALL     	5 3 0
	27	[1000]	CALL     	3 0 1
	28	[1001]	RETURN   	0 1

function <./frontend/apps/reader/modules/readerrolling.lua:1003,1013> (31 instructions, 124 bytes at 0x7fc0a2418eb0)
1 param, 6 slots, 2 upvalues, 3 locals, 13 constants, 0 functions
	1	[1004]	GETTABLE 	1 0 -1	; "view"
	2	[1004]	GETTABLE 	1 1 -2	; "view_mode"
	3	[1004]	EQ       	0 1 -3	; - "page"
	4	[1004]	JMP      	26	; to 31
	5	[1004]	GETTABLE 	1 0 -4	; "cre_top_bar_enabled"
	6	[1004]	TEST     	1 0 0
	7	[1004]	JMP      	23	; to 31
	8	[1005]	GETUPVAL 	1 0	; logger
	9	[1005]	GETTABLE 	1 1 -5	; "dbg"
	10	[1005]	LOADK    	2 -6	; "update battery state"
	11	[1005]	CALL     	1 2 1
	12	[1006]	GETUPVAL 	1 1	; Device
	13	[1006]	SELF     	1 1 -7	; "getPowerDevice"
	14	[1006]	CALL     	1 2 2
	15	[1008]	SELF     	2 1 -8	; "isCharging"
	16	[1008]	CALL     	2 2 2
	17	[1008]	TEST     	2 0 0
	18	[1008]	JMP      	3	; to 22
	19	[1008]	LOADK    	2 -9	; -1
	20	[1008]	TEST     	2 0 1
	21	[1008]	JMP      	2	; to 24
	22	[1008]	SELF     	2 1 -10	; "getCapacity"
	23	[1008]	CALL     	2 2 2
	24	[1009]	TEST     	2 0 0
	25	[1009]	JMP      	5	; to 31
	26	[1010]	GETTABLE 	3 0 -11	; "ui"
	27	[1010]	GETTABLE 	3 3 -12	; "document"
	28	[1010]	SELF     	3 3 -13	; "setBatteryState"
	29	[1010]	MOVE     	5 2
	30	[1010]	CALL     	3 3 1
	31	[1013]	RETURN   	0 1

function <./frontend/apps/reader/modules/readerrolling.lua:1015,1046> (75 instructions, 300 bytes at 0x7fc0a2418f70)
2+ params, 7 slots, 1 upvalue, 4 locals, 19 constants, 0 functions
	1	[1016]	NEWTABLE 	3 0 0
	2	[1016]	VARARG   	4 0
	3	[1016]	SETLIST  	3 0 1	; 1
	4	[1018]	EQ       	0 1 -1	; - "OnLoadFileStart"
	5	[1018]	JMP      	4	; to 10
	6	[1019]	SELF     	4 0 -2	; "showEngineProgress"
	7	[1019]	LOADK    	6 -3	; 0
	8	[1019]	CALL     	4 3 1
	9	[1019]	JMP      	65	; to 75
	10	[1020]	EQ       	0 1 -4	; - "OnLoadFileProgress"
	11	[1020]	JMP      	6	; to 18
	12	[1022]	SELF     	4 0 -2	; "showEngineProgress"
	13	[1022]	GETTABLE 	6 3 -5	; 1
	14	[1022]	DIV      	6 6 -6	; - 100
	15	[1022]	DIV      	6 6 -7	; - 2
	16	[1022]	CALL     	4 3 1
	17	[1022]	JMP      	57	; to 75
	18	[1023]	EQ       	0 1 -8	; - "OnNodeStylesUpdateStart"
	19	[1023]	JMP      	4	; to 24
	20	[1024]	SELF     	4 0 -2	; "showEngineProgress"
	21	[1024]	LOADK    	6 -3	; 0
	22	[1024]	CALL     	4 3 1
	23	[1024]	JMP      	51	; to 75
	24	[1025]	EQ       	0 1 -9	; - "OnNodeStylesUpdateProgress"
	25	[1025]	JMP      	6	; to 32
	26	[1027]	SELF     	4 0 -2	; "showEngineProgress"
	27	[1027]	GETTABLE 	6 3 -5	; 1
	28	[1027]	DIV      	6 6 -6	; - 100
	29	[1027]	DIV      	6 6 -7	; - 2
	30	[1027]	CALL     	4 3 1
	31	[1027]	JMP      	43	; to 75
	32	[1028]	EQ       	0 1 -10	; - "OnFormatStart"
	33	[1028]	JMP      	4	; to 38
	34	[1029]	SELF     	4 0 -2	; "showEngineProgress"
	35	[1029]	LOADK    	6 -11	; 0.5
	36	[1029]	CALL     	4 3 1
	37	[1029]	JMP      	37	; to 75
	38	[1030]	EQ       	0 1 -12	; - "OnFormatProgress"
	39	[1030]	JMP      	7	; to 47
	40	[1033]	SELF     	4 0 -2	; "showEngineProgress"
	41	[1033]	GETTABLE 	6 3 -5	; 1
	42	[1033]	DIV      	6 6 -6	; - 100
	43	[1033]	DIV      	6 6 -7	; - 2
	44	[1033]	ADD      	6 -11 6	; 0.5 -
	45	[1033]	CALL     	4 3 1
	46	[1033]	JMP      	28	; to 75
	47	[1034]	EQ       	0 1 -13	; - "OnSaveCacheFileStart"
	48	[1034]	JMP      	4	; to 53
	49	[1035]	SELF     	4 0 -2	; "showEngineProgress"
	50	[1035]	LOADK    	6 -5	; 1
	51	[1035]	CALL     	4 3 1
	52	[1035]	JMP      	22	; to 75
	53	[1036]	EQ       	0 1 -14	; - "OnSaveCacheFileProgress"
	54	[1036]	JMP      	6	; to 61
	55	[1039]	SELF     	4 0 -2	; "showEngineProgress"
	56	[1039]	GETTABLE 	6 3 -5	; 1
	57	[1039]	DIV      	6 6 -6	; - 100
	58	[1039]	SUB      	6 -5 6	; 1 -
	59	[1039]	CALL     	4 3 1
	60	[1039]	JMP      	14	; to 75
	61	[1040]	EQ       	1 1 -15	; - "OnDocumentReady"
	62	[1040]	JMP      	2	; to 65
	63	[1040]	EQ       	0 1 -16	; - "OnSaveCacheFileEnd"
	64	[1040]	JMP      	3	; to 68
	65	[1041]	SELF     	4 0 -2	; "showEngineProgress"
	66	[1041]	CALL     	4 2 1
	67	[1041]	JMP      	7	; to 75
	68	[1042]	EQ       	0 1 -17	; - "OnLoadFileError"
	69	[1042]	JMP      	5	; to 75
	70	[1043]	GETUPVAL 	4 0	; logger
	71	[1043]	GETTABLE 	4 4 -18	; "warn"
	72	[1043]	LOADK    	5 -19	; "Cre error loading file:"
	73	[1043]	GETTABLE 	6 3 -5	; 1
	74	[1043]	CALL     	4 3 1
	75	[1046]	RETURN   	0 1

function <./frontend/apps/reader/modules/readerrolling.lua:1051,1106> (92 instructions, 368 bytes at 0x7fc0a24192e0)
2 params, 13 slots, 6 upvalues, 7 locals, 31 constants, 0 functions
	1	[1052]	GETGLOBAL	2 -1	; G_reader_settings
	2	[1052]	TEST     	2 0 0
	3	[1052]	JMP      	7	; to 11
	4	[1052]	GETGLOBAL	2 -1	; G_reader_settings
	5	[1052]	SELF     	2 2 -2	; "isFalse"
	6	[1052]	LOADK    	4 -3	; "cre_show_progress"
	7	[1052]	CALL     	2 3 2
	8	[1052]	TEST     	2 0 0
	9	[1052]	JMP      	1	; to 11
	10	[1057]	RETURN   	0 1
	11	[1059]	TEST     	1 0 0
	12	[1059]	JMP      	77	; to 90
	13	[1060]	GETUPVAL 	2 0	; TimeVal
	14	[1060]	SELF     	2 2 -4	; "now"
	15	[1060]	CALL     	2 2 2
	16	[1061]	GETTABLE 	3 0 -5	; "engine_progress_update_not_before"
	17	[1061]	TEST     	3 0 0
	18	[1061]	JMP      	4	; to 23
	19	[1061]	GETTABLE 	3 0 -5	; "engine_progress_update_not_before"
	20	[1061]	LT       	0 2 3
	21	[1061]	JMP      	1	; to 23
	22	[1062]	RETURN   	0 1
	23	[1064]	GETTABLE 	3 0 -5	; "engine_progress_update_not_before"
	24	[1064]	TEST     	3 0 1
	25	[1064]	JMP      	4	; to 30
	26	[1067]	GETUPVAL 	3 1	; ENGINE_PROGRESS_INITIAL_DELAY
	27	[1067]	ADD      	3 2 3
	28	[1067]	SETTABLE 	0 -5 3	; "engine_progress_update_not_before" -
	29	[1068]	RETURN   	0 1
	30	[1072]	LOADK    	3 -6	; 0
	31	[1073]	GETUPVAL 	4 2	; Size
	32	[1073]	GETTABLE 	4 4 -7	; "margin"
	33	[1073]	GETTABLE 	4 4 -8	; "small"
	34	[1074]	GETUPVAL 	5 3	; Screen
	35	[1074]	SELF     	5 5 -9	; "getWidth"
	36	[1074]	CALL     	5 2 2
	37	[1074]	DIV      	5 5 -10	; - 3
	38	[1075]	GETUPVAL 	6 2	; Size
	39	[1075]	GETTABLE 	6 6 -11	; "line"
	40	[1075]	GETTABLE 	6 6 -12	; "progress"
	41	[1076]	GETTABLE 	7 0 -13	; "engine_progress_widget"
	42	[1076]	TEST     	7 0 0
	43	[1076]	JMP      	5	; to 49
	44	[1077]	GETTABLE 	7 0 -13	; "engine_progress_widget"
	45	[1077]	SELF     	7 7 -14	; "setPercentage"
	46	[1077]	MOVE     	9 1
	47	[1077]	CALL     	7 3 1
	48	[1077]	JMP      	22	; to 71
	49	[1079]	GETUPVAL 	7 4	; ProgressWidget
	50	[1079]	SELF     	7 7 -15	; "new"
	51	[1079]	NEWTABLE 	9 0 9
	52	[1080]	SETTABLE 	9 -16 5	; "width" -
	53	[1081]	SETTABLE 	9 -17 6	; "height" -
	54	[1082]	SETTABLE 	9 -18 1	; "percentage" -
	55	[1083]	SETTABLE 	9 -19 -6	; "margin_h" 0
	56	[1084]	SETTABLE 	9 -20 -6	; "margin_v" 0
	57	[1085]	SETTABLE 	9 -21 -6	; "radius" 0
	58	[1087]	GETUPVAL 	10 3	; Screen
	59	[1087]	SELF     	10 10 -23	; "scaleBySize"
	60	[1087]	LOADK    	12 -24	; 1
	61	[1087]	CALL     	10 3 2
	62	[1087]	SETTABLE 	9 -22 10	; "tick_width" -
	63	[1088]	NEWTABLE 	10 2 0
	64	[1088]	LOADK    	11 -24	; 1
	65	[1088]	LOADK    	12 -26	; 2
	66	[1088]	SETLIST  	10 2 1	; 1
	67	[1088]	SETTABLE 	9 -25 10	; "ticks" -
	68	[1089]	SETTABLE 	9 -27 -26	; "last" 2
	69	[1079]	CALL     	7 3 2
	70	[1090]	SETTABLE 	0 -13 7	; "engine_progress_widget" -
	71	[1095]	GETTABLE 	7 0 -13	; "engine_progress_widget"
	72	[1095]	SELF     	7 7 -28	; "paintTo"
	73	[1095]	GETUPVAL 	9 3	; Screen
	74	[1095]	GETTABLE 	9 9 -29	; "bb"
	75	[1095]	MOVE     	10 3
	76	[1095]	MOVE     	11 4
	77	[1095]	CALL     	7 5 1
	78	[1096]	GETUPVAL 	7 3	; Screen
	79	[1096]	GETTABLE 	7 7 -30	; "refreshFast"
	80	[1096]	GETUPVAL 	8 3	; Screen
	81	[1096]	MOVE     	9 3
	82	[1096]	MOVE     	10 4
	83	[1096]	MOVE     	11 5
	84	[1096]	MOVE     	12 6
	85	[1096]	CALL     	7 6 1
	86	[1097]	GETUPVAL 	7 5	; ENGINE_PROGRESS_UPDATE_DELAY
	87	[1097]	ADD      	7 2 7
	88	[1097]	SETTABLE 	0 -5 7	; "engine_progress_update_not_before" -
	89	[1097]	JMP      	2	; to 92
	90	[1100]	SETTABLE 	0 -13 -31	; "engine_progress_widget" nil
	91	[1101]	SETTABLE 	0 -5 -31	; "engine_progress_update_not_before" nil
	92	[1106]	RETURN   	0 1

function <./frontend/apps/reader/modules/readerrolling.lua:1108,1318> (154 instructions, 616 bytes at 0x7fc0a240c240)
1 param, 23 slots, 5 upvalues, 18 locals, 32 constants, 6 functions
	1	[1109]	GETTABLE 	1 0 -1	; "ui"
	2	[1109]	GETTABLE 	1 1 -2	; "document"
	3	[1109]	TEST     	1 0 0
	4	[1109]	JMP      	7	; to 12
	5	[1109]	GETTABLE 	1 0 -1	; "ui"
	6	[1109]	GETTABLE 	1 1 -2	; "document"
	7	[1109]	SELF     	1 1 -3	; "isBuiltDomStale"
	8	[1109]	CALL     	1 2 2
	9	[1109]	TEST     	1 0 0
	10	[1109]	JMP      	1	; to 12
	11	[1113]	RETURN   	0 1
	12	[1143]	CLOSURE  	1 0	; 0x7fc0a2417fc0
	13	[1143]	MOVE     	0 0
	14	[1146]	NEWTABLE 	2 0 0
	15	[1147]	NEWTABLE 	3 0 0
	16	[1148]	LOADK    	4 -4	; 0
	17	[1149]	LOADK    	5 -4	; 0
	18	[1150]	LOADK    	6 -4	; 0
	19	[1151]	LOADK    	7 -4	; 0
	20	[1174]	CLOSURE  	8 1	; 0x7fc0a2419c70
	21	[1174]	MOVE     	0 2
	22	[1174]	MOVE     	0 4
	23	[1174]	MOVE     	0 0
	24	[1174]	MOVE     	0 5
	25	[1174]	MOVE     	0 6
	26	[1174]	MOVE     	0 7
	27	[1174]	MOVE     	0 3
	28	[1196]	CLOSURE  	9 2	; 0x7fc0a2410b30
	29	[1196]	MOVE     	0 2
	30	[1240]	CLOSURE  	10 3	; 0x7fc0a2416800
	31	[1240]	GETUPVAL 	0 0	; logger
	32	[1240]	MOVE     	0 0
	33	[1240]	MOVE     	0 1
	34	[1240]	MOVE     	0 9
	35	[1240]	GETUPVAL 	0 1	; T
	36	[1240]	MOVE     	0 5
	37	[1240]	MOVE     	0 6
	38	[1240]	MOVE     	0 7
	39	[1243]	MOVE     	11 1
	40	[1243]	MOVE     	12 8
	41	[1243]	CALL     	11 2 1
	42	[1244]	GETUPVAL 	11 0	; logger
	43	[1244]	GETTABLE 	11 11 -5	; "info"
	44	[1244]	GETUPVAL 	12 1	; T
	45	[1244]	LOADK    	13 -6	; "%1 xpointers checked: %2 found (%3 changed) - %4 lost"
	46	[1245]	MOVE     	14 4
	47	[1245]	MOVE     	15 5
	48	[1245]	MOVE     	16 6
	49	[1245]	MOVE     	17 7
	50	[1244]	CALL     	12 6 0
	51	[1244]	CALL     	11 0 1
	52	[1246]	LT       	0 -4 7	; 0 -
	53	[1246]	JMP      	17	; to 71
	54	[1247]	GETUPVAL 	11 0	; logger
	55	[1247]	GETTABLE 	11 11 -7	; "warn"
	56	[1247]	LOADK    	12 -8	; "Lost xpointers:"
	57	[1247]	CALL     	11 2 1
	58	[1248]	GETGLOBAL	11 -9	; pairs
	59	[1248]	MOVE     	12 3
	60	[1248]	CALL     	11 2 4
	61	[1248]	JMP      	7	; to 69
	62	[1249]	GETUPVAL 	16 0	; logger
	63	[1249]	GETTABLE 	16 16 -7	; "warn"
	64	[1249]	LOADK    	17 -10	; "  "
	65	[1249]	MOVE     	18 14
	66	[1249]	LOADK    	19 -11	; ":"
	67	[1249]	MOVE     	20 15
	68	[1249]	CALL     	16 5 1
	69	[1248]	TFORLOOP 	11 2
	70	[1249]	JMP      	-9	; to 62
	71	[1253]	GETUPVAL 	11 2	; _
	72	[1259]	LOADK    	12 -12	; "This book was first opened, and has been handled since, by an older version of the rendering code.\nBookmarks and highlights can be upgraded to the latest version of the code.\n\n%1\n\nProceed with this upgrade and reload the book?"
	73	[1253]	CALL     	11 2 2
	74	[1260]	NEWTABLE 	12 0 0
	75	[1261]	EQ       	0 7 -4	; - 0
	76	[1261]	JMP      	8	; to 85
	77	[1262]	GETGLOBAL	13 -13	; table
	78	[1262]	GETTABLE 	13 13 -14	; "insert"
	79	[1262]	MOVE     	14 12
	80	[1262]	GETUPVAL 	15 2	; _
	81	[1262]	LOADK    	16 -15	; "All your bookmarks and highlights are valid and will be available after the migration."
	82	[1262]	CALL     	15 2 0
	83	[1262]	CALL     	13 0 1
	84	[1262]	JMP      	11	; to 96
	85	[1264]	GETGLOBAL	13 -13	; table
	86	[1264]	GETTABLE 	13 13 -14	; "insert"
	87	[1264]	MOVE     	14 12
	88	[1264]	GETUPVAL 	15 1	; T
	89	[1264]	GETUPVAL 	16 2	; _
	90	[1265]	LOADK    	17 -16	; "Note that %1 (out of %2) xpaths from your bookmarks and highlights aren't currently found in the book, and may have been lost. You might want to toggle Rendering mode between 'legacy' and 'flat', and re-open this book, and see if they are found again, before proceeding."
	91	[1264]	CALL     	16 2 2
	92	[1266]	MOVE     	17 7
	93	[1266]	MOVE     	18 4
	94	[1264]	CALL     	15 4 0
	95	[1264]	CALL     	13 0 1
	96	[1268]	LT       	0 -4 6	; 0 -
	97	[1268]	JMP      	11	; to 109
	98	[1269]	GETGLOBAL	13 -13	; table
	99	[1269]	GETTABLE 	13 13 -14	; "insert"
	100	[1269]	MOVE     	14 12
	101	[1269]	GETUPVAL 	15 1	; T
	102	[1269]	GETUPVAL 	16 2	; _
	103	[1270]	LOADK    	17 -17	; "Note that %1 (out of %2) xpaths from your bookmarks and highlights have been normalized, and may not work on previous KOReader versions (if you're synchronizing your reading between multiple devices, you'll need to update KOReader on all of them)."
	104	[1269]	CALL     	16 2 2
	105	[1271]	MOVE     	17 6
	106	[1271]	MOVE     	18 4
	107	[1269]	CALL     	15 4 0
	108	[1269]	CALL     	13 0 1
	109	[1273]	GETUPVAL 	13 1	; T
	110	[1273]	MOVE     	14 11
	111	[1273]	GETGLOBAL	15 -13	; table
	112	[1273]	GETTABLE 	15 15 -18	; "concat"
	113	[1273]	MOVE     	16 12
	114	[1273]	LOADK    	17 -19	; "\n\n"
	115	[1273]	CALL     	15 3 0
	116	[1273]	CALL     	13 0 2
	117	[1273]	MOVE     	11 13
	118	[1275]	GETUPVAL 	13 3	; UIManager
	119	[1275]	SELF     	13 13 -20	; "show"
	120	[1275]	GETUPVAL 	15 4	; ConfirmBox
	121	[1275]	SELF     	15 15 -21	; "new"
	122	[1275]	NEWTABLE 	17 0 7
	123	[1276]	SETTABLE 	17 -22 11	; "text" -
	124	[1280]	SETTABLE 	17 -23 -24	; "dismissable" false
	125	[1281]	NEWTABLE 	18 1 0
	126	[1281]	NEWTABLE 	19 1 0
	127	[1281]	NEWTABLE 	20 0 1
	128	[1284]	GETUPVAL 	21 2	; _
	129	[1284]	LOADK    	22 -26	; "Not now"
	130	[1284]	CALL     	21 2 2
	131	[1284]	SETTABLE 	20 -22 21	; "text" -
	132	[1286]	SETLIST  	19 1 1	; 1
	133	[1286]	SETLIST  	18 1 1	; 1
	134	[1286]	SETTABLE 	17 -25 18	; "other_buttons" -
	135	[1287]	GETUPVAL 	18 2	; _
	136	[1287]	LOADK    	19 -28	; "Not for this book"
	137	[1287]	CALL     	18 2 2
	138	[1287]	SETTABLE 	17 -27 18	; "cancel_text" -
	139	[1290]	CLOSURE  	18 4	; 0x7fc0a241a500
	140	[1290]	MOVE     	0 0
	141	[1290]	SETTABLE 	17 -29 18	; "cancel_callback" -
	142	[1291]	GETUPVAL 	18 2	; _
	143	[1291]	LOADK    	19 -31	; "Upgrade now"
	144	[1291]	CALL     	18 2 2
	145	[1291]	SETTABLE 	17 -30 18	; "ok_text" -
	146	[1316]	CLOSURE  	18 5	; 0x7fc0a241a7f0
	147	[1316]	GETUPVAL 	0 3	; UIManager
	148	[1316]	MOVE     	0 0
	149	[1316]	GETUPVAL 	0 2	; _
	150	[1316]	MOVE     	0 10
	151	[1316]	SETTABLE 	17 -32 18	; "ok_callback" -
	152	[1275]	CALL     	15 3 0
	153	[1275]	CALL     	13 0 1
	154	[1318]	RETURN   	0 1

function <./frontend/apps/reader/modules/readerrolling.lua:1118,1143> (101 instructions, 404 bytes at 0x7fc0a2417fc0)
1 param, 21 slots, 1 upvalue, 28 locals, 16 constants, 0 functions
	1	[1120]	MOVE     	1 0
	2	[1120]	GETUPVAL 	2 0	; self
	3	[1120]	LOADK    	3 -1	; "xpointer"
	4	[1120]	LOADK    	4 -2	; "last position in book"
	5	[1120]	CALL     	1 4 1
	6	[1122]	GETUPVAL 	1 0	; self
	7	[1122]	GETTABLE 	1 1 -3	; "ui"
	8	[1122]	GETTABLE 	1 1 -4	; "bookmark"
	9	[1122]	TEST     	1 0 0
	10	[1122]	JMP      	41	; to 52
	11	[1122]	GETUPVAL 	1 0	; self
	12	[1122]	GETTABLE 	1 1 -3	; "ui"
	13	[1122]	GETTABLE 	1 1 -4	; "bookmark"
	14	[1122]	GETTABLE 	1 1 -5	; "bookmarks"
	15	[1122]	TEST     	1 0 0
	16	[1122]	JMP      	35	; to 52
	17	[1122]	GETUPVAL 	1 0	; self
	18	[1122]	GETTABLE 	1 1 -3	; "ui"
	19	[1122]	GETTABLE 	1 1 -4	; "bookmark"
	20	[1122]	GETTABLE 	1 1 -5	; "bookmarks"
	21	[1122]	LEN      	1 1
	22	[1122]	LT       	0 -6 1	; 0 -
	23	[1122]	JMP      	28	; to 52
	24	[1123]	NEWTABLE 	1 3 0
	25	[1123]	LOADK    	2 -7	; "page"
	26	[1123]	LOADK    	3 -8	; "pos0"
	27	[1123]	LOADK    	4 -9	; "pos1"
	28	[1123]	SETLIST  	1 3 1	; 1
	29	[1124]	GETGLOBAL	2 -10	; ipairs
	30	[1124]	GETUPVAL 	3 0	; self
	31	[1124]	GETTABLE 	3 3 -3	; "ui"
	32	[1124]	GETTABLE 	3 3 -4	; "bookmark"
	33	[1124]	GETTABLE 	3 3 -5	; "bookmarks"
	34	[1124]	CALL     	2 2 4
	35	[1124]	JMP      	14	; to 50
	36	[1125]	GETGLOBAL	7 -10	; ipairs
	37	[1125]	MOVE     	8 1
	38	[1125]	CALL     	7 2 4
	39	[1125]	JMP      	8	; to 48
	40	[1126]	MOVE     	12 0
	41	[1126]	MOVE     	13 6
	42	[1126]	MOVE     	14 11
	43	[1126]	GETTABLE 	15 6 -11	; "notes"
	44	[1126]	TEST     	15 0 1
	45	[1126]	JMP      	1	; to 47
	46	[1126]	LOADK    	15 -4	; "bookmark"
	47	[1126]	CALL     	12 4 1
	48	[1125]	TFORLOOP 	7 2
	49	[1126]	JMP      	-10	; to 40
	50	[1124]	TFORLOOP 	2 2
	51	[1127]	JMP      	-16	; to 36
	52	[1131]	GETUPVAL 	1 0	; self
	53	[1131]	GETTABLE 	1 1 -12	; "view"
	54	[1131]	GETTABLE 	1 1 -13	; "highlight"
	55	[1131]	TEST     	1 0 0
	56	[1131]	JMP      	44	; to 101
	57	[1131]	GETUPVAL 	1 0	; self
	58	[1131]	GETTABLE 	1 1 -12	; "view"
	59	[1131]	GETTABLE 	1 1 -13	; "highlight"
	60	[1131]	GETTABLE 	1 1 -14	; "saved"
	61	[1131]	TEST     	1 0 0
	62	[1131]	JMP      	38	; to 101
	63	[1132]	NEWTABLE 	1 2 0
	64	[1132]	LOADK    	2 -8	; "pos0"
	65	[1132]	LOADK    	3 -9	; "pos1"
	66	[1132]	SETLIST  	1 2 1	; 1
	67	[1133]	GETGLOBAL	2 -15	; pairs
	68	[1133]	GETUPVAL 	3 0	; self
	69	[1133]	GETTABLE 	3 3 -12	; "view"
	70	[1133]	GETTABLE 	3 3 -13	; "highlight"
	71	[1133]	GETTABLE 	3 3 -14	; "saved"
	72	[1133]	CALL     	2 2 4
	73	[1133]	JMP      	25	; to 99
	74	[1134]	TEST     	6 0 0
	75	[1134]	JMP      	23	; to 99
	76	[1134]	LEN      	7 6
	77	[1134]	LT       	0 -6 7	; 0 -
	78	[1134]	JMP      	20	; to 99
	79	[1135]	GETGLOBAL	7 -10	; ipairs
	80	[1135]	MOVE     	8 6
	81	[1135]	CALL     	7 2 4
	82	[1135]	JMP      	14	; to 97
	83	[1136]	GETGLOBAL	12 -10	; ipairs
	84	[1136]	MOVE     	13 1
	85	[1136]	CALL     	12 2 4
	86	[1136]	JMP      	8	; to 95
	87	[1137]	MOVE     	17 0
	88	[1137]	MOVE     	18 11
	89	[1137]	MOVE     	19 16
	90	[1137]	GETTABLE 	20 11 -16	; "text"
	91	[1137]	TEST     	20 0 1
	92	[1137]	JMP      	1	; to 94
	93	[1137]	LOADK    	20 -13	; "highlight"
	94	[1137]	CALL     	17 4 1
	95	[1136]	TFORLOOP 	12 2
	96	[1137]	JMP      	-10	; to 87
	97	[1135]	TFORLOOP 	7 2
	98	[1138]	JMP      	-16	; to 83
	99	[1133]	TFORLOOP 	2 2
	100	[1140]	JMP      	-27	; to 74
	101	[1143]	RETURN   	0 1

function <./frontend/apps/reader/modules/readerrolling.lua:1154,1174> (37 instructions, 148 bytes at 0x7fc0a2419c70)
3 params, 7 slots, 7 upvalues, 5 locals, 5 constants, 0 functions
	1	[1155]	GETTABLE 	3 0 1
	2	[1156]	TEST     	3 0 1
	3	[1156]	JMP      	1	; to 5
	4	[1157]	RETURN   	0 1
	5	[1159]	GETUPVAL 	4 0	; normalized_xpointers
	6	[1159]	GETTABLE 	4 4 3
	7	[1159]	EQ       	1 4 -1	; - nil
	8	[1159]	JMP      	1	; to 10
	9	[1160]	RETURN   	0 1
	10	[1162]	GETUPVAL 	4 1	; nb_xpointers
	11	[1162]	ADD      	4 4 -2	; - 1
	12	[1162]	SETUPVAL 	4 1	; nb_xpointers
	13	[1163]	GETUPVAL 	4 2	; self
	14	[1163]	GETTABLE 	4 4 -3	; "ui"
	15	[1163]	GETTABLE 	4 4 -4	; "document"
	16	[1163]	SELF     	4 4 -5	; "getNormalizedXPointer"
	17	[1163]	MOVE     	6 3
	18	[1163]	CALL     	4 3 2
	19	[1164]	GETUPVAL 	5 0	; normalized_xpointers
	20	[1164]	SETTABLE 	5 3 4
	21	[1165]	TEST     	4 0 0
	22	[1165]	JMP      	9	; to 32
	23	[1166]	GETUPVAL 	5 3	; nb_xpointers_found
	24	[1166]	ADD      	5 5 -2	; - 1
	25	[1166]	SETUPVAL 	5 3	; nb_xpointers_found
	26	[1167]	EQ       	1 4 3
	27	[1167]	JMP      	9	; to 37
	28	[1168]	GETUPVAL 	5 4	; nb_xpointers_changed
	29	[1168]	ADD      	5 5 -2	; - 1
	30	[1168]	SETUPVAL 	5 4	; nb_xpointers_changed
	31	[1169]	JMP      	5	; to 37
	32	[1171]	GETUPVAL 	5 5	; nb_xpointers_lost
	33	[1171]	ADD      	5 5 -2	; - 1
	34	[1171]	SETUPVAL 	5 5	; nb_xpointers_lost
	35	[1172]	GETUPVAL 	5 6	; lost_xpointer_info
	36	[1172]	SETTABLE 	5 3 2
	37	[1174]	RETURN   	0 1

function <./frontend/apps/reader/modules/readerrolling.lua:1177,1196> (14 instructions, 56 bytes at 0x7fc0a2410b30)
3 params, 5 slots, 1 upvalue, 5 locals, 3 constants, 0 functions
	1	[1178]	GETTABLE 	3 0 1
	2	[1179]	TEST     	3 0 1
	3	[1179]	JMP      	1	; to 5
	4	[1180]	RETURN   	0 1
	5	[1182]	GETUPVAL 	4 0	; normalized_xpointers
	6	[1182]	GETTABLE 	4 4 3
	7	[1183]	TEST     	4 0 0
	8	[1183]	JMP      	2	; to 11
	9	[1184]	SETTABLE 	0 1 4
	10	[1184]	JMP      	3	; to 14
	11	[1192]	EQ       	1 1 -1	; - "xpointer"
	12	[1192]	JMP      	1	; to 14
	13	[1193]	SETTABLE 	0 -2 -3	; "not_found_not_migrated" true
	14	[1196]	RETURN   	0 1

function <./frontend/apps/reader/modules/readerrolling.lua:1199,1240> (105 instructions, 420 bytes at 0x7fc0a2416800)
0 params, 7 slots, 8 upvalues, 5 locals, 27 constants, 0 functions
	1	[1200]	GETUPVAL 	0 0	; logger
	2	[1200]	GETTABLE 	0 0 -1	; "info"
	3	[1200]	LOADK    	1 -2	; "Upgrading book to latest DOM version:"
	4	[1200]	CALL     	0 2 1
	5	[1203]	GETUPVAL 	0 1	; self
	6	[1203]	GETTABLE 	0 0 -3	; "ui"
	7	[1203]	GETTABLE 	0 0 -4	; "doc_settings"
	8	[1203]	SELF     	0 0 -5	; "readSetting"
	9	[1203]	LOADK    	2 -6	; "cre_dom_version"
	10	[1203]	CALL     	0 3 2
	11	[1203]	TEST     	0 0 1
	12	[1203]	JMP      	1	; to 14
	13	[1203]	LOADK    	0 -7	; "unknown"
	14	[1204]	GETUPVAL 	1 1	; self
	15	[1204]	GETTABLE 	1 1 -3	; "ui"
	16	[1204]	GETTABLE 	1 1 -4	; "doc_settings"
	17	[1204]	GETTABLE 	1 1 -8	; "filepath"
	18	[1204]	TEST     	1 0 0
	19	[1204]	JMP      	28	; to 48
	20	[1205]	GETUPVAL 	1 1	; self
	21	[1205]	GETTABLE 	1 1 -3	; "ui"
	22	[1205]	GETTABLE 	1 1 -4	; "doc_settings"
	23	[1205]	GETTABLE 	1 1 -8	; "filepath"
	24	[1205]	LOADK    	2 -9	; ".old_dom"
	25	[1205]	GETGLOBAL	3 -10	; tostring
	26	[1205]	MOVE     	4 0
	27	[1205]	CALL     	3 2 2
	28	[1205]	CONCAT   	1 1 3
	29	[1206]	GETGLOBAL	2 -11	; lfs
	30	[1206]	GETTABLE 	2 2 -12	; "attributes"
	31	[1206]	MOVE     	3 1
	32	[1206]	CALL     	2 2 2
	33	[1206]	TEST     	2 0 1
	34	[1206]	JMP      	13	; to 48
	35	[1207]	GETGLOBAL	2 -13	; os
	36	[1207]	GETTABLE 	2 2 -14	; "rename"
	37	[1207]	GETUPVAL 	3 1	; self
	38	[1207]	GETTABLE 	3 3 -3	; "ui"
	39	[1207]	GETTABLE 	3 3 -4	; "doc_settings"
	40	[1207]	GETTABLE 	3 3 -8	; "filepath"
	41	[1207]	MOVE     	4 1
	42	[1207]	CALL     	2 3 1
	43	[1208]	GETUPVAL 	2 0	; logger
	44	[1208]	GETTABLE 	2 2 -1	; "info"
	45	[1208]	LOADK    	3 -15	; "  previous docsetting file saved as"
	46	[1208]	MOVE     	4 1
	47	[1208]	CALL     	2 3 1
	48	[1213]	GETUPVAL 	1 2	; applyFuncToXPointersSlots
	49	[1213]	GETUPVAL 	2 3	; migrateXPointer
	50	[1213]	CALL     	1 2 1
	51	[1214]	GETUPVAL 	1 0	; logger
	52	[1214]	GETTABLE 	1 1 -1	; "info"
	53	[1214]	GETUPVAL 	2 4	; T
	54	[1214]	LOADK    	3 -16	; "  xpointers updated: %1 unchanged, %2 modified, %3 not found let as-is"
	55	[1215]	GETUPVAL 	4 5	; nb_xpointers_found
	56	[1215]	GETUPVAL 	5 6	; nb_xpointers_changed
	57	[1215]	SUB      	4 4 5
	58	[1215]	GETUPVAL 	5 6	; nb_xpointers_changed
	59	[1215]	GETUPVAL 	6 7	; nb_xpointers_lost
	60	[1214]	CALL     	2 5 0
	61	[1214]	CALL     	1 0 1
	62	[1218]	GETUPVAL 	1 1	; self
	63	[1218]	GETTABLE 	1 1 -3	; "ui"
	64	[1218]	GETTABLE 	1 1 -17	; "document"
	65	[1218]	SELF     	1 1 -18	; "getLatestDomVersion"
	66	[1218]	CALL     	1 2 2
	67	[1219]	GETUPVAL 	2 1	; self
	68	[1219]	GETTABLE 	2 2 -3	; "ui"
	69	[1219]	GETTABLE 	2 2 -4	; "doc_settings"
	70	[1219]	SELF     	2 2 -19	; "saveSetting"
	71	[1219]	LOADK    	4 -6	; "cre_dom_version"
	72	[1219]	MOVE     	5 1
	73	[1219]	CALL     	2 4 1
	74	[1220]	GETUPVAL 	2 0	; logger
	75	[1220]	GETTABLE 	2 2 -1	; "info"
	76	[1220]	LOADK    	3 -20	; "  cre_dom_version updated to"
	77	[1220]	MOVE     	4 1
	78	[1220]	CALL     	2 3 1
	79	[1225]	GETGLOBAL	2 -21	; G_reader_settings
	80	[1225]	SELF     	2 2 -5	; "readSetting"
	81	[1225]	LOADK    	4 -22	; "copt_block_rendering_mode"
	82	[1225]	CALL     	2 3 2
	83	[1226]	EQ       	1 2 -23	; - 0
	84	[1226]	JMP      	20	; to 105
	85	[1227]	TEST     	2 0 1
	86	[1227]	JMP      	1	; to 88
	87	[1228]	LOADK    	2 -24	; 3
	88	[1231]	GETUPVAL 	3 1	; self
	89	[1231]	GETTABLE 	3 3 -3	; "ui"
	90	[1231]	GETTABLE 	3 3 -17	; "document"
	91	[1231]	GETTABLE 	3 3 -25	; "configurable"
	92	[1231]	GETTABLE 	3 3 -26	; "block_rendering_mode"
	93	[1232]	EQ       	0 3 -23	; - 0
	94	[1232]	JMP      	10	; to 105
	95	[1233]	GETUPVAL 	4 1	; self
	96	[1233]	GETTABLE 	4 4 -3	; "ui"
	97	[1233]	GETTABLE 	4 4 -17	; "document"
	98	[1233]	GETTABLE 	4 4 -25	; "configurable"
	99	[1233]	SETTABLE 	4 -26 2	; "block_rendering_mode" -
	100	[1234]	GETUPVAL 	4 0	; logger
	101	[1234]	GETTABLE 	4 4 -1	; "info"
	102	[1234]	LOADK    	5 -27	; "  block_rendering_mode switched to"
	103	[1234]	MOVE     	6 2
	104	[1234]	CALL     	4 3 1
	105	[1240]	RETURN   	0 1

function <./frontend/apps/reader/modules/readerrolling.lua:1288,1290> (8 instructions, 32 bytes at 0x7fc0a241a500)
0 params, 4 slots, 1 upvalue, 0 locals, 4 constants, 0 functions
	1	[1289]	GETUPVAL 	0 0	; self
	2	[1289]	GETTABLE 	0 0 -1	; "ui"
	3	[1289]	GETTABLE 	0 0 -2	; "doc_settings"
	4	[1289]	SELF     	0 0 -3	; "saveSetting"
	5	[1289]	LOADK    	2 -4	; "cre_keep_old_dom_version"
	6	[1289]	LOADBOOL 	3 1 0
	7	[1289]	CALL     	0 4 1
	8	[1290]	RETURN   	0 1

function <./frontend/apps/reader/modules/readerrolling.lua:1292,1316> (10 instructions, 40 bytes at 0x7fc0a241a7f0)
0 params, 4 slots, 4 upvalues, 0 locals, 2 constants, 1 function
	1	[1294]	GETUPVAL 	0 0	; UIManager
	2	[1294]	SELF     	0 0 -1	; "scheduleIn"
	3	[1294]	LOADK    	2 -2	; 0.5
	4	[1315]	CLOSURE  	3 0	; 0x7fc0a241b0f0
	5	[1315]	GETUPVAL 	0 1	; self
	6	[1315]	GETUPVAL 	0 2	; _
	7	[1315]	GETUPVAL 	0 0	; UIManager
	8	[1315]	GETUPVAL 	0 3	; upgradeToLatestDOMVersion
	9	[1294]	CALL     	0 4 1
	10	[1316]	RETURN   	0 1

function <./frontend/apps/reader/modules/readerrolling.lua:1294,1315> (30 instructions, 120 bytes at 0x7fc0a241b0f0)
0 params, 6 slots, 4 upvalues, 2 locals, 10 constants, 1 function
	1	[1296]	GETUPVAL 	0 0	; self
	2	[1296]	GETTABLE 	0 0 -1	; "ui"
	3	[1296]	GETTABLE 	0 0 -2	; "document"
	4	[1296]	TEST     	0 0 0
	5	[1296]	JMP      	24	; to 30
	6	[1301]	GETGLOBAL	0 -3	; require
	7	[1301]	LOADK    	1 -4	; "ui/widget/infomessage"
	8	[1301]	CALL     	0 2 2
	9	[1302]	SELF     	1 0 -5	; "new"
	10	[1302]	NEWTABLE 	3 0 1
	11	[1303]	GETUPVAL 	4 1	; _
	12	[1303]	LOADK    	5 -7	; "Upgrading and reloading book\226\128\166"
	13	[1303]	CALL     	4 2 2
	14	[1303]	SETTABLE 	3 -6 4	; "text" -
	15	[1302]	CALL     	1 3 2
	16	[1305]	GETUPVAL 	2 2	; UIManager
	17	[1305]	SELF     	2 2 -8	; "show"
	18	[1305]	MOVE     	4 1
	19	[1305]	CALL     	2 3 1
	20	[1307]	GETUPVAL 	2 2	; UIManager
	21	[1307]	SELF     	2 2 -9	; "scheduleIn"
	22	[1307]	LOADK    	4 -10	; 2
	23	[1313]	CLOSURE  	5 0	; 0x7fc0a241b210
	24	[1313]	GETUPVAL 	0 2	; UIManager
	25	[1313]	MOVE     	0 1
	26	[1313]	GETUPVAL 	0 0	; self
	27	[1313]	GETUPVAL 	0 3	; upgradeToLatestDOMVersion
	28	[1307]	CALL     	2 4 1
	29	[1313]	CLOSE    	0
	30	[1315]	RETURN   	0 1

function <./frontend/apps/reader/modules/readerrolling.lua:1307,1313> (16 instructions, 64 bytes at 0x7fc0a241b210)
0 params, 3 slots, 4 upvalues, 0 locals, 4 constants, 0 functions
	1	[1308]	GETUPVAL 	0 0	; UIManager
	2	[1308]	SELF     	0 0 -1	; "close"
	3	[1308]	GETUPVAL 	2 1	; infomsg
	4	[1308]	CALL     	0 3 1
	5	[1309]	GETUPVAL 	0 2	; self
	6	[1309]	GETTABLE 	0 0 -2	; "ui"
	7	[1309]	GETTABLE 	0 0 -3	; "document"
	8	[1309]	TEST     	0 0 0
	9	[1309]	JMP      	6	; to 16
	10	[1310]	GETUPVAL 	0 3	; upgradeToLatestDOMVersion
	11	[1310]	CALL     	0 1 1
	12	[1311]	GETUPVAL 	0 2	; self
	13	[1311]	GETTABLE 	0 0 -2	; "ui"
	14	[1311]	SELF     	0 0 -4	; "reloadDocument"
	15	[1311]	CALL     	0 2 1
	16	[1313]	RETURN   	0 1
