
main <./frontend/apps/reader/modules/readercoptlistener.lua:0,0> (16 instructions, 64 bytes at 0x7f83a6c06900)
0+ params, 5 slots, 0 upvalues, 3 locals, 6 constants, 2 functions
	1	[1]	GETGLOBAL	0 -1	; require
	2	[1]	LOADK    	1 -2	; "ui/event"
	3	[1]	CALL     	0 2 2
	4	[2]	GETGLOBAL	1 -1	; require
	5	[2]	LOADK    	2 -3	; "ui/widget/eventlistener"
	6	[2]	CALL     	1 2 2
	7	[4]	SELF     	2 1 -4	; "new"
	8	[4]	NEWTABLE 	4 0 0
	9	[4]	CALL     	2 3 2
	10	[21]	CLOSURE  	3 0	; 0x7f83a6c06fc0
	11	[21]	MOVE     	0 0
	12	[6]	SETTABLE 	2 -5 3	; "onReadSettings" -
	13	[25]	CLOSURE  	3 1	; 0x7f83a6c07170
	14	[23]	SETTABLE 	2 -6 3	; "onSetFontSize" -
	15	[27]	RETURN   	2 2
	16	[27]	RETURN   	0 1

function <./frontend/apps/reader/modules/readercoptlistener.lua:6,21> (46 instructions, 184 bytes at 0x7f83a6c06fc0)
2 params, 11 slots, 1 upvalue, 4 locals, 11 constants, 2 functions
	1	[7]	SELF     	2 1 -1	; "readSetting"
	2	[7]	LOADK    	4 -2	; "copt_view_mode"
	3	[7]	CALL     	2 3 2
	4	[7]	TEST     	2 0 1
	5	[7]	JMP      	4	; to 10
	6	[8]	GETGLOBAL	2 -3	; G_reader_settings
	7	[8]	SELF     	2 2 -1	; "readSetting"
	8	[8]	LOADK    	4 -2	; "copt_view_mode"
	9	[8]	CALL     	2 3 2
	10	[9]	EQ       	0 2 -4	; - 0
	11	[9]	JMP      	6	; to 18
	12	[10]	GETTABLE 	3 0 -5	; "ui"
	13	[10]	SELF     	3 3 -6	; "registerPostReadyCallback"
	14	[12]	CLOSURE  	5 0	; 0x7f83a6c071f0
	15	[12]	MOVE     	0 0
	16	[10]	CALL     	3 3 1
	17	[12]	JMP      	7	; to 25
	18	[13]	EQ       	0 2 -7	; - 1
	19	[13]	JMP      	5	; to 25
	20	[14]	GETTABLE 	3 0 -5	; "ui"
	21	[14]	SELF     	3 3 -6	; "registerPostReadyCallback"
	22	[16]	CLOSURE  	5 1	; 0x7f83a6c07910
	23	[16]	MOVE     	0 0
	24	[14]	CALL     	3 3 1
	25	[19]	SELF     	3 1 -1	; "readSetting"
	26	[19]	LOADK    	5 -8	; "copt_status_line"
	27	[19]	CALL     	3 3 2
	28	[19]	TEST     	3 0 1
	29	[19]	JMP      	7	; to 37
	30	[19]	GETGLOBAL	3 -3	; G_reader_settings
	31	[19]	SELF     	3 3 -1	; "readSetting"
	32	[19]	LOADK    	5 -8	; "copt_status_line"
	33	[19]	CALL     	3 3 2
	34	[19]	TEST     	3 0 1
	35	[19]	JMP      	1	; to 37
	36	[19]	LOADK    	3 -7	; 1
	37	[20]	GETTABLE 	4 0 -5	; "ui"
	38	[20]	SELF     	4 4 -9	; "handleEvent"
	39	[20]	GETUPVAL 	6 0	; Event
	40	[20]	SELF     	6 6 -10	; "new"
	41	[20]	LOADK    	8 -11	; "SetStatusLine"
	42	[20]	MOVE     	9 3
	43	[20]	LOADBOOL 	10 1 0
	44	[20]	CALL     	6 5 0
	45	[20]	CALL     	4 0 1
	46	[21]	RETURN   	0 1

function <./frontend/apps/reader/modules/readercoptlistener.lua:10,12> (6 instructions, 24 bytes at 0x7f83a6c071f0)
0 params, 3 slots, 1 upvalue, 0 locals, 3 constants, 0 functions
	1	[11]	GETUPVAL 	0 0	; self
	2	[11]	GETTABLE 	0 0 -1	; "view"
	3	[11]	SELF     	0 0 -2	; "onSetViewMode"
	4	[11]	LOADK    	2 -3	; "page"
	5	[11]	CALL     	0 3 1
	6	[12]	RETURN   	0 1

function <./frontend/apps/reader/modules/readercoptlistener.lua:14,16> (6 instructions, 24 bytes at 0x7f83a6c07910)
0 params, 3 slots, 1 upvalue, 0 locals, 3 constants, 0 functions
	1	[15]	GETUPVAL 	0 0	; self
	2	[15]	GETTABLE 	0 0 -1	; "view"
	3	[15]	SELF     	0 0 -2	; "onSetViewMode"
	4	[15]	LOADK    	2 -3	; "scroll"
	5	[15]	CALL     	0 3 1
	6	[16]	RETURN   	0 1

function <./frontend/apps/reader/modules/readercoptlistener.lua:23,25> (4 instructions, 16 bytes at 0x7f83a6c07170)
2 params, 3 slots, 0 upvalues, 2 locals, 3 constants, 0 functions
	1	[24]	GETTABLE 	2 0 -1	; "document"
	2	[24]	GETTABLE 	2 2 -2	; "configurable"
	3	[24]	SETTABLE 	2 -3 1	; "font_size" -
	4	[25]	RETURN   	0 1
