
main <./spec/unit/readertoc_spec.lua:0,0> (5 instructions, 20 bytes at 0x7fcd9e4068c0)
0+ params, 3 slots, 0 upvalues, 0 locals, 2 constants, 1 function
	1	[1]	GETGLOBAL	0 -1	; describe
	2	[1]	LOADK    	1 -2	; "Readertoc module"
	3	[101]	CLOSURE  	2 0	; 0x7fcd9e406b60
	4	[1]	CALL     	0 3 1
	5	[101]	RETURN   	0 1

function <./spec/unit/readertoc_spec.lua:1,101> (53 instructions, 212 bytes at 0x7fcd9e406b60)
0 params, 10 slots, 0 upvalues, 7 locals, 11 constants, 9 functions
	1	[5]	GETGLOBAL	7 -1	; setup
	2	[18]	CLOSURE  	8 0	; 0x7fcd9e406de0
	3	[18]	MOVE     	0 0
	4	[18]	MOVE     	0 1
	5	[18]	MOVE     	0 2
	6	[18]	MOVE     	0 3
	7	[18]	MOVE     	0 4
	8	[5]	CALL     	7 2 1
	9	[20]	GETGLOBAL	7 -2	; it
	10	[20]	LOADK    	8 -3	; "should get max toc depth"
	11	[23]	CLOSURE  	9 1	; 0x7fcd9e406740
	12	[23]	MOVE     	0 5
	13	[23]	MOVE     	0 4
	14	[20]	CALL     	7 3 1
	15	[24]	GETGLOBAL	7 -2	; it
	16	[24]	LOADK    	8 -4	; "should get toc title from page"
	17	[30]	CLOSURE  	9 2	; 0x7fcd9e407a30
	18	[30]	MOVE     	0 6
	19	[30]	MOVE     	0 4
	20	[30]	MOVE     	0 2
	21	[24]	CALL     	7 3 1
	22	[31]	GETGLOBAL	7 -5	; describe
	23	[31]	LOADK    	8 -6	; "getTocTicks API"
	24	[58]	CLOSURE  	9 3	; 0x7fcd9e4073c0
	25	[58]	MOVE     	0 4
	26	[58]	MOVE     	0 5
	27	[31]	CALL     	7 3 1
	28	[59]	GETGLOBAL	7 -2	; it
	29	[59]	LOADK    	8 -7	; "should get page of next chapter"
	30	[63]	CLOSURE  	9 4	; 0x7fcd9e409100
	31	[63]	MOVE     	0 4
	32	[59]	CALL     	7 3 1
	33	[64]	GETGLOBAL	7 -2	; it
	34	[64]	LOADK    	8 -8	; "should get page of previous chapter"
	35	[68]	CLOSURE  	9 5	; 0x7fcd9e407c60
	36	[68]	MOVE     	0 4
	37	[64]	CALL     	7 3 1
	38	[69]	GETGLOBAL	7 -2	; it
	39	[69]	LOADK    	8 -9	; "should get page left of chapter"
	40	[73]	CLOSURE  	9 6	; 0x7fcd9e408120
	41	[73]	MOVE     	0 4
	42	[69]	CALL     	7 3 1
	43	[74]	GETGLOBAL	7 -2	; it
	44	[74]	LOADK    	8 -10	; "should get page done of chapter"
	45	[78]	CLOSURE  	9 7	; 0x7fcd9e409e70
	46	[78]	MOVE     	0 4
	47	[74]	CALL     	7 3 1
	48	[79]	GETGLOBAL	7 -5	; describe
	49	[79]	LOADK    	8 -11	; "collasible TOC"
	50	[100]	CLOSURE  	9 8	; 0x7fcd9e4089a0
	51	[100]	MOVE     	0 4
	52	[79]	CALL     	7 3 1
	53	[101]	RETURN   	0 1

function <./spec/unit/readertoc_spec.lua:5,18> (35 instructions, 140 bytes at 0x7fcd9e406de0)
0 params, 7 slots, 5 upvalues, 1 local, 13 constants, 0 functions
	1	[6]	GETGLOBAL	0 -1	; require
	2	[6]	LOADK    	1 -2	; "commonrequire"
	3	[6]	CALL     	0 2 1
	4	[7]	GETGLOBAL	0 -1	; require
	5	[7]	LOADK    	1 -3	; "document/documentregistry"
	6	[7]	CALL     	0 2 2
	7	[7]	SETUPVAL 	0 0	; DocumentRegistry
	8	[8]	GETGLOBAL	0 -1	; require
	9	[8]	LOADK    	1 -4	; "apps/reader/readerui"
	10	[8]	CALL     	0 2 2
	11	[8]	SETUPVAL 	0 1	; ReaderUI
	12	[9]	GETGLOBAL	0 -1	; require
	13	[9]	LOADK    	1 -5	; "dbg"
	14	[9]	CALL     	0 2 2
	15	[9]	SETUPVAL 	0 2	; DEBUG
	16	[11]	LOADK    	0 -6	; "spec/front/unit/data/juliet.epub"
	17	[12]	GETUPVAL 	1 1	; ReaderUI
	18	[12]	SELF     	1 1 -7	; "new"
	19	[12]	NEWTABLE 	3 0 1
	20	[13]	GETUPVAL 	4 0	; DocumentRegistry
	21	[13]	SELF     	4 4 -9	; "openDocument"
	22	[13]	MOVE     	6 0
	23	[13]	CALL     	4 3 2
	24	[13]	SETTABLE 	3 -8 4	; "document" -
	25	[12]	CALL     	1 3 2
	26	[14]	SETUPVAL 	1 3	; readerui
	27	[16]	GETUPVAL 	1 3	; readerui
	28	[16]	GETTABLE 	1 1 -10	; "rolling"
	29	[16]	SELF     	1 1 -11	; "onGotoPage"
	30	[16]	LOADK    	3 -12	; 0
	31	[16]	CALL     	1 3 1
	32	[17]	GETUPVAL 	1 3	; readerui
	33	[17]	GETTABLE 	1 1 -13	; "toc"
	34	[17]	SETUPVAL 	1 4	; toc
	35	[18]	RETURN   	0 1

function <./spec/unit/readertoc_spec.lua:20,23> (11 instructions, 44 bytes at 0x7fcd9e406740)
0 params, 3 slots, 2 upvalues, 0 locals, 5 constants, 0 functions
	1	[21]	GETUPVAL 	0 1	; toc
	2	[21]	SELF     	0 0 -1	; "getMaxDepth"
	3	[21]	CALL     	0 2 2
	4	[21]	SETUPVAL 	0 0	; toc_max_depth
	5	[22]	GETGLOBAL	0 -2	; assert
	6	[22]	GETTABLE 	0 0 -3	; "are"
	7	[22]	GETTABLE 	0 0 -4	; "same"
	8	[22]	LOADK    	1 -5	; 2
	9	[22]	GETUPVAL 	2 0	; toc_max_depth
	10	[22]	CALL     	0 3 1
	11	[23]	RETURN   	0 1

function <./spec/unit/readertoc_spec.lua:24,30> (28 instructions, 112 bytes at 0x7fcd9e407a30)
0 params, 3 slots, 3 upvalues, 0 locals, 9 constants, 0 functions
	1	[25]	GETUPVAL 	0 1	; toc
	2	[25]	SELF     	0 0 -1	; "getTocTitleByPage"
	3	[25]	LOADK    	2 -2	; 60
	4	[25]	CALL     	0 3 2
	5	[25]	SETUPVAL 	0 0	; title
	6	[26]	GETUPVAL 	0 2	; DEBUG
	7	[26]	LOADK    	1 -3	; "toc"
	8	[26]	GETUPVAL 	2 1	; toc
	9	[26]	GETTABLE 	2 2 -3	; "toc"
	10	[26]	CALL     	0 3 1
	11	[27]	GETGLOBAL	0 -4	; assert
	12	[27]	GETTABLE 	0 0 -5	; "is"
	13	[27]	GETTABLE 	0 0 -6	; "equal"
	14	[27]	LOADK    	1 -7	; "SCENE V. A hall in Capulet's house."
	15	[27]	GETUPVAL 	2 0	; title
	16	[27]	CALL     	0 3 1
	17	[28]	GETUPVAL 	0 1	; toc
	18	[28]	SELF     	0 0 -1	; "getTocTitleByPage"
	19	[28]	LOADK    	2 -8	; 187
	20	[28]	CALL     	0 3 2
	21	[28]	SETUPVAL 	0 0	; title
	22	[29]	GETGLOBAL	0 -4	; assert
	23	[29]	GETTABLE 	0 0 -5	; "is"
	24	[29]	GETTABLE 	0 0 -6	; "equal"
	25	[29]	LOADK    	1 -9	; "SCENE I. Friar Laurence's cell."
	26	[29]	GETUPVAL 	2 0	; title
	27	[29]	CALL     	0 3 1
	28	[30]	RETURN   	0 1

function <./spec/unit/readertoc_spec.lua:31,58> (35 instructions, 140 bytes at 0x7fcd9e4073c0)
0 params, 7 slots, 2 upvalues, 4 locals, 6 constants, 5 functions
	1	[33]	GETGLOBAL	1 -1	; it
	2	[33]	LOADK    	2 -2	; "should get ticks of level 0"
	3	[37]	CLOSURE  	3 0	; 0x7fcd9e4084f0
	4	[37]	MOVE     	0 0
	5	[37]	GETUPVAL 	0 0	; toc
	6	[33]	CALL     	1 3 1
	7	[38]	LOADNIL  	1 1
	8	[39]	GETGLOBAL	2 -1	; it
	9	[39]	LOADK    	3 -3	; "should get ticks of level 1"
	10	[42]	CLOSURE  	4 1	; 0x7fcd9e408a40
	11	[42]	MOVE     	0 1
	12	[42]	GETUPVAL 	0 0	; toc
	13	[39]	CALL     	2 3 1
	14	[43]	LOADNIL  	2 2
	15	[44]	GETGLOBAL	3 -1	; it
	16	[44]	LOADK    	4 -4	; "should get ticks of level 2"
	17	[47]	CLOSURE  	5 2	; 0x7fcd9e4083b0
	18	[47]	MOVE     	0 2
	19	[47]	GETUPVAL 	0 0	; toc
	20	[44]	CALL     	3 3 1
	21	[48]	LOADNIL  	3 3
	22	[49]	GETGLOBAL	4 -1	; it
	23	[49]	LOADK    	5 -5	; "should get ticks of level -1"
	24	[52]	CLOSURE  	6 3	; 0x7fcd9e409560
	25	[52]	MOVE     	0 3
	26	[52]	GETUPVAL 	0 0	; toc
	27	[49]	CALL     	4 3 1
	28	[53]	GETGLOBAL	4 -1	; it
	29	[53]	LOADK    	5 -6	; "should get the same ticks of level -1 and level 2"
	30	[57]	CLOSURE  	6 4	; 0x7fcd9e4096b0
	31	[57]	GETUPVAL 	0 1	; toc_max_depth
	32	[57]	MOVE     	0 2
	33	[57]	MOVE     	0 3
	34	[53]	CALL     	4 3 1
	35	[58]	RETURN   	0 1

function <./spec/unit/readertoc_spec.lua:33,37> (13 instructions, 52 bytes at 0x7fcd9e4084f0)
0 params, 3 slots, 2 upvalues, 0 locals, 6 constants, 0 functions
	1	[34]	GETUPVAL 	0 1	; toc
	2	[34]	SELF     	0 0 -1	; "getTocTicks"
	3	[34]	LOADK    	2 -2	; 0
	4	[34]	CALL     	0 3 2
	5	[34]	SETUPVAL 	0 0	; ticks_level_0
	6	[36]	GETGLOBAL	0 -3	; assert
	7	[36]	GETTABLE 	0 0 -4	; "are"
	8	[36]	GETTABLE 	0 0 -5	; "same"
	9	[36]	LOADK    	1 -6	; 28
	10	[36]	GETUPVAL 	2 0	; ticks_level_0
	11	[36]	LEN      	2 2
	12	[36]	CALL     	0 3 1
	13	[37]	RETURN   	0 1

function <./spec/unit/readertoc_spec.lua:39,42> (13 instructions, 52 bytes at 0x7fcd9e408a40)
0 params, 3 slots, 2 upvalues, 0 locals, 6 constants, 0 functions
	1	[40]	GETUPVAL 	0 1	; toc
	2	[40]	SELF     	0 0 -1	; "getTocTicks"
	3	[40]	LOADK    	2 -2	; 1
	4	[40]	CALL     	0 3 2
	5	[40]	SETUPVAL 	0 0	; ticks_level_1
	6	[41]	GETGLOBAL	0 -3	; assert
	7	[41]	GETTABLE 	0 0 -4	; "are"
	8	[41]	GETTABLE 	0 0 -5	; "same"
	9	[41]	LOADK    	1 -6	; 7
	10	[41]	GETUPVAL 	2 0	; ticks_level_1
	11	[41]	LEN      	2 2
	12	[41]	CALL     	0 3 1
	13	[42]	RETURN   	0 1

function <./spec/unit/readertoc_spec.lua:44,47> (13 instructions, 52 bytes at 0x7fcd9e4083b0)
0 params, 3 slots, 2 upvalues, 0 locals, 6 constants, 0 functions
	1	[45]	GETUPVAL 	0 1	; toc
	2	[45]	SELF     	0 0 -1	; "getTocTicks"
	3	[45]	LOADK    	2 -2	; 2
	4	[45]	CALL     	0 3 2
	5	[45]	SETUPVAL 	0 0	; ticks_level_2
	6	[46]	GETGLOBAL	0 -3	; assert
	7	[46]	GETTABLE 	0 0 -4	; "are"
	8	[46]	GETTABLE 	0 0 -5	; "same"
	9	[46]	LOADK    	1 -6	; 26
	10	[46]	GETUPVAL 	2 0	; ticks_level_2
	11	[46]	LEN      	2 2
	12	[46]	CALL     	0 3 1
	13	[47]	RETURN   	0 1

function <./spec/unit/readertoc_spec.lua:49,52> (13 instructions, 52 bytes at 0x7fcd9e409560)
0 params, 3 slots, 2 upvalues, 0 locals, 6 constants, 0 functions
	1	[50]	GETUPVAL 	0 1	; toc
	2	[50]	SELF     	0 0 -1	; "getTocTicks"
	3	[50]	LOADK    	2 -2	; -1
	4	[50]	CALL     	0 3 2
	5	[50]	SETUPVAL 	0 0	; ticks_level_m1
	6	[51]	GETGLOBAL	0 -3	; assert
	7	[51]	GETTABLE 	0 0 -4	; "are"
	8	[51]	GETTABLE 	0 0 -5	; "same"
	9	[51]	LOADK    	1 -6	; 26
	10	[51]	GETUPVAL 	2 0	; ticks_level_m1
	11	[51]	LEN      	2 2
	12	[51]	CALL     	0 3 1
	13	[52]	RETURN   	0 1

function <./spec/unit/readertoc_spec.lua:53,57> (10 instructions, 40 bytes at 0x7fcd9e4096b0)
0 params, 3 slots, 3 upvalues, 0 locals, 4 constants, 0 functions
	1	[54]	GETUPVAL 	0 0	; toc_max_depth
	2	[54]	EQ       	0 0 -1	; - 2
	3	[54]	JMP      	6	; to 10
	4	[55]	GETGLOBAL	0 -2	; assert
	5	[55]	GETTABLE 	0 0 -3	; "are"
	6	[55]	GETTABLE 	0 0 -4	; "same"
	7	[55]	GETUPVAL 	1 1	; ticks_level_2
	8	[55]	GETUPVAL 	2 2	; ticks_level_m1
	9	[55]	CALL     	0 3 1
	10	[57]	RETURN   	0 1

function <./spec/unit/readertoc_spec.lua:59,63> (35 instructions, 140 bytes at 0x7fcd9e409100)
0 params, 6 slots, 1 upvalue, 0 locals, 9 constants, 0 functions
	1	[60]	GETGLOBAL	0 -1	; assert
	2	[60]	GETTABLE 	0 0 -2	; "truthy"
	3	[60]	GETUPVAL 	1 0	; toc
	4	[60]	SELF     	1 1 -3	; "getNextChapter"
	5	[60]	LOADK    	3 -4	; 10
	6	[60]	LOADK    	4 -5	; 0
	7	[60]	CALL     	1 4 2
	8	[60]	LT       	1 -4 1	; 10 -
	9	[60]	JMP      	1	; to 11
	10	[60]	LOADBOOL 	1 0 1
	11	[60]	LOADBOOL 	1 1 0
	12	[60]	CALL     	0 2 1
	13	[61]	GETGLOBAL	0 -1	; assert
	14	[61]	GETTABLE 	0 0 -2	; "truthy"
	15	[61]	GETUPVAL 	1 0	; toc
	16	[61]	SELF     	1 1 -3	; "getNextChapter"
	17	[61]	LOADK    	3 -6	; 100
	18	[61]	LOADK    	4 -5	; 0
	19	[61]	CALL     	1 4 2
	20	[61]	LT       	1 -6 1	; 100 -
	21	[61]	JMP      	1	; to 23
	22	[61]	LOADBOOL 	1 0 1
	23	[61]	LOADBOOL 	1 1 0
	24	[61]	CALL     	0 2 1
	25	[62]	GETGLOBAL	0 -1	; assert
	26	[62]	GETTABLE 	0 0 -7	; "are"
	27	[62]	GETTABLE 	0 0 -8	; "same"
	28	[62]	LOADNIL  	1 1
	29	[62]	GETUPVAL 	2 0	; toc
	30	[62]	SELF     	2 2 -3	; "getNextChapter"
	31	[62]	LOADK    	4 -9	; 290
	32	[62]	LOADK    	5 -5	; 0
	33	[62]	CALL     	2 4 0
	34	[62]	CALL     	0 0 1
	35	[63]	RETURN   	0 1

function <./spec/unit/readertoc_spec.lua:64,68> (37 instructions, 148 bytes at 0x7fcd9e407c60)
0 params, 5 slots, 1 upvalue, 0 locals, 7 constants, 0 functions
	1	[65]	GETGLOBAL	0 -1	; assert
	2	[65]	GETTABLE 	0 0 -2	; "truthy"
	3	[65]	GETUPVAL 	1 0	; toc
	4	[65]	SELF     	1 1 -3	; "getPreviousChapter"
	5	[65]	LOADK    	3 -4	; 10
	6	[65]	LOADK    	4 -5	; 0
	7	[65]	CALL     	1 4 2
	8	[65]	LT       	1 1 -4	; - 10
	9	[65]	JMP      	1	; to 11
	10	[65]	LOADBOOL 	1 0 1
	11	[65]	LOADBOOL 	1 1 0
	12	[65]	CALL     	0 2 1
	13	[66]	GETGLOBAL	0 -1	; assert
	14	[66]	GETTABLE 	0 0 -2	; "truthy"
	15	[66]	GETUPVAL 	1 0	; toc
	16	[66]	SELF     	1 1 -3	; "getPreviousChapter"
	17	[66]	LOADK    	3 -6	; 100
	18	[66]	LOADK    	4 -5	; 0
	19	[66]	CALL     	1 4 2
	20	[66]	LT       	1 1 -6	; - 100
	21	[66]	JMP      	1	; to 23
	22	[66]	LOADBOOL 	1 0 1
	23	[66]	LOADBOOL 	1 1 0
	24	[66]	CALL     	0 2 1
	25	[67]	GETGLOBAL	0 -1	; assert
	26	[67]	GETTABLE 	0 0 -2	; "truthy"
	27	[67]	GETUPVAL 	1 0	; toc
	28	[67]	SELF     	1 1 -3	; "getPreviousChapter"
	29	[67]	LOADK    	3 -7	; 200
	30	[67]	LOADK    	4 -5	; 0
	31	[67]	CALL     	1 4 2
	32	[67]	LT       	1 1 -7	; - 200
	33	[67]	JMP      	1	; to 35
	34	[67]	LOADBOOL 	1 0 1
	35	[67]	LOADBOOL 	1 1 0
	36	[67]	CALL     	0 2 1
	37	[68]	RETURN   	0 1

function <./spec/unit/readertoc_spec.lua:69,73> (35 instructions, 140 bytes at 0x7fcd9e408120)
0 params, 6 slots, 1 upvalue, 0 locals, 9 constants, 0 functions
	1	[70]	GETGLOBAL	0 -1	; assert
	2	[70]	GETTABLE 	0 0 -2	; "truthy"
	3	[70]	GETUPVAL 	1 0	; toc
	4	[70]	SELF     	1 1 -3	; "getChapterPagesLeft"
	5	[70]	LOADK    	3 -4	; 10
	6	[70]	LOADK    	4 -5	; 0
	7	[70]	CALL     	1 4 2
	8	[70]	LT       	1 -4 1	; 10 -
	9	[70]	JMP      	1	; to 11
	10	[70]	LOADBOOL 	1 0 1
	11	[70]	LOADBOOL 	1 1 0
	12	[70]	CALL     	0 2 1
	13	[71]	GETGLOBAL	0 -1	; assert
	14	[71]	GETTABLE 	0 0 -2	; "truthy"
	15	[71]	GETUPVAL 	1 0	; toc
	16	[71]	SELF     	1 1 -3	; "getChapterPagesLeft"
	17	[71]	LOADK    	3 -6	; 95
	18	[71]	LOADK    	4 -5	; 0
	19	[71]	CALL     	1 4 2
	20	[71]	LT       	1 -4 1	; 10 -
	21	[71]	JMP      	1	; to 23
	22	[71]	LOADBOOL 	1 0 1
	23	[71]	LOADBOOL 	1 1 0
	24	[71]	CALL     	0 2 1
	25	[72]	GETGLOBAL	0 -1	; assert
	26	[72]	GETTABLE 	0 0 -7	; "are"
	27	[72]	GETTABLE 	0 0 -8	; "same"
	28	[72]	LOADNIL  	1 1
	29	[72]	GETUPVAL 	2 0	; toc
	30	[72]	SELF     	2 2 -3	; "getChapterPagesLeft"
	31	[72]	LOADK    	4 -9	; 290
	32	[72]	LOADK    	5 -5	; 0
	33	[72]	CALL     	2 4 0
	34	[72]	CALL     	0 0 1
	35	[73]	RETURN   	0 1

function <./spec/unit/readertoc_spec.lua:74,78> (37 instructions, 148 bytes at 0x7fcd9e409e70)
0 params, 5 slots, 1 upvalue, 0 locals, 9 constants, 0 functions
	1	[75]	GETGLOBAL	0 -1	; assert
	2	[75]	GETTABLE 	0 0 -2	; "truthy"
	3	[75]	GETUPVAL 	1 0	; toc
	4	[75]	SELF     	1 1 -3	; "getChapterPagesDone"
	5	[75]	LOADK    	3 -4	; 11
	6	[75]	LOADK    	4 -5	; 0
	7	[75]	CALL     	1 4 2
	8	[75]	LT       	1 1 -6	; - 5
	9	[75]	JMP      	1	; to 11
	10	[75]	LOADBOOL 	1 0 1
	11	[75]	LOADBOOL 	1 1 0
	12	[75]	CALL     	0 2 1
	13	[76]	GETGLOBAL	0 -1	; assert
	14	[76]	GETTABLE 	0 0 -2	; "truthy"
	15	[76]	GETUPVAL 	1 0	; toc
	16	[76]	SELF     	1 1 -3	; "getChapterPagesDone"
	17	[76]	LOADK    	3 -7	; 88
	18	[76]	LOADK    	4 -5	; 0
	19	[76]	CALL     	1 4 2
	20	[76]	LT       	1 1 -6	; - 5
	21	[76]	JMP      	1	; to 23
	22	[76]	LOADBOOL 	1 0 1
	23	[76]	LOADBOOL 	1 1 0
	24	[76]	CALL     	0 2 1
	25	[77]	GETGLOBAL	0 -1	; assert
	26	[77]	GETTABLE 	0 0 -2	; "truthy"
	27	[77]	GETUPVAL 	1 0	; toc
	28	[77]	SELF     	1 1 -3	; "getChapterPagesDone"
	29	[77]	LOADK    	3 -8	; 290
	30	[77]	LOADK    	4 -5	; 0
	31	[77]	CALL     	1 4 2
	32	[77]	LT       	1 -9 1	; 10 -
	33	[77]	JMP      	1	; to 35
	34	[77]	LOADBOOL 	1 0 1
	35	[77]	LOADBOOL 	1 1 0
	36	[77]	CALL     	0 2 1
	37	[78]	RETURN   	0 1

function <./spec/unit/readertoc_spec.lua:79,100> (21 instructions, 84 bytes at 0x7fcd9e4089a0)
0 params, 3 slots, 1 upvalue, 0 locals, 5 constants, 4 functions
	1	[80]	GETGLOBAL	0 -1	; it
	2	[80]	LOADK    	1 -2	; "should collapse the secondary toc nodes by default"
	3	[83]	CLOSURE  	2 0	; 0x7fcd9e407100
	4	[83]	GETUPVAL 	0 0	; toc
	5	[80]	CALL     	0 3 1
	6	[84]	GETGLOBAL	0 -1	; it
	7	[84]	LOADK    	1 -3	; "should not expand toc nodes that have no child nodes"
	8	[87]	CLOSURE  	2 1	; 0x7fcd9e40ad30
	9	[87]	GETUPVAL 	0 0	; toc
	10	[84]	CALL     	0 3 1
	11	[88]	GETGLOBAL	0 -1	; it
	12	[88]	LOADK    	1 -4	; "should expand toc nodes that have child nodes"
	13	[93]	CLOSURE  	2 2	; 0x7fcd9e40aff0
	14	[93]	GETUPVAL 	0 0	; toc
	15	[88]	CALL     	0 3 1
	16	[94]	GETGLOBAL	0 -1	; it
	17	[94]	LOADK    	1 -5	; "should collapse toc nodes that have been expanded"
	18	[99]	CLOSURE  	2 3	; 0x7fcd9e40ba70
	19	[99]	GETUPVAL 	0 0	; toc
	20	[94]	CALL     	0 3 1
	21	[100]	RETURN   	0 1

function <./spec/unit/readertoc_spec.lua:80,83> (12 instructions, 48 bytes at 0x7fcd9e407100)
0 params, 3 slots, 1 upvalue, 0 locals, 6 constants, 0 functions
	1	[81]	GETUPVAL 	0 0	; toc
	2	[81]	SELF     	0 0 -1	; "onShowToc"
	3	[81]	CALL     	0 2 1
	4	[82]	GETGLOBAL	0 -2	; assert
	5	[82]	GETTABLE 	0 0 -3	; "are"
	6	[82]	GETTABLE 	0 0 -4	; "same"
	7	[82]	LOADK    	1 -5	; 7
	8	[82]	GETUPVAL 	2 0	; toc
	9	[82]	GETTABLE 	2 2 -6	; "collapsed_toc"
	10	[82]	LEN      	2 2
	11	[82]	CALL     	0 3 1
	12	[83]	RETURN   	0 1

function <./spec/unit/readertoc_spec.lua:84,87> (13 instructions, 52 bytes at 0x7fcd9e40ad30)
0 params, 3 slots, 1 upvalue, 0 locals, 7 constants, 0 functions
	1	[85]	GETUPVAL 	0 0	; toc
	2	[85]	SELF     	0 0 -1	; "expandToc"
	3	[85]	LOADK    	2 -2	; 2
	4	[85]	CALL     	0 3 1
	5	[86]	GETGLOBAL	0 -3	; assert
	6	[86]	GETTABLE 	0 0 -4	; "are"
	7	[86]	GETTABLE 	0 0 -5	; "same"
	8	[86]	LOADK    	1 -6	; 7
	9	[86]	GETUPVAL 	2 0	; toc
	10	[86]	GETTABLE 	2 2 -7	; "collapsed_toc"
	11	[86]	LEN      	2 2
	12	[86]	CALL     	0 3 1
	13	[87]	RETURN   	0 1

function <./spec/unit/readertoc_spec.lua:88,93> (25 instructions, 100 bytes at 0x7fcd9e40aff0)
0 params, 3 slots, 1 upvalue, 0 locals, 8 constants, 0 functions
	1	[89]	GETUPVAL 	0 0	; toc
	2	[89]	SELF     	0 0 -1	; "expandToc"
	3	[89]	LOADK    	2 -2	; 3
	4	[89]	CALL     	0 3 1
	5	[90]	GETGLOBAL	0 -3	; assert
	6	[90]	GETTABLE 	0 0 -4	; "are"
	7	[90]	GETTABLE 	0 0 -5	; "same"
	8	[90]	LOADK    	1 -6	; 13
	9	[90]	GETUPVAL 	2 0	; toc
	10	[90]	GETTABLE 	2 2 -7	; "collapsed_toc"
	11	[90]	LEN      	2 2
	12	[90]	CALL     	0 3 1
	13	[91]	GETUPVAL 	0 0	; toc
	14	[91]	SELF     	0 0 -1	; "expandToc"
	15	[91]	LOADK    	2 -8	; 18
	16	[91]	CALL     	0 3 1
	17	[92]	GETGLOBAL	0 -3	; assert
	18	[92]	GETTABLE 	0 0 -4	; "are"
	19	[92]	GETTABLE 	0 0 -5	; "same"
	20	[92]	LOADK    	1 -8	; 18
	21	[92]	GETUPVAL 	2 0	; toc
	22	[92]	GETTABLE 	2 2 -7	; "collapsed_toc"
	23	[92]	LEN      	2 2
	24	[92]	CALL     	0 3 1
	25	[93]	RETURN   	0 1

function <./spec/unit/readertoc_spec.lua:94,99> (25 instructions, 100 bytes at 0x7fcd9e40ba70)
0 params, 3 slots, 1 upvalue, 0 locals, 9 constants, 0 functions
	1	[95]	GETUPVAL 	0 0	; toc
	2	[95]	SELF     	0 0 -1	; "collapseToc"
	3	[95]	LOADK    	2 -2	; 3
	4	[95]	CALL     	0 3 1
	5	[96]	GETGLOBAL	0 -3	; assert
	6	[96]	GETTABLE 	0 0 -4	; "are"
	7	[96]	GETTABLE 	0 0 -5	; "same"
	8	[96]	LOADK    	1 -6	; 12
	9	[96]	GETUPVAL 	2 0	; toc
	10	[96]	GETTABLE 	2 2 -7	; "collapsed_toc"
	11	[96]	LEN      	2 2
	12	[96]	CALL     	0 3 1
	13	[97]	GETUPVAL 	0 0	; toc
	14	[97]	SELF     	0 0 -1	; "collapseToc"
	15	[97]	LOADK    	2 -8	; 18
	16	[97]	CALL     	0 3 1
	17	[98]	GETGLOBAL	0 -3	; assert
	18	[98]	GETTABLE 	0 0 -4	; "are"
	19	[98]	GETTABLE 	0 0 -5	; "same"
	20	[98]	LOADK    	1 -9	; 7
	21	[98]	GETUPVAL 	2 0	; toc
	22	[98]	GETTABLE 	2 2 -7	; "collapsed_toc"
	23	[98]	LEN      	2 2
	24	[98]	CALL     	0 3 1
	25	[99]	RETURN   	0 1
