-- BYTECODE -- readerdictionary_spec.lua:4-10
0001    GGET     0   0      ; "require"
0002    KSTR     1   1      ; "commonrequire"
0003    CALL     0   1   2
0004    GGET     0   0      ; "require"
0005    KSTR     1   2      ; "document/documentregistry"
0006    CALL     0   2   2
0007    USETV    0   0      ; DocumentRegistry
0008    GGET     0   0      ; "require"
0009    KSTR     1   3      ; "apps/reader/readerui"
0010    CALL     0   2   2
0011    USETV    1   0      ; ReaderUI
0012    GGET     0   0      ; "require"
0013    KSTR     1   4      ; "ui/uimanager"
0014    CALL     0   2   2
0015    USETV    2   0      ; UIManager
0016    GGET     0   0      ; "require"
0017    KSTR     1   5      ; "device"
0018    CALL     0   2   2
0019    TGETS    0   0   6  ; "screen"
0020    USETV    3   0      ; Screen
0021    RET0     0   1

-- BYTECODE -- readerdictionary_spec.lua:13-20
0001    KSTR     0   0      ; "spec/front/unit/data/leaves.epub"
0002    UGET     1   1      ; ReaderUI
0003    MOV      2   1
0004    TGETS    1   1   1  ; "new"
0005    TDUP     3   3
0006    UGET     4   2      ; DocumentRegistry
0007    MOV      5   4
0008    TGETS    4   4   2  ; "openDocument"
0009    MOV      6   0
0010    CALL     4   2   3
0011    TSETS    4   3   4  ; "document"
0012    CALL     1   2   3
0013    USETV    0   1      ; readerui
0014    UGET     1   0      ; readerui
0015    TGETS    1   1   5  ; "rolling"
0016    USETV    3   1      ; rolling
0017    UGET     1   0      ; readerui
0018    TGETS    1   1   6  ; "dictionary"
0019    USETV    4   1      ; dictionary
0020    RET0     0   1

-- BYTECODE -- readerdictionary_spec.lua:27-30
0001    UGET     0   0      ; UIManager
0002    MOV      1   0
0003    TGETS    0   0   0  ; "close"
0004    UGET     2   1      ; dictionary
0005    TGETS    2   2   1  ; "dict_window"
0006    CALL     0   1   3
0007    UGET     0   0      ; UIManager
0008    MOV      1   0
0009    TGETS    0   0   0  ; "close"
0010    UGET     2   2      ; readerui
0011    CALL     0   1   3
0012    RET0     0   1

-- BYTECODE -- readerdictionary_spec.lua:21-33
0001    KSTR     0   0      ; "screenshots/reader_dictionary.png"
0002    UGET     1   0      ; UIManager
0003    MOV      2   1
0004    TGETS    1   1   1  ; "quit"
0005    CALL     1   1   2
0006    UGET     1   0      ; UIManager
0007    MOV      2   1
0008    TGETS    1   1   2  ; "show"
0009    UGET     3   1      ; readerui
0010    CALL     1   1   3
0011    UGET     1   2      ; rolling
0012    MOV      2   1
0013    TGETS    1   1   3  ; "onGotoPage"
0014    KSHORT   3 100
0015    CALL     1   1   3
0016    UGET     1   3      ; dictionary
0017    MOV      2   1
0018    TGETS    1   1   4  ; "onLookupWord"
0019    KSTR     3   5      ; "test"
0020    CALL     1   1   3
0021    UGET     1   0      ; UIManager
0022    MOV      2   1
0023    TGETS    1   1   6  ; "scheduleIn"
0024    KSHORT   3   1
0025    FNEW     4   7      ; readerdictionary_spec.lua:27
0026    CALL     1   1   4
0027    UGET     1   0      ; UIManager
0028    MOV      2   1
0029    TGETS    1   1   8  ; "run"
0030    CALL     1   1   2
0031    UGET     1   4      ; Screen
0032    MOV      2   1
0033    TGETS    1   1   9  ; "shot"
0034    MOV      3   0
0035    CALL     1   1   3
0036    RET0     0   1

-- BYTECODE -- readerdictionary_spec.lua:1-34
0001    KNIL     0   3
0002    GGET     4   0      ; "setup"
0003    FNEW     5   1      ; readerdictionary_spec.lua:4
0004    CALL     4   1   2
0005    KNIL     4   6
0006    GGET     7   0      ; "setup"
0007    FNEW     8   2      ; readerdictionary_spec.lua:13
0008    CALL     7   1   2
0009    GGET     7   3      ; "it"
0010    KSTR     8   4      ; "should show quick lookup window"
0011    FNEW     9   5      ; readerdictionary_spec.lua:21
0012    CALL     7   1   3
0013    UCLO     0 => 0014
0014 => RET0     0   1

-- BYTECODE -- readerdictionary_spec.lua:0-35
0001    GGET     0   0      ; "describe"
0002    KSTR     1   1      ; "Readerdictionary module"
0003    FNEW     2   2      ; readerdictionary_spec.lua:1
0004    CALL     0   1   3
0005    RET0     0   1

