
main <./frontend/ui/elements/reader_menu_order.lua:0,0> (210 instructions, 840 bytes at 0x7f9f154068f0)
0+ params, 19 slots, 0 upvalues, 2 locals, 126 constants, 0 functions
	1	[1]	GETGLOBAL	0 -1	; require
	2	[1]	LOADK    	1 -2	; "device"
	3	[1]	CALL     	0 2 2
	4	[3]	NEWTABLE 	1 0 16
	5	[4]	NEWTABLE 	2 7 0
	6	[5]	LOADK    	3 -4	; "navi"
	7	[6]	LOADK    	4 -5	; "typeset"
	8	[7]	LOADK    	5 -6	; "setting"
	9	[8]	LOADK    	6 -7	; "tools"
	10	[9]	LOADK    	7 -8	; "search"
	11	[10]	LOADK    	8 -9	; "filemanager"
	12	[12]	LOADK    	9 -10	; "main"
	13	[12]	SETLIST  	2 7 1	; 1
	14	[12]	SETTABLE 	1 -3 2	; "KOMenu:menu_buttons" -
	15	[13]	NEWTABLE 	2 11 0
	16	[14]	LOADK    	3 -11	; "table_of_contents"
	17	[15]	LOADK    	4 -12	; "bookmarks"
	18	[16]	LOADK    	5 -13	; "toggle_bookmark"
	19	[17]	LOADK    	6 -14	; "bookmark_browsing_mode"
	20	[18]	LOADK    	7 -15	; "page_map"
	21	[19]	LOADK    	8 -16	; "----------------------------"
	22	[20]	LOADK    	9 -17	; "go_to"
	23	[21]	LOADK    	10 -18	; "skim_to"
	24	[22]	LOADK    	11 -19	; "autoturn"
	25	[23]	LOADK    	12 -16	; "----------------------------"
	26	[25]	LOADK    	13 -20	; "go_to_previous_location"
	27	[25]	SETLIST  	2 11 1	; 1
	28	[25]	SETTABLE 	1 -4 2	; "navi" -
	29	[26]	NEWTABLE 	2 13 0
	30	[27]	LOADK    	3 -21	; "set_render_style"
	31	[28]	LOADK    	4 -22	; "style_tweaks"
	32	[29]	LOADK    	5 -16	; "----------------------------"
	33	[30]	LOADK    	6 -23	; "change_font"
	34	[31]	LOADK    	7 -24	; "typography"
	35	[32]	LOADK    	8 -25	; "floating_punctuation"
	36	[33]	LOADK    	9 -16	; "----------------------------"
	37	[34]	LOADK    	10 -26	; "switch_zoom_mode"
	38	[35]	LOADK    	11 -16	; "----------------------------"
	39	[36]	LOADK    	12 -27	; "page_overlap"
	40	[37]	LOADK    	13 -28	; "speed_reading_module_perception_expander"
	41	[38]	LOADK    	14 -16	; "----------------------------"
	42	[40]	LOADK    	15 -29	; "highlight_options"
	43	[40]	SETLIST  	2 13 1	; 1
	44	[40]	SETTABLE 	1 -5 2	; "typeset" -
	45	[41]	NEWTABLE 	2 15 0
	46	[44]	LOADK    	3 -30	; "frontlight"
	47	[45]	LOADK    	4 -31	; "night_mode"
	48	[46]	LOADK    	5 -16	; "----------------------------"
	49	[47]	LOADK    	6 -32	; "network"
	50	[48]	LOADK    	7 -33	; "screen"
	51	[49]	LOADK    	8 -16	; "----------------------------"
	52	[50]	LOADK    	9 -34	; "taps_and_gestures"
	53	[51]	LOADK    	10 -35	; "navigation"
	54	[52]	LOADK    	11 -36	; "document"
	55	[53]	LOADK    	12 -16	; "----------------------------"
	56	[54]	LOADK    	13 -37	; "language"
	57	[55]	LOADK    	14 -2	; "device"
	58	[56]	LOADK    	15 -16	; "----------------------------"
	59	[57]	LOADK    	16 -38	; "djvu_render_mode"
	60	[59]	LOADK    	17 -39	; "status_bar"
	61	[59]	SETLIST  	2 15 1	; 1
	62	[59]	SETTABLE 	1 -6 2	; "setting" -
	63	[60]	NEWTABLE 	2 9 0
	64	[61]	LOADK    	3 -40	; "keyboard_layout"
	65	[62]	LOADK    	4 -41	; "time"
	66	[63]	LOADK    	5 -42	; "battery"
	67	[64]	LOADK    	6 -43	; "autosuspend"
	68	[65]	LOADK    	7 -44	; "autoshutdown"
	69	[66]	LOADK    	8 -45	; "ignore_sleepcover"
	70	[67]	LOADK    	9 -46	; "ignore_open_sleepcover"
	71	[68]	LOADK    	10 -47	; "mass_storage_settings"
	72	[70]	LOADK    	11 -48	; "screenshot"
	73	[70]	SETLIST  	2 9 1	; 1
	74	[70]	SETTABLE 	1 -2 2	; "device" -
	75	[71]	NEWTABLE 	2 9 0
	76	[72]	LOADK    	3 -49	; "back_to_exit"
	77	[73]	LOADK    	4 -50	; "back_in_filemanager"
	78	[74]	LOADK    	5 -51	; "enable_back_history"
	79	[75]	LOADK    	6 -52	; "android_volume_keys"
	80	[76]	LOADK    	7 -53	; "android_camera_key"
	81	[77]	LOADK    	8 -54	; "android_haptic_feedback"
	82	[78]	LOADK    	9 -16	; "----------------------------"
	83	[79]	LOADK    	10 -55	; "invert_page_turn_gestures"
	84	[81]	LOADK    	11 -56	; "invert_page_turn_buttons"
	85	[81]	SETLIST  	2 9 1	; 1
	86	[81]	SETTABLE 	1 -35 2	; "navigation" -
	87	[82]	NEWTABLE 	2 8 0
	88	[83]	LOADK    	3 -57	; "network_wifi"
	89	[84]	LOADK    	4 -58	; "network_proxy"
	90	[85]	LOADK    	5 -59	; "network_restore"
	91	[86]	LOADK    	6 -60	; "network_info"
	92	[87]	LOADK    	7 -61	; "network_before_wifi_action"
	93	[88]	LOADK    	8 -62	; "network_dismiss_scan"
	94	[89]	LOADK    	9 -16	; "----------------------------"
	95	[91]	LOADK    	10 -63	; "ssh"
	96	[91]	SETLIST  	2 8 1	; 1
	97	[91]	SETTABLE 	1 -32 2	; "network" -
	98	[92]	NEWTABLE 	2 10 0
	99	[93]	LOADK    	3 -64	; "screensaver"
	100	[94]	LOADK    	4 -16	; "----------------------------"
	101	[95]	LOADK    	5 -65	; "screen_dpi"
	102	[96]	LOADK    	6 -66	; "screen_eink_opt"
	103	[97]	LOADK    	7 -67	; "color_rendering"
	104	[98]	LOADK    	8 -16	; "----------------------------"
	105	[99]	LOADK    	9 -68	; "screen_toggle_gsensor"
	106	[100]	LOADK    	10 -16	; "----------------------------"
	107	[101]	LOADK    	11 -69	; "screen_timeout"
	108	[103]	LOADK    	12 -70	; "fullscreen"
	109	[103]	SETLIST  	2 10 1	; 1
	110	[103]	SETTABLE 	1 -33 2	; "screen" -
	111	[104]	NEWTABLE 	2 8 0
	112	[105]	LOADK    	3 -71	; "gesture_manager"
	113	[106]	LOADK    	4 -72	; "gesture_intervals"
	114	[107]	LOADK    	5 -16	; "----------------------------"
	115	[108]	LOADK    	6 -73	; "follow_links"
	116	[109]	LOADK    	7 -16	; "----------------------------"
	117	[110]	LOADK    	8 -74	; "menu_activate"
	118	[111]	LOADK    	9 -75	; "ignore_hold_corners"
	119	[113]	LOADK    	10 -76	; "screen_disable_double_tab"
	120	[113]	SETLIST  	2 8 1	; 1
	121	[113]	SETTABLE 	1 -34 2	; "taps_and_gestures" -
	122	[114]	NEWTABLE 	2 14 0
	123	[115]	LOADK    	3 -77	; "read_timer"
	124	[116]	LOADK    	4 -78	; "calibre_wireless_connection"
	125	[117]	LOADK    	5 -79	; "evernote"
	126	[118]	LOADK    	6 -80	; "statistics"
	127	[119]	LOADK    	7 -81	; "progress_sync"
	128	[120]	LOADK    	8 -82	; "move_to_archive"
	129	[121]	LOADK    	9 -83	; "wallabag"
	130	[122]	LOADK    	10 -84	; "zsync"
	131	[123]	LOADK    	11 -85	; "news_downloader"
	132	[124]	LOADK    	12 -86	; "send2ebook"
	133	[125]	LOADK    	13 -87	; "text_editor"
	134	[126]	LOADK    	14 -16	; "----------------------------"
	135	[127]	LOADK    	15 -88	; "more_plugins"
	136	[129]	LOADK    	16 -89	; "plugin_management"
	137	[129]	SETLIST  	2 14 1	; 1
	138	[129]	SETTABLE 	1 -7 2	; "tools" -
	139	[130]	NEWTABLE 	2 6 0
	140	[131]	LOADK    	3 -90	; "auto_frontlight"
	141	[132]	LOADK    	4 -91	; "battery_statistics"
	142	[133]	LOADK    	5 -92	; "synchronize_time"
	143	[134]	LOADK    	6 -93	; "keep_alive"
	144	[135]	LOADK    	7 -94	; "doc_setting_tweak"
	145	[137]	LOADK    	8 -95	; "terminal"
	146	[137]	SETLIST  	2 6 1	; 1
	147	[137]	SETTABLE 	1 -88 2	; "more_plugins" -
	148	[138]	NEWTABLE 	2 13 0
	149	[139]	LOADK    	3 -96	; "dictionary_lookup"
	150	[140]	LOADK    	4 -97	; "dictionary_lookup_history"
	151	[141]	LOADK    	5 -98	; "dictionary_settings"
	152	[142]	LOADK    	6 -16	; "----------------------------"
	153	[143]	LOADK    	7 -99	; "wikipedia_lookup"
	154	[144]	LOADK    	8 -100	; "wikipedia_history"
	155	[145]	LOADK    	9 -101	; "wikipedia_settings"
	156	[146]	LOADK    	10 -16	; "----------------------------"
	157	[147]	LOADK    	11 -102	; "translation_settings"
	158	[148]	LOADK    	12 -16	; "----------------------------"
	159	[149]	LOADK    	13 -103	; "goodreads"
	160	[150]	LOADK    	14 -16	; "----------------------------"
	161	[152]	LOADK    	15 -104	; "fulltext_search"
	162	[152]	SETLIST  	2 13 1	; 1
	163	[152]	SETTABLE 	1 -8 2	; "search" -
	164	[153]	NEWTABLE 	2 0 0
	165	[153]	SETTABLE 	1 -9 2	; "filemanager" -
	166	[154]	NEWTABLE 	2 16 0
	167	[155]	LOADK    	3 -105	; "history"
	168	[156]	LOADK    	4 -106	; "open_previous_document"
	169	[157]	LOADK    	5 -16	; "----------------------------"
	170	[158]	LOADK    	6 -107	; "collections"
	171	[159]	LOADK    	7 -16	; "----------------------------"
	172	[160]	LOADK    	8 -108	; "book_status"
	173	[161]	LOADK    	9 -109	; "book_info"
	174	[162]	LOADK    	10 -16	; "----------------------------"
	175	[163]	LOADK    	11 -110	; "system_statistics"
	176	[164]	LOADK    	12 -111	; "mass_storage_actions"
	177	[165]	LOADK    	13 -16	; "----------------------------"
	178	[166]	LOADK    	14 -112	; "ota_update"
	179	[167]	LOADK    	15 -113	; "version"
	180	[168]	LOADK    	16 -114	; "help"
	181	[169]	LOADK    	17 -16	; "----------------------------"
	182	[171]	LOADK    	18 -115	; "exit_menu"
	183	[171]	SETLIST  	2 16 1	; 1
	184	[171]	SETTABLE 	1 -10 2	; "main" -
	185	[172]	NEWTABLE 	2 5 0
	186	[173]	LOADK    	3 -116	; "quickstart_guide"
	187	[174]	LOADK    	4 -16	; "----------------------------"
	188	[175]	LOADK    	5 -117	; "report_bug"
	189	[176]	LOADK    	6 -16	; "----------------------------"
	190	[178]	LOADK    	7 -118	; "about"
	191	[178]	SETLIST  	2 5 1	; 1
	192	[178]	SETTABLE 	1 -114 2	; "help" -
	193	[179]	NEWTABLE 	2 8 0
	194	[180]	LOADK    	3 -119	; "restart_koreader"
	195	[181]	LOADK    	4 -16	; "----------------------------"
	196	[182]	LOADK    	5 -120	; "sleep"
	197	[183]	LOADK    	6 -121	; "poweroff"
	198	[184]	LOADK    	7 -122	; "reboot"
	199	[185]	LOADK    	8 -16	; "----------------------------"
	200	[186]	LOADK    	9 -123	; "start_bq"
	201	[188]	LOADK    	10 -124	; "exit"
	202	[188]	SETLIST  	2 8 1	; 1
	203	[188]	SETTABLE 	1 -115 2	; "exit_menu" -
	204	[191]	SELF     	2 0 -125	; "isAndroid"
	205	[191]	CALL     	2 2 2
	206	[191]	TEST     	2 0 0
	207	[191]	JMP      	1	; to 209
	208	[192]	SETTABLE 	1 -115 -126	; "exit_menu" nil
	209	[195]	RETURN   	1 2
	210	[195]	RETURN   	0 1
