
main <./frontend/apps/reader/modules/readerhighlight.lua:0,0> (232 instructions, 928 bytes at 0x7f869cc06900)
0+ params, 22 slots, 0 upvalues, 21 locals, 68 constants, 44 functions
	1	[1]	GETGLOBAL	0 -1	; require
	2	[1]	LOADK    	1 -2	; "ui/bidi"
	3	[1]	CALL     	0 2 2
	4	[2]	GETGLOBAL	1 -1	; require
	5	[2]	LOADK    	2 -3	; "ui/widget/buttondialog"
	6	[2]	CALL     	1 2 2
	7	[3]	GETGLOBAL	2 -1	; require
	8	[3]	LOADK    	3 -4	; "device"
	9	[3]	CALL     	2 2 2
	10	[4]	GETGLOBAL	3 -1	; require
	11	[4]	LOADK    	4 -5	; "ui/event"
	12	[4]	CALL     	3 2 2
	13	[5]	GETGLOBAL	4 -1	; require
	14	[5]	LOADK    	5 -6	; "ui/widget/infomessage"
	15	[5]	CALL     	4 2 2
	16	[6]	GETGLOBAL	5 -1	; require
	17	[6]	LOADK    	6 -7	; "ui/widget/container/inputcontainer"
	18	[6]	CALL     	5 2 2
	19	[7]	GETGLOBAL	6 -1	; require
	20	[7]	LOADK    	7 -8	; "ui/widget/multiconfirmbox"
	21	[7]	CALL     	6 2 2
	22	[8]	GETGLOBAL	7 -1	; require
	23	[8]	LOADK    	8 -9	; "ui/widget/notification"
	24	[8]	CALL     	7 2 2
	25	[9]	GETGLOBAL	8 -1	; require
	26	[9]	LOADK    	9 -10	; "ui/timeval"
	27	[9]	CALL     	8 2 2
	28	[10]	GETGLOBAL	9 -1	; require
	29	[10]	LOADK    	10 -11	; "ui/translator"
	30	[10]	CALL     	9 2 2
	31	[11]	GETGLOBAL	10 -1	; require
	32	[11]	LOADK    	11 -12	; "ui/uimanager"
	33	[11]	CALL     	10 2 2
	34	[12]	GETGLOBAL	11 -1	; require
	35	[12]	LOADK    	12 -13	; "logger"
	36	[12]	CALL     	11 2 2
	37	[13]	GETGLOBAL	12 -1	; require
	38	[13]	LOADK    	13 -14	; "gettext"
	39	[13]	CALL     	12 2 2
	40	[14]	GETTABLE 	13 12 -15	; "pgettext"
	41	[15]	GETGLOBAL	14 -1	; require
	42	[15]	LOADK    	15 -16	; "ffi/util"
	43	[15]	CALL     	14 2 2
	44	[15]	GETTABLE 	14 14 -17	; "template"
	45	[16]	GETTABLE 	15 2 -18	; "screen"
	46	[18]	SELF     	16 5 -19	; "new"
	47	[18]	NEWTABLE 	18 0 0
	48	[18]	CALL     	16 3 2
	49	[24]	CLOSURE  	17 0	; 0x7f869cc070f0
	50	[20]	SETTABLE 	16 -20 17	; "init" -
	51	[85]	CLOSURE  	17 1	; 0x7f869cc06f00
	52	[85]	MOVE     	0 2
	53	[26]	SETTABLE 	16 -21 17	; "setupTouchZones" -
	54	[89]	CLOSURE  	17 2	; 0x7f869cc08160
	55	[87]	SETTABLE 	16 -22 17	; "onReaderReady" -
	56	[98]	CLOSURE  	17 3	; 0x7f869cc08370
	57	[98]	MOVE     	0 12
	58	[98]	MOVE     	0 9
	59	[91]	SETTABLE 	16 -23 17	; "addToMainMenu" -
	60	[100]	NEWTABLE 	17 0 3
	61	[101]	MOVE     	18 12
	62	[101]	LOADK    	19 -25	; "Lighten"
	63	[101]	CALL     	18 2 2
	64	[101]	SETTABLE 	17 -24 18	; "lighten" -
	65	[102]	MOVE     	18 12
	66	[102]	LOADK    	19 -27	; "Underline"
	67	[102]	CALL     	18 2 2
	68	[102]	SETTABLE 	17 -26 18	; "underscore" -
	69	[103]	MOVE     	18 12
	70	[103]	LOADK    	19 -29	; "Invert"
	71	[103]	CALL     	18 2 2
	72	[103]	SETTABLE 	17 -28 18	; "invert" -
	73	[139]	CLOSURE  	18 4	; 0x7f869cc07240
	74	[139]	MOVE     	0 17
	75	[139]	MOVE     	0 12
	76	[106]	SETTABLE 	16 -30 18	; "genHighlightDrawerMenu" -
	77	[147]	CLOSURE  	18 5	; 0x7f869cc0ac20
	78	[147]	MOVE     	0 8
	79	[144]	SETTABLE 	16 -31 18	; "getClearId" -
	80	[174]	CLOSURE  	18 6	; 0x7f869cc0a9b0
	81	[174]	MOVE     	0 10
	82	[149]	SETTABLE 	16 -32 18	; "clear" -
	83	[179]	CLOSURE  	18 7	; 0x7f869cc0b330
	84	[176]	SETTABLE 	16 -33 18	; "onClearHighlight" -
	85	[189]	CLOSURE  	18 8	; 0x7f869cc072d0
	86	[181]	SETTABLE 	16 -34 18	; "onTap" -
	87	[200]	CLOSURE  	18 9	; 0x7f869cc0ba70
	88	[222]	CLOSURE  	19 10	; 0x7f869cc0bd80
	89	[222]	MOVE     	0 18
	90	[222]	MOVE     	0 11
	91	[202]	SETTABLE 	16 -35 19	; "onTapPageSavedHighlight" -
	92	[267]	CLOSURE  	19 11	; 0x7f869cc0c320
	93	[267]	MOVE     	0 18
	94	[267]	MOVE     	0 11
	95	[224]	SETTABLE 	16 -36 19	; "onTapXPointerSavedHighlight" -
	96	[353]	CLOSURE  	19 12	; 0x7f869cc0cc90
	97	[353]	MOVE     	0 3
	98	[353]	MOVE     	0 15
	99	[353]	MOVE     	0 10
	100	[269]	SETTABLE 	16 -37 19	; "updateHighlight" -
	101	[441]	CLOSURE  	19 13	; 0x7f869cc090a0
	102	[441]	MOVE     	0 12
	103	[441]	MOVE     	0 10
	104	[441]	MOVE     	0 0
	105	[441]	MOVE     	0 1
	106	[355]	SETTABLE 	16 -38 19	; "onShowHighlightDialog" -
	107	[551]	CLOSURE  	19 14	; 0x7f869cc0f860
	108	[551]	MOVE     	0 12
	109	[551]	MOVE     	0 13
	110	[551]	MOVE     	0 2
	111	[551]	MOVE     	0 10
	112	[551]	MOVE     	0 1
	113	[551]	MOVE     	0 3
	114	[443]	SETTABLE 	16 -39 19	; "onShowHighlightMenu" -
	115	[559]	CLOSURE  	19 15	; 0x7f869cc11ad0
	116	[559]	MOVE     	0 8
	117	[553]	SETTABLE 	16 -40 19	; "_resetHoldTimer" -
	118	[621]	CLOSURE  	19 16	; 0x7f869cc0fef0
	119	[621]	MOVE     	0 11
	120	[621]	MOVE     	0 10
	121	[561]	SETTABLE 	16 -41 19	; "onHold" -
	122	[769]	CLOSURE  	19 17	; 0x7f869cc0b9f0
	123	[769]	MOVE     	0 11
	124	[769]	MOVE     	0 0
	125	[769]	MOVE     	0 15
	126	[769]	MOVE     	0 3
	127	[769]	MOVE     	0 10
	128	[623]	SETTABLE 	16 -42 19	; "onHoldPan" -
	129	[771]	MOVE     	19 12
	130	[778]	LOADK    	20 -43	; "No OCR results or no language data.\n\nKOReader has a build-in OCR engine for recognizing words in scanned PDF and DjVu documents. In order to use OCR in scanned pages, you need to install tesseract trained data for your document language.\n\nYou can download language data files for version 3.04 from https://github.com/tesseract-ocr/tesseract/wiki/Data-Files\n\nCopy the language data files for Tesseract 3.04 (e.g., eng.traineddata for English and spa.traineddata for Spanish) into koreader/data/tessdata"
	131	[771]	CALL     	19 2 2
	132	[798]	CLOSURE  	20 18	; 0x7f869cc0ded0
	133	[798]	MOVE     	0 3
	134	[798]	MOVE     	0 11
	135	[798]	MOVE     	0 10
	136	[798]	MOVE     	0 4
	137	[798]	MOVE     	0 19
	138	[780]	SETTABLE 	16 -44 20	; "lookup" -
	139	[822]	CLOSURE  	20 19	; 0x7f869cc11d60
	140	[954]	CLOSURE  	21 20	; 0x7f869cc093e0
	141	[954]	MOVE     	0 20
	142	[954]	MOVE     	0 14
	143	[954]	MOVE     	0 12
	144	[954]	MOVE     	0 0
	145	[954]	MOVE     	0 10
	146	[954]	MOVE     	0 4
	147	[824]	SETTABLE 	16 -45 21	; "viewSelectionHTML" -
	148	[971]	CLOSURE  	21 21	; 0x7f869cc138c0
	149	[971]	MOVE     	0 11
	150	[971]	MOVE     	0 10
	151	[971]	MOVE     	0 4
	152	[971]	MOVE     	0 19
	153	[956]	SETTABLE 	16 -46 21	; "translate" -
	154	[975]	CLOSURE  	21 22	; 0x7f869cc14e80
	155	[975]	MOVE     	0 9
	156	[973]	SETTABLE 	16 -47 21	; "onTranslateText" -
	157	[1023]	CLOSURE  	21 23	; 0x7f869cc13a00
	158	[1023]	MOVE     	0 8
	159	[977]	SETTABLE 	16 -48 21	; "onHoldRelease" -
	160	[1049]	CLOSURE  	21 24	; 0x7f869cc155a0
	161	[1049]	MOVE     	0 10
	162	[1049]	MOVE     	0 7
	163	[1049]	MOVE     	0 12
	164	[1049]	MOVE     	0 14
	165	[1025]	SETTABLE 	16 -49 21	; "onCycleHighlightAction" -
	166	[1064]	CLOSURE  	21 25	; 0x7f869cc15f10
	167	[1064]	MOVE     	0 10
	168	[1064]	MOVE     	0 7
	169	[1064]	MOVE     	0 14
	170	[1064]	MOVE     	0 12
	171	[1051]	SETTABLE 	16 -50 21	; "onCycleHighlightStyle" -
	172	[1073]	CLOSURE  	21 26	; 0x7f869cc16400
	173	[1073]	MOVE     	0 11
	174	[1066]	SETTABLE 	16 -51 21	; "highlightFromHoldPos" -
	175	[1077]	CLOSURE  	21 27	; 0x7f869cc16a60
	176	[1075]	SETTABLE 	16 -52 21	; "onHighlight" -
	177	[1139]	CLOSURE  	21 28	; 0x7f869cc16ed0
	178	[1139]	MOVE     	0 11
	179	[1079]	SETTABLE 	16 -53 21	; "onUnhighlight" -
	180	[1158]	CLOSURE  	21 29	; 0x7f869cc13bd0
	181	[1141]	SETTABLE 	16 -54 21	; "getHighlightBookmarkItem" -
	182	[1196]	CLOSURE  	21 30	; 0x7f869cc16e30
	183	[1196]	MOVE     	0 3
	184	[1196]	MOVE     	0 11
	185	[1160]	SETTABLE 	16 -55 21	; "saveHighlight" -
	186	[1232]	CLOSURE  	21 31	; 0x7f869cc16ce0
	187	[1232]	MOVE     	0 11
	188	[1232]	MOVE     	0 10
	189	[1232]	MOVE     	0 4
	190	[1232]	MOVE     	0 12
	191	[1217]	SETTABLE 	16 -56 21	; "exportToDocument" -
	192	[1239]	CLOSURE  	21 32	; 0x7f869cc14840
	193	[1239]	MOVE     	0 10
	194	[1239]	MOVE     	0 3
	195	[1234]	SETTABLE 	16 -57 21	; "addNote" -
	196	[1245]	CLOSURE  	21 33	; 0x7f869cc0ee40
	197	[1245]	MOVE     	0 3
	198	[1241]	SETTABLE 	16 -58 21	; "lookupWikipedia" -
	199	[1254]	CLOSURE  	21 34	; 0x7f869cc14240
	200	[1254]	MOVE     	0 11
	201	[1254]	MOVE     	0 3
	202	[1247]	SETTABLE 	16 -59 21	; "onHighlightSearch" -
	203	[1262]	CLOSURE  	21 35	; 0x7f869cc10b30
	204	[1262]	MOVE     	0 11
	205	[1262]	MOVE     	0 3
	206	[1256]	SETTABLE 	16 -60 21	; "onHighlightDictLookup" -
	207	[1266]	CLOSURE  	21 36	; 0x7f869cc184b0
	208	[1266]	MOVE     	0 11
	209	[1264]	SETTABLE 	16 -61 21	; "shareHighlight" -
	210	[1270]	CLOSURE  	21 37	; 0x7f869cc18a70
	211	[1270]	MOVE     	0 11
	212	[1268]	SETTABLE 	16 -62 21	; "moreAction" -
	213	[1284]	CLOSURE  	21 38	; 0x7f869cc18d20
	214	[1284]	MOVE     	0 3
	215	[1284]	MOVE     	0 11
	216	[1272]	SETTABLE 	16 -63 21	; "deleteHighlight" -
	217	[1292]	CLOSURE  	21 39	; 0x7f869cc18f70
	218	[1286]	SETTABLE 	16 -64 21	; "editHighlight" -
	219	[1301]	CLOSURE  	21 40	; 0x7f869cc19860
	220	[1294]	SETTABLE 	16 -65 21	; "onReadSettings" -
	221	[1306]	CLOSURE  	21 41	; 0x7f869cc19a40
	222	[1303]	SETTABLE 	16 -66 21	; "onSaveSettings" -
	223	[1312]	CLOSURE  	21 42	; 0x7f869cc19cf0
	224	[1312]	MOVE     	0 10
	225	[1308]	SETTABLE 	16 -67 21	; "onClose" -
	226	[1332]	CLOSURE  	21 43	; 0x7f869cc1a2a0
	227	[1332]	MOVE     	0 10
	228	[1332]	MOVE     	0 6
	229	[1332]	MOVE     	0 12
	230	[1314]	SETTABLE 	16 -68 21	; "toggleDefault" -
	231	[1334]	RETURN   	16 2
	232	[1334]	RETURN   	0 1

function <./frontend/apps/reader/modules/readerhighlight.lua:20,24> (6 instructions, 24 bytes at 0x7f869cc070f0)
1 param, 4 slots, 0 upvalues, 1 local, 2 constants, 1 function
	1	[21]	GETTABLE 	1 0 -1	; "ui"
	2	[21]	SELF     	1 1 -2	; "registerPostInitCallback"
	3	[23]	CLOSURE  	3 0	; 0x7f869cc076d0
	4	[23]	MOVE     	0 0
	5	[21]	CALL     	1 3 1
	6	[24]	RETURN   	0 1

function <./frontend/apps/reader/modules/readerhighlight.lua:21,23> (7 instructions, 28 bytes at 0x7f869cc076d0)
0 params, 3 slots, 1 upvalue, 0 locals, 3 constants, 0 functions
	1	[22]	GETUPVAL 	0 0	; self
	2	[22]	GETTABLE 	0 0 -1	; "ui"
	3	[22]	GETTABLE 	0 0 -2	; "menu"
	4	[22]	SELF     	0 0 -3	; "registerToMainMenu"
	5	[22]	GETUPVAL 	2 0	; self
	6	[22]	CALL     	0 3 1
	7	[23]	RETURN   	0 1

function <./frontend/apps/reader/modules/readerhighlight.lua:26,85> (80 instructions, 320 bytes at 0x7f869cc06f00)
1 param, 15 slots, 1 upvalue, 1 local, 37 constants, 4 functions
	1	[28]	NEWTABLE 	1 0 0
	2	[28]	SETTABLE 	0 -1 1	; "ges_events" -
	3	[29]	SETTABLE 	0 -2 -3	; "onGesture" nil
	4	[31]	GETUPVAL 	1 0	; Device
	5	[31]	SELF     	1 1 -4	; "isTouchDevice"
	6	[31]	CALL     	1 2 2
	7	[31]	TEST     	1 0 1
	8	[31]	JMP      	1	; to 10
	9	[31]	RETURN   	0 1
	10	[33]	GETTABLE 	1 0 -5	; "ui"
	11	[33]	SELF     	1 1 -6	; "registerTouchZones"
	12	[33]	NEWTABLE 	3 4 0
	13	[33]	NEWTABLE 	4 0 5
	14	[35]	SETTABLE 	4 -7 -8	; "id" "readerhighlight_tap"
	15	[36]	SETTABLE 	4 -9 -10	; "ges" "tap"
	16	[37]	NEWTABLE 	5 0 4
	17	[38]	SETTABLE 	5 -12 -13	; "ratio_x" 0
	18	[38]	SETTABLE 	5 -14 -13	; "ratio_y" 0
	19	[38]	SETTABLE 	5 -15 -16	; "ratio_w" 1
	20	[38]	SETTABLE 	5 -17 -16	; "ratio_h" 1
	21	[39]	SETTABLE 	4 -11 5	; "screen_zone" -
	22	[40]	NEWTABLE 	5 9 0
	23	[44]	LOADK    	6 -19	; "tap_forward"
	24	[45]	LOADK    	7 -20	; "tap_backward"
	25	[46]	LOADK    	8 -21	; "readermenu_tap"
	26	[47]	LOADK    	9 -22	; "readerconfigmenu_tap"
	27	[48]	LOADK    	10 -23	; "readerfooter_tap"
	28	[49]	LOADK    	11 -24	; "tap_top_left_corner"
	29	[50]	LOADK    	12 -25	; "tap_top_right_corner"
	30	[51]	LOADK    	13 -26	; "tap_left_bottom_corner"
	31	[53]	LOADK    	14 -27	; "tap_right_bottom_corner"
	32	[53]	SETLIST  	5 9 1	; 1
	33	[53]	SETTABLE 	4 -18 5	; "overrides" -
	34	[54]	CLOSURE  	5 0	; 0x7f869cc07f00
	35	[54]	MOVE     	0 0
	36	[54]	SETTABLE 	4 -28 5	; "handler" -
	37	[55]	NEWTABLE 	5 0 5
	38	[57]	SETTABLE 	5 -7 -29	; "id" "readerhighlight_hold"
	39	[58]	SETTABLE 	5 -9 -30	; "ges" "hold"
	40	[59]	NEWTABLE 	6 0 4
	41	[60]	SETTABLE 	6 -12 -13	; "ratio_x" 0
	42	[60]	SETTABLE 	6 -14 -13	; "ratio_y" 0
	43	[60]	SETTABLE 	6 -15 -16	; "ratio_w" 1
	44	[60]	SETTABLE 	6 -17 -16	; "ratio_h" 1
	45	[61]	SETTABLE 	5 -11 6	; "screen_zone" -
	46	[62]	NEWTABLE 	6 1 0
	47	[64]	LOADK    	7 -31	; "readerfooter_hold"
	48	[64]	SETLIST  	6 1 1	; 1
	49	[64]	SETTABLE 	5 -18 6	; "overrides" -
	50	[65]	CLOSURE  	6 1	; 0x7f869cc08740
	51	[65]	MOVE     	0 0
	52	[65]	SETTABLE 	5 -28 6	; "handler" -
	53	[66]	NEWTABLE 	6 0 4
	54	[68]	SETTABLE 	6 -7 -32	; "id" "readerhighlight_hold_release"
	55	[69]	SETTABLE 	6 -9 -33	; "ges" "hold_release"
	56	[70]	NEWTABLE 	7 0 4
	57	[71]	SETTABLE 	7 -12 -13	; "ratio_x" 0
	58	[71]	SETTABLE 	7 -14 -13	; "ratio_y" 0
	59	[71]	SETTABLE 	7 -15 -16	; "ratio_w" 1
	60	[71]	SETTABLE 	7 -17 -16	; "ratio_h" 1
	61	[72]	SETTABLE 	6 -11 7	; "screen_zone" -
	62	[73]	CLOSURE  	7 2	; 0x7f869cc08890
	63	[73]	MOVE     	0 0
	64	[73]	SETTABLE 	6 -28 7	; "handler" -
	65	[74]	NEWTABLE 	7 0 5
	66	[76]	SETTABLE 	7 -7 -34	; "id" "readerhighlight_hold_pan"
	67	[77]	SETTABLE 	7 -9 -35	; "ges" "hold_pan"
	68	[78]	SETTABLE 	7 -36 -37	; "rate" 2
	69	[79]	NEWTABLE 	8 0 4
	70	[80]	SETTABLE 	8 -12 -13	; "ratio_x" 0
	71	[80]	SETTABLE 	8 -14 -13	; "ratio_y" 0
	72	[80]	SETTABLE 	8 -15 -16	; "ratio_w" 1
	73	[80]	SETTABLE 	8 -17 -16	; "ratio_h" 1
	74	[81]	SETTABLE 	7 -11 8	; "screen_zone" -
	75	[82]	CLOSURE  	8 3	; 0x7f869cc082b0
	76	[82]	MOVE     	0 0
	77	[82]	SETTABLE 	7 -28 8	; "handler" -
	78	[84]	SETLIST  	3 4 1	; 1
	79	[33]	CALL     	1 3 1
	80	[85]	RETURN   	0 1

function <./frontend/apps/reader/modules/readerhighlight.lua:54,54> (7 instructions, 28 bytes at 0x7f869cc07f00)
1 param, 5 slots, 1 upvalue, 1 local, 1 constant, 0 functions
	1	[54]	GETUPVAL 	1 0	; self
	2	[54]	SELF     	1 1 -1	; "onTap"
	3	[54]	LOADNIL  	3 3
	4	[54]	MOVE     	4 0
	5	[54]	TAILCALL 	1 4 0
	6	[54]	RETURN   	1 0
	7	[54]	RETURN   	0 1

function <./frontend/apps/reader/modules/readerhighlight.lua:65,65> (7 instructions, 28 bytes at 0x7f869cc08740)
1 param, 5 slots, 1 upvalue, 1 local, 1 constant, 0 functions
	1	[65]	GETUPVAL 	1 0	; self
	2	[65]	SELF     	1 1 -1	; "onHold"
	3	[65]	LOADNIL  	3 3
	4	[65]	MOVE     	4 0
	5	[65]	TAILCALL 	1 4 0
	6	[65]	RETURN   	1 0
	7	[65]	RETURN   	0 1

function <./frontend/apps/reader/modules/readerhighlight.lua:73,73> (5 instructions, 20 bytes at 0x7f869cc08890)
0 params, 2 slots, 1 upvalue, 0 locals, 1 constant, 0 functions
	1	[73]	GETUPVAL 	0 0	; self
	2	[73]	SELF     	0 0 -1	; "onHoldRelease"
	3	[73]	TAILCALL 	0 2 0
	4	[73]	RETURN   	0 0
	5	[73]	RETURN   	0 1

function <./frontend/apps/reader/modules/readerhighlight.lua:82,82> (7 instructions, 28 bytes at 0x7f869cc082b0)
1 param, 5 slots, 1 upvalue, 1 local, 1 constant, 0 functions
	1	[82]	GETUPVAL 	1 0	; self
	2	[82]	SELF     	1 1 -1	; "onHoldPan"
	3	[82]	LOADNIL  	3 3
	4	[82]	MOVE     	4 0
	5	[82]	TAILCALL 	1 4 0
	6	[82]	RETURN   	1 0
	7	[82]	RETURN   	0 1

function <./frontend/apps/reader/modules/readerhighlight.lua:87,89> (3 instructions, 12 bytes at 0x7f869cc08160)
1 param, 3 slots, 0 upvalues, 1 local, 1 constant, 0 functions
	1	[88]	SELF     	1 0 -1	; "setupTouchZones"
	2	[88]	CALL     	1 2 1
	3	[89]	RETURN   	0 1

function <./frontend/apps/reader/modules/readerhighlight.lua:91,98> (14 instructions, 56 bytes at 0x7f869cc08370)
2 params, 5 slots, 2 upvalues, 2 locals, 7 constants, 0 functions
	1	[93]	NEWTABLE 	2 0 2
	2	[94]	GETUPVAL 	3 0	; _
	3	[94]	LOADK    	4 -3	; "Highlighting"
	4	[94]	CALL     	3 2 2
	5	[94]	SETTABLE 	2 -2 3	; "text" -
	6	[95]	SELF     	3 0 -5	; "genHighlightDrawerMenu"
	7	[95]	CALL     	3 2 2
	8	[95]	SETTABLE 	2 -4 3	; "sub_item_table" -
	9	[96]	SETTABLE 	1 -1 2	; "highlight_options" -
	10	[97]	GETUPVAL 	2 1	; Translator
	11	[97]	SELF     	2 2 -7	; "genSettingsMenu"
	12	[97]	CALL     	2 2 2
	13	[97]	SETTABLE 	1 -6 2	; "translation_settings" -
	14	[98]	RETURN   	0 1

function <./frontend/apps/reader/modules/readerhighlight.lua:106,139> (31 instructions, 124 bytes at 0x7f869cc07240)
1 param, 8 slots, 2 upvalues, 2 locals, 10 constants, 4 functions
	1	[120]	CLOSURE  	1 0	; 0x7f869cc09520
	2	[120]	GETUPVAL 	0 0	; highlight_style
	3	[120]	MOVE     	0 0
	4	[121]	NEWTABLE 	2 3 0
	5	[121]	NEWTABLE 	3 0 5
	6	[123]	GETUPVAL 	4 1	; _
	7	[123]	LOADK    	5 -2	; "Allow highlighting"
	8	[123]	CALL     	4 2 2
	9	[123]	SETTABLE 	3 -1 4	; "text" -
	10	[126]	CLOSURE  	4 1	; 0x7f869cc0a570
	11	[126]	MOVE     	0 0
	12	[126]	SETTABLE 	3 -3 4	; "checked_func" -
	13	[129]	CLOSURE  	4 2	; 0x7f869cc0a5f0
	14	[129]	MOVE     	0 0
	15	[129]	SETTABLE 	3 -4 4	; "callback" -
	16	[132]	CLOSURE  	4 3	; 0x7f869cc0aca0
	17	[132]	MOVE     	0 0
	18	[132]	SETTABLE 	3 -5 4	; "hold_callback" -
	19	[133]	SETTABLE 	3 -6 -7	; "separator" true
	20	[135]	MOVE     	4 1
	21	[135]	LOADK    	5 -8	; "lighten"
	22	[135]	CALL     	4 2 2
	23	[136]	MOVE     	5 1
	24	[136]	LOADK    	6 -9	; "underscore"
	25	[136]	CALL     	5 2 2
	26	[137]	MOVE     	6 1
	27	[137]	LOADK    	7 -10	; "invert"
	28	[137]	CALL     	6 2 0
	29	[138]	SETLIST  	2 0 1	; 1
	30	[138]	RETURN   	2 2
	31	[139]	RETURN   	0 1

function <./frontend/apps/reader/modules/readerhighlight.lua:107,120> (17 instructions, 68 bytes at 0x7f869cc09520)
1 param, 3 slots, 2 upvalues, 1 local, 4 constants, 3 functions
	1	[108]	NEWTABLE 	1 0 4
	2	[109]	GETUPVAL 	2 0	; highlight_style
	3	[109]	GETTABLE 	2 2 0
	4	[109]	SETTABLE 	1 -1 2	; "text" -
	5	[112]	CLOSURE  	2 0	; 0x7f869cc09880
	6	[112]	GETUPVAL 	0 1	; self
	7	[112]	MOVE     	0 0
	8	[112]	SETTABLE 	1 -2 2	; "checked_func" -
	9	[115]	CLOSURE  	2 1	; 0x7f869cc09b90
	10	[115]	GETUPVAL 	0 1	; self
	11	[115]	SETTABLE 	1 -3 2	; "enabled_func" -
	12	[118]	CLOSURE  	2 2	; 0x7f869cc09f20
	13	[118]	GETUPVAL 	0 1	; self
	14	[118]	MOVE     	0 0
	15	[118]	SETTABLE 	1 -4 2	; "callback" -
	16	[119]	RETURN   	1 2
	17	[120]	RETURN   	0 1

function <./frontend/apps/reader/modules/readerhighlight.lua:110,112> (11 instructions, 44 bytes at 0x7f869cc09880)
0 params, 2 slots, 2 upvalues, 0 locals, 3 constants, 0 functions
	1	[111]	GETUPVAL 	0 0	; self
	2	[111]	GETTABLE 	0 0 -1	; "view"
	3	[111]	GETTABLE 	0 0 -2	; "highlight"
	4	[111]	GETTABLE 	0 0 -3	; "saved_drawer"
	5	[111]	GETUPVAL 	1 1	; style
	6	[111]	EQ       	1 0 1
	7	[111]	JMP      	1	; to 9
	8	[111]	LOADBOOL 	0 0 1
	9	[111]	LOADBOOL 	0 1 0
	10	[111]	RETURN   	0 2
	11	[112]	RETURN   	0 1

function <./frontend/apps/reader/modules/readerhighlight.lua:113,115> (7 instructions, 28 bytes at 0x7f869cc09b90)
0 params, 2 slots, 1 upvalue, 0 locals, 3 constants, 0 functions
	1	[114]	GETUPVAL 	0 0	; self
	2	[114]	GETTABLE 	0 0 -1	; "view"
	3	[114]	GETTABLE 	0 0 -2	; "highlight"
	4	[114]	GETTABLE 	0 0 -3	; "disabled"
	5	[114]	NOT      	0 0
	6	[114]	RETURN   	0 2
	7	[115]	RETURN   	0 1

function <./frontend/apps/reader/modules/readerhighlight.lua:116,118> (6 instructions, 24 bytes at 0x7f869cc09f20)
0 params, 2 slots, 2 upvalues, 0 locals, 3 constants, 0 functions
	1	[117]	GETUPVAL 	0 0	; self
	2	[117]	GETTABLE 	0 0 -1	; "view"
	3	[117]	GETTABLE 	0 0 -2	; "highlight"
	4	[117]	GETUPVAL 	1 1	; style
	5	[117]	SETTABLE 	0 -3 1	; "saved_drawer" -
	6	[118]	RETURN   	0 1

function <./frontend/apps/reader/modules/readerhighlight.lua:124,126> (7 instructions, 28 bytes at 0x7f869cc0a570)
0 params, 2 slots, 1 upvalue, 0 locals, 3 constants, 0 functions
	1	[125]	GETUPVAL 	0 0	; self
	2	[125]	GETTABLE 	0 0 -1	; "view"
	3	[125]	GETTABLE 	0 0 -2	; "highlight"
	4	[125]	GETTABLE 	0 0 -3	; "disabled"
	5	[125]	NOT      	0 0
	6	[125]	RETURN   	0 2
	7	[126]	RETURN   	0 1

function <./frontend/apps/reader/modules/readerhighlight.lua:127,129> (10 instructions, 40 bytes at 0x7f869cc0a5f0)
0 params, 2 slots, 1 upvalue, 0 locals, 3 constants, 0 functions
	1	[128]	GETUPVAL 	0 0	; self
	2	[128]	GETTABLE 	0 0 -1	; "view"
	3	[128]	GETTABLE 	0 0 -2	; "highlight"
	4	[128]	GETUPVAL 	1 0	; self
	5	[128]	GETTABLE 	1 1 -1	; "view"
	6	[128]	GETTABLE 	1 1 -2	; "highlight"
	7	[128]	GETTABLE 	1 1 -3	; "disabled"
	8	[128]	NOT      	1 1
	9	[128]	SETTABLE 	0 -3 1	; "disabled" -
	10	[129]	RETURN   	0 1

function <./frontend/apps/reader/modules/readerhighlight.lua:130,132> (4 instructions, 16 bytes at 0x7f869cc0aca0)
1 param, 3 slots, 1 upvalue, 1 local, 1 constant, 0 functions
	1	[131]	GETUPVAL 	1 0	; self
	2	[131]	SELF     	1 1 -1	; "toggleDefault"
	3	[131]	CALL     	1 2 1
	4	[132]	RETURN   	0 1

function <./frontend/apps/reader/modules/readerhighlight.lua:144,147> (7 instructions, 28 bytes at 0x7f869cc0ac20)
1 param, 2 slots, 1 upvalue, 1 local, 2 constants, 0 functions
	1	[145]	GETUPVAL 	1 0	; TimeVal
	2	[145]	GETTABLE 	1 1 -2	; "now"
	3	[145]	CALL     	1 1 2
	4	[145]	SETTABLE 	0 -1 1	; "clear_id" -
	5	[146]	GETTABLE 	1 0 -1	; "clear_id"
	6	[146]	RETURN   	1 2
	7	[147]	RETURN   	0 1

function <./frontend/apps/reader/modules/readerhighlight.lua:149,174> (42 instructions, 168 bytes at 0x7f869cc0a9b0)
2 params, 6 slots, 1 upvalue, 2 locals, 16 constants, 0 functions
	1	[150]	TEST     	1 0 0
	2	[150]	JMP      	4	; to 7
	3	[151]	GETTABLE 	2 0 -1	; "clear_id"
	4	[151]	EQ       	1 1 2
	5	[151]	JMP      	1	; to 7
	6	[154]	RETURN   	0 1
	7	[157]	SETTABLE 	0 -1 -2	; "clear_id" nil
	8	[158]	GETTABLE 	2 0 -3	; "ui"
	9	[158]	GETTABLE 	2 2 -4	; "document"
	10	[158]	GETTABLE 	2 2 -5	; "info"
	11	[158]	GETTABLE 	2 2 -6	; "has_pages"
	12	[158]	TEST     	2 0 0
	13	[158]	JMP      	5	; to 19
	14	[159]	GETTABLE 	2 0 -7	; "view"
	15	[159]	GETTABLE 	2 2 -8	; "highlight"
	16	[159]	NEWTABLE 	3 0 0
	17	[159]	SETTABLE 	2 -9 3	; "temp" -
	18	[159]	JMP      	4	; to 23
	19	[161]	GETTABLE 	2 0 -3	; "ui"
	20	[161]	GETTABLE 	2 2 -4	; "document"
	21	[161]	SELF     	2 2 -10	; "clearSelection"
	22	[161]	CALL     	2 2 1
	23	[163]	GETTABLE 	2 0 -11	; "restore_page_mode_func"
	24	[163]	TEST     	2 0 0
	25	[163]	JMP      	3	; to 29
	26	[164]	GETTABLE 	2 0 -11	; "restore_page_mode_func"
	27	[164]	CALL     	2 1 1
	28	[165]	SETTABLE 	0 -11 -2	; "restore_page_mode_func" nil
	29	[167]	SETTABLE 	0 -12 -2	; "selected_text_start_xpointer" nil
	30	[168]	GETTABLE 	2 0 -13	; "hold_pos"
	31	[168]	TEST     	2 0 0
	32	[168]	JMP      	9	; to 42
	33	[169]	SETTABLE 	0 -13 -2	; "hold_pos" nil
	34	[170]	SETTABLE 	0 -14 -2	; "selected_text" nil
	35	[171]	GETUPVAL 	2 0	; UIManager
	36	[171]	SELF     	2 2 -15	; "setDirty"
	37	[171]	GETTABLE 	4 0 -16	; "dialog"
	38	[171]	LOADK    	5 -3	; "ui"
	39	[171]	CALL     	2 4 1
	40	[172]	LOADBOOL 	2 1 0
	41	[172]	RETURN   	2 2
	42	[174]	RETURN   	0 1

function <./frontend/apps/reader/modules/readerhighlight.lua:176,179> (5 instructions, 20 bytes at 0x7f869cc0b330)
1 param, 3 slots, 0 upvalues, 1 local, 1 constant, 0 functions
	1	[177]	SELF     	1 0 -1	; "clear"
	2	[177]	CALL     	1 2 1
	3	[178]	LOADBOOL 	1 1 0
	4	[178]	RETURN   	1 2
	5	[179]	RETURN   	0 1

function <./frontend/apps/reader/modules/readerhighlight.lua:181,189> (22 instructions, 88 bytes at 0x7f869cc072d0)
3 params, 6 slots, 0 upvalues, 3 locals, 7 constants, 0 functions
	1	[182]	SELF     	3 0 -1	; "clear"
	2	[182]	CALL     	3 2 2
	3	[182]	TEST     	3 0 1
	4	[182]	JMP      	17	; to 22
	5	[182]	TEST     	2 0 0
	6	[182]	JMP      	15	; to 22
	7	[183]	GETTABLE 	3 0 -2	; "ui"
	8	[183]	GETTABLE 	3 3 -3	; "document"
	9	[183]	GETTABLE 	3 3 -4	; "info"
	10	[183]	GETTABLE 	3 3 -5	; "has_pages"
	11	[183]	TEST     	3 0 0
	12	[183]	JMP      	5	; to 18
	13	[184]	SELF     	3 0 -6	; "onTapPageSavedHighlight"
	14	[184]	MOVE     	5 2
	15	[184]	TAILCALL 	3 3 0
	16	[184]	RETURN   	3 0
	17	[184]	JMP      	4	; to 22
	18	[186]	SELF     	3 0 -7	; "onTapXPointerSavedHighlight"
	19	[186]	MOVE     	5 2
	20	[186]	TAILCALL 	3 3 0
	21	[186]	RETURN   	3 0
	22	[189]	RETURN   	0 1

function <./frontend/apps/reader/modules/readerhighlight.lua:191,200> (23 instructions, 92 bytes at 0x7f869cc0ba70)
2 params, 6 slots, 0 upvalues, 4 locals, 4 constants, 0 functions
	1	[192]	TEST     	0 0 0
	2	[192]	JMP      	20	; to 23
	3	[193]	GETTABLE 	2 0 -1	; "x"
	4	[193]	GETTABLE 	3 0 -2	; "y"
	5	[194]	GETTABLE 	4 1 -1	; "x"
	6	[194]	LE       	0 4 2
	7	[194]	JMP      	15	; to 23
	8	[194]	GETTABLE 	4 1 -2	; "y"
	9	[194]	LE       	0 4 3
	10	[194]	JMP      	12	; to 23
	11	[195]	GETTABLE 	4 1 -1	; "x"
	12	[195]	GETTABLE 	5 1 -3	; "w"
	13	[195]	ADD      	4 4 5
	14	[195]	LE       	0 2 4
	15	[195]	JMP      	7	; to 23
	16	[196]	GETTABLE 	4 1 -2	; "y"
	17	[196]	GETTABLE 	5 1 -4	; "h"
	18	[196]	ADD      	4 4 5
	19	[196]	LE       	0 3 4
	20	[196]	JMP      	2	; to 23
	21	[197]	LOADBOOL 	4 1 0
	22	[197]	RETURN   	4 2
	23	[200]	RETURN   	0 1

function <./frontend/apps/reader/modules/readerhighlight.lua:202,222> (59 instructions, 236 bytes at 0x7f869cc0bd80)
2 params, 26 slots, 2 upvalues, 22 locals, 16 constants, 0 functions
	1	[203]	GETTABLE 	2 0 -1	; "view"
	2	[203]	SELF     	2 2 -2	; "getCurrentPageList"
	3	[203]	CALL     	2 2 2
	4	[204]	GETTABLE 	3 0 -1	; "view"
	5	[204]	SELF     	3 3 -3	; "screenToPageTransform"
	6	[204]	GETTABLE 	5 1 -4	; "pos"
	7	[204]	CALL     	3 3 2
	8	[205]	GETGLOBAL	4 -5	; pairs
	9	[205]	MOVE     	5 2
	10	[205]	CALL     	4 2 4
	11	[205]	JMP      	45	; to 57
	12	[206]	GETTABLE 	9 0 -1	; "view"
	13	[206]	GETTABLE 	9 9 -6	; "highlight"
	14	[206]	GETTABLE 	9 9 -7	; "saved"
	15	[206]	GETTABLE 	9 9 8
	16	[207]	TEST     	9 0 0
	17	[207]	JMP      	39	; to 57
	18	[208]	LOADK    	10 -8	; 1
	19	[208]	LEN      	11 9
	20	[208]	LOADK    	12 -8	; 1
	21	[208]	FORPREP  	10 34	; to 56
	22	[209]	GETTABLE 	14 9 13
	23	[209]	GETTABLE 	14 14 -9	; "pos0"
	24	[209]	GETTABLE 	15 9 13
	25	[209]	GETTABLE 	15 15 -10	; "pos1"
	26	[210]	GETTABLE 	16 0 -11	; "ui"
	27	[210]	GETTABLE 	16 16 -12	; "document"
	28	[210]	SELF     	16 16 -13	; "getPageBoxesFromPositions"
	29	[210]	MOVE     	18 8
	30	[210]	MOVE     	19 14
	31	[210]	MOVE     	20 15
	32	[210]	CALL     	16 5 2
	33	[211]	TEST     	16 0 0
	34	[211]	JMP      	21	; to 56
	35	[212]	GETGLOBAL	17 -5	; pairs
	36	[212]	MOVE     	18 16
	37	[212]	CALL     	17 2 4
	38	[212]	JMP      	15	; to 54
	39	[213]	GETUPVAL 	22 0	; inside_box
	40	[213]	MOVE     	23 3
	41	[213]	MOVE     	24 21
	42	[213]	CALL     	22 3 2
	43	[213]	TEST     	22 0 0
	44	[213]	JMP      	9	; to 54
	45	[214]	GETUPVAL 	22 1	; logger
	46	[214]	GETTABLE 	22 22 -14	; "dbg"
	47	[214]	LOADK    	23 -15	; "Tap on highlight"
	48	[214]	CALL     	22 2 1
	49	[215]	SELF     	22 0 -16	; "onShowHighlightDialog"
	50	[215]	MOVE     	24 8
	51	[215]	MOVE     	25 13
	52	[215]	TAILCALL 	22 4 0
	53	[215]	RETURN   	22 0
	54	[212]	TFORLOOP 	17 2
	55	[216]	JMP      	-17	; to 39
	56	[208]	FORLOOP  	10 -35	; to 22
	57	[205]	TFORLOOP 	4 2
	58	[220]	JMP      	-47	; to 12
	59	[222]	RETURN   	0 1

function <./frontend/apps/reader/modules/readerhighlight.lua:224,267> (109 instructions, 436 bytes at 0x7f869cc0c320)
2 params, 31 slots, 2 upvalues, 27 locals, 26 constants, 0 functions
	1	[230]	GETTABLE 	4 0 -1	; "view"
	2	[230]	SELF     	4 4 -2	; "screenToPageTransform"
	3	[230]	GETTABLE 	6 1 -3	; "pos"
	4	[230]	CALL     	4 3 2
	5	[231]	GETGLOBAL	5 -4	; pairs
	6	[231]	GETTABLE 	6 0 -1	; "view"
	7	[231]	GETTABLE 	6 6 -5	; "highlight"
	8	[231]	GETTABLE 	6 6 -6	; "saved"
	9	[231]	CALL     	5 2 4
	10	[231]	JMP      	96	; to 107
	11	[232]	GETTABLE 	10 0 -1	; "view"
	12	[232]	GETTABLE 	10 10 -5	; "highlight"
	13	[232]	GETTABLE 	10 10 -6	; "saved"
	14	[232]	GETTABLE 	10 10 8
	15	[233]	TEST     	10 0 0
	16	[233]	JMP      	90	; to 107
	17	[234]	LOADK    	11 -7	; 1
	18	[234]	LEN      	12 10
	19	[234]	LOADK    	13 -7	; 1
	20	[234]	FORPREP  	11 85	; to 106
	21	[235]	GETTABLE 	15 10 14
	22	[235]	GETTABLE 	15 15 -8	; "pos0"
	23	[235]	GETTABLE 	16 10 14
	24	[235]	GETTABLE 	16 16 -9	; "pos1"
	25	[238]	TEST     	2 0 1
	26	[238]	JMP      	25	; to 52
	27	[242]	GETTABLE 	17 0 -10	; "ui"
	28	[242]	GETTABLE 	17 17 -11	; "document"
	29	[242]	SELF     	17 17 -12	; "getCurrentPos"
	30	[242]	CALL     	17 2 2
	31	[242]	MOVE     	2 17
	32	[243]	GETTABLE 	17 0 -1	; "view"
	33	[243]	GETTABLE 	17 17 -13	; "view_mode"
	34	[243]	EQ       	0 17 -14	; - "page"
	35	[243]	JMP      	12	; to 48
	36	[243]	GETTABLE 	17 0 -10	; "ui"
	37	[243]	GETTABLE 	17 17 -11	; "document"
	38	[243]	SELF     	17 17 -15	; "getVisiblePageCount"
	39	[243]	CALL     	17 2 2
	40	[243]	LT       	0 -7 17	; 1 -
	41	[243]	JMP      	6	; to 48
	42	[244]	GETTABLE 	17 0 -10	; "ui"
	43	[244]	GETTABLE 	17 17 -16	; "dimen"
	44	[244]	GETTABLE 	17 17 -17	; "h"
	45	[244]	MUL      	17 -18 17	; 2 -
	46	[244]	ADD      	3 2 17
	47	[244]	JMP      	4	; to 52
	48	[246]	GETTABLE 	17 0 -10	; "ui"
	49	[246]	GETTABLE 	17 17 -16	; "dimen"
	50	[246]	GETTABLE 	17 17 -17	; "h"
	51	[246]	ADD      	3 2 17
	52	[249]	GETTABLE 	17 0 -10	; "ui"
	53	[249]	GETTABLE 	17 17 -11	; "document"
	54	[249]	SELF     	17 17 -19	; "getPosFromXPointer"
	55	[249]	MOVE     	19 15
	56	[249]	CALL     	17 3 2
	57	[250]	GETTABLE 	18 0 -10	; "ui"
	58	[250]	GETTABLE 	18 18 -11	; "document"
	59	[250]	SELF     	18 18 -19	; "getPosFromXPointer"
	60	[250]	MOVE     	20 16
	61	[250]	CALL     	18 3 2
	62	[251]	GETGLOBAL	19 -20	; math
	63	[251]	GETTABLE 	19 19 -21	; "min"
	64	[251]	MOVE     	20 17
	65	[251]	MOVE     	21 18
	66	[251]	CALL     	19 3 2
	67	[252]	GETGLOBAL	20 -20	; math
	68	[252]	GETTABLE 	20 20 -22	; "max"
	69	[252]	MOVE     	21 17
	70	[252]	MOVE     	22 18
	71	[252]	CALL     	20 3 2
	72	[253]	LE       	0 19 3
	73	[253]	JMP      	32	; to 106
	74	[253]	LE       	0 2 20
	75	[253]	JMP      	30	; to 106
	76	[254]	GETTABLE 	21 0 -10	; "ui"
	77	[254]	GETTABLE 	21 21 -11	; "document"
	78	[254]	SELF     	21 21 -23	; "getScreenBoxesFromPositions"
	79	[254]	MOVE     	23 15
	80	[254]	MOVE     	24 16
	81	[254]	LOADBOOL 	25 1 0
	82	[254]	CALL     	21 5 2
	83	[255]	TEST     	21 0 0
	84	[255]	JMP      	21	; to 106
	85	[256]	GETGLOBAL	22 -4	; pairs
	86	[256]	MOVE     	23 21
	87	[256]	CALL     	22 2 4
	88	[256]	JMP      	15	; to 104
	89	[257]	GETUPVAL 	27 0	; inside_box
	90	[257]	MOVE     	28 4
	91	[257]	MOVE     	29 26
	92	[257]	CALL     	27 3 2
	93	[257]	TEST     	27 0 0
	94	[257]	JMP      	9	; to 104
	95	[258]	GETUPVAL 	27 1	; logger
	96	[258]	GETTABLE 	27 27 -24	; "dbg"
	97	[258]	LOADK    	28 -25	; "Tap on highlight"
	98	[258]	CALL     	27 2 1
	99	[259]	SELF     	27 0 -26	; "onShowHighlightDialog"
	100	[259]	MOVE     	29 8
	101	[259]	MOVE     	30 14
	102	[259]	TAILCALL 	27 4 0
	103	[259]	RETURN   	27 0
	104	[256]	TFORLOOP 	22 2
	105	[260]	JMP      	-17	; to 89
	106	[234]	FORLOOP  	11 -86	; to 21
	107	[231]	TFORLOOP 	5 2
	108	[265]	JMP      	-98	; to 11
	109	[267]	RETURN   	0 1

function <./frontend/apps/reader/modules/readerhighlight.lua:269,353> (223 instructions, 892 bytes at 0x7f869cc0cc90)
6 params, 20 slots, 3 upvalues, 20 locals, 40 constants, 0 functions
	1	[270]	GETTABLE 	6 0 -1	; "ui"
	2	[270]	GETTABLE 	6 6 -2	; "document"
	3	[270]	GETTABLE 	6 6 -3	; "info"
	4	[270]	GETTABLE 	6 6 -4	; "has_pages"
	5	[270]	TEST     	6 0 0
	6	[270]	JMP      	1	; to 8
	7	[271]	RETURN   	0 1
	8	[274]	GETTABLE 	6 0 -5	; "view"
	9	[274]	GETTABLE 	6 6 -6	; "highlight"
	10	[274]	GETTABLE 	6 6 -7	; "saved"
	11	[274]	GETTABLE 	6 6 1
	12	[274]	GETTABLE 	6 6 2
	13	[275]	GETTABLE 	7 6 -8	; "datetime"
	14	[276]	GETTABLE 	8 6 -9	; "pos0"
	15	[277]	GETTABLE 	9 6 -10	; "pos1"
	16	[278]	EQ       	0 3 -11	; - 0
	17	[278]	JMP      	53	; to 71
	18	[279]	LOADNIL  	10 10
	19	[280]	EQ       	0 4 -12	; - 1
	20	[280]	JMP      	16	; to 37
	21	[281]	TEST     	5 0 0
	22	[281]	JMP      	7	; to 30
	23	[282]	GETTABLE 	11 0 -1	; "ui"
	24	[282]	GETTABLE 	11 11 -2	; "document"
	25	[282]	SELF     	11 11 -13	; "getNextVisibleChar"
	26	[282]	MOVE     	13 8
	27	[282]	CALL     	11 3 2
	28	[282]	MOVE     	10 11
	29	[282]	JMP      	22	; to 52
	30	[284]	GETTABLE 	11 0 -1	; "ui"
	31	[284]	GETTABLE 	11 11 -2	; "document"
	32	[284]	SELF     	11 11 -14	; "getNextVisibleWordStart"
	33	[284]	MOVE     	13 8
	34	[284]	CALL     	11 3 2
	35	[284]	MOVE     	10 11
	36	[285]	JMP      	15	; to 52
	37	[287]	TEST     	5 0 0
	38	[287]	JMP      	7	; to 46
	39	[288]	GETTABLE 	11 0 -1	; "ui"
	40	[288]	GETTABLE 	11 11 -2	; "document"
	41	[288]	SELF     	11 11 -15	; "getPrevVisibleChar"
	42	[288]	MOVE     	13 8
	43	[288]	CALL     	11 3 2
	44	[288]	MOVE     	10 11
	45	[288]	JMP      	6	; to 52
	46	[290]	GETTABLE 	11 0 -1	; "ui"
	47	[290]	GETTABLE 	11 11 -2	; "document"
	48	[290]	SELF     	11 11 -16	; "getPrevVisibleWordStart"
	49	[290]	MOVE     	13 8
	50	[290]	CALL     	11 3 2
	51	[290]	MOVE     	10 11
	52	[293]	TEST     	10 0 0
	53	[293]	JMP      	69	; to 123
	54	[294]	GETTABLE 	11 0 -1	; "ui"
	55	[294]	GETTABLE 	11 11 -2	; "document"
	56	[294]	SELF     	11 11 -17	; "compareXPointers"
	57	[294]	MOVE     	13 10
	58	[294]	MOVE     	14 9
	59	[294]	CALL     	11 4 2
	60	[295]	TEST     	11 0 0
	61	[295]	JMP      	61	; to 123
	62	[295]	LT       	0 -11 11	; 0 -
	63	[295]	JMP      	59	; to 123
	64	[296]	GETTABLE 	12 0 -5	; "view"
	65	[296]	GETTABLE 	12 12 -6	; "highlight"
	66	[296]	GETTABLE 	12 12 -7	; "saved"
	67	[296]	GETTABLE 	12 12 1
	68	[296]	GETTABLE 	12 12 2
	69	[296]	SETTABLE 	12 -9 10	; "pos0" -
	70	[298]	JMP      	52	; to 123
	71	[300]	LOADNIL  	10 10
	72	[301]	EQ       	0 4 -12	; - 1
	73	[301]	JMP      	16	; to 90
	74	[302]	TEST     	5 0 0
	75	[302]	JMP      	7	; to 83
	76	[303]	GETTABLE 	11 0 -1	; "ui"
	77	[303]	GETTABLE 	11 11 -2	; "document"
	78	[303]	SELF     	11 11 -13	; "getNextVisibleChar"
	79	[303]	MOVE     	13 9
	80	[303]	CALL     	11 3 2
	81	[303]	MOVE     	10 11
	82	[303]	JMP      	22	; to 105
	83	[305]	GETTABLE 	11 0 -1	; "ui"
	84	[305]	GETTABLE 	11 11 -2	; "document"
	85	[305]	SELF     	11 11 -18	; "getNextVisibleWordEnd"
	86	[305]	MOVE     	13 9
	87	[305]	CALL     	11 3 2
	88	[305]	MOVE     	10 11
	89	[306]	JMP      	15	; to 105
	90	[308]	TEST     	5 0 0
	91	[308]	JMP      	7	; to 99
	92	[309]	GETTABLE 	11 0 -1	; "ui"
	93	[309]	GETTABLE 	11 11 -2	; "document"
	94	[309]	SELF     	11 11 -15	; "getPrevVisibleChar"
	95	[309]	MOVE     	13 9
	96	[309]	CALL     	11 3 2
	97	[309]	MOVE     	10 11
	98	[309]	JMP      	6	; to 105
	99	[311]	GETTABLE 	11 0 -1	; "ui"
	100	[311]	GETTABLE 	11 11 -2	; "document"
	101	[311]	SELF     	11 11 -19	; "getPrevVisibleWordEnd"
	102	[311]	MOVE     	13 9
	103	[311]	CALL     	11 3 2
	104	[311]	MOVE     	10 11
	105	[314]	TEST     	10 0 0
	106	[314]	JMP      	16	; to 123
	107	[315]	GETTABLE 	11 0 -1	; "ui"
	108	[315]	GETTABLE 	11 11 -2	; "document"
	109	[315]	SELF     	11 11 -17	; "compareXPointers"
	110	[315]	MOVE     	13 8
	111	[315]	MOVE     	14 10
	112	[315]	CALL     	11 4 2
	113	[316]	TEST     	11 0 0
	114	[316]	JMP      	8	; to 123
	115	[316]	LT       	0 -11 11	; 0 -
	116	[316]	JMP      	6	; to 123
	117	[317]	GETTABLE 	12 0 -5	; "view"
	118	[317]	GETTABLE 	12 12 -6	; "highlight"
	119	[317]	GETTABLE 	12 12 -7	; "saved"
	120	[317]	GETTABLE 	12 12 1
	121	[317]	GETTABLE 	12 12 2
	122	[317]	SETTABLE 	12 -10 10	; "pos1" -
	123	[322]	GETTABLE 	10 0 -5	; "view"
	124	[322]	GETTABLE 	10 10 -6	; "highlight"
	125	[322]	GETTABLE 	10 10 -7	; "saved"
	126	[322]	GETTABLE 	10 10 1
	127	[322]	GETTABLE 	10 10 2
	128	[322]	GETTABLE 	10 10 -9	; "pos0"
	129	[323]	GETTABLE 	11 0 -5	; "view"
	130	[323]	GETTABLE 	11 11 -6	; "highlight"
	131	[323]	GETTABLE 	11 11 -7	; "saved"
	132	[323]	GETTABLE 	11 11 1
	133	[323]	GETTABLE 	11 11 2
	134	[323]	GETTABLE 	11 11 -10	; "pos1"
	135	[324]	GETTABLE 	12 0 -1	; "ui"
	136	[324]	GETTABLE 	12 12 -2	; "document"
	137	[324]	SELF     	12 12 -20	; "getTextFromXPointers"
	138	[324]	MOVE     	14 10
	139	[324]	MOVE     	15 11
	140	[324]	CALL     	12 4 2
	141	[325]	GETTABLE 	13 0 -5	; "view"
	142	[325]	GETTABLE 	13 13 -6	; "highlight"
	143	[325]	GETTABLE 	13 13 -7	; "saved"
	144	[325]	GETTABLE 	13 13 1
	145	[325]	GETTABLE 	13 13 2
	146	[325]	SETTABLE 	13 -21 12	; "text" -
	147	[326]	GETTABLE 	13 0 -5	; "view"
	148	[326]	GETTABLE 	13 13 -6	; "highlight"
	149	[326]	GETTABLE 	13 13 -7	; "saved"
	150	[326]	GETTABLE 	13 13 1
	151	[326]	GETTABLE 	13 13 2
	152	[327]	GETTABLE 	14 0 -1	; "ui"
	153	[327]	GETTABLE 	14 14 -22	; "bookmark"
	154	[327]	SELF     	14 14 -23	; "updateBookmark"
	155	[327]	NEWTABLE 	16 0 3
	156	[328]	SETTABLE 	16 -24 8	; "page" -
	157	[329]	SETTABLE 	16 -8 7	; "datetime" -
	158	[330]	SETTABLE 	16 -25 13	; "updated_highlight" -
	159	[331]	LOADBOOL 	17 1 0
	160	[327]	CALL     	14 4 1
	161	[332]	EQ       	0 3 -11	; - 0
	162	[332]	JMP      	16	; to 179
	163	[334]	GETTABLE 	14 0 -1	; "ui"
	164	[334]	GETTABLE 	14 14 -2	; "document"
	165	[334]	SELF     	14 14 -26	; "isXPointerInCurrentPage"
	166	[334]	MOVE     	16 10
	167	[334]	CALL     	14 3 2
	168	[334]	TEST     	14 0 1
	169	[334]	JMP      	48	; to 218
	170	[335]	GETTABLE 	14 0 -1	; "ui"
	171	[335]	SELF     	14 14 -27	; "handleEvent"
	172	[335]	GETUPVAL 	16 0	; Event
	173	[335]	SELF     	16 16 -28	; "new"
	174	[335]	LOADK    	18 -29	; "GotoXPointer"
	175	[335]	MOVE     	19 10
	176	[335]	CALL     	16 4 0
	177	[335]	CALL     	14 0 1
	178	[336]	JMP      	39	; to 218
	179	[339]	GETTABLE 	14 0 -1	; "ui"
	180	[339]	GETTABLE 	14 14 -2	; "document"
	181	[339]	SELF     	14 14 -26	; "isXPointerInCurrentPage"
	182	[339]	MOVE     	16 11
	183	[339]	CALL     	14 3 2
	184	[339]	TEST     	14 0 1
	185	[339]	JMP      	32	; to 218
	186	[340]	GETTABLE 	14 0 -5	; "view"
	187	[340]	GETTABLE 	14 14 -30	; "view_mode"
	188	[340]	EQ       	0 14 -24	; - "page"
	189	[340]	JMP      	9	; to 199
	190	[341]	GETTABLE 	14 0 -1	; "ui"
	191	[341]	SELF     	14 14 -27	; "handleEvent"
	192	[341]	GETUPVAL 	16 0	; Event
	193	[341]	SELF     	16 16 -28	; "new"
	194	[341]	LOADK    	18 -29	; "GotoXPointer"
	195	[341]	MOVE     	19 11
	196	[341]	CALL     	16 4 0
	197	[341]	CALL     	14 0 1
	198	[341]	JMP      	19	; to 218
	199	[346]	GETTABLE 	14 0 -1	; "ui"
	200	[346]	GETTABLE 	14 14 -2	; "document"
	201	[346]	SELF     	14 14 -31	; "getPosFromXPointer"
	202	[346]	MOVE     	16 11
	203	[346]	CALL     	14 3 2
	204	[347]	GETGLOBAL	15 -32	; math
	205	[347]	GETTABLE 	15 15 -33	; "floor"
	206	[347]	GETUPVAL 	16 1	; Screen
	207	[347]	SELF     	16 16 -34	; "getHeight"
	208	[347]	CALL     	16 2 2
	209	[347]	MUL      	16 16 -35	; - 2
	210	[347]	DIV      	16 16 -36	; - 3
	211	[347]	CALL     	15 2 2
	212	[347]	SUB      	15 14 15
	213	[348]	GETTABLE 	16 0 -1	; "ui"
	214	[348]	GETTABLE 	16 16 -37	; "rolling"
	215	[348]	SELF     	16 16 -38	; "_gotoPos"
	216	[348]	MOVE     	18 15
	217	[348]	CALL     	16 3 1
	218	[352]	GETUPVAL 	14 2	; UIManager
	219	[352]	SELF     	14 14 -39	; "setDirty"
	220	[352]	GETTABLE 	16 0 -40	; "dialog"
	221	[352]	LOADK    	17 -1	; "ui"
	222	[352]	CALL     	14 4 1
	223	[353]	RETURN   	0 1

function <./frontend/apps/reader/modules/readerhighlight.lua:355,441> (139 instructions, 556 bytes at 0x7f869cc090a0)
3 params, 16 slots, 4 upvalues, 8 locals, 22 constants, 11 functions
	1	[356]	NEWTABLE 	3 1 0
	2	[356]	NEWTABLE 	4 3 0
	3	[357]	NEWTABLE 	5 0 2
	4	[359]	GETUPVAL 	6 0	; _
	5	[359]	LOADK    	7 -2	; "Delete"
	6	[359]	CALL     	6 2 2
	7	[359]	SETTABLE 	5 -1 6	; "text" -
	8	[364]	CLOSURE  	6 0	; 0x7f869cc09ab0
	9	[364]	MOVE     	0 0
	10	[364]	MOVE     	0 1
	11	[364]	MOVE     	0 2
	12	[364]	GETUPVAL 	0 1	; UIManager
	13	[364]	SETTABLE 	5 -3 6	; "callback" -
	14	[365]	NEWTABLE 	6 0 2
	15	[367]	GETUPVAL 	7 0	; _
	16	[367]	LOADK    	8 -4	; "Edit"
	17	[367]	CALL     	7 2 2
	18	[367]	SETTABLE 	6 -1 7	; "text" -
	19	[371]	CLOSURE  	7 1	; 0x7f869cc0ab50
	20	[371]	MOVE     	0 0
	21	[371]	MOVE     	0 1
	22	[371]	MOVE     	0 2
	23	[371]	GETUPVAL 	0 1	; UIManager
	24	[371]	SETTABLE 	6 -3 7	; "callback" -
	25	[372]	NEWTABLE 	7 0 2
	26	[374]	GETUPVAL 	8 0	; _
	27	[374]	LOADK    	9 -5	; "\226\128\166"
	28	[374]	CALL     	8 2 2
	29	[374]	SETTABLE 	7 -1 8	; "text" -
	30	[379]	CLOSURE  	8 2	; 0x7f869cc0a7a0
	31	[379]	MOVE     	0 0
	32	[379]	MOVE     	0 1
	33	[379]	MOVE     	0 2
	34	[379]	GETUPVAL 	0 1	; UIManager
	35	[379]	SETTABLE 	7 -3 8	; "callback" -
	36	[381]	SETLIST  	4 3 1	; 1
	37	[382]	SETLIST  	3 1 1	; 1
	38	[384]	GETTABLE 	4 0 -6	; "ui"
	39	[384]	GETTABLE 	4 4 -7	; "document"
	40	[384]	GETTABLE 	4 4 -8	; "info"
	41	[384]	GETTABLE 	4 4 -9	; "has_pages"
	42	[384]	TEST     	4 0 1
	43	[384]	JMP      	83	; to 127
	44	[385]	LOADK    	4 -10	; "\226\151\129\226\135\177"
	45	[386]	LOADK    	5 -11	; "\226\135\177\226\150\183"
	46	[387]	LOADK    	6 -12	; "\226\151\129\226\135\178"
	47	[388]	LOADK    	7 -13	; "\226\135\178\226\150\183"
	48	[389]	GETUPVAL 	8 2	; BD
	49	[389]	GETTABLE 	8 8 -14	; "mirroredUILayout"
	50	[389]	CALL     	8 1 2
	51	[389]	TEST     	8 0 0
	52	[389]	JMP      	20	; to 73
	53	[392]	GETUPVAL 	8 2	; BD
	54	[392]	GETTABLE 	8 8 -15	; "ltr"
	55	[392]	MOVE     	9 5
	56	[392]	CALL     	8 2 2
	57	[392]	GETUPVAL 	9 2	; BD
	58	[392]	GETTABLE 	9 9 -15	; "ltr"
	59	[392]	MOVE     	10 4
	60	[392]	CALL     	9 2 2
	61	[392]	MOVE     	5 9
	62	[392]	MOVE     	4 8
	63	[393]	GETUPVAL 	8 2	; BD
	64	[393]	GETTABLE 	8 8 -15	; "ltr"
	65	[393]	MOVE     	9 7
	66	[393]	CALL     	8 2 2
	67	[393]	GETUPVAL 	9 2	; BD
	68	[393]	GETTABLE 	9 9 -15	; "ltr"
	69	[393]	MOVE     	10 6
	70	[393]	CALL     	9 2 2
	71	[393]	MOVE     	7 9
	72	[393]	MOVE     	6 8
	73	[395]	GETGLOBAL	8 -16	; table
	74	[395]	GETTABLE 	8 8 -17	; "insert"
	75	[395]	MOVE     	9 3
	76	[395]	NEWTABLE 	10 4 0
	77	[395]	NEWTABLE 	11 0 3
	78	[397]	SETTABLE 	11 -1 4	; "text" -
	79	[400]	CLOSURE  	12 3	; 0x7f869cc0d9d0
	80	[400]	MOVE     	0 0
	81	[400]	MOVE     	0 1
	82	[400]	MOVE     	0 2
	83	[400]	SETTABLE 	11 -3 12	; "callback" -
	84	[404]	CLOSURE  	12 4	; 0x7f869cc0d6d0
	85	[404]	MOVE     	0 0
	86	[404]	MOVE     	0 1
	87	[404]	MOVE     	0 2
	88	[404]	SETTABLE 	11 -18 12	; "hold_callback" -
	89	[405]	NEWTABLE 	12 0 3
	90	[407]	SETTABLE 	12 -1 5	; "text" -
	91	[410]	CLOSURE  	13 5	; 0x7f869cc0e560
	92	[410]	MOVE     	0 0
	93	[410]	MOVE     	0 1
	94	[410]	MOVE     	0 2
	95	[410]	SETTABLE 	12 -3 13	; "callback" -
	96	[414]	CLOSURE  	13 6	; 0x7f869cc0e980
	97	[414]	MOVE     	0 0
	98	[414]	MOVE     	0 1
	99	[414]	MOVE     	0 2
	100	[414]	SETTABLE 	12 -18 13	; "hold_callback" -
	101	[415]	NEWTABLE 	13 0 3
	102	[417]	SETTABLE 	13 -1 6	; "text" -
	103	[420]	CLOSURE  	14 7	; 0x7f869cc0ec60
	104	[420]	MOVE     	0 0
	105	[420]	MOVE     	0 1
	106	[420]	MOVE     	0 2
	107	[420]	SETTABLE 	13 -3 14	; "callback" -
	108	[423]	CLOSURE  	14 8	; 0x7f869cc0ef80
	109	[423]	MOVE     	0 0
	110	[423]	MOVE     	0 1
	111	[423]	MOVE     	0 2
	112	[423]	SETTABLE 	13 -18 14	; "hold_callback" -
	113	[424]	NEWTABLE 	14 0 3
	114	[426]	SETTABLE 	14 -1 7	; "text" -
	115	[429]	CLOSURE  	15 9	; 0x7f869cc0f2c0
	116	[429]	MOVE     	0 0
	117	[429]	MOVE     	0 1
	118	[429]	MOVE     	0 2
	119	[429]	SETTABLE 	14 -3 15	; "callback" -
	120	[432]	CLOSURE  	15 10	; 0x7f869cc0f520
	121	[432]	MOVE     	0 0
	122	[432]	MOVE     	0 1
	123	[432]	MOVE     	0 2
	124	[432]	SETTABLE 	14 -18 15	; "hold_callback" -
	125	[434]	SETLIST  	10 4 1	; 1
	126	[395]	CALL     	8 3 1
	127	[436]	GETUPVAL 	4 3	; ButtonDialog
	128	[436]	SELF     	4 4 -20	; "new"
	129	[436]	NEWTABLE 	6 0 1
	130	[437]	SETTABLE 	6 -21 3	; "buttons" -
	131	[436]	CALL     	4 3 2
	132	[438]	SETTABLE 	0 -19 4	; "edit_highlight_dialog" -
	133	[439]	GETUPVAL 	4 1	; UIManager
	134	[439]	SELF     	4 4 -22	; "show"
	135	[439]	GETTABLE 	6 0 -19	; "edit_highlight_dialog"
	136	[439]	CALL     	4 3 1
	137	[440]	LOADBOOL 	4 1 0
	138	[440]	RETURN   	4 2
	139	[441]	RETURN   	0 1

function <./frontend/apps/reader/modules/readerhighlight.lua:360,364> (12 instructions, 48 bytes at 0x7f869cc09ab0)
0 params, 4 slots, 4 upvalues, 0 locals, 4 constants, 0 functions
	1	[361]	GETUPVAL 	0 0	; self
	2	[361]	SELF     	0 0 -1	; "deleteHighlight"
	3	[361]	GETUPVAL 	2 1	; page
	4	[361]	GETUPVAL 	3 2	; index
	5	[361]	CALL     	0 4 1
	6	[363]	GETUPVAL 	0 3	; UIManager
	7	[363]	SELF     	0 0 -2	; "close"
	8	[363]	GETUPVAL 	2 0	; self
	9	[363]	GETTABLE 	2 2 -3	; "edit_highlight_dialog"
	10	[363]	LOADK    	3 -4	; "ui"
	11	[363]	CALL     	0 4 1
	12	[364]	RETURN   	0 1

function <./frontend/apps/reader/modules/readerhighlight.lua:368,371> (11 instructions, 44 bytes at 0x7f869cc0ab50)
0 params, 4 slots, 4 upvalues, 0 locals, 3 constants, 0 functions
	1	[369]	GETUPVAL 	0 0	; self
	2	[369]	SELF     	0 0 -1	; "editHighlight"
	3	[369]	GETUPVAL 	2 1	; page
	4	[369]	GETUPVAL 	3 2	; index
	5	[369]	CALL     	0 4 1
	6	[370]	GETUPVAL 	0 3	; UIManager
	7	[370]	SELF     	0 0 -2	; "close"
	8	[370]	GETUPVAL 	2 0	; self
	9	[370]	GETTABLE 	2 2 -3	; "edit_highlight_dialog"
	10	[370]	CALL     	0 3 1
	11	[371]	RETURN   	0 1

function <./frontend/apps/reader/modules/readerhighlight.lua:375,379> (19 instructions, 76 bytes at 0x7f869cc0a7a0)
0 params, 3 slots, 4 upvalues, 0 locals, 7 constants, 0 functions
	1	[376]	GETUPVAL 	0 0	; self
	2	[376]	GETUPVAL 	1 0	; self
	3	[376]	GETTABLE 	1 1 -2	; "view"
	4	[376]	GETTABLE 	1 1 -3	; "highlight"
	5	[376]	GETTABLE 	1 1 -4	; "saved"
	6	[376]	GETUPVAL 	2 1	; page
	7	[376]	GETTABLE 	1 1 2
	8	[376]	GETUPVAL 	2 2	; index
	9	[376]	GETTABLE 	1 1 2
	10	[376]	SETTABLE 	0 -1 1	; "selected_text" -
	11	[377]	GETUPVAL 	0 0	; self
	12	[377]	SELF     	0 0 -5	; "onShowHighlightMenu"
	13	[377]	CALL     	0 2 1
	14	[378]	GETUPVAL 	0 3	; UIManager
	15	[378]	SELF     	0 0 -6	; "close"
	16	[378]	GETUPVAL 	2 0	; self
	17	[378]	GETTABLE 	2 2 -7	; "edit_highlight_dialog"
	18	[378]	CALL     	0 3 1
	19	[379]	RETURN   	0 1

function <./frontend/apps/reader/modules/readerhighlight.lua:398,400> (9 instructions, 36 bytes at 0x7f869cc0d9d0)
0 params, 7 slots, 3 upvalues, 0 locals, 3 constants, 0 functions
	1	[399]	GETUPVAL 	0 0	; self
	2	[399]	SELF     	0 0 -1	; "updateHighlight"
	3	[399]	GETUPVAL 	2 1	; page
	4	[399]	GETUPVAL 	3 2	; index
	5	[399]	LOADK    	4 -2	; 0
	6	[399]	LOADK    	5 -3	; -1
	7	[399]	LOADBOOL 	6 0 0
	8	[399]	CALL     	0 7 1
	9	[400]	RETURN   	0 1

function <./frontend/apps/reader/modules/readerhighlight.lua:401,404> (11 instructions, 44 bytes at 0x7f869cc0d6d0)
0 params, 7 slots, 3 upvalues, 0 locals, 3 constants, 0 functions
	1	[402]	GETUPVAL 	0 0	; self
	2	[402]	SELF     	0 0 -1	; "updateHighlight"
	3	[402]	GETUPVAL 	2 1	; page
	4	[402]	GETUPVAL 	3 2	; index
	5	[402]	LOADK    	4 -2	; 0
	6	[402]	LOADK    	5 -3	; -1
	7	[402]	LOADBOOL 	6 1 0
	8	[402]	CALL     	0 7 1
	9	[403]	LOADBOOL 	0 1 0
	10	[403]	RETURN   	0 2
	11	[404]	RETURN   	0 1

function <./frontend/apps/reader/modules/readerhighlight.lua:408,410> (9 instructions, 36 bytes at 0x7f869cc0e560)
0 params, 7 slots, 3 upvalues, 0 locals, 3 constants, 0 functions
	1	[409]	GETUPVAL 	0 0	; self
	2	[409]	SELF     	0 0 -1	; "updateHighlight"
	3	[409]	GETUPVAL 	2 1	; page
	4	[409]	GETUPVAL 	3 2	; index
	5	[409]	LOADK    	4 -2	; 0
	6	[409]	LOADK    	5 -3	; 1
	7	[409]	LOADBOOL 	6 0 0
	8	[409]	CALL     	0 7 1
	9	[410]	RETURN   	0 1

function <./frontend/apps/reader/modules/readerhighlight.lua:411,414> (11 instructions, 44 bytes at 0x7f869cc0e980)
0 params, 7 slots, 3 upvalues, 0 locals, 3 constants, 0 functions
	1	[412]	GETUPVAL 	0 0	; self
	2	[412]	SELF     	0 0 -1	; "updateHighlight"
	3	[412]	GETUPVAL 	2 1	; page
	4	[412]	GETUPVAL 	3 2	; index
	5	[412]	LOADK    	4 -2	; 0
	6	[412]	LOADK    	5 -3	; 1
	7	[412]	LOADBOOL 	6 1 0
	8	[412]	CALL     	0 7 1
	9	[413]	LOADBOOL 	0 1 0
	10	[413]	RETURN   	0 2
	11	[414]	RETURN   	0 1

function <./frontend/apps/reader/modules/readerhighlight.lua:418,420> (9 instructions, 36 bytes at 0x7f869cc0ec60)
0 params, 7 slots, 3 upvalues, 0 locals, 3 constants, 0 functions
	1	[419]	GETUPVAL 	0 0	; self
	2	[419]	SELF     	0 0 -1	; "updateHighlight"
	3	[419]	GETUPVAL 	2 1	; page
	4	[419]	GETUPVAL 	3 2	; index
	5	[419]	LOADK    	4 -2	; 1
	6	[419]	LOADK    	5 -3	; -1
	7	[419]	LOADBOOL 	6 0 0
	8	[419]	CALL     	0 7 1
	9	[420]	RETURN   	0 1

function <./frontend/apps/reader/modules/readerhighlight.lua:421,423> (9 instructions, 36 bytes at 0x7f869cc0ef80)
0 params, 7 slots, 3 upvalues, 0 locals, 3 constants, 0 functions
	1	[422]	GETUPVAL 	0 0	; self
	2	[422]	SELF     	0 0 -1	; "updateHighlight"
	3	[422]	GETUPVAL 	2 1	; page
	4	[422]	GETUPVAL 	3 2	; index
	5	[422]	LOADK    	4 -2	; 1
	6	[422]	LOADK    	5 -3	; -1
	7	[422]	LOADBOOL 	6 1 0
	8	[422]	CALL     	0 7 1
	9	[423]	RETURN   	0 1

function <./frontend/apps/reader/modules/readerhighlight.lua:427,429> (9 instructions, 36 bytes at 0x7f869cc0f2c0)
0 params, 7 slots, 3 upvalues, 0 locals, 2 constants, 0 functions
	1	[428]	GETUPVAL 	0 0	; self
	2	[428]	SELF     	0 0 -1	; "updateHighlight"
	3	[428]	GETUPVAL 	2 1	; page
	4	[428]	GETUPVAL 	3 2	; index
	5	[428]	LOADK    	4 -2	; 1
	6	[428]	LOADK    	5 -2	; 1
	7	[428]	LOADBOOL 	6 0 0
	8	[428]	CALL     	0 7 1
	9	[429]	RETURN   	0 1

function <./frontend/apps/reader/modules/readerhighlight.lua:430,432> (9 instructions, 36 bytes at 0x7f869cc0f520)
0 params, 7 slots, 3 upvalues, 0 locals, 2 constants, 0 functions
	1	[431]	GETUPVAL 	0 0	; self
	2	[431]	SELF     	0 0 -1	; "updateHighlight"
	3	[431]	GETUPVAL 	2 1	; page
	4	[431]	GETUPVAL 	3 2	; index
	5	[431]	LOADK    	4 -2	; 1
	6	[431]	LOADK    	5 -2	; 1
	7	[431]	LOADBOOL 	6 1 0
	8	[431]	CALL     	0 7 1
	9	[432]	RETURN   	0 1

function <./frontend/apps/reader/modules/readerhighlight.lua:443,551> (152 instructions, 608 bytes at 0x7f869cc0f860)
1 param, 10 slots, 6 upvalues, 2 locals, 30 constants, 11 functions
	1	[444]	NEWTABLE 	1 4 0
	2	[444]	NEWTABLE 	2 2 0
	3	[445]	NEWTABLE 	3 0 3
	4	[447]	GETUPVAL 	4 0	; _
	5	[447]	LOADK    	5 -2	; "Highlight"
	6	[447]	CALL     	4 2 2
	7	[447]	SETTABLE 	3 -1 4	; "text" -
	8	[451]	CLOSURE  	4 0	; 0x7f869cc0df90
	9	[451]	MOVE     	0 0
	10	[451]	SETTABLE 	3 -3 4	; "callback" -
	11	[452]	GETTABLE 	4 0 -5	; "hold_pos"
	12	[452]	EQ       	0 4 -6	; - nil
	13	[452]	JMP      	1	; to 15
	14	[452]	LOADBOOL 	4 0 1
	15	[452]	LOADBOOL 	4 1 0
	16	[452]	SETTABLE 	3 -4 4	; "enabled" -
	17	[453]	NEWTABLE 	4 0 3
	18	[455]	GETUPVAL 	5 0	; _
	19	[455]	LOADK    	6 -7	; "Add Note"
	20	[455]	CALL     	5 2 2
	21	[455]	SETTABLE 	4 -1 5	; "text" -
	22	[459]	CLOSURE  	5 1	; 0x7f869cc0fde0
	23	[459]	MOVE     	0 0
	24	[459]	SETTABLE 	4 -3 5	; "callback" -
	25	[460]	GETTABLE 	5 0 -5	; "hold_pos"
	26	[460]	EQ       	0 5 -6	; - nil
	27	[460]	JMP      	1	; to 29
	28	[460]	LOADBOOL 	5 0 1
	29	[460]	LOADBOOL 	5 1 0
	30	[460]	SETTABLE 	4 -4 5	; "enabled" -
	31	[462]	SETLIST  	2 2 1	; 1
	32	[462]	NEWTABLE 	3 2 0
	33	[463]	NEWTABLE 	4 0 3
	34	[465]	GETUPVAL 	5 1	; C_
	35	[465]	LOADK    	6 -8	; "Text"
	36	[465]	LOADK    	7 -9	; "Copy"
	37	[465]	CALL     	5 3 2
	38	[465]	SETTABLE 	4 -1 5	; "text" -
	39	[466]	GETUPVAL 	5 2	; Device
	40	[466]	SELF     	5 5 -10	; "hasClipboard"
	41	[466]	CALL     	5 2 2
	42	[466]	SETTABLE 	4 -4 5	; "enabled" -
	43	[469]	CLOSURE  	5 2	; 0x7f869cc0e180
	44	[469]	GETUPVAL 	0 2	; Device
	45	[469]	MOVE     	0 0
	46	[469]	SETTABLE 	4 -3 5	; "callback" -
	47	[470]	NEWTABLE 	5 0 3
	48	[472]	GETUPVAL 	6 0	; _
	49	[472]	LOADK    	7 -11	; "View HTML"
	50	[472]	CALL     	6 2 2
	51	[472]	SETTABLE 	5 -1 6	; "text" -
	52	[473]	GETTABLE 	6 0 -12	; "ui"
	53	[473]	GETTABLE 	6 6 -13	; "document"
	54	[473]	GETTABLE 	6 6 -14	; "info"
	55	[473]	GETTABLE 	6 6 -15	; "has_pages"
	56	[473]	NOT      	6 6
	57	[473]	SETTABLE 	5 -4 6	; "enabled" -
	58	[476]	CLOSURE  	6 3	; 0x7f869cc0fd00
	59	[476]	MOVE     	0 0
	60	[476]	SETTABLE 	5 -3 6	; "callback" -
	61	[478]	SETLIST  	3 2 1	; 1
	62	[478]	NEWTABLE 	4 2 0
	63	[479]	NEWTABLE 	5 0 2
	64	[481]	GETUPVAL 	6 0	; _
	65	[481]	LOADK    	7 -16	; "Wikipedia"
	66	[481]	CALL     	6 2 2
	67	[481]	SETTABLE 	5 -1 6	; "text" -
	68	[489]	CLOSURE  	6 4	; 0x7f869cc0ff90
	69	[489]	GETUPVAL 	0 3	; UIManager
	70	[489]	MOVE     	0 0
	71	[489]	SETTABLE 	5 -3 6	; "callback" -
	72	[490]	NEWTABLE 	6 0 2
	73	[492]	GETUPVAL 	7 0	; _
	74	[492]	LOADK    	8 -17	; "Dictionary"
	75	[492]	CALL     	7 2 2
	76	[492]	SETTABLE 	6 -1 7	; "text" -
	77	[496]	CLOSURE  	7 5	; 0x7f869cc100c0
	78	[496]	MOVE     	0 0
	79	[496]	SETTABLE 	6 -3 7	; "callback" -
	80	[498]	SETLIST  	4 2 1	; 1
	81	[498]	NEWTABLE 	5 2 0
	82	[499]	NEWTABLE 	6 0 2
	83	[501]	GETUPVAL 	7 0	; _
	84	[501]	LOADK    	8 -18	; "Translate"
	85	[501]	CALL     	7 2 2
	86	[501]	SETTABLE 	6 -1 7	; "text" -
	87	[509]	CLOSURE  	7 6	; 0x7f869cc10e70
	88	[509]	MOVE     	0 0
	89	[509]	SETTABLE 	6 -3 7	; "callback" -
	90	[510]	NEWTABLE 	7 0 2
	91	[512]	GETUPVAL 	8 0	; _
	92	[512]	LOADK    	9 -19	; "Search"
	93	[512]	CALL     	8 2 2
	94	[512]	SETTABLE 	7 -1 8	; "text" -
	95	[516]	CLOSURE  	8 7	; 0x7f869cc11030
	96	[516]	MOVE     	0 0
	97	[516]	GETUPVAL 	0 3	; UIManager
	98	[516]	SETTABLE 	7 -3 8	; "callback" -
	99	[518]	SETLIST  	5 2 1	; 1
	100	[519]	SETLIST  	1 4 1	; 1
	101	[520]	GETTABLE 	2 0 -20	; "selected_link"
	102	[520]	EQ       	1 2 -6	; - nil
	103	[520]	JMP      	14	; to 118
	104	[521]	GETGLOBAL	2 -21	; table
	105	[521]	GETTABLE 	2 2 -22	; "insert"
	106	[521]	MOVE     	3 1
	107	[521]	NEWTABLE 	4 1 0
	108	[521]	NEWTABLE 	5 0 2
	109	[523]	GETUPVAL 	6 0	; _
	110	[523]	LOADK    	7 -23	; "Follow Link"
	111	[523]	CALL     	6 2 2
	112	[523]	SETTABLE 	5 -1 6	; "text" -
	113	[528]	CLOSURE  	6 8	; 0x7f869cc113f0
	114	[528]	MOVE     	0 0
	115	[528]	SETTABLE 	5 -3 6	; "callback" -
	116	[530]	SETLIST  	4 1 1	; 1
	117	[521]	CALL     	2 3 1
	118	[532]	GETUPVAL 	2 2	; Device
	119	[532]	SELF     	2 2 -24	; "canShareText"
	120	[532]	CALL     	2 2 2
	121	[532]	TEST     	2 0 0
	122	[532]	JMP      	15	; to 138
	123	[533]	GETGLOBAL	2 -21	; table
	124	[533]	GETTABLE 	2 2 -22	; "insert"
	125	[533]	MOVE     	3 1
	126	[533]	NEWTABLE 	4 1 0
	127	[533]	NEWTABLE 	5 0 2
	128	[535]	GETUPVAL 	6 0	; _
	129	[535]	LOADK    	7 -25	; "Share text"
	130	[535]	CALL     	6 2 2
	131	[535]	SETTABLE 	5 -1 6	; "text" -
	132	[541]	CLOSURE  	6 9	; 0x7f869cc10460
	133	[541]	MOVE     	0 0
	134	[541]	GETUPVAL 	0 2	; Device
	135	[541]	SETTABLE 	5 -3 6	; "callback" -
	136	[543]	SETLIST  	4 1 1	; 1
	137	[533]	CALL     	2 3 1
	138	[546]	GETUPVAL 	2 4	; ButtonDialog
	139	[546]	SELF     	2 2 -27	; "new"
	140	[546]	NEWTABLE 	4 0 2
	141	[547]	SETTABLE 	4 -28 1	; "buttons" -
	142	[548]	CLOSURE  	5 10	; 0x7f869cc10750
	143	[548]	MOVE     	0 0
	144	[548]	GETUPVAL 	0 5	; Event
	145	[548]	SETTABLE 	4 -29 5	; "tap_close_callback" -
	146	[546]	CALL     	2 3 2
	147	[549]	SETTABLE 	0 -26 2	; "highlight_dialog" -
	148	[550]	GETUPVAL 	2 3	; UIManager
	149	[550]	SELF     	2 2 -30	; "show"
	150	[550]	GETTABLE 	4 0 -26	; "highlight_dialog"
	151	[550]	CALL     	2 3 1
	152	[551]	RETURN   	0 1

function <./frontend/apps/reader/modules/readerhighlight.lua:448,451> (7 instructions, 28 bytes at 0x7f869cc0df90)
0 params, 2 slots, 1 upvalue, 0 locals, 2 constants, 0 functions
	1	[449]	GETUPVAL 	0 0	; self
	2	[449]	SELF     	0 0 -1	; "saveHighlight"
	3	[449]	CALL     	0 2 1
	4	[450]	GETUPVAL 	0 0	; self
	5	[450]	SELF     	0 0 -2	; "onClose"
	6	[450]	CALL     	0 2 1
	7	[451]	RETURN   	0 1

function <./frontend/apps/reader/modules/readerhighlight.lua:456,459> (7 instructions, 28 bytes at 0x7f869cc0fde0)
0 params, 2 slots, 1 upvalue, 0 locals, 2 constants, 0 functions
	1	[457]	GETUPVAL 	0 0	; self
	2	[457]	SELF     	0 0 -1	; "addNote"
	3	[457]	CALL     	0 2 1
	4	[458]	GETUPVAL 	0 0	; self
	5	[458]	SELF     	0 0 -2	; "onClose"
	6	[458]	CALL     	0 2 1
	7	[459]	RETURN   	0 1

function <./frontend/apps/reader/modules/readerhighlight.lua:467,469> (8 instructions, 32 bytes at 0x7f869cc0e180)
0 params, 2 slots, 2 upvalues, 0 locals, 4 constants, 0 functions
	1	[468]	GETUPVAL 	0 0	; Device
	2	[468]	GETTABLE 	0 0 -1	; "input"
	3	[468]	GETTABLE 	0 0 -2	; "setClipboardText"
	4	[468]	GETUPVAL 	1 1	; self
	5	[468]	GETTABLE 	1 1 -3	; "selected_text"
	6	[468]	GETTABLE 	1 1 -4	; "text"
	7	[468]	CALL     	0 2 1
	8	[469]	RETURN   	0 1

function <./frontend/apps/reader/modules/readerhighlight.lua:474,476> (4 instructions, 16 bytes at 0x7f869cc0fd00)
0 params, 2 slots, 1 upvalue, 0 locals, 1 constant, 0 functions
	1	[475]	GETUPVAL 	0 0	; self
	2	[475]	SELF     	0 0 -1	; "viewSelectionHTML"
	3	[475]	CALL     	0 2 1
	4	[476]	RETURN   	0 1

function <./frontend/apps/reader/modules/readerhighlight.lua:482,489> (7 instructions, 28 bytes at 0x7f869cc0ff90)
0 params, 4 slots, 2 upvalues, 0 locals, 2 constants, 1 function
	1	[483]	GETUPVAL 	0 0	; UIManager
	2	[483]	SELF     	0 0 -1	; "scheduleIn"
	3	[483]	LOADK    	2 -2	; 0.1
	4	[488]	CLOSURE  	3 0	; 0x7f869cc10860
	5	[488]	GETUPVAL 	0 1	; self
	6	[483]	CALL     	0 4 1
	7	[489]	RETURN   	0 1

function <./frontend/apps/reader/modules/readerhighlight.lua:483,488> (4 instructions, 16 bytes at 0x7f869cc10860)
0 params, 2 slots, 1 upvalue, 0 locals, 1 constant, 0 functions
	1	[484]	GETUPVAL 	0 0	; self
	2	[484]	SELF     	0 0 -1	; "lookupWikipedia"
	3	[484]	CALL     	0 2 1
	4	[488]	RETURN   	0 1

function <./frontend/apps/reader/modules/readerhighlight.lua:493,496> (4 instructions, 16 bytes at 0x7f869cc100c0)
0 params, 2 slots, 1 upvalue, 0 locals, 1 constant, 0 functions
	1	[494]	GETUPVAL 	0 0	; self
	2	[494]	SELF     	0 0 -1	; "onHighlightDictLookup"
	3	[494]	CALL     	0 2 1
	4	[496]	RETURN   	0 1

function <./frontend/apps/reader/modules/readerhighlight.lua:502,509> (6 instructions, 24 bytes at 0x7f869cc10e70)
0 params, 3 slots, 1 upvalue, 0 locals, 2 constants, 0 functions
	1	[503]	GETUPVAL 	0 0	; self
	2	[503]	SELF     	0 0 -1	; "translate"
	3	[503]	GETUPVAL 	2 0	; self
	4	[503]	GETTABLE 	2 2 -2	; "selected_text"
	5	[503]	CALL     	0 3 1
	6	[509]	RETURN   	0 1

function <./frontend/apps/reader/modules/readerhighlight.lua:513,516> (9 instructions, 36 bytes at 0x7f869cc11030)
0 params, 3 slots, 2 upvalues, 0 locals, 3 constants, 0 functions
	1	[514]	GETUPVAL 	0 0	; self
	2	[514]	SELF     	0 0 -1	; "onHighlightSearch"
	3	[514]	CALL     	0 2 1
	4	[515]	GETUPVAL 	0 1	; UIManager
	5	[515]	SELF     	0 0 -2	; "close"
	6	[515]	GETUPVAL 	2 0	; self
	7	[515]	GETTABLE 	2 2 -3	; "highlight_dialog"
	8	[515]	CALL     	0 3 1
	9	[516]	RETURN   	0 1

function <./frontend/apps/reader/modules/readerhighlight.lua:524,528> (17 instructions, 68 bytes at 0x7f869cc113f0)
0 params, 4 slots, 1 upvalue, 1 local, 5 constants, 0 functions
	1	[525]	GETUPVAL 	0 0	; self
	2	[525]	GETTABLE 	0 0 -1	; "selected_link"
	3	[525]	GETTABLE 	0 0 -2	; "link"
	4	[525]	TEST     	0 0 1
	5	[525]	JMP      	2	; to 8
	6	[525]	GETUPVAL 	0 0	; self
	7	[525]	GETTABLE 	0 0 -1	; "selected_link"
	8	[526]	GETUPVAL 	1 0	; self
	9	[526]	GETTABLE 	1 1 -3	; "ui"
	10	[526]	GETTABLE 	1 1 -2	; "link"
	11	[526]	SELF     	1 1 -4	; "onGotoLink"
	12	[526]	MOVE     	3 0
	13	[526]	CALL     	1 3 1
	14	[527]	GETUPVAL 	1 0	; self
	15	[527]	SELF     	1 1 -5	; "onClose"
	16	[527]	CALL     	1 2 1
	17	[528]	RETURN   	0 1

function <./frontend/apps/reader/modules/readerhighlight.lua:536,541> (11 instructions, 44 bytes at 0x7f869cc10460)
0 params, 3 slots, 2 upvalues, 1 local, 4 constants, 0 functions
	1	[537]	GETUPVAL 	0 0	; self
	2	[537]	GETTABLE 	0 0 -1	; "selected_text"
	3	[537]	GETTABLE 	0 0 -2	; "text"
	4	[539]	GETUPVAL 	1 0	; self
	5	[539]	SELF     	1 1 -3	; "onClose"
	6	[539]	CALL     	1 2 1
	7	[540]	GETUPVAL 	1 1	; Device
	8	[540]	GETTABLE 	1 1 -4	; "doShareText"
	9	[540]	MOVE     	2 0
	10	[540]	CALL     	1 2 1
	11	[541]	RETURN   	0 1

function <./frontend/apps/reader/modules/readerhighlight.lua:548,548> (8 instructions, 32 bytes at 0x7f869cc10750)
0 params, 5 slots, 2 upvalues, 0 locals, 3 constants, 0 functions
	1	[548]	GETUPVAL 	0 0	; self
	2	[548]	SELF     	0 0 -1	; "handleEvent"
	3	[548]	GETUPVAL 	2 1	; Event
	4	[548]	SELF     	2 2 -2	; "new"
	5	[548]	LOADK    	4 -3	; "Tap"
	6	[548]	CALL     	2 3 0
	7	[548]	CALL     	0 0 1
	8	[548]	RETURN   	0 1

function <./frontend/apps/reader/modules/readerhighlight.lua:553,559> (9 instructions, 36 bytes at 0x7f869cc11ad0)
2 params, 3 slots, 1 upvalue, 2 locals, 3 constants, 0 functions
	1	[554]	TEST     	1 0 0
	2	[554]	JMP      	2	; to 5
	3	[555]	SETTABLE 	0 -1 -2	; "hold_last_tv" nil
	4	[555]	JMP      	4	; to 9
	5	[557]	GETUPVAL 	2 0	; TimeVal
	6	[557]	GETTABLE 	2 2 -3	; "now"
	7	[557]	CALL     	2 1 2
	8	[557]	SETTABLE 	0 -1 2	; "hold_last_tv" -
	9	[559]	RETURN   	0 1

function <./frontend/apps/reader/modules/readerhighlight.lua:561,621> (125 instructions, 500 bytes at 0x7f869cc0fef0)
3 params, 11 slots, 2 upvalues, 10 locals, 45 constants, 0 functions
	1	[563]	GETTABLE 	3 0 -1	; "view"
	2	[563]	GETTABLE 	3 3 -2	; "highlight"
	3	[563]	GETTABLE 	3 3 -3	; "disabled"
	4	[563]	TEST     	3 0 0
	5	[563]	JMP      	2	; to 8
	6	[563]	LOADBOOL 	3 0 0
	7	[563]	RETURN   	3 2
	8	[564]	SELF     	3 0 -4	; "clear"
	9	[564]	CALL     	3 2 1
	10	[565]	GETTABLE 	3 2 -6	; "pos"
	11	[565]	SETTABLE 	0 -5 3	; "hold_ges_pos" -
	12	[566]	GETTABLE 	3 0 -1	; "view"
	13	[566]	SELF     	3 3 -8	; "screenToPageTransform"
	14	[566]	GETTABLE 	5 2 -6	; "pos"
	15	[566]	CALL     	3 3 2
	16	[566]	SETTABLE 	0 -7 3	; "hold_pos" -
	17	[567]	GETUPVAL 	3 0	; logger
	18	[567]	GETTABLE 	3 3 -9	; "dbg"
	19	[567]	LOADK    	4 -10	; "hold position in page"
	20	[567]	GETTABLE 	5 0 -7	; "hold_pos"
	21	[567]	CALL     	3 3 1
	22	[568]	GETTABLE 	3 0 -7	; "hold_pos"
	23	[568]	TEST     	3 0 1
	24	[568]	JMP      	6	; to 31
	25	[569]	GETUPVAL 	3 0	; logger
	26	[569]	GETTABLE 	3 3 -9	; "dbg"
	27	[569]	LOADK    	4 -11	; "not inside page area"
	28	[569]	CALL     	3 2 1
	29	[570]	LOADBOOL 	3 0 0
	30	[570]	RETURN   	3 2
	31	[576]	GETTABLE 	3 0 -12	; "ui"
	32	[576]	GETTABLE 	3 3 -13	; "document"
	33	[576]	SELF     	3 3 -14	; "getImageFromPosition"
	34	[576]	GETTABLE 	5 0 -7	; "hold_pos"
	35	[576]	LOADBOOL 	6 1 0
	36	[576]	CALL     	3 4 2
	37	[577]	TEST     	3 0 0
	38	[577]	JMP      	19	; to 58
	39	[578]	GETUPVAL 	4 0	; logger
	40	[578]	GETTABLE 	4 4 -9	; "dbg"
	41	[578]	LOADK    	5 -15	; "hold on image"
	42	[578]	CALL     	4 2 1
	43	[579]	GETGLOBAL	4 -16	; require
	44	[579]	LOADK    	5 -17	; "ui/widget/imageviewer"
	45	[579]	CALL     	4 2 2
	46	[580]	SELF     	5 4 -18	; "new"
	47	[580]	NEWTABLE 	7 0 3
	48	[581]	SETTABLE 	7 -19 3	; "image" -
	49	[584]	SETTABLE 	7 -20 -21	; "with_title_bar" false
	50	[585]	SETTABLE 	7 -22 -23	; "fullscreen" true
	51	[580]	CALL     	5 3 2
	52	[587]	GETUPVAL 	6 1	; UIManager
	53	[587]	SELF     	6 6 -24	; "show"
	54	[587]	MOVE     	8 5
	55	[587]	CALL     	6 3 1
	56	[588]	LOADBOOL 	6 1 0
	57	[588]	RETURN   	6 2
	58	[592]	GETGLOBAL	4 -25	; pcall
	59	[592]	GETTABLE 	5 0 -12	; "ui"
	60	[592]	GETTABLE 	5 5 -13	; "document"
	61	[592]	GETTABLE 	5 5 -26	; "getWordFromPosition"
	62	[592]	GETTABLE 	6 0 -12	; "ui"
	63	[592]	GETTABLE 	6 6 -13	; "document"
	64	[592]	GETTABLE 	7 0 -7	; "hold_pos"
	65	[592]	CALL     	4 4 3
	66	[593]	TEST     	4 0 0
	67	[593]	JMP      	55	; to 123
	68	[593]	TEST     	5 0 0
	69	[593]	JMP      	53	; to 123
	70	[594]	GETUPVAL 	6 0	; logger
	71	[594]	GETTABLE 	6 6 -9	; "dbg"
	72	[594]	LOADK    	7 -27	; "selected word:"
	73	[594]	MOVE     	8 5
	74	[594]	CALL     	6 3 1
	75	[595]	SETTABLE 	0 -28 5	; "selected_word" -
	76	[596]	GETTABLE 	6 0 -12	; "ui"
	77	[596]	GETTABLE 	6 6 -29	; "link"
	78	[596]	SELF     	6 6 -30	; "getLinkFromGes"
	79	[596]	MOVE     	8 2
	80	[596]	CALL     	6 3 2
	81	[597]	SETTABLE 	0 -31 -32	; "selected_link" nil
	82	[598]	TEST     	6 0 0
	83	[598]	JMP      	6	; to 90
	84	[599]	GETUPVAL 	7 0	; logger
	85	[599]	GETTABLE 	7 7 -9	; "dbg"
	86	[599]	LOADK    	8 -33	; "link:"
	87	[599]	MOVE     	9 6
	88	[599]	CALL     	7 3 1
	89	[600]	SETTABLE 	0 -31 6	; "selected_link" -
	90	[602]	GETTABLE 	7 0 -12	; "ui"
	91	[602]	GETTABLE 	7 7 -13	; "document"
	92	[602]	GETTABLE 	7 7 -34	; "info"
	93	[602]	GETTABLE 	7 7 -35	; "has_pages"
	94	[602]	TEST     	7 0 0
	95	[602]	JMP      	13	; to 109
	96	[603]	NEWTABLE 	7 0 0
	97	[604]	GETGLOBAL	8 -36	; table
	98	[604]	GETTABLE 	8 8 -37	; "insert"
	99	[604]	MOVE     	9 7
	100	[604]	GETTABLE 	10 0 -28	; "selected_word"
	101	[604]	GETTABLE 	10 10 -38	; "sbox"
	102	[604]	CALL     	8 3 1
	103	[605]	GETTABLE 	8 0 -1	; "view"
	104	[605]	GETTABLE 	8 8 -2	; "highlight"
	105	[605]	GETTABLE 	8 8 -39	; "temp"
	106	[605]	GETTABLE 	9 0 -7	; "hold_pos"
	107	[605]	GETTABLE 	9 9 -40	; "page"
	108	[605]	SETTABLE 	8 9 7
	109	[607]	GETUPVAL 	7 1	; UIManager
	110	[607]	SELF     	7 7 -41	; "setDirty"
	111	[607]	GETTABLE 	9 0 -42	; "dialog"
	112	[607]	LOADK    	10 -12	; "ui"
	113	[607]	CALL     	7 4 1
	114	[611]	SELF     	7 0 -43	; "_resetHoldTimer"
	115	[611]	CALL     	7 2 1
	116	[612]	GETTABLE 	7 5 -44	; "pos0"
	117	[612]	TEST     	7 0 0
	118	[612]	JMP      	2	; to 121
	119	[616]	GETTABLE 	7 5 -44	; "pos0"
	120	[616]	SETTABLE 	0 -45 7	; "selected_text_start_xpointer" -
	121	[618]	LOADBOOL 	7 1 0
	122	[618]	RETURN   	7 2
	123	[620]	LOADBOOL 	6 0 0
	124	[620]	RETURN   	6 2
	125	[621]	RETURN   	0 1

function <./frontend/apps/reader/modules/readerhighlight.lua:623,769> (392 instructions, 1568 bytes at 0x7f869cc0b9f0)
3 params, 15 slots, 5 upvalues, 16 locals, 62 constants, 2 functions
	1	[624]	GETTABLE 	3 0 -1	; "hold_pos"
	2	[624]	EQ       	0 3 -2	; - nil
	3	[624]	JMP      	9	; to 13
	4	[625]	GETUPVAL 	3 0	; logger
	5	[625]	GETTABLE 	3 3 -3	; "dbg"
	6	[625]	LOADK    	4 -4	; "no previous hold position"
	7	[625]	CALL     	3 2 1
	8	[626]	SELF     	3 0 -5	; "_resetHoldTimer"
	9	[626]	LOADBOOL 	5 1 0
	10	[626]	CALL     	3 3 1
	11	[627]	LOADBOOL 	3 1 0
	12	[627]	RETURN   	3 2
	13	[629]	GETTABLE 	3 0 -6	; "view"
	14	[629]	SELF     	3 3 -7	; "getScreenPageArea"
	15	[629]	GETTABLE 	5 0 -1	; "hold_pos"
	16	[629]	GETTABLE 	5 5 -8	; "page"
	17	[629]	CALL     	3 3 2
	18	[630]	GETTABLE 	4 2 -9	; "pos"
	19	[630]	SELF     	4 4 -10	; "notIntersectWith"
	20	[630]	MOVE     	6 3
	21	[630]	CALL     	4 3 2
	22	[630]	TEST     	4 0 0
	23	[630]	JMP      	10	; to 34
	24	[631]	GETUPVAL 	4 0	; logger
	25	[631]	GETTABLE 	4 4 -3	; "dbg"
	26	[631]	LOADK    	5 -11	; "not inside page area"
	27	[631]	MOVE     	6 2
	28	[631]	MOVE     	7 3
	29	[631]	CALL     	4 4 1
	30	[632]	SELF     	4 0 -5	; "_resetHoldTimer"
	31	[632]	CALL     	4 2 1
	32	[633]	LOADBOOL 	4 1 0
	33	[633]	RETURN   	4 2
	34	[636]	GETTABLE 	4 0 -6	; "view"
	35	[636]	SELF     	4 4 -13	; "screenToPageTransform"
	36	[636]	GETTABLE 	6 2 -9	; "pos"
	37	[636]	CALL     	4 3 2
	38	[636]	SETTABLE 	0 -12 4	; "holdpan_pos" -
	39	[637]	GETUPVAL 	4 0	; logger
	40	[637]	GETTABLE 	4 4 -3	; "dbg"
	41	[637]	LOADK    	5 -14	; "holdpan position in page"
	42	[637]	GETTABLE 	6 0 -12	; "holdpan_pos"
	43	[637]	CALL     	4 3 1
	44	[639]	GETTABLE 	4 0 -15	; "ui"
	45	[639]	GETTABLE 	4 4 -16	; "document"
	46	[639]	GETTABLE 	4 4 -17	; "info"
	47	[639]	GETTABLE 	4 4 -18	; "has_pages"
	48	[639]	TEST     	4 0 1
	49	[639]	JMP      	255	; to 305
	50	[639]	GETTABLE 	4 0 -19	; "selected_text_start_xpointer"
	51	[639]	TEST     	4 0 0
	52	[639]	JMP      	252	; to 305
	53	[643]	GETUPVAL 	4 1	; BD
	54	[643]	GETTABLE 	4 4 -20	; "mirroredUILayout"
	55	[643]	CALL     	4 1 2
	56	[644]	GETTABLE 	5 0 -15	; "ui"
	57	[644]	GETTABLE 	5 5 -21	; "rolling"
	58	[644]	TEST     	5 0 0
	59	[644]	JMP      	6	; to 66
	60	[644]	GETTABLE 	5 0 -15	; "ui"
	61	[644]	GETTABLE 	5 5 -21	; "rolling"
	62	[644]	GETTABLE 	5 5 -22	; "inverse_reading_order"
	63	[644]	TEST     	5 0 0
	64	[644]	JMP      	1	; to 66
	65	[645]	NOT      	4 4
	66	[647]	LOADNIL  	5 6
	67	[648]	TEST     	4 0 0
	68	[648]	JMP      	37	; to 106
	69	[652]	GETTABLE 	7 0 -12	; "holdpan_pos"
	70	[652]	GETTABLE 	7 7 -23	; "y"
	71	[652]	GETUPVAL 	8 2	; Screen
	72	[652]	SELF     	8 8 -24	; "getHeight"
	73	[652]	CALL     	8 2 2
	74	[652]	MUL      	8 -25 8	; 0.125 -
	75	[652]	LT       	0 7 8
	76	[652]	JMP      	8	; to 85
	77	[653]	GETTABLE 	7 0 -12	; "holdpan_pos"
	78	[653]	GETTABLE 	7 7 -26	; "x"
	79	[653]	GETUPVAL 	8 2	; Screen
	80	[653]	SELF     	8 8 -27	; "getWidth"
	81	[653]	CALL     	8 2 2
	82	[653]	MUL      	8 -28 8	; 0.875 -
	83	[653]	LT       	1 8 7
	84	[653]	JMP      	1	; to 86
	85	[653]	LOADBOOL 	5 0 1
	86	[653]	LOADBOOL 	5 1 0
	87	[655]	GETTABLE 	7 0 -12	; "holdpan_pos"
	88	[655]	GETTABLE 	7 7 -23	; "y"
	89	[655]	GETUPVAL 	8 2	; Screen
	90	[655]	SELF     	8 8 -24	; "getHeight"
	91	[655]	CALL     	8 2 2
	92	[655]	MUL      	8 -28 8	; 0.875 -
	93	[655]	LT       	0 8 7
	94	[655]	JMP      	8	; to 103
	95	[656]	GETTABLE 	7 0 -12	; "holdpan_pos"
	96	[656]	GETTABLE 	7 7 -26	; "x"
	97	[656]	GETUPVAL 	8 2	; Screen
	98	[656]	SELF     	8 8 -27	; "getWidth"
	99	[656]	CALL     	8 2 2
	100	[656]	MUL      	8 -25 8	; 0.125 -
	101	[656]	LT       	1 7 8
	102	[656]	JMP      	1	; to 104
	103	[656]	LOADBOOL 	6 0 1
	104	[656]	LOADBOOL 	6 1 0
	105	[656]	JMP      	36	; to 142
	106	[659]	GETTABLE 	7 0 -12	; "holdpan_pos"
	107	[659]	GETTABLE 	7 7 -23	; "y"
	108	[659]	GETUPVAL 	8 2	; Screen
	109	[659]	SELF     	8 8 -24	; "getHeight"
	110	[659]	CALL     	8 2 2
	111	[659]	MUL      	8 -25 8	; 0.125 -
	112	[659]	LT       	0 7 8
	113	[659]	JMP      	8	; to 122
	114	[660]	GETTABLE 	7 0 -12	; "holdpan_pos"
	115	[660]	GETTABLE 	7 7 -26	; "x"
	116	[660]	GETUPVAL 	8 2	; Screen
	117	[660]	SELF     	8 8 -27	; "getWidth"
	118	[660]	CALL     	8 2 2
	119	[660]	MUL      	8 -25 8	; 0.125 -
	120	[660]	LT       	1 7 8
	121	[660]	JMP      	1	; to 123
	122	[660]	LOADBOOL 	5 0 1
	123	[660]	LOADBOOL 	5 1 0
	124	[662]	GETTABLE 	7 0 -12	; "holdpan_pos"
	125	[662]	GETTABLE 	7 7 -23	; "y"
	126	[662]	GETUPVAL 	8 2	; Screen
	127	[662]	SELF     	8 8 -24	; "getHeight"
	128	[662]	CALL     	8 2 2
	129	[662]	MUL      	8 -28 8	; 0.875 -
	130	[662]	LT       	0 8 7
	131	[662]	JMP      	8	; to 140
	132	[663]	GETTABLE 	7 0 -12	; "holdpan_pos"
	133	[663]	GETTABLE 	7 7 -26	; "x"
	134	[663]	GETUPVAL 	8 2	; Screen
	135	[663]	SELF     	8 8 -27	; "getWidth"
	136	[663]	CALL     	8 2 2
	137	[663]	MUL      	8 -28 8	; 0.875 -
	138	[663]	LT       	1 8 7
	139	[663]	JMP      	1	; to 141
	140	[663]	LOADBOOL 	6 0 1
	141	[663]	LOADBOOL 	6 1 0
	142	[665]	TEST     	5 0 1
	143	[665]	JMP      	2	; to 146
	144	[665]	TEST     	6 0 0
	145	[665]	JMP      	158	; to 304
	146	[666]	SELF     	7 0 -5	; "_resetHoldTimer"
	147	[666]	CALL     	7 2 1
	148	[667]	GETTABLE 	7 0 -29	; "was_in_some_corner"
	149	[667]	TEST     	7 0 0
	150	[667]	JMP      	2	; to 153
	151	[669]	LOADBOOL 	7 1 0
	152	[669]	RETURN   	7 2
	153	[671]	SETTABLE 	0 -29 -30	; "was_in_some_corner" true
	154	[672]	GETTABLE 	7 0 -15	; "ui"
	155	[672]	GETTABLE 	7 7 -16	; "document"
	156	[672]	SELF     	7 7 -31	; "getVisiblePageCount"
	157	[672]	CALL     	7 2 2
	158	[672]	EQ       	0 7 -32	; - 1
	159	[672]	JMP      	68	; to 228
	160	[675]	GETTABLE 	7 0 -15	; "ui"
	161	[675]	GETTABLE 	7 7 -16	; "document"
	162	[675]	SELF     	7 7 -33	; "getScreenPositionFromXPointer"
	163	[675]	GETTABLE 	9 0 -19	; "selected_text_start_xpointer"
	164	[675]	CALL     	7 3 2
	165	[676]	GETTABLE 	8 0 -6	; "view"
	166	[676]	GETTABLE 	8 8 -34	; "view_mode"
	167	[676]	EQ       	1 8 -35	; - "scroll"
	168	[676]	JMP      	18	; to 187
	169	[678]	GETTABLE 	8 0 -15	; "ui"
	170	[678]	GETTABLE 	8 8 -16	; "document"
	171	[678]	SELF     	8 8 -36	; "getXPointer"
	172	[678]	CALL     	8 2 2
	173	[682]	CLOSURE  	9 0	; 0x7f869cc0f3c0
	174	[682]	MOVE     	0 0
	175	[682]	GETUPVAL 	0 3	; Event
	176	[682]	MOVE     	0 8
	177	[682]	SETTABLE 	0 -37 9	; "restore_page_mode_func" -
	178	[683]	GETTABLE 	9 0 -15	; "ui"
	179	[683]	SELF     	9 9 -38	; "handleEvent"
	180	[683]	GETUPVAL 	11 3	; Event
	181	[683]	SELF     	11 11 -39	; "new"
	182	[683]	LOADK    	13 -40	; "SetViewMode"
	183	[683]	LOADK    	14 -35	; "scroll"
	184	[683]	CALL     	11 4 0
	185	[683]	CALL     	9 0 1
	186	[683]	CLOSE    	8
	187	[686]	GETGLOBAL	8 -41	; math
	188	[686]	GETTABLE 	8 8 -42	; "floor"
	189	[686]	GETUPVAL 	9 2	; Screen
	190	[686]	SELF     	9 9 -24	; "getHeight"
	191	[686]	CALL     	9 2 2
	192	[686]	MUL      	9 9 -32	; - 1
	193	[686]	DIV      	9 9 -43	; - 3
	194	[686]	CALL     	8 2 2
	195	[687]	TEST     	6 0 0
	196	[687]	JMP      	2	; to 199
	197	[687]	TESTSET  	9 8 1
	198	[687]	JMP      	1	; to 200
	199	[687]	UNM      	9 8
	200	[688]	GETTABLE 	10 0 -15	; "ui"
	201	[688]	GETTABLE 	10 10 -21	; "rolling"
	202	[688]	SELF     	10 10 -44	; "_gotoPos"
	203	[688]	GETTABLE 	12 0 -15	; "ui"
	204	[688]	GETTABLE 	12 12 -16	; "document"
	205	[688]	SELF     	12 12 -45	; "getCurrentPos"
	206	[688]	CALL     	12 2 2
	207	[688]	ADD      	12 12 9
	208	[688]	CALL     	10 3 1
	209	[689]	GETTABLE 	10 0 -15	; "ui"
	210	[689]	GETTABLE 	10 10 -16	; "document"
	211	[689]	SELF     	10 10 -33	; "getScreenPositionFromXPointer"
	212	[689]	GETTABLE 	12 0 -19	; "selected_text_start_xpointer"
	213	[689]	CALL     	10 3 2
	214	[690]	GETTABLE 	11 0 -1	; "hold_pos"
	215	[690]	GETTABLE 	12 0 -1	; "hold_pos"
	216	[690]	GETTABLE 	12 12 -23	; "y"
	217	[690]	SUB      	12 12 7
	218	[690]	ADD      	12 12 10
	219	[690]	SETTABLE 	11 -23 12	; "y" -
	220	[691]	GETUPVAL 	11 4	; UIManager
	221	[691]	SELF     	11 11 -46	; "setDirty"
	222	[691]	GETTABLE 	13 0 -47	; "dialog"
	223	[691]	LOADK    	14 -15	; "ui"
	224	[691]	CALL     	11 4 1
	225	[692]	LOADBOOL 	11 1 0
	226	[692]	RETURN   	11 2
	227	[692]	JMP      	77	; to 305
	228	[703]	GETTABLE 	7 0 -37	; "restore_page_mode_func"
	229	[703]	TEST     	7 0 0
	230	[703]	JMP      	2	; to 233
	231	[704]	LOADBOOL 	7 1 0
	232	[704]	RETURN   	7 2
	233	[709]	GETGLOBAL	7 -41	; math
	234	[709]	GETTABLE 	7 7 -42	; "floor"
	235	[709]	GETUPVAL 	8 2	; Screen
	236	[709]	SELF     	8 8 -27	; "getWidth"
	237	[709]	CALL     	8 2 2
	238	[709]	MUL      	8 8 -32	; - 1
	239	[709]	DIV      	8 8 -48	; - 2
	240	[709]	CALL     	7 2 2
	241	[710]	GETTABLE 	8 0 -1	; "hold_pos"
	242	[710]	GETTABLE 	8 8 -26	; "x"
	243	[710]	LE       	0 7 8
	244	[710]	JMP      	5	; to 250
	245	[710]	TEST     	5 0 0
	246	[710]	JMP      	3	; to 250
	247	[711]	LOADBOOL 	8 1 0
	248	[711]	RETURN   	8 2
	249	[711]	JMP      	8	; to 258
	250	[712]	GETTABLE 	8 0 -1	; "hold_pos"
	251	[712]	GETTABLE 	8 8 -26	; "x"
	252	[712]	LE       	0 8 7
	253	[712]	JMP      	4	; to 258
	254	[712]	TEST     	6 0 0
	255	[712]	JMP      	2	; to 258
	256	[713]	LOADBOOL 	8 1 0
	257	[713]	RETURN   	8 2
	258	[715]	GETTABLE 	8 0 -15	; "ui"
	259	[715]	GETTABLE 	8 8 -16	; "document"
	260	[715]	SELF     	8 8 -49	; "getCurrentPage"
	261	[715]	CALL     	8 2 2
	262	[716]	GETTABLE 	9 0 -15	; "ui"
	263	[716]	GETTABLE 	9 9 -16	; "document"
	264	[716]	SELF     	9 9 -36	; "getXPointer"
	265	[716]	CALL     	9 2 2
	266	[719]	CLOSURE  	10 1	; 0x7f869cc0ea20
	267	[719]	MOVE     	0 0
	268	[719]	MOVE     	0 9
	269	[719]	SETTABLE 	0 -37 10	; "restore_page_mode_func" -
	270	[720]	TEST     	6 0 0
	271	[720]	JMP      	12	; to 284
	272	[721]	GETTABLE 	10 0 -15	; "ui"
	273	[721]	GETTABLE 	10 10 -21	; "rolling"
	274	[721]	SELF     	10 10 -50	; "_gotoPage"
	275	[721]	ADD      	12 8 -32	; - 1
	276	[721]	LOADBOOL 	13 1 0
	277	[721]	CALL     	10 4 1
	278	[722]	GETTABLE 	10 0 -1	; "hold_pos"
	279	[722]	GETTABLE 	11 0 -1	; "hold_pos"
	280	[722]	GETTABLE 	11 11 -26	; "x"
	281	[722]	SUB      	11 11 7
	282	[722]	SETTABLE 	10 -26 11	; "x" -
	283	[722]	JMP      	11	; to 295
	284	[724]	GETTABLE 	10 0 -15	; "ui"
	285	[724]	GETTABLE 	10 10 -21	; "rolling"
	286	[724]	SELF     	10 10 -50	; "_gotoPage"
	287	[724]	SUB      	12 8 -32	; - 1
	288	[724]	LOADBOOL 	13 1 0
	289	[724]	CALL     	10 4 1
	290	[725]	GETTABLE 	10 0 -1	; "hold_pos"
	291	[725]	GETTABLE 	11 0 -1	; "hold_pos"
	292	[725]	GETTABLE 	11 11 -26	; "x"
	293	[725]	ADD      	11 11 7
	294	[725]	SETTABLE 	10 -26 11	; "x" -
	295	[727]	GETUPVAL 	10 4	; UIManager
	296	[727]	SELF     	10 10 -46	; "setDirty"
	297	[727]	GETTABLE 	12 0 -47	; "dialog"
	298	[727]	LOADK    	13 -15	; "ui"
	299	[727]	CALL     	10 4 1
	300	[728]	LOADBOOL 	10 1 0
	301	[728]	RETURN   	10 2
	302	[728]	CLOSE    	7
	303	[729]	JMP      	1	; to 305
	304	[731]	SETTABLE 	0 -29 -2	; "was_in_some_corner" nil
	305	[735]	GETTABLE 	4 0 -51	; "selected_text"
	306	[735]	TEST     	4 0 0
	307	[735]	JMP      	2	; to 310
	308	[735]	GETTABLE 	4 0 -51	; "selected_text"
	309	[735]	GETTABLE 	4 4 -52	; "text"
	310	[736]	GETTABLE 	5 0 -15	; "ui"
	311	[736]	GETTABLE 	5 5 -16	; "document"
	312	[736]	SELF     	5 5 -53	; "getTextFromPositions"
	313	[736]	GETTABLE 	7 0 -1	; "hold_pos"
	314	[736]	GETTABLE 	8 0 -12	; "holdpan_pos"
	315	[736]	CALL     	5 4 2
	316	[736]	SETTABLE 	0 -51 5	; "selected_text" -
	317	[738]	GETTABLE 	5 0 -51	; "selected_text"
	318	[738]	TEST     	5 0 0
	319	[738]	JMP      	10	; to 330
	320	[738]	GETTABLE 	5 0 -51	; "selected_text"
	321	[738]	GETTABLE 	5 5 -54	; "pos0"
	322	[738]	TEST     	5 0 0
	323	[738]	JMP      	6	; to 330
	324	[739]	GETTABLE 	5 0 -19	; "selected_text_start_xpointer"
	325	[739]	TEST     	5 0 1
	326	[739]	JMP      	3	; to 330
	327	[748]	GETTABLE 	5 0 -51	; "selected_text"
	328	[748]	GETTABLE 	5 5 -54	; "pos0"
	329	[748]	SETTABLE 	0 -19 5	; "selected_text_start_xpointer" -
	330	[752]	GETTABLE 	5 0 -51	; "selected_text"
	331	[752]	TEST     	5 0 0
	332	[752]	JMP      	7	; to 340
	333	[752]	TEST     	4 0 0
	334	[752]	JMP      	5	; to 340
	335	[752]	GETTABLE 	5 0 -51	; "selected_text"
	336	[752]	GETTABLE 	5 5 -52	; "text"
	337	[752]	EQ       	0 4 5
	338	[752]	JMP      	1	; to 340
	339	[754]	RETURN   	0 1
	340	[756]	SELF     	5 0 -5	; "_resetHoldTimer"
	341	[756]	CALL     	5 2 1
	342	[757]	GETUPVAL 	5 0	; logger
	343	[757]	GETTABLE 	5 5 -3	; "dbg"
	344	[757]	LOADK    	6 -55	; "selected text:"
	345	[757]	GETTABLE 	7 0 -51	; "selected_text"
	346	[757]	CALL     	5 3 1
	347	[758]	GETTABLE 	5 0 -51	; "selected_text"
	348	[758]	TEST     	5 0 0
	349	[758]	JMP      	37	; to 387
	350	[759]	GETTABLE 	5 0 -6	; "view"
	351	[759]	GETTABLE 	5 5 -56	; "highlight"
	352	[759]	GETTABLE 	5 5 -57	; "temp"
	353	[759]	GETTABLE 	6 0 -1	; "hold_pos"
	354	[759]	GETTABLE 	6 6 -8	; "page"
	355	[759]	GETTABLE 	7 0 -51	; "selected_text"
	356	[759]	GETTABLE 	7 7 -58	; "sboxes"
	357	[759]	SETTABLE 	5 6 7
	358	[761]	GETTABLE 	5 0 -51	; "selected_text"
	359	[761]	GETTABLE 	5 5 -58	; "sboxes"
	360	[761]	TEST     	5 0 0
	361	[761]	JMP      	5	; to 367
	362	[761]	GETTABLE 	5 0 -51	; "selected_text"
	363	[761]	GETTABLE 	5 5 -58	; "sboxes"
	364	[761]	LEN      	5 5
	365	[761]	EQ       	0 5 -59	; - 0
	366	[761]	JMP      	2	; to 369
	367	[762]	SETTABLE 	0 -60 -2	; "selected_word" nil
	368	[762]	JMP      	18	; to 387
	369	[763]	GETTABLE 	5 0 -60	; "selected_word"
	370	[763]	TEST     	5 0 0
	371	[763]	JMP      	9	; to 381
	372	[763]	GETTABLE 	5 0 -60	; "selected_word"
	373	[763]	GETTABLE 	5 5 -61	; "sbox"
	374	[763]	SELF     	5 5 -62	; "contains"
	375	[763]	GETTABLE 	7 0 -51	; "selected_text"
	376	[763]	GETTABLE 	7 7 -58	; "sboxes"
	377	[763]	GETTABLE 	7 7 -32	; 1
	378	[763]	CALL     	5 3 2
	379	[763]	TEST     	5 0 0
	380	[763]	JMP      	5	; to 386
	381	[764]	GETTABLE 	5 0 -51	; "selected_text"
	382	[764]	GETTABLE 	5 5 -58	; "sboxes"
	383	[764]	LEN      	5 5
	384	[764]	LT       	0 -32 5	; 1 -
	385	[764]	JMP      	1	; to 387
	386	[765]	SETTABLE 	0 -60 -2	; "selected_word" nil
	387	[768]	GETUPVAL 	5 4	; UIManager
	388	[768]	SELF     	5 5 -46	; "setDirty"
	389	[768]	GETTABLE 	7 0 -47	; "dialog"
	390	[768]	LOADK    	8 -15	; "ui"
	391	[768]	CALL     	5 4 1
	392	[769]	RETURN   	0 1

function <./frontend/apps/reader/modules/readerhighlight.lua:679,682> (18 instructions, 72 bytes at 0x7f869cc0f3c0)
0 params, 6 slots, 3 upvalues, 0 locals, 8 constants, 0 functions
	1	[680]	GETUPVAL 	0 0	; self
	2	[680]	GETTABLE 	0 0 -1	; "ui"
	3	[680]	SELF     	0 0 -2	; "handleEvent"
	4	[680]	GETUPVAL 	2 1	; Event
	5	[680]	SELF     	2 2 -3	; "new"
	6	[680]	LOADK    	4 -4	; "SetViewMode"
	7	[680]	LOADK    	5 -5	; "page"
	8	[680]	CALL     	2 4 0
	9	[680]	CALL     	0 0 1
	10	[681]	GETUPVAL 	0 0	; self
	11	[681]	GETTABLE 	0 0 -1	; "ui"
	12	[681]	GETTABLE 	0 0 -6	; "rolling"
	13	[681]	SELF     	0 0 -7	; "onGotoXPointer"
	14	[681]	GETUPVAL 	2 2	; restore_page_mode_xpointer
	15	[681]	GETUPVAL 	3 0	; self
	16	[681]	GETTABLE 	3 3 -8	; "selected_text_start_xpointer"
	17	[681]	CALL     	0 4 1
	18	[682]	RETURN   	0 1

function <./frontend/apps/reader/modules/readerhighlight.lua:717,719> (9 instructions, 36 bytes at 0x7f869cc0ea20)
0 params, 4 slots, 2 upvalues, 0 locals, 4 constants, 0 functions
	1	[718]	GETUPVAL 	0 0	; self
	2	[718]	GETTABLE 	0 0 -1	; "ui"
	3	[718]	GETTABLE 	0 0 -2	; "rolling"
	4	[718]	SELF     	0 0 -3	; "onGotoXPointer"
	5	[718]	GETUPVAL 	2 1	; restore_page_mode_xpointer
	6	[718]	GETUPVAL 	3 0	; self
	7	[718]	GETTABLE 	3 3 -4	; "selected_text_start_xpointer"
	8	[718]	CALL     	0 4 1
	9	[719]	RETURN   	0 1

function <./frontend/apps/reader/modules/readerhighlight.lua:780,798> (71 instructions, 284 bytes at 0x7f869cc0ded0)
3 params, 14 slots, 5 upvalues, 6 locals, 17 constants, 0 functions
	1	[782]	GETTABLE 	3 1 -1	; "word"
	2	[782]	TEST     	3 0 0
	3	[782]	JMP      	18	; to 22
	4	[783]	GETTABLE 	3 0 -2	; "view"
	5	[783]	SELF     	3 3 -3	; "pageToScreenTransform"
	6	[783]	GETTABLE 	5 0 -4	; "hold_pos"
	7	[783]	GETTABLE 	5 5 -5	; "page"
	8	[783]	GETTABLE 	6 1 -6	; "sbox"
	9	[783]	CALL     	3 4 2
	10	[784]	GETTABLE 	4 0 -7	; "ui"
	11	[784]	SELF     	4 4 -8	; "handleEvent"
	12	[784]	GETUPVAL 	6 0	; Event
	13	[784]	SELF     	6 6 -9	; "new"
	14	[784]	LOADK    	8 -10	; "LookupWord"
	15	[784]	GETTABLE 	9 1 -1	; "word"
	16	[784]	MOVE     	10 3
	17	[784]	MOVE     	11 0
	18	[784]	MOVE     	12 2
	19	[784]	CALL     	6 7 0
	20	[784]	CALL     	4 0 1
	21	[784]	JMP      	49	; to 71
	22	[786]	GETTABLE 	3 1 -6	; "sbox"
	23	[786]	TEST     	3 0 0
	24	[786]	JMP      	46	; to 71
	25	[786]	GETTABLE 	3 0 -4	; "hold_pos"
	26	[786]	TEST     	3 0 0
	27	[786]	JMP      	43	; to 71
	28	[787]	GETTABLE 	3 0 -7	; "ui"
	29	[787]	GETTABLE 	3 3 -11	; "document"
	30	[787]	SELF     	3 3 -12	; "getOCRWord"
	31	[787]	GETTABLE 	5 0 -4	; "hold_pos"
	32	[787]	GETTABLE 	5 5 -5	; "page"
	33	[787]	MOVE     	6 1
	34	[787]	CALL     	3 4 2
	35	[788]	GETUPVAL 	4 1	; logger
	36	[788]	GETTABLE 	4 4 -13	; "dbg"
	37	[788]	LOADK    	5 -14	; "OCRed word:"
	38	[788]	MOVE     	6 3
	39	[788]	CALL     	4 3 1
	40	[789]	TEST     	3 0 0
	41	[789]	JMP      	20	; to 62
	42	[789]	EQ       	1 3 -15	; - ""
	43	[789]	JMP      	18	; to 62
	44	[790]	GETTABLE 	4 0 -2	; "view"
	45	[790]	SELF     	4 4 -3	; "pageToScreenTransform"
	46	[790]	GETTABLE 	6 0 -4	; "hold_pos"
	47	[790]	GETTABLE 	6 6 -5	; "page"
	48	[790]	GETTABLE 	7 1 -6	; "sbox"
	49	[790]	CALL     	4 4 2
	50	[791]	GETTABLE 	5 0 -7	; "ui"
	51	[791]	SELF     	5 5 -8	; "handleEvent"
	52	[791]	GETUPVAL 	7 0	; Event
	53	[791]	SELF     	7 7 -9	; "new"
	54	[791]	LOADK    	9 -10	; "LookupWord"
	55	[791]	MOVE     	10 3
	56	[791]	MOVE     	11 4
	57	[791]	MOVE     	12 0
	58	[791]	MOVE     	13 2
	59	[791]	CALL     	7 7 0
	60	[791]	CALL     	5 0 1
	61	[791]	JMP      	9	; to 71
	62	[793]	GETUPVAL 	4 2	; UIManager
	63	[793]	SELF     	4 4 -16	; "show"
	64	[793]	GETUPVAL 	6 3	; InfoMessage
	65	[793]	SELF     	6 6 -9	; "new"
	66	[793]	NEWTABLE 	8 0 1
	67	[794]	GETUPVAL 	9 4	; info_message_ocr_text
	68	[794]	SETTABLE 	8 -17 9	; "text" -
	69	[793]	CALL     	6 3 0
	70	[793]	CALL     	4 0 1
	71	[798]	RETURN   	0 1

function <./frontend/apps/reader/modules/readerhighlight.lua:800,822> (42 instructions, 168 bytes at 0x7f869cc11d60)
1 param, 5 slots, 0 upvalues, 1 local, 15 constants, 1 function
	1	[803]	SELF     	1 0 -1	; "gsub"
	2	[803]	LOADK    	3 -2	; "\t"
	3	[803]	LOADK    	4 -3	; " "
	4	[803]	CALL     	1 4 2
	5	[803]	MOVE     	0 1
	6	[805]	SELF     	1 0 -1	; "gsub"
	7	[805]	LOADK    	3 -4	; "%s*{%s*"
	8	[805]	LOADK    	4 -5	; " {\n    "
	9	[805]	CALL     	1 4 2
	10	[805]	MOVE     	0 1
	11	[806]	SELF     	1 0 -1	; "gsub"
	12	[806]	LOADK    	3 -6	; ";%s*}%s*"
	13	[806]	LOADK    	4 -7	; ";\n}\n"
	14	[806]	CALL     	1 4 2
	15	[806]	MOVE     	0 1
	16	[807]	SELF     	1 0 -1	; "gsub"
	17	[807]	LOADK    	3 -8	; ";%s*([^}])"
	18	[807]	LOADK    	4 -9	; ";\n    %1"
	19	[807]	CALL     	1 4 2
	20	[807]	MOVE     	0 1
	21	[808]	SELF     	1 0 -1	; "gsub"
	22	[808]	LOADK    	3 -10	; "%s*}%s*"
	23	[808]	LOADK    	4 -11	; "\n}\n"
	24	[808]	CALL     	1 4 2
	25	[808]	MOVE     	0 1
	26	[810]	SELF     	1 0 -1	; "gsub"
	27	[810]	LOADK    	3 -12	; "{[^}]*}"
	28	[816]	CLOSURE  	4 0	; 0x7f869cc126c0
	29	[810]	CALL     	1 4 2
	30	[816]	MOVE     	0 1
	31	[818]	SELF     	1 0 -1	; "gsub"
	32	[818]	LOADK    	3 -13	; "%s*,%s*"
	33	[818]	LOADK    	4 -14	; " ,\n"
	34	[818]	CALL     	1 4 2
	35	[818]	MOVE     	0 1
	36	[820]	SELF     	1 0 -1	; "gsub"
	37	[820]	LOADK    	3 -2	; "\t"
	38	[820]	LOADK    	4 -15	; ", "
	39	[820]	CALL     	1 4 2
	40	[820]	MOVE     	0 1
	41	[821]	RETURN   	0 2
	42	[822]	RETURN   	0 1

function <./frontend/apps/reader/modules/readerhighlight.lua:810,816> (12 instructions, 48 bytes at 0x7f869cc126c0)
1 param, 5 slots, 0 upvalues, 1 local, 5 constants, 0 functions
	1	[811]	SELF     	1 0 -1	; "gsub"
	2	[811]	LOADK    	3 -2	; "%s*:%s*"
	3	[811]	LOADK    	4 -3	; ": "
	4	[811]	CALL     	1 4 2
	5	[811]	MOVE     	0 1
	6	[814]	SELF     	1 0 -1	; "gsub"
	7	[814]	LOADK    	3 -4	; "%s*,%s*"
	8	[814]	LOADK    	4 -5	; "\t"
	9	[814]	CALL     	1 4 2
	10	[814]	MOVE     	0 1
	11	[815]	RETURN   	0 2
	12	[816]	RETURN   	0 1

function <./frontend/apps/reader/modules/readerhighlight.lua:824,954> (200 instructions, 800 bytes at 0x7f869cc093e0)
2 params, 18 slots, 6 upvalues, 16 locals, 49 constants, 4 functions
	1	[825]	GETTABLE 	2 0 -1	; "ui"
	2	[825]	GETTABLE 	2 2 -2	; "document"
	3	[825]	GETTABLE 	2 2 -3	; "info"
	4	[825]	GETTABLE 	2 2 -4	; "has_pages"
	5	[825]	TEST     	2 0 0
	6	[825]	JMP      	1	; to 8
	7	[826]	RETURN   	0 1
	8	[828]	GETTABLE 	2 0 -5	; "selected_text"
	9	[828]	TEST     	2 0 0
	10	[828]	JMP      	189	; to 200
	11	[828]	GETTABLE 	2 0 -5	; "selected_text"
	12	[828]	GETTABLE 	2 2 -6	; "pos0"
	13	[828]	TEST     	2 0 0
	14	[828]	JMP      	185	; to 200
	15	[828]	GETTABLE 	2 0 -5	; "selected_text"
	16	[828]	GETTABLE 	2 2 -7	; "pos1"
	17	[828]	TEST     	2 0 0
	18	[828]	JMP      	181	; to 200
	19	[832]	LOADK    	2 -8	; 24624
	20	[833]	TEST     	1 0 1
	21	[833]	JMP      	1	; to 23
	22	[834]	LOADK    	1 -9	; 0
	23	[836]	EQ       	0 1 -10	; - 1
	24	[836]	JMP      	2	; to 27
	25	[839]	LOADK    	2 -11	; 25434
	26	[839]	JMP      	7	; to 34
	27	[840]	EQ       	0 1 -12	; - 2
	28	[840]	JMP      	2	; to 31
	29	[842]	LOADK    	2 -13	; 26458
	30	[842]	JMP      	3	; to 34
	31	[843]	EQ       	0 1 -14	; - 3
	32	[843]	JMP      	1	; to 34
	33	[845]	LOADK    	2 -15	; 25438
	34	[847]	GETTABLE 	3 0 -1	; "ui"
	35	[847]	GETTABLE 	3 3 -2	; "document"
	36	[847]	SELF     	3 3 -16	; "getHTMLFromXPointers"
	37	[847]	GETTABLE 	5 0 -5	; "selected_text"
	38	[847]	GETTABLE 	5 5 -6	; "pos0"
	39	[848]	GETTABLE 	6 0 -5	; "selected_text"
	40	[848]	GETTABLE 	6 6 -7	; "pos1"
	41	[848]	MOVE     	7 2
	42	[848]	LOADBOOL 	8 1 0
	43	[847]	CALL     	3 6 3
	44	[849]	TEST     	3 0 0
	45	[849]	JMP      	142	; to 188
	46	[851]	LE       	0 -10 1	; 1 -
	47	[851]	JMP      	16	; to 64
	48	[852]	SELF     	5 3 -17	; "gsub"
	49	[852]	LOADK    	7 -18	; "xC2xA0"
	50	[852]	LOADK    	8 -19	; "\226\144\163"
	51	[852]	CALL     	5 4 2
	52	[852]	MOVE     	3 5
	53	[853]	SELF     	5 3 -17	; "gsub"
	54	[853]	LOADK    	7 -20	; "xC2xAD"
	55	[853]	LOADK    	8 -21	; "\226\139\133"
	56	[853]	CALL     	5 4 2
	57	[853]	MOVE     	3 5
	58	[860]	SELF     	5 3 -17	; "gsub"
	59	[860]	LOADK    	7 -22	; "(<stylesheet[^>]*>)%s*(.-)%s*(</stylesheet>)"
	60	[862]	CLOSURE  	8 0	; 0x7f869cc128a0
	61	[862]	GETUPVAL 	0 0	; prettifyCss
	62	[860]	CALL     	5 4 2
	63	[862]	MOVE     	3 5
	64	[864]	GETGLOBAL	5 -23	; require
	65	[864]	LOADK    	6 -24	; "ui/widget/textviewer"
	66	[864]	CALL     	5 2 2
	67	[865]	GETGLOBAL	6 -23	; require
	68	[865]	LOADK    	7 -25	; "ui/font"
	69	[865]	CALL     	6 2 2
	70	[866]	LOADNIL  	7 7
	71	[867]	NEWTABLE 	8 0 0
	72	[868]	TEST     	4 0 0
	73	[868]	JMP      	34	; to 108
	74	[869]	LOADK    	9 -10	; 1
	75	[869]	LEN      	10 4
	76	[869]	LOADK    	11 -10	; 1
	77	[869]	FORPREP  	9 29	; to 107
	78	[870]	NEWTABLE 	13 0 2
	79	[871]	GETUPVAL 	14 1	; T
	80	[871]	GETUPVAL 	15 2	; _
	81	[871]	LOADK    	16 -27	; "View %1"
	82	[871]	CALL     	15 2 2
	83	[871]	GETUPVAL 	16 3	; BD
	84	[871]	GETTABLE 	16 16 -28	; "filepath"
	85	[871]	GETTABLE 	17 4 12
	86	[871]	CALL     	16 2 0
	87	[871]	CALL     	14 0 2
	88	[871]	SETTABLE 	13 -26 14	; "text" -
	89	[907]	CLOSURE  	14 1	; 0x7f869cc12740
	90	[907]	MOVE     	0 0
	91	[907]	MOVE     	0 4
	92	[907]	MOVE     	0 12
	93	[907]	MOVE     	0 5
	94	[907]	GETUPVAL 	0 2	; _
	95	[907]	MOVE     	0 6
	96	[907]	GETUPVAL 	0 4	; UIManager
	97	[907]	GETUPVAL 	0 0	; prettifyCss
	98	[907]	SETTABLE 	13 -29 14	; "callback" -
	99	[910]	GETGLOBAL	14 -30	; table
	100	[910]	GETTABLE 	14 14 -31	; "insert"
	101	[910]	MOVE     	15 8
	102	[910]	NEWTABLE 	16 1 0
	103	[910]	MOVE     	17 13
	104	[910]	SETLIST  	16 1 1	; 1
	105	[910]	CALL     	14 3 1
	106	[910]	CLOSE    	12
	107	[869]	FORLOOP  	9 -30	; to 78
	108	[913]	LOADNIL  	9 9
	109	[914]	ADD      	10 1 -10	; - 1
	110	[915]	EQ       	0 10 -10	; - 1
	111	[915]	JMP      	5	; to 117
	112	[916]	GETUPVAL 	11 2	; _
	113	[916]	LOADK    	12 -32	; "Switch to debug view"
	114	[916]	CALL     	11 2 2
	115	[916]	MOVE     	9 11
	116	[916]	JMP      	19	; to 136
	117	[917]	EQ       	0 10 -12	; - 2
	118	[917]	JMP      	5	; to 124
	119	[918]	GETUPVAL 	11 2	; _
	120	[918]	LOADK    	12 -33	; "Switch to rendering debug view"
	121	[918]	CALL     	11 2 2
	122	[918]	MOVE     	9 11
	123	[918]	JMP      	12	; to 136
	124	[919]	EQ       	0 10 -14	; - 3
	125	[919]	JMP      	5	; to 131
	126	[920]	GETUPVAL 	11 2	; _
	127	[920]	LOADK    	12 -34	; "Switch to unicode debug view"
	128	[920]	CALL     	11 2 2
	129	[920]	MOVE     	9 11
	130	[920]	JMP      	5	; to 136
	131	[922]	LOADK    	10 -9	; 0
	132	[923]	GETUPVAL 	11 2	; _
	133	[923]	LOADK    	12 -35	; "Switch to standard view"
	134	[923]	CALL     	11 2 2
	135	[923]	MOVE     	9 11
	136	[925]	GETGLOBAL	11 -30	; table
	137	[925]	GETTABLE 	11 11 -31	; "insert"
	138	[925]	MOVE     	12 8
	139	[925]	NEWTABLE 	13 1 0
	140	[925]	NEWTABLE 	14 0 2
	141	[926]	SETTABLE 	14 -26 9	; "text" -
	142	[930]	CLOSURE  	15 2	; 0x7f869cc133a0
	143	[930]	GETUPVAL 	0 4	; UIManager
	144	[930]	MOVE     	0 7
	145	[930]	MOVE     	0 0
	146	[930]	MOVE     	0 10
	147	[930]	SETTABLE 	14 -29 15	; "callback" -
	148	[931]	SETLIST  	13 1 1	; 1
	149	[925]	CALL     	11 3 1
	150	[932]	GETGLOBAL	11 -30	; table
	151	[932]	GETTABLE 	11 11 -31	; "insert"
	152	[932]	MOVE     	12 8
	153	[932]	NEWTABLE 	13 1 0
	154	[932]	NEWTABLE 	14 0 2
	155	[933]	GETUPVAL 	15 2	; _
	156	[933]	LOADK    	16 -36	; "Close"
	157	[933]	CALL     	15 2 2
	158	[933]	SETTABLE 	14 -26 15	; "text" -
	159	[936]	CLOSURE  	15 3	; 0x7f869cc14380
	160	[936]	GETUPVAL 	0 4	; UIManager
	161	[936]	MOVE     	0 7
	162	[936]	SETTABLE 	14 -29 15	; "callback" -
	163	[937]	SETLIST  	13 1 1	; 1
	164	[932]	CALL     	11 3 1
	165	[938]	SELF     	11 5 -37	; "new"
	166	[938]	NEWTABLE 	13 0 7
	167	[939]	GETUPVAL 	14 2	; _
	168	[939]	LOADK    	15 -39	; "Selection HTML"
	169	[939]	CALL     	14 2 2
	170	[939]	SETTABLE 	13 -38 14	; "title" -
	171	[940]	SETTABLE 	13 -26 3	; "text" -
	172	[941]	SELF     	14 6 -41	; "getFace"
	173	[941]	LOADK    	16 -42	; "smallinfont"
	174	[941]	CALL     	14 3 2
	175	[941]	SETTABLE 	13 -40 14	; "text_face" -
	176	[942]	SETTABLE 	13 -43 -44	; "justified" false
	177	[943]	SETTABLE 	13 -45 -44	; "para_direction_rtl" false
	178	[944]	SETTABLE 	13 -46 -44	; "auto_para_direction" false
	179	[945]	SETTABLE 	13 -47 8	; "buttons_table" -
	180	[938]	CALL     	11 3 2
	181	[946]	MOVE     	7 11
	182	[947]	GETUPVAL 	11 4	; UIManager
	183	[947]	SELF     	11 11 -48	; "show"
	184	[947]	MOVE     	13 7
	185	[947]	CALL     	11 3 1
	186	[947]	CLOSE    	5
	187	[947]	JMP      	11	; to 199
	188	[949]	GETUPVAL 	5 4	; UIManager
	189	[949]	SELF     	5 5 -48	; "show"
	190	[949]	GETUPVAL 	7 5	; InfoMessage
	191	[949]	SELF     	7 7 -37	; "new"
	192	[949]	NEWTABLE 	9 0 1
	193	[950]	GETUPVAL 	10 2	; _
	194	[950]	LOADK    	11 -49	; "Failed getting HTML for selection"
	195	[950]	CALL     	10 2 2
	196	[950]	SETTABLE 	9 -26 10	; "text" -
	197	[949]	CALL     	7 3 0
	198	[949]	CALL     	5 0 1
	199	[952]	CLOSE    	2
	200	[954]	RETURN   	0 1

function <./frontend/apps/reader/modules/readerhighlight.lua:860,862> (9 instructions, 36 bytes at 0x7f869cc128a0)
3 params, 7 slots, 1 upvalue, 3 locals, 1 constant, 0 functions
	1	[861]	MOVE     	3 0
	2	[861]	LOADK    	4 -1	; "\n"
	3	[861]	GETUPVAL 	5 0	; prettifyCss
	4	[861]	MOVE     	6 1
	5	[861]	CALL     	5 2 2
	6	[861]	MOVE     	6 2
	7	[861]	CONCAT   	3 3 6
	8	[861]	RETURN   	3 2
	9	[862]	RETURN   	0 1

function <./frontend/apps/reader/modules/readerhighlight.lua:872,907> (75 instructions, 300 bytes at 0x7f869cc12740)
0 params, 11 slots, 8 upvalues, 2 locals, 20 constants, 2 functions
	1	[873]	GETUPVAL 	0 0	; self
	2	[873]	GETTABLE 	0 0 -1	; "ui"
	3	[873]	GETTABLE 	0 0 -2	; "document"
	4	[873]	SELF     	0 0 -3	; "getDocumentFileContent"
	5	[873]	GETUPVAL 	2 1	; css_files
	6	[873]	GETUPVAL 	3 2	; i
	7	[873]	GETTABLE 	2 2 3
	8	[873]	CALL     	0 3 2
	9	[874]	LOADNIL  	1 1
	10	[875]	GETUPVAL 	2 3	; TextViewer
	11	[875]	SELF     	2 2 -4	; "new"
	12	[875]	NEWTABLE 	4 0 7
	13	[876]	GETUPVAL 	5 1	; css_files
	14	[876]	GETUPVAL 	6 2	; i
	15	[876]	GETTABLE 	5 5 6
	16	[876]	SETTABLE 	4 -5 5	; "title" -
	17	[877]	TESTSET  	5 0 1
	18	[877]	JMP      	3	; to 22
	19	[877]	GETUPVAL 	5 4	; _
	20	[877]	LOADK    	6 -7	; "Failed getting CSS content"
	21	[877]	CALL     	5 2 2
	22	[877]	SETTABLE 	4 -6 5	; "text" -
	23	[878]	GETUPVAL 	5 5	; Font
	24	[878]	SELF     	5 5 -9	; "getFace"
	25	[878]	LOADK    	7 -10	; "smallinfont"
	26	[878]	CALL     	5 3 2
	27	[878]	SETTABLE 	4 -8 5	; "text_face" -
	28	[879]	SETTABLE 	4 -11 -12	; "justified" false
	29	[880]	SETTABLE 	4 -13 -12	; "para_direction_rtl" false
	30	[881]	SETTABLE 	4 -14 -12	; "auto_para_direction" false
	31	[882]	NEWTABLE 	5 2 0
	32	[882]	NEWTABLE 	6 1 0
	33	[883]	NEWTABLE 	7 0 3
	34	[884]	GETUPVAL 	8 4	; _
	35	[884]	LOADK    	9 -16	; "Prettify"
	36	[884]	CALL     	8 2 2
	37	[884]	SETTABLE 	7 -6 8	; "text" -
	38	[885]	TEST     	0 0 0
	39	[885]	JMP      	3	; to 43
	40	[885]	LOADBOOL 	8 1 0
	41	[885]	TEST     	8 0 1
	42	[885]	JMP      	1	; to 44
	43	[885]	LOADBOOL 	8 0 0
	44	[885]	SETTABLE 	7 -17 8	; "enabled" -
	45	[896]	CLOSURE  	8 0	; 0x7f869cc141c0
	46	[896]	GETUPVAL 	0 6	; UIManager
	47	[896]	MOVE     	0 1
	48	[896]	GETUPVAL 	0 3	; TextViewer
	49	[896]	GETUPVAL 	0 1	; css_files
	50	[896]	GETUPVAL 	0 2	; i
	51	[896]	GETUPVAL 	0 7	; prettifyCss
	52	[896]	MOVE     	0 0
	53	[896]	GETUPVAL 	0 5	; Font
	54	[896]	SETTABLE 	7 -18 8	; "callback" -
	55	[897]	SETLIST  	6 1 1	; 1
	56	[897]	NEWTABLE 	7 1 0
	57	[898]	NEWTABLE 	8 0 2
	58	[899]	GETUPVAL 	9 4	; _
	59	[899]	LOADK    	10 -19	; "Close"
	60	[899]	CALL     	9 2 2
	61	[899]	SETTABLE 	8 -6 9	; "text" -
	62	[902]	CLOSURE  	9 1	; 0x7f869cc13f50
	63	[902]	GETUPVAL 	0 6	; UIManager
	64	[902]	MOVE     	0 1
	65	[902]	SETTABLE 	8 -18 9	; "callback" -
	66	[903]	SETLIST  	7 1 1	; 1
	67	[904]	SETLIST  	5 2 1	; 1
	68	[904]	SETTABLE 	4 -15 5	; "buttons_table" -
	69	[875]	CALL     	2 3 2
	70	[905]	MOVE     	1 2
	71	[906]	GETUPVAL 	2 6	; UIManager
	72	[906]	SELF     	2 2 -20	; "show"
	73	[906]	MOVE     	4 1
	74	[906]	CALL     	2 3 1
	75	[907]	RETURN   	0 1

function <./frontend/apps/reader/modules/readerhighlight.lua:886,896> (28 instructions, 112 bytes at 0x7f869cc141c0)
0 params, 8 slots, 8 upvalues, 0 locals, 12 constants, 0 functions
	1	[887]	GETUPVAL 	0 0	; UIManager
	2	[887]	SELF     	0 0 -1	; "close"
	3	[887]	GETUPVAL 	2 1	; cssviewer
	4	[887]	CALL     	0 3 1
	5	[888]	GETUPVAL 	0 0	; UIManager
	6	[888]	SELF     	0 0 -2	; "show"
	7	[888]	GETUPVAL 	2 2	; TextViewer
	8	[888]	SELF     	2 2 -3	; "new"
	9	[888]	NEWTABLE 	4 0 6
	10	[889]	GETUPVAL 	5 3	; css_files
	11	[889]	GETUPVAL 	6 4	; i
	12	[889]	GETTABLE 	5 5 6
	13	[889]	SETTABLE 	4 -4 5	; "title" -
	14	[890]	GETUPVAL 	5 5	; prettifyCss
	15	[890]	GETUPVAL 	6 6	; css_text
	16	[890]	CALL     	5 2 2
	17	[890]	SETTABLE 	4 -5 5	; "text" -
	18	[891]	GETUPVAL 	5 7	; Font
	19	[891]	SELF     	5 5 -7	; "getFace"
	20	[891]	LOADK    	7 -8	; "smallinfont"
	21	[891]	CALL     	5 3 2
	22	[891]	SETTABLE 	4 -6 5	; "text_face" -
	23	[892]	SETTABLE 	4 -9 -10	; "justified" false
	24	[893]	SETTABLE 	4 -11 -10	; "para_direction_rtl" false
	25	[894]	SETTABLE 	4 -12 -10	; "auto_para_direction" false
	26	[888]	CALL     	2 3 0
	27	[888]	CALL     	0 0 1
	28	[896]	RETURN   	0 1

function <./frontend/apps/reader/modules/readerhighlight.lua:900,902> (5 instructions, 20 bytes at 0x7f869cc13f50)
0 params, 3 slots, 2 upvalues, 0 locals, 1 constant, 0 functions
	1	[901]	GETUPVAL 	0 0	; UIManager
	2	[901]	SELF     	0 0 -1	; "close"
	3	[901]	GETUPVAL 	2 1	; cssviewer
	4	[901]	CALL     	0 3 1
	5	[902]	RETURN   	0 1

function <./frontend/apps/reader/modules/readerhighlight.lua:927,930> (9 instructions, 36 bytes at 0x7f869cc133a0)
0 params, 3 slots, 4 upvalues, 0 locals, 2 constants, 0 functions
	1	[928]	GETUPVAL 	0 0	; UIManager
	2	[928]	SELF     	0 0 -1	; "close"
	3	[928]	GETUPVAL 	2 1	; textviewer
	4	[928]	CALL     	0 3 1
	5	[929]	GETUPVAL 	0 2	; self
	6	[929]	SELF     	0 0 -2	; "viewSelectionHTML"
	7	[929]	GETUPVAL 	2 3	; next_debug_view
	8	[929]	CALL     	0 3 1
	9	[930]	RETURN   	0 1

function <./frontend/apps/reader/modules/readerhighlight.lua:934,936> (5 instructions, 20 bytes at 0x7f869cc14380)
0 params, 3 slots, 2 upvalues, 0 locals, 1 constant, 0 functions
	1	[935]	GETUPVAL 	0 0	; UIManager
	2	[935]	SELF     	0 0 -1	; "close"
	3	[935]	GETUPVAL 	2 1	; textviewer
	4	[935]	CALL     	0 3 1
	5	[936]	RETURN   	0 1

function <./frontend/apps/reader/modules/readerhighlight.lua:956,971> (37 instructions, 148 bytes at 0x7f869cc138c0)
2 params, 9 slots, 4 upvalues, 3 locals, 12 constants, 0 functions
	1	[957]	GETTABLE 	2 1 -1	; "text"
	2	[957]	EQ       	1 2 -2	; - ""
	3	[957]	JMP      	4	; to 8
	4	[958]	SELF     	2 0 -3	; "onTranslateText"
	5	[958]	GETTABLE 	4 1 -1	; "text"
	6	[958]	CALL     	2 3 1
	7	[958]	JMP      	29	; to 37
	8	[961]	GETTABLE 	2 0 -4	; "ui"
	9	[961]	GETTABLE 	2 2 -5	; "document"
	10	[961]	SELF     	2 2 -6	; "getOCRText"
	11	[961]	GETTABLE 	4 0 -7	; "hold_pos"
	12	[961]	GETTABLE 	4 4 -8	; "page"
	13	[961]	MOVE     	5 1
	14	[961]	CALL     	2 4 2
	15	[962]	GETUPVAL 	3 0	; logger
	16	[962]	GETTABLE 	3 3 -9	; "dbg"
	17	[962]	LOADK    	4 -10	; "OCRed text:"
	18	[962]	MOVE     	5 2
	19	[962]	CALL     	3 3 1
	20	[963]	TEST     	2 0 0
	21	[963]	JMP      	6	; to 28
	22	[963]	EQ       	1 2 -2	; - ""
	23	[963]	JMP      	4	; to 28
	24	[964]	SELF     	3 0 -3	; "onTranslateText"
	25	[964]	MOVE     	5 2
	26	[964]	CALL     	3 3 1
	27	[964]	JMP      	9	; to 37
	28	[966]	GETUPVAL 	3 1	; UIManager
	29	[966]	SELF     	3 3 -11	; "show"
	30	[966]	GETUPVAL 	5 2	; InfoMessage
	31	[966]	SELF     	5 5 -12	; "new"
	32	[966]	NEWTABLE 	7 0 1
	33	[967]	GETUPVAL 	8 3	; info_message_ocr_text
	34	[967]	SETTABLE 	7 -1 8	; "text" -
	35	[966]	CALL     	5 3 0
	36	[966]	CALL     	3 0 1
	37	[971]	RETURN   	0 1

function <./frontend/apps/reader/modules/readerhighlight.lua:973,975> (5 instructions, 20 bytes at 0x7f869cc14e80)
2 params, 5 slots, 1 upvalue, 2 locals, 1 constant, 0 functions
	1	[974]	GETUPVAL 	2 0	; Translator
	2	[974]	SELF     	2 2 -1	; "showTranslation"
	3	[974]	MOVE     	4 1
	4	[974]	CALL     	2 3 1
	5	[975]	RETURN   	0 1

function <./frontend/apps/reader/modules/readerhighlight.lua:977,1023> (93 instructions, 372 bytes at 0x7f869cc13a00)
1 param, 7 slots, 1 upvalue, 4 locals, 30 constants, 0 functions
	1	[978]	LOADBOOL 	1 0 0
	2	[979]	GETTABLE 	2 0 -1	; "hold_last_tv"
	3	[979]	TEST     	2 0 0
	4	[979]	JMP      	13	; to 18
	5	[980]	GETUPVAL 	2 0	; TimeVal
	6	[980]	GETTABLE 	2 2 -2	; "now"
	7	[980]	CALL     	2 1 2
	8	[980]	GETTABLE 	3 0 -1	; "hold_last_tv"
	9	[980]	SUB      	2 2 3
	10	[981]	GETTABLE 	3 2 -3	; "sec"
	11	[981]	GETTABLE 	4 2 -4	; "usec"
	12	[981]	DIV      	4 4 -5	; - 1000000
	13	[981]	ADD      	2 3 4
	14	[982]	LT       	0 -6 2	; 3 -
	15	[982]	JMP      	1	; to 17
	16	[984]	LOADBOOL 	1 1 0
	17	[986]	SETTABLE 	0 -1 -7	; "hold_last_tv" nil
	18	[988]	GETTABLE 	2 0 -8	; "selected_word"
	19	[988]	TEST     	2 0 0
	20	[988]	JMP      	14	; to 35
	21	[989]	TEST     	1 0 1
	22	[989]	JMP      	6	; to 29
	23	[989]	GETGLOBAL	2 -9	; G_reader_settings
	24	[989]	SELF     	2 2 -10	; "isTrue"
	25	[989]	LOADK    	4 -11	; "highlight_action_on_single_word"
	26	[989]	CALL     	2 3 2
	27	[989]	TEST     	2 0 0
	28	[989]	JMP      	6	; to 35
	29	[992]	SELF     	2 0 -12	; "onHoldPan"
	30	[992]	LOADNIL  	4 4
	31	[992]	NEWTABLE 	5 0 1
	32	[992]	GETTABLE 	6 0 -14	; "hold_ges_pos"
	33	[992]	SETTABLE 	5 -13 6	; "pos" -
	34	[992]	CALL     	2 4 1
	35	[996]	GETTABLE 	2 0 -15	; "selected_text"
	36	[996]	TEST     	2 0 0
	37	[996]	JMP      	45	; to 83
	38	[997]	GETGLOBAL	2 -9	; G_reader_settings
	39	[997]	SELF     	2 2 -16	; "readSetting"
	40	[997]	LOADK    	4 -17	; "default_highlight_action"
	41	[997]	CALL     	2 3 2
	42	[998]	TEST     	1 0 1
	43	[998]	JMP      	2	; to 46
	44	[998]	TEST     	2 0 1
	45	[998]	JMP      	3	; to 49
	46	[1000]	SELF     	3 0 -18	; "onShowHighlightMenu"
	47	[1000]	CALL     	3 2 1
	48	[1000]	JMP      	42	; to 91
	49	[1001]	EQ       	0 2 -19	; - "highlight"
	50	[1001]	JMP      	5	; to 56
	51	[1002]	SELF     	3 0 -20	; "saveHighlight"
	52	[1002]	CALL     	3 2 1
	53	[1003]	SELF     	3 0 -21	; "onClose"
	54	[1003]	CALL     	3 2 1
	55	[1003]	JMP      	35	; to 91
	56	[1004]	EQ       	0 2 -22	; - "translate"
	57	[1004]	JMP      	6	; to 64
	58	[1005]	SELF     	3 0 -22	; "translate"
	59	[1005]	GETTABLE 	5 0 -15	; "selected_text"
	60	[1005]	CALL     	3 3 1
	61	[1006]	SELF     	3 0 -21	; "onClose"
	62	[1006]	CALL     	3 2 1
	63	[1006]	JMP      	27	; to 91
	64	[1007]	EQ       	0 2 -23	; - "wikipedia"
	65	[1007]	JMP      	5	; to 71
	66	[1008]	SELF     	3 0 -24	; "lookupWikipedia"
	67	[1008]	CALL     	3 2 1
	68	[1009]	SELF     	3 0 -21	; "onClose"
	69	[1009]	CALL     	3 2 1
	70	[1009]	JMP      	20	; to 91
	71	[1010]	EQ       	0 2 -25	; - "dictionary"
	72	[1010]	JMP      	5	; to 78
	73	[1011]	SELF     	3 0 -26	; "onHighlightDictLookup"
	74	[1011]	CALL     	3 2 1
	75	[1012]	SELF     	3 0 -21	; "onClose"
	76	[1012]	CALL     	3 2 1
	77	[1012]	JMP      	13	; to 91
	78	[1013]	EQ       	0 2 -27	; - "search"
	79	[1013]	JMP      	11	; to 91
	80	[1014]	SELF     	3 0 -28	; "onHighlightSearch"
	81	[1014]	CALL     	3 2 1
	82	[1017]	JMP      	8	; to 91
	83	[1018]	GETTABLE 	2 0 -8	; "selected_word"
	84	[1018]	TEST     	2 0 0
	85	[1018]	JMP      	5	; to 91
	86	[1019]	SELF     	2 0 -29	; "lookup"
	87	[1019]	GETTABLE 	4 0 -8	; "selected_word"
	88	[1019]	GETTABLE 	5 0 -30	; "selected_link"
	89	[1019]	CALL     	2 4 1
	90	[1020]	SETTABLE 	0 -8 -7	; "selected_word" nil
	91	[1022]	LOADBOOL 	2 1 0
	92	[1022]	RETURN   	2 2
	93	[1023]	RETURN   	0 1

function <./frontend/apps/reader/modules/readerhighlight.lua:1025,1049> (56 instructions, 224 bytes at 0x7f869cc155a0)
1 param, 12 slots, 4 upvalues, 4 locals, 18 constants, 0 functions
	1	[1026]	NEWTABLE 	1 0 5
	2	[1027]	SETTABLE 	1 -1 -2	; "highlight" "translate"
	3	[1028]	SETTABLE 	1 -2 -3	; "translate" "wikipedia"
	4	[1029]	SETTABLE 	1 -3 -4	; "wikipedia" "dictionary"
	5	[1030]	SETTABLE 	1 -4 -5	; "dictionary" "search"
	6	[1031]	SETTABLE 	1 -5 -6	; "search" nil
	7	[1033]	GETGLOBAL	2 -7	; G_reader_settings
	8	[1033]	SELF     	2 2 -8	; "readSetting"
	9	[1033]	LOADK    	4 -9	; "default_highlight_action"
	10	[1033]	CALL     	2 3 2
	11	[1034]	TEST     	2 0 1
	12	[1034]	JMP      	18	; to 31
	13	[1035]	GETGLOBAL	3 -7	; G_reader_settings
	14	[1035]	SELF     	3 3 -10	; "saveSetting"
	15	[1035]	LOADK    	5 -9	; "default_highlight_action"
	16	[1035]	LOADK    	6 -1	; "highlight"
	17	[1035]	CALL     	3 4 1
	18	[1036]	GETUPVAL 	3 0	; UIManager
	19	[1036]	SELF     	3 3 -11	; "show"
	20	[1036]	GETUPVAL 	5 1	; Notification
	21	[1036]	SELF     	5 5 -12	; "new"
	22	[1036]	NEWTABLE 	7 0 2
	23	[1037]	GETUPVAL 	8 2	; _
	24	[1037]	LOADK    	9 -14	; "Default highlight action changed to 'highlight'."
	25	[1037]	CALL     	8 2 2
	26	[1037]	SETTABLE 	7 -13 8	; "text" -
	27	[1038]	SETTABLE 	7 -15 -16	; "timeout" 1
	28	[1036]	CALL     	5 3 0
	29	[1036]	CALL     	3 0 1
	30	[1039]	JMP      	23	; to 54
	31	[1041]	GETTABLE 	3 1 2
	32	[1042]	GETGLOBAL	4 -7	; G_reader_settings
	33	[1042]	SELF     	4 4 -10	; "saveSetting"
	34	[1042]	LOADK    	6 -9	; "default_highlight_action"
	35	[1042]	MOVE     	7 3
	36	[1042]	CALL     	4 4 1
	37	[1043]	GETUPVAL 	4 0	; UIManager
	38	[1043]	SELF     	4 4 -11	; "show"
	39	[1043]	GETUPVAL 	6 1	; Notification
	40	[1043]	SELF     	6 6 -12	; "new"
	41	[1043]	NEWTABLE 	8 0 2
	42	[1044]	GETUPVAL 	9 3	; T
	43	[1044]	GETUPVAL 	10 2	; _
	44	[1044]	LOADK    	11 -17	; "Default highlight action changed to '%1'."
	45	[1044]	CALL     	10 2 2
	46	[1044]	TESTSET  	11 3 1
	47	[1044]	JMP      	1	; to 49
	48	[1044]	LOADK    	11 -18	; "default"
	49	[1044]	CALL     	9 3 2
	50	[1044]	SETTABLE 	8 -13 9	; "text" -
	51	[1045]	SETTABLE 	8 -15 -16	; "timeout" 1
	52	[1043]	CALL     	6 3 0
	53	[1043]	CALL     	4 0 1
	54	[1048]	LOADBOOL 	3 1 0
	55	[1048]	RETURN   	3 2
	56	[1049]	RETURN   	0 1

function <./frontend/apps/reader/modules/readerhighlight.lua:1051,1064> (39 instructions, 156 bytes at 0x7f869cc15f10)
1 param, 10 slots, 4 upvalues, 2 locals, 16 constants, 0 functions
	1	[1052]	NEWTABLE 	1 0 3
	2	[1053]	SETTABLE 	1 -1 -2	; "lighten" "underscore"
	3	[1054]	SETTABLE 	1 -2 -3	; "underscore" "invert"
	4	[1055]	SETTABLE 	1 -3 -1	; "invert" "lighten"
	5	[1057]	GETTABLE 	2 0 -4	; "view"
	6	[1057]	GETTABLE 	2 2 -5	; "highlight"
	7	[1057]	GETTABLE 	3 0 -4	; "view"
	8	[1057]	GETTABLE 	3 3 -5	; "highlight"
	9	[1057]	GETTABLE 	3 3 -6	; "saved_drawer"
	10	[1057]	GETTABLE 	3 1 3
	11	[1057]	SETTABLE 	2 -6 3	; "saved_drawer" -
	12	[1058]	GETTABLE 	2 0 -7	; "ui"
	13	[1058]	GETTABLE 	2 2 -8	; "doc_settings"
	14	[1058]	SELF     	2 2 -9	; "saveSetting"
	15	[1058]	LOADK    	4 -10	; "highlight_drawer"
	16	[1058]	GETTABLE 	5 0 -4	; "view"
	17	[1058]	GETTABLE 	5 5 -5	; "highlight"
	18	[1058]	GETTABLE 	5 5 -6	; "saved_drawer"
	19	[1058]	CALL     	2 4 1
	20	[1059]	GETUPVAL 	2 0	; UIManager
	21	[1059]	SELF     	2 2 -11	; "show"
	22	[1059]	GETUPVAL 	4 1	; Notification
	23	[1059]	SELF     	4 4 -12	; "new"
	24	[1059]	NEWTABLE 	6 0 2
	25	[1060]	GETUPVAL 	7 2	; T
	26	[1060]	GETUPVAL 	8 3	; _
	27	[1060]	LOADK    	9 -14	; "Default highlight style changed to '%1'."
	28	[1060]	CALL     	8 2 2
	29	[1060]	GETTABLE 	9 0 -4	; "view"
	30	[1060]	GETTABLE 	9 9 -5	; "highlight"
	31	[1060]	GETTABLE 	9 9 -6	; "saved_drawer"
	32	[1060]	CALL     	7 3 2
	33	[1060]	SETTABLE 	6 -13 7	; "text" -
	34	[1061]	SETTABLE 	6 -15 -16	; "timeout" 1
	35	[1059]	CALL     	4 3 0
	36	[1059]	CALL     	2 0 1
	37	[1063]	LOADBOOL 	2 1 0
	38	[1063]	RETURN   	2 2
	39	[1064]	RETURN   	0 1

function <./frontend/apps/reader/modules/readerhighlight.lua:1066,1073> (19 instructions, 76 bytes at 0x7f869cc16400)
1 param, 5 slots, 1 upvalue, 1 local, 7 constants, 0 functions
	1	[1067]	GETTABLE 	1 0 -1	; "hold_pos"
	2	[1067]	TEST     	1 0 0
	3	[1067]	JMP      	15	; to 19
	4	[1068]	GETTABLE 	1 0 -2	; "selected_text"
	5	[1068]	TEST     	1 0 1
	6	[1068]	JMP      	12	; to 19
	7	[1069]	GETTABLE 	1 0 -3	; "ui"
	8	[1069]	GETTABLE 	1 1 -4	; "document"
	9	[1069]	SELF     	1 1 -5	; "getTextFromPositions"
	10	[1069]	GETTABLE 	3 0 -1	; "hold_pos"
	11	[1069]	GETTABLE 	4 0 -1	; "hold_pos"
	12	[1069]	CALL     	1 4 2
	13	[1069]	SETTABLE 	0 -2 1	; "selected_text" -
	14	[1070]	GETUPVAL 	1 0	; logger
	15	[1070]	GETTABLE 	1 1 -6	; "dbg"
	16	[1070]	LOADK    	2 -7	; "selected text:"
	17	[1070]	GETTABLE 	3 0 -2	; "selected_text"
	18	[1070]	CALL     	1 3 1
	19	[1073]	RETURN   	0 1

function <./frontend/apps/reader/modules/readerhighlight.lua:1075,1077> (3 instructions, 12 bytes at 0x7f869cc16a60)
1 param, 3 slots, 0 upvalues, 1 local, 1 constant, 0 functions
	1	[1076]	SELF     	1 0 -1	; "saveHighlight"
	2	[1076]	CALL     	1 2 1
	3	[1077]	RETURN   	0 1

function <./frontend/apps/reader/modules/readerhighlight.lua:1079,1139> (111 instructions, 444 bytes at 0x7f869cc16ed0)
2 params, 18 slots, 1 upvalue, 22 locals, 24 constants, 0 functions
	1	[1085]	TEST     	1 0 0
	2	[1085]	JMP      	5	; to 8
	3	[1086]	GETTABLE 	2 1 -1	; "page"
	4	[1087]	GETTABLE 	3 1 -2	; "notes"
	5	[1088]	GETTABLE 	4 1 -3	; "pos0"
	6	[1089]	GETTABLE 	5 1 -4	; "datetime"
	7	[1089]	JMP      	6	; to 14
	8	[1091]	GETTABLE 	7 0 -5	; "hold_pos"
	9	[1091]	GETTABLE 	2 7 -1	; "page"
	10	[1092]	GETTABLE 	7 0 -6	; "selected_text"
	11	[1092]	GETTABLE 	3 7 -7	; "text"
	12	[1093]	GETTABLE 	7 0 -6	; "selected_text"
	13	[1093]	GETTABLE 	4 7 -3	; "pos0"
	14	[1095]	GETTABLE 	7 0 -8	; "ui"
	15	[1095]	GETTABLE 	7 7 -9	; "document"
	16	[1095]	GETTABLE 	7 7 -10	; "info"
	17	[1095]	GETTABLE 	7 7 -11	; "has_pages"
	18	[1095]	TEST     	7 0 0
	19	[1095]	JMP      	30	; to 50
	20	[1096]	LOADK    	7 -12	; 1
	21	[1096]	GETTABLE 	8 0 -13	; "view"
	22	[1096]	GETTABLE 	8 8 -14	; "highlight"
	23	[1096]	GETTABLE 	8 8 -15	; "saved"
	24	[1096]	GETTABLE 	8 8 2
	25	[1096]	LEN      	8 8
	26	[1096]	LOADK    	9 -12	; 1
	27	[1096]	FORPREP  	7 20	; to 48
	28	[1097]	GETTABLE 	11 0 -13	; "view"
	29	[1097]	GETTABLE 	11 11 -14	; "highlight"
	30	[1097]	GETTABLE 	11 11 -15	; "saved"
	31	[1097]	GETTABLE 	11 11 2
	32	[1097]	GETTABLE 	11 11 10
	33	[1101]	GETTABLE 	12 11 -7	; "text"
	34	[1101]	EQ       	0 12 3
	35	[1101]	JMP      	12	; to 48
	36	[1102]	EQ       	0 5 -16	; - nil
	37	[1102]	JMP      	3	; to 41
	38	[1102]	GETTABLE 	12 11 -3	; "pos0"
	39	[1102]	EQ       	1 12 4
	40	[1102]	JMP      	5	; to 46
	41	[1103]	EQ       	1 5 -16	; - nil
	42	[1103]	JMP      	5	; to 48
	43	[1103]	GETTABLE 	12 11 -4	; "datetime"
	44	[1103]	EQ       	0 12 5
	45	[1103]	JMP      	2	; to 48
	46	[1104]	MOVE     	6 10
	47	[1105]	JMP      	35	; to 83
	48	[1096]	FORLOOP  	7 -21	; to 28
	49	[1107]	JMP      	33	; to 83
	50	[1112]	GETGLOBAL	7 -17	; pairs
	51	[1112]	GETTABLE 	8 0 -13	; "view"
	52	[1112]	GETTABLE 	8 8 -14	; "highlight"
	53	[1112]	GETTABLE 	8 8 -15	; "saved"
	54	[1112]	CALL     	7 2 4
	55	[1112]	JMP      	25	; to 81
	56	[1113]	LOADK    	12 -12	; 1
	57	[1113]	LEN      	13 11
	58	[1113]	LOADK    	14 -12	; 1
	59	[1113]	FORPREP  	12 17	; to 77
	60	[1114]	GETTABLE 	16 11 15
	61	[1116]	GETTABLE 	17 16 -7	; "text"
	62	[1116]	EQ       	0 17 3
	63	[1116]	JMP      	13	; to 77
	64	[1117]	EQ       	0 5 -16	; - nil
	65	[1117]	JMP      	3	; to 69
	66	[1117]	GETTABLE 	17 16 -3	; "pos0"
	67	[1117]	EQ       	1 17 4
	68	[1117]	JMP      	5	; to 74
	69	[1118]	EQ       	1 5 -16	; - nil
	70	[1118]	JMP      	6	; to 77
	71	[1118]	GETTABLE 	17 16 -4	; "datetime"
	72	[1118]	EQ       	0 17 5
	73	[1118]	JMP      	3	; to 77
	74	[1119]	MOVE     	2 10
	75	[1120]	MOVE     	6 15
	76	[1121]	JMP      	1	; to 78
	77	[1113]	FORLOOP  	12 -18	; to 60
	78	[1124]	TEST     	6 0 0
	79	[1124]	JMP      	1	; to 81
	80	[1125]	JMP      	2	; to 83
	81	[1112]	TFORLOOP 	7 2
	82	[1126]	JMP      	-27	; to 56
	83	[1129]	TEST     	1 0 0
	84	[1129]	JMP      	13	; to 98
	85	[1129]	TEST     	6 0 1
	86	[1129]	JMP      	11	; to 98
	87	[1130]	GETUPVAL 	7 0	; logger
	88	[1130]	GETTABLE 	7 7 -18	; "warn"
	89	[1130]	LOADK    	8 -19	; "unhighlight: bookmark_item not found among highlights"
	90	[1130]	MOVE     	9 1
	91	[1130]	CALL     	7 3 1
	92	[1133]	GETTABLE 	7 0 -8	; "ui"
	93	[1133]	GETTABLE 	7 7 -20	; "bookmark"
	94	[1133]	SELF     	7 7 -21	; "removeBookmark"
	95	[1133]	MOVE     	9 1
	96	[1133]	CALL     	7 3 1
	97	[1134]	RETURN   	0 1
	98	[1136]	GETUPVAL 	7 0	; logger
	99	[1136]	GETTABLE 	7 7 -22	; "dbg"
	100	[1136]	LOADK    	8 -23	; "found highlight to delete on page"
	101	[1136]	MOVE     	9 2
	102	[1136]	MOVE     	10 6
	103	[1136]	CALL     	7 4 1
	104	[1137]	SELF     	7 0 -24	; "deleteHighlight"
	105	[1137]	MOVE     	9 2
	106	[1137]	MOVE     	10 6
	107	[1137]	MOVE     	11 1
	108	[1137]	CALL     	7 5 1
	109	[1138]	LOADBOOL 	7 1 0
	110	[1138]	RETURN   	7 2
	111	[1139]	RETURN   	0 1

function <./frontend/apps/reader/modules/readerhighlight.lua:1141,1158> (50 instructions, 200 bytes at 0x7f869cc13bd0)
1 param, 5 slots, 0 upvalues, 3 locals, 18 constants, 0 functions
	1	[1142]	GETTABLE 	1 0 -1	; "hold_pos"
	2	[1142]	TEST     	1 0 0
	3	[1142]	JMP      	5	; to 9
	4	[1142]	GETTABLE 	1 0 -2	; "selected_text"
	5	[1142]	TEST     	1 0 1
	6	[1142]	JMP      	2	; to 9
	7	[1143]	SELF     	1 0 -3	; "highlightFromHoldPos"
	8	[1143]	CALL     	1 2 1
	9	[1145]	GETTABLE 	1 0 -2	; "selected_text"
	10	[1145]	TEST     	1 0 0
	11	[1145]	JMP      	38	; to 50
	12	[1145]	GETTABLE 	1 0 -2	; "selected_text"
	13	[1145]	GETTABLE 	1 1 -4	; "pos0"
	14	[1145]	TEST     	1 0 0
	15	[1145]	JMP      	34	; to 50
	16	[1145]	GETTABLE 	1 0 -2	; "selected_text"
	17	[1145]	GETTABLE 	1 1 -5	; "pos1"
	18	[1145]	TEST     	1 0 0
	19	[1145]	JMP      	30	; to 50
	20	[1146]	GETGLOBAL	1 -6	; os
	21	[1146]	GETTABLE 	1 1 -7	; "date"
	22	[1146]	LOADK    	2 -8	; "%Y-%m-%d %H:%M:%S"
	23	[1146]	CALL     	1 2 2
	24	[1147]	GETTABLE 	2 0 -9	; "ui"
	25	[1147]	GETTABLE 	2 2 -10	; "document"
	26	[1147]	GETTABLE 	2 2 -11	; "info"
	27	[1147]	GETTABLE 	2 2 -12	; "has_pages"
	28	[1147]	TEST     	2 0 0
	29	[1147]	JMP      	4	; to 34
	30	[1148]	GETTABLE 	2 0 -1	; "hold_pos"
	31	[1148]	GETTABLE 	2 2 -13	; "page"
	32	[1148]	TEST     	2 0 1
	33	[1148]	JMP      	2	; to 36
	34	[1148]	GETTABLE 	2 0 -2	; "selected_text"
	35	[1148]	GETTABLE 	2 2 -4	; "pos0"
	36	[1149]	NEWTABLE 	3 0 6
	37	[1150]	SETTABLE 	3 -13 2	; "page" -
	38	[1151]	GETTABLE 	4 0 -2	; "selected_text"
	39	[1151]	GETTABLE 	4 4 -4	; "pos0"
	40	[1151]	SETTABLE 	3 -4 4	; "pos0" -
	41	[1152]	GETTABLE 	4 0 -2	; "selected_text"
	42	[1152]	GETTABLE 	4 4 -5	; "pos1"
	43	[1152]	SETTABLE 	3 -5 4	; "pos1" -
	44	[1153]	SETTABLE 	3 -14 1	; "datetime" -
	45	[1154]	GETTABLE 	4 0 -2	; "selected_text"
	46	[1154]	GETTABLE 	4 4 -16	; "text"
	47	[1154]	SETTABLE 	3 -15 4	; "notes" -
	48	[1155]	SETTABLE 	3 -17 -18	; "highlighted" true
	49	[1156]	RETURN   	3 2
	50	[1158]	RETURN   	0 1

function <./frontend/apps/reader/modules/readerhighlight.lua:1160,1196> (93 instructions, 372 bytes at 0x7f869cc16e30)
1 param, 9 slots, 2 upvalues, 5 locals, 28 constants, 0 functions
	1	[1161]	GETTABLE 	1 0 -1	; "ui"
	2	[1161]	SELF     	1 1 -2	; "handleEvent"
	3	[1161]	GETUPVAL 	3 0	; Event
	4	[1161]	SELF     	3 3 -3	; "new"
	5	[1161]	LOADK    	5 -4	; "AddHighlight"
	6	[1161]	CALL     	3 3 0
	7	[1161]	CALL     	1 0 1
	8	[1162]	GETUPVAL 	1 1	; logger
	9	[1162]	GETTABLE 	1 1 -5	; "dbg"
	10	[1162]	LOADK    	2 -6	; "save highlight"
	11	[1162]	CALL     	1 2 1
	12	[1163]	GETTABLE 	1 0 -7	; "hold_pos"
	13	[1163]	GETTABLE 	1 1 -8	; "page"
	14	[1164]	GETTABLE 	2 0 -7	; "hold_pos"
	15	[1164]	TEST     	2 0 0
	16	[1164]	JMP      	76	; to 93
	17	[1164]	GETTABLE 	2 0 -9	; "selected_text"
	18	[1164]	TEST     	2 0 0
	19	[1164]	JMP      	73	; to 93
	20	[1164]	GETTABLE 	2 0 -9	; "selected_text"
	21	[1164]	GETTABLE 	2 2 -10	; "pos0"
	22	[1165]	TEST     	2 0 0
	23	[1165]	JMP      	69	; to 93
	24	[1165]	GETTABLE 	2 0 -9	; "selected_text"
	25	[1165]	GETTABLE 	2 2 -11	; "pos1"
	26	[1165]	TEST     	2 0 0
	27	[1165]	JMP      	65	; to 93
	28	[1166]	GETTABLE 	2 0 -12	; "view"
	29	[1166]	GETTABLE 	2 2 -13	; "highlight"
	30	[1166]	GETTABLE 	2 2 -14	; "saved"
	31	[1166]	GETTABLE 	2 2 1
	32	[1166]	TEST     	2 0 1
	33	[1166]	JMP      	5	; to 39
	34	[1167]	GETTABLE 	2 0 -12	; "view"
	35	[1167]	GETTABLE 	2 2 -13	; "highlight"
	36	[1167]	GETTABLE 	2 2 -14	; "saved"
	37	[1167]	NEWTABLE 	3 0 0
	38	[1167]	SETTABLE 	2 1 3
	39	[1169]	GETGLOBAL	2 -15	; os
	40	[1169]	GETTABLE 	2 2 -16	; "date"
	41	[1169]	LOADK    	3 -17	; "%Y-%m-%d %H:%M:%S"
	42	[1169]	CALL     	2 2 2
	43	[1170]	NEWTABLE 	3 0 6
	44	[1171]	SETTABLE 	3 -18 2	; "datetime" -
	45	[1172]	GETTABLE 	4 0 -9	; "selected_text"
	46	[1172]	GETTABLE 	4 4 -19	; "text"
	47	[1172]	SETTABLE 	3 -19 4	; "text" -
	48	[1173]	GETTABLE 	4 0 -9	; "selected_text"
	49	[1173]	GETTABLE 	4 4 -10	; "pos0"
	50	[1173]	SETTABLE 	3 -10 4	; "pos0" -
	51	[1174]	GETTABLE 	4 0 -9	; "selected_text"
	52	[1174]	GETTABLE 	4 4 -11	; "pos1"
	53	[1174]	SETTABLE 	3 -11 4	; "pos1" -
	54	[1175]	GETTABLE 	4 0 -9	; "selected_text"
	55	[1175]	GETTABLE 	4 4 -20	; "pboxes"
	56	[1175]	SETTABLE 	3 -20 4	; "pboxes" -
	57	[1176]	GETTABLE 	4 0 -12	; "view"
	58	[1176]	GETTABLE 	4 4 -13	; "highlight"
	59	[1176]	GETTABLE 	4 4 -22	; "saved_drawer"
	60	[1176]	SETTABLE 	3 -21 4	; "drawer" -
	61	[1178]	GETGLOBAL	4 -23	; table
	62	[1178]	GETTABLE 	4 4 -24	; "insert"
	63	[1178]	GETTABLE 	5 0 -12	; "view"
	64	[1178]	GETTABLE 	5 5 -13	; "highlight"
	65	[1178]	GETTABLE 	5 5 -14	; "saved"
	66	[1178]	GETTABLE 	5 5 1
	67	[1178]	MOVE     	6 3
	68	[1178]	CALL     	4 3 1
	69	[1179]	SELF     	4 0 -25	; "getHighlightBookmarkItem"
	70	[1179]	CALL     	4 2 2
	71	[1180]	TEST     	4 0 0
	72	[1180]	JMP      	5	; to 78
	73	[1181]	GETTABLE 	5 0 -1	; "ui"
	74	[1181]	GETTABLE 	5 5 -26	; "bookmark"
	75	[1181]	SELF     	5 5 -27	; "addBookmark"
	76	[1181]	MOVE     	7 4
	77	[1181]	CALL     	5 3 1
	78	[1191]	GETTABLE 	5 0 -9	; "selected_text"
	79	[1191]	GETTABLE 	5 5 -20	; "pboxes"
	80	[1191]	TEST     	5 0 0
	81	[1191]	JMP      	4	; to 86
	82	[1192]	SELF     	5 0 -28	; "exportToDocument"
	83	[1192]	MOVE     	7 1
	84	[1192]	MOVE     	8 3
	85	[1192]	CALL     	5 4 1
	86	[1194]	MOVE     	5 1
	87	[1194]	GETTABLE 	6 0 -12	; "view"
	88	[1194]	GETTABLE 	6 6 -13	; "highlight"
	89	[1194]	GETTABLE 	6 6 -14	; "saved"
	90	[1194]	GETTABLE 	6 6 1
	91	[1194]	LEN      	6 6
	92	[1194]	RETURN   	5 3
	93	[1196]	RETURN   	0 1

function <./frontend/apps/reader/modules/readerhighlight.lua:1217,1232> (37 instructions, 148 bytes at 0x7f869cc16ce0)
3 params, 12 slots, 4 upvalues, 5 locals, 18 constants, 0 functions
	1	[1218]	GETGLOBAL	3 -1	; G_reader_settings
	2	[1218]	SELF     	3 3 -2	; "readSetting"
	3	[1218]	LOADK    	5 -3	; "save_document"
	4	[1218]	CALL     	3 3 2
	5	[1219]	EQ       	0 3 -4	; - "disable"
	6	[1219]	JMP      	1	; to 8
	7	[1219]	RETURN   	0 1
	8	[1220]	GETUPVAL 	4 0	; logger
	9	[1220]	GETTABLE 	4 4 -5	; "dbg"
	10	[1220]	LOADK    	5 -6	; "export highlight to document"
	11	[1220]	MOVE     	6 2
	12	[1220]	CALL     	4 3 1
	13	[1221]	GETTABLE 	4 0 -7	; "ui"
	14	[1221]	GETTABLE 	4 4 -8	; "document"
	15	[1221]	SELF     	4 4 -9	; "saveHighlight"
	16	[1221]	MOVE     	6 1
	17	[1221]	MOVE     	7 2
	18	[1221]	CALL     	4 4 2
	19	[1222]	EQ       	0 4 -10	; - false
	20	[1222]	JMP      	16	; to 37
	21	[1222]	GETTABLE 	5 0 -11	; "warned_once"
	22	[1222]	TEST     	5 0 1
	23	[1222]	JMP      	13	; to 37
	24	[1223]	SETTABLE 	0 -11 -12	; "warned_once" true
	25	[1224]	GETUPVAL 	5 1	; UIManager
	26	[1224]	SELF     	5 5 -13	; "show"
	27	[1224]	GETUPVAL 	7 2	; InfoMessage
	28	[1224]	SELF     	7 7 -14	; "new"
	29	[1224]	NEWTABLE 	9 0 2
	30	[1225]	GETUPVAL 	10 3	; _
	31	[1228]	LOADK    	11 -16	; "Highlights in this document will be saved in the settings file, but they won't be written in the document itself because the file is in a read-only location.\n\nIf you wish your highlights to be saved in the document, just move it to a writable directory first."
	32	[1225]	CALL     	10 2 2
	33	[1228]	SETTABLE 	9 -15 10	; "text" -
	34	[1229]	SETTABLE 	9 -17 -18	; "timeout" 5
	35	[1224]	CALL     	7 3 0
	36	[1224]	CALL     	5 0 1
	37	[1232]	RETURN   	0 1

function <./frontend/apps/reader/modules/readerhighlight.lua:1234,1239> (18 instructions, 72 bytes at 0x7f869cc14840)
1 param, 8 slots, 2 upvalues, 3 locals, 8 constants, 0 functions
	1	[1235]	SELF     	1 0 -1	; "saveHighlight"
	2	[1235]	CALL     	1 2 3
	3	[1236]	SELF     	3 0 -2	; "editHighlight"
	4	[1236]	MOVE     	5 1
	5	[1236]	MOVE     	6 2
	6	[1236]	CALL     	3 4 1
	7	[1237]	GETUPVAL 	3 0	; UIManager
	8	[1237]	SELF     	3 3 -3	; "close"
	9	[1237]	GETTABLE 	5 0 -4	; "edit_highlight_dialog"
	10	[1237]	CALL     	3 3 1
	11	[1238]	GETTABLE 	3 0 -5	; "ui"
	12	[1238]	SELF     	3 3 -6	; "handleEvent"
	13	[1238]	GETUPVAL 	5 1	; Event
	14	[1238]	SELF     	5 5 -7	; "new"
	15	[1238]	LOADK    	7 -8	; "AddNote"
	16	[1238]	CALL     	5 3 0
	17	[1238]	CALL     	3 0 1
	18	[1239]	RETURN   	0 1

function <./frontend/apps/reader/modules/readerhighlight.lua:1241,1245> (13 instructions, 52 bytes at 0x7f869cc0ee40)
1 param, 7 slots, 1 upvalue, 1 local, 6 constants, 0 functions
	1	[1242]	GETTABLE 	1 0 -1	; "selected_text"
	2	[1242]	TEST     	1 0 0
	3	[1242]	JMP      	9	; to 13
	4	[1243]	GETTABLE 	1 0 -2	; "ui"
	5	[1243]	SELF     	1 1 -3	; "handleEvent"
	6	[1243]	GETUPVAL 	3 0	; Event
	7	[1243]	SELF     	3 3 -4	; "new"
	8	[1243]	LOADK    	5 -5	; "LookupWikipedia"
	9	[1243]	GETTABLE 	6 0 -1	; "selected_text"
	10	[1243]	GETTABLE 	6 6 -6	; "text"
	11	[1243]	CALL     	3 4 0
	12	[1243]	CALL     	1 0 1
	13	[1245]	RETURN   	0 1

function <./frontend/apps/reader/modules/readerhighlight.lua:1247,1254> (25 instructions, 100 bytes at 0x7f869cc14240)
1 param, 8 slots, 2 upvalues, 2 locals, 12 constants, 0 functions
	1	[1248]	GETUPVAL 	1 0	; logger
	2	[1248]	GETTABLE 	1 1 -1	; "dbg"
	3	[1248]	LOADK    	2 -2	; "search highlight"
	4	[1248]	CALL     	1 2 1
	5	[1249]	SELF     	1 0 -3	; "highlightFromHoldPos"
	6	[1249]	CALL     	1 2 1
	7	[1250]	GETTABLE 	1 0 -4	; "selected_text"
	8	[1250]	TEST     	1 0 0
	9	[1250]	JMP      	15	; to 25
	10	[1251]	GETGLOBAL	1 -5	; require
	11	[1251]	LOADK    	2 -6	; "util"
	12	[1251]	CALL     	1 2 2
	13	[1251]	GETTABLE 	1 1 -7	; "stripPunctuation"
	14	[1251]	GETTABLE 	2 0 -4	; "selected_text"
	15	[1251]	GETTABLE 	2 2 -8	; "text"
	16	[1251]	CALL     	1 2 2
	17	[1252]	GETTABLE 	2 0 -9	; "ui"
	18	[1252]	SELF     	2 2 -10	; "handleEvent"
	19	[1252]	GETUPVAL 	4 1	; Event
	20	[1252]	SELF     	4 4 -11	; "new"
	21	[1252]	LOADK    	6 -12	; "ShowSearchDialog"
	22	[1252]	MOVE     	7 1
	23	[1252]	CALL     	4 4 0
	24	[1252]	CALL     	2 0 1
	25	[1254]	RETURN   	0 1

function <./frontend/apps/reader/modules/readerhighlight.lua:1256,1262> (19 instructions, 76 bytes at 0x7f869cc10b30)
1 param, 7 slots, 2 upvalues, 1 local, 9 constants, 0 functions
	1	[1257]	GETUPVAL 	1 0	; logger
	2	[1257]	GETTABLE 	1 1 -1	; "dbg"
	3	[1257]	LOADK    	2 -2	; "dictionary lookup highlight"
	4	[1257]	CALL     	1 2 1
	5	[1258]	SELF     	1 0 -3	; "highlightFromHoldPos"
	6	[1258]	CALL     	1 2 1
	7	[1259]	GETTABLE 	1 0 -4	; "selected_text"
	8	[1259]	TEST     	1 0 0
	9	[1259]	JMP      	9	; to 19
	10	[1260]	GETTABLE 	1 0 -5	; "ui"
	11	[1260]	SELF     	1 1 -6	; "handleEvent"
	12	[1260]	GETUPVAL 	3 1	; Event
	13	[1260]	SELF     	3 3 -7	; "new"
	14	[1260]	LOADK    	5 -8	; "LookupWord"
	15	[1260]	GETTABLE 	6 0 -4	; "selected_text"
	16	[1260]	GETTABLE 	6 6 -9	; "text"
	17	[1260]	CALL     	3 4 0
	18	[1260]	CALL     	1 0 1
	19	[1262]	RETURN   	0 1

function <./frontend/apps/reader/modules/readerhighlight.lua:1264,1266> (5 instructions, 20 bytes at 0x7f869cc184b0)
1 param, 3 slots, 1 upvalue, 1 local, 2 constants, 0 functions
	1	[1265]	GETUPVAL 	1 0	; logger
	2	[1265]	GETTABLE 	1 1 -1	; "info"
	3	[1265]	LOADK    	2 -2	; "share highlight"
	4	[1265]	CALL     	1 2 1
	5	[1266]	RETURN   	0 1

function <./frontend/apps/reader/modules/readerhighlight.lua:1268,1270> (5 instructions, 20 bytes at 0x7f869cc18a70)
1 param, 3 slots, 1 upvalue, 1 local, 2 constants, 0 functions
	1	[1269]	GETUPVAL 	1 0	; logger
	2	[1269]	GETTABLE 	1 1 -1	; "info"
	3	[1269]	LOADK    	2 -2	; "more action"
	4	[1269]	CALL     	1 2 1
	5	[1270]	RETURN   	0 1

function <./frontend/apps/reader/modules/readerhighlight.lua:1272,1284> (47 instructions, 188 bytes at 0x7f869cc18d20)
4 params, 9 slots, 2 upvalues, 5 locals, 19 constants, 0 functions
	1	[1273]	GETTABLE 	4 0 -1	; "ui"
	2	[1273]	SELF     	4 4 -2	; "handleEvent"
	3	[1273]	GETUPVAL 	6 0	; Event
	4	[1273]	SELF     	6 6 -3	; "new"
	5	[1273]	LOADK    	8 -4	; "DelHighlight"
	6	[1273]	CALL     	6 3 0
	7	[1273]	CALL     	4 0 1
	8	[1274]	GETUPVAL 	4 1	; logger
	9	[1274]	GETTABLE 	4 4 -5	; "dbg"
	10	[1274]	LOADK    	5 -6	; "delete highlight"
	11	[1274]	MOVE     	6 1
	12	[1274]	MOVE     	7 2
	13	[1274]	CALL     	4 4 1
	14	[1275]	GETGLOBAL	4 -7	; table
	15	[1275]	GETTABLE 	4 4 -8	; "remove"
	16	[1275]	GETTABLE 	5 0 -9	; "view"
	17	[1275]	GETTABLE 	5 5 -10	; "highlight"
	18	[1275]	GETTABLE 	5 5 -11	; "saved"
	19	[1275]	GETTABLE 	5 5 1
	20	[1275]	MOVE     	6 2
	21	[1275]	CALL     	4 3 2
	22	[1276]	TEST     	3 0 0
	23	[1276]	JMP      	6	; to 30
	24	[1277]	GETTABLE 	5 0 -1	; "ui"
	25	[1277]	GETTABLE 	5 5 -12	; "bookmark"
	26	[1277]	SELF     	5 5 -13	; "removeBookmark"
	27	[1277]	MOVE     	7 3
	28	[1277]	CALL     	5 3 1
	29	[1277]	JMP      	17	; to 47
	30	[1279]	GETTABLE 	5 0 -1	; "ui"
	31	[1279]	GETTABLE 	5 5 -12	; "bookmark"
	32	[1279]	SELF     	5 5 -13	; "removeBookmark"
	33	[1279]	NEWTABLE 	7 0 2
	34	[1280]	GETTABLE 	8 0 -1	; "ui"
	35	[1280]	GETTABLE 	8 8 -15	; "document"
	36	[1280]	GETTABLE 	8 8 -16	; "info"
	37	[1280]	GETTABLE 	8 8 -17	; "has_pages"
	38	[1280]	TEST     	8 0 0
	39	[1280]	JMP      	2	; to 42
	40	[1280]	TESTSET  	8 1 1
	41	[1280]	JMP      	1	; to 43
	42	[1280]	GETTABLE 	8 4 -18	; "pos0"
	43	[1280]	SETTABLE 	7 -14 8	; "page" -
	44	[1281]	GETTABLE 	8 4 -19	; "datetime"
	45	[1281]	SETTABLE 	7 -19 8	; "datetime" -
	46	[1279]	CALL     	5 3 1
	47	[1284]	RETURN   	0 1

function <./frontend/apps/reader/modules/readerhighlight.lua:1286,1292> (24 instructions, 96 bytes at 0x7f869cc18f70)
3 params, 8 slots, 0 upvalues, 4 locals, 12 constants, 0 functions
	1	[1287]	GETTABLE 	3 0 -1	; "view"
	2	[1287]	GETTABLE 	3 3 -2	; "highlight"
	3	[1287]	GETTABLE 	3 3 -3	; "saved"
	4	[1287]	GETTABLE 	3 3 1
	5	[1287]	GETTABLE 	3 3 2
	6	[1288]	GETTABLE 	4 0 -4	; "ui"
	7	[1288]	GETTABLE 	4 4 -5	; "bookmark"
	8	[1288]	SELF     	4 4 -6	; "renameBookmark"
	9	[1288]	NEWTABLE 	6 0 2
	10	[1289]	GETTABLE 	7 0 -4	; "ui"
	11	[1289]	GETTABLE 	7 7 -8	; "document"
	12	[1289]	GETTABLE 	7 7 -9	; "info"
	13	[1289]	GETTABLE 	7 7 -10	; "has_pages"
	14	[1289]	TEST     	7 0 0
	15	[1289]	JMP      	2	; to 18
	16	[1289]	TESTSET  	7 1 1
	17	[1289]	JMP      	1	; to 19
	18	[1289]	GETTABLE 	7 3 -11	; "pos0"
	19	[1289]	SETTABLE 	6 -7 7	; "page" -
	20	[1290]	GETTABLE 	7 3 -12	; "datetime"
	21	[1290]	SETTABLE 	6 -12 7	; "datetime" -
	22	[1291]	LOADBOOL 	7 1 0
	23	[1288]	CALL     	4 4 1
	24	[1292]	RETURN   	0 1

function <./frontend/apps/reader/modules/readerhighlight.lua:1294,1301> (27 instructions, 108 bytes at 0x7f869cc19860)
2 params, 6 slots, 0 upvalues, 3 locals, 9 constants, 0 functions
	1	[1295]	GETTABLE 	2 0 -1	; "view"
	2	[1295]	GETTABLE 	2 2 -2	; "highlight"
	3	[1295]	SELF     	3 1 -4	; "readSetting"
	4	[1295]	LOADK    	5 -5	; "highlight_drawer"
	5	[1295]	CALL     	3 3 2
	6	[1295]	TEST     	3 0 1
	7	[1295]	JMP      	3	; to 11
	8	[1295]	GETTABLE 	3 0 -1	; "view"
	9	[1295]	GETTABLE 	3 3 -2	; "highlight"
	10	[1295]	GETTABLE 	3 3 -3	; "saved_drawer"
	11	[1295]	SETTABLE 	2 -3 3	; "saved_drawer" -
	12	[1296]	SELF     	2 1 -4	; "readSetting"
	13	[1296]	LOADK    	4 -6	; "highlight_disabled"
	14	[1296]	CALL     	2 3 2
	15	[1297]	EQ       	0 2 -7	; - nil
	16	[1297]	JMP      	7	; to 24
	17	[1298]	GETGLOBAL	3 -8	; G_reader_settings
	18	[1298]	SELF     	3 3 -4	; "readSetting"
	19	[1298]	LOADK    	5 -6	; "highlight_disabled"
	20	[1298]	CALL     	3 3 2
	21	[1298]	TESTSET  	2 3 1
	22	[1298]	JMP      	1	; to 24
	23	[1298]	LOADBOOL 	2 0 0
	24	[1300]	GETTABLE 	3 0 -1	; "view"
	25	[1300]	GETTABLE 	3 3 -2	; "highlight"
	26	[1300]	SETTABLE 	3 -9 2	; "disabled" -
	27	[1301]	RETURN   	0 1

function <./frontend/apps/reader/modules/readerhighlight.lua:1303,1306> (17 instructions, 68 bytes at 0x7f869cc19a40)
1 param, 5 slots, 0 upvalues, 1 local, 9 constants, 0 functions
	1	[1304]	GETTABLE 	1 0 -1	; "ui"
	2	[1304]	GETTABLE 	1 1 -2	; "doc_settings"
	3	[1304]	SELF     	1 1 -3	; "saveSetting"
	4	[1304]	LOADK    	3 -4	; "highlight_drawer"
	5	[1304]	GETTABLE 	4 0 -5	; "view"
	6	[1304]	GETTABLE 	4 4 -6	; "highlight"
	7	[1304]	GETTABLE 	4 4 -7	; "saved_drawer"
	8	[1304]	CALL     	1 4 1
	9	[1305]	GETTABLE 	1 0 -1	; "ui"
	10	[1305]	GETTABLE 	1 1 -2	; "doc_settings"
	11	[1305]	SELF     	1 1 -3	; "saveSetting"
	12	[1305]	LOADK    	3 -8	; "highlight_disabled"
	13	[1305]	GETTABLE 	4 0 -5	; "view"
	14	[1305]	GETTABLE 	4 4 -6	; "highlight"
	15	[1305]	GETTABLE 	4 4 -9	; "disabled"
	16	[1305]	CALL     	1 4 1
	17	[1306]	RETURN   	0 1

function <./frontend/apps/reader/modules/readerhighlight.lua:1308,1312> (7 instructions, 28 bytes at 0x7f869cc19cf0)
1 param, 4 slots, 1 upvalue, 1 local, 3 constants, 0 functions
	1	[1309]	GETUPVAL 	1 0	; UIManager
	2	[1309]	SELF     	1 1 -1	; "close"
	3	[1309]	GETTABLE 	3 0 -2	; "highlight_dialog"
	4	[1309]	CALL     	1 3 1
	5	[1311]	SELF     	1 0 -3	; "clear"
	6	[1311]	CALL     	1 2 1
	7	[1312]	RETURN   	0 1

function <./frontend/apps/reader/modules/readerhighlight.lua:1314,1332> (35 instructions, 140 bytes at 0x7f869cc1a2a0)
1 param, 9 slots, 3 upvalues, 2 locals, 12 constants, 4 functions
	1	[1315]	GETGLOBAL	1 -1	; G_reader_settings
	2	[1315]	SELF     	1 1 -2	; "isTrue"
	3	[1315]	LOADK    	3 -3	; "highlight_disabled"
	4	[1315]	CALL     	1 3 2
	5	[1316]	GETUPVAL 	2 0	; UIManager
	6	[1316]	SELF     	2 2 -4	; "show"
	7	[1316]	GETUPVAL 	4 1	; MultiConfirmBox
	8	[1316]	SELF     	4 4 -5	; "new"
	9	[1316]	NEWTABLE 	6 0 5
	10	[1317]	TEST     	1 0 0
	11	[1317]	JMP      	5	; to 17
	12	[1317]	GETUPVAL 	7 2	; _
	13	[1317]	LOADK    	8 -7	; "Would you like to enable or disable highlighting by default?\n\nThe current default (\226\152\133) is disabled."
	14	[1317]	CALL     	7 2 2
	15	[1318]	TEST     	7 0 1
	16	[1318]	JMP      	3	; to 20
	17	[1318]	GETUPVAL 	7 2	; _
	18	[1318]	LOADK    	8 -8	; "Would you like to enable or disable highlighting by default?\n\nThe current default (\226\152\133) is enabled."
	19	[1318]	CALL     	7 2 2
	20	[1318]	SETTABLE 	6 -6 7	; "text" -
	21	[1321]	CLOSURE  	7 0	; 0x7f869cc1a600
	22	[1321]	MOVE     	0 1
	23	[1321]	GETUPVAL 	0 2	; _
	24	[1321]	SETTABLE 	6 -9 7	; "choice1_text_func" -
	25	[1324]	CLOSURE  	7 1	; 0x7f869cc1abb0
	26	[1324]	SETTABLE 	6 -10 7	; "choice1_callback" -
	27	[1327]	CLOSURE  	7 2	; 0x7f869cc1ad10
	28	[1327]	MOVE     	0 1
	29	[1327]	GETUPVAL 	0 2	; _
	30	[1327]	SETTABLE 	6 -11 7	; "choice2_text_func" -
	31	[1330]	CLOSURE  	7 3	; 0x7f869cc1b1d0
	32	[1330]	SETTABLE 	6 -12 7	; "choice2_callback" -
	33	[1316]	CALL     	4 3 0
	34	[1316]	CALL     	2 0 1
	35	[1332]	RETURN   	0 1

function <./frontend/apps/reader/modules/readerhighlight.lua:1319,1321> (13 instructions, 52 bytes at 0x7f869cc1a600)
0 params, 2 slots, 2 upvalues, 0 locals, 2 constants, 0 functions
	1	[1320]	GETUPVAL 	0 0	; highlight_disabled
	2	[1320]	TEST     	0 0 0
	3	[1320]	JMP      	5	; to 9
	4	[1320]	GETUPVAL 	0 1	; _
	5	[1320]	LOADK    	1 -1	; "Disable (\226\152\133)"
	6	[1320]	CALL     	0 2 2
	7	[1320]	TEST     	0 0 1
	8	[1320]	JMP      	3	; to 12
	9	[1320]	GETUPVAL 	0 1	; _
	10	[1320]	LOADK    	1 -2	; "Disable"
	11	[1320]	CALL     	0 2 2
	12	[1320]	RETURN   	0 2
	13	[1321]	RETURN   	0 1

function <./frontend/apps/reader/modules/readerhighlight.lua:1322,1324> (6 instructions, 24 bytes at 0x7f869cc1abb0)
0 params, 4 slots, 0 upvalues, 0 locals, 3 constants, 0 functions
	1	[1323]	GETGLOBAL	0 -1	; G_reader_settings
	2	[1323]	SELF     	0 0 -2	; "saveSetting"
	3	[1323]	LOADK    	2 -3	; "highlight_disabled"
	4	[1323]	LOADBOOL 	3 1 0
	5	[1323]	CALL     	0 4 1
	6	[1324]	RETURN   	0 1

function <./frontend/apps/reader/modules/readerhighlight.lua:1325,1327> (13 instructions, 52 bytes at 0x7f869cc1ad10)
0 params, 2 slots, 2 upvalues, 0 locals, 2 constants, 0 functions
	1	[1326]	GETUPVAL 	0 0	; highlight_disabled
	2	[1326]	TEST     	0 0 0
	3	[1326]	JMP      	5	; to 9
	4	[1326]	GETUPVAL 	0 1	; _
	5	[1326]	LOADK    	1 -1	; "Enable"
	6	[1326]	CALL     	0 2 2
	7	[1326]	TEST     	0 0 1
	8	[1326]	JMP      	3	; to 12
	9	[1326]	GETUPVAL 	0 1	; _
	10	[1326]	LOADK    	1 -2	; "Enable (\226\152\133)"
	11	[1326]	CALL     	0 2 2
	12	[1326]	RETURN   	0 2
	13	[1327]	RETURN   	0 1

function <./frontend/apps/reader/modules/readerhighlight.lua:1328,1330> (6 instructions, 24 bytes at 0x7f869cc1b1d0)
0 params, 4 slots, 0 upvalues, 0 locals, 3 constants, 0 functions
	1	[1329]	GETGLOBAL	0 -1	; G_reader_settings
	2	[1329]	SELF     	0 0 -2	; "saveSetting"
	3	[1329]	LOADK    	2 -3	; "highlight_disabled"
	4	[1329]	LOADBOOL 	3 0 0
	5	[1329]	CALL     	0 4 1
	6	[1330]	RETURN   	0 1
