
main <./frontend/readhistory.lua:0,0> (95 instructions, 380 bytes at 0x7fc9b44068c0)
0+ params, 15 slots, 0 upvalues, 13 locals, 33 constants, 21 functions
	1	[1]	GETGLOBAL	0 -1	; require
	2	[1]	LOADK    	1 -2	; "datastorage"
	3	[1]	CALL     	0 2 2
	4	[2]	GETGLOBAL	1 -1	; require
	5	[2]	LOADK    	2 -3	; "docsettings"
	6	[2]	CALL     	1 2 2
	7	[3]	GETGLOBAL	2 -1	; require
	8	[3]	LOADK    	3 -4	; "dump"
	9	[3]	CALL     	2 2 2
	10	[4]	GETGLOBAL	3 -1	; require
	11	[4]	LOADK    	4 -5	; "ffi/util"
	12	[4]	CALL     	3 2 2
	13	[5]	GETGLOBAL	4 -1	; require
	14	[5]	LOADK    	5 -6	; "util"
	15	[5]	CALL     	4 2 2
	16	[5]	GETTABLE 	4 4 -7	; "getFriendlySize"
	17	[6]	GETTABLE 	5 3 -8	; "joinPath"
	18	[7]	GETGLOBAL	6 -1	; require
	19	[7]	LOADK    	7 -9	; "libs/libkoreader-lfs"
	20	[7]	CALL     	6 2 2
	21	[8]	GETTABLE 	7 3 -10	; "realpath"
	22	[10]	MOVE     	8 5
	23	[10]	SELF     	9 0 -11	; "getDataDir"
	24	[10]	CALL     	9 2 2
	25	[10]	LOADK    	10 -12	; "history.lua"
	26	[10]	CALL     	8 3 2
	27	[12]	NEWTABLE 	9 0 2
	28	[13]	NEWTABLE 	10 0 0
	29	[13]	SETTABLE 	9 -13 10	; "hist" -
	30	[14]	SETTABLE 	9 -14 -15	; "last_read_time" 0
	31	[30]	CLOSURE  	10 0	; 0x7fc9b4406c80
	32	[30]	MOVE     	0 6
	33	[30]	MOVE     	0 7
	34	[30]	MOVE     	0 4
	35	[38]	CLOSURE  	11 1	; 0x7fc9b4407040
	36	[46]	CLOSURE  	12 2	; 0x7fc9b4407ca0
	37	[54]	CLOSURE  	13 3	; 0x7fc9b44081a0
	38	[48]	SETTABLE 	9 -16 13	; "_indexing" -
	39	[72]	CLOSURE  	13 4	; 0x7fc9b44070c0
	40	[72]	MOVE     	0 11
	41	[72]	MOVE     	0 12
	42	[56]	SETTABLE 	9 -17 13	; "_sort" -
	43	[81]	CLOSURE  	13 5	; 0x7fc9b4408f90
	44	[76]	SETTABLE 	9 -18 13	; "_reduce" -
	45	[97]	CLOSURE  	13 6	; 0x7fc9b4409050
	46	[97]	MOVE     	0 8
	47	[97]	MOVE     	0 2
	48	[97]	MOVE     	0 3
	49	[84]	SETTABLE 	9 -19 13	; "_flush" -
	50	[116]	CLOSURE  	13 7	; 0x7fc9b4407de0
	51	[116]	MOVE     	0 6
	52	[116]	MOVE     	0 8
	53	[116]	MOVE     	0 10
	54	[101]	SETTABLE 	9 -20 13	; "_read" -
	55	[137]	CLOSURE  	13 8	; 0x7fc9b4409800
	56	[137]	MOVE     	0 0
	57	[137]	MOVE     	0 6
	58	[137]	MOVE     	0 5
	59	[137]	MOVE     	0 1
	60	[137]	MOVE     	0 10
	61	[119]	SETTABLE 	9 -21 13	; "_readLegacyHistory" -
	62	[142]	CLOSURE  	13 9	; 0x7fc9b4409dc0
	63	[139]	SETTABLE 	9 -22 13	; "_init" -
	64	[153]	CLOSURE  	13 10	; 0x7fc9b440a450
	65	[153]	MOVE     	0 6
	66	[144]	SETTABLE 	9 -23 13	; "ensureLastFile" -
	67	[158]	CLOSURE  	13 11	; 0x7fc9b440abb0
	68	[155]	SETTABLE 	9 -24 13	; "getLastFile" -
	69	[174]	CLOSURE  	13 12	; 0x7fc9b44079d0
	70	[174]	MOVE     	0 6
	71	[160]	SETTABLE 	9 -25 13	; "getPreviousFile" -
	72	[189]	CLOSURE  	13 13	; 0x7fc9b440b010
	73	[176]	SETTABLE 	9 -26 13	; "fileDeleted" -
	74	[196]	CLOSURE  	13 14	; 0x7fc9b4408ce0
	75	[191]	SETTABLE 	9 -27 13	; "fileSettingsPurged" -
	76	[206]	CLOSURE  	13 15	; 0x7fc9b440b250
	77	[206]	MOVE     	0 6
	78	[198]	SETTABLE 	9 -28 13	; "clearMissing" -
	79	[217]	CLOSURE  	13 16	; 0x7fc9b440a380
	80	[208]	SETTABLE 	9 -29 13	; "removeItemByPath" -
	81	[237]	CLOSURE  	13 17	; 0x7fc9b4409c80
	82	[219]	SETTABLE 	9 -30 13	; "updateItemByPath" -
	83	[246]	CLOSURE  	13 18	; 0x7fc9b440b9e0
	84	[246]	MOVE     	0 1
	85	[239]	SETTABLE 	9 -31 13	; "removeItem" -
	86	[265]	CLOSURE  	13 19	; 0x7fc9b440ba60
	87	[265]	MOVE     	0 6
	88	[265]	MOVE     	0 10
	89	[248]	SETTABLE 	9 -32 13	; "addItem" -
	90	[279]	CLOSURE  	13 20	; 0x7fc9b440c3b0
	91	[269]	SETTABLE 	9 -33 13	; "reload" -
	92	[281]	SELF     	13 9 -22	; "_init"
	93	[281]	CALL     	13 2 1
	94	[283]	RETURN   	9 2
	95	[283]	RETURN   	0 1

function <./frontend/readhistory.lua:17,30> (43 instructions, 172 bytes at 0x7fc9b4406c80)
2 params, 8 slots, 3 upvalues, 3 locals, 13 constants, 1 function
	1	[18]	GETUPVAL 	2 0	; lfs
	2	[18]	GETTABLE 	2 2 -1	; "attributes"
	3	[18]	MOVE     	3 1
	4	[18]	LOADK    	4 -2	; "mode"
	5	[18]	CALL     	2 3 2
	6	[18]	EQ       	1 2 -3	; - "file"
	7	[18]	JMP      	1	; to 9
	8	[18]	LOADBOOL 	2 0 1
	9	[18]	LOADBOOL 	2 1 0
	10	[19]	NEWTABLE 	3 0 6
	11	[20]	SETTABLE 	3 -4 0	; "time" -
	12	[21]	SELF     	4 1 -6	; "gsub"
	13	[21]	LOADK    	6 -7	; ".*/"
	14	[21]	LOADK    	7 -8	; ""
	15	[21]	CALL     	4 4 2
	16	[21]	SETTABLE 	3 -5 4	; "text" -
	17	[22]	GETUPVAL 	4 1	; realpath
	18	[22]	MOVE     	5 1
	19	[22]	CALL     	4 2 2
	20	[22]	TEST     	4 0 1
	21	[22]	JMP      	1	; to 23
	22	[22]	MOVE     	4 1
	23	[22]	SETTABLE 	3 -3 4	; "file" -
	24	[23]	NOT      	4 2
	25	[23]	SETTABLE 	3 -9 4	; "dim" -
	26	[24]	TESTSET  	4 2 0
	27	[24]	JMP      	10	; to 38
	28	[24]	GETUPVAL 	4 2	; getFriendlySize
	29	[24]	GETUPVAL 	5 0	; lfs
	30	[24]	GETTABLE 	5 5 -1	; "attributes"
	31	[24]	MOVE     	6 1
	32	[24]	LOADK    	7 -11	; "size"
	33	[24]	CALL     	5 3 2
	34	[24]	TEST     	5 0 1
	35	[24]	JMP      	1	; to 37
	36	[24]	LOADK    	5 -12	; 0
	37	[24]	CALL     	4 2 2
	38	[24]	SETTABLE 	3 -10 4	; "mandatory" -
	39	[28]	CLOSURE  	4 0	; 0x7fc9b4406720
	40	[28]	MOVE     	0 1
	41	[28]	SETTABLE 	3 -13 4	; "callback" -
	42	[29]	RETURN   	3 2
	43	[30]	RETURN   	0 1

function <./frontend/readhistory.lua:25,28> (7 instructions, 28 bytes at 0x7fc9b4406720)
0 params, 4 slots, 1 upvalue, 1 local, 3 constants, 0 functions
	1	[26]	GETGLOBAL	0 -1	; require
	2	[26]	LOADK    	1 -2	; "apps/reader/readerui"
	3	[26]	CALL     	0 2 2
	4	[27]	SELF     	1 0 -3	; "showReader"
	5	[27]	GETUPVAL 	3 0	; input_file
	6	[27]	CALL     	1 3 1
	7	[28]	RETURN   	0 1

function <./frontend/readhistory.lua:32,38> (20 instructions, 80 bytes at 0x7fc9b4407040)
2 params, 4 slots, 0 upvalues, 2 locals, 2 constants, 0 functions
	1	[33]	GETTABLE 	2 0 -1	; "file"
	2	[33]	GETTABLE 	3 1 -1	; "file"
	3	[33]	EQ       	0 2 3
	4	[33]	JMP      	8	; to 13
	5	[34]	GETTABLE 	2 0 -2	; "time"
	6	[34]	GETTABLE 	3 1 -2	; "time"
	7	[34]	LT       	1 3 2
	8	[34]	JMP      	1	; to 10
	9	[34]	LOADBOOL 	2 0 1
	10	[34]	LOADBOOL 	2 1 0
	11	[34]	RETURN   	2 2
	12	[34]	JMP      	7	; to 20
	13	[36]	GETTABLE 	2 0 -1	; "file"
	14	[36]	GETTABLE 	3 1 -1	; "file"
	15	[36]	LT       	1 2 3
	16	[36]	JMP      	1	; to 18
	17	[36]	LOADBOOL 	2 0 1
	18	[36]	LOADBOOL 	2 1 0
	19	[36]	RETURN   	2 2
	20	[38]	RETURN   	0 1

function <./frontend/readhistory.lua:40,46> (20 instructions, 80 bytes at 0x7fc9b4407ca0)
2 params, 4 slots, 0 upvalues, 2 locals, 2 constants, 0 functions
	1	[41]	GETTABLE 	2 0 -1	; "time"
	2	[41]	GETTABLE 	3 1 -1	; "time"
	3	[41]	EQ       	0 2 3
	4	[41]	JMP      	8	; to 13
	5	[42]	GETTABLE 	2 0 -2	; "file"
	6	[42]	GETTABLE 	3 1 -2	; "file"
	7	[42]	LT       	1 2 3
	8	[42]	JMP      	1	; to 10
	9	[42]	LOADBOOL 	2 0 1
	10	[42]	LOADBOOL 	2 1 0
	11	[42]	RETURN   	2 2
	12	[42]	JMP      	7	; to 20
	13	[44]	GETTABLE 	2 0 -1	; "time"
	14	[44]	GETTABLE 	3 1 -1	; "time"
	15	[44]	LT       	1 3 2
	16	[44]	JMP      	1	; to 18
	17	[44]	LOADBOOL 	2 0 1
	18	[44]	LOADBOOL 	2 1 0
	19	[44]	RETURN   	2 2
	20	[46]	RETURN   	0 1

function <./frontend/readhistory.lua:48,54> (16 instructions, 64 bytes at 0x7fc9b44081a0)
2 params, 7 slots, 0 upvalues, 6 locals, 5 constants, 0 functions
	1	[49]	GETGLOBAL	2 -1	; assert
	2	[49]	EQ       	0 0 -2	; - nil
	3	[49]	JMP      	1	; to 5
	4	[49]	LOADBOOL 	3 0 1
	5	[49]	LOADBOOL 	3 1 0
	6	[49]	CALL     	2 2 1
	7	[51]	MOVE     	2 1
	8	[51]	GETTABLE 	3 0 -3	; "hist"
	9	[51]	LEN      	3 3
	10	[51]	LOADK    	4 -4	; 1
	11	[51]	FORPREP  	2 3	; to 15
	12	[52]	GETTABLE 	6 0 -3	; "hist"
	13	[52]	GETTABLE 	6 6 5
	14	[52]	SETTABLE 	6 -5 5	; "index" -
	15	[51]	FORLOOP  	2 -4	; to 12
	16	[54]	RETURN   	0 1

function <./frontend/readhistory.lua:56,72> (49 instructions, 196 bytes at 0x7fc9b44070c0)
1 param, 9 slots, 2 upvalues, 6 locals, 15 constants, 0 functions
	1	[57]	GETGLOBAL	1 -1	; assert
	2	[57]	EQ       	0 0 -2	; - nil
	3	[57]	JMP      	1	; to 5
	4	[57]	LOADBOOL 	2 0 1
	5	[57]	LOADBOOL 	2 1 0
	6	[57]	CALL     	1 2 1
	7	[59]	GETGLOBAL	1 -3	; G_reader_settings
	8	[59]	SELF     	1 1 -4	; "nilOrFalse"
	9	[59]	LOADK    	3 -5	; "autoremove_deleted_items_from_history"
	10	[59]	CALL     	1 3 2
	11	[59]	NOT      	1 1
	12	[60]	TEST     	1 0 0
	13	[60]	JMP      	2	; to 16
	14	[61]	SELF     	2 0 -6	; "clearMissing"
	15	[61]	CALL     	2 2 1
	16	[63]	GETGLOBAL	2 -7	; table
	17	[63]	GETTABLE 	2 2 -8	; "sort"
	18	[63]	GETTABLE 	3 0 -9	; "hist"
	19	[63]	GETUPVAL 	4 0	; fileFirstOrdering
	20	[63]	CALL     	2 3 1
	21	[65]	GETTABLE 	2 0 -9	; "hist"
	22	[65]	LEN      	2 2
	23	[65]	LOADK    	3 -10	; 2
	24	[65]	LOADK    	4 -11	; -1
	25	[65]	FORPREP  	2 14	; to 40
	26	[66]	GETTABLE 	6 0 -9	; "hist"
	27	[66]	GETTABLE 	6 6 5
	28	[66]	GETTABLE 	6 6 -12	; "file"
	29	[66]	GETTABLE 	7 0 -9	; "hist"
	30	[66]	SUB      	8 5 -13	; - 1
	31	[66]	GETTABLE 	7 7 8
	32	[66]	GETTABLE 	7 7 -12	; "file"
	33	[66]	EQ       	0 6 7
	34	[66]	JMP      	5	; to 40
	35	[67]	GETGLOBAL	6 -7	; table
	36	[67]	GETTABLE 	6 6 -14	; "remove"
	37	[67]	GETTABLE 	7 0 -9	; "hist"
	38	[67]	MOVE     	8 5
	39	[67]	CALL     	6 3 1
	40	[65]	FORLOOP  	2 -15	; to 26
	41	[70]	GETGLOBAL	2 -7	; table
	42	[70]	GETTABLE 	2 2 -8	; "sort"
	43	[70]	GETTABLE 	3 0 -9	; "hist"
	44	[70]	GETUPVAL 	4 1	; timeFirstOrdering
	45	[70]	CALL     	2 3 1
	46	[71]	SELF     	2 0 -15	; "_indexing"
	47	[71]	LOADK    	4 -13	; 1
	48	[71]	CALL     	2 3 1
	49	[72]	RETURN   	0 1

function <./frontend/readhistory.lua:76,81> (18 instructions, 72 bytes at 0x7fc9b4408f90)
1 param, 4 slots, 0 upvalues, 1 local, 6 constants, 0 functions
	1	[77]	GETGLOBAL	1 -1	; assert
	2	[77]	EQ       	0 0 -2	; - nil
	3	[77]	JMP      	1	; to 5
	4	[77]	LOADBOOL 	2 0 1
	5	[77]	LOADBOOL 	2 1 0
	6	[77]	CALL     	1 2 1
	7	[78]	GETTABLE 	1 0 -3	; "hist"
	8	[78]	LEN      	1 1
	9	[78]	LT       	0 -4 1	; 500 -
	10	[78]	JMP      	7	; to 18
	11	[79]	GETGLOBAL	1 -5	; table
	12	[79]	GETTABLE 	1 1 -6	; "remove"
	13	[79]	GETTABLE 	2 0 -3	; "hist"
	14	[79]	GETTABLE 	3 0 -3	; "hist"
	15	[79]	LEN      	3 3
	16	[79]	CALL     	1 3 1
	17	[79]	JMP      	-11	; to 7
	18	[81]	RETURN   	0 1

function <./frontend/readhistory.lua:84,97> (39 instructions, 156 bytes at 0x7fc9b4409050)
1 param, 9 slots, 3 upvalues, 8 locals, 14 constants, 0 functions
	1	[85]	GETGLOBAL	1 -1	; assert
	2	[85]	EQ       	0 0 -2	; - nil
	3	[85]	JMP      	1	; to 5
	4	[85]	LOADBOOL 	2 0 1
	5	[85]	LOADBOOL 	2 1 0
	6	[85]	CALL     	1 2 1
	7	[86]	NEWTABLE 	1 0 0
	8	[87]	GETGLOBAL	2 -3	; pairs
	9	[87]	GETTABLE 	3 0 -4	; "hist"
	10	[87]	CALL     	2 2 4
	11	[87]	JMP      	6	; to 18
	12	[88]	NEWTABLE 	7 0 2
	13	[89]	GETTABLE 	8 6 -5	; "time"
	14	[89]	SETTABLE 	7 -5 8	; "time" -
	15	[90]	GETTABLE 	8 6 -6	; "file"
	16	[90]	SETTABLE 	7 -6 8	; "file" -
	17	[91]	SETTABLE 	1 5 7
	18	[87]	TFORLOOP 	2 2
	19	[91]	JMP      	-8	; to 12
	20	[93]	GETGLOBAL	2 -7	; io
	21	[93]	GETTABLE 	2 2 -8	; "open"
	22	[93]	GETUPVAL 	3 0	; history_file
	23	[93]	LOADK    	4 -9	; "w"
	24	[93]	CALL     	2 3 2
	25	[94]	SELF     	3 2 -10	; "write"
	26	[94]	LOADK    	5 -11	; "return "
	27	[94]	GETUPVAL 	6 1	; dump
	28	[94]	MOVE     	7 1
	29	[94]	CALL     	6 2 2
	30	[94]	LOADK    	7 -12	; "\n"
	31	[94]	CONCAT   	5 5 7
	32	[94]	CALL     	3 3 1
	33	[95]	GETUPVAL 	3 2	; ffiutil
	34	[95]	GETTABLE 	3 3 -13	; "fsyncOpenedFile"
	35	[95]	MOVE     	4 2
	36	[95]	CALL     	3 2 1
	37	[96]	SELF     	3 2 -14	; "close"
	38	[96]	CALL     	3 2 1
	39	[97]	RETURN   	0 1

function <./frontend/readhistory.lua:101,116> (44 instructions, 176 bytes at 0x7fc9b4407de0)
1 param, 14 slots, 3 upvalues, 9 locals, 13 constants, 0 functions
	1	[102]	GETGLOBAL	1 -1	; assert
	2	[102]	EQ       	0 0 -2	; - nil
	3	[102]	JMP      	1	; to 5
	4	[102]	LOADBOOL 	2 0 1
	5	[102]	LOADBOOL 	2 1 0
	6	[102]	CALL     	1 2 1
	7	[103]	GETUPVAL 	1 0	; lfs
	8	[103]	GETTABLE 	1 1 -3	; "attributes"
	9	[103]	GETUPVAL 	2 1	; history_file
	10	[103]	LOADK    	3 -4	; "modification"
	11	[103]	CALL     	1 3 2
	12	[104]	EQ       	1 1 -2	; - nil
	13	[104]	JMP      	3	; to 17
	14	[105]	GETTABLE 	2 0 -5	; "last_read_time"
	15	[105]	LE       	0 1 2
	16	[105]	JMP      	2	; to 19
	17	[106]	LOADBOOL 	2 0 0
	18	[106]	RETURN   	2 2
	19	[108]	SETTABLE 	0 -5 1	; "last_read_time" -
	20	[109]	GETGLOBAL	2 -6	; pcall
	21	[109]	GETGLOBAL	3 -7	; dofile
	22	[109]	GETUPVAL 	4 1	; history_file
	23	[109]	CALL     	2 3 3
	24	[110]	TEST     	2 0 0
	25	[110]	JMP      	16	; to 42
	26	[110]	TEST     	3 0 0
	27	[110]	JMP      	14	; to 42
	28	[111]	GETGLOBAL	4 -8	; pairs
	29	[111]	MOVE     	5 3
	30	[111]	CALL     	4 2 4
	31	[111]	JMP      	8	; to 40
	32	[112]	GETGLOBAL	9 -9	; table
	33	[112]	GETTABLE 	9 9 -10	; "insert"
	34	[112]	GETTABLE 	10 0 -11	; "hist"
	35	[112]	GETUPVAL 	11 2	; buildEntry
	36	[112]	GETTABLE 	12 8 -12	; "time"
	37	[112]	GETTABLE 	13 8 -13	; "file"
	38	[112]	CALL     	11 3 0
	39	[112]	CALL     	9 0 1
	40	[111]	TFORLOOP 	4 2
	41	[112]	JMP      	-10	; to 32
	42	[115]	LOADBOOL 	4 1 0
	43	[115]	RETURN   	4 2
	44	[116]	RETURN   	0 1

function <./frontend/readhistory.lua:119,137> (63 instructions, 252 bytes at 0x7fc9b4409800)
1 param, 15 slots, 5 upvalues, 8 locals, 14 constants, 0 functions
	1	[120]	GETGLOBAL	1 -1	; assert
	2	[120]	EQ       	0 0 -2	; - nil
	3	[120]	JMP      	1	; to 5
	4	[120]	LOADBOOL 	2 0 1
	5	[120]	LOADBOOL 	2 1 0
	6	[120]	CALL     	1 2 1
	7	[121]	GETUPVAL 	1 0	; DataStorage
	8	[121]	SELF     	1 1 -3	; "getHistoryDir"
	9	[121]	CALL     	1 2 2
	10	[122]	GETUPVAL 	2 1	; lfs
	11	[122]	GETTABLE 	2 2 -4	; "dir"
	12	[122]	MOVE     	3 1
	13	[122]	CALL     	2 2 4
	14	[122]	JMP      	46	; to 61
	15	[123]	GETUPVAL 	6 2	; joinPath
	16	[123]	MOVE     	7 1
	17	[123]	MOVE     	8 5
	18	[123]	CALL     	6 3 2
	19	[124]	GETUPVAL 	7 1	; lfs
	20	[124]	GETTABLE 	7 7 -5	; "attributes"
	21	[124]	MOVE     	8 6
	22	[124]	LOADK    	9 -6	; "mode"
	23	[124]	CALL     	7 3 2
	24	[124]	EQ       	0 7 -7	; - "file"
	25	[124]	JMP      	35	; to 61
	26	[125]	GETUPVAL 	7 3	; DocSettings
	27	[125]	SELF     	7 7 -8	; "getPathFromHistory"
	28	[125]	MOVE     	9 5
	29	[125]	CALL     	7 3 2
	30	[125]	MOVE     	6 7
	31	[126]	EQ       	1 6 -2	; - nil
	32	[126]	JMP      	28	; to 61
	33	[126]	EQ       	1 6 -9	; - ""
	34	[126]	JMP      	26	; to 61
	35	[127]	GETUPVAL 	7 3	; DocSettings
	36	[127]	SELF     	7 7 -10	; "getNameFromHistory"
	37	[127]	MOVE     	9 5
	38	[127]	CALL     	7 3 2
	39	[128]	EQ       	1 7 -2	; - nil
	40	[128]	JMP      	20	; to 61
	41	[128]	EQ       	1 7 -9	; - ""
	42	[128]	JMP      	18	; to 61
	43	[129]	GETGLOBAL	8 -11	; table
	44	[129]	GETTABLE 	8 8 -12	; "insert"
	45	[130]	GETTABLE 	9 0 -13	; "hist"
	46	[131]	GETUPVAL 	10 4	; buildEntry
	47	[131]	GETUPVAL 	11 1	; lfs
	48	[131]	GETTABLE 	11 11 -5	; "attributes"
	49	[131]	GETUPVAL 	12 2	; joinPath
	50	[131]	MOVE     	13 1
	51	[131]	MOVE     	14 5
	52	[131]	CALL     	12 3 2
	53	[131]	LOADK    	13 -14	; "modification"
	54	[131]	CALL     	11 3 2
	55	[132]	GETUPVAL 	12 2	; joinPath
	56	[132]	MOVE     	13 6
	57	[132]	MOVE     	14 7
	58	[132]	CALL     	12 3 0
	59	[131]	CALL     	10 0 0
	60	[129]	CALL     	8 0 1
	61	[122]	TFORLOOP 	2 1
	62	[135]	JMP      	-48	; to 15
	63	[137]	RETURN   	0 1

function <./frontend/readhistory.lua:139,142> (9 instructions, 36 bytes at 0x7fc9b4409dc0)
1 param, 3 slots, 0 upvalues, 1 local, 3 constants, 0 functions
	1	[140]	GETGLOBAL	1 -1	; assert
	2	[140]	EQ       	0 0 -2	; - nil
	3	[140]	JMP      	1	; to 5
	4	[140]	LOADBOOL 	2 0 1
	5	[140]	LOADBOOL 	2 1 0
	6	[140]	CALL     	1 2 1
	7	[141]	SELF     	1 0 -3	; "reload"
	8	[141]	CALL     	1 2 1
	9	[142]	RETURN   	0 1

function <./frontend/readhistory.lua:144,153> (25 instructions, 100 bytes at 0x7fc9b440a450)
1 param, 9 slots, 1 upvalue, 6 locals, 8 constants, 0 functions
	1	[146]	LOADK    	2 -1	; 1
	2	[146]	GETTABLE 	3 0 -2	; "hist"
	3	[146]	LEN      	3 3
	4	[146]	LOADK    	4 -1	; 1
	5	[146]	FORPREP  	2 13	; to 19
	6	[147]	GETUPVAL 	6 0	; lfs
	7	[147]	GETTABLE 	6 6 -3	; "attributes"
	8	[147]	GETTABLE 	7 0 -2	; "hist"
	9	[147]	GETTABLE 	7 7 5
	10	[147]	GETTABLE 	7 7 -4	; "file"
	11	[147]	LOADK    	8 -5	; "mode"
	12	[147]	CALL     	6 3 2
	13	[147]	EQ       	0 6 -4	; - "file"
	14	[147]	JMP      	4	; to 19
	15	[148]	GETTABLE 	6 0 -2	; "hist"
	16	[148]	GETTABLE 	6 6 5
	17	[148]	GETTABLE 	1 6 -4	; "file"
	18	[149]	JMP      	1	; to 20
	19	[146]	FORLOOP  	2 -14	; to 6
	20	[152]	GETGLOBAL	2 -6	; G_reader_settings
	21	[152]	SELF     	2 2 -7	; "saveSetting"
	22	[152]	LOADK    	4 -8	; "lastfile"
	23	[152]	MOVE     	5 1
	24	[152]	CALL     	2 4 1
	25	[153]	RETURN   	0 1

function <./frontend/readhistory.lua:155,158> (8 instructions, 32 bytes at 0x7fc9b440abb0)
1 param, 4 slots, 0 upvalues, 1 local, 4 constants, 0 functions
	1	[156]	SELF     	1 0 -1	; "ensureLastFile"
	2	[156]	CALL     	1 2 1
	3	[157]	GETGLOBAL	1 -2	; G_reader_settings
	4	[157]	SELF     	1 1 -3	; "readSetting"
	5	[157]	LOADK    	3 -4	; "lastfile"
	6	[157]	TAILCALL 	1 3 0
	7	[157]	RETURN   	1 0
	8	[158]	RETURN   	0 1

function <./frontend/readhistory.lua:160,174> (27 instructions, 108 bytes at 0x7fc9b44079d0)
2 params, 10 slots, 1 upvalue, 7 locals, 8 constants, 0 functions
	1	[164]	TEST     	1 0 1
	2	[164]	JMP      	5	; to 8
	3	[165]	GETGLOBAL	2 -1	; G_reader_settings
	4	[165]	SELF     	2 2 -2	; "readSetting"
	5	[165]	LOADK    	4 -3	; "lastfile"
	6	[165]	CALL     	2 3 2
	7	[165]	MOVE     	1 2
	8	[167]	LOADK    	2 -4	; 1
	9	[167]	GETTABLE 	3 0 -5	; "hist"
	10	[167]	LEN      	3 3
	11	[167]	LOADK    	4 -4	; 1
	12	[167]	FORPREP  	2 13	; to 26
	13	[169]	GETTABLE 	6 0 -5	; "hist"
	14	[169]	GETTABLE 	6 6 5
	15	[169]	GETTABLE 	6 6 -6	; "file"
	16	[170]	EQ       	1 6 1
	17	[170]	JMP      	8	; to 26
	18	[170]	GETUPVAL 	7 0	; lfs
	19	[170]	GETTABLE 	7 7 -7	; "attributes"
	20	[170]	MOVE     	8 6
	21	[170]	LOADK    	9 -8	; "mode"
	22	[170]	CALL     	7 3 2
	23	[170]	EQ       	0 7 -6	; - "file"
	24	[170]	JMP      	1	; to 26
	25	[171]	RETURN   	6 2
	26	[167]	FORLOOP  	2 -14	; to 13
	27	[174]	RETURN   	0 1

function <./frontend/readhistory.lua:176,189> (28 instructions, 112 bytes at 0x7fc9b440b010)
2 params, 7 slots, 0 upvalues, 6 locals, 10 constants, 0 functions
	1	[177]	GETGLOBAL	2 -1	; G_reader_settings
	2	[177]	SELF     	2 2 -2	; "readSetting"
	3	[177]	LOADK    	4 -3	; "autoremove_deleted_items_from_history"
	4	[177]	CALL     	2 3 2
	5	[177]	TEST     	2 0 0
	6	[177]	JMP      	4	; to 11
	7	[178]	SELF     	2 0 -4	; "removeItemByPath"
	8	[178]	MOVE     	4 1
	9	[178]	CALL     	2 3 1
	10	[178]	JMP      	17	; to 28
	11	[181]	LOADK    	2 -5	; 1
	12	[181]	GETTABLE 	3 0 -6	; "hist"
	13	[181]	LEN      	3 3
	14	[181]	LOADK    	4 -5	; 1
	15	[181]	FORPREP  	2 9	; to 25
	16	[182]	GETTABLE 	6 0 -6	; "hist"
	17	[182]	GETTABLE 	6 6 5
	18	[182]	GETTABLE 	6 6 -7	; "file"
	19	[182]	EQ       	0 6 1
	20	[182]	JMP      	4	; to 25
	21	[183]	GETTABLE 	6 0 -6	; "hist"
	22	[183]	GETTABLE 	6 6 5
	23	[183]	SETTABLE 	6 -8 -9	; "dim" true
	24	[184]	JMP      	1	; to 26
	25	[181]	FORLOOP  	2 -10	; to 16
	26	[187]	SELF     	2 0 -10	; "ensureLastFile"
	27	[187]	CALL     	2 2 1
	28	[189]	RETURN   	0 1

function <./frontend/readhistory.lua:191,196> (10 instructions, 40 bytes at 0x7fc9b4408ce0)
2 params, 5 slots, 0 upvalues, 2 locals, 4 constants, 0 functions
	1	[192]	GETGLOBAL	2 -1	; G_reader_settings
	2	[192]	SELF     	2 2 -2	; "readSetting"
	3	[192]	LOADK    	4 -3	; "autoremove_deleted_items_from_history"
	4	[192]	CALL     	2 3 2
	5	[192]	TEST     	2 0 0
	6	[192]	JMP      	3	; to 10
	7	[194]	SELF     	2 0 -4	; "removeItemByPath"
	8	[194]	MOVE     	4 1
	9	[194]	CALL     	2 3 1
	10	[196]	RETURN   	0 1

function <./frontend/readhistory.lua:198,206> (34 instructions, 136 bytes at 0x7fc9b440b250)
1 param, 8 slots, 1 upvalue, 5 locals, 11 constants, 0 functions
	1	[199]	GETGLOBAL	1 -1	; assert
	2	[199]	EQ       	0 0 -2	; - nil
	3	[199]	JMP      	1	; to 5
	4	[199]	LOADBOOL 	2 0 1
	5	[199]	LOADBOOL 	2 1 0
	6	[199]	CALL     	1 2 1
	7	[200]	GETTABLE 	1 0 -3	; "hist"
	8	[200]	LEN      	1 1
	9	[200]	LOADK    	2 -4	; 1
	10	[200]	LOADK    	3 -5	; -1
	11	[200]	FORPREP  	1 19	; to 31
	12	[201]	GETTABLE 	5 0 -3	; "hist"
	13	[201]	GETTABLE 	5 5 4
	14	[201]	GETTABLE 	5 5 -6	; "file"
	15	[201]	EQ       	1 5 -2	; - nil
	16	[201]	JMP      	9	; to 26
	17	[201]	GETUPVAL 	5 0	; lfs
	18	[201]	GETTABLE 	5 5 -7	; "attributes"
	19	[201]	GETTABLE 	6 0 -3	; "hist"
	20	[201]	GETTABLE 	6 6 4
	21	[201]	GETTABLE 	6 6 -6	; "file"
	22	[201]	LOADK    	7 -8	; "mode"
	23	[201]	CALL     	5 3 2
	24	[201]	EQ       	1 5 -6	; - "file"
	25	[201]	JMP      	5	; to 31
	26	[202]	GETGLOBAL	5 -9	; table
	27	[202]	GETTABLE 	5 5 -10	; "remove"
	28	[202]	GETTABLE 	6 0 -3	; "hist"
	29	[202]	MOVE     	7 4
	30	[202]	CALL     	5 3 1
	31	[200]	FORLOOP  	1 -20	; to 12
	32	[205]	SELF     	1 0 -11	; "ensureLastFile"
	33	[205]	CALL     	1 2 1
	34	[206]	RETURN   	0 1

function <./frontend/readhistory.lua:208,217> (25 instructions, 100 bytes at 0x7fc9b440a380)
2 params, 9 slots, 0 upvalues, 6 locals, 8 constants, 0 functions
	1	[209]	GETGLOBAL	2 -1	; assert
	2	[209]	EQ       	0 0 -2	; - nil
	3	[209]	JMP      	1	; to 5
	4	[209]	LOADBOOL 	3 0 1
	5	[209]	LOADBOOL 	3 1 0
	6	[209]	CALL     	2 2 1
	7	[210]	GETTABLE 	2 0 -3	; "hist"
	8	[210]	LEN      	2 2
	9	[210]	LOADK    	3 -4	; 1
	10	[210]	LOADK    	4 -5	; -1
	11	[210]	FORPREP  	2 10	; to 22
	12	[211]	GETTABLE 	6 0 -3	; "hist"
	13	[211]	GETTABLE 	6 6 5
	14	[211]	GETTABLE 	6 6 -6	; "file"
	15	[211]	EQ       	0 6 1
	16	[211]	JMP      	5	; to 22
	17	[212]	SELF     	6 0 -7	; "removeItem"
	18	[212]	GETTABLE 	8 0 -3	; "hist"
	19	[212]	GETTABLE 	8 8 5
	20	[212]	CALL     	6 3 1
	21	[213]	JMP      	1	; to 23
	22	[210]	FORLOOP  	2 -11	; to 12
	23	[216]	SELF     	2 0 -8	; "ensureLastFile"
	24	[216]	CALL     	2 2 1
	25	[217]	RETURN   	0 1

function <./frontend/readhistory.lua:219,237> (49 instructions, 196 bytes at 0x7fc9b4409c80)
3 params, 12 slots, 0 upvalues, 7 locals, 17 constants, 1 function
	1	[220]	GETGLOBAL	3 -1	; assert
	2	[220]	EQ       	0 0 -2	; - nil
	3	[220]	JMP      	1	; to 5
	4	[220]	LOADBOOL 	4 0 1
	5	[220]	LOADBOOL 	4 1 0
	6	[220]	CALL     	3 2 1
	7	[221]	GETTABLE 	3 0 -3	; "hist"
	8	[221]	LEN      	3 3
	9	[221]	LOADK    	4 -4	; 1
	10	[221]	LOADK    	5 -5	; -1
	11	[221]	FORPREP  	3 23	; to 35
	12	[222]	GETTABLE 	7 0 -3	; "hist"
	13	[222]	GETTABLE 	7 7 6
	14	[222]	GETTABLE 	7 7 -6	; "file"
	15	[222]	EQ       	0 7 1
	16	[222]	JMP      	18	; to 35
	17	[223]	GETTABLE 	7 0 -3	; "hist"
	18	[223]	GETTABLE 	7 7 6
	19	[223]	SETTABLE 	7 -6 2	; "file" -
	20	[224]	GETTABLE 	7 0 -3	; "hist"
	21	[224]	GETTABLE 	7 7 6
	22	[224]	SELF     	8 2 -8	; "gsub"
	23	[224]	LOADK    	10 -9	; ".*/"
	24	[224]	LOADK    	11 -10	; ""
	25	[224]	CALL     	8 4 2
	26	[224]	SETTABLE 	7 -7 8	; "text" -
	27	[225]	SELF     	7 0 -11	; "_flush"
	28	[225]	CALL     	7 2 1
	29	[226]	GETTABLE 	7 0 -3	; "hist"
	30	[226]	GETTABLE 	7 7 6
	31	[229]	CLOSURE  	8 0	; 0x7fc9b440b8e0
	32	[229]	MOVE     	0 2
	33	[229]	SETTABLE 	7 -12 8	; "callback" -
	34	[230]	JMP      	1	; to 36
	35	[221]	FORLOOP  	3 -24	; to 12
	36	[233]	GETGLOBAL	3 -13	; G_reader_settings
	37	[233]	SELF     	3 3 -14	; "readSetting"
	38	[233]	LOADK    	5 -15	; "lastfile"
	39	[233]	CALL     	3 3 2
	40	[233]	EQ       	0 3 1
	41	[233]	JMP      	5	; to 47
	42	[234]	GETGLOBAL	3 -13	; G_reader_settings
	43	[234]	SELF     	3 3 -16	; "saveSetting"
	44	[234]	LOADK    	5 -15	; "lastfile"
	45	[234]	MOVE     	6 2
	46	[234]	CALL     	3 4 1
	47	[236]	SELF     	3 0 -17	; "ensureLastFile"
	48	[236]	CALL     	3 2 1
	49	[237]	RETURN   	0 1

function <./frontend/readhistory.lua:226,229> (7 instructions, 28 bytes at 0x7fc9b440b8e0)
0 params, 4 slots, 1 upvalue, 1 local, 3 constants, 0 functions
	1	[227]	GETGLOBAL	0 -1	; require
	2	[227]	LOADK    	1 -2	; "apps/reader/readerui"
	3	[227]	CALL     	0 2 2
	4	[228]	SELF     	1 0 -3	; "showReader"
	5	[228]	GETUPVAL 	3 0	; new_path
	6	[228]	CALL     	1 3 1
	7	[229]	RETURN   	0 1

function <./frontend/readhistory.lua:239,246> (26 instructions, 104 bytes at 0x7fc9b440b9e0)
2 params, 6 slots, 1 upvalue, 2 locals, 12 constants, 0 functions
	1	[240]	GETGLOBAL	2 -1	; assert
	2	[240]	EQ       	0 0 -2	; - nil
	3	[240]	JMP      	1	; to 5
	4	[240]	LOADBOOL 	3 0 1
	5	[240]	LOADBOOL 	3 1 0
	6	[240]	CALL     	2 2 1
	7	[241]	GETGLOBAL	2 -3	; table
	8	[241]	GETTABLE 	2 2 -4	; "remove"
	9	[241]	GETTABLE 	3 0 -5	; "hist"
	10	[241]	GETTABLE 	4 1 -6	; "index"
	11	[241]	CALL     	2 3 1
	12	[242]	GETGLOBAL	2 -7	; os
	13	[242]	GETTABLE 	2 2 -4	; "remove"
	14	[242]	GETUPVAL 	3 0	; DocSettings
	15	[242]	SELF     	3 3 -8	; "getHistoryPath"
	16	[242]	GETTABLE 	5 1 -9	; "file"
	17	[242]	CALL     	3 3 0
	18	[242]	CALL     	2 0 1
	19	[243]	SELF     	2 0 -10	; "_indexing"
	20	[243]	GETTABLE 	4 1 -6	; "index"
	21	[243]	CALL     	2 3 1
	22	[244]	SELF     	2 0 -11	; "_flush"
	23	[244]	CALL     	2 2 1
	24	[245]	SELF     	2 0 -12	; "ensureLastFile"
	25	[245]	CALL     	2 2 1
	26	[246]	RETURN   	0 1

function <./frontend/readhistory.lua:248,265> (50 instructions, 200 bytes at 0x7fc9b440ba60)
2 params, 9 slots, 2 upvalues, 4 locals, 19 constants, 0 functions
	1	[249]	GETGLOBAL	2 -1	; assert
	2	[249]	EQ       	0 0 -2	; - nil
	3	[249]	JMP      	1	; to 5
	4	[249]	LOADBOOL 	3 0 1
	5	[249]	LOADBOOL 	3 1 0
	6	[249]	CALL     	2 2 1
	7	[250]	EQ       	1 1 -2	; - nil
	8	[250]	JMP      	41	; to 50
	9	[250]	GETUPVAL 	2 0	; lfs
	10	[250]	GETTABLE 	2 2 -3	; "attributes"
	11	[250]	MOVE     	3 1
	12	[250]	LOADK    	4 -4	; "mode"
	13	[250]	CALL     	2 3 2
	14	[250]	EQ       	0 2 -5	; - "file"
	15	[250]	JMP      	34	; to 50
	16	[251]	GETGLOBAL	2 -6	; os
	17	[251]	GETTABLE 	2 2 -7	; "time"
	18	[251]	CALL     	2 1 2
	19	[252]	GETGLOBAL	3 -8	; table
	20	[252]	GETTABLE 	3 3 -9	; "insert"
	21	[252]	GETTABLE 	4 0 -10	; "hist"
	22	[252]	LOADK    	5 -11	; 1
	23	[252]	GETUPVAL 	6 1	; buildEntry
	24	[252]	MOVE     	7 2
	25	[252]	MOVE     	8 1
	26	[252]	CALL     	6 3 0
	27	[252]	CALL     	3 0 1
	28	[258]	GETUPVAL 	3 0	; lfs
	29	[258]	GETTABLE 	3 3 -3	; "attributes"
	30	[258]	MOVE     	4 1
	31	[258]	LOADK    	5 -12	; "modification"
	32	[258]	CALL     	3 3 2
	33	[259]	GETUPVAL 	4 0	; lfs
	34	[259]	GETTABLE 	4 4 -13	; "touch"
	35	[259]	MOVE     	5 1
	36	[259]	MOVE     	6 2
	37	[259]	MOVE     	7 3
	38	[259]	CALL     	4 4 1
	39	[260]	SELF     	4 0 -14	; "_sort"
	40	[260]	CALL     	4 2 1
	41	[261]	SELF     	4 0 -15	; "_reduce"
	42	[261]	CALL     	4 2 1
	43	[262]	SELF     	4 0 -16	; "_flush"
	44	[262]	CALL     	4 2 1
	45	[263]	GETGLOBAL	4 -17	; G_reader_settings
	46	[263]	SELF     	4 4 -18	; "saveSetting"
	47	[263]	LOADK    	6 -19	; "lastfile"
	48	[263]	MOVE     	7 1
	49	[263]	CALL     	4 4 1
	50	[265]	RETURN   	0 1

function <./frontend/readhistory.lua:269,279> (21 instructions, 84 bytes at 0x7fc9b440c3b0)
1 param, 3 slots, 0 upvalues, 1 local, 6 constants, 0 functions
	1	[270]	GETGLOBAL	1 -1	; assert
	2	[270]	EQ       	0 0 -2	; - nil
	3	[270]	JMP      	1	; to 5
	4	[270]	LOADBOOL 	2 0 1
	5	[270]	LOADBOOL 	2 1 0
	6	[270]	CALL     	1 2 1
	7	[271]	SELF     	1 0 -3	; "_read"
	8	[271]	CALL     	1 2 2
	9	[271]	TEST     	1 0 0
	10	[271]	JMP      	8	; to 19
	11	[272]	SELF     	1 0 -4	; "_readLegacyHistory"
	12	[272]	CALL     	1 2 1
	13	[273]	SELF     	1 0 -5	; "_sort"
	14	[273]	CALL     	1 2 1
	15	[274]	SELF     	1 0 -6	; "_reduce"
	16	[274]	CALL     	1 2 1
	17	[275]	LOADBOOL 	1 1 0
	18	[275]	RETURN   	1 2
	19	[278]	LOADBOOL 	1 0 0
	20	[278]	RETURN   	1 2
	21	[279]	RETURN   	0 1
