
main <./spec/unit/readerui_spec.lua:0,0> (5 instructions, 20 bytes at 0x7fd02fc068c0)
0+ params, 3 slots, 0 upvalues, 0 locals, 2 constants, 1 function
	1	[1]	GETGLOBAL	0 -1	; describe
	2	[1]	LOADK    	1 -2	; "Readerui module"
	3	[48]	CLOSURE  	2 0	; 0x7fd02fc06b60
	4	[1]	CALL     	0 3 1
	5	[48]	RETURN   	0 1

function <./spec/unit/readerui_spec.lua:1,48> (37 instructions, 148 bytes at 0x7fd02fc06b60)
0 params, 9 slots, 0 upvalues, 6 locals, 7 constants, 5 functions
	1	[3]	LOADK    	4 -1	; "spec/front/unit/data/leaves.epub"
	2	[4]	LOADNIL  	5 5
	3	[5]	GETGLOBAL	6 -2	; setup
	4	[15]	CLOSURE  	7 0	; 0x7fd02fc06d90
	5	[15]	MOVE     	0 0
	6	[15]	MOVE     	0 1
	7	[15]	MOVE     	0 2
	8	[15]	MOVE     	0 3
	9	[15]	MOVE     	0 5
	10	[15]	MOVE     	0 4
	11	[5]	CALL     	6 2 1
	12	[16]	GETGLOBAL	6 -3	; it
	13	[16]	LOADK    	7 -4	; "should save settings"
	14	[27]	CLOSURE  	8 1	; 0x7fd02fc07910
	15	[27]	MOVE     	0 2
	16	[27]	MOVE     	0 4
	17	[27]	MOVE     	0 5
	18	[16]	CALL     	6 3 1
	19	[28]	GETGLOBAL	6 -3	; it
	20	[28]	LOADK    	7 -5	; "should show reader"
	21	[33]	CLOSURE  	8 2	; 0x7fd02fc074e0
	22	[33]	MOVE     	0 3
	23	[33]	MOVE     	0 5
	24	[28]	CALL     	6 3 1
	25	[34]	GETGLOBAL	6 -3	; it
	26	[34]	LOADK    	7 -6	; "should close document"
	27	[37]	CLOSURE  	8 3	; 0x7fd02fc08350
	28	[37]	MOVE     	0 5
	29	[34]	CALL     	6 3 1
	30	[38]	GETGLOBAL	6 -3	; it
	31	[38]	LOADK    	7 -7	; "should not reset running_instance by mistake"
	32	[47]	CLOSURE  	8 4	; 0x7fd02fc08a50
	33	[47]	MOVE     	0 1
	34	[47]	MOVE     	0 4
	35	[47]	MOVE     	0 0
	36	[38]	CALL     	6 3 1
	37	[48]	RETURN   	0 1

function <./spec/unit/readerui_spec.lua:5,15> (30 instructions, 120 bytes at 0x7fd02fc06d90)
0 params, 6 slots, 6 upvalues, 0 locals, 9 constants, 0 functions
	1	[6]	GETGLOBAL	0 -1	; require
	2	[6]	LOADK    	1 -2	; "commonrequire"
	3	[6]	CALL     	0 2 1
	4	[7]	GETGLOBAL	0 -1	; require
	5	[7]	LOADK    	1 -3	; "document/documentregistry"
	6	[7]	CALL     	0 2 2
	7	[7]	SETUPVAL 	0 0	; DocumentRegistry
	8	[8]	GETGLOBAL	0 -1	; require
	9	[8]	LOADK    	1 -4	; "apps/reader/readerui"
	10	[8]	CALL     	0 2 2
	11	[8]	SETUPVAL 	0 1	; ReaderUI
	12	[9]	GETGLOBAL	0 -1	; require
	13	[9]	LOADK    	1 -5	; "docsettings"
	14	[9]	CALL     	0 2 2
	15	[9]	SETUPVAL 	0 2	; DocSettings
	16	[10]	GETGLOBAL	0 -1	; require
	17	[10]	LOADK    	1 -6	; "ui/uimanager"
	18	[10]	CALL     	0 2 2
	19	[10]	SETUPVAL 	0 3	; UIManager
	20	[12]	GETUPVAL 	0 1	; ReaderUI
	21	[12]	SELF     	0 0 -7	; "new"
	22	[12]	NEWTABLE 	2 0 1
	23	[13]	GETUPVAL 	3 0	; DocumentRegistry
	24	[13]	SELF     	3 3 -9	; "openDocument"
	25	[13]	GETUPVAL 	5 5	; sample_epub
	26	[13]	CALL     	3 3 2
	27	[13]	SETTABLE 	2 -8 3	; "document" -
	28	[12]	CALL     	0 3 2
	29	[14]	SETUPVAL 	0 4	; readerui
	30	[15]	RETURN   	0 1

function <./spec/unit/readerui_spec.lua:16,27> (48 instructions, 192 bytes at 0x7fd02fc07910)
0 params, 4 slots, 3 upvalues, 1 local, 11 constants, 0 functions
	1	[18]	GETUPVAL 	0 0	; DocSettings
	2	[18]	SELF     	0 0 -1	; "open"
	3	[18]	GETUPVAL 	2 1	; sample_epub
	4	[18]	CALL     	0 3 2
	5	[18]	SELF     	0 0 -2	; "purge"
	6	[18]	CALL     	0 2 1
	7	[19]	GETUPVAL 	0 0	; DocSettings
	8	[19]	SELF     	0 0 -1	; "open"
	9	[19]	GETUPVAL 	2 1	; sample_epub
	10	[19]	CALL     	0 3 2
	11	[20]	GETGLOBAL	1 -3	; assert
	12	[20]	GETTABLE 	1 1 -4	; "are"
	13	[20]	GETTABLE 	1 1 -5	; "same"
	14	[20]	GETTABLE 	2 0 -6	; "data"
	15	[20]	NEWTABLE 	3 0 0
	16	[20]	CALL     	1 3 1
	17	[21]	GETUPVAL 	1 2	; readerui
	18	[21]	SELF     	1 1 -7	; "saveSettings"
	19	[21]	CALL     	1 2 1
	20	[22]	GETGLOBAL	1 -3	; assert
	21	[22]	GETTABLE 	1 1 -8	; "are_not"
	22	[22]	GETTABLE 	1 1 -5	; "same"
	23	[22]	GETUPVAL 	2 2	; readerui
	24	[22]	GETTABLE 	2 2 -9	; "doc_settings"
	25	[22]	GETTABLE 	2 2 -6	; "data"
	26	[22]	NEWTABLE 	3 0 0
	27	[22]	CALL     	1 3 1
	28	[23]	GETUPVAL 	1 0	; DocSettings
	29	[23]	SELF     	1 1 -1	; "open"
	30	[23]	GETUPVAL 	3 1	; sample_epub
	31	[23]	CALL     	1 3 2
	32	[23]	MOVE     	0 1
	33	[24]	GETGLOBAL	1 -3	; assert
	34	[24]	GETTABLE 	1 1 -10	; "truthy"
	35	[24]	GETTABLE 	2 0 -6	; "data"
	36	[24]	GETTABLE 	2 2 -11	; "last_xpointer"
	37	[24]	CALL     	1 2 1
	38	[25]	GETGLOBAL	1 -3	; assert
	39	[25]	GETTABLE 	1 1 -4	; "are"
	40	[25]	GETTABLE 	1 1 -5	; "same"
	41	[25]	GETTABLE 	2 0 -6	; "data"
	42	[25]	GETTABLE 	2 2 -11	; "last_xpointer"
	43	[26]	GETUPVAL 	3 2	; readerui
	44	[26]	GETTABLE 	3 3 -9	; "doc_settings"
	45	[26]	GETTABLE 	3 3 -6	; "data"
	46	[26]	GETTABLE 	3 3 -11	; "last_xpointer"
	47	[25]	CALL     	1 3 1
	48	[27]	RETURN   	0 1

function <./spec/unit/readerui_spec.lua:28,33> (18 instructions, 72 bytes at 0x7fd02fc074e0)
0 params, 4 slots, 2 upvalues, 0 locals, 5 constants, 1 function
	1	[29]	GETUPVAL 	0 0	; UIManager
	2	[29]	SELF     	0 0 -1	; "quit"
	3	[29]	CALL     	0 2 1
	4	[30]	GETUPVAL 	0 0	; UIManager
	5	[30]	SELF     	0 0 -2	; "show"
	6	[30]	GETUPVAL 	2 1	; readerui
	7	[30]	CALL     	0 3 1
	8	[31]	GETUPVAL 	0 0	; UIManager
	9	[31]	SELF     	0 0 -3	; "scheduleIn"
	10	[31]	LOADK    	2 -4	; 1
	11	[31]	CLOSURE  	3 0	; 0x7fd02fc083d0
	12	[31]	GETUPVAL 	0 0	; UIManager
	13	[31]	GETUPVAL 	0 1	; readerui
	14	[31]	CALL     	0 4 1
	15	[32]	GETUPVAL 	0 0	; UIManager
	16	[32]	SELF     	0 0 -5	; "run"
	17	[32]	CALL     	0 2 1
	18	[33]	RETURN   	0 1

function <./spec/unit/readerui_spec.lua:31,31> (5 instructions, 20 bytes at 0x7fd02fc083d0)
0 params, 3 slots, 2 upvalues, 0 locals, 1 constant, 0 functions
	1	[31]	GETUPVAL 	0 0	; UIManager
	2	[31]	SELF     	0 0 -1	; "close"
	3	[31]	GETUPVAL 	2 1	; readerui
	4	[31]	CALL     	0 3 1
	5	[31]	RETURN   	0 1

function <./spec/unit/readerui_spec.lua:34,37> (12 instructions, 48 bytes at 0x7fd02fc08350)
0 params, 2 slots, 1 upvalue, 0 locals, 4 constants, 0 functions
	1	[35]	GETUPVAL 	0 0	; readerui
	2	[35]	SELF     	0 0 -1	; "closeDocument"
	3	[35]	CALL     	0 2 1
	4	[36]	GETGLOBAL	0 -2	; assert
	5	[36]	GETUPVAL 	1 0	; readerui
	6	[36]	GETTABLE 	1 1 -3	; "document"
	7	[36]	EQ       	1 1 -4	; - nil
	8	[36]	JMP      	1	; to 10
	9	[36]	LOADBOOL 	1 0 1
	10	[36]	LOADBOOL 	1 1 0
	11	[36]	CALL     	0 2 1
	12	[37]	RETURN   	0 1

function <./spec/unit/readerui_spec.lua:38,47> (31 instructions, 124 bytes at 0x7fd02fc08a50)
0 params, 7 slots, 3 upvalues, 1 local, 9 constants, 0 functions
	1	[39]	GETUPVAL 	0 0	; ReaderUI
	2	[39]	SELF     	0 0 -1	; "doShowReader"
	3	[39]	GETUPVAL 	2 1	; sample_epub
	4	[39]	CALL     	0 3 1
	5	[40]	GETUPVAL 	0 0	; ReaderUI
	6	[40]	SELF     	0 0 -2	; "_getRunningInstance"
	7	[40]	CALL     	0 2 2
	8	[41]	GETGLOBAL	1 -3	; assert
	9	[41]	GETTABLE 	1 1 -4	; "is"
	10	[41]	GETTABLE 	1 1 -5	; "truthy"
	11	[41]	GETTABLE 	2 0 -6	; "document"
	12	[41]	CALL     	1 2 1
	13	[42]	GETUPVAL 	1 0	; ReaderUI
	14	[42]	SELF     	1 1 -7	; "new"
	15	[42]	NEWTABLE 	3 0 1
	16	[43]	GETUPVAL 	4 2	; DocumentRegistry
	17	[43]	SELF     	4 4 -8	; "openDocument"
	18	[43]	GETUPVAL 	6 1	; sample_epub
	19	[43]	CALL     	4 3 2
	20	[43]	SETTABLE 	3 -6 4	; "document" -
	21	[42]	CALL     	1 3 2
	22	[44]	SELF     	1 1 -9	; "onClose"
	23	[44]	CALL     	1 2 1
	24	[45]	GETGLOBAL	1 -3	; assert
	25	[45]	GETTABLE 	1 1 -4	; "is"
	26	[45]	GETTABLE 	1 1 -5	; "truthy"
	27	[45]	GETTABLE 	2 0 -6	; "document"
	28	[45]	CALL     	1 2 1
	29	[46]	SELF     	1 0 -9	; "onClose"
	30	[46]	CALL     	1 2 1
	31	[47]	RETURN   	0 1
