-- BYTECODE -- readercropping.lua:21-21
0001    RET0     0   1

-- BYTECODE -- readercropping.lua:22-22
0001    RET0     0   1

-- BYTECODE -- readercropping.lua:26-61
0001    UGET     1   0      ; HorizontalGroup
0002    MOV      2   1
0003    TGETS    1   1   0  ; "new"
0004    TNEW     3   0
0005    CALL     1   2   3
0006    UGET     2   1      ; Button
0007    MOV      3   2
0008    TGETS    2   2   0  ; "new"
0009    TDUP     4   2
0010    TGETS    5   0   1  ; "ok_text"
0011    TSETS    5   4   3  ; "text"
0012    TGETS    5   0   4  ; "ok_callback"
0013    TSETS    5   4   5  ; "callback"
0014    TGETS    5   0   6  ; "button_width"
0015    TSETS    5   4   7  ; "width"
0016    TSETS    0   4   8  ; "show_parent"
0017    CALL     2   2   3
0018    UGET     3   1      ; Button
0019    MOV      4   3
0020    TGETS    3   3   0  ; "new"
0021    TDUP     5  10
0022    TGETS    6   0   9  ; "cancel_text"
0023    TSETS    6   5   3  ; "text"
0024    TGETS    6   0  11  ; "cancel_callback"
0025    TSETS    6   5   5  ; "callback"
0026    TGETS    6   0   6  ; "button_width"
0027    TSETS    6   5   7  ; "width"
0028    TSETS    0   5   8  ; "show_parent"
0029    CALL     3   2   3
0030    UGET     4   2      ; RightContainer
0031    MOV      5   4
0032    TGETS    4   4   0  ; "new"
0033    TDUP     6  17
0034    UGET     7   3      ; Geom
0035    MOV      8   7
0036    TGETS    7   7   0  ; "new"
0037    TDUP     9  13
0038    UGET    10   4      ; Screen
0039    MOV     11  10
0040    TGETS   10  10  12  ; "getWidth"
0041    CALL    10   2   2
0042    MULVN   10  10   0  ; 0.33
0043    TSETS   10   9  14  ; "w"
0044    UGET    10   4      ; Screen
0045    MOV     11  10
0046    TGETS   10  10  15  ; "getHeight"
0047    CALL    10   2   2
0048    DIVVN   10  10   1  ; 12
0049    TSETS   10   9  16  ; "h"
0050    CALL     7   2   3
0051    TSETS    7   6  18  ; "dimen"
0052    TSETB    2   6   1
0053    CALL     4   2   3
0054    UGET     5   5      ; LeftContainer
0055    MOV      6   5
0056    TGETS    5   5   0  ; "new"
0057    TDUP     7  20
0058    UGET     8   3      ; Geom
0059    MOV      9   8
0060    TGETS    8   8   0  ; "new"
0061    TDUP    10  19
0062    UGET    11   4      ; Screen
0063    MOV     12  11
0064    TGETS   11  11  12  ; "getWidth"
0065    CALL    11   2   2
0066    MULVN   11  11   0  ; 0.33
0067    TSETS   11  10  14  ; "w"
0068    UGET    11   4      ; Screen
0069    MOV     12  11
0070    TGETS   11  11  15  ; "getHeight"
0071    CALL    11   2   2
0072    DIVVN   11  11   1  ; 12
0073    TSETS   11  10  16  ; "h"
0074    CALL     8   2   3
0075    TSETS    8   7  18  ; "dimen"
0076    TSETB    3   7   1
0077    CALL     5   2   3
0078    GGET     6  21      ; "table"
0079    TGETS    6   6  22  ; "insert"
0080    MOV      7   1
0081    MOV      8   4
0082    CALL     6   1   3
0083    GGET     6  21      ; "table"
0084    TGETS    6   6  22  ; "insert"
0085    MOV      7   1
0086    UGET     8   6      ; HorizontalSpan
0087    MOV      9   8
0088    TGETS    8   8   0  ; "new"
0089    TDUP    10  23
0090    UGET    11   4      ; Screen
0091    MOV     12  11
0092    TGETS   11  11  12  ; "getWidth"
0093    CALL    11   2   2
0094    MULVN   11  11   2  ; 0.34
0095    TSETS   11  10   7  ; "width"
0096    CALL     8   0   3
0097    CALLM    6   1   1
0098    GGET     6  21      ; "table"
0099    TGETS    6   6  22  ; "insert"
0100    MOV      7   1
0101    MOV      8   5
0102    CALL     6   1   3
0103    UGET     6   7      ; FrameContainer
0104    MOV      7   6
0105    TGETS    6   6   0  ; "new"
0106    TDUP     8  25
0107    TSETB    1   8   1
0108    UGET     9   8      ; Blitbuffer
0109    TGETS    9   9  24  ; "COLOR_WHITE"
0110    TSETS    9   8  26  ; "background"
0111    CALL     6   2   3
0112    TSETB    6   0   2
0113    RET0     0   1

-- BYTECODE -- readercropping.lua:64-66
0001    KSTR     0   0      ; "partial"
0002    UGET     1   0      ; self
0003    TGETB    1   1   1
0004    TGETS    1   1   1  ; "dimen"
0005    MOV      2   1
0006    TGETS    1   1   2  ; "combine"
0007    UGET     3   0      ; self
0008    TGETB    3   3   2
0009    TGETS    3   3   1  ; "dimen"
0010    CALL     1   0   3
0011    RETM     0   1

-- BYTECODE -- readercropping.lua:63-68
0001    UGET     1   0      ; UIManager
0002    MOV      2   1
0003    TGETS    1   1   0  ; "setDirty"
0004    KPRI     3   0
0005    FNEW     4   1      ; readercropping.lua:64
0006    CALL     1   1   4
0007    KPRI     1   2
0008    UCLO     0 => 0009
0009 => RET1     1   2

-- BYTECODE -- readercropping.lua:71-73
0001    KSTR     0   0      ; "ui"
0002    UGET     1   0      ; self
0003    TGETB    1   1   1
0004    TGETS    1   1   1  ; "dimen"
0005    MOV      2   1
0006    TGETS    1   1   2  ; "combine"
0007    UGET     3   0      ; self
0008    TGETB    3   3   2
0009    TGETS    3   3   1  ; "dimen"
0010    CALL     1   0   3
0011    RETM     0   1

-- BYTECODE -- readercropping.lua:70-75
0001    UGET     1   0      ; UIManager
0002    MOV      2   1
0003    TGETS    1   1   0  ; "setDirty"
0004    MOV      3   0
0005    FNEW     4   1      ; readercropping.lua:71
0006    CALL     1   1   4
0007    KPRI     1   2
0008    UCLO     0 => 0009
0009 => RET1     1   2

-- BYTECODE -- readercropping.lua:125-125
0001    UGET     0   0      ; self
0002    MOV      1   0
0003    TGETS    0   0   0  ; "onConfirmPageCrop"
0004    CALL     0   1   2
0005    RET0     0   1

-- BYTECODE -- readercropping.lua:126-126
0001    UGET     0   0      ; self
0002    MOV      1   0
0003    TGETS    0   0   0  ; "onCancelPageCrop"
0004    CALL     0   1   2
0005    RET0     0   1

-- BYTECODE -- readercropping.lua:79-130
0001    TGETS    2   0   0  ; "ui"
0002    MOV      3   2
0003    TGETS    2   2   1  ; "handleEvent"
0004    UGET     4   0      ; Event
0005    MOV      5   4
0006    TGETS    4   4   2  ; "new"
0007    KSTR     6   3      ; "CloseConfigMenu"
0008    CALL     4   0   3
0009    CALLM    2   1   1
0010    TGETS    2   0   5  ; "view"
0011    TGETS    2   2   6  ; "zoom_mode"
0012    TSETS    2   0   4  ; "orig_zoom_mode"
0013    ISNES    1   7      ; "auto"
0014    JMP      2 => 0026
0015    TGETS    2   0   8  ; "document"
0016    TGETS    2   2   9  ; "configurable"
0017    TGETS    2   2  10  ; "text_wrap"
0018    ISEQN    2   0      ; 1
0019    JMP      2 => 0024
0020    MOV      3   0
0021    TGETS    2   0  11  ; "setCropZoomMode"
0022    KPRI     4   2
0023    CALL     2   1   3
0024 => UCLO     0 => 0167
0025    JMP      2 => 0045
0026 => ISNES    1  12      ; "none"
0027    JMP      2 => 0045
0028    TGETS    2   0   8  ; "document"
0029    TGETS    2   2   9  ; "configurable"
0030    TGETS    2   2  10  ; "text_wrap"
0031    ISEQN    2   0      ; 1
0032    JMP      2 => 0044
0033    TGETS    2   0   0  ; "ui"
0034    MOV      3   2
0035    TGETS    2   2   1  ; "handleEvent"
0036    UGET     4   0      ; Event
0037    MOV      5   4
0038    TGETS    4   4   2  ; "new"
0039    KSTR     6  13      ; "SetZoomMode"
0040    KSTR     7  14      ; "pagewidth"
0041    KSTR     8  15      ; "cropping"
0042    CALL     4   0   5
0043    CALLM    2   1   1
0044 => UCLO     0 => 0168
0045 => UGET     2   1      ; Geom
0046    MOV      3   2
0047    TGETS    2   2   2  ; "new"
0048    TDUP     4  19
0049    TGETS    5   0   5  ; "view"
0050    TGETS    5   5  17  ; "dimen"
0051    TGETS    5   5  18  ; "w"
0052    TSETS    5   4  18  ; "w"
0053    TGETS    5   0   5  ; "view"
0054    TGETS    5   5  17  ; "dimen"
0055    TGETS    5   5  20  ; "h"
0056    TSETS    5   4  20  ; "h"
0057    CALL     2   2   3
0058    TSETS    2   0  16  ; "orig_view_dimen"
0059    TGETS    2   0   5  ; "view"
0060    TGETS    2   2  22  ; "outer_page_color"
0061    TSETS    2   0  21  ; "orig_view_bgcolor"
0062    TGETS    2   0   5  ; "view"
0063    UGET     3   2      ; Blitbuffer
0064    TGETS    3   3  23  ; "COLOR_DARK_GRAY"
0065    TSETS    3   2  22  ; "outer_page_color"
0066    TGETS    2   0   5  ; "view"
0067    TGETS    2   2  25  ; "page_scroll"
0068    TSETS    2   0  24  ; "orig_page_scroll"
0069    TGETS    2   0   5  ; "view"
0070    KPRI     3   1
0071    TSETS    3   2  25  ; "page_scroll"
0072    TGETS    2   0   0  ; "ui"
0073    MOV      3   2
0074    TGETS    2   2   1  ; "handleEvent"
0075    UGET     4   0      ; Event
0076    MOV      5   4
0077    TGETS    4   4   2  ; "new"
0078    KSTR     6  26      ; "DisableHinting"
0079    CALL     4   0   3
0080    CALLM    2   1   1
0081    TGETS    2   0   8  ; "document"
0082    TGETS    2   2   9  ; "configurable"
0083    TGETS    2   2  10  ; "text_wrap"
0084    TSETS    2   0  27  ; "orig_reflow_mode"
0085    TGETS    2   0  27  ; "orig_reflow_mode"
0086    ISNEN    2   0      ; 1
0087    JMP      2 => 0097
0088    TGETS    2   0   8  ; "document"
0089    TGETS    2   2   9  ; "configurable"
0090    KSHORT   3   0
0091    TSETS    3   2  10  ; "text_wrap"
0092    TGETS    2   0   5  ; "view"
0093    MOV      3   2
0094    TGETS    2   2  28  ; "recalculate"
0095    CALL     2   1   2
0096    JMP      2 => 0108
0097 => TGETS    2   0   0  ; "ui"
0098    MOV      3   2
0099    TGETS    2   2   1  ; "handleEvent"
0100    UGET     4   0      ; Event
0101    MOV      5   4
0102    TGETS    4   4   2  ; "new"
0103    KSTR     6  13      ; "SetZoomMode"
0104    KSTR     7  29      ; "page"
0105    KSTR     8  15      ; "cropping"
0106    CALL     4   0   5
0107    CALLM    2   1   1
0108 => TGETS    2   0   0  ; "ui"
0109    MOV      3   2
0110    TGETS    2   2   1  ; "handleEvent"
0111    UGET     4   0      ; Event
0112    MOV      5   4
0113    TGETS    4   4   2  ; "new"
0114    KSTR     6  30      ; "SetDimensions"
0115    UGET     7   1      ; Geom
0116    MOV      8   7
0117    TGETS    7   7   2  ; "new"
0118    TDUP     9  32
0119    UGET    10   3      ; Screen
0120    MOV     11  10
0121    TGETS   10  10  31  ; "getWidth"
0122    CALL    10   2   2
0123    TSETS   10   9  18  ; "w"
0124    UGET    10   3      ; Screen
0125    MOV     11  10
0126    TGETS   10  10  33  ; "getHeight"
0127    CALL    10   2   2
0128    MULVN   10  10   1  ; 11
0129    DIVVN   10  10   2  ; 12
0130    TSETS   10   9  20  ; "h"
0131    CALL     7   0   3
0132    CALLM    4   0   2
0133    CALLM    2   1   1
0134    UGET     2   4      ; BBoxWidget
0135    MOV      3   2
0136    TGETS    2   2   2  ; "new"
0137    TDUP     4  35
0138    TSETS    0   4  36  ; "crop"
0139    TGETS    5   0   0  ; "ui"
0140    TSETS    5   4   0  ; "ui"
0141    TGETS    5   0   5  ; "view"
0142    TSETS    5   4   5  ; "view"
0143    TGETS    5   0   8  ; "document"
0144    TSETS    5   4   8  ; "document"
0145    CALL     2   2   3
0146    TSETS    2   0  34  ; "bbox_widget"
0147    UGET     2   5      ; PageCropDialog
0148    MOV      3   2
0149    TGETS    2   2   2  ; "new"
0150    TDUP     4  39
0151    TGETS    5   0  34  ; "bbox_widget"
0152    TSETB    5   4   1
0153    FNEW     5  38      ; readercropping.lua:125
0154    TSETS    5   4  40  ; "ok_callback"
0155    FNEW     5  41      ; readercropping.lua:126
0156    TSETS    5   4  42  ; "cancel_callback"
0157    CALL     2   2   3
0158    TSETS    2   0  37  ; "crop_dialog"
0159    UGET     2   6      ; UIManager
0160    MOV      3   2
0161    TGETS    2   2  43  ; "show"
0162    TGETS    4   0  37  ; "crop_dialog"
0163    CALL     2   1   3
0164    KPRI     2   2
0165    UCLO     0 => 0166
0166 => RET1     2   2
0167 => RET0     0   1
0168 => RET0     0   1

-- BYTECODE -- readercropping.lua:132-142
0001    UGET     1   0      ; UIManager
0002    MOV      2   1
0003    TGETS    1   1   0  ; "close"
0004    TGETS    3   0   1  ; "crop_dialog"
0005    CALL     1   1   3
0006    TGETS    1   0   2  ; "bbox_widget"
0007    MOV      2   1
0008    TGETS    1   1   3  ; "getModifiedPageBBox"
0009    CALL     1   2   2
0010    TGETS    2   0   4  ; "ui"
0011    MOV      3   2
0012    TGETS    2   2   5  ; "handleEvent"
0013    UGET     4   1      ; Event
0014    MOV      5   4
0015    TGETS    4   4   6  ; "new"
0016    KSTR     6   7      ; "BBoxUpdate"
0017    MOV      7   1
0018    CALL     4   0   4
0019    CALLM    2   1   1
0020    TGETS    2   0   8  ; "view"
0021    TGETS    2   2   9  ; "state"
0022    TGETS    2   2  10  ; "page"
0023    TGETS    3   0  11  ; "document"
0024    TGETS    3   3  12  ; "bbox"
0025    TSETV    1   3   2
0026    TGETS    3   0  11  ; "document"
0027    TGETS    3   3  12  ; "bbox"
0028    UGET     4   2      ; Math
0029    TGETS    4   4  13  ; "oddEven"
0030    MOV      5   2
0031    CALL     4   2   2
0032    TSETV    1   3   4
0033    MOV      4   0
0034    TGETS    3   0  14  ; "exitPageCrop"
0035    KPRI     5   2
0036    CALL     3   1   3
0037    KPRI     3   2
0038    RET1     3   2

-- BYTECODE -- readercropping.lua:144-148
0001    UGET     1   0      ; UIManager
0002    MOV      2   1
0003    TGETS    1   1   0  ; "close"
0004    TGETS    3   0   1  ; "crop_dialog"
0005    CALL     1   1   3
0006    MOV      2   0
0007    TGETS    1   0   2  ; "exitPageCrop"
0008    KPRI     3   1
0009    CALL     1   1   3
0010    KPRI     1   2
0011    RET1     1   2

-- BYTECODE -- readercropping.lua:150-168
0001    TGETS    2   0   0  ; "ui"
0002    MOV      3   2
0003    TGETS    2   2   1  ; "handleEvent"
0004    UGET     4   0      ; Event
0005    MOV      5   4
0006    TGETS    4   4   2  ; "new"
0007    KSTR     6   3      ; "RestoreHinting"
0008    CALL     4   0   3
0009    CALLM    2   1   1
0010    TGETS    2   0   4  ; "view"
0011    TGETS    3   0   6  ; "orig_page_scroll"
0012    TSETS    3   2   5  ; "page_scroll"
0013    TGETS    2   0   4  ; "view"
0014    TGETS    3   0   8  ; "orig_view_bgcolor"
0015    TSETS    3   2   7  ; "outer_page_color"
0016    TGETS    2   0   9  ; "document"
0017    TGETS    2   2  10  ; "configurable"
0018    TGETS    3   0  12  ; "orig_reflow_mode"
0019    TSETS    3   2  11  ; "text_wrap"
0020    TGETS    2   0   0  ; "ui"
0021    MOV      3   2
0022    TGETS    2   2   1  ; "handleEvent"
0023    UGET     4   0      ; Event
0024    MOV      5   4
0025    TGETS    4   4   2  ; "new"
0026    KSTR     6  13      ; "RestoreDimensions"
0027    TGETS    7   0  14  ; "orig_view_dimen"
0028    CALL     4   0   4
0029    CALLM    2   1   1
0030    TGETS    2   0   4  ; "view"
0031    MOV      3   2
0032    TGETS    2   2  15  ; "recalculate"
0033    CALL     2   1   2
0034    TGETS    2   0  12  ; "orig_reflow_mode"
0035    ISNEN    2   0      ; 1
0036    JMP      2 => 0047
0037    TGETS    2   0   0  ; "ui"
0038    MOV      3   2
0039    TGETS    2   2   1  ; "handleEvent"
0040    UGET     4   0      ; Event
0041    MOV      5   4
0042    TGETS    4   4   2  ; "new"
0043    KSTR     6  16      ; "RestoreZoomMode"
0044    CALL     4   0   3
0045    CALLM    2   1   1
0046    JMP      2 => 0051
0047 => MOV      3   0
0048    TGETS    2   0  17  ; "setCropZoomMode"
0049    MOV      4   1
0050    CALL     2   1   3
0051 => RET0     0   1

-- BYTECODE -- readercropping.lua:170-181
0001    ISF          1
0002    JMP      2 => 0027
0003    MOV      3   0
0004    TGETS    2   0   0  ; "setZoomMode"
0005    TGETS    4   0   1  ; "orig_zoom_mode"
0006    MOV      5   4
0007    TGETS    4   4   2  ; "find"
0008    KSTR     6   3      ; "content"
0009    CALL     4   2   3
0010    ISF          4
0011    JMP      5 => 0015
0012    TGETS    4   0   1  ; "orig_zoom_mode"
0013    IST          4
0014    JMP      5 => 0016
0015 => KSTR     4   4      ; "contentwidth"
0016 => CALL     2   1   3
0017    TGETS    2   0   5  ; "ui"
0018    MOV      3   2
0019    TGETS    2   2   6  ; "handleEvent"
0020    UGET     4   0      ; Event
0021    MOV      5   4
0022    TGETS    4   4   7  ; "new"
0023    KSTR     6   8      ; "InitScrollPageStates"
0024    CALL     4   0   3
0025    CALLM    2   1   1
0026    JMP      2 => 0031
0027 => MOV      3   0
0028    TGETS    2   0   0  ; "setZoomMode"
0029    TGETS    4   0   1  ; "orig_zoom_mode"
0030    CALL     2   1   3
0031 => RET0     0   1

-- BYTECODE -- readercropping.lua:183-185
0001    TGETS    2   0   0  ; "ui"
0002    MOV      3   2
0003    TGETS    2   2   1  ; "handleEvent"
0004    UGET     4   0      ; Event
0005    MOV      5   4
0006    TGETS    4   4   2  ; "new"
0007    KSTR     6   3      ; "SetZoomMode"
0008    MOV      7   1
0009    CALL     4   0   4
0010    CALLM    2   1   1
0011    RET0     0   1

-- BYTECODE -- readercropping.lua:187-189
0001    TGETS    2   0   0  ; "document"
0002    MOV      4   1
0003    TGETS    3   1   2  ; "readSetting"
0004    KSTR     5   1      ; "bbox"
0005    CALL     3   2   3
0006    TSETS    3   2   1  ; "bbox"
0007    RET0     0   1

-- BYTECODE -- readercropping.lua:191-193
0001    TGETS    1   0   0  ; "ui"
0002    TGETS    1   1   1  ; "doc_settings"
0003    MOV      2   1
0004    TGETS    1   1   2  ; "saveSetting"
0005    KSTR     3   3      ; "bbox"
0006    TGETS    4   0   4  ; "document"
0007    TGETS    4   4   3  ; "bbox"
0008    CALL     1   1   4
0009    RET0     0   1

-- BYTECODE -- readercropping.lua:0-196
0001    GGET     0   0      ; "require"
0002    KSTR     1   1      ; "ui/widget/bboxwidget"
0003    CALL     0   2   2
0004    GGET     1   0      ; "require"
0005    KSTR     2   2      ; "ffi/blitbuffer"
0006    CALL     1   2   2
0007    GGET     2   0      ; "require"
0008    KSTR     3   3      ; "ui/widget/button"
0009    CALL     2   2   2
0010    GGET     3   0      ; "require"
0011    KSTR     4   4      ; "ui/event"
0012    CALL     3   2   2
0013    GGET     4   0      ; "require"
0014    KSTR     5   5      ; "ui/widget/container/framecontainer"
0015    CALL     4   2   2
0016    GGET     5   0      ; "require"
0017    KSTR     6   6      ; "ui/geometry"
0018    CALL     5   2   2
0019    GGET     6   0      ; "require"
0020    KSTR     7   7      ; "ui/widget/container/inputcontainer"
0021    CALL     6   2   2
0022    GGET     7   0      ; "require"
0023    KSTR     8   8      ; "ui/widget/horizontalgroup"
0024    CALL     7   2   2
0025    GGET     8   0      ; "require"
0026    KSTR     9   9      ; "ui/widget/horizontalspan"
0027    CALL     8   2   2
0028    GGET     9   0      ; "require"
0029    KSTR    10  10      ; "ui/widget/container/leftcontainer"
0030    CALL     9   2   2
0031    GGET    10   0      ; "require"
0032    KSTR    11  11      ; "optmath"
0033    CALL    10   2   2
0034    GGET    11   0      ; "require"
0035    KSTR    12  12      ; "ui/widget/container/rightcontainer"
0036    CALL    11   2   2
0037    GGET    12   0      ; "require"
0038    KSTR    13  13      ; "ui/uimanager"
0039    CALL    12   2   2
0040    GGET    13   0      ; "require"
0041    KSTR    14  14      ; "ui/widget/verticalgroup"
0042    CALL    13   2   2
0043    GGET    14   0      ; "require"
0044    KSTR    15  15      ; "device"
0045    CALL    14   2   2
0046    TGETS   14  14  16  ; "screen"
0047    GGET    15   0      ; "require"
0048    KSTR    16  17      ; "gettext"
0049    CALL    15   2   2
0050    MOV     17  13
0051    TGETS   16  13  18  ; "new"
0052    TDUP    18  20
0053    MOV     19  15
0054    KSTR    20  19      ; "OK"
0055    CALL    19   2   2
0056    TSETS   19  18  21  ; "ok_text"
0057    MOV     19  15
0058    KSTR    20  22      ; "Cancel"
0059    CALL    19   2   2
0060    TSETS   19  18  23  ; "cancel_text"
0061    FNEW    19  24      ; readercropping.lua:21
0062    TSETS   19  18  25  ; "ok_callback"
0063    FNEW    19  26      ; readercropping.lua:22
0064    TSETS   19  18  27  ; "cancel_callback"
0065    GGET    19  28      ; "math"
0066    TGETS   19  19  29  ; "floor"
0067    MOV     21  14
0068    TGETS   20  14  30  ; "scaleBySize"
0069    KSHORT  22  70
0070    CALL    20   0   3
0071    CALLM   19   2   0
0072    TSETS   19  18  31  ; "button_width"
0073    CALL    16   2   3
0074    FNEW    17  33      ; readercropping.lua:26
0075    TSETS   17  16  32  ; "init"
0076    FNEW    17  35      ; readercropping.lua:63
0077    TSETS   17  16  34  ; "onCloseWidget"
0078    FNEW    17  37      ; readercropping.lua:70
0079    TSETS   17  16  36  ; "onShow"
0080    MOV     18   6
0081    TGETS   17   6  18  ; "new"
0082    TNEW    19   0
0083    CALL    17   2   3
0084    FNEW    18  39      ; readercropping.lua:79
0085    TSETS   18  17  38  ; "onPageCrop"
0086    FNEW    18  41      ; readercropping.lua:132
0087    TSETS   18  17  40  ; "onConfirmPageCrop"
0088    FNEW    18  43      ; readercropping.lua:144
0089    TSETS   18  17  42  ; "onCancelPageCrop"
0090    FNEW    18  45      ; readercropping.lua:150
0091    TSETS   18  17  44  ; "exitPageCrop"
0092    FNEW    18  47      ; readercropping.lua:170
0093    TSETS   18  17  46  ; "setCropZoomMode"
0094    FNEW    18  49      ; readercropping.lua:183
0095    TSETS   18  17  48  ; "setZoomMode"
0096    FNEW    18  51      ; readercropping.lua:187
0097    TSETS   18  17  50  ; "onReadSettings"
0098    FNEW    18  53      ; readercropping.lua:191
0099    TSETS   18  17  52  ; "onSaveSettings"
0100    UCLO     0 => 0101
0101 => RET1    17   2

