
main <./frontend/apps/reader/readerui.lua:0,0> (323 instructions, 1292 bytes at 0x7fc5a14068d0)
0+ params, 60 slots, 0 upvalues, 58 locals, 92 constants, 24 functions
	1	[7]	GETGLOBAL	0 -1	; require
	2	[7]	LOADK    	1 -2	; "ui/bidi"
	3	[7]	CALL     	0 2 2
	4	[8]	GETGLOBAL	1 -1	; require
	5	[8]	LOADK    	2 -3	; "cache"
	6	[8]	CALL     	1 2 2
	7	[9]	GETGLOBAL	2 -1	; require
	8	[9]	LOADK    	3 -4	; "ui/widget/confirmbox"
	9	[9]	CALL     	2 2 2
	10	[10]	GETGLOBAL	3 -1	; require
	11	[10]	LOADK    	4 -5	; "device"
	12	[10]	CALL     	3 2 2
	13	[11]	GETGLOBAL	4 -1	; require
	14	[11]	LOADK    	5 -6	; "docsettings"
	15	[11]	CALL     	4 2 2
	16	[12]	GETGLOBAL	5 -1	; require
	17	[12]	LOADK    	6 -7	; "document/documentregistry"
	18	[12]	CALL     	5 2 2
	19	[13]	GETGLOBAL	6 -1	; require
	20	[13]	LOADK    	7 -8	; "ui/event"
	21	[13]	CALL     	6 2 2
	22	[14]	GETGLOBAL	7 -1	; require
	23	[14]	LOADK    	8 -9	; "apps/filemanager/filemanagerbookinfo"
	24	[14]	CALL     	7 2 2
	25	[15]	GETGLOBAL	8 -1	; require
	26	[15]	LOADK    	9 -10	; "apps/filemanager/filemanagercollection"
	27	[15]	CALL     	8 2 2
	28	[16]	GETGLOBAL	9 -1	; require
	29	[16]	LOADK    	10 -11	; "apps/filemanager/filemanagerhistory"
	30	[16]	CALL     	9 2 2
	31	[17]	GETGLOBAL	10 -1	; require
	32	[17]	LOADK    	11 -12	; "apps/filemanager/filemanagerfilesearcher"
	33	[17]	CALL     	10 2 2
	34	[18]	GETGLOBAL	11 -1	; require
	35	[18]	LOADK    	12 -13	; "apps/filemanager/filemanagershortcuts"
	36	[18]	CALL     	11 2 2
	37	[19]	GETGLOBAL	12 -1	; require
	38	[19]	LOADK    	13 -14	; "ui/widget/infomessage"
	39	[19]	CALL     	12 2 2
	40	[20]	GETGLOBAL	13 -1	; require
	41	[20]	LOADK    	14 -15	; "ui/widget/container/inputcontainer"
	42	[20]	CALL     	13 2 2
	43	[21]	GETGLOBAL	14 -1	; require
	44	[21]	LOADK    	15 -16	; "ui/widget/inputdialog"
	45	[21]	CALL     	14 2 2
	46	[22]	GETGLOBAL	15 -1	; require
	47	[22]	LOADK    	16 -17	; "pluginloader"
	48	[22]	CALL     	15 2 2
	49	[23]	GETGLOBAL	16 -1	; require
	50	[23]	LOADK    	17 -18	; "apps/reader/modules/readeractivityindicator"
	51	[23]	CALL     	16 2 2
	52	[24]	GETGLOBAL	17 -1	; require
	53	[24]	LOADK    	18 -19	; "apps/reader/modules/readerback"
	54	[24]	CALL     	17 2 2
	55	[25]	GETGLOBAL	18 -1	; require
	56	[25]	LOADK    	19 -20	; "apps/reader/modules/readerbookmark"
	57	[25]	CALL     	18 2 2
	58	[26]	GETGLOBAL	19 -1	; require
	59	[26]	LOADK    	20 -21	; "apps/reader/modules/readerconfig"
	60	[26]	CALL     	19 2 2
	61	[27]	GETGLOBAL	20 -1	; require
	62	[27]	LOADK    	21 -22	; "apps/reader/modules/readercoptlistener"
	63	[27]	CALL     	20 2 2
	64	[28]	GETGLOBAL	21 -1	; require
	65	[28]	LOADK    	22 -23	; "apps/reader/modules/readercropping"
	66	[28]	CALL     	21 2 2
	67	[29]	GETGLOBAL	22 -1	; require
	68	[29]	LOADK    	23 -24	; "apps/reader/modules/readerdevicestatus"
	69	[29]	CALL     	22 2 2
	70	[30]	GETGLOBAL	23 -1	; require
	71	[30]	LOADK    	24 -25	; "apps/reader/modules/readerdictionary"
	72	[30]	CALL     	23 2 2
	73	[31]	GETGLOBAL	24 -1	; require
	74	[31]	LOADK    	25 -26	; "apps/reader/modules/readerfont"
	75	[31]	CALL     	24 2 2
	76	[32]	GETGLOBAL	25 -1	; require
	77	[32]	LOADK    	26 -27	; "apps/reader/modules/readerfrontlight"
	78	[32]	CALL     	25 2 2
	79	[33]	GETGLOBAL	26 -1	; require
	80	[33]	LOADK    	27 -28	; "apps/reader/modules/readergesture"
	81	[33]	CALL     	26 2 2
	82	[34]	GETGLOBAL	27 -1	; require
	83	[34]	LOADK    	28 -29	; "apps/reader/modules/readergoto"
	84	[34]	CALL     	27 2 2
	85	[35]	GETGLOBAL	28 -1	; require
	86	[35]	LOADK    	29 -30	; "apps/reader/modules/readerhinting"
	87	[35]	CALL     	28 2 2
	88	[36]	GETGLOBAL	29 -1	; require
	89	[36]	LOADK    	30 -31	; "apps/reader/modules/readerhighlight"
	90	[36]	CALL     	29 2 2
	91	[37]	GETGLOBAL	30 -1	; require
	92	[37]	LOADK    	31 -32	; "apps/reader/modules/readerkoptlistener"
	93	[37]	CALL     	30 2 2
	94	[38]	GETGLOBAL	31 -1	; require
	95	[38]	LOADK    	32 -33	; "apps/reader/modules/readerlink"
	96	[38]	CALL     	31 2 2
	97	[39]	GETGLOBAL	32 -1	; require
	98	[39]	LOADK    	33 -34	; "apps/reader/modules/readermenu"
	99	[39]	CALL     	32 2 2
	100	[40]	GETGLOBAL	33 -1	; require
	101	[40]	LOADK    	34 -35	; "apps/reader/modules/readerpagemap"
	102	[40]	CALL     	33 2 2
	103	[41]	GETGLOBAL	34 -1	; require
	104	[41]	LOADK    	35 -36	; "apps/reader/modules/readerpanning"
	105	[41]	CALL     	34 2 2
	106	[42]	GETGLOBAL	35 -1	; require
	107	[42]	LOADK    	36 -37	; "apps/reader/modules/readerrotation"
	108	[42]	CALL     	35 2 2
	109	[43]	GETGLOBAL	36 -1	; require
	110	[43]	LOADK    	37 -38	; "apps/reader/modules/readerpaging"
	111	[43]	CALL     	36 2 2
	112	[44]	GETGLOBAL	37 -1	; require
	113	[44]	LOADK    	38 -39	; "apps/reader/modules/readerrolling"
	114	[44]	CALL     	37 2 2
	115	[45]	GETGLOBAL	38 -1	; require
	116	[45]	LOADK    	39 -40	; "apps/reader/modules/readersearch"
	117	[45]	CALL     	38 2 2
	118	[46]	GETGLOBAL	39 -1	; require
	119	[46]	LOADK    	40 -41	; "apps/reader/modules/readerstatus"
	120	[46]	CALL     	39 2 2
	121	[47]	GETGLOBAL	40 -1	; require
	122	[47]	LOADK    	41 -42	; "apps/reader/modules/readerstyletweak"
	123	[47]	CALL     	40 2 2
	124	[48]	GETGLOBAL	41 -1	; require
	125	[48]	LOADK    	42 -43	; "apps/reader/modules/readertoc"
	126	[48]	CALL     	41 2 2
	127	[49]	GETGLOBAL	42 -1	; require
	128	[49]	LOADK    	43 -44	; "apps/reader/modules/readertypeset"
	129	[49]	CALL     	42 2 2
	130	[50]	GETGLOBAL	43 -1	; require
	131	[50]	LOADK    	44 -45	; "apps/reader/modules/readertypography"
	132	[50]	CALL     	43 2 2
	133	[51]	GETGLOBAL	44 -1	; require
	134	[51]	LOADK    	45 -46	; "apps/reader/modules/readerview"
	135	[51]	CALL     	44 2 2
	136	[52]	GETGLOBAL	45 -1	; require
	137	[52]	LOADK    	46 -47	; "apps/reader/modules/readerwikipedia"
	138	[52]	CALL     	45 2 2
	139	[53]	GETGLOBAL	46 -1	; require
	140	[53]	LOADK    	47 -48	; "apps/reader/modules/readerzooming"
	141	[53]	CALL     	46 2 2
	142	[54]	GETGLOBAL	47 -1	; require
	143	[54]	LOADK    	48 -49	; "ui/widget/screenshoter"
	144	[54]	CALL     	47 2 2
	145	[55]	GETGLOBAL	48 -1	; require
	146	[55]	LOADK    	49 -50	; "ui/data/settings_migration"
	147	[55]	CALL     	48 2 2
	148	[56]	GETGLOBAL	49 -1	; require
	149	[56]	LOADK    	50 -51	; "ui/uimanager"
	150	[56]	CALL     	49 2 2
	151	[57]	GETGLOBAL	50 -1	; require
	152	[57]	LOADK    	51 -52	; "libs/libkoreader-lfs"
	153	[57]	CALL     	50 2 2
	154	[58]	GETGLOBAL	51 -1	; require
	155	[58]	LOADK    	52 -53	; "logger"
	156	[58]	CALL     	51 2 2
	157	[59]	GETGLOBAL	52 -1	; require
	158	[59]	LOADK    	53 -54	; "util"
	159	[59]	CALL     	52 2 2
	160	[60]	GETGLOBAL	53 -1	; require
	161	[60]	LOADK    	54 -55	; "gettext"
	162	[60]	CALL     	53 2 2
	163	[61]	GETGLOBAL	54 -1	; require
	164	[61]	LOADK    	55 -5	; "device"
	165	[61]	CALL     	54 2 2
	166	[61]	GETTABLE 	54 54 -56	; "screen"
	167	[62]	GETGLOBAL	55 -1	; require
	168	[62]	LOADK    	56 -57	; "ffi/util"
	169	[62]	CALL     	55 2 2
	170	[62]	GETTABLE 	55 55 -58	; "template"
	171	[64]	SELF     	56 13 -59	; "new"
	172	[64]	NEWTABLE 	58 0 7
	173	[65]	SETTABLE 	58 -60 -61	; "name" "ReaderUI"
	174	[66]	NEWTABLE 	59 0 0
	175	[66]	SETTABLE 	58 -62 59	; "active_widgets" -
	176	[69]	SETTABLE 	58 -63 -64	; "dialog" nil
	177	[72]	SETTABLE 	58 -65 -64	; "document" nil
	178	[75]	SETTABLE 	58 -66 -64	; "password" nil
	179	[77]	SETTABLE 	58 -67 -64	; "postInitCallback" nil
	180	[78]	SETTABLE 	58 -68 -64	; "postReaderCallback" nil
	181	[64]	CALL     	56 3 2
	182	[85]	CLOSURE  	57 0	; 0x7fc5a1407ff0
	183	[81]	SETTABLE 	56 -69 57	; "registerModule" -
	184	[89]	CLOSURE  	57 1	; 0x7fc5a14086c0
	185	[87]	SETTABLE 	56 -70 57	; "registerPostInitCallback" -
	186	[93]	CLOSURE  	57 2	; 0x7fc5a14087e0
	187	[91]	SETTABLE 	56 -71 57	; "registerPostReadyCallback" -
	188	[429]	CLOSURE  	57 3	; 0x7fc5a1408ab0
	189	[429]	MOVE     	0 54
	190	[429]	MOVE     	0 4
	191	[429]	MOVE     	0 48
	192	[429]	MOVE     	0 3
	193	[429]	MOVE     	0 44
	194	[429]	MOVE     	0 31
	195	[429]	MOVE     	0 29
	196	[429]	MOVE     	0 32
	197	[429]	MOVE     	0 35
	198	[429]	MOVE     	0 41
	199	[429]	MOVE     	0 18
	200	[429]	MOVE     	0 27
	201	[429]	MOVE     	0 23
	202	[429]	MOVE     	0 45
	203	[429]	MOVE     	0 47
	204	[429]	MOVE     	0 25
	205	[429]	MOVE     	0 22
	206	[429]	MOVE     	0 19
	207	[429]	MOVE     	0 30
	208	[429]	MOVE     	0 20
	209	[429]	MOVE     	0 16
	210	[429]	MOVE     	0 21
	211	[429]	MOVE     	0 36
	212	[429]	MOVE     	0 46
	213	[429]	MOVE     	0 34
	214	[429]	MOVE     	0 28
	215	[429]	MOVE     	0 6
	216	[429]	MOVE     	0 40
	217	[429]	MOVE     	0 42
	218	[429]	MOVE     	0 24
	219	[429]	MOVE     	0 43
	220	[429]	MOVE     	0 37
	221	[429]	MOVE     	0 33
	222	[429]	MOVE     	0 17
	223	[429]	MOVE     	0 38
	224	[429]	MOVE     	0 39
	225	[429]	MOVE     	0 10
	226	[429]	MOVE     	0 11
	227	[429]	MOVE     	0 9
	228	[429]	MOVE     	0 8
	229	[429]	MOVE     	0 7
	230	[429]	MOVE     	0 15
	231	[429]	MOVE     	0 51
	232	[429]	MOVE     	0 26
	233	[95]	SETTABLE 	56 -72 57	; "init" -
	234	[440]	CLOSURE  	57 4	; 0x7fc5a1409970
	235	[431]	SETTABLE 	56 -73 57	; "getLastDirFile" -
	236	[457]	CLOSURE  	57 5	; 0x7fc5a140a310
	237	[457]	MOVE     	0 52
	238	[442]	SETTABLE 	56 -74 57	; "showFileManager" -
	239	[500]	CLOSURE  	57 6	; 0x7fc5a140a910
	240	[500]	MOVE     	0 51
	241	[500]	MOVE     	0 50
	242	[500]	MOVE     	0 49
	243	[500]	MOVE     	0 12
	244	[500]	MOVE     	0 55
	245	[500]	MOVE     	0 53
	246	[500]	MOVE     	0 0
	247	[500]	MOVE     	0 5
	248	[500]	MOVE     	0 4
	249	[500]	MOVE     	0 2
	250	[459]	SETTABLE 	56 -75 57	; "showReader" -
	251	[524]	CLOSURE  	57 7	; 0x7fc5a140b0f0
	252	[524]	MOVE     	0 49
	253	[524]	MOVE     	0 12
	254	[524]	MOVE     	0 55
	255	[524]	MOVE     	0 53
	256	[524]	MOVE     	0 0
	257	[524]	MOVE     	0 51
	258	[502]	SETTABLE 	56 -76 57	; "showReaderCoroutine" -
	259	[526]	LOADNIL  	57 57
	260	[575]	CLOSURE  	58 8	; 0x7fc5a140b3b0
	261	[575]	MOVE     	0 51
	262	[575]	MOVE     	0 57
	263	[575]	MOVE     	0 5
	264	[575]	MOVE     	0 49
	265	[575]	MOVE     	0 12
	266	[575]	MOVE     	0 53
	267	[575]	MOVE     	0 56
	268	[575]	MOVE     	0 54
	269	[575]	MOVE     	0 52
	270	[527]	SETTABLE 	56 -77 58	; "doShowReader" -
	271	[579]	CLOSURE  	58 9	; 0x7fc5a140d430
	272	[579]	MOVE     	0 57
	273	[577]	SETTABLE 	56 -78 58	; "_getRunningInstance" -
	274	[615]	CLOSURE  	58 10	; 0x7fc5a140d6e0
	275	[615]	MOVE     	0 51
	276	[615]	MOVE     	0 14
	277	[615]	MOVE     	0 53
	278	[615]	MOVE     	0 49
	279	[581]	SETTABLE 	56 -79 58	; "unlockDocumentWithPassword" -
	280	[620]	CLOSURE  	58 11	; 0x7fc5a140d980
	281	[617]	SETTABLE 	56 -80 58	; "onVerifyPassword" -
	282	[625]	CLOSURE  	58 12	; 0x7fc5a140e750
	283	[625]	MOVE     	0 49
	284	[622]	SETTABLE 	56 -81 58	; "closeDialog" -
	285	[630]	CLOSURE  	58 13	; 0x7fc5a140ebb0
	286	[627]	SETTABLE 	56 -82 58	; "onScreenResize" -
	287	[636]	CLOSURE  	58 14	; 0x7fc5a140eed0
	288	[636]	MOVE     	0 6
	289	[632]	SETTABLE 	56 -83 58	; "saveSettings" -
	290	[640]	CLOSURE  	58 15	; 0x7fc5a140f230
	291	[638]	SETTABLE 	56 -84 58	; "onFlushSettings" -
	292	[645]	CLOSURE  	58 16	; 0x7fc5a140f740
	293	[642]	SETTABLE 	56 -85 58	; "closeDocument" -
	294	[673]	CLOSURE  	58 17	; 0x7fc5a140d3b0
	295	[673]	MOVE     	0 6
	296	[673]	MOVE     	0 49
	297	[673]	MOVE     	0 2
	298	[673]	MOVE     	0 53
	299	[647]	SETTABLE 	56 -86 58	; "notifyCloseDocument" -
	300	[695]	CLOSURE  	58 18	; 0x7fc5a140c2c0
	301	[695]	MOVE     	0 51
	302	[695]	MOVE     	0 49
	303	[695]	MOVE     	0 1
	304	[695]	MOVE     	0 57
	305	[675]	SETTABLE 	56 -87 58	; "onClose" -
	306	[721]	CLOSURE  	58 19	; 0x7fc5a140ddb0
	307	[721]	MOVE     	0 51
	308	[721]	MOVE     	0 49
	309	[721]	MOVE     	0 12
	310	[721]	MOVE     	0 53
	311	[697]	SETTABLE 	56 -88 58	; "dealWithLoadDocumentFailure" -
	312	[727]	CLOSURE  	58 20	; 0x7fc5a140fc90
	313	[723]	SETTABLE 	56 -89 58	; "onHome" -
	314	[741]	CLOSURE  	58 21	; 0x7fc5a140b980
	315	[741]	MOVE     	0 6
	316	[729]	SETTABLE 	56 -90 58	; "reloadDocument" -
	317	[750]	CLOSURE  	58 22	; 0x7fc5a140f470
	318	[750]	MOVE     	0 6
	319	[743]	SETTABLE 	56 -91 58	; "switchDocument" -
	320	[758]	CLOSURE  	58 23	; 0x7fc5a14103c0
	321	[752]	SETTABLE 	56 -92 58	; "getCurrentPage" -
	322	[760]	RETURN   	56 2
	323	[760]	RETURN   	0 1

function <./frontend/apps/reader/readerui.lua:81,85> (18 instructions, 72 bytes at 0x7fc5a1407ff0)
4 params, 7 slots, 0 upvalues, 4 locals, 5 constants, 0 functions
	1	[82]	TEST     	1 0 0
	2	[82]	JMP      	1	; to 4
	3	[82]	SETTABLE 	0 1 2
	4	[83]	LOADK    	4 -2	; "reader"
	5	[83]	MOVE     	5 1
	6	[83]	CONCAT   	4 4 5
	7	[83]	SETTABLE 	2 -1 4	; "name" -
	8	[84]	GETGLOBAL	4 -3	; table
	9	[84]	GETTABLE 	4 4 -4	; "insert"
	10	[84]	TEST     	3 0 0
	11	[84]	JMP      	3	; to 15
	12	[84]	GETTABLE 	5 0 -5	; "active_widgets"
	13	[84]	TEST     	5 0 1
	14	[84]	JMP      	1	; to 16
	15	[84]	MOVE     	5 0
	16	[84]	MOVE     	6 2
	17	[84]	CALL     	4 3 1
	18	[85]	RETURN   	0 1

function <./frontend/apps/reader/readerui.lua:87,89> (6 instructions, 24 bytes at 0x7fc5a14086c0)
2 params, 5 slots, 0 upvalues, 2 locals, 3 constants, 0 functions
	1	[88]	GETGLOBAL	2 -1	; table
	2	[88]	GETTABLE 	2 2 -2	; "insert"
	3	[88]	GETTABLE 	3 0 -3	; "postInitCallback"
	4	[88]	MOVE     	4 1
	5	[88]	CALL     	2 3 1
	6	[89]	RETURN   	0 1

function <./frontend/apps/reader/readerui.lua:91,93> (6 instructions, 24 bytes at 0x7fc5a14087e0)
2 params, 5 slots, 0 upvalues, 2 locals, 3 constants, 0 functions
	1	[92]	GETGLOBAL	2 -1	; table
	2	[92]	GETTABLE 	2 2 -2	; "insert"
	3	[92]	GETTABLE 	3 0 -3	; "postReaderCallback"
	4	[92]	MOVE     	4 1
	5	[92]	CALL     	2 3 1
	6	[93]	RETURN   	0 1

function <./frontend/apps/reader/readerui.lua:95,429> (631 instructions, 2524 bytes at 0x7fc5a1408ab0)
1 param, 14 slots, 44 upvalues, 19 locals, 87 constants, 1 function
	1	[97]	GETUPVAL 	1 0	; Screen
	2	[97]	GETTABLE 	1 1 -1	; "low_pan_rate"
	3	[97]	TEST     	1 0 0
	4	[97]	JMP      	3	; to 8
	5	[97]	LOADK    	1 -2	; 2
	6	[97]	TEST     	1 0 1
	7	[97]	JMP      	1	; to 9
	8	[97]	LOADK    	1 -3	; 30
	9	[99]	NEWTABLE 	2 0 0
	10	[99]	SETTABLE 	0 -4 2	; "postInitCallback" -
	11	[100]	NEWTABLE 	2 0 0
	12	[100]	SETTABLE 	0 -5 2	; "postReaderCallback" -
	13	[102]	GETTABLE 	2 0 -6	; "dialog"
	14	[102]	TEST     	2 0 1
	15	[102]	JMP      	1	; to 17
	16	[103]	SETTABLE 	0 -6 0	; "dialog" -
	17	[106]	GETUPVAL 	2 1	; DocSettings
	18	[106]	SELF     	2 2 -8	; "open"
	19	[106]	GETTABLE 	4 0 -9	; "document"
	20	[106]	GETTABLE 	4 4 -10	; "file"
	21	[106]	CALL     	2 3 2
	22	[106]	SETTABLE 	0 -7 2	; "doc_settings" -
	23	[108]	GETUPVAL 	2 2	; SettingsMigration
	24	[108]	SELF     	2 2 -11	; "migrateSettings"
	25	[108]	GETTABLE 	4 0 -7	; "doc_settings"
	26	[108]	CALL     	2 3 1
	27	[110]	GETUPVAL 	2 3	; Device
	28	[110]	SELF     	2 2 -12	; "hasKeys"
	29	[110]	CALL     	2 2 2
	30	[110]	TEST     	2 0 0
	31	[110]	JMP      	8	; to 40
	32	[111]	GETTABLE 	2 0 -13	; "key_events"
	33	[111]	NEWTABLE 	3 1 1
	34	[111]	NEWTABLE 	4 1 0
	35	[111]	LOADK    	5 -14	; "Home"
	36	[111]	SETLIST  	4 1 1	; 1
	37	[111]	SETTABLE 	3 -15 -16	; "doc" "open file browser"
	38	[111]	SETLIST  	3 1 1	; 1
	39	[111]	SETTABLE 	2 -14 3	; "Home" -
	40	[116]	SELF     	2 0 -17	; "registerModule"
	41	[116]	LOADK    	4 -18	; "view"
	42	[116]	GETUPVAL 	5 4	; ReaderView
	43	[116]	SELF     	5 5 -19	; "new"
	44	[116]	NEWTABLE 	7 0 4
	45	[117]	GETTABLE 	8 0 -6	; "dialog"
	46	[117]	SETTABLE 	7 -6 8	; "dialog" -
	47	[118]	GETTABLE 	8 0 -20	; "dimen"
	48	[118]	SETTABLE 	7 -20 8	; "dimen" -
	49	[119]	SETTABLE 	7 -21 0	; "ui" -
	50	[120]	GETTABLE 	8 0 -9	; "document"
	51	[120]	SETTABLE 	7 -9 8	; "document" -
	52	[116]	CALL     	5 3 0
	53	[116]	CALL     	2 0 1
	54	[123]	SELF     	2 0 -17	; "registerModule"
	55	[123]	LOADK    	4 -22	; "link"
	56	[123]	GETUPVAL 	5 5	; ReaderLink
	57	[123]	SELF     	5 5 -19	; "new"
	58	[123]	NEWTABLE 	7 0 4
	59	[124]	GETTABLE 	8 0 -6	; "dialog"
	60	[124]	SETTABLE 	7 -6 8	; "dialog" -
	61	[125]	GETTABLE 	8 0 -18	; "view"
	62	[125]	SETTABLE 	7 -18 8	; "view" -
	63	[126]	SETTABLE 	7 -21 0	; "ui" -
	64	[127]	GETTABLE 	8 0 -9	; "document"
	65	[127]	SETTABLE 	7 -9 8	; "document" -
	66	[123]	CALL     	5 3 0
	67	[123]	CALL     	2 0 1
	68	[130]	SELF     	2 0 -17	; "registerModule"
	69	[130]	LOADK    	4 -23	; "highlight"
	70	[130]	GETUPVAL 	5 6	; ReaderHighlight
	71	[130]	SELF     	5 5 -19	; "new"
	72	[130]	NEWTABLE 	7 0 4
	73	[131]	GETTABLE 	8 0 -6	; "dialog"
	74	[131]	SETTABLE 	7 -6 8	; "dialog" -
	75	[132]	GETTABLE 	8 0 -18	; "view"
	76	[132]	SETTABLE 	7 -18 8	; "view" -
	77	[133]	SETTABLE 	7 -21 0	; "ui" -
	78	[134]	GETTABLE 	8 0 -9	; "document"
	79	[134]	SETTABLE 	7 -9 8	; "document" -
	80	[130]	CALL     	5 3 0
	81	[130]	CALL     	2 0 1
	82	[139]	SELF     	2 0 -17	; "registerModule"
	83	[139]	LOADK    	4 -24	; "menu"
	84	[139]	GETUPVAL 	5 7	; ReaderMenu
	85	[139]	SELF     	5 5 -19	; "new"
	86	[139]	NEWTABLE 	7 0 2
	87	[140]	GETTABLE 	8 0 -18	; "view"
	88	[140]	SETTABLE 	7 -18 8	; "view" -
	89	[141]	SETTABLE 	7 -21 0	; "ui" -
	90	[139]	CALL     	5 3 0
	91	[139]	CALL     	2 0 1
	92	[144]	SELF     	2 0 -17	; "registerModule"
	93	[144]	LOADK    	4 -25	; "rotation"
	94	[144]	GETUPVAL 	5 8	; ReaderRotation
	95	[144]	SELF     	5 5 -19	; "new"
	96	[144]	NEWTABLE 	7 0 3
	97	[145]	GETTABLE 	8 0 -6	; "dialog"
	98	[145]	SETTABLE 	7 -6 8	; "dialog" -
	99	[146]	GETTABLE 	8 0 -18	; "view"
	100	[146]	SETTABLE 	7 -18 8	; "view" -
	101	[147]	SETTABLE 	7 -21 0	; "ui" -
	102	[144]	CALL     	5 3 0
	103	[144]	CALL     	2 0 1
	104	[150]	SELF     	2 0 -17	; "registerModule"
	105	[150]	LOADK    	4 -26	; "toc"
	106	[150]	GETUPVAL 	5 9	; ReaderToc
	107	[150]	SELF     	5 5 -19	; "new"
	108	[150]	NEWTABLE 	7 0 3
	109	[151]	GETTABLE 	8 0 -6	; "dialog"
	110	[151]	SETTABLE 	7 -6 8	; "dialog" -
	111	[152]	GETTABLE 	8 0 -18	; "view"
	112	[152]	SETTABLE 	7 -18 8	; "view" -
	113	[153]	SETTABLE 	7 -21 0	; "ui" -
	114	[150]	CALL     	5 3 0
	115	[150]	CALL     	2 0 1
	116	[156]	SELF     	2 0 -17	; "registerModule"
	117	[156]	LOADK    	4 -27	; "bookmark"
	118	[156]	GETUPVAL 	5 10	; ReaderBookmark
	119	[156]	SELF     	5 5 -19	; "new"
	120	[156]	NEWTABLE 	7 0 3
	121	[157]	GETTABLE 	8 0 -6	; "dialog"
	122	[157]	SETTABLE 	7 -6 8	; "dialog" -
	123	[158]	GETTABLE 	8 0 -18	; "view"
	124	[158]	SETTABLE 	7 -18 8	; "view" -
	125	[159]	SETTABLE 	7 -21 0	; "ui" -
	126	[156]	CALL     	5 3 0
	127	[156]	CALL     	2 0 1
	128	[163]	SELF     	2 0 -17	; "registerModule"
	129	[163]	LOADK    	4 -28	; "gotopage"
	130	[163]	GETUPVAL 	5 11	; ReaderGoto
	131	[163]	SELF     	5 5 -19	; "new"
	132	[163]	NEWTABLE 	7 0 4
	133	[164]	GETTABLE 	8 0 -6	; "dialog"
	134	[164]	SETTABLE 	7 -6 8	; "dialog" -
	135	[165]	GETTABLE 	8 0 -18	; "view"
	136	[165]	SETTABLE 	7 -18 8	; "view" -
	137	[166]	SETTABLE 	7 -21 0	; "ui" -
	138	[167]	GETTABLE 	8 0 -9	; "document"
	139	[167]	SETTABLE 	7 -9 8	; "document" -
	140	[163]	CALL     	5 3 0
	141	[163]	CALL     	2 0 1
	142	[170]	SELF     	2 0 -17	; "registerModule"
	143	[170]	LOADK    	4 -29	; "dictionary"
	144	[170]	GETUPVAL 	5 12	; ReaderDictionary
	145	[170]	SELF     	5 5 -19	; "new"
	146	[170]	NEWTABLE 	7 0 4
	147	[171]	GETTABLE 	8 0 -6	; "dialog"
	148	[171]	SETTABLE 	7 -6 8	; "dialog" -
	149	[172]	GETTABLE 	8 0 -18	; "view"
	150	[172]	SETTABLE 	7 -18 8	; "view" -
	151	[173]	SETTABLE 	7 -21 0	; "ui" -
	152	[174]	GETTABLE 	8 0 -9	; "document"
	153	[174]	SETTABLE 	7 -9 8	; "document" -
	154	[170]	CALL     	5 3 0
	155	[170]	CALL     	2 0 1
	156	[177]	SELF     	2 0 -17	; "registerModule"
	157	[177]	LOADK    	4 -30	; "wikipedia"
	158	[177]	GETUPVAL 	5 13	; ReaderWikipedia
	159	[177]	SELF     	5 5 -19	; "new"
	160	[177]	NEWTABLE 	7 0 4
	161	[178]	GETTABLE 	8 0 -6	; "dialog"
	162	[178]	SETTABLE 	7 -6 8	; "dialog" -
	163	[179]	GETTABLE 	8 0 -18	; "view"
	164	[179]	SETTABLE 	7 -18 8	; "view" -
	165	[180]	SETTABLE 	7 -21 0	; "ui" -
	166	[181]	GETTABLE 	8 0 -9	; "document"
	167	[181]	SETTABLE 	7 -9 8	; "document" -
	168	[177]	CALL     	5 3 0
	169	[177]	CALL     	2 0 1
	170	[184]	SELF     	2 0 -17	; "registerModule"
	171	[184]	LOADK    	4 -31	; "screenshot"
	172	[184]	GETUPVAL 	5 14	; Screenshoter
	173	[184]	SELF     	5 5 -19	; "new"
	174	[184]	NEWTABLE 	7 0 4
	175	[185]	SETTABLE 	7 -32 -33	; "prefix" "Reader"
	176	[186]	GETTABLE 	8 0 -6	; "dialog"
	177	[186]	SETTABLE 	7 -6 8	; "dialog" -
	178	[187]	GETTABLE 	8 0 -18	; "view"
	179	[187]	SETTABLE 	7 -18 8	; "view" -
	180	[188]	SETTABLE 	7 -21 0	; "ui" -
	181	[184]	CALL     	5 3 2
	182	[189]	LOADBOOL 	6 1 0
	183	[184]	CALL     	2 5 1
	184	[191]	GETUPVAL 	2 3	; Device
	185	[191]	SELF     	2 2 -34	; "hasFrontlight"
	186	[191]	CALL     	2 2 2
	187	[191]	TEST     	2 0 0
	188	[191]	JMP      	12	; to 201
	189	[192]	SELF     	2 0 -17	; "registerModule"
	190	[192]	LOADK    	4 -35	; "frontlight"
	191	[192]	GETUPVAL 	5 15	; ReaderFrontLight
	192	[192]	SELF     	5 5 -19	; "new"
	193	[192]	NEWTABLE 	7 0 3
	194	[193]	GETTABLE 	8 0 -6	; "dialog"
	195	[193]	SETTABLE 	7 -6 8	; "dialog" -
	196	[194]	GETTABLE 	8 0 -18	; "view"
	197	[194]	SETTABLE 	7 -18 8	; "view" -
	198	[195]	SETTABLE 	7 -21 0	; "ui" -
	199	[192]	CALL     	5 3 0
	200	[192]	CALL     	2 0 1
	201	[199]	SELF     	2 0 -17	; "registerModule"
	202	[199]	LOADK    	4 -36	; "battery"
	203	[199]	GETUPVAL 	5 16	; ReaderDeviceStatus
	204	[199]	SELF     	5 5 -19	; "new"
	205	[199]	NEWTABLE 	7 0 1
	206	[200]	SETTABLE 	7 -21 0	; "ui" -
	207	[199]	CALL     	5 3 0
	208	[199]	CALL     	2 0 1
	209	[203]	GETTABLE 	2 0 -9	; "document"
	210	[203]	GETTABLE 	2 2 -37	; "info"
	211	[203]	GETTABLE 	2 2 -38	; "configurable"
	212	[203]	TEST     	2 0 0
	213	[203]	JMP      	65	; to 279
	214	[205]	SELF     	2 0 -17	; "registerModule"
	215	[205]	LOADK    	4 -39	; "config"
	216	[205]	GETUPVAL 	5 17	; ReaderConfig
	217	[205]	SELF     	5 5 -19	; "new"
	218	[205]	NEWTABLE 	7 0 5
	219	[206]	GETTABLE 	8 0 -9	; "document"
	220	[206]	GETTABLE 	8 8 -38	; "configurable"
	221	[206]	SETTABLE 	7 -38 8	; "configurable" -
	222	[207]	GETTABLE 	8 0 -6	; "dialog"
	223	[207]	SETTABLE 	7 -6 8	; "dialog" -
	224	[208]	GETTABLE 	8 0 -18	; "view"
	225	[208]	SETTABLE 	7 -18 8	; "view" -
	226	[209]	SETTABLE 	7 -21 0	; "ui" -
	227	[210]	GETTABLE 	8 0 -9	; "document"
	228	[210]	SETTABLE 	7 -9 8	; "document" -
	229	[205]	CALL     	5 3 0
	230	[205]	CALL     	2 0 1
	231	[212]	GETTABLE 	2 0 -9	; "document"
	232	[212]	GETTABLE 	2 2 -37	; "info"
	233	[212]	GETTABLE 	2 2 -40	; "has_pages"
	234	[212]	TEST     	2 0 0
	235	[212]	JMP      	15	; to 251
	236	[214]	SELF     	2 0 -17	; "registerModule"
	237	[214]	LOADK    	4 -41	; "koptlistener"
	238	[214]	GETUPVAL 	5 18	; ReaderKoptListener
	239	[214]	SELF     	5 5 -19	; "new"
	240	[214]	NEWTABLE 	7 0 4
	241	[215]	GETTABLE 	8 0 -6	; "dialog"
	242	[215]	SETTABLE 	7 -6 8	; "dialog" -
	243	[216]	GETTABLE 	8 0 -18	; "view"
	244	[216]	SETTABLE 	7 -18 8	; "view" -
	245	[217]	SETTABLE 	7 -21 0	; "ui" -
	246	[218]	GETTABLE 	8 0 -9	; "document"
	247	[218]	SETTABLE 	7 -9 8	; "document" -
	248	[214]	CALL     	5 3 0
	249	[214]	CALL     	2 0 1
	250	[219]	JMP      	14	; to 265
	251	[222]	SELF     	2 0 -17	; "registerModule"
	252	[222]	LOADK    	4 -42	; "crelistener"
	253	[222]	GETUPVAL 	5 19	; ReaderCoptListener
	254	[222]	SELF     	5 5 -19	; "new"
	255	[222]	NEWTABLE 	7 0 4
	256	[223]	GETTABLE 	8 0 -6	; "dialog"
	257	[223]	SETTABLE 	7 -6 8	; "dialog" -
	258	[224]	GETTABLE 	8 0 -18	; "view"
	259	[224]	SETTABLE 	7 -18 8	; "view" -
	260	[225]	SETTABLE 	7 -21 0	; "ui" -
	261	[226]	GETTABLE 	8 0 -9	; "document"
	262	[226]	SETTABLE 	7 -9 8	; "document" -
	263	[222]	CALL     	5 3 0
	264	[222]	CALL     	2 0 1
	265	[230]	SELF     	2 0 -17	; "registerModule"
	266	[230]	LOADK    	4 -43	; "activityindicator"
	267	[230]	GETUPVAL 	5 20	; ReaderActivityIndicator
	268	[230]	SELF     	5 5 -19	; "new"
	269	[230]	NEWTABLE 	7 0 4
	270	[231]	GETTABLE 	8 0 -6	; "dialog"
	271	[231]	SETTABLE 	7 -6 8	; "dialog" -
	272	[232]	GETTABLE 	8 0 -18	; "view"
	273	[232]	SETTABLE 	7 -18 8	; "view" -
	274	[233]	SETTABLE 	7 -21 0	; "ui" -
	275	[234]	GETTABLE 	8 0 -9	; "document"
	276	[234]	SETTABLE 	7 -9 8	; "document" -
	277	[230]	CALL     	5 3 0
	278	[230]	CALL     	2 0 1
	279	[238]	GETTABLE 	2 0 -9	; "document"
	280	[238]	GETTABLE 	2 2 -37	; "info"
	281	[238]	GETTABLE 	2 2 -40	; "has_pages"
	282	[238]	TEST     	2 0 0
	283	[238]	JMP      	70	; to 354
	284	[240]	SELF     	2 0 -17	; "registerModule"
	285	[240]	LOADK    	4 -44	; "cropping"
	286	[240]	GETUPVAL 	5 21	; ReaderCropping
	287	[240]	SELF     	5 5 -19	; "new"
	288	[240]	NEWTABLE 	7 0 4
	289	[241]	GETTABLE 	8 0 -6	; "dialog"
	290	[241]	SETTABLE 	7 -6 8	; "dialog" -
	291	[242]	GETTABLE 	8 0 -18	; "view"
	292	[242]	SETTABLE 	7 -18 8	; "view" -
	293	[243]	SETTABLE 	7 -21 0	; "ui" -
	294	[244]	GETTABLE 	8 0 -9	; "document"
	295	[244]	SETTABLE 	7 -9 8	; "document" -
	296	[240]	CALL     	5 3 0
	297	[240]	CALL     	2 0 1
	298	[247]	SELF     	2 0 -17	; "registerModule"
	299	[247]	LOADK    	4 -45	; "paging"
	300	[247]	GETUPVAL 	5 22	; ReaderPaging
	301	[247]	SELF     	5 5 -19	; "new"
	302	[247]	NEWTABLE 	7 0 4
	303	[248]	SETTABLE 	7 -46 1	; "pan_rate" -
	304	[249]	GETTABLE 	8 0 -6	; "dialog"
	305	[249]	SETTABLE 	7 -6 8	; "dialog" -
	306	[250]	GETTABLE 	8 0 -18	; "view"
	307	[250]	SETTABLE 	7 -18 8	; "view" -
	308	[251]	SETTABLE 	7 -21 0	; "ui" -
	309	[247]	CALL     	5 3 0
	310	[247]	CALL     	2 0 1
	311	[254]	SELF     	2 0 -17	; "registerModule"
	312	[254]	LOADK    	4 -47	; "zooming"
	313	[254]	GETUPVAL 	5 23	; ReaderZooming
	314	[254]	SELF     	5 5 -19	; "new"
	315	[254]	NEWTABLE 	7 0 4
	316	[255]	GETTABLE 	8 0 -6	; "dialog"
	317	[255]	SETTABLE 	7 -6 8	; "dialog" -
	318	[256]	GETTABLE 	8 0 -9	; "document"
	319	[256]	SETTABLE 	7 -9 8	; "document" -
	320	[257]	GETTABLE 	8 0 -18	; "view"
	321	[257]	SETTABLE 	7 -18 8	; "view" -
	322	[258]	SETTABLE 	7 -21 0	; "ui" -
	323	[254]	CALL     	5 3 0
	324	[254]	CALL     	2 0 1
	325	[261]	SELF     	2 0 -17	; "registerModule"
	326	[261]	LOADK    	4 -48	; "panning"
	327	[261]	GETUPVAL 	5 24	; ReaderPanning
	328	[261]	SELF     	5 5 -19	; "new"
	329	[261]	NEWTABLE 	7 0 3
	330	[262]	GETTABLE 	8 0 -6	; "dialog"
	331	[262]	SETTABLE 	7 -6 8	; "dialog" -
	332	[263]	GETTABLE 	8 0 -18	; "view"
	333	[263]	SETTABLE 	7 -18 8	; "view" -
	334	[264]	SETTABLE 	7 -21 0	; "ui" -
	335	[261]	CALL     	5 3 0
	336	[261]	CALL     	2 0 1
	337	[267]	SELF     	2 0 -17	; "registerModule"
	338	[267]	LOADK    	4 -49	; "hinting"
	339	[267]	GETUPVAL 	5 25	; ReaderHinting
	340	[267]	SELF     	5 5 -19	; "new"
	341	[267]	NEWTABLE 	7 0 5
	342	[268]	GETTABLE 	8 0 -6	; "dialog"
	343	[268]	SETTABLE 	7 -6 8	; "dialog" -
	344	[269]	GETTABLE 	8 0 -47	; "zooming"
	345	[269]	SETTABLE 	7 -50 8	; "zoom" -
	346	[270]	GETTABLE 	8 0 -18	; "view"
	347	[270]	SETTABLE 	7 -18 8	; "view" -
	348	[271]	SETTABLE 	7 -21 0	; "ui" -
	349	[272]	GETTABLE 	8 0 -9	; "document"
	350	[272]	SETTABLE 	7 -9 8	; "document" -
	351	[267]	CALL     	5 3 0
	352	[267]	CALL     	2 0 1
	353	[273]	JMP      	94	; to 448
	354	[277]	GETTABLE 	2 0 -9	; "document"
	355	[277]	GETTABLE 	2 2 -51	; "setupDefaultView"
	356	[277]	TEST     	2 0 0
	357	[277]	JMP      	3	; to 361
	358	[278]	GETTABLE 	2 0 -9	; "document"
	359	[278]	SELF     	2 2 -51	; "setupDefaultView"
	360	[278]	CALL     	2 2 1
	361	[281]	SELF     	2 0 -52	; "registerPostInitCallback"
	362	[291]	CLOSURE  	4 0	; 0x7fc5a14088e0
	363	[291]	MOVE     	0 0
	364	[291]	GETUPVAL 	0 26	; Event
	365	[281]	CALL     	2 3 1
	366	[293]	SELF     	2 0 -17	; "registerModule"
	367	[293]	LOADK    	4 -53	; "styletweak"
	368	[293]	GETUPVAL 	5 27	; ReaderStyleTweak
	369	[293]	SELF     	5 5 -19	; "new"
	370	[293]	NEWTABLE 	7 0 3
	371	[294]	GETTABLE 	8 0 -6	; "dialog"
	372	[294]	SETTABLE 	7 -6 8	; "dialog" -
	373	[295]	GETTABLE 	8 0 -18	; "view"
	374	[295]	SETTABLE 	7 -18 8	; "view" -
	375	[296]	SETTABLE 	7 -21 0	; "ui" -
	376	[293]	CALL     	5 3 0
	377	[293]	CALL     	2 0 1
	378	[299]	SELF     	2 0 -17	; "registerModule"
	379	[299]	LOADK    	4 -54	; "typeset"
	380	[299]	GETUPVAL 	5 28	; ReaderTypeset
	381	[299]	SELF     	5 5 -19	; "new"
	382	[299]	NEWTABLE 	7 0 3
	383	[300]	GETTABLE 	8 0 -6	; "dialog"
	384	[300]	SETTABLE 	7 -6 8	; "dialog" -
	385	[301]	GETTABLE 	8 0 -18	; "view"
	386	[301]	SETTABLE 	7 -18 8	; "view" -
	387	[302]	SETTABLE 	7 -21 0	; "ui" -
	388	[299]	CALL     	5 3 0
	389	[299]	CALL     	2 0 1
	390	[305]	SELF     	2 0 -17	; "registerModule"
	391	[305]	LOADK    	4 -55	; "font"
	392	[305]	GETUPVAL 	5 29	; ReaderFont
	393	[305]	SELF     	5 5 -19	; "new"
	394	[305]	NEWTABLE 	7 0 3
	395	[306]	GETTABLE 	8 0 -6	; "dialog"
	396	[306]	SETTABLE 	7 -6 8	; "dialog" -
	397	[307]	GETTABLE 	8 0 -18	; "view"
	398	[307]	SETTABLE 	7 -18 8	; "view" -
	399	[308]	SETTABLE 	7 -21 0	; "ui" -
	400	[305]	CALL     	5 3 0
	401	[305]	CALL     	2 0 1
	402	[311]	SELF     	2 0 -17	; "registerModule"
	403	[311]	LOADK    	4 -56	; "typography"
	404	[311]	GETUPVAL 	5 30	; ReaderTypography
	405	[311]	SELF     	5 5 -19	; "new"
	406	[311]	NEWTABLE 	7 0 3
	407	[312]	GETTABLE 	8 0 -6	; "dialog"
	408	[312]	SETTABLE 	7 -6 8	; "dialog" -
	409	[313]	GETTABLE 	8 0 -18	; "view"
	410	[313]	SETTABLE 	7 -18 8	; "view" -
	411	[314]	SETTABLE 	7 -21 0	; "ui" -
	412	[311]	CALL     	5 3 0
	413	[311]	CALL     	2 0 1
	414	[317]	SELF     	2 0 -17	; "registerModule"
	415	[317]	LOADK    	4 -57	; "rolling"
	416	[317]	GETUPVAL 	5 31	; ReaderRolling
	417	[317]	SELF     	5 5 -19	; "new"
	418	[317]	NEWTABLE 	7 0 4
	419	[318]	SETTABLE 	7 -46 1	; "pan_rate" -
	420	[319]	GETTABLE 	8 0 -6	; "dialog"
	421	[319]	SETTABLE 	7 -6 8	; "dialog" -
	422	[320]	GETTABLE 	8 0 -18	; "view"
	423	[320]	SETTABLE 	7 -18 8	; "view" -
	424	[321]	SETTABLE 	7 -21 0	; "ui" -
	425	[317]	CALL     	5 3 0
	426	[317]	CALL     	2 0 1
	427	[324]	SELF     	2 0 -17	; "registerModule"
	428	[324]	LOADK    	4 -58	; "pagemap"
	429	[324]	GETUPVAL 	5 32	; ReaderPageMap
	430	[324]	SELF     	5 5 -19	; "new"
	431	[324]	NEWTABLE 	7 0 3
	432	[325]	GETTABLE 	8 0 -6	; "dialog"
	433	[325]	SETTABLE 	7 -6 8	; "dialog" -
	434	[326]	GETTABLE 	8 0 -18	; "view"
	435	[326]	SETTABLE 	7 -18 8	; "view" -
	436	[327]	SETTABLE 	7 -21 0	; "ui" -
	437	[324]	CALL     	5 3 0
	438	[324]	CALL     	2 0 1
	439	[329]	GETGLOBAL	2 -60	; G_reader_settings
	440	[329]	SELF     	2 2 -61	; "readSetting"
	441	[329]	LOADK    	4 -59	; "disable_double_tap"
	442	[329]	CALL     	2 3 2
	443	[329]	EQ       	0 2 -62	; - false
	444	[329]	JMP      	1	; to 446
	445	[329]	LOADBOOL 	2 0 1
	446	[329]	LOADBOOL 	2 1 0
	447	[329]	SETTABLE 	0 -59 2	; "disable_double_tap" -
	448	[332]	SELF     	2 0 -17	; "registerModule"
	449	[332]	LOADK    	4 -63	; "back"
	450	[332]	GETUPVAL 	5 33	; ReaderBack
	451	[332]	SELF     	5 5 -19	; "new"
	452	[332]	NEWTABLE 	7 0 2
	453	[333]	SETTABLE 	7 -21 0	; "ui" -
	454	[334]	GETTABLE 	8 0 -18	; "view"
	455	[334]	SETTABLE 	7 -18 8	; "view" -
	456	[332]	CALL     	5 3 0
	457	[332]	CALL     	2 0 1
	458	[337]	SELF     	2 0 -17	; "registerModule"
	459	[337]	LOADK    	4 -64	; "search"
	460	[337]	GETUPVAL 	5 34	; ReaderSearch
	461	[337]	SELF     	5 5 -19	; "new"
	462	[337]	NEWTABLE 	7 0 3
	463	[338]	GETTABLE 	8 0 -6	; "dialog"
	464	[338]	SETTABLE 	7 -6 8	; "dialog" -
	465	[339]	GETTABLE 	8 0 -18	; "view"
	466	[339]	SETTABLE 	7 -18 8	; "view" -
	467	[340]	SETTABLE 	7 -21 0	; "ui" -
	468	[337]	CALL     	5 3 0
	469	[337]	CALL     	2 0 1
	470	[343]	SELF     	2 0 -17	; "registerModule"
	471	[343]	LOADK    	4 -65	; "status"
	472	[343]	GETUPVAL 	5 35	; ReaderStatus
	473	[343]	SELF     	5 5 -19	; "new"
	474	[343]	NEWTABLE 	7 0 3
	475	[344]	SETTABLE 	7 -21 0	; "ui" -
	476	[345]	GETTABLE 	8 0 -9	; "document"
	477	[345]	SETTABLE 	7 -9 8	; "document" -
	478	[346]	GETTABLE 	8 0 -18	; "view"
	479	[346]	SETTABLE 	7 -18 8	; "view" -
	480	[343]	CALL     	5 3 0
	481	[343]	CALL     	2 0 1
	482	[349]	SELF     	2 0 -17	; "registerModule"
	483	[349]	LOADK    	4 -66	; "filesearcher"
	484	[349]	GETUPVAL 	5 36	; FileManagerFileSearcher
	485	[349]	SELF     	5 5 -19	; "new"
	486	[349]	NEWTABLE 	7 0 2
	487	[350]	GETTABLE 	8 0 -6	; "dialog"
	488	[350]	SETTABLE 	7 -6 8	; "dialog" -
	489	[351]	SETTABLE 	7 -21 0	; "ui" -
	490	[349]	CALL     	5 3 0
	491	[349]	CALL     	2 0 1
	492	[354]	SELF     	2 0 -17	; "registerModule"
	493	[354]	LOADK    	4 -67	; "folder_shortcuts"
	494	[354]	GETUPVAL 	5 37	; FileManagerShortcuts
	495	[354]	SELF     	5 5 -19	; "new"
	496	[354]	NEWTABLE 	7 0 2
	497	[355]	GETTABLE 	8 0 -6	; "dialog"
	498	[355]	SETTABLE 	7 -6 8	; "dialog" -
	499	[356]	SETTABLE 	7 -21 0	; "ui" -
	500	[354]	CALL     	5 3 0
	501	[354]	CALL     	2 0 1
	502	[359]	SELF     	2 0 -17	; "registerModule"
	503	[359]	LOADK    	4 -68	; "history"
	504	[359]	GETUPVAL 	5 38	; FileManagerHistory
	505	[359]	SELF     	5 5 -19	; "new"
	506	[359]	NEWTABLE 	7 0 2
	507	[360]	GETTABLE 	8 0 -6	; "dialog"
	508	[360]	SETTABLE 	7 -6 8	; "dialog" -
	509	[361]	SETTABLE 	7 -21 0	; "ui" -
	510	[359]	CALL     	5 3 0
	511	[359]	CALL     	2 0 1
	512	[364]	SELF     	2 0 -17	; "registerModule"
	513	[364]	LOADK    	4 -69	; "collections"
	514	[364]	GETUPVAL 	5 39	; FileManagerCollection
	515	[364]	SELF     	5 5 -19	; "new"
	516	[364]	NEWTABLE 	7 0 2
	517	[365]	GETTABLE 	8 0 -6	; "dialog"
	518	[365]	SETTABLE 	7 -6 8	; "dialog" -
	519	[366]	SETTABLE 	7 -21 0	; "ui" -
	520	[364]	CALL     	5 3 0
	521	[364]	CALL     	2 0 1
	522	[369]	SELF     	2 0 -17	; "registerModule"
	523	[369]	LOADK    	4 -70	; "bookinfo"
	524	[369]	GETUPVAL 	5 40	; FileManagerBookInfo
	525	[369]	SELF     	5 5 -19	; "new"
	526	[369]	NEWTABLE 	7 0 3
	527	[370]	GETTABLE 	8 0 -6	; "dialog"
	528	[370]	SETTABLE 	7 -6 8	; "dialog" -
	529	[371]	GETTABLE 	8 0 -9	; "document"
	530	[371]	SETTABLE 	7 -9 8	; "document" -
	531	[372]	SETTABLE 	7 -21 0	; "ui" -
	532	[369]	CALL     	5 3 0
	533	[369]	CALL     	2 0 1
	534	[375]	GETGLOBAL	2 -71	; ipairs
	535	[375]	GETUPVAL 	3 41	; PluginLoader
	536	[375]	SELF     	3 3 -72	; "loadPlugins"
	537	[375]	CALL     	3 2 0
	538	[375]	CALL     	2 0 4
	539	[375]	JMP      	25	; to 565
	540	[376]	GETUPVAL 	7 41	; PluginLoader
	541	[376]	SELF     	7 7 -73	; "createPluginInstance"
	542	[377]	MOVE     	9 6
	543	[377]	NEWTABLE 	10 0 4
	544	[379]	GETTABLE 	11 0 -6	; "dialog"
	545	[379]	SETTABLE 	10 -6 11	; "dialog" -
	546	[380]	GETTABLE 	11 0 -18	; "view"
	547	[380]	SETTABLE 	10 -18 11	; "view" -
	548	[381]	SETTABLE 	10 -21 0	; "ui" -
	549	[382]	GETTABLE 	11 0 -9	; "document"
	550	[382]	SETTABLE 	10 -9 11	; "document" -
	551	[376]	CALL     	7 4 3
	552	[384]	TEST     	7 0 0
	553	[384]	JMP      	11	; to 565
	554	[385]	SELF     	9 0 -17	; "registerModule"
	555	[385]	GETTABLE 	11 6 -74	; "name"
	556	[385]	MOVE     	12 8
	557	[385]	CALL     	9 4 1
	558	[386]	GETUPVAL 	9 42	; logger
	559	[386]	GETTABLE 	9 9 -37	; "info"
	560	[386]	LOADK    	10 -75	; "RD loaded plugin"
	561	[386]	GETTABLE 	11 6 -74	; "name"
	562	[387]	LOADK    	12 -76	; "at"
	563	[387]	GETTABLE 	13 6 -77	; "path"
	564	[386]	CALL     	9 5 1
	565	[375]	TFORLOOP 	2 2
	566	[388]	JMP      	-27	; to 540
	567	[390]	GETUPVAL 	2 3	; Device
	568	[390]	SELF     	2 2 -78	; "isTouchDevice"
	569	[390]	CALL     	2 2 2
	570	[390]	TEST     	2 0 0
	571	[390]	JMP      	12	; to 584
	572	[392]	SELF     	2 0 -17	; "registerModule"
	573	[392]	LOADK    	4 -79	; "gesture"
	574	[392]	GETUPVAL 	5 43	; ReaderGesture
	575	[392]	SELF     	5 5 -19	; "new"
	576	[392]	NEWTABLE 	7 0 3
	577	[393]	GETTABLE 	8 0 -9	; "document"
	578	[393]	SETTABLE 	7 -9 8	; "document" -
	579	[394]	GETTABLE 	8 0 -18	; "view"
	580	[394]	SETTABLE 	7 -18 8	; "view" -
	581	[395]	SETTABLE 	7 -21 0	; "ui" -
	582	[392]	CALL     	5 3 0
	583	[392]	CALL     	2 0 1
	584	[401]	SELF     	2 0 -80	; "handleEvent"
	585	[401]	GETUPVAL 	4 26	; Event
	586	[401]	SELF     	4 4 -19	; "new"
	587	[401]	LOADK    	6 -81	; "DocSettingsLoad"
	588	[401]	GETTABLE 	7 0 -7	; "doc_settings"
	589	[401]	GETTABLE 	8 0 -9	; "document"
	590	[401]	CALL     	4 5 0
	591	[401]	CALL     	2 0 1
	592	[403]	SELF     	2 0 -80	; "handleEvent"
	593	[403]	GETUPVAL 	4 26	; Event
	594	[403]	SELF     	4 4 -19	; "new"
	595	[403]	LOADK    	6 -82	; "ReadSettings"
	596	[403]	GETTABLE 	7 0 -7	; "doc_settings"
	597	[403]	CALL     	4 4 0
	598	[403]	CALL     	2 0 1
	599	[405]	GETGLOBAL	2 -71	; ipairs
	600	[405]	GETTABLE 	3 0 -4	; "postInitCallback"
	601	[405]	CALL     	2 2 4
	602	[405]	JMP      	2	; to 605
	603	[406]	MOVE     	7 6
	604	[406]	CALL     	7 1 1
	605	[405]	TFORLOOP 	2 2
	606	[406]	JMP      	-4	; to 603
	607	[408]	SETTABLE 	0 -4 -83	; "postInitCallback" nil
	608	[413]	GETTABLE 	2 0 -7	; "doc_settings"
	609	[413]	SELF     	2 2 -84	; "saveSetting"
	610	[413]	LOADK    	4 -85	; "doc_props"
	611	[413]	GETTABLE 	5 0 -9	; "document"
	612	[413]	SELF     	5 5 -86	; "getProps"
	613	[413]	CALL     	5 2 0
	614	[413]	CALL     	2 0 1
	615	[418]	SELF     	2 0 -80	; "handleEvent"
	616	[418]	GETUPVAL 	4 26	; Event
	617	[418]	SELF     	4 4 -19	; "new"
	618	[418]	LOADK    	6 -87	; "ReaderReady"
	619	[418]	GETTABLE 	7 0 -7	; "doc_settings"
	620	[418]	CALL     	4 4 0
	621	[418]	CALL     	2 0 1
	622	[420]	GETGLOBAL	2 -71	; ipairs
	623	[420]	GETTABLE 	3 0 -5	; "postReaderCallback"
	624	[420]	CALL     	2 2 4
	625	[420]	JMP      	2	; to 628
	626	[421]	MOVE     	7 6
	627	[421]	CALL     	7 1 1
	628	[420]	TFORLOOP 	2 2
	629	[421]	JMP      	-4	; to 626
	630	[423]	SETTABLE 	0 -5 -83	; "postReaderCallback" nil
	631	[429]	RETURN   	0 1

function <./frontend/apps/reader/readerui.lua:281,291> (23 instructions, 92 bytes at 0x7fc5a14088e0)
0 params, 6 slots, 2 upvalues, 0 locals, 8 constants, 0 functions
	1	[282]	GETUPVAL 	0 0	; self
	2	[282]	GETTABLE 	0 0 -1	; "document"
	3	[282]	SELF     	0 0 -2	; "loadDocument"
	4	[282]	CALL     	0 2 2
	5	[282]	TEST     	0 0 1
	6	[282]	JMP      	3	; to 10
	7	[283]	GETUPVAL 	0 0	; self
	8	[283]	SELF     	0 0 -3	; "dealWithLoadDocumentFailure"
	9	[283]	CALL     	0 2 1
	10	[288]	GETUPVAL 	0 0	; self
	11	[288]	SELF     	0 0 -4	; "handleEvent"
	12	[288]	GETUPVAL 	2 1	; Event
	13	[288]	SELF     	2 2 -5	; "new"
	14	[288]	LOADK    	4 -6	; "PreRenderDocument"
	15	[288]	GETUPVAL 	5 0	; self
	16	[288]	GETTABLE 	5 5 -7	; "doc_settings"
	17	[288]	CALL     	2 4 0
	18	[288]	CALL     	0 0 1
	19	[290]	GETUPVAL 	0 0	; self
	20	[290]	GETTABLE 	0 0 -1	; "document"
	21	[290]	SELF     	0 0 -8	; "render"
	22	[290]	CALL     	0 2 1
	23	[291]	RETURN   	0 1

function <./frontend/apps/reader/readerui.lua:431,440> (21 instructions, 84 bytes at 0x7fc5a1409970)
1 param, 7 slots, 0 upvalues, 4 locals, 8 constants, 0 functions
	1	[432]	GETGLOBAL	1 -1	; require
	2	[432]	LOADK    	2 -2	; "ui/quickstart"
	3	[432]	CALL     	1 2 2
	4	[433]	LOADNIL  	2 2
	5	[434]	GETGLOBAL	3 -3	; G_reader_settings
	6	[434]	SELF     	3 3 -4	; "readSetting"
	7	[434]	LOADK    	5 -5	; "lastfile"
	8	[434]	CALL     	3 3 2
	9	[436]	TEST     	3 0 0
	10	[436]	JMP      	7	; to 18
	11	[436]	GETTABLE 	4 1 -6	; "quickstart_filename"
	12	[436]	EQ       	1 3 4
	13	[436]	JMP      	4	; to 18
	14	[437]	SELF     	4 3 -7	; "match"
	15	[437]	LOADK    	6 -8	; "(.*)/"
	16	[437]	CALL     	4 3 2
	17	[437]	MOVE     	2 4
	18	[439]	MOVE     	4 2
	19	[439]	MOVE     	5 3
	20	[439]	RETURN   	4 3
	21	[440]	RETURN   	0 1

function <./frontend/apps/reader/readerui.lua:442,457> (35 instructions, 140 bytes at 0x7fc5a140a310)
2 params, 9 slots, 1 upvalue, 5 locals, 9 constants, 0 functions
	1	[443]	GETGLOBAL	2 -1	; require
	2	[443]	LOADK    	3 -2	; "apps/filemanager/filemanager"
	3	[443]	CALL     	2 2 2
	4	[445]	LOADNIL  	3 4
	5	[446]	TEST     	1 0 0
	6	[446]	JMP      	11	; to 18
	7	[447]	GETUPVAL 	5 0	; util
	8	[447]	GETTABLE 	5 5 -3	; "splitFilePathName"
	9	[447]	MOVE     	6 1
	10	[447]	CALL     	5 2 3
	11	[447]	MOVE     	4 6
	12	[447]	MOVE     	3 5
	13	[448]	SELF     	5 3 -4	; "match"
	14	[448]	LOADK    	7 -5	; "(.*)/"
	15	[448]	CALL     	5 3 2
	16	[448]	MOVE     	3 5
	17	[448]	JMP      	4	; to 22
	18	[450]	SELF     	5 0 -6	; "getLastDirFile"
	19	[450]	CALL     	5 2 3
	20	[450]	MOVE     	4 6
	21	[450]	MOVE     	3 5
	22	[452]	GETTABLE 	5 2 -7	; "instance"
	23	[452]	TEST     	5 0 0
	24	[452]	JMP      	6	; to 31
	25	[453]	GETTABLE 	5 2 -7	; "instance"
	26	[453]	SELF     	5 5 -8	; "reinit"
	27	[453]	MOVE     	7 3
	28	[453]	MOVE     	8 4
	29	[453]	CALL     	5 4 1
	30	[453]	JMP      	4	; to 35
	31	[455]	SELF     	5 2 -9	; "showFiles"
	32	[455]	MOVE     	7 3
	33	[455]	MOVE     	8 4
	34	[455]	CALL     	5 4 1
	35	[457]	RETURN   	0 1

function <./frontend/apps/reader/readerui.lua:459,500> (136 instructions, 544 bytes at 0x7fc5a140a910)
3 params, 14 slots, 10 upvalues, 5 locals, 32 constants, 2 functions
	1	[460]	GETUPVAL 	3 0	; logger
	2	[460]	GETTABLE 	3 3 -1	; "dbg"
	3	[460]	LOADK    	4 -2	; "show reader ui"
	4	[460]	CALL     	3 2 1
	5	[462]	GETUPVAL 	3 1	; lfs
	6	[462]	GETTABLE 	3 3 -3	; "attributes"
	7	[462]	MOVE     	4 1
	8	[462]	LOADK    	5 -4	; "mode"
	9	[462]	CALL     	3 3 2
	10	[462]	EQ       	1 3 -5	; - "file"
	11	[462]	JMP      	18	; to 30
	12	[463]	GETUPVAL 	3 2	; UIManager
	13	[463]	SELF     	3 3 -6	; "show"
	14	[463]	GETUPVAL 	5 3	; InfoMessage
	15	[463]	SELF     	5 5 -7	; "new"
	16	[463]	NEWTABLE 	7 0 1
	17	[464]	GETUPVAL 	8 4	; T
	18	[464]	GETUPVAL 	9 5	; _
	19	[464]	LOADK    	10 -9	; "File '%1' does not exist."
	20	[464]	CALL     	9 2 2
	21	[464]	GETUPVAL 	10 6	; BD
	22	[464]	GETTABLE 	10 10 -10	; "filepath"
	23	[464]	MOVE     	11 1
	24	[464]	CALL     	10 2 0
	25	[464]	CALL     	8 0 2
	26	[464]	SETTABLE 	7 -8 8	; "text" -
	27	[463]	CALL     	5 3 0
	28	[463]	CALL     	3 0 1
	29	[466]	RETURN   	0 1
	30	[469]	GETUPVAL 	3 7	; DocumentRegistry
	31	[469]	SELF     	3 3 -11	; "hasProvider"
	32	[469]	MOVE     	5 1
	33	[469]	CALL     	3 3 2
	34	[469]	TEST     	3 0 1
	35	[469]	JMP      	23	; to 59
	36	[469]	EQ       	0 2 -12	; - nil
	37	[469]	JMP      	21	; to 59
	38	[470]	GETUPVAL 	3 2	; UIManager
	39	[470]	SELF     	3 3 -6	; "show"
	40	[470]	GETUPVAL 	5 3	; InfoMessage
	41	[470]	SELF     	5 5 -7	; "new"
	42	[470]	NEWTABLE 	7 0 1
	43	[471]	GETUPVAL 	8 4	; T
	44	[471]	GETUPVAL 	9 5	; _
	45	[471]	LOADK    	10 -13	; "File '%1' is not supported."
	46	[471]	CALL     	9 2 2
	47	[471]	GETUPVAL 	10 6	; BD
	48	[471]	GETTABLE 	10 10 -10	; "filepath"
	49	[471]	MOVE     	11 1
	50	[471]	CALL     	10 2 0
	51	[471]	CALL     	8 0 2
	52	[471]	SETTABLE 	7 -8 8	; "text" -
	53	[470]	CALL     	5 3 0
	54	[470]	CALL     	3 0 1
	55	[473]	SELF     	3 0 -14	; "showFileManager"
	56	[473]	MOVE     	5 1
	57	[473]	CALL     	3 3 1
	58	[474]	RETURN   	0 1
	59	[478]	TEST     	2 0 1
	60	[478]	JMP      	5	; to 66
	61	[478]	GETUPVAL 	3 7	; DocumentRegistry
	62	[478]	SELF     	3 3 -15	; "getProvider"
	63	[478]	MOVE     	5 1
	64	[478]	CALL     	3 3 2
	65	[478]	MOVE     	2 3
	66	[479]	GETTABLE 	3 2 -16	; "provider"
	67	[479]	TEST     	3 0 0
	68	[479]	JMP      	67	; to 136
	69	[480]	GETUPVAL 	3 8	; DocSettings
	70	[480]	SELF     	3 3 -17	; "open"
	71	[480]	MOVE     	5 1
	72	[480]	CALL     	3 3 2
	73	[481]	SELF     	4 3 -18	; "readSetting"
	74	[481]	LOADK    	6 -19	; "bookmarks"
	75	[481]	CALL     	4 3 2
	76	[481]	TEST     	4 0 1
	77	[481]	JMP      	1	; to 79
	78	[481]	NEWTABLE 	4 0 0
	79	[482]	LEN      	5 4
	80	[482]	LE       	0 -20 5	; 1 -
	81	[482]	JMP      	49	; to 131
	82	[483]	GETTABLE 	5 2 -16	; "provider"
	83	[483]	EQ       	0 5 -21	; - "crengine"
	84	[483]	JMP      	6	; to 91
	85	[483]	GETGLOBAL	5 -22	; type
	86	[483]	GETTABLE 	6 4 -20	; 1
	87	[483]	GETTABLE 	6 6 -23	; "page"
	88	[483]	CALL     	5 2 2
	89	[483]	EQ       	1 5 -24	; - "number"
	90	[483]	JMP      	9	; to 100
	91	[484]	GETTABLE 	5 2 -16	; "provider"
	92	[484]	EQ       	0 5 -25	; - "mupdf"
	93	[484]	JMP      	37	; to 131
	94	[484]	GETGLOBAL	5 -22	; type
	95	[484]	GETTABLE 	6 4 -20	; 1
	96	[484]	GETTABLE 	6 6 -23	; "page"
	97	[484]	CALL     	5 2 2
	98	[484]	EQ       	0 5 -26	; - "string"
	99	[484]	JMP      	31	; to 131
	100	[485]	GETUPVAL 	5 2	; UIManager
	101	[485]	SELF     	5 5 -6	; "show"
	102	[485]	GETUPVAL 	7 9	; ConfirmBox
	103	[485]	SELF     	7 7 -7	; "new"
	104	[485]	NEWTABLE 	9 0 4
	105	[486]	GETUPVAL 	10 4	; T
	106	[486]	GETUPVAL 	11 5	; _
	107	[486]	LOADK    	12 -27	; "The document '%1' with bookmarks or highlights was previously opened with a different engine. To prevent issues, bookmarks need to be deleted before continuing."
	108	[486]	CALL     	11 2 2
	109	[487]	GETUPVAL 	12 6	; BD
	110	[487]	GETTABLE 	12 12 -10	; "filepath"
	111	[487]	MOVE     	13 1
	112	[487]	CALL     	12 2 0
	113	[486]	CALL     	10 0 2
	114	[487]	SETTABLE 	9 -8 10	; "text" -
	115	[488]	GETUPVAL 	10 5	; _
	116	[488]	LOADK    	11 -29	; "Delete"
	117	[488]	CALL     	10 2 2
	118	[488]	SETTABLE 	9 -28 10	; "ok_text" -
	119	[493]	CLOSURE  	10 0	; 0x7fc5a140b5b0
	120	[493]	MOVE     	0 3
	121	[493]	MOVE     	0 0
	122	[493]	MOVE     	0 1
	123	[493]	MOVE     	0 2
	124	[493]	SETTABLE 	9 -30 10	; "ok_callback" -
	125	[494]	CLOSURE  	10 1	; 0x7fc5a140b7b0
	126	[494]	MOVE     	0 0
	127	[494]	SETTABLE 	9 -31 10	; "cancel_callback" -
	128	[485]	CALL     	7 3 0
	129	[485]	CALL     	5 0 1
	130	[495]	JMP      	4	; to 135
	131	[497]	SELF     	5 0 -32	; "showReaderCoroutine"
	132	[497]	MOVE     	7 1
	133	[497]	MOVE     	8 2
	134	[497]	CALL     	5 4 1
	135	[498]	CLOSE    	3
	136	[500]	RETURN   	0 1

function <./frontend/apps/reader/readerui.lua:489,493> (13 instructions, 52 bytes at 0x7fc5a140b5b0)
0 params, 4 slots, 4 upvalues, 0 locals, 4 constants, 0 functions
	1	[490]	GETUPVAL 	0 0	; doc_settings
	2	[490]	SELF     	0 0 -1	; "delSetting"
	3	[490]	LOADK    	2 -2	; "bookmarks"
	4	[490]	CALL     	0 3 1
	5	[491]	GETUPVAL 	0 0	; doc_settings
	6	[491]	SELF     	0 0 -3	; "close"
	7	[491]	CALL     	0 2 1
	8	[492]	GETUPVAL 	0 1	; self
	9	[492]	SELF     	0 0 -4	; "showReaderCoroutine"
	10	[492]	GETUPVAL 	2 2	; file
	11	[492]	GETUPVAL 	3 3	; provider
	12	[492]	CALL     	0 4 1
	13	[493]	RETURN   	0 1

function <./frontend/apps/reader/readerui.lua:494,494> (4 instructions, 16 bytes at 0x7fc5a140b7b0)
0 params, 2 slots, 1 upvalue, 0 locals, 1 constant, 0 functions
	1	[494]	GETUPVAL 	0 0	; self
	2	[494]	SELF     	0 0 -1	; "showFileManager"
	3	[494]	CALL     	0 2 1
	4	[494]	RETURN   	0 1

function <./frontend/apps/reader/readerui.lua:502,524> (33 instructions, 132 bytes at 0x7fc5a140b0f0)
3 params, 12 slots, 6 upvalues, 3 locals, 9 constants, 1 function
	1	[503]	GETUPVAL 	3 0	; UIManager
	2	[503]	SELF     	3 3 -1	; "show"
	3	[503]	GETUPVAL 	5 1	; InfoMessage
	4	[503]	SELF     	5 5 -2	; "new"
	5	[503]	NEWTABLE 	7 0 2
	6	[504]	GETUPVAL 	8 2	; T
	7	[504]	GETUPVAL 	9 3	; _
	8	[504]	LOADK    	10 -4	; "Opening file '%1'."
	9	[504]	CALL     	9 2 2
	10	[504]	GETUPVAL 	10 4	; BD
	11	[504]	GETTABLE 	10 10 -5	; "filepath"
	12	[504]	MOVE     	11 1
	13	[504]	CALL     	10 2 0
	14	[504]	CALL     	8 0 2
	15	[504]	SETTABLE 	7 -3 8	; "text" -
	16	[505]	SETTABLE 	7 -6 -7	; "timeout" 0
	17	[503]	CALL     	5 3 0
	18	[503]	CALL     	3 0 1
	19	[508]	GETUPVAL 	3 0	; UIManager
	20	[508]	SELF     	3 3 -8	; "forceRePaint"
	21	[508]	CALL     	3 2 1
	22	[509]	GETUPVAL 	3 0	; UIManager
	23	[509]	SELF     	3 3 -9	; "nextTick"
	24	[523]	CLOSURE  	5 0	; 0x7fc5a140b2b0
	25	[523]	GETUPVAL 	0 5	; logger
	26	[523]	MOVE     	0 0
	27	[523]	MOVE     	0 1
	28	[523]	MOVE     	0 2
	29	[523]	GETUPVAL 	0 0	; UIManager
	30	[523]	GETUPVAL 	0 1	; InfoMessage
	31	[523]	GETUPVAL 	0 3	; _
	32	[509]	CALL     	3 3 1
	33	[524]	RETURN   	0 1

function <./frontend/apps/reader/readerui.lua:509,523> (49 instructions, 196 bytes at 0x7fc5a140b2b0)
0 params, 10 slots, 7 upvalues, 3 locals, 19 constants, 1 function
	1	[510]	GETUPVAL 	0 0	; logger
	2	[510]	GETTABLE 	0 0 -1	; "dbg"
	3	[510]	LOADK    	1 -2	; "creating coroutine for showing reader"
	4	[510]	CALL     	0 2 1
	5	[511]	GETGLOBAL	0 -3	; coroutine
	6	[511]	GETTABLE 	0 0 -4	; "create"
	7	[513]	CLOSURE  	1 0	; 0x7fc5a140be60
	8	[513]	GETUPVAL 	0 1	; self
	9	[513]	GETUPVAL 	0 2	; file
	10	[513]	GETUPVAL 	0 3	; provider
	11	[511]	CALL     	0 2 2
	12	[514]	GETGLOBAL	1 -3	; coroutine
	13	[514]	GETTABLE 	1 1 -5	; "resume"
	14	[514]	MOVE     	2 0
	15	[514]	CALL     	1 2 3
	16	[515]	EQ       	0 2 -6	; - nil
	17	[515]	JMP      	2	; to 20
	18	[515]	EQ       	0 1 -7	; - false
	19	[515]	JMP      	29	; to 49
	20	[516]	GETGLOBAL	3 -8	; io
	21	[516]	GETTABLE 	3 3 -9	; "stderr"
	22	[516]	SELF     	3 3 -10	; "write"
	23	[516]	LOADK    	5 -11	; "[!] doShowReader coroutine crashed:\n"
	24	[516]	CALL     	3 3 1
	25	[517]	GETGLOBAL	3 -8	; io
	26	[517]	GETTABLE 	3 3 -9	; "stderr"
	27	[517]	SELF     	3 3 -10	; "write"
	28	[517]	GETGLOBAL	5 -12	; debug
	29	[517]	GETTABLE 	5 5 -13	; "traceback"
	30	[517]	MOVE     	6 0
	31	[517]	MOVE     	7 2
	32	[517]	LOADK    	8 -14	; 1
	33	[517]	CALL     	5 4 0
	34	[517]	CALL     	3 0 1
	35	[518]	GETUPVAL 	3 4	; UIManager
	36	[518]	SELF     	3 3 -15	; "show"
	37	[518]	GETUPVAL 	5 5	; InfoMessage
	38	[518]	SELF     	5 5 -16	; "new"
	39	[518]	NEWTABLE 	7 0 1
	40	[519]	GETUPVAL 	8 6	; _
	41	[519]	LOADK    	9 -18	; "No reader engine for this file or invalid file."
	42	[519]	CALL     	8 2 2
	43	[519]	SETTABLE 	7 -17 8	; "text" -
	44	[518]	CALL     	5 3 0
	45	[518]	CALL     	3 0 1
	46	[521]	GETUPVAL 	3 1	; self
	47	[521]	SELF     	3 3 -19	; "showFileManager"
	48	[521]	CALL     	3 2 1
	49	[523]	RETURN   	0 1

function <./frontend/apps/reader/readerui.lua:511,513> (6 instructions, 24 bytes at 0x7fc5a140be60)
0 params, 4 slots, 3 upvalues, 0 locals, 1 constant, 0 functions
	1	[512]	GETUPVAL 	0 0	; self
	2	[512]	SELF     	0 0 -1	; "doShowReader"
	3	[512]	GETUPVAL 	2 1	; file
	4	[512]	GETUPVAL 	3 2	; provider
	5	[512]	CALL     	0 4 1
	6	[513]	RETURN   	0 1

function <./frontend/apps/reader/readerui.lua:527,575> (112 instructions, 448 bytes at 0x7fc5a140b3b0)
3 params, 11 slots, 9 upvalues, 10 locals, 31 constants, 0 functions
	1	[528]	GETUPVAL 	3 0	; logger
	2	[528]	GETTABLE 	3 3 -1	; "info"
	3	[528]	LOADK    	4 -2	; "opening file"
	4	[528]	MOVE     	5 1
	5	[528]	CALL     	3 3 1
	6	[530]	GETUPVAL 	3 1	; _running_instance
	7	[530]	TEST     	3 0 0
	8	[530]	JMP      	3	; to 12
	9	[531]	GETUPVAL 	3 1	; _running_instance
	10	[531]	SELF     	3 3 -3	; "onClose"
	11	[531]	CALL     	3 2 1
	12	[533]	GETUPVAL 	3 2	; DocumentRegistry
	13	[533]	SELF     	3 3 -4	; "openDocument"
	14	[533]	MOVE     	5 1
	15	[533]	MOVE     	6 2
	16	[533]	CALL     	3 4 2
	17	[534]	TEST     	3 0 1
	18	[534]	JMP      	14	; to 33
	19	[535]	GETUPVAL 	4 3	; UIManager
	20	[535]	SELF     	4 4 -5	; "show"
	21	[535]	GETUPVAL 	6 4	; InfoMessage
	22	[535]	SELF     	6 6 -6	; "new"
	23	[535]	NEWTABLE 	8 0 1
	24	[536]	GETUPVAL 	9 5	; _
	25	[536]	LOADK    	10 -8	; "No reader engine for this file or invalid file."
	26	[536]	CALL     	9 2 2
	27	[536]	SETTABLE 	8 -7 9	; "text" -
	28	[535]	CALL     	6 3 0
	29	[535]	CALL     	4 0 1
	30	[538]	SELF     	4 0 -9	; "showFileManager"
	31	[538]	CALL     	4 2 1
	32	[539]	RETURN   	0 1
	33	[541]	GETTABLE 	4 3 -10	; "is_locked"
	34	[541]	TEST     	4 0 0
	35	[541]	JMP      	27	; to 63
	36	[542]	GETUPVAL 	4 0	; logger
	37	[542]	GETTABLE 	4 4 -1	; "info"
	38	[542]	LOADK    	5 -11	; "document is locked"
	39	[542]	CALL     	4 2 1
	40	[543]	GETGLOBAL	4 -13	; coroutine
	41	[543]	GETTABLE 	4 4 -14	; "running"
	42	[543]	CALL     	4 1 2
	43	[543]	TEST     	4 0 1
	44	[543]	JMP      	1	; to 46
	45	[543]	GETTABLE 	4 0 -12	; "_coroutine"
	46	[543]	SETTABLE 	0 -12 4	; "_coroutine" -
	47	[544]	SELF     	4 0 -15	; "unlockDocumentWithPassword"
	48	[544]	MOVE     	6 3
	49	[544]	CALL     	4 3 1
	50	[545]	GETGLOBAL	4 -13	; coroutine
	51	[545]	GETTABLE 	4 4 -14	; "running"
	52	[545]	CALL     	4 1 2
	53	[545]	TEST     	4 0 0
	54	[545]	JMP      	8	; to 63
	55	[546]	GETGLOBAL	4 -13	; coroutine
	56	[546]	GETTABLE 	4 4 -16	; "yield"
	57	[546]	CALL     	4 1 2
	58	[547]	TEST     	4 0 1
	59	[547]	JMP      	3	; to 63
	60	[548]	SELF     	5 0 -9	; "showFileManager"
	61	[548]	CALL     	5 2 1
	62	[549]	RETURN   	0 1
	63	[553]	GETGLOBAL	4 -17	; require
	64	[553]	LOADK    	5 -18	; "readhistory"
	65	[553]	CALL     	4 2 2
	66	[553]	SELF     	4 4 -19	; "addItem"
	67	[553]	MOVE     	6 1
	68	[553]	CALL     	4 3 1
	69	[554]	GETUPVAL 	4 6	; ReaderUI
	70	[554]	SELF     	4 4 -6	; "new"
	71	[554]	NEWTABLE 	6 0 3
	72	[555]	GETUPVAL 	7 7	; Screen
	73	[555]	SELF     	7 7 -21	; "getSize"
	74	[555]	CALL     	7 2 2
	75	[555]	SETTABLE 	6 -20 7	; "dimen" -
	76	[556]	SETTABLE 	6 -22 -23	; "covers_fullscreen" true
	77	[557]	SETTABLE 	6 -24 3	; "document" -
	78	[554]	CALL     	4 3 2
	79	[560]	GETTABLE 	5 4 -24	; "document"
	80	[560]	SELF     	5 5 -25	; "getProps"
	81	[560]	CALL     	5 2 2
	82	[560]	GETTABLE 	5 5 -26	; "title"
	83	[562]	EQ       	1 5 -27	; - ""
	84	[562]	JMP      	5	; to 90
	85	[563]	GETUPVAL 	6 7	; Screen
	86	[563]	SELF     	6 6 -28	; "setWindowTitle"
	87	[563]	MOVE     	8 5
	88	[563]	CALL     	6 3 1
	89	[563]	JMP      	8	; to 98
	90	[565]	GETUPVAL 	6 8	; util
	91	[565]	GETTABLE 	6 6 -29	; "splitFilePathName"
	92	[565]	MOVE     	7 1
	93	[565]	CALL     	6 2 3
	94	[566]	GETUPVAL 	8 7	; Screen
	95	[566]	SELF     	8 8 -28	; "setWindowTitle"
	96	[566]	MOVE     	10 7
	97	[566]	CALL     	8 3 1
	98	[569]	GETUPVAL 	6 3	; UIManager
	99	[569]	SELF     	6 6 -5	; "show"
	100	[569]	MOVE     	8 4
	101	[569]	CALL     	6 3 1
	102	[570]	SETUPVAL 	4 1	; _running_instance
	103	[571]	GETGLOBAL	6 -17	; require
	104	[571]	LOADK    	7 -30	; "apps/filemanager/filemanager"
	105	[571]	CALL     	6 2 2
	106	[572]	GETTABLE 	7 6 -31	; "instance"
	107	[572]	TEST     	7 0 0
	108	[572]	JMP      	3	; to 112
	109	[573]	GETTABLE 	7 6 -31	; "instance"
	110	[573]	SELF     	7 7 -3	; "onClose"
	111	[573]	CALL     	7 2 1
	112	[575]	RETURN   	0 1

function <./frontend/apps/reader/readerui.lua:577,579> (3 instructions, 12 bytes at 0x7fc5a140d430)
1 param, 2 slots, 1 upvalue, 1 local, 0 constants, 0 functions
	1	[578]	GETUPVAL 	1 0	; _running_instance
	2	[578]	RETURN   	1 2
	3	[579]	RETURN   	0 1

function <./frontend/apps/reader/readerui.lua:581,615> (53 instructions, 212 bytes at 0x7fc5a140d6e0)
3 params, 12 slots, 4 upvalues, 3 locals, 18 constants, 2 functions
	1	[582]	GETUPVAL 	3 0	; logger
	2	[582]	GETTABLE 	3 3 -1	; "dbg"
	3	[582]	LOADK    	4 -2	; "show input password dialog"
	4	[582]	CALL     	3 2 1
	5	[583]	GETUPVAL 	3 1	; InputDialog
	6	[583]	SELF     	3 3 -4	; "new"
	7	[583]	NEWTABLE 	5 0 3
	8	[584]	TEST     	2 0 0
	9	[584]	JMP      	5	; to 15
	10	[584]	GETUPVAL 	6 2	; _
	11	[584]	LOADK    	7 -6	; "Password is incorrect, try again?"
	12	[584]	CALL     	6 2 2
	13	[585]	TEST     	6 0 1
	14	[585]	JMP      	3	; to 18
	15	[585]	GETUPVAL 	6 2	; _
	16	[585]	LOADK    	7 -7	; "Input document password"
	17	[585]	CALL     	6 2 2
	18	[585]	SETTABLE 	5 -5 6	; "title" -
	19	[586]	NEWTABLE 	6 1 0
	20	[586]	NEWTABLE 	7 2 0
	21	[587]	NEWTABLE 	8 0 3
	22	[589]	GETUPVAL 	9 2	; _
	23	[589]	LOADK    	10 -10	; "Cancel"
	24	[589]	CALL     	9 2 2
	25	[589]	SETTABLE 	8 -9 9	; "text" -
	26	[590]	SETTABLE 	8 -11 -12	; "enabled" true
	27	[594]	CLOSURE  	9 0	; 0x7fc5a140d7c0
	28	[594]	MOVE     	0 0
	29	[594]	SETTABLE 	8 -13 9	; "callback" -
	30	[595]	NEWTABLE 	9 0 3
	31	[597]	GETUPVAL 	10 2	; _
	32	[597]	LOADK    	11 -14	; "OK"
	33	[597]	CALL     	10 2 2
	34	[597]	SETTABLE 	9 -9 10	; "text" -
	35	[598]	SETTABLE 	9 -11 -12	; "enabled" true
	36	[607]	CLOSURE  	10 1	; 0x7fc5a140d900
	37	[607]	MOVE     	0 0
	38	[607]	MOVE     	0 1
	39	[607]	SETTABLE 	9 -13 10	; "callback" -
	40	[609]	SETLIST  	7 2 1	; 1
	41	[610]	SETLIST  	6 1 1	; 1
	42	[610]	SETTABLE 	5 -8 6	; "buttons" -
	43	[611]	SETTABLE 	5 -15 -16	; "text_type" "password"
	44	[583]	CALL     	3 3 2
	45	[612]	SETTABLE 	0 -3 3	; "password_dialog" -
	46	[613]	GETUPVAL 	3 3	; UIManager
	47	[613]	SELF     	3 3 -17	; "show"
	48	[613]	GETTABLE 	5 0 -3	; "password_dialog"
	49	[613]	CALL     	3 3 1
	50	[614]	GETTABLE 	3 0 -3	; "password_dialog"
	51	[614]	SELF     	3 3 -18	; "onShowKeyboard"
	52	[614]	CALL     	3 2 1
	53	[615]	RETURN   	0 1

function <./frontend/apps/reader/readerui.lua:591,594> (9 instructions, 36 bytes at 0x7fc5a140d7c0)
0 params, 2 slots, 1 upvalue, 0 locals, 4 constants, 0 functions
	1	[592]	GETUPVAL 	0 0	; self
	2	[592]	SELF     	0 0 -1	; "closeDialog"
	3	[592]	CALL     	0 2 1
	4	[593]	GETGLOBAL	0 -2	; coroutine
	5	[593]	GETTABLE 	0 0 -3	; "resume"
	6	[593]	GETUPVAL 	1 0	; self
	7	[593]	GETTABLE 	1 1 -4	; "_coroutine"
	8	[593]	CALL     	0 2 1
	9	[594]	RETURN   	0 1

function <./frontend/apps/reader/readerui.lua:599,607> (22 instructions, 88 bytes at 0x7fc5a140d900)
0 params, 5 slots, 2 upvalues, 1 local, 6 constants, 0 functions
	1	[600]	GETUPVAL 	0 0	; self
	2	[600]	SELF     	0 0 -1	; "onVerifyPassword"
	3	[600]	GETUPVAL 	2 1	; document
	4	[600]	CALL     	0 3 2
	5	[601]	GETUPVAL 	1 0	; self
	6	[601]	SELF     	1 1 -2	; "closeDialog"
	7	[601]	CALL     	1 2 1
	8	[602]	TEST     	0 0 0
	9	[602]	JMP      	7	; to 17
	10	[603]	GETGLOBAL	1 -3	; coroutine
	11	[603]	GETTABLE 	1 1 -4	; "resume"
	12	[603]	GETUPVAL 	2 0	; self
	13	[603]	GETTABLE 	2 2 -5	; "_coroutine"
	14	[603]	MOVE     	3 0
	15	[603]	CALL     	1 3 1
	16	[603]	JMP      	5	; to 22
	17	[605]	GETUPVAL 	1 0	; self
	18	[605]	SELF     	1 1 -6	; "unlockDocumentWithPassword"
	19	[605]	GETUPVAL 	3 1	; document
	20	[605]	LOADBOOL 	4 1 0
	21	[605]	CALL     	1 4 1
	22	[607]	RETURN   	0 1

function <./frontend/apps/reader/readerui.lua:617,620> (8 instructions, 32 bytes at 0x7fc5a140d980)
2 params, 6 slots, 0 upvalues, 3 locals, 3 constants, 0 functions
	1	[618]	GETTABLE 	2 0 -1	; "password_dialog"
	2	[618]	SELF     	2 2 -2	; "getInputText"
	3	[618]	CALL     	2 2 2
	4	[619]	SELF     	3 1 -3	; "unlock"
	5	[619]	MOVE     	5 2
	6	[619]	TAILCALL 	3 3 0
	7	[619]	RETURN   	3 0
	8	[620]	RETURN   	0 1

function <./frontend/apps/reader/readerui.lua:622,625> (8 instructions, 32 bytes at 0x7fc5a140e750)
1 param, 4 slots, 1 upvalue, 1 local, 3 constants, 0 functions
	1	[623]	GETTABLE 	1 0 -1	; "password_dialog"
	2	[623]	SELF     	1 1 -2	; "onClose"
	3	[623]	CALL     	1 2 1
	4	[624]	GETUPVAL 	1 0	; UIManager
	5	[624]	SELF     	1 1 -3	; "close"
	6	[624]	GETTABLE 	3 0 -1	; "password_dialog"
	7	[624]	CALL     	1 3 1
	8	[625]	RETURN   	0 1

function <./frontend/apps/reader/readerui.lua:627,630> (5 instructions, 20 bytes at 0x7fc5a140ebb0)
2 params, 5 slots, 0 upvalues, 2 locals, 2 constants, 0 functions
	1	[628]	SETTABLE 	0 -1 1	; "dimen" -
	2	[629]	SELF     	2 0 -2	; "updateTouchZonesOnScreenResize"
	3	[629]	MOVE     	4 1
	4	[629]	CALL     	2 3 1
	5	[630]	RETURN   	0 1

function <./frontend/apps/reader/readerui.lua:632,636> (13 instructions, 52 bytes at 0x7fc5a140eed0)
1 param, 6 slots, 1 upvalue, 1 local, 6 constants, 0 functions
	1	[633]	SELF     	1 0 -1	; "handleEvent"
	2	[633]	GETUPVAL 	3 0	; Event
	3	[633]	SELF     	3 3 -2	; "new"
	4	[633]	LOADK    	5 -3	; "SaveSettings"
	5	[633]	CALL     	3 3 0
	6	[633]	CALL     	1 0 1
	7	[634]	GETTABLE 	1 0 -4	; "doc_settings"
	8	[634]	SELF     	1 1 -5	; "flush"
	9	[634]	CALL     	1 2 1
	10	[635]	GETGLOBAL	1 -6	; G_reader_settings
	11	[635]	SELF     	1 1 -5	; "flush"
	12	[635]	CALL     	1 2 1
	13	[636]	RETURN   	0 1

function <./frontend/apps/reader/readerui.lua:638,640> (3 instructions, 12 bytes at 0x7fc5a140f230)
1 param, 3 slots, 0 upvalues, 1 local, 1 constant, 0 functions
	1	[639]	SELF     	1 0 -1	; "saveSettings"
	2	[639]	CALL     	1 2 1
	3	[640]	RETURN   	0 1

function <./frontend/apps/reader/readerui.lua:642,645> (5 instructions, 20 bytes at 0x7fc5a140f740)
1 param, 3 slots, 0 upvalues, 1 local, 3 constants, 0 functions
	1	[643]	GETTABLE 	1 0 -1	; "document"
	2	[643]	SELF     	1 1 -2	; "close"
	3	[643]	CALL     	1 2 1
	4	[644]	SETTABLE 	0 -1 -3	; "document" nil
	5	[645]	RETURN   	0 1

function <./frontend/apps/reader/readerui.lua:647,673> (57 instructions, 228 bytes at 0x7fc5a140d3b0)
1 param, 9 slots, 4 upvalues, 2 locals, 21 constants, 2 functions
	1	[648]	SELF     	1 0 -1	; "handleEvent"
	2	[648]	GETUPVAL 	3 0	; Event
	3	[648]	SELF     	3 3 -2	; "new"
	4	[648]	LOADK    	5 -3	; "CloseDocument"
	5	[648]	CALL     	3 3 0
	6	[648]	CALL     	1 0 1
	7	[649]	GETTABLE 	1 0 -4	; "document"
	8	[649]	SELF     	1 1 -5	; "isEdited"
	9	[649]	CALL     	1 2 2
	10	[649]	TEST     	1 0 0
	11	[649]	JMP      	43	; to 55
	12	[650]	GETGLOBAL	1 -6	; G_reader_settings
	13	[650]	SELF     	1 1 -7	; "readSetting"
	14	[650]	LOADK    	3 -8	; "save_document"
	15	[650]	CALL     	1 3 2
	16	[651]	EQ       	0 1 -9	; - "always"
	17	[651]	JMP      	3	; to 21
	18	[652]	SELF     	2 0 -10	; "closeDocument"
	19	[652]	CALL     	2 2 1
	20	[652]	JMP      	36	; to 57
	21	[653]	EQ       	0 1 -11	; - "disable"
	22	[653]	JMP      	6	; to 29
	23	[654]	GETTABLE 	2 0 -4	; "document"
	24	[654]	SELF     	2 2 -12	; "discardChange"
	25	[654]	CALL     	2 2 1
	26	[655]	SELF     	2 0 -10	; "closeDocument"
	27	[655]	CALL     	2 2 1
	28	[655]	JMP      	28	; to 57
	29	[657]	GETUPVAL 	2 1	; UIManager
	30	[657]	SELF     	2 2 -13	; "show"
	31	[657]	GETUPVAL 	4 2	; ConfirmBox
	32	[657]	SELF     	4 4 -2	; "new"
	33	[657]	NEWTABLE 	6 0 5
	34	[658]	GETUPVAL 	7 3	; _
	35	[658]	LOADK    	8 -15	; "Do you want to save this document?"
	36	[658]	CALL     	7 2 2
	37	[658]	SETTABLE 	6 -14 7	; "text" -
	38	[659]	GETUPVAL 	7 3	; _
	39	[659]	LOADK    	8 -17	; "Save"
	40	[659]	CALL     	7 2 2
	41	[659]	SETTABLE 	6 -16 7	; "ok_text" -
	42	[660]	GETUPVAL 	7 3	; _
	43	[660]	LOADK    	8 -19	; "Don't save"
	44	[660]	CALL     	7 2 2
	45	[660]	SETTABLE 	6 -18 7	; "cancel_text" -
	46	[663]	CLOSURE  	7 0	; 0x7fc5a140f9a0
	47	[663]	MOVE     	0 0
	48	[663]	SETTABLE 	6 -20 7	; "ok_callback" -
	49	[667]	CLOSURE  	7 1	; 0x7fc5a140f6a0
	50	[667]	MOVE     	0 0
	51	[667]	SETTABLE 	6 -21 7	; "cancel_callback" -
	52	[657]	CALL     	4 3 0
	53	[657]	CALL     	2 0 1
	54	[669]	JMP      	2	; to 57
	55	[671]	SELF     	1 0 -10	; "closeDocument"
	56	[671]	CALL     	1 2 1
	57	[673]	RETURN   	0 1

function <./frontend/apps/reader/readerui.lua:661,663> (4 instructions, 16 bytes at 0x7fc5a140f9a0)
0 params, 2 slots, 1 upvalue, 0 locals, 1 constant, 0 functions
	1	[662]	GETUPVAL 	0 0	; self
	2	[662]	SELF     	0 0 -1	; "closeDocument"
	3	[662]	CALL     	0 2 1
	4	[663]	RETURN   	0 1

function <./frontend/apps/reader/readerui.lua:664,667> (8 instructions, 32 bytes at 0x7fc5a140f6a0)
0 params, 2 slots, 1 upvalue, 0 locals, 3 constants, 0 functions
	1	[665]	GETUPVAL 	0 0	; self
	2	[665]	GETTABLE 	0 0 -1	; "document"
	3	[665]	SELF     	0 0 -2	; "discardChange"
	4	[665]	CALL     	0 2 1
	5	[666]	GETUPVAL 	0 0	; self
	6	[666]	SELF     	0 0 -3	; "closeDocument"
	7	[666]	CALL     	0 2 1
	8	[667]	RETURN   	0 1

function <./frontend/apps/reader/readerui.lua:675,695> (37 instructions, 148 bytes at 0x7fc5a140c2c0)
2 params, 6 slots, 4 upvalues, 2 locals, 11 constants, 0 functions
	1	[676]	GETUPVAL 	2 0	; logger
	2	[676]	GETTABLE 	2 2 -1	; "dbg"
	3	[676]	LOADK    	3 -2	; "closing reader"
	4	[676]	CALL     	2 2 1
	5	[677]	EQ       	0 1 -3	; - nil
	6	[677]	JMP      	1	; to 8
	7	[678]	LOADBOOL 	1 1 0
	8	[682]	GETTABLE 	2 0 -4	; "dialog"
	9	[682]	EQ       	1 2 0
	10	[682]	JMP      	2	; to 13
	11	[683]	SELF     	2 0 -5	; "saveSettings"
	12	[683]	CALL     	2 2 1
	13	[685]	GETTABLE 	2 0 -6	; "document"
	14	[685]	EQ       	1 2 -3	; - nil
	15	[685]	JMP      	6	; to 22
	16	[686]	GETUPVAL 	2 0	; logger
	17	[686]	GETTABLE 	2 2 -1	; "dbg"
	18	[686]	LOADK    	3 -7	; "closing document"
	19	[686]	CALL     	2 2 1
	20	[687]	SELF     	2 0 -8	; "notifyCloseDocument"
	21	[687]	CALL     	2 2 1
	22	[689]	GETUPVAL 	2 1	; UIManager
	23	[689]	SELF     	2 2 -9	; "close"
	24	[689]	GETTABLE 	4 0 -4	; "dialog"
	25	[689]	TESTSET  	5 1 0
	26	[689]	JMP      	1	; to 28
	27	[689]	LOADK    	5 -10	; "full"
	28	[689]	CALL     	2 4 1
	29	[691]	GETUPVAL 	2 2	; Cache
	30	[691]	SELF     	2 2 -11	; "serialize"
	31	[691]	CALL     	2 2 1
	32	[692]	GETUPVAL 	2 3	; _running_instance
	33	[692]	EQ       	0 2 0
	34	[692]	JMP      	2	; to 37
	35	[693]	LOADNIL  	2 2
	36	[693]	SETUPVAL 	2 3	; _running_instance
	37	[695]	RETURN   	0 1

function <./frontend/apps/reader/readerui.lua:697,721> (38 instructions, 152 bytes at 0x7fc5a140ddb0)
1 param, 9 slots, 4 upvalues, 2 locals, 16 constants, 1 function
	1	[706]	GETGLOBAL	1 -1	; require
	2	[706]	LOADK    	2 -2	; "readhistory"
	3	[706]	CALL     	1 2 2
	4	[706]	SELF     	1 1 -3	; "removeItemByPath"
	5	[706]	GETTABLE 	3 0 -4	; "document"
	6	[706]	GETTABLE 	3 3 -5	; "file"
	7	[706]	CALL     	1 3 1
	8	[708]	GETGLOBAL	1 -6	; coroutine
	9	[708]	GETTABLE 	1 1 -7	; "running"
	10	[708]	CALL     	1 1 2
	11	[709]	GETGLOBAL	2 -6	; coroutine
	12	[709]	TEST     	2 0 0
	13	[709]	JMP      	21	; to 35
	14	[710]	GETUPVAL 	2 0	; logger
	15	[710]	GETTABLE 	2 2 -8	; "warn"
	16	[710]	LOADK    	3 -9	; "crengine failed recognizing or parsing this file: unsupported or invalid document"
	17	[710]	CALL     	2 2 1
	18	[711]	GETUPVAL 	2 1	; UIManager
	19	[711]	SELF     	2 2 -10	; "show"
	20	[711]	GETUPVAL 	4 2	; InfoMessage
	21	[711]	SELF     	4 4 -11	; "new"
	22	[711]	NEWTABLE 	6 0 2
	23	[712]	GETUPVAL 	7 3	; _
	24	[712]	LOADK    	8 -13	; "Failed recognizing or parsing this file: unsupported or invalid document.\nKOReader will exit now."
	25	[712]	CALL     	7 2 2
	26	[712]	SETTABLE 	6 -12 7	; "text" -
	27	[715]	CLOSURE  	7 0	; 0x7fc5a14095f0
	28	[715]	MOVE     	0 1
	29	[715]	SETTABLE 	6 -14 7	; "dismiss_callback" -
	30	[711]	CALL     	4 3 0
	31	[711]	CALL     	2 0 1
	32	[717]	GETGLOBAL	2 -6	; coroutine
	33	[717]	GETTABLE 	2 2 -15	; "yield"
	34	[717]	CALL     	2 1 1
	35	[720]	GETGLOBAL	2 -16	; error
	36	[720]	LOADK    	3 -9	; "crengine failed recognizing or parsing this file: unsupported or invalid document"
	37	[720]	CALL     	2 2 1
	38	[721]	RETURN   	0 1

function <./frontend/apps/reader/readerui.lua:713,715> (6 instructions, 24 bytes at 0x7fc5a14095f0)
0 params, 3 slots, 1 upvalue, 0 locals, 2 constants, 0 functions
	1	[714]	GETGLOBAL	0 -1	; coroutine
	2	[714]	GETTABLE 	0 0 -2	; "resume"
	3	[714]	GETUPVAL 	1 0	; _coroutine
	4	[714]	LOADBOOL 	2 0 0
	5	[714]	CALL     	0 3 1
	6	[715]	RETURN   	0 1

function <./frontend/apps/reader/readerui.lua:723,727> (7 instructions, 28 bytes at 0x7fc5a140fc90)
1 param, 3 slots, 0 upvalues, 1 local, 2 constants, 0 functions
	1	[724]	SELF     	1 0 -1	; "onClose"
	2	[724]	CALL     	1 2 1
	3	[725]	SELF     	1 0 -2	; "showFileManager"
	4	[725]	CALL     	1 2 1
	5	[726]	LOADBOOL 	1 1 0
	6	[726]	RETURN   	1 2
	7	[727]	RETURN   	0 1

function <./frontend/apps/reader/readerui.lua:729,741> (35 instructions, 140 bytes at 0x7fc5a140b980)
2 params, 9 slots, 1 upvalue, 4 locals, 11 constants, 0 functions
	1	[730]	GETTABLE 	2 0 -1	; "document"
	2	[730]	GETTABLE 	2 2 -2	; "file"
	3	[731]	GETGLOBAL	3 -3	; getmetatable
	4	[731]	GETTABLE 	4 0 -1	; "document"
	5	[731]	CALL     	3 2 2
	6	[731]	GETTABLE 	3 3 -4	; "__index"
	7	[732]	SELF     	4 0 -5	; "handleEvent"
	8	[732]	GETUPVAL 	6 0	; Event
	9	[732]	SELF     	6 6 -6	; "new"
	10	[732]	LOADK    	8 -7	; "CloseReaderMenu"
	11	[732]	CALL     	6 3 0
	12	[732]	CALL     	4 0 1
	13	[733]	SELF     	4 0 -5	; "handleEvent"
	14	[733]	GETUPVAL 	6 0	; Event
	15	[733]	SELF     	6 6 -6	; "new"
	16	[733]	LOADK    	8 -8	; "CloseConfigMenu"
	17	[733]	CALL     	6 3 0
	18	[733]	CALL     	4 0 1
	19	[734]	GETTABLE 	4 0 -9	; "highlight"
	20	[734]	SELF     	4 4 -10	; "onClose"
	21	[734]	CALL     	4 2 1
	22	[735]	SELF     	4 0 -10	; "onClose"
	23	[735]	LOADBOOL 	6 0 0
	24	[735]	CALL     	4 3 1
	25	[736]	TEST     	1 0 0
	26	[736]	JMP      	4	; to 31
	27	[738]	MOVE     	4 1
	28	[738]	MOVE     	5 2
	29	[738]	MOVE     	6 3
	30	[738]	CALL     	4 3 1
	31	[740]	SELF     	4 0 -11	; "showReader"
	32	[740]	MOVE     	6 2
	33	[740]	MOVE     	7 3
	34	[740]	CALL     	4 4 1
	35	[741]	RETURN   	0 1

function <./frontend/apps/reader/readerui.lua:743,750> (25 instructions, 100 bytes at 0x7fc5a140f470)
2 params, 7 slots, 1 upvalue, 2 locals, 7 constants, 0 functions
	1	[744]	TEST     	1 0 1
	2	[744]	JMP      	1	; to 4
	3	[744]	RETURN   	0 1
	4	[745]	SELF     	2 0 -1	; "handleEvent"
	5	[745]	GETUPVAL 	4 0	; Event
	6	[745]	SELF     	4 4 -2	; "new"
	7	[745]	LOADK    	6 -3	; "CloseReaderMenu"
	8	[745]	CALL     	4 3 0
	9	[745]	CALL     	2 0 1
	10	[746]	SELF     	2 0 -1	; "handleEvent"
	11	[746]	GETUPVAL 	4 0	; Event
	12	[746]	SELF     	4 4 -2	; "new"
	13	[746]	LOADK    	6 -4	; "CloseConfigMenu"
	14	[746]	CALL     	4 3 0
	15	[746]	CALL     	2 0 1
	16	[747]	GETTABLE 	2 0 -5	; "highlight"
	17	[747]	SELF     	2 2 -6	; "onClose"
	18	[747]	CALL     	2 2 1
	19	[748]	SELF     	2 0 -6	; "onClose"
	20	[748]	LOADBOOL 	4 0 0
	21	[748]	CALL     	2 3 1
	22	[749]	SELF     	2 0 -7	; "showReader"
	23	[749]	MOVE     	4 1
	24	[749]	CALL     	2 3 1
	25	[750]	RETURN   	0 1

function <./frontend/apps/reader/readerui.lua:752,758> (14 instructions, 56 bytes at 0x7fc5a14103c0)
1 param, 3 slots, 0 upvalues, 1 local, 6 constants, 0 functions
	1	[753]	GETTABLE 	1 0 -1	; "document"
	2	[753]	GETTABLE 	1 1 -2	; "info"
	3	[753]	GETTABLE 	1 1 -3	; "has_pages"
	4	[753]	TEST     	1 0 0
	5	[753]	JMP      	4	; to 10
	6	[754]	GETTABLE 	1 0 -4	; "paging"
	7	[754]	GETTABLE 	1 1 -5	; "current_page"
	8	[754]	RETURN   	1 2
	9	[754]	JMP      	4	; to 14
	10	[756]	GETTABLE 	1 0 -1	; "document"
	11	[756]	SELF     	1 1 -6	; "getCurrentPage"
	12	[756]	TAILCALL 	1 2 0
	13	[756]	RETURN   	1 0
	14	[758]	RETURN   	0 1
