-- BYTECODE -- readerfooter.lua:101-101
0001    KSTR     0   0      ; ""
0002    RET1     0   2

-- BYTECODE -- readerfooter.lua:102-115
0001    TGETS    1   0   0  ; "settings"
0002    TGETS    1   1   1  ; "item_prefix"
0003    IST          1
0004    JMP      2 => 0006
0005    KSTR     1   2      ; "icons"
0006 => UGET     2   0      ; symbol_prefix
0007    TGETV    2   2   1
0008    TGETS    2   2   3  ; "frontlight"
0009    UGET     3   1      ; Device
0010    MOV      4   3
0011    TGETS    3   3   4  ; "getPowerDevice"
0012    CALL     3   2   2
0013    MOV      5   3
0014    TGETS    4   3   5  ; "isFrontlightOn"
0015    CALL     4   2   2
0016    ISF          4
0017    JMP      5 => 0050
0018    UGET     4   1      ; Device
0019    MOV      5   4
0020    TGETS    4   4   6  ; "isCervantes"
0021    CALL     4   2   2
0022    IST          4
0023    JMP      5 => 0030
0024    UGET     4   1      ; Device
0025    MOV      5   4
0026    TGETS    4   4   7  ; "isKobo"
0027    CALL     4   2   2
0028    ISF          4
0029    JMP      5 => 0040
0030 => MOV      4   2
0031    KSTR     5   8      ; " %d%%"
0032    CAT      4   4   5
0033    MOV      5   4
0034    TGETS    4   4   9  ; "format"
0035    MOV      7   3
0036    TGETS    6   3  10  ; "frontlightIntensity"
0037    CALL     6   0   2
0038    CALLMT   4   1
0039    JMP      4 => 0056
0040 => MOV      4   2
0041    KSTR     5  11      ; " %d"
0042    CAT      4   4   5
0043    MOV      5   4
0044    TGETS    4   4   9  ; "format"
0045    MOV      7   3
0046    TGETS    6   3  10  ; "frontlightIntensity"
0047    CALL     6   0   2
0048    CALLMT   4   1
0049    JMP      4 => 0056
0050 => UGET     4   2      ; T
0051    UGET     5   3      ; _
0052    KSTR     6  12      ; "%1 Off"
0053    CALL     5   2   2
0054    MOV      6   2
0055    CALLT    4   3
0056 => RET0     0   1

-- BYTECODE -- readerfooter.lua:116-154
0001    TGETS    1   0   0  ; "settings"
0002    TGETS    1   1   1  ; "item_prefix"
0003    IST          1
0004    JMP      2 => 0006
0005    KSTR     1   2      ; "icons"
0006 => UGET     2   0      ; symbol_prefix
0007    TGETV    2   2   1
0008    TGETS    2   2   3  ; "battery"
0009    UGET     3   1      ; Device
0010    MOV      4   3
0011    TGETS    3   3   4  ; "getPowerDevice"
0012    CALL     3   2   2
0013    MOV      5   3
0014    TGETS    4   3   5  ; "getCapacity"
0015    CALL     4   2   2
0016    ISNES    1   2      ; "icons"
0017    JMP      5 => 0085
0018    MOV      6   3
0019    TGETS    5   3   6  ; "isCharging"
0020    CALL     5   2   2
0021    ISF          5
0022    JMP      6 => 0025
0023    KSTR     2   7      ; ""
0024    JMP      5 => 0076
0025 => KSHORT   5 100
0026    ISGT     5   4
0027    JMP      5 => 0030
0028    KSTR     2   8      ; ""
0029    JMP      5 => 0076
0030 => KSHORT   5  90
0031    ISGT     5   4
0032    JMP      5 => 0035
0033    KSTR     2   9      ; ""
0034    JMP      5 => 0076
0035 => KSHORT   5  80
0036    ISGT     5   4
0037    JMP      5 => 0040
0038    KSTR     2  10      ; ""
0039    JMP      5 => 0076
0040 => KSHORT   5  70
0041    ISGT     5   4
0042    JMP      5 => 0045
0043    KSTR     2  11      ; ""
0044    JMP      5 => 0076
0045 => KSHORT   5  60
0046    ISGT     5   4
0047    JMP      5 => 0050
0048    KSTR     2  12      ; ""
0049    JMP      5 => 0076
0050 => KSHORT   5  50
0051    ISGT     5   4
0052    JMP      5 => 0055
0053    KSTR     2  13      ; ""
0054    JMP      5 => 0076
0055 => KSHORT   5  40
0056    ISGT     5   4
0057    JMP      5 => 0060
0058    KSTR     2  14      ; ""
0059    JMP      5 => 0076
0060 => KSHORT   5  30
0061    ISGT     5   4
0062    JMP      5 => 0065
0063    KSTR     2  15      ; ""
0064    JMP      5 => 0076
0065 => KSHORT   5  20
0066    ISGT     5   4
0067    JMP      5 => 0070
0068    KSTR     2  16      ; ""
0069    JMP      5 => 0076
0070 => KSHORT   5  10
0071    ISGT     5   4
0072    JMP      5 => 0075
0073    KSTR     2  17      ; ""
0074    JMP      5 => 0076
0075 => KSTR     2  18      ; ""
0076 => UGET     5   2      ; BD
0077    TGETS    5   5  19  ; "wrap"
0078    MOV      6   2
0079    CALL     5   2   2
0080    MOV      6   4
0081    KSTR     7  20      ; "%"
0082    CAT      5   5   7
0083    RET1     5   2
0084    JMP      5 => 0102
0085 => UGET     5   2      ; BD
0086    TGETS    5   5  19  ; "wrap"
0087    MOV      6   2
0088    CALL     5   2   2
0089    KSTR     6  21      ; " "
0090    MOV      8   3
0091    TGETS    7   3   6  ; "isCharging"
0092    CALL     7   2   2
0093    ISF          7
0094    JMP      8 => 0097
0095    KSTR     7  22      ; "+"
0096    JMP      8 => 0098
0097 => KSTR     7  23      ; ""
0098 => MOV      8   4
0099    KSTR     9  20      ; "%"
0100    CAT      5   5   9
0101    RET1     5   2
0102 => RET0     0   1

-- BYTECODE -- readerfooter.lua:155-176
0001    TGETS    1   0   0  ; "settings"
0002    TGETS    1   1   1  ; "item_prefix"
0003    IST          1
0004    JMP      2 => 0006
0005    KSTR     1   2      ; "icons"
0006 => UGET     2   0      ; symbol_prefix
0007    TGETV    2   2   1
0008    TGETS    2   2   3  ; "time"
0009    KPRI     3   0
0010    TGETS    4   0   0  ; "settings"
0011    TGETS    4   4   4  ; "time_format"
0012    ISNES    4   5      ; "12"
0013    JMP      4 => 0036
0014    GGET     4   6      ; "os"
0015    TGETS    4   4   7  ; "date"
0016    KSTR     5   8      ; "%p"
0017    CALL     4   2   2
0018    ISNES    4   9      ; "AM"
0019    JMP      4 => 0028
0020    GGET     4   6      ; "os"
0021    TGETS    4   4   7  ; "date"
0022    UGET     5   1      ; _
0023    KSTR     6  10      ; "%I:%M AM"
0024    CALL     5   0   2
0025    CALLM    4   2   0
0026    MOV      3   4
0027    JMP      4 => 0043
0028 => GGET     4   6      ; "os"
0029    TGETS    4   4   7  ; "date"
0030    UGET     5   1      ; _
0031    KSTR     6  11      ; "%I:%M PM"
0032    CALL     5   0   2
0033    CALLM    4   2   0
0034    MOV      3   4
0035    JMP      4 => 0043
0036 => GGET     4   6      ; "os"
0037    TGETS    4   4   7  ; "date"
0038    UGET     5   1      ; _
0039    KSTR     6  12      ; "%H:%M"
0040    CALL     5   0   2
0041    CALLM    4   2   0
0042    MOV      3   4
0043 => IST          2
0044    JMP      4 => 0047
0045    RET1     3   2
0046    JMP      4 => 0052
0047 => MOV      4   2
0048    KSTR     5  13      ; " "
0049    MOV      6   3
0050    CAT      4   4   6
0051    RET1     4   2
0052 => RET0     0   1

-- BYTECODE -- readerfooter.lua:177-188
0001    TGETS    1   0   0  ; "pageno"
0002    ISF          1
0003    JMP      2 => 0038
0004    TGETS    1   0   1  ; "ui"
0005    TGETS    1   1   2  ; "pagemap"
0006    ISF          1
0007    JMP      2 => 0031
0008    TGETS    1   0   1  ; "ui"
0009    TGETS    1   1   2  ; "pagemap"
0010    MOV      2   1
0011    TGETS    1   1   3  ; "wantsPageLabels"
0012    CALL     1   2   2
0013    ISF          1
0014    JMP      2 => 0031
0015    KSTR     1   4      ; "%s / %s"
0016    MOV      2   1
0017    TGETS    1   1   5  ; "format"
0018    TGETS    3   0   1  ; "ui"
0019    TGETS    3   3   2  ; "pagemap"
0020    MOV      4   3
0021    TGETS    3   3   6  ; "getCurrentPageLabel"
0022    KPRI     5   2
0023    CALL     3   2   3
0024    TGETS    4   0   1  ; "ui"
0025    TGETS    4   4   2  ; "pagemap"
0026    MOV      5   4
0027    TGETS    4   4   7  ; "getLastPageLabel"
0028    KPRI     6   2
0029    CALL     4   0   3
0030    CALLMT   1   2
0031 => KSTR     1   8      ; "%d / %d"
0032    MOV      2   1
0033    TGETS    1   1   5  ; "format"
0034    TGETS    3   0   0  ; "pageno"
0035    TGETS    4   0   9  ; "pages"
0036    CALLT    1   4
0037    JMP      1 => 0047
0038 => TGETS    1   0  10  ; "position"
0039    ISF          1
0040    JMP      2 => 0047
0041    KSTR     1   8      ; "%d / %d"
0042    MOV      2   1
0043    TGETS    1   1   5  ; "format"
0044    TGETS    3   0  10  ; "position"
0045    TGETS    4   0  11  ; "doc_height"
0046    CALLT    1   4
0047 => RET0     0   1

-- BYTECODE -- readerfooter.lua:189-195
0001    TGETS    1   0   0  ; "settings"
0002    TGETS    1   1   1  ; "item_prefix"
0003    IST          1
0004    JMP      2 => 0006
0005    KSTR     1   2      ; "icons"
0006 => UGET     2   0      ; symbol_prefix
0007    TGETV    2   2   1
0008    TGETS    2   2   3  ; "pages_left"
0009    TGETS    3   0   4  ; "ui"
0010    TGETS    3   3   5  ; "toc"
0011    MOV      4   3
0012    TGETS    3   3   6  ; "getChapterPagesLeft"
0013    TGETS    5   0   7  ; "pageno"
0014    TGETS    6   0   8  ; "toc_level"
0015    CALL     3   2   4
0016    MOV      4   2
0017    KSTR     5   9      ; " "
0018    ISF          3
0019    JMP      6 => 0022
0020    ISTC     6   3
0021    JMP      6 => 0025
0022 => TGETS    6   0  10  ; "pages"
0023    TGETS    7   0   7  ; "pageno"
0024    SUBVV    6   6   7
0025 => CAT      4   4   6
0026    RET1     4   2

-- BYTECODE -- readerfooter.lua:196-207
0001    TGETS    1   0   0  ; "settings"
0002    TGETS    1   1   1  ; "item_prefix"
0003    IST          1
0004    JMP      2 => 0006
0005    KSTR     1   2      ; "icons"
0006 => UGET     2   0      ; symbol_prefix
0007    TGETV    2   2   1
0008    TGETS    2   2   3  ; "percentage"
0009    TGETS    3   0   0  ; "settings"
0010    TGETS    3   3   4  ; "progress_pct_format"
0011    IST          3
0012    JMP      4 => 0014
0013    KSTR     3   5      ; "0"
0014 => KPRI     4   0
0015    IST          2
0016    JMP      5 => 0022
0017    KSTR     5   6      ; "%."
0018    MOV      6   3
0019    KSTR     7   7      ; "f%%"
0020    CAT      4   5   7
0021    JMP      5 => 0027
0022 => MOV      5   2
0023    KSTR     6   8      ; " %."
0024    MOV      7   3
0025    KSTR     8   7      ; "f%%"
0026    CAT      4   5   8
0027 => MOV      6   4
0028    TGETS    5   4   9  ; "format"
0029    TGETS    7   0  10  ; "progress_bar"
0030    TGETS    7   7   3  ; "percentage"
0031    MULVN    7   7   0  ; 100
0032    CALLT    5   3

-- BYTECODE -- readerfooter.lua:208-213
0001    TGETS    1   0   0  ; "settings"
0002    TGETS    1   1   1  ; "item_prefix"
0003    IST          1
0004    JMP      2 => 0006
0005    KSTR     1   2      ; "icons"
0006 => UGET     2   0      ; symbol_prefix
0007    TGETV    2   2   1
0008    TGETS    2   2   3  ; "book_time_to_read"
0009    TGETS    3   0   4  ; "ui"
0010    MOV      4   3
0011    TGETS    3   3   5  ; "getCurrentPage"
0012    CALL     3   2   2
0013    MOV      5   0
0014    TGETS    4   0   6  ; "getDataFromStatistics"
0015    MOV      6   2
0016    KSTR     7   7      ; " "
0017    CAT      6   6   7
0018    TGETS    7   0   8  ; "pages"
0019    SUBVV    7   7   3
0020    CALLT    4   4

-- BYTECODE -- readerfooter.lua:214-221
0001    TGETS    1   0   0  ; "settings"
0002    TGETS    1   1   1  ; "item_prefix"
0003    IST          1
0004    JMP      2 => 0006
0005    KSTR     1   2      ; "icons"
0006 => UGET     2   0      ; symbol_prefix
0007    TGETV    2   2   1
0008    TGETS    2   2   3  ; "chapter_time_to_read"
0009    TGETS    3   0   4  ; "ui"
0010    TGETS    3   3   5  ; "toc"
0011    MOV      4   3
0012    TGETS    3   3   6  ; "getChapterPagesLeft"
0013    TGETS    5   0   7  ; "pageno"
0014    TGETS    6   0   8  ; "toc_level"
0015    CALL     3   2   4
0016    MOV      5   0
0017    TGETS    4   0   9  ; "getDataFromStatistics"
0018    MOV      6   2
0019    KSTR     7  10      ; " "
0020    CAT      6   6   7
0021    ISF          3
0022    JMP      7 => 0025
0023    ISTC     7   3
0024    JMP      7 => 0028
0025 => TGETS    7   0  11  ; "pages"
0026    TGETS    8   0   7  ; "pageno"
0027    SUBVV    7   7   8
0028 => CALLT    4   4

-- BYTECODE -- readerfooter.lua:222-235
0001    TGETS    1   0   0  ; "settings"
0002    TGETS    1   1   1  ; "item_prefix"
0003    IST          1
0004    JMP      2 => 0006
0005    KSTR     1   2      ; "icons"
0006 => UGET     2   0      ; symbol_prefix
0007    TGETV    2   2   1
0008    TGETS    2   2   3  ; "mem_usage"
0009    GGET     3   4      ; "io"
0010    TGETS    3   3   5  ; "open"
0011    KSTR     4   6      ; "/proc/self/statm"
0012    KSTR     5   7      ; "r"
0013    CALL     3   2   3
0014    ISF          3
0015    JMP      4 => 0044
0016    MOV      5   3
0017    TGETS    4   3   8  ; "read"
0018    KSTR     6   9      ; "*all"
0019    CALL     4   2   3
0020    MOV      6   3
0021    TGETS    5   3  10  ; "close"
0022    CALL     5   1   2
0023    MOV      6   4
0024    TGETS    5   4  11  ; "match"
0025    KSTR     7  12      ; "^%S+ (%S+) "
0026    CALL     5   2   3
0027    GGET     6  13      ; "math"
0028    TGETS    6   6  14  ; "floor"
0029    GGET     7  15      ; "tonumber"
0030    MOV      8   5
0031    CALL     7   2   2
0032    MULVN    7   7   0  ; 4096
0033    DIVVN    7   7   1  ; 1024
0034    DIVVN    7   7   1  ; 1024
0035    CALL     6   2   2
0036    MOV      5   6
0037    MOV      6   2
0038    KSTR     7  16      ; " %d"
0039    CAT      6   6   7
0040    MOV      7   6
0041    TGETS    6   6  17  ; "format"
0042    MOV      8   5
0043    CALLT    6   3
0044 => KSTR     4  18      ; ""
0045    RET1     4   2

-- BYTECODE -- readerfooter.lua:236-245
0001    TGETS    1   0   0  ; "settings"
0002    TGETS    1   1   1  ; "item_prefix"
0003    IST          1
0004    JMP      2 => 0006
0005    KSTR     1   2      ; "icons"
0006 => UGET     2   0      ; symbol_prefix
0007    TGETV    2   2   1
0008    TGETS    2   2   3  ; "wifi_status"
0009    GGET     3   4      ; "require"
0010    KSTR     4   5      ; "ui/network/manager"
0011    CALL     3   2   2
0012    MOV      5   3
0013    TGETS    4   3   6  ; "isWifiOn"
0014    CALL     4   2   2
0015    ISF          4
0016    JMP      5 => 0024
0017    UGET     4   1      ; T
0018    UGET     5   2      ; _
0019    KSTR     6   7      ; "%1 On"
0020    CALL     5   2   2
0021    MOV      6   2
0022    CALLT    4   3
0023    JMP      4 => 0030
0024 => UGET     4   1      ; T
0025    UGET     5   2      ; _
0026    KSTR     6   8      ; "%1 Off"
0027    CALL     5   2   2
0028    MOV      6   2
0029    CALLT    4   3
0030 => RET0     0   1

-- BYTECODE -- readerfooter.lua:246-264
0001    TGETS    1   0   0  ; "ui"
0002    TGETS    1   1   1  ; "document"
0003    MOV      2   1
0004    TGETS    1   1   2  ; "getProps"
0005    CALL     1   2   2
0006    ISF          1
0007    JMP      2 => 0051
0008    TGETS    2   1   3  ; "title"
0009    ISF          2
0010    JMP      3 => 0051
0011    UGET     2   0      ; TextWidget
0012    MOV      3   2
0013    TGETS    2   2   4  ; "new"
0014    TDUP     4   5
0015    TGETS    5   1   3  ; "title"
0016    TSETS    5   4   6  ; "text"
0017    TGETS    5   0   7  ; "_saved_screen_width"
0018    TGETS    6   0   8  ; "settings"
0019    TGETS    6   6   9  ; "book_title_max_width_pct"
0020    MULVV    5   5   6
0021    DIVVN    5   5   0  ; 100
0022    TSETS    5   4  10  ; "max_width"
0023    UGET     5   1      ; Font
0024    MOV      6   5
0025    TGETS    5   5  11  ; "getFace"
0026    TGETS    7   0  12  ; "text_font_face"
0027    TGETS    8   0   8  ; "settings"
0028    TGETS    8   8  13  ; "text_font_size"
0029    CALL     5   2   4
0030    TSETS    5   4  14  ; "face"
0031    TGETS    5   0   8  ; "settings"
0032    TGETS    5   5  15  ; "text_font_bold"
0033    TSETS    5   4  16  ; "bold"
0034    CALL     2   2   3
0035    MOV      4   2
0036    TGETS    3   2  17  ; "getFittedText"
0037    CALL     3   3   2
0038    MOV      6   2
0039    TGETS    5   2  18  ; "free"
0040    CALL     5   1   2
0041    ISF          4
0042    JMP      5 => 0046
0043    MOV      5   3
0044    KSTR     6  19      ; "…"
0045    CAT      3   5   6
0046 => UGET     5   2      ; BD
0047    TGETS    5   5  20  ; "auto"
0048    MOV      6   3
0049    CALLT    5   2
0050    JMP      2 => 0052
0051 => RET0     0   1
0052 => RET0     0   1

-- BYTECODE -- readerfooter.lua:265-283
0001    TGETS    1   0   0  ; "ui"
0002    TGETS    1   1   1  ; "toc"
0003    MOV      2   1
0004    TGETS    1   1   2  ; "getTocTitleByPage"
0005    TGETS    3   0   3  ; "pageno"
0006    CALL     1   2   3
0007    ISF          1
0008    JMP      2 => 0050
0009    ISEQS    1   4      ; ""
0010    JMP      2 => 0050
0011    UGET     2   0      ; TextWidget
0012    MOV      3   2
0013    TGETS    2   2   5  ; "new"
0014    TDUP     4   6
0015    TSETS    1   4   7  ; "text"
0016    TGETS    5   0   8  ; "_saved_screen_width"
0017    TGETS    6   0   9  ; "settings"
0018    TGETS    6   6  10  ; "book_chapter_max_width_pct"
0019    MULVV    5   5   6
0020    DIVVN    5   5   0  ; 100
0021    TSETS    5   4  11  ; "max_width"
0022    UGET     5   1      ; Font
0023    MOV      6   5
0024    TGETS    5   5  12  ; "getFace"
0025    TGETS    7   0  13  ; "text_font_face"
0026    TGETS    8   0   9  ; "settings"
0027    TGETS    8   8  14  ; "text_font_size"
0028    CALL     5   2   4
0029    TSETS    5   4  15  ; "face"
0030    TGETS    5   0   9  ; "settings"
0031    TGETS    5   5  16  ; "text_font_bold"
0032    TSETS    5   4  17  ; "bold"
0033    CALL     2   2   3
0034    MOV      4   2
0035    TGETS    3   2  18  ; "getFittedText"
0036    CALL     3   3   2
0037    MOV      6   2
0038    TGETS    5   2  19  ; "free"
0039    CALL     5   1   2
0040    ISF          4
0041    JMP      5 => 0045
0042    MOV      5   3
0043    KSTR     6  20      ; "…"
0044    CAT      3   5   6
0045 => UGET     5   2      ; BD
0046    TGETS    5   5  21  ; "auto"
0047    MOV      6   3
0048    CALLT    5   2
0049    JMP      2 => 0051
0050 => RET0     0   1
0051 => RET0     0   1

-- BYTECODE -- readerfooter.lua:303-449
0001    GGET     1   1      ; "G_reader_settings"
0002    MOV      2   1
0003    TGETS    1   1   2  ; "readSetting"
0004    KSTR     3   3      ; "footer"
0005    CALL     1   2   3
0006    IST          1
0007    JMP      2 => 0013
0008    TDUP     1   4
0009    UGET     2   0      ; DMINIBAR_TOC_MARKER_WIDTH
0010    TSETS    2   1   5  ; "toc_markers_width"
0011    UGET     2   1      ; DMINIBAR_FONT_SIZE
0012    TSETS    2   1   6  ; "text_font_size"
0013 => TSETS    1   0   0  ; "settings"
0014    TNEW     1   0
0015    KPRI     2   0
0016    KSHORT   3   0
0017    TSETS    3   0   7  ; "mode_nb"
0018    TNEW     3   0
0019    TSETS    3   0   8  ; "mode_index"
0020    UGET     3   2      ; Device
0021    MOV      4   3
0022    TGETS    3   3   9  ; "isAndroid"
0023    CALL     3   2   2
0024    IST          3
0025    JMP      3 => 0029
0026    UGET     3   3      ; MODE
0027    KPRI     4   0
0028    TSETS    4   3  10  ; "wifi_status"
0029 => UGET     3   2      ; Device
0030    MOV      4   3
0031    TGETS    3   3  11  ; "hasFrontlight"
0032    CALL     3   2   2
0033    IST          3
0034    JMP      3 => 0038
0035    UGET     3   3      ; MODE
0036    KPRI     4   0
0037    TSETS    4   3  12  ; "frontlight"
0038 => UGET     3   2      ; Device
0039    MOV      4   3
0040    TGETS    3   3  13  ; "isDesktop"
0041    CALL     3   2   2
0042    ISF          3
0043    JMP      4 => 0047
0044    UGET     3   3      ; MODE
0045    KPRI     4   0
0046    TSETS    4   3  14  ; "battery"
0047 => GGET     3  15      ; "pairs"
0048    UGET     4   3      ; MODE
0049    CALL     3   4   2
0050    ISNEXT   6 => 0052
0051 => TSETV    6   1   7
0052 => ITERN    6   3   3
0053    ITERL    6 => 0051
0054    KSHORT   3   0
0055    LEN      4   1
0056    KSHORT   5   1
0057    FORI     3 => 0068
0058 => TGETV    2   1   6
0059    ISF          2
0060    JMP      7 => 0067
0061    TGETS    7   0   8  ; "mode_index"
0062    TGETS    8   0   7  ; "mode_nb"
0063    TSETV    2   7   8
0064    TGETS    7   0   7  ; "mode_nb"
0065    ADDVN    7   7   0  ; 1
0066    TSETS    7   0   7  ; "mode_nb"
0067 => FORL     3 => 0058
0068 => TGETS    3   0   0  ; "settings"
0069    TGETS    3   3  16  ; "order"
0070    ISF          3
0071    JMP      4 => 0100
0072 => TGETS    3   0   0  ; "settings"
0073    TGETS    3   3  16  ; "order"
0074    LEN      3   3
0075    TGETS    4   0   8  ; "mode_index"
0076    LEN      4   4
0077    ISGE     3   4
0078    JMP      3 => 0094
0079    LOOP     3 => 0094
0080    TGETS    3   0   0  ; "settings"
0081    TGETS    3   3  16  ; "order"
0082    TGETS    4   0   0  ; "settings"
0083    TGETS    4   4  16  ; "order"
0084    LEN      4   4
0085    ADDVN    4   4   0  ; 1
0086    TGETS    5   0   8  ; "mode_index"
0087    TGETS    6   0   0  ; "settings"
0088    TGETS    6   6  16  ; "order"
0089    LEN      6   6
0090    ADDVN    6   6   0  ; 1
0091    TGETV    5   5   6
0092    TSETV    5   3   4
0093    JMP      3 => 0072
0094 => TGETS    3   0   0  ; "settings"
0095    TGETS    3   3  16  ; "order"
0096    TSETS    3   0   8  ; "mode_index"
0097    TGETS    3   0   8  ; "mode_index"
0098    LEN      3   3
0099    TSETS    3   0   7  ; "mode_nb"
0100 => TGETS    3   0   0  ; "settings"
0101    TGETS    3   3  17  ; "progress_margin_width"
0102    IST          3
0103    JMP      3 => 0111
0104    TGETS    3   0   0  ; "settings"
0105    UGET     4   4      ; Screen
0106    MOV      5   4
0107    TGETS    4   4  18  ; "scaleBySize"
0108    KSHORT   6  10
0109    CALL     4   2   3
0110    TSETS    4   3  17  ; "progress_margin_width"
0111 => TGETS    3   0   0  ; "settings"
0112    TGETS    3   3   5  ; "toc_markers_width"
0113    IST          3
0114    JMP      3 => 0118
0115    TGETS    3   0   0  ; "settings"
0116    UGET     4   0      ; DMINIBAR_TOC_MARKER_WIDTH
0117    TSETS    4   3   5  ; "toc_markers_width"
0118 => TGETS    3   0   0  ; "settings"
0119    TGETS    3   3  19  ; "progress_bar_min_width_pct"
0120    IST          3
0121    JMP      3 => 0125
0122    TGETS    3   0   0  ; "settings"
0123    KSHORT   4  20
0124    TSETS    4   3  19  ; "progress_bar_min_width_pct"
0125 => TGETS    3   0   0  ; "settings"
0126    TGETS    3   3  20  ; "book_title_max_width_pct"
0127    IST          3
0128    JMP      3 => 0132
0129    TGETS    3   0   0  ; "settings"
0130    KSHORT   4  30
0131    TSETS    4   3  20  ; "book_title_max_width_pct"
0132 => TGETS    3   0   0  ; "settings"
0133    TGETS    3   3  21  ; "book_chapter_max_width_pct"
0134    IST          3
0135    JMP      3 => 0139
0136    TGETS    3   0   0  ; "settings"
0137    KSHORT   4  30
0138    TSETS    4   3  21  ; "book_chapter_max_width_pct"
0139 => TNEW     3   0
0140    TSETS    3   0  22  ; "mode_list"
0141    KSHORT   3   0
0142    TGETS    4   0   8  ; "mode_index"
0143    LEN      4   4
0144    KSHORT   5   1
0145    FORI     3 => 0151
0146 => TGETS    7   0  22  ; "mode_list"
0147    TGETS    8   0   8  ; "mode_index"
0148    TGETV    8   8   6
0149    TSETV    6   7   8
0150    FORL     3 => 0146
0151 => TGETS    3   0   0  ; "settings"
0152    TGETS    3   3  23  ; "disabled"
0153    ISF          3
0154    JMP      4 => 0159
0155    MOV      4   0
0156    TGETS    3   0  24  ; "disableFooter"
0157    CALL     3   1   2
0158    RET0     0   1
0159 => TGETS    3   0  26  ; "view"
0160    TGETS    3   3  27  ; "state"
0161    TGETS    3   3  28  ; "page"
0162    TSETS    3   0  25  ; "pageno"
0163    KPRI     3   2
0164    TSETS    3   0  29  ; "has_no_mode"
0165    TGETS    3   0   0  ; "settings"
0166    TGETS    3   3  30  ; "reclaim_height"
0167    IST          3
0168    JMP      4 => 0170
0169    KPRI     3   1
0170 => TSETS    3   0  30  ; "reclaim_height"
0171    GGET     3  31      ; "ipairs"
0172    TGETS    4   0   8  ; "mode_index"
0173    CALL     3   4   2
0174    JMP      6 => 0182
0175 => TGETS    8   0   0  ; "settings"
0176    TGETV    8   8   7
0177    ISF          8
0178    JMP      9 => 0182
0179    KPRI     8   1
0180    TSETS    8   0  29  ; "has_no_mode"
0181    JMP      3 => 0184
0182 => ITERC    6   3   3
0183    ITERL    6 => 0175
0184 => TGETS    3   0   0  ; "settings"
0185    TGETS    3   3   6  ; "text_font_size"
0186    IST          3
0187    JMP      3 => 0191
0188    TGETS    3   0   0  ; "settings"
0189    UGET     4   1      ; DMINIBAR_FONT_SIZE
0190    TSETS    4   3   6  ; "text_font_size"
0191 => TGETS    3   0   0  ; "settings"
0192    TGETS    3   3  32  ; "text_font_bold"
0193    IST          3
0194    JMP      3 => 0198
0195    TGETS    3   0   0  ; "settings"
0196    KPRI     4   1
0197    TSETS    4   3  32  ; "text_font_bold"
0198 => UGET     3   5      ; TextWidget
0199    MOV      4   3
0200    TGETS    3   3  34  ; "new"
0201    TDUP     5  35
0202    UGET     6   6      ; Font
0203    MOV      7   6
0204    TGETS    6   6  36  ; "getFace"
0205    TGETS    8   0  37  ; "text_font_face"
0206    TGETS    9   0   0  ; "settings"
0207    TGETS    9   9   6  ; "text_font_size"
0208    CALL     6   2   4
0209    TSETS    6   5  38  ; "face"
0210    TGETS    6   0   0  ; "settings"
0211    TGETS    6   6  32  ; "text_font_bold"
0212    TSETS    6   5  39  ; "bold"
0213    CALL     3   2   3
0214    TSETS    3   0  33  ; "footer_text"
0215    KSHORT   3   0
0216    TSETS    3   0  40  ; "text_width"
0217    UGET     3   7      ; ProgressWidget
0218    MOV      4   3
0219    TGETS    3   3  34  ; "new"
0220    TDUP     5  42
0221    TGETS    6   0  43  ; "progress_percentage"
0222    TSETS    6   5  44  ; "percentage"
0223    UGET     6   4      ; Screen
0224    MOV      7   6
0225    TGETS    6   6  18  ; "scaleBySize"
0226    TGETS    8   0   0  ; "settings"
0227    TGETS    8   8   5  ; "toc_markers_width"
0228    CALL     6   2   3
0229    TSETS    6   5  45  ; "tick_width"
0230    CALL     3   2   3
0231    TSETS    3   0  41  ; "progress_bar"
0232    TGETS    3   0   0  ; "settings"
0233    TGETS    3   3  46  ; "progress_style_thin"
0234    ISF          3
0235    JMP      4 => 0242
0236    TGETS    3   0  41  ; "progress_bar"
0237    MOV      4   3
0238    TGETS    3   3  47  ; "updateStyle"
0239    KPRI     5   1
0240    KPRI     6   0
0241    CALL     3   1   4
0242 => UGET     3   8      ; RightContainer
0243    MOV      4   3
0244    TGETS    3   3  34  ; "new"
0245    TDUP     5  52
0246    UGET     6   9      ; Geom
0247    MOV      7   6
0248    TGETS    6   6  34  ; "new"
0249    TDUP     8  49
0250    TGETS    9   0  50  ; "height"
0251    TSETS    9   8  51  ; "h"
0252    CALL     6   2   3
0253    TSETS    6   5  53  ; "dimen"
0254    TGETS    6   0  33  ; "footer_text"
0255    TSETB    6   5   1
0256    CALL     3   2   3
0257    TSETS    3   0  48  ; "text_container"
0258    MOV      4   0
0259    TGETS    3   0  54  ; "updateFooterContainer"
0260    CALL     3   1   2
0261    GGET     3   1      ; "G_reader_settings"
0262    MOV      4   3
0263    TGETS    3   3   2  ; "readSetting"
0264    KSTR     5  56      ; "reader_footer_mode"
0265    CALL     3   2   3
0266    IST          3
0267    JMP      4 => 0269
0268    TGETS    3   0  55  ; "mode"
0269 => TSETS    3   0  55  ; "mode"
0270    TGETS    3   0  29  ; "has_no_mode"
0271    ISF          3
0272    JMP      4 => 0293
0273    TGETS    3   0   0  ; "settings"
0274    TGETS    3   3  57  ; "disable_progress_bar"
0275    ISF          3
0276    JMP      4 => 0293
0277    TGETS    3   0  22  ; "mode_list"
0278    TGETS    3   3  58  ; "off"
0279    TSETS    3   0  55  ; "mode"
0280    TGETS    3   0  26  ; "view"
0281    KPRI     4   1
0282    TSETS    4   3  59  ; "footer_visible"
0283    MOV      4   0
0284    TGETS    3   0  60  ; "resetLayout"
0285    CALL     3   1   2
0286    TGETS    3   0  61  ; "footer_container"
0287    TGETS    3   3  53  ; "dimen"
0288    KSHORT   4   0
0289    TSETS    4   3  51  ; "h"
0290    TGETS    3   0  33  ; "footer_text"
0291    KSHORT   4   0
0292    TSETS    4   3  50  ; "height"
0293 => TGETS    3   0   0  ; "settings"
0294    TGETS    3   3  62  ; "all_at_once"
0295    ISF          3
0296    JMP      4 => 0325
0297    TGETS    3   0  26  ; "view"
0298    TGETS    4   0  55  ; "mode"
0299    TGETS    5   0  22  ; "mode_list"
0300    TGETS    5   5  58  ; "off"
0301    ISNEV    4   5
0302    JMP      4 => 0305
0303    KPRI     4   1
0304    JMP      5 => 0306
0305 => KPRI     4   2
0306 => TSETS    4   3  59  ; "footer_visible"
0307    MOV      4   0
0308    TGETS    3   0  63  ; "updateFooterTextGenerator"
0309    CALL     3   1   2
0310    TGETS    3   0   0  ; "settings"
0311    TGETS    3   3  64  ; "progress_bar_position"
0312    ISF          3
0313    JMP      4 => 0328
0314    TGETS    3   0  29  ; "has_no_mode"
0315    ISF          3
0316    JMP      4 => 0328
0317    TGETS    3   0  61  ; "footer_container"
0318    TGETS    3   3  53  ; "dimen"
0319    KSHORT   4   0
0320    TSETS    4   3  51  ; "h"
0321    TGETS    3   0  33  ; "footer_text"
0322    KSHORT   4   0
0323    TSETS    4   3  50  ; "height"
0324    JMP      3 => 0328
0325 => MOV      4   0
0326    TGETS    3   0  65  ; "applyFooterMode"
0327    CALL     3   1   2
0328 => TGETS    3   0   0  ; "settings"
0329    TGETS    3   3  66  ; "auto_refresh_time"
0330    ISF          3
0331    JMP      4 => 0335
0332    MOV      4   0
0333    TGETS    3   0  67  ; "setupAutoRefreshTime"
0334    CALL     3   1   2
0335 => RET0     0   1

-- BYTECODE -- readerfooter.lua:451-523
0001    UGET     1   0      ; HorizontalSpan
0002    MOV      2   1
0003    TGETS    1   1   0  ; "new"
0004    TDUP     3   2
0005    TGETS    4   0   1  ; "horizontal_margin"
0006    TSETS    4   3   3  ; "width"
0007    CALL     1   2   3
0008    UGET     2   1      ; VerticalGroup
0009    MOV      3   2
0010    TGETS    2   2   0  ; "new"
0011    TNEW     4   0
0012    CALL     2   2   3
0013    TSETS    2   0   4  ; "vertical_frame"
0014    TGETS    2   0   5  ; "settings"
0015    TGETS    2   2   6  ; "bottom_horizontal_separator"
0016    ISF          2
0017    JMP      3 => 0052
0018    UGET     2   2      ; LineWidget
0019    MOV      3   2
0020    TGETS    2   2   0  ; "new"
0021    TDUP     4  12
0022    UGET     5   3      ; Geom
0023    MOV      6   5
0024    TGETS    5   5   0  ; "new"
0025    TDUP     7   8
0026    UGET     8   4      ; Size
0027    TGETS    8   8   9  ; "line"
0028    TGETS    8   8  10  ; "medium"
0029    TSETS    8   7  11  ; "h"
0030    CALL     5   2   3
0031    TSETS    5   4  13  ; "dimen"
0032    CALL     2   2   3
0033    TSETS    2   0   7  ; "separator_line"
0034    UGET     2   5      ; VerticalSpan
0035    MOV      3   2
0036    TGETS    2   2   0  ; "new"
0037    TDUP     4  15
0038    TGETS    5   0  14  ; "bottom_padding"
0039    MULVN    5   5   0  ; 2
0040    TSETS    5   4   3  ; "width"
0041    CALL     2   2   3
0042    GGET     3  16      ; "table"
0043    TGETS    3   3  17  ; "insert"
0044    TGETS    4   0   4  ; "vertical_frame"
0045    TGETS    5   0   7  ; "separator_line"
0046    CALL     3   1   3
0047    GGET     3  16      ; "table"
0048    TGETS    3   3  17  ; "insert"
0049    TGETS    4   0   4  ; "vertical_frame"
0050    MOV      5   2
0051    CALL     3   1   3
0052 => TGETS    2   0   5  ; "settings"
0053    TGETS    2   2  18  ; "progress_bar_position"
0054    ISF          2
0055    JMP      3 => 0071
0056    TGETS    2   0   5  ; "settings"
0057    TGETS    2   2  19  ; "disable_progress_bar"
0058    IST          2
0059    JMP      2 => 0071
0060    UGET     2   6      ; HorizontalGroup
0061    MOV      3   2
0062    TGETS    2   2   0  ; "new"
0063    TNEW     4   4
0064    TSETB    1   4   1
0065    TGETS    5   0  21  ; "text_container"
0066    TSETB    5   4   2
0067    TSETB    1   4   3
0068    CALL     2   2   3
0069    TSETS    2   0  20  ; "horizontal_group"
0070    JMP      2 => 0083
0071 => UGET     2   6      ; HorizontalGroup
0072    MOV      3   2
0073    TGETS    2   2   0  ; "new"
0074    TNEW     4   5
0075    TSETB    1   4   1
0076    TGETS    5   0  22  ; "progress_bar"
0077    TSETB    5   4   2
0078    TGETS    5   0  21  ; "text_container"
0079    TSETB    5   4   3
0080    TSETB    1   4   4
0081    CALL     2   2   3
0082    TSETS    2   0  20  ; "horizontal_group"
0083 => TGETS    2   0   5  ; "settings"
0084    TGETS    2   2  23  ; "align"
0085    ISNES    2  24      ; "left"
0086    JMP      2 => 0104
0087    UGET     2   7      ; LeftContainer
0088    MOV      3   2
0089    TGETS    2   2   0  ; "new"
0090    TDUP     4  28
0091    UGET     5   3      ; Geom
0092    MOV      6   5
0093    TGETS    5   5   0  ; "new"
0094    TDUP     7  26
0095    TGETS    8   0  27  ; "height"
0096    TSETS    8   7  11  ; "h"
0097    CALL     5   2   3
0098    TSETS    5   4  13  ; "dimen"
0099    TGETS    5   0  20  ; "horizontal_group"
0100    TSETB    5   4   1
0101    CALL     2   2   3
0102    TSETS    2   0  25  ; "footer_container"
0103    JMP      2 => 0141
0104 => TGETS    2   0   5  ; "settings"
0105    TGETS    2   2  23  ; "align"
0106    ISNES    2  29      ; "right"
0107    JMP      2 => 0125
0108    UGET     2   8      ; RightContainer
0109    MOV      3   2
0110    TGETS    2   2   0  ; "new"
0111    TDUP     4  31
0112    UGET     5   3      ; Geom
0113    MOV      6   5
0114    TGETS    5   5   0  ; "new"
0115    TDUP     7  30
0116    TGETS    8   0  27  ; "height"
0117    TSETS    8   7  11  ; "h"
0118    CALL     5   2   3
0119    TSETS    5   4  13  ; "dimen"
0120    TGETS    5   0  20  ; "horizontal_group"
0121    TSETB    5   4   1
0122    CALL     2   2   3
0123    TSETS    2   0  25  ; "footer_container"
0124    JMP      2 => 0141
0125 => UGET     2   9      ; CenterContainer
0126    MOV      3   2
0127    TGETS    2   2   0  ; "new"
0128    TDUP     4  33
0129    UGET     5   3      ; Geom
0130    MOV      6   5
0131    TGETS    5   5   0  ; "new"
0132    TDUP     7  32
0133    TGETS    8   0  27  ; "height"
0134    TSETS    8   7  11  ; "h"
0135    CALL     5   2   3
0136    TSETS    5   4  13  ; "dimen"
0137    TGETS    5   0  20  ; "horizontal_group"
0138    TSETB    5   4   1
0139    CALL     2   2   3
0140    TSETS    2   0  25  ; "footer_container"
0141 => UGET     2   5      ; VerticalSpan
0142    MOV      3   2
0143    TGETS    2   2   0  ; "new"
0144    TDUP     4  34
0145    TGETS    5   0  14  ; "bottom_padding"
0146    MULVN    5   5   0  ; 2
0147    TSETS    5   4   3  ; "width"
0148    CALL     2   2   3
0149    TGETS    3   0   5  ; "settings"
0150    TGETS    3   3  18  ; "progress_bar_position"
0151    ISNES    3  35      ; "above"
0152    JMP      3 => 0173
0153    TGETS    3   0   5  ; "settings"
0154    TGETS    3   3  19  ; "disable_progress_bar"
0155    IST          3
0156    JMP      3 => 0173
0157    GGET     3  16      ; "table"
0158    TGETS    3   3  17  ; "insert"
0159    TGETS    4   0   4  ; "vertical_frame"
0160    TGETS    5   0  22  ; "progress_bar"
0161    CALL     3   1   3
0162    GGET     3  16      ; "table"
0163    TGETS    3   3  17  ; "insert"
0164    TGETS    4   0   4  ; "vertical_frame"
0165    MOV      5   2
0166    CALL     3   1   3
0167    GGET     3  16      ; "table"
0168    TGETS    3   3  17  ; "insert"
0169    TGETS    4   0   4  ; "vertical_frame"
0170    TGETS    5   0  25  ; "footer_container"
0171    CALL     3   1   3
0172    JMP      3 => 0202
0173 => TGETS    3   0   5  ; "settings"
0174    TGETS    3   3  18  ; "progress_bar_position"
0175    ISNES    3  36      ; "below"
0176    JMP      3 => 0197
0177    TGETS    3   0   5  ; "settings"
0178    TGETS    3   3  19  ; "disable_progress_bar"
0179    IST          3
0180    JMP      3 => 0197
0181    GGET     3  16      ; "table"
0182    TGETS    3   3  17  ; "insert"
0183    TGETS    4   0   4  ; "vertical_frame"
0184    TGETS    5   0  25  ; "footer_container"
0185    CALL     3   1   3
0186    GGET     3  16      ; "table"
0187    TGETS    3   3  17  ; "insert"
0188    TGETS    4   0   4  ; "vertical_frame"
0189    MOV      5   2
0190    CALL     3   1   3
0191    GGET     3  16      ; "table"
0192    TGETS    3   3  17  ; "insert"
0193    TGETS    4   0   4  ; "vertical_frame"
0194    TGETS    5   0  22  ; "progress_bar"
0195    CALL     3   1   3
0196    JMP      3 => 0202
0197 => GGET     3  16      ; "table"
0198    TGETS    3   3  17  ; "insert"
0199    TGETS    4   0   4  ; "vertical_frame"
0200    TGETS    5   0  25  ; "footer_container"
0201    CALL     3   1   3
0202 => UGET     3  10      ; FrameContainer
0203    MOV      4   3
0204    TGETS    3   3   0  ; "new"
0205    TDUP     5  39
0206    TGETS    6   0   4  ; "vertical_frame"
0207    TSETB    6   5   1
0208    UGET     6  11      ; Blitbuffer
0209    TGETS    6   6  38  ; "COLOR_WHITE"
0210    TSETS    6   5  40  ; "background"
0211    TGETS    6   0  14  ; "bottom_padding"
0212    TSETS    6   5  41  ; "padding_bottom"
0213    CALL     3   2   3
0214    TSETS    3   0  37  ; "footer_content"
0215    UGET     3  12      ; BottomContainer
0216    MOV      4   3
0217    TGETS    3   3   0  ; "new"
0218    TDUP     5  43
0219    UGET     6   3      ; Geom
0220    MOV      7   6
0221    TGETS    6   6   0  ; "new"
0222    TNEW     8   0
0223    CALL     6   2   3
0224    TSETS    6   5  13  ; "dimen"
0225    TGETS    6   0  37  ; "footer_content"
0226    TSETB    6   5   1
0227    CALL     3   2   3
0228    TSETS    3   0  42  ; "footer_positioner"
0229    TGETS    3   0  42  ; "footer_positioner"
0230    TSETB    3   0   1
0231    RET0     0   1

-- BYTECODE -- readerfooter.lua:527-530
0001    UGET     0   0      ; self
0002    MOV      1   0
0003    TGETS    0   0   0  ; "updateFooter"
0004    KPRI     2   2
0005    CALL     0   1   3
0006    UGET     0   1      ; UIManager
0007    MOV      1   0
0008    TGETS    0   0   1  ; "scheduleIn"
0009    GGET     2   2      ; "tonumber"
0010    GGET     3   3      ; "os"
0011    TGETS    3   3   4  ; "date"
0012    KSTR     4   5      ; "%S"
0013    CALL     3   0   2
0014    CALLM    2   2   0
0015    SUBNV    2   2   0  ; 61
0016    UGET     3   0      ; self
0017    TGETS    3   3   6  ; "autoRefreshTime"
0018    CALL     0   1   4
0019    RET0     0   1

-- BYTECODE -- readerfooter.lua:532-534
0001    UGET     0   0      ; UIManager
0002    MOV      1   0
0003    TGETS    0   0   0  ; "unschedule"
0004    UGET     2   1      ; self
0005    TGETS    2   2   1  ; "autoRefreshTime"
0006    CALL     0   1   3
0007    RET0     0   1

-- BYTECODE -- readerfooter.lua:525-536
0001    TGETS    1   0   0  ; "autoRefreshTime"
0002    IST          1
0003    JMP      1 => 0006
0004    FNEW     1   1      ; readerfooter.lua:527
0005    TSETS    1   0   0  ; "autoRefreshTime"
0006 => FNEW     1   3      ; readerfooter.lua:532
0007    TSETS    1   0   2  ; "onCloseDocument"
0008    UGET     1   0      ; UIManager
0009    MOV      2   1
0010    TGETS    1   1   4  ; "scheduleIn"
0011    GGET     3   5      ; "tonumber"
0012    GGET     4   6      ; "os"
0013    TGETS    4   4   7  ; "date"
0014    KSTR     5   8      ; "%S"
0015    CALL     4   0   2
0016    CALLM    3   2   0
0017    SUBNV    3   3   0  ; 61
0018    TGETS    4   0   0  ; "autoRefreshTime"
0019    CALL     1   1   4
0020    UCLO     0 => 0021
0021 => RET0     0   1

-- BYTECODE -- readerfooter.lua:549-549
0001    UGET     1   0      ; self
0002    MOV      2   1
0003    TGETS    1   1   0  ; "onTapFooter"
0004    MOV      3   0
0005    CALLT    1   3

-- BYTECODE -- readerfooter.lua:562-562
0001    UGET     0   0      ; self
0002    MOV      1   0
0003    TGETS    0   0   0  ; "onHoldFooter"
0004    CALLT    0   2

-- BYTECODE -- readerfooter.lua:538-568
0001    UGET     1   0      ; Device
0002    MOV      2   1
0003    TGETS    1   1   0  ; "isTouchDevice"
0004    CALL     1   2   2
0005    IST          1
0006    JMP      1 => 0008
0007    UCLO     0 => 0040
0008 => TDUP     1   3
0009    GGET     2   1      ; "DTAP_ZONE_MINIBAR"
0010    TGETS    2   2   2  ; "x"
0011    TSETS    2   1   4  ; "ratio_x"
0012    GGET     2   1      ; "DTAP_ZONE_MINIBAR"
0013    TGETS    2   2   5  ; "y"
0014    TSETS    2   1   6  ; "ratio_y"
0015    GGET     2   1      ; "DTAP_ZONE_MINIBAR"
0016    TGETS    2   2   7  ; "w"
0017    TSETS    2   1   8  ; "ratio_w"
0018    GGET     2   1      ; "DTAP_ZONE_MINIBAR"
0019    TGETS    2   2   9  ; "h"
0020    TSETS    2   1  10  ; "ratio_h"
0021    TGETS    2   0  11  ; "ui"
0022    MOV      3   2
0023    TGETS    2   2  12  ; "registerTouchZones"
0024    TNEW     4   3
0025    TDUP     5  13
0026    TSETS    1   5  14  ; "screen_zone"
0027    FNEW     6  15      ; readerfooter.lua:549
0028    TSETS    6   5  16  ; "handler"
0029    TDUP     6  17
0030    TSETS    6   5  18  ; "overrides"
0031    TSETB    5   4   1
0032    TDUP     5  19
0033    TSETS    1   5  14  ; "screen_zone"
0034    FNEW     6  20      ; readerfooter.lua:562
0035    TSETS    6   5  16  ; "handler"
0036    TSETB    5   4   2
0037    CALL     2   1   3
0038    UCLO     0 => 0039
0039 => RET0     0   1
0040 => RET0     0   1

-- BYTECODE -- readerfooter.lua:571-604
0001    UGET     2   0      ; Screen
0002    MOV      3   2
0003    TGETS    2   2   0  ; "getWidth"
0004    CALL     2   2   2
0005    UGET     3   0      ; Screen
0006    MOV      4   3
0007    TGETS    3   3   1  ; "getHeight"
0008    CALL     3   2   2
0009    TGETS    4   0   2  ; "_saved_screen_width"
0010    ISNEV    2   4
0011    JMP      4 => 0018
0012    TGETS    4   0   3  ; "_saved_screen_height"
0013    ISNEV    3   4
0014    JMP      4 => 0018
0015    IST          1
0016    JMP      4 => 0018
0017    RET0     0   1
0018 => TGETS    4   0   4  ; "settings"
0019    TGETS    4   4   5  ; "disable_progress_bar"
0020    ISF          4
0021    JMP      5 => 0026
0022    TGETS    4   0   6  ; "progress_bar"
0023    KSHORT   5   0
0024    TSETS    5   4   7  ; "width"
0025    JMP      4 => 0051
0026 => TGETS    4   0   4  ; "settings"
0027    TGETS    4   4   8  ; "progress_bar_position"
0028    ISF          4
0029    JMP      5 => 0040
0030    TGETS    4   0   6  ; "progress_bar"
0031    GGET     5   9      ; "math"
0032    TGETS    5   5  10  ; "floor"
0033    TGETS    6   0   4  ; "settings"
0034    TGETS    6   6  11  ; "progress_margin_width"
0035    MULNV    6   6   0  ; 2
0036    SUBVV    6   2   6
0037    CALL     5   2   2
0038    TSETS    5   4   7  ; "width"
0039    JMP      4 => 0051
0040 => TGETS    4   0   6  ; "progress_bar"
0041    GGET     5   9      ; "math"
0042    TGETS    5   5  10  ; "floor"
0043    TGETS    6   0  12  ; "text_width"
0044    SUBVV    6   2   6
0045    TGETS    7   0   4  ; "settings"
0046    TGETS    7   7  11  ; "progress_margin_width"
0047    MULVN    7   7   0  ; 2
0048    SUBVV    6   6   7
0049    CALL     5   2   2
0050    TSETS    5   4   7  ; "width"
0051 => TGETS    4   0  13  ; "separator_line"
0052    ISF          4
0053    JMP      5 => 0060
0054    TGETS    4   0  13  ; "separator_line"
0055    TGETS    4   4  14  ; "dimen"
0056    TGETS    5   0  16  ; "horizontal_margin"
0057    MULNV    5   5   0  ; 2
0058    SUBVV    5   2   5
0059    TSETS    5   4  15  ; "w"
0060 => KPRI     4   0
0061    TGETS    5   0   4  ; "settings"
0062    TGETS    5   5  17  ; "progress_style_thin"
0063    ISF          5
0064    JMP      6 => 0071
0065    TGETS    5   0   4  ; "settings"
0066    TGETS    5   5  18  ; "progress_style_thin_height"
0067    ISTC     4   5
0068    JMP      6 => 0070
0069    UGET     4   1      ; PROGRESS_BAR_STYLE_THIN_DEFAULT_HEIGHT
0070 => JMP      5 => 0076
0071 => TGETS    5   0   4  ; "settings"
0072    TGETS    5   5  19  ; "progress_style_thick_height"
0073    ISTC     4   5
0074    JMP      6 => 0076
0075    UGET     4   2      ; PROGRESS_BAR_STYLE_THICK_DEFAULT_HEIGHT
0076 => TGETS    5   0   6  ; "progress_bar"
0077    UGET     6   0      ; Screen
0078    MOV      7   6
0079    TGETS    6   6  21  ; "scaleBySize"
0080    MOV      8   4
0081    CALL     6   2   3
0082    TSETS    6   5  20  ; "height"
0083    TGETS    5   0  22  ; "horizontal_group"
0084    MOV      6   5
0085    TGETS    5   5  23  ; "resetLayout"
0086    CALL     5   1   2
0087    TGETS    5   0  24  ; "footer_positioner"
0088    TGETS    5   5  14  ; "dimen"
0089    TSETS    2   5  15  ; "w"
0090    TGETS    5   0  24  ; "footer_positioner"
0091    TGETS    5   5  14  ; "dimen"
0092    TSETS    3   5  25  ; "h"
0093    TGETS    5   0  26  ; "footer_container"
0094    TGETS    5   5  14  ; "dimen"
0095    TSETS    2   5  15  ; "w"
0096    TGETS    5   0  24  ; "footer_positioner"
0097    MOV      6   5
0098    TGETS    5   5  27  ; "getSize"
0099    CALL     5   2   2
0100    TSETS    5   0  14  ; "dimen"
0101    TSETS    2   0   2  ; "_saved_screen_width"
0102    TSETS    3   0   3  ; "_saved_screen_height"
0103    RET0     0   1

-- BYTECODE -- readerfooter.lua:606-612
0001    TGETS    1   0   0  ; "footer_content"
0002    ISF          1
0003    JMP      2 => 0011
0004    TGETS    1   0   0  ; "footer_content"
0005    MOV      2   1
0006    TGETS    1   1   1  ; "getSize"
0007    CALL     1   2   2
0008    TGETS    1   1   2  ; "h"
0009    RET1     1   2
0010    JMP      1 => 0013
0011 => KSHORT   1   0
0012    RET1     1   2
0013 => RET0     0   1

-- BYTECODE -- readerfooter.lua:615-615
0001    RET0     0   1

-- BYTECODE -- readerfooter.lua:616-616
0001    RET0     0   1

-- BYTECODE -- readerfooter.lua:618-618
0001    RET0     0   1

-- BYTECODE -- readerfooter.lua:619-619
0001    RET0     0   1

-- BYTECODE -- readerfooter.lua:620-620
0001    RET0     0   1

-- BYTECODE -- readerfooter.lua:621-621
0001    RET0     0   1

-- BYTECODE -- readerfooter.lua:614-624
0001    FNEW     1   1      ; readerfooter.lua:615
0002    TSETS    1   0   0  ; "onReaderReady"
0003    FNEW     1   3      ; readerfooter.lua:616
0004    TSETS    1   0   2  ; "resetLayout"
0005    KPRI     1   0
0006    TSETS    1   0   4  ; "onCloseDocument"
0007    FNEW     1   6      ; readerfooter.lua:618
0008    TSETS    1   0   5  ; "updateFooterPage"
0009    FNEW     1   8      ; readerfooter.lua:619
0010    TSETS    1   0   7  ; "updateFooterPos"
0011    FNEW     1  10      ; readerfooter.lua:620
0012    TSETS    1   0   9  ; "onUpdatePos"
0013    FNEW     1  12      ; readerfooter.lua:621
0014    TSETS    1   0  11  ; "onSetStatusLine"
0015    TGETS    1   0  14  ; "mode_list"
0016    TGETS    1   1  15  ; "off"
0017    TSETS    1   0  13  ; "mode"
0018    TGETS    1   0  16  ; "view"
0019    KPRI     2   1
0020    TSETS    2   1  17  ; "footer_visible"
0021    RET0     0   1

-- BYTECODE -- readerfooter.lua:626-652
0001    TNEW     1   0
0002    GGET     2   0      ; "pairs"
0003    TGETS    3   0   1  ; "mode_index"
0004    CALL     2   4   2
0005    ISNEXT   5 => 0022
0006 => TGETS    7   0   2  ; "settings"
0007    TGETV    7   7   6
0008    ISF          7
0009    JMP      8 => 0022
0010    GGET     7   3      ; "table"
0011    TGETS    7   7   4  ; "insert"
0012    MOV      8   1
0013    UGET     9   0      ; footerTextGeneratorMap
0014    TGETV    9   9   6
0015    CALL     7   1   3
0016    TGETS    7   0   2  ; "settings"
0017    TGETS    7   7   5  ; "all_at_once"
0018    IST          7
0019    JMP      7 => 0022
0020    TSETS    5   0   6  ; "mode"
0021    JMP      2 => 0024
0022 => ITERN    5   3   3
0023    ITERL    5 => 0006
0024 => LEN      2   1
0025    ISNEN    2   0      ; 0
0026    JMP      2 => 0031
0027    UGET     2   0      ; footerTextGeneratorMap
0028    TGETS    2   2   8  ; "empty"
0029    TSETS    2   0   7  ; "genFooterText"
0030    JMP      2 => 0040
0031 => LEN      2   1
0032    ISNEN    2   1      ; 1
0033    JMP      2 => 0037
0034    TGETB    2   1   1
0035    TSETS    2   0   7  ; "genFooterText"
0036    JMP      2 => 0040
0037 => TSETS    1   0   9  ; "footerTextGenerators"
0038    TGETS    2   0  10  ; "genAllFooterText"
0039    TSETS    2   0   7  ; "genFooterText"
0040 => KPRI     2   2
0041    RET1     2   2

-- BYTECODE -- readerfooter.lua:654-665
0001    TGETS    2   0   0  ; "settings"
0002    TGETS    2   2   1  ; "item_prefix"
0003    IST          2
0004    JMP      3 => 0006
0005    KSTR     2   2      ; "icons"
0006 => UGET     3   0      ; symbol_prefix
0007    TGETV    3   3   2
0008    TGETS    3   3   3  ; "percentage"
0009    KPRI     4   0
0010    IST          3
0011    JMP      5 => 0017
0012    KSTR     5   4      ; "%."
0013    MOV      6   1
0014    KSTR     7   5      ; "f%%"
0015    CAT      4   5   7
0016    JMP      5 => 0022
0017 => MOV      5   3
0018    KSTR     6   6      ; " %."
0019    MOV      7   1
0020    KSTR     8   5      ; "f%%"
0021    CAT      4   5   8
0022 => MOV      6   4
0023    TGETS    5   4   7  ; "format"
0024    TGETS    7   0   8  ; "progress_bar"
0025    TGETS    7   7   3  ; "percentage"
0026    MULVN    7   7   0  ; 100
0027    CALLT    5   3

-- BYTECODE -- readerfooter.lua:667-688
0001    TGETS    2   0   0  ; "settings"
0002    TGETS    2   2   1  ; "item_prefix"
0003    IST          2
0004    JMP      3 => 0006
0005    KSTR     2   2      ; "icons"
0006 => TDUP     3   4
0007    UGET     4   0      ; _
0008    KSTR     5   3      ; "Show all at once"
0009    CALL     4   2   2
0010    TSETS    4   3   5  ; "all_at_once"
0011    UGET     4   0      ; _
0012    KSTR     5   6      ; "Reclaim bar height from bottom margin"
0013    CALL     4   2   2
0014    TSETS    4   3   7  ; "reclaim_height"
0015    UGET     4   1      ; T
0016    UGET     5   0      ; _
0017    KSTR     6   8      ; "Current page (%1)"
0018    CALL     5   2   2
0019    KSTR     6   9      ; "/"
0020    CALL     4   2   3
0021    TSETS    4   3  10  ; "page_progress"
0022    UGET     4   2      ; symbol_prefix
0023    TGETV    4   4   2
0024    TGETS    4   4  11  ; "time"
0025    ISF          4
0026    JMP      5 => 0037
0027    UGET     4   1      ; T
0028    UGET     5   0      ; _
0029    KSTR     6  12      ; "Current time (%1)"
0030    CALL     5   2   2
0031    UGET     6   2      ; symbol_prefix
0032    TGETV    6   6   2
0033    TGETS    6   6  11  ; "time"
0034    CALL     4   2   3
0035    IST          4
0036    JMP      5 => 0040
0037 => UGET     4   0      ; _
0038    KSTR     5  13      ; "Current time"
0039    CALL     4   2   2
0040 => TSETS    4   3  11  ; "time"
0041    UGET     4   1      ; T
0042    UGET     5   0      ; _
0043    KSTR     6  14      ; "Pages left in chapter (%1)"
0044    CALL     5   2   2
0045    UGET     6   2      ; symbol_prefix
0046    TGETV    6   6   2
0047    TGETS    6   6  15  ; "pages_left"
0048    CALL     4   2   3
0049    TSETS    4   3  15  ; "pages_left"
0050    UGET     4   1      ; T
0051    UGET     5   0      ; _
0052    KSTR     6  16      ; "Battery status (%1)"
0053    CALL     5   2   2
0054    UGET     6   2      ; symbol_prefix
0055    TGETV    6   6   2
0056    TGETS    6   6  17  ; "battery"
0057    CALL     4   2   3
0058    TSETS    4   3  17  ; "battery"
0059    UGET     4   2      ; symbol_prefix
0060    TGETV    4   4   2
0061    TGETS    4   4  18  ; "percentage"
0062    ISF          4
0063    JMP      5 => 0074
0064    UGET     4   1      ; T
0065    UGET     5   0      ; _
0066    KSTR     6  19      ; "Progress percentage (%1)"
0067    CALL     5   2   2
0068    UGET     6   2      ; symbol_prefix
0069    TGETV    6   6   2
0070    TGETS    6   6  18  ; "percentage"
0071    CALL     4   2   3
0072    IST          4
0073    JMP      5 => 0075
0074 => KSTR     4  20      ; "Progress percentage"
0075 => TSETS    4   3  18  ; "percentage"
0076    UGET     4   1      ; T
0077    UGET     5   0      ; _
0078    KSTR     6  21      ; "Book time to read (%1)"
0079    CALL     5   2   2
0080    UGET     6   2      ; symbol_prefix
0081    TGETV    6   6   2
0082    TGETS    6   6  22  ; "book_time_to_read"
0083    CALL     4   2   3
0084    TSETS    4   3  22  ; "book_time_to_read"
0085    UGET     4   1      ; T
0086    UGET     5   0      ; _
0087    KSTR     6  23      ; "Chapter time to read (%1)"
0088    CALL     5   2   2
0089    UGET     6   2      ; symbol_prefix
0090    TGETV    6   6   2
0091    TGETS    6   6  24  ; "chapter_time_to_read"
0092    CALL     4   2   3
0093    TSETS    4   3  24  ; "chapter_time_to_read"
0094    UGET     4   1      ; T
0095    UGET     5   0      ; _
0096    KSTR     6  25      ; "Frontlight level (%1)"
0097    CALL     5   2   2
0098    UGET     6   2      ; symbol_prefix
0099    TGETV    6   6   2
0100    TGETS    6   6  26  ; "frontlight"
0101    CALL     4   2   3
0102    TSETS    4   3  26  ; "frontlight"
0103    UGET     4   1      ; T
0104    UGET     5   0      ; _
0105    KSTR     6  27      ; "KOReader memory usage (%1)"
0106    CALL     5   2   2
0107    UGET     6   2      ; symbol_prefix
0108    TGETV    6   6   2
0109    TGETS    6   6  28  ; "mem_usage"
0110    CALL     4   2   3
0111    TSETS    4   3  28  ; "mem_usage"
0112    UGET     4   1      ; T
0113    UGET     5   0      ; _
0114    KSTR     6  29      ; "Wi-Fi status (%1)"
0115    CALL     5   2   2
0116    UGET     6   2      ; symbol_prefix
0117    TGETV    6   6   2
0118    TGETS    6   6  30  ; "wifi_status"
0119    CALL     4   2   3
0120    TSETS    4   3  30  ; "wifi_status"
0121    UGET     4   0      ; _
0122    KSTR     5  31      ; "Book title"
0123    CALL     4   2   2
0124    TSETS    4   3  32  ; "book_title"
0125    UGET     4   0      ; _
0126    KSTR     5  33      ; "Current chapter"
0127    CALL     4   2   2
0128    TSETS    4   3  34  ; "book_chapter"
0129    TGETV    4   3   1
0130    RET1     4   2

-- BYTECODE -- readerfooter.lua:706-708
0001    UGET     0   0      ; self
0002    TGETS    0   0   0  ; "view"
0003    TGETS    0   0   1  ; "flipping_visible"
0004    NOT      0   0
0005    RET1     0   2

-- BYTECODE -- readerfooter.lua:709-709
0001    UGET     0   0      ; self
0002    MOV      1   0
0003    TGETS    0   0   0  ; "onTapFooter"
0004    CALL     0   1   2
0005    RET0     0   1

-- BYTECODE -- readerfooter.lua:715-717
0001    UGET     0   0      ; self
0002    MOV      1   0
0003    TGETS    0   0   0  ; "textOptionTitles"
0004    UGET     2   1      ; option
0005    CALLT    0   3

-- BYTECODE -- readerfooter.lua:718-720
0001    UGET     0   0      ; self
0002    TGETS    0   0   0  ; "settings"
0003    UGET     1   1      ; option
0004    TGETV    0   0   1
0005    ISEQP    0   2
0006    JMP      0 => 0009
0007    KPRI     0   1
0008    JMP      1 => 0010
0009 => KPRI     0   2
0010 => RET1     0   2

-- BYTECODE -- readerfooter.lua:721-785
0001    UGET     0   0      ; self
0002    TGETS    0   0   0  ; "settings"
0003    UGET     1   1      ; option
0004    UGET     2   0      ; self
0005    TGETS    2   2   0  ; "settings"
0006    UGET     3   1      ; option
0007    TGETV    2   2   3
0008    NOT      2   2
0009    TSETV    2   0   1
0010    GGET     0   1      ; "G_reader_settings"
0011    MOV      1   0
0012    TGETS    0   0   2  ; "saveSetting"
0013    KSTR     2   3      ; "footer"
0014    UGET     3   0      ; self
0015    TGETS    3   3   0  ; "settings"
0016    CALL     0   1   4
0017    KPRI     0   1
0018    KPRI     1   1
0019    KPRI     2   0
0020    UGET     3   0      ; self
0021    TGETS    3   3   4  ; "has_no_mode"
0022    UGET     4   0      ; self
0023    TGETS    4   4   5  ; "reclaim_height"
0024    UGET     5   0      ; self
0025    KPRI     6   2
0026    TSETS    6   5   4  ; "has_no_mode"
0027    GGET     5   6      ; "pairs"
0028    UGET     6   0      ; self
0029    TGETS    6   6   7  ; "mode_index"
0030    CALL     5   4   2
0031    ISNEXT   8 => 0042
0032 => UGET    10   0      ; self
0033    TGETS   10  10   0  ; "settings"
0034    TGETV   10  10   9
0035    ISF         10
0036    JMP     11 => 0042
0037    MOV      2   8
0038    UGET    10   0      ; self
0039    KPRI    11   1
0040    TSETS   11  10   4  ; "has_no_mode"
0041    JMP      5 => 0044
0042 => ITERN    8   3   3
0043    ITERL    8 => 0032
0044 => UGET     5   0      ; self
0045    UGET     6   0      ; self
0046    TGETS    6   6   0  ; "settings"
0047    TGETS    6   6   5  ; "reclaim_height"
0048    IST          6
0049    JMP      7 => 0051
0050    KPRI     6   1
0051 => TSETS    6   5   5  ; "reclaim_height"
0052    UGET     5   0      ; self
0053    TGETS    5   5   4  ; "has_no_mode"
0054    ISF          5
0055    JMP      6 => 0076
0056    UGET     5   0      ; self
0057    TGETS    5   5   8  ; "footer_container"
0058    TGETS    5   5   9  ; "dimen"
0059    KSHORT   6   0
0060    TSETS    6   5  10  ; "h"
0061    UGET     5   0      ; self
0062    TGETS    5   5  11  ; "footer_text"
0063    KSHORT   6   0
0064    TSETS    6   5  12  ; "height"
0065    KPRI     0   2
0066    UGET     5   0      ; self
0067    UGET     6   2      ; footerTextGeneratorMap
0068    TGETS    6   6  14  ; "empty"
0069    TSETS    6   5  13  ; "genFooterText"
0070    UGET     5   0      ; self
0071    UGET     6   0      ; self
0072    TGETS    6   6  16  ; "mode_list"
0073    TGETS    6   6  17  ; "off"
0074    TSETS    6   5  15  ; "mode"
0075    JMP      5 => 0117
0076 => ISF          3
0077    JMP      5 => 0111
0078    UGET     5   0      ; self
0079    TGETS    5   5   8  ; "footer_container"
0080    TGETS    5   5   9  ; "dimen"
0081    UGET     6   0      ; self
0082    TGETS    6   6  12  ; "height"
0083    TSETS    6   5  10  ; "h"
0084    UGET     5   0      ; self
0085    TGETS    5   5  11  ; "footer_text"
0086    UGET     6   0      ; self
0087    TGETS    6   6  12  ; "height"
0088    TSETS    6   5  12  ; "height"
0089    UGET     5   0      ; self
0090    TGETS    5   5   0  ; "settings"
0091    TGETS    5   5  18  ; "all_at_once"
0092    ISF          5
0093    JMP      6 => 0103
0094    UGET     5   0      ; self
0095    UGET     6   0      ; self
0096    TGETS    6   6  16  ; "mode_list"
0097    TGETS    6   6  19  ; "page_progress"
0098    TSETS    6   5  15  ; "mode"
0099    UGET     5   0      ; self
0100    MOV      6   5
0101    TGETS    5   5  20  ; "applyFooterMode"
0102    CALL     5   1   2
0103 => KPRI     0   2
0104    GGET     5   1      ; "G_reader_settings"
0105    MOV      6   5
0106    TGETS    5   5   2  ; "saveSetting"
0107    KSTR     7  21      ; "reader_footer_mode"
0108    MOV      8   2
0109    CALL     5   1   4
0110    JMP      5 => 0117
0111 => UGET     5   0      ; self
0112    TGETS    5   5   5  ; "reclaim_height"
0113    ISEQV    5   4
0114    JMP      5 => 0117
0115    KPRI     0   2
0116    KPRI     1   2
0117 => UGET     5   3      ; callback
0118    ISF          5
0119    JMP      6 => 0125
0120    UGET     5   3      ; callback
0121    UGET     6   0      ; self
0122    CALL     5   2   2
0123    MOV      1   5
0124    JMP      5 => 0181
0125 => UGET     5   0      ; self
0126    TGETS    5   5   0  ; "settings"
0127    TGETS    5   5  18  ; "all_at_once"
0128    ISF          5
0129    JMP      6 => 0136
0130    UGET     5   0      ; self
0131    MOV      6   5
0132    TGETS    5   5  22  ; "updateFooterTextGenerator"
0133    CALL     5   2   2
0134    MOV      1   5
0135    JMP      5 => 0181
0136 => UGET     5   0      ; self
0137    TGETS    5   5  16  ; "mode_list"
0138    UGET     6   1      ; option
0139    TGETV    5   5   6
0140    UGET     6   0      ; self
0141    TGETS    6   6  15  ; "mode"
0142    ISNEV    5   6
0143    JMP      5 => 0150
0144    UGET     5   0      ; self
0145    TGETS    5   5   0  ; "settings"
0146    UGET     6   1      ; option
0147    TGETV    5   5   6
0148    ISEQP    5   1
0149    JMP      5 => 0154
0150 => UGET     5   0      ; self
0151    TGETS    5   5   4  ; "has_no_mode"
0152    ISEQV    3   5
0153    JMP      5 => 0181
0154 => UGET     5   0      ; self
0155    TGETS    5   5   4  ; "has_no_mode"
0156    IST          5
0157    JMP      5 => 0161
0158    UGET     5   0      ; self
0159    TSETS    2   5  15  ; "mode"
0160    JMP      5 => 0176
0161 => UGET     5   0      ; self
0162    UGET     6   0      ; self
0163    TGETS    6   6   0  ; "settings"
0164    TGETS    6   6  23  ; "disable_progress_bar"
0165    ISF          6
0166    JMP      7 => 0172
0167    UGET     6   0      ; self
0168    TGETS    6   6  16  ; "mode_list"
0169    TGETS    6   6  17  ; "off"
0170    IST          6
0171    JMP      7 => 0175
0172 => UGET     6   0      ; self
0173    TGETS    6   6  16  ; "mode_list"
0174    TGETS    6   6  19  ; "page_progress"
0175 => TSETS    6   5  15  ; "mode"
0176 => KPRI     1   2
0177    UGET     5   0      ; self
0178    MOV      6   5
0179    TGETS    5   5  20  ; "applyFooterMode"
0180    CALL     5   1   2
0181 => IST          1
0182    JMP      5 => 0185
0183    ISF          0
0184    JMP      5 => 0191
0185 => UGET     5   0      ; self
0186    MOV      6   5
0187    TGETS    5   5  24  ; "refreshFooter"
0188    MOV      7   1
0189    MOV      8   0
0190    CALL     5   1   4
0191 => RET0     0   1

-- BYTECODE -- readerfooter.lua:713-787
0001    TDUP     2   1
0002    FNEW     3   0      ; readerfooter.lua:715
0003    TSETS    3   2   2  ; "text_func"
0004    FNEW     3   3      ; readerfooter.lua:718
0005    TSETS    3   2   4  ; "checked_func"
0006    FNEW     3   5      ; readerfooter.lua:721
0007    TSETS    3   2   6  ; "callback"
0008    UCLO     0 => 0009
0009 => RET1     2   2

-- BYTECODE -- readerfooter.lua:803-812
0001    KSHORT   0   1
0002    UGET     1   0      ; sort_item
0003    TGETS    1   1   0  ; "item_table"
0004    LEN      1   1
0005    KSHORT   2   1
0006    FORI     0 => 0015
0007 => UGET     4   1      ; self
0008    TGETS    4   4   1  ; "mode_index"
0009    UGET     5   0      ; sort_item
0010    TGETS    5   5   0  ; "item_table"
0011    TGETV    5   5   3
0012    TGETS    5   5   2  ; "label"
0013    TSETV    5   4   3
0014    FORL     0 => 0007
0015 => UGET     0   1      ; self
0016    TGETS    0   0   3  ; "settings"
0017    UGET     1   1      ; self
0018    TGETS    1   1   1  ; "mode_index"
0019    TSETS    1   0   4  ; "order"
0020    GGET     0   5      ; "G_reader_settings"
0021    MOV      1   0
0022    TGETS    0   0   6  ; "saveSetting"
0023    KSTR     2   7      ; "footer"
0024    UGET     3   1      ; self
0025    TGETS    3   3   3  ; "settings"
0026    CALL     0   1   4
0027    UGET     0   1      ; self
0028    MOV      1   0
0029    TGETS    0   0   8  ; "updateFooterTextGenerator"
0030    CALL     0   1   2
0031    UGET     0   1      ; self
0032    MOV      1   0
0033    TGETS    0   0   9  ; "updateFooter"
0034    CALL     0   1   2
0035    UGET     0   2      ; UIManager
0036    MOV      1   0
0037    TGETS    0   0  10  ; "setDirty"
0038    KPRI     2   0
0039    KSTR     3  11      ; "ui"
0040    CALL     0   1   4
0041    RET0     0   1

-- BYTECODE -- readerfooter.lua:793-815
0001    TNEW     0   0
0002    KSHORT   1   1
0003    UGET     2   0      ; self
0004    TGETS    2   2   0  ; "mode_index"
0005    LEN      2   2
0006    KSHORT   3   1
0007    FORI     1 => 0026
0008 => GGET     5   1      ; "table"
0009    TGETS    5   5   2  ; "insert"
0010    MOV      6   0
0011    TDUP     7   4
0012    UGET     8   0      ; self
0013    MOV      9   8
0014    TGETS    8   8   3  ; "textOptionTitles"
0015    UGET    10   0      ; self
0016    TGETS   10  10   0  ; "mode_index"
0017    TGETV   10  10   4
0018    CALL     8   2   3
0019    TSETS    8   7   5  ; "text"
0020    UGET     8   0      ; self
0021    TGETS    8   8   0  ; "mode_index"
0022    TGETV    8   8   4
0023    TSETS    8   7   6  ; "label"
0024    CALL     5   1   3
0025    FORL     1 => 0008
0026 => GGET     1   7      ; "require"
0027    KSTR     2   8      ; "ui/widget/sortwidget"
0028    CALL     1   2   2
0029    KPRI     2   0
0030    MOV      4   1
0031    TGETS    3   1   9  ; "new"
0032    TDUP     5  11
0033    UGET     6   1      ; _
0034    KSTR     7  10      ; "Sort footer items"
0035    CALL     6   2   2
0036    TSETS    6   5  12  ; "title"
0037    TSETS    0   5  13  ; "item_table"
0038    FNEW     6  14      ; readerfooter.lua:803
0039    TSETS    6   5  15  ; "callback"
0040    CALL     3   2   3
0041    MOV      2   3
0042    UGET     3   2      ; UIManager
0043    MOV      4   3
0044    TGETS    3   3  16  ; "show"
0045    MOV      5   2
0046    CALL     3   1   3
0047    UCLO     0 => 0048
0048 => RET0     0   1

-- BYTECODE -- readerfooter.lua:821-823
0001    UGET     0   0      ; self
0002    TGETS    0   0   0  ; "settings"
0003    TGETS    0   0   1  ; "auto_refresh_time"
0004    ISEQP    0   2
0005    JMP      0 => 0008
0006    KPRI     0   1
0007    JMP      1 => 0009
0008 => KPRI     0   2
0009 => RET1     0   2

-- BYTECODE -- readerfooter.lua:825-825
0001    UGET     0   0      ; self
0002    TGETS    0   0   0  ; "settings"
0003    TGETS    0   0   1  ; "time"
0004    RET1     0   2

-- BYTECODE -- readerfooter.lua:826-835
0001    UGET     0   0      ; self
0002    TGETS    0   0   0  ; "settings"
0003    UGET     1   0      ; self
0004    TGETS    1   1   0  ; "settings"
0005    TGETS    1   1   1  ; "auto_refresh_time"
0006    NOT      1   1
0007    TSETS    1   0   1  ; "auto_refresh_time"
0008    GGET     0   2      ; "G_reader_settings"
0009    MOV      1   0
0010    TGETS    0   0   3  ; "saveSetting"
0011    KSTR     2   4      ; "footer"
0012    UGET     3   0      ; self
0013    TGETS    3   3   0  ; "settings"
0014    CALL     0   1   4
0015    UGET     0   0      ; self
0016    TGETS    0   0   0  ; "settings"
0017    TGETS    0   0   1  ; "auto_refresh_time"
0018    ISF          0
0019    JMP      1 => 0025
0020    UGET     0   0      ; self
0021    MOV      1   0
0022    TGETS    0   0   5  ; "setupAutoRefreshTime"
0023    CALL     0   1   2
0024    JMP      0 => 0034
0025 => UGET     0   1      ; UIManager
0026    MOV      1   0
0027    TGETS    0   0   6  ; "unschedule"
0028    UGET     2   0      ; self
0029    TGETS    2   2   7  ; "autoRefreshTime"
0030    CALL     0   1   3
0031    UGET     0   0      ; self
0032    KPRI     1   0
0033    TSETS    1   0   8  ; "onCloseDocument"
0034 => RET0     0   1

-- BYTECODE -- readerfooter.lua:839-841
0001    UGET     0   0      ; self
0002    TGETS    0   0   0  ; "settings"
0003    TGETS    0   0   1  ; "bottom_horizontal_separator"
0004    RET1     0   2

-- BYTECODE -- readerfooter.lua:842-845
0001    UGET     0   0      ; self
0002    TGETS    0   0   0  ; "settings"
0003    UGET     1   0      ; self
0004    TGETS    1   1   0  ; "settings"
0005    TGETS    1   1   1  ; "bottom_horizontal_separator"
0006    NOT      1   1
0007    TSETS    1   0   1  ; "bottom_horizontal_separator"
0008    UGET     0   0      ; self
0009    MOV      1   0
0010    TGETS    0   0   2  ; "refreshFooter"
0011    KPRI     2   2
0012    KPRI     3   2
0013    CALL     0   1   4
0014    RET0     0   1

-- BYTECODE -- readerfooter.lua:849-851
0001    UGET     0   0      ; self
0002    TGETS    0   0   0  ; "settings"
0003    TGETS    0   0   1  ; "lock_tap"
0004    RET1     0   2

-- BYTECODE -- readerfooter.lua:852-854
0001    UGET     0   0      ; self
0002    TGETS    0   0   0  ; "settings"
0003    UGET     1   0      ; self
0004    TGETS    1   1   0  ; "settings"
0005    TGETS    1   1   1  ; "lock_tap"
0006    NOT      1   1
0007    TSETS    1   0   1  ; "lock_tap"
0008    RET0     0   1

-- BYTECODE -- readerfooter.lua:861-863
0001    UGET     0   0      ; T
0002    UGET     1   1      ; _
0003    KSTR     2   0      ; "Font size (%1)"
0004    CALL     1   2   2
0005    UGET     2   2      ; self
0006    TGETS    2   2   1  ; "settings"
0007    TGETS    2   2   2  ; "text_font_size"
0008    CALLT    0   3

-- BYTECODE -- readerfooter.lua:876-887
0001    UGET     1   0      ; self
0002    TGETS    1   1   0  ; "settings"
0003    TGETS    2   0   2  ; "value"
0004    TSETS    2   1   1  ; "text_font_size"
0005    UGET     1   0      ; self
0006    TGETS    1   1   3  ; "footer_text"
0007    MOV      2   1
0008    TGETS    1   1   4  ; "free"
0009    CALL     1   1   2
0010    UGET     1   0      ; self
0011    UGET     2   1      ; TextWidget
0012    MOV      3   2
0013    TGETS    2   2   5  ; "new"
0014    TDUP     4   7
0015    UGET     5   0      ; self
0016    TGETS    5   5   3  ; "footer_text"
0017    TGETS    5   5   6  ; "text"
0018    TSETS    5   4   6  ; "text"
0019    UGET     5   2      ; Font
0020    MOV      6   5
0021    TGETS    5   5   8  ; "getFace"
0022    UGET     7   0      ; self
0023    TGETS    7   7   9  ; "text_font_face"
0024    UGET     8   0      ; self
0025    TGETS    8   8   0  ; "settings"
0026    TGETS    8   8   1  ; "text_font_size"
0027    CALL     5   2   4
0028    TSETS    5   4  10  ; "face"
0029    UGET     5   0      ; self
0030    TGETS    5   5   0  ; "settings"
0031    TGETS    5   5  11  ; "text_font_bold"
0032    TSETS    5   4  12  ; "bold"
0033    CALL     2   2   3
0034    TSETS    2   1   3  ; "footer_text"
0035    UGET     1   0      ; self
0036    TGETS    1   1  13  ; "text_container"
0037    UGET     2   0      ; self
0038    TGETS    2   2   3  ; "footer_text"
0039    TSETB    2   1   1
0040    UGET     1   0      ; self
0041    MOV      2   1
0042    TGETS    1   1  14  ; "refreshFooter"
0043    KPRI     3   2
0044    KPRI     4   2
0045    CALL     1   1   4
0046    UGET     1   3      ; touchmenu_instance
0047    ISF          1
0048    JMP      2 => 0053
0049    UGET     1   3      ; touchmenu_instance
0050    MOV      2   1
0051    TGETS    1   1  15  ; "updateItems"
0052    CALL     1   1   2
0053 => RET0     0   1

-- BYTECODE -- readerfooter.lua:864-890
0001    GGET     1   0      ; "require"
0002    KSTR     2   1      ; "ui/widget/spinwidget"
0003    CALL     1   2   2
0004    UGET     2   0      ; self
0005    TGETS    2   2   2  ; "settings"
0006    TGETS    2   2   3  ; "text_font_size"
0007    MOV      4   1
0008    TGETS    3   1   4  ; "new"
0009    TDUP     5   6
0010    UGET     6   1      ; Screen
0011    MOV      7   6
0012    TGETS    6   6   5  ; "getWidth"
0013    CALL     6   2   2
0014    MULVN    6   6   0  ; 0.6
0015    TSETS    6   5   7  ; "width"
0016    TSETS    2   5   8  ; "value"
0017    UGET     6   2      ; _
0018    KSTR     7   9      ; "Set size"
0019    CALL     6   2   2
0020    TSETS    6   5  10  ; "ok_text"
0021    UGET     6   2      ; _
0022    KSTR     7  11      ; "Footer font size"
0023    CALL     6   2   2
0024    TSETS    6   5  12  ; "title_text"
0025    FNEW     6  13      ; readerfooter.lua:876
0026    TSETS    6   5  14  ; "callback"
0027    CALL     3   2   3
0028    UGET     4   5      ; UIManager
0029    MOV      5   4
0030    TGETS    4   4  15  ; "show"
0031    MOV      6   3
0032    CALL     4   1   3
0033    UCLO     0 => 0034
0034 => RET0     0   1

-- BYTECODE -- readerfooter.lua:895-897
0001    UGET     0   0      ; self
0002    TGETS    0   0   0  ; "settings"
0003    TGETS    0   0   1  ; "text_font_bold"
0004    ISEQP    0   2
0005    JMP      0 => 0008
0006    KPRI     0   1
0007    JMP      1 => 0009
0008 => KPRI     0   2
0009 => RET1     0   2

-- BYTECODE -- readerfooter.lua:898-909
0001    UGET     1   0      ; self
0002    TGETS    1   1   0  ; "settings"
0003    UGET     2   0      ; self
0004    TGETS    2   2   0  ; "settings"
0005    TGETS    2   2   1  ; "text_font_bold"
0006    NOT      2   2
0007    TSETS    2   1   1  ; "text_font_bold"
0008    UGET     1   0      ; self
0009    TGETS    1   1   2  ; "footer_text"
0010    MOV      2   1
0011    TGETS    1   1   3  ; "free"
0012    CALL     1   1   2
0013    UGET     1   0      ; self
0014    UGET     2   1      ; TextWidget
0015    MOV      3   2
0016    TGETS    2   2   4  ; "new"
0017    TDUP     4   6
0018    UGET     5   0      ; self
0019    TGETS    5   5   2  ; "footer_text"
0020    TGETS    5   5   5  ; "text"
0021    TSETS    5   4   5  ; "text"
0022    UGET     5   2      ; Font
0023    MOV      6   5
0024    TGETS    5   5   7  ; "getFace"
0025    UGET     7   0      ; self
0026    TGETS    7   7   8  ; "text_font_face"
0027    UGET     8   0      ; self
0028    TGETS    8   8   0  ; "settings"
0029    TGETS    8   8   9  ; "text_font_size"
0030    CALL     5   2   4
0031    TSETS    5   4  10  ; "face"
0032    UGET     5   0      ; self
0033    TGETS    5   5   0  ; "settings"
0034    TGETS    5   5   1  ; "text_font_bold"
0035    TSETS    5   4  11  ; "bold"
0036    CALL     2   2   3
0037    TSETS    2   1   2  ; "footer_text"
0038    UGET     1   0      ; self
0039    TGETS    1   1  12  ; "text_container"
0040    UGET     2   0      ; self
0041    TGETS    2   2   2  ; "footer_text"
0042    TSETB    2   1   1
0043    UGET     1   0      ; self
0044    MOV      2   1
0045    TGETS    1   1  13  ; "refreshFooter"
0046    KPRI     3   2
0047    KPRI     4   2
0048    CALL     1   1   4
0049    ISF          0
0050    JMP      1 => 0054
0051    MOV      2   0
0052    TGETS    1   0  14  ; "updateItems"
0053    CALL     1   1   2
0054 => RET0     0   1

-- BYTECODE -- readerfooter.lua:918-920
0001    UGET     0   0      ; T
0002    UGET     1   1      ; _
0003    KSTR     2   0      ; "Book title (%1%)"
0004    CALL     1   2   2
0005    UGET     2   2      ; self
0006    TGETS    2   2   1  ; "settings"
0007    TGETS    2   2   2  ; "book_title_max_width_pct"
0008    CALLT    0   3

-- BYTECODE -- readerfooter.lua:933-937
0001    UGET     1   0      ; self
0002    TGETS    1   1   0  ; "settings"
0003    TGETS    2   0   2  ; "value"
0004    TSETS    2   1   1  ; "book_title_max_width_pct"
0005    UGET     1   0      ; self
0006    MOV      2   1
0007    TGETS    1   1   3  ; "refreshFooter"
0008    KPRI     3   2
0009    KPRI     4   2
0010    CALL     1   1   4
0011    UGET     1   1      ; touchmenu_instance
0012    ISF          1
0013    JMP      2 => 0018
0014    UGET     1   1      ; touchmenu_instance
0015    MOV      2   1
0016    TGETS    1   1   4  ; "updateItems"
0017    CALL     1   1   2
0018 => RET0     0   1

-- BYTECODE -- readerfooter.lua:921-940
0001    GGET     1   0      ; "require"
0002    KSTR     2   1      ; "ui/widget/spinwidget"
0003    CALL     1   2   2
0004    MOV      3   1
0005    TGETS    2   1   2  ; "new"
0006    TDUP     4   4
0007    UGET     5   0      ; Screen
0008    MOV      6   5
0009    TGETS    5   5   3  ; "getWidth"
0010    CALL     5   2   2
0011    MULVN    5   5   0  ; 0.6
0012    TSETS    5   4   5  ; "width"
0013    UGET     5   1      ; self
0014    TGETS    5   5   6  ; "settings"
0015    TGETS    5   5   7  ; "book_title_max_width_pct"
0016    TSETS    5   4   8  ; "value"
0017    UGET     5   2      ; _
0018    KSTR     6   9      ; "Maximum width"
0019    CALL     5   2   2
0020    TSETS    5   4  10  ; "title_text"
0021    UGET     5   2      ; _
0022    KSTR     6  11      ; "Maximum book title width in percentage o"~
0023    CALL     5   2   2
0024    TSETS    5   4  12  ; "info_text"
0025    FNEW     5  13      ; readerfooter.lua:933
0026    TSETS    5   4  14  ; "callback"
0027    CALL     2   2   3
0028    UGET     3   3      ; UIManager
0029    MOV      4   3
0030    TGETS    3   3  15  ; "show"
0031    MOV      5   2
0032    CALL     3   1   3
0033    UCLO     0 => 0034
0034 => RET0     0   1

-- BYTECODE -- readerfooter.lua:944-946
0001    UGET     0   0      ; T
0002    UGET     1   1      ; _
0003    KSTR     2   0      ; "Current chapter (%1%)"
0004    CALL     1   2   2
0005    UGET     2   2      ; self
0006    TGETS    2   2   1  ; "settings"
0007    TGETS    2   2   2  ; "book_chapter_max_width_pct"
0008    CALLT    0   3

-- BYTECODE -- readerfooter.lua:959-963
0001    UGET     1   0      ; self
0002    TGETS    1   1   0  ; "settings"
0003    TGETS    2   0   2  ; "value"
0004    TSETS    2   1   1  ; "book_chapter_max_width_pct"
0005    UGET     1   0      ; self
0006    MOV      2   1
0007    TGETS    1   1   3  ; "refreshFooter"
0008    KPRI     3   2
0009    KPRI     4   2
0010    CALL     1   1   4
0011    UGET     1   1      ; touchmenu_instance
0012    ISF          1
0013    JMP      2 => 0018
0014    UGET     1   1      ; touchmenu_instance
0015    MOV      2   1
0016    TGETS    1   1   4  ; "updateItems"
0017    CALL     1   1   2
0018 => RET0     0   1

-- BYTECODE -- readerfooter.lua:947-966
0001    GGET     1   0      ; "require"
0002    KSTR     2   1      ; "ui/widget/spinwidget"
0003    CALL     1   2   2
0004    MOV      3   1
0005    TGETS    2   1   2  ; "new"
0006    TDUP     4   4
0007    UGET     5   0      ; Screen
0008    MOV      6   5
0009    TGETS    5   5   3  ; "getWidth"
0010    CALL     5   2   2
0011    MULVN    5   5   0  ; 0.6
0012    TSETS    5   4   5  ; "width"
0013    UGET     5   1      ; self
0014    TGETS    5   5   6  ; "settings"
0015    TGETS    5   5   7  ; "book_chapter_max_width_pct"
0016    TSETS    5   4   8  ; "value"
0017    UGET     5   2      ; _
0018    KSTR     6   9      ; "Maximum width"
0019    CALL     5   2   2
0020    TSETS    5   4  10  ; "title_text"
0021    UGET     5   2      ; _
0022    KSTR     6  11      ; "Maximum chapter width in percentage of s"~
0023    CALL     5   2   2
0024    TSETS    5   4  12  ; "info_text"
0025    FNEW     5  13      ; readerfooter.lua:959
0026    TSETS    5   4  14  ; "callback"
0027    CALL     2   2   3
0028    UGET     3   3      ; UIManager
0029    MOV      4   3
0030    TGETS    3   3  15  ; "show"
0031    MOV      5   2
0032    CALL     3   1   3
0033    UCLO     0 => 0034
0034 => RET0     0   1

-- BYTECODE -- readerfooter.lua:973-975
0001    UGET     0   0      ; self
0002    TGETS    0   0   0  ; "settings"
0003    TGETS    0   0   1  ; "disable_progress_bar"
0004    IST          0
0005    JMP      1 => 0014
0006    UGET     0   0      ; self
0007    TGETS    0   0   0  ; "settings"
0008    TGETS    0   0   2  ; "progress_bar_position"
0009    ISNEP    0   0
0010    JMP      0 => 0013
0011    KPRI     0   1
0012    JMP      1 => 0014
0013 => KPRI     0   2
0014 => RET1     0   2

-- BYTECODE -- readerfooter.lua:979-981
0001    UGET     0   0      ; self
0002    TGETS    0   0   0  ; "settings"
0003    TGETS    0   0   1  ; "align"
0004    ISEQS    0   2      ; "center"
0005    JMP      0 => 0013
0006    UGET     0   0      ; self
0007    TGETS    0   0   0  ; "settings"
0008    TGETS    0   0   1  ; "align"
0009    ISEQP    0   0
0010    JMP      0 => 0013
0011    KPRI     0   1
0012    JMP      1 => 0014
0013 => KPRI     0   2
0014 => RET1     0   2

-- BYTECODE -- readerfooter.lua:982-985
0001    UGET     0   0      ; self
0002    TGETS    0   0   0  ; "settings"
0003    KSTR     1   2      ; "center"
0004    TSETS    1   0   1  ; "align"
0005    UGET     0   0      ; self
0006    MOV      1   0
0007    TGETS    0   0   3  ; "refreshFooter"
0008    KPRI     2   2
0009    CALL     0   1   3
0010    RET0     0   1

-- BYTECODE -- readerfooter.lua:989-991
0001    UGET     0   0      ; self
0002    TGETS    0   0   0  ; "settings"
0003    TGETS    0   0   1  ; "align"
0004    ISEQS    0   2      ; "left"
0005    JMP      0 => 0008
0006    KPRI     0   1
0007    JMP      1 => 0009
0008 => KPRI     0   2
0009 => RET1     0   2

-- BYTECODE -- readerfooter.lua:992-995
0001    UGET     0   0      ; self
0002    TGETS    0   0   0  ; "settings"
0003    KSTR     1   2      ; "left"
0004    TSETS    1   0   1  ; "align"
0005    UGET     0   0      ; self
0006    MOV      1   0
0007    TGETS    0   0   3  ; "refreshFooter"
0008    KPRI     2   2
0009    CALL     0   1   3
0010    RET0     0   1

-- BYTECODE -- readerfooter.lua:999-1001
0001    UGET     0   0      ; self
0002    TGETS    0   0   0  ; "settings"
0003    TGETS    0   0   1  ; "align"
0004    ISEQS    0   2      ; "right"
0005    JMP      0 => 0008
0006    KPRI     0   1
0007    JMP      1 => 0009
0008 => KPRI     0   2
0009 => RET1     0   2

-- BYTECODE -- readerfooter.lua:1002-1005
0001    UGET     0   0      ; self
0002    TGETS    0   0   0  ; "settings"
0003    KSTR     1   2      ; "right"
0004    TSETS    1   0   1  ; "align"
0005    UGET     0   0      ; self
0006    MOV      1   0
0007    TGETS    0   0   3  ; "refreshFooter"
0008    KPRI     2   2
0009    CALL     0   1   3
0010    RET0     0   1

-- BYTECODE -- readerfooter.lua:1013-1019
0001    TNEW     0   0
0002    GGET     1   0      ; "pairs"
0003    UGET     2   0      ; symbol_prefix
0004    TGETS    2   2   1  ; "icons"
0005    CALL     1   4   2
0006    ISNEXT   4 => 0012
0007 => GGET     6   2      ; "table"
0008    TGETS    6   6   3  ; "insert"
0009    MOV      7   0
0010    MOV      8   5
0011    CALL     6   1   3
0012 => ITERN    4   3   3
0013    ITERL    4 => 0007
0014    UGET     1   1      ; T
0015    UGET     2   2      ; _
0016    KSTR     3   4      ; "Icons (%1)"
0017    CALL     2   2   2
0018    GGET     3   2      ; "table"
0019    TGETS    3   3   5  ; "concat"
0020    MOV      4   0
0021    KSTR     5   6      ; " "
0022    CALL     3   0   3
0023    CALLMT   1   1

-- BYTECODE -- readerfooter.lua:1020-1022
0001    UGET     0   0      ; self
0002    TGETS    0   0   0  ; "settings"
0003    TGETS    0   0   1  ; "item_prefix"
0004    ISEQS    0   2      ; "icons"
0005    JMP      0 => 0013
0006    UGET     0   0      ; self
0007    TGETS    0   0   0  ; "settings"
0008    TGETS    0   0   1  ; "item_prefix"
0009    ISEQP    0   0
0010    JMP      0 => 0013
0011    KPRI     0   1
0012    JMP      1 => 0014
0013 => KPRI     0   2
0014 => RET1     0   2

-- BYTECODE -- readerfooter.lua:1023-1027
0001    UGET     0   0      ; self
0002    TGETS    0   0   0  ; "settings"
0003    KSTR     1   2      ; "icons"
0004    TSETS    1   0   1  ; "item_prefix"
0005    UGET     0   0      ; self
0006    MOV      1   0
0007    TGETS    0   0   3  ; "updateFooter"
0008    CALL     0   1   2
0009    UGET     0   1      ; UIManager
0010    MOV      1   0
0011    TGETS    0   0   4  ; "setDirty"
0012    KPRI     2   0
0013    KSTR     3   5      ; "ui"
0014    CALL     0   1   4
0015    RET0     0   1

-- BYTECODE -- readerfooter.lua:1030-1036
0001    TNEW     0   0
0002    GGET     1   0      ; "pairs"
0003    UGET     2   0      ; symbol_prefix
0004    TGETS    2   2   1  ; "letters"
0005    CALL     1   4   2
0006    ISNEXT   4 => 0012
0007 => GGET     6   2      ; "table"
0008    TGETS    6   6   3  ; "insert"
0009    MOV      7   0
0010    MOV      8   5
0011    CALL     6   1   3
0012 => ITERN    4   3   3
0013    ITERL    4 => 0007
0014    UGET     1   1      ; T
0015    UGET     2   2      ; _
0016    KSTR     3   4      ; "Letters (%1)"
0017    CALL     2   2   2
0018    GGET     3   2      ; "table"
0019    TGETS    3   3   5  ; "concat"
0020    MOV      4   0
0021    KSTR     5   6      ; " "
0022    CALL     3   0   3
0023    CALLMT   1   1

-- BYTECODE -- readerfooter.lua:1037-1039
0001    UGET     0   0      ; self
0002    TGETS    0   0   0  ; "settings"
0003    TGETS    0   0   1  ; "item_prefix"
0004    ISEQS    0   2      ; "letters"
0005    JMP      0 => 0008
0006    KPRI     0   1
0007    JMP      1 => 0009
0008 => KPRI     0   2
0009 => RET1     0   2

-- BYTECODE -- readerfooter.lua:1040-1044
0001    UGET     0   0      ; self
0002    TGETS    0   0   0  ; "settings"
0003    KSTR     1   2      ; "letters"
0004    TSETS    1   0   1  ; "item_prefix"
0005    UGET     0   0      ; self
0006    MOV      1   0
0007    TGETS    0   0   3  ; "updateFooter"
0008    CALL     0   1   2
0009    UGET     0   1      ; UIManager
0010    MOV      1   0
0011    TGETS    0   0   4  ; "setDirty"
0012    KPRI     2   0
0013    KSTR     3   5      ; "ui"
0014    CALL     0   1   4
0015    RET0     0   1

-- BYTECODE -- readerfooter.lua:1053-1055
0001    UGET     0   0      ; self
0002    TGETS    0   0   0  ; "settings"
0003    TGETS    0   0   1  ; "items_separator"
0004    ISEQS    0   2      ; "bar"
0005    JMP      0 => 0013
0006    UGET     0   0      ; self
0007    TGETS    0   0   0  ; "settings"
0008    TGETS    0   0   1  ; "items_separator"
0009    ISEQP    0   0
0010    JMP      0 => 0013
0011    KPRI     0   1
0012    JMP      1 => 0014
0013 => KPRI     0   2
0014 => RET1     0   2

-- BYTECODE -- readerfooter.lua:1056-1060
0001    UGET     0   0      ; self
0002    TGETS    0   0   0  ; "settings"
0003    KSTR     1   2      ; "bar"
0004    TSETS    1   0   1  ; "items_separator"
0005    UGET     0   0      ; self
0006    MOV      1   0
0007    TGETS    0   0   3  ; "updateFooter"
0008    CALL     0   1   2
0009    UGET     0   1      ; UIManager
0010    MOV      1   0
0011    TGETS    0   0   4  ; "setDirty"
0012    KPRI     2   0
0013    KSTR     3   5      ; "ui"
0014    CALL     0   1   4
0015    RET0     0   1

-- BYTECODE -- readerfooter.lua:1064-1066
0001    UGET     0   0      ; self
0002    TGETS    0   0   0  ; "settings"
0003    TGETS    0   0   1  ; "items_separator"
0004    ISEQS    0   2      ; "bullet"
0005    JMP      0 => 0008
0006    KPRI     0   1
0007    JMP      1 => 0009
0008 => KPRI     0   2
0009 => RET1     0   2

-- BYTECODE -- readerfooter.lua:1067-1071
0001    UGET     0   0      ; self
0002    TGETS    0   0   0  ; "settings"
0003    KSTR     1   2      ; "bullet"
0004    TSETS    1   0   1  ; "items_separator"
0005    UGET     0   0      ; self
0006    MOV      1   0
0007    TGETS    0   0   3  ; "updateFooter"
0008    CALL     0   1   2
0009    UGET     0   1      ; UIManager
0010    MOV      1   0
0011    TGETS    0   0   4  ; "setDirty"
0012    KPRI     2   0
0013    KSTR     3   5      ; "ui"
0014    CALL     0   1   4
0015    RET0     0   1

-- BYTECODE -- readerfooter.lua:1075-1077
0001    UGET     0   0      ; self
0002    TGETS    0   0   0  ; "settings"
0003    TGETS    0   0   1  ; "items_separator"
0004    ISEQS    0   2      ; "none"
0005    JMP      0 => 0008
0006    KPRI     0   1
0007    JMP      1 => 0009
0008 => KPRI     0   2
0009 => RET1     0   2

-- BYTECODE -- readerfooter.lua:1078-1082
0001    UGET     0   0      ; self
0002    TGETS    0   0   0  ; "settings"
0003    KSTR     1   2      ; "none"
0004    TSETS    1   0   1  ; "items_separator"
0005    UGET     0   0      ; self
0006    MOV      1   0
0007    TGETS    0   0   3  ; "updateFooter"
0008    CALL     0   1   2
0009    UGET     0   1      ; UIManager
0010    MOV      1   0
0011    TGETS    0   0   4  ; "setDirty"
0012    KPRI     2   0
0013    KSTR     3   5      ; "ui"
0014    CALL     0   1   4
0015    RET0     0   1

-- BYTECODE -- readerfooter.lua:1090-1092
0001    UGET     0   0      ; T
0002    UGET     1   1      ; _
0003    KSTR     2   0      ; "No decimal point (%1)"
0004    CALL     1   2   2
0005    UGET     2   2      ; self
0006    MOV      3   2
0007    TGETS    2   2   1  ; "progressPercentage"
0008    KSHORT   4   0
0009    CALL     2   0   3
0010    CALLMT   0   1

-- BYTECODE -- readerfooter.lua:1093-1095
0001    UGET     0   0      ; self
0002    TGETS    0   0   0  ; "settings"
0003    TGETS    0   0   1  ; "progress_pct_format"
0004    ISEQS    0   2      ; "0"
0005    JMP      0 => 0013
0006    UGET     0   0      ; self
0007    TGETS    0   0   0  ; "settings"
0008    TGETS    0   0   1  ; "progress_pct_format"
0009    ISEQP    0   0
0010    JMP      0 => 0013
0011    KPRI     0   1
0012    JMP      1 => 0014
0013 => KPRI     0   2
0014 => RET1     0   2

-- BYTECODE -- readerfooter.lua:1096-1100
0001    UGET     0   0      ; self
0002    TGETS    0   0   0  ; "settings"
0003    KSTR     1   2      ; "0"
0004    TSETS    1   0   1  ; "progress_pct_format"
0005    UGET     0   0      ; self
0006    MOV      1   0
0007    TGETS    0   0   3  ; "updateFooter"
0008    CALL     0   1   2
0009    UGET     0   1      ; UIManager
0010    MOV      1   0
0011    TGETS    0   0   4  ; "setDirty"
0012    KPRI     2   0
0013    KSTR     3   5      ; "ui"
0014    CALL     0   1   4
0015    RET0     0   1

-- BYTECODE -- readerfooter.lua:1103-1105
0001    UGET     0   0      ; T
0002    UGET     1   1      ; _
0003    KSTR     2   0      ; "1 digit after decimal point (%1)"
0004    CALL     1   2   2
0005    UGET     2   2      ; self
0006    MOV      3   2
0007    TGETS    2   2   1  ; "progressPercentage"
0008    KSHORT   4   1
0009    CALL     2   0   3
0010    CALLMT   0   1

-- BYTECODE -- readerfooter.lua:1106-1108
0001    UGET     0   0      ; self
0002    TGETS    0   0   0  ; "settings"
0003    TGETS    0   0   1  ; "progress_pct_format"
0004    ISEQS    0   2      ; "1"
0005    JMP      0 => 0008
0006    KPRI     0   1
0007    JMP      1 => 0009
0008 => KPRI     0   2
0009 => RET1     0   2

-- BYTECODE -- readerfooter.lua:1109-1113
0001    UGET     0   0      ; self
0002    TGETS    0   0   0  ; "settings"
0003    KSTR     1   2      ; "1"
0004    TSETS    1   0   1  ; "progress_pct_format"
0005    UGET     0   0      ; self
0006    MOV      1   0
0007    TGETS    0   0   3  ; "updateFooter"
0008    CALL     0   1   2
0009    UGET     0   1      ; UIManager
0010    MOV      1   0
0011    TGETS    0   0   4  ; "setDirty"
0012    KPRI     2   0
0013    KSTR     3   5      ; "ui"
0014    CALL     0   1   4
0015    RET0     0   1

-- BYTECODE -- readerfooter.lua:1116-1118
0001    UGET     0   0      ; T
0002    UGET     1   1      ; _
0003    KSTR     2   0      ; "2 digits after decimal point (%1)"
0004    CALL     1   2   2
0005    UGET     2   2      ; self
0006    MOV      3   2
0007    TGETS    2   2   1  ; "progressPercentage"
0008    KSHORT   4   2
0009    CALL     2   0   3
0010    CALLMT   0   1

-- BYTECODE -- readerfooter.lua:1119-1121
0001    UGET     0   0      ; self
0002    TGETS    0   0   0  ; "settings"
0003    TGETS    0   0   1  ; "progress_pct_format"
0004    ISEQS    0   2      ; "2"
0005    JMP      0 => 0008
0006    KPRI     0   1
0007    JMP      1 => 0009
0008 => KPRI     0   2
0009 => RET1     0   2

-- BYTECODE -- readerfooter.lua:1122-1126
0001    UGET     0   0      ; self
0002    TGETS    0   0   0  ; "settings"
0003    KSTR     1   2      ; "2"
0004    TSETS    1   0   1  ; "progress_pct_format"
0005    UGET     0   0      ; self
0006    MOV      1   0
0007    TGETS    0   0   3  ; "updateFooter"
0008    CALL     0   1   2
0009    UGET     0   1      ; UIManager
0010    MOV      1   0
0011    TGETS    0   0   4  ; "setDirty"
0012    KPRI     2   0
0013    KSTR     3   5      ; "ui"
0014    CALL     0   1   4
0015    RET0     0   1

-- BYTECODE -- readerfooter.lua:1134-1140
0001    TNEW     0   0
0002    TNEW     1   0
0003    TSETS    1   0   0  ; "settings"
0004    TGETS    1   0   0  ; "settings"
0005    KSTR     2   2      ; "24"
0006    TSETS    2   1   1  ; "time_format"
0007    TGETS    1   0   0  ; "settings"
0008    UGET     2   0      ; self
0009    TGETS    2   2   0  ; "settings"
0010    TGETS    2   2   3  ; "item_prefix"
0011    IST          2
0012    JMP      3 => 0014
0013    KSTR     2   4      ; "icons"
0014 => TSETS    2   1   3  ; "item_prefix"
0015    UGET     1   1      ; T
0016    UGET     2   2      ; _
0017    KSTR     3   5      ; "24-hour (%1)"
0018    CALL     2   2   2
0019    UGET     3   3      ; footerTextGeneratorMap
0020    TGETS    3   3   6  ; "time"
0021    MOV      4   0
0022    CALL     3   0   2
0023    CALLMT   1   1

-- BYTECODE -- readerfooter.lua:1141-1143
0001    UGET     0   0      ; self
0002    TGETS    0   0   0  ; "settings"
0003    TGETS    0   0   1  ; "time_format"
0004    ISEQS    0   2      ; "24"
0005    JMP      0 => 0013
0006    UGET     0   0      ; self
0007    TGETS    0   0   0  ; "settings"
0008    TGETS    0   0   1  ; "time_format"
0009    ISEQP    0   0
0010    JMP      0 => 0013
0011    KPRI     0   1
0012    JMP      1 => 0014
0013 => KPRI     0   2
0014 => RET1     0   2

-- BYTECODE -- readerfooter.lua:1144-1148
0001    UGET     0   0      ; self
0002    TGETS    0   0   0  ; "settings"
0003    KSTR     1   2      ; "24"
0004    TSETS    1   0   1  ; "time_format"
0005    UGET     0   0      ; self
0006    MOV      1   0
0007    TGETS    0   0   3  ; "updateFooter"
0008    CALL     0   1   2
0009    UGET     0   1      ; UIManager
0010    MOV      1   0
0011    TGETS    0   0   4  ; "setDirty"
0012    KPRI     2   0
0013    KSTR     3   5      ; "ui"
0014    CALL     0   1   4
0015    RET0     0   1

-- BYTECODE -- readerfooter.lua:1151-1157
0001    TNEW     0   0
0002    TNEW     1   0
0003    TSETS    1   0   0  ; "settings"
0004    TGETS    1   0   0  ; "settings"
0005    KSTR     2   2      ; "12"
0006    TSETS    2   1   1  ; "time_format"
0007    TGETS    1   0   0  ; "settings"
0008    UGET     2   0      ; self
0009    TGETS    2   2   0  ; "settings"
0010    TGETS    2   2   3  ; "item_prefix"
0011    IST          2
0012    JMP      3 => 0014
0013    KSTR     2   4      ; "icons"
0014 => TSETS    2   1   3  ; "item_prefix"
0015    UGET     1   1      ; T
0016    UGET     2   2      ; _
0017    KSTR     3   5      ; "12-hour (%1)"
0018    CALL     2   2   2
0019    UGET     3   3      ; footerTextGeneratorMap
0020    TGETS    3   3   6  ; "time"
0021    MOV      4   0
0022    CALL     3   0   2
0023    CALLMT   1   1

-- BYTECODE -- readerfooter.lua:1158-1160
0001    UGET     0   0      ; self
0002    TGETS    0   0   0  ; "settings"
0003    TGETS    0   0   1  ; "time_format"
0004    ISEQS    0   2      ; "12"
0005    JMP      0 => 0008
0006    KPRI     0   1
0007    JMP      1 => 0009
0008 => KPRI     0   2
0009 => RET1     0   2

-- BYTECODE -- readerfooter.lua:1161-1165
0001    UGET     0   0      ; self
0002    TGETS    0   0   0  ; "settings"
0003    KSTR     1   2      ; "12"
0004    TSETS    1   0   1  ; "time_format"
0005    UGET     0   0      ; self
0006    MOV      1   0
0007    TGETS    0   0   3  ; "updateFooter"
0008    CALL     0   1   2
0009    UGET     0   1      ; UIManager
0010    MOV      1   0
0011    TGETS    0   0   4  ; "setDirty"
0012    KPRI     2   0
0013    KSTR     3   5      ; "ui"
0014    CALL     0   1   4
0015    RET0     0   1

-- BYTECODE -- readerfooter.lua:1173-1180
0001    UGET     0   0      ; self
0002    TGETS    0   0   0  ; "settings"
0003    TGETS    0   0   1  ; "duration_format"
0004    KPRI     1   0
0005    UGET     2   0      ; self
0006    TGETS    2   2   0  ; "settings"
0007    KSTR     3   2      ; "modern"
0008    TSETS    3   2   1  ; "duration_format"
0009    UGET     2   1      ; footerTextGeneratorMap
0010    TGETS    2   2   3  ; "book_time_to_read"
0011    UGET     3   0      ; self
0012    CALL     2   2   2
0013    MOV      1   2
0014    UGET     2   0      ; self
0015    TGETS    2   2   0  ; "settings"
0016    TSETS    0   2   1  ; "duration_format"
0017    UGET     2   2      ; T
0018    UGET     3   3      ; _
0019    KSTR     4   4      ; "Modern (%1)"
0020    CALL     3   2   2
0021    MOV      4   1
0022    CALLT    2   3

-- BYTECODE -- readerfooter.lua:1181-1183
0001    UGET     0   0      ; self
0002    TGETS    0   0   0  ; "settings"
0003    TGETS    0   0   1  ; "duration_format"
0004    ISEQS    0   2      ; "modern"
0005    JMP      0 => 0013
0006    UGET     0   0      ; self
0007    TGETS    0   0   0  ; "settings"
0008    TGETS    0   0   1  ; "duration_format"
0009    ISEQP    0   0
0010    JMP      0 => 0013
0011    KPRI     0   1
0012    JMP      1 => 0014
0013 => KPRI     0   2
0014 => RET1     0   2

-- BYTECODE -- readerfooter.lua:1184-1188
0001    UGET     0   0      ; self
0002    TGETS    0   0   0  ; "settings"
0003    KSTR     1   2      ; "modern"
0004    TSETS    1   0   1  ; "duration_format"
0005    UGET     0   0      ; self
0006    MOV      1   0
0007    TGETS    0   0   3  ; "updateFooter"
0008    CALL     0   1   2
0009    UGET     0   1      ; UIManager
0010    MOV      1   0
0011    TGETS    0   0   4  ; "setDirty"
0012    KPRI     2   0
0013    KSTR     3   5      ; "ui"
0014    CALL     0   1   4
0015    RET0     0   1

-- BYTECODE -- readerfooter.lua:1191-1198
0001    UGET     0   0      ; self
0002    TGETS    0   0   0  ; "settings"
0003    TGETS    0   0   1  ; "duration_format"
0004    KPRI     1   0
0005    UGET     2   0      ; self
0006    TGETS    2   2   0  ; "settings"
0007    KSTR     3   2      ; "classic"
0008    TSETS    3   2   1  ; "duration_format"
0009    UGET     2   1      ; footerTextGeneratorMap
0010    TGETS    2   2   3  ; "book_time_to_read"
0011    UGET     3   0      ; self
0012    CALL     2   2   2
0013    MOV      1   2
0014    UGET     2   0      ; self
0015    TGETS    2   2   0  ; "settings"
0016    TSETS    0   2   1  ; "duration_format"
0017    UGET     2   2      ; T
0018    UGET     3   3      ; _
0019    KSTR     4   4      ; "Classic (%1)"
0020    CALL     3   2   2
0021    MOV      4   1
0022    CALLT    2   3

-- BYTECODE -- readerfooter.lua:1199-1201
0001    UGET     0   0      ; self
0002    TGETS    0   0   0  ; "settings"
0003    TGETS    0   0   1  ; "duration_format"
0004    ISEQS    0   2      ; "classic"
0005    JMP      0 => 0008
0006    KPRI     0   1
0007    JMP      1 => 0009
0008 => KPRI     0   2
0009 => RET1     0   2

-- BYTECODE -- readerfooter.lua:1202-1206
0001    UGET     0   0      ; self
0002    TGETS    0   0   0  ; "settings"
0003    KSTR     1   2      ; "classic"
0004    TSETS    1   0   1  ; "duration_format"
0005    UGET     0   0      ; self
0006    MOV      1   0
0007    TGETS    0   0   3  ; "updateFooter"
0008    CALL     0   1   2
0009    UGET     0   1      ; UIManager
0010    MOV      1   0
0011    TGETS    0   0   4  ; "setDirty"
0012    KPRI     2   0
0013    KSTR     3   5      ; "ui"
0014    CALL     0   1   4
0015    RET0     0   1

-- BYTECODE -- readerfooter.lua:1218-1220
0001    UGET     0   0      ; self
0002    TGETS    0   0   0  ; "settings"
0003    TGETS    0   0   1  ; "disable_progress_bar"
0004    NOT      0   0
0005    RET1     0   2

-- BYTECODE -- readerfooter.lua:1221-1231
0001    UGET     0   0      ; self
0002    TGETS    0   0   0  ; "settings"
0003    UGET     1   0      ; self
0004    TGETS    1   1   0  ; "settings"
0005    TGETS    1   1   1  ; "disable_progress_bar"
0006    NOT      1   1
0007    TSETS    1   0   1  ; "disable_progress_bar"
0008    UGET     0   0      ; self
0009    TGETS    0   0   0  ; "settings"
0010    TGETS    0   0   1  ; "disable_progress_bar"
0011    IST          0
0012    JMP      0 => 0037
0013    UGET     0   0      ; self
0014    TGETS    0   0   2  ; "footer_container"
0015    TGETS    0   0   3  ; "dimen"
0016    UGET     1   0      ; self
0017    TGETS    1   1   5  ; "height"
0018    TSETS    1   0   4  ; "h"
0019    UGET     0   0      ; self
0020    TGETS    0   0   6  ; "footer_text"
0021    UGET     1   0      ; self
0022    TGETS    1   1   5  ; "height"
0023    TSETS    1   0   5  ; "height"
0024    UGET     0   0      ; self
0025    MOV      1   0
0026    TGETS    0   0   7  ; "setTocMarkers"
0027    CALL     0   1   2
0028    UGET     0   0      ; self
0029    UGET     1   0      ; self
0030    TGETS    1   1   9  ; "mode_list"
0031    TGETS    1   1  10  ; "page_progress"
0032    TSETS    1   0   8  ; "mode"
0033    UGET     0   0      ; self
0034    MOV      1   0
0035    TGETS    0   0  11  ; "applyFooterMode"
0036    CALL     0   1   2
0037 => UGET     0   0      ; self
0038    MOV      1   0
0039    TGETS    0   0  12  ; "refreshFooter"
0040    KPRI     2   2
0041    KPRI     3   2
0042    CALL     0   1   4
0043    RET0     0   1

-- BYTECODE -- readerfooter.lua:1234-1242
0001    UGET     0   0      ; _
0002    KSTR     1   0      ; "alongside items"
0003    CALL     0   2   2
0004    UGET     1   1      ; self
0005    TGETS    1   1   1  ; "settings"
0006    TGETS    1   1   2  ; "progress_bar_position"
0007    ISNES    1   3      ; "above"
0008    JMP      1 => 0014
0009    UGET     1   0      ; _
0010    KSTR     2   4      ; "above items"
0011    CALL     1   2   2
0012    MOV      0   1
0013    JMP      1 => 0023
0014 => UGET     1   1      ; self
0015    TGETS    1   1   1  ; "settings"
0016    TGETS    1   1   2  ; "progress_bar_position"
0017    ISNES    1   5      ; "below"
0018    JMP      1 => 0023
0019    UGET     1   0      ; _
0020    KSTR     2   6      ; "below items"
0021    CALL     1   2   2
0022    MOV      0   1
0023 => UGET     1   2      ; T
0024    UGET     2   0      ; _
0025    KSTR     3   7      ; "Position: %1"
0026    CALL     2   2   2
0027    MOV      3   0
0028    CALLT    1   3

-- BYTECODE -- readerfooter.lua:1243-1245
0001    UGET     0   0      ; self
0002    TGETS    0   0   0  ; "settings"
0003    TGETS    0   0   1  ; "disable_progress_bar"
0004    NOT      0   0
0005    RET1     0   2

-- BYTECODE -- readerfooter.lua:1249-1251
0001    UGET     0   0      ; self
0002    TGETS    0   0   0  ; "settings"
0003    TGETS    0   0   1  ; "progress_bar_position"
0004    ISEQS    0   2      ; "above"
0005    JMP      0 => 0008
0006    KPRI     0   1
0007    JMP      1 => 0009
0008 => KPRI     0   2
0009 => RET1     0   2

-- BYTECODE -- readerfooter.lua:1252-1255
0001    UGET     0   0      ; self
0002    TGETS    0   0   0  ; "settings"
0003    KSTR     1   2      ; "above"
0004    TSETS    1   0   1  ; "progress_bar_position"
0005    UGET     0   0      ; self
0006    MOV      1   0
0007    TGETS    0   0   3  ; "refreshFooter"
0008    KPRI     2   2
0009    KPRI     3   2
0010    CALL     0   1   4
0011    RET0     0   1

-- BYTECODE -- readerfooter.lua:1259-1261
0001    UGET     0   0      ; self
0002    TGETS    0   0   0  ; "settings"
0003    TGETS    0   0   1  ; "progress_bar_position"
0004    ISEQS    0   2      ; "below"
0005    JMP      0 => 0008
0006    KPRI     0   1
0007    JMP      1 => 0009
0008 => KPRI     0   2
0009 => RET1     0   2

-- BYTECODE -- readerfooter.lua:1262-1265
0001    UGET     0   0      ; self
0002    TGETS    0   0   0  ; "settings"
0003    KSTR     1   2      ; "below"
0004    TSETS    1   0   1  ; "progress_bar_position"
0005    UGET     0   0      ; self
0006    MOV      1   0
0007    TGETS    0   0   3  ; "refreshFooter"
0008    KPRI     2   2
0009    KPRI     3   2
0010    CALL     0   1   4
0011    RET0     0   1

-- BYTECODE -- readerfooter.lua:1269-1271
0001    UGET     0   0      ; self
0002    TGETS    0   0   0  ; "settings"
0003    TGETS    0   0   1  ; "progress_bar_position"
0004    NOT      0   0
0005    RET1     0   2

-- BYTECODE -- readerfooter.lua:1272-1279
0001    UGET     0   0      ; self
0002    TGETS    0   0   0  ; "settings"
0003    TGETS    0   0   1  ; "progress_margin"
0004    ISF          0
0005    JMP      1 => 0018
0006    UGET     0   0      ; self
0007    TGETS    0   0   0  ; "settings"
0008    KPRI     1   1
0009    TSETS    1   0   1  ; "progress_margin"
0010    UGET     0   0      ; self
0011    TGETS    0   0   0  ; "settings"
0012    UGET     1   1      ; Screen
0013    MOV      2   1
0014    TGETS    1   1   3  ; "scaleBySize"
0015    KSHORT   3  10
0016    CALL     1   2   3
0017    TSETS    1   0   2  ; "progress_margin_width"
0018 => UGET     0   0      ; self
0019    TGETS    0   0   0  ; "settings"
0020    KPRI     1   0
0021    TSETS    1   0   4  ; "progress_bar_position"
0022    UGET     0   0      ; self
0023    MOV      1   0
0024    TGETS    0   0   5  ; "refreshFooter"
0025    KPRI     2   2
0026    KPRI     3   2
0027    CALL     0   1   4
0028    RET0     0   1

-- BYTECODE -- readerfooter.lua:1284-1290
0001    UGET     0   0      ; self
0002    TGETS    0   0   0  ; "settings"
0003    TGETS    0   0   1  ; "progress_style_thin"
0004    ISF          0
0005    JMP      1 => 0010
0006    UGET     0   1      ; _
0007    KSTR     1   2      ; "Style: thin"
0008    CALLT    0   2
0009    JMP      0 => 0013
0010 => UGET     0   1      ; _
0011    KSTR     1   3      ; "Style: thick"
0012    CALLT    0   2
0013 => RET0     0   1

-- BYTECODE -- readerfooter.lua:1291-1293
0001    UGET     0   0      ; self
0002    TGETS    0   0   0  ; "settings"
0003    TGETS    0   0   1  ; "disable_progress_bar"
0004    NOT      0   0
0005    RET1     0   2

-- BYTECODE -- readerfooter.lua:1297-1299
0001    UGET     0   0      ; self
0002    TGETS    0   0   0  ; "settings"
0003    TGETS    0   0   1  ; "progress_style_thin"
0004    NOT      0   0
0005    RET1     0   2

-- BYTECODE -- readerfooter.lua:1300-1306
0001    UGET     0   0      ; self
0002    TGETS    0   0   0  ; "settings"
0003    KPRI     1   0
0004    TSETS    1   0   1  ; "progress_style_thin"
0005    UGET     0   0      ; self
0006    TGETS    0   0   0  ; "settings"
0007    TGETS    0   0   2  ; "progress_style_thick_height"
0008    IST          0
0009    JMP      1 => 0011
0010    UGET     0   1      ; PROGRESS_BAR_STYLE_THICK_DEFAULT_HEIGHT
0011 => UGET     1   0      ; self
0012    TGETS    1   1   3  ; "progress_bar"
0013    MOV      2   1
0014    TGETS    1   1   4  ; "updateStyle"
0015    KPRI     3   2
0016    MOV      4   0
0017    CALL     1   1   4
0018    UGET     1   0      ; self
0019    MOV      2   1
0020    TGETS    1   1   5  ; "setTocMarkers"
0021    CALL     1   1   2
0022    UGET     1   0      ; self
0023    MOV      2   1
0024    TGETS    1   1   6  ; "refreshFooter"
0025    KPRI     3   2
0026    KPRI     4   2
0027    CALL     1   1   4
0028    RET0     0   1

-- BYTECODE -- readerfooter.lua:1310-1312
0001    UGET     0   0      ; self
0002    TGETS    0   0   0  ; "settings"
0003    TGETS    0   0   1  ; "progress_style_thin"
0004    RET1     0   2

-- BYTECODE -- readerfooter.lua:1313-1318
0001    UGET     0   0      ; self
0002    TGETS    0   0   0  ; "settings"
0003    KPRI     1   2
0004    TSETS    1   0   1  ; "progress_style_thin"
0005    UGET     0   0      ; self
0006    TGETS    0   0   0  ; "settings"
0007    TGETS    0   0   2  ; "progress_style_thin_height"
0008    IST          0
0009    JMP      1 => 0011
0010    UGET     0   1      ; PROGRESS_BAR_STYLE_THIN_DEFAULT_HEIGHT
0011 => UGET     1   0      ; self
0012    TGETS    1   1   3  ; "progress_bar"
0013    MOV      2   1
0014    TGETS    1   1   4  ; "updateStyle"
0015    KPRI     3   1
0016    MOV      4   0
0017    CALL     1   1   4
0018    UGET     1   0      ; self
0019    MOV      2   1
0020    TGETS    1   1   5  ; "refreshFooter"
0021    KPRI     3   2
0022    KPRI     4   2
0023    CALL     1   1   4
0024    RET0     0   1

-- BYTECODE -- readerfooter.lua:1346-1353
0001    UGET     1   0      ; self
0002    TGETS    1   1   0  ; "settings"
0003    TGETS    1   1   1  ; "progress_style_thin"
0004    ISF          1
0005    JMP      2 => 0011
0006    UGET     1   0      ; self
0007    TGETS    1   1   0  ; "settings"
0008    TGETS    2   0   3  ; "value"
0009    TSETS    2   1   2  ; "progress_style_thin_height"
0010    JMP      1 => 0015
0011 => UGET     1   0      ; self
0012    TGETS    1   1   0  ; "settings"
0013    TGETS    2   0   3  ; "value"
0014    TSETS    2   1   4  ; "progress_style_thick_height"
0015 => UGET     1   0      ; self
0016    MOV      2   1
0017    TGETS    1   1   5  ; "refreshFooter"
0018    KPRI     3   2
0019    KPRI     4   2
0020    CALL     1   1   4
0021    RET0     0   1

-- BYTECODE -- readerfooter.lua:1322-1356
0001    KNIL     0   3
0002    UGET     4   0      ; self
0003    TGETS    4   4   0  ; "settings"
0004    TGETS    4   4   1  ; "progress_style_thin"
0005    ISF          4
0006    JMP      5 => 0017
0007    UGET     3   1      ; PROGRESS_BAR_STYLE_THIN_DEFAULT_HEIGHT
0008    UGET     4   0      ; self
0009    TGETS    4   4   0  ; "settings"
0010    TGETS    4   4   2  ; "progress_style_thin_height"
0011    ISTC     0   4
0012    JMP      5 => 0014
0013    MOV      0   3
0014 => KSHORT   1   1
0015    KSHORT   2   4
0016    JMP      4 => 0026
0017 => UGET     3   2      ; PROGRESS_BAR_STYLE_THICK_DEFAULT_HEIGHT
0018    UGET     4   0      ; self
0019    TGETS    4   4   0  ; "settings"
0020    TGETS    4   4   3  ; "progress_style_thick_height"
0021    ISTC     0   4
0022    JMP      5 => 0024
0023    MOV      0   3
0024 => KSHORT   1   5
0025    KSHORT   2  14
0026 => GGET     4   4      ; "require"
0027    KSTR     5   5      ; "ui/widget/spinwidget"
0028    CALL     4   2   2
0029    MOV      6   4
0030    TGETS    5   4   6  ; "new"
0031    TDUP     7   8
0032    UGET     8   3      ; Screen
0033    MOV      9   8
0034    TGETS    8   8   7  ; "getWidth"
0035    CALL     8   2   2
0036    MULVN    8   8   0  ; 0.6
0037    TSETS    8   7   9  ; "width"
0038    TSETS    0   7  10  ; "value"
0039    TSETS    1   7  11  ; "value_min"
0040    TSETS    2   7  12  ; "value_max"
0041    TSETS    3   7  13  ; "default_value"
0042    UGET     8   4      ; _
0043    KSTR     9  14      ; "Progress bar size"
0044    CALL     8   2   2
0045    TSETS    8   7  15  ; "title_text"
0046    FNEW     8  16      ; readerfooter.lua:1346
0047    TSETS    8   7  17  ; "callback"
0048    CALL     5   2   3
0049    UGET     6   5      ; UIManager
0050    MOV      7   6
0051    TGETS    6   6  18  ; "show"
0052    MOV      8   5
0053    CALL     6   1   3
0054    RET0     0   1

-- BYTECODE -- readerfooter.lua:1362-1364
0001    UGET     0   0      ; self
0002    TGETS    0   0   0  ; "settings"
0003    TGETS    0   0   1  ; "toc_markers"
0004    RET1     0   2

-- BYTECODE -- readerfooter.lua:1365-1367
0001    UGET     0   0      ; self
0002    TGETS    0   0   0  ; "settings"
0003    TGETS    0   0   1  ; "progress_style_thin"
0004    NOT      0   0
0005    RET1     0   2

-- BYTECODE -- readerfooter.lua:1368-1372
0001    UGET     0   0      ; self
0002    TGETS    0   0   0  ; "settings"
0003    UGET     1   0      ; self
0004    TGETS    1   1   0  ; "settings"
0005    TGETS    1   1   1  ; "toc_markers"
0006    NOT      1   1
0007    TSETS    1   0   1  ; "toc_markers"
0008    UGET     0   0      ; self
0009    MOV      1   0
0010    TGETS    0   0   2  ; "setTocMarkers"
0011    CALL     0   1   2
0012    UGET     0   0      ; self
0013    MOV      1   0
0014    TGETS    0   0   3  ; "refreshFooter"
0015    KPRI     2   2
0016    CALL     0   1   3
0017    RET0     0   1

-- BYTECODE -- readerfooter.lua:1375-1383
0001    UGET     0   0      ; _
0002    KSTR     1   0      ; "thick"
0003    CALL     0   2   2
0004    UGET     1   1      ; self
0005    TGETS    1   1   1  ; "settings"
0006    TGETS    1   1   2  ; "toc_markers_width"
0007    ISNEN    1   0      ; 1
0008    JMP      1 => 0014
0009    UGET     1   0      ; _
0010    KSTR     2   3      ; "thin"
0011    CALL     1   2   2
0012    MOV      0   1
0013    JMP      1 => 0023
0014 => UGET     1   1      ; self
0015    TGETS    1   1   1  ; "settings"
0016    TGETS    1   1   2  ; "toc_markers_width"
0017    ISNEN    1   1      ; 2
0018    JMP      1 => 0023
0019    UGET     1   0      ; _
0020    KSTR     2   4      ; "medium"
0021    CALL     1   2   2
0022    MOV      0   1
0023 => UGET     1   2      ; T
0024    UGET     2   0      ; _
0025    KSTR     3   5      ; "Chapter marker width (%1)"
0026    CALL     2   2   2
0027    MOV      3   0
0028    CALLT    1   3

-- BYTECODE -- readerfooter.lua:1384-1386
0001    UGET     0   0      ; self
0002    TGETS    0   0   0  ; "settings"
0003    TGETS    0   0   1  ; "progress_style_thin"
0004    IST          0
0005    JMP      0 => 0010
0006    UGET     0   0      ; self
0007    TGETS    0   0   0  ; "settings"
0008    TGETS    0   0   2  ; "toc_markers"
0009    JMP      1 => 0013
0010 => KPRI     0   1
0011    JMP      1 => 0013
0012    KPRI     0   2
0013 => RET1     0   2

-- BYTECODE -- readerfooter.lua:1390-1392
0001    UGET     0   0      ; self
0002    TGETS    0   0   0  ; "settings"
0003    TGETS    0   0   1  ; "toc_markers_width"
0004    ISEQN    0   0      ; 1
0005    JMP      0 => 0008
0006    KPRI     0   1
0007    JMP      1 => 0009
0008 => KPRI     0   2
0009 => RET1     0   2

-- BYTECODE -- readerfooter.lua:1393-1397
0001    UGET     0   0      ; self
0002    TGETS    0   0   0  ; "settings"
0003    KSHORT   1   1
0004    TSETS    1   0   1  ; "toc_markers_width"
0005    UGET     0   0      ; self
0006    MOV      1   0
0007    TGETS    0   0   2  ; "setTocMarkers"
0008    CALL     0   1   2
0009    UGET     0   0      ; self
0010    MOV      1   0
0011    TGETS    0   0   3  ; "refreshFooter"
0012    KPRI     2   2
0013    CALL     0   1   3
0014    RET0     0   1

-- BYTECODE -- readerfooter.lua:1401-1403
0001    UGET     0   0      ; self
0002    TGETS    0   0   0  ; "settings"
0003    TGETS    0   0   1  ; "toc_markers_width"
0004    ISEQN    0   0      ; 2
0005    JMP      0 => 0008
0006    KPRI     0   1
0007    JMP      1 => 0009
0008 => KPRI     0   2
0009 => RET1     0   2

-- BYTECODE -- readerfooter.lua:1404-1408
0001    UGET     0   0      ; self
0002    TGETS    0   0   0  ; "settings"
0003    KSHORT   1   2
0004    TSETS    1   0   1  ; "toc_markers_width"
0005    UGET     0   0      ; self
0006    MOV      1   0
0007    TGETS    0   0   2  ; "setTocMarkers"
0008    CALL     0   1   2
0009    UGET     0   0      ; self
0010    MOV      1   0
0011    TGETS    0   0   3  ; "refreshFooter"
0012    KPRI     2   2
0013    CALL     0   1   3
0014    RET0     0   1

-- BYTECODE -- readerfooter.lua:1412-1414
0001    UGET     0   0      ; self
0002    TGETS    0   0   0  ; "settings"
0003    TGETS    0   0   1  ; "toc_markers_width"
0004    ISEQN    0   0      ; 3
0005    JMP      0 => 0008
0006    KPRI     0   1
0007    JMP      1 => 0009
0008 => KPRI     0   2
0009 => RET1     0   2

-- BYTECODE -- readerfooter.lua:1415-1419
0001    UGET     0   0      ; self
0002    TGETS    0   0   0  ; "settings"
0003    KSHORT   1   3
0004    TSETS    1   0   1  ; "toc_markers_width"
0005    UGET     0   0      ; self
0006    MOV      1   0
0007    TGETS    0   0   2  ; "setTocMarkers"
0008    CALL     0   1   2
0009    UGET     0   0      ; self
0010    MOV      1   0
0011    TGETS    0   0   3  ; "refreshFooter"
0012    KPRI     2   2
0013    CALL     0   1   3
0014    RET0     0   1

-- BYTECODE -- readerfooter.lua:1426-1435
0001    UGET     0   0      ; _
0002    KSTR     1   0      ; "static margins (10)"
0003    CALL     0   2   2
0004    UGET     1   1      ; self
0005    TGETS    1   1   1  ; "settings"
0006    TGETS    1   1   2  ; "progress_margin_width"
0007    UGET     2   2      ; Screen
0008    MOV      3   2
0009    TGETS    2   2   3  ; "scaleBySize"
0010    KSHORT   4   0
0011    CALL     2   2   3
0012    ISNEV    1   2
0013    JMP      1 => 0018
0014    UGET     1   0      ; _
0015    KSTR     2   4      ; "no margins (0)"
0016    CALL     1   2   2
0017    MOV      0   1
0018 => UGET     1   1      ; self
0019    TGETS    1   1   1  ; "settings"
0020    TGETS    1   1   5  ; "progress_margin"
0021    ISF          1
0022    JMP      2 => 0038
0023    UGET     1   1      ; self
0024    TGETS    1   1   6  ; "ui"
0025    TGETS    1   1   7  ; "document"
0026    TGETS    1   1   8  ; "info"
0027    TGETS    1   1   9  ; "has_pages"
0028    IST          1
0029    JMP      1 => 0038
0030    UGET     1   3      ; T
0031    UGET     2   0      ; _
0032    KSTR     3  10      ; "same as book margins (%1)"
0033    CALL     2   2   2
0034    UGET     3   1      ; self
0035    TGETS    3   3  11  ; "book_margins_footer_width"
0036    CALL     1   2   3
0037    MOV      0   1
0038 => UGET     1   3      ; T
0039    UGET     2   0      ; _
0040    KSTR     3  12      ; "Margins: %1"
0041    CALL     2   2   2
0042    MOV      3   0
0043    CALLT    1   3

-- BYTECODE -- readerfooter.lua:1436-1438
0001    UGET     0   0      ; self
0002    TGETS    0   0   0  ; "settings"
0003    TGETS    0   0   1  ; "disable_progress_bar"
0004    NOT      0   0
0005    RET1     0   2

-- BYTECODE -- readerfooter.lua:1442-1445
0001    UGET     0   0      ; self
0002    TGETS    0   0   0  ; "settings"
0003    TGETS    0   0   1  ; "progress_margin_width"
0004    UGET     1   1      ; Screen
0005    MOV      2   1
0006    TGETS    1   1   2  ; "scaleBySize"
0007    KSHORT   3   0
0008    CALL     1   2   3
0009    ISNEV    0   1
0010    JMP      0 => 0016
0011    UGET     0   0      ; self
0012    TGETS    0   0   0  ; "settings"
0013    TGETS    0   0   3  ; "progress_margin"
0014    NOT      0   0
0015    JMP      1 => 0019
0016 => KPRI     0   1
0017    JMP      1 => 0019
0018    KPRI     0   2
0019 => RET1     0   2

-- BYTECODE -- readerfooter.lua:1446-1450
0001    UGET     0   0      ; self
0002    TGETS    0   0   0  ; "settings"
0003    UGET     1   1      ; Screen
0004    MOV      2   1
0005    TGETS    1   1   2  ; "scaleBySize"
0006    KSHORT   3   0
0007    CALL     1   2   3
0008    TSETS    1   0   1  ; "progress_margin_width"
0009    UGET     0   0      ; self
0010    TGETS    0   0   0  ; "settings"
0011    KPRI     1   1
0012    TSETS    1   0   3  ; "progress_margin"
0013    UGET     0   0      ; self
0014    MOV      1   0
0015    TGETS    0   0   4  ; "refreshFooter"
0016    KPRI     2   2
0017    CALL     0   1   3
0018    RET0     0   1

-- BYTECODE -- readerfooter.lua:1454-1459
0001    UGET     0   0      ; self
0002    TGETS    0   0   0  ; "settings"
0003    TGETS    0   0   1  ; "progress_margin_width"
0004    UGET     1   1      ; Screen
0005    MOV      2   1
0006    TGETS    1   1   2  ; "scaleBySize"
0007    KSHORT   3  10
0008    CALL     1   2   3
0009    ISNEV    0   1
0010    JMP      0 => 0016
0011    UGET     0   0      ; self
0012    TGETS    0   0   0  ; "settings"
0013    TGETS    0   0   3  ; "progress_margin"
0014    ISF          0
0015    JMP      0 => 0029
0016 => UGET     0   0      ; self
0017    TGETS    0   0   4  ; "ui"
0018    TGETS    0   0   5  ; "document"
0019    TGETS    0   0   6  ; "info"
0020    TGETS    0   0   7  ; "has_pages"
0021    ISF          0
0022    JMP      1 => 0030
0023    UGET     0   0      ; self
0024    TGETS    0   0   0  ; "settings"
0025    TGETS    0   0   3  ; "progress_margin"
0026    JMP      1 => 0030
0027    KPRI     0   1
0028    JMP      1 => 0030
0029 => KPRI     0   2
0030 => RET1     0   2

-- BYTECODE -- readerfooter.lua:1460-1464
0001    UGET     0   0      ; self
0002    TGETS    0   0   0  ; "settings"
0003    UGET     1   1      ; Screen
0004    MOV      2   1
0005    TGETS    1   1   2  ; "scaleBySize"
0006    KSHORT   3  10
0007    CALL     1   2   3
0008    TSETS    1   0   1  ; "progress_margin_width"
0009    UGET     0   0      ; self
0010    TGETS    0   0   0  ; "settings"
0011    KPRI     1   1
0012    TSETS    1   0   3  ; "progress_margin"
0013    UGET     0   0      ; self
0014    MOV      1   0
0015    TGETS    0   0   4  ; "refreshFooter"
0016    KPRI     2   2
0017    CALL     0   1   3
0018    RET0     0   1

-- BYTECODE -- readerfooter.lua:1467-1472
0001    UGET     0   0      ; self
0002    TGETS    0   0   0  ; "ui"
0003    TGETS    0   0   1  ; "document"
0004    TGETS    0   0   2  ; "info"
0005    TGETS    0   0   3  ; "has_pages"
0006    ISF          0
0007    JMP      1 => 0011
0008    UGET     0   1      ; _
0009    KSTR     1   4      ; "Same as book margins"
0010    CALLT    0   2
0011 => UGET     0   2      ; T
0012    UGET     1   1      ; _
0013    KSTR     2   5      ; "Same as book margins (%1)"
0014    CALL     1   2   2
0015    UGET     2   0      ; self
0016    TGETS    2   2   6  ; "book_margins_footer_width"
0017    CALLT    0   3

-- BYTECODE -- readerfooter.lua:1473-1475
0001    UGET     0   0      ; self
0002    TGETS    0   0   0  ; "settings"
0003    TGETS    0   0   1  ; "progress_margin"
0004    ISF          0
0005    JMP      1 => 0012
0006    UGET     0   0      ; self
0007    TGETS    0   0   2  ; "ui"
0008    TGETS    0   0   3  ; "document"
0009    TGETS    0   0   4  ; "info"
0010    TGETS    0   0   5  ; "has_pages"
0011    NOT      0   0
0012 => RET1     0   2

-- BYTECODE -- readerfooter.lua:1476-1478
0001    UGET     0   0      ; self
0002    TGETS    0   0   0  ; "ui"
0003    TGETS    0   0   1  ; "document"
0004    TGETS    0   0   2  ; "info"
0005    TGETS    0   0   3  ; "has_pages"
0006    IST          0
0007    JMP      0 => 0013
0008    UGET     0   0      ; self
0009    TGETS    0   0   4  ; "settings"
0010    TGETS    0   0   5  ; "progress_bar_position"
0011    ISNEP    0   0
0012    JMP      0 => 0015
0013 => KPRI     0   1
0014    JMP      1 => 0016
0015 => KPRI     0   2
0016 => RET1     0   2

-- BYTECODE -- readerfooter.lua:1479-1483
0001    UGET     0   0      ; self
0002    TGETS    0   0   0  ; "settings"
0003    KPRI     1   2
0004    TSETS    1   0   1  ; "progress_margin"
0005    UGET     0   0      ; self
0006    TGETS    0   0   0  ; "settings"
0007    UGET     1   1      ; Screen
0008    MOV      2   1
0009    TGETS    1   1   3  ; "scaleBySize"
0010    UGET     3   0      ; self
0011    TGETS    3   3   4  ; "book_margins_footer_width"
0012    CALL     1   2   3
0013    TSETS    1   0   2  ; "progress_margin_width"
0014    UGET     0   0      ; self
0015    MOV      1   0
0016    TGETS    0   0   5  ; "refreshFooter"
0017    KPRI     2   2
0018    CALL     0   1   3
0019    RET0     0   1

-- BYTECODE -- readerfooter.lua:1488-1490
0001    UGET     0   0      ; T
0002    UGET     1   1      ; _
0003    KSTR     2   0      ; "Minimal width (%1%)"
0004    CALL     1   2   2
0005    UGET     2   2      ; self
0006    TGETS    2   2   1  ; "settings"
0007    TGETS    2   2   2  ; "progress_bar_min_width_pct"
0008    CALLT    0   3

-- BYTECODE -- readerfooter.lua:1491-1494
0001    UGET     0   0      ; self
0002    TGETS    0   0   0  ; "settings"
0003    TGETS    0   0   1  ; "progress_bar_position"
0004    IST          0
0005    JMP      0 => 0015
0006    UGET     0   0      ; self
0007    TGETS    0   0   0  ; "settings"
0008    TGETS    0   0   2  ; "disable_progress_bar"
0009    IST          0
0010    JMP      0 => 0015
0011    UGET     0   0      ; self
0012    TGETS    0   0   0  ; "settings"
0013    TGETS    0   0   3  ; "all_at_once"
0014    JMP      1 => 0018
0015 => KPRI     0   1
0016    JMP      1 => 0018
0017    KPRI     0   2
0018 => RET1     0   2

-- BYTECODE -- readerfooter.lua:1507-1511
0001    UGET     1   0      ; self
0002    TGETS    1   1   0  ; "settings"
0003    TGETS    2   0   2  ; "value"
0004    TSETS    2   1   1  ; "progress_bar_min_width_pct"
0005    UGET     1   0      ; self
0006    MOV      2   1
0007    TGETS    1   1   3  ; "refreshFooter"
0008    KPRI     3   2
0009    KPRI     4   2
0010    CALL     1   1   4
0011    UGET     1   1      ; touchmenu_instance
0012    ISF          1
0013    JMP      2 => 0018
0014    UGET     1   1      ; touchmenu_instance
0015    MOV      2   1
0016    TGETS    1   1   4  ; "updateItems"
0017    CALL     1   1   2
0018 => RET0     0   1

-- BYTECODE -- readerfooter.lua:1495-1514
0001    GGET     1   0      ; "require"
0002    KSTR     2   1      ; "ui/widget/spinwidget"
0003    CALL     1   2   2
0004    MOV      3   1
0005    TGETS    2   1   2  ; "new"
0006    TDUP     4   4
0007    UGET     5   0      ; Screen
0008    MOV      6   5
0009    TGETS    5   5   3  ; "getWidth"
0010    CALL     5   2   2
0011    MULVN    5   5   0  ; 0.6
0012    TSETS    5   4   5  ; "width"
0013    UGET     5   1      ; self
0014    TGETS    5   5   6  ; "settings"
0015    TGETS    5   5   7  ; "progress_bar_min_width_pct"
0016    TSETS    5   4   8  ; "value"
0017    UGET     5   2      ; _
0018    KSTR     6   9      ; "Minimal width"
0019    CALL     5   2   2
0020    TSETS    5   4  10  ; "title_text"
0021    UGET     5   2      ; _
0022    KSTR     6  11      ; "Minimal progress bar width in percentage"~
0023    CALL     5   2   2
0024    TSETS    5   4  12  ; "text"
0025    FNEW     5  13      ; readerfooter.lua:1507
0026    TSETS    5   4  14  ; "callback"
0027    CALL     2   2   3
0028    UGET     3   3      ; UIManager
0029    MOV      4   3
0030    TGETS    3   3  15  ; "show"
0031    MOV      5   2
0032    CALL     3   1   3
0033    UCLO     0 => 0034
0034 => RET0     0   1

-- BYTECODE -- readerfooter.lua:690-1535
0001    TNEW     2   0
0002    TDUP     3   2
0003    UGET     4   0      ; _
0004    KSTR     5   1      ; "Status bar"
0005    CALL     4   2   2
0006    TSETS    4   3   3  ; "text"
0007    TSETS    2   3   4  ; "sub_item_table"
0008    TSETS    3   1   0  ; "status_bar"
0009    UGET     3   1      ; Geom
0010    MOV      4   3
0011    TGETS    3   3   5  ; "new"
0012    TDUP     5   8
0013    GGET     6   6      ; "DTAP_ZONE_MINIBAR"
0014    TGETS    6   6   7  ; "x"
0015    TSETS    6   5   7  ; "x"
0016    GGET     6   6      ; "DTAP_ZONE_MINIBAR"
0017    TGETS    6   6   9  ; "y"
0018    TSETS    6   5   9  ; "y"
0019    GGET     6   6      ; "DTAP_ZONE_MINIBAR"
0020    TGETS    6   6  10  ; "w"
0021    TSETS    6   5  10  ; "w"
0022    GGET     6   6      ; "DTAP_ZONE_MINIBAR"
0023    TGETS    6   6  11  ; "h"
0024    TSETS    6   5  11  ; "h"
0025    CALL     3   2   3
0026    MOV      4   3
0027    TGETS    3   3  12  ; "area"
0028    CALL     3   2   2
0029    ISNEN    3   0      ; 0
0030    JMP      3 => 0044
0031    GGET     3  13      ; "table"
0032    TGETS    3   3  14  ; "insert"
0033    MOV      4   2
0034    TDUP     5  16
0035    UGET     6   0      ; _
0036    KSTR     7  15      ; "Toggle mode"
0037    CALL     6   2   2
0038    TSETS    6   5   3  ; "text"
0039    FNEW     6  17      ; readerfooter.lua:706
0040    TSETS    6   5  18  ; "enabled_func"
0041    FNEW     6  19      ; readerfooter.lua:709
0042    TSETS    6   5  20  ; "callback"
0043    CALL     3   1   3
0044 => FNEW     3  21      ; readerfooter.lua:713
0045    GGET     4  13      ; "table"
0046    TGETS    4   4  14  ; "insert"
0047    MOV      5   2
0048    TDUP     6  23
0049    UGET     7   0      ; _
0050    KSTR     8  22      ; "Settings"
0051    CALL     7   2   2
0052    TSETS    7   6   3  ; "text"
0053    TNEW     7  15
0054    TDUP     8  25
0055    UGET     9   0      ; _
0056    KSTR    10  24      ; "Sort items"
0057    CALL     9   2   2
0058    TSETS    9   8   3  ; "text"
0059    FNEW     9  26      ; readerfooter.lua:793
0060    TSETS    9   8  20  ; "callback"
0061    TSETB    8   7   1
0062    MOV      8   3
0063    KSTR     9  27      ; "all_at_once"
0064    TGETS   10   0  28  ; "updateFooterTextGenerator"
0065    CALL     8   2   3
0066    TSETB    8   7   2
0067    MOV      8   3
0068    KSTR     9  29      ; "reclaim_height"
0069    CALL     8   2   2
0070    TSETB    8   7   3
0071    TDUP     8  31
0072    UGET     9   0      ; _
0073    KSTR    10  30      ; "Auto refresh time"
0074    CALL     9   2   2
0075    TSETS    9   8   3  ; "text"
0076    FNEW     9  32      ; readerfooter.lua:821
0077    TSETS    9   8  33  ; "checked_func"
0078    FNEW     9  34      ; readerfooter.lua:825
0079    TSETS    9   8  18  ; "enabled_func"
0080    FNEW     9  35      ; readerfooter.lua:826
0081    TSETS    9   8  20  ; "callback"
0082    TSETB    8   7   4
0083    TDUP     8  37
0084    UGET     9   0      ; _
0085    KSTR    10  36      ; "Show footer separator"
0086    CALL     9   2   2
0087    TSETS    9   8   3  ; "text"
0088    FNEW     9  38      ; readerfooter.lua:839
0089    TSETS    9   8  33  ; "checked_func"
0090    FNEW     9  39      ; readerfooter.lua:842
0091    TSETS    9   8  20  ; "callback"
0092    TSETB    8   7   5
0093    TDUP     8  41
0094    UGET     9   0      ; _
0095    KSTR    10  40      ; "Lock status bar"
0096    CALL     9   2   2
0097    TSETS    9   8   3  ; "text"
0098    FNEW     9  42      ; readerfooter.lua:849
0099    TSETS    9   8  33  ; "checked_func"
0100    FNEW     9  43      ; readerfooter.lua:852
0101    TSETS    9   8  20  ; "callback"
0102    TSETB    8   7   6
0103    TDUP     8  45
0104    UGET     9   0      ; _
0105    KSTR    10  44      ; "Font"
0106    CALL     9   2   2
0107    TSETS    9   8   3  ; "text"
0108    TNEW     9   3
0109    TDUP    10  47
0110    FNEW    11  46      ; readerfooter.lua:861
0111    TSETS   11  10  48  ; "text_func"
0112    FNEW    11  49      ; readerfooter.lua:864
0113    TSETS   11  10  20  ; "callback"
0114    TSETB   10   9   1
0115    TDUP    10  51
0116    UGET    11   0      ; _
0117    KSTR    12  50      ; "Use bold font"
0118    CALL    11   2   2
0119    TSETS   11  10   3  ; "text"
0120    FNEW    11  52      ; readerfooter.lua:895
0121    TSETS   11  10  33  ; "checked_func"
0122    FNEW    11  53      ; readerfooter.lua:898
0123    TSETS   11  10  20  ; "callback"
0124    TSETB   10   9   2
0125    TSETS    9   8   4  ; "sub_item_table"
0126    TSETB    8   7   7
0127    TDUP     8  55
0128    UGET     9   0      ; _
0129    KSTR    10  54      ; "Maximum width of items"
0130    CALL     9   2   2
0131    TSETS    9   8   3  ; "text"
0132    TNEW     9   3
0133    TDUP    10  57
0134    FNEW    11  56      ; readerfooter.lua:918
0135    TSETS   11  10  48  ; "text_func"
0136    FNEW    11  58      ; readerfooter.lua:921
0137    TSETS   11  10  20  ; "callback"
0138    TSETB   10   9   1
0139    TDUP    10  60
0140    FNEW    11  59      ; readerfooter.lua:944
0141    TSETS   11  10  48  ; "text_func"
0142    FNEW    11  61      ; readerfooter.lua:947
0143    TSETS   11  10  20  ; "callback"
0144    TSETB   10   9   2
0145    TSETS    9   8   4  ; "sub_item_table"
0146    TSETB    8   7   8
0147    TDUP     8  63
0148    UGET     9   0      ; _
0149    KSTR    10  62      ; "Alignment"
0150    CALL     9   2   2
0151    TSETS    9   8   3  ; "text"
0152    FNEW     9  64      ; readerfooter.lua:973
0153    TSETS    9   8  18  ; "enabled_func"
0154    TNEW     9   4
0155    TDUP    10  66
0156    UGET    11   0      ; _
0157    KSTR    12  65      ; "Center"
0158    CALL    11   2   2
0159    TSETS   11  10   3  ; "text"
0160    FNEW    11  67      ; readerfooter.lua:979
0161    TSETS   11  10  33  ; "checked_func"
0162    FNEW    11  68      ; readerfooter.lua:982
0163    TSETS   11  10  20  ; "callback"
0164    TSETB   10   9   1
0165    TDUP    10  70
0166    UGET    11   0      ; _
0167    KSTR    12  69      ; "Left"
0168    CALL    11   2   2
0169    TSETS   11  10   3  ; "text"
0170    FNEW    11  71      ; readerfooter.lua:989
0171    TSETS   11  10  33  ; "checked_func"
0172    FNEW    11  72      ; readerfooter.lua:992
0173    TSETS   11  10  20  ; "callback"
0174    TSETB   10   9   2
0175    TDUP    10  74
0176    UGET    11   0      ; _
0177    KSTR    12  73      ; "Right"
0178    CALL    11   2   2
0179    TSETS   11  10   3  ; "text"
0180    FNEW    11  75      ; readerfooter.lua:999
0181    TSETS   11  10  33  ; "checked_func"
0182    FNEW    11  76      ; readerfooter.lua:1002
0183    TSETS   11  10  20  ; "callback"
0184    TSETB   10   9   3
0185    TSETS    9   8   4  ; "sub_item_table"
0186    TSETB    8   7   9
0187    TDUP     8  78
0188    UGET     9   0      ; _
0189    KSTR    10  77      ; "Prefix"
0190    CALL     9   2   2
0191    TSETS    9   8   3  ; "text"
0192    TNEW     9   3
0193    TDUP    10  80
0194    FNEW    11  79      ; readerfooter.lua:1013
0195    TSETS   11  10  48  ; "text_func"
0196    FNEW    11  81      ; readerfooter.lua:1020
0197    TSETS   11  10  33  ; "checked_func"
0198    FNEW    11  82      ; readerfooter.lua:1023
0199    TSETS   11  10  20  ; "callback"
0200    TSETB   10   9   1
0201    TDUP    10  84
0202    FNEW    11  83      ; readerfooter.lua:1030
0203    TSETS   11  10  48  ; "text_func"
0204    FNEW    11  85      ; readerfooter.lua:1037
0205    TSETS   11  10  33  ; "checked_func"
0206    FNEW    11  86      ; readerfooter.lua:1040
0207    TSETS   11  10  20  ; "callback"
0208    TSETB   10   9   2
0209    TSETS    9   8   4  ; "sub_item_table"
0210    TSETB    8   7  10
0211    TDUP     8  88
0212    UGET     9   0      ; _
0213    KSTR    10  87      ; "Item separator"
0214    CALL     9   2   2
0215    TSETS    9   8   3  ; "text"
0216    TNEW     9   4
0217    TDUP    10  90
0218    UGET    11   0      ; _
0219    KSTR    12  89      ; "Vertical line (|)"
0220    CALL    11   2   2
0221    TSETS   11  10   3  ; "text"
0222    FNEW    11  91      ; readerfooter.lua:1053
0223    TSETS   11  10  33  ; "checked_func"
0224    FNEW    11  92      ; readerfooter.lua:1056
0225    TSETS   11  10  20  ; "callback"
0226    TSETB   10   9   1
0227    TDUP    10  94
0228    UGET    11   0      ; _
0229    KSTR    12  93      ; "Bullet (•)"
0230    CALL    11   2   2
0231    TSETS   11  10   3  ; "text"
0232    FNEW    11  95      ; readerfooter.lua:1064
0233    TSETS   11  10  33  ; "checked_func"
0234    FNEW    11  96      ; readerfooter.lua:1067
0235    TSETS   11  10  20  ; "callback"
0236    TSETB   10   9   2
0237    TDUP    10  98
0238    UGET    11   0      ; _
0239    KSTR    12  97      ; "No separator"
0240    CALL    11   2   2
0241    TSETS   11  10   3  ; "text"
0242    FNEW    11  99      ; readerfooter.lua:1075
0243    TSETS   11  10  33  ; "checked_func"
0244    FNEW    11 100      ; readerfooter.lua:1078
0245    TSETS   11  10  20  ; "callback"
0246    TSETB   10   9   3
0247    TSETS    9   8   4  ; "sub_item_table"
0248    TSETB    8   7  11
0249    TDUP     8 102
0250    UGET     9   0      ; _
0251    KSTR    10 101      ; "Progress percentage format"
0252    CALL     9   2   2
0253    TSETS    9   8   3  ; "text"
0254    TNEW     9   4
0255    TDUP    10 104
0256    FNEW    11 103      ; readerfooter.lua:1090
0257    TSETS   11  10  48  ; "text_func"
0258    FNEW    11 105      ; readerfooter.lua:1093
0259    TSETS   11  10  33  ; "checked_func"
0260    FNEW    11 106      ; readerfooter.lua:1096
0261    TSETS   11  10  20  ; "callback"
0262    TSETB   10   9   1
0263    TDUP    10 108
0264    FNEW    11 107      ; readerfooter.lua:1103
0265    TSETS   11  10  48  ; "text_func"
0266    FNEW    11 109      ; readerfooter.lua:1106
0267    TSETS   11  10  33  ; "checked_func"
0268    FNEW    11 110      ; readerfooter.lua:1109
0269    TSETS   11  10  20  ; "callback"
0270    TSETB   10   9   2
0271    TDUP    10 112
0272    FNEW    11 111      ; readerfooter.lua:1116
0273    TSETS   11  10  48  ; "text_func"
0274    FNEW    11 113      ; readerfooter.lua:1119
0275    TSETS   11  10  33  ; "checked_func"
0276    FNEW    11 114      ; readerfooter.lua:1122
0277    TSETS   11  10  20  ; "callback"
0278    TSETB   10   9   3
0279    TSETS    9   8   4  ; "sub_item_table"
0280    TSETB    8   7  12
0281    TDUP     8 116
0282    UGET     9   0      ; _
0283    KSTR    10 115      ; "Time format"
0284    CALL     9   2   2
0285    TSETS    9   8   3  ; "text"
0286    TNEW     9   3
0287    TDUP    10 118
0288    FNEW    11 117      ; readerfooter.lua:1134
0289    TSETS   11  10  48  ; "text_func"
0290    FNEW    11 119      ; readerfooter.lua:1141
0291    TSETS   11  10  33  ; "checked_func"
0292    FNEW    11 120      ; readerfooter.lua:1144
0293    TSETS   11  10  20  ; "callback"
0294    TSETB   10   9   1
0295    TDUP    10 122
0296    FNEW    11 121      ; readerfooter.lua:1151
0297    TSETS   11  10  48  ; "text_func"
0298    FNEW    11 123      ; readerfooter.lua:1158
0299    TSETS   11  10  33  ; "checked_func"
0300    FNEW    11 124      ; readerfooter.lua:1161
0301    TSETS   11  10  20  ; "callback"
0302    TSETB   10   9   2
0303    TSETS    9   8   4  ; "sub_item_table"
0304    TSETB    8   7  13
0305    TDUP     8 126
0306    UGET     9   0      ; _
0307    KSTR    10 125      ; "Duration format"
0308    CALL     9   2   2
0309    TSETS    9   8   3  ; "text"
0310    TNEW     9   3
0311    TDUP    10 128
0312    FNEW    11 127      ; readerfooter.lua:1173
0313    TSETS   11  10  48  ; "text_func"
0314    FNEW    11 129      ; readerfooter.lua:1181
0315    TSETS   11  10  33  ; "checked_func"
0316    FNEW    11 130      ; readerfooter.lua:1184
0317    TSETS   11  10  20  ; "callback"
0318    TSETB   10   9   1
0319    TDUP    10 132
0320    FNEW    11 131      ; readerfooter.lua:1191
0321    TSETS   11  10  48  ; "text_func"
0322    FNEW    11 133      ; readerfooter.lua:1199
0323    TSETS   11  10  33  ; "checked_func"
0324    FNEW    11 134      ; readerfooter.lua:1202
0325    TSETS   11  10  20  ; "callback"
0326    TSETB   10   9   2
0327    TSETS    9   8   4  ; "sub_item_table"
0328    TSETB    8   7  14
0329    TSETS    7   6   4  ; "sub_item_table"
0330    CALL     4   1   3
0331    GGET     4  13      ; "table"
0332    TGETS    4   4  14  ; "insert"
0333    MOV      5   2
0334    TDUP     6 136
0335    UGET     7   0      ; _
0336    KSTR     8 135      ; "Progress bar"
0337    CALL     7   2   2
0338    TSETS    7   6   3  ; "text"
0339    TNEW     7   6
0340    TDUP     8 138
0341    UGET     9   0      ; _
0342    KSTR    10 137      ; "Show progress bar"
0343    CALL     9   2   2
0344    TSETS    9   8   3  ; "text"
0345    FNEW     9 139      ; readerfooter.lua:1218
0346    TSETS    9   8  33  ; "checked_func"
0347    FNEW     9 140      ; readerfooter.lua:1221
0348    TSETS    9   8  20  ; "callback"
0349    TSETB    8   7   1
0350    TDUP     8 142
0351    FNEW     9 141      ; readerfooter.lua:1234
0352    TSETS    9   8  48  ; "text_func"
0353    FNEW     9 143      ; readerfooter.lua:1243
0354    TSETS    9   8  18  ; "enabled_func"
0355    TNEW     9   4
0356    TDUP    10 145
0357    UGET    11   0      ; _
0358    KSTR    12 144      ; "Above items"
0359    CALL    11   2   2
0360    TSETS   11  10   3  ; "text"
0361    FNEW    11 146      ; readerfooter.lua:1249
0362    TSETS   11  10  33  ; "checked_func"
0363    FNEW    11 147      ; readerfooter.lua:1252
0364    TSETS   11  10  20  ; "callback"
0365    TSETB   10   9   1
0366    TDUP    10 149
0367    UGET    11   0      ; _
0368    KSTR    12 148      ; "Below items"
0369    CALL    11   2   2
0370    TSETS   11  10   3  ; "text"
0371    FNEW    11 150      ; readerfooter.lua:1259
0372    TSETS   11  10  33  ; "checked_func"
0373    FNEW    11 151      ; readerfooter.lua:1262
0374    TSETS   11  10  20  ; "callback"
0375    TSETB   10   9   2
0376    TDUP    10 153
0377    UGET    11   0      ; _
0378    KSTR    12 152      ; "Alongside items"
0379    CALL    11   2   2
0380    TSETS   11  10   3  ; "text"
0381    FNEW    11 154      ; readerfooter.lua:1269
0382    TSETS   11  10  33  ; "checked_func"
0383    FNEW    11 155      ; readerfooter.lua:1272
0384    TSETS   11  10  20  ; "callback"
0385    TSETB   10   9   3
0386    TSETS    9   8   4  ; "sub_item_table"
0387    TSETB    8   7   2
0388    TDUP     8 157
0389    FNEW     9 156      ; readerfooter.lua:1284
0390    TSETS    9   8  48  ; "text_func"
0391    FNEW     9 158      ; readerfooter.lua:1291
0392    TSETS    9   8  18  ; "enabled_func"
0393    TNEW     9   6
0394    TDUP    10 160
0395    UGET    11   0      ; _
0396    KSTR    12 159      ; "Thick"
0397    CALL    11   2   2
0398    TSETS   11  10   3  ; "text"
0399    FNEW    11 161      ; readerfooter.lua:1297
0400    TSETS   11  10  33  ; "checked_func"
0401    FNEW    11 162      ; readerfooter.lua:1300
0402    TSETS   11  10  20  ; "callback"
0403    TSETB   10   9   1
0404    TDUP    10 164
0405    UGET    11   0      ; _
0406    KSTR    12 163      ; "Thin"
0407    CALL    11   2   2
0408    TSETS   11  10   3  ; "text"
0409    FNEW    11 165      ; readerfooter.lua:1310
0410    TSETS   11  10  33  ; "checked_func"
0411    FNEW    11 166      ; readerfooter.lua:1313
0412    TSETS   11  10  20  ; "callback"
0413    TSETB   10   9   2
0414    TDUP    10 168
0415    UGET    11   0      ; _
0416    KSTR    12 167      ; "Set size"
0417    CALL    11   2   2
0418    TSETS   11  10   3  ; "text"
0419    FNEW    11 169      ; readerfooter.lua:1322
0420    TSETS   11  10  20  ; "callback"
0421    TSETB   10   9   3
0422    TDUP    10 171
0423    UGET    11   0      ; _
0424    KSTR    12 170      ; "Show chapter markers"
0425    CALL    11   2   2
0426    TSETS   11  10   3  ; "text"
0427    FNEW    11 172      ; readerfooter.lua:1362
0428    TSETS   11  10  33  ; "checked_func"
0429    FNEW    11 173      ; readerfooter.lua:1365
0430    TSETS   11  10  18  ; "enabled_func"
0431    FNEW    11 174      ; readerfooter.lua:1368
0432    TSETS   11  10  20  ; "callback"
0433    TSETB   10   9   4
0434    TDUP    10 176
0435    FNEW    11 175      ; readerfooter.lua:1375
0436    TSETS   11  10  48  ; "text_func"
0437    FNEW    11 177      ; readerfooter.lua:1384
0438    TSETS   11  10  18  ; "enabled_func"
0439    TNEW    11   4
0440    TDUP    12 178
0441    UGET    13   0      ; _
0442    KSTR    14 163      ; "Thin"
0443    CALL    13   2   2
0444    TSETS   13  12   3  ; "text"
0445    FNEW    13 179      ; readerfooter.lua:1390
0446    TSETS   13  12  33  ; "checked_func"
0447    FNEW    13 180      ; readerfooter.lua:1393
0448    TSETS   13  12  20  ; "callback"
0449    TSETB   12  11   1
0450    TDUP    12 182
0451    UGET    13   0      ; _
0452    KSTR    14 181      ; "Medium"
0453    CALL    13   2   2
0454    TSETS   13  12   3  ; "text"
0455    FNEW    13 183      ; readerfooter.lua:1401
0456    TSETS   13  12  33  ; "checked_func"
0457    FNEW    13 184      ; readerfooter.lua:1404
0458    TSETS   13  12  20  ; "callback"
0459    TSETB   12  11   2
0460    TDUP    12 185
0461    UGET    13   0      ; _
0462    KSTR    14 159      ; "Thick"
0463    CALL    13   2   2
0464    TSETS   13  12   3  ; "text"
0465    FNEW    13 186      ; readerfooter.lua:1412
0466    TSETS   13  12  33  ; "checked_func"
0467    FNEW    13 187      ; readerfooter.lua:1415
0468    TSETS   13  12  20  ; "callback"
0469    TSETB   12  11   3
0470    TSETS   11  10   4  ; "sub_item_table"
0471    TSETB   10   9   5
0472    TSETS    9   8   4  ; "sub_item_table"
0473    TSETB    8   7   3
0474    TDUP     8 189
0475    FNEW     9 188      ; readerfooter.lua:1426
0476    TSETS    9   8  48  ; "text_func"
0477    FNEW     9 190      ; readerfooter.lua:1436
0478    TSETS    9   8  18  ; "enabled_func"
0479    TNEW     9   4
0480    TDUP    10 192
0481    UGET    11   0      ; _
0482    KSTR    12 191      ; "No margins (0)"
0483    CALL    11   2   2
0484    TSETS   11  10   3  ; "text"
0485    FNEW    11 193      ; readerfooter.lua:1442
0486    TSETS   11  10  33  ; "checked_func"
0487    FNEW    11 194      ; readerfooter.lua:1446
0488    TSETS   11  10  20  ; "callback"
0489    TSETB   10   9   1
0490    TDUP    10 196
0491    UGET    11   0      ; _
0492    KSTR    12 195      ; "Static margins (10)"
0493    CALL    11   2   2
0494    TSETS   11  10   3  ; "text"
0495    FNEW    11 197      ; readerfooter.lua:1454
0496    TSETS   11  10  33  ; "checked_func"
0497    FNEW    11 198      ; readerfooter.lua:1460
0498    TSETS   11  10  20  ; "callback"
0499    TSETB   10   9   2
0500    TDUP    10 200
0501    FNEW    11 199      ; readerfooter.lua:1467
0502    TSETS   11  10  48  ; "text_func"
0503    FNEW    11 201      ; readerfooter.lua:1473
0504    TSETS   11  10  33  ; "checked_func"
0505    FNEW    11 202      ; readerfooter.lua:1476
0506    TSETS   11  10  18  ; "enabled_func"
0507    FNEW    11 203      ; readerfooter.lua:1479
0508    TSETS   11  10  20  ; "callback"
0509    TSETB   10   9   3
0510    TSETS    9   8   4  ; "sub_item_table"
0511    TSETB    8   7   4
0512    TDUP     8 205
0513    FNEW     9 204      ; readerfooter.lua:1488
0514    TSETS    9   8  48  ; "text_func"
0515    FNEW     9 206      ; readerfooter.lua:1491
0516    TSETS    9   8  18  ; "enabled_func"
0517    FNEW     9 207      ; readerfooter.lua:1495
0518    TSETS    9   8  20  ; "callback"
0519    TSETB    8   7   5
0520    TSETS    7   6   4  ; "sub_item_table"
0521    CALL     4   1   3
0522    GGET     4  13      ; "table"
0523    TGETS    4   4  14  ; "insert"
0524    MOV      5   2
0525    MOV      6   3
0526    KSTR     7 208      ; "page_progress"
0527    CALL     6   0   2
0528    CALLM    4   1   1
0529    GGET     4  13      ; "table"
0530    TGETS    4   4  14  ; "insert"
0531    MOV      5   2
0532    MOV      6   3
0533    KSTR     7 209      ; "time"
0534    CALL     6   0   2
0535    CALLM    4   1   1
0536    GGET     4  13      ; "table"
0537    TGETS    4   4  14  ; "insert"
0538    MOV      5   2
0539    MOV      6   3
0540    KSTR     7 210      ; "pages_left"
0541    CALL     6   0   2
0542    CALLM    4   1   1
0543    GGET     4  13      ; "table"
0544    TGETS    4   4  14  ; "insert"
0545    MOV      5   2
0546    MOV      6   3
0547    KSTR     7 211      ; "battery"
0548    CALL     6   0   2
0549    CALLM    4   1   1
0550    GGET     4  13      ; "table"
0551    TGETS    4   4  14  ; "insert"
0552    MOV      5   2
0553    MOV      6   3
0554    KSTR     7 212      ; "percentage"
0555    CALL     6   0   2
0556    CALLM    4   1   1
0557    GGET     4  13      ; "table"
0558    TGETS    4   4  14  ; "insert"
0559    MOV      5   2
0560    MOV      6   3
0561    KSTR     7 213      ; "book_time_to_read"
0562    CALL     6   0   2
0563    CALLM    4   1   1
0564    GGET     4  13      ; "table"
0565    TGETS    4   4  14  ; "insert"
0566    MOV      5   2
0567    MOV      6   3
0568    KSTR     7 214      ; "chapter_time_to_read"
0569    CALL     6   0   2
0570    CALLM    4   1   1
0571    UGET     4  11      ; Device
0572    MOV      5   4
0573    TGETS    4   4 215  ; "hasFrontlight"
0574    CALL     4   2   2
0575    ISF          4
0576    JMP      5 => 0584
0577    GGET     4  13      ; "table"
0578    TGETS    4   4  14  ; "insert"
0579    MOV      5   2
0580    MOV      6   3
0581    KSTR     7 216      ; "frontlight"
0582    CALL     6   0   2
0583    CALLM    4   1   1
0584 => GGET     4  13      ; "table"
0585    TGETS    4   4  14  ; "insert"
0586    MOV      5   2
0587    MOV      6   3
0588    KSTR     7 217      ; "mem_usage"
0589    CALL     6   0   2
0590    CALLM    4   1   1
0591    UGET     4  11      ; Device
0592    MOV      5   4
0593    TGETS    4   4 218  ; "isAndroid"
0594    CALL     4   2   2
0595    ISF          4
0596    JMP      5 => 0604
0597    GGET     4  13      ; "table"
0598    TGETS    4   4  14  ; "insert"
0599    MOV      5   2
0600    MOV      6   3
0601    KSTR     7 219      ; "wifi_status"
0602    CALL     6   0   2
0603    CALLM    4   1   1
0604 => GGET     4  13      ; "table"
0605    TGETS    4   4  14  ; "insert"
0606    MOV      5   2
0607    MOV      6   3
0608    KSTR     7 220      ; "book_title"
0609    CALL     6   0   2
0610    CALLM    4   1   1
0611    GGET     4  13      ; "table"
0612    TGETS    4   4  14  ; "insert"
0613    MOV      5   2
0614    MOV      6   3
0615    KSTR     7 221      ; "book_chapter"
0616    CALL     6   0   2
0617    CALLM    4   1   1
0618    UCLO     0 => 0619
0619 => RET0     0   1

-- BYTECODE -- readerfooter.lua:1538-1538
0001    RET0     0   1

-- BYTECODE -- readerfooter.lua:1540-1555
0001    TNEW     1   0
0002    KSTR     2   0      ; "  "
0003    TGETS    3   0   1  ; "settings"
0004    TGETS    3   3   2  ; "items_separator"
0005    ISEQS    3   3      ; "bar"
0006    JMP      3 => 0011
0007    TGETS    3   0   1  ; "settings"
0008    TGETS    3   3   2  ; "items_separator"
0009    ISNEP    3   0
0010    JMP      3 => 0013
0011 => KSTR     2   4      ; " | "
0012    JMP      3 => 0018
0013 => TGETS    3   0   1  ; "settings"
0014    TGETS    3   3   2  ; "items_separator"
0015    ISNES    3   5      ; "bullet"
0016    JMP      3 => 0018
0017    KSTR     2   6      ; " • "
0018 => GGET     3   7      ; "ipairs"
0019    TGETS    4   0   8  ; "footerTextGenerators"
0020    CALL     3   4   2
0021    JMP      6 => 0032
0022 => GGET     8   9      ; "table"
0023    TGETS    8   8  10  ; "insert"
0024    MOV      9   1
0025    UGET    10   0      ; BD
0026    TGETS   10  10  11  ; "wrap"
0027    MOV     11   7
0028    MOV     12   0
0029    CALL    11   0   2
0030    CALLM   10   0   0
0031    CALLM    8   1   1
0032 => ITERC    6   3   3
0033    ITERL    6 => 0022
0034    GGET     3   9      ; "table"
0035    TGETS    3   3  12  ; "concat"
0036    MOV      4   1
0037    UGET     5   0      ; BD
0038    TGETS    5   5  11  ; "wrap"
0039    MOV      6   2
0040    CALL     5   0   2
0041    CALLMT   3   1

-- BYTECODE -- readerfooter.lua:1574-1574
0001    LEN      2   0
0002    LEN      3   1
0003    ISLT     3   2
0004    JMP      2 => 0007
0005    KPRI     2   1
0006    JMP      3 => 0008
0007 => KPRI     2   2
0008 => RET1     2   2

-- BYTECODE -- readerfooter.lua:1557-1590
0001    TGETS    2   0   0  ; "settings"
0002    TGETS    2   2   1  ; "disable_progress_bar"
0003    IST          2
0004    JMP      3 => 0009
0005    TGETS    2   0   0  ; "settings"
0006    TGETS    2   2   2  ; "progress_style_thin"
0007    ISF          2
0008    JMP      3 => 0010
0009 => UCLO     0 => 0097
0010 => ISF          1
0011    JMP      2 => 0021
0012    TGETS    2   0   3  ; "progress_bar"
0013    KPRI     3   0
0014    TSETS    3   2   4  ; "ticks"
0015    TGETS    2   0   6  ; "view"
0016    TGETS    2   2   7  ; "document"
0017    MOV      3   2
0018    TGETS    2   2   8  ; "getPageCount"
0019    CALL     2   2   2
0020    TSETS    2   0   5  ; "pages"
0021 => TGETS    2   0   0  ; "settings"
0022    TGETS    2   2   9  ; "toc_markers"
0023    ISF          2
0024    JMP      3 => 0091
0025    TGETS    2   0   3  ; "progress_bar"
0026    UGET     3   0      ; Screen
0027    MOV      4   3
0028    TGETS    3   3  11  ; "scaleBySize"
0029    TGETS    5   0   0  ; "settings"
0030    TGETS    5   5  12  ; "toc_markers_width"
0031    CALL     3   2   3
0032    TSETS    3   2  10  ; "tick_width"
0033    TGETS    2   0   3  ; "progress_bar"
0034    TGETS    2   2   4  ; "ticks"
0035    ISEQP    2   0
0036    JMP      2 => 0038
0037    UCLO     0 => 0098
0038 => TNEW     2   0
0039    TGETS    3   0  13  ; "ui"
0040    TGETS    3   3  14  ; "toc"
0041    ISF          3
0042    JMP      4 => 0069
0043    TGETS    3   0  13  ; "ui"
0044    TGETS    3   3  14  ; "toc"
0045    MOV      4   3
0046    TGETS    3   3  15  ; "getMaxDepth"
0047    CALL     3   2   2
0048    KSHORT   4   0
0049    UNM      5   3
0050    KSHORT   6  -1
0051    FORI     4 => 0064
0052 => TGETS    8   0  13  ; "ui"
0053    TGETS    8   8  14  ; "toc"
0054    MOV      9   8
0055    TGETS    8   8  16  ; "getTocTicks"
0056    MOV     10   7
0057    CALL     8   2   3
0058    GGET     9  17      ; "table"
0059    TGETS    9   9  18  ; "insert"
0060    MOV     10   2
0061    MOV     11   8
0062    CALL     9   1   3
0063    FORL     4 => 0052
0064 => GGET     4  17      ; "table"
0065    TGETS    4   4  19  ; "sort"
0066    MOV      5   2
0067    FNEW     6  20      ; readerfooter.lua:1574
0068    CALL     4   1   3
0069 => LEN      3   2
0070    KSHORT   4   0
0071    ISGE     4   3
0072    JMP      3 => 0087
0073    TGETS    3   0   3  ; "progress_bar"
0074    TGETB    4   2   1
0075    TSETS    4   3   4  ; "ticks"
0076    TGETS    3   0   3  ; "progress_bar"
0077    TGETS    4   0   5  ; "pages"
0078    IST          4
0079    JMP      5 => 0085
0080    TGETS    4   0   6  ; "view"
0081    TGETS    4   4   7  ; "document"
0082    MOV      5   4
0083    TGETS    4   4   8  ; "getPageCount"
0084    CALL     4   2   2
0085 => TSETS    4   3  21  ; "last"
0086    JMP      3 => 0094
0087 => TGETS    3   0   3  ; "progress_bar"
0088    TNEW     4   0
0089    TSETS    4   3   4  ; "ticks"
0090    JMP      2 => 0094
0091 => TGETS    2   0   3  ; "progress_bar"
0092    KPRI     3   0
0093    TSETS    3   2   4  ; "ticks"
0094 => KPRI     2   2
0095    UCLO     0 => 0096
0096 => RET1     2   2
0097 => RET0     0   1
0098 => RET0     0   1

-- BYTECODE -- readerfooter.lua:1592-1594
0001    RET0     0   1

-- BYTECODE -- readerfooter.lua:1596-1607
0001    KSTR     3   0      ; "na"
0002    MOV      5   0
0003    TGETS    4   0   1  ; "getAvgTimePerPage"
0004    CALL     4   2   2
0005    ISF          4
0006    JMP      5 => 0024
0007    TGETS    5   0   2  ; "settings"
0008    TGETS    5   5   3  ; "duration_format"
0009    ISNES    5   4      ; "classic"
0010    JMP      5 => 0018
0011    UGET     5   0      ; util
0012    TGETS    5   5   5  ; "secondsToClock"
0013    MULVV    6   2   4
0014    KPRI     7   2
0015    CALL     5   2   3
0016    MOV      3   5
0017    JMP      5 => 0024
0018 => UGET     5   0      ; util
0019    TGETS    5   5   6  ; "secondsToHClock"
0020    MULVV    6   2   4
0021    KPRI     7   2
0022    CALL     5   2   3
0023    MOV      3   5
0024 => MOV      5   1
0025    MOV      6   3
0026    CAT      5   5   6
0027    RET1     5   2

-- BYTECODE -- readerfooter.lua:1609-1615
0001    TGETS    3   0   0  ; "pageno"
0002    ISF          3
0003    JMP      4 => 0010
0004    MOV      4   0
0005    TGETS    3   0   1  ; "updateFooterPage"
0006    MOV      5   1
0007    MOV      6   2
0008    CALL     3   1   4
0009    JMP      3 => 0015
0010 => MOV      4   0
0011    TGETS    3   0   2  ; "updateFooterPos"
0012    MOV      5   1
0013    MOV      6   2
0014    CALL     3   1   4
0015 => RET0     0   1

-- BYTECODE -- readerfooter.lua:1617-1621
0001    GGET     3   0      ; "type"
0002    TGETS    4   0   1  ; "pageno"
0003    CALL     3   2   2
0004    ISEQS    3   2      ; "number"
0005    JMP      3 => 0007
0006    RET0     0   1
0007 => TGETS    3   0   3  ; "progress_bar"
0008    TGETS    4   0   1  ; "pageno"
0009    TGETS    5   0   5  ; "pages"
0010    DIVVV    4   4   5
0011    TSETS    4   3   4  ; "percentage"
0012    MOV      4   0
0013    TGETS    3   0   6  ; "updateFooterText"
0014    MOV      5   1
0015    MOV      6   2
0016    CALL     3   1   4
0017    RET0     0   1

-- BYTECODE -- readerfooter.lua:1623-1627
0001    GGET     3   0      ; "type"
0002    TGETS    4   0   1  ; "position"
0003    CALL     3   2   2
0004    ISEQS    3   2      ; "number"
0005    JMP      3 => 0007
0006    RET0     0   1
0007 => TGETS    3   0   3  ; "progress_bar"
0008    TGETS    4   0   1  ; "position"
0009    TGETS    5   0   5  ; "doc_height"
0010    DIVVV    4   4   5
0011    TSETS    4   3   4  ; "percentage"
0012    MOV      4   0
0013    TGETS    3   0   6  ; "updateFooterText"
0014    MOV      5   1
0015    MOV      6   2
0016    CALL     3   1   4
0017    RET0     0   1

-- BYTECODE -- readerfooter.lua:1631-1632
0001    RET0     0   1

-- BYTECODE -- readerfooter.lua:1690-1692
0001    KSTR     0   0      ; "ui"
0002    UGET     1   0      ; self
0003    TGETS    1   1   1  ; "footer_content"
0004    TGETS    1   1   2  ; "dimen"
0005    RET      0   3

-- BYTECODE -- readerfooter.lua:1635-1694
0001    TGETS    3   0   0  ; "view"
0002    TGETS    3   3   1  ; "footer_visible"
0003    IST          3
0004    JMP      3 => 0010
0005    IST          1
0006    JMP      3 => 0010
0007    IST          2
0008    JMP      3 => 0010
0009    UCLO     0 => 0189
0010 => MOV      4   0
0011    TGETS    3   0   2  ; "genFooterText"
0012    CALL     3   2   2
0013    IST          3
0014    JMP      4 => 0016
0015    KSTR     3   3      ; ""
0016 => TGETS    4   0   4  ; "footer_text"
0017    MOV      5   4
0018    TGETS    4   4   5  ; "setText"
0019    MOV      6   3
0020    CALL     4   1   3
0021    TGETS    4   0   4  ; "footer_text"
0022    MOV      5   4
0023    TGETS    4   4   6  ; "setMaxWidth"
0024    GGET     6   7      ; "math"
0025    TGETS    6   6   8  ; "floor"
0026    TGETS    7   0   9  ; "_saved_screen_width"
0027    TGETS    8   0  10  ; "settings"
0028    TGETS    8   8  11  ; "progress_margin_width"
0029    MULNV    8   8   0  ; 2
0030    SUBVV    7   7   8
0031    CALL     6   0   2
0032    CALLM    4   1   1
0033    TGETS    4   0  10  ; "settings"
0034    TGETS    4   4  12  ; "disable_progress_bar"
0035    ISF          4
0036    JMP      5 => 0062
0037    TGETS    4   0  13  ; "has_no_mode"
0038    IST          4
0039    JMP      5 => 0042
0040    ISNES    3   3      ; ""
0041    JMP      4 => 0052
0042 => KSHORT   4   0
0043    TSETS    4   0  14  ; "text_width"
0044    TGETS    4   0  15  ; "footer_container"
0045    TGETS    4   4  16  ; "dimen"
0046    KSHORT   5   0
0047    TSETS    5   4  17  ; "h"
0048    TGETS    4   0   4  ; "footer_text"
0049    KSHORT   5   0
0050    TSETS    5   4  18  ; "height"
0051    JMP      4 => 0058
0052 => TGETS    4   0   4  ; "footer_text"
0053    MOV      5   4
0054    TGETS    4   4  19  ; "getSize"
0055    CALL     4   2   2
0056    TGETS    4   4  20  ; "w"
0057    TSETS    4   0  14  ; "text_width"
0058 => TGETS    4   0  21  ; "progress_bar"
0059    KSHORT   5   0
0060    TSETS    5   4  22  ; "width"
0061    JMP      4 => 0137
0062 => TGETS    4   0  10  ; "settings"
0063    TGETS    4   4  23  ; "progress_bar_position"
0064    ISF          4
0065    JMP      5 => 0092
0066    ISNES    3   3      ; ""
0067    JMP      4 => 0075
0068    TGETS    4   0  15  ; "footer_container"
0069    TGETS    4   4  16  ; "dimen"
0070    KSHORT   5   0
0071    TSETS    5   4  17  ; "h"
0072    TGETS    4   0   4  ; "footer_text"
0073    KSHORT   5   0
0074    TSETS    5   4  18  ; "height"
0075 => TGETS    4   0  21  ; "progress_bar"
0076    GGET     5   7      ; "math"
0077    TGETS    5   5   8  ; "floor"
0078    TGETS    6   0   9  ; "_saved_screen_width"
0079    TGETS    7   0  10  ; "settings"
0080    TGETS    7   7  11  ; "progress_margin_width"
0081    MULNV    7   7   0  ; 2
0082    SUBVV    6   6   7
0083    CALL     5   2   2
0084    TSETS    5   4  22  ; "width"
0085    TGETS    4   0   4  ; "footer_text"
0086    MOV      5   4
0087    TGETS    4   4  19  ; "getSize"
0088    CALL     4   2   2
0089    TGETS    4   4  20  ; "w"
0090    TSETS    4   0  14  ; "text_width"
0091    JMP      4 => 0137
0092 => TGETS    4   0  13  ; "has_no_mode"
0093    IST          4
0094    JMP      5 => 0097
0095    ISNES    3   3      ; ""
0096    JMP      4 => 0100
0097 => KSHORT   4   0
0098    TSETS    4   0  14  ; "text_width"
0099    JMP      4 => 0125
0100 => TGETS    4   0  10  ; "settings"
0101    TGETS    4   4  24  ; "progress_bar_min_width_pct"
0102    SUBNV    4   4   1  ; 100
0103    DIVVN    4   4   1  ; 100
0104    TGETS    5   0   4  ; "footer_text"
0105    MOV      6   5
0106    TGETS    5   5   6  ; "setMaxWidth"
0107    GGET     7   7      ; "math"
0108    TGETS    7   7   8  ; "floor"
0109    TGETS    8   0   9  ; "_saved_screen_width"
0110    MULVV    8   4   8
0111    TGETS    9   0  10  ; "settings"
0112    TGETS    9   9  11  ; "progress_margin_width"
0113    MULNV    9   9   0  ; 2
0114    SUBVV    8   8   9
0115    CALL     7   0   2
0116    CALLM    5   1   1
0117    TGETS    5   0   4  ; "footer_text"
0118    MOV      6   5
0119    TGETS    5   5  19  ; "getSize"
0120    CALL     5   2   2
0121    TGETS    5   5  20  ; "w"
0122    TGETS    6   0  25  ; "text_left_margin"
0123    ADDVV    5   5   6
0124    TSETS    5   0  14  ; "text_width"
0125 => TGETS    4   0  21  ; "progress_bar"
0126    GGET     5   7      ; "math"
0127    TGETS    5   5   8  ; "floor"
0128    TGETS    6   0   9  ; "_saved_screen_width"
0129    TGETS    7   0  14  ; "text_width"
0130    SUBVV    6   6   7
0131    TGETS    7   0  10  ; "settings"
0132    TGETS    7   7  11  ; "progress_margin_width"
0133    MULVN    7   7   0  ; 2
0134    SUBVV    6   6   7
0135    CALL     5   2   2
0136    TSETS    5   4  22  ; "width"
0137 => KPRI     4   0
0138    TGETS    5   0  10  ; "settings"
0139    TGETS    5   5  26  ; "progress_style_thin"
0140    ISF          5
0141    JMP      6 => 0148
0142    TGETS    5   0  10  ; "settings"
0143    TGETS    5   5  27  ; "progress_style_thin_height"
0144    ISTC     4   5
0145    JMP      6 => 0147
0146    UGET     4   0      ; PROGRESS_BAR_STYLE_THIN_DEFAULT_HEIGHT
0147 => JMP      5 => 0153
0148 => TGETS    5   0  10  ; "settings"
0149    TGETS    5   5  28  ; "progress_style_thick_height"
0150    ISTC     4   5
0151    JMP      6 => 0153
0152    UGET     4   1      ; PROGRESS_BAR_STYLE_THICK_DEFAULT_HEIGHT
0153 => TGETS    5   0  21  ; "progress_bar"
0154    UGET     6   2      ; Screen
0155    MOV      7   6
0156    TGETS    6   6  29  ; "scaleBySize"
0157    MOV      8   4
0158    CALL     6   2   3
0159    TSETS    6   5  18  ; "height"
0160    TGETS    5   0  30  ; "separator_line"
0161    ISF          5
0162    JMP      6 => 0170
0163    TGETS    5   0  30  ; "separator_line"
0164    TGETS    5   5  16  ; "dimen"
0165    TGETS    6   0   9  ; "_saved_screen_width"
0166    TGETS    7   0  31  ; "horizontal_margin"
0167    MULNV    7   7   0  ; 2
0168    SUBVV    6   6   7
0169    TSETS    6   5  20  ; "w"
0170 => TGETS    5   0  32  ; "text_container"
0171    TGETS    5   5  16  ; "dimen"
0172    TGETS    6   0  14  ; "text_width"
0173    TSETS    6   5  20  ; "w"
0174    TGETS    5   0  33  ; "horizontal_group"
0175    MOV      6   5
0176    TGETS    5   5  34  ; "resetLayout"
0177    CALL     5   1   2
0178    ISF          1
0179    JMP      5 => 0187
0180    UGET     5   3      ; UIManager
0181    MOV      6   5
0182    TGETS    5   5  35  ; "setDirty"
0183    TGETS    7   0   0  ; "view"
0184    TGETS    7   7  36  ; "dialog"
0185    FNEW     8  37      ; readerfooter.lua:1690
0186    CALL     5   1   4
0187 => UCLO     0 => 0188
0188 => RET0     0   1
0189 => RET0     0   1

-- BYTECODE -- readerfooter.lua:1696-1701
0001    TSETS    1   0   0  ; "pageno"
0002    TGETS    2   0   2  ; "view"
0003    TGETS    2   2   3  ; "document"
0004    MOV      3   2
0005    TGETS    2   2   4  ; "getPageCount"
0006    CALL     2   2   2
0007    TSETS    2   0   1  ; "pages"
0008    TGETS    2   0   5  ; "ui"
0009    TGETS    2   2   6  ; "doc_settings"
0010    MOV      3   2
0011    TGETS    2   2   7  ; "saveSetting"
0012    KSTR     4   8      ; "doc_pages"
0013    TGETS    5   0   1  ; "pages"
0014    CALL     2   1   4
0015    MOV      3   0
0016    TGETS    2   0   9  ; "updateFooterPage"
0017    CALL     2   1   2
0018    RET0     0   1

-- BYTECODE -- readerfooter.lua:1703-1712
0001    TSETS    1   0   0  ; "position"
0002    TGETS    3   0   2  ; "view"
0003    TGETS    3   3   3  ; "document"
0004    TGETS    3   3   4  ; "info"
0005    TGETS    3   3   1  ; "doc_height"
0006    TSETS    3   0   1  ; "doc_height"
0007    ISF          2
0008    JMP      3 => 0023
0009    TSETS    2   0   5  ; "pageno"
0010    TGETS    3   0   2  ; "view"
0011    TGETS    3   3   3  ; "document"
0012    MOV      4   3
0013    TGETS    3   3   7  ; "getPageCount"
0014    CALL     3   2   2
0015    TSETS    3   0   6  ; "pages"
0016    TGETS    3   0   8  ; "ui"
0017    TGETS    3   3   9  ; "doc_settings"
0018    MOV      4   3
0019    TGETS    3   3  10  ; "saveSetting"
0020    KSTR     5  11      ; "doc_pages"
0021    TGETS    6   0   6  ; "pages"
0022    CALL     3   1   4
0023 => MOV      4   0
0024    TGETS    3   0  12  ; "updateFooterPos"
0025    CALL     3   1   2
0026    RET0     0   1

-- BYTECODE -- readerfooter.lua:1718-1735
0001    TGETS    1   0   0  ; "ui"
0002    TGETS    1   1   1  ; "menu"
0003    MOV      2   1
0004    TGETS    1   1   2  ; "registerToMainMenu"
0005    MOV      3   0
0006    CALL     1   1   3
0007    MOV      2   0
0008    TGETS    1   0   3  ; "setupTouchZones"
0009    CALL     1   1   2
0010    TGETS    1   0   0  ; "ui"
0011    TGETS    1   1   4  ; "document"
0012    TGETS    1   1   5  ; "info"
0013    TGETS    1   1   6  ; "has_pages"
0014    ISF          1
0015    JMP      2 => 0031
0016    TGETS    1   0   7  ; "settings"
0017    TGETS    1   1   8  ; "progress_margin"
0018    ISF          1
0019    JMP      2 => 0031
0020    TGETS    1   0   7  ; "settings"
0021    UGET     2   0      ; Screen
0022    MOV      3   2
0023    TGETS    2   2  10  ; "scaleBySize"
0024    KSHORT   4  10
0025    CALL     2   2   3
0026    TSETS    2   1   9  ; "progress_margin_width"
0027    MOV      2   0
0028    TGETS    1   0  11  ; "updateFooterContainer"
0029    CALL     1   1   2
0030    JMP      1 => 0052
0031 => TGETS    1   0   7  ; "settings"
0032    TGETS    1   1   8  ; "progress_margin"
0033    ISF          1
0034    JMP      2 => 0052
0035    TGETS    1   0   0  ; "ui"
0036    TGETS    1   1   4  ; "document"
0037    MOV      2   1
0038    TGETS    1   1  12  ; "getPageMargins"
0039    CALL     1   2   2
0040    TGETS    2   0   7  ; "settings"
0041    GGET     3  13      ; "math"
0042    TGETS    3   3  14  ; "floor"
0043    TGETS    4   1  15  ; "left"
0044    TGETS    5   1  16  ; "right"
0045    ADDVV    4   4   5
0046    DIVVN    4   4   0  ; 2
0047    CALL     3   2   2
0048    TSETS    3   2   9  ; "progress_margin_width"
0049    MOV      3   0
0050    TGETS    2   0  11  ; "updateFooterContainer"
0051    CALL     2   1   2
0052 => MOV      2   0
0053    TGETS    1   0  17  ; "resetLayout"
0054    TGETS    3   0   7  ; "settings"
0055    TGETS    3   3   9  ; "progress_margin_width"
0056    CALL     1   1   3
0057    MOV      2   0
0058    TGETS    1   0  18  ; "setTocMarkers"
0059    CALL     1   1   2
0060    TGETS    1   0  20  ; "_updateFooterText"
0061    TSETS    1   0  19  ; "updateFooterText"
0062    MOV      2   0
0063    TGETS    1   0  21  ; "updateFooter"
0064    CALL     1   1   2
0065    RET0     0   1

-- BYTECODE -- readerfooter.lua:1737-1744
0001    TGETS    2   0   0  ; "ui"
0002    TGETS    2   2   1  ; "document"
0003    TGETS    2   2   2  ; "info"
0004    TGETS    2   2   3  ; "has_pages"
0005    IST          2
0006    JMP      2 => 0029
0007    MOV      3   1
0008    TGETS    2   1   4  ; "readSetting"
0009    KSTR     4   5      ; "copt_h_page_margins"
0010    CALL     2   2   3
0011    IST          2
0012    JMP      3 => 0021
0013    GGET     2   6      ; "G_reader_settings"
0014    MOV      3   2
0015    TGETS    2   2   4  ; "readSetting"
0016    KSTR     4   5      ; "copt_h_page_margins"
0017    CALL     2   2   3
0018    IST          2
0019    JMP      3 => 0021
0020    GGET     2   7      ; "DCREREADER_CONFIG_H_MARGIN_SIZES_MEDIUM"
0021 => GGET     3   9      ; "math"
0022    TGETS    3   3  10  ; "floor"
0023    TGETB    4   2   1
0024    TGETB    5   2   2
0025    ADDVV    4   4   5
0026    DIVVN    4   4   0  ; 2
0027    CALL     3   2   2
0028    TSETS    3   0   8  ; "book_margins_footer_width"
0029 => RET0     0   1

-- BYTECODE -- readerfooter.lua:1746-1781
0001    ISEQP    1   0
0002    JMP      2 => 0004
0003    TSETS    1   0   0  ; "mode"
0004 => TGETS    2   0   1  ; "view"
0005    TGETS    3   0   0  ; "mode"
0006    TGETS    4   0   3  ; "mode_list"
0007    TGETS    4   4   4  ; "off"
0008    ISNEV    3   4
0009    JMP      3 => 0012
0010    KPRI     3   1
0011    JMP      4 => 0013
0012 => KPRI     3   2
0013 => TSETS    3   2   2  ; "footer_visible"
0014    TGETS    2   0   5  ; "settings"
0015    TGETS    2   2   6  ; "all_at_once"
0016    ISF          2
0017    JMP      3 => 0019
0018    RET0     0   1
0019 => TGETS    2   0   1  ; "view"
0020    TGETS    2   2   2  ; "footer_visible"
0021    IST          2
0022    JMP      2 => 0027
0023    UGET     2   0      ; footerTextGeneratorMap
0024    TGETS    2   2   8  ; "empty"
0025    TSETS    2   0   7  ; "genFooterText"
0026    RET0     0   1
0027 => TGETS    2   0   9  ; "mode_index"
0028    TGETS    3   0   0  ; "mode"
0029    TGETV    2   2   3
0030    TGETS    3   0   5  ; "settings"
0031    TGETV    3   3   2
0032    ISF          3
0033    JMP      3 => 0037
0034    TGETS    3   0  10  ; "has_no_mode"
0035    ISF          3
0036    JMP      4 => 0038
0037 => KSTR     2   8      ; "empty"
0038 => UGET     3   0      ; footerTextGeneratorMap
0039    TGETV    3   3   2
0040    TSETS    3   0   7  ; "genFooterText"
0041    RET0     0   1

-- BYTECODE -- readerfooter.lua:1783-1786
0001    TGETS    1   0   1  ; "mode"
0002    TSETS    1   0   0  ; "orig_mode"
0003    MOV      2   0
0004    TGETS    1   0   2  ; "applyFooterMode"
0005    TGETS    3   0   3  ; "mode_list"
0006    TGETS    3   3   4  ; "page_progress"
0007    CALL     1   1   3
0008    RET0     0   1

-- BYTECODE -- readerfooter.lua:1788-1790
0001    MOV      2   0
0002    TGETS    1   0   0  ; "applyFooterMode"
0003    TGETS    3   0   1  ; "orig_mode"
0004    CALL     1   1   3
0005    RET0     0   1

-- BYTECODE -- readerfooter.lua:1792-1829
0001    TGETS    2   0   0  ; "has_no_mode"
0002    IST          2
0003    JMP      3 => 0008
0004    TGETS    2   0   1  ; "settings"
0005    TGETS    2   2   2  ; "lock_tap"
0006    ISF          2
0007    JMP      3 => 0009
0008 => RET0     0   1
0009 => TGETS    2   0   3  ; "view"
0010    TGETS    2   2   4  ; "flipping_visible"
0011    ISF          2
0012    JMP      3 => 0034
0013    TGETS    2   1   5  ; "pos"
0014    TGETS    3   0   6  ; "progress_bar"
0015    TGETS    3   3   7  ; "dimen"
0016    ISF          3
0017    JMP      4 => 0093
0018    TGETS    4   2   8  ; "x"
0019    TGETS    5   3   8  ; "x"
0020    SUBVV    4   4   5
0021    TGETS    5   3   9  ; "w"
0022    DIVVV    4   4   5
0023    TGETS    5   0  10  ; "ui"
0024    MOV      6   5
0025    TGETS    5   5  11  ; "handleEvent"
0026    UGET     7   0      ; Event
0027    MOV      8   7
0028    TGETS    7   7  12  ; "new"
0029    KSTR     9  13      ; "GotoPercentage"
0030    MOV     10   4
0031    CALL     7   0   4
0032    CALLM    5   1   1
0033    JMP      2 => 0093
0034 => TGETS    2   0   1  ; "settings"
0035    TGETS    2   2  14  ; "all_at_once"
0036    IST          2
0037    JMP      3 => 0041
0038    TGETS    2   0   0  ; "has_no_mode"
0039    ISF          2
0040    JMP      3 => 0053
0041 => TGETS    2   0  15  ; "mode"
0042    KSHORT   3   1
0043    ISGT     3   2
0044    JMP      2 => 0049
0045    TGETS    2   0  16  ; "mode_list"
0046    TGETS    2   2  17  ; "off"
0047    TSETS    2   0  15  ; "mode"
0048    JMP      2 => 0084
0049 => TGETS    2   0  16  ; "mode_list"
0050    TGETS    2   2  18  ; "page_progress"
0051    TSETS    2   0  15  ; "mode"
0052    JMP      2 => 0084
0053 => TGETS    2   0  15  ; "mode"
0054    ADDVN    2   2   0  ; 1
0055    TGETS    3   0  19  ; "mode_nb"
0056    MODVV    2   2   3
0057    TSETS    2   0  15  ; "mode"
0058    GGET     2  20      ; "ipairs"
0059    TGETS    3   0  21  ; "mode_index"
0060    CALL     2   4   2
0061    JMP      5 => 0082
0062 => TGETS    7   0  15  ; "mode"
0063    TGETS    8   0  16  ; "mode_list"
0064    TGETS    8   8  17  ; "off"
0065    ISNEV    7   8
0066    JMP      7 => 0068
0067    JMP      2 => 0084
0068 => TGETS    7   0  15  ; "mode"
0069    ISNEV    7   5
0070    JMP      7 => 0082
0071    TGETS    7   0   1  ; "settings"
0072    TGETV    7   7   6
0073    ISF          7
0074    JMP      8 => 0077
0075    JMP      2 => 0084
0076    JMP      7 => 0082
0077 => TGETS    7   0  15  ; "mode"
0078    ADDVN    7   7   0  ; 1
0079    TGETS    8   0  19  ; "mode_nb"
0080    MODVV    7   7   8
0081    TSETS    7   0  15  ; "mode"
0082 => ITERC    5   3   3
0083    ITERL    5 => 0062
0084 => MOV      3   0
0085    TGETS    2   0  22  ; "applyFooterMode"
0086    CALL     2   1   2
0087    GGET     2  23      ; "G_reader_settings"
0088    MOV      3   2
0089    TGETS    2   2  24  ; "saveSetting"
0090    KSTR     4  25      ; "reader_footer_mode"
0091    TGETS    5   0  15  ; "mode"
0092    CALL     2   1   4
0093 => MOV      3   0
0094    TGETS    2   0  26  ; "updateFooter"
0095    KPRI     4   2
0096    CALL     2   1   3
0097    KPRI     2   2
0098    RET1     2   2

-- BYTECODE -- readerfooter.lua:1831-1835
0001    TGETS    1   0   0  ; "mode"
0002    TGETS    2   0   1  ; "mode_list"
0003    TGETS    2   2   2  ; "off"
0004    ISNEV    1   2
0005    JMP      1 => 0007
0006    RET0     0   1
0007 => TGETS    1   0   3  ; "ui"
0008    MOV      2   1
0009    TGETS    1   1   4  ; "handleEvent"
0010    UGET     3   0      ; Event
0011    MOV      4   3
0012    TGETS    3   3   5  ; "new"
0013    KSTR     5   6      ; "ShowSkimtoDialog"
0014    CALL     3   0   3
0015    CALLM    1   1   1
0016    KPRI     1   2
0017    RET1     1   2

-- BYTECODE -- readerfooter.lua:1837-1849
0001    ISF          1
0002    JMP      2 => 0026
0003    TGETS    2   0   0  ; "mode"
0004    TGETS    3   0   1  ; "mode_list"
0005    TGETS    3   3   2  ; "off"
0006    ISNEV    2   3
0007    JMP      2 => 0015
0008    TGETS    2   0   3  ; "view"
0009    TGETS    2   2   4  ; "flipping_visible"
0010    IST          2
0011    JMP      2 => 0015
0012    MOV      3   0
0013    TGETS    2   0   5  ; "onTapFooter"
0014    CALL     2   1   2
0015 => TGETS    2   0   3  ; "view"
0016    TGETS    3   0   0  ; "mode"
0017    TGETS    4   0   1  ; "mode_list"
0018    TGETS    4   4   2  ; "off"
0019    ISNEV    3   4
0020    JMP      3 => 0023
0021    KPRI     3   1
0022    JMP      4 => 0024
0023 => KPRI     3   2
0024 => TSETS    3   2   6  ; "footer_visible"
0025    JMP      2 => 0031
0026 => MOV      3   0
0027    TGETS    2   0   7  ; "applyFooterMode"
0028    TGETS    4   0   1  ; "mode_list"
0029    TGETS    4   4   2  ; "off"
0030    CALL     2   1   3
0031 => RET0     0   1

-- BYTECODE -- readerfooter.lua:1851-1860
0001    MOV      4   0
0002    TGETS    3   0   0  ; "updateFooterContainer"
0003    CALL     3   1   2
0004    MOV      4   0
0005    TGETS    3   0   1  ; "resetLayout"
0006    KPRI     5   2
0007    CALL     3   1   3
0008    MOV      4   0
0009    TGETS    3   0   2  ; "updateFooter"
0010    ISFC     5   1
0011    JMP      5 => 0013
0012    NOT      5   2
0013 => ISFC     6   1
0014    JMP      6 => 0016
0015    MOV      6   2
0016 => CALL     3   1   4
0017    ISF          2
0018    JMP      3 => 0032
0019    TGETS    3   0   3  ; "ui"
0020    MOV      4   3
0021    TGETS    3   3   4  ; "handleEvent"
0022    UGET     5   0      ; Event
0023    MOV      6   5
0024    TGETS    5   5   5  ; "new"
0025    KSTR     7   6      ; "SetPageBottomMargin"
0026    TGETS    8   0   7  ; "view"
0027    TGETS    8   8   8  ; "document"
0028    TGETS    8   8   9  ; "configurable"
0029    TGETS    8   8  10  ; "b_page_margin"
0030    CALL     5   0   4
0031    CALLM    3   1   1
0032 => RET0     0   1

-- BYTECODE -- readerfooter.lua:1862-1867
0001    MOV      2   0
0002    TGETS    1   0   0  ; "updateFooter"
0003    CALL     1   1   2
0004    TGETS    1   0   1  ; "settings"
0005    TGETS    1   1   2  ; "auto_refresh_time"
0006    ISF          1
0007    JMP      2 => 0011
0008    MOV      2   0
0009    TGETS    1   0   3  ; "setupAutoRefreshTime"
0010    CALL     1   1   2
0011 => RET0     0   1

-- BYTECODE -- readerfooter.lua:1869-1874
0001    TGETS    1   0   0  ; "settings"
0002    TGETS    1   1   1  ; "auto_refresh_time"
0003    ISF          1
0004    JMP      2 => 0012
0005    UGET     1   0      ; UIManager
0006    MOV      2   1
0007    TGETS    1   1   2  ; "unschedule"
0008    TGETS    3   0   3  ; "autoRefreshTime"
0009    CALL     1   1   3
0010    KPRI     1   0
0011    TSETS    1   0   4  ; "onCloseDocument"
0012 => RET0     0   1

-- BYTECODE -- readerfooter.lua:1876-1880
0001    TGETS    1   0   0  ; "settings"
0002    TGETS    1   1   1  ; "frontlight"
0003    ISF          1
0004    JMP      2 => 0009
0005    MOV      2   0
0006    TGETS    1   0   2  ; "updateFooter"
0007    KPRI     3   2
0008    CALL     1   1   3
0009 => RET0     0   1

-- BYTECODE -- readerfooter.lua:1882-1885
0001    MOV      2   0
0002    TGETS    1   0   0  ; "updateFooterContainer"
0003    CALL     1   1   2
0004    MOV      2   0
0005    TGETS    1   0   1  ; "resetLayout"
0006    KPRI     3   2
0007    CALL     1   1   3
0008    RET0     0   1

-- BYTECODE -- readerfooter.lua:1887-1893
0001    GGET     2   1      ; "math"
0002    TGETS    2   2   2  ; "floor"
0003    TGETB    3   1   1
0004    TGETB    4   1   2
0005    ADDVV    3   3   4
0006    DIVVN    3   3   0  ; 2
0007    CALL     2   2   2
0008    TSETS    2   0   0  ; "book_margins_footer_width"
0009    TGETS    2   0   3  ; "settings"
0010    TGETS    2   2   4  ; "progress_margin"
0011    ISF          2
0012    JMP      3 => 0024
0013    TGETS    2   0   3  ; "settings"
0014    UGET     3   0      ; Screen
0015    MOV      4   3
0016    TGETS    3   3   6  ; "scaleBySize"
0017    TGETS    5   0   0  ; "book_margins_footer_width"
0018    CALL     3   2   3
0019    TSETS    3   2   5  ; "progress_margin_width"
0020    MOV      3   0
0021    TGETS    2   0   7  ; "refreshFooter"
0022    KPRI     4   2
0023    CALL     2   1   3
0024 => RET0     0   1

-- BYTECODE -- readerfooter.lua:1895-1898
0001    MOV      2   0
0002    TGETS    1   0   0  ; "updateFooterContainer"
0003    CALL     1   1   2
0004    MOV      2   0
0005    TGETS    1   0   1  ; "resetLayout"
0006    KPRI     3   2
0007    CALL     1   1   3
0008    RET0     0   1

-- BYTECODE -- readerfooter.lua:0-1901
0001    GGET     0   0      ; "require"
0002    KSTR     1   1      ; "ui/bidi"
0003    CALL     0   2   2
0004    GGET     1   0      ; "require"
0005    KSTR     2   2      ; "ffi/blitbuffer"
0006    CALL     1   2   2
0007    GGET     2   0      ; "require"
0008    KSTR     3   3      ; "ui/widget/container/bottomcontainer"
0009    CALL     2   2   2
0010    GGET     3   0      ; "require"
0011    KSTR     4   4      ; "ui/widget/container/centercontainer"
0012    CALL     3   2   2
0013    GGET     4   0      ; "require"
0014    KSTR     5   5      ; "device"
0015    CALL     4   2   2
0016    GGET     5   0      ; "require"
0017    KSTR     6   6      ; "ui/event"
0018    CALL     5   2   2
0019    GGET     6   0      ; "require"
0020    KSTR     7   7      ; "ui/font"
0021    CALL     6   2   2
0022    GGET     7   0      ; "require"
0023    KSTR     8   8      ; "ui/widget/container/framecontainer"
0024    CALL     7   2   2
0025    GGET     8   0      ; "require"
0026    KSTR     9   9      ; "ui/geometry"
0027    CALL     8   2   2
0028    GGET     9   0      ; "require"
0029    KSTR    10  10      ; "ui/widget/horizontalgroup"
0030    CALL     9   2   2
0031    GGET    10   0      ; "require"
0032    KSTR    11  11      ; "ui/widget/horizontalspan"
0033    CALL    10   2   2
0034    GGET    11   0      ; "require"
0035    KSTR    12  12      ; "ui/widget/container/leftcontainer"
0036    CALL    11   2   2
0037    GGET    12   0      ; "require"
0038    KSTR    13  13      ; "ui/widget/linewidget"
0039    CALL    12   2   2
0040    GGET    13   0      ; "require"
0041    KSTR    14  14      ; "ui/widget/progresswidget"
0042    CALL    13   2   2
0043    GGET    14   0      ; "require"
0044    KSTR    15  15      ; "ui/widget/container/rightcontainer"
0045    CALL    14   2   2
0046    GGET    15   0      ; "require"
0047    KSTR    16  16      ; "ui/size"
0048    CALL    15   2   2
0049    GGET    16   0      ; "require"
0050    KSTR    17  17      ; "ui/widget/textwidget"
0051    CALL    16   2   2
0052    GGET    17   0      ; "require"
0053    KSTR    18  18      ; "ui/uimanager"
0054    CALL    17   2   2
0055    GGET    18   0      ; "require"
0056    KSTR    19  19      ; "ui/widget/verticalgroup"
0057    CALL    18   2   2
0058    GGET    19   0      ; "require"
0059    KSTR    20  20      ; "ui/widget/verticalspan"
0060    CALL    19   2   2
0061    GGET    20   0      ; "require"
0062    KSTR    21  21      ; "ui/widget/container/widgetcontainer"
0063    CALL    20   2   2
0064    GGET    21   0      ; "require"
0065    KSTR    22  22      ; "util"
0066    CALL    21   2   2
0067    GGET    22   0      ; "require"
0068    KSTR    23  23      ; "ffi/util"
0069    CALL    22   2   2
0070    TGETS   22  22  24  ; "template"
0071    GGET    23   0      ; "require"
0072    KSTR    24  25      ; "gettext"
0073    CALL    23   2   2
0074    TGETS   24  23  26  ; "pgettext"
0075    TGETS   25   4  27  ; "screen"
0076    TDUP    26  28
0077    TDUP    27  45
0078    TDUP    28  29
0079    MOV     29  24
0080    KSTR    30  30      ; "FooterLetterPrefix"
0081    KSTR    31  31      ; "B:"
0082    CALL    29   2   3
0083    TSETS   29  28  32  ; "battery"
0084    MOV     29  24
0085    KSTR    30  30      ; "FooterLetterPrefix"
0086    KSTR    31  33      ; "R:"
0087    CALL    29   2   3
0088    TSETS   29  28  34  ; "percentage"
0089    MOV     29  24
0090    KSTR    30  30      ; "FooterLetterPrefix"
0091    KSTR    31  35      ; "TB:"
0092    CALL    29   2   3
0093    TSETS   29  28  36  ; "book_time_to_read"
0094    MOV     29  24
0095    KSTR    30  30      ; "FooterLetterPrefix"
0096    KSTR    31  37      ; "TC:"
0097    CALL    29   2   3
0098    TSETS   29  28  38  ; "chapter_time_to_read"
0099    MOV     29  24
0100    KSTR    30  30      ; "FooterLetterPrefix"
0101    KSTR    31  39      ; "L:"
0102    CALL    29   2   3
0103    TSETS   29  28  40  ; "frontlight"
0104    MOV     29  24
0105    KSTR    30  30      ; "FooterLetterPrefix"
0106    KSTR    31  41      ; "M:"
0107    CALL    29   2   3
0108    TSETS   29  28  42  ; "mem_usage"
0109    MOV     29  24
0110    KSTR    30  30      ; "FooterLetterPrefix"
0111    KSTR    31  43      ; "W:"
0112    CALL    29   2   3
0113    TSETS   29  28  44  ; "wifi_status"
0114    TSETS   28  27  46  ; "letters"
0115    TDUP    28  47
0116    TGETS   29   0  48  ; "mirroredUILayout"
0117    CALL    29   2   1
0118    ISF         29
0119    JMP     30 => 0122
0120    KSTR    29  49      ; "⇐"
0121    JMP     30 => 0123
0122 => KSTR    29  50      ; "⇒"
0123 => TSETS   29  28  51  ; "pages_left"
0124    TGETS   29   0  48  ; "mirroredUILayout"
0125    CALL    29   2   1
0126    ISF         29
0127    JMP     30 => 0130
0128    KSTR    29  52      ; "⤟"
0129    JMP     30 => 0131
0130 => KSTR    29  53      ; "⤠"
0131 => TSETS   29  28  34  ; "percentage"
0132    TGETS   29   0  48  ; "mirroredUILayout"
0133    CALL    29   2   1
0134    ISF         29
0135    JMP     30 => 0138
0136    KSTR    29  54      ; "⥖"
0137    JMP     30 => 0139
0138 => KSTR    29  55      ; "⤻"
0139 => TSETS   29  28  38  ; "chapter_time_to_read"
0140    TSETS   28  27  56  ; "icons"
0141    TGETS   28   0  48  ; "mirroredUILayout"
0142    CALL    28   2   1
0143    ISF         28
0144    JMP     29 => 0192
0145    GGET    28  57      ; "pairs"
0146    TGETS   29  27  46  ; "letters"
0147    CALL    28   4   2
0148    ISNEXT  31 => 0179
0149 => MOV     34  32
0150    TGETS   33  32  58  ; "find"
0151    KSTR    35  59      ; ":"
0152    CALL    33   2   3
0153    KPRI    34   0
0154    ISF         33
0155    JMP     35 => 0173
0156    MOV     36  32
0157    TGETS   35  32  60  ; "sub"
0158    KSHORT  37   1
0159    SUBVN   38  33   0  ; 1
0160    CALL    35   2   4
0161    MOV     37  32
0162    TGETS   36  32  60  ; "sub"
0163    MOV     38  33
0164    CALL    36   2   3
0165    TGETS   37   0  61  ; "wrap"
0166    MOV     38  35
0167    CALL    37   2   2
0168    TGETS   38   0  61  ; "wrap"
0169    MOV     39  36
0170    CALL    38   2   2
0171    CAT     34  37  38
0172    JMP     35 => 0177
0173 => TGETS   35   0  61  ; "wrap"
0174    MOV     36  32
0175    CALL    35   2   2
0176    MOV     34  35
0177 => TGETS   35  27  46  ; "letters"
0178    TSETV   34  35  31
0179 => ITERN   31   3   3
0180    ITERL   31 => 0149
0181    GGET    28  57      ; "pairs"
0182    TGETS   29  27  56  ; "icons"
0183    CALL    28   4   2
0184    ISNEXT  31 => 0190
0185 => TGETS   33  27  56  ; "icons"
0186    TGETS   34   0  61  ; "wrap"
0187    MOV     35  32
0188    CALL    34   2   2
0189    TSETV   34  33  31
0190 => ITERN   31   3   3
0191    ITERL   31 => 0185
0192 => KSHORT  28   7
0193    KSHORT  29   3
0194    KSHORT  30   2
0195    KSHORT  31  14
0196    TDUP    32  63
0197    FNEW    33  62      ; readerfooter.lua:101
0198    TSETS   33  32  64  ; "empty"
0199    FNEW    33  65      ; readerfooter.lua:102
0200    TSETS   33  32  40  ; "frontlight"
0201    FNEW    33  66      ; readerfooter.lua:116
0202    TSETS   33  32  32  ; "battery"
0203    FNEW    33  67      ; readerfooter.lua:155
0204    TSETS   33  32  68  ; "time"
0205    FNEW    33  69      ; readerfooter.lua:177
0206    TSETS   33  32  70  ; "page_progress"
0207    FNEW    33  71      ; readerfooter.lua:189
0208    TSETS   33  32  51  ; "pages_left"
0209    FNEW    33  72      ; readerfooter.lua:196
0210    TSETS   33  32  34  ; "percentage"
0211    FNEW    33  73      ; readerfooter.lua:208
0212    TSETS   33  32  36  ; "book_time_to_read"
0213    FNEW    33  74      ; readerfooter.lua:214
0214    TSETS   33  32  38  ; "chapter_time_to_read"
0215    FNEW    33  75      ; readerfooter.lua:222
0216    TSETS   33  32  42  ; "mem_usage"
0217    FNEW    33  76      ; readerfooter.lua:236
0218    TSETS   33  32  44  ; "wifi_status"
0219    FNEW    33  77      ; readerfooter.lua:246
0220    TSETS   33  32  78  ; "book_title"
0221    FNEW    33  79      ; readerfooter.lua:265
0222    TSETS   33  32  80  ; "book_chapter"
0223    MOV     34  20
0224    TGETS   33  20  81  ; "extend"
0225    TDUP    35  82
0226    TGETS   36  26  70  ; "page_progress"
0227    TSETS   36  35  83  ; "mode"
0228    MOV     37  25
0229    TGETS   36  25  84  ; "scaleBySize"
0230    GGET    38  85      ; "DMINIBAR_CONTAINER_HEIGHT"
0231    CALL    36   2   3
0232    TSETS   36  35  86  ; "height"
0233    MOV     37  25
0234    TGETS   36  25  84  ; "scaleBySize"
0235    KSHORT  38  10
0236    CALL    36   2   3
0237    TSETS   36  35  87  ; "horizontal_margin"
0238    MOV     37  25
0239    TGETS   36  25  84  ; "scaleBySize"
0240    KSHORT  38  10
0241    CALL    36   2   3
0242    TSETS   36  35  88  ; "text_left_margin"
0243    MOV     37  25
0244    TGETS   36  25  84  ; "scaleBySize"
0245    KSHORT  38   1
0246    CALL    36   2   3
0247    TSETS   36  35  89  ; "bottom_padding"
0248    TNEW    36   0
0249    TSETS   36  35  90  ; "settings"
0250    TSETS   32  35  91  ; "textGeneratorMap"
0251    CALL    33   2   3
0252    FNEW    34  93      ; readerfooter.lua:303
0253    TSETS   34  33  92  ; "init"
0254    FNEW    34  95      ; readerfooter.lua:451
0255    TSETS   34  33  94  ; "updateFooterContainer"
0256    FNEW    34  97      ; readerfooter.lua:525
0257    TSETS   34  33  96  ; "setupAutoRefreshTime"
0258    FNEW    34  99      ; readerfooter.lua:538
0259    TSETS   34  33  98  ; "setupTouchZones"
0260    FNEW    34 101      ; readerfooter.lua:571
0261    TSETS   34  33 100  ; "resetLayout"
0262    FNEW    34 103      ; readerfooter.lua:606
0263    TSETS   34  33 102  ; "getHeight"
0264    FNEW    34 105      ; readerfooter.lua:614
0265    TSETS   34  33 104  ; "disableFooter"
0266    FNEW    34 107      ; readerfooter.lua:626
0267    TSETS   34  33 106  ; "updateFooterTextGenerator"
0268    FNEW    34 109      ; readerfooter.lua:654
0269    TSETS   34  33 108  ; "progressPercentage"
0270    FNEW    34 111      ; readerfooter.lua:667
0271    TSETS   34  33 110  ; "textOptionTitles"
0272    FNEW    34 113      ; readerfooter.lua:690
0273    TSETS   34  33 112  ; "addToMainMenu"
0274    FNEW    34 115      ; readerfooter.lua:1538
0275    TSETS   34  33 114  ; "genFooterText"
0276    FNEW    34 117      ; readerfooter.lua:1540
0277    TSETS   34  33 116  ; "genAllFooterText"
0278    FNEW    34 119      ; readerfooter.lua:1557
0279    TSETS   34  33 118  ; "setTocMarkers"
0280    FNEW    34 121      ; readerfooter.lua:1592
0281    TSETS   34  33 120  ; "getAvgTimePerPage"
0282    FNEW    34 123      ; readerfooter.lua:1596
0283    TSETS   34  33 122  ; "getDataFromStatistics"
0284    FNEW    34 125      ; readerfooter.lua:1609
0285    TSETS   34  33 124  ; "updateFooter"
0286    FNEW    34 127      ; readerfooter.lua:1617
0287    TSETS   34  33 126  ; "updateFooterPage"
0288    FNEW    34 129      ; readerfooter.lua:1623
0289    TSETS   34  33 128  ; "updateFooterPos"
0290    FNEW    34 131      ; readerfooter.lua:1631
0291    TSETS   34  33 130  ; "updateFooterText"
0292    FNEW    34 133      ; readerfooter.lua:1635
0293    TSETS   34  33 132  ; "_updateFooterText"
0294    FNEW    34 135      ; readerfooter.lua:1696
0295    TSETS   34  33 134  ; "onPageUpdate"
0296    FNEW    34 137      ; readerfooter.lua:1703
0297    TSETS   34  33 136  ; "onPosUpdate"
0298    TGETS   34  33 124  ; "updateFooter"
0299    TSETS   34  33 138  ; "onUpdatePos"
0300    FNEW    34 140      ; readerfooter.lua:1718
0301    TSETS   34  33 139  ; "onReaderReady"
0302    FNEW    34 142      ; readerfooter.lua:1737
0303    TSETS   34  33 141  ; "onReadSettings"
0304    FNEW    34 144      ; readerfooter.lua:1746
0305    TSETS   34  33 143  ; "applyFooterMode"
0306    FNEW    34 146      ; readerfooter.lua:1783
0307    TSETS   34  33 145  ; "onEnterFlippingMode"
0308    FNEW    34 148      ; readerfooter.lua:1788
0309    TSETS   34  33 147  ; "onExitFlippingMode"
0310    FNEW    34 150      ; readerfooter.lua:1792
0311    TSETS   34  33 149  ; "onTapFooter"
0312    FNEW    34 152      ; readerfooter.lua:1831
0313    TSETS   34  33 151  ; "onHoldFooter"
0314    FNEW    34 154      ; readerfooter.lua:1837
0315    TSETS   34  33 153  ; "setVisible"
0316    FNEW    34 156      ; readerfooter.lua:1851
0317    TSETS   34  33 155  ; "refreshFooter"
0318    FNEW    34 158      ; readerfooter.lua:1862
0319    TSETS   34  33 157  ; "onResume"
0320    FNEW    34 160      ; readerfooter.lua:1869
0321    TSETS   34  33 159  ; "onSuspend"
0322    FNEW    34 162      ; readerfooter.lua:1876
0323    TSETS   34  33 161  ; "onFrontlightStateChanged"
0324    FNEW    34 164      ; readerfooter.lua:1882
0325    TSETS   34  33 163  ; "onChangeScreenMode"
0326    FNEW    34 166      ; readerfooter.lua:1887
0327    TSETS   34  33 165  ; "onSetPageHorizMargins"
0328    FNEW    34 168      ; readerfooter.lua:1895
0329    TSETS   34  33 167  ; "onScreenResize"
0330    UCLO     0 => 0331
0331 => RET1    33   2

