
main <./frontend/apps/reader/modules/readergesture.lua:0,0> (544 instructions, 2176 bytes at 0x7fad94406900)
0+ params, 64 slots, 0 upvalues, 27 locals, 255 constants, 19 functions
	1	[1]	GETGLOBAL	0 -1	; require
	2	[1]	LOADK    	1 -2	; "ui/bidi"
	3	[1]	CALL     	0 2 2
	4	[2]	GETGLOBAL	1 -1	; require
	5	[2]	LOADK    	2 -3	; "ui/widget/confirmbox"
	6	[2]	CALL     	1 2 2
	7	[3]	GETGLOBAL	2 -1	; require
	8	[3]	LOADK    	3 -4	; "datastorage"
	9	[3]	CALL     	2 2 2
	10	[4]	GETGLOBAL	3 -1	; require
	11	[4]	LOADK    	4 -5	; "device"
	12	[4]	CALL     	3 2 2
	13	[5]	GETGLOBAL	4 -1	; require
	14	[5]	LOADK    	5 -6	; "ui/event"
	15	[5]	CALL     	4 2 2
	16	[6]	GETGLOBAL	5 -1	; require
	17	[6]	LOADK    	6 -7	; "ui/geometry"
	18	[6]	CALL     	5 2 2
	19	[7]	GETGLOBAL	6 -1	; require
	20	[7]	LOADK    	7 -8	; "ui/gesturerange"
	21	[7]	CALL     	6 2 2
	22	[8]	GETGLOBAL	7 -1	; require
	23	[8]	LOADK    	8 -9	; "ui/widget/infomessage"
	24	[8]	CALL     	7 2 2
	25	[9]	GETGLOBAL	8 -1	; require
	26	[9]	LOADK    	9 -10	; "ui/widget/container/inputcontainer"
	27	[9]	CALL     	8 2 2
	28	[10]	GETGLOBAL	9 -1	; require
	29	[10]	LOADK    	10 -11	; "ui/widget/inputdialog"
	30	[10]	CALL     	9 2 2
	31	[11]	GETGLOBAL	10 -1	; require
	32	[11]	LOADK    	11 -12	; "luadata"
	33	[11]	CALL     	10 2 2
	34	[12]	GETGLOBAL	11 -1	; require
	35	[12]	LOADK    	12 -13	; "ui/widget/notification"
	36	[12]	CALL     	11 2 2
	37	[13]	GETGLOBAL	12 -1	; require
	38	[13]	LOADK    	13 -5	; "device"
	39	[13]	CALL     	12 2 2
	40	[13]	GETTABLE 	12 12 -14	; "screen"
	41	[14]	GETGLOBAL	13 -1	; require
	42	[14]	LOADK    	14 -15	; "ui/uimanager"
	43	[14]	CALL     	13 2 2
	44	[15]	GETGLOBAL	14 -1	; require
	45	[15]	LOADK    	15 -16	; "ffi/util"
	46	[15]	CALL     	14 2 2
	47	[15]	GETTABLE 	14 14 -17	; "template"
	48	[16]	GETGLOBAL	15 -1	; require
	49	[16]	LOADK    	16 -18	; "gettext"
	50	[16]	CALL     	15 2 2
	51	[17]	GETGLOBAL	16 -1	; require
	52	[17]	LOADK    	17 -19	; "logger"
	53	[17]	CALL     	16 2 2
	54	[19]	SELF     	17 8 -20	; "new"
	55	[19]	NEWTABLE 	19 0 0
	56	[19]	CALL     	17 3 2
	57	[21]	NEWTABLE 	18 0 34
	58	[22]	MOVE     	19 15
	59	[22]	LOADK    	20 -22	; "Nothing"
	60	[22]	CALL     	19 2 2
	61	[22]	SETTABLE 	18 -21 19	; "nothing" -
	62	[23]	MOVE     	19 15
	63	[23]	LOADK    	20 -24	; "Pass through"
	64	[23]	CALL     	19 2 2
	65	[23]	SETTABLE 	18 -23 19	; "ignore" -
	66	[25]	MOVE     	19 15
	67	[25]	LOADK    	20 -26	; "Back 10 pages"
	68	[25]	CALL     	19 2 2
	69	[25]	SETTABLE 	18 -25 19	; "page_jmp_back_10" -
	70	[26]	MOVE     	19 15
	71	[26]	LOADK    	20 -28	; "Previous page"
	72	[26]	CALL     	19 2 2
	73	[26]	SETTABLE 	18 -27 19	; "page_jmp_back_1" -
	74	[27]	MOVE     	19 15
	75	[27]	LOADK    	20 -30	; "Forward 10 pages"
	76	[27]	CALL     	19 2 2
	77	[27]	SETTABLE 	18 -29 19	; "page_jmp_fwd_10" -
	78	[28]	MOVE     	19 15
	79	[28]	LOADK    	20 -32	; "Next page"
	80	[28]	CALL     	19 2 2
	81	[28]	SETTABLE 	18 -31 19	; "page_jmp_fwd_1" -
	82	[29]	MOVE     	19 15
	83	[29]	LOADK    	20 -34	; "Previous chapter"
	84	[29]	CALL     	19 2 2
	85	[29]	SETTABLE 	18 -33 19	; "prev_chapter" -
	86	[30]	MOVE     	19 15
	87	[30]	LOADK    	20 -36	; "Next chapter"
	88	[30]	CALL     	19 2 2
	89	[30]	SETTABLE 	18 -35 19	; "next_chapter" -
	90	[31]	MOVE     	19 15
	91	[31]	LOADK    	20 -38	; "First page"
	92	[31]	CALL     	19 2 2
	93	[31]	SETTABLE 	18 -37 19	; "first_page" -
	94	[32]	MOVE     	19 15
	95	[32]	LOADK    	20 -40	; "Last page"
	96	[32]	CALL     	19 2 2
	97	[32]	SETTABLE 	18 -39 19	; "last_page" -
	98	[33]	MOVE     	19 15
	99	[33]	LOADK    	20 -42	; "Previous bookmark"
	100	[33]	CALL     	19 2 2
	101	[33]	SETTABLE 	18 -41 19	; "prev_bookmark" -
	102	[34]	MOVE     	19 15
	103	[34]	LOADK    	20 -44	; "Next bookmark"
	104	[34]	CALL     	19 2 2
	105	[34]	SETTABLE 	18 -43 19	; "next_bookmark" -
	106	[35]	MOVE     	19 15
	107	[35]	LOADK    	20 -46	; "Go to"
	108	[35]	CALL     	19 2 2
	109	[35]	SETTABLE 	18 -45 19	; "go_to" -
	110	[36]	MOVE     	19 15
	111	[36]	LOADK    	20 -48	; "Skim"
	112	[36]	CALL     	19 2 2
	113	[36]	SETTABLE 	18 -47 19	; "skim" -
	114	[37]	MOVE     	19 15
	115	[37]	LOADK    	20 -50	; "Back"
	116	[37]	CALL     	19 2 2
	117	[37]	SETTABLE 	18 -49 19	; "back" -
	118	[38]	MOVE     	19 15
	119	[38]	LOADK    	20 -52	; "Back to previous location"
	120	[38]	CALL     	19 2 2
	121	[38]	SETTABLE 	18 -51 19	; "previous_location" -
	122	[39]	MOVE     	19 15
	123	[39]	LOADK    	20 -54	; "Go to latest bookmark"
	124	[39]	CALL     	19 2 2
	125	[39]	SETTABLE 	18 -53 19	; "latest_bookmark" -
	126	[40]	MOVE     	19 15
	127	[40]	LOADK    	20 -56	; "Follow nearest link"
	128	[40]	CALL     	19 2 2
	129	[40]	SETTABLE 	18 -55 19	; "follow_nearest_link" -
	130	[41]	MOVE     	19 15
	131	[41]	LOADK    	20 -58	; "Follow nearest internal link"
	132	[41]	CALL     	19 2 2
	133	[41]	SETTABLE 	18 -57 19	; "follow_nearest_internal_link" -
	134	[42]	MOVE     	19 15
	135	[42]	LOADK    	20 -60	; "Clear location history"
	136	[42]	CALL     	19 2 2
	137	[42]	SETTABLE 	18 -59 19	; "clear_location_history" -
	138	[44]	MOVE     	19 15
	139	[44]	LOADK    	20 -62	; "Table of contents"
	140	[44]	CALL     	19 2 2
	141	[44]	SETTABLE 	18 -61 19	; "toc" -
	142	[45]	MOVE     	19 15
	143	[45]	LOADK    	20 -64	; "Bookmarks"
	144	[45]	CALL     	19 2 2
	145	[45]	SETTABLE 	18 -63 19	; "bookmarks" -
	146	[46]	MOVE     	19 15
	147	[46]	LOADK    	20 -66	; "Reading progress"
	148	[46]	CALL     	19 2 2
	149	[46]	SETTABLE 	18 -65 19	; "reading_progress" -
	150	[47]	MOVE     	19 15
	151	[47]	LOADK    	20 -68	; "Book statistics"
	152	[47]	CALL     	19 2 2
	153	[47]	SETTABLE 	18 -67 19	; "book_statistics" -
	154	[48]	MOVE     	19 15
	155	[48]	LOADK    	20 -70	; "Book status"
	156	[48]	CALL     	19 2 2
	157	[48]	SETTABLE 	18 -69 19	; "book_status" -
	158	[49]	MOVE     	19 15
	159	[49]	LOADK    	20 -72	; "Book information"
	160	[49]	CALL     	19 2 2
	161	[49]	SETTABLE 	18 -71 19	; "book_info" -
	162	[50]	MOVE     	19 15
	163	[50]	LOADK    	20 -74	; "Book description"
	164	[50]	CALL     	19 2 2
	165	[50]	SETTABLE 	18 -73 19	; "book_description" -
	166	[51]	MOVE     	19 15
	167	[51]	LOADK    	20 -76	; "Book cover"
	168	[51]	CALL     	19 2 2
	169	[51]	SETTABLE 	18 -75 19	; "book_cover" -
	170	[52]	MOVE     	19 15
	171	[52]	LOADK    	20 -78	; "Statistics calendar view"
	172	[52]	CALL     	19 2 2
	173	[52]	SETTABLE 	18 -77 19	; "stats_calendar_view" -
	174	[54]	MOVE     	19 15
	175	[54]	LOADK    	20 -80	; "History"
	176	[54]	CALL     	19 2 2
	177	[54]	SETTABLE 	18 -79 19	; "history" -
	178	[55]	MOVE     	19 15
	179	[55]	LOADK    	20 -82	; "Open previous document"
	180	[55]	CALL     	19 2 2
	181	[55]	SETTABLE 	18 -81 19	; "open_previous_document" -
	182	[56]	MOVE     	19 15
	183	[56]	LOADK    	20 -84	; "File browser"
	184	[56]	CALL     	19 2 2
	185	[56]	SETTABLE 	18 -83 19	; "filemanager" -
	186	[57]	MOVE     	19 15
	187	[57]	LOADK    	20 -86	; "Favorites"
	188	[57]	CALL     	19 2 2
	189	[57]	SETTABLE 	18 -85 19	; "favorites" -
	190	[59]	MOVE     	19 15
	191	[59]	LOADK    	20 -88	; "Dictionary lookup"
	192	[59]	CALL     	19 2 2
	193	[59]	SETTABLE 	18 -87 19	; "dictionary_lookup" -
	194	[60]	MOVE     	19 15
	195	[60]	LOADK    	20 -90	; "Wikipedia lookup"
	196	[60]	CALL     	19 2 2
	197	[60]	SETTABLE 	18 -89 19	; "wikipedia_lookup" -
	198	[61]	MOVE     	19 15
	199	[61]	LOADK    	20 -92	; "Fulltext search"
	200	[61]	CALL     	19 2 2
	201	[61]	SETTABLE 	18 -91 19	; "fulltext_search" -
	202	[62]	MOVE     	19 15
	203	[62]	LOADK    	20 -94	; "File search"
	204	[62]	CALL     	19 2 2
	205	[62]	SETTABLE 	18 -93 19	; "file_search" -
	206	[64]	MOVE     	19 15
	207	[64]	LOADK    	20 -96	; "Full screen refresh"
	208	[64]	CALL     	19 2 2
	209	[64]	SETTABLE 	18 -95 19	; "full_refresh" -
	210	[65]	MOVE     	19 15
	211	[65]	LOADK    	20 -98	; "Night mode"
	212	[65]	CALL     	19 2 2
	213	[65]	SETTABLE 	18 -97 19	; "night_mode" -
	214	[66]	MOVE     	19 15
	215	[66]	LOADK    	20 -100	; "Suspend"
	216	[66]	CALL     	19 2 2
	217	[66]	SETTABLE 	18 -99 19	; "suspend" -
	218	[67]	MOVE     	19 15
	219	[67]	LOADK    	20 -102	; "Exit KOReader"
	220	[67]	CALL     	19 2 2
	221	[67]	SETTABLE 	18 -101 19	; "exit" -
	222	[68]	MOVE     	19 15
	223	[68]	LOADK    	20 -104	; "Restart KOReader"
	224	[68]	CALL     	19 2 2
	225	[68]	SETTABLE 	18 -103 19	; "restart" -
	226	[69]	MOVE     	19 15
	227	[69]	LOADK    	20 -106	; "Reboot the device"
	228	[69]	CALL     	19 2 2
	229	[69]	SETTABLE 	18 -105 19	; "reboot" -
	230	[70]	MOVE     	19 15
	231	[70]	LOADK    	20 -108	; "Power off"
	232	[70]	CALL     	19 2 2
	233	[70]	SETTABLE 	18 -107 19	; "poweroff" -
	234	[71]	MOVE     	19 15
	235	[71]	LOADK    	20 -110	; "Show menu"
	236	[71]	CALL     	19 2 2
	237	[71]	SETTABLE 	18 -109 19	; "show_menu" -
	238	[72]	MOVE     	19 15
	239	[72]	LOADK    	20 -112	; "Show bottom menu"
	240	[72]	CALL     	19 2 2
	241	[72]	SETTABLE 	18 -111 19	; "show_config_menu" -
	242	[73]	MOVE     	19 15
	243	[73]	LOADK    	20 -114	; "Show frontlight dialog"
	244	[73]	CALL     	19 2 2
	245	[73]	SETTABLE 	18 -113 19	; "show_frontlight_dialog" -
	246	[74]	MOVE     	19 15
	247	[74]	LOADK    	20 -116	; "Toggle frontlight"
	248	[74]	CALL     	19 2 2
	249	[74]	SETTABLE 	18 -115 19	; "toggle_frontlight" -
	250	[75]	MOVE     	19 15
	251	[75]	LOADK    	20 -118	; "Increase frontlight brightness"
	252	[75]	CALL     	19 2 2
	253	[75]	SETTABLE 	18 -117 19	; "increase_frontlight" -
	254	[76]	MOVE     	19 15
	255	[76]	LOADK    	20 -120	; "Decrease frontlight brightness"
	256	[76]	CALL     	19 2 2
	257	[76]	SETTABLE 	18 -119 19	; "decrease_frontlight" -
	258	[77]	MOVE     	19 15
	259	[77]	LOADK    	20 -122	; "Increase frontlight warmth"
	260	[77]	CALL     	19 2 2
	261	[77]	SETTABLE 	18 -121 19	; "increase_frontlight_warmth" -
	262	[78]	MOVE     	19 15
	263	[78]	LOADK    	20 -124	; "Decrease frontlight warmth"
	264	[78]	CALL     	19 2 2
	265	[78]	SETTABLE 	18 -123 19	; "decrease_frontlight_warmth" -
	266	[79]	MOVE     	19 15
	267	[79]	LOADK    	20 -126	; "Toggle hold corners"
	268	[79]	CALL     	19 2 2
	269	[79]	SETTABLE 	18 -125 19	; "toggle_hold_corners" -
	270	[80]	MOVE     	19 15
	271	[80]	LOADK    	20 -128	; "Toggle accelerometer"
	272	[80]	CALL     	19 2 2
	273	[80]	SETTABLE 	18 -127 19	; "toggle_gsensor" -
	274	[81]	MOVE     	19 15
	275	[81]	LOADK    	20 -130	; "Toggle rotation"
	276	[81]	CALL     	19 2 2
	277	[81]	SETTABLE 	18 -129 19	; "toggle_rotation" -
	278	[83]	MOVE     	19 15
	279	[83]	LOADK    	20 -132	; "Turn on Wi-Fi"
	280	[83]	CALL     	19 2 2
	281	[83]	SETTABLE 	18 -131 19	; "wifi_on" -
	282	[84]	MOVE     	19 15
	283	[84]	LOADK    	20 -134	; "Turn off Wi-Fi"
	284	[84]	CALL     	19 2 2
	285	[84]	SETTABLE 	18 -133 19	; "wifi_off" -
	286	[85]	MOVE     	19 15
	287	[85]	LOADK    	20 -136	; "Toggle Wi-Fi"
	288	[85]	CALL     	19 2 2
	289	[85]	SETTABLE 	18 -135 19	; "toggle_wifi" -
	290	[87]	MOVE     	19 15
	291	[87]	LOADK    	20 -138	; "Toggle bookmark"
	292	[87]	CALL     	19 2 2
	293	[87]	SETTABLE 	18 -137 19	; "toggle_bookmark" -
	294	[88]	MOVE     	19 15
	295	[88]	LOADK    	20 -140	; "Toggle page flipping"
	296	[88]	CALL     	19 2 2
	297	[88]	SETTABLE 	18 -139 19	; "toggle_page_flipping" -
	298	[89]	MOVE     	19 15
	299	[89]	LOADK    	20 -142	; "Toggle reflow"
	300	[89]	CALL     	19 2 2
	301	[89]	SETTABLE 	18 -141 19	; "toggle_reflow" -
	302	[90]	MOVE     	19 15
	303	[90]	LOADK    	20 -144	; "Toggle page turn direction"
	304	[90]	CALL     	19 2 2
	305	[90]	SETTABLE 	18 -143 19	; "toggle_inverse_reading_order" -
	306	[92]	MOVE     	19 15
	307	[92]	LOADK    	20 -146	; "Zoom to fit content width"
	308	[92]	CALL     	19 2 2
	309	[92]	SETTABLE 	18 -145 19	; "zoom_contentwidth" -
	310	[93]	MOVE     	19 15
	311	[93]	LOADK    	20 -148	; "Zoom to fit content height"
	312	[93]	CALL     	19 2 2
	313	[93]	SETTABLE 	18 -147 19	; "zoom_contentheight" -
	314	[94]	MOVE     	19 15
	315	[94]	LOADK    	20 -150	; "Zoom to fit page width"
	316	[94]	CALL     	19 2 2
	317	[94]	SETTABLE 	18 -149 19	; "zoom_pagewidth" -
	318	[95]	MOVE     	19 15
	319	[95]	LOADK    	20 -152	; "Zoom to fit page height"
	320	[95]	CALL     	19 2 2
	321	[95]	SETTABLE 	18 -151 19	; "zoom_pageheight" -
	322	[96]	MOVE     	19 15
	323	[96]	LOADK    	20 -154	; "Zoom to fit column"
	324	[96]	CALL     	19 2 2
	325	[96]	SETTABLE 	18 -153 19	; "zoom_column" -
	326	[97]	MOVE     	19 15
	327	[97]	LOADK    	20 -156	; "Zoom to fit content"
	328	[97]	CALL     	19 2 2
	329	[97]	SETTABLE 	18 -155 19	; "zoom_content" -
	330	[98]	MOVE     	19 15
	331	[98]	LOADK    	20 -158	; "Zoom to fit page"
	332	[98]	CALL     	19 2 2
	333	[98]	SETTABLE 	18 -157 19	; "zoom_page" -
	334	[100]	MOVE     	19 15
	335	[100]	LOADK    	20 -160	; "Increase font size"
	336	[100]	CALL     	19 2 2
	337	[100]	SETTABLE 	18 -159 19	; "increase_font" -
	338	[101]	MOVE     	19 15
	339	[101]	LOADK    	20 -162	; "Decrease font size"
	340	[101]	CALL     	19 2 2
	341	[101]	SETTABLE 	18 -161 19	; "decrease_font" -
	342	[103]	MOVE     	19 15
	343	[103]	LOADK    	20 -164	; "Folder up"
	344	[103]	CALL     	19 2 2
	345	[103]	SETTABLE 	18 -163 19	; "folder_up" -
	346	[104]	MOVE     	19 15
	347	[104]	LOADK    	20 -166	; "Show plus menu"
	348	[104]	CALL     	19 2 2
	349	[104]	SETTABLE 	18 -165 19	; "show_plus_menu" -
	350	[105]	MOVE     	19 15
	351	[105]	LOADK    	20 -168	; "Folder shortcuts"
	352	[105]	CALL     	19 2 2
	353	[105]	SETTABLE 	18 -167 19	; "folder_shortcuts" -
	354	[106]	MOVE     	19 15
	355	[106]	LOADK    	20 -170	; "Cycle highlight action"
	356	[106]	CALL     	19 2 2
	357	[106]	SETTABLE 	18 -169 19	; "cycle_highlight_action" -
	358	[107]	MOVE     	19 15
	359	[107]	LOADK    	20 -172	; "Cycle highlight style"
	360	[107]	CALL     	19 2 2
	361	[107]	SETTABLE 	18 -171 19	; "cycle_highlight_style" -
	362	[108]	MOVE     	19 15
	363	[108]	LOADK    	20 -174	; "Wallabag retrieval"
	364	[108]	CALL     	19 2 2
	365	[108]	SETTABLE 	18 -173 19	; "wallabag_download" -
	366	[109]	MOVE     	19 15
	367	[109]	LOADK    	20 -176	; "Push progress from this device"
	368	[109]	CALL     	19 2 2
	369	[109]	SETTABLE 	18 -175 19	; "kosync_push_progress" -
	370	[110]	MOVE     	19 15
	371	[110]	LOADK    	20 -178	; "Pull progress from other devices"
	372	[110]	CALL     	19 2 2
	373	[110]	SETTABLE 	18 -177 19	; "kosync_pull_progress" -
	374	[113]	SELF     	19 2 -179	; "getSettingsDir"
	375	[113]	CALL     	19 2 2
	376	[113]	LOADK    	20 -180	; "/multiswipes.lua"
	377	[113]	CONCAT   	19 19 20
	378	[114]	SELF     	20 10 -181	; "open"
	379	[114]	MOVE     	22 19
	380	[114]	NEWTABLE 	23 0 1
	381	[114]	SETTABLE 	23 -182 -183	; "name" "MultiSwipes"
	382	[114]	CALL     	20 4 2
	383	[115]	SELF     	21 20 -184	; "readSetting"
	384	[115]	LOADK    	23 -185	; "multiswipes"
	385	[115]	CALL     	21 3 2
	386	[117]	NEWTABLE 	22 27 0
	387	[118]	LOADK    	23 -186	; "west east"
	388	[119]	LOADK    	24 -187	; "east west"
	389	[120]	LOADK    	25 -188	; "north south"
	390	[121]	LOADK    	26 -189	; "south north"
	391	[122]	LOADBOOL 	27 1 0
	392	[123]	LOADK    	28 -190	; "north west"
	393	[124]	LOADK    	29 -191	; "north east"
	394	[125]	LOADK    	30 -192	; "south west"
	395	[126]	LOADK    	31 -193	; "south east"
	396	[127]	LOADK    	32 -194	; "east north"
	397	[128]	LOADK    	33 -195	; "west north"
	398	[129]	LOADK    	34 -196	; "east south"
	399	[130]	LOADK    	35 -197	; "west south"
	400	[131]	LOADBOOL 	36 1 0
	401	[132]	LOADK    	37 -198	; "north south north"
	402	[133]	LOADK    	38 -199	; "south north south"
	403	[134]	LOADK    	39 -200	; "west east west"
	404	[135]	LOADK    	40 -201	; "east west east"
	405	[136]	LOADBOOL 	41 1 0
	406	[137]	LOADK    	42 -202	; "south west north"
	407	[138]	LOADK    	43 -203	; "north east south"
	408	[139]	LOADK    	44 -204	; "north west south"
	409	[140]	LOADK    	45 -205	; "west south east"
	410	[141]	LOADK    	46 -206	; "west north east"
	411	[142]	LOADK    	47 -207	; "east south west"
	412	[143]	LOADK    	48 -208	; "east north west"
	413	[144]	LOADK    	49 -209	; "south east north"
	414	[145]	LOADBOOL 	50 1 0
	415	[146]	LOADK    	51 -210	; "east north west east"
	416	[147]	LOADK    	52 -211	; "south east north south"
	417	[148]	LOADBOOL 	53 1 0
	418	[149]	LOADK    	54 -212	; "east south west north"
	419	[150]	LOADK    	55 -213	; "west south east north"
	420	[151]	LOADK    	56 -214	; "south east north west"
	421	[152]	LOADK    	57 -215	; "south west north east"
	422	[153]	LOADBOOL 	58 1 0
	423	[154]	LOADK    	59 -216	; "southeast northeast"
	424	[155]	LOADK    	60 -217	; "northeast southeast"
	425	[158]	LOADK    	61 -218	; "northwest southwest northwest"
	426	[159]	LOADK    	62 -219	; "southeast southwest northwest"
	427	[161]	LOADK    	63 -220	; "southeast northeast northwest"
	428	[161]	SETLIST  	22 41 1	; 1
	429	[162]	NEWTABLE 	23 0 0
	430	[163]	MOVE     	24 15
	431	[166]	LOADK    	25 -221	; "Multiswipes allow you to perform complex gestures built up out of multiple swipe directions, never losing touch with the screen.\n\nThese advanced gestures consist of either straight swipes or diagonal swipes. To ensure accuracy, they can't be mixed."
	432	[163]	CALL     	24 2 2
	433	[276]	CLOSURE  	25 0	; 0x7fad94409900
	434	[276]	MOVE     	0 3
	435	[276]	MOVE     	0 0
	436	[276]	MOVE     	0 16
	437	[168]	SETTABLE 	17 -222 25	; "init" -
	438	[289]	CLOSURE  	25 1	; 0x7fad94409ec0
	439	[278]	SETTABLE 	17 -223 25	; "initGesture" -
	440	[298]	CLOSURE  	25 2	; 0x7fad9440b390
	441	[298]	MOVE     	0 15
	442	[291]	SETTABLE 	17 -224 25	; "genMultiswipeSubmenu" -
	443	[699]	CLOSURE  	25 3	; 0x7fad9440bad0
	444	[699]	MOVE     	0 18
	445	[699]	MOVE     	0 15
	446	[699]	MOVE     	0 14
	447	[699]	MOVE     	0 24
	448	[699]	MOVE     	0 9
	449	[699]	MOVE     	0 13
	450	[699]	MOVE     	0 16
	451	[699]	MOVE     	0 23
	452	[699]	MOVE     	0 7
	453	[699]	MOVE     	0 20
	454	[699]	MOVE     	0 6
	455	[699]	MOVE     	0 5
	456	[699]	MOVE     	0 12
	457	[699]	MOVE     	0 17
	458	[699]	MOVE     	0 3
	459	[300]	SETTABLE 	17 -225 25	; "addToMainMenu" -
	460	[822]	CLOSURE  	25 4	; 0x7fad944161c0
	461	[822]	MOVE     	0 17
	462	[822]	MOVE     	0 3
	463	[822]	MOVE     	0 14
	464	[822]	MOVE     	0 15
	465	[822]	MOVE     	0 18
	466	[701]	SETTABLE 	17 -226 25	; "buildMenu" -
	467	[909]	CLOSURE  	25 5	; 0x7fad94416480
	468	[909]	MOVE     	0 23
	469	[909]	MOVE     	0 22
	470	[909]	MOVE     	0 21
	471	[909]	MOVE     	0 18
	472	[909]	MOVE     	0 15
	473	[909]	MOVE     	0 14
	474	[909]	MOVE     	0 13
	475	[909]	MOVE     	0 1
	476	[909]	MOVE     	0 20
	477	[824]	SETTABLE 	17 -227 25	; "buildMultiswipeMenu" -
	478	[925]	CLOSURE  	25 6	; 0x7fad9440dde0
	479	[911]	SETTABLE 	17 -228 25	; "createSubMenu" -
	480	[927]	NEWTABLE 	25 0 8
	481	[928]	SETTABLE 	25 -229 -230	; "east" "\226\158\161"
	482	[929]	SETTABLE 	25 -231 -232	; "west" "\226\172\133"
	483	[930]	SETTABLE 	25 -233 -234	; "north" "\226\172\134"
	484	[931]	SETTABLE 	25 -235 -236	; "south" "\226\172\135"
	485	[932]	SETTABLE 	25 -237 -238	; "northeast" "\226\172\136"
	486	[933]	SETTABLE 	25 -239 -240	; "northwest" "\226\172\137"
	487	[934]	SETTABLE 	25 -241 -242	; "southeast" "\226\172\138"
	488	[935]	SETTABLE 	25 -243 -244	; "southwest" "\226\172\139"
	489	[939]	CLOSURE  	26 7	; 0x7fad9440d2e0
	490	[939]	MOVE     	0 25
	491	[937]	SETTABLE 	17 -245 26	; "friendlyMultiswipeName" -
	492	[943]	CLOSURE  	26 8	; 0x7fad9440d360
	493	[941]	SETTABLE 	17 -246 26	; "safeMultiswipeName" -
	494	[1227]	CLOSURE  	26 9	; 0x7fad944144e0
	495	[945]	SETTABLE 	17 -247 26	; "setupGesture" -
	496	[1265]	CLOSURE  	26 10	; 0x7fad944152b0
	497	[1265]	MOVE     	0 12
	498	[1265]	MOVE     	0 13
	499	[1265]	MOVE     	0 1
	500	[1265]	MOVE     	0 15
	501	[1265]	MOVE     	0 24
	502	[1229]	SETTABLE 	17 -248 26	; "registerGesture" -
	503	[1269]	CLOSURE  	26 11	; 0x7fad94417a20
	504	[1269]	MOVE     	0 3
	505	[1585]	CLOSURE  	27 12	; 0x7fad94410b90
	506	[1585]	MOVE     	0 17
	507	[1585]	MOVE     	0 13
	508	[1585]	MOVE     	0 4
	509	[1585]	MOVE     	0 12
	510	[1585]	MOVE     	0 26
	511	[1585]	MOVE     	0 11
	512	[1585]	MOVE     	0 15
	513	[1585]	MOVE     	0 3
	514	[1585]	MOVE     	0 7
	515	[1585]	MOVE     	0 14
	516	[1585]	MOVE     	0 0
	517	[1585]	MOVE     	0 1
	518	[1271]	SETTABLE 	17 -249 27	; "gestureAction" -
	519	[1595]	CLOSURE  	27 13	; 0x7fad94419fe0
	520	[1587]	SETTABLE 	17 -250 27	; "multiswipeAction" -
	521	[1604]	CLOSURE  	27 14	; 0x7fad9441a390
	522	[1604]	MOVE     	0 4
	523	[1597]	SETTABLE 	17 -251 27	; "pageUpdate" -
	524	[1614]	CLOSURE  	27 15	; 0x7fad9441a980
	525	[1606]	SETTABLE 	17 -252 27	; "onIgnoreHoldCorners" -
	526	[1629]	CLOSURE  	27 16	; 0x7fad9441ae60
	527	[1629]	MOVE     	0 3
	528	[1629]	MOVE     	0 15
	529	[1629]	MOVE     	0 13
	530	[1629]	MOVE     	0 11
	531	[1616]	SETTABLE 	17 -253 27	; "onShowFLOnOff" -
	532	[1643]	CLOSURE  	27 17	; 0x7fad94414460
	533	[1643]	MOVE     	0 15
	534	[1643]	MOVE     	0 13
	535	[1643]	MOVE     	0 11
	536	[1631]	SETTABLE 	17 -254 27	; "onGSensorToggle" -
	537	[1658]	CLOSURE  	27 18	; 0x7fad9441b4a0
	538	[1658]	MOVE     	0 0
	539	[1658]	MOVE     	0 13
	540	[1658]	MOVE     	0 11
	541	[1658]	MOVE     	0 15
	542	[1645]	SETTABLE 	17 -255 27	; "onToggleReadingOrder" -
	543	[1660]	RETURN   	17 2
	544	[1660]	RETURN   	0 1

function <./frontend/apps/reader/modules/readergesture.lua:168,276> (421 instructions, 1684 bytes at 0x7fad94409900)
1 param, 14 slots, 3 upvalues, 17 locals, 122 constants, 0 functions
	1	[169]	GETUPVAL 	1 0	; Device
	2	[169]	SELF     	1 1 -1	; "isTouchDevice"
	3	[169]	CALL     	1 2 2
	4	[169]	TEST     	1 0 1
	5	[169]	JMP      	1	; to 7
	6	[169]	RETURN   	0 1
	7	[170]	GETGLOBAL	1 -3	; G_reader_settings
	8	[170]	SELF     	1 1 -4	; "readSetting"
	9	[170]	LOADK    	3 -2	; "ignore_hold_corners"
	10	[170]	CALL     	1 3 2
	11	[170]	SETTABLE 	0 -2 1	; "ignore_hold_corners" -
	12	[171]	GETGLOBAL	1 -3	; G_reader_settings
	13	[171]	SELF     	1 1 -4	; "readSetting"
	14	[171]	LOADK    	3 -5	; "multiswipes_enabled"
	15	[171]	CALL     	1 3 2
	16	[171]	SETTABLE 	0 -5 1	; "multiswipes_enabled" -
	17	[172]	GETTABLE 	1 0 -7	; "ui"
	18	[172]	EQ       	1 1 -8	; - nil
	19	[172]	JMP      	5	; to 25
	20	[172]	GETTABLE 	1 0 -7	; "ui"
	21	[172]	GETTABLE 	1 1 -9	; "document"
	22	[172]	EQ       	1 1 -8	; - nil
	23	[172]	JMP      	1	; to 25
	24	[172]	LOADBOOL 	1 0 1
	25	[172]	LOADBOOL 	1 1 0
	26	[172]	SETTABLE 	0 -6 1	; "is_docless" -
	27	[173]	GETTABLE 	1 0 -6	; "is_docless"
	28	[173]	TEST     	1 0 0
	29	[173]	JMP      	3	; to 33
	30	[173]	LOADK    	1 -11	; "gesture_fm"
	31	[173]	TEST     	1 0 1
	32	[173]	JMP      	1	; to 34
	33	[173]	LOADK    	1 -12	; "gesture_reader"
	34	[173]	SETTABLE 	0 -10 1	; "ges_mode" -
	35	[174]	NEWTABLE 	1 0 31
	36	[175]	GETTABLE 	2 0 -10	; "ges_mode"
	37	[175]	EQ       	0 2 -12	; - "gesture_reader"
	38	[175]	JMP      	3	; to 42
	39	[175]	LOADK    	2 -15	; "toggle_page_flipping"
	40	[175]	TEST     	2 0 1
	41	[175]	JMP      	1	; to 43
	42	[175]	LOADK    	2 -16	; "ignore"
	43	[175]	SETTABLE 	1 -14 2	; "tap_top_left_corner" -
	44	[176]	GETTABLE 	2 0 -10	; "ges_mode"
	45	[176]	EQ       	0 2 -12	; - "gesture_reader"
	46	[176]	JMP      	3	; to 50
	47	[176]	LOADK    	2 -18	; "toggle_bookmark"
	48	[176]	TEST     	2 0 1
	49	[176]	JMP      	1	; to 51
	50	[176]	LOADK    	2 -19	; "show_plus_menu"
	51	[176]	SETTABLE 	1 -17 2	; "tap_top_right_corner" -
	52	[177]	SETTABLE 	1 -20 -16	; "tap_right_bottom_corner" "ignore"
	53	[178]	GETUPVAL 	2 0	; Device
	54	[178]	SELF     	2 2 -22	; "hasFrontlight"
	55	[178]	CALL     	2 2 2
	56	[178]	TEST     	2 0 0
	57	[178]	JMP      	3	; to 61
	58	[178]	LOADK    	2 -23	; "toggle_frontlight"
	59	[178]	TEST     	2 0 1
	60	[178]	JMP      	1	; to 62
	61	[178]	LOADK    	2 -16	; "ignore"
	62	[178]	SETTABLE 	1 -21 2	; "tap_left_bottom_corner" -
	63	[179]	SETTABLE 	1 -24 -16	; "hold_top_left_corner" "ignore"
	64	[180]	SETTABLE 	1 -25 -16	; "hold_top_right_corner" "ignore"
	65	[181]	SETTABLE 	1 -26 -16	; "hold_bottom_left_corner" "ignore"
	66	[182]	SETTABLE 	1 -27 -16	; "hold_bottom_right_corner" "ignore"
	67	[183]	GETUPVAL 	2 0	; Device
	68	[183]	SELF     	2 2 -22	; "hasFrontlight"
	69	[183]	CALL     	2 2 2
	70	[183]	TEST     	2 0 0
	71	[183]	JMP      	3	; to 75
	72	[183]	LOADK    	2 -29	; "decrease_frontlight"
	73	[183]	TEST     	2 0 1
	74	[183]	JMP      	1	; to 76
	75	[183]	LOADK    	2 -16	; "ignore"
	76	[183]	SETTABLE 	1 -28 2	; "one_finger_swipe_left_edge_down" -
	77	[184]	GETUPVAL 	2 0	; Device
	78	[184]	SELF     	2 2 -22	; "hasFrontlight"
	79	[184]	CALL     	2 2 2
	80	[184]	TEST     	2 0 0
	81	[184]	JMP      	3	; to 85
	82	[184]	LOADK    	2 -31	; "increase_frontlight"
	83	[184]	TEST     	2 0 1
	84	[184]	JMP      	1	; to 86
	85	[184]	LOADK    	2 -16	; "ignore"
	86	[184]	SETTABLE 	1 -30 2	; "one_finger_swipe_left_edge_up" -
	87	[185]	GETUPVAL 	2 0	; Device
	88	[185]	SELF     	2 2 -33	; "hasNaturalLight"
	89	[185]	CALL     	2 2 2
	90	[185]	TEST     	2 0 0
	91	[185]	JMP      	3	; to 95
	92	[185]	LOADK    	2 -34	; "decrease_frontlight_warmth"
	93	[185]	TEST     	2 0 1
	94	[185]	JMP      	1	; to 96
	95	[185]	LOADK    	2 -16	; "ignore"
	96	[185]	SETTABLE 	1 -32 2	; "one_finger_swipe_right_edge_down" -
	97	[186]	GETUPVAL 	2 0	; Device
	98	[186]	SELF     	2 2 -33	; "hasNaturalLight"
	99	[186]	CALL     	2 2 2
	100	[186]	TEST     	2 0 0
	101	[186]	JMP      	3	; to 105
	102	[186]	LOADK    	2 -36	; "increase_frontlight_warmth"
	103	[186]	TEST     	2 0 1
	104	[186]	JMP      	1	; to 106
	105	[186]	LOADK    	2 -16	; "ignore"
	106	[186]	SETTABLE 	1 -35 2	; "one_finger_swipe_right_edge_up" -
	107	[187]	SETTABLE 	1 -37 -16	; "one_finger_swipe_top_edge_right" "ignore"
	108	[188]	SETTABLE 	1 -38 -16	; "one_finger_swipe_top_edge_left" "ignore"
	109	[189]	SETTABLE 	1 -39 -16	; "one_finger_swipe_bottom_edge_right" "ignore"
	110	[190]	SETTABLE 	1 -40 -16	; "one_finger_swipe_bottom_edge_left" "ignore"
	111	[191]	SETTABLE 	1 -41 -16	; "two_finger_tap_top_left_corner" "ignore"
	112	[192]	SETTABLE 	1 -42 -16	; "two_finger_tap_top_right_corner" "ignore"
	113	[193]	SETTABLE 	1 -43 -16	; "two_finger_tap_bottom_left_corner" "ignore"
	114	[194]	SETTABLE 	1 -44 -16	; "two_finger_tap_bottom_right_corner" "ignore"
	115	[195]	SETTABLE 	1 -45 -46	; "short_diagonal_swipe" "full_refresh"
	116	[196]	SETTABLE 	1 -47 -48	; "multiswipe" "nothing"
	117	[197]	GETTABLE 	2 0 -10	; "ges_mode"
	118	[197]	EQ       	0 2 -12	; - "gesture_reader"
	119	[197]	JMP      	3	; to 123
	120	[197]	LOADK    	2 -50	; "previous_location"
	121	[197]	TEST     	2 0 1
	122	[197]	JMP      	1	; to 124
	123	[197]	LOADK    	2 -48	; "nothing"
	124	[197]	SETTABLE 	1 -49 2	; "multiswipe_west_east" -
	125	[198]	GETTABLE 	2 0 -10	; "ges_mode"
	126	[198]	EQ       	0 2 -12	; - "gesture_reader"
	127	[198]	JMP      	3	; to 131
	128	[198]	LOADK    	2 -52	; "latest_bookmark"
	129	[198]	TEST     	2 0 1
	130	[198]	JMP      	1	; to 132
	131	[198]	LOADK    	2 -48	; "nothing"
	132	[198]	SETTABLE 	1 -51 2	; "multiswipe_east_west" -
	133	[199]	GETTABLE 	2 0 -10	; "ges_mode"
	134	[199]	EQ       	0 2 -12	; - "gesture_reader"
	135	[199]	JMP      	3	; to 139
	136	[199]	LOADK    	2 -54	; "toc"
	137	[199]	TEST     	2 0 1
	138	[199]	JMP      	1	; to 140
	139	[199]	LOADK    	2 -48	; "nothing"
	140	[199]	SETTABLE 	1 -53 2	; "multiswipe_north_east" -
	141	[200]	GETTABLE 	2 0 -10	; "ges_mode"
	142	[200]	EQ       	0 2 -12	; - "gesture_reader"
	143	[200]	JMP      	3	; to 147
	144	[200]	LOADK    	2 -56	; "bookmarks"
	145	[200]	TEST     	2 0 1
	146	[200]	JMP      	1	; to 148
	147	[200]	LOADK    	2 -57	; "folder_shortcuts"
	148	[200]	SETTABLE 	1 -55 2	; "multiswipe_north_west" -
	149	[201]	GETTABLE 	2 0 -10	; "ges_mode"
	150	[201]	EQ       	0 2 -12	; - "gesture_reader"
	151	[201]	JMP      	3	; to 155
	152	[201]	LOADK    	2 -48	; "nothing"
	153	[201]	TEST     	2 0 1
	154	[201]	JMP      	1	; to 156
	155	[201]	LOADK    	2 -59	; "folder_up"
	156	[201]	SETTABLE 	1 -58 2	; "multiswipe_north_south" -
	157	[202]	SETTABLE 	1 -60 -61	; "multiswipe_east_north" "history"
	158	[203]	GETTABLE 	2 0 -10	; "ges_mode"
	159	[203]	EQ       	0 2 -12	; - "gesture_reader"
	160	[203]	JMP      	3	; to 164
	161	[203]	LOADK    	2 -63	; "book_status"
	162	[203]	TEST     	2 0 1
	163	[203]	JMP      	1	; to 165
	164	[203]	LOADK    	2 -48	; "nothing"
	165	[203]	SETTABLE 	1 -62 2	; "multiswipe_west_north" -
	166	[204]	SETTABLE 	1 -64 -65	; "multiswipe_east_south" "go_to"
	167	[205]	GETTABLE 	2 0 -10	; "ges_mode"
	168	[205]	EQ       	0 2 -12	; - "gesture_reader"
	169	[205]	JMP      	3	; to 173
	170	[205]	LOADK    	2 -67	; "skim"
	171	[205]	TEST     	2 0 1
	172	[205]	JMP      	1	; to 174
	173	[205]	LOADK    	2 -48	; "nothing"
	174	[205]	SETTABLE 	1 -66 2	; "multiswipe_south_north" -
	175	[206]	GETTABLE 	2 0 -10	; "ges_mode"
	176	[206]	EQ       	0 2 -12	; - "gesture_reader"
	177	[206]	JMP      	3	; to 181
	178	[206]	LOADK    	2 -69	; "toggle_reflow"
	179	[206]	TEST     	2 0 1
	180	[206]	JMP      	1	; to 182
	181	[206]	LOADK    	2 -48	; "nothing"
	182	[206]	SETTABLE 	1 -68 2	; "multiswipe_south_east" -
	183	[207]	SETTABLE 	1 -70 -71	; "multiswipe_south_west" "show_frontlight_dialog"
	184	[208]	SETTABLE 	1 -72 -73	; "multiswipe_west_south" "back"
	185	[209]	GETTABLE 	2 0 -10	; "ges_mode"
	186	[209]	EQ       	0 2 -12	; - "gesture_reader"
	187	[209]	JMP      	3	; to 191
	188	[209]	LOADK    	2 -75	; "prev_chapter"
	189	[209]	TEST     	2 0 1
	190	[209]	JMP      	1	; to 192
	191	[209]	LOADK    	2 -48	; "nothing"
	192	[209]	SETTABLE 	1 -74 2	; "multiswipe_north_south_north" -
	193	[210]	GETTABLE 	2 0 -10	; "ges_mode"
	194	[210]	EQ       	0 2 -12	; - "gesture_reader"
	195	[210]	JMP      	3	; to 199
	196	[210]	LOADK    	2 -77	; "next_chapter"
	197	[210]	TEST     	2 0 1
	198	[210]	JMP      	1	; to 200
	199	[210]	LOADK    	2 -48	; "nothing"
	200	[210]	SETTABLE 	1 -76 2	; "multiswipe_south_north_south" -
	201	[211]	SETTABLE 	1 -78 -79	; "multiswipe_west_east_west" "open_previous_document"
	202	[212]	SETTABLE 	1 -80 -81	; "multiswipe_east_west_east" "favorites"
	203	[213]	GETTABLE 	2 0 -10	; "ges_mode"
	204	[213]	EQ       	0 2 -12	; - "gesture_reader"
	205	[213]	JMP      	3	; to 209
	206	[213]	LOADK    	2 -83	; "zoom_contentwidth"
	207	[213]	TEST     	2 0 1
	208	[213]	JMP      	1	; to 210
	209	[213]	LOADK    	2 -48	; "nothing"
	210	[213]	SETTABLE 	1 -82 2	; "multiswipe_east_north_west" -
	211	[214]	GETTABLE 	2 0 -10	; "ges_mode"
	212	[214]	EQ       	0 2 -12	; - "gesture_reader"
	213	[214]	JMP      	3	; to 217
	214	[214]	LOADK    	2 -85	; "zoom_contentheight"
	215	[214]	TEST     	2 0 1
	216	[214]	JMP      	1	; to 218
	217	[214]	LOADK    	2 -48	; "nothing"
	218	[214]	SETTABLE 	1 -84 2	; "multiswipe_south_east_north" -
	219	[215]	GETTABLE 	2 0 -10	; "ges_mode"
	220	[215]	EQ       	0 2 -12	; - "gesture_reader"
	221	[215]	JMP      	3	; to 225
	222	[215]	LOADK    	2 -87	; "zoom_pagewidth"
	223	[215]	TEST     	2 0 1
	224	[215]	JMP      	1	; to 226
	225	[215]	LOADK    	2 -48	; "nothing"
	226	[215]	SETTABLE 	1 -86 2	; "multiswipe_east_north_west_east" -
	227	[216]	GETTABLE 	2 0 -10	; "ges_mode"
	228	[216]	EQ       	0 2 -12	; - "gesture_reader"
	229	[216]	JMP      	3	; to 233
	230	[216]	LOADK    	2 -89	; "zoom_pageheight"
	231	[216]	TEST     	2 0 1
	232	[216]	JMP      	1	; to 234
	233	[216]	LOADK    	2 -48	; "nothing"
	234	[216]	SETTABLE 	1 -88 2	; "multiswipe_south_east_north_south" -
	235	[217]	SETTABLE 	1 -90 -46	; "multiswipe_east_south_west_north" "full_refresh"
	236	[218]	GETTABLE 	2 0 -10	; "ges_mode"
	237	[218]	EQ       	0 2 -12	; - "gesture_reader"
	238	[218]	JMP      	3	; to 242
	239	[218]	LOADK    	2 -92	; "follow_nearest_link"
	240	[218]	TEST     	2 0 1
	241	[218]	JMP      	1	; to 243
	242	[218]	LOADK    	2 -48	; "nothing"
	243	[218]	SETTABLE 	1 -91 2	; "multiswipe_southeast_northeast" -
	244	[219]	GETUPVAL 	2 0	; Device
	245	[219]	SELF     	2 2 -94	; "hasWifiToggle"
	246	[219]	CALL     	2 2 2
	247	[219]	TEST     	2 0 0
	248	[219]	JMP      	3	; to 252
	249	[219]	LOADK    	2 -95	; "toggle_wifi"
	250	[219]	TEST     	2 0 1
	251	[219]	JMP      	1	; to 253
	252	[219]	LOADK    	2 -48	; "nothing"
	253	[219]	SETTABLE 	1 -93 2	; "multiswipe_northwest_southwest_northwest" -
	254	[220]	GETUPVAL 	2 0	; Device
	255	[220]	SELF     	2 2 -94	; "hasWifiToggle"
	256	[220]	CALL     	2 2 2
	257	[220]	TEST     	2 0 0
	258	[220]	JMP      	3	; to 262
	259	[220]	LOADK    	2 -97	; "wifi_off"
	260	[220]	TEST     	2 0 1
	261	[220]	JMP      	1	; to 263
	262	[220]	LOADK    	2 -48	; "nothing"
	263	[220]	SETTABLE 	1 -96 2	; "multiswipe_southeast_southwest_northwest" -
	264	[221]	GETUPVAL 	2 0	; Device
	265	[221]	SELF     	2 2 -94	; "hasWifiToggle"
	266	[221]	CALL     	2 2 2
	267	[221]	TEST     	2 0 0
	268	[221]	JMP      	3	; to 272
	269	[221]	LOADK    	2 -99	; "wifi_on"
	270	[221]	TEST     	2 0 1
	271	[221]	JMP      	1	; to 273
	272	[221]	LOADK    	2 -48	; "nothing"
	273	[221]	SETTABLE 	1 -98 2	; "multiswipe_southeast_northeast_northwest" -
	274	[223]	GETTABLE 	2 0 -10	; "ges_mode"
	275	[223]	EQ       	0 2 -12	; - "gesture_reader"
	276	[223]	JMP      	3	; to 280
	277	[223]	LOADK    	2 -54	; "toc"
	278	[223]	TEST     	2 0 1
	279	[223]	JMP      	1	; to 281
	280	[223]	LOADK    	2 -16	; "ignore"
	281	[223]	SETTABLE 	1 -100 2	; "two_finger_swipe_east" -
	282	[224]	GETTABLE 	2 0 -10	; "ges_mode"
	283	[224]	EQ       	0 2 -12	; - "gesture_reader"
	284	[224]	JMP      	3	; to 288
	285	[224]	LOADK    	2 -56	; "bookmarks"
	286	[224]	TEST     	2 0 1
	287	[224]	JMP      	1	; to 289
	288	[224]	LOADK    	2 -57	; "folder_shortcuts"
	289	[224]	SETTABLE 	1 -101 2	; "two_finger_swipe_west" -
	290	[225]	GETUPVAL 	2 0	; Device
	291	[225]	SELF     	2 2 -22	; "hasFrontlight"
	292	[225]	CALL     	2 2 2
	293	[225]	TEST     	2 0 0
	294	[225]	JMP      	3	; to 298
	295	[225]	LOADK    	2 -29	; "decrease_frontlight"
	296	[225]	TEST     	2 0 1
	297	[225]	JMP      	1	; to 299
	298	[225]	LOADK    	2 -16	; "ignore"
	299	[225]	SETTABLE 	1 -102 2	; "two_finger_swipe_south" -
	300	[226]	GETUPVAL 	2 0	; Device
	301	[226]	SELF     	2 2 -22	; "hasFrontlight"
	302	[226]	CALL     	2 2 2
	303	[226]	TEST     	2 0 0
	304	[226]	JMP      	3	; to 308
	305	[226]	LOADK    	2 -31	; "increase_frontlight"
	306	[226]	TEST     	2 0 1
	307	[226]	JMP      	1	; to 309
	308	[226]	LOADK    	2 -16	; "ignore"
	309	[226]	SETTABLE 	1 -103 2	; "two_finger_swipe_north" -
	310	[227]	SETTABLE 	1 -104 -16	; "two_finger_swipe_northeast" "ignore"
	311	[228]	SETTABLE 	1 -105 -16	; "two_finger_swipe_northwest" "ignore"
	312	[229]	SETTABLE 	1 -106 -16	; "two_finger_swipe_southeast" "ignore"
	313	[230]	SETTABLE 	1 -107 -16	; "two_finger_swipe_southwest" "ignore"
	314	[231]	GETTABLE 	2 0 -10	; "ges_mode"
	315	[231]	EQ       	0 2 -12	; - "gesture_reader"
	316	[231]	JMP      	3	; to 320
	317	[231]	LOADK    	2 -109	; "increase_font"
	318	[231]	TEST     	2 0 1
	319	[231]	JMP      	1	; to 321
	320	[231]	LOADK    	2 -16	; "ignore"
	321	[231]	SETTABLE 	1 -108 2	; "spread_gesture" -
	322	[232]	GETTABLE 	2 0 -10	; "ges_mode"
	323	[232]	EQ       	0 2 -12	; - "gesture_reader"
	324	[232]	JMP      	3	; to 328
	325	[232]	LOADK    	2 -111	; "decrease_font"
	326	[232]	TEST     	2 0 1
	327	[232]	JMP      	1	; to 329
	328	[232]	LOADK    	2 -16	; "ignore"
	329	[232]	SETTABLE 	1 -110 2	; "pinch_gesture" -
	330	[233]	SETTABLE 	0 -13 1	; "default_gesture" -
	331	[234]	GETGLOBAL	1 -3	; G_reader_settings
	332	[234]	SELF     	1 1 -4	; "readSetting"
	333	[234]	GETTABLE 	3 0 -10	; "ges_mode"
	334	[234]	CALL     	1 3 2
	335	[235]	EQ       	0 1 -8	; - nil
	336	[235]	JMP      	5	; to 342
	337	[235]	GETGLOBAL	2 -3	; G_reader_settings
	338	[235]	SELF     	2 2 -112	; "saveSetting"
	339	[235]	GETTABLE 	4 0 -10	; "ges_mode"
	340	[235]	NEWTABLE 	5 0 0
	341	[235]	CALL     	2 4 1
	342	[240]	NEWTABLE 	2 0 2
	343	[241]	SETTABLE 	2 -14 -17	; "tap_top_left_corner" "tap_top_right_corner"
	344	[242]	SETTABLE 	2 -20 -21	; "tap_right_bottom_corner" "tap_left_bottom_corner"
	345	[244]	GETUPVAL 	3 1	; BD
	346	[244]	GETTABLE 	3 3 -113	; "mirroredUILayout"
	347	[244]	CALL     	3 1 2
	348	[245]	TEST     	3 0 0
	349	[245]	JMP      	14	; to 364
	350	[246]	GETGLOBAL	4 -114	; pairs
	351	[246]	MOVE     	5 2
	352	[246]	CALL     	4 2 4
	353	[246]	JMP      	8	; to 362
	354	[247]	GETTABLE 	9 0 -13	; "default_gesture"
	355	[247]	GETTABLE 	10 0 -13	; "default_gesture"
	356	[247]	GETTABLE 	11 0 -13	; "default_gesture"
	357	[247]	GETTABLE 	11 11 8
	358	[247]	GETTABLE 	12 0 -13	; "default_gesture"
	359	[247]	GETTABLE 	12 12 7
	360	[247]	SETTABLE 	10 8 12
	361	[247]	SETTABLE 	9 7 11
	362	[246]	TFORLOOP 	4 2
	363	[247]	JMP      	-10	; to 354
	364	[252]	GETTABLE 	4 0 -10	; "ges_mode"
	365	[252]	LOADK    	5 -115	; "ui_lang_direction_rtl"
	366	[252]	CONCAT   	4 4 5
	367	[253]	GETGLOBAL	5 -3	; G_reader_settings
	368	[253]	SELF     	5 5 -116	; "isTrue"
	369	[253]	MOVE     	7 4
	370	[253]	CALL     	5 3 2
	371	[254]	TEST     	3 0 0
	372	[254]	JMP      	2	; to 375
	373	[254]	TEST     	5 0 0
	374	[254]	JMP      	4	; to 379
	375	[254]	TEST     	3 0 1
	376	[254]	JMP      	37	; to 414
	377	[254]	TEST     	5 0 0
	378	[254]	JMP      	35	; to 414
	379	[255]	LOADBOOL 	6 0 0
	380	[256]	GETGLOBAL	7 -114	; pairs
	381	[256]	MOVE     	8 2
	382	[256]	CALL     	7 2 4
	383	[256]	JMP      	18	; to 402
	384	[259]	GETTABLE 	12 1 10
	385	[259]	GETTABLE 	13 0 -13	; "default_gesture"
	386	[259]	GETTABLE 	13 13 11
	387	[259]	EQ       	0 12 13
	388	[259]	JMP      	4	; to 393
	389	[260]	GETTABLE 	12 0 -13	; "default_gesture"
	390	[260]	GETTABLE 	12 12 10
	391	[260]	SETTABLE 	1 10 12
	392	[261]	LOADBOOL 	6 1 0
	393	[263]	GETTABLE 	12 1 11
	394	[263]	GETTABLE 	13 0 -13	; "default_gesture"
	395	[263]	GETTABLE 	13 13 10
	396	[263]	EQ       	0 12 13
	397	[263]	JMP      	4	; to 402
	398	[264]	GETTABLE 	12 0 -13	; "default_gesture"
	399	[264]	GETTABLE 	12 12 11
	400	[264]	SETTABLE 	1 11 12
	401	[265]	LOADBOOL 	6 1 0
	402	[256]	TFORLOOP 	7 2
	403	[266]	JMP      	-20	; to 384
	404	[268]	TEST     	6 0 0
	405	[268]	JMP      	4	; to 410
	406	[269]	GETUPVAL 	7 2	; logger
	407	[269]	GETTABLE 	7 7 -117	; "info"
	408	[269]	LOADK    	8 -118	; "UI language direction changed: resetting some gestures to direction default"
	409	[269]	CALL     	7 2 1
	410	[271]	GETGLOBAL	7 -3	; G_reader_settings
	411	[271]	SELF     	7 7 -119	; "flipNilOrFalse"
	412	[271]	MOVE     	9 4
	413	[271]	CALL     	7 3 1
	414	[274]	GETTABLE 	6 0 -7	; "ui"
	415	[274]	GETTABLE 	6 6 -120	; "menu"
	416	[274]	SELF     	6 6 -121	; "registerToMainMenu"
	417	[274]	MOVE     	8 0
	418	[274]	CALL     	6 3 1
	419	[275]	SELF     	6 0 -122	; "initGesture"
	420	[275]	CALL     	6 2 1
	421	[276]	RETURN   	0 1

function <./frontend/apps/reader/modules/readergesture.lua:278,289> (30 instructions, 120 bytes at 0x7fad94409ec0)
1 param, 11 slots, 0 upvalues, 12 locals, 7 constants, 0 functions
	1	[279]	GETGLOBAL	1 -1	; G_reader_settings
	2	[279]	SELF     	1 1 -2	; "readSetting"
	3	[279]	GETTABLE 	3 0 -3	; "ges_mode"
	4	[279]	CALL     	1 3 2
	5	[280]	GETGLOBAL	2 -4	; pairs
	6	[280]	GETTABLE 	3 0 -5	; "default_gesture"
	7	[280]	CALL     	2 2 4
	8	[280]	JMP      	4	; to 13
	9	[281]	GETTABLE 	7 1 5
	10	[281]	TEST     	7 0 1
	11	[281]	JMP      	1	; to 13
	12	[282]	SETTABLE 	1 5 6
	13	[280]	TFORLOOP 	2 2
	14	[283]	JMP      	-6	; to 9
	15	[285]	GETGLOBAL	2 -4	; pairs
	16	[285]	MOVE     	3 1
	17	[285]	CALL     	2 2 4
	18	[285]	JMP      	4	; to 23
	19	[286]	SELF     	7 0 -6	; "setupGesture"
	20	[286]	MOVE     	9 5
	21	[286]	MOVE     	10 6
	22	[286]	CALL     	7 4 1
	23	[285]	TFORLOOP 	2 2
	24	[286]	JMP      	-6	; to 19
	25	[288]	GETGLOBAL	2 -1	; G_reader_settings
	26	[288]	SELF     	2 2 -7	; "saveSetting"
	27	[288]	GETTABLE 	4 0 -3	; "ges_mode"
	28	[288]	MOVE     	5 1
	29	[288]	CALL     	2 4 1
	30	[289]	RETURN   	0 1

function <./frontend/apps/reader/modules/readergesture.lua:291,298> (14 instructions, 56 bytes at 0x7fad9440b390)
1 param, 4 slots, 1 upvalue, 1 local, 7 constants, 1 function
	1	[292]	NEWTABLE 	1 0 4
	2	[293]	GETUPVAL 	2 0	; _
	3	[293]	LOADK    	3 -2	; "Multiswipe"
	4	[293]	CALL     	2 2 2
	5	[293]	SETTABLE 	1 -1 2	; "text" -
	6	[294]	SELF     	2 0 -4	; "buildMultiswipeMenu"
	7	[294]	CALL     	2 2 2
	8	[294]	SETTABLE 	1 -3 2	; "sub_item_table" -
	9	[295]	CLOSURE  	2 0	; 0x7fad9440b5a0
	10	[295]	MOVE     	0 0
	11	[295]	SETTABLE 	1 -5 2	; "enabled_func" -
	12	[296]	SETTABLE 	1 -6 -7	; "separator" true
	13	[297]	RETURN   	1 2
	14	[298]	RETURN   	0 1

function <./frontend/apps/reader/modules/readergesture.lua:295,295> (4 instructions, 16 bytes at 0x7fad9440b5a0)
0 params, 2 slots, 1 upvalue, 0 locals, 1 constant, 0 functions
	1	[295]	GETUPVAL 	0 0	; self
	2	[295]	GETTABLE 	0 0 -1	; "multiswipes_enabled"
	3	[295]	RETURN   	0 2
	4	[295]	RETURN   	0 1

function <./frontend/apps/reader/modules/readergesture.lua:300,699> (541 instructions, 2164 bytes at 0x7fad9440bad0)
2 params, 28 slots, 15 upvalues, 8 locals, 69 constants, 43 functions
	1	[301]	GETGLOBAL	2 -1	; G_reader_settings
	2	[301]	SELF     	2 2 -2	; "readSetting"
	3	[301]	GETTABLE 	4 0 -3	; "ges_mode"
	4	[301]	CALL     	2 3 2
	5	[306]	CLOSURE  	3 0	; 0x7fad9440bce0
	6	[306]	MOVE     	0 2
	7	[306]	GETUPVAL 	0 0	; action_strings
	8	[306]	GETUPVAL 	0 1	; _
	9	[306]	GETUPVAL 	0 2	; T
	10	[307]	NEWTABLE 	4 0 2
	11	[308]	GETUPVAL 	5 1	; _
	12	[308]	LOADK    	6 -5	; "Tap corner"
	13	[308]	CALL     	5 2 2
	14	[308]	SETTABLE 	4 -4 5	; "text" -
	15	[309]	NEWTABLE 	5 4 0
	16	[309]	NEWTABLE 	6 0 3
	17	[311]	CLOSURE  	7 1	; 0x7fad9440c6a0
	18	[311]	MOVE     	0 3
	19	[311]	GETUPVAL 	0 1	; _
	20	[311]	SETTABLE 	6 -7 7	; "text_func" -
	21	[312]	CLOSURE  	7 2	; 0x7fad9440ca10
	22	[312]	MOVE     	0 0
	23	[312]	SETTABLE 	6 -8 7	; "enabled_func" -
	24	[313]	SELF     	7 0 -9	; "buildMenu"
	25	[313]	LOADK    	9 -10	; "tap_top_left_corner"
	26	[313]	GETTABLE 	10 0 -11	; "default_gesture"
	27	[313]	GETTABLE 	10 10 -10	; "tap_top_left_corner"
	28	[313]	CALL     	7 4 2
	29	[313]	SETTABLE 	6 -6 7	; "sub_item_table" -
	30	[314]	NEWTABLE 	7 0 2
	31	[316]	CLOSURE  	8 3	; 0x7fad9440c620
	32	[316]	MOVE     	0 3
	33	[316]	GETUPVAL 	0 1	; _
	34	[316]	SETTABLE 	7 -7 8	; "text_func" -
	35	[317]	SELF     	8 0 -9	; "buildMenu"
	36	[317]	LOADK    	10 -12	; "tap_top_right_corner"
	37	[317]	GETTABLE 	11 0 -11	; "default_gesture"
	38	[317]	GETTABLE 	11 11 -12	; "tap_top_right_corner"
	39	[317]	CALL     	8 4 2
	40	[317]	SETTABLE 	7 -6 8	; "sub_item_table" -
	41	[318]	NEWTABLE 	8 0 2
	42	[320]	CLOSURE  	9 4	; 0x7fad9440c990
	43	[320]	MOVE     	0 3
	44	[320]	GETUPVAL 	0 1	; _
	45	[320]	SETTABLE 	8 -7 9	; "text_func" -
	46	[321]	SELF     	9 0 -9	; "buildMenu"
	47	[321]	LOADK    	11 -13	; "tap_left_bottom_corner"
	48	[321]	GETTABLE 	12 0 -11	; "default_gesture"
	49	[321]	GETTABLE 	12 12 -13	; "tap_left_bottom_corner"
	50	[321]	CALL     	9 4 2
	51	[321]	SETTABLE 	8 -6 9	; "sub_item_table" -
	52	[322]	NEWTABLE 	9 0 3
	53	[324]	CLOSURE  	10 5	; 0x7fad9440d140
	54	[324]	MOVE     	0 3
	55	[324]	GETUPVAL 	0 1	; _
	56	[324]	SETTABLE 	9 -7 10	; "text_func" -
	57	[325]	SELF     	10 0 -9	; "buildMenu"
	58	[325]	LOADK    	12 -14	; "tap_right_bottom_corner"
	59	[325]	GETTABLE 	13 0 -11	; "default_gesture"
	60	[325]	GETTABLE 	13 13 -14	; "tap_right_bottom_corner"
	61	[325]	CALL     	10 4 2
	62	[325]	SETTABLE 	9 -6 10	; "sub_item_table" -
	63	[326]	SETTABLE 	9 -15 -16	; "separator" true
	64	[328]	SETLIST  	5 4 1	; 1
	65	[328]	SETTABLE 	4 -6 5	; "sub_item_table" -
	66	[330]	NEWTABLE 	5 0 2
	67	[331]	GETUPVAL 	6 1	; _
	68	[331]	LOADK    	7 -17	; "Hold corner"
	69	[331]	CALL     	6 2 2
	70	[331]	SETTABLE 	5 -4 6	; "text" -
	71	[332]	NEWTABLE 	6 4 0
	72	[332]	NEWTABLE 	7 0 3
	73	[334]	CLOSURE  	8 6	; 0x7fad9440be10
	74	[334]	MOVE     	0 3
	75	[334]	GETUPVAL 	0 1	; _
	76	[334]	SETTABLE 	7 -7 8	; "text_func" -
	77	[335]	CLOSURE  	8 7	; 0x7fad9440d830
	78	[335]	MOVE     	0 0
	79	[335]	SETTABLE 	7 -8 8	; "enabled_func" -
	80	[336]	SELF     	8 0 -9	; "buildMenu"
	81	[336]	LOADK    	10 -18	; "hold_top_left_corner"
	82	[336]	GETTABLE 	11 0 -11	; "default_gesture"
	83	[336]	GETTABLE 	11 11 -18	; "hold_top_left_corner"
	84	[336]	CALL     	8 4 2
	85	[336]	SETTABLE 	7 -6 8	; "sub_item_table" -
	86	[337]	NEWTABLE 	8 0 2
	87	[339]	CLOSURE  	9 8	; 0x7fad9440da50
	88	[339]	MOVE     	0 3
	89	[339]	GETUPVAL 	0 1	; _
	90	[339]	SETTABLE 	8 -7 9	; "text_func" -
	91	[340]	SELF     	9 0 -9	; "buildMenu"
	92	[340]	LOADK    	11 -19	; "hold_top_right_corner"
	93	[340]	GETTABLE 	12 0 -11	; "default_gesture"
	94	[340]	GETTABLE 	12 12 -19	; "hold_top_right_corner"
	95	[340]	CALL     	9 4 2
	96	[340]	SETTABLE 	8 -6 9	; "sub_item_table" -
	97	[341]	NEWTABLE 	9 0 2
	98	[343]	CLOSURE  	10 9	; 0x7fad9440df20
	99	[343]	MOVE     	0 3
	100	[343]	GETUPVAL 	0 1	; _
	101	[343]	SETTABLE 	9 -7 10	; "text_func" -
	102	[344]	SELF     	10 0 -9	; "buildMenu"
	103	[344]	LOADK    	12 -20	; "hold_bottom_left_corner"
	104	[344]	GETTABLE 	13 0 -11	; "default_gesture"
	105	[344]	GETTABLE 	13 13 -20	; "hold_bottom_left_corner"
	106	[344]	CALL     	10 4 2
	107	[344]	SETTABLE 	9 -6 10	; "sub_item_table" -
	108	[345]	NEWTABLE 	10 0 2
	109	[347]	CLOSURE  	11 10	; 0x7fad9440dfa0
	110	[347]	MOVE     	0 3
	111	[347]	GETUPVAL 	0 1	; _
	112	[347]	SETTABLE 	10 -7 11	; "text_func" -
	113	[348]	SELF     	11 0 -9	; "buildMenu"
	114	[348]	LOADK    	13 -21	; "hold_bottom_right_corner"
	115	[348]	GETTABLE 	14 0 -11	; "default_gesture"
	116	[348]	GETTABLE 	14 14 -21	; "hold_bottom_right_corner"
	117	[348]	CALL     	11 4 2
	118	[348]	SETTABLE 	10 -6 11	; "sub_item_table" -
	119	[350]	SETLIST  	6 4 1	; 1
	120	[350]	SETTABLE 	5 -6 6	; "sub_item_table" -
	121	[352]	NEWTABLE 	6 0 2
	122	[353]	GETUPVAL 	7 1	; _
	123	[353]	LOADK    	8 -23	; "Gesture manager"
	124	[353]	CALL     	7 2 2
	125	[353]	SETTABLE 	6 -4 7	; "text" -
	126	[354]	NEWTABLE 	7 7 0
	127	[354]	NEWTABLE 	8 0 4
	128	[356]	GETUPVAL 	9 1	; _
	129	[356]	LOADK    	10 -24	; "Turn on multiswipes"
	130	[356]	CALL     	9 2 2
	131	[356]	SETTABLE 	8 -4 9	; "text" -
	132	[357]	CLOSURE  	9 11	; 0x7fad9440d430
	133	[357]	MOVE     	0 0
	134	[357]	SETTABLE 	8 -25 9	; "checked_func" -
	135	[361]	CLOSURE  	9 12	; 0x7fad9440d5e0
	136	[361]	MOVE     	0 0
	137	[361]	SETTABLE 	8 -26 9	; "callback" -
	138	[362]	GETUPVAL 	9 3	; multiswipes_info_text
	139	[362]	SETTABLE 	8 -27 9	; "help_text" -
	140	[363]	NEWTABLE 	9 0 5
	141	[365]	GETUPVAL 	10 1	; _
	142	[365]	LOADK    	11 -28	; "Multiswipe recorder"
	143	[365]	CALL     	10 2 2
	144	[365]	SETTABLE 	9 -4 10	; "text" -
	145	[366]	CLOSURE  	10 13	; 0x7fad9440e5c0
	146	[366]	MOVE     	0 0
	147	[366]	SETTABLE 	9 -8 10	; "enabled_func" -
	148	[367]	SETTABLE 	9 -29 -16	; "keep_menu_open" true
	149	[429]	CLOSURE  	10 14	; 0x7fad9440e760
	150	[429]	GETUPVAL 	0 4	; InputDialog
	151	[429]	GETUPVAL 	0 1	; _
	152	[429]	GETUPVAL 	0 5	; UIManager
	153	[429]	GETUPVAL 	0 6	; logger
	154	[429]	GETUPVAL 	0 7	; multiswipes
	155	[429]	GETUPVAL 	0 8	; InfoMessage
	156	[429]	GETUPVAL 	0 9	; custom_multiswipes
	157	[429]	MOVE     	0 0
	158	[429]	GETUPVAL 	0 10	; GestureRange
	159	[429]	GETUPVAL 	0 11	; Geom
	160	[429]	GETUPVAL 	0 12	; Screen
	161	[429]	GETUPVAL 	0 13	; ReaderGesture
	162	[429]	SETTABLE 	9 -26 10	; "callback" -
	163	[430]	GETUPVAL 	10 1	; _
	164	[430]	LOADK    	11 -30	; "The number of possible multiswipe gestures is theoretically infinite. With the multiswipe recorder you can easily record your own."
	165	[430]	CALL     	10 2 2
	166	[430]	SETTABLE 	9 -27 10	; "help_text" -
	167	[433]	SELF     	10 0 -31	; "genMultiswipeSubmenu"
	168	[433]	CALL     	10 2 2
	169	[434]	MOVE     	11 4
	170	[435]	MOVE     	12 5
	171	[435]	NEWTABLE 	13 0 2
	172	[437]	GETUPVAL 	14 1	; _
	173	[437]	LOADK    	15 -32	; "Short diagonal swipe"
	174	[437]	CALL     	14 2 2
	175	[437]	SETTABLE 	13 -4 14	; "text" -
	176	[438]	SELF     	14 0 -9	; "buildMenu"
	177	[438]	LOADK    	16 -33	; "short_diagonal_swipe"
	178	[438]	GETTABLE 	17 0 -11	; "default_gesture"
	179	[438]	GETTABLE 	17 17 -33	; "short_diagonal_swipe"
	180	[438]	CALL     	14 4 2
	181	[438]	SETTABLE 	13 -6 14	; "sub_item_table" -
	182	[439]	NEWTABLE 	14 0 2
	183	[441]	GETUPVAL 	15 1	; _
	184	[441]	LOADK    	16 -34	; "One-finger swipe"
	185	[441]	CALL     	15 2 2
	186	[441]	SETTABLE 	14 -4 15	; "text" -
	187	[442]	NEWTABLE 	15 8 0
	188	[442]	NEWTABLE 	16 0 2
	189	[444]	CLOSURE  	17 15	; 0x7fad9440c490
	190	[444]	MOVE     	0 3
	191	[444]	GETUPVAL 	0 1	; _
	192	[444]	SETTABLE 	16 -7 17	; "text_func" -
	193	[445]	SELF     	17 0 -9	; "buildMenu"
	194	[445]	LOADK    	19 -35	; "one_finger_swipe_left_edge_down"
	195	[445]	GETTABLE 	20 0 -11	; "default_gesture"
	196	[445]	GETTABLE 	20 20 -35	; "one_finger_swipe_left_edge_down"
	197	[445]	CALL     	17 4 2
	198	[445]	SETTABLE 	16 -6 17	; "sub_item_table" -
	199	[446]	NEWTABLE 	17 0 2
	200	[448]	CLOSURE  	18 16	; 0x7fad9440d530
	201	[448]	MOVE     	0 3
	202	[448]	GETUPVAL 	0 1	; _
	203	[448]	SETTABLE 	17 -7 18	; "text_func" -
	204	[449]	SELF     	18 0 -9	; "buildMenu"
	205	[449]	LOADK    	20 -36	; "one_finger_swipe_left_edge_up"
	206	[449]	GETTABLE 	21 0 -11	; "default_gesture"
	207	[449]	GETTABLE 	21 21 -36	; "one_finger_swipe_left_edge_up"
	208	[449]	CALL     	18 4 2
	209	[449]	SETTABLE 	17 -6 18	; "sub_item_table" -
	210	[450]	NEWTABLE 	18 0 2
	211	[452]	CLOSURE  	19 17	; 0x7fad9440dd10
	212	[452]	MOVE     	0 3
	213	[452]	GETUPVAL 	0 1	; _
	214	[452]	SETTABLE 	18 -7 19	; "text_func" -
	215	[453]	SELF     	19 0 -9	; "buildMenu"
	216	[453]	LOADK    	21 -37	; "one_finger_swipe_right_edge_down"
	217	[453]	GETTABLE 	22 0 -11	; "default_gesture"
	218	[453]	GETTABLE 	22 22 -37	; "one_finger_swipe_right_edge_down"
	219	[453]	CALL     	19 4 2
	220	[453]	SETTABLE 	18 -6 19	; "sub_item_table" -
	221	[454]	NEWTABLE 	19 0 2
	222	[456]	CLOSURE  	20 18	; 0x7fad9440f360
	223	[456]	MOVE     	0 3
	224	[456]	GETUPVAL 	0 1	; _
	225	[456]	SETTABLE 	19 -7 20	; "text_func" -
	226	[457]	SELF     	20 0 -9	; "buildMenu"
	227	[457]	LOADK    	22 -38	; "one_finger_swipe_right_edge_up"
	228	[457]	GETTABLE 	23 0 -11	; "default_gesture"
	229	[457]	GETTABLE 	23 23 -38	; "one_finger_swipe_right_edge_up"
	230	[457]	CALL     	20 4 2
	231	[457]	SETTABLE 	19 -6 20	; "sub_item_table" -
	232	[458]	NEWTABLE 	20 0 2
	233	[460]	CLOSURE  	21 19	; 0x7fad9440ee00
	234	[460]	MOVE     	0 3
	235	[460]	GETUPVAL 	0 1	; _
	236	[460]	SETTABLE 	20 -7 21	; "text_func" -
	237	[461]	SELF     	21 0 -9	; "buildMenu"
	238	[461]	LOADK    	23 -39	; "one_finger_swipe_top_edge_right"
	239	[461]	GETTABLE 	24 0 -11	; "default_gesture"
	240	[461]	GETTABLE 	24 24 -39	; "one_finger_swipe_top_edge_right"
	241	[461]	CALL     	21 4 2
	242	[461]	SETTABLE 	20 -6 21	; "sub_item_table" -
	243	[462]	NEWTABLE 	21 0 2
	244	[464]	CLOSURE  	22 20	; 0x7fad9440cd80
	245	[464]	MOVE     	0 3
	246	[464]	GETUPVAL 	0 1	; _
	247	[464]	SETTABLE 	21 -7 22	; "text_func" -
	248	[465]	SELF     	22 0 -9	; "buildMenu"
	249	[465]	LOADK    	24 -40	; "one_finger_swipe_top_edge_left"
	250	[465]	GETTABLE 	25 0 -11	; "default_gesture"
	251	[465]	GETTABLE 	25 25 -40	; "one_finger_swipe_top_edge_left"
	252	[465]	CALL     	22 4 2
	253	[465]	SETTABLE 	21 -6 22	; "sub_item_table" -
	254	[466]	NEWTABLE 	22 0 2
	255	[468]	CLOSURE  	23 21	; 0x7fad9440f620
	256	[468]	MOVE     	0 3
	257	[468]	GETUPVAL 	0 1	; _
	258	[468]	SETTABLE 	22 -7 23	; "text_func" -
	259	[469]	SELF     	23 0 -9	; "buildMenu"
	260	[469]	LOADK    	25 -41	; "one_finger_swipe_bottom_edge_right"
	261	[469]	GETTABLE 	26 0 -11	; "default_gesture"
	262	[469]	GETTABLE 	26 26 -41	; "one_finger_swipe_bottom_edge_right"
	263	[469]	CALL     	23 4 2
	264	[469]	SETTABLE 	22 -6 23	; "sub_item_table" -
	265	[470]	NEWTABLE 	23 0 2
	266	[472]	CLOSURE  	24 22	; 0x7fad9440f870
	267	[472]	MOVE     	0 3
	268	[472]	GETUPVAL 	0 1	; _
	269	[472]	SETTABLE 	23 -7 24	; "text_func" -
	270	[473]	SELF     	24 0 -9	; "buildMenu"
	271	[473]	LOADK    	26 -42	; "one_finger_swipe_bottom_edge_left"
	272	[473]	GETTABLE 	27 0 -11	; "default_gesture"
	273	[473]	GETTABLE 	27 27 -42	; "one_finger_swipe_bottom_edge_left"
	274	[473]	CALL     	24 4 2
	275	[473]	SETTABLE 	23 -6 24	; "sub_item_table" -
	276	[475]	SETLIST  	15 8 1	; 1
	277	[475]	SETTABLE 	14 -6 15	; "sub_item_table" -
	278	[477]	SETLIST  	7 7 1	; 1
	279	[477]	SETTABLE 	6 -6 7	; "sub_item_table" -
	280	[478]	SETTABLE 	1 -22 6	; "gesture_manager" -
	281	[479]	NEWTABLE 	6 0 2
	282	[480]	GETUPVAL 	7 1	; _
	283	[480]	LOADK    	8 -44	; "Gesture intervals"
	284	[480]	CALL     	7 2 2
	285	[480]	SETTABLE 	6 -4 7	; "text" -
	286	[481]	NEWTABLE 	7 5 0
	287	[481]	NEWTABLE 	8 0 2
	288	[483]	GETUPVAL 	9 1	; _
	289	[483]	LOADK    	10 -45	; "Double tap interval"
	290	[483]	CALL     	9 2 2
	291	[483]	SETTABLE 	8 -4 9	; "text" -
	292	[507]	CLOSURE  	9 23	; 0x7fad9440fd50
	293	[507]	GETUPVAL 	0 2	; T
	294	[507]	GETUPVAL 	0 1	; _
	295	[507]	GETUPVAL 	0 12	; Screen
	296	[507]	GETUPVAL 	0 5	; UIManager
	297	[507]	SETTABLE 	8 -26 9	; "callback" -
	298	[508]	NEWTABLE 	9 0 2
	299	[510]	GETUPVAL 	10 1	; _
	300	[510]	LOADK    	11 -46	; "Two finger tap duration"
	301	[510]	CALL     	10 2 2
	302	[510]	SETTABLE 	9 -4 10	; "text" -
	303	[534]	CLOSURE  	10 24	; 0x7fad94410880
	304	[534]	GETUPVAL 	0 2	; T
	305	[534]	GETUPVAL 	0 1	; _
	306	[534]	GETUPVAL 	0 12	; Screen
	307	[534]	GETUPVAL 	0 5	; UIManager
	308	[534]	SETTABLE 	9 -26 10	; "callback" -
	309	[535]	NEWTABLE 	10 0 2
	310	[537]	GETUPVAL 	11 1	; _
	311	[537]	LOADK    	12 -47	; "Hold interval"
	312	[537]	CALL     	11 2 2
	313	[537]	SETTABLE 	10 -4 11	; "text" -
	314	[561]	CLOSURE  	11 25	; 0x7fad94411440
	315	[561]	GETUPVAL 	0 2	; T
	316	[561]	GETUPVAL 	0 1	; _
	317	[561]	GETUPVAL 	0 12	; Screen
	318	[561]	GETUPVAL 	0 5	; UIManager
	319	[561]	SETTABLE 	10 -26 11	; "callback" -
	320	[562]	NEWTABLE 	11 0 2
	321	[564]	GETUPVAL 	12 1	; _
	322	[564]	LOADK    	13 -48	; "Pan delay interval"
	323	[564]	CALL     	12 2 2
	324	[564]	SETTABLE 	11 -4 12	; "text" -
	325	[588]	CLOSURE  	12 26	; 0x7fad94411ed0
	326	[588]	GETUPVAL 	0 2	; T
	327	[588]	GETUPVAL 	0 1	; _
	328	[588]	GETUPVAL 	0 12	; Screen
	329	[588]	GETUPVAL 	0 5	; UIManager
	330	[588]	SETTABLE 	11 -26 12	; "callback" -
	331	[589]	NEWTABLE 	12 0 2
	332	[591]	GETUPVAL 	13 1	; _
	333	[591]	LOADK    	14 -49	; "Swipe interval"
	334	[591]	CALL     	13 2 2
	335	[591]	SETTABLE 	12 -4 13	; "text" -
	336	[615]	CLOSURE  	13 27	; 0x7fad94412a30
	337	[615]	GETUPVAL 	0 2	; T
	338	[615]	GETUPVAL 	0 1	; _
	339	[615]	GETUPVAL 	0 12	; Screen
	340	[615]	GETUPVAL 	0 5	; UIManager
	341	[615]	SETTABLE 	12 -26 13	; "callback" -
	342	[617]	SETLIST  	7 5 1	; 1
	343	[617]	SETTABLE 	6 -6 7	; "sub_item_table" -
	344	[618]	SETTABLE 	1 -43 6	; "gesture_intervals" -
	345	[623]	CLOSURE  	6 28	; 0x7fad944134f0
	346	[623]	MOVE     	0 2
	347	[623]	GETUPVAL 	0 0	; action_strings
	348	[623]	GETUPVAL 	0 1	; _
	349	[623]	GETUPVAL 	0 2	; T
	350	[625]	GETUPVAL 	7 14	; Device
	351	[625]	SELF     	7 7 -50	; "hasMultitouch"
	352	[625]	CALL     	7 2 2
	353	[625]	TEST     	7 0 0
	354	[625]	JMP      	186	; to 541
	355	[626]	NEWTABLE 	7 0 2
	356	[627]	GETUPVAL 	8 1	; _
	357	[627]	LOADK    	9 -51	; "Two-finger tap corner"
	358	[627]	CALL     	8 2 2
	359	[627]	SETTABLE 	7 -4 8	; "text" -
	360	[628]	NEWTABLE 	8 4 0
	361	[628]	NEWTABLE 	9 0 2
	362	[630]	CLOSURE  	10 29	; 0x7fad94413a90
	363	[630]	MOVE     	0 3
	364	[630]	GETUPVAL 	0 1	; _
	365	[630]	SETTABLE 	9 -7 10	; "text_func" -
	366	[631]	SELF     	10 0 -9	; "buildMenu"
	367	[631]	LOADK    	12 -52	; "two_finger_tap_top_left_corner"
	368	[631]	GETTABLE 	13 0 -11	; "default_gesture"
	369	[631]	GETTABLE 	13 13 -52	; "two_finger_tap_top_left_corner"
	370	[631]	CALL     	10 4 2
	371	[631]	SETTABLE 	9 -6 10	; "sub_item_table" -
	372	[632]	NEWTABLE 	10 0 2
	373	[634]	CLOSURE  	11 30	; 0x7fad94413e20
	374	[634]	MOVE     	0 3
	375	[634]	GETUPVAL 	0 1	; _
	376	[634]	SETTABLE 	10 -7 11	; "text_func" -
	377	[635]	SELF     	11 0 -9	; "buildMenu"
	378	[635]	LOADK    	13 -53	; "two_finger_tap_top_right_corner"
	379	[635]	GETTABLE 	14 0 -11	; "default_gesture"
	380	[635]	GETTABLE 	14 14 -53	; "two_finger_tap_top_right_corner"
	381	[635]	CALL     	11 4 2
	382	[635]	SETTABLE 	10 -6 11	; "sub_item_table" -
	383	[636]	NEWTABLE 	11 0 2
	384	[638]	CLOSURE  	12 31	; 0x7fad944140b0
	385	[638]	MOVE     	0 3
	386	[638]	GETUPVAL 	0 1	; _
	387	[638]	SETTABLE 	11 -7 12	; "text_func" -
	388	[639]	SELF     	12 0 -9	; "buildMenu"
	389	[639]	LOADK    	14 -54	; "two_finger_tap_bottom_left_corner"
	390	[639]	GETTABLE 	15 0 -11	; "default_gesture"
	391	[639]	GETTABLE 	15 15 -54	; "two_finger_tap_bottom_left_corner"
	392	[639]	CALL     	12 4 2
	393	[639]	SETTABLE 	11 -6 12	; "sub_item_table" -
	394	[640]	NEWTABLE 	12 0 2
	395	[642]	CLOSURE  	13 32	; 0x7fad94414330
	396	[642]	MOVE     	0 3
	397	[642]	GETUPVAL 	0 1	; _
	398	[642]	SETTABLE 	12 -7 13	; "text_func" -
	399	[643]	SELF     	13 0 -9	; "buildMenu"
	400	[643]	LOADK    	15 -55	; "two_finger_tap_bottom_right_corner"
	401	[643]	GETTABLE 	16 0 -11	; "default_gesture"
	402	[643]	GETTABLE 	16 16 -55	; "two_finger_tap_bottom_right_corner"
	403	[643]	CALL     	13 4 2
	404	[643]	SETTABLE 	12 -6 13	; "sub_item_table" -
	405	[645]	SETLIST  	8 4 1	; 1
	406	[645]	SETTABLE 	7 -6 8	; "sub_item_table" -
	407	[647]	GETGLOBAL	8 -56	; table
	408	[647]	GETTABLE 	8 8 -57	; "insert"
	409	[647]	GETTABLE 	9 1 -22	; "gesture_manager"
	410	[647]	GETTABLE 	9 9 -6	; "sub_item_table"
	411	[647]	MOVE     	10 7
	412	[647]	CALL     	8 3 1
	413	[648]	GETGLOBAL	8 -56	; table
	414	[648]	GETTABLE 	8 8 -57	; "insert"
	415	[648]	GETTABLE 	9 1 -22	; "gesture_manager"
	416	[648]	GETTABLE 	9 9 -6	; "sub_item_table"
	417	[648]	NEWTABLE 	10 0 2
	418	[649]	GETUPVAL 	11 1	; _
	419	[649]	LOADK    	12 -58	; "Two-finger swipe"
	420	[649]	CALL     	11 2 2
	421	[649]	SETTABLE 	10 -4 11	; "text" -
	422	[650]	NEWTABLE 	11 8 0
	423	[650]	NEWTABLE 	12 0 2
	424	[652]	CLOSURE  	13 33	; 0x7fad94414620
	425	[652]	MOVE     	0 6
	426	[652]	SETTABLE 	12 -7 13	; "text_func" -
	427	[653]	SELF     	13 0 -9	; "buildMenu"
	428	[653]	LOADK    	15 -59	; "two_finger_swipe_east"
	429	[653]	GETTABLE 	16 0 -11	; "default_gesture"
	430	[653]	GETTABLE 	16 16 -59	; "two_finger_swipe_east"
	431	[653]	CALL     	13 4 2
	432	[653]	SETTABLE 	12 -6 13	; "sub_item_table" -
	433	[654]	NEWTABLE 	13 0 2
	434	[656]	CLOSURE  	14 34	; 0x7fad94414a20
	435	[656]	MOVE     	0 6
	436	[656]	SETTABLE 	13 -7 14	; "text_func" -
	437	[657]	SELF     	14 0 -9	; "buildMenu"
	438	[657]	LOADK    	16 -60	; "two_finger_swipe_west"
	439	[657]	GETTABLE 	17 0 -11	; "default_gesture"
	440	[657]	GETTABLE 	17 17 -60	; "two_finger_swipe_west"
	441	[657]	CALL     	14 4 2
	442	[657]	SETTABLE 	13 -6 14	; "sub_item_table" -
	443	[658]	NEWTABLE 	14 0 2
	444	[660]	CLOSURE  	15 35	; 0x7fad94414c60
	445	[660]	MOVE     	0 6
	446	[660]	SETTABLE 	14 -7 15	; "text_func" -
	447	[661]	SELF     	15 0 -9	; "buildMenu"
	448	[661]	LOADK    	17 -61	; "two_finger_swipe_south"
	449	[661]	GETTABLE 	18 0 -11	; "default_gesture"
	450	[661]	GETTABLE 	18 18 -61	; "two_finger_swipe_south"
	451	[661]	CALL     	15 4 2
	452	[661]	SETTABLE 	14 -6 15	; "sub_item_table" -
	453	[662]	NEWTABLE 	15 0 2
	454	[664]	CLOSURE  	16 36	; 0x7fad94414f20
	455	[664]	MOVE     	0 6
	456	[664]	SETTABLE 	15 -7 16	; "text_func" -
	457	[665]	SELF     	16 0 -9	; "buildMenu"
	458	[665]	LOADK    	18 -62	; "two_finger_swipe_north"
	459	[665]	GETTABLE 	19 0 -11	; "default_gesture"
	460	[665]	GETTABLE 	19 19 -62	; "two_finger_swipe_north"
	461	[665]	CALL     	16 4 2
	462	[665]	SETTABLE 	15 -6 16	; "sub_item_table" -
	463	[666]	NEWTABLE 	16 0 2
	464	[668]	CLOSURE  	17 37	; 0x7fad944151b0
	465	[668]	MOVE     	0 6
	466	[668]	SETTABLE 	16 -7 17	; "text_func" -
	467	[669]	SELF     	17 0 -9	; "buildMenu"
	468	[669]	LOADK    	19 -63	; "two_finger_swipe_northeast"
	469	[669]	GETTABLE 	20 0 -11	; "default_gesture"
	470	[669]	GETTABLE 	20 20 -63	; "two_finger_swipe_northeast"
	471	[669]	CALL     	17 4 2
	472	[669]	SETTABLE 	16 -6 17	; "sub_item_table" -
	473	[670]	NEWTABLE 	17 0 2
	474	[672]	CLOSURE  	18 38	; 0x7fad94415460
	475	[672]	MOVE     	0 6
	476	[672]	SETTABLE 	17 -7 18	; "text_func" -
	477	[673]	SELF     	18 0 -9	; "buildMenu"
	478	[673]	LOADK    	20 -64	; "two_finger_swipe_northwest"
	479	[673]	GETTABLE 	21 0 -11	; "default_gesture"
	480	[673]	GETTABLE 	21 21 -64	; "two_finger_swipe_northwest"
	481	[673]	CALL     	18 4 2
	482	[673]	SETTABLE 	17 -6 18	; "sub_item_table" -
	483	[674]	NEWTABLE 	18 0 2
	484	[676]	CLOSURE  	19 39	; 0x7fad94415700
	485	[676]	MOVE     	0 6
	486	[676]	SETTABLE 	18 -7 19	; "text_func" -
	487	[677]	SELF     	19 0 -9	; "buildMenu"
	488	[677]	LOADK    	21 -65	; "two_finger_swipe_southeast"
	489	[677]	GETTABLE 	22 0 -11	; "default_gesture"
	490	[677]	GETTABLE 	22 22 -65	; "two_finger_swipe_southeast"
	491	[677]	CALL     	19 4 2
	492	[677]	SETTABLE 	18 -6 19	; "sub_item_table" -
	493	[678]	NEWTABLE 	19 0 2
	494	[680]	CLOSURE  	20 40	; 0x7fad944159a0
	495	[680]	MOVE     	0 6
	496	[680]	SETTABLE 	19 -7 20	; "text_func" -
	497	[681]	SELF     	20 0 -9	; "buildMenu"
	498	[681]	LOADK    	22 -66	; "two_finger_swipe_southwest"
	499	[681]	GETTABLE 	23 0 -11	; "default_gesture"
	500	[681]	GETTABLE 	23 23 -66	; "two_finger_swipe_southwest"
	501	[681]	CALL     	20 4 2
	502	[681]	SETTABLE 	19 -6 20	; "sub_item_table" -
	503	[683]	SETLIST  	11 8 1	; 1
	504	[683]	SETTABLE 	10 -6 11	; "sub_item_table" -
	505	[648]	CALL     	8 3 1
	506	[685]	GETGLOBAL	8 -56	; table
	507	[685]	GETTABLE 	8 8 -57	; "insert"
	508	[685]	GETTABLE 	9 1 -22	; "gesture_manager"
	509	[685]	GETTABLE 	9 9 -6	; "sub_item_table"
	510	[685]	NEWTABLE 	10 0 2
	511	[686]	GETUPVAL 	11 1	; _
	512	[686]	LOADK    	12 -67	; "Spread and pinch"
	513	[686]	CALL     	11 2 2
	514	[686]	SETTABLE 	10 -4 11	; "text" -
	515	[687]	NEWTABLE 	11 2 0
	516	[687]	NEWTABLE 	12 0 2
	517	[689]	CLOSURE  	13 41	; 0x7fad94415c70
	518	[689]	MOVE     	0 3
	519	[689]	GETUPVAL 	0 1	; _
	520	[689]	SETTABLE 	12 -7 13	; "text_func" -
	521	[690]	SELF     	13 0 -9	; "buildMenu"
	522	[690]	LOADK    	15 -68	; "spread_gesture"
	523	[690]	GETTABLE 	16 0 -11	; "default_gesture"
	524	[690]	GETTABLE 	16 16 -68	; "spread_gesture"
	525	[690]	CALL     	13 4 2
	526	[690]	SETTABLE 	12 -6 13	; "sub_item_table" -
	527	[691]	NEWTABLE 	13 0 2
	528	[693]	CLOSURE  	14 42	; 0x7fad94415f20
	529	[693]	MOVE     	0 3
	530	[693]	GETUPVAL 	0 1	; _
	531	[693]	SETTABLE 	13 -7 14	; "text_func" -
	532	[694]	SELF     	14 0 -9	; "buildMenu"
	533	[694]	LOADK    	16 -69	; "pinch_gesture"
	534	[694]	GETTABLE 	17 0 -11	; "default_gesture"
	535	[694]	GETTABLE 	17 17 -69	; "pinch_gesture"
	536	[694]	CALL     	14 4 2
	537	[694]	SETTABLE 	13 -6 14	; "sub_item_table" -
	538	[696]	SETLIST  	11 2 1	; 1
	539	[696]	SETTABLE 	10 -6 11	; "sub_item_table" -
	540	[685]	CALL     	8 3 1
	541	[699]	RETURN   	0 1

function <./frontend/apps/reader/modules/readergesture.lua:303,306> (22 instructions, 88 bytes at 0x7fad9440bce0)
2 params, 7 slots, 4 upvalues, 3 locals, 3 constants, 0 functions
	1	[304]	GETUPVAL 	2 0	; gesture_manager
	2	[304]	GETTABLE 	2 2 0
	3	[304]	EQ       	1 2 -1	; - "nothing"
	4	[304]	JMP      	6	; to 11
	5	[304]	GETUPVAL 	2 1	; action_strings
	6	[304]	GETUPVAL 	3 0	; gesture_manager
	7	[304]	GETTABLE 	3 3 0
	8	[304]	GETTABLE 	2 2 3
	9	[304]	TEST     	2 0 1
	10	[304]	JMP      	3	; to 14
	11	[304]	GETUPVAL 	2 2	; _
	12	[304]	LOADK    	3 -2	; "Available"
	13	[304]	CALL     	2 2 2
	14	[305]	GETUPVAL 	3 3	; T
	15	[305]	GETUPVAL 	4 2	; _
	16	[305]	LOADK    	5 -3	; "%1   (%2)"
	17	[305]	CALL     	4 2 2
	18	[305]	MOVE     	5 1
	19	[305]	MOVE     	6 2
	20	[305]	TAILCALL 	3 4 0
	21	[305]	RETURN   	3 0
	22	[306]	RETURN   	0 1

function <./frontend/apps/reader/modules/readergesture.lua:311,311> (8 instructions, 32 bytes at 0x7fad9440c6a0)
0 params, 4 slots, 2 upvalues, 0 locals, 2 constants, 0 functions
	1	[311]	GETUPVAL 	0 0	; actionTextFunc
	2	[311]	LOADK    	1 -1	; "tap_top_left_corner"
	3	[311]	GETUPVAL 	2 1	; _
	4	[311]	LOADK    	3 -2	; "Top left"
	5	[311]	CALL     	2 2 0
	6	[311]	TAILCALL 	0 0 0
	7	[311]	RETURN   	0 0
	8	[311]	RETURN   	0 1

function <./frontend/apps/reader/modules/readergesture.lua:312,312> (8 instructions, 32 bytes at 0x7fad9440ca10)
0 params, 2 slots, 1 upvalue, 0 locals, 2 constants, 0 functions
	1	[312]	GETUPVAL 	0 0	; self
	2	[312]	GETTABLE 	0 0 -1	; "ges_mode"
	3	[312]	EQ       	1 0 -2	; - "gesture_reader"
	4	[312]	JMP      	1	; to 6
	5	[312]	LOADBOOL 	0 0 1
	6	[312]	LOADBOOL 	0 1 0
	7	[312]	RETURN   	0 2
	8	[312]	RETURN   	0 1

function <./frontend/apps/reader/modules/readergesture.lua:316,316> (8 instructions, 32 bytes at 0x7fad9440c620)
0 params, 4 slots, 2 upvalues, 0 locals, 2 constants, 0 functions
	1	[316]	GETUPVAL 	0 0	; actionTextFunc
	2	[316]	LOADK    	1 -1	; "tap_top_right_corner"
	3	[316]	GETUPVAL 	2 1	; _
	4	[316]	LOADK    	3 -2	; "Top right"
	5	[316]	CALL     	2 2 0
	6	[316]	TAILCALL 	0 0 0
	7	[316]	RETURN   	0 0
	8	[316]	RETURN   	0 1

function <./frontend/apps/reader/modules/readergesture.lua:320,320> (8 instructions, 32 bytes at 0x7fad9440c990)
0 params, 4 slots, 2 upvalues, 0 locals, 2 constants, 0 functions
	1	[320]	GETUPVAL 	0 0	; actionTextFunc
	2	[320]	LOADK    	1 -1	; "tap_left_bottom_corner"
	3	[320]	GETUPVAL 	2 1	; _
	4	[320]	LOADK    	3 -2	; "Bottom left"
	5	[320]	CALL     	2 2 0
	6	[320]	TAILCALL 	0 0 0
	7	[320]	RETURN   	0 0
	8	[320]	RETURN   	0 1

function <./frontend/apps/reader/modules/readergesture.lua:324,324> (8 instructions, 32 bytes at 0x7fad9440d140)
0 params, 4 slots, 2 upvalues, 0 locals, 2 constants, 0 functions
	1	[324]	GETUPVAL 	0 0	; actionTextFunc
	2	[324]	LOADK    	1 -1	; "tap_right_bottom_corner"
	3	[324]	GETUPVAL 	2 1	; _
	4	[324]	LOADK    	3 -2	; "Bottom right"
	5	[324]	CALL     	2 2 0
	6	[324]	TAILCALL 	0 0 0
	7	[324]	RETURN   	0 0
	8	[324]	RETURN   	0 1

function <./frontend/apps/reader/modules/readergesture.lua:334,334> (8 instructions, 32 bytes at 0x7fad9440be10)
0 params, 4 slots, 2 upvalues, 0 locals, 2 constants, 0 functions
	1	[334]	GETUPVAL 	0 0	; actionTextFunc
	2	[334]	LOADK    	1 -1	; "hold_top_left_corner"
	3	[334]	GETUPVAL 	2 1	; _
	4	[334]	LOADK    	3 -2	; "Top left"
	5	[334]	CALL     	2 2 0
	6	[334]	TAILCALL 	0 0 0
	7	[334]	RETURN   	0 0
	8	[334]	RETURN   	0 1

function <./frontend/apps/reader/modules/readergesture.lua:335,335> (8 instructions, 32 bytes at 0x7fad9440d830)
0 params, 2 slots, 1 upvalue, 0 locals, 2 constants, 0 functions
	1	[335]	GETUPVAL 	0 0	; self
	2	[335]	GETTABLE 	0 0 -1	; "ges_mode"
	3	[335]	EQ       	1 0 -2	; - "gesture_reader"
	4	[335]	JMP      	1	; to 6
	5	[335]	LOADBOOL 	0 0 1
	6	[335]	LOADBOOL 	0 1 0
	7	[335]	RETURN   	0 2
	8	[335]	RETURN   	0 1

function <./frontend/apps/reader/modules/readergesture.lua:339,339> (8 instructions, 32 bytes at 0x7fad9440da50)
0 params, 4 slots, 2 upvalues, 0 locals, 2 constants, 0 functions
	1	[339]	GETUPVAL 	0 0	; actionTextFunc
	2	[339]	LOADK    	1 -1	; "hold_top_right_corner"
	3	[339]	GETUPVAL 	2 1	; _
	4	[339]	LOADK    	3 -2	; "Top right"
	5	[339]	CALL     	2 2 0
	6	[339]	TAILCALL 	0 0 0
	7	[339]	RETURN   	0 0
	8	[339]	RETURN   	0 1

function <./frontend/apps/reader/modules/readergesture.lua:343,343> (8 instructions, 32 bytes at 0x7fad9440df20)
0 params, 4 slots, 2 upvalues, 0 locals, 2 constants, 0 functions
	1	[343]	GETUPVAL 	0 0	; actionTextFunc
	2	[343]	LOADK    	1 -1	; "hold_bottom_left_corner"
	3	[343]	GETUPVAL 	2 1	; _
	4	[343]	LOADK    	3 -2	; "Bottom left"
	5	[343]	CALL     	2 2 0
	6	[343]	TAILCALL 	0 0 0
	7	[343]	RETURN   	0 0
	8	[343]	RETURN   	0 1

function <./frontend/apps/reader/modules/readergesture.lua:347,347> (8 instructions, 32 bytes at 0x7fad9440dfa0)
0 params, 4 slots, 2 upvalues, 0 locals, 2 constants, 0 functions
	1	[347]	GETUPVAL 	0 0	; actionTextFunc
	2	[347]	LOADK    	1 -1	; "hold_bottom_right_corner"
	3	[347]	GETUPVAL 	2 1	; _
	4	[347]	LOADK    	3 -2	; "Bottom right"
	5	[347]	CALL     	2 2 0
	6	[347]	TAILCALL 	0 0 0
	7	[347]	RETURN   	0 0
	8	[347]	RETURN   	0 1

function <./frontend/apps/reader/modules/readergesture.lua:357,357> (4 instructions, 16 bytes at 0x7fad9440d430)
0 params, 2 slots, 1 upvalue, 0 locals, 1 constant, 0 functions
	1	[357]	GETUPVAL 	0 0	; self
	2	[357]	GETTABLE 	0 0 -1	; "multiswipes_enabled"
	3	[357]	RETURN   	0 2
	4	[357]	RETURN   	0 1

function <./frontend/apps/reader/modules/readergesture.lua:358,361> (14 instructions, 56 bytes at 0x7fad9440d5e0)
0 params, 4 slots, 1 upvalue, 0 locals, 4 constants, 0 functions
	1	[359]	GETGLOBAL	0 -1	; G_reader_settings
	2	[359]	SELF     	0 0 -2	; "saveSetting"
	3	[359]	LOADK    	2 -3	; "multiswipes_enabled"
	4	[359]	GETUPVAL 	3 0	; self
	5	[359]	GETTABLE 	3 3 -3	; "multiswipes_enabled"
	6	[359]	NOT      	3 3
	7	[359]	CALL     	0 4 1
	8	[360]	GETUPVAL 	0 0	; self
	9	[360]	GETGLOBAL	1 -1	; G_reader_settings
	10	[360]	SELF     	1 1 -4	; "isTrue"
	11	[360]	LOADK    	3 -3	; "multiswipes_enabled"
	12	[360]	CALL     	1 3 2
	13	[360]	SETTABLE 	0 -3 1	; "multiswipes_enabled" -
	14	[361]	RETURN   	0 1

function <./frontend/apps/reader/modules/readergesture.lua:366,366> (4 instructions, 16 bytes at 0x7fad9440e5c0)
0 params, 2 slots, 1 upvalue, 0 locals, 1 constant, 0 functions
	1	[366]	GETUPVAL 	0 0	; self
	2	[366]	GETTABLE 	0 0 -1	; "multiswipes_enabled"
	3	[366]	RETURN   	0 2
	4	[366]	RETURN   	0 1

function <./frontend/apps/reader/modules/readergesture.lua:368,429> (78 instructions, 312 bytes at 0x7fad9440e760)
1 param, 12 slots, 12 upvalues, 2 locals, 28 constants, 3 functions
	1	[370]	GETUPVAL 	2 0	; InputDialog
	2	[370]	SELF     	2 2 -1	; "new"
	3	[370]	NEWTABLE 	4 0 3
	4	[371]	GETUPVAL 	5 1	; _
	5	[371]	LOADK    	6 -3	; "Multiswipe recorder"
	6	[371]	CALL     	5 2 2
	7	[371]	SETTABLE 	4 -2 5	; "title" -
	8	[372]	GETUPVAL 	5 1	; _
	9	[372]	LOADK    	6 -5	; "Make a multiswipe gesture"
	10	[372]	CALL     	5 2 2
	11	[372]	SETTABLE 	4 -4 5	; "input_hint" -
	12	[373]	NEWTABLE 	5 1 0
	13	[373]	NEWTABLE 	6 2 0
	14	[374]	NEWTABLE 	7 0 2
	15	[376]	GETUPVAL 	8 1	; _
	16	[376]	LOADK    	9 -8	; "Cancel"
	17	[376]	CALL     	8 2 2
	18	[376]	SETTABLE 	7 -7 8	; "text" -
	19	[379]	CLOSURE  	8 0	; 0x7fad9440e960
	20	[379]	GETUPVAL 	0 2	; UIManager
	21	[379]	MOVE     	0 1
	22	[379]	SETTABLE 	7 -9 8	; "callback" -
	23	[380]	NEWTABLE 	8 0 3
	24	[382]	GETUPVAL 	9 1	; _
	25	[382]	LOADK    	10 -10	; "Save"
	26	[382]	CALL     	9 2 2
	27	[382]	SETTABLE 	8 -7 9	; "text" -
	28	[383]	SETTABLE 	8 -11 -12	; "is_enter_default" true
	29	[405]	CLOSURE  	9 1	; 0x7fad9440eae0
	30	[405]	MOVE     	0 1
	31	[405]	GETUPVAL 	0 3	; logger
	32	[405]	GETUPVAL 	0 4	; multiswipes
	33	[405]	GETUPVAL 	0 2	; UIManager
	34	[405]	GETUPVAL 	0 5	; InfoMessage
	35	[405]	GETUPVAL 	0 1	; _
	36	[405]	GETUPVAL 	0 6	; custom_multiswipes
	37	[405]	MOVE     	0 0
	38	[405]	GETUPVAL 	0 7	; self
	39	[405]	SETTABLE 	8 -9 9	; "callback" -
	40	[407]	SETLIST  	6 2 1	; 1
	41	[408]	SETLIST  	5 1 1	; 1
	42	[408]	SETTABLE 	4 -6 5	; "buttons" -
	43	[370]	CALL     	2 3 2
	44	[409]	MOVE     	1 2
	45	[411]	GETTABLE 	2 1 -13	; "ges_events"
	46	[411]	NEWTABLE 	3 0 0
	47	[412]	GETUPVAL 	4 8	; GestureRange
	48	[412]	SELF     	4 4 -1	; "new"
	49	[412]	NEWTABLE 	6 0 3
	50	[413]	SETTABLE 	6 -15 -16	; "ges" "multiswipe"
	51	[414]	GETUPVAL 	7 9	; Geom
	52	[414]	SELF     	7 7 -1	; "new"
	53	[414]	NEWTABLE 	9 0 4
	54	[415]	SETTABLE 	9 -18 -19	; "x" 0
	55	[415]	SETTABLE 	9 -20 -19	; "y" 0
	56	[416]	GETUPVAL 	10 10	; Screen
	57	[416]	SELF     	10 10 -22	; "getWidth"
	58	[416]	CALL     	10 2 2
	59	[416]	SETTABLE 	9 -21 10	; "w" -
	60	[417]	GETUPVAL 	10 10	; Screen
	61	[417]	SELF     	10 10 -24	; "getHeight"
	62	[417]	CALL     	10 2 2
	63	[417]	SETTABLE 	9 -23 10	; "h" -
	64	[414]	CALL     	7 3 2
	65	[418]	SETTABLE 	6 -17 7	; "range" -
	66	[419]	SETTABLE 	6 -25 -26	; "doc" "Multiswipe in gesture creator"
	67	[412]	CALL     	4 3 0
	68	[421]	SETLIST  	3 0 1	; 1
	69	[421]	SETTABLE 	2 -14 3	; "Multiswipe" -
	70	[426]	CLOSURE  	2 2	; 0x7fad9440e540
	71	[426]	MOVE     	0 1
	72	[426]	GETUPVAL 	0 11	; ReaderGesture
	73	[423]	SETTABLE 	1 -27 2	; "onMultiswipe" -
	74	[428]	GETUPVAL 	2 2	; UIManager
	75	[428]	SELF     	2 2 -28	; "show"
	76	[428]	MOVE     	4 1
	77	[428]	CALL     	2 3 1
	78	[429]	RETURN   	0 1

function <./frontend/apps/reader/modules/readergesture.lua:377,379> (5 instructions, 20 bytes at 0x7fad9440e960)
0 params, 3 slots, 2 upvalues, 0 locals, 1 constant, 0 functions
	1	[378]	GETUPVAL 	0 0	; UIManager
	2	[378]	SELF     	0 0 -1	; "close"
	3	[378]	GETUPVAL 	2 1	; multiswipe_recorder
	4	[378]	CALL     	0 3 1
	5	[379]	RETURN   	0 1

function <./frontend/apps/reader/modules/readergesture.lua:384,405> (51 instructions, 204 bytes at 0x7fad9440eae0)
0 params, 13 slots, 9 upvalues, 6 locals, 19 constants, 0 functions
	1	[385]	GETUPVAL 	0 0	; multiswipe_recorder
	2	[385]	GETTABLE 	0 0 -1	; "_raw_multiswipe"
	3	[386]	TEST     	0 0 1
	4	[386]	JMP      	1	; to 6
	5	[386]	RETURN   	0 1
	6	[387]	GETUPVAL 	1 1	; logger
	7	[387]	GETTABLE 	1 1 -2	; "dbg"
	8	[387]	LOADK    	2 -3	; "Multiswipe recorder detected:"
	9	[387]	MOVE     	3 0
	10	[387]	CALL     	1 3 1
	11	[389]	GETGLOBAL	1 -4	; pairs
	12	[389]	GETUPVAL 	2 2	; multiswipes
	13	[389]	CALL     	1 2 4
	14	[389]	JMP      	16	; to 31
	15	[390]	EQ       	0 0 5
	16	[390]	JMP      	14	; to 31
	17	[391]	GETUPVAL 	6 3	; UIManager
	18	[391]	SELF     	6 6 -5	; "show"
	19	[391]	GETUPVAL 	8 4	; InfoMessage
	20	[391]	SELF     	8 8 -6	; "new"
	21	[391]	NEWTABLE 	10 0 3
	22	[392]	GETUPVAL 	11 5	; _
	23	[392]	LOADK    	12 -8	; "Recorded multiswipe already exists."
	24	[392]	CALL     	11 2 2
	25	[392]	SETTABLE 	10 -7 11	; "text" -
	26	[393]	SETTABLE 	10 -9 -10	; "show_icon" false
	27	[394]	SETTABLE 	10 -11 -12	; "timeout" 5
	28	[391]	CALL     	8 3 0
	29	[391]	CALL     	6 0 1
	30	[396]	RETURN   	0 1
	31	[389]	TFORLOOP 	1 2
	32	[397]	JMP      	-18	; to 15
	33	[400]	GETUPVAL 	1 6	; custom_multiswipes
	34	[400]	SELF     	1 1 -13	; "addTableItem"
	35	[400]	LOADK    	3 -14	; "multiswipes"
	36	[400]	MOVE     	4 0
	37	[400]	CALL     	1 4 1
	38	[402]	GETUPVAL 	1 7	; touchmenu_instance
	39	[402]	GETTABLE 	1 1 -15	; "item_table"
	40	[402]	GETUPVAL 	2 8	; self
	41	[402]	SELF     	2 2 -17	; "genMultiswipeSubmenu"
	42	[402]	CALL     	2 2 2
	43	[402]	SETTABLE 	1 -16 2	; 3 -
	44	[403]	GETUPVAL 	1 7	; touchmenu_instance
	45	[403]	SELF     	1 1 -18	; "updateItems"
	46	[403]	CALL     	1 2 1
	47	[404]	GETUPVAL 	1 3	; UIManager
	48	[404]	SELF     	1 1 -19	; "close"
	49	[404]	GETUPVAL 	3 0	; multiswipe_recorder
	50	[404]	CALL     	1 3 1
	51	[405]	RETURN   	0 1

function <./frontend/apps/reader/modules/readergesture.lua:423,426> (12 instructions, 48 bytes at 0x7fad9440e540)
3 params, 8 slots, 2 upvalues, 3 locals, 4 constants, 0 functions
	1	[424]	GETUPVAL 	3 0	; multiswipe_recorder
	2	[424]	GETTABLE 	4 2 -2	; "multiswipe_directions"
	3	[424]	SETTABLE 	3 -1 4	; "_raw_multiswipe" -
	4	[425]	GETUPVAL 	3 0	; multiswipe_recorder
	5	[425]	SELF     	3 3 -3	; "setInputText"
	6	[425]	GETUPVAL 	5 1	; ReaderGesture
	7	[425]	SELF     	5 5 -4	; "friendlyMultiswipeName"
	8	[425]	GETUPVAL 	7 0	; multiswipe_recorder
	9	[425]	GETTABLE 	7 7 -1	; "_raw_multiswipe"
	10	[425]	CALL     	5 3 0
	11	[425]	CALL     	3 0 1
	12	[426]	RETURN   	0 1

function <./frontend/apps/reader/modules/readergesture.lua:444,444> (8 instructions, 32 bytes at 0x7fad9440c490)
0 params, 4 slots, 2 upvalues, 0 locals, 2 constants, 0 functions
	1	[444]	GETUPVAL 	0 0	; actionTextFunc
	2	[444]	LOADK    	1 -1	; "one_finger_swipe_left_edge_down"
	3	[444]	GETUPVAL 	2 1	; _
	4	[444]	LOADK    	3 -2	; "Left edge down"
	5	[444]	CALL     	2 2 0
	6	[444]	TAILCALL 	0 0 0
	7	[444]	RETURN   	0 0
	8	[444]	RETURN   	0 1

function <./frontend/apps/reader/modules/readergesture.lua:448,448> (8 instructions, 32 bytes at 0x7fad9440d530)
0 params, 4 slots, 2 upvalues, 0 locals, 2 constants, 0 functions
	1	[448]	GETUPVAL 	0 0	; actionTextFunc
	2	[448]	LOADK    	1 -1	; "one_finger_swipe_left_edge_up"
	3	[448]	GETUPVAL 	2 1	; _
	4	[448]	LOADK    	3 -2	; "Left edge up"
	5	[448]	CALL     	2 2 0
	6	[448]	TAILCALL 	0 0 0
	7	[448]	RETURN   	0 0
	8	[448]	RETURN   	0 1

function <./frontend/apps/reader/modules/readergesture.lua:452,452> (8 instructions, 32 bytes at 0x7fad9440dd10)
0 params, 4 slots, 2 upvalues, 0 locals, 2 constants, 0 functions
	1	[452]	GETUPVAL 	0 0	; actionTextFunc
	2	[452]	LOADK    	1 -1	; "one_finger_swipe_right_edge_down"
	3	[452]	GETUPVAL 	2 1	; _
	4	[452]	LOADK    	3 -2	; "Right edge down"
	5	[452]	CALL     	2 2 0
	6	[452]	TAILCALL 	0 0 0
	7	[452]	RETURN   	0 0
	8	[452]	RETURN   	0 1

function <./frontend/apps/reader/modules/readergesture.lua:456,456> (8 instructions, 32 bytes at 0x7fad9440f360)
0 params, 4 slots, 2 upvalues, 0 locals, 2 constants, 0 functions
	1	[456]	GETUPVAL 	0 0	; actionTextFunc
	2	[456]	LOADK    	1 -1	; "one_finger_swipe_right_edge_up"
	3	[456]	GETUPVAL 	2 1	; _
	4	[456]	LOADK    	3 -2	; "Right edge up"
	5	[456]	CALL     	2 2 0
	6	[456]	TAILCALL 	0 0 0
	7	[456]	RETURN   	0 0
	8	[456]	RETURN   	0 1

function <./frontend/apps/reader/modules/readergesture.lua:460,460> (8 instructions, 32 bytes at 0x7fad9440ee00)
0 params, 4 slots, 2 upvalues, 0 locals, 2 constants, 0 functions
	1	[460]	GETUPVAL 	0 0	; actionTextFunc
	2	[460]	LOADK    	1 -1	; "one_finger_swipe_top_edge_right"
	3	[460]	GETUPVAL 	2 1	; _
	4	[460]	LOADK    	3 -2	; "Top edge right"
	5	[460]	CALL     	2 2 0
	6	[460]	TAILCALL 	0 0 0
	7	[460]	RETURN   	0 0
	8	[460]	RETURN   	0 1

function <./frontend/apps/reader/modules/readergesture.lua:464,464> (8 instructions, 32 bytes at 0x7fad9440cd80)
0 params, 4 slots, 2 upvalues, 0 locals, 2 constants, 0 functions
	1	[464]	GETUPVAL 	0 0	; actionTextFunc
	2	[464]	LOADK    	1 -1	; "one_finger_swipe_top_edge_left"
	3	[464]	GETUPVAL 	2 1	; _
	4	[464]	LOADK    	3 -2	; "Top edge left"
	5	[464]	CALL     	2 2 0
	6	[464]	TAILCALL 	0 0 0
	7	[464]	RETURN   	0 0
	8	[464]	RETURN   	0 1

function <./frontend/apps/reader/modules/readergesture.lua:468,468> (8 instructions, 32 bytes at 0x7fad9440f620)
0 params, 4 slots, 2 upvalues, 0 locals, 2 constants, 0 functions
	1	[468]	GETUPVAL 	0 0	; actionTextFunc
	2	[468]	LOADK    	1 -1	; "one_finger_swipe_bottom_edge_right"
	3	[468]	GETUPVAL 	2 1	; _
	4	[468]	LOADK    	3 -2	; "Bottom edge right"
	5	[468]	CALL     	2 2 0
	6	[468]	TAILCALL 	0 0 0
	7	[468]	RETURN   	0 0
	8	[468]	RETURN   	0 1

function <./frontend/apps/reader/modules/readergesture.lua:472,472> (8 instructions, 32 bytes at 0x7fad9440f870)
0 params, 4 slots, 2 upvalues, 0 locals, 2 constants, 0 functions
	1	[472]	GETUPVAL 	0 0	; actionTextFunc
	2	[472]	LOADK    	1 -1	; "one_finger_swipe_bottom_edge_left"
	3	[472]	GETUPVAL 	2 1	; _
	4	[472]	LOADK    	3 -2	; "Bottom edge left"
	5	[472]	CALL     	2 2 0
	6	[472]	TAILCALL 	0 0 0
	7	[472]	RETURN   	0 0
	8	[472]	RETURN   	0 1

function <./frontend/apps/reader/modules/readergesture.lua:484,507> (50 instructions, 200 bytes at 0x7fad9440fd50)
0 params, 8 slots, 4 upvalues, 3 locals, 28 constants, 1 function
	1	[485]	GETGLOBAL	0 -1	; require
	2	[485]	LOADK    	1 -2	; "ui/widget/spinwidget"
	3	[485]	CALL     	0 2 2
	4	[486]	GETGLOBAL	1 -1	; require
	5	[486]	LOADK    	2 -3	; "device/gesturedetector"
	6	[486]	CALL     	1 2 2
	7	[487]	SELF     	2 0 -4	; "new"
	8	[487]	NEWTABLE 	4 0 11
	9	[488]	GETUPVAL 	5 0	; T
	10	[488]	GETUPVAL 	6 1	; _
	11	[491]	LOADK    	7 -6	; "Set double tap interval in milliseconds.\nThe interval value can range from 100 (0.1 seconds) to 2000 (2 seconds).\nDefault value: %1"
	12	[488]	CALL     	6 2 2
	13	[491]	GETTABLE 	7 1 -7	; "DOUBLE_TAP_INTERVAL"
	14	[491]	DIV      	7 7 -8	; - 1000
	15	[488]	CALL     	5 3 2
	16	[491]	SETTABLE 	4 -5 5	; "text" -
	17	[492]	GETUPVAL 	5 2	; Screen
	18	[492]	SELF     	5 5 -10	; "getWidth"
	19	[492]	CALL     	5 2 2
	20	[492]	MUL      	5 5 -11	; - 0.6
	21	[492]	SETTABLE 	4 -9 5	; "width" -
	22	[493]	SELF     	5 1 -13	; "getInterval"
	23	[493]	LOADK    	7 -14	; "ges_double_tap_interval"
	24	[493]	CALL     	5 3 2
	25	[493]	DIV      	5 5 -8	; - 1000
	26	[493]	SETTABLE 	4 -12 5	; "value" -
	27	[494]	SETTABLE 	4 -15 -16	; "value_min" 100
	28	[495]	SETTABLE 	4 -17 -18	; "value_max" 2000
	29	[496]	SETTABLE 	4 -19 -16	; "value_step" 100
	30	[497]	SETTABLE 	4 -20 -21	; "value_hold_step" 500
	31	[498]	GETUPVAL 	5 1	; _
	32	[498]	LOADK    	6 -23	; "Set interval"
	33	[498]	CALL     	5 2 2
	34	[498]	SETTABLE 	4 -22 5	; "ok_text" -
	35	[499]	GETUPVAL 	5 1	; _
	36	[499]	LOADK    	6 -25	; "Double tap interval"
	37	[499]	CALL     	5 2 2
	38	[499]	SETTABLE 	4 -24 5	; "title_text" -
	39	[500]	GETTABLE 	5 1 -7	; "DOUBLE_TAP_INTERVAL"
	40	[500]	DIV      	5 5 -8	; - 1000
	41	[500]	SETTABLE 	4 -26 5	; "default_value" -
	42	[504]	CLOSURE  	5 0	; 0x7fad94410120
	43	[504]	MOVE     	0 1
	44	[504]	SETTABLE 	4 -27 5	; "callback" -
	45	[487]	CALL     	2 3 2
	46	[506]	GETUPVAL 	3 3	; UIManager
	47	[506]	SELF     	3 3 -28	; "show"
	48	[506]	MOVE     	5 2
	49	[506]	CALL     	3 3 1
	50	[507]	RETURN   	0 1

function <./frontend/apps/reader/modules/readergesture.lua:501,504> (13 instructions, 52 bytes at 0x7fad94410120)
1 param, 5 slots, 1 upvalue, 1 local, 6 constants, 0 functions
	1	[502]	GETGLOBAL	1 -1	; G_reader_settings
	2	[502]	SELF     	1 1 -2	; "saveSetting"
	3	[502]	LOADK    	3 -3	; "ges_double_tap_interval"
	4	[502]	GETTABLE 	4 0 -4	; "value"
	5	[502]	MUL      	4 4 -5	; - 1000
	6	[502]	CALL     	1 4 1
	7	[503]	GETUPVAL 	1 0	; GestureDetector
	8	[503]	SELF     	1 1 -6	; "setNewInterval"
	9	[503]	LOADK    	3 -3	; "ges_double_tap_interval"
	10	[503]	GETTABLE 	4 0 -4	; "value"
	11	[503]	MUL      	4 4 -5	; - 1000
	12	[503]	CALL     	1 4 1
	13	[504]	RETURN   	0 1

function <./frontend/apps/reader/modules/readergesture.lua:511,534> (50 instructions, 200 bytes at 0x7fad94410880)
0 params, 8 slots, 4 upvalues, 3 locals, 28 constants, 1 function
	1	[512]	GETGLOBAL	0 -1	; require
	2	[512]	LOADK    	1 -2	; "ui/widget/spinwidget"
	3	[512]	CALL     	0 2 2
	4	[513]	GETGLOBAL	1 -1	; require
	5	[513]	LOADK    	2 -3	; "device/gesturedetector"
	6	[513]	CALL     	1 2 2
	7	[514]	SELF     	2 0 -4	; "new"
	8	[514]	NEWTABLE 	4 0 11
	9	[515]	GETUPVAL 	5 0	; T
	10	[515]	GETUPVAL 	6 1	; _
	11	[518]	LOADK    	7 -6	; "Set two finger tap duration in milliseconds.\nThe duration value can range from 100 (0.1 seconds) to 2000 (2 seconds).\nDefault value: %1"
	12	[515]	CALL     	6 2 2
	13	[518]	GETTABLE 	7 1 -7	; "TWO_FINGER_TAP_DURATION"
	14	[518]	DIV      	7 7 -8	; - 1000
	15	[515]	CALL     	5 3 2
	16	[518]	SETTABLE 	4 -5 5	; "text" -
	17	[519]	GETUPVAL 	5 2	; Screen
	18	[519]	SELF     	5 5 -10	; "getWidth"
	19	[519]	CALL     	5 2 2
	20	[519]	MUL      	5 5 -11	; - 0.6
	21	[519]	SETTABLE 	4 -9 5	; "width" -
	22	[520]	SELF     	5 1 -13	; "getInterval"
	23	[520]	LOADK    	7 -14	; "ges_two_finger_tap_duration"
	24	[520]	CALL     	5 3 2
	25	[520]	DIV      	5 5 -8	; - 1000
	26	[520]	SETTABLE 	4 -12 5	; "value" -
	27	[521]	SETTABLE 	4 -15 -16	; "value_min" 100
	28	[522]	SETTABLE 	4 -17 -18	; "value_max" 2000
	29	[523]	SETTABLE 	4 -19 -16	; "value_step" 100
	30	[524]	SETTABLE 	4 -20 -21	; "value_hold_step" 500
	31	[525]	GETUPVAL 	5 1	; _
	32	[525]	LOADK    	6 -23	; "Set duration"
	33	[525]	CALL     	5 2 2
	34	[525]	SETTABLE 	4 -22 5	; "ok_text" -
	35	[526]	GETUPVAL 	5 1	; _
	36	[526]	LOADK    	6 -25	; "Two finger tap duration"
	37	[526]	CALL     	5 2 2
	38	[526]	SETTABLE 	4 -24 5	; "title_text" -
	39	[527]	GETTABLE 	5 1 -7	; "TWO_FINGER_TAP_DURATION"
	40	[527]	DIV      	5 5 -8	; - 1000
	41	[527]	SETTABLE 	4 -26 5	; "default_value" -
	42	[531]	CLOSURE  	5 0	; 0x7fad94410cf0
	43	[531]	MOVE     	0 1
	44	[531]	SETTABLE 	4 -27 5	; "callback" -
	45	[514]	CALL     	2 3 2
	46	[533]	GETUPVAL 	3 3	; UIManager
	47	[533]	SELF     	3 3 -28	; "show"
	48	[533]	MOVE     	5 2
	49	[533]	CALL     	3 3 1
	50	[534]	RETURN   	0 1

function <./frontend/apps/reader/modules/readergesture.lua:528,531> (13 instructions, 52 bytes at 0x7fad94410cf0)
1 param, 5 slots, 1 upvalue, 1 local, 6 constants, 0 functions
	1	[529]	GETGLOBAL	1 -1	; G_reader_settings
	2	[529]	SELF     	1 1 -2	; "saveSetting"
	3	[529]	LOADK    	3 -3	; "ges_two_finger_tap_duration"
	4	[529]	GETTABLE 	4 0 -4	; "value"
	5	[529]	MUL      	4 4 -5	; - 1000
	6	[529]	CALL     	1 4 1
	7	[530]	GETUPVAL 	1 0	; GestureDetector
	8	[530]	SELF     	1 1 -6	; "setNewInterval"
	9	[530]	LOADK    	3 -3	; "ges_two_finger_tap_duration"
	10	[530]	GETTABLE 	4 0 -4	; "value"
	11	[530]	MUL      	4 4 -5	; - 1000
	12	[530]	CALL     	1 4 1
	13	[531]	RETURN   	0 1

function <./frontend/apps/reader/modules/readergesture.lua:538,561> (50 instructions, 200 bytes at 0x7fad94411440)
0 params, 8 slots, 4 upvalues, 3 locals, 28 constants, 1 function
	1	[539]	GETGLOBAL	0 -1	; require
	2	[539]	LOADK    	1 -2	; "ui/widget/spinwidget"
	3	[539]	CALL     	0 2 2
	4	[540]	GETGLOBAL	1 -1	; require
	5	[540]	LOADK    	2 -3	; "device/gesturedetector"
	6	[540]	CALL     	1 2 2
	7	[541]	SELF     	2 0 -4	; "new"
	8	[541]	NEWTABLE 	4 0 11
	9	[542]	GETUPVAL 	5 0	; T
	10	[542]	GETUPVAL 	6 1	; _
	11	[545]	LOADK    	7 -6	; "Set hold interval in milliseconds.\nThe interval value can range from 100 (0.1 seconds) to 2000 (2 seconds).\nDefault value: %1"
	12	[542]	CALL     	6 2 2
	13	[545]	GETTABLE 	7 1 -7	; "HOLD_INTERVAL"
	14	[545]	DIV      	7 7 -8	; - 1000
	15	[542]	CALL     	5 3 2
	16	[545]	SETTABLE 	4 -5 5	; "text" -
	17	[546]	GETUPVAL 	5 2	; Screen
	18	[546]	SELF     	5 5 -10	; "getWidth"
	19	[546]	CALL     	5 2 2
	20	[546]	MUL      	5 5 -11	; - 0.6
	21	[546]	SETTABLE 	4 -9 5	; "width" -
	22	[547]	SELF     	5 1 -13	; "getInterval"
	23	[547]	LOADK    	7 -14	; "ges_hold_interval"
	24	[547]	CALL     	5 3 2
	25	[547]	DIV      	5 5 -8	; - 1000
	26	[547]	SETTABLE 	4 -12 5	; "value" -
	27	[548]	SETTABLE 	4 -15 -16	; "value_min" 100
	28	[549]	SETTABLE 	4 -17 -18	; "value_max" 2000
	29	[550]	SETTABLE 	4 -19 -16	; "value_step" 100
	30	[551]	SETTABLE 	4 -20 -21	; "value_hold_step" 500
	31	[552]	GETUPVAL 	5 1	; _
	32	[552]	LOADK    	6 -23	; "Set interval"
	33	[552]	CALL     	5 2 2
	34	[552]	SETTABLE 	4 -22 5	; "ok_text" -
	35	[553]	GETUPVAL 	5 1	; _
	36	[553]	LOADK    	6 -25	; "Hold interval"
	37	[553]	CALL     	5 2 2
	38	[553]	SETTABLE 	4 -24 5	; "title_text" -
	39	[554]	GETTABLE 	5 1 -7	; "HOLD_INTERVAL"
	40	[554]	DIV      	5 5 -8	; - 1000
	41	[554]	SETTABLE 	4 -26 5	; "default_value" -
	42	[558]	CLOSURE  	5 0	; 0x7fad94411830
	43	[558]	MOVE     	0 1
	44	[558]	SETTABLE 	4 -27 5	; "callback" -
	45	[541]	CALL     	2 3 2
	46	[560]	GETUPVAL 	3 3	; UIManager
	47	[560]	SELF     	3 3 -28	; "show"
	48	[560]	MOVE     	5 2
	49	[560]	CALL     	3 3 1
	50	[561]	RETURN   	0 1

function <./frontend/apps/reader/modules/readergesture.lua:555,558> (13 instructions, 52 bytes at 0x7fad94411830)
1 param, 5 slots, 1 upvalue, 1 local, 6 constants, 0 functions
	1	[556]	GETGLOBAL	1 -1	; G_reader_settings
	2	[556]	SELF     	1 1 -2	; "saveSetting"
	3	[556]	LOADK    	3 -3	; "ges_hold_interval"
	4	[556]	GETTABLE 	4 0 -4	; "value"
	5	[556]	MUL      	4 4 -5	; - 1000
	6	[556]	CALL     	1 4 1
	7	[557]	GETUPVAL 	1 0	; GestureDetector
	8	[557]	SELF     	1 1 -6	; "setNewInterval"
	9	[557]	LOADK    	3 -3	; "ges_hold_interval"
	10	[557]	GETTABLE 	4 0 -4	; "value"
	11	[557]	MUL      	4 4 -5	; - 1000
	12	[557]	CALL     	1 4 1
	13	[558]	RETURN   	0 1

function <./frontend/apps/reader/modules/readergesture.lua:565,588> (50 instructions, 200 bytes at 0x7fad94411ed0)
0 params, 8 slots, 4 upvalues, 3 locals, 28 constants, 1 function
	1	[566]	GETGLOBAL	0 -1	; require
	2	[566]	LOADK    	1 -2	; "ui/widget/spinwidget"
	3	[566]	CALL     	0 2 2
	4	[567]	GETGLOBAL	1 -1	; require
	5	[567]	LOADK    	2 -3	; "device/gesturedetector"
	6	[567]	CALL     	1 2 2
	7	[568]	SELF     	2 0 -4	; "new"
	8	[568]	NEWTABLE 	4 0 11
	9	[569]	GETUPVAL 	5 0	; T
	10	[569]	GETUPVAL 	6 1	; _
	11	[572]	LOADK    	7 -6	; "Set pan delay interval in milliseconds.\nThe interval value can range from 100 (0.1 seconds) to 2000 (2 seconds).\nDefault value: %1"
	12	[569]	CALL     	6 2 2
	13	[572]	GETTABLE 	7 1 -7	; "PAN_DELAYED_INTERVAL"
	14	[572]	DIV      	7 7 -8	; - 1000
	15	[569]	CALL     	5 3 2
	16	[572]	SETTABLE 	4 -5 5	; "text" -
	17	[573]	GETUPVAL 	5 2	; Screen
	18	[573]	SELF     	5 5 -10	; "getWidth"
	19	[573]	CALL     	5 2 2
	20	[573]	MUL      	5 5 -11	; - 0.6
	21	[573]	SETTABLE 	4 -9 5	; "width" -
	22	[574]	SELF     	5 1 -13	; "getInterval"
	23	[574]	LOADK    	7 -14	; "ges_pan_delayed_interval"
	24	[574]	CALL     	5 3 2
	25	[574]	DIV      	5 5 -8	; - 1000
	26	[574]	SETTABLE 	4 -12 5	; "value" -
	27	[575]	SETTABLE 	4 -15 -16	; "value_min" 100
	28	[576]	SETTABLE 	4 -17 -18	; "value_max" 2000
	29	[577]	SETTABLE 	4 -19 -16	; "value_step" 100
	30	[578]	SETTABLE 	4 -20 -21	; "value_hold_step" 500
	31	[579]	GETUPVAL 	5 1	; _
	32	[579]	LOADK    	6 -23	; "Set interval"
	33	[579]	CALL     	5 2 2
	34	[579]	SETTABLE 	4 -22 5	; "ok_text" -
	35	[580]	GETUPVAL 	5 1	; _
	36	[580]	LOADK    	6 -25	; "Pan delay interval"
	37	[580]	CALL     	5 2 2
	38	[580]	SETTABLE 	4 -24 5	; "title_text" -
	39	[581]	GETTABLE 	5 1 -7	; "PAN_DELAYED_INTERVAL"
	40	[581]	DIV      	5 5 -8	; - 1000
	41	[581]	SETTABLE 	4 -26 5	; "default_value" -
	42	[585]	CLOSURE  	5 0	; 0x7fad94412020
	43	[585]	MOVE     	0 1
	44	[585]	SETTABLE 	4 -27 5	; "callback" -
	45	[568]	CALL     	2 3 2
	46	[587]	GETUPVAL 	3 3	; UIManager
	47	[587]	SELF     	3 3 -28	; "show"
	48	[587]	MOVE     	5 2
	49	[587]	CALL     	3 3 1
	50	[588]	RETURN   	0 1

function <./frontend/apps/reader/modules/readergesture.lua:582,585> (13 instructions, 52 bytes at 0x7fad94412020)
1 param, 5 slots, 1 upvalue, 1 local, 6 constants, 0 functions
	1	[583]	GETGLOBAL	1 -1	; G_reader_settings
	2	[583]	SELF     	1 1 -2	; "saveSetting"
	3	[583]	LOADK    	3 -3	; "ges_pan_delayed_interval"
	4	[583]	GETTABLE 	4 0 -4	; "value"
	5	[583]	MUL      	4 4 -5	; - 1000
	6	[583]	CALL     	1 4 1
	7	[584]	GETUPVAL 	1 0	; GestureDetector
	8	[584]	SELF     	1 1 -6	; "setNewInterval"
	9	[584]	LOADK    	3 -3	; "ges_pan_delayed_interval"
	10	[584]	GETTABLE 	4 0 -4	; "value"
	11	[584]	MUL      	4 4 -5	; - 1000
	12	[584]	CALL     	1 4 1
	13	[585]	RETURN   	0 1

function <./frontend/apps/reader/modules/readergesture.lua:592,615> (50 instructions, 200 bytes at 0x7fad94412a30)
0 params, 8 slots, 4 upvalues, 3 locals, 28 constants, 1 function
	1	[593]	GETGLOBAL	0 -1	; require
	2	[593]	LOADK    	1 -2	; "ui/widget/spinwidget"
	3	[593]	CALL     	0 2 2
	4	[594]	GETGLOBAL	1 -1	; require
	5	[594]	LOADK    	2 -3	; "device/gesturedetector"
	6	[594]	CALL     	1 2 2
	7	[595]	SELF     	2 0 -4	; "new"
	8	[595]	NEWTABLE 	4 0 11
	9	[596]	GETUPVAL 	5 0	; T
	10	[596]	GETUPVAL 	6 1	; _
	11	[599]	LOADK    	7 -6	; "Set swipe interval in milliseconds.\nThe interval value can range from 100 (0.1 seconds) to 2000 (2 seconds).\nDefault value: %1"
	12	[596]	CALL     	6 2 2
	13	[599]	GETTABLE 	7 1 -7	; "SWIPE_INTERVAL"
	14	[599]	DIV      	7 7 -8	; - 1000
	15	[596]	CALL     	5 3 2
	16	[599]	SETTABLE 	4 -5 5	; "text" -
	17	[600]	GETUPVAL 	5 2	; Screen
	18	[600]	SELF     	5 5 -10	; "getWidth"
	19	[600]	CALL     	5 2 2
	20	[600]	MUL      	5 5 -11	; - 0.6
	21	[600]	SETTABLE 	4 -9 5	; "width" -
	22	[601]	SELF     	5 1 -13	; "getInterval"
	23	[601]	LOADK    	7 -14	; "ges_swipe_interval"
	24	[601]	CALL     	5 3 2
	25	[601]	DIV      	5 5 -8	; - 1000
	26	[601]	SETTABLE 	4 -12 5	; "value" -
	27	[602]	SETTABLE 	4 -15 -16	; "value_min" 100
	28	[603]	SETTABLE 	4 -17 -18	; "value_max" 2000
	29	[604]	SETTABLE 	4 -19 -16	; "value_step" 100
	30	[605]	SETTABLE 	4 -20 -21	; "value_hold_step" 500
	31	[606]	GETUPVAL 	5 1	; _
	32	[606]	LOADK    	6 -23	; "Set interval"
	33	[606]	CALL     	5 2 2
	34	[606]	SETTABLE 	4 -22 5	; "ok_text" -
	35	[607]	GETUPVAL 	5 1	; _
	36	[607]	LOADK    	6 -25	; "Swipe interval"
	37	[607]	CALL     	5 2 2
	38	[607]	SETTABLE 	4 -24 5	; "title_text" -
	39	[608]	GETTABLE 	5 1 -7	; "SWIPE_INTERVAL"
	40	[608]	DIV      	5 5 -8	; - 1000
	41	[608]	SETTABLE 	4 -26 5	; "default_value" -
	42	[612]	CLOSURE  	5 0	; 0x7fad94412f60
	43	[612]	MOVE     	0 1
	44	[612]	SETTABLE 	4 -27 5	; "callback" -
	45	[595]	CALL     	2 3 2
	46	[614]	GETUPVAL 	3 3	; UIManager
	47	[614]	SELF     	3 3 -28	; "show"
	48	[614]	MOVE     	5 2
	49	[614]	CALL     	3 3 1
	50	[615]	RETURN   	0 1

function <./frontend/apps/reader/modules/readergesture.lua:609,612> (13 instructions, 52 bytes at 0x7fad94412f60)
1 param, 5 slots, 1 upvalue, 1 local, 6 constants, 0 functions
	1	[610]	GETGLOBAL	1 -1	; G_reader_settings
	2	[610]	SELF     	1 1 -2	; "saveSetting"
	3	[610]	LOADK    	3 -3	; "ges_swipe_interval"
	4	[610]	GETTABLE 	4 0 -4	; "value"
	5	[610]	MUL      	4 4 -5	; - 1000
	6	[610]	CALL     	1 4 1
	7	[611]	GETUPVAL 	1 0	; GestureDetector
	8	[611]	SELF     	1 1 -6	; "setNewInterval"
	9	[611]	LOADK    	3 -3	; "ges_swipe_interval"
	10	[611]	GETTABLE 	4 0 -4	; "value"
	11	[611]	MUL      	4 4 -5	; - 1000
	12	[611]	CALL     	1 4 1
	13	[612]	RETURN   	0 1

function <./frontend/apps/reader/modules/readergesture.lua:620,623> (22 instructions, 88 bytes at 0x7fad944134f0)
2 params, 7 slots, 4 upvalues, 3 locals, 3 constants, 0 functions
	1	[621]	GETUPVAL 	2 0	; gesture_manager
	2	[621]	GETTABLE 	2 2 0
	3	[621]	EQ       	1 2 -1	; - "nothing"
	4	[621]	JMP      	6	; to 11
	5	[621]	GETUPVAL 	2 1	; action_strings
	6	[621]	GETUPVAL 	3 0	; gesture_manager
	7	[621]	GETTABLE 	3 3 0
	8	[621]	GETTABLE 	2 2 3
	9	[621]	TEST     	2 0 1
	10	[621]	JMP      	3	; to 14
	11	[621]	GETUPVAL 	2 2	; _
	12	[621]	LOADK    	3 -2	; "Available"
	13	[621]	CALL     	2 2 2
	14	[622]	GETUPVAL 	3 3	; T
	15	[622]	GETUPVAL 	4 2	; _
	16	[622]	LOADK    	5 -3	; "%1   (%2)"
	17	[622]	CALL     	4 2 2
	18	[622]	MOVE     	5 1
	19	[622]	MOVE     	6 2
	20	[622]	TAILCALL 	3 4 0
	21	[622]	RETURN   	3 0
	22	[623]	RETURN   	0 1

function <./frontend/apps/reader/modules/readergesture.lua:630,630> (8 instructions, 32 bytes at 0x7fad94413a90)
0 params, 4 slots, 2 upvalues, 0 locals, 2 constants, 0 functions
	1	[630]	GETUPVAL 	0 0	; actionTextFunc
	2	[630]	LOADK    	1 -1	; "two_finger_tap_top_left_corner"
	3	[630]	GETUPVAL 	2 1	; _
	4	[630]	LOADK    	3 -2	; "Top left"
	5	[630]	CALL     	2 2 0
	6	[630]	TAILCALL 	0 0 0
	7	[630]	RETURN   	0 0
	8	[630]	RETURN   	0 1

function <./frontend/apps/reader/modules/readergesture.lua:634,634> (8 instructions, 32 bytes at 0x7fad94413e20)
0 params, 4 slots, 2 upvalues, 0 locals, 2 constants, 0 functions
	1	[634]	GETUPVAL 	0 0	; actionTextFunc
	2	[634]	LOADK    	1 -1	; "two_finger_tap_top_right_corner"
	3	[634]	GETUPVAL 	2 1	; _
	4	[634]	LOADK    	3 -2	; "Top right"
	5	[634]	CALL     	2 2 0
	6	[634]	TAILCALL 	0 0 0
	7	[634]	RETURN   	0 0
	8	[634]	RETURN   	0 1

function <./frontend/apps/reader/modules/readergesture.lua:638,638> (8 instructions, 32 bytes at 0x7fad944140b0)
0 params, 4 slots, 2 upvalues, 0 locals, 2 constants, 0 functions
	1	[638]	GETUPVAL 	0 0	; actionTextFunc
	2	[638]	LOADK    	1 -1	; "two_finger_tap_bottom_left_corner"
	3	[638]	GETUPVAL 	2 1	; _
	4	[638]	LOADK    	3 -2	; "Bottom left"
	5	[638]	CALL     	2 2 0
	6	[638]	TAILCALL 	0 0 0
	7	[638]	RETURN   	0 0
	8	[638]	RETURN   	0 1

function <./frontend/apps/reader/modules/readergesture.lua:642,642> (8 instructions, 32 bytes at 0x7fad94414330)
0 params, 4 slots, 2 upvalues, 0 locals, 2 constants, 0 functions
	1	[642]	GETUPVAL 	0 0	; actionTextFunc
	2	[642]	LOADK    	1 -1	; "two_finger_tap_bottom_right_corner"
	3	[642]	GETUPVAL 	2 1	; _
	4	[642]	LOADK    	3 -2	; "Bottom right"
	5	[642]	CALL     	2 2 0
	6	[642]	TAILCALL 	0 0 0
	7	[642]	RETURN   	0 0
	8	[642]	RETURN   	0 1

function <./frontend/apps/reader/modules/readergesture.lua:652,652> (6 instructions, 24 bytes at 0x7fad94414620)
0 params, 3 slots, 1 upvalue, 0 locals, 2 constants, 0 functions
	1	[652]	GETUPVAL 	0 0	; twoFingerSwipeTextFunc
	2	[652]	LOADK    	1 -1	; "two_finger_swipe_east"
	3	[652]	LOADK    	2 -2	; "\226\135\146"
	4	[652]	TAILCALL 	0 3 0
	5	[652]	RETURN   	0 0
	6	[652]	RETURN   	0 1

function <./frontend/apps/reader/modules/readergesture.lua:656,656> (6 instructions, 24 bytes at 0x7fad94414a20)
0 params, 3 slots, 1 upvalue, 0 locals, 2 constants, 0 functions
	1	[656]	GETUPVAL 	0 0	; twoFingerSwipeTextFunc
	2	[656]	LOADK    	1 -1	; "two_finger_swipe_west"
	3	[656]	LOADK    	2 -2	; "\226\135\144"
	4	[656]	TAILCALL 	0 3 0
	5	[656]	RETURN   	0 0
	6	[656]	RETURN   	0 1

function <./frontend/apps/reader/modules/readergesture.lua:660,660> (6 instructions, 24 bytes at 0x7fad94414c60)
0 params, 3 slots, 1 upvalue, 0 locals, 2 constants, 0 functions
	1	[660]	GETUPVAL 	0 0	; twoFingerSwipeTextFunc
	2	[660]	LOADK    	1 -1	; "two_finger_swipe_south"
	3	[660]	LOADK    	2 -2	; "\226\135\147"
	4	[660]	TAILCALL 	0 3 0
	5	[660]	RETURN   	0 0
	6	[660]	RETURN   	0 1

function <./frontend/apps/reader/modules/readergesture.lua:664,664> (6 instructions, 24 bytes at 0x7fad94414f20)
0 params, 3 slots, 1 upvalue, 0 locals, 2 constants, 0 functions
	1	[664]	GETUPVAL 	0 0	; twoFingerSwipeTextFunc
	2	[664]	LOADK    	1 -1	; "two_finger_swipe_north"
	3	[664]	LOADK    	2 -2	; "\226\135\145"
	4	[664]	TAILCALL 	0 3 0
	5	[664]	RETURN   	0 0
	6	[664]	RETURN   	0 1

function <./frontend/apps/reader/modules/readergesture.lua:668,668> (6 instructions, 24 bytes at 0x7fad944151b0)
0 params, 3 slots, 1 upvalue, 0 locals, 2 constants, 0 functions
	1	[668]	GETUPVAL 	0 0	; twoFingerSwipeTextFunc
	2	[668]	LOADK    	1 -1	; "two_finger_swipe_northeast"
	3	[668]	LOADK    	2 -2	; "\226\135\151"
	4	[668]	TAILCALL 	0 3 0
	5	[668]	RETURN   	0 0
	6	[668]	RETURN   	0 1

function <./frontend/apps/reader/modules/readergesture.lua:672,672> (6 instructions, 24 bytes at 0x7fad94415460)
0 params, 3 slots, 1 upvalue, 0 locals, 2 constants, 0 functions
	1	[672]	GETUPVAL 	0 0	; twoFingerSwipeTextFunc
	2	[672]	LOADK    	1 -1	; "two_finger_swipe_northwest"
	3	[672]	LOADK    	2 -2	; "\226\135\150"
	4	[672]	TAILCALL 	0 3 0
	5	[672]	RETURN   	0 0
	6	[672]	RETURN   	0 1

function <./frontend/apps/reader/modules/readergesture.lua:676,676> (6 instructions, 24 bytes at 0x7fad94415700)
0 params, 3 slots, 1 upvalue, 0 locals, 2 constants, 0 functions
	1	[676]	GETUPVAL 	0 0	; twoFingerSwipeTextFunc
	2	[676]	LOADK    	1 -1	; "two_finger_swipe_southeast"
	3	[676]	LOADK    	2 -2	; "\226\135\152"
	4	[676]	TAILCALL 	0 3 0
	5	[676]	RETURN   	0 0
	6	[676]	RETURN   	0 1

function <./frontend/apps/reader/modules/readergesture.lua:680,680> (6 instructions, 24 bytes at 0x7fad944159a0)
0 params, 3 slots, 1 upvalue, 0 locals, 2 constants, 0 functions
	1	[680]	GETUPVAL 	0 0	; twoFingerSwipeTextFunc
	2	[680]	LOADK    	1 -1	; "two_finger_swipe_southwest"
	3	[680]	LOADK    	2 -2	; "\226\135\153"
	4	[680]	TAILCALL 	0 3 0
	5	[680]	RETURN   	0 0
	6	[680]	RETURN   	0 1

function <./frontend/apps/reader/modules/readergesture.lua:689,689> (8 instructions, 32 bytes at 0x7fad94415c70)
0 params, 4 slots, 2 upvalues, 0 locals, 2 constants, 0 functions
	1	[689]	GETUPVAL 	0 0	; actionTextFunc
	2	[689]	LOADK    	1 -1	; "spread_gesture"
	3	[689]	GETUPVAL 	2 1	; _
	4	[689]	LOADK    	3 -2	; "Spread"
	5	[689]	CALL     	2 2 0
	6	[689]	TAILCALL 	0 0 0
	7	[689]	RETURN   	0 0
	8	[689]	RETURN   	0 1

function <./frontend/apps/reader/modules/readergesture.lua:693,693> (8 instructions, 32 bytes at 0x7fad94415f20)
0 params, 4 slots, 2 upvalues, 0 locals, 2 constants, 0 functions
	1	[693]	GETUPVAL 	0 0	; actionTextFunc
	2	[693]	LOADK    	1 -1	; "pinch_gesture"
	3	[693]	GETUPVAL 	2 1	; _
	4	[693]	LOADK    	3 -2	; "Pinch"
	5	[693]	CALL     	2 2 0
	6	[693]	TAILCALL 	0 0 0
	7	[693]	RETURN   	0 0
	8	[693]	RETURN   	0 1

function <./frontend/apps/reader/modules/readergesture.lua:701,822> (508 instructions, 2032 bytes at 0x7fad944161c0)
3 params, 58 slots, 5 upvalues, 18 locals, 104 constants, 0 functions
	1	[702]	GETGLOBAL	3 -1	; G_reader_settings
	2	[702]	SELF     	3 3 -2	; "readSetting"
	3	[702]	GETTABLE 	5 0 -3	; "ges_mode"
	4	[702]	CALL     	3 3 2
	5	[703]	NEWTABLE 	4 34 0
	6	[703]	NEWTABLE 	5 2 0
	7	[704]	LOADK    	6 -4	; "nothing"
	8	[704]	LOADBOOL 	7 1 0
	9	[704]	SETLIST  	5 2 1	; 1
	10	[704]	NEWTABLE 	6 3 0
	11	[705]	LOADK    	7 -5	; "ignore"
	12	[705]	LOADBOOL 	8 1 0
	13	[705]	LOADBOOL 	9 1 0
	14	[705]	SETLIST  	6 3 1	; 1
	15	[705]	NEWTABLE 	7 2 0
	16	[706]	LOADK    	8 -6	; "page_jmp_back_10"
	17	[706]	GETTABLE 	9 0 -7	; "is_docless"
	18	[706]	NOT      	9 9
	19	[706]	SETLIST  	7 2 1	; 1
	20	[706]	NEWTABLE 	8 2 0
	21	[707]	LOADK    	9 -8	; "page_jmp_back_1"
	22	[707]	GETTABLE 	10 0 -7	; "is_docless"
	23	[707]	NOT      	10 10
	24	[707]	SETLIST  	8 2 1	; 1
	25	[707]	NEWTABLE 	9 2 0
	26	[708]	LOADK    	10 -9	; "page_jmp_fwd_10"
	27	[708]	GETTABLE 	11 0 -7	; "is_docless"
	28	[708]	NOT      	11 11
	29	[708]	SETLIST  	9 2 1	; 1
	30	[708]	NEWTABLE 	10 2 0
	31	[709]	LOADK    	11 -10	; "page_jmp_fwd_1"
	32	[709]	GETTABLE 	12 0 -7	; "is_docless"
	33	[709]	NOT      	12 12
	34	[709]	SETLIST  	10 2 1	; 1
	35	[709]	NEWTABLE 	11 2 0
	36	[710]	LOADK    	12 -11	; "prev_chapter"
	37	[710]	GETTABLE 	13 0 -7	; "is_docless"
	38	[710]	NOT      	13 13
	39	[710]	SETLIST  	11 2 1	; 1
	40	[710]	NEWTABLE 	12 2 0
	41	[711]	LOADK    	13 -12	; "next_chapter"
	42	[711]	GETTABLE 	14 0 -7	; "is_docless"
	43	[711]	NOT      	14 14
	44	[711]	SETLIST  	12 2 1	; 1
	45	[711]	NEWTABLE 	13 2 0
	46	[712]	LOADK    	14 -13	; "first_page"
	47	[712]	GETTABLE 	15 0 -7	; "is_docless"
	48	[712]	NOT      	15 15
	49	[712]	SETLIST  	13 2 1	; 1
	50	[712]	NEWTABLE 	14 2 0
	51	[713]	LOADK    	15 -14	; "last_page"
	52	[713]	GETTABLE 	16 0 -7	; "is_docless"
	53	[713]	NOT      	16 16
	54	[713]	SETLIST  	14 2 1	; 1
	55	[713]	NEWTABLE 	15 2 0
	56	[714]	LOADK    	16 -15	; "prev_bookmark"
	57	[714]	GETTABLE 	17 0 -7	; "is_docless"
	58	[714]	NOT      	17 17
	59	[714]	SETLIST  	15 2 1	; 1
	60	[714]	NEWTABLE 	16 2 0
	61	[715]	LOADK    	17 -16	; "next_bookmark"
	62	[715]	GETTABLE 	18 0 -7	; "is_docless"
	63	[715]	NOT      	18 18
	64	[715]	SETLIST  	16 2 1	; 1
	65	[715]	NEWTABLE 	17 2 0
	66	[716]	LOADK    	18 -17	; "go_to"
	67	[716]	LOADBOOL 	19 1 0
	68	[716]	SETLIST  	17 2 1	; 1
	69	[716]	NEWTABLE 	18 2 0
	70	[717]	LOADK    	19 -18	; "skim"
	71	[717]	GETTABLE 	20 0 -7	; "is_docless"
	72	[717]	NOT      	20 20
	73	[717]	SETLIST  	18 2 1	; 1
	74	[717]	NEWTABLE 	19 2 0
	75	[718]	LOADK    	20 -19	; "back"
	76	[718]	LOADBOOL 	21 1 0
	77	[718]	SETLIST  	19 2 1	; 1
	78	[718]	NEWTABLE 	20 2 0
	79	[719]	LOADK    	21 -20	; "previous_location"
	80	[719]	GETTABLE 	22 0 -7	; "is_docless"
	81	[719]	NOT      	22 22
	82	[719]	SETLIST  	20 2 1	; 1
	83	[719]	NEWTABLE 	21 2 0
	84	[720]	LOADK    	22 -21	; "latest_bookmark"
	85	[720]	GETTABLE 	23 0 -7	; "is_docless"
	86	[720]	NOT      	23 23
	87	[720]	SETLIST  	21 2 1	; 1
	88	[720]	NEWTABLE 	22 2 0
	89	[721]	LOADK    	23 -22	; "follow_nearest_link"
	90	[721]	GETTABLE 	24 0 -7	; "is_docless"
	91	[721]	NOT      	24 24
	92	[721]	SETLIST  	22 2 1	; 1
	93	[721]	NEWTABLE 	23 2 0
	94	[722]	LOADK    	24 -23	; "follow_nearest_internal_link"
	95	[722]	GETTABLE 	25 0 -7	; "is_docless"
	96	[722]	NOT      	25 25
	97	[722]	SETLIST  	23 2 1	; 1
	98	[722]	NEWTABLE 	24 3 0
	99	[723]	LOADK    	25 -24	; "clear_location_history"
	100	[723]	GETTABLE 	26 0 -7	; "is_docless"
	101	[723]	NOT      	26 26
	102	[723]	LOADBOOL 	27 1 0
	103	[723]	SETLIST  	24 3 1	; 1
	104	[723]	NEWTABLE 	25 2 0
	105	[725]	LOADK    	26 -25	; "folder_up"
	106	[725]	GETTABLE 	27 0 -7	; "is_docless"
	107	[725]	SETLIST  	25 2 1	; 1
	108	[725]	NEWTABLE 	26 2 0
	109	[726]	LOADK    	27 -26	; "show_plus_menu"
	110	[726]	GETTABLE 	28 0 -7	; "is_docless"
	111	[726]	SETLIST  	26 2 1	; 1
	112	[726]	NEWTABLE 	27 3 0
	113	[727]	LOADK    	28 -27	; "folder_shortcuts"
	114	[727]	LOADBOOL 	29 1 0
	115	[727]	LOADBOOL 	30 1 0
	116	[727]	SETLIST  	27 3 1	; 1
	117	[727]	NEWTABLE 	28 2 0
	118	[729]	LOADK    	29 -28	; "toc"
	119	[729]	GETTABLE 	30 0 -7	; "is_docless"
	120	[729]	NOT      	30 30
	121	[729]	SETLIST  	28 2 1	; 1
	122	[729]	NEWTABLE 	29 2 0
	123	[730]	LOADK    	30 -29	; "bookmarks"
	124	[730]	GETTABLE 	31 0 -7	; "is_docless"
	125	[730]	NOT      	31 31
	126	[730]	SETLIST  	29 2 1	; 1
	127	[730]	NEWTABLE 	30 2 0
	128	[731]	LOADK    	31 -30	; "reading_progress"
	129	[731]	GETUPVAL 	32 0	; ReaderGesture
	130	[731]	GETTABLE 	32 32 -31	; "getReaderProgress"
	131	[731]	EQ       	0 32 -32	; - nil
	132	[731]	JMP      	1	; to 134
	133	[731]	LOADBOOL 	32 0 1
	134	[731]	LOADBOOL 	32 1 0
	135	[731]	SETLIST  	30 2 1	; 1
	136	[731]	NEWTABLE 	31 2 0
	137	[732]	LOADK    	32 -33	; "book_statistics"
	138	[732]	GETTABLE 	33 0 -7	; "is_docless"
	139	[732]	NOT      	33 33
	140	[732]	SETLIST  	31 2 1	; 1
	141	[732]	NEWTABLE 	32 2 0
	142	[734]	LOADK    	33 -34	; "book_status"
	143	[734]	GETTABLE 	34 0 -7	; "is_docless"
	144	[734]	NOT      	34 34
	145	[734]	SETLIST  	32 2 1	; 1
	146	[734]	NEWTABLE 	33 2 0
	147	[735]	LOADK    	34 -35	; "book_info"
	148	[735]	GETTABLE 	35 0 -7	; "is_docless"
	149	[735]	NOT      	35 35
	150	[735]	SETLIST  	33 2 1	; 1
	151	[735]	NEWTABLE 	34 2 0
	152	[736]	LOADK    	35 -36	; "book_description"
	153	[736]	GETTABLE 	36 0 -7	; "is_docless"
	154	[736]	NOT      	36 36
	155	[736]	SETLIST  	34 2 1	; 1
	156	[736]	NEWTABLE 	35 3 0
	157	[737]	LOADK    	36 -37	; "book_cover"
	158	[737]	GETTABLE 	37 0 -7	; "is_docless"
	159	[737]	NOT      	37 37
	160	[737]	LOADBOOL 	38 1 0
	161	[737]	SETLIST  	35 3 1	; 1
	162	[737]	NEWTABLE 	36 2 0
	163	[739]	LOADK    	37 -38	; "history"
	164	[739]	LOADBOOL 	38 1 0
	165	[739]	SETLIST  	36 2 1	; 1
	166	[739]	NEWTABLE 	37 3 0
	167	[740]	LOADK    	38 -39	; "open_previous_document"
	168	[740]	LOADBOOL 	39 1 0
	169	[740]	LOADBOOL 	40 1 0
	170	[740]	SETLIST  	37 3 1	; 1
	171	[740]	NEWTABLE 	38 2 0
	172	[741]	LOADK    	39 -40	; "favorites"
	173	[741]	LOADBOOL 	40 1 0
	174	[741]	SETLIST  	38 2 1	; 1
	175	[741]	NEWTABLE 	39 3 0
	176	[742]	LOADK    	40 -41	; "filemanager"
	177	[742]	GETTABLE 	41 0 -7	; "is_docless"
	178	[742]	NOT      	41 41
	179	[742]	LOADBOOL 	42 1 0
	180	[742]	SETLIST  	39 3 1	; 1
	181	[742]	NEWTABLE 	40 3 0
	182	[743]	LOADK    	41 -42	; "stats_calendar_view"
	183	[743]	LOADBOOL 	42 1 0
	184	[743]	LOADBOOL 	43 1 0
	185	[743]	SETLIST  	40 3 1	; 1
	186	[743]	NEWTABLE 	41 2 0
	187	[745]	LOADK    	42 -43	; "dictionary_lookup"
	188	[745]	LOADBOOL 	43 1 0
	189	[745]	SETLIST  	41 2 1	; 1
	190	[745]	NEWTABLE 	42 3 0
	191	[746]	LOADK    	43 -44	; "wikipedia_lookup"
	192	[746]	LOADBOOL 	44 1 0
	193	[746]	LOADBOOL 	45 1 0
	194	[746]	SETLIST  	42 3 1	; 1
	195	[746]	NEWTABLE 	43 2 0
	196	[747]	LOADK    	44 -45	; "fulltext_search"
	197	[747]	GETTABLE 	45 0 -7	; "is_docless"
	198	[747]	NOT      	45 45
	199	[747]	SETLIST  	43 2 1	; 1
	200	[747]	NEWTABLE 	44 3 0
	201	[748]	LOADK    	45 -46	; "file_search"
	202	[748]	LOADBOOL 	46 1 0
	203	[748]	LOADBOOL 	47 1 0
	204	[748]	SETLIST  	44 3 1	; 1
	205	[748]	NEWTABLE 	45 2 0
	206	[750]	LOADK    	46 -47	; "full_refresh"
	207	[750]	LOADBOOL 	47 1 0
	208	[750]	SETLIST  	45 2 1	; 1
	209	[750]	NEWTABLE 	46 2 0
	210	[751]	LOADK    	47 -48	; "night_mode"
	211	[751]	LOADBOOL 	48 1 0
	212	[751]	SETLIST  	46 2 1	; 1
	213	[751]	NEWTABLE 	47 2 0
	214	[752]	LOADK    	48 -49	; "suspend"
	215	[752]	LOADBOOL 	49 1 0
	216	[752]	SETLIST  	47 2 1	; 1
	217	[752]	NEWTABLE 	48 2 0
	218	[753]	LOADK    	49 -50	; "exit"
	219	[753]	LOADBOOL 	50 1 0
	220	[753]	SETLIST  	48 2 1	; 1
	221	[753]	NEWTABLE 	49 1 0
	222	[754]	LOADK    	50 -51	; "restart"
	223	[754]	GETUPVAL 	51 1	; Device
	224	[754]	SELF     	51 51 -52	; "canRestart"
	225	[754]	CALL     	51 2 0
	226	[754]	SETLIST  	49 0 1	; 1
	227	[754]	NEWTABLE 	50 1 0
	228	[755]	LOADK    	51 -53	; "reboot"
	229	[755]	GETUPVAL 	52 1	; Device
	230	[755]	SELF     	52 52 -54	; "canReboot"
	231	[755]	CALL     	52 2 0
	232	[755]	SETLIST  	50 0 1	; 1
	233	[755]	NEWTABLE 	51 1 0
	234	[756]	LOADK    	52 -55	; "poweroff"
	235	[756]	GETUPVAL 	53 1	; Device
	236	[756]	SELF     	53 53 -56	; "canPowerOff"
	237	[756]	CALL     	53 2 0
	238	[756]	SETLIST  	51 0 1	; 1
	239	[756]	NEWTABLE 	52 2 0
	240	[758]	LOADK    	53 -57	; "show_menu"
	241	[758]	LOADBOOL 	54 1 0
	242	[758]	SETLIST  	52 2 1	; 1
	243	[758]	NEWTABLE 	53 3 0
	244	[759]	LOADK    	54 -58	; "show_config_menu"
	245	[759]	GETTABLE 	55 0 -7	; "is_docless"
	246	[759]	NOT      	55 55
	247	[759]	LOADBOOL 	56 1 0
	248	[759]	SETLIST  	53 3 1	; 1
	249	[759]	NEWTABLE 	54 1 0
	250	[760]	LOADK    	55 -59	; "show_frontlight_dialog"
	251	[760]	GETUPVAL 	56 1	; Device
	252	[760]	SELF     	56 56 -60	; "hasFrontlight"
	253	[760]	CALL     	56 2 0
	254	[760]	SETLIST  	54 0 1	; 1
	255	[760]	SETLIST  	4 50 1	; 1
	256	[760]	NEWTABLE 	5 1 0
	257	[761]	LOADK    	6 -61	; "toggle_frontlight"
	258	[761]	GETUPVAL 	7 1	; Device
	259	[761]	SELF     	7 7 -60	; "hasFrontlight"
	260	[761]	CALL     	7 2 0
	261	[761]	SETLIST  	5 0 1	; 1
	262	[761]	NEWTABLE 	6 1 0
	263	[762]	LOADK    	7 -62	; "increase_frontlight"
	264	[762]	GETUPVAL 	8 1	; Device
	265	[762]	SELF     	8 8 -60	; "hasFrontlight"
	266	[762]	CALL     	8 2 0
	267	[762]	SETLIST  	6 0 1	; 1
	268	[762]	NEWTABLE 	7 3 0
	269	[763]	LOADK    	8 -63	; "decrease_frontlight"
	270	[763]	GETUPVAL 	9 1	; Device
	271	[763]	SELF     	9 9 -60	; "hasFrontlight"
	272	[763]	CALL     	9 2 2
	273	[763]	LOADBOOL 	10 1 0
	274	[763]	SETLIST  	7 3 1	; 1
	275	[763]	NEWTABLE 	8 1 0
	276	[764]	LOADK    	9 -64	; "increase_frontlight_warmth"
	277	[764]	GETUPVAL 	10 1	; Device
	278	[764]	SELF     	10 10 -65	; "hasNaturalLight"
	279	[764]	CALL     	10 2 0
	280	[764]	SETLIST  	8 0 1	; 1
	281	[764]	NEWTABLE 	9 3 0
	282	[765]	LOADK    	10 -66	; "decrease_frontlight_warmth"
	283	[765]	GETUPVAL 	11 1	; Device
	284	[765]	SELF     	11 11 -65	; "hasNaturalLight"
	285	[765]	CALL     	11 2 2
	286	[765]	LOADBOOL 	12 1 0
	287	[765]	SETLIST  	9 3 1	; 1
	288	[765]	NEWTABLE 	10 2 0
	289	[767]	LOADK    	11 -67	; "toggle_hold_corners"
	290	[767]	LOADBOOL 	12 1 0
	291	[767]	SETLIST  	10 2 1	; 1
	292	[767]	NEWTABLE 	11 1 0
	293	[768]	LOADK    	12 -68	; "toggle_gsensor"
	294	[768]	GETUPVAL 	13 1	; Device
	295	[768]	SELF     	13 13 -69	; "canToggleGSensor"
	296	[768]	CALL     	13 2 0
	297	[768]	SETLIST  	11 0 1	; 1
	298	[768]	NEWTABLE 	12 3 0
	299	[769]	LOADK    	13 -70	; "toggle_rotation"
	300	[769]	GETTABLE 	14 0 -7	; "is_docless"
	301	[769]	NOT      	14 14
	302	[769]	LOADBOOL 	15 1 0
	303	[769]	SETLIST  	12 3 1	; 1
	304	[769]	NEWTABLE 	13 1 0
	305	[771]	LOADK    	14 -71	; "wifi_on"
	306	[771]	GETUPVAL 	15 1	; Device
	307	[771]	SELF     	15 15 -72	; "hasWifiToggle"
	308	[771]	CALL     	15 2 0
	309	[771]	SETLIST  	13 0 1	; 1
	310	[771]	NEWTABLE 	14 1 0
	311	[772]	LOADK    	15 -73	; "wifi_off"
	312	[772]	GETUPVAL 	16 1	; Device
	313	[772]	SELF     	16 16 -72	; "hasWifiToggle"
	314	[772]	CALL     	16 2 0
	315	[772]	SETLIST  	14 0 1	; 1
	316	[772]	NEWTABLE 	15 3 0
	317	[773]	LOADK    	16 -74	; "toggle_wifi"
	318	[773]	GETUPVAL 	17 1	; Device
	319	[773]	SELF     	17 17 -72	; "hasWifiToggle"
	320	[773]	CALL     	17 2 2
	321	[773]	LOADBOOL 	18 1 0
	322	[773]	SETLIST  	15 3 1	; 1
	323	[773]	NEWTABLE 	16 2 0
	324	[775]	LOADK    	17 -75	; "increase_font"
	325	[775]	GETTABLE 	18 0 -7	; "is_docless"
	326	[775]	NOT      	18 18
	327	[775]	SETLIST  	16 2 1	; 1
	328	[775]	NEWTABLE 	17 3 0
	329	[776]	LOADK    	18 -76	; "decrease_font"
	330	[776]	GETTABLE 	19 0 -7	; "is_docless"
	331	[776]	NOT      	19 19
	332	[776]	LOADBOOL 	20 1 0
	333	[776]	SETLIST  	17 3 1	; 1
	334	[776]	NEWTABLE 	18 3 0
	335	[778]	LOADK    	19 -77	; "toggle_bookmark"
	336	[778]	GETTABLE 	20 0 -7	; "is_docless"
	337	[778]	NOT      	20 20
	338	[778]	LOADBOOL 	21 1 0
	339	[778]	SETLIST  	18 3 1	; 1
	340	[778]	NEWTABLE 	19 3 0
	341	[779]	LOADK    	20 -78	; "toggle_page_flipping"
	342	[779]	GETTABLE 	21 0 -7	; "is_docless"
	343	[779]	NOT      	21 21
	344	[779]	LOADBOOL 	22 1 0
	345	[779]	SETLIST  	19 3 1	; 1
	346	[779]	NEWTABLE 	20 3 0
	347	[780]	LOADK    	21 -79	; "toggle_reflow"
	348	[780]	GETTABLE 	22 0 -7	; "is_docless"
	349	[780]	NOT      	22 22
	350	[780]	LOADBOOL 	23 1 0
	351	[780]	SETLIST  	20 3 1	; 1
	352	[780]	NEWTABLE 	21 3 0
	353	[781]	LOADK    	22 -80	; "toggle_inverse_reading_order"
	354	[781]	GETTABLE 	23 0 -7	; "is_docless"
	355	[781]	NOT      	23 23
	356	[781]	LOADBOOL 	24 1 0
	357	[781]	SETLIST  	21 3 1	; 1
	358	[781]	NEWTABLE 	22 2 0
	359	[782]	LOADK    	23 -81	; "zoom_contentwidth"
	360	[782]	GETTABLE 	24 0 -7	; "is_docless"
	361	[782]	NOT      	24 24
	362	[782]	SETLIST  	22 2 1	; 1
	363	[782]	NEWTABLE 	23 2 0
	364	[783]	LOADK    	24 -82	; "zoom_contentheight"
	365	[783]	GETTABLE 	25 0 -7	; "is_docless"
	366	[783]	NOT      	25 25
	367	[783]	SETLIST  	23 2 1	; 1
	368	[783]	NEWTABLE 	24 2 0
	369	[784]	LOADK    	25 -83	; "zoom_pagewidth"
	370	[784]	GETTABLE 	26 0 -7	; "is_docless"
	371	[784]	NOT      	26 26
	372	[784]	SETLIST  	24 2 1	; 1
	373	[784]	NEWTABLE 	25 2 0
	374	[785]	LOADK    	26 -84	; "zoom_pageheight"
	375	[785]	GETTABLE 	27 0 -7	; "is_docless"
	376	[785]	NOT      	27 27
	377	[785]	SETLIST  	25 2 1	; 1
	378	[785]	NEWTABLE 	26 2 0
	379	[786]	LOADK    	27 -85	; "zoom_column"
	380	[786]	GETTABLE 	28 0 -7	; "is_docless"
	381	[786]	NOT      	28 28
	382	[786]	SETLIST  	26 2 1	; 1
	383	[786]	NEWTABLE 	27 2 0
	384	[787]	LOADK    	28 -86	; "zoom_content"
	385	[787]	GETTABLE 	29 0 -7	; "is_docless"
	386	[787]	NOT      	29 29
	387	[787]	SETLIST  	27 2 1	; 1
	388	[787]	NEWTABLE 	28 3 0
	389	[788]	LOADK    	29 -87	; "zoom_page"
	390	[788]	GETTABLE 	30 0 -7	; "is_docless"
	391	[788]	NOT      	30 30
	392	[788]	LOADBOOL 	31 1 0
	393	[788]	SETLIST  	28 3 1	; 1
	394	[788]	NEWTABLE 	29 2 0
	395	[789]	LOADK    	30 -88	; "cycle_highlight_action"
	396	[789]	GETTABLE 	31 0 -7	; "is_docless"
	397	[789]	NOT      	31 31
	398	[789]	SETLIST  	29 2 1	; 1
	399	[789]	NEWTABLE 	30 2 0
	400	[790]	LOADK    	31 -89	; "cycle_highlight_style"
	401	[790]	GETTABLE 	32 0 -7	; "is_docless"
	402	[790]	NOT      	32 32
	403	[790]	SETLIST  	30 2 1	; 1
	404	[790]	NEWTABLE 	31 2 0
	405	[791]	LOADK    	32 -90	; "wallabag_download"
	406	[791]	GETTABLE 	33 0 -91	; "ui"
	407	[791]	GETTABLE 	33 33 -92	; "wallabag"
	408	[791]	EQ       	0 33 -32	; - nil
	409	[791]	JMP      	1	; to 411
	410	[791]	LOADBOOL 	33 0 1
	411	[791]	LOADBOOL 	33 1 0
	412	[791]	SETLIST  	31 2 1	; 1
	413	[791]	NEWTABLE 	32 2 0
	414	[793]	LOADK    	33 -93	; "kosync_push_progress"
	415	[793]	GETTABLE 	34 0 -7	; "is_docless"
	416	[793]	NOT      	34 34
	417	[793]	SETLIST  	32 2 1	; 1
	418	[793]	NEWTABLE 	33 2 0
	419	[794]	LOADK    	34 -94	; "kosync_pull_progress"
	420	[794]	GETTABLE 	35 0 -7	; "is_docless"
	421	[794]	NOT      	35 35
	422	[794]	SETLIST  	33 2 1	; 1
	423	[795]	SETLIST  	4 29 2	; 2
	424	[796]	NEWTABLE 	5 0 0
	425	[798]	GETGLOBAL	6 -95	; pairs
	426	[798]	MOVE     	7 4
	427	[798]	CALL     	6 2 4
	428	[798]	JMP      	31	; to 460
	429	[799]	GETTABLE 	11 10 -96	; 1
	430	[799]	EQ       	0 11 2
	431	[799]	JMP      	28	; to 460
	432	[800]	GETUPVAL 	11 2	; T
	433	[800]	GETUPVAL 	12 3	; _
	434	[800]	LOADK    	13 -97	; "%1 (default)"
	435	[800]	CALL     	12 2 2
	436	[800]	GETUPVAL 	13 4	; action_strings
	437	[800]	GETTABLE 	14 10 -96	; 1
	438	[800]	GETTABLE 	13 13 14
	439	[800]	CALL     	11 3 2
	440	[801]	GETGLOBAL	12 -98	; table
	441	[801]	GETTABLE 	12 12 -99	; "insert"
	442	[801]	MOVE     	13 5
	443	[801]	SELF     	14 0 -100	; "createSubMenu"
	444	[801]	MOVE     	16 11
	445	[801]	GETTABLE 	17 10 -96	; 1
	446	[801]	MOVE     	18 1
	447	[801]	LOADBOOL 	19 1 0
	448	[801]	CALL     	14 6 0
	449	[801]	CALL     	12 0 1
	450	[803]	GETTABLE 	12 3 1
	451	[803]	TEST     	12 0 1
	452	[803]	JMP      	9	; to 462
	453	[804]	SETTABLE 	3 1 2
	454	[805]	GETGLOBAL	12 -1	; G_reader_settings
	455	[805]	SELF     	12 12 -101	; "saveSetting"
	456	[805]	GETTABLE 	14 0 -3	; "ges_mode"
	457	[805]	MOVE     	15 3
	458	[805]	CALL     	12 4 1
	459	[807]	JMP      	2	; to 462
	460	[798]	TFORLOOP 	6 2
	461	[808]	JMP      	-33	; to 429
	462	[811]	GETGLOBAL	6 -95	; pairs
	463	[811]	MOVE     	7 4
	464	[811]	CALL     	6 2 4
	465	[811]	JMP      	39	; to 505
	466	[812]	GETTABLE 	11 10 -102	; 2
	467	[812]	TEST     	11 0 1
	468	[812]	JMP      	10	; to 479
	469	[812]	GETTABLE 	11 3 1
	470	[812]	GETTABLE 	12 10 -96	; 1
	471	[812]	EQ       	0 11 12
	472	[812]	JMP      	6	; to 479
	473	[813]	SETTABLE 	3 1 -4	; - "nothing"
	474	[814]	GETGLOBAL	11 -1	; G_reader_settings
	475	[814]	SELF     	11 11 -101	; "saveSetting"
	476	[814]	GETTABLE 	13 0 -3	; "ges_mode"
	477	[814]	MOVE     	14 3
	478	[814]	CALL     	11 4 1
	479	[816]	GETTABLE 	11 10 -96	; 1
	480	[816]	EQ       	1 11 2
	481	[816]	JMP      	23	; to 505
	482	[816]	GETTABLE 	11 10 -102	; 2
	483	[816]	TEST     	11 0 0
	484	[816]	JMP      	20	; to 505
	485	[817]	GETTABLE 	11 10 -96	; 1
	486	[817]	EQ       	1 11 -4	; - "nothing"
	487	[817]	JMP      	4	; to 492
	488	[817]	GETTABLE 	11 10 -103	; 3
	489	[817]	EQ       	1 11 -104	; - true
	490	[817]	JMP      	1	; to 492
	491	[817]	LOADBOOL 	11 0 1
	492	[817]	LOADBOOL 	11 1 0
	493	[818]	GETGLOBAL	12 -98	; table
	494	[818]	GETTABLE 	12 12 -99	; "insert"
	495	[818]	MOVE     	13 5
	496	[818]	SELF     	14 0 -100	; "createSubMenu"
	497	[818]	GETUPVAL 	16 4	; action_strings
	498	[818]	GETTABLE 	17 10 -96	; 1
	499	[818]	GETTABLE 	16 16 17
	500	[818]	GETTABLE 	17 10 -96	; 1
	501	[818]	MOVE     	18 1
	502	[818]	MOVE     	19 11
	503	[818]	CALL     	14 6 0
	504	[818]	CALL     	12 0 1
	505	[811]	TFORLOOP 	6 2
	506	[819]	JMP      	-41	; to 466
	507	[821]	RETURN   	5 2
	508	[822]	RETURN   	0 1

function <./frontend/apps/reader/modules/readergesture.lua:824,909> (164 instructions, 656 bytes at 0x7fad94416480)
1 param, 20 slots, 9 upvalues, 33 locals, 29 constants, 2 functions
	1	[825]	GETGLOBAL	1 -1	; G_reader_settings
	2	[825]	SELF     	1 1 -2	; "readSetting"
	3	[825]	GETTABLE 	3 0 -3	; "ges_mode"
	4	[825]	CALL     	1 3 2
	5	[826]	NEWTABLE 	2 0 0
	6	[827]	NEWTABLE 	3 0 0
	7	[827]	SETUPVAL 	3 0	; multiswipes
	8	[832]	NEWTABLE 	3 0 0
	9	[833]	GETGLOBAL	4 -4	; pairs
	10	[833]	MOVE     	5 1
	11	[833]	CALL     	4 2 4
	12	[833]	JMP      	15	; to 28
	13	[834]	SELF     	9 7 -5	; "sub"
	14	[834]	LOADK    	11 -6	; 1
	15	[834]	LOADK    	12 -7	; 11
	16	[834]	CALL     	9 4 2
	17	[834]	EQ       	0 9 -8	; - "multiswipe_"
	18	[834]	JMP      	9	; to 28
	19	[835]	SELF     	9 7 -5	; "sub"
	20	[835]	LOADK    	11 -9	; 12
	21	[835]	CALL     	9 3 2
	22	[835]	SELF     	9 9 -10	; "gsub"
	23	[835]	LOADK    	11 -11	; "_"
	24	[835]	LOADK    	12 -12	; " "
	25	[835]	CALL     	9 4 2
	26	[835]	MOVE     	7 9
	27	[836]	SETTABLE 	3 7 8
	28	[833]	TFORLOOP 	4 2
	29	[837]	JMP      	-17	; to 13
	30	[840]	GETGLOBAL	4 -4	; pairs
	31	[840]	GETUPVAL 	5 1	; default_multiswipes
	32	[840]	CALL     	4 2 4
	33	[840]	JMP      	6	; to 40
	34	[841]	GETGLOBAL	9 -13	; table
	35	[841]	GETTABLE 	9 9 -14	; "insert"
	36	[841]	GETUPVAL 	10 0	; multiswipes
	37	[841]	MOVE     	11 8
	38	[841]	CALL     	9 3 1
	39	[842]	SETTABLE 	3 8 -15	; - nil
	40	[840]	TFORLOOP 	4 2
	41	[842]	JMP      	-8	; to 34
	42	[845]	GETUPVAL 	4 2	; custom_multiswipes_table
	43	[845]	TEST     	4 0 0
	44	[845]	JMP      	21	; to 66
	45	[845]	GETUPVAL 	4 2	; custom_multiswipes_table
	46	[845]	LEN      	4 4
	47	[845]	LT       	0 -16 4	; 0 -
	48	[845]	JMP      	17	; to 66
	49	[846]	GETGLOBAL	4 -13	; table
	50	[846]	GETTABLE 	4 4 -14	; "insert"
	51	[846]	GETUPVAL 	5 0	; multiswipes
	52	[846]	LOADBOOL 	6 1 0
	53	[846]	CALL     	4 3 1
	54	[847]	GETGLOBAL	4 -4	; pairs
	55	[847]	GETUPVAL 	5 2	; custom_multiswipes_table
	56	[847]	CALL     	4 2 4
	57	[847]	JMP      	6	; to 64
	58	[848]	GETGLOBAL	9 -13	; table
	59	[848]	GETTABLE 	9 9 -14	; "insert"
	60	[848]	GETUPVAL 	10 0	; multiswipes
	61	[848]	MOVE     	11 8
	62	[848]	CALL     	9 3 1
	63	[849]	SETTABLE 	3 8 -15	; - nil
	64	[847]	TFORLOOP 	4 2
	65	[849]	JMP      	-8	; to 58
	66	[853]	GETGLOBAL	4 -17	; next
	67	[853]	MOVE     	5 3
	68	[853]	CALL     	4 2 2
	69	[853]	TEST     	4 0 0
	70	[853]	JMP      	16	; to 87
	71	[854]	GETGLOBAL	4 -13	; table
	72	[854]	GETTABLE 	4 4 -14	; "insert"
	73	[854]	GETUPVAL 	5 0	; multiswipes
	74	[854]	LOADBOOL 	6 1 0
	75	[854]	CALL     	4 3 1
	76	[855]	GETGLOBAL	4 -4	; pairs
	77	[855]	MOVE     	5 3
	78	[855]	CALL     	4 2 4
	79	[855]	JMP      	5	; to 85
	80	[856]	GETGLOBAL	9 -13	; table
	81	[856]	GETTABLE 	9 9 -14	; "insert"
	82	[856]	GETUPVAL 	10 0	; multiswipes
	83	[856]	MOVE     	11 7
	84	[856]	CALL     	9 3 1
	85	[855]	TFORLOOP 	4 2
	86	[856]	JMP      	-7	; to 80
	87	[860]	LOADK    	4 -6	; 1
	88	[860]	GETUPVAL 	5 0	; multiswipes
	89	[860]	LEN      	5 5
	90	[860]	LOADK    	6 -6	; 1
	91	[860]	FORPREP  	4 70	; to 162
	92	[861]	LOADBOOL 	8 0 0
	93	[862]	GETUPVAL 	9 0	; multiswipes
	94	[862]	LEN      	9 9
	95	[862]	LT       	0 7 9
	96	[862]	JMP      	6	; to 103
	97	[862]	GETUPVAL 	9 0	; multiswipes
	98	[862]	ADD      	10 7 -6	; - 1
	99	[862]	GETTABLE 	9 9 10
	100	[862]	EQ       	0 9 -18	; - true
	101	[862]	JMP      	1	; to 103
	102	[863]	LOADBOOL 	8 1 0
	103	[865]	GETGLOBAL	9 -19	; type
	104	[865]	GETUPVAL 	10 0	; multiswipes
	105	[865]	GETTABLE 	10 10 7
	106	[865]	CALL     	9 2 2
	107	[865]	EQ       	0 9 -20	; - "string"
	108	[865]	JMP      	52	; to 161
	109	[866]	GETUPVAL 	9 0	; multiswipes
	110	[866]	GETTABLE 	9 9 7
	111	[867]	SELF     	10 0 -21	; "friendlyMultiswipeName"
	112	[867]	MOVE     	12 9
	113	[867]	CALL     	10 3 2
	114	[869]	LOADK    	11 -8	; "multiswipe_"
	115	[869]	SELF     	12 0 -22	; "safeMultiswipeName"
	116	[869]	MOVE     	14 9
	117	[869]	CALL     	12 3 2
	118	[869]	CONCAT   	11 11 12
	119	[870]	GETTABLE 	12 0 -23	; "default_gesture"
	120	[870]	GETTABLE 	12 12 11
	121	[870]	TEST     	12 0 0
	122	[870]	JMP      	4	; to 127
	123	[870]	GETTABLE 	12 0 -23	; "default_gesture"
	124	[870]	GETTABLE 	12 12 11
	125	[870]	TEST     	12 0 1
	126	[870]	JMP      	1	; to 128
	127	[870]	LOADK    	12 -24	; "nothing"
	128	[871]	GETGLOBAL	13 -13	; table
	129	[871]	GETTABLE 	13 13 -14	; "insert"
	130	[871]	MOVE     	14 2
	131	[871]	NEWTABLE 	15 0 4
	132	[875]	CLOSURE  	16 0	; 0x7fad94416d10
	133	[875]	MOVE     	0 1
	134	[875]	MOVE     	0 11
	135	[875]	GETUPVAL 	0 3	; action_strings
	136	[875]	GETUPVAL 	0 4	; _
	137	[875]	GETUPVAL 	0 5	; T
	138	[875]	MOVE     	0 10
	139	[875]	SETTABLE 	15 -25 16	; "text_func" -
	140	[876]	SELF     	16 0 -27	; "buildMenu"
	141	[876]	MOVE     	18 11
	142	[876]	MOVE     	19 12
	143	[876]	CALL     	16 4 2
	144	[876]	SETTABLE 	15 -26 16	; "sub_item_table" -
	145	[902]	CLOSURE  	16 1	; 0x7fad94417060
	146	[902]	MOVE     	0 7
	147	[902]	GETUPVAL 	0 1	; default_multiswipes
	148	[902]	GETUPVAL 	0 6	; UIManager
	149	[902]	GETUPVAL 	0 7	; ConfirmBox
	150	[902]	GETUPVAL 	0 5	; T
	151	[902]	GETUPVAL 	0 4	; _
	152	[902]	MOVE     	0 10
	153	[902]	MOVE     	0 1
	154	[902]	MOVE     	0 11
	155	[902]	GETUPVAL 	0 8	; custom_multiswipes
	156	[902]	MOVE     	0 0
	157	[902]	SETTABLE 	15 -28 16	; "hold_callback" -
	158	[903]	SETTABLE 	15 -29 8	; "separator" -
	159	[871]	CALL     	13 3 1
	160	[904]	CLOSE    	9
	161	[905]	CLOSE    	7
	162	[860]	FORLOOP  	4 -71	; to 92
	163	[908]	RETURN   	2 2
	164	[909]	RETURN   	0 1

function <./frontend/apps/reader/modules/readergesture.lua:872,875> (24 instructions, 96 bytes at 0x7fad94416d10)
0 params, 5 slots, 6 upvalues, 1 local, 3 constants, 0 functions
	1	[873]	GETUPVAL 	0 0	; gesture_manager
	2	[873]	GETUPVAL 	1 1	; safe_multiswipe_name
	3	[873]	GETTABLE 	0 0 1
	4	[873]	EQ       	1 0 -1	; - "nothing"
	5	[873]	JMP      	7	; to 13
	6	[873]	GETUPVAL 	0 2	; action_strings
	7	[873]	GETUPVAL 	1 0	; gesture_manager
	8	[873]	GETUPVAL 	2 1	; safe_multiswipe_name
	9	[873]	GETTABLE 	1 1 2
	10	[873]	GETTABLE 	0 0 1
	11	[873]	TEST     	0 0 1
	12	[873]	JMP      	3	; to 16
	13	[873]	GETUPVAL 	0 3	; _
	14	[873]	LOADK    	1 -2	; "Available"
	15	[873]	CALL     	0 2 2
	16	[874]	GETUPVAL 	1 4	; T
	17	[874]	GETUPVAL 	2 3	; _
	18	[874]	LOADK    	3 -3	; "%1   (%2)"
	19	[874]	CALL     	2 2 2
	20	[874]	GETUPVAL 	3 5	; friendly_multiswipe_name
	21	[874]	MOVE     	4 0
	22	[874]	TAILCALL 	1 4 0
	23	[874]	RETURN   	1 0
	24	[875]	RETURN   	0 1

function <./frontend/apps/reader/modules/readergesture.lua:877,902> (34 instructions, 136 bytes at 0x7fad94417060)
1 param, 9 slots, 11 upvalues, 1 local, 8 constants, 1 function
	1	[878]	GETUPVAL 	1 0	; i
	2	[878]	GETUPVAL 	2 1	; default_multiswipes
	3	[878]	LEN      	2 2
	4	[878]	ADD      	2 2 -1	; - 1
	5	[878]	LT       	0 2 1
	6	[878]	JMP      	27	; to 34
	7	[879]	GETUPVAL 	1 2	; UIManager
	8	[879]	SELF     	1 1 -2	; "show"
	9	[879]	GETUPVAL 	3 3	; ConfirmBox
	10	[879]	SELF     	3 3 -3	; "new"
	11	[879]	NEWTABLE 	5 0 3
	12	[880]	GETUPVAL 	6 4	; T
	13	[880]	GETUPVAL 	7 5	; _
	14	[880]	LOADK    	8 -5	; "Remove custom multiswipe %1?"
	15	[880]	CALL     	7 2 2
	16	[880]	GETUPVAL 	8 6	; friendly_multiswipe_name
	17	[880]	CALL     	6 3 2
	18	[880]	SETTABLE 	5 -4 6	; "text" -
	19	[881]	GETUPVAL 	6 5	; _
	20	[881]	LOADK    	7 -7	; "Remove"
	21	[881]	CALL     	6 2 2
	22	[881]	SETTABLE 	5 -6 6	; "ok_text" -
	23	[899]	CLOSURE  	6 0	; 0x7fad9440de60
	24	[899]	GETUPVAL 	0 7	; gesture_manager
	25	[899]	GETUPVAL 	0 8	; safe_multiswipe_name
	26	[899]	GETUPVAL 	0 9	; custom_multiswipes
	27	[899]	GETUPVAL 	0 0	; i
	28	[899]	GETUPVAL 	0 1	; default_multiswipes
	29	[899]	MOVE     	0 0
	30	[899]	GETUPVAL 	0 10	; self
	31	[899]	SETTABLE 	5 -8 6	; "ok_callback" -
	32	[879]	CALL     	3 3 0
	33	[879]	CALL     	1 0 1
	34	[902]	RETURN   	0 1

function <./frontend/apps/reader/modules/readergesture.lua:882,899> (40 instructions, 160 bytes at 0x7fad9440de60)
0 params, 9 slots, 7 upvalues, 6 locals, 12 constants, 0 functions
	1	[884]	GETUPVAL 	0 0	; gesture_manager
	2	[884]	GETUPVAL 	1 1	; safe_multiswipe_name
	3	[884]	SETTABLE 	0 1 -1	; - nil
	4	[887]	GETUPVAL 	0 2	; custom_multiswipes
	5	[887]	SELF     	0 0 -2	; "removeTableItem"
	6	[887]	LOADK    	2 -3	; "multiswipes"
	7	[887]	GETUPVAL 	3 3	; i
	8	[887]	GETUPVAL 	4 4	; default_multiswipes
	9	[887]	LEN      	4 4
	10	[887]	SUB      	3 3 4
	11	[887]	SUB      	3 3 -4	; - 1
	12	[887]	CALL     	0 4 1
	13	[891]	GETUPVAL 	0 5	; touchmenu_instance
	14	[891]	GETTABLE 	0 0 -5	; "item_table"
	15	[892]	LEN      	1 0
	16	[892]	LT       	0 -6 1	; 0 -
	17	[892]	JMP      	6	; to 24
	18	[893]	GETGLOBAL	1 -7	; table
	19	[893]	GETTABLE 	1 1 -8	; "remove"
	20	[893]	MOVE     	2 0
	21	[893]	LEN      	3 0
	22	[893]	CALL     	1 3 1
	23	[893]	JMP      	-9	; to 15
	24	[895]	GETGLOBAL	1 -9	; ipairs
	25	[895]	GETUPVAL 	2 6	; self
	26	[895]	SELF     	2 2 -10	; "buildMultiswipeMenu"
	27	[895]	CALL     	2 2 0
	28	[895]	CALL     	1 0 4
	29	[895]	JMP      	5	; to 35
	30	[896]	GETGLOBAL	6 -7	; table
	31	[896]	GETTABLE 	6 6 -11	; "insert"
	32	[896]	MOVE     	7 0
	33	[896]	MOVE     	8 5
	34	[896]	CALL     	6 3 1
	35	[895]	TFORLOOP 	1 2
	36	[896]	JMP      	-7	; to 30
	37	[898]	GETUPVAL 	1 5	; touchmenu_instance
	38	[898]	SELF     	1 1 -12	; "updateItems"
	39	[898]	CALL     	1 2 1
	40	[899]	RETURN   	0 1

function <./frontend/apps/reader/modules/readergesture.lua:911,925> (23 instructions, 92 bytes at 0x7fad9440dde0)
5 params, 8 slots, 0 upvalues, 6 locals, 7 constants, 2 functions
	1	[912]	GETGLOBAL	5 -1	; G_reader_settings
	2	[912]	SELF     	5 5 -2	; "readSetting"
	3	[912]	GETTABLE 	7 0 -3	; "ges_mode"
	4	[912]	CALL     	5 3 2
	5	[913]	NEWTABLE 	6 0 4
	6	[914]	SETTABLE 	6 -4 1	; "text" -
	7	[917]	CLOSURE  	7 0	; 0x7fad9440f780
	8	[917]	MOVE     	0 5
	9	[917]	MOVE     	0 3
	10	[917]	MOVE     	0 2
	11	[917]	SETTABLE 	6 -5 7	; "checked_func" -
	12	[922]	CLOSURE  	7 1	; 0x7fad9440e150
	13	[922]	MOVE     	0 5
	14	[922]	MOVE     	0 3
	15	[922]	MOVE     	0 2
	16	[922]	MOVE     	0 0
	17	[922]	SETTABLE 	6 -6 7	; "callback" -
	18	[923]	TESTSET  	7 4 1
	19	[923]	JMP      	1	; to 21
	20	[923]	LOADBOOL 	7 0 0
	21	[923]	SETTABLE 	6 -7 7	; "separator" -
	22	[924]	RETURN   	6 2
	23	[925]	RETURN   	0 1

function <./frontend/apps/reader/modules/readergesture.lua:915,917> (10 instructions, 40 bytes at 0x7fad9440f780)
0 params, 2 slots, 3 upvalues, 0 locals, 0 constants, 0 functions
	1	[916]	GETUPVAL 	0 0	; gesture_manager
	2	[916]	GETUPVAL 	1 1	; ges
	3	[916]	GETTABLE 	0 0 1
	4	[916]	GETUPVAL 	1 2	; action
	5	[916]	EQ       	1 0 1
	6	[916]	JMP      	1	; to 8
	7	[916]	LOADBOOL 	0 0 1
	8	[916]	LOADBOOL 	0 1 0
	9	[916]	RETURN   	0 2
	10	[917]	RETURN   	0 1

function <./frontend/apps/reader/modules/readergesture.lua:918,922> (16 instructions, 64 bytes at 0x7fad9440e150)
0 params, 4 slots, 4 upvalues, 0 locals, 4 constants, 0 functions
	1	[919]	GETUPVAL 	0 0	; gesture_manager
	2	[919]	GETUPVAL 	1 1	; ges
	3	[919]	GETUPVAL 	2 2	; action
	4	[919]	SETTABLE 	0 1 2
	5	[920]	GETGLOBAL	0 -1	; G_reader_settings
	6	[920]	SELF     	0 0 -2	; "saveSetting"
	7	[920]	GETUPVAL 	2 3	; self
	8	[920]	GETTABLE 	2 2 -3	; "ges_mode"
	9	[920]	GETUPVAL 	3 0	; gesture_manager
	10	[920]	CALL     	0 4 1
	11	[921]	GETUPVAL 	0 3	; self
	12	[921]	SELF     	0 0 -4	; "setupGesture"
	13	[921]	GETUPVAL 	2 1	; ges
	14	[921]	GETUPVAL 	3 2	; action
	15	[921]	CALL     	0 4 1
	16	[922]	RETURN   	0 1

function <./frontend/apps/reader/modules/readergesture.lua:937,939> (6 instructions, 24 bytes at 0x7fad9440d2e0)
2 params, 6 slots, 1 upvalue, 2 locals, 2 constants, 0 functions
	1	[938]	SELF     	2 1 -1	; "gsub"
	2	[938]	LOADK    	4 -2	; "%S+"
	3	[938]	GETUPVAL 	5 0	; multiswipe_to_arrow
	4	[938]	TAILCALL 	2 4 0
	5	[938]	RETURN   	2 0
	6	[939]	RETURN   	0 1

function <./frontend/apps/reader/modules/readergesture.lua:941,943> (6 instructions, 24 bytes at 0x7fad9440d360)
2 params, 6 slots, 0 upvalues, 2 locals, 3 constants, 0 functions
	1	[942]	SELF     	2 1 -1	; "gsub"
	2	[942]	LOADK    	4 -2	; " "
	3	[942]	LOADK    	5 -3	; "_"
	4	[942]	TAILCALL 	2 4 0
	5	[942]	RETURN   	2 0
	6	[943]	RETURN   	0 1

function <./frontend/apps/reader/modules/readergesture.lua:945,1227> (448 instructions, 1792 bytes at 0x7fad944144e0)
3 params, 38 slots, 0 upvalues, 29 locals, 89 constants, 0 functions
	1	[951]	NEWTABLE 	8 0 4
	2	[952]	SETTABLE 	8 -1 -2	; "ratio_x" 0
	3	[952]	SETTABLE 	8 -3 -2	; "ratio_y" 0
	4	[953]	SETTABLE 	8 -4 -5	; "ratio_w" 1
	5	[953]	SETTABLE 	8 -6 -5	; "ratio_h" 1
	6	[956]	NEWTABLE 	9 0 4
	7	[957]	SETTABLE 	9 -1 -2	; "ratio_x" 0
	8	[957]	SETTABLE 	9 -3 -2	; "ratio_y" 0
	9	[958]	SETTABLE 	9 -4 -7	; "ratio_w" 0.125
	10	[958]	SETTABLE 	9 -6 -5	; "ratio_h" 1
	11	[960]	NEWTABLE 	10 0 4
	12	[961]	SETTABLE 	10 -1 -8	; "ratio_x" 0.875
	13	[961]	SETTABLE 	10 -3 -2	; "ratio_y" 0
	14	[962]	SETTABLE 	10 -4 -7	; "ratio_w" 0.125
	15	[962]	SETTABLE 	10 -6 -5	; "ratio_h" 1
	16	[964]	NEWTABLE 	11 0 4
	17	[965]	SETTABLE 	11 -1 -2	; "ratio_x" 0
	18	[965]	SETTABLE 	11 -3 -2	; "ratio_y" 0
	19	[966]	SETTABLE 	11 -4 -5	; "ratio_w" 1
	20	[966]	SETTABLE 	11 -6 -7	; "ratio_h" 0.125
	21	[968]	NEWTABLE 	12 0 4
	22	[969]	SETTABLE 	12 -1 -2	; "ratio_x" 0
	23	[969]	SETTABLE 	12 -3 -8	; "ratio_y" 0.875
	24	[970]	SETTABLE 	12 -4 -5	; "ratio_w" 1
	25	[970]	SETTABLE 	12 -6 -7	; "ratio_h" 0.125
	26	[974]	GETGLOBAL	13 -9	; DTAP_ZONE_FLIPPING
	27	[974]	TEST     	13 0 0
	28	[974]	JMP      	3	; to 32
	29	[974]	GETGLOBAL	13 -9	; DTAP_ZONE_FLIPPING
	30	[974]	TEST     	13 0 1
	31	[974]	JMP      	1	; to 33
	32	[974]	GETGLOBAL	13 -10	; DTAP_ZONE_TOP_LEFT
	33	[975]	NEWTABLE 	14 0 4
	34	[976]	GETTABLE 	15 13 -11	; "x"
	35	[976]	SETTABLE 	14 -1 15	; "ratio_x" -
	36	[977]	GETTABLE 	15 13 -12	; "y"
	37	[977]	SETTABLE 	14 -3 15	; "ratio_y" -
	38	[978]	GETTABLE 	15 13 -13	; "w"
	39	[978]	SETTABLE 	14 -4 15	; "ratio_w" -
	40	[979]	GETTABLE 	15 13 -14	; "h"
	41	[979]	SETTABLE 	14 -6 15	; "ratio_h" -
	42	[982]	GETGLOBAL	15 -15	; DTAP_ZONE_BOOKMARK
	43	[982]	TEST     	15 0 0
	44	[982]	JMP      	3	; to 48
	45	[982]	GETGLOBAL	15 -15	; DTAP_ZONE_BOOKMARK
	46	[982]	TEST     	15 0 1
	47	[982]	JMP      	1	; to 49
	48	[982]	GETGLOBAL	15 -16	; DTAP_ZONE_TOP_RIGHT
	49	[983]	NEWTABLE 	16 0 4
	50	[984]	GETTABLE 	17 15 -11	; "x"
	51	[984]	SETTABLE 	16 -1 17	; "ratio_x" -
	52	[985]	GETTABLE 	17 15 -12	; "y"
	53	[985]	SETTABLE 	16 -3 17	; "ratio_y" -
	54	[986]	GETTABLE 	17 15 -13	; "w"
	55	[986]	SETTABLE 	16 -4 17	; "ratio_w" -
	56	[987]	GETTABLE 	17 15 -14	; "h"
	57	[987]	SETTABLE 	16 -6 17	; "ratio_h" -
	58	[989]	NEWTABLE 	17 0 4
	59	[990]	GETGLOBAL	18 -17	; DTAP_ZONE_BOTTOM_LEFT
	60	[990]	GETTABLE 	18 18 -11	; "x"
	61	[990]	SETTABLE 	17 -1 18	; "ratio_x" -
	62	[991]	GETGLOBAL	18 -17	; DTAP_ZONE_BOTTOM_LEFT
	63	[991]	GETTABLE 	18 18 -12	; "y"
	64	[991]	SETTABLE 	17 -3 18	; "ratio_y" -
	65	[992]	GETGLOBAL	18 -17	; DTAP_ZONE_BOTTOM_LEFT
	66	[992]	GETTABLE 	18 18 -13	; "w"
	67	[992]	SETTABLE 	17 -4 18	; "ratio_w" -
	68	[993]	GETGLOBAL	18 -17	; DTAP_ZONE_BOTTOM_LEFT
	69	[993]	GETTABLE 	18 18 -14	; "h"
	70	[993]	SETTABLE 	17 -6 18	; "ratio_h" -
	71	[995]	NEWTABLE 	18 0 4
	72	[996]	GETGLOBAL	19 -18	; DTAP_ZONE_BOTTOM_RIGHT
	73	[996]	GETTABLE 	19 19 -11	; "x"
	74	[996]	SETTABLE 	18 -1 19	; "ratio_x" -
	75	[997]	GETGLOBAL	19 -18	; DTAP_ZONE_BOTTOM_RIGHT
	76	[997]	GETTABLE 	19 19 -12	; "y"
	77	[997]	SETTABLE 	18 -3 19	; "ratio_y" -
	78	[998]	GETGLOBAL	19 -18	; DTAP_ZONE_BOTTOM_RIGHT
	79	[998]	GETTABLE 	19 19 -13	; "w"
	80	[998]	SETTABLE 	18 -4 19	; "ratio_w" -
	81	[999]	GETGLOBAL	19 -18	; DTAP_ZONE_BOTTOM_RIGHT
	82	[999]	GETTABLE 	19 19 -14	; "h"
	83	[999]	SETTABLE 	18 -6 19	; "ratio_h" -
	84	[1002]	LOADNIL  	19 26
	85	[1007]	GETTABLE 	27 0 -19	; "is_docless"
	86	[1007]	TEST     	27 0 0
	87	[1007]	JMP      	9	; to 97
	88	[1008]	NEWTABLE 	27 1 0
	89	[1010]	LOADK    	28 -20	; "filemanager_tap"
	90	[1010]	SETLIST  	27 1 1	; 1
	91	[1010]	MOVE     	19 27
	92	[1011]	NEWTABLE 	27 1 0
	93	[1013]	LOADK    	28 -21	; "filemanager_swipe"
	94	[1013]	SETLIST  	27 1 1	; 1
	95	[1013]	MOVE     	22 27
	96	[1013]	JMP      	37	; to 134
	97	[1015]	NEWTABLE 	27 5 0
	98	[1016]	LOADK    	28 -22	; "tap_backward"
	99	[1017]	LOADK    	29 -23	; "tap_forward"
	100	[1018]	LOADK    	30 -24	; "readermenu_tap"
	101	[1019]	LOADK    	31 -25	; "readerconfigmenu_tap"
	102	[1021]	LOADK    	32 -26	; "readerfooter_tap"
	103	[1021]	SETLIST  	27 5 1	; 1
	104	[1021]	MOVE     	19 27
	105	[1022]	NEWTABLE 	27 2 0
	106	[1026]	LOADK    	28 -27	; "readerhighlight_hold"
	107	[1028]	LOADK    	29 -28	; "readerfooter_hold"
	108	[1028]	SETLIST  	27 2 1	; 1
	109	[1028]	MOVE     	20 27
	110	[1029]	NEWTABLE 	27 4 0
	111	[1030]	LOADK    	28 -29	; "paging_swipe"
	112	[1031]	LOADK    	29 -30	; "rolling_swipe"
	113	[1032]	LOADK    	30 -31	; "readermenu_swipe"
	114	[1034]	LOADK    	31 -32	; "readerconfigmenu_swipe"
	115	[1034]	SETLIST  	27 4 1	; 1
	116	[1034]	MOVE     	21 27
	117	[1035]	NEWTABLE 	27 5 0
	118	[1036]	LOADK    	28 -33	; "swipe_link"
	119	[1037]	LOADK    	29 -29	; "paging_swipe"
	120	[1038]	LOADK    	30 -30	; "rolling_swipe"
	121	[1039]	LOADK    	31 -31	; "readermenu_swipe"
	122	[1041]	LOADK    	32 -32	; "readerconfigmenu_swipe"
	123	[1041]	SETLIST  	27 5 1	; 1
	124	[1041]	MOVE     	22 27
	125	[1042]	NEWTABLE 	27 2 0
	126	[1043]	LOADK    	28 -29	; "paging_swipe"
	127	[1045]	LOADK    	29 -30	; "rolling_swipe"
	128	[1045]	SETLIST  	27 2 1	; 1
	129	[1045]	MOVE     	23 27
	130	[1046]	NEWTABLE 	27 1 0
	131	[1048]	LOADK    	28 -34	; "paging_pan_release"
	132	[1048]	SETLIST  	27 1 1	; 1
	133	[1048]	MOVE     	24 27
	134	[1051]	EQ       	0 1 -35	; - "multiswipe"
	135	[1051]	JMP      	13	; to 149
	136	[1052]	LOADK    	3 -35	; "multiswipe"
	137	[1053]	MOVE     	4 8
	138	[1054]	NEWTABLE 	27 0 8
	139	[1055]	SETTABLE 	27 -36 -37	; "northeast" true
	140	[1055]	SETTABLE 	27 -38 -37	; "northwest" true
	141	[1056]	SETTABLE 	27 -39 -37	; "southeast" true
	142	[1056]	SETTABLE 	27 -40 -37	; "southwest" true
	143	[1057]	SETTABLE 	27 -41 -37	; "east" true
	144	[1057]	SETTABLE 	27 -42 -37	; "west" true
	145	[1058]	SETTABLE 	27 -43 -37	; "north" true
	146	[1058]	SETTABLE 	27 -44 -37	; "south" true
	147	[1059]	MOVE     	6 27
	148	[1059]	JMP      	262	; to 411
	149	[1060]	EQ       	0 1 -45	; - "tap_top_left_corner"
	150	[1060]	JMP      	4	; to 155
	151	[1061]	LOADK    	3 -46	; "tap"
	152	[1062]	MOVE     	4 14
	153	[1063]	MOVE     	5 19
	154	[1063]	JMP      	256	; to 411
	155	[1064]	EQ       	0 1 -47	; - "tap_top_right_corner"
	156	[1064]	JMP      	4	; to 161
	157	[1065]	LOADK    	3 -46	; "tap"
	158	[1066]	MOVE     	4 16
	159	[1067]	MOVE     	5 19
	160	[1067]	JMP      	250	; to 411
	161	[1068]	EQ       	0 1 -48	; - "tap_right_bottom_corner"
	162	[1068]	JMP      	4	; to 167
	163	[1069]	LOADK    	3 -46	; "tap"
	164	[1070]	MOVE     	4 18
	165	[1071]	MOVE     	5 19
	166	[1071]	JMP      	244	; to 411
	167	[1072]	EQ       	0 1 -49	; - "tap_left_bottom_corner"
	168	[1072]	JMP      	4	; to 173
	169	[1073]	LOADK    	3 -46	; "tap"
	170	[1074]	MOVE     	4 17
	171	[1075]	MOVE     	5 19
	172	[1075]	JMP      	238	; to 411
	173	[1076]	EQ       	0 1 -50	; - "hold_top_left_corner"
	174	[1076]	JMP      	4	; to 179
	175	[1077]	LOADK    	3 -51	; "hold"
	176	[1078]	MOVE     	4 14
	177	[1079]	MOVE     	5 20
	178	[1079]	JMP      	232	; to 411
	179	[1080]	EQ       	0 1 -52	; - "hold_top_right_corner"
	180	[1080]	JMP      	4	; to 185
	181	[1081]	LOADK    	3 -51	; "hold"
	182	[1082]	MOVE     	4 16
	183	[1083]	MOVE     	5 20
	184	[1083]	JMP      	226	; to 411
	185	[1084]	EQ       	0 1 -53	; - "hold_bottom_right_corner"
	186	[1084]	JMP      	4	; to 191
	187	[1085]	LOADK    	3 -51	; "hold"
	188	[1086]	MOVE     	4 18
	189	[1087]	MOVE     	5 20
	190	[1087]	JMP      	220	; to 411
	191	[1088]	EQ       	0 1 -54	; - "hold_bottom_left_corner"
	192	[1088]	JMP      	4	; to 197
	193	[1089]	LOADK    	3 -51	; "hold"
	194	[1090]	MOVE     	4 17
	195	[1091]	MOVE     	5 20
	196	[1091]	JMP      	214	; to 411
	197	[1092]	EQ       	0 1 -55	; - "one_finger_swipe_left_edge_down"
	198	[1092]	JMP      	9	; to 208
	199	[1093]	LOADK    	3 -56	; "swipe"
	200	[1094]	MOVE     	4 9
	201	[1095]	NEWTABLE 	27 0 1
	202	[1095]	SETTABLE 	27 -44 -37	; "south" true
	203	[1095]	MOVE     	6 27
	204	[1096]	MOVE     	5 21
	205	[1097]	MOVE     	25 23
	206	[1098]	MOVE     	26 24
	207	[1098]	JMP      	203	; to 411
	208	[1099]	EQ       	0 1 -57	; - "one_finger_swipe_left_edge_up"
	209	[1099]	JMP      	9	; to 219
	210	[1100]	LOADK    	3 -56	; "swipe"
	211	[1101]	MOVE     	4 9
	212	[1102]	NEWTABLE 	27 0 1
	213	[1102]	SETTABLE 	27 -43 -37	; "north" true
	214	[1102]	MOVE     	6 27
	215	[1103]	MOVE     	5 21
	216	[1104]	MOVE     	25 23
	217	[1105]	MOVE     	26 24
	218	[1105]	JMP      	192	; to 411
	219	[1106]	EQ       	0 1 -58	; - "one_finger_swipe_right_edge_down"
	220	[1106]	JMP      	9	; to 230
	221	[1107]	LOADK    	3 -56	; "swipe"
	222	[1108]	MOVE     	4 10
	223	[1109]	NEWTABLE 	27 0 1
	224	[1109]	SETTABLE 	27 -44 -37	; "south" true
	225	[1109]	MOVE     	6 27
	226	[1110]	MOVE     	5 21
	227	[1111]	MOVE     	25 23
	228	[1112]	MOVE     	26 24
	229	[1112]	JMP      	181	; to 411
	230	[1113]	EQ       	0 1 -59	; - "one_finger_swipe_right_edge_up"
	231	[1113]	JMP      	9	; to 241
	232	[1114]	LOADK    	3 -56	; "swipe"
	233	[1115]	MOVE     	4 10
	234	[1116]	NEWTABLE 	27 0 1
	235	[1116]	SETTABLE 	27 -43 -37	; "north" true
	236	[1116]	MOVE     	6 27
	237	[1117]	MOVE     	5 21
	238	[1118]	MOVE     	25 23
	239	[1119]	MOVE     	26 24
	240	[1119]	JMP      	170	; to 411
	241	[1120]	EQ       	0 1 -60	; - "one_finger_swipe_top_edge_right"
	242	[1120]	JMP      	9	; to 252
	243	[1121]	LOADK    	3 -56	; "swipe"
	244	[1122]	MOVE     	4 11
	245	[1123]	NEWTABLE 	27 0 1
	246	[1123]	SETTABLE 	27 -41 -37	; "east" true
	247	[1123]	MOVE     	6 27
	248	[1124]	MOVE     	5 22
	249	[1125]	MOVE     	25 23
	250	[1126]	MOVE     	26 24
	251	[1126]	JMP      	159	; to 411
	252	[1127]	EQ       	0 1 -61	; - "one_finger_swipe_top_edge_left"
	253	[1127]	JMP      	9	; to 263
	254	[1128]	LOADK    	3 -56	; "swipe"
	255	[1129]	MOVE     	4 11
	256	[1130]	NEWTABLE 	27 0 1
	257	[1130]	SETTABLE 	27 -42 -37	; "west" true
	258	[1130]	MOVE     	6 27
	259	[1131]	MOVE     	5 22
	260	[1132]	MOVE     	25 23
	261	[1133]	MOVE     	26 24
	262	[1133]	JMP      	148	; to 411
	263	[1134]	EQ       	0 1 -62	; - "one_finger_swipe_bottom_edge_right"
	264	[1134]	JMP      	9	; to 274
	265	[1135]	LOADK    	3 -56	; "swipe"
	266	[1136]	MOVE     	4 12
	267	[1137]	NEWTABLE 	27 0 1
	268	[1137]	SETTABLE 	27 -41 -37	; "east" true
	269	[1137]	MOVE     	6 27
	270	[1138]	MOVE     	5 22
	271	[1139]	MOVE     	25 23
	272	[1140]	MOVE     	26 24
	273	[1140]	JMP      	137	; to 411
	274	[1141]	EQ       	0 1 -63	; - "one_finger_swipe_bottom_edge_left"
	275	[1141]	JMP      	9	; to 285
	276	[1142]	LOADK    	3 -56	; "swipe"
	277	[1143]	MOVE     	4 12
	278	[1144]	NEWTABLE 	27 0 1
	279	[1144]	SETTABLE 	27 -42 -37	; "west" true
	280	[1144]	MOVE     	6 27
	281	[1145]	MOVE     	5 22
	282	[1146]	MOVE     	25 23
	283	[1147]	MOVE     	26 24
	284	[1147]	JMP      	126	; to 411
	285	[1148]	EQ       	0 1 -64	; - "two_finger_tap_top_left_corner"
	286	[1148]	JMP      	3	; to 290
	287	[1149]	LOADK    	3 -65	; "two_finger_tap"
	288	[1150]	MOVE     	4 14
	289	[1150]	JMP      	121	; to 411
	290	[1151]	EQ       	0 1 -66	; - "two_finger_tap_top_right_corner"
	291	[1151]	JMP      	3	; to 295
	292	[1152]	LOADK    	3 -65	; "two_finger_tap"
	293	[1153]	MOVE     	4 16
	294	[1153]	JMP      	116	; to 411
	295	[1154]	EQ       	0 1 -67	; - "two_finger_tap_bottom_right_corner"
	296	[1154]	JMP      	3	; to 300
	297	[1155]	LOADK    	3 -65	; "two_finger_tap"
	298	[1156]	MOVE     	4 18
	299	[1156]	JMP      	111	; to 411
	300	[1157]	EQ       	0 1 -68	; - "two_finger_tap_bottom_left_corner"
	301	[1157]	JMP      	3	; to 305
	302	[1158]	LOADK    	3 -65	; "two_finger_tap"
	303	[1159]	MOVE     	4 17
	304	[1159]	JMP      	106	; to 411
	305	[1160]	EQ       	0 1 -69	; - "two_finger_swipe_west"
	306	[1160]	JMP      	6	; to 313
	307	[1161]	LOADK    	3 -70	; "two_finger_swipe"
	308	[1162]	MOVE     	4 8
	309	[1163]	NEWTABLE 	27 0 1
	310	[1163]	SETTABLE 	27 -42 -37	; "west" true
	311	[1163]	MOVE     	6 27
	312	[1163]	JMP      	98	; to 411
	313	[1164]	EQ       	0 1 -71	; - "two_finger_swipe_east"
	314	[1164]	JMP      	6	; to 321
	315	[1165]	LOADK    	3 -70	; "two_finger_swipe"
	316	[1166]	MOVE     	4 8
	317	[1167]	NEWTABLE 	27 0 1
	318	[1167]	SETTABLE 	27 -41 -37	; "east" true
	319	[1167]	MOVE     	6 27
	320	[1167]	JMP      	90	; to 411
	321	[1168]	EQ       	0 1 -72	; - "two_finger_swipe_south"
	322	[1168]	JMP      	6	; to 329
	323	[1169]	LOADK    	3 -70	; "two_finger_swipe"
	324	[1170]	MOVE     	4 8
	325	[1171]	NEWTABLE 	27 0 1
	326	[1171]	SETTABLE 	27 -44 -37	; "south" true
	327	[1171]	MOVE     	6 27
	328	[1171]	JMP      	82	; to 411
	329	[1172]	EQ       	0 1 -73	; - "two_finger_swipe_north"
	330	[1172]	JMP      	6	; to 337
	331	[1173]	LOADK    	3 -70	; "two_finger_swipe"
	332	[1174]	MOVE     	4 8
	333	[1175]	NEWTABLE 	27 0 1
	334	[1175]	SETTABLE 	27 -43 -37	; "north" true
	335	[1175]	MOVE     	6 27
	336	[1175]	JMP      	74	; to 411
	337	[1176]	EQ       	0 1 -74	; - "two_finger_swipe_northwest"
	338	[1176]	JMP      	6	; to 345
	339	[1177]	LOADK    	3 -70	; "two_finger_swipe"
	340	[1178]	MOVE     	4 8
	341	[1179]	NEWTABLE 	27 0 1
	342	[1179]	SETTABLE 	27 -38 -37	; "northwest" true
	343	[1179]	MOVE     	6 27
	344	[1179]	JMP      	66	; to 411
	345	[1180]	EQ       	0 1 -75	; - "two_finger_swipe_northeast"
	346	[1180]	JMP      	6	; to 353
	347	[1181]	LOADK    	3 -70	; "two_finger_swipe"
	348	[1182]	MOVE     	4 8
	349	[1183]	NEWTABLE 	27 0 1
	350	[1183]	SETTABLE 	27 -36 -37	; "northeast" true
	351	[1183]	MOVE     	6 27
	352	[1183]	JMP      	58	; to 411
	353	[1184]	EQ       	0 1 -76	; - "two_finger_swipe_southwest"
	354	[1184]	JMP      	6	; to 361
	355	[1185]	LOADK    	3 -70	; "two_finger_swipe"
	356	[1186]	MOVE     	4 8
	357	[1187]	NEWTABLE 	27 0 1
	358	[1187]	SETTABLE 	27 -40 -37	; "southwest" true
	359	[1187]	MOVE     	6 27
	360	[1187]	JMP      	50	; to 411
	361	[1188]	EQ       	0 1 -77	; - "two_finger_swipe_southeast"
	362	[1188]	JMP      	6	; to 369
	363	[1189]	LOADK    	3 -70	; "two_finger_swipe"
	364	[1190]	MOVE     	4 8
	365	[1191]	NEWTABLE 	27 0 1
	366	[1191]	SETTABLE 	27 -39 -37	; "southeast" true
	367	[1191]	MOVE     	6 27
	368	[1191]	JMP      	42	; to 411
	369	[1192]	EQ       	0 1 -78	; - "short_diagonal_swipe"
	370	[1192]	JMP      	29	; to 400
	371	[1193]	LOADK    	3 -56	; "swipe"
	372	[1194]	NEWTABLE 	27 0 4
	373	[1195]	SETTABLE 	27 -1 -2	; "ratio_x" 0
	374	[1195]	SETTABLE 	27 -3 -2	; "ratio_y" 0
	375	[1196]	SETTABLE 	27 -4 -5	; "ratio_w" 1
	376	[1196]	SETTABLE 	27 -6 -5	; "ratio_h" 1
	377	[1197]	MOVE     	4 27
	378	[1198]	NEWTABLE 	27 0 4
	379	[1198]	SETTABLE 	27 -36 -37	; "northeast" true
	380	[1198]	SETTABLE 	27 -38 -37	; "northwest" true
	381	[1198]	SETTABLE 	27 -39 -37	; "southeast" true
	382	[1198]	SETTABLE 	27 -40 -37	; "southwest" true
	383	[1198]	MOVE     	6 27
	384	[1199]	LOADK    	7 -79	; "short"
	385	[1200]	GETTABLE 	27 0 -19	; "is_docless"
	386	[1200]	TEST     	27 0 0
	387	[1200]	JMP      	6	; to 394
	388	[1201]	NEWTABLE 	27 2 0
	389	[1202]	LOADK    	28 -20	; "filemanager_tap"
	390	[1204]	LOADK    	29 -21	; "filemanager_swipe"
	391	[1204]	SETLIST  	27 2 1	; 1
	392	[1204]	MOVE     	5 27
	393	[1204]	JMP      	17	; to 411
	394	[1206]	NEWTABLE 	27 2 0
	395	[1207]	LOADK    	28 -30	; "rolling_swipe"
	396	[1209]	LOADK    	29 -29	; "paging_swipe"
	397	[1209]	SETLIST  	27 2 1	; 1
	398	[1209]	MOVE     	5 27
	399	[1210]	JMP      	11	; to 411
	400	[1211]	EQ       	0 1 -80	; - "spread_gesture"
	401	[1211]	JMP      	3	; to 405
	402	[1212]	LOADK    	3 -81	; "spread"
	403	[1213]	MOVE     	4 8
	404	[1213]	JMP      	6	; to 411
	405	[1214]	EQ       	0 1 -82	; - "pinch_gesture"
	406	[1214]	JMP      	3	; to 410
	407	[1215]	LOADK    	3 -83	; "pinch"
	408	[1216]	MOVE     	4 8
	409	[1216]	JMP      	1	; to 411
	410	[1217]	RETURN   	0 1
	411	[1219]	SELF     	27 0 -84	; "registerGesture"
	412	[1219]	MOVE     	29 1
	413	[1219]	MOVE     	30 2
	414	[1219]	MOVE     	31 3
	415	[1219]	MOVE     	32 4
	416	[1219]	MOVE     	33 5
	417	[1219]	MOVE     	34 6
	418	[1219]	MOVE     	35 7
	419	[1219]	CALL     	27 9 1
	420	[1221]	EQ       	0 3 -56	; - "swipe"
	421	[1221]	JMP      	26	; to 448
	422	[1221]	EQ       	1 1 -78	; - "short_diagonal_swipe"
	423	[1221]	JMP      	24	; to 448
	424	[1222]	MOVE     	27 1
	425	[1222]	LOADK    	28 -85	; "_pan"
	426	[1222]	CONCAT   	27 27 28
	427	[1223]	MOVE     	28 1
	428	[1223]	LOADK    	29 -86	; "_pan_release"
	429	[1223]	CONCAT   	28 28 29
	430	[1224]	SELF     	29 0 -84	; "registerGesture"
	431	[1224]	MOVE     	31 27
	432	[1224]	LOADK    	32 -87	; ""
	433	[1224]	LOADK    	33 -88	; "pan"
	434	[1224]	MOVE     	34 4
	435	[1224]	MOVE     	35 25
	436	[1224]	MOVE     	36 6
	437	[1224]	MOVE     	37 7
	438	[1224]	CALL     	29 9 1
	439	[1225]	SELF     	29 0 -84	; "registerGesture"
	440	[1225]	MOVE     	31 28
	441	[1225]	LOADK    	32 -87	; ""
	442	[1225]	LOADK    	33 -89	; "pan_release"
	443	[1225]	MOVE     	34 4
	444	[1225]	MOVE     	35 26
	445	[1225]	MOVE     	36 6
	446	[1225]	MOVE     	37 7
	447	[1225]	CALL     	29 9 1
	448	[1227]	RETURN   	0 1

function <./frontend/apps/reader/modules/readergesture.lua:1229,1265> (23 instructions, 92 bytes at 0x7fad944152b0)
8 params, 13 slots, 5 upvalues, 8 locals, 7 constants, 1 function
	1	[1230]	GETTABLE 	8 0 -1	; "ui"
	2	[1230]	SELF     	8 8 -2	; "registerTouchZones"
	3	[1230]	NEWTABLE 	10 1 0
	4	[1230]	NEWTABLE 	11 0 5
	5	[1232]	SETTABLE 	11 -3 1	; "id" -
	6	[1233]	SETTABLE 	11 -4 3	; "ges" -
	7	[1234]	SETTABLE 	11 -5 4	; "screen_zone" -
	8	[1261]	CLOSURE  	12 0	; 0x7fad94415de0
	9	[1261]	MOVE     	0 7
	10	[1261]	GETUPVAL 	0 0	; Screen
	11	[1261]	MOVE     	0 6
	12	[1261]	MOVE     	0 1
	13	[1261]	MOVE     	0 0
	14	[1261]	GETUPVAL 	0 1	; UIManager
	15	[1261]	GETUPVAL 	0 2	; ConfirmBox
	16	[1261]	GETUPVAL 	0 3	; _
	17	[1261]	GETUPVAL 	0 4	; multiswipes_info_text
	18	[1261]	MOVE     	0 2
	19	[1261]	SETTABLE 	11 -6 12	; "handler" -
	20	[1262]	SETTABLE 	11 -7 5	; "overrides" -
	21	[1264]	SETLIST  	10 1 1	; 1
	22	[1230]	CALL     	8 3 1
	23	[1265]	RETURN   	0 1

function <./frontend/apps/reader/modules/readergesture.lua:1235,1261> (70 instructions, 280 bytes at 0x7fad94415de0)
1 param, 9 slots, 10 upvalues, 1 local, 22 constants, 2 functions
	1	[1236]	GETUPVAL 	1 0	; distance
	2	[1236]	EQ       	0 1 -1	; - "short"
	3	[1236]	JMP      	8	; to 12
	4	[1236]	GETTABLE 	1 0 -2	; "distance"
	5	[1236]	GETUPVAL 	2 1	; Screen
	6	[1236]	SELF     	2 2 -3	; "scaleBySize"
	7	[1236]	LOADK    	4 -4	; 300
	8	[1236]	CALL     	2 3 2
	9	[1236]	LT       	0 2 1
	10	[1236]	JMP      	1	; to 12
	11	[1236]	RETURN   	0 1
	12	[1237]	GETUPVAL 	1 2	; direction
	13	[1237]	TEST     	1 0 0
	14	[1237]	JMP      	6	; to 21
	15	[1237]	GETUPVAL 	1 2	; direction
	16	[1237]	GETTABLE 	2 0 -5	; "direction"
	17	[1237]	GETTABLE 	1 1 2
	18	[1237]	TEST     	1 0 1
	19	[1237]	JMP      	1	; to 21
	20	[1237]	RETURN   	0 1
	21	[1239]	GETUPVAL 	1 3	; ges
	22	[1239]	EQ       	0 1 -6	; - "multiswipe"
	23	[1239]	JMP      	40	; to 64
	24	[1240]	GETUPVAL 	1 4	; self
	25	[1240]	GETTABLE 	1 1 -7	; "multiswipes_enabled"
	26	[1240]	EQ       	0 1 -8	; - nil
	27	[1240]	JMP      	30	; to 58
	28	[1241]	GETUPVAL 	1 5	; UIManager
	29	[1241]	SELF     	1 1 -9	; "show"
	30	[1241]	GETUPVAL 	3 6	; ConfirmBox
	31	[1241]	SELF     	3 3 -10	; "new"
	32	[1241]	NEWTABLE 	5 0 5
	33	[1242]	GETUPVAL 	6 7	; _
	34	[1242]	LOADK    	7 -12	; "You have just performed your first multiswipe gesture."
	35	[1242]	CALL     	6 2 2
	36	[1242]	LOADK    	7 -13	; "\n\n"
	37	[1242]	GETUPVAL 	8 8	; multiswipes_info_text
	38	[1242]	CONCAT   	6 6 8
	39	[1242]	SETTABLE 	5 -11 6	; "text" -
	40	[1243]	GETUPVAL 	6 7	; _
	41	[1243]	LOADK    	7 -15	; "Turn on"
	42	[1243]	CALL     	6 2 2
	43	[1243]	SETTABLE 	5 -14 6	; "ok_text" -
	44	[1247]	CLOSURE  	6 0	; 0x7fad94412c70
	45	[1247]	GETUPVAL 	0 4	; self
	46	[1247]	SETTABLE 	5 -16 6	; "ok_callback" -
	47	[1248]	GETUPVAL 	6 7	; _
	48	[1248]	LOADK    	7 -18	; "Turn off"
	49	[1248]	CALL     	6 2 2
	50	[1248]	SETTABLE 	5 -17 6	; "cancel_text" -
	51	[1252]	CLOSURE  	6 1	; 0x7fad94413d10
	52	[1252]	GETUPVAL 	0 4	; self
	53	[1252]	SETTABLE 	5 -19 6	; "cancel_callback" -
	54	[1241]	CALL     	3 3 0
	55	[1241]	CALL     	1 0 1
	56	[1254]	RETURN   	0 1
	57	[1254]	JMP      	6	; to 64
	58	[1256]	GETUPVAL 	1 4	; self
	59	[1256]	SELF     	1 1 -20	; "multiswipeAction"
	60	[1256]	GETTABLE 	3 0 -21	; "multiswipe_directions"
	61	[1256]	MOVE     	4 0
	62	[1256]	TAILCALL 	1 4 0
	63	[1256]	RETURN   	1 0
	64	[1260]	GETUPVAL 	1 4	; self
	65	[1260]	SELF     	1 1 -22	; "gestureAction"
	66	[1260]	GETUPVAL 	3 9	; action
	67	[1260]	MOVE     	4 0
	68	[1260]	TAILCALL 	1 4 0
	69	[1260]	RETURN   	1 0
	70	[1261]	RETURN   	0 1

function <./frontend/apps/reader/modules/readergesture.lua:1244,1247> (8 instructions, 32 bytes at 0x7fad94412c70)
0 params, 4 slots, 1 upvalue, 0 locals, 4 constants, 0 functions
	1	[1245]	GETGLOBAL	0 -1	; G_reader_settings
	2	[1245]	SELF     	0 0 -2	; "saveSetting"
	3	[1245]	LOADK    	2 -3	; "multiswipes_enabled"
	4	[1245]	LOADBOOL 	3 1 0
	5	[1245]	CALL     	0 4 1
	6	[1246]	GETUPVAL 	0 0	; self
	7	[1246]	SETTABLE 	0 -3 -4	; "multiswipes_enabled" true
	8	[1247]	RETURN   	0 1

function <./frontend/apps/reader/modules/readergesture.lua:1249,1252> (8 instructions, 32 bytes at 0x7fad94413d10)
0 params, 4 slots, 1 upvalue, 0 locals, 4 constants, 0 functions
	1	[1250]	GETGLOBAL	0 -1	; G_reader_settings
	2	[1250]	SELF     	0 0 -2	; "saveSetting"
	3	[1250]	LOADK    	2 -3	; "multiswipes_enabled"
	4	[1250]	LOADBOOL 	3 0 0
	5	[1250]	CALL     	0 4 1
	6	[1251]	GETUPVAL 	0 0	; self
	7	[1251]	SETTABLE 	0 -3 -4	; "multiswipes_enabled" false
	8	[1252]	RETURN   	0 1

function <./frontend/apps/reader/modules/readergesture.lua:1267,1269> (11 instructions, 44 bytes at 0x7fad94417a20)
0 params, 3 slots, 1 upvalue, 0 locals, 4 constants, 0 functions
	1	[1268]	GETUPVAL 	0 0	; Device
	2	[1268]	SELF     	0 0 -1	; "hasLightLevelFallback"
	3	[1268]	CALL     	0 2 2
	4	[1268]	TEST     	0 0 0
	5	[1268]	JMP      	4	; to 10
	6	[1268]	GETGLOBAL	0 -2	; G_reader_settings
	7	[1268]	SELF     	0 0 -3	; "nilOrTrue"
	8	[1268]	LOADK    	2 -4	; "light_fallback"
	9	[1268]	CALL     	0 3 2
	10	[1268]	RETURN   	0 2
	11	[1269]	RETURN   	0 1

function <./frontend/apps/reader/modules/readergesture.lua:1271,1585> (1162 instructions, 4648 bytes at 0x7fad94410b90)
3 params, 13 slots, 12 upvalues, 17 locals, 223 constants, 3 functions
	1	[1272]	EQ       	1 1 -1	; - "ignore"
	2	[1272]	JMP      	6	; to 9
	3	[1273]	GETTABLE 	3 2 -2	; "ges"
	4	[1273]	EQ       	0 3 -3	; - "hold"
	5	[1273]	JMP      	5	; to 11
	6	[1273]	GETTABLE 	3 0 -4	; "ignore_hold_corners"
	7	[1273]	TEST     	3 0 0
	8	[1273]	JMP      	2	; to 11
	9	[1274]	RETURN   	0 1
	10	[1274]	JMP      	1149	; to 1160
	11	[1275]	EQ       	0 1 -5	; - "reading_progress"
	12	[1275]	JMP      	11	; to 24
	13	[1275]	GETUPVAL 	3 0	; ReaderGesture
	14	[1275]	GETTABLE 	3 3 -6	; "getReaderProgress"
	15	[1275]	TEST     	3 0 0
	16	[1275]	JMP      	7	; to 24
	17	[1276]	GETUPVAL 	3 1	; UIManager
	18	[1276]	SELF     	3 3 -7	; "show"
	19	[1276]	GETUPVAL 	5 0	; ReaderGesture
	20	[1276]	GETTABLE 	5 5 -6	; "getReaderProgress"
	21	[1276]	CALL     	5 1 0
	22	[1276]	CALL     	3 0 1
	23	[1276]	JMP      	1136	; to 1160
	24	[1277]	EQ       	0 1 -8	; - "book_statistics"
	25	[1277]	JMP      	11	; to 37
	26	[1277]	GETUPVAL 	3 0	; ReaderGesture
	27	[1277]	GETTABLE 	3 3 -9	; "getBookStats"
	28	[1277]	TEST     	3 0 0
	29	[1277]	JMP      	7	; to 37
	30	[1278]	GETUPVAL 	3 1	; UIManager
	31	[1278]	SELF     	3 3 -7	; "show"
	32	[1278]	GETUPVAL 	5 0	; ReaderGesture
	33	[1278]	GETTABLE 	5 5 -9	; "getBookStats"
	34	[1278]	CALL     	5 1 0
	35	[1278]	CALL     	3 0 1
	36	[1278]	JMP      	1123	; to 1160
	37	[1279]	EQ       	0 1 -10	; - "stats_calendar_view"
	38	[1279]	JMP      	11	; to 50
	39	[1279]	GETUPVAL 	3 0	; ReaderGesture
	40	[1279]	GETTABLE 	3 3 -11	; "getCalendarView"
	41	[1279]	TEST     	3 0 0
	42	[1279]	JMP      	7	; to 50
	43	[1280]	GETUPVAL 	3 1	; UIManager
	44	[1280]	SELF     	3 3 -7	; "show"
	45	[1280]	GETUPVAL 	5 0	; ReaderGesture
	46	[1280]	GETTABLE 	5 5 -11	; "getCalendarView"
	47	[1280]	CALL     	5 1 0
	48	[1280]	CALL     	3 0 1
	49	[1280]	JMP      	1110	; to 1160
	50	[1281]	EQ       	0 1 -12	; - "toc"
	51	[1281]	JMP      	8	; to 60
	52	[1282]	GETTABLE 	3 0 -13	; "ui"
	53	[1282]	SELF     	3 3 -14	; "handleEvent"
	54	[1282]	GETUPVAL 	5 2	; Event
	55	[1282]	SELF     	5 5 -15	; "new"
	56	[1282]	LOADK    	7 -16	; "ShowToc"
	57	[1282]	CALL     	5 3 0
	58	[1282]	CALL     	3 0 1
	59	[1282]	JMP      	1100	; to 1160
	60	[1283]	EQ       	0 1 -17	; - "night_mode"
	61	[1283]	JMP      	18	; to 80
	62	[1284]	GETGLOBAL	3 -18	; G_reader_settings
	63	[1284]	SELF     	3 3 -19	; "isTrue"
	64	[1284]	LOADK    	5 -17	; "night_mode"
	65	[1284]	CALL     	3 3 2
	66	[1285]	GETUPVAL 	4 3	; Screen
	67	[1285]	SELF     	4 4 -20	; "toggleNightMode"
	68	[1285]	CALL     	4 2 1
	69	[1286]	GETUPVAL 	4 1	; UIManager
	70	[1286]	SELF     	4 4 -21	; "setDirty"
	71	[1286]	LOADK    	6 -22	; "all"
	72	[1286]	LOADK    	7 -23	; "full"
	73	[1286]	CALL     	4 4 1
	74	[1287]	GETGLOBAL	4 -18	; G_reader_settings
	75	[1287]	SELF     	4 4 -24	; "saveSetting"
	76	[1287]	LOADK    	6 -17	; "night_mode"
	77	[1287]	NOT      	7 3
	78	[1287]	CALL     	4 4 1
	79	[1287]	JMP      	1080	; to 1160
	80	[1288]	EQ       	0 1 -25	; - "full_refresh"
	81	[1288]	JMP      	13	; to 95
	82	[1289]	GETTABLE 	3 0 -26	; "view"
	83	[1289]	TEST     	3 0 0
	84	[1289]	JMP      	4	; to 89
	85	[1291]	GETTABLE 	3 0 -26	; "view"
	86	[1291]	GETTABLE 	3 3 -27	; "footer"
	87	[1291]	SELF     	3 3 -28	; "updateFooter"
	88	[1291]	CALL     	3 2 1
	89	[1293]	GETUPVAL 	3 1	; UIManager
	90	[1293]	SELF     	3 3 -21	; "setDirty"
	91	[1293]	LOADK    	5 -22	; "all"
	92	[1293]	LOADK    	6 -23	; "full"
	93	[1293]	CALL     	3 4 1
	94	[1293]	JMP      	1065	; to 1160
	95	[1294]	EQ       	0 1 -29	; - "bookmarks"
	96	[1294]	JMP      	8	; to 105
	97	[1295]	GETTABLE 	3 0 -13	; "ui"
	98	[1295]	SELF     	3 3 -14	; "handleEvent"
	99	[1295]	GETUPVAL 	5 2	; Event
	100	[1295]	SELF     	5 5 -15	; "new"
	101	[1295]	LOADK    	7 -30	; "ShowBookmark"
	102	[1295]	CALL     	5 3 0
	103	[1295]	CALL     	3 0 1
	104	[1295]	JMP      	1055	; to 1160
	105	[1296]	EQ       	0 1 -31	; - "history"
	106	[1296]	JMP      	8	; to 115
	107	[1297]	GETTABLE 	3 0 -13	; "ui"
	108	[1297]	SELF     	3 3 -14	; "handleEvent"
	109	[1297]	GETUPVAL 	5 2	; Event
	110	[1297]	SELF     	5 5 -15	; "new"
	111	[1297]	LOADK    	7 -32	; "ShowHist"
	112	[1297]	CALL     	5 3 0
	113	[1297]	CALL     	3 0 1
	114	[1297]	JMP      	1045	; to 1160
	115	[1298]	EQ       	0 1 -33	; - "favorites"
	116	[1298]	JMP      	9	; to 126
	117	[1299]	GETTABLE 	3 0 -13	; "ui"
	118	[1299]	SELF     	3 3 -14	; "handleEvent"
	119	[1299]	GETUPVAL 	5 2	; Event
	120	[1299]	SELF     	5 5 -15	; "new"
	121	[1299]	LOADK    	7 -34	; "ShowColl"
	122	[1299]	LOADK    	8 -33	; "favorites"
	123	[1299]	CALL     	5 4 0
	124	[1299]	CALL     	3 0 1
	125	[1299]	JMP      	1034	; to 1160
	126	[1300]	EQ       	0 1 -35	; - "book_info"
	127	[1300]	JMP      	8	; to 136
	128	[1301]	GETTABLE 	3 0 -13	; "ui"
	129	[1301]	SELF     	3 3 -14	; "handleEvent"
	130	[1301]	GETUPVAL 	5 2	; Event
	131	[1301]	SELF     	5 5 -15	; "new"
	132	[1301]	LOADK    	7 -36	; "ShowBookInfo"
	133	[1301]	CALL     	5 3 0
	134	[1301]	CALL     	3 0 1
	135	[1301]	JMP      	1024	; to 1160
	136	[1302]	EQ       	0 1 -37	; - "book_description"
	137	[1302]	JMP      	8	; to 146
	138	[1303]	GETTABLE 	3 0 -13	; "ui"
	139	[1303]	SELF     	3 3 -14	; "handleEvent"
	140	[1303]	GETUPVAL 	5 2	; Event
	141	[1303]	SELF     	5 5 -15	; "new"
	142	[1303]	LOADK    	7 -38	; "ShowBookDescription"
	143	[1303]	CALL     	5 3 0
	144	[1303]	CALL     	3 0 1
	145	[1303]	JMP      	1014	; to 1160
	146	[1304]	EQ       	0 1 -39	; - "book_cover"
	147	[1304]	JMP      	8	; to 156
	148	[1305]	GETTABLE 	3 0 -13	; "ui"
	149	[1305]	SELF     	3 3 -14	; "handleEvent"
	150	[1305]	GETUPVAL 	5 2	; Event
	151	[1305]	SELF     	5 5 -15	; "new"
	152	[1305]	LOADK    	7 -40	; "ShowBookCover"
	153	[1305]	CALL     	5 3 0
	154	[1305]	CALL     	3 0 1
	155	[1305]	JMP      	1004	; to 1160
	156	[1306]	EQ       	0 1 -41	; - "book_status"
	157	[1306]	JMP      	8	; to 166
	158	[1307]	GETTABLE 	3 0 -13	; "ui"
	159	[1307]	SELF     	3 3 -14	; "handleEvent"
	160	[1307]	GETUPVAL 	5 2	; Event
	161	[1307]	SELF     	5 5 -15	; "new"
	162	[1307]	LOADK    	7 -42	; "ShowBookStatus"
	163	[1307]	CALL     	5 3 0
	164	[1307]	CALL     	3 0 1
	165	[1307]	JMP      	994	; to 1160
	166	[1308]	EQ       	0 1 -43	; - "page_jmp_fwd_10"
	167	[1308]	JMP      	4	; to 172
	168	[1309]	SELF     	3 0 -44	; "pageUpdate"
	169	[1309]	LOADK    	5 -45	; 10
	170	[1309]	CALL     	3 3 1
	171	[1309]	JMP      	988	; to 1160
	172	[1310]	EQ       	0 1 -46	; - "page_jmp_fwd_1"
	173	[1310]	JMP      	9	; to 183
	174	[1311]	GETTABLE 	3 0 -13	; "ui"
	175	[1311]	SELF     	3 3 -14	; "handleEvent"
	176	[1311]	GETUPVAL 	5 2	; Event
	177	[1311]	SELF     	5 5 -15	; "new"
	178	[1311]	LOADK    	7 -47	; "GotoViewRel"
	179	[1311]	LOADK    	8 -48	; 1
	180	[1311]	CALL     	5 4 0
	181	[1311]	CALL     	3 0 1
	182	[1311]	JMP      	977	; to 1160
	183	[1312]	EQ       	0 1 -49	; - "page_jmp_back_10"
	184	[1312]	JMP      	4	; to 189
	185	[1313]	SELF     	3 0 -44	; "pageUpdate"
	186	[1313]	LOADK    	5 -50	; -10
	187	[1313]	CALL     	3 3 1
	188	[1313]	JMP      	971	; to 1160
	189	[1314]	EQ       	0 1 -51	; - "page_jmp_back_1"
	190	[1314]	JMP      	9	; to 200
	191	[1315]	GETTABLE 	3 0 -13	; "ui"
	192	[1315]	SELF     	3 3 -14	; "handleEvent"
	193	[1315]	GETUPVAL 	5 2	; Event
	194	[1315]	SELF     	5 5 -15	; "new"
	195	[1315]	LOADK    	7 -47	; "GotoViewRel"
	196	[1315]	LOADK    	8 -52	; -1
	197	[1315]	CALL     	5 4 0
	198	[1315]	CALL     	3 0 1
	199	[1315]	JMP      	960	; to 1160
	200	[1316]	EQ       	0 1 -53	; - "next_chapter"
	201	[1316]	JMP      	8	; to 210
	202	[1317]	GETTABLE 	3 0 -13	; "ui"
	203	[1317]	SELF     	3 3 -14	; "handleEvent"
	204	[1317]	GETUPVAL 	5 2	; Event
	205	[1317]	SELF     	5 5 -15	; "new"
	206	[1317]	LOADK    	7 -54	; "GotoNextChapter"
	207	[1317]	CALL     	5 3 0
	208	[1317]	CALL     	3 0 1
	209	[1317]	JMP      	950	; to 1160
	210	[1318]	EQ       	0 1 -55	; - "first_page"
	211	[1318]	JMP      	9	; to 221
	212	[1319]	GETTABLE 	3 0 -13	; "ui"
	213	[1319]	SELF     	3 3 -14	; "handleEvent"
	214	[1319]	GETUPVAL 	5 2	; Event
	215	[1319]	SELF     	5 5 -15	; "new"
	216	[1319]	LOADK    	7 -56	; "GotoPage"
	217	[1319]	LOADK    	8 -48	; 1
	218	[1319]	CALL     	5 4 0
	219	[1319]	CALL     	3 0 1
	220	[1319]	JMP      	939	; to 1160
	221	[1320]	EQ       	0 1 -57	; - "last_page"
	222	[1320]	JMP      	16	; to 239
	223	[1321]	GETTABLE 	3 0 -26	; "view"
	224	[1321]	GETTABLE 	3 3 -58	; "document"
	225	[1321]	TEST     	3 0 0
	226	[1321]	JMP      	933	; to 1160
	227	[1322]	GETTABLE 	3 0 -13	; "ui"
	228	[1322]	SELF     	3 3 -14	; "handleEvent"
	229	[1322]	GETUPVAL 	5 2	; Event
	230	[1322]	SELF     	5 5 -15	; "new"
	231	[1322]	LOADK    	7 -56	; "GotoPage"
	232	[1322]	GETTABLE 	8 0 -26	; "view"
	233	[1322]	GETTABLE 	8 8 -58	; "document"
	234	[1322]	SELF     	8 8 -59	; "getPageCount"
	235	[1322]	CALL     	8 2 0
	236	[1322]	CALL     	5 0 0
	237	[1322]	CALL     	3 0 1
	238	[1323]	JMP      	921	; to 1160
	239	[1324]	EQ       	0 1 -60	; - "prev_chapter"
	240	[1324]	JMP      	8	; to 249
	241	[1325]	GETTABLE 	3 0 -13	; "ui"
	242	[1325]	SELF     	3 3 -14	; "handleEvent"
	243	[1325]	GETUPVAL 	5 2	; Event
	244	[1325]	SELF     	5 5 -15	; "new"
	245	[1325]	LOADK    	7 -61	; "GotoPrevChapter"
	246	[1325]	CALL     	5 3 0
	247	[1325]	CALL     	3 0 1
	248	[1325]	JMP      	911	; to 1160
	249	[1326]	EQ       	0 1 -62	; - "next_bookmark"
	250	[1326]	JMP      	8	; to 259
	251	[1327]	GETTABLE 	3 0 -13	; "ui"
	252	[1327]	SELF     	3 3 -14	; "handleEvent"
	253	[1327]	GETUPVAL 	5 2	; Event
	254	[1327]	SELF     	5 5 -15	; "new"
	255	[1327]	LOADK    	7 -63	; "GotoNextBookmarkFromPage"
	256	[1327]	CALL     	5 3 0
	257	[1327]	CALL     	3 0 1
	258	[1327]	JMP      	901	; to 1160
	259	[1328]	EQ       	0 1 -64	; - "prev_bookmark"
	260	[1328]	JMP      	8	; to 269
	261	[1329]	GETTABLE 	3 0 -13	; "ui"
	262	[1329]	SELF     	3 3 -14	; "handleEvent"
	263	[1329]	GETUPVAL 	5 2	; Event
	264	[1329]	SELF     	5 5 -15	; "new"
	265	[1329]	LOADK    	7 -65	; "GotoPreviousBookmarkFromPage"
	266	[1329]	CALL     	5 3 0
	267	[1329]	CALL     	3 0 1
	268	[1329]	JMP      	891	; to 1160
	269	[1330]	EQ       	0 1 -66	; - "go_to"
	270	[1330]	JMP      	8	; to 279
	271	[1331]	GETTABLE 	3 0 -13	; "ui"
	272	[1331]	SELF     	3 3 -14	; "handleEvent"
	273	[1331]	GETUPVAL 	5 2	; Event
	274	[1331]	SELF     	5 5 -15	; "new"
	275	[1331]	LOADK    	7 -67	; "ShowGotoDialog"
	276	[1331]	CALL     	5 3 0
	277	[1331]	CALL     	3 0 1
	278	[1331]	JMP      	881	; to 1160
	279	[1332]	EQ       	0 1 -68	; - "skim"
	280	[1332]	JMP      	8	; to 289
	281	[1333]	GETTABLE 	3 0 -13	; "ui"
	282	[1333]	SELF     	3 3 -14	; "handleEvent"
	283	[1333]	GETUPVAL 	5 2	; Event
	284	[1333]	SELF     	5 5 -15	; "new"
	285	[1333]	LOADK    	7 -69	; "ShowSkimtoDialog"
	286	[1333]	CALL     	5 3 0
	287	[1333]	CALL     	3 0 1
	288	[1333]	JMP      	871	; to 1160
	289	[1334]	EQ       	0 1 -70	; - "back"
	290	[1334]	JMP      	8	; to 299
	291	[1335]	GETTABLE 	3 0 -13	; "ui"
	292	[1335]	SELF     	3 3 -14	; "handleEvent"
	293	[1335]	GETUPVAL 	5 2	; Event
	294	[1335]	SELF     	5 5 -15	; "new"
	295	[1335]	LOADK    	7 -71	; "Back"
	296	[1335]	CALL     	5 3 0
	297	[1335]	CALL     	3 0 1
	298	[1335]	JMP      	861	; to 1160
	299	[1336]	EQ       	0 1 -72	; - "previous_location"
	300	[1336]	JMP      	9	; to 310
	301	[1337]	GETTABLE 	3 0 -13	; "ui"
	302	[1337]	SELF     	3 3 -14	; "handleEvent"
	303	[1337]	GETUPVAL 	5 2	; Event
	304	[1337]	SELF     	5 5 -15	; "new"
	305	[1337]	LOADK    	7 -73	; "GoBackLink"
	306	[1337]	LOADBOOL 	8 1 0
	307	[1337]	CALL     	5 4 0
	308	[1337]	CALL     	3 0 1
	309	[1337]	JMP      	850	; to 1160
	310	[1338]	EQ       	0 1 -74	; - "latest_bookmark"
	311	[1338]	JMP      	8	; to 320
	312	[1339]	GETTABLE 	3 0 -13	; "ui"
	313	[1339]	SELF     	3 3 -14	; "handleEvent"
	314	[1339]	GETUPVAL 	5 2	; Event
	315	[1339]	SELF     	5 5 -15	; "new"
	316	[1339]	LOADK    	7 -75	; "GoToLatestBookmark"
	317	[1339]	CALL     	5 3 0
	318	[1339]	CALL     	3 0 1
	319	[1339]	JMP      	840	; to 1160
	320	[1340]	EQ       	0 1 -76	; - "follow_nearest_link"
	321	[1340]	JMP      	14	; to 336
	322	[1341]	GETTABLE 	3 0 -13	; "ui"
	323	[1341]	SELF     	3 3 -14	; "handleEvent"
	324	[1341]	GETUPVAL 	5 2	; Event
	325	[1341]	SELF     	5 5 -15	; "new"
	326	[1341]	LOADK    	7 -77	; "GoToPageLink"
	327	[1341]	MOVE     	8 2
	328	[1341]	LOADBOOL 	9 0 0
	329	[1341]	GETGLOBAL	10 -18	; G_reader_settings
	330	[1341]	SELF     	10 10 -19	; "isTrue"
	331	[1341]	LOADK    	12 -78	; "footnote_link_in_popup"
	332	[1341]	CALL     	10 3 0
	333	[1341]	CALL     	5 0 0
	334	[1341]	CALL     	3 0 1
	335	[1341]	JMP      	824	; to 1160
	336	[1342]	EQ       	0 1 -79	; - "follow_nearest_internal_link"
	337	[1342]	JMP      	14	; to 352
	338	[1343]	GETTABLE 	3 0 -13	; "ui"
	339	[1343]	SELF     	3 3 -14	; "handleEvent"
	340	[1343]	GETUPVAL 	5 2	; Event
	341	[1343]	SELF     	5 5 -15	; "new"
	342	[1343]	LOADK    	7 -77	; "GoToPageLink"
	343	[1343]	MOVE     	8 2
	344	[1343]	LOADBOOL 	9 1 0
	345	[1343]	GETGLOBAL	10 -18	; G_reader_settings
	346	[1343]	SELF     	10 10 -19	; "isTrue"
	347	[1343]	LOADK    	12 -78	; "footnote_link_in_popup"
	348	[1343]	CALL     	10 3 0
	349	[1343]	CALL     	5 0 0
	350	[1343]	CALL     	3 0 1
	351	[1343]	JMP      	808	; to 1160
	352	[1344]	EQ       	0 1 -80	; - "clear_location_history"
	353	[1344]	JMP      	9	; to 363
	354	[1345]	GETTABLE 	3 0 -13	; "ui"
	355	[1345]	SELF     	3 3 -14	; "handleEvent"
	356	[1345]	GETUPVAL 	5 2	; Event
	357	[1345]	SELF     	5 5 -15	; "new"
	358	[1345]	LOADK    	7 -81	; "ClearLocationStack"
	359	[1345]	LOADBOOL 	8 1 0
	360	[1345]	CALL     	5 4 0
	361	[1345]	CALL     	3 0 1
	362	[1345]	JMP      	797	; to 1160
	363	[1346]	EQ       	0 1 -82	; - "filemanager"
	364	[1346]	JMP      	7	; to 372
	365	[1347]	GETTABLE 	3 0 -13	; "ui"
	366	[1347]	SELF     	3 3 -83	; "onClose"
	367	[1347]	CALL     	3 2 1
	368	[1348]	GETTABLE 	3 0 -13	; "ui"
	369	[1348]	SELF     	3 3 -84	; "showFileManager"
	370	[1348]	CALL     	3 2 1
	371	[1348]	JMP      	788	; to 1160
	372	[1349]	EQ       	0 1 -85	; - "file_search"
	373	[1349]	JMP      	26	; to 400
	374	[1350]	GETTABLE 	3 0 -86	; "ges_mode"
	375	[1350]	EQ       	0 3 -87	; - "gesture_fm"
	376	[1350]	JMP      	11	; to 388
	377	[1351]	GETTABLE 	3 0 -13	; "ui"
	378	[1351]	SELF     	3 3 -14	; "handleEvent"
	379	[1351]	GETUPVAL 	5 2	; Event
	380	[1351]	SELF     	5 5 -15	; "new"
	381	[1351]	LOADK    	7 -88	; "ShowFileSearch"
	382	[1351]	GETTABLE 	8 0 -13	; "ui"
	383	[1351]	GETTABLE 	8 8 -89	; "file_chooser"
	384	[1351]	GETTABLE 	8 8 -90	; "path"
	385	[1351]	CALL     	5 4 0
	386	[1351]	CALL     	3 0 1
	387	[1351]	JMP      	772	; to 1160
	388	[1353]	GETTABLE 	3 0 -13	; "ui"
	389	[1353]	SELF     	3 3 -91	; "getLastDirFile"
	390	[1353]	CALL     	3 2 2
	391	[1354]	GETTABLE 	4 0 -13	; "ui"
	392	[1354]	SELF     	4 4 -14	; "handleEvent"
	393	[1354]	GETUPVAL 	6 2	; Event
	394	[1354]	SELF     	6 6 -15	; "new"
	395	[1354]	LOADK    	8 -88	; "ShowFileSearch"
	396	[1354]	MOVE     	9 3
	397	[1354]	CALL     	6 4 0
	398	[1354]	CALL     	4 0 1
	399	[1355]	JMP      	760	; to 1160
	400	[1356]	EQ       	0 1 -92	; - "folder_up"
	401	[1356]	JMP      	12	; to 414
	402	[1357]	GETTABLE 	3 0 -13	; "ui"
	403	[1357]	GETTABLE 	3 3 -89	; "file_chooser"
	404	[1357]	SELF     	3 3 -93	; "changeToPath"
	405	[1357]	GETGLOBAL	5 -94	; string
	406	[1357]	GETTABLE 	5 5 -95	; "format"
	407	[1357]	LOADK    	6 -96	; "%s/.."
	408	[1357]	GETTABLE 	7 0 -13	; "ui"
	409	[1357]	GETTABLE 	7 7 -89	; "file_chooser"
	410	[1357]	GETTABLE 	7 7 -90	; "path"
	411	[1357]	CALL     	5 3 0
	412	[1357]	CALL     	3 0 1
	413	[1357]	JMP      	746	; to 1160
	414	[1358]	EQ       	0 1 -97	; - "show_plus_menu"
	415	[1358]	JMP      	8	; to 424
	416	[1359]	GETTABLE 	3 0 -13	; "ui"
	417	[1359]	SELF     	3 3 -14	; "handleEvent"
	418	[1359]	GETUPVAL 	5 2	; Event
	419	[1359]	SELF     	5 5 -15	; "new"
	420	[1359]	LOADK    	7 -98	; "ShowPlusMenu"
	421	[1359]	CALL     	5 3 0
	422	[1359]	CALL     	3 0 1
	423	[1359]	JMP      	736	; to 1160
	424	[1360]	EQ       	0 1 -99	; - "folder_shortcuts"
	425	[1360]	JMP      	8	; to 434
	426	[1361]	GETTABLE 	3 0 -13	; "ui"
	427	[1361]	SELF     	3 3 -14	; "handleEvent"
	428	[1361]	GETUPVAL 	5 2	; Event
	429	[1361]	SELF     	5 5 -15	; "new"
	430	[1361]	LOADK    	7 -100	; "ShowFolderShortcutsDialog"
	431	[1361]	CALL     	5 3 0
	432	[1361]	CALL     	3 0 1
	433	[1361]	JMP      	726	; to 1160
	434	[1362]	EQ       	0 1 -101	; - "open_previous_document"
	435	[1362]	JMP      	32	; to 468
	436	[1364]	GETTABLE 	3 0 -13	; "ui"
	437	[1364]	GETTABLE 	3 3 -102	; "menu"
	438	[1364]	GETTABLE 	3 3 -103	; "openLastDoc"
	439	[1364]	TEST     	3 0 0
	440	[1364]	JMP      	11	; to 452
	441	[1364]	GETGLOBAL	3 -18	; G_reader_settings
	442	[1364]	SELF     	3 3 -104	; "readSetting"
	443	[1364]	LOADK    	5 -105	; "lastfile"
	444	[1364]	CALL     	3 3 2
	445	[1364]	EQ       	1 3 -106	; - nil
	446	[1364]	JMP      	5	; to 452
	447	[1365]	GETTABLE 	3 0 -13	; "ui"
	448	[1365]	GETTABLE 	3 3 -102	; "menu"
	449	[1365]	SELF     	3 3 -103	; "openLastDoc"
	450	[1365]	CALL     	3 2 1
	451	[1365]	JMP      	708	; to 1160
	452	[1367]	GETTABLE 	3 0 -13	; "ui"
	453	[1367]	GETTABLE 	3 3 -107	; "switchDocument"
	454	[1367]	TEST     	3 0 0
	455	[1367]	JMP      	704	; to 1160
	456	[1367]	GETTABLE 	3 0 -13	; "ui"
	457	[1367]	GETTABLE 	3 3 -102	; "menu"
	458	[1367]	TEST     	3 0 0
	459	[1367]	JMP      	700	; to 1160
	460	[1368]	GETTABLE 	3 0 -13	; "ui"
	461	[1368]	SELF     	3 3 -107	; "switchDocument"
	462	[1368]	GETTABLE 	5 0 -13	; "ui"
	463	[1368]	GETTABLE 	5 5 -102	; "menu"
	464	[1368]	SELF     	5 5 -108	; "getPreviousFile"
	465	[1368]	CALL     	5 2 0
	466	[1368]	CALL     	3 0 1
	467	[1369]	JMP      	692	; to 1160
	468	[1370]	EQ       	0 1 -109	; - "dictionary_lookup"
	469	[1370]	JMP      	8	; to 478
	470	[1371]	GETTABLE 	3 0 -13	; "ui"
	471	[1371]	SELF     	3 3 -14	; "handleEvent"
	472	[1371]	GETUPVAL 	5 2	; Event
	473	[1371]	SELF     	5 5 -15	; "new"
	474	[1371]	LOADK    	7 -110	; "ShowDictionaryLookup"
	475	[1371]	CALL     	5 3 0
	476	[1371]	CALL     	3 0 1
	477	[1371]	JMP      	682	; to 1160
	478	[1372]	EQ       	0 1 -111	; - "wikipedia_lookup"
	479	[1372]	JMP      	8	; to 488
	480	[1373]	GETTABLE 	3 0 -13	; "ui"
	481	[1373]	SELF     	3 3 -14	; "handleEvent"
	482	[1373]	GETUPVAL 	5 2	; Event
	483	[1373]	SELF     	5 5 -15	; "new"
	484	[1373]	LOADK    	7 -112	; "ShowWikipediaLookup"
	485	[1373]	CALL     	5 3 0
	486	[1373]	CALL     	3 0 1
	487	[1373]	JMP      	672	; to 1160
	488	[1374]	EQ       	0 1 -113	; - "fulltext_search"
	489	[1374]	JMP      	8	; to 498
	490	[1375]	GETTABLE 	3 0 -13	; "ui"
	491	[1375]	SELF     	3 3 -14	; "handleEvent"
	492	[1375]	GETUPVAL 	5 2	; Event
	493	[1375]	SELF     	5 5 -15	; "new"
	494	[1375]	LOADK    	7 -114	; "ShowFulltextSearchInput"
	495	[1375]	CALL     	5 3 0
	496	[1375]	CALL     	3 0 1
	497	[1375]	JMP      	662	; to 1160
	498	[1376]	EQ       	0 1 -115	; - "show_menu"
	499	[1376]	JMP      	19	; to 519
	500	[1377]	GETTABLE 	3 0 -86	; "ges_mode"
	501	[1377]	EQ       	0 3 -87	; - "gesture_fm"
	502	[1377]	JMP      	8	; to 511
	503	[1378]	GETTABLE 	3 0 -13	; "ui"
	504	[1378]	SELF     	3 3 -14	; "handleEvent"
	505	[1378]	GETUPVAL 	5 2	; Event
	506	[1378]	SELF     	5 5 -15	; "new"
	507	[1378]	LOADK    	7 -116	; "ShowMenu"
	508	[1378]	CALL     	5 3 0
	509	[1378]	CALL     	3 0 1
	510	[1378]	JMP      	649	; to 1160
	511	[1380]	GETTABLE 	3 0 -13	; "ui"
	512	[1380]	SELF     	3 3 -14	; "handleEvent"
	513	[1380]	GETUPVAL 	5 2	; Event
	514	[1380]	SELF     	5 5 -15	; "new"
	515	[1380]	LOADK    	7 -117	; "ShowReaderMenu"
	516	[1380]	CALL     	5 3 0
	517	[1380]	CALL     	3 0 1
	518	[1381]	JMP      	641	; to 1160
	519	[1382]	EQ       	0 1 -118	; - "show_config_menu"
	520	[1382]	JMP      	8	; to 529
	521	[1383]	GETTABLE 	3 0 -13	; "ui"
	522	[1383]	SELF     	3 3 -14	; "handleEvent"
	523	[1383]	GETUPVAL 	5 2	; Event
	524	[1383]	SELF     	5 5 -15	; "new"
	525	[1383]	LOADK    	7 -119	; "ShowConfigMenu"
	526	[1383]	CALL     	5 3 0
	527	[1383]	CALL     	3 0 1
	528	[1383]	JMP      	631	; to 1160
	529	[1384]	EQ       	0 1 -120	; - "show_frontlight_dialog"
	530	[1384]	JMP      	17	; to 548
	531	[1385]	GETTABLE 	3 0 -86	; "ges_mode"
	532	[1385]	EQ       	0 3 -87	; - "gesture_fm"
	533	[1385]	JMP      	6	; to 540
	534	[1386]	GETGLOBAL	3 -121	; require
	535	[1386]	LOADK    	4 -122	; "apps/reader/modules/readerfrontlight"
	536	[1386]	CALL     	3 2 2
	537	[1387]	SELF     	4 3 -123	; "onShowFlDialog"
	538	[1387]	CALL     	4 2 1
	539	[1387]	JMP      	620	; to 1160
	540	[1389]	GETTABLE 	3 0 -13	; "ui"
	541	[1389]	SELF     	3 3 -14	; "handleEvent"
	542	[1389]	GETUPVAL 	5 2	; Event
	543	[1389]	SELF     	5 5 -15	; "new"
	544	[1389]	LOADK    	7 -124	; "ShowFlDialog"
	545	[1389]	CALL     	5 3 0
	546	[1389]	CALL     	3 0 1
	547	[1390]	JMP      	612	; to 1160
	548	[1391]	EQ       	0 1 -125	; - "increase_frontlight"
	549	[1391]	JMP      	39	; to 589
	550	[1393]	GETUPVAL 	3 4	; lightFrontlight
	551	[1393]	CALL     	3 1 2
	552	[1393]	TEST     	3 0 0
	553	[1393]	JMP      	14	; to 568
	554	[1394]	GETUPVAL 	3 1	; UIManager
	555	[1394]	SELF     	3 3 -7	; "show"
	556	[1394]	GETUPVAL 	5 5	; Notification
	557	[1394]	SELF     	5 5 -15	; "new"
	558	[1394]	NEWTABLE 	7 0 2
	559	[1395]	GETUPVAL 	8 6	; _
	560	[1395]	LOADK    	9 -127	; "Frontlight controlled by system settings."
	561	[1395]	CALL     	8 2 2
	562	[1395]	SETTABLE 	7 -126 8	; "text" -
	563	[1396]	SETTABLE 	7 -128 -129	; "timeout" 2.5
	564	[1394]	CALL     	5 3 0
	565	[1394]	CALL     	3 0 1
	566	[1398]	LOADBOOL 	3 1 0
	567	[1398]	RETURN   	3 2
	568	[1400]	GETTABLE 	3 0 -86	; "ges_mode"
	569	[1400]	EQ       	0 3 -87	; - "gesture_fm"
	570	[1400]	JMP      	8	; to 579
	571	[1401]	GETGLOBAL	3 -121	; require
	572	[1401]	LOADK    	4 -122	; "apps/reader/modules/readerfrontlight"
	573	[1401]	CALL     	3 2 2
	574	[1402]	SELF     	4 3 -130	; "onChangeFlIntensity"
	575	[1402]	MOVE     	6 2
	576	[1402]	LOADK    	7 -48	; 1
	577	[1402]	CALL     	4 4 1
	578	[1402]	JMP      	581	; to 1160
	579	[1404]	GETTABLE 	3 0 -13	; "ui"
	580	[1404]	SELF     	3 3 -14	; "handleEvent"
	581	[1404]	GETUPVAL 	5 2	; Event
	582	[1404]	SELF     	5 5 -15	; "new"
	583	[1404]	LOADK    	7 -131	; "ChangeFlIntensity"
	584	[1404]	MOVE     	8 2
	585	[1404]	LOADK    	9 -48	; 1
	586	[1404]	CALL     	5 5 0
	587	[1404]	CALL     	3 0 1
	588	[1405]	JMP      	571	; to 1160
	589	[1406]	EQ       	0 1 -132	; - "decrease_frontlight"
	590	[1406]	JMP      	39	; to 630
	591	[1408]	GETUPVAL 	3 4	; lightFrontlight
	592	[1408]	CALL     	3 1 2
	593	[1408]	TEST     	3 0 0
	594	[1408]	JMP      	14	; to 609
	595	[1409]	GETUPVAL 	3 1	; UIManager
	596	[1409]	SELF     	3 3 -7	; "show"
	597	[1409]	GETUPVAL 	5 5	; Notification
	598	[1409]	SELF     	5 5 -15	; "new"
	599	[1409]	NEWTABLE 	7 0 2
	600	[1410]	GETUPVAL 	8 6	; _
	601	[1410]	LOADK    	9 -127	; "Frontlight controlled by system settings."
	602	[1410]	CALL     	8 2 2
	603	[1410]	SETTABLE 	7 -126 8	; "text" -
	604	[1411]	SETTABLE 	7 -128 -129	; "timeout" 2.5
	605	[1409]	CALL     	5 3 0
	606	[1409]	CALL     	3 0 1
	607	[1413]	LOADBOOL 	3 1 0
	608	[1413]	RETURN   	3 2
	609	[1415]	GETTABLE 	3 0 -86	; "ges_mode"
	610	[1415]	EQ       	0 3 -87	; - "gesture_fm"
	611	[1415]	JMP      	8	; to 620
	612	[1416]	GETGLOBAL	3 -121	; require
	613	[1416]	LOADK    	4 -122	; "apps/reader/modules/readerfrontlight"
	614	[1416]	CALL     	3 2 2
	615	[1417]	SELF     	4 3 -130	; "onChangeFlIntensity"
	616	[1417]	MOVE     	6 2
	617	[1417]	LOADK    	7 -52	; -1
	618	[1417]	CALL     	4 4 1
	619	[1417]	JMP      	540	; to 1160
	620	[1419]	GETTABLE 	3 0 -13	; "ui"
	621	[1419]	SELF     	3 3 -14	; "handleEvent"
	622	[1419]	GETUPVAL 	5 2	; Event
	623	[1419]	SELF     	5 5 -15	; "new"
	624	[1419]	LOADK    	7 -131	; "ChangeFlIntensity"
	625	[1419]	MOVE     	8 2
	626	[1419]	LOADK    	9 -52	; -1
	627	[1419]	CALL     	5 5 0
	628	[1419]	CALL     	3 0 1
	629	[1420]	JMP      	530	; to 1160
	630	[1421]	EQ       	0 1 -133	; - "increase_frontlight_warmth"
	631	[1421]	JMP      	21	; to 653
	632	[1422]	GETTABLE 	3 0 -86	; "ges_mode"
	633	[1422]	EQ       	0 3 -87	; - "gesture_fm"
	634	[1422]	JMP      	8	; to 643
	635	[1423]	GETGLOBAL	3 -121	; require
	636	[1423]	LOADK    	4 -122	; "apps/reader/modules/readerfrontlight"
	637	[1423]	CALL     	3 2 2
	638	[1424]	SELF     	4 3 -134	; "onChangeFlWarmth"
	639	[1424]	MOVE     	6 2
	640	[1424]	LOADK    	7 -48	; 1
	641	[1424]	CALL     	4 4 1
	642	[1424]	JMP      	517	; to 1160
	643	[1426]	GETTABLE 	3 0 -13	; "ui"
	644	[1426]	SELF     	3 3 -14	; "handleEvent"
	645	[1426]	GETUPVAL 	5 2	; Event
	646	[1426]	SELF     	5 5 -15	; "new"
	647	[1426]	LOADK    	7 -135	; "ChangeFlWarmth"
	648	[1426]	MOVE     	8 2
	649	[1426]	LOADK    	9 -48	; 1
	650	[1426]	CALL     	5 5 0
	651	[1426]	CALL     	3 0 1
	652	[1427]	JMP      	507	; to 1160
	653	[1428]	EQ       	0 1 -136	; - "decrease_frontlight_warmth"
	654	[1428]	JMP      	21	; to 676
	655	[1429]	GETTABLE 	3 0 -86	; "ges_mode"
	656	[1429]	EQ       	0 3 -87	; - "gesture_fm"
	657	[1429]	JMP      	8	; to 666
	658	[1430]	GETGLOBAL	3 -121	; require
	659	[1430]	LOADK    	4 -122	; "apps/reader/modules/readerfrontlight"
	660	[1430]	CALL     	3 2 2
	661	[1431]	SELF     	4 3 -134	; "onChangeFlWarmth"
	662	[1431]	MOVE     	6 2
	663	[1431]	LOADK    	7 -52	; -1
	664	[1431]	CALL     	4 4 1
	665	[1431]	JMP      	494	; to 1160
	666	[1433]	GETTABLE 	3 0 -13	; "ui"
	667	[1433]	SELF     	3 3 -14	; "handleEvent"
	668	[1433]	GETUPVAL 	5 2	; Event
	669	[1433]	SELF     	5 5 -15	; "new"
	670	[1433]	LOADK    	7 -135	; "ChangeFlWarmth"
	671	[1433]	MOVE     	8 2
	672	[1433]	LOADK    	9 -52	; -1
	673	[1433]	CALL     	5 5 0
	674	[1433]	CALL     	3 0 1
	675	[1434]	JMP      	484	; to 1160
	676	[1435]	EQ       	0 1 -137	; - "toggle_bookmark"
	677	[1435]	JMP      	8	; to 686
	678	[1436]	GETTABLE 	3 0 -13	; "ui"
	679	[1436]	SELF     	3 3 -14	; "handleEvent"
	680	[1436]	GETUPVAL 	5 2	; Event
	681	[1436]	SELF     	5 5 -15	; "new"
	682	[1436]	LOADK    	7 -138	; "ToggleBookmark"
	683	[1436]	CALL     	5 3 0
	684	[1436]	CALL     	3 0 1
	685	[1436]	JMP      	474	; to 1160
	686	[1437]	EQ       	0 1 -139	; - "toggle_inverse_reading_order"
	687	[1437]	JMP      	3	; to 691
	688	[1438]	SELF     	3 0 -140	; "onToggleReadingOrder"
	689	[1438]	CALL     	3 2 1
	690	[1438]	JMP      	469	; to 1160
	691	[1439]	EQ       	0 1 -141	; - "toggle_frontlight"
	692	[1439]	JMP      	26	; to 719
	693	[1441]	GETUPVAL 	3 4	; lightFrontlight
	694	[1441]	CALL     	3 1 2
	695	[1441]	TEST     	3 0 0
	696	[1441]	JMP      	14	; to 711
	697	[1442]	GETUPVAL 	3 1	; UIManager
	698	[1442]	SELF     	3 3 -7	; "show"
	699	[1442]	GETUPVAL 	5 5	; Notification
	700	[1442]	SELF     	5 5 -15	; "new"
	701	[1442]	NEWTABLE 	7 0 2
	702	[1443]	GETUPVAL 	8 6	; _
	703	[1443]	LOADK    	9 -127	; "Frontlight controlled by system settings."
	704	[1443]	CALL     	8 2 2
	705	[1443]	SETTABLE 	7 -126 8	; "text" -
	706	[1444]	SETTABLE 	7 -128 -129	; "timeout" 2.5
	707	[1442]	CALL     	5 3 0
	708	[1442]	CALL     	3 0 1
	709	[1446]	LOADBOOL 	3 1 0
	710	[1446]	RETURN   	3 2
	711	[1448]	GETUPVAL 	3 7	; Device
	712	[1448]	SELF     	3 3 -142	; "getPowerDevice"
	713	[1448]	CALL     	3 2 2
	714	[1448]	SELF     	3 3 -143	; "toggleFrontlight"
	715	[1448]	CALL     	3 2 1
	716	[1449]	SELF     	3 0 -144	; "onShowFLOnOff"
	717	[1449]	CALL     	3 2 1
	718	[1449]	JMP      	441	; to 1160
	719	[1450]	EQ       	0 1 -145	; - "toggle_hold_corners"
	720	[1450]	JMP      	3	; to 724
	721	[1451]	SELF     	3 0 -146	; "onIgnoreHoldCorners"
	722	[1451]	CALL     	3 2 1
	723	[1451]	JMP      	436	; to 1160
	724	[1452]	EQ       	0 1 -147	; - "toggle_gsensor"
	725	[1452]	JMP      	15	; to 741
	726	[1453]	GETGLOBAL	3 -18	; G_reader_settings
	727	[1453]	SELF     	3 3 -148	; "flipNilOrFalse"
	728	[1453]	LOADK    	5 -149	; "input_ignore_gsensor"
	729	[1453]	CALL     	3 3 1
	730	[1454]	GETUPVAL 	3 7	; Device
	731	[1454]	SELF     	3 3 -150	; "toggleGSensor"
	732	[1454]	GETGLOBAL	5 -18	; G_reader_settings
	733	[1454]	SELF     	5 5 -19	; "isTrue"
	734	[1454]	LOADK    	7 -149	; "input_ignore_gsensor"
	735	[1454]	CALL     	5 3 2
	736	[1454]	NOT      	5 5
	737	[1454]	CALL     	3 3 1
	738	[1455]	SELF     	3 0 -151	; "onGSensorToggle"
	739	[1455]	CALL     	3 2 1
	740	[1455]	JMP      	419	; to 1160
	741	[1456]	EQ       	0 1 -152	; - "toggle_page_flipping"
	742	[1456]	JMP      	16	; to 759
	743	[1457]	GETTABLE 	3 0 -13	; "ui"
	744	[1457]	GETTABLE 	3 3 -58	; "document"
	745	[1457]	GETTABLE 	3 3 -153	; "info"
	746	[1457]	GETTABLE 	3 3 -154	; "has_pages"
	747	[1457]	TEST     	3 0 1
	748	[1457]	JMP      	2	; to 751
	749	[1461]	LOADBOOL 	3 0 0
	750	[1461]	RETURN   	3 2
	751	[1463]	GETTABLE 	3 0 -13	; "ui"
	752	[1463]	SELF     	3 3 -14	; "handleEvent"
	753	[1463]	GETUPVAL 	5 2	; Event
	754	[1463]	SELF     	5 5 -15	; "new"
	755	[1463]	LOADK    	7 -155	; "TogglePageFlipping"
	756	[1463]	CALL     	5 3 0
	757	[1463]	CALL     	3 0 1
	758	[1463]	JMP      	401	; to 1160
	759	[1464]	EQ       	0 1 -156	; - "toggle_reflow"
	760	[1464]	JMP      	40	; to 801
	761	[1465]	GETTABLE 	3 0 -58	; "document"
	762	[1465]	GETTABLE 	3 3 -153	; "info"
	763	[1465]	GETTABLE 	3 3 -154	; "has_pages"
	764	[1465]	TEST     	3 0 1
	765	[1465]	JMP      	1	; to 767
	766	[1465]	RETURN   	0 1
	767	[1466]	GETTABLE 	3 0 -58	; "document"
	768	[1466]	GETTABLE 	3 3 -157	; "configurable"
	769	[1466]	GETTABLE 	3 3 -158	; "text_wrap"
	770	[1466]	EQ       	0 3 -48	; - 1
	771	[1466]	JMP      	4	; to 776
	772	[1467]	GETTABLE 	3 0 -58	; "document"
	773	[1467]	GETTABLE 	3 3 -157	; "configurable"
	774	[1467]	SETTABLE 	3 -158 -159	; "text_wrap" 0
	775	[1467]	JMP      	3	; to 779
	776	[1469]	GETTABLE 	3 0 -58	; "document"
	777	[1469]	GETTABLE 	3 3 -157	; "configurable"
	778	[1469]	SETTABLE 	3 -158 -48	; "text_wrap" 1
	779	[1471]	GETTABLE 	3 0 -13	; "ui"
	780	[1471]	SELF     	3 3 -14	; "handleEvent"
	781	[1471]	GETUPVAL 	5 2	; Event
	782	[1471]	SELF     	5 5 -15	; "new"
	783	[1471]	LOADK    	7 -160	; "RedrawCurrentPage"
	784	[1471]	CALL     	5 3 0
	785	[1471]	CALL     	3 0 1
	786	[1472]	GETTABLE 	3 0 -13	; "ui"
	787	[1472]	SELF     	3 3 -14	; "handleEvent"
	788	[1472]	GETUPVAL 	5 2	; Event
	789	[1472]	SELF     	5 5 -15	; "new"
	790	[1472]	LOADK    	7 -161	; "RestoreZoomMode"
	791	[1472]	CALL     	5 3 0
	792	[1472]	CALL     	3 0 1
	793	[1473]	GETTABLE 	3 0 -13	; "ui"
	794	[1473]	SELF     	3 3 -14	; "handleEvent"
	795	[1473]	GETUPVAL 	5 2	; Event
	796	[1473]	SELF     	5 5 -15	; "new"
	797	[1473]	LOADK    	7 -162	; "InitScrollPageStates"
	798	[1473]	CALL     	5 3 0
	799	[1473]	CALL     	3 0 1
	800	[1473]	JMP      	359	; to 1160
	801	[1474]	EQ       	0 1 -163	; - "toggle_rotation"
	802	[1474]	JMP      	27	; to 830
	803	[1475]	GETTABLE 	3 0 -58	; "document"
	804	[1475]	GETTABLE 	3 3 -153	; "info"
	805	[1475]	GETTABLE 	3 3 -154	; "has_pages"
	806	[1475]	TEST     	3 0 0
	807	[1475]	JMP      	3	; to 811
	808	[1475]	LOADK    	3 -164	; "SwapScreenMode"
	809	[1475]	TEST     	3 0 1
	810	[1475]	JMP      	1	; to 812
	811	[1475]	LOADK    	3 -165	; "ChangeScreenMode"
	812	[1476]	GETUPVAL 	4 3	; Screen
	813	[1476]	SELF     	4 4 -166	; "getScreenMode"
	814	[1476]	CALL     	4 2 2
	815	[1476]	EQ       	0 4 -167	; - "portrait"
	816	[1476]	JMP      	3	; to 820
	817	[1476]	LOADK    	4 -168	; "landscape"
	818	[1476]	TEST     	4 0 1
	819	[1476]	JMP      	1	; to 821
	820	[1476]	LOADK    	4 -167	; "portrait"
	821	[1477]	GETTABLE 	5 0 -13	; "ui"
	822	[1477]	SELF     	5 5 -14	; "handleEvent"
	823	[1477]	GETUPVAL 	7 2	; Event
	824	[1477]	SELF     	7 7 -15	; "new"
	825	[1477]	MOVE     	9 3
	826	[1477]	MOVE     	10 4
	827	[1477]	CALL     	7 4 0
	828	[1477]	CALL     	5 0 1
	829	[1477]	JMP      	330	; to 1160
	830	[1478]	EQ       	0 1 -169	; - "toggle_wifi"
	831	[1478]	JMP      	37	; to 869
	832	[1479]	GETGLOBAL	3 -121	; require
	833	[1479]	LOADK    	4 -170	; "ui/network/manager"
	834	[1479]	CALL     	3 2 2
	835	[1481]	SELF     	4 3 -171	; "isOnline"
	836	[1481]	CALL     	4 2 2
	837	[1481]	TEST     	4 0 1
	838	[1481]	JMP      	15	; to 854
	839	[1482]	GETUPVAL 	4 1	; UIManager
	840	[1482]	SELF     	4 4 -7	; "show"
	841	[1482]	GETUPVAL 	6 8	; InfoMessage
	842	[1482]	SELF     	6 6 -15	; "new"
	843	[1482]	NEWTABLE 	8 0 2
	844	[1483]	GETUPVAL 	9 6	; _
	845	[1483]	LOADK    	10 -172	; "Turning on Wi-Fi\226\128\166"
	846	[1483]	CALL     	9 2 2
	847	[1483]	SETTABLE 	8 -126 9	; "text" -
	848	[1484]	SETTABLE 	8 -128 -48	; "timeout" 1
	849	[1482]	CALL     	6 3 0
	850	[1482]	CALL     	4 0 1
	851	[1489]	SELF     	4 3 -173	; "turnOnWifi"
	852	[1489]	CALL     	4 2 1
	853	[1489]	JMP      	306	; to 1160
	854	[1491]	SELF     	4 3 -174	; "turnOffWifi"
	855	[1491]	CALL     	4 2 1
	856	[1493]	GETUPVAL 	4 1	; UIManager
	857	[1493]	SELF     	4 4 -7	; "show"
	858	[1493]	GETUPVAL 	6 8	; InfoMessage
	859	[1493]	SELF     	6 6 -15	; "new"
	860	[1493]	NEWTABLE 	8 0 2
	861	[1494]	GETUPVAL 	9 6	; _
	862	[1494]	LOADK    	10 -175	; "Wi-Fi off."
	863	[1494]	CALL     	9 2 2
	864	[1494]	SETTABLE 	8 -126 9	; "text" -
	865	[1495]	SETTABLE 	8 -128 -48	; "timeout" 1
	866	[1493]	CALL     	6 3 0
	867	[1493]	CALL     	4 0 1
	868	[1497]	JMP      	291	; to 1160
	869	[1498]	EQ       	0 1 -176	; - "wifi_off"
	870	[1498]	JMP      	18	; to 889
	871	[1499]	GETGLOBAL	3 -121	; require
	872	[1499]	LOADK    	4 -170	; "ui/network/manager"
	873	[1499]	CALL     	3 2 2
	874	[1501]	SELF     	4 3 -174	; "turnOffWifi"
	875	[1501]	CALL     	4 2 1
	876	[1503]	GETUPVAL 	4 1	; UIManager
	877	[1503]	SELF     	4 4 -7	; "show"
	878	[1503]	GETUPVAL 	6 8	; InfoMessage
	879	[1503]	SELF     	6 6 -15	; "new"
	880	[1503]	NEWTABLE 	8 0 2
	881	[1504]	GETUPVAL 	9 6	; _
	882	[1504]	LOADK    	10 -175	; "Wi-Fi off."
	883	[1504]	CALL     	9 2 2
	884	[1504]	SETTABLE 	8 -126 9	; "text" -
	885	[1505]	SETTABLE 	8 -128 -48	; "timeout" 1
	886	[1503]	CALL     	6 3 0
	887	[1503]	CALL     	4 0 1
	888	[1506]	JMP      	271	; to 1160
	889	[1507]	EQ       	0 1 -177	; - "wifi_on"
	890	[1507]	JMP      	55	; to 946
	891	[1508]	GETGLOBAL	3 -121	; require
	892	[1508]	LOADK    	4 -170	; "ui/network/manager"
	893	[1508]	CALL     	3 2 2
	894	[1510]	SELF     	4 3 -171	; "isOnline"
	895	[1510]	CALL     	4 2 2
	896	[1510]	TEST     	4 0 1
	897	[1510]	JMP      	15	; to 913
	898	[1511]	GETUPVAL 	4 1	; UIManager
	899	[1511]	SELF     	4 4 -7	; "show"
	900	[1511]	GETUPVAL 	6 8	; InfoMessage
	901	[1511]	SELF     	6 6 -15	; "new"
	902	[1511]	NEWTABLE 	8 0 2
	903	[1512]	GETUPVAL 	9 6	; _
	904	[1512]	LOADK    	10 -178	; "Enabling wifi\226\128\166"
	905	[1512]	CALL     	9 2 2
	906	[1512]	SETTABLE 	8 -126 9	; "text" -
	907	[1513]	SETTABLE 	8 -128 -48	; "timeout" 1
	908	[1511]	CALL     	6 3 0
	909	[1511]	CALL     	4 0 1
	910	[1518]	SELF     	4 3 -173	; "turnOnWifi"
	911	[1518]	CALL     	4 2 1
	912	[1518]	JMP      	247	; to 1160
	913	[1520]	LOADNIL  	4 4
	914	[1521]	SELF     	5 3 -179	; "getCurrentNetwork"
	915	[1521]	CALL     	5 2 2
	916	[1523]	TEST     	5 0 0
	917	[1523]	JMP      	14	; to 932
	918	[1523]	GETTABLE 	6 5 -180	; "ssid"
	919	[1523]	TEST     	6 0 0
	920	[1523]	JMP      	11	; to 932
	921	[1524]	GETUPVAL 	6 9	; T
	922	[1524]	GETUPVAL 	7 6	; _
	923	[1524]	LOADK    	8 -181	; "Already connected to network %1."
	924	[1524]	CALL     	7 2 2
	925	[1524]	GETUPVAL 	8 10	; BD
	926	[1524]	GETTABLE 	8 8 -182	; "wrap"
	927	[1524]	GETTABLE 	9 5 -180	; "ssid"
	928	[1524]	CALL     	8 2 0
	929	[1524]	CALL     	6 0 2
	930	[1524]	MOVE     	4 6
	931	[1524]	JMP      	4	; to 936
	932	[1526]	GETUPVAL 	6 6	; _
	933	[1526]	LOADK    	7 -183	; "Already connected."
	934	[1526]	CALL     	6 2 2
	935	[1526]	MOVE     	4 6
	936	[1528]	GETUPVAL 	6 1	; UIManager
	937	[1528]	SELF     	6 6 -7	; "show"
	938	[1528]	GETUPVAL 	8 8	; InfoMessage
	939	[1528]	SELF     	8 8 -15	; "new"
	940	[1528]	NEWTABLE 	10 0 2
	941	[1529]	SETTABLE 	10 -126 4	; "text" -
	942	[1530]	SETTABLE 	10 -128 -48	; "timeout" 1
	943	[1528]	CALL     	8 3 0
	944	[1528]	CALL     	6 0 1
	945	[1532]	JMP      	214	; to 1160
	946	[1533]	EQ       	0 1 -184	; - "increase_font"
	947	[1533]	JMP      	10	; to 958
	948	[1534]	GETTABLE 	3 0 -13	; "ui"
	949	[1534]	SELF     	3 3 -14	; "handleEvent"
	950	[1534]	GETUPVAL 	5 2	; Event
	951	[1534]	SELF     	5 5 -15	; "new"
	952	[1534]	LOADK    	7 -185	; "AdjustFontSize"
	953	[1534]	MOVE     	8 2
	954	[1534]	LOADK    	9 -48	; 1
	955	[1534]	CALL     	5 5 0
	956	[1534]	CALL     	3 0 1
	957	[1534]	JMP      	202	; to 1160
	958	[1535]	EQ       	0 1 -186	; - "decrease_font"
	959	[1535]	JMP      	10	; to 970
	960	[1536]	GETTABLE 	3 0 -13	; "ui"
	961	[1536]	SELF     	3 3 -14	; "handleEvent"
	962	[1536]	GETUPVAL 	5 2	; Event
	963	[1536]	SELF     	5 5 -15	; "new"
	964	[1536]	LOADK    	7 -185	; "AdjustFontSize"
	965	[1536]	MOVE     	8 2
	966	[1536]	LOADK    	9 -52	; -1
	967	[1536]	CALL     	5 5 0
	968	[1536]	CALL     	3 0 1
	969	[1536]	JMP      	190	; to 1160
	970	[1537]	EQ       	0 1 -187	; - "suspend"
	971	[1537]	JMP      	4	; to 976
	972	[1538]	GETUPVAL 	3 1	; UIManager
	973	[1538]	SELF     	3 3 -187	; "suspend"
	974	[1538]	CALL     	3 2 1
	975	[1538]	JMP      	184	; to 1160
	976	[1539]	EQ       	0 1 -188	; - "exit"
	977	[1539]	JMP      	5	; to 983
	978	[1540]	GETTABLE 	3 0 -13	; "ui"
	979	[1540]	GETTABLE 	3 3 -102	; "menu"
	980	[1540]	SELF     	3 3 -189	; "exitOrRestart"
	981	[1540]	CALL     	3 2 1
	982	[1540]	JMP      	177	; to 1160
	983	[1541]	EQ       	0 1 -190	; - "restart"
	984	[1541]	JMP      	7	; to 992
	985	[1542]	GETTABLE 	3 0 -13	; "ui"
	986	[1542]	GETTABLE 	3 3 -102	; "menu"
	987	[1542]	SELF     	3 3 -189	; "exitOrRestart"
	988	[1542]	CLOSURE  	5 0	; 0x7fad944196b0
	989	[1542]	GETUPVAL 	0 1	; UIManager
	990	[1542]	CALL     	3 3 1
	991	[1542]	JMP      	168	; to 1160
	992	[1543]	EQ       	0 1 -191	; - "reboot"
	993	[1543]	JMP      	19	; to 1013
	994	[1544]	GETUPVAL 	3 1	; UIManager
	995	[1544]	SELF     	3 3 -7	; "show"
	996	[1544]	GETUPVAL 	5 11	; ConfirmBox
	997	[1544]	SELF     	5 5 -15	; "new"
	998	[1544]	NEWTABLE 	7 0 3
	999	[1545]	GETUPVAL 	8 6	; _
	1000	[1545]	LOADK    	9 -192	; "Are you sure you want to reboot the device?"
	1001	[1545]	CALL     	8 2 2
	1002	[1545]	SETTABLE 	7 -126 8	; "text" -
	1003	[1546]	GETUPVAL 	8 6	; _
	1004	[1546]	LOADK    	9 -194	; "Reboot"
	1005	[1546]	CALL     	8 2 2
	1006	[1546]	SETTABLE 	7 -193 8	; "ok_text" -
	1007	[1549]	CLOSURE  	8 1	; 0x7fad94419900
	1008	[1549]	GETUPVAL 	0 1	; UIManager
	1009	[1549]	SETTABLE 	7 -195 8	; "ok_callback" -
	1010	[1544]	CALL     	5 3 0
	1011	[1544]	CALL     	3 0 1
	1012	[1550]	JMP      	147	; to 1160
	1013	[1551]	EQ       	0 1 -196	; - "poweroff"
	1014	[1551]	JMP      	19	; to 1034
	1015	[1552]	GETUPVAL 	3 1	; UIManager
	1016	[1552]	SELF     	3 3 -7	; "show"
	1017	[1552]	GETUPVAL 	5 11	; ConfirmBox
	1018	[1552]	SELF     	5 5 -15	; "new"
	1019	[1552]	NEWTABLE 	7 0 3
	1020	[1553]	GETUPVAL 	8 6	; _
	1021	[1553]	LOADK    	9 -197	; "Are you sure you want to power off the device?"
	1022	[1553]	CALL     	8 2 2
	1023	[1553]	SETTABLE 	7 -126 8	; "text" -
	1024	[1554]	GETUPVAL 	8 6	; _
	1025	[1554]	LOADK    	9 -198	; "Power off"
	1026	[1554]	CALL     	8 2 2
	1027	[1554]	SETTABLE 	7 -193 8	; "ok_text" -
	1028	[1557]	CLOSURE  	8 2	; 0x7fad94419be0
	1029	[1557]	GETUPVAL 	0 1	; UIManager
	1030	[1557]	SETTABLE 	7 -195 8	; "ok_callback" -
	1031	[1552]	CALL     	5 3 0
	1032	[1552]	CALL     	3 0 1
	1033	[1558]	JMP      	126	; to 1160
	1034	[1559]	EQ       	0 1 -199	; - "zoom_contentwidth"
	1035	[1559]	JMP      	9	; to 1045
	1036	[1560]	GETTABLE 	3 0 -13	; "ui"
	1037	[1560]	SELF     	3 3 -14	; "handleEvent"
	1038	[1560]	GETUPVAL 	5 2	; Event
	1039	[1560]	SELF     	5 5 -15	; "new"
	1040	[1560]	LOADK    	7 -200	; "SetZoomMode"
	1041	[1560]	LOADK    	8 -201	; "contentwidth"
	1042	[1560]	CALL     	5 4 0
	1043	[1560]	CALL     	3 0 1
	1044	[1560]	JMP      	115	; to 1160
	1045	[1561]	EQ       	0 1 -202	; - "zoom_contentheight"
	1046	[1561]	JMP      	9	; to 1056
	1047	[1562]	GETTABLE 	3 0 -13	; "ui"
	1048	[1562]	SELF     	3 3 -14	; "handleEvent"
	1049	[1562]	GETUPVAL 	5 2	; Event
	1050	[1562]	SELF     	5 5 -15	; "new"
	1051	[1562]	LOADK    	7 -200	; "SetZoomMode"
	1052	[1562]	LOADK    	8 -203	; "contentheight"
	1053	[1562]	CALL     	5 4 0
	1054	[1562]	CALL     	3 0 1
	1055	[1562]	JMP      	104	; to 1160
	1056	[1563]	EQ       	0 1 -204	; - "zoom_pagewidth"
	1057	[1563]	JMP      	9	; to 1067
	1058	[1564]	GETTABLE 	3 0 -13	; "ui"
	1059	[1564]	SELF     	3 3 -14	; "handleEvent"
	1060	[1564]	GETUPVAL 	5 2	; Event
	1061	[1564]	SELF     	5 5 -15	; "new"
	1062	[1564]	LOADK    	7 -200	; "SetZoomMode"
	1063	[1564]	LOADK    	8 -205	; "pagewidth"
	1064	[1564]	CALL     	5 4 0
	1065	[1564]	CALL     	3 0 1
	1066	[1564]	JMP      	93	; to 1160
	1067	[1565]	EQ       	0 1 -206	; - "zoom_pageheight"
	1068	[1565]	JMP      	9	; to 1078
	1069	[1566]	GETTABLE 	3 0 -13	; "ui"
	1070	[1566]	SELF     	3 3 -14	; "handleEvent"
	1071	[1566]	GETUPVAL 	5 2	; Event
	1072	[1566]	SELF     	5 5 -15	; "new"
	1073	[1566]	LOADK    	7 -200	; "SetZoomMode"
	1074	[1566]	LOADK    	8 -207	; "pageheight"
	1075	[1566]	CALL     	5 4 0
	1076	[1566]	CALL     	3 0 1
	1077	[1566]	JMP      	82	; to 1160
	1078	[1567]	EQ       	0 1 -208	; - "zoom_column"
	1079	[1567]	JMP      	9	; to 1089
	1080	[1568]	GETTABLE 	3 0 -13	; "ui"
	1081	[1568]	SELF     	3 3 -14	; "handleEvent"
	1082	[1568]	GETUPVAL 	5 2	; Event
	1083	[1568]	SELF     	5 5 -15	; "new"
	1084	[1568]	LOADK    	7 -200	; "SetZoomMode"
	1085	[1568]	LOADK    	8 -209	; "column"
	1086	[1568]	CALL     	5 4 0
	1087	[1568]	CALL     	3 0 1
	1088	[1568]	JMP      	71	; to 1160
	1089	[1569]	EQ       	0 1 -210	; - "zoom_content"
	1090	[1569]	JMP      	9	; to 1100
	1091	[1570]	GETTABLE 	3 0 -13	; "ui"
	1092	[1570]	SELF     	3 3 -14	; "handleEvent"
	1093	[1570]	GETUPVAL 	5 2	; Event
	1094	[1570]	SELF     	5 5 -15	; "new"
	1095	[1570]	LOADK    	7 -200	; "SetZoomMode"
	1096	[1570]	LOADK    	8 -211	; "content"
	1097	[1570]	CALL     	5 4 0
	1098	[1570]	CALL     	3 0 1
	1099	[1570]	JMP      	60	; to 1160
	1100	[1571]	EQ       	0 1 -212	; - "zoom_page"
	1101	[1571]	JMP      	9	; to 1111
	1102	[1572]	GETTABLE 	3 0 -13	; "ui"
	1103	[1572]	SELF     	3 3 -14	; "handleEvent"
	1104	[1572]	GETUPVAL 	5 2	; Event
	1105	[1572]	SELF     	5 5 -15	; "new"
	1106	[1572]	LOADK    	7 -200	; "SetZoomMode"
	1107	[1572]	LOADK    	8 -213	; "page"
	1108	[1572]	CALL     	5 4 0
	1109	[1572]	CALL     	3 0 1
	1110	[1572]	JMP      	49	; to 1160
	1111	[1573]	EQ       	0 1 -214	; - "wallabag_download"
	1112	[1573]	JMP      	8	; to 1121
	1113	[1574]	GETTABLE 	3 0 -13	; "ui"
	1114	[1574]	SELF     	3 3 -14	; "handleEvent"
	1115	[1574]	GETUPVAL 	5 2	; Event
	1116	[1574]	SELF     	5 5 -15	; "new"
	1117	[1574]	LOADK    	7 -215	; "SynchronizeWallabag"
	1118	[1574]	CALL     	5 3 0
	1119	[1574]	CALL     	3 0 1
	1120	[1574]	JMP      	39	; to 1160
	1121	[1575]	EQ       	0 1 -216	; - "cycle_highlight_action"
	1122	[1575]	JMP      	8	; to 1131
	1123	[1576]	GETTABLE 	3 0 -13	; "ui"
	1124	[1576]	SELF     	3 3 -14	; "handleEvent"
	1125	[1576]	GETUPVAL 	5 2	; Event
	1126	[1576]	SELF     	5 5 -15	; "new"
	1127	[1576]	LOADK    	7 -217	; "CycleHighlightAction"
	1128	[1576]	CALL     	5 3 0
	1129	[1576]	CALL     	3 0 1
	1130	[1576]	JMP      	29	; to 1160
	1131	[1577]	EQ       	0 1 -218	; - "cycle_highlight_style"
	1132	[1577]	JMP      	8	; to 1141
	1133	[1578]	GETTABLE 	3 0 -13	; "ui"
	1134	[1578]	SELF     	3 3 -14	; "handleEvent"
	1135	[1578]	GETUPVAL 	5 2	; Event
	1136	[1578]	SELF     	5 5 -15	; "new"
	1137	[1578]	LOADK    	7 -219	; "CycleHighlightStyle"
	1138	[1578]	CALL     	5 3 0
	1139	[1578]	CALL     	3 0 1
	1140	[1578]	JMP      	19	; to 1160
	1141	[1579]	EQ       	0 1 -220	; - "kosync_push_progress"
	1142	[1579]	JMP      	8	; to 1151
	1143	[1580]	GETTABLE 	3 0 -13	; "ui"
	1144	[1580]	SELF     	3 3 -14	; "handleEvent"
	1145	[1580]	GETUPVAL 	5 2	; Event
	1146	[1580]	SELF     	5 5 -15	; "new"
	1147	[1580]	LOADK    	7 -221	; "KOSyncPushProgress"
	1148	[1580]	CALL     	5 3 0
	1149	[1580]	CALL     	3 0 1
	1150	[1580]	JMP      	9	; to 1160
	1151	[1581]	EQ       	0 1 -222	; - "kosync_pull_progress"
	1152	[1581]	JMP      	7	; to 1160
	1153	[1582]	GETTABLE 	3 0 -13	; "ui"
	1154	[1582]	SELF     	3 3 -14	; "handleEvent"
	1155	[1582]	GETUPVAL 	5 2	; Event
	1156	[1582]	SELF     	5 5 -15	; "new"
	1157	[1582]	LOADK    	7 -223	; "KOSyncPullProgress"
	1158	[1582]	CALL     	5 3 0
	1159	[1582]	CALL     	3 0 1
	1160	[1584]	LOADBOOL 	3 1 0
	1161	[1584]	RETURN   	3 2
	1162	[1585]	RETURN   	0 1

function <./frontend/apps/reader/modules/readergesture.lua:1542,1542> (4 instructions, 16 bytes at 0x7fad944196b0)
0 params, 2 slots, 1 upvalue, 0 locals, 1 constant, 0 functions
	1	[1542]	GETUPVAL 	0 0	; UIManager
	2	[1542]	SELF     	0 0 -1	; "restartKOReader"
	3	[1542]	CALL     	0 2 1
	4	[1542]	RETURN   	0 1

function <./frontend/apps/reader/modules/readergesture.lua:1547,1549> (6 instructions, 24 bytes at 0x7fad94419900)
0 params, 3 slots, 1 upvalue, 0 locals, 2 constants, 0 functions
	1	[1548]	GETUPVAL 	0 0	; UIManager
	2	[1548]	SELF     	0 0 -1	; "nextTick"
	3	[1548]	GETUPVAL 	2 0	; UIManager
	4	[1548]	GETTABLE 	2 2 -2	; "reboot_action"
	5	[1548]	CALL     	0 3 1
	6	[1549]	RETURN   	0 1

function <./frontend/apps/reader/modules/readergesture.lua:1555,1557> (6 instructions, 24 bytes at 0x7fad94419be0)
0 params, 3 slots, 1 upvalue, 0 locals, 2 constants, 0 functions
	1	[1556]	GETUPVAL 	0 0	; UIManager
	2	[1556]	SELF     	0 0 -1	; "nextTick"
	3	[1556]	GETUPVAL 	2 0	; UIManager
	4	[1556]	GETTABLE 	2 2 -2	; "poweroff_action"
	5	[1556]	CALL     	0 3 1
	6	[1557]	RETURN   	0 1

function <./frontend/apps/reader/modules/readergesture.lua:1587,1595> (24 instructions, 96 bytes at 0x7fad94419fe0)
3 params, 10 slots, 0 upvalues, 6 locals, 8 constants, 0 functions
	1	[1588]	GETTABLE 	3 0 -1	; "multiswipes_enabled"
	2	[1588]	TEST     	3 0 1
	3	[1588]	JMP      	1	; to 5
	4	[1588]	RETURN   	0 1
	5	[1589]	GETGLOBAL	3 -2	; G_reader_settings
	6	[1589]	SELF     	3 3 -3	; "readSetting"
	7	[1589]	GETTABLE 	5 0 -4	; "ges_mode"
	8	[1589]	CALL     	3 3 2
	9	[1590]	LOADK    	4 -5	; "multiswipe_"
	10	[1590]	SELF     	5 0 -6	; "safeMultiswipeName"
	11	[1590]	MOVE     	7 1
	12	[1590]	CALL     	5 3 2
	13	[1590]	CONCAT   	4 4 5
	14	[1591]	GETTABLE 	5 3 4
	15	[1592]	TEST     	5 0 0
	16	[1592]	JMP      	7	; to 24
	17	[1592]	EQ       	1 5 -7	; - "nothing"
	18	[1592]	JMP      	5	; to 24
	19	[1593]	SELF     	6 0 -8	; "gestureAction"
	20	[1593]	MOVE     	8 5
	21	[1593]	MOVE     	9 2
	22	[1593]	TAILCALL 	6 4 0
	23	[1593]	RETURN   	6 0
	24	[1595]	RETURN   	0 1

function <./frontend/apps/reader/modules/readergesture.lua:1597,1604> (17 instructions, 68 bytes at 0x7fad9441a390)
2 params, 9 slots, 1 upvalue, 3 locals, 5 constants, 0 functions
	1	[1598]	GETTABLE 	2 0 -1	; "ui"
	2	[1598]	SELF     	2 2 -2	; "getCurrentPage"
	3	[1598]	CALL     	2 2 2
	4	[1599]	TEST     	2 0 0
	5	[1599]	JMP      	11	; to 17
	6	[1599]	TEST     	1 0 0
	7	[1599]	JMP      	9	; to 17
	8	[1600]	ADD      	2 2 1
	9	[1601]	GETTABLE 	3 0 -1	; "ui"
	10	[1601]	SELF     	3 3 -3	; "handleEvent"
	11	[1601]	GETUPVAL 	5 0	; Event
	12	[1601]	SELF     	5 5 -4	; "new"
	13	[1601]	LOADK    	7 -5	; "GotoPage"
	14	[1601]	MOVE     	8 2
	15	[1601]	CALL     	5 4 0
	16	[1601]	CALL     	3 0 1
	17	[1604]	RETURN   	0 1

function <./frontend/apps/reader/modules/readergesture.lua:1606,1614> (20 instructions, 80 bytes at 0x7fad9441a980)
2 params, 6 slots, 0 upvalues, 2 locals, 6 constants, 0 functions
	1	[1607]	EQ       	0 1 -1	; - nil
	2	[1607]	JMP      	5	; to 8
	3	[1608]	GETGLOBAL	2 -2	; G_reader_settings
	4	[1608]	SELF     	2 2 -3	; "flipNilOrFalse"
	5	[1608]	LOADK    	4 -4	; "ignore_hold_corners"
	6	[1608]	CALL     	2 3 1
	7	[1608]	JMP      	5	; to 13
	8	[1610]	GETGLOBAL	2 -2	; G_reader_settings
	9	[1610]	SELF     	2 2 -5	; "saveSetting"
	10	[1610]	LOADK    	4 -4	; "ignore_hold_corners"
	11	[1610]	MOVE     	5 1
	12	[1610]	CALL     	2 4 1
	13	[1612]	GETGLOBAL	2 -2	; G_reader_settings
	14	[1612]	SELF     	2 2 -6	; "isTrue"
	15	[1612]	LOADK    	4 -4	; "ignore_hold_corners"
	16	[1612]	CALL     	2 3 2
	17	[1612]	SETTABLE 	0 -4 2	; "ignore_hold_corners" -
	18	[1613]	LOADBOOL 	2 1 0
	19	[1613]	RETURN   	2 2
	20	[1614]	RETURN   	0 1

function <./frontend/apps/reader/modules/readergesture.lua:1616,1629> (28 instructions, 112 bytes at 0x7fad9441ae60)
1 param, 8 slots, 4 upvalues, 3 locals, 9 constants, 0 functions
	1	[1617]	GETUPVAL 	1 0	; Device
	2	[1617]	SELF     	1 1 -1	; "getPowerDevice"
	3	[1617]	CALL     	1 2 2
	4	[1618]	LOADNIL  	2 2
	5	[1619]	GETTABLE 	3 1 -2	; "is_fl_on"
	6	[1619]	TEST     	3 0 0
	7	[1619]	JMP      	5	; to 13
	8	[1620]	GETUPVAL 	3 1	; _
	9	[1620]	LOADK    	4 -3	; "Frontlight on."
	10	[1620]	CALL     	3 2 2
	11	[1620]	MOVE     	2 3
	12	[1620]	JMP      	4	; to 17
	13	[1622]	GETUPVAL 	3 1	; _
	14	[1622]	LOADK    	4 -4	; "Frontlight off."
	15	[1622]	CALL     	3 2 2
	16	[1622]	MOVE     	2 3
	17	[1624]	GETUPVAL 	3 2	; UIManager
	18	[1624]	SELF     	3 3 -5	; "show"
	19	[1624]	GETUPVAL 	5 3	; Notification
	20	[1624]	SELF     	5 5 -6	; "new"
	21	[1624]	NEWTABLE 	7 0 2
	22	[1625]	SETTABLE 	7 -7 2	; "text" -
	23	[1626]	SETTABLE 	7 -8 -9	; "timeout" 1
	24	[1624]	CALL     	5 3 0
	25	[1624]	CALL     	3 0 1
	26	[1628]	LOADBOOL 	3 1 0
	27	[1628]	RETURN   	3 2
	28	[1629]	RETURN   	0 1

function <./frontend/apps/reader/modules/readergesture.lua:1631,1643> (27 instructions, 108 bytes at 0x7fad94414460)
1 param, 7 slots, 3 upvalues, 2 locals, 10 constants, 0 functions
	1	[1633]	GETGLOBAL	2 -1	; G_reader_settings
	2	[1633]	SELF     	2 2 -2	; "isTrue"
	3	[1633]	LOADK    	4 -3	; "input_ignore_gsensor"
	4	[1633]	CALL     	2 3 2
	5	[1633]	TEST     	2 0 0
	6	[1633]	JMP      	5	; to 12
	7	[1634]	GETUPVAL 	2 0	; _
	8	[1634]	LOADK    	3 -4	; "Accelerometer rotation events off."
	9	[1634]	CALL     	2 2 2
	10	[1634]	MOVE     	1 2
	11	[1634]	JMP      	4	; to 16
	12	[1636]	GETUPVAL 	2 0	; _
	13	[1636]	LOADK    	3 -5	; "Accelerometer rotation events on."
	14	[1636]	CALL     	2 2 2
	15	[1636]	MOVE     	1 2
	16	[1638]	GETUPVAL 	2 1	; UIManager
	17	[1638]	SELF     	2 2 -6	; "show"
	18	[1638]	GETUPVAL 	4 2	; Notification
	19	[1638]	SELF     	4 4 -7	; "new"
	20	[1638]	NEWTABLE 	6 0 2
	21	[1639]	SETTABLE 	6 -8 1	; "text" -
	22	[1640]	SETTABLE 	6 -9 -10	; "timeout" 1
	23	[1638]	CALL     	4 3 0
	24	[1638]	CALL     	2 0 1
	25	[1642]	LOADBOOL 	2 1 0
	26	[1642]	RETURN   	2 2
	27	[1643]	RETURN   	0 1

function <./frontend/apps/reader/modules/readergesture.lua:1645,1658> (46 instructions, 184 bytes at 0x7fad9441b4a0)
1 param, 10 slots, 4 upvalues, 3 locals, 16 constants, 0 functions
	1	[1646]	GETTABLE 	1 0 -1	; "ui"
	2	[1646]	GETTABLE 	1 1 -2	; "document"
	3	[1646]	GETTABLE 	1 1 -3	; "info"
	4	[1646]	GETTABLE 	1 1 -4	; "has_pages"
	5	[1646]	TEST     	1 0 0
	6	[1646]	JMP      	4	; to 11
	7	[1646]	GETTABLE 	1 0 -1	; "ui"
	8	[1646]	GETTABLE 	1 1 -5	; "paging"
	9	[1646]	TEST     	1 0 1
	10	[1646]	JMP      	2	; to 13
	11	[1646]	GETTABLE 	1 0 -1	; "ui"
	12	[1646]	GETTABLE 	1 1 -6	; "rolling"
	13	[1647]	GETTABLE 	2 1 -7	; "inverse_reading_order"
	14	[1647]	NOT      	2 2
	15	[1647]	SETTABLE 	1 -7 2	; "inverse_reading_order" -
	16	[1648]	SELF     	2 1 -8	; "setupTouchZones"
	17	[1648]	CALL     	2 2 1
	18	[1649]	GETUPVAL 	2 0	; BD
	19	[1649]	GETTABLE 	2 2 -9	; "mirroredUILayout"
	20	[1649]	CALL     	2 1 2
	21	[1650]	GETTABLE 	3 1 -7	; "inverse_reading_order"
	22	[1650]	TEST     	3 0 0
	23	[1650]	JMP      	1	; to 25
	24	[1651]	NOT      	2 2
	25	[1653]	GETUPVAL 	3 1	; UIManager
	26	[1653]	SELF     	3 3 -10	; "show"
	27	[1653]	GETUPVAL 	5 2	; Notification
	28	[1653]	SELF     	5 5 -11	; "new"
	29	[1653]	NEWTABLE 	7 0 2
	30	[1654]	TEST     	2 0 0
	31	[1654]	JMP      	5	; to 37
	32	[1654]	GETUPVAL 	8 3	; _
	33	[1654]	LOADK    	9 -13	; "RTL page turning."
	34	[1654]	CALL     	8 2 2
	35	[1654]	TEST     	8 0 1
	36	[1654]	JMP      	3	; to 40
	37	[1654]	GETUPVAL 	8 3	; _
	38	[1654]	LOADK    	9 -14	; "LTR page turning."
	39	[1654]	CALL     	8 2 2
	40	[1654]	SETTABLE 	7 -12 8	; "text" -
	41	[1655]	SETTABLE 	7 -15 -16	; "timeout" 2.5
	42	[1653]	CALL     	5 3 0
	43	[1653]	CALL     	3 0 1
	44	[1657]	LOADBOOL 	3 1 0
	45	[1657]	RETURN   	3 2
	46	[1658]	RETURN   	0 1
