
main <./spec/unit/readerlink_spec.lua:0,0> (5 instructions, 20 bytes at 0x7fdd36c068c0)
0+ params, 3 slots, 0 upvalues, 0 locals, 2 constants, 1 function
	1	[1]	GETGLOBAL	0 -1	; describe
	2	[1]	LOADK    	1 -2	; "ReaderLink module"
	3	[171]	CLOSURE  	2 0	; 0x7fdd36c06b60
	4	[1]	CALL     	0 3 1
	5	[171]	RETURN   	0 1

function <./spec/unit/readerlink_spec.lua:1,171> (69 instructions, 276 bytes at 0x7fdd36c06b60)
0 params, 9 slots, 0 upvalues, 6 locals, 9 constants, 8 functions
	1	[4]	GETGLOBAL	6 -1	; setup
	2	[14]	CLOSURE  	7 0	; 0x7fdd36c06d90
	3	[14]	MOVE     	0 0
	4	[14]	MOVE     	0 5
	5	[14]	MOVE     	0 1
	6	[14]	MOVE     	0 2
	7	[14]	MOVE     	0 3
	8	[14]	MOVE     	0 4
	9	[4]	CALL     	6 2 1
	10	[16]	GETGLOBAL	6 -2	; it
	11	[16]	LOADK    	7 -3	; "should jump to links in epub #nocov"
	12	[23]	CLOSURE  	8 1	; 0x7fdd36c07520
	13	[23]	MOVE     	0 1
	14	[23]	MOVE     	0 0
	15	[23]	MOVE     	0 3
	16	[16]	CALL     	6 3 1
	17	[25]	GETGLOBAL	6 -2	; it
	18	[25]	LOADK    	7 -4	; "should jump to links in pdf page mode"
	19	[36]	CLOSURE  	8 2	; 0x7fdd36c07a90
	20	[36]	MOVE     	0 2
	21	[36]	MOVE     	0 1
	22	[36]	MOVE     	0 0
	23	[36]	MOVE     	0 4
	24	[36]	MOVE     	0 5
	25	[25]	CALL     	6 3 1
	26	[38]	GETGLOBAL	6 -2	; it
	27	[38]	LOADK    	7 -5	; "should jump to links in pdf scroll mode"
	28	[53]	CLOSURE  	8 3	; 0x7fdd36c082d0
	29	[53]	MOVE     	0 2
	30	[53]	MOVE     	0 1
	31	[53]	MOVE     	0 0
	32	[53]	MOVE     	0 4
	33	[53]	MOVE     	0 5
	34	[38]	CALL     	6 3 1
	35	[55]	GETGLOBAL	6 -2	; it
	36	[55]	LOADK    	7 -6	; "should be able to go back after link jump in epub #nocov"
	37	[64]	CLOSURE  	8 4	; 0x7fdd36c07a10
	38	[64]	MOVE     	0 1
	39	[64]	MOVE     	0 0
	40	[64]	MOVE     	0 3
	41	[55]	CALL     	6 3 1
	42	[66]	GETGLOBAL	6 -2	; it
	43	[66]	LOADK    	7 -7	; "should be able to go back after link jump in pdf page mode"
	44	[79]	CLOSURE  	8 5	; 0x7fdd36c078e0
	45	[79]	MOVE     	0 2
	46	[79]	MOVE     	0 1
	47	[79]	MOVE     	0 0
	48	[79]	MOVE     	0 4
	49	[79]	MOVE     	0 5
	50	[66]	CALL     	6 3 1
	51	[81]	GETGLOBAL	6 -2	; it
	52	[81]	LOADK    	7 -8	; "should be able to go back after link jump in pdf scroll mode"
	53	[96]	CLOSURE  	8 6	; 0x7fdd36c08e50
	54	[96]	MOVE     	0 2
	55	[96]	MOVE     	0 1
	56	[96]	MOVE     	0 0
	57	[96]	MOVE     	0 4
	58	[96]	MOVE     	0 5
	59	[81]	CALL     	6 3 1
	60	[98]	GETGLOBAL	6 -2	; it
	61	[98]	LOADK    	7 -9	; "should be able to go back to the same position after link jump in pdf scroll mode"
	62	[170]	CLOSURE  	8 7	; 0x7fdd36c08020
	63	[170]	MOVE     	0 2
	64	[170]	MOVE     	0 4
	65	[170]	MOVE     	0 1
	66	[170]	MOVE     	0 0
	67	[170]	MOVE     	0 5
	68	[98]	CALL     	6 3 1
	69	[171]	RETURN   	0 1

function <./spec/unit/readerlink_spec.lua:4,14> (35 instructions, 140 bytes at 0x7fdd36c06d90)
0 params, 4 slots, 6 upvalues, 0 locals, 13 constants, 0 functions
	1	[5]	GETGLOBAL	0 -1	; require
	2	[5]	LOADK    	1 -2	; "commonrequire"
	3	[5]	CALL     	0 2 1
	4	[6]	GETGLOBAL	0 -3	; package
	5	[6]	GETTABLE 	0 0 -4	; "unloadAll"
	6	[6]	CALL     	0 1 1
	7	[7]	GETGLOBAL	0 -1	; require
	8	[7]	LOADK    	1 -5	; "document/canvascontext"
	9	[7]	CALL     	0 2 2
	10	[7]	SELF     	0 0 -6	; "init"
	11	[7]	GETGLOBAL	2 -1	; require
	12	[7]	LOADK    	3 -7	; "device"
	13	[7]	CALL     	2 2 0
	14	[7]	CALL     	0 0 1
	15	[8]	GETGLOBAL	0 -1	; require
	16	[8]	LOADK    	1 -8	; "document/documentregistry"
	17	[8]	CALL     	0 2 2
	18	[8]	SETUPVAL 	0 0	; DocumentRegistry
	19	[9]	GETGLOBAL	0 -1	; require
	20	[9]	LOADK    	1 -9	; "ui/event"
	21	[9]	CALL     	0 2 2
	22	[9]	SETUPVAL 	0 1	; Event
	23	[10]	GETGLOBAL	0 -1	; require
	24	[10]	LOADK    	1 -10	; "apps/reader/readerui"
	25	[10]	CALL     	0 2 2
	26	[10]	SETUPVAL 	0 2	; ReaderUI
	27	[11]	GETGLOBAL	0 -1	; require
	28	[11]	LOADK    	1 -11	; "ui/uimanager"
	29	[11]	CALL     	0 2 2
	30	[11]	SETUPVAL 	0 3	; UIManager
	31	[12]	LOADK    	0 -12	; "spec/front/unit/data/leaves.epub"
	32	[12]	SETUPVAL 	0 4	; sample_epub
	33	[13]	LOADK    	0 -13	; "spec/front/unit/data/paper.pdf"
	34	[13]	SETUPVAL 	0 5	; sample_pdf
	35	[14]	RETURN   	0 1

function <./spec/unit/readerlink_spec.lua:16,23> (30 instructions, 120 bytes at 0x7fdd36c07520)
0 params, 6 slots, 3 upvalues, 1 local, 18 constants, 0 functions
	1	[17]	GETUPVAL 	0 0	; ReaderUI
	2	[17]	SELF     	0 0 -1	; "new"
	3	[17]	NEWTABLE 	2 0 1
	4	[18]	GETUPVAL 	3 1	; DocumentRegistry
	5	[18]	SELF     	3 3 -3	; "openDocument"
	6	[18]	GETUPVAL 	5 2	; sample_epub
	7	[18]	CALL     	3 3 2
	8	[18]	SETTABLE 	2 -2 3	; "document" -
	9	[17]	CALL     	0 3 2
	10	[20]	GETTABLE 	1 0 -4	; "rolling"
	11	[20]	SELF     	1 1 -5	; "onGotoPage"
	12	[20]	LOADK    	3 -6	; 5
	13	[20]	CALL     	1 3 1
	14	[21]	GETTABLE 	1 0 -7	; "link"
	15	[21]	SELF     	1 1 -8	; "onTap"
	16	[21]	LOADNIL  	3 3
	17	[21]	NEWTABLE 	4 0 1
	18	[21]	NEWTABLE 	5 0 2
	19	[21]	SETTABLE 	5 -10 -11	; "x" 320
	20	[21]	SETTABLE 	5 -12 -13	; "y" 190
	21	[21]	SETTABLE 	4 -9 5	; "pos" -
	22	[21]	CALL     	1 4 1
	23	[22]	GETGLOBAL	1 -14	; assert
	24	[22]	GETTABLE 	1 1 -15	; "is"
	25	[22]	GETTABLE 	1 1 -16	; "same"
	26	[22]	LOADK    	2 -17	; 37
	27	[22]	GETTABLE 	3 0 -4	; "rolling"
	28	[22]	GETTABLE 	3 3 -18	; "current_page"
	29	[22]	CALL     	1 3 1
	30	[23]	RETURN   	0 1

function <./spec/unit/readerlink_spec.lua:25,36> (50 instructions, 200 bytes at 0x7fdd36c07a90)
0 params, 7 slots, 5 upvalues, 1 local, 24 constants, 0 functions
	1	[26]	GETUPVAL 	0 0	; UIManager
	2	[26]	SELF     	0 0 -1	; "quit"
	3	[26]	CALL     	0 2 1
	4	[27]	GETUPVAL 	0 1	; ReaderUI
	5	[27]	SELF     	0 0 -2	; "new"
	6	[27]	NEWTABLE 	2 0 1
	7	[28]	GETUPVAL 	3 2	; DocumentRegistry
	8	[28]	SELF     	3 3 -4	; "openDocument"
	9	[28]	GETUPVAL 	5 3	; sample_pdf
	10	[28]	CALL     	3 3 2
	11	[28]	SETTABLE 	2 -3 3	; "document" -
	12	[27]	CALL     	0 3 2
	13	[30]	SELF     	1 0 -5	; "handleEvent"
	14	[30]	GETUPVAL 	3 4	; Event
	15	[30]	SELF     	3 3 -2	; "new"
	16	[30]	LOADK    	5 -6	; "SetScrollMode"
	17	[30]	LOADBOOL 	6 0 0
	18	[30]	CALL     	3 4 0
	19	[30]	CALL     	1 0 1
	20	[31]	SELF     	1 0 -5	; "handleEvent"
	21	[31]	GETUPVAL 	3 4	; Event
	22	[31]	SELF     	3 3 -2	; "new"
	23	[31]	LOADK    	5 -7	; "SetZoomMode"
	24	[31]	LOADK    	6 -8	; "page"
	25	[31]	CALL     	3 4 0
	26	[31]	CALL     	1 0 1
	27	[32]	GETTABLE 	1 0 -9	; "paging"
	28	[32]	SELF     	1 1 -10	; "onGotoPage"
	29	[32]	LOADK    	3 -11	; 1
	30	[32]	CALL     	1 3 1
	31	[33]	GETTABLE 	1 0 -12	; "link"
	32	[33]	SELF     	1 1 -13	; "onTap"
	33	[33]	LOADNIL  	3 3
	34	[33]	NEWTABLE 	4 0 1
	35	[33]	NEWTABLE 	5 0 2
	36	[33]	SETTABLE 	5 -15 -16	; "x" 363
	37	[33]	SETTABLE 	5 -17 -18	; "y" 565
	38	[33]	SETTABLE 	4 -14 5	; "pos" -
	39	[33]	CALL     	1 4 1
	40	[34]	GETUPVAL 	1 0	; UIManager
	41	[34]	SELF     	1 1 -19	; "run"
	42	[34]	CALL     	1 2 1
	43	[35]	GETGLOBAL	1 -20	; assert
	44	[35]	GETTABLE 	1 1 -21	; "is"
	45	[35]	GETTABLE 	1 1 -22	; "same"
	46	[35]	LOADK    	2 -23	; 22
	47	[35]	GETTABLE 	3 0 -9	; "paging"
	48	[35]	GETTABLE 	3 3 -24	; "current_page"
	49	[35]	CALL     	1 3 1
	50	[36]	RETURN   	0 1

function <./spec/unit/readerlink_spec.lua:38,53> (63 instructions, 252 bytes at 0x7fdd36c082d0)
0 params, 7 slots, 5 upvalues, 1 local, 26 constants, 0 functions
	1	[39]	GETUPVAL 	0 0	; UIManager
	2	[39]	SELF     	0 0 -1	; "quit"
	3	[39]	CALL     	0 2 1
	4	[40]	GETUPVAL 	0 1	; ReaderUI
	5	[40]	SELF     	0 0 -2	; "new"
	6	[40]	NEWTABLE 	2 0 1
	7	[41]	GETUPVAL 	3 2	; DocumentRegistry
	8	[41]	SELF     	3 3 -4	; "openDocument"
	9	[41]	GETUPVAL 	5 3	; sample_pdf
	10	[41]	CALL     	3 3 2
	11	[41]	SETTABLE 	2 -3 3	; "document" -
	12	[40]	CALL     	0 3 2
	13	[43]	SELF     	1 0 -5	; "handleEvent"
	14	[43]	GETUPVAL 	3 4	; Event
	15	[43]	SELF     	3 3 -2	; "new"
	16	[43]	LOADK    	5 -6	; "SetScrollMode"
	17	[43]	LOADBOOL 	6 1 0
	18	[43]	CALL     	3 4 0
	19	[43]	CALL     	1 0 1
	20	[44]	SELF     	1 0 -5	; "handleEvent"
	21	[44]	GETUPVAL 	3 4	; Event
	22	[44]	SELF     	3 3 -2	; "new"
	23	[44]	LOADK    	5 -7	; "SetZoomMode"
	24	[44]	LOADK    	6 -8	; "page"
	25	[44]	CALL     	3 4 0
	26	[44]	CALL     	1 0 1
	27	[45]	GETTABLE 	1 0 -9	; "paging"
	28	[45]	SELF     	1 1 -10	; "onGotoPage"
	29	[45]	LOADK    	3 -11	; 1
	30	[45]	CALL     	1 3 1
	31	[46]	GETGLOBAL	1 -12	; assert
	32	[46]	GETTABLE 	1 1 -13	; "is"
	33	[46]	GETTABLE 	1 1 -14	; "same"
	34	[46]	LOADK    	2 -11	; 1
	35	[46]	GETTABLE 	3 0 -9	; "paging"
	36	[46]	GETTABLE 	3 3 -15	; "current_page"
	37	[46]	CALL     	1 3 1
	38	[47]	GETTABLE 	1 0 -16	; "link"
	39	[47]	SELF     	1 1 -17	; "onTap"
	40	[47]	LOADNIL  	3 3
	41	[47]	NEWTABLE 	4 0 1
	42	[47]	NEWTABLE 	5 0 2
	43	[47]	SETTABLE 	5 -19 -20	; "x" 228
	44	[47]	SETTABLE 	5 -21 -22	; "y" 534
	45	[47]	SETTABLE 	4 -18 5	; "pos" -
	46	[47]	CALL     	1 4 1
	47	[48]	GETUPVAL 	1 0	; UIManager
	48	[48]	SELF     	1 1 -23	; "run"
	49	[48]	CALL     	1 2 1
	50	[51]	GETGLOBAL	1 -12	; assert
	51	[51]	GETTABLE 	1 1 -24	; "truthy"
	52	[51]	GETTABLE 	2 0 -9	; "paging"
	53	[51]	GETTABLE 	2 2 -15	; "current_page"
	54	[51]	EQ       	1 2 -25	; - 21
	55	[51]	JMP      	5	; to 61
	56	[52]	GETTABLE 	2 0 -9	; "paging"
	57	[52]	GETTABLE 	2 2 -15	; "current_page"
	58	[52]	EQ       	1 2 -26	; - 20
	59	[52]	JMP      	1	; to 61
	60	[52]	LOADBOOL 	2 0 1
	61	[52]	LOADBOOL 	2 1 0
	62	[51]	CALL     	1 2 1
	63	[53]	RETURN   	0 1

function <./spec/unit/readerlink_spec.lua:55,64> (40 instructions, 160 bytes at 0x7fdd36c07a10)
0 params, 6 slots, 3 upvalues, 1 local, 19 constants, 0 functions
	1	[56]	GETUPVAL 	0 0	; ReaderUI
	2	[56]	SELF     	0 0 -1	; "new"
	3	[56]	NEWTABLE 	2 0 1
	4	[57]	GETUPVAL 	3 1	; DocumentRegistry
	5	[57]	SELF     	3 3 -3	; "openDocument"
	6	[57]	GETUPVAL 	5 2	; sample_epub
	7	[57]	CALL     	3 3 2
	8	[57]	SETTABLE 	2 -2 3	; "document" -
	9	[56]	CALL     	0 3 2
	10	[59]	GETTABLE 	1 0 -4	; "rolling"
	11	[59]	SELF     	1 1 -5	; "onGotoPage"
	12	[59]	LOADK    	3 -6	; 5
	13	[59]	CALL     	1 3 1
	14	[60]	GETTABLE 	1 0 -7	; "link"
	15	[60]	SELF     	1 1 -8	; "onTap"
	16	[60]	LOADNIL  	3 3
	17	[60]	NEWTABLE 	4 0 1
	18	[60]	NEWTABLE 	5 0 2
	19	[60]	SETTABLE 	5 -10 -11	; "x" 320
	20	[60]	SETTABLE 	5 -12 -13	; "y" 190
	21	[60]	SETTABLE 	4 -9 5	; "pos" -
	22	[60]	CALL     	1 4 1
	23	[61]	GETGLOBAL	1 -14	; assert
	24	[61]	GETTABLE 	1 1 -15	; "is"
	25	[61]	GETTABLE 	1 1 -16	; "same"
	26	[61]	LOADK    	2 -17	; 37
	27	[61]	GETTABLE 	3 0 -4	; "rolling"
	28	[61]	GETTABLE 	3 3 -18	; "current_page"
	29	[61]	CALL     	1 3 1
	30	[62]	GETTABLE 	1 0 -7	; "link"
	31	[62]	SELF     	1 1 -19	; "onGoBackLink"
	32	[62]	CALL     	1 2 1
	33	[63]	GETGLOBAL	1 -14	; assert
	34	[63]	GETTABLE 	1 1 -15	; "is"
	35	[63]	GETTABLE 	1 1 -16	; "same"
	36	[63]	LOADK    	2 -6	; 5
	37	[63]	GETTABLE 	3 0 -4	; "rolling"
	38	[63]	GETTABLE 	3 3 -18	; "current_page"
	39	[63]	CALL     	1 3 1
	40	[64]	RETURN   	0 1

function <./spec/unit/readerlink_spec.lua:66,79> (60 instructions, 240 bytes at 0x7fdd36c078e0)
0 params, 7 slots, 5 upvalues, 1 local, 25 constants, 0 functions
	1	[67]	GETUPVAL 	0 0	; UIManager
	2	[67]	SELF     	0 0 -1	; "quit"
	3	[67]	CALL     	0 2 1
	4	[68]	GETUPVAL 	0 1	; ReaderUI
	5	[68]	SELF     	0 0 -2	; "new"
	6	[68]	NEWTABLE 	2 0 1
	7	[69]	GETUPVAL 	3 2	; DocumentRegistry
	8	[69]	SELF     	3 3 -4	; "openDocument"
	9	[69]	GETUPVAL 	5 3	; sample_pdf
	10	[69]	CALL     	3 3 2
	11	[69]	SETTABLE 	2 -3 3	; "document" -
	12	[68]	CALL     	0 3 2
	13	[71]	SELF     	1 0 -5	; "handleEvent"
	14	[71]	GETUPVAL 	3 4	; Event
	15	[71]	SELF     	3 3 -2	; "new"
	16	[71]	LOADK    	5 -6	; "SetScrollMode"
	17	[71]	LOADBOOL 	6 0 0
	18	[71]	CALL     	3 4 0
	19	[71]	CALL     	1 0 1
	20	[72]	SELF     	1 0 -5	; "handleEvent"
	21	[72]	GETUPVAL 	3 4	; Event
	22	[72]	SELF     	3 3 -2	; "new"
	23	[72]	LOADK    	5 -7	; "SetZoomMode"
	24	[72]	LOADK    	6 -8	; "page"
	25	[72]	CALL     	3 4 0
	26	[72]	CALL     	1 0 1
	27	[73]	GETTABLE 	1 0 -9	; "paging"
	28	[73]	SELF     	1 1 -10	; "onGotoPage"
	29	[73]	LOADK    	3 -11	; 1
	30	[73]	CALL     	1 3 1
	31	[74]	GETTABLE 	1 0 -12	; "link"
	32	[74]	SELF     	1 1 -13	; "onTap"
	33	[74]	LOADNIL  	3 3
	34	[74]	NEWTABLE 	4 0 1
	35	[74]	NEWTABLE 	5 0 2
	36	[74]	SETTABLE 	5 -15 -16	; "x" 363
	37	[74]	SETTABLE 	5 -17 -18	; "y" 565
	38	[74]	SETTABLE 	4 -14 5	; "pos" -
	39	[74]	CALL     	1 4 1
	40	[75]	GETUPVAL 	1 0	; UIManager
	41	[75]	SELF     	1 1 -19	; "run"
	42	[75]	CALL     	1 2 1
	43	[76]	GETGLOBAL	1 -20	; assert
	44	[76]	GETTABLE 	1 1 -21	; "is"
	45	[76]	GETTABLE 	1 1 -22	; "same"
	46	[76]	LOADK    	2 -23	; 22
	47	[76]	GETTABLE 	3 0 -9	; "paging"
	48	[76]	GETTABLE 	3 3 -24	; "current_page"
	49	[76]	CALL     	1 3 1
	50	[77]	GETTABLE 	1 0 -12	; "link"
	51	[77]	SELF     	1 1 -25	; "onGoBackLink"
	52	[77]	CALL     	1 2 1
	53	[78]	GETGLOBAL	1 -20	; assert
	54	[78]	GETTABLE 	1 1 -21	; "is"
	55	[78]	GETTABLE 	1 1 -22	; "same"
	56	[78]	LOADK    	2 -11	; 1
	57	[78]	GETTABLE 	3 0 -9	; "paging"
	58	[78]	GETTABLE 	3 3 -24	; "current_page"
	59	[78]	CALL     	1 3 1
	60	[79]	RETURN   	0 1

function <./spec/unit/readerlink_spec.lua:81,96> (73 instructions, 292 bytes at 0x7fdd36c08e50)
0 params, 7 slots, 5 upvalues, 1 local, 27 constants, 0 functions
	1	[82]	GETUPVAL 	0 0	; UIManager
	2	[82]	SELF     	0 0 -1	; "quit"
	3	[82]	CALL     	0 2 1
	4	[83]	GETUPVAL 	0 1	; ReaderUI
	5	[83]	SELF     	0 0 -2	; "new"
	6	[83]	NEWTABLE 	2 0 1
	7	[84]	GETUPVAL 	3 2	; DocumentRegistry
	8	[84]	SELF     	3 3 -4	; "openDocument"
	9	[84]	GETUPVAL 	5 3	; sample_pdf
	10	[84]	CALL     	3 3 2
	11	[84]	SETTABLE 	2 -3 3	; "document" -
	12	[83]	CALL     	0 3 2
	13	[86]	SELF     	1 0 -5	; "handleEvent"
	14	[86]	GETUPVAL 	3 4	; Event
	15	[86]	SELF     	3 3 -2	; "new"
	16	[86]	LOADK    	5 -6	; "SetScrollMode"
	17	[86]	LOADBOOL 	6 1 0
	18	[86]	CALL     	3 4 0
	19	[86]	CALL     	1 0 1
	20	[87]	SELF     	1 0 -5	; "handleEvent"
	21	[87]	GETUPVAL 	3 4	; Event
	22	[87]	SELF     	3 3 -2	; "new"
	23	[87]	LOADK    	5 -7	; "SetZoomMode"
	24	[87]	LOADK    	6 -8	; "page"
	25	[87]	CALL     	3 4 0
	26	[87]	CALL     	1 0 1
	27	[88]	GETTABLE 	1 0 -9	; "paging"
	28	[88]	SELF     	1 1 -10	; "onGotoPage"
	29	[88]	LOADK    	3 -11	; 1
	30	[88]	CALL     	1 3 1
	31	[89]	GETGLOBAL	1 -12	; assert
	32	[89]	GETTABLE 	1 1 -13	; "is"
	33	[89]	GETTABLE 	1 1 -14	; "same"
	34	[89]	LOADK    	2 -11	; 1
	35	[89]	GETTABLE 	3 0 -9	; "paging"
	36	[89]	GETTABLE 	3 3 -15	; "current_page"
	37	[89]	CALL     	1 3 1
	38	[90]	GETTABLE 	1 0 -16	; "link"
	39	[90]	SELF     	1 1 -17	; "onTap"
	40	[90]	LOADNIL  	3 3
	41	[90]	NEWTABLE 	4 0 1
	42	[90]	NEWTABLE 	5 0 2
	43	[90]	SETTABLE 	5 -19 -20	; "x" 228
	44	[90]	SETTABLE 	5 -21 -22	; "y" 534
	45	[90]	SETTABLE 	4 -18 5	; "pos" -
	46	[90]	CALL     	1 4 1
	47	[91]	GETUPVAL 	1 0	; UIManager
	48	[91]	SELF     	1 1 -23	; "run"
	49	[91]	CALL     	1 2 1
	50	[92]	GETGLOBAL	1 -12	; assert
	51	[92]	GETTABLE 	1 1 -24	; "truthy"
	52	[92]	GETTABLE 	2 0 -9	; "paging"
	53	[92]	GETTABLE 	2 2 -15	; "current_page"
	54	[92]	EQ       	1 2 -25	; - 21
	55	[92]	JMP      	5	; to 61
	56	[93]	GETTABLE 	2 0 -9	; "paging"
	57	[93]	GETTABLE 	2 2 -15	; "current_page"
	58	[93]	EQ       	1 2 -26	; - 20
	59	[93]	JMP      	1	; to 61
	60	[93]	LOADBOOL 	2 0 1
	61	[93]	LOADBOOL 	2 1 0
	62	[92]	CALL     	1 2 1
	63	[94]	GETTABLE 	1 0 -16	; "link"
	64	[94]	SELF     	1 1 -27	; "onGoBackLink"
	65	[94]	CALL     	1 2 1
	66	[95]	GETGLOBAL	1 -12	; assert
	67	[95]	GETTABLE 	1 1 -13	; "is"
	68	[95]	GETTABLE 	1 1 -14	; "same"
	69	[95]	LOADK    	2 -11	; 1
	70	[95]	GETTABLE 	3 0 -9	; "paging"
	71	[95]	GETTABLE 	3 3 -15	; "current_page"
	72	[95]	CALL     	1 3 1
	73	[96]	RETURN   	0 1

function <./spec/unit/readerlink_spec.lua:98,170> (218 instructions, 872 bytes at 0x7fdd36c08020)
0 params, 8 slots, 5 upvalues, 2 locals, 58 constants, 0 functions
	1	[99]	GETUPVAL 	0 0	; UIManager
	2	[99]	SELF     	0 0 -1	; "quit"
	3	[99]	CALL     	0 2 1
	4	[100]	NEWTABLE 	0 2 0
	5	[100]	NEWTABLE 	1 0 7
	6	[102]	SETTABLE 	1 -2 -3	; "gamma" 1
	7	[103]	NEWTABLE 	2 0 2
	8	[103]	SETTABLE 	2 -5 -6	; "x" 0
	9	[103]	SETTABLE 	2 -7 -6	; "y" 0
	10	[103]	SETTABLE 	1 -4 2	; "offset" -
	11	[104]	SETTABLE 	1 -8 -9	; "page" 3
	12	[105]	NEWTABLE 	2 0 4
	13	[106]	SETTABLE 	2 -5 -6	; "x" 0
	14	[106]	SETTABLE 	2 -7 -6	; "y" 0
	15	[107]	SETTABLE 	2 -11 -12	; "h" 800
	16	[107]	SETTABLE 	2 -13 -14	; "w" 566
	17	[108]	SETTABLE 	1 -10 2	; "page_area" -
	18	[109]	SETTABLE 	1 -15 -6	; "rotation" 0
	19	[110]	NEWTABLE 	2 0 4
	20	[111]	SETTABLE 	2 -5 -6	; "x" 0
	21	[111]	SETTABLE 	2 -7 -17	; "y" 694
	22	[112]	SETTABLE 	2 -11 -18	; "h" 106
	23	[112]	SETTABLE 	2 -13 -14	; "w" 566
	24	[113]	SETTABLE 	1 -16 2	; "visible_area" -
	25	[114]	SETTABLE 	1 -19 -20	; "zoom" 0.95011876484561
	26	[115]	NEWTABLE 	2 0 7
	27	[117]	SETTABLE 	2 -2 -3	; "gamma" 1
	28	[118]	NEWTABLE 	3 0 2
	29	[118]	SETTABLE 	3 -5 -6	; "x" 0
	30	[118]	SETTABLE 	3 -7 -6	; "y" 0
	31	[118]	SETTABLE 	2 -4 3	; "offset" -
	32	[119]	SETTABLE 	2 -8 -21	; "page" 4
	33	[120]	NEWTABLE 	3 0 4
	34	[121]	SETTABLE 	3 -11 -12	; "h" 800
	35	[121]	SETTABLE 	3 -13 -14	; "w" 566
	36	[122]	SETTABLE 	3 -5 -6	; "x" 0
	37	[122]	SETTABLE 	3 -7 -6	; "y" 0
	38	[123]	SETTABLE 	2 -10 3	; "page_area" -
	39	[124]	SETTABLE 	2 -15 -6	; "rotation" 0
	40	[125]	NEWTABLE 	3 0 4
	41	[126]	SETTABLE 	3 -11 -22	; "h" 686
	42	[126]	SETTABLE 	3 -13 -14	; "w" 566
	43	[127]	SETTABLE 	3 -5 -6	; "x" 0
	44	[127]	SETTABLE 	3 -7 -6	; "y" 0
	45	[128]	SETTABLE 	2 -16 3	; "visible_area" -
	46	[129]	SETTABLE 	2 -19 -20	; "zoom" 0.95011876484561
	47	[131]	SETLIST  	0 2 1	; 1
	48	[133]	GETGLOBAL	1 -23	; G_reader_settings
	49	[133]	SELF     	1 1 -24	; "saveSetting"
	50	[133]	LOADK    	3 -25	; "reader_footer_mode"
	51	[133]	LOADK    	4 -6	; 0
	52	[133]	CALL     	1 4 1
	53	[134]	GETGLOBAL	1 -26	; require
	54	[134]	LOADK    	2 -27	; "docsettings"
	55	[134]	CALL     	1 2 2
	56	[134]	SELF     	1 1 -28	; "open"
	57	[134]	GETUPVAL 	3 1	; sample_pdf
	58	[134]	CALL     	1 3 2
	59	[134]	SELF     	1 1 -29	; "purge"
	60	[134]	CALL     	1 2 1
	61	[135]	GETUPVAL 	1 2	; ReaderUI
	62	[135]	SELF     	1 1 -30	; "new"
	63	[135]	NEWTABLE 	3 0 1
	64	[136]	GETUPVAL 	4 3	; DocumentRegistry
	65	[136]	SELF     	4 4 -32	; "openDocument"
	66	[136]	GETUPVAL 	6 1	; sample_pdf
	67	[136]	CALL     	4 3 2
	68	[136]	SETTABLE 	3 -31 4	; "document" -
	69	[135]	CALL     	1 3 2
	70	[138]	SELF     	2 1 -33	; "handleEvent"
	71	[138]	GETUPVAL 	4 4	; Event
	72	[138]	SELF     	4 4 -30	; "new"
	73	[138]	LOADK    	6 -34	; "SetZoomMode"
	74	[138]	LOADK    	7 -8	; "page"
	75	[138]	CALL     	4 4 0
	76	[138]	CALL     	2 0 1
	77	[139]	GETGLOBAL	2 -35	; assert
	78	[139]	GETTABLE 	2 2 -36	; "is"
	79	[139]	GETTABLE 	2 2 -37	; "falsy"
	80	[139]	GETTABLE 	3 1 -38	; "view"
	81	[139]	GETTABLE 	3 3 -39	; "footer_visible"
	82	[139]	CALL     	2 2 1
	83	[140]	GETTABLE 	2 1 -40	; "paging"
	84	[140]	SELF     	2 2 -41	; "onGotoPage"
	85	[140]	LOADK    	4 -3	; 1
	86	[140]	CALL     	2 3 1
	87	[141]	GETGLOBAL	2 -35	; assert
	88	[141]	GETTABLE 	2 2 -36	; "is"
	89	[141]	GETTABLE 	2 2 -42	; "same"
	90	[141]	LOADK    	3 -3	; 1
	91	[141]	GETTABLE 	4 1 -40	; "paging"
	92	[141]	GETTABLE 	4 4 -43	; "current_page"
	93	[141]	CALL     	2 3 1
	94	[142]	GETTABLE 	2 1 -38	; "view"
	95	[142]	SELF     	2 2 -44	; "onSetScrollMode"
	96	[142]	LOADBOOL 	4 1 0
	97	[142]	CALL     	2 3 1
	98	[143]	GETGLOBAL	2 -35	; assert
	99	[143]	GETTABLE 	2 2 -36	; "is"
	100	[143]	GETTABLE 	2 2 -42	; "same"
	101	[143]	LOADBOOL 	3 1 0
	102	[143]	GETTABLE 	4 1 -38	; "view"
	103	[143]	GETTABLE 	4 4 -45	; "page_scroll"
	104	[143]	CALL     	2 3 1
	105	[144]	GETGLOBAL	2 -35	; assert
	106	[144]	GETTABLE 	2 2 -36	; "is"
	107	[144]	GETTABLE 	2 2 -42	; "same"
	108	[144]	LOADK    	3 -3	; 1
	109	[144]	GETTABLE 	4 1 -40	; "paging"
	110	[144]	GETTABLE 	4 4 -43	; "current_page"
	111	[144]	CALL     	2 3 1
	112	[146]	GETTABLE 	2 1 -40	; "paging"
	113	[146]	SELF     	2 2 -46	; "onGotoViewRel"
	114	[146]	LOADK    	4 -3	; 1
	115	[146]	CALL     	2 3 1
	116	[147]	GETGLOBAL	2 -35	; assert
	117	[147]	GETTABLE 	2 2 -36	; "is"
	118	[147]	GETTABLE 	2 2 -42	; "same"
	119	[147]	LOADK    	3 -47	; 2
	120	[147]	GETTABLE 	4 1 -40	; "paging"
	121	[147]	GETTABLE 	4 4 -43	; "current_page"
	122	[147]	CALL     	2 3 1
	123	[149]	GETTABLE 	2 1 -40	; "paging"
	124	[149]	SELF     	2 2 -46	; "onGotoViewRel"
	125	[149]	LOADK    	4 -48	; -1
	126	[149]	CALL     	2 3 1
	127	[150]	GETGLOBAL	2 -35	; assert
	128	[150]	GETTABLE 	2 2 -36	; "is"
	129	[150]	GETTABLE 	2 2 -42	; "same"
	130	[150]	LOADK    	3 -3	; 1
	131	[150]	GETTABLE 	4 1 -40	; "paging"
	132	[150]	GETTABLE 	4 4 -43	; "current_page"
	133	[150]	CALL     	2 3 1
	134	[152]	GETTABLE 	2 1 -40	; "paging"
	135	[152]	SELF     	2 2 -46	; "onGotoViewRel"
	136	[152]	LOADK    	4 -3	; 1
	137	[152]	CALL     	2 3 1
	138	[153]	GETTABLE 	2 1 -40	; "paging"
	139	[153]	SELF     	2 2 -46	; "onGotoViewRel"
	140	[153]	LOADK    	4 -3	; 1
	141	[153]	CALL     	2 3 1
	142	[154]	GETGLOBAL	2 -35	; assert
	143	[154]	GETTABLE 	2 2 -36	; "is"
	144	[154]	GETTABLE 	2 2 -42	; "same"
	145	[154]	LOADK    	3 -9	; 3
	146	[154]	GETTABLE 	4 1 -40	; "paging"
	147	[154]	GETTABLE 	4 4 -43	; "current_page"
	148	[154]	CALL     	2 3 1
	149	[156]	GETTABLE 	2 1 -40	; "paging"
	150	[156]	SELF     	2 2 -46	; "onGotoViewRel"
	151	[156]	LOADK    	4 -48	; -1
	152	[156]	CALL     	2 3 1
	153	[157]	GETGLOBAL	2 -35	; assert
	154	[157]	GETTABLE 	2 2 -36	; "is"
	155	[157]	GETTABLE 	2 2 -42	; "same"
	156	[157]	LOADK    	3 -47	; 2
	157	[157]	GETTABLE 	4 1 -40	; "paging"
	158	[157]	GETTABLE 	4 4 -43	; "current_page"
	159	[157]	CALL     	2 3 1
	160	[159]	GETTABLE 	2 1 -40	; "paging"
	161	[159]	SELF     	2 2 -46	; "onGotoViewRel"
	162	[159]	LOADK    	4 -3	; 1
	163	[159]	CALL     	2 3 1
	164	[160]	GETTABLE 	2 1 -40	; "paging"
	165	[160]	SELF     	2 2 -46	; "onGotoViewRel"
	166	[160]	LOADK    	4 -3	; 1
	167	[160]	CALL     	2 3 1
	168	[161]	GETGLOBAL	2 -35	; assert
	169	[161]	GETTABLE 	2 2 -36	; "is"
	170	[161]	GETTABLE 	2 2 -42	; "same"
	171	[161]	LOADK    	3 -21	; 4
	172	[161]	GETTABLE 	4 1 -40	; "paging"
	173	[161]	GETTABLE 	4 4 -43	; "current_page"
	174	[161]	CALL     	2 3 1
	175	[162]	GETGLOBAL	2 -35	; assert
	176	[162]	GETTABLE 	2 2 -49	; "are"
	177	[162]	GETTABLE 	2 2 -42	; "same"
	178	[162]	MOVE     	3 0
	179	[162]	GETTABLE 	4 1 -38	; "view"
	180	[162]	GETTABLE 	4 4 -50	; "page_states"
	181	[162]	CALL     	2 3 1
	182	[164]	GETTABLE 	2 1 -51	; "link"
	183	[164]	SELF     	2 2 -52	; "onTap"
	184	[164]	LOADNIL  	4 4
	185	[164]	NEWTABLE 	5 0 1
	186	[164]	NEWTABLE 	6 0 2
	187	[164]	SETTABLE 	6 -5 -54	; "x" 164
	188	[164]	SETTABLE 	6 -7 -55	; "y" 366
	189	[164]	SETTABLE 	5 -53 6	; "pos" -
	190	[164]	CALL     	2 4 1
	191	[165]	GETUPVAL 	2 0	; UIManager
	192	[165]	SELF     	2 2 -56	; "run"
	193	[165]	CALL     	2 2 1
	194	[166]	GETGLOBAL	2 -35	; assert
	195	[166]	GETTABLE 	2 2 -36	; "is"
	196	[166]	GETTABLE 	2 2 -42	; "same"
	197	[166]	LOADK    	3 -57	; 22
	198	[166]	GETTABLE 	4 1 -40	; "paging"
	199	[166]	GETTABLE 	4 4 -43	; "current_page"
	200	[166]	CALL     	2 3 1
	201	[167]	GETTABLE 	2 1 -51	; "link"
	202	[167]	SELF     	2 2 -58	; "onGoBackLink"
	203	[167]	CALL     	2 2 1
	204	[168]	GETGLOBAL	2 -35	; assert
	205	[168]	GETTABLE 	2 2 -36	; "is"
	206	[168]	GETTABLE 	2 2 -42	; "same"
	207	[168]	LOADK    	3 -9	; 3
	208	[168]	GETTABLE 	4 1 -40	; "paging"
	209	[168]	GETTABLE 	4 4 -43	; "current_page"
	210	[168]	CALL     	2 3 1
	211	[169]	GETGLOBAL	2 -35	; assert
	212	[169]	GETTABLE 	2 2 -49	; "are"
	213	[169]	GETTABLE 	2 2 -42	; "same"
	214	[169]	MOVE     	3 0
	215	[169]	GETTABLE 	4 1 -38	; "view"
	216	[169]	GETTABLE 	4 4 -50	; "page_states"
	217	[169]	CALL     	2 3 1
	218	[170]	RETURN   	0 1
