-- BYTECODE -- readerback.lua:17-21
0001    UGET     1   0      ; Device
0002    MOV      2   1
0003    TGETS    1   1   0  ; "hasKeys"
0004    CALL     1   2   2
0005    ISF          1
0006    JMP      2 => 0013
0007    TGETS    1   0   1  ; "ui"
0008    TGETS    1   1   2  ; "key_events"
0009    TDUP     2   5
0010    TDUP     3   4
0011    TSETB    3   2   1
0012    TSETS    2   1   3  ; "Back"
0013 => RET0     0   1

-- BYTECODE -- readerback.lua:23-35
0001    KPRI     1   0
0002    TGETS    2   0   0  ; "ui"
0003    TGETS    2   2   1  ; "document"
0004    TGETS    2   2   2  ; "info"
0005    TGETS    2   2   3  ; "has_pages"
0006    ISF          2
0007    JMP      3 => 0015
0008    TGETS    2   0   0  ; "ui"
0009    TGETS    2   2   4  ; "paging"
0010    MOV      3   2
0011    TGETS    2   2   5  ; "getBookLocation"
0012    CALL     2   2   2
0013    MOV      1   2
0014    JMP      2 => 0023
0015 => TDUP     2   7
0016    TGETS    3   0   0  ; "ui"
0017    TGETS    3   3   6  ; "rolling"
0018    MOV      4   3
0019    TGETS    3   3   5  ; "getBookLocation"
0020    CALL     3   2   2
0021    TSETS    3   2   8  ; "xpointer"
0022    MOV      1   2
0023 => RET1     1   2

-- BYTECODE -- readerback.lua:39-50
0001    TGETS    1   0   0  ; "location_stack"
0002    MOV      3   0
0003    TGETS    2   0   1  ; "_getCurrentLocation"
0004    CALL     2   2   2
0005    UGET     3   0      ; util
0006    TGETS    3   3   2  ; "tableEquals"
0007    UGET     4   1      ; ignore_location
0008    MOV      5   2
0009    CALL     3   2   3
0010    ISF          3
0011    JMP      4 => 0013
0012    RET0     0   1
0013 => GGET     3   3      ; "table"
0014    TGETS    3   3   4  ; "insert"
0015    MOV      4   1
0016    MOV      5   2
0017    CALL     3   1   3
0018    LEN      3   1
0019    TGETS    4   0   5  ; "max_stack"
0020    ISGE     4   3
0021    JMP      3 => 0027
0022    GGET     3   3      ; "table"
0023    TGETS    3   3   6  ; "remove"
0024    MOV      4   1
0025    KSHORT   5   1
0026    CALL     3   1   3
0027 => RET0     0   1

-- BYTECODE -- readerback.lua:53-56
0001    TGETS    1   0   0  ; "disabled"
0002    ISF          1
0003    JMP      2 => 0005
0004    RET0     0   1
0005 => MOV      2   0
0006    TGETS    1   0   1  ; "addCurrentLocationToStack"
0007    CALL     1   1   2
0008    RET0     0   1

-- BYTECODE -- readerback.lua:59-62
0001    TGETS    1   0   0  ; "disabled"
0002    ISF          1
0003    JMP      2 => 0005
0004    RET0     0   1
0005 => MOV      2   0
0006    TGETS    1   0   1  ; "addCurrentLocationToStack"
0007    CALL     1   1   2
0008    RET0     0   1

-- BYTECODE -- readerback.lua:65-67
0001    TNEW     2   0
0002    TSETS    2   0   0  ; "location_stack"
0003    RET0     0   1

-- BYTECODE -- readerback.lua:69-87
0001    TGETS    1   0   0  ; "location_stack"
0002    TGETS    2   0   1  ; "disabled"
0003    ISF          2
0004    JMP      3 => 0015
0005    TGETS    2   0   2  ; "ui"
0006    MOV      3   2
0007    TGETS    2   2   3  ; "handleEvent"
0008    UGET     4   0      ; Event
0009    MOV      5   4
0010    TGETS    4   4   4  ; "new"
0011    KSTR     6   5      ; "Close"
0012    CALL     4   0   3
0013    CALLM    2   1   1
0014    JMP      2 => 0060
0015 => LEN      2   1
0016    KSHORT   3   1
0017    ISGE     3   2
0018    JMP      2 => 0047
0019    GGET     2   6      ; "table"
0020    TGETS    2   2   7  ; "remove"
0021    MOV      3   1
0022    CALL     2   2   2
0023    ISF          2
0024    JMP      3 => 0060
0025    MOV      4   0
0026    TGETS    3   0   8  ; "_getCurrentLocation"
0027    CALL     3   2   2
0028    USETV    1   3      ; ignore_location
0029    UGET     3   2      ; logger
0030    TGETS    3   3   9  ; "dbg"
0031    KSTR     4  10      ; "[ReaderBack] restoring:"
0032    MOV      5   2
0033    CALL     3   1   3
0034    TGETS    3   0   2  ; "ui"
0035    MOV      4   3
0036    TGETS    3   3   3  ; "handleEvent"
0037    UGET     5   0      ; Event
0038    MOV      6   5
0039    TGETS    5   5   4  ; "new"
0040    KSTR     7  11      ; "RestoreBookLocation"
0041    MOV      8   2
0042    CALL     5   0   4
0043    CALLM    3   1   1
0044    KPRI     3   2
0045    RET1     3   2
0046    JMP      2 => 0060
0047 => UGET     2   2      ; logger
0048    TGETS    2   2   9  ; "dbg"
0049    KSTR     3  12      ; "[ReaderBack] no location history, closin"~
0050    CALL     2   1   2
0051    TGETS    2   0   2  ; "ui"
0052    MOV      3   2
0053    TGETS    2   2   3  ; "handleEvent"
0054    UGET     4   0      ; Event
0055    MOV      5   4
0056    TGETS    4   4   4  ; "new"
0057    KSTR     6  13      ; "Home"
0058    CALL     4   0   3
0059    CALLM    2   1   1
0060 => RET0     0   1

-- BYTECODE -- readerback.lua:0-90
0001    GGET     0   0      ; "require"
0002    KSTR     1   1      ; "device"
0003    CALL     0   2   2
0004    GGET     1   0      ; "require"
0005    KSTR     2   2      ; "ui/event"
0006    CALL     1   2   2
0007    GGET     2   0      ; "require"
0008    KSTR     3   3      ; "ui/widget/eventlistener"
0009    CALL     2   2   2
0010    GGET     3   0      ; "require"
0011    KSTR     4   4      ; "logger"
0012    CALL     3   2   2
0013    GGET     4   0      ; "require"
0014    KSTR     5   5      ; "util"
0015    CALL     4   2   2
0016    GGET     5   0      ; "require"
0017    KSTR     6   6      ; "gettext"
0018    CALL     5   2   2
0019    MOV      7   2
0020    TGETS    6   2   7  ; "new"
0021    TDUP     8   8
0022    TNEW     9   0
0023    TSETS    9   8   9  ; "location_stack"
0024    GGET     9  10      ; "G_reader_settings"
0025    MOV     10   9
0026    TGETS    9   9  11  ; "isFalse"
0027    KSTR    11  12      ; "enable_back_history"
0028    CALL     9   2   3
0029    TSETS    9   8  13  ; "disabled"
0030    CALL     6   2   3
0031    FNEW     7  15      ; readerback.lua:17
0032    TSETS    7   6  14  ; "init"
0033    FNEW     7  17      ; readerback.lua:23
0034    TSETS    7   6  16  ; "_getCurrentLocation"
0035    KPRI     7   0
0036    FNEW     8  19      ; readerback.lua:39
0037    TSETS    8   6  18  ; "addCurrentLocationToStack"
0038    FNEW     8  21      ; readerback.lua:53
0039    TSETS    8   6  20  ; "onPosUpdate"
0040    FNEW     8  23      ; readerback.lua:59
0041    TSETS    8   6  22  ; "onPageUpdate"
0042    FNEW     8  25      ; readerback.lua:65
0043    TSETS    8   6  24  ; "onReadSettings"
0044    FNEW     8  27      ; readerback.lua:69
0045    TSETS    8   6  26  ; "onBack"
0046    UCLO     0 => 0047
0047 => RET1     6   2

