
main <./plugins/statistics.koplugin/readerprogress.lua:0,0> (202 instructions, 808 bytes at 0x7fd095c06900)
0+ params, 29 slots, 0 upvalues, 27 locals, 47 constants, 11 functions
	1	[1]	GETGLOBAL	0 -1	; require
	2	[1]	LOADK    	1 -2	; "ffi/blitbuffer"
	3	[1]	CALL     	0 2 2
	4	[2]	GETGLOBAL	1 -1	; require
	5	[2]	LOADK    	2 -3	; "ui/widget/container/centercontainer"
	6	[2]	CALL     	1 2 2
	7	[3]	GETGLOBAL	2 -1	; require
	8	[3]	LOADK    	3 -4	; "ui/widget/closebutton"
	9	[3]	CALL     	2 2 2
	10	[4]	GETGLOBAL	3 -1	; require
	11	[4]	LOADK    	4 -5	; "device"
	12	[4]	CALL     	3 2 2
	13	[5]	GETGLOBAL	4 -1	; require
	14	[5]	LOADK    	5 -6	; "ui/font"
	15	[5]	CALL     	4 2 2
	16	[6]	GETGLOBAL	5 -1	; require
	17	[6]	LOADK    	6 -7	; "ui/widget/container/framecontainer"
	18	[6]	CALL     	5 2 2
	19	[7]	GETGLOBAL	6 -1	; require
	20	[7]	LOADK    	7 -8	; "ui/geometry"
	21	[7]	CALL     	6 2 2
	22	[8]	GETGLOBAL	7 -1	; require
	23	[8]	LOADK    	8 -9	; "ui/gesturerange"
	24	[8]	CALL     	7 2 2
	25	[9]	GETGLOBAL	8 -1	; require
	26	[9]	LOADK    	9 -10	; "ui/widget/horizontalgroup"
	27	[9]	CALL     	8 2 2
	28	[10]	GETGLOBAL	9 -1	; require
	29	[10]	LOADK    	10 -11	; "ui/widget/horizontalspan"
	30	[10]	CALL     	9 2 2
	31	[11]	GETGLOBAL	10 -1	; require
	32	[11]	LOADK    	11 -12	; "ui/widget/container/inputcontainer"
	33	[11]	CALL     	10 2 2
	34	[12]	GETGLOBAL	11 -1	; require
	35	[12]	LOADK    	12 -13	; "ui/widget/container/leftcontainer"
	36	[12]	CALL     	11 2 2
	37	[13]	GETGLOBAL	12 -1	; require
	38	[13]	LOADK    	13 -14	; "ui/widget/linewidget"
	39	[13]	CALL     	12 2 2
	40	[14]	GETGLOBAL	13 -1	; require
	41	[14]	LOADK    	14 -15	; "ui/widget/overlapgroup"
	42	[14]	CALL     	13 2 2
	43	[15]	GETGLOBAL	14 -1	; require
	44	[15]	LOADK    	15 -16	; "ui/widget/progresswidget"
	45	[15]	CALL     	14 2 2
	46	[16]	GETGLOBAL	15 -1	; require
	47	[16]	LOADK    	16 -17	; "ui/size"
	48	[16]	CALL     	15 2 2
	49	[17]	GETGLOBAL	16 -1	; require
	50	[17]	LOADK    	17 -18	; "ui/widget/textwidget"
	51	[17]	CALL     	16 2 2
	52	[18]	GETGLOBAL	17 -1	; require
	53	[18]	LOADK    	18 -19	; "ui/uimanager"
	54	[18]	CALL     	17 2 2
	55	[19]	GETGLOBAL	18 -1	; require
	56	[19]	LOADK    	19 -20	; "ui/widget/verticalgroup"
	57	[19]	CALL     	18 2 2
	58	[20]	GETGLOBAL	19 -1	; require
	59	[20]	LOADK    	20 -21	; "ui/widget/verticalspan"
	60	[20]	CALL     	19 2 2
	61	[21]	GETGLOBAL	20 -1	; require
	62	[21]	LOADK    	21 -22	; "util"
	63	[21]	CALL     	20 2 2
	64	[22]	GETGLOBAL	21 -1	; require
	65	[22]	LOADK    	22 -23	; "gettext"
	66	[22]	CALL     	21 2 2
	67	[23]	GETTABLE 	22 3 -24	; "screen"
	68	[25]	GETTABLE 	23 0 -25	; "COLOR_WEB_GRAY"
	69	[26]	GETTABLE 	24 0 -26	; "COLOR_LIGHT_GRAY"
	70	[28]	SELF     	25 10 -27	; "new"
	71	[28]	NEWTABLE 	27 0 1
	72	[29]	GETTABLE 	28 15 -28	; "padding"
	73	[29]	GETTABLE 	28 28 -29	; "fullscreen"
	74	[29]	SETTABLE 	27 -28 28	; "padding" -
	75	[28]	CALL     	25 3 2
	76	[32]	NEWTABLE 	26 0 7
	77	[33]	MOVE     	27 21
	78	[33]	LOADK    	28 -30	; "Monday"
	79	[33]	CALL     	27 2 2
	80	[33]	SETTABLE 	26 -30 27	; "Monday" -
	81	[34]	MOVE     	27 21
	82	[34]	LOADK    	28 -31	; "Tuesday"
	83	[34]	CALL     	27 2 2
	84	[34]	SETTABLE 	26 -31 27	; "Tuesday" -
	85	[35]	MOVE     	27 21
	86	[35]	LOADK    	28 -32	; "Wednesday"
	87	[35]	CALL     	27 2 2
	88	[35]	SETTABLE 	26 -32 27	; "Wednesday" -
	89	[36]	MOVE     	27 21
	90	[36]	LOADK    	28 -33	; "Thursday"
	91	[36]	CALL     	27 2 2
	92	[36]	SETTABLE 	26 -33 27	; "Thursday" -
	93	[37]	MOVE     	27 21
	94	[37]	LOADK    	28 -34	; "Friday"
	95	[37]	CALL     	27 2 2
	96	[37]	SETTABLE 	26 -34 27	; "Friday" -
	97	[38]	MOVE     	27 21
	98	[38]	LOADK    	28 -35	; "Saturday"
	99	[38]	CALL     	27 2 2
	100	[38]	SETTABLE 	26 -35 27	; "Saturday" -
	101	[39]	MOVE     	27 21
	102	[39]	LOADK    	28 -36	; "Sunday"
	103	[39]	CALL     	27 2 2
	104	[39]	SETTABLE 	26 -36 27	; "Sunday" -
	105	[83]	CLOSURE  	27 0	; 0x7fd095c070d0
	106	[83]	MOVE     	0 4
	107	[83]	MOVE     	0 22
	108	[83]	MOVE     	0 17
	109	[83]	MOVE     	0 3
	110	[83]	MOVE     	0 7
	111	[83]	MOVE     	0 5
	112	[83]	MOVE     	0 0
	113	[42]	SETTABLE 	25 -37 27	; "init" -
	114	[93]	CLOSURE  	27 1	; 0x7fd095c089b0
	115	[85]	SETTABLE 	25 -38 27	; "getTotalStats" -
	116	[113]	CLOSURE  	27 2	; 0x7fd095c08dd0
	117	[113]	MOVE     	0 2
	118	[113]	MOVE     	0 18
	119	[113]	MOVE     	0 13
	120	[113]	MOVE     	0 6
	121	[113]	MOVE     	0 15
	122	[113]	MOVE     	0 21
	123	[95]	SETTABLE 	25 -39 27	; "getStatusContent" -
	124	[148]	CLOSURE  	27 3	; 0x7fd095c092d0
	125	[148]	MOVE     	0 16
	126	[148]	MOVE     	0 23
	127	[148]	MOVE     	0 9
	128	[148]	MOVE     	0 11
	129	[148]	MOVE     	0 6
	130	[148]	MOVE     	0 12
	131	[148]	MOVE     	0 24
	132	[148]	MOVE     	0 15
	133	[148]	MOVE     	0 18
	134	[148]	MOVE     	0 19
	135	[148]	MOVE     	0 22
	136	[148]	MOVE     	0 8
	137	[115]	SETTABLE 	25 -40 27	; "genSingleHeader" -
	138	[194]	CLOSURE  	27 4	; 0x7fd095c09b30
	139	[194]	MOVE     	0 16
	140	[194]	MOVE     	0 23
	141	[194]	MOVE     	0 9
	142	[194]	MOVE     	0 11
	143	[194]	MOVE     	0 6
	144	[194]	MOVE     	0 12
	145	[194]	MOVE     	0 24
	146	[194]	MOVE     	0 15
	147	[194]	MOVE     	0 18
	148	[194]	MOVE     	0 19
	149	[194]	MOVE     	0 22
	150	[194]	MOVE     	0 8
	151	[150]	SETTABLE 	25 -41 27	; "genDoubleHeader" -
	152	[278]	CLOSURE  	27 5	; 0x7fd095c09f30
	153	[278]	MOVE     	0 22
	154	[278]	MOVE     	0 1
	155	[278]	MOVE     	0 6
	156	[278]	MOVE     	0 18
	157	[278]	MOVE     	0 9
	158	[278]	MOVE     	0 8
	159	[278]	MOVE     	0 11
	160	[278]	MOVE     	0 26
	161	[278]	MOVE     	0 15
	162	[278]	MOVE     	0 16
	163	[278]	MOVE     	0 20
	164	[278]	MOVE     	0 4
	165	[278]	MOVE     	0 14
	166	[196]	SETTABLE 	25 -42 27	; "genWeekStats" -
	167	[371]	CLOSURE  	27 6	; 0x7fd095c08440
	168	[371]	MOVE     	0 22
	169	[371]	MOVE     	0 1
	170	[371]	MOVE     	0 6
	171	[371]	MOVE     	0 18
	172	[371]	MOVE     	0 8
	173	[371]	MOVE     	0 16
	174	[371]	MOVE     	0 21
	175	[371]	MOVE     	0 9
	176	[371]	MOVE     	0 11
	177	[371]	MOVE     	0 15
	178	[371]	MOVE     	0 20
	179	[280]	SETTABLE 	25 -43 27	; "genSummaryDay" -
	180	[496]	CLOSURE  	27 7	; 0x7fd095c0ab40
	181	[496]	MOVE     	0 22
	182	[496]	MOVE     	0 1
	183	[496]	MOVE     	0 6
	184	[496]	MOVE     	0 18
	185	[496]	MOVE     	0 8
	186	[496]	MOVE     	0 16
	187	[496]	MOVE     	0 15
	188	[496]	MOVE     	0 21
	189	[496]	MOVE     	0 9
	190	[496]	MOVE     	0 11
	191	[496]	MOVE     	0 20
	192	[373]	SETTABLE 	25 -44 27	; "genSummaryWeek" -
	193	[500]	CLOSURE  	27 8	; 0x7fd095c0b340
	194	[498]	SETTABLE 	25 -45 27	; "onAnyKeyPressed" -
	195	[516]	CLOSURE  	27 9	; 0x7fd095c0b450
	196	[516]	MOVE     	0 17
	197	[502]	SETTABLE 	25 -46 27	; "onSwipe" -
	198	[521]	CLOSURE  	27 10	; 0x7fd095c0b920
	199	[521]	MOVE     	0 17
	200	[518]	SETTABLE 	25 -47 27	; "onClose" -
	201	[523]	RETURN   	25 2
	202	[523]	RETURN   	0 1

function <./plugins/statistics.koplugin/readerprogress.lua:42,83> (104 instructions, 416 bytes at 0x7fd095c070d0)
1 param, 7 slots, 7 upvalues, 1 local, 46 constants, 2 functions
	1	[43]	GETGLOBAL	1 -2	; tostring
	2	[43]	GETTABLE 	2 0 -1	; "current_pages"
	3	[43]	CALL     	1 2 2
	4	[43]	SETTABLE 	0 -1 1	; "current_pages" -
	5	[44]	GETGLOBAL	1 -2	; tostring
	6	[44]	GETTABLE 	2 0 -3	; "today_pages"
	7	[44]	CALL     	1 2 2
	8	[44]	SETTABLE 	0 -3 1	; "today_pages" -
	9	[45]	GETUPVAL 	1 0	; Font
	10	[45]	SELF     	1 1 -5	; "getFace"
	11	[45]	LOADK    	3 -6	; "smallffont"
	12	[45]	CALL     	1 3 2
	13	[45]	SETTABLE 	0 -4 1	; "small_font_face" -
	14	[46]	GETUPVAL 	1 0	; Font
	15	[46]	SELF     	1 1 -5	; "getFace"
	16	[46]	LOADK    	3 -8	; "ffont"
	17	[46]	CALL     	1 3 2
	18	[46]	SETTABLE 	0 -7 1	; "medium_font_face" -
	19	[47]	GETUPVAL 	1 0	; Font
	20	[47]	SELF     	1 1 -5	; "getFace"
	21	[47]	LOADK    	3 -10	; "largeffont"
	22	[47]	CALL     	1 3 2
	23	[47]	SETTABLE 	0 -9 1	; "large_font_face" -
	24	[48]	GETUPVAL 	1 1	; Screen
	25	[48]	SELF     	1 1 -12	; "getWidth"
	26	[48]	CALL     	1 2 2
	27	[48]	SETTABLE 	0 -11 1	; "screen_width" -
	28	[49]	GETUPVAL 	1 1	; Screen
	29	[49]	SELF     	1 1 -14	; "getHeight"
	30	[49]	CALL     	1 2 2
	31	[49]	SETTABLE 	0 -13 1	; "screen_height" -
	32	[50]	GETUPVAL 	1 1	; Screen
	33	[50]	SELF     	1 1 -12	; "getWidth"
	34	[50]	CALL     	1 2 2
	35	[50]	GETUPVAL 	2 1	; Screen
	36	[50]	SELF     	2 2 -14	; "getHeight"
	37	[50]	CALL     	2 2 2
	38	[50]	LT       	0 1 2
	39	[50]	JMP      	3	; to 43
	40	[51]	SETTABLE 	0 -15 -16	; "header_span" 25
	41	[52]	SETTABLE 	0 -17 -18	; "stats_span" 20
	42	[52]	JMP      	2	; to 45
	43	[54]	SETTABLE 	0 -15 -19	; "header_span" 0
	44	[55]	SETTABLE 	0 -17 -20	; "stats_span" 10
	45	[57]	GETUPVAL 	1 2	; UIManager
	46	[57]	SELF     	1 1 -21	; "setDirty"
	47	[57]	MOVE     	3 0
	48	[59]	CLOSURE  	4 0	; 0x7fd095c07cc0
	49	[59]	MOVE     	0 0
	50	[57]	CALL     	1 4 1
	51	[60]	GETUPVAL 	1 3	; Device
	52	[60]	SELF     	1 1 -22	; "hasKeys"
	53	[60]	CALL     	1 2 2
	54	[60]	TEST     	1 0 0
	55	[60]	JMP      	13	; to 69
	56	[61]	NEWTABLE 	1 0 1
	57	[63]	NEWTABLE 	2 1 2
	58	[63]	NEWTABLE 	3 1 0
	59	[63]	GETUPVAL 	4 3	; Device
	60	[63]	GETTABLE 	4 4 -25	; "input"
	61	[63]	GETTABLE 	4 4 -26	; "group"
	62	[63]	GETTABLE 	4 4 -27	; "Any"
	63	[63]	SETLIST  	3 1 1	; 1
	64	[64]	SETTABLE 	2 -28 -29	; "seqtext" "any key"
	65	[64]	SETTABLE 	2 -30 -31	; "doc" "close dialog"
	66	[64]	SETLIST  	2 1 1	; 1
	67	[64]	SETTABLE 	1 -24 2	; "AnyKeyPressed" -
	68	[65]	SETTABLE 	0 -23 1	; "key_events" -
	69	[67]	GETUPVAL 	1 3	; Device
	70	[67]	SELF     	1 1 -32	; "isTouchDevice"
	71	[67]	CALL     	1 2 2
	72	[67]	TEST     	1 0 0
	73	[67]	JMP      	12	; to 86
	74	[68]	GETTABLE 	1 0 -33	; "ges_events"
	75	[68]	NEWTABLE 	2 0 0
	76	[69]	GETUPVAL 	3 4	; GestureRange
	77	[69]	SELF     	3 3 -35	; "new"
	78	[69]	NEWTABLE 	5 0 2
	79	[70]	SETTABLE 	5 -36 -37	; "ges" "swipe"
	80	[71]	CLOSURE  	6 1	; 0x7fd095c07f40
	81	[71]	MOVE     	0 0
	82	[71]	SETTABLE 	5 -38 6	; "range" -
	83	[69]	CALL     	3 3 0
	84	[73]	SETLIST  	2 0 1	; 1
	85	[73]	SETTABLE 	1 -34 2	; "Swipe" -
	86	[75]	GETUPVAL 	1 5	; FrameContainer
	87	[75]	SELF     	1 1 -35	; "new"
	88	[75]	NEWTABLE 	3 0 5
	89	[76]	GETTABLE 	4 0 -40	; "width"
	90	[76]	SETTABLE 	3 -40 4	; "width" -
	91	[77]	GETTABLE 	4 0 -41	; "height"
	92	[77]	SETTABLE 	3 -41 4	; "height" -
	93	[78]	GETUPVAL 	4 6	; Blitbuffer
	94	[78]	GETTABLE 	4 4 -43	; "COLOR_WHITE"
	95	[78]	SETTABLE 	3 -42 4	; "background" -
	96	[79]	SETTABLE 	3 -44 -19	; "bordersize" 0
	97	[80]	SETTABLE 	3 -45 -19	; "padding" 0
	98	[81]	SELF     	4 0 -46	; "getStatusContent"
	99	[81]	GETTABLE 	6 0 -11	; "screen_width"
	100	[81]	CALL     	4 3 0
	101	[82]	SETLIST  	3 0 1	; 1
	102	[75]	CALL     	1 3 2
	103	[82]	SETTABLE 	0 -39 1	; 1 -
	104	[83]	RETURN   	0 1

function <./plugins/statistics.koplugin/readerprogress.lua:57,59> (5 instructions, 20 bytes at 0x7fd095c07cc0)
0 params, 2 slots, 1 upvalue, 0 locals, 2 constants, 0 functions
	1	[58]	LOADK    	0 -1	; "ui"
	2	[58]	GETUPVAL 	1 0	; self
	3	[58]	GETTABLE 	1 1 -2	; "dimen"
	4	[58]	RETURN   	0 3
	5	[59]	RETURN   	0 1

function <./plugins/statistics.koplugin/readerprogress.lua:71,71> (4 instructions, 16 bytes at 0x7fd095c07f40)
0 params, 2 slots, 1 upvalue, 0 locals, 1 constant, 0 functions
	1	[71]	GETUPVAL 	0 0	; self
	2	[71]	GETTABLE 	0 0 -1	; "dimen"
	3	[71]	RETURN   	0 2
	4	[71]	RETURN   	0 1

function <./plugins/statistics.koplugin/readerprogress.lua:85,93> (19 instructions, 76 bytes at 0x7fd095c089b0)
2 params, 9 slots, 0 upvalues, 8 locals, 4 constants, 0 functions
	1	[86]	LOADK    	2 -1	; 0
	2	[87]	LOADK    	3 -1	; 0
	3	[88]	LOADK    	4 -2	; 1
	4	[88]	MOVE     	5 1
	5	[88]	LOADK    	6 -2	; 1
	6	[88]	FORPREP  	4 8	; to 15
	7	[89]	GETTABLE 	8 0 -3	; "dates"
	8	[89]	GETTABLE 	8 8 7
	9	[89]	GETTABLE 	8 8 -2	; 1
	10	[89]	ADD      	3 3 8
	11	[90]	GETTABLE 	8 0 -3	; "dates"
	12	[90]	GETTABLE 	8 8 7
	13	[90]	GETTABLE 	8 8 -4	; 2
	14	[90]	ADD      	2 2 8
	15	[88]	FORLOOP  	4 -9	; to 7
	16	[92]	MOVE     	4 2
	17	[92]	MOVE     	5 3
	18	[92]	RETURN   	4 3
	19	[93]	RETURN   	0 1

function <./plugins/statistics.koplugin/readerprogress.lua:95,113> (60 instructions, 240 bytes at 0x7fd095c08dd0)
2 params, 16 slots, 6 upvalues, 3 locals, 21 constants, 0 functions
	1	[97]	GETTABLE 	3 0 -1	; "readonly"
	2	[97]	EQ       	1 3 -2	; - true
	3	[97]	JMP      	6	; to 10
	4	[98]	GETUPVAL 	3 0	; CloseButton
	5	[98]	SELF     	3 3 -3	; "new"
	6	[98]	NEWTABLE 	5 0 1
	7	[98]	SETTABLE 	5 -4 0	; "window" -
	8	[98]	CALL     	3 3 2
	9	[98]	MOVE     	2 3
	10	[100]	GETUPVAL 	3 1	; VerticalGroup
	11	[100]	SELF     	3 3 -3	; "new"
	12	[100]	NEWTABLE 	5 6 1
	13	[101]	SETTABLE 	5 -5 -6	; "align" "left"
	14	[102]	GETUPVAL 	6 2	; OverlapGroup
	15	[102]	SELF     	6 6 -3	; "new"
	16	[102]	NEWTABLE 	8 1 1
	17	[103]	GETUPVAL 	9 3	; Geom
	18	[103]	SELF     	9 9 -3	; "new"
	19	[103]	NEWTABLE 	11 0 2
	20	[103]	SETTABLE 	11 -8 1	; "w" -
	21	[103]	GETUPVAL 	12 4	; Size
	22	[103]	GETTABLE 	12 12 -10	; "item"
	23	[103]	GETTABLE 	12 12 -11	; "height_default"
	24	[103]	SETTABLE 	11 -9 12	; "h" -
	25	[103]	CALL     	9 3 2
	26	[103]	SETTABLE 	8 -7 9	; "dimen" -
	27	[105]	MOVE     	9 2
	28	[105]	SETLIST  	8 1 1	; 1
	29	[102]	CALL     	6 3 2
	30	[106]	SELF     	7 0 -12	; "genSingleHeader"
	31	[106]	GETUPVAL 	9 5	; _
	32	[106]	LOADK    	10 -13	; "Last week"
	33	[106]	CALL     	9 2 0
	34	[106]	CALL     	7 0 2
	35	[107]	SELF     	8 0 -14	; "genSummaryWeek"
	36	[107]	MOVE     	10 1
	37	[107]	CALL     	8 3 2
	38	[108]	SELF     	9 0 -12	; "genSingleHeader"
	39	[108]	GETUPVAL 	11 5	; _
	40	[108]	LOADK    	12 -15	; "Week progress"
	41	[108]	CALL     	11 2 0
	42	[108]	CALL     	9 0 2
	43	[109]	SELF     	10 0 -16	; "genWeekStats"
	44	[109]	LOADK    	12 -17	; 7
	45	[109]	CALL     	10 3 2
	46	[110]	SELF     	11 0 -18	; "genDoubleHeader"
	47	[110]	GETUPVAL 	13 5	; _
	48	[110]	LOADK    	14 -19	; "Current"
	49	[110]	CALL     	13 2 2
	50	[110]	GETUPVAL 	14 5	; _
	51	[110]	LOADK    	15 -20	; "Today"
	52	[110]	CALL     	14 2 0
	53	[110]	CALL     	11 0 2
	54	[111]	SELF     	12 0 -21	; "genSummaryDay"
	55	[111]	MOVE     	14 1
	56	[111]	CALL     	12 3 0
	57	[112]	SETLIST  	5 0 1	; 1
	58	[100]	TAILCALL 	3 3 0
	59	[112]	RETURN   	3 0
	60	[113]	RETURN   	0 1

function <./plugins/statistics.koplugin/readerprogress.lua:115,148> (97 instructions, 388 bytes at 0x7fd095c092d0)
2 params, 20 slots, 12 upvalues, 6 locals, 25 constants, 0 functions
	1	[116]	GETUPVAL 	2 0	; TextWidget
	2	[116]	SELF     	2 2 -1	; "new"
	3	[116]	NEWTABLE 	4 0 3
	4	[117]	SETTABLE 	4 -2 1	; "text" -
	5	[118]	GETTABLE 	5 0 -4	; "medium_font_face"
	6	[118]	SETTABLE 	4 -3 5	; "face" -
	7	[119]	GETUPVAL 	5 1	; LINE_COLOR
	8	[119]	SETTABLE 	4 -5 5	; "fgcolor" -
	9	[116]	CALL     	2 3 2
	10	[121]	GETUPVAL 	3 2	; HorizontalSpan
	11	[121]	SELF     	3 3 -1	; "new"
	12	[121]	NEWTABLE 	5 0 1
	13	[121]	GETTABLE 	6 0 -7	; "padding"
	14	[121]	SETTABLE 	5 -6 6	; "width" -
	15	[121]	CALL     	3 3 2
	16	[122]	GETTABLE 	4 0 -8	; "screen_width"
	17	[122]	SELF     	5 2 -9	; "getSize"
	18	[122]	CALL     	5 2 2
	19	[122]	GETTABLE 	5 5 -10	; "w"
	20	[122]	SUB      	4 4 5
	21	[122]	DIV      	4 4 -11	; - 2
	22	[122]	GETTABLE 	5 0 -7	; "padding"
	23	[122]	MUL      	5 5 -11	; - 2
	24	[122]	SUB      	4 4 5
	25	[123]	GETUPVAL 	5 3	; LeftContainer
	26	[123]	SELF     	5 5 -1	; "new"
	27	[123]	NEWTABLE 	7 0 1
	28	[124]	GETUPVAL 	8 4	; Geom
	29	[124]	SELF     	8 8 -1	; "new"
	30	[124]	NEWTABLE 	10 0 2
	31	[124]	SETTABLE 	10 -10 4	; "w" -
	32	[124]	GETTABLE 	11 0 -14	; "screen_height"
	33	[124]	DIV      	11 11 -15	; - 25
	34	[124]	SETTABLE 	10 -13 11	; "h" -
	35	[124]	CALL     	8 3 2
	36	[124]	SETTABLE 	7 -12 8	; "dimen" -
	37	[125]	GETUPVAL 	8 5	; LineWidget
	38	[125]	SELF     	8 8 -1	; "new"
	39	[125]	NEWTABLE 	10 0 2
	40	[126]	GETUPVAL 	11 6	; BG_COLOR
	41	[126]	SETTABLE 	10 -16 11	; "background" -
	42	[127]	GETUPVAL 	11 4	; Geom
	43	[127]	SELF     	11 11 -1	; "new"
	44	[127]	NEWTABLE 	13 0 2
	45	[128]	SETTABLE 	13 -10 4	; "w" -
	46	[129]	GETUPVAL 	14 7	; Size
	47	[129]	GETTABLE 	14 14 -17	; "line"
	48	[129]	GETTABLE 	14 14 -18	; "thick"
	49	[129]	SETTABLE 	13 -13 14	; "h" -
	50	[127]	CALL     	11 3 2
	51	[130]	SETTABLE 	10 -12 11	; "dimen" -
	52	[125]	CALL     	8 3 0
	53	[132]	SETLIST  	7 0 1	; 1
	54	[123]	CALL     	5 3 2
	55	[134]	GETUPVAL 	6 8	; VerticalGroup
	56	[134]	SELF     	6 6 -1	; "new"
	57	[134]	NEWTABLE 	8 2 0
	58	[135]	GETUPVAL 	9 9	; VerticalSpan
	59	[135]	SELF     	9 9 -1	; "new"
	60	[135]	NEWTABLE 	11 0 2
	61	[135]	GETUPVAL 	12 10	; Screen
	62	[135]	SELF     	12 12 -19	; "scaleBySize"
	63	[135]	GETTABLE 	14 0 -20	; "header_span"
	64	[135]	CALL     	12 3 2
	65	[135]	SETTABLE 	11 -6 12	; "width" -
	66	[135]	GETTABLE 	12 0 -14	; "screen_height"
	67	[135]	DIV      	12 12 -15	; - 25
	68	[135]	SETTABLE 	11 -21 12	; "height" -
	69	[135]	CALL     	9 3 2
	70	[136]	GETUPVAL 	10 11	; HorizontalGroup
	71	[136]	SELF     	10 10 -1	; "new"
	72	[136]	NEWTABLE 	12 7 1
	73	[137]	SETTABLE 	12 -22 -23	; "align" "center"
	74	[138]	MOVE     	13 3
	75	[139]	MOVE     	14 5
	76	[140]	MOVE     	15 3
	77	[141]	MOVE     	16 2
	78	[142]	MOVE     	17 3
	79	[143]	MOVE     	18 5
	80	[145]	MOVE     	19 3
	81	[145]	SETLIST  	12 7 1	; 1
	82	[136]	CALL     	10 3 2
	83	[146]	GETUPVAL 	11 9	; VerticalSpan
	84	[146]	SELF     	11 11 -1	; "new"
	85	[146]	NEWTABLE 	13 0 2
	86	[146]	GETUPVAL 	14 7	; Size
	87	[146]	GETTABLE 	14 14 -24	; "span"
	88	[146]	GETTABLE 	14 14 -25	; "vertical_large"
	89	[146]	SETTABLE 	13 -6 14	; "width" -
	90	[146]	GETTABLE 	14 0 -14	; "screen_height"
	91	[146]	DIV      	14 14 -15	; - 25
	92	[146]	SETTABLE 	13 -21 14	; "height" -
	93	[146]	CALL     	11 3 0
	94	[147]	SETLIST  	8 0 1	; 1
	95	[134]	TAILCALL 	6 3 0
	96	[147]	RETURN   	6 0
	97	[148]	RETURN   	0 1

function <./plugins/statistics.koplugin/readerprogress.lua:150,194> (116 instructions, 464 bytes at 0x7fd095c09b30)
3 params, 28 slots, 12 upvalues, 8 locals, 25 constants, 0 functions
	1	[151]	GETUPVAL 	3 0	; TextWidget
	2	[151]	SELF     	3 3 -1	; "new"
	3	[151]	NEWTABLE 	5 0 3
	4	[152]	SETTABLE 	5 -2 1	; "text" -
	5	[153]	GETTABLE 	6 0 -4	; "medium_font_face"
	6	[153]	SETTABLE 	5 -3 6	; "face" -
	7	[154]	GETUPVAL 	6 1	; LINE_COLOR
	8	[154]	SETTABLE 	5 -5 6	; "fgcolor" -
	9	[151]	CALL     	3 3 2
	10	[156]	GETUPVAL 	4 0	; TextWidget
	11	[156]	SELF     	4 4 -1	; "new"
	12	[156]	NEWTABLE 	6 0 3
	13	[157]	SETTABLE 	6 -2 2	; "text" -
	14	[158]	GETTABLE 	7 0 -4	; "medium_font_face"
	15	[158]	SETTABLE 	6 -3 7	; "face" -
	16	[159]	GETUPVAL 	7 1	; LINE_COLOR
	17	[159]	SETTABLE 	6 -5 7	; "fgcolor" -
	18	[156]	CALL     	4 3 2
	19	[161]	GETUPVAL 	5 2	; HorizontalSpan
	20	[161]	SELF     	5 5 -1	; "new"
	21	[161]	NEWTABLE 	7 0 1
	22	[161]	GETTABLE 	8 0 -7	; "padding"
	23	[161]	SETTABLE 	7 -6 8	; "width" -
	24	[161]	CALL     	5 3 2
	25	[162]	GETTABLE 	6 0 -8	; "screen_width"
	26	[162]	SELF     	7 3 -9	; "getSize"
	27	[162]	CALL     	7 2 2
	28	[162]	GETTABLE 	7 7 -10	; "w"
	29	[162]	SUB      	6 6 7
	30	[162]	SELF     	7 4 -9	; "getSize"
	31	[162]	CALL     	7 2 2
	32	[162]	GETTABLE 	7 7 -10	; "w"
	33	[162]	SUB      	6 6 7
	34	[162]	GETTABLE 	7 0 -7	; "padding"
	35	[162]	MUL      	7 7 -11	; - 7
	36	[162]	SUB      	6 6 7
	37	[162]	DIV      	6 6 -12	; - 4
	38	[163]	GETUPVAL 	7 3	; LeftContainer
	39	[163]	SELF     	7 7 -1	; "new"
	40	[163]	NEWTABLE 	9 0 1
	41	[164]	GETUPVAL 	10 4	; Geom
	42	[164]	SELF     	10 10 -1	; "new"
	43	[164]	NEWTABLE 	12 0 2
	44	[164]	SETTABLE 	12 -10 6	; "w" -
	45	[164]	GETTABLE 	13 0 -15	; "screen_height"
	46	[164]	DIV      	13 13 -16	; - 25
	47	[164]	SETTABLE 	12 -14 13	; "h" -
	48	[164]	CALL     	10 3 2
	49	[164]	SETTABLE 	9 -13 10	; "dimen" -
	50	[165]	GETUPVAL 	10 5	; LineWidget
	51	[165]	SELF     	10 10 -1	; "new"
	52	[165]	NEWTABLE 	12 0 2
	53	[166]	GETUPVAL 	13 6	; BG_COLOR
	54	[166]	SETTABLE 	12 -17 13	; "background" -
	55	[167]	GETUPVAL 	13 4	; Geom
	56	[167]	SELF     	13 13 -1	; "new"
	57	[167]	NEWTABLE 	15 0 2
	58	[168]	SETTABLE 	15 -10 6	; "w" -
	59	[169]	GETUPVAL 	16 7	; Size
	60	[169]	GETTABLE 	16 16 -18	; "line"
	61	[169]	GETTABLE 	16 16 -19	; "thick"
	62	[169]	SETTABLE 	15 -14 16	; "h" -
	63	[167]	CALL     	13 3 2
	64	[170]	SETTABLE 	12 -13 13	; "dimen" -
	65	[165]	CALL     	10 3 0
	66	[172]	SETLIST  	9 0 1	; 1
	67	[163]	CALL     	7 3 2
	68	[174]	GETUPVAL 	8 8	; VerticalGroup
	69	[174]	SELF     	8 8 -1	; "new"
	70	[174]	NEWTABLE 	10 2 0
	71	[175]	GETUPVAL 	11 9	; VerticalSpan
	72	[175]	SELF     	11 11 -1	; "new"
	73	[175]	NEWTABLE 	13 0 2
	74	[175]	GETUPVAL 	14 10	; Screen
	75	[175]	SELF     	14 14 -20	; "scaleBySize"
	76	[175]	LOADK    	16 -16	; 25
	77	[175]	CALL     	14 3 2
	78	[175]	SETTABLE 	13 -6 14	; "width" -
	79	[175]	GETTABLE 	14 0 -15	; "screen_height"
	80	[175]	DIV      	14 14 -16	; - 25
	81	[175]	SETTABLE 	13 -21 14	; "height" -
	82	[175]	CALL     	11 3 2
	83	[176]	GETUPVAL 	12 11	; HorizontalGroup
	84	[176]	SELF     	12 12 -1	; "new"
	85	[176]	NEWTABLE 	14 13 1
	86	[177]	SETTABLE 	14 -22 -23	; "align" "center"
	87	[178]	MOVE     	15 5
	88	[179]	MOVE     	16 7
	89	[180]	MOVE     	17 5
	90	[181]	MOVE     	18 3
	91	[182]	MOVE     	19 5
	92	[183]	MOVE     	20 7
	93	[184]	MOVE     	21 5
	94	[185]	MOVE     	22 7
	95	[186]	MOVE     	23 5
	96	[187]	MOVE     	24 4
	97	[188]	MOVE     	25 5
	98	[189]	MOVE     	26 7
	99	[191]	MOVE     	27 5
	100	[191]	SETLIST  	14 13 1	; 1
	101	[176]	CALL     	12 3 2
	102	[192]	GETUPVAL 	13 9	; VerticalSpan
	103	[192]	SELF     	13 13 -1	; "new"
	104	[192]	NEWTABLE 	15 0 2
	105	[192]	GETUPVAL 	16 7	; Size
	106	[192]	GETTABLE 	16 16 -24	; "span"
	107	[192]	GETTABLE 	16 16 -25	; "vertical_large"
	108	[192]	SETTABLE 	15 -6 16	; "width" -
	109	[192]	GETTABLE 	16 0 -15	; "screen_height"
	110	[192]	DIV      	16 16 -16	; - 25
	111	[192]	SETTABLE 	15 -21 16	; "height" -
	112	[192]	CALL     	13 3 0
	113	[193]	SETLIST  	10 0 1	; 1
	114	[174]	TAILCALL 	8 3 0
	115	[193]	RETURN   	8 0
	116	[194]	RETURN   	0 1

function <./plugins/statistics.koplugin/readerprogress.lua:196,278> (271 instructions, 1084 bytes at 0x7fd095c09f30)
2 params, 35 slots, 13 upvalues, 27 locals, 50 constants, 0 functions
	1	[197]	LOADK    	2 -1	; 86400
	2	[198]	LOADNIL  	3 5
	3	[201]	GETGLOBAL	6 -2	; os
	4	[201]	GETTABLE 	6 6 -3	; "time"
	5	[201]	CALL     	6 1 2
	6	[202]	GETUPVAL 	7 0	; Screen
	7	[202]	SELF     	7 7 -4	; "scaleBySize"
	8	[202]	LOADK    	9 -5	; 60
	9	[202]	CALL     	7 3 2
	10	[203]	GETUPVAL 	8 1	; CenterContainer
	11	[203]	SELF     	8 8 -6	; "new"
	12	[203]	NEWTABLE 	10 0 1
	13	[204]	GETUPVAL 	11 2	; Geom
	14	[204]	SELF     	11 11 -6	; "new"
	15	[204]	NEWTABLE 	13 0 2
	16	[204]	GETTABLE 	14 0 -9	; "screen_width"
	17	[204]	SETTABLE 	13 -8 14	; "w" -
	18	[204]	SETTABLE 	13 -10 7	; "h" -
	19	[204]	CALL     	11 3 2
	20	[204]	SETTABLE 	10 -7 11	; "dimen" -
	21	[203]	CALL     	8 3 2
	22	[206]	GETUPVAL 	9 3	; VerticalGroup
	23	[206]	SELF     	9 9 -6	; "new"
	24	[206]	NEWTABLE 	11 0 1
	25	[206]	SETTABLE 	11 -11 -12	; "align" "left"
	26	[206]	CALL     	9 3 2
	27	[207]	LOADK    	10 -13	; -1
	28	[208]	LOADNIL  	11 11
	29	[209]	LOADK    	12 -14	; 1
	30	[209]	MOVE     	13 1
	31	[209]	LOADK    	14 -14	; 1
	32	[209]	FORPREP  	12 6	; to 39
	33	[210]	GETTABLE 	16 0 -15	; "dates"
	34	[210]	GETTABLE 	16 16 15
	35	[210]	GETTABLE 	11 16 -16	; 2
	36	[211]	LT       	0 10 11
	37	[211]	JMP      	1	; to 39
	38	[211]	MOVE     	10 11
	39	[209]	FORLOOP  	12 -7	; to 33
	40	[213]	GETUPVAL 	12 4	; HorizontalSpan
	41	[213]	SELF     	12 12 -6	; "new"
	42	[213]	NEWTABLE 	14 0 1
	43	[213]	GETUPVAL 	15 0	; Screen
	44	[213]	SELF     	15 15 -4	; "scaleBySize"
	45	[213]	LOADK    	17 -18	; 15
	46	[213]	CALL     	15 3 2
	47	[213]	SETTABLE 	14 -17 15	; "width" -
	48	[213]	CALL     	12 3 2
	49	[214]	GETUPVAL 	13 5	; HorizontalGroup
	50	[214]	SELF     	13 13 -6	; "new"
	51	[214]	NEWTABLE 	15 0 1
	52	[215]	SETTABLE 	15 -11 -19	; "align" "center"
	53	[216]	GETUPVAL 	16 6	; LeftContainer
	54	[216]	SELF     	16 16 -6	; "new"
	55	[216]	NEWTABLE 	18 1 1
	56	[217]	GETUPVAL 	19 2	; Geom
	57	[217]	SELF     	19 19 -6	; "new"
	58	[217]	NEWTABLE 	21 0 1
	59	[217]	GETUPVAL 	22 0	; Screen
	60	[217]	SELF     	22 22 -4	; "scaleBySize"
	61	[217]	LOADK    	24 -20	; 30
	62	[217]	CALL     	22 3 2
	63	[217]	SETTABLE 	21 -10 22	; "h" -
	64	[217]	CALL     	19 3 2
	65	[217]	SETTABLE 	18 -7 19	; "dimen" -
	66	[219]	MOVE     	19 12
	67	[219]	SETLIST  	18 1 1	; 1
	68	[216]	CALL     	16 3 0
	69	[220]	SETLIST  	15 0 1	; 1
	70	[214]	CALL     	13 3 2
	71	[221]	GETGLOBAL	14 -21	; table
	72	[221]	GETTABLE 	14 14 -22	; "insert"
	73	[221]	MOVE     	15 9
	74	[221]	MOVE     	16 13
	75	[221]	CALL     	14 3 1
	76	[223]	GETUPVAL 	14 4	; HorizontalSpan
	77	[223]	SELF     	14 14 -6	; "new"
	78	[223]	NEWTABLE 	16 0 1
	79	[223]	GETUPVAL 	17 0	; Screen
	80	[223]	SELF     	17 17 -4	; "scaleBySize"
	81	[223]	LOADK    	19 -18	; 15
	82	[223]	CALL     	17 3 2
	83	[223]	SETTABLE 	16 -17 17	; "width" -
	84	[223]	CALL     	14 3 2
	85	[224]	GETUPVAL 	15 5	; HorizontalGroup
	86	[224]	SELF     	15 15 -6	; "new"
	87	[224]	NEWTABLE 	17 0 1
	88	[225]	SETTABLE 	17 -11 -19	; "align" "center"
	89	[226]	GETUPVAL 	18 6	; LeftContainer
	90	[226]	SELF     	18 18 -6	; "new"
	91	[226]	NEWTABLE 	20 1 1
	92	[227]	GETUPVAL 	21 2	; Geom
	93	[227]	SELF     	21 21 -6	; "new"
	94	[227]	NEWTABLE 	23 0 1
	95	[227]	GETUPVAL 	24 0	; Screen
	96	[227]	SELF     	24 24 -4	; "scaleBySize"
	97	[227]	GETTABLE 	26 0 -23	; "stats_span"
	98	[227]	CALL     	24 3 2
	99	[227]	SETTABLE 	23 -10 24	; "h" -
	100	[227]	CALL     	21 3 2
	101	[227]	SETTABLE 	20 -7 21	; "dimen" -
	102	[229]	MOVE     	21 14
	103	[229]	SETLIST  	20 1 1	; 1
	104	[226]	CALL     	18 3 0
	105	[230]	SETLIST  	17 0 1	; 1
	106	[224]	CALL     	15 3 2
	107	[232]	LOADK    	16 -14	; 1
	108	[233]	LOADK    	17 -14	; 1
	109	[233]	MOVE     	18 1
	110	[233]	LOADK    	19 -14	; 1
	111	[233]	FORPREP  	17 135	; to 247
	112	[234]	SUB      	21 20 -14	; - 1
	113	[234]	MUL      	21 2 21
	114	[234]	SUB      	5 6 21
	115	[235]	GETTABLE 	21 0 -15	; "dates"
	116	[235]	GETTABLE 	21 21 16
	117	[235]	GETTABLE 	21 21 -24	; 3
	118	[235]	GETGLOBAL	22 -2	; os
	119	[235]	GETTABLE 	22 22 -25	; "date"
	120	[235]	LOADK    	23 -26	; "%Y-%m-%d"
	121	[235]	MOVE     	24 5
	122	[235]	CALL     	22 3 2
	123	[235]	EQ       	0 21 22
	124	[235]	JMP      	5	; to 130
	125	[236]	GETTABLE 	21 0 -15	; "dates"
	126	[236]	GETTABLE 	21 21 16
	127	[236]	GETTABLE 	4 21 -16	; 2
	128	[237]	ADD      	16 16 -14	; - 1
	129	[237]	JMP      	1	; to 131
	130	[239]	LOADK    	4 -27	; 0
	131	[241]	GETUPVAL 	21 7	; dayOfWeekTranslation
	132	[241]	GETGLOBAL	22 -2	; os
	133	[241]	GETTABLE 	22 22 -25	; "date"
	134	[241]	LOADK    	23 -28	; "%A"
	135	[241]	MOVE     	24 5
	136	[241]	CALL     	22 3 2
	137	[241]	GETTABLE 	21 21 22
	138	[241]	GETGLOBAL	22 -2	; os
	139	[241]	GETTABLE 	22 22 -25	; "date"
	140	[241]	LOADK    	23 -29	; " (%d.%m)"
	141	[241]	MOVE     	24 5
	142	[241]	CALL     	22 3 2
	143	[241]	CONCAT   	3 21 22
	144	[242]	GETUPVAL 	21 5	; HorizontalGroup
	145	[242]	SELF     	21 21 -6	; "new"
	146	[242]	NEWTABLE 	23 0 2
	147	[243]	SETTABLE 	23 -11 -19	; "align" "center"
	148	[244]	GETUPVAL 	24 8	; Size
	149	[244]	GETTABLE 	24 24 -30	; "padding"
	150	[244]	GETTABLE 	24 24 -31	; "small"
	151	[244]	SETTABLE 	23 -30 24	; "padding" -
	152	[245]	GETUPVAL 	24 6	; LeftContainer
	153	[245]	SELF     	24 24 -6	; "new"
	154	[245]	NEWTABLE 	26 0 1
	155	[246]	GETUPVAL 	27 2	; Geom
	156	[246]	SELF     	27 27 -6	; "new"
	157	[246]	NEWTABLE 	29 0 2
	158	[246]	GETTABLE 	30 0 -9	; "screen_width"
	159	[246]	SETTABLE 	29 -8 30	; "w" -
	160	[246]	DIV      	30 7 -24	; - 3
	161	[246]	SETTABLE 	29 -10 30	; "h" -
	162	[246]	CALL     	27 3 2
	163	[246]	SETTABLE 	26 -7 27	; "dimen" -
	164	[247]	GETUPVAL 	27 9	; TextWidget
	165	[247]	SELF     	27 27 -6	; "new"
	166	[247]	NEWTABLE 	29 0 3
	167	[248]	GETUPVAL 	30 8	; Size
	168	[248]	GETTABLE 	30 30 -30	; "padding"
	169	[248]	GETTABLE 	30 30 -31	; "small"
	170	[248]	SETTABLE 	29 -30 30	; "padding" -
	171	[249]	MOVE     	30 3
	172	[249]	LOADK    	31 -33	; " - "
	173	[249]	GETUPVAL 	32 10	; util
	174	[249]	GETTABLE 	32 32 -34	; "secondsToClock"
	175	[249]	MOVE     	33 4
	176	[249]	LOADBOOL 	34 1 0
	177	[249]	CALL     	32 3 2
	178	[249]	CONCAT   	30 30 32
	179	[249]	SETTABLE 	29 -32 30	; "text" -
	180	[250]	GETUPVAL 	30 11	; Font
	181	[250]	SELF     	30 30 -36	; "getFace"
	182	[250]	LOADK    	32 -37	; "smallffont"
	183	[250]	CALL     	30 3 2
	184	[250]	SETTABLE 	29 -35 30	; "face" -
	185	[247]	CALL     	27 3 0
	186	[252]	SETLIST  	26 0 1	; 1
	187	[245]	CALL     	24 3 0
	188	[253]	SETLIST  	23 0 1	; 1
	189	[242]	CALL     	21 3 2
	190	[254]	GETUPVAL 	22 5	; HorizontalGroup
	191	[254]	SELF     	22 22 -6	; "new"
	192	[254]	NEWTABLE 	24 0 1
	193	[255]	SETTABLE 	24 -11 -19	; "align" "center"
	194	[256]	GETUPVAL 	25 6	; LeftContainer
	195	[256]	SELF     	25 25 -6	; "new"
	196	[256]	NEWTABLE 	27 0 1
	197	[257]	GETUPVAL 	28 2	; Geom
	198	[257]	SELF     	28 28 -6	; "new"
	199	[257]	NEWTABLE 	30 0 2
	200	[257]	GETTABLE 	31 0 -9	; "screen_width"
	201	[257]	SETTABLE 	30 -8 31	; "w" -
	202	[257]	DIV      	31 7 -24	; - 3
	203	[257]	SETTABLE 	30 -10 31	; "h" -
	204	[257]	CALL     	28 3 2
	205	[257]	SETTABLE 	27 -7 28	; "dimen" -
	206	[258]	GETUPVAL 	28 12	; ProgressWidget
	207	[258]	SELF     	28 28 -6	; "new"
	208	[258]	NEWTABLE 	30 0 7
	209	[259]	GETTABLE 	31 0 -9	; "screen_width"
	210	[259]	MUL      	31 31 -38	; - 0.005
	211	[259]	GETTABLE 	32 0 -9	; "screen_width"
	212	[259]	MUL      	32 32 -39	; - 0.9
	213	[259]	MUL      	32 32 4
	214	[259]	DIV      	32 32 10
	215	[259]	ADD      	31 31 32
	216	[259]	SETTABLE 	30 -17 31	; "width" -
	217	[260]	GETUPVAL 	31 0	; Screen
	218	[260]	SELF     	31 31 -4	; "scaleBySize"
	219	[260]	LOADK    	33 -41	; 14
	220	[260]	CALL     	31 3 2
	221	[260]	SETTABLE 	30 -40 31	; "height" -
	222	[261]	SETTABLE 	30 -42 -14	; "percentage" 1
	223	[262]	SETTABLE 	30 -43 -44	; "ticks" nil
	224	[263]	SETTABLE 	30 -45 -44	; "last" nil
	225	[264]	SETTABLE 	30 -46 -27	; "margin_h" 0
	226	[265]	SETTABLE 	30 -47 -27	; "margin_v" 0
	227	[258]	CALL     	28 3 0
	228	[267]	SETLIST  	27 0 1	; 1
	229	[256]	CALL     	25 3 0
	230	[268]	SETLIST  	24 0 1	; 1
	231	[254]	CALL     	22 3 2
	232	[269]	GETGLOBAL	23 -21	; table
	233	[269]	GETTABLE 	23 23 -22	; "insert"
	234	[269]	MOVE     	24 9
	235	[269]	MOVE     	25 21
	236	[269]	CALL     	23 3 1
	237	[270]	GETGLOBAL	23 -21	; table
	238	[270]	GETTABLE 	23 23 -22	; "insert"
	239	[270]	MOVE     	24 9
	240	[270]	MOVE     	25 22
	241	[270]	CALL     	23 3 1
	242	[271]	GETGLOBAL	23 -21	; table
	243	[271]	GETTABLE 	23 23 -22	; "insert"
	244	[271]	MOVE     	24 9
	245	[271]	MOVE     	25 15
	246	[271]	CALL     	23 3 1
	247	[233]	FORLOOP  	17 -136	; to 112
	248	[273]	GETGLOBAL	17 -21	; table
	249	[273]	GETTABLE 	17 17 -22	; "insert"
	250	[273]	MOVE     	18 8
	251	[273]	MOVE     	19 9
	252	[273]	CALL     	17 3 1
	253	[274]	GETUPVAL 	17 1	; CenterContainer
	254	[274]	SELF     	17 17 -6	; "new"
	255	[274]	NEWTABLE 	19 1 1
	256	[275]	GETUPVAL 	20 2	; Geom
	257	[275]	SELF     	20 20 -6	; "new"
	258	[275]	NEWTABLE 	22 0 2
	259	[275]	GETTABLE 	23 0 -9	; "screen_width"
	260	[275]	MUL      	23 23 -48	; - 1.1
	261	[275]	SETTABLE 	22 -8 23	; "w" -
	262	[275]	GETTABLE 	23 0 -49	; "screen_height"
	263	[275]	MUL      	23 23 -50	; - 0.5
	264	[275]	SETTABLE 	22 -10 23	; "h" -
	265	[275]	CALL     	20 3 2
	266	[275]	SETTABLE 	19 -7 20	; "dimen" -
	267	[277]	MOVE     	20 8
	268	[277]	SETLIST  	19 1 1	; 1
	269	[274]	TAILCALL 	17 3 0
	270	[277]	RETURN   	17 0
	271	[278]	RETURN   	0 1

function <./plugins/statistics.koplugin/readerprogress.lua:280,371> (288 instructions, 1152 bytes at 0x7fd095c08440)
2 params, 25 slots, 11 upvalues, 11 locals, 31 constants, 0 functions
	1	[281]	GETUPVAL 	2 0	; Screen
	2	[281]	SELF     	2 2 -1	; "scaleBySize"
	3	[281]	LOADK    	4 -2	; 60
	4	[281]	CALL     	2 3 2
	5	[282]	GETUPVAL 	3 1	; CenterContainer
	6	[282]	SELF     	3 3 -3	; "new"
	7	[282]	NEWTABLE 	5 0 1
	8	[283]	GETUPVAL 	6 2	; Geom
	9	[283]	SELF     	6 6 -3	; "new"
	10	[283]	NEWTABLE 	8 0 2
	11	[283]	SETTABLE 	8 -5 1	; "w" -
	12	[283]	SETTABLE 	8 -6 2	; "h" -
	13	[283]	CALL     	6 3 2
	14	[283]	SETTABLE 	5 -4 6	; "dimen" -
	15	[282]	CALL     	3 3 2
	16	[285]	GETUPVAL 	4 3	; VerticalGroup
	17	[285]	SELF     	4 4 -3	; "new"
	18	[285]	NEWTABLE 	6 0 1
	19	[285]	SETTABLE 	6 -7 -8	; "align" "left"
	20	[285]	CALL     	4 3 2
	21	[286]	DIV      	5 1 -9	; - 4
	22	[287]	DIV      	6 2 -10	; - 3
	23	[289]	GETUPVAL 	7 4	; HorizontalGroup
	24	[289]	SELF     	7 7 -3	; "new"
	25	[289]	NEWTABLE 	9 3 1
	26	[290]	SETTABLE 	9 -7 -11	; "align" "center"
	27	[291]	GETUPVAL 	10 1	; CenterContainer
	28	[291]	SELF     	10 10 -3	; "new"
	29	[291]	NEWTABLE 	12 0 1
	30	[292]	GETUPVAL 	13 2	; Geom
	31	[292]	SELF     	13 13 -3	; "new"
	32	[292]	NEWTABLE 	15 0 2
	33	[292]	SETTABLE 	15 -5 5	; "w" -
	34	[292]	SETTABLE 	15 -6 6	; "h" -
	35	[292]	CALL     	13 3 2
	36	[292]	SETTABLE 	12 -4 13	; "dimen" -
	37	[293]	GETUPVAL 	13 5	; TextWidget
	38	[293]	SELF     	13 13 -3	; "new"
	39	[293]	NEWTABLE 	15 0 2
	40	[294]	GETUPVAL 	16 6	; _
	41	[294]	LOADK    	17 -13	; "Pages"
	42	[294]	CALL     	16 2 2
	43	[294]	SETTABLE 	15 -12 16	; "text" -
	44	[295]	GETTABLE 	16 0 -15	; "small_font_face"
	45	[295]	SETTABLE 	15 -14 16	; "face" -
	46	[293]	CALL     	13 3 0
	47	[297]	SETLIST  	12 0 1	; 1
	48	[291]	CALL     	10 3 2
	49	[298]	GETUPVAL 	11 1	; CenterContainer
	50	[298]	SELF     	11 11 -3	; "new"
	51	[298]	NEWTABLE 	13 0 1
	52	[299]	GETUPVAL 	14 2	; Geom
	53	[299]	SELF     	14 14 -3	; "new"
	54	[299]	NEWTABLE 	16 0 2
	55	[299]	SETTABLE 	16 -5 5	; "w" -
	56	[299]	SETTABLE 	16 -6 6	; "h" -
	57	[299]	CALL     	14 3 2
	58	[299]	SETTABLE 	13 -4 14	; "dimen" -
	59	[300]	GETUPVAL 	14 5	; TextWidget
	60	[300]	SELF     	14 14 -3	; "new"
	61	[300]	NEWTABLE 	16 0 2
	62	[301]	GETUPVAL 	17 6	; _
	63	[301]	LOADK    	18 -16	; "Time"
	64	[301]	CALL     	17 2 2
	65	[301]	SETTABLE 	16 -12 17	; "text" -
	66	[302]	GETTABLE 	17 0 -15	; "small_font_face"
	67	[302]	SETTABLE 	16 -14 17	; "face" -
	68	[300]	CALL     	14 3 0
	69	[304]	SETLIST  	13 0 1	; 1
	70	[298]	CALL     	11 3 2
	71	[305]	GETUPVAL 	12 1	; CenterContainer
	72	[305]	SELF     	12 12 -3	; "new"
	73	[305]	NEWTABLE 	14 0 1
	74	[306]	GETUPVAL 	15 2	; Geom
	75	[306]	SELF     	15 15 -3	; "new"
	76	[306]	NEWTABLE 	17 0 2
	77	[306]	SETTABLE 	17 -5 5	; "w" -
	78	[306]	SETTABLE 	17 -6 6	; "h" -
	79	[306]	CALL     	15 3 2
	80	[306]	SETTABLE 	14 -4 15	; "dimen" -
	81	[307]	GETUPVAL 	15 5	; TextWidget
	82	[307]	SELF     	15 15 -3	; "new"
	83	[307]	NEWTABLE 	17 0 2
	84	[308]	GETUPVAL 	18 6	; _
	85	[308]	LOADK    	19 -13	; "Pages"
	86	[308]	CALL     	18 2 2
	87	[308]	SETTABLE 	17 -12 18	; "text" -
	88	[309]	GETTABLE 	18 0 -15	; "small_font_face"
	89	[309]	SETTABLE 	17 -14 18	; "face" -
	90	[307]	CALL     	15 3 0
	91	[311]	SETLIST  	14 0 1	; 1
	92	[305]	CALL     	12 3 2
	93	[312]	GETUPVAL 	13 1	; CenterContainer
	94	[312]	SELF     	13 13 -3	; "new"
	95	[312]	NEWTABLE 	15 0 1
	96	[313]	GETUPVAL 	16 2	; Geom
	97	[313]	SELF     	16 16 -3	; "new"
	98	[313]	NEWTABLE 	18 0 2
	99	[313]	SETTABLE 	18 -5 5	; "w" -
	100	[313]	SETTABLE 	18 -6 6	; "h" -
	101	[313]	CALL     	16 3 2
	102	[313]	SETTABLE 	15 -4 16	; "dimen" -
	103	[314]	GETUPVAL 	16 5	; TextWidget
	104	[314]	SELF     	16 16 -3	; "new"
	105	[314]	NEWTABLE 	18 0 2
	106	[315]	GETUPVAL 	19 6	; _
	107	[315]	LOADK    	20 -16	; "Time"
	108	[315]	CALL     	19 2 2
	109	[315]	SETTABLE 	18 -12 19	; "text" -
	110	[316]	GETTABLE 	19 0 -15	; "small_font_face"
	111	[316]	SETTABLE 	18 -14 19	; "face" -
	112	[314]	CALL     	16 3 0
	113	[318]	SETLIST  	15 0 1	; 1
	114	[312]	CALL     	13 3 0
	115	[319]	SETLIST  	9 0 1	; 1
	116	[289]	CALL     	7 3 2
	117	[321]	GETUPVAL 	8 7	; HorizontalSpan
	118	[321]	SELF     	8 8 -3	; "new"
	119	[321]	NEWTABLE 	10 0 1
	120	[321]	GETUPVAL 	11 0	; Screen
	121	[321]	SELF     	11 11 -1	; "scaleBySize"
	122	[321]	LOADK    	13 -18	; 15
	123	[321]	CALL     	11 3 2
	124	[321]	SETTABLE 	10 -17 11	; "width" -
	125	[321]	CALL     	8 3 2
	126	[322]	GETUPVAL 	9 4	; HorizontalGroup
	127	[322]	SELF     	9 9 -3	; "new"
	128	[322]	NEWTABLE 	11 0 1
	129	[323]	SETTABLE 	11 -7 -11	; "align" "center"
	130	[324]	GETUPVAL 	12 8	; LeftContainer
	131	[324]	SELF     	12 12 -3	; "new"
	132	[324]	NEWTABLE 	14 1 1
	133	[325]	GETUPVAL 	15 2	; Geom
	134	[325]	SELF     	15 15 -3	; "new"
	135	[325]	NEWTABLE 	17 0 1
	136	[325]	GETUPVAL 	18 9	; Size
	137	[325]	GETTABLE 	18 18 -19	; "span"
	138	[325]	GETTABLE 	18 18 -20	; "horizontal_default"
	139	[325]	SETTABLE 	17 -6 18	; "h" -
	140	[325]	CALL     	15 3 2
	141	[325]	SETTABLE 	14 -4 15	; "dimen" -
	142	[327]	MOVE     	15 8
	143	[327]	SETLIST  	14 1 1	; 1
	144	[324]	CALL     	12 3 0
	145	[328]	SETLIST  	11 0 1	; 1
	146	[322]	CALL     	9 3 2
	147	[330]	GETUPVAL 	10 4	; HorizontalGroup
	148	[330]	SELF     	10 10 -3	; "new"
	149	[330]	NEWTABLE 	12 3 1
	150	[331]	SETTABLE 	12 -7 -11	; "align" "center"
	151	[332]	GETUPVAL 	13 1	; CenterContainer
	152	[332]	SELF     	13 13 -3	; "new"
	153	[332]	NEWTABLE 	15 0 1
	154	[333]	GETUPVAL 	16 2	; Geom
	155	[333]	SELF     	16 16 -3	; "new"
	156	[333]	NEWTABLE 	18 0 2
	157	[333]	SETTABLE 	18 -5 5	; "w" -
	158	[333]	SETTABLE 	18 -6 6	; "h" -
	159	[333]	CALL     	16 3 2
	160	[333]	SETTABLE 	15 -4 16	; "dimen" -
	161	[334]	GETUPVAL 	16 5	; TextWidget
	162	[334]	SELF     	16 16 -3	; "new"
	163	[334]	NEWTABLE 	18 0 2
	164	[335]	GETTABLE 	19 0 -21	; "current_pages"
	165	[335]	SETTABLE 	18 -12 19	; "text" -
	166	[336]	GETTABLE 	19 0 -22	; "medium_font_face"
	167	[336]	SETTABLE 	18 -14 19	; "face" -
	168	[334]	CALL     	16 3 0
	169	[338]	SETLIST  	15 0 1	; 1
	170	[332]	CALL     	13 3 2
	171	[339]	GETUPVAL 	14 1	; CenterContainer
	172	[339]	SELF     	14 14 -3	; "new"
	173	[339]	NEWTABLE 	16 0 1
	174	[340]	GETUPVAL 	17 2	; Geom
	175	[340]	SELF     	17 17 -3	; "new"
	176	[340]	NEWTABLE 	19 0 2
	177	[340]	SETTABLE 	19 -5 5	; "w" -
	178	[340]	SETTABLE 	19 -6 6	; "h" -
	179	[340]	CALL     	17 3 2
	180	[340]	SETTABLE 	16 -4 17	; "dimen" -
	181	[341]	GETUPVAL 	17 5	; TextWidget
	182	[341]	SELF     	17 17 -3	; "new"
	183	[341]	NEWTABLE 	19 0 2
	184	[342]	GETUPVAL 	20 10	; util
	185	[342]	GETTABLE 	20 20 -23	; "secondsToClock"
	186	[342]	GETTABLE 	21 0 -24	; "current_period"
	187	[342]	LOADBOOL 	22 1 0
	188	[342]	CALL     	20 3 2
	189	[342]	SETTABLE 	19 -12 20	; "text" -
	190	[343]	GETTABLE 	20 0 -22	; "medium_font_face"
	191	[343]	SETTABLE 	19 -14 20	; "face" -
	192	[341]	CALL     	17 3 0
	193	[345]	SETLIST  	16 0 1	; 1
	194	[339]	CALL     	14 3 2
	195	[346]	GETUPVAL 	15 1	; CenterContainer
	196	[346]	SELF     	15 15 -3	; "new"
	197	[346]	NEWTABLE 	17 0 1
	198	[347]	GETUPVAL 	18 2	; Geom
	199	[347]	SELF     	18 18 -3	; "new"
	200	[347]	NEWTABLE 	20 0 2
	201	[347]	SETTABLE 	20 -5 5	; "w" -
	202	[347]	SETTABLE 	20 -6 6	; "h" -
	203	[347]	CALL     	18 3 2
	204	[347]	SETTABLE 	17 -4 18	; "dimen" -
	205	[348]	GETUPVAL 	18 5	; TextWidget
	206	[348]	SELF     	18 18 -3	; "new"
	207	[348]	NEWTABLE 	20 0 2
	208	[349]	GETTABLE 	21 0 -25	; "today_pages"
	209	[349]	SETTABLE 	20 -12 21	; "text" -
	210	[350]	GETTABLE 	21 0 -22	; "medium_font_face"
	211	[350]	SETTABLE 	20 -14 21	; "face" -
	212	[348]	CALL     	18 3 0
	213	[352]	SETLIST  	17 0 1	; 1
	214	[346]	CALL     	15 3 2
	215	[353]	GETUPVAL 	16 1	; CenterContainer
	216	[353]	SELF     	16 16 -3	; "new"
	217	[353]	NEWTABLE 	18 0 1
	218	[354]	GETUPVAL 	19 2	; Geom
	219	[354]	SELF     	19 19 -3	; "new"
	220	[354]	NEWTABLE 	21 0 2
	221	[354]	SETTABLE 	21 -5 5	; "w" -
	222	[354]	SETTABLE 	21 -6 6	; "h" -
	223	[354]	CALL     	19 3 2
	224	[354]	SETTABLE 	18 -4 19	; "dimen" -
	225	[355]	GETUPVAL 	19 5	; TextWidget
	226	[355]	SELF     	19 19 -3	; "new"
	227	[355]	NEWTABLE 	21 0 2
	228	[356]	GETUPVAL 	22 10	; util
	229	[356]	GETTABLE 	22 22 -23	; "secondsToClock"
	230	[356]	GETTABLE 	23 0 -26	; "today_period"
	231	[356]	LOADBOOL 	24 1 0
	232	[356]	CALL     	22 3 2
	233	[356]	SETTABLE 	21 -12 22	; "text" -
	234	[357]	GETTABLE 	22 0 -22	; "medium_font_face"
	235	[357]	SETTABLE 	21 -14 22	; "face" -
	236	[355]	CALL     	19 3 0
	237	[359]	SETLIST  	18 0 1	; 1
	238	[353]	CALL     	16 3 0
	239	[360]	SETLIST  	12 0 1	; 1
	240	[330]	CALL     	10 3 2
	241	[361]	GETGLOBAL	11 -27	; table
	242	[361]	GETTABLE 	11 11 -28	; "insert"
	243	[361]	MOVE     	12 4
	244	[361]	MOVE     	13 7
	245	[361]	CALL     	11 3 1
	246	[362]	GETGLOBAL	11 -27	; table
	247	[362]	GETTABLE 	11 11 -28	; "insert"
	248	[362]	MOVE     	12 4
	249	[362]	MOVE     	13 9
	250	[362]	CALL     	11 3 1
	251	[363]	GETGLOBAL	11 -27	; table
	252	[363]	GETTABLE 	11 11 -28	; "insert"
	253	[363]	MOVE     	12 4
	254	[363]	MOVE     	13 10
	255	[363]	CALL     	11 3 1
	256	[364]	GETGLOBAL	11 -27	; table
	257	[364]	GETTABLE 	11 11 -28	; "insert"
	258	[364]	MOVE     	12 4
	259	[364]	MOVE     	13 9
	260	[364]	CALL     	11 3 1
	261	[365]	GETGLOBAL	11 -27	; table
	262	[365]	GETTABLE 	11 11 -28	; "insert"
	263	[365]	MOVE     	12 4
	264	[365]	MOVE     	13 9
	265	[365]	CALL     	11 3 1
	266	[366]	GETGLOBAL	11 -27	; table
	267	[366]	GETTABLE 	11 11 -28	; "insert"
	268	[366]	MOVE     	12 3
	269	[366]	MOVE     	13 4
	270	[366]	CALL     	11 3 1
	271	[367]	GETUPVAL 	11 1	; CenterContainer
	272	[367]	SELF     	11 11 -3	; "new"
	273	[367]	NEWTABLE 	13 1 1
	274	[368]	GETUPVAL 	14 2	; Geom
	275	[368]	SELF     	14 14 -3	; "new"
	276	[368]	NEWTABLE 	16 0 2
	277	[368]	GETTABLE 	17 0 -29	; "screen_width"
	278	[368]	SETTABLE 	16 -5 17	; "w" -
	279	[368]	GETTABLE 	17 0 -30	; "screen_height"
	280	[368]	MUL      	17 17 -31	; - 0.13
	281	[368]	SETTABLE 	16 -6 17	; "h" -
	282	[368]	CALL     	14 3 2
	283	[368]	SETTABLE 	13 -4 14	; "dimen" -
	284	[370]	MOVE     	14 3
	285	[370]	SETLIST  	13 1 1	; 1
	286	[367]	TAILCALL 	11 3 0
	287	[370]	RETURN   	11 0
	288	[371]	RETURN   	0 1

function <./plugins/statistics.koplugin/readerprogress.lua:373,496> (399 instructions, 1596 bytes at 0x7fd095c0ab40)
2 params, 28 slots, 11 upvalues, 14 locals, 37 constants, 0 functions
	1	[374]	GETUPVAL 	2 0	; Screen
	2	[374]	SELF     	2 2 -1	; "scaleBySize"
	3	[374]	LOADK    	4 -2	; 60
	4	[374]	CALL     	2 3 2
	5	[375]	SELF     	3 0 -3	; "getTotalStats"
	6	[375]	GETTABLE 	5 0 -4	; "dates"
	7	[375]	LEN      	5 5
	8	[375]	CALL     	3 3 3
	9	[376]	GETUPVAL 	5 1	; CenterContainer
	10	[376]	SELF     	5 5 -5	; "new"
	11	[376]	NEWTABLE 	7 0 1
	12	[377]	GETUPVAL 	8 2	; Geom
	13	[377]	SELF     	8 8 -5	; "new"
	14	[377]	NEWTABLE 	10 0 2
	15	[377]	SETTABLE 	10 -7 1	; "w" -
	16	[377]	SETTABLE 	10 -8 2	; "h" -
	17	[377]	CALL     	8 3 2
	18	[377]	SETTABLE 	7 -6 8	; "dimen" -
	19	[376]	CALL     	5 3 2
	20	[379]	GETUPVAL 	6 3	; VerticalGroup
	21	[379]	SELF     	6 6 -5	; "new"
	22	[379]	NEWTABLE 	8 0 1
	23	[379]	SETTABLE 	8 -9 -10	; "align" "left"
	24	[379]	CALL     	6 3 2
	25	[380]	DIV      	7 1 -11	; - 4
	26	[381]	DIV      	8 2 -12	; - 3
	27	[382]	GETUPVAL 	9 4	; HorizontalGroup
	28	[382]	SELF     	9 9 -5	; "new"
	29	[382]	NEWTABLE 	11 3 1
	30	[383]	SETTABLE 	11 -9 -13	; "align" "center"
	31	[384]	GETUPVAL 	12 1	; CenterContainer
	32	[384]	SELF     	12 12 -5	; "new"
	33	[384]	NEWTABLE 	14 0 1
	34	[385]	GETUPVAL 	15 2	; Geom
	35	[385]	SELF     	15 15 -5	; "new"
	36	[385]	NEWTABLE 	17 0 2
	37	[385]	SETTABLE 	17 -7 7	; "w" -
	38	[385]	SETTABLE 	17 -8 8	; "h" -
	39	[385]	CALL     	15 3 2
	40	[385]	SETTABLE 	14 -6 15	; "dimen" -
	41	[386]	GETUPVAL 	15 5	; TextWidget
	42	[386]	SELF     	15 15 -5	; "new"
	43	[386]	NEWTABLE 	17 0 3
	44	[387]	GETUPVAL 	18 6	; Size
	45	[387]	GETTABLE 	18 18 -14	; "padding"
	46	[387]	GETTABLE 	18 18 -15	; "default"
	47	[387]	SETTABLE 	17 -14 18	; "padding" -
	48	[388]	GETUPVAL 	18 7	; _
	49	[388]	LOADK    	19 -17	; "Total"
	50	[388]	CALL     	18 2 2
	51	[388]	SETTABLE 	17 -16 18	; "text" -
	52	[389]	GETTABLE 	18 0 -19	; "small_font_face"
	53	[389]	SETTABLE 	17 -18 18	; "face" -
	54	[386]	CALL     	15 3 0
	55	[391]	SETLIST  	14 0 1	; 1
	56	[384]	CALL     	12 3 2
	57	[392]	GETUPVAL 	13 1	; CenterContainer
	58	[392]	SELF     	13 13 -5	; "new"
	59	[392]	NEWTABLE 	15 0 1
	60	[393]	GETUPVAL 	16 2	; Geom
	61	[393]	SELF     	16 16 -5	; "new"
	62	[393]	NEWTABLE 	18 0 2
	63	[393]	SETTABLE 	18 -7 7	; "w" -
	64	[393]	SETTABLE 	18 -8 8	; "h" -
	65	[393]	CALL     	16 3 2
	66	[393]	SETTABLE 	15 -6 16	; "dimen" -
	67	[394]	GETUPVAL 	16 5	; TextWidget
	68	[394]	SELF     	16 16 -5	; "new"
	69	[394]	NEWTABLE 	18 0 2
	70	[395]	GETUPVAL 	19 7	; _
	71	[395]	LOADK    	20 -17	; "Total"
	72	[395]	CALL     	19 2 2
	73	[395]	SETTABLE 	18 -16 19	; "text" -
	74	[396]	GETTABLE 	19 0 -19	; "small_font_face"
	75	[396]	SETTABLE 	18 -18 19	; "face" -
	76	[394]	CALL     	16 3 0
	77	[398]	SETLIST  	15 0 1	; 1
	78	[392]	CALL     	13 3 2
	79	[399]	GETUPVAL 	14 1	; CenterContainer
	80	[399]	SELF     	14 14 -5	; "new"
	81	[399]	NEWTABLE 	16 0 1
	82	[400]	GETUPVAL 	17 2	; Geom
	83	[400]	SELF     	17 17 -5	; "new"
	84	[400]	NEWTABLE 	19 0 2
	85	[400]	SETTABLE 	19 -7 7	; "w" -
	86	[400]	SETTABLE 	19 -8 8	; "h" -
	87	[400]	CALL     	17 3 2
	88	[400]	SETTABLE 	16 -6 17	; "dimen" -
	89	[401]	GETUPVAL 	17 5	; TextWidget
	90	[401]	SELF     	17 17 -5	; "new"
	91	[401]	NEWTABLE 	19 0 2
	92	[402]	GETUPVAL 	20 7	; _
	93	[402]	LOADK    	21 -20	; "Average"
	94	[402]	CALL     	20 2 2
	95	[402]	SETTABLE 	19 -16 20	; "text" -
	96	[403]	GETTABLE 	20 0 -19	; "small_font_face"
	97	[403]	SETTABLE 	19 -18 20	; "face" -
	98	[401]	CALL     	17 3 0
	99	[405]	SETLIST  	16 0 1	; 1
	100	[399]	CALL     	14 3 2
	101	[406]	GETUPVAL 	15 1	; CenterContainer
	102	[406]	SELF     	15 15 -5	; "new"
	103	[406]	NEWTABLE 	17 0 1
	104	[407]	GETUPVAL 	18 2	; Geom
	105	[407]	SELF     	18 18 -5	; "new"
	106	[407]	NEWTABLE 	20 0 2
	107	[407]	SETTABLE 	20 -7 7	; "w" -
	108	[407]	SETTABLE 	20 -8 8	; "h" -
	109	[407]	CALL     	18 3 2
	110	[407]	SETTABLE 	17 -6 18	; "dimen" -
	111	[408]	GETUPVAL 	18 5	; TextWidget
	112	[408]	SELF     	18 18 -5	; "new"
	113	[408]	NEWTABLE 	20 0 2
	114	[409]	GETUPVAL 	21 7	; _
	115	[409]	LOADK    	22 -20	; "Average"
	116	[409]	CALL     	21 2 2
	117	[409]	SETTABLE 	20 -16 21	; "text" -
	118	[410]	GETTABLE 	21 0 -19	; "small_font_face"
	119	[410]	SETTABLE 	20 -18 21	; "face" -
	120	[408]	CALL     	18 3 0
	121	[412]	SETLIST  	17 0 1	; 1
	122	[406]	CALL     	15 3 0
	123	[413]	SETLIST  	11 0 1	; 1
	124	[382]	CALL     	9 3 2
	125	[415]	GETUPVAL 	10 4	; HorizontalGroup
	126	[415]	SELF     	10 10 -5	; "new"
	127	[415]	NEWTABLE 	12 3 1
	128	[416]	SETTABLE 	12 -9 -13	; "align" "center"
	129	[417]	GETUPVAL 	13 1	; CenterContainer
	130	[417]	SELF     	13 13 -5	; "new"
	131	[417]	NEWTABLE 	15 0 1
	132	[418]	GETUPVAL 	16 2	; Geom
	133	[418]	SELF     	16 16 -5	; "new"
	134	[418]	NEWTABLE 	18 0 2
	135	[418]	SETTABLE 	18 -7 7	; "w" -
	136	[418]	SETTABLE 	18 -8 8	; "h" -
	137	[418]	CALL     	16 3 2
	138	[418]	SETTABLE 	15 -6 16	; "dimen" -
	139	[419]	GETUPVAL 	16 5	; TextWidget
	140	[419]	SELF     	16 16 -5	; "new"
	141	[419]	NEWTABLE 	18 0 2
	142	[420]	GETUPVAL 	19 7	; _
	143	[420]	LOADK    	20 -21	; "Pages"
	144	[420]	CALL     	19 2 2
	145	[420]	SETTABLE 	18 -16 19	; "text" -
	146	[421]	GETTABLE 	19 0 -19	; "small_font_face"
	147	[421]	SETTABLE 	18 -18 19	; "face" -
	148	[419]	CALL     	16 3 0
	149	[423]	SETLIST  	15 0 1	; 1
	150	[417]	CALL     	13 3 2
	151	[424]	GETUPVAL 	14 1	; CenterContainer
	152	[424]	SELF     	14 14 -5	; "new"
	153	[424]	NEWTABLE 	16 0 1
	154	[425]	GETUPVAL 	17 2	; Geom
	155	[425]	SELF     	17 17 -5	; "new"
	156	[425]	NEWTABLE 	19 0 2
	157	[425]	SETTABLE 	19 -7 7	; "w" -
	158	[425]	SETTABLE 	19 -8 8	; "h" -
	159	[425]	CALL     	17 3 2
	160	[425]	SETTABLE 	16 -6 17	; "dimen" -
	161	[426]	GETUPVAL 	17 5	; TextWidget
	162	[426]	SELF     	17 17 -5	; "new"
	163	[426]	NEWTABLE 	19 0 2
	164	[427]	GETUPVAL 	20 7	; _
	165	[427]	LOADK    	21 -22	; "Time"
	166	[427]	CALL     	20 2 2
	167	[427]	SETTABLE 	19 -16 20	; "text" -
	168	[428]	GETTABLE 	20 0 -19	; "small_font_face"
	169	[428]	SETTABLE 	19 -18 20	; "face" -
	170	[426]	CALL     	17 3 0
	171	[430]	SETLIST  	16 0 1	; 1
	172	[424]	CALL     	14 3 2
	173	[431]	GETUPVAL 	15 1	; CenterContainer
	174	[431]	SELF     	15 15 -5	; "new"
	175	[431]	NEWTABLE 	17 0 1
	176	[432]	GETUPVAL 	18 2	; Geom
	177	[432]	SELF     	18 18 -5	; "new"
	178	[432]	NEWTABLE 	20 0 2
	179	[432]	SETTABLE 	20 -7 7	; "w" -
	180	[432]	SETTABLE 	20 -8 8	; "h" -
	181	[432]	CALL     	18 3 2
	182	[432]	SETTABLE 	17 -6 18	; "dimen" -
	183	[433]	GETUPVAL 	18 5	; TextWidget
	184	[433]	SELF     	18 18 -5	; "new"
	185	[433]	NEWTABLE 	20 0 2
	186	[434]	GETUPVAL 	21 7	; _
	187	[434]	LOADK    	22 -21	; "Pages"
	188	[434]	CALL     	21 2 2
	189	[434]	SETTABLE 	20 -16 21	; "text" -
	190	[435]	GETTABLE 	21 0 -19	; "small_font_face"
	191	[435]	SETTABLE 	20 -18 21	; "face" -
	192	[433]	CALL     	18 3 0
	193	[437]	SETLIST  	17 0 1	; 1
	194	[431]	CALL     	15 3 2
	195	[438]	GETUPVAL 	16 1	; CenterContainer
	196	[438]	SELF     	16 16 -5	; "new"
	197	[438]	NEWTABLE 	18 0 1
	198	[439]	GETUPVAL 	19 2	; Geom
	199	[439]	SELF     	19 19 -5	; "new"
	200	[439]	NEWTABLE 	21 0 2
	201	[439]	SETTABLE 	21 -7 7	; "w" -
	202	[439]	SETTABLE 	21 -8 8	; "h" -
	203	[439]	CALL     	19 3 2
	204	[439]	SETTABLE 	18 -6 19	; "dimen" -
	205	[440]	GETUPVAL 	19 5	; TextWidget
	206	[440]	SELF     	19 19 -5	; "new"
	207	[440]	NEWTABLE 	21 0 2
	208	[441]	GETUPVAL 	22 7	; _
	209	[441]	LOADK    	23 -22	; "Time"
	210	[441]	CALL     	22 2 2
	211	[441]	SETTABLE 	21 -16 22	; "text" -
	212	[442]	GETTABLE 	22 0 -19	; "small_font_face"
	213	[442]	SETTABLE 	21 -18 22	; "face" -
	214	[440]	CALL     	19 3 0
	215	[444]	SETLIST  	18 0 1	; 1
	216	[438]	CALL     	16 3 0
	217	[445]	SETLIST  	12 0 1	; 1
	218	[415]	CALL     	10 3 2
	219	[447]	GETUPVAL 	11 8	; HorizontalSpan
	220	[447]	SELF     	11 11 -5	; "new"
	221	[447]	NEWTABLE 	13 0 1
	222	[447]	GETUPVAL 	14 0	; Screen
	223	[447]	SELF     	14 14 -1	; "scaleBySize"
	224	[447]	LOADK    	16 -24	; 15
	225	[447]	CALL     	14 3 2
	226	[447]	SETTABLE 	13 -23 14	; "width" -
	227	[447]	CALL     	11 3 2
	228	[448]	GETUPVAL 	12 4	; HorizontalGroup
	229	[448]	SELF     	12 12 -5	; "new"
	230	[448]	NEWTABLE 	14 0 1
	231	[449]	SETTABLE 	14 -9 -13	; "align" "center"
	232	[450]	GETUPVAL 	15 9	; LeftContainer
	233	[450]	SELF     	15 15 -5	; "new"
	234	[450]	NEWTABLE 	17 1 1
	235	[451]	GETUPVAL 	18 2	; Geom
	236	[451]	SELF     	18 18 -5	; "new"
	237	[451]	NEWTABLE 	20 0 1
	238	[451]	GETUPVAL 	21 6	; Size
	239	[451]	GETTABLE 	21 21 -25	; "span"
	240	[451]	GETTABLE 	21 21 -26	; "horizontal_default"
	241	[451]	SETTABLE 	20 -8 21	; "h" -
	242	[451]	CALL     	18 3 2
	243	[451]	SETTABLE 	17 -6 18	; "dimen" -
	244	[453]	MOVE     	18 11
	245	[453]	SETLIST  	17 1 1	; 1
	246	[450]	CALL     	15 3 0
	247	[454]	SETLIST  	14 0 1	; 1
	248	[448]	CALL     	12 3 2
	249	[456]	GETUPVAL 	13 4	; HorizontalGroup
	250	[456]	SELF     	13 13 -5	; "new"
	251	[456]	NEWTABLE 	15 3 1
	252	[457]	SETTABLE 	15 -9 -13	; "align" "center"
	253	[458]	GETUPVAL 	16 1	; CenterContainer
	254	[458]	SELF     	16 16 -5	; "new"
	255	[458]	NEWTABLE 	18 0 1
	256	[459]	GETUPVAL 	19 2	; Geom
	257	[459]	SELF     	19 19 -5	; "new"
	258	[459]	NEWTABLE 	21 0 2
	259	[459]	SETTABLE 	21 -7 7	; "w" -
	260	[459]	SETTABLE 	21 -8 8	; "h" -
	261	[459]	CALL     	19 3 2
	262	[459]	SETTABLE 	18 -6 19	; "dimen" -
	263	[460]	GETUPVAL 	19 5	; TextWidget
	264	[460]	SELF     	19 19 -5	; "new"
	265	[460]	NEWTABLE 	21 0 2
	266	[461]	GETGLOBAL	22 -27	; tostring
	267	[461]	MOVE     	23 4
	268	[461]	CALL     	22 2 2
	269	[461]	SETTABLE 	21 -16 22	; "text" -
	270	[462]	GETTABLE 	22 0 -28	; "medium_font_face"
	271	[462]	SETTABLE 	21 -18 22	; "face" -
	272	[460]	CALL     	19 3 0
	273	[464]	SETLIST  	18 0 1	; 1
	274	[458]	CALL     	16 3 2
	275	[465]	GETUPVAL 	17 1	; CenterContainer
	276	[465]	SELF     	17 17 -5	; "new"
	277	[465]	NEWTABLE 	19 0 1
	278	[466]	GETUPVAL 	20 2	; Geom
	279	[466]	SELF     	20 20 -5	; "new"
	280	[466]	NEWTABLE 	22 0 2
	281	[466]	SETTABLE 	22 -7 7	; "w" -
	282	[466]	SETTABLE 	22 -8 8	; "h" -
	283	[466]	CALL     	20 3 2
	284	[466]	SETTABLE 	19 -6 20	; "dimen" -
	285	[467]	GETUPVAL 	20 5	; TextWidget
	286	[467]	SELF     	20 20 -5	; "new"
	287	[467]	NEWTABLE 	22 0 2
	288	[468]	GETUPVAL 	23 10	; util
	289	[468]	GETTABLE 	23 23 -29	; "secondsToClock"
	290	[468]	GETGLOBAL	24 -30	; math
	291	[468]	GETTABLE 	24 24 -31	; "floor"
	292	[468]	MOVE     	25 3
	293	[468]	CALL     	24 2 2
	294	[468]	LOADBOOL 	25 1 0
	295	[468]	CALL     	23 3 2
	296	[468]	SETTABLE 	22 -16 23	; "text" -
	297	[469]	GETTABLE 	23 0 -28	; "medium_font_face"
	298	[469]	SETTABLE 	22 -18 23	; "face" -
	299	[467]	CALL     	20 3 0
	300	[471]	SETLIST  	19 0 1	; 1
	301	[465]	CALL     	17 3 2
	302	[472]	GETUPVAL 	18 1	; CenterContainer
	303	[472]	SELF     	18 18 -5	; "new"
	304	[472]	NEWTABLE 	20 0 1
	305	[473]	GETUPVAL 	21 2	; Geom
	306	[473]	SELF     	21 21 -5	; "new"
	307	[473]	NEWTABLE 	23 0 2
	308	[473]	SETTABLE 	23 -7 7	; "w" -
	309	[473]	SETTABLE 	23 -8 8	; "h" -
	310	[473]	CALL     	21 3 2
	311	[473]	SETTABLE 	20 -6 21	; "dimen" -
	312	[474]	GETUPVAL 	21 5	; TextWidget
	313	[474]	SELF     	21 21 -5	; "new"
	314	[474]	NEWTABLE 	23 0 2
	315	[475]	GETGLOBAL	24 -27	; tostring
	316	[475]	GETGLOBAL	25 -30	; math
	317	[475]	GETTABLE 	25 25 -31	; "floor"
	318	[475]	DIV      	26 4 -32	; - 7
	319	[475]	CALL     	25 2 0
	320	[475]	CALL     	24 0 2
	321	[475]	SETTABLE 	23 -16 24	; "text" -
	322	[476]	GETTABLE 	24 0 -28	; "medium_font_face"
	323	[476]	SETTABLE 	23 -18 24	; "face" -
	324	[474]	CALL     	21 3 0
	325	[478]	SETLIST  	20 0 1	; 1
	326	[472]	CALL     	18 3 2
	327	[479]	GETUPVAL 	19 1	; CenterContainer
	328	[479]	SELF     	19 19 -5	; "new"
	329	[479]	NEWTABLE 	21 0 1
	330	[480]	GETUPVAL 	22 2	; Geom
	331	[480]	SELF     	22 22 -5	; "new"
	332	[480]	NEWTABLE 	24 0 2
	333	[480]	SETTABLE 	24 -7 7	; "w" -
	334	[480]	SETTABLE 	24 -8 8	; "h" -
	335	[480]	CALL     	22 3 2
	336	[480]	SETTABLE 	21 -6 22	; "dimen" -
	337	[481]	GETUPVAL 	22 5	; TextWidget
	338	[481]	SELF     	22 22 -5	; "new"
	339	[481]	NEWTABLE 	24 0 2
	340	[482]	GETUPVAL 	25 10	; util
	341	[482]	GETTABLE 	25 25 -29	; "secondsToClock"
	342	[482]	GETGLOBAL	26 -30	; math
	343	[482]	GETTABLE 	26 26 -31	; "floor"
	344	[482]	MOVE     	27 3
	345	[482]	CALL     	26 2 2
	346	[482]	DIV      	26 26 -32	; - 7
	347	[482]	LOADBOOL 	27 1 0
	348	[482]	CALL     	25 3 2
	349	[482]	SETTABLE 	24 -16 25	; "text" -
	350	[483]	GETTABLE 	25 0 -28	; "medium_font_face"
	351	[483]	SETTABLE 	24 -18 25	; "face" -
	352	[481]	CALL     	22 3 0
	353	[485]	SETLIST  	21 0 1	; 1
	354	[479]	CALL     	19 3 0
	355	[486]	SETLIST  	15 0 1	; 1
	356	[456]	CALL     	13 3 2
	357	[487]	GETGLOBAL	14 -33	; table
	358	[487]	GETTABLE 	14 14 -34	; "insert"
	359	[487]	MOVE     	15 6
	360	[487]	MOVE     	16 9
	361	[487]	CALL     	14 3 1
	362	[488]	GETGLOBAL	14 -33	; table
	363	[488]	GETTABLE 	14 14 -34	; "insert"
	364	[488]	MOVE     	15 6
	365	[488]	MOVE     	16 10
	366	[488]	CALL     	14 3 1
	367	[489]	GETGLOBAL	14 -33	; table
	368	[489]	GETTABLE 	14 14 -34	; "insert"
	369	[489]	MOVE     	15 6
	370	[489]	MOVE     	16 12
	371	[489]	CALL     	14 3 1
	372	[490]	GETGLOBAL	14 -33	; table
	373	[490]	GETTABLE 	14 14 -34	; "insert"
	374	[490]	MOVE     	15 6
	375	[490]	MOVE     	16 13
	376	[490]	CALL     	14 3 1
	377	[491]	GETGLOBAL	14 -33	; table
	378	[491]	GETTABLE 	14 14 -34	; "insert"
	379	[491]	MOVE     	15 5
	380	[491]	MOVE     	16 6
	381	[491]	CALL     	14 3 1
	382	[492]	GETUPVAL 	14 1	; CenterContainer
	383	[492]	SELF     	14 14 -5	; "new"
	384	[492]	NEWTABLE 	16 1 1
	385	[493]	GETUPVAL 	17 2	; Geom
	386	[493]	SELF     	17 17 -5	; "new"
	387	[493]	NEWTABLE 	19 0 2
	388	[493]	GETTABLE 	20 0 -35	; "screen_width"
	389	[493]	SETTABLE 	19 -7 20	; "w" -
	390	[493]	GETTABLE 	20 0 -36	; "screen_height"
	391	[493]	MUL      	20 20 -37	; - 0.1
	392	[493]	SETTABLE 	19 -8 20	; "h" -
	393	[493]	CALL     	17 3 2
	394	[493]	SETTABLE 	16 -6 17	; "dimen" -
	395	[495]	MOVE     	17 5
	396	[495]	SETLIST  	16 1 1	; 1
	397	[492]	TAILCALL 	14 3 0
	398	[495]	RETURN   	14 0
	399	[496]	RETURN   	0 1

function <./plugins/statistics.koplugin/readerprogress.lua:498,500> (4 instructions, 16 bytes at 0x7fd095c0b340)
1 param, 3 slots, 0 upvalues, 1 local, 1 constant, 0 functions
	1	[499]	SELF     	1 0 -1	; "onClose"
	2	[499]	TAILCALL 	1 2 0
	3	[499]	RETURN   	1 0
	4	[500]	RETURN   	0 1

function <./plugins/statistics.koplugin/readerprogress.lua:502,516> (24 instructions, 96 bytes at 0x7fd095c0b450)
3 params, 7 slots, 1 upvalue, 3 locals, 8 constants, 0 functions
	1	[503]	GETTABLE 	3 2 -1	; "direction"
	2	[503]	EQ       	0 3 -2	; - "south"
	3	[503]	JMP      	3	; to 7
	4	[505]	SELF     	3 0 -3	; "onClose"
	5	[505]	CALL     	3 2 1
	6	[505]	JMP      	17	; to 24
	7	[506]	GETTABLE 	3 2 -1	; "direction"
	8	[506]	EQ       	1 3 -4	; - "east"
	9	[506]	JMP      	14	; to 24
	10	[506]	GETTABLE 	3 2 -1	; "direction"
	11	[506]	EQ       	1 3 -5	; - "west"
	12	[506]	JMP      	11	; to 24
	13	[506]	GETTABLE 	3 2 -1	; "direction"
	14	[506]	EQ       	0 3 -6	; - "north"
	15	[506]	JMP      	1	; to 17
	16	[508]	JMP      	7	; to 24
	17	[511]	GETUPVAL 	3 0	; UIManager
	18	[511]	SELF     	3 3 -7	; "setDirty"
	19	[511]	LOADNIL  	5 5
	20	[511]	LOADK    	6 -8	; "full"
	21	[511]	CALL     	3 4 1
	22	[514]	LOADBOOL 	3 0 0
	23	[514]	RETURN   	3 2
	24	[516]	RETURN   	0 1

function <./plugins/statistics.koplugin/readerprogress.lua:518,521> (7 instructions, 28 bytes at 0x7fd095c0b920)
1 param, 4 slots, 1 upvalue, 1 local, 1 constant, 0 functions
	1	[519]	GETUPVAL 	1 0	; UIManager
	2	[519]	SELF     	1 1 -1	; "close"
	3	[519]	MOVE     	3 0
	4	[519]	CALL     	1 3 1
	5	[520]	LOADBOOL 	1 1 0
	6	[520]	RETURN   	1 2
	7	[521]	RETURN   	0 1
