
main <./spec/unit/readerrolling_spec.lua:0,0> (5 instructions, 20 bytes at 0x7ffe95c068d0)
0+ params, 3 slots, 0 upvalues, 0 locals, 2 constants, 1 function
	1	[1]	GETGLOBAL	0 -1	; describe
	2	[1]	LOADK    	1 -2	; "Readerrolling module"
	3	[214]	CLOSURE  	2 0	; 0x7ffe95c06b70
	4	[1]	CALL     	0 3 1
	5	[214]	RETURN   	0 1

function <./spec/unit/readerrolling_spec.lua:1,214> (44 instructions, 176 bytes at 0x7ffe95c06b70)
0 params, 8 slots, 0 upvalues, 5 locals, 7 constants, 6 functions
	1	[5]	GETGLOBAL	5 -1	; setup
	2	[16]	CLOSURE  	6 0	; 0x7ffe95c06f20
	3	[16]	MOVE     	0 0
	4	[16]	MOVE     	0 1
	5	[16]	MOVE     	0 2
	6	[16]	MOVE     	0 3
	7	[16]	MOVE     	0 4
	8	[5]	CALL     	5 2 1
	9	[18]	GETGLOBAL	5 -2	; describe
	10	[18]	LOADK    	6 -3	; "test in portrait screen mode"
	11	[107]	CLOSURE  	7 1	; 0x7ffe95c06d90
	12	[107]	MOVE     	0 3
	13	[107]	MOVE     	0 2
	14	[107]	MOVE     	0 4
	15	[107]	MOVE     	0 1
	16	[107]	MOVE     	0 0
	17	[18]	CALL     	5 3 1
	18	[109]	GETGLOBAL	5 -2	; describe
	19	[109]	LOADK    	6 -4	; "test in landscape screen mode"
	20	[155]	CLOSURE  	7 2	; 0x7ffe95c09640
	21	[155]	MOVE     	0 3
	22	[155]	MOVE     	0 2
	23	[155]	MOVE     	0 4
	24	[109]	CALL     	5 3 1
	25	[157]	GETGLOBAL	5 -2	; describe
	26	[157]	LOADK    	6 -5	; "switching screen mode should not change current page number"
	27	[183]	CLOSURE  	7 3	; 0x7ffe95c0af60
	28	[183]	MOVE     	0 3
	29	[183]	MOVE     	0 2
	30	[183]	MOVE     	0 4
	31	[157]	CALL     	5 3 1
	32	[185]	GETGLOBAL	5 -2	; describe
	33	[185]	LOADK    	6 -6	; "test changing word gap - space condensing"
	34	[197]	CLOSURE  	7 4	; 0x7ffe95c08270
	35	[197]	MOVE     	0 3
	36	[197]	MOVE     	0 2
	37	[185]	CALL     	5 3 1
	38	[199]	GETGLOBAL	5 -2	; describe
	39	[199]	LOADK    	6 -7	; "test initialization"
	40	[213]	CLOSURE  	7 5	; 0x7ffe95c0c480
	41	[213]	MOVE     	0 1
	42	[213]	MOVE     	0 0
	43	[199]	CALL     	5 3 1
	44	[214]	RETURN   	0 1

function <./spec/unit/readerrolling_spec.lua:5,16> (30 instructions, 120 bytes at 0x7ffe95c06f20)
0 params, 7 slots, 5 upvalues, 1 local, 10 constants, 0 functions
	1	[6]	GETGLOBAL	0 -1	; require
	2	[6]	LOADK    	1 -2	; "commonrequire"
	3	[6]	CALL     	0 2 1
	4	[7]	GETGLOBAL	0 -1	; require
	5	[7]	LOADK    	1 -3	; "document/documentregistry"
	6	[7]	CALL     	0 2 2
	7	[7]	SETUPVAL 	0 0	; DocumentRegistry
	8	[8]	GETGLOBAL	0 -1	; require
	9	[8]	LOADK    	1 -4	; "apps/reader/readerui"
	10	[8]	CALL     	0 2 2
	11	[8]	SETUPVAL 	0 1	; ReaderUI
	12	[9]	GETGLOBAL	0 -1	; require
	13	[9]	LOADK    	1 -5	; "ui/event"
	14	[9]	CALL     	0 2 2
	15	[9]	SETUPVAL 	0 2	; Event
	16	[11]	LOADK    	0 -6	; "spec/front/unit/data/juliet.epub"
	17	[12]	GETUPVAL 	1 1	; ReaderUI
	18	[12]	SELF     	1 1 -7	; "new"
	19	[12]	NEWTABLE 	3 0 1
	20	[13]	GETUPVAL 	4 0	; DocumentRegistry
	21	[13]	SELF     	4 4 -9	; "openDocument"
	22	[13]	MOVE     	6 0
	23	[13]	CALL     	4 3 2
	24	[13]	SETTABLE 	3 -8 4	; "document" -
	25	[12]	CALL     	1 3 2
	26	[14]	SETUPVAL 	1 3	; readerui
	27	[15]	GETUPVAL 	1 3	; readerui
	28	[15]	GETTABLE 	1 1 -10	; "rolling"
	29	[15]	SETUPVAL 	1 4	; rolling
	30	[16]	RETURN   	0 1

function <./spec/unit/readerrolling_spec.lua:18,107> (42 instructions, 168 bytes at 0x7ffe95c06d90)
0 params, 3 slots, 5 upvalues, 0 locals, 8 constants, 7 functions
	1	[19]	GETGLOBAL	0 -1	; it
	2	[19]	LOADK    	1 -2	; "should goto portrait screen mode"
	3	[21]	CLOSURE  	2 0	; 0x7ffe95c078d0
	4	[21]	GETUPVAL 	0 0	; readerui
	5	[21]	GETUPVAL 	0 1	; Event
	6	[19]	CALL     	0 3 1
	7	[23]	GETGLOBAL	0 -1	; it
	8	[23]	LOADK    	1 -3	; "should goto certain page"
	9	[28]	CLOSURE  	2 1	; 0x7ffe95c06700
	10	[28]	GETUPVAL 	0 2	; rolling
	11	[23]	CALL     	0 3 1
	12	[30]	GETGLOBAL	0 -1	; it
	13	[30]	LOADK    	1 -4	; "should goto relative page"
	14	[38]	CLOSURE  	2 2	; 0x7ffe95c08340
	15	[38]	GETUPVAL 	0 2	; rolling
	16	[30]	CALL     	0 3 1
	17	[40]	GETGLOBAL	0 -1	; it
	18	[40]	LOADK    	1 -5	; "should goto next chapter"
	19	[47]	CLOSURE  	2 3	; 0x7ffe95c08a40
	20	[47]	GETUPVAL 	0 0	; readerui
	21	[47]	GETUPVAL 	0 2	; rolling
	22	[40]	CALL     	0 3 1
	23	[49]	GETGLOBAL	0 -1	; it
	24	[49]	LOADK    	1 -6	; "should goto previous chapter"
	25	[56]	CLOSURE  	2 4	; 0x7ffe95c08780
	26	[56]	GETUPVAL 	0 0	; readerui
	27	[56]	GETUPVAL 	0 2	; rolling
	28	[49]	CALL     	0 3 1
	29	[58]	GETGLOBAL	0 -1	; it
	30	[58]	LOADK    	1 -7	; "should emit EndOfBook event at the end of sample epub"
	31	[77]	CLOSURE  	2 5	; 0x7ffe95c06780
	32	[77]	GETUPVAL 	0 0	; readerui
	33	[77]	GETUPVAL 	0 2	; rolling
	34	[58]	CALL     	0 3 1
	35	[79]	GETGLOBAL	0 -1	; it
	36	[79]	LOADK    	1 -8	; "should emit EndOfBook event at the end sample txt"
	37	[106]	CLOSURE  	2 6	; 0x7ffe95c083c0
	38	[106]	GETUPVAL 	0 3	; ReaderUI
	39	[106]	GETUPVAL 	0 4	; DocumentRegistry
	40	[106]	GETUPVAL 	0 0	; readerui
	41	[79]	CALL     	0 3 1
	42	[107]	RETURN   	0 1

function <./spec/unit/readerrolling_spec.lua:19,21> (9 instructions, 36 bytes at 0x7ffe95c078d0)
0 params, 6 slots, 2 upvalues, 0 locals, 4 constants, 0 functions
	1	[20]	GETUPVAL 	0 0	; readerui
	2	[20]	SELF     	0 0 -1	; "handleEvent"
	3	[20]	GETUPVAL 	2 1	; Event
	4	[20]	SELF     	2 2 -2	; "new"
	5	[20]	LOADK    	4 -3	; "ChangeScreenMode"
	6	[20]	LOADK    	5 -4	; "portrait"
	7	[20]	CALL     	2 4 0
	8	[20]	CALL     	0 0 1
	9	[21]	RETURN   	0 1

function <./spec/unit/readerrolling_spec.lua:23,28> (17 instructions, 68 bytes at 0x7ffe95c06700)
0 params, 7 slots, 1 upvalue, 4 locals, 8 constants, 0 functions
	1	[24]	LOADK    	0 -1	; 1
	2	[24]	LOADK    	1 -2	; 10
	3	[24]	LOADK    	2 -3	; 5
	4	[24]	FORPREP  	0 11	; to 16
	5	[25]	GETUPVAL 	4 0	; rolling
	6	[25]	SELF     	4 4 -4	; "onGotoPage"
	7	[25]	MOVE     	6 3
	8	[25]	CALL     	4 3 1
	9	[26]	GETGLOBAL	4 -5	; assert
	10	[26]	GETTABLE 	4 4 -6	; "are"
	11	[26]	GETTABLE 	4 4 -7	; "same"
	12	[26]	MOVE     	5 3
	13	[26]	GETUPVAL 	6 0	; rolling
	14	[26]	GETTABLE 	6 6 -8	; "current_page"
	15	[26]	CALL     	4 3 1
	16	[24]	FORLOOP  	0 -12	; to 5
	17	[28]	RETURN   	0 1

function <./spec/unit/readerrolling_spec.lua:30,38> (32 instructions, 128 bytes at 0x7ffe95c08340)
0 params, 7 slots, 1 upvalue, 4 locals, 11 constants, 0 functions
	1	[31]	LOADK    	0 -1	; 20
	2	[31]	LOADK    	1 -2	; 40
	3	[31]	LOADK    	2 -3	; 5
	4	[31]	FORPREP  	0 26	; to 31
	5	[32]	GETUPVAL 	4 0	; rolling
	6	[32]	SELF     	4 4 -4	; "onGotoPage"
	7	[32]	MOVE     	6 3
	8	[32]	CALL     	4 3 1
	9	[33]	GETUPVAL 	4 0	; rolling
	10	[33]	SELF     	4 4 -5	; "onGotoViewRel"
	11	[33]	LOADK    	6 -6	; 1
	12	[33]	CALL     	4 3 1
	13	[34]	GETGLOBAL	4 -7	; assert
	14	[34]	GETTABLE 	4 4 -8	; "are"
	15	[34]	GETTABLE 	4 4 -9	; "same"
	16	[34]	ADD      	5 3 -6	; - 1
	17	[34]	GETUPVAL 	6 0	; rolling
	18	[34]	GETTABLE 	6 6 -10	; "current_page"
	19	[34]	CALL     	4 3 1
	20	[35]	GETUPVAL 	4 0	; rolling
	21	[35]	SELF     	4 4 -5	; "onGotoViewRel"
	22	[35]	LOADK    	6 -11	; -1
	23	[35]	CALL     	4 3 1
	24	[36]	GETGLOBAL	4 -7	; assert
	25	[36]	GETTABLE 	4 4 -8	; "are"
	26	[36]	GETTABLE 	4 4 -9	; "same"
	27	[36]	MOVE     	5 3
	28	[36]	GETUPVAL 	6 0	; rolling
	29	[36]	GETTABLE 	6 6 -10	; "current_page"
	30	[36]	CALL     	4 3 1
	31	[31]	FORLOOP  	0 -27	; to 5
	32	[38]	RETURN   	0 1

function <./spec/unit/readerrolling_spec.lua:40,47> (25 instructions, 100 bytes at 0x7ffe95c08a40)
0 params, 10 slots, 2 upvalues, 5 locals, 12 constants, 0 functions
	1	[41]	GETUPVAL 	0 0	; readerui
	2	[41]	GETTABLE 	0 0 -1	; "toc"
	3	[42]	LOADK    	1 -2	; 30
	4	[42]	LOADK    	2 -3	; 50
	5	[42]	LOADK    	3 -4	; 5
	6	[42]	FORPREP  	1 17	; to 24
	7	[43]	GETUPVAL 	5 1	; rolling
	8	[43]	SELF     	5 5 -5	; "onGotoPage"
	9	[43]	MOVE     	7 4
	10	[43]	CALL     	5 3 1
	11	[44]	GETUPVAL 	5 1	; rolling
	12	[44]	SELF     	5 5 -6	; "onGotoNextChapter"
	13	[44]	CALL     	5 2 1
	14	[45]	GETGLOBAL	5 -7	; assert
	15	[45]	GETTABLE 	5 5 -8	; "are"
	16	[45]	GETTABLE 	5 5 -9	; "same"
	17	[45]	SELF     	6 0 -10	; "getNextChapter"
	18	[45]	MOVE     	8 4
	19	[45]	LOADK    	9 -11	; 0
	20	[45]	CALL     	6 4 2
	21	[45]	GETUPVAL 	7 1	; rolling
	22	[45]	GETTABLE 	7 7 -12	; "current_page"
	23	[45]	CALL     	5 3 1
	24	[42]	FORLOOP  	1 -18	; to 7
	25	[47]	RETURN   	0 1

function <./spec/unit/readerrolling_spec.lua:49,56> (25 instructions, 100 bytes at 0x7ffe95c08780)
0 params, 10 slots, 2 upvalues, 5 locals, 12 constants, 0 functions
	1	[50]	GETUPVAL 	0 0	; readerui
	2	[50]	GETTABLE 	0 0 -1	; "toc"
	3	[51]	LOADK    	1 -2	; 60
	4	[51]	LOADK    	2 -3	; 80
	5	[51]	LOADK    	3 -4	; 5
	6	[51]	FORPREP  	1 17	; to 24
	7	[52]	GETUPVAL 	5 1	; rolling
	8	[52]	SELF     	5 5 -5	; "onGotoPage"
	9	[52]	MOVE     	7 4
	10	[52]	CALL     	5 3 1
	11	[53]	GETUPVAL 	5 1	; rolling
	12	[53]	SELF     	5 5 -6	; "onGotoPrevChapter"
	13	[53]	CALL     	5 2 1
	14	[54]	GETGLOBAL	5 -7	; assert
	15	[54]	GETTABLE 	5 5 -8	; "are"
	16	[54]	GETTABLE 	5 5 -9	; "same"
	17	[54]	SELF     	6 0 -10	; "getPreviousChapter"
	18	[54]	MOVE     	8 4
	19	[54]	LOADK    	9 -11	; 0
	20	[54]	CALL     	6 4 2
	21	[54]	GETUPVAL 	7 1	; rolling
	22	[54]	GETTABLE 	7 7 -12	; "current_page"
	23	[54]	CALL     	5 3 1
	24	[51]	FORLOOP  	1 -18	; to 7
	25	[56]	RETURN   	0 1

function <./spec/unit/readerrolling_spec.lua:58,77> (60 instructions, 240 bytes at 0x7ffe95c06780)
0 params, 5 slots, 2 upvalues, 1 local, 12 constants, 1 function
	1	[59]	LOADBOOL 	0 0 0
	2	[60]	GETUPVAL 	1 0	; readerui
	3	[62]	CLOSURE  	2 0	; 0x7ffe95c09020
	4	[62]	MOVE     	0 0
	5	[62]	SETTABLE 	1 -1 2	; "onEndOfBook" -
	6	[64]	GETUPVAL 	1 1	; rolling
	7	[64]	SELF     	1 1 -2	; "onGotoPage"
	8	[64]	LOADK    	3 -3	; 1
	9	[64]	CALL     	1 3 1
	10	[65]	GETGLOBAL	1 -4	; assert
	11	[65]	GETTABLE 	1 1 -5	; "is"
	12	[65]	GETTABLE 	1 1 -6	; "falsy"
	13	[65]	MOVE     	2 0
	14	[65]	CALL     	1 2 1
	15	[66]	GETUPVAL 	1 1	; rolling
	16	[66]	SELF     	1 1 -7	; "onGotoViewRel"
	17	[66]	LOADK    	3 -8	; -1
	18	[66]	CALL     	1 3 1
	19	[67]	GETUPVAL 	1 1	; rolling
	20	[67]	SELF     	1 1 -7	; "onGotoViewRel"
	21	[67]	LOADK    	3 -8	; -1
	22	[67]	CALL     	1 3 1
	23	[68]	GETGLOBAL	1 -4	; assert
	24	[68]	GETTABLE 	1 1 -5	; "is"
	25	[68]	GETTABLE 	1 1 -6	; "falsy"
	26	[68]	MOVE     	2 0
	27	[68]	CALL     	1 2 1
	28	[70]	GETUPVAL 	1 1	; rolling
	29	[70]	SELF     	1 1 -2	; "onGotoPage"
	30	[70]	GETUPVAL 	3 0	; readerui
	31	[70]	GETTABLE 	3 3 -9	; "document"
	32	[70]	SELF     	3 3 -10	; "getPageCount"
	33	[70]	CALL     	3 2 0
	34	[70]	CALL     	1 0 1
	35	[71]	GETGLOBAL	1 -4	; assert
	36	[71]	GETTABLE 	1 1 -5	; "is"
	37	[71]	GETTABLE 	1 1 -6	; "falsy"
	38	[71]	MOVE     	2 0
	39	[71]	CALL     	1 2 1
	40	[72]	GETUPVAL 	1 1	; rolling
	41	[72]	SELF     	1 1 -7	; "onGotoViewRel"
	42	[72]	LOADK    	3 -3	; 1
	43	[72]	CALL     	1 3 1
	44	[73]	GETGLOBAL	1 -4	; assert
	45	[73]	GETTABLE 	1 1 -5	; "is"
	46	[73]	GETTABLE 	1 1 -11	; "truthy"
	47	[73]	MOVE     	2 0
	48	[73]	CALL     	1 2 1
	49	[74]	GETUPVAL 	1 1	; rolling
	50	[74]	SELF     	1 1 -7	; "onGotoViewRel"
	51	[74]	LOADK    	3 -3	; 1
	52	[74]	CALL     	1 3 1
	53	[75]	GETGLOBAL	1 -4	; assert
	54	[75]	GETTABLE 	1 1 -5	; "is"
	55	[75]	GETTABLE 	1 1 -11	; "truthy"
	56	[75]	MOVE     	2 0
	57	[75]	CALL     	1 2 1
	58	[76]	GETUPVAL 	1 0	; readerui
	59	[76]	SETTABLE 	1 -1 -12	; "onEndOfBook" nil
	60	[77]	RETURN   	0 1

function <./spec/unit/readerrolling_spec.lua:60,62> (3 instructions, 12 bytes at 0x7ffe95c09020)
0 params, 2 slots, 1 upvalue, 0 locals, 0 constants, 0 functions
	1	[61]	LOADBOOL 	0 1 0
	2	[61]	SETUPVAL 	0 0	; called
	3	[62]	RETURN   	0 1

function <./spec/unit/readerrolling_spec.lua:79,106> (71 instructions, 284 bytes at 0x7ffe95c083c0)
0 params, 8 slots, 3 upvalues, 4 locals, 17 constants, 1 function
	1	[80]	LOADK    	0 -1	; "spec/front/unit/data/sample.txt"
	2	[81]	GETUPVAL 	1 0	; ReaderUI
	3	[81]	SELF     	1 1 -2	; "new"
	4	[81]	NEWTABLE 	3 0 1
	5	[82]	GETUPVAL 	4 1	; DocumentRegistry
	6	[82]	SELF     	4 4 -4	; "openDocument"
	7	[82]	MOVE     	6 0
	8	[82]	CALL     	4 3 2
	9	[82]	SETTABLE 	3 -3 4	; "document" -
	10	[81]	CALL     	1 3 2
	11	[84]	LOADBOOL 	2 0 0
	12	[87]	CLOSURE  	3 0	; 0x7ffe95c09700
	13	[87]	MOVE     	0 2
	14	[87]	SETTABLE 	1 -5 3	; "onEndOfBook" -
	15	[88]	GETTABLE 	3 1 -6	; "rolling"
	16	[90]	SELF     	4 3 -7	; "onGotoPage"
	17	[90]	LOADK    	6 -8	; 1
	18	[90]	CALL     	4 3 1
	19	[91]	GETGLOBAL	4 -9	; assert
	20	[91]	GETTABLE 	4 4 -10	; "is"
	21	[91]	GETTABLE 	4 4 -11	; "falsy"
	22	[91]	MOVE     	5 2
	23	[91]	CALL     	4 2 1
	24	[92]	SELF     	4 3 -12	; "onGotoViewRel"
	25	[92]	LOADK    	6 -13	; -1
	26	[92]	CALL     	4 3 1
	27	[93]	SELF     	4 3 -12	; "onGotoViewRel"
	28	[93]	LOADK    	6 -13	; -1
	29	[93]	CALL     	4 3 1
	30	[94]	GETGLOBAL	4 -9	; assert
	31	[94]	GETTABLE 	4 4 -10	; "is"
	32	[94]	GETTABLE 	4 4 -11	; "falsy"
	33	[94]	MOVE     	5 2
	34	[94]	CALL     	4 2 1
	35	[96]	SELF     	4 3 -7	; "onGotoPage"
	36	[96]	LOADK    	6 -14	; 3
	37	[96]	CALL     	4 3 1
	38	[97]	GETGLOBAL	4 -9	; assert
	39	[97]	GETTABLE 	4 4 -10	; "is"
	40	[97]	GETTABLE 	4 4 -11	; "falsy"
	41	[97]	MOVE     	5 2
	42	[97]	CALL     	4 2 1
	43	[98]	SELF     	4 3 -12	; "onGotoViewRel"
	44	[98]	LOADK    	6 -8	; 1
	45	[98]	CALL     	4 3 1
	46	[99]	GETGLOBAL	4 -9	; assert
	47	[99]	GETTABLE 	4 4 -10	; "is"
	48	[99]	GETTABLE 	4 4 -11	; "falsy"
	49	[99]	MOVE     	5 2
	50	[99]	CALL     	4 2 1
	51	[101]	SELF     	4 3 -7	; "onGotoPage"
	52	[101]	GETTABLE 	6 1 -3	; "document"
	53	[101]	SELF     	6 6 -15	; "getPageCount"
	54	[101]	CALL     	6 2 0
	55	[101]	CALL     	4 0 1
	56	[102]	GETGLOBAL	4 -9	; assert
	57	[102]	GETTABLE 	4 4 -10	; "is"
	58	[102]	GETTABLE 	4 4 -11	; "falsy"
	59	[102]	MOVE     	5 2
	60	[102]	CALL     	4 2 1
	61	[103]	SELF     	4 3 -12	; "onGotoViewRel"
	62	[103]	LOADK    	6 -8	; 1
	63	[103]	CALL     	4 3 1
	64	[104]	GETGLOBAL	4 -9	; assert
	65	[104]	GETTABLE 	4 4 -10	; "is"
	66	[104]	GETTABLE 	4 4 -16	; "truthy"
	67	[104]	MOVE     	5 2
	68	[104]	CALL     	4 2 1
	69	[105]	GETUPVAL 	4 2	; readerui
	70	[105]	SETTABLE 	4 -5 -17	; "onEndOfBook" nil
	71	[106]	RETURN   	0 1

function <./spec/unit/readerrolling_spec.lua:85,87> (3 instructions, 12 bytes at 0x7ffe95c09700)
0 params, 2 slots, 1 upvalue, 0 locals, 0 constants, 0 functions
	1	[86]	LOADBOOL 	0 1 0
	2	[86]	SETUPVAL 	0 0	; called
	3	[87]	RETURN   	0 1

function <./spec/unit/readerrolling_spec.lua:109,155> (35 instructions, 140 bytes at 0x7ffe95c09640)
0 params, 3 slots, 3 upvalues, 0 locals, 7 constants, 6 functions
	1	[110]	GETGLOBAL	0 -1	; it
	2	[110]	LOADK    	1 -2	; "should go to landscape screen mode"
	3	[112]	CLOSURE  	2 0	; 0x7ffe95c09bb0
	4	[112]	GETUPVAL 	0 0	; readerui
	5	[112]	GETUPVAL 	0 1	; Event
	6	[110]	CALL     	0 3 1
	7	[113]	GETGLOBAL	0 -1	; it
	8	[113]	LOADK    	1 -3	; "should goto certain page"
	9	[118]	CLOSURE  	2 1	; 0x7ffe95c0a2c0
	10	[118]	GETUPVAL 	0 2	; rolling
	11	[113]	CALL     	0 3 1
	12	[119]	GETGLOBAL	0 -1	; it
	13	[119]	LOADK    	1 -4	; "should goto relative page"
	14	[127]	CLOSURE  	2 2	; 0x7ffe95c0a9e0
	15	[127]	GETUPVAL 	0 2	; rolling
	16	[119]	CALL     	0 3 1
	17	[128]	GETGLOBAL	0 -1	; it
	18	[128]	LOADK    	1 -5	; "should goto next chapter"
	19	[135]	CLOSURE  	2 3	; 0x7ffe95c0b060
	20	[135]	GETUPVAL 	0 0	; readerui
	21	[135]	GETUPVAL 	0 2	; rolling
	22	[128]	CALL     	0 3 1
	23	[136]	GETGLOBAL	0 -1	; it
	24	[136]	LOADK    	1 -6	; "should goto previous chapter"
	25	[143]	CLOSURE  	2 4	; 0x7ffe95c0ac20
	26	[143]	GETUPVAL 	0 0	; readerui
	27	[143]	GETUPVAL 	0 2	; rolling
	28	[136]	CALL     	0 3 1
	29	[144]	GETGLOBAL	0 -1	; it
	30	[144]	LOADK    	1 -7	; "should emit EndOfBook event at the end"
	31	[154]	CLOSURE  	2 5	; 0x7ffe95c0aca0
	32	[154]	GETUPVAL 	0 2	; rolling
	33	[154]	GETUPVAL 	0 0	; readerui
	34	[144]	CALL     	0 3 1
	35	[155]	RETURN   	0 1

function <./spec/unit/readerrolling_spec.lua:110,112> (9 instructions, 36 bytes at 0x7ffe95c09bb0)
0 params, 6 slots, 2 upvalues, 0 locals, 4 constants, 0 functions
	1	[111]	GETUPVAL 	0 0	; readerui
	2	[111]	SELF     	0 0 -1	; "handleEvent"
	3	[111]	GETUPVAL 	2 1	; Event
	4	[111]	SELF     	2 2 -2	; "new"
	5	[111]	LOADK    	4 -3	; "ChangeScreenMode"
	6	[111]	LOADK    	5 -4	; "landscape"
	7	[111]	CALL     	2 4 0
	8	[111]	CALL     	0 0 1
	9	[112]	RETURN   	0 1

function <./spec/unit/readerrolling_spec.lua:113,118> (17 instructions, 68 bytes at 0x7ffe95c0a2c0)
0 params, 7 slots, 1 upvalue, 4 locals, 8 constants, 0 functions
	1	[114]	LOADK    	0 -1	; 1
	2	[114]	LOADK    	1 -2	; 10
	3	[114]	LOADK    	2 -3	; 5
	4	[114]	FORPREP  	0 11	; to 16
	5	[115]	GETUPVAL 	4 0	; rolling
	6	[115]	SELF     	4 4 -4	; "onGotoPage"
	7	[115]	MOVE     	6 3
	8	[115]	CALL     	4 3 1
	9	[116]	GETGLOBAL	4 -5	; assert
	10	[116]	GETTABLE 	4 4 -6	; "are"
	11	[116]	GETTABLE 	4 4 -7	; "same"
	12	[116]	MOVE     	5 3
	13	[116]	GETUPVAL 	6 0	; rolling
	14	[116]	GETTABLE 	6 6 -8	; "current_page"
	15	[116]	CALL     	4 3 1
	16	[114]	FORLOOP  	0 -12	; to 5
	17	[118]	RETURN   	0 1

function <./spec/unit/readerrolling_spec.lua:119,127> (32 instructions, 128 bytes at 0x7ffe95c0a9e0)
0 params, 7 slots, 1 upvalue, 4 locals, 11 constants, 0 functions
	1	[120]	LOADK    	0 -1	; 20
	2	[120]	LOADK    	1 -2	; 40
	3	[120]	LOADK    	2 -3	; 5
	4	[120]	FORPREP  	0 26	; to 31
	5	[121]	GETUPVAL 	4 0	; rolling
	6	[121]	SELF     	4 4 -4	; "onGotoPage"
	7	[121]	MOVE     	6 3
	8	[121]	CALL     	4 3 1
	9	[122]	GETUPVAL 	4 0	; rolling
	10	[122]	SELF     	4 4 -5	; "onGotoViewRel"
	11	[122]	LOADK    	6 -6	; 1
	12	[122]	CALL     	4 3 1
	13	[123]	GETGLOBAL	4 -7	; assert
	14	[123]	GETTABLE 	4 4 -8	; "are"
	15	[123]	GETTABLE 	4 4 -9	; "same"
	16	[123]	ADD      	5 3 -6	; - 1
	17	[123]	GETUPVAL 	6 0	; rolling
	18	[123]	GETTABLE 	6 6 -10	; "current_page"
	19	[123]	CALL     	4 3 1
	20	[124]	GETUPVAL 	4 0	; rolling
	21	[124]	SELF     	4 4 -5	; "onGotoViewRel"
	22	[124]	LOADK    	6 -11	; -1
	23	[124]	CALL     	4 3 1
	24	[125]	GETGLOBAL	4 -7	; assert
	25	[125]	GETTABLE 	4 4 -8	; "are"
	26	[125]	GETTABLE 	4 4 -9	; "same"
	27	[125]	MOVE     	5 3
	28	[125]	GETUPVAL 	6 0	; rolling
	29	[125]	GETTABLE 	6 6 -10	; "current_page"
	30	[125]	CALL     	4 3 1
	31	[120]	FORLOOP  	0 -27	; to 5
	32	[127]	RETURN   	0 1

function <./spec/unit/readerrolling_spec.lua:128,135> (25 instructions, 100 bytes at 0x7ffe95c0b060)
0 params, 10 slots, 2 upvalues, 5 locals, 12 constants, 0 functions
	1	[129]	GETUPVAL 	0 0	; readerui
	2	[129]	GETTABLE 	0 0 -1	; "toc"
	3	[130]	LOADK    	1 -2	; 30
	4	[130]	LOADK    	2 -3	; 50
	5	[130]	LOADK    	3 -4	; 5
	6	[130]	FORPREP  	1 17	; to 24
	7	[131]	GETUPVAL 	5 1	; rolling
	8	[131]	SELF     	5 5 -5	; "onGotoPage"
	9	[131]	MOVE     	7 4
	10	[131]	CALL     	5 3 1
	11	[132]	GETUPVAL 	5 1	; rolling
	12	[132]	SELF     	5 5 -6	; "onGotoNextChapter"
	13	[132]	CALL     	5 2 1
	14	[133]	GETGLOBAL	5 -7	; assert
	15	[133]	GETTABLE 	5 5 -8	; "are"
	16	[133]	GETTABLE 	5 5 -9	; "same"
	17	[133]	SELF     	6 0 -10	; "getNextChapter"
	18	[133]	MOVE     	8 4
	19	[133]	LOADK    	9 -11	; 0
	20	[133]	CALL     	6 4 2
	21	[133]	GETUPVAL 	7 1	; rolling
	22	[133]	GETTABLE 	7 7 -12	; "current_page"
	23	[133]	CALL     	5 3 1
	24	[130]	FORLOOP  	1 -18	; to 7
	25	[135]	RETURN   	0 1

function <./spec/unit/readerrolling_spec.lua:136,143> (25 instructions, 100 bytes at 0x7ffe95c0ac20)
0 params, 10 slots, 2 upvalues, 5 locals, 12 constants, 0 functions
	1	[137]	GETUPVAL 	0 0	; readerui
	2	[137]	GETTABLE 	0 0 -1	; "toc"
	3	[138]	LOADK    	1 -2	; 60
	4	[138]	LOADK    	2 -3	; 80
	5	[138]	LOADK    	3 -4	; 5
	6	[138]	FORPREP  	1 17	; to 24
	7	[139]	GETUPVAL 	5 1	; rolling
	8	[139]	SELF     	5 5 -5	; "onGotoPage"
	9	[139]	MOVE     	7 4
	10	[139]	CALL     	5 3 1
	11	[140]	GETUPVAL 	5 1	; rolling
	12	[140]	SELF     	5 5 -6	; "onGotoPrevChapter"
	13	[140]	CALL     	5 2 1
	14	[141]	GETGLOBAL	5 -7	; assert
	15	[141]	GETTABLE 	5 5 -8	; "are"
	16	[141]	GETTABLE 	5 5 -9	; "same"
	17	[141]	SELF     	6 0 -10	; "getPreviousChapter"
	18	[141]	MOVE     	8 4
	19	[141]	LOADK    	9 -11	; 0
	20	[141]	CALL     	6 4 2
	21	[141]	GETUPVAL 	7 1	; rolling
	22	[141]	GETTABLE 	7 7 -12	; "current_page"
	23	[141]	CALL     	5 3 1
	24	[138]	FORLOOP  	1 -18	; to 7
	25	[143]	RETURN   	0 1

function <./spec/unit/readerrolling_spec.lua:144,154> (28 instructions, 112 bytes at 0x7ffe95c0aca0)
0 params, 4 slots, 2 upvalues, 1 local, 10 constants, 1 function
	1	[145]	GETUPVAL 	0 0	; rolling
	2	[145]	SELF     	0 0 -1	; "onGotoPage"
	3	[145]	GETUPVAL 	2 1	; readerui
	4	[145]	GETTABLE 	2 2 -2	; "document"
	5	[145]	SELF     	2 2 -3	; "getPageCount"
	6	[145]	CALL     	2 2 0
	7	[145]	CALL     	0 0 1
	8	[146]	LOADBOOL 	0 0 0
	9	[147]	GETUPVAL 	1 1	; readerui
	10	[149]	CLOSURE  	2 0	; 0x7ffe95c0b5c0
	11	[149]	MOVE     	0 0
	12	[149]	SETTABLE 	1 -4 2	; "onEndOfBook" -
	13	[150]	GETUPVAL 	1 0	; rolling
	14	[150]	SELF     	1 1 -5	; "onGotoViewRel"
	15	[150]	LOADK    	3 -6	; 1
	16	[150]	CALL     	1 3 1
	17	[151]	GETUPVAL 	1 0	; rolling
	18	[151]	SELF     	1 1 -5	; "onGotoViewRel"
	19	[151]	LOADK    	3 -6	; 1
	20	[151]	CALL     	1 3 1
	21	[152]	GETGLOBAL	1 -7	; assert
	22	[152]	GETTABLE 	1 1 -8	; "is"
	23	[152]	GETTABLE 	1 1 -9	; "truthy"
	24	[152]	MOVE     	2 0
	25	[152]	CALL     	1 2 1
	26	[153]	GETUPVAL 	1 1	; readerui
	27	[153]	SETTABLE 	1 -4 -10	; "onEndOfBook" nil
	28	[154]	RETURN   	0 1

function <./spec/unit/readerrolling_spec.lua:147,149> (3 instructions, 12 bytes at 0x7ffe95c0b5c0)
0 params, 2 slots, 1 upvalue, 0 locals, 0 constants, 0 functions
	1	[148]	LOADBOOL 	0 1 0
	2	[148]	SETUPVAL 	0 0	; called
	3	[149]	RETURN   	0 1

function <./spec/unit/readerrolling_spec.lua:157,183> (20 instructions, 80 bytes at 0x7ffe95c0af60)
0 params, 3 slots, 3 upvalues, 0 locals, 4 constants, 3 functions
	1	[158]	GETGLOBAL	0 -1	; teardown
	2	[160]	CLOSURE  	1 0	; 0x7ffe95c0a670
	3	[160]	GETUPVAL 	0 0	; readerui
	4	[160]	GETUPVAL 	0 1	; Event
	5	[158]	CALL     	0 2 1
	6	[161]	GETGLOBAL	0 -2	; it
	7	[161]	LOADK    	1 -3	; "for portrait-landscape-portrait switching"
	8	[171]	CLOSURE  	2 1	; 0x7ffe95c0a340
	9	[171]	GETUPVAL 	0 0	; readerui
	10	[171]	GETUPVAL 	0 1	; Event
	11	[171]	GETUPVAL 	0 2	; rolling
	12	[161]	CALL     	0 3 1
	13	[172]	GETGLOBAL	0 -2	; it
	14	[172]	LOADK    	1 -4	; "for landscape-portrait-landscape switching"
	15	[182]	CLOSURE  	2 2	; 0x7ffe95c0b700
	16	[182]	GETUPVAL 	0 0	; readerui
	17	[182]	GETUPVAL 	0 1	; Event
	18	[182]	GETUPVAL 	0 2	; rolling
	19	[172]	CALL     	0 3 1
	20	[183]	RETURN   	0 1

function <./spec/unit/readerrolling_spec.lua:158,160> (9 instructions, 36 bytes at 0x7ffe95c0a670)
0 params, 6 slots, 2 upvalues, 0 locals, 4 constants, 0 functions
	1	[159]	GETUPVAL 	0 0	; readerui
	2	[159]	SELF     	0 0 -1	; "handleEvent"
	3	[159]	GETUPVAL 	2 1	; Event
	4	[159]	SELF     	2 2 -2	; "new"
	5	[159]	LOADK    	4 -3	; "ChangeScreenMode"
	6	[159]	LOADK    	5 -4	; "portrait"
	7	[159]	CALL     	2 4 0
	8	[159]	CALL     	0 0 1
	9	[160]	RETURN   	0 1

function <./spec/unit/readerrolling_spec.lua:161,171> (55 instructions, 220 bytes at 0x7ffe95c0a340)
0 params, 10 slots, 3 upvalues, 4 locals, 14 constants, 0 functions
	1	[162]	LOADK    	0 -1	; 80
	2	[162]	LOADK    	1 -2	; 100
	3	[162]	LOADK    	2 -3	; 10
	4	[162]	FORPREP  	0 49	; to 54
	5	[163]	GETUPVAL 	4 0	; readerui
	6	[163]	SELF     	4 4 -4	; "handleEvent"
	7	[163]	GETUPVAL 	6 1	; Event
	8	[163]	SELF     	6 6 -5	; "new"
	9	[163]	LOADK    	8 -6	; "ChangeScreenMode"
	10	[163]	LOADK    	9 -7	; "portrait"
	11	[163]	CALL     	6 4 0
	12	[163]	CALL     	4 0 1
	13	[164]	GETUPVAL 	4 2	; rolling
	14	[164]	SELF     	4 4 -8	; "onGotoPage"
	15	[164]	MOVE     	6 3
	16	[164]	CALL     	4 3 1
	17	[165]	GETGLOBAL	4 -9	; assert
	18	[165]	GETTABLE 	4 4 -10	; "are"
	19	[165]	GETTABLE 	4 4 -11	; "same"
	20	[165]	MOVE     	5 3
	21	[165]	GETUPVAL 	6 2	; rolling
	22	[165]	GETTABLE 	6 6 -12	; "current_page"
	23	[165]	CALL     	4 3 1
	24	[166]	GETUPVAL 	4 0	; readerui
	25	[166]	SELF     	4 4 -4	; "handleEvent"
	26	[166]	GETUPVAL 	6 1	; Event
	27	[166]	SELF     	6 6 -5	; "new"
	28	[166]	LOADK    	8 -6	; "ChangeScreenMode"
	29	[166]	LOADK    	9 -13	; "landscape"
	30	[166]	CALL     	6 4 0
	31	[166]	CALL     	4 0 1
	32	[167]	GETGLOBAL	4 -9	; assert
	33	[167]	GETTABLE 	4 4 -14	; "are_not"
	34	[167]	GETTABLE 	4 4 -11	; "same"
	35	[167]	MOVE     	5 3
	36	[167]	GETUPVAL 	6 2	; rolling
	37	[167]	GETTABLE 	6 6 -12	; "current_page"
	38	[167]	CALL     	4 3 1
	39	[168]	GETUPVAL 	4 0	; readerui
	40	[168]	SELF     	4 4 -4	; "handleEvent"
	41	[168]	GETUPVAL 	6 1	; Event
	42	[168]	SELF     	6 6 -5	; "new"
	43	[168]	LOADK    	8 -6	; "ChangeScreenMode"
	44	[168]	LOADK    	9 -7	; "portrait"
	45	[168]	CALL     	6 4 0
	46	[168]	CALL     	4 0 1
	47	[169]	GETGLOBAL	4 -9	; assert
	48	[169]	GETTABLE 	4 4 -10	; "are"
	49	[169]	GETTABLE 	4 4 -11	; "same"
	50	[169]	MOVE     	5 3
	51	[169]	GETUPVAL 	6 2	; rolling
	52	[169]	GETTABLE 	6 6 -12	; "current_page"
	53	[169]	CALL     	4 3 1
	54	[162]	FORLOOP  	0 -50	; to 5
	55	[171]	RETURN   	0 1

function <./spec/unit/readerrolling_spec.lua:172,182> (55 instructions, 220 bytes at 0x7ffe95c0b700)
0 params, 10 slots, 3 upvalues, 4 locals, 14 constants, 0 functions
	1	[173]	LOADK    	0 -1	; 110
	2	[173]	LOADK    	1 -2	; 130
	3	[173]	LOADK    	2 -3	; 10
	4	[173]	FORPREP  	0 49	; to 54
	5	[174]	GETUPVAL 	4 0	; readerui
	6	[174]	SELF     	4 4 -4	; "handleEvent"
	7	[174]	GETUPVAL 	6 1	; Event
	8	[174]	SELF     	6 6 -5	; "new"
	9	[174]	LOADK    	8 -6	; "ChangeScreenMode"
	10	[174]	LOADK    	9 -7	; "landscape"
	11	[174]	CALL     	6 4 0
	12	[174]	CALL     	4 0 1
	13	[175]	GETUPVAL 	4 2	; rolling
	14	[175]	SELF     	4 4 -8	; "onGotoPage"
	15	[175]	MOVE     	6 3
	16	[175]	CALL     	4 3 1
	17	[176]	GETGLOBAL	4 -9	; assert
	18	[176]	GETTABLE 	4 4 -10	; "are"
	19	[176]	GETTABLE 	4 4 -11	; "same"
	20	[176]	MOVE     	5 3
	21	[176]	GETUPVAL 	6 2	; rolling
	22	[176]	GETTABLE 	6 6 -12	; "current_page"
	23	[176]	CALL     	4 3 1
	24	[177]	GETUPVAL 	4 0	; readerui
	25	[177]	SELF     	4 4 -4	; "handleEvent"
	26	[177]	GETUPVAL 	6 1	; Event
	27	[177]	SELF     	6 6 -5	; "new"
	28	[177]	LOADK    	8 -6	; "ChangeScreenMode"
	29	[177]	LOADK    	9 -13	; "portrait"
	30	[177]	CALL     	6 4 0
	31	[177]	CALL     	4 0 1
	32	[178]	GETGLOBAL	4 -9	; assert
	33	[178]	GETTABLE 	4 4 -14	; "are_not"
	34	[178]	GETTABLE 	4 4 -11	; "same"
	35	[178]	MOVE     	5 3
	36	[178]	GETUPVAL 	6 2	; rolling
	37	[178]	GETTABLE 	6 6 -12	; "current_page"
	38	[178]	CALL     	4 3 1
	39	[179]	GETUPVAL 	4 0	; readerui
	40	[179]	SELF     	4 4 -4	; "handleEvent"
	41	[179]	GETUPVAL 	6 1	; Event
	42	[179]	SELF     	6 6 -5	; "new"
	43	[179]	LOADK    	8 -6	; "ChangeScreenMode"
	44	[179]	LOADK    	9 -7	; "landscape"
	45	[179]	CALL     	6 4 0
	46	[179]	CALL     	4 0 1
	47	[180]	GETGLOBAL	4 -9	; assert
	48	[180]	GETTABLE 	4 4 -10	; "are"
	49	[180]	GETTABLE 	4 4 -11	; "same"
	50	[180]	MOVE     	5 3
	51	[180]	GETUPVAL 	6 2	; rolling
	52	[180]	GETTABLE 	6 6 -12	; "current_page"
	53	[180]	CALL     	4 3 1
	54	[173]	FORLOOP  	0 -50	; to 5
	55	[182]	RETURN   	0 1

function <./spec/unit/readerrolling_spec.lua:185,197> (7 instructions, 28 bytes at 0x7ffe95c08270)
0 params, 3 slots, 2 upvalues, 0 locals, 2 constants, 1 function
	1	[186]	GETGLOBAL	0 -1	; it
	2	[186]	LOADK    	1 -2	; "should show pages for different word gap"
	3	[196]	CLOSURE  	2 0	; 0x7ffe95c0c400
	4	[196]	GETUPVAL 	0 0	; readerui
	5	[196]	GETUPVAL 	0 1	; Event
	6	[186]	CALL     	0 3 1
	7	[197]	RETURN   	0 1

function <./spec/unit/readerrolling_spec.lua:186,196> (76 instructions, 304 bytes at 0x7ffe95c0c400)
0 params, 6 slots, 2 upvalues, 0 locals, 18 constants, 0 functions
	1	[187]	GETUPVAL 	0 0	; readerui
	2	[187]	GETTABLE 	0 0 -1	; "document"
	3	[187]	SELF     	0 0 -2	; "setWordSpacing"
	4	[187]	NEWTABLE 	2 2 0
	5	[187]	LOADK    	3 -3	; 100
	6	[187]	LOADK    	4 -4	; 90
	7	[187]	SETLIST  	2 2 1	; 1
	8	[187]	CALL     	0 3 1
	9	[188]	GETUPVAL 	0 0	; readerui
	10	[188]	SELF     	0 0 -5	; "handleEvent"
	11	[188]	GETUPVAL 	2 1	; Event
	12	[188]	SELF     	2 2 -6	; "new"
	13	[188]	LOADK    	4 -7	; "ChangeScreenMode"
	14	[188]	LOADK    	5 -8	; "portrait"
	15	[188]	CALL     	2 4 0
	16	[188]	CALL     	0 0 1
	17	[189]	GETGLOBAL	0 -9	; assert
	18	[189]	GETTABLE 	0 0 -10	; "are"
	19	[189]	GETTABLE 	0 0 -11	; "same"
	20	[189]	LOADK    	1 -12	; 252
	21	[189]	GETUPVAL 	2 0	; readerui
	22	[189]	GETTABLE 	2 2 -1	; "document"
	23	[189]	SELF     	2 2 -13	; "getPageCount"
	24	[189]	CALL     	2 2 0
	25	[189]	CALL     	0 0 1
	26	[190]	GETUPVAL 	0 0	; readerui
	27	[190]	GETTABLE 	0 0 -1	; "document"
	28	[190]	SELF     	0 0 -2	; "setWordSpacing"
	29	[190]	NEWTABLE 	2 2 0
	30	[190]	LOADK    	3 -14	; 95
	31	[190]	LOADK    	4 -15	; 75
	32	[190]	SETLIST  	2 2 1	; 1
	33	[190]	CALL     	0 3 1
	34	[191]	GETUPVAL 	0 0	; readerui
	35	[191]	SELF     	0 0 -5	; "handleEvent"
	36	[191]	GETUPVAL 	2 1	; Event
	37	[191]	SELF     	2 2 -6	; "new"
	38	[191]	LOADK    	4 -7	; "ChangeScreenMode"
	39	[191]	LOADK    	5 -8	; "portrait"
	40	[191]	CALL     	2 4 0
	41	[191]	CALL     	0 0 1
	42	[192]	GETGLOBAL	0 -9	; assert
	43	[192]	GETTABLE 	0 0 -10	; "are"
	44	[192]	GETTABLE 	0 0 -11	; "same"
	45	[192]	LOADK    	1 -16	; 241
	46	[192]	GETUPVAL 	2 0	; readerui
	47	[192]	GETTABLE 	2 2 -1	; "document"
	48	[192]	SELF     	2 2 -13	; "getPageCount"
	49	[192]	CALL     	2 2 0
	50	[192]	CALL     	0 0 1
	51	[193]	GETUPVAL 	0 0	; readerui
	52	[193]	GETTABLE 	0 0 -1	; "document"
	53	[193]	SELF     	0 0 -2	; "setWordSpacing"
	54	[193]	NEWTABLE 	2 2 0
	55	[193]	LOADK    	3 -15	; 75
	56	[193]	LOADK    	4 -17	; 50
	57	[193]	SETLIST  	2 2 1	; 1
	58	[193]	CALL     	0 3 1
	59	[194]	GETUPVAL 	0 0	; readerui
	60	[194]	SELF     	0 0 -5	; "handleEvent"
	61	[194]	GETUPVAL 	2 1	; Event
	62	[194]	SELF     	2 2 -6	; "new"
	63	[194]	LOADK    	4 -7	; "ChangeScreenMode"
	64	[194]	LOADK    	5 -8	; "portrait"
	65	[194]	CALL     	2 4 0
	66	[194]	CALL     	0 0 1
	67	[195]	GETGLOBAL	0 -9	; assert
	68	[195]	GETTABLE 	0 0 -10	; "are"
	69	[195]	GETTABLE 	0 0 -11	; "same"
	70	[195]	LOADK    	1 -18	; 231
	71	[195]	GETUPVAL 	2 0	; readerui
	72	[195]	GETTABLE 	2 2 -1	; "document"
	73	[195]	SELF     	2 2 -13	; "getPageCount"
	74	[195]	CALL     	2 2 0
	75	[195]	CALL     	0 0 1
	76	[196]	RETURN   	0 1

function <./spec/unit/readerrolling_spec.lua:199,213> (7 instructions, 28 bytes at 0x7ffe95c0c480)
0 params, 3 slots, 2 upvalues, 0 locals, 2 constants, 1 function
	1	[200]	GETGLOBAL	0 -1	; it
	2	[200]	LOADK    	1 -2	; "should emit PageUpdate event after book is rendered"
	3	[212]	CLOSURE  	2 0	; 0x7ffe95c0c6c0
	4	[212]	GETUPVAL 	0 0	; ReaderUI
	5	[212]	GETUPVAL 	0 1	; DocumentRegistry
	6	[200]	CALL     	0 3 1
	7	[213]	RETURN   	0 1

function <./spec/unit/readerrolling_spec.lua:200,212> (26 instructions, 104 bytes at 0x7ffe95c0c6c0)
0 params, 9 slots, 2 upvalues, 3 locals, 10 constants, 1 function
	1	[201]	GETGLOBAL	0 -1	; require
	2	[201]	LOADK    	1 -2	; "apps/reader/modules/readerview"
	3	[201]	CALL     	0 2 2
	4	[202]	GETTABLE 	1 0 -3	; "onPageUpdate"
	5	[205]	CLOSURE  	2 0	; 0x7ffe95c0d040
	6	[205]	SETTABLE 	0 -3 2	; "onPageUpdate" -
	7	[206]	LOADK    	2 -4	; "spec/front/unit/data/sample.txt"
	8	[207]	GETGLOBAL	3 -1	; require
	9	[207]	LOADK    	4 -5	; "docsettings"
	10	[207]	CALL     	3 2 2
	11	[207]	SELF     	3 3 -6	; "open"
	12	[207]	MOVE     	5 2
	13	[207]	CALL     	3 3 2
	14	[207]	SELF     	3 3 -7	; "purge"
	15	[207]	CALL     	3 2 1
	16	[208]	GETUPVAL 	3 0	; ReaderUI
	17	[208]	SELF     	3 3 -8	; "new"
	18	[208]	NEWTABLE 	5 0 1
	19	[209]	GETUPVAL 	6 1	; DocumentRegistry
	20	[209]	SELF     	6 6 -10	; "openDocument"
	21	[209]	MOVE     	8 2
	22	[209]	CALL     	6 3 2
	23	[209]	SETTABLE 	5 -9 6	; "document" -
	24	[208]	CALL     	3 3 1
	25	[211]	SETTABLE 	0 -3 1	; "onPageUpdate" -
	26	[212]	RETURN   	0 1

function <./spec/unit/readerrolling_spec.lua:203,205> (10 instructions, 40 bytes at 0x7ffe95c0d040)
1 param, 5 slots, 0 upvalues, 1 local, 7 constants, 0 functions
	1	[204]	GETGLOBAL	1 -1	; assert
	2	[204]	GETTABLE 	1 1 -2	; "are"
	3	[204]	GETTABLE 	1 1 -3	; "same"
	4	[204]	LOADK    	2 -4	; 6
	5	[204]	GETTABLE 	3 0 -5	; "ui"
	6	[204]	GETTABLE 	3 3 -6	; "document"
	7	[204]	SELF     	3 3 -7	; "getPageCount"
	8	[204]	CALL     	3 2 0
	9	[204]	CALL     	1 0 1
	10	[205]	RETURN   	0 1
