-- BYTECODE -- readerhinting.lua:7-20
0001    TGETS    1   0   0  ; "view"
0002    TGETS    1   1   1  ; "hinting"
0003    IST          1
0004    JMP      1 => 0007
0005    KPRI     1   2
0006    RET1     1   2
0007 => KSHORT   1   1
0008    GGET     2   2      ; "DHINTCOUNT"
0009    KSHORT   3   1
0010    FORI     1 => 0045
0011 => TGETS    5   0   0  ; "view"
0012    TGETS    5   5   3  ; "state"
0013    TGETS    5   5   4  ; "page"
0014    ADDVV    5   5   4
0015    TGETS    6   0   5  ; "document"
0016    TGETS    6   6   6  ; "info"
0017    TGETS    6   6   7  ; "number_of_pages"
0018    ISGT     5   6
0019    JMP      5 => 0044
0020    TGETS    5   0   5  ; "document"
0021    MOV      6   5
0022    TGETS    5   5   8  ; "hintPage"
0023    TGETS    7   0   0  ; "view"
0024    TGETS    7   7   3  ; "state"
0025    TGETS    7   7   4  ; "page"
0026    ADDVV    7   7   4
0027    TGETS    8   0   9  ; "zoom"
0028    MOV      9   8
0029    TGETS    8   8  10  ; "getZoom"
0030    TGETS   10   0   0  ; "view"
0031    TGETS   10  10   3  ; "state"
0032    TGETS   10  10   4  ; "page"
0033    ADDVV   10  10   4
0034    CALL     8   2   3
0035    TGETS    9   0   0  ; "view"
0036    TGETS    9   9   3  ; "state"
0037    TGETS    9   9  11  ; "rotation"
0038    TGETS   10   0   0  ; "view"
0039    TGETS   10  10   3  ; "state"
0040    TGETS   10  10  12  ; "gamma"
0041    TGETS   11   0   0  ; "view"
0042    TGETS   11  11  13  ; "render_mode"
0043    CALL     5   1   7
0044 => FORL     1 => 0011
0045 => KPRI     1   2
0046    RET1     1   2

-- BYTECODE -- readerhinting.lua:22-24
0001    TGETS    2   0   0  ; "view"
0002    TSETS    1   2   1  ; "hinting"
0003    RET0     0   1

-- BYTECODE -- readerhinting.lua:26-30
0001    GGET     1   0      ; "table"
0002    TGETS    1   1   1  ; "insert"
0003    TGETS    2   0   2  ; "hinting_states"
0004    TGETS    3   0   3  ; "view"
0005    TGETS    3   3   4  ; "hinting"
0006    CALL     1   1   3
0007    TGETS    1   0   3  ; "view"
0008    KPRI     2   1
0009    TSETS    2   1   4  ; "hinting"
0010    KPRI     1   2
0011    RET1     1   2

-- BYTECODE -- readerhinting.lua:32-35
0001    TGETS    1   0   0  ; "view"
0002    GGET     2   2      ; "table"
0003    TGETS    2   2   3  ; "remove"
0004    TGETS    3   0   4  ; "hinting_states"
0005    CALL     2   2   2
0006    TSETS    2   1   1  ; "hinting"
0007    KPRI     1   2
0008    RET1     1   2

-- BYTECODE -- readerhinting.lua:0-38
0001    GGET     0   0      ; "require"
0002    KSTR     1   1      ; "ui/widget/eventlistener"
0003    CALL     0   2   2
0004    MOV      2   0
0005    TGETS    1   0   2  ; "new"
0006    TDUP     3   3
0007    TNEW     4   0
0008    TSETS    4   3   4  ; "hinting_states"
0009    CALL     1   2   3
0010    FNEW     2   6      ; readerhinting.lua:7
0011    TSETS    2   1   5  ; "onHintPage"
0012    FNEW     2   8      ; readerhinting.lua:22
0013    TSETS    2   1   7  ; "onSetHinting"
0014    FNEW     2  10      ; readerhinting.lua:26
0015    TSETS    2   1   9  ; "onDisableHinting"
0016    FNEW     2  12      ; readerhinting.lua:32
0017    TSETS    2   1  11  ; "onRestoreHinting"
0018    UCLO     0 => 0019
0019 => RET1     1   2

