
main <./frontend/apps/reader/modules/readerfooter.lua:0,0> (435 instructions, 1740 bytes at 0x7fd3a0c068f0)
0+ params, 40 slots, 0 upvalues, 48 locals, 142 constants, 51 functions
	1	[1]	GETGLOBAL	0 -1	; require
	2	[1]	LOADK    	1 -2	; "ui/bidi"
	3	[1]	CALL     	0 2 2
	4	[2]	GETGLOBAL	1 -1	; require
	5	[2]	LOADK    	2 -3	; "ffi/blitbuffer"
	6	[2]	CALL     	1 2 2
	7	[3]	GETGLOBAL	2 -1	; require
	8	[3]	LOADK    	3 -4	; "ui/widget/container/bottomcontainer"
	9	[3]	CALL     	2 2 2
	10	[4]	GETGLOBAL	3 -1	; require
	11	[4]	LOADK    	4 -5	; "ui/widget/container/centercontainer"
	12	[4]	CALL     	3 2 2
	13	[5]	GETGLOBAL	4 -1	; require
	14	[5]	LOADK    	5 -6	; "device"
	15	[5]	CALL     	4 2 2
	16	[6]	GETGLOBAL	5 -1	; require
	17	[6]	LOADK    	6 -7	; "ui/event"
	18	[6]	CALL     	5 2 2
	19	[7]	GETGLOBAL	6 -1	; require
	20	[7]	LOADK    	7 -8	; "ui/font"
	21	[7]	CALL     	6 2 2
	22	[8]	GETGLOBAL	7 -1	; require
	23	[8]	LOADK    	8 -9	; "ui/widget/container/framecontainer"
	24	[8]	CALL     	7 2 2
	25	[9]	GETGLOBAL	8 -1	; require
	26	[9]	LOADK    	9 -10	; "ui/geometry"
	27	[9]	CALL     	8 2 2
	28	[10]	GETGLOBAL	9 -1	; require
	29	[10]	LOADK    	10 -11	; "ui/widget/horizontalgroup"
	30	[10]	CALL     	9 2 2
	31	[11]	GETGLOBAL	10 -1	; require
	32	[11]	LOADK    	11 -12	; "ui/widget/horizontalspan"
	33	[11]	CALL     	10 2 2
	34	[12]	GETGLOBAL	11 -1	; require
	35	[12]	LOADK    	12 -13	; "ui/widget/container/leftcontainer"
	36	[12]	CALL     	11 2 2
	37	[13]	GETGLOBAL	12 -1	; require
	38	[13]	LOADK    	13 -14	; "ui/widget/linewidget"
	39	[13]	CALL     	12 2 2
	40	[14]	GETGLOBAL	13 -1	; require
	41	[14]	LOADK    	14 -15	; "ui/widget/progresswidget"
	42	[14]	CALL     	13 2 2
	43	[15]	GETGLOBAL	14 -1	; require
	44	[15]	LOADK    	15 -16	; "ui/widget/container/rightcontainer"
	45	[15]	CALL     	14 2 2
	46	[16]	GETGLOBAL	15 -1	; require
	47	[16]	LOADK    	16 -17	; "ui/size"
	48	[16]	CALL     	15 2 2
	49	[17]	GETGLOBAL	16 -1	; require
	50	[17]	LOADK    	17 -18	; "ui/widget/textwidget"
	51	[17]	CALL     	16 2 2
	52	[18]	GETGLOBAL	17 -1	; require
	53	[18]	LOADK    	18 -19	; "ui/uimanager"
	54	[18]	CALL     	17 2 2
	55	[19]	GETGLOBAL	18 -1	; require
	56	[19]	LOADK    	19 -20	; "ui/widget/verticalgroup"
	57	[19]	CALL     	18 2 2
	58	[20]	GETGLOBAL	19 -1	; require
	59	[20]	LOADK    	20 -21	; "ui/widget/verticalspan"
	60	[20]	CALL     	19 2 2
	61	[21]	GETGLOBAL	20 -1	; require
	62	[21]	LOADK    	21 -22	; "ui/widget/container/widgetcontainer"
	63	[21]	CALL     	20 2 2
	64	[22]	GETGLOBAL	21 -1	; require
	65	[22]	LOADK    	22 -23	; "util"
	66	[22]	CALL     	21 2 2
	67	[23]	GETGLOBAL	22 -1	; require
	68	[23]	LOADK    	23 -24	; "ffi/util"
	69	[23]	CALL     	22 2 2
	70	[23]	GETTABLE 	22 22 -25	; "template"
	71	[24]	GETGLOBAL	23 -1	; require
	72	[24]	LOADK    	24 -26	; "gettext"
	73	[24]	CALL     	23 2 2
	74	[25]	GETTABLE 	24 23 -27	; "pgettext"
	75	[26]	GETTABLE 	25 4 -28	; "screen"
	76	[28]	NEWTABLE 	26 0 13
	77	[29]	SETTABLE 	26 -29 -30	; "off" 0
	78	[30]	SETTABLE 	26 -31 -32	; "page_progress" 1
	79	[31]	SETTABLE 	26 -33 -34	; "time" 2
	80	[32]	SETTABLE 	26 -35 -36	; "pages_left" 3
	81	[33]	SETTABLE 	26 -37 -38	; "battery" 4
	82	[34]	SETTABLE 	26 -39 -40	; "percentage" 5
	83	[35]	SETTABLE 	26 -41 -42	; "book_time_to_read" 6
	84	[36]	SETTABLE 	26 -43 -44	; "chapter_time_to_read" 7
	85	[37]	SETTABLE 	26 -45 -46	; "frontlight" 8
	86	[38]	SETTABLE 	26 -47 -48	; "mem_usage" 9
	87	[39]	SETTABLE 	26 -49 -50	; "wifi_status" 10
	88	[40]	SETTABLE 	26 -51 -52	; "book_title" 11
	89	[41]	SETTABLE 	26 -53 -54	; "book_chapter" 12
	90	[44]	NEWTABLE 	27 0 2
	91	[45]	NEWTABLE 	28 0 9
	92	[46]	SETTABLE 	28 -33 -56	; "time" nil
	93	[47]	SETTABLE 	28 -35 -57	; "pages_left" "=>"
	94	[49]	MOVE     	29 24
	95	[49]	LOADK    	30 -58	; "FooterLetterPrefix"
	96	[49]	LOADK    	31 -59	; "B:"
	97	[49]	CALL     	29 3 2
	98	[49]	SETTABLE 	28 -37 29	; "battery" -
	99	[51]	MOVE     	29 24
	100	[51]	LOADK    	30 -58	; "FooterLetterPrefix"
	101	[51]	LOADK    	31 -60	; "R:"
	102	[51]	CALL     	29 3 2
	103	[51]	SETTABLE 	28 -39 29	; "percentage" -
	104	[53]	MOVE     	29 24
	105	[53]	LOADK    	30 -58	; "FooterLetterPrefix"
	106	[53]	LOADK    	31 -61	; "TB:"
	107	[53]	CALL     	29 3 2
	108	[53]	SETTABLE 	28 -41 29	; "book_time_to_read" -
	109	[55]	MOVE     	29 24
	110	[55]	LOADK    	30 -58	; "FooterLetterPrefix"
	111	[55]	LOADK    	31 -62	; "TC:"
	112	[55]	CALL     	29 3 2
	113	[55]	SETTABLE 	28 -43 29	; "chapter_time_to_read" -
	114	[57]	MOVE     	29 24
	115	[57]	LOADK    	30 -58	; "FooterLetterPrefix"
	116	[57]	LOADK    	31 -63	; "L:"
	117	[57]	CALL     	29 3 2
	118	[57]	SETTABLE 	28 -45 29	; "frontlight" -
	119	[59]	MOVE     	29 24
	120	[59]	LOADK    	30 -58	; "FooterLetterPrefix"
	121	[59]	LOADK    	31 -64	; "M:"
	122	[59]	CALL     	29 3 2
	123	[59]	SETTABLE 	28 -47 29	; "mem_usage" -
	124	[61]	MOVE     	29 24
	125	[61]	LOADK    	30 -58	; "FooterLetterPrefix"
	126	[61]	LOADK    	31 -65	; "W:"
	127	[61]	CALL     	29 3 2
	128	[61]	SETTABLE 	28 -49 29	; "wifi_status" -
	129	[62]	SETTABLE 	27 -55 28	; "letters" -
	130	[63]	NEWTABLE 	28 0 9
	131	[64]	SETTABLE 	28 -33 -67	; "time" "\226\140\154"
	132	[65]	GETTABLE 	29 0 -68	; "mirroredUILayout"
	133	[65]	CALL     	29 1 2
	134	[65]	TEST     	29 0 0
	135	[65]	JMP      	3	; to 139
	136	[65]	LOADK    	29 -69	; "\226\135\144"
	137	[65]	TEST     	29 0 1
	138	[65]	JMP      	1	; to 140
	139	[65]	LOADK    	29 -70	; "\226\135\146"
	140	[65]	SETTABLE 	28 -35 29	; "pages_left" -
	141	[66]	SETTABLE 	28 -37 -71	; "battery" "\238\158\144"
	142	[67]	GETTABLE 	29 0 -68	; "mirroredUILayout"
	143	[67]	CALL     	29 1 2
	144	[67]	TEST     	29 0 0
	145	[67]	JMP      	3	; to 149
	146	[67]	LOADK    	29 -72	; "\226\164\159"
	147	[67]	TEST     	29 0 1
	148	[67]	JMP      	1	; to 150
	149	[67]	LOADK    	29 -73	; "\226\164\160"
	150	[67]	SETTABLE 	28 -39 29	; "percentage" -
	151	[68]	SETTABLE 	28 -41 -74	; "book_time_to_read" "\226\143\179"
	152	[69]	GETTABLE 	29 0 -68	; "mirroredUILayout"
	153	[69]	CALL     	29 1 2
	154	[69]	TEST     	29 0 0
	155	[69]	JMP      	3	; to 159
	156	[69]	LOADK    	29 -75	; "\226\165\150"
	157	[69]	TEST     	29 0 1
	158	[69]	JMP      	1	; to 160
	159	[69]	LOADK    	29 -76	; "\226\164\187"
	160	[69]	SETTABLE 	28 -43 29	; "chapter_time_to_read" -
	161	[70]	SETTABLE 	28 -45 -77	; "frontlight" "\226\152\188"
	162	[71]	SETTABLE 	28 -47 -78	; "mem_usage" "\238\169\154"
	163	[72]	SETTABLE 	28 -49 -79	; "wifi_status" "\238\178\168"
	164	[73]	SETTABLE 	27 -66 28	; "icons" -
	165	[75]	GETTABLE 	28 0 -68	; "mirroredUILayout"
	166	[75]	CALL     	28 1 2
	167	[75]	TEST     	28 0 0
	168	[75]	JMP      	44	; to 213
	169	[77]	GETGLOBAL	28 -80	; pairs
	170	[77]	GETTABLE 	29 27 -55	; "letters"
	171	[77]	CALL     	28 2 4
	172	[77]	JMP      	27	; to 200
	173	[78]	SELF     	33 32 -81	; "find"
	174	[78]	LOADK    	35 -82	; ":"
	175	[78]	CALL     	33 3 2
	176	[79]	LOADNIL  	34 34
	177	[80]	TEST     	33 0 0
	178	[80]	JMP      	15	; to 194
	179	[81]	SELF     	35 32 -83	; "sub"
	180	[81]	LOADK    	37 -32	; 1
	181	[81]	SUB      	38 33 -32	; - 1
	182	[81]	CALL     	35 4 2
	183	[82]	SELF     	36 32 -83	; "sub"
	184	[82]	MOVE     	38 33
	185	[82]	CALL     	36 3 2
	186	[83]	GETTABLE 	37 0 -84	; "wrap"
	187	[83]	MOVE     	38 35
	188	[83]	CALL     	37 2 2
	189	[83]	GETTABLE 	38 0 -84	; "wrap"
	190	[83]	MOVE     	39 36
	191	[83]	CALL     	38 2 2
	192	[83]	CONCAT   	34 37 38
	193	[83]	JMP      	4	; to 198
	194	[85]	GETTABLE 	35 0 -84	; "wrap"
	195	[85]	MOVE     	36 32
	196	[85]	CALL     	35 2 2
	197	[85]	MOVE     	34 35
	198	[87]	GETTABLE 	35 27 -55	; "letters"
	199	[87]	SETTABLE 	35 31 34
	200	[77]	TFORLOOP 	28 2
	201	[87]	JMP      	-29	; to 173
	202	[89]	GETGLOBAL	28 -80	; pairs
	203	[89]	GETTABLE 	29 27 -66	; "icons"
	204	[89]	CALL     	28 2 4
	205	[89]	JMP      	5	; to 211
	206	[90]	GETTABLE 	33 27 -66	; "icons"
	207	[90]	GETTABLE 	34 0 -84	; "wrap"
	208	[90]	MOVE     	35 32
	209	[90]	CALL     	34 2 2
	210	[90]	SETTABLE 	33 31 34
	211	[89]	TFORLOOP 	28 2
	212	[90]	JMP      	-7	; to 206
	213	[94]	LOADK    	28 -44	; 7
	214	[95]	LOADK    	29 -36	; 3
	215	[96]	LOADK    	30 -34	; 2
	216	[97]	LOADK    	31 -85	; 14
	217	[100]	NEWTABLE 	32 0 13
	218	[101]	CLOSURE  	33 0	; 0x7fd3a0c07060
	219	[101]	SETTABLE 	32 -86 33	; "empty" -
	220	[115]	CLOSURE  	33 1	; 0x7fd3a0c07d50
	221	[115]	MOVE     	0 27
	222	[115]	MOVE     	0 4
	223	[115]	MOVE     	0 22
	224	[115]	MOVE     	0 23
	225	[115]	SETTABLE 	32 -45 33	; "frontlight" -
	226	[154]	CLOSURE  	33 2	; 0x7fd3a0c08130
	227	[154]	MOVE     	0 27
	228	[154]	MOVE     	0 4
	229	[154]	MOVE     	0 0
	230	[154]	SETTABLE 	32 -37 33	; "battery" -
	231	[176]	CLOSURE  	33 3	; 0x7fd3a0c086f0
	232	[176]	MOVE     	0 27
	233	[176]	MOVE     	0 23
	234	[176]	SETTABLE 	32 -33 33	; "time" -
	235	[188]	CLOSURE  	33 4	; 0x7fd3a0c08c10
	236	[188]	SETTABLE 	32 -31 33	; "page_progress" -
	237	[195]	CLOSURE  	33 5	; 0x7fd3a0c09310
	238	[195]	MOVE     	0 27
	239	[195]	SETTABLE 	32 -35 33	; "pages_left" -
	240	[207]	CLOSURE  	33 6	; 0x7fd3a0c09af0
	241	[207]	MOVE     	0 27
	242	[207]	SETTABLE 	32 -39 33	; "percentage" -
	243	[213]	CLOSURE  	33 7	; 0x7fd3a0c09e60
	244	[213]	MOVE     	0 27
	245	[213]	SETTABLE 	32 -41 33	; "book_time_to_read" -
	246	[221]	CLOSURE  	33 8	; 0x7fd3a0c0a4a0
	247	[221]	MOVE     	0 27
	248	[221]	SETTABLE 	32 -43 33	; "chapter_time_to_read" -
	249	[235]	CLOSURE  	33 9	; 0x7fd3a0c0a790
	250	[235]	MOVE     	0 27
	251	[235]	SETTABLE 	32 -47 33	; "mem_usage" -
	252	[245]	CLOSURE  	33 10	; 0x7fd3a0c0aa10
	253	[245]	MOVE     	0 27
	254	[245]	MOVE     	0 22
	255	[245]	MOVE     	0 23
	256	[245]	SETTABLE 	32 -49 33	; "wifi_status" -
	257	[264]	CLOSURE  	33 11	; 0x7fd3a0c0ae50
	258	[264]	MOVE     	0 16
	259	[264]	MOVE     	0 6
	260	[264]	MOVE     	0 0
	261	[264]	SETTABLE 	32 -51 33	; "book_title" -
	262	[283]	CLOSURE  	33 12	; 0x7fd3a0c0b540
	263	[283]	MOVE     	0 16
	264	[283]	MOVE     	0 6
	265	[283]	MOVE     	0 0
	266	[283]	SETTABLE 	32 -53 33	; "book_chapter" -
	267	[286]	SELF     	33 20 -87	; "extend"
	268	[286]	NEWTABLE 	35 0 13
	269	[287]	GETTABLE 	36 26 -31	; "page_progress"
	270	[287]	SETTABLE 	35 -88 36	; "mode" -
	271	[288]	SETTABLE 	35 -89 -56	; "pageno" nil
	272	[289]	SETTABLE 	35 -90 -56	; "pages" nil
	273	[290]	SETTABLE 	35 -91 -30	; "toc_level" 0
	274	[291]	SETTABLE 	35 -92 -30	; "progress_percentage" 0
	275	[292]	SETTABLE 	35 -93 -56	; "footer_text" nil
	276	[293]	SETTABLE 	35 -94 -95	; "text_font_face" "ffont"
	277	[294]	SELF     	36 25 -97	; "scaleBySize"
	278	[294]	GETGLOBAL	38 -98	; DMINIBAR_CONTAINER_HEIGHT
	279	[294]	CALL     	36 3 2
	280	[294]	SETTABLE 	35 -96 36	; "height" -
	281	[295]	SELF     	36 25 -97	; "scaleBySize"
	282	[295]	LOADK    	38 -50	; 10
	283	[295]	CALL     	36 3 2
	284	[295]	SETTABLE 	35 -99 36	; "horizontal_margin" -
	285	[296]	SELF     	36 25 -97	; "scaleBySize"
	286	[296]	LOADK    	38 -50	; 10
	287	[296]	CALL     	36 3 2
	288	[296]	SETTABLE 	35 -100 36	; "text_left_margin" -
	289	[297]	SELF     	36 25 -97	; "scaleBySize"
	290	[297]	LOADK    	38 -32	; 1
	291	[297]	CALL     	36 3 2
	292	[297]	SETTABLE 	35 -101 36	; "bottom_padding" -
	293	[298]	NEWTABLE 	36 0 0
	294	[298]	SETTABLE 	35 -102 36	; "settings" -
	295	[300]	SETTABLE 	35 -103 32	; "textGeneratorMap" -
	296	[286]	CALL     	33 3 2
	297	[449]	CLOSURE  	34 13	; 0x7fd3a0c0bd80
	298	[449]	MOVE     	0 30
	299	[449]	MOVE     	0 31
	300	[449]	MOVE     	0 4
	301	[449]	MOVE     	0 26
	302	[449]	MOVE     	0 25
	303	[449]	MOVE     	0 16
	304	[449]	MOVE     	0 6
	305	[449]	MOVE     	0 13
	306	[449]	MOVE     	0 14
	307	[449]	MOVE     	0 8
	308	[303]	SETTABLE 	33 -104 34	; "init" -
	309	[523]	CLOSURE  	34 14	; 0x7fd3a0c0ceb0
	310	[523]	MOVE     	0 10
	311	[523]	MOVE     	0 18
	312	[523]	MOVE     	0 12
	313	[523]	MOVE     	0 8
	314	[523]	MOVE     	0 15
	315	[523]	MOVE     	0 19
	316	[523]	MOVE     	0 9
	317	[523]	MOVE     	0 11
	318	[523]	MOVE     	0 14
	319	[523]	MOVE     	0 3
	320	[523]	MOVE     	0 7
	321	[523]	MOVE     	0 1
	322	[523]	MOVE     	0 2
	323	[451]	SETTABLE 	33 -105 34	; "updateFooterContainer" -
	324	[536]	CLOSURE  	34 15	; 0x7fd3a0c0d8e0
	325	[536]	MOVE     	0 17
	326	[525]	SETTABLE 	33 -106 34	; "setupAutoRefreshTime" -
	327	[568]	CLOSURE  	34 16	; 0x7fd3a0c0e170
	328	[568]	MOVE     	0 4
	329	[538]	SETTABLE 	33 -107 34	; "setupTouchZones" -
	330	[604]	CLOSURE  	34 17	; 0x7fd3a0c0a5e0
	331	[604]	MOVE     	0 25
	332	[604]	MOVE     	0 29
	333	[604]	MOVE     	0 28
	334	[571]	SETTABLE 	33 -108 34	; "resetLayout" -
	335	[612]	CLOSURE  	34 18	; 0x7fd3a0c0f4c0
	336	[606]	SETTABLE 	33 -109 34	; "getHeight" -
	337	[624]	CLOSURE  	34 19	; 0x7fd3a0c0f9c0
	338	[614]	SETTABLE 	33 -110 34	; "disableFooter" -
	339	[652]	CLOSURE  	34 20	; 0x7fd3a0c10270
	340	[652]	MOVE     	0 32
	341	[626]	SETTABLE 	33 -111 34	; "updateFooterTextGenerator" -
	342	[665]	CLOSURE  	34 21	; 0x7fd3a0c109b0
	343	[665]	MOVE     	0 27
	344	[654]	SETTABLE 	33 -112 34	; "progressPercentage" -
	345	[688]	CLOSURE  	34 22	; 0x7fd3a0c10da0
	346	[688]	MOVE     	0 23
	347	[688]	MOVE     	0 22
	348	[688]	MOVE     	0 27
	349	[667]	SETTABLE 	33 -113 34	; "textOptionTitles" -
	350	[1535]	CLOSURE  	34 23	; 0x7fd3a0c11310
	351	[1535]	MOVE     	0 23
	352	[1535]	MOVE     	0 8
	353	[1535]	MOVE     	0 32
	354	[1535]	MOVE     	0 17
	355	[1535]	MOVE     	0 22
	356	[1535]	MOVE     	0 25
	357	[1535]	MOVE     	0 16
	358	[1535]	MOVE     	0 6
	359	[1535]	MOVE     	0 27
	360	[1535]	MOVE     	0 28
	361	[1535]	MOVE     	0 29
	362	[1535]	MOVE     	0 4
	363	[690]	SETTABLE 	33 -114 34	; "addToMainMenu" -
	364	[1538]	CLOSURE  	34 24	; 0x7fd3a0c28be0
	365	[1538]	SETTABLE 	33 -115 34	; "genFooterText" -
	366	[1555]	CLOSURE  	34 25	; 0x7fd3a0c29560
	367	[1555]	MOVE     	0 0
	368	[1540]	SETTABLE 	33 -116 34	; "genAllFooterText" -
	369	[1590]	CLOSURE  	34 26	; 0x7fd3a0c29720
	370	[1590]	MOVE     	0 25
	371	[1557]	SETTABLE 	33 -117 34	; "setTocMarkers" -
	372	[1594]	CLOSURE  	34 27	; 0x7fd3a0c29d70
	373	[1592]	SETTABLE 	33 -118 34	; "getAvgTimePerPage" -
	374	[1607]	CLOSURE  	34 28	; 0x7fd3a0c29ef0
	375	[1607]	MOVE     	0 21
	376	[1596]	SETTABLE 	33 -119 34	; "getDataFromStatistics" -
	377	[1615]	CLOSURE  	34 29	; 0x7fd3a0c2aa60
	378	[1609]	SETTABLE 	33 -120 34	; "updateFooter" -
	379	[1621]	CLOSURE  	34 30	; 0x7fd3a0c2ac70
	380	[1617]	SETTABLE 	33 -121 34	; "updateFooterPage" -
	381	[1627]	CLOSURE  	34 31	; 0x7fd3a0c2b160
	382	[1623]	SETTABLE 	33 -122 34	; "updateFooterPos" -
	383	[1632]	CLOSURE  	34 32	; 0x7fd3a0c2b630
	384	[1631]	SETTABLE 	33 -123 34	; "updateFooterText" -
	385	[1694]	CLOSURE  	34 33	; 0x7fd3a0c0edf0
	386	[1694]	MOVE     	0 29
	387	[1694]	MOVE     	0 28
	388	[1694]	MOVE     	0 25
	389	[1694]	MOVE     	0 17
	390	[1635]	SETTABLE 	33 -124 34	; "_updateFooterText" -
	391	[1701]	CLOSURE  	34 34	; 0x7fd3a0c294c0
	392	[1696]	SETTABLE 	33 -125 34	; "onPageUpdate" -
	393	[1712]	CLOSURE  	34 35	; 0x7fd3a0c2a6d0
	394	[1703]	SETTABLE 	33 -126 34	; "onPosUpdate" -
	395	[1716]	GETTABLE 	34 33 -120	; "updateFooter"
	396	[1716]	SETTABLE 	33 -127 34	; "onUpdatePos" -
	397	[1735]	CLOSURE  	34 36	; 0x7fd3a0c118b0
	398	[1735]	MOVE     	0 25
	399	[1718]	SETTABLE 	33 -128 34	; "onReaderReady" -
	400	[1744]	CLOSURE  	34 37	; 0x7fd3a0c195c0
	401	[1737]	SETTABLE 	33 -129 34	; "onReadSettings" -
	402	[1781]	CLOSURE  	34 38	; 0x7fd3a0c0fd00
	403	[1781]	MOVE     	0 32
	404	[1746]	SETTABLE 	33 -130 34	; "applyFooterMode" -
	405	[1786]	CLOSURE  	34 39	; 0x7fd3a0c208a0
	406	[1783]	SETTABLE 	33 -131 34	; "onEnterFlippingMode" -
	407	[1790]	CLOSURE  	34 40	; 0x7fd3a0c1ac70
	408	[1788]	SETTABLE 	33 -132 34	; "onExitFlippingMode" -
	409	[1829]	CLOSURE  	34 41	; 0x7fd3a0c25270
	410	[1829]	MOVE     	0 5
	411	[1792]	SETTABLE 	33 -133 34	; "onTapFooter" -
	412	[1835]	CLOSURE  	34 42	; 0x7fd3a0c140c0
	413	[1835]	MOVE     	0 5
	414	[1831]	SETTABLE 	33 -134 34	; "onHoldFooter" -
	415	[1849]	CLOSURE  	34 43	; 0x7fd3a0c19460
	416	[1837]	SETTABLE 	33 -135 34	; "setVisible" -
	417	[1860]	CLOSURE  	34 44	; 0x7fd3a0c214f0
	418	[1860]	MOVE     	0 5
	419	[1851]	SETTABLE 	33 -136 34	; "refreshFooter" -
	420	[1867]	CLOSURE  	34 45	; 0x7fd3a0c21570
	421	[1862]	SETTABLE 	33 -137 34	; "onResume" -
	422	[1874]	CLOSURE  	34 46	; 0x7fd3a0c23470
	423	[1874]	MOVE     	0 17
	424	[1869]	SETTABLE 	33 -138 34	; "onSuspend" -
	425	[1880]	CLOSURE  	34 47	; 0x7fd3a0c21f20
	426	[1876]	SETTABLE 	33 -139 34	; "onFrontlightStateChanged" -
	427	[1885]	CLOSURE  	34 48	; 0x7fd3a0c21fa0
	428	[1882]	SETTABLE 	33 -140 34	; "onChangeScreenMode" -
	429	[1893]	CLOSURE  	34 49	; 0x7fd3a0c242c0
	430	[1893]	MOVE     	0 25
	431	[1887]	SETTABLE 	33 -141 34	; "onSetPageHorizMargins" -
	432	[1898]	CLOSURE  	34 50	; 0x7fd3a0c1b3b0
	433	[1895]	SETTABLE 	33 -142 34	; "onScreenResize" -
	434	[1900]	RETURN   	33 2
	435	[1900]	RETURN   	0 1

function <./frontend/apps/reader/modules/readerfooter.lua:101,101> (3 instructions, 12 bytes at 0x7fd3a0c07060)
0 params, 2 slots, 0 upvalues, 0 locals, 1 constant, 0 functions
	1	[101]	LOADK    	0 -1	; ""
	2	[101]	RETURN   	0 2
	3	[101]	RETURN   	0 1

function <./frontend/apps/reader/modules/readerfooter.lua:102,115> (51 instructions, 204 bytes at 0x7fd3a0c07d50)
1 param, 8 slots, 4 upvalues, 4 locals, 13 constants, 0 functions
	1	[103]	GETTABLE 	1 0 -1	; "settings"
	2	[103]	GETTABLE 	1 1 -2	; "item_prefix"
	3	[103]	TEST     	1 0 1
	4	[103]	JMP      	1	; to 6
	5	[103]	LOADK    	1 -3	; "icons"
	6	[104]	GETUPVAL 	2 0	; symbol_prefix
	7	[104]	GETTABLE 	2 2 1
	8	[104]	GETTABLE 	2 2 -4	; "frontlight"
	9	[105]	GETUPVAL 	3 1	; Device
	10	[105]	SELF     	3 3 -5	; "getPowerDevice"
	11	[105]	CALL     	3 2 2
	12	[106]	SELF     	4 3 -6	; "isFrontlightOn"
	13	[106]	CALL     	4 2 2
	14	[106]	TEST     	4 0 0
	15	[106]	JMP      	28	; to 44
	16	[107]	GETUPVAL 	4 1	; Device
	17	[107]	SELF     	4 4 -7	; "isCervantes"
	18	[107]	CALL     	4 2 2
	19	[107]	TEST     	4 0 1
	20	[107]	JMP      	5	; to 26
	21	[107]	GETUPVAL 	4 1	; Device
	22	[107]	SELF     	4 4 -8	; "isKobo"
	23	[107]	CALL     	4 2 2
	24	[107]	TEST     	4 0 0
	25	[107]	JMP      	9	; to 35
	26	[108]	MOVE     	4 2
	27	[108]	LOADK    	5 -9	; " %d%%"
	28	[108]	CONCAT   	4 4 5
	29	[108]	SELF     	4 4 -10	; "format"
	30	[108]	SELF     	6 3 -11	; "frontlightIntensity"
	31	[108]	CALL     	6 2 0
	32	[108]	TAILCALL 	4 0 0
	33	[108]	RETURN   	4 0
	34	[108]	JMP      	16	; to 51
	35	[110]	MOVE     	4 2
	36	[110]	LOADK    	5 -12	; " %d"
	37	[110]	CONCAT   	4 4 5
	38	[110]	SELF     	4 4 -10	; "format"
	39	[110]	SELF     	6 3 -11	; "frontlightIntensity"
	40	[110]	CALL     	6 2 0
	41	[110]	TAILCALL 	4 0 0
	42	[110]	RETURN   	4 0
	43	[111]	JMP      	7	; to 51
	44	[113]	GETUPVAL 	4 2	; T
	45	[113]	GETUPVAL 	5 3	; _
	46	[113]	LOADK    	6 -13	; "%1 Off"
	47	[113]	CALL     	5 2 2
	48	[113]	MOVE     	6 2
	49	[113]	TAILCALL 	4 3 0
	50	[113]	RETURN   	4 0
	51	[115]	RETURN   	0 1

function <./frontend/apps/reader/modules/readerfooter.lua:116,154> (89 instructions, 356 bytes at 0x7fd3a0c08130)
1 param, 10 slots, 3 upvalues, 5 locals, 34 constants, 0 functions
	1	[117]	GETTABLE 	1 0 -1	; "settings"
	2	[117]	GETTABLE 	1 1 -2	; "item_prefix"
	3	[117]	TEST     	1 0 1
	4	[117]	JMP      	1	; to 6
	5	[117]	LOADK    	1 -3	; "icons"
	6	[118]	GETUPVAL 	2 0	; symbol_prefix
	7	[118]	GETTABLE 	2 2 1
	8	[118]	GETTABLE 	2 2 -4	; "battery"
	9	[119]	GETUPVAL 	3 1	; Device
	10	[119]	SELF     	3 3 -5	; "getPowerDevice"
	11	[119]	CALL     	3 2 2
	12	[120]	SELF     	4 3 -6	; "getCapacity"
	13	[120]	CALL     	4 2 2
	14	[122]	EQ       	0 1 -3	; - "icons"
	15	[122]	JMP      	56	; to 72
	16	[123]	SELF     	5 3 -7	; "isCharging"
	17	[123]	CALL     	5 2 2
	18	[123]	TEST     	5 0 0
	19	[123]	JMP      	2	; to 22
	20	[124]	LOADK    	2 -8	; "\238\158\131"
	21	[124]	JMP      	41	; to 63
	22	[126]	LE       	0 -9 4	; 100 -
	23	[126]	JMP      	2	; to 26
	24	[127]	LOADK    	2 -10	; "\238\157\184"
	25	[127]	JMP      	37	; to 63
	26	[128]	LE       	0 -11 4	; 90 -
	27	[128]	JMP      	2	; to 30
	28	[129]	LOADK    	2 -12	; "\238\158\129"
	29	[129]	JMP      	33	; to 63
	30	[130]	LE       	0 -13 4	; 80 -
	31	[130]	JMP      	2	; to 34
	32	[131]	LOADK    	2 -14	; "\238\158\128"
	33	[131]	JMP      	29	; to 63
	34	[132]	LE       	0 -15 4	; 70 -
	35	[132]	JMP      	2	; to 38
	36	[133]	LOADK    	2 -16	; "\238\157\191"
	37	[133]	JMP      	25	; to 63
	38	[134]	LE       	0 -17 4	; 60 -
	39	[134]	JMP      	2	; to 42
	40	[135]	LOADK    	2 -18	; "\238\157\190"
	41	[135]	JMP      	21	; to 63
	42	[136]	LE       	0 -19 4	; 50 -
	43	[136]	JMP      	2	; to 46
	44	[137]	LOADK    	2 -20	; "\238\157\189"
	45	[137]	JMP      	17	; to 63
	46	[138]	LE       	0 -21 4	; 40 -
	47	[138]	JMP      	2	; to 50
	48	[139]	LOADK    	2 -22	; "\238\157\188"
	49	[139]	JMP      	13	; to 63
	50	[140]	LE       	0 -23 4	; 30 -
	51	[140]	JMP      	2	; to 54
	52	[141]	LOADK    	2 -24	; "\238\157\187"
	53	[141]	JMP      	9	; to 63
	54	[142]	LE       	0 -25 4	; 20 -
	55	[142]	JMP      	2	; to 58
	56	[143]	LOADK    	2 -26	; "\238\157\186"
	57	[143]	JMP      	5	; to 63
	58	[144]	LE       	0 -27 4	; 10 -
	59	[144]	JMP      	2	; to 62
	60	[145]	LOADK    	2 -28	; "\238\157\185"
	61	[145]	JMP      	1	; to 63
	62	[147]	LOADK    	2 -29	; "\238\158\130"
	63	[150]	GETUPVAL 	5 2	; BD
	64	[150]	GETTABLE 	5 5 -30	; "wrap"
	65	[150]	MOVE     	6 2
	66	[150]	CALL     	5 2 2
	67	[150]	MOVE     	6 4
	68	[150]	LOADK    	7 -31	; "%"
	69	[150]	CONCAT   	5 5 7
	70	[150]	RETURN   	5 2
	71	[150]	JMP      	17	; to 89
	72	[152]	GETUPVAL 	5 2	; BD
	73	[152]	GETTABLE 	5 5 -30	; "wrap"
	74	[152]	MOVE     	6 2
	75	[152]	CALL     	5 2 2
	76	[152]	LOADK    	6 -32	; " "
	77	[152]	SELF     	7 3 -7	; "isCharging"
	78	[152]	CALL     	7 2 2
	79	[152]	TEST     	7 0 0
	80	[152]	JMP      	3	; to 84
	81	[152]	LOADK    	7 -33	; "+"
	82	[152]	TEST     	7 0 1
	83	[152]	JMP      	1	; to 85
	84	[152]	LOADK    	7 -34	; ""
	85	[152]	MOVE     	8 4
	86	[152]	LOADK    	9 -31	; "%"
	87	[152]	CONCAT   	5 5 9
	88	[152]	RETURN   	5 2
	89	[154]	RETURN   	0 1

function <./frontend/apps/reader/modules/readerfooter.lua:155,176> (52 instructions, 208 bytes at 0x7fd3a0c086f0)
1 param, 7 slots, 2 upvalues, 4 locals, 14 constants, 0 functions
	1	[156]	GETTABLE 	1 0 -1	; "settings"
	2	[156]	GETTABLE 	1 1 -2	; "item_prefix"
	3	[156]	TEST     	1 0 1
	4	[156]	JMP      	1	; to 6
	5	[156]	LOADK    	1 -3	; "icons"
	6	[157]	GETUPVAL 	2 0	; symbol_prefix
	7	[157]	GETTABLE 	2 2 1
	8	[157]	GETTABLE 	2 2 -4	; "time"
	9	[158]	LOADNIL  	3 3
	10	[159]	GETTABLE 	4 0 -1	; "settings"
	11	[159]	GETTABLE 	4 4 -5	; "time_format"
	12	[159]	EQ       	0 4 -6	; - "12"
	13	[159]	JMP      	22	; to 36
	14	[160]	GETGLOBAL	4 -7	; os
	15	[160]	GETTABLE 	4 4 -8	; "date"
	16	[160]	LOADK    	5 -9	; "%p"
	17	[160]	CALL     	4 2 2
	18	[160]	EQ       	0 4 -10	; - "AM"
	19	[160]	JMP      	8	; to 28
	20	[162]	GETGLOBAL	4 -7	; os
	21	[162]	GETTABLE 	4 4 -8	; "date"
	22	[162]	GETUPVAL 	5 1	; _
	23	[162]	LOADK    	6 -11	; "%I:%M AM"
	24	[162]	CALL     	5 2 0
	25	[162]	CALL     	4 0 2
	26	[162]	MOVE     	3 4
	27	[162]	JMP      	15	; to 43
	28	[165]	GETGLOBAL	4 -7	; os
	29	[165]	GETTABLE 	4 4 -8	; "date"
	30	[165]	GETUPVAL 	5 1	; _
	31	[165]	LOADK    	6 -12	; "%I:%M PM"
	32	[165]	CALL     	5 2 0
	33	[165]	CALL     	4 0 2
	34	[165]	MOVE     	3 4
	35	[166]	JMP      	7	; to 43
	36	[169]	GETGLOBAL	4 -7	; os
	37	[169]	GETTABLE 	4 4 -8	; "date"
	38	[169]	GETUPVAL 	5 1	; _
	39	[169]	LOADK    	6 -13	; "%H:%M"
	40	[169]	CALL     	5 2 0
	41	[169]	CALL     	4 0 2
	42	[169]	MOVE     	3 4
	43	[171]	TEST     	2 0 1
	44	[171]	JMP      	2	; to 47
	45	[172]	RETURN   	3 2
	46	[172]	JMP      	5	; to 52
	47	[174]	MOVE     	4 2
	48	[174]	LOADK    	5 -14	; " "
	49	[174]	MOVE     	6 3
	50	[174]	CONCAT   	4 4 6
	51	[174]	RETURN   	4 2
	52	[176]	RETURN   	0 1

function <./frontend/apps/reader/modules/readerfooter.lua:177,188> (44 instructions, 176 bytes at 0x7fd3a0c08c10)
1 param, 7 slots, 0 upvalues, 1 local, 12 constants, 0 functions
	1	[178]	GETTABLE 	1 0 -1	; "pageno"
	2	[178]	TEST     	1 0 0
	3	[178]	JMP      	31	; to 35
	4	[179]	GETTABLE 	1 0 -2	; "ui"
	5	[179]	GETTABLE 	1 1 -3	; "pagemap"
	6	[179]	TEST     	1 0 0
	7	[179]	JMP      	20	; to 28
	8	[179]	GETTABLE 	1 0 -2	; "ui"
	9	[179]	GETTABLE 	1 1 -3	; "pagemap"
	10	[179]	SELF     	1 1 -4	; "wantsPageLabels"
	11	[179]	CALL     	1 2 2
	12	[179]	TEST     	1 0 0
	13	[179]	JMP      	14	; to 28
	14	[181]	LOADK    	1 -5	; "%s / %s"
	15	[181]	SELF     	1 1 -6	; "format"
	16	[181]	GETTABLE 	3 0 -2	; "ui"
	17	[181]	GETTABLE 	3 3 -3	; "pagemap"
	18	[181]	SELF     	3 3 -7	; "getCurrentPageLabel"
	19	[181]	LOADBOOL 	5 1 0
	20	[181]	CALL     	3 3 2
	21	[182]	GETTABLE 	4 0 -2	; "ui"
	22	[182]	GETTABLE 	4 4 -3	; "pagemap"
	23	[182]	SELF     	4 4 -8	; "getLastPageLabel"
	24	[182]	LOADBOOL 	6 1 0
	25	[182]	CALL     	4 3 0
	26	[181]	TAILCALL 	1 0 0
	27	[182]	RETURN   	1 0
	28	[184]	LOADK    	1 -9	; "%d / %d"
	29	[184]	SELF     	1 1 -6	; "format"
	30	[184]	GETTABLE 	3 0 -1	; "pageno"
	31	[184]	GETTABLE 	4 0 -10	; "pages"
	32	[184]	TAILCALL 	1 4 0
	33	[184]	RETURN   	1 0
	34	[184]	JMP      	9	; to 44
	35	[185]	GETTABLE 	1 0 -11	; "position"
	36	[185]	TEST     	1 0 0
	37	[185]	JMP      	6	; to 44
	38	[186]	LOADK    	1 -9	; "%d / %d"
	39	[186]	SELF     	1 1 -6	; "format"
	40	[186]	GETTABLE 	3 0 -11	; "position"
	41	[186]	GETTABLE 	4 0 -12	; "doc_height"
	42	[186]	TAILCALL 	1 4 0
	43	[186]	RETURN   	1 0
	44	[188]	RETURN   	0 1

function <./frontend/apps/reader/modules/readerfooter.lua:189,195> (26 instructions, 104 bytes at 0x7fd3a0c09310)
1 param, 8 slots, 1 upvalue, 4 locals, 11 constants, 0 functions
	1	[190]	GETTABLE 	1 0 -1	; "settings"
	2	[190]	GETTABLE 	1 1 -2	; "item_prefix"
	3	[190]	TEST     	1 0 1
	4	[190]	JMP      	1	; to 6
	5	[190]	LOADK    	1 -3	; "icons"
	6	[191]	GETUPVAL 	2 0	; symbol_prefix
	7	[191]	GETTABLE 	2 2 1
	8	[191]	GETTABLE 	2 2 -4	; "pages_left"
	9	[192]	GETTABLE 	3 0 -5	; "ui"
	10	[192]	GETTABLE 	3 3 -6	; "toc"
	11	[192]	SELF     	3 3 -7	; "getChapterPagesLeft"
	12	[193]	GETTABLE 	5 0 -8	; "pageno"
	13	[193]	GETTABLE 	6 0 -9	; "toc_level"
	14	[192]	CALL     	3 4 2
	15	[194]	MOVE     	4 2
	16	[194]	LOADK    	5 -10	; " "
	17	[194]	TEST     	3 0 0
	18	[194]	JMP      	2	; to 21
	19	[194]	TESTSET  	6 3 1
	20	[194]	JMP      	3	; to 24
	21	[194]	GETTABLE 	6 0 -11	; "pages"
	22	[194]	GETTABLE 	7 0 -8	; "pageno"
	23	[194]	SUB      	6 6 7
	24	[194]	CONCAT   	4 4 6
	25	[194]	RETURN   	4 2
	26	[195]	RETURN   	0 1

function <./frontend/apps/reader/modules/readerfooter.lua:196,207> (33 instructions, 132 bytes at 0x7fd3a0c09af0)
1 param, 9 slots, 1 upvalue, 5 locals, 12 constants, 0 functions
	1	[197]	GETTABLE 	1 0 -1	; "settings"
	2	[197]	GETTABLE 	1 1 -2	; "item_prefix"
	3	[197]	TEST     	1 0 1
	4	[197]	JMP      	1	; to 6
	5	[197]	LOADK    	1 -3	; "icons"
	6	[198]	GETUPVAL 	2 0	; symbol_prefix
	7	[198]	GETTABLE 	2 2 1
	8	[198]	GETTABLE 	2 2 -4	; "percentage"
	9	[199]	GETTABLE 	3 0 -1	; "settings"
	10	[199]	GETTABLE 	3 3 -5	; "progress_pct_format"
	11	[199]	TEST     	3 0 1
	12	[199]	JMP      	1	; to 14
	13	[199]	LOADK    	3 -6	; "0"
	14	[200]	LOADNIL  	4 4
	15	[201]	TEST     	2 0 1
	16	[201]	JMP      	5	; to 22
	17	[202]	LOADK    	5 -7	; "%."
	18	[202]	MOVE     	6 3
	19	[202]	LOADK    	7 -8	; "f%%"
	20	[202]	CONCAT   	4 5 7
	21	[202]	JMP      	5	; to 27
	22	[204]	MOVE     	5 2
	23	[204]	LOADK    	6 -9	; " %."
	24	[204]	MOVE     	7 3
	25	[204]	LOADK    	8 -8	; "f%%"
	26	[204]	CONCAT   	4 5 8
	27	[206]	SELF     	5 4 -10	; "format"
	28	[206]	GETTABLE 	7 0 -11	; "progress_bar"
	29	[206]	GETTABLE 	7 7 -4	; "percentage"
	30	[206]	MUL      	7 7 -12	; - 100
	31	[206]	TAILCALL 	5 3 0
	32	[206]	RETURN   	5 0
	33	[207]	RETURN   	0 1

function <./frontend/apps/reader/modules/readerfooter.lua:208,213> (20 instructions, 80 bytes at 0x7fd3a0c09e60)
1 param, 8 slots, 1 upvalue, 4 locals, 9 constants, 0 functions
	1	[209]	GETTABLE 	1 0 -1	; "settings"
	2	[209]	GETTABLE 	1 1 -2	; "item_prefix"
	3	[209]	TEST     	1 0 1
	4	[209]	JMP      	1	; to 6
	5	[209]	LOADK    	1 -3	; "icons"
	6	[210]	GETUPVAL 	2 0	; symbol_prefix
	7	[210]	GETTABLE 	2 2 1
	8	[210]	GETTABLE 	2 2 -4	; "book_time_to_read"
	9	[211]	GETTABLE 	3 0 -5	; "ui"
	10	[211]	SELF     	3 3 -6	; "getCurrentPage"
	11	[211]	CALL     	3 2 2
	12	[212]	SELF     	4 0 -7	; "getDataFromStatistics"
	13	[212]	MOVE     	6 2
	14	[212]	LOADK    	7 -8	; " "
	15	[212]	CONCAT   	6 6 7
	16	[212]	GETTABLE 	7 0 -9	; "pages"
	17	[212]	SUB      	7 7 3
	18	[212]	TAILCALL 	4 4 0
	19	[212]	RETURN   	4 0
	20	[213]	RETURN   	0 1

function <./frontend/apps/reader/modules/readerfooter.lua:214,221> (28 instructions, 112 bytes at 0x7fd3a0c0a4a0)
1 param, 9 slots, 1 upvalue, 4 locals, 12 constants, 0 functions
	1	[215]	GETTABLE 	1 0 -1	; "settings"
	2	[215]	GETTABLE 	1 1 -2	; "item_prefix"
	3	[215]	TEST     	1 0 1
	4	[215]	JMP      	1	; to 6
	5	[215]	LOADK    	1 -3	; "icons"
	6	[216]	GETUPVAL 	2 0	; symbol_prefix
	7	[216]	GETTABLE 	2 2 1
	8	[216]	GETTABLE 	2 2 -4	; "chapter_time_to_read"
	9	[217]	GETTABLE 	3 0 -5	; "ui"
	10	[217]	GETTABLE 	3 3 -6	; "toc"
	11	[217]	SELF     	3 3 -7	; "getChapterPagesLeft"
	12	[218]	GETTABLE 	5 0 -8	; "pageno"
	13	[218]	GETTABLE 	6 0 -9	; "toc_level"
	14	[217]	CALL     	3 4 2
	15	[219]	SELF     	4 0 -10	; "getDataFromStatistics"
	16	[220]	MOVE     	6 2
	17	[220]	LOADK    	7 -11	; " "
	18	[220]	CONCAT   	6 6 7
	19	[220]	TEST     	3 0 0
	20	[220]	JMP      	2	; to 23
	21	[220]	TESTSET  	7 3 1
	22	[220]	JMP      	3	; to 26
	23	[220]	GETTABLE 	7 0 -12	; "pages"
	24	[220]	GETTABLE 	8 0 -8	; "pageno"
	25	[220]	SUB      	7 7 8
	26	[219]	TAILCALL 	4 4 0
	27	[220]	RETURN   	4 0
	28	[221]	RETURN   	0 1

function <./frontend/apps/reader/modules/readerfooter.lua:222,235> (43 instructions, 172 bytes at 0x7fd3a0c0a790)
1 param, 9 slots, 1 upvalue, 6 locals, 21 constants, 0 functions
	1	[223]	GETTABLE 	1 0 -1	; "settings"
	2	[223]	GETTABLE 	1 1 -2	; "item_prefix"
	3	[223]	TEST     	1 0 1
	4	[223]	JMP      	1	; to 6
	5	[223]	LOADK    	1 -3	; "icons"
	6	[224]	GETUPVAL 	2 0	; symbol_prefix
	7	[224]	GETTABLE 	2 2 1
	8	[224]	GETTABLE 	2 2 -4	; "mem_usage"
	9	[225]	GETGLOBAL	3 -5	; io
	10	[225]	GETTABLE 	3 3 -6	; "open"
	11	[225]	LOADK    	4 -7	; "/proc/self/statm"
	12	[225]	LOADK    	5 -8	; "r"
	13	[225]	CALL     	3 3 2
	14	[226]	TEST     	3 0 0
	15	[226]	JMP      	25	; to 41
	16	[227]	SELF     	4 3 -9	; "read"
	17	[227]	LOADK    	6 -10	; "*all"
	18	[227]	CALL     	4 3 2
	19	[228]	SELF     	5 3 -11	; "close"
	20	[228]	CALL     	5 2 1
	21	[229]	SELF     	5 4 -12	; "match"
	22	[229]	LOADK    	7 -13	; "^%S+ (%S+) "
	23	[229]	CALL     	5 3 2
	24	[231]	GETGLOBAL	6 -14	; math
	25	[231]	GETTABLE 	6 6 -15	; "floor"
	26	[231]	GETGLOBAL	7 -16	; tonumber
	27	[231]	MOVE     	8 5
	28	[231]	CALL     	7 2 2
	29	[231]	MUL      	7 7 -17	; - 4096
	30	[231]	DIV      	7 7 -18	; - 1024
	31	[231]	DIV      	7 7 -18	; - 1024
	32	[231]	CALL     	6 2 2
	33	[231]	MOVE     	5 6
	34	[232]	MOVE     	6 2
	35	[232]	LOADK    	7 -19	; " %d"
	36	[232]	CONCAT   	6 6 7
	37	[232]	SELF     	6 6 -20	; "format"
	38	[232]	MOVE     	8 5
	39	[232]	TAILCALL 	6 3 0
	40	[232]	RETURN   	6 0
	41	[234]	LOADK    	4 -21	; ""
	42	[234]	RETURN   	4 2
	43	[235]	RETURN   	0 1

function <./frontend/apps/reader/modules/readerfooter.lua:236,245> (31 instructions, 124 bytes at 0x7fd3a0c0aa10)
1 param, 7 slots, 3 upvalues, 4 locals, 9 constants, 0 functions
	1	[237]	GETTABLE 	1 0 -1	; "settings"
	2	[237]	GETTABLE 	1 1 -2	; "item_prefix"
	3	[237]	TEST     	1 0 1
	4	[237]	JMP      	1	; to 6
	5	[237]	LOADK    	1 -3	; "icons"
	6	[238]	GETUPVAL 	2 0	; symbol_prefix
	7	[238]	GETTABLE 	2 2 1
	8	[238]	GETTABLE 	2 2 -4	; "wifi_status"
	9	[239]	GETGLOBAL	3 -5	; require
	10	[239]	LOADK    	4 -6	; "ui/network/manager"
	11	[239]	CALL     	3 2 2
	12	[240]	SELF     	4 3 -7	; "isWifiOn"
	13	[240]	CALL     	4 2 2
	14	[240]	TEST     	4 0 0
	15	[240]	JMP      	8	; to 24
	16	[241]	GETUPVAL 	4 1	; T
	17	[241]	GETUPVAL 	5 2	; _
	18	[241]	LOADK    	6 -8	; "%1 On"
	19	[241]	CALL     	5 2 2
	20	[241]	MOVE     	6 2
	21	[241]	TAILCALL 	4 3 0
	22	[241]	RETURN   	4 0
	23	[241]	JMP      	7	; to 31
	24	[243]	GETUPVAL 	4 1	; T
	25	[243]	GETUPVAL 	5 2	; _
	26	[243]	LOADK    	6 -9	; "%1 Off"
	27	[243]	CALL     	5 2 2
	28	[243]	MOVE     	6 2
	29	[243]	TAILCALL 	4 3 0
	30	[243]	RETURN   	4 0
	31	[245]	RETURN   	0 1

function <./frontend/apps/reader/modules/readerfooter.lua:246,264> (48 instructions, 192 bytes at 0x7fd3a0c0ae50)
1 param, 9 slots, 3 upvalues, 5 locals, 21 constants, 0 functions
	1	[247]	GETTABLE 	1 0 -1	; "ui"
	2	[247]	GETTABLE 	1 1 -2	; "document"
	3	[247]	SELF     	1 1 -3	; "getProps"
	4	[247]	CALL     	1 2 2
	5	[248]	TEST     	1 0 0
	6	[248]	JMP      	40	; to 47
	7	[248]	GETTABLE 	2 1 -4	; "title"
	8	[248]	TEST     	2 0 0
	9	[248]	JMP      	37	; to 47
	10	[249]	GETUPVAL 	2 0	; TextWidget
	11	[249]	SELF     	2 2 -5	; "new"
	12	[249]	NEWTABLE 	4 0 4
	13	[250]	GETTABLE 	5 1 -4	; "title"
	14	[250]	SETTABLE 	4 -6 5	; "text" -
	15	[251]	GETTABLE 	5 0 -8	; "_saved_screen_width"
	16	[251]	GETTABLE 	6 0 -9	; "settings"
	17	[251]	GETTABLE 	6 6 -10	; "book_title_max_width_pct"
	18	[251]	MUL      	5 5 6
	19	[251]	DIV      	5 5 -11	; - 100
	20	[251]	SETTABLE 	4 -7 5	; "max_width" -
	21	[252]	GETUPVAL 	5 1	; Font
	22	[252]	SELF     	5 5 -13	; "getFace"
	23	[252]	GETTABLE 	7 0 -14	; "text_font_face"
	24	[252]	GETTABLE 	8 0 -9	; "settings"
	25	[252]	GETTABLE 	8 8 -15	; "text_font_size"
	26	[252]	CALL     	5 4 2
	27	[252]	SETTABLE 	4 -12 5	; "face" -
	28	[253]	GETTABLE 	5 0 -9	; "settings"
	29	[253]	GETTABLE 	5 5 -17	; "text_font_bold"
	30	[253]	SETTABLE 	4 -16 5	; "bold" -
	31	[249]	CALL     	2 3 2
	32	[255]	SELF     	3 2 -18	; "getFittedText"
	33	[255]	CALL     	3 2 3
	34	[256]	SELF     	5 2 -19	; "free"
	35	[256]	CALL     	5 2 1
	36	[257]	TEST     	4 0 0
	37	[257]	JMP      	3	; to 41
	38	[258]	MOVE     	5 3
	39	[258]	LOADK    	6 -20	; "\226\128\166"
	40	[258]	CONCAT   	3 5 6
	41	[260]	GETUPVAL 	5 2	; BD
	42	[260]	GETTABLE 	5 5 -21	; "auto"
	43	[260]	MOVE     	6 3
	44	[260]	TAILCALL 	5 2 0
	45	[260]	RETURN   	5 0
	46	[260]	JMP      	1	; to 48
	47	[262]	RETURN   	0 1
	48	[264]	RETURN   	0 1

function <./frontend/apps/reader/modules/readerfooter.lua:265,283> (47 instructions, 188 bytes at 0x7fd3a0c0b540)
1 param, 9 slots, 3 upvalues, 5 locals, 22 constants, 0 functions
	1	[266]	GETTABLE 	1 0 -1	; "ui"
	2	[266]	GETTABLE 	1 1 -2	; "toc"
	3	[266]	SELF     	1 1 -3	; "getTocTitleByPage"
	4	[266]	GETTABLE 	3 0 -4	; "pageno"
	5	[266]	CALL     	1 3 2
	6	[267]	TEST     	1 0 0
	7	[267]	JMP      	38	; to 46
	8	[267]	EQ       	1 1 -5	; - ""
	9	[267]	JMP      	36	; to 46
	10	[268]	GETUPVAL 	2 0	; TextWidget
	11	[268]	SELF     	2 2 -6	; "new"
	12	[268]	NEWTABLE 	4 0 4
	13	[269]	SETTABLE 	4 -7 1	; "text" -
	14	[270]	GETTABLE 	5 0 -9	; "_saved_screen_width"
	15	[270]	GETTABLE 	6 0 -10	; "settings"
	16	[270]	GETTABLE 	6 6 -11	; "book_chapter_max_width_pct"
	17	[270]	MUL      	5 5 6
	18	[270]	DIV      	5 5 -12	; - 100
	19	[270]	SETTABLE 	4 -8 5	; "max_width" -
	20	[271]	GETUPVAL 	5 1	; Font
	21	[271]	SELF     	5 5 -14	; "getFace"
	22	[271]	GETTABLE 	7 0 -15	; "text_font_face"
	23	[271]	GETTABLE 	8 0 -10	; "settings"
	24	[271]	GETTABLE 	8 8 -16	; "text_font_size"
	25	[271]	CALL     	5 4 2
	26	[271]	SETTABLE 	4 -13 5	; "face" -
	27	[272]	GETTABLE 	5 0 -10	; "settings"
	28	[272]	GETTABLE 	5 5 -18	; "text_font_bold"
	29	[272]	SETTABLE 	4 -17 5	; "bold" -
	30	[268]	CALL     	2 3 2
	31	[274]	SELF     	3 2 -19	; "getFittedText"
	32	[274]	CALL     	3 2 3
	33	[275]	SELF     	5 2 -20	; "free"
	34	[275]	CALL     	5 2 1
	35	[276]	TEST     	4 0 0
	36	[276]	JMP      	3	; to 40
	37	[277]	MOVE     	5 3
	38	[277]	LOADK    	6 -21	; "\226\128\166"
	39	[277]	CONCAT   	3 5 6
	40	[279]	GETUPVAL 	5 2	; BD
	41	[279]	GETTABLE 	5 5 -22	; "auto"
	42	[279]	MOVE     	6 3
	43	[279]	TAILCALL 	5 2 0
	44	[279]	RETURN   	5 0
	45	[279]	JMP      	1	; to 47
	46	[281]	RETURN   	0 1
	47	[283]	RETURN   	0 1

function <./frontend/apps/reader/modules/readerfooter.lua:303,449> (322 instructions, 1288 bytes at 0x7fd3a0c0bd80)
1 param, 10 slots, 10 upvalues, 21 locals, 88 constants, 0 functions
	1	[304]	GETGLOBAL	1 -2	; G_reader_settings
	2	[304]	SELF     	1 1 -3	; "readSetting"
	3	[304]	LOADK    	3 -4	; "footer"
	4	[304]	CALL     	1 3 2
	5	[304]	TEST     	1 0 1
	6	[304]	JMP      	23	; to 30
	7	[304]	NEWTABLE 	1 0 18
	8	[307]	SETTABLE 	1 -5 -6	; "disabled" false
	9	[308]	SETTABLE 	1 -7 -6	; "all_at_once" false
	10	[309]	SETTABLE 	1 -8 -6	; "reclaim_height" false
	11	[310]	SETTABLE 	1 -9 -10	; "toc_markers" true
	12	[311]	SETTABLE 	1 -11 -10	; "battery" true
	13	[312]	SETTABLE 	1 -12 -10	; "time" true
	14	[313]	SETTABLE 	1 -13 -10	; "page_progress" true
	15	[314]	SETTABLE 	1 -14 -10	; "pages_left" true
	16	[315]	SETTABLE 	1 -15 -10	; "percentage" true
	17	[316]	SETTABLE 	1 -16 -10	; "book_time_to_read" true
	18	[317]	SETTABLE 	1 -17 -10	; "chapter_time_to_read" true
	19	[318]	SETTABLE 	1 -18 -6	; "frontlight" false
	20	[319]	SETTABLE 	1 -19 -6	; "mem_usage" false
	21	[320]	SETTABLE 	1 -20 -6	; "wifi_status" false
	22	[321]	SETTABLE 	1 -21 -6	; "book_title" false
	23	[322]	SETTABLE 	1 -22 -6	; "book_chapter" false
	24	[323]	SETTABLE 	1 -23 -24	; "item_prefix" "icons"
	25	[324]	GETUPVAL 	2 0	; DMINIBAR_TOC_MARKER_WIDTH
	26	[324]	SETTABLE 	1 -25 2	; "toc_markers_width" -
	27	[325]	GETUPVAL 	2 1	; DMINIBAR_FONT_SIZE
	28	[325]	SETTABLE 	1 -26 2	; "text_font_size" -
	29	[326]	SETTABLE 	1 -27 -6	; "text_font_bold" false
	30	[327]	SETTABLE 	0 -1 1	; "settings" -
	31	[329]	NEWTABLE 	1 0 0
	32	[330]	LOADNIL  	2 2
	33	[331]	SETTABLE 	0 -28 -29	; "mode_nb" 0
	34	[332]	NEWTABLE 	3 0 0
	35	[332]	SETTABLE 	0 -30 3	; "mode_index" -
	36	[333]	GETUPVAL 	3 2	; Device
	37	[333]	SELF     	3 3 -31	; "isAndroid"
	38	[333]	CALL     	3 2 2
	39	[333]	TEST     	3 0 1
	40	[333]	JMP      	2	; to 43
	41	[334]	GETUPVAL 	3 3	; MODE
	42	[334]	SETTABLE 	3 -20 -32	; "wifi_status" nil
	43	[336]	GETUPVAL 	3 2	; Device
	44	[336]	SELF     	3 3 -33	; "hasFrontlight"
	45	[336]	CALL     	3 2 2
	46	[336]	TEST     	3 0 1
	47	[336]	JMP      	2	; to 50
	48	[337]	GETUPVAL 	3 3	; MODE
	49	[337]	SETTABLE 	3 -18 -32	; "frontlight" nil
	50	[339]	GETUPVAL 	3 2	; Device
	51	[339]	SELF     	3 3 -34	; "isDesktop"
	52	[339]	CALL     	3 2 2
	53	[339]	TEST     	3 0 0
	54	[339]	JMP      	2	; to 57
	55	[340]	GETUPVAL 	3 3	; MODE
	56	[340]	SETTABLE 	3 -11 -32	; "battery" nil
	57	[342]	GETGLOBAL	3 -35	; pairs
	58	[342]	GETUPVAL 	4 3	; MODE
	59	[342]	CALL     	3 2 4
	60	[342]	JMP      	1	; to 62
	61	[343]	SETTABLE 	1 7 6
	62	[342]	TFORLOOP 	3 2
	63	[343]	JMP      	-3	; to 61
	64	[345]	LOADK    	3 -29	; 0
	65	[345]	LEN      	4 1
	66	[345]	LOADK    	5 -36	; 1
	67	[345]	FORPREP  	3 9	; to 77
	68	[346]	GETTABLE 	2 1 6
	69	[347]	TEST     	2 0 0
	70	[347]	JMP      	6	; to 77
	71	[348]	GETTABLE 	7 0 -30	; "mode_index"
	72	[348]	GETTABLE 	8 0 -28	; "mode_nb"
	73	[348]	SETTABLE 	7 8 2
	74	[349]	GETTABLE 	7 0 -28	; "mode_nb"
	75	[349]	ADD      	7 7 -36	; - 1
	76	[349]	SETTABLE 	0 -28 7	; "mode_nb" -
	77	[345]	FORLOOP  	3 -10	; to 68
	78	[352]	GETTABLE 	3 0 -1	; "settings"
	79	[352]	GETTABLE 	3 3 -37	; "order"
	80	[352]	TEST     	3 0 0
	81	[352]	JMP      	27	; to 109
	82	[353]	GETTABLE 	3 0 -1	; "settings"
	83	[353]	GETTABLE 	3 3 -37	; "order"
	84	[353]	LEN      	3 3
	85	[353]	GETTABLE 	4 0 -30	; "mode_index"
	86	[353]	LEN      	4 4
	87	[353]	LT       	0 3 4
	88	[353]	JMP      	14	; to 103
	89	[354]	GETTABLE 	3 0 -1	; "settings"
	90	[354]	GETTABLE 	3 3 -37	; "order"
	91	[354]	GETTABLE 	4 0 -1	; "settings"
	92	[354]	GETTABLE 	4 4 -37	; "order"
	93	[354]	LEN      	4 4
	94	[354]	ADD      	4 4 -36	; - 1
	95	[354]	GETTABLE 	5 0 -30	; "mode_index"
	96	[354]	GETTABLE 	6 0 -1	; "settings"
	97	[354]	GETTABLE 	6 6 -37	; "order"
	98	[354]	LEN      	6 6
	99	[354]	ADD      	6 6 -36	; - 1
	100	[354]	GETTABLE 	5 5 6
	101	[354]	SETTABLE 	3 4 5
	102	[354]	JMP      	-21	; to 82
	103	[356]	GETTABLE 	3 0 -1	; "settings"
	104	[356]	GETTABLE 	3 3 -37	; "order"
	105	[356]	SETTABLE 	0 -30 3	; "mode_index" -
	106	[357]	GETTABLE 	3 0 -30	; "mode_index"
	107	[357]	LEN      	3 3
	108	[357]	SETTABLE 	0 -28 3	; "mode_nb" -
	109	[361]	GETTABLE 	3 0 -1	; "settings"
	110	[361]	GETTABLE 	3 3 -38	; "progress_margin_width"
	111	[361]	TEST     	3 0 1
	112	[361]	JMP      	6	; to 119
	113	[362]	GETTABLE 	3 0 -1	; "settings"
	114	[362]	GETUPVAL 	4 4	; Screen
	115	[362]	SELF     	4 4 -39	; "scaleBySize"
	116	[362]	LOADK    	6 -40	; 10
	117	[362]	CALL     	4 3 2
	118	[362]	SETTABLE 	3 -38 4	; "progress_margin_width" -
	119	[364]	GETTABLE 	3 0 -1	; "settings"
	120	[364]	GETTABLE 	3 3 -25	; "toc_markers_width"
	121	[364]	TEST     	3 0 1
	122	[364]	JMP      	3	; to 126
	123	[365]	GETTABLE 	3 0 -1	; "settings"
	124	[365]	GETUPVAL 	4 0	; DMINIBAR_TOC_MARKER_WIDTH
	125	[365]	SETTABLE 	3 -25 4	; "toc_markers_width" -
	126	[367]	GETTABLE 	3 0 -1	; "settings"
	127	[367]	GETTABLE 	3 3 -41	; "progress_bar_min_width_pct"
	128	[367]	TEST     	3 0 1
	129	[367]	JMP      	2	; to 132
	130	[368]	GETTABLE 	3 0 -1	; "settings"
	131	[368]	SETTABLE 	3 -41 -42	; "progress_bar_min_width_pct" 20
	132	[370]	GETTABLE 	3 0 -1	; "settings"
	133	[370]	GETTABLE 	3 3 -43	; "book_title_max_width_pct"
	134	[370]	TEST     	3 0 1
	135	[370]	JMP      	2	; to 138
	136	[371]	GETTABLE 	3 0 -1	; "settings"
	137	[371]	SETTABLE 	3 -43 -44	; "book_title_max_width_pct" 30
	138	[373]	GETTABLE 	3 0 -1	; "settings"
	139	[373]	GETTABLE 	3 3 -45	; "book_chapter_max_width_pct"
	140	[373]	TEST     	3 0 1
	141	[373]	JMP      	2	; to 144
	142	[374]	GETTABLE 	3 0 -1	; "settings"
	143	[374]	SETTABLE 	3 -45 -44	; "book_chapter_max_width_pct" 30
	144	[376]	NEWTABLE 	3 0 0
	145	[376]	SETTABLE 	0 -46 3	; "mode_list" -
	146	[377]	LOADK    	3 -29	; 0
	147	[377]	GETTABLE 	4 0 -30	; "mode_index"
	148	[377]	LEN      	4 4
	149	[377]	LOADK    	5 -36	; 1
	150	[377]	FORPREP  	3 4	; to 155
	151	[378]	GETTABLE 	7 0 -46	; "mode_list"
	152	[378]	GETTABLE 	8 0 -30	; "mode_index"
	153	[378]	GETTABLE 	8 8 6
	154	[378]	SETTABLE 	7 8 6
	155	[377]	FORLOOP  	3 -5	; to 151
	156	[380]	GETTABLE 	3 0 -1	; "settings"
	157	[380]	GETTABLE 	3 3 -5	; "disabled"
	158	[380]	TEST     	3 0 0
	159	[380]	JMP      	3	; to 163
	160	[382]	SELF     	3 0 -47	; "disableFooter"
	161	[382]	CALL     	3 2 1
	162	[383]	RETURN   	0 1
	163	[386]	GETTABLE 	3 0 -49	; "view"
	164	[386]	GETTABLE 	3 3 -50	; "state"
	165	[386]	GETTABLE 	3 3 -51	; "page"
	166	[386]	SETTABLE 	0 -48 3	; "pageno" -
	167	[387]	SETTABLE 	0 -52 -10	; "has_no_mode" true
	168	[388]	GETTABLE 	3 0 -1	; "settings"
	169	[388]	GETTABLE 	3 3 -8	; "reclaim_height"
	170	[388]	TEST     	3 0 1
	171	[388]	JMP      	1	; to 173
	172	[388]	LOADBOOL 	3 0 0
	173	[388]	SETTABLE 	0 -8 3	; "reclaim_height" -
	174	[389]	GETGLOBAL	3 -53	; ipairs
	175	[389]	GETTABLE 	4 0 -30	; "mode_index"
	176	[389]	CALL     	3 2 4
	177	[389]	JMP      	6	; to 184
	178	[390]	GETTABLE 	8 0 -1	; "settings"
	179	[390]	GETTABLE 	8 8 7
	180	[390]	TEST     	8 0 0
	181	[390]	JMP      	2	; to 184
	182	[391]	SETTABLE 	0 -52 -6	; "has_no_mode" false
	183	[392]	JMP      	2	; to 186
	184	[389]	TFORLOOP 	3 2
	185	[393]	JMP      	-8	; to 178
	186	[396]	GETTABLE 	3 0 -1	; "settings"
	187	[396]	GETTABLE 	3 3 -26	; "text_font_size"
	188	[396]	TEST     	3 0 1
	189	[396]	JMP      	3	; to 193
	190	[397]	GETTABLE 	3 0 -1	; "settings"
	191	[397]	GETUPVAL 	4 1	; DMINIBAR_FONT_SIZE
	192	[397]	SETTABLE 	3 -26 4	; "text_font_size" -
	193	[399]	GETTABLE 	3 0 -1	; "settings"
	194	[399]	GETTABLE 	3 3 -27	; "text_font_bold"
	195	[399]	TEST     	3 0 1
	196	[399]	JMP      	2	; to 199
	197	[400]	GETTABLE 	3 0 -1	; "settings"
	198	[400]	SETTABLE 	3 -27 -6	; "text_font_bold" false
	199	[402]	GETUPVAL 	3 5	; TextWidget
	200	[402]	SELF     	3 3 -55	; "new"
	201	[402]	NEWTABLE 	5 0 3
	202	[403]	SETTABLE 	5 -56 -57	; "text" ""
	203	[404]	GETUPVAL 	6 6	; Font
	204	[404]	SELF     	6 6 -59	; "getFace"
	205	[404]	GETTABLE 	8 0 -60	; "text_font_face"
	206	[404]	GETTABLE 	9 0 -1	; "settings"
	207	[404]	GETTABLE 	9 9 -26	; "text_font_size"
	208	[404]	CALL     	6 4 2
	209	[404]	SETTABLE 	5 -58 6	; "face" -
	210	[405]	GETTABLE 	6 0 -1	; "settings"
	211	[405]	GETTABLE 	6 6 -27	; "text_font_bold"
	212	[405]	SETTABLE 	5 -61 6	; "bold" -
	213	[402]	CALL     	3 3 2
	214	[406]	SETTABLE 	0 -54 3	; "footer_text" -
	215	[408]	SETTABLE 	0 -62 -29	; "text_width" 0
	216	[409]	GETUPVAL 	3 7	; ProgressWidget
	217	[409]	SELF     	3 3 -55	; "new"
	218	[409]	NEWTABLE 	5 0 6
	219	[410]	SETTABLE 	5 -64 -32	; "width" nil
	220	[411]	SETTABLE 	5 -65 -32	; "height" nil
	221	[412]	GETTABLE 	6 0 -66	; "progress_percentage"
	222	[412]	SETTABLE 	5 -15 6	; "percentage" -
	223	[413]	GETUPVAL 	6 4	; Screen
	224	[413]	SELF     	6 6 -39	; "scaleBySize"
	225	[413]	GETTABLE 	8 0 -1	; "settings"
	226	[413]	GETTABLE 	8 8 -25	; "toc_markers_width"
	227	[413]	CALL     	6 3 2
	228	[413]	SETTABLE 	5 -67 6	; "tick_width" -
	229	[414]	SETTABLE 	5 -68 -32	; "ticks" nil
	230	[415]	SETTABLE 	5 -69 -32	; "last" nil
	231	[409]	CALL     	3 3 2
	232	[416]	SETTABLE 	0 -63 3	; "progress_bar" -
	233	[418]	GETTABLE 	3 0 -1	; "settings"
	234	[418]	GETTABLE 	3 3 -70	; "progress_style_thin"
	235	[418]	TEST     	3 0 0
	236	[418]	JMP      	5	; to 242
	237	[419]	GETTABLE 	3 0 -63	; "progress_bar"
	238	[419]	SELF     	3 3 -71	; "updateStyle"
	239	[419]	LOADBOOL 	5 0 0
	240	[419]	LOADNIL  	6 6
	241	[419]	CALL     	3 4 1
	242	[422]	GETUPVAL 	3 8	; RightContainer
	243	[422]	SELF     	3 3 -55	; "new"
	244	[422]	NEWTABLE 	5 1 1
	245	[423]	GETUPVAL 	6 9	; Geom
	246	[423]	SELF     	6 6 -55	; "new"
	247	[423]	NEWTABLE 	8 0 2
	248	[423]	SETTABLE 	8 -74 -29	; "w" 0
	249	[423]	GETTABLE 	9 0 -65	; "height"
	250	[423]	SETTABLE 	8 -75 9	; "h" -
	251	[423]	CALL     	6 3 2
	252	[423]	SETTABLE 	5 -73 6	; "dimen" -
	253	[425]	GETTABLE 	6 0 -54	; "footer_text"
	254	[425]	SETLIST  	5 1 1	; 1
	255	[422]	CALL     	3 3 2
	256	[425]	SETTABLE 	0 -72 3	; "text_container" -
	257	[426]	SELF     	3 0 -76	; "updateFooterContainer"
	258	[426]	CALL     	3 2 1
	259	[427]	GETGLOBAL	3 -2	; G_reader_settings
	260	[427]	SELF     	3 3 -3	; "readSetting"
	261	[427]	LOADK    	5 -78	; "reader_footer_mode"
	262	[427]	CALL     	3 3 2
	263	[427]	TEST     	3 0 1
	264	[427]	JMP      	1	; to 266
	265	[427]	GETTABLE 	3 0 -77	; "mode"
	266	[427]	SETTABLE 	0 -77 3	; "mode" -
	267	[428]	GETTABLE 	3 0 -52	; "has_no_mode"
	268	[428]	TEST     	3 0 0
	269	[428]	JMP      	16	; to 286
	270	[428]	GETTABLE 	3 0 -1	; "settings"
	271	[428]	GETTABLE 	3 3 -79	; "disable_progress_bar"
	272	[428]	TEST     	3 0 0
	273	[428]	JMP      	12	; to 286
	274	[429]	GETTABLE 	3 0 -46	; "mode_list"
	275	[429]	GETTABLE 	3 3 -80	; "off"
	276	[429]	SETTABLE 	0 -77 3	; "mode" -
	277	[430]	GETTABLE 	3 0 -49	; "view"
	278	[430]	SETTABLE 	3 -81 -6	; "footer_visible" false
	279	[431]	SELF     	3 0 -82	; "resetLayout"
	280	[431]	CALL     	3 2 1
	281	[432]	GETTABLE 	3 0 -83	; "footer_container"
	282	[432]	GETTABLE 	3 3 -73	; "dimen"
	283	[432]	SETTABLE 	3 -75 -29	; "h" 0
	284	[433]	GETTABLE 	3 0 -54	; "footer_text"
	285	[433]	SETTABLE 	3 -65 -29	; "height" 0
	286	[436]	GETTABLE 	3 0 -1	; "settings"
	287	[436]	GETTABLE 	3 3 -7	; "all_at_once"
	288	[436]	TEST     	3 0 0
	289	[436]	JMP      	24	; to 314
	290	[437]	GETTABLE 	3 0 -49	; "view"
	291	[437]	GETTABLE 	4 0 -77	; "mode"
	292	[437]	GETTABLE 	5 0 -46	; "mode_list"
	293	[437]	GETTABLE 	5 5 -80	; "off"
	294	[437]	EQ       	0 4 5
	295	[437]	JMP      	1	; to 297
	296	[437]	LOADBOOL 	4 0 1
	297	[437]	LOADBOOL 	4 1 0
	298	[437]	SETTABLE 	3 -81 4	; "footer_visible" -
	299	[438]	SELF     	3 0 -84	; "updateFooterTextGenerator"
	300	[438]	CALL     	3 2 1
	301	[439]	GETTABLE 	3 0 -1	; "settings"
	302	[439]	GETTABLE 	3 3 -85	; "progress_bar_position"
	303	[439]	TEST     	3 0 0
	304	[439]	JMP      	11	; to 316
	305	[439]	GETTABLE 	3 0 -52	; "has_no_mode"
	306	[439]	TEST     	3 0 0
	307	[439]	JMP      	8	; to 316
	308	[440]	GETTABLE 	3 0 -83	; "footer_container"
	309	[440]	GETTABLE 	3 3 -73	; "dimen"
	310	[440]	SETTABLE 	3 -75 -29	; "h" 0
	311	[441]	GETTABLE 	3 0 -54	; "footer_text"
	312	[441]	SETTABLE 	3 -65 -29	; "height" 0
	313	[442]	JMP      	2	; to 316
	314	[444]	SELF     	3 0 -86	; "applyFooterMode"
	315	[444]	CALL     	3 2 1
	316	[446]	GETTABLE 	3 0 -1	; "settings"
	317	[446]	GETTABLE 	3 3 -87	; "auto_refresh_time"
	318	[446]	TEST     	3 0 0
	319	[446]	JMP      	2	; to 322
	320	[447]	SELF     	3 0 -88	; "setupAutoRefreshTime"
	321	[447]	CALL     	3 2 1
	322	[449]	RETURN   	0 1

function <./frontend/apps/reader/modules/readerfooter.lua:451,523> (219 instructions, 876 bytes at 0x7fd3a0c0ceb0)
1 param, 9 slots, 13 upvalues, 4 locals, 37 constants, 0 functions
	1	[452]	GETUPVAL 	1 0	; HorizontalSpan
	2	[452]	SELF     	1 1 -1	; "new"
	3	[452]	NEWTABLE 	3 0 1
	4	[452]	GETTABLE 	4 0 -3	; "horizontal_margin"
	5	[452]	SETTABLE 	3 -2 4	; "width" -
	6	[452]	CALL     	1 3 2
	7	[453]	GETUPVAL 	2 1	; VerticalGroup
	8	[453]	SELF     	2 2 -1	; "new"
	9	[453]	NEWTABLE 	4 0 0
	10	[453]	CALL     	2 3 2
	11	[453]	SETTABLE 	0 -4 2	; "vertical_frame" -
	12	[454]	GETTABLE 	2 0 -5	; "settings"
	13	[454]	GETTABLE 	2 2 -6	; "bottom_horizontal_separator"
	14	[454]	TEST     	2 0 0
	15	[454]	JMP      	32	; to 48
	16	[455]	GETUPVAL 	2 2	; LineWidget
	17	[455]	SELF     	2 2 -1	; "new"
	18	[455]	NEWTABLE 	4 0 1
	19	[456]	GETUPVAL 	5 3	; Geom
	20	[456]	SELF     	5 5 -1	; "new"
	21	[456]	NEWTABLE 	7 0 2
	22	[457]	SETTABLE 	7 -9 -10	; "w" 0
	23	[458]	GETUPVAL 	8 4	; Size
	24	[458]	GETTABLE 	8 8 -12	; "line"
	25	[458]	GETTABLE 	8 8 -13	; "medium"
	26	[458]	SETTABLE 	7 -11 8	; "h" -
	27	[456]	CALL     	5 3 2
	28	[459]	SETTABLE 	4 -8 5	; "dimen" -
	29	[455]	CALL     	2 3 2
	30	[460]	SETTABLE 	0 -7 2	; "separator_line" -
	31	[461]	GETUPVAL 	2 5	; VerticalSpan
	32	[461]	SELF     	2 2 -1	; "new"
	33	[461]	NEWTABLE 	4 0 1
	34	[461]	GETTABLE 	5 0 -14	; "bottom_padding"
	35	[461]	MUL      	5 5 -15	; - 2
	36	[461]	SETTABLE 	4 -2 5	; "width" -
	37	[461]	CALL     	2 3 2
	38	[462]	GETGLOBAL	3 -16	; table
	39	[462]	GETTABLE 	3 3 -17	; "insert"
	40	[462]	GETTABLE 	4 0 -4	; "vertical_frame"
	41	[462]	GETTABLE 	5 0 -7	; "separator_line"
	42	[462]	CALL     	3 3 1
	43	[463]	GETGLOBAL	3 -16	; table
	44	[463]	GETTABLE 	3 3 -17	; "insert"
	45	[463]	GETTABLE 	4 0 -4	; "vertical_frame"
	46	[463]	MOVE     	5 2
	47	[463]	CALL     	3 3 1
	48	[465]	GETTABLE 	2 0 -5	; "settings"
	49	[465]	GETTABLE 	2 2 -18	; "progress_bar_position"
	50	[465]	TEST     	2 0 0
	51	[465]	JMP      	14	; to 66
	52	[465]	GETTABLE 	2 0 -5	; "settings"
	53	[465]	GETTABLE 	2 2 -19	; "disable_progress_bar"
	54	[465]	TEST     	2 0 1
	55	[465]	JMP      	10	; to 66
	56	[466]	GETUPVAL 	2 6	; HorizontalGroup
	57	[466]	SELF     	2 2 -1	; "new"
	58	[466]	NEWTABLE 	4 3 0
	59	[467]	MOVE     	5 1
	60	[468]	GETTABLE 	6 0 -21	; "text_container"
	61	[470]	MOVE     	7 1
	62	[470]	SETLIST  	4 3 1	; 1
	63	[466]	CALL     	2 3 2
	64	[470]	SETTABLE 	0 -20 2	; "horizontal_group" -
	65	[470]	JMP      	10	; to 76
	66	[472]	GETUPVAL 	2 6	; HorizontalGroup
	67	[472]	SELF     	2 2 -1	; "new"
	68	[472]	NEWTABLE 	4 4 0
	69	[473]	MOVE     	5 1
	70	[474]	GETTABLE 	6 0 -22	; "progress_bar"
	71	[475]	GETTABLE 	7 0 -21	; "text_container"
	72	[477]	MOVE     	8 1
	73	[477]	SETLIST  	4 4 1	; 1
	74	[472]	CALL     	2 3 2
	75	[477]	SETTABLE 	0 -20 2	; "horizontal_group" -
	76	[480]	GETTABLE 	2 0 -5	; "settings"
	77	[480]	GETTABLE 	2 2 -23	; "align"
	78	[480]	EQ       	0 2 -24	; - "left"
	79	[480]	JMP      	16	; to 96
	80	[481]	GETUPVAL 	2 7	; LeftContainer
	81	[481]	SELF     	2 2 -1	; "new"
	82	[481]	NEWTABLE 	4 1 1
	83	[482]	GETUPVAL 	5 3	; Geom
	84	[482]	SELF     	5 5 -1	; "new"
	85	[482]	NEWTABLE 	7 0 2
	86	[482]	SETTABLE 	7 -9 -10	; "w" 0
	87	[482]	GETTABLE 	8 0 -26	; "height"
	88	[482]	SETTABLE 	7 -11 8	; "h" -
	89	[482]	CALL     	5 3 2
	90	[482]	SETTABLE 	4 -8 5	; "dimen" -
	91	[484]	GETTABLE 	5 0 -20	; "horizontal_group"
	92	[484]	SETLIST  	4 1 1	; 1
	93	[481]	CALL     	2 3 2
	94	[484]	SETTABLE 	0 -25 2	; "footer_container" -
	95	[484]	JMP      	35	; to 131
	96	[485]	GETTABLE 	2 0 -5	; "settings"
	97	[485]	GETTABLE 	2 2 -23	; "align"
	98	[485]	EQ       	0 2 -27	; - "right"
	99	[485]	JMP      	16	; to 116
	100	[486]	GETUPVAL 	2 8	; RightContainer
	101	[486]	SELF     	2 2 -1	; "new"
	102	[486]	NEWTABLE 	4 1 1
	103	[487]	GETUPVAL 	5 3	; Geom
	104	[487]	SELF     	5 5 -1	; "new"
	105	[487]	NEWTABLE 	7 0 2
	106	[487]	SETTABLE 	7 -9 -10	; "w" 0
	107	[487]	GETTABLE 	8 0 -26	; "height"
	108	[487]	SETTABLE 	7 -11 8	; "h" -
	109	[487]	CALL     	5 3 2
	110	[487]	SETTABLE 	4 -8 5	; "dimen" -
	111	[489]	GETTABLE 	5 0 -20	; "horizontal_group"
	112	[489]	SETLIST  	4 1 1	; 1
	113	[486]	CALL     	2 3 2
	114	[489]	SETTABLE 	0 -25 2	; "footer_container" -
	115	[489]	JMP      	15	; to 131
	116	[491]	GETUPVAL 	2 9	; CenterContainer
	117	[491]	SELF     	2 2 -1	; "new"
	118	[491]	NEWTABLE 	4 1 1
	119	[492]	GETUPVAL 	5 3	; Geom
	120	[492]	SELF     	5 5 -1	; "new"
	121	[492]	NEWTABLE 	7 0 2
	122	[492]	SETTABLE 	7 -9 -10	; "w" 0
	123	[492]	GETTABLE 	8 0 -26	; "height"
	124	[492]	SETTABLE 	7 -11 8	; "h" -
	125	[492]	CALL     	5 3 2
	126	[492]	SETTABLE 	4 -8 5	; "dimen" -
	127	[494]	GETTABLE 	5 0 -20	; "horizontal_group"
	128	[494]	SETLIST  	4 1 1	; 1
	129	[491]	CALL     	2 3 2
	130	[494]	SETTABLE 	0 -25 2	; "footer_container" -
	131	[497]	GETUPVAL 	2 5	; VerticalSpan
	132	[497]	SELF     	2 2 -1	; "new"
	133	[497]	NEWTABLE 	4 0 1
	134	[497]	GETTABLE 	5 0 -14	; "bottom_padding"
	135	[497]	MUL      	5 5 -15	; - 2
	136	[497]	SETTABLE 	4 -2 5	; "width" -
	137	[497]	CALL     	2 3 2
	138	[499]	GETTABLE 	3 0 -5	; "settings"
	139	[499]	GETTABLE 	3 3 -18	; "progress_bar_position"
	140	[499]	EQ       	0 3 -28	; - "above"
	141	[499]	JMP      	20	; to 162
	142	[499]	GETTABLE 	3 0 -5	; "settings"
	143	[499]	GETTABLE 	3 3 -19	; "disable_progress_bar"
	144	[499]	TEST     	3 0 1
	145	[499]	JMP      	16	; to 162
	146	[500]	GETGLOBAL	3 -16	; table
	147	[500]	GETTABLE 	3 3 -17	; "insert"
	148	[500]	GETTABLE 	4 0 -4	; "vertical_frame"
	149	[500]	GETTABLE 	5 0 -22	; "progress_bar"
	150	[500]	CALL     	3 3 1
	151	[501]	GETGLOBAL	3 -16	; table
	152	[501]	GETTABLE 	3 3 -17	; "insert"
	153	[501]	GETTABLE 	4 0 -4	; "vertical_frame"
	154	[501]	MOVE     	5 2
	155	[501]	CALL     	3 3 1
	156	[502]	GETGLOBAL	3 -16	; table
	157	[502]	GETTABLE 	3 3 -17	; "insert"
	158	[502]	GETTABLE 	4 0 -4	; "vertical_frame"
	159	[502]	GETTABLE 	5 0 -25	; "footer_container"
	160	[502]	CALL     	3 3 1
	161	[502]	JMP      	29	; to 191
	162	[503]	GETTABLE 	3 0 -5	; "settings"
	163	[503]	GETTABLE 	3 3 -18	; "progress_bar_position"
	164	[503]	EQ       	0 3 -29	; - "below"
	165	[503]	JMP      	20	; to 186
	166	[503]	GETTABLE 	3 0 -5	; "settings"
	167	[503]	GETTABLE 	3 3 -19	; "disable_progress_bar"
	168	[503]	TEST     	3 0 1
	169	[503]	JMP      	16	; to 186
	170	[504]	GETGLOBAL	3 -16	; table
	171	[504]	GETTABLE 	3 3 -17	; "insert"
	172	[504]	GETTABLE 	4 0 -4	; "vertical_frame"
	173	[504]	GETTABLE 	5 0 -25	; "footer_container"
	174	[504]	CALL     	3 3 1
	175	[505]	GETGLOBAL	3 -16	; table
	176	[505]	GETTABLE 	3 3 -17	; "insert"
	177	[505]	GETTABLE 	4 0 -4	; "vertical_frame"
	178	[505]	MOVE     	5 2
	179	[505]	CALL     	3 3 1
	180	[506]	GETGLOBAL	3 -16	; table
	181	[506]	GETTABLE 	3 3 -17	; "insert"
	182	[506]	GETTABLE 	4 0 -4	; "vertical_frame"
	183	[506]	GETTABLE 	5 0 -22	; "progress_bar"
	184	[506]	CALL     	3 3 1
	185	[506]	JMP      	5	; to 191
	186	[508]	GETGLOBAL	3 -16	; table
	187	[508]	GETTABLE 	3 3 -17	; "insert"
	188	[508]	GETTABLE 	4 0 -4	; "vertical_frame"
	189	[508]	GETTABLE 	5 0 -25	; "footer_container"
	190	[508]	CALL     	3 3 1
	191	[510]	GETUPVAL 	3 10	; FrameContainer
	192	[510]	SELF     	3 3 -1	; "new"
	193	[510]	NEWTABLE 	5 1 4
	194	[511]	GETTABLE 	6 0 -4	; "vertical_frame"
	195	[512]	GETUPVAL 	7 11	; Blitbuffer
	196	[512]	GETTABLE 	7 7 -32	; "COLOR_WHITE"
	197	[512]	SETTABLE 	5 -31 7	; "background" -
	198	[513]	SETTABLE 	5 -33 -10	; "bordersize" 0
	199	[514]	SETTABLE 	5 -34 -10	; "padding" 0
	200	[515]	GETTABLE 	7 0 -14	; "bottom_padding"
	201	[515]	SETTABLE 	5 -35 7	; "padding_bottom" -
	202	[516]	SETLIST  	5 1 1	; 1
	203	[510]	CALL     	3 3 2
	204	[516]	SETTABLE 	0 -30 3	; "footer_content" -
	205	[518]	GETUPVAL 	3 12	; BottomContainer
	206	[518]	SELF     	3 3 -1	; "new"
	207	[518]	NEWTABLE 	5 1 1
	208	[519]	GETUPVAL 	6 3	; Geom
	209	[519]	SELF     	6 6 -1	; "new"
	210	[519]	NEWTABLE 	8 0 0
	211	[519]	CALL     	6 3 2
	212	[519]	SETTABLE 	5 -8 6	; "dimen" -
	213	[521]	GETTABLE 	6 0 -30	; "footer_content"
	214	[521]	SETLIST  	5 1 1	; 1
	215	[518]	CALL     	3 3 2
	216	[521]	SETTABLE 	0 -36 3	; "footer_positioner" -
	217	[522]	GETTABLE 	3 0 -36	; "footer_positioner"
	218	[522]	SETTABLE 	0 -37 3	; 1 -
	219	[523]	RETURN   	0 1

function <./frontend/apps/reader/modules/readerfooter.lua:525,536> (23 instructions, 92 bytes at 0x7fd3a0c0d8e0)
1 param, 6 slots, 1 upvalue, 1 local, 8 constants, 2 functions
	1	[526]	GETTABLE 	1 0 -1	; "autoRefreshTime"
	2	[526]	TEST     	1 0 1
	3	[526]	JMP      	4	; to 8
	4	[530]	CLOSURE  	1 0	; 0x7fd3a0c0d3c0
	5	[530]	MOVE     	0 0
	6	[530]	GETUPVAL 	0 0	; UIManager
	7	[530]	SETTABLE 	0 -1 1	; "autoRefreshTime" -
	8	[534]	CLOSURE  	1 1	; 0x7fd3a0c0d6a0
	9	[534]	GETUPVAL 	0 0	; UIManager
	10	[534]	MOVE     	0 0
	11	[534]	SETTABLE 	0 -2 1	; "onCloseDocument" -
	12	[535]	GETUPVAL 	1 0	; UIManager
	13	[535]	SELF     	1 1 -3	; "scheduleIn"
	14	[535]	GETGLOBAL	3 -4	; tonumber
	15	[535]	GETGLOBAL	4 -5	; os
	16	[535]	GETTABLE 	4 4 -6	; "date"
	17	[535]	LOADK    	5 -7	; "%S"
	18	[535]	CALL     	4 2 0
	19	[535]	CALL     	3 0 2
	20	[535]	SUB      	3 -8 3	; 61 -
	21	[535]	GETTABLE 	4 0 -1	; "autoRefreshTime"
	22	[535]	CALL     	1 4 1
	23	[536]	RETURN   	0 1

function <./frontend/apps/reader/modules/readerfooter.lua:527,530> (17 instructions, 68 bytes at 0x7fd3a0c0d3c0)
0 params, 5 slots, 2 upvalues, 0 locals, 8 constants, 0 functions
	1	[528]	GETUPVAL 	0 0	; self
	2	[528]	SELF     	0 0 -1	; "updateFooter"
	3	[528]	LOADBOOL 	2 1 0
	4	[528]	CALL     	0 3 1
	5	[529]	GETUPVAL 	0 1	; UIManager
	6	[529]	SELF     	0 0 -2	; "scheduleIn"
	7	[529]	GETGLOBAL	2 -3	; tonumber
	8	[529]	GETGLOBAL	3 -4	; os
	9	[529]	GETTABLE 	3 3 -5	; "date"
	10	[529]	LOADK    	4 -6	; "%S"
	11	[529]	CALL     	3 2 0
	12	[529]	CALL     	2 0 2
	13	[529]	SUB      	2 -7 2	; 61 -
	14	[529]	GETUPVAL 	3 0	; self
	15	[529]	GETTABLE 	3 3 -8	; "autoRefreshTime"
	16	[529]	CALL     	0 4 1
	17	[530]	RETURN   	0 1

function <./frontend/apps/reader/modules/readerfooter.lua:532,534> (6 instructions, 24 bytes at 0x7fd3a0c0d6a0)
0 params, 3 slots, 2 upvalues, 0 locals, 2 constants, 0 functions
	1	[533]	GETUPVAL 	0 0	; UIManager
	2	[533]	SELF     	0 0 -1	; "unschedule"
	3	[533]	GETUPVAL 	2 1	; self
	4	[533]	GETTABLE 	2 2 -2	; "autoRefreshTime"
	5	[533]	CALL     	0 3 1
	6	[534]	RETURN   	0 1

function <./frontend/apps/reader/modules/readerfooter.lua:538,568> (45 instructions, 180 bytes at 0x7fd3a0c0e170)
1 param, 10 slots, 1 upvalue, 2 locals, 24 constants, 2 functions
	1	[539]	GETUPVAL 	1 0	; Device
	2	[539]	SELF     	1 1 -1	; "isTouchDevice"
	3	[539]	CALL     	1 2 2
	4	[539]	TEST     	1 0 1
	5	[539]	JMP      	1	; to 7
	6	[539]	RETURN   	0 1
	7	[540]	NEWTABLE 	1 0 4
	8	[541]	GETGLOBAL	2 -3	; DTAP_ZONE_MINIBAR
	9	[541]	GETTABLE 	2 2 -4	; "x"
	10	[541]	SETTABLE 	1 -2 2	; "ratio_x" -
	11	[541]	GETGLOBAL	2 -3	; DTAP_ZONE_MINIBAR
	12	[541]	GETTABLE 	2 2 -6	; "y"
	13	[541]	SETTABLE 	1 -5 2	; "ratio_y" -
	14	[542]	GETGLOBAL	2 -3	; DTAP_ZONE_MINIBAR
	15	[542]	GETTABLE 	2 2 -8	; "w"
	16	[542]	SETTABLE 	1 -7 2	; "ratio_w" -
	17	[542]	GETGLOBAL	2 -3	; DTAP_ZONE_MINIBAR
	18	[542]	GETTABLE 	2 2 -10	; "h"
	19	[542]	SETTABLE 	1 -9 2	; "ratio_h" -
	20	[544]	GETTABLE 	2 0 -11	; "ui"
	21	[544]	SELF     	2 2 -12	; "registerTouchZones"
	22	[544]	NEWTABLE 	4 2 0
	23	[544]	NEWTABLE 	5 0 5
	24	[546]	SETTABLE 	5 -13 -14	; "id" "readerfooter_tap"
	25	[547]	SETTABLE 	5 -15 -16	; "ges" "tap"
	26	[548]	SETTABLE 	5 -17 1	; "screen_zone" -
	27	[549]	CLOSURE  	6 0	; 0x7fd3a0c0e3d0
	28	[549]	MOVE     	0 0
	29	[549]	SETTABLE 	5 -18 6	; "handler" -
	30	[550]	NEWTABLE 	6 3 0
	31	[551]	LOADK    	7 -20	; "tap_forward"
	32	[552]	LOADK    	8 -21	; "tap_backward"
	33	[554]	LOADK    	9 -22	; "readerconfigmenu_tap"
	34	[554]	SETLIST  	6 3 1	; 1
	35	[554]	SETTABLE 	5 -19 6	; "overrides" -
	36	[557]	NEWTABLE 	6 0 4
	37	[559]	SETTABLE 	6 -13 -23	; "id" "readerfooter_hold"
	38	[560]	SETTABLE 	6 -15 -24	; "ges" "hold"
	39	[561]	SETTABLE 	6 -17 1	; "screen_zone" -
	40	[562]	CLOSURE  	7 1	; 0x7fd3a0c0e4d0
	41	[562]	MOVE     	0 0
	42	[562]	SETTABLE 	6 -18 7	; "handler" -
	43	[567]	SETLIST  	4 2 1	; 1
	44	[544]	CALL     	2 3 1
	45	[568]	RETURN   	0 1

function <./frontend/apps/reader/modules/readerfooter.lua:549,549> (6 instructions, 24 bytes at 0x7fd3a0c0e3d0)
1 param, 4 slots, 1 upvalue, 1 local, 1 constant, 0 functions
	1	[549]	GETUPVAL 	1 0	; self
	2	[549]	SELF     	1 1 -1	; "onTapFooter"
	3	[549]	MOVE     	3 0
	4	[549]	TAILCALL 	1 3 0
	5	[549]	RETURN   	1 0
	6	[549]	RETURN   	0 1

function <./frontend/apps/reader/modules/readerfooter.lua:562,562> (5 instructions, 20 bytes at 0x7fd3a0c0e4d0)
0 params, 2 slots, 1 upvalue, 0 locals, 1 constant, 0 functions
	1	[562]	GETUPVAL 	0 0	; self
	2	[562]	SELF     	0 0 -1	; "onHoldFooter"
	3	[562]	TAILCALL 	0 2 0
	4	[562]	RETURN   	0 0
	5	[562]	RETURN   	0 1

function <./frontend/apps/reader/modules/readerfooter.lua:571,604> (97 instructions, 388 bytes at 0x7fd3a0c0a5e0)
2 params, 9 slots, 3 upvalues, 5 locals, 30 constants, 0 functions
	1	[572]	GETUPVAL 	2 0	; Screen
	2	[572]	SELF     	2 2 -1	; "getWidth"
	3	[572]	CALL     	2 2 2
	4	[573]	GETUPVAL 	3 0	; Screen
	5	[573]	SELF     	3 3 -2	; "getHeight"
	6	[573]	CALL     	3 2 2
	7	[574]	GETTABLE 	4 0 -3	; "_saved_screen_width"
	8	[574]	EQ       	0 2 4
	9	[574]	JMP      	6	; to 16
	10	[575]	GETTABLE 	4 0 -4	; "_saved_screen_height"
	11	[575]	EQ       	0 3 4
	12	[575]	JMP      	3	; to 16
	13	[575]	TEST     	1 0 1
	14	[575]	JMP      	1	; to 16
	15	[575]	RETURN   	0 1
	16	[577]	GETTABLE 	4 0 -5	; "settings"
	17	[577]	GETTABLE 	4 4 -6	; "disable_progress_bar"
	18	[577]	TEST     	4 0 0
	19	[577]	JMP      	3	; to 23
	20	[578]	GETTABLE 	4 0 -7	; "progress_bar"
	21	[578]	SETTABLE 	4 -8 -9	; "width" 0
	22	[578]	JMP      	25	; to 48
	23	[579]	GETTABLE 	4 0 -5	; "settings"
	24	[579]	GETTABLE 	4 4 -10	; "progress_bar_position"
	25	[579]	TEST     	4 0 0
	26	[579]	JMP      	10	; to 37
	27	[580]	GETTABLE 	4 0 -7	; "progress_bar"
	28	[580]	GETGLOBAL	5 -11	; math
	29	[580]	GETTABLE 	5 5 -12	; "floor"
	30	[580]	GETTABLE 	6 0 -5	; "settings"
	31	[580]	GETTABLE 	6 6 -13	; "progress_margin_width"
	32	[580]	MUL      	6 -14 6	; 2 -
	33	[580]	SUB      	6 2 6
	34	[580]	CALL     	5 2 2
	35	[580]	SETTABLE 	4 -8 5	; "width" -
	36	[580]	JMP      	11	; to 48
	37	[582]	GETTABLE 	4 0 -7	; "progress_bar"
	38	[582]	GETGLOBAL	5 -11	; math
	39	[582]	GETTABLE 	5 5 -12	; "floor"
	40	[583]	GETTABLE 	6 0 -15	; "text_width"
	41	[583]	SUB      	6 2 6
	42	[583]	GETTABLE 	7 0 -5	; "settings"
	43	[583]	GETTABLE 	7 7 -13	; "progress_margin_width"
	44	[583]	MUL      	7 7 -14	; - 2
	45	[583]	SUB      	6 6 7
	46	[582]	CALL     	5 2 2
	47	[583]	SETTABLE 	4 -8 5	; "width" -
	48	[585]	GETTABLE 	4 0 -16	; "separator_line"
	49	[585]	TEST     	4 0 0
	50	[585]	JMP      	6	; to 57
	51	[586]	GETTABLE 	4 0 -16	; "separator_line"
	52	[586]	GETTABLE 	4 4 -17	; "dimen"
	53	[586]	GETTABLE 	5 0 -19	; "horizontal_margin"
	54	[586]	MUL      	5 -14 5	; 2 -
	55	[586]	SUB      	5 2 5
	56	[586]	SETTABLE 	4 -18 5	; "w" -
	57	[588]	LOADNIL  	4 4
	58	[589]	GETTABLE 	5 0 -5	; "settings"
	59	[589]	GETTABLE 	5 5 -20	; "progress_style_thin"
	60	[589]	TEST     	5 0 0
	61	[589]	JMP      	6	; to 68
	62	[590]	GETTABLE 	5 0 -5	; "settings"
	63	[590]	GETTABLE 	5 5 -21	; "progress_style_thin_height"
	64	[590]	TESTSET  	4 5 1
	65	[590]	JMP      	1	; to 67
	66	[590]	GETUPVAL 	4 1	; PROGRESS_BAR_STYLE_THIN_DEFAULT_HEIGHT
	67	[590]	JMP      	5	; to 73
	68	[592]	GETTABLE 	5 0 -5	; "settings"
	69	[592]	GETTABLE 	5 5 -22	; "progress_style_thick_height"
	70	[592]	TESTSET  	4 5 1
	71	[592]	JMP      	1	; to 73
	72	[592]	GETUPVAL 	4 2	; PROGRESS_BAR_STYLE_THICK_DEFAULT_HEIGHT
	73	[594]	GETTABLE 	5 0 -7	; "progress_bar"
	74	[594]	GETUPVAL 	6 0	; Screen
	75	[594]	SELF     	6 6 -24	; "scaleBySize"
	76	[594]	MOVE     	8 4
	77	[594]	CALL     	6 3 2
	78	[594]	SETTABLE 	5 -23 6	; "height" -
	79	[596]	GETTABLE 	5 0 -25	; "horizontal_group"
	80	[596]	SELF     	5 5 -26	; "resetLayout"
	81	[596]	CALL     	5 2 1
	82	[597]	GETTABLE 	5 0 -27	; "footer_positioner"
	83	[597]	GETTABLE 	5 5 -17	; "dimen"
	84	[597]	SETTABLE 	5 -18 2	; "w" -
	85	[598]	GETTABLE 	5 0 -27	; "footer_positioner"
	86	[598]	GETTABLE 	5 5 -17	; "dimen"
	87	[598]	SETTABLE 	5 -28 3	; "h" -
	88	[599]	GETTABLE 	5 0 -29	; "footer_container"
	89	[599]	GETTABLE 	5 5 -17	; "dimen"
	90	[599]	SETTABLE 	5 -18 2	; "w" -
	91	[600]	GETTABLE 	5 0 -27	; "footer_positioner"
	92	[600]	SELF     	5 5 -30	; "getSize"
	93	[600]	CALL     	5 2 2
	94	[600]	SETTABLE 	0 -17 5	; "dimen" -
	95	[602]	SETTABLE 	0 -3 2	; "_saved_screen_width" -
	96	[603]	SETTABLE 	0 -4 3	; "_saved_screen_height" -
	97	[604]	RETURN   	0 1

function <./frontend/apps/reader/modules/readerfooter.lua:606,612> (12 instructions, 48 bytes at 0x7fd3a0c0f4c0)
1 param, 3 slots, 0 upvalues, 1 local, 4 constants, 0 functions
	1	[607]	GETTABLE 	1 0 -1	; "footer_content"
	2	[607]	TEST     	1 0 0
	3	[607]	JMP      	6	; to 10
	4	[608]	GETTABLE 	1 0 -1	; "footer_content"
	5	[608]	SELF     	1 1 -2	; "getSize"
	6	[608]	CALL     	1 2 2
	7	[608]	GETTABLE 	1 1 -3	; "h"
	8	[608]	RETURN   	1 2
	9	[608]	JMP      	2	; to 12
	10	[610]	LOADK    	1 -4	; 0
	11	[610]	RETURN   	1 2
	12	[612]	RETURN   	0 1

function <./frontend/apps/reader/modules/readerfooter.lua:614,624> (19 instructions, 76 bytes at 0x7fd3a0c0f9c0)
1 param, 2 slots, 0 upvalues, 1 local, 14 constants, 6 functions
	1	[615]	CLOSURE  	1 0	; 0x7fd3a0c0fe60
	2	[615]	SETTABLE 	0 -1 1	; "onReaderReady" -
	3	[616]	CLOSURE  	1 1	; 0x7fd3a0c0ff20
	4	[616]	SETTABLE 	0 -2 1	; "resetLayout" -
	5	[617]	SETTABLE 	0 -3 -4	; "onCloseDocument" nil
	6	[618]	CLOSURE  	1 2	; 0x7fd3a0c10170
	7	[618]	SETTABLE 	0 -5 1	; "updateFooterPage" -
	8	[619]	CLOSURE  	1 3	; 0x7fd3a0c10030
	9	[619]	SETTABLE 	0 -6 1	; "updateFooterPos" -
	10	[620]	CLOSURE  	1 4	; 0x7fd3a0c10570
	11	[620]	SETTABLE 	0 -7 1	; "onUpdatePos" -
	12	[621]	CLOSURE  	1 5	; 0x7fd3a0c106f0
	13	[621]	SETTABLE 	0 -8 1	; "onSetStatusLine" -
	14	[622]	GETTABLE 	1 0 -10	; "mode_list"
	15	[622]	GETTABLE 	1 1 -11	; "off"
	16	[622]	SETTABLE 	0 -9 1	; "mode" -
	17	[623]	GETTABLE 	1 0 -12	; "view"
	18	[623]	SETTABLE 	1 -13 -14	; "footer_visible" false
	19	[624]	RETURN   	0 1

function <./frontend/apps/reader/modules/readerfooter.lua:615,615> (1 instruction, 4 bytes at 0x7fd3a0c0fe60)
0 params, 2 slots, 0 upvalues, 0 locals, 0 constants, 0 functions
	1	[615]	RETURN   	0 1

function <./frontend/apps/reader/modules/readerfooter.lua:616,616> (1 instruction, 4 bytes at 0x7fd3a0c0ff20)
0 params, 2 slots, 0 upvalues, 0 locals, 0 constants, 0 functions
	1	[616]	RETURN   	0 1

function <./frontend/apps/reader/modules/readerfooter.lua:618,618> (1 instruction, 4 bytes at 0x7fd3a0c10170)
0 params, 2 slots, 0 upvalues, 0 locals, 0 constants, 0 functions
	1	[618]	RETURN   	0 1

function <./frontend/apps/reader/modules/readerfooter.lua:619,619> (1 instruction, 4 bytes at 0x7fd3a0c10030)
0 params, 2 slots, 0 upvalues, 0 locals, 0 constants, 0 functions
	1	[619]	RETURN   	0 1

function <./frontend/apps/reader/modules/readerfooter.lua:620,620> (1 instruction, 4 bytes at 0x7fd3a0c10570)
0 params, 2 slots, 0 upvalues, 0 locals, 0 constants, 0 functions
	1	[620]	RETURN   	0 1

function <./frontend/apps/reader/modules/readerfooter.lua:621,621> (1 instruction, 4 bytes at 0x7fd3a0c106f0)
0 params, 2 slots, 0 upvalues, 0 locals, 0 constants, 0 functions
	1	[621]	RETURN   	0 1

function <./frontend/apps/reader/modules/readerfooter.lua:626,652> (42 instructions, 168 bytes at 0x7fd3a0c10270)
1 param, 10 slots, 1 upvalue, 7 locals, 13 constants, 0 functions
	1	[627]	NEWTABLE 	1 0 0
	2	[628]	GETGLOBAL	2 -1	; pairs
	3	[628]	GETTABLE 	3 0 -2	; "mode_index"
	4	[628]	CALL     	2 2 4
	5	[628]	JMP      	16	; to 22
	6	[629]	GETTABLE 	7 0 -3	; "settings"
	7	[629]	GETTABLE 	7 7 6
	8	[629]	TEST     	7 0 0
	9	[629]	JMP      	12	; to 22
	10	[630]	GETGLOBAL	7 -4	; table
	11	[630]	GETTABLE 	7 7 -5	; "insert"
	12	[630]	MOVE     	8 1
	13	[631]	GETUPVAL 	9 0	; footerTextGeneratorMap
	14	[631]	GETTABLE 	9 9 6
	15	[630]	CALL     	7 3 1
	16	[632]	GETTABLE 	7 0 -3	; "settings"
	17	[632]	GETTABLE 	7 7 -6	; "all_at_once"
	18	[632]	TEST     	7 0 1
	19	[632]	JMP      	2	; to 22
	20	[634]	SETTABLE 	0 -7 5	; "mode" -
	21	[635]	JMP      	2	; to 24
	22	[628]	TFORLOOP 	2 2
	23	[637]	JMP      	-18	; to 6
	24	[639]	LEN      	2 1
	25	[639]	EQ       	0 2 -8	; - 0
	26	[639]	JMP      	4	; to 31
	27	[641]	GETUPVAL 	2 0	; footerTextGeneratorMap
	28	[641]	GETTABLE 	2 2 -10	; "empty"
	29	[641]	SETTABLE 	0 -9 2	; "genFooterText" -
	30	[641]	JMP      	9	; to 40
	31	[642]	LEN      	2 1
	32	[642]	EQ       	0 2 -11	; - 1
	33	[642]	JMP      	3	; to 37
	34	[645]	GETTABLE 	2 1 -11	; 1
	35	[645]	SETTABLE 	0 -9 2	; "genFooterText" -
	36	[645]	JMP      	3	; to 40
	37	[647]	SETTABLE 	0 -12 1	; "footerTextGenerators" -
	38	[648]	GETTABLE 	2 0 -13	; "genAllFooterText"
	39	[648]	SETTABLE 	0 -9 2	; "genFooterText" -
	40	[651]	LOADBOOL 	2 1 0
	41	[651]	RETURN   	2 2
	42	[652]	RETURN   	0 1

function <./frontend/apps/reader/modules/readerfooter.lua:654,665> (28 instructions, 112 bytes at 0x7fd3a0c109b0)
2 params, 9 slots, 1 upvalue, 5 locals, 10 constants, 0 functions
	1	[655]	GETTABLE 	2 0 -1	; "settings"
	2	[655]	GETTABLE 	2 2 -2	; "item_prefix"
	3	[655]	TEST     	2 0 1
	4	[655]	JMP      	1	; to 6
	5	[655]	LOADK    	2 -3	; "icons"
	6	[656]	GETUPVAL 	3 0	; symbol_prefix
	7	[656]	GETTABLE 	3 3 2
	8	[656]	GETTABLE 	3 3 -4	; "percentage"
	9	[658]	LOADNIL  	4 4
	10	[659]	TEST     	3 0 1
	11	[659]	JMP      	5	; to 17
	12	[660]	LOADK    	5 -5	; "%."
	13	[660]	MOVE     	6 1
	14	[660]	LOADK    	7 -6	; "f%%"
	15	[660]	CONCAT   	4 5 7
	16	[660]	JMP      	5	; to 22
	17	[662]	MOVE     	5 3
	18	[662]	LOADK    	6 -7	; " %."
	19	[662]	MOVE     	7 1
	20	[662]	LOADK    	8 -6	; "f%%"
	21	[662]	CONCAT   	4 5 8
	22	[664]	SELF     	5 4 -8	; "format"
	23	[664]	GETTABLE 	7 0 -9	; "progress_bar"
	24	[664]	GETTABLE 	7 7 -4	; "percentage"
	25	[664]	MUL      	7 7 -10	; - 100
	26	[664]	TAILCALL 	5 3 0
	27	[664]	RETURN   	5 0
	28	[665]	RETURN   	0 1

function <./frontend/apps/reader/modules/readerfooter.lua:667,688> (131 instructions, 524 bytes at 0x7fd3a0c10da0)
2 params, 7 slots, 3 upvalues, 4 locals, 34 constants, 0 functions
	1	[668]	GETTABLE 	2 0 -1	; "settings"
	2	[668]	GETTABLE 	2 2 -2	; "item_prefix"
	3	[668]	TEST     	2 0 1
	4	[668]	JMP      	1	; to 6
	5	[668]	LOADK    	2 -3	; "icons"
	6	[669]	NEWTABLE 	3 0 14
	7	[670]	GETUPVAL 	4 0	; _
	8	[670]	LOADK    	5 -5	; "Show all at once"
	9	[670]	CALL     	4 2 2
	10	[670]	SETTABLE 	3 -4 4	; "all_at_once" -
	11	[671]	GETUPVAL 	4 0	; _
	12	[671]	LOADK    	5 -7	; "Reclaim bar height from bottom margin"
	13	[671]	CALL     	4 2 2
	14	[671]	SETTABLE 	3 -6 4	; "reclaim_height" -
	15	[672]	GETUPVAL 	4 1	; T
	16	[672]	GETUPVAL 	5 0	; _
	17	[672]	LOADK    	6 -9	; "Current page (%1)"
	18	[672]	CALL     	5 2 2
	19	[672]	LOADK    	6 -10	; "/"
	20	[672]	CALL     	4 3 2
	21	[672]	SETTABLE 	3 -8 4	; "page_progress" -
	22	[673]	GETUPVAL 	4 2	; symbol_prefix
	23	[673]	GETTABLE 	4 4 2
	24	[674]	GETTABLE 	4 4 -11	; "time"
	25	[674]	TEST     	4 0 0
	26	[674]	JMP      	10	; to 37
	27	[674]	GETUPVAL 	4 1	; T
	28	[674]	GETUPVAL 	5 0	; _
	29	[674]	LOADK    	6 -12	; "Current time (%1)"
	30	[674]	CALL     	5 2 2
	31	[674]	GETUPVAL 	6 2	; symbol_prefix
	32	[674]	GETTABLE 	6 6 2
	33	[674]	GETTABLE 	6 6 -11	; "time"
	34	[674]	CALL     	4 3 2
	35	[674]	TEST     	4 0 1
	36	[674]	JMP      	3	; to 40
	37	[674]	GETUPVAL 	4 0	; _
	38	[674]	LOADK    	5 -13	; "Current time"
	39	[674]	CALL     	4 2 2
	40	[674]	SETTABLE 	3 -11 4	; "time" -
	41	[675]	GETUPVAL 	4 1	; T
	42	[675]	GETUPVAL 	5 0	; _
	43	[675]	LOADK    	6 -15	; "Pages left in chapter (%1)"
	44	[675]	CALL     	5 2 2
	45	[675]	GETUPVAL 	6 2	; symbol_prefix
	46	[675]	GETTABLE 	6 6 2
	47	[675]	GETTABLE 	6 6 -14	; "pages_left"
	48	[675]	CALL     	4 3 2
	49	[675]	SETTABLE 	3 -14 4	; "pages_left" -
	50	[676]	GETUPVAL 	4 1	; T
	51	[676]	GETUPVAL 	5 0	; _
	52	[676]	LOADK    	6 -17	; "Battery status (%1)"
	53	[676]	CALL     	5 2 2
	54	[676]	GETUPVAL 	6 2	; symbol_prefix
	55	[676]	GETTABLE 	6 6 2
	56	[676]	GETTABLE 	6 6 -16	; "battery"
	57	[676]	CALL     	4 3 2
	58	[676]	SETTABLE 	3 -16 4	; "battery" -
	59	[677]	GETUPVAL 	4 2	; symbol_prefix
	60	[677]	GETTABLE 	4 4 2
	61	[678]	GETTABLE 	4 4 -18	; "percentage"
	62	[678]	TEST     	4 0 0
	63	[678]	JMP      	10	; to 74
	64	[678]	GETUPVAL 	4 1	; T
	65	[678]	GETUPVAL 	5 0	; _
	66	[678]	LOADK    	6 -19	; "Progress percentage (%1)"
	67	[678]	CALL     	5 2 2
	68	[678]	GETUPVAL 	6 2	; symbol_prefix
	69	[678]	GETTABLE 	6 6 2
	70	[678]	GETTABLE 	6 6 -18	; "percentage"
	71	[678]	CALL     	4 3 2
	72	[678]	TEST     	4 0 1
	73	[678]	JMP      	1	; to 75
	74	[678]	LOADK    	4 -20	; "Progress percentage"
	75	[678]	SETTABLE 	3 -18 4	; "percentage" -
	76	[679]	GETUPVAL 	4 1	; T
	77	[679]	GETUPVAL 	5 0	; _
	78	[679]	LOADK    	6 -22	; "Book time to read (%1)"
	79	[679]	CALL     	5 2 2
	80	[679]	GETUPVAL 	6 2	; symbol_prefix
	81	[679]	GETTABLE 	6 6 2
	82	[679]	GETTABLE 	6 6 -21	; "book_time_to_read"
	83	[679]	CALL     	4 3 2
	84	[679]	SETTABLE 	3 -21 4	; "book_time_to_read" -
	85	[680]	GETUPVAL 	4 1	; T
	86	[680]	GETUPVAL 	5 0	; _
	87	[680]	LOADK    	6 -24	; "Chapter time to read (%1)"
	88	[680]	CALL     	5 2 2
	89	[680]	GETUPVAL 	6 2	; symbol_prefix
	90	[680]	GETTABLE 	6 6 2
	91	[680]	GETTABLE 	6 6 -23	; "chapter_time_to_read"
	92	[680]	CALL     	4 3 2
	93	[680]	SETTABLE 	3 -23 4	; "chapter_time_to_read" -
	94	[681]	GETUPVAL 	4 1	; T
	95	[681]	GETUPVAL 	5 0	; _
	96	[681]	LOADK    	6 -26	; "Frontlight level (%1)"
	97	[681]	CALL     	5 2 2
	98	[681]	GETUPVAL 	6 2	; symbol_prefix
	99	[681]	GETTABLE 	6 6 2
	100	[681]	GETTABLE 	6 6 -25	; "frontlight"
	101	[681]	CALL     	4 3 2
	102	[681]	SETTABLE 	3 -25 4	; "frontlight" -
	103	[682]	GETUPVAL 	4 1	; T
	104	[682]	GETUPVAL 	5 0	; _
	105	[682]	LOADK    	6 -28	; "KOReader memory usage (%1)"
	106	[682]	CALL     	5 2 2
	107	[682]	GETUPVAL 	6 2	; symbol_prefix
	108	[682]	GETTABLE 	6 6 2
	109	[682]	GETTABLE 	6 6 -27	; "mem_usage"
	110	[682]	CALL     	4 3 2
	111	[682]	SETTABLE 	3 -27 4	; "mem_usage" -
	112	[683]	GETUPVAL 	4 1	; T
	113	[683]	GETUPVAL 	5 0	; _
	114	[683]	LOADK    	6 -30	; "Wi-Fi status (%1)"
	115	[683]	CALL     	5 2 2
	116	[683]	GETUPVAL 	6 2	; symbol_prefix
	117	[683]	GETTABLE 	6 6 2
	118	[683]	GETTABLE 	6 6 -29	; "wifi_status"
	119	[683]	CALL     	4 3 2
	120	[683]	SETTABLE 	3 -29 4	; "wifi_status" -
	121	[684]	GETUPVAL 	4 0	; _
	122	[684]	LOADK    	5 -32	; "Book title"
	123	[684]	CALL     	4 2 2
	124	[684]	SETTABLE 	3 -31 4	; "book_title" -
	125	[685]	GETUPVAL 	4 0	; _
	126	[685]	LOADK    	5 -34	; "Current chapter"
	127	[685]	CALL     	4 2 2
	128	[685]	SETTABLE 	3 -33 4	; "book_chapter" -
	129	[687]	GETTABLE 	4 3 1
	130	[687]	RETURN   	4 2
	131	[688]	RETURN   	0 1

function <./frontend/apps/reader/modules/readerfooter.lua:690,1535> (770 instructions, 3080 bytes at 0x7fd3a0c11310)
2 params, 26 slots, 12 upvalues, 4 locals, 71 constants, 100 functions
	1	[691]	NEWTABLE 	2 0 0
	2	[692]	NEWTABLE 	3 0 2
	3	[693]	GETUPVAL 	4 0	; _
	4	[693]	LOADK    	5 -3	; "Status bar"
	5	[693]	CALL     	4 2 2
	6	[693]	SETTABLE 	3 -2 4	; "text" -
	7	[694]	SETTABLE 	3 -4 2	; "sub_item_table" -
	8	[695]	SETTABLE 	1 -1 3	; "status_bar" -
	9	[698]	GETUPVAL 	3 1	; Geom
	10	[698]	SELF     	3 3 -5	; "new"
	11	[698]	NEWTABLE 	5 0 4
	12	[699]	GETGLOBAL	6 -7	; DTAP_ZONE_MINIBAR
	13	[699]	GETTABLE 	6 6 -6	; "x"
	14	[699]	SETTABLE 	5 -6 6	; "x" -
	15	[700]	GETGLOBAL	6 -7	; DTAP_ZONE_MINIBAR
	16	[700]	GETTABLE 	6 6 -8	; "y"
	17	[700]	SETTABLE 	5 -8 6	; "y" -
	18	[701]	GETGLOBAL	6 -7	; DTAP_ZONE_MINIBAR
	19	[701]	GETTABLE 	6 6 -9	; "w"
	20	[701]	SETTABLE 	5 -9 6	; "w" -
	21	[702]	GETGLOBAL	6 -7	; DTAP_ZONE_MINIBAR
	22	[702]	GETTABLE 	6 6 -10	; "h"
	23	[702]	SETTABLE 	5 -10 6	; "h" -
	24	[698]	CALL     	3 3 2
	25	[703]	SELF     	3 3 -11	; "area"
	26	[703]	CALL     	3 2 2
	27	[703]	EQ       	0 3 -12	; - 0
	28	[703]	JMP      	15	; to 44
	29	[704]	GETGLOBAL	3 -13	; table
	30	[704]	GETTABLE 	3 3 -14	; "insert"
	31	[704]	MOVE     	4 2
	32	[704]	NEWTABLE 	5 0 3
	33	[705]	GETUPVAL 	6 0	; _
	34	[705]	LOADK    	7 -15	; "Toggle mode"
	35	[705]	CALL     	6 2 2
	36	[705]	SETTABLE 	5 -2 6	; "text" -
	37	[708]	CLOSURE  	6 0	; 0x7fd3a0c11740
	38	[708]	MOVE     	0 0
	39	[708]	SETTABLE 	5 -16 6	; "enabled_func" -
	40	[709]	CLOSURE  	6 1	; 0x7fd3a0c11a30
	41	[709]	MOVE     	0 0
	42	[709]	SETTABLE 	5 -17 6	; "callback" -
	43	[704]	CALL     	3 3 1
	44	[787]	CLOSURE  	3 2	; 0x7fd3a0c11fd0
	45	[787]	MOVE     	0 0
	46	[787]	GETUPVAL 	0 2	; footerTextGeneratorMap
	47	[788]	GETGLOBAL	4 -13	; table
	48	[788]	GETTABLE 	4 4 -14	; "insert"
	49	[788]	MOVE     	5 2
	50	[788]	NEWTABLE 	6 0 2
	51	[789]	GETUPVAL 	7 0	; _
	52	[789]	LOADK    	8 -18	; "Settings"
	53	[789]	CALL     	7 2 2
	54	[789]	SETTABLE 	6 -2 7	; "text" -
	55	[790]	NEWTABLE 	7 14 0
	56	[790]	NEWTABLE 	8 0 2
	57	[792]	GETUPVAL 	9 0	; _
	58	[792]	LOADK    	10 -19	; "Sort items"
	59	[792]	CALL     	9 2 2
	60	[792]	SETTABLE 	8 -2 9	; "text" -
	61	[815]	CLOSURE  	9 3	; 0x7fd3a0c12eb0
	62	[815]	MOVE     	0 0
	63	[815]	GETUPVAL 	0 0	; _
	64	[815]	GETUPVAL 	0 3	; UIManager
	65	[815]	SETTABLE 	8 -17 9	; "callback" -
	66	[817]	MOVE     	9 3
	67	[817]	LOADK    	10 -20	; "all_at_once"
	68	[817]	GETTABLE 	11 0 -21	; "updateFooterTextGenerator"
	69	[817]	CALL     	9 3 2
	70	[818]	MOVE     	10 3
	71	[818]	LOADK    	11 -22	; "reclaim_height"
	72	[818]	CALL     	10 2 2
	73	[818]	NEWTABLE 	11 0 4
	74	[820]	GETUPVAL 	12 0	; _
	75	[820]	LOADK    	13 -23	; "Auto refresh time"
	76	[820]	CALL     	12 2 2
	77	[820]	SETTABLE 	11 -2 12	; "text" -
	78	[823]	CLOSURE  	12 4	; 0x7fd3a0c13410
	79	[823]	MOVE     	0 0
	80	[823]	SETTABLE 	11 -24 12	; "checked_func" -
	81	[825]	CLOSURE  	12 5	; 0x7fd3a0c13a30
	82	[825]	MOVE     	0 0
	83	[825]	SETTABLE 	11 -16 12	; "enabled_func" -
	84	[835]	CLOSURE  	12 6	; 0x7fd3a0c119b0
	85	[835]	MOVE     	0 0
	86	[835]	GETUPVAL 	0 3	; UIManager
	87	[835]	SETTABLE 	11 -17 12	; "callback" -
	88	[836]	NEWTABLE 	12 0 3
	89	[838]	GETUPVAL 	13 0	; _
	90	[838]	LOADK    	14 -25	; "Show footer separator"
	91	[838]	CALL     	13 2 2
	92	[838]	SETTABLE 	12 -2 13	; "text" -
	93	[841]	CLOSURE  	13 7	; 0x7fd3a0c143b0
	94	[841]	MOVE     	0 0
	95	[841]	SETTABLE 	12 -24 13	; "checked_func" -
	96	[845]	CLOSURE  	13 8	; 0x7fd3a0c14310
	97	[845]	MOVE     	0 0
	98	[845]	SETTABLE 	12 -17 13	; "callback" -
	99	[846]	NEWTABLE 	13 0 3
	100	[848]	GETUPVAL 	14 0	; _
	101	[848]	LOADK    	15 -26	; "Lock status bar"
	102	[848]	CALL     	14 2 2
	103	[848]	SETTABLE 	13 -2 14	; "text" -
	104	[851]	CLOSURE  	14 9	; 0x7fd3a0c14990
	105	[851]	MOVE     	0 0
	106	[851]	SETTABLE 	13 -24 14	; "checked_func" -
	107	[854]	CLOSURE  	14 10	; 0x7fd3a0c14a60
	108	[854]	MOVE     	0 0
	109	[854]	SETTABLE 	13 -17 14	; "callback" -
	110	[855]	NEWTABLE 	14 0 3
	111	[857]	GETUPVAL 	15 0	; _
	112	[857]	LOADK    	16 -27	; "Font"
	113	[857]	CALL     	15 2 2
	114	[857]	SETTABLE 	14 -2 15	; "text" -
	115	[858]	SETTABLE 	14 -28 -29	; "separator" true
	116	[859]	NEWTABLE 	15 2 0
	117	[859]	NEWTABLE 	16 0 3
	118	[863]	CLOSURE  	17 11	; 0x7fd3a0c14d50
	119	[863]	GETUPVAL 	0 4	; T
	120	[863]	GETUPVAL 	0 0	; _
	121	[863]	MOVE     	0 0
	122	[863]	SETTABLE 	16 -30 17	; "text_func" -
	123	[890]	CLOSURE  	17 12	; 0x7fd3a0c15230
	124	[890]	MOVE     	0 0
	125	[890]	GETUPVAL 	0 5	; Screen
	126	[890]	GETUPVAL 	0 0	; _
	127	[890]	GETUPVAL 	0 6	; TextWidget
	128	[890]	GETUPVAL 	0 7	; Font
	129	[890]	GETUPVAL 	0 3	; UIManager
	130	[890]	SETTABLE 	16 -17 17	; "callback" -
	131	[891]	SETTABLE 	16 -31 -29	; "keep_menu_open" true
	132	[892]	NEWTABLE 	17 0 4
	133	[894]	GETUPVAL 	18 0	; _
	134	[894]	LOADK    	19 -32	; "Use bold font"
	135	[894]	CALL     	18 2 2
	136	[894]	SETTABLE 	17 -2 18	; "text" -
	137	[897]	CLOSURE  	18 13	; 0x7fd3a0c156c0
	138	[897]	MOVE     	0 0
	139	[897]	SETTABLE 	17 -24 18	; "checked_func" -
	140	[909]	CLOSURE  	18 14	; 0x7fd3a0c13cb0
	141	[909]	MOVE     	0 0
	142	[909]	GETUPVAL 	0 6	; TextWidget
	143	[909]	GETUPVAL 	0 7	; Font
	144	[909]	SETTABLE 	17 -17 18	; "callback" -
	145	[910]	SETTABLE 	17 -31 -29	; "keep_menu_open" true
	146	[912]	SETLIST  	15 2 1	; 1
	147	[912]	SETTABLE 	14 -4 15	; "sub_item_table" -
	148	[913]	NEWTABLE 	15 0 2
	149	[915]	GETUPVAL 	16 0	; _
	150	[915]	LOADK    	17 -33	; "Maximum width of items"
	151	[915]	CALL     	16 2 2
	152	[915]	SETTABLE 	15 -2 16	; "text" -
	153	[916]	NEWTABLE 	16 2 0
	154	[916]	NEWTABLE 	17 0 3
	155	[920]	CLOSURE  	18 15	; 0x7fd3a0c13da0
	156	[920]	GETUPVAL 	0 4	; T
	157	[920]	GETUPVAL 	0 0	; _
	158	[920]	MOVE     	0 0
	159	[920]	SETTABLE 	17 -30 18	; "text_func" -
	160	[940]	CLOSURE  	18 16	; 0x7fd3a0c11dd0
	161	[940]	GETUPVAL 	0 5	; Screen
	162	[940]	MOVE     	0 0
	163	[940]	GETUPVAL 	0 0	; _
	164	[940]	GETUPVAL 	0 3	; UIManager
	165	[940]	SETTABLE 	17 -17 18	; "callback" -
	166	[941]	SETTABLE 	17 -31 -29	; "keep_menu_open" true
	167	[942]	NEWTABLE 	18 0 3
	168	[946]	CLOSURE  	19 17	; 0x7fd3a0c147b0
	169	[946]	GETUPVAL 	0 4	; T
	170	[946]	GETUPVAL 	0 0	; _
	171	[946]	MOVE     	0 0
	172	[946]	SETTABLE 	18 -30 19	; "text_func" -
	173	[966]	CLOSURE  	19 18	; 0x7fd3a0c0ecf0
	174	[966]	GETUPVAL 	0 5	; Screen
	175	[966]	MOVE     	0 0
	176	[966]	GETUPVAL 	0 0	; _
	177	[966]	GETUPVAL 	0 3	; UIManager
	178	[966]	SETTABLE 	18 -17 19	; "callback" -
	179	[967]	SETTABLE 	18 -31 -29	; "keep_menu_open" true
	180	[969]	SETLIST  	16 2 1	; 1
	181	[969]	SETTABLE 	15 -4 16	; "sub_item_table" -
	182	[970]	NEWTABLE 	16 0 3
	183	[972]	GETUPVAL 	17 0	; _
	184	[972]	LOADK    	18 -34	; "Alignment"
	185	[972]	CALL     	17 2 2
	186	[972]	SETTABLE 	16 -2 17	; "text" -
	187	[975]	CLOSURE  	17 19	; 0x7fd3a0c150f0
	188	[975]	MOVE     	0 0
	189	[975]	SETTABLE 	16 -16 17	; "enabled_func" -
	190	[976]	NEWTABLE 	17 3 0
	191	[976]	NEWTABLE 	18 0 3
	192	[978]	GETUPVAL 	19 0	; _
	193	[978]	LOADK    	20 -35	; "Center"
	194	[978]	CALL     	19 2 2
	195	[978]	SETTABLE 	18 -2 19	; "text" -
	196	[981]	CLOSURE  	19 20	; 0x7fd3a0c11bc0
	197	[981]	MOVE     	0 0
	198	[981]	SETTABLE 	18 -24 19	; "checked_func" -
	199	[985]	CLOSURE  	19 21	; 0x7fd3a0c16660
	200	[985]	MOVE     	0 0
	201	[985]	SETTABLE 	18 -17 19	; "callback" -
	202	[986]	NEWTABLE 	19 0 3
	203	[988]	GETUPVAL 	20 0	; _
	204	[988]	LOADK    	21 -36	; "Left"
	205	[988]	CALL     	20 2 2
	206	[988]	SETTABLE 	19 -2 20	; "text" -
	207	[991]	CLOSURE  	20 22	; 0x7fd3a0c0e030
	208	[991]	MOVE     	0 0
	209	[991]	SETTABLE 	19 -24 20	; "checked_func" -
	210	[995]	CLOSURE  	20 23	; 0x7fd3a0c0e0b0
	211	[995]	MOVE     	0 0
	212	[995]	SETTABLE 	19 -17 20	; "callback" -
	213	[996]	NEWTABLE 	20 0 3
	214	[998]	GETUPVAL 	21 0	; _
	215	[998]	LOADK    	22 -37	; "Right"
	216	[998]	CALL     	21 2 2
	217	[998]	SETTABLE 	20 -2 21	; "text" -
	218	[1001]	CLOSURE  	21 24	; 0x7fd3a0c14b60
	219	[1001]	MOVE     	0 0
	220	[1001]	SETTABLE 	20 -24 21	; "checked_func" -
	221	[1005]	CLOSURE  	21 25	; 0x7fd3a0c14be0
	222	[1005]	MOVE     	0 0
	223	[1005]	SETTABLE 	20 -17 21	; "callback" -
	224	[1007]	SETLIST  	17 3 1	; 1
	225	[1007]	SETTABLE 	16 -4 17	; "sub_item_table" -
	226	[1008]	NEWTABLE 	17 0 2
	227	[1010]	GETUPVAL 	18 0	; _
	228	[1010]	LOADK    	19 -38	; "Prefix"
	229	[1010]	CALL     	18 2 2
	230	[1010]	SETTABLE 	17 -2 18	; "text" -
	231	[1011]	NEWTABLE 	18 2 0
	232	[1011]	NEWTABLE 	19 0 3
	233	[1019]	CLOSURE  	20 26	; 0x7fd3a0c12460
	234	[1019]	GETUPVAL 	0 8	; symbol_prefix
	235	[1019]	GETUPVAL 	0 4	; T
	236	[1019]	GETUPVAL 	0 0	; _
	237	[1019]	SETTABLE 	19 -30 20	; "text_func" -
	238	[1022]	CLOSURE  	20 27	; 0x7fd3a0c16f50
	239	[1022]	MOVE     	0 0
	240	[1022]	SETTABLE 	19 -24 20	; "checked_func" -
	241	[1027]	CLOSURE  	20 28	; 0x7fd3a0c17010
	242	[1027]	MOVE     	0 0
	243	[1027]	GETUPVAL 	0 3	; UIManager
	244	[1027]	SETTABLE 	19 -17 20	; "callback" -
	245	[1028]	NEWTABLE 	20 0 3
	246	[1036]	CLOSURE  	21 29	; 0x7fd3a0c170d0
	247	[1036]	GETUPVAL 	0 8	; symbol_prefix
	248	[1036]	GETUPVAL 	0 4	; T
	249	[1036]	GETUPVAL 	0 0	; _
	250	[1036]	SETTABLE 	20 -30 21	; "text_func" -
	251	[1039]	CLOSURE  	21 30	; 0x7fd3a0c17ac0
	252	[1039]	MOVE     	0 0
	253	[1039]	SETTABLE 	20 -24 21	; "checked_func" -
	254	[1044]	CLOSURE  	21 31	; 0x7fd3a0c17b80
	255	[1044]	MOVE     	0 0
	256	[1044]	GETUPVAL 	0 3	; UIManager
	257	[1044]	SETTABLE 	20 -17 21	; "callback" -
	258	[1046]	SETLIST  	18 2 1	; 1
	259	[1046]	SETTABLE 	17 -4 18	; "sub_item_table" -
	260	[1047]	NEWTABLE 	18 0 2
	261	[1049]	GETUPVAL 	19 0	; _
	262	[1049]	LOADK    	20 -39	; "Item separator"
	263	[1049]	CALL     	19 2 2
	264	[1049]	SETTABLE 	18 -2 19	; "text" -
	265	[1050]	NEWTABLE 	19 3 0
	266	[1050]	NEWTABLE 	20 0 3
	267	[1052]	GETUPVAL 	21 0	; _
	268	[1052]	LOADK    	22 -40	; "Vertical line (|)"
	269	[1052]	CALL     	21 2 2
	270	[1052]	SETTABLE 	20 -2 21	; "text" -
	271	[1055]	CLOSURE  	21 32	; 0x7fd3a0c17f50
	272	[1055]	MOVE     	0 0
	273	[1055]	SETTABLE 	20 -24 21	; "checked_func" -
	274	[1060]	CLOSURE  	21 33	; 0x7fd3a0c12760
	275	[1060]	MOVE     	0 0
	276	[1060]	GETUPVAL 	0 3	; UIManager
	277	[1060]	SETTABLE 	20 -17 21	; "callback" -
	278	[1061]	NEWTABLE 	21 0 3
	279	[1063]	GETUPVAL 	22 0	; _
	280	[1063]	LOADK    	23 -41	; "Bullet (\226\128\162)"
	281	[1063]	CALL     	22 2 2
	282	[1063]	SETTABLE 	21 -2 22	; "text" -
	283	[1066]	CLOSURE  	22 34	; 0x7fd3a0c184e0
	284	[1066]	MOVE     	0 0
	285	[1066]	SETTABLE 	21 -24 22	; "checked_func" -
	286	[1071]	CLOSURE  	22 35	; 0x7fd3a0c18da0
	287	[1071]	MOVE     	0 0
	288	[1071]	GETUPVAL 	0 3	; UIManager
	289	[1071]	SETTABLE 	21 -17 22	; "callback" -
	290	[1072]	NEWTABLE 	22 0 3
	291	[1074]	GETUPVAL 	23 0	; _
	292	[1074]	LOADK    	24 -42	; "No separator"
	293	[1074]	CALL     	23 2 2
	294	[1074]	SETTABLE 	22 -2 23	; "text" -
	295	[1077]	CLOSURE  	23 36	; 0x7fd3a0c190f0
	296	[1077]	MOVE     	0 0
	297	[1077]	SETTABLE 	22 -24 23	; "checked_func" -
	298	[1082]	CLOSURE  	23 37	; 0x7fd3a0c19700
	299	[1082]	MOVE     	0 0
	300	[1082]	GETUPVAL 	0 3	; UIManager
	301	[1082]	SETTABLE 	22 -17 23	; "callback" -
	302	[1084]	SETLIST  	19 3 1	; 1
	303	[1084]	SETTABLE 	18 -4 19	; "sub_item_table" -
	304	[1085]	NEWTABLE 	19 0 2
	305	[1087]	GETUPVAL 	20 0	; _
	306	[1087]	LOADK    	21 -43	; "Progress percentage format"
	307	[1087]	CALL     	20 2 2
	308	[1087]	SETTABLE 	19 -2 20	; "text" -
	309	[1088]	NEWTABLE 	20 3 0
	310	[1088]	NEWTABLE 	21 0 3
	311	[1092]	CLOSURE  	22 38	; 0x7fd3a0c198d0
	312	[1092]	GETUPVAL 	0 4	; T
	313	[1092]	GETUPVAL 	0 0	; _
	314	[1092]	MOVE     	0 0
	315	[1092]	SETTABLE 	21 -30 22	; "text_func" -
	316	[1095]	CLOSURE  	22 39	; 0x7fd3a0c19e90
	317	[1095]	MOVE     	0 0
	318	[1095]	SETTABLE 	21 -24 22	; "checked_func" -
	319	[1100]	CLOSURE  	22 40	; 0x7fd3a0c19f90
	320	[1100]	MOVE     	0 0
	321	[1100]	GETUPVAL 	0 3	; UIManager
	322	[1100]	SETTABLE 	21 -17 22	; "callback" -
	323	[1101]	NEWTABLE 	22 0 3
	324	[1105]	CLOSURE  	23 41	; 0x7fd3a0c1a430
	325	[1105]	GETUPVAL 	0 4	; T
	326	[1105]	GETUPVAL 	0 0	; _
	327	[1105]	MOVE     	0 0
	328	[1105]	SETTABLE 	22 -30 23	; "text_func" -
	329	[1108]	CLOSURE  	23 42	; 0x7fd3a0c1a590
	330	[1108]	MOVE     	0 0
	331	[1108]	SETTABLE 	22 -24 23	; "checked_func" -
	332	[1113]	CLOSURE  	23 43	; 0x7fd3a0c1ad30
	333	[1113]	MOVE     	0 0
	334	[1113]	GETUPVAL 	0 3	; UIManager
	335	[1113]	SETTABLE 	22 -17 23	; "callback" -
	336	[1114]	NEWTABLE 	23 0 3
	337	[1118]	CLOSURE  	24 44	; 0x7fd3a0c1aeb0
	338	[1118]	GETUPVAL 	0 4	; T
	339	[1118]	GETUPVAL 	0 0	; _
	340	[1118]	MOVE     	0 0
	341	[1118]	SETTABLE 	23 -30 24	; "text_func" -
	342	[1121]	CLOSURE  	24 45	; 0x7fd3a0c1b2d0
	343	[1121]	MOVE     	0 0
	344	[1121]	SETTABLE 	23 -24 24	; "checked_func" -
	345	[1126]	CLOSURE  	24 46	; 0x7fd3a0c1b5d0
	346	[1126]	MOVE     	0 0
	347	[1126]	GETUPVAL 	0 3	; UIManager
	348	[1126]	SETTABLE 	23 -17 24	; "callback" -
	349	[1128]	SETLIST  	20 3 1	; 1
	350	[1128]	SETTABLE 	19 -4 20	; "sub_item_table" -
	351	[1129]	NEWTABLE 	20 0 2
	352	[1131]	GETUPVAL 	21 0	; _
	353	[1131]	LOADK    	22 -44	; "Time format"
	354	[1131]	CALL     	21 2 2
	355	[1131]	SETTABLE 	20 -2 21	; "text" -
	356	[1132]	NEWTABLE 	21 2 0
	357	[1132]	NEWTABLE 	22 0 3
	358	[1140]	CLOSURE  	23 47	; 0x7fd3a0c1b980
	359	[1140]	MOVE     	0 0
	360	[1140]	GETUPVAL 	0 4	; T
	361	[1140]	GETUPVAL 	0 0	; _
	362	[1140]	GETUPVAL 	0 2	; footerTextGeneratorMap
	363	[1140]	SETTABLE 	22 -30 23	; "text_func" -
	364	[1143]	CLOSURE  	23 48	; 0x7fd3a0c1c220
	365	[1143]	MOVE     	0 0
	366	[1143]	SETTABLE 	22 -24 23	; "checked_func" -
	367	[1148]	CLOSURE  	23 49	; 0x7fd3a0c1c2e0
	368	[1148]	MOVE     	0 0
	369	[1148]	GETUPVAL 	0 3	; UIManager
	370	[1148]	SETTABLE 	22 -17 23	; "callback" -
	371	[1149]	NEWTABLE 	23 0 3
	372	[1157]	CLOSURE  	24 50	; 0x7fd3a0c1c750
	373	[1157]	MOVE     	0 0
	374	[1157]	GETUPVAL 	0 4	; T
	375	[1157]	GETUPVAL 	0 0	; _
	376	[1157]	GETUPVAL 	0 2	; footerTextGeneratorMap
	377	[1157]	SETTABLE 	23 -30 24	; "text_func" -
	378	[1160]	CLOSURE  	24 51	; 0x7fd3a0c1d010
	379	[1160]	MOVE     	0 0
	380	[1160]	SETTABLE 	23 -24 24	; "checked_func" -
	381	[1165]	CLOSURE  	24 52	; 0x7fd3a0c1d270
	382	[1165]	MOVE     	0 0
	383	[1165]	GETUPVAL 	0 3	; UIManager
	384	[1165]	SETTABLE 	23 -17 24	; "callback" -
	385	[1167]	SETLIST  	21 2 1	; 1
	386	[1167]	SETTABLE 	20 -4 21	; "sub_item_table" -
	387	[1168]	NEWTABLE 	21 0 2
	388	[1170]	GETUPVAL 	22 0	; _
	389	[1170]	LOADK    	23 -45	; "Duration format"
	390	[1170]	CALL     	22 2 2
	391	[1170]	SETTABLE 	21 -2 22	; "text" -
	392	[1171]	NEWTABLE 	22 2 0
	393	[1171]	NEWTABLE 	23 0 3
	394	[1180]	CLOSURE  	24 53	; 0x7fd3a0c1d400
	395	[1180]	MOVE     	0 0
	396	[1180]	GETUPVAL 	0 2	; footerTextGeneratorMap
	397	[1180]	GETUPVAL 	0 4	; T
	398	[1180]	GETUPVAL 	0 0	; _
	399	[1180]	SETTABLE 	23 -30 24	; "text_func" -
	400	[1183]	CLOSURE  	24 54	; 0x7fd3a0c1dcd0
	401	[1183]	MOVE     	0 0
	402	[1183]	SETTABLE 	23 -24 24	; "checked_func" -
	403	[1188]	CLOSURE  	24 55	; 0x7fd3a0c1dd90
	404	[1188]	MOVE     	0 0
	405	[1188]	GETUPVAL 	0 3	; UIManager
	406	[1188]	SETTABLE 	23 -17 24	; "callback" -
	407	[1189]	NEWTABLE 	24 0 3
	408	[1198]	CLOSURE  	25 56	; 0x7fd3a0c1e280
	409	[1198]	MOVE     	0 0
	410	[1198]	GETUPVAL 	0 2	; footerTextGeneratorMap
	411	[1198]	GETUPVAL 	0 4	; T
	412	[1198]	GETUPVAL 	0 0	; _
	413	[1198]	SETTABLE 	24 -30 25	; "text_func" -
	414	[1201]	CLOSURE  	25 57	; 0x7fd3a0c1e6a0
	415	[1201]	MOVE     	0 0
	416	[1201]	SETTABLE 	24 -24 25	; "checked_func" -
	417	[1206]	CLOSURE  	25 58	; 0x7fd3a0c1edb0
	418	[1206]	MOVE     	0 0
	419	[1206]	GETUPVAL 	0 3	; UIManager
	420	[1206]	SETTABLE 	24 -17 25	; "callback" -
	421	[1208]	SETLIST  	22 2 1	; 1
	422	[1208]	SETTABLE 	21 -4 22	; "sub_item_table" -
	423	[1210]	SETLIST  	7 14 1	; 1
	424	[1210]	SETTABLE 	6 -4 7	; "sub_item_table" -
	425	[788]	CALL     	4 3 1
	426	[1212]	GETGLOBAL	4 -13	; table
	427	[1212]	GETTABLE 	4 4 -14	; "insert"
	428	[1212]	MOVE     	5 2
	429	[1212]	NEWTABLE 	6 0 3
	430	[1213]	GETUPVAL 	7 0	; _
	431	[1213]	LOADK    	8 -46	; "Progress bar"
	432	[1213]	CALL     	7 2 2
	433	[1213]	SETTABLE 	6 -2 7	; "text" -
	434	[1214]	SETTABLE 	6 -28 -29	; "separator" true
	435	[1215]	NEWTABLE 	7 5 0
	436	[1215]	NEWTABLE 	8 0 3
	437	[1217]	GETUPVAL 	9 0	; _
	438	[1217]	LOADK    	10 -47	; "Show progress bar"
	439	[1217]	CALL     	9 2 2
	440	[1217]	SETTABLE 	8 -2 9	; "text" -
	441	[1220]	CLOSURE  	9 59	; 0x7fd3a0c1efa0
	442	[1220]	MOVE     	0 0
	443	[1220]	SETTABLE 	8 -24 9	; "checked_func" -
	444	[1231]	CLOSURE  	9 60	; 0x7fd3a0c1f340
	445	[1231]	MOVE     	0 0
	446	[1231]	SETTABLE 	8 -17 9	; "callback" -
	447	[1232]	NEWTABLE 	9 0 3
	448	[1242]	CLOSURE  	10 61	; 0x7fd3a0c1f590
	449	[1242]	GETUPVAL 	0 0	; _
	450	[1242]	MOVE     	0 0
	451	[1242]	GETUPVAL 	0 4	; T
	452	[1242]	SETTABLE 	9 -30 10	; "text_func" -
	453	[1245]	CLOSURE  	10 62	; 0x7fd3a0c1fc70
	454	[1245]	MOVE     	0 0
	455	[1245]	SETTABLE 	9 -16 10	; "enabled_func" -
	456	[1246]	NEWTABLE 	10 3 0
	457	[1246]	NEWTABLE 	11 0 3
	458	[1248]	GETUPVAL 	12 0	; _
	459	[1248]	LOADK    	13 -48	; "Above items"
	460	[1248]	CALL     	12 2 2
	461	[1248]	SETTABLE 	11 -2 12	; "text" -
	462	[1251]	CLOSURE  	12 63	; 0x7fd3a0c1fe70
	463	[1251]	MOVE     	0 0
	464	[1251]	SETTABLE 	11 -24 12	; "checked_func" -
	465	[1255]	CLOSURE  	12 64	; 0x7fd3a0c20250
	466	[1255]	MOVE     	0 0
	467	[1255]	SETTABLE 	11 -17 12	; "callback" -
	468	[1256]	NEWTABLE 	12 0 3
	469	[1258]	GETUPVAL 	13 0	; _
	470	[1258]	LOADK    	14 -49	; "Below items"
	471	[1258]	CALL     	13 2 2
	472	[1258]	SETTABLE 	12 -2 13	; "text" -
	473	[1261]	CLOSURE  	13 65	; 0x7fd3a0c187e0
	474	[1261]	MOVE     	0 0
	475	[1261]	SETTABLE 	12 -24 13	; "checked_func" -
	476	[1265]	CLOSURE  	13 66	; 0x7fd3a0c188e0
	477	[1265]	MOVE     	0 0
	478	[1265]	SETTABLE 	12 -17 13	; "callback" -
	479	[1266]	NEWTABLE 	13 0 3
	480	[1268]	GETUPVAL 	14 0	; _
	481	[1268]	LOADK    	15 -50	; "Alongside items"
	482	[1268]	CALL     	14 2 2
	483	[1268]	SETTABLE 	13 -2 14	; "text" -
	484	[1271]	CLOSURE  	14 67	; 0x7fd3a0c20960
	485	[1271]	MOVE     	0 0
	486	[1271]	SETTABLE 	13 -24 14	; "checked_func" -
	487	[1279]	CLOSURE  	14 68	; 0x7fd3a0c209e0
	488	[1279]	MOVE     	0 0
	489	[1279]	GETUPVAL 	0 5	; Screen
	490	[1279]	SETTABLE 	13 -17 14	; "callback" -
	491	[1281]	SETLIST  	10 3 1	; 1
	492	[1281]	SETTABLE 	9 -4 10	; "sub_item_table" -
	493	[1282]	NEWTABLE 	10 0 3
	494	[1290]	CLOSURE  	11 69	; 0x7fd3a0c20d40
	495	[1290]	MOVE     	0 0
	496	[1290]	GETUPVAL 	0 0	; _
	497	[1290]	SETTABLE 	10 -30 11	; "text_func" -
	498	[1293]	CLOSURE  	11 70	; 0x7fd3a0c20e80
	499	[1293]	MOVE     	0 0
	500	[1293]	SETTABLE 	10 -16 11	; "enabled_func" -
	501	[1294]	NEWTABLE 	11 5 0
	502	[1294]	NEWTABLE 	12 0 3
	503	[1296]	GETUPVAL 	13 0	; _
	504	[1296]	LOADK    	14 -51	; "Thick"
	505	[1296]	CALL     	13 2 2
	506	[1296]	SETTABLE 	12 -2 13	; "text" -
	507	[1299]	CLOSURE  	13 71	; 0x7fd3a0c20fd0
	508	[1299]	MOVE     	0 0
	509	[1299]	SETTABLE 	12 -24 13	; "checked_func" -
	510	[1306]	CLOSURE  	13 72	; 0x7fd3a0c21680
	511	[1306]	MOVE     	0 0
	512	[1306]	GETUPVAL 	0 9	; PROGRESS_BAR_STYLE_THICK_DEFAULT_HEIGHT
	513	[1306]	SETTABLE 	12 -17 13	; "callback" -
	514	[1307]	NEWTABLE 	13 0 3
	515	[1309]	GETUPVAL 	14 0	; _
	516	[1309]	LOADK    	15 -52	; "Thin"
	517	[1309]	CALL     	14 2 2
	518	[1309]	SETTABLE 	13 -2 14	; "text" -
	519	[1312]	CLOSURE  	14 73	; 0x7fd3a0c21ae0
	520	[1312]	MOVE     	0 0
	521	[1312]	SETTABLE 	13 -24 14	; "checked_func" -
	522	[1318]	CLOSURE  	14 74	; 0x7fd3a0c21e20
	523	[1318]	MOVE     	0 0
	524	[1318]	GETUPVAL 	0 10	; PROGRESS_BAR_STYLE_THIN_DEFAULT_HEIGHT
	525	[1318]	SETTABLE 	13 -17 14	; "callback" -
	526	[1319]	NEWTABLE 	14 0 4
	527	[1321]	GETUPVAL 	15 0	; _
	528	[1321]	LOADK    	16 -53	; "Set size"
	529	[1321]	CALL     	15 2 2
	530	[1321]	SETTABLE 	14 -2 15	; "text" -
	531	[1356]	CLOSURE  	15 75	; 0x7fd3a0c22590
	532	[1356]	MOVE     	0 0
	533	[1356]	GETUPVAL 	0 10	; PROGRESS_BAR_STYLE_THIN_DEFAULT_HEIGHT
	534	[1356]	GETUPVAL 	0 9	; PROGRESS_BAR_STYLE_THICK_DEFAULT_HEIGHT
	535	[1356]	GETUPVAL 	0 5	; Screen
	536	[1356]	GETUPVAL 	0 0	; _
	537	[1356]	GETUPVAL 	0 3	; UIManager
	538	[1356]	SETTABLE 	14 -17 15	; "callback" -
	539	[1357]	SETTABLE 	14 -28 -29	; "separator" true
	540	[1358]	SETTABLE 	14 -31 -29	; "keep_menu_open" true
	541	[1359]	NEWTABLE 	15 0 4
	542	[1361]	GETUPVAL 	16 0	; _
	543	[1361]	LOADK    	17 -54	; "Show chapter markers"
	544	[1361]	CALL     	16 2 2
	545	[1361]	SETTABLE 	15 -2 16	; "text" -
	546	[1364]	CLOSURE  	16 76	; 0x7fd3a0c22df0
	547	[1364]	MOVE     	0 0
	548	[1364]	SETTABLE 	15 -24 16	; "checked_func" -
	549	[1367]	CLOSURE  	16 77	; 0x7fd3a0c23110
	550	[1367]	MOVE     	0 0
	551	[1367]	SETTABLE 	15 -16 16	; "enabled_func" -
	552	[1372]	CLOSURE  	16 78	; 0x7fd3a0c23360
	553	[1372]	MOVE     	0 0
	554	[1372]	SETTABLE 	15 -17 16	; "callback" -
	555	[1373]	NEWTABLE 	16 0 3
	556	[1383]	CLOSURE  	17 79	; 0x7fd3a0c23860
	557	[1383]	GETUPVAL 	0 0	; _
	558	[1383]	MOVE     	0 0
	559	[1383]	GETUPVAL 	0 4	; T
	560	[1383]	SETTABLE 	16 -30 17	; "text_func" -
	561	[1386]	CLOSURE  	17 80	; 0x7fd3a0c23b70
	562	[1386]	MOVE     	0 0
	563	[1386]	SETTABLE 	16 -16 17	; "enabled_func" -
	564	[1387]	NEWTABLE 	17 3 0
	565	[1387]	NEWTABLE 	18 0 3
	566	[1389]	GETUPVAL 	19 0	; _
	567	[1389]	LOADK    	20 -52	; "Thin"
	568	[1389]	CALL     	19 2 2
	569	[1389]	SETTABLE 	18 -2 19	; "text" -
	570	[1392]	CLOSURE  	19 81	; 0x7fd3a0c23d60
	571	[1392]	MOVE     	0 0
	572	[1392]	SETTABLE 	18 -24 19	; "checked_func" -
	573	[1397]	CLOSURE  	19 82	; 0x7fd3a0c24410
	574	[1397]	MOVE     	0 0
	575	[1397]	SETTABLE 	18 -17 19	; "callback" -
	576	[1398]	NEWTABLE 	19 0 3
	577	[1400]	GETUPVAL 	20 0	; _
	578	[1400]	LOADK    	21 -55	; "Medium"
	579	[1400]	CALL     	20 2 2
	580	[1400]	SETTABLE 	19 -2 20	; "text" -
	581	[1403]	CLOSURE  	20 83	; 0x7fd3a0c245a0
	582	[1403]	MOVE     	0 0
	583	[1403]	SETTABLE 	19 -24 20	; "checked_func" -
	584	[1408]	CLOSURE  	20 84	; 0x7fd3a0c24a10
	585	[1408]	MOVE     	0 0
	586	[1408]	SETTABLE 	19 -17 20	; "callback" -
	587	[1409]	NEWTABLE 	20 0 3
	588	[1411]	GETUPVAL 	21 0	; _
	589	[1411]	LOADK    	22 -51	; "Thick"
	590	[1411]	CALL     	21 2 2
	591	[1411]	SETTABLE 	20 -2 21	; "text" -
	592	[1414]	CLOSURE  	21 85	; 0x7fd3a0c24d00
	593	[1414]	MOVE     	0 0
	594	[1414]	SETTABLE 	20 -24 21	; "checked_func" -
	595	[1419]	CLOSURE  	21 86	; 0x7fd3a0c24e60
	596	[1419]	MOVE     	0 0
	597	[1419]	SETTABLE 	20 -17 21	; "callback" -
	598	[1421]	SETLIST  	17 3 1	; 1
	599	[1421]	SETTABLE 	16 -4 17	; "sub_item_table" -
	600	[1423]	SETLIST  	11 5 1	; 1
	601	[1423]	SETTABLE 	10 -4 11	; "sub_item_table" -
	602	[1424]	NEWTABLE 	11 0 3
	603	[1435]	CLOSURE  	12 87	; 0x7fd3a0c25310
	604	[1435]	GETUPVAL 	0 0	; _
	605	[1435]	MOVE     	0 0
	606	[1435]	GETUPVAL 	0 5	; Screen
	607	[1435]	GETUPVAL 	0 4	; T
	608	[1435]	SETTABLE 	11 -30 12	; "text_func" -
	609	[1438]	CLOSURE  	12 88	; 0x7fd3a0c25630
	610	[1438]	MOVE     	0 0
	611	[1438]	SETTABLE 	11 -16 12	; "enabled_func" -
	612	[1439]	NEWTABLE 	12 3 0
	613	[1439]	NEWTABLE 	13 0 3
	614	[1441]	GETUPVAL 	14 0	; _
	615	[1441]	LOADK    	15 -56	; "No margins (0)"
	616	[1441]	CALL     	14 2 2
	617	[1441]	SETTABLE 	13 -2 14	; "text" -
	618	[1445]	CLOSURE  	14 89	; 0x7fd3a0c255a0
	619	[1445]	MOVE     	0 0
	620	[1445]	GETUPVAL 	0 5	; Screen
	621	[1445]	SETTABLE 	13 -24 14	; "checked_func" -
	622	[1450]	CLOSURE  	14 90	; 0x7fd3a0c25e10
	623	[1450]	MOVE     	0 0
	624	[1450]	GETUPVAL 	0 5	; Screen
	625	[1450]	SETTABLE 	13 -17 14	; "callback" -
	626	[1451]	NEWTABLE 	14 0 3
	627	[1453]	GETUPVAL 	15 0	; _
	628	[1453]	LOADK    	16 -57	; "Static margins (10)"
	629	[1453]	CALL     	15 2 2
	630	[1453]	SETTABLE 	14 -2 15	; "text" -
	631	[1459]	CLOSURE  	15 91	; 0x7fd3a0c261e0
	632	[1459]	MOVE     	0 0
	633	[1459]	GETUPVAL 	0 5	; Screen
	634	[1459]	SETTABLE 	14 -24 15	; "checked_func" -
	635	[1464]	CLOSURE  	15 92	; 0x7fd3a0c26680
	636	[1464]	MOVE     	0 0
	637	[1464]	GETUPVAL 	0 5	; Screen
	638	[1464]	SETTABLE 	14 -17 15	; "callback" -
	639	[1465]	NEWTABLE 	15 0 4
	640	[1472]	CLOSURE  	16 93	; 0x7fd3a0c26c00
	641	[1472]	MOVE     	0 0
	642	[1472]	GETUPVAL 	0 0	; _
	643	[1472]	GETUPVAL 	0 4	; T
	644	[1472]	SETTABLE 	15 -30 16	; "text_func" -
	645	[1475]	CLOSURE  	16 94	; 0x7fd3a0c274c0
	646	[1475]	MOVE     	0 0
	647	[1475]	SETTABLE 	15 -24 16	; "checked_func" -
	648	[1478]	CLOSURE  	16 95	; 0x7fd3a0c27540
	649	[1478]	MOVE     	0 0
	650	[1478]	SETTABLE 	15 -16 16	; "enabled_func" -
	651	[1483]	CLOSURE  	16 96	; 0x7fd3a0c27a20
	652	[1483]	MOVE     	0 0
	653	[1483]	GETUPVAL 	0 5	; Screen
	654	[1483]	SETTABLE 	15 -17 16	; "callback" -
	655	[1485]	SETLIST  	12 3 1	; 1
	656	[1485]	SETTABLE 	11 -4 12	; "sub_item_table" -
	657	[1486]	NEWTABLE 	12 0 4
	658	[1490]	CLOSURE  	13 97	; 0x7fd3a0c27e80
	659	[1490]	GETUPVAL 	0 4	; T
	660	[1490]	GETUPVAL 	0 0	; _
	661	[1490]	MOVE     	0 0
	662	[1490]	SETTABLE 	12 -30 13	; "text_func" -
	663	[1494]	CLOSURE  	13 98	; 0x7fd3a0c28480
	664	[1494]	MOVE     	0 0
	665	[1494]	SETTABLE 	12 -16 13	; "enabled_func" -
	666	[1514]	CLOSURE  	13 99	; 0x7fd3a0c286e0
	667	[1514]	GETUPVAL 	0 5	; Screen
	668	[1514]	MOVE     	0 0
	669	[1514]	GETUPVAL 	0 0	; _
	670	[1514]	GETUPVAL 	0 3	; UIManager
	671	[1514]	SETTABLE 	12 -17 13	; "callback" -
	672	[1515]	SETTABLE 	12 -31 -29	; "keep_menu_open" true
	673	[1517]	SETLIST  	7 5 1	; 1
	674	[1517]	SETTABLE 	6 -4 7	; "sub_item_table" -
	675	[1212]	CALL     	4 3 1
	676	[1519]	GETGLOBAL	4 -13	; table
	677	[1519]	GETTABLE 	4 4 -14	; "insert"
	678	[1519]	MOVE     	5 2
	679	[1519]	MOVE     	6 3
	680	[1519]	LOADK    	7 -58	; "page_progress"
	681	[1519]	CALL     	6 2 0
	682	[1519]	CALL     	4 0 1
	683	[1520]	GETGLOBAL	4 -13	; table
	684	[1520]	GETTABLE 	4 4 -14	; "insert"
	685	[1520]	MOVE     	5 2
	686	[1520]	MOVE     	6 3
	687	[1520]	LOADK    	7 -59	; "time"
	688	[1520]	CALL     	6 2 0
	689	[1520]	CALL     	4 0 1
	690	[1521]	GETGLOBAL	4 -13	; table
	691	[1521]	GETTABLE 	4 4 -14	; "insert"
	692	[1521]	MOVE     	5 2
	693	[1521]	MOVE     	6 3
	694	[1521]	LOADK    	7 -60	; "pages_left"
	695	[1521]	CALL     	6 2 0
	696	[1521]	CALL     	4 0 1
	697	[1522]	GETGLOBAL	4 -13	; table
	698	[1522]	GETTABLE 	4 4 -14	; "insert"
	699	[1522]	MOVE     	5 2
	700	[1522]	MOVE     	6 3
	701	[1522]	LOADK    	7 -61	; "battery"
	702	[1522]	CALL     	6 2 0
	703	[1522]	CALL     	4 0 1
	704	[1523]	GETGLOBAL	4 -13	; table
	705	[1523]	GETTABLE 	4 4 -14	; "insert"
	706	[1523]	MOVE     	5 2
	707	[1523]	MOVE     	6 3
	708	[1523]	LOADK    	7 -62	; "percentage"
	709	[1523]	CALL     	6 2 0
	710	[1523]	CALL     	4 0 1
	711	[1524]	GETGLOBAL	4 -13	; table
	712	[1524]	GETTABLE 	4 4 -14	; "insert"
	713	[1524]	MOVE     	5 2
	714	[1524]	MOVE     	6 3
	715	[1524]	LOADK    	7 -63	; "book_time_to_read"
	716	[1524]	CALL     	6 2 0
	717	[1524]	CALL     	4 0 1
	718	[1525]	GETGLOBAL	4 -13	; table
	719	[1525]	GETTABLE 	4 4 -14	; "insert"
	720	[1525]	MOVE     	5 2
	721	[1525]	MOVE     	6 3
	722	[1525]	LOADK    	7 -64	; "chapter_time_to_read"
	723	[1525]	CALL     	6 2 0
	724	[1525]	CALL     	4 0 1
	725	[1526]	GETUPVAL 	4 11	; Device
	726	[1526]	SELF     	4 4 -65	; "hasFrontlight"
	727	[1526]	CALL     	4 2 2
	728	[1526]	TEST     	4 0 0
	729	[1526]	JMP      	7	; to 737
	730	[1527]	GETGLOBAL	4 -13	; table
	731	[1527]	GETTABLE 	4 4 -14	; "insert"
	732	[1527]	MOVE     	5 2
	733	[1527]	MOVE     	6 3
	734	[1527]	LOADK    	7 -66	; "frontlight"
	735	[1527]	CALL     	6 2 0
	736	[1527]	CALL     	4 0 1
	737	[1529]	GETGLOBAL	4 -13	; table
	738	[1529]	GETTABLE 	4 4 -14	; "insert"
	739	[1529]	MOVE     	5 2
	740	[1529]	MOVE     	6 3
	741	[1529]	LOADK    	7 -67	; "mem_usage"
	742	[1529]	CALL     	6 2 0
	743	[1529]	CALL     	4 0 1
	744	[1530]	GETUPVAL 	4 11	; Device
	745	[1530]	SELF     	4 4 -68	; "isAndroid"
	746	[1530]	CALL     	4 2 2
	747	[1530]	TEST     	4 0 0
	748	[1530]	JMP      	7	; to 756
	749	[1531]	GETGLOBAL	4 -13	; table
	750	[1531]	GETTABLE 	4 4 -14	; "insert"
	751	[1531]	MOVE     	5 2
	752	[1531]	MOVE     	6 3
	753	[1531]	LOADK    	7 -69	; "wifi_status"
	754	[1531]	CALL     	6 2 0
	755	[1531]	CALL     	4 0 1
	756	[1533]	GETGLOBAL	4 -13	; table
	757	[1533]	GETTABLE 	4 4 -14	; "insert"
	758	[1533]	MOVE     	5 2
	759	[1533]	MOVE     	6 3
	760	[1533]	LOADK    	7 -70	; "book_title"
	761	[1533]	CALL     	6 2 0
	762	[1533]	CALL     	4 0 1
	763	[1534]	GETGLOBAL	4 -13	; table
	764	[1534]	GETTABLE 	4 4 -14	; "insert"
	765	[1534]	MOVE     	5 2
	766	[1534]	MOVE     	6 3
	767	[1534]	LOADK    	7 -71	; "book_chapter"
	768	[1534]	CALL     	6 2 0
	769	[1534]	CALL     	4 0 1
	770	[1535]	RETURN   	0 1

function <./frontend/apps/reader/modules/readerfooter.lua:706,708> (6 instructions, 24 bytes at 0x7fd3a0c11740)
0 params, 2 slots, 1 upvalue, 0 locals, 2 constants, 0 functions
	1	[707]	GETUPVAL 	0 0	; self
	2	[707]	GETTABLE 	0 0 -1	; "view"
	3	[707]	GETTABLE 	0 0 -2	; "flipping_visible"
	4	[707]	NOT      	0 0
	5	[707]	RETURN   	0 2
	6	[708]	RETURN   	0 1

function <./frontend/apps/reader/modules/readerfooter.lua:709,709> (4 instructions, 16 bytes at 0x7fd3a0c11a30)
0 params, 2 slots, 1 upvalue, 0 locals, 1 constant, 0 functions
	1	[709]	GETUPVAL 	0 0	; self
	2	[709]	SELF     	0 0 -1	; "onTapFooter"
	3	[709]	CALL     	0 2 1
	4	[709]	RETURN   	0 1

function <./frontend/apps/reader/modules/readerfooter.lua:713,787> (17 instructions, 68 bytes at 0x7fd3a0c11fd0)
2 params, 4 slots, 2 upvalues, 2 locals, 3 constants, 3 functions
	1	[714]	NEWTABLE 	2 0 3
	2	[717]	CLOSURE  	3 0	; 0x7fd3a0c122f0
	3	[717]	GETUPVAL 	0 0	; self
	4	[717]	MOVE     	0 0
	5	[717]	SETTABLE 	2 -1 3	; "text_func" -
	6	[720]	CLOSURE  	3 1	; 0x7fd3a0c123e0
	7	[720]	GETUPVAL 	0 0	; self
	8	[720]	MOVE     	0 0
	9	[720]	SETTABLE 	2 -2 3	; "checked_func" -
	10	[785]	CLOSURE  	3 2	; 0x7fd3a0c128a0
	11	[785]	GETUPVAL 	0 0	; self
	12	[785]	MOVE     	0 0
	13	[785]	GETUPVAL 	0 1	; footerTextGeneratorMap
	14	[785]	MOVE     	0 1
	15	[785]	SETTABLE 	2 -3 3	; "callback" -
	16	[786]	RETURN   	2 2
	17	[787]	RETURN   	0 1

function <./frontend/apps/reader/modules/readerfooter.lua:715,717> (6 instructions, 24 bytes at 0x7fd3a0c122f0)
0 params, 3 slots, 2 upvalues, 0 locals, 1 constant, 0 functions
	1	[716]	GETUPVAL 	0 0	; self
	2	[716]	SELF     	0 0 -1	; "textOptionTitles"
	3	[716]	GETUPVAL 	2 1	; option
	4	[716]	TAILCALL 	0 3 0
	5	[716]	RETURN   	0 0
	6	[717]	RETURN   	0 1

function <./frontend/apps/reader/modules/readerfooter.lua:718,720> (10 instructions, 40 bytes at 0x7fd3a0c123e0)
0 params, 2 slots, 2 upvalues, 0 locals, 2 constants, 0 functions
	1	[719]	GETUPVAL 	0 0	; self
	2	[719]	GETTABLE 	0 0 -1	; "settings"
	3	[719]	GETUPVAL 	1 1	; option
	4	[719]	GETTABLE 	0 0 1
	5	[719]	EQ       	1 0 -2	; - true
	6	[719]	JMP      	1	; to 8
	7	[719]	LOADBOOL 	0 0 1
	8	[719]	LOADBOOL 	0 1 0
	9	[719]	RETURN   	0 2
	10	[720]	RETURN   	0 1

function <./frontend/apps/reader/modules/readerfooter.lua:721,785> (181 instructions, 724 bytes at 0x7fd3a0c128a0)
0 params, 11 slots, 4 upvalues, 10 locals, 28 constants, 0 functions
	1	[722]	GETUPVAL 	0 0	; self
	2	[722]	GETTABLE 	0 0 -1	; "settings"
	3	[722]	GETUPVAL 	1 1	; option
	4	[722]	GETUPVAL 	2 0	; self
	5	[722]	GETTABLE 	2 2 -1	; "settings"
	6	[722]	GETUPVAL 	3 1	; option
	7	[722]	GETTABLE 	2 2 3
	8	[722]	NOT      	2 2
	9	[722]	SETTABLE 	0 1 2
	10	[723]	GETGLOBAL	0 -2	; G_reader_settings
	11	[723]	SELF     	0 0 -3	; "saveSetting"
	12	[723]	LOADK    	2 -4	; "footer"
	13	[723]	GETUPVAL 	3 0	; self
	14	[723]	GETTABLE 	3 3 -1	; "settings"
	15	[723]	CALL     	0 4 1
	16	[725]	LOADBOOL 	0 0 0
	17	[728]	LOADBOOL 	1 0 0
	18	[729]	LOADNIL  	2 2
	19	[730]	GETUPVAL 	3 0	; self
	20	[730]	GETTABLE 	3 3 -5	; "has_no_mode"
	21	[731]	GETUPVAL 	4 0	; self
	22	[731]	GETTABLE 	4 4 -6	; "reclaim_height"
	23	[732]	GETUPVAL 	5 0	; self
	24	[732]	SETTABLE 	5 -5 -7	; "has_no_mode" true
	25	[733]	GETGLOBAL	5 -8	; pairs
	26	[733]	GETUPVAL 	6 0	; self
	27	[733]	GETTABLE 	6 6 -9	; "mode_index"
	28	[733]	CALL     	5 2 4
	29	[733]	JMP      	9	; to 39
	30	[734]	GETUPVAL 	10 0	; self
	31	[734]	GETTABLE 	10 10 -1	; "settings"
	32	[734]	GETTABLE 	10 10 9
	33	[734]	TEST     	10 0 0
	34	[734]	JMP      	4	; to 39
	35	[735]	MOVE     	2 8
	36	[736]	GETUPVAL 	10 0	; self
	37	[736]	SETTABLE 	10 -5 -10	; "has_no_mode" false
	38	[737]	JMP      	2	; to 41
	39	[733]	TFORLOOP 	5 2
	40	[738]	JMP      	-11	; to 30
	41	[740]	GETUPVAL 	5 0	; self
	42	[740]	GETUPVAL 	6 0	; self
	43	[740]	GETTABLE 	6 6 -1	; "settings"
	44	[740]	GETTABLE 	6 6 -6	; "reclaim_height"
	45	[740]	TEST     	6 0 1
	46	[740]	JMP      	1	; to 48
	47	[740]	LOADBOOL 	6 0 0
	48	[740]	SETTABLE 	5 -6 6	; "reclaim_height" -
	49	[742]	GETUPVAL 	5 0	; self
	50	[742]	GETTABLE 	5 5 -5	; "has_no_mode"
	51	[742]	TEST     	5 0 0
	52	[742]	JMP      	18	; to 71
	53	[743]	GETUPVAL 	5 0	; self
	54	[743]	GETTABLE 	5 5 -11	; "footer_container"
	55	[743]	GETTABLE 	5 5 -12	; "dimen"
	56	[743]	SETTABLE 	5 -13 -14	; "h" 0
	57	[744]	GETUPVAL 	5 0	; self
	58	[744]	GETTABLE 	5 5 -15	; "footer_text"
	59	[744]	SETTABLE 	5 -16 -14	; "height" 0
	60	[745]	LOADBOOL 	0 1 0
	61	[746]	GETUPVAL 	5 0	; self
	62	[746]	GETUPVAL 	6 2	; footerTextGeneratorMap
	63	[746]	GETTABLE 	6 6 -18	; "empty"
	64	[746]	SETTABLE 	5 -17 6	; "genFooterText" -
	65	[747]	GETUPVAL 	5 0	; self
	66	[747]	GETUPVAL 	6 0	; self
	67	[747]	GETTABLE 	6 6 -20	; "mode_list"
	68	[747]	GETTABLE 	6 6 -21	; "off"
	69	[747]	SETTABLE 	5 -19 6	; "mode" -
	70	[747]	JMP      	39	; to 110
	71	[748]	TEST     	3 0 0
	72	[748]	JMP      	31	; to 104
	73	[749]	GETUPVAL 	5 0	; self
	74	[749]	GETTABLE 	5 5 -11	; "footer_container"
	75	[749]	GETTABLE 	5 5 -12	; "dimen"
	76	[749]	GETUPVAL 	6 0	; self
	77	[749]	GETTABLE 	6 6 -16	; "height"
	78	[749]	SETTABLE 	5 -13 6	; "h" -
	79	[750]	GETUPVAL 	5 0	; self
	80	[750]	GETTABLE 	5 5 -15	; "footer_text"
	81	[750]	GETUPVAL 	6 0	; self
	82	[750]	GETTABLE 	6 6 -16	; "height"
	83	[750]	SETTABLE 	5 -16 6	; "height" -
	84	[751]	GETUPVAL 	5 0	; self
	85	[751]	GETTABLE 	5 5 -1	; "settings"
	86	[751]	GETTABLE 	5 5 -22	; "all_at_once"
	87	[751]	TEST     	5 0 0
	88	[751]	JMP      	8	; to 97
	89	[752]	GETUPVAL 	5 0	; self
	90	[752]	GETUPVAL 	6 0	; self
	91	[752]	GETTABLE 	6 6 -20	; "mode_list"
	92	[752]	GETTABLE 	6 6 -23	; "page_progress"
	93	[752]	SETTABLE 	5 -19 6	; "mode" -
	94	[753]	GETUPVAL 	5 0	; self
	95	[753]	SELF     	5 5 -24	; "applyFooterMode"
	96	[753]	CALL     	5 2 1
	97	[755]	LOADBOOL 	0 1 0
	98	[756]	GETGLOBAL	5 -2	; G_reader_settings
	99	[756]	SELF     	5 5 -3	; "saveSetting"
	100	[756]	LOADK    	7 -25	; "reader_footer_mode"
	101	[756]	MOVE     	8 2
	102	[756]	CALL     	5 4 1
	103	[756]	JMP      	6	; to 110
	104	[757]	GETUPVAL 	5 0	; self
	105	[757]	GETTABLE 	5 5 -6	; "reclaim_height"
	106	[757]	EQ       	1 5 4
	107	[757]	JMP      	2	; to 110
	108	[758]	LOADBOOL 	0 1 0
	109	[759]	LOADBOOL 	1 1 0
	110	[761]	GETUPVAL 	5 3	; callback
	111	[761]	TEST     	5 0 0
	112	[761]	JMP      	5	; to 118
	113	[762]	GETUPVAL 	5 3	; callback
	114	[762]	GETUPVAL 	6 0	; self
	115	[762]	CALL     	5 2 2
	116	[762]	MOVE     	1 5
	117	[762]	JMP      	54	; to 172
	118	[763]	GETUPVAL 	5 0	; self
	119	[763]	GETTABLE 	5 5 -1	; "settings"
	120	[763]	GETTABLE 	5 5 -22	; "all_at_once"
	121	[763]	TEST     	5 0 0
	122	[763]	JMP      	5	; to 128
	123	[764]	GETUPVAL 	5 0	; self
	124	[764]	SELF     	5 5 -26	; "updateFooterTextGenerator"
	125	[764]	CALL     	5 2 2
	126	[764]	MOVE     	1 5
	127	[764]	JMP      	44	; to 172
	128	[765]	GETUPVAL 	5 0	; self
	129	[765]	GETTABLE 	5 5 -20	; "mode_list"
	130	[765]	GETUPVAL 	6 1	; option
	131	[765]	GETTABLE 	5 5 6
	132	[765]	GETUPVAL 	6 0	; self
	133	[765]	GETTABLE 	6 6 -19	; "mode"
	134	[765]	EQ       	0 5 6
	135	[765]	JMP      	6	; to 142
	136	[765]	GETUPVAL 	5 0	; self
	137	[765]	GETTABLE 	5 5 -1	; "settings"
	138	[765]	GETUPVAL 	6 1	; option
	139	[765]	GETTABLE 	5 5 6
	140	[765]	EQ       	1 5 -10	; - false
	141	[765]	JMP      	4	; to 146
	142	[766]	GETUPVAL 	5 0	; self
	143	[766]	GETTABLE 	5 5 -5	; "has_no_mode"
	144	[766]	EQ       	1 3 5
	145	[766]	JMP      	26	; to 172
	146	[770]	GETUPVAL 	5 0	; self
	147	[770]	GETTABLE 	5 5 -5	; "has_no_mode"
	148	[770]	TEST     	5 0 1
	149	[770]	JMP      	3	; to 153
	150	[771]	GETUPVAL 	5 0	; self
	151	[771]	SETTABLE 	5 -19 2	; "mode" -
	152	[771]	JMP      	15	; to 168
	153	[777]	GETUPVAL 	5 0	; self
	154	[777]	GETUPVAL 	6 0	; self
	155	[777]	GETTABLE 	6 6 -1	; "settings"
	156	[777]	GETTABLE 	6 6 -27	; "disable_progress_bar"
	157	[777]	TEST     	6 0 0
	158	[777]	JMP      	5	; to 164
	159	[777]	GETUPVAL 	6 0	; self
	160	[777]	GETTABLE 	6 6 -20	; "mode_list"
	161	[777]	GETTABLE 	6 6 -21	; "off"
	162	[777]	TEST     	6 0 1
	163	[777]	JMP      	3	; to 167
	164	[777]	GETUPVAL 	6 0	; self
	165	[777]	GETTABLE 	6 6 -20	; "mode_list"
	166	[777]	GETTABLE 	6 6 -23	; "page_progress"
	167	[777]	SETTABLE 	5 -19 6	; "mode" -
	168	[779]	LOADBOOL 	1 1 0
	169	[780]	GETUPVAL 	5 0	; self
	170	[780]	SELF     	5 5 -24	; "applyFooterMode"
	171	[780]	CALL     	5 2 1
	172	[782]	TEST     	1 0 1
	173	[782]	JMP      	2	; to 176
	174	[782]	TEST     	0 0 0
	175	[782]	JMP      	5	; to 181
	176	[783]	GETUPVAL 	5 0	; self
	177	[783]	SELF     	5 5 -28	; "refreshFooter"
	178	[783]	MOVE     	7 1
	179	[783]	MOVE     	8 0
	180	[783]	CALL     	5 4 1
	181	[785]	RETURN   	0 1

function <./frontend/apps/reader/modules/readerfooter.lua:793,815> (47 instructions, 188 bytes at 0x7fd3a0c12eb0)
0 params, 11 slots, 3 upvalues, 7 locals, 15 constants, 1 function
	1	[794]	NEWTABLE 	0 0 0
	2	[795]	LOADK    	1 -1	; 1
	3	[795]	GETUPVAL 	2 0	; self
	4	[795]	GETTABLE 	2 2 -2	; "mode_index"
	5	[795]	LEN      	2 2
	6	[795]	LOADK    	3 -1	; 1
	7	[795]	FORPREP  	1 16	; to 24
	8	[796]	GETGLOBAL	5 -3	; table
	9	[796]	GETTABLE 	5 5 -4	; "insert"
	10	[796]	MOVE     	6 0
	11	[796]	NEWTABLE 	7 0 2
	12	[796]	GETUPVAL 	8 0	; self
	13	[796]	SELF     	8 8 -6	; "textOptionTitles"
	14	[796]	GETUPVAL 	10 0	; self
	15	[796]	GETTABLE 	10 10 -2	; "mode_index"
	16	[796]	GETTABLE 	10 10 4
	17	[796]	CALL     	8 3 2
	18	[796]	SETTABLE 	7 -5 8	; "text" -
	19	[796]	GETUPVAL 	8 0	; self
	20	[796]	GETTABLE 	8 8 -2	; "mode_index"
	21	[796]	GETTABLE 	8 8 4
	22	[796]	SETTABLE 	7 -7 8	; "label" -
	23	[796]	CALL     	5 3 1
	24	[795]	FORLOOP  	1 -17	; to 8
	25	[798]	GETGLOBAL	1 -8	; require
	26	[798]	LOADK    	2 -9	; "ui/widget/sortwidget"
	27	[798]	CALL     	1 2 2
	28	[799]	LOADNIL  	2 2
	29	[800]	SELF     	3 1 -10	; "new"
	30	[800]	NEWTABLE 	5 0 3
	31	[801]	GETUPVAL 	6 1	; _
	32	[801]	LOADK    	7 -12	; "Sort footer items"
	33	[801]	CALL     	6 2 2
	34	[801]	SETTABLE 	5 -11 6	; "title" -
	35	[802]	SETTABLE 	5 -13 0	; "item_table" -
	36	[812]	CLOSURE  	6 0	; 0x7fd3a0c134b0
	37	[812]	MOVE     	0 2
	38	[812]	GETUPVAL 	0 0	; self
	39	[812]	GETUPVAL 	0 2	; UIManager
	40	[812]	SETTABLE 	5 -14 6	; "callback" -
	41	[800]	CALL     	3 3 2
	42	[813]	MOVE     	2 3
	43	[814]	GETUPVAL 	3 2	; UIManager
	44	[814]	SELF     	3 3 -15	; "show"
	45	[814]	MOVE     	5 2
	46	[814]	CALL     	3 3 1
	47	[815]	RETURN   	0 1

function <./frontend/apps/reader/modules/readerfooter.lua:803,812> (37 instructions, 148 bytes at 0x7fd3a0c134b0)
0 params, 6 slots, 3 upvalues, 4 locals, 13 constants, 0 functions
	1	[804]	LOADK    	0 -1	; 1
	2	[804]	GETUPVAL 	1 0	; sort_item
	3	[804]	GETTABLE 	1 1 -2	; "item_table"
	4	[804]	LEN      	1 1
	5	[804]	LOADK    	2 -1	; 1
	6	[804]	FORPREP  	0 7	; to 14
	7	[805]	GETUPVAL 	4 1	; self
	8	[805]	GETTABLE 	4 4 -3	; "mode_index"
	9	[805]	GETUPVAL 	5 0	; sort_item
	10	[805]	GETTABLE 	5 5 -2	; "item_table"
	11	[805]	GETTABLE 	5 5 3
	12	[805]	GETTABLE 	5 5 -4	; "label"
	13	[805]	SETTABLE 	4 3 5
	14	[804]	FORLOOP  	0 -8	; to 7
	15	[807]	GETUPVAL 	0 1	; self
	16	[807]	GETTABLE 	0 0 -5	; "settings"
	17	[807]	GETUPVAL 	1 1	; self
	18	[807]	GETTABLE 	1 1 -3	; "mode_index"
	19	[807]	SETTABLE 	0 -6 1	; "order" -
	20	[808]	GETGLOBAL	0 -7	; G_reader_settings
	21	[808]	SELF     	0 0 -8	; "saveSetting"
	22	[808]	LOADK    	2 -9	; "footer"
	23	[808]	GETUPVAL 	3 1	; self
	24	[808]	GETTABLE 	3 3 -5	; "settings"
	25	[808]	CALL     	0 4 1
	26	[809]	GETUPVAL 	0 1	; self
	27	[809]	SELF     	0 0 -10	; "updateFooterTextGenerator"
	28	[809]	CALL     	0 2 1
	29	[810]	GETUPVAL 	0 1	; self
	30	[810]	SELF     	0 0 -11	; "updateFooter"
	31	[810]	CALL     	0 2 1
	32	[811]	GETUPVAL 	0 2	; UIManager
	33	[811]	SELF     	0 0 -12	; "setDirty"
	34	[811]	LOADNIL  	2 2
	35	[811]	LOADK    	3 -13	; "ui"
	36	[811]	CALL     	0 4 1
	37	[812]	RETURN   	0 1

function <./frontend/apps/reader/modules/readerfooter.lua:821,823> (9 instructions, 36 bytes at 0x7fd3a0c13410)
0 params, 2 slots, 1 upvalue, 0 locals, 3 constants, 0 functions
	1	[822]	GETUPVAL 	0 0	; self
	2	[822]	GETTABLE 	0 0 -1	; "settings"
	3	[822]	GETTABLE 	0 0 -2	; "auto_refresh_time"
	4	[822]	EQ       	1 0 -3	; - true
	5	[822]	JMP      	1	; to 7
	6	[822]	LOADBOOL 	0 0 1
	7	[822]	LOADBOOL 	0 1 0
	8	[822]	RETURN   	0 2
	9	[823]	RETURN   	0 1

function <./frontend/apps/reader/modules/readerfooter.lua:825,825> (5 instructions, 20 bytes at 0x7fd3a0c13a30)
0 params, 2 slots, 1 upvalue, 0 locals, 2 constants, 0 functions
	1	[825]	GETUPVAL 	0 0	; self
	2	[825]	GETTABLE 	0 0 -1	; "settings"
	3	[825]	GETTABLE 	0 0 -2	; "time"
	4	[825]	RETURN   	0 2
	5	[825]	RETURN   	0 1

function <./frontend/apps/reader/modules/readerfooter.lua:826,835> (30 instructions, 120 bytes at 0x7fd3a0c119b0)
0 params, 4 slots, 2 upvalues, 0 locals, 10 constants, 0 functions
	1	[827]	GETUPVAL 	0 0	; self
	2	[827]	GETTABLE 	0 0 -1	; "settings"
	3	[827]	GETUPVAL 	1 0	; self
	4	[827]	GETTABLE 	1 1 -1	; "settings"
	5	[827]	GETTABLE 	1 1 -2	; "auto_refresh_time"
	6	[827]	NOT      	1 1
	7	[827]	SETTABLE 	0 -2 1	; "auto_refresh_time" -
	8	[828]	GETGLOBAL	0 -3	; G_reader_settings
	9	[828]	SELF     	0 0 -4	; "saveSetting"
	10	[828]	LOADK    	2 -5	; "footer"
	11	[828]	GETUPVAL 	3 0	; self
	12	[828]	GETTABLE 	3 3 -1	; "settings"
	13	[828]	CALL     	0 4 1
	14	[829]	GETUPVAL 	0 0	; self
	15	[829]	GETTABLE 	0 0 -1	; "settings"
	16	[829]	GETTABLE 	0 0 -2	; "auto_refresh_time"
	17	[829]	TEST     	0 0 0
	18	[829]	JMP      	4	; to 23
	19	[830]	GETUPVAL 	0 0	; self
	20	[830]	SELF     	0 0 -6	; "setupAutoRefreshTime"
	21	[830]	CALL     	0 2 1
	22	[830]	JMP      	7	; to 30
	23	[832]	GETUPVAL 	0 1	; UIManager
	24	[832]	SELF     	0 0 -7	; "unschedule"
	25	[832]	GETUPVAL 	2 0	; self
	26	[832]	GETTABLE 	2 2 -8	; "autoRefreshTime"
	27	[832]	CALL     	0 3 1
	28	[833]	GETUPVAL 	0 0	; self
	29	[833]	SETTABLE 	0 -9 -10	; "onCloseDocument" nil
	30	[835]	RETURN   	0 1

function <./frontend/apps/reader/modules/readerfooter.lua:839,841> (5 instructions, 20 bytes at 0x7fd3a0c143b0)
0 params, 2 slots, 1 upvalue, 0 locals, 2 constants, 0 functions
	1	[840]	GETUPVAL 	0 0	; self
	2	[840]	GETTABLE 	0 0 -1	; "settings"
	3	[840]	GETTABLE 	0 0 -2	; "bottom_horizontal_separator"
	4	[840]	RETURN   	0 2
	5	[841]	RETURN   	0 1

function <./frontend/apps/reader/modules/readerfooter.lua:842,845> (13 instructions, 52 bytes at 0x7fd3a0c14310)
0 params, 4 slots, 1 upvalue, 0 locals, 3 constants, 0 functions
	1	[843]	GETUPVAL 	0 0	; self
	2	[843]	GETTABLE 	0 0 -1	; "settings"
	3	[843]	GETUPVAL 	1 0	; self
	4	[843]	GETTABLE 	1 1 -1	; "settings"
	5	[843]	GETTABLE 	1 1 -2	; "bottom_horizontal_separator"
	6	[843]	NOT      	1 1
	7	[843]	SETTABLE 	0 -2 1	; "bottom_horizontal_separator" -
	8	[844]	GETUPVAL 	0 0	; self
	9	[844]	SELF     	0 0 -3	; "refreshFooter"
	10	[844]	LOADBOOL 	2 1 0
	11	[844]	LOADBOOL 	3 1 0
	12	[844]	CALL     	0 4 1
	13	[845]	RETURN   	0 1

function <./frontend/apps/reader/modules/readerfooter.lua:849,851> (5 instructions, 20 bytes at 0x7fd3a0c14990)
0 params, 2 slots, 1 upvalue, 0 locals, 2 constants, 0 functions
	1	[850]	GETUPVAL 	0 0	; self
	2	[850]	GETTABLE 	0 0 -1	; "settings"
	3	[850]	GETTABLE 	0 0 -2	; "lock_tap"
	4	[850]	RETURN   	0 2
	5	[851]	RETURN   	0 1

function <./frontend/apps/reader/modules/readerfooter.lua:852,854> (8 instructions, 32 bytes at 0x7fd3a0c14a60)
0 params, 2 slots, 1 upvalue, 0 locals, 2 constants, 0 functions
	1	[853]	GETUPVAL 	0 0	; self
	2	[853]	GETTABLE 	0 0 -1	; "settings"
	3	[853]	GETUPVAL 	1 0	; self
	4	[853]	GETTABLE 	1 1 -1	; "settings"
	5	[853]	GETTABLE 	1 1 -2	; "lock_tap"
	6	[853]	NOT      	1 1
	7	[853]	SETTABLE 	0 -2 1	; "lock_tap" -
	8	[854]	RETURN   	0 1

function <./frontend/apps/reader/modules/readerfooter.lua:861,863> (10 instructions, 40 bytes at 0x7fd3a0c14d50)
0 params, 3 slots, 3 upvalues, 0 locals, 3 constants, 0 functions
	1	[862]	GETUPVAL 	0 0	; T
	2	[862]	GETUPVAL 	1 1	; _
	3	[862]	LOADK    	2 -1	; "Font size (%1)"
	4	[862]	CALL     	1 2 2
	5	[862]	GETUPVAL 	2 2	; self
	6	[862]	GETTABLE 	2 2 -2	; "settings"
	7	[862]	GETTABLE 	2 2 -3	; "text_font_size"
	8	[862]	TAILCALL 	0 3 0
	9	[862]	RETURN   	0 0
	10	[863]	RETURN   	0 1

function <./frontend/apps/reader/modules/readerfooter.lua:864,890> (38 instructions, 152 bytes at 0x7fd3a0c15230)
1 param, 8 slots, 6 upvalues, 4 locals, 23 constants, 1 function
	1	[865]	GETGLOBAL	1 -1	; require
	2	[865]	LOADK    	2 -2	; "ui/widget/spinwidget"
	3	[865]	CALL     	1 2 2
	4	[866]	GETUPVAL 	2 0	; self
	5	[866]	GETTABLE 	2 2 -3	; "settings"
	6	[866]	GETTABLE 	2 2 -4	; "text_font_size"
	7	[867]	SELF     	3 1 -5	; "new"
	8	[867]	NEWTABLE 	5 0 9
	9	[868]	GETUPVAL 	6 1	; Screen
	10	[868]	SELF     	6 6 -7	; "getWidth"
	11	[868]	CALL     	6 2 2
	12	[868]	MUL      	6 6 -8	; - 0.6
	13	[868]	SETTABLE 	5 -6 6	; "width" -
	14	[869]	SETTABLE 	5 -9 2	; "value" -
	15	[870]	SETTABLE 	5 -10 -11	; "value_min" 8
	16	[871]	SETTABLE 	5 -12 -13	; "value_max" 36
	17	[872]	SETTABLE 	5 -14 -15	; "default_value" 14
	18	[873]	GETUPVAL 	6 2	; _
	19	[873]	LOADK    	7 -17	; "Set size"
	20	[873]	CALL     	6 2 2
	21	[873]	SETTABLE 	5 -16 6	; "ok_text" -
	22	[874]	GETUPVAL 	6 2	; _
	23	[874]	LOADK    	7 -19	; "Footer font size"
	24	[874]	CALL     	6 2 2
	25	[874]	SETTABLE 	5 -18 6	; "title_text" -
	26	[875]	SETTABLE 	5 -20 -21	; "keep_shown_on_apply" true
	27	[887]	CLOSURE  	6 0	; 0x7fd3a0c15740
	28	[887]	GETUPVAL 	0 0	; self
	29	[887]	GETUPVAL 	0 3	; TextWidget
	30	[887]	GETUPVAL 	0 4	; Font
	31	[887]	MOVE     	0 0
	32	[887]	SETTABLE 	5 -22 6	; "callback" -
	33	[867]	CALL     	3 3 2
	34	[889]	GETUPVAL 	4 5	; UIManager
	35	[889]	SELF     	4 4 -23	; "show"
	36	[889]	MOVE     	6 3
	37	[889]	CALL     	4 3 1
	38	[890]	RETURN   	0 1

function <./frontend/apps/reader/modules/readerfooter.lua:876,887> (48 instructions, 192 bytes at 0x7fd3a0c15740)
1 param, 9 slots, 4 upvalues, 1 local, 16 constants, 0 functions
	1	[877]	GETUPVAL 	1 0	; self
	2	[877]	GETTABLE 	1 1 -1	; "settings"
	3	[877]	GETTABLE 	2 0 -3	; "value"
	4	[877]	SETTABLE 	1 -2 2	; "text_font_size" -
	5	[878]	GETUPVAL 	1 0	; self
	6	[878]	GETTABLE 	1 1 -4	; "footer_text"
	7	[878]	SELF     	1 1 -5	; "free"
	8	[878]	CALL     	1 2 1
	9	[879]	GETUPVAL 	1 0	; self
	10	[879]	GETUPVAL 	2 1	; TextWidget
	11	[879]	SELF     	2 2 -6	; "new"
	12	[879]	NEWTABLE 	4 0 3
	13	[880]	GETUPVAL 	5 0	; self
	14	[880]	GETTABLE 	5 5 -4	; "footer_text"
	15	[880]	GETTABLE 	5 5 -7	; "text"
	16	[880]	SETTABLE 	4 -7 5	; "text" -
	17	[881]	GETUPVAL 	5 2	; Font
	18	[881]	SELF     	5 5 -9	; "getFace"
	19	[881]	GETUPVAL 	7 0	; self
	20	[881]	GETTABLE 	7 7 -10	; "text_font_face"
	21	[881]	GETUPVAL 	8 0	; self
	22	[881]	GETTABLE 	8 8 -1	; "settings"
	23	[881]	GETTABLE 	8 8 -2	; "text_font_size"
	24	[881]	CALL     	5 4 2
	25	[881]	SETTABLE 	4 -8 5	; "face" -
	26	[882]	GETUPVAL 	5 0	; self
	27	[882]	GETTABLE 	5 5 -1	; "settings"
	28	[882]	GETTABLE 	5 5 -12	; "text_font_bold"
	29	[882]	SETTABLE 	4 -11 5	; "bold" -
	30	[879]	CALL     	2 3 2
	31	[883]	SETTABLE 	1 -4 2	; "footer_text" -
	32	[884]	GETUPVAL 	1 0	; self
	33	[884]	GETTABLE 	1 1 -13	; "text_container"
	34	[884]	GETUPVAL 	2 0	; self
	35	[884]	GETTABLE 	2 2 -4	; "footer_text"
	36	[884]	SETTABLE 	1 -14 2	; 1 -
	37	[885]	GETUPVAL 	1 0	; self
	38	[885]	SELF     	1 1 -15	; "refreshFooter"
	39	[885]	LOADBOOL 	3 1 0
	40	[885]	LOADBOOL 	4 1 0
	41	[885]	CALL     	1 4 1
	42	[886]	GETUPVAL 	1 3	; touchmenu_instance
	43	[886]	TEST     	1 0 0
	44	[886]	JMP      	3	; to 48
	45	[886]	GETUPVAL 	1 3	; touchmenu_instance
	46	[886]	SELF     	1 1 -16	; "updateItems"
	47	[886]	CALL     	1 2 1
	48	[887]	RETURN   	0 1

function <./frontend/apps/reader/modules/readerfooter.lua:895,897> (9 instructions, 36 bytes at 0x7fd3a0c156c0)
0 params, 2 slots, 1 upvalue, 0 locals, 3 constants, 0 functions
	1	[896]	GETUPVAL 	0 0	; self
	2	[896]	GETTABLE 	0 0 -1	; "settings"
	3	[896]	GETTABLE 	0 0 -2	; "text_font_bold"
	4	[896]	EQ       	1 0 -3	; - true
	5	[896]	JMP      	1	; to 7
	6	[896]	LOADBOOL 	0 0 1
	7	[896]	LOADBOOL 	0 1 0
	8	[896]	RETURN   	0 2
	9	[897]	RETURN   	0 1

function <./frontend/apps/reader/modules/readerfooter.lua:898,909> (49 instructions, 196 bytes at 0x7fd3a0c13cb0)
1 param, 9 slots, 3 upvalues, 1 local, 15 constants, 0 functions
	1	[899]	GETUPVAL 	1 0	; self
	2	[899]	GETTABLE 	1 1 -1	; "settings"
	3	[899]	GETUPVAL 	2 0	; self
	4	[899]	GETTABLE 	2 2 -1	; "settings"
	5	[899]	GETTABLE 	2 2 -2	; "text_font_bold"
	6	[899]	NOT      	2 2
	7	[899]	SETTABLE 	1 -2 2	; "text_font_bold" -
	8	[900]	GETUPVAL 	1 0	; self
	9	[900]	GETTABLE 	1 1 -3	; "footer_text"
	10	[900]	SELF     	1 1 -4	; "free"
	11	[900]	CALL     	1 2 1
	12	[901]	GETUPVAL 	1 0	; self
	13	[901]	GETUPVAL 	2 1	; TextWidget
	14	[901]	SELF     	2 2 -5	; "new"
	15	[901]	NEWTABLE 	4 0 3
	16	[902]	GETUPVAL 	5 0	; self
	17	[902]	GETTABLE 	5 5 -3	; "footer_text"
	18	[902]	GETTABLE 	5 5 -6	; "text"
	19	[902]	SETTABLE 	4 -6 5	; "text" -
	20	[903]	GETUPVAL 	5 2	; Font
	21	[903]	SELF     	5 5 -8	; "getFace"
	22	[903]	GETUPVAL 	7 0	; self
	23	[903]	GETTABLE 	7 7 -9	; "text_font_face"
	24	[903]	GETUPVAL 	8 0	; self
	25	[903]	GETTABLE 	8 8 -1	; "settings"
	26	[903]	GETTABLE 	8 8 -10	; "text_font_size"
	27	[903]	CALL     	5 4 2
	28	[903]	SETTABLE 	4 -7 5	; "face" -
	29	[904]	GETUPVAL 	5 0	; self
	30	[904]	GETTABLE 	5 5 -1	; "settings"
	31	[904]	GETTABLE 	5 5 -2	; "text_font_bold"
	32	[904]	SETTABLE 	4 -11 5	; "bold" -
	33	[901]	CALL     	2 3 2
	34	[905]	SETTABLE 	1 -3 2	; "footer_text" -
	35	[906]	GETUPVAL 	1 0	; self
	36	[906]	GETTABLE 	1 1 -12	; "text_container"
	37	[906]	GETUPVAL 	2 0	; self
	38	[906]	GETTABLE 	2 2 -3	; "footer_text"
	39	[906]	SETTABLE 	1 -13 2	; 1 -
	40	[907]	GETUPVAL 	1 0	; self
	41	[907]	SELF     	1 1 -14	; "refreshFooter"
	42	[907]	LOADBOOL 	3 1 0
	43	[907]	LOADBOOL 	4 1 0
	44	[907]	CALL     	1 4 1
	45	[908]	TEST     	0 0 0
	46	[908]	JMP      	2	; to 49
	47	[908]	SELF     	1 0 -15	; "updateItems"
	48	[908]	CALL     	1 2 1
	49	[909]	RETURN   	0 1

function <./frontend/apps/reader/modules/readerfooter.lua:918,920> (10 instructions, 40 bytes at 0x7fd3a0c13da0)
0 params, 3 slots, 3 upvalues, 0 locals, 3 constants, 0 functions
	1	[919]	GETUPVAL 	0 0	; T
	2	[919]	GETUPVAL 	1 1	; _
	3	[919]	LOADK    	2 -1	; "Book title (%1%)"
	4	[919]	CALL     	1 2 2
	5	[919]	GETUPVAL 	2 2	; self
	6	[919]	GETTABLE 	2 2 -2	; "settings"
	7	[919]	GETTABLE 	2 2 -3	; "book_title_max_width_pct"
	8	[919]	TAILCALL 	0 3 0
	9	[919]	RETURN   	0 0
	10	[920]	RETURN   	0 1

function <./frontend/apps/reader/modules/readerfooter.lua:921,940> (37 instructions, 148 bytes at 0x7fd3a0c11dd0)
1 param, 7 slots, 4 upvalues, 3 locals, 25 constants, 1 function
	1	[922]	GETGLOBAL	1 -1	; require
	2	[922]	LOADK    	2 -2	; "ui/widget/spinwidget"
	3	[922]	CALL     	1 2 2
	4	[923]	SELF     	2 1 -3	; "new"
	5	[923]	NEWTABLE 	4 0 10
	6	[924]	GETUPVAL 	5 0	; Screen
	7	[924]	SELF     	5 5 -5	; "getWidth"
	8	[924]	CALL     	5 2 2
	9	[924]	MUL      	5 5 -6	; - 0.6
	10	[924]	SETTABLE 	4 -4 5	; "width" -
	11	[925]	GETUPVAL 	5 1	; self
	12	[925]	GETTABLE 	5 5 -8	; "settings"
	13	[925]	GETTABLE 	5 5 -9	; "book_title_max_width_pct"
	14	[925]	SETTABLE 	4 -7 5	; "value" -
	15	[926]	SETTABLE 	4 -10 -11	; "value_min" 10
	16	[927]	SETTABLE 	4 -12 -13	; "value_step" 5
	17	[928]	SETTABLE 	4 -14 -15	; "value_hold_step" 20
	18	[929]	SETTABLE 	4 -16 -17	; "value_max" 100
	19	[930]	GETUPVAL 	5 2	; _
	20	[930]	LOADK    	6 -19	; "Maximum width"
	21	[930]	CALL     	5 2 2
	22	[930]	SETTABLE 	4 -18 5	; "title_text" -
	23	[931]	GETUPVAL 	5 2	; _
	24	[931]	LOADK    	6 -21	; "Maximum book title width in percentage of screen width"
	25	[931]	CALL     	5 2 2
	26	[931]	SETTABLE 	4 -20 5	; "info_text" -
	27	[932]	SETTABLE 	4 -22 -23	; "keep_shown_on_apply" true
	28	[937]	CLOSURE  	5 0	; 0x7fd3a0c0ffa0
	29	[937]	GETUPVAL 	0 1	; self
	30	[937]	MOVE     	0 0
	31	[937]	SETTABLE 	4 -24 5	; "callback" -
	32	[923]	CALL     	2 3 2
	33	[939]	GETUPVAL 	3 3	; UIManager
	34	[939]	SELF     	3 3 -25	; "show"
	35	[939]	MOVE     	5 2
	36	[939]	CALL     	3 3 1
	37	[940]	RETURN   	0 1

function <./frontend/apps/reader/modules/readerfooter.lua:933,937> (16 instructions, 64 bytes at 0x7fd3a0c0ffa0)
1 param, 5 slots, 2 upvalues, 1 local, 5 constants, 0 functions
	1	[934]	GETUPVAL 	1 0	; self
	2	[934]	GETTABLE 	1 1 -1	; "settings"
	3	[934]	GETTABLE 	2 0 -3	; "value"
	4	[934]	SETTABLE 	1 -2 2	; "book_title_max_width_pct" -
	5	[935]	GETUPVAL 	1 0	; self
	6	[935]	SELF     	1 1 -4	; "refreshFooter"
	7	[935]	LOADBOOL 	3 1 0
	8	[935]	LOADBOOL 	4 1 0
	9	[935]	CALL     	1 4 1
	10	[936]	GETUPVAL 	1 1	; touchmenu_instance
	11	[936]	TEST     	1 0 0
	12	[936]	JMP      	3	; to 16
	13	[936]	GETUPVAL 	1 1	; touchmenu_instance
	14	[936]	SELF     	1 1 -5	; "updateItems"
	15	[936]	CALL     	1 2 1
	16	[937]	RETURN   	0 1

function <./frontend/apps/reader/modules/readerfooter.lua:944,946> (10 instructions, 40 bytes at 0x7fd3a0c147b0)
0 params, 3 slots, 3 upvalues, 0 locals, 3 constants, 0 functions
	1	[945]	GETUPVAL 	0 0	; T
	2	[945]	GETUPVAL 	1 1	; _
	3	[945]	LOADK    	2 -1	; "Current chapter (%1%)"
	4	[945]	CALL     	1 2 2
	5	[945]	GETUPVAL 	2 2	; self
	6	[945]	GETTABLE 	2 2 -2	; "settings"
	7	[945]	GETTABLE 	2 2 -3	; "book_chapter_max_width_pct"
	8	[945]	TAILCALL 	0 3 0
	9	[945]	RETURN   	0 0
	10	[946]	RETURN   	0 1

function <./frontend/apps/reader/modules/readerfooter.lua:947,966> (37 instructions, 148 bytes at 0x7fd3a0c0ecf0)
1 param, 7 slots, 4 upvalues, 3 locals, 25 constants, 1 function
	1	[948]	GETGLOBAL	1 -1	; require
	2	[948]	LOADK    	2 -2	; "ui/widget/spinwidget"
	3	[948]	CALL     	1 2 2
	4	[949]	SELF     	2 1 -3	; "new"
	5	[949]	NEWTABLE 	4 0 10
	6	[950]	GETUPVAL 	5 0	; Screen
	7	[950]	SELF     	5 5 -5	; "getWidth"
	8	[950]	CALL     	5 2 2
	9	[950]	MUL      	5 5 -6	; - 0.6
	10	[950]	SETTABLE 	4 -4 5	; "width" -
	11	[951]	GETUPVAL 	5 1	; self
	12	[951]	GETTABLE 	5 5 -8	; "settings"
	13	[951]	GETTABLE 	5 5 -9	; "book_chapter_max_width_pct"
	14	[951]	SETTABLE 	4 -7 5	; "value" -
	15	[952]	SETTABLE 	4 -10 -11	; "value_min" 10
	16	[953]	SETTABLE 	4 -12 -13	; "value_step" 5
	17	[954]	SETTABLE 	4 -14 -15	; "value_hold_step" 20
	18	[955]	SETTABLE 	4 -16 -17	; "value_max" 100
	19	[956]	GETUPVAL 	5 2	; _
	20	[956]	LOADK    	6 -19	; "Maximum width"
	21	[956]	CALL     	5 2 2
	22	[956]	SETTABLE 	4 -18 5	; "title_text" -
	23	[957]	GETUPVAL 	5 2	; _
	24	[957]	LOADK    	6 -21	; "Maximum chapter width in percentage of screen width"
	25	[957]	CALL     	5 2 2
	26	[957]	SETTABLE 	4 -20 5	; "info_text" -
	27	[958]	SETTABLE 	4 -22 -23	; "keep_shown_on_apply" true
	28	[963]	CLOSURE  	5 0	; 0x7fd3a0c15170
	29	[963]	GETUPVAL 	0 1	; self
	30	[963]	MOVE     	0 0
	31	[963]	SETTABLE 	4 -24 5	; "callback" -
	32	[949]	CALL     	2 3 2
	33	[965]	GETUPVAL 	3 3	; UIManager
	34	[965]	SELF     	3 3 -25	; "show"
	35	[965]	MOVE     	5 2
	36	[965]	CALL     	3 3 1
	37	[966]	RETURN   	0 1

function <./frontend/apps/reader/modules/readerfooter.lua:959,963> (16 instructions, 64 bytes at 0x7fd3a0c15170)
1 param, 5 slots, 2 upvalues, 1 local, 5 constants, 0 functions
	1	[960]	GETUPVAL 	1 0	; self
	2	[960]	GETTABLE 	1 1 -1	; "settings"
	3	[960]	GETTABLE 	2 0 -3	; "value"
	4	[960]	SETTABLE 	1 -2 2	; "book_chapter_max_width_pct" -
	5	[961]	GETUPVAL 	1 0	; self
	6	[961]	SELF     	1 1 -4	; "refreshFooter"
	7	[961]	LOADBOOL 	3 1 0
	8	[961]	LOADBOOL 	4 1 0
	9	[961]	CALL     	1 4 1
	10	[962]	GETUPVAL 	1 1	; touchmenu_instance
	11	[962]	TEST     	1 0 0
	12	[962]	JMP      	3	; to 16
	13	[962]	GETUPVAL 	1 1	; touchmenu_instance
	14	[962]	SELF     	1 1 -5	; "updateItems"
	15	[962]	CALL     	1 2 1
	16	[963]	RETURN   	0 1

function <./frontend/apps/reader/modules/readerfooter.lua:973,975> (14 instructions, 56 bytes at 0x7fd3a0c150f0)
0 params, 2 slots, 1 upvalue, 0 locals, 4 constants, 0 functions
	1	[974]	GETUPVAL 	0 0	; self
	2	[974]	GETTABLE 	0 0 -1	; "settings"
	3	[974]	GETTABLE 	0 0 -2	; "disable_progress_bar"
	4	[974]	TEST     	0 0 1
	5	[974]	JMP      	7	; to 13
	6	[974]	GETUPVAL 	0 0	; self
	7	[974]	GETTABLE 	0 0 -1	; "settings"
	8	[974]	GETTABLE 	0 0 -3	; "progress_bar_position"
	9	[974]	EQ       	0 0 -4	; - nil
	10	[974]	JMP      	1	; to 12
	11	[974]	LOADBOOL 	0 0 1
	12	[974]	LOADBOOL 	0 1 0
	13	[974]	RETURN   	0 2
	14	[975]	RETURN   	0 1

function <./frontend/apps/reader/modules/readerfooter.lua:979,981> (14 instructions, 56 bytes at 0x7fd3a0c11bc0)
0 params, 2 slots, 1 upvalue, 0 locals, 4 constants, 0 functions
	1	[980]	GETUPVAL 	0 0	; self
	2	[980]	GETTABLE 	0 0 -1	; "settings"
	3	[980]	GETTABLE 	0 0 -2	; "align"
	4	[980]	EQ       	1 0 -3	; - "center"
	5	[980]	JMP      	6	; to 12
	6	[980]	GETUPVAL 	0 0	; self
	7	[980]	GETTABLE 	0 0 -1	; "settings"
	8	[980]	GETTABLE 	0 0 -2	; "align"
	9	[980]	EQ       	1 0 -4	; - nil
	10	[980]	JMP      	1	; to 12
	11	[980]	LOADBOOL 	0 0 1
	12	[980]	LOADBOOL 	0 1 0
	13	[980]	RETURN   	0 2
	14	[981]	RETURN   	0 1

function <./frontend/apps/reader/modules/readerfooter.lua:982,985> (8 instructions, 32 bytes at 0x7fd3a0c16660)
0 params, 3 slots, 1 upvalue, 0 locals, 4 constants, 0 functions
	1	[983]	GETUPVAL 	0 0	; self
	2	[983]	GETTABLE 	0 0 -1	; "settings"
	3	[983]	SETTABLE 	0 -2 -3	; "align" "center"
	4	[984]	GETUPVAL 	0 0	; self
	5	[984]	SELF     	0 0 -4	; "refreshFooter"
	6	[984]	LOADBOOL 	2 1 0
	7	[984]	CALL     	0 3 1
	8	[985]	RETURN   	0 1

function <./frontend/apps/reader/modules/readerfooter.lua:989,991> (9 instructions, 36 bytes at 0x7fd3a0c0e030)
0 params, 2 slots, 1 upvalue, 0 locals, 3 constants, 0 functions
	1	[990]	GETUPVAL 	0 0	; self
	2	[990]	GETTABLE 	0 0 -1	; "settings"
	3	[990]	GETTABLE 	0 0 -2	; "align"
	4	[990]	EQ       	1 0 -3	; - "left"
	5	[990]	JMP      	1	; to 7
	6	[990]	LOADBOOL 	0 0 1
	7	[990]	LOADBOOL 	0 1 0
	8	[990]	RETURN   	0 2
	9	[991]	RETURN   	0 1

function <./frontend/apps/reader/modules/readerfooter.lua:992,995> (8 instructions, 32 bytes at 0x7fd3a0c0e0b0)
0 params, 3 slots, 1 upvalue, 0 locals, 4 constants, 0 functions
	1	[993]	GETUPVAL 	0 0	; self
	2	[993]	GETTABLE 	0 0 -1	; "settings"
	3	[993]	SETTABLE 	0 -2 -3	; "align" "left"
	4	[994]	GETUPVAL 	0 0	; self
	5	[994]	SELF     	0 0 -4	; "refreshFooter"
	6	[994]	LOADBOOL 	2 1 0
	7	[994]	CALL     	0 3 1
	8	[995]	RETURN   	0 1

function <./frontend/apps/reader/modules/readerfooter.lua:999,1001> (9 instructions, 36 bytes at 0x7fd3a0c14b60)
0 params, 2 slots, 1 upvalue, 0 locals, 3 constants, 0 functions
	1	[1000]	GETUPVAL 	0 0	; self
	2	[1000]	GETTABLE 	0 0 -1	; "settings"
	3	[1000]	GETTABLE 	0 0 -2	; "align"
	4	[1000]	EQ       	1 0 -3	; - "right"
	5	[1000]	JMP      	1	; to 7
	6	[1000]	LOADBOOL 	0 0 1
	7	[1000]	LOADBOOL 	0 1 0
	8	[1000]	RETURN   	0 2
	9	[1001]	RETURN   	0 1

function <./frontend/apps/reader/modules/readerfooter.lua:1002,1005> (8 instructions, 32 bytes at 0x7fd3a0c14be0)
0 params, 3 slots, 1 upvalue, 0 locals, 4 constants, 0 functions
	1	[1003]	GETUPVAL 	0 0	; self
	2	[1003]	GETTABLE 	0 0 -1	; "settings"
	3	[1003]	SETTABLE 	0 -2 -3	; "align" "right"
	4	[1004]	GETUPVAL 	0 0	; self
	5	[1004]	SELF     	0 0 -4	; "refreshFooter"
	6	[1004]	LOADBOOL 	2 1 0
	7	[1004]	CALL     	0 3 1
	8	[1005]	RETURN   	0 1

function <./frontend/apps/reader/modules/readerfooter.lua:1013,1019> (25 instructions, 100 bytes at 0x7fd3a0c12460)
0 params, 9 slots, 3 upvalues, 6 locals, 7 constants, 0 functions
	1	[1014]	NEWTABLE 	0 0 0
	2	[1015]	GETGLOBAL	1 -1	; pairs
	3	[1015]	GETUPVAL 	2 0	; symbol_prefix
	4	[1015]	GETTABLE 	2 2 -2	; "icons"
	5	[1015]	CALL     	1 2 4
	6	[1015]	JMP      	5	; to 12
	7	[1016]	GETGLOBAL	6 -3	; table
	8	[1016]	GETTABLE 	6 6 -4	; "insert"
	9	[1016]	MOVE     	7 0
	10	[1016]	MOVE     	8 5
	11	[1016]	CALL     	6 3 1
	12	[1015]	TFORLOOP 	1 2
	13	[1016]	JMP      	-7	; to 7
	14	[1018]	GETUPVAL 	1 1	; T
	15	[1018]	GETUPVAL 	2 2	; _
	16	[1018]	LOADK    	3 -5	; "Icons (%1)"
	17	[1018]	CALL     	2 2 2
	18	[1018]	GETGLOBAL	3 -3	; table
	19	[1018]	GETTABLE 	3 3 -6	; "concat"
	20	[1018]	MOVE     	4 0
	21	[1018]	LOADK    	5 -7	; " "
	22	[1018]	CALL     	3 3 0
	23	[1018]	TAILCALL 	1 0 0
	24	[1018]	RETURN   	1 0
	25	[1019]	RETURN   	0 1

function <./frontend/apps/reader/modules/readerfooter.lua:1020,1022> (14 instructions, 56 bytes at 0x7fd3a0c16f50)
0 params, 2 slots, 1 upvalue, 0 locals, 4 constants, 0 functions
	1	[1021]	GETUPVAL 	0 0	; self
	2	[1021]	GETTABLE 	0 0 -1	; "settings"
	3	[1021]	GETTABLE 	0 0 -2	; "item_prefix"
	4	[1021]	EQ       	1 0 -3	; - "icons"
	5	[1021]	JMP      	6	; to 12
	6	[1021]	GETUPVAL 	0 0	; self
	7	[1021]	GETTABLE 	0 0 -1	; "settings"
	8	[1021]	GETTABLE 	0 0 -2	; "item_prefix"
	9	[1021]	EQ       	1 0 -4	; - nil
	10	[1021]	JMP      	1	; to 12
	11	[1021]	LOADBOOL 	0 0 1
	12	[1021]	LOADBOOL 	0 1 0
	13	[1021]	RETURN   	0 2
	14	[1022]	RETURN   	0 1

function <./frontend/apps/reader/modules/readerfooter.lua:1023,1027> (12 instructions, 48 bytes at 0x7fd3a0c17010)
0 params, 4 slots, 2 upvalues, 0 locals, 6 constants, 0 functions
	1	[1024]	GETUPVAL 	0 0	; self
	2	[1024]	GETTABLE 	0 0 -1	; "settings"
	3	[1024]	SETTABLE 	0 -2 -3	; "item_prefix" "icons"
	4	[1025]	GETUPVAL 	0 0	; self
	5	[1025]	SELF     	0 0 -4	; "updateFooter"
	6	[1025]	CALL     	0 2 1
	7	[1026]	GETUPVAL 	0 1	; UIManager
	8	[1026]	SELF     	0 0 -5	; "setDirty"
	9	[1026]	LOADNIL  	2 2
	10	[1026]	LOADK    	3 -6	; "ui"
	11	[1026]	CALL     	0 4 1
	12	[1027]	RETURN   	0 1

function <./frontend/apps/reader/modules/readerfooter.lua:1030,1036> (25 instructions, 100 bytes at 0x7fd3a0c170d0)
0 params, 9 slots, 3 upvalues, 6 locals, 7 constants, 0 functions
	1	[1031]	NEWTABLE 	0 0 0
	2	[1032]	GETGLOBAL	1 -1	; pairs
	3	[1032]	GETUPVAL 	2 0	; symbol_prefix
	4	[1032]	GETTABLE 	2 2 -2	; "letters"
	5	[1032]	CALL     	1 2 4
	6	[1032]	JMP      	5	; to 12
	7	[1033]	GETGLOBAL	6 -3	; table
	8	[1033]	GETTABLE 	6 6 -4	; "insert"
	9	[1033]	MOVE     	7 0
	10	[1033]	MOVE     	8 5
	11	[1033]	CALL     	6 3 1
	12	[1032]	TFORLOOP 	1 2
	13	[1033]	JMP      	-7	; to 7
	14	[1035]	GETUPVAL 	1 1	; T
	15	[1035]	GETUPVAL 	2 2	; _
	16	[1035]	LOADK    	3 -5	; "Letters (%1)"
	17	[1035]	CALL     	2 2 2
	18	[1035]	GETGLOBAL	3 -3	; table
	19	[1035]	GETTABLE 	3 3 -6	; "concat"
	20	[1035]	MOVE     	4 0
	21	[1035]	LOADK    	5 -7	; " "
	22	[1035]	CALL     	3 3 0
	23	[1035]	TAILCALL 	1 0 0
	24	[1035]	RETURN   	1 0
	25	[1036]	RETURN   	0 1

function <./frontend/apps/reader/modules/readerfooter.lua:1037,1039> (9 instructions, 36 bytes at 0x7fd3a0c17ac0)
0 params, 2 slots, 1 upvalue, 0 locals, 3 constants, 0 functions
	1	[1038]	GETUPVAL 	0 0	; self
	2	[1038]	GETTABLE 	0 0 -1	; "settings"
	3	[1038]	GETTABLE 	0 0 -2	; "item_prefix"
	4	[1038]	EQ       	1 0 -3	; - "letters"
	5	[1038]	JMP      	1	; to 7
	6	[1038]	LOADBOOL 	0 0 1
	7	[1038]	LOADBOOL 	0 1 0
	8	[1038]	RETURN   	0 2
	9	[1039]	RETURN   	0 1

function <./frontend/apps/reader/modules/readerfooter.lua:1040,1044> (12 instructions, 48 bytes at 0x7fd3a0c17b80)
0 params, 4 slots, 2 upvalues, 0 locals, 6 constants, 0 functions
	1	[1041]	GETUPVAL 	0 0	; self
	2	[1041]	GETTABLE 	0 0 -1	; "settings"
	3	[1041]	SETTABLE 	0 -2 -3	; "item_prefix" "letters"
	4	[1042]	GETUPVAL 	0 0	; self
	5	[1042]	SELF     	0 0 -4	; "updateFooter"
	6	[1042]	CALL     	0 2 1
	7	[1043]	GETUPVAL 	0 1	; UIManager
	8	[1043]	SELF     	0 0 -5	; "setDirty"
	9	[1043]	LOADNIL  	2 2
	10	[1043]	LOADK    	3 -6	; "ui"
	11	[1043]	CALL     	0 4 1
	12	[1044]	RETURN   	0 1

function <./frontend/apps/reader/modules/readerfooter.lua:1053,1055> (14 instructions, 56 bytes at 0x7fd3a0c17f50)
0 params, 2 slots, 1 upvalue, 0 locals, 4 constants, 0 functions
	1	[1054]	GETUPVAL 	0 0	; self
	2	[1054]	GETTABLE 	0 0 -1	; "settings"
	3	[1054]	GETTABLE 	0 0 -2	; "items_separator"
	4	[1054]	EQ       	1 0 -3	; - "bar"
	5	[1054]	JMP      	6	; to 12
	6	[1054]	GETUPVAL 	0 0	; self
	7	[1054]	GETTABLE 	0 0 -1	; "settings"
	8	[1054]	GETTABLE 	0 0 -2	; "items_separator"
	9	[1054]	EQ       	1 0 -4	; - nil
	10	[1054]	JMP      	1	; to 12
	11	[1054]	LOADBOOL 	0 0 1
	12	[1054]	LOADBOOL 	0 1 0
	13	[1054]	RETURN   	0 2
	14	[1055]	RETURN   	0 1

function <./frontend/apps/reader/modules/readerfooter.lua:1056,1060> (12 instructions, 48 bytes at 0x7fd3a0c12760)
0 params, 4 slots, 2 upvalues, 0 locals, 6 constants, 0 functions
	1	[1057]	GETUPVAL 	0 0	; self
	2	[1057]	GETTABLE 	0 0 -1	; "settings"
	3	[1057]	SETTABLE 	0 -2 -3	; "items_separator" "bar"
	4	[1058]	GETUPVAL 	0 0	; self
	5	[1058]	SELF     	0 0 -4	; "updateFooter"
	6	[1058]	CALL     	0 2 1
	7	[1059]	GETUPVAL 	0 1	; UIManager
	8	[1059]	SELF     	0 0 -5	; "setDirty"
	9	[1059]	LOADNIL  	2 2
	10	[1059]	LOADK    	3 -6	; "ui"
	11	[1059]	CALL     	0 4 1
	12	[1060]	RETURN   	0 1

function <./frontend/apps/reader/modules/readerfooter.lua:1064,1066> (9 instructions, 36 bytes at 0x7fd3a0c184e0)
0 params, 2 slots, 1 upvalue, 0 locals, 3 constants, 0 functions
	1	[1065]	GETUPVAL 	0 0	; self
	2	[1065]	GETTABLE 	0 0 -1	; "settings"
	3	[1065]	GETTABLE 	0 0 -2	; "items_separator"
	4	[1065]	EQ       	1 0 -3	; - "bullet"
	5	[1065]	JMP      	1	; to 7
	6	[1065]	LOADBOOL 	0 0 1
	7	[1065]	LOADBOOL 	0 1 0
	8	[1065]	RETURN   	0 2
	9	[1066]	RETURN   	0 1

function <./frontend/apps/reader/modules/readerfooter.lua:1067,1071> (12 instructions, 48 bytes at 0x7fd3a0c18da0)
0 params, 4 slots, 2 upvalues, 0 locals, 6 constants, 0 functions
	1	[1068]	GETUPVAL 	0 0	; self
	2	[1068]	GETTABLE 	0 0 -1	; "settings"
	3	[1068]	SETTABLE 	0 -2 -3	; "items_separator" "bullet"
	4	[1069]	GETUPVAL 	0 0	; self
	5	[1069]	SELF     	0 0 -4	; "updateFooter"
	6	[1069]	CALL     	0 2 1
	7	[1070]	GETUPVAL 	0 1	; UIManager
	8	[1070]	SELF     	0 0 -5	; "setDirty"
	9	[1070]	LOADNIL  	2 2
	10	[1070]	LOADK    	3 -6	; "ui"
	11	[1070]	CALL     	0 4 1
	12	[1071]	RETURN   	0 1

function <./frontend/apps/reader/modules/readerfooter.lua:1075,1077> (9 instructions, 36 bytes at 0x7fd3a0c190f0)
0 params, 2 slots, 1 upvalue, 0 locals, 3 constants, 0 functions
	1	[1076]	GETUPVAL 	0 0	; self
	2	[1076]	GETTABLE 	0 0 -1	; "settings"
	3	[1076]	GETTABLE 	0 0 -2	; "items_separator"
	4	[1076]	EQ       	1 0 -3	; - "none"
	5	[1076]	JMP      	1	; to 7
	6	[1076]	LOADBOOL 	0 0 1
	7	[1076]	LOADBOOL 	0 1 0
	8	[1076]	RETURN   	0 2
	9	[1077]	RETURN   	0 1

function <./frontend/apps/reader/modules/readerfooter.lua:1078,1082> (12 instructions, 48 bytes at 0x7fd3a0c19700)
0 params, 4 slots, 2 upvalues, 0 locals, 6 constants, 0 functions
	1	[1079]	GETUPVAL 	0 0	; self
	2	[1079]	GETTABLE 	0 0 -1	; "settings"
	3	[1079]	SETTABLE 	0 -2 -3	; "items_separator" "none"
	4	[1080]	GETUPVAL 	0 0	; self
	5	[1080]	SELF     	0 0 -4	; "updateFooter"
	6	[1080]	CALL     	0 2 1
	7	[1081]	GETUPVAL 	0 1	; UIManager
	8	[1081]	SELF     	0 0 -5	; "setDirty"
	9	[1081]	LOADNIL  	2 2
	10	[1081]	LOADK    	3 -6	; "ui"
	11	[1081]	CALL     	0 4 1
	12	[1082]	RETURN   	0 1

function <./frontend/apps/reader/modules/readerfooter.lua:1090,1092> (11 instructions, 44 bytes at 0x7fd3a0c198d0)
0 params, 5 slots, 3 upvalues, 0 locals, 3 constants, 0 functions
	1	[1091]	GETUPVAL 	0 0	; T
	2	[1091]	GETUPVAL 	1 1	; _
	3	[1091]	LOADK    	2 -1	; "No decimal point (%1)"
	4	[1091]	CALL     	1 2 2
	5	[1091]	GETUPVAL 	2 2	; self
	6	[1091]	SELF     	2 2 -2	; "progressPercentage"
	7	[1091]	LOADK    	4 -3	; 0
	8	[1091]	CALL     	2 3 0
	9	[1091]	TAILCALL 	0 0 0
	10	[1091]	RETURN   	0 0
	11	[1092]	RETURN   	0 1

function <./frontend/apps/reader/modules/readerfooter.lua:1093,1095> (14 instructions, 56 bytes at 0x7fd3a0c19e90)
0 params, 2 slots, 1 upvalue, 0 locals, 4 constants, 0 functions
	1	[1094]	GETUPVAL 	0 0	; self
	2	[1094]	GETTABLE 	0 0 -1	; "settings"
	3	[1094]	GETTABLE 	0 0 -2	; "progress_pct_format"
	4	[1094]	EQ       	1 0 -3	; - "0"
	5	[1094]	JMP      	6	; to 12
	6	[1094]	GETUPVAL 	0 0	; self
	7	[1094]	GETTABLE 	0 0 -1	; "settings"
	8	[1094]	GETTABLE 	0 0 -2	; "progress_pct_format"
	9	[1094]	EQ       	1 0 -4	; - nil
	10	[1094]	JMP      	1	; to 12
	11	[1094]	LOADBOOL 	0 0 1
	12	[1094]	LOADBOOL 	0 1 0
	13	[1094]	RETURN   	0 2
	14	[1095]	RETURN   	0 1

function <./frontend/apps/reader/modules/readerfooter.lua:1096,1100> (12 instructions, 48 bytes at 0x7fd3a0c19f90)
0 params, 4 slots, 2 upvalues, 0 locals, 6 constants, 0 functions
	1	[1097]	GETUPVAL 	0 0	; self
	2	[1097]	GETTABLE 	0 0 -1	; "settings"
	3	[1097]	SETTABLE 	0 -2 -3	; "progress_pct_format" "0"
	4	[1098]	GETUPVAL 	0 0	; self
	5	[1098]	SELF     	0 0 -4	; "updateFooter"
	6	[1098]	CALL     	0 2 1
	7	[1099]	GETUPVAL 	0 1	; UIManager
	8	[1099]	SELF     	0 0 -5	; "setDirty"
	9	[1099]	LOADNIL  	2 2
	10	[1099]	LOADK    	3 -6	; "ui"
	11	[1099]	CALL     	0 4 1
	12	[1100]	RETURN   	0 1

function <./frontend/apps/reader/modules/readerfooter.lua:1103,1105> (11 instructions, 44 bytes at 0x7fd3a0c1a430)
0 params, 5 slots, 3 upvalues, 0 locals, 3 constants, 0 functions
	1	[1104]	GETUPVAL 	0 0	; T
	2	[1104]	GETUPVAL 	1 1	; _
	3	[1104]	LOADK    	2 -1	; "1 digit after decimal point (%1)"
	4	[1104]	CALL     	1 2 2
	5	[1104]	GETUPVAL 	2 2	; self
	6	[1104]	SELF     	2 2 -2	; "progressPercentage"
	7	[1104]	LOADK    	4 -3	; 1
	8	[1104]	CALL     	2 3 0
	9	[1104]	TAILCALL 	0 0 0
	10	[1104]	RETURN   	0 0
	11	[1105]	RETURN   	0 1

function <./frontend/apps/reader/modules/readerfooter.lua:1106,1108> (9 instructions, 36 bytes at 0x7fd3a0c1a590)
0 params, 2 slots, 1 upvalue, 0 locals, 3 constants, 0 functions
	1	[1107]	GETUPVAL 	0 0	; self
	2	[1107]	GETTABLE 	0 0 -1	; "settings"
	3	[1107]	GETTABLE 	0 0 -2	; "progress_pct_format"
	4	[1107]	EQ       	1 0 -3	; - "1"
	5	[1107]	JMP      	1	; to 7
	6	[1107]	LOADBOOL 	0 0 1
	7	[1107]	LOADBOOL 	0 1 0
	8	[1107]	RETURN   	0 2
	9	[1108]	RETURN   	0 1

function <./frontend/apps/reader/modules/readerfooter.lua:1109,1113> (12 instructions, 48 bytes at 0x7fd3a0c1ad30)
0 params, 4 slots, 2 upvalues, 0 locals, 6 constants, 0 functions
	1	[1110]	GETUPVAL 	0 0	; self
	2	[1110]	GETTABLE 	0 0 -1	; "settings"
	3	[1110]	SETTABLE 	0 -2 -3	; "progress_pct_format" "1"
	4	[1111]	GETUPVAL 	0 0	; self
	5	[1111]	SELF     	0 0 -4	; "updateFooter"
	6	[1111]	CALL     	0 2 1
	7	[1112]	GETUPVAL 	0 1	; UIManager
	8	[1112]	SELF     	0 0 -5	; "setDirty"
	9	[1112]	LOADNIL  	2 2
	10	[1112]	LOADK    	3 -6	; "ui"
	11	[1112]	CALL     	0 4 1
	12	[1113]	RETURN   	0 1

function <./frontend/apps/reader/modules/readerfooter.lua:1116,1118> (11 instructions, 44 bytes at 0x7fd3a0c1aeb0)
0 params, 5 slots, 3 upvalues, 0 locals, 3 constants, 0 functions
	1	[1117]	GETUPVAL 	0 0	; T
	2	[1117]	GETUPVAL 	1 1	; _
	3	[1117]	LOADK    	2 -1	; "2 digits after decimal point (%1)"
	4	[1117]	CALL     	1 2 2
	5	[1117]	GETUPVAL 	2 2	; self
	6	[1117]	SELF     	2 2 -2	; "progressPercentage"
	7	[1117]	LOADK    	4 -3	; 2
	8	[1117]	CALL     	2 3 0
	9	[1117]	TAILCALL 	0 0 0
	10	[1117]	RETURN   	0 0
	11	[1118]	RETURN   	0 1

function <./frontend/apps/reader/modules/readerfooter.lua:1119,1121> (9 instructions, 36 bytes at 0x7fd3a0c1b2d0)
0 params, 2 slots, 1 upvalue, 0 locals, 3 constants, 0 functions
	1	[1120]	GETUPVAL 	0 0	; self
	2	[1120]	GETTABLE 	0 0 -1	; "settings"
	3	[1120]	GETTABLE 	0 0 -2	; "progress_pct_format"
	4	[1120]	EQ       	1 0 -3	; - "2"
	5	[1120]	JMP      	1	; to 7
	6	[1120]	LOADBOOL 	0 0 1
	7	[1120]	LOADBOOL 	0 1 0
	8	[1120]	RETURN   	0 2
	9	[1121]	RETURN   	0 1

function <./frontend/apps/reader/modules/readerfooter.lua:1122,1126> (12 instructions, 48 bytes at 0x7fd3a0c1b5d0)
0 params, 4 slots, 2 upvalues, 0 locals, 6 constants, 0 functions
	1	[1123]	GETUPVAL 	0 0	; self
	2	[1123]	GETTABLE 	0 0 -1	; "settings"
	3	[1123]	SETTABLE 	0 -2 -3	; "progress_pct_format" "2"
	4	[1124]	GETUPVAL 	0 0	; self
	5	[1124]	SELF     	0 0 -4	; "updateFooter"
	6	[1124]	CALL     	0 2 1
	7	[1125]	GETUPVAL 	0 1	; UIManager
	8	[1125]	SELF     	0 0 -5	; "setDirty"
	9	[1125]	LOADNIL  	2 2
	10	[1125]	LOADK    	3 -6	; "ui"
	11	[1125]	CALL     	0 4 1
	12	[1126]	RETURN   	0 1

function <./frontend/apps/reader/modules/readerfooter.lua:1134,1140> (24 instructions, 96 bytes at 0x7fd3a0c1b980)
0 params, 5 slots, 4 upvalues, 1 local, 7 constants, 0 functions
	1	[1135]	NEWTABLE 	0 0 0
	2	[1136]	NEWTABLE 	1 0 0
	3	[1136]	SETTABLE 	0 -1 1	; "settings" -
	4	[1137]	GETTABLE 	1 0 -1	; "settings"
	5	[1137]	SETTABLE 	1 -2 -3	; "time_format" "24"
	6	[1138]	GETTABLE 	1 0 -1	; "settings"
	7	[1138]	GETUPVAL 	2 0	; self
	8	[1138]	GETTABLE 	2 2 -1	; "settings"
	9	[1138]	GETTABLE 	2 2 -4	; "item_prefix"
	10	[1138]	TEST     	2 0 1
	11	[1138]	JMP      	1	; to 13
	12	[1138]	LOADK    	2 -5	; "icons"
	13	[1138]	SETTABLE 	1 -4 2	; "item_prefix" -
	14	[1139]	GETUPVAL 	1 1	; T
	15	[1139]	GETUPVAL 	2 2	; _
	16	[1139]	LOADK    	3 -6	; "24-hour (%1)"
	17	[1139]	CALL     	2 2 2
	18	[1139]	GETUPVAL 	3 3	; footerTextGeneratorMap
	19	[1139]	GETTABLE 	3 3 -7	; "time"
	20	[1139]	MOVE     	4 0
	21	[1139]	CALL     	3 2 0
	22	[1139]	TAILCALL 	1 0 0
	23	[1139]	RETURN   	1 0
	24	[1140]	RETURN   	0 1

function <./frontend/apps/reader/modules/readerfooter.lua:1141,1143> (14 instructions, 56 bytes at 0x7fd3a0c1c220)
0 params, 2 slots, 1 upvalue, 0 locals, 4 constants, 0 functions
	1	[1142]	GETUPVAL 	0 0	; self
	2	[1142]	GETTABLE 	0 0 -1	; "settings"
	3	[1142]	GETTABLE 	0 0 -2	; "time_format"
	4	[1142]	EQ       	1 0 -3	; - "24"
	5	[1142]	JMP      	6	; to 12
	6	[1142]	GETUPVAL 	0 0	; self
	7	[1142]	GETTABLE 	0 0 -1	; "settings"
	8	[1142]	GETTABLE 	0 0 -2	; "time_format"
	9	[1142]	EQ       	1 0 -4	; - nil
	10	[1142]	JMP      	1	; to 12
	11	[1142]	LOADBOOL 	0 0 1
	12	[1142]	LOADBOOL 	0 1 0
	13	[1142]	RETURN   	0 2
	14	[1143]	RETURN   	0 1

function <./frontend/apps/reader/modules/readerfooter.lua:1144,1148> (12 instructions, 48 bytes at 0x7fd3a0c1c2e0)
0 params, 4 slots, 2 upvalues, 0 locals, 6 constants, 0 functions
	1	[1145]	GETUPVAL 	0 0	; self
	2	[1145]	GETTABLE 	0 0 -1	; "settings"
	3	[1145]	SETTABLE 	0 -2 -3	; "time_format" "24"
	4	[1146]	GETUPVAL 	0 0	; self
	5	[1146]	SELF     	0 0 -4	; "updateFooter"
	6	[1146]	CALL     	0 2 1
	7	[1147]	GETUPVAL 	0 1	; UIManager
	8	[1147]	SELF     	0 0 -5	; "setDirty"
	9	[1147]	LOADNIL  	2 2
	10	[1147]	LOADK    	3 -6	; "ui"
	11	[1147]	CALL     	0 4 1
	12	[1148]	RETURN   	0 1

function <./frontend/apps/reader/modules/readerfooter.lua:1151,1157> (24 instructions, 96 bytes at 0x7fd3a0c1c750)
0 params, 5 slots, 4 upvalues, 1 local, 7 constants, 0 functions
	1	[1152]	NEWTABLE 	0 0 0
	2	[1153]	NEWTABLE 	1 0 0
	3	[1153]	SETTABLE 	0 -1 1	; "settings" -
	4	[1154]	GETTABLE 	1 0 -1	; "settings"
	5	[1154]	SETTABLE 	1 -2 -3	; "time_format" "12"
	6	[1155]	GETTABLE 	1 0 -1	; "settings"
	7	[1155]	GETUPVAL 	2 0	; self
	8	[1155]	GETTABLE 	2 2 -1	; "settings"
	9	[1155]	GETTABLE 	2 2 -4	; "item_prefix"
	10	[1155]	TEST     	2 0 1
	11	[1155]	JMP      	1	; to 13
	12	[1155]	LOADK    	2 -5	; "icons"
	13	[1155]	SETTABLE 	1 -4 2	; "item_prefix" -
	14	[1156]	GETUPVAL 	1 1	; T
	15	[1156]	GETUPVAL 	2 2	; _
	16	[1156]	LOADK    	3 -6	; "12-hour (%1)"
	17	[1156]	CALL     	2 2 2
	18	[1156]	GETUPVAL 	3 3	; footerTextGeneratorMap
	19	[1156]	GETTABLE 	3 3 -7	; "time"
	20	[1156]	MOVE     	4 0
	21	[1156]	CALL     	3 2 0
	22	[1156]	TAILCALL 	1 0 0
	23	[1156]	RETURN   	1 0
	24	[1157]	RETURN   	0 1

function <./frontend/apps/reader/modules/readerfooter.lua:1158,1160> (9 instructions, 36 bytes at 0x7fd3a0c1d010)
0 params, 2 slots, 1 upvalue, 0 locals, 3 constants, 0 functions
	1	[1159]	GETUPVAL 	0 0	; self
	2	[1159]	GETTABLE 	0 0 -1	; "settings"
	3	[1159]	GETTABLE 	0 0 -2	; "time_format"
	4	[1159]	EQ       	1 0 -3	; - "12"
	5	[1159]	JMP      	1	; to 7
	6	[1159]	LOADBOOL 	0 0 1
	7	[1159]	LOADBOOL 	0 1 0
	8	[1159]	RETURN   	0 2
	9	[1160]	RETURN   	0 1

function <./frontend/apps/reader/modules/readerfooter.lua:1161,1165> (12 instructions, 48 bytes at 0x7fd3a0c1d270)
0 params, 4 slots, 2 upvalues, 0 locals, 6 constants, 0 functions
	1	[1162]	GETUPVAL 	0 0	; self
	2	[1162]	GETTABLE 	0 0 -1	; "settings"
	3	[1162]	SETTABLE 	0 -2 -3	; "time_format" "12"
	4	[1163]	GETUPVAL 	0 0	; self
	5	[1163]	SELF     	0 0 -4	; "updateFooter"
	6	[1163]	CALL     	0 2 1
	7	[1164]	GETUPVAL 	0 1	; UIManager
	8	[1164]	SELF     	0 0 -5	; "setDirty"
	9	[1164]	LOADNIL  	2 2
	10	[1164]	LOADK    	3 -6	; "ui"
	11	[1164]	CALL     	0 4 1
	12	[1165]	RETURN   	0 1

function <./frontend/apps/reader/modules/readerfooter.lua:1173,1180> (23 instructions, 92 bytes at 0x7fd3a0c1d400)
0 params, 5 slots, 4 upvalues, 2 locals, 5 constants, 0 functions
	1	[1174]	GETUPVAL 	0 0	; self
	2	[1174]	GETTABLE 	0 0 -1	; "settings"
	3	[1174]	GETTABLE 	0 0 -2	; "duration_format"
	4	[1175]	LOADNIL  	1 1
	5	[1176]	GETUPVAL 	2 0	; self
	6	[1176]	GETTABLE 	2 2 -1	; "settings"
	7	[1176]	SETTABLE 	2 -2 -3	; "duration_format" "modern"
	8	[1177]	GETUPVAL 	2 1	; footerTextGeneratorMap
	9	[1177]	GETTABLE 	2 2 -4	; "book_time_to_read"
	10	[1177]	GETUPVAL 	3 0	; self
	11	[1177]	CALL     	2 2 2
	12	[1177]	MOVE     	1 2
	13	[1178]	GETUPVAL 	2 0	; self
	14	[1178]	GETTABLE 	2 2 -1	; "settings"
	15	[1178]	SETTABLE 	2 -2 0	; "duration_format" -
	16	[1179]	GETUPVAL 	2 2	; T
	17	[1179]	GETUPVAL 	3 3	; _
	18	[1179]	LOADK    	4 -5	; "Modern (%1)"
	19	[1179]	CALL     	3 2 2
	20	[1179]	MOVE     	4 1
	21	[1179]	TAILCALL 	2 3 0
	22	[1179]	RETURN   	2 0
	23	[1180]	RETURN   	0 1

function <./frontend/apps/reader/modules/readerfooter.lua:1181,1183> (14 instructions, 56 bytes at 0x7fd3a0c1dcd0)
0 params, 2 slots, 1 upvalue, 0 locals, 4 constants, 0 functions
	1	[1182]	GETUPVAL 	0 0	; self
	2	[1182]	GETTABLE 	0 0 -1	; "settings"
	3	[1182]	GETTABLE 	0 0 -2	; "duration_format"
	4	[1182]	EQ       	1 0 -3	; - "modern"
	5	[1182]	JMP      	6	; to 12
	6	[1182]	GETUPVAL 	0 0	; self
	7	[1182]	GETTABLE 	0 0 -1	; "settings"
	8	[1182]	GETTABLE 	0 0 -2	; "duration_format"
	9	[1182]	EQ       	1 0 -4	; - nil
	10	[1182]	JMP      	1	; to 12
	11	[1182]	LOADBOOL 	0 0 1
	12	[1182]	LOADBOOL 	0 1 0
	13	[1182]	RETURN   	0 2
	14	[1183]	RETURN   	0 1

function <./frontend/apps/reader/modules/readerfooter.lua:1184,1188> (12 instructions, 48 bytes at 0x7fd3a0c1dd90)
0 params, 4 slots, 2 upvalues, 0 locals, 6 constants, 0 functions
	1	[1185]	GETUPVAL 	0 0	; self
	2	[1185]	GETTABLE 	0 0 -1	; "settings"
	3	[1185]	SETTABLE 	0 -2 -3	; "duration_format" "modern"
	4	[1186]	GETUPVAL 	0 0	; self
	5	[1186]	SELF     	0 0 -4	; "updateFooter"
	6	[1186]	CALL     	0 2 1
	7	[1187]	GETUPVAL 	0 1	; UIManager
	8	[1187]	SELF     	0 0 -5	; "setDirty"
	9	[1187]	LOADNIL  	2 2
	10	[1187]	LOADK    	3 -6	; "ui"
	11	[1187]	CALL     	0 4 1
	12	[1188]	RETURN   	0 1

function <./frontend/apps/reader/modules/readerfooter.lua:1191,1198> (23 instructions, 92 bytes at 0x7fd3a0c1e280)
0 params, 5 slots, 4 upvalues, 2 locals, 5 constants, 0 functions
	1	[1192]	GETUPVAL 	0 0	; self
	2	[1192]	GETTABLE 	0 0 -1	; "settings"
	3	[1192]	GETTABLE 	0 0 -2	; "duration_format"
	4	[1193]	LOADNIL  	1 1
	5	[1194]	GETUPVAL 	2 0	; self
	6	[1194]	GETTABLE 	2 2 -1	; "settings"
	7	[1194]	SETTABLE 	2 -2 -3	; "duration_format" "classic"
	8	[1195]	GETUPVAL 	2 1	; footerTextGeneratorMap
	9	[1195]	GETTABLE 	2 2 -4	; "book_time_to_read"
	10	[1195]	GETUPVAL 	3 0	; self
	11	[1195]	CALL     	2 2 2
	12	[1195]	MOVE     	1 2
	13	[1196]	GETUPVAL 	2 0	; self
	14	[1196]	GETTABLE 	2 2 -1	; "settings"
	15	[1196]	SETTABLE 	2 -2 0	; "duration_format" -
	16	[1197]	GETUPVAL 	2 2	; T
	17	[1197]	GETUPVAL 	3 3	; _
	18	[1197]	LOADK    	4 -5	; "Classic (%1)"
	19	[1197]	CALL     	3 2 2
	20	[1197]	MOVE     	4 1
	21	[1197]	TAILCALL 	2 3 0
	22	[1197]	RETURN   	2 0
	23	[1198]	RETURN   	0 1

function <./frontend/apps/reader/modules/readerfooter.lua:1199,1201> (9 instructions, 36 bytes at 0x7fd3a0c1e6a0)
0 params, 2 slots, 1 upvalue, 0 locals, 3 constants, 0 functions
	1	[1200]	GETUPVAL 	0 0	; self
	2	[1200]	GETTABLE 	0 0 -1	; "settings"
	3	[1200]	GETTABLE 	0 0 -2	; "duration_format"
	4	[1200]	EQ       	1 0 -3	; - "classic"
	5	[1200]	JMP      	1	; to 7
	6	[1200]	LOADBOOL 	0 0 1
	7	[1200]	LOADBOOL 	0 1 0
	8	[1200]	RETURN   	0 2
	9	[1201]	RETURN   	0 1

function <./frontend/apps/reader/modules/readerfooter.lua:1202,1206> (12 instructions, 48 bytes at 0x7fd3a0c1edb0)
0 params, 4 slots, 2 upvalues, 0 locals, 6 constants, 0 functions
	1	[1203]	GETUPVAL 	0 0	; self
	2	[1203]	GETTABLE 	0 0 -1	; "settings"
	3	[1203]	SETTABLE 	0 -2 -3	; "duration_format" "classic"
	4	[1204]	GETUPVAL 	0 0	; self
	5	[1204]	SELF     	0 0 -4	; "updateFooter"
	6	[1204]	CALL     	0 2 1
	7	[1205]	GETUPVAL 	0 1	; UIManager
	8	[1205]	SELF     	0 0 -5	; "setDirty"
	9	[1205]	LOADNIL  	2 2
	10	[1205]	LOADK    	3 -6	; "ui"
	11	[1205]	CALL     	0 4 1
	12	[1206]	RETURN   	0 1

function <./frontend/apps/reader/modules/readerfooter.lua:1218,1220> (6 instructions, 24 bytes at 0x7fd3a0c1efa0)
0 params, 2 slots, 1 upvalue, 0 locals, 2 constants, 0 functions
	1	[1219]	GETUPVAL 	0 0	; self
	2	[1219]	GETTABLE 	0 0 -1	; "settings"
	3	[1219]	GETTABLE 	0 0 -2	; "disable_progress_bar"
	4	[1219]	NOT      	0 0
	5	[1219]	RETURN   	0 2
	6	[1220]	RETURN   	0 1

function <./frontend/apps/reader/modules/readerfooter.lua:1221,1231> (40 instructions, 160 bytes at 0x7fd3a0c1f340)
0 params, 4 slots, 1 upvalue, 0 locals, 13 constants, 0 functions
	1	[1222]	GETUPVAL 	0 0	; self
	2	[1222]	GETTABLE 	0 0 -1	; "settings"
	3	[1222]	GETUPVAL 	1 0	; self
	4	[1222]	GETTABLE 	1 1 -1	; "settings"
	5	[1222]	GETTABLE 	1 1 -2	; "disable_progress_bar"
	6	[1222]	NOT      	1 1
	7	[1222]	SETTABLE 	0 -2 1	; "disable_progress_bar" -
	8	[1223]	GETUPVAL 	0 0	; self
	9	[1223]	GETTABLE 	0 0 -1	; "settings"
	10	[1223]	GETTABLE 	0 0 -2	; "disable_progress_bar"
	11	[1223]	TEST     	0 0 1
	12	[1223]	JMP      	22	; to 35
	13	[1224]	GETUPVAL 	0 0	; self
	14	[1224]	GETTABLE 	0 0 -3	; "footer_container"
	15	[1224]	GETTABLE 	0 0 -4	; "dimen"
	16	[1224]	GETUPVAL 	1 0	; self
	17	[1224]	GETTABLE 	1 1 -6	; "height"
	18	[1224]	SETTABLE 	0 -5 1	; "h" -
	19	[1225]	GETUPVAL 	0 0	; self
	20	[1225]	GETTABLE 	0 0 -7	; "footer_text"
	21	[1225]	GETUPVAL 	1 0	; self
	22	[1225]	GETTABLE 	1 1 -6	; "height"
	23	[1225]	SETTABLE 	0 -6 1	; "height" -
	24	[1226]	GETUPVAL 	0 0	; self
	25	[1226]	SELF     	0 0 -8	; "setTocMarkers"
	26	[1226]	CALL     	0 2 1
	27	[1227]	GETUPVAL 	0 0	; self
	28	[1227]	GETUPVAL 	1 0	; self
	29	[1227]	GETTABLE 	1 1 -10	; "mode_list"
	30	[1227]	GETTABLE 	1 1 -11	; "page_progress"
	31	[1227]	SETTABLE 	0 -9 1	; "mode" -
	32	[1228]	GETUPVAL 	0 0	; self
	33	[1228]	SELF     	0 0 -12	; "applyFooterMode"
	34	[1228]	CALL     	0 2 1
	35	[1230]	GETUPVAL 	0 0	; self
	36	[1230]	SELF     	0 0 -13	; "refreshFooter"
	37	[1230]	LOADBOOL 	2 1 0
	38	[1230]	LOADBOOL 	3 1 0
	39	[1230]	CALL     	0 4 1
	40	[1231]	RETURN   	0 1

function <./frontend/apps/reader/modules/readerfooter.lua:1234,1242> (30 instructions, 120 bytes at 0x7fd3a0c1f590)
0 params, 4 slots, 3 upvalues, 1 local, 8 constants, 0 functions
	1	[1235]	GETUPVAL 	0 0	; _
	2	[1235]	LOADK    	1 -1	; "alongside items"
	3	[1235]	CALL     	0 2 2
	4	[1236]	GETUPVAL 	1 1	; self
	5	[1236]	GETTABLE 	1 1 -2	; "settings"
	6	[1236]	GETTABLE 	1 1 -3	; "progress_bar_position"
	7	[1236]	EQ       	0 1 -4	; - "above"
	8	[1236]	JMP      	5	; to 14
	9	[1237]	GETUPVAL 	1 0	; _
	10	[1237]	LOADK    	2 -5	; "above items"
	11	[1237]	CALL     	1 2 2
	12	[1237]	MOVE     	0 1
	13	[1237]	JMP      	9	; to 23
	14	[1238]	GETUPVAL 	1 1	; self
	15	[1238]	GETTABLE 	1 1 -2	; "settings"
	16	[1238]	GETTABLE 	1 1 -3	; "progress_bar_position"
	17	[1238]	EQ       	0 1 -6	; - "below"
	18	[1238]	JMP      	4	; to 23
	19	[1239]	GETUPVAL 	1 0	; _
	20	[1239]	LOADK    	2 -7	; "below items"
	21	[1239]	CALL     	1 2 2
	22	[1239]	MOVE     	0 1
	23	[1241]	GETUPVAL 	1 2	; T
	24	[1241]	GETUPVAL 	2 0	; _
	25	[1241]	LOADK    	3 -8	; "Position: %1"
	26	[1241]	CALL     	2 2 2
	27	[1241]	MOVE     	3 0
	28	[1241]	TAILCALL 	1 3 0
	29	[1241]	RETURN   	1 0
	30	[1242]	RETURN   	0 1

function <./frontend/apps/reader/modules/readerfooter.lua:1243,1245> (6 instructions, 24 bytes at 0x7fd3a0c1fc70)
0 params, 2 slots, 1 upvalue, 0 locals, 2 constants, 0 functions
	1	[1244]	GETUPVAL 	0 0	; self
	2	[1244]	GETTABLE 	0 0 -1	; "settings"
	3	[1244]	GETTABLE 	0 0 -2	; "disable_progress_bar"
	4	[1244]	NOT      	0 0
	5	[1244]	RETURN   	0 2
	6	[1245]	RETURN   	0 1

function <./frontend/apps/reader/modules/readerfooter.lua:1249,1251> (9 instructions, 36 bytes at 0x7fd3a0c1fe70)
0 params, 2 slots, 1 upvalue, 0 locals, 3 constants, 0 functions
	1	[1250]	GETUPVAL 	0 0	; self
	2	[1250]	GETTABLE 	0 0 -1	; "settings"
	3	[1250]	GETTABLE 	0 0 -2	; "progress_bar_position"
	4	[1250]	EQ       	1 0 -3	; - "above"
	5	[1250]	JMP      	1	; to 7
	6	[1250]	LOADBOOL 	0 0 1
	7	[1250]	LOADBOOL 	0 1 0
	8	[1250]	RETURN   	0 2
	9	[1251]	RETURN   	0 1

function <./frontend/apps/reader/modules/readerfooter.lua:1252,1255> (9 instructions, 36 bytes at 0x7fd3a0c20250)
0 params, 4 slots, 1 upvalue, 0 locals, 4 constants, 0 functions
	1	[1253]	GETUPVAL 	0 0	; self
	2	[1253]	GETTABLE 	0 0 -1	; "settings"
	3	[1253]	SETTABLE 	0 -2 -3	; "progress_bar_position" "above"
	4	[1254]	GETUPVAL 	0 0	; self
	5	[1254]	SELF     	0 0 -4	; "refreshFooter"
	6	[1254]	LOADBOOL 	2 1 0
	7	[1254]	LOADBOOL 	3 1 0
	8	[1254]	CALL     	0 4 1
	9	[1255]	RETURN   	0 1

function <./frontend/apps/reader/modules/readerfooter.lua:1259,1261> (9 instructions, 36 bytes at 0x7fd3a0c187e0)
0 params, 2 slots, 1 upvalue, 0 locals, 3 constants, 0 functions
	1	[1260]	GETUPVAL 	0 0	; self
	2	[1260]	GETTABLE 	0 0 -1	; "settings"
	3	[1260]	GETTABLE 	0 0 -2	; "progress_bar_position"
	4	[1260]	EQ       	1 0 -3	; - "below"
	5	[1260]	JMP      	1	; to 7
	6	[1260]	LOADBOOL 	0 0 1
	7	[1260]	LOADBOOL 	0 1 0
	8	[1260]	RETURN   	0 2
	9	[1261]	RETURN   	0 1

function <./frontend/apps/reader/modules/readerfooter.lua:1262,1265> (9 instructions, 36 bytes at 0x7fd3a0c188e0)
0 params, 4 slots, 1 upvalue, 0 locals, 4 constants, 0 functions
	1	[1263]	GETUPVAL 	0 0	; self
	2	[1263]	GETTABLE 	0 0 -1	; "settings"
	3	[1263]	SETTABLE 	0 -2 -3	; "progress_bar_position" "below"
	4	[1264]	GETUPVAL 	0 0	; self
	5	[1264]	SELF     	0 0 -4	; "refreshFooter"
	6	[1264]	LOADBOOL 	2 1 0
	7	[1264]	LOADBOOL 	3 1 0
	8	[1264]	CALL     	0 4 1
	9	[1265]	RETURN   	0 1

function <./frontend/apps/reader/modules/readerfooter.lua:1269,1271> (6 instructions, 24 bytes at 0x7fd3a0c20960)
0 params, 2 slots, 1 upvalue, 0 locals, 2 constants, 0 functions
	1	[1270]	GETUPVAL 	0 0	; self
	2	[1270]	GETTABLE 	0 0 -1	; "settings"
	3	[1270]	GETTABLE 	0 0 -2	; "progress_bar_position"
	4	[1270]	NOT      	0 0
	5	[1270]	RETURN   	0 2
	6	[1271]	RETURN   	0 1

function <./frontend/apps/reader/modules/readerfooter.lua:1272,1279> (24 instructions, 96 bytes at 0x7fd3a0c209e0)
0 params, 4 slots, 2 upvalues, 0 locals, 9 constants, 0 functions
	1	[1273]	GETUPVAL 	0 0	; self
	2	[1273]	GETTABLE 	0 0 -1	; "settings"
	3	[1273]	GETTABLE 	0 0 -2	; "progress_margin"
	4	[1273]	TEST     	0 0 0
	5	[1273]	JMP      	10	; to 16
	6	[1274]	GETUPVAL 	0 0	; self
	7	[1274]	GETTABLE 	0 0 -1	; "settings"
	8	[1274]	SETTABLE 	0 -2 -3	; "progress_margin" false
	9	[1275]	GETUPVAL 	0 0	; self
	10	[1275]	GETTABLE 	0 0 -1	; "settings"
	11	[1275]	GETUPVAL 	1 1	; Screen
	12	[1275]	SELF     	1 1 -5	; "scaleBySize"
	13	[1275]	LOADK    	3 -6	; 10
	14	[1275]	CALL     	1 3 2
	15	[1275]	SETTABLE 	0 -4 1	; "progress_margin_width" -
	16	[1277]	GETUPVAL 	0 0	; self
	17	[1277]	GETTABLE 	0 0 -1	; "settings"
	18	[1277]	SETTABLE 	0 -7 -8	; "progress_bar_position" nil
	19	[1278]	GETUPVAL 	0 0	; self
	20	[1278]	SELF     	0 0 -9	; "refreshFooter"
	21	[1278]	LOADBOOL 	2 1 0
	22	[1278]	LOADBOOL 	3 1 0
	23	[1278]	CALL     	0 4 1
	24	[1279]	RETURN   	0 1

function <./frontend/apps/reader/modules/readerfooter.lua:1284,1290> (15 instructions, 60 bytes at 0x7fd3a0c20d40)
0 params, 2 slots, 2 upvalues, 0 locals, 4 constants, 0 functions
	1	[1285]	GETUPVAL 	0 0	; self
	2	[1285]	GETTABLE 	0 0 -1	; "settings"
	3	[1285]	GETTABLE 	0 0 -2	; "progress_style_thin"
	4	[1285]	TEST     	0 0 0
	5	[1285]	JMP      	5	; to 11
	6	[1286]	GETUPVAL 	0 1	; _
	7	[1286]	LOADK    	1 -3	; "Style: thin"
	8	[1286]	TAILCALL 	0 2 0
	9	[1286]	RETURN   	0 0
	10	[1286]	JMP      	4	; to 15
	11	[1288]	GETUPVAL 	0 1	; _
	12	[1288]	LOADK    	1 -4	; "Style: thick"
	13	[1288]	TAILCALL 	0 2 0
	14	[1288]	RETURN   	0 0
	15	[1290]	RETURN   	0 1

function <./frontend/apps/reader/modules/readerfooter.lua:1291,1293> (6 instructions, 24 bytes at 0x7fd3a0c20e80)
0 params, 2 slots, 1 upvalue, 0 locals, 2 constants, 0 functions
	1	[1292]	GETUPVAL 	0 0	; self
	2	[1292]	GETTABLE 	0 0 -1	; "settings"
	3	[1292]	GETTABLE 	0 0 -2	; "disable_progress_bar"
	4	[1292]	NOT      	0 0
	5	[1292]	RETURN   	0 2
	6	[1293]	RETURN   	0 1

function <./frontend/apps/reader/modules/readerfooter.lua:1297,1299> (6 instructions, 24 bytes at 0x7fd3a0c20fd0)
0 params, 2 slots, 1 upvalue, 0 locals, 2 constants, 0 functions
	1	[1298]	GETUPVAL 	0 0	; self
	2	[1298]	GETTABLE 	0 0 -1	; "settings"
	3	[1298]	GETTABLE 	0 0 -2	; "progress_style_thin"
	4	[1298]	NOT      	0 0
	5	[1298]	RETURN   	0 2
	6	[1299]	RETURN   	0 1

function <./frontend/apps/reader/modules/readerfooter.lua:1300,1306> (24 instructions, 96 bytes at 0x7fd3a0c21680)
0 params, 5 slots, 2 upvalues, 1 local, 8 constants, 0 functions
	1	[1301]	GETUPVAL 	0 0	; self
	2	[1301]	GETTABLE 	0 0 -1	; "settings"
	3	[1301]	SETTABLE 	0 -2 -3	; "progress_style_thin" nil
	4	[1302]	GETUPVAL 	0 0	; self
	5	[1302]	GETTABLE 	0 0 -1	; "settings"
	6	[1302]	GETTABLE 	0 0 -4	; "progress_style_thick_height"
	7	[1302]	TEST     	0 0 1
	8	[1302]	JMP      	1	; to 10
	9	[1302]	GETUPVAL 	0 1	; PROGRESS_BAR_STYLE_THICK_DEFAULT_HEIGHT
	10	[1303]	GETUPVAL 	1 0	; self
	11	[1303]	GETTABLE 	1 1 -5	; "progress_bar"
	12	[1303]	SELF     	1 1 -6	; "updateStyle"
	13	[1303]	LOADBOOL 	3 1 0
	14	[1303]	MOVE     	4 0
	15	[1303]	CALL     	1 4 1
	16	[1304]	GETUPVAL 	1 0	; self
	17	[1304]	SELF     	1 1 -7	; "setTocMarkers"
	18	[1304]	CALL     	1 2 1
	19	[1305]	GETUPVAL 	1 0	; self
	20	[1305]	SELF     	1 1 -8	; "refreshFooter"
	21	[1305]	LOADBOOL 	3 1 0
	22	[1305]	LOADBOOL 	4 1 0
	23	[1305]	CALL     	1 4 1
	24	[1306]	RETURN   	0 1

function <./frontend/apps/reader/modules/readerfooter.lua:1310,1312> (5 instructions, 20 bytes at 0x7fd3a0c21ae0)
0 params, 2 slots, 1 upvalue, 0 locals, 2 constants, 0 functions
	1	[1311]	GETUPVAL 	0 0	; self
	2	[1311]	GETTABLE 	0 0 -1	; "settings"
	3	[1311]	GETTABLE 	0 0 -2	; "progress_style_thin"
	4	[1311]	RETURN   	0 2
	5	[1312]	RETURN   	0 1

function <./frontend/apps/reader/modules/readerfooter.lua:1313,1318> (21 instructions, 84 bytes at 0x7fd3a0c21e20)
0 params, 5 slots, 2 upvalues, 1 local, 7 constants, 0 functions
	1	[1314]	GETUPVAL 	0 0	; self
	2	[1314]	GETTABLE 	0 0 -1	; "settings"
	3	[1314]	SETTABLE 	0 -2 -3	; "progress_style_thin" true
	4	[1315]	GETUPVAL 	0 0	; self
	5	[1315]	GETTABLE 	0 0 -1	; "settings"
	6	[1315]	GETTABLE 	0 0 -4	; "progress_style_thin_height"
	7	[1315]	TEST     	0 0 1
	8	[1315]	JMP      	1	; to 10
	9	[1315]	GETUPVAL 	0 1	; PROGRESS_BAR_STYLE_THIN_DEFAULT_HEIGHT
	10	[1316]	GETUPVAL 	1 0	; self
	11	[1316]	GETTABLE 	1 1 -5	; "progress_bar"
	12	[1316]	SELF     	1 1 -6	; "updateStyle"
	13	[1316]	LOADBOOL 	3 0 0
	14	[1316]	MOVE     	4 0
	15	[1316]	CALL     	1 4 1
	16	[1317]	GETUPVAL 	1 0	; self
	17	[1317]	SELF     	1 1 -7	; "refreshFooter"
	18	[1317]	LOADBOOL 	3 1 0
	19	[1317]	LOADBOOL 	4 1 0
	20	[1317]	CALL     	1 4 1
	21	[1318]	RETURN   	0 1

function <./frontend/apps/reader/modules/readerfooter.lua:1322,1356> (54 instructions, 216 bytes at 0x7fd3a0c22590)
0 params, 10 slots, 6 upvalues, 6 locals, 27 constants, 1 function
	1	[1324]	GETUPVAL 	4 0	; self
	2	[1324]	GETTABLE 	4 4 -1	; "settings"
	3	[1324]	GETTABLE 	4 4 -2	; "progress_style_thin"
	4	[1324]	TEST     	4 0 0
	5	[1324]	JMP      	10	; to 16
	6	[1325]	GETUPVAL 	3 1	; PROGRESS_BAR_STYLE_THIN_DEFAULT_HEIGHT
	7	[1326]	GETUPVAL 	4 0	; self
	8	[1326]	GETTABLE 	4 4 -1	; "settings"
	9	[1326]	GETTABLE 	4 4 -3	; "progress_style_thin_height"
	10	[1326]	TESTSET  	0 4 1
	11	[1326]	JMP      	1	; to 13
	12	[1326]	MOVE     	0 3
	13	[1327]	LOADK    	1 -4	; 1
	14	[1328]	LOADK    	2 -5	; 4
	15	[1328]	JMP      	9	; to 25
	16	[1330]	GETUPVAL 	3 2	; PROGRESS_BAR_STYLE_THICK_DEFAULT_HEIGHT
	17	[1331]	GETUPVAL 	4 0	; self
	18	[1331]	GETTABLE 	4 4 -1	; "settings"
	19	[1331]	GETTABLE 	4 4 -6	; "progress_style_thick_height"
	20	[1331]	TESTSET  	0 4 1
	21	[1331]	JMP      	1	; to 23
	22	[1331]	MOVE     	0 3
	23	[1332]	LOADK    	1 -7	; 5
	24	[1333]	LOADK    	2 -8	; 14
	25	[1335]	GETGLOBAL	4 -9	; require
	26	[1335]	LOADK    	5 -10	; "ui/widget/spinwidget"
	27	[1335]	CALL     	4 2 2
	28	[1336]	SELF     	5 4 -11	; "new"
	29	[1336]	NEWTABLE 	7 0 10
	30	[1337]	GETUPVAL 	8 3	; Screen
	31	[1337]	SELF     	8 8 -13	; "getWidth"
	32	[1337]	CALL     	8 2 2
	33	[1337]	MUL      	8 8 -14	; - 0.6
	34	[1337]	SETTABLE 	7 -12 8	; "width" -
	35	[1338]	SETTABLE 	7 -15 0	; "value" -
	36	[1339]	SETTABLE 	7 -16 1	; "value_min" -
	37	[1340]	SETTABLE 	7 -17 -4	; "value_step" 1
	38	[1341]	SETTABLE 	7 -18 -19	; "value_hold_step" 2
	39	[1342]	SETTABLE 	7 -20 2	; "value_max" -
	40	[1343]	SETTABLE 	7 -21 3	; "default_value" -
	41	[1344]	GETUPVAL 	8 4	; _
	42	[1344]	LOADK    	9 -23	; "Progress bar size"
	43	[1344]	CALL     	8 2 2
	44	[1344]	SETTABLE 	7 -22 8	; "title_text" -
	45	[1345]	SETTABLE 	7 -24 -25	; "keep_shown_on_apply" true
	46	[1353]	CLOSURE  	8 0	; 0x7fd3a0c228b0
	47	[1353]	GETUPVAL 	0 0	; self
	48	[1353]	SETTABLE 	7 -26 8	; "callback" -
	49	[1336]	CALL     	5 3 2
	50	[1355]	GETUPVAL 	6 5	; UIManager
	51	[1355]	SELF     	6 6 -27	; "show"
	52	[1355]	MOVE     	8 5
	53	[1355]	CALL     	6 3 1
	54	[1356]	RETURN   	0 1

function <./frontend/apps/reader/modules/readerfooter.lua:1346,1353> (20 instructions, 80 bytes at 0x7fd3a0c228b0)
1 param, 5 slots, 1 upvalue, 1 local, 6 constants, 0 functions
	1	[1347]	GETUPVAL 	1 0	; self
	2	[1347]	GETTABLE 	1 1 -1	; "settings"
	3	[1347]	GETTABLE 	1 1 -2	; "progress_style_thin"
	4	[1347]	TEST     	1 0 0
	5	[1347]	JMP      	5	; to 11
	6	[1348]	GETUPVAL 	1 0	; self
	7	[1348]	GETTABLE 	1 1 -1	; "settings"
	8	[1348]	GETTABLE 	2 0 -4	; "value"
	9	[1348]	SETTABLE 	1 -3 2	; "progress_style_thin_height" -
	10	[1348]	JMP      	4	; to 15
	11	[1350]	GETUPVAL 	1 0	; self
	12	[1350]	GETTABLE 	1 1 -1	; "settings"
	13	[1350]	GETTABLE 	2 0 -4	; "value"
	14	[1350]	SETTABLE 	1 -5 2	; "progress_style_thick_height" -
	15	[1352]	GETUPVAL 	1 0	; self
	16	[1352]	SELF     	1 1 -6	; "refreshFooter"
	17	[1352]	LOADBOOL 	3 1 0
	18	[1352]	LOADBOOL 	4 1 0
	19	[1352]	CALL     	1 4 1
	20	[1353]	RETURN   	0 1

function <./frontend/apps/reader/modules/readerfooter.lua:1362,1364> (5 instructions, 20 bytes at 0x7fd3a0c22df0)
0 params, 2 slots, 1 upvalue, 0 locals, 2 constants, 0 functions
	1	[1363]	GETUPVAL 	0 0	; self
	2	[1363]	GETTABLE 	0 0 -1	; "settings"
	3	[1363]	GETTABLE 	0 0 -2	; "toc_markers"
	4	[1363]	RETURN   	0 2
	5	[1364]	RETURN   	0 1

function <./frontend/apps/reader/modules/readerfooter.lua:1365,1367> (6 instructions, 24 bytes at 0x7fd3a0c23110)
0 params, 2 slots, 1 upvalue, 0 locals, 2 constants, 0 functions
	1	[1366]	GETUPVAL 	0 0	; self
	2	[1366]	GETTABLE 	0 0 -1	; "settings"
	3	[1366]	GETTABLE 	0 0 -2	; "progress_style_thin"
	4	[1366]	NOT      	0 0
	5	[1366]	RETURN   	0 2
	6	[1367]	RETURN   	0 1

function <./frontend/apps/reader/modules/readerfooter.lua:1368,1372> (15 instructions, 60 bytes at 0x7fd3a0c23360)
0 params, 3 slots, 1 upvalue, 0 locals, 4 constants, 0 functions
	1	[1369]	GETUPVAL 	0 0	; self
	2	[1369]	GETTABLE 	0 0 -1	; "settings"
	3	[1369]	GETUPVAL 	1 0	; self
	4	[1369]	GETTABLE 	1 1 -1	; "settings"
	5	[1369]	GETTABLE 	1 1 -2	; "toc_markers"
	6	[1369]	NOT      	1 1
	7	[1369]	SETTABLE 	0 -2 1	; "toc_markers" -
	8	[1370]	GETUPVAL 	0 0	; self
	9	[1370]	SELF     	0 0 -3	; "setTocMarkers"
	10	[1370]	CALL     	0 2 1
	11	[1371]	GETUPVAL 	0 0	; self
	12	[1371]	SELF     	0 0 -4	; "refreshFooter"
	13	[1371]	LOADBOOL 	2 1 0
	14	[1371]	CALL     	0 3 1
	15	[1372]	RETURN   	0 1

function <./frontend/apps/reader/modules/readerfooter.lua:1375,1383> (30 instructions, 120 bytes at 0x7fd3a0c23860)
0 params, 4 slots, 3 upvalues, 1 local, 8 constants, 0 functions
	1	[1376]	GETUPVAL 	0 0	; _
	2	[1376]	LOADK    	1 -1	; "thick"
	3	[1376]	CALL     	0 2 2
	4	[1377]	GETUPVAL 	1 1	; self
	5	[1377]	GETTABLE 	1 1 -2	; "settings"
	6	[1377]	GETTABLE 	1 1 -3	; "toc_markers_width"
	7	[1377]	EQ       	0 1 -4	; - 1
	8	[1377]	JMP      	5	; to 14
	9	[1378]	GETUPVAL 	1 0	; _
	10	[1378]	LOADK    	2 -5	; "thin"
	11	[1378]	CALL     	1 2 2
	12	[1378]	MOVE     	0 1
	13	[1378]	JMP      	9	; to 23
	14	[1379]	GETUPVAL 	1 1	; self
	15	[1379]	GETTABLE 	1 1 -2	; "settings"
	16	[1379]	GETTABLE 	1 1 -3	; "toc_markers_width"
	17	[1379]	EQ       	0 1 -6	; - 2
	18	[1379]	JMP      	4	; to 23
	19	[1380]	GETUPVAL 	1 0	; _
	20	[1380]	LOADK    	2 -7	; "medium"
	21	[1380]	CALL     	1 2 2
	22	[1380]	MOVE     	0 1
	23	[1382]	GETUPVAL 	1 2	; T
	24	[1382]	GETUPVAL 	2 0	; _
	25	[1382]	LOADK    	3 -8	; "Chapter marker width (%1)"
	26	[1382]	CALL     	2 2 2
	27	[1382]	MOVE     	3 0
	28	[1382]	TAILCALL 	1 3 0
	29	[1382]	RETURN   	1 0
	30	[1383]	RETURN   	0 1

function <./frontend/apps/reader/modules/readerfooter.lua:1384,1386> (13 instructions, 52 bytes at 0x7fd3a0c23b70)
0 params, 2 slots, 1 upvalue, 0 locals, 3 constants, 0 functions
	1	[1385]	GETUPVAL 	0 0	; self
	2	[1385]	GETTABLE 	0 0 -1	; "settings"
	3	[1385]	GETTABLE 	0 0 -2	; "progress_style_thin"
	4	[1385]	TEST     	0 0 1
	5	[1385]	JMP      	4	; to 10
	6	[1385]	GETUPVAL 	0 0	; self
	7	[1385]	GETTABLE 	0 0 -1	; "settings"
	8	[1385]	GETTABLE 	0 0 -3	; "toc_markers"
	9	[1385]	JMP      	2	; to 12
	10	[1385]	LOADBOOL 	0 0 1
	11	[1385]	LOADBOOL 	0 1 0
	12	[1385]	RETURN   	0 2
	13	[1386]	RETURN   	0 1

function <./frontend/apps/reader/modules/readerfooter.lua:1390,1392> (9 instructions, 36 bytes at 0x7fd3a0c23d60)
0 params, 2 slots, 1 upvalue, 0 locals, 3 constants, 0 functions
	1	[1391]	GETUPVAL 	0 0	; self
	2	[1391]	GETTABLE 	0 0 -1	; "settings"
	3	[1391]	GETTABLE 	0 0 -2	; "toc_markers_width"
	4	[1391]	EQ       	1 0 -3	; - 1
	5	[1391]	JMP      	1	; to 7
	6	[1391]	LOADBOOL 	0 0 1
	7	[1391]	LOADBOOL 	0 1 0
	8	[1391]	RETURN   	0 2
	9	[1392]	RETURN   	0 1

function <./frontend/apps/reader/modules/readerfooter.lua:1393,1397> (11 instructions, 44 bytes at 0x7fd3a0c24410)
0 params, 3 slots, 1 upvalue, 0 locals, 5 constants, 0 functions
	1	[1394]	GETUPVAL 	0 0	; self
	2	[1394]	GETTABLE 	0 0 -1	; "settings"
	3	[1394]	SETTABLE 	0 -2 -3	; "toc_markers_width" 1
	4	[1395]	GETUPVAL 	0 0	; self
	5	[1395]	SELF     	0 0 -4	; "setTocMarkers"
	6	[1395]	CALL     	0 2 1
	7	[1396]	GETUPVAL 	0 0	; self
	8	[1396]	SELF     	0 0 -5	; "refreshFooter"
	9	[1396]	LOADBOOL 	2 1 0
	10	[1396]	CALL     	0 3 1
	11	[1397]	RETURN   	0 1

function <./frontend/apps/reader/modules/readerfooter.lua:1401,1403> (9 instructions, 36 bytes at 0x7fd3a0c245a0)
0 params, 2 slots, 1 upvalue, 0 locals, 3 constants, 0 functions
	1	[1402]	GETUPVAL 	0 0	; self
	2	[1402]	GETTABLE 	0 0 -1	; "settings"
	3	[1402]	GETTABLE 	0 0 -2	; "toc_markers_width"
	4	[1402]	EQ       	1 0 -3	; - 2
	5	[1402]	JMP      	1	; to 7
	6	[1402]	LOADBOOL 	0 0 1
	7	[1402]	LOADBOOL 	0 1 0
	8	[1402]	RETURN   	0 2
	9	[1403]	RETURN   	0 1

function <./frontend/apps/reader/modules/readerfooter.lua:1404,1408> (11 instructions, 44 bytes at 0x7fd3a0c24a10)
0 params, 3 slots, 1 upvalue, 0 locals, 5 constants, 0 functions
	1	[1405]	GETUPVAL 	0 0	; self
	2	[1405]	GETTABLE 	0 0 -1	; "settings"
	3	[1405]	SETTABLE 	0 -2 -3	; "toc_markers_width" 2
	4	[1406]	GETUPVAL 	0 0	; self
	5	[1406]	SELF     	0 0 -4	; "setTocMarkers"
	6	[1406]	CALL     	0 2 1
	7	[1407]	GETUPVAL 	0 0	; self
	8	[1407]	SELF     	0 0 -5	; "refreshFooter"
	9	[1407]	LOADBOOL 	2 1 0
	10	[1407]	CALL     	0 3 1
	11	[1408]	RETURN   	0 1

function <./frontend/apps/reader/modules/readerfooter.lua:1412,1414> (9 instructions, 36 bytes at 0x7fd3a0c24d00)
0 params, 2 slots, 1 upvalue, 0 locals, 3 constants, 0 functions
	1	[1413]	GETUPVAL 	0 0	; self
	2	[1413]	GETTABLE 	0 0 -1	; "settings"
	3	[1413]	GETTABLE 	0 0 -2	; "toc_markers_width"
	4	[1413]	EQ       	1 0 -3	; - 3
	5	[1413]	JMP      	1	; to 7
	6	[1413]	LOADBOOL 	0 0 1
	7	[1413]	LOADBOOL 	0 1 0
	8	[1413]	RETURN   	0 2
	9	[1414]	RETURN   	0 1

function <./frontend/apps/reader/modules/readerfooter.lua:1415,1419> (11 instructions, 44 bytes at 0x7fd3a0c24e60)
0 params, 3 slots, 1 upvalue, 0 locals, 5 constants, 0 functions
	1	[1416]	GETUPVAL 	0 0	; self
	2	[1416]	GETTABLE 	0 0 -1	; "settings"
	3	[1416]	SETTABLE 	0 -2 -3	; "toc_markers_width" 3
	4	[1417]	GETUPVAL 	0 0	; self
	5	[1417]	SELF     	0 0 -4	; "setTocMarkers"
	6	[1417]	CALL     	0 2 1
	7	[1418]	GETUPVAL 	0 0	; self
	8	[1418]	SELF     	0 0 -5	; "refreshFooter"
	9	[1418]	LOADBOOL 	2 1 0
	10	[1418]	CALL     	0 3 1
	11	[1419]	RETURN   	0 1

function <./frontend/apps/reader/modules/readerfooter.lua:1426,1435> (44 instructions, 176 bytes at 0x7fd3a0c25310)
0 params, 5 slots, 4 upvalues, 1 local, 14 constants, 0 functions
	1	[1427]	GETUPVAL 	0 0	; _
	2	[1427]	LOADK    	1 -1	; "static margins (10)"
	3	[1427]	CALL     	0 2 2
	4	[1428]	GETUPVAL 	1 1	; self
	5	[1428]	GETTABLE 	1 1 -2	; "settings"
	6	[1428]	GETTABLE 	1 1 -3	; "progress_margin_width"
	7	[1428]	GETUPVAL 	2 2	; Screen
	8	[1428]	SELF     	2 2 -4	; "scaleBySize"
	9	[1428]	LOADK    	4 -5	; 0
	10	[1428]	CALL     	2 3 2
	11	[1428]	EQ       	0 1 2
	12	[1428]	JMP      	4	; to 17
	13	[1429]	GETUPVAL 	1 0	; _
	14	[1429]	LOADK    	2 -6	; "no margins (0)"
	15	[1429]	CALL     	1 2 2
	16	[1429]	MOVE     	0 1
	17	[1431]	GETUPVAL 	1 1	; self
	18	[1431]	GETTABLE 	1 1 -2	; "settings"
	19	[1431]	GETTABLE 	1 1 -7	; "progress_margin"
	20	[1431]	TEST     	1 0 0
	21	[1431]	JMP      	15	; to 37
	22	[1431]	GETUPVAL 	1 1	; self
	23	[1431]	GETTABLE 	1 1 -8	; "ui"
	24	[1431]	GETTABLE 	1 1 -9	; "document"
	25	[1431]	GETTABLE 	1 1 -10	; "info"
	26	[1431]	GETTABLE 	1 1 -11	; "has_pages"
	27	[1431]	TEST     	1 0 1
	28	[1431]	JMP      	8	; to 37
	29	[1432]	GETUPVAL 	1 3	; T
	30	[1432]	GETUPVAL 	2 0	; _
	31	[1432]	LOADK    	3 -12	; "same as book margins (%1)"
	32	[1432]	CALL     	2 2 2
	33	[1432]	GETUPVAL 	3 1	; self
	34	[1432]	GETTABLE 	3 3 -13	; "book_margins_footer_width"
	35	[1432]	CALL     	1 3 2
	36	[1432]	MOVE     	0 1
	37	[1434]	GETUPVAL 	1 3	; T
	38	[1434]	GETUPVAL 	2 0	; _
	39	[1434]	LOADK    	3 -14	; "Margins: %1"
	40	[1434]	CALL     	2 2 2
	41	[1434]	MOVE     	3 0
	42	[1434]	TAILCALL 	1 3 0
	43	[1434]	RETURN   	1 0
	44	[1435]	RETURN   	0 1

function <./frontend/apps/reader/modules/readerfooter.lua:1436,1438> (6 instructions, 24 bytes at 0x7fd3a0c25630)
0 params, 2 slots, 1 upvalue, 0 locals, 2 constants, 0 functions
	1	[1437]	GETUPVAL 	0 0	; self
	2	[1437]	GETTABLE 	0 0 -1	; "settings"
	3	[1437]	GETTABLE 	0 0 -2	; "disable_progress_bar"
	4	[1437]	NOT      	0 0
	5	[1437]	RETURN   	0 2
	6	[1438]	RETURN   	0 1

function <./frontend/apps/reader/modules/readerfooter.lua:1442,1445> (18 instructions, 72 bytes at 0x7fd3a0c255a0)
0 params, 4 slots, 2 upvalues, 0 locals, 5 constants, 0 functions
	1	[1443]	GETUPVAL 	0 0	; self
	2	[1443]	GETTABLE 	0 0 -1	; "settings"
	3	[1443]	GETTABLE 	0 0 -2	; "progress_margin_width"
	4	[1443]	GETUPVAL 	1 1	; Screen
	5	[1443]	SELF     	1 1 -3	; "scaleBySize"
	6	[1443]	LOADK    	3 -4	; 0
	7	[1443]	CALL     	1 3 2
	8	[1443]	EQ       	0 0 1
	9	[1443]	JMP      	5	; to 15
	10	[1444]	GETUPVAL 	0 0	; self
	11	[1444]	GETTABLE 	0 0 -1	; "settings"
	12	[1444]	GETTABLE 	0 0 -5	; "progress_margin"
	13	[1444]	NOT      	0 0
	14	[1444]	JMP      	2	; to 17
	15	[1444]	LOADBOOL 	0 0 1
	16	[1444]	LOADBOOL 	0 1 0
	17	[1444]	RETURN   	0 2
	18	[1445]	RETURN   	0 1

function <./frontend/apps/reader/modules/readerfooter.lua:1446,1450> (15 instructions, 60 bytes at 0x7fd3a0c25e10)
0 params, 4 slots, 2 upvalues, 0 locals, 7 constants, 0 functions
	1	[1447]	GETUPVAL 	0 0	; self
	2	[1447]	GETTABLE 	0 0 -1	; "settings"
	3	[1447]	GETUPVAL 	1 1	; Screen
	4	[1447]	SELF     	1 1 -3	; "scaleBySize"
	5	[1447]	LOADK    	3 -4	; 0
	6	[1447]	CALL     	1 3 2
	7	[1447]	SETTABLE 	0 -2 1	; "progress_margin_width" -
	8	[1448]	GETUPVAL 	0 0	; self
	9	[1448]	GETTABLE 	0 0 -1	; "settings"
	10	[1448]	SETTABLE 	0 -5 -6	; "progress_margin" false
	11	[1449]	GETUPVAL 	0 0	; self
	12	[1449]	SELF     	0 0 -7	; "refreshFooter"
	13	[1449]	LOADBOOL 	2 1 0
	14	[1449]	CALL     	0 3 1
	15	[1450]	RETURN   	0 1

function <./frontend/apps/reader/modules/readerfooter.lua:1454,1459> (29 instructions, 116 bytes at 0x7fd3a0c261e0)
0 params, 4 slots, 2 upvalues, 0 locals, 9 constants, 0 functions
	1	[1455]	GETUPVAL 	0 0	; self
	2	[1455]	GETTABLE 	0 0 -1	; "settings"
	3	[1455]	GETTABLE 	0 0 -2	; "progress_margin_width"
	4	[1455]	GETUPVAL 	1 1	; Screen
	5	[1455]	SELF     	1 1 -3	; "scaleBySize"
	6	[1455]	LOADK    	3 -4	; 10
	7	[1455]	CALL     	1 3 2
	8	[1455]	EQ       	0 0 1
	9	[1455]	JMP      	5	; to 15
	10	[1456]	GETUPVAL 	0 0	; self
	11	[1456]	GETTABLE 	0 0 -1	; "settings"
	12	[1456]	GETTABLE 	0 0 -5	; "progress_margin"
	13	[1458]	TEST     	0 0 0
	14	[1458]	JMP      	12	; to 27
	15	[1458]	GETUPVAL 	0 0	; self
	16	[1458]	GETTABLE 	0 0 -6	; "ui"
	17	[1458]	GETTABLE 	0 0 -7	; "document"
	18	[1458]	GETTABLE 	0 0 -8	; "info"
	19	[1458]	GETTABLE 	0 0 -9	; "has_pages"
	20	[1458]	TEST     	0 0 0
	21	[1458]	JMP      	6	; to 28
	22	[1458]	GETUPVAL 	0 0	; self
	23	[1458]	GETTABLE 	0 0 -1	; "settings"
	24	[1458]	GETTABLE 	0 0 -5	; "progress_margin"
	25	[1458]	JMP      	2	; to 28
	26	[1458]	LOADBOOL 	0 0 1
	27	[1458]	LOADBOOL 	0 1 0
	28	[1458]	RETURN   	0 2
	29	[1459]	RETURN   	0 1

function <./frontend/apps/reader/modules/readerfooter.lua:1460,1464> (15 instructions, 60 bytes at 0x7fd3a0c26680)
0 params, 4 slots, 2 upvalues, 0 locals, 7 constants, 0 functions
	1	[1461]	GETUPVAL 	0 0	; self
	2	[1461]	GETTABLE 	0 0 -1	; "settings"
	3	[1461]	GETUPVAL 	1 1	; Screen
	4	[1461]	SELF     	1 1 -3	; "scaleBySize"
	5	[1461]	LOADK    	3 -4	; 10
	6	[1461]	CALL     	1 3 2
	7	[1461]	SETTABLE 	0 -2 1	; "progress_margin_width" -
	8	[1462]	GETUPVAL 	0 0	; self
	9	[1462]	GETTABLE 	0 0 -1	; "settings"
	10	[1462]	SETTABLE 	0 -5 -6	; "progress_margin" false
	11	[1463]	GETUPVAL 	0 0	; self
	12	[1463]	SELF     	0 0 -7	; "refreshFooter"
	13	[1463]	LOADBOOL 	2 1 0
	14	[1463]	CALL     	0 3 1
	15	[1464]	RETURN   	0 1

function <./frontend/apps/reader/modules/readerfooter.lua:1467,1472> (20 instructions, 80 bytes at 0x7fd3a0c26c00)
0 params, 3 slots, 3 upvalues, 0 locals, 7 constants, 0 functions
	1	[1468]	GETUPVAL 	0 0	; self
	2	[1468]	GETTABLE 	0 0 -1	; "ui"
	3	[1468]	GETTABLE 	0 0 -2	; "document"
	4	[1468]	GETTABLE 	0 0 -3	; "info"
	5	[1468]	GETTABLE 	0 0 -4	; "has_pages"
	6	[1468]	TEST     	0 0 0
	7	[1468]	JMP      	4	; to 12
	8	[1469]	GETUPVAL 	0 1	; _
	9	[1469]	LOADK    	1 -5	; "Same as book margins"
	10	[1469]	TAILCALL 	0 2 0
	11	[1469]	RETURN   	0 0
	12	[1471]	GETUPVAL 	0 2	; T
	13	[1471]	GETUPVAL 	1 1	; _
	14	[1471]	LOADK    	2 -6	; "Same as book margins (%1)"
	15	[1471]	CALL     	1 2 2
	16	[1471]	GETUPVAL 	2 0	; self
	17	[1471]	GETTABLE 	2 2 -7	; "book_margins_footer_width"
	18	[1471]	TAILCALL 	0 3 0
	19	[1471]	RETURN   	0 0
	20	[1472]	RETURN   	0 1

function <./frontend/apps/reader/modules/readerfooter.lua:1473,1475> (13 instructions, 52 bytes at 0x7fd3a0c274c0)
0 params, 2 slots, 1 upvalue, 0 locals, 6 constants, 0 functions
	1	[1474]	GETUPVAL 	0 0	; self
	2	[1474]	GETTABLE 	0 0 -1	; "settings"
	3	[1474]	GETTABLE 	0 0 -2	; "progress_margin"
	4	[1474]	TEST     	0 0 0
	5	[1474]	JMP      	6	; to 12
	6	[1474]	GETUPVAL 	0 0	; self
	7	[1474]	GETTABLE 	0 0 -3	; "ui"
	8	[1474]	GETTABLE 	0 0 -4	; "document"
	9	[1474]	GETTABLE 	0 0 -5	; "info"
	10	[1474]	GETTABLE 	0 0 -6	; "has_pages"
	11	[1474]	NOT      	0 0
	12	[1474]	RETURN   	0 2
	13	[1475]	RETURN   	0 1

function <./frontend/apps/reader/modules/readerfooter.lua:1476,1478> (16 instructions, 64 bytes at 0x7fd3a0c27540)
0 params, 2 slots, 1 upvalue, 0 locals, 7 constants, 0 functions
	1	[1477]	GETUPVAL 	0 0	; self
	2	[1477]	GETTABLE 	0 0 -1	; "ui"
	3	[1477]	GETTABLE 	0 0 -2	; "document"
	4	[1477]	GETTABLE 	0 0 -3	; "info"
	5	[1477]	GETTABLE 	0 0 -4	; "has_pages"
	6	[1477]	TEST     	0 0 1
	7	[1477]	JMP      	5	; to 13
	8	[1477]	GETUPVAL 	0 0	; self
	9	[1477]	GETTABLE 	0 0 -5	; "settings"
	10	[1477]	GETTABLE 	0 0 -6	; "progress_bar_position"
	11	[1477]	EQ       	0 0 -7	; - nil
	12	[1477]	JMP      	1	; to 14
	13	[1477]	LOADBOOL 	0 0 1
	14	[1477]	LOADBOOL 	0 1 0
	15	[1477]	RETURN   	0 2
	16	[1478]	RETURN   	0 1

function <./frontend/apps/reader/modules/readerfooter.lua:1479,1483> (16 instructions, 64 bytes at 0x7fd3a0c27a20)
0 params, 4 slots, 2 upvalues, 0 locals, 7 constants, 0 functions
	1	[1480]	GETUPVAL 	0 0	; self
	2	[1480]	GETTABLE 	0 0 -1	; "settings"
	3	[1480]	SETTABLE 	0 -2 -3	; "progress_margin" true
	4	[1481]	GETUPVAL 	0 0	; self
	5	[1481]	GETTABLE 	0 0 -1	; "settings"
	6	[1481]	GETUPVAL 	1 1	; Screen
	7	[1481]	SELF     	1 1 -5	; "scaleBySize"
	8	[1481]	GETUPVAL 	3 0	; self
	9	[1481]	GETTABLE 	3 3 -6	; "book_margins_footer_width"
	10	[1481]	CALL     	1 3 2
	11	[1481]	SETTABLE 	0 -4 1	; "progress_margin_width" -
	12	[1482]	GETUPVAL 	0 0	; self
	13	[1482]	SELF     	0 0 -7	; "refreshFooter"
	14	[1482]	LOADBOOL 	2 1 0
	15	[1482]	CALL     	0 3 1
	16	[1483]	RETURN   	0 1

function <./frontend/apps/reader/modules/readerfooter.lua:1488,1490> (10 instructions, 40 bytes at 0x7fd3a0c27e80)
0 params, 3 slots, 3 upvalues, 0 locals, 3 constants, 0 functions
	1	[1489]	GETUPVAL 	0 0	; T
	2	[1489]	GETUPVAL 	1 1	; _
	3	[1489]	LOADK    	2 -1	; "Minimal width (%1%)"
	4	[1489]	CALL     	1 2 2
	5	[1489]	GETUPVAL 	2 2	; self
	6	[1489]	GETTABLE 	2 2 -2	; "settings"
	7	[1489]	GETTABLE 	2 2 -3	; "progress_bar_min_width_pct"
	8	[1489]	TAILCALL 	0 3 0
	9	[1489]	RETURN   	0 0
	10	[1490]	RETURN   	0 1

function <./frontend/apps/reader/modules/readerfooter.lua:1491,1494> (18 instructions, 72 bytes at 0x7fd3a0c28480)
0 params, 2 slots, 1 upvalue, 0 locals, 4 constants, 0 functions
	1	[1492]	GETUPVAL 	0 0	; self
	2	[1492]	GETTABLE 	0 0 -1	; "settings"
	3	[1492]	GETTABLE 	0 0 -2	; "progress_bar_position"
	4	[1492]	TEST     	0 0 1
	5	[1492]	JMP      	9	; to 15
	6	[1492]	GETUPVAL 	0 0	; self
	7	[1492]	GETTABLE 	0 0 -1	; "settings"
	8	[1492]	GETTABLE 	0 0 -3	; "disable_progress_bar"
	9	[1493]	TEST     	0 0 1
	10	[1493]	JMP      	4	; to 15
	11	[1493]	GETUPVAL 	0 0	; self
	12	[1493]	GETTABLE 	0 0 -1	; "settings"
	13	[1493]	GETTABLE 	0 0 -4	; "all_at_once"
	14	[1493]	JMP      	2	; to 17
	15	[1493]	LOADBOOL 	0 0 1
	16	[1493]	LOADBOOL 	0 1 0
	17	[1493]	RETURN   	0 2
	18	[1494]	RETURN   	0 1

function <./frontend/apps/reader/modules/readerfooter.lua:1495,1514> (37 instructions, 148 bytes at 0x7fd3a0c286e0)
1 param, 7 slots, 4 upvalues, 3 locals, 24 constants, 1 function
	1	[1496]	GETGLOBAL	1 -1	; require
	2	[1496]	LOADK    	2 -2	; "ui/widget/spinwidget"
	3	[1496]	CALL     	1 2 2
	4	[1497]	SELF     	2 1 -3	; "new"
	5	[1497]	NEWTABLE 	4 0 10
	6	[1498]	GETUPVAL 	5 0	; Screen
	7	[1498]	SELF     	5 5 -5	; "getWidth"
	8	[1498]	CALL     	5 2 2
	9	[1498]	MUL      	5 5 -6	; - 0.6
	10	[1498]	SETTABLE 	4 -4 5	; "width" -
	11	[1499]	GETUPVAL 	5 1	; self
	12	[1499]	GETTABLE 	5 5 -8	; "settings"
	13	[1499]	GETTABLE 	5 5 -9	; "progress_bar_min_width_pct"
	14	[1499]	SETTABLE 	4 -7 5	; "value" -
	15	[1500]	SETTABLE 	4 -10 -11	; "value_min" 5
	16	[1501]	SETTABLE 	4 -12 -11	; "value_step" 5
	17	[1502]	SETTABLE 	4 -13 -14	; "value_hold_step" 20
	18	[1503]	SETTABLE 	4 -15 -16	; "value_max" 50
	19	[1504]	GETUPVAL 	5 2	; _
	20	[1504]	LOADK    	6 -18	; "Minimal width"
	21	[1504]	CALL     	5 2 2
	22	[1504]	SETTABLE 	4 -17 5	; "title_text" -
	23	[1505]	GETUPVAL 	5 2	; _
	24	[1505]	LOADK    	6 -20	; "Minimal progress bar width in percentage of screen width"
	25	[1505]	CALL     	5 2 2
	26	[1505]	SETTABLE 	4 -19 5	; "text" -
	27	[1506]	SETTABLE 	4 -21 -22	; "keep_shown_on_apply" true
	28	[1511]	CLOSURE  	5 0	; 0x7fd3a0c28ae0
	29	[1511]	GETUPVAL 	0 1	; self
	30	[1511]	MOVE     	0 0
	31	[1511]	SETTABLE 	4 -23 5	; "callback" -
	32	[1497]	CALL     	2 3 2
	33	[1513]	GETUPVAL 	3 3	; UIManager
	34	[1513]	SELF     	3 3 -24	; "show"
	35	[1513]	MOVE     	5 2
	36	[1513]	CALL     	3 3 1
	37	[1514]	RETURN   	0 1

function <./frontend/apps/reader/modules/readerfooter.lua:1507,1511> (16 instructions, 64 bytes at 0x7fd3a0c28ae0)
1 param, 5 slots, 2 upvalues, 1 local, 5 constants, 0 functions
	1	[1508]	GETUPVAL 	1 0	; self
	2	[1508]	GETTABLE 	1 1 -1	; "settings"
	3	[1508]	GETTABLE 	2 0 -3	; "value"
	4	[1508]	SETTABLE 	1 -2 2	; "progress_bar_min_width_pct" -
	5	[1509]	GETUPVAL 	1 0	; self
	6	[1509]	SELF     	1 1 -4	; "refreshFooter"
	7	[1509]	LOADBOOL 	3 1 0
	8	[1509]	LOADBOOL 	4 1 0
	9	[1509]	CALL     	1 4 1
	10	[1510]	GETUPVAL 	1 1	; touchmenu_instance
	11	[1510]	TEST     	1 0 0
	12	[1510]	JMP      	3	; to 16
	13	[1510]	GETUPVAL 	1 1	; touchmenu_instance
	14	[1510]	SELF     	1 1 -5	; "updateItems"
	15	[1510]	CALL     	1 2 1
	16	[1511]	RETURN   	0 1

function <./frontend/apps/reader/modules/readerfooter.lua:1538,1538> (1 instruction, 4 bytes at 0x7fd3a0c28be0)
1 param, 2 slots, 0 upvalues, 1 local, 0 constants, 0 functions
	1	[1538]	RETURN   	0 1

function <./frontend/apps/reader/modules/readerfooter.lua:1540,1555> (43 instructions, 172 bytes at 0x7fd3a0c29560)
1 param, 13 slots, 1 upvalue, 8 locals, 14 constants, 0 functions
	1	[1541]	NEWTABLE 	1 0 0
	2	[1542]	LOADK    	2 -1	; "  "
	3	[1543]	GETTABLE 	3 0 -2	; "settings"
	4	[1543]	GETTABLE 	3 3 -3	; "items_separator"
	5	[1543]	EQ       	1 3 -4	; - "bar"
	6	[1543]	JMP      	4	; to 11
	7	[1543]	GETTABLE 	3 0 -2	; "settings"
	8	[1543]	GETTABLE 	3 3 -3	; "items_separator"
	9	[1543]	EQ       	0 3 -5	; - nil
	10	[1543]	JMP      	2	; to 13
	11	[1544]	LOADK    	2 -6	; " | "
	12	[1544]	JMP      	5	; to 18
	13	[1545]	GETTABLE 	3 0 -2	; "settings"
	14	[1545]	GETTABLE 	3 3 -3	; "items_separator"
	15	[1545]	EQ       	0 3 -7	; - "bullet"
	16	[1545]	JMP      	1	; to 18
	17	[1546]	LOADK    	2 -8	; " \226\128\162 "
	18	[1551]	GETGLOBAL	3 -9	; ipairs
	19	[1551]	GETTABLE 	4 0 -10	; "footerTextGenerators"
	20	[1551]	CALL     	3 2 4
	21	[1551]	JMP      	10	; to 32
	22	[1552]	GETGLOBAL	8 -11	; table
	23	[1552]	GETTABLE 	8 8 -12	; "insert"
	24	[1552]	MOVE     	9 1
	25	[1552]	GETUPVAL 	10 0	; BD
	26	[1552]	GETTABLE 	10 10 -13	; "wrap"
	27	[1552]	MOVE     	11 7
	28	[1552]	MOVE     	12 0
	29	[1552]	CALL     	11 2 0
	30	[1552]	CALL     	10 0 0
	31	[1552]	CALL     	8 0 1
	32	[1551]	TFORLOOP 	3 2
	33	[1552]	JMP      	-12	; to 22
	34	[1554]	GETGLOBAL	3 -11	; table
	35	[1554]	GETTABLE 	3 3 -14	; "concat"
	36	[1554]	MOVE     	4 1
	37	[1554]	GETUPVAL 	5 0	; BD
	38	[1554]	GETTABLE 	5 5 -13	; "wrap"
	39	[1554]	MOVE     	6 2
	40	[1554]	CALL     	5 2 0
	41	[1554]	TAILCALL 	3 0 0
	42	[1554]	RETURN   	3 0
	43	[1555]	RETURN   	0 1

function <./frontend/apps/reader/modules/readerfooter.lua:1557,1590> (88 instructions, 352 bytes at 0x7fd3a0c29720)
2 params, 12 slots, 1 upvalue, 9 locals, 25 constants, 1 function
	1	[1558]	GETTABLE 	2 0 -1	; "settings"
	2	[1558]	GETTABLE 	2 2 -2	; "disable_progress_bar"
	3	[1558]	TEST     	2 0 1
	4	[1558]	JMP      	4	; to 9
	5	[1558]	GETTABLE 	2 0 -1	; "settings"
	6	[1558]	GETTABLE 	2 2 -3	; "progress_style_thin"
	7	[1558]	TEST     	2 0 0
	8	[1558]	JMP      	1	; to 10
	9	[1558]	RETURN   	0 1
	10	[1559]	TEST     	1 0 0
	11	[1559]	JMP      	7	; to 19
	12	[1560]	GETTABLE 	2 0 -4	; "progress_bar"
	13	[1560]	SETTABLE 	2 -5 -6	; "ticks" nil
	14	[1561]	GETTABLE 	2 0 -8	; "view"
	15	[1561]	GETTABLE 	2 2 -9	; "document"
	16	[1561]	SELF     	2 2 -10	; "getPageCount"
	17	[1561]	CALL     	2 2 2
	18	[1561]	SETTABLE 	0 -7 2	; "pages" -
	19	[1563]	GETTABLE 	2 0 -1	; "settings"
	20	[1563]	GETTABLE 	2 2 -11	; "toc_markers"
	21	[1563]	TEST     	2 0 0
	22	[1563]	JMP      	61	; to 84
	23	[1564]	GETTABLE 	2 0 -4	; "progress_bar"
	24	[1564]	GETUPVAL 	3 0	; Screen
	25	[1564]	SELF     	3 3 -13	; "scaleBySize"
	26	[1564]	GETTABLE 	5 0 -1	; "settings"
	27	[1564]	GETTABLE 	5 5 -14	; "toc_markers_width"
	28	[1564]	CALL     	3 3 2
	29	[1564]	SETTABLE 	2 -12 3	; "tick_width" -
	30	[1565]	GETTABLE 	2 0 -4	; "progress_bar"
	31	[1565]	GETTABLE 	2 2 -5	; "ticks"
	32	[1565]	EQ       	1 2 -6	; - nil
	33	[1565]	JMP      	1	; to 35
	34	[1565]	RETURN   	0 1
	35	[1566]	NEWTABLE 	2 0 0
	36	[1567]	GETTABLE 	3 0 -15	; "ui"
	37	[1567]	GETTABLE 	3 3 -16	; "toc"
	38	[1567]	TEST     	3 0 0
	39	[1567]	JMP      	24	; to 64
	40	[1568]	GETTABLE 	3 0 -15	; "ui"
	41	[1568]	GETTABLE 	3 3 -16	; "toc"
	42	[1568]	SELF     	3 3 -17	; "getMaxDepth"
	43	[1568]	CALL     	3 2 2
	44	[1569]	LOADK    	4 -18	; 0
	45	[1569]	UNM      	5 3
	46	[1569]	LOADK    	6 -19	; -1
	47	[1569]	FORPREP  	4 10	; to 58
	48	[1570]	GETTABLE 	8 0 -15	; "ui"
	49	[1570]	GETTABLE 	8 8 -16	; "toc"
	50	[1570]	SELF     	8 8 -20	; "getTocTicks"
	51	[1570]	MOVE     	10 7
	52	[1570]	CALL     	8 3 2
	53	[1571]	GETGLOBAL	9 -21	; table
	54	[1571]	GETTABLE 	9 9 -22	; "insert"
	55	[1571]	MOVE     	10 2
	56	[1571]	MOVE     	11 8
	57	[1571]	CALL     	9 3 1
	58	[1569]	FORLOOP  	4 -11	; to 48
	59	[1574]	GETGLOBAL	4 -21	; table
	60	[1574]	GETTABLE 	4 4 -23	; "sort"
	61	[1574]	MOVE     	5 2
	62	[1574]	CLOSURE  	6 0	; 0x7fd3a0c299c0
	63	[1574]	CALL     	4 3 1
	64	[1577]	LEN      	3 2
	65	[1577]	LT       	0 -18 3	; 0 -
	66	[1577]	JMP      	13	; to 80
	67	[1578]	GETTABLE 	3 0 -4	; "progress_bar"
	68	[1578]	GETTABLE 	4 2 -24	; 1
	69	[1578]	SETTABLE 	3 -5 4	; "ticks" -
	70	[1579]	GETTABLE 	3 0 -4	; "progress_bar"
	71	[1579]	GETTABLE 	4 0 -7	; "pages"
	72	[1579]	TEST     	4 0 1
	73	[1579]	JMP      	4	; to 78
	74	[1579]	GETTABLE 	4 0 -8	; "view"
	75	[1579]	GETTABLE 	4 4 -9	; "document"
	76	[1579]	SELF     	4 4 -10	; "getPageCount"
	77	[1579]	CALL     	4 2 2
	78	[1579]	SETTABLE 	3 -25 4	; "last" -
	79	[1579]	JMP      	6	; to 86
	80	[1583]	GETTABLE 	3 0 -4	; "progress_bar"
	81	[1583]	NEWTABLE 	4 0 0
	82	[1583]	SETTABLE 	3 -5 4	; "ticks" -
	83	[1584]	JMP      	2	; to 86
	84	[1586]	GETTABLE 	2 0 -4	; "progress_bar"
	85	[1586]	SETTABLE 	2 -5 -6	; "ticks" nil
	86	[1589]	LOADBOOL 	2 1 0
	87	[1589]	RETURN   	2 2
	88	[1590]	RETURN   	0 1

function <./frontend/apps/reader/modules/readerfooter.lua:1574,1574> (8 instructions, 32 bytes at 0x7fd3a0c299c0)
2 params, 4 slots, 0 upvalues, 2 locals, 0 constants, 0 functions
	1	[1574]	LEN      	2 0
	2	[1574]	LEN      	3 1
	3	[1574]	LT       	1 3 2
	4	[1574]	JMP      	1	; to 6
	5	[1574]	LOADBOOL 	2 0 1
	6	[1574]	LOADBOOL 	2 1 0
	7	[1574]	RETURN   	2 2
	8	[1574]	RETURN   	0 1

function <./frontend/apps/reader/modules/readerfooter.lua:1592,1594> (2 instructions, 8 bytes at 0x7fd3a0c29d70)
1 param, 2 slots, 0 upvalues, 1 local, 0 constants, 0 functions
	1	[1593]	RETURN   	0 1
	2	[1594]	RETURN   	0 1

function <./frontend/apps/reader/modules/readerfooter.lua:1596,1607> (27 instructions, 108 bytes at 0x7fd3a0c29ef0)
3 params, 8 slots, 1 upvalue, 5 locals, 7 constants, 0 functions
	1	[1597]	LOADK    	3 -1	; "na"
	2	[1598]	SELF     	4 0 -2	; "getAvgTimePerPage"
	3	[1598]	CALL     	4 2 2
	4	[1599]	TEST     	4 0 0
	5	[1599]	JMP      	17	; to 23
	6	[1600]	GETTABLE 	5 0 -3	; "settings"
	7	[1600]	GETTABLE 	5 5 -4	; "duration_format"
	8	[1600]	EQ       	0 5 -5	; - "classic"
	9	[1600]	JMP      	7	; to 17
	10	[1601]	GETUPVAL 	5 0	; util
	11	[1601]	GETTABLE 	5 5 -6	; "secondsToClock"
	12	[1601]	MUL      	6 2 4
	13	[1601]	LOADBOOL 	7 1 0
	14	[1601]	CALL     	5 3 2
	15	[1601]	MOVE     	3 5
	16	[1601]	JMP      	6	; to 23
	17	[1603]	GETUPVAL 	5 0	; util
	18	[1603]	GETTABLE 	5 5 -7	; "secondsToHClock"
	19	[1603]	MUL      	6 2 4
	20	[1603]	LOADBOOL 	7 1 0
	21	[1603]	CALL     	5 3 2
	22	[1603]	MOVE     	3 5
	23	[1606]	MOVE     	5 1
	24	[1606]	MOVE     	6 3
	25	[1606]	CONCAT   	5 5 6
	26	[1606]	RETURN   	5 2
	27	[1607]	RETURN   	0 1

function <./frontend/apps/reader/modules/readerfooter.lua:1609,1615> (13 instructions, 52 bytes at 0x7fd3a0c2aa60)
3 params, 7 slots, 0 upvalues, 3 locals, 3 constants, 0 functions
	1	[1610]	GETTABLE 	3 0 -1	; "pageno"
	2	[1610]	TEST     	3 0 0
	3	[1610]	JMP      	5	; to 9
	4	[1611]	SELF     	3 0 -2	; "updateFooterPage"
	5	[1611]	MOVE     	5 1
	6	[1611]	MOVE     	6 2
	7	[1611]	CALL     	3 4 1
	8	[1611]	JMP      	4	; to 13
	9	[1613]	SELF     	3 0 -3	; "updateFooterPos"
	10	[1613]	MOVE     	5 1
	11	[1613]	MOVE     	6 2
	12	[1613]	CALL     	3 4 1
	13	[1615]	RETURN   	0 1

function <./frontend/apps/reader/modules/readerfooter.lua:1617,1621> (16 instructions, 64 bytes at 0x7fd3a0c2ac70)
3 params, 7 slots, 0 upvalues, 3 locals, 7 constants, 0 functions
	1	[1618]	GETGLOBAL	3 -1	; type
	2	[1618]	GETTABLE 	4 0 -2	; "pageno"
	3	[1618]	CALL     	3 2 2
	4	[1618]	EQ       	1 3 -3	; - "number"
	5	[1618]	JMP      	1	; to 7
	6	[1618]	RETURN   	0 1
	7	[1619]	GETTABLE 	3 0 -4	; "progress_bar"
	8	[1619]	GETTABLE 	4 0 -2	; "pageno"
	9	[1619]	GETTABLE 	5 0 -6	; "pages"
	10	[1619]	DIV      	4 4 5
	11	[1619]	SETTABLE 	3 -5 4	; "percentage" -
	12	[1620]	SELF     	3 0 -7	; "updateFooterText"
	13	[1620]	MOVE     	5 1
	14	[1620]	MOVE     	6 2
	15	[1620]	CALL     	3 4 1
	16	[1621]	RETURN   	0 1

function <./frontend/apps/reader/modules/readerfooter.lua:1623,1627> (16 instructions, 64 bytes at 0x7fd3a0c2b160)
3 params, 7 slots, 0 upvalues, 3 locals, 7 constants, 0 functions
	1	[1624]	GETGLOBAL	3 -1	; type
	2	[1624]	GETTABLE 	4 0 -2	; "position"
	3	[1624]	CALL     	3 2 2
	4	[1624]	EQ       	1 3 -3	; - "number"
	5	[1624]	JMP      	1	; to 7
	6	[1624]	RETURN   	0 1
	7	[1625]	GETTABLE 	3 0 -4	; "progress_bar"
	8	[1625]	GETTABLE 	4 0 -2	; "position"
	9	[1625]	GETTABLE 	5 0 -6	; "doc_height"
	10	[1625]	DIV      	4 4 5
	11	[1625]	SETTABLE 	3 -5 4	; "percentage" -
	12	[1626]	SELF     	3 0 -7	; "updateFooterText"
	13	[1626]	MOVE     	5 1
	14	[1626]	MOVE     	6 2
	15	[1626]	CALL     	3 4 1
	16	[1627]	RETURN   	0 1

function <./frontend/apps/reader/modules/readerfooter.lua:1631,1632> (1 instruction, 4 bytes at 0x7fd3a0c2b630)
3 params, 3 slots, 0 upvalues, 3 locals, 0 constants, 0 functions
	1	[1632]	RETURN   	0 1

function <./frontend/apps/reader/modules/readerfooter.lua:1635,1694> (171 instructions, 684 bytes at 0x7fd3a0c0edf0)
3 params, 10 slots, 4 upvalues, 6 locals, 40 constants, 1 function
	1	[1637]	GETTABLE 	3 0 -1	; "view"
	2	[1637]	GETTABLE 	3 3 -2	; "footer_visible"
	3	[1637]	TEST     	3 0 1
	4	[1637]	JMP      	5	; to 10
	5	[1637]	TEST     	1 0 1
	6	[1637]	JMP      	3	; to 10
	7	[1637]	TEST     	2 0 1
	8	[1637]	JMP      	1	; to 10
	9	[1638]	RETURN   	0 1
	10	[1640]	SELF     	3 0 -3	; "genFooterText"
	11	[1640]	CALL     	3 2 2
	12	[1641]	TEST     	3 0 1
	13	[1641]	JMP      	1	; to 15
	14	[1641]	LOADK    	3 -4	; ""
	15	[1642]	GETTABLE 	4 0 -5	; "footer_text"
	16	[1642]	SELF     	4 4 -6	; "setText"
	17	[1642]	MOVE     	6 3
	18	[1642]	CALL     	4 3 1
	19	[1643]	GETTABLE 	4 0 -5	; "footer_text"
	20	[1643]	SELF     	4 4 -7	; "setMaxWidth"
	21	[1643]	GETGLOBAL	6 -8	; math
	22	[1643]	GETTABLE 	6 6 -9	; "floor"
	23	[1643]	GETTABLE 	7 0 -10	; "_saved_screen_width"
	24	[1643]	GETTABLE 	8 0 -11	; "settings"
	25	[1643]	GETTABLE 	8 8 -12	; "progress_margin_width"
	26	[1643]	MUL      	8 -13 8	; 2 -
	27	[1643]	SUB      	7 7 8
	28	[1643]	CALL     	6 2 0
	29	[1643]	CALL     	4 0 1
	30	[1644]	GETTABLE 	4 0 -11	; "settings"
	31	[1644]	GETTABLE 	4 4 -14	; "disable_progress_bar"
	32	[1644]	TEST     	4 0 0
	33	[1644]	JMP      	20	; to 54
	34	[1645]	GETTABLE 	4 0 -15	; "has_no_mode"
	35	[1645]	TEST     	4 0 1
	36	[1645]	JMP      	2	; to 39
	37	[1645]	EQ       	0 3 -4	; - ""
	38	[1645]	JMP      	7	; to 46
	39	[1646]	SETTABLE 	0 -16 -17	; "text_width" 0
	40	[1647]	GETTABLE 	4 0 -18	; "footer_container"
	41	[1647]	GETTABLE 	4 4 -19	; "dimen"
	42	[1647]	SETTABLE 	4 -20 -17	; "h" 0
	43	[1648]	GETTABLE 	4 0 -5	; "footer_text"
	44	[1648]	SETTABLE 	4 -21 -17	; "height" 0
	45	[1648]	JMP      	5	; to 51
	46	[1650]	GETTABLE 	4 0 -5	; "footer_text"
	47	[1650]	SELF     	4 4 -22	; "getSize"
	48	[1650]	CALL     	4 2 2
	49	[1650]	GETTABLE 	4 4 -23	; "w"
	50	[1650]	SETTABLE 	0 -16 4	; "text_width" -
	51	[1652]	GETTABLE 	4 0 -24	; "progress_bar"
	52	[1652]	SETTABLE 	4 -25 -17	; "width" 0
	53	[1652]	JMP      	69	; to 123
	54	[1653]	GETTABLE 	4 0 -11	; "settings"
	55	[1653]	GETTABLE 	4 4 -26	; "progress_bar_position"
	56	[1653]	TEST     	4 0 0
	57	[1653]	JMP      	23	; to 81
	58	[1654]	EQ       	0 3 -4	; - ""
	59	[1654]	JMP      	5	; to 65
	60	[1655]	GETTABLE 	4 0 -18	; "footer_container"
	61	[1655]	GETTABLE 	4 4 -19	; "dimen"
	62	[1655]	SETTABLE 	4 -20 -17	; "h" 0
	63	[1656]	GETTABLE 	4 0 -5	; "footer_text"
	64	[1656]	SETTABLE 	4 -21 -17	; "height" 0
	65	[1658]	GETTABLE 	4 0 -24	; "progress_bar"
	66	[1658]	GETGLOBAL	5 -8	; math
	67	[1658]	GETTABLE 	5 5 -9	; "floor"
	68	[1658]	GETTABLE 	6 0 -10	; "_saved_screen_width"
	69	[1658]	GETTABLE 	7 0 -11	; "settings"
	70	[1658]	GETTABLE 	7 7 -12	; "progress_margin_width"
	71	[1658]	MUL      	7 -13 7	; 2 -
	72	[1658]	SUB      	6 6 7
	73	[1658]	CALL     	5 2 2
	74	[1658]	SETTABLE 	4 -25 5	; "width" -
	75	[1659]	GETTABLE 	4 0 -5	; "footer_text"
	76	[1659]	SELF     	4 4 -22	; "getSize"
	77	[1659]	CALL     	4 2 2
	78	[1659]	GETTABLE 	4 4 -23	; "w"
	79	[1659]	SETTABLE 	0 -16 4	; "text_width" -
	80	[1659]	JMP      	42	; to 123
	81	[1661]	GETTABLE 	4 0 -15	; "has_no_mode"
	82	[1661]	TEST     	4 0 1
	83	[1661]	JMP      	2	; to 86
	84	[1661]	EQ       	0 3 -4	; - ""
	85	[1661]	JMP      	2	; to 88
	86	[1662]	SETTABLE 	0 -16 -17	; "text_width" 0
	87	[1662]	JMP      	23	; to 111
	88	[1664]	GETTABLE 	4 0 -11	; "settings"
	89	[1664]	GETTABLE 	4 4 -27	; "progress_bar_min_width_pct"
	90	[1664]	SUB      	4 -28 4	; 100 -
	91	[1664]	DIV      	4 4 -28	; - 100
	92	[1665]	GETTABLE 	5 0 -5	; "footer_text"
	93	[1665]	SELF     	5 5 -7	; "setMaxWidth"
	94	[1665]	GETGLOBAL	7 -8	; math
	95	[1665]	GETTABLE 	7 7 -9	; "floor"
	96	[1665]	GETTABLE 	8 0 -10	; "_saved_screen_width"
	97	[1665]	MUL      	8 4 8
	98	[1665]	GETTABLE 	9 0 -11	; "settings"
	99	[1665]	GETTABLE 	9 9 -12	; "progress_margin_width"
	100	[1665]	MUL      	9 -13 9	; 2 -
	101	[1665]	SUB      	8 8 9
	102	[1665]	CALL     	7 2 0
	103	[1665]	CALL     	5 0 1
	104	[1666]	GETTABLE 	5 0 -5	; "footer_text"
	105	[1666]	SELF     	5 5 -22	; "getSize"
	106	[1666]	CALL     	5 2 2
	107	[1666]	GETTABLE 	5 5 -23	; "w"
	108	[1666]	GETTABLE 	6 0 -29	; "text_left_margin"
	109	[1666]	ADD      	5 5 6
	110	[1666]	SETTABLE 	0 -16 5	; "text_width" -
	111	[1668]	GETTABLE 	4 0 -24	; "progress_bar"
	112	[1668]	GETGLOBAL	5 -8	; math
	113	[1668]	GETTABLE 	5 5 -9	; "floor"
	114	[1669]	GETTABLE 	6 0 -10	; "_saved_screen_width"
	115	[1669]	GETTABLE 	7 0 -16	; "text_width"
	116	[1669]	SUB      	6 6 7
	117	[1669]	GETTABLE 	7 0 -11	; "settings"
	118	[1669]	GETTABLE 	7 7 -12	; "progress_margin_width"
	119	[1669]	MUL      	7 7 -13	; - 2
	120	[1669]	SUB      	6 6 7
	121	[1668]	CALL     	5 2 2
	122	[1669]	SETTABLE 	4 -25 5	; "width" -
	123	[1671]	LOADNIL  	4 4
	124	[1672]	GETTABLE 	5 0 -11	; "settings"
	125	[1672]	GETTABLE 	5 5 -30	; "progress_style_thin"
	126	[1672]	TEST     	5 0 0
	127	[1672]	JMP      	6	; to 134
	128	[1673]	GETTABLE 	5 0 -11	; "settings"
	129	[1673]	GETTABLE 	5 5 -31	; "progress_style_thin_height"
	130	[1673]	TESTSET  	4 5 1
	131	[1673]	JMP      	1	; to 133
	132	[1673]	GETUPVAL 	4 0	; PROGRESS_BAR_STYLE_THIN_DEFAULT_HEIGHT
	133	[1673]	JMP      	5	; to 139
	134	[1675]	GETTABLE 	5 0 -11	; "settings"
	135	[1675]	GETTABLE 	5 5 -32	; "progress_style_thick_height"
	136	[1675]	TESTSET  	4 5 1
	137	[1675]	JMP      	1	; to 139
	138	[1675]	GETUPVAL 	4 1	; PROGRESS_BAR_STYLE_THICK_DEFAULT_HEIGHT
	139	[1677]	GETTABLE 	5 0 -24	; "progress_bar"
	140	[1677]	GETUPVAL 	6 2	; Screen
	141	[1677]	SELF     	6 6 -33	; "scaleBySize"
	142	[1677]	MOVE     	8 4
	143	[1677]	CALL     	6 3 2
	144	[1677]	SETTABLE 	5 -21 6	; "height" -
	145	[1679]	GETTABLE 	5 0 -34	; "separator_line"
	146	[1679]	TEST     	5 0 0
	147	[1679]	JMP      	7	; to 155
	148	[1680]	GETTABLE 	5 0 -34	; "separator_line"
	149	[1680]	GETTABLE 	5 5 -19	; "dimen"
	150	[1680]	GETTABLE 	6 0 -10	; "_saved_screen_width"
	151	[1680]	GETTABLE 	7 0 -35	; "horizontal_margin"
	152	[1680]	MUL      	7 -13 7	; 2 -
	153	[1680]	SUB      	6 6 7
	154	[1680]	SETTABLE 	5 -23 6	; "w" -
	155	[1682]	GETTABLE 	5 0 -36	; "text_container"
	156	[1682]	GETTABLE 	5 5 -19	; "dimen"
	157	[1682]	GETTABLE 	6 0 -16	; "text_width"
	158	[1682]	SETTABLE 	5 -23 6	; "w" -
	159	[1683]	GETTABLE 	5 0 -37	; "horizontal_group"
	160	[1683]	SELF     	5 5 -38	; "resetLayout"
	161	[1683]	CALL     	5 2 1
	162	[1688]	TEST     	1 0 0
	163	[1688]	JMP      	7	; to 171
	164	[1690]	GETUPVAL 	5 3	; UIManager
	165	[1690]	SELF     	5 5 -39	; "setDirty"
	166	[1690]	GETTABLE 	7 0 -1	; "view"
	167	[1690]	GETTABLE 	7 7 -40	; "dialog"
	168	[1692]	CLOSURE  	8 0	; 0x7fd3a0c0eea0
	169	[1692]	MOVE     	0 0
	170	[1690]	CALL     	5 4 1
	171	[1694]	RETURN   	0 1

function <./frontend/apps/reader/modules/readerfooter.lua:1690,1692> (6 instructions, 24 bytes at 0x7fd3a0c0eea0)
0 params, 2 slots, 1 upvalue, 0 locals, 3 constants, 0 functions
	1	[1691]	LOADK    	0 -1	; "ui"
	2	[1691]	GETUPVAL 	1 0	; self
	3	[1691]	GETTABLE 	1 1 -2	; "footer_content"
	4	[1691]	GETTABLE 	1 1 -3	; "dimen"
	5	[1691]	RETURN   	0 3
	6	[1692]	RETURN   	0 1

function <./frontend/apps/reader/modules/readerfooter.lua:1696,1701> (15 instructions, 60 bytes at 0x7fd3a0c294c0)
2 params, 6 slots, 0 upvalues, 2 locals, 10 constants, 0 functions
	1	[1697]	SETTABLE 	0 -1 1	; "pageno" -
	2	[1698]	GETTABLE 	2 0 -3	; "view"
	3	[1698]	GETTABLE 	2 2 -4	; "document"
	4	[1698]	SELF     	2 2 -5	; "getPageCount"
	5	[1698]	CALL     	2 2 2
	6	[1698]	SETTABLE 	0 -2 2	; "pages" -
	7	[1699]	GETTABLE 	2 0 -6	; "ui"
	8	[1699]	GETTABLE 	2 2 -7	; "doc_settings"
	9	[1699]	SELF     	2 2 -8	; "saveSetting"
	10	[1699]	LOADK    	4 -9	; "doc_pages"
	11	[1699]	GETTABLE 	5 0 -2	; "pages"
	12	[1699]	CALL     	2 4 1
	13	[1700]	SELF     	2 0 -10	; "updateFooterPage"
	14	[1700]	CALL     	2 2 1
	15	[1701]	RETURN   	0 1

function <./frontend/apps/reader/modules/readerfooter.lua:1703,1712> (23 instructions, 92 bytes at 0x7fd3a0c2a6d0)
3 params, 7 slots, 0 upvalues, 3 locals, 13 constants, 0 functions
	1	[1704]	SETTABLE 	0 -1 1	; "position" -
	2	[1705]	GETTABLE 	3 0 -3	; "view"
	3	[1705]	GETTABLE 	3 3 -4	; "document"
	4	[1705]	GETTABLE 	3 3 -5	; "info"
	5	[1705]	GETTABLE 	3 3 -2	; "doc_height"
	6	[1705]	SETTABLE 	0 -2 3	; "doc_height" -
	7	[1706]	TEST     	2 0 0
	8	[1706]	JMP      	12	; to 21
	9	[1707]	SETTABLE 	0 -6 2	; "pageno" -
	10	[1708]	GETTABLE 	3 0 -3	; "view"
	11	[1708]	GETTABLE 	3 3 -4	; "document"
	12	[1708]	SELF     	3 3 -8	; "getPageCount"
	13	[1708]	CALL     	3 2 2
	14	[1708]	SETTABLE 	0 -7 3	; "pages" -
	15	[1709]	GETTABLE 	3 0 -9	; "ui"
	16	[1709]	GETTABLE 	3 3 -10	; "doc_settings"
	17	[1709]	SELF     	3 3 -11	; "saveSetting"
	18	[1709]	LOADK    	5 -12	; "doc_pages"
	19	[1709]	GETTABLE 	6 0 -7	; "pages"
	20	[1709]	CALL     	3 4 1
	21	[1711]	SELF     	3 0 -13	; "updateFooterPos"
	22	[1711]	CALL     	3 2 1
	23	[1712]	RETURN   	0 1

function <./frontend/apps/reader/modules/readerfooter.lua:1718,1735> (56 instructions, 224 bytes at 0x7fd3a0c118b0)
1 param, 6 slots, 1 upvalue, 2 locals, 24 constants, 0 functions
	1	[1719]	GETTABLE 	1 0 -1	; "ui"
	2	[1719]	GETTABLE 	1 1 -2	; "menu"
	3	[1719]	SELF     	1 1 -3	; "registerToMainMenu"
	4	[1719]	MOVE     	3 0
	5	[1719]	CALL     	1 3 1
	6	[1720]	SELF     	1 0 -4	; "setupTouchZones"
	7	[1720]	CALL     	1 2 1
	8	[1722]	GETTABLE 	1 0 -1	; "ui"
	9	[1722]	GETTABLE 	1 1 -5	; "document"
	10	[1722]	GETTABLE 	1 1 -6	; "info"
	11	[1722]	GETTABLE 	1 1 -7	; "has_pages"
	12	[1722]	TEST     	1 0 0
	13	[1722]	JMP      	13	; to 27
	14	[1722]	GETTABLE 	1 0 -8	; "settings"
	15	[1722]	GETTABLE 	1 1 -9	; "progress_margin"
	16	[1722]	TEST     	1 0 0
	17	[1722]	JMP      	9	; to 27
	18	[1723]	GETTABLE 	1 0 -8	; "settings"
	19	[1723]	GETUPVAL 	2 0	; Screen
	20	[1723]	SELF     	2 2 -11	; "scaleBySize"
	21	[1723]	LOADK    	4 -12	; 10
	22	[1723]	CALL     	2 3 2
	23	[1723]	SETTABLE 	1 -10 2	; "progress_margin_width" -
	24	[1724]	SELF     	1 0 -13	; "updateFooterContainer"
	25	[1724]	CALL     	1 2 1
	26	[1724]	JMP      	19	; to 46
	27	[1726]	GETTABLE 	1 0 -8	; "settings"
	28	[1726]	GETTABLE 	1 1 -9	; "progress_margin"
	29	[1726]	TEST     	1 0 0
	30	[1726]	JMP      	15	; to 46
	31	[1727]	GETTABLE 	1 0 -1	; "ui"
	32	[1727]	GETTABLE 	1 1 -5	; "document"
	33	[1727]	SELF     	1 1 -14	; "getPageMargins"
	34	[1727]	CALL     	1 2 2
	35	[1728]	GETTABLE 	2 0 -8	; "settings"
	36	[1728]	GETGLOBAL	3 -15	; math
	37	[1728]	GETTABLE 	3 3 -16	; "floor"
	38	[1728]	GETTABLE 	4 1 -17	; "left"
	39	[1728]	GETTABLE 	5 1 -18	; "right"
	40	[1728]	ADD      	4 4 5
	41	[1728]	DIV      	4 4 -19	; - 2
	42	[1728]	CALL     	3 2 2
	43	[1728]	SETTABLE 	2 -10 3	; "progress_margin_width" -
	44	[1729]	SELF     	2 0 -13	; "updateFooterContainer"
	45	[1729]	CALL     	2 2 1
	46	[1731]	SELF     	1 0 -20	; "resetLayout"
	47	[1731]	GETTABLE 	3 0 -8	; "settings"
	48	[1731]	GETTABLE 	3 3 -10	; "progress_margin_width"
	49	[1731]	CALL     	1 3 1
	50	[1732]	SELF     	1 0 -21	; "setTocMarkers"
	51	[1732]	CALL     	1 2 1
	52	[1733]	GETTABLE 	1 0 -23	; "_updateFooterText"
	53	[1733]	SETTABLE 	0 -22 1	; "updateFooterText" -
	54	[1734]	SELF     	1 0 -24	; "updateFooter"
	55	[1734]	CALL     	1 2 1
	56	[1735]	RETURN   	0 1

function <./frontend/apps/reader/modules/readerfooter.lua:1737,1744> (27 instructions, 108 bytes at 0x7fd3a0c195c0)
2 params, 6 slots, 0 upvalues, 3 locals, 13 constants, 0 functions
	1	[1738]	GETTABLE 	2 0 -1	; "ui"
	2	[1738]	GETTABLE 	2 2 -2	; "document"
	3	[1738]	GETTABLE 	2 2 -3	; "info"
	4	[1738]	GETTABLE 	2 2 -4	; "has_pages"
	5	[1738]	TEST     	2 0 1
	6	[1738]	JMP      	20	; to 27
	7	[1739]	SELF     	2 1 -5	; "readSetting"
	8	[1739]	LOADK    	4 -6	; "copt_h_page_margins"
	9	[1739]	CALL     	2 3 2
	10	[1739]	TEST     	2 0 1
	11	[1739]	JMP      	7	; to 19
	12	[1740]	GETGLOBAL	2 -7	; G_reader_settings
	13	[1740]	SELF     	2 2 -5	; "readSetting"
	14	[1740]	LOADK    	4 -6	; "copt_h_page_margins"
	15	[1740]	CALL     	2 3 2
	16	[1740]	TEST     	2 0 1
	17	[1740]	JMP      	1	; to 19
	18	[1741]	GETGLOBAL	2 -8	; DCREREADER_CONFIG_H_MARGIN_SIZES_MEDIUM
	19	[1742]	GETGLOBAL	3 -10	; math
	20	[1742]	GETTABLE 	3 3 -11	; "floor"
	21	[1742]	GETTABLE 	4 2 -12	; 1
	22	[1742]	GETTABLE 	5 2 -13	; 2
	23	[1742]	ADD      	4 4 5
	24	[1742]	DIV      	4 4 -13	; - 2
	25	[1742]	CALL     	3 2 2
	26	[1742]	SETTABLE 	0 -9 3	; "book_margins_footer_width" -
	27	[1744]	RETURN   	0 1

function <./frontend/apps/reader/modules/readerfooter.lua:1746,1781> (40 instructions, 160 bytes at 0x7fd3a0c0fd00)
2 params, 5 slots, 1 upvalue, 3 locals, 12 constants, 0 functions
	1	[1762]	EQ       	1 1 -1	; - nil
	2	[1762]	JMP      	1	; to 4
	3	[1762]	SETTABLE 	0 -2 1	; "mode" -
	4	[1763]	GETTABLE 	2 0 -3	; "view"
	5	[1763]	GETTABLE 	3 0 -2	; "mode"
	6	[1763]	GETTABLE 	4 0 -5	; "mode_list"
	7	[1763]	GETTABLE 	4 4 -6	; "off"
	8	[1763]	EQ       	0 3 4
	9	[1763]	JMP      	1	; to 11
	10	[1763]	LOADBOOL 	3 0 1
	11	[1763]	LOADBOOL 	3 1 0
	12	[1763]	SETTABLE 	2 -4 3	; "footer_visible" -
	13	[1766]	GETTABLE 	2 0 -7	; "settings"
	14	[1766]	GETTABLE 	2 2 -8	; "all_at_once"
	15	[1766]	TEST     	2 0 0
	16	[1766]	JMP      	1	; to 18
	17	[1767]	RETURN   	0 1
	18	[1770]	GETTABLE 	2 0 -3	; "view"
	19	[1770]	GETTABLE 	2 2 -4	; "footer_visible"
	20	[1770]	TEST     	2 0 1
	21	[1770]	JMP      	4	; to 26
	22	[1771]	GETUPVAL 	2 0	; footerTextGeneratorMap
	23	[1771]	GETTABLE 	2 2 -10	; "empty"
	24	[1771]	SETTABLE 	0 -9 2	; "genFooterText" -
	25	[1772]	RETURN   	0 1
	26	[1775]	GETTABLE 	2 0 -11	; "mode_index"
	27	[1775]	GETTABLE 	3 0 -2	; "mode"
	28	[1775]	GETTABLE 	2 2 3
	29	[1776]	GETTABLE 	3 0 -7	; "settings"
	30	[1776]	GETTABLE 	3 3 2
	31	[1776]	TEST     	3 0 0
	32	[1776]	JMP      	3	; to 36
	33	[1776]	GETTABLE 	3 0 -12	; "has_no_mode"
	34	[1776]	TEST     	3 0 0
	35	[1776]	JMP      	1	; to 37
	36	[1778]	LOADK    	2 -10	; "empty"
	37	[1780]	GETUPVAL 	3 0	; footerTextGeneratorMap
	38	[1780]	GETTABLE 	3 3 2
	39	[1780]	SETTABLE 	0 -9 3	; "genFooterText" -
	40	[1781]	RETURN   	0 1

function <./frontend/apps/reader/modules/readerfooter.lua:1783,1786> (7 instructions, 28 bytes at 0x7fd3a0c208a0)
1 param, 4 slots, 0 upvalues, 1 local, 5 constants, 0 functions
	1	[1784]	GETTABLE 	1 0 -2	; "mode"
	2	[1784]	SETTABLE 	0 -1 1	; "orig_mode" -
	3	[1785]	SELF     	1 0 -3	; "applyFooterMode"
	4	[1785]	GETTABLE 	3 0 -4	; "mode_list"
	5	[1785]	GETTABLE 	3 3 -5	; "page_progress"
	6	[1785]	CALL     	1 3 1
	7	[1786]	RETURN   	0 1

function <./frontend/apps/reader/modules/readerfooter.lua:1788,1790> (4 instructions, 16 bytes at 0x7fd3a0c1ac70)
1 param, 4 slots, 0 upvalues, 1 local, 2 constants, 0 functions
	1	[1789]	SELF     	1 0 -1	; "applyFooterMode"
	2	[1789]	GETTABLE 	3 0 -2	; "orig_mode"
	3	[1789]	CALL     	1 3 1
	4	[1790]	RETURN   	0 1

function <./frontend/apps/reader/modules/readerfooter.lua:1792,1829> (93 instructions, 372 bytes at 0x7fd3a0c25270)
2 params, 11 slots, 1 upvalue, 10 locals, 28 constants, 0 functions
	1	[1793]	GETTABLE 	2 0 -1	; "has_no_mode"
	2	[1793]	TEST     	2 0 1
	3	[1793]	JMP      	4	; to 8
	4	[1793]	GETTABLE 	2 0 -2	; "settings"
	5	[1793]	GETTABLE 	2 2 -3	; "lock_tap"
	6	[1793]	TEST     	2 0 0
	7	[1793]	JMP      	1	; to 9
	8	[1794]	RETURN   	0 1
	9	[1796]	GETTABLE 	2 0 -4	; "view"
	10	[1796]	GETTABLE 	2 2 -5	; "flipping_visible"
	11	[1796]	TEST     	2 0 0
	12	[1796]	JMP      	19	; to 32
	13	[1797]	GETTABLE 	2 1 -6	; "pos"
	14	[1798]	GETTABLE 	3 0 -7	; "progress_bar"
	15	[1798]	GETTABLE 	3 3 -8	; "dimen"
	16	[1800]	TEST     	3 0 0
	17	[1800]	JMP      	70	; to 88
	18	[1801]	GETTABLE 	4 2 -9	; "x"
	19	[1801]	GETTABLE 	5 3 -9	; "x"
	20	[1801]	SUB      	4 4 5
	21	[1801]	GETTABLE 	5 3 -10	; "w"
	22	[1801]	DIV      	4 4 5
	23	[1802]	GETTABLE 	5 0 -11	; "ui"
	24	[1802]	SELF     	5 5 -12	; "handleEvent"
	25	[1802]	GETUPVAL 	7 0	; Event
	26	[1802]	SELF     	7 7 -13	; "new"
	27	[1802]	LOADK    	9 -14	; "GotoPercentage"
	28	[1802]	MOVE     	10 4
	29	[1802]	CALL     	7 4 0
	30	[1802]	CALL     	5 0 1
	31	[1803]	JMP      	56	; to 88
	32	[1805]	GETTABLE 	2 0 -2	; "settings"
	33	[1805]	GETTABLE 	2 2 -15	; "all_at_once"
	34	[1805]	TEST     	2 0 1
	35	[1805]	JMP      	3	; to 39
	36	[1805]	GETTABLE 	2 0 -1	; "has_no_mode"
	37	[1805]	TEST     	2 0 0
	38	[1805]	JMP      	11	; to 50
	39	[1806]	GETTABLE 	2 0 -16	; "mode"
	40	[1806]	LE       	0 -17 2	; 1 -
	41	[1806]	JMP      	4	; to 46
	42	[1807]	GETTABLE 	2 0 -18	; "mode_list"
	43	[1807]	GETTABLE 	2 2 -19	; "off"
	44	[1807]	SETTABLE 	0 -16 2	; "mode" -
	45	[1807]	JMP      	35	; to 81
	46	[1809]	GETTABLE 	2 0 -18	; "mode_list"
	47	[1809]	GETTABLE 	2 2 -20	; "page_progress"
	48	[1809]	SETTABLE 	0 -16 2	; "mode" -
	49	[1810]	JMP      	31	; to 81
	50	[1812]	GETTABLE 	2 0 -16	; "mode"
	51	[1812]	ADD      	2 2 -17	; - 1
	52	[1812]	GETTABLE 	3 0 -21	; "mode_nb"
	53	[1812]	MOD      	2 2 3
	54	[1812]	SETTABLE 	0 -16 2	; "mode" -
	55	[1813]	GETGLOBAL	2 -22	; ipairs
	56	[1813]	GETTABLE 	3 0 -23	; "mode_index"
	57	[1813]	CALL     	2 2 4
	58	[1813]	JMP      	20	; to 79
	59	[1814]	GETTABLE 	7 0 -16	; "mode"
	60	[1814]	GETTABLE 	8 0 -18	; "mode_list"
	61	[1814]	GETTABLE 	8 8 -19	; "off"
	62	[1814]	EQ       	0 7 8
	63	[1814]	JMP      	1	; to 65
	64	[1814]	JMP      	16	; to 81
	65	[1815]	GETTABLE 	7 0 -16	; "mode"
	66	[1815]	EQ       	0 7 5
	67	[1815]	JMP      	11	; to 79
	68	[1816]	GETTABLE 	7 0 -2	; "settings"
	69	[1816]	GETTABLE 	7 7 6
	70	[1816]	TEST     	7 0 0
	71	[1816]	JMP      	2	; to 74
	72	[1817]	JMP      	8	; to 81
	73	[1817]	JMP      	5	; to 79
	74	[1819]	GETTABLE 	7 0 -16	; "mode"
	75	[1819]	ADD      	7 7 -17	; - 1
	76	[1819]	GETTABLE 	8 0 -21	; "mode_nb"
	77	[1819]	MOD      	7 7 8
	78	[1819]	SETTABLE 	0 -16 7	; "mode" -
	79	[1813]	TFORLOOP 	2 2
	80	[1821]	JMP      	-22	; to 59
	81	[1824]	SELF     	2 0 -24	; "applyFooterMode"
	82	[1824]	CALL     	2 2 1
	83	[1825]	GETGLOBAL	2 -25	; G_reader_settings
	84	[1825]	SELF     	2 2 -26	; "saveSetting"
	85	[1825]	LOADK    	4 -27	; "reader_footer_mode"
	86	[1825]	GETTABLE 	5 0 -16	; "mode"
	87	[1825]	CALL     	2 4 1
	88	[1827]	SELF     	2 0 -28	; "updateFooter"
	89	[1827]	LOADBOOL 	4 1 0
	90	[1827]	CALL     	2 3 1
	91	[1828]	LOADBOOL 	2 1 0
	92	[1828]	RETURN   	2 2
	93	[1829]	RETURN   	0 1

function <./frontend/apps/reader/modules/readerfooter.lua:1831,1835> (16 instructions, 64 bytes at 0x7fd3a0c140c0)
1 param, 6 slots, 1 upvalue, 1 local, 7 constants, 0 functions
	1	[1832]	GETTABLE 	1 0 -1	; "mode"
	2	[1832]	GETTABLE 	2 0 -2	; "mode_list"
	3	[1832]	GETTABLE 	2 2 -3	; "off"
	4	[1832]	EQ       	0 1 2
	5	[1832]	JMP      	1	; to 7
	6	[1832]	RETURN   	0 1
	7	[1833]	GETTABLE 	1 0 -4	; "ui"
	8	[1833]	SELF     	1 1 -5	; "handleEvent"
	9	[1833]	GETUPVAL 	3 0	; Event
	10	[1833]	SELF     	3 3 -6	; "new"
	11	[1833]	LOADK    	5 -7	; "ShowSkimtoDialog"
	12	[1833]	CALL     	3 3 0
	13	[1833]	CALL     	1 0 1
	14	[1834]	LOADBOOL 	1 1 0
	15	[1834]	RETURN   	1 2
	16	[1835]	RETURN   	0 1

function <./frontend/apps/reader/modules/readerfooter.lua:1837,1849> (28 instructions, 112 bytes at 0x7fd3a0c19460)
2 params, 5 slots, 0 upvalues, 2 locals, 8 constants, 0 functions
	1	[1838]	TEST     	1 0 0
	2	[1838]	JMP      	21	; to 24
	3	[1842]	GETTABLE 	2 0 -1	; "mode"
	4	[1842]	GETTABLE 	3 0 -2	; "mode_list"
	5	[1842]	GETTABLE 	3 3 -3	; "off"
	6	[1842]	EQ       	0 2 3
	7	[1842]	JMP      	6	; to 14
	8	[1842]	GETTABLE 	2 0 -4	; "view"
	9	[1842]	GETTABLE 	2 2 -5	; "flipping_visible"
	10	[1842]	TEST     	2 0 1
	11	[1842]	JMP      	2	; to 14
	12	[1843]	SELF     	2 0 -6	; "onTapFooter"
	13	[1843]	CALL     	2 2 1
	14	[1845]	GETTABLE 	2 0 -4	; "view"
	15	[1845]	GETTABLE 	3 0 -1	; "mode"
	16	[1845]	GETTABLE 	4 0 -2	; "mode_list"
	17	[1845]	GETTABLE 	4 4 -3	; "off"
	18	[1845]	EQ       	0 3 4
	19	[1845]	JMP      	1	; to 21
	20	[1845]	LOADBOOL 	3 0 1
	21	[1845]	LOADBOOL 	3 1 0
	22	[1845]	SETTABLE 	2 -7 3	; "footer_visible" -
	23	[1845]	JMP      	4	; to 28
	24	[1847]	SELF     	2 0 -8	; "applyFooterMode"
	25	[1847]	GETTABLE 	4 0 -2	; "mode_list"
	26	[1847]	GETTABLE 	4 4 -3	; "off"
	27	[1847]	CALL     	2 3 1
	28	[1849]	RETURN   	0 1

function <./frontend/apps/reader/modules/readerfooter.lua:1851,1860> (27 instructions, 108 bytes at 0x7fd3a0c214f0)
3 params, 9 slots, 1 upvalue, 3 locals, 11 constants, 0 functions
	1	[1852]	SELF     	3 0 -1	; "updateFooterContainer"
	2	[1852]	CALL     	3 2 1
	3	[1853]	SELF     	3 0 -2	; "resetLayout"
	4	[1853]	LOADBOOL 	5 1 0
	5	[1853]	CALL     	3 3 1
	6	[1856]	SELF     	3 0 -3	; "updateFooter"
	7	[1856]	TESTSET  	5 1 0
	8	[1856]	JMP      	1	; to 10
	9	[1856]	NOT      	5 2
	10	[1856]	TESTSET  	6 1 0
	11	[1856]	JMP      	1	; to 13
	12	[1856]	MOVE     	6 2
	13	[1856]	CALL     	3 4 1
	14	[1857]	TEST     	2 0 0
	15	[1857]	JMP      	11	; to 27
	16	[1858]	GETTABLE 	3 0 -4	; "ui"
	17	[1858]	SELF     	3 3 -5	; "handleEvent"
	18	[1858]	GETUPVAL 	5 0	; Event
	19	[1858]	SELF     	5 5 -6	; "new"
	20	[1858]	LOADK    	7 -7	; "SetPageBottomMargin"
	21	[1858]	GETTABLE 	8 0 -8	; "view"
	22	[1858]	GETTABLE 	8 8 -9	; "document"
	23	[1858]	GETTABLE 	8 8 -10	; "configurable"
	24	[1858]	GETTABLE 	8 8 -11	; "b_page_margin"
	25	[1858]	CALL     	5 4 0
	26	[1858]	CALL     	3 0 1
	27	[1860]	RETURN   	0 1

function <./frontend/apps/reader/modules/readerfooter.lua:1862,1867> (9 instructions, 36 bytes at 0x7fd3a0c21570)
1 param, 3 slots, 0 upvalues, 1 local, 4 constants, 0 functions
	1	[1863]	SELF     	1 0 -1	; "updateFooter"
	2	[1863]	CALL     	1 2 1
	3	[1864]	GETTABLE 	1 0 -2	; "settings"
	4	[1864]	GETTABLE 	1 1 -3	; "auto_refresh_time"
	5	[1864]	TEST     	1 0 0
	6	[1864]	JMP      	2	; to 9
	7	[1865]	SELF     	1 0 -4	; "setupAutoRefreshTime"
	8	[1865]	CALL     	1 2 1
	9	[1867]	RETURN   	0 1

function <./frontend/apps/reader/modules/readerfooter.lua:1869,1874> (10 instructions, 40 bytes at 0x7fd3a0c23470)
1 param, 4 slots, 1 upvalue, 1 local, 6 constants, 0 functions
	1	[1870]	GETTABLE 	1 0 -1	; "settings"
	2	[1870]	GETTABLE 	1 1 -2	; "auto_refresh_time"
	3	[1870]	TEST     	1 0 0
	4	[1870]	JMP      	5	; to 10
	5	[1871]	GETUPVAL 	1 0	; UIManager
	6	[1871]	SELF     	1 1 -3	; "unschedule"
	7	[1871]	GETTABLE 	3 0 -4	; "autoRefreshTime"
	8	[1871]	CALL     	1 3 1
	9	[1872]	SETTABLE 	0 -5 -6	; "onCloseDocument" nil
	10	[1874]	RETURN   	0 1

function <./frontend/apps/reader/modules/readerfooter.lua:1876,1880> (8 instructions, 32 bytes at 0x7fd3a0c21f20)
1 param, 4 slots, 0 upvalues, 1 local, 3 constants, 0 functions
	1	[1877]	GETTABLE 	1 0 -1	; "settings"
	2	[1877]	GETTABLE 	1 1 -2	; "frontlight"
	3	[1877]	TEST     	1 0 0
	4	[1877]	JMP      	3	; to 8
	5	[1878]	SELF     	1 0 -3	; "updateFooter"
	6	[1878]	LOADBOOL 	3 1 0
	7	[1878]	CALL     	1 3 1
	8	[1880]	RETURN   	0 1

function <./frontend/apps/reader/modules/readerfooter.lua:1882,1885> (6 instructions, 24 bytes at 0x7fd3a0c21fa0)
1 param, 4 slots, 0 upvalues, 1 local, 2 constants, 0 functions
	1	[1883]	SELF     	1 0 -1	; "updateFooterContainer"
	2	[1883]	CALL     	1 2 1
	3	[1884]	SELF     	1 0 -2	; "resetLayout"
	4	[1884]	LOADBOOL 	3 1 0
	5	[1884]	CALL     	1 3 1
	6	[1885]	RETURN   	0 1

function <./frontend/apps/reader/modules/readerfooter.lua:1887,1893> (22 instructions, 88 bytes at 0x7fd3a0c242c0)
2 params, 6 slots, 1 upvalue, 2 locals, 10 constants, 0 functions
	1	[1888]	GETGLOBAL	2 -2	; math
	2	[1888]	GETTABLE 	2 2 -3	; "floor"
	3	[1888]	GETTABLE 	3 1 -4	; 1
	4	[1888]	GETTABLE 	4 1 -5	; 2
	5	[1888]	ADD      	3 3 4
	6	[1888]	DIV      	3 3 -5	; - 2
	7	[1888]	CALL     	2 2 2
	8	[1888]	SETTABLE 	0 -1 2	; "book_margins_footer_width" -
	9	[1889]	GETTABLE 	2 0 -6	; "settings"
	10	[1889]	GETTABLE 	2 2 -7	; "progress_margin"
	11	[1889]	TEST     	2 0 0
	12	[1889]	JMP      	9	; to 22
	13	[1890]	GETTABLE 	2 0 -6	; "settings"
	14	[1890]	GETUPVAL 	3 0	; Screen
	15	[1890]	SELF     	3 3 -9	; "scaleBySize"
	16	[1890]	GETTABLE 	5 0 -1	; "book_margins_footer_width"
	17	[1890]	CALL     	3 3 2
	18	[1890]	SETTABLE 	2 -8 3	; "progress_margin_width" -
	19	[1891]	SELF     	2 0 -10	; "refreshFooter"
	20	[1891]	LOADBOOL 	4 1 0
	21	[1891]	CALL     	2 3 1
	22	[1893]	RETURN   	0 1

function <./frontend/apps/reader/modules/readerfooter.lua:1895,1898> (6 instructions, 24 bytes at 0x7fd3a0c1b3b0)
1 param, 4 slots, 0 upvalues, 1 local, 2 constants, 0 functions
	1	[1896]	SELF     	1 0 -1	; "updateFooterContainer"
	2	[1896]	CALL     	1 2 1
	3	[1897]	SELF     	1 0 -2	; "resetLayout"
	4	[1897]	LOADBOOL 	3 1 0
	5	[1897]	CALL     	1 3 1
	6	[1898]	RETURN   	0 1
