
main <./frontend/apps/reader/modules/readerstatus.lua:0,0> (79 instructions, 316 bytes at 0x7fc2f7c068f0)
0+ params, 14 slots, 0 upvalues, 11 locals, 34 constants, 9 functions
	1	[1]	GETGLOBAL	0 -1	; require
	2	[1]	LOADK    	1 -2	; "ui/bidi"
	3	[1]	CALL     	0 2 2
	4	[2]	GETGLOBAL	1 -1	; require
	5	[2]	LOADK    	2 -3	; "ui/widget/bookstatuswidget"
	6	[2]	CALL     	1 2 2
	7	[3]	GETGLOBAL	2 -1	; require
	8	[3]	LOADK    	3 -4	; "ui/widget/buttondialogtitle"
	9	[3]	CALL     	2 2 2
	10	[4]	GETGLOBAL	3 -1	; require
	11	[4]	LOADK    	4 -5	; "device"
	12	[4]	CALL     	3 2 2
	13	[5]	GETGLOBAL	4 -1	; require
	14	[5]	LOADK    	5 -6	; "ui/event"
	15	[5]	CALL     	4 2 2
	16	[6]	GETGLOBAL	5 -1	; require
	17	[6]	LOADK    	6 -7	; "ui/widget/infomessage"
	18	[6]	CALL     	5 2 2
	19	[7]	GETGLOBAL	6 -1	; require
	20	[7]	LOADK    	7 -8	; "ui/widget/container/inputcontainer"
	21	[7]	CALL     	6 2 2
	22	[8]	GETGLOBAL	7 -1	; require
	23	[8]	LOADK    	8 -9	; "ui/uimanager"
	24	[8]	CALL     	7 2 2
	25	[9]	GETGLOBAL	8 -1	; require
	26	[9]	LOADK    	9 -10	; "gettext"
	27	[9]	CALL     	8 2 2
	28	[10]	GETGLOBAL	9 -1	; require
	29	[10]	LOADK    	10 -11	; "ffi/util"
	30	[10]	CALL     	9 2 2
	31	[10]	GETTABLE 	9 9 -12	; "template"
	32	[12]	SELF     	10 6 -13	; "new"
	33	[12]	NEWTABLE 	12 0 4
	34	[13]	SETTABLE 	12 -14 -15	; "document" nil
	35	[14]	NEWTABLE 	13 0 4
	36	[15]	SETTABLE 	13 -17 -18	; "rating" 0
	37	[16]	SETTABLE 	13 -19 -15	; "note" nil
	38	[17]	SETTABLE 	13 -20 -21	; "status" ""
	39	[18]	SETTABLE 	13 -22 -21	; "modified" ""
	40	[19]	SETTABLE 	12 -16 13	; "summary" -
	41	[20]	SETTABLE 	12 -23 -24	; "enabled" true
	42	[21]	SETTABLE 	12 -25 -18	; "total_pages" 0
	43	[12]	CALL     	10 3 2
	44	[32]	CLOSURE  	11 0	; 0x7fc2f7c07100
	45	[24]	SETTABLE 	10 -26 11	; "init" -
	46	[41]	CLOSURE  	11 1	; 0x7fc2f7c075c0
	47	[41]	MOVE     	0 8
	48	[34]	SETTABLE 	10 -27 11	; "addToMainMenu" -
	49	[163]	CLOSURE  	11 2	; 0x7fc2f7c07a00
	50	[163]	MOVE     	0 3
	51	[163]	MOVE     	0 8
	52	[163]	MOVE     	0 7
	53	[163]	MOVE     	0 4
	54	[163]	MOVE     	0 2
	55	[163]	MOVE     	0 5
	56	[43]	SETTABLE 	10 -28 11	; "onEndOfBook" -
	57	[172]	CLOSURE  	11 3	; 0x7fc2f7c0a300
	58	[165]	SETTABLE 	10 -29 11	; "openFileBrowser" -
	59	[188]	CLOSURE  	11 4	; 0x7fc2f7c0a520
	60	[188]	MOVE     	0 7
	61	[188]	MOVE     	0 5
	62	[188]	MOVE     	0 8
	63	[174]	SETTABLE 	10 -30 11	; "openNextFile" -
	64	[211]	CLOSURE  	11 5	; 0x7fc2f7c0a7a0
	65	[211]	MOVE     	0 7
	66	[211]	MOVE     	0 9
	67	[211]	MOVE     	0 8
	68	[211]	MOVE     	0 0
	69	[190]	SETTABLE 	10 -31 11	; "deleteFile" -
	70	[227]	CLOSURE  	11 6	; 0x7fc2f7c0a6a0
	71	[227]	MOVE     	0 1
	72	[227]	MOVE     	0 7
	73	[213]	SETTABLE 	10 -32 11	; "onShowBookStatus" -
	74	[248]	CLOSURE  	11 7	; 0x7fc2f7c09e40
	75	[231]	SETTABLE 	10 -33 11	; "onMarkBook" -
	76	[252]	CLOSURE  	11 8	; 0x7fc2f7c08a70
	77	[250]	SETTABLE 	10 -34 11	; "onReadSettings" -
	78	[254]	RETURN   	10 2
	79	[254]	RETURN   	0 1

function <./frontend/apps/reader/modules/readerstatus.lua:24,32> (18 instructions, 72 bytes at 0x7fc2f7c07100)
1 param, 4 slots, 0 upvalues, 1 local, 9 constants, 0 functions
	1	[25]	GETTABLE 	1 0 -1	; "ui"
	2	[25]	GETTABLE 	1 1 -2	; "document"
	3	[25]	GETTABLE 	1 1 -3	; "is_pic"
	4	[25]	TEST     	1 0 0
	5	[25]	JMP      	3	; to 9
	6	[26]	SETTABLE 	0 -4 -5	; "enabled" false
	7	[27]	RETURN   	0 1
	8	[27]	JMP      	9	; to 18
	9	[29]	GETTABLE 	1 0 -2	; "document"
	10	[29]	SELF     	1 1 -7	; "getPageCount"
	11	[29]	CALL     	1 2 2
	12	[29]	SETTABLE 	0 -6 1	; "total_pages" -
	13	[30]	GETTABLE 	1 0 -1	; "ui"
	14	[30]	GETTABLE 	1 1 -8	; "menu"
	15	[30]	SELF     	1 1 -9	; "registerToMainMenu"
	16	[30]	MOVE     	3 0
	17	[30]	CALL     	1 3 1
	18	[32]	RETURN   	0 1

function <./frontend/apps/reader/modules/readerstatus.lua:34,41> (10 instructions, 40 bytes at 0x7fc2f7c075c0)
2 params, 5 slots, 1 upvalue, 2 locals, 4 constants, 1 function
	1	[35]	NEWTABLE 	2 0 2
	2	[36]	GETUPVAL 	3 0	; _
	3	[36]	LOADK    	4 -3	; "Book status"
	4	[36]	CALL     	3 2 2
	5	[36]	SETTABLE 	2 -2 3	; "text" -
	6	[39]	CLOSURE  	3 0	; 0x7fc2f7c07730
	7	[39]	MOVE     	0 0
	8	[39]	SETTABLE 	2 -4 3	; "callback" -
	9	[40]	SETTABLE 	1 -1 2	; "book_status" -
	10	[41]	RETURN   	0 1

function <./frontend/apps/reader/modules/readerstatus.lua:37,39> (4 instructions, 16 bytes at 0x7fc2f7c07730)
0 params, 2 slots, 1 upvalue, 0 locals, 1 constant, 0 functions
	1	[38]	GETUPVAL 	0 0	; self
	2	[38]	SELF     	0 0 -1	; "onShowBookStatus"
	3	[38]	CALL     	0 2 1
	4	[39]	RETURN   	0 1

function <./frontend/apps/reader/modules/readerstatus.lua:43,163> (231 instructions, 924 bytes at 0x7fc2f7c07a00)
1 param, 14 slots, 6 upvalues, 9 locals, 54 constants, 9 functions
	1	[44]	GETUPVAL 	1 0	; Device
	2	[44]	SELF     	1 1 -1	; "performHapticFeedback"
	3	[44]	LOADK    	3 -2	; "CONTEXT_CLICK"
	4	[44]	CALL     	1 3 1
	5	[45]	GETGLOBAL	1 -3	; G_reader_settings
	6	[45]	SELF     	1 1 -4	; "readSetting"
	7	[45]	LOADK    	3 -5	; "end_document_action"
	8	[45]	CALL     	1 3 2
	9	[46]	LOADNIL  	2 2
	10	[47]	LOADBOOL 	3 1 0
	11	[48]	GETGLOBAL	4 -6	; require
	12	[48]	LOADK    	5 -7	; "ui/quickstart"
	13	[48]	CALL     	4 2 2
	14	[49]	GETGLOBAL	5 -3	; G_reader_settings
	15	[49]	SELF     	5 5 -4	; "readSetting"
	16	[49]	LOADK    	7 -8	; "lastfile"
	17	[49]	CALL     	5 3 2
	18	[50]	TEST     	5 0 0
	19	[50]	JMP      	6	; to 26
	20	[50]	GETTABLE 	6 4 -9	; "quickstart_filename"
	21	[50]	EQ       	0 5 6
	22	[50]	JMP      	3	; to 26
	23	[51]	SELF     	6 0 -10	; "openFileBrowser"
	24	[51]	CALL     	6 2 1
	25	[52]	RETURN   	0 1
	26	[54]	GETGLOBAL	6 -3	; G_reader_settings
	27	[54]	SELF     	6 6 -4	; "readSetting"
	28	[54]	LOADK    	8 -11	; "collate"
	29	[54]	CALL     	6 3 2
	30	[54]	EQ       	0 6 -12	; - "access"
	31	[54]	JMP      	1	; to 33
	32	[55]	LOADBOOL 	3 0 0
	33	[57]	EQ       	1 1 -13	; - "pop-up"
	34	[57]	JMP      	2	; to 37
	35	[57]	EQ       	0 1 -14	; - nil
	36	[57]	JMP      	97	; to 134
	37	[58]	NEWTABLE 	6 4 0
	38	[58]	NEWTABLE 	7 2 0
	39	[59]	NEWTABLE 	8 0 2
	40	[67]	CLOSURE  	9 0	; 0x7fc2f7c08290
	41	[67]	MOVE     	0 0
	42	[67]	GETUPVAL 	0 1	; _
	43	[67]	SETTABLE 	8 -15 9	; "text_func" -
	44	[71]	CLOSURE  	9 1	; 0x7fc2f7c07cb0
	45	[71]	MOVE     	0 0
	46	[71]	GETUPVAL 	0 2	; UIManager
	47	[71]	MOVE     	0 2
	48	[71]	SETTABLE 	8 -16 9	; "callback" -
	49	[72]	NEWTABLE 	9 0 2
	50	[74]	GETUPVAL 	10 1	; _
	51	[74]	LOADK    	11 -18	; "Book status"
	52	[74]	CALL     	10 2 2
	53	[74]	SETTABLE 	9 -17 10	; "text" -
	54	[78]	CLOSURE  	10 2	; 0x7fc2f7c08310
	55	[78]	MOVE     	0 0
	56	[78]	GETUPVAL 	0 2	; UIManager
	57	[78]	MOVE     	0 2
	58	[78]	SETTABLE 	9 -16 10	; "callback" -
	59	[81]	SETLIST  	7 2 1	; 1
	60	[81]	NEWTABLE 	8 2 0
	61	[82]	NEWTABLE 	9 0 2
	62	[84]	GETUPVAL 	10 1	; _
	63	[84]	LOADK    	11 -19	; "Go to beginning"
	64	[84]	CALL     	10 2 2
	65	[84]	SETTABLE 	9 -17 10	; "text" -
	66	[88]	CLOSURE  	10 3	; 0x7fc2f7c08390
	67	[88]	MOVE     	0 0
	68	[88]	GETUPVAL 	0 3	; Event
	69	[88]	GETUPVAL 	0 2	; UIManager
	70	[88]	MOVE     	0 2
	71	[88]	SETTABLE 	9 -16 10	; "callback" -
	72	[89]	NEWTABLE 	10 0 3
	73	[91]	GETUPVAL 	11 1	; _
	74	[91]	LOADK    	12 -20	; "Open next file"
	75	[91]	CALL     	11 2 2
	76	[91]	SETTABLE 	10 -17 11	; "text" -
	77	[92]	SETTABLE 	10 -21 3	; "enabled" -
	78	[96]	CLOSURE  	11 4	; 0x7fc2f7c086d0
	79	[96]	MOVE     	0 0
	80	[96]	GETUPVAL 	0 2	; UIManager
	81	[96]	MOVE     	0 2
	82	[96]	SETTABLE 	10 -16 11	; "callback" -
	83	[98]	SETLIST  	8 2 1	; 1
	84	[98]	NEWTABLE 	9 2 0
	85	[99]	NEWTABLE 	10 0 2
	86	[101]	GETUPVAL 	11 1	; _
	87	[101]	LOADK    	12 -22	; "Delete file"
	88	[101]	CALL     	11 2 2
	89	[101]	SETTABLE 	10 -17 11	; "text" -
	90	[105]	CLOSURE  	11 5	; 0x7fc2f7c098b0
	91	[105]	MOVE     	0 0
	92	[105]	GETUPVAL 	0 2	; UIManager
	93	[105]	MOVE     	0 2
	94	[105]	SETTABLE 	10 -16 11	; "callback" -
	95	[106]	NEWTABLE 	11 0 2
	96	[108]	GETUPVAL 	12 1	; _
	97	[108]	LOADK    	13 -23	; "File browser"
	98	[108]	CALL     	12 2 2
	99	[108]	SETTABLE 	11 -17 12	; "text" -
	100	[112]	CLOSURE  	12 6	; 0x7fc2f7c09aa0
	101	[112]	MOVE     	0 0
	102	[112]	GETUPVAL 	0 2	; UIManager
	103	[112]	MOVE     	0 2
	104	[112]	SETTABLE 	11 -16 12	; "callback" -
	105	[114]	SETLIST  	9 2 1	; 1
	106	[114]	NEWTABLE 	10 1 0
	107	[115]	NEWTABLE 	11 0 2
	108	[117]	GETUPVAL 	12 1	; _
	109	[117]	LOADK    	13 -24	; "Cancel"
	110	[117]	CALL     	12 2 2
	111	[117]	SETTABLE 	11 -17 12	; "text" -
	112	[120]	CLOSURE  	12 7	; 0x7fc2f7c09b60
	113	[120]	GETUPVAL 	0 2	; UIManager
	114	[120]	MOVE     	0 2
	115	[120]	SETTABLE 	11 -16 12	; "callback" -
	116	[122]	SETLIST  	10 1 1	; 1
	117	[123]	SETLIST  	6 4 1	; 1
	118	[124]	GETUPVAL 	7 4	; ButtonDialogTitle
	119	[124]	SELF     	7 7 -25	; "new"
	120	[124]	NEWTABLE 	9 0 3
	121	[125]	GETUPVAL 	10 1	; _
	122	[125]	LOADK    	11 -27	; "You've reached the end of the document.\nWhat would you like to do?"
	123	[125]	CALL     	10 2 2
	124	[125]	SETTABLE 	9 -26 10	; "title" -
	125	[126]	SETTABLE 	9 -28 -29	; "title_align" "center"
	126	[127]	SETTABLE 	9 -30 6	; "buttons" -
	127	[124]	CALL     	7 3 2
	128	[128]	MOVE     	2 7
	129	[130]	GETUPVAL 	7 2	; UIManager
	130	[130]	SELF     	7 7 -31	; "show"
	131	[130]	MOVE     	9 2
	132	[130]	CALL     	7 3 1
	133	[130]	JMP      	97	; to 231
	134	[131]	EQ       	0 1 -32	; - "book_status"
	135	[131]	JMP      	3	; to 139
	136	[132]	SELF     	6 0 -33	; "onShowBookStatus"
	137	[132]	CALL     	6 2 1
	138	[132]	JMP      	92	; to 231
	139	[133]	EQ       	0 1 -34	; - "next_file"
	140	[133]	JMP      	42	; to 183
	141	[134]	GETGLOBAL	6 -3	; G_reader_settings
	142	[134]	SELF     	6 6 -4	; "readSetting"
	143	[134]	LOADK    	8 -11	; "collate"
	144	[134]	CALL     	6 3 2
	145	[134]	EQ       	1 6 -12	; - "access"
	146	[134]	JMP      	24	; to 171
	147	[135]	GETUPVAL 	6 5	; InfoMessage
	148	[135]	SELF     	6 6 -25	; "new"
	149	[135]	NEWTABLE 	8 0 1
	150	[136]	GETUPVAL 	9 1	; _
	151	[136]	LOADK    	10 -35	; "Searching next file\226\128\166"
	152	[136]	CALL     	9 2 2
	153	[136]	SETTABLE 	8 -17 9	; "text" -
	154	[135]	CALL     	6 3 2
	155	[138]	GETUPVAL 	7 2	; UIManager
	156	[138]	SELF     	7 7 -31	; "show"
	157	[138]	MOVE     	9 6
	158	[138]	CALL     	7 3 1
	159	[139]	GETUPVAL 	7 2	; UIManager
	160	[139]	SELF     	7 7 -36	; "forceRePaint"
	161	[139]	CALL     	7 2 1
	162	[140]	SELF     	7 0 -37	; "openNextFile"
	163	[140]	GETTABLE 	9 0 -38	; "document"
	164	[140]	GETTABLE 	9 9 -39	; "file"
	165	[140]	CALL     	7 3 1
	166	[141]	GETUPVAL 	7 2	; UIManager
	167	[141]	SELF     	7 7 -40	; "close"
	168	[141]	MOVE     	9 6
	169	[141]	CALL     	7 3 1
	170	[141]	JMP      	60	; to 231
	171	[143]	GETUPVAL 	6 2	; UIManager
	172	[143]	SELF     	6 6 -31	; "show"
	173	[143]	GETUPVAL 	8 5	; InfoMessage
	174	[143]	SELF     	8 8 -25	; "new"
	175	[143]	NEWTABLE 	10 0 1
	176	[144]	GETUPVAL 	11 1	; _
	177	[144]	LOADK    	12 -41	; "Could not open next file. Sort by last read date does not support this feature."
	178	[144]	CALL     	11 2 2
	179	[144]	SETTABLE 	10 -17 11	; "text" -
	180	[143]	CALL     	8 3 0
	181	[143]	CALL     	6 0 1
	182	[146]	JMP      	48	; to 231
	183	[147]	EQ       	0 1 -42	; - "goto_beginning"
	184	[147]	JMP      	8	; to 193
	185	[148]	GETTABLE 	6 0 -43	; "ui"
	186	[148]	SELF     	6 6 -44	; "handleEvent"
	187	[148]	GETUPVAL 	8 3	; Event
	188	[148]	SELF     	8 8 -25	; "new"
	189	[148]	LOADK    	10 -45	; "GoToBeginning"
	190	[148]	CALL     	8 3 0
	191	[148]	CALL     	6 0 1
	192	[148]	JMP      	38	; to 231
	193	[149]	EQ       	0 1 -46	; - "file_browser"
	194	[149]	JMP      	3	; to 198
	195	[150]	SELF     	6 0 -10	; "openFileBrowser"
	196	[150]	CALL     	6 2 1
	197	[150]	JMP      	33	; to 231
	198	[151]	EQ       	0 1 -47	; - "mark_read"
	199	[151]	JMP      	16	; to 216
	200	[152]	SELF     	6 0 -48	; "onMarkBook"
	201	[152]	LOADBOOL 	8 1 0
	202	[152]	CALL     	6 3 1
	203	[153]	GETUPVAL 	6 2	; UIManager
	204	[153]	SELF     	6 6 -31	; "show"
	205	[153]	GETUPVAL 	8 5	; InfoMessage
	206	[153]	SELF     	8 8 -25	; "new"
	207	[153]	NEWTABLE 	10 0 2
	208	[154]	GETUPVAL 	11 1	; _
	209	[154]	LOADK    	12 -49	; "You've reached the end of the document.\nThe current book is marked as read."
	210	[154]	CALL     	11 2 2
	211	[154]	SETTABLE 	10 -17 11	; "text" -
	212	[155]	SETTABLE 	10 -50 -51	; "timeout" 3
	213	[153]	CALL     	8 3 0
	214	[153]	CALL     	6 0 1
	215	[156]	JMP      	15	; to 231
	216	[157]	EQ       	0 1 -52	; - "book_status_file_browser"
	217	[157]	JMP      	6	; to 224
	218	[158]	CLOSURE  	6 8	; 0x7fc2f7c08490
	219	[158]	MOVE     	0 0
	220	[159]	SELF     	7 0 -33	; "onShowBookStatus"
	221	[159]	MOVE     	9 6
	222	[159]	CALL     	7 3 1
	223	[159]	JMP      	7	; to 231
	224	[160]	EQ       	0 1 -53	; - "delete_file"
	225	[160]	JMP      	5	; to 231
	226	[161]	SELF     	6 0 -54	; "deleteFile"
	227	[161]	GETTABLE 	8 0 -38	; "document"
	228	[161]	GETTABLE 	8 8 -39	; "file"
	229	[161]	LOADBOOL 	9 1 0
	230	[161]	CALL     	6 4 1
	231	[163]	RETURN   	0 1

function <./frontend/apps/reader/modules/readerstatus.lua:61,67> (23 instructions, 92 bytes at 0x7fc2f7c08290)
0 params, 2 slots, 2 upvalues, 0 locals, 7 constants, 0 functions
	1	[62]	GETUPVAL 	0 0	; self
	2	[62]	GETTABLE 	0 0 -1	; "settings"
	3	[62]	GETTABLE 	0 0 -2	; "data"
	4	[62]	GETTABLE 	0 0 -3	; "summary"
	5	[62]	TEST     	0 0 0
	6	[62]	JMP      	12	; to 19
	7	[62]	GETUPVAL 	0 0	; self
	8	[62]	GETTABLE 	0 0 -1	; "settings"
	9	[62]	GETTABLE 	0 0 -2	; "data"
	10	[62]	GETTABLE 	0 0 -3	; "summary"
	11	[62]	GETTABLE 	0 0 -4	; "status"
	12	[62]	EQ       	0 0 -5	; - "complete"
	13	[62]	JMP      	5	; to 19
	14	[63]	GETUPVAL 	0 1	; _
	15	[63]	LOADK    	1 -6	; "Mark as reading"
	16	[63]	TAILCALL 	0 2 0
	17	[63]	RETURN   	0 0
	18	[63]	JMP      	4	; to 23
	19	[65]	GETUPVAL 	0 1	; _
	20	[65]	LOADK    	1 -7	; "Mark as read"
	21	[65]	TAILCALL 	0 2 0
	22	[65]	RETURN   	0 0
	23	[67]	RETURN   	0 1

function <./frontend/apps/reader/modules/readerstatus.lua:68,71> (8 instructions, 32 bytes at 0x7fc2f7c07cb0)
0 params, 3 slots, 3 upvalues, 0 locals, 2 constants, 0 functions
	1	[69]	GETUPVAL 	0 0	; self
	2	[69]	SELF     	0 0 -1	; "onMarkBook"
	3	[69]	CALL     	0 2 1
	4	[70]	GETUPVAL 	0 1	; UIManager
	5	[70]	SELF     	0 0 -2	; "close"
	6	[70]	GETUPVAL 	2 2	; choose_action
	7	[70]	CALL     	0 3 1
	8	[71]	RETURN   	0 1

function <./frontend/apps/reader/modules/readerstatus.lua:75,78> (8 instructions, 32 bytes at 0x7fc2f7c08310)
0 params, 3 slots, 3 upvalues, 0 locals, 2 constants, 0 functions
	1	[76]	GETUPVAL 	0 0	; self
	2	[76]	SELF     	0 0 -1	; "onShowBookStatus"
	3	[76]	CALL     	0 2 1
	4	[77]	GETUPVAL 	0 1	; UIManager
	5	[77]	SELF     	0 0 -2	; "close"
	6	[77]	GETUPVAL 	2 2	; choose_action
	7	[77]	CALL     	0 3 1
	8	[78]	RETURN   	0 1

function <./frontend/apps/reader/modules/readerstatus.lua:85,88> (13 instructions, 52 bytes at 0x7fc2f7c08390)
0 params, 5 slots, 4 upvalues, 0 locals, 5 constants, 0 functions
	1	[86]	GETUPVAL 	0 0	; self
	2	[86]	GETTABLE 	0 0 -1	; "ui"
	3	[86]	SELF     	0 0 -2	; "handleEvent"
	4	[86]	GETUPVAL 	2 1	; Event
	5	[86]	SELF     	2 2 -3	; "new"
	6	[86]	LOADK    	4 -4	; "GoToBeginning"
	7	[86]	CALL     	2 3 0
	8	[86]	CALL     	0 0 1
	9	[87]	GETUPVAL 	0 2	; UIManager
	10	[87]	SELF     	0 0 -5	; "close"
	11	[87]	GETUPVAL 	2 3	; choose_action
	12	[87]	CALL     	0 3 1
	13	[88]	RETURN   	0 1

function <./frontend/apps/reader/modules/readerstatus.lua:93,96> (11 instructions, 44 bytes at 0x7fc2f7c086d0)
0 params, 3 slots, 3 upvalues, 0 locals, 4 constants, 0 functions
	1	[94]	GETUPVAL 	0 0	; self
	2	[94]	SELF     	0 0 -1	; "openNextFile"
	3	[94]	GETUPVAL 	2 0	; self
	4	[94]	GETTABLE 	2 2 -2	; "document"
	5	[94]	GETTABLE 	2 2 -3	; "file"
	6	[94]	CALL     	0 3 1
	7	[95]	GETUPVAL 	0 1	; UIManager
	8	[95]	SELF     	0 0 -4	; "close"
	9	[95]	GETUPVAL 	2 2	; choose_action
	10	[95]	CALL     	0 3 1
	11	[96]	RETURN   	0 1

function <./frontend/apps/reader/modules/readerstatus.lua:102,105> (12 instructions, 48 bytes at 0x7fc2f7c098b0)
0 params, 4 slots, 3 upvalues, 0 locals, 4 constants, 0 functions
	1	[103]	GETUPVAL 	0 0	; self
	2	[103]	SELF     	0 0 -1	; "deleteFile"
	3	[103]	GETUPVAL 	2 0	; self
	4	[103]	GETTABLE 	2 2 -2	; "document"
	5	[103]	GETTABLE 	2 2 -3	; "file"
	6	[103]	LOADBOOL 	3 0 0
	7	[103]	CALL     	0 4 1
	8	[104]	GETUPVAL 	0 1	; UIManager
	9	[104]	SELF     	0 0 -4	; "close"
	10	[104]	GETUPVAL 	2 2	; choose_action
	11	[104]	CALL     	0 3 1
	12	[105]	RETURN   	0 1

function <./frontend/apps/reader/modules/readerstatus.lua:109,112> (8 instructions, 32 bytes at 0x7fc2f7c09aa0)
0 params, 3 slots, 3 upvalues, 0 locals, 2 constants, 0 functions
	1	[110]	GETUPVAL 	0 0	; self
	2	[110]	SELF     	0 0 -1	; "openFileBrowser"
	3	[110]	CALL     	0 2 1
	4	[111]	GETUPVAL 	0 1	; UIManager
	5	[111]	SELF     	0 0 -2	; "close"
	6	[111]	GETUPVAL 	2 2	; choose_action
	7	[111]	CALL     	0 3 1
	8	[112]	RETURN   	0 1

function <./frontend/apps/reader/modules/readerstatus.lua:118,120> (5 instructions, 20 bytes at 0x7fc2f7c09b60)
0 params, 3 slots, 2 upvalues, 0 locals, 1 constant, 0 functions
	1	[119]	GETUPVAL 	0 0	; UIManager
	2	[119]	SELF     	0 0 -1	; "close"
	3	[119]	GETUPVAL 	2 1	; choose_action
	4	[119]	CALL     	0 3 1
	5	[120]	RETURN   	0 1

function <./frontend/apps/reader/modules/readerstatus.lua:158,158> (4 instructions, 16 bytes at 0x7fc2f7c08490)
0 params, 2 slots, 1 upvalue, 0 locals, 1 constant, 0 functions
	1	[158]	GETUPVAL 	0 0	; self
	2	[158]	SELF     	0 0 -1	; "openFileBrowser"
	3	[158]	CALL     	0 2 1
	4	[158]	RETURN   	0 1

function <./frontend/apps/reader/modules/readerstatus.lua:165,172> (14 instructions, 56 bytes at 0x7fc2f7c0a300)
1 param, 4 slots, 0 upvalues, 2 locals, 8 constants, 0 functions
	1	[166]	GETGLOBAL	1 -1	; require
	2	[166]	LOADK    	2 -2	; "apps/filemanager/filemanager"
	3	[166]	CALL     	1 2 2
	4	[167]	GETTABLE 	2 0 -3	; "ui"
	5	[167]	SELF     	2 2 -4	; "onClose"
	6	[167]	CALL     	2 2 1
	7	[168]	GETTABLE 	2 1 -5	; "instance"
	8	[168]	TEST     	2 0 1
	9	[168]	JMP      	3	; to 13
	10	[169]	GETTABLE 	2 0 -3	; "ui"
	11	[169]	SELF     	2 2 -6	; "showFileManager"
	12	[169]	CALL     	2 2 1
	13	[171]	SETTABLE 	0 -7 -8	; "document" nil
	14	[172]	RETURN   	0 1

function <./frontend/apps/reader/modules/readerstatus.lua:174,188> (37 instructions, 148 bytes at 0x7fc2f7c0a520)
2 params, 10 slots, 3 upvalues, 3 locals, 13 constants, 0 functions
	1	[175]	GETGLOBAL	2 -1	; require
	2	[175]	LOADK    	3 -2	; "apps/filemanager/filemanager"
	3	[175]	CALL     	2 2 2
	4	[176]	GETTABLE 	3 2 -3	; "instance"
	5	[176]	TEST     	3 0 1
	6	[176]	JMP      	3	; to 10
	7	[177]	GETTABLE 	3 0 -4	; "ui"
	8	[177]	SELF     	3 3 -5	; "showFileManager"
	9	[177]	CALL     	3 2 1
	10	[179]	GETTABLE 	3 2 -3	; "instance"
	11	[179]	GETTABLE 	3 3 -6	; "file_chooser"
	12	[179]	SELF     	3 3 -7	; "getNextFile"
	13	[179]	MOVE     	5 1
	14	[179]	CALL     	3 3 2
	15	[179]	MOVE     	1 3
	16	[180]	GETTABLE 	3 2 -3	; "instance"
	17	[180]	SELF     	3 3 -8	; "onClose"
	18	[180]	CALL     	3 2 1
	19	[181]	TEST     	1 0 0
	20	[181]	JMP      	5	; to 26
	21	[182]	GETTABLE 	3 0 -4	; "ui"
	22	[182]	SELF     	3 3 -9	; "switchDocument"
	23	[182]	MOVE     	5 1
	24	[182]	CALL     	3 3 1
	25	[182]	JMP      	11	; to 37
	26	[184]	GETUPVAL 	3 0	; UIManager
	27	[184]	SELF     	3 3 -10	; "show"
	28	[184]	GETUPVAL 	5 1	; InfoMessage
	29	[184]	SELF     	5 5 -11	; "new"
	30	[184]	NEWTABLE 	7 0 1
	31	[185]	GETUPVAL 	8 2	; _
	32	[185]	LOADK    	9 -13	; "This is the last file in the current folder. No next file to open."
	33	[185]	CALL     	8 2 2
	34	[185]	SETTABLE 	7 -12 8	; "text" -
	35	[184]	CALL     	5 3 0
	36	[184]	CALL     	3 0 1
	37	[188]	RETURN   	0 1

function <./frontend/apps/reader/modules/readerstatus.lua:190,211> (33 instructions, 132 bytes at 0x7fc2f7c0a7a0)
3 params, 15 slots, 4 upvalues, 5 locals, 12 constants, 1 function
	1	[191]	GETGLOBAL	3 -1	; require
	2	[191]	LOADK    	4 -2	; "ui/widget/confirmbox"
	3	[191]	CALL     	3 2 2
	4	[192]	LOADK    	4 -3	; ""
	5	[193]	TEST     	2 0 0
	6	[193]	JMP      	1	; to 8
	7	[194]	LOADK    	4 -4	; "You've reached the end of the document.\n"
	8	[196]	GETUPVAL 	5 0	; UIManager
	9	[196]	SELF     	5 5 -5	; "show"
	10	[196]	SELF     	7 3 -6	; "new"
	11	[196]	NEWTABLE 	9 0 3
	12	[197]	GETUPVAL 	10 1	; T
	13	[197]	GETUPVAL 	11 2	; _
	14	[197]	LOADK    	12 -8	; "%1Are you sure that you want to delete this file?\n%2\nIf you delete a file, it is permanently lost."
	15	[197]	CALL     	11 2 2
	16	[197]	MOVE     	12 4
	17	[197]	GETUPVAL 	13 3	; BD
	18	[197]	GETTABLE 	13 13 -9	; "filepath"
	19	[197]	MOVE     	14 1
	20	[197]	CALL     	13 2 0
	21	[197]	CALL     	10 0 2
	22	[197]	SETTABLE 	9 -7 10	; "text" -
	23	[198]	GETUPVAL 	10 2	; _
	24	[198]	LOADK    	11 -11	; "Delete"
	25	[198]	CALL     	10 2 2
	26	[198]	SETTABLE 	9 -10 10	; "ok_text" -
	27	[209]	CLOSURE  	10 0	; 0x7fc2f7c0acb0
	28	[209]	MOVE     	0 0
	29	[209]	MOVE     	0 1
	30	[209]	SETTABLE 	9 -12 10	; "ok_callback" -
	31	[196]	CALL     	7 3 0
	32	[196]	CALL     	5 0 1
	33	[211]	RETURN   	0 1

function <./frontend/apps/reader/modules/readerstatus.lua:199,209> (27 instructions, 108 bytes at 0x7fc2f7c0acb0)
0 params, 4 slots, 2 upvalues, 1 local, 11 constants, 0 functions
	1	[200]	GETGLOBAL	0 -1	; require
	2	[200]	LOADK    	1 -2	; "apps/filemanager/filemanager"
	3	[200]	CALL     	0 2 2
	4	[201]	GETUPVAL 	1 0	; self
	5	[201]	GETTABLE 	1 1 -3	; "ui"
	6	[201]	SELF     	1 1 -4	; "onClose"
	7	[201]	CALL     	1 2 1
	8	[202]	SELF     	1 0 -5	; "deleteFile"
	9	[202]	GETUPVAL 	3 1	; file
	10	[202]	CALL     	1 3 1
	11	[203]	GETGLOBAL	1 -1	; require
	12	[203]	LOADK    	2 -6	; "readhistory"
	13	[203]	CALL     	1 2 2
	14	[203]	SELF     	1 1 -7	; "fileDeleted"
	15	[203]	GETUPVAL 	3 1	; file
	16	[203]	CALL     	1 3 1
	17	[204]	GETTABLE 	1 0 -8	; "instance"
	18	[204]	TEST     	1 0 0
	19	[204]	JMP      	5	; to 25
	20	[205]	GETTABLE 	1 0 -8	; "instance"
	21	[205]	GETTABLE 	1 1 -9	; "file_chooser"
	22	[205]	SELF     	1 1 -10	; "refreshPath"
	23	[205]	CALL     	1 2 1
	24	[205]	JMP      	2	; to 27
	25	[207]	SELF     	1 0 -11	; "showFiles"
	26	[207]	CALL     	1 2 1
	27	[209]	RETURN   	0 1

function <./frontend/apps/reader/modules/readerstatus.lua:213,227> (31 instructions, 124 bytes at 0x7fc2f7c0a6a0)
2 params, 7 slots, 2 upvalues, 3 locals, 12 constants, 0 functions
	1	[214]	GETUPVAL 	2 0	; BookStatusWidget
	2	[214]	SELF     	2 2 -1	; "new"
	3	[214]	NEWTABLE 	4 0 5
	4	[215]	GETTABLE 	5 0 -3	; "document"
	5	[215]	SELF     	5 5 -4	; "getCoverPageImage"
	6	[215]	CALL     	5 2 2
	7	[215]	SETTABLE 	4 -2 5	; "thumbnail" -
	8	[216]	GETTABLE 	5 0 -3	; "document"
	9	[216]	SELF     	5 5 -6	; "getProps"
	10	[216]	CALL     	5 2 2
	11	[216]	SETTABLE 	4 -5 5	; "props" -
	12	[217]	GETTABLE 	5 0 -3	; "document"
	13	[217]	SETTABLE 	4 -3 5	; "document" -
	14	[218]	GETTABLE 	5 0 -7	; "settings"
	15	[218]	SETTABLE 	4 -7 5	; "settings" -
	16	[219]	GETTABLE 	5 0 -8	; "view"
	17	[219]	SETTABLE 	4 -8 5	; "view" -
	18	[214]	CALL     	2 3 2
	19	[221]	TEST     	1 0 0
	20	[221]	JMP      	2	; to 23
	21	[222]	MOVE     	3 1
	22	[222]	CALL     	3 1 1
	23	[224]	SETTABLE 	2 -9 -10	; "dithered" true
	24	[225]	GETUPVAL 	3 1	; UIManager
	25	[225]	SELF     	3 3 -11	; "show"
	26	[225]	MOVE     	5 2
	27	[225]	LOADK    	6 -12	; "full"
	28	[225]	CALL     	3 4 1
	29	[226]	LOADBOOL 	3 1 0
	30	[226]	RETURN   	3 2
	31	[227]	RETURN   	0 1

function <./frontend/apps/reader/modules/readerstatus.lua:231,248> (40 instructions, 160 bytes at 0x7fc2f7c09e40)
2 params, 4 slots, 0 upvalues, 3 locals, 6 constants, 0 functions
	1	[232]	GETTABLE 	2 0 -1	; "settings"
	2	[232]	GETTABLE 	2 2 -2	; "data"
	3	[232]	GETTABLE 	2 2 -3	; "summary"
	4	[232]	TEST     	2 0 0
	5	[232]	JMP      	29	; to 35
	6	[232]	GETTABLE 	2 0 -1	; "settings"
	7	[232]	GETTABLE 	2 2 -2	; "data"
	8	[232]	GETTABLE 	2 2 -3	; "summary"
	9	[232]	GETTABLE 	2 2 -4	; "status"
	10	[232]	TEST     	2 0 0
	11	[232]	JMP      	23	; to 35
	12	[233]	GETTABLE 	2 0 -1	; "settings"
	13	[233]	GETTABLE 	2 2 -2	; "data"
	14	[233]	GETTABLE 	2 2 -3	; "summary"
	15	[233]	GETTABLE 	2 2 -4	; "status"
	16	[234]	EQ       	0 2 -5	; - "complete"
	17	[234]	JMP      	12	; to 30
	18	[235]	TEST     	1 0 0
	19	[235]	JMP      	5	; to 25
	20	[237]	GETTABLE 	3 0 -1	; "settings"
	21	[237]	GETTABLE 	3 3 -2	; "data"
	22	[237]	GETTABLE 	3 3 -3	; "summary"
	23	[237]	SETTABLE 	3 -4 -5	; "status" "complete"
	24	[237]	JMP      	15	; to 40
	25	[240]	GETTABLE 	3 0 -1	; "settings"
	26	[240]	GETTABLE 	3 3 -2	; "data"
	27	[240]	GETTABLE 	3 3 -3	; "summary"
	28	[240]	SETTABLE 	3 -4 -6	; "status" "reading"
	29	[241]	JMP      	10	; to 40
	30	[243]	GETTABLE 	3 0 -1	; "settings"
	31	[243]	GETTABLE 	3 3 -2	; "data"
	32	[243]	GETTABLE 	3 3 -3	; "summary"
	33	[243]	SETTABLE 	3 -4 -5	; "status" "complete"
	34	[244]	JMP      	5	; to 40
	35	[246]	GETTABLE 	2 0 -1	; "settings"
	36	[246]	GETTABLE 	2 2 -2	; "data"
	37	[246]	NEWTABLE 	3 0 1
	38	[246]	SETTABLE 	3 -4 -5	; "status" "complete"
	39	[246]	SETTABLE 	2 -3 3	; "summary" -
	40	[248]	RETURN   	0 1

function <./frontend/apps/reader/modules/readerstatus.lua:250,252> (2 instructions, 8 bytes at 0x7fc2f7c08a70)
2 params, 2 slots, 0 upvalues, 2 locals, 1 constant, 0 functions
	1	[251]	SETTABLE 	0 -1 1	; "settings" -
	2	[252]	RETURN   	0 1
