
main <./frontend/apps/reader/modules/readerdictionary.lua:0,0> (217 instructions, 868 bytes at 0x7fc712c06900)
0+ params, 32 slots, 0 upvalues, 31 locals, 54 constants, 28 functions
	1	[1]	GETGLOBAL	0 -1	; require
	2	[1]	LOADK    	1 -2	; "ui/bidi"
	3	[1]	CALL     	0 2 2
	4	[2]	GETGLOBAL	1 -1	; require
	5	[2]	LOADK    	2 -3	; "ui/widget/confirmbox"
	6	[2]	CALL     	1 2 2
	7	[3]	GETGLOBAL	2 -1	; require
	8	[3]	LOADK    	3 -4	; "datastorage"
	9	[3]	CALL     	2 2 2
	10	[4]	GETGLOBAL	3 -1	; require
	11	[4]	LOADK    	4 -5	; "device"
	12	[4]	CALL     	3 2 2
	13	[5]	GETGLOBAL	4 -1	; require
	14	[5]	LOADK    	5 -6	; "ui/widget/dictquicklookup"
	15	[5]	CALL     	4 2 2
	16	[6]	GETGLOBAL	5 -1	; require
	17	[6]	LOADK    	6 -7	; "ui/geometry"
	18	[6]	CALL     	5 2 2
	19	[7]	GETGLOBAL	6 -1	; require
	20	[7]	LOADK    	7 -8	; "ui/widget/infomessage"
	21	[7]	CALL     	6 2 2
	22	[8]	GETGLOBAL	7 -1	; require
	23	[8]	LOADK    	8 -9	; "ui/widget/container/inputcontainer"
	24	[8]	CALL     	7 2 2
	25	[9]	GETGLOBAL	8 -1	; require
	26	[9]	LOADK    	9 -10	; "ui/widget/inputdialog"
	27	[9]	CALL     	8 2 2
	28	[10]	GETGLOBAL	9 -1	; require
	29	[10]	LOADK    	10 -11	; "json"
	30	[10]	CALL     	9 2 2
	31	[11]	GETGLOBAL	10 -1	; require
	32	[11]	LOADK    	11 -12	; "ui/widget/keyvaluepage"
	33	[11]	CALL     	10 2 2
	34	[12]	GETGLOBAL	11 -1	; require
	35	[12]	LOADK    	12 -13	; "luadata"
	36	[12]	CALL     	11 2 2
	37	[13]	GETGLOBAL	12 -1	; require
	38	[13]	LOADK    	13 -14	; "ui/widget/multiconfirmbox"
	39	[13]	CALL     	12 2 2
	40	[14]	GETGLOBAL	13 -1	; require
	41	[14]	LOADK    	14 -15	; "ui/network/manager"
	42	[14]	CALL     	13 2 2
	43	[15]	GETGLOBAL	14 -1	; require
	44	[15]	LOADK    	15 -16	; "ui/trapper"
	45	[15]	CALL     	14 2 2
	46	[16]	GETGLOBAL	15 -1	; require
	47	[16]	LOADK    	16 -17	; "ui/uimanager"
	48	[16]	CALL     	15 2 2
	49	[17]	GETGLOBAL	16 -1	; require
	50	[17]	LOADK    	17 -18	; "ffi/util"
	51	[17]	CALL     	16 2 2
	52	[18]	GETGLOBAL	17 -1	; require
	53	[18]	LOADK    	18 -19	; "logger"
	54	[18]	CALL     	17 2 2
	55	[19]	GETGLOBAL	18 -1	; require
	56	[19]	LOADK    	19 -20	; "util"
	57	[19]	CALL     	18 2 2
	58	[20]	GETGLOBAL	19 -1	; require
	59	[20]	LOADK    	20 -21	; "gettext"
	60	[20]	CALL     	19 2 2
	61	[21]	GETTABLE 	20 3 -22	; "screen"
	62	[22]	GETGLOBAL	21 -1	; require
	63	[22]	LOADK    	22 -18	; "ffi/util"
	64	[22]	CALL     	21 2 2
	65	[22]	GETTABLE 	21 21 -23	; "template"
	66	[26]	LOADNIL  	22 23
	67	[60]	CLOSURE  	24 0	; 0x7fc712c070a0
	68	[60]	MOVE     	0 24
	69	[62]	SELF     	25 7 -24	; "new"
	70	[62]	NEWTABLE 	27 0 4
	71	[63]	SETTABLE 	27 -25 -26	; "data_dir" nil
	72	[64]	NEWTABLE 	28 0 0
	73	[64]	SETTABLE 	27 -27 28	; "dict_window_list" -
	74	[65]	GETGLOBAL	28 -29	; G_reader_settings
	75	[65]	SELF     	28 28 -30	; "isTrue"
	76	[65]	LOADK    	30 -28	; "disable_lookup_history"
	77	[65]	CALL     	28 3 2
	78	[65]	SETTABLE 	27 -28 28	; "disable_lookup_history" -
	79	[66]	MOVE     	28 19
	80	[66]	LOADK    	29 -32	; "Searching dictionary for:\n%1"
	81	[66]	CALL     	28 2 2
	82	[66]	SETTABLE 	27 -31 28	; "lookup_msg" -
	83	[62]	CALL     	25 3 2
	84	[80]	CLOSURE  	26 1	; 0x7fc712c071c0
	85	[100]	CLOSURE  	27 2	; 0x7fc712c086a0
	86	[100]	MOVE     	0 17
	87	[153]	CLOSURE  	28 3	; 0x7fc712c07280
	88	[153]	MOVE     	0 2
	89	[153]	MOVE     	0 22
	90	[153]	MOVE     	0 17
	91	[153]	MOVE     	0 24
	92	[153]	MOVE     	0 26
	93	[153]	MOVE     	0 27
	94	[153]	MOVE     	0 23
	95	[153]	MOVE     	0 11
	96	[102]	SETTABLE 	25 -33 28	; "init" -
	97	[175]	CLOSURE  	28 4	; 0x7fc712c09090
	98	[175]	MOVE     	0 22
	99	[155]	SETTABLE 	25 -34 28	; "updateSdcvDictNamesOptions" -
	100	[379]	CLOSURE  	28 5	; 0x7fc712c09230
	101	[379]	MOVE     	0 19
	102	[379]	MOVE     	0 23
	103	[379]	MOVE     	0 15
	104	[379]	MOVE     	0 10
	105	[379]	MOVE     	0 21
	106	[379]	MOVE     	0 6
	107	[379]	MOVE     	0 0
	108	[379]	MOVE     	0 1
	109	[379]	MOVE     	0 20
	110	[379]	MOVE     	0 3
	111	[177]	SETTABLE 	25 -35 28	; "addToMainMenu" -
	112	[394]	CLOSURE  	28 6	; 0x7fc712c0fc90
	113	[394]	MOVE     	0 17
	114	[394]	MOVE     	0 14
	115	[381]	SETTABLE 	25 -36 28	; "onLookupWord" -
	116	[432]	CLOSURE  	28 7	; 0x7fc712c10640
	117	[432]	MOVE     	0 5
	118	[432]	MOVE     	0 14
	119	[396]	SETTABLE 	25 -37 28	; "onHtmlDictionaryLinkTapped" -
	120	[451]	CLOSURE  	28 8	; 0x7fc712c11000
	121	[451]	MOVE     	0 22
	122	[438]	SETTABLE 	25 -38 28	; "getNumberOfDictionaries" -
	123	[496]	CLOSURE  	28 9	; 0x7fc712c11a20
	124	[496]	MOVE     	0 16
	125	[453]	SETTABLE 	25 -39 28	; "_genDownloadDictionariesMenu" -
	126	[520]	CLOSURE  	28 10	; 0x7fc712c0c510
	127	[520]	MOVE     	0 22
	128	[498]	SETTABLE 	25 -40 28	; "genDictionariesMenu" -
	129	[529]	CLOSURE  	28 11	; 0x7fc712c0ebd0
	130	[529]	MOVE     	0 18
	131	[539]	CLOSURE  	29 12	; 0x7fc712c0fdc0
	132	[539]	MOVE     	0 22
	133	[579]	CLOSURE  	30 13	; 0x7fc712c0a930
	134	[579]	MOVE     	0 29
	135	[579]	MOVE     	0 17
	136	[579]	MOVE     	0 18
	137	[616]	CLOSURE  	31 14	; 0x7fc712c0b030
	138	[616]	MOVE     	0 18
	139	[581]	SETTABLE 	25 -41 31	; "cleanSelection" -
	140	[623]	CLOSURE  	31 15	; 0x7fc712c0ca80
	141	[623]	MOVE     	0 21
	142	[623]	MOVE     	0 6
	143	[623]	MOVE     	0 15
	144	[618]	SETTABLE 	25 -42 31	; "showLookupInfo" -
	145	[631]	CLOSURE  	31 16	; 0x7fc712c0c800
	146	[631]	MOVE     	0 15
	147	[625]	SETTABLE 	25 -43 31	; "dismissLookupInfo" -
	148	[660]	CLOSURE  	31 17	; 0x7fc712c118e0
	149	[660]	MOVE     	0 8
	150	[660]	MOVE     	0 19
	151	[660]	MOVE     	0 15
	152	[633]	SETTABLE 	25 -44 31	; "onShowDictionaryLookup" -
	153	[757]	CLOSURE  	31 18	; 0x7fc712c131b0
	154	[757]	MOVE     	0 28
	155	[757]	MOVE     	0 19
	156	[757]	MOVE     	0 18
	157	[757]	MOVE     	0 14
	158	[757]	MOVE     	0 9
	159	[757]	MOVE     	0 17
	160	[662]	SETTABLE 	25 -45 31	; "startSdcv" -
	161	[797]	CLOSURE  	31 19	; 0x7fc712c14130
	162	[797]	MOVE     	0 19
	163	[797]	MOVE     	0 18
	164	[797]	MOVE     	0 23
	165	[797]	MOVE     	0 3
	166	[797]	MOVE     	0 15
	167	[797]	MOVE     	0 30
	168	[759]	SETTABLE 	25 -46 31	; "stardictLookup" -
	169	[832]	CLOSURE  	31 20	; 0x7fc712c14ec0
	170	[832]	MOVE     	0 17
	171	[832]	MOVE     	0 4
	172	[832]	MOVE     	0 20
	173	[832]	MOVE     	0 15
	174	[799]	SETTABLE 	25 -47 31	; "showDict" -
	175	[861]	CLOSURE  	31 21	; 0x7fc712c15a80
	176	[861]	MOVE     	0 13
	177	[861]	MOVE     	0 19
	178	[861]	MOVE     	0 10
	179	[861]	MOVE     	0 15
	180	[834]	SETTABLE 	25 -48 31	; "showDownload" -
	181	[879]	CLOSURE  	31 22	; 0x7fc712c16150
	182	[879]	MOVE     	0 18
	183	[879]	MOVE     	0 15
	184	[879]	MOVE     	0 1
	185	[879]	MOVE     	0 19
	186	[863]	SETTABLE 	25 -49 31	; "downloadDictionaryPrep" -
	187	[952]	CLOSURE  	31 23	; 0x7fc712c16d90
	188	[952]	MOVE     	0 15
	189	[952]	MOVE     	0 1
	190	[952]	MOVE     	0 21
	191	[952]	MOVE     	0 19
	192	[952]	MOVE     	0 18
	193	[952]	MOVE     	0 6
	194	[952]	MOVE     	0 17
	195	[952]	MOVE     	0 0
	196	[952]	MOVE     	0 22
	197	[881]	SETTABLE 	25 -50 31	; "downloadDictionary" -
	198	[963]	CLOSURE  	31 24	; 0x7fc712c18630
	199	[963]	MOVE     	0 17
	200	[963]	MOVE     	0 15
	201	[963]	MOVE     	0 6
	202	[963]	MOVE     	0 21
	203	[963]	MOVE     	0 19
	204	[954]	SETTABLE 	25 -51 31	; "onUpdateDefaultDict" -
	205	[971]	CLOSURE  	31 25	; 0x7fc712c182c0
	206	[965]	SETTABLE 	25 -52 31	; "onReadSettings" -
	207	[979]	CLOSURE  	31 26	; 0x7fc712c18c40
	208	[979]	MOVE     	0 17
	209	[973]	SETTABLE 	25 -53 31	; "onSaveSettings" -
	210	[1012]	CLOSURE  	31 27	; 0x7fc712c19170
	211	[1012]	MOVE     	0 15
	212	[1012]	MOVE     	0 12
	213	[1012]	MOVE     	0 21
	214	[1012]	MOVE     	0 19
	215	[981]	SETTABLE 	25 -54 31	; "toggleFuzzyDefault" -
	216	[1014]	RETURN   	25 2
	217	[1014]	RETURN   	0 1

function <./frontend/apps/reader/modules/readerdictionary.lua:29,60> (60 instructions, 240 bytes at 0x7fc712c070a0)
1 param, 20 slots, 1 upvalue, 17 locals, 16 constants, 0 functions
	1	[39]	NEWTABLE 	1 0 0
	2	[40]	GETGLOBAL	2 -1	; pcall
	3	[40]	GETGLOBAL	3 -2	; lfs
	4	[40]	GETTABLE 	3 3 -3	; "dir"
	5	[40]	MOVE     	4 0
	6	[40]	CALL     	2 3 4
	7	[41]	TEST     	2 0 0
	8	[41]	JMP      	50	; to 59
	9	[42]	MOVE     	5 3
	10	[42]	MOVE     	6 4
	11	[42]	LOADNIL  	7 7
	12	[42]	JMP      	44	; to 57
	13	[43]	EQ       	1 8 -4	; - "."
	14	[43]	JMP      	42	; to 57
	15	[43]	EQ       	1 8 -5	; - ".."
	16	[43]	JMP      	40	; to 57
	17	[43]	EQ       	1 8 -6	; - "res"
	18	[43]	JMP      	38	; to 57
	19	[44]	MOVE     	9 0
	20	[44]	LOADK    	10 -7	; "/"
	21	[44]	MOVE     	11 8
	22	[44]	CONCAT   	9 9 11
	23	[45]	GETGLOBAL	10 -2	; lfs
	24	[45]	GETTABLE 	10 10 -8	; "attributes"
	25	[45]	MOVE     	11 9
	26	[45]	CALL     	10 2 2
	27	[46]	EQ       	1 10 -9	; - nil
	28	[46]	JMP      	28	; to 57
	29	[47]	GETTABLE 	11 10 -10	; "mode"
	30	[47]	EQ       	0 11 -11	; - "directory"
	31	[47]	JMP      	15	; to 47
	32	[48]	GETUPVAL 	11 0	; getIfosInDir
	33	[48]	MOVE     	12 9
	34	[48]	CALL     	11 2 2
	35	[49]	GETGLOBAL	12 -12	; pairs
	36	[49]	MOVE     	13 11
	37	[49]	CALL     	12 2 4
	38	[49]	JMP      	5	; to 44
	39	[50]	GETGLOBAL	17 -13	; table
	40	[50]	GETTABLE 	17 17 -14	; "insert"
	41	[50]	MOVE     	18 1
	42	[50]	MOVE     	19 16
	43	[50]	CALL     	17 3 1
	44	[49]	TFORLOOP 	12 2
	45	[50]	JMP      	-7	; to 39
	46	[51]	JMP      	10	; to 57
	47	[52]	SELF     	11 9 -15	; "match"
	48	[52]	LOADK    	13 -16	; "%.ifo$"
	49	[52]	CALL     	11 3 2
	50	[52]	TEST     	11 0 0
	51	[52]	JMP      	5	; to 57
	52	[53]	GETGLOBAL	11 -13	; table
	53	[53]	GETTABLE 	11 11 -14	; "insert"
	54	[53]	MOVE     	12 1
	55	[53]	MOVE     	13 9
	56	[53]	CALL     	11 3 1
	57	[42]	TFORLOOP 	5 1
	58	[56]	JMP      	-46	; to 13
	59	[59]	RETURN   	1 2
	60	[60]	RETURN   	0 1

function <./frontend/apps/reader/modules/readerdictionary.lua:71,80> (16 instructions, 64 bytes at 0x7fc712c071c0)
1 param, 5 slots, 0 upvalues, 3 locals, 6 constants, 0 functions
	1	[72]	GETGLOBAL	1 -1	; io
	2	[72]	GETTABLE 	1 1 -2	; "open"
	3	[72]	MOVE     	2 0
	4	[72]	LOADK    	3 -3	; "r"
	5	[72]	CALL     	1 3 2
	6	[73]	TEST     	1 0 1
	7	[73]	JMP      	2	; to 10
	8	[74]	LOADNIL  	2 2
	9	[74]	RETURN   	2 2
	10	[77]	SELF     	2 1 -4	; "read"
	11	[77]	LOADK    	4 -5	; "*all"
	12	[77]	CALL     	2 3 2
	13	[78]	SELF     	3 1 -6	; "close"
	14	[78]	CALL     	3 2 1
	15	[79]	RETURN   	2 2
	16	[80]	RETURN   	0 1

function <./frontend/apps/reader/modules/readerdictionary.lua:91,100> (23 instructions, 92 bytes at 0x7fc712c086a0)
1 param, 6 slots, 1 upvalue, 3 locals, 8 constants, 0 functions
	1	[92]	GETGLOBAL	1 -1	; lfs
	2	[92]	GETTABLE 	1 1 -2	; "attributes"
	3	[92]	MOVE     	2 0
	4	[92]	LOADK    	3 -3	; "mode"
	5	[92]	CALL     	1 3 2
	6	[92]	EQ       	0 1 -4	; - "file"
	7	[92]	JMP      	15	; to 23
	8	[93]	GETGLOBAL	1 -5	; pcall
	9	[93]	GETGLOBAL	2 -6	; dofile
	10	[93]	MOVE     	3 0
	11	[93]	CALL     	1 3 3
	12	[94]	TEST     	1 0 0
	13	[94]	JMP      	4	; to 18
	14	[94]	TEST     	2 0 0
	15	[94]	JMP      	2	; to 18
	16	[95]	RETURN   	2 2
	17	[95]	JMP      	5	; to 23
	18	[97]	GETUPVAL 	3 0	; logger
	19	[97]	GETTABLE 	3 3 -7	; "warn"
	20	[97]	LOADK    	4 -8	; "Dict's user provided file failed:"
	21	[97]	MOVE     	5 2
	22	[97]	CALL     	3 3 1
	23	[100]	RETURN   	0 1

function <./frontend/apps/reader/modules/readerdictionary.lua:102,153> (145 instructions, 580 bytes at 0x7fc712c07280)
1 param, 20 slots, 8 upvalues, 18 locals, 50 constants, 0 functions
	1	[103]	GETTABLE 	1 0 -1	; "ui"
	2	[103]	GETTABLE 	1 1 -2	; "menu"
	3	[103]	SELF     	1 1 -3	; "registerToMainMenu"
	4	[103]	MOVE     	3 0
	5	[103]	CALL     	1 3 1
	6	[104]	GETGLOBAL	1 -5	; STARDICT_DATA_DIR
	7	[104]	TEST     	1 0 1
	8	[104]	JMP      	11	; to 20
	9	[105]	GETGLOBAL	1 -6	; os
	10	[105]	GETTABLE 	1 1 -7	; "getenv"
	11	[105]	LOADK    	2 -5	; "STARDICT_DATA_DIR"
	12	[105]	CALL     	1 2 2
	13	[105]	TEST     	1 0 1
	14	[105]	JMP      	5	; to 20
	15	[106]	GETUPVAL 	1 0	; DataStorage
	16	[106]	SELF     	1 1 -8	; "getDataDir"
	17	[106]	CALL     	1 2 2
	18	[106]	LOADK    	2 -9	; "/data/dict"
	19	[106]	CONCAT   	1 1 2
	20	[106]	SETTABLE 	0 -4 1	; "data_dir" -
	21	[109]	GETUPVAL 	1 1	; available_ifos
	22	[109]	TEST     	1 0 1
	23	[109]	JMP      	105	; to 129
	24	[110]	NEWTABLE 	1 0 0
	25	[110]	SETUPVAL 	1 1	; available_ifos
	26	[111]	GETUPVAL 	1 2	; logger
	27	[111]	GETTABLE 	1 1 -10	; "dbg"
	28	[111]	LOADK    	2 -11	; "Getting list of dictionaries"
	29	[111]	CALL     	1 2 1
	30	[112]	GETUPVAL 	1 3	; getIfosInDir
	31	[112]	GETTABLE 	2 0 -4	; "data_dir"
	32	[112]	CALL     	1 2 2
	33	[113]	GETTABLE 	2 0 -4	; "data_dir"
	34	[113]	LOADK    	3 -12	; "_ext"
	35	[113]	CONCAT   	2 2 3
	36	[114]	GETGLOBAL	3 -13	; lfs
	37	[114]	GETTABLE 	3 3 -14	; "attributes"
	38	[114]	MOVE     	4 2
	39	[114]	LOADK    	5 -15	; "mode"
	40	[114]	CALL     	3 3 2
	41	[114]	EQ       	0 3 -16	; - "directory"
	42	[114]	JMP      	14	; to 57
	43	[115]	GETUPVAL 	3 3	; getIfosInDir
	44	[115]	MOVE     	4 2
	45	[115]	CALL     	3 2 2
	46	[116]	GETGLOBAL	4 -17	; pairs
	47	[116]	MOVE     	5 3
	48	[116]	CALL     	4 2 4
	49	[116]	JMP      	5	; to 55
	50	[117]	GETGLOBAL	9 -18	; table
	51	[117]	GETTABLE 	9 9 -19	; "insert"
	52	[117]	MOVE     	10 1
	53	[117]	MOVE     	11 8
	54	[117]	CALL     	9 3 1
	55	[116]	TFORLOOP 	4 2
	56	[117]	JMP      	-7	; to 50
	57	[120]	GETGLOBAL	3 -17	; pairs
	58	[120]	MOVE     	4 1
	59	[120]	CALL     	3 2 4
	60	[120]	JMP      	48	; to 109
	61	[121]	GETGLOBAL	8 -20	; io
	62	[121]	GETTABLE 	8 8 -21	; "open"
	63	[121]	MOVE     	9 7
	64	[121]	LOADK    	10 -22	; "r"
	65	[121]	CALL     	8 3 2
	66	[122]	TEST     	8 0 0
	67	[122]	JMP      	41	; to 109
	68	[123]	SELF     	9 8 -23	; "read"
	69	[123]	LOADK    	11 -24	; "*all"
	70	[123]	CALL     	9 3 2
	71	[124]	SELF     	10 8 -25	; "close"
	72	[124]	CALL     	10 2 1
	73	[125]	SELF     	10 9 -26	; "match"
	74	[125]	LOADK    	12 -27	; "\nbookname=(.-)\n"
	75	[125]	CALL     	10 3 2
	76	[126]	SELF     	11 9 -28	; "find"
	77	[126]	LOADK    	13 -29	; "sametypesequence=h"
	78	[126]	LOADK    	14 -30	; 1
	79	[126]	LOADBOOL 	15 1 0
	80	[126]	CALL     	11 5 2
	81	[126]	EQ       	0 11 -31	; - nil
	82	[126]	JMP      	1	; to 84
	83	[126]	LOADBOOL 	11 0 1
	84	[126]	LOADBOOL 	11 1 0
	85	[128]	TEST     	10 0 0
	86	[128]	JMP      	22	; to 109
	87	[129]	GETGLOBAL	12 -18	; table
	88	[129]	GETTABLE 	12 12 -19	; "insert"
	89	[129]	GETUPVAL 	13 1	; available_ifos
	90	[129]	NEWTABLE 	14 0 5
	91	[130]	SETTABLE 	14 -32 7	; "file" -
	92	[131]	SETTABLE 	14 -33 10	; "name" -
	93	[132]	SETTABLE 	14 -34 11	; "is_html" -
	94	[133]	GETUPVAL 	15 4	; readDictionaryCss
	95	[133]	SELF     	16 7 -36	; "gsub"
	96	[133]	LOADK    	18 -37	; "%.ifo$"
	97	[133]	LOADK    	19 -38	; ".css"
	98	[133]	CALL     	16 4 0
	99	[133]	CALL     	15 0 2
	100	[133]	SETTABLE 	14 -35 15	; "css" -
	101	[134]	GETUPVAL 	15 5	; getDictionaryFixHtmlFunc
	102	[134]	SELF     	16 7 -36	; "gsub"
	103	[134]	LOADK    	18 -37	; "%.ifo$"
	104	[134]	LOADK    	19 -40	; ".lua"
	105	[134]	CALL     	16 4 0
	106	[134]	CALL     	15 0 2
	107	[134]	SETTABLE 	14 -39 15	; "fix_html_func" -
	108	[129]	CALL     	12 3 1
	109	[120]	TFORLOOP 	3 2
	110	[137]	JMP      	-50	; to 61
	111	[139]	GETUPVAL 	3 2	; logger
	112	[139]	GETTABLE 	3 3 -10	; "dbg"
	113	[139]	LOADK    	4 -41	; "found"
	114	[139]	GETUPVAL 	5 1	; available_ifos
	115	[139]	LEN      	5 5
	116	[139]	LOADK    	6 -42	; "dictionaries"
	117	[139]	CALL     	3 4 1
	118	[141]	GETGLOBAL	3 -43	; G_reader_settings
	119	[141]	SELF     	3 3 -44	; "readSetting"
	120	[141]	LOADK    	5 -45	; "dicts_disabled"
	121	[141]	CALL     	3 3 2
	122	[141]	TEST     	3 0 1
	123	[141]	JMP      	5	; to 129
	124	[145]	GETGLOBAL	3 -43	; G_reader_settings
	125	[145]	SELF     	3 3 -46	; "saveSetting"
	126	[145]	LOADK    	5 -45	; "dicts_disabled"
	127	[145]	NEWTABLE 	6 0 0
	128	[145]	CALL     	3 4 1
	129	[149]	SELF     	1 0 -47	; "updateSdcvDictNamesOptions"
	130	[149]	CALL     	1 2 1
	131	[150]	GETUPVAL 	1 6	; lookup_history
	132	[150]	TEST     	1 0 1
	133	[150]	JMP      	11	; to 145
	134	[151]	GETUPVAL 	1 7	; LuaData
	135	[151]	SELF     	1 1 -21	; "open"
	136	[151]	GETUPVAL 	3 0	; DataStorage
	137	[151]	SELF     	3 3 -48	; "getSettingsDir"
	138	[151]	CALL     	3 2 2
	139	[151]	LOADK    	4 -49	; "/lookup_history.lua"
	140	[151]	CONCAT   	3 3 4
	141	[151]	NEWTABLE 	4 0 1
	142	[151]	SETTABLE 	4 -33 -50	; "name" "LookupHistory"
	143	[151]	CALL     	1 4 2
	144	[151]	SETUPVAL 	1 6	; lookup_history
	145	[153]	RETURN   	0 1

function <./frontend/apps/reader/modules/readerdictionary.lua:155,175> (32 instructions, 128 bytes at 0x7fc712c09090)
1 param, 10 slots, 1 upvalue, 7 locals, 11 constants, 0 functions
	1	[156]	SETTABLE 	0 -1 -2	; "enabled_dict_names" nil
	2	[163]	GETGLOBAL	1 -3	; G_reader_settings
	3	[163]	SELF     	1 1 -4	; "readSetting"
	4	[163]	LOADK    	3 -5	; "dicts_disabled"
	5	[163]	CALL     	1 3 2
	6	[164]	GETGLOBAL	2 -6	; next
	7	[164]	MOVE     	3 1
	8	[164]	CALL     	2 2 2
	9	[164]	TEST     	2 0 1
	10	[164]	JMP      	1	; to 12
	11	[165]	RETURN   	0 1
	12	[167]	GETGLOBAL	2 -7	; pairs
	13	[167]	GETUPVAL 	3 0	; available_ifos
	14	[167]	CALL     	2 2 4
	15	[167]	JMP      	14	; to 30
	16	[168]	GETTABLE 	7 6 -8	; "file"
	17	[168]	GETTABLE 	7 1 7
	18	[168]	TEST     	7 0 1
	19	[168]	JMP      	10	; to 30
	20	[169]	GETTABLE 	7 0 -1	; "enabled_dict_names"
	21	[169]	TEST     	7 0 1
	22	[169]	JMP      	2	; to 25
	23	[170]	NEWTABLE 	7 0 0
	24	[170]	SETTABLE 	0 -1 7	; "enabled_dict_names" -
	25	[172]	GETGLOBAL	7 -9	; table
	26	[172]	GETTABLE 	7 7 -10	; "insert"
	27	[172]	GETTABLE 	8 0 -1	; "enabled_dict_names"
	28	[172]	GETTABLE 	9 6 -11	; "name"
	29	[172]	CALL     	7 3 1
	30	[167]	TFORLOOP 	2 2
	31	[173]	JMP      	-16	; to 16
	32	[175]	RETURN   	0 1

function <./frontend/apps/reader/modules/readerdictionary.lua:177,379> (177 instructions, 708 bytes at 0x7fc712c09230)
2 params, 14 slots, 10 upvalues, 3 locals, 31 constants, 23 functions
	1	[178]	NEWTABLE 	2 0 2
	2	[179]	GETUPVAL 	3 0	; _
	3	[179]	LOADK    	4 -3	; "Dictionary lookup"
	4	[179]	CALL     	3 2 2
	5	[179]	SETTABLE 	2 -2 3	; "text" -
	6	[182]	CLOSURE  	3 0	; 0x7fc712c098c0
	7	[182]	MOVE     	0 0
	8	[182]	SETTABLE 	2 -4 3	; "callback" -
	9	[183]	SETTABLE 	1 -1 2	; "dictionary_lookup" -
	10	[184]	NEWTABLE 	2 0 3
	11	[185]	GETUPVAL 	3 0	; _
	12	[185]	LOADK    	4 -6	; "Dictionary lookup history"
	13	[185]	CALL     	3 2 2
	14	[185]	SETTABLE 	2 -2 3	; "text" -
	15	[188]	CLOSURE  	3 1	; 0x7fc712c09800
	16	[188]	GETUPVAL 	0 1	; lookup_history
	17	[188]	SETTABLE 	2 -7 3	; "enabled_func" -
	18	[211]	CLOSURE  	3 2	; 0x7fc712c0a050
	19	[211]	GETUPVAL 	0 1	; lookup_history
	20	[211]	MOVE     	0 0
	21	[211]	GETUPVAL 	0 2	; UIManager
	22	[211]	GETUPVAL 	0 3	; KeyValuePage
	23	[211]	GETUPVAL 	0 0	; _
	24	[211]	SETTABLE 	2 -4 3	; "callback" -
	25	[212]	SETTABLE 	1 -5 2	; "dictionary_lookup_history" -
	26	[213]	NEWTABLE 	2 0 2
	27	[214]	GETUPVAL 	3 0	; _
	28	[214]	LOADK    	4 -9	; "Dictionary settings"
	29	[214]	CALL     	3 2 2
	30	[214]	SETTABLE 	2 -2 3	; "text" -
	31	[215]	NEWTABLE 	3 9 0
	32	[215]	NEWTABLE 	4 0 3
	33	[224]	CLOSURE  	5 3	; 0x7fc712c09740
	34	[224]	MOVE     	0 0
	35	[224]	GETUPVAL 	0 4	; T
	36	[224]	GETUPVAL 	0 0	; _
	37	[224]	SETTABLE 	4 -11 5	; "text_func" -
	38	[227]	CLOSURE  	5 4	; 0x7fc712c09fd0
	39	[227]	MOVE     	0 0
	40	[227]	SETTABLE 	4 -7 5	; "enabled_func" -
	41	[228]	SELF     	5 0 -12	; "genDictionariesMenu"
	42	[228]	CALL     	5 2 2
	43	[228]	SETTABLE 	4 -10 5	; "sub_item_table" -
	44	[229]	NEWTABLE 	5 0 3
	45	[231]	GETUPVAL 	6 0	; _
	46	[231]	LOADK    	7 -13	; "Info on dictionary order"
	47	[231]	CALL     	6 2 2
	48	[231]	SETTABLE 	5 -2 6	; "text" -
	49	[232]	SETTABLE 	5 -14 -15	; "keep_menu_open" true
	50	[240]	CLOSURE  	6 5	; 0x7fc712c09ba0
	51	[240]	GETUPVAL 	0 2	; UIManager
	52	[240]	GETUPVAL 	0 5	; InfoMessage
	53	[240]	GETUPVAL 	0 4	; T
	54	[240]	GETUPVAL 	0 0	; _
	55	[240]	GETUPVAL 	0 6	; BD
	56	[240]	MOVE     	0 0
	57	[240]	SETTABLE 	5 -4 6	; "callback" -
	58	[241]	NEWTABLE 	6 0 2
	59	[243]	GETUPVAL 	7 0	; _
	60	[243]	LOADK    	8 -16	; "Download dictionaries"
	61	[243]	CALL     	7 2 2
	62	[243]	SETTABLE 	6 -2 7	; "text" -
	63	[244]	SELF     	7 0 -17	; "_genDownloadDictionariesMenu"
	64	[244]	CALL     	7 2 2
	65	[244]	SETTABLE 	6 -10 7	; "sub_item_table" -
	66	[245]	NEWTABLE 	7 0 5
	67	[247]	GETUPVAL 	8 0	; _
	68	[247]	LOADK    	9 -18	; "Enable fuzzy search"
	69	[247]	CALL     	8 2 2
	70	[247]	SETTABLE 	7 -2 8	; "text" -
	71	[250]	CLOSURE  	8 6	; 0x7fc712c0b760
	72	[250]	MOVE     	0 0
	73	[250]	SETTABLE 	7 -19 8	; "checked_func" -
	74	[253]	CLOSURE  	8 7	; 0x7fc712c09a50
	75	[253]	MOVE     	0 0
	76	[253]	SETTABLE 	7 -4 8	; "callback" -
	77	[256]	CLOSURE  	8 8	; 0x7fc712c09e70
	78	[256]	MOVE     	0 0
	79	[256]	SETTABLE 	7 -20 8	; "hold_callback" -
	80	[257]	SETTABLE 	7 -21 -15	; "separator" true
	81	[258]	NEWTABLE 	8 0 3
	82	[260]	GETUPVAL 	9 0	; _
	83	[260]	LOADK    	10 -22	; "Enable dictionary lookup history"
	84	[260]	CALL     	9 2 2
	85	[260]	SETTABLE 	8 -2 9	; "text" -
	86	[263]	CLOSURE  	9 9	; 0x7fc712c0b3b0
	87	[263]	MOVE     	0 0
	88	[263]	SETTABLE 	8 -19 9	; "checked_func" -
	89	[267]	CLOSURE  	9 10	; 0x7fc712c0b490
	90	[267]	MOVE     	0 0
	91	[267]	SETTABLE 	8 -4 9	; "callback" -
	92	[268]	NEWTABLE 	9 0 4
	93	[270]	GETUPVAL 	10 0	; _
	94	[270]	LOADK    	11 -23	; "Clean dictionary lookup history"
	95	[270]	CALL     	10 2 2
	96	[270]	SETTABLE 	9 -2 10	; "text" -
	97	[271]	SETTABLE 	9 -14 -15	; "keep_menu_open" true
	98	[281]	CLOSURE  	10 11	; 0x7fc712c0c450
	99	[281]	GETUPVAL 	0 2	; UIManager
	100	[281]	GETUPVAL 	0 7	; ConfirmBox
	101	[281]	GETUPVAL 	0 0	; _
	102	[281]	GETUPVAL 	0 1	; lookup_history
	103	[281]	SETTABLE 	9 -4 10	; "callback" -
	104	[282]	SETTABLE 	9 -21 -15	; "separator" true
	105	[283]	NEWTABLE 	10 0 3
	106	[285]	GETUPVAL 	11 0	; _
	107	[285]	LOADK    	12 -24	; "Large window"
	108	[285]	CALL     	11 2 2
	109	[285]	SETTABLE 	10 -2 11	; "text" -
	110	[288]	CLOSURE  	11 12	; 0x7fc712c0cc20
	111	[288]	SETTABLE 	10 -19 11	; "checked_func" -
	112	[291]	CLOSURE  	11 13	; 0x7fc712c0cd30
	113	[291]	SETTABLE 	10 -4 11	; "callback" -
	114	[292]	NEWTABLE 	11 0 3
	115	[294]	GETUPVAL 	12 0	; _
	116	[294]	LOADK    	13 -25	; "Justify text"
	117	[294]	CALL     	12 2 2
	118	[294]	SETTABLE 	11 -2 12	; "text" -
	119	[297]	CLOSURE  	12 14	; 0x7fc712c0d0a0
	120	[297]	SETTABLE 	11 -19 12	; "checked_func" -
	121	[300]	CLOSURE  	12 15	; 0x7fc712c0d220
	122	[300]	SETTABLE 	11 -4 12	; "callback" -
	123	[301]	NEWTABLE 	12 0 3
	124	[306]	CLOSURE  	13 16	; 0x7fc712c0d5d0
	125	[306]	GETUPVAL 	0 4	; T
	126	[306]	GETUPVAL 	0 0	; _
	127	[306]	SETTABLE 	12 -11 13	; "text_func" -
	128	[324]	CLOSURE  	13 17	; 0x7fc712c0b330
	129	[324]	GETUPVAL 	0 8	; Screen
	130	[324]	GETUPVAL 	0 0	; _
	131	[324]	GETUPVAL 	0 2	; UIManager
	132	[324]	SETTABLE 	12 -4 13	; "callback" -
	133	[325]	SETTABLE 	12 -14 -15	; "keep_menu_open" true
	134	[327]	SETLIST  	3 9 1	; 1
	135	[327]	SETTABLE 	2 -10 3	; "sub_item_table" -
	136	[328]	SETTABLE 	1 -8 2	; "dictionary_settings" -
	137	[329]	GETUPVAL 	2 9	; Device
	138	[329]	SELF     	2 2 -26	; "canExternalDictLookup"
	139	[329]	CALL     	2 2 2
	140	[329]	TEST     	2 0 0
	141	[329]	JMP      	35	; to 177
	142	[350]	CLOSURE  	2 18	; 0x7fc712c0ded0
	143	[350]	GETUPVAL 	0 9	; Device
	144	[351]	GETGLOBAL	3 -27	; table
	145	[351]	GETTABLE 	3 3 -28	; "insert"
	146	[351]	GETTABLE 	4 1 -8	; "dictionary_settings"
	147	[351]	GETTABLE 	4 4 -10	; "sub_item_table"
	148	[351]	LOADK    	5 -29	; 1
	149	[351]	NEWTABLE 	6 0 3
	150	[352]	GETUPVAL 	7 0	; _
	151	[352]	LOADK    	8 -30	; "Use external dictionary"
	152	[352]	CALL     	7 2 2
	153	[352]	SETTABLE 	6 -2 7	; "text" -
	154	[355]	CLOSURE  	7 19	; 0x7fc712c0f0c0
	155	[355]	SETTABLE 	6 -19 7	; "checked_func" -
	156	[358]	CLOSURE  	7 20	; 0x7fc712c0f3b0
	157	[358]	SETTABLE 	6 -4 7	; "callback" -
	158	[351]	CALL     	3 4 1
	159	[360]	GETGLOBAL	3 -27	; table
	160	[360]	GETTABLE 	3 3 -28	; "insert"
	161	[360]	GETTABLE 	4 1 -8	; "dictionary_settings"
	162	[360]	GETTABLE 	4 4 -10	; "sub_item_table"
	163	[360]	LOADK    	5 -31	; 2
	164	[360]	NEWTABLE 	6 0 4
	165	[371]	CLOSURE  	7 21	; 0x7fc712c0f6f0
	166	[371]	GETUPVAL 	0 0	; _
	167	[371]	GETUPVAL 	0 9	; Device
	168	[371]	GETUPVAL 	0 4	; T
	169	[371]	SETTABLE 	6 -11 7	; "text_func" -
	170	[374]	CLOSURE  	7 22	; 0x7fc712c0f980
	171	[374]	SETTABLE 	6 -7 7	; "enabled_func" -
	172	[375]	MOVE     	7 2
	173	[375]	CALL     	7 1 2
	174	[375]	SETTABLE 	6 -10 7	; "sub_item_table" -
	175	[376]	SETTABLE 	6 -21 -15	; "separator" true
	176	[360]	CALL     	3 4 1
	177	[379]	RETURN   	0 1

function <./frontend/apps/reader/modules/readerdictionary.lua:180,182> (4 instructions, 16 bytes at 0x7fc712c098c0)
0 params, 2 slots, 1 upvalue, 0 locals, 1 constant, 0 functions
	1	[181]	GETUPVAL 	0 0	; self
	2	[181]	SELF     	0 0 -1	; "onShowDictionaryLookup"
	3	[181]	CALL     	0 2 1
	4	[182]	RETURN   	0 1

function <./frontend/apps/reader/modules/readerdictionary.lua:186,188> (6 instructions, 24 bytes at 0x7fc712c09800)
0 params, 3 slots, 1 upvalue, 0 locals, 2 constants, 0 functions
	1	[187]	GETUPVAL 	0 0	; lookup_history
	2	[187]	SELF     	0 0 -1	; "has"
	3	[187]	LOADK    	2 -2	; "lookup_history"
	4	[187]	TAILCALL 	0 3 0
	5	[187]	RETURN   	0 0
	6	[188]	RETURN   	0 1

function <./frontend/apps/reader/modules/readerdictionary.lua:189,211> (56 instructions, 224 bytes at 0x7fc712c0a050)
0 params, 14 slots, 5 upvalues, 8 locals, 20 constants, 1 function
	1	[190]	GETUPVAL 	0 0	; lookup_history
	2	[190]	SELF     	0 0 -1	; "readSetting"
	3	[190]	LOADK    	2 -2	; "lookup_history"
	4	[190]	CALL     	0 3 2
	5	[191]	NEWTABLE 	1 0 0
	6	[192]	LOADNIL  	2 2
	7	[193]	LEN      	3 0
	8	[193]	LOADK    	4 -3	; 1
	9	[193]	LOADK    	5 -4	; -1
	10	[193]	FORPREP  	3 32	; to 43
	11	[194]	GETTABLE 	7 0 6
	12	[195]	GETTABLE 	8 7 -5	; "book_title"
	13	[195]	EQ       	1 8 2
	14	[195]	JMP      	10	; to 25
	15	[196]	GETGLOBAL	8 -6	; table
	16	[196]	GETTABLE 	8 8 -7	; "insert"
	17	[196]	MOVE     	9 1
	18	[196]	NEWTABLE 	10 2 0
	19	[196]	GETTABLE 	11 7 -5	; "book_title"
	20	[196]	LOADK    	12 -8	; ":"
	21	[196]	CONCAT   	11 11 12
	22	[196]	LOADK    	12 -9	; ""
	23	[196]	SETLIST  	10 2 1	; 1
	24	[196]	CALL     	8 3 1
	25	[198]	GETTABLE 	2 7 -5	; "book_title"
	26	[199]	GETGLOBAL	8 -6	; table
	27	[199]	GETTABLE 	8 8 -7	; "insert"
	28	[199]	MOVE     	9 1
	29	[199]	NEWTABLE 	10 2 1
	30	[200]	GETGLOBAL	11 -10	; os
	31	[200]	GETTABLE 	11 11 -11	; "date"
	32	[200]	LOADK    	12 -12	; "%Y-%m-%d %H:%M:%S"
	33	[200]	GETTABLE 	13 7 -13	; "time"
	34	[200]	CALL     	11 3 2
	35	[201]	GETTABLE 	12 7 -14	; "word"
	36	[204]	CLOSURE  	13 0	; 0x7fc712c0a450
	37	[204]	GETUPVAL 	0 1	; self
	38	[204]	MOVE     	0 7
	39	[204]	SETTABLE 	10 -15 13	; "callback" -
	40	[205]	SETLIST  	10 2 1	; 1
	41	[199]	CALL     	8 3 1
	42	[205]	CLOSE    	7
	43	[193]	FORLOOP  	3 -33	; to 11
	44	[207]	GETUPVAL 	3 2	; UIManager
	45	[207]	SELF     	3 3 -16	; "show"
	46	[207]	GETUPVAL 	5 3	; KeyValuePage
	47	[207]	SELF     	5 5 -17	; "new"
	48	[207]	NEWTABLE 	7 0 2
	49	[208]	GETUPVAL 	8 4	; _
	50	[208]	LOADK    	9 -19	; "Dictionary lookup history"
	51	[208]	CALL     	8 2 2
	52	[208]	SETTABLE 	7 -18 8	; "title" -
	53	[209]	SETTABLE 	7 -20 1	; "kv_pairs" -
	54	[207]	CALL     	5 3 0
	55	[207]	CALL     	3 0 1
	56	[211]	RETURN   	0 1

function <./frontend/apps/reader/modules/readerdictionary.lua:202,204> (6 instructions, 24 bytes at 0x7fc712c0a450)
0 params, 3 slots, 2 upvalues, 0 locals, 2 constants, 0 functions
	1	[203]	GETUPVAL 	0 0	; self
	2	[203]	SELF     	0 0 -1	; "onLookupWord"
	3	[203]	GETUPVAL 	2 1	; value
	4	[203]	GETTABLE 	2 2 -2	; "word"
	5	[203]	CALL     	0 3 1
	6	[204]	RETURN   	0 1

function <./frontend/apps/reader/modules/readerdictionary.lua:217,224> (18 instructions, 72 bytes at 0x7fc712c09740)
0 params, 7 slots, 3 upvalues, 4 locals, 4 constants, 0 functions
	1	[218]	GETUPVAL 	0 0	; self
	2	[218]	SELF     	0 0 -1	; "getNumberOfDictionaries"
	3	[218]	CALL     	0 2 4
	4	[219]	MOVE     	3 0
	5	[220]	LT       	0 -2 2	; 0 -
	6	[220]	JMP      	4	; to 11
	7	[221]	MOVE     	4 1
	8	[221]	LOADK    	5 -3	; "/"
	9	[221]	MOVE     	6 0
	10	[221]	CONCAT   	3 4 6
	11	[223]	GETUPVAL 	4 1	; T
	12	[223]	GETUPVAL 	5 2	; _
	13	[223]	LOADK    	6 -4	; "Installed dictionaries (%1)"
	14	[223]	CALL     	5 2 2
	15	[223]	MOVE     	6 3
	16	[223]	TAILCALL 	4 3 0
	17	[223]	RETURN   	4 0
	18	[224]	RETURN   	0 1

function <./frontend/apps/reader/modules/readerdictionary.lua:225,227> (9 instructions, 36 bytes at 0x7fc712c09fd0)
0 params, 2 slots, 1 upvalue, 0 locals, 2 constants, 0 functions
	1	[226]	GETUPVAL 	0 0	; self
	2	[226]	SELF     	0 0 -1	; "getNumberOfDictionaries"
	3	[226]	CALL     	0 2 2
	4	[226]	LT       	1 -2 0	; 0 -
	5	[226]	JMP      	1	; to 7
	6	[226]	LOADBOOL 	0 0 1
	7	[226]	LOADBOOL 	0 1 0
	8	[226]	RETURN   	0 2
	9	[227]	RETURN   	0 1

function <./frontend/apps/reader/modules/readerdictionary.lua:233,240> (19 instructions, 76 bytes at 0x7fc712c09ba0)
0 params, 9 slots, 6 upvalues, 0 locals, 6 constants, 0 functions
	1	[234]	GETUPVAL 	0 0	; UIManager
	2	[234]	SELF     	0 0 -1	; "show"
	3	[234]	GETUPVAL 	2 1	; InfoMessage
	4	[234]	SELF     	2 2 -2	; "new"
	5	[234]	NEWTABLE 	4 0 1
	6	[235]	GETUPVAL 	5 2	; T
	7	[235]	GETUPVAL 	6 3	; _
	8	[238]	LOADK    	7 -4	; "If you'd like to change the order in which dictionaries are queried (and their results displayed), you can:\n- move all dictionary directories out of %1.\n- move them back there, one by one, in the order you want them to be used."
	9	[235]	CALL     	6 2 2
	10	[238]	GETUPVAL 	7 4	; BD
	11	[238]	GETTABLE 	7 7 -5	; "dirpath"
	12	[238]	GETUPVAL 	8 5	; self
	13	[238]	GETTABLE 	8 8 -6	; "data_dir"
	14	[238]	CALL     	7 2 0
	15	[235]	CALL     	5 0 2
	16	[238]	SETTABLE 	4 -3 5	; "text" -
	17	[234]	CALL     	2 3 0
	18	[234]	CALL     	0 0 1
	19	[240]	RETURN   	0 1

function <./frontend/apps/reader/modules/readerdictionary.lua:248,250> (9 instructions, 36 bytes at 0x7fc712c0b760)
0 params, 2 slots, 1 upvalue, 0 locals, 2 constants, 0 functions
	1	[249]	GETUPVAL 	0 0	; self
	2	[249]	GETTABLE 	0 0 -1	; "disable_fuzzy_search"
	3	[249]	NOT      	0 0
	4	[249]	EQ       	1 0 -2	; - true
	5	[249]	JMP      	1	; to 7
	6	[249]	LOADBOOL 	0 0 1
	7	[249]	LOADBOOL 	0 1 0
	8	[249]	RETURN   	0 2
	9	[250]	RETURN   	0 1

function <./frontend/apps/reader/modules/readerdictionary.lua:251,253> (6 instructions, 24 bytes at 0x7fc712c09a50)
0 params, 2 slots, 1 upvalue, 0 locals, 1 constant, 0 functions
	1	[252]	GETUPVAL 	0 0	; self
	2	[252]	GETUPVAL 	1 0	; self
	3	[252]	GETTABLE 	1 1 -1	; "disable_fuzzy_search"
	4	[252]	NOT      	1 1
	5	[252]	SETTABLE 	0 -1 1	; "disable_fuzzy_search" -
	6	[253]	RETURN   	0 1

function <./frontend/apps/reader/modules/readerdictionary.lua:254,256> (4 instructions, 16 bytes at 0x7fc712c09e70)
0 params, 2 slots, 1 upvalue, 0 locals, 1 constant, 0 functions
	1	[255]	GETUPVAL 	0 0	; self
	2	[255]	SELF     	0 0 -1	; "toggleFuzzyDefault"
	3	[255]	CALL     	0 2 1
	4	[256]	RETURN   	0 1

function <./frontend/apps/reader/modules/readerdictionary.lua:261,263> (5 instructions, 20 bytes at 0x7fc712c0b3b0)
0 params, 2 slots, 1 upvalue, 0 locals, 1 constant, 0 functions
	1	[262]	GETUPVAL 	0 0	; self
	2	[262]	GETTABLE 	0 0 -1	; "disable_lookup_history"
	3	[262]	NOT      	0 0
	4	[262]	RETURN   	0 2
	5	[263]	RETURN   	0 1

function <./frontend/apps/reader/modules/readerdictionary.lua:264,267> (12 instructions, 48 bytes at 0x7fc712c0b490)
0 params, 4 slots, 1 upvalue, 0 locals, 3 constants, 0 functions
	1	[265]	GETUPVAL 	0 0	; self
	2	[265]	GETUPVAL 	1 0	; self
	3	[265]	GETTABLE 	1 1 -1	; "disable_lookup_history"
	4	[265]	NOT      	1 1
	5	[265]	SETTABLE 	0 -1 1	; "disable_lookup_history" -
	6	[266]	GETGLOBAL	0 -2	; G_reader_settings
	7	[266]	SELF     	0 0 -3	; "saveSetting"
	8	[266]	LOADK    	2 -1	; "disable_lookup_history"
	9	[266]	GETUPVAL 	3 0	; self
	10	[266]	GETTABLE 	3 3 -1	; "disable_lookup_history"
	11	[266]	CALL     	0 4 1
	12	[267]	RETURN   	0 1

function <./frontend/apps/reader/modules/readerdictionary.lua:272,281> (19 instructions, 76 bytes at 0x7fc712c0c450)
0 params, 7 slots, 4 upvalues, 0 locals, 7 constants, 1 function
	1	[273]	GETUPVAL 	0 0	; UIManager
	2	[273]	SELF     	0 0 -1	; "show"
	3	[273]	GETUPVAL 	2 1	; ConfirmBox
	4	[273]	SELF     	2 2 -2	; "new"
	5	[273]	NEWTABLE 	4 0 3
	6	[274]	GETUPVAL 	5 2	; _
	7	[274]	LOADK    	6 -4	; "Clean dictionary lookup history?"
	8	[274]	CALL     	5 2 2
	9	[274]	SETTABLE 	4 -3 5	; "text" -
	10	[275]	GETUPVAL 	5 2	; _
	11	[275]	LOADK    	6 -6	; "Clean"
	12	[275]	CALL     	5 2 2
	13	[275]	SETTABLE 	4 -5 5	; "ok_text" -
	14	[279]	CLOSURE  	5 0	; 0x7fc712c0c5a0
	15	[279]	GETUPVAL 	0 3	; lookup_history
	16	[279]	SETTABLE 	4 -7 5	; "ok_callback" -
	17	[273]	CALL     	2 3 0
	18	[273]	CALL     	0 0 1
	19	[281]	RETURN   	0 1

function <./frontend/apps/reader/modules/readerdictionary.lua:276,279> (5 instructions, 20 bytes at 0x7fc712c0c5a0)
0 params, 3 slots, 1 upvalue, 0 locals, 1 constant, 0 functions
	1	[278]	GETUPVAL 	0 0	; lookup_history
	2	[278]	SELF     	0 0 -1	; "reset"
	3	[278]	NEWTABLE 	2 0 0
	4	[278]	CALL     	0 3 1
	5	[279]	RETURN   	0 1

function <./frontend/apps/reader/modules/readerdictionary.lua:286,288> (6 instructions, 24 bytes at 0x7fc712c0cc20)
0 params, 3 slots, 0 upvalues, 0 locals, 3 constants, 0 functions
	1	[287]	GETGLOBAL	0 -1	; G_reader_settings
	2	[287]	SELF     	0 0 -2	; "isTrue"
	3	[287]	LOADK    	2 -3	; "dict_largewindow"
	4	[287]	TAILCALL 	0 3 0
	5	[287]	RETURN   	0 0
	6	[288]	RETURN   	0 1

function <./frontend/apps/reader/modules/readerdictionary.lua:289,291> (5 instructions, 20 bytes at 0x7fc712c0cd30)
0 params, 3 slots, 0 upvalues, 0 locals, 3 constants, 0 functions
	1	[290]	GETGLOBAL	0 -1	; G_reader_settings
	2	[290]	SELF     	0 0 -2	; "flipNilOrFalse"
	3	[290]	LOADK    	2 -3	; "dict_largewindow"
	4	[290]	CALL     	0 3 1
	5	[291]	RETURN   	0 1

function <./frontend/apps/reader/modules/readerdictionary.lua:295,297> (6 instructions, 24 bytes at 0x7fc712c0d0a0)
0 params, 3 slots, 0 upvalues, 0 locals, 3 constants, 0 functions
	1	[296]	GETGLOBAL	0 -1	; G_reader_settings
	2	[296]	SELF     	0 0 -2	; "nilOrTrue"
	3	[296]	LOADK    	2 -3	; "dict_justify"
	4	[296]	TAILCALL 	0 3 0
	5	[296]	RETURN   	0 0
	6	[297]	RETURN   	0 1

function <./frontend/apps/reader/modules/readerdictionary.lua:298,300> (5 instructions, 20 bytes at 0x7fc712c0d220)
0 params, 3 slots, 0 upvalues, 0 locals, 3 constants, 0 functions
	1	[299]	GETGLOBAL	0 -1	; G_reader_settings
	2	[299]	SELF     	0 0 -2	; "flipNilOrTrue"
	3	[299]	LOADK    	2 -3	; "dict_justify"
	4	[299]	CALL     	0 3 1
	5	[300]	RETURN   	0 1

function <./frontend/apps/reader/modules/readerdictionary.lua:303,306> (15 instructions, 60 bytes at 0x7fc712c0d5d0)
0 params, 4 slots, 2 upvalues, 1 local, 5 constants, 0 functions
	1	[304]	GETGLOBAL	0 -1	; G_reader_settings
	2	[304]	SELF     	0 0 -2	; "readSetting"
	3	[304]	LOADK    	2 -3	; "dict_font_size"
	4	[304]	CALL     	0 3 2
	5	[304]	TEST     	0 0 1
	6	[304]	JMP      	1	; to 8
	7	[304]	LOADK    	0 -4	; 20
	8	[305]	GETUPVAL 	1 0	; T
	9	[305]	GETUPVAL 	2 1	; _
	10	[305]	LOADK    	3 -5	; "Font size (%1)"
	11	[305]	CALL     	2 2 2
	12	[305]	MOVE     	3 0
	13	[305]	TAILCALL 	1 3 0
	14	[305]	RETURN   	1 0
	15	[306]	RETURN   	0 1

function <./frontend/apps/reader/modules/readerdictionary.lua:307,324> (38 instructions, 152 bytes at 0x7fc712c0b330)
1 param, 8 slots, 3 upvalues, 4 locals, 22 constants, 1 function
	1	[308]	GETGLOBAL	1 -1	; require
	2	[308]	LOADK    	2 -2	; "ui/widget/spinwidget"
	3	[308]	CALL     	1 2 2
	4	[309]	GETGLOBAL	2 -3	; G_reader_settings
	5	[309]	SELF     	2 2 -4	; "readSetting"
	6	[309]	LOADK    	4 -5	; "dict_font_size"
	7	[309]	CALL     	2 3 2
	8	[309]	TEST     	2 0 1
	9	[309]	JMP      	1	; to 11
	10	[309]	LOADK    	2 -6	; 20
	11	[310]	SELF     	3 1 -7	; "new"
	12	[310]	NEWTABLE 	5 0 8
	13	[311]	GETUPVAL 	6 0	; Screen
	14	[311]	SELF     	6 6 -9	; "getWidth"
	15	[311]	CALL     	6 2 2
	16	[311]	MUL      	6 6 -10	; - 0.6
	17	[311]	SETTABLE 	5 -8 6	; "width" -
	18	[312]	SETTABLE 	5 -11 2	; "value" -
	19	[313]	SETTABLE 	5 -12 -13	; "value_min" 8
	20	[314]	SETTABLE 	5 -14 -15	; "value_max" 32
	21	[315]	SETTABLE 	5 -16 -6	; "default_value" 20
	22	[316]	GETUPVAL 	6 1	; _
	23	[316]	LOADK    	7 -18	; "Set size"
	24	[316]	CALL     	6 2 2
	25	[316]	SETTABLE 	5 -17 6	; "ok_text" -
	26	[317]	GETUPVAL 	6 1	; _
	27	[317]	LOADK    	7 -20	; "Dictionary font size"
	28	[317]	CALL     	6 2 2
	29	[317]	SETTABLE 	5 -19 6	; "title_text" -
	30	[321]	CLOSURE  	6 0	; 0x7fc712c0e010
	31	[321]	MOVE     	0 0
	32	[321]	SETTABLE 	5 -21 6	; "callback" -
	33	[310]	CALL     	3 3 2
	34	[323]	GETUPVAL 	4 2	; UIManager
	35	[323]	SELF     	4 4 -22	; "show"
	36	[323]	MOVE     	6 3
	37	[323]	CALL     	4 3 1
	38	[324]	RETURN   	0 1

function <./frontend/apps/reader/modules/readerdictionary.lua:318,321> (12 instructions, 48 bytes at 0x7fc712c0e010)
1 param, 5 slots, 1 upvalue, 1 local, 5 constants, 0 functions
	1	[319]	GETGLOBAL	1 -1	; G_reader_settings
	2	[319]	SELF     	1 1 -2	; "saveSetting"
	3	[319]	LOADK    	3 -3	; "dict_font_size"
	4	[319]	GETTABLE 	4 0 -4	; "value"
	5	[319]	CALL     	1 4 1
	6	[320]	GETUPVAL 	1 0	; touchmenu_instance
	7	[320]	TEST     	1 0 0
	8	[320]	JMP      	3	; to 12
	9	[320]	GETUPVAL 	1 0	; touchmenu_instance
	10	[320]	SELF     	1 1 -5	; "updateItems"
	11	[320]	CALL     	1 2 1
	12	[321]	RETURN   	0 1

function <./frontend/apps/reader/modules/readerdictionary.lua:330,350> (31 instructions, 124 bytes at 0x7fc712c0ded0)
0 params, 13 slots, 1 upvalue, 9 locals, 11 constants, 3 functions
	1	[331]	NEWTABLE 	0 0 0
	2	[332]	GETGLOBAL	1 -1	; ipairs
	3	[332]	GETUPVAL 	2 0	; Device
	4	[332]	SELF     	2 2 -2	; "getExternalDictLookupList"
	5	[332]	CALL     	2 2 0
	6	[332]	CALL     	1 0 4
	7	[332]	JMP      	20	; to 28
	8	[333]	GETTABLE 	6 5 -3	; 1
	9	[334]	GETTABLE 	7 5 -4	; 2
	10	[335]	GETTABLE 	8 5 -5	; 3
	11	[336]	GETGLOBAL	9 -6	; table
	12	[336]	GETTABLE 	9 9 -7	; "insert"
	13	[336]	MOVE     	10 0
	14	[336]	NEWTABLE 	11 0 4
	15	[337]	SETTABLE 	11 -8 7	; "text" -
	16	[340]	CLOSURE  	12 0	; 0x7fc712c0c050
	17	[340]	MOVE     	0 6
	18	[340]	SETTABLE 	11 -9 12	; "checked_func" -
	19	[343]	CLOSURE  	12 1	; 0x7fc712c0ed90
	20	[343]	MOVE     	0 8
	21	[343]	SETTABLE 	11 -10 12	; "enabled_func" -
	22	[346]	CLOSURE  	12 2	; 0x7fc712c0ee10
	23	[346]	MOVE     	0 5
	24	[346]	SETTABLE 	11 -11 12	; "callback" -
	25	[336]	CALL     	9 3 1
	26	[347]	CLOSE    	6
	27	[347]	CLOSE    	4
	28	[332]	TFORLOOP 	1 2
	29	[347]	JMP      	-22	; to 8
	30	[349]	RETURN   	0 2
	31	[350]	RETURN   	0 1

function <./frontend/apps/reader/modules/readerdictionary.lua:338,340> (11 instructions, 44 bytes at 0x7fc712c0c050)
0 params, 4 slots, 1 upvalue, 0 locals, 3 constants, 0 functions
	1	[339]	GETUPVAL 	0 0	; setting
	2	[339]	GETGLOBAL	1 -1	; G_reader_settings
	3	[339]	SELF     	1 1 -2	; "readSetting"
	4	[339]	LOADK    	3 -3	; "external_dict_lookup_method"
	5	[339]	CALL     	1 3 2
	6	[339]	EQ       	1 0 1
	7	[339]	JMP      	1	; to 9
	8	[339]	LOADBOOL 	0 0 1
	9	[339]	LOADBOOL 	0 1 0
	10	[339]	RETURN   	0 2
	11	[340]	RETURN   	0 1

function <./frontend/apps/reader/modules/readerdictionary.lua:341,343> (7 instructions, 28 bytes at 0x7fc712c0ed90)
0 params, 2 slots, 1 upvalue, 0 locals, 1 constant, 0 functions
	1	[342]	GETUPVAL 	0 0	; is_enabled
	2	[342]	EQ       	1 0 -1	; - true
	3	[342]	JMP      	1	; to 5
	4	[342]	LOADBOOL 	0 0 1
	5	[342]	LOADBOOL 	0 1 0
	6	[342]	RETURN   	0 2
	7	[343]	RETURN   	0 1

function <./frontend/apps/reader/modules/readerdictionary.lua:344,346> (7 instructions, 28 bytes at 0x7fc712c0ee10)
0 params, 4 slots, 1 upvalue, 0 locals, 4 constants, 0 functions
	1	[345]	GETGLOBAL	0 -1	; G_reader_settings
	2	[345]	SELF     	0 0 -2	; "saveSetting"
	3	[345]	LOADK    	2 -3	; "external_dict_lookup_method"
	4	[345]	GETUPVAL 	3 0	; v
	5	[345]	GETTABLE 	3 3 -4	; 1
	6	[345]	CALL     	0 4 1
	7	[346]	RETURN   	0 1

function <./frontend/apps/reader/modules/readerdictionary.lua:353,355> (6 instructions, 24 bytes at 0x7fc712c0f0c0)
0 params, 3 slots, 0 upvalues, 0 locals, 3 constants, 0 functions
	1	[354]	GETGLOBAL	0 -1	; G_reader_settings
	2	[354]	SELF     	0 0 -2	; "isTrue"
	3	[354]	LOADK    	2 -3	; "external_dict_lookup"
	4	[354]	TAILCALL 	0 3 0
	5	[354]	RETURN   	0 0
	6	[355]	RETURN   	0 1

function <./frontend/apps/reader/modules/readerdictionary.lua:356,358> (5 instructions, 20 bytes at 0x7fc712c0f3b0)
0 params, 3 slots, 0 upvalues, 0 locals, 3 constants, 0 functions
	1	[357]	GETGLOBAL	0 -1	; G_reader_settings
	2	[357]	SELF     	0 0 -2	; "flipNilOrFalse"
	3	[357]	LOADK    	2 -3	; "external_dict_lookup"
	4	[357]	CALL     	0 3 1
	5	[358]	RETURN   	0 1

function <./frontend/apps/reader/modules/readerdictionary.lua:361,371> (28 instructions, 112 bytes at 0x7fc712c0f6f0)
0 params, 8 slots, 3 upvalues, 7 locals, 9 constants, 0 functions
	1	[362]	GETUPVAL 	0 0	; _
	2	[362]	LOADK    	1 -1	; "none"
	3	[362]	CALL     	0 2 2
	4	[363]	GETGLOBAL	1 -2	; G_reader_settings
	5	[363]	SELF     	1 1 -3	; "readSetting"
	6	[363]	LOADK    	3 -4	; "external_dict_lookup_method"
	7	[363]	CALL     	1 3 2
	8	[364]	GETGLOBAL	2 -5	; ipairs
	9	[364]	GETUPVAL 	3 1	; Device
	10	[364]	SELF     	3 3 -6	; "getExternalDictLookupList"
	11	[364]	CALL     	3 2 0
	12	[364]	CALL     	2 0 4
	13	[364]	JMP      	5	; to 19
	14	[365]	GETTABLE 	7 6 -7	; 1
	15	[365]	EQ       	0 7 1
	16	[365]	JMP      	2	; to 19
	17	[366]	GETTABLE 	0 6 -8	; 2
	18	[367]	JMP      	2	; to 21
	19	[364]	TFORLOOP 	2 2
	20	[368]	JMP      	-7	; to 14
	21	[370]	GETUPVAL 	2 2	; T
	22	[370]	GETUPVAL 	3 0	; _
	23	[370]	LOADK    	4 -9	; "Dictionary: %1"
	24	[370]	CALL     	3 2 2
	25	[370]	MOVE     	4 0
	26	[370]	TAILCALL 	2 3 0
	27	[370]	RETURN   	2 0
	28	[371]	RETURN   	0 1

function <./frontend/apps/reader/modules/readerdictionary.lua:372,374> (6 instructions, 24 bytes at 0x7fc712c0f980)
0 params, 3 slots, 0 upvalues, 0 locals, 3 constants, 0 functions
	1	[373]	GETGLOBAL	0 -1	; G_reader_settings
	2	[373]	SELF     	0 0 -2	; "isTrue"
	3	[373]	LOADK    	2 -3	; "external_dict_lookup"
	4	[373]	TAILCALL 	0 3 0
	5	[373]	RETURN   	0 0
	6	[374]	RETURN   	0 1

function <./frontend/apps/reader/modules/readerdictionary.lua:381,394> (27 instructions, 108 bytes at 0x7fc712c0fc90)
5 params, 9 slots, 2 upvalues, 5 locals, 6 constants, 1 function
	1	[382]	GETUPVAL 	5 0	; logger
	2	[382]	GETTABLE 	5 5 -1	; "dbg"
	3	[382]	LOADK    	6 -2	; "dict lookup word:"
	4	[382]	MOVE     	7 1
	5	[382]	MOVE     	8 2
	6	[382]	CALL     	5 4 1
	7	[384]	SELF     	5 0 -3	; "cleanSelection"
	8	[384]	MOVE     	7 1
	9	[384]	CALL     	5 3 2
	10	[384]	MOVE     	1 5
	11	[385]	GETUPVAL 	5 0	; logger
	12	[385]	GETTABLE 	5 5 -1	; "dbg"
	13	[385]	LOADK    	6 -4	; "dict stripped word:"
	14	[385]	MOVE     	7 1
	15	[385]	CALL     	5 3 1
	16	[387]	SETTABLE 	0 -5 3	; "highlight" -
	17	[390]	GETUPVAL 	5 1	; Trapper
	18	[390]	SELF     	5 5 -6	; "wrap"
	19	[392]	CLOSURE  	7 0	; 0x7fc712c104f0
	20	[392]	MOVE     	0 0
	21	[392]	MOVE     	0 1
	22	[392]	MOVE     	0 2
	23	[392]	MOVE     	0 4
	24	[390]	CALL     	5 3 1
	25	[393]	LOADBOOL 	5 1 0
	26	[393]	RETURN   	5 2
	27	[394]	RETURN   	0 1

function <./frontend/apps/reader/modules/readerdictionary.lua:390,392> (12 instructions, 48 bytes at 0x7fc712c104f0)
0 params, 7 slots, 4 upvalues, 0 locals, 3 constants, 0 functions
	1	[391]	GETUPVAL 	0 0	; self
	2	[391]	SELF     	0 0 -1	; "stardictLookup"
	3	[391]	GETUPVAL 	2 1	; word
	4	[391]	GETUPVAL 	3 0	; self
	5	[391]	GETTABLE 	3 3 -2	; "enabled_dict_names"
	6	[391]	GETUPVAL 	4 0	; self
	7	[391]	GETTABLE 	4 4 -3	; "disable_fuzzy_search"
	8	[391]	NOT      	4 4
	9	[391]	GETUPVAL 	5 2	; box
	10	[391]	GETUPVAL 	6 3	; link
	11	[391]	CALL     	0 7 1
	12	[392]	RETURN   	0 1

function <./frontend/apps/reader/modules/readerdictionary.lua:396,432> (66 instructions, 264 bytes at 0x7fc712c10640)
3 params, 11 slots, 2 upvalues, 6 locals, 22 constants, 1 function
	1	[397]	GETTABLE 	3 2 -1	; "uri"
	2	[397]	TEST     	3 0 1
	3	[397]	JMP      	1	; to 5
	4	[398]	RETURN   	0 1
	5	[403]	LOADK    	3 -2	; "bword://"
	6	[404]	LOADNIL  	4 4
	7	[405]	GETTABLE 	5 2 -1	; "uri"
	8	[405]	SELF     	5 5 -3	; "sub"
	9	[405]	LOADK    	7 -4	; 1
	10	[405]	SELF     	8 3 -5	; "len"
	11	[405]	CALL     	8 2 0
	12	[405]	CALL     	5 0 2
	13	[405]	EQ       	0 5 3
	14	[405]	JMP      	8	; to 23
	15	[406]	GETTABLE 	5 2 -1	; "uri"
	16	[406]	SELF     	5 5 -3	; "sub"
	17	[406]	SELF     	7 3 -5	; "len"
	18	[406]	CALL     	7 2 2
	19	[406]	ADD      	7 7 -4	; - 1
	20	[406]	CALL     	5 3 2
	21	[406]	MOVE     	4 5
	22	[406]	JMP      	9	; to 32
	23	[407]	GETTABLE 	5 2 -1	; "uri"
	24	[407]	SELF     	5 5 -6	; "find"
	25	[407]	LOADK    	7 -7	; "://"
	26	[407]	CALL     	5 3 2
	27	[407]	TEST     	5 0 0
	28	[407]	JMP      	2	; to 31
	29	[408]	RETURN   	0 1
	30	[408]	JMP      	1	; to 32
	31	[410]	GETTABLE 	4 2 -1	; "uri"
	32	[413]	EQ       	0 4 -8	; - ""
	33	[413]	JMP      	1	; to 35
	34	[414]	RETURN   	0 1
	35	[417]	GETUPVAL 	5 0	; Geom
	36	[417]	SELF     	5 5 -9	; "new"
	37	[417]	NEWTABLE 	7 0 4
	38	[418]	GETTABLE 	8 2 -11	; "x0"
	39	[418]	SETTABLE 	7 -10 8	; "x" -
	40	[419]	GETTABLE 	8 2 -13	; "y0"
	41	[419]	SETTABLE 	7 -12 8	; "y" -
	42	[420]	GETGLOBAL	8 -15	; math
	43	[420]	GETTABLE 	8 8 -16	; "abs"
	44	[420]	GETTABLE 	9 2 -17	; "x1"
	45	[420]	GETTABLE 	10 2 -11	; "x0"
	46	[420]	SUB      	9 9 10
	47	[420]	CALL     	8 2 2
	48	[420]	SETTABLE 	7 -14 8	; "w" -
	49	[421]	GETGLOBAL	8 -15	; math
	50	[421]	GETTABLE 	8 8 -16	; "abs"
	51	[421]	GETTABLE 	9 2 -19	; "y1"
	52	[421]	GETTABLE 	10 2 -13	; "y0"
	53	[421]	SUB      	9 9 10
	54	[421]	CALL     	8 2 2
	55	[421]	SETTABLE 	7 -18 8	; "h" -
	56	[417]	CALL     	5 3 2
	57	[426]	SETTABLE 	0 -20 -21	; "highlight" nil
	58	[429]	GETUPVAL 	6 1	; Trapper
	59	[429]	SELF     	6 6 -22	; "wrap"
	60	[431]	CLOSURE  	8 0	; 0x7fc712c10f80
	61	[431]	MOVE     	0 0
	62	[431]	MOVE     	0 4
	63	[431]	MOVE     	0 1
	64	[431]	MOVE     	0 5
	65	[429]	CALL     	6 3 1
	66	[432]	RETURN   	0 1

function <./frontend/apps/reader/modules/readerdictionary.lua:429,431> (11 instructions, 44 bytes at 0x7fc712c10f80)
0 params, 7 slots, 4 upvalues, 0 locals, 1 constant, 0 functions
	1	[430]	GETUPVAL 	0 0	; self
	2	[430]	SELF     	0 0 -1	; "stardictLookup"
	3	[430]	GETUPVAL 	2 1	; word
	4	[430]	NEWTABLE 	3 1 0
	5	[430]	GETUPVAL 	4 2	; dictionary
	6	[430]	SETLIST  	3 1 1	; 1
	7	[430]	LOADBOOL 	4 0 0
	8	[430]	GETUPVAL 	5 3	; link_box
	9	[430]	LOADNIL  	6 6
	10	[430]	CALL     	0 7 1
	11	[431]	RETURN   	0 1

function <./frontend/apps/reader/modules/readerdictionary.lua:438,451> (26 instructions, 104 bytes at 0x7fc712c11000)
1 param, 11 slots, 1 upvalue, 10 locals, 7 constants, 0 functions
	1	[439]	GETUPVAL 	1 0	; available_ifos
	2	[439]	LEN      	1 1
	3	[440]	LOADK    	2 -1	; 0
	4	[441]	LOADK    	3 -1	; 0
	5	[442]	GETGLOBAL	4 -2	; G_reader_settings
	6	[442]	SELF     	4 4 -3	; "readSetting"
	7	[442]	LOADK    	6 -4	; "dicts_disabled"
	8	[442]	CALL     	4 3 2
	9	[443]	GETGLOBAL	5 -5	; pairs
	10	[443]	GETUPVAL 	6 0	; available_ifos
	11	[443]	CALL     	5 2 4
	12	[443]	JMP      	7	; to 20
	13	[444]	GETTABLE 	10 9 -6	; "file"
	14	[444]	GETTABLE 	10 4 10
	15	[444]	TEST     	10 0 0
	16	[444]	JMP      	2	; to 19
	17	[445]	ADD      	3 3 -7	; - 1
	18	[445]	JMP      	1	; to 20
	19	[447]	ADD      	2 2 -7	; - 1
	20	[443]	TFORLOOP 	5 2
	21	[448]	JMP      	-9	; to 13
	22	[450]	MOVE     	5 1
	23	[450]	MOVE     	6 2
	24	[450]	MOVE     	7 3
	25	[450]	RETURN   	5 4
	26	[451]	RETURN   	0 1

function <./frontend/apps/reader/modules/readerdictionary.lua:453,496> (78 instructions, 312 bytes at 0x7fc712c11a20)
1 param, 16 slots, 1 upvalue, 28 locals, 15 constants, 1 function
	1	[454]	GETGLOBAL	1 -1	; require
	2	[454]	LOADK    	2 -2	; "ui/data/dictionaries"
	3	[454]	CALL     	1 2 2
	4	[455]	NEWTABLE 	2 0 0
	5	[457]	LOADK    	3 -3	; 1
	6	[457]	LEN      	4 1
	7	[457]	LOADK    	5 -3	; 1
	8	[457]	FORPREP  	3 23	; to 32
	9	[458]	GETTABLE 	7 1 6
	10	[459]	GETTABLE 	8 7 -4	; "lang_in"
	11	[460]	GETTABLE 	9 7 -5	; "lang_out"
	12	[461]	GETTABLE 	10 2 8
	13	[461]	TEST     	10 0 1
	14	[461]	JMP      	2	; to 17
	15	[462]	NEWTABLE 	10 0 0
	16	[462]	SETTABLE 	2 8 10
	17	[464]	GETGLOBAL	10 -6	; table
	18	[464]	GETTABLE 	10 10 -7	; "insert"
	19	[464]	GETTABLE 	11 2 8
	20	[464]	MOVE     	12 7
	21	[464]	CALL     	10 3 1
	22	[465]	GETTABLE 	10 2 9
	23	[465]	TEST     	10 0 1
	24	[465]	JMP      	2	; to 27
	25	[466]	NEWTABLE 	10 0 0
	26	[466]	SETTABLE 	2 9 10
	27	[468]	GETGLOBAL	10 -6	; table
	28	[468]	GETTABLE 	10 10 -7	; "insert"
	29	[468]	GETTABLE 	11 2 9
	30	[468]	MOVE     	12 7
	31	[468]	CALL     	10 3 1
	32	[457]	FORLOOP  	3 -24	; to 9
	33	[472]	GETGLOBAL	3 -8	; pairs
	34	[472]	MOVE     	4 2
	35	[472]	CALL     	3 2 4
	36	[472]	JMP      	18	; to 55
	37	[473]	NEWTABLE 	8 0 0
	38	[474]	NEWTABLE 	9 0 0
	39	[475]	GETGLOBAL	10 -9	; ipairs
	40	[475]	MOVE     	11 7
	41	[475]	CALL     	10 2 4
	42	[475]	JMP      	9	; to 52
	43	[476]	GETTABLE 	15 14 -10	; "name"
	44	[476]	GETTABLE 	15 8 15
	45	[476]	TEST     	15 0 1
	46	[476]	JMP      	5	; to 52
	47	[477]	LEN      	15 9
	48	[477]	ADD      	15 15 -3	; - 1
	49	[477]	SETTABLE 	9 15 14
	50	[478]	GETTABLE 	15 14 -10	; "name"
	51	[478]	SETTABLE 	8 15 -11	; - true
	52	[475]	TFORLOOP 	10 2
	53	[479]	JMP      	-11	; to 43
	54	[481]	SETTABLE 	2 6 9
	55	[472]	TFORLOOP 	3 2
	56	[481]	JMP      	-20	; to 37
	57	[484]	NEWTABLE 	3 0 0
	58	[485]	GETUPVAL 	4 0	; ffiUtil
	59	[485]	GETTABLE 	4 4 -12	; "orderedPairs"
	60	[485]	MOVE     	5 2
	61	[485]	CALL     	4 2 4
	62	[485]	JMP      	12	; to 75
	63	[486]	GETGLOBAL	9 -6	; table
	64	[486]	GETTABLE 	9 9 -7	; "insert"
	65	[486]	MOVE     	10 3
	66	[486]	NEWTABLE 	11 0 3
	67	[487]	SETTABLE 	11 -13 -11	; "keep_menu_open" true
	68	[488]	SETTABLE 	11 -14 7	; "text" -
	69	[491]	CLOSURE  	12 0	; 0x7fc712c11e30
	70	[491]	MOVE     	0 0
	71	[491]	MOVE     	0 8
	72	[491]	SETTABLE 	11 -15 12	; "callback" -
	73	[486]	CALL     	9 3 1
	74	[492]	CLOSE    	7
	75	[485]	TFORLOOP 	4 2
	76	[492]	JMP      	-14	; to 63
	77	[495]	RETURN   	3 2
	78	[496]	RETURN   	0 1

function <./frontend/apps/reader/modules/readerdictionary.lua:489,491> (5 instructions, 20 bytes at 0x7fc712c11e30)
0 params, 3 slots, 2 upvalues, 0 locals, 1 constant, 0 functions
	1	[490]	GETUPVAL 	0 0	; self
	2	[490]	SELF     	0 0 -1	; "showDownload"
	3	[490]	GETUPVAL 	2 1	; available_langs
	4	[490]	CALL     	0 3 1
	5	[491]	RETURN   	0 1

function <./frontend/apps/reader/modules/readerdictionary.lua:498,520> (24 instructions, 96 bytes at 0x7fc712c0c510)
1 param, 11 slots, 1 upvalue, 7 locals, 7 constants, 2 functions
	1	[499]	NEWTABLE 	1 0 0
	2	[500]	GETGLOBAL	2 -1	; pairs
	3	[500]	GETUPVAL 	3 0	; available_ifos
	4	[500]	CALL     	2 2 4
	5	[500]	JMP      	15	; to 21
	6	[501]	GETGLOBAL	7 -2	; table
	7	[501]	GETTABLE 	7 7 -3	; "insert"
	8	[501]	MOVE     	8 1
	9	[501]	NEWTABLE 	9 0 3
	10	[502]	GETTABLE 	10 6 -5	; "name"
	11	[502]	SETTABLE 	9 -4 10	; "text" -
	12	[512]	CLOSURE  	10 0	; 0x7fc712c0d4e0
	13	[512]	MOVE     	0 6
	14	[512]	MOVE     	0 0
	15	[512]	SETTABLE 	9 -6 10	; "callback" -
	16	[516]	CLOSURE  	10 1	; 0x7fc712c0cdd0
	17	[516]	MOVE     	0 6
	18	[516]	SETTABLE 	9 -7 10	; "checked_func" -
	19	[501]	CALL     	7 3 1
	20	[517]	CLOSE    	5
	21	[500]	TFORLOOP 	2 2
	22	[517]	JMP      	-17	; to 6
	23	[519]	RETURN   	1 2
	24	[520]	RETURN   	0 1

function <./frontend/apps/reader/modules/readerdictionary.lua:503,512> (20 instructions, 80 bytes at 0x7fc712c0d4e0)
0 params, 3 slots, 2 upvalues, 1 local, 7 constants, 0 functions
	1	[504]	GETGLOBAL	0 -1	; G_reader_settings
	2	[504]	SELF     	0 0 -2	; "readSetting"
	3	[504]	LOADK    	2 -3	; "dicts_disabled"
	4	[504]	CALL     	0 3 2
	5	[505]	GETUPVAL 	1 0	; ifo
	6	[505]	GETTABLE 	1 1 -4	; "file"
	7	[505]	GETTABLE 	1 0 1
	8	[505]	TEST     	1 0 0
	9	[505]	JMP      	4	; to 14
	10	[506]	GETUPVAL 	1 0	; ifo
	11	[506]	GETTABLE 	1 1 -4	; "file"
	12	[506]	SETTABLE 	0 1 -5	; - nil
	13	[506]	JMP      	3	; to 17
	14	[508]	GETUPVAL 	1 0	; ifo
	15	[508]	GETTABLE 	1 1 -4	; "file"
	16	[508]	SETTABLE 	0 1 -6	; - true
	17	[511]	GETUPVAL 	1 1	; self
	18	[511]	SELF     	1 1 -7	; "updateSdcvDictNamesOptions"
	19	[511]	CALL     	1 2 1
	20	[512]	RETURN   	0 1

function <./frontend/apps/reader/modules/readerdictionary.lua:513,516> (10 instructions, 40 bytes at 0x7fc712c0cdd0)
0 params, 3 slots, 1 upvalue, 1 local, 4 constants, 0 functions
	1	[514]	GETGLOBAL	0 -1	; G_reader_settings
	2	[514]	SELF     	0 0 -2	; "readSetting"
	3	[514]	LOADK    	2 -3	; "dicts_disabled"
	4	[514]	CALL     	0 3 2
	5	[515]	GETUPVAL 	1 0	; ifo
	6	[515]	GETTABLE 	1 1 -4	; "file"
	7	[515]	GETTABLE 	1 0 1
	8	[515]	NOT      	1 1
	9	[515]	RETURN   	1 2
	10	[516]	RETURN   	0 1

function <./frontend/apps/reader/modules/readerdictionary.lua:522,529> (17 instructions, 68 bytes at 0x7fc712c0ebd0)
1 param, 8 slots, 1 upvalue, 6 locals, 2 constants, 0 functions
	1	[523]	GETGLOBAL	1 -1	; ipairs
	2	[523]	MOVE     	2 0
	3	[523]	CALL     	1 2 4
	4	[523]	JMP      	8	; to 13
	5	[524]	GETUPVAL 	6 0	; util
	6	[524]	GETTABLE 	6 6 -2	; "isEmptyDir"
	7	[524]	MOVE     	7 5
	8	[524]	CALL     	6 2 2
	9	[524]	TEST     	6 0 1
	10	[524]	JMP      	2	; to 13
	11	[525]	LOADBOOL 	6 0 0
	12	[525]	RETURN   	6 2
	13	[523]	TFORLOOP 	1 2
	14	[526]	JMP      	-10	; to 5
	15	[528]	LOADBOOL 	1 1 0
	16	[528]	RETURN   	1 2
	17	[529]	RETURN   	0 1

function <./frontend/apps/reader/modules/readerdictionary.lua:531,539> (13 instructions, 52 bytes at 0x7fc712c0fdc0)
1 param, 7 slots, 1 upvalue, 6 locals, 2 constants, 0 functions
	1	[532]	GETGLOBAL	1 -1	; ipairs
	2	[532]	GETUPVAL 	2 0	; available_ifos
	3	[532]	CALL     	1 2 4
	4	[532]	JMP      	4	; to 9
	5	[533]	GETTABLE 	6 5 -2	; "name"
	6	[533]	EQ       	0 6 0
	7	[533]	JMP      	1	; to 9
	8	[534]	RETURN   	5 2
	9	[532]	TFORLOOP 	1 2
	10	[535]	JMP      	-6	; to 5
	11	[538]	LOADNIL  	1 1
	12	[538]	RETURN   	1 2
	13	[539]	RETURN   	0 1

function <./frontend/apps/reader/modules/readerdictionary.lua:541,579> (82 instructions, 328 bytes at 0x7fc712c0a930)
1 param, 14 slots, 3 upvalues, 12 locals, 20 constants, 0 functions
	1	[542]	LOADK    	1 -1	; "<!%[CDATA%[(.-)%]%]>"
	2	[543]	LOADK    	2 -2	; "&[29Ib%+]{(.-)}"
	3	[544]	GETGLOBAL	3 -3	; ipairs
	4	[544]	MOVE     	4 0
	5	[544]	CALL     	3 2 4
	6	[544]	JMP      	72	; to 79
	7	[545]	GETUPVAL 	8 0	; getAvailableIfoByName
	8	[545]	GETTABLE 	9 7 -4	; "dict"
	9	[545]	CALL     	8 2 2
	10	[546]	TEST     	8 0 0
	11	[546]	JMP      	24	; to 36
	12	[546]	GETTABLE 	9 8 -5	; "is_html"
	13	[546]	TEST     	9 0 0
	14	[546]	JMP      	21	; to 36
	15	[547]	GETTABLE 	9 8 -5	; "is_html"
	16	[547]	SETTABLE 	7 -5 9	; "is_html" -
	17	[548]	GETTABLE 	9 8 -6	; "css"
	18	[548]	SETTABLE 	7 -6 9	; "css" -
	19	[549]	GETTABLE 	9 8 -7	; "fix_html_func"
	20	[549]	TEST     	9 0 0
	21	[549]	JMP      	57	; to 79
	22	[550]	GETGLOBAL	9 -8	; pcall
	23	[550]	GETTABLE 	10 8 -7	; "fix_html_func"
	24	[550]	GETTABLE 	11 7 -9	; "definition"
	25	[550]	CALL     	9 3 3
	26	[551]	TEST     	9 0 0
	27	[551]	JMP      	2	; to 30
	28	[552]	SETTABLE 	7 -9 10	; "definition" -
	29	[552]	JMP      	49	; to 79
	30	[554]	GETUPVAL 	11 1	; logger
	31	[554]	GETTABLE 	11 11 -10	; "warn"
	32	[554]	LOADK    	12 -11	; "Dict's user provided funcion failed:"
	33	[554]	MOVE     	13 10
	34	[554]	CALL     	11 3 1
	35	[556]	JMP      	43	; to 79
	36	[558]	GETTABLE 	9 7 -9	; "definition"
	37	[560]	SELF     	10 9 -12	; "gsub"
	38	[560]	LOADK    	12 -13	; "<[bB][rR] ?/?>"
	39	[560]	LOADK    	13 -14	; "\n"
	40	[560]	CALL     	10 4 2
	41	[560]	MOVE     	9 10
	42	[562]	SELF     	10 9 -15	; "find"
	43	[562]	MOVE     	12 1
	44	[562]	CALL     	10 3 2
	45	[562]	TEST     	10 0 0
	46	[562]	JMP      	16	; to 63
	47	[563]	SELF     	10 9 -12	; "gsub"
	48	[563]	MOVE     	12 1
	49	[563]	LOADK    	13 -16	; "%1"
	50	[563]	CALL     	10 4 2
	51	[563]	MOVE     	9 10
	52	[565]	SELF     	10 9 -15	; "find"
	53	[565]	MOVE     	12 2
	54	[565]	CALL     	10 3 2
	55	[565]	TEST     	10 0 0
	56	[565]	JMP      	6	; to 63
	57	[566]	SELF     	10 9 -12	; "gsub"
	58	[566]	MOVE     	12 2
	59	[566]	LOADK    	13 -16	; "%1"
	60	[566]	CALL     	10 4 2
	61	[566]	MOVE     	9 10
	62	[566]	JMP      	-11	; to 52
	63	[570]	GETUPVAL 	10 2	; util
	64	[570]	GETTABLE 	10 10 -17	; "htmlEntitiesToUtf8"
	65	[570]	MOVE     	11 9
	66	[570]	CALL     	10 2 2
	67	[570]	MOVE     	9 10
	68	[572]	SELF     	10 9 -12	; "gsub"
	69	[572]	LOADK    	12 -18	; "%b<>"
	70	[572]	LOADK    	13 -19	; ""
	71	[572]	CALL     	10 4 2
	72	[572]	MOVE     	9 10
	73	[574]	SELF     	10 9 -12	; "gsub"
	74	[574]	LOADK    	12 -20	; "^%s+"
	75	[574]	LOADK    	13 -19	; ""
	76	[574]	CALL     	10 4 2
	77	[574]	MOVE     	9 10
	78	[575]	SETTABLE 	7 -9 9	; "definition" -
	79	[544]	TFORLOOP 	3 2
	80	[576]	JMP      	-74	; to 7
	81	[578]	RETURN   	0 2
	82	[579]	RETURN   	0 1

function <./frontend/apps/reader/modules/readerdictionary.lua:581,616> (56 instructions, 224 bytes at 0x7fc712c0b030)
2 params, 6 slots, 1 upvalue, 2 locals, 12 constants, 0 functions
	1	[583]	TEST     	1 0 1
	2	[583]	JMP      	2	; to 5
	3	[584]	LOADK    	2 -1	; ""
	4	[584]	RETURN   	2 2
	5	[591]	SELF     	2 1 -2	; "gsub"
	6	[591]	LOADK    	4 -3	; "^%s+"
	7	[591]	LOADK    	5 -1	; ""
	8	[591]	CALL     	2 4 2
	9	[591]	MOVE     	1 2
	10	[592]	SELF     	2 1 -2	; "gsub"
	11	[592]	LOADK    	4 -4	; "%s+$"
	12	[592]	LOADK    	5 -1	; ""
	13	[592]	CALL     	2 4 2
	14	[592]	MOVE     	1 2
	15	[595]	SELF     	2 1 -2	; "gsub"
	16	[595]	LOADK    	4 -5	; "xE2x80x99"
	17	[595]	LOADK    	5 -6	; "'"
	18	[595]	CALL     	2 4 2
	19	[595]	MOVE     	1 2
	20	[597]	GETUPVAL 	2 0	; util
	21	[597]	GETTABLE 	2 2 -7	; "stripPunctuation"
	22	[597]	MOVE     	3 1
	23	[597]	CALL     	2 2 2
	24	[597]	MOVE     	1 2
	25	[599]	SELF     	2 1 -2	; "gsub"
	26	[599]	LOADK    	4 -8	; "'s$"
	27	[599]	LOADK    	5 -1	; ""
	28	[599]	CALL     	2 4 2
	29	[599]	MOVE     	1 2
	30	[601]	SELF     	2 1 -2	; "gsub"
	31	[601]	LOADK    	4 -9	; "^[LSDMNTlsdmnt]'"
	32	[601]	LOADK    	5 -1	; ""
	33	[601]	CALL     	2 4 2
	34	[601]	MOVE     	1 2
	35	[602]	SELF     	2 1 -2	; "gsub"
	36	[602]	LOADK    	4 -10	; "^[Qq][Uu]'"
	37	[602]	LOADK    	5 -1	; ""
	38	[602]	CALL     	2 4 2
	39	[602]	MOVE     	1 2
	40	[604]	SELF     	2 1 -2	; "gsub"
	41	[604]	LOADK    	4 -11	; "xC2xA0"
	42	[604]	LOADK    	5 -12	; " "
	43	[604]	CALL     	2 4 2
	44	[604]	MOVE     	1 2
	45	[613]	SELF     	2 1 -2	; "gsub"
	46	[613]	LOADK    	4 -3	; "^%s+"
	47	[613]	LOADK    	5 -1	; ""
	48	[613]	CALL     	2 4 2
	49	[613]	MOVE     	1 2
	50	[614]	SELF     	2 1 -2	; "gsub"
	51	[614]	LOADK    	4 -4	; "%s+$"
	52	[614]	LOADK    	5 -1	; ""
	53	[614]	CALL     	2 4 2
	54	[614]	MOVE     	1 2
	55	[615]	RETURN   	1 2
	56	[616]	RETURN   	0 1

function <./frontend/apps/reader/modules/readerdictionary.lua:618,623> (18 instructions, 72 bytes at 0x7fc712c0ca80)
2 params, 6 slots, 3 upvalues, 3 locals, 6 constants, 0 functions
	1	[619]	GETUPVAL 	2 0	; T
	2	[619]	GETTABLE 	3 0 -1	; "lookup_msg"
	3	[619]	MOVE     	4 1
	4	[619]	CALL     	2 3 2
	5	[620]	GETUPVAL 	3 1	; InfoMessage
	6	[620]	SELF     	3 3 -3	; "new"
	7	[620]	NEWTABLE 	5 0 1
	8	[620]	SETTABLE 	5 -4 2	; "text" -
	9	[620]	CALL     	3 3 2
	10	[620]	SETTABLE 	0 -2 3	; "lookup_progress_msg" -
	11	[621]	GETUPVAL 	3 2	; UIManager
	12	[621]	SELF     	3 3 -5	; "show"
	13	[621]	GETTABLE 	5 0 -2	; "lookup_progress_msg"
	14	[621]	CALL     	3 3 1
	15	[622]	GETUPVAL 	3 2	; UIManager
	16	[622]	SELF     	3 3 -6	; "forceRePaint"
	17	[622]	CALL     	3 2 1
	18	[623]	RETURN   	0 1

function <./frontend/apps/reader/modules/readerdictionary.lua:625,631> (9 instructions, 36 bytes at 0x7fc712c0c800)
1 param, 4 slots, 1 upvalue, 1 local, 3 constants, 0 functions
	1	[626]	GETTABLE 	1 0 -1	; "lookup_progress_msg"
	2	[626]	TEST     	1 0 0
	3	[626]	JMP      	4	; to 8
	4	[627]	GETUPVAL 	1 0	; UIManager
	5	[627]	SELF     	1 1 -2	; "close"
	6	[627]	GETTABLE 	3 0 -1	; "lookup_progress_msg"
	7	[627]	CALL     	1 3 1
	8	[630]	SETTABLE 	0 -1 -3	; "lookup_progress_msg" nil
	9	[631]	RETURN   	0 1

function <./frontend/apps/reader/modules/readerdictionary.lua:633,660> (45 instructions, 180 bytes at 0x7fc712c118e0)
1 param, 10 slots, 3 upvalues, 1 local, 16 constants, 2 functions
	1	[634]	GETUPVAL 	1 0	; InputDialog
	2	[634]	SELF     	1 1 -2	; "new"
	3	[634]	NEWTABLE 	3 0 4
	4	[635]	GETUPVAL 	4 1	; _
	5	[635]	LOADK    	5 -4	; "Enter a word to look up"
	6	[635]	CALL     	4 2 2
	7	[635]	SETTABLE 	3 -3 4	; "title" -
	8	[636]	SETTABLE 	3 -5 -6	; "input" ""
	9	[637]	SETTABLE 	3 -7 -8	; "input_type" "text"
	10	[638]	NEWTABLE 	4 1 0
	11	[638]	NEWTABLE 	5 2 0
	12	[639]	NEWTABLE 	6 0 2
	13	[641]	GETUPVAL 	7 1	; _
	14	[641]	LOADK    	8 -10	; "Cancel"
	15	[641]	CALL     	7 2 2
	16	[641]	SETTABLE 	6 -8 7	; "text" -
	17	[644]	CLOSURE  	7 0	; 0x7fc712c12aa0
	18	[644]	GETUPVAL 	0 2	; UIManager
	19	[644]	MOVE     	0 0
	20	[644]	SETTABLE 	6 -11 7	; "callback" -
	21	[645]	NEWTABLE 	7 0 3
	22	[647]	GETUPVAL 	8 1	; _
	23	[647]	LOADK    	9 -12	; "Search dictionary"
	24	[647]	CALL     	8 2 2
	25	[647]	SETTABLE 	7 -8 8	; "text" -
	26	[648]	SETTABLE 	7 -13 -14	; "is_enter_default" true
	27	[652]	CLOSURE  	8 1	; 0x7fc712c12c80
	28	[652]	GETUPVAL 	0 2	; UIManager
	29	[652]	MOVE     	0 0
	30	[652]	SETTABLE 	7 -11 8	; "callback" -
	31	[654]	SETLIST  	5 2 1	; 1
	32	[655]	SETLIST  	4 1 1	; 1
	33	[655]	SETTABLE 	3 -9 4	; "buttons" -
	34	[634]	CALL     	1 3 2
	35	[656]	SETTABLE 	0 -1 1	; "dictionary_lookup_dialog" -
	36	[657]	GETUPVAL 	1 2	; UIManager
	37	[657]	SELF     	1 1 -15	; "show"
	38	[657]	GETTABLE 	3 0 -1	; "dictionary_lookup_dialog"
	39	[657]	CALL     	1 3 1
	40	[658]	GETTABLE 	1 0 -1	; "dictionary_lookup_dialog"
	41	[658]	SELF     	1 1 -16	; "onShowKeyboard"
	42	[658]	CALL     	1 2 1
	43	[659]	LOADBOOL 	1 1 0
	44	[659]	RETURN   	1 2
	45	[660]	RETURN   	0 1

function <./frontend/apps/reader/modules/readerdictionary.lua:642,644> (6 instructions, 24 bytes at 0x7fc712c12aa0)
0 params, 3 slots, 2 upvalues, 0 locals, 2 constants, 0 functions
	1	[643]	GETUPVAL 	0 0	; UIManager
	2	[643]	SELF     	0 0 -1	; "close"
	3	[643]	GETUPVAL 	2 1	; self
	4	[643]	GETTABLE 	2 2 -2	; "dictionary_lookup_dialog"
	5	[643]	CALL     	0 3 1
	6	[644]	RETURN   	0 1

function <./frontend/apps/reader/modules/readerdictionary.lua:649,652> (13 instructions, 52 bytes at 0x7fc712c12c80)
0 params, 4 slots, 2 upvalues, 0 locals, 4 constants, 0 functions
	1	[650]	GETUPVAL 	0 0	; UIManager
	2	[650]	SELF     	0 0 -1	; "close"
	3	[650]	GETUPVAL 	2 1	; self
	4	[650]	GETTABLE 	2 2 -2	; "dictionary_lookup_dialog"
	5	[650]	CALL     	0 3 1
	6	[651]	GETUPVAL 	0 1	; self
	7	[651]	SELF     	0 0 -3	; "onLookupWord"
	8	[651]	GETUPVAL 	2 1	; self
	9	[651]	GETTABLE 	2 2 -2	; "dictionary_lookup_dialog"
	10	[651]	SELF     	2 2 -4	; "getInputText"
	11	[651]	CALL     	2 2 0
	12	[651]	CALL     	0 0 1
	13	[652]	RETURN   	0 1

function <./frontend/apps/reader/modules/readerdictionary.lua:662,757> (158 instructions, 632 bytes at 0x7fc712c131b0)
4 params, 29 slots, 6 upvalues, 31 locals, 37 constants, 0 functions
	1	[663]	NEWTABLE 	4 0 0
	2	[664]	NEWTABLE 	5 0 0
	3	[671]	NEWTABLE 	6 1 0
	4	[671]	GETTABLE 	7 0 -1	; "data_dir"
	5	[671]	SETLIST  	6 1 1	; 1
	6	[672]	GETTABLE 	7 0 -1	; "data_dir"
	7	[672]	LOADK    	8 -2	; "_ext"
	8	[672]	CONCAT   	7 7 8
	9	[673]	GETGLOBAL	8 -3	; lfs
	10	[673]	GETTABLE 	8 8 -4	; "attributes"
	11	[673]	MOVE     	9 7
	12	[673]	LOADK    	10 -5	; "mode"
	13	[673]	CALL     	8 3 2
	14	[673]	EQ       	0 8 -6	; - "directory"
	15	[673]	JMP      	5	; to 21
	16	[674]	GETGLOBAL	8 -7	; table
	17	[674]	GETTABLE 	8 8 -8	; "insert"
	18	[674]	MOVE     	9 6
	19	[674]	MOVE     	10 7
	20	[674]	CALL     	8 3 1
	21	[677]	GETUPVAL 	8 0	; dictDirsEmpty
	22	[677]	MOVE     	9 6
	23	[677]	CALL     	8 2 2
	24	[677]	TEST     	8 0 0
	25	[677]	JMP      	11	; to 37
	26	[678]	NEWTABLE 	8 1 0
	27	[678]	NEWTABLE 	9 0 3
	28	[680]	SETTABLE 	9 -9 -10	; "dict" ""
	29	[681]	SETTABLE 	9 -11 1	; "word" -
	30	[682]	GETUPVAL 	10 1	; _
	31	[682]	LOADK    	11 -13	; "No dictionaries installed. Please search for \"Dictionary support\" in the KOReader Wiki to get more information about installing new dictionaries."
	32	[682]	CALL     	10 2 2
	33	[682]	SETTABLE 	9 -12 10	; "definition" -
	34	[684]	SETLIST  	8 1 1	; 1
	35	[684]	MOVE     	4 8
	36	[685]	RETURN   	4 2
	37	[687]	LOADBOOL 	8 0 0
	38	[688]	GETGLOBAL	9 -14	; ipairs
	39	[688]	MOVE     	10 6
	40	[688]	CALL     	9 2 4
	41	[688]	JMP      	93	; to 135
	42	[689]	TEST     	8 0 0
	43	[689]	JMP      	1	; to 45
	44	[690]	JMP      	92	; to 137
	45	[693]	NEWTABLE 	14 8 0
	46	[693]	LOADK    	15 -15	; "./sdcv"
	47	[693]	LOADK    	16 -16	; "--utf8-input"
	48	[693]	LOADK    	17 -17	; "--utf8-output"
	49	[693]	LOADK    	18 -18	; "--json-output"
	50	[693]	LOADK    	19 -19	; "--non-interactive"
	51	[693]	LOADK    	20 -20	; "--data-dir"
	52	[693]	MOVE     	21 13
	53	[693]	MOVE     	22 1
	54	[693]	SETLIST  	14 8 1	; 1
	55	[694]	TEST     	3 0 1
	56	[694]	JMP      	5	; to 62
	57	[695]	GETGLOBAL	15 -7	; table
	58	[695]	GETTABLE 	15 15 -8	; "insert"
	59	[695]	MOVE     	16 14
	60	[695]	LOADK    	17 -21	; "--exact-search"
	61	[695]	CALL     	15 3 1
	62	[697]	TEST     	2 0 0
	63	[697]	JMP      	16	; to 80
	64	[698]	GETGLOBAL	15 -22	; pairs
	65	[698]	MOVE     	16 2
	66	[698]	CALL     	15 2 4
	67	[698]	JMP      	10	; to 78
	68	[699]	GETGLOBAL	20 -7	; table
	69	[699]	GETTABLE 	20 20 -8	; "insert"
	70	[699]	MOVE     	21 14
	71	[699]	LOADK    	22 -23	; "-u"
	72	[699]	CALL     	20 3 1
	73	[700]	GETGLOBAL	20 -7	; table
	74	[700]	GETTABLE 	20 20 -8	; "insert"
	75	[700]	MOVE     	21 14
	76	[700]	MOVE     	22 19
	77	[700]	CALL     	20 3 1
	78	[698]	TFORLOOP 	15 2
	79	[700]	JMP      	-12	; to 68
	80	[704]	GETUPVAL 	15 2	; util
	81	[704]	GETTABLE 	15 15 -24	; "shell_escape"
	82	[704]	MOVE     	16 14
	83	[704]	CALL     	15 2 2
	84	[723]	MOVE     	16 15
	85	[723]	LOADK    	17 -25	; "; echo"
	86	[723]	CONCAT   	15 16 17
	87	[724]	GETUPVAL 	16 3	; Trapper
	88	[724]	SELF     	16 16 -26	; "dismissablePopen"
	89	[724]	MOVE     	18 15
	90	[724]	GETTABLE 	19 0 -27	; "lookup_progress_msg"
	91	[724]	TEST     	19 0 1
	92	[724]	JMP      	1	; to 94
	93	[724]	LOADBOOL 	19 0 0
	94	[724]	CALL     	16 4 3
	95	[725]	NOT      	8 16
	96	[727]	TEST     	17 0 0
	97	[727]	JMP      	37	; to 135
	98	[727]	EQ       	1 17 -28	; - "\n"
	99	[727]	JMP      	35	; to 135
	100	[728]	GETGLOBAL	18 -29	; pcall
	101	[728]	GETUPVAL 	19 4	; JSON
	102	[728]	GETTABLE 	19 19 -30	; "decode"
	103	[728]	MOVE     	20 17
	104	[728]	CALL     	18 3 3
	105	[729]	TEST     	18 0 0
	106	[729]	JMP      	23	; to 130
	107	[729]	TEST     	19 0 0
	108	[729]	JMP      	21	; to 130
	109	[732]	LOADNIL  	20 20
	110	[733]	GETGLOBAL	21 -14	; ipairs
	111	[733]	MOVE     	22 19
	112	[733]	CALL     	21 2 4
	113	[733]	JMP      	13	; to 127
	114	[734]	GETTABLE 	26 25 -9	; "dict"
	115	[734]	GETTABLE 	27 25 -11	; "word"
	116	[734]	GETTABLE 	28 25 -12	; "definition"
	117	[734]	CONCAT   	20 26 28
	118	[735]	GETTABLE 	26 5 20
	119	[735]	EQ       	0 26 -31	; - nil
	120	[735]	JMP      	6	; to 127
	121	[736]	GETGLOBAL	26 -7	; table
	122	[736]	GETTABLE 	26 26 -8	; "insert"
	123	[736]	MOVE     	27 4
	124	[736]	MOVE     	28 25
	125	[736]	CALL     	26 3 1
	126	[737]	SETTABLE 	5 20 -32	; - true
	127	[733]	TFORLOOP 	21 2
	128	[738]	JMP      	-15	; to 114
	129	[739]	JMP      	5	; to 135
	130	[741]	GETUPVAL 	20 5	; logger
	131	[741]	GETTABLE 	20 20 -33	; "warn"
	132	[741]	LOADK    	21 -34	; "JSON data cannot be decoded"
	133	[741]	MOVE     	22 19
	134	[741]	CALL     	20 3 1
	135	[688]	TFORLOOP 	9 2
	136	[743]	JMP      	-95	; to 42
	137	[745]	LEN      	9 4
	138	[745]	EQ       	0 9 -35	; - 0
	139	[745]	JMP      	17	; to 157
	140	[747]	NEWTABLE 	9 1 0
	141	[747]	NEWTABLE 	10 0 3
	142	[749]	SETTABLE 	10 -9 -10	; "dict" ""
	143	[750]	SETTABLE 	10 -11 1	; "word" -
	144	[751]	TEST     	8 0 0
	145	[751]	JMP      	5	; to 151
	146	[751]	GETUPVAL 	11 1	; _
	147	[751]	LOADK    	12 -36	; "Dictionary lookup canceled."
	148	[751]	CALL     	11 2 2
	149	[751]	TEST     	11 0 1
	150	[751]	JMP      	3	; to 154
	151	[751]	GETUPVAL 	11 1	; _
	152	[751]	LOADK    	12 -37	; "No definition found."
	153	[751]	CALL     	11 2 2
	154	[751]	SETTABLE 	10 -12 11	; "definition" -
	155	[753]	SETLIST  	9 1 1	; 1
	156	[753]	MOVE     	4 9
	157	[756]	RETURN   	4 2
	158	[757]	RETURN   	0 1

function <./frontend/apps/reader/modules/readerdictionary.lua:759,797> (96 instructions, 384 bytes at 0x7fc712c14130)
6 params, 13 slots, 6 upvalues, 10 locals, 27 constants, 1 function
	1	[760]	EQ       	0 1 -1	; - ""
	2	[760]	JMP      	1	; to 4
	3	[761]	RETURN   	0 1
	4	[764]	GETTABLE 	6 0 -2	; "disable_lookup_history"
	5	[764]	TEST     	6 0 1
	6	[764]	JMP      	48	; to 55
	7	[765]	GETTABLE 	6 0 -3	; "ui"
	8	[765]	GETTABLE 	6 6 -4	; "doc_settings"
	9	[765]	TEST     	6 0 0
	10	[765]	JMP      	8	; to 19
	11	[765]	GETTABLE 	6 0 -3	; "ui"
	12	[765]	GETTABLE 	6 6 -4	; "doc_settings"
	13	[765]	SELF     	6 6 -5	; "readSetting"
	14	[765]	LOADK    	8 -6	; "doc_props"
	15	[765]	CALL     	6 3 2
	16	[765]	GETTABLE 	6 6 -7	; "title"
	17	[765]	TEST     	6 0 1
	18	[765]	JMP      	3	; to 22
	19	[765]	GETUPVAL 	6 0	; _
	20	[765]	LOADK    	7 -8	; "Dictionary lookup"
	21	[765]	CALL     	6 2 2
	22	[766]	EQ       	0 6 -1	; - ""
	23	[766]	JMP      	20	; to 44
	24	[767]	GETTABLE 	7 0 -3	; "ui"
	25	[767]	GETTABLE 	7 7 -9	; "document"
	26	[767]	TEST     	7 0 0
	27	[767]	JMP      	16	; to 44
	28	[767]	GETTABLE 	7 0 -3	; "ui"
	29	[767]	GETTABLE 	7 7 -9	; "document"
	30	[767]	GETTABLE 	7 7 -10	; "file"
	31	[767]	TEST     	7 0 0
	32	[767]	JMP      	11	; to 44
	33	[768]	GETUPVAL 	7 1	; util
	34	[768]	GETTABLE 	7 7 -11	; "splitFilePathName"
	35	[768]	GETTABLE 	8 0 -3	; "ui"
	36	[768]	GETTABLE 	8 8 -9	; "document"
	37	[768]	GETTABLE 	8 8 -10	; "file"
	38	[768]	CALL     	7 2 3
	39	[769]	GETUPVAL 	9 1	; util
	40	[769]	GETTABLE 	9 9 -12	; "splitFileNameSuffix"
	41	[769]	MOVE     	10 8
	42	[769]	CALL     	9 2 2
	43	[769]	MOVE     	6 9
	44	[772]	GETUPVAL 	7 2	; lookup_history
	45	[772]	SELF     	7 7 -13	; "addTableItem"
	46	[772]	LOADK    	9 -14	; "lookup_history"
	47	[772]	NEWTABLE 	10 0 3
	48	[773]	SETTABLE 	10 -15 6	; "book_title" -
	49	[774]	GETGLOBAL	11 -17	; os
	50	[774]	GETTABLE 	11 11 -16	; "time"
	51	[774]	CALL     	11 1 2
	52	[774]	SETTABLE 	10 -16 11	; "time" -
	53	[775]	SETTABLE 	10 -18 1	; "word" -
	54	[772]	CALL     	7 4 1
	55	[779]	GETUPVAL 	6 3	; Device
	56	[779]	SELF     	6 6 -19	; "canExternalDictLookup"
	57	[779]	CALL     	6 2 2
	58	[779]	TEST     	6 0 0
	59	[779]	JMP      	18	; to 78
	60	[779]	GETGLOBAL	6 -20	; G_reader_settings
	61	[779]	SELF     	6 6 -21	; "isTrue"
	62	[779]	LOADK    	8 -22	; "external_dict_lookup"
	63	[779]	CALL     	6 3 2
	64	[779]	TEST     	6 0 0
	65	[779]	JMP      	12	; to 78
	66	[780]	GETUPVAL 	6 3	; Device
	67	[780]	SELF     	6 6 -23	; "doExternalDictLookup"
	68	[780]	MOVE     	8 1
	69	[780]	GETGLOBAL	9 -20	; G_reader_settings
	70	[780]	SELF     	9 9 -5	; "readSetting"
	71	[780]	LOADK    	11 -24	; "external_dict_lookup_method"
	72	[780]	CALL     	9 3 2
	73	[787]	CLOSURE  	10 0	; 0x7fc712c14310
	74	[787]	MOVE     	0 0
	75	[787]	GETUPVAL 	0 4	; UIManager
	76	[780]	CALL     	6 5 1
	77	[788]	RETURN   	0 1
	78	[791]	TEST     	3 0 0
	79	[791]	JMP      	3	; to 83
	80	[792]	SELF     	6 0 -25	; "showLookupInfo"
	81	[792]	MOVE     	8 1
	82	[792]	CALL     	6 3 1
	83	[795]	SELF     	6 0 -26	; "startSdcv"
	84	[795]	MOVE     	8 1
	85	[795]	MOVE     	9 2
	86	[795]	MOVE     	10 3
	87	[795]	CALL     	6 5 2
	88	[796]	SELF     	7 0 -27	; "showDict"
	89	[796]	MOVE     	9 1
	90	[796]	GETUPVAL 	10 5	; tidyMarkup
	91	[796]	MOVE     	11 6
	92	[796]	CALL     	10 2 2
	93	[796]	MOVE     	11 4
	94	[796]	MOVE     	12 5
	95	[796]	CALL     	7 6 1
	96	[797]	RETURN   	0 1

function <./frontend/apps/reader/modules/readerdictionary.lua:780,787> (17 instructions, 68 bytes at 0x7fc712c14310)
0 params, 5 slots, 2 upvalues, 1 local, 4 constants, 1 function
	1	[781]	GETUPVAL 	0 0	; self
	2	[781]	GETTABLE 	0 0 -1	; "highlight"
	3	[781]	TEST     	0 0 0
	4	[781]	JMP      	12	; to 17
	5	[782]	GETUPVAL 	0 0	; self
	6	[782]	GETTABLE 	0 0 -1	; "highlight"
	7	[782]	SELF     	0 0 -2	; "getClearId"
	8	[782]	CALL     	0 2 2
	9	[783]	GETUPVAL 	1 1	; UIManager
	10	[783]	SELF     	1 1 -3	; "scheduleIn"
	11	[783]	LOADK    	3 -4	; 0.5
	12	[785]	CLOSURE  	4 0	; 0x7fc712c14410
	13	[785]	GETUPVAL 	0 0	; self
	14	[785]	MOVE     	0 0
	15	[783]	CALL     	1 4 1
	16	[785]	CLOSE    	0
	17	[787]	RETURN   	0 1

function <./frontend/apps/reader/modules/readerdictionary.lua:783,785> (6 instructions, 24 bytes at 0x7fc712c14410)
0 params, 3 slots, 2 upvalues, 0 locals, 2 constants, 0 functions
	1	[784]	GETUPVAL 	0 0	; self
	2	[784]	GETTABLE 	0 0 -1	; "highlight"
	3	[784]	SELF     	0 0 -2	; "clear"
	4	[784]	GETUPVAL 	2 1	; clear_id
	5	[784]	CALL     	0 3 1
	6	[785]	RETURN   	0 1

function <./frontend/apps/reader/modules/readerdictionary.lua:799,832> (61 instructions, 244 bytes at 0x7fc712c14ec0)
5 params, 12 slots, 4 upvalues, 5 locals, 28 constants, 2 functions
	1	[800]	SELF     	5 0 -1	; "dismissLookupInfo"
	2	[800]	CALL     	5 2 1
	3	[801]	TEST     	2 0 0
	4	[801]	JMP      	56	; to 61
	5	[801]	GETTABLE 	5 2 -2	; 1
	6	[801]	TEST     	5 0 0
	7	[801]	JMP      	53	; to 61
	8	[802]	GETUPVAL 	5 0	; logger
	9	[802]	GETTABLE 	5 5 -3	; "dbg"
	10	[802]	LOADK    	6 -4	; "showing quick lookup window"
	11	[802]	MOVE     	7 1
	12	[802]	MOVE     	8 2
	13	[802]	CALL     	5 4 1
	14	[803]	GETUPVAL 	5 1	; DictQuickLookup
	15	[803]	SELF     	5 5 -6	; "new"
	16	[803]	NEWTABLE 	7 0 14
	17	[804]	GETTABLE 	8 0 -8	; "dict_window_list"
	18	[804]	SETTABLE 	7 -7 8	; "window_list" -
	19	[805]	GETTABLE 	8 0 -9	; "ui"
	20	[805]	SETTABLE 	7 -9 8	; "ui" -
	21	[806]	GETTABLE 	8 0 -10	; "highlight"
	22	[806]	SETTABLE 	7 -10 8	; "highlight" -
	23	[807]	GETTABLE 	8 0 -11	; "dialog"
	24	[807]	SETTABLE 	7 -11 8	; "dialog" -
	25	[809]	SETTABLE 	7 -12 1	; "word" -
	26	[811]	SETTABLE 	7 -13 4	; "selected_link" -
	27	[812]	SETTABLE 	7 -14 2	; "results" -
	28	[813]	GETTABLE 	8 0 -16	; "default_dictionary"
	29	[813]	SETTABLE 	7 -15 8	; "dictionary" -
	30	[814]	GETUPVAL 	8 2	; Screen
	31	[814]	SELF     	8 8 -18	; "getWidth"
	32	[814]	CALL     	8 2 2
	33	[814]	GETUPVAL 	9 2	; Screen
	34	[814]	SELF     	9 9 -19	; "scaleBySize"
	35	[814]	LOADK    	11 -20	; 80
	36	[814]	CALL     	9 3 2
	37	[814]	SUB      	8 8 9
	38	[814]	SETTABLE 	7 -17 8	; "width" -
	39	[815]	SETTABLE 	7 -21 3	; "word_box" -
	40	[817]	GETTABLE 	8 0 -22	; "is_wiki"
	41	[817]	SETTABLE 	7 -22 8	; "is_wiki" -
	42	[818]	GETTABLE 	8 0 -23	; "wiki_languages"
	43	[818]	SETTABLE 	7 -23 8	; "wiki_languages" -
	44	[824]	CLOSURE  	8 0	; 0x7fc712c151e0
	45	[824]	MOVE     	0 0
	46	[824]	SETTABLE 	7 -24 8	; "refresh_callback" -
	47	[827]	CLOSURE  	8 1	; 0x7fc712c15940
	48	[827]	MOVE     	0 0
	49	[827]	SETTABLE 	7 -25 8	; "html_dictionary_link_tapped_callback" -
	50	[803]	CALL     	5 3 2
	51	[828]	SETTABLE 	0 -5 5	; "dict_window" -
	52	[829]	GETGLOBAL	5 -26	; table
	53	[829]	GETTABLE 	5 5 -27	; "insert"
	54	[829]	GETTABLE 	6 0 -8	; "dict_window_list"
	55	[829]	GETTABLE 	7 0 -5	; "dict_window"
	56	[829]	CALL     	5 3 1
	57	[830]	GETUPVAL 	5 3	; UIManager
	58	[830]	SELF     	5 5 -28	; "show"
	59	[830]	GETTABLE 	7 0 -5	; "dict_window"
	60	[830]	CALL     	5 3 1
	61	[832]	RETURN   	0 1

function <./frontend/apps/reader/modules/readerdictionary.lua:819,824> (10 instructions, 40 bytes at 0x7fc712c151e0)
0 params, 2 slots, 1 upvalue, 0 locals, 3 constants, 0 functions
	1	[820]	GETUPVAL 	0 0	; self
	2	[820]	GETTABLE 	0 0 -1	; "view"
	3	[820]	TEST     	0 0 0
	4	[820]	JMP      	5	; to 10
	5	[822]	GETUPVAL 	0 0	; self
	6	[822]	GETTABLE 	0 0 -1	; "view"
	7	[822]	GETTABLE 	0 0 -2	; "footer"
	8	[822]	SELF     	0 0 -3	; "updateFooter"
	9	[822]	CALL     	0 2 1
	10	[824]	RETURN   	0 1

function <./frontend/apps/reader/modules/readerdictionary.lua:825,827> (6 instructions, 24 bytes at 0x7fc712c15940)
2 params, 6 slots, 1 upvalue, 2 locals, 1 constant, 0 functions
	1	[826]	GETUPVAL 	2 0	; self
	2	[826]	SELF     	2 2 -1	; "onHtmlDictionaryLinkTapped"
	3	[826]	MOVE     	4 0
	4	[826]	MOVE     	5 1
	5	[826]	CALL     	2 4 1
	6	[827]	RETURN   	0 1

function <./frontend/apps/reader/modules/readerdictionary.lua:834,861> (92 instructions, 368 bytes at 0x7fc712c15a80)
2 params, 15 slots, 4 upvalues, 9 locals, 24 constants, 1 function
	1	[835]	NEWTABLE 	2 0 0
	2	[836]	GETGLOBAL	3 -1	; ipairs
	3	[836]	MOVE     	4 1
	4	[836]	CALL     	3 2 4
	5	[836]	JMP      	70	; to 76
	6	[837]	GETGLOBAL	8 -2	; table
	7	[837]	GETTABLE 	8 8 -3	; "insert"
	8	[837]	MOVE     	9 2
	9	[837]	NEWTABLE 	10 2 1
	10	[837]	GETTABLE 	11 7 -4	; "name"
	11	[837]	LOADK    	12 -5	; ""
	12	[844]	CLOSURE  	13 0	; 0x7fc712c15ec0
	13	[844]	GETUPVAL 	0 0	; NetworkMgr
	14	[844]	MOVE     	0 0
	15	[844]	MOVE     	0 7
	16	[844]	SETTABLE 	10 -6 13	; "callback" -
	17	[844]	SETLIST  	10 2 1	; 1
	18	[837]	CALL     	8 3 1
	19	[845]	LOADNIL  	8 8
	20	[846]	GETTABLE 	9 7 -7	; "lang_in"
	21	[846]	GETTABLE 	10 7 -8	; "lang_out"
	22	[846]	EQ       	0 9 10
	23	[846]	JMP      	7	; to 31
	24	[847]	GETGLOBAL	9 -9	; string
	25	[847]	GETTABLE 	9 9 -10	; "format"
	26	[847]	LOADK    	10 -11	; "    %s"
	27	[847]	GETTABLE 	11 7 -7	; "lang_in"
	28	[847]	CALL     	9 3 2
	29	[847]	MOVE     	8 9
	30	[847]	JMP      	7	; to 38
	31	[849]	GETGLOBAL	9 -9	; string
	32	[849]	GETTABLE 	9 9 -10	; "format"
	33	[849]	LOADK    	10 -12	; "    %s\226\128\147%s"
	34	[849]	GETTABLE 	11 7 -7	; "lang_in"
	35	[849]	GETTABLE 	12 7 -8	; "lang_out"
	36	[849]	CALL     	9 4 2
	37	[849]	MOVE     	8 9
	38	[851]	GETGLOBAL	9 -2	; table
	39	[851]	GETTABLE 	9 9 -3	; "insert"
	40	[851]	MOVE     	10 2
	41	[851]	NEWTABLE 	11 2 0
	42	[851]	MOVE     	12 8
	43	[851]	LOADK    	13 -5	; ""
	44	[851]	SETLIST  	11 2 1	; 1
	45	[851]	CALL     	9 3 1
	46	[852]	GETGLOBAL	9 -2	; table
	47	[852]	GETTABLE 	9 9 -3	; "insert"
	48	[852]	MOVE     	10 2
	49	[852]	NEWTABLE 	11 2 0
	50	[852]	LOADK    	12 -13	; "    "
	51	[852]	GETUPVAL 	13 1	; _
	52	[852]	LOADK    	14 -14	; "License"
	53	[852]	CALL     	13 2 2
	54	[852]	CONCAT   	12 12 13
	55	[852]	GETTABLE 	13 7 -15	; "license"
	56	[852]	SETLIST  	11 2 1	; 1
	57	[852]	CALL     	9 3 1
	58	[853]	GETGLOBAL	9 -2	; table
	59	[853]	GETTABLE 	9 9 -3	; "insert"
	60	[853]	MOVE     	10 2
	61	[853]	NEWTABLE 	11 2 0
	62	[853]	LOADK    	12 -13	; "    "
	63	[853]	GETUPVAL 	13 1	; _
	64	[853]	LOADK    	14 -16	; "Entries"
	65	[853]	CALL     	13 2 2
	66	[853]	CONCAT   	12 12 13
	67	[853]	GETTABLE 	13 7 -17	; "entries"
	68	[853]	SETLIST  	11 2 1	; 1
	69	[853]	CALL     	9 3 1
	70	[854]	GETGLOBAL	9 -2	; table
	71	[854]	GETTABLE 	9 9 -3	; "insert"
	72	[854]	MOVE     	10 2
	73	[854]	LOADK    	11 -18	; "----------------------------"
	74	[854]	CALL     	9 3 1
	75	[854]	CLOSE    	6
	76	[836]	TFORLOOP 	3 2
	77	[854]	JMP      	-72	; to 6
	78	[856]	GETUPVAL 	3 2	; KeyValuePage
	79	[856]	SELF     	3 3 -20	; "new"
	80	[856]	NEWTABLE 	5 0 2
	81	[857]	GETUPVAL 	6 1	; _
	82	[857]	LOADK    	7 -22	; "Tap dictionary name to download"
	83	[857]	CALL     	6 2 2
	84	[857]	SETTABLE 	5 -21 6	; "title" -
	85	[858]	SETTABLE 	5 -23 2	; "kv_pairs" -
	86	[856]	CALL     	3 3 2
	87	[859]	SETTABLE 	0 -19 3	; "download_window" -
	88	[860]	GETUPVAL 	3 3	; UIManager
	89	[860]	SELF     	3 3 -24	; "show"
	90	[860]	GETTABLE 	5 0 -19	; "download_window"
	91	[860]	CALL     	3 3 1
	92	[861]	RETURN   	0 1

function <./frontend/apps/reader/modules/readerdictionary.lua:838,844> (14 instructions, 56 bytes at 0x7fc712c15ec0)
0 params, 3 slots, 3 upvalues, 0 locals, 3 constants, 0 functions
	1	[839]	GETUPVAL 	0 0	; NetworkMgr
	2	[839]	SELF     	0 0 -1	; "isOnline"
	3	[839]	CALL     	0 2 2
	4	[839]	TEST     	0 0 1
	5	[839]	JMP      	4	; to 10
	6	[840]	GETUPVAL 	0 0	; NetworkMgr
	7	[840]	SELF     	0 0 -2	; "promptWifiOn"
	8	[840]	CALL     	0 2 1
	9	[841]	RETURN   	0 1
	10	[843]	GETUPVAL 	0 1	; self
	11	[843]	SELF     	0 0 -3	; "downloadDictionaryPrep"
	12	[843]	GETUPVAL 	2 2	; dict
	13	[843]	CALL     	0 3 1
	14	[844]	RETURN   	0 1

function <./frontend/apps/reader/modules/readerdictionary.lua:863,879> (44 instructions, 176 bytes at 0x7fc712c16150)
3 params, 14 slots, 4 upvalues, 7 locals, 17 constants, 1 function
	1	[864]	GETUPVAL 	3 0	; util
	2	[864]	GETTABLE 	3 3 -1	; "splitFilePathName"
	3	[864]	GETTABLE 	4 1 -2	; "url"
	4	[864]	CALL     	3 2 3
	5	[865]	GETGLOBAL	5 -3	; string
	6	[865]	GETTABLE 	5 5 -4	; "format"
	7	[865]	LOADK    	6 -5	; "%s/%s"
	8	[865]	GETTABLE 	7 0 -6	; "data_dir"
	9	[865]	MOVE     	8 4
	10	[865]	CALL     	5 4 2
	11	[867]	GETGLOBAL	6 -7	; require
	12	[867]	LOADK    	7 -8	; "libs/libkoreader-lfs"
	13	[867]	CALL     	6 2 2
	14	[868]	GETTABLE 	7 6 -9	; "attributes"
	15	[868]	MOVE     	8 5
	16	[868]	CALL     	7 2 2
	17	[868]	TEST     	7 0 0
	18	[868]	JMP      	21	; to 40
	19	[869]	GETUPVAL 	7 1	; UIManager
	20	[869]	SELF     	7 7 -10	; "show"
	21	[869]	GETUPVAL 	9 2	; ConfirmBox
	22	[869]	SELF     	9 9 -11	; "new"
	23	[869]	NEWTABLE 	11 0 3
	24	[870]	GETUPVAL 	12 3	; _
	25	[870]	LOADK    	13 -13	; "File already exists. Overwrite?"
	26	[870]	CALL     	12 2 2
	27	[870]	SETTABLE 	11 -12 12	; "text" -
	28	[871]	GETUPVAL 	12 3	; _
	29	[871]	LOADK    	13 -15	; "Overwrite"
	30	[871]	CALL     	12 2 2
	31	[871]	SETTABLE 	11 -14 12	; "ok_text" -
	32	[874]	CLOSURE  	12 0	; 0x7fc712c16fe0
	33	[874]	MOVE     	0 0
	34	[874]	MOVE     	0 1
	35	[874]	MOVE     	0 5
	36	[874]	SETTABLE 	11 -16 12	; "ok_callback" -
	37	[869]	CALL     	9 3 0
	38	[869]	CALL     	7 0 1
	39	[875]	JMP      	4	; to 44
	40	[877]	SELF     	7 0 -17	; "downloadDictionary"
	41	[877]	MOVE     	9 1
	42	[877]	MOVE     	10 5
	43	[877]	CALL     	7 4 1
	44	[879]	RETURN   	0 1

function <./frontend/apps/reader/modules/readerdictionary.lua:872,874> (6 instructions, 24 bytes at 0x7fc712c16fe0)
0 params, 4 slots, 3 upvalues, 0 locals, 1 constant, 0 functions
	1	[873]	GETUPVAL 	0 0	; self
	2	[873]	SELF     	0 0 -1	; "downloadDictionary"
	3	[873]	GETUPVAL 	2 1	; dict
	4	[873]	GETUPVAL 	3 2	; download_location
	5	[873]	CALL     	0 4 1
	6	[874]	RETURN   	0 1

function <./frontend/apps/reader/modules/readerdictionary.lua:881,952> (166 instructions, 664 bytes at 0x7fc712c16d90)
4 params, 26 slots, 9 upvalues, 20 locals, 43 constants, 2 functions
	1	[882]	TEST     	3 0 1
	2	[882]	JMP      	1	; to 4
	3	[882]	LOADBOOL 	3 0 0
	4	[883]	GETGLOBAL	4 -1	; require
	5	[883]	LOADK    	5 -2	; "socket"
	6	[883]	CALL     	4 2 2
	7	[884]	GETTABLE 	5 4 -3	; "http"
	8	[885]	GETGLOBAL	6 -1	; require
	9	[885]	LOADK    	7 -4	; "ssl.https"
	10	[885]	CALL     	6 2 2
	11	[886]	GETGLOBAL	7 -1	; require
	12	[886]	LOADK    	8 -5	; "ltn12"
	13	[886]	CALL     	7 2 2
	14	[887]	GETTABLE 	8 4 -6	; "url"
	15	[889]	GETTABLE 	9 8 -7	; "parse"
	16	[889]	GETTABLE 	10 1 -6	; "url"
	17	[889]	CALL     	9 2 2
	18	[890]	GETTABLE 	10 9 -8	; "scheme"
	19	[890]	EQ       	0 10 -3	; - "http"
	20	[890]	JMP      	3	; to 24
	21	[890]	GETTABLE 	10 5 -9	; "request"
	22	[890]	TEST     	10 0 1
	23	[890]	JMP      	1	; to 25
	24	[890]	GETTABLE 	10 6 -9	; "request"
	25	[892]	TEST     	3 0 1
	26	[892]	JMP      	45	; to 72
	27	[893]	LOADNIL  	11 11
	28	[895]	GETTABLE 	12 4 -10	; "skip"
	29	[895]	LOADK    	13 -11	; 1
	30	[895]	MOVE     	14 10
	31	[895]	NEWTABLE 	15 0 2
	32	[896]	SETTABLE 	15 -12 -13	; "method" "HEAD"
	33	[897]	GETTABLE 	16 1 -6	; "url"
	34	[897]	SETTABLE 	15 -6 16	; "url" -
	35	[895]	CALL     	14 2 0
	36	[895]	CALL     	12 0 4
	37	[903]	TESTSET  	11 13 0
	38	[903]	JMP      	1	; to 40
	39	[903]	GETTABLE 	11 13 -14	; "content-length"
	40	[905]	GETUPVAL 	15 0	; UIManager
	41	[905]	SELF     	15 15 -15	; "show"
	42	[905]	GETUPVAL 	17 1	; ConfirmBox
	43	[905]	SELF     	17 17 -16	; "new"
	44	[905]	NEWTABLE 	19 0 3
	45	[906]	GETUPVAL 	20 2	; T
	46	[906]	GETUPVAL 	21 3	; _
	47	[906]	LOADK    	22 -18	; "Dictionary filesize is %1 (%2 bytes). Continue with download?"
	48	[906]	CALL     	21 2 2
	49	[906]	GETUPVAL 	22 4	; util
	50	[906]	GETTABLE 	22 22 -19	; "getFriendlySize"
	51	[906]	MOVE     	23 11
	52	[906]	CALL     	22 2 2
	53	[906]	GETUPVAL 	23 4	; util
	54	[906]	GETTABLE 	23 23 -20	; "getFormattedSize"
	55	[906]	MOVE     	24 11
	56	[906]	CALL     	23 2 0
	57	[906]	CALL     	20 0 2
	58	[906]	SETTABLE 	19 -17 20	; "text" -
	59	[907]	GETUPVAL 	20 3	; _
	60	[907]	LOADK    	21 -22	; "Download"
	61	[907]	CALL     	20 2 2
	62	[907]	SETTABLE 	19 -21 20	; "ok_text" -
	63	[911]	CLOSURE  	20 0	; 0x7fc712c177c0
	64	[911]	MOVE     	0 0
	65	[911]	MOVE     	0 1
	66	[911]	MOVE     	0 2
	67	[911]	SETTABLE 	19 -23 20	; "ok_callback" -
	68	[905]	CALL     	17 3 0
	69	[905]	CALL     	15 0 1
	70	[913]	RETURN   	0 1
	71	[913]	JMP      	7	; to 79
	72	[915]	GETUPVAL 	11 0	; UIManager
	73	[915]	SELF     	11 11 -24	; "nextTick"
	74	[920]	CLOSURE  	13 1	; 0x7fc712c17f70
	75	[920]	GETUPVAL 	0 0	; UIManager
	76	[920]	GETUPVAL 	0 5	; InfoMessage
	77	[920]	GETUPVAL 	0 3	; _
	78	[915]	CALL     	11 3 1
	79	[923]	MOVE     	11 10
	80	[923]	NEWTABLE 	12 0 2
	81	[924]	GETTABLE 	13 1 -6	; "url"
	82	[924]	SETTABLE 	12 -6 13	; "url" -
	83	[925]	GETTABLE 	13 7 -25	; "sink"
	84	[925]	GETTABLE 	13 13 -26	; "file"
	85	[925]	GETGLOBAL	14 -27	; io
	86	[925]	GETTABLE 	14 14 -28	; "open"
	87	[925]	MOVE     	15 2
	88	[925]	LOADK    	16 -29	; "w"
	89	[925]	CALL     	14 3 0
	90	[925]	CALL     	13 0 2
	91	[925]	SETTABLE 	12 -25 13	; "sink" -
	92	[923]	CALL     	11 2 4
	93	[927]	EQ       	0 12 -30	; - 200
	94	[927]	JMP      	6	; to 101
	95	[928]	GETUPVAL 	14 6	; logger
	96	[928]	GETTABLE 	14 14 -31	; "dbg"
	97	[928]	LOADK    	15 -32	; "file downloaded to"
	98	[928]	MOVE     	16 2
	99	[928]	CALL     	14 3 1
	100	[928]	JMP      	18	; to 119
	101	[930]	GETUPVAL 	14 0	; UIManager
	102	[930]	SELF     	14 14 -15	; "show"
	103	[930]	GETUPVAL 	16 5	; InfoMessage
	104	[930]	SELF     	16 16 -16	; "new"
	105	[930]	NEWTABLE 	18 0 1
	106	[931]	GETUPVAL 	19 3	; _
	107	[931]	LOADK    	20 -33	; "Could not save file to:\n"
	108	[931]	CALL     	19 2 2
	109	[931]	GETUPVAL 	20 7	; BD
	110	[931]	GETTABLE 	20 20 -34	; "filepath"
	111	[931]	MOVE     	21 2
	112	[931]	CALL     	20 2 2
	113	[931]	CONCAT   	19 19 20
	114	[931]	SETTABLE 	18 -17 19	; "text" -
	115	[930]	CALL     	16 3 0
	116	[930]	CALL     	14 0 1
	117	[934]	LOADBOOL 	14 0 0
	118	[934]	RETURN   	14 2
	119	[937]	GETUPVAL 	14 4	; util
	120	[937]	GETTABLE 	14 14 -35	; "unpackArchive"
	121	[937]	MOVE     	15 2
	122	[937]	GETTABLE 	16 0 -36	; "data_dir"
	123	[937]	CALL     	14 3 3
	124	[939]	TEST     	14 0 0
	125	[939]	JMP      	20	; to 146
	126	[940]	LOADBOOL 	16 0 0
	127	[940]	SETUPVAL 	16 8	; available_ifos
	128	[941]	SELF     	16 0 -37	; "init"
	129	[941]	CALL     	16 2 1
	130	[942]	GETUPVAL 	16 0	; UIManager
	131	[942]	SELF     	16 16 -15	; "show"
	132	[942]	GETUPVAL 	18 5	; InfoMessage
	133	[942]	SELF     	18 18 -16	; "new"
	134	[942]	NEWTABLE 	20 0 1
	135	[943]	GETUPVAL 	21 3	; _
	136	[943]	LOADK    	22 -38	; "Dictionary downloaded:\n"
	137	[943]	CALL     	21 2 2
	138	[943]	GETTABLE 	22 1 -39	; "name"
	139	[943]	CONCAT   	21 21 22
	140	[943]	SETTABLE 	20 -17 21	; "text" -
	141	[942]	CALL     	18 3 0
	142	[942]	CALL     	16 0 1
	143	[945]	LOADBOOL 	16 1 0
	144	[945]	RETURN   	16 2
	145	[945]	JMP      	20	; to 166
	146	[947]	GETUPVAL 	16 0	; UIManager
	147	[947]	SELF     	16 16 -15	; "show"
	148	[947]	GETUPVAL 	18 5	; InfoMessage
	149	[947]	SELF     	18 18 -16	; "new"
	150	[947]	NEWTABLE 	20 0 1
	151	[948]	GETUPVAL 	21 3	; _
	152	[948]	LOADK    	22 -40	; "Dictionary failed to download:\n"
	153	[948]	CALL     	21 2 2
	154	[948]	GETGLOBAL	22 -41	; string
	155	[948]	GETTABLE 	22 22 -42	; "format"
	156	[948]	LOADK    	23 -43	; "%s\n%s"
	157	[948]	GETTABLE 	24 1 -39	; "name"
	158	[948]	MOVE     	25 15
	159	[948]	CALL     	22 4 2
	160	[948]	CONCAT   	21 21 22
	161	[948]	SETTABLE 	20 -17 21	; "text" -
	162	[947]	CALL     	18 3 0
	163	[947]	CALL     	16 0 1
	164	[950]	LOADBOOL 	16 0 0
	165	[950]	RETURN   	16 2
	166	[952]	RETURN   	0 1

function <./frontend/apps/reader/modules/readerdictionary.lua:908,911> (7 instructions, 28 bytes at 0x7fc712c177c0)
0 params, 5 slots, 3 upvalues, 0 locals, 1 constant, 0 functions
	1	[910]	GETUPVAL 	0 0	; self
	2	[910]	SELF     	0 0 -1	; "downloadDictionary"
	3	[910]	GETUPVAL 	2 1	; dict
	4	[910]	GETUPVAL 	3 2	; download_location
	5	[910]	LOADBOOL 	4 1 0
	6	[910]	CALL     	0 5 1
	7	[911]	RETURN   	0 1

function <./frontend/apps/reader/modules/readerdictionary.lua:915,920> (13 instructions, 52 bytes at 0x7fc712c17f70)
0 params, 7 slots, 3 upvalues, 0 locals, 6 constants, 0 functions
	1	[916]	GETUPVAL 	0 0	; UIManager
	2	[916]	SELF     	0 0 -1	; "show"
	3	[916]	GETUPVAL 	2 1	; InfoMessage
	4	[916]	SELF     	2 2 -2	; "new"
	5	[916]	NEWTABLE 	4 0 2
	6	[917]	GETUPVAL 	5 2	; _
	7	[917]	LOADK    	6 -4	; "Downloading\226\128\166"
	8	[917]	CALL     	5 2 2
	9	[917]	SETTABLE 	4 -3 5	; "text" -
	10	[918]	SETTABLE 	4 -5 -6	; "timeout" 3
	11	[916]	CALL     	2 3 0
	12	[916]	CALL     	0 0 1
	13	[920]	RETURN   	0 1

function <./frontend/apps/reader/modules/readerdictionary.lua:954,963> (24 instructions, 96 bytes at 0x7fc712c18630)
2 params, 10 slots, 5 upvalues, 2 locals, 9 constants, 0 functions
	1	[955]	GETUPVAL 	2 0	; logger
	2	[955]	GETTABLE 	2 2 -1	; "dbg"
	3	[955]	LOADK    	3 -2	; "make default dictionary:"
	4	[955]	MOVE     	4 1
	5	[955]	CALL     	2 3 1
	6	[956]	SETTABLE 	0 -3 1	; "default_dictionary" -
	7	[957]	GETUPVAL 	2 1	; UIManager
	8	[957]	SELF     	2 2 -4	; "show"
	9	[957]	GETUPVAL 	4 2	; InfoMessage
	10	[957]	SELF     	4 4 -5	; "new"
	11	[957]	NEWTABLE 	6 0 2
	12	[958]	GETUPVAL 	7 3	; T
	13	[958]	GETUPVAL 	8 4	; _
	14	[958]	LOADK    	9 -7	; "%1 is now the default dictionary for this document."
	15	[958]	CALL     	8 2 2
	16	[959]	MOVE     	9 1
	17	[958]	CALL     	7 3 2
	18	[959]	SETTABLE 	6 -6 7	; "text" -
	19	[960]	SETTABLE 	6 -8 -9	; "timeout" 2
	20	[957]	CALL     	4 3 0
	21	[957]	CALL     	2 0 1
	22	[962]	LOADBOOL 	2 1 0
	23	[962]	RETURN   	2 2
	24	[963]	RETURN   	0 1

function <./frontend/apps/reader/modules/readerdictionary.lua:965,971> (17 instructions, 68 bytes at 0x7fc712c182c0)
2 params, 5 slots, 0 upvalues, 2 locals, 6 constants, 0 functions
	1	[966]	SELF     	2 1 -2	; "readSetting"
	2	[966]	LOADK    	4 -1	; "default_dictionary"
	3	[966]	CALL     	2 3 2
	4	[966]	SETTABLE 	0 -1 2	; "default_dictionary" -
	5	[967]	SELF     	2 1 -2	; "readSetting"
	6	[967]	LOADK    	4 -3	; "disable_fuzzy_search"
	7	[967]	CALL     	2 3 2
	8	[967]	SETTABLE 	0 -3 2	; "disable_fuzzy_search" -
	9	[968]	GETTABLE 	2 0 -3	; "disable_fuzzy_search"
	10	[968]	EQ       	0 2 -4	; - nil
	11	[968]	JMP      	5	; to 17
	12	[969]	GETGLOBAL	2 -5	; G_reader_settings
	13	[969]	SELF     	2 2 -6	; "isTrue"
	14	[969]	LOADK    	4 -3	; "disable_fuzzy_search"
	15	[969]	CALL     	2 3 2
	16	[969]	SETTABLE 	0 -3 2	; "disable_fuzzy_search" -
	17	[971]	RETURN   	0 1

function <./frontend/apps/reader/modules/readerdictionary.lua:973,979> (22 instructions, 88 bytes at 0x7fc712c18c40)
1 param, 5 slots, 1 upvalue, 1 local, 7 constants, 0 functions
	1	[974]	GETTABLE 	1 0 -1	; "ui"
	2	[974]	GETTABLE 	1 1 -2	; "doc_settings"
	3	[974]	TEST     	1 0 0
	4	[974]	JMP      	17	; to 22
	5	[975]	GETUPVAL 	1 0	; logger
	6	[975]	GETTABLE 	1 1 -3	; "dbg"
	7	[975]	LOADK    	2 -4	; "save default dictionary"
	8	[975]	GETTABLE 	3 0 -5	; "default_dictionary"
	9	[975]	CALL     	1 3 1
	10	[976]	GETTABLE 	1 0 -1	; "ui"
	11	[976]	GETTABLE 	1 1 -2	; "doc_settings"
	12	[976]	SELF     	1 1 -6	; "saveSetting"
	13	[976]	LOADK    	3 -5	; "default_dictionary"
	14	[976]	GETTABLE 	4 0 -5	; "default_dictionary"
	15	[976]	CALL     	1 4 1
	16	[977]	GETTABLE 	1 0 -1	; "ui"
	17	[977]	GETTABLE 	1 1 -2	; "doc_settings"
	18	[977]	SELF     	1 1 -6	; "saveSetting"
	19	[977]	LOADK    	3 -7	; "disable_fuzzy_search"
	20	[977]	GETTABLE 	4 0 -7	; "disable_fuzzy_search"
	21	[977]	CALL     	1 4 1
	22	[979]	RETURN   	0 1

function <./frontend/apps/reader/modules/readerdictionary.lua:981,1012> (37 instructions, 148 bytes at 0x7fc712c19170)
1 param, 10 slots, 4 upvalues, 2 locals, 12 constants, 4 functions
	1	[982]	GETGLOBAL	1 -1	; G_reader_settings
	2	[982]	SELF     	1 1 -2	; "isTrue"
	3	[982]	LOADK    	3 -3	; "disable_fuzzy_search"
	4	[982]	CALL     	1 3 2
	5	[983]	GETUPVAL 	2 0	; UIManager
	6	[983]	SELF     	2 2 -4	; "show"
	7	[983]	GETUPVAL 	4 1	; MultiConfirmBox
	8	[983]	SELF     	4 4 -5	; "new"
	9	[983]	NEWTABLE 	6 0 5
	10	[984]	GETUPVAL 	7 2	; T
	11	[986]	TEST     	1 0 0
	12	[986]	JMP      	5	; to 18
	13	[986]	GETUPVAL 	8 3	; _
	14	[991]	LOADK    	9 -7	; "Would you like to enable or disable fuzzy search by default?\n\nFuzzy search can match epuisante, \195\169puisante and \195\169puisantes to \195\169puisant, even if only the latter has an entry in the dictionary. It can be disabled to improve performance, but it might be worthwhile to look into disabling unneeded dictionaries before disabling fuzzy search.\n\nThe current default (\226\152\133) is disabled."
	15	[986]	CALL     	8 2 2
	16	[992]	TEST     	8 0 1
	17	[992]	JMP      	3	; to 21
	18	[992]	GETUPVAL 	8 3	; _
	19	[997]	LOADK    	9 -8	; "Would you like to enable or disable fuzzy search by default?\n\nFuzzy search can match epuisante, \195\169puisante and \195\169puisantes to \195\169puisant, even if only the latter has an entry in the dictionary. It can be disabled to improve performance, but it might be worthwhile to look into disabling unneeded dictionaries before disabling fuzzy search.\n\nThe current default (\226\152\133) is enabled."
	20	[992]	CALL     	8 2 2
	21	[984]	CALL     	7 2 2
	22	[998]	SETTABLE 	6 -6 7	; "text" -
	23	[1001]	CLOSURE  	7 0	; 0x7fc712c195a0
	24	[1001]	MOVE     	0 1
	25	[1001]	GETUPVAL 	0 3	; _
	26	[1001]	SETTABLE 	6 -9 7	; "choice1_text_func" -
	27	[1004]	CLOSURE  	7 1	; 0x7fc712c17c90
	28	[1004]	SETTABLE 	6 -10 7	; "choice1_callback" -
	29	[1007]	CLOSURE  	7 2	; 0x7fc712c0a4d0
	30	[1007]	MOVE     	0 1
	31	[1007]	GETUPVAL 	0 3	; _
	32	[1007]	SETTABLE 	6 -11 7	; "choice2_text_func" -
	33	[1010]	CLOSURE  	7 3	; 0x7fc712c13060
	34	[1010]	SETTABLE 	6 -12 7	; "choice2_callback" -
	35	[983]	CALL     	4 3 0
	36	[983]	CALL     	2 0 1
	37	[1012]	RETURN   	0 1

function <./frontend/apps/reader/modules/readerdictionary.lua:999,1001> (13 instructions, 52 bytes at 0x7fc712c195a0)
0 params, 2 slots, 2 upvalues, 0 locals, 2 constants, 0 functions
	1	[1000]	GETUPVAL 	0 0	; disable_fuzzy_search
	2	[1000]	TEST     	0 0 0
	3	[1000]	JMP      	5	; to 9
	4	[1000]	GETUPVAL 	0 1	; _
	5	[1000]	LOADK    	1 -1	; "Disable (\226\152\133)"
	6	[1000]	CALL     	0 2 2
	7	[1000]	TEST     	0 0 1
	8	[1000]	JMP      	3	; to 12
	9	[1000]	GETUPVAL 	0 1	; _
	10	[1000]	LOADK    	1 -2	; "Disable"
	11	[1000]	CALL     	0 2 2
	12	[1000]	RETURN   	0 2
	13	[1001]	RETURN   	0 1

function <./frontend/apps/reader/modules/readerdictionary.lua:1002,1004> (6 instructions, 24 bytes at 0x7fc712c17c90)
0 params, 4 slots, 0 upvalues, 0 locals, 3 constants, 0 functions
	1	[1003]	GETGLOBAL	0 -1	; G_reader_settings
	2	[1003]	SELF     	0 0 -2	; "saveSetting"
	3	[1003]	LOADK    	2 -3	; "disable_fuzzy_search"
	4	[1003]	LOADBOOL 	3 1 0
	5	[1003]	CALL     	0 4 1
	6	[1004]	RETURN   	0 1

function <./frontend/apps/reader/modules/readerdictionary.lua:1005,1007> (13 instructions, 52 bytes at 0x7fc712c0a4d0)
0 params, 2 slots, 2 upvalues, 0 locals, 2 constants, 0 functions
	1	[1006]	GETUPVAL 	0 0	; disable_fuzzy_search
	2	[1006]	TEST     	0 0 0
	3	[1006]	JMP      	5	; to 9
	4	[1006]	GETUPVAL 	0 1	; _
	5	[1006]	LOADK    	1 -1	; "Enable"
	6	[1006]	CALL     	0 2 2
	7	[1006]	TEST     	0 0 1
	8	[1006]	JMP      	3	; to 12
	9	[1006]	GETUPVAL 	0 1	; _
	10	[1006]	LOADK    	1 -2	; "Enable (\226\152\133)"
	11	[1006]	CALL     	0 2 2
	12	[1006]	RETURN   	0 2
	13	[1007]	RETURN   	0 1

function <./frontend/apps/reader/modules/readerdictionary.lua:1008,1010> (6 instructions, 24 bytes at 0x7fc712c13060)
0 params, 4 slots, 0 upvalues, 0 locals, 3 constants, 0 functions
	1	[1009]	GETGLOBAL	0 -1	; G_reader_settings
	2	[1009]	SELF     	0 0 -2	; "saveSetting"
	3	[1009]	LOADK    	2 -3	; "disable_fuzzy_search"
	4	[1009]	LOADBOOL 	3 0 0
	5	[1009]	CALL     	0 4 1
	6	[1010]	RETURN   	0 1
