
main <./frontend/apps/reader/modules/readerkoptlistener.lua:0,0> (29 instructions, 116 bytes at 0x7f890d406900)
0+ params, 5 slots, 0 upvalues, 3 locals, 12 constants, 8 functions
	1	[1]	GETGLOBAL	0 -1	; require
	2	[1]	LOADK    	1 -2	; "ui/widget/eventlistener"
	3	[1]	CALL     	0 2 2
	4	[2]	GETGLOBAL	1 -1	; require
	5	[2]	LOADK    	2 -3	; "ui/event"
	6	[2]	CALL     	1 2 2
	7	[4]	SELF     	2 0 -4	; "new"
	8	[4]	NEWTABLE 	4 0 0
	9	[4]	CALL     	2 3 2
	10	[13]	CLOSURE  	3 0	; 0x7f890d406fc0
	11	[13]	MOVE     	0 1
	12	[6]	SETTABLE 	2 -5 3	; "setZoomMode" -
	13	[28]	CLOSURE  	3 1	; 0x7f890d407450
	14	[28]	MOVE     	0 1
	15	[15]	SETTABLE 	2 -6 3	; "onReadSettings" -
	16	[32]	CLOSURE  	3 2	; 0x7f890d4075d0
	17	[30]	SETTABLE 	2 -7 3	; "onSaveSettings" -
	18	[38]	CLOSURE  	3 3	; 0x7f890d407df0
	19	[34]	SETTABLE 	2 -8 3	; "onRestoreZoomMode" -
	20	[45]	CLOSURE  	3 4	; 0x7f890d406c70
	21	[40]	SETTABLE 	2 -9 3	; "onSetZoomMode" -
	22	[49]	CLOSURE  	3 5	; 0x7f890d4081c0
	23	[47]	SETTABLE 	2 -10 3	; "onFineTuningFontSize" -
	24	[56]	CLOSURE  	3 6	; 0x7f890d4085f0
	25	[51]	SETTABLE 	2 -11 3	; "onZoomUpdate" -
	26	[66]	CLOSURE  	3 7	; 0x7f890d408a30
	27	[59]	SETTABLE 	2 -12 3	; "onDocLangUpdate" -
	28	[68]	RETURN   	2 2
	29	[68]	RETURN   	0 1

function <./frontend/apps/reader/modules/readerkoptlistener.lua:6,13> (25 instructions, 100 bytes at 0x7f890d406fc0)
2 params, 9 slots, 1 upvalue, 2 locals, 10 constants, 0 functions
	1	[7]	GETTABLE 	2 0 -1	; "document"
	2	[7]	GETTABLE 	2 2 -2	; "configurable"
	3	[7]	GETTABLE 	2 2 -3	; "text_wrap"
	4	[7]	EQ       	0 2 -4	; - 1
	5	[7]	JMP      	10	; to 16
	6	[9]	GETTABLE 	2 0 -5	; "ui"
	7	[9]	SELF     	2 2 -6	; "handleEvent"
	8	[9]	GETUPVAL 	4 0	; Event
	9	[9]	SELF     	4 4 -7	; "new"
	10	[9]	LOADK    	6 -8	; "SetZoomMode"
	11	[9]	LOADK    	7 -9	; "page"
	12	[9]	LOADK    	8 -10	; "koptlistener"
	13	[9]	CALL     	4 5 0
	14	[9]	CALL     	2 0 1
	15	[9]	JMP      	9	; to 25
	16	[11]	GETTABLE 	2 0 -5	; "ui"
	17	[11]	SELF     	2 2 -6	; "handleEvent"
	18	[11]	GETUPVAL 	4 0	; Event
	19	[11]	SELF     	4 4 -7	; "new"
	20	[11]	LOADK    	6 -8	; "SetZoomMode"
	21	[11]	MOVE     	7 1
	22	[11]	LOADK    	8 -10	; "koptlistener"
	23	[11]	CALL     	4 5 0
	24	[11]	CALL     	2 0 1
	25	[13]	RETURN   	0 1

function <./frontend/apps/reader/modules/readerkoptlistener.lua:15,28> (51 instructions, 204 bytes at 0x7f890d407450)
2 params, 8 slots, 1 upvalue, 2 locals, 18 constants, 0 functions
	1	[17]	SELF     	2 1 -2	; "readSetting"
	2	[17]	LOADK    	4 -1	; "normal_zoom_mode"
	3	[17]	CALL     	2 3 2
	4	[17]	TEST     	2 0 1
	5	[17]	JMP      	7	; to 13
	6	[18]	GETGLOBAL	2 -3	; G_reader_settings
	7	[18]	SELF     	2 2 -2	; "readSetting"
	8	[18]	LOADK    	4 -4	; "zoom_mode"
	9	[18]	CALL     	2 3 2
	10	[18]	TEST     	2 0 1
	11	[18]	JMP      	1	; to 13
	12	[18]	LOADK    	2 -5	; "page"
	13	[18]	SETTABLE 	0 -1 2	; "normal_zoom_mode" -
	14	[19]	SELF     	2 0 -6	; "setZoomMode"
	15	[19]	GETTABLE 	4 0 -1	; "normal_zoom_mode"
	16	[19]	CALL     	2 3 1
	17	[20]	GETTABLE 	2 0 -7	; "document"
	18	[20]	GETTABLE 	2 2 -8	; "configurable"
	19	[20]	SELF     	3 1 -2	; "readSetting"
	20	[20]	LOADK    	5 -10	; "kopt_contrast"
	21	[20]	CALL     	3 3 2
	22	[20]	TEST     	3 0 1
	23	[20]	JMP      	7	; to 31
	24	[21]	GETGLOBAL	3 -3	; G_reader_settings
	25	[21]	SELF     	3 3 -2	; "readSetting"
	26	[21]	LOADK    	5 -10	; "kopt_contrast"
	27	[21]	CALL     	3 3 2
	28	[21]	TEST     	3 0 1
	29	[21]	JMP      	1	; to 31
	30	[21]	LOADK    	3 -11	; 1
	31	[21]	SETTABLE 	2 -9 3	; "contrast" -
	32	[22]	GETTABLE 	2 0 -12	; "ui"
	33	[22]	SELF     	2 2 -13	; "handleEvent"
	34	[22]	GETUPVAL 	4 0	; Event
	35	[22]	SELF     	4 4 -14	; "new"
	36	[22]	LOADK    	6 -15	; "GammaUpdate"
	37	[22]	GETTABLE 	7 0 -7	; "document"
	38	[22]	GETTABLE 	7 7 -8	; "configurable"
	39	[22]	GETTABLE 	7 7 -9	; "contrast"
	40	[22]	DIV      	7 -11 7	; 1 -
	41	[22]	CALL     	4 4 0
	42	[22]	CALL     	2 0 1
	43	[25]	GETTABLE 	2 0 -7	; "document"
	44	[25]	GETTABLE 	2 2 -8	; "configurable"
	45	[25]	GETTABLE 	2 2 -16	; "word_spacing"
	46	[25]	EQ       	0 2 -17	; - -1
	47	[25]	JMP      	3	; to 51
	48	[26]	GETTABLE 	2 0 -7	; "document"
	49	[26]	GETTABLE 	2 2 -8	; "configurable"
	50	[26]	SETTABLE 	2 -16 -18	; "word_spacing" -0.2
	51	[28]	RETURN   	0 1

function <./frontend/apps/reader/modules/readerkoptlistener.lua:30,32> (7 instructions, 28 bytes at 0x7f890d4075d0)
1 param, 5 slots, 0 upvalues, 1 local, 4 constants, 0 functions
	1	[31]	GETTABLE 	1 0 -1	; "ui"
	2	[31]	GETTABLE 	1 1 -2	; "doc_settings"
	3	[31]	SELF     	1 1 -3	; "saveSetting"
	4	[31]	LOADK    	3 -4	; "normal_zoom_mode"
	5	[31]	GETTABLE 	4 0 -4	; "normal_zoom_mode"
	6	[31]	CALL     	1 4 1
	7	[32]	RETURN   	0 1

function <./frontend/apps/reader/modules/readerkoptlistener.lua:34,38> (6 instructions, 24 bytes at 0x7f890d407df0)
1 param, 4 slots, 0 upvalues, 1 local, 2 constants, 0 functions
	1	[36]	SELF     	1 0 -1	; "setZoomMode"
	2	[36]	GETTABLE 	3 0 -2	; "normal_zoom_mode"
	3	[36]	CALL     	1 3 1
	4	[37]	LOADBOOL 	1 1 0
	5	[37]	RETURN   	1 2
	6	[38]	RETURN   	0 1

function <./frontend/apps/reader/modules/readerkoptlistener.lua:40,45> (8 instructions, 32 bytes at 0x7f890d406c70)
3 params, 6 slots, 0 upvalues, 3 locals, 3 constants, 0 functions
	1	[41]	EQ       	0 2 -1	; - "koptlistener"
	2	[41]	JMP      	1	; to 4
	3	[41]	RETURN   	0 1
	4	[43]	SETTABLE 	0 -2 1	; "normal_zoom_mode" -
	5	[44]	SELF     	3 0 -3	; "setZoomMode"
	6	[44]	GETTABLE 	5 0 -2	; "normal_zoom_mode"
	7	[44]	CALL     	3 3 1
	8	[45]	RETURN   	0 1

function <./frontend/apps/reader/modules/readerkoptlistener.lua:47,49> (8 instructions, 32 bytes at 0x7f890d4081c0)
2 params, 4 slots, 0 upvalues, 2 locals, 3 constants, 0 functions
	1	[48]	GETTABLE 	2 0 -1	; "document"
	2	[48]	GETTABLE 	2 2 -2	; "configurable"
	3	[48]	GETTABLE 	3 0 -1	; "document"
	4	[48]	GETTABLE 	3 3 -2	; "configurable"
	5	[48]	GETTABLE 	3 3 -3	; "font_size"
	6	[48]	ADD      	3 3 1
	7	[48]	SETTABLE 	2 -3 3	; "font_size" -
	8	[49]	RETURN   	0 1

function <./frontend/apps/reader/modules/readerkoptlistener.lua:51,56> (9 instructions, 36 bytes at 0x7f890d4085f0)
2 params, 3 slots, 0 upvalues, 2 locals, 7 constants, 0 functions
	1	[53]	GETTABLE 	2 0 -1	; "document"
	2	[53]	GETTABLE 	2 2 -2	; "configurable"
	3	[53]	GETTABLE 	2 2 -3	; "text_wrap"
	4	[53]	EQ       	0 2 -4	; - 1
	5	[53]	JMP      	3	; to 9
	6	[54]	GETTABLE 	2 0 -5	; "view"
	7	[54]	GETTABLE 	2 2 -6	; "state"
	8	[54]	SETTABLE 	2 -7 -4	; "zoom" 1
	9	[56]	RETURN   	0 1

function <./frontend/apps/reader/modules/readerkoptlistener.lua:59,66> (20 instructions, 80 bytes at 0x7f890d408a30)
2 params, 4 slots, 0 upvalues, 2 locals, 10 constants, 0 functions
	1	[60]	EQ       	1 1 -1	; - "chi_sim"
	2	[60]	JMP      	6	; to 9
	3	[60]	EQ       	1 1 -2	; - "chi_tra"
	4	[60]	JMP      	4	; to 9
	5	[61]	EQ       	1 1 -3	; - "jpn"
	6	[61]	JMP      	2	; to 9
	7	[61]	EQ       	0 1 -4	; - "kor"
	8	[61]	JMP      	6	; to 15
	9	[62]	GETTABLE 	2 0 -5	; "document"
	10	[62]	GETTABLE 	2 2 -6	; "configurable"
	11	[62]	GETGLOBAL	3 -8	; DKOPTREADER_CONFIG_WORD_SPACINGS
	12	[62]	GETTABLE 	3 3 -9	; 1
	13	[62]	SETTABLE 	2 -7 3	; "word_spacing" -
	14	[62]	JMP      	5	; to 20
	15	[64]	GETTABLE 	2 0 -5	; "document"
	16	[64]	GETTABLE 	2 2 -6	; "configurable"
	17	[64]	GETGLOBAL	3 -8	; DKOPTREADER_CONFIG_WORD_SPACINGS
	18	[64]	GETTABLE 	3 3 -10	; 3
	19	[64]	SETTABLE 	2 -7 3	; "word_spacing" -
	20	[66]	RETURN   	0 1
