-- BYTECODE -- readerrolling.lua:119-123
0001    UGET     0   0      ; self
0002    TGETS    0   0   0  ; "ui"
0003    TGETS    0   0   1  ; "document"
0004    MOV      1   0
0005    TGETS    0   0   2  ; "_readMetadata"
0006    CALL     0   1   2
0007    UGET     0   0      ; self
0008    UGET     1   0      ; self
0009    TGETS    1   1   0  ; "ui"
0010    TGETS    1   1   1  ; "document"
0011    TGETS    1   1   4  ; "info"
0012    TGETS    1   1   5  ; "doc_height"
0013    TSETS    1   0   3  ; "old_doc_height"
0014    UGET     0   0      ; self
0015    UGET     1   0      ; self
0016    TGETS    1   1   0  ; "ui"
0017    TGETS    1   1   1  ; "document"
0018    TGETS    1   1   4  ; "info"
0019    TGETS    1   1   7  ; "number_of_pages"
0020    TSETS    1   0   6  ; "old_page"
0021    RET0     0   1

-- BYTECODE -- readerrolling.lua:124-129
0001    UGET     0   0      ; self
0002    MOV      1   0
0003    TGETS    0   0   0  ; "updatePos"
0004    CALL     0   1   2
0005    UGET     0   0      ; self
0006    TGETS    0   0   1  ; "ui"
0007    TGETS    0   0   2  ; "document"
0008    MOV      1   0
0009    TGETS    0   0   3  ; "enableInternalHistory"
0010    KPRI     2   1
0011    CALL     0   1   3
0012    UGET     0   0      ; self
0013    MOV      1   0
0014    TGETS    0   0   4  ; "onRedrawCurrentView"
0015    CALL     0   1   2
0016    RET0     0   1

-- BYTECODE -- readerrolling.lua:60-131
0001    TNEW     1   0
0002    TSETS    1   0   0  ; "key_events"
0003    UGET     1   0      ; Device
0004    MOV      2   1
0005    TGETS    1   1   1  ; "hasKeys"
0006    CALL     1   2   2
0007    ISF          1
0008    JMP      2 => 0023
0009    TGETS    1   0   0  ; "key_events"
0010    TDUP     2   4
0011    TNEW     3   3
0012    TDUP     4   3
0013    TSETB    4   3   1
0014    TSETB    3   2   1
0015    TSETS    2   1   2  ; "GotoNextView"
0016    TGETS    1   0   0  ; "key_events"
0017    TDUP     2   7
0018    TNEW     3   3
0019    TDUP     4   6
0020    TSETB    4   3   1
0021    TSETB    3   2   1
0022    TSETS    2   1   5  ; "GotoPrevView"
0023 => UGET     1   0      ; Device
0024    MOV      2   1
0025    TGETS    1   1   8  ; "hasDPad"
0026    CALL     1   2   2
0027    ISF          1
0028    JMP      2 => 0043
0029    TGETS    1   0   0  ; "key_events"
0030    TDUP     2  11
0031    TDUP     3  10
0032    TSETB    3   2   1
0033    TDUP     3  12
0034    TSETS    3   2  13  ; "args"
0035    TSETS    2   1   9  ; "MoveUp"
0036    TGETS    1   0   0  ; "key_events"
0037    TDUP     2  16
0038    TDUP     3  15
0039    TSETB    3   2   1
0040    TDUP     3  17
0041    TSETS    3   2  13  ; "args"
0042    TSETS    2   1  14  ; "MoveDown"
0043 => UGET     1   0      ; Device
0044    MOV      2   1
0045    TGETS    1   1  18  ; "hasKeyboard"
0046    CALL     1   2   2
0047    ISF          1
0048    JMP      2 => 0099
0049    TGETS    1   0   0  ; "key_events"
0050    TDUP     2  21
0051    TDUP     3  20
0052    TSETB    3   2   1
0053    TSETS    2   1  19  ; "GotoFirst"
0054    TGETS    1   0   0  ; "key_events"
0055    TDUP     2  24
0056    TDUP     3  23
0057    TSETB    3   2   1
0058    TSETS    2   1  22  ; "Goto11"
0059    TGETS    1   0   0  ; "key_events"
0060    TDUP     2  27
0061    TDUP     3  26
0062    TSETB    3   2   1
0063    TSETS    2   1  25  ; "Goto22"
0064    TGETS    1   0   0  ; "key_events"
0065    TDUP     2  30
0066    TDUP     3  29
0067    TSETB    3   2   1
0068    TSETS    2   1  28  ; "Goto33"
0069    TGETS    1   0   0  ; "key_events"
0070    TDUP     2  33
0071    TDUP     3  32
0072    TSETB    3   2   1
0073    TSETS    2   1  31  ; "Goto44"
0074    TGETS    1   0   0  ; "key_events"
0075    TDUP     2  36
0076    TDUP     3  35
0077    TSETB    3   2   1
0078    TSETS    2   1  34  ; "Goto55"
0079    TGETS    1   0   0  ; "key_events"
0080    TDUP     2  39
0081    TDUP     3  38
0082    TSETB    3   2   1
0083    TSETS    2   1  37  ; "Goto66"
0084    TGETS    1   0   0  ; "key_events"
0085    TDUP     2  42
0086    TDUP     3  41
0087    TSETB    3   2   1
0088    TSETS    2   1  40  ; "Goto77"
0089    TGETS    1   0   0  ; "key_events"
0090    TDUP     2  45
0091    TDUP     3  44
0092    TSETB    3   2   1
0093    TSETS    2   1  43  ; "Goto88"
0094    TGETS    1   0   0  ; "key_events"
0095    TDUP     2  48
0096    TDUP     3  47
0097    TSETB    3   2   1
0098    TSETS    2   1  46  ; "GotoLast"
0099 => GGET     1  49      ; "table"
0100    TGETS    1   1  50  ; "insert"
0101    TGETS    2   0  51  ; "ui"
0102    TGETS    2   2  52  ; "postInitCallback"
0103    FNEW     3  53      ; readerrolling.lua:119
0104    CALL     1   1   3
0105    GGET     1  49      ; "table"
0106    TGETS    1   1  50  ; "insert"
0107    TGETS    2   0  51  ; "ui"
0108    TGETS    2   2  54  ; "postReaderCallback"
0109    FNEW     3  55      ; readerrolling.lua:124
0110    CALL     1   1   3
0111    TGETS    1   0  51  ; "ui"
0112    TGETS    1   1  56  ; "menu"
0113    MOV      2   1
0114    TGETS    1   1  57  ; "registerToMainMenu"
0115    MOV      3   0
0116    CALL     1   1   3
0117    UCLO     0 => 0118
0118 => RET0     0   1

-- BYTECODE -- readerrolling.lua:170-172
0001    UGET     0   0      ; self
0002    MOV      1   0
0003    TGETS    0   0   0  ; "checkXPointersAndProposeDOMVersionUpgrad"~
0004    CALL     0   1   2
0005    RET0     0   1

-- BYTECODE -- readerrolling.lua:180-185
0001    UGET     0   0      ; self
0002    MOV      1   0
0003    TGETS    0   0   0  ; "_gotoXPointer"
0004    UGET     2   0      ; self
0005    TGETS    2   2   1  ; "xpointer"
0006    CALL     0   1   3
0007    UGET     0   0      ; self
0008    TGETS    0   0   2  ; "ui"
0009    TGETS    0   0   3  ; "document"
0010    MOV      1   0
0011    TGETS    0   0   4  ; "gotoXPointer"
0012    UGET     2   0      ; self
0013    TGETS    2   2   1  ; "xpointer"
0014    CALL     0   1   3
0015    RET0     0   1

-- BYTECODE -- readerrolling.lua:189-203
0001    UGET     0   0      ; self
0002    MOV      1   0
0003    TGETS    0   0   0  ; "_gotoPercent"
0004    UGET     2   1      ; last_per
0005    CALL     0   1   3
0006    UGET     0   0      ; self
0007    TGETS    0   0   1  ; "ui"
0008    TGETS    0   0   2  ; "document"
0009    MOV      1   0
0010    TGETS    0   0   3  ; "gotoPos"
0011    UGET     2   0      ; self
0012    TGETS    2   2   4  ; "current_pos"
0013    CALL     0   1   3
0014    UGET     0   0      ; self
0015    TGETS    0   0   5  ; "view"
0016    TGETS    0   0   6  ; "view_mode"
0017    ISNES    0   7      ; "page"
0018    JMP      0 => 0035
0019    UGET     0   0      ; self
0020    TGETS    0   0   1  ; "ui"
0021    MOV      1   0
0022    TGETS    0   0   8  ; "handleEvent"
0023    UGET     2   2      ; Event
0024    MOV      3   2
0025    TGETS    2   2   9  ; "new"
0026    KSTR     4  10      ; "PageUpdate"
0027    UGET     5   0      ; self
0028    TGETS    5   5   1  ; "ui"
0029    TGETS    5   5   2  ; "document"
0030    MOV      6   5
0031    TGETS    5   5  11  ; "getCurrentPage"
0032    CALL     5   0   2
0033    CALLM    2   0   2
0034    CALLM    0   1   1
0035 => UGET     0   0      ; self
0036    UGET     1   0      ; self
0037    TGETS    1   1   1  ; "ui"
0038    TGETS    1   1   2  ; "document"
0039    MOV      2   1
0040    TGETS    1   1  13  ; "getXPointer"
0041    CALL     1   2   2
0042    TSETS    1   0  12  ; "xpointer"
0043    RET0     0   1

-- BYTECODE -- readerrolling.lua:205-210
0001    UGET     0   0      ; self
0002    UGET     1   0      ; self
0003    TGETS    1   1   1  ; "ui"
0004    TGETS    1   1   2  ; "document"
0005    MOV      2   1
0006    TGETS    1   1   3  ; "getXPointer"
0007    CALL     1   2   2
0008    TSETS    1   0   0  ; "xpointer"
0009    UGET     0   0      ; self
0010    TGETS    0   0   4  ; "view"
0011    TGETS    0   0   5  ; "view_mode"
0012    ISNES    0   6      ; "page"
0013    JMP      0 => 0025
0014    UGET     0   0      ; self
0015    TGETS    0   0   1  ; "ui"
0016    MOV      1   0
0017    TGETS    0   0   7  ; "handleEvent"
0018    UGET     2   1      ; Event
0019    MOV      3   2
0020    TGETS    2   2   8  ; "new"
0021    KSTR     4   9      ; "PageUpdate"
0022    KSHORT   5   1
0023    CALL     2   0   4
0024    CALLM    0   1   1
0025 => RET0     0   1

-- BYTECODE -- readerrolling.lua:235-243
0001    GGET     0   0      ; "xpcall"
0002    UGET     1   0      ; self
0003    TGETS    1   1   1  ; "handleEngineCallback"
0004    GGET     2   2      ; "debug"
0005    TGETS    2   2   3  ; "traceback"
0006    UGET     3   0      ; self
0007    VARG     4   0   0
0008    CALLM    0   3   3
0009    IST          0
0010    JMP      2 => 0016
0011    UGET     2   1      ; logger
0012    TGETS    2   2   4  ; "warn"
0013    KSTR     3   5      ; "cre callback() error:"
0014    MOV      4   1
0015    CALL     2   1   3
0016 => RET0     0   1

-- BYTECODE -- readerrolling.lua:133-244
0001    MOV      3   1
0002    TGETS    2   1   0  ; "readSetting"
0003    KSTR     4   1      ; "cre_dom_version"
0004    CALL     2   2   3
0005    IST          2
0006    JMP      2 => 0032
0007    MOV      3   1
0008    TGETS    2   1   0  ; "readSetting"
0009    KSTR     4   2      ; "last_xpointer"
0010    CALL     2   2   3
0011    ISF          2
0012    JMP      3 => 0023
0013    MOV      3   1
0014    TGETS    2   1   3  ; "saveSetting"
0015    KSTR     4   1      ; "cre_dom_version"
0016    TGETS    5   0   4  ; "ui"
0017    TGETS    5   5   5  ; "document"
0018    MOV      6   5
0019    TGETS    5   5   6  ; "getOldestDomVersion"
0020    CALL     5   0   2
0021    CALLM    2   1   2
0022    JMP      2 => 0032
0023 => MOV      3   1
0024    TGETS    2   1   3  ; "saveSetting"
0025    KSTR     4   1      ; "cre_dom_version"
0026    TGETS    5   0   4  ; "ui"
0027    TGETS    5   5   5  ; "document"
0028    MOV      6   5
0029    TGETS    5   5   7  ; "getLatestDomVersion"
0030    CALL     5   0   2
0031    CALLM    2   1   2
0032 => TGETS    2   0   4  ; "ui"
0033    TGETS    2   2   5  ; "document"
0034    MOV      3   2
0035    TGETS    2   2   8  ; "requestDomVersion"
0036    MOV      5   1
0037    TGETS    4   1   0  ; "readSetting"
0038    KSTR     6   1      ; "cre_dom_version"
0039    CALL     4   0   3
0040    CALLM    2   1   1
0041    MOV      3   1
0042    TGETS    2   1   0  ; "readSetting"
0043    KSTR     4   1      ; "cre_dom_version"
0044    CALL     2   2   3
0045    GGET     3   9      ; "cre"
0046    TGETS    3   3  10  ; "getDomVersionWithNormalizedXPointers"
0047    CALL     3   2   1
0048    ISGE     2   3
0049    JMP      2 => 0068
0050    KPRI     2   2
0051    TSETS    2   0  11  ; "using_non_normalized_xpointers"
0052    TGETS    2   0   4  ; "ui"
0053    TGETS    2   2  12  ; "typeset"
0054    MOV      3   2
0055    TGETS    2   2  13  ; "ensureSanerBlockRenderingFlags"
0056    CALL     2   1   2
0057    MOV      3   1
0058    TGETS    2   1   0  ; "readSetting"
0059    KSTR     4  14      ; "cre_keep_old_dom_version"
0060    CALL     2   2   3
0061    IST          2
0062    JMP      2 => 0068
0063    TGETS    2   0   4  ; "ui"
0064    MOV      3   2
0065    TGETS    2   2  15  ; "registerPostReadyCallback"
0066    FNEW     4  16      ; readerrolling.lua:170
0067    CALL     2   1   3
0068 => MOV      3   1
0069    TGETS    2   1   0  ; "readSetting"
0070    KSTR     4   2      ; "last_xpointer"
0071    CALL     2   2   3
0072    MOV      4   1
0073    TGETS    3   1   0  ; "readSetting"
0074    KSTR     5  17      ; "last_percent"
0075    CALL     3   2   3
0076    ISF          2
0077    JMP      4 => 0082
0078    TSETS    2   0  18  ; "xpointer"
0079    FNEW     4  20      ; readerrolling.lua:180
0080    TSETS    4   0  19  ; "setupXpointer"
0081    JMP      4 => 0089
0082 => ISF          3
0083    JMP      4 => 0087
0084    FNEW     4  21      ; readerrolling.lua:189
0085    TSETS    4   0  19  ; "setupXpointer"
0086    JMP      4 => 0089
0087 => FNEW     4  22      ; readerrolling.lua:205
0088    TSETS    4   0  19  ; "setupXpointer"
0089 => MOV      5   1
0090    TGETS    4   1   0  ; "readSetting"
0091    KSTR     6  23      ; "show_overlap_enable"
0092    CALL     4   2   3
0093    TSETS    4   0  23  ; "show_overlap_enable"
0094    TGETS    4   0  23  ; "show_overlap_enable"
0095    ISNEP    4   0
0096    JMP      4 => 0099
0097    GGET     4  24      ; "DSHOWOVERLAP"
0098    TSETS    4   0  23  ; "show_overlap_enable"
0099 => MOV      5   1
0100    TGETS    4   1   0  ; "readSetting"
0101    KSTR     6  25      ; "inverse_reading_order"
0102    CALL     4   2   3
0103    TSETS    4   0  25  ; "inverse_reading_order"
0104    TGETS    4   0  25  ; "inverse_reading_order"
0105    ISNEP    4   0
0106    JMP      4 => 0113
0107    GGET     4  26      ; "G_reader_settings"
0108    MOV      5   4
0109    TGETS    4   4  27  ; "isTrue"
0110    KSTR     6  25      ; "inverse_reading_order"
0111    CALL     4   2   3
0112    TSETS    4   0  25  ; "inverse_reading_order"
0113 => MOV      5   1
0114    TGETS    4   1   0  ; "readSetting"
0115    KSTR     6  28      ; "visible_pages"
0116    CALL     4   2   3
0117    IST          4
0118    JMP      5 => 0127
0119    GGET     4  26      ; "G_reader_settings"
0120    MOV      5   4
0121    TGETS    4   4   0  ; "readSetting"
0122    KSTR     6  29      ; "copt_visible_pages"
0123    CALL     4   2   3
0124    IST          4
0125    JMP      5 => 0127
0126    KSHORT   4   1
0127 => TSETS    4   0  28  ; "visible_pages"
0128    TGETS    4   0   4  ; "ui"
0129    TGETS    4   4   5  ; "document"
0130    MOV      5   4
0131    TGETS    4   4  30  ; "setVisiblePageCount"
0132    TGETS    6   0  28  ; "visible_pages"
0133    CALL     4   1   3
0134    TGETS    4   0   4  ; "ui"
0135    TGETS    4   4   5  ; "document"
0136    MOV      5   4
0137    TGETS    4   4  31  ; "setCallback"
0138    FNEW     6  32      ; readerrolling.lua:235
0139    CALL     4   1   3
0140    UCLO     0 => 0141
0141 => RET0     0   1

-- BYTECODE -- readerrolling.lua:248-261
0001    TGETS    1   0   0  ; "ui"
0002    TGETS    1   1   1  ; "doc_settings"
0003    MOV      2   1
0004    TGETS    1   1   2  ; "saveSetting"
0005    KSTR     3   3      ; "percent_finished"
0006    MOV      5   0
0007    TGETS    4   0   4  ; "getLastPercent"
0008    CALL     4   0   2
0009    CALLM    1   1   2
0010    TGETS    1   0   0  ; "ui"
0011    TGETS    1   1   5  ; "document"
0012    MOV      2   1
0013    TGETS    1   1   6  ; "getCacheFilePath"
0014    CALL     1   2   2
0015    TGETS    2   0   0  ; "ui"
0016    TGETS    2   2   1  ; "doc_settings"
0017    MOV      3   2
0018    TGETS    2   2   2  ; "saveSetting"
0019    KSTR     4   7      ; "cache_file_path"
0020    MOV      5   1
0021    CALL     2   1   4
0022    TGETS    2   0   0  ; "ui"
0023    TGETS    2   2   5  ; "document"
0024    MOV      3   2
0025    TGETS    2   2   8  ; "hasCacheFile"
0026    CALL     2   2   2
0027    ISF          2
0028    JMP      3 => 0045
0029    TGETS    2   0   0  ; "ui"
0030    TGETS    2   2   5  ; "document"
0031    MOV      3   2
0032    TGETS    2   2   9  ; "isBuiltDomStale"
0033    CALL     2   2   2
0034    ISF          2
0035    JMP      3 => 0045
0036    UGET     2   0      ; logger
0037    TGETS    2   2  10  ; "dbg"
0038    KSTR     3  11      ; "cre DOM may not be in sync with styles, "~
0039    CALL     2   1   2
0040    TGETS    2   0   0  ; "ui"
0041    TGETS    2   2   5  ; "document"
0042    MOV      3   2
0043    TGETS    2   2  12  ; "invalidateCacheFile"
0044    CALL     2   1   2
0045 => UGET     2   0      ; logger
0046    TGETS    2   2  10  ; "dbg"
0047    KSTR     3  13      ; "cre cache used:"
0048    ISTC     4   1
0049    JMP      4 => 0051
0050    KSTR     4  14      ; "none"
0051 => CALL     2   1   3
0052    RET0     0   1

-- BYTECODE -- readerrolling.lua:275-280
0001    UGET     0   0      ; self
0002    TGETS    0   0   0  ; "ui"
0003    TGETS    0   0   1  ; "document"
0004    ISF          0
0005    JMP      1 => 0011
0006    UGET     0   0      ; self
0007    TGETS    0   0   0  ; "ui"
0008    MOV      1   0
0009    TGETS    0   0   2  ; "reloadDocument"
0010    CALL     0   1   2
0011 => RET0     0   1

-- BYTECODE -- readerrolling.lua:272-281
0001    UGET     0   0      ; UIManager
0002    MOV      1   0
0003    TGETS    0   0   0  ; "scheduleIn"
0004    KNUM     2   0      ; 0.5
0005    FNEW     3   1      ; readerrolling.lua:275
0006    CALL     0   1   4
0007    RET0     0   1

-- BYTECODE -- readerrolling.lua:263-284
0001    TGETS    1   0   0  ; "ui"
0002    TGETS    1   1   1  ; "document"
0003    ISF          1
0004    JMP      2 => 0045
0005    TGETS    1   0   0  ; "ui"
0006    TGETS    1   1   1  ; "document"
0007    MOV      2   1
0008    TGETS    1   1   2  ; "isBuiltDomStale"
0009    CALL     1   2   2
0010    ISF          1
0011    JMP      2 => 0045
0012    KSTR     1   3      ; ""
0013    TGETS    2   0   4  ; "using_non_normalized_xpointers"
0014    ISF          2
0015    JMP      3 => 0027
0016    TGETS    2   0   0  ; "ui"
0017    TGETS    2   2   5  ; "bookmark"
0018    MOV      3   2
0019    TGETS    2   2   6  ; "hasBookmarks"
0020    CALL     2   2   2
0021    ISF          2
0022    JMP      3 => 0027
0023    UGET     2   0      ; _
0024    KSTR     3   7      ; "\nNote that this change in styles may re"~
0025    CALL     2   2   2
0026    MOV      1   2
0027 => UGET     2   1      ; UIManager
0028    MOV      3   2
0029    TGETS    2   2   8  ; "show"
0030    UGET     4   2      ; ConfirmBox
0031    MOV      5   4
0032    TGETS    4   4   9  ; "new"
0033    TDUP     6  11
0034    UGET     7   3      ; T
0035    UGET     8   0      ; _
0036    KSTR     9  10      ; "Styles have changed in such a way that f"~
0037    CALL     8   2   2
0038    MOV      9   1
0039    CALL     7   2   3
0040    TSETS    7   6  12  ; "text"
0041    FNEW     7  13      ; readerrolling.lua:272
0042    TSETS    7   6  14  ; "ok_callback"
0043    CALL     4   0   3
0044    CALLM    2   1   1
0045 => UCLO     0 => 0046
0046 => RET0     0   1

-- BYTECODE -- readerrolling.lua:286-299
0001    TGETS    1   0   0  ; "ui"
0002    TGETS    1   1   1  ; "doc_settings"
0003    MOV      2   1
0004    TGETS    1   1   2  ; "saveSetting"
0005    KSTR     3   3      ; "last_percent"
0006    KPRI     4   0
0007    CALL     1   1   4
0008    TGETS    1   0   0  ; "ui"
0009    TGETS    1   1   1  ; "doc_settings"
0010    MOV      2   1
0011    TGETS    1   1   2  ; "saveSetting"
0012    KSTR     3   4      ; "last_xpointer"
0013    TGETS    4   0   5  ; "xpointer"
0014    CALL     1   1   4
0015    TGETS    1   0   0  ; "ui"
0016    TGETS    1   1   6  ; "document"
0017    ISF          1
0018    JMP      2 => 0028
0019    TGETS    1   0   0  ; "ui"
0020    TGETS    1   1   1  ; "doc_settings"
0021    MOV      2   1
0022    TGETS    1   1   2  ; "saveSetting"
0023    KSTR     3   7      ; "percent_finished"
0024    MOV      5   0
0025    TGETS    4   0   8  ; "getLastPercent"
0026    CALL     4   0   2
0027    CALLM    1   1   2
0028 => TGETS    1   0   0  ; "ui"
0029    TGETS    1   1   1  ; "doc_settings"
0030    MOV      2   1
0031    TGETS    1   1   2  ; "saveSetting"
0032    KSTR     3   9      ; "show_overlap_enable"
0033    TGETS    4   0   9  ; "show_overlap_enable"
0034    CALL     1   1   4
0035    TGETS    1   0   0  ; "ui"
0036    TGETS    1   1   1  ; "doc_settings"
0037    MOV      2   1
0038    TGETS    1   1   2  ; "saveSetting"
0039    KSTR     3  10      ; "inverse_reading_order"
0040    TGETS    4   0  10  ; "inverse_reading_order"
0041    CALL     1   1   4
0042    TGETS    1   0   0  ; "ui"
0043    TGETS    1   1   1  ; "doc_settings"
0044    MOV      2   1
0045    TGETS    1   1   2  ; "saveSetting"
0046    KSTR     3  11      ; "visible_pages"
0047    TGETS    4   0  11  ; "visible_pages"
0048    CALL     1   1   4
0049    RET0     0   1

-- BYTECODE -- readerrolling.lua:301-304
0001    MOV      2   0
0002    TGETS    1   0   0  ; "setupTouchZones"
0003    CALL     1   1   2
0004    TGETS    1   0   1  ; "setupXpointer"
0005    CALL     1   1   1
0006    RET0     0   1

-- BYTECODE -- readerrolling.lua:348-348
0001    UGET     0   0      ; self
0002    MOV      1   0
0003    TGETS    0   0   0  ; "onGotoViewRel"
0004    KSHORT   2   1
0005    CALLT    0   3

-- BYTECODE -- readerrolling.lua:354-354
0001    UGET     0   0      ; self
0002    MOV      1   0
0003    TGETS    0   0   0  ; "onGotoViewRel"
0004    KSHORT   2  -1
0005    CALLT    0   3

-- BYTECODE -- readerrolling.lua:360-360
0001    UGET     0   0      ; self
0002    MOV      1   0
0003    TGETS    0   0   0  ; "onGotoNextChapter"
0004    CALLT    0   2

-- BYTECODE -- readerrolling.lua:366-366
0001    UGET     0   0      ; self
0002    MOV      1   0
0003    TGETS    0   0   0  ; "onGotoPrevChapter"
0004    CALLT    0   2

-- BYTECODE -- readerrolling.lua:374-374
0001    UGET     1   0      ; self
0002    MOV      2   1
0003    TGETS    1   1   0  ; "onSwipe"
0004    KPRI     3   0
0005    MOV      4   0
0006    CALLT    1   4

-- BYTECODE -- readerrolling.lua:383-383
0001    UGET     1   0      ; self
0002    MOV      2   1
0003    TGETS    1   1   0  ; "onPan"
0004    KPRI     3   0
0005    MOV      4   0
0006    CALLT    1   4

-- BYTECODE -- readerrolling.lua:306-386
0001    TNEW     1   0
0002    TSETS    1   0   0  ; "ges_events"
0003    KPRI     1   0
0004    TSETS    1   0   1  ; "onGesture"
0005    UGET     1   0      ; Device
0006    MOV      2   1
0007    TGETS    1   1   2  ; "isTouchDevice"
0008    CALL     1   2   2
0009    IST          1
0010    JMP      1 => 0012
0011    UCLO     0 => 0134
0012 => TDUP     1   5
0013    GGET     2   3      ; "DTAP_ZONE_FORWARD"
0014    TGETS    2   2   4  ; "x"
0015    TSETS    2   1   6  ; "ratio_x"
0016    GGET     2   3      ; "DTAP_ZONE_FORWARD"
0017    TGETS    2   2   7  ; "y"
0018    TSETS    2   1   8  ; "ratio_y"
0019    GGET     2   3      ; "DTAP_ZONE_FORWARD"
0020    TGETS    2   2   9  ; "w"
0021    TSETS    2   1  10  ; "ratio_w"
0022    GGET     2   3      ; "DTAP_ZONE_FORWARD"
0023    TGETS    2   2  11  ; "h"
0024    TSETS    2   1  12  ; "ratio_h"
0025    TDUP     2  14
0026    GGET     3  13      ; "DTAP_ZONE_BACKWARD"
0027    TGETS    3   3   4  ; "x"
0028    TSETS    3   2   6  ; "ratio_x"
0029    GGET     3  13      ; "DTAP_ZONE_BACKWARD"
0030    TGETS    3   3   7  ; "y"
0031    TSETS    3   2   8  ; "ratio_y"
0032    GGET     3  13      ; "DTAP_ZONE_BACKWARD"
0033    TGETS    3   3   9  ; "w"
0034    TSETS    3   2  10  ; "ratio_w"
0035    GGET     3  13      ; "DTAP_ZONE_BACKWARD"
0036    TGETS    3   3  11  ; "h"
0037    TSETS    3   2  12  ; "ratio_h"
0038    TDUP     3  16
0039    GGET     4  15      ; "DDOUBLE_TAP_ZONE_NEXT_CHAPTER"
0040    TGETS    4   4   4  ; "x"
0041    TSETS    4   3   6  ; "ratio_x"
0042    GGET     4  15      ; "DDOUBLE_TAP_ZONE_NEXT_CHAPTER"
0043    TGETS    4   4   7  ; "y"
0044    TSETS    4   3   8  ; "ratio_y"
0045    GGET     4  15      ; "DDOUBLE_TAP_ZONE_NEXT_CHAPTER"
0046    TGETS    4   4   9  ; "w"
0047    TSETS    4   3  10  ; "ratio_w"
0048    GGET     4  15      ; "DDOUBLE_TAP_ZONE_NEXT_CHAPTER"
0049    TGETS    4   4  11  ; "h"
0050    TSETS    4   3  12  ; "ratio_h"
0051    TDUP     4  18
0052    GGET     5  17      ; "DDOUBLE_TAP_ZONE_PREV_CHAPTER"
0053    TGETS    5   5   4  ; "x"
0054    TSETS    5   4   6  ; "ratio_x"
0055    GGET     5  17      ; "DDOUBLE_TAP_ZONE_PREV_CHAPTER"
0056    TGETS    5   5   7  ; "y"
0057    TSETS    5   4   8  ; "ratio_y"
0058    GGET     5  17      ; "DDOUBLE_TAP_ZONE_PREV_CHAPTER"
0059    TGETS    5   5   9  ; "w"
0060    TSETS    5   4  10  ; "ratio_w"
0061    GGET     5  17      ; "DDOUBLE_TAP_ZONE_PREV_CHAPTER"
0062    TGETS    5   5  11  ; "h"
0063    TSETS    5   4  12  ; "ratio_h"
0064    UGET     5   1      ; BD
0065    TGETS    5   5  19  ; "mirroredUILayout"
0066    CALL     5   2   1
0067    TGETS    6   0  20  ; "inverse_reading_order"
0068    ISF          6
0069    JMP      7 => 0071
0070    NOT      5   5
0071 => ISF          5
0072    JMP      6 => 0093
0073    TGETS    6   1   6  ; "ratio_x"
0074    SUBNV    6   6   0  ; 1
0075    TGETS    7   1  10  ; "ratio_w"
0076    SUBVV    6   6   7
0077    TSETS    6   1   6  ; "ratio_x"
0078    TGETS    6   2   6  ; "ratio_x"
0079    SUBNV    6   6   0  ; 1
0080    TGETS    7   2  10  ; "ratio_w"
0081    SUBVV    6   6   7
0082    TSETS    6   2   6  ; "ratio_x"
0083    TGETS    6   3   6  ; "ratio_x"
0084    SUBNV    6   6   0  ; 1
0085    TGETS    7   3  10  ; "ratio_w"
0086    SUBVV    6   6   7
0087    TSETS    6   3   6  ; "ratio_x"
0088    TGETS    6   4   6  ; "ratio_x"
0089    SUBNV    6   6   0  ; 1
0090    TGETS    7   4  10  ; "ratio_w"
0091    SUBVV    6   6   7
0092    TSETS    6   4   6  ; "ratio_x"
0093 => TGETS    6   0  21  ; "ui"
0094    MOV      7   6
0095    TGETS    6   6  22  ; "registerTouchZones"
0096    TNEW     8   7
0097    TDUP     9  23
0098    TSETS    1   9  24  ; "screen_zone"
0099    FNEW    10  25      ; readerrolling.lua:348
0100    TSETS   10   9  26  ; "handler"
0101    TSETB    9   8   1
0102    TDUP     9  27
0103    TSETS    2   9  24  ; "screen_zone"
0104    FNEW    10  28      ; readerrolling.lua:354
0105    TSETS   10   9  26  ; "handler"
0106    TSETB    9   8   2
0107    TDUP     9  29
0108    TSETS    3   9  24  ; "screen_zone"
0109    FNEW    10  30      ; readerrolling.lua:360
0110    TSETS   10   9  26  ; "handler"
0111    TSETB    9   8   3
0112    TDUP     9  31
0113    TSETS    4   9  24  ; "screen_zone"
0114    FNEW    10  32      ; readerrolling.lua:366
0115    TSETS   10   9  26  ; "handler"
0116    TSETB    9   8   4
0117    TDUP     9  33
0118    TDUP    10  34
0119    TSETS   10   9  24  ; "screen_zone"
0120    FNEW    10  35      ; readerrolling.lua:374
0121    TSETS   10   9  26  ; "handler"
0122    TSETB    9   8   5
0123    TDUP     9  36
0124    TGETS   10   0  37  ; "pan_rate"
0125    TSETS   10   9  38  ; "rate"
0126    TDUP    10  39
0127    TSETS   10   9  24  ; "screen_zone"
0128    FNEW    10  40      ; readerrolling.lua:383
0129    TSETS   10   9  26  ; "handler"
0130    TSETB    9   8   6
0131    CALL     6   1   3
0132    UCLO     0 => 0133
0133 => RET0     0   1
0134 => RET0     0   1

-- BYTECODE -- readerrolling.lua:388-390
0001    TGETS    1   0   0  ; "xpointer"
0002    RET1     1   2

-- BYTECODE -- readerrolling.lua:396-396
0001    UGET     0   0      ; self
0002    TGETS    0   0   0  ; "inverse_reading_order"
0003    RET1     0   2

-- BYTECODE -- readerrolling.lua:397-399
0001    UGET     0   0      ; self
0002    TGETS    0   0   0  ; "ui"
0003    MOV      1   0
0004    TGETS    0   0   1  ; "handleEvent"
0005    UGET     2   1      ; Event
0006    MOV      3   2
0007    TGETS    2   2   2  ; "new"
0008    KSTR     4   3      ; "ToggleReadingOrder"
0009    CALL     2   0   3
0010    CALLM    0   1   1
0011    RET0     0   1

-- BYTECODE -- readerrolling.lua:405-407
0001    UGET     0   0      ; inverse_reading_order
0002    ISF          0
0003    JMP      1 => 0009
0004    UGET     0   1      ; _
0005    KSTR     1   0      ; "LTR"
0006    CALL     0   2   2
0007    IST          0
0008    JMP      1 => 0012
0009 => UGET     0   1      ; _
0010    KSTR     1   1      ; "LTR (★)"
0011    CALL     0   2   2
0012 => RET1     0   2

-- BYTECODE -- readerrolling.lua:408-411
0001    GGET     0   0      ; "G_reader_settings"
0002    MOV      1   0
0003    TGETS    0   0   1  ; "saveSetting"
0004    KSTR     2   2      ; "inverse_reading_order"
0005    KPRI     3   1
0006    CALL     0   1   4
0007    UGET     0   0      ; touchmenu_instance
0008    ISF          0
0009    JMP      1 => 0014
0010    UGET     0   0      ; touchmenu_instance
0011    MOV      1   0
0012    TGETS    0   0   3  ; "updateItems"
0013    CALL     0   1   2
0014 => RET0     0   1

-- BYTECODE -- readerrolling.lua:412-414
0001    UGET     0   0      ; inverse_reading_order
0002    ISF          0
0003    JMP      1 => 0009
0004    UGET     0   1      ; _
0005    KSTR     1   0      ; "RTL (★)"
0006    CALL     0   2   2
0007    IST          0
0008    JMP      1 => 0012
0009 => UGET     0   1      ; _
0010    KSTR     1   1      ; "RTL"
0011    CALL     0   2   2
0012 => RET1     0   2

-- BYTECODE -- readerrolling.lua:415-418
0001    GGET     0   0      ; "G_reader_settings"
0002    MOV      1   0
0003    TGETS    0   0   1  ; "saveSetting"
0004    KSTR     2   2      ; "inverse_reading_order"
0005    KPRI     3   2
0006    CALL     0   1   4
0007    UGET     0   0      ; touchmenu_instance
0008    ISF          0
0009    JMP      1 => 0014
0010    UGET     0   0      ; touchmenu_instance
0011    MOV      1   0
0012    TGETS    0   0   3  ; "updateItems"
0013    CALL     0   1   2
0014 => RET0     0   1

-- BYTECODE -- readerrolling.lua:400-420
0001    GGET     1   0      ; "G_reader_settings"
0002    MOV      2   1
0003    TGETS    1   1   1  ; "isTrue"
0004    KSTR     3   2      ; "inverse_reading_order"
0005    CALL     1   2   3
0006    UGET     2   0      ; UIManager
0007    MOV      3   2
0008    TGETS    2   2   3  ; "show"
0009    UGET     4   1      ; MultiConfirmBox
0010    MOV      5   4
0011    TGETS    4   4   4  ; "new"
0012    TDUP     6   7
0013    ISF          1
0014    JMP      7 => 0020
0015    UGET     7   2      ; _
0016    KSTR     8   5      ; "The default (★) for newly opened books"~
0017    CALL     7   2   2
0018    IST          7
0019    JMP      8 => 0023
0020 => UGET     7   2      ; _
0021    KSTR     8   6      ; "The default (★) for newly opened books"~
0022    CALL     7   2   2
0023 => TSETS    7   6   8  ; "text"
0024    FNEW     7   9      ; readerrolling.lua:405
0025    TSETS    7   6  10  ; "choice1_text_func"
0026    FNEW     7  11      ; readerrolling.lua:408
0027    TSETS    7   6  12  ; "choice1_callback"
0028    FNEW     7  13      ; readerrolling.lua:412
0029    TSETS    7   6  14  ; "choice2_text_func"
0030    FNEW     7  15      ; readerrolling.lua:415
0031    TSETS    7   6  16  ; "choice2_callback"
0032    CALL     4   0   3
0033    CALLM    2   1   1
0034    UCLO     0 => 0035
0035 => RET0     0   1

-- BYTECODE -- readerrolling.lua:431-433
0001    UGET     0   0      ; self
0002    TGETS    0   0   0  ; "show_overlap_enable"
0003    RET1     0   2

-- BYTECODE -- readerrolling.lua:434-439
0001    UGET     0   0      ; self
0002    UGET     1   0      ; self
0003    TGETS    1   1   0  ; "show_overlap_enable"
0004    NOT      1   1
0005    TSETS    1   0   0  ; "show_overlap_enable"
0006    UGET     0   0      ; self
0007    TGETS    0   0   0  ; "show_overlap_enable"
0008    IST          0
0009    JMP      0 => 0015
0010    UGET     0   0      ; self
0011    TGETS    0   0   1  ; "view"
0012    MOV      1   0
0013    TGETS    0   0   2  ; "resetDimArea"
0014    CALL     0   1   2
0015 => RET0     0   1

-- BYTECODE -- readerrolling.lua:442-444
0001    UGET     0   0      ; T
0002    UGET     1   1      ; _
0003    KSTR     2   0      ; "Number of lines: %1"
0004    CALL     1   2   2
0005    GGET     2   1      ; "G_reader_settings"
0006    MOV      3   2
0007    TGETS    2   2   2  ; "readSetting"
0008    KSTR     4   3      ; "copt_overlap_lines"
0009    CALL     2   2   3
0010    IST          2
0011    JMP      3 => 0013
0012    KSHORT   2   1
0013 => CALLT    0   3

-- BYTECODE -- readerrolling.lua:445-447
0001    UGET     0   0      ; self
0002    TGETS    0   0   0  ; "show_overlap_enable"
0003    RET1     0   2

-- BYTECODE -- readerrolling.lua:459-462
0001    GGET     1   0      ; "G_reader_settings"
0002    MOV      2   1
0003    TGETS    1   1   1  ; "saveSetting"
0004    KSTR     3   2      ; "copt_overlap_lines"
0005    TGETS    4   0   3  ; "value"
0006    CALL     1   1   4
0007    UGET     1   0      ; touchmenu_instance
0008    MOV      2   1
0009    TGETS    1   1   4  ; "updateItems"
0010    CALL     1   1   2
0011    RET0     0   1

-- BYTECODE -- readerrolling.lua:448-464
0001    GGET     1   0      ; "require"
0002    KSTR     2   1      ; "ui/widget/spinwidget"
0003    CALL     1   2   2
0004    UGET     2   0      ; UIManager
0005    MOV      3   2
0006    TGETS    2   2   2  ; "show"
0007    MOV      5   1
0008    TGETS    4   1   3  ; "new"
0009    TDUP     6   5
0010    UGET     7   1      ; Screen
0011    MOV      8   7
0012    TGETS    7   7   4  ; "getWidth"
0013    CALL     7   2   2
0014    MULVN    7   7   0  ; 0.75
0015    TSETS    7   6   6  ; "width"
0016    GGET     7   7      ; "G_reader_settings"
0017    MOV      8   7
0018    TGETS    7   7   8  ; "readSetting"
0019    KSTR     9   9      ; "copt_overlap_lines"
0020    CALL     7   2   3
0021    IST          7
0022    JMP      8 => 0024
0023    KSHORT   7   1
0024 => TSETS    7   6  10  ; "value"
0025    UGET     7   2      ; _
0026    KSTR     8  11      ; "Set"
0027    CALL     7   2   2
0028    TSETS    7   6  12  ; "ok_text"
0029    UGET     7   2      ; _
0030    KSTR     8  13      ; "Set overlapped lines"
0031    CALL     7   2   2
0032    TSETS    7   6  14  ; "title_text"
0033    UGET     7   3      ; overlap_lines_help_text
0034    TSETS    7   6  15  ; "info_text"
0035    FNEW     7  16      ; readerrolling.lua:459
0036    TSETS    7   6  17  ; "callback"
0037    CALL     4   0   3
0038    CALLM    2   1   1
0039    UCLO     0 => 0040
0040 => RET0     0   1

-- BYTECODE -- readerrolling.lua:470-470
0001    UGET     0   0      ; self
0002    TGETS    0   0   0  ; "show_overlap_enable"
0003    RET1     0   2

-- BYTECODE -- readerrolling.lua:476-476
0001    UGET     0   0      ; self
0002    TGETS    0   0   0  ; "view"
0003    TGETS    0   0   1  ; "view_mode"
0004    ISNES    0   2      ; "page"
0005    JMP      0 => 0008
0006    KPRI     0   1
0007    JMP      1 => 0009
0008 => KPRI     0   2
0009 => RET1     0   2

-- BYTECODE -- readerrolling.lua:392-480
0001    TDUP     2   2
0002    UGET     3   0      ; _
0003    KSTR     4   1      ; "Invert page turn taps and swipes"
0004    CALL     3   2   2
0005    TSETS    3   2   3  ; "text"
0006    FNEW     3   4      ; readerrolling.lua:396
0007    TSETS    3   2   5  ; "checked_func"
0008    FNEW     3   6      ; readerrolling.lua:397
0009    TSETS    3   2   7  ; "callback"
0010    FNEW     3   8      ; readerrolling.lua:400
0011    TSETS    3   2   9  ; "hold_callback"
0012    TSETS    2   1   0  ; "invert_page_turn_gestures"
0013    UGET     2   0      ; _
0014    KSTR     3  10      ; "When page overlap is enabled, some lines"~
0015    CALL     2   2   2
0016    TNEW     3   3
0017    TDUP     4  12
0018    UGET     5   0      ; _
0019    KSTR     6  11      ; "Page overlap"
0020    CALL     5   2   2
0021    TSETS    5   4   3  ; "text"
0022    FNEW     5  13      ; readerrolling.lua:431
0023    TSETS    5   4   5  ; "checked_func"
0024    FNEW     5  14      ; readerrolling.lua:434
0025    TSETS    5   4   7  ; "callback"
0026    TSETB    4   3   1
0027    TDUP     4  16
0028    FNEW     5  15      ; readerrolling.lua:442
0029    TSETS    5   4  17  ; "text_func"
0030    FNEW     5  18      ; readerrolling.lua:445
0031    TSETS    5   4  19  ; "enabled_func"
0032    FNEW     5  20      ; readerrolling.lua:448
0033    TSETS    5   4   7  ; "callback"
0034    TSETS    2   4  21  ; "help_text"
0035    TSETB    4   3   2
0036    FNEW     4  22      ; readerrolling.lua:470
0037    GGET     5  23      ; "ipairs"
0038    TGETS    6   0  24  ; "view"
0039    MOV      7   6
0040    TGETS    6   6  25  ; "genOverlapStyleMenu"
0041    MOV      8   4
0042    CALL     6   0   3
0043    CALLM    5   4   0
0044    JMP      8 => 0050
0045 => GGET    10  26      ; "table"
0046    TGETS   10  10  27  ; "insert"
0047    MOV     11   3
0048    MOV     12   9
0049    CALL    10   1   3
0050 => ITERC    8   3   3
0051    ITERL    8 => 0045
0052    TDUP     5  29
0053    UGET     6   0      ; _
0054    KSTR     7  11      ; "Page overlap"
0055    CALL     6   2   2
0056    TSETS    6   5   3  ; "text"
0057    FNEW     6  30      ; readerrolling.lua:476
0058    TSETS    6   5  19  ; "enabled_func"
0059    UGET     6   0      ; _
0060    KSTR     7  31      ; "When page overlap is enabled, some lines"~
0061    CALL     6   2   2
0062    TSETS    6   5  21  ; "help_text"
0063    TSETS    3   5  32  ; "sub_item_table"
0064    TSETS    5   1  28  ; "page_overlap"
0065    UCLO     0 => 0066
0066 => RET0     0   1

-- BYTECODE -- readerrolling.lua:482-490
0001    TGETS    1   0   0  ; "view"
0002    TGETS    1   1   1  ; "view_mode"
0003    ISNES    1   2      ; "page"
0004    JMP      1 => 0010
0005    TGETS    1   0   3  ; "current_page"
0006    TGETS    2   0   4  ; "old_page"
0007    DIVVV    1   1   2
0008    RET1     1   2
0009    JMP      1 => 0026
0010 => TGETS    1   0   5  ; "ui"
0011    TGETS    1   1   6  ; "document"
0012    MOV      2   1
0013    TGETS    1   1   7  ; "getPosFromXPointer"
0014    TGETS    3   0   5  ; "ui"
0015    TGETS    3   3   6  ; "document"
0016    MOV      4   3
0017    TGETS    3   3   8  ; "getXPointer"
0018    CALL     3   0   2
0019    CALLM    1   2   1
0020    TGETS    2   0   5  ; "ui"
0021    TGETS    2   2   6  ; "document"
0022    TGETS    2   2   9  ; "info"
0023    TGETS    2   2  10  ; "doc_height"
0024    DIVVV    1   1   2
0025    RET1     1   2
0026 => RET0     0   1

-- BYTECODE -- readerrolling.lua:492-512
0001    UGET     3   0      ; BD
0002    TGETS    3   3   0  ; "flipDirectionIfMirroredUILayout"
0003    TGETS    4   2   1  ; "direction"
0004    CALL     3   2   2
0005    ISNES    3   2      ; "west"
0006    JMP      4 => 0020
0007    TGETS    4   0   3  ; "inverse_reading_order"
0008    ISF          4
0009    JMP      5 => 0015
0010    MOV      5   0
0011    TGETS    4   0   4  ; "onGotoViewRel"
0012    KSHORT   6  -1
0013    CALL     4   1   3
0014    JMP      4 => 0046
0015 => MOV      5   0
0016    TGETS    4   0   4  ; "onGotoViewRel"
0017    KSHORT   6   1
0018    CALL     4   1   3
0019    JMP      4 => 0046
0020 => ISNES    3   5      ; "east"
0021    JMP      4 => 0035
0022    TGETS    4   0   3  ; "inverse_reading_order"
0023    ISF          4
0024    JMP      5 => 0030
0025    MOV      5   0
0026    TGETS    4   0   4  ; "onGotoViewRel"
0027    KSHORT   6   1
0028    CALL     4   1   3
0029    JMP      4 => 0046
0030 => MOV      5   0
0031    TGETS    4   0   4  ; "onGotoViewRel"
0032    KSHORT   6  -1
0033    CALL     4   1   3
0034    JMP      4 => 0046
0035 => TGETS    4   0   6  ; "view"
0036    TGETS    4   4   7  ; "footer"
0037    MOV      5   4
0038    TGETS    4   4   8  ; "updateFooter"
0039    CALL     4   1   2
0040    UGET     4   1      ; UIManager
0041    MOV      5   4
0042    TGETS    4   4   9  ; "setDirty"
0043    KPRI     6   0
0044    KSTR     7  10      ; "full"
0045    CALL     4   1   4
0046 => RET0     0   1

-- BYTECODE -- readerrolling.lua:514-530
0001    TGETS    3   0   0  ; "view"
0002    TGETS    3   3   1  ; "view_mode"
0003    ISNES    3   2      ; "scroll"
0004    JMP      3 => 0036
0005    KSTR     3   3      ; "distance"
0006    TGETS    4   0   4  ; "ui"
0007    TGETS    4   4   5  ; "gesture"
0008    ISF          4
0009    JMP      5 => 0016
0010    TGETS    4   0   4  ; "ui"
0011    TGETS    4   4   5  ; "gesture"
0012    TGETS    4   4   6  ; "multiswipes_enabled"
0013    ISF          4
0014    JMP      5 => 0016
0015    KSTR     3   7      ; "distance_delayed"
0016 => TGETS    4   2   8  ; "direction"
0017    ISNES    4   9      ; "north"
0018    JMP      4 => 0026
0019    MOV      5   0
0020    TGETS    4   0  10  ; "_gotoPos"
0021    TGETS    6   0  11  ; "current_pos"
0022    TGETV    7   2   3
0023    ADDVV    6   6   7
0024    CALL     4   1   3
0025    JMP      4 => 0054
0026 => TGETS    4   2   8  ; "direction"
0027    ISNES    4  12      ; "south"
0028    JMP      4 => 0054
0029    MOV      5   0
0030    TGETS    4   0  10  ; "_gotoPos"
0031    TGETS    6   0  11  ; "current_pos"
0032    TGETV    7   2   3
0033    SUBVV    6   6   7
0034    CALL     4   1   3
0035    JMP      3 => 0054
0036 => TGETS    3   2  13  ; "mousewheel_direction"
0037    ISF          3
0038    JMP      4 => 0054
0039    TGETS    3   0   0  ; "view"
0040    TGETS    3   3   1  ; "view_mode"
0041    ISNES    3  14      ; "page"
0042    JMP      3 => 0054
0043    UGET     3   0      ; UIManager
0044    MOV      4   3
0045    TGETS    3   3  15  ; "broadcastEvent"
0046    UGET     5   1      ; Event
0047    MOV      6   5
0048    TGETS    5   5  16  ; "new"
0049    KSTR     7  17      ; "GotoViewRel"
0050    TGETS    8   2  13  ; "mousewheel_direction"
0051    MULNV    8   8   0  ; -1
0052    CALL     5   0   4
0053    CALLM    3   1   1
0054 => KPRI     3   2
0055    RET1     3   2

-- BYTECODE -- readerrolling.lua:532-535
0001    TSETS    1   0   0  ; "current_pos"
0002    MOV      3   0
0003    TGETS    2   0   1  ; "updateBatteryState"
0004    CALL     2   1   2
0005    RET0     0   1

-- BYTECODE -- readerrolling.lua:537-540
0001    TSETS    1   0   0  ; "current_page"
0002    MOV      3   0
0003    TGETS    2   0   1  ; "updateBatteryState"
0004    CALL     2   1   2
0005    RET0     0   1

-- BYTECODE -- readerrolling.lua:542-544
0001    MOV      2   0
0002    TGETS    1   0   0  ; "updateBatteryState"
0003    CALL     1   1   2
0004    RET0     0   1

-- BYTECODE -- readerrolling.lua:546-555
0001    TGETS    1   0   0  ; "ui"
0002    TGETS    1   1   1  ; "document"
0003    MOV      2   1
0004    TGETS    1   1   2  ; "getVisiblePageCount"
0005    CALL     1   2   2
0006    TGETS    2   0   3  ; "current_page"
0007    KSHORT   3   1
0008    ISGE     3   1
0009    JMP      3 => 0012
0010    KSHORT   3   1
0011    JMP      4 => 0013
0012 => KSHORT   3   0
0013 => ADDVV    2   2   3
0014    TGETS    3   0   0  ; "ui"
0015    TGETS    3   3   4  ; "toc"
0016    MOV      4   3
0017    TGETS    3   3   5  ; "getNextChapter"
0018    MOV      5   2
0019    KSHORT   6   0
0020    CALL     3   2   4
0021    ISF          3
0022    JMP      4 => 0032
0023    TGETS    4   0   0  ; "ui"
0024    TGETS    4   4   6  ; "link"
0025    MOV      5   4
0026    TGETS    4   4   7  ; "addCurrentLocationToStack"
0027    CALL     4   1   2
0028    MOV      5   0
0029    TGETS    4   0   8  ; "onGotoPage"
0030    MOV      6   3
0031    CALL     4   1   3
0032 => KPRI     4   2
0033    RET1     4   2

-- BYTECODE -- readerrolling.lua:557-565
0001    TGETS    1   0   0  ; "current_page"
0002    TGETS    2   0   1  ; "ui"
0003    TGETS    2   2   2  ; "toc"
0004    MOV      3   2
0005    TGETS    2   2   3  ; "getPreviousChapter"
0006    MOV      4   1
0007    KSHORT   5   0
0008    CALL     2   2   4
0009    ISF          2
0010    JMP      3 => 0020
0011    TGETS    3   0   1  ; "ui"
0012    TGETS    3   3   4  ; "link"
0013    MOV      4   3
0014    TGETS    3   3   5  ; "addCurrentLocationToStack"
0015    CALL     3   1   2
0016    MOV      4   0
0017    TGETS    3   0   6  ; "onGotoPage"
0018    MOV      5   2
0019    CALL     3   1   3
0020 => KPRI     3   2
0021    RET1     3   2

-- BYTECODE -- readerrolling.lua:567-569
0001    MOV      2   0
0002    TGETS    1   0   0  ; "updateBatteryState"
0003    CALL     1   1   2
0004    RET0     0   1

-- BYTECODE -- readerrolling.lua:571-576
0001    UGET     2   0      ; logger
0002    TGETS    2   2   0  ; "dbg"
0003    KSTR     3   1      ; "goto document offset in percent:"
0004    MOV      4   1
0005    CALL     2   1   3
0006    MOV      3   0
0007    TGETS    2   0   2  ; "_gotoPercent"
0008    MOV      4   1
0009    CALL     2   1   3
0010    TGETS    2   0   4  ; "ui"
0011    TGETS    2   2   5  ; "document"
0012    MOV      3   2
0013    TGETS    2   2   6  ; "getXPointer"
0014    CALL     2   2   2
0015    TSETS    2   0   3  ; "xpointer"
0016    KPRI     2   2
0017    RET1     2   2

-- BYTECODE -- readerrolling.lua:578-584
0001    ISF          1
0002    JMP      2 => 0007
0003    MOV      3   0
0004    TGETS    2   0   0  ; "_gotoPage"
0005    MOV      4   1
0006    CALL     2   1   3
0007 => TGETS    2   0   2  ; "ui"
0008    TGETS    2   2   3  ; "document"
0009    MOV      3   2
0010    TGETS    2   2   4  ; "getXPointer"
0011    CALL     2   2   2
0012    TSETS    2   0   1  ; "xpointer"
0013    KPRI     2   2
0014    RET1     2   2

-- BYTECODE -- readerrolling.lua:586-592
0001    ISF          1
0002    JMP      2 => 0008
0003    MOV      3   0
0004    TGETS    2   0   0  ; "_gotoPage"
0005    TGETS    4   0   1  ; "current_page"
0006    ADDVV    4   4   1
0007    CALL     2   1   3
0008 => TGETS    2   0   3  ; "ui"
0009    TGETS    2   2   4  ; "document"
0010    MOV      3   2
0011    TGETS    2   2   5  ; "getXPointer"
0012    CALL     2   2   2
0013    TSETS    2   0   2  ; "xpointer"
0014    KPRI     2   2
0015    RET1     2   2

-- BYTECODE -- readerrolling.lua:683-696
0001    UGET     0   0      ; self
0002    KPRI     1   0
0003    TSETS    1   0   0  ; "unmark_func"
0004    UGET     0   0      ; self
0005    TGETS    0   0   1  ; "mark_orig_content_bb"
0006    ISF          0
0007    JMP      1 => 0037
0008    UGET     0   1      ; Screen
0009    TGETS    0   0   2  ; "bb"
0010    MOV      1   0
0011    TGETS    0   0   3  ; "blitFrom"
0012    UGET     2   0      ; self
0013    TGETS    2   2   1  ; "mark_orig_content_bb"
0014    UGET     3   2      ; screen_x
0015    UGET     4   3      ; screen_y
0016    KSHORT   5   0
0017    KSHORT   6   0
0018    UGET     7   4      ; marker_w
0019    UGET     8   5      ; marker_h
0020    CALL     0   1   9
0021    UGET     0   1      ; Screen
0022    TGETS    0   0   4  ; "refreshUI"
0023    UGET     1   1      ; Screen
0024    UGET     2   2      ; screen_x
0025    UGET     3   3      ; screen_y
0026    UGET     4   4      ; marker_w
0027    UGET     5   5      ; marker_h
0028    CALL     0   1   6
0029    UGET     0   0      ; self
0030    TGETS    0   0   1  ; "mark_orig_content_bb"
0031    MOV      1   0
0032    TGETS    0   0   5  ; "free"
0033    CALL     0   1   2
0034    UGET     0   0      ; self
0035    KPRI     1   0
0036    TSETS    1   0   1  ; "mark_orig_content_bb"
0037 => RET0     0   1

-- BYTECODE -- readerrolling.lua:659-699
0001    UGET     0   0      ; self
0002    KPRI     1   0
0003    TSETS    1   0   0  ; "mark_func"
0004    GGET     0   1      ; "type"
0005    UGET     1   1      ; marker_setting
0006    CALL     0   2   2
0007    ISEQS    0   2      ; "number"
0008    JMP      0 => 0011
0009    KPRI     0   1
0010    JMP      1 => 0012
0011 => KPRI     0   2
0012 => ISF          0
0013    JMP      1 => 0051
0014    UGET     1   0      ; self
0015    TGETS    1   1   3  ; "mark_orig_content_bb"
0016    ISF          1
0017    JMP      2 => 0026
0018    UGET     1   0      ; self
0019    TGETS    1   1   3  ; "mark_orig_content_bb"
0020    MOV      2   1
0021    TGETS    1   1   4  ; "free"
0022    CALL     1   1   2
0023    UGET     1   0      ; self
0024    KPRI     2   0
0025    TSETS    2   1   3  ; "mark_orig_content_bb"
0026 => UGET     1   0      ; self
0027    UGET     2   2      ; Blitbuffer
0028    TGETS    2   2   5  ; "new"
0029    UGET     3   3      ; marker_w
0030    UGET     4   4      ; marker_h
0031    UGET     5   5      ; Screen
0032    TGETS    5   5   6  ; "bb"
0033    MOV      6   5
0034    TGETS    5   5   7  ; "getType"
0035    CALL     5   0   2
0036    CALLM    2   2   2
0037    TSETS    2   1   3  ; "mark_orig_content_bb"
0038    UGET     1   0      ; self
0039    TGETS    1   1   3  ; "mark_orig_content_bb"
0040    MOV      2   1
0041    TGETS    1   1   8  ; "blitFrom"
0042    UGET     3   5      ; Screen
0043    TGETS    3   3   6  ; "bb"
0044    KSHORT   4   0
0045    KSHORT   5   0
0046    UGET     6   6      ; screen_x
0047    UGET     7   7      ; screen_y
0048    UGET     8   3      ; marker_w
0049    UGET     9   4      ; marker_h
0050    CALL     1   1   9
0051 => UGET     1   5      ; Screen
0052    TGETS    1   1   6  ; "bb"
0053    MOV      2   1
0054    TGETS    1   1   9  ; "paintRect"
0055    UGET     3   6      ; screen_x
0056    UGET     4   7      ; screen_y
0057    UGET     5   3      ; marker_w
0058    UGET     6   4      ; marker_h
0059    UGET     7   2      ; Blitbuffer
0060    TGETS    7   7  10  ; "COLOR_BLACK"
0061    CALL     1   1   7
0062    UGET     1   5      ; Screen
0063    TGETS    1   1  11  ; "refreshFast"
0064    UGET     2   5      ; Screen
0065    UGET     3   6      ; screen_x
0066    UGET     4   7      ; screen_y
0067    UGET     5   3      ; marker_w
0068    UGET     6   4      ; marker_h
0069    CALL     1   1   6
0070    ISF          0
0071    JMP      1 => 0082
0072    UGET     1   0      ; self
0073    FNEW     2  13      ; readerrolling.lua:683
0074    TSETS    2   1  12  ; "unmark_func"
0075    UGET     1   8      ; UIManager
0076    MOV      2   1
0077    TGETS    1   1  14  ; "scheduleIn"
0078    UGET     3   1      ; marker_setting
0079    UGET     4   0      ; self
0080    TGETS    4   4  12  ; "unmark_func"
0081    CALL     1   1   4
0082 => RET0     0   1

-- BYTECODE -- readerrolling.lua:594-703
0001    TGETS    3   0   0  ; "mark_func"
0002    ISF          3
0003    JMP      4 => 0011
0004    UGET     3   0      ; UIManager
0005    MOV      4   3
0006    TGETS    3   3   1  ; "unschedule"
0007    TGETS    5   0   0  ; "mark_func"
0008    CALL     3   1   3
0009    KPRI     3   0
0010    TSETS    3   0   0  ; "mark_func"
0011 => TGETS    3   0   2  ; "unmark_func"
0012    ISF          3
0013    JMP      4 => 0018
0014    TGETS    3   0   2  ; "unmark_func"
0015    CALL     3   1   1
0016    KPRI     3   0
0017    TSETS    3   0   2  ; "unmark_func"
0018 => MOV      4   0
0019    TGETS    3   0   3  ; "_gotoXPointer"
0020    MOV      5   1
0021    CALL     3   1   3
0022    TSETS    1   0   4  ; "xpointer"
0023    GGET     3   5      ; "G_reader_settings"
0024    MOV      4   3
0025    TGETS    3   3   6  ; "readSetting"
0026    KSTR     5   7      ; "followed_link_marker"
0027    CALL     3   2   3
0028    ISNEP    3   0
0029    JMP      4 => 0031
0030    KSHORT   3   1
0031 => ISF          2
0032    JMP      4 => 0168
0033    ISF          3
0034    JMP      4 => 0168
0035    TGETS    4   0   8  ; "ui"
0036    TGETS    4   4   9  ; "document"
0037    MOV      5   4
0038    TGETS    4   4  10  ; "getScreenPositionFromXPointer"
0039    MOV      6   2
0040    CALL     4   3   3
0041    TGETS    6   0   8  ; "ui"
0042    TGETS    6   6   9  ; "document"
0043    MOV      7   6
0044    TGETS    6   6  11  ; "getPageMargins"
0045    CALL     6   2   2
0046    UGET     7   1      ; Screen
0047    MOV      8   7
0048    TGETS    7   7  12  ; "scaleBySize"
0049    TGETS    9   0   8  ; "ui"
0050    TGETS    9   9  13  ; "font"
0051    TGETS    9   9  14  ; "font_size"
0052    MULVN    9   9   0  ; 1.1
0053    TGETS   10   0   8  ; "ui"
0054    TGETS   10  10  13  ; "font"
0055    TGETS   10  10  15  ; "line_space_percent"
0056    MULVV    9   9  10
0057    DIVVN    9   9   1  ; 100
0058    CALL     7   2   3
0059    GGET     8  16      ; "math"
0060    TGETS    8   8  17  ; "floor"
0061    GGET     9  16      ; "math"
0062    TGETS    9   9  18  ; "max"
0063    TGETS   10   6  19  ; "left"
0064    UGET    11   1      ; Screen
0065    MOV     12  11
0066    TGETS   11  11  12  ; "scaleBySize"
0067    KSHORT  13   5
0068    CALL    11   2   3
0069    SUBVV   10  10  11
0070    TGETS   11   6  19  ; "left"
0071    MULVN   11  11   2  ; 4
0072    DIVVN   11  11   3  ; 5
0073    CALL     9   0   3
0074    CALLM    8   2   0
0075    TGETS    9   0   8  ; "ui"
0076    TGETS    9   9   9  ; "document"
0077    MOV     10   9
0078    TGETS    9   9  20  ; "getVisiblePageCount"
0079    CALL     9   2   2
0080    KSHORT  10   1
0081    ISGE    10   9
0082    JMP      9 => 0147
0083    UGET     9   1      ; Screen
0084    MOV     10   9
0085    TGETS    9   9  21  ; "getWidth"
0086    CALL     9   2   2
0087    DIVVN    9   9   4  ; 2
0088    ISGE     5   9
0089    JMP      9 => 0117
0090    UGET     9   2      ; BD
0091    TGETS    9   9  22  ; "mirroredUILayout"
0092    CALL     9   2   1
0093    ISF          9
0094    JMP     10 => 0115
0095    UGET     9   1      ; Screen
0096    MOV     10   9
0097    TGETS    9   9  21  ; "getWidth"
0098    CALL     9   2   2
0099    DIVVN    5   9   4  ; 2
0100    TGETS    9   0   8  ; "ui"
0101    TGETS    9   9   9  ; "document"
0102    MOV     10   9
0103    TGETS    9   9  23  ; "getPageOffsetX"
0104    TGETS   11   0   8  ; "ui"
0105    TGETS   11  11   9  ; "document"
0106    MOV     12  11
0107    TGETS   11  11  24  ; "getCurrentPage"
0108    CALL    11   2   2
0109    ADDVN   11  11   5  ; 1
0110    CALL     9   2   3
0111    ADDVV   10   9   8
0112    SUBVV    8  10   5
0113    SUBVV    5   5   8
0114    JMP      9 => 0159
0115 => KSHORT   5   0
0116    JMP      9 => 0159
0117 => UGET     9   2      ; BD
0118    TGETS    9   9  22  ; "mirroredUILayout"
0119    CALL     9   2   1
0120    ISF          9
0121    JMP     10 => 0128
0122    UGET     9   1      ; Screen
0123    MOV     10   9
0124    TGETS    9   9  21  ; "getWidth"
0125    CALL     9   2   2
0126    SUBVV    5   9   8
0127    JMP      9 => 0159
0128 => UGET     9   1      ; Screen
0129    MOV     10   9
0130    TGETS    9   9  21  ; "getWidth"
0131    CALL     9   2   2
0132    DIVVN    5   9   4  ; 2
0133    TGETS    9   0   8  ; "ui"
0134    TGETS    9   9   9  ; "document"
0135    MOV     10   9
0136    TGETS    9   9  23  ; "getPageOffsetX"
0137    TGETS   11   0   8  ; "ui"
0138    TGETS   11  11   9  ; "document"
0139    MOV     12  11
0140    TGETS   11  11  24  ; "getCurrentPage"
0141    CALL    11   2   2
0142    ADDVN   11  11   5  ; 1
0143    CALL     9   2   3
0144    ADDVV   10   9   8
0145    SUBVV    8  10   5
0146    JMP      9 => 0159
0147 => UGET     9   2      ; BD
0148    TGETS    9   9  22  ; "mirroredUILayout"
0149    CALL     9   2   1
0150    ISF          9
0151    JMP     10 => 0158
0152    UGET     9   1      ; Screen
0153    MOV     10   9
0154    TGETS    9   9  21  ; "getWidth"
0155    CALL     9   2   2
0156    SUBVV    5   9   8
0157    JMP      9 => 0159
0158 => KSHORT   5   0
0159 => FNEW     9  25      ; readerrolling.lua:659
0160    TSETS    9   0   0  ; "mark_func"
0161    UGET     9   0      ; UIManager
0162    MOV     10   9
0163    TGETS    9   9  26  ; "scheduleIn"
0164    KNUM    11   6      ; 0.5
0165    TGETS   12   0   0  ; "mark_func"
0166    CALL     9   1   4
0167    UCLO     4 => 0168
0168 => KPRI     4   2
0169    UCLO     0 => 0170
0170 => RET1     4   2

-- BYTECODE -- readerrolling.lua:705-707
0001    TGETS    1   0   0  ; "xpointer"
0002    RET1     1   2

-- BYTECODE -- readerrolling.lua:709-711
0001    MOV      3   0
0002    TGETS    2   0   0  ; "onGotoXPointer"
0003    TGETS    4   1   1  ; "xpointer"
0004    TGETS    5   1   2  ; "marker_xpointer"
0005    CALLT    2   4

-- BYTECODE -- readerrolling.lua:713-753
0001    UGET     2   0      ; logger
0002    TGETS    2   2   0  ; "dbg"
0003    KSTR     3   1      ; "goto relative screen:"
0004    MOV      4   1
0005    KSTR     5   2      ; ", in mode: "
0006    TGETS    6   0   3  ; "view"
0007    TGETS    6   6   4  ; "view_mode"
0008    CALL     2   1   5
0009    TGETS    2   0   3  ; "view"
0010    TGETS    2   2   4  ; "view_mode"
0011    ISNES    2   5      ; "scroll"
0012    JMP      2 => 0096
0013    TGETS    2   0   3  ; "view"
0014    TGETS    2   2   6  ; "footer_visible"
0015    ISF          2
0016    JMP      3 => 0019
0017    KSHORT   2   1
0018    JMP      3 => 0020
0019 => KSHORT   2   0
0020 => TGETS    3   0   3  ; "view"
0021    TGETS    3   3   7  ; "footer"
0022    MOV      4   3
0023    TGETS    3   3   8  ; "getHeight"
0024    CALL     3   2   2
0025    MULVV    2   2   3
0026    TGETS    3   0   9  ; "ui"
0027    TGETS    3   3  10  ; "dimen"
0028    TGETS    3   3  11  ; "h"
0029    SUBVV    3   3   2
0030    MULVV    4   1   3
0031    TGETS    5   0  12  ; "show_overlap_enable"
0032    ISF          5
0033    JMP      6 => 0064
0034    GGET     5  13      ; "G_reader_settings"
0035    MOV      6   5
0036    TGETS    5   5  14  ; "readSetting"
0037    KSTR     7  15      ; "copt_overlap_lines"
0038    CALL     5   2   3
0039    IST          5
0040    JMP      6 => 0042
0041    KSHORT   5   1
0042 => UGET     6   1      ; Screen
0043    MOV      7   6
0044    TGETS    6   6  16  ; "scaleBySize"
0045    TGETS    8   0   9  ; "ui"
0046    TGETS    8   8  17  ; "font"
0047    TGETS    8   8  18  ; "font_size"
0048    MULVN    8   8   0  ; 1.1
0049    TGETS    9   0   9  ; "ui"
0050    TGETS    9   9  17  ; "font"
0051    TGETS    9   9  19  ; "line_space_percent"
0052    MULVV    8   8   9
0053    DIVVN    8   8   1  ; 100
0054    CALL     6   2   3
0055    MULVV    6   6   5
0056    ISGE     6   4
0057    JMP      7 => 0060
0058    SUBVV    4   4   6
0059    JMP      7 => 0064
0060 => UNM      7   6
0061    ISGE     4   7
0062    JMP      7 => 0064
0063    ADDVV    4   4   6
0064 => TGETS    5   0  20  ; "current_pos"
0065    GGET     6  21      ; "math"
0066    TGETS    6   6  22  ; "abs"
0067    MOV      7   1
0068    CALL     6   2   2
0069    ISEQN    6   2      ; 1
0070    JMP      6 => 0073
0071    KPRI     6   1
0072    JMP      7 => 0074
0073 => KPRI     6   2
0074 => MOV      8   0
0075    TGETS    7   0  23  ; "_gotoPos"
0076    TGETS    9   0  20  ; "current_pos"
0077    ADDVV    9   9   4
0078    MOV     10   6
0079    CALL     7   1   4
0080    KSHORT   7   0
0081    ISGE     7   1
0082    JMP      7 => 0141
0083    TGETS    7   0  20  ; "current_pos"
0084    ISNEV    5   7
0085    JMP      7 => 0141
0086    TGETS    7   0   9  ; "ui"
0087    MOV      8   7
0088    TGETS    7   7  24  ; "handleEvent"
0089    UGET     9   2      ; Event
0090    MOV     10   9
0091    TGETS    9   9  25  ; "new"
0092    KSTR    11  26      ; "EndOfBook"
0093    CALL     9   0   3
0094    CALLM    7   1   1
0095    JMP      2 => 0141
0096 => TGETS    2   0   3  ; "view"
0097    TGETS    2   2   4  ; "view_mode"
0098    ISNES    2  27      ; "page"
0099    JMP      2 => 0141
0100    TGETS    2   0   9  ; "ui"
0101    TGETS    2   2  28  ; "document"
0102    MOV      3   2
0103    TGETS    2   2  29  ; "getVisiblePageCount"
0104    CALL     2   2   2
0105    TGETS    3   0  30  ; "current_page"
0106    KSHORT   4   0
0107    ISGE     4   1
0108    JMP      4 => 0115
0109    GGET     4  21      ; "math"
0110    TGETS    4   4  31  ; "ceil"
0111    MOV      5   1
0112    CALL     4   2   2
0113    MOV      1   4
0114    JMP      4 => 0120
0115 => GGET     4  21      ; "math"
0116    TGETS    4   4  32  ; "floor"
0117    MOV      5   1
0118    CALL     4   2   2
0119    MOV      1   4
0120 => MOV      5   0
0121    TGETS    4   0  33  ; "_gotoPage"
0122    TGETS    6   0  30  ; "current_page"
0123    MULVV    7   1   2
0124    ADDVV    6   6   7
0125    CALL     4   1   3
0126    KSHORT   4   0
0127    ISGE     4   1
0128    JMP      4 => 0141
0129    TGETS    4   0  30  ; "current_page"
0130    ISNEV    3   4
0131    JMP      4 => 0141
0132    TGETS    4   0   9  ; "ui"
0133    MOV      5   4
0134    TGETS    4   4  24  ; "handleEvent"
0135    UGET     6   2      ; Event
0136    MOV      7   6
0137    TGETS    6   6  25  ; "new"
0138    KSTR     8  26      ; "EndOfBook"
0139    CALL     6   0   3
0140    CALLM    4   1   1
0141 => TGETS    2   0   9  ; "ui"
0142    TGETS    2   2  28  ; "document"
0143    ISEQP    2   0
0144    JMP      2 => 0151
0145    TGETS    2   0   9  ; "ui"
0146    TGETS    2   2  28  ; "document"
0147    MOV      3   2
0148    TGETS    2   2  35  ; "getXPointer"
0149    CALL     2   2   2
0150    TSETS    2   0  34  ; "xpointer"
0151 => KPRI     2   2
0152    RET1     2   2

-- BYTECODE -- readerrolling.lua:755-764
0001    GGET     3   0      ; "unpack"
0002    MOV      4   1
0003    CALL     3   3   2
0004    TGETS    5   0   1  ; "view"
0005    TGETS    5   5   2  ; "view_mode"
0006    ISEQS    5   3      ; "scroll"
0007    JMP      5 => 0019
0008    UGET     5   0      ; UIManager
0009    MOV      6   5
0010    TGETS    5   5   4  ; "broadcastEvent"
0011    UGET     7   1      ; Event
0012    MOV      8   7
0013    TGETS    7   7   5  ; "new"
0014    KSTR     9   6      ; "GotoViewRel"
0015    MOV     10   4
0016    CALL     7   0   4
0017    CALLM    5   1   1
0018    RET0     0   1
0019 => MOV      6   0
0020    TGETS    5   0   7  ; "_gotoPos"
0021    TGETS    7   0   8  ; "current_pos"
0022    TGETS    8   0   9  ; "panning_steps"
0023    TGETS    8   8  10  ; "normal"
0024    MULVV    8   4   8
0025    ADDVV    7   7   8
0026    CALL     5   1   3
0027    TGETS    5   0  12  ; "ui"
0028    TGETS    5   5  13  ; "document"
0029    MOV      6   5
0030    TGETS    5   5  14  ; "getXPointer"
0031    CALL     5   2   2
0032    TSETS    5   0  11  ; "xpointer"
0033    KPRI     5   2
0034    RET1     5   2

-- BYTECODE -- readerrolling.lua:766-769
0001    MOV      2   0
0002    TGETS    1   0   0  ; "updatePos"
0003    CALL     1   1   2
0004    RET0     0   1

-- BYTECODE -- readerrolling.lua:792-792
0001    UGET     0   0      ; self
0002    MOV      1   0
0003    TGETS    0   0   0  ; "updatePos"
0004    CALL     0   1   2
0005    RET0     0   1

-- BYTECODE -- readerrolling.lua:776-793
0001    TGETS    1   0   0  ; "ui"
0002    TGETS    1   1   1  ; "postReaderCallback"
0003    ISEQP    1   0
0004    JMP      1 => 0007
0005    KPRI     1   2
0006    UCLO     0 => 0020
0007 => TGETS    1   0   0  ; "ui"
0008    TGETS    1   1   2  ; "document"
0009    MOV      2   1
0010    TGETS    1   1   3  ; "getCurrentPos"
0011    CALL     1   1   2
0012    UGET     1   0      ; UIManager
0013    MOV      2   1
0014    TGETS    1   1   4  ; "scheduleIn"
0015    KNUM     3   0      ; 0.1
0016    FNEW     4   5      ; readerrolling.lua:792
0017    CALL     1   1   4
0018    UCLO     0 => 0019
0019 => RET0     0   1
0020 => RET1     1   2

-- BYTECODE -- readerrolling.lua:816-818
0001    UGET     0   0      ; self
0002    MOV      1   0
0003    TGETS    0   0   0  ; "onCheckDomStyleCoherence"
0004    CALL     0   1   2
0005    RET0     0   1

-- BYTECODE -- readerrolling.lua:795-819
0001    TGETS    1   0   0  ; "ui"
0002    TGETS    1   1   1  ; "document"
0003    IST          1
0004    JMP      1 => 0006
0005    UCLO     0 => 0060
0006 => TGETS    1   0   0  ; "ui"
0007    TGETS    1   1   1  ; "document"
0008    MOV      2   1
0009    TGETS    1   1   2  ; "_readMetadata"
0010    CALL     1   1   2
0011    TGETS    1   0   0  ; "ui"
0012    TGETS    1   1   1  ; "document"
0013    TGETS    1   1   3  ; "info"
0014    TGETS    1   1   4  ; "doc_height"
0015    TGETS    2   0   0  ; "ui"
0016    TGETS    2   2   1  ; "document"
0017    TGETS    2   2   3  ; "info"
0018    TGETS    2   2   5  ; "number_of_pages"
0019    TGETS    3   0   6  ; "old_doc_height"
0020    ISNEV    3   1
0021    JMP      3 => 0025
0022    TGETS    3   0   7  ; "old_page"
0023    ISEQV    3   2
0024    JMP      3 => 0045
0025 => MOV      4   0
0026    TGETS    3   0   8  ; "_gotoXPointer"
0027    TGETS    5   0   9  ; "xpointer"
0028    CALL     3   1   3
0029    TSETS    1   0   6  ; "old_doc_height"
0030    TSETS    2   0   7  ; "old_page"
0031    TGETS    3   0   0  ; "ui"
0032    MOV      4   3
0033    TGETS    3   3  10  ; "handleEvent"
0034    UGET     5   0      ; Event
0035    MOV      6   5
0036    TGETS    5   5  11  ; "new"
0037    KSTR     7  12      ; "UpdateToc"
0038    CALL     5   0   3
0039    CALLM    3   1   1
0040    TGETS    3   0  13  ; "view"
0041    TGETS    3   3  14  ; "footer"
0042    MOV      4   3
0043    TGETS    3   3  15  ; "updateFooter"
0044    CALL     3   1   2
0045 => UGET     3   1      ; UIManager
0046    MOV      4   3
0047    TGETS    3   3  16  ; "setDirty"
0048    TGETS    5   0  13  ; "view"
0049    TGETS    5   5  17  ; "dialog"
0050    KSTR     6  18      ; "partial"
0051    CALL     3   1   4
0052    UGET     3   1      ; UIManager
0053    MOV      4   3
0054    TGETS    3   3  19  ; "scheduleIn"
0055    KNUM     5   0      ; 0.1
0056    FNEW     6  20      ; readerrolling.lua:816
0057    CALL     3   1   4
0058    UCLO     0 => 0059
0059 => RET0     0   1
0060 => RET0     0   1

-- BYTECODE -- readerrolling.lua:835-837
0001    UGET     0   0      ; self
0002    MOV      1   0
0003    TGETS    0   0   0  ; "_gotoXPointer"
0004    UGET     2   0      ; self
0005    TGETS    2   2   1  ; "xpointer"
0006    CALL     0   1   3
0007    RET0     0   1

-- BYTECODE -- readerrolling.lua:824-839
0001    TGETS    1   0   0  ; "ui"
0002    TGETS    1   1   1  ; "document"
0003    MOV      2   1
0004    TGETS    1   1   2  ; "_readMetadata"
0005    CALL     1   1   2
0006    TGETS    1   0   0  ; "ui"
0007    TGETS    1   1   1  ; "document"
0008    TGETS    1   1   4  ; "info"
0009    TGETS    1   1   5  ; "doc_height"
0010    TSETS    1   0   3  ; "old_doc_height"
0011    TGETS    1   0   0  ; "ui"
0012    TGETS    1   1   1  ; "document"
0013    TGETS    1   1   4  ; "info"
0014    TGETS    1   1   7  ; "number_of_pages"
0015    TSETS    1   0   6  ; "old_page"
0016    TGETS    1   0   0  ; "ui"
0017    MOV      2   1
0018    TGETS    1   1   8  ; "handleEvent"
0019    UGET     3   0      ; Event
0020    MOV      4   3
0021    TGETS    3   3   9  ; "new"
0022    KSTR     5  10      ; "UpdateToc"
0023    CALL     3   0   3
0024    CALLM    1   1   1
0025    TGETS    1   0  11  ; "view"
0026    TGETS    1   1  12  ; "footer"
0027    MOV      2   1
0028    TGETS    1   1  13  ; "setTocMarkers"
0029    KPRI     3   2
0030    CALL     1   1   3
0031    TGETS    1   0  14  ; "xpointer"
0032    ISF          1
0033    JMP      2 => 0046
0034    MOV      2   0
0035    TGETS    1   0  15  ; "_gotoXPointer"
0036    TGETS    3   0  14  ; "xpointer"
0037    CALL     1   1   3
0038    UGET     1   1      ; UIManager
0039    MOV      2   1
0040    TGETS    1   1  16  ; "setDirty"
0041    TGETS    3   0  11  ; "view"
0042    TGETS    3   3  17  ; "dialog"
0043    KSTR     4  18      ; "partial"
0044    CALL     1   1   4
0045    JMP      1 => 0052
0046 => GGET     1  19      ; "table"
0047    TGETS    1   1  20  ; "insert"
0048    TGETS    2   0   0  ; "ui"
0049    TGETS    2   2  21  ; "postInitCallback"
0050    FNEW     3  22      ; readerrolling.lua:835
0051    CALL     1   1   3
0052 => UCLO     0 => 0053
0053 => RET0     0   1

-- BYTECODE -- readerrolling.lua:841-848
0001    TGETS    1   0   0  ; "view"
0002    TGETS    1   1   1  ; "view_mode"
0003    ISNES    1   2      ; "page"
0004    JMP      1 => 0016
0005    TGETS    1   0   3  ; "ui"
0006    MOV      2   1
0007    TGETS    1   1   4  ; "handleEvent"
0008    UGET     3   0      ; Event
0009    MOV      4   3
0010    TGETS    3   3   5  ; "new"
0011    KSTR     5   6      ; "PageUpdate"
0012    TGETS    6   0   7  ; "current_page"
0013    CALL     3   0   4
0014    CALLM    1   1   1
0015    JMP      1 => 0026
0016 => TGETS    1   0   3  ; "ui"
0017    MOV      2   1
0018    TGETS    1   1   4  ; "handleEvent"
0019    UGET     3   0      ; Event
0020    MOV      4   3
0021    TGETS    3   3   5  ; "new"
0022    KSTR     5   8      ; "PosUpdate"
0023    TGETS    6   0   9  ; "current_pos"
0024    CALL     3   0   4
0025    CALLM    1   1   1
0026 => KPRI     1   2
0027    RET1     1   2

-- BYTECODE -- readerrolling.lua:850-871
0001    TGETS    2   0   0  ; "ui"
0002    TGETS    2   2   1  ; "postReaderCallback"
0003    ISEQP    2   0
0004    JMP      2 => 0015
0005    TGETS    2   0   0  ; "ui"
0006    TGETS    2   2   2  ; "document"
0007    MOV      3   2
0008    TGETS    2   2   3  ; "setViewDimen"
0009    UGET     4   0      ; Screen
0010    MOV      5   4
0011    TGETS    4   4   4  ; "getSize"
0012    CALL     4   0   2
0013    CALLM    2   1   1
0014    JMP      2 => 0045
0015 => TGETS    2   0   0  ; "ui"
0016    TGETS    2   2   2  ; "document"
0017    MOV      3   2
0018    TGETS    2   2   5  ; "enableInternalHistory"
0019    KPRI     4   2
0020    CALL     2   1   3
0021    TGETS    2   0   0  ; "ui"
0022    TGETS    2   2   2  ; "document"
0023    MOV      3   2
0024    TGETS    2   2   3  ; "setViewDimen"
0025    UGET     4   0      ; Screen
0026    MOV      5   4
0027    TGETS    4   4   4  ; "getSize"
0028    CALL     4   0   2
0029    CALLM    2   1   1
0030    MOV      3   0
0031    TGETS    2   0   6  ; "onChangeViewMode"
0032    CALL     2   1   2
0033    MOV      3   0
0034    TGETS    2   0   7  ; "onUpdatePos"
0035    CALL     2   1   2
0036    TGETS    2   0   0  ; "ui"
0037    TGETS    2   2   2  ; "document"
0038    MOV      3   2
0039    TGETS    2   2   5  ; "enableInternalHistory"
0040    KPRI     4   1
0041    CALL     2   1   3
0042    MOV      3   0
0043    TGETS    2   0   8  ; "onRedrawCurrentView"
0044    CALL     2   1   2
0045 => RET0     0   1

-- BYTECODE -- readerrolling.lua:873-879
0001    TGETS    3   0   0  ; "ui"
0002    MOV      4   3
0003    TGETS    3   3   1  ; "handleEvent"
0004    UGET     5   0      ; Event
0005    MOV      6   5
0006    TGETS    5   5   2  ; "new"
0007    KSTR     7   3      ; "SetScreenMode"
0008    MOV      8   1
0009    ISTC     9   2
0010    JMP      9 => 0012
0011    KPRI     9   2
0012 => CALL     5   0   5
0013    CALLM    3   1   1
0014    RET0     0   1

-- BYTECODE -- readerrolling.lua:881-884
0001    TGETS    1   0   0  ; "ui"
0002    TGETS    1   1   1  ; "document"
0003    MOV      2   1
0004    TGETS    1   1   2  ; "updateColorRendering"
0005    CALL     1   1   2
0006    UGET     1   0      ; UIManager
0007    MOV      2   1
0008    TGETS    1   1   3  ; "setDirty"
0009    TGETS    3   0   4  ; "view"
0010    TGETS    3   3   5  ; "dialog"
0011    KSTR     4   6      ; "partial"
0012    CALL     1   1   4
0013    RET0     0   1

-- BYTECODE -- readerrolling.lua:889-922
0001    TGETS    3   0   0  ; "current_pos"
0002    ISNEV    1   3
0003    JMP      3 => 0005
0004    RET0     0   1
0005 => KSHORT   3   0
0006    ISGE     1   3
0007    JMP      3 => 0009
0008    KSHORT   1   0
0009 => TGETS    3   0   1  ; "ui"
0010    TGETS    3   3   2  ; "document"
0011    TGETS    3   3   3  ; "info"
0012    TGETS    3   3   4  ; "doc_height"
0013    TGETS    4   0   1  ; "ui"
0014    TGETS    4   4   5  ; "dimen"
0015    TGETS    4   4   6  ; "h"
0016    SUBVV    3   3   4
0017    TGETS    4   0   7  ; "view"
0018    TGETS    4   4   8  ; "footer"
0019    MOV      5   4
0020    TGETS    4   4   9  ; "getHeight"
0021    CALL     4   2   2
0022    ADDVV    3   3   4
0023    ISGE     3   1
0024    JMP      4 => 0026
0025    MOV      1   3
0026 => TGETS    4   0   7  ; "view"
0027    TGETS    4   4  10  ; "view_mode"
0028    ISEQS    4  11      ; "page"
0029    JMP      4 => 0103
0030    TGETS    4   0  12  ; "show_overlap_enable"
0031    ISF          4
0032    JMP      5 => 0103
0033    ISF          2
0034    JMP      4 => 0103
0035    TGETS    4   0   7  ; "view"
0036    TGETS    4   4  13  ; "footer_visible"
0037    ISF          4
0038    JMP      5 => 0041
0039    KSHORT   4   1
0040    JMP      5 => 0042
0041 => KSHORT   4   0
0042 => TGETS    5   0   7  ; "view"
0043    TGETS    5   5   8  ; "footer"
0044    MOV      6   5
0045    TGETS    5   5   9  ; "getHeight"
0046    CALL     5   2   2
0047    MULVV    4   4   5
0048    TGETS    5   0   1  ; "ui"
0049    TGETS    5   5   5  ; "dimen"
0050    TGETS    5   5   6  ; "h"
0051    SUBVV    5   5   4
0052    TGETS    6   0   0  ; "current_pos"
0053    SUBVV    6   1   6
0054    TGETS    7   0   7  ; "view"
0055    TGETS    7   7  14  ; "dim_area"
0056    KSHORT   8   0
0057    TSETS    8   7  15  ; "x"
0058    TGETS    7   0   7  ; "view"
0059    TGETS    7   7  14  ; "dim_area"
0060    GGET     8  16      ; "math"
0061    TGETS    8   8  17  ; "abs"
0062    MOV      9   6
0063    CALL     8   2   2
0064    SUBVV    8   5   8
0065    TSETS    8   7   6  ; "h"
0066    TGETS    7   0   7  ; "view"
0067    TGETS    7   7  14  ; "dim_area"
0068    TGETS    8   0   1  ; "ui"
0069    TGETS    8   8   5  ; "dimen"
0070    TGETS    8   8  18  ; "w"
0071    TSETS    8   7  18  ; "w"
0072    KSHORT   7   0
0073    ISGE     6   7
0074    JMP      7 => 0083
0075    TGETS    7   0   7  ; "view"
0076    TGETS    7   7  14  ; "dim_area"
0077    TGETS    8   0   7  ; "view"
0078    TGETS    8   8  14  ; "dim_area"
0079    TGETS    8   8   6  ; "h"
0080    SUBVV    8   5   8
0081    TSETS    8   7  19  ; "y"
0082    JMP      7 => 0090
0083 => KSHORT   7   0
0084    ISGE     7   6
0085    JMP      7 => 0090
0086    TGETS    7   0   7  ; "view"
0087    TGETS    7   7  14  ; "dim_area"
0088    KSHORT   8   0
0089    TSETS    8   7  19  ; "y"
0090 => TGETS    7   0   0  ; "current_pos"
0091    TGETS    8   0   1  ; "ui"
0092    TGETS    8   8   5  ; "dimen"
0093    TGETS    8   8   6  ; "h"
0094    DIVVN    8   8   0  ; 2
0095    SUBVV    8   3   8
0096    ISGE     8   7
0097    JMP      7 => 0107
0098    TGETS    7   0   7  ; "view"
0099    MOV      8   7
0100    TGETS    7   7  20  ; "resetDimArea"
0101    CALL     7   1   2
0102    JMP      4 => 0107
0103 => TGETS    4   0   7  ; "view"
0104    MOV      5   4
0105    TGETS    4   4  20  ; "resetDimArea"
0106    CALL     4   1   2
0107 => TGETS    4   0   1  ; "ui"
0108    TGETS    4   4   2  ; "document"
0109    MOV      5   4
0110    TGETS    4   4  21  ; "gotoPos"
0111    MOV      6   1
0112    CALL     4   1   3
0113    TGETS    4   0   1  ; "ui"
0114    MOV      5   4
0115    TGETS    4   4  22  ; "handleEvent"
0116    UGET     6   0      ; Event
0117    MOV      7   6
0118    TGETS    6   6  23  ; "new"
0119    KSTR     8  24      ; "PosUpdate"
0120    MOV      9   1
0121    TGETS   10   0   1  ; "ui"
0122    TGETS   10  10   2  ; "document"
0123    MOV     11  10
0124    TGETS   10  10  25  ; "getCurrentPage"
0125    CALL    10   0   2
0126    CALLM    6   0   3
0127    CALLM    4   1   1
0128    RET0     0   1

-- BYTECODE -- readerrolling.lua:924-926
0001    MOV      3   0
0002    TGETS    2   0   0  ; "_gotoPos"
0003    TGETS    4   0   1  ; "ui"
0004    TGETS    4   4   2  ; "document"
0005    TGETS    4   4   3  ; "info"
0006    TGETS    4   4   4  ; "doc_height"
0007    MULVV    4   1   4
0008    DIVVN    4   4   0  ; 10000
0009    CALL     2   1   3
0010    RET0     0   1

-- BYTECODE -- readerrolling.lua:928-949
0001    TGETS    3   0   0  ; "ui"
0002    TGETS    3   3   1  ; "document"
0003    MOV      4   3
0004    TGETS    3   3   2  ; "getVisiblePageCount"
0005    CALL     3   2   2
0006    KSHORT   4   1
0007    ISGE     4   3
0008    JMP      3 => 0032
0009    IST          2
0010    JMP      3 => 0032
0011    TGETS    3   0   3  ; "odd_or_even_first_page"
0012    ISNEN    3   0      ; 1
0013    JMP      3 => 0022
0014    UGET     3   0      ; band
0015    MOV      4   1
0016    KSHORT   5   1
0017    CALL     3   2   3
0018    ISNEN    3   1      ; 0
0019    JMP      3 => 0032
0020    SUBVN    1   1   0  ; 1
0021    JMP      3 => 0032
0022 => TGETS    3   0   3  ; "odd_or_even_first_page"
0023    ISNEN    3   2      ; 2
0024    JMP      3 => 0032
0025    UGET     3   0      ; band
0026    MOV      4   1
0027    KSHORT   5   1
0028    CALL     3   2   3
0029    ISNEN    3   0      ; 1
0030    JMP      3 => 0032
0031    SUBVN    1   1   0  ; 1
0032 => TGETS    3   0   0  ; "ui"
0033    TGETS    3   3   1  ; "document"
0034    MOV      4   3
0035    TGETS    3   3   4  ; "gotoPage"
0036    MOV      5   1
0037    CALL     3   1   3
0038    TGETS    3   0   5  ; "view"
0039    TGETS    3   3   6  ; "view_mode"
0040    ISNES    3   7      ; "page"
0041    JMP      3 => 0057
0042    TGETS    3   0   0  ; "ui"
0043    MOV      4   3
0044    TGETS    3   3   8  ; "handleEvent"
0045    UGET     5   1      ; Event
0046    MOV      6   5
0047    TGETS    5   5   9  ; "new"
0048    KSTR     7  10      ; "PageUpdate"
0049    TGETS    8   0   0  ; "ui"
0050    TGETS    8   8   1  ; "document"
0051    MOV      9   8
0052    TGETS    8   8  11  ; "getCurrentPage"
0053    CALL     8   0   2
0054    CALLM    5   0   2
0055    CALLM    3   1   1
0056    JMP      3 => 0076
0057 => TGETS    3   0   0  ; "ui"
0058    MOV      4   3
0059    TGETS    3   3   8  ; "handleEvent"
0060    UGET     5   1      ; Event
0061    MOV      6   5
0062    TGETS    5   5   9  ; "new"
0063    KSTR     7  12      ; "PosUpdate"
0064    TGETS    8   0   0  ; "ui"
0065    TGETS    8   8   1  ; "document"
0066    MOV      9   8
0067    TGETS    8   8  13  ; "getCurrentPos"
0068    CALL     8   2   2
0069    TGETS    9   0   0  ; "ui"
0070    TGETS    9   9   1  ; "document"
0071    MOV     10   9
0072    TGETS    9   9  11  ; "getCurrentPage"
0073    CALL     9   0   2
0074    CALLM    5   0   3
0075    CALLM    3   1   1
0076 => RET0     0   1

-- BYTECODE -- readerrolling.lua:951-957
0001    TGETS    2   0   0  ; "view"
0002    TGETS    2   2   1  ; "view_mode"
0003    ISNES    2   2      ; "page"
0004    JMP      2 => 0015
0005    MOV      3   0
0006    TGETS    2   0   3  ; "_gotoPage"
0007    TGETS    4   0   4  ; "ui"
0008    TGETS    4   4   5  ; "document"
0009    MOV      5   4
0010    TGETS    4   4   6  ; "getPageFromXPointer"
0011    MOV      6   1
0012    CALL     4   0   3
0013    CALLM    2   1   1
0014    JMP      2 => 0024
0015 => MOV      3   0
0016    TGETS    2   0   7  ; "_gotoPos"
0017    TGETS    4   0   4  ; "ui"
0018    TGETS    4   4   5  ; "document"
0019    MOV      5   4
0020    TGETS    4   4   8  ; "getPosFromXPointer"
0021    MOV      6   1
0022    CALL     4   0   3
0023    CALLM    2   1   1
0024 => RET0     0   1

-- BYTECODE -- readerrolling.lua:969-987
0001    TSETS    1   0   0  ; "visible_pages"
0002    TGETS    2   0   1  ; "ui"
0003    TGETS    2   2   2  ; "document"
0004    MOV      3   2
0005    TGETS    2   2   3  ; "getVisiblePageCount"
0006    CALL     2   2   2
0007    TGETS    3   0   1  ; "ui"
0008    TGETS    3   3   2  ; "document"
0009    MOV      4   3
0010    TGETS    3   3   4  ; "setVisiblePageCount"
0011    MOV      5   1
0012    CALL     3   1   3
0013    TGETS    3   0   1  ; "ui"
0014    TGETS    3   3   2  ; "document"
0015    MOV      4   3
0016    TGETS    3   3   3  ; "getVisiblePageCount"
0017    CALL     3   2   2
0018    ISEQV    3   2
0019    JMP      4 => 0029
0020    TGETS    4   0   1  ; "ui"
0021    MOV      5   4
0022    TGETS    4   4   5  ; "handleEvent"
0023    UGET     6   0      ; Event
0024    MOV      7   6
0025    TGETS    6   6   6  ; "new"
0026    KSTR     8   7      ; "UpdatePos"
0027    CALL     6   0   3
0028    CALLM    4   1   1
0029 => RET0     0   1

-- BYTECODE -- readerrolling.lua:989-1001
0001    TGETS    3   0   0  ; "ui"
0002    TGETS    3   3   1  ; "document"
0003    MOV      4   3
0004    TGETS    3   3   2  ; "setStatusLineProp"
0005    MOV      5   1
0006    CALL     3   1   3
0007    ISEQN    1   0      ; 0
0008    JMP      3 => 0011
0009    KPRI     3   1
0010    JMP      4 => 0012
0011 => KPRI     3   2
0012 => TSETS    3   0   3  ; "cre_top_bar_enabled"
0013    IST          2
0014    JMP      3 => 0025
0015    TGETS    3   0   4  ; "view"
0016    TGETS    3   3   5  ; "footer"
0017    MOV      4   3
0018    TGETS    3   3   6  ; "setVisible"
0019    ISEQN    1   1      ; 1
0020    JMP      5 => 0023
0021    KPRI     5   1
0022    JMP      6 => 0024
0023 => KPRI     5   2
0024 => CALL     3   1   3
0025 => TGETS    3   0   0  ; "ui"
0026    MOV      4   3
0027    TGETS    3   3   7  ; "handleEvent"
0028    UGET     5   0      ; Event
0029    MOV      6   5
0030    TGETS    5   5   8  ; "new"
0031    KSTR     7   9      ; "UpdatePos"
0032    CALL     5   0   3
0033    CALLM    3   1   1
0034    RET0     0   1

-- BYTECODE -- readerrolling.lua:1003-1013
0001    TGETS    1   0   0  ; "view"
0002    TGETS    1   1   1  ; "view_mode"
0003    ISNES    1   2      ; "page"
0004    JMP      1 => 0034
0005    TGETS    1   0   3  ; "cre_top_bar_enabled"
0006    ISF          1
0007    JMP      2 => 0034
0008    UGET     1   0      ; logger
0009    TGETS    1   1   4  ; "dbg"
0010    KSTR     2   5      ; "update battery state"
0011    CALL     1   1   2
0012    UGET     1   1      ; Device
0013    MOV      2   1
0014    TGETS    1   1   6  ; "getPowerDevice"
0015    CALL     1   2   2
0016    MOV      3   1
0017    TGETS    2   1   7  ; "isCharging"
0018    CALL     2   2   2
0019    ISF          2
0020    JMP      3 => 0023
0021    KSHORT   2  -1
0022    JMP      3 => 0026
0023 => MOV      3   1
0024    TGETS    2   1   8  ; "getCapacity"
0025    CALL     2   2   2
0026 => ISF          2
0027    JMP      3 => 0034
0028    TGETS    3   0   9  ; "ui"
0029    TGETS    3   3  10  ; "document"
0030    MOV      4   3
0031    TGETS    3   3  11  ; "setBatteryState"
0032    MOV      5   2
0033    CALL     3   1   3
0034 => RET0     0   1

-- BYTECODE -- readerrolling.lua:1015-1046
0001    TNEW     2   3
0002    VARG     3   0   2
0003    TSETM    3   0      ; 1
0004    ISNES    1   0      ; "OnLoadFileStart"
0005    JMP      3 => 0011
0006    MOV      4   0
0007    TGETS    3   0   1  ; "showEngineProgress"
0008    KSHORT   5   0
0009    CALL     3   1   3
0010    JMP      3 => 0084
0011 => ISNES    1   2      ; "OnLoadFileProgress"
0012    JMP      3 => 0020
0013    MOV      4   0
0014    TGETS    3   0   1  ; "showEngineProgress"
0015    TGETB    5   2   1
0016    DIVVN    5   5   1  ; 100
0017    DIVVN    5   5   2  ; 2
0018    CALL     3   1   3
0019    JMP      3 => 0084
0020 => ISNES    1   3      ; "OnNodeStylesUpdateStart"
0021    JMP      3 => 0027
0022    MOV      4   0
0023    TGETS    3   0   1  ; "showEngineProgress"
0024    KSHORT   5   0
0025    CALL     3   1   3
0026    JMP      3 => 0084
0027 => ISNES    1   4      ; "OnNodeStylesUpdateProgress"
0028    JMP      3 => 0036
0029    MOV      4   0
0030    TGETS    3   0   1  ; "showEngineProgress"
0031    TGETB    5   2   1
0032    DIVVN    5   5   1  ; 100
0033    DIVVN    5   5   2  ; 2
0034    CALL     3   1   3
0035    JMP      3 => 0084
0036 => ISNES    1   5      ; "OnFormatStart"
0037    JMP      3 => 0043
0038    MOV      4   0
0039    TGETS    3   0   1  ; "showEngineProgress"
0040    KNUM     5   3      ; 0.5
0041    CALL     3   1   3
0042    JMP      3 => 0084
0043 => ISNES    1   6      ; "OnFormatProgress"
0044    JMP      3 => 0053
0045    MOV      4   0
0046    TGETS    3   0   1  ; "showEngineProgress"
0047    TGETB    5   2   1
0048    DIVVN    5   5   1  ; 100
0049    DIVVN    5   5   2  ; 2
0050    ADDNV    5   5   3  ; 0.5
0051    CALL     3   1   3
0052    JMP      3 => 0084
0053 => ISNES    1   7      ; "OnSaveCacheFileStart"
0054    JMP      3 => 0060
0055    MOV      4   0
0056    TGETS    3   0   1  ; "showEngineProgress"
0057    KSHORT   5   1
0058    CALL     3   1   3
0059    JMP      3 => 0084
0060 => ISNES    1   8      ; "OnSaveCacheFileProgress"
0061    JMP      3 => 0069
0062    MOV      4   0
0063    TGETS    3   0   1  ; "showEngineProgress"
0064    TGETB    5   2   1
0065    DIVVN    5   5   1  ; 100
0066    SUBNV    5   5   4  ; 1
0067    CALL     3   1   3
0068    JMP      3 => 0084
0069 => ISEQS    1   9      ; "OnDocumentReady"
0070    JMP      3 => 0073
0071    ISNES    1  10      ; "OnSaveCacheFileEnd"
0072    JMP      3 => 0077
0073 => MOV      4   0
0074    TGETS    3   0   1  ; "showEngineProgress"
0075    CALL     3   1   2
0076    JMP      3 => 0084
0077 => ISNES    1  11      ; "OnLoadFileError"
0078    JMP      3 => 0084
0079    UGET     3   0      ; logger
0080    TGETS    3   3  12  ; "warn"
0081    KSTR     4  13      ; "Cre error loading file:"
0082    TGETB    5   2   1
0083    CALL     3   1   3
0084 => RET0     0   1

-- BYTECODE -- readerrolling.lua:1051-1106
0001    GGET     2   0      ; "G_reader_settings"
0002    ISF          2
0003    JMP      3 => 0012
0004    GGET     2   0      ; "G_reader_settings"
0005    MOV      3   2
0006    TGETS    2   2   1  ; "isFalse"
0007    KSTR     4   2      ; "cre_show_progress"
0008    CALL     2   2   3
0009    ISF          2
0010    JMP      3 => 0012
0011    RET0     0   1
0012 => ISF          1
0013    JMP      2 => 0090
0014    UGET     2   0      ; TimeVal
0015    MOV      3   2
0016    TGETS    2   2   3  ; "now"
0017    CALL     2   2   2
0018    TGETS    3   0   4  ; "engine_progress_update_not_before"
0019    ISF          3
0020    JMP      4 => 0025
0021    TGETS    3   0   4  ; "engine_progress_update_not_before"
0022    ISGE     2   3
0023    JMP      3 => 0025
0024    RET0     0   1
0025 => TGETS    3   0   4  ; "engine_progress_update_not_before"
0026    IST          3
0027    JMP      3 => 0032
0028    UGET     3   1      ; ENGINE_PROGRESS_INITIAL_DELAY
0029    ADDVV    3   2   3
0030    TSETS    3   0   4  ; "engine_progress_update_not_before"
0031    RET0     0   1
0032 => KSHORT   3   0
0033    UGET     4   2      ; Size
0034    TGETS    4   4   5  ; "margin"
0035    TGETS    4   4   6  ; "small"
0036    UGET     5   3      ; Screen
0037    MOV      6   5
0038    TGETS    5   5   7  ; "getWidth"
0039    CALL     5   2   2
0040    DIVVN    5   5   0  ; 3
0041    UGET     6   2      ; Size
0042    TGETS    6   6   8  ; "line"
0043    TGETS    6   6   9  ; "progress"
0044    TGETS    7   0  10  ; "engine_progress_widget"
0045    ISF          7
0046    JMP      8 => 0053
0047    TGETS    7   0  10  ; "engine_progress_widget"
0048    MOV      8   7
0049    TGETS    7   7  11  ; "setPercentage"
0050    MOV      9   1
0051    CALL     7   1   3
0052    JMP      7 => 0070
0053 => UGET     7   4      ; ProgressWidget
0054    MOV      8   7
0055    TGETS    7   7  12  ; "new"
0056    TDUP     9  13
0057    TSETS    5   9  14  ; "width"
0058    TSETS    6   9  15  ; "height"
0059    TSETS    1   9  16  ; "percentage"
0060    UGET    10   3      ; Screen
0061    MOV     11  10
0062    TGETS   10  10  17  ; "scaleBySize"
0063    KSHORT  12   1
0064    CALL    10   2   3
0065    TSETS   10   9  18  ; "tick_width"
0066    TDUP    10  19
0067    TSETS   10   9  20  ; "ticks"
0068    CALL     7   2   3
0069    TSETS    7   0  10  ; "engine_progress_widget"
0070 => TGETS    7   0  10  ; "engine_progress_widget"
0071    MOV      8   7
0072    TGETS    7   7  21  ; "paintTo"
0073    UGET     9   3      ; Screen
0074    TGETS    9   9  22  ; "bb"
0075    MOV     10   3
0076    MOV     11   4
0077    CALL     7   1   5
0078    UGET     7   3      ; Screen
0079    TGETS    7   7  23  ; "refreshFast"
0080    UGET     8   3      ; Screen
0081    MOV      9   3
0082    MOV     10   4
0083    MOV     11   5
0084    MOV     12   6
0085    CALL     7   1   6
0086    UGET     7   5      ; ENGINE_PROGRESS_UPDATE_DELAY
0087    ADDVV    7   2   7
0088    TSETS    7   0   4  ; "engine_progress_update_not_before"
0089    JMP      2 => 0094
0090 => KPRI     2   0
0091    TSETS    2   0  10  ; "engine_progress_widget"
0092    KPRI     2   0
0093    TSETS    2   0   4  ; "engine_progress_update_not_before"
0094 => RET0     0   1

-- BYTECODE -- readerrolling.lua:1118-1143
0001    MOV      1   0
0002    UGET     2   0      ; self
0003    KSTR     3   0      ; "xpointer"
0004    KSTR     4   1      ; "last position in book"
0005    CALL     1   1   4
0006    UGET     1   0      ; self
0007    TGETS    1   1   2  ; "ui"
0008    TGETS    1   1   3  ; "bookmark"
0009    ISF          1
0010    JMP      2 => 0049
0011    UGET     1   0      ; self
0012    TGETS    1   1   2  ; "ui"
0013    TGETS    1   1   3  ; "bookmark"
0014    TGETS    1   1   4  ; "bookmarks"
0015    ISF          1
0016    JMP      2 => 0049
0017    UGET     1   0      ; self
0018    TGETS    1   1   2  ; "ui"
0019    TGETS    1   1   3  ; "bookmark"
0020    TGETS    1   1   4  ; "bookmarks"
0021    LEN      1   1
0022    KSHORT   2   0
0023    ISGE     2   1
0024    JMP      1 => 0049
0025    TDUP     1   5
0026    GGET     2   6      ; "ipairs"
0027    UGET     3   0      ; self
0028    TGETS    3   3   2  ; "ui"
0029    TGETS    3   3   3  ; "bookmark"
0030    TGETS    3   3   4  ; "bookmarks"
0031    CALL     2   4   2
0032    JMP      5 => 0047
0033 => GGET     7   6      ; "ipairs"
0034    MOV      8   1
0035    CALL     7   4   2
0036    JMP     10 => 0045
0037 => MOV     12   0
0038    MOV     13   6
0039    MOV     14  11
0040    TGETS   15   6   7  ; "notes"
0041    IST         15
0042    JMP     16 => 0044
0043    KSTR    15   3      ; "bookmark"
0044 => CALL    12   1   4
0045 => ITERC   10   3   3
0046    ITERL   10 => 0037
0047 => ITERC    5   3   3
0048    ITERL    5 => 0033
0049 => UGET     1   0      ; self
0050    TGETS    1   1   8  ; "view"
0051    TGETS    1   1   9  ; "highlight"
0052    ISF          1
0053    JMP      2 => 0096
0054    UGET     1   0      ; self
0055    TGETS    1   1   8  ; "view"
0056    TGETS    1   1   9  ; "highlight"
0057    TGETS    1   1  10  ; "saved"
0058    ISF          1
0059    JMP      2 => 0096
0060    TDUP     1  11
0061    GGET     2  12      ; "pairs"
0062    UGET     3   0      ; self
0063    TGETS    3   3   8  ; "view"
0064    TGETS    3   3   9  ; "highlight"
0065    TGETS    3   3  10  ; "saved"
0066    CALL     2   4   2
0067    ISNEXT   5 => 0094
0068 => ISF          6
0069    JMP      7 => 0094
0070    LEN      7   6
0071    KSHORT   8   0
0072    ISGE     8   7
0073    JMP      7 => 0094
0074    GGET     7   6      ; "ipairs"
0075    MOV      8   6
0076    CALL     7   4   2
0077    JMP     10 => 0092
0078 => GGET    12   6      ; "ipairs"
0079    MOV     13   1
0080    CALL    12   4   2
0081    JMP     15 => 0090
0082 => MOV     17   0
0083    MOV     18  11
0084    MOV     19  16
0085    TGETS   20  11  13  ; "text"
0086    IST         20
0087    JMP     21 => 0089
0088    KSTR    20   9      ; "highlight"
0089 => CALL    17   1   4
0090 => ITERC   15   3   3
0091    ITERL   15 => 0082
0092 => ITERC   10   3   3
0093    ITERL   10 => 0078
0094 => ITERN    5   3   3
0095    ITERL    5 => 0068
0096 => RET0     0   1

-- BYTECODE -- readerrolling.lua:1154-1174
0001    TGETV    3   0   1
0002    IST          3
0003    JMP      4 => 0005
0004    RET0     0   1
0005 => UGET     4   0      ; normalized_xpointers
0006    TGETV    4   4   3
0007    ISEQP    4   0
0008    JMP      4 => 0010
0009    RET0     0   1
0010 => UGET     4   1      ; nb_xpointers
0011    ADDVN    4   4   0  ; 1
0012    USETV    1   4      ; nb_xpointers
0013    UGET     4   2      ; self
0014    TGETS    4   4   0  ; "ui"
0015    TGETS    4   4   1  ; "document"
0016    MOV      5   4
0017    TGETS    4   4   2  ; "getNormalizedXPointer"
0018    MOV      6   3
0019    CALL     4   2   3
0020    UGET     5   0      ; normalized_xpointers
0021    TSETV    4   5   3
0022    ISF          4
0023    JMP      5 => 0033
0024    UGET     5   3      ; nb_xpointers_found
0025    ADDVN    5   5   0  ; 1
0026    USETV    3   5      ; nb_xpointers_found
0027    ISEQV    4   3
0028    JMP      5 => 0038
0029    UGET     5   4      ; nb_xpointers_changed
0030    ADDVN    5   5   0  ; 1
0031    USETV    4   5      ; nb_xpointers_changed
0032    JMP      5 => 0038
0033 => UGET     5   5      ; nb_xpointers_lost
0034    ADDVN    5   5   0  ; 1
0035    USETV    5   5      ; nb_xpointers_lost
0036    UGET     5   6      ; lost_xpointer_info
0037    TSETV    2   5   3
0038 => RET0     0   1

-- BYTECODE -- readerrolling.lua:1177-1196
0001    TGETV    3   0   1
0002    IST          3
0003    JMP      4 => 0005
0004    RET0     0   1
0005 => UGET     4   0      ; normalized_xpointers
0006    TGETV    4   4   3
0007    ISF          4
0008    JMP      5 => 0011
0009    TSETV    4   0   1
0010    JMP      5 => 0015
0011 => ISEQS    1   0      ; "xpointer"
0012    JMP      5 => 0015
0013    KPRI     5   2
0014    TSETS    5   0   1  ; "not_found_not_migrated"
0015 => RET0     0   1

-- BYTECODE -- readerrolling.lua:1199-1240
0001    UGET     0   0      ; logger
0002    TGETS    0   0   0  ; "info"
0003    KSTR     1   1      ; "Upgrading book to latest DOM version:"
0004    CALL     0   1   2
0005    UGET     0   1      ; self
0006    TGETS    0   0   2  ; "ui"
0007    TGETS    0   0   3  ; "doc_settings"
0008    MOV      1   0
0009    TGETS    0   0   4  ; "readSetting"
0010    KSTR     2   5      ; "cre_dom_version"
0011    CALL     0   2   3
0012    IST          0
0013    JMP      1 => 0015
0014    KSTR     0   6      ; "unknown"
0015 => UGET     1   1      ; self
0016    TGETS    1   1   2  ; "ui"
0017    TGETS    1   1   3  ; "doc_settings"
0018    TGETS    1   1   7  ; "filepath"
0019    ISF          1
0020    JMP      2 => 0049
0021    UGET     1   1      ; self
0022    TGETS    1   1   2  ; "ui"
0023    TGETS    1   1   3  ; "doc_settings"
0024    TGETS    1   1   7  ; "filepath"
0025    KSTR     2   8      ; ".old_dom"
0026    GGET     3   9      ; "tostring"
0027    MOV      4   0
0028    CALL     3   2   2
0029    CAT      1   1   3
0030    GGET     2  10      ; "lfs"
0031    TGETS    2   2  11  ; "attributes"
0032    MOV      3   1
0033    CALL     2   2   2
0034    IST          2
0035    JMP      2 => 0049
0036    GGET     2  12      ; "os"
0037    TGETS    2   2  13  ; "rename"
0038    UGET     3   1      ; self
0039    TGETS    3   3   2  ; "ui"
0040    TGETS    3   3   3  ; "doc_settings"
0041    TGETS    3   3   7  ; "filepath"
0042    MOV      4   1
0043    CALL     2   1   3
0044    UGET     2   0      ; logger
0045    TGETS    2   2   0  ; "info"
0046    KSTR     3  14      ; "  previous docsetting file saved as"
0047    MOV      4   1
0048    CALL     2   1   3
0049 => UGET     1   2      ; applyFuncToXPointersSlots
0050    UGET     2   3      ; migrateXPointer
0051    CALL     1   1   2
0052    UGET     1   0      ; logger
0053    TGETS    1   1   0  ; "info"
0054    UGET     2   4      ; T
0055    KSTR     3  15      ; "  xpointers updated: %1 unchanged, %2 mo"~
0056    UGET     4   5      ; nb_xpointers_found
0057    UGET     5   6      ; nb_xpointers_changed
0058    SUBVV    4   4   5
0059    UGET     5   6      ; nb_xpointers_changed
0060    UGET     6   7      ; nb_xpointers_lost
0061    CALL     2   0   5
0062    CALLM    1   1   0
0063    UGET     1   1      ; self
0064    TGETS    1   1   2  ; "ui"
0065    TGETS    1   1  16  ; "document"
0066    MOV      2   1
0067    TGETS    1   1  17  ; "getLatestDomVersion"
0068    CALL     1   2   2
0069    UGET     2   1      ; self
0070    TGETS    2   2   2  ; "ui"
0071    TGETS    2   2   3  ; "doc_settings"
0072    MOV      3   2
0073    TGETS    2   2  18  ; "saveSetting"
0074    KSTR     4   5      ; "cre_dom_version"
0075    MOV      5   1
0076    CALL     2   1   4
0077    UGET     2   0      ; logger
0078    TGETS    2   2   0  ; "info"
0079    KSTR     3  19      ; "  cre_dom_version updated to"
0080    MOV      4   1
0081    CALL     2   1   3
0082    GGET     2  20      ; "G_reader_settings"
0083    MOV      3   2
0084    TGETS    2   2   4  ; "readSetting"
0085    KSTR     4  21      ; "copt_block_rendering_mode"
0086    CALL     2   2   3
0087    ISEQN    2   0      ; 0
0088    JMP      3 => 0109
0089    IST          2
0090    JMP      3 => 0092
0091    KSHORT   2   3
0092 => UGET     3   1      ; self
0093    TGETS    3   3   2  ; "ui"
0094    TGETS    3   3  16  ; "document"
0095    TGETS    3   3  22  ; "configurable"
0096    TGETS    3   3  23  ; "block_rendering_mode"
0097    ISNEN    3   0      ; 0
0098    JMP      4 => 0109
0099    UGET     4   1      ; self
0100    TGETS    4   4   2  ; "ui"
0101    TGETS    4   4  16  ; "document"
0102    TGETS    4   4  22  ; "configurable"
0103    TSETS    2   4  23  ; "block_rendering_mode"
0104    UGET     4   0      ; logger
0105    TGETS    4   4   0  ; "info"
0106    KSTR     5  24      ; "  block_rendering_mode switched to"
0107    MOV      6   2
0108    CALL     4   1   3
0109 => RET0     0   1

-- BYTECODE -- readerrolling.lua:1288-1290
0001    UGET     0   0      ; self
0002    TGETS    0   0   0  ; "ui"
0003    TGETS    0   0   1  ; "doc_settings"
0004    MOV      1   0
0005    TGETS    0   0   2  ; "saveSetting"
0006    KSTR     2   3      ; "cre_keep_old_dom_version"
0007    KPRI     3   2
0008    CALL     0   1   4
0009    RET0     0   1

-- BYTECODE -- readerrolling.lua:1307-1313
0001    UGET     0   0      ; UIManager
0002    MOV      1   0
0003    TGETS    0   0   0  ; "close"
0004    UGET     2   1      ; infomsg
0005    CALL     0   1   3
0006    UGET     0   2      ; self
0007    TGETS    0   0   1  ; "ui"
0008    TGETS    0   0   2  ; "document"
0009    ISF          0
0010    JMP      1 => 0018
0011    UGET     0   3      ; upgradeToLatestDOMVersion
0012    CALL     0   1   1
0013    UGET     0   2      ; self
0014    TGETS    0   0   1  ; "ui"
0015    MOV      1   0
0016    TGETS    0   0   3  ; "reloadDocument"
0017    CALL     0   1   2
0018 => RET0     0   1

-- BYTECODE -- readerrolling.lua:1294-1315
0001    UGET     0   0      ; self
0002    TGETS    0   0   0  ; "ui"
0003    TGETS    0   0   1  ; "document"
0004    ISF          0
0005    JMP      1 => 0029
0006    GGET     0   2      ; "require"
0007    KSTR     1   3      ; "ui/widget/infomessage"
0008    CALL     0   2   2
0009    MOV      2   0
0010    TGETS    1   0   4  ; "new"
0011    TDUP     3   6
0012    UGET     4   1      ; _
0013    KSTR     5   5      ; "Upgrading and reloading book…"
0014    CALL     4   2   2
0015    TSETS    4   3   7  ; "text"
0016    CALL     1   2   3
0017    UGET     2   2      ; UIManager
0018    MOV      3   2
0019    TGETS    2   2   8  ; "show"
0020    MOV      4   1
0021    CALL     2   1   3
0022    UGET     2   2      ; UIManager
0023    MOV      3   2
0024    TGETS    2   2   9  ; "scheduleIn"
0025    KSHORT   4   2
0026    FNEW     5  10      ; readerrolling.lua:1307
0027    CALL     2   1   4
0028    UCLO     0 => 0029
0029 => RET0     0   1

-- BYTECODE -- readerrolling.lua:1292-1316
0001    UGET     0   0      ; UIManager
0002    MOV      1   0
0003    TGETS    0   0   0  ; "scheduleIn"
0004    KNUM     2   0      ; 0.5
0005    FNEW     3   1      ; readerrolling.lua:1294
0006    CALL     0   1   4
0007    RET0     0   1

-- BYTECODE -- readerrolling.lua:1108-1318
0001    TGETS    1   0   0  ; "ui"
0002    TGETS    1   1   1  ; "document"
0003    ISF          1
0004    JMP      2 => 0013
0005    TGETS    1   0   0  ; "ui"
0006    TGETS    1   1   1  ; "document"
0007    MOV      2   1
0008    TGETS    1   1   2  ; "isBuiltDomStale"
0009    CALL     1   2   2
0010    ISF          1
0011    JMP      2 => 0013
0012    UCLO     0 => 0138
0013 => FNEW     1   3      ; readerrolling.lua:1118
0014    TNEW     2   0
0015    TNEW     3   0
0016    KSHORT   4   0
0017    KSHORT   5   0
0018    KSHORT   6   0
0019    KSHORT   7   0
0020    FNEW     8   4      ; readerrolling.lua:1154
0021    FNEW     9   5      ; readerrolling.lua:1177
0022    FNEW    10   6      ; readerrolling.lua:1199
0023    MOV     11   1
0024    MOV     12   8
0025    CALL    11   1   2
0026    UGET    11   0      ; logger
0027    TGETS   11  11   7  ; "info"
0028    UGET    12   1      ; T
0029    KSTR    13   8      ; "%1 xpointers checked: %2 found (%3 chang"~
0030    MOV     14   4
0031    MOV     15   5
0032    MOV     16   6
0033    MOV     17   7
0034    CALL    12   0   6
0035    CALLM   11   1   0
0036    KSHORT  11   0
0037    ISGE    11   7
0038    JMP     11 => 0056
0039    UGET    11   0      ; logger
0040    TGETS   11  11   9  ; "warn"
0041    KSTR    12  10      ; "Lost xpointers:"
0042    CALL    11   1   2
0043    GGET    11  11      ; "pairs"
0044    MOV     12   3
0045    CALL    11   4   2
0046    ISNEXT  14 => 0054
0047 => UGET    16   0      ; logger
0048    TGETS   16  16   9  ; "warn"
0049    KSTR    17  12      ; "  "
0050    MOV     18  14
0051    KSTR    19  13      ; ":"
0052    MOV     20  15
0053    CALL    16   1   5
0054 => ITERN   14   3   3
0055    ITERL   14 => 0047
0056 => UGET    11   2      ; _
0057    KSTR    12  14      ; "This book was first opened, and has been"~
0058    CALL    11   2   2
0059    TNEW    12   0
0060    ISNEN    7   0      ; 0
0061    JMP     13 => 0070
0062    GGET    13  15      ; "table"
0063    TGETS   13  13  16  ; "insert"
0064    MOV     14  12
0065    UGET    15   2      ; _
0066    KSTR    16  17      ; "All your bookmarks and highlights are va"~
0067    CALL    15   0   2
0068    CALLM   13   1   1
0069    JMP     13 => 0081
0070 => GGET    13  15      ; "table"
0071    TGETS   13  13  16  ; "insert"
0072    MOV     14  12
0073    UGET    15   1      ; T
0074    UGET    16   2      ; _
0075    KSTR    17  18      ; "Note that %1 (out of %2) xpaths from you"~
0076    CALL    16   2   2
0077    MOV     17   7
0078    MOV     18   4
0079    CALL    15   0   4
0080    CALLM   13   1   1
0081 => KSHORT  13   0
0082    ISGE    13   6
0083    JMP     13 => 0095
0084    GGET    13  15      ; "table"
0085    TGETS   13  13  16  ; "insert"
0086    MOV     14  12
0087    UGET    15   1      ; T
0088    UGET    16   2      ; _
0089    KSTR    17  19      ; "Note that %1 (out of %2) xpaths from you"~
0090    CALL    16   2   2
0091    MOV     17   6
0092    MOV     18   4
0093    CALL    15   0   4
0094    CALLM   13   1   1
0095 => UGET    13   1      ; T
0096    MOV     14  11
0097    GGET    15  15      ; "table"
0098    TGETS   15  15  20  ; "concat"
0099    MOV     16  12
0100    KSTR    17  21      ; "\n\n"
0101    CALL    15   0   3
0102    CALLM   13   2   1
0103    MOV     11  13
0104    UGET    13   3      ; UIManager
0105    MOV     14  13
0106    TGETS   13  13  22  ; "show"
0107    UGET    15   4      ; ConfirmBox
0108    MOV     16  15
0109    TGETS   15  15  23  ; "new"
0110    TDUP    17  24
0111    TSETS   11  17  25  ; "text"
0112    TNEW    18   3
0113    TNEW    19   3
0114    TDUP    20  27
0115    UGET    21   2      ; _
0116    KSTR    22  26      ; "Not now"
0117    CALL    21   2   2
0118    TSETS   21  20  25  ; "text"
0119    TSETB   20  19   1
0120    TSETB   19  18   1
0121    TSETS   18  17  28  ; "other_buttons"
0122    UGET    18   2      ; _
0123    KSTR    19  29      ; "Not for this book"
0124    CALL    18   2   2
0125    TSETS   18  17  30  ; "cancel_text"
0126    FNEW    18  31      ; readerrolling.lua:1288
0127    TSETS   18  17  32  ; "cancel_callback"
0128    UGET    18   2      ; _
0129    KSTR    19  33      ; "Upgrade now"
0130    CALL    18   2   2
0131    TSETS   18  17  34  ; "ok_text"
0132    FNEW    18  35      ; readerrolling.lua:1292
0133    TSETS   18  17  36  ; "ok_callback"
0134    CALL    15   0   3
0135    CALLM   13   1   1
0136    UCLO     0 => 0137
0137 => RET0     0   1
0138 => RET0     0   1

-- BYTECODE -- readerrolling.lua:0-1321
0001    GGET     0   0      ; "require"
0002    KSTR     1   1      ; "ui/bidi"
0003    CALL     0   2   2
0004    GGET     1   0      ; "require"
0005    KSTR     2   2      ; "ffi/blitbuffer"
0006    CALL     1   2   2
0007    GGET     2   0      ; "require"
0008    KSTR     3   3      ; "ui/widget/confirmbox"
0009    CALL     2   2   2
0010    GGET     3   0      ; "require"
0011    KSTR     4   4      ; "device"
0012    CALL     3   2   2
0013    GGET     4   0      ; "require"
0014    KSTR     5   5      ; "ui/event"
0015    CALL     4   2   2
0016    GGET     5   0      ; "require"
0017    KSTR     6   6      ; "ui/widget/container/inputcontainer"
0018    CALL     5   2   2
0019    GGET     6   0      ; "require"
0020    KSTR     7   7      ; "ui/widget/multiconfirmbox"
0021    CALL     6   2   2
0022    GGET     7   0      ; "require"
0023    KSTR     8   8      ; "ui/widget/progresswidget"
0024    CALL     7   2   2
0025    GGET     8   0      ; "require"
0026    KSTR     9   9      ; "apps/reader/modules/readerpanning"
0027    CALL     8   2   2
0028    GGET     9   0      ; "require"
0029    KSTR    10  10      ; "ui/size"
0030    CALL     9   2   2
0031    GGET    10   0      ; "require"
0032    KSTR    11  11      ; "ui/timeval"
0033    CALL    10   2   2
0034    GGET    11   0      ; "require"
0035    KSTR    12  12      ; "ui/uimanager"
0036    CALL    11   2   2
0037    GGET    12   0      ; "require"
0038    KSTR    13  13      ; "bit"
0039    CALL    12   2   2
0040    GGET    13   0      ; "require"
0041    KSTR    14  14      ; "logger"
0042    CALL    13   2   2
0043    GGET    14   0      ; "require"
0044    KSTR    15  15      ; "gettext"
0045    CALL    14   2   2
0046    TGETS   15   3  16  ; "screen"
0047    GGET    16   0      ; "require"
0048    KSTR    17  17      ; "ffi/util"
0049    CALL    16   2   2
0050    TGETS   16  16  18  ; "template"
0051    TGETS   17  12  19  ; "band"
0052    MOV     19   5
0053    TGETS   18   5  20  ; "new"
0054    TDUP    20  21
0055    TGETS   21   8  22  ; "panning_steps"
0056    TSETS   21  20  22  ; "panning_steps"
0057    CALL    18   2   3
0058    FNEW    19  24      ; readerrolling.lua:60
0059    TSETS   19  18  23  ; "init"
0060    FNEW    19  26      ; readerrolling.lua:133
0061    TSETS   19  18  25  ; "onReadSettings"
0062    FNEW    19  28      ; readerrolling.lua:248
0063    TSETS   19  18  27  ; "onCloseDocument"
0064    FNEW    19  30      ; readerrolling.lua:263
0065    TSETS   19  18  29  ; "onCheckDomStyleCoherence"
0066    FNEW    19  32      ; readerrolling.lua:286
0067    TSETS   19  18  31  ; "onSaveSettings"
0068    FNEW    19  34      ; readerrolling.lua:301
0069    TSETS   19  18  33  ; "onReaderReady"
0070    FNEW    19  36      ; readerrolling.lua:306
0071    TSETS   19  18  35  ; "setupTouchZones"
0072    FNEW    19  38      ; readerrolling.lua:388
0073    TSETS   19  18  37  ; "getLastProgress"
0074    FNEW    19  40      ; readerrolling.lua:392
0075    TSETS   19  18  39  ; "addToMainMenu"
0076    FNEW    19  42      ; readerrolling.lua:482
0077    TSETS   19  18  41  ; "getLastPercent"
0078    FNEW    19  44      ; readerrolling.lua:492
0079    TSETS   19  18  43  ; "onSwipe"
0080    FNEW    19  46      ; readerrolling.lua:514
0081    TSETS   19  18  45  ; "onPan"
0082    FNEW    19  48      ; readerrolling.lua:532
0083    TSETS   19  18  47  ; "onPosUpdate"
0084    FNEW    19  50      ; readerrolling.lua:537
0085    TSETS   19  18  49  ; "onPageUpdate"
0086    FNEW    19  52      ; readerrolling.lua:542
0087    TSETS   19  18  51  ; "onResume"
0088    FNEW    19  54      ; readerrolling.lua:546
0089    TSETS   19  18  53  ; "onGotoNextChapter"
0090    FNEW    19  56      ; readerrolling.lua:557
0091    TSETS   19  18  55  ; "onGotoPrevChapter"
0092    FNEW    19  58      ; readerrolling.lua:567
0093    TSETS   19  18  57  ; "onNotCharging"
0094    FNEW    19  60      ; readerrolling.lua:571
0095    TSETS   19  18  59  ; "onGotoPercent"
0096    FNEW    19  62      ; readerrolling.lua:578
0097    TSETS   19  18  61  ; "onGotoPage"
0098    FNEW    19  64      ; readerrolling.lua:586
0099    TSETS   19  18  63  ; "onGotoRelativePage"
0100    FNEW    19  66      ; readerrolling.lua:594
0101    TSETS   19  18  65  ; "onGotoXPointer"
0102    FNEW    19  68      ; readerrolling.lua:705
0103    TSETS   19  18  67  ; "getBookLocation"
0104    FNEW    19  70      ; readerrolling.lua:709
0105    TSETS   19  18  69  ; "onRestoreBookLocation"
0106    FNEW    19  72      ; readerrolling.lua:713
0107    TSETS   19  18  71  ; "onGotoViewRel"
0108    FNEW    19  74      ; readerrolling.lua:755
0109    TSETS   19  18  73  ; "onPanning"
0110    FNEW    19  76      ; readerrolling.lua:766
0111    TSETS   19  18  75  ; "onZoom"
0112    FNEW    19  78      ; readerrolling.lua:776
0113    TSETS   19  18  77  ; "onUpdatePos"
0114    FNEW    19  80      ; readerrolling.lua:795
0115    TSETS   19  18  79  ; "updatePos"
0116    FNEW    19  82      ; readerrolling.lua:824
0117    TSETS   19  18  81  ; "onChangeViewMode"
0118    FNEW    19  84      ; readerrolling.lua:841
0119    TSETS   19  18  83  ; "onRedrawCurrentView"
0120    FNEW    19  86      ; readerrolling.lua:850
0121    TSETS   19  18  85  ; "onSetDimensions"
0122    FNEW    19  88      ; readerrolling.lua:873
0123    TSETS   19  18  87  ; "onChangeScreenMode"
0124    FNEW    19  90      ; readerrolling.lua:881
0125    TSETS   19  18  89  ; "onColorRenderingUpdate"
0126    FNEW    19  92      ; readerrolling.lua:889
0127    TSETS   19  18  91  ; "_gotoPos"
0128    FNEW    19  94      ; readerrolling.lua:924
0129    TSETS   19  18  93  ; "_gotoPercent"
0130    FNEW    19  96      ; readerrolling.lua:928
0131    TSETS   19  18  95  ; "_gotoPage"
0132    FNEW    19  98      ; readerrolling.lua:951
0133    TSETS   19  18  97  ; "_gotoXPointer"
0134    FNEW    19 100      ; readerrolling.lua:969
0135    TSETS   19  18  99  ; "onSetVisiblePages"
0136    FNEW    19 102      ; readerrolling.lua:989
0137    TSETS   19  18 101  ; "onSetStatusLine"
0138    FNEW    19 104      ; readerrolling.lua:1003
0139    TSETS   19  18 103  ; "updateBatteryState"
0140    FNEW    19 106      ; readerrolling.lua:1015
0141    TSETS   19  18 105  ; "handleEngineCallback"
0142    MOV     20  10
0143    TGETS   19  10  20  ; "new"
0144    TDUP    21 107
0145    CALL    19   2   3
0146    MOV     21  10
0147    TGETS   20  10  20  ; "new"
0148    TDUP    22 108
0149    CALL    20   2   3
0150    FNEW    21 110      ; readerrolling.lua:1051
0151    TSETS   21  18 109  ; "showEngineProgress"
0152    FNEW    21 112      ; readerrolling.lua:1108
0153    TSETS   21  18 111  ; "checkXPointersAndProposeDOMVersionUpgrad"~
0154    UCLO     0 => 0155
0155 => RET1    18   2

