
main <./frontend/apps/reader/modules/readerpaging.lua:0,0> (221 instructions, 884 bytes at 0x7ffb2d4068f0)
0+ params, 25 slots, 0 upvalues, 14 locals, 92 constants, 54 functions
	1	[1]	GETGLOBAL	0 -1	; require
	2	[1]	LOADK    	1 -2	; "ui/bidi"
	3	[1]	CALL     	0 2 2
	4	[2]	GETGLOBAL	1 -1	; require
	5	[2]	LOADK    	2 -3	; "device"
	6	[2]	CALL     	1 2 2
	7	[3]	GETGLOBAL	2 -1	; require
	8	[3]	LOADK    	3 -4	; "ui/event"
	9	[3]	CALL     	2 2 2
	10	[4]	GETGLOBAL	3 -1	; require
	11	[4]	LOADK    	4 -5	; "ui/geometry"
	12	[4]	CALL     	3 2 2
	13	[5]	GETGLOBAL	4 -1	; require
	14	[5]	LOADK    	5 -6	; "ui/widget/container/inputcontainer"
	15	[5]	CALL     	4 2 2
	16	[6]	GETGLOBAL	5 -1	; require
	17	[6]	LOADK    	6 -7	; "optmath"
	18	[6]	CALL     	5 2 2
	19	[7]	GETGLOBAL	6 -1	; require
	20	[7]	LOADK    	7 -8	; "ui/widget/multiconfirmbox"
	21	[7]	CALL     	6 2 2
	22	[8]	GETGLOBAL	7 -1	; require
	23	[8]	LOADK    	8 -9	; "ui/uimanager"
	24	[8]	CALL     	7 2 2
	25	[9]	GETGLOBAL	8 -1	; require
	26	[9]	LOADK    	9 -10	; "logger"
	27	[9]	CALL     	8 2 2
	28	[10]	GETGLOBAL	9 -1	; require
	29	[10]	LOADK    	10 -11	; "gettext"
	30	[10]	CALL     	9 2 2
	31	[11]	GETTABLE 	10 1 -12	; "input"
	32	[12]	GETTABLE 	11 1 -13	; "screen"
	33	[25]	CLOSURE  	12 0	; 0x7ffb2d406c80
	34	[28]	SELF     	13 4 -14	; "new"
	35	[28]	NEWTABLE 	15 0 12
	36	[29]	SETTABLE 	15 -15 -16	; "pan_rate" 30
	37	[30]	SETTABLE 	15 -17 -18	; "current_page" 0
	38	[31]	SETTABLE 	15 -19 -18	; "number_of_pages" 0
	39	[32]	SETTABLE 	15 -20 -18	; "last_pan_relative_y" 0
	40	[33]	SETTABLE 	15 -21 -22	; "visible_area" nil
	41	[34]	SETTABLE 	15 -23 -22	; "page_area" nil
	42	[35]	SETTABLE 	15 -24 -22	; "show_overlap_enable" nil
	43	[36]	SELF     	16 11 -26	; "scaleBySize"
	44	[36]	GETGLOBAL	18 -27	; DOVERLAPPIXELS
	45	[36]	CALL     	16 3 2
	46	[36]	SETTABLE 	15 -25 16	; "overlap" -
	47	[38]	SETTABLE 	15 -28 -22	; "inverse_reading_order" nil
	48	[39]	SETTABLE 	15 -29 -30	; "page_flipping_mode" false
	49	[40]	SETTABLE 	15 -31 -30	; "bookmark_flipping_mode" false
	50	[41]	NEWTABLE 	16 8 0
	51	[41]	LOADK    	17 -18	; 0
	52	[41]	LOADK    	18 -33	; 1
	53	[41]	LOADK    	19 -34	; 2
	54	[41]	LOADK    	20 -35	; 5
	55	[41]	LOADK    	21 -36	; 10
	56	[41]	LOADK    	22 -37	; 20
	57	[41]	LOADK    	23 -38	; 50
	58	[41]	LOADK    	24 -39	; 100
	59	[41]	SETLIST  	16 8 1	; 1
	60	[41]	SETTABLE 	15 -32 16	; "flip_steps" -
	61	[28]	CALL     	13 3 2
	62	[99]	CLOSURE  	14 1	; 0x7ffb2d407070
	63	[99]	MOVE     	0 1
	64	[44]	SETTABLE 	13 -40 14	; "init" -
	65	[103]	CLOSURE  	14 2	; 0x7ffb2d407550
	66	[101]	SETTABLE 	13 -41 14	; "onReaderReady" -
	67	[138]	CLOSURE  	14 3	; 0x7ffb2d408670
	68	[138]	MOVE     	0 0
	69	[105]	SETTABLE 	13 -42 14	; "setupTapTouchZones" -
	70	[176]	CLOSURE  	14 4	; 0x7ffb2d408fe0
	71	[176]	MOVE     	0 1
	72	[141]	SETTABLE 	13 -43 14	; "setupTouchZones" -
	73	[191]	CLOSURE  	14 5	; 0x7ffb2d40a120
	74	[178]	SETTABLE 	13 -44 14	; "onReadSettings" -
	75	[202]	CLOSURE  	14 6	; 0x7ffb2d40a760
	76	[193]	SETTABLE 	13 -45 14	; "onSaveSettings" -
	77	[206]	CLOSURE  	14 7	; 0x7ffb2d40ad30
	78	[204]	SETTABLE 	13 -46 14	; "getLastProgress" -
	79	[212]	CLOSURE  	14 8	; 0x7ffb2d40aa40
	80	[208]	SETTABLE 	13 -47 14	; "getLastPercent" -
	81	[273]	CLOSURE  	14 9	; 0x7ffb2d40b520
	82	[273]	MOVE     	0 9
	83	[273]	MOVE     	0 2
	84	[273]	MOVE     	0 7
	85	[273]	MOVE     	0 6
	86	[214]	SETTABLE 	13 -48 14	; "addToMainMenu" -
	87	[278]	CLOSURE  	14 10	; 0x7ffb2d40a1f0
	88	[278]	MOVE     	0 7
	89	[275]	SETTABLE 	13 -49 14	; "onColorRenderingUpdate" -
	90	[290]	CLOSURE  	14 11	; 0x7ffb2d40d980
	91	[290]	MOVE     	0 8
	92	[287]	SETTABLE 	13 -50 14	; "setPagePosition" -
	93	[302]	CLOSURE  	14 12	; 0x7ffb2d40de00
	94	[302]	MOVE     	0 8
	95	[295]	SETTABLE 	13 -51 14	; "getPagePosition" -
	96	[323]	CLOSURE  	14 13	; 0x7ffb2d40e3d0
	97	[323]	MOVE     	0 2
	98	[323]	MOVE     	0 7
	99	[304]	SETTABLE 	13 -52 14	; "onTogglePageFlipping" -
	100	[345]	CLOSURE  	14 14	; 0x7ffb2d40e940
	101	[345]	MOVE     	0 2
	102	[345]	MOVE     	0 7
	103	[325]	SETTABLE 	13 -53 14	; "onToggleBookmarkFlipping" -
	104	[356]	CLOSURE  	14 15	; 0x7ffb2d40e8b0
	105	[356]	MOVE     	0 8
	106	[356]	MOVE     	0 10
	107	[356]	MOVE     	0 2
	108	[347]	SETTABLE 	13 -54 14	; "enterFlippingMode" -
	109	[366]	CLOSURE  	14 16	; 0x7ffb2d40f270
	110	[366]	MOVE     	0 10
	111	[366]	MOVE     	0 8
	112	[366]	MOVE     	0 2
	113	[358]	SETTABLE 	13 -55 14	; "exitFlippingMode" -
	114	[370]	CLOSURE  	14 17	; 0x7ffb2d40b4a0
	115	[368]	SETTABLE 	13 -56 14	; "updateOriginalPage" -
	116	[374]	CLOSURE  	14 18	; 0x7ffb2d4101a0
	117	[372]	SETTABLE 	13 -57 14	; "updateFlippingPage" -
	118	[392]	CLOSURE  	14 19	; 0x7ffb2d410220
	119	[392]	MOVE     	0 11
	120	[392]	MOVE     	0 0
	121	[392]	MOVE     	0 7
	122	[376]	SETTABLE 	13 -58 14	; "pageFlipping" -
	123	[402]	CLOSURE  	14 20	; 0x7ffb2d4107d0
	124	[402]	MOVE     	0 0
	125	[402]	MOVE     	0 2
	126	[402]	MOVE     	0 7
	127	[394]	SETTABLE 	13 -59 14	; "bookmarkFlipping" -
	128	[428]	CLOSURE  	14 21	; 0x7ffb2d410a90
	129	[428]	MOVE     	0 0
	130	[428]	MOVE     	0 7
	131	[404]	SETTABLE 	13 -60 14	; "onSwipe" -
	132	[453]	CLOSURE  	14 22	; 0x7ffb2d411350
	133	[430]	SETTABLE 	13 -61 14	; "onPan" -
	134	[467]	CLOSURE  	14 23	; 0x7ffb2d40afb0
	135	[467]	MOVE     	0 7
	136	[455]	SETTABLE 	13 -62 14	; "onPanRelease" -
	137	[472]	CLOSURE  	14 24	; 0x7ffb2d40d120
	138	[469]	SETTABLE 	13 -63 14	; "onZoomModeUpdate" -
	139	[479]	CLOSURE  	14 25	; 0x7ffb2d410100
	140	[479]	MOVE     	0 2
	141	[474]	SETTABLE 	13 -64 14	; "onPageUpdate" -
	142	[485]	CLOSURE  	14 26	; 0x7ffb2d408470
	143	[481]	SETTABLE 	13 -65 14	; "onViewRecalculate" -
	144	[496]	CLOSURE  	14 27	; 0x7ffb2d4084f0
	145	[496]	MOVE     	0 8
	146	[487]	SETTABLE 	13 -66 14	; "onGotoPercent" -
	147	[506]	CLOSURE  	14 28	; 0x7ffb2d40ce00
	148	[498]	SETTABLE 	13 -67 14	; "onGotoViewRel" -
	149	[516]	CLOSURE  	14 29	; 0x7ffb2d40dbd0
	150	[508]	SETTABLE 	13 -68 14	; "onGotoPosRel" -
	151	[524]	CLOSURE  	14 30	; 0x7ffb2d40e110
	152	[518]	SETTABLE 	13 -69 14	; "onPanningRel" -
	153	[528]	CLOSURE  	14 31	; 0x7ffb2d40e550
	154	[526]	SETTABLE 	13 -70 14	; "getBookLocation" -
	155	[543]	CLOSURE  	14 32	; 0x7ffb2d40e650
	156	[530]	SETTABLE 	13 -71 14	; "onRestoreBookLocation" -
	157	[555]	CLOSURE  	14 33	; 0x7ffb2d4124d0
	158	[548]	SETTABLE 	13 -72 14	; "getTopPosition" -
	159	[567]	CLOSURE  	14 34	; 0x7ffb2d4127d0
	160	[560]	SETTABLE 	13 -73 14	; "getTopPage" -
	161	[598]	CLOSURE  	14 35	; 0x7ffb2d412a80
	162	[598]	MOVE     	0 8
	163	[598]	MOVE     	0 3
	164	[569]	SETTABLE 	13 -74 14	; "onInitScrollPageStates" -
	165	[605]	CLOSURE  	14 36	; 0x7ffb2d412b90
	166	[600]	SETTABLE 	13 -75 14	; "onUpdateScrollPageRotation" -
	167	[612]	CLOSURE  	14 37	; 0x7ffb2d4137c0
	168	[607]	SETTABLE 	13 -76 14	; "onUpdateScrollPageGamma" -
	169	[634]	CLOSURE  	14 38	; 0x7ffb2d4139c0
	170	[634]	MOVE     	0 3
	171	[614]	SETTABLE 	13 -77 14	; "getNextPageState" -
	172	[657]	CLOSURE  	14 39	; 0x7ffb2d413d40
	173	[657]	MOVE     	0 3
	174	[636]	SETTABLE 	13 -78 14	; "getPrevPageState" -
	175	[674]	CLOSURE  	14 40	; 0x7ffb2d414570
	176	[674]	MOVE     	0 3
	177	[659]	SETTABLE 	13 -79 14	; "updateTopPageState" -
	178	[691]	CLOSURE  	14 41	; 0x7ffb2d413b30
	179	[691]	MOVE     	0 3
	180	[676]	SETTABLE 	13 -80 14	; "updateBottomPageState" -
	181	[719]	CLOSURE  	14 42	; 0x7ffb2d4144f0
	182	[719]	MOVE     	0 3
	183	[693]	SETTABLE 	13 -81 14	; "genPageStatesFromTop" -
	184	[744]	CLOSURE  	14 43	; 0x7ffb2d4155b0
	185	[744]	MOVE     	0 3
	186	[721]	SETTABLE 	13 -82 14	; "genPageStatesFromBottom" -
	187	[775]	CLOSURE  	14 44	; 0x7ffb2d415b50
	188	[775]	MOVE     	0 8
	189	[775]	MOVE     	0 3
	190	[775]	MOVE     	0 12
	191	[775]	MOVE     	0 7
	192	[746]	SETTABLE 	13 -83 14	; "onScrollPanRel" -
	193	[815]	CLOSURE  	14 45	; 0x7ffb2d415e10
	194	[815]	MOVE     	0 2
	195	[815]	MOVE     	0 3
	196	[815]	MOVE     	0 7
	197	[777]	SETTABLE 	13 -84 14	; "onScrollPageRel" -
	198	[967]	CLOSURE  	14 46	; 0x7ffb2d416350
	199	[967]	MOVE     	0 8
	200	[967]	MOVE     	0 5
	201	[967]	MOVE     	0 2
	202	[817]	SETTABLE 	13 -85 14	; "onGotoPageRel" -
	203	[972]	CLOSURE  	14 47	; 0x7ffb2d417190
	204	[972]	MOVE     	0 2
	205	[969]	SETTABLE 	13 -86 14	; "onRedrawCurrentPage" -
	206	[992]	CLOSURE  	14 48	; 0x7ffb2d417860
	207	[992]	MOVE     	0 8
	208	[992]	MOVE     	0 2
	209	[975]	SETTABLE 	13 -87 14	; "_gotoPage" -
	210	[997]	CLOSURE  	14 49	; 0x7ffb2d4179d0
	211	[994]	SETTABLE 	13 -88 14	; "onGotoPage" -
	212	[1002]	CLOSURE  	14 50	; 0x7ffb2d417c50
	213	[999]	SETTABLE 	13 -89 14	; "onGotoRelativePage" -
	214	[1009]	CLOSURE  	14 51	; 0x7ffb2d417fb0
	215	[1004]	SETTABLE 	13 -90 14	; "onGotoPercentage" -
	216	[1021]	CLOSURE  	14 52	; 0x7ffb2d418380
	217	[1013]	SETTABLE 	13 -91 14	; "onGotoNextChapter" -
	218	[1031]	CLOSURE  	14 53	; 0x7ffb2d411210
	219	[1023]	SETTABLE 	13 -92 14	; "onGotoPrevChapter" -
	220	[1033]	RETURN   	13 2
	221	[1033]	RETURN   	0 1

function <./frontend/apps/reader/modules/readerpaging.lua:15,25> (23 instructions, 92 bytes at 0x7ffb2d406c80)
1 param, 4 slots, 0 upvalues, 1 local, 8 constants, 0 functions
	1	[16]	NEWTABLE 	1 0 7
	2	[17]	GETTABLE 	2 0 -1	; "page"
	3	[17]	SETTABLE 	1 -1 2	; "page" -
	4	[18]	GETTABLE 	2 0 -2	; "zoom"
	5	[18]	SETTABLE 	1 -2 2	; "zoom" -
	6	[19]	GETTABLE 	2 0 -3	; "rotation"
	7	[19]	SETTABLE 	1 -3 2	; "rotation" -
	8	[20]	GETTABLE 	2 0 -4	; "gamma"
	9	[20]	SETTABLE 	1 -4 2	; "gamma" -
	10	[21]	GETTABLE 	2 0 -5	; "offset"
	11	[21]	SELF     	2 2 -6	; "copy"
	12	[21]	CALL     	2 2 2
	13	[21]	SETTABLE 	1 -5 2	; "offset" -
	14	[22]	GETTABLE 	2 0 -7	; "visible_area"
	15	[22]	SELF     	2 2 -6	; "copy"
	16	[22]	CALL     	2 2 2
	17	[22]	SETTABLE 	1 -7 2	; "visible_area" -
	18	[23]	GETTABLE 	2 0 -8	; "page_area"
	19	[23]	SELF     	2 2 -6	; "copy"
	20	[23]	CALL     	2 2 2
	21	[23]	SETTABLE 	1 -8 2	; "page_area" -
	22	[24]	RETURN   	1 2
	23	[25]	RETURN   	0 1

function <./frontend/apps/reader/modules/readerpaging.lua:44,99> (175 instructions, 700 bytes at 0x7ffb2d407070)
1 param, 8 slots, 1 upvalue, 1 local, 73 constants, 0 functions
	1	[45]	NEWTABLE 	1 0 0
	2	[45]	SETTABLE 	0 -1 1	; "key_events" -
	3	[46]	GETUPVAL 	1 0	; Device
	4	[46]	SELF     	1 1 -2	; "hasKeys"
	5	[46]	CALL     	1 2 2
	6	[46]	TEST     	1 0 0
	7	[46]	JMP      	52	; to 60
	8	[47]	GETTABLE 	1 0 -1	; "key_events"
	9	[47]	NEWTABLE 	2 1 3
	10	[47]	NEWTABLE 	3 1 0
	11	[48]	NEWTABLE 	4 3 0
	12	[48]	LOADK    	5 -4	; "RPgFwd"
	13	[48]	LOADK    	6 -5	; "LPgFwd"
	14	[48]	LOADK    	7 -6	; "Right"
	15	[48]	SETLIST  	4 3 1	; 1
	16	[48]	SETLIST  	3 1 1	; 1
	17	[48]	SETTABLE 	2 -7 -8	; "doc" "go to next page"
	18	[49]	SETTABLE 	2 -9 -10	; "event" "GotoViewRel"
	19	[49]	SETTABLE 	2 -11 -12	; "args" 1
	20	[50]	SETLIST  	2 1 1	; 1
	21	[50]	SETTABLE 	1 -3 2	; "GotoNextPage" -
	22	[51]	GETTABLE 	1 0 -1	; "key_events"
	23	[51]	NEWTABLE 	2 1 3
	24	[51]	NEWTABLE 	3 1 0
	25	[52]	NEWTABLE 	4 3 0
	26	[52]	LOADK    	5 -14	; "RPgBack"
	27	[52]	LOADK    	6 -15	; "LPgBack"
	28	[52]	LOADK    	7 -16	; "Left"
	29	[52]	SETLIST  	4 3 1	; 1
	30	[52]	SETLIST  	3 1 1	; 1
	31	[52]	SETTABLE 	2 -7 -17	; "doc" "go to previous page"
	32	[53]	SETTABLE 	2 -9 -10	; "event" "GotoViewRel"
	33	[53]	SETTABLE 	2 -11 -18	; "args" -1
	34	[54]	SETLIST  	2 1 1	; 1
	35	[54]	SETTABLE 	1 -13 2	; "GotoPrevPage" -
	36	[55]	GETTABLE 	1 0 -1	; "key_events"
	37	[55]	NEWTABLE 	2 1 3
	38	[55]	NEWTABLE 	3 1 0
	39	[56]	NEWTABLE 	4 1 0
	40	[56]	LOADK    	5 -20	; "Down"
	41	[56]	SETLIST  	4 1 1	; 1
	42	[56]	SETLIST  	3 1 1	; 1
	43	[56]	SETTABLE 	2 -7 -21	; "doc" "go to next position"
	44	[57]	SETTABLE 	2 -9 -22	; "event" "GotoPosRel"
	45	[57]	SETTABLE 	2 -11 -12	; "args" 1
	46	[58]	SETLIST  	2 1 1	; 1
	47	[58]	SETTABLE 	1 -19 2	; "GotoNextPos" -
	48	[59]	GETTABLE 	1 0 -1	; "key_events"
	49	[59]	NEWTABLE 	2 1 3
	50	[59]	NEWTABLE 	3 1 0
	51	[60]	NEWTABLE 	4 1 0
	52	[60]	LOADK    	5 -24	; "Up"
	53	[60]	SETLIST  	4 1 1	; 1
	54	[60]	SETLIST  	3 1 1	; 1
	55	[60]	SETTABLE 	2 -7 -25	; "doc" "go to previous position"
	56	[61]	SETTABLE 	2 -9 -22	; "event" "GotoPosRel"
	57	[61]	SETTABLE 	2 -11 -18	; "args" -1
	58	[62]	SETLIST  	2 1 1	; 1
	59	[62]	SETTABLE 	1 -23 2	; "GotoPrevPos" -
	60	[65]	GETUPVAL 	1 0	; Device
	61	[65]	SELF     	1 1 -26	; "hasKeyboard"
	62	[65]	CALL     	1 2 2
	63	[65]	TEST     	1 0 0
	64	[65]	JMP      	100	; to 165
	65	[66]	GETTABLE 	1 0 -1	; "key_events"
	66	[66]	NEWTABLE 	2 1 3
	67	[66]	NEWTABLE 	3 1 0
	68	[67]	LOADK    	4 -28	; "1"
	69	[67]	SETLIST  	3 1 1	; 1
	70	[67]	SETTABLE 	2 -7 -29	; "doc" "go to start"
	71	[67]	SETTABLE 	2 -9 -30	; "event" "GotoPercent"
	72	[67]	SETTABLE 	2 -11 -31	; "args" 0
	73	[68]	SETLIST  	2 1 1	; 1
	74	[68]	SETTABLE 	1 -27 2	; "GotoFirst" -
	75	[69]	GETTABLE 	1 0 -1	; "key_events"
	76	[69]	NEWTABLE 	2 1 3
	77	[69]	NEWTABLE 	3 1 0
	78	[70]	LOADK    	4 -33	; "2"
	79	[70]	SETLIST  	3 1 1	; 1
	80	[70]	SETTABLE 	2 -7 -34	; "doc" "go to 11%"
	81	[70]	SETTABLE 	2 -9 -30	; "event" "GotoPercent"
	82	[70]	SETTABLE 	2 -11 -35	; "args" 11
	83	[71]	SETLIST  	2 1 1	; 1
	84	[71]	SETTABLE 	1 -32 2	; "Goto11" -
	85	[72]	GETTABLE 	1 0 -1	; "key_events"
	86	[72]	NEWTABLE 	2 1 3
	87	[72]	NEWTABLE 	3 1 0
	88	[73]	LOADK    	4 -37	; "3"
	89	[73]	SETLIST  	3 1 1	; 1
	90	[73]	SETTABLE 	2 -7 -38	; "doc" "go to 22%"
	91	[73]	SETTABLE 	2 -9 -30	; "event" "GotoPercent"
	92	[73]	SETTABLE 	2 -11 -39	; "args" 22
	93	[74]	SETLIST  	2 1 1	; 1
	94	[74]	SETTABLE 	1 -36 2	; "Goto22" -
	95	[75]	GETTABLE 	1 0 -1	; "key_events"
	96	[75]	NEWTABLE 	2 1 3
	97	[75]	NEWTABLE 	3 1 0
	98	[76]	LOADK    	4 -41	; "4"
	99	[76]	SETLIST  	3 1 1	; 1
	100	[76]	SETTABLE 	2 -7 -42	; "doc" "go to 33%"
	101	[76]	SETTABLE 	2 -9 -30	; "event" "GotoPercent"
	102	[76]	SETTABLE 	2 -11 -43	; "args" 33
	103	[77]	SETLIST  	2 1 1	; 1
	104	[77]	SETTABLE 	1 -40 2	; "Goto33" -
	105	[78]	GETTABLE 	1 0 -1	; "key_events"
	106	[78]	NEWTABLE 	2 1 3
	107	[78]	NEWTABLE 	3 1 0
	108	[79]	LOADK    	4 -45	; "5"
	109	[79]	SETLIST  	3 1 1	; 1
	110	[79]	SETTABLE 	2 -7 -46	; "doc" "go to 44%"
	111	[79]	SETTABLE 	2 -9 -30	; "event" "GotoPercent"
	112	[79]	SETTABLE 	2 -11 -47	; "args" 44
	113	[80]	SETLIST  	2 1 1	; 1
	114	[80]	SETTABLE 	1 -44 2	; "Goto44" -
	115	[81]	GETTABLE 	1 0 -1	; "key_events"
	116	[81]	NEWTABLE 	2 1 3
	117	[81]	NEWTABLE 	3 1 0
	118	[82]	LOADK    	4 -49	; "6"
	119	[82]	SETLIST  	3 1 1	; 1
	120	[82]	SETTABLE 	2 -7 -50	; "doc" "go to 55%"
	121	[82]	SETTABLE 	2 -9 -30	; "event" "GotoPercent"
	122	[82]	SETTABLE 	2 -11 -51	; "args" 55
	123	[83]	SETLIST  	2 1 1	; 1
	124	[83]	SETTABLE 	1 -48 2	; "Goto55" -
	125	[84]	GETTABLE 	1 0 -1	; "key_events"
	126	[84]	NEWTABLE 	2 1 3
	127	[84]	NEWTABLE 	3 1 0
	128	[85]	LOADK    	4 -53	; "7"
	129	[85]	SETLIST  	3 1 1	; 1
	130	[85]	SETTABLE 	2 -7 -54	; "doc" "go to 66%"
	131	[85]	SETTABLE 	2 -9 -30	; "event" "GotoPercent"
	132	[85]	SETTABLE 	2 -11 -55	; "args" 66
	133	[86]	SETLIST  	2 1 1	; 1
	134	[86]	SETTABLE 	1 -52 2	; "Goto66" -
	135	[87]	GETTABLE 	1 0 -1	; "key_events"
	136	[87]	NEWTABLE 	2 1 3
	137	[87]	NEWTABLE 	3 1 0
	138	[88]	LOADK    	4 -57	; "8"
	139	[88]	SETLIST  	3 1 1	; 1
	140	[88]	SETTABLE 	2 -7 -58	; "doc" "go to 77%"
	141	[88]	SETTABLE 	2 -9 -30	; "event" "GotoPercent"
	142	[88]	SETTABLE 	2 -11 -59	; "args" 77
	143	[89]	SETLIST  	2 1 1	; 1
	144	[89]	SETTABLE 	1 -56 2	; "Goto77" -
	145	[90]	GETTABLE 	1 0 -1	; "key_events"
	146	[90]	NEWTABLE 	2 1 3
	147	[90]	NEWTABLE 	3 1 0
	148	[91]	LOADK    	4 -61	; "9"
	149	[91]	SETLIST  	3 1 1	; 1
	150	[91]	SETTABLE 	2 -7 -62	; "doc" "go to 88%"
	151	[91]	SETTABLE 	2 -9 -30	; "event" "GotoPercent"
	152	[91]	SETTABLE 	2 -11 -63	; "args" 88
	153	[92]	SETLIST  	2 1 1	; 1
	154	[92]	SETTABLE 	1 -60 2	; "Goto88" -
	155	[93]	GETTABLE 	1 0 -1	; "key_events"
	156	[93]	NEWTABLE 	2 1 3
	157	[93]	NEWTABLE 	3 1 0
	158	[94]	LOADK    	4 -65	; "0"
	159	[94]	SETLIST  	3 1 1	; 1
	160	[94]	SETTABLE 	2 -7 -66	; "doc" "go to end"
	161	[94]	SETTABLE 	2 -9 -30	; "event" "GotoPercent"
	162	[94]	SETTABLE 	2 -11 -67	; "args" 100
	163	[95]	SETLIST  	2 1 1	; 1
	164	[95]	SETTABLE 	1 -64 2	; "GotoLast" -
	165	[97]	GETTABLE 	1 0 -69	; "ui"
	166	[97]	GETTABLE 	1 1 -70	; "document"
	167	[97]	GETTABLE 	1 1 -71	; "info"
	168	[97]	GETTABLE 	1 1 -68	; "number_of_pages"
	169	[97]	SETTABLE 	0 -68 1	; "number_of_pages" -
	170	[98]	GETTABLE 	1 0 -69	; "ui"
	171	[98]	GETTABLE 	1 1 -72	; "menu"
	172	[98]	SELF     	1 1 -73	; "registerToMainMenu"
	173	[98]	MOVE     	3 0
	174	[98]	CALL     	1 3 1
	175	[99]	RETURN   	0 1

function <./frontend/apps/reader/modules/readerpaging.lua:101,103> (3 instructions, 12 bytes at 0x7ffb2d407550)
1 param, 3 slots, 0 upvalues, 1 local, 1 constant, 0 functions
	1	[102]	SELF     	1 0 -1	; "setupTouchZones"
	2	[102]	CALL     	1 2 1
	3	[103]	RETURN   	0 1

function <./frontend/apps/reader/modules/readerpaging.lua:105,138> (65 instructions, 260 bytes at 0x7ffb2d408670)
1 param, 10 slots, 1 upvalue, 4 locals, 22 constants, 2 functions
	1	[106]	NEWTABLE 	1 0 4
	2	[107]	GETGLOBAL	2 -2	; DTAP_ZONE_FORWARD
	3	[107]	GETTABLE 	2 2 -3	; "x"
	4	[107]	SETTABLE 	1 -1 2	; "ratio_x" -
	5	[107]	GETGLOBAL	2 -2	; DTAP_ZONE_FORWARD
	6	[107]	GETTABLE 	2 2 -5	; "y"
	7	[107]	SETTABLE 	1 -4 2	; "ratio_y" -
	8	[108]	GETGLOBAL	2 -2	; DTAP_ZONE_FORWARD
	9	[108]	GETTABLE 	2 2 -7	; "w"
	10	[108]	SETTABLE 	1 -6 2	; "ratio_w" -
	11	[108]	GETGLOBAL	2 -2	; DTAP_ZONE_FORWARD
	12	[108]	GETTABLE 	2 2 -9	; "h"
	13	[108]	SETTABLE 	1 -8 2	; "ratio_h" -
	14	[110]	NEWTABLE 	2 0 4
	15	[111]	GETGLOBAL	3 -10	; DTAP_ZONE_BACKWARD
	16	[111]	GETTABLE 	3 3 -3	; "x"
	17	[111]	SETTABLE 	2 -1 3	; "ratio_x" -
	18	[111]	GETGLOBAL	3 -10	; DTAP_ZONE_BACKWARD
	19	[111]	GETTABLE 	3 3 -5	; "y"
	20	[111]	SETTABLE 	2 -4 3	; "ratio_y" -
	21	[112]	GETGLOBAL	3 -10	; DTAP_ZONE_BACKWARD
	22	[112]	GETTABLE 	3 3 -7	; "w"
	23	[112]	SETTABLE 	2 -6 3	; "ratio_w" -
	24	[112]	GETGLOBAL	3 -10	; DTAP_ZONE_BACKWARD
	25	[112]	GETTABLE 	3 3 -9	; "h"
	26	[112]	SETTABLE 	2 -8 3	; "ratio_h" -
	27	[115]	GETUPVAL 	3 0	; BD
	28	[115]	GETTABLE 	3 3 -11	; "mirroredUILayout"
	29	[115]	CALL     	3 1 2
	30	[116]	GETTABLE 	4 0 -12	; "inverse_reading_order"
	31	[116]	TEST     	4 0 0
	32	[116]	JMP      	1	; to 34
	33	[117]	NOT      	3 3
	34	[119]	TEST     	3 0 0
	35	[119]	JMP      	10	; to 46
	36	[120]	GETTABLE 	4 1 -1	; "ratio_x"
	37	[120]	SUB      	4 -13 4	; 1 -
	38	[120]	GETTABLE 	5 1 -6	; "ratio_w"
	39	[120]	SUB      	4 4 5
	40	[120]	SETTABLE 	1 -1 4	; "ratio_x" -
	41	[121]	GETTABLE 	4 2 -1	; "ratio_x"
	42	[121]	SUB      	4 -13 4	; 1 -
	43	[121]	GETTABLE 	5 2 -6	; "ratio_w"
	44	[121]	SUB      	4 4 5
	45	[121]	SETTABLE 	2 -1 4	; "ratio_x" -
	46	[124]	GETTABLE 	4 0 -14	; "ui"
	47	[124]	SELF     	4 4 -15	; "registerTouchZones"
	48	[124]	NEWTABLE 	6 2 0
	49	[124]	NEWTABLE 	7 0 4
	50	[126]	SETTABLE 	7 -16 -17	; "id" "tap_forward"
	51	[127]	SETTABLE 	7 -18 -19	; "ges" "tap"
	52	[128]	SETTABLE 	7 -20 1	; "screen_zone" -
	53	[129]	CLOSURE  	8 0	; 0x7ffb2d408b10
	54	[129]	MOVE     	0 0
	55	[129]	SETTABLE 	7 -21 8	; "handler" -
	56	[130]	NEWTABLE 	8 0 4
	57	[132]	SETTABLE 	8 -16 -22	; "id" "tap_backward"
	58	[133]	SETTABLE 	8 -18 -19	; "ges" "tap"
	59	[134]	SETTABLE 	8 -20 2	; "screen_zone" -
	60	[135]	CLOSURE  	9 1	; 0x7ffb2d408f00
	61	[135]	MOVE     	0 0
	62	[135]	SETTABLE 	8 -21 9	; "handler" -
	63	[137]	SETLIST  	6 2 1	; 1
	64	[124]	CALL     	4 3 1
	65	[138]	RETURN   	0 1

function <./frontend/apps/reader/modules/readerpaging.lua:129,129> (6 instructions, 24 bytes at 0x7ffb2d408b10)
0 params, 3 slots, 1 upvalue, 0 locals, 2 constants, 0 functions
	1	[129]	GETUPVAL 	0 0	; self
	2	[129]	SELF     	0 0 -1	; "onGotoViewRel"
	3	[129]	LOADK    	2 -2	; 1
	4	[129]	TAILCALL 	0 3 0
	5	[129]	RETURN   	0 0
	6	[129]	RETURN   	0 1

function <./frontend/apps/reader/modules/readerpaging.lua:135,135> (6 instructions, 24 bytes at 0x7ffb2d408f00)
0 params, 3 slots, 1 upvalue, 0 locals, 2 constants, 0 functions
	1	[135]	GETUPVAL 	0 0	; self
	2	[135]	SELF     	0 0 -1	; "onGotoViewRel"
	3	[135]	LOADK    	2 -2	; -1
	4	[135]	TAILCALL 	0 3 0
	5	[135]	RETURN   	0 0
	6	[135]	RETURN   	0 1

function <./frontend/apps/reader/modules/readerpaging.lua:141,176> (55 instructions, 220 bytes at 0x7ffb2d408fe0)
1 param, 8 slots, 1 upvalue, 1 local, 25 constants, 3 functions
	1	[143]	NEWTABLE 	1 0 0
	2	[143]	SETTABLE 	0 -1 1	; "ges_events" -
	3	[144]	SETTABLE 	0 -2 -3	; "onGesture" nil
	4	[146]	GETUPVAL 	1 0	; Device
	5	[146]	SELF     	1 1 -4	; "isTouchDevice"
	6	[146]	CALL     	1 2 2
	7	[146]	TEST     	1 0 1
	8	[146]	JMP      	1	; to 10
	9	[146]	RETURN   	0 1
	10	[148]	SELF     	1 0 -5	; "setupTapTouchZones"
	11	[148]	CALL     	1 2 1
	12	[149]	GETTABLE 	1 0 -6	; "ui"
	13	[149]	SELF     	1 1 -7	; "registerTouchZones"
	14	[149]	NEWTABLE 	3 3 0
	15	[149]	NEWTABLE 	4 0 4
	16	[151]	SETTABLE 	4 -8 -9	; "id" "paging_swipe"
	17	[152]	SETTABLE 	4 -10 -11	; "ges" "swipe"
	18	[153]	NEWTABLE 	5 0 4
	19	[154]	SETTABLE 	5 -13 -14	; "ratio_x" 0
	20	[154]	SETTABLE 	5 -15 -14	; "ratio_y" 0
	21	[154]	SETTABLE 	5 -16 -17	; "ratio_w" 1
	22	[154]	SETTABLE 	5 -18 -17	; "ratio_h" 1
	23	[155]	SETTABLE 	4 -12 5	; "screen_zone" -
	24	[156]	CLOSURE  	5 0	; 0x7ffb2d409610
	25	[156]	MOVE     	0 0
	26	[156]	SETTABLE 	4 -19 5	; "handler" -
	27	[157]	NEWTABLE 	5 0 5
	28	[159]	SETTABLE 	5 -8 -20	; "id" "paging_pan"
	29	[160]	SETTABLE 	5 -10 -21	; "ges" "pan"
	30	[161]	GETTABLE 	6 0 -23	; "pan_rate"
	31	[161]	SETTABLE 	5 -22 6	; "rate" -
	32	[162]	NEWTABLE 	6 0 4
	33	[163]	SETTABLE 	6 -13 -14	; "ratio_x" 0
	34	[163]	SETTABLE 	6 -15 -14	; "ratio_y" 0
	35	[163]	SETTABLE 	6 -16 -17	; "ratio_w" 1
	36	[163]	SETTABLE 	6 -18 -17	; "ratio_h" 1
	37	[164]	SETTABLE 	5 -12 6	; "screen_zone" -
	38	[165]	CLOSURE  	6 1	; 0x7ffb2d408900
	39	[165]	MOVE     	0 0
	40	[165]	SETTABLE 	5 -19 6	; "handler" -
	41	[166]	NEWTABLE 	6 0 4
	42	[168]	SETTABLE 	6 -8 -24	; "id" "paging_pan_release"
	43	[169]	SETTABLE 	6 -10 -25	; "ges" "pan_release"
	44	[170]	NEWTABLE 	7 0 4
	45	[171]	SETTABLE 	7 -13 -14	; "ratio_x" 0
	46	[171]	SETTABLE 	7 -15 -14	; "ratio_y" 0
	47	[171]	SETTABLE 	7 -16 -17	; "ratio_w" 1
	48	[171]	SETTABLE 	7 -18 -17	; "ratio_h" 1
	49	[172]	SETTABLE 	6 -12 7	; "screen_zone" -
	50	[173]	CLOSURE  	7 2	; 0x7ffb2d409df0
	51	[173]	MOVE     	0 0
	52	[173]	SETTABLE 	6 -19 7	; "handler" -
	53	[175]	SETLIST  	3 3 1	; 1
	54	[149]	CALL     	1 3 1
	55	[176]	RETURN   	0 1

function <./frontend/apps/reader/modules/readerpaging.lua:156,156> (7 instructions, 28 bytes at 0x7ffb2d409610)
1 param, 5 slots, 1 upvalue, 1 local, 1 constant, 0 functions
	1	[156]	GETUPVAL 	1 0	; self
	2	[156]	SELF     	1 1 -1	; "onSwipe"
	3	[156]	LOADNIL  	3 3
	4	[156]	MOVE     	4 0
	5	[156]	TAILCALL 	1 4 0
	6	[156]	RETURN   	1 0
	7	[156]	RETURN   	0 1

function <./frontend/apps/reader/modules/readerpaging.lua:165,165> (7 instructions, 28 bytes at 0x7ffb2d408900)
1 param, 5 slots, 1 upvalue, 1 local, 1 constant, 0 functions
	1	[165]	GETUPVAL 	1 0	; self
	2	[165]	SELF     	1 1 -1	; "onPan"
	3	[165]	LOADNIL  	3 3
	4	[165]	MOVE     	4 0
	5	[165]	TAILCALL 	1 4 0
	6	[165]	RETURN   	1 0
	7	[165]	RETURN   	0 1

function <./frontend/apps/reader/modules/readerpaging.lua:173,173> (7 instructions, 28 bytes at 0x7ffb2d409df0)
1 param, 5 slots, 1 upvalue, 1 local, 1 constant, 0 functions
	1	[173]	GETUPVAL 	1 0	; self
	2	[173]	SELF     	1 1 -1	; "onPanRelease"
	3	[173]	LOADNIL  	3 3
	4	[173]	MOVE     	4 0
	5	[173]	TAILCALL 	1 4 0
	6	[173]	RETURN   	1 0
	7	[173]	RETURN   	0 1

function <./frontend/apps/reader/modules/readerpaging.lua:178,191> (51 instructions, 204 bytes at 0x7ffb2d40a120)
2 params, 7 slots, 0 upvalues, 2 locals, 14 constants, 0 functions
	1	[179]	SELF     	2 1 -2	; "readSetting"
	2	[179]	LOADK    	4 -1	; "page_positions"
	3	[179]	CALL     	2 3 2
	4	[179]	TEST     	2 0 1
	5	[179]	JMP      	1	; to 7
	6	[179]	NEWTABLE 	2 0 0
	7	[179]	SETTABLE 	0 -1 2	; "page_positions" -
	8	[180]	SELF     	2 0 -3	; "_gotoPage"
	9	[180]	SELF     	4 1 -2	; "readSetting"
	10	[180]	LOADK    	6 -4	; "last_page"
	11	[180]	CALL     	4 3 2
	12	[180]	TEST     	4 0 1
	13	[180]	JMP      	1	; to 15
	14	[180]	LOADK    	4 -5	; 1
	15	[180]	CALL     	2 3 1
	16	[181]	SELF     	2 1 -2	; "readSetting"
	17	[181]	LOADK    	4 -6	; "show_overlap_enable"
	18	[181]	CALL     	2 3 2
	19	[181]	SETTABLE 	0 -6 2	; "show_overlap_enable" -
	20	[182]	GETTABLE 	2 0 -6	; "show_overlap_enable"
	21	[182]	EQ       	0 2 -7	; - nil
	22	[182]	JMP      	2	; to 25
	23	[183]	GETGLOBAL	2 -8	; DSHOWOVERLAP
	24	[183]	SETTABLE 	0 -6 2	; "show_overlap_enable" -
	25	[185]	SELF     	2 1 -2	; "readSetting"
	26	[185]	LOADK    	4 -9	; "flipping_zoom_mode"
	27	[185]	CALL     	2 3 2
	28	[185]	TEST     	2 0 1
	29	[185]	JMP      	1	; to 31
	30	[185]	LOADK    	2 -10	; "page"
	31	[185]	SETTABLE 	0 -9 2	; "flipping_zoom_mode" -
	32	[186]	SELF     	2 1 -2	; "readSetting"
	33	[186]	LOADK    	4 -11	; "flipping_scroll_mode"
	34	[186]	CALL     	2 3 2
	35	[186]	TEST     	2 0 1
	36	[186]	JMP      	1	; to 38
	37	[186]	LOADBOOL 	2 0 0
	38	[186]	SETTABLE 	0 -11 2	; "flipping_scroll_mode" -
	39	[187]	SELF     	2 1 -2	; "readSetting"
	40	[187]	LOADK    	4 -12	; "inverse_reading_order"
	41	[187]	CALL     	2 3 2
	42	[187]	SETTABLE 	0 -12 2	; "inverse_reading_order" -
	43	[188]	GETTABLE 	2 0 -12	; "inverse_reading_order"
	44	[188]	EQ       	0 2 -7	; - nil
	45	[188]	JMP      	5	; to 51
	46	[189]	GETGLOBAL	2 -13	; G_reader_settings
	47	[189]	SELF     	2 2 -14	; "isTrue"
	48	[189]	LOADK    	4 -12	; "inverse_reading_order"
	49	[189]	CALL     	2 3 2
	50	[189]	SETTABLE 	0 -12 2	; "inverse_reading_order" -
	51	[191]	RETURN   	0 1

function <./frontend/apps/reader/modules/readerpaging.lua:193,202> (45 instructions, 180 bytes at 0x7ffb2d40a760)
1 param, 6 slots, 0 upvalues, 1 local, 12 constants, 0 functions
	1	[195]	GETTABLE 	1 0 -1	; "ui"
	2	[195]	GETTABLE 	1 1 -2	; "doc_settings"
	3	[195]	SELF     	1 1 -3	; "saveSetting"
	4	[195]	LOADK    	3 -4	; "page_positions"
	5	[195]	GETTABLE 	4 0 -4	; "page_positions"
	6	[195]	CALL     	1 4 1
	7	[196]	GETTABLE 	1 0 -1	; "ui"
	8	[196]	GETTABLE 	1 1 -2	; "doc_settings"
	9	[196]	SELF     	1 1 -3	; "saveSetting"
	10	[196]	LOADK    	3 -5	; "last_page"
	11	[196]	SELF     	4 0 -6	; "getTopPage"
	12	[196]	CALL     	4 2 0
	13	[196]	CALL     	1 0 1
	14	[197]	GETTABLE 	1 0 -1	; "ui"
	15	[197]	GETTABLE 	1 1 -2	; "doc_settings"
	16	[197]	SELF     	1 1 -3	; "saveSetting"
	17	[197]	LOADK    	3 -7	; "percent_finished"
	18	[197]	SELF     	4 0 -8	; "getLastPercent"
	19	[197]	CALL     	4 2 0
	20	[197]	CALL     	1 0 1
	21	[198]	GETTABLE 	1 0 -1	; "ui"
	22	[198]	GETTABLE 	1 1 -2	; "doc_settings"
	23	[198]	SELF     	1 1 -3	; "saveSetting"
	24	[198]	LOADK    	3 -9	; "show_overlap_enable"
	25	[198]	GETTABLE 	4 0 -9	; "show_overlap_enable"
	26	[198]	CALL     	1 4 1
	27	[199]	GETTABLE 	1 0 -1	; "ui"
	28	[199]	GETTABLE 	1 1 -2	; "doc_settings"
	29	[199]	SELF     	1 1 -3	; "saveSetting"
	30	[199]	LOADK    	3 -10	; "flipping_zoom_mode"
	31	[199]	GETTABLE 	4 0 -10	; "flipping_zoom_mode"
	32	[199]	CALL     	1 4 1
	33	[200]	GETTABLE 	1 0 -1	; "ui"
	34	[200]	GETTABLE 	1 1 -2	; "doc_settings"
	35	[200]	SELF     	1 1 -3	; "saveSetting"
	36	[200]	LOADK    	3 -11	; "flipping_scroll_mode"
	37	[200]	GETTABLE 	4 0 -11	; "flipping_scroll_mode"
	38	[200]	CALL     	1 4 1
	39	[201]	GETTABLE 	1 0 -1	; "ui"
	40	[201]	GETTABLE 	1 1 -2	; "doc_settings"
	41	[201]	SELF     	1 1 -3	; "saveSetting"
	42	[201]	LOADK    	3 -12	; "inverse_reading_order"
	43	[201]	GETTABLE 	4 0 -12	; "inverse_reading_order"
	44	[201]	CALL     	1 4 1
	45	[202]	RETURN   	0 1

function <./frontend/apps/reader/modules/readerpaging.lua:204,206> (4 instructions, 16 bytes at 0x7ffb2d40ad30)
1 param, 3 slots, 0 upvalues, 1 local, 1 constant, 0 functions
	1	[205]	SELF     	1 0 -1	; "getTopPage"
	2	[205]	TAILCALL 	1 2 0
	3	[205]	RETURN   	1 0
	4	[206]	RETURN   	0 1

function <./frontend/apps/reader/modules/readerpaging.lua:208,212> (11 instructions, 44 bytes at 0x7ffb2d40aa40)
1 param, 3 slots, 0 upvalues, 1 local, 3 constants, 0 functions
	1	[209]	GETTABLE 	1 0 -1	; "current_page"
	2	[209]	LT       	0 -2 1	; 0 -
	3	[209]	JMP      	7	; to 11
	4	[209]	GETTABLE 	1 0 -3	; "number_of_pages"
	5	[209]	LT       	0 -2 1	; 0 -
	6	[209]	JMP      	4	; to 11
	7	[210]	GETTABLE 	1 0 -1	; "current_page"
	8	[210]	GETTABLE 	2 0 -3	; "number_of_pages"
	9	[210]	DIV      	1 1 2
	10	[210]	RETURN   	1 2
	11	[212]	RETURN   	0 1

function <./frontend/apps/reader/modules/readerpaging.lua:214,273> (59 instructions, 236 bytes at 0x7ffb2d40b520)
2 params, 12 slots, 4 upvalues, 9 locals, 17 constants, 7 functions
	1	[218]	NEWTABLE 	2 1 0
	2	[218]	NEWTABLE 	3 0 4
	3	[220]	GETUPVAL 	4 0	; _
	4	[220]	LOADK    	5 -2	; "Page overlap"
	5	[220]	CALL     	4 2 2
	6	[220]	SETTABLE 	3 -1 4	; "text" -
	7	[223]	CLOSURE  	4 0	; 0x7ffb2d40b8b0
	8	[223]	MOVE     	0 0
	9	[223]	SETTABLE 	3 -3 4	; "checked_func" -
	10	[229]	CLOSURE  	4 1	; 0x7ffb2d40bdf0
	11	[229]	MOVE     	0 0
	12	[229]	SETTABLE 	3 -4 4	; "callback" -
	13	[230]	SETTABLE 	3 -5 -6	; "separator" true
	14	[232]	SETLIST  	2 1 1	; 1
	15	[233]	CLOSURE  	3 2	; 0x7ffb2d40c200
	16	[233]	MOVE     	0 0
	17	[234]	GETGLOBAL	4 -7	; ipairs
	18	[234]	GETTABLE 	5 0 -8	; "view"
	19	[234]	SELF     	5 5 -9	; "genOverlapStyleMenu"
	20	[234]	MOVE     	7 3
	21	[234]	CALL     	5 3 0
	22	[234]	CALL     	4 0 4
	23	[234]	JMP      	5	; to 29
	24	[235]	GETGLOBAL	9 -10	; table
	25	[235]	GETTABLE 	9 9 -11	; "insert"
	26	[235]	MOVE     	10 2
	27	[235]	MOVE     	11 8
	28	[235]	CALL     	9 3 1
	29	[234]	TFORLOOP 	4 2
	30	[235]	JMP      	-7	; to 24
	31	[237]	NEWTABLE 	4 0 3
	32	[238]	GETUPVAL 	5 0	; _
	33	[238]	LOADK    	6 -2	; "Page overlap"
	34	[238]	CALL     	5 2 2
	35	[238]	SETTABLE 	4 -1 5	; "text" -
	36	[242]	CLOSURE  	5 3	; 0x7ffb2d40bb80
	37	[242]	MOVE     	0 0
	38	[242]	SETTABLE 	4 -13 5	; "enabled_func" -
	39	[243]	SETTABLE 	4 -14 2	; "sub_item_table" -
	40	[244]	SETTABLE 	1 -12 4	; "page_overlap" -
	41	[245]	NEWTABLE 	4 0 4
	42	[246]	GETUPVAL 	5 0	; _
	43	[246]	LOADK    	6 -16	; "Invert page turn taps and swipes"
	44	[246]	CALL     	5 2 2
	45	[246]	SETTABLE 	4 -1 5	; "text" -
	46	[247]	CLOSURE  	5 4	; 0x7ffb2d4090d0
	47	[247]	MOVE     	0 0
	48	[247]	SETTABLE 	4 -3 5	; "checked_func" -
	49	[250]	CLOSURE  	5 5	; 0x7ffb2d40b2d0
	50	[250]	MOVE     	0 0
	51	[250]	GETUPVAL 	0 1	; Event
	52	[250]	SETTABLE 	4 -4 5	; "callback" -
	53	[271]	CLOSURE  	5 6	; 0x7ffb2d40b350
	54	[271]	GETUPVAL 	0 2	; UIManager
	55	[271]	GETUPVAL 	0 3	; MultiConfirmBox
	56	[271]	GETUPVAL 	0 0	; _
	57	[271]	SETTABLE 	4 -17 5	; "hold_callback" -
	58	[272]	SETTABLE 	1 -15 4	; "invert_page_turn_gestures" -
	59	[273]	RETURN   	0 1

function <./frontend/apps/reader/modules/readerpaging.lua:221,223> (4 instructions, 16 bytes at 0x7ffb2d40b8b0)
0 params, 2 slots, 1 upvalue, 0 locals, 1 constant, 0 functions
	1	[222]	GETUPVAL 	0 0	; self
	2	[222]	GETTABLE 	0 0 -1	; "show_overlap_enable"
	3	[222]	RETURN   	0 2
	4	[223]	RETURN   	0 1

function <./frontend/apps/reader/modules/readerpaging.lua:224,229> (14 instructions, 56 bytes at 0x7ffb2d40bdf0)
0 params, 2 slots, 1 upvalue, 0 locals, 3 constants, 0 functions
	1	[225]	GETUPVAL 	0 0	; self
	2	[225]	GETUPVAL 	1 0	; self
	3	[225]	GETTABLE 	1 1 -1	; "show_overlap_enable"
	4	[225]	NOT      	1 1
	5	[225]	SETTABLE 	0 -1 1	; "show_overlap_enable" -
	6	[226]	GETUPVAL 	0 0	; self
	7	[226]	GETTABLE 	0 0 -1	; "show_overlap_enable"
	8	[226]	TEST     	0 0 1
	9	[226]	JMP      	4	; to 14
	10	[227]	GETUPVAL 	0 0	; self
	11	[227]	GETTABLE 	0 0 -2	; "view"
	12	[227]	SELF     	0 0 -3	; "resetDimArea"
	13	[227]	CALL     	0 2 1
	14	[229]	RETURN   	0 1

function <./frontend/apps/reader/modules/readerpaging.lua:233,233> (4 instructions, 16 bytes at 0x7ffb2d40c200)
0 params, 2 slots, 1 upvalue, 0 locals, 1 constant, 0 functions
	1	[233]	GETUPVAL 	0 0	; self
	2	[233]	GETTABLE 	0 0 -1	; "show_overlap_enable"
	3	[233]	RETURN   	0 2
	4	[233]	RETURN   	0 1

function <./frontend/apps/reader/modules/readerpaging.lua:239,242> (20 instructions, 80 bytes at 0x7ffb2d40bb80)
0 params, 3 slots, 1 upvalue, 0 locals, 6 constants, 0 functions
	1	[240]	GETUPVAL 	0 0	; self
	2	[240]	GETTABLE 	0 0 -1	; "view"
	3	[240]	GETTABLE 	0 0 -2	; "page_scroll"
	4	[240]	TEST     	0 0 1
	5	[240]	JMP      	11	; to 17
	6	[240]	GETUPVAL 	0 0	; self
	7	[240]	GETTABLE 	0 0 -3	; "zoom_mode"
	8	[240]	EQ       	1 0 -4	; - "page"
	9	[240]	JMP      	7	; to 17
	10	[241]	GETUPVAL 	0 0	; self
	11	[241]	GETTABLE 	0 0 -3	; "zoom_mode"
	12	[241]	SELF     	0 0 -5	; "find"
	13	[241]	LOADK    	2 -6	; "height"
	14	[241]	CALL     	0 3 2
	15	[241]	NOT      	0 0
	16	[241]	JMP      	2	; to 19
	17	[241]	LOADBOOL 	0 0 1
	18	[241]	LOADBOOL 	0 1 0
	19	[241]	RETURN   	0 2
	20	[242]	RETURN   	0 1

function <./frontend/apps/reader/modules/readerpaging.lua:247,247> (4 instructions, 16 bytes at 0x7ffb2d4090d0)
0 params, 2 slots, 1 upvalue, 0 locals, 1 constant, 0 functions
	1	[247]	GETUPVAL 	0 0	; self
	2	[247]	GETTABLE 	0 0 -1	; "inverse_reading_order"
	3	[247]	RETURN   	0 2
	4	[247]	RETURN   	0 1

function <./frontend/apps/reader/modules/readerpaging.lua:248,250> (9 instructions, 36 bytes at 0x7ffb2d40b2d0)
0 params, 5 slots, 2 upvalues, 0 locals, 4 constants, 0 functions
	1	[249]	GETUPVAL 	0 0	; self
	2	[249]	GETTABLE 	0 0 -1	; "ui"
	3	[249]	SELF     	0 0 -2	; "handleEvent"
	4	[249]	GETUPVAL 	2 1	; Event
	5	[249]	SELF     	2 2 -3	; "new"
	6	[249]	LOADK    	4 -4	; "ToggleReadingOrder"
	7	[249]	CALL     	2 3 0
	8	[249]	CALL     	0 0 1
	9	[250]	RETURN   	0 1

function <./frontend/apps/reader/modules/readerpaging.lua:251,271> (37 instructions, 148 bytes at 0x7ffb2d40b350)
1 param, 9 slots, 3 upvalues, 2 locals, 12 constants, 4 functions
	1	[252]	GETGLOBAL	1 -1	; G_reader_settings
	2	[252]	SELF     	1 1 -2	; "isTrue"
	3	[252]	LOADK    	3 -3	; "inverse_reading_order"
	4	[252]	CALL     	1 3 2
	5	[253]	GETUPVAL 	2 0	; UIManager
	6	[253]	SELF     	2 2 -4	; "show"
	7	[253]	GETUPVAL 	4 1	; MultiConfirmBox
	8	[253]	SELF     	4 4 -5	; "new"
	9	[253]	NEWTABLE 	6 0 5
	10	[254]	TEST     	1 0 0
	11	[254]	JMP      	5	; to 17
	12	[254]	GETUPVAL 	7 2	; _
	13	[254]	LOADK    	8 -7	; "The default (\226\152\133) for newly opened books is right-to-left (RTL) page turning.\n\nWould you like to change it?"
	14	[254]	CALL     	7 2 2
	15	[255]	TEST     	7 0 1
	16	[255]	JMP      	3	; to 20
	17	[255]	GETUPVAL 	7 2	; _
	18	[255]	LOADK    	8 -8	; "The default (\226\152\133) for newly opened books is left-to-right (LTR) page turning.\n\nWould you like to change it?"
	19	[255]	CALL     	7 2 2
	20	[255]	SETTABLE 	6 -6 7	; "text" -
	21	[258]	CLOSURE  	7 0	; 0x7ffb2d409b40
	22	[258]	MOVE     	0 1
	23	[258]	GETUPVAL 	0 2	; _
	24	[258]	SETTABLE 	6 -9 7	; "choice1_text_func" -
	25	[262]	CLOSURE  	7 1	; 0x7ffb2d40c110
	26	[262]	MOVE     	0 0
	27	[262]	SETTABLE 	6 -10 7	; "choice1_callback" -
	28	[265]	CLOSURE  	7 2	; 0x7ffb2d40cbc0
	29	[265]	MOVE     	0 1
	30	[265]	GETUPVAL 	0 2	; _
	31	[265]	SETTABLE 	6 -11 7	; "choice2_text_func" -
	32	[269]	CLOSURE  	7 3	; 0x7ffb2d40d1e0
	33	[269]	MOVE     	0 0
	34	[269]	SETTABLE 	6 -12 7	; "choice2_callback" -
	35	[253]	CALL     	4 3 0
	36	[253]	CALL     	2 0 1
	37	[271]	RETURN   	0 1

function <./frontend/apps/reader/modules/readerpaging.lua:256,258> (13 instructions, 52 bytes at 0x7ffb2d409b40)
0 params, 2 slots, 2 upvalues, 0 locals, 2 constants, 0 functions
	1	[257]	GETUPVAL 	0 0	; inverse_reading_order
	2	[257]	TEST     	0 0 0
	3	[257]	JMP      	5	; to 9
	4	[257]	GETUPVAL 	0 1	; _
	5	[257]	LOADK    	1 -1	; "LTR"
	6	[257]	CALL     	0 2 2
	7	[257]	TEST     	0 0 1
	8	[257]	JMP      	3	; to 12
	9	[257]	GETUPVAL 	0 1	; _
	10	[257]	LOADK    	1 -2	; "LTR (\226\152\133)"
	11	[257]	CALL     	0 2 2
	12	[257]	RETURN   	0 2
	13	[258]	RETURN   	0 1

function <./frontend/apps/reader/modules/readerpaging.lua:259,262> (12 instructions, 48 bytes at 0x7ffb2d40c110)
0 params, 4 slots, 1 upvalue, 0 locals, 4 constants, 0 functions
	1	[260]	GETGLOBAL	0 -1	; G_reader_settings
	2	[260]	SELF     	0 0 -2	; "saveSetting"
	3	[260]	LOADK    	2 -3	; "inverse_reading_order"
	4	[260]	LOADBOOL 	3 0 0
	5	[260]	CALL     	0 4 1
	6	[261]	GETUPVAL 	0 0	; touchmenu_instance
	7	[261]	TEST     	0 0 0
	8	[261]	JMP      	3	; to 12
	9	[261]	GETUPVAL 	0 0	; touchmenu_instance
	10	[261]	SELF     	0 0 -4	; "updateItems"
	11	[261]	CALL     	0 2 1
	12	[262]	RETURN   	0 1

function <./frontend/apps/reader/modules/readerpaging.lua:263,265> (13 instructions, 52 bytes at 0x7ffb2d40cbc0)
0 params, 2 slots, 2 upvalues, 0 locals, 2 constants, 0 functions
	1	[264]	GETUPVAL 	0 0	; inverse_reading_order
	2	[264]	TEST     	0 0 0
	3	[264]	JMP      	5	; to 9
	4	[264]	GETUPVAL 	0 1	; _
	5	[264]	LOADK    	1 -1	; "RTL (\226\152\133)"
	6	[264]	CALL     	0 2 2
	7	[264]	TEST     	0 0 1
	8	[264]	JMP      	3	; to 12
	9	[264]	GETUPVAL 	0 1	; _
	10	[264]	LOADK    	1 -2	; "RTL"
	11	[264]	CALL     	0 2 2
	12	[264]	RETURN   	0 2
	13	[265]	RETURN   	0 1

function <./frontend/apps/reader/modules/readerpaging.lua:266,269> (12 instructions, 48 bytes at 0x7ffb2d40d1e0)
0 params, 4 slots, 1 upvalue, 0 locals, 4 constants, 0 functions
	1	[267]	GETGLOBAL	0 -1	; G_reader_settings
	2	[267]	SELF     	0 0 -2	; "saveSetting"
	3	[267]	LOADK    	2 -3	; "inverse_reading_order"
	4	[267]	LOADBOOL 	3 1 0
	5	[267]	CALL     	0 4 1
	6	[268]	GETUPVAL 	0 0	; touchmenu_instance
	7	[268]	TEST     	0 0 0
	8	[268]	JMP      	3	; to 12
	9	[268]	GETUPVAL 	0 0	; touchmenu_instance
	10	[268]	SELF     	0 0 -4	; "updateItems"
	11	[268]	CALL     	0 2 1
	12	[269]	RETURN   	0 1

function <./frontend/apps/reader/modules/readerpaging.lua:275,278> (11 instructions, 44 bytes at 0x7ffb2d40a1f0)
1 param, 5 slots, 1 upvalue, 1 local, 7 constants, 0 functions
	1	[276]	GETTABLE 	1 0 -1	; "ui"
	2	[276]	GETTABLE 	1 1 -2	; "document"
	3	[276]	SELF     	1 1 -3	; "updateColorRendering"
	4	[276]	CALL     	1 2 1
	5	[277]	GETUPVAL 	1 0	; UIManager
	6	[277]	SELF     	1 1 -4	; "setDirty"
	7	[277]	GETTABLE 	3 0 -5	; "view"
	8	[277]	GETTABLE 	3 3 -6	; "dialog"
	9	[277]	LOADK    	4 -7	; "partial"
	10	[277]	CALL     	1 4 1
	11	[278]	RETURN   	0 1

function <./frontend/apps/reader/modules/readerpaging.lua:287,290> (8 instructions, 32 bytes at 0x7ffb2d40d980)
3 params, 6 slots, 1 upvalue, 3 locals, 3 constants, 0 functions
	1	[288]	GETUPVAL 	3 0	; logger
	2	[288]	GETTABLE 	3 3 -1	; "dbg"
	3	[288]	LOADK    	4 -2	; "set page position"
	4	[288]	MOVE     	5 2
	5	[288]	CALL     	3 3 1
	6	[289]	GETTABLE 	3 0 -3	; "page_positions"
	7	[289]	SETTABLE 	3 1 2
	8	[290]	RETURN   	0 1

function <./frontend/apps/reader/modules/readerpaging.lua:295,302> (18 instructions, 72 bytes at 0x7ffb2d40de00)
2 params, 5 slots, 1 upvalue, 2 locals, 6 constants, 0 functions
	1	[299]	GETGLOBAL	2 -1	; math
	2	[299]	GETTABLE 	2 2 -2	; "floor"
	3	[299]	MOVE     	3 1
	4	[299]	CALL     	2 2 2
	5	[299]	MOVE     	1 2
	6	[300]	GETUPVAL 	2 0	; logger
	7	[300]	GETTABLE 	2 2 -3	; "dbg"
	8	[300]	LOADK    	3 -4	; "get page position"
	9	[300]	GETTABLE 	4 0 -5	; "page_positions"
	10	[300]	GETTABLE 	4 4 1
	11	[300]	CALL     	2 3 1
	12	[301]	GETTABLE 	2 0 -5	; "page_positions"
	13	[301]	GETTABLE 	2 2 1
	14	[301]	TEST     	2 0 1
	15	[301]	JMP      	1	; to 17
	16	[301]	LOADK    	2 -6	; 0
	17	[301]	RETURN   	2 2
	18	[302]	RETURN   	0 1

function <./frontend/apps/reader/modules/readerpaging.lua:304,323> (51 instructions, 204 bytes at 0x7ffb2d40e3d0)
1 param, 7 slots, 2 upvalues, 1 local, 17 constants, 0 functions
	1	[305]	GETTABLE 	1 0 -1	; "bookmark_flipping_mode"
	2	[305]	TEST     	1 0 0
	3	[305]	JMP      	1	; to 5
	4	[307]	RETURN   	0 1
	5	[309]	GETTABLE 	1 0 -2	; "view"
	6	[309]	GETTABLE 	2 0 -2	; "view"
	7	[309]	GETTABLE 	2 2 -3	; "flipping_visible"
	8	[309]	NOT      	2 2
	9	[309]	SETTABLE 	1 -3 2	; "flipping_visible" -
	10	[310]	GETTABLE 	1 0 -2	; "view"
	11	[310]	GETTABLE 	1 1 -3	; "flipping_visible"
	12	[310]	SETTABLE 	0 -4 1	; "page_flipping_mode" -
	13	[311]	GETTABLE 	1 0 -6	; "current_page"
	14	[311]	SETTABLE 	0 -5 1	; "flipping_page" -
	15	[313]	GETTABLE 	1 0 -4	; "page_flipping_mode"
	16	[313]	TEST     	1 0 0
	17	[313]	JMP      	6	; to 24
	18	[314]	SELF     	1 0 -7	; "updateOriginalPage"
	19	[314]	GETTABLE 	3 0 -6	; "current_page"
	20	[314]	CALL     	1 3 1
	21	[315]	SELF     	1 0 -8	; "enterFlippingMode"
	22	[315]	CALL     	1 2 1
	23	[315]	JMP      	5	; to 29
	24	[317]	SELF     	1 0 -7	; "updateOriginalPage"
	25	[317]	LOADNIL  	3 3
	26	[317]	CALL     	1 3 1
	27	[318]	SELF     	1 0 -9	; "exitFlippingMode"
	28	[318]	CALL     	1 2 1
	29	[320]	GETTABLE 	1 0 -10	; "ui"
	30	[320]	SELF     	1 1 -11	; "handleEvent"
	31	[320]	GETUPVAL 	3 0	; Event
	32	[320]	SELF     	3 3 -12	; "new"
	33	[320]	LOADK    	5 -13	; "SetHinting"
	34	[320]	GETTABLE 	6 0 -4	; "page_flipping_mode"
	35	[320]	NOT      	6 6
	36	[320]	CALL     	3 4 0
	37	[320]	CALL     	1 0 1
	38	[321]	GETTABLE 	1 0 -10	; "ui"
	39	[321]	SELF     	1 1 -11	; "handleEvent"
	40	[321]	GETUPVAL 	3 0	; Event
	41	[321]	SELF     	3 3 -12	; "new"
	42	[321]	LOADK    	5 -14	; "ReZoom"
	43	[321]	CALL     	3 3 0
	44	[321]	CALL     	1 0 1
	45	[322]	GETUPVAL 	1 1	; UIManager
	46	[322]	SELF     	1 1 -15	; "setDirty"
	47	[322]	GETTABLE 	3 0 -2	; "view"
	48	[322]	GETTABLE 	3 3 -16	; "dialog"
	49	[322]	LOADK    	4 -17	; "partial"
	50	[322]	CALL     	1 4 1
	51	[323]	RETURN   	0 1

function <./frontend/apps/reader/modules/readerpaging.lua:325,345> (55 instructions, 220 bytes at 0x7ffb2d40e940)
1 param, 7 slots, 2 upvalues, 1 local, 20 constants, 0 functions
	1	[326]	GETTABLE 	1 0 -1	; "bookmark_flipping_mode"
	2	[326]	NOT      	1 1
	3	[326]	SETTABLE 	0 -1 1	; "bookmark_flipping_mode" -
	4	[328]	GETTABLE 	1 0 -1	; "bookmark_flipping_mode"
	5	[328]	TEST     	1 0 0
	6	[328]	JMP      	15	; to 22
	7	[329]	GETTABLE 	1 0 -3	; "view"
	8	[329]	GETTABLE 	1 1 -4	; "flipping_visible"
	9	[329]	SETTABLE 	0 -2 1	; "orig_flipping_mode" -
	10	[330]	GETTABLE 	1 0 -3	; "view"
	11	[330]	GETTABLE 	1 1 -6	; "dogear_visible"
	12	[330]	SETTABLE 	0 -5 1	; "orig_dogear_mode" -
	13	[332]	GETTABLE 	1 0 -3	; "view"
	14	[332]	SETTABLE 	1 -4 -7	; "flipping_visible" true
	15	[333]	GETTABLE 	1 0 -3	; "view"
	16	[333]	SETTABLE 	1 -6 -7	; "dogear_visible" true
	17	[334]	GETTABLE 	1 0 -9	; "current_page"
	18	[334]	SETTABLE 	0 -8 1	; "bm_flipping_orig_page" -
	19	[335]	SELF     	1 0 -10	; "enterFlippingMode"
	20	[335]	CALL     	1 2 1
	21	[335]	JMP      	11	; to 33
	22	[337]	GETTABLE 	1 0 -3	; "view"
	23	[337]	GETTABLE 	2 0 -2	; "orig_flipping_mode"
	24	[337]	SETTABLE 	1 -4 2	; "flipping_visible" -
	25	[338]	GETTABLE 	1 0 -3	; "view"
	26	[338]	GETTABLE 	2 0 -5	; "orig_dogear_mode"
	27	[338]	SETTABLE 	1 -6 2	; "dogear_visible" -
	28	[339]	SELF     	1 0 -11	; "exitFlippingMode"
	29	[339]	CALL     	1 2 1
	30	[340]	SELF     	1 0 -12	; "_gotoPage"
	31	[340]	GETTABLE 	3 0 -8	; "bm_flipping_orig_page"
	32	[340]	CALL     	1 3 1
	33	[342]	GETTABLE 	1 0 -13	; "ui"
	34	[342]	SELF     	1 1 -14	; "handleEvent"
	35	[342]	GETUPVAL 	3 0	; Event
	36	[342]	SELF     	3 3 -15	; "new"
	37	[342]	LOADK    	5 -16	; "SetHinting"
	38	[342]	GETTABLE 	6 0 -1	; "bookmark_flipping_mode"
	39	[342]	NOT      	6 6
	40	[342]	CALL     	3 4 0
	41	[342]	CALL     	1 0 1
	42	[343]	GETTABLE 	1 0 -13	; "ui"
	43	[343]	SELF     	1 1 -14	; "handleEvent"
	44	[343]	GETUPVAL 	3 0	; Event
	45	[343]	SELF     	3 3 -15	; "new"
	46	[343]	LOADK    	5 -17	; "ReZoom"
	47	[343]	CALL     	3 3 0
	48	[343]	CALL     	1 0 1
	49	[344]	GETUPVAL 	1 1	; UIManager
	50	[344]	SELF     	1 1 -18	; "setDirty"
	51	[344]	GETTABLE 	3 0 -3	; "view"
	52	[344]	GETTABLE 	3 3 -19	; "dialog"
	53	[344]	LOADK    	4 -20	; "partial"
	54	[344]	CALL     	1 4 1
	55	[345]	RETURN   	0 1

function <./frontend/apps/reader/modules/readerpaging.lua:347,356> (34 instructions, 136 bytes at 0x7ffb2d40e8b0)
1 param, 7 slots, 3 upvalues, 1 local, 20 constants, 0 functions
	1	[348]	GETTABLE 	1 0 -2	; "view"
	2	[348]	GETTABLE 	1 1 -3	; "document"
	3	[348]	GETTABLE 	1 1 -4	; "configurable"
	4	[348]	GETTABLE 	1 1 -5	; "text_wrap"
	5	[348]	SETTABLE 	0 -1 1	; "orig_reflow_mode" -
	6	[349]	GETTABLE 	1 0 -2	; "view"
	7	[349]	GETTABLE 	1 1 -7	; "page_scroll"
	8	[349]	SETTABLE 	0 -6 1	; "orig_scroll_mode" -
	9	[350]	GETTABLE 	1 0 -2	; "view"
	10	[350]	GETTABLE 	1 1 -9	; "zoom_mode"
	11	[350]	SETTABLE 	0 -8 1	; "orig_zoom_mode" -
	12	[351]	GETUPVAL 	1 0	; logger
	13	[351]	GETTABLE 	1 1 -10	; "dbg"
	14	[351]	LOADK    	2 -11	; "store zoom mode"
	15	[351]	GETTABLE 	3 0 -8	; "orig_zoom_mode"
	16	[351]	CALL     	1 3 1
	17	[352]	GETTABLE 	1 0 -2	; "view"
	18	[352]	GETTABLE 	1 1 -3	; "document"
	19	[352]	GETTABLE 	1 1 -4	; "configurable"
	20	[352]	SETTABLE 	1 -5 -12	; "text_wrap" 0
	21	[353]	GETTABLE 	1 0 -2	; "view"
	22	[353]	GETTABLE 	2 0 -13	; "flipping_scroll_mode"
	23	[353]	SETTABLE 	1 -7 2	; "page_scroll" -
	24	[354]	GETUPVAL 	1 1	; Input
	25	[354]	SETTABLE 	1 -14 -15	; "disable_double_tap" false
	26	[355]	GETTABLE 	1 0 -16	; "ui"
	27	[355]	SELF     	1 1 -17	; "handleEvent"
	28	[355]	GETUPVAL 	3 2	; Event
	29	[355]	SELF     	3 3 -18	; "new"
	30	[355]	LOADK    	5 -19	; "EnterFlippingMode"
	31	[355]	GETTABLE 	6 0 -20	; "flipping_zoom_mode"
	32	[355]	CALL     	3 4 0
	33	[355]	CALL     	1 0 1
	34	[356]	RETURN   	0 1

function <./frontend/apps/reader/modules/readerpaging.lua:358,366> (30 instructions, 120 bytes at 0x7ffb2d40f270)
1 param, 7 slots, 3 upvalues, 1 local, 19 constants, 0 functions
	1	[359]	GETTABLE 	1 0 -1	; "view"
	2	[359]	GETTABLE 	1 1 -2	; "document"
	3	[359]	GETTABLE 	1 1 -3	; "configurable"
	4	[359]	GETTABLE 	2 0 -5	; "orig_reflow_mode"
	5	[359]	SETTABLE 	1 -4 2	; "text_wrap" -
	6	[360]	GETTABLE 	1 0 -1	; "view"
	7	[360]	GETTABLE 	2 0 -7	; "orig_scroll_mode"
	8	[360]	SETTABLE 	1 -6 2	; "page_scroll" -
	9	[361]	GETUPVAL 	1 0	; Input
	10	[361]	SETTABLE 	1 -8 -9	; "disable_double_tap" true
	11	[362]	GETTABLE 	1 0 -1	; "view"
	12	[362]	GETTABLE 	1 1 -11	; "zoom_mode"
	13	[362]	SETTABLE 	0 -10 1	; "flipping_zoom_mode" -
	14	[363]	GETTABLE 	1 0 -1	; "view"
	15	[363]	GETTABLE 	1 1 -6	; "page_scroll"
	16	[363]	SETTABLE 	0 -12 1	; "flipping_scroll_mode" -
	17	[364]	GETUPVAL 	1 1	; logger
	18	[364]	GETTABLE 	1 1 -13	; "dbg"
	19	[364]	LOADK    	2 -14	; "restore zoom mode"
	20	[364]	GETTABLE 	3 0 -15	; "orig_zoom_mode"
	21	[364]	CALL     	1 3 1
	22	[365]	GETTABLE 	1 0 -16	; "ui"
	23	[365]	SELF     	1 1 -17	; "handleEvent"
	24	[365]	GETUPVAL 	3 2	; Event
	25	[365]	SELF     	3 3 -18	; "new"
	26	[365]	LOADK    	5 -19	; "ExitFlippingMode"
	27	[365]	GETTABLE 	6 0 -15	; "orig_zoom_mode"
	28	[365]	CALL     	3 4 0
	29	[365]	CALL     	1 0 1
	30	[366]	RETURN   	0 1

function <./frontend/apps/reader/modules/readerpaging.lua:368,370> (2 instructions, 8 bytes at 0x7ffb2d40b4a0)
2 params, 2 slots, 0 upvalues, 2 locals, 1 constant, 0 functions
	1	[369]	SETTABLE 	0 -1 1	; "original_page" -
	2	[370]	RETURN   	0 1

function <./frontend/apps/reader/modules/readerpaging.lua:372,374> (2 instructions, 8 bytes at 0x7ffb2d4101a0)
2 params, 2 slots, 0 upvalues, 2 locals, 1 constant, 0 functions
	1	[373]	SETTABLE 	0 -1 1	; "flipping_page" -
	2	[374]	RETURN   	0 1

function <./frontend/apps/reader/modules/readerpaging.lua:376,392> (67 instructions, 268 bytes at 0x7ffb2d410220)
3 params, 13 slots, 3 upvalues, 8 locals, 19 constants, 0 functions
	1	[377]	GETTABLE 	3 0 -1	; "number_of_pages"
	2	[378]	GETTABLE 	4 0 -2	; "flip_steps"
	3	[378]	LEN      	4 4
	4	[379]	GETTABLE 	5 2 -3	; "distance"
	5	[379]	GETUPVAL 	6 0	; Screen
	6	[379]	SELF     	6 6 -4	; "getWidth"
	7	[379]	CALL     	6 2 2
	8	[379]	DIV      	5 5 6
	9	[380]	GETTABLE 	6 2 -3	; "distance"
	10	[380]	GETUPVAL 	7 0	; Screen
	11	[380]	SELF     	7 7 -5	; "getHeight"
	12	[380]	CALL     	7 2 2
	13	[380]	DIV      	6 6 7
	14	[381]	GETUPVAL 	7 1	; BD
	15	[381]	GETTABLE 	7 7 -6	; "flipDirectionIfMirroredUILayout"
	16	[381]	GETTABLE 	8 2 -7	; "direction"
	17	[381]	CALL     	7 2 2
	18	[382]	EQ       	0 7 -8	; - "east"
	19	[382]	JMP      	10	; to 30
	20	[383]	SELF     	8 0 -9	; "_gotoPage"
	21	[383]	GETTABLE 	10 0 -2	; "flip_steps"
	22	[383]	GETGLOBAL	11 -10	; math
	23	[383]	GETTABLE 	11 11 -11	; "ceil"
	24	[383]	MUL      	12 4 5
	25	[383]	CALL     	11 2 2
	26	[383]	GETTABLE 	10 10 11
	27	[383]	SUB      	10 1 10
	28	[383]	CALL     	8 3 1
	29	[383]	JMP      	31	; to 61
	30	[384]	EQ       	0 7 -12	; - "west"
	31	[384]	JMP      	10	; to 42
	32	[385]	SELF     	8 0 -9	; "_gotoPage"
	33	[385]	GETTABLE 	10 0 -2	; "flip_steps"
	34	[385]	GETGLOBAL	11 -10	; math
	35	[385]	GETTABLE 	11 11 -11	; "ceil"
	36	[385]	MUL      	12 4 5
	37	[385]	CALL     	11 2 2
	38	[385]	GETTABLE 	10 10 11
	39	[385]	ADD      	10 1 10
	40	[385]	CALL     	8 3 1
	41	[385]	JMP      	19	; to 61
	42	[386]	EQ       	0 7 -13	; - "south"
	43	[386]	JMP      	8	; to 52
	44	[387]	SELF     	8 0 -9	; "_gotoPage"
	45	[387]	GETGLOBAL	10 -10	; math
	46	[387]	GETTABLE 	10 10 -14	; "floor"
	47	[387]	MUL      	11 3 6
	48	[387]	CALL     	10 2 2
	49	[387]	SUB      	10 1 10
	50	[387]	CALL     	8 3 1
	51	[387]	JMP      	9	; to 61
	52	[388]	EQ       	0 7 -15	; - "north"
	53	[388]	JMP      	7	; to 61
	54	[389]	SELF     	8 0 -9	; "_gotoPage"
	55	[389]	GETGLOBAL	10 -10	; math
	56	[389]	GETTABLE 	10 10 -14	; "floor"
	57	[389]	MUL      	11 3 6
	58	[389]	CALL     	10 2 2
	59	[389]	ADD      	10 1 10
	60	[389]	CALL     	8 3 1
	61	[391]	GETUPVAL 	8 2	; UIManager
	62	[391]	SELF     	8 8 -16	; "setDirty"
	63	[391]	GETTABLE 	10 0 -17	; "view"
	64	[391]	GETTABLE 	10 10 -18	; "dialog"
	65	[391]	LOADK    	11 -19	; "partial"
	66	[391]	CALL     	8 4 1
	67	[392]	RETURN   	0 1

function <./frontend/apps/reader/modules/readerpaging.lua:394,402> (32 instructions, 128 bytes at 0x7ffb2d4107d0)
3 params, 10 slots, 3 upvalues, 4 locals, 13 constants, 0 functions
	1	[395]	GETUPVAL 	3 0	; BD
	2	[395]	GETTABLE 	3 3 -1	; "flipDirectionIfMirroredUILayout"
	3	[395]	GETTABLE 	4 2 -2	; "direction"
	4	[395]	CALL     	3 2 2
	5	[396]	EQ       	0 3 -3	; - "east"
	6	[396]	JMP      	9	; to 16
	7	[397]	GETTABLE 	4 0 -4	; "ui"
	8	[397]	SELF     	4 4 -5	; "handleEvent"
	9	[397]	GETUPVAL 	6 1	; Event
	10	[397]	SELF     	6 6 -6	; "new"
	11	[397]	LOADK    	8 -7	; "GotoPreviousBookmark"
	12	[397]	MOVE     	9 1
	13	[397]	CALL     	6 4 0
	14	[397]	CALL     	4 0 1
	15	[397]	JMP      	10	; to 26
	16	[398]	EQ       	0 3 -8	; - "west"
	17	[398]	JMP      	8	; to 26
	18	[399]	GETTABLE 	4 0 -4	; "ui"
	19	[399]	SELF     	4 4 -5	; "handleEvent"
	20	[399]	GETUPVAL 	6 1	; Event
	21	[399]	SELF     	6 6 -6	; "new"
	22	[399]	LOADK    	8 -9	; "GotoNextBookmark"
	23	[399]	MOVE     	9 1
	24	[399]	CALL     	6 4 0
	25	[399]	CALL     	4 0 1
	26	[401]	GETUPVAL 	4 2	; UIManager
	27	[401]	SELF     	4 4 -10	; "setDirty"
	28	[401]	GETTABLE 	6 0 -11	; "view"
	29	[401]	GETTABLE 	6 6 -12	; "dialog"
	30	[401]	LOADK    	7 -13	; "partial"
	31	[401]	CALL     	4 4 1
	32	[402]	RETURN   	0 1

function <./frontend/apps/reader/modules/readerpaging.lua:404,428> (58 instructions, 232 bytes at 0x7ffb2d410a90)
3 params, 8 slots, 2 upvalues, 4 locals, 19 constants, 0 functions
	1	[405]	GETUPVAL 	3 0	; BD
	2	[405]	GETTABLE 	3 3 -1	; "flipDirectionIfMirroredUILayout"
	3	[405]	GETTABLE 	4 2 -2	; "direction"
	4	[405]	CALL     	3 2 2
	5	[406]	GETTABLE 	4 0 -3	; "bookmark_flipping_mode"
	6	[406]	TEST     	4 0 0
	7	[406]	JMP      	5	; to 13
	8	[407]	SELF     	4 0 -4	; "bookmarkFlipping"
	9	[407]	GETTABLE 	6 0 -5	; "current_page"
	10	[407]	MOVE     	7 2
	11	[407]	CALL     	4 4 1
	12	[407]	JMP      	45	; to 58
	13	[408]	GETTABLE 	4 0 -6	; "page_flipping_mode"
	14	[408]	TEST     	4 0 0
	15	[408]	JMP      	7	; to 23
	16	[408]	GETTABLE 	4 0 -7	; "original_page"
	17	[408]	TEST     	4 0 0
	18	[408]	JMP      	4	; to 23
	19	[409]	SELF     	4 0 -8	; "_gotoPage"
	20	[409]	GETTABLE 	6 0 -7	; "original_page"
	21	[409]	CALL     	4 3 1
	22	[409]	JMP      	35	; to 58
	23	[410]	EQ       	0 3 -9	; - "west"
	24	[410]	JMP      	11	; to 36
	25	[411]	GETTABLE 	4 0 -10	; "inverse_reading_order"
	26	[411]	TEST     	4 0 0
	27	[411]	JMP      	4	; to 32
	28	[412]	SELF     	4 0 -11	; "onGotoViewRel"
	29	[412]	LOADK    	6 -12	; -1
	30	[412]	CALL     	4 3 1
	31	[412]	JMP      	26	; to 58
	32	[414]	SELF     	4 0 -11	; "onGotoViewRel"
	33	[414]	LOADK    	6 -13	; 1
	34	[414]	CALL     	4 3 1
	35	[415]	JMP      	22	; to 58
	36	[416]	EQ       	0 3 -14	; - "east"
	37	[416]	JMP      	11	; to 49
	38	[417]	GETTABLE 	4 0 -10	; "inverse_reading_order"
	39	[417]	TEST     	4 0 0
	40	[417]	JMP      	4	; to 45
	41	[418]	SELF     	4 0 -11	; "onGotoViewRel"
	42	[418]	LOADK    	6 -13	; 1
	43	[418]	CALL     	4 3 1
	44	[418]	JMP      	13	; to 58
	45	[420]	SELF     	4 0 -11	; "onGotoViewRel"
	46	[420]	LOADK    	6 -12	; -1
	47	[420]	CALL     	4 3 1
	48	[421]	JMP      	9	; to 58
	49	[424]	GETTABLE 	4 0 -15	; "view"
	50	[424]	GETTABLE 	4 4 -16	; "footer"
	51	[424]	SELF     	4 4 -17	; "updateFooter"
	52	[424]	CALL     	4 2 1
	53	[426]	GETUPVAL 	4 1	; UIManager
	54	[426]	SELF     	4 4 -18	; "setDirty"
	55	[426]	LOADNIL  	6 6
	56	[426]	LOADK    	7 -19	; "full"
	57	[426]	CALL     	4 4 1
	58	[428]	RETURN   	0 1

function <./frontend/apps/reader/modules/readerpaging.lua:430,453> (69 instructions, 276 bytes at 0x7ffb2d411350)
3 params, 8 slots, 0 upvalues, 4 locals, 24 constants, 0 functions
	1	[431]	GETTABLE 	3 0 -1	; "bookmark_flipping_mode"
	2	[431]	TEST     	3 0 0
	3	[431]	JMP      	3	; to 7
	4	[432]	LOADBOOL 	3 1 0
	5	[432]	RETURN   	3 2
	6	[432]	JMP      	60	; to 67
	7	[433]	GETTABLE 	3 0 -2	; "page_flipping_mode"
	8	[433]	TEST     	3 0 0
	9	[433]	JMP      	19	; to 29
	10	[434]	GETTABLE 	3 0 -3	; "view"
	11	[434]	GETTABLE 	3 3 -4	; "zoom_mode"
	12	[434]	EQ       	0 3 -5	; - "page"
	13	[434]	JMP      	5	; to 19
	14	[435]	SELF     	3 0 -6	; "pageFlipping"
	15	[435]	GETTABLE 	5 0 -7	; "flipping_page"
	16	[435]	MOVE     	6 2
	17	[435]	CALL     	3 4 1
	18	[435]	JMP      	48	; to 67
	19	[437]	GETTABLE 	3 0 -3	; "view"
	20	[437]	SELF     	3 3 -8	; "PanningStart"
	21	[437]	GETTABLE 	5 2 -9	; "relative"
	22	[437]	GETTABLE 	5 5 -10	; "x"
	23	[437]	UNM      	5 5
	24	[437]	GETTABLE 	6 2 -9	; "relative"
	25	[437]	GETTABLE 	6 6 -11	; "y"
	26	[437]	UNM      	6 6
	27	[437]	CALL     	3 4 1
	28	[438]	JMP      	38	; to 67
	29	[439]	GETTABLE 	3 2 -12	; "direction"
	30	[439]	EQ       	1 3 -13	; - "north"
	31	[439]	JMP      	3	; to 35
	32	[439]	GETTABLE 	3 2 -12	; "direction"
	33	[439]	EQ       	0 3 -14	; - "south"
	34	[439]	JMP      	32	; to 67
	35	[440]	LOADK    	3 -9	; "relative"
	36	[441]	GETTABLE 	4 0 -15	; "ui"
	37	[441]	GETTABLE 	4 4 -16	; "gesture"
	38	[441]	TEST     	4 0 0
	39	[441]	JMP      	6	; to 46
	40	[441]	GETTABLE 	4 0 -15	; "ui"
	41	[441]	GETTABLE 	4 4 -16	; "gesture"
	42	[441]	GETTABLE 	4 4 -17	; "multiswipes_enabled"
	43	[441]	TEST     	4 0 0
	44	[441]	JMP      	1	; to 46
	45	[442]	LOADK    	3 -18	; "relative_delayed"
	46	[445]	GETTABLE 	4 2 -19	; "mousewheel_direction"
	47	[445]	TEST     	4 0 0
	48	[445]	JMP      	9	; to 58
	49	[445]	GETTABLE 	4 0 -3	; "view"
	50	[445]	GETTABLE 	4 4 -20	; "page_scroll"
	51	[445]	TEST     	4 0 1
	52	[445]	JMP      	5	; to 58
	53	[446]	SELF     	4 0 -21	; "onGotoViewRel"
	54	[446]	GETTABLE 	6 2 -19	; "mousewheel_direction"
	55	[446]	MUL      	6 -22 6	; -1 -
	56	[446]	CALL     	4 3 1
	57	[446]	JMP      	9	; to 67
	58	[448]	SELF     	4 0 -23	; "onPanningRel"
	59	[448]	GETTABLE 	6 0 -24	; "last_pan_relative_y"
	60	[448]	GETTABLE 	7 2 3
	61	[448]	GETTABLE 	7 7 -11	; "y"
	62	[448]	SUB      	6 6 7
	63	[448]	CALL     	4 3 1
	64	[449]	GETTABLE 	4 2 3
	65	[449]	GETTABLE 	4 4 -11	; "y"
	66	[449]	SETTABLE 	0 -24 4	; "last_pan_relative_y" -
	67	[452]	LOADBOOL 	3 1 0
	68	[452]	RETURN   	3 2
	69	[453]	RETURN   	0 1

function <./frontend/apps/reader/modules/readerpaging.lua:455,467> (22 instructions, 88 bytes at 0x7ffb2d40afb0)
3 params, 7 slots, 1 upvalue, 3 locals, 11 constants, 0 functions
	1	[456]	GETTABLE 	3 0 -1	; "page_flipping_mode"
	2	[456]	TEST     	3 0 0
	3	[456]	JMP      	12	; to 16
	4	[457]	GETTABLE 	3 0 -2	; "view"
	5	[457]	GETTABLE 	3 3 -3	; "zoom_mode"
	6	[457]	EQ       	0 3 -4	; - "page"
	7	[457]	JMP      	4	; to 12
	8	[458]	SELF     	3 0 -5	; "updateFlippingPage"
	9	[458]	GETTABLE 	5 0 -6	; "current_page"
	10	[458]	CALL     	3 3 1
	11	[458]	JMP      	10	; to 22
	12	[460]	GETTABLE 	3 0 -2	; "view"
	13	[460]	SELF     	3 3 -7	; "PanningStop"
	14	[460]	CALL     	3 2 1
	15	[461]	JMP      	6	; to 22
	16	[463]	SETTABLE 	0 -8 -9	; "last_pan_relative_y" 0
	17	[465]	GETUPVAL 	3 0	; UIManager
	18	[465]	SELF     	3 3 -10	; "setDirty"
	19	[465]	LOADNIL  	5 5
	20	[465]	LOADK    	6 -11	; "full"
	21	[465]	CALL     	3 4 1
	22	[467]	RETURN   	0 1

function <./frontend/apps/reader/modules/readerpaging.lua:469,472> (2 instructions, 8 bytes at 0x7ffb2d40d120)
2 params, 2 slots, 0 upvalues, 2 locals, 1 constant, 0 functions
	1	[471]	SETTABLE 	0 -1 1	; "zoom_mode" -
	2	[472]	RETURN   	0 1

function <./frontend/apps/reader/modules/readerpaging.lua:474,479> (16 instructions, 64 bytes at 0x7ffb2d410100)
3 params, 9 slots, 1 upvalue, 3 locals, 8 constants, 0 functions
	1	[475]	SETTABLE 	0 -1 1	; "current_page" -
	2	[476]	GETTABLE 	3 0 -2	; "view"
	3	[476]	GETTABLE 	3 3 -3	; "page_scroll"
	4	[476]	TEST     	3 0 0
	5	[476]	JMP      	10	; to 16
	6	[476]	EQ       	1 2 -4	; - "scrolling"
	7	[476]	JMP      	8	; to 16
	8	[477]	GETTABLE 	3 0 -5	; "ui"
	9	[477]	SELF     	3 3 -6	; "handleEvent"
	10	[477]	GETUPVAL 	5 0	; Event
	11	[477]	SELF     	5 5 -7	; "new"
	12	[477]	LOADK    	7 -8	; "InitScrollPageStates"
	13	[477]	MOVE     	8 2
	14	[477]	CALL     	5 4 0
	15	[477]	CALL     	3 0 1
	16	[479]	RETURN   	0 1

function <./frontend/apps/reader/modules/readerpaging.lua:481,485> (5 instructions, 20 bytes at 0x7ffb2d408470)
3 params, 5 slots, 0 upvalues, 3 locals, 3 constants, 0 functions
	1	[483]	SELF     	3 1 -2	; "copy"
	2	[483]	CALL     	3 2 2
	3	[483]	SETTABLE 	0 -1 3	; "visible_area" -
	4	[484]	SETTABLE 	0 -3 2	; "page_area" -
	5	[485]	RETURN   	0 1

function <./frontend/apps/reader/modules/readerpaging.lua:487,496> (24 instructions, 96 bytes at 0x7ffb2d4084f0)
2 params, 6 slots, 1 upvalue, 3 locals, 8 constants, 0 functions
	1	[488]	GETUPVAL 	2 0	; logger
	2	[488]	GETTABLE 	2 2 -1	; "dbg"
	3	[488]	LOADK    	3 -2	; "goto document offset in percent:"
	4	[488]	MOVE     	4 1
	5	[488]	CALL     	2 3 1
	6	[489]	GETGLOBAL	2 -3	; math
	7	[489]	GETTABLE 	2 2 -4	; "floor"
	8	[489]	GETTABLE 	3 0 -5	; "number_of_pages"
	9	[489]	MUL      	3 3 1
	10	[489]	DIV      	3 3 -6	; - 100
	11	[489]	CALL     	2 2 2
	12	[490]	LT       	0 2 -7	; - 1
	13	[490]	JMP      	1	; to 15
	14	[490]	LOADK    	2 -7	; 1
	15	[491]	GETTABLE 	3 0 -5	; "number_of_pages"
	16	[491]	LT       	0 3 2
	17	[491]	JMP      	1	; to 19
	18	[492]	GETTABLE 	2 0 -5	; "number_of_pages"
	19	[494]	SELF     	3 0 -8	; "_gotoPage"
	20	[494]	MOVE     	5 2
	21	[494]	CALL     	3 3 1
	22	[495]	LOADBOOL 	3 1 0
	23	[495]	RETURN   	3 2
	24	[496]	RETURN   	0 1

function <./frontend/apps/reader/modules/readerpaging.lua:498,506> (20 instructions, 80 bytes at 0x7ffb2d40ce00)
2 params, 7 slots, 0 upvalues, 2 locals, 7 constants, 0 functions
	1	[499]	GETTABLE 	2 0 -1	; "view"
	2	[499]	GETTABLE 	2 2 -2	; "page_scroll"
	3	[499]	TEST     	2 0 0
	4	[499]	JMP      	4	; to 9
	5	[500]	SELF     	2 0 -3	; "onScrollPageRel"
	6	[500]	MOVE     	4 1
	7	[500]	CALL     	2 3 1
	8	[500]	JMP      	3	; to 12
	9	[502]	SELF     	2 0 -4	; "onGotoPageRel"
	10	[502]	MOVE     	4 1
	11	[502]	CALL     	2 3 1
	12	[504]	SELF     	2 0 -5	; "setPagePosition"
	13	[504]	SELF     	4 0 -6	; "getTopPage"
	14	[504]	CALL     	4 2 2
	15	[504]	SELF     	5 0 -7	; "getTopPosition"
	16	[504]	CALL     	5 2 0
	17	[504]	CALL     	2 0 1
	18	[505]	LOADBOOL 	2 1 0
	19	[505]	RETURN   	2 2
	20	[506]	RETURN   	0 1

function <./frontend/apps/reader/modules/readerpaging.lua:508,516> (20 instructions, 80 bytes at 0x7ffb2d40dbd0)
2 params, 7 slots, 0 upvalues, 2 locals, 8 constants, 0 functions
	1	[509]	GETTABLE 	2 0 -1	; "view"
	2	[509]	GETTABLE 	2 2 -2	; "page_scroll"
	3	[509]	TEST     	2 0 0
	4	[509]	JMP      	4	; to 9
	5	[510]	SELF     	2 0 -3	; "onPanningRel"
	6	[510]	MUL      	4 -4 1	; 100 -
	7	[510]	CALL     	2 3 1
	8	[510]	JMP      	3	; to 12
	9	[512]	SELF     	2 0 -5	; "onGotoPageRel"
	10	[512]	MOVE     	4 1
	11	[512]	CALL     	2 3 1
	12	[514]	SELF     	2 0 -6	; "setPagePosition"
	13	[514]	SELF     	4 0 -7	; "getTopPage"
	14	[514]	CALL     	4 2 2
	15	[514]	SELF     	5 0 -8	; "getTopPosition"
	16	[514]	CALL     	5 2 0
	17	[514]	CALL     	2 0 1
	18	[515]	LOADBOOL 	2 1 0
	19	[515]	RETURN   	2 2
	20	[516]	RETURN   	0 1

function <./frontend/apps/reader/modules/readerpaging.lua:518,524> (16 instructions, 64 bytes at 0x7ffb2d40e110)
2 params, 7 slots, 0 upvalues, 2 locals, 6 constants, 0 functions
	1	[519]	GETTABLE 	2 0 -1	; "view"
	2	[519]	GETTABLE 	2 2 -2	; "page_scroll"
	3	[519]	TEST     	2 0 0
	4	[519]	JMP      	3	; to 8
	5	[520]	SELF     	2 0 -3	; "onScrollPanRel"
	6	[520]	MOVE     	4 1
	7	[520]	CALL     	2 3 1
	8	[522]	SELF     	2 0 -4	; "setPagePosition"
	9	[522]	SELF     	4 0 -5	; "getTopPage"
	10	[522]	CALL     	4 2 2
	11	[522]	SELF     	5 0 -6	; "getTopPosition"
	12	[522]	CALL     	5 2 0
	13	[522]	CALL     	2 0 1
	14	[523]	LOADBOOL 	2 1 0
	15	[523]	RETURN   	2 2
	16	[524]	RETURN   	0 1

function <./frontend/apps/reader/modules/readerpaging.lua:526,528> (5 instructions, 20 bytes at 0x7ffb2d40e550)
1 param, 3 slots, 0 upvalues, 1 local, 2 constants, 0 functions
	1	[527]	GETTABLE 	1 0 -1	; "view"
	2	[527]	SELF     	1 1 -2	; "getViewContext"
	3	[527]	TAILCALL 	1 2 0
	4	[527]	RETURN   	1 0
	5	[528]	RETURN   	0 1

function <./frontend/apps/reader/modules/readerpaging.lua:530,543> (33 instructions, 132 bytes at 0x7ffb2d40e650)
2 params, 7 slots, 0 upvalues, 2 locals, 11 constants, 0 functions
	1	[531]	GETTABLE 	2 0 -1	; "view"
	2	[531]	GETTABLE 	2 2 -2	; "page_scroll"
	3	[531]	TEST     	2 0 0
	4	[531]	JMP      	12	; to 17
	5	[532]	GETTABLE 	2 0 -1	; "view"
	6	[532]	SELF     	2 2 -3	; "restoreViewContext"
	7	[532]	MOVE     	4 1
	8	[532]	CALL     	2 3 1
	9	[533]	SELF     	2 0 -4	; "_gotoPage"
	10	[533]	GETTABLE 	4 0 -1	; "view"
	11	[533]	GETTABLE 	4 4 -5	; "page_states"
	12	[533]	GETTABLE 	4 4 -6	; 1
	13	[533]	GETTABLE 	4 4 -7	; "page"
	14	[533]	LOADK    	5 -8	; "scrolling"
	15	[533]	CALL     	2 4 1
	16	[533]	JMP      	8	; to 25
	17	[538]	SELF     	2 0 -4	; "_gotoPage"
	18	[538]	GETTABLE 	4 1 -6	; 1
	19	[538]	GETTABLE 	4 4 -7	; "page"
	20	[538]	CALL     	2 3 1
	21	[539]	GETTABLE 	2 0 -1	; "view"
	22	[539]	SELF     	2 2 -3	; "restoreViewContext"
	23	[539]	MOVE     	4 1
	24	[539]	CALL     	2 3 1
	25	[541]	SELF     	2 0 -9	; "setPagePosition"
	26	[541]	SELF     	4 0 -10	; "getTopPage"
	27	[541]	CALL     	4 2 2
	28	[541]	SELF     	5 0 -11	; "getTopPosition"
	29	[541]	CALL     	5 2 0
	30	[541]	CALL     	2 0 1
	31	[542]	LOADBOOL 	2 1 0
	32	[542]	RETURN   	2 2
	33	[543]	RETURN   	0 1

function <./frontend/apps/reader/modules/readerpaging.lua:548,555> (20 instructions, 80 bytes at 0x7ffb2d4124d0)
1 param, 4 slots, 0 upvalues, 2 locals, 9 constants, 0 functions
	1	[549]	GETTABLE 	1 0 -1	; "view"
	2	[549]	GETTABLE 	1 1 -2	; "page_scroll"
	3	[549]	TEST     	1 0 0
	4	[549]	JMP      	13	; to 18
	5	[550]	GETTABLE 	1 0 -1	; "view"
	6	[550]	GETTABLE 	1 1 -3	; "page_states"
	7	[550]	GETTABLE 	1 1 -4	; 1
	8	[551]	GETTABLE 	2 1 -5	; "visible_area"
	9	[551]	GETTABLE 	2 2 -6	; "y"
	10	[551]	GETTABLE 	3 1 -7	; "page_area"
	11	[551]	GETTABLE 	3 3 -6	; "y"
	12	[551]	SUB      	2 2 3
	13	[551]	GETTABLE 	3 1 -7	; "page_area"
	14	[551]	GETTABLE 	3 3 -8	; "h"
	15	[551]	DIV      	2 2 3
	16	[551]	RETURN   	2 2
	17	[551]	JMP      	2	; to 20
	18	[553]	LOADK    	1 -9	; 0
	19	[553]	RETURN   	1 2
	20	[555]	RETURN   	0 1

function <./frontend/apps/reader/modules/readerpaging.lua:560,567> (18 instructions, 72 bytes at 0x7ffb2d4127d0)
1 param, 3 slots, 0 upvalues, 2 locals, 6 constants, 0 functions
	1	[561]	GETTABLE 	1 0 -1	; "view"
	2	[561]	GETTABLE 	1 1 -2	; "page_scroll"
	3	[561]	TEST     	1 0 0
	4	[561]	JMP      	11	; to 16
	5	[562]	GETTABLE 	1 0 -1	; "view"
	6	[562]	GETTABLE 	1 1 -3	; "page_states"
	7	[562]	GETTABLE 	1 1 -4	; 1
	8	[563]	TEST     	1 0 0
	9	[563]	JMP      	3	; to 13
	10	[563]	GETTABLE 	2 1 -5	; "page"
	11	[563]	TEST     	2 0 1
	12	[563]	JMP      	1	; to 14
	13	[563]	GETTABLE 	2 0 -6	; "current_page"
	14	[563]	RETURN   	2 2
	15	[563]	JMP      	2	; to 18
	16	[565]	GETTABLE 	1 0 -6	; "current_page"
	17	[565]	RETURN   	1 2
	18	[567]	RETURN   	0 1

function <./frontend/apps/reader/modules/readerpaging.lua:569,598> (91 instructions, 364 bytes at 0x7ffb2d412a80)
2 params, 9 slots, 2 upvalues, 6 locals, 27 constants, 0 functions
	1	[570]	GETUPVAL 	2 0	; logger
	2	[570]	GETTABLE 	2 2 -1	; "dbg"
	3	[570]	LOADK    	3 -2	; "init scroll page states"
	4	[570]	MOVE     	4 1
	5	[570]	CALL     	2 3 1
	6	[571]	GETTABLE 	2 0 -3	; "view"
	7	[571]	GETTABLE 	2 2 -4	; "page_scroll"
	8	[571]	TEST     	2 0 0
	9	[571]	JMP      	79	; to 89
	10	[571]	GETTABLE 	2 0 -3	; "view"
	11	[571]	GETTABLE 	2 2 -5	; "state"
	12	[571]	GETTABLE 	2 2 -6	; "page"
	13	[571]	TEST     	2 0 0
	14	[571]	JMP      	74	; to 89
	15	[572]	GETTABLE 	2 0 -8	; "current_page"
	16	[572]	SETTABLE 	0 -7 2	; "orig_page" -
	17	[573]	GETTABLE 	2 0 -3	; "view"
	18	[573]	NEWTABLE 	3 0 0
	19	[573]	SETTABLE 	2 -9 3	; "page_states" -
	20	[574]	GETUPVAL 	2 1	; Geom
	21	[574]	SELF     	2 2 -10	; "new"
	22	[574]	NEWTABLE 	4 0 0
	23	[574]	CALL     	2 3 2
	24	[575]	SELF     	3 2 -11	; "setSizeTo"
	25	[575]	GETTABLE 	5 0 -3	; "view"
	26	[575]	GETTABLE 	5 5 -12	; "visible_area"
	27	[575]	CALL     	3 3 1
	28	[576]	GETTABLE 	3 2 -13	; "h"
	29	[576]	LT       	0 -14 3	; 0 -
	30	[576]	JMP      	54	; to 85
	31	[577]	GETUPVAL 	3 1	; Geom
	32	[577]	SELF     	3 3 -10	; "new"
	33	[577]	NEWTABLE 	5 0 0
	34	[577]	CALL     	3 3 2
	35	[579]	GETTABLE 	4 0 -8	; "current_page"
	36	[579]	GETTABLE 	5 0 -7	; "orig_page"
	37	[579]	EQ       	0 4 5
	38	[579]	JMP      	18	; to 57
	39	[580]	GETTABLE 	4 0 -3	; "view"
	40	[580]	SELF     	4 4 -15	; "getPageArea"
	41	[581]	GETTABLE 	6 0 -3	; "view"
	42	[581]	GETTABLE 	6 6 -5	; "state"
	43	[581]	GETTABLE 	6 6 -6	; "page"
	44	[582]	GETTABLE 	7 0 -3	; "view"
	45	[582]	GETTABLE 	7 7 -5	; "state"
	46	[582]	GETTABLE 	7 7 -16	; "zoom"
	47	[583]	GETTABLE 	8 0 -3	; "view"
	48	[583]	GETTABLE 	8 8 -5	; "state"
	49	[583]	GETTABLE 	8 8 -17	; "rotation"
	50	[580]	CALL     	4 5 2
	51	[584]	GETTABLE 	5 4 -13	; "h"
	52	[584]	SELF     	6 0 -19	; "getPagePosition"
	53	[584]	GETTABLE 	8 0 -8	; "current_page"
	54	[584]	CALL     	6 3 2
	55	[584]	MUL      	5 5 6
	56	[584]	SETTABLE 	3 -18 5	; "y" -
	57	[586]	SELF     	4 0 -20	; "getNextPageState"
	58	[586]	MOVE     	6 2
	59	[586]	MOVE     	7 3
	60	[586]	CALL     	4 4 2
	61	[587]	GETGLOBAL	5 -21	; table
	62	[587]	GETTABLE 	5 5 -22	; "insert"
	63	[587]	GETTABLE 	6 0 -3	; "view"
	64	[587]	GETTABLE 	6 6 -9	; "page_states"
	65	[587]	MOVE     	7 4
	66	[587]	CALL     	5 3 1
	67	[588]	GETTABLE 	5 2 -13	; "h"
	68	[588]	LT       	0 -14 5	; 0 -
	69	[588]	JMP      	6	; to 76
	70	[589]	GETTABLE 	5 2 -13	; "h"
	71	[589]	GETTABLE 	6 0 -3	; "view"
	72	[589]	GETTABLE 	6 6 -23	; "page_gap"
	73	[589]	GETTABLE 	6 6 -24	; "height"
	74	[589]	SUB      	5 5 6
	75	[589]	SETTABLE 	2 -13 5	; "h" -
	76	[591]	GETTABLE 	5 2 -13	; "h"
	77	[591]	LT       	0 -14 5	; 0 -
	78	[591]	JMP      	-51	; to 28
	79	[592]	SELF     	5 0 -25	; "_gotoPage"
	80	[592]	GETTABLE 	7 0 -8	; "current_page"
	81	[592]	ADD      	7 7 -26	; - 1
	82	[592]	LOADK    	8 -27	; "scrolling"
	83	[592]	CALL     	5 4 1
	84	[593]	JMP      	-57	; to 28
	85	[595]	SELF     	3 0 -25	; "_gotoPage"
	86	[595]	GETTABLE 	5 0 -7	; "orig_page"
	87	[595]	LOADK    	6 -27	; "scrolling"
	88	[595]	CALL     	3 4 1
	89	[597]	LOADBOOL 	2 1 0
	90	[597]	RETURN   	2 2
	91	[598]	RETURN   	0 1

function <./frontend/apps/reader/modules/readerpaging.lua:600,605> (11 instructions, 44 bytes at 0x7ffb2d412b90)
2 params, 8 slots, 0 upvalues, 7 locals, 4 constants, 0 functions
	1	[601]	GETGLOBAL	2 -1	; ipairs
	2	[601]	GETTABLE 	3 0 -2	; "view"
	3	[601]	GETTABLE 	3 3 -3	; "page_states"
	4	[601]	CALL     	2 2 4
	5	[601]	JMP      	1	; to 7
	6	[602]	SETTABLE 	6 -4 1	; "rotation" -
	7	[601]	TFORLOOP 	2 2
	8	[602]	JMP      	-3	; to 6
	9	[604]	LOADBOOL 	2 1 0
	10	[604]	RETURN   	2 2
	11	[605]	RETURN   	0 1

function <./frontend/apps/reader/modules/readerpaging.lua:607,612> (11 instructions, 44 bytes at 0x7ffb2d4137c0)
2 params, 8 slots, 0 upvalues, 7 locals, 4 constants, 0 functions
	1	[608]	GETGLOBAL	2 -1	; ipairs
	2	[608]	GETTABLE 	3 0 -2	; "view"
	3	[608]	GETTABLE 	3 3 -3	; "page_states"
	4	[608]	CALL     	2 2 4
	5	[608]	JMP      	1	; to 7
	6	[609]	SETTABLE 	6 -4 1	; "gamma" -
	7	[608]	TFORLOOP 	2 2
	8	[609]	JMP      	-3	; to 6
	9	[611]	LOADBOOL 	2 1 0
	10	[611]	RETURN   	2 2
	11	[612]	RETURN   	0 1

function <./frontend/apps/reader/modules/readerpaging.lua:614,634> (68 instructions, 272 bytes at 0x7ffb2d4139c0)
3 params, 10 slots, 1 upvalue, 5 locals, 17 constants, 0 functions
	1	[615]	GETTABLE 	3 0 -1	; "view"
	2	[615]	SELF     	3 3 -2	; "getPageArea"
	3	[616]	GETTABLE 	5 0 -1	; "view"
	4	[616]	GETTABLE 	5 5 -3	; "state"
	5	[616]	GETTABLE 	5 5 -4	; "page"
	6	[617]	GETTABLE 	6 0 -1	; "view"
	7	[617]	GETTABLE 	6 6 -3	; "state"
	8	[617]	GETTABLE 	6 6 -5	; "zoom"
	9	[618]	GETTABLE 	7 0 -1	; "view"
	10	[618]	GETTABLE 	7 7 -3	; "state"
	11	[618]	GETTABLE 	7 7 -6	; "rotation"
	12	[615]	CALL     	3 5 2
	13	[619]	GETUPVAL 	4 0	; Geom
	14	[619]	SELF     	4 4 -7	; "new"
	15	[619]	NEWTABLE 	6 0 2
	16	[619]	SETTABLE 	6 -8 -9	; "x" 0
	17	[619]	SETTABLE 	6 -10 -9	; "y" 0
	18	[619]	CALL     	4 3 2
	19	[620]	GETTABLE 	5 1 -11	; "w"
	20	[620]	GETTABLE 	6 1 -12	; "h"
	21	[620]	SETTABLE 	4 -12 6	; "h" -
	22	[620]	SETTABLE 	4 -11 5	; "w" -
	23	[621]	GETTABLE 	5 3 -8	; "x"
	24	[621]	GETTABLE 	6 3 -10	; "y"
	25	[621]	SETTABLE 	4 -10 6	; "y" -
	26	[621]	SETTABLE 	4 -8 5	; "x" -
	27	[622]	SELF     	5 4 -13	; "shrinkInside"
	28	[622]	MOVE     	7 3
	29	[622]	GETTABLE 	8 2 -8	; "x"
	30	[622]	GETTABLE 	9 2 -10	; "y"
	31	[622]	CALL     	5 5 2
	32	[622]	MOVE     	4 5
	33	[624]	GETTABLE 	5 1 -12	; "h"
	34	[624]	GETTABLE 	6 4 -12	; "h"
	35	[624]	SUB      	5 5 6
	36	[624]	SETTABLE 	1 -12 5	; "h" -
	37	[625]	NEWTABLE 	5 0 7
	38	[626]	GETTABLE 	6 0 -1	; "view"
	39	[626]	GETTABLE 	6 6 -3	; "state"
	40	[626]	GETTABLE 	6 6 -4	; "page"
	41	[626]	SETTABLE 	5 -4 6	; "page" -
	42	[627]	GETTABLE 	6 0 -1	; "view"
	43	[627]	GETTABLE 	6 6 -3	; "state"
	44	[627]	GETTABLE 	6 6 -5	; "zoom"
	45	[627]	SETTABLE 	5 -5 6	; "zoom" -
	46	[628]	GETTABLE 	6 0 -1	; "view"
	47	[628]	GETTABLE 	6 6 -3	; "state"
	48	[628]	GETTABLE 	6 6 -6	; "rotation"
	49	[628]	SETTABLE 	5 -6 6	; "rotation" -
	50	[629]	GETTABLE 	6 0 -1	; "view"
	51	[629]	GETTABLE 	6 6 -3	; "state"
	52	[629]	GETTABLE 	6 6 -14	; "gamma"
	53	[629]	SETTABLE 	5 -14 6	; "gamma" -
	54	[630]	GETUPVAL 	6 0	; Geom
	55	[630]	SELF     	6 6 -7	; "new"
	56	[630]	NEWTABLE 	8 0 2
	57	[630]	GETTABLE 	9 0 -1	; "view"
	58	[630]	GETTABLE 	9 9 -3	; "state"
	59	[630]	GETTABLE 	9 9 -15	; "offset"
	60	[630]	GETTABLE 	9 9 -8	; "x"
	61	[630]	SETTABLE 	8 -8 9	; "x" -
	62	[630]	SETTABLE 	8 -10 -9	; "y" 0
	63	[630]	CALL     	6 3 2
	64	[630]	SETTABLE 	5 -15 6	; "offset" -
	65	[631]	SETTABLE 	5 -16 4	; "visible_area" -
	66	[632]	SETTABLE 	5 -17 3	; "page_area" -
	67	[633]	RETURN   	5 2
	68	[634]	RETURN   	0 1

function <./frontend/apps/reader/modules/readerpaging.lua:636,657> (72 instructions, 288 bytes at 0x7ffb2d413d40)
3 params, 10 slots, 1 upvalue, 5 locals, 17 constants, 0 functions
	1	[637]	GETTABLE 	3 0 -1	; "view"
	2	[637]	SELF     	3 3 -2	; "getPageArea"
	3	[638]	GETTABLE 	5 0 -1	; "view"
	4	[638]	GETTABLE 	5 5 -3	; "state"
	5	[638]	GETTABLE 	5 5 -4	; "page"
	6	[639]	GETTABLE 	6 0 -1	; "view"
	7	[639]	GETTABLE 	6 6 -3	; "state"
	8	[639]	GETTABLE 	6 6 -5	; "zoom"
	9	[640]	GETTABLE 	7 0 -1	; "view"
	10	[640]	GETTABLE 	7 7 -3	; "state"
	11	[640]	GETTABLE 	7 7 -6	; "rotation"
	12	[637]	CALL     	3 5 2
	13	[641]	GETUPVAL 	4 0	; Geom
	14	[641]	SELF     	4 4 -7	; "new"
	15	[641]	NEWTABLE 	6 0 2
	16	[641]	SETTABLE 	6 -8 -9	; "x" 0
	17	[641]	SETTABLE 	6 -10 -9	; "y" 0
	18	[641]	CALL     	4 3 2
	19	[642]	GETTABLE 	5 1 -11	; "w"
	20	[642]	GETTABLE 	6 1 -12	; "h"
	21	[642]	SETTABLE 	4 -12 6	; "h" -
	22	[642]	SETTABLE 	4 -11 5	; "w" -
	23	[643]	GETTABLE 	5 3 -8	; "x"
	24	[643]	SETTABLE 	4 -8 5	; "x" -
	25	[644]	GETTABLE 	5 3 -10	; "y"
	26	[644]	GETTABLE 	6 3 -12	; "h"
	27	[644]	ADD      	5 5 6
	28	[644]	GETTABLE 	6 4 -12	; "h"
	29	[644]	SUB      	5 5 6
	30	[644]	SETTABLE 	4 -10 5	; "y" -
	31	[645]	SELF     	5 4 -13	; "shrinkInside"
	32	[645]	MOVE     	7 3
	33	[645]	GETTABLE 	8 2 -8	; "x"
	34	[645]	GETTABLE 	9 2 -10	; "y"
	35	[645]	CALL     	5 5 2
	36	[645]	MOVE     	4 5
	37	[647]	GETTABLE 	5 1 -12	; "h"
	38	[647]	GETTABLE 	6 4 -12	; "h"
	39	[647]	SUB      	5 5 6
	40	[647]	SETTABLE 	1 -12 5	; "h" -
	41	[648]	NEWTABLE 	5 0 7
	42	[649]	GETTABLE 	6 0 -1	; "view"
	43	[649]	GETTABLE 	6 6 -3	; "state"
	44	[649]	GETTABLE 	6 6 -4	; "page"
	45	[649]	SETTABLE 	5 -4 6	; "page" -
	46	[650]	GETTABLE 	6 0 -1	; "view"
	47	[650]	GETTABLE 	6 6 -3	; "state"
	48	[650]	GETTABLE 	6 6 -5	; "zoom"
	49	[650]	SETTABLE 	5 -5 6	; "zoom" -
	50	[651]	GETTABLE 	6 0 -1	; "view"
	51	[651]	GETTABLE 	6 6 -3	; "state"
	52	[651]	GETTABLE 	6 6 -6	; "rotation"
	53	[651]	SETTABLE 	5 -6 6	; "rotation" -
	54	[652]	GETTABLE 	6 0 -1	; "view"
	55	[652]	GETTABLE 	6 6 -3	; "state"
	56	[652]	GETTABLE 	6 6 -14	; "gamma"
	57	[652]	SETTABLE 	5 -14 6	; "gamma" -
	58	[653]	GETUPVAL 	6 0	; Geom
	59	[653]	SELF     	6 6 -7	; "new"
	60	[653]	NEWTABLE 	8 0 2
	61	[653]	GETTABLE 	9 0 -1	; "view"
	62	[653]	GETTABLE 	9 9 -3	; "state"
	63	[653]	GETTABLE 	9 9 -15	; "offset"
	64	[653]	GETTABLE 	9 9 -8	; "x"
	65	[653]	SETTABLE 	8 -8 9	; "x" -
	66	[653]	SETTABLE 	8 -10 -9	; "y" 0
	67	[653]	CALL     	6 3 2
	68	[653]	SETTABLE 	5 -15 6	; "offset" -
	69	[654]	SETTABLE 	5 -16 4	; "visible_area" -
	70	[655]	SETTABLE 	5 -17 3	; "page_area" -
	71	[656]	RETURN   	5 2
	72	[657]	RETURN   	0 1

function <./frontend/apps/reader/modules/readerpaging.lua:659,674> (36 instructions, 144 bytes at 0x7ffb2d414570)
4 params, 10 slots, 1 upvalue, 5 locals, 11 constants, 0 functions
	1	[660]	GETUPVAL 	4 0	; Geom
	2	[660]	SELF     	4 4 -1	; "new"
	3	[660]	NEWTABLE 	6 0 4
	4	[661]	GETTABLE 	7 1 -3	; "visible_area"
	5	[661]	GETTABLE 	7 7 -2	; "x"
	6	[661]	SETTABLE 	6 -2 7	; "x" -
	7	[662]	GETTABLE 	7 1 -3	; "visible_area"
	8	[662]	GETTABLE 	7 7 -4	; "y"
	9	[662]	SETTABLE 	6 -4 7	; "y" -
	10	[663]	GETTABLE 	7 2 -5	; "w"
	11	[663]	SETTABLE 	6 -5 7	; "w" -
	12	[664]	GETTABLE 	7 2 -6	; "h"
	13	[664]	SETTABLE 	6 -6 7	; "h" -
	14	[660]	CALL     	4 3 2
	15	[666]	GETTABLE 	5 1 -7	; "page"
	16	[666]	GETTABLE 	6 0 -8	; "number_of_pages"
	17	[666]	EQ       	0 5 6
	18	[666]	JMP      	6	; to 25
	19	[667]	SELF     	5 4 -9	; "offsetWithin"
	20	[667]	GETTABLE 	7 1 -10	; "page_area"
	21	[667]	GETTABLE 	8 3 -2	; "x"
	22	[667]	GETTABLE 	9 3 -4	; "y"
	23	[667]	CALL     	5 5 1
	24	[667]	JMP      	6	; to 31
	25	[669]	SELF     	5 4 -11	; "shrinkInside"
	26	[669]	GETTABLE 	7 1 -10	; "page_area"
	27	[669]	GETTABLE 	8 3 -2	; "x"
	28	[669]	GETTABLE 	9 3 -4	; "y"
	29	[669]	CALL     	5 5 2
	30	[669]	MOVE     	4 5
	31	[672]	GETTABLE 	5 2 -6	; "h"
	32	[672]	GETTABLE 	6 4 -6	; "h"
	33	[672]	SUB      	5 5 6
	34	[672]	SETTABLE 	2 -6 5	; "h" -
	35	[673]	SETTABLE 	1 -3 4	; "visible_area" -
	36	[674]	RETURN   	0 1

function <./frontend/apps/reader/modules/readerpaging.lua:676,691> (40 instructions, 160 bytes at 0x7ffb2d413b30)
4 params, 10 slots, 1 upvalue, 5 locals, 11 constants, 0 functions
	1	[677]	GETUPVAL 	4 0	; Geom
	2	[677]	SELF     	4 4 -1	; "new"
	3	[677]	NEWTABLE 	6 0 4
	4	[678]	GETTABLE 	7 1 -3	; "page_area"
	5	[678]	GETTABLE 	7 7 -2	; "x"
	6	[678]	SETTABLE 	6 -2 7	; "x" -
	7	[679]	GETTABLE 	7 1 -5	; "visible_area"
	8	[679]	GETTABLE 	7 7 -4	; "y"
	9	[679]	GETTABLE 	8 1 -5	; "visible_area"
	10	[679]	GETTABLE 	8 8 -6	; "h"
	11	[679]	ADD      	7 7 8
	12	[679]	GETTABLE 	8 2 -6	; "h"
	13	[679]	SUB      	7 7 8
	14	[679]	SETTABLE 	6 -4 7	; "y" -
	15	[680]	GETTABLE 	7 2 -7	; "w"
	16	[680]	SETTABLE 	6 -7 7	; "w" -
	17	[681]	GETTABLE 	7 2 -6	; "h"
	18	[681]	SETTABLE 	6 -6 7	; "h" -
	19	[677]	CALL     	4 3 2
	20	[683]	GETTABLE 	5 1 -8	; "page"
	21	[683]	EQ       	0 5 -9	; - 1
	22	[683]	JMP      	6	; to 29
	23	[684]	SELF     	5 4 -10	; "offsetWithin"
	24	[684]	GETTABLE 	7 1 -3	; "page_area"
	25	[684]	GETTABLE 	8 3 -2	; "x"
	26	[684]	GETTABLE 	9 3 -4	; "y"
	27	[684]	CALL     	5 5 1
	28	[684]	JMP      	6	; to 35
	29	[686]	SELF     	5 4 -11	; "shrinkInside"
	30	[686]	GETTABLE 	7 1 -3	; "page_area"
	31	[686]	GETTABLE 	8 3 -2	; "x"
	32	[686]	GETTABLE 	9 3 -4	; "y"
	33	[686]	CALL     	5 5 2
	34	[686]	MOVE     	4 5
	35	[689]	GETTABLE 	5 2 -6	; "h"
	36	[689]	GETTABLE 	6 4 -6	; "h"
	37	[689]	SUB      	5 5 6
	38	[689]	SETTABLE 	2 -6 5	; "h" -
	39	[690]	SETTABLE 	1 -5 4	; "visible_area" -
	40	[691]	RETURN   	0 1

function <./frontend/apps/reader/modules/readerpaging.lua:693,719> (58 instructions, 232 bytes at 0x7ffb2d4144f0)
4 params, 13 slots, 1 upvalue, 7 locals, 17 constants, 0 functions
	1	[699]	GETTABLE 	4 3 -1	; "y"
	2	[699]	LT       	0 4 -2	; - 0
	3	[699]	JMP      	1	; to 5
	4	[699]	SETTABLE 	3 -1 -2	; "y" 0
	5	[700]	SELF     	4 0 -3	; "updateTopPageState"
	6	[700]	MOVE     	6 1
	7	[700]	MOVE     	7 2
	8	[700]	MOVE     	8 3
	9	[700]	CALL     	4 5 1
	10	[701]	NEWTABLE 	4 0 0
	11	[702]	GETTABLE 	5 1 -4	; "visible_area"
	12	[702]	GETTABLE 	5 5 -5	; "h"
	13	[702]	LT       	0 -2 5	; 0 -
	14	[702]	JMP      	5	; to 20
	15	[704]	GETGLOBAL	5 -6	; table
	16	[704]	GETTABLE 	5 5 -7	; "insert"
	17	[704]	MOVE     	6 4
	18	[704]	MOVE     	7 1
	19	[704]	CALL     	5 3 1
	20	[706]	LOADNIL  	5 5
	21	[707]	GETTABLE 	6 1 -8	; "page"
	22	[708]	GETTABLE 	7 2 -5	; "h"
	23	[708]	LT       	0 -2 7	; 0 -
	24	[708]	JMP      	32	; to 57
	25	[709]	GETTABLE 	7 2 -5	; "h"
	26	[709]	GETTABLE 	8 0 -9	; "view"
	27	[709]	GETTABLE 	8 8 -10	; "page_gap"
	28	[709]	GETTABLE 	8 8 -11	; "height"
	29	[709]	SUB      	7 7 8
	30	[709]	SETTABLE 	2 -5 7	; "h" -
	31	[710]	GETTABLE 	7 2 -5	; "h"
	32	[710]	LT       	0 -2 7	; 0 -
	33	[710]	JMP      	-12	; to 22
	34	[711]	GETTABLE 	7 0 -12	; "number_of_pages"
	35	[711]	EQ       	0 6 7
	36	[711]	JMP      	1	; to 38
	37	[711]	JMP      	19	; to 57
	38	[712]	SELF     	7 0 -13	; "_gotoPage"
	39	[712]	ADD      	9 6 -14	; - 1
	40	[712]	LOADK    	10 -15	; "scrolling"
	41	[712]	CALL     	7 4 1
	42	[713]	ADD      	6 6 -14	; - 1
	43	[714]	SELF     	7 0 -16	; "getNextPageState"
	44	[714]	MOVE     	9 2
	45	[714]	GETUPVAL 	10 0	; Geom
	46	[714]	SELF     	10 10 -17	; "new"
	47	[714]	NEWTABLE 	12 0 0
	48	[714]	CALL     	10 3 0
	49	[714]	CALL     	7 0 2
	50	[714]	MOVE     	5 7
	51	[715]	GETGLOBAL	7 -6	; table
	52	[715]	GETTABLE 	7 7 -7	; "insert"
	53	[715]	MOVE     	8 4
	54	[715]	MOVE     	9 5
	55	[715]	CALL     	7 3 1
	56	[716]	JMP      	-35	; to 22
	57	[718]	RETURN   	4 2
	58	[719]	RETURN   	0 1

function <./frontend/apps/reader/modules/readerpaging.lua:721,744> (58 instructions, 232 bytes at 0x7ffb2d4155b0)
4 params, 13 slots, 1 upvalue, 7 locals, 16 constants, 0 functions
	1	[723]	GETTABLE 	4 3 -1	; "y"
	2	[723]	LT       	0 -2 4	; 0 -
	3	[723]	JMP      	1	; to 5
	4	[723]	SETTABLE 	3 -1 -2	; "y" 0
	5	[725]	SELF     	4 0 -3	; "updateBottomPageState"
	6	[725]	MOVE     	6 1
	7	[725]	MOVE     	7 2
	8	[725]	MOVE     	8 3
	9	[725]	CALL     	4 5 1
	10	[726]	NEWTABLE 	4 0 0
	11	[727]	GETTABLE 	5 1 -4	; "visible_area"
	12	[727]	GETTABLE 	5 5 -5	; "h"
	13	[727]	LT       	0 -2 5	; 0 -
	14	[727]	JMP      	5	; to 20
	15	[728]	GETGLOBAL	5 -6	; table
	16	[728]	GETTABLE 	5 5 -7	; "insert"
	17	[728]	MOVE     	6 4
	18	[728]	MOVE     	7 1
	19	[728]	CALL     	5 3 1
	20	[731]	LOADNIL  	5 5
	21	[732]	GETTABLE 	6 1 -8	; "page"
	22	[733]	GETTABLE 	7 2 -5	; "h"
	23	[733]	LT       	0 -2 7	; 0 -
	24	[733]	JMP      	32	; to 57
	25	[734]	GETTABLE 	7 2 -5	; "h"
	26	[734]	GETTABLE 	8 0 -9	; "view"
	27	[734]	GETTABLE 	8 8 -10	; "page_gap"
	28	[734]	GETTABLE 	8 8 -11	; "height"
	29	[734]	SUB      	7 7 8
	30	[734]	SETTABLE 	2 -5 7	; "h" -
	31	[735]	GETTABLE 	7 2 -5	; "h"
	32	[735]	LT       	0 -2 7	; 0 -
	33	[735]	JMP      	-12	; to 22
	34	[736]	EQ       	0 6 -12	; - 1
	35	[736]	JMP      	1	; to 37
	36	[736]	JMP      	20	; to 57
	37	[737]	SELF     	7 0 -13	; "_gotoPage"
	38	[737]	SUB      	9 6 -12	; - 1
	39	[737]	LOADK    	10 -14	; "scrolling"
	40	[737]	CALL     	7 4 1
	41	[738]	SUB      	6 6 -12	; - 1
	42	[739]	SELF     	7 0 -15	; "getPrevPageState"
	43	[739]	MOVE     	9 2
	44	[739]	GETUPVAL 	10 0	; Geom
	45	[739]	SELF     	10 10 -16	; "new"
	46	[739]	NEWTABLE 	12 0 0
	47	[739]	CALL     	10 3 0
	48	[739]	CALL     	7 0 2
	49	[739]	MOVE     	5 7
	50	[740]	GETGLOBAL	7 -6	; table
	51	[740]	GETTABLE 	7 7 -7	; "insert"
	52	[740]	MOVE     	8 4
	53	[740]	LOADK    	9 -12	; 1
	54	[740]	MOVE     	10 5
	55	[740]	CALL     	7 4 1
	56	[741]	JMP      	-35	; to 22
	57	[743]	RETURN   	4 2
	58	[744]	RETURN   	0 1

function <./frontend/apps/reader/modules/readerpaging.lua:746,775> (80 instructions, 320 bytes at 0x7ffb2d415b50)
2 params, 11 slots, 4 upvalues, 7 locals, 19 constants, 0 functions
	1	[747]	EQ       	0 1 -1	; - 0
	2	[747]	JMP      	2	; to 5
	3	[747]	LOADBOOL 	2 1 0
	4	[747]	RETURN   	2 2
	5	[748]	GETUPVAL 	2 0	; logger
	6	[748]	GETTABLE 	2 2 -2	; "dbg"
	7	[748]	LOADK    	3 -3	; "pan relative height:"
	8	[748]	MOVE     	4 1
	9	[748]	CALL     	2 3 1
	10	[749]	GETUPVAL 	2 1	; Geom
	11	[749]	SELF     	2 2 -4	; "new"
	12	[749]	NEWTABLE 	4 0 2
	13	[749]	SETTABLE 	4 -5 -1	; "x" 0
	14	[749]	SETTABLE 	4 -6 1	; "y" -
	15	[749]	CALL     	2 3 2
	16	[750]	GETUPVAL 	3 1	; Geom
	17	[750]	SELF     	3 3 -4	; "new"
	18	[750]	NEWTABLE 	5 0 0
	19	[750]	CALL     	3 3 2
	20	[751]	SELF     	4 3 -7	; "setSizeTo"
	21	[751]	GETTABLE 	6 0 -8	; "view"
	22	[751]	GETTABLE 	6 6 -9	; "visible_area"
	23	[751]	CALL     	4 3 1
	24	[752]	LOADNIL  	4 4
	25	[753]	LT       	0 -1 1	; 0 -
	26	[753]	JMP      	12	; to 39
	27	[755]	GETUPVAL 	5 2	; copyPageState
	28	[755]	GETTABLE 	6 0 -8	; "view"
	29	[755]	GETTABLE 	6 6 -10	; "page_states"
	30	[755]	GETTABLE 	6 6 -11	; 1
	31	[755]	CALL     	5 2 2
	32	[756]	SELF     	6 0 -12	; "genPageStatesFromTop"
	33	[757]	MOVE     	8 5
	34	[757]	MOVE     	9 3
	35	[757]	MOVE     	10 2
	36	[756]	CALL     	6 5 2
	37	[757]	MOVE     	4 6
	38	[757]	JMP      	16	; to 55
	39	[758]	LT       	0 1 -1	; - 0
	40	[758]	JMP      	14	; to 55
	41	[759]	GETUPVAL 	5 2	; copyPageState
	42	[760]	GETTABLE 	6 0 -8	; "view"
	43	[760]	GETTABLE 	6 6 -10	; "page_states"
	44	[760]	GETTABLE 	7 0 -8	; "view"
	45	[760]	GETTABLE 	7 7 -10	; "page_states"
	46	[760]	LEN      	7 7
	47	[760]	GETTABLE 	6 6 7
	48	[759]	CALL     	5 2 2
	49	[761]	SELF     	6 0 -13	; "genPageStatesFromBottom"
	50	[762]	MOVE     	8 5
	51	[762]	MOVE     	9 3
	52	[762]	MOVE     	10 2
	53	[761]	CALL     	6 5 2
	54	[762]	MOVE     	4 6
	55	[764]	LEN      	5 4
	56	[764]	EQ       	0 5 -1	; - 0
	57	[764]	JMP      	2	; to 60
	58	[767]	LOADBOOL 	5 1 0
	59	[767]	RETURN   	5 2
	60	[769]	GETTABLE 	5 0 -8	; "view"
	61	[769]	SETTABLE 	5 -10 4	; "page_states" -
	62	[771]	SELF     	5 0 -14	; "_gotoPage"
	63	[771]	GETTABLE 	7 0 -8	; "view"
	64	[771]	GETTABLE 	7 7 -10	; "page_states"
	65	[771]	GETTABLE 	8 0 -8	; "view"
	66	[771]	GETTABLE 	8 8 -10	; "page_states"
	67	[771]	LEN      	8 8
	68	[771]	GETTABLE 	7 7 8
	69	[771]	GETTABLE 	7 7 -15	; "page"
	70	[772]	LOADK    	8 -16	; "scrolling"
	71	[771]	CALL     	5 4 1
	72	[773]	GETUPVAL 	5 3	; UIManager
	73	[773]	SELF     	5 5 -17	; "setDirty"
	74	[773]	GETTABLE 	7 0 -8	; "view"
	75	[773]	GETTABLE 	7 7 -18	; "dialog"
	76	[773]	LOADK    	8 -19	; "partial"
	77	[773]	CALL     	5 4 1
	78	[774]	LOADBOOL 	5 1 0
	79	[774]	RETURN   	5 2
	80	[775]	RETURN   	0 1

function <./frontend/apps/reader/modules/readerpaging.lua:777,815> (116 instructions, 464 bytes at 0x7ffb2d415e10)
2 params, 13 slots, 3 upvalues, 11 locals, 27 constants, 0 functions
	1	[778]	EQ       	0 1 -1	; - 0
	2	[778]	JMP      	2	; to 5
	3	[778]	LOADBOOL 	2 1 0
	4	[778]	RETURN   	2 2
	5	[779]	LT       	0 -1 1	; 0 -
	6	[779]	JMP      	57	; to 64
	7	[781]	GETGLOBAL	2 -2	; table
	8	[781]	GETTABLE 	2 2 -3	; "remove"
	9	[781]	GETTABLE 	3 0 -4	; "view"
	10	[781]	GETTABLE 	3 3 -5	; "page_states"
	11	[781]	CALL     	2 2 2
	12	[782]	GETTABLE 	3 2 -6	; "visible_area"
	13	[783]	GETTABLE 	4 2 -7	; "page"
	14	[783]	GETTABLE 	5 0 -8	; "number_of_pages"
	15	[783]	EQ       	0 4 5
	16	[783]	JMP      	22	; to 39
	17	[784]	GETTABLE 	4 3 -9	; "y"
	18	[784]	GETTABLE 	5 3 -10	; "h"
	19	[784]	ADD      	4 4 5
	20	[784]	GETTABLE 	5 2 -11	; "page_area"
	21	[784]	GETTABLE 	5 5 -10	; "h"
	22	[784]	LE       	0 5 4
	23	[784]	JMP      	15	; to 39
	24	[785]	GETGLOBAL	4 -2	; table
	25	[785]	GETTABLE 	4 4 -12	; "insert"
	26	[785]	GETTABLE 	5 0 -4	; "view"
	27	[785]	GETTABLE 	5 5 -5	; "page_states"
	28	[785]	MOVE     	6 2
	29	[785]	CALL     	4 3 1
	30	[786]	GETTABLE 	4 0 -13	; "ui"
	31	[786]	SELF     	4 4 -14	; "handleEvent"
	32	[786]	GETUPVAL 	6 0	; Event
	33	[786]	SELF     	6 6 -15	; "new"
	34	[786]	LOADK    	8 -16	; "EndOfBook"
	35	[786]	CALL     	6 3 0
	36	[786]	CALL     	4 0 1
	37	[787]	LOADBOOL 	4 1 0
	38	[787]	RETURN   	4 2
	39	[790]	GETUPVAL 	4 1	; Geom
	40	[790]	SELF     	4 4 -15	; "new"
	41	[790]	NEWTABLE 	6 0 0
	42	[790]	CALL     	4 3 2
	43	[791]	SELF     	5 4 -17	; "setSizeTo"
	44	[791]	GETTABLE 	7 0 -4	; "view"
	45	[791]	GETTABLE 	7 7 -6	; "visible_area"
	46	[791]	CALL     	5 3 1
	47	[792]	GETTABLE 	5 0 -18	; "overlap"
	48	[793]	GETUPVAL 	6 1	; Geom
	49	[793]	SELF     	6 6 -15	; "new"
	50	[793]	NEWTABLE 	8 0 2
	51	[794]	SETTABLE 	8 -19 -1	; "x" 0
	52	[795]	GETTABLE 	9 3 -10	; "h"
	53	[795]	SUB      	9 9 5
	54	[795]	SETTABLE 	8 -9 9	; "y" -
	55	[793]	CALL     	6 3 2
	56	[797]	GETTABLE 	7 0 -4	; "view"
	57	[797]	SELF     	8 0 -20	; "genPageStatesFromTop"
	58	[797]	MOVE     	10 2
	59	[797]	MOVE     	11 4
	60	[797]	MOVE     	12 6
	61	[797]	CALL     	8 5 2
	62	[797]	SETTABLE 	7 -5 8	; "page_states" -
	63	[797]	JMP      	34	; to 98
	64	[798]	LT       	0 1 -1	; - 0
	65	[798]	JMP      	32	; to 98
	66	[800]	GETUPVAL 	2 1	; Geom
	67	[800]	SELF     	2 2 -15	; "new"
	68	[800]	NEWTABLE 	4 0 0
	69	[800]	CALL     	2 3 2
	70	[801]	SELF     	3 2 -17	; "setSizeTo"
	71	[801]	GETTABLE 	5 0 -4	; "view"
	72	[801]	GETTABLE 	5 5 -6	; "visible_area"
	73	[801]	CALL     	3 3 1
	74	[802]	GETTABLE 	3 0 -18	; "overlap"
	75	[803]	GETGLOBAL	4 -2	; table
	76	[803]	GETTABLE 	4 4 -3	; "remove"
	77	[803]	GETTABLE 	5 0 -4	; "view"
	78	[803]	GETTABLE 	5 5 -5	; "page_states"
	79	[803]	LOADK    	6 -21	; 1
	80	[803]	CALL     	4 3 2
	81	[804]	GETUPVAL 	5 1	; Geom
	82	[804]	SELF     	5 5 -15	; "new"
	83	[804]	NEWTABLE 	7 0 2
	84	[805]	SETTABLE 	7 -19 -1	; "x" 0
	85	[806]	GETTABLE 	8 4 -6	; "visible_area"
	86	[806]	GETTABLE 	8 8 -10	; "h"
	87	[806]	UNM      	8 8
	88	[806]	ADD      	8 8 3
	89	[806]	SETTABLE 	7 -9 8	; "y" -
	90	[804]	CALL     	5 3 2
	91	[808]	GETTABLE 	6 0 -4	; "view"
	92	[808]	SELF     	7 0 -22	; "genPageStatesFromBottom"
	93	[809]	MOVE     	9 4
	94	[809]	MOVE     	10 2
	95	[809]	MOVE     	11 5
	96	[808]	CALL     	7 5 2
	97	[809]	SETTABLE 	6 -5 7	; "page_states" -
	98	[812]	SELF     	2 0 -23	; "_gotoPage"
	99	[812]	GETTABLE 	4 0 -4	; "view"
	100	[812]	GETTABLE 	4 4 -5	; "page_states"
	101	[812]	GETTABLE 	5 0 -4	; "view"
	102	[812]	GETTABLE 	5 5 -5	; "page_states"
	103	[812]	LEN      	5 5
	104	[812]	GETTABLE 	4 4 5
	105	[812]	GETTABLE 	4 4 -7	; "page"
	106	[812]	LOADK    	5 -24	; "scrolling"
	107	[812]	CALL     	2 4 1
	108	[813]	GETUPVAL 	2 2	; UIManager
	109	[813]	SELF     	2 2 -25	; "setDirty"
	110	[813]	GETTABLE 	4 0 -4	; "view"
	111	[813]	GETTABLE 	4 4 -26	; "dialog"
	112	[813]	LOADK    	5 -27	; "partial"
	113	[813]	CALL     	2 4 1
	114	[814]	LOADBOOL 	2 1 0
	115	[814]	RETURN   	2 2
	116	[815]	RETURN   	0 1

function <./frontend/apps/reader/modules/readerpaging.lua:817,967> (342 instructions, 1368 bytes at 0x7ffb2d416350)
2 params, 12 slots, 3 upvalues, 11 locals, 38 constants, 0 functions
	1	[818]	GETUPVAL 	2 0	; logger
	2	[818]	GETTABLE 	2 2 -1	; "dbg"
	3	[818]	LOADK    	3 -2	; "goto relative page:"
	4	[818]	MOVE     	4 1
	5	[818]	CALL     	2 3 1
	6	[819]	GETTABLE 	2 0 -3	; "visible_area"
	7	[819]	SELF     	2 2 -4	; "copy"
	8	[819]	CALL     	2 2 2
	9	[820]	LOADK    	3 -5	; 0
	10	[820]	LOADK    	4 -5	; 0
	11	[822]	GETTABLE 	5 0 -6	; "zoom_mode"
	12	[822]	SELF     	5 5 -7	; "find"
	13	[822]	LOADK    	7 -8	; "width"
	14	[822]	CALL     	5 3 2
	15	[822]	TEST     	5 0 0
	16	[822]	JMP      	4	; to 21
	17	[823]	GETTABLE 	5 0 -3	; "visible_area"
	18	[823]	GETTABLE 	5 5 -9	; "h"
	19	[823]	MUL      	4 5 1
	20	[823]	JMP      	146	; to 167
	21	[824]	GETTABLE 	5 0 -6	; "zoom_mode"
	22	[824]	SELF     	5 5 -7	; "find"
	23	[824]	LOADK    	7 -10	; "height"
	24	[824]	CALL     	5 3 2
	25	[824]	TEST     	5 0 0
	26	[824]	JMP      	15	; to 42
	27	[826]	GETTABLE 	5 0 -11	; "ui"
	28	[826]	GETTABLE 	5 5 -12	; "document"
	29	[826]	GETTABLE 	5 5 -13	; "configurable"
	30	[826]	GETTABLE 	5 5 -14	; "writing_direction"
	31	[827]	GETTABLE 	6 0 -3	; "visible_area"
	32	[827]	GETTABLE 	6 6 -15	; "w"
	33	[827]	MUL      	6 6 1
	34	[827]	EQ       	0 5 -16	; - 1
	35	[827]	JMP      	3	; to 39
	36	[827]	LOADK    	7 -17	; -1
	37	[827]	TEST     	7 0 1
	38	[827]	JMP      	1	; to 40
	39	[827]	LOADK    	7 -16	; 1
	40	[827]	MUL      	3 6 7
	41	[827]	JMP      	125	; to 167
	42	[828]	GETTABLE 	5 0 -6	; "zoom_mode"
	43	[828]	SELF     	5 5 -7	; "find"
	44	[828]	LOADK    	7 -18	; "column"
	45	[828]	CALL     	5 3 2
	46	[828]	TEST     	5 0 0
	47	[828]	JMP      	103	; to 151
	48	[831]	GETTABLE 	5 0 -3	; "visible_area"
	49	[831]	GETTABLE 	5 5 -9	; "h"
	50	[831]	MUL      	4 5 1
	51	[832]	GETUPVAL 	5 1	; Math
	52	[832]	GETTABLE 	5 5 -19	; "roundAwayFromZero"
	53	[832]	MOVE     	6 4
	54	[832]	CALL     	5 2 2
	55	[832]	MOVE     	4 5
	56	[833]	GETUPVAL 	5 1	; Math
	57	[833]	GETTABLE 	5 5 -19	; "roundAwayFromZero"
	58	[833]	GETTABLE 	6 0 -3	; "visible_area"
	59	[833]	GETTABLE 	6 6 -20	; "x"
	60	[833]	CALL     	5 2 2
	61	[833]	SETTABLE 	2 -20 5	; "x" -
	62	[834]	GETUPVAL 	5 1	; Math
	63	[834]	GETTABLE 	5 5 -19	; "roundAwayFromZero"
	64	[834]	GETTABLE 	6 0 -3	; "visible_area"
	65	[834]	GETTABLE 	6 6 -21	; "y"
	66	[834]	ADD      	6 6 4
	67	[834]	CALL     	5 2 2
	68	[834]	SETTABLE 	2 -21 5	; "y" -
	69	[838]	SELF     	5 2 -22	; "notIntersectWith"
	70	[838]	GETTABLE 	7 0 -23	; "page_area"
	71	[838]	CALL     	5 3 2
	72	[838]	TEST     	5 0 0
	73	[838]	JMP      	93	; to 167
	74	[842]	GETTABLE 	5 0 -3	; "visible_area"
	75	[842]	GETTABLE 	5 5 -15	; "w"
	76	[842]	MUL      	3 5 1
	77	[843]	GETUPVAL 	5 1	; Math
	78	[843]	GETTABLE 	5 5 -19	; "roundAwayFromZero"
	79	[843]	MOVE     	6 3
	80	[843]	CALL     	5 2 2
	81	[843]	MOVE     	3 5
	82	[844]	GETUPVAL 	5 1	; Math
	83	[844]	GETTABLE 	5 5 -19	; "roundAwayFromZero"
	84	[844]	GETTABLE 	6 0 -3	; "visible_area"
	85	[844]	GETTABLE 	6 6 -20	; "x"
	86	[844]	ADD      	6 6 3
	87	[844]	CALL     	5 2 2
	88	[844]	SETTABLE 	2 -20 5	; "x" -
	89	[845]	GETUPVAL 	5 1	; Math
	90	[845]	GETTABLE 	5 5 -19	; "roundAwayFromZero"
	91	[845]	GETTABLE 	6 0 -3	; "visible_area"
	92	[845]	GETTABLE 	6 6 -21	; "y"
	93	[845]	CALL     	5 2 2
	94	[845]	SETTABLE 	2 -21 5	; "y" -
	95	[848]	SELF     	5 2 -22	; "notIntersectWith"
	96	[848]	GETTABLE 	7 0 -23	; "page_area"
	97	[848]	CALL     	5 3 2
	98	[848]	TEST     	5 0 0
	99	[848]	JMP      	29	; to 129
	100	[852]	GETTABLE 	5 0 -24	; "current_page"
	101	[852]	ADD      	5 5 1
	102	[853]	LT       	0 -5 1	; 0 -
	103	[853]	JMP      	12	; to 116
	104	[853]	GETTABLE 	6 0 -25	; "number_of_pages"
	105	[853]	ADD      	6 6 -16	; - 1
	106	[853]	EQ       	0 5 6
	107	[853]	JMP      	8	; to 116
	108	[854]	GETTABLE 	6 0 -11	; "ui"
	109	[854]	SELF     	6 6 -26	; "handleEvent"
	110	[854]	GETUPVAL 	8 2	; Event
	111	[854]	SELF     	8 8 -27	; "new"
	112	[854]	LOADK    	10 -28	; "EndOfBook"
	113	[854]	CALL     	8 3 0
	114	[854]	CALL     	6 0 1
	115	[854]	JMP      	3	; to 119
	116	[856]	SELF     	6 0 -29	; "_gotoPage"
	117	[856]	MOVE     	8 5
	118	[856]	CALL     	6 3 1
	119	[859]	LT       	0 4 -5	; - 0
	120	[859]	JMP      	27	; to 148
	121	[862]	GETTABLE 	6 0 -30	; "view"
	122	[862]	SELF     	6 6 -31	; "PanningUpdate"
	123	[862]	GETTABLE 	8 0 -23	; "page_area"
	124	[862]	GETTABLE 	8 8 -15	; "w"
	125	[862]	GETTABLE 	9 0 -23	; "page_area"
	126	[862]	GETTABLE 	9 9 -9	; "h"
	127	[862]	CALL     	6 4 1
	128	[863]	JMP      	19	; to 148
	129	[869]	LT       	0 -5 1	; 0 -
	130	[869]	JMP      	9	; to 140
	131	[872]	GETTABLE 	5 0 -30	; "view"
	132	[872]	SELF     	5 5 -31	; "PanningUpdate"
	133	[872]	GETTABLE 	7 0 -23	; "page_area"
	134	[872]	GETTABLE 	7 7 -15	; "w"
	135	[872]	GETTABLE 	8 0 -23	; "page_area"
	136	[872]	GETTABLE 	8 8 -9	; "h"
	137	[872]	UNM      	8 8
	138	[872]	CALL     	5 4 1
	139	[872]	JMP      	8	; to 148
	140	[876]	GETTABLE 	5 0 -30	; "view"
	141	[876]	SELF     	5 5 -31	; "PanningUpdate"
	142	[876]	GETTABLE 	7 0 -23	; "page_area"
	143	[876]	GETTABLE 	7 7 -15	; "w"
	144	[876]	UNM      	7 7
	145	[876]	GETTABLE 	8 0 -23	; "page_area"
	146	[876]	GETTABLE 	8 8 -9	; "h"
	147	[876]	CALL     	5 4 1
	148	[881]	LOADBOOL 	5 1 0
	149	[881]	RETURN   	5 2
	150	[882]	JMP      	16	; to 167
	151	[884]	GETTABLE 	5 0 -6	; "zoom_mode"
	152	[884]	EQ       	1 5 -32	; - "free"
	153	[884]	JMP      	13	; to 167
	154	[886]	GETTABLE 	5 0 -3	; "visible_area"
	155	[886]	GETTABLE 	5 5 -15	; "w"
	156	[886]	GETTABLE 	6 0 -23	; "page_area"
	157	[886]	GETTABLE 	6 6 -15	; "w"
	158	[886]	EQ       	0 5 6
	159	[886]	JMP      	4	; to 164
	160	[887]	GETTABLE 	5 0 -3	; "visible_area"
	161	[887]	GETTABLE 	5 5 -9	; "h"
	162	[887]	MUL      	4 5 1
	163	[887]	JMP      	3	; to 167
	164	[889]	GETTABLE 	5 0 -3	; "visible_area"
	165	[889]	GETTABLE 	5 5 -15	; "w"
	166	[889]	MUL      	3 5 1
	167	[895]	GETUPVAL 	5 1	; Math
	168	[895]	GETTABLE 	5 5 -19	; "roundAwayFromZero"
	169	[895]	MOVE     	6 3
	170	[895]	CALL     	5 2 2
	171	[895]	MOVE     	3 5
	172	[896]	GETUPVAL 	5 1	; Math
	173	[896]	GETTABLE 	5 5 -19	; "roundAwayFromZero"
	174	[896]	MOVE     	6 4
	175	[896]	CALL     	5 2 2
	176	[896]	MOVE     	4 5
	177	[897]	GETUPVAL 	5 1	; Math
	178	[897]	GETTABLE 	5 5 -19	; "roundAwayFromZero"
	179	[897]	GETTABLE 	6 0 -3	; "visible_area"
	180	[897]	GETTABLE 	6 6 -20	; "x"
	181	[897]	ADD      	6 6 3
	182	[897]	CALL     	5 2 2
	183	[897]	SETTABLE 	2 -20 5	; "x" -
	184	[898]	GETUPVAL 	5 1	; Math
	185	[898]	GETTABLE 	5 5 -19	; "roundAwayFromZero"
	186	[898]	GETTABLE 	6 0 -3	; "visible_area"
	187	[898]	GETTABLE 	6 6 -21	; "y"
	188	[898]	ADD      	6 6 4
	189	[898]	CALL     	5 2 2
	190	[898]	SETTABLE 	2 -21 5	; "y" -
	191	[900]	SELF     	5 2 -22	; "notIntersectWith"
	192	[900]	GETTABLE 	7 0 -23	; "page_area"
	193	[900]	CALL     	5 3 2
	194	[900]	TEST     	5 0 0
	195	[900]	JMP      	37	; to 233
	196	[902]	GETTABLE 	5 0 -24	; "current_page"
	197	[902]	ADD      	5 5 1
	198	[903]	LT       	0 -5 1	; 0 -
	199	[903]	JMP      	12	; to 212
	200	[903]	GETTABLE 	6 0 -25	; "number_of_pages"
	201	[903]	ADD      	6 6 -16	; - 1
	202	[903]	EQ       	0 5 6
	203	[903]	JMP      	8	; to 212
	204	[904]	GETTABLE 	6 0 -11	; "ui"
	205	[904]	SELF     	6 6 -26	; "handleEvent"
	206	[904]	GETUPVAL 	8 2	; Event
	207	[904]	SELF     	8 8 -27	; "new"
	208	[904]	LOADK    	10 -28	; "EndOfBook"
	209	[904]	CALL     	8 3 0
	210	[904]	CALL     	6 0 1
	211	[904]	JMP      	3	; to 215
	212	[906]	SELF     	6 0 -29	; "_gotoPage"
	213	[906]	MOVE     	8 5
	214	[906]	CALL     	6 3 1
	215	[910]	LT       	0 3 -5	; - 0
	216	[910]	JMP      	7	; to 224
	217	[911]	GETTABLE 	6 0 -30	; "view"
	218	[911]	SELF     	6 6 -31	; "PanningUpdate"
	219	[911]	GETTABLE 	8 0 -23	; "page_area"
	220	[911]	GETTABLE 	8 8 -15	; "w"
	221	[911]	LOADK    	9 -5	; 0
	222	[911]	CALL     	6 4 1
	223	[911]	JMP      	116	; to 340
	224	[912]	LT       	0 4 -5	; - 0
	225	[912]	JMP      	114	; to 340
	226	[913]	GETTABLE 	6 0 -30	; "view"
	227	[913]	SELF     	6 6 -31	; "PanningUpdate"
	228	[913]	LOADK    	8 -5	; 0
	229	[913]	GETTABLE 	9 0 -23	; "page_area"
	230	[913]	GETTABLE 	9 9 -9	; "h"
	231	[913]	CALL     	6 4 1
	232	[914]	JMP      	107	; to 340
	233	[918]	GETTABLE 	5 0 -33	; "overlap"
	234	[919]	LT       	0 5 3
	235	[919]	JMP      	2	; to 238
	236	[921]	SUB      	3 3 5
	237	[921]	JMP      	4	; to 242
	238	[922]	UNM      	6 5
	239	[922]	LT       	0 3 6
	240	[922]	JMP      	1	; to 242
	241	[923]	ADD      	3 3 5
	242	[925]	LT       	0 5 4
	243	[925]	JMP      	2	; to 246
	244	[926]	SUB      	4 4 5
	245	[926]	JMP      	4	; to 250
	246	[927]	UNM      	6 5
	247	[927]	LT       	0 4 6
	248	[927]	JMP      	1	; to 250
	249	[928]	ADD      	4 4 5
	250	[931]	GETUPVAL 	6 1	; Math
	251	[931]	GETTABLE 	6 6 -19	; "roundAwayFromZero"
	252	[931]	GETTABLE 	7 0 -3	; "visible_area"
	253	[931]	GETTABLE 	7 7 -20	; "x"
	254	[931]	ADD      	7 7 3
	255	[931]	CALL     	6 2 2
	256	[931]	SETTABLE 	2 -20 6	; "x" -
	257	[932]	GETUPVAL 	6 1	; Math
	258	[932]	GETTABLE 	6 6 -19	; "roundAwayFromZero"
	259	[932]	GETTABLE 	7 0 -3	; "visible_area"
	260	[932]	GETTABLE 	7 7 -21	; "y"
	261	[932]	ADD      	7 7 4
	262	[932]	CALL     	6 2 2
	263	[932]	SETTABLE 	2 -21 6	; "y" -
	264	[934]	SELF     	6 2 -34	; "offsetWithin"
	265	[934]	GETTABLE 	8 0 -23	; "page_area"
	266	[934]	LOADK    	9 -5	; 0
	267	[934]	LOADK    	10 -5	; 0
	268	[934]	CALL     	6 5 1
	269	[936]	GETTABLE 	6 2 -20	; "x"
	270	[936]	GETTABLE 	7 0 -3	; "visible_area"
	271	[936]	GETTABLE 	7 7 -20	; "x"
	272	[936]	SUB      	6 6 7
	273	[937]	GETTABLE 	7 2 -21	; "y"
	274	[937]	GETTABLE 	8 0 -3	; "visible_area"
	275	[937]	GETTABLE 	8 8 -21	; "y"
	276	[937]	SUB      	7 7 8
	277	[939]	GETGLOBAL	8 -35	; math
	278	[939]	GETTABLE 	8 8 -36	; "abs"
	279	[939]	MOVE     	9 6
	280	[939]	CALL     	8 2 2
	281	[939]	LT       	0 8 -16	; - 1
	282	[939]	JMP      	1	; to 284
	283	[940]	LOADK    	6 -5	; 0
	284	[942]	GETGLOBAL	8 -35	; math
	285	[942]	GETTABLE 	8 8 -36	; "abs"
	286	[942]	MOVE     	9 7
	287	[942]	CALL     	8 2 2
	288	[942]	LT       	0 8 -16	; - 1
	289	[942]	JMP      	1	; to 291
	290	[943]	LOADK    	7 -5	; 0
	291	[946]	GETTABLE 	8 0 -30	; "view"
	292	[946]	SELF     	8 8 -31	; "PanningUpdate"
	293	[946]	MOVE     	10 6
	294	[946]	MOVE     	11 7
	295	[946]	CALL     	8 4 1
	296	[948]	GETTABLE 	8 0 -37	; "show_overlap_enable"
	297	[948]	TEST     	8 0 0
	298	[948]	JMP      	40	; to 339
	299	[949]	GETTABLE 	8 0 -30	; "view"
	300	[949]	GETTABLE 	8 8 -38	; "dim_area"
	301	[949]	GETTABLE 	9 2 -9	; "h"
	302	[949]	GETGLOBAL	10 -35	; math
	303	[949]	GETTABLE 	10 10 -36	; "abs"
	304	[949]	MOVE     	11 7
	305	[949]	CALL     	10 2 2
	306	[949]	SUB      	9 9 10
	307	[949]	SETTABLE 	8 -9 9	; "h" -
	308	[950]	GETTABLE 	8 0 -30	; "view"
	309	[950]	GETTABLE 	8 8 -38	; "dim_area"
	310	[950]	GETTABLE 	9 2 -15	; "w"
	311	[950]	GETGLOBAL	10 -35	; math
	312	[950]	GETTABLE 	10 10 -36	; "abs"
	313	[950]	MOVE     	11 6
	314	[950]	CALL     	10 2 2
	315	[950]	SUB      	9 9 10
	316	[950]	SETTABLE 	8 -15 9	; "w" -
	317	[951]	LT       	0 7 -5	; - 0
	318	[951]	JMP      	6	; to 325
	319	[952]	GETTABLE 	8 0 -30	; "view"
	320	[952]	GETTABLE 	8 8 -38	; "dim_area"
	321	[952]	GETTABLE 	9 2 -21	; "y"
	322	[952]	SUB      	9 9 7
	323	[952]	SETTABLE 	8 -21 9	; "y" -
	324	[952]	JMP      	3	; to 328
	325	[954]	GETTABLE 	8 0 -30	; "view"
	326	[954]	GETTABLE 	8 8 -38	; "dim_area"
	327	[954]	SETTABLE 	8 -21 -5	; "y" 0
	328	[956]	LT       	0 6 -5	; - 0
	329	[956]	JMP      	6	; to 336
	330	[957]	GETTABLE 	8 0 -30	; "view"
	331	[957]	GETTABLE 	8 8 -38	; "dim_area"
	332	[957]	GETTABLE 	9 2 -20	; "x"
	333	[957]	SUB      	9 9 6
	334	[957]	SETTABLE 	8 -20 9	; "x" -
	335	[957]	JMP      	3	; to 339
	336	[959]	GETTABLE 	8 0 -30	; "view"
	337	[959]	GETTABLE 	8 8 -38	; "dim_area"
	338	[959]	SETTABLE 	8 -20 -5	; "x" 0
	339	[963]	SETTABLE 	0 -3 2	; "visible_area" -
	340	[966]	LOADBOOL 	5 1 0
	341	[966]	RETURN   	5 2
	342	[967]	RETURN   	0 1

function <./frontend/apps/reader/modules/readerpaging.lua:969,972> (11 instructions, 44 bytes at 0x7ffb2d417190)
1 param, 7 slots, 1 upvalue, 1 local, 5 constants, 0 functions
	1	[970]	GETTABLE 	1 0 -1	; "ui"
	2	[970]	SELF     	1 1 -2	; "handleEvent"
	3	[970]	GETUPVAL 	3 0	; Event
	4	[970]	SELF     	3 3 -3	; "new"
	5	[970]	LOADK    	5 -4	; "PageUpdate"
	6	[970]	GETTABLE 	6 0 -5	; "current_page"
	7	[970]	CALL     	3 4 0
	8	[970]	CALL     	1 0 1
	9	[971]	LOADBOOL 	1 1 0
	10	[971]	RETURN   	1 2
	11	[972]	RETURN   	0 1

function <./frontend/apps/reader/modules/readerpaging.lua:975,992> (45 instructions, 180 bytes at 0x7ffb2d417860)
3 params, 10 slots, 2 upvalues, 3 locals, 14 constants, 0 functions
	1	[976]	GETTABLE 	3 0 -1	; "current_page"
	2	[976]	EQ       	1 1 3
	3	[976]	JMP      	2	; to 6
	4	[976]	TEST     	1 0 1
	5	[976]	JMP      	6	; to 12
	6	[979]	GETTABLE 	3 0 -2	; "view"
	7	[979]	GETTABLE 	3 3 -3	; "footer"
	8	[979]	SELF     	3 3 -4	; "updateFooter"
	9	[979]	CALL     	3 2 1
	10	[980]	LOADBOOL 	3 1 0
	11	[980]	RETURN   	3 2
	12	[982]	GETTABLE 	3 0 -5	; "number_of_pages"
	13	[982]	LT       	0 3 1
	14	[982]	JMP      	9	; to 24
	15	[983]	GETUPVAL 	3 0	; logger
	16	[983]	GETTABLE 	3 3 -6	; "warn"
	17	[983]	LOADK    	4 -7	; "page number too high: "
	18	[983]	MOVE     	5 1
	19	[983]	LOADK    	6 -8	; "!"
	20	[983]	CONCAT   	4 4 6
	21	[983]	CALL     	3 2 1
	22	[984]	GETTABLE 	1 0 -5	; "number_of_pages"
	23	[984]	JMP      	10	; to 34
	24	[985]	LT       	0 1 -9	; - 1
	25	[985]	JMP      	8	; to 34
	26	[986]	GETUPVAL 	3 0	; logger
	27	[986]	GETTABLE 	3 3 -6	; "warn"
	28	[986]	LOADK    	4 -10	; "page number too low: "
	29	[986]	MOVE     	5 1
	30	[986]	LOADK    	6 -8	; "!"
	31	[986]	CONCAT   	4 4 6
	32	[986]	CALL     	3 2 1
	33	[987]	LOADK    	1 -9	; 1
	34	[990]	GETTABLE 	3 0 -11	; "ui"
	35	[990]	SELF     	3 3 -12	; "handleEvent"
	36	[990]	GETUPVAL 	5 1	; Event
	37	[990]	SELF     	5 5 -13	; "new"
	38	[990]	LOADK    	7 -14	; "PageUpdate"
	39	[990]	MOVE     	8 1
	40	[990]	MOVE     	9 2
	41	[990]	CALL     	5 5 0
	42	[990]	CALL     	3 0 1
	43	[991]	LOADBOOL 	3 1 0
	44	[991]	RETURN   	3 2
	45	[992]	RETURN   	0 1

function <./frontend/apps/reader/modules/readerpaging.lua:994,997> (6 instructions, 24 bytes at 0x7ffb2d4179d0)
2 params, 5 slots, 0 upvalues, 2 locals, 1 constant, 0 functions
	1	[995]	SELF     	2 0 -1	; "_gotoPage"
	2	[995]	MOVE     	4 1
	3	[995]	CALL     	2 3 1
	4	[996]	LOADBOOL 	2 1 0
	5	[996]	RETURN   	2 2
	6	[997]	RETURN   	0 1

function <./frontend/apps/reader/modules/readerpaging.lua:999,1002> (7 instructions, 28 bytes at 0x7ffb2d417c50)
2 params, 5 slots, 0 upvalues, 2 locals, 2 constants, 0 functions
	1	[1000]	SELF     	2 0 -1	; "_gotoPage"
	2	[1000]	GETTABLE 	4 0 -2	; "current_page"
	3	[1000]	ADD      	4 4 1
	4	[1000]	CALL     	2 3 1
	5	[1001]	LOADBOOL 	2 1 0
	6	[1001]	RETURN   	2 2
	7	[1002]	RETURN   	0 1

function <./frontend/apps/reader/modules/readerpaging.lua:1004,1009> (16 instructions, 64 bytes at 0x7ffb2d417fb0)
2 params, 6 slots, 0 upvalues, 2 locals, 6 constants, 0 functions
	1	[1005]	LT       	0 1 -1	; - 0
	2	[1005]	JMP      	1	; to 4
	3	[1005]	LOADK    	1 -1	; 0
	4	[1006]	LT       	0 -2 1	; 1 -
	5	[1006]	JMP      	1	; to 7
	6	[1006]	LOADK    	1 -2	; 1
	7	[1007]	SELF     	2 0 -3	; "_gotoPage"
	8	[1007]	GETGLOBAL	4 -4	; math
	9	[1007]	GETTABLE 	4 4 -5	; "floor"
	10	[1007]	GETTABLE 	5 0 -6	; "number_of_pages"
	11	[1007]	MUL      	5 1 5
	12	[1007]	CALL     	4 2 0
	13	[1007]	CALL     	2 0 1
	14	[1008]	LOADBOOL 	2 1 0
	15	[1008]	RETURN   	2 2
	16	[1009]	RETURN   	0 1

function <./frontend/apps/reader/modules/readerpaging.lua:1013,1021> (19 instructions, 76 bytes at 0x7ffb2d418380)
1 param, 6 slots, 0 upvalues, 3 locals, 8 constants, 0 functions
	1	[1014]	GETTABLE 	1 0 -1	; "current_page"
	2	[1015]	GETTABLE 	2 0 -2	; "ui"
	3	[1015]	GETTABLE 	2 2 -3	; "toc"
	4	[1015]	SELF     	2 2 -4	; "getNextChapter"
	5	[1015]	MOVE     	4 1
	6	[1015]	LOADK    	5 -5	; 0
	7	[1015]	CALL     	2 4 2
	8	[1016]	TEST     	2 0 0
	9	[1016]	JMP      	7	; to 17
	10	[1017]	GETTABLE 	3 0 -2	; "ui"
	11	[1017]	GETTABLE 	3 3 -6	; "link"
	12	[1017]	SELF     	3 3 -7	; "addCurrentLocationToStack"
	13	[1017]	CALL     	3 2 1
	14	[1018]	SELF     	3 0 -8	; "onGotoPage"
	15	[1018]	MOVE     	5 2
	16	[1018]	CALL     	3 3 1
	17	[1020]	LOADBOOL 	3 1 0
	18	[1020]	RETURN   	3 2
	19	[1021]	RETURN   	0 1

function <./frontend/apps/reader/modules/readerpaging.lua:1023,1031> (19 instructions, 76 bytes at 0x7ffb2d411210)
1 param, 6 slots, 0 upvalues, 3 locals, 8 constants, 0 functions
	1	[1024]	GETTABLE 	1 0 -1	; "current_page"
	2	[1025]	GETTABLE 	2 0 -2	; "ui"
	3	[1025]	GETTABLE 	2 2 -3	; "toc"
	4	[1025]	SELF     	2 2 -4	; "getPreviousChapter"
	5	[1025]	MOVE     	4 1
	6	[1025]	LOADK    	5 -5	; 0
	7	[1025]	CALL     	2 4 2
	8	[1026]	TEST     	2 0 0
	9	[1026]	JMP      	7	; to 17
	10	[1027]	GETTABLE 	3 0 -2	; "ui"
	11	[1027]	GETTABLE 	3 3 -6	; "link"
	12	[1027]	SELF     	3 3 -7	; "addCurrentLocationToStack"
	13	[1027]	CALL     	3 2 1
	14	[1028]	SELF     	3 0 -8	; "onGotoPage"
	15	[1028]	MOVE     	5 2
	16	[1028]	CALL     	3 3 1
	17	[1030]	LOADBOOL 	3 1 0
	18	[1030]	RETURN   	3 2
	19	[1031]	RETURN   	0 1
