
main <./frontend/apps/reader/modules/readertypography.lua:0,0> (659 instructions, 2636 bytes at 0x7faa78406900)
0+ params, 53 slots, 0 upvalues, 33 locals, 163 constants, 8 functions
	1	[1]	GETGLOBAL	0 -1	; require
	2	[1]	LOADK    	1 -2	; "ui/bidi"
	3	[1]	CALL     	0 2 2
	4	[2]	GETGLOBAL	1 -1	; require
	5	[2]	LOADK    	2 -3	; "device"
	6	[2]	CALL     	1 2 2
	7	[3]	GETGLOBAL	2 -1	; require
	8	[3]	LOADK    	3 -4	; "ui/event"
	9	[3]	CALL     	2 2 2
	10	[4]	GETGLOBAL	3 -1	; require
	11	[4]	LOADK    	4 -5	; "ui/widget/infomessage"
	12	[4]	CALL     	3 2 2
	13	[5]	GETGLOBAL	4 -1	; require
	14	[5]	LOADK    	5 -6	; "ui/widget/container/inputcontainer"
	15	[5]	CALL     	4 2 2
	16	[6]	GETGLOBAL	5 -1	; require
	17	[6]	LOADK    	6 -7	; "ui/widget/multiconfirmbox"
	18	[6]	CALL     	5 2 2
	19	[7]	GETGLOBAL	6 -1	; require
	20	[7]	LOADK    	7 -8	; "ui/uimanager"
	21	[7]	CALL     	6 2 2
	22	[8]	GETGLOBAL	7 -1	; require
	23	[8]	LOADK    	8 -9	; "logger"
	24	[8]	CALL     	7 2 2
	25	[9]	GETGLOBAL	8 -1	; require
	26	[9]	LOADK    	9 -10	; "util"
	27	[9]	CALL     	8 2 2
	28	[10]	GETGLOBAL	9 -1	; require
	29	[10]	LOADK    	10 -11	; "gettext"
	30	[10]	CALL     	9 2 2
	31	[11]	GETTABLE 	10 9 -12	; "pgettext"
	32	[12]	GETGLOBAL	11 -1	; require
	33	[12]	LOADK    	12 -13	; "ffi/util"
	34	[12]	CALL     	11 2 2
	35	[12]	GETTABLE 	11 11 -14	; "template"
	36	[13]	GETTABLE 	12 1 -15	; "screen"
	37	[17]	NEWTABLE 	13 0 24
	38	[18]	NEWTABLE 	14 2 0
	39	[18]	LOADK    	15 -16	; "@none"
	40	[18]	LOADK    	16 -17	; "en"
	41	[18]	SETLIST  	14 2 1	; 1
	42	[18]	SETTABLE 	13 -16 14	; "@none" -
	43	[19]	NEWTABLE 	14 2 0
	44	[19]	LOADK    	15 -18	; "@softhyphens"
	45	[19]	LOADK    	16 -17	; "en"
	46	[19]	SETLIST  	14 2 1	; 1
	47	[19]	SETTABLE 	13 -18 14	; "@softhyphens" -
	48	[20]	NEWTABLE 	14 2 0
	49	[20]	LOADK    	15 -19	; "@algorithm"
	50	[20]	LOADK    	16 -17	; "en"
	51	[20]	SETLIST  	14 2 1	; 1
	52	[20]	SETTABLE 	13 -19 14	; "@algorithm" -
	53	[21]	NEWTABLE 	14 2 0
	54	[21]	MOVE     	15 9
	55	[21]	LOADK    	16 -21	; "Bulgarian"
	56	[21]	CALL     	15 2 2
	57	[21]	LOADK    	16 -22	; "bg"
	58	[21]	SETLIST  	14 2 1	; 1
	59	[21]	SETTABLE 	13 -20 14	; "Bulgarian.pattern" -
	60	[22]	NEWTABLE 	14 2 0
	61	[22]	MOVE     	15 9
	62	[22]	LOADK    	16 -24	; "Catalan"
	63	[22]	CALL     	15 2 2
	64	[22]	LOADK    	16 -25	; "ca"
	65	[22]	SETLIST  	14 2 1	; 1
	66	[22]	SETTABLE 	13 -23 14	; "Catalan.pattern" -
	67	[23]	NEWTABLE 	14 2 0
	68	[23]	MOVE     	15 9
	69	[23]	LOADK    	16 -27	; "Czech"
	70	[23]	CALL     	15 2 2
	71	[23]	LOADK    	16 -28	; "cs"
	72	[23]	SETLIST  	14 2 1	; 1
	73	[23]	SETTABLE 	13 -26 14	; "Czech.pattern" -
	74	[24]	NEWTABLE 	14 2 0
	75	[24]	MOVE     	15 9
	76	[24]	LOADK    	16 -30	; "Danish"
	77	[24]	CALL     	15 2 2
	78	[24]	LOADK    	16 -31	; "da"
	79	[24]	SETLIST  	14 2 1	; 1
	80	[24]	SETTABLE 	13 -29 14	; "Danish.pattern" -
	81	[25]	NEWTABLE 	14 2 0
	82	[25]	MOVE     	15 9
	83	[25]	LOADK    	16 -33	; "Dutch"
	84	[25]	CALL     	15 2 2
	85	[25]	LOADK    	16 -34	; "nl"
	86	[25]	SETLIST  	14 2 1	; 1
	87	[25]	SETTABLE 	13 -32 14	; "Dutch.pattern" -
	88	[26]	NEWTABLE 	14 2 0
	89	[26]	MOVE     	15 9
	90	[26]	LOADK    	16 -36	; "English (UK)"
	91	[26]	CALL     	15 2 2
	92	[26]	LOADK    	16 -37	; "en-GB"
	93	[26]	SETLIST  	14 2 1	; 1
	94	[26]	SETTABLE 	13 -35 14	; "English_GB.pattern" -
	95	[27]	NEWTABLE 	14 2 0
	96	[27]	MOVE     	15 9
	97	[27]	LOADK    	16 -39	; "English (US)"
	98	[27]	CALL     	15 2 2
	99	[27]	LOADK    	16 -40	; "en-US"
	100	[27]	SETLIST  	14 2 1	; 1
	101	[27]	SETTABLE 	13 -38 14	; "English_US.pattern" -
	102	[28]	NEWTABLE 	14 2 0
	103	[28]	MOVE     	15 9
	104	[28]	LOADK    	16 -42	; "Finnish"
	105	[28]	CALL     	15 2 2
	106	[28]	LOADK    	16 -43	; "fi"
	107	[28]	SETLIST  	14 2 1	; 1
	108	[28]	SETTABLE 	13 -41 14	; "Finnish.pattern" -
	109	[29]	NEWTABLE 	14 4 0
	110	[29]	MOVE     	15 9
	111	[29]	LOADK    	16 -45	; "French"
	112	[29]	CALL     	15 2 2
	113	[29]	LOADK    	16 -46	; "fr"
	114	[29]	LOADK    	17 -47	; 2
	115	[29]	LOADK    	18 -48	; 1
	116	[29]	SETLIST  	14 4 1	; 1
	117	[29]	SETTABLE 	13 -44 14	; "French.pattern" -
	118	[30]	NEWTABLE 	14 2 0
	119	[30]	MOVE     	15 9
	120	[30]	LOADK    	16 -50	; "Galician"
	121	[30]	CALL     	15 2 2
	122	[30]	LOADK    	16 -51	; "gl"
	123	[30]	SETLIST  	14 2 1	; 1
	124	[30]	SETTABLE 	13 -49 14	; "Galician.pattern" -
	125	[31]	NEWTABLE 	14 2 0
	126	[31]	MOVE     	15 9
	127	[31]	LOADK    	16 -53	; "German"
	128	[31]	CALL     	15 2 2
	129	[31]	LOADK    	16 -54	; "de"
	130	[31]	SETLIST  	14 2 1	; 1
	131	[31]	SETTABLE 	13 -52 14	; "German.pattern" -
	132	[32]	NEWTABLE 	14 2 0
	133	[32]	MOVE     	15 9
	134	[32]	LOADK    	16 -56	; "Greek"
	135	[32]	CALL     	15 2 2
	136	[32]	LOADK    	16 -57	; "el"
	137	[32]	SETLIST  	14 2 1	; 1
	138	[32]	SETTABLE 	13 -55 14	; "Greek.pattern" -
	139	[33]	NEWTABLE 	14 2 0
	140	[33]	MOVE     	15 9
	141	[33]	LOADK    	16 -59	; "Hungarian"
	142	[33]	CALL     	15 2 2
	143	[33]	LOADK    	16 -60	; "hu"
	144	[33]	SETLIST  	14 2 1	; 1
	145	[33]	SETTABLE 	13 -58 14	; "Hungarian.pattern" -
	146	[34]	NEWTABLE 	14 2 0
	147	[34]	MOVE     	15 9
	148	[34]	LOADK    	16 -62	; "Icelandic"
	149	[34]	CALL     	15 2 2
	150	[34]	LOADK    	16 -63	; "is"
	151	[34]	SETLIST  	14 2 1	; 1
	152	[34]	SETTABLE 	13 -61 14	; "Icelandic.pattern" -
	153	[35]	NEWTABLE 	14 2 0
	154	[35]	MOVE     	15 9
	155	[35]	LOADK    	16 -65	; "Irish"
	156	[35]	CALL     	15 2 2
	157	[35]	LOADK    	16 -66	; "ga"
	158	[35]	SETLIST  	14 2 1	; 1
	159	[35]	SETTABLE 	13 -64 14	; "Irish.pattern" -
	160	[36]	NEWTABLE 	14 2 0
	161	[36]	MOVE     	15 9
	162	[36]	LOADK    	16 -68	; "Italian"
	163	[36]	CALL     	15 2 2
	164	[36]	LOADK    	16 -69	; "it"
	165	[36]	SETLIST  	14 2 1	; 1
	166	[36]	SETTABLE 	13 -67 14	; "Italian.pattern" -
	167	[37]	NEWTABLE 	14 2 0
	168	[37]	MOVE     	15 9
	169	[37]	LOADK    	16 -71	; "Norwegian"
	170	[37]	CALL     	15 2 2
	171	[37]	LOADK    	16 -72	; "no"
	172	[37]	SETLIST  	14 2 1	; 1
	173	[37]	SETTABLE 	13 -70 14	; "Norwegian.pattern" -
	174	[38]	NEWTABLE 	14 2 0
	175	[38]	MOVE     	15 9
	176	[38]	LOADK    	16 -74	; "Polish"
	177	[38]	CALL     	15 2 2
	178	[38]	LOADK    	16 -75	; "pl"
	179	[38]	SETLIST  	14 2 1	; 1
	180	[38]	SETTABLE 	13 -73 14	; "Polish.pattern" -
	181	[39]	NEWTABLE 	14 2 0
	182	[39]	MOVE     	15 9
	183	[39]	LOADK    	16 -77	; "Portuguese"
	184	[39]	CALL     	15 2 2
	185	[39]	LOADK    	16 -78	; "pt"
	186	[39]	SETLIST  	14 2 1	; 1
	187	[39]	SETTABLE 	13 -76 14	; "Portuguese.pattern" -
	188	[40]	NEWTABLE 	14 2 0
	189	[40]	MOVE     	15 9
	190	[40]	LOADK    	16 -80	; "Romanian"
	191	[40]	CALL     	15 2 2
	192	[40]	LOADK    	16 -81	; "ro"
	193	[40]	SETLIST  	14 2 1	; 1
	194	[40]	SETTABLE 	13 -79 14	; "Roman.pattern" -
	195	[41]	NEWTABLE 	14 2 0
	196	[41]	MOVE     	15 9
	197	[41]	LOADK    	16 -83	; "Russian + English (UK)"
	198	[41]	CALL     	15 2 2
	199	[41]	LOADK    	16 -84	; "ru-GB"
	200	[41]	SETLIST  	14 2 1	; 1
	201	[41]	SETTABLE 	13 -82 14	; "Russian_EnGB.pattern" -
	202	[42]	NEWTABLE 	14 2 0
	203	[42]	MOVE     	15 9
	204	[42]	LOADK    	16 -86	; "Russian + English (US)"
	205	[42]	CALL     	15 2 2
	206	[42]	LOADK    	16 -87	; "ru-US"
	207	[42]	SETLIST  	14 2 1	; 1
	208	[42]	SETTABLE 	13 -85 14	; "Russian_EnUS.pattern" -
	209	[43]	NEWTABLE 	14 2 0
	210	[43]	MOVE     	15 9
	211	[43]	LOADK    	16 -89	; "Russian"
	212	[43]	CALL     	15 2 2
	213	[43]	LOADK    	16 -90	; "ru"
	214	[43]	SETLIST  	14 2 1	; 1
	215	[43]	SETTABLE 	13 -88 14	; "Russian.pattern" -
	216	[44]	NEWTABLE 	14 2 0
	217	[44]	MOVE     	15 9
	218	[44]	LOADK    	16 -92	; "Slovak"
	219	[44]	CALL     	15 2 2
	220	[44]	LOADK    	16 -93	; "sk"
	221	[44]	SETLIST  	14 2 1	; 1
	222	[44]	SETTABLE 	13 -91 14	; "Slovak.pattern" -
	223	[45]	NEWTABLE 	14 2 0
	224	[45]	MOVE     	15 9
	225	[45]	LOADK    	16 -95	; "Slovenian"
	226	[45]	CALL     	15 2 2
	227	[45]	LOADK    	16 -96	; "sl"
	228	[45]	SETLIST  	14 2 1	; 1
	229	[45]	SETTABLE 	13 -94 14	; "Slovenian.pattern" -
	230	[46]	NEWTABLE 	14 2 0
	231	[46]	MOVE     	15 9
	232	[46]	LOADK    	16 -98	; "Spanish"
	233	[46]	CALL     	15 2 2
	234	[46]	LOADK    	16 -99	; "es"
	235	[46]	SETLIST  	14 2 1	; 1
	236	[46]	SETTABLE 	13 -97 14	; "Spanish.pattern" -
	237	[47]	NEWTABLE 	14 2 0
	238	[47]	MOVE     	15 9
	239	[47]	LOADK    	16 -101	; "Swedish"
	240	[47]	CALL     	15 2 2
	241	[47]	LOADK    	16 -102	; "sv"
	242	[47]	SETLIST  	14 2 1	; 1
	243	[47]	SETTABLE 	13 -100 14	; "Swedish.pattern" -
	244	[48]	NEWTABLE 	14 2 0
	245	[48]	MOVE     	15 9
	246	[48]	LOADK    	16 -104	; "Turkish"
	247	[48]	CALL     	15 2 2
	248	[48]	LOADK    	16 -105	; "tr"
	249	[48]	SETLIST  	14 2 1	; 1
	250	[48]	SETTABLE 	13 -103 14	; "Turkish.pattern" -
	251	[49]	NEWTABLE 	14 2 0
	252	[49]	MOVE     	15 9
	253	[49]	LOADK    	16 -107	; "Ukrainian"
	254	[49]	CALL     	15 2 2
	255	[49]	LOADK    	16 -108	; "uk"
	256	[49]	SETLIST  	14 2 1	; 1
	257	[49]	SETTABLE 	13 -106 14	; "Ukrain.pattern" -
	258	[60]	NEWTABLE 	14 25 0
	259	[60]	NEWTABLE 	15 3 0
	260	[62]	LOADK    	16 -22	; "bg"
	261	[62]	NEWTABLE 	17 1 0
	262	[62]	LOADK    	18 -109	; "bul"
	263	[62]	SETLIST  	17 1 1	; 1
	264	[62]	LOADK    	18 -110	; "H   "
	265	[62]	MOVE     	19 9
	266	[62]	LOADK    	20 -21	; "Bulgarian"
	267	[62]	CALL     	19 2 0
	268	[62]	SETLIST  	15 0 1	; 1
	269	[62]	NEWTABLE 	16 3 0
	270	[63]	LOADK    	17 -25	; "ca"
	271	[63]	NEWTABLE 	18 1 0
	272	[63]	LOADK    	19 -111	; "cat"
	273	[63]	SETLIST  	18 1 1	; 1
	274	[63]	LOADK    	19 -110	; "H   "
	275	[63]	MOVE     	20 9
	276	[63]	LOADK    	21 -24	; "Catalan"
	277	[63]	CALL     	20 2 0
	278	[63]	SETLIST  	16 0 1	; 1
	279	[63]	NEWTABLE 	17 3 0
	280	[64]	LOADK    	18 -112	; "zh-CN"
	281	[64]	NEWTABLE 	19 2 0
	282	[64]	LOADK    	20 -113	; "zh"
	283	[64]	LOADK    	21 -114	; "zh-Hans"
	284	[64]	SETLIST  	19 2 1	; 1
	285	[64]	LOADK    	20 -115	; " b  "
	286	[64]	MOVE     	21 9
	287	[64]	LOADK    	22 -116	; "Chinese (Simplified)"
	288	[64]	CALL     	21 2 0
	289	[64]	SETLIST  	17 0 1	; 1
	290	[64]	NEWTABLE 	18 3 0
	291	[65]	LOADK    	19 -117	; "zh-TW"
	292	[65]	NEWTABLE 	20 1 0
	293	[65]	LOADK    	21 -118	; "zh-Hant"
	294	[65]	SETLIST  	20 1 1	; 1
	295	[65]	LOADK    	21 -115	; " b  "
	296	[65]	MOVE     	22 9
	297	[65]	LOADK    	23 -119	; "Chinese (Traditional)"
	298	[65]	CALL     	22 2 0
	299	[65]	SETLIST  	18 0 1	; 1
	300	[65]	NEWTABLE 	19 3 0
	301	[66]	LOADK    	20 -28	; "cs"
	302	[66]	NEWTABLE 	21 1 0
	303	[66]	LOADK    	22 -120	; "ces"
	304	[66]	SETLIST  	21 1 1	; 1
	305	[66]	LOADK    	22 -121	; "HB  "
	306	[66]	MOVE     	23 9
	307	[66]	LOADK    	24 -27	; "Czech"
	308	[66]	CALL     	23 2 0
	309	[66]	SETLIST  	19 0 1	; 1
	310	[66]	NEWTABLE 	20 3 0
	311	[67]	LOADK    	21 -31	; "da"
	312	[67]	NEWTABLE 	22 1 0
	313	[67]	LOADK    	23 -122	; "dan"
	314	[67]	SETLIST  	22 1 1	; 1
	315	[67]	LOADK    	23 -110	; "H   "
	316	[67]	MOVE     	24 9
	317	[67]	LOADK    	25 -30	; "Danish"
	318	[67]	CALL     	24 2 0
	319	[67]	SETLIST  	20 0 1	; 1
	320	[67]	NEWTABLE 	21 3 0
	321	[68]	LOADK    	22 -34	; "nl"
	322	[68]	NEWTABLE 	23 1 0
	323	[68]	LOADK    	24 -123	; "nld"
	324	[68]	SETLIST  	23 1 1	; 1
	325	[68]	LOADK    	24 -110	; "H   "
	326	[68]	MOVE     	25 9
	327	[68]	LOADK    	26 -33	; "Dutch"
	328	[68]	CALL     	25 2 0
	329	[68]	SETLIST  	21 0 1	; 1
	330	[68]	NEWTABLE 	22 3 0
	331	[69]	LOADK    	23 -37	; "en-GB"
	332	[69]	NEWTABLE 	24 0 0
	333	[69]	LOADK    	25 -124	; "Hb  "
	334	[69]	MOVE     	26 9
	335	[69]	LOADK    	27 -36	; "English (UK)"
	336	[69]	CALL     	26 2 0
	337	[69]	SETLIST  	22 0 1	; 1
	338	[69]	NEWTABLE 	23 3 0
	339	[70]	LOADK    	24 -40	; "en-US"
	340	[70]	NEWTABLE 	25 2 0
	341	[70]	LOADK    	26 -17	; "en"
	342	[70]	LOADK    	27 -125	; "eng"
	343	[70]	SETLIST  	25 2 1	; 1
	344	[70]	LOADK    	26 -124	; "Hb  "
	345	[70]	MOVE     	27 9
	346	[70]	LOADK    	28 -39	; "English (US)"
	347	[70]	CALL     	27 2 0
	348	[70]	SETLIST  	23 0 1	; 1
	349	[70]	NEWTABLE 	24 3 0
	350	[71]	LOADK    	25 -43	; "fi"
	351	[71]	NEWTABLE 	26 1 0
	352	[71]	LOADK    	27 -126	; "fin"
	353	[71]	SETLIST  	26 1 1	; 1
	354	[71]	LOADK    	27 -110	; "H   "
	355	[71]	MOVE     	28 9
	356	[71]	LOADK    	29 -42	; "Finnish"
	357	[71]	CALL     	28 2 0
	358	[71]	SETLIST  	24 0 1	; 1
	359	[71]	NEWTABLE 	25 3 0
	360	[72]	LOADK    	26 -46	; "fr"
	361	[72]	NEWTABLE 	27 2 0
	362	[72]	LOADK    	28 -127	; "fra"
	363	[72]	LOADK    	29 -128	; "fre"
	364	[72]	SETLIST  	27 2 1	; 1
	365	[72]	LOADK    	28 -124	; "Hb  "
	366	[72]	MOVE     	29 9
	367	[72]	LOADK    	30 -45	; "French"
	368	[72]	CALL     	29 2 0
	369	[72]	SETLIST  	25 0 1	; 1
	370	[72]	NEWTABLE 	26 3 0
	371	[73]	LOADK    	27 -51	; "gl"
	372	[73]	NEWTABLE 	28 1 0
	373	[73]	LOADK    	29 -129	; "glg"
	374	[73]	SETLIST  	28 1 1	; 1
	375	[73]	LOADK    	29 -110	; "H   "
	376	[73]	MOVE     	30 9
	377	[73]	LOADK    	31 -50	; "Galician"
	378	[73]	CALL     	30 2 0
	379	[73]	SETLIST  	26 0 1	; 1
	380	[73]	NEWTABLE 	27 3 0
	381	[74]	LOADK    	28 -54	; "de"
	382	[74]	NEWTABLE 	29 1 0
	383	[74]	LOADK    	30 -130	; "deu"
	384	[74]	SETLIST  	29 1 1	; 1
	385	[74]	LOADK    	30 -124	; "Hb  "
	386	[74]	MOVE     	31 9
	387	[74]	LOADK    	32 -53	; "German"
	388	[74]	CALL     	31 2 0
	389	[74]	SETLIST  	27 0 1	; 1
	390	[74]	NEWTABLE 	28 3 0
	391	[75]	LOADK    	29 -57	; "el"
	392	[75]	NEWTABLE 	30 1 0
	393	[75]	LOADK    	31 -131	; "ell"
	394	[75]	SETLIST  	30 1 1	; 1
	395	[75]	LOADK    	31 -110	; "H   "
	396	[75]	MOVE     	32 9
	397	[75]	LOADK    	33 -56	; "Greek"
	398	[75]	CALL     	32 2 0
	399	[75]	SETLIST  	28 0 1	; 1
	400	[75]	NEWTABLE 	29 3 0
	401	[76]	LOADK    	30 -60	; "hu"
	402	[76]	NEWTABLE 	31 1 0
	403	[76]	LOADK    	32 -132	; "hun"
	404	[76]	SETLIST  	31 1 1	; 1
	405	[76]	LOADK    	32 -110	; "H   "
	406	[76]	MOVE     	33 9
	407	[76]	LOADK    	34 -59	; "Hungarian"
	408	[76]	CALL     	33 2 0
	409	[76]	SETLIST  	29 0 1	; 1
	410	[76]	NEWTABLE 	30 3 0
	411	[77]	LOADK    	31 -63	; "is"
	412	[77]	NEWTABLE 	32 1 0
	413	[77]	LOADK    	33 -133	; "isl"
	414	[77]	SETLIST  	32 1 1	; 1
	415	[77]	LOADK    	33 -110	; "H   "
	416	[77]	MOVE     	34 9
	417	[77]	LOADK    	35 -62	; "Icelandic"
	418	[77]	CALL     	34 2 0
	419	[77]	SETLIST  	30 0 1	; 1
	420	[77]	NEWTABLE 	31 3 0
	421	[78]	LOADK    	32 -66	; "ga"
	422	[78]	NEWTABLE 	33 1 0
	423	[78]	LOADK    	34 -134	; "gle"
	424	[78]	SETLIST  	33 1 1	; 1
	425	[78]	LOADK    	34 -110	; "H   "
	426	[78]	MOVE     	35 9
	427	[78]	LOADK    	36 -65	; "Irish"
	428	[78]	CALL     	35 2 0
	429	[78]	SETLIST  	31 0 1	; 1
	430	[78]	NEWTABLE 	32 3 0
	431	[79]	LOADK    	33 -69	; "it"
	432	[79]	NEWTABLE 	34 1 0
	433	[79]	LOADK    	35 -135	; "ita"
	434	[79]	SETLIST  	34 1 1	; 1
	435	[79]	LOADK    	35 -110	; "H   "
	436	[79]	MOVE     	36 9
	437	[79]	LOADK    	37 -68	; "Italian"
	438	[79]	CALL     	36 2 0
	439	[79]	SETLIST  	32 0 1	; 1
	440	[79]	NEWTABLE 	33 3 0
	441	[80]	LOADK    	34 -136	; "ja"
	442	[80]	NEWTABLE 	35 0 0
	443	[80]	LOADK    	36 -137	; "    "
	444	[80]	MOVE     	37 9
	445	[80]	LOADK    	38 -138	; "Japanese"
	446	[80]	CALL     	37 2 0
	447	[80]	SETLIST  	33 0 1	; 1
	448	[80]	NEWTABLE 	34 3 0
	449	[81]	LOADK    	35 -139	; "ko"
	450	[81]	NEWTABLE 	36 0 0
	451	[81]	LOADK    	37 -137	; "    "
	452	[81]	MOVE     	38 9
	453	[81]	LOADK    	39 -140	; "Korean"
	454	[81]	CALL     	38 2 0
	455	[81]	SETLIST  	34 0 1	; 1
	456	[81]	NEWTABLE 	35 3 0
	457	[82]	LOADK    	36 -72	; "no"
	458	[82]	NEWTABLE 	37 1 0
	459	[82]	LOADK    	38 -141	; "nor"
	460	[82]	SETLIST  	37 1 1	; 1
	461	[82]	LOADK    	38 -110	; "H   "
	462	[82]	MOVE     	39 9
	463	[82]	LOADK    	40 -71	; "Norwegian"
	464	[82]	CALL     	39 2 0
	465	[82]	SETLIST  	35 0 1	; 1
	466	[82]	NEWTABLE 	36 3 0
	467	[83]	LOADK    	37 -75	; "pl"
	468	[83]	NEWTABLE 	38 1 0
	469	[83]	LOADK    	39 -142	; "pol"
	470	[83]	SETLIST  	38 1 1	; 1
	471	[83]	LOADK    	39 -121	; "HB  "
	472	[83]	MOVE     	40 9
	473	[83]	LOADK    	41 -74	; "Polish"
	474	[83]	CALL     	40 2 0
	475	[83]	SETLIST  	36 0 1	; 1
	476	[83]	NEWTABLE 	37 3 0
	477	[84]	LOADK    	38 -78	; "pt"
	478	[84]	NEWTABLE 	39 1 0
	479	[84]	LOADK    	40 -143	; "por"
	480	[84]	SETLIST  	39 1 1	; 1
	481	[84]	LOADK    	40 -121	; "HB  "
	482	[84]	MOVE     	41 9
	483	[84]	LOADK    	42 -77	; "Portuguese"
	484	[84]	CALL     	41 2 0
	485	[84]	SETLIST  	37 0 1	; 1
	486	[84]	NEWTABLE 	38 3 0
	487	[85]	LOADK    	39 -81	; "ro"
	488	[85]	NEWTABLE 	40 1 0
	489	[85]	LOADK    	41 -144	; "ron"
	490	[85]	SETLIST  	40 1 1	; 1
	491	[85]	LOADK    	41 -110	; "H   "
	492	[85]	MOVE     	42 9
	493	[85]	LOADK    	43 -80	; "Romanian"
	494	[85]	CALL     	42 2 0
	495	[85]	SETLIST  	38 0 1	; 1
	496	[85]	NEWTABLE 	39 3 0
	497	[86]	LOADK    	40 -84	; "ru-GB"
	498	[86]	NEWTABLE 	41 0 0
	499	[86]	LOADK    	42 -124	; "Hb  "
	500	[86]	MOVE     	43 9
	501	[86]	LOADK    	44 -83	; "Russian + English (UK)"
	502	[86]	CALL     	43 2 0
	503	[86]	SETLIST  	39 0 1	; 1
	504	[86]	NEWTABLE 	40 3 0
	505	[87]	LOADK    	41 -87	; "ru-US"
	506	[87]	NEWTABLE 	42 0 0
	507	[87]	LOADK    	43 -124	; "Hb  "
	508	[87]	MOVE     	44 9
	509	[87]	LOADK    	45 -86	; "Russian + English (US)"
	510	[87]	CALL     	44 2 0
	511	[87]	SETLIST  	40 0 1	; 1
	512	[87]	NEWTABLE 	41 3 0
	513	[88]	LOADK    	42 -90	; "ru"
	514	[88]	NEWTABLE 	43 1 0
	515	[88]	LOADK    	44 -145	; "rus"
	516	[88]	SETLIST  	43 1 1	; 1
	517	[88]	LOADK    	44 -124	; "Hb  "
	518	[88]	MOVE     	45 9
	519	[88]	LOADK    	46 -89	; "Russian"
	520	[88]	CALL     	45 2 0
	521	[88]	SETLIST  	41 0 1	; 1
	522	[88]	NEWTABLE 	42 3 0
	523	[89]	LOADK    	43 -93	; "sk"
	524	[89]	NEWTABLE 	44 1 0
	525	[89]	LOADK    	45 -146	; "slk"
	526	[89]	SETLIST  	44 1 1	; 1
	527	[89]	LOADK    	45 -121	; "HB  "
	528	[89]	MOVE     	46 9
	529	[89]	LOADK    	47 -92	; "Slovak"
	530	[89]	CALL     	46 2 0
	531	[89]	SETLIST  	42 0 1	; 1
	532	[89]	NEWTABLE 	43 3 0
	533	[90]	LOADK    	44 -96	; "sl"
	534	[90]	NEWTABLE 	45 1 0
	535	[90]	LOADK    	46 -147	; "slv"
	536	[90]	SETLIST  	45 1 1	; 1
	537	[90]	LOADK    	46 -110	; "H   "
	538	[90]	MOVE     	47 9
	539	[90]	LOADK    	48 -95	; "Slovenian"
	540	[90]	CALL     	47 2 0
	541	[90]	SETLIST  	43 0 1	; 1
	542	[90]	NEWTABLE 	44 3 0
	543	[91]	LOADK    	45 -99	; "es"
	544	[91]	NEWTABLE 	46 1 0
	545	[91]	LOADK    	47 -148	; "spa"
	546	[91]	SETLIST  	46 1 1	; 1
	547	[91]	LOADK    	47 -124	; "Hb  "
	548	[91]	MOVE     	48 9
	549	[91]	LOADK    	49 -98	; "Spanish"
	550	[91]	CALL     	48 2 0
	551	[91]	SETLIST  	44 0 1	; 1
	552	[91]	NEWTABLE 	45 3 0
	553	[92]	LOADK    	46 -102	; "sv"
	554	[92]	NEWTABLE 	47 1 0
	555	[92]	LOADK    	48 -149	; "swe"
	556	[92]	SETLIST  	47 1 1	; 1
	557	[92]	LOADK    	48 -110	; "H   "
	558	[92]	MOVE     	49 9
	559	[92]	LOADK    	50 -101	; "Swedish"
	560	[92]	CALL     	49 2 0
	561	[92]	SETLIST  	45 0 1	; 1
	562	[92]	NEWTABLE 	46 3 0
	563	[93]	LOADK    	47 -105	; "tr"
	564	[93]	NEWTABLE 	48 1 0
	565	[93]	LOADK    	49 -150	; "tur"
	566	[93]	SETLIST  	48 1 1	; 1
	567	[93]	LOADK    	49 -110	; "H   "
	568	[93]	MOVE     	50 9
	569	[93]	LOADK    	51 -104	; "Turkish"
	570	[93]	CALL     	50 2 0
	571	[93]	SETLIST  	46 0 1	; 1
	572	[93]	NEWTABLE 	47 3 0
	573	[94]	LOADK    	48 -108	; "uk"
	574	[94]	NEWTABLE 	49 1 0
	575	[94]	LOADK    	50 -151	; "ukr"
	576	[94]	SETLIST  	49 1 1	; 1
	577	[94]	LOADK    	50 -110	; "H   "
	578	[94]	MOVE     	51 9
	579	[94]	LOADK    	52 -107	; "Ukrainian"
	580	[94]	CALL     	51 2 0
	581	[94]	SETLIST  	47 0 1	; 1
	582	[95]	SETLIST  	14 33 1	; 1
	583	[97]	LOADK    	15 -40	; "en-US"
	584	[99]	NEWTABLE 	16 0 0
	585	[100]	NEWTABLE 	17 0 0
	586	[101]	GETGLOBAL	18 -152	; ipairs
	587	[101]	MOVE     	19 14
	588	[101]	CALL     	18 2 4
	589	[101]	JMP      	16	; to 606
	590	[102]	GETGLOBAL	23 -153	; unpack
	591	[102]	MOVE     	24 22
	592	[102]	CALL     	23 2 5
	593	[103]	SETTABLE 	16 23 26
	594	[104]	TEST     	24 0 0
	595	[104]	JMP      	10	; to 606
	596	[104]	LEN      	27 24
	597	[104]	LT       	0 -154 27	; 0 -
	598	[104]	JMP      	7	; to 606
	599	[105]	GETGLOBAL	27 -152	; ipairs
	600	[105]	MOVE     	28 24
	601	[105]	CALL     	27 2 4
	602	[105]	JMP      	1	; to 604
	603	[106]	SETTABLE 	17 31 23
	604	[105]	TFORLOOP 	27 2
	605	[106]	JMP      	-3	; to 603
	606	[101]	TFORLOOP 	18 2
	607	[108]	JMP      	-18	; to 590
	608	[111]	SELF     	18 4 -155	; "new"
	609	[111]	NEWTABLE 	20 0 0
	610	[111]	CALL     	18 3 2
	611	[587]	CLOSURE  	19 0	; 0x7faa78408180
	612	[587]	MOVE     	0 13
	613	[587]	MOVE     	0 15
	614	[587]	MOVE     	0 9
	615	[587]	MOVE     	0 6
	616	[587]	MOVE     	0 3
	617	[587]	MOVE     	0 8
	618	[587]	MOVE     	0 12
	619	[587]	MOVE     	0 14
	620	[587]	MOVE     	0 11
	621	[587]	MOVE     	0 0
	622	[587]	MOVE     	0 2
	623	[587]	MOVE     	0 5
	624	[587]	MOVE     	0 10
	625	[587]	MOVE     	0 16
	626	[113]	SETTABLE 	18 -156 19	; "init" -
	627	[599]	CLOSURE  	19 1	; 0x7faa78506c10
	628	[599]	MOVE     	0 16
	629	[599]	MOVE     	0 11
	630	[599]	MOVE     	0 9
	631	[589]	SETTABLE 	18 -157 19	; "addToMainMenu" -
	632	[610]	CLOSURE  	19 2	; 0x7faa78507300
	633	[610]	MOVE     	0 13
	634	[601]	SETTABLE 	18 -158 19	; "getCurrentDefaultHyphDictLanguage" -
	635	[628]	CLOSURE  	19 3	; 0x7faa785079e0
	636	[628]	MOVE     	0 8
	637	[612]	SETTABLE 	18 -159 19	; "parseLanguageTag" -
	638	[653]	CLOSURE  	19 4	; 0x7faa78507d80
	639	[653]	MOVE     	0 17
	640	[630]	SETTABLE 	18 -160 19	; "fixLangTag" -
	641	[750]	CLOSURE  	19 5	; 0x7faa785081c0
	642	[750]	MOVE     	0 13
	643	[750]	MOVE     	0 7
	644	[750]	MOVE     	0 15
	645	[663]	SETTABLE 	18 -161 19	; "onReadSettings" -
	646	[800]	CLOSURE  	19 6	; 0x7faa78704170
	647	[800]	MOVE     	0 16
	648	[800]	MOVE     	0 11
	649	[800]	MOVE     	0 9
	650	[800]	MOVE     	0 6
	651	[800]	MOVE     	0 3
	652	[800]	MOVE     	0 0
	653	[800]	MOVE     	0 2
	654	[800]	MOVE     	0 7
	655	[752]	SETTABLE 	18 -162 19	; "onPreRenderDocument" -
	656	[809]	CLOSURE  	19 7	; 0x7faa78704640
	657	[802]	SETTABLE 	18 -163 19	; "onSaveSettings" -
	658	[811]	RETURN   	18 2
	659	[811]	RETURN   	0 1

function <./frontend/apps/reader/modules/readertypography.lua:113,587> (347 instructions, 1388 bytes at 0x7faa78408180)
1 param, 15 slots, 14 upvalues, 17 locals, 48 constants, 33 functions
	1	[114]	NEWTABLE 	1 0 0
	2	[114]	SETTABLE 	0 -1 1	; "menu_table" -
	3	[115]	NEWTABLE 	1 0 0
	4	[115]	SETTABLE 	0 -2 1	; "language_submenu" -
	5	[116]	SETTABLE 	0 -3 -4	; "book_lang_tag" nil
	6	[117]	SETTABLE 	0 -5 -4	; "text_lang_tag" nil
	7	[118]	SETTABLE 	0 -6 -7	; "text_lang_embedded_langs" true
	8	[119]	SETTABLE 	0 -8 -7	; "hyphenation" true
	9	[120]	SETTABLE 	0 -9 -10	; "hyph_trust_soft_hyphens" false
	10	[121]	SETTABLE 	0 -11 -10	; "hyph_soft_hyphens_only" false
	11	[122]	SETTABLE 	0 -12 -10	; "hyph_force_algorithmic" false
	12	[126]	GETGLOBAL	1 -13	; G_reader_settings
	13	[126]	SELF     	1 1 -14	; "readSetting"
	14	[126]	LOADK    	3 -15	; "text_lang_default"
	15	[126]	CALL     	1 3 2
	16	[126]	TEST     	1 0 1
	17	[126]	JMP      	71	; to 89
	18	[126]	GETGLOBAL	1 -13	; G_reader_settings
	19	[126]	SELF     	1 1 -14	; "readSetting"
	20	[126]	LOADK    	3 -16	; "text_lang_fallback"
	21	[126]	CALL     	1 3 2
	22	[126]	TEST     	1 0 1
	23	[126]	JMP      	65	; to 89
	24	[127]	LOADBOOL 	1 0 0
	25	[128]	GETGLOBAL	2 -13	; G_reader_settings
	26	[128]	SELF     	2 2 -14	; "readSetting"
	27	[128]	LOADK    	4 -17	; "hyph_alg_default"
	28	[128]	CALL     	2 3 2
	29	[129]	TEST     	2 0 0
	30	[129]	JMP      	33	; to 64
	31	[130]	GETUPVAL 	3 0	; HYPH_DICT_NAME_TO_LANG_NAME_TAG
	32	[130]	GETTABLE 	3 3 2
	33	[131]	TEST     	3 0 0
	34	[131]	JMP      	29	; to 64
	35	[132]	GETGLOBAL	4 -13	; G_reader_settings
	36	[132]	SELF     	4 4 -18	; "saveSetting"
	37	[132]	LOADK    	6 -15	; "text_lang_default"
	38	[132]	GETTABLE 	7 3 -19	; 2
	39	[132]	CALL     	4 4 1
	40	[133]	LOADBOOL 	1 1 0
	41	[136]	EQ       	0 2 -20	; - "@none"
	42	[136]	JMP      	6	; to 49
	43	[137]	GETGLOBAL	4 -13	; G_reader_settings
	44	[137]	SELF     	4 4 -18	; "saveSetting"
	45	[137]	LOADK    	6 -8	; "hyphenation"
	46	[137]	LOADBOOL 	7 0 0
	47	[137]	CALL     	4 4 1
	48	[137]	JMP      	15	; to 64
	49	[138]	EQ       	0 2 -21	; - "@softhyphens"
	50	[138]	JMP      	6	; to 57
	51	[139]	GETGLOBAL	4 -13	; G_reader_settings
	52	[139]	SELF     	4 4 -18	; "saveSetting"
	53	[139]	LOADK    	6 -11	; "hyph_soft_hyphens_only"
	54	[139]	LOADBOOL 	7 1 0
	55	[139]	CALL     	4 4 1
	56	[139]	JMP      	7	; to 64
	57	[140]	EQ       	0 2 -22	; - "@algorithm"
	58	[140]	JMP      	5	; to 64
	59	[141]	GETGLOBAL	4 -13	; G_reader_settings
	60	[141]	SELF     	4 4 -18	; "saveSetting"
	61	[141]	LOADK    	6 -12	; "hyph_force_algorithmic"
	62	[141]	LOADBOOL 	7 1 0
	63	[141]	CALL     	4 4 1
	64	[145]	GETGLOBAL	3 -13	; G_reader_settings
	65	[145]	SELF     	3 3 -14	; "readSetting"
	66	[145]	LOADK    	5 -23	; "hyph_alg_fallback"
	67	[145]	CALL     	3 3 2
	68	[146]	TEST     	1 0 1
	69	[146]	JMP      	12	; to 82
	70	[146]	TEST     	3 0 0
	71	[146]	JMP      	10	; to 82
	72	[147]	GETUPVAL 	4 0	; HYPH_DICT_NAME_TO_LANG_NAME_TAG
	73	[147]	GETTABLE 	4 4 3
	74	[148]	TEST     	4 0 0
	75	[148]	JMP      	6	; to 82
	76	[149]	GETGLOBAL	5 -13	; G_reader_settings
	77	[149]	SELF     	5 5 -18	; "saveSetting"
	78	[149]	LOADK    	7 -16	; "text_lang_fallback"
	79	[149]	GETTABLE 	8 4 -19	; 2
	80	[149]	CALL     	5 4 1
	81	[150]	LOADBOOL 	1 1 0
	82	[155]	TEST     	1 0 1
	83	[155]	JMP      	5	; to 89
	84	[158]	GETGLOBAL	4 -13	; G_reader_settings
	85	[158]	SELF     	4 4 -18	; "saveSetting"
	86	[158]	LOADK    	6 -16	; "text_lang_fallback"
	87	[158]	GETUPVAL 	7 1	; DEFAULT_LANG_TAG
	88	[158]	CALL     	4 4 1
	89	[162]	GETUPVAL 	1 2	; _
	90	[173]	LOADK    	2 -24	; "Some languages have specific typographic rules: these include hyphenation, line breaking rules, and language specific glyph variants.\nKOReader will chose one according to the language tag from the book's metadata, but you can select another one.\nYou can also set a default language or a fallback one with a long-press.\n\nFeatures available per language are marked with:\n\238\156\171\226\128\144 : language specific hyphenation dictionary\n\238\179\134 : specific line breaking rules (mostly related to quotation marks)\n\238\172\145 : more line breaking rules (e.g., single letter prepositions not allowed at end of line)\n\nNote that when a language does not come with its own hyphenation dictionary, the English (US) one will be used.\nWhen the book's language tag is not among our presets, no specific features will be enabled, but it might be enough to get language specific glyph variants (when supported by the fonts)."
	91	[162]	CALL     	1 2 2
	92	[174]	GETGLOBAL	2 -25	; table
	93	[174]	GETTABLE 	2 2 -26	; "insert"
	94	[174]	GETTABLE 	3 0 -1	; "menu_table"
	95	[174]	NEWTABLE 	4 0 5
	96	[175]	GETUPVAL 	5 2	; _
	97	[175]	LOADK    	6 -28	; "About typography rules"
	98	[175]	CALL     	5 2 2
	99	[175]	SETTABLE 	4 -27 5	; "text" -
	100	[180]	CLOSURE  	5 0	; 0x7faa784088b0
	101	[180]	GETUPVAL 	0 3	; UIManager
	102	[180]	GETUPVAL 	0 4	; InfoMessage
	103	[180]	MOVE     	0 1
	104	[180]	SETTABLE 	4 -29 5	; "callback" -
	105	[236]	CLOSURE  	5 1	; 0x7faa78409660
	106	[236]	GETUPVAL 	0 2	; _
	107	[236]	GETUPVAL 	0 5	; util
	108	[236]	GETUPVAL 	0 3	; UIManager
	109	[236]	GETUPVAL 	0 6	; Screen
	110	[236]	SETTABLE 	4 -30 5	; "hold_callback" -
	111	[237]	SETTABLE 	4 -31 -7	; "keep_menu_open" true
	112	[238]	SETTABLE 	4 -32 -7	; "separator" true
	113	[174]	CALL     	2 3 1
	114	[241]	GETGLOBAL	2 -33	; ipairs
	115	[241]	GETUPVAL 	3 7	; LANGUAGES
	116	[241]	CALL     	2 2 4
	117	[241]	JMP      	39	; to 157
	118	[242]	GETGLOBAL	7 -34	; unpack
	119	[242]	MOVE     	8 6
	120	[242]	CALL     	7 2 5
	121	[244]	GETGLOBAL	11 -25	; table
	122	[244]	GETTABLE 	11 11 -26	; "insert"
	123	[244]	GETTABLE 	12 0 -2	; "language_submenu"
	124	[244]	NEWTABLE 	13 0 4
	125	[266]	CLOSURE  	14 2	; 0x7faa784087b0
	126	[266]	MOVE     	0 10
	127	[266]	MOVE     	0 9
	128	[266]	MOVE     	0 7
	129	[266]	SETTABLE 	13 -35 14	; "text_func" -
	130	[274]	CLOSURE  	14 3	; 0x7faa7840a3a0
	131	[274]	GETUPVAL 	0 3	; UIManager
	132	[274]	GETUPVAL 	0 4	; InfoMessage
	133	[274]	GETUPVAL 	0 8	; T
	134	[274]	GETUPVAL 	0 2	; _
	135	[274]	GETUPVAL 	0 9	; BD
	136	[274]	MOVE     	0 10
	137	[274]	MOVE     	0 0
	138	[274]	MOVE     	0 7
	139	[274]	GETUPVAL 	0 10	; Event
	140	[274]	SETTABLE 	13 -29 14	; "callback" -
	141	[296]	CLOSURE  	14 4	; 0x7faa7840a1e0
	142	[296]	GETUPVAL 	0 3	; UIManager
	143	[296]	GETUPVAL 	0 11	; MultiConfirmBox
	144	[296]	GETUPVAL 	0 8	; T
	145	[296]	GETUPVAL 	0 2	; _
	146	[296]	GETUPVAL 	0 9	; BD
	147	[296]	MOVE     	0 10
	148	[296]	MOVE     	0 7
	149	[296]	GETUPVAL 	0 12	; C_
	150	[296]	SETTABLE 	13 -30 14	; "hold_callback" -
	151	[299]	CLOSURE  	14 5	; 0x7faa7840ad20
	152	[299]	MOVE     	0 0
	153	[299]	MOVE     	0 7
	154	[299]	SETTABLE 	13 -36 14	; "checked_func" -
	155	[244]	CALL     	11 3 1
	156	[300]	CLOSE    	7
	157	[241]	TFORLOOP 	2 2
	158	[300]	JMP      	-41	; to 118
	159	[303]	GETTABLE 	2 0 -2	; "language_submenu"
	160	[303]	SETTABLE 	2 -37 -38	; "max_per_page" 5
	161	[304]	GETGLOBAL	2 -25	; table
	162	[304]	GETTABLE 	2 2 -26	; "insert"
	163	[304]	GETTABLE 	3 0 -1	; "menu_table"
	164	[304]	NEWTABLE 	4 0 2
	165	[308]	CLOSURE  	5 6	; 0x7faa7840baa0
	166	[308]	GETUPVAL 	0 13	; LANG_TAG_TO_LANG_NAME
	167	[308]	MOVE     	0 0
	168	[308]	GETUPVAL 	0 8	; T
	169	[308]	GETUPVAL 	0 2	; _
	170	[308]	SETTABLE 	4 -35 5	; "text_func" -
	171	[309]	GETTABLE 	5 0 -2	; "language_submenu"
	172	[309]	SETTABLE 	4 -39 5	; "sub_item_table" -
	173	[304]	CALL     	2 3 1
	174	[312]	GETGLOBAL	2 -25	; table
	175	[312]	GETTABLE 	2 2 -26	; "insert"
	176	[312]	GETTABLE 	3 0 -1	; "menu_table"
	177	[312]	NEWTABLE 	4 0 5
	178	[313]	GETUPVAL 	5 2	; _
	179	[313]	LOADK    	6 -40	; "Respect embedded lang tags"
	180	[313]	CALL     	5 2 2
	181	[313]	SETTABLE 	4 -27 5	; "text" -
	182	[318]	CLOSURE  	5 7	; 0x7faa7840bc70
	183	[318]	MOVE     	0 0
	184	[318]	GETUPVAL 	0 10	; Event
	185	[318]	SETTABLE 	4 -29 5	; "callback" -
	186	[337]	CLOSURE  	5 8	; 0x7faa7840c190
	187	[337]	GETUPVAL 	0 3	; UIManager
	188	[337]	GETUPVAL 	0 11	; MultiConfirmBox
	189	[337]	GETUPVAL 	0 2	; _
	190	[337]	SETTABLE 	4 -30 5	; "hold_callback" -
	191	[340]	CLOSURE  	5 9	; 0x7faa7840c9d0
	192	[340]	MOVE     	0 0
	193	[340]	SETTABLE 	4 -36 5	; "checked_func" -
	194	[341]	SETTABLE 	4 -32 -7	; "separator" true
	195	[312]	CALL     	2 3 1
	196	[344]	NEWTABLE 	2 0 0
	197	[345]	GETGLOBAL	3 -25	; table
	198	[345]	GETTABLE 	3 3 -26	; "insert"
	199	[345]	MOVE     	4 2
	200	[345]	NEWTABLE 	5 0 4
	201	[346]	GETUPVAL 	6 2	; _
	202	[346]	LOADK    	7 -41	; "Enable hyphenation"
	203	[346]	CALL     	6 2 2
	204	[346]	SETTABLE 	5 -27 6	; "text" -
	205	[351]	CLOSURE  	6 10	; 0x7faa78409ee0
	206	[351]	MOVE     	0 0
	207	[351]	GETUPVAL 	0 10	; Event
	208	[351]	SETTABLE 	5 -29 6	; "callback" -
	209	[370]	CLOSURE  	6 11	; 0x7faa7840db90
	210	[370]	GETUPVAL 	0 3	; UIManager
	211	[370]	GETUPVAL 	0 11	; MultiConfirmBox
	212	[370]	GETUPVAL 	0 2	; _
	213	[370]	SETTABLE 	5 -30 6	; "hold_callback" -
	214	[373]	CLOSURE  	6 12	; 0x7faa78409520
	215	[373]	MOVE     	0 0
	216	[373]	SETTABLE 	5 -36 6	; "checked_func" -
	217	[345]	CALL     	3 3 1
	218	[375]	GETGLOBAL	3 -25	; table
	219	[375]	GETTABLE 	3 3 -26	; "insert"
	220	[375]	MOVE     	4 2
	221	[375]	NEWTABLE 	5 0 3
	222	[387]	CLOSURE  	6 13	; 0x7faa7840c4b0
	223	[387]	GETUPVAL 	0 8	; T
	224	[387]	GETUPVAL 	0 2	; _
	225	[387]	SETTABLE 	5 -35 6	; "text_func" -
	226	[434]	CLOSURE  	6 14	; 0x7faa7840cfa0
	227	[434]	GETUPVAL 	0 0	; HYPH_DICT_NAME_TO_LANG_NAME_TAG
	228	[434]	GETUPVAL 	0 6	; Screen
	229	[434]	GETUPVAL 	0 2	; _
	230	[434]	MOVE     	0 0
	231	[434]	GETUPVAL 	0 10	; Event
	232	[434]	GETUPVAL 	0 3	; UIManager
	233	[434]	SETTABLE 	5 -29 6	; "callback" -
	234	[437]	CLOSURE  	6 15	; 0x7faa7840eba0
	235	[437]	MOVE     	0 0
	236	[437]	SETTABLE 	5 -42 6	; "enabled_func" -
	237	[375]	CALL     	3 3 1
	238	[439]	GETGLOBAL	3 -25	; table
	239	[439]	GETTABLE 	3 3 -26	; "insert"
	240	[439]	MOVE     	4 2
	241	[439]	NEWTABLE 	5 0 6
	242	[440]	GETUPVAL 	6 2	; _
	243	[440]	LOADK    	7 -43	; "Trust soft hyphens"
	244	[440]	CALL     	6 2 2
	245	[440]	SETTABLE 	5 -27 6	; "text" -
	246	[445]	CLOSURE  	6 16	; 0x7faa7840e900
	247	[445]	MOVE     	0 0
	248	[445]	GETUPVAL 	0 10	; Event
	249	[445]	SETTABLE 	5 -29 6	; "callback" -
	250	[464]	CLOSURE  	6 17	; 0x7faa7840ca50
	251	[464]	GETUPVAL 	0 3	; UIManager
	252	[464]	GETUPVAL 	0 11	; MultiConfirmBox
	253	[464]	GETUPVAL 	0 2	; _
	254	[464]	SETTABLE 	5 -30 6	; "hold_callback" -
	255	[467]	CLOSURE  	6 18	; 0x7faa7840fda0
	256	[467]	MOVE     	0 0
	257	[467]	SETTABLE 	5 -36 6	; "checked_func" -
	258	[470]	CLOSURE  	6 19	; 0x7faa78410570
	259	[470]	MOVE     	0 0
	260	[470]	SETTABLE 	5 -42 6	; "enabled_func" -
	261	[471]	SETTABLE 	5 -32 -7	; "separator" true
	262	[439]	CALL     	3 3 1
	263	[473]	GETGLOBAL	3 -25	; table
	264	[473]	GETTABLE 	3 3 -26	; "insert"
	265	[473]	MOVE     	4 2
	266	[473]	NEWTABLE 	5 0 4
	267	[477]	CLOSURE  	6 20	; 0x7faa78410ba0
	268	[477]	GETUPVAL 	0 8	; T
	269	[477]	GETUPVAL 	0 2	; _
	270	[477]	MOVE     	0 0
	271	[477]	SETTABLE 	5 -35 6	; "text_func" -
	272	[484]	CLOSURE  	6 21	; 0x7faa784110e0
	273	[484]	MOVE     	0 0
	274	[484]	GETUPVAL 	0 10	; Event
	275	[484]	SETTABLE 	5 -29 6	; "callback" -
	276	[489]	CLOSURE  	6 22	; 0x7faa784111e0
	277	[489]	MOVE     	0 0
	278	[489]	SETTABLE 	5 -36 6	; "checked_func" -
	279	[492]	CLOSURE  	6 23	; 0x7faa784117c0
	280	[492]	MOVE     	0 0
	281	[492]	SETTABLE 	5 -42 6	; "enabled_func" -
	282	[473]	CALL     	3 3 1
	283	[494]	GETGLOBAL	3 -25	; table
	284	[494]	GETTABLE 	3 3 -26	; "insert"
	285	[494]	MOVE     	4 2
	286	[494]	NEWTABLE 	5 0 5
	287	[495]	GETUPVAL 	6 2	; _
	288	[495]	LOADK    	7 -44	; "Algorithmic hyphenation"
	289	[495]	CALL     	6 2 2
	290	[495]	SETTABLE 	5 -27 6	; "text" -
	291	[502]	CLOSURE  	6 24	; 0x7faa78411b80
	292	[502]	MOVE     	0 0
	293	[502]	GETUPVAL 	0 10	; Event
	294	[502]	SETTABLE 	5 -29 6	; "callback" -
	295	[521]	CLOSURE  	6 25	; 0x7faa78411c40
	296	[521]	GETUPVAL 	0 3	; UIManager
	297	[521]	GETUPVAL 	0 11	; MultiConfirmBox
	298	[521]	GETUPVAL 	0 2	; _
	299	[521]	SETTABLE 	5 -30 6	; "hold_callback" -
	300	[526]	CLOSURE  	6 26	; 0x7faa785044b0
	301	[526]	MOVE     	0 0
	302	[526]	SETTABLE 	5 -36 6	; "checked_func" -
	303	[529]	CLOSURE  	6 27	; 0x7faa78504b50
	304	[529]	MOVE     	0 0
	305	[529]	SETTABLE 	5 -42 6	; "enabled_func" -
	306	[494]	CALL     	3 3 1
	307	[531]	GETGLOBAL	3 -25	; table
	308	[531]	GETTABLE 	3 3 -26	; "insert"
	309	[531]	MOVE     	4 2
	310	[531]	NEWTABLE 	5 0 5
	311	[532]	GETUPVAL 	6 2	; _
	312	[532]	LOADK    	7 -45	; "Soft-hyphens only"
	313	[532]	CALL     	6 2 2
	314	[532]	SETTABLE 	5 -27 6	; "text" -
	315	[539]	CLOSURE  	6 28	; 0x7faa78504d00
	316	[539]	MOVE     	0 0
	317	[539]	GETUPVAL 	0 10	; Event
	318	[539]	SETTABLE 	5 -29 6	; "callback" -
	319	[558]	CLOSURE  	6 29	; 0x7faa78504dd0
	320	[558]	GETUPVAL 	0 3	; UIManager
	321	[558]	GETUPVAL 	0 11	; MultiConfirmBox
	322	[558]	GETUPVAL 	0 2	; _
	323	[558]	SETTABLE 	5 -30 6	; "hold_callback" -
	324	[561]	CLOSURE  	6 30	; 0x7faa78505850
	325	[561]	MOVE     	0 0
	326	[561]	SETTABLE 	5 -36 6	; "checked_func" -
	327	[564]	CLOSURE  	6 31	; 0x7faa785054d0
	328	[564]	MOVE     	0 0
	329	[564]	SETTABLE 	5 -42 6	; "enabled_func" -
	330	[531]	CALL     	3 3 1
	331	[567]	GETGLOBAL	3 -25	; table
	332	[567]	GETTABLE 	3 3 -26	; "insert"
	333	[567]	GETTABLE 	4 0 -1	; "menu_table"
	334	[567]	NEWTABLE 	5 0 2
	335	[582]	CLOSURE  	6 32	; 0x7faa785066d0
	336	[582]	MOVE     	0 0
	337	[582]	GETUPVAL 	0 2	; _
	338	[582]	GETUPVAL 	0 8	; T
	339	[582]	SETTABLE 	5 -35 6	; "text_func" -
	340	[583]	SETTABLE 	5 -39 2	; "sub_item_table" -
	341	[567]	CALL     	3 3 1
	342	[586]	GETTABLE 	3 0 -46	; "ui"
	343	[586]	GETTABLE 	3 3 -47	; "menu"
	344	[586]	SELF     	3 3 -48	; "registerToMainMenu"
	345	[586]	MOVE     	5 0
	346	[586]	CALL     	3 3 1
	347	[587]	RETURN   	0 1

function <./frontend/apps/reader/modules/readertypography.lua:176,180> (10 instructions, 40 bytes at 0x7faa784088b0)
0 params, 6 slots, 3 upvalues, 0 locals, 3 constants, 0 functions
	1	[177]	GETUPVAL 	0 0	; UIManager
	2	[177]	SELF     	0 0 -1	; "show"
	3	[177]	GETUPVAL 	2 1	; InfoMessage
	4	[177]	SELF     	2 2 -2	; "new"
	5	[177]	NEWTABLE 	4 0 1
	6	[178]	GETUPVAL 	5 2	; info_text
	7	[178]	SETTABLE 	4 -3 5	; "text" -
	8	[177]	CALL     	2 3 0
	9	[177]	CALL     	0 0 1
	10	[180]	RETURN   	0 1

function <./frontend/apps/reader/modules/readertypography.lua:181,236> (143 instructions, 572 bytes at 0x7faa78409660)
0 params, 23 slots, 4 upvalues, 21 locals, 37 constants, 0 functions
	1	[183]	NEWTABLE 	0 0 0
	2	[184]	NEWTABLE 	1 0 0
	3	[185]	GETGLOBAL	2 -1	; cre
	4	[185]	GETTABLE 	2 2 -2	; "getTextLangStatus"
	5	[185]	CALL     	2 1 4
	6	[187]	GETTABLE 	5 4 2
	7	[188]	GETGLOBAL	6 -3	; table
	8	[188]	GETTABLE 	6 6 -4	; "insert"
	9	[188]	MOVE     	7 0
	10	[188]	GETUPVAL 	8 0	; _
	11	[188]	LOADK    	9 -5	; "Current main language tag:"
	12	[188]	CALL     	8 2 0
	13	[188]	CALL     	6 0 1
	14	[189]	GETGLOBAL	6 -3	; table
	15	[189]	GETTABLE 	6 6 -4	; "insert"
	16	[189]	MOVE     	7 0
	17	[189]	GETGLOBAL	8 -6	; string
	18	[189]	GETTABLE 	8 8 -7	; "format"
	19	[189]	LOADK    	9 -8	; "%s\t\t(%s - %s - %s)"
	20	[190]	MOVE     	10 2
	21	[191]	GETTABLE 	11 5 -9	; "hyph_dict_name"
	22	[192]	GETUPVAL 	12 1	; util
	23	[192]	GETTABLE 	12 12 -10	; "getFormattedSize"
	24	[192]	GETTABLE 	13 5 -11	; "hyph_nb_patterns"
	25	[192]	CALL     	12 2 2
	26	[193]	GETUPVAL 	13 1	; util
	27	[193]	GETTABLE 	13 13 -12	; "getFriendlySize"
	28	[193]	GETTABLE 	14 5 -13	; "hyph_mem_size"
	29	[193]	CALL     	13 2 0
	30	[189]	CALL     	8 0 0
	31	[189]	CALL     	6 0 1
	32	[194]	GETTABLE 	6 5 -9	; "hyph_dict_name"
	33	[194]	SETTABLE 	1 6 -14	; - true
	34	[196]	LOADBOOL 	6 0 0
	35	[197]	NEWTABLE 	7 0 0
	36	[198]	GETGLOBAL	8 -15	; pairs
	37	[198]	MOVE     	9 4
	38	[198]	CALL     	8 2 4
	39	[198]	JMP      	6	; to 46
	40	[199]	LOADBOOL 	6 1 0
	41	[200]	GETGLOBAL	12 -3	; table
	42	[200]	GETTABLE 	12 12 -4	; "insert"
	43	[200]	MOVE     	13 7
	44	[200]	MOVE     	14 11
	45	[200]	CALL     	12 3 1
	46	[198]	TFORLOOP 	8 1
	47	[200]	JMP      	-8	; to 40
	48	[202]	TEST     	6 0 0
	49	[202]	JMP      	61	; to 111
	50	[203]	GETGLOBAL	8 -3	; table
	51	[203]	GETTABLE 	8 8 -16	; "sort"
	52	[203]	MOVE     	9 7
	53	[203]	CALL     	8 2 1
	54	[204]	GETGLOBAL	8 -3	; table
	55	[204]	GETTABLE 	8 8 -4	; "insert"
	56	[204]	MOVE     	9 0
	57	[204]	LOADK    	10 -17	; ""
	58	[204]	CALL     	8 3 1
	59	[205]	GETGLOBAL	8 -3	; table
	60	[205]	GETTABLE 	8 8 -4	; "insert"
	61	[205]	MOVE     	9 0
	62	[205]	GETUPVAL 	10 0	; _
	63	[205]	LOADK    	11 -18	; "Other language tags:"
	64	[205]	CALL     	10 2 0
	65	[205]	CALL     	8 0 1
	66	[207]	GETGLOBAL	8 -19	; ipairs
	67	[207]	MOVE     	9 7
	68	[207]	CALL     	8 2 4
	69	[207]	JMP      	39	; to 109
	70	[208]	GETTABLE 	13 4 12
	71	[209]	EQ       	0 12 2
	72	[209]	JMP      	1	; to 74
	73	[211]	JMP      	35	; to 109
	74	[212]	GETTABLE 	14 13 -9	; "hyph_dict_name"
	75	[212]	GETTABLE 	14 1 14
	76	[212]	TEST     	14 0 0
	77	[212]	JMP      	11	; to 89
	78	[213]	GETGLOBAL	14 -3	; table
	79	[213]	GETTABLE 	14 14 -4	; "insert"
	80	[213]	MOVE     	15 0
	81	[213]	GETGLOBAL	16 -6	; string
	82	[213]	GETTABLE 	16 16 -7	; "format"
	83	[213]	LOADK    	17 -20	; "%s\t\t(%s)"
	84	[214]	MOVE     	18 12
	85	[215]	GETTABLE 	19 13 -9	; "hyph_dict_name"
	86	[213]	CALL     	16 4 0
	87	[213]	CALL     	14 0 1
	88	[215]	JMP      	20	; to 109
	89	[217]	GETGLOBAL	14 -3	; table
	90	[217]	GETTABLE 	14 14 -4	; "insert"
	91	[217]	MOVE     	15 0
	92	[217]	GETGLOBAL	16 -6	; string
	93	[217]	GETTABLE 	16 16 -7	; "format"
	94	[217]	LOADK    	17 -8	; "%s\t\t(%s - %s - %s)"
	95	[218]	MOVE     	18 12
	96	[219]	GETTABLE 	19 13 -9	; "hyph_dict_name"
	97	[220]	GETUPVAL 	20 1	; util
	98	[220]	GETTABLE 	20 20 -10	; "getFormattedSize"
	99	[220]	GETTABLE 	21 13 -11	; "hyph_nb_patterns"
	100	[220]	CALL     	20 2 2
	101	[221]	GETUPVAL 	21 1	; util
	102	[221]	GETTABLE 	21 21 -12	; "getFriendlySize"
	103	[221]	GETTABLE 	22 13 -13	; "hyph_mem_size"
	104	[221]	CALL     	21 2 0
	105	[217]	CALL     	16 0 0
	106	[217]	CALL     	14 0 1
	107	[222]	GETTABLE 	14 13 -9	; "hyph_dict_name"
	108	[222]	SETTABLE 	1 14 -14	; - true
	109	[207]	TFORLOOP 	8 2
	110	[223]	JMP      	-41	; to 70
	111	[227]	GETGLOBAL	8 -3	; table
	112	[227]	GETTABLE 	8 8 -21	; "concat"
	113	[227]	MOVE     	9 0
	114	[227]	LOADK    	10 -22	; "\n"
	115	[227]	CALL     	8 3 2
	116	[228]	GETGLOBAL	9 -23	; require
	117	[228]	LOADK    	10 -24	; "ui/widget/textviewer"
	118	[228]	CALL     	9 2 2
	119	[229]	GETGLOBAL	10 -23	; require
	120	[229]	LOADK    	11 -25	; "ui/font"
	121	[229]	CALL     	10 2 2
	122	[230]	GETUPVAL 	11 2	; UIManager
	123	[230]	SELF     	11 11 -26	; "show"
	124	[230]	SELF     	13 9 -27	; "new"
	125	[230]	NEWTABLE 	15 0 4
	126	[231]	GETUPVAL 	16 0	; _
	127	[231]	LOADK    	17 -29	; "Language tags (and hyphenation dictionaries) used since start up"
	128	[231]	CALL     	16 2 2
	129	[231]	SETTABLE 	15 -28 16	; "title" -
	130	[232]	SETTABLE 	15 -30 8	; "text" -
	131	[233]	SELF     	16 10 -32	; "getFace"
	132	[233]	LOADK    	18 -33	; "smallinfont"
	133	[233]	CALL     	16 3 2
	134	[233]	SETTABLE 	15 -31 16	; "text_face" -
	135	[234]	GETUPVAL 	16 3	; Screen
	136	[234]	SELF     	16 16 -35	; "getHeight"
	137	[234]	CALL     	16 2 2
	138	[234]	MUL      	16 16 -36	; - 4
	139	[234]	DIV      	16 16 -37	; - 5
	140	[234]	SETTABLE 	15 -34 16	; "height" -
	141	[230]	CALL     	13 3 0
	142	[230]	CALL     	11 0 1
	143	[236]	RETURN   	0 1

function <./frontend/apps/reader/modules/readertypography.lua:245,266> (56 instructions, 224 bytes at 0x7faa784087b0)
0 params, 6 slots, 3 upvalues, 2 locals, 15 constants, 0 functions
	1	[246]	GETUPVAL 	0 0	; lang_name
	2	[247]	LOADK    	1 -1	; ""
	3	[248]	GETUPVAL 	2 1	; lang_features
	4	[248]	SELF     	2 2 -2	; "find"
	5	[248]	LOADK    	4 -3	; "H"
	6	[248]	CALL     	2 3 2
	7	[248]	TEST     	2 0 0
	8	[248]	JMP      	3	; to 12
	9	[249]	MOVE     	2 1
	10	[249]	LOADK    	3 -4	; "\238\156\171\226\128\144 "
	11	[249]	CONCAT   	1 2 3
	12	[251]	GETUPVAL 	2 1	; lang_features
	13	[251]	SELF     	2 2 -2	; "find"
	14	[251]	LOADK    	4 -5	; "b"
	15	[251]	CALL     	2 3 2
	16	[251]	TEST     	2 0 0
	17	[251]	JMP      	4	; to 22
	18	[252]	MOVE     	2 1
	19	[252]	LOADK    	3 -6	; "\238\179\134"
	20	[252]	CONCAT   	1 2 3
	21	[252]	JMP      	9	; to 31
	22	[253]	GETUPVAL 	2 1	; lang_features
	23	[253]	SELF     	2 2 -2	; "find"
	24	[253]	LOADK    	4 -7	; "B"
	25	[253]	CALL     	2 3 2
	26	[253]	TEST     	2 0 0
	27	[253]	JMP      	3	; to 31
	28	[254]	MOVE     	2 1
	29	[254]	LOADK    	3 -8	; "\238\172\145"
	30	[254]	CONCAT   	1 2 3
	31	[258]	MOVE     	2 0
	32	[258]	LOADK    	3 -9	; "   "
	33	[258]	MOVE     	4 1
	34	[258]	CONCAT   	0 2 4
	35	[259]	GETUPVAL 	2 2	; lang_tag
	36	[259]	GETGLOBAL	3 -10	; G_reader_settings
	37	[259]	SELF     	3 3 -11	; "readSetting"
	38	[259]	LOADK    	5 -12	; "text_lang_default"
	39	[259]	CALL     	3 3 2
	40	[259]	EQ       	0 2 3
	41	[259]	JMP      	3	; to 45
	42	[260]	MOVE     	2 0
	43	[260]	LOADK    	3 -13	; "   \226\152\133"
	44	[260]	CONCAT   	0 2 3
	45	[262]	GETUPVAL 	2 2	; lang_tag
	46	[262]	GETGLOBAL	3 -10	; G_reader_settings
	47	[262]	SELF     	3 3 -11	; "readSetting"
	48	[262]	LOADK    	5 -14	; "text_lang_fallback"
	49	[262]	CALL     	3 3 2
	50	[262]	EQ       	0 2 3
	51	[262]	JMP      	3	; to 55
	52	[263]	MOVE     	2 0
	53	[263]	LOADK    	3 -15	; "   \239\191\189"
	54	[263]	CONCAT   	0 2 3
	55	[265]	RETURN   	0 2
	56	[266]	RETURN   	0 1

function <./frontend/apps/reader/modules/readertypography.lua:267,274> (35 instructions, 140 bytes at 0x7faa7840a3a0)
0 params, 9 slots, 9 upvalues, 0 locals, 11 constants, 0 functions
	1	[268]	GETUPVAL 	0 0	; UIManager
	2	[268]	SELF     	0 0 -1	; "show"
	3	[268]	GETUPVAL 	2 1	; InfoMessage
	4	[268]	SELF     	2 2 -2	; "new"
	5	[268]	NEWTABLE 	4 0 1
	6	[269]	GETUPVAL 	5 2	; T
	7	[269]	GETUPVAL 	6 3	; _
	8	[269]	LOADK    	7 -4	; "Changed language for typography rules to %1."
	9	[269]	CALL     	6 2 2
	10	[269]	GETUPVAL 	7 4	; BD
	11	[269]	GETTABLE 	7 7 -5	; "wrap"
	12	[269]	GETUPVAL 	8 5	; lang_name
	13	[269]	CALL     	7 2 0
	14	[269]	CALL     	5 0 2
	15	[269]	SETTABLE 	4 -3 5	; "text" -
	16	[268]	CALL     	2 3 0
	17	[268]	CALL     	0 0 1
	18	[271]	GETUPVAL 	0 6	; self
	19	[271]	GETUPVAL 	1 7	; lang_tag
	20	[271]	SETTABLE 	0 -6 1	; "text_lang_tag" -
	21	[272]	GETUPVAL 	0 6	; self
	22	[272]	GETTABLE 	0 0 -7	; "ui"
	23	[272]	GETTABLE 	0 0 -8	; "document"
	24	[272]	SELF     	0 0 -9	; "setTextMainLang"
	25	[272]	GETUPVAL 	2 7	; lang_tag
	26	[272]	CALL     	0 3 1
	27	[273]	GETUPVAL 	0 6	; self
	28	[273]	GETTABLE 	0 0 -7	; "ui"
	29	[273]	SELF     	0 0 -10	; "handleEvent"
	30	[273]	GETUPVAL 	2 8	; Event
	31	[273]	SELF     	2 2 -2	; "new"
	32	[273]	LOADK    	4 -11	; "UpdatePos"
	33	[273]	CALL     	2 3 0
	34	[273]	CALL     	0 0 1
	35	[274]	RETURN   	0 1

function <./frontend/apps/reader/modules/readertypography.lua:275,296> (35 instructions, 140 bytes at 0x7faa7840a1e0)
1 param, 10 slots, 8 upvalues, 1 local, 12 constants, 2 functions
	1	[276]	GETUPVAL 	1 0	; UIManager
	2	[276]	SELF     	1 1 -1	; "show"
	3	[276]	GETUPVAL 	3 1	; MultiConfirmBox
	4	[276]	SELF     	3 3 -2	; "new"
	5	[276]	NEWTABLE 	5 0 5
	6	[282]	GETUPVAL 	6 2	; T
	7	[282]	GETUPVAL 	7 3	; _
	8	[282]	LOADK    	8 -4	; "Would you like %1 to be used as the default\194\160(\226\152\133) or fallback\194\160(\239\191\189) language for typography rules?\n\nDefault will always take precedence while fallback will only be used if the language of the book can't be automatically determined."
	9	[282]	CALL     	7 2 2
	10	[282]	GETUPVAL 	8 4	; BD
	11	[282]	GETTABLE 	8 8 -5	; "wrap"
	12	[282]	GETUPVAL 	9 5	; lang_name
	13	[282]	CALL     	8 2 0
	14	[282]	CALL     	6 0 2
	15	[282]	SETTABLE 	5 -3 6	; "text" -
	16	[283]	GETUPVAL 	6 3	; _
	17	[283]	LOADK    	7 -7	; "Default"
	18	[283]	CALL     	6 2 2
	19	[283]	SETTABLE 	5 -6 6	; "choice1_text" -
	20	[288]	CLOSURE  	6 0	; 0x7faa7840ae50
	21	[288]	GETUPVAL 	0 6	; lang_tag
	22	[288]	MOVE     	0 0
	23	[288]	SETTABLE 	5 -8 6	; "choice1_callback" -
	24	[289]	GETUPVAL 	6 7	; C_
	25	[289]	LOADK    	7 -10	; "Typography"
	26	[289]	LOADK    	8 -11	; "Fallback"
	27	[289]	CALL     	6 3 2
	28	[289]	SETTABLE 	5 -9 6	; "choice2_text" -
	29	[294]	CLOSURE  	6 1	; 0x7faa7840a940
	30	[294]	GETUPVAL 	0 6	; lang_tag
	31	[294]	MOVE     	0 0
	32	[294]	SETTABLE 	5 -12 6	; "choice2_callback" -
	33	[276]	CALL     	3 3 0
	34	[276]	CALL     	1 0 1
	35	[296]	RETURN   	0 1

function <./frontend/apps/reader/modules/readertypography.lua:284,288> (16 instructions, 64 bytes at 0x7faa7840ae50)
0 params, 4 slots, 2 upvalues, 0 locals, 6 constants, 0 functions
	1	[285]	GETGLOBAL	0 -1	; G_reader_settings
	2	[285]	SELF     	0 0 -2	; "saveSetting"
	3	[285]	LOADK    	2 -3	; "text_lang_default"
	4	[285]	GETUPVAL 	3 0	; lang_tag
	5	[285]	CALL     	0 4 1
	6	[286]	GETGLOBAL	0 -1	; G_reader_settings
	7	[286]	SELF     	0 0 -4	; "delSetting"
	8	[286]	LOADK    	2 -5	; "text_lang_fallback"
	9	[286]	CALL     	0 3 1
	10	[287]	GETUPVAL 	0 1	; touchmenu_instance
	11	[287]	TEST     	0 0 0
	12	[287]	JMP      	3	; to 16
	13	[287]	GETUPVAL 	0 1	; touchmenu_instance
	14	[287]	SELF     	0 0 -6	; "updateItems"
	15	[287]	CALL     	0 2 1
	16	[288]	RETURN   	0 1

function <./frontend/apps/reader/modules/readertypography.lua:290,294> (16 instructions, 64 bytes at 0x7faa7840a940)
0 params, 4 slots, 2 upvalues, 0 locals, 6 constants, 0 functions
	1	[291]	GETGLOBAL	0 -1	; G_reader_settings
	2	[291]	SELF     	0 0 -2	; "saveSetting"
	3	[291]	LOADK    	2 -3	; "text_lang_fallback"
	4	[291]	GETUPVAL 	3 0	; lang_tag
	5	[291]	CALL     	0 4 1
	6	[292]	GETGLOBAL	0 -1	; G_reader_settings
	7	[292]	SELF     	0 0 -4	; "delSetting"
	8	[292]	LOADK    	2 -5	; "text_lang_default"
	9	[292]	CALL     	0 3 1
	10	[293]	GETUPVAL 	0 1	; touchmenu_instance
	11	[293]	TEST     	0 0 0
	12	[293]	JMP      	3	; to 16
	13	[293]	GETUPVAL 	0 1	; touchmenu_instance
	14	[293]	SELF     	0 0 -6	; "updateItems"
	15	[293]	CALL     	0 2 1
	16	[294]	RETURN   	0 1

function <./frontend/apps/reader/modules/readertypography.lua:297,299> (9 instructions, 36 bytes at 0x7faa7840ad20)
0 params, 2 slots, 2 upvalues, 0 locals, 1 constant, 0 functions
	1	[298]	GETUPVAL 	0 0	; self
	2	[298]	GETTABLE 	0 0 -1	; "text_lang_tag"
	3	[298]	GETUPVAL 	1 1	; lang_tag
	4	[298]	EQ       	1 0 1
	5	[298]	JMP      	1	; to 7
	6	[298]	LOADBOOL 	0 0 1
	7	[298]	LOADBOOL 	0 1 0
	8	[298]	RETURN   	0 2
	9	[299]	RETURN   	0 1

function <./frontend/apps/reader/modules/readertypography.lua:305,308> (16 instructions, 64 bytes at 0x7faa7840baa0)
0 params, 4 slots, 4 upvalues, 1 local, 2 constants, 0 functions
	1	[306]	GETUPVAL 	0 0	; LANG_TAG_TO_LANG_NAME
	2	[306]	GETUPVAL 	1 1	; self
	3	[306]	GETTABLE 	1 1 -1	; "text_lang_tag"
	4	[306]	GETTABLE 	0 0 1
	5	[306]	TEST     	0 0 1
	6	[306]	JMP      	2	; to 9
	7	[306]	GETUPVAL 	0 1	; self
	8	[306]	GETTABLE 	0 0 -1	; "text_lang_tag"
	9	[307]	GETUPVAL 	1 2	; T
	10	[307]	GETUPVAL 	2 3	; _
	11	[307]	LOADK    	3 -2	; "Typography rules: %1"
	12	[307]	CALL     	2 2 2
	13	[307]	MOVE     	3 0
	14	[307]	TAILCALL 	1 3 0
	15	[307]	RETURN   	1 0
	16	[308]	RETURN   	0 1

function <./frontend/apps/reader/modules/readertypography.lua:314,318> (21 instructions, 84 bytes at 0x7faa7840bc70)
0 params, 5 slots, 2 upvalues, 0 locals, 7 constants, 0 functions
	1	[315]	GETUPVAL 	0 0	; self
	2	[315]	GETUPVAL 	1 0	; self
	3	[315]	GETTABLE 	1 1 -1	; "text_lang_embedded_langs"
	4	[315]	NOT      	1 1
	5	[315]	SETTABLE 	0 -1 1	; "text_lang_embedded_langs" -
	6	[316]	GETUPVAL 	0 0	; self
	7	[316]	GETTABLE 	0 0 -2	; "ui"
	8	[316]	GETTABLE 	0 0 -3	; "document"
	9	[316]	SELF     	0 0 -4	; "setTextEmbeddedLangs"
	10	[316]	GETUPVAL 	2 0	; self
	11	[316]	GETTABLE 	2 2 -1	; "text_lang_embedded_langs"
	12	[316]	CALL     	0 3 1
	13	[317]	GETUPVAL 	0 0	; self
	14	[317]	GETTABLE 	0 0 -2	; "ui"
	15	[317]	SELF     	0 0 -5	; "handleEvent"
	16	[317]	GETUPVAL 	2 1	; Event
	17	[317]	SELF     	2 2 -6	; "new"
	18	[317]	LOADK    	4 -7	; "UpdatePos"
	19	[317]	CALL     	2 3 0
	20	[317]	CALL     	0 0 1
	21	[318]	RETURN   	0 1

function <./frontend/apps/reader/modules/readertypography.lua:319,337> (35 instructions, 140 bytes at 0x7faa7840c190)
0 params, 8 slots, 3 upvalues, 1 local, 12 constants, 4 functions
	1	[320]	GETGLOBAL	0 -1	; G_reader_settings
	2	[320]	SELF     	0 0 -2	; "nilOrTrue"
	3	[320]	LOADK    	2 -3	; "text_lang_embedded_langs"
	4	[320]	CALL     	0 3 2
	5	[321]	GETUPVAL 	1 0	; UIManager
	6	[321]	SELF     	1 1 -4	; "show"
	7	[321]	GETUPVAL 	3 1	; MultiConfirmBox
	8	[321]	SELF     	3 3 -5	; "new"
	9	[321]	NEWTABLE 	5 0 5
	10	[322]	TEST     	0 0 0
	11	[322]	JMP      	5	; to 17
	12	[322]	GETUPVAL 	6 2	; _
	13	[322]	LOADK    	7 -7	; "Would you like to respect or ignore embedded lang tags by default?\n\nRespecting them will use relevant typographic rules to render their content, while ignoring them will always use the main language typography rules.\n\nThe current default (\226\152\133) is to respect them."
	14	[322]	CALL     	6 2 2
	15	[323]	TEST     	6 0 1
	16	[323]	JMP      	3	; to 20
	17	[323]	GETUPVAL 	6 2	; _
	18	[323]	LOADK    	7 -8	; "Would you like to respect or ignore embedded lang tags by default?\n\nRespecting them will use relevant typographic rules to render their content, while ignoring them will always use the main language typography rules\n\nThe current default (\226\152\133) is to ignore them."
	19	[323]	CALL     	6 2 2
	20	[323]	SETTABLE 	5 -6 6	; "text" -
	21	[326]	CLOSURE  	6 0	; 0x7faa7840c530
	22	[326]	MOVE     	0 0
	23	[326]	GETUPVAL 	0 2	; _
	24	[326]	SETTABLE 	5 -9 6	; "choice1_text_func" -
	25	[329]	CLOSURE  	6 1	; 0x7faa7840c730
	26	[329]	SETTABLE 	5 -10 6	; "choice1_callback" -
	27	[332]	CLOSURE  	6 2	; 0x7faa7840c860
	28	[332]	MOVE     	0 0
	29	[332]	GETUPVAL 	0 2	; _
	30	[332]	SETTABLE 	5 -11 6	; "choice2_text_func" -
	31	[335]	CLOSURE  	6 3	; 0x7faa7840d280
	32	[335]	SETTABLE 	5 -12 6	; "choice2_callback" -
	33	[321]	CALL     	3 3 0
	34	[321]	CALL     	1 0 1
	35	[337]	RETURN   	0 1

function <./frontend/apps/reader/modules/readertypography.lua:324,326> (13 instructions, 52 bytes at 0x7faa7840c530)
0 params, 2 slots, 2 upvalues, 0 locals, 2 constants, 0 functions
	1	[325]	GETUPVAL 	0 0	; text_lang_embedded_langs
	2	[325]	TEST     	0 0 0
	3	[325]	JMP      	5	; to 9
	4	[325]	GETUPVAL 	0 1	; _
	5	[325]	LOADK    	1 -1	; "Ignore"
	6	[325]	CALL     	0 2 2
	7	[325]	TEST     	0 0 1
	8	[325]	JMP      	3	; to 12
	9	[325]	GETUPVAL 	0 1	; _
	10	[325]	LOADK    	1 -2	; "Ignore (\226\152\133)"
	11	[325]	CALL     	0 2 2
	12	[325]	RETURN   	0 2
	13	[326]	RETURN   	0 1

function <./frontend/apps/reader/modules/readertypography.lua:327,329> (6 instructions, 24 bytes at 0x7faa7840c730)
0 params, 4 slots, 0 upvalues, 0 locals, 3 constants, 0 functions
	1	[328]	GETGLOBAL	0 -1	; G_reader_settings
	2	[328]	SELF     	0 0 -2	; "saveSetting"
	3	[328]	LOADK    	2 -3	; "text_lang_embedded_langs"
	4	[328]	LOADBOOL 	3 0 0
	5	[328]	CALL     	0 4 1
	6	[329]	RETURN   	0 1

function <./frontend/apps/reader/modules/readertypography.lua:330,332> (13 instructions, 52 bytes at 0x7faa7840c860)
0 params, 2 slots, 2 upvalues, 0 locals, 2 constants, 0 functions
	1	[331]	GETUPVAL 	0 0	; text_lang_embedded_langs
	2	[331]	TEST     	0 0 0
	3	[331]	JMP      	5	; to 9
	4	[331]	GETUPVAL 	0 1	; _
	5	[331]	LOADK    	1 -1	; "Respect (\226\152\133)"
	6	[331]	CALL     	0 2 2
	7	[331]	TEST     	0 0 1
	8	[331]	JMP      	3	; to 12
	9	[331]	GETUPVAL 	0 1	; _
	10	[331]	LOADK    	1 -2	; "Respect"
	11	[331]	CALL     	0 2 2
	12	[331]	RETURN   	0 2
	13	[332]	RETURN   	0 1

function <./frontend/apps/reader/modules/readertypography.lua:333,335> (6 instructions, 24 bytes at 0x7faa7840d280)
0 params, 4 slots, 0 upvalues, 0 locals, 3 constants, 0 functions
	1	[334]	GETGLOBAL	0 -1	; G_reader_settings
	2	[334]	SELF     	0 0 -2	; "saveSetting"
	3	[334]	LOADK    	2 -3	; "text_lang_embedded_langs"
	4	[334]	LOADBOOL 	3 1 0
	5	[334]	CALL     	0 4 1
	6	[335]	RETURN   	0 1

function <./frontend/apps/reader/modules/readertypography.lua:338,340> (4 instructions, 16 bytes at 0x7faa7840c9d0)
0 params, 2 slots, 1 upvalue, 0 locals, 1 constant, 0 functions
	1	[339]	GETUPVAL 	0 0	; self
	2	[339]	GETTABLE 	0 0 -1	; "text_lang_embedded_langs"
	3	[339]	RETURN   	0 2
	4	[340]	RETURN   	0 1

function <./frontend/apps/reader/modules/readertypography.lua:347,351> (21 instructions, 84 bytes at 0x7faa78409ee0)
0 params, 5 slots, 2 upvalues, 0 locals, 7 constants, 0 functions
	1	[348]	GETUPVAL 	0 0	; self
	2	[348]	GETUPVAL 	1 0	; self
	3	[348]	GETTABLE 	1 1 -1	; "hyphenation"
	4	[348]	NOT      	1 1
	5	[348]	SETTABLE 	0 -1 1	; "hyphenation" -
	6	[349]	GETUPVAL 	0 0	; self
	7	[349]	GETTABLE 	0 0 -2	; "ui"
	8	[349]	GETTABLE 	0 0 -3	; "document"
	9	[349]	SELF     	0 0 -4	; "setTextHyphenation"
	10	[349]	GETUPVAL 	2 0	; self
	11	[349]	GETTABLE 	2 2 -1	; "hyphenation"
	12	[349]	CALL     	0 3 1
	13	[350]	GETUPVAL 	0 0	; self
	14	[350]	GETTABLE 	0 0 -2	; "ui"
	15	[350]	SELF     	0 0 -5	; "handleEvent"
	16	[350]	GETUPVAL 	2 1	; Event
	17	[350]	SELF     	2 2 -6	; "new"
	18	[350]	LOADK    	4 -7	; "UpdatePos"
	19	[350]	CALL     	2 3 0
	20	[350]	CALL     	0 0 1
	21	[351]	RETURN   	0 1

function <./frontend/apps/reader/modules/readertypography.lua:352,370> (35 instructions, 140 bytes at 0x7faa7840db90)
0 params, 8 slots, 3 upvalues, 1 local, 12 constants, 4 functions
	1	[353]	GETGLOBAL	0 -1	; G_reader_settings
	2	[353]	SELF     	0 0 -2	; "nilOrTrue"
	3	[353]	LOADK    	2 -3	; "hyphenation"
	4	[353]	CALL     	0 3 2
	5	[354]	GETUPVAL 	1 0	; UIManager
	6	[354]	SELF     	1 1 -4	; "show"
	7	[354]	GETUPVAL 	3 1	; MultiConfirmBox
	8	[354]	SELF     	3 3 -5	; "new"
	9	[354]	NEWTABLE 	5 0 5
	10	[355]	TEST     	0 0 0
	11	[355]	JMP      	5	; to 17
	12	[355]	GETUPVAL 	6 2	; _
	13	[355]	LOADK    	7 -7	; "Would you like to enable or disable hyphenation by default?\n\nThe current default (\226\152\133) is enabled."
	14	[355]	CALL     	6 2 2
	15	[356]	TEST     	6 0 1
	16	[356]	JMP      	3	; to 20
	17	[356]	GETUPVAL 	6 2	; _
	18	[356]	LOADK    	7 -8	; "Would you like to enable or disable hyphenation by default?\n\nThe current default (\226\152\133) is disabled."
	19	[356]	CALL     	6 2 2
	20	[356]	SETTABLE 	5 -6 6	; "text" -
	21	[359]	CLOSURE  	6 0	; 0x7faa7840e070
	22	[359]	MOVE     	0 0
	23	[359]	GETUPVAL 	0 2	; _
	24	[359]	SETTABLE 	5 -9 6	; "choice1_text_func" -
	25	[362]	CLOSURE  	6 1	; 0x7faa7840b960
	26	[362]	SETTABLE 	5 -10 6	; "choice1_callback" -
	27	[365]	CLOSURE  	6 2	; 0x7faa7840b9e0
	28	[365]	MOVE     	0 0
	29	[365]	GETUPVAL 	0 2	; _
	30	[365]	SETTABLE 	5 -11 6	; "choice2_text_func" -
	31	[368]	CLOSURE  	6 3	; 0x7faa7840b180
	32	[368]	SETTABLE 	5 -12 6	; "choice2_callback" -
	33	[354]	CALL     	3 3 0
	34	[354]	CALL     	1 0 1
	35	[370]	RETURN   	0 1

function <./frontend/apps/reader/modules/readertypography.lua:357,359> (13 instructions, 52 bytes at 0x7faa7840e070)
0 params, 2 slots, 2 upvalues, 0 locals, 2 constants, 0 functions
	1	[358]	GETUPVAL 	0 0	; hyphenation
	2	[358]	TEST     	0 0 0
	3	[358]	JMP      	5	; to 9
	4	[358]	GETUPVAL 	0 1	; _
	5	[358]	LOADK    	1 -1	; "Disable"
	6	[358]	CALL     	0 2 2
	7	[358]	TEST     	0 0 1
	8	[358]	JMP      	3	; to 12
	9	[358]	GETUPVAL 	0 1	; _
	10	[358]	LOADK    	1 -2	; "Disable (\226\152\133)"
	11	[358]	CALL     	0 2 2
	12	[358]	RETURN   	0 2
	13	[359]	RETURN   	0 1

function <./frontend/apps/reader/modules/readertypography.lua:360,362> (6 instructions, 24 bytes at 0x7faa7840b960)
0 params, 4 slots, 0 upvalues, 0 locals, 3 constants, 0 functions
	1	[361]	GETGLOBAL	0 -1	; G_reader_settings
	2	[361]	SELF     	0 0 -2	; "saveSetting"
	3	[361]	LOADK    	2 -3	; "hyphenation"
	4	[361]	LOADBOOL 	3 0 0
	5	[361]	CALL     	0 4 1
	6	[362]	RETURN   	0 1

function <./frontend/apps/reader/modules/readertypography.lua:363,365> (13 instructions, 52 bytes at 0x7faa7840b9e0)
0 params, 2 slots, 2 upvalues, 0 locals, 2 constants, 0 functions
	1	[364]	GETUPVAL 	0 0	; hyphenation
	2	[364]	TEST     	0 0 0
	3	[364]	JMP      	5	; to 9
	4	[364]	GETUPVAL 	0 1	; _
	5	[364]	LOADK    	1 -1	; "Enable (\226\152\133)"
	6	[364]	CALL     	0 2 2
	7	[364]	TEST     	0 0 1
	8	[364]	JMP      	3	; to 12
	9	[364]	GETUPVAL 	0 1	; _
	10	[364]	LOADK    	1 -2	; "Enable"
	11	[364]	CALL     	0 2 2
	12	[364]	RETURN   	0 2
	13	[365]	RETURN   	0 1

function <./frontend/apps/reader/modules/readertypography.lua:366,368> (6 instructions, 24 bytes at 0x7faa7840b180)
0 params, 4 slots, 0 upvalues, 0 locals, 3 constants, 0 functions
	1	[367]	GETGLOBAL	0 -1	; G_reader_settings
	2	[367]	SELF     	0 0 -2	; "saveSetting"
	3	[367]	LOADK    	2 -3	; "hyphenation"
	4	[367]	LOADBOOL 	3 1 0
	5	[367]	CALL     	0 4 1
	6	[368]	RETURN   	0 1

function <./frontend/apps/reader/modules/readertypography.lua:371,373> (4 instructions, 16 bytes at 0x7faa78409520)
0 params, 2 slots, 1 upvalue, 0 locals, 1 constant, 0 functions
	1	[372]	GETUPVAL 	0 0	; self
	2	[372]	GETTABLE 	0 0 -1	; "hyphenation"
	3	[372]	RETURN   	0 2
	4	[373]	RETURN   	0 1

function <./frontend/apps/reader/modules/readertypography.lua:376,387> (31 instructions, 124 bytes at 0x7faa7840c4b0)
0 params, 6 slots, 2 upvalues, 0 locals, 6 constants, 0 functions
	1	[379]	GETGLOBAL	0 -1	; G_reader_settings
	2	[379]	SELF     	0 0 -2	; "readSetting"
	3	[379]	LOADK    	2 -3	; "hyph_left_hyphen_min"
	4	[379]	CALL     	0 3 2
	5	[379]	TEST     	0 0 1
	6	[379]	JMP      	6	; to 13
	7	[380]	GETGLOBAL	0 -1	; G_reader_settings
	8	[380]	SELF     	0 0 -2	; "readSetting"
	9	[380]	LOADK    	2 -4	; "hyph_right_hyphen_min"
	10	[380]	CALL     	0 3 2
	11	[380]	TEST     	0 0 0
	12	[380]	JMP      	14	; to 27
	13	[382]	GETUPVAL 	0 0	; T
	14	[382]	GETUPVAL 	1 1	; _
	15	[382]	LOADK    	2 -5	; "Left/right minimal sizes: %1 - %2"
	16	[382]	CALL     	1 2 2
	17	[383]	GETGLOBAL	2 -1	; G_reader_settings
	18	[383]	SELF     	2 2 -2	; "readSetting"
	19	[383]	LOADK    	4 -3	; "hyph_left_hyphen_min"
	20	[383]	CALL     	2 3 2
	21	[384]	GETGLOBAL	3 -1	; G_reader_settings
	22	[384]	SELF     	3 3 -2	; "readSetting"
	23	[384]	LOADK    	5 -4	; "hyph_right_hyphen_min"
	24	[384]	CALL     	3 3 0
	25	[382]	TAILCALL 	0 0 0
	26	[384]	RETURN   	0 0
	27	[386]	GETUPVAL 	0 1	; _
	28	[386]	LOADK    	1 -6	; "Left/right minimal sizes: language defaults"
	29	[386]	TAILCALL 	0 2 0
	30	[386]	RETURN   	0 0
	31	[387]	RETURN   	0 1

function <./frontend/apps/reader/modules/readertypography.lua:388,434> (73 instructions, 292 bytes at 0x7faa7840cfa0)
0 params, 11 slots, 6 upvalues, 6 locals, 36 constants, 1 function
	1	[389]	GETGLOBAL	0 -1	; require
	2	[389]	LOADK    	1 -2	; "/ui/widget/doublespinwidget"
	3	[389]	CALL     	0 2 2
	4	[391]	LOADK    	1 -3	; 2
	5	[392]	LOADK    	2 -3	; 2
	6	[393]	GETGLOBAL	3 -4	; cre
	7	[393]	GETTABLE 	3 3 -5	; "getSelectedHyphDict"
	8	[393]	CALL     	3 1 2
	9	[394]	GETUPVAL 	4 0	; HYPH_DICT_NAME_TO_LANG_NAME_TAG
	10	[394]	GETTABLE 	4 4 3
	11	[395]	TEST     	4 0 0
	12	[395]	JMP      	8	; to 21
	13	[396]	GETTABLE 	5 4 -6	; 3
	14	[396]	TESTSET  	1 5 1
	15	[396]	JMP      	1	; to 17
	16	[396]	LOADK    	1 -3	; 2
	17	[397]	GETTABLE 	5 4 -7	; 4
	18	[397]	TESTSET  	2 5 1
	19	[397]	JMP      	1	; to 21
	20	[397]	LOADK    	2 -3	; 2
	21	[399]	SELF     	5 0 -8	; "new"
	22	[399]	NEWTABLE 	7 0 15
	23	[405]	GETGLOBAL	8 -10	; G_reader_settings
	24	[405]	SELF     	8 8 -11	; "readSetting"
	25	[405]	LOADK    	10 -12	; "hyph_left_hyphen_min"
	26	[405]	CALL     	8 3 2
	27	[405]	TEST     	8 0 1
	28	[405]	JMP      	1	; to 30
	29	[405]	MOVE     	8 1
	30	[405]	SETTABLE 	7 -9 8	; "left_value" -
	31	[406]	SETTABLE 	7 -13 -14	; "left_min" 1
	32	[407]	SETTABLE 	7 -15 -16	; "left_max" 10
	33	[408]	GETGLOBAL	8 -10	; G_reader_settings
	34	[408]	SELF     	8 8 -11	; "readSetting"
	35	[408]	LOADK    	10 -18	; "hyph_right_hyphen_min"
	36	[408]	CALL     	8 3 2
	37	[408]	TEST     	8 0 1
	38	[408]	JMP      	1	; to 40
	39	[408]	MOVE     	8 2
	40	[408]	SETTABLE 	7 -17 8	; "right_value" -
	41	[409]	SETTABLE 	7 -19 -14	; "right_min" 1
	42	[410]	SETTABLE 	7 -20 -16	; "right_max" 10
	43	[411]	SETTABLE 	7 -21 1	; "left_default" -
	44	[412]	SETTABLE 	7 -22 2	; "right_default" -
	45	[415]	GETUPVAL 	8 1	; Screen
	46	[415]	SELF     	8 8 -24	; "getWidth"
	47	[415]	CALL     	8 2 2
	48	[415]	MUL      	8 8 -25	; - 0.6
	49	[415]	SETTABLE 	7 -23 8	; "width" -
	50	[416]	SETTABLE 	7 -26 -27	; "default_values" true
	51	[417]	GETUPVAL 	8 2	; _
	52	[417]	LOADK    	9 -29	; "Use language defaults"
	53	[417]	CALL     	8 2 2
	54	[417]	SETTABLE 	7 -28 8	; "default_text" -
	55	[418]	GETUPVAL 	8 2	; _
	56	[418]	LOADK    	9 -31	; "Hyphenation limits"
	57	[418]	CALL     	8 2 2
	58	[418]	SETTABLE 	7 -30 8	; "title_text" -
	59	[419]	GETUPVAL 	8 2	; _
	60	[422]	LOADK    	9 -33	; "Set minimum length before hyphenation occurs.\nThese settings will apply to all books with any hyphenation dictionary.\n'Use language defaults' resets them."
	61	[419]	CALL     	8 2 2
	62	[422]	SETTABLE 	7 -32 8	; "info_text" -
	63	[423]	SETTABLE 	7 -34 -27	; "keep_shown_on_apply" true
	64	[431]	CLOSURE  	8 0	; 0x7faa7840e440
	65	[431]	GETUPVAL 	0 3	; self
	66	[431]	GETUPVAL 	0 4	; Event
	67	[431]	SETTABLE 	7 -35 8	; "callback" -
	68	[399]	CALL     	5 3 2
	69	[433]	GETUPVAL 	6 5	; UIManager
	70	[433]	SELF     	6 6 -36	; "show"
	71	[433]	MOVE     	8 5
	72	[433]	CALL     	6 3 1
	73	[434]	RETURN   	0 1

function <./frontend/apps/reader/modules/readertypography.lua:424,431> (43 instructions, 172 bytes at 0x7faa7840e440)
2 params, 7 slots, 2 upvalues, 2 locals, 13 constants, 0 functions
	1	[425]	GETGLOBAL	2 -1	; G_reader_settings
	2	[425]	SELF     	2 2 -2	; "saveSetting"
	3	[425]	LOADK    	4 -3	; "hyph_left_hyphen_min"
	4	[425]	MOVE     	5 0
	5	[425]	CALL     	2 4 1
	6	[426]	GETGLOBAL	2 -1	; G_reader_settings
	7	[426]	SELF     	2 2 -2	; "saveSetting"
	8	[426]	LOADK    	4 -4	; "hyph_right_hyphen_min"
	9	[426]	MOVE     	5 1
	10	[426]	CALL     	2 4 1
	11	[427]	GETUPVAL 	2 0	; self
	12	[427]	GETTABLE 	2 2 -5	; "ui"
	13	[427]	GETTABLE 	2 2 -6	; "document"
	14	[427]	SELF     	2 2 -7	; "setHyphLeftHyphenMin"
	15	[427]	GETGLOBAL	4 -1	; G_reader_settings
	16	[427]	SELF     	4 4 -8	; "readSetting"
	17	[427]	LOADK    	6 -3	; "hyph_left_hyphen_min"
	18	[427]	CALL     	4 3 2
	19	[427]	TEST     	4 0 1
	20	[427]	JMP      	1	; to 22
	21	[427]	LOADK    	4 -9	; 0
	22	[427]	CALL     	2 3 1
	23	[428]	GETUPVAL 	2 0	; self
	24	[428]	GETTABLE 	2 2 -5	; "ui"
	25	[428]	GETTABLE 	2 2 -6	; "document"
	26	[428]	SELF     	2 2 -10	; "setHyphRightHyphenMin"
	27	[428]	GETGLOBAL	4 -1	; G_reader_settings
	28	[428]	SELF     	4 4 -8	; "readSetting"
	29	[428]	LOADK    	6 -4	; "hyph_right_hyphen_min"
	30	[428]	CALL     	4 3 2
	31	[428]	TEST     	4 0 1
	32	[428]	JMP      	1	; to 34
	33	[428]	LOADK    	4 -9	; 0
	34	[428]	CALL     	2 3 1
	35	[430]	GETUPVAL 	2 0	; self
	36	[430]	GETTABLE 	2 2 -5	; "ui"
	37	[430]	SELF     	2 2 -11	; "handleEvent"
	38	[430]	GETUPVAL 	4 1	; Event
	39	[430]	SELF     	4 4 -12	; "new"
	40	[430]	LOADK    	6 -13	; "UpdatePos"
	41	[430]	CALL     	4 3 0
	42	[430]	CALL     	2 0 1
	43	[431]	RETURN   	0 1

function <./frontend/apps/reader/modules/readertypography.lua:435,437> (4 instructions, 16 bytes at 0x7faa7840eba0)
0 params, 2 slots, 1 upvalue, 0 locals, 1 constant, 0 functions
	1	[436]	GETUPVAL 	0 0	; self
	2	[436]	GETTABLE 	0 0 -1	; "hyphenation"
	3	[436]	RETURN   	0 2
	4	[437]	RETURN   	0 1

function <./frontend/apps/reader/modules/readertypography.lua:441,445> (21 instructions, 84 bytes at 0x7faa7840e900)
0 params, 5 slots, 2 upvalues, 0 locals, 7 constants, 0 functions
	1	[442]	GETUPVAL 	0 0	; self
	2	[442]	GETUPVAL 	1 0	; self
	3	[442]	GETTABLE 	1 1 -1	; "hyph_trust_soft_hyphens"
	4	[442]	NOT      	1 1
	5	[442]	SETTABLE 	0 -1 1	; "hyph_trust_soft_hyphens" -
	6	[443]	GETUPVAL 	0 0	; self
	7	[443]	GETTABLE 	0 0 -2	; "ui"
	8	[443]	GETTABLE 	0 0 -3	; "document"
	9	[443]	SELF     	0 0 -4	; "setTrustSoftHyphens"
	10	[443]	GETUPVAL 	2 0	; self
	11	[443]	GETTABLE 	2 2 -1	; "hyph_trust_soft_hyphens"
	12	[443]	CALL     	0 3 1
	13	[444]	GETUPVAL 	0 0	; self
	14	[444]	GETTABLE 	0 0 -2	; "ui"
	15	[444]	SELF     	0 0 -5	; "handleEvent"
	16	[444]	GETUPVAL 	2 1	; Event
	17	[444]	SELF     	2 2 -6	; "new"
	18	[444]	LOADK    	4 -7	; "UpdatePos"
	19	[444]	CALL     	2 3 0
	20	[444]	CALL     	0 0 1
	21	[445]	RETURN   	0 1

function <./frontend/apps/reader/modules/readertypography.lua:446,464> (35 instructions, 140 bytes at 0x7faa7840ca50)
0 params, 8 slots, 3 upvalues, 1 local, 12 constants, 4 functions
	1	[447]	GETGLOBAL	0 -1	; G_reader_settings
	2	[447]	SELF     	0 0 -2	; "isTrue"
	3	[447]	LOADK    	2 -3	; "hyph_trust_soft_hyphens"
	4	[447]	CALL     	0 3 2
	5	[448]	GETUPVAL 	1 0	; UIManager
	6	[448]	SELF     	1 1 -4	; "show"
	7	[448]	GETUPVAL 	3 1	; MultiConfirmBox
	8	[448]	SELF     	3 3 -5	; "new"
	9	[448]	NEWTABLE 	5 0 5
	10	[449]	TEST     	0 0 0
	11	[449]	JMP      	5	; to 17
	12	[449]	GETUPVAL 	6 2	; _
	13	[449]	LOADK    	7 -7	; "Would you like to enable or disable trusting soft hyphens by default?\n\nThe current default (\226\152\133) is enabled."
	14	[449]	CALL     	6 2 2
	15	[450]	TEST     	6 0 1
	16	[450]	JMP      	3	; to 20
	17	[450]	GETUPVAL 	6 2	; _
	18	[450]	LOADK    	7 -8	; "Would you like to enable or disable trusting soft hyphens by default?\n\nThe current default (\226\152\133) is disabled."
	19	[450]	CALL     	6 2 2
	20	[450]	SETTABLE 	5 -6 6	; "text" -
	21	[453]	CLOSURE  	6 0	; 0x7faa7840f900
	22	[453]	MOVE     	0 0
	23	[453]	GETUPVAL 	0 2	; _
	24	[453]	SETTABLE 	5 -9 6	; "choice1_text_func" -
	25	[456]	CLOSURE  	6 1	; 0x7faa7840fb20
	26	[456]	SETTABLE 	5 -10 6	; "choice1_callback" -
	27	[459]	CLOSURE  	6 2	; 0x7faa7840fbe0
	28	[459]	MOVE     	0 0
	29	[459]	GETUPVAL 	0 2	; _
	30	[459]	SETTABLE 	5 -11 6	; "choice2_text_func" -
	31	[462]	CLOSURE  	6 3	; 0x7faa784104b0
	32	[462]	SETTABLE 	5 -12 6	; "choice2_callback" -
	33	[448]	CALL     	3 3 0
	34	[448]	CALL     	1 0 1
	35	[464]	RETURN   	0 1

function <./frontend/apps/reader/modules/readertypography.lua:451,453> (13 instructions, 52 bytes at 0x7faa7840f900)
0 params, 2 slots, 2 upvalues, 0 locals, 2 constants, 0 functions
	1	[452]	GETUPVAL 	0 0	; hyph_trust_soft_hyphens
	2	[452]	TEST     	0 0 0
	3	[452]	JMP      	5	; to 9
	4	[452]	GETUPVAL 	0 1	; _
	5	[452]	LOADK    	1 -1	; "Disable"
	6	[452]	CALL     	0 2 2
	7	[452]	TEST     	0 0 1
	8	[452]	JMP      	3	; to 12
	9	[452]	GETUPVAL 	0 1	; _
	10	[452]	LOADK    	1 -2	; "Disable (\226\152\133)"
	11	[452]	CALL     	0 2 2
	12	[452]	RETURN   	0 2
	13	[453]	RETURN   	0 1

function <./frontend/apps/reader/modules/readertypography.lua:454,456> (6 instructions, 24 bytes at 0x7faa7840fb20)
0 params, 4 slots, 0 upvalues, 0 locals, 3 constants, 0 functions
	1	[455]	GETGLOBAL	0 -1	; G_reader_settings
	2	[455]	SELF     	0 0 -2	; "saveSetting"
	3	[455]	LOADK    	2 -3	; "hyph_trust_soft_hyphens"
	4	[455]	LOADBOOL 	3 0 0
	5	[455]	CALL     	0 4 1
	6	[456]	RETURN   	0 1

function <./frontend/apps/reader/modules/readertypography.lua:457,459> (13 instructions, 52 bytes at 0x7faa7840fbe0)
0 params, 2 slots, 2 upvalues, 0 locals, 2 constants, 0 functions
	1	[458]	GETUPVAL 	0 0	; hyph_trust_soft_hyphens
	2	[458]	TEST     	0 0 0
	3	[458]	JMP      	5	; to 9
	4	[458]	GETUPVAL 	0 1	; _
	5	[458]	LOADK    	1 -1	; "Enable (\226\152\133)"
	6	[458]	CALL     	0 2 2
	7	[458]	TEST     	0 0 1
	8	[458]	JMP      	3	; to 12
	9	[458]	GETUPVAL 	0 1	; _
	10	[458]	LOADK    	1 -2	; "Enable"
	11	[458]	CALL     	0 2 2
	12	[458]	RETURN   	0 2
	13	[459]	RETURN   	0 1

function <./frontend/apps/reader/modules/readertypography.lua:460,462> (6 instructions, 24 bytes at 0x7faa784104b0)
0 params, 4 slots, 0 upvalues, 0 locals, 3 constants, 0 functions
	1	[461]	GETGLOBAL	0 -1	; G_reader_settings
	2	[461]	SELF     	0 0 -2	; "saveSetting"
	3	[461]	LOADK    	2 -3	; "hyph_trust_soft_hyphens"
	4	[461]	LOADBOOL 	3 1 0
	5	[461]	CALL     	0 4 1
	6	[462]	RETURN   	0 1

function <./frontend/apps/reader/modules/readertypography.lua:465,467> (12 instructions, 48 bytes at 0x7faa7840fda0)
0 params, 2 slots, 1 upvalue, 0 locals, 3 constants, 0 functions
	1	[466]	GETUPVAL 	0 0	; self
	2	[466]	GETTABLE 	0 0 -1	; "hyphenation"
	3	[466]	TEST     	0 0 0
	4	[466]	JMP      	6	; to 11
	5	[466]	GETUPVAL 	0 0	; self
	6	[466]	GETTABLE 	0 0 -2	; "hyph_trust_soft_hyphens"
	7	[466]	TEST     	0 0 1
	8	[466]	JMP      	2	; to 11
	9	[466]	GETUPVAL 	0 0	; self
	10	[466]	GETTABLE 	0 0 -3	; "hyph_soft_hyphens_only"
	11	[466]	RETURN   	0 2
	12	[467]	RETURN   	0 1

function <./frontend/apps/reader/modules/readertypography.lua:468,470> (9 instructions, 36 bytes at 0x7faa78410570)
0 params, 2 slots, 1 upvalue, 0 locals, 2 constants, 0 functions
	1	[469]	GETUPVAL 	0 0	; self
	2	[469]	GETTABLE 	0 0 -1	; "hyphenation"
	3	[469]	TEST     	0 0 0
	4	[469]	JMP      	3	; to 8
	5	[469]	GETUPVAL 	0 0	; self
	6	[469]	GETTABLE 	0 0 -2	; "hyph_soft_hyphens_only"
	7	[469]	NOT      	0 0
	8	[469]	RETURN   	0 2
	9	[470]	RETURN   	0 1

function <./frontend/apps/reader/modules/readertypography.lua:474,477> (10 instructions, 40 bytes at 0x7faa78410ba0)
0 params, 4 slots, 3 upvalues, 0 locals, 2 constants, 0 functions
	1	[476]	GETUPVAL 	0 0	; T
	2	[476]	GETUPVAL 	1 1	; _
	3	[476]	LOADK    	2 -1	; "Hyphenation dictionary: %1"
	4	[476]	CALL     	1 2 2
	5	[476]	GETUPVAL 	2 2	; self
	6	[476]	SELF     	2 2 -2	; "getCurrentDefaultHyphDictLanguage"
	7	[476]	CALL     	2 2 0
	8	[476]	TAILCALL 	0 0 0
	9	[476]	RETURN   	0 0
	10	[477]	RETURN   	0 1

function <./frontend/apps/reader/modules/readertypography.lua:478,484> (27 instructions, 108 bytes at 0x7faa784110e0)
0 params, 5 slots, 2 upvalues, 0 locals, 10 constants, 0 functions
	1	[479]	GETUPVAL 	0 0	; self
	2	[479]	SETTABLE 	0 -1 -2	; "hyph_soft_hyphens_only" false
	3	[480]	GETUPVAL 	0 0	; self
	4	[480]	SETTABLE 	0 -3 -2	; "hyph_force_algorithmic" false
	5	[481]	GETUPVAL 	0 0	; self
	6	[481]	GETTABLE 	0 0 -4	; "ui"
	7	[481]	GETTABLE 	0 0 -5	; "document"
	8	[481]	SELF     	0 0 -6	; "setTextHyphenationSoftHyphensOnly"
	9	[481]	GETUPVAL 	2 0	; self
	10	[481]	GETTABLE 	2 2 -1	; "hyph_soft_hyphens_only"
	11	[481]	CALL     	0 3 1
	12	[482]	GETUPVAL 	0 0	; self
	13	[482]	GETTABLE 	0 0 -4	; "ui"
	14	[482]	GETTABLE 	0 0 -5	; "document"
	15	[482]	SELF     	0 0 -7	; "setTextHyphenationForceAlgorithmic"
	16	[482]	GETUPVAL 	2 0	; self
	17	[482]	GETTABLE 	2 2 -3	; "hyph_force_algorithmic"
	18	[482]	CALL     	0 3 1
	19	[483]	GETUPVAL 	0 0	; self
	20	[483]	GETTABLE 	0 0 -4	; "ui"
	21	[483]	SELF     	0 0 -8	; "handleEvent"
	22	[483]	GETUPVAL 	2 1	; Event
	23	[483]	SELF     	2 2 -9	; "new"
	24	[483]	LOADK    	4 -10	; "UpdatePos"
	25	[483]	CALL     	2 3 0
	26	[483]	CALL     	0 0 1
	27	[484]	RETURN   	0 1

function <./frontend/apps/reader/modules/readertypography.lua:486,489> (16 instructions, 64 bytes at 0x7faa784111e0)
0 params, 2 slots, 1 upvalue, 0 locals, 3 constants, 0 functions
	1	[487]	GETUPVAL 	0 0	; self
	2	[487]	GETTABLE 	0 0 -1	; "hyphenation"
	3	[487]	TEST     	0 0 0
	4	[487]	JMP      	10	; to 15
	5	[487]	GETUPVAL 	0 0	; self
	6	[487]	GETTABLE 	0 0 -2	; "hyph_soft_hyphens_only"
	7	[488]	TEST     	0 0 1
	8	[488]	JMP      	4	; to 13
	9	[488]	GETUPVAL 	0 0	; self
	10	[488]	GETTABLE 	0 0 -3	; "hyph_force_algorithmic"
	11	[488]	NOT      	0 0
	12	[488]	JMP      	2	; to 15
	13	[488]	LOADBOOL 	0 0 1
	14	[488]	LOADBOOL 	0 1 0
	15	[488]	RETURN   	0 2
	16	[489]	RETURN   	0 1

function <./frontend/apps/reader/modules/readertypography.lua:490,492> (4 instructions, 16 bytes at 0x7faa784117c0)
0 params, 2 slots, 1 upvalue, 0 locals, 1 constant, 0 functions
	1	[491]	GETUPVAL 	0 0	; self
	2	[491]	GETTABLE 	0 0 -1	; "hyphenation"
	3	[491]	RETURN   	0 2
	4	[492]	RETURN   	0 1

function <./frontend/apps/reader/modules/readertypography.lua:496,502> (30 instructions, 120 bytes at 0x7faa78411b80)
0 params, 5 slots, 2 upvalues, 0 locals, 10 constants, 0 functions
	1	[497]	GETUPVAL 	0 0	; self
	2	[497]	GETUPVAL 	1 0	; self
	3	[497]	GETTABLE 	1 1 -1	; "hyph_force_algorithmic"
	4	[497]	NOT      	1 1
	5	[497]	SETTABLE 	0 -1 1	; "hyph_force_algorithmic" -
	6	[498]	GETUPVAL 	0 0	; self
	7	[498]	SETTABLE 	0 -2 -3	; "hyph_soft_hyphens_only" false
	8	[499]	GETUPVAL 	0 0	; self
	9	[499]	GETTABLE 	0 0 -4	; "ui"
	10	[499]	GETTABLE 	0 0 -5	; "document"
	11	[499]	SELF     	0 0 -6	; "setTextHyphenationSoftHyphensOnly"
	12	[499]	GETUPVAL 	2 0	; self
	13	[499]	GETTABLE 	2 2 -2	; "hyph_soft_hyphens_only"
	14	[499]	CALL     	0 3 1
	15	[500]	GETUPVAL 	0 0	; self
	16	[500]	GETTABLE 	0 0 -4	; "ui"
	17	[500]	GETTABLE 	0 0 -5	; "document"
	18	[500]	SELF     	0 0 -7	; "setTextHyphenationForceAlgorithmic"
	19	[500]	GETUPVAL 	2 0	; self
	20	[500]	GETTABLE 	2 2 -1	; "hyph_force_algorithmic"
	21	[500]	CALL     	0 3 1
	22	[501]	GETUPVAL 	0 0	; self
	23	[501]	GETTABLE 	0 0 -4	; "ui"
	24	[501]	SELF     	0 0 -8	; "handleEvent"
	25	[501]	GETUPVAL 	2 1	; Event
	26	[501]	SELF     	2 2 -9	; "new"
	27	[501]	LOADK    	4 -10	; "UpdatePos"
	28	[501]	CALL     	2 3 0
	29	[501]	CALL     	0 0 1
	30	[502]	RETURN   	0 1

function <./frontend/apps/reader/modules/readertypography.lua:503,521> (35 instructions, 140 bytes at 0x7faa78411c40)
0 params, 8 slots, 3 upvalues, 1 local, 12 constants, 4 functions
	1	[504]	GETGLOBAL	0 -1	; G_reader_settings
	2	[504]	SELF     	0 0 -2	; "isTrue"
	3	[504]	LOADK    	2 -3	; "hyph_force_algorithmic"
	4	[504]	CALL     	0 3 2
	5	[505]	GETUPVAL 	1 0	; UIManager
	6	[505]	SELF     	1 1 -4	; "show"
	7	[505]	GETUPVAL 	3 1	; MultiConfirmBox
	8	[505]	SELF     	3 3 -5	; "new"
	9	[505]	NEWTABLE 	5 0 5
	10	[506]	TEST     	0 0 0
	11	[506]	JMP      	5	; to 17
	12	[506]	GETUPVAL 	6 2	; _
	13	[506]	LOADK    	7 -7	; "Would you like to enable or disable algorithmic hyphenation by default?\n\nThe current default (\226\152\133) is enabled."
	14	[506]	CALL     	6 2 2
	15	[507]	TEST     	6 0 1
	16	[507]	JMP      	3	; to 20
	17	[507]	GETUPVAL 	6 2	; _
	18	[507]	LOADK    	7 -8	; "Would you like to enable or disable algorithmic hyphenation by default?\n\nThe current default (\226\152\133) is disabled."
	19	[507]	CALL     	6 2 2
	20	[507]	SETTABLE 	5 -6 6	; "text" -
	21	[510]	CLOSURE  	6 0	; 0x7faa784121e0
	22	[510]	MOVE     	0 0
	23	[510]	GETUPVAL 	0 2	; _
	24	[510]	SETTABLE 	5 -9 6	; "choice1_text_func" -
	25	[513]	CLOSURE  	6 1	; 0x7faa78412390
	26	[513]	SETTABLE 	5 -10 6	; "choice1_callback" -
	27	[516]	CLOSURE  	6 2	; 0x7faa78504080
	28	[516]	MOVE     	0 0
	29	[516]	GETUPVAL 	0 2	; _
	30	[516]	SETTABLE 	5 -11 6	; "choice2_text_func" -
	31	[519]	CLOSURE  	6 3	; 0x7faa785043f0
	32	[519]	SETTABLE 	5 -12 6	; "choice2_callback" -
	33	[505]	CALL     	3 3 0
	34	[505]	CALL     	1 0 1
	35	[521]	RETURN   	0 1

function <./frontend/apps/reader/modules/readertypography.lua:508,510> (13 instructions, 52 bytes at 0x7faa784121e0)
0 params, 2 slots, 2 upvalues, 0 locals, 2 constants, 0 functions
	1	[509]	GETUPVAL 	0 0	; hyph_force_algorithmic
	2	[509]	TEST     	0 0 0
	3	[509]	JMP      	5	; to 9
	4	[509]	GETUPVAL 	0 1	; _
	5	[509]	LOADK    	1 -1	; "Disable"
	6	[509]	CALL     	0 2 2
	7	[509]	TEST     	0 0 1
	8	[509]	JMP      	3	; to 12
	9	[509]	GETUPVAL 	0 1	; _
	10	[509]	LOADK    	1 -2	; "Disable (\226\152\133)"
	11	[509]	CALL     	0 2 2
	12	[509]	RETURN   	0 2
	13	[510]	RETURN   	0 1

function <./frontend/apps/reader/modules/readertypography.lua:511,513> (6 instructions, 24 bytes at 0x7faa78412390)
0 params, 4 slots, 0 upvalues, 0 locals, 3 constants, 0 functions
	1	[512]	GETGLOBAL	0 -1	; G_reader_settings
	2	[512]	SELF     	0 0 -2	; "saveSetting"
	3	[512]	LOADK    	2 -3	; "hyph_force_algorithmic"
	4	[512]	LOADBOOL 	3 0 0
	5	[512]	CALL     	0 4 1
	6	[513]	RETURN   	0 1

function <./frontend/apps/reader/modules/readertypography.lua:514,516> (13 instructions, 52 bytes at 0x7faa78504080)
0 params, 2 slots, 2 upvalues, 0 locals, 2 constants, 0 functions
	1	[515]	GETUPVAL 	0 0	; hyph_force_algorithmic
	2	[515]	TEST     	0 0 0
	3	[515]	JMP      	5	; to 9
	4	[515]	GETUPVAL 	0 1	; _
	5	[515]	LOADK    	1 -1	; "Enable (\226\152\133)"
	6	[515]	CALL     	0 2 2
	7	[515]	TEST     	0 0 1
	8	[515]	JMP      	3	; to 12
	9	[515]	GETUPVAL 	0 1	; _
	10	[515]	LOADK    	1 -2	; "Enable"
	11	[515]	CALL     	0 2 2
	12	[515]	RETURN   	0 2
	13	[516]	RETURN   	0 1

function <./frontend/apps/reader/modules/readertypography.lua:517,519> (6 instructions, 24 bytes at 0x7faa785043f0)
0 params, 4 slots, 0 upvalues, 0 locals, 3 constants, 0 functions
	1	[518]	GETGLOBAL	0 -1	; G_reader_settings
	2	[518]	SELF     	0 0 -2	; "saveSetting"
	3	[518]	LOADK    	2 -3	; "hyph_force_algorithmic"
	4	[518]	LOADBOOL 	3 1 0
	5	[518]	CALL     	0 4 1
	6	[519]	RETURN   	0 1

function <./frontend/apps/reader/modules/readertypography.lua:522,526> (15 instructions, 60 bytes at 0x7faa785044b0)
0 params, 2 slots, 1 upvalue, 0 locals, 3 constants, 0 functions
	1	[525]	GETUPVAL 	0 0	; self
	2	[525]	GETTABLE 	0 0 -1	; "hyphenation"
	3	[525]	TEST     	0 0 0
	4	[525]	JMP      	9	; to 14
	5	[525]	GETUPVAL 	0 0	; self
	6	[525]	GETTABLE 	0 0 -2	; "hyph_soft_hyphens_only"
	7	[525]	TEST     	0 0 1
	8	[525]	JMP      	3	; to 12
	9	[525]	GETUPVAL 	0 0	; self
	10	[525]	GETTABLE 	0 0 -3	; "hyph_force_algorithmic"
	11	[525]	JMP      	2	; to 14
	12	[525]	LOADBOOL 	0 0 1
	13	[525]	LOADBOOL 	0 1 0
	14	[525]	RETURN   	0 2
	15	[526]	RETURN   	0 1

function <./frontend/apps/reader/modules/readertypography.lua:527,529> (4 instructions, 16 bytes at 0x7faa78504b50)
0 params, 2 slots, 1 upvalue, 0 locals, 1 constant, 0 functions
	1	[528]	GETUPVAL 	0 0	; self
	2	[528]	GETTABLE 	0 0 -1	; "hyphenation"
	3	[528]	RETURN   	0 2
	4	[529]	RETURN   	0 1

function <./frontend/apps/reader/modules/readertypography.lua:533,539> (30 instructions, 120 bytes at 0x7faa78504d00)
0 params, 5 slots, 2 upvalues, 0 locals, 10 constants, 0 functions
	1	[534]	GETUPVAL 	0 0	; self
	2	[534]	GETUPVAL 	1 0	; self
	3	[534]	GETTABLE 	1 1 -1	; "hyph_soft_hyphens_only"
	4	[534]	NOT      	1 1
	5	[534]	SETTABLE 	0 -1 1	; "hyph_soft_hyphens_only" -
	6	[535]	GETUPVAL 	0 0	; self
	7	[535]	SETTABLE 	0 -2 -3	; "hyph_force_algorithmic" false
	8	[536]	GETUPVAL 	0 0	; self
	9	[536]	GETTABLE 	0 0 -4	; "ui"
	10	[536]	GETTABLE 	0 0 -5	; "document"
	11	[536]	SELF     	0 0 -6	; "setTextHyphenationSoftHyphensOnly"
	12	[536]	GETUPVAL 	2 0	; self
	13	[536]	GETTABLE 	2 2 -1	; "hyph_soft_hyphens_only"
	14	[536]	CALL     	0 3 1
	15	[537]	GETUPVAL 	0 0	; self
	16	[537]	GETTABLE 	0 0 -4	; "ui"
	17	[537]	GETTABLE 	0 0 -5	; "document"
	18	[537]	SELF     	0 0 -7	; "setTextHyphenationForceAlgorithmic"
	19	[537]	GETUPVAL 	2 0	; self
	20	[537]	GETTABLE 	2 2 -2	; "hyph_force_algorithmic"
	21	[537]	CALL     	0 3 1
	22	[538]	GETUPVAL 	0 0	; self
	23	[538]	GETTABLE 	0 0 -4	; "ui"
	24	[538]	SELF     	0 0 -8	; "handleEvent"
	25	[538]	GETUPVAL 	2 1	; Event
	26	[538]	SELF     	2 2 -9	; "new"
	27	[538]	LOADK    	4 -10	; "UpdatePos"
	28	[538]	CALL     	2 3 0
	29	[538]	CALL     	0 0 1
	30	[539]	RETURN   	0 1

function <./frontend/apps/reader/modules/readertypography.lua:540,558> (35 instructions, 140 bytes at 0x7faa78504dd0)
0 params, 8 slots, 3 upvalues, 1 local, 12 constants, 4 functions
	1	[541]	GETGLOBAL	0 -1	; G_reader_settings
	2	[541]	SELF     	0 0 -2	; "isTrue"
	3	[541]	LOADK    	2 -3	; "hyph_soft_hyphens_only"
	4	[541]	CALL     	0 3 2
	5	[542]	GETUPVAL 	1 0	; UIManager
	6	[542]	SELF     	1 1 -4	; "show"
	7	[542]	GETUPVAL 	3 1	; MultiConfirmBox
	8	[542]	SELF     	3 3 -5	; "new"
	9	[542]	NEWTABLE 	5 0 5
	10	[543]	TEST     	0 0 0
	11	[543]	JMP      	5	; to 17
	12	[543]	GETUPVAL 	6 2	; _
	13	[543]	LOADK    	7 -7	; "Would you like to enable or disable hyphenation with soft hyphens only by default?\n\nThe current default (\226\152\133) is enabled."
	14	[543]	CALL     	6 2 2
	15	[544]	TEST     	6 0 1
	16	[544]	JMP      	3	; to 20
	17	[544]	GETUPVAL 	6 2	; _
	18	[544]	LOADK    	7 -8	; "Would you like to enable or disable hyphenation with soft hyphens only by default?\n\nThe current default (\226\152\133) is disabled."
	19	[544]	CALL     	6 2 2
	20	[544]	SETTABLE 	5 -6 6	; "text" -
	21	[547]	CLOSURE  	6 0	; 0x7faa785053b0
	22	[547]	MOVE     	0 0
	23	[547]	GETUPVAL 	0 2	; _
	24	[547]	SETTABLE 	5 -9 6	; "choice1_text_func" -
	25	[550]	CLOSURE  	6 1	; 0x7faa785055b0
	26	[550]	SETTABLE 	5 -10 6	; "choice1_callback" -
	27	[553]	CLOSURE  	6 2	; 0x7faa785056b0
	28	[553]	MOVE     	0 0
	29	[553]	GETUPVAL 	0 2	; _
	30	[553]	SETTABLE 	5 -11 6	; "choice2_text_func" -
	31	[556]	CLOSURE  	6 3	; 0x7faa78505f70
	32	[556]	SETTABLE 	5 -12 6	; "choice2_callback" -
	33	[542]	CALL     	3 3 0
	34	[542]	CALL     	1 0 1
	35	[558]	RETURN   	0 1

function <./frontend/apps/reader/modules/readertypography.lua:545,547> (13 instructions, 52 bytes at 0x7faa785053b0)
0 params, 2 slots, 2 upvalues, 0 locals, 2 constants, 0 functions
	1	[546]	GETUPVAL 	0 0	; hyph_soft_hyphens_only
	2	[546]	TEST     	0 0 0
	3	[546]	JMP      	5	; to 9
	4	[546]	GETUPVAL 	0 1	; _
	5	[546]	LOADK    	1 -1	; "Disable"
	6	[546]	CALL     	0 2 2
	7	[546]	TEST     	0 0 1
	8	[546]	JMP      	3	; to 12
	9	[546]	GETUPVAL 	0 1	; _
	10	[546]	LOADK    	1 -2	; "Disable (\226\152\133)"
	11	[546]	CALL     	0 2 2
	12	[546]	RETURN   	0 2
	13	[547]	RETURN   	0 1

function <./frontend/apps/reader/modules/readertypography.lua:548,550> (6 instructions, 24 bytes at 0x7faa785055b0)
0 params, 4 slots, 0 upvalues, 0 locals, 3 constants, 0 functions
	1	[549]	GETGLOBAL	0 -1	; G_reader_settings
	2	[549]	SELF     	0 0 -2	; "saveSetting"
	3	[549]	LOADK    	2 -3	; "hyph_soft_hyphens_only"
	4	[549]	LOADBOOL 	3 0 0
	5	[549]	CALL     	0 4 1
	6	[550]	RETURN   	0 1

function <./frontend/apps/reader/modules/readertypography.lua:551,553> (13 instructions, 52 bytes at 0x7faa785056b0)
0 params, 2 slots, 2 upvalues, 0 locals, 2 constants, 0 functions
	1	[552]	GETUPVAL 	0 0	; hyph_soft_hyphens_only
	2	[552]	TEST     	0 0 0
	3	[552]	JMP      	5	; to 9
	4	[552]	GETUPVAL 	0 1	; _
	5	[552]	LOADK    	1 -1	; "Enable (\226\152\133)"
	6	[552]	CALL     	0 2 2
	7	[552]	TEST     	0 0 1
	8	[552]	JMP      	3	; to 12
	9	[552]	GETUPVAL 	0 1	; _
	10	[552]	LOADK    	1 -2	; "Enable"
	11	[552]	CALL     	0 2 2
	12	[552]	RETURN   	0 2
	13	[553]	RETURN   	0 1

function <./frontend/apps/reader/modules/readertypography.lua:554,556> (6 instructions, 24 bytes at 0x7faa78505f70)
0 params, 4 slots, 0 upvalues, 0 locals, 3 constants, 0 functions
	1	[555]	GETGLOBAL	0 -1	; G_reader_settings
	2	[555]	SELF     	0 0 -2	; "saveSetting"
	3	[555]	LOADK    	2 -3	; "hyph_soft_hyphens_only"
	4	[555]	LOADBOOL 	3 1 0
	5	[555]	CALL     	0 4 1
	6	[556]	RETURN   	0 1

function <./frontend/apps/reader/modules/readertypography.lua:559,561> (8 instructions, 32 bytes at 0x7faa78505850)
0 params, 2 slots, 1 upvalue, 0 locals, 2 constants, 0 functions
	1	[560]	GETUPVAL 	0 0	; self
	2	[560]	GETTABLE 	0 0 -1	; "hyphenation"
	3	[560]	TEST     	0 0 0
	4	[560]	JMP      	2	; to 7
	5	[560]	GETUPVAL 	0 0	; self
	6	[560]	GETTABLE 	0 0 -2	; "hyph_soft_hyphens_only"
	7	[560]	RETURN   	0 2
	8	[561]	RETURN   	0 1

function <./frontend/apps/reader/modules/readertypography.lua:562,564> (4 instructions, 16 bytes at 0x7faa785054d0)
0 params, 2 slots, 1 upvalue, 0 locals, 1 constant, 0 functions
	1	[563]	GETUPVAL 	0 0	; self
	2	[563]	GETTABLE 	0 0 -1	; "hyphenation"
	3	[563]	RETURN   	0 2
	4	[564]	RETURN   	0 1

function <./frontend/apps/reader/modules/readertypography.lua:568,582> (39 instructions, 156 bytes at 0x7faa785066d0)
0 params, 4 slots, 3 upvalues, 1 local, 8 constants, 0 functions
	1	[572]	GETUPVAL 	1 0	; self
	2	[572]	GETTABLE 	1 1 -1	; "hyphenation"
	3	[572]	TEST     	1 0 1
	4	[572]	JMP      	5	; to 10
	5	[573]	GETUPVAL 	1 1	; _
	6	[573]	LOADK    	2 -2	; "disabled"
	7	[573]	CALL     	1 2 2
	8	[573]	MOVE     	0 1
	9	[573]	JMP      	22	; to 32
	10	[574]	GETUPVAL 	1 0	; self
	11	[574]	GETTABLE 	1 1 -3	; "hyph_soft_hyphens_only"
	12	[574]	TEST     	1 0 0
	13	[574]	JMP      	5	; to 19
	14	[575]	GETUPVAL 	1 1	; _
	15	[575]	LOADK    	2 -4	; "soft-hyphens only"
	16	[575]	CALL     	1 2 2
	17	[575]	MOVE     	0 1
	18	[575]	JMP      	13	; to 32
	19	[576]	GETUPVAL 	1 0	; self
	20	[576]	GETTABLE 	1 1 -5	; "hyph_force_algorithmic"
	21	[576]	TEST     	1 0 0
	22	[576]	JMP      	5	; to 28
	23	[577]	GETUPVAL 	1 1	; _
	24	[577]	LOADK    	2 -6	; "algorithmic"
	25	[577]	CALL     	1 2 2
	26	[577]	MOVE     	0 1
	27	[577]	JMP      	4	; to 32
	28	[579]	GETUPVAL 	1 0	; self
	29	[579]	SELF     	1 1 -7	; "getCurrentDefaultHyphDictLanguage"
	30	[579]	CALL     	1 2 2
	31	[579]	MOVE     	0 1
	32	[581]	GETUPVAL 	1 2	; T
	33	[581]	GETUPVAL 	2 1	; _
	34	[581]	LOADK    	3 -8	; "Hyphenation: %1"
	35	[581]	CALL     	2 2 2
	36	[581]	MOVE     	3 0
	37	[581]	TAILCALL 	1 3 0
	38	[581]	RETURN   	1 0
	39	[582]	RETURN   	0 1

function <./frontend/apps/reader/modules/readertypography.lua:589,599> (13 instructions, 52 bytes at 0x7faa78506c10)
2 params, 4 slots, 3 upvalues, 2 locals, 6 constants, 1 function
	1	[590]	GETTABLE 	2 0 -1	; "menu_table"
	2	[590]	SETTABLE 	2 -2 -3	; "max_per_page" 7
	3	[592]	NEWTABLE 	2 0 2
	4	[596]	CLOSURE  	3 0	; 0x7faa78506f10
	5	[596]	GETUPVAL 	0 0	; LANG_TAG_TO_LANG_NAME
	6	[596]	MOVE     	0 0
	7	[596]	GETUPVAL 	0 1	; T
	8	[596]	GETUPVAL 	0 2	; _
	9	[596]	SETTABLE 	2 -5 3	; "text_func" -
	10	[597]	GETTABLE 	3 0 -1	; "menu_table"
	11	[597]	SETTABLE 	2 -6 3	; "sub_item_table" -
	12	[598]	SETTABLE 	1 -4 2	; "typography" -
	13	[599]	RETURN   	0 1

function <./frontend/apps/reader/modules/readertypography.lua:593,596> (16 instructions, 64 bytes at 0x7faa78506f10)
0 params, 4 slots, 4 upvalues, 1 local, 2 constants, 0 functions
	1	[594]	GETUPVAL 	0 0	; LANG_TAG_TO_LANG_NAME
	2	[594]	GETUPVAL 	1 1	; self
	3	[594]	GETTABLE 	1 1 -1	; "text_lang_tag"
	4	[594]	GETTABLE 	0 0 1
	5	[594]	TEST     	0 0 1
	6	[594]	JMP      	2	; to 9
	7	[594]	GETUPVAL 	0 1	; self
	8	[594]	GETTABLE 	0 0 -1	; "text_lang_tag"
	9	[595]	GETUPVAL 	1 2	; T
	10	[595]	GETUPVAL 	2 3	; _
	11	[595]	LOADK    	3 -2	; "Typography rules: %1"
	12	[595]	CALL     	2 2 2
	13	[595]	MOVE     	3 0
	14	[595]	TAILCALL 	1 3 0
	15	[595]	RETURN   	1 0
	16	[596]	RETURN   	0 1

function <./frontend/apps/reader/modules/readertypography.lua:601,610> (17 instructions, 68 bytes at 0x7faa78507300)
1 param, 7 slots, 1 upvalue, 3 locals, 7 constants, 0 functions
	1	[602]	GETTABLE 	1 0 -1	; "ui"
	2	[602]	GETTABLE 	1 1 -2	; "document"
	3	[602]	SELF     	1 1 -3	; "getTextMainLangDefaultHyphDictionary"
	4	[602]	CALL     	1 2 2
	5	[603]	GETUPVAL 	2 0	; HYPH_DICT_NAME_TO_LANG_NAME_TAG
	6	[603]	GETTABLE 	2 2 1
	7	[604]	TEST     	2 0 0
	8	[604]	JMP      	2	; to 11
	9	[605]	GETTABLE 	1 2 -4	; 1
	10	[605]	JMP      	5	; to 16
	11	[607]	SELF     	3 1 -5	; "gsub"
	12	[607]	LOADK    	5 -6	; ".pattern$"
	13	[607]	LOADK    	6 -7	; ""
	14	[607]	CALL     	3 4 2
	15	[607]	MOVE     	1 3
	16	[609]	RETURN   	1 2
	17	[610]	RETURN   	0 1

function <./frontend/apps/reader/modules/readertypography.lua:612,628> (39 instructions, 156 bytes at 0x7faa785079e0)
2 params, 11 slots, 1 upvalue, 8 locals, 9 constants, 0 functions
	1	[620]	GETUPVAL 	4 0	; util
	2	[620]	GETTABLE 	4 4 -1	; "gsplit"
	3	[620]	MOVE     	5 1
	4	[620]	LOADK    	6 -2	; "-"
	5	[620]	LOADBOOL 	7 0 0
	6	[620]	CALL     	4 4 4
	7	[620]	JMP      	26	; to 34
	8	[621]	TEST     	2 0 1
	9	[621]	JMP      	6	; to 16
	10	[622]	GETGLOBAL	8 -3	; string
	11	[622]	GETTABLE 	8 8 -4	; "lower"
	12	[622]	MOVE     	9 7
	13	[622]	CALL     	8 2 2
	14	[622]	MOVE     	2 8
	15	[622]	JMP      	18	; to 34
	16	[623]	GETGLOBAL	8 -3	; string
	17	[623]	GETTABLE 	8 8 -5	; "len"
	18	[623]	MOVE     	9 7
	19	[623]	CALL     	8 2 2
	20	[623]	EQ       	0 8 -6	; - 2
	21	[623]	JMP      	12	; to 34
	22	[623]	GETGLOBAL	8 -3	; string
	23	[623]	GETTABLE 	8 8 -7	; "match"
	24	[623]	MOVE     	9 7
	25	[623]	LOADK    	10 -8	; "[^%a]"
	26	[623]	CALL     	8 3 2
	27	[623]	TEST     	8 0 1
	28	[623]	JMP      	5	; to 34
	29	[624]	GETGLOBAL	8 -3	; string
	30	[624]	GETTABLE 	8 8 -9	; "upper"
	31	[624]	MOVE     	9 7
	32	[624]	CALL     	8 2 2
	33	[624]	MOVE     	3 8
	34	[620]	TFORLOOP 	4 1
	35	[625]	JMP      	-28	; to 8
	36	[627]	MOVE     	4 2
	37	[627]	MOVE     	5 3
	38	[627]	RETURN   	4 3
	39	[628]	RETURN   	0 1

function <./frontend/apps/reader/modules/readertypography.lua:630,653> (14 instructions, 56 bytes at 0x7faa78507d80)
2 params, 3 slots, 1 upvalue, 2 locals, 1 constant, 0 functions
	1	[637]	TEST     	1 0 0
	2	[637]	JMP      	2	; to 5
	3	[637]	EQ       	0 1 -1	; - ""
	4	[637]	JMP      	2	; to 7
	5	[638]	LOADNIL  	2 2
	6	[638]	RETURN   	2 2
	7	[648]	GETUPVAL 	2 0	; LANG_ALIAS_TO_LANG_TAG
	8	[648]	GETTABLE 	2 2 1
	9	[648]	TEST     	2 0 0
	10	[648]	JMP      	2	; to 13
	11	[649]	GETUPVAL 	2 0	; LANG_ALIAS_TO_LANG_TAG
	12	[649]	GETTABLE 	1 2 1
	13	[652]	RETURN   	1 2
	14	[653]	RETURN   	0 1

function <./frontend/apps/reader/modules/readertypography.lua:663,750> (221 instructions, 884 bytes at 0x7faa785081c0)
2 params, 8 slots, 3 upvalues, 4 locals, 43 constants, 0 functions
	1	[665]	SELF     	2 1 -1	; "readSetting"
	2	[665]	LOADK    	4 -2	; "text_lang"
	3	[665]	CALL     	2 3 2
	4	[665]	TEST     	2 0 1
	5	[665]	JMP      	36	; to 42
	6	[665]	SELF     	2 1 -1	; "readSetting"
	7	[665]	LOADK    	4 -3	; "hyph_alg"
	8	[665]	CALL     	2 3 2
	9	[665]	TEST     	2 0 0
	10	[665]	JMP      	31	; to 42
	11	[666]	SELF     	2 1 -1	; "readSetting"
	12	[666]	LOADK    	4 -3	; "hyph_alg"
	13	[666]	CALL     	2 3 2
	14	[667]	GETUPVAL 	3 0	; HYPH_DICT_NAME_TO_LANG_NAME_TAG
	15	[667]	GETTABLE 	3 3 2
	16	[668]	TEST     	3 0 0
	17	[668]	JMP      	24	; to 42
	18	[669]	SELF     	4 1 -4	; "saveSetting"
	19	[669]	LOADK    	6 -2	; "text_lang"
	20	[669]	GETTABLE 	7 3 -5	; 2
	21	[669]	CALL     	4 4 1
	22	[672]	EQ       	0 2 -6	; - "@none"
	23	[672]	JMP      	5	; to 29
	24	[673]	SELF     	4 1 -4	; "saveSetting"
	25	[673]	LOADK    	6 -7	; "hyphenation"
	26	[673]	LOADBOOL 	7 0 0
	27	[673]	CALL     	4 4 1
	28	[673]	JMP      	13	; to 42
	29	[674]	EQ       	0 2 -8	; - "@softhyphens"
	30	[674]	JMP      	5	; to 36
	31	[675]	SELF     	4 1 -4	; "saveSetting"
	32	[675]	LOADK    	6 -9	; "hyph_soft_hyphens_only"
	33	[675]	LOADBOOL 	7 1 0
	34	[675]	CALL     	4 4 1
	35	[675]	JMP      	6	; to 42
	36	[676]	EQ       	0 2 -10	; - "@algorithm"
	37	[676]	JMP      	4	; to 42
	38	[677]	SELF     	4 1 -4	; "saveSetting"
	39	[677]	LOADK    	6 -11	; "hyph_force_algorithmic"
	40	[677]	LOADBOOL 	7 1 0
	41	[677]	CALL     	4 4 1
	42	[683]	SELF     	2 1 -1	; "readSetting"
	43	[683]	LOADK    	4 -12	; "text_lang_embedded_langs"
	44	[683]	CALL     	2 3 2
	45	[683]	SETTABLE 	0 -12 2	; "text_lang_embedded_langs" -
	46	[684]	GETTABLE 	2 0 -12	; "text_lang_embedded_langs"
	47	[684]	EQ       	0 2 -13	; - nil
	48	[684]	JMP      	5	; to 54
	49	[685]	GETGLOBAL	2 -14	; G_reader_settings
	50	[685]	SELF     	2 2 -15	; "nilOrTrue"
	51	[685]	LOADK    	4 -12	; "text_lang_embedded_langs"
	52	[685]	CALL     	2 3 2
	53	[685]	SETTABLE 	0 -12 2	; "text_lang_embedded_langs" -
	54	[687]	GETTABLE 	2 0 -16	; "ui"
	55	[687]	GETTABLE 	2 2 -17	; "document"
	56	[687]	SELF     	2 2 -18	; "setTextEmbeddedLangs"
	57	[687]	GETTABLE 	4 0 -12	; "text_lang_embedded_langs"
	58	[687]	CALL     	2 3 1
	59	[690]	SELF     	2 1 -1	; "readSetting"
	60	[690]	LOADK    	4 -7	; "hyphenation"
	61	[690]	CALL     	2 3 2
	62	[690]	SETTABLE 	0 -7 2	; "hyphenation" -
	63	[691]	GETTABLE 	2 0 -7	; "hyphenation"
	64	[691]	EQ       	0 2 -13	; - nil
	65	[691]	JMP      	5	; to 71
	66	[692]	GETGLOBAL	2 -14	; G_reader_settings
	67	[692]	SELF     	2 2 -15	; "nilOrTrue"
	68	[692]	LOADK    	4 -7	; "hyphenation"
	69	[692]	CALL     	2 3 2
	70	[692]	SETTABLE 	0 -7 2	; "hyphenation" -
	71	[694]	GETTABLE 	2 0 -16	; "ui"
	72	[694]	GETTABLE 	2 2 -17	; "document"
	73	[694]	SELF     	2 2 -19	; "setTextHyphenation"
	74	[694]	GETTABLE 	4 0 -7	; "hyphenation"
	75	[694]	CALL     	2 3 1
	76	[697]	SELF     	2 1 -1	; "readSetting"
	77	[697]	LOADK    	4 -20	; "hyph_trust_soft_hyphens"
	78	[697]	CALL     	2 3 2
	79	[697]	SETTABLE 	0 -20 2	; "hyph_trust_soft_hyphens" -
	80	[698]	GETTABLE 	2 0 -20	; "hyph_trust_soft_hyphens"
	81	[698]	EQ       	0 2 -13	; - nil
	82	[698]	JMP      	5	; to 88
	83	[699]	GETGLOBAL	2 -14	; G_reader_settings
	84	[699]	SELF     	2 2 -21	; "isTrue"
	85	[699]	LOADK    	4 -20	; "hyph_trust_soft_hyphens"
	86	[699]	CALL     	2 3 2
	87	[699]	SETTABLE 	0 -20 2	; "hyph_trust_soft_hyphens" -
	88	[701]	GETTABLE 	2 0 -16	; "ui"
	89	[701]	GETTABLE 	2 2 -17	; "document"
	90	[701]	SELF     	2 2 -22	; "setTrustSoftHyphens"
	91	[701]	GETTABLE 	4 0 -20	; "hyph_trust_soft_hyphens"
	92	[701]	CALL     	2 3 1
	93	[704]	SELF     	2 1 -1	; "readSetting"
	94	[704]	LOADK    	4 -9	; "hyph_soft_hyphens_only"
	95	[704]	CALL     	2 3 2
	96	[704]	SETTABLE 	0 -9 2	; "hyph_soft_hyphens_only" -
	97	[705]	GETTABLE 	2 0 -9	; "hyph_soft_hyphens_only"
	98	[705]	EQ       	0 2 -13	; - nil
	99	[705]	JMP      	5	; to 105
	100	[706]	GETGLOBAL	2 -14	; G_reader_settings
	101	[706]	SELF     	2 2 -21	; "isTrue"
	102	[706]	LOADK    	4 -9	; "hyph_soft_hyphens_only"
	103	[706]	CALL     	2 3 2
	104	[706]	SETTABLE 	0 -9 2	; "hyph_soft_hyphens_only" -
	105	[708]	GETTABLE 	2 0 -16	; "ui"
	106	[708]	GETTABLE 	2 2 -17	; "document"
	107	[708]	SELF     	2 2 -23	; "setTextHyphenationSoftHyphensOnly"
	108	[708]	GETTABLE 	4 0 -9	; "hyph_soft_hyphens_only"
	109	[708]	CALL     	2 3 1
	110	[711]	SELF     	2 1 -1	; "readSetting"
	111	[711]	LOADK    	4 -11	; "hyph_force_algorithmic"
	112	[711]	CALL     	2 3 2
	113	[711]	SETTABLE 	0 -11 2	; "hyph_force_algorithmic" -
	114	[712]	GETTABLE 	2 0 -11	; "hyph_force_algorithmic"
	115	[712]	EQ       	0 2 -13	; - nil
	116	[712]	JMP      	5	; to 122
	117	[713]	GETGLOBAL	2 -14	; G_reader_settings
	118	[713]	SELF     	2 2 -21	; "isTrue"
	119	[713]	LOADK    	4 -11	; "hyph_force_algorithmic"
	120	[713]	CALL     	2 3 2
	121	[713]	SETTABLE 	0 -11 2	; "hyph_force_algorithmic" -
	122	[715]	GETTABLE 	2 0 -16	; "ui"
	123	[715]	GETTABLE 	2 2 -17	; "document"
	124	[715]	SELF     	2 2 -24	; "setTextHyphenationForceAlgorithmic"
	125	[715]	GETTABLE 	4 0 -11	; "hyph_force_algorithmic"
	126	[715]	CALL     	2 3 1
	127	[718]	GETTABLE 	2 0 -16	; "ui"
	128	[718]	GETTABLE 	2 2 -17	; "document"
	129	[718]	SELF     	2 2 -25	; "setHyphLeftHyphenMin"
	130	[718]	GETGLOBAL	4 -14	; G_reader_settings
	131	[718]	SELF     	4 4 -1	; "readSetting"
	132	[718]	LOADK    	6 -26	; "hyph_left_hyphen_min"
	133	[718]	CALL     	4 3 2
	134	[718]	TEST     	4 0 1
	135	[718]	JMP      	1	; to 137
	136	[718]	LOADK    	4 -27	; 0
	137	[718]	CALL     	2 3 1
	138	[719]	GETTABLE 	2 0 -16	; "ui"
	139	[719]	GETTABLE 	2 2 -17	; "document"
	140	[719]	SELF     	2 2 -28	; "setHyphRightHyphenMin"
	141	[719]	GETGLOBAL	4 -14	; G_reader_settings
	142	[719]	SELF     	4 4 -1	; "readSetting"
	143	[719]	LOADK    	6 -29	; "hyph_right_hyphen_min"
	144	[719]	CALL     	4 3 2
	145	[719]	TEST     	4 0 1
	146	[719]	JMP      	1	; to 148
	147	[719]	LOADK    	4 -27	; 0
	148	[719]	CALL     	2 3 1
	149	[722]	SETTABLE 	0 -30 -31	; "allow_doc_lang_tag_override" false
	150	[724]	SELF     	2 1 -1	; "readSetting"
	151	[724]	LOADK    	4 -2	; "text_lang"
	152	[724]	CALL     	2 3 2
	153	[724]	SETTABLE 	0 -32 2	; "text_lang_tag" -
	154	[725]	GETTABLE 	2 0 -32	; "text_lang_tag"
	155	[725]	TEST     	2 0 0
	156	[725]	JMP      	12	; to 169
	157	[726]	GETUPVAL 	2 1	; logger
	158	[726]	GETTABLE 	2 2 -33	; "dbg"
	159	[726]	LOADK    	3 -34	; "Typography lang: using"
	160	[726]	GETTABLE 	4 0 -32	; "text_lang_tag"
	161	[726]	LOADK    	5 -35	; "from doc settings"
	162	[726]	CALL     	2 4 1
	163	[727]	GETTABLE 	2 0 -16	; "ui"
	164	[727]	GETTABLE 	2 2 -17	; "document"
	165	[727]	SELF     	2 2 -36	; "setTextMainLang"
	166	[727]	GETTABLE 	4 0 -32	; "text_lang_tag"
	167	[727]	CALL     	2 3 1
	168	[728]	RETURN   	0 1
	169	[731]	GETGLOBAL	2 -14	; G_reader_settings
	170	[731]	SELF     	2 2 -1	; "readSetting"
	171	[731]	LOADK    	4 -37	; "text_lang_default"
	172	[731]	CALL     	2 3 2
	173	[731]	SETTABLE 	0 -32 2	; "text_lang_tag" -
	174	[732]	GETTABLE 	2 0 -32	; "text_lang_tag"
	175	[732]	TEST     	2 0 0
	176	[732]	JMP      	11	; to 188
	177	[733]	GETUPVAL 	2 1	; logger
	178	[733]	GETTABLE 	2 2 -33	; "dbg"
	179	[733]	LOADK    	3 -38	; "Typography lang: using default "
	180	[733]	GETTABLE 	4 0 -32	; "text_lang_tag"
	181	[733]	CALL     	2 3 1
	182	[734]	GETTABLE 	2 0 -16	; "ui"
	183	[734]	GETTABLE 	2 2 -17	; "document"
	184	[734]	SELF     	2 2 -36	; "setTextMainLang"
	185	[734]	GETTABLE 	4 0 -32	; "text_lang_tag"
	186	[734]	CALL     	2 3 1
	187	[735]	RETURN   	0 1
	188	[738]	SETTABLE 	0 -30 -39	; "allow_doc_lang_tag_override" true
	189	[740]	GETGLOBAL	2 -14	; G_reader_settings
	190	[740]	SELF     	2 2 -1	; "readSetting"
	191	[740]	LOADK    	4 -40	; "text_lang_fallback"
	192	[740]	CALL     	2 3 2
	193	[740]	SETTABLE 	0 -32 2	; "text_lang_tag" -
	194	[741]	GETTABLE 	2 0 -32	; "text_lang_tag"
	195	[741]	TEST     	2 0 0
	196	[741]	JMP      	12	; to 209
	197	[742]	GETUPVAL 	2 1	; logger
	198	[742]	GETTABLE 	2 2 -33	; "dbg"
	199	[742]	LOADK    	3 -41	; "Typography lang: using fallback "
	200	[742]	GETTABLE 	4 0 -32	; "text_lang_tag"
	201	[742]	LOADK    	5 -42	; ", might be overriden by doc language"
	202	[742]	CALL     	2 4 1
	203	[743]	GETTABLE 	2 0 -16	; "ui"
	204	[743]	GETTABLE 	2 2 -17	; "document"
	205	[743]	SELF     	2 2 -36	; "setTextMainLang"
	206	[743]	GETTABLE 	4 0 -32	; "text_lang_tag"
	207	[743]	CALL     	2 3 1
	208	[744]	RETURN   	0 1
	209	[747]	GETUPVAL 	2 2	; DEFAULT_LANG_TAG
	210	[747]	SETTABLE 	0 -32 2	; "text_lang_tag" -
	211	[748]	GETUPVAL 	2 1	; logger
	212	[748]	GETTABLE 	2 2 -33	; "dbg"
	213	[748]	LOADK    	3 -43	; "Typography lang: no lang set, using"
	214	[748]	GETTABLE 	4 0 -32	; "text_lang_tag"
	215	[748]	CALL     	2 3 1
	216	[749]	GETTABLE 	2 0 -16	; "ui"
	217	[749]	GETTABLE 	2 2 -17	; "document"
	218	[749]	SELF     	2 2 -36	; "setTextMainLang"
	219	[749]	GETTABLE 	4 0 -32	; "text_lang_tag"
	220	[749]	CALL     	2 3 1
	221	[750]	RETURN   	0 1

function <./frontend/apps/reader/modules/readertypography.lua:752,800> (118 instructions, 472 bytes at 0x7faa78704170)
2 params, 12 slots, 8 upvalues, 4 locals, 34 constants, 3 functions
	1	[755]	GETTABLE 	2 0 -1	; "ui"
	2	[755]	GETTABLE 	2 2 -2	; "document"
	3	[755]	SELF     	2 2 -3	; "getProps"
	4	[755]	CALL     	2 2 2
	5	[755]	GETTABLE 	2 2 -4	; "language"
	6	[756]	SELF     	3 0 -6	; "fixLangTag"
	7	[756]	MOVE     	5 2
	8	[756]	CALL     	3 3 2
	9	[756]	SETTABLE 	0 -5 3	; "book_lang_tag" -
	10	[758]	GETTABLE 	3 0 -5	; "book_lang_tag"
	11	[758]	TEST     	3 0 0
	12	[758]	JMP      	7	; to 20
	13	[758]	GETUPVAL 	3 0	; LANG_TAG_TO_LANG_NAME
	14	[758]	GETTABLE 	4 0 -5	; "book_lang_tag"
	15	[758]	GETTABLE 	3 3 4
	16	[758]	EQ       	0 3 -7	; - nil
	17	[758]	JMP      	1	; to 19
	18	[758]	LOADBOOL 	3 0 1
	19	[758]	LOADBOOL 	3 1 0
	20	[761]	GETGLOBAL	4 -8	; table
	21	[761]	GETTABLE 	4 4 -9	; "insert"
	22	[761]	GETTABLE 	5 0 -10	; "language_submenu"
	23	[761]	LOADK    	6 -11	; 1
	24	[761]	NEWTABLE 	7 0 5
	25	[762]	GETUPVAL 	8 1	; T
	26	[762]	GETUPVAL 	9 2	; _
	27	[762]	LOADK    	10 -13	; "Book language: %1"
	28	[762]	CALL     	9 2 2
	29	[762]	GETTABLE 	10 0 -5	; "book_lang_tag"
	30	[762]	TEST     	10 0 1
	31	[762]	JMP      	3	; to 35
	32	[762]	GETUPVAL 	10 2	; _
	33	[762]	LOADK    	11 -14	; "n/a"
	34	[762]	CALL     	10 2 2
	35	[762]	CALL     	8 3 2
	36	[762]	SETTABLE 	7 -12 8	; "text" -
	37	[771]	CLOSURE  	8 0	; 0x7faa78704400
	38	[771]	GETUPVAL 	0 3	; UIManager
	39	[771]	GETUPVAL 	0 4	; InfoMessage
	40	[771]	GETUPVAL 	0 1	; T
	41	[771]	GETUPVAL 	0 2	; _
	42	[771]	GETUPVAL 	0 5	; BD
	43	[771]	MOVE     	0 0
	44	[771]	GETUPVAL 	0 6	; Event
	45	[771]	SETTABLE 	7 -15 8	; "callback" -
	46	[774]	CLOSURE  	8 1	; 0x7faa787049f0
	47	[774]	MOVE     	0 0
	48	[774]	SETTABLE 	7 -16 8	; "enabled_func" -
	49	[777]	CLOSURE  	8 2	; 0x7faa787048f0
	50	[777]	MOVE     	0 0
	51	[777]	SETTABLE 	7 -17 8	; "checked_func" -
	52	[778]	SETTABLE 	7 -18 -19	; "separator" true
	53	[761]	CALL     	4 4 1
	54	[781]	GETTABLE 	4 0 -20	; "allow_doc_lang_tag_override"
	55	[781]	TEST     	4 0 1
	56	[781]	JMP      	14	; to 71
	57	[782]	GETUPVAL 	4 7	; logger
	58	[782]	GETTABLE 	4 4 -21	; "dbg"
	59	[782]	LOADK    	5 -22	; "Typography lang: not overriding"
	60	[782]	GETTABLE 	6 0 -23	; "text_lang_tag"
	61	[782]	LOADK    	7 -24	; "with doc language:"
	62	[783]	GETTABLE 	8 0 -5	; "book_lang_tag"
	63	[783]	TEST     	8 0 0
	64	[783]	JMP      	3	; to 68
	65	[783]	GETTABLE 	8 0 -5	; "book_lang_tag"
	66	[783]	TEST     	8 0 1
	67	[783]	JMP      	1	; to 69
	68	[783]	LOADK    	8 -25	; "none"
	69	[782]	CALL     	4 5 1
	70	[783]	JMP      	47	; to 118
	71	[784]	GETTABLE 	4 0 -5	; "book_lang_tag"
	72	[784]	TEST     	4 0 1
	73	[784]	JMP      	6	; to 80
	74	[785]	GETUPVAL 	4 7	; logger
	75	[785]	GETTABLE 	4 4 -21	; "dbg"
	76	[785]	LOADK    	5 -26	; "Typography lang: no doc language, keeping"
	77	[785]	GETTABLE 	6 0 -23	; "text_lang_tag"
	78	[785]	CALL     	4 3 1
	79	[785]	JMP      	38	; to 118
	80	[787]	TEST     	3 0 0
	81	[787]	JMP      	21	; to 103
	82	[788]	GETTABLE 	4 0 -5	; "book_lang_tag"
	83	[788]	GETTABLE 	5 0 -23	; "text_lang_tag"
	84	[788]	EQ       	0 4 5
	85	[788]	JMP      	7	; to 93
	86	[789]	GETUPVAL 	4 7	; logger
	87	[789]	GETTABLE 	4 4 -21	; "dbg"
	88	[789]	LOADK    	5 -27	; "Typography lang: current"
	89	[789]	GETTABLE 	6 0 -23	; "text_lang_tag"
	90	[789]	LOADK    	7 -28	; "is same as doc language"
	91	[789]	CALL     	4 4 1
	92	[789]	JMP      	18	; to 111
	93	[791]	GETUPVAL 	4 7	; logger
	94	[791]	GETTABLE 	4 4 -21	; "dbg"
	95	[791]	LOADK    	5 -29	; "Typography lang: updating for doc language"
	96	[791]	MOVE     	6 2
	97	[791]	LOADK    	7 -30	; ":"
	98	[791]	GETTABLE 	8 0 -23	; "text_lang_tag"
	99	[791]	LOADK    	9 -31	; "=>"
	100	[791]	GETTABLE 	10 0 -5	; "book_lang_tag"
	101	[791]	CALL     	4 7 1
	102	[792]	JMP      	8	; to 111
	103	[795]	GETUPVAL 	4 7	; logger
	104	[795]	GETTABLE 	4 4 -32	; "info"
	105	[795]	LOADK    	5 -29	; "Typography lang: updating for doc language"
	106	[795]	MOVE     	6 2
	107	[795]	LOADK    	7 -30	; ":"
	108	[795]	GETTABLE 	8 0 -5	; "book_lang_tag"
	109	[795]	LOADK    	9 -33	; "(not a preset)"
	110	[795]	CALL     	4 6 1
	111	[797]	GETTABLE 	4 0 -5	; "book_lang_tag"
	112	[797]	SETTABLE 	0 -23 4	; "text_lang_tag" -
	113	[798]	GETTABLE 	4 0 -1	; "ui"
	114	[798]	GETTABLE 	4 4 -2	; "document"
	115	[798]	SELF     	4 4 -34	; "setTextMainLang"
	116	[798]	GETTABLE 	6 0 -23	; "text_lang_tag"
	117	[798]	CALL     	4 3 1
	118	[800]	RETURN   	0 1

function <./frontend/apps/reader/modules/readertypography.lua:763,771> (46 instructions, 184 bytes at 0x7faa78704400)
0 params, 9 slots, 7 upvalues, 0 locals, 15 constants, 0 functions
	1	[764]	GETUPVAL 	0 0	; UIManager
	2	[764]	SELF     	0 0 -1	; "show"
	3	[764]	GETUPVAL 	2 1	; InfoMessage
	4	[764]	SELF     	2 2 -2	; "new"
	5	[764]	NEWTABLE 	4 0 1
	6	[765]	GETUPVAL 	5 2	; T
	7	[765]	GETUPVAL 	6 3	; _
	8	[765]	LOADK    	7 -4	; "Changed language for typography rules to book language: %1."
	9	[765]	CALL     	6 2 2
	10	[765]	GETUPVAL 	7 4	; BD
	11	[765]	GETTABLE 	7 7 -5	; "wrap"
	12	[765]	GETUPVAL 	8 5	; self
	13	[765]	GETTABLE 	8 8 -6	; "book_lang_tag"
	14	[765]	CALL     	7 2 0
	15	[765]	CALL     	5 0 2
	16	[765]	SETTABLE 	4 -3 5	; "text" -
	17	[764]	CALL     	2 3 0
	18	[764]	CALL     	0 0 1
	19	[767]	GETUPVAL 	0 5	; self
	20	[767]	GETUPVAL 	1 5	; self
	21	[767]	GETTABLE 	1 1 -6	; "book_lang_tag"
	22	[767]	SETTABLE 	0 -7 1	; "text_lang_tag" -
	23	[768]	GETUPVAL 	0 5	; self
	24	[768]	GETTABLE 	0 0 -8	; "ui"
	25	[768]	GETTABLE 	0 0 -9	; "doc_settings"
	26	[768]	SELF     	0 0 -10	; "saveSetting"
	27	[768]	LOADK    	2 -11	; "text_lang"
	28	[768]	GETUPVAL 	3 5	; self
	29	[768]	GETTABLE 	3 3 -7	; "text_lang_tag"
	30	[768]	CALL     	0 4 1
	31	[769]	GETUPVAL 	0 5	; self
	32	[769]	GETTABLE 	0 0 -8	; "ui"
	33	[769]	GETTABLE 	0 0 -12	; "document"
	34	[769]	SELF     	0 0 -13	; "setTextMainLang"
	35	[769]	GETUPVAL 	2 5	; self
	36	[769]	GETTABLE 	2 2 -7	; "text_lang_tag"
	37	[769]	CALL     	0 3 1
	38	[770]	GETUPVAL 	0 5	; self
	39	[770]	GETTABLE 	0 0 -8	; "ui"
	40	[770]	SELF     	0 0 -14	; "handleEvent"
	41	[770]	GETUPVAL 	2 6	; Event
	42	[770]	SELF     	2 2 -2	; "new"
	43	[770]	LOADK    	4 -15	; "UpdatePos"
	44	[770]	CALL     	2 3 0
	45	[770]	CALL     	0 0 1
	46	[771]	RETURN   	0 1

function <./frontend/apps/reader/modules/readertypography.lua:772,774> (8 instructions, 32 bytes at 0x7faa787049f0)
0 params, 2 slots, 1 upvalue, 0 locals, 2 constants, 0 functions
	1	[773]	GETUPVAL 	0 0	; self
	2	[773]	GETTABLE 	0 0 -1	; "book_lang_tag"
	3	[773]	EQ       	0 0 -2	; - nil
	4	[773]	JMP      	1	; to 6
	5	[773]	LOADBOOL 	0 0 1
	6	[773]	LOADBOOL 	0 1 0
	7	[773]	RETURN   	0 2
	8	[774]	RETURN   	0 1

function <./frontend/apps/reader/modules/readertypography.lua:775,777> (10 instructions, 40 bytes at 0x7faa787048f0)
0 params, 2 slots, 1 upvalue, 0 locals, 2 constants, 0 functions
	1	[776]	GETUPVAL 	0 0	; self
	2	[776]	GETTABLE 	0 0 -1	; "text_lang_tag"
	3	[776]	GETUPVAL 	1 0	; self
	4	[776]	GETTABLE 	1 1 -2	; "book_lang_tag"
	5	[776]	EQ       	1 0 1
	6	[776]	JMP      	1	; to 8
	7	[776]	LOADBOOL 	0 0 1
	8	[776]	LOADBOOL 	0 1 0
	9	[776]	RETURN   	0 2
	10	[777]	RETURN   	0 1

function <./frontend/apps/reader/modules/readertypography.lua:802,809> (37 instructions, 148 bytes at 0x7faa78704640)
1 param, 5 slots, 0 upvalues, 1 local, 10 constants, 0 functions
	1	[803]	GETTABLE 	1 0 -1	; "ui"
	2	[803]	GETTABLE 	1 1 -2	; "doc_settings"
	3	[803]	SELF     	1 1 -3	; "saveSetting"
	4	[803]	LOADK    	3 -4	; "text_lang"
	5	[803]	GETTABLE 	4 0 -5	; "text_lang_tag"
	6	[803]	CALL     	1 4 1
	7	[804]	GETTABLE 	1 0 -1	; "ui"
	8	[804]	GETTABLE 	1 1 -2	; "doc_settings"
	9	[804]	SELF     	1 1 -3	; "saveSetting"
	10	[804]	LOADK    	3 -6	; "text_lang_embedded_langs"
	11	[804]	GETTABLE 	4 0 -6	; "text_lang_embedded_langs"
	12	[804]	CALL     	1 4 1
	13	[805]	GETTABLE 	1 0 -1	; "ui"
	14	[805]	GETTABLE 	1 1 -2	; "doc_settings"
	15	[805]	SELF     	1 1 -3	; "saveSetting"
	16	[805]	LOADK    	3 -7	; "hyphenation"
	17	[805]	GETTABLE 	4 0 -7	; "hyphenation"
	18	[805]	CALL     	1 4 1
	19	[806]	GETTABLE 	1 0 -1	; "ui"
	20	[806]	GETTABLE 	1 1 -2	; "doc_settings"
	21	[806]	SELF     	1 1 -3	; "saveSetting"
	22	[806]	LOADK    	3 -8	; "hyph_trust_soft_hyphens"
	23	[806]	GETTABLE 	4 0 -8	; "hyph_trust_soft_hyphens"
	24	[806]	CALL     	1 4 1
	25	[807]	GETTABLE 	1 0 -1	; "ui"
	26	[807]	GETTABLE 	1 1 -2	; "doc_settings"
	27	[807]	SELF     	1 1 -3	; "saveSetting"
	28	[807]	LOADK    	3 -9	; "hyph_soft_hyphens_only"
	29	[807]	GETTABLE 	4 0 -9	; "hyph_soft_hyphens_only"
	30	[807]	CALL     	1 4 1
	31	[808]	GETTABLE 	1 0 -1	; "ui"
	32	[808]	GETTABLE 	1 1 -2	; "doc_settings"
	33	[808]	SELF     	1 1 -3	; "saveSetting"
	34	[808]	LOADK    	3 -10	; "hyph_force_algorithmic"
	35	[808]	GETTABLE 	4 0 -10	; "hyph_force_algorithmic"
	36	[808]	CALL     	1 4 1
	37	[809]	RETURN   	0 1
