
main <./frontend/apps/reader/modules/readerfrontlight.lua:0,0> (90 instructions, 360 bytes at 0x7fd0dac06900)
0+ params, 27 slots, 0 upvalues, 8 locals, 36 constants, 7 functions
	1	[1]	GETGLOBAL	0 -1	; require
	2	[1]	LOADK    	1 -2	; "ui/widget/container/inputcontainer"
	3	[1]	CALL     	0 2 2
	4	[2]	GETGLOBAL	1 -1	; require
	5	[2]	LOADK    	2 -3	; "ui/widget/notification"
	6	[2]	CALL     	1 2 2
	7	[3]	GETGLOBAL	2 -1	; require
	8	[3]	LOADK    	3 -4	; "ui/uimanager"
	9	[3]	CALL     	2 2 2
	10	[4]	GETGLOBAL	3 -1	; require
	11	[4]	LOADK    	4 -5	; "device"
	12	[4]	CALL     	3 2 2
	13	[4]	GETTABLE 	3 3 -6	; "screen"
	14	[5]	GETGLOBAL	4 -1	; require
	15	[5]	LOADK    	5 -5	; "device"
	16	[5]	CALL     	4 2 2
	17	[6]	GETGLOBAL	5 -1	; require
	18	[6]	LOADK    	6 -7	; "ffi/util"
	19	[6]	CALL     	5 2 2
	20	[6]	GETTABLE 	5 5 -8	; "template"
	21	[7]	GETGLOBAL	6 -1	; require
	22	[7]	LOADK    	7 -9	; "gettext"
	23	[7]	CALL     	6 2 2
	24	[9]	SELF     	7 0 -10	; "new"
	25	[9]	NEWTABLE 	9 0 2
	26	[10]	NEWTABLE 	10 16 0
	27	[10]	LOADK    	11 -12	; 0.1
	28	[10]	LOADK    	12 -12	; 0.1
	29	[10]	LOADK    	13 -13	; 0.2
	30	[10]	LOADK    	14 -14	; 0.4
	31	[10]	LOADK    	15 -15	; 0.7
	32	[10]	LOADK    	16 -16	; 1.1
	33	[10]	LOADK    	17 -17	; 1.6
	34	[10]	LOADK    	18 -18	; 2.2
	35	[10]	LOADK    	19 -19	; 2.9
	36	[10]	LOADK    	20 -20	; 3.7
	37	[10]	LOADK    	21 -21	; 4.6
	38	[10]	LOADK    	22 -22	; 5.6
	39	[10]	LOADK    	23 -23	; 6.7
	40	[10]	LOADK    	24 -24	; 7.9
	41	[10]	LOADK    	25 -25	; 9.2
	42	[10]	LOADK    	26 -26	; 10.6
	43	[10]	SETLIST  	10 16 1	; 1
	44	[10]	SETTABLE 	9 -11 10	; "steps_fl" -
	45	[11]	SELF     	10 3 -28	; "getWidth"
	46	[11]	CALL     	10 2 2
	47	[11]	GETGLOBAL	11 -29	; FRONTLIGHT_SENSITIVITY_DECREASE
	48	[11]	MUL      	10 10 11
	49	[11]	SETTABLE 	9 -27 10	; "gestureScale" -
	50	[9]	CALL     	7 3 2
	51	[70]	CLOSURE  	8 0	; 0x7fd0dac070d0
	52	[70]	MOVE     	0 4
	53	[70]	MOVE     	0 3
	54	[16]	SETTABLE 	7 -30 8	; "onChangeFlIntensity" -
	55	[135]	CLOSURE  	8 1	; 0x7fd0dac07820
	56	[135]	MOVE     	0 4
	57	[135]	MOVE     	0 2
	58	[135]	MOVE     	0 1
	59	[135]	MOVE     	0 6
	60	[135]	MOVE     	0 3
	61	[74]	SETTABLE 	7 -31 8	; "onChangeFlWarmth" -
	62	[151]	CLOSURE  	8 2	; 0x7fd0dac07d40
	63	[151]	MOVE     	0 4
	64	[151]	MOVE     	0 6
	65	[151]	MOVE     	0 2
	66	[151]	MOVE     	0 1
	67	[138]	SETTABLE 	7 -32 8	; "onShowOnOff" -
	68	[167]	CLOSURE  	8 3	; 0x7fd0dac08140
	69	[167]	MOVE     	0 4
	70	[167]	MOVE     	0 6
	71	[167]	MOVE     	0 5
	72	[167]	MOVE     	0 2
	73	[167]	MOVE     	0 1
	74	[153]	SETTABLE 	7 -33 8	; "onShowIntensity" -
	75	[178]	CLOSURE  	8 4	; 0x7fd0dac06e40
	76	[178]	MOVE     	0 4
	77	[178]	MOVE     	0 2
	78	[178]	MOVE     	0 1
	79	[178]	MOVE     	0 5
	80	[178]	MOVE     	0 6
	81	[169]	SETTABLE 	7 -34 8	; "onShowWarmth" -
	82	[185]	CLOSURE  	8 5	; 0x7fd0dac08980
	83	[185]	MOVE     	0 2
	84	[185]	MOVE     	0 4
	85	[180]	SETTABLE 	7 -35 8	; "onShowFlDialog" -
	86	[190]	CLOSURE  	8 6	; 0x7fd0dac08ee0
	87	[190]	MOVE     	0 2
	88	[187]	SETTABLE 	7 -36 8	; "close" -
	89	[192]	RETURN   	7 2
	90	[192]	RETURN   	0 1

function <./frontend/apps/reader/modules/readerfrontlight.lua:16,70> (133 instructions, 532 bytes at 0x7fd0dac070d0)
3 params, 14 slots, 2 upvalues, 17 locals, 36 constants, 0 functions
	1	[17]	GETUPVAL 	3 0	; Device
	2	[17]	SELF     	3 3 -1	; "getPowerDevice"
	3	[17]	CALL     	3 2 2
	4	[18]	LOADNIL  	4 5
	5	[20]	GETTABLE 	6 1 -2	; "ges"
	6	[20]	EQ       	0 6 -3	; - "two_finger_swipe"
	7	[20]	JMP      	3	; to 11
	8	[22]	GETGLOBAL	6 -4	; FRONTLIGHT_SENSITIVITY_DECREASE
	9	[22]	MUL      	5 6 -5	; - 0.8
	10	[22]	JMP      	6	; to 17
	11	[23]	GETTABLE 	6 1 -2	; "ges"
	12	[23]	EQ       	0 6 -6	; - "swipe"
	13	[23]	JMP      	2	; to 16
	14	[24]	LOADK    	5 -5	; 0.8
	15	[24]	JMP      	1	; to 17
	16	[26]	LOADK    	5 -7	; 1
	17	[28]	GETTABLE 	6 1 -8	; "direction"
	18	[28]	EQ       	1 6 -9	; - "south"
	19	[28]	JMP      	3	; to 23
	20	[28]	GETTABLE 	6 1 -8	; "direction"
	21	[28]	EQ       	0 6 -10	; - "north"
	22	[28]	JMP      	5	; to 28
	23	[29]	GETUPVAL 	6 1	; Screen
	24	[29]	SELF     	6 6 -11	; "getHeight"
	25	[29]	CALL     	6 2 2
	26	[29]	MUL      	4 6 5
	27	[29]	JMP      	24	; to 52
	28	[30]	GETTABLE 	6 1 -8	; "direction"
	29	[30]	EQ       	1 6 -12	; - "west"
	30	[30]	JMP      	3	; to 34
	31	[30]	GETTABLE 	6 1 -8	; "direction"
	32	[30]	EQ       	0 6 -13	; - "east"
	33	[30]	JMP      	5	; to 39
	34	[31]	GETUPVAL 	6 1	; Screen
	35	[31]	SELF     	6 6 -14	; "getWidth"
	36	[31]	CALL     	6 2 2
	37	[31]	MUL      	4 6 5
	38	[31]	JMP      	13	; to 52
	39	[33]	GETUPVAL 	6 1	; Screen
	40	[33]	SELF     	6 6 -14	; "getWidth"
	41	[33]	CALL     	6 2 2
	42	[34]	GETUPVAL 	7 1	; Screen
	43	[34]	SELF     	7 7 -11	; "getHeight"
	44	[34]	CALL     	7 2 2
	45	[36]	GETGLOBAL	8 -15	; math
	46	[36]	GETTABLE 	8 8 -16	; "sqrt"
	47	[36]	MUL      	9 6 6
	48	[36]	MUL      	10 7 7
	49	[36]	ADD      	9 9 10
	50	[36]	CALL     	8 2 2
	51	[36]	MUL      	4 8 5
	52	[38]	GETTABLE 	6 3 -17	; "fl_intensity"
	53	[38]	EQ       	0 6 -18	; - nil
	54	[38]	JMP      	2	; to 57
	55	[38]	LOADBOOL 	6 0 0
	56	[38]	RETURN   	6 2
	57	[40]	NEWTABLE 	6 0 0
	58	[41]	GETTABLE 	7 3 -19	; "fl_max"
	59	[41]	GETTABLE 	8 3 -20	; "fl_min"
	60	[41]	SUB      	7 7 8
	61	[41]	DIV      	7 7 -21	; - 2
	62	[41]	DIV      	7 7 -22	; - 10.6
	63	[42]	LOADK    	8 -7	; 1
	64	[42]	GETTABLE 	9 0 -23	; "steps_fl"
	65	[42]	LEN      	9 9
	66	[42]	LOADK    	10 -7	; 1
	67	[43]	FORPREP  	8 7	; to 75
	68	[44]	GETGLOBAL	12 -15	; math
	69	[44]	GETTABLE 	12 12 -24	; "ceil"
	70	[44]	GETTABLE 	13 0 -23	; "steps_fl"
	71	[44]	GETTABLE 	13 13 11
	72	[44]	MUL      	13 13 7
	73	[44]	CALL     	12 2 2
	74	[44]	SETTABLE 	6 11 12
	75	[42]	FORLOOP  	8 -8	; to 68
	76	[47]	GETTABLE 	8 1 -25	; "distance"
	77	[47]	EQ       	0 8 -18	; - nil
	78	[47]	JMP      	1	; to 80
	79	[48]	SETTABLE 	1 -25 -7	; "distance" 1
	80	[50]	GETGLOBAL	8 -15	; math
	81	[50]	GETTABLE 	8 8 -24	; "ceil"
	82	[50]	LEN      	9 6
	83	[50]	GETTABLE 	10 1 -25	; "distance"
	84	[50]	MUL      	9 9 10
	85	[50]	DIV      	9 9 4
	86	[50]	CALL     	8 2 2
	87	[51]	GETTABLE 	9 6 8
	88	[51]	TEST     	9 0 1
	89	[51]	JMP      	2	; to 92
	90	[51]	LEN      	9 6
	91	[51]	GETTABLE 	9 6 9
	92	[52]	EQ       	1 2 -26	; - -1
	93	[52]	JMP      	3	; to 97
	94	[52]	EQ       	1 2 -7	; - 1
	95	[52]	JMP      	1	; to 97
	96	[54]	LOADK    	2 -7	; 1
	97	[56]	GETTABLE 	10 3 -17	; "fl_intensity"
	98	[56]	MUL      	11 2 9
	99	[56]	ADD      	10 10 11
	100	[58]	EQ       	0 10 -18	; - nil
	101	[58]	JMP      	2	; to 104
	102	[58]	LOADBOOL 	11 1 0
	103	[58]	RETURN   	11 2
	104	[60]	LE       	0 10 -27	; - 0
	105	[60]	JMP      	3	; to 109
	106	[61]	SELF     	11 3 -28	; "turnOffFrontlight"
	107	[61]	CALL     	11 2 1
	108	[61]	JMP      	3	; to 112
	109	[63]	SELF     	11 3 -29	; "setIntensity"
	110	[63]	MOVE     	13 10
	111	[63]	CALL     	11 3 1
	112	[65]	SELF     	11 0 -30	; "onShowIntensity"
	113	[65]	CALL     	11 2 1
	114	[66]	GETTABLE 	11 0 -31	; "view"
	115	[66]	TEST     	11 0 0
	116	[66]	JMP      	14	; to 131
	117	[66]	GETTABLE 	11 0 -31	; "view"
	118	[66]	GETTABLE 	11 11 -32	; "footer_visible"
	119	[66]	TEST     	11 0 0
	120	[66]	JMP      	10	; to 131
	121	[66]	GETTABLE 	11 0 -31	; "view"
	122	[66]	GETTABLE 	11 11 -33	; "footer"
	123	[66]	GETTABLE 	11 11 -34	; "settings"
	124	[66]	GETTABLE 	11 11 -35	; "frontlight"
	125	[66]	TEST     	11 0 0
	126	[66]	JMP      	4	; to 131
	127	[67]	GETTABLE 	11 0 -31	; "view"
	128	[67]	GETTABLE 	11 11 -33	; "footer"
	129	[67]	SELF     	11 11 -36	; "updateFooter"
	130	[67]	CALL     	11 2 1
	131	[69]	LOADBOOL 	11 1 0
	132	[69]	RETURN   	11 2
	133	[70]	RETURN   	0 1

function <./frontend/apps/reader/modules/readerfrontlight.lua:74,135> (132 instructions, 528 bytes at 0x7fd0dac07820)
3 params, 14 slots, 5 upvalues, 17 locals, 36 constants, 0 functions
	1	[75]	GETUPVAL 	3 0	; Device
	2	[75]	SELF     	3 3 -1	; "getPowerDevice"
	3	[75]	CALL     	3 2 2
	4	[76]	GETTABLE 	4 3 -2	; "fl_warmth"
	5	[76]	EQ       	0 4 -3	; - nil
	6	[76]	JMP      	2	; to 9
	7	[76]	LOADBOOL 	4 0 0
	8	[76]	RETURN   	4 2
	9	[78]	GETTABLE 	4 3 -4	; "auto_warmth"
	10	[78]	TEST     	4 0 0
	11	[78]	JMP      	14	; to 26
	12	[79]	GETUPVAL 	4 1	; UIManager
	13	[79]	SELF     	4 4 -5	; "show"
	14	[79]	GETUPVAL 	6 2	; Notification
	15	[79]	SELF     	6 6 -6	; "new"
	16	[79]	NEWTABLE 	8 0 2
	17	[80]	GETUPVAL 	9 3	; _
	18	[80]	LOADK    	10 -8	; "Warmth is handled automatically."
	19	[80]	CALL     	9 2 2
	20	[80]	SETTABLE 	8 -7 9	; "text" -
	21	[81]	SETTABLE 	8 -9 -10	; "timeout" 1
	22	[79]	CALL     	6 3 0
	23	[79]	CALL     	4 0 1
	24	[83]	LOADBOOL 	4 1 0
	25	[83]	RETURN   	4 2
	26	[86]	LOADNIL  	4 5
	27	[88]	GETTABLE 	6 1 -11	; "ges"
	28	[88]	EQ       	0 6 -12	; - "two_finger_swipe"
	29	[88]	JMP      	3	; to 33
	30	[90]	GETGLOBAL	6 -13	; FRONTLIGHT_SENSITIVITY_DECREASE
	31	[90]	MUL      	5 6 -14	; - 0.8
	32	[90]	JMP      	6	; to 39
	33	[91]	GETTABLE 	6 1 -11	; "ges"
	34	[91]	EQ       	0 6 -15	; - "swipe"
	35	[91]	JMP      	2	; to 38
	36	[92]	LOADK    	5 -14	; 0.8
	37	[92]	JMP      	1	; to 39
	38	[94]	LOADK    	5 -10	; 1
	39	[97]	GETTABLE 	6 1 -16	; "direction"
	40	[97]	EQ       	1 6 -17	; - "south"
	41	[97]	JMP      	3	; to 45
	42	[97]	GETTABLE 	6 1 -16	; "direction"
	43	[97]	EQ       	0 6 -18	; - "north"
	44	[97]	JMP      	5	; to 50
	45	[98]	GETUPVAL 	6 4	; Screen
	46	[98]	SELF     	6 6 -19	; "getHeight"
	47	[98]	CALL     	6 2 2
	48	[98]	MUL      	4 6 5
	49	[98]	JMP      	24	; to 74
	50	[99]	GETTABLE 	6 1 -16	; "direction"
	51	[99]	EQ       	1 6 -20	; - "west"
	52	[99]	JMP      	3	; to 56
	53	[99]	GETTABLE 	6 1 -16	; "direction"
	54	[99]	EQ       	0 6 -21	; - "east"
	55	[99]	JMP      	5	; to 61
	56	[100]	GETUPVAL 	6 4	; Screen
	57	[100]	SELF     	6 6 -22	; "getWidth"
	58	[100]	CALL     	6 2 2
	59	[100]	MUL      	4 6 5
	60	[100]	JMP      	13	; to 74
	61	[102]	GETUPVAL 	6 4	; Screen
	62	[102]	SELF     	6 6 -22	; "getWidth"
	63	[102]	CALL     	6 2 2
	64	[103]	GETUPVAL 	7 4	; Screen
	65	[103]	SELF     	7 7 -19	; "getHeight"
	66	[103]	CALL     	7 2 2
	67	[105]	GETGLOBAL	8 -23	; math
	68	[105]	GETTABLE 	8 8 -24	; "sqrt"
	69	[105]	MUL      	9 6 6
	70	[105]	MUL      	10 7 7
	71	[105]	ADD      	9 9 10
	72	[105]	CALL     	8 2 2
	73	[105]	MUL      	4 8 5
	74	[108]	NEWTABLE 	6 0 0
	75	[109]	GETTABLE 	7 3 -25	; "fl_max"
	76	[109]	GETTABLE 	8 3 -26	; "fl_min"
	77	[109]	SUB      	7 7 8
	78	[109]	DIV      	7 7 -27	; - 2
	79	[109]	DIV      	7 7 -28	; - 10.6
	80	[110]	LOADK    	8 -10	; 1
	81	[110]	GETTABLE 	9 0 -29	; "steps_fl"
	82	[110]	LEN      	9 9
	83	[110]	LOADK    	10 -10	; 1
	84	[111]	FORPREP  	8 7	; to 92
	85	[112]	GETGLOBAL	12 -23	; math
	86	[112]	GETTABLE 	12 12 -30	; "ceil"
	87	[112]	GETTABLE 	13 0 -29	; "steps_fl"
	88	[112]	GETTABLE 	13 13 11
	89	[112]	MUL      	13 13 7
	90	[112]	CALL     	12 2 2
	91	[112]	SETTABLE 	6 11 12
	92	[110]	FORLOOP  	8 -8	; to 85
	93	[115]	GETTABLE 	8 1 -31	; "distance"
	94	[115]	EQ       	0 8 -3	; - nil
	95	[115]	JMP      	1	; to 97
	96	[116]	SETTABLE 	1 -31 -10	; "distance" 1
	97	[119]	GETGLOBAL	8 -23	; math
	98	[119]	GETTABLE 	8 8 -30	; "ceil"
	99	[119]	LEN      	9 6
	100	[119]	GETTABLE 	10 1 -31	; "distance"
	101	[119]	MUL      	9 9 10
	102	[119]	DIV      	9 9 4
	103	[119]	CALL     	8 2 2
	104	[120]	GETTABLE 	9 6 8
	105	[120]	TEST     	9 0 1
	106	[120]	JMP      	2	; to 109
	107	[120]	LEN      	9 6
	108	[120]	GETTABLE 	9 6 9
	109	[121]	LOADNIL  	10 10
	110	[122]	EQ       	1 2 -32	; - -1
	111	[122]	JMP      	3	; to 115
	112	[122]	EQ       	1 2 -10	; - 1
	113	[122]	JMP      	1	; to 115
	114	[124]	LOADK    	2 -10	; 1
	115	[126]	GETTABLE 	11 3 -2	; "fl_warmth"
	116	[126]	MUL      	12 2 9
	117	[126]	ADD      	10 11 12
	118	[127]	LT       	0 -33 10	; 100 -
	119	[127]	JMP      	2	; to 122
	120	[128]	LOADK    	10 -33	; 100
	121	[128]	JMP      	3	; to 125
	122	[129]	LT       	0 10 -34	; - 0
	123	[129]	JMP      	1	; to 125
	124	[130]	LOADK    	10 -34	; 0
	125	[132]	SELF     	11 3 -35	; "setWarmth"
	126	[132]	MOVE     	13 10
	127	[132]	CALL     	11 3 1
	128	[133]	SELF     	11 0 -36	; "onShowWarmth"
	129	[133]	CALL     	11 2 1
	130	[134]	LOADBOOL 	11 1 0
	131	[134]	RETURN   	11 2
	132	[135]	RETURN   	0 1

function <./frontend/apps/reader/modules/readerfrontlight.lua:138,151> (28 instructions, 112 bytes at 0x7fd0dac07d40)
1 param, 8 slots, 4 upvalues, 3 locals, 9 constants, 0 functions
	1	[139]	GETUPVAL 	1 0	; Device
	2	[139]	SELF     	1 1 -1	; "getPowerDevice"
	3	[139]	CALL     	1 2 2
	4	[140]	LOADNIL  	2 2
	5	[141]	GETTABLE 	3 1 -2	; "is_fl_on"
	6	[141]	TEST     	3 0 0
	7	[141]	JMP      	5	; to 13
	8	[142]	GETUPVAL 	3 1	; _
	9	[142]	LOADK    	4 -3	; "Frontlight enabled."
	10	[142]	CALL     	3 2 2
	11	[142]	MOVE     	2 3
	12	[142]	JMP      	4	; to 17
	13	[144]	GETUPVAL 	3 1	; _
	14	[144]	LOADK    	4 -4	; "Frontlight disabled."
	15	[144]	CALL     	3 2 2
	16	[144]	MOVE     	2 3
	17	[146]	GETUPVAL 	3 2	; UIManager
	18	[146]	SELF     	3 3 -5	; "show"
	19	[146]	GETUPVAL 	5 3	; Notification
	20	[146]	SELF     	5 5 -6	; "new"
	21	[146]	NEWTABLE 	7 0 2
	22	[147]	SETTABLE 	7 -7 2	; "text" -
	23	[148]	SETTABLE 	7 -8 -9	; "timeout" 1
	24	[146]	CALL     	5 3 0
	25	[146]	CALL     	3 0 1
	26	[150]	LOADBOOL 	3 1 0
	27	[150]	RETURN   	3 2
	28	[151]	RETURN   	0 1

function <./frontend/apps/reader/modules/readerfrontlight.lua:153,167> (40 instructions, 160 bytes at 0x7fd0dac08140)
1 param, 8 slots, 5 upvalues, 3 locals, 11 constants, 0 functions
	1	[154]	GETUPVAL 	1 0	; Device
	2	[154]	SELF     	1 1 -1	; "hasFrontlight"
	3	[154]	CALL     	1 2 2
	4	[154]	TEST     	1 0 1
	5	[154]	JMP      	2	; to 8
	6	[154]	LOADBOOL 	1 1 0
	7	[154]	RETURN   	1 2
	8	[155]	GETUPVAL 	1 0	; Device
	9	[155]	SELF     	1 1 -2	; "getPowerDevice"
	10	[155]	CALL     	1 2 2
	11	[156]	LOADNIL  	2 2
	12	[157]	SELF     	3 1 -3	; "isFrontlightOff"
	13	[157]	CALL     	3 2 2
	14	[157]	TEST     	3 0 0
	15	[157]	JMP      	5	; to 21
	16	[158]	GETUPVAL 	3 1	; _
	17	[158]	LOADK    	4 -4	; "Frontlight disabled."
	18	[158]	CALL     	3 2 2
	19	[158]	MOVE     	2 3
	20	[158]	JMP      	8	; to 29
	21	[160]	GETUPVAL 	3 2	; T
	22	[160]	GETUPVAL 	4 1	; _
	23	[160]	LOADK    	5 -5	; "Frontlight intensity set to %1."
	24	[160]	CALL     	4 2 2
	25	[160]	SELF     	5 1 -6	; "frontlightIntensity"
	26	[160]	CALL     	5 2 0
	27	[160]	CALL     	3 0 2
	28	[160]	MOVE     	2 3
	29	[162]	GETUPVAL 	3 3	; UIManager
	30	[162]	SELF     	3 3 -7	; "show"
	31	[162]	GETUPVAL 	5 4	; Notification
	32	[162]	SELF     	5 5 -8	; "new"
	33	[162]	NEWTABLE 	7 0 2
	34	[163]	SETTABLE 	7 -9 2	; "text" -
	35	[164]	SETTABLE 	7 -10 -11	; "timeout" 1
	36	[162]	CALL     	5 3 0
	37	[162]	CALL     	3 0 1
	38	[166]	LOADBOOL 	3 1 0
	39	[166]	RETURN   	3 2
	40	[167]	RETURN   	0 1

function <./frontend/apps/reader/modules/readerfrontlight.lua:169,178> (24 instructions, 96 bytes at 0x7fd0dac06e40)
2 params, 11 slots, 5 upvalues, 3 locals, 9 constants, 0 functions
	1	[170]	GETUPVAL 	2 0	; Device
	2	[170]	SELF     	2 2 -1	; "getPowerDevice"
	3	[170]	CALL     	2 2 2
	4	[171]	GETTABLE 	3 2 -2	; "fl_warmth"
	5	[171]	EQ       	1 3 -3	; - nil
	6	[171]	JMP      	15	; to 22
	7	[172]	GETUPVAL 	3 1	; UIManager
	8	[172]	SELF     	3 3 -4	; "show"
	9	[172]	GETUPVAL 	5 2	; Notification
	10	[172]	SELF     	5 5 -5	; "new"
	11	[172]	NEWTABLE 	7 0 2
	12	[173]	GETUPVAL 	8 3	; T
	13	[173]	GETUPVAL 	9 4	; _
	14	[173]	LOADK    	10 -7	; "Warmth set to %1."
	15	[173]	CALL     	9 2 2
	16	[173]	GETTABLE 	10 2 -2	; "fl_warmth"
	17	[173]	CALL     	8 3 2
	18	[173]	SETTABLE 	7 -6 8	; "text" -
	19	[174]	SETTABLE 	7 -8 -9	; "timeout" 1
	20	[172]	CALL     	5 3 0
	21	[172]	CALL     	3 0 1
	22	[177]	LOADBOOL 	3 1 0
	23	[177]	RETURN   	3 2
	24	[178]	RETURN   	0 1

function <./frontend/apps/reader/modules/readerfrontlight.lua:180,185> (14 instructions, 56 bytes at 0x7fd0dac08980)
1 param, 9 slots, 2 upvalues, 2 locals, 6 constants, 0 functions
	1	[181]	GETGLOBAL	1 -1	; require
	2	[181]	LOADK    	2 -2	; "ui/widget/frontlightwidget"
	3	[181]	CALL     	1 2 2
	4	[182]	GETUPVAL 	2 0	; UIManager
	5	[182]	SELF     	2 2 -3	; "show"
	6	[182]	SELF     	4 1 -4	; "new"
	7	[182]	NEWTABLE 	6 0 1
	8	[183]	GETUPVAL 	7 1	; Device
	9	[183]	SELF     	7 7 -6	; "hasLightLevelFallback"
	10	[183]	CALL     	7 2 2
	11	[183]	SETTABLE 	6 -5 7	; "use_system_fl" -
	12	[182]	CALL     	4 3 0
	13	[182]	CALL     	2 0 1
	14	[185]	RETURN   	0 1

function <./frontend/apps/reader/modules/readerfrontlight.lua:187,190> (8 instructions, 32 bytes at 0x7fd0dac08ee0)
1 param, 4 slots, 1 upvalue, 1 local, 3 constants, 0 functions
	1	[188]	GETTABLE 	1 0 -1	; "fl_dialog"
	2	[188]	SELF     	1 1 -2	; "onClose"
	3	[188]	CALL     	1 2 1
	4	[189]	GETUPVAL 	1 0	; UIManager
	5	[189]	SELF     	1 1 -3	; "close"
	6	[189]	GETTABLE 	3 0 -1	; "fl_dialog"
	7	[189]	CALL     	1 3 1
	8	[190]	RETURN   	0 1
