
main <./spec/unit/readerpaging_spec.lua:0,0> (5 instructions, 20 bytes at 0x7fce984068d0)
0+ params, 3 slots, 0 upvalues, 0 locals, 2 constants, 1 function
	1	[1]	GETGLOBAL	0 -1	; describe
	2	[1]	LOADK    	1 -2	; "Readerpaging module"
	3	[94]	CLOSURE  	2 0	; 0x7fce98406b70
	4	[1]	CALL     	0 3 1
	5	[94]	RETURN   	0 1

function <./spec/unit/readerpaging_spec.lua:1,94> (32 instructions, 128 bytes at 0x7fce98406b70)
0 params, 10 slots, 0 upvalues, 7 locals, 5 constants, 3 functions
	1	[2]	LOADK    	0 -1	; "spec/front/unit/data/sample.pdf"
	2	[3]	LOADNIL  	1 6
	3	[6]	GETGLOBAL	7 -2	; setup
	4	[12]	CLOSURE  	8 0	; 0x7fce98406e30
	5	[12]	MOVE     	0 2
	6	[12]	MOVE     	0 3
	7	[12]	MOVE     	0 4
	8	[12]	MOVE     	0 5
	9	[6]	CALL     	7 2 1
	10	[14]	GETGLOBAL	7 -3	; describe
	11	[14]	LOADK    	8 -4	; "Page mode"
	12	[39]	CLOSURE  	9 1	; 0x7fce98407810
	13	[39]	MOVE     	0 1
	14	[39]	MOVE     	0 5
	15	[39]	MOVE     	0 4
	16	[39]	MOVE     	0 0
	17	[39]	MOVE     	0 6
	18	[39]	MOVE     	0 2
	19	[39]	MOVE     	0 3
	20	[14]	CALL     	7 3 1
	21	[41]	GETGLOBAL	7 -3	; describe
	22	[41]	LOADK    	8 -5	; "Scroll mode"
	23	[93]	CLOSURE  	9 2	; 0x7fce98408cf0
	24	[93]	MOVE     	0 0
	25	[93]	MOVE     	0 1
	26	[93]	MOVE     	0 5
	27	[93]	MOVE     	0 4
	28	[93]	MOVE     	0 6
	29	[93]	MOVE     	0 2
	30	[93]	MOVE     	0 3
	31	[41]	CALL     	7 3 1
	32	[94]	RETURN   	0 1

function <./spec/unit/readerpaging_spec.lua:6,12> (20 instructions, 80 bytes at 0x7fce98406e30)
0 params, 2 slots, 4 upvalues, 0 locals, 6 constants, 0 functions
	1	[7]	GETGLOBAL	0 -1	; require
	2	[7]	LOADK    	1 -2	; "commonrequire"
	3	[7]	CALL     	0 2 1
	4	[8]	GETGLOBAL	0 -1	; require
	5	[8]	LOADK    	1 -3	; "ui/uimanager"
	6	[8]	CALL     	0 2 2
	7	[8]	SETUPVAL 	0 0	; UIManager
	8	[9]	GETGLOBAL	0 -1	; require
	9	[9]	LOADK    	1 -4	; "ui/event"
	10	[9]	CALL     	0 2 2
	11	[9]	SETUPVAL 	0 1	; Event
	12	[10]	GETGLOBAL	0 -1	; require
	13	[10]	LOADK    	1 -5	; "document/documentregistry"
	14	[10]	CALL     	0 2 2
	15	[10]	SETUPVAL 	0 2	; DocumentRegistry
	16	[11]	GETGLOBAL	0 -1	; require
	17	[11]	LOADK    	1 -6	; "apps/reader/readerui"
	18	[11]	CALL     	0 2 2
	19	[11]	SETUPVAL 	0 3	; ReaderUI
	20	[12]	RETURN   	0 1

function <./spec/unit/readerpaging_spec.lua:14,39> (17 instructions, 68 bytes at 0x7fce98407810)
0 params, 3 slots, 7 upvalues, 0 locals, 3 constants, 2 functions
	1	[15]	GETGLOBAL	0 -1	; setup
	2	[20]	CLOSURE  	1 0	; 0x7fce98407960
	3	[20]	GETUPVAL 	0 0	; readerui
	4	[20]	GETUPVAL 	0 1	; ReaderUI
	5	[20]	GETUPVAL 	0 2	; DocumentRegistry
	6	[20]	GETUPVAL 	0 3	; sample_pdf
	7	[20]	GETUPVAL 	0 4	; paging
	8	[15]	CALL     	0 2 1
	9	[22]	GETGLOBAL	0 -2	; it
	10	[22]	LOADK    	1 -3	; "should emit EndOfBook event at the end"
	11	[38]	CLOSURE  	2 1	; 0x7fce984065c0
	12	[38]	GETUPVAL 	0 5	; UIManager
	13	[38]	GETUPVAL 	0 0	; readerui
	14	[38]	GETUPVAL 	0 6	; Event
	15	[38]	GETUPVAL 	0 4	; paging
	16	[22]	CALL     	0 3 1
	17	[39]	RETURN   	0 1

function <./spec/unit/readerpaging_spec.lua:15,20> (14 instructions, 56 bytes at 0x7fce98407960)
0 params, 6 slots, 5 upvalues, 0 locals, 4 constants, 0 functions
	1	[16]	GETUPVAL 	0 1	; ReaderUI
	2	[16]	SELF     	0 0 -1	; "new"
	3	[16]	NEWTABLE 	2 0 1
	4	[17]	GETUPVAL 	3 2	; DocumentRegistry
	5	[17]	SELF     	3 3 -3	; "openDocument"
	6	[17]	GETUPVAL 	5 3	; sample_pdf
	7	[17]	CALL     	3 3 2
	8	[17]	SETTABLE 	2 -2 3	; "document" -
	9	[16]	CALL     	0 3 2
	10	[18]	SETUPVAL 	0 0	; readerui
	11	[19]	GETUPVAL 	0 0	; readerui
	12	[19]	GETTABLE 	0 0 -4	; "paging"
	13	[19]	SETUPVAL 	0 4	; paging
	14	[20]	RETURN   	0 1

function <./spec/unit/readerpaging_spec.lua:22,38> (56 instructions, 224 bytes at 0x7fce984065c0)
0 params, 6 slots, 4 upvalues, 1 local, 20 constants, 2 functions
	1	[23]	GETUPVAL 	0 0	; UIManager
	2	[23]	SELF     	0 0 -1	; "quit"
	3	[23]	CALL     	0 2 1
	4	[24]	GETUPVAL 	0 0	; UIManager
	5	[24]	SELF     	0 0 -2	; "show"
	6	[24]	GETUPVAL 	2 1	; readerui
	7	[24]	CALL     	0 3 1
	8	[25]	GETUPVAL 	0 0	; UIManager
	9	[25]	SELF     	0 0 -3	; "nextTick"
	10	[25]	CLOSURE  	2 0	; 0x7fce98408160
	11	[25]	GETUPVAL 	0 0	; UIManager
	12	[25]	GETUPVAL 	0 1	; readerui
	13	[25]	CALL     	0 3 1
	14	[26]	GETUPVAL 	0 0	; UIManager
	15	[26]	SELF     	0 0 -4	; "run"
	16	[26]	CALL     	0 2 1
	17	[27]	GETUPVAL 	0 1	; readerui
	18	[27]	SELF     	0 0 -5	; "handleEvent"
	19	[27]	GETUPVAL 	2 2	; Event
	20	[27]	SELF     	2 2 -6	; "new"
	21	[27]	LOADK    	4 -7	; "SetScrollMode"
	22	[27]	LOADBOOL 	5 0 0
	23	[27]	CALL     	2 4 0
	24	[27]	CALL     	0 0 1
	25	[28]	GETUPVAL 	0 1	; readerui
	26	[28]	GETTABLE 	0 0 -8	; "zooming"
	27	[28]	SELF     	0 0 -9	; "setZoomMode"
	28	[28]	LOADK    	2 -10	; "pageheight"
	29	[28]	CALL     	0 3 1
	30	[29]	GETUPVAL 	0 3	; paging
	31	[29]	SELF     	0 0 -11	; "onGotoPage"
	32	[29]	GETUPVAL 	2 1	; readerui
	33	[29]	GETTABLE 	2 2 -12	; "document"
	34	[29]	SELF     	2 2 -13	; "getPageCount"
	35	[29]	CALL     	2 2 0
	36	[29]	CALL     	0 0 1
	37	[30]	LOADBOOL 	0 0 0
	38	[31]	GETUPVAL 	1 1	; readerui
	39	[33]	CLOSURE  	2 1	; 0x7fce98408440
	40	[33]	MOVE     	0 0
	41	[33]	SETTABLE 	1 -14 2	; "onEndOfBook" -
	42	[34]	GETUPVAL 	1 3	; paging
	43	[34]	SELF     	1 1 -15	; "onGotoViewRel"
	44	[34]	LOADK    	3 -16	; 1
	45	[34]	CALL     	1 3 1
	46	[35]	GETGLOBAL	1 -17	; assert
	47	[35]	GETTABLE 	1 1 -18	; "is"
	48	[35]	GETTABLE 	1 1 -19	; "truthy"
	49	[35]	MOVE     	2 0
	50	[35]	CALL     	1 2 1
	51	[36]	GETUPVAL 	1 1	; readerui
	52	[36]	SETTABLE 	1 -14 -20	; "onEndOfBook" nil
	53	[37]	GETUPVAL 	1 0	; UIManager
	54	[37]	SELF     	1 1 -1	; "quit"
	55	[37]	CALL     	1 2 1
	56	[38]	RETURN   	0 1

function <./spec/unit/readerpaging_spec.lua:25,25> (5 instructions, 20 bytes at 0x7fce98408160)
0 params, 3 slots, 2 upvalues, 0 locals, 1 constant, 0 functions
	1	[25]	GETUPVAL 	0 0	; UIManager
	2	[25]	SELF     	0 0 -1	; "close"
	3	[25]	GETUPVAL 	2 1	; readerui
	4	[25]	CALL     	0 3 1
	5	[25]	RETURN   	0 1

function <./spec/unit/readerpaging_spec.lua:31,33> (3 instructions, 12 bytes at 0x7fce98408440)
0 params, 2 slots, 1 upvalue, 0 locals, 0 constants, 0 functions
	1	[32]	LOADBOOL 	0 1 0
	2	[32]	SETUPVAL 	0 0	; called
	3	[33]	RETURN   	0 1

function <./spec/unit/readerpaging_spec.lua:41,93> (30 instructions, 120 bytes at 0x7fce98408cf0)
0 params, 3 slots, 7 upvalues, 0 locals, 5 constants, 4 functions
	1	[42]	GETGLOBAL	0 -1	; setup
	2	[52]	CLOSURE  	1 0	; 0x7fce98408d70
	3	[52]	GETUPVAL 	0 0	; sample_pdf
	4	[52]	GETUPVAL 	0 1	; readerui
	5	[52]	GETUPVAL 	0 2	; ReaderUI
	6	[52]	GETUPVAL 	0 3	; DocumentRegistry
	7	[52]	GETUPVAL 	0 4	; paging
	8	[42]	CALL     	0 2 1
	9	[54]	GETGLOBAL	0 -2	; it
	10	[54]	LOADK    	1 -3	; "should emit EndOfBook event at the end"
	11	[72]	CLOSURE  	2 1	; 0x7fce984090c0
	12	[72]	GETUPVAL 	0 5	; UIManager
	13	[72]	GETUPVAL 	0 1	; readerui
	14	[72]	GETUPVAL 	0 4	; paging
	15	[72]	GETUPVAL 	0 6	; Event
	16	[54]	CALL     	0 3 1
	17	[74]	GETGLOBAL	0 -2	; it
	18	[74]	LOADK    	1 -4	; "should scroll backward on the first page without crash"
	19	[80]	CLOSURE  	2 2	; 0x7fce98409550
	20	[80]	GETUPVAL 	0 2	; ReaderUI
	21	[80]	GETUPVAL 	0 3	; DocumentRegistry
	22	[74]	CALL     	0 3 1
	23	[82]	GETGLOBAL	0 -2	; it
	24	[82]	LOADK    	1 -5	; "should scroll forward on the last page without crash"
	25	[92]	CLOSURE  	2 3	; 0x7fce98409990
	26	[92]	GETUPVAL 	0 2	; ReaderUI
	27	[92]	GETUPVAL 	0 3	; DocumentRegistry
	28	[92]	GETUPVAL 	0 4	; paging
	29	[82]	CALL     	0 3 1
	30	[93]	RETURN   	0 1

function <./spec/unit/readerpaging_spec.lua:42,52> (32 instructions, 128 bytes at 0x7fce98408d70)
0 params, 8 slots, 5 upvalues, 2 locals, 12 constants, 0 functions
	1	[43]	GETGLOBAL	0 -1	; require
	2	[43]	LOADK    	1 -2	; "ffi/util"
	3	[43]	CALL     	0 2 2
	4	[43]	GETTABLE 	0 0 -3	; "purgeDir"
	5	[44]	GETGLOBAL	1 -1	; require
	6	[44]	LOADK    	2 -4	; "docsettings"
	7	[44]	CALL     	1 2 2
	8	[45]	MOVE     	2 0
	9	[45]	SELF     	3 1 -5	; "getSidecarDir"
	10	[45]	GETUPVAL 	5 0	; sample_pdf
	11	[45]	CALL     	3 3 0
	12	[45]	CALL     	2 0 1
	13	[46]	GETGLOBAL	2 -6	; os
	14	[46]	GETTABLE 	2 2 -7	; "remove"
	15	[46]	SELF     	3 1 -8	; "getHistoryPath"
	16	[46]	GETUPVAL 	5 0	; sample_pdf
	17	[46]	CALL     	3 3 0
	18	[46]	CALL     	2 0 1
	19	[48]	GETUPVAL 	2 2	; ReaderUI
	20	[48]	SELF     	2 2 -9	; "new"
	21	[48]	NEWTABLE 	4 0 1
	22	[49]	GETUPVAL 	5 3	; DocumentRegistry
	23	[49]	SELF     	5 5 -11	; "openDocument"
	24	[49]	GETUPVAL 	7 0	; sample_pdf
	25	[49]	CALL     	5 3 2
	26	[49]	SETTABLE 	4 -10 5	; "document" -
	27	[48]	CALL     	2 3 2
	28	[50]	SETUPVAL 	2 1	; readerui
	29	[51]	GETUPVAL 	2 1	; readerui
	30	[51]	GETTABLE 	2 2 -12	; "paging"
	31	[51]	SETUPVAL 	2 4	; paging
	32	[52]	RETURN   	0 1

function <./spec/unit/readerpaging_spec.lua:54,72> (63 instructions, 252 bytes at 0x7fce984090c0)
0 params, 6 slots, 4 upvalues, 1 local, 21 constants, 2 functions
	1	[55]	GETUPVAL 	0 0	; UIManager
	2	[55]	SELF     	0 0 -1	; "quit"
	3	[55]	CALL     	0 2 1
	4	[56]	GETUPVAL 	0 0	; UIManager
	5	[56]	SELF     	0 0 -2	; "show"
	6	[56]	GETUPVAL 	2 1	; readerui
	7	[56]	CALL     	0 3 1
	8	[57]	GETUPVAL 	0 0	; UIManager
	9	[57]	SELF     	0 0 -3	; "nextTick"
	10	[57]	CLOSURE  	2 0	; 0x7fce98409240
	11	[57]	GETUPVAL 	0 0	; UIManager
	12	[57]	GETUPVAL 	0 1	; readerui
	13	[57]	CALL     	0 3 1
	14	[58]	GETUPVAL 	0 0	; UIManager
	15	[58]	SELF     	0 0 -4	; "run"
	16	[58]	CALL     	0 2 1
	17	[59]	GETUPVAL 	0 2	; paging
	18	[59]	NEWTABLE 	1 0 0
	19	[59]	SETTABLE 	0 -5 1	; "page_positions" -
	20	[60]	GETUPVAL 	0 1	; readerui
	21	[60]	SELF     	0 0 -6	; "handleEvent"
	22	[60]	GETUPVAL 	2 3	; Event
	23	[60]	SELF     	2 2 -7	; "new"
	24	[60]	LOADK    	4 -8	; "SetScrollMode"
	25	[60]	LOADBOOL 	5 1 0
	26	[60]	CALL     	2 4 0
	27	[60]	CALL     	0 0 1
	28	[61]	GETUPVAL 	0 2	; paging
	29	[61]	SELF     	0 0 -9	; "onGotoPage"
	30	[61]	GETUPVAL 	2 1	; readerui
	31	[61]	GETTABLE 	2 2 -10	; "document"
	32	[61]	SELF     	2 2 -11	; "getPageCount"
	33	[61]	CALL     	2 2 0
	34	[61]	CALL     	0 0 1
	35	[62]	GETUPVAL 	0 1	; readerui
	36	[62]	GETTABLE 	0 0 -12	; "zooming"
	37	[62]	SELF     	0 0 -13	; "setZoomMode"
	38	[62]	LOADK    	2 -14	; "pageheight"
	39	[62]	CALL     	0 3 1
	40	[63]	LOADBOOL 	0 0 0
	41	[64]	GETUPVAL 	1 1	; readerui
	42	[66]	CLOSURE  	2 1	; 0x7fce984067b0
	43	[66]	MOVE     	0 0
	44	[66]	SETTABLE 	1 -15 2	; "onEndOfBook" -
	45	[67]	GETUPVAL 	1 2	; paging
	46	[67]	SELF     	1 1 -16	; "onGotoViewRel"
	47	[67]	LOADK    	3 -17	; 1
	48	[67]	CALL     	1 3 1
	49	[68]	GETUPVAL 	1 2	; paging
	50	[68]	SELF     	1 1 -16	; "onGotoViewRel"
	51	[68]	LOADK    	3 -17	; 1
	52	[68]	CALL     	1 3 1
	53	[69]	GETGLOBAL	1 -18	; assert
	54	[69]	GETTABLE 	1 1 -19	; "is"
	55	[69]	GETTABLE 	1 1 -20	; "truthy"
	56	[69]	MOVE     	2 0
	57	[69]	CALL     	1 2 1
	58	[70]	GETUPVAL 	1 1	; readerui
	59	[70]	SETTABLE 	1 -15 -21	; "onEndOfBook" nil
	60	[71]	GETUPVAL 	1 0	; UIManager
	61	[71]	SELF     	1 1 -1	; "quit"
	62	[71]	CALL     	1 2 1
	63	[72]	RETURN   	0 1

function <./spec/unit/readerpaging_spec.lua:57,57> (5 instructions, 20 bytes at 0x7fce98409240)
0 params, 3 slots, 2 upvalues, 0 locals, 1 constant, 0 functions
	1	[57]	GETUPVAL 	0 0	; UIManager
	2	[57]	SELF     	0 0 -1	; "close"
	3	[57]	GETUPVAL 	2 1	; readerui
	4	[57]	CALL     	0 3 1
	5	[57]	RETURN   	0 1

function <./spec/unit/readerpaging_spec.lua:64,66> (3 instructions, 12 bytes at 0x7fce984067b0)
0 params, 2 slots, 1 upvalue, 0 locals, 0 constants, 0 functions
	1	[65]	LOADBOOL 	0 1 0
	2	[65]	SETUPVAL 	0 0	; called
	3	[66]	RETURN   	0 1

function <./spec/unit/readerpaging_spec.lua:74,80> (15 instructions, 60 bytes at 0x7fce98409550)
0 params, 7 slots, 2 upvalues, 2 locals, 7 constants, 0 functions
	1	[75]	LOADK    	0 -1	; "spec/front/unit/data/djvu3spec.djvu"
	2	[76]	GETUPVAL 	1 0	; ReaderUI
	3	[76]	SELF     	1 1 -2	; "new"
	4	[76]	NEWTABLE 	3 0 1
	5	[77]	GETUPVAL 	4 1	; DocumentRegistry
	6	[77]	SELF     	4 4 -4	; "openDocument"
	7	[77]	MOVE     	6 0
	8	[77]	CALL     	4 3 2
	9	[77]	SETTABLE 	3 -3 4	; "document" -
	10	[76]	CALL     	1 3 2
	11	[79]	GETTABLE 	2 1 -5	; "paging"
	12	[79]	SELF     	2 2 -6	; "onScrollPanRel"
	13	[79]	LOADK    	4 -7	; -100
	14	[79]	CALL     	2 3 1
	15	[80]	RETURN   	0 1

function <./spec/unit/readerpaging_spec.lua:82,92> (31 instructions, 124 bytes at 0x7fce98409990)
0 params, 7 slots, 3 upvalues, 2 locals, 10 constants, 0 functions
	1	[83]	LOADK    	0 -1	; "spec/front/unit/data/djvu3spec.djvu"
	2	[84]	GETUPVAL 	1 0	; ReaderUI
	3	[84]	SELF     	1 1 -2	; "new"
	4	[84]	NEWTABLE 	3 0 1
	5	[85]	GETUPVAL 	4 1	; DocumentRegistry
	6	[85]	SELF     	4 4 -4	; "openDocument"
	7	[85]	MOVE     	6 0
	8	[85]	CALL     	4 3 2
	9	[85]	SETTABLE 	3 -3 4	; "document" -
	10	[84]	CALL     	1 3 2
	11	[87]	GETTABLE 	2 1 -5	; "paging"
	12	[87]	SETUPVAL 	2 2	; paging
	13	[88]	GETUPVAL 	2 2	; paging
	14	[88]	SELF     	2 2 -6	; "onGotoPage"
	15	[88]	GETTABLE 	4 1 -3	; "document"
	16	[88]	SELF     	4 4 -7	; "getPageCount"
	17	[88]	CALL     	4 2 0
	18	[88]	CALL     	2 0 1
	19	[89]	GETUPVAL 	2 2	; paging
	20	[89]	SELF     	2 2 -8	; "onScrollPanRel"
	21	[89]	LOADK    	4 -9	; 120
	22	[89]	CALL     	2 3 1
	23	[90]	GETUPVAL 	2 2	; paging
	24	[90]	SELF     	2 2 -8	; "onScrollPanRel"
	25	[90]	LOADK    	4 -10	; -1
	26	[90]	CALL     	2 3 1
	27	[91]	GETUPVAL 	2 2	; paging
	28	[91]	SELF     	2 2 -8	; "onScrollPanRel"
	29	[91]	LOADK    	4 -9	; 120
	30	[91]	CALL     	2 3 1
	31	[92]	RETURN   	0 1
