
main <./spec/unit/readerdictionary_spec.lua:0,0> (5 instructions, 20 bytes at 0x7fd01d4068d0)
0+ params, 3 slots, 0 upvalues, 0 locals, 2 constants, 1 function
	1	[1]	GETGLOBAL	0 -1	; describe
	2	[1]	LOADK    	1 -2	; "Readerdictionary module"
	3	[34]	CLOSURE  	2 0	; 0x7fd01d406b70
	4	[1]	CALL     	0 3 1
	5	[34]	RETURN   	0 1

function <./spec/unit/readerdictionary_spec.lua:1,34> (26 instructions, 104 bytes at 0x7fd01d406b70)
0 params, 10 slots, 0 upvalues, 7 locals, 3 constants, 3 functions
	1	[4]	GETGLOBAL	4 -1	; setup
	2	[10]	CLOSURE  	5 0	; 0x7fd01d406f10
	3	[10]	MOVE     	0 0
	4	[10]	MOVE     	0 1
	5	[10]	MOVE     	0 2
	6	[10]	MOVE     	0 3
	7	[4]	CALL     	4 2 1
	8	[12]	LOADNIL  	4 6
	9	[13]	GETGLOBAL	7 -1	; setup
	10	[20]	CLOSURE  	8 1	; 0x7fd01d406e00
	11	[20]	MOVE     	0 4
	12	[20]	MOVE     	0 1
	13	[20]	MOVE     	0 0
	14	[20]	MOVE     	0 5
	15	[20]	MOVE     	0 6
	16	[13]	CALL     	7 2 1
	17	[21]	GETGLOBAL	7 -2	; it
	18	[21]	LOADK    	8 -3	; "should show quick lookup window"
	19	[33]	CLOSURE  	9 2	; 0x7fd01d4066c0
	20	[33]	MOVE     	0 2
	21	[33]	MOVE     	0 4
	22	[33]	MOVE     	0 5
	23	[33]	MOVE     	0 6
	24	[33]	MOVE     	0 3
	25	[21]	CALL     	7 3 1
	26	[34]	RETURN   	0 1

function <./spec/unit/readerdictionary_spec.lua:4,10> (21 instructions, 84 bytes at 0x7fd01d406f10)
0 params, 2 slots, 4 upvalues, 0 locals, 7 constants, 0 functions
	1	[5]	GETGLOBAL	0 -1	; require
	2	[5]	LOADK    	1 -2	; "commonrequire"
	3	[5]	CALL     	0 2 1
	4	[6]	GETGLOBAL	0 -1	; require
	5	[6]	LOADK    	1 -3	; "document/documentregistry"
	6	[6]	CALL     	0 2 2
	7	[6]	SETUPVAL 	0 0	; DocumentRegistry
	8	[7]	GETGLOBAL	0 -1	; require
	9	[7]	LOADK    	1 -4	; "apps/reader/readerui"
	10	[7]	CALL     	0 2 2
	11	[7]	SETUPVAL 	0 1	; ReaderUI
	12	[8]	GETGLOBAL	0 -1	; require
	13	[8]	LOADK    	1 -5	; "ui/uimanager"
	14	[8]	CALL     	0 2 2
	15	[8]	SETUPVAL 	0 2	; UIManager
	16	[9]	GETGLOBAL	0 -1	; require
	17	[9]	LOADK    	1 -6	; "device"
	18	[9]	CALL     	0 2 2
	19	[9]	GETTABLE 	0 0 -7	; "screen"
	20	[9]	SETUPVAL 	0 3	; Screen
	21	[10]	RETURN   	0 1

function <./spec/unit/readerdictionary_spec.lua:13,20> (18 instructions, 72 bytes at 0x7fd01d406e00)
0 params, 7 slots, 5 upvalues, 1 local, 6 constants, 0 functions
	1	[14]	LOADK    	0 -1	; "spec/front/unit/data/leaves.epub"
	2	[15]	GETUPVAL 	1 1	; ReaderUI
	3	[15]	SELF     	1 1 -2	; "new"
	4	[15]	NEWTABLE 	3 0 1
	5	[16]	GETUPVAL 	4 2	; DocumentRegistry
	6	[16]	SELF     	4 4 -4	; "openDocument"
	7	[16]	MOVE     	6 0
	8	[16]	CALL     	4 3 2
	9	[16]	SETTABLE 	3 -3 4	; "document" -
	10	[15]	CALL     	1 3 2
	11	[17]	SETUPVAL 	1 0	; readerui
	12	[18]	GETUPVAL 	1 0	; readerui
	13	[18]	GETTABLE 	1 1 -5	; "rolling"
	14	[18]	SETUPVAL 	1 3	; rolling
	15	[19]	GETUPVAL 	1 0	; readerui
	16	[19]	GETTABLE 	1 1 -6	; "dictionary"
	17	[19]	SETUPVAL 	1 4	; dictionary
	18	[20]	RETURN   	0 1

function <./spec/unit/readerdictionary_spec.lua:21,33> (32 instructions, 128 bytes at 0x7fd01d4066c0)
0 params, 5 slots, 5 upvalues, 1 local, 11 constants, 1 function
	1	[22]	LOADK    	0 -1	; "screenshots/reader_dictionary.png"
	2	[23]	GETUPVAL 	1 0	; UIManager
	3	[23]	SELF     	1 1 -2	; "quit"
	4	[23]	CALL     	1 2 1
	5	[24]	GETUPVAL 	1 0	; UIManager
	6	[24]	SELF     	1 1 -3	; "show"
	7	[24]	GETUPVAL 	3 1	; readerui
	8	[24]	CALL     	1 3 1
	9	[25]	GETUPVAL 	1 2	; rolling
	10	[25]	SELF     	1 1 -4	; "onGotoPage"
	11	[25]	LOADK    	3 -5	; 100
	12	[25]	CALL     	1 3 1
	13	[26]	GETUPVAL 	1 3	; dictionary
	14	[26]	SELF     	1 1 -6	; "onLookupWord"
	15	[26]	LOADK    	3 -7	; "test"
	16	[26]	CALL     	1 3 1
	17	[27]	GETUPVAL 	1 0	; UIManager
	18	[27]	SELF     	1 1 -8	; "scheduleIn"
	19	[27]	LOADK    	3 -9	; 1
	20	[30]	CLOSURE  	4 0	; 0x7fd01d407f40
	21	[30]	GETUPVAL 	0 0	; UIManager
	22	[30]	GETUPVAL 	0 3	; dictionary
	23	[30]	GETUPVAL 	0 1	; readerui
	24	[27]	CALL     	1 4 1
	25	[31]	GETUPVAL 	1 0	; UIManager
	26	[31]	SELF     	1 1 -10	; "run"
	27	[31]	CALL     	1 2 1
	28	[32]	GETUPVAL 	1 4	; Screen
	29	[32]	SELF     	1 1 -11	; "shot"
	30	[32]	MOVE     	3 0
	31	[32]	CALL     	1 3 1
	32	[33]	RETURN   	0 1

function <./spec/unit/readerdictionary_spec.lua:27,30> (10 instructions, 40 bytes at 0x7fd01d407f40)
0 params, 3 slots, 3 upvalues, 0 locals, 2 constants, 0 functions
	1	[28]	GETUPVAL 	0 0	; UIManager
	2	[28]	SELF     	0 0 -1	; "close"
	3	[28]	GETUPVAL 	2 1	; dictionary
	4	[28]	GETTABLE 	2 2 -2	; "dict_window"
	5	[28]	CALL     	0 3 1
	6	[29]	GETUPVAL 	0 0	; UIManager
	7	[29]	SELF     	0 0 -1	; "close"
	8	[29]	GETUPVAL 	2 2	; readerui
	9	[29]	CALL     	0 3 1
	10	[30]	RETURN   	0 1
