
main <./frontend/ui/widget/rectspan.lua:0,0> (12 instructions, 48 bytes at 0x7f7fc0c068d0)
0+ params, 4 slots, 0 upvalues, 2 locals, 7 constants, 1 function
	1	[1]	GETGLOBAL	0 -1	; require
	2	[1]	LOADK    	1 -2	; "ui/widget/widget"
	3	[1]	CALL     	0 2 2
	4	[6]	SELF     	1 0 -3	; "new"
	5	[6]	NEWTABLE 	3 0 2
	6	[7]	SETTABLE 	3 -4 -5	; "width" 0
	7	[8]	SETTABLE 	3 -6 -5	; "hright" 0
	8	[6]	CALL     	1 3 2
	9	[13]	CLOSURE  	2 0	; 0x7f7fc0c06bf0
	10	[11]	SETTABLE 	1 -7 2	; "getSize" -
	11	[15]	RETURN   	1 2
	12	[15]	RETURN   	0 1

function <./frontend/ui/widget/rectspan.lua:11,13> (7 instructions, 28 bytes at 0x7f7fc0c06bf0)
1 param, 3 slots, 0 upvalues, 1 local, 4 constants, 0 functions
	1	[12]	NEWTABLE 	1 0 2
	2	[12]	GETTABLE 	2 0 -2	; "width"
	3	[12]	SETTABLE 	1 -1 2	; "w" -
	4	[12]	GETTABLE 	2 0 -4	; "height"
	5	[12]	SETTABLE 	1 -3 2	; "h" -
	6	[12]	RETURN   	1 2
	7	[13]	RETURN   	0 1
