
main <./frontend/ui/elements/refresh_menu_table.lua:0,0> (126 instructions, 504 bytes at 0x7f95214068f0)
0+ params, 18 slots, 0 upvalues, 7 locals, 20 constants, 22 functions
	1	[1]	GETGLOBAL	0 -1	; require
	2	[1]	LOADK    	1 -2	; "device"
	3	[1]	CALL     	0 2 2
	4	[2]	GETGLOBAL	1 -1	; require
	5	[2]	LOADK    	2 -3	; "ui/uimanager"
	6	[2]	CALL     	1 2 2
	7	[3]	GETGLOBAL	2 -1	; require
	8	[3]	LOADK    	3 -4	; "gettext"
	9	[3]	CALL     	2 2 2
	10	[4]	GETTABLE 	3 0 -5	; "screen"
	11	[5]	GETGLOBAL	4 -1	; require
	12	[5]	LOADK    	5 -6	; "ffi/util"
	13	[5]	CALL     	4 2 2
	14	[5]	GETTABLE 	4 4 -7	; "template"
	15	[17]	CLOSURE  	5 0	; 0x7f9521407000
	16	[37]	CLOSURE  	6 1	; 0x7f9521407430
	17	[37]	MOVE     	0 3
	18	[37]	MOVE     	0 5
	19	[37]	MOVE     	0 2
	20	[37]	MOVE     	0 1
	21	[40]	NEWTABLE 	7 0 3
	22	[41]	MOVE     	8 2
	23	[41]	LOADK    	9 -9	; "Full refresh rate"
	24	[41]	CALL     	8 2 2
	25	[41]	SETTABLE 	7 -8 8	; "text" -
	26	[42]	SETTABLE 	7 -10 -11	; "separator" true
	27	[43]	NEWTABLE 	8 7 0
	28	[43]	NEWTABLE 	9 0 3
	29	[45]	MOVE     	10 2
	30	[45]	LOADK    	11 -13	; "Never"
	31	[45]	CALL     	10 2 2
	32	[45]	SETTABLE 	9 -8 10	; "text" -
	33	[46]	CLOSURE  	10 2	; 0x7f9521406be0
	34	[46]	MOVE     	0 1
	35	[46]	SETTABLE 	9 -14 10	; "checked_func" -
	36	[47]	CLOSURE  	10 3	; 0x7f9521407830
	37	[47]	MOVE     	0 1
	38	[47]	SETTABLE 	9 -15 10	; "callback" -
	39	[48]	NEWTABLE 	10 0 3
	40	[50]	MOVE     	11 2
	41	[50]	LOADK    	12 -16	; "Every page"
	42	[50]	CALL     	11 2 2
	43	[50]	SETTABLE 	10 -8 11	; "text" -
	44	[51]	CLOSURE  	11 4	; 0x7f9521406f40
	45	[51]	MOVE     	0 1
	46	[51]	SETTABLE 	10 -14 11	; "checked_func" -
	47	[52]	CLOSURE  	11 5	; 0x7f9521408790
	48	[52]	MOVE     	0 1
	49	[52]	SETTABLE 	10 -15 11	; "callback" -
	50	[53]	NEWTABLE 	11 0 3
	51	[55]	MOVE     	12 2
	52	[55]	LOADK    	13 -17	; "Every 6 pages"
	53	[55]	CALL     	12 2 2
	54	[55]	SETTABLE 	11 -8 12	; "text" -
	55	[56]	CLOSURE  	12 6	; 0x7f9521406d60
	56	[56]	MOVE     	0 1
	57	[56]	SETTABLE 	11 -14 12	; "checked_func" -
	58	[57]	CLOSURE  	12 7	; 0x7f9521408d90
	59	[57]	MOVE     	0 1
	60	[57]	SETTABLE 	11 -15 12	; "callback" -
	61	[58]	NEWTABLE 	12 0 4
	62	[62]	CLOSURE  	13 8	; 0x7f9521408f70
	63	[62]	MOVE     	0 4
	64	[62]	MOVE     	0 2
	65	[62]	MOVE     	0 5
	66	[62]	SETTABLE 	12 -18 13	; "text_func" -
	67	[63]	CLOSURE  	13 9	; 0x7f95214082b0
	68	[63]	MOVE     	0 1
	69	[63]	MOVE     	0 5
	70	[63]	SETTABLE 	12 -14 13	; "checked_func" -
	71	[64]	CLOSURE  	13 10	; 0x7f9521408550
	72	[64]	MOVE     	0 1
	73	[64]	MOVE     	0 5
	74	[64]	SETTABLE 	12 -15 13	; "callback" -
	75	[67]	CLOSURE  	13 11	; 0x7f95214088c0
	76	[67]	MOVE     	0 6
	77	[67]	SETTABLE 	12 -19 13	; "hold_callback" -
	78	[68]	NEWTABLE 	13 0 4
	79	[72]	CLOSURE  	14 12	; 0x7f9521408330
	80	[72]	MOVE     	0 4
	81	[72]	MOVE     	0 2
	82	[72]	MOVE     	0 5
	83	[72]	SETTABLE 	13 -18 14	; "text_func" -
	84	[73]	CLOSURE  	14 13	; 0x7f9521407e30
	85	[73]	MOVE     	0 1
	86	[73]	MOVE     	0 5
	87	[73]	SETTABLE 	13 -14 14	; "checked_func" -
	88	[74]	CLOSURE  	14 14	; 0x7f9521407eb0
	89	[74]	MOVE     	0 1
	90	[74]	MOVE     	0 5
	91	[74]	SETTABLE 	13 -15 14	; "callback" -
	92	[77]	CLOSURE  	14 15	; 0x7f9521409b60
	93	[77]	MOVE     	0 6
	94	[77]	SETTABLE 	13 -19 14	; "hold_callback" -
	95	[78]	NEWTABLE 	14 0 4
	96	[82]	CLOSURE  	15 16	; 0x7f9521409c30
	97	[82]	MOVE     	0 4
	98	[82]	MOVE     	0 2
	99	[82]	MOVE     	0 5
	100	[82]	SETTABLE 	14 -18 15	; "text_func" -
	101	[83]	CLOSURE  	15 17	; 0x7f9521409290
	102	[83]	MOVE     	0 1
	103	[83]	MOVE     	0 5
	104	[83]	SETTABLE 	14 -14 15	; "checked_func" -
	105	[84]	CLOSURE  	15 18	; 0x7f952140a370
	106	[84]	MOVE     	0 1
	107	[84]	MOVE     	0 5
	108	[84]	SETTABLE 	14 -15 15	; "callback" -
	109	[87]	CLOSURE  	15 19	; 0x7f952140a660
	110	[87]	MOVE     	0 6
	111	[87]	SETTABLE 	14 -19 15	; "hold_callback" -
	112	[88]	NEWTABLE 	15 0 3
	113	[90]	MOVE     	16 2
	114	[90]	LOADK    	17 -20	; "Every chapter"
	115	[90]	CALL     	16 2 2
	116	[90]	SETTABLE 	15 -8 16	; "text" -
	117	[91]	CLOSURE  	16 20	; 0x7f952140a7e0
	118	[91]	MOVE     	0 1
	119	[91]	SETTABLE 	15 -14 16	; "checked_func" -
	120	[92]	CLOSURE  	16 21	; 0x7f9521504280
	121	[92]	MOVE     	0 1
	122	[92]	SETTABLE 	15 -15 16	; "callback" -
	123	[94]	SETLIST  	8 7 1	; 1
	124	[94]	SETTABLE 	7 -12 8	; "sub_item_table" -
	125	[95]	RETURN   	7 2
	126	[95]	RETURN   	0 1

function <./frontend/ui/elements/refresh_menu_table.lua:7,17> (18 instructions, 72 bytes at 0x7f9521407000)
1 param, 5 slots, 0 upvalues, 2 locals, 7 constants, 0 functions
	1	[9]	EQ       	0 0 -1	; - "refresh_rate_1"
	2	[9]	JMP      	2	; to 5
	3	[10]	LOADK    	1 -2	; 12
	4	[10]	JMP      	5	; to 10
	5	[11]	EQ       	0 0 -3	; - "refresh_rate_2"
	6	[11]	JMP      	2	; to 9
	7	[12]	LOADK    	1 -4	; 22
	8	[12]	JMP      	1	; to 10
	9	[14]	LOADK    	1 -5	; 99
	10	[16]	GETGLOBAL	2 -6	; G_reader_settings
	11	[16]	SELF     	2 2 -7	; "readSetting"
	12	[16]	MOVE     	4 0
	13	[16]	CALL     	2 3 2
	14	[16]	TEST     	2 0 1
	15	[16]	JMP      	1	; to 17
	16	[16]	MOVE     	2 1
	17	[16]	RETURN   	2 2
	18	[17]	RETURN   	0 1

function <./frontend/ui/elements/refresh_menu_table.lua:19,37> (37 instructions, 148 bytes at 0x7f9521407430)
2 params, 8 slots, 4 upvalues, 4 locals, 21 constants, 1 function
	1	[20]	GETGLOBAL	2 -1	; require
	2	[20]	LOADK    	3 -2	; "ui/widget/spinwidget"
	3	[20]	CALL     	2 2 2
	4	[21]	SELF     	3 2 -3	; "new"
	5	[21]	NEWTABLE 	5 0 9
	6	[22]	GETUPVAL 	6 0	; Screen
	7	[22]	SELF     	6 6 -5	; "getWidth"
	8	[22]	CALL     	6 2 2
	9	[22]	MUL      	6 6 -6	; - 0.6
	10	[22]	SETTABLE 	5 -4 6	; "width" -
	11	[23]	GETUPVAL 	6 1	; custom
	12	[23]	MOVE     	7 1
	13	[23]	CALL     	6 2 2
	14	[23]	SETTABLE 	5 -7 6	; "value" -
	15	[24]	SETTABLE 	5 -8 -9	; "value_min" 0
	16	[25]	SETTABLE 	5 -10 -11	; "value_max" 200
	17	[26]	SETTABLE 	5 -12 -13	; "value_step" 1
	18	[27]	SETTABLE 	5 -14 -15	; "value_hold_step" 10
	19	[28]	GETUPVAL 	6 2	; _
	20	[28]	LOADK    	7 -17	; "Set refresh"
	21	[28]	CALL     	6 2 2
	22	[28]	SETTABLE 	5 -16 6	; "ok_text" -
	23	[29]	GETUPVAL 	6 2	; _
	24	[29]	LOADK    	7 -19	; "Set custom refresh rate"
	25	[29]	CALL     	6 2 2
	26	[29]	SETTABLE 	5 -18 6	; "title_text" -
	27	[34]	CLOSURE  	6 0	; 0x7f9521407710
	28	[34]	MOVE     	0 1
	29	[34]	GETUPVAL 	0 3	; UIManager
	30	[34]	MOVE     	0 0
	31	[34]	SETTABLE 	5 -20 6	; "callback" -
	32	[21]	CALL     	3 3 2
	33	[36]	GETUPVAL 	4 3	; UIManager
	34	[36]	SELF     	4 4 -21	; "show"
	35	[36]	MOVE     	6 3
	36	[36]	CALL     	4 3 1
	37	[37]	RETURN   	0 1

function <./frontend/ui/elements/refresh_menu_table.lua:30,34> (13 instructions, 52 bytes at 0x7f9521407710)
1 param, 5 slots, 3 upvalues, 1 local, 5 constants, 0 functions
	1	[31]	GETGLOBAL	1 -1	; G_reader_settings
	2	[31]	SELF     	1 1 -2	; "saveSetting"
	3	[31]	GETUPVAL 	3 0	; refresh_rate_num
	4	[31]	GETTABLE 	4 0 -3	; "value"
	5	[31]	CALL     	1 4 1
	6	[32]	GETUPVAL 	1 1	; UIManager
	7	[32]	SELF     	1 1 -4	; "setRefreshRate"
	8	[32]	GETTABLE 	3 0 -3	; "value"
	9	[32]	CALL     	1 3 1
	10	[33]	GETUPVAL 	1 2	; touchmenu_instance
	11	[33]	SELF     	1 1 -5	; "updateItems"
	12	[33]	CALL     	1 2 1
	13	[34]	RETURN   	0 1

function <./frontend/ui/elements/refresh_menu_table.lua:46,46> (9 instructions, 36 bytes at 0x7f9521406be0)
0 params, 2 slots, 1 upvalue, 0 locals, 2 constants, 0 functions
	1	[46]	GETUPVAL 	0 0	; UIManager
	2	[46]	SELF     	0 0 -1	; "getRefreshRate"
	3	[46]	CALL     	0 2 2
	4	[46]	EQ       	1 0 -2	; - 0
	5	[46]	JMP      	1	; to 7
	6	[46]	LOADBOOL 	0 0 1
	7	[46]	LOADBOOL 	0 1 0
	8	[46]	RETURN   	0 2
	9	[46]	RETURN   	0 1

function <./frontend/ui/elements/refresh_menu_table.lua:47,47> (5 instructions, 20 bytes at 0x7f9521407830)
0 params, 3 slots, 1 upvalue, 0 locals, 2 constants, 0 functions
	1	[47]	GETUPVAL 	0 0	; UIManager
	2	[47]	SELF     	0 0 -1	; "setRefreshRate"
	3	[47]	LOADK    	2 -2	; 0
	4	[47]	CALL     	0 3 1
	5	[47]	RETURN   	0 1

function <./frontend/ui/elements/refresh_menu_table.lua:51,51> (9 instructions, 36 bytes at 0x7f9521406f40)
0 params, 2 slots, 1 upvalue, 0 locals, 2 constants, 0 functions
	1	[51]	GETUPVAL 	0 0	; UIManager
	2	[51]	SELF     	0 0 -1	; "getRefreshRate"
	3	[51]	CALL     	0 2 2
	4	[51]	EQ       	1 0 -2	; - 1
	5	[51]	JMP      	1	; to 7
	6	[51]	LOADBOOL 	0 0 1
	7	[51]	LOADBOOL 	0 1 0
	8	[51]	RETURN   	0 2
	9	[51]	RETURN   	0 1

function <./frontend/ui/elements/refresh_menu_table.lua:52,52> (5 instructions, 20 bytes at 0x7f9521408790)
0 params, 3 slots, 1 upvalue, 0 locals, 2 constants, 0 functions
	1	[52]	GETUPVAL 	0 0	; UIManager
	2	[52]	SELF     	0 0 -1	; "setRefreshRate"
	3	[52]	LOADK    	2 -2	; 1
	4	[52]	CALL     	0 3 1
	5	[52]	RETURN   	0 1

function <./frontend/ui/elements/refresh_menu_table.lua:56,56> (9 instructions, 36 bytes at 0x7f9521406d60)
0 params, 2 slots, 1 upvalue, 0 locals, 2 constants, 0 functions
	1	[56]	GETUPVAL 	0 0	; UIManager
	2	[56]	SELF     	0 0 -1	; "getRefreshRate"
	3	[56]	CALL     	0 2 2
	4	[56]	EQ       	1 0 -2	; - 6
	5	[56]	JMP      	1	; to 7
	6	[56]	LOADBOOL 	0 0 1
	7	[56]	LOADBOOL 	0 1 0
	8	[56]	RETURN   	0 2
	9	[56]	RETURN   	0 1

function <./frontend/ui/elements/refresh_menu_table.lua:57,57> (5 instructions, 20 bytes at 0x7f9521408d90)
0 params, 3 slots, 1 upvalue, 0 locals, 2 constants, 0 functions
	1	[57]	GETUPVAL 	0 0	; UIManager
	2	[57]	SELF     	0 0 -1	; "setRefreshRate"
	3	[57]	LOADK    	2 -2	; 6
	4	[57]	CALL     	0 3 1
	5	[57]	RETURN   	0 1

function <./frontend/ui/elements/refresh_menu_table.lua:60,62> (10 instructions, 40 bytes at 0x7f9521408f70)
0 params, 4 slots, 3 upvalues, 0 locals, 2 constants, 0 functions
	1	[61]	GETUPVAL 	0 0	; T
	2	[61]	GETUPVAL 	1 1	; _
	3	[61]	LOADK    	2 -1	; "Custom 1: %1 pages"
	4	[61]	CALL     	1 2 2
	5	[61]	GETUPVAL 	2 2	; custom
	6	[61]	LOADK    	3 -2	; "refresh_rate_1"
	7	[61]	CALL     	2 2 0
	8	[61]	TAILCALL 	0 0 0
	9	[61]	RETURN   	0 0
	10	[62]	RETURN   	0 1

function <./frontend/ui/elements/refresh_menu_table.lua:63,63> (12 instructions, 48 bytes at 0x7f95214082b0)
0 params, 3 slots, 2 upvalues, 0 locals, 2 constants, 0 functions
	1	[63]	GETUPVAL 	0 0	; UIManager
	2	[63]	SELF     	0 0 -1	; "getRefreshRate"
	3	[63]	CALL     	0 2 2
	4	[63]	GETUPVAL 	1 1	; custom
	5	[63]	LOADK    	2 -2	; "refresh_rate_1"
	6	[63]	CALL     	1 2 2
	7	[63]	EQ       	1 0 1
	8	[63]	JMP      	1	; to 10
	9	[63]	LOADBOOL 	0 0 1
	10	[63]	LOADBOOL 	0 1 0
	11	[63]	RETURN   	0 2
	12	[63]	RETURN   	0 1

function <./frontend/ui/elements/refresh_menu_table.lua:64,64> (7 instructions, 28 bytes at 0x7f9521408550)
0 params, 4 slots, 2 upvalues, 0 locals, 2 constants, 0 functions
	1	[64]	GETUPVAL 	0 0	; UIManager
	2	[64]	SELF     	0 0 -1	; "setRefreshRate"
	3	[64]	GETUPVAL 	2 1	; custom
	4	[64]	LOADK    	3 -2	; "refresh_rate_1"
	5	[64]	CALL     	2 2 0
	6	[64]	CALL     	0 0 1
	7	[64]	RETURN   	0 1

function <./frontend/ui/elements/refresh_menu_table.lua:65,67> (5 instructions, 20 bytes at 0x7f95214088c0)
1 param, 4 slots, 1 upvalue, 1 local, 1 constant, 0 functions
	1	[66]	GETUPVAL 	1 0	; spinWidgetSetRefresh
	2	[66]	MOVE     	2 0
	3	[66]	LOADK    	3 -1	; "refresh_rate_1"
	4	[66]	CALL     	1 3 1
	5	[67]	RETURN   	0 1

function <./frontend/ui/elements/refresh_menu_table.lua:70,72> (10 instructions, 40 bytes at 0x7f9521408330)
0 params, 4 slots, 3 upvalues, 0 locals, 2 constants, 0 functions
	1	[71]	GETUPVAL 	0 0	; T
	2	[71]	GETUPVAL 	1 1	; _
	3	[71]	LOADK    	2 -1	; "Custom 2: %1 pages"
	4	[71]	CALL     	1 2 2
	5	[71]	GETUPVAL 	2 2	; custom
	6	[71]	LOADK    	3 -2	; "refresh_rate_2"
	7	[71]	CALL     	2 2 0
	8	[71]	TAILCALL 	0 0 0
	9	[71]	RETURN   	0 0
	10	[72]	RETURN   	0 1

function <./frontend/ui/elements/refresh_menu_table.lua:73,73> (12 instructions, 48 bytes at 0x7f9521407e30)
0 params, 3 slots, 2 upvalues, 0 locals, 2 constants, 0 functions
	1	[73]	GETUPVAL 	0 0	; UIManager
	2	[73]	SELF     	0 0 -1	; "getRefreshRate"
	3	[73]	CALL     	0 2 2
	4	[73]	GETUPVAL 	1 1	; custom
	5	[73]	LOADK    	2 -2	; "refresh_rate_2"
	6	[73]	CALL     	1 2 2
	7	[73]	EQ       	1 0 1
	8	[73]	JMP      	1	; to 10
	9	[73]	LOADBOOL 	0 0 1
	10	[73]	LOADBOOL 	0 1 0
	11	[73]	RETURN   	0 2
	12	[73]	RETURN   	0 1

function <./frontend/ui/elements/refresh_menu_table.lua:74,74> (7 instructions, 28 bytes at 0x7f9521407eb0)
0 params, 4 slots, 2 upvalues, 0 locals, 2 constants, 0 functions
	1	[74]	GETUPVAL 	0 0	; UIManager
	2	[74]	SELF     	0 0 -1	; "setRefreshRate"
	3	[74]	GETUPVAL 	2 1	; custom
	4	[74]	LOADK    	3 -2	; "refresh_rate_2"
	5	[74]	CALL     	2 2 0
	6	[74]	CALL     	0 0 1
	7	[74]	RETURN   	0 1

function <./frontend/ui/elements/refresh_menu_table.lua:75,77> (5 instructions, 20 bytes at 0x7f9521409b60)
1 param, 4 slots, 1 upvalue, 1 local, 1 constant, 0 functions
	1	[76]	GETUPVAL 	1 0	; spinWidgetSetRefresh
	2	[76]	MOVE     	2 0
	3	[76]	LOADK    	3 -1	; "refresh_rate_2"
	4	[76]	CALL     	1 3 1
	5	[77]	RETURN   	0 1

function <./frontend/ui/elements/refresh_menu_table.lua:80,82> (10 instructions, 40 bytes at 0x7f9521409c30)
0 params, 4 slots, 3 upvalues, 0 locals, 2 constants, 0 functions
	1	[81]	GETUPVAL 	0 0	; T
	2	[81]	GETUPVAL 	1 1	; _
	3	[81]	LOADK    	2 -1	; "Custom 3: %1 pages"
	4	[81]	CALL     	1 2 2
	5	[81]	GETUPVAL 	2 2	; custom
	6	[81]	LOADK    	3 -2	; "refresh_rate_3"
	7	[81]	CALL     	2 2 0
	8	[81]	TAILCALL 	0 0 0
	9	[81]	RETURN   	0 0
	10	[82]	RETURN   	0 1

function <./frontend/ui/elements/refresh_menu_table.lua:83,83> (12 instructions, 48 bytes at 0x7f9521409290)
0 params, 3 slots, 2 upvalues, 0 locals, 2 constants, 0 functions
	1	[83]	GETUPVAL 	0 0	; UIManager
	2	[83]	SELF     	0 0 -1	; "getRefreshRate"
	3	[83]	CALL     	0 2 2
	4	[83]	GETUPVAL 	1 1	; custom
	5	[83]	LOADK    	2 -2	; "refresh_rate_3"
	6	[83]	CALL     	1 2 2
	7	[83]	EQ       	1 0 1
	8	[83]	JMP      	1	; to 10
	9	[83]	LOADBOOL 	0 0 1
	10	[83]	LOADBOOL 	0 1 0
	11	[83]	RETURN   	0 2
	12	[83]	RETURN   	0 1

function <./frontend/ui/elements/refresh_menu_table.lua:84,84> (7 instructions, 28 bytes at 0x7f952140a370)
0 params, 4 slots, 2 upvalues, 0 locals, 2 constants, 0 functions
	1	[84]	GETUPVAL 	0 0	; UIManager
	2	[84]	SELF     	0 0 -1	; "setRefreshRate"
	3	[84]	GETUPVAL 	2 1	; custom
	4	[84]	LOADK    	3 -2	; "refresh_rate_3"
	5	[84]	CALL     	2 2 0
	6	[84]	CALL     	0 0 1
	7	[84]	RETURN   	0 1

function <./frontend/ui/elements/refresh_menu_table.lua:85,87> (5 instructions, 20 bytes at 0x7f952140a660)
1 param, 4 slots, 1 upvalue, 1 local, 1 constant, 0 functions
	1	[86]	GETUPVAL 	1 0	; spinWidgetSetRefresh
	2	[86]	MOVE     	2 0
	3	[86]	LOADK    	3 -1	; "refresh_rate_3"
	4	[86]	CALL     	1 3 1
	5	[87]	RETURN   	0 1

function <./frontend/ui/elements/refresh_menu_table.lua:91,91> (9 instructions, 36 bytes at 0x7f952140a7e0)
0 params, 2 slots, 1 upvalue, 0 locals, 2 constants, 0 functions
	1	[91]	GETUPVAL 	0 0	; UIManager
	2	[91]	SELF     	0 0 -1	; "getRefreshRate"
	3	[91]	CALL     	0 2 2
	4	[91]	EQ       	1 0 -2	; - -1
	5	[91]	JMP      	1	; to 7
	6	[91]	LOADBOOL 	0 0 1
	7	[91]	LOADBOOL 	0 1 0
	8	[91]	RETURN   	0 2
	9	[91]	RETURN   	0 1

function <./frontend/ui/elements/refresh_menu_table.lua:92,92> (5 instructions, 20 bytes at 0x7f9521504280)
0 params, 3 slots, 1 upvalue, 0 locals, 2 constants, 0 functions
	1	[92]	GETUPVAL 	0 0	; UIManager
	2	[92]	SELF     	0 0 -1	; "setRefreshRate"
	3	[92]	LOADK    	2 -2	; -1
	4	[92]	CALL     	0 3 1
	5	[92]	RETURN   	0 1
