-- BYTECODE -- refresh_menu_table.lua:7-17
0001    KPRI     1   0
0002    ISNES    0   0      ; "refresh_rate_1"
0003    JMP      2 => 0006
0004    KSHORT   1  12
0005    JMP      2 => 0011
0006 => ISNES    0   1      ; "refresh_rate_2"
0007    JMP      2 => 0010
0008    KSHORT   1  22
0009    JMP      2 => 0011
0010 => KSHORT   1  99
0011 => GGET     2   2      ; "G_reader_settings"
0012    MOV      3   2
0013    TGETS    2   2   3  ; "readSetting"
0014    MOV      4   0
0015    CALL     2   2   3
0016    IST          2
0017    JMP      3 => 0019
0018    MOV      2   1
0019 => RET1     2   2

-- BYTECODE -- refresh_menu_table.lua:30-34
0001    GGET     1   0      ; "G_reader_settings"
0002    MOV      2   1
0003    TGETS    1   1   1  ; "saveSetting"
0004    UGET     3   0      ; refresh_rate_num
0005    TGETS    4   0   2  ; "value"
0006    CALL     1   1   4
0007    UGET     1   1      ; UIManager
0008    MOV      2   1
0009    TGETS    1   1   3  ; "setRefreshRate"
0010    TGETS    3   0   2  ; "value"
0011    CALL     1   1   3
0012    UGET     1   2      ; touchmenu_instance
0013    MOV      2   1
0014    TGETS    1   1   4  ; "updateItems"
0015    CALL     1   1   2
0016    RET0     0   1

-- BYTECODE -- refresh_menu_table.lua:19-37
0001    GGET     2   0      ; "require"
0002    KSTR     3   1      ; "ui/widget/spinwidget"
0003    CALL     2   2   2
0004    MOV      4   2
0005    TGETS    3   2   2  ; "new"
0006    TDUP     5   4
0007    UGET     6   0      ; Screen
0008    MOV      7   6
0009    TGETS    6   6   3  ; "getWidth"
0010    CALL     6   2   2
0011    MULVN    6   6   0  ; 0.6
0012    TSETS    6   5   5  ; "width"
0013    UGET     6   1      ; custom
0014    MOV      7   1
0015    CALL     6   2   2
0016    TSETS    6   5   6  ; "value"
0017    UGET     6   2      ; _
0018    KSTR     7   7      ; "Set refresh"
0019    CALL     6   2   2
0020    TSETS    6   5   8  ; "ok_text"
0021    UGET     6   2      ; _
0022    KSTR     7   9      ; "Set custom refresh rate"
0023    CALL     6   2   2
0024    TSETS    6   5  10  ; "title_text"
0025    FNEW     6  11      ; refresh_menu_table.lua:30
0026    TSETS    6   5  12  ; "callback"
0027    CALL     3   2   3
0028    UGET     4   3      ; UIManager
0029    MOV      5   4
0030    TGETS    4   4  13  ; "show"
0031    MOV      6   3
0032    CALL     4   1   3
0033    UCLO     0 => 0034
0034 => RET0     0   1

-- BYTECODE -- refresh_menu_table.lua:46-46
0001    UGET     0   0      ; UIManager
0002    MOV      1   0
0003    TGETS    0   0   0  ; "getRefreshRate"
0004    CALL     0   2   2
0005    ISEQN    0   0      ; 0
0006    JMP      0 => 0009
0007    KPRI     0   1
0008    JMP      1 => 0010
0009 => KPRI     0   2
0010 => RET1     0   2

-- BYTECODE -- refresh_menu_table.lua:47-47
0001    UGET     0   0      ; UIManager
0002    MOV      1   0
0003    TGETS    0   0   0  ; "setRefreshRate"
0004    KSHORT   2   0
0005    CALL     0   1   3
0006    RET0     0   1

-- BYTECODE -- refresh_menu_table.lua:51-51
0001    UGET     0   0      ; UIManager
0002    MOV      1   0
0003    TGETS    0   0   0  ; "getRefreshRate"
0004    CALL     0   2   2
0005    ISEQN    0   0      ; 1
0006    JMP      0 => 0009
0007    KPRI     0   1
0008    JMP      1 => 0010
0009 => KPRI     0   2
0010 => RET1     0   2

-- BYTECODE -- refresh_menu_table.lua:52-52
0001    UGET     0   0      ; UIManager
0002    MOV      1   0
0003    TGETS    0   0   0  ; "setRefreshRate"
0004    KSHORT   2   1
0005    CALL     0   1   3
0006    RET0     0   1

-- BYTECODE -- refresh_menu_table.lua:56-56
0001    UGET     0   0      ; UIManager
0002    MOV      1   0
0003    TGETS    0   0   0  ; "getRefreshRate"
0004    CALL     0   2   2
0005    ISEQN    0   0      ; 6
0006    JMP      0 => 0009
0007    KPRI     0   1
0008    JMP      1 => 0010
0009 => KPRI     0   2
0010 => RET1     0   2

-- BYTECODE -- refresh_menu_table.lua:57-57
0001    UGET     0   0      ; UIManager
0002    MOV      1   0
0003    TGETS    0   0   0  ; "setRefreshRate"
0004    KSHORT   2   6
0005    CALL     0   1   3
0006    RET0     0   1

-- BYTECODE -- refresh_menu_table.lua:60-62
0001    UGET     0   0      ; T
0002    UGET     1   1      ; _
0003    KSTR     2   0      ; "Custom 1: %1 pages"
0004    CALL     1   2   2
0005    UGET     2   2      ; custom
0006    KSTR     3   1      ; "refresh_rate_1"
0007    CALL     2   0   2
0008    CALLMT   0   1

-- BYTECODE -- refresh_menu_table.lua:63-63
0001    UGET     0   0      ; UIManager
0002    MOV      1   0
0003    TGETS    0   0   0  ; "getRefreshRate"
0004    CALL     0   2   2
0005    UGET     1   1      ; custom
0006    KSTR     2   1      ; "refresh_rate_1"
0007    CALL     1   2   2
0008    ISEQV    0   1
0009    JMP      0 => 0012
0010    KPRI     0   1
0011    JMP      1 => 0013
0012 => KPRI     0   2
0013 => RET1     0   2

-- BYTECODE -- refresh_menu_table.lua:64-64
0001    UGET     0   0      ; UIManager
0002    MOV      1   0
0003    TGETS    0   0   0  ; "setRefreshRate"
0004    UGET     2   1      ; custom
0005    KSTR     3   1      ; "refresh_rate_1"
0006    CALL     2   0   2
0007    CALLM    0   1   1
0008    RET0     0   1

-- BYTECODE -- refresh_menu_table.lua:65-67
0001    UGET     1   0      ; spinWidgetSetRefresh
0002    MOV      2   0
0003    KSTR     3   0      ; "refresh_rate_1"
0004    CALL     1   1   3
0005    RET0     0   1

-- BYTECODE -- refresh_menu_table.lua:70-72
0001    UGET     0   0      ; T
0002    UGET     1   1      ; _
0003    KSTR     2   0      ; "Custom 2: %1 pages"
0004    CALL     1   2   2
0005    UGET     2   2      ; custom
0006    KSTR     3   1      ; "refresh_rate_2"
0007    CALL     2   0   2
0008    CALLMT   0   1

-- BYTECODE -- refresh_menu_table.lua:73-73
0001    UGET     0   0      ; UIManager
0002    MOV      1   0
0003    TGETS    0   0   0  ; "getRefreshRate"
0004    CALL     0   2   2
0005    UGET     1   1      ; custom
0006    KSTR     2   1      ; "refresh_rate_2"
0007    CALL     1   2   2
0008    ISEQV    0   1
0009    JMP      0 => 0012
0010    KPRI     0   1
0011    JMP      1 => 0013
0012 => KPRI     0   2
0013 => RET1     0   2

-- BYTECODE -- refresh_menu_table.lua:74-74
0001    UGET     0   0      ; UIManager
0002    MOV      1   0
0003    TGETS    0   0   0  ; "setRefreshRate"
0004    UGET     2   1      ; custom
0005    KSTR     3   1      ; "refresh_rate_2"
0006    CALL     2   0   2
0007    CALLM    0   1   1
0008    RET0     0   1

-- BYTECODE -- refresh_menu_table.lua:75-77
0001    UGET     1   0      ; spinWidgetSetRefresh
0002    MOV      2   0
0003    KSTR     3   0      ; "refresh_rate_2"
0004    CALL     1   1   3
0005    RET0     0   1

-- BYTECODE -- refresh_menu_table.lua:80-82
0001    UGET     0   0      ; T
0002    UGET     1   1      ; _
0003    KSTR     2   0      ; "Custom 3: %1 pages"
0004    CALL     1   2   2
0005    UGET     2   2      ; custom
0006    KSTR     3   1      ; "refresh_rate_3"
0007    CALL     2   0   2
0008    CALLMT   0   1

-- BYTECODE -- refresh_menu_table.lua:83-83
0001    UGET     0   0      ; UIManager
0002    MOV      1   0
0003    TGETS    0   0   0  ; "getRefreshRate"
0004    CALL     0   2   2
0005    UGET     1   1      ; custom
0006    KSTR     2   1      ; "refresh_rate_3"
0007    CALL     1   2   2
0008    ISEQV    0   1
0009    JMP      0 => 0012
0010    KPRI     0   1
0011    JMP      1 => 0013
0012 => KPRI     0   2
0013 => RET1     0   2

-- BYTECODE -- refresh_menu_table.lua:84-84
0001    UGET     0   0      ; UIManager
0002    MOV      1   0
0003    TGETS    0   0   0  ; "setRefreshRate"
0004    UGET     2   1      ; custom
0005    KSTR     3   1      ; "refresh_rate_3"
0006    CALL     2   0   2
0007    CALLM    0   1   1
0008    RET0     0   1

-- BYTECODE -- refresh_menu_table.lua:85-87
0001    UGET     1   0      ; spinWidgetSetRefresh
0002    MOV      2   0
0003    KSTR     3   0      ; "refresh_rate_3"
0004    CALL     1   1   3
0005    RET0     0   1

-- BYTECODE -- refresh_menu_table.lua:91-91
0001    UGET     0   0      ; UIManager
0002    MOV      1   0
0003    TGETS    0   0   0  ; "getRefreshRate"
0004    CALL     0   2   2
0005    ISEQN    0   0      ; -1
0006    JMP      0 => 0009
0007    KPRI     0   1
0008    JMP      1 => 0010
0009 => KPRI     0   2
0010 => RET1     0   2

-- BYTECODE -- refresh_menu_table.lua:92-92
0001    UGET     0   0      ; UIManager
0002    MOV      1   0
0003    TGETS    0   0   0  ; "setRefreshRate"
0004    KSHORT   2  -1
0005    CALL     0   1   3
0006    RET0     0   1

-- BYTECODE -- refresh_menu_table.lua:0-96
0001    GGET     0   0      ; "require"
0002    KSTR     1   1      ; "device"
0003    CALL     0   2   2
0004    GGET     1   0      ; "require"
0005    KSTR     2   2      ; "ui/uimanager"
0006    CALL     1   2   2
0007    GGET     2   0      ; "require"
0008    KSTR     3   3      ; "gettext"
0009    CALL     2   2   2
0010    TGETS    3   0   4  ; "screen"
0011    GGET     4   0      ; "require"
0012    KSTR     5   5      ; "ffi/util"
0013    CALL     4   2   2
0014    TGETS    4   4   6  ; "template"
0015    FNEW     5   7      ; refresh_menu_table.lua:7
0016    FNEW     6   8      ; refresh_menu_table.lua:19
0017    TDUP     7  10
0018    MOV      8   2
0019    KSTR     9   9      ; "Full refresh rate"
0020    CALL     8   2   2
0021    TSETS    8   7  11  ; "text"
0022    TNEW     8   8
0023    TDUP     9  13
0024    MOV     10   2
0025    KSTR    11  12      ; "Never"
0026    CALL    10   2   2
0027    TSETS   10   9  11  ; "text"
0028    FNEW    10  14      ; refresh_menu_table.lua:46
0029    TSETS   10   9  15  ; "checked_func"
0030    FNEW    10  16      ; refresh_menu_table.lua:47
0031    TSETS   10   9  17  ; "callback"
0032    TSETB    9   8   1
0033    TDUP     9  19
0034    MOV     10   2
0035    KSTR    11  18      ; "Every page"
0036    CALL    10   2   2
0037    TSETS   10   9  11  ; "text"
0038    FNEW    10  20      ; refresh_menu_table.lua:51
0039    TSETS   10   9  15  ; "checked_func"
0040    FNEW    10  21      ; refresh_menu_table.lua:52
0041    TSETS   10   9  17  ; "callback"
0042    TSETB    9   8   2
0043    TDUP     9  23
0044    MOV     10   2
0045    KSTR    11  22      ; "Every 6 pages"
0046    CALL    10   2   2
0047    TSETS   10   9  11  ; "text"
0048    FNEW    10  24      ; refresh_menu_table.lua:56
0049    TSETS   10   9  15  ; "checked_func"
0050    FNEW    10  25      ; refresh_menu_table.lua:57
0051    TSETS   10   9  17  ; "callback"
0052    TSETB    9   8   3
0053    TDUP     9  27
0054    FNEW    10  26      ; refresh_menu_table.lua:60
0055    TSETS   10   9  28  ; "text_func"
0056    FNEW    10  29      ; refresh_menu_table.lua:63
0057    TSETS   10   9  15  ; "checked_func"
0058    FNEW    10  30      ; refresh_menu_table.lua:64
0059    TSETS   10   9  17  ; "callback"
0060    FNEW    10  31      ; refresh_menu_table.lua:65
0061    TSETS   10   9  32  ; "hold_callback"
0062    TSETB    9   8   4
0063    TDUP     9  34
0064    FNEW    10  33      ; refresh_menu_table.lua:70
0065    TSETS   10   9  28  ; "text_func"
0066    FNEW    10  35      ; refresh_menu_table.lua:73
0067    TSETS   10   9  15  ; "checked_func"
0068    FNEW    10  36      ; refresh_menu_table.lua:74
0069    TSETS   10   9  17  ; "callback"
0070    FNEW    10  37      ; refresh_menu_table.lua:75
0071    TSETS   10   9  32  ; "hold_callback"
0072    TSETB    9   8   5
0073    TDUP     9  39
0074    FNEW    10  38      ; refresh_menu_table.lua:80
0075    TSETS   10   9  28  ; "text_func"
0076    FNEW    10  40      ; refresh_menu_table.lua:83
0077    TSETS   10   9  15  ; "checked_func"
0078    FNEW    10  41      ; refresh_menu_table.lua:84
0079    TSETS   10   9  17  ; "callback"
0080    FNEW    10  42      ; refresh_menu_table.lua:85
0081    TSETS   10   9  32  ; "hold_callback"
0082    TSETB    9   8   6
0083    TDUP     9  44
0084    MOV     10   2
0085    KSTR    11  43      ; "Every chapter"
0086    CALL    10   2   2
0087    TSETS   10   9  11  ; "text"
0088    FNEW    10  45      ; refresh_menu_table.lua:91
0089    TSETS   10   9  15  ; "checked_func"
0090    FNEW    10  46      ; refresh_menu_table.lua:92
0091    TSETS   10   9  17  ; "callback"
0092    TSETB    9   8   7
0093    TSETS    8   7  47  ; "sub_item_table"
0094    UCLO     0 => 0095
0095 => RET1     7   2

