-- BYTECODE -- rendertext.lua:36-76
0001    GGET     2   0      ; "string"
0002    TGETS    2   2   1  ; "len"
0003    MOV      3   0
0004    CALL     2   2   2
0005    ISGE     2   1
0006    JMP      2 => 0009
0007    KPRI     2   0
0008    RET1     2   2
0009 => GGET     2   0      ; "string"
0010    TGETS    2   2   2  ; "byte"
0011    MOV      3   0
0012    MOV      4   1
0013    CALL     2   2   3
0014    UGET     3   0      ; band
0015    MOV      4   2
0016    KSHORT   5 128
0017    CALL     3   2   3
0018    ISNEN    3   0      ; 0
0019    JMP      3 => 0030
0020    ADDVN    3   1   1  ; 1
0021    MOV      4   2
0022    GGET     5   0      ; "string"
0023    TGETS    5   5   3  ; "sub"
0024    MOV      6   0
0025    MOV      7   1
0026    MOV      8   1
0027    CALL     5   0   4
0028    RETM     3   2
0029    JMP      3 => 0145
0030 => UGET     3   0      ; band
0031    MOV      4   2
0032    KSHORT   5 192
0033    CALL     3   2   3
0034    ISEQN    3   2      ; 128
0035    JMP      3 => 0042
0036    UGET     3   0      ; band
0037    MOV      4   2
0038    KSHORT   5 248
0039    CALL     3   2   3
0040    ISNEN    3   3      ; 248
0041    JMP      3 => 0047
0042 => ADDVN    3   1   1  ; 1
0043    KNUM     4   4      ; 65533
0044    KSTR     5   4      ; "ÿý"
0045    RET      3   4
0046    JMP      3 => 0145
0047 => KNIL     3   4
0048    UGET     5   0      ; band
0049    MOV      6   2
0050    KSHORT   7 224
0051    CALL     5   2   3
0052    ISNEN    5   5      ; 192
0053    JMP      5 => 0061
0054    UGET     5   0      ; band
0055    MOV      6   2
0056    KSHORT   7  31
0057    CALL     5   2   3
0058    MOV      3   5
0059    KSHORT   4   1
0060    JMP      5 => 0091
0061 => UGET     5   0      ; band
0062    MOV      6   2
0063    KSHORT   7 240
0064    CALL     5   2   3
0065    ISNEN    5   6      ; 224
0066    JMP      5 => 0074
0067    UGET     5   0      ; band
0068    MOV      6   2
0069    KSHORT   7  15
0070    CALL     5   2   3
0071    MOV      3   5
0072    KSHORT   4   2
0073    JMP      5 => 0091
0074 => UGET     5   0      ; band
0075    MOV      6   2
0076    KSHORT   7 248
0077    CALL     5   2   3
0078    ISNEN    5   7      ; 240
0079    JMP      5 => 0087
0080    UGET     5   0      ; band
0081    MOV      6   2
0082    KSHORT   7   7
0083    CALL     5   2   3
0084    MOV      3   5
0085    KSHORT   4   3
0086    JMP      5 => 0091
0087 => ADDVN    5   1   1  ; 1
0088    KNUM     6   4      ; 65533
0089    KSTR     7   4      ; "ÿý"
0090    RET      5   4
0091 => GGET     5   0      ; "string"
0092    TGETS    5   5   1  ; "len"
0093    MOV      6   0
0094    CALL     5   2   2
0095    ADDVV    6   1   4
0096    ISGE     5   6
0097    JMP      5 => 0102
0098    ADDVN    5   1   1  ; 1
0099    KNUM     6   4      ; 65533
0100    KSTR     7   4      ; "ÿý"
0101    RET      5   4
0102 => ADDVN    5   1   1  ; 1
0103    ADDVV    6   1   4
0104    KSHORT   7   1
0105    FORI     5 => 0135
0106 => GGET     9   0      ; "string"
0107    TGETS    9   9   2  ; "byte"
0108    MOV     10   0
0109    MOV     11   8
0110    CALL     9   2   3
0111    MOV      2   9
0112    UGET     9   0      ; band
0113    MOV     10   2
0114    KSHORT  11 192
0115    CALL     9   2   3
0116    ISNEN    9   2      ; 128
0117    JMP      9 => 0130
0118    UGET     9   1      ; bor
0119    UGET    10   2      ; lshift
0120    MOV     11   3
0121    KSHORT  12   6
0122    CALL    10   2   3
0123    UGET    11   0      ; band
0124    MOV     12   2
0125    KSHORT  13  63
0126    CALL    11   0   3
0127    CALLM    9   2   1
0128    MOV      3   9
0129    JMP      9 => 0134
0130 => ADDVN    9   1   1  ; 1
0131    KNUM    10   4      ; 65533
0132    KSTR    11   4      ; "ÿý"
0133    RET      9   4
0134 => FORL     5 => 0106
0135 => ADDVV    5   1   4
0136    ADDVN    5   5   1  ; 1
0137    MOV      6   3
0138    GGET     7   0      ; "string"
0139    TGETS    7   7   3  ; "sub"
0140    MOV      8   0
0141    MOV      9   1
0142    ADDVV   10   1   4
0143    CALL     7   0   4
0144    RETM     5   2
0145 => RET0     0   1

-- BYTECODE -- rendertext.lua:35-78
0001    FNEW     1   0      ; rendertext.lua:36
0002    MOV      2   1
0003    MOV      3   0
0004    KSHORT   4   1
0005    UCLO     0 => 0006
0006 => RET      2   4

-- BYTECODE -- rendertext.lua:86-119
0001    MOV      4   3
0002    TGETS    5   1   0  ; "is_real_bold"
0003    ISF          5
0004    JMP      6 => 0006
0005    KPRI     3   1
0006 => KSTR     5   1      ; "glyph|"
0007    TGETS    6   1   2  ; "hash"
0008    KSTR     7   3      ; "|"
0009    MOV      8   2
0010    KSTR     9   3      ; "|"
0011    ISF          3
0012    JMP     10 => 0015
0013    KSHORT  10   1
0014    JMP     11 => 0016
0015 => KSHORT  10   0
0016 => CAT      5   5  10
0017    UGET     6   0      ; GlyphCache
0018    MOV      7   6
0019    TGETS    6   6   4  ; "check"
0020    MOV      8   5
0021    CALL     6   2   3
0022    ISF          6
0023    JMP      7 => 0026
0024    TGETB    7   6   1
0025    RET1     7   2
0026 => TGETS    7   1   5  ; "ftface"
0027    MOV      8   7
0028    TGETS    7   7   6  ; "renderGlyph"
0029    MOV      9   2
0030    MOV     10   3
0031    CALL     7   2   4
0032    TGETS    8   1   5  ; "ftface"
0033    MOV      9   8
0034    TGETS    8   8   7  ; "checkGlyph"
0035    MOV     10   2
0036    CALL     8   2   3
0037    ISNEN    8   0      ; 0
0038    JMP      8 => 0069
0039    GGET     8   8      ; "pairs"
0040    UGET     9   1      ; Font
0041    TGETS    9   9   9  ; "fallbacks"
0042    CALL     8   4   2
0043    ISNEXT  11 => 0067
0044 => UGET    13   1      ; Font
0045    MOV     14  13
0046    TGETS   13  13  10  ; "getFace"
0047    MOV     15  12
0048    TGETS   16   1  11  ; "orig_size"
0049    CALL    13   2   4
0050    ISEQP   13   0
0051    JMP     14 => 0067
0052    TGETS   14  13   5  ; "ftface"
0053    MOV     15  14
0054    TGETS   14  14   7  ; "checkGlyph"
0055    MOV     16   2
0056    CALL    14   2   3
0057    ISEQN   14   0      ; 0
0058    JMP     14 => 0067
0059    TGETS   14  13   5  ; "ftface"
0060    MOV     15  14
0061    TGETS   14  14   6  ; "renderGlyph"
0062    MOV     16   2
0063    MOV     17   4
0064    CALL    14   2   4
0065    MOV      7  14
0066    JMP      8 => 0069
0067 => ITERN   11   3   3
0068    ITERL   11 => 0044
0069 => IST          7
0070    JMP      8 => 0079
0071    UGET     8   2      ; logger
0072    TGETS    8   8  12  ; "warn"
0073    KSTR     9  13      ; "error rendering glyph (charcode="
0074    MOV     10   2
0075    KSTR    11  14      ; ") for face"
0076    MOV     12   1
0077    CALL     8   1   5
0078    RET0     0   1
0079 => UGET     8   3      ; CacheItem
0080    MOV      9   8
0081    TGETS    8   8  15  ; "new"
0082    TNEW    10   3
0083    TSETB    7  10   1
0084    CALL     8   2   3
0085    MOV      6   8
0086    TGETB    8   6   1
0087    TGETS    8   8  17  ; "bb"
0088    MOV      9   8
0089    TGETS    8   8  18  ; "getWidth"
0090    CALL     8   2   2
0091    TGETB    9   6   1
0092    TGETS    9   9  17  ; "bb"
0093    MOV     10   9
0094    TGETS    9   9  19  ; "getHeight"
0095    CALL     9   2   2
0096    MULVV    8   8   9
0097    DIVVN    8   8   1  ; 2
0098    ADDVN    8   8   2  ; 32
0099    TSETS    8   6  16  ; "size"
0100    UGET     8   0      ; GlyphCache
0101    MOV      9   8
0102    TGETS    8   8  20  ; "insert"
0103    MOV     10   5
0104    MOV     11   6
0105    CALL     8   1   4
0106    RET1     7   2

-- BYTECODE -- rendertext.lua:131-152
0001    KSHORT   6   0
0002    KPRI     7   0
0003    TNEW     8   0
0004    UGET     9   0      ; utf8Chars
0005    MOV     10   1
0006    CALL     9   4   2
0007    JMP     12 => 0039
0008 => ISGE     6   3
0009    JMP     15 => 0039
0010    MOV     16   0
0011    TGETS   15   0   0  ; "getGlyph"
0012    MOV     17   2
0013    MOV     18  13
0014    MOV     19   5
0015    CALL    15   2   5
0016    ISF          4
0017    JMP     16 => 0027
0018    ISF          7
0019    JMP     16 => 0027
0020    TGETS   16   2   1  ; "ftface"
0021    MOV     17  16
0022    TGETS   16  16   2  ; "getKerning"
0023    MOV     18   7
0024    MOV     19  13
0025    CALL    16   2   4
0026    ADDVV    6   6  16
0027 => TGETS   16  15   3  ; "ax"
0028    ADDVV    6   6  16
0029    ISGT     6   3
0030    JMP     16 => 0041
0031    MOV      7  13
0032    GGET    16   4      ; "table"
0033    TGETS   16  16   5  ; "insert"
0034    MOV     17   8
0035    MOV     18  14
0036    CALL    16   1   3
0037    JMP     16 => 0039
0038    JMP      9 => 0041
0039 => ITERC   12   4   3
0040    ITERL   12 => 0008
0041 => GGET     9   4      ; "table"
0042    TGETS    9   9   6  ; "concat"
0043    MOV     10   8
0044    CALLT    9   2

-- BYTECODE -- rendertext.lua:166-199
0001    IST          4
0002    JMP      7 => 0009
0003    UGET     7   0      ; logger
0004    TGETS    7   7   0  ; "warn"
0005    KSTR     8   1      ; "sizeUtf8Text called without text"
0006    CALL     7   1   2
0007    TDUP     7   2
0008    RET1     7   2
0009 => KSHORT   7   0
0010    KSHORT   8   0
0011    KSHORT   9   0
0012    KSHORT  10   0
0013    UGET    11   1      ; utf8Chars
0014    MOV     12   4
0015    CALL    11   4   2
0016    JMP     14 => 0059
0017 => ISF          2
0018    JMP     17 => 0022
0019    SUBVV   17   2   1
0020    ISGE     7  17
0021    JMP     17 => 0059
0022 => MOV     18   0
0023    TGETS   17   0   3  ; "getGlyph"
0024    MOV     19   3
0025    MOV     20  15
0026    MOV     21   6
0027    CALL    17   2   5
0028    ISF          5
0029    JMP     18 => 0039
0030    ISEQN   10   0      ; 0
0031    JMP     18 => 0039
0032    TGETS   18   3   4  ; "ftface"
0033    MOV     19  18
0034    TGETS   18  18   5  ; "getKerning"
0035    MOV     20  10
0036    MOV     21  15
0037    CALL    18   2   4
0038    ADDVV    7   7  18
0039 => TGETS   18  17   6  ; "ax"
0040    ADDVV    7   7  18
0041    GGET    18   7      ; "math"
0042    TGETS   18  18   8  ; "max"
0043    MOV     19   8
0044    TGETS   20  17   9  ; "t"
0045    CALL    18   2   3
0046    MOV      8  18
0047    GGET    18   7      ; "math"
0048    TGETS   18  18   8  ; "max"
0049    MOV     19   9
0050    TGETS   20  17  10  ; "bb"
0051    MOV     21  20
0052    TGETS   20  20  11  ; "getHeight"
0053    CALL    20   2   2
0054    TGETS   21  17   9  ; "t"
0055    SUBVV   20  20  21
0056    CALL    18   2   3
0057    MOV      9  18
0058    MOV     10  15
0059 => ITERC   14   4   3
0060    ITERL   14 => 0017
0061    TDUP    11  12
0062    TSETS    7  11  13  ; "x"
0063    TSETS    8  11  14  ; "y_top"
0064    TSETS    9  11  15  ; "y_bottom"
0065    RET1    11   2

-- BYTECODE -- rendertext.lua:214-268
0001    IST          5
0002    JMP     11 => 0009
0003    UGET    11   0      ; logger
0004    TGETS   11  11   0  ; "warn"
0005    KSTR    12   1      ; "renderUtf8Text called without text"
0006    CALL    11   1   2
0007    KSHORT  11   0
0008    RET1    11   2
0009 => IST          8
0010    JMP     11 => 0013
0011    UGET    11   1      ; BlitBuffer
0012    TGETS    8  11   2  ; "COLOR_BLACK"
0013 => KSHORT  11   0
0014    KSHORT  12   0
0015    MOV     14   1
0016    TGETS   13   1   3  ; "getWidth"
0017    CALL    13   2   2
0018    SUBVV   13  13   2
0019    ISF          9
0020    JMP     14 => 0024
0021    ISGE     9  13
0022    JMP     14 => 0024
0023    MOV     13   9
0024 => KSHORT  14   0
0025    UGET    15   2      ; utf8Chars
0026    MOV     16   5
0027    CALL    15   4   2
0028    JMP     18 => 0079
0029 => ISGE    11  13
0030    JMP     21 => 0071
0031    MOV     22   0
0032    TGETS   21   0   4  ; "getGlyph"
0033    MOV     23   4
0034    MOV     24  19
0035    MOV     25   7
0036    CALL    21   2   5
0037    ISF          6
0038    JMP     22 => 0048
0039    ISEQN   12   0      ; 0
0040    JMP     22 => 0048
0041    TGETS   22   4   5  ; "ftface"
0042    MOV     23  22
0043    TGETS   22  22   6  ; "getKerning"
0044    MOV     24  12
0045    MOV     25  19
0046    CALL    22   2   4
0047    ADDVV   11  11  22
0048 => MOV     23   1
0049    TGETS   22   1   7  ; "colorblitFrom"
0050    TGETS   24  21   8  ; "bb"
0051    ADDVV   25   2  11
0052    TGETS   26  21   9  ; "l"
0053    ADDVV   25  25  26
0054    TGETS   26  21  10  ; "t"
0055    SUBVV   26   3  26
0056    KSHORT  27   0
0057    KSHORT  28   0
0058    TGETS   29  21   8  ; "bb"
0059    MOV     30  29
0060    TGETS   29  29   3  ; "getWidth"
0061    CALL    29   2   2
0062    TGETS   30  21   8  ; "bb"
0063    MOV     31  30
0064    TGETS   30  30  11  ; "getHeight"
0065    CALL    30   2   2
0066    MOV     31   8
0067    CALL    22   1  10
0068    TGETS   22  21  12  ; "ax"
0069    ADDVV   11  11  22
0070    MOV     12  19
0071 => ISF         10
0072    JMP     21 => 0079
0073    ADDVN   14  14   1  ; 1
0074    TGETV   21  10  14
0075    IST         21
0076    JMP     22 => 0078
0077    KSHORT  21   0
0078 => ADDVV   11  11  21
0079 => ITERC   18   4   3
0080    ITERL   18 => 0029
0081    RET1    11   2

-- BYTECODE -- rendertext.lua:272-274
0001    MOV      4   0
0002    TGETS    3   0   0  ; "sizeUtf8Text"
0003    KSHORT   5   0
0004    KPRI     6   1
0005    MOV      7   1
0006    UGET     8   0      ; ellipsis
0007    KPRI     9   1
0008    MOV     10   2
0009    CALL     3   2   8
0010    TGETS    3   3   1  ; "x"
0011    RET1     3   2

-- BYTECODE -- rendertext.lua:286-291
0001    MOV      7   0
0002    TGETS    6   0   0  ; "getEllipsisWidth"
0003    MOV      8   2
0004    MOV      9   5
0005    CALL     6   2   4
0006    SUBVV    7   3   6
0007    MOV      9   0
0008    TGETS    8   0   1  ; "getSubTextByWidth"
0009    MOV     10   1
0010    MOV     11   2
0011    MOV     12   7
0012    MOV     13   4
0013    MOV     14   5
0014    CALL     8   2   7
0015    MOV      9   8
0016    UGET    10   0      ; ellipsis
0017    CAT      9   9  10
0018    RET1     9   2

-- BYTECODE -- rendertext.lua:301-320
0001    TGETS    4   1   0  ; "is_real_bold"
0002    ISF          4
0003    JMP      5 => 0005
0004    KPRI     3   1
0005 => KSTR     4   1      ; "xglyph|"
0006    TGETS    5   1   2  ; "hash"
0007    KSTR     6   3      ; "|"
0008    MOV      7   2
0009    KSTR     8   3      ; "|"
0010    ISF          3
0011    JMP      9 => 0014
0012    KSHORT   9   1
0013    JMP     10 => 0015
0014 => KSHORT   9   0
0015 => CAT      4   4   9
0016    UGET     5   0      ; GlyphCache
0017    MOV      6   5
0018    TGETS    5   5   4  ; "check"
0019    MOV      7   4
0020    CALL     5   2   3
0021    ISF          5
0022    JMP      6 => 0025
0023    TGETB    6   5   1
0024    RET1     6   2
0025 => TGETS    6   1   5  ; "ftface"
0026    MOV      7   6
0027    TGETS    6   6   6  ; "renderGlyphByIndex"
0028    MOV      8   2
0029    ISFC     9   3
0030    JMP      9 => 0032
0031    TGETS    9   1   7  ; "embolden_half_strength"
0032 => CALL     6   2   4
0033    IST          6
0034    JMP      7 => 0043
0035    UGET     7   1      ; logger
0036    TGETS    7   7   8  ; "warn"
0037    KSTR     8   9      ; "error rendering glyph (glyphindex="
0038    MOV      9   2
0039    KSTR    10  10      ; ") for face"
0040    MOV     11   1
0041    CALL     7   1   5
0042    RET0     0   1
0043 => UGET     7   2      ; CacheItem
0044    MOV      8   7
0045    TGETS    7   7  11  ; "new"
0046    TNEW     9   3
0047    TSETB    6   9   1
0048    CALL     7   2   3
0049    MOV      5   7
0050    TGETB    7   5   1
0051    TGETS    7   7  13  ; "bb"
0052    MOV      8   7
0053    TGETS    7   7  14  ; "getWidth"
0054    CALL     7   2   2
0055    TGETB    8   5   1
0056    TGETS    8   8  13  ; "bb"
0057    MOV      9   8
0058    TGETS    8   8  15  ; "getHeight"
0059    CALL     8   2   2
0060    MULVV    7   7   8
0061    DIVVN    7   7   0  ; 2
0062    ADDVN    7   7   1  ; 32
0063    TSETS    7   5  12  ; "size"
0064    UGET     7   0      ; GlyphCache
0065    MOV      8   7
0066    TGETS    7   7  16  ; "insert"
0067    MOV      9   4
0068    MOV     10   5
0069    CALL     7   1   4
0070    RET1     6   2

-- BYTECODE -- rendertext.lua:0-323
0001    GGET     0   0      ; "require"
0002    KSTR     1   1      ; "bit"
0003    CALL     0   2   2
0004    GGET     1   0      ; "require"
0005    KSTR     2   2      ; "ui/font"
0006    CALL     1   2   2
0007    GGET     2   0      ; "require"
0008    KSTR     3   3      ; "cache"
0009    CALL     2   2   2
0010    GGET     3   0      ; "require"
0011    KSTR     4   4      ; "cacheitem"
0012    CALL     3   2   2
0013    GGET     4   0      ; "require"
0014    KSTR     5   5      ; "ffi/blitbuffer"
0015    CALL     4   2   2
0016    GGET     5   0      ; "require"
0017    KSTR     6   6      ; "device"
0018    CALL     5   2   2
0019    GGET     6   0      ; "require"
0020    KSTR     7   7      ; "logger"
0021    CALL     6   2   2
0022    TGETS    7   0   8  ; "band"
0023    TGETS    8   0   9  ; "bor"
0024    TGETS    9   0  10  ; "lshift"
0025    TGETS   10   5  11  ; "should_restrict_JIT"
0026    ISF         10
0027    JMP     11 => 0035
0028    GGET    10   0      ; "require"
0029    KSTR    11  12      ; "jit"
0030    CALL    10   2   2
0031    TGETS   10  10  13  ; "off"
0032    KPRI    11   2
0033    KPRI    12   2
0034    CALL    10   1   3
0035 => TNEW    10   0
0036    MOV     12   2
0037    TGETS   11   2  14  ; "new"
0038    TDUP    13  15
0039    TNEW    14   0
0040    TSETS   14  13   3  ; "cache"
0041    TNEW    14   0
0042    TSETS   14  13  16  ; "cache_order"
0043    CALL    11   2   3
0044    FNEW    12  17      ; rendertext.lua:35
0045    FNEW    13  19      ; rendertext.lua:86
0046    TSETS   13  10  18  ; "getGlyph"
0047    FNEW    13  21      ; rendertext.lua:131
0048    TSETS   13  10  20  ; "getSubTextByWidth"
0049    FNEW    13  23      ; rendertext.lua:166
0050    TSETS   13  10  22  ; "sizeUtf8Text"
0051    FNEW    13  25      ; rendertext.lua:214
0052    TSETS   13  10  24  ; "renderUtf8Text"
0053    KSTR    13  26      ; "â€¦"
0054    FNEW    14  28      ; rendertext.lua:272
0055    TSETS   14  10  27  ; "getEllipsisWidth"
0056    FNEW    14  30      ; rendertext.lua:286
0057    TSETS   14  10  29  ; "truncateTextByWidth"
0058    FNEW    14  32      ; rendertext.lua:301
0059    TSETS   14  10  31  ; "getGlyphByIndex"
0060    UCLO     0 => 0061
0061 => RET1    10   2

