
main <./frontend/ui/rendertext.lua:0,0> (80 instructions, 320 bytes at 0x7f7ffb505070)
0+ params, 15 slots, 0 upvalues, 14 locals, 28 constants, 8 functions
	1	[5]	GETGLOBAL	0 -1	; require
	2	[5]	LOADK    	1 -2	; "bit"
	3	[5]	CALL     	0 2 2
	4	[6]	GETGLOBAL	1 -1	; require
	5	[6]	LOADK    	2 -3	; "ui/font"
	6	[6]	CALL     	1 2 2
	7	[7]	GETGLOBAL	2 -1	; require
	8	[7]	LOADK    	3 -4	; "cache"
	9	[7]	CALL     	2 2 2
	10	[8]	GETGLOBAL	3 -1	; require
	11	[8]	LOADK    	4 -5	; "cacheitem"
	12	[8]	CALL     	3 2 2
	13	[9]	GETGLOBAL	4 -1	; require
	14	[9]	LOADK    	5 -6	; "ffi/blitbuffer"
	15	[9]	CALL     	4 2 2
	16	[10]	GETGLOBAL	5 -1	; require
	17	[10]	LOADK    	6 -7	; "device"
	18	[10]	CALL     	5 2 2
	19	[11]	GETGLOBAL	6 -1	; require
	20	[11]	LOADK    	7 -8	; "logger"
	21	[11]	CALL     	6 2 2
	22	[13]	GETTABLE 	7 0 -9	; "band"
	23	[14]	GETTABLE 	8 0 -10	; "bor"
	24	[15]	GETTABLE 	9 0 -11	; "lshift"
	25	[17]	GETTABLE 	10 5 -12	; "should_restrict_JIT"
	26	[17]	TEST     	10 0 0
	27	[17]	JMP      	7	; to 35
	28	[18]	GETGLOBAL	10 -1	; require
	29	[18]	LOADK    	11 -13	; "jit"
	30	[18]	CALL     	10 2 2
	31	[18]	GETTABLE 	10 10 -14	; "off"
	32	[18]	LOADBOOL 	11 1 0
	33	[18]	LOADBOOL 	12 1 0
	34	[18]	CALL     	10 3 1
	35	[24]	NEWTABLE 	10 0 0
	36	[26]	SELF     	11 2 -15	; "new"
	37	[26]	NEWTABLE 	13 0 4
	38	[27]	SETTABLE 	13 -16 -17	; "max_memsize" 524288
	39	[28]	SETTABLE 	13 -18 -19	; "current_memsize" 0
	40	[29]	NEWTABLE 	14 0 0
	41	[29]	SETTABLE 	13 -4 14	; "cache" -
	42	[31]	NEWTABLE 	14 0 0
	43	[31]	SETTABLE 	13 -20 14	; "cache_order" -
	44	[26]	CALL     	11 3 2
	45	[78]	CLOSURE  	12 0	; 0x7f7ffb5057f0
	46	[78]	MOVE     	0 7
	47	[78]	MOVE     	0 8
	48	[78]	MOVE     	0 9
	49	[119]	CLOSURE  	13 1	; 0x7f7ffb505a70
	50	[119]	MOVE     	0 11
	51	[119]	MOVE     	0 1
	52	[119]	MOVE     	0 6
	53	[119]	MOVE     	0 3
	54	[86]	SETTABLE 	10 -21 13	; "getGlyph" -
	55	[152]	CLOSURE  	13 2	; 0x7f7ffb506a50
	56	[152]	MOVE     	0 12
	57	[131]	SETTABLE 	10 -22 13	; "getSubTextByWidth" -
	58	[199]	CLOSURE  	13 3	; 0x7f7ffb507140
	59	[199]	MOVE     	0 6
	60	[199]	MOVE     	0 12
	61	[166]	SETTABLE 	10 -23 13	; "sizeUtf8Text" -
	62	[268]	CLOSURE  	13 4	; 0x7f7ffb5079c0
	63	[268]	MOVE     	0 6
	64	[268]	MOVE     	0 4
	65	[268]	MOVE     	0 12
	66	[214]	SETTABLE 	10 -24 13	; "renderUtf8Text" -
	67	[270]	LOADK    	13 -25	; "\226\128\166"
	68	[274]	CLOSURE  	14 5	; 0x7f7ffb507e70
	69	[274]	MOVE     	0 13
	70	[272]	SETTABLE 	10 -26 14	; "getEllipsisWidth" -
	71	[291]	CLOSURE  	14 6	; 0x7f7ffb5090d0
	72	[291]	MOVE     	0 13
	73	[286]	SETTABLE 	10 -27 14	; "truncateTextByWidth" -
	74	[320]	CLOSURE  	14 7	; 0x7f7ffb5098c0
	75	[320]	MOVE     	0 11
	76	[320]	MOVE     	0 6
	77	[320]	MOVE     	0 3
	78	[301]	SETTABLE 	10 -28 14	; "getGlyphByIndex" -
	79	[322]	RETURN   	10 2
	80	[322]	RETURN   	0 1

function <./frontend/ui/rendertext.lua:35,78> (9 instructions, 36 bytes at 0x7f7ffb5057f0)
1 param, 5 slots, 3 upvalues, 2 locals, 1 constant, 1 function
	1	[76]	CLOSURE  	1 0	; 0x7f7ffb505b10
	2	[76]	GETUPVAL 	0 0	; band
	3	[76]	GETUPVAL 	0 1	; bor
	4	[76]	GETUPVAL 	0 2	; lshift
	5	[77]	MOVE     	2 1
	6	[77]	MOVE     	3 0
	7	[77]	LOADK    	4 -1	; 1
	8	[77]	RETURN   	2 4
	9	[78]	RETURN   	0 1

function <./frontend/ui/rendertext.lua:36,76> (145 instructions, 580 bytes at 0x7f7ffb505b10)
2 params, 14 slots, 3 upvalues, 9 locals, 20 constants, 0 functions
	1	[37]	GETGLOBAL	2 -1	; string
	2	[37]	GETTABLE 	2 2 -2	; "len"
	3	[37]	MOVE     	3 0
	4	[37]	CALL     	2 2 2
	5	[37]	LT       	0 2 1
	6	[37]	JMP      	2	; to 9
	7	[37]	LOADNIL  	2 2
	8	[37]	RETURN   	2 2
	9	[38]	GETGLOBAL	2 -1	; string
	10	[38]	GETTABLE 	2 2 -3	; "byte"
	11	[38]	MOVE     	3 0
	12	[38]	MOVE     	4 1
	13	[38]	CALL     	2 3 2
	14	[39]	GETUPVAL 	3 0	; band
	15	[39]	MOVE     	4 2
	16	[39]	LOADK    	5 -4	; 128
	17	[39]	CALL     	3 3 2
	18	[39]	EQ       	0 3 -5	; - 0
	19	[39]	JMP      	10	; to 30
	20	[41]	ADD      	3 1 -6	; - 1
	21	[41]	MOVE     	4 2
	22	[41]	GETGLOBAL	5 -1	; string
	23	[41]	GETTABLE 	5 5 -7	; "sub"
	24	[41]	MOVE     	6 0
	25	[41]	MOVE     	7 1
	26	[41]	MOVE     	8 1
	27	[41]	CALL     	5 4 0
	28	[41]	RETURN   	3 0
	29	[41]	JMP      	115	; to 145
	30	[42]	GETUPVAL 	3 0	; band
	31	[42]	MOVE     	4 2
	32	[42]	LOADK    	5 -8	; 192
	33	[42]	CALL     	3 3 2
	34	[42]	EQ       	1 3 -4	; - 128
	35	[42]	JMP      	6	; to 42
	36	[43]	GETUPVAL 	3 0	; band
	37	[43]	MOVE     	4 2
	38	[43]	LOADK    	5 -9	; 248
	39	[43]	CALL     	3 3 2
	40	[43]	EQ       	0 3 -9	; - 248
	41	[43]	JMP      	5	; to 47
	42	[45]	ADD      	3 1 -6	; - 1
	43	[45]	LOADK    	4 -10	; 65533
	44	[45]	LOADK    	5 -11	; "xFFxFD"
	45	[45]	RETURN   	3 4
	46	[45]	JMP      	98	; to 145
	47	[47]	LOADNIL  	3 4
	48	[48]	GETUPVAL 	5 0	; band
	49	[48]	MOVE     	6 2
	50	[48]	LOADK    	7 -12	; 224
	51	[48]	CALL     	5 3 2
	52	[48]	EQ       	0 5 -8	; - 192
	53	[48]	JMP      	7	; to 61
	54	[49]	GETUPVAL 	5 0	; band
	55	[49]	MOVE     	6 2
	56	[49]	LOADK    	7 -13	; 31
	57	[49]	CALL     	5 3 2
	58	[49]	MOVE     	3 5
	59	[50]	LOADK    	4 -6	; 1
	60	[50]	JMP      	30	; to 91
	61	[51]	GETUPVAL 	5 0	; band
	62	[51]	MOVE     	6 2
	63	[51]	LOADK    	7 -14	; 240
	64	[51]	CALL     	5 3 2
	65	[51]	EQ       	0 5 -12	; - 224
	66	[51]	JMP      	7	; to 74
	67	[52]	GETUPVAL 	5 0	; band
	68	[52]	MOVE     	6 2
	69	[52]	LOADK    	7 -15	; 15
	70	[52]	CALL     	5 3 2
	71	[52]	MOVE     	3 5
	72	[53]	LOADK    	4 -16	; 2
	73	[53]	JMP      	17	; to 91
	74	[54]	GETUPVAL 	5 0	; band
	75	[54]	MOVE     	6 2
	76	[54]	LOADK    	7 -9	; 248
	77	[54]	CALL     	5 3 2
	78	[54]	EQ       	0 5 -14	; - 240
	79	[54]	JMP      	7	; to 87
	80	[55]	GETUPVAL 	5 0	; band
	81	[55]	MOVE     	6 2
	82	[55]	LOADK    	7 -17	; 7
	83	[55]	CALL     	5 3 2
	84	[55]	MOVE     	3 5
	85	[56]	LOADK    	4 -18	; 3
	86	[56]	JMP      	4	; to 91
	87	[58]	ADD      	5 1 -6	; - 1
	88	[58]	LOADK    	6 -10	; 65533
	89	[58]	LOADK    	7 -11	; "xFFxFD"
	90	[58]	RETURN   	5 4
	91	[60]	GETGLOBAL	5 -1	; string
	92	[60]	GETTABLE 	5 5 -2	; "len"
	93	[60]	MOVE     	6 0
	94	[60]	CALL     	5 2 2
	95	[60]	ADD      	6 1 4
	96	[60]	LT       	0 5 6
	97	[60]	JMP      	4	; to 102
	98	[61]	ADD      	5 1 -6	; - 1
	99	[61]	LOADK    	6 -10	; 65533
	100	[61]	LOADK    	7 -11	; "xFFxFD"
	101	[61]	RETURN   	5 4
	102	[63]	ADD      	5 1 -6	; - 1
	103	[63]	ADD      	6 1 4
	104	[63]	LOADK    	7 -6	; 1
	105	[63]	FORPREP  	5 28	; to 134
	106	[64]	GETGLOBAL	9 -1	; string
	107	[64]	GETTABLE 	9 9 -3	; "byte"
	108	[64]	MOVE     	10 0
	109	[64]	MOVE     	11 8
	110	[64]	CALL     	9 3 2
	111	[64]	MOVE     	2 9
	112	[65]	GETUPVAL 	9 0	; band
	113	[65]	MOVE     	10 2
	114	[65]	LOADK    	11 -8	; 192
	115	[65]	CALL     	9 3 2
	116	[65]	EQ       	0 9 -4	; - 128
	117	[65]	JMP      	12	; to 130
	118	[66]	GETUPVAL 	9 1	; bor
	119	[66]	GETUPVAL 	10 2	; lshift
	120	[66]	MOVE     	11 3
	121	[66]	LOADK    	12 -19	; 6
	122	[66]	CALL     	10 3 2
	123	[66]	GETUPVAL 	11 0	; band
	124	[66]	MOVE     	12 2
	125	[66]	LOADK    	13 -20	; 63
	126	[66]	CALL     	11 3 0
	127	[66]	CALL     	9 0 2
	128	[66]	MOVE     	3 9
	129	[66]	JMP      	4	; to 134
	130	[70]	ADD      	9 1 -6	; - 1
	131	[70]	LOADK    	10 -10	; 65533
	132	[70]	LOADK    	11 -11	; "xFFxFD"
	133	[70]	RETURN   	9 4
	134	[63]	FORLOOP  	5 -29	; to 106
	135	[74]	ADD      	5 1 4
	136	[74]	ADD      	5 5 -6	; - 1
	137	[74]	MOVE     	6 3
	138	[74]	GETGLOBAL	7 -1	; string
	139	[74]	GETTABLE 	7 7 -7	; "sub"
	140	[74]	MOVE     	8 0
	141	[74]	MOVE     	9 1
	142	[74]	ADD      	10 1 4
	143	[74]	CALL     	7 4 0
	144	[74]	RETURN   	5 0
	145	[76]	RETURN   	0 1

function <./frontend/ui/rendertext.lua:86,119> (99 instructions, 396 bytes at 0x7f7ffb505a70)
4 params, 18 slots, 4 upvalues, 14 locals, 26 constants, 0 functions
	1	[87]	MOVE     	4 3
	2	[88]	GETTABLE 	5 1 -1	; "is_real_bold"
	3	[88]	TEST     	5 0 0
	4	[88]	JMP      	1	; to 6
	5	[89]	LOADBOOL 	3 0 0
	6	[91]	LOADK    	5 -2	; "glyph|"
	7	[91]	GETTABLE 	6 1 -3	; "hash"
	8	[91]	LOADK    	7 -4	; "|"
	9	[91]	MOVE     	8 2
	10	[91]	LOADK    	9 -4	; "|"
	11	[91]	TEST     	3 0 0
	12	[91]	JMP      	3	; to 16
	13	[91]	LOADK    	10 -5	; 1
	14	[91]	TEST     	10 0 1
	15	[91]	JMP      	1	; to 17
	16	[91]	LOADK    	10 -6	; 0
	17	[91]	CONCAT   	5 5 10
	18	[92]	GETUPVAL 	6 0	; GlyphCache
	19	[92]	SELF     	6 6 -7	; "check"
	20	[92]	MOVE     	8 5
	21	[92]	CALL     	6 3 2
	22	[93]	TEST     	6 0 0
	23	[93]	JMP      	2	; to 26
	24	[95]	GETTABLE 	7 6 -5	; 1
	25	[95]	RETURN   	7 2
	26	[97]	GETTABLE 	7 1 -8	; "ftface"
	27	[97]	SELF     	7 7 -9	; "renderGlyph"
	28	[97]	MOVE     	9 2
	29	[97]	MOVE     	10 3
	30	[97]	CALL     	7 4 2
	31	[98]	GETTABLE 	8 1 -8	; "ftface"
	32	[98]	SELF     	8 8 -10	; "checkGlyph"
	33	[98]	MOVE     	10 2
	34	[98]	CALL     	8 3 2
	35	[98]	EQ       	0 8 -6	; - 0
	36	[98]	JMP      	27	; to 64
	37	[99]	GETGLOBAL	8 -11	; pairs
	38	[99]	GETUPVAL 	9 1	; Font
	39	[99]	GETTABLE 	9 9 -12	; "fallbacks"
	40	[99]	CALL     	8 2 4
	41	[99]	JMP      	20	; to 62
	42	[101]	GETUPVAL 	13 1	; Font
	43	[101]	SELF     	13 13 -13	; "getFace"
	44	[101]	MOVE     	15 12
	45	[101]	GETTABLE 	16 1 -14	; "orig_size"
	46	[101]	CALL     	13 4 2
	47	[102]	EQ       	1 13 -15	; - nil
	48	[102]	JMP      	13	; to 62
	49	[104]	GETTABLE 	14 13 -8	; "ftface"
	50	[104]	SELF     	14 14 -10	; "checkGlyph"
	51	[104]	MOVE     	16 2
	52	[104]	CALL     	14 3 2
	53	[104]	EQ       	1 14 -6	; - 0
	54	[104]	JMP      	7	; to 62
	55	[105]	GETTABLE 	14 13 -8	; "ftface"
	56	[105]	SELF     	14 14 -9	; "renderGlyph"
	57	[105]	MOVE     	16 2
	58	[105]	MOVE     	17 4
	59	[105]	CALL     	14 4 2
	60	[105]	MOVE     	7 14
	61	[106]	JMP      	2	; to 64
	62	[99]	TFORLOOP 	8 2
	63	[108]	JMP      	-22	; to 42
	64	[111]	TEST     	7 0 1
	65	[111]	JMP      	8	; to 74
	66	[112]	GETUPVAL 	8 2	; logger
	67	[112]	GETTABLE 	8 8 -16	; "warn"
	68	[112]	LOADK    	9 -17	; "error rendering glyph (charcode="
	69	[112]	MOVE     	10 2
	70	[112]	LOADK    	11 -18	; ") for face"
	71	[112]	MOVE     	12 1
	72	[112]	CALL     	8 5 1
	73	[113]	RETURN   	0 1
	74	[115]	GETUPVAL 	8 3	; CacheItem
	75	[115]	SELF     	8 8 -19	; "new"
	76	[115]	NEWTABLE 	10 1 0
	77	[115]	MOVE     	11 7
	78	[115]	SETLIST  	10 1 1	; 1
	79	[115]	CALL     	8 3 2
	80	[115]	MOVE     	6 8
	81	[116]	GETTABLE 	8 6 -5	; 1
	82	[116]	GETTABLE 	8 8 -21	; "bb"
	83	[116]	SELF     	8 8 -22	; "getWidth"
	84	[116]	CALL     	8 2 2
	85	[116]	GETTABLE 	9 6 -5	; 1
	86	[116]	GETTABLE 	9 9 -21	; "bb"
	87	[116]	SELF     	9 9 -23	; "getHeight"
	88	[116]	CALL     	9 2 2
	89	[116]	MUL      	8 8 9
	90	[116]	DIV      	8 8 -24	; - 2
	91	[116]	ADD      	8 8 -25	; - 32
	92	[116]	SETTABLE 	6 -20 8	; "size" -
	93	[117]	GETUPVAL 	8 0	; GlyphCache
	94	[117]	SELF     	8 8 -26	; "insert"
	95	[117]	MOVE     	10 5
	96	[117]	MOVE     	11 6
	97	[117]	CALL     	8 4 1
	98	[118]	RETURN   	7 2
	99	[119]	RETURN   	0 1

function <./frontend/ui/rendertext.lua:131,152> (44 instructions, 176 bytes at 0x7f7ffb506a50)
6 params, 20 slots, 1 upvalue, 17 locals, 8 constants, 0 functions
	1	[132]	LOADK    	6 -1	; 0
	2	[133]	LOADNIL  	7 7
	3	[134]	NEWTABLE 	8 0 0
	4	[135]	GETUPVAL 	9 0	; utf8Chars
	5	[135]	MOVE     	10 1
	6	[135]	CALL     	9 2 4
	7	[135]	JMP      	29	; to 37
	8	[136]	LT       	0 6 3
	9	[136]	JMP      	27	; to 37
	10	[137]	SELF     	15 0 -2	; "getGlyph"
	11	[137]	MOVE     	17 2
	12	[137]	MOVE     	18 13
	13	[137]	MOVE     	19 5
	14	[137]	CALL     	15 5 2
	15	[138]	TEST     	4 0 0
	16	[138]	JMP      	8	; to 25
	17	[138]	TEST     	7 0 0
	18	[138]	JMP      	6	; to 25
	19	[139]	GETTABLE 	16 2 -3	; "ftface"
	20	[139]	SELF     	16 16 -4	; "getKerning"
	21	[139]	MOVE     	18 7
	22	[139]	MOVE     	19 13
	23	[139]	CALL     	16 4 2
	24	[140]	ADD      	6 6 16
	25	[142]	GETTABLE 	16 15 -5	; "ax"
	26	[142]	ADD      	6 6 16
	27	[143]	LE       	0 6 3
	28	[143]	JMP      	10	; to 39
	29	[144]	MOVE     	7 13
	30	[145]	GETGLOBAL	16 -6	; table
	31	[145]	GETTABLE 	16 16 -7	; "insert"
	32	[145]	MOVE     	17 8
	33	[145]	MOVE     	18 14
	34	[145]	CALL     	16 3 1
	35	[145]	JMP      	1	; to 37
	36	[147]	JMP      	2	; to 39
	37	[135]	TFORLOOP 	9 3
	38	[149]	JMP      	-31	; to 8
	39	[151]	GETGLOBAL	9 -6	; table
	40	[151]	GETTABLE 	9 9 -8	; "concat"
	41	[151]	MOVE     	10 8
	42	[151]	TAILCALL 	9 2 0
	43	[151]	RETURN   	9 0
	44	[152]	RETURN   	0 1

function <./frontend/ui/rendertext.lua:166,199> (66 instructions, 264 bytes at 0x7f7ffb507140)
7 params, 22 slots, 2 upvalues, 18 locals, 15 constants, 0 functions
	1	[167]	TEST     	4 0 1
	2	[167]	JMP      	9	; to 12
	3	[168]	GETUPVAL 	7 0	; logger
	4	[168]	GETTABLE 	7 7 -1	; "warn"
	5	[168]	LOADK    	8 -2	; "sizeUtf8Text called without text"
	6	[168]	CALL     	7 2 1
	7	[169]	NEWTABLE 	7 0 3
	8	[169]	SETTABLE 	7 -3 -4	; "x" 0
	9	[169]	SETTABLE 	7 -5 -4	; "y_top" 0
	10	[169]	SETTABLE 	7 -6 -4	; "y_bottom" 0
	11	[169]	RETURN   	7 2
	12	[174]	LOADK    	7 -4	; 0
	13	[175]	LOADK    	8 -4	; 0
	14	[176]	LOADK    	9 -4	; 0
	15	[177]	LOADK    	10 -4	; 0
	16	[178]	GETUPVAL 	11 1	; utf8Chars
	17	[178]	MOVE     	12 4
	18	[178]	CALL     	11 2 4
	19	[178]	JMP      	39	; to 59
	20	[179]	TEST     	2 0 0
	21	[179]	JMP      	3	; to 25
	22	[179]	SUB      	17 2 1
	23	[179]	LT       	0 7 17
	24	[179]	JMP      	34	; to 59
	25	[180]	SELF     	17 0 -7	; "getGlyph"
	26	[180]	MOVE     	19 3
	27	[180]	MOVE     	20 15
	28	[180]	MOVE     	21 6
	29	[180]	CALL     	17 5 2
	30	[181]	TEST     	5 0 0
	31	[181]	JMP      	8	; to 40
	32	[181]	EQ       	1 10 -4	; - 0
	33	[181]	JMP      	6	; to 40
	34	[182]	GETTABLE 	18 3 -8	; "ftface"
	35	[182]	SELF     	18 18 -9	; "getKerning"
	36	[182]	MOVE     	20 10
	37	[182]	MOVE     	21 15
	38	[182]	CALL     	18 4 2
	39	[182]	ADD      	7 7 18
	40	[184]	GETTABLE 	18 17 -10	; "ax"
	41	[184]	ADD      	7 7 18
	42	[185]	GETGLOBAL	18 -11	; math
	43	[185]	GETTABLE 	18 18 -12	; "max"
	44	[185]	MOVE     	19 8
	45	[185]	GETTABLE 	20 17 -13	; "t"
	46	[185]	CALL     	18 3 2
	47	[185]	MOVE     	8 18
	48	[186]	GETGLOBAL	18 -11	; math
	49	[186]	GETTABLE 	18 18 -12	; "max"
	50	[186]	MOVE     	19 9
	51	[186]	GETTABLE 	20 17 -14	; "bb"
	52	[186]	SELF     	20 20 -15	; "getHeight"
	53	[186]	CALL     	20 2 2
	54	[186]	GETTABLE 	21 17 -13	; "t"
	55	[186]	SUB      	20 20 21
	56	[186]	CALL     	18 3 2
	57	[186]	MOVE     	9 18
	58	[187]	MOVE     	10 15
	59	[178]	TFORLOOP 	11 3
	60	[188]	JMP      	-41	; to 20
	61	[198]	NEWTABLE 	11 0 3
	62	[198]	SETTABLE 	11 -3 7	; "x" -
	63	[198]	SETTABLE 	11 -5 8	; "y_top" -
	64	[198]	SETTABLE 	11 -6 9	; "y_bottom" -
	65	[198]	RETURN   	11 2
	66	[199]	RETURN   	0 1

function <./frontend/ui/rendertext.lua:214,268> (76 instructions, 304 bytes at 0x7f7ffb5079c0)
11 params, 32 slots, 3 upvalues, 22 locals, 15 constants, 0 functions
	1	[215]	TEST     	5 0 1
	2	[215]	JMP      	6	; to 9
	3	[216]	GETUPVAL 	11 0	; logger
	4	[216]	GETTABLE 	11 11 -1	; "warn"
	5	[216]	LOADK    	12 -2	; "renderUtf8Text called without text"
	6	[216]	CALL     	11 2 1
	7	[217]	LOADK    	11 -3	; 0
	8	[217]	RETURN   	11 2
	9	[220]	TEST     	8 0 1
	10	[220]	JMP      	2	; to 13
	11	[221]	GETUPVAL 	11 1	; BlitBuffer
	12	[221]	GETTABLE 	8 11 -4	; "COLOR_BLACK"
	13	[226]	LOADK    	11 -3	; 0
	14	[227]	LOADK    	12 -3	; 0
	15	[228]	SELF     	13 1 -5	; "getWidth"
	16	[228]	CALL     	13 2 2
	17	[228]	SUB      	13 13 2
	18	[229]	TEST     	9 0 0
	19	[229]	JMP      	3	; to 23
	20	[229]	LT       	0 9 13
	21	[229]	JMP      	1	; to 23
	22	[230]	MOVE     	13 9
	23	[232]	LOADK    	14 -3	; 0
	24	[233]	GETUPVAL 	15 2	; utf8Chars
	25	[233]	MOVE     	16 5
	26	[233]	CALL     	15 2 4
	27	[233]	JMP      	45	; to 73
	28	[234]	LT       	0 11 13
	29	[234]	JMP      	35	; to 65
	30	[235]	SELF     	21 0 -6	; "getGlyph"
	31	[235]	MOVE     	23 4
	32	[235]	MOVE     	24 19
	33	[235]	MOVE     	25 7
	34	[235]	CALL     	21 5 2
	35	[236]	TEST     	6 0 0
	36	[236]	JMP      	8	; to 45
	37	[236]	EQ       	1 12 -3	; - 0
	38	[236]	JMP      	6	; to 45
	39	[237]	GETTABLE 	22 4 -7	; "ftface"
	40	[237]	SELF     	22 22 -8	; "getKerning"
	41	[237]	MOVE     	24 12
	42	[237]	MOVE     	25 19
	43	[237]	CALL     	22 4 2
	44	[237]	ADD      	11 11 22
	45	[239]	SELF     	22 1 -9	; "colorblitFrom"
	46	[240]	GETTABLE 	24 21 -10	; "bb"
	47	[241]	ADD      	25 2 11
	48	[241]	GETTABLE 	26 21 -11	; "l"
	49	[241]	ADD      	25 25 26
	50	[242]	GETTABLE 	26 21 -12	; "t"
	51	[242]	SUB      	26 3 26
	52	[243]	LOADK    	27 -3	; 0
	53	[243]	LOADK    	28 -3	; 0
	54	[244]	GETTABLE 	29 21 -10	; "bb"
	55	[244]	SELF     	29 29 -5	; "getWidth"
	56	[244]	CALL     	29 2 2
	57	[244]	GETTABLE 	30 21 -10	; "bb"
	58	[244]	SELF     	30 30 -13	; "getHeight"
	59	[244]	CALL     	30 2 2
	60	[245]	MOVE     	31 8
	61	[239]	CALL     	22 10 1
	62	[246]	GETTABLE 	22 21 -14	; "ax"
	63	[246]	ADD      	11 11 22
	64	[247]	MOVE     	12 19
	65	[249]	TEST     	10 0 0
	66	[249]	JMP      	6	; to 73
	67	[250]	ADD      	14 14 -15	; - 1
	68	[251]	GETTABLE 	21 10 14
	69	[251]	TEST     	21 0 1
	70	[251]	JMP      	1	; to 72
	71	[251]	LOADK    	21 -3	; 0
	72	[251]	ADD      	11 11 21
	73	[233]	TFORLOOP 	15 3
	74	[264]	JMP      	-47	; to 28
	75	[267]	RETURN   	11 2
	76	[268]	RETURN   	0 1

function <./frontend/ui/rendertext.lua:272,274> (11 instructions, 44 bytes at 0x7f7ffb507e70)
3 params, 11 slots, 1 upvalue, 3 locals, 3 constants, 0 functions
	1	[273]	SELF     	3 0 -1	; "sizeUtf8Text"
	2	[273]	LOADK    	5 -2	; 0
	3	[273]	LOADBOOL 	6 0 0
	4	[273]	MOVE     	7 1
	5	[273]	GETUPVAL 	8 0	; ellipsis
	6	[273]	LOADBOOL 	9 0 0
	7	[273]	MOVE     	10 2
	8	[273]	CALL     	3 8 2
	9	[273]	GETTABLE 	3 3 -3	; "x"
	10	[273]	RETURN   	3 2
	11	[274]	RETURN   	0 1

function <./frontend/ui/rendertext.lua:286,291> (17 instructions, 68 bytes at 0x7f7ffb5090d0)
6 params, 15 slots, 1 upvalue, 9 locals, 2 constants, 0 functions
	1	[287]	SELF     	6 0 -1	; "getEllipsisWidth"
	2	[287]	MOVE     	8 2
	3	[287]	MOVE     	9 5
	4	[287]	CALL     	6 4 2
	5	[288]	SUB      	7 3 6
	6	[289]	SELF     	8 0 -2	; "getSubTextByWidth"
	7	[289]	MOVE     	10 1
	8	[289]	MOVE     	11 2
	9	[289]	MOVE     	12 7
	10	[289]	MOVE     	13 4
	11	[289]	MOVE     	14 5
	12	[289]	CALL     	8 7 2
	13	[290]	MOVE     	9 8
	14	[290]	GETUPVAL 	10 0	; ellipsis
	15	[290]	CONCAT   	9 9 10
	16	[290]	RETURN   	9 2
	17	[291]	RETURN   	0 1

function <./frontend/ui/rendertext.lua:301,320> (67 instructions, 268 bytes at 0x7f7ffb5098c0)
4 params, 12 slots, 3 upvalues, 7 locals, 21 constants, 0 functions
	1	[302]	GETTABLE 	4 1 -1	; "is_real_bold"
	2	[302]	TEST     	4 0 0
	3	[302]	JMP      	1	; to 5
	4	[303]	LOADBOOL 	3 0 0
	5	[305]	LOADK    	4 -2	; "xglyph|"
	6	[305]	GETTABLE 	5 1 -3	; "hash"
	7	[305]	LOADK    	6 -4	; "|"
	8	[305]	MOVE     	7 2
	9	[305]	LOADK    	8 -4	; "|"
	10	[305]	TEST     	3 0 0
	11	[305]	JMP      	3	; to 15
	12	[305]	LOADK    	9 -5	; 1
	13	[305]	TEST     	9 0 1
	14	[305]	JMP      	1	; to 16
	15	[305]	LOADK    	9 -6	; 0
	16	[305]	CONCAT   	4 4 9
	17	[306]	GETUPVAL 	5 0	; GlyphCache
	18	[306]	SELF     	5 5 -7	; "check"
	19	[306]	MOVE     	7 4
	20	[306]	CALL     	5 3 2
	21	[307]	TEST     	5 0 0
	22	[307]	JMP      	2	; to 25
	23	[309]	GETTABLE 	6 5 -5	; 1
	24	[309]	RETURN   	6 2
	25	[311]	GETTABLE 	6 1 -8	; "ftface"
	26	[311]	SELF     	6 6 -9	; "renderGlyphByIndex"
	27	[311]	MOVE     	8 2
	28	[311]	TESTSET  	9 3 0
	29	[311]	JMP      	1	; to 31
	30	[311]	GETTABLE 	9 1 -10	; "embolden_half_strength"
	31	[311]	CALL     	6 4 2
	32	[312]	TEST     	6 0 1
	33	[312]	JMP      	8	; to 42
	34	[313]	GETUPVAL 	7 1	; logger
	35	[313]	GETTABLE 	7 7 -11	; "warn"
	36	[313]	LOADK    	8 -12	; "error rendering glyph (glyphindex="
	37	[313]	MOVE     	9 2
	38	[313]	LOADK    	10 -13	; ") for face"
	39	[313]	MOVE     	11 1
	40	[313]	CALL     	7 5 1
	41	[314]	RETURN   	0 1
	42	[316]	GETUPVAL 	7 2	; CacheItem
	43	[316]	SELF     	7 7 -14	; "new"
	44	[316]	NEWTABLE 	9 1 0
	45	[316]	MOVE     	10 6
	46	[316]	SETLIST  	9 1 1	; 1
	47	[316]	CALL     	7 3 2
	48	[316]	MOVE     	5 7
	49	[317]	GETTABLE 	7 5 -5	; 1
	50	[317]	GETTABLE 	7 7 -16	; "bb"
	51	[317]	SELF     	7 7 -17	; "getWidth"
	52	[317]	CALL     	7 2 2
	53	[317]	GETTABLE 	8 5 -5	; 1
	54	[317]	GETTABLE 	8 8 -16	; "bb"
	55	[317]	SELF     	8 8 -18	; "getHeight"
	56	[317]	CALL     	8 2 2
	57	[317]	MUL      	7 7 8
	58	[317]	DIV      	7 7 -19	; - 2
	59	[317]	ADD      	7 7 -20	; - 32
	60	[317]	SETTABLE 	5 -15 7	; "size" -
	61	[318]	GETUPVAL 	7 0	; GlyphCache
	62	[318]	SELF     	7 7 -21	; "insert"
	63	[318]	MOVE     	9 4
	64	[318]	MOVE     	10 5
	65	[318]	CALL     	7 4 1
	66	[319]	RETURN   	6 2
	67	[320]	RETURN   	0 1
