
main <./frontend/ui/widget/container/rightcontainer.lua:0,0> (17 instructions, 68 bytes at 0x7fcd98406900)
0+ params, 6 slots, 0 upvalues, 3 locals, 9 constants, 1 function
	1	[5]	GETGLOBAL	0 -1	; require
	2	[5]	LOADK    	1 -2	; "ui/bidi"
	3	[5]	CALL     	0 2 2
	4	[6]	GETGLOBAL	1 -1	; require
	5	[6]	LOADK    	2 -3	; "ui/widget/container/widgetcontainer"
	6	[6]	CALL     	1 2 2
	7	[8]	SELF     	2 1 -4	; "new"
	8	[8]	NEWTABLE 	4 0 2
	9	[9]	SETTABLE 	4 -5 -6	; "allow_mirroring" true
	10	[10]	GETTABLE 	5 0 -8	; "mirroredUILayout"
	11	[10]	CALL     	5 1 2
	12	[10]	SETTABLE 	4 -7 5	; "_mirroredUI" -
	13	[8]	CALL     	2 3 2
	14	[27]	CLOSURE  	3 0	; 0x7fcd98406bf0
	15	[13]	SETTABLE 	2 -9 3	; "paintTo" -
	16	[29]	RETURN   	2 2
	17	[29]	RETURN   	0 1

function <./frontend/ui/widget/container/rightcontainer.lua:13,27> (29 instructions, 116 bytes at 0x7fcd98406bf0)
4 params, 12 slots, 0 upvalues, 5 locals, 11 constants, 0 functions
	1	[14]	GETTABLE 	4 0 -1	; 1
	2	[14]	SELF     	4 4 -2	; "getSize"
	3	[14]	CALL     	4 2 2
	4	[20]	GETTABLE 	5 0 -3	; "_mirroredUI"
	5	[20]	TEST     	5 0 0
	6	[20]	JMP      	3	; to 10
	7	[20]	GETTABLE 	5 0 -4	; "allow_mirroring"
	8	[20]	TEST     	5 0 1
	9	[20]	JMP      	5	; to 15
	10	[21]	GETTABLE 	5 0 -5	; "dimen"
	11	[21]	GETTABLE 	5 5 -6	; "w"
	12	[21]	GETTABLE 	6 4 -6	; "w"
	13	[21]	SUB      	5 5 6
	14	[21]	ADD      	2 2 5
	15	[24]	GETTABLE 	5 0 -1	; 1
	16	[24]	SELF     	5 5 -7	; "paintTo"
	17	[24]	MOVE     	7 1
	18	[25]	MOVE     	8 2
	19	[26]	GETGLOBAL	9 -8	; math
	20	[26]	GETTABLE 	9 9 -9	; "floor"
	21	[26]	GETTABLE 	10 0 -5	; "dimen"
	22	[26]	GETTABLE 	10 10 -10	; "h"
	23	[26]	GETTABLE 	11 4 -10	; "h"
	24	[26]	SUB      	10 10 11
	25	[26]	DIV      	10 10 -11	; - 2
	26	[26]	CALL     	9 2 2
	27	[26]	ADD      	9 3 9
	28	[24]	CALL     	5 5 1
	29	[27]	RETURN   	0 1
