-- BYTECODE -- ro_keyboard.lua:0-87
0001    GGET     0   0      ; "require"
0002    KSTR     1   1      ; "ui/data/keyboardlayouts/keypopup/en_popu"~
0003    CALL     0   2   2
0004    GGET     1   0      ; "require"
0005    KSTR     2   2      ; "ui/data/keyboardlayouts/keypopup/ro_popu"~
0006    CALL     1   2   2
0007    TGETS    2   0   3  ; "com"
0008    TGETS    3   0   4  ; "prd"
0009    TGETS    4   0   5  ; "_at"
0010    TGETS    5   0   6  ; "_eq"
0011    TGETS    6   1   7  ; "_A_"
0012    TGETS    7   1   8  ; "_a_"
0013    TGETS    8   1   9  ; "_I_"
0014    TGETS    9   1  10  ; "_i_"
0015    TGETS   10   1  11  ; "_S_"
0016    TGETS   11   1  12  ; "_s_"
0017    TGETS   12   1  13  ; "_T_"
0018    TGETS   13   1  14  ; "_t_"
0019    TGETS   14   1  15  ; "_U_"
0020    TGETS   15   1  16  ; "_u_"
0021    TDUP    16  17
0022    TDUP    17  18
0023    TSETS   17  16  19  ; "shiftmode_keys"
0024    TDUP    17  20
0025    TSETS   17  16  21  ; "symbolmode_keys"
0026    TDUP    17  22
0027    TSETS   17  16  23  ; "utf8mode_keys"
0028    TDUP    17  24
0029    TSETS   17  16  25  ; "umlautmode_keys"
0030    TNEW    17   5
0031    TNEW    18  11
0032    TDUP    19  26
0033    TSETB   19  18   1
0034    TDUP    19  27
0035    TSETB   19  18   2
0036    TDUP    19  28
0037    TSETB    4  19   3
0038    TSETB   19  18   3
0039    TDUP    19  29
0040    TSETB   19  18   4
0041    TDUP    19  30
0042    TSETB   12  19   1
0043    TSETB   13  19   2
0044    TSETB    5  19   4
0045    TSETB   19  18   5
0046    TDUP    19  31
0047    TSETB   19  18   6
0048    TDUP    19  32
0049    TSETB   14  19   1
0050    TSETB   15  19   2
0051    TSETB   19  18   7
0052    TDUP    19  33
0053    TSETB    8  19   1
0054    TSETB    9  19   2
0055    TSETB   19  18   8
0056    TDUP    19  34
0057    TSETB   19  18   9
0058    TDUP    19  35
0059    TSETB   19  18  10
0060    TSETB   18  17   1
0061    TNEW    18  10
0062    TDUP    19  36
0063    TSETB    6  19   1
0064    TSETB    7  19   2
0065    TSETB    4  19   4
0066    TSETB   19  18   1
0067    TDUP    19  37
0068    TSETB   10  19   1
0069    TSETB   11  19   2
0070    TSETB   19  18   2
0071    TDUP    19  38
0072    TSETB   19  18   3
0073    TDUP    19  39
0074    TSETB   19  18   4
0075    TDUP    19  40
0076    TSETB   19  18   5
0077    TDUP    19  41
0078    TSETB   19  18   6
0079    TDUP    19  42
0080    TSETB   19  18   7
0081    TDUP    19  43
0082    TSETB   19  18   8
0083    TDUP    19  44
0084    TSETB   19  18   9
0085    TSETB   18  17   2
0086    TNEW    18  10
0087    TDUP    19  45
0088    TSETB   19  18   1
0089    TDUP    19  46
0090    TSETB   19  18   2
0091    TDUP    19  47
0092    TSETB   19  18   3
0093    TDUP    19  48
0094    TSETB   19  18   4
0095    TDUP    19  49
0096    TSETB    2  19   4
0097    TSETB   19  18   5
0098    TDUP    19  50
0099    TSETB    3  19   4
0100    TSETB   19  18   6
0101    TDUP    19  51
0102    TSETB   19  18   7
0103    TDUP    19  52
0104    TSETB   19  18   8
0105    TDUP    19  53
0106    TSETB   19  18   9
0107    TSETB   18  17   3
0108    TNEW    18   8
0109    TDUP    19  54
0110    TSETB   19  18   1
0111    TDUP    19  55
0112    TSETB   19  18   2
0113    TDUP    19  56
0114    TSETB   19  18   3
0115    TDUP    19  57
0116    TSETB   19  18   4
0117    TDUP    19  58
0118    TSETB    2  19   1
0119    TSETB    2  19   2
0120    TSETB    2  19   7
0121    TSETB    2  19   8
0122    TSETB   19  18   5
0123    TDUP    19  59
0124    TSETB    3  19   1
0125    TSETB    3  19   2
0126    TSETB    3  19   7
0127    TSETB    3  19   8
0128    TSETB   19  18   6
0129    TDUP    19  60
0130    TSETB   19  18   7
0131    TSETB   18  17   4
0132    TSETS   17  16  61  ; "keys"
0133    RET1    16   2

