
main <./frontend/ui/data/keyboardlayouts/ru_keyboard.lua:0,0> (468 instructions, 1872 bytes at 0x7ff586c06900)
0+ params, 52 slots, 0 upvalues, 29 locals, 250 constants, 0 functions
	1	[1]	GETGLOBAL	0 -1	; require
	2	[1]	LOADK    	1 -2	; "ui/data/keyboardlayouts/keypopup/en_popup"
	3	[1]	CALL     	0 2 2
	4	[2]	GETGLOBAL	1 -1	; require
	5	[2]	LOADK    	2 -3	; "ui/data/keyboardlayouts/keypopup/ru_popup"
	6	[2]	CALL     	1 2 2
	7	[3]	GETTABLE 	2 0 -4	; "com"
	8	[4]	GETTABLE 	3 0 -5	; "prd"
	9	[5]	GETTABLE 	4 0 -6	; "_at"
	10	[6]	GETTABLE 	5 0 -7	; "_eq"
	11	[7]	GETTABLE 	6 1 -8	; "_Je_"
	12	[8]	GETTABLE 	7 1 -9	; "_je_"
	13	[9]	GETTABLE 	8 1 -10	; "_Ye_"
	14	[10]	GETTABLE 	9 1 -11	; "_ye_"
	15	[13]	GETTABLE 	10 1 -12	; "_SH_"
	16	[14]	GETTABLE 	11 1 -13	; "_sh_"
	17	[17]	GETTABLE 	12 1 -14	; "_KA_"
	18	[18]	GETTABLE 	13 1 -15	; "_ka_"
	19	[19]	GETTABLE 	14 1 -16	; "_KI_"
	20	[20]	GETTABLE 	15 1 -17	; "_ki_"
	21	[21]	GETTABLE 	16 1 -18	; "_KN_"
	22	[22]	GETTABLE 	17 1 -19	; "_kn_"
	23	[23]	GETTABLE 	18 1 -20	; "_KG_"
	24	[24]	GETTABLE 	19 1 -21	; "_kg_"
	25	[25]	GETTABLE 	20 1 -22	; "_KU_"
	26	[26]	GETTABLE 	21 1 -23	; "_ku_"
	27	[27]	GETTABLE 	22 1 -24	; "_KK_"
	28	[28]	GETTABLE 	23 1 -25	; "_kk_"
	29	[29]	GETTABLE 	24 1 -26	; "_KO_"
	30	[30]	GETTABLE 	25 1 -27	; "_ko_"
	31	[31]	GETTABLE 	26 1 -28	; "_KH_"
	32	[32]	GETTABLE 	27 1 -29	; "_kh_"
	33	[35]	GETTABLE 	28 1 -30	; "_qe_"
	34	[38]	NEWTABLE 	29 0 7
	35	[39]	SETTABLE 	29 -31 -32	; "min_layer" 1
	36	[40]	SETTABLE 	29 -33 -34	; "max_layer" 8
	37	[41]	NEWTABLE 	30 0 3
	38	[41]	SETTABLE 	30 -36 -37	; "\238\180\181" true
	39	[41]	SETTABLE 	30 -38 -37	; "1/2" true
	40	[41]	SETTABLE 	30 -39 -37	; "2/2" true
	41	[41]	SETTABLE 	29 -35 30	; "shiftmode_keys" -
	42	[42]	NEWTABLE 	30 0 3
	43	[42]	SETTABLE 	30 -41 -37	; "123" true
	44	[42]	SETTABLE 	30 -42 -37	; "\208\144\208\145\208\146" true
	45	[42]	SETTABLE 	30 -43 -37	; "\208\181\209\137\209\145" true
	46	[42]	SETTABLE 	29 -40 30	; "symbolmode_keys" -
	47	[43]	NEWTABLE 	30 0 1
	48	[43]	SETTABLE 	30 -45 -37	; "\240\159\140\144" true
	49	[43]	SETTABLE 	29 -44 30	; "utf8mode_keys" -
	50	[44]	NEWTABLE 	30 0 1
	51	[44]	SETTABLE 	30 -47 -37	; "\206\177\206\178\206\179" true
	52	[44]	SETTABLE 	29 -46 30	; "umlautmode_keys" -
	53	[45]	NEWTABLE 	30 4 0
	54	[45]	NEWTABLE 	31 11 0
	55	[47]	NEWTABLE 	32 8 0
	56	[48]	LOADK    	33 -49	; "\208\153"
	57	[48]	LOADK    	34 -50	; "\208\185"
	58	[48]	LOADK    	35 -51	; "'"
	59	[48]	LOADK    	36 -52	; "`"
	60	[48]	LOADK    	37 -53	; "\226\136\171"
	61	[48]	LOADK    	38 -54	; "\226\136\130"
	62	[48]	LOADK    	39 -55	; "\226\136\180"
	63	[48]	LOADK    	40 -52	; "`"
	64	[48]	SETLIST  	32 8 1	; 1
	65	[48]	NEWTABLE 	33 8 0
	66	[49]	LOADK    	34 -56	; "\208\166"
	67	[49]	LOADK    	35 -57	; "\209\134"
	68	[49]	LOADK    	36 -58	; "["
	69	[49]	LOADK    	37 -59	; "1"
	70	[49]	LOADK    	38 -60	; "\207\130"
	71	[49]	LOADK    	39 -60	; "\207\130"
	72	[49]	LOADK    	40 -61	; "\194\185"
	73	[49]	LOADK    	41 -59	; "1"
	74	[49]	SETLIST  	33 8 1	; 1
	75	[49]	NEWTABLE 	34 8 0
	76	[50]	MOVE     	35 20
	77	[50]	MOVE     	36 21
	78	[50]	LOADK    	37 -62	; "]"
	79	[50]	LOADK    	38 -63	; "2"
	80	[50]	LOADK    	39 -64	; "\206\149"
	81	[50]	LOADK    	40 -65	; "\206\181"
	82	[50]	LOADK    	41 -66	; "\194\178"
	83	[50]	LOADK    	42 -63	; "2"
	84	[50]	SETLIST  	34 8 1	; 1
	85	[50]	NEWTABLE 	35 8 0
	86	[51]	MOVE     	36 22
	87	[51]	MOVE     	37 23
	88	[51]	LOADK    	38 -67	; "{"
	89	[51]	LOADK    	39 -68	; "3"
	90	[51]	LOADK    	40 -69	; "\206\161"
	91	[51]	LOADK    	41 -70	; "\207\129"
	92	[51]	LOADK    	42 -71	; "\194\179"
	93	[51]	LOADK    	43 -68	; "3"
	94	[51]	SETLIST  	35 8 1	; 1
	95	[51]	NEWTABLE 	36 8 0
	96	[52]	MOVE     	37 8
	97	[52]	MOVE     	38 9
	98	[52]	LOADK    	39 -72	; "}"
	99	[52]	LOADK    	40 -73	; "4"
	100	[52]	LOADK    	41 -74	; "\206\164"
	101	[52]	LOADK    	42 -75	; "\207\132"
	102	[52]	LOADK    	43 -76	; "\226\129\180"
	103	[52]	LOADK    	44 -73	; "4"
	104	[52]	SETLIST  	36 8 1	; 1
	105	[52]	NEWTABLE 	37 8 0
	106	[53]	MOVE     	38 16
	107	[53]	MOVE     	39 17
	108	[53]	LOADK    	40 -77	; "#"
	109	[53]	LOADK    	41 -78	; "5"
	110	[53]	LOADK    	42 -79	; "\206\165"
	111	[53]	LOADK    	43 -80	; "\207\133"
	112	[53]	LOADK    	44 -81	; "\226\129\181"
	113	[53]	LOADK    	45 -78	; "5"
	114	[53]	SETLIST  	37 8 1	; 1
	115	[53]	NEWTABLE 	38 8 0
	116	[54]	MOVE     	39 18
	117	[54]	MOVE     	40 19
	118	[54]	LOADK    	41 -82	; "%"
	119	[54]	LOADK    	42 -83	; "6"
	120	[54]	LOADK    	43 -84	; "\206\152"
	121	[54]	LOADK    	44 -85	; "\206\184"
	122	[54]	LOADK    	45 -86	; "\226\129\182"
	123	[54]	LOADK    	46 -83	; "6"
	124	[54]	SETLIST  	38 8 1	; 1
	125	[54]	NEWTABLE 	39 8 0
	126	[55]	LOADK    	40 -87	; "\208\168"
	127	[55]	LOADK    	41 -88	; "\209\136"
	128	[55]	LOADK    	42 -89	; "^"
	129	[55]	LOADK    	43 -90	; "7"
	130	[55]	LOADK    	44 -91	; "\206\153"
	131	[55]	LOADK    	45 -92	; "\206\185"
	132	[55]	LOADK    	46 -93	; "\226\129\183"
	133	[55]	LOADK    	47 -90	; "7"
	134	[55]	SETLIST  	39 8 1	; 1
	135	[55]	NEWTABLE 	40 8 0
	136	[56]	LOADK    	41 -94	; "\208\169"
	137	[56]	LOADK    	42 -95	; "\209\137"
	138	[56]	LOADK    	43 -96	; "*"
	139	[56]	LOADK    	44 -97	; "8"
	140	[56]	LOADK    	45 -98	; "\206\159"
	141	[56]	LOADK    	46 -99	; "\206\191"
	142	[56]	LOADK    	47 -100	; "\226\129\184"
	143	[56]	LOADK    	48 -97	; "8"
	144	[56]	SETLIST  	40 8 1	; 1
	145	[56]	NEWTABLE 	41 8 0
	146	[57]	LOADK    	42 -101	; "\208\151"
	147	[57]	LOADK    	43 -102	; "\208\183"
	148	[57]	LOADK    	44 -103	; "+"
	149	[57]	LOADK    	45 -104	; "9"
	150	[57]	LOADK    	46 -105	; "\206\160"
	151	[57]	LOADK    	47 -106	; "\207\128"
	152	[57]	LOADK    	48 -107	; "\226\129\185"
	153	[57]	LOADK    	49 -104	; "9"
	154	[57]	SETLIST  	41 8 1	; 1
	155	[57]	NEWTABLE 	42 8 0
	156	[58]	MOVE     	43 26
	157	[58]	MOVE     	44 27
	158	[58]	MOVE     	45 5
	159	[58]	LOADK    	46 -108	; "0"
	160	[58]	LOADK    	47 -66	; "\194\178"
	161	[58]	LOADK    	48 -109	; "\226\136\154"
	162	[58]	LOADK    	49 -110	; "\226\129\176"
	163	[58]	LOADK    	50 -108	; "0"
	164	[58]	SETLIST  	42 8 1	; 1
	165	[59]	SETLIST  	31 11 1	; 1
	166	[59]	NEWTABLE 	32 11 0
	167	[61]	NEWTABLE 	33 8 0
	168	[62]	LOADK    	34 -111	; "\208\164"
	169	[62]	LOADK    	35 -112	; "\209\132"
	170	[62]	LOADK    	36 -113	; "_"
	171	[62]	LOADK    	37 -103	; "+"
	172	[62]	LOADK    	38 -114	; "\206\145"
	173	[62]	LOADK    	39 -115	; "\206\177"
	174	[62]	LOADK    	40 -116	; "\226\128\158"
	175	[62]	LOADK    	41 -117	; "\194\171"
	176	[62]	SETLIST  	33 8 1	; 1
	177	[62]	NEWTABLE 	34 8 0
	178	[63]	MOVE     	35 14
	179	[63]	MOVE     	36 15
	180	[63]	LOADK    	37 -118	; "\\"
	181	[63]	LOADK    	38 -119	; "-"
	182	[63]	LOADK    	39 -120	; "\206\163"
	183	[63]	LOADK    	40 -121	; "\207\131"
	184	[63]	LOADK    	41 -122	; "\226\128\156"
	185	[63]	LOADK    	42 -123	; "\194\187"
	186	[63]	SETLIST  	34 8 1	; 1
	187	[63]	NEWTABLE 	35 8 0
	188	[64]	LOADK    	36 -124	; "\208\146"
	189	[64]	LOADK    	37 -125	; "\208\178"
	190	[64]	LOADK    	38 -113	; "_"
	191	[64]	LOADK    	39 -126	; "/"
	192	[64]	LOADK    	40 -127	; "\206\148"
	193	[64]	LOADK    	41 -128	; "\206\180"
	194	[64]	LOADK    	42 -129	; "\226\132\150"
	195	[64]	LOADK    	43 -130	; "\226\137\164"
	196	[64]	SETLIST  	35 8 1	; 1
	197	[64]	NEWTABLE 	36 8 0
	198	[65]	MOVE     	37 12
	199	[65]	MOVE     	38 13
	200	[65]	LOADK    	39 -131	; "~"
	201	[65]	LOADK    	40 -132	; ":"
	202	[65]	LOADK    	41 -133	; "\206\166"
	203	[65]	LOADK    	42 -134	; "\207\134"
	204	[65]	LOADK    	43 -135	; "\226\128\160"
	205	[65]	LOADK    	44 -136	; "\226\137\165"
	206	[65]	SETLIST  	36 8 1	; 1
	207	[65]	NEWTABLE 	37 8 0
	208	[66]	LOADK    	38 -137	; "\208\159"
	209	[66]	LOADK    	39 -138	; "\208\191"
	210	[66]	LOADK    	40 -139	; "<"
	211	[66]	LOADK    	41 -140	; ";"
	212	[66]	LOADK    	42 -141	; "\206\147"
	213	[66]	LOADK    	43 -142	; "\206\179"
	214	[66]	LOADK    	44 -143	; "\226\128\161"
	215	[66]	LOADK    	45 -144	; "\226\137\136"
	216	[66]	SETLIST  	37 8 1	; 1
	217	[66]	NEWTABLE 	38 8 0
	218	[67]	LOADK    	39 -145	; "\208\160"
	219	[67]	LOADK    	40 -146	; "\209\128"
	220	[67]	LOADK    	41 -147	; ">"
	221	[67]	LOADK    	42 -148	; "("
	222	[67]	LOADK    	43 -149	; "\206\151"
	223	[67]	LOADK    	44 -150	; "\206\183"
	224	[67]	LOADK    	45 -151	; "\194\169"
	225	[67]	LOADK    	46 -152	; "\226\137\160"
	226	[67]	SETLIST  	38 8 1	; 1
	227	[67]	NEWTABLE 	39 8 0
	228	[68]	MOVE     	40 24
	229	[68]	MOVE     	41 25
	230	[68]	LOADK    	42 -153	; "\226\130\172"
	231	[68]	LOADK    	43 -154	; ")"
	232	[68]	LOADK    	44 -155	; "\206\158"
	233	[68]	LOADK    	45 -156	; "\206\190"
	234	[68]	LOADK    	46 -157	; "\226\132\162"
	235	[68]	LOADK    	47 -158	; "\226\137\161"
	236	[68]	SETLIST  	39 8 1	; 1
	237	[68]	NEWTABLE 	40 8 0
	238	[69]	LOADK    	41 -159	; "\208\155"
	239	[69]	LOADK    	42 -160	; "\208\187"
	240	[69]	LOADK    	43 -161	; "\194\163"
	241	[69]	LOADK    	44 -162	; "$"
	242	[69]	LOADK    	45 -163	; "\206\154"
	243	[69]	LOADK    	46 -164	; "\206\186"
	244	[69]	LOADK    	47 -165	; "\240\159\132\175"
	245	[69]	LOADK    	48 -166	; "\194\182"
	246	[69]	SETLIST  	40 8 1	; 1
	247	[69]	NEWTABLE 	41 8 0
	248	[70]	LOADK    	42 -167	; "\208\148"
	249	[70]	LOADK    	43 -168	; "\208\180"
	250	[70]	LOADK    	44 -169	; "\194\165"
	251	[70]	LOADK    	45 -170	; "&"
	252	[70]	LOADK    	46 -171	; "\206\155"
	253	[70]	LOADK    	47 -172	; "\206\187"
	254	[70]	LOADK    	48 -173	; "\194\174"
	255	[70]	LOADK    	49 -174	; "\194\167"
	256	[70]	SETLIST  	41 8 1	; 1
	257	[70]	NEWTABLE 	42 8 0
	258	[71]	MOVE     	43 6
	259	[71]	MOVE     	44 7
	260	[71]	LOADK    	45 -175	; "\226\130\184"
	261	[71]	MOVE     	46 4
	262	[71]	LOADK    	47 -176	; "\195\151"
	263	[71]	LOADK    	48 -176	; "\195\151"
	264	[71]	LOADK    	49 -177	; "\194\189"
	265	[71]	LOADK    	50 -178	; "\194\164"
	266	[71]	SETLIST  	42 8 1	; 1
	267	[71]	NEWTABLE 	43 8 0
	268	[72]	LOADK    	44 -179	; "\208\173"
	269	[72]	LOADK    	45 -180	; "\209\141"
	270	[72]	LOADK    	46 -181	; "\194\162"
	271	[72]	LOADK    	47 -182	; "\226\128\157"
	272	[72]	LOADK    	48 -183	; "\226\139\133"
	273	[72]	LOADK    	49 -183	; "\226\139\133"
	274	[72]	LOADK    	50 -184	; "\194\188"
	275	[72]	LOADK    	51 -185	; "\226\128\176"
	276	[72]	SETLIST  	43 8 1	; 1
	277	[73]	SETLIST  	32 11 1	; 1
	278	[73]	NEWTABLE 	33 11 0
	279	[75]	NEWTABLE 	34 8 1
	280	[76]	LOADK    	35 -36	; "\238\180\181"
	281	[76]	LOADK    	36 -36	; "\238\180\181"
	282	[76]	LOADK    	37 -39	; "2/2"
	283	[76]	LOADK    	38 -38	; "1/2"
	284	[76]	LOADK    	39 -36	; "\238\180\181"
	285	[76]	LOADK    	40 -36	; "\238\180\181"
	286	[76]	LOADK    	41 -36	; "\238\180\181"
	287	[76]	LOADK    	42 -36	; "\238\180\181"
	288	[77]	SETTABLE 	34 -186 -32	; "width" 1
	289	[78]	SETLIST  	34 8 1	; 1
	290	[78]	NEWTABLE 	35 8 0
	291	[79]	LOADK    	36 -187	; "\208\175"
	292	[79]	LOADK    	37 -188	; "\209\143"
	293	[79]	LOADK    	38 -189	; "\226\128\147"
	294	[79]	LOADK    	39 -189	; "\226\128\147"
	295	[79]	LOADK    	40 -190	; "\206\150"
	296	[79]	LOADK    	41 -191	; "\206\182"
	297	[79]	LOADK    	42 -192	; "\226\136\170"
	298	[79]	LOADK    	43 -193	; "\194\177"
	299	[79]	SETLIST  	35 8 1	; 1
	300	[79]	NEWTABLE 	36 8 0
	301	[80]	LOADK    	37 -194	; "\208\167"
	302	[80]	LOADK    	38 -195	; "\209\135"
	303	[80]	LOADK    	39 -196	; "\226\128\148"
	304	[80]	LOADK    	40 -196	; "\226\128\148"
	305	[80]	LOADK    	41 -197	; "\206\167"
	306	[80]	LOADK    	42 -198	; "\207\135"
	307	[80]	LOADK    	43 -199	; "\226\136\169"
	308	[80]	LOADK    	44 -200	; "\194\186"
	309	[80]	SETLIST  	36 8 1	; 1
	310	[80]	NEWTABLE 	37 8 0
	311	[81]	LOADK    	38 -201	; "\208\161"
	312	[81]	LOADK    	39 -202	; "\209\129"
	313	[81]	MOVE     	40 2
	314	[81]	MOVE     	41 2
	315	[81]	LOADK    	42 -203	; "\206\168"
	316	[81]	LOADK    	43 -204	; "\207\136"
	317	[81]	LOADK    	44 -205	; "\226\136\136"
	318	[81]	LOADK    	45 -206	; "\226\136\158"
	319	[81]	SETLIST  	37 8 1	; 1
	320	[81]	NEWTABLE 	38 8 0
	321	[82]	LOADK    	39 -207	; "\208\156"
	322	[82]	LOADK    	40 -208	; "\208\188"
	323	[82]	MOVE     	41 3
	324	[82]	MOVE     	42 3
	325	[82]	LOADK    	43 -209	; "\206\169"
	326	[82]	LOADK    	44 -210	; "\207\137"
	327	[82]	LOADK    	45 -211	; "\226\136\137"
	328	[82]	LOADK    	46 -212	; "\226\128\166"
	329	[82]	SETLIST  	38 8 1	; 1
	330	[82]	NEWTABLE 	39 8 0
	331	[83]	LOADK    	40 -213	; "\208\152"
	332	[83]	LOADK    	41 -214	; "\208\184"
	333	[83]	LOADK    	42 -215	; "?"
	334	[83]	LOADK    	43 -215	; "?"
	335	[83]	LOADK    	44 -216	; "\206\146"
	336	[83]	LOADK    	45 -217	; "\206\178"
	337	[83]	LOADK    	46 -218	; "\226\136\133"
	338	[83]	LOADK    	47 -219	; "\194\191"
	339	[83]	SETLIST  	39 8 1	; 1
	340	[83]	NEWTABLE 	40 8 0
	341	[84]	LOADK    	41 -220	; "\208\162"
	342	[84]	LOADK    	42 -221	; "\209\130"
	343	[84]	LOADK    	43 -222	; "!"
	344	[84]	LOADK    	44 -222	; "!"
	345	[84]	LOADK    	45 -223	; "\206\157"
	346	[84]	LOADK    	46 -224	; "\206\189"
	347	[84]	LOADK    	47 -225	; "\226\136\128"
	348	[84]	LOADK    	48 -226	; "\194\161"
	349	[84]	SETLIST  	40 8 1	; 1
	350	[84]	NEWTABLE 	41 8 0
	351	[85]	MOVE     	42 10
	352	[85]	MOVE     	43 11
	353	[85]	LOADK    	44 -227	; "\226\128\153"
	354	[85]	LOADK    	45 -227	; "\226\128\153"
	355	[85]	LOADK    	46 -228	; "\206\156"
	356	[85]	LOADK    	47 -229	; "\206\188"
	357	[85]	LOADK    	48 -230	; "\226\136\131"
	358	[85]	LOADK    	49 -231	; "\226\136\157"
	359	[85]	SETLIST  	41 8 1	; 1
	360	[85]	NEWTABLE 	42 8 0
	361	[86]	LOADK    	43 -232	; "\208\145"
	362	[86]	LOADK    	44 -233	; "\208\177"
	363	[86]	LOADK    	45 -234	; "\226\134\145"
	364	[86]	LOADK    	46 -234	; "\226\134\145"
	365	[86]	LOADK    	47 -144	; "\226\137\136"
	366	[86]	LOADK    	48 -144	; "\226\137\136"
	367	[86]	LOADK    	49 -234	; "\226\134\145"
	368	[86]	LOADK    	50 -234	; "\226\134\145"
	369	[86]	SETLIST  	42 8 1	; 1
	370	[86]	NEWTABLE 	43 8 0
	371	[87]	LOADK    	44 -235	; "\208\174"
	372	[87]	LOADK    	45 -236	; "\209\142"
	373	[87]	LOADK    	46 -237	; "|"
	374	[87]	LOADK    	47 -237	; "|"
	375	[87]	LOADK    	48 -238	; "\226\136\135"
	376	[87]	LOADK    	49 -238	; "\226\136\135"
	377	[87]	LOADK    	50 -237	; "|"
	378	[87]	LOADK    	51 -237	; "|"
	379	[87]	SETLIST  	43 8 1	; 1
	380	[87]	NEWTABLE 	44 0 3
	381	[88]	SETTABLE 	44 -239 -240	; "label" "\238\157\173"
	382	[89]	SETTABLE 	44 -186 -32	; "width" 1
	383	[90]	SETTABLE 	44 -241 -242	; "bold" false
	384	[92]	SETLIST  	33 11 1	; 1
	385	[92]	NEWTABLE 	34 8 0
	386	[94]	NEWTABLE 	35 8 1
	387	[95]	LOADK    	36 -41	; "123"
	388	[95]	LOADK    	37 -41	; "123"
	389	[95]	LOADK    	38 -42	; "\208\144\208\145\208\146"
	390	[95]	LOADK    	39 -42	; "\208\144\208\145\208\146"
	391	[95]	LOADK    	40 -43	; "\208\181\209\137\209\145"
	392	[95]	LOADK    	41 -43	; "\208\181\209\137\209\145"
	393	[95]	LOADK    	42 -43	; "\208\181\209\137\209\145"
	394	[95]	LOADK    	43 -43	; "\208\181\209\137\209\145"
	395	[96]	SETTABLE 	35 -186 -32	; "width" 1
	396	[96]	SETLIST  	35 8 1	; 1
	397	[96]	NEWTABLE 	36 0 1
	398	[97]	SETTABLE 	36 -239 -45	; "label" "\240\159\140\144"
	399	[97]	NEWTABLE 	37 8 0
	400	[98]	LOADK    	38 -47	; "\206\177\206\178\206\179"
	401	[98]	LOADK    	39 -47	; "\206\177\206\178\206\179"
	402	[98]	LOADK    	40 -47	; "\206\177\206\178\206\179"
	403	[98]	LOADK    	41 -47	; "\206\177\206\178\206\179"
	404	[98]	LOADK    	42 -47	; "\206\177\206\178\206\179"
	405	[98]	LOADK    	43 -47	; "\206\177\206\178\206\179"
	406	[98]	LOADK    	44 -47	; "\206\177\206\178\206\179"
	407	[98]	LOADK    	45 -47	; "\206\177\206\178\206\179"
	408	[98]	SETLIST  	37 8 1	; 1
	409	[98]	NEWTABLE 	38 8 2
	410	[99]	SETTABLE 	38 -239 -243	; "label" "\208\191\209\128\208\190\208\177\208\181\208\187"
	411	[100]	LOADK    	39 -244	; " "
	412	[100]	LOADK    	40 -244	; " "
	413	[100]	LOADK    	41 -244	; " "
	414	[100]	LOADK    	42 -244	; " "
	415	[100]	LOADK    	43 -244	; " "
	416	[100]	LOADK    	44 -244	; " "
	417	[100]	LOADK    	45 -244	; " "
	418	[100]	LOADK    	46 -244	; " "
	419	[101]	SETTABLE 	38 -186 -245	; "width" 4
	420	[101]	SETLIST  	38 8 1	; 1
	421	[101]	NEWTABLE 	39 8 0
	422	[102]	MOVE     	40 28
	423	[102]	MOVE     	41 28
	424	[102]	LOADK    	42 -246	; "\226\134\144"
	425	[102]	LOADK    	43 -246	; "\226\134\144"
	426	[102]	MOVE     	44 28
	427	[102]	MOVE     	45 28
	428	[102]	LOADK    	46 -246	; "\226\134\144"
	429	[102]	LOADK    	47 -246	; "\226\134\144"
	430	[102]	SETLIST  	39 8 1	; 1
	431	[102]	NEWTABLE 	40 8 0
	432	[103]	MOVE     	41 2
	433	[103]	MOVE     	42 2
	434	[103]	LOADK    	43 -247	; "\226\134\147"
	435	[103]	LOADK    	44 -247	; "\226\134\147"
	436	[103]	MOVE     	45 2
	437	[103]	MOVE     	46 2
	438	[103]	LOADK    	47 -247	; "\226\134\147"
	439	[103]	LOADK    	48 -247	; "\226\134\147"
	440	[103]	SETLIST  	40 8 1	; 1
	441	[103]	NEWTABLE 	41 8 0
	442	[104]	MOVE     	42 3
	443	[104]	MOVE     	43 3
	444	[104]	LOADK    	44 -248	; "\226\134\146"
	445	[104]	LOADK    	45 -248	; "\226\134\146"
	446	[104]	MOVE     	46 3
	447	[104]	MOVE     	47 3
	448	[104]	LOADK    	48 -248	; "\226\134\146"
	449	[104]	LOADK    	49 -248	; "\226\134\146"
	450	[104]	SETLIST  	41 8 1	; 1
	451	[104]	NEWTABLE 	42 8 3
	452	[105]	SETTABLE 	42 -239 -249	; "label" "\226\174\160"
	453	[106]	LOADK    	43 -250	; "\n"
	454	[106]	LOADK    	44 -250	; "\n"
	455	[106]	LOADK    	45 -250	; "\n"
	456	[106]	LOADK    	46 -250	; "\n"
	457	[106]	LOADK    	47 -250	; "\n"
	458	[106]	LOADK    	48 -250	; "\n"
	459	[106]	LOADK    	49 -250	; "\n"
	460	[106]	LOADK    	50 -250	; "\n"
	461	[107]	SETTABLE 	42 -186 -32	; "width" 1
	462	[108]	SETTABLE 	42 -241 -37	; "bold" true
	463	[109]	SETLIST  	42 8 1	; 1
	464	[110]	SETLIST  	34 8 1	; 1
	465	[111]	SETLIST  	30 4 1	; 1
	466	[111]	SETTABLE 	29 -48 30	; "keys" -
	467	[112]	RETURN   	29 2
	468	[112]	RETURN   	0 1
