-- BYTECODE -- ru_keyboard.lua:0-113
0001    GGET     0   0      ; "require"
0002    KSTR     1   1      ; "ui/data/keyboardlayouts/keypopup/en_popu"~
0003    CALL     0   2   2
0004    GGET     1   0      ; "require"
0005    KSTR     2   2      ; "ui/data/keyboardlayouts/keypopup/ru_popu"~
0006    CALL     1   2   2
0007    TGETS    2   0   3  ; "com"
0008    TGETS    3   0   4  ; "prd"
0009    TGETS    4   0   5  ; "_at"
0010    TGETS    5   0   6  ; "_eq"
0011    TGETS    6   1   7  ; "_Je_"
0012    TGETS    7   1   8  ; "_je_"
0013    TGETS    8   1   9  ; "_Ye_"
0014    TGETS    9   1  10  ; "_ye_"
0015    TGETS   10   1  11  ; "_SH_"
0016    TGETS   11   1  12  ; "_sh_"
0017    TGETS   12   1  13  ; "_KA_"
0018    TGETS   13   1  14  ; "_ka_"
0019    TGETS   14   1  15  ; "_KI_"
0020    TGETS   15   1  16  ; "_ki_"
0021    TGETS   16   1  17  ; "_KN_"
0022    TGETS   17   1  18  ; "_kn_"
0023    TGETS   18   1  19  ; "_KG_"
0024    TGETS   19   1  20  ; "_kg_"
0025    TGETS   20   1  21  ; "_KU_"
0026    TGETS   21   1  22  ; "_ku_"
0027    TGETS   22   1  23  ; "_KK_"
0028    TGETS   23   1  24  ; "_kk_"
0029    TGETS   24   1  25  ; "_KO_"
0030    TGETS   25   1  26  ; "_ko_"
0031    TGETS   26   1  27  ; "_KH_"
0032    TGETS   27   1  28  ; "_kh_"
0033    TGETS   28   1  29  ; "_qe_"
0034    TDUP    29  30
0035    TDUP    30  31
0036    TSETS   30  29  32  ; "shiftmode_keys"
0037    TDUP    30  33
0038    TSETS   30  29  34  ; "symbolmode_keys"
0039    TDUP    30  35
0040    TSETS   30  29  36  ; "utf8mode_keys"
0041    TDUP    30  37
0042    TSETS   30  29  38  ; "umlautmode_keys"
0043    TNEW    30   5
0044    TNEW    31  12
0045    TDUP    32  39
0046    TSETB   32  31   1
0047    TDUP    32  40
0048    TSETB   32  31   2
0049    TDUP    32  41
0050    TSETB   20  32   1
0051    TSETB   21  32   2
0052    TSETB   32  31   3
0053    TDUP    32  42
0054    TSETB   22  32   1
0055    TSETB   23  32   2
0056    TSETB   32  31   4
0057    TDUP    32  43
0058    TSETB    8  32   1
0059    TSETB    9  32   2
0060    TSETB   32  31   5
0061    TDUP    32  44
0062    TSETB   16  32   1
0063    TSETB   17  32   2
0064    TSETB   32  31   6
0065    TDUP    32  45
0066    TSETB   18  32   1
0067    TSETB   19  32   2
0068    TSETB   32  31   7
0069    TDUP    32  46
0070    TSETB   32  31   8
0071    TDUP    32  47
0072    TSETB   32  31   9
0073    TDUP    32  48
0074    TSETB   32  31  10
0075    TDUP    32  49
0076    TSETB   26  32   1
0077    TSETB   27  32   2
0078    TSETB    5  32   3
0079    TSETB   32  31  11
0080    TSETB   31  30   1
0081    TNEW    31  12
0082    TDUP    32  50
0083    TSETB   32  31   1
0084    TDUP    32  51
0085    TSETB   14  32   1
0086    TSETB   15  32   2
0087    TSETB   32  31   2
0088    TDUP    32  52
0089    TSETB   32  31   3
0090    TDUP    32  53
0091    TSETB   12  32   1
0092    TSETB   13  32   2
0093    TSETB   32  31   4
0094    TDUP    32  54
0095    TSETB   32  31   5
0096    TDUP    32  55
0097    TSETB   32  31   6
0098    TDUP    32  56
0099    TSETB   24  32   1
0100    TSETB   25  32   2
0101    TSETB   32  31   7
0102    TDUP    32  57
0103    TSETB   32  31   8
0104    TDUP    32  58
0105    TSETB   32  31   9
0106    TDUP    32  59
0107    TSETB    6  32   1
0108    TSETB    7  32   2
0109    TSETB    4  32   4
0110    TSETB   32  31  10
0111    TDUP    32  60
0112    TSETB   32  31  11
0113    TSETB   31  30   2
0114    TNEW    31  12
0115    TDUP    32  61
0116    TSETB   32  31   1
0117    TDUP    32  62
0118    TSETB   32  31   2
0119    TDUP    32  63
0120    TSETB   32  31   3
0121    TDUP    32  64
0122    TSETB    2  32   3
0123    TSETB    2  32   4
0124    TSETB   32  31   4
0125    TDUP    32  65
0126    TSETB    3  32   3
0127    TSETB    3  32   4
0128    TSETB   32  31   5
0129    TDUP    32  66
0130    TSETB   32  31   6
0131    TDUP    32  67
0132    TSETB   32  31   7
0133    TDUP    32  68
0134    TSETB   10  32   1
0135    TSETB   11  32   2
0136    TSETB   32  31   8
0137    TDUP    32  69
0138    TSETB   32  31   9
0139    TDUP    32  70
0140    TSETB   32  31  10
0141    TDUP    32  71
0142    TSETB   32  31  11
0143    TSETB   31  30   3
0144    TNEW    31   9
0145    TDUP    32  72
0146    TSETB   32  31   1
0147    TDUP    32  73
0148    TSETB   32  31   2
0149    TDUP    32  74
0150    TSETB   32  31   3
0151    TDUP    32  75
0152    TSETB   32  31   4
0153    TDUP    32  76
0154    TSETB   28  32   1
0155    TSETB   28  32   2
0156    TSETB   28  32   5
0157    TSETB   28  32   6
0158    TSETB   32  31   5
0159    TDUP    32  77
0160    TSETB    2  32   1
0161    TSETB    2  32   2
0162    TSETB    2  32   5
0163    TSETB    2  32   6
0164    TSETB   32  31   6
0165    TDUP    32  78
0166    TSETB    3  32   1
0167    TSETB    3  32   2
0168    TSETB    3  32   5
0169    TSETB    3  32   6
0170    TSETB   32  31   7
0171    TDUP    32  79
0172    TSETB   32  31   8
0173    TSETB   31  30   4
0174    TSETS   30  29  80  ; "keys"
0175    RET1    29   2

