
main <./frontend/ui/elements/screen_disable_double_tap_table.lua:0,0> (23 instructions, 92 bytes at 0x7fa5b4406920)
0+ params, 6 slots, 0 upvalues, 3 locals, 8 constants, 2 functions
	1	[1]	GETGLOBAL	0 -1	; require
	2	[1]	LOADK    	1 -2	; "ui/widget/infomessage"
	3	[1]	CALL     	0 2 2
	4	[2]	GETGLOBAL	1 -1	; require
	5	[2]	LOADK    	2 -3	; "ui/uimanager"
	6	[2]	CALL     	1 2 2
	7	[3]	GETGLOBAL	2 -1	; require
	8	[3]	LOADK    	3 -4	; "gettext"
	9	[3]	CALL     	2 2 2
	10	[5]	NEWTABLE 	3 0 3
	11	[6]	MOVE     	4 2
	12	[6]	LOADK    	5 -6	; "Disable double tap"
	13	[6]	CALL     	4 2 2
	14	[6]	SETTABLE 	3 -5 4	; "text" -
	15	[9]	CLOSURE  	4 0	; 0x7fa5b4406ff0
	16	[9]	SETTABLE 	3 -7 4	; "checked_func" -
	17	[16]	CLOSURE  	4 1	; 0x7fa5b4407370
	18	[16]	MOVE     	0 1
	19	[16]	MOVE     	0 0
	20	[16]	MOVE     	0 2
	21	[16]	SETTABLE 	3 -8 4	; "callback" -
	22	[17]	RETURN   	3 2
	23	[17]	RETURN   	0 1

function <./frontend/ui/elements/screen_disable_double_tap_table.lua:7,9> (10 instructions, 40 bytes at 0x7fa5b4406ff0)
0 params, 3 slots, 0 upvalues, 0 locals, 4 constants, 0 functions
	1	[8]	GETGLOBAL	0 -1	; G_reader_settings
	2	[8]	SELF     	0 0 -2	; "readSetting"
	3	[8]	LOADK    	2 -3	; "disable_double_tap"
	4	[8]	CALL     	0 3 2
	5	[8]	EQ       	0 0 -4	; - false
	6	[8]	JMP      	1	; to 8
	7	[8]	LOADBOOL 	0 0 1
	8	[8]	LOADBOOL 	0 1 0
	9	[8]	RETURN   	0 2
	10	[9]	RETURN   	0 1

function <./frontend/ui/elements/screen_disable_double_tap_table.lua:10,16> (25 instructions, 100 bytes at 0x7fa5b4407370)
0 params, 8 slots, 3 upvalues, 1 local, 9 constants, 0 functions
	1	[11]	GETGLOBAL	0 -1	; G_reader_settings
	2	[11]	SELF     	0 0 -2	; "readSetting"
	3	[11]	LOADK    	2 -3	; "disable_double_tap"
	4	[11]	CALL     	0 3 2
	5	[11]	EQ       	0 0 -4	; - false
	6	[11]	JMP      	1	; to 8
	7	[11]	LOADBOOL 	0 0 1
	8	[11]	LOADBOOL 	0 1 0
	9	[12]	GETGLOBAL	1 -1	; G_reader_settings
	10	[12]	SELF     	1 1 -5	; "saveSetting"
	11	[12]	LOADK    	3 -3	; "disable_double_tap"
	12	[12]	NOT      	4 0
	13	[12]	CALL     	1 4 1
	14	[13]	GETUPVAL 	1 0	; UIManager
	15	[13]	SELF     	1 1 -6	; "show"
	16	[13]	GETUPVAL 	3 1	; InfoMessage
	17	[13]	SELF     	3 3 -7	; "new"
	18	[13]	NEWTABLE 	5 0 1
	19	[14]	GETUPVAL 	6 2	; _
	20	[14]	LOADK    	7 -9	; "This will take effect on next restart."
	21	[14]	CALL     	6 2 2
	22	[14]	SETTABLE 	5 -8 6	; "text" -
	23	[13]	CALL     	3 3 0
	24	[13]	CALL     	1 0 1
	25	[16]	RETURN   	0 1
