
main <./frontend/ui/screensaver.lua:0,0> (155 instructions, 620 bytes at 0x7fe6644068c0)
0+ params, 28 slots, 0 upvalues, 27 locals, 44 constants, 12 functions
	1	[1]	GETGLOBAL	0 -1	; require
	2	[1]	LOADK    	1 -2	; "ui/bidi"
	3	[1]	CALL     	0 2 2
	4	[2]	GETGLOBAL	1 -1	; require
	5	[2]	LOADK    	2 -3	; "ffi/blitbuffer"
	6	[2]	CALL     	1 2 2
	7	[3]	GETGLOBAL	2 -1	; require
	8	[3]	LOADK    	3 -4	; "ui/widget/buttondialogtitle"
	9	[3]	CALL     	2 2 2
	10	[4]	GETGLOBAL	3 -1	; require
	11	[4]	LOADK    	4 -5	; "ui/widget/bookstatuswidget"
	12	[4]	CALL     	3 2 2
	13	[5]	GETGLOBAL	4 -1	; require
	14	[5]	LOADK    	5 -6	; "ui/widget/container/bottomcontainer"
	15	[5]	CALL     	4 2 2
	16	[6]	GETGLOBAL	5 -1	; require
	17	[6]	LOADK    	6 -7	; "datastorage"
	18	[6]	CALL     	5 2 2
	19	[7]	GETGLOBAL	6 -1	; require
	20	[7]	LOADK    	7 -8	; "device"
	21	[7]	CALL     	6 2 2
	22	[8]	GETGLOBAL	7 -1	; require
	23	[8]	LOADK    	8 -9	; "docsettings"
	24	[8]	CALL     	7 2 2
	25	[9]	GETGLOBAL	8 -1	; require
	26	[9]	LOADK    	9 -10	; "document/documentregistry"
	27	[9]	CALL     	8 2 2
	28	[10]	GETGLOBAL	9 -1	; require
	29	[10]	LOADK    	10 -11	; "ui/font"
	30	[10]	CALL     	9 2 2
	31	[11]	GETGLOBAL	10 -1	; require
	32	[11]	LOADK    	11 -12	; "ui/geometry"
	33	[11]	CALL     	10 2 2
	34	[12]	GETGLOBAL	11 -1	; require
	35	[12]	LOADK    	12 -13	; "ui/widget/infomessage"
	36	[12]	CALL     	11 2 2
	37	[13]	GETGLOBAL	12 -1	; require
	38	[13]	LOADK    	13 -14	; "ui/widget/imagewidget"
	39	[13]	CALL     	12 2 2
	40	[14]	GETGLOBAL	13 -1	; require
	41	[14]	LOADK    	14 -15	; "optmath"
	42	[14]	CALL     	13 2 2
	43	[15]	GETGLOBAL	14 -1	; require
	44	[15]	LOADK    	15 -16	; "ui/widget/screensaverwidget"
	45	[15]	CALL     	14 2 2
	46	[16]	GETGLOBAL	15 -1	; require
	47	[16]	LOADK    	16 -17	; "ui/widget/textboxwidget"
	48	[16]	CALL     	15 2 2
	49	[17]	GETGLOBAL	16 -1	; require
	50	[17]	LOADK    	17 -18	; "ui/widget/container/topcontainer"
	51	[17]	CALL     	16 2 2
	52	[18]	GETGLOBAL	17 -1	; require
	53	[18]	LOADK    	18 -19	; "ui/uimanager"
	54	[18]	CALL     	17 2 2
	55	[19]	GETGLOBAL	18 -1	; require
	56	[19]	LOADK    	19 -20	; "libs/libkoreader-lfs"
	57	[19]	CALL     	18 2 2
	58	[20]	GETGLOBAL	19 -1	; require
	59	[20]	LOADK    	20 -21	; "logger"
	60	[20]	CALL     	19 2 2
	61	[21]	GETGLOBAL	20 -1	; require
	62	[21]	LOADK    	21 -22	; "gettext"
	63	[21]	CALL     	20 2 2
	64	[22]	GETTABLE 	21 6 -23	; "screen"
	65	[23]	GETGLOBAL	22 -1	; require
	66	[23]	LOADK    	23 -24	; "ffi/util"
	67	[23]	CALL     	22 2 2
	68	[23]	GETTABLE 	22 22 -25	; "template"
	69	[25]	NEWTABLE 	23 0 6
	70	[26]	SETTABLE 	23 -26 -27	; "jpg" true
	71	[27]	SETTABLE 	23 -28 -27	; "jpeg" true
	72	[28]	SETTABLE 	23 -29 -27	; "png" true
	73	[29]	SETTABLE 	23 -30 -27	; "gif" true
	74	[30]	SETTABLE 	23 -31 -27	; "tif" true
	75	[31]	SETTABLE 	23 -32 -27	; "tiff" true
	76	[33]	MOVE     	24 20
	77	[33]	LOADK    	25 -33	; "Sleeping"
	78	[33]	CALL     	24 2 2
	79	[34]	NEWTABLE 	25 0 0
	80	[61]	CLOSURE  	26 0	; 0x7fe664407050
	81	[61]	MOVE     	0 18
	82	[61]	MOVE     	0 23
	83	[100]	CLOSURE  	27 1	; 0x7fe664407eb0
	84	[100]	MOVE     	0 20
	85	[100]	MOVE     	0 17
	86	[100]	MOVE     	0 19
	87	[100]	MOVE     	0 11
	88	[100]	MOVE     	0 22
	89	[100]	MOVE     	0 0
	90	[100]	MOVE     	0 5
	91	[100]	MOVE     	0 2
	92	[63]	SETTABLE 	25 -34 27	; "chooseFolder" -
	93	[165]	CLOSURE  	27 2	; 0x7fe664408730
	94	[165]	MOVE     	0 20
	95	[165]	MOVE     	0 17
	96	[165]	MOVE     	0 8
	97	[165]	MOVE     	0 23
	98	[165]	MOVE     	0 11
	99	[165]	MOVE     	0 22
	100	[165]	MOVE     	0 0
	101	[165]	MOVE     	0 5
	102	[165]	MOVE     	0 2
	103	[102]	SETTABLE 	25 -35 27	; "chooseFile" -
	104	[169]	CLOSURE  	27 3	; 0x7fe66440a110
	105	[167]	SETTABLE 	25 -36 27	; "stretchImages" -
	106	[173]	CLOSURE  	27 4	; 0x7fe66440b630
	107	[171]	SETTABLE 	25 -37 27	; "whiteBackground" -
	108	[177]	CLOSURE  	27 5	; 0x7fe66440bd40
	109	[175]	SETTABLE 	25 -38 27	; "noBackground" -
	110	[187]	CLOSURE  	27 6	; 0x7fe66440c020
	111	[187]	MOVE     	0 7
	112	[179]	SETTABLE 	25 -39 27	; "excluded" -
	113	[220]	CLOSURE  	27 7	; 0x7fe66440c590
	114	[220]	MOVE     	0 24
	115	[220]	MOVE     	0 20
	116	[220]	MOVE     	0 17
	117	[189]	SETTABLE 	25 -40 27	; "setMessage" -
	118	[432]	CLOSURE  	27 8	; 0x7fe66440c660
	119	[432]	MOVE     	0 17
	120	[432]	MOVE     	0 1
	121	[432]	MOVE     	0 7
	122	[432]	MOVE     	0 18
	123	[432]	MOVE     	0 8
	124	[432]	MOVE     	0 12
	125	[432]	MOVE     	0 21
	126	[432]	MOVE     	0 3
	127	[432]	MOVE     	0 5
	128	[432]	MOVE     	0 26
	129	[432]	MOVE     	0 25
	130	[432]	MOVE     	0 24
	131	[432]	MOVE     	0 11
	132	[432]	MOVE     	0 9
	133	[432]	MOVE     	0 4
	134	[432]	MOVE     	0 16
	135	[432]	MOVE     	0 10
	136	[432]	MOVE     	0 15
	137	[432]	MOVE     	0 14
	138	[222]	SETTABLE 	25 -41 27	; "show" -
	139	[464]	CLOSURE  	27 9	; 0x7fe664407630
	140	[464]	MOVE     	0 18
	141	[464]	MOVE     	0 8
	142	[464]	MOVE     	0 13
	143	[434]	SETTABLE 	25 -42 27	; "expandSpecial" -
	144	[487]	CLOSURE  	27 10	; 0x7fe664407800
	145	[487]	MOVE     	0 17
	146	[487]	MOVE     	0 19
	147	[466]	SETTABLE 	25 -43 27	; "close" -
	148	[534]	CLOSURE  	27 11	; 0x7fe66440e1b0
	149	[534]	MOVE     	0 9
	150	[534]	MOVE     	0 21
	151	[534]	MOVE     	0 15
	152	[534]	MOVE     	0 1
	153	[489]	SETTABLE 	25 -44 27	; "addOverlayMessage" -
	154	[536]	RETURN   	25 2
	155	[536]	RETURN   	0 1

function <./frontend/ui/screensaver.lua:36,61> (76 instructions, 304 bytes at 0x7fe664407050)
1 param, 14 slots, 2 upvalues, 11 locals, 20 constants, 0 functions
	1	[37]	GETGLOBAL	1 -1	; string
	2	[37]	GETTABLE 	1 1 -2	; "sub"
	3	[37]	MOVE     	2 0
	4	[37]	GETGLOBAL	3 -1	; string
	5	[37]	GETTABLE 	3 3 -3	; "len"
	6	[37]	MOVE     	4 0
	7	[37]	CALL     	3 2 0
	8	[37]	CALL     	1 0 2
	9	[37]	EQ       	1 1 -4	; - "/"
	10	[37]	JMP      	3	; to 14
	11	[38]	MOVE     	1 0
	12	[38]	LOADK    	2 -4	; "/"
	13	[38]	CONCAT   	0 1 2
	14	[40]	NEWTABLE 	1 0 0
	15	[41]	LOADK    	2 -5	; 0
	16	[42]	GETGLOBAL	3 -6	; math
	17	[42]	GETTABLE 	3 3 -7	; "randomseed"
	18	[42]	GETGLOBAL	4 -8	; os
	19	[42]	GETTABLE 	4 4 -9	; "time"
	20	[42]	CALL     	4 1 0
	21	[42]	CALL     	3 0 1
	22	[43]	GETGLOBAL	3 -10	; pcall
	23	[43]	GETUPVAL 	4 0	; lfs
	24	[43]	GETTABLE 	4 4 -11	; "dir"
	25	[43]	MOVE     	5 0
	26	[43]	CALL     	3 3 4
	27	[44]	TEST     	3 0 0
	28	[44]	JMP      	37	; to 66
	29	[45]	MOVE     	6 4
	30	[45]	MOVE     	7 5
	31	[45]	LOADNIL  	8 8
	32	[45]	JMP      	26	; to 59
	33	[46]	GETUPVAL 	10 0	; lfs
	34	[46]	GETTABLE 	10 10 -12	; "attributes"
	35	[46]	MOVE     	11 0
	36	[46]	MOVE     	12 9
	37	[46]	CONCAT   	11 11 12
	38	[46]	LOADK    	12 -13	; "mode"
	39	[46]	CALL     	10 3 2
	40	[46]	EQ       	0 10 -14	; - "file"
	41	[46]	JMP      	17	; to 59
	42	[47]	GETGLOBAL	10 -1	; string
	43	[47]	GETTABLE 	10 10 -15	; "lower"
	44	[47]	GETGLOBAL	11 -1	; string
	45	[47]	GETTABLE 	11 11 -16	; "match"
	46	[47]	MOVE     	12 9
	47	[47]	LOADK    	13 -17	; ".+%.([^.]+)"
	48	[47]	CALL     	11 3 2
	49	[47]	TEST     	11 0 1
	50	[47]	JMP      	1	; to 52
	51	[47]	LOADK    	11 -18	; ""
	52	[47]	CALL     	10 2 2
	53	[48]	GETUPVAL 	11 1	; screensaver_provider
	54	[48]	GETTABLE 	11 11 10
	55	[48]	TEST     	11 0 0
	56	[48]	JMP      	2	; to 59
	57	[49]	ADD      	2 2 -19	; - 1
	58	[50]	SETTABLE 	1 2 9
	59	[45]	TFORLOOP 	6 1
	60	[52]	JMP      	-28	; to 33
	61	[54]	EQ       	0 2 -5	; - 0
	62	[54]	JMP      	5	; to 68
	63	[55]	LOADNIL  	6 6
	64	[55]	RETURN   	6 2
	65	[56]	JMP      	2	; to 68
	66	[58]	LOADNIL  	6 6
	67	[58]	RETURN   	6 2
	68	[60]	MOVE     	6 0
	69	[60]	GETGLOBAL	7 -6	; math
	70	[60]	GETTABLE 	7 7 -20	; "random"
	71	[60]	MOVE     	8 2
	72	[60]	CALL     	7 2 2
	73	[60]	GETTABLE 	7 1 7
	74	[60]	CONCAT   	6 6 7
	75	[60]	RETURN   	6 2
	76	[61]	RETURN   	0 1

function <./frontend/ui/screensaver.lua:63,100> (68 instructions, 272 bytes at 0x7fe664407eb0)
1 param, 10 slots, 8 upvalues, 3 locals, 19 constants, 2 functions
	1	[64]	NEWTABLE 	1 0 0
	2	[65]	GETGLOBAL	2 -1	; table
	3	[65]	GETTABLE 	2 2 -2	; "insert"
	4	[65]	MOVE     	3 1
	5	[65]	NEWTABLE 	4 1 0
	6	[65]	NEWTABLE 	5 0 2
	7	[67]	GETUPVAL 	6 0	; _
	8	[67]	LOADK    	7 -4	; "Choose screensaver directory"
	9	[67]	CALL     	6 2 2
	10	[67]	SETTABLE 	5 -3 6	; "text" -
	11	[80]	CLOSURE  	6 0	; 0x7fe6644087b0
	12	[80]	GETUPVAL 	0 1	; UIManager
	13	[80]	MOVE     	0 0
	14	[80]	GETUPVAL 	0 2	; logger
	15	[80]	GETUPVAL 	0 3	; InfoMessage
	16	[80]	GETUPVAL 	0 4	; T
	17	[80]	GETUPVAL 	0 0	; _
	18	[80]	GETUPVAL 	0 5	; BD
	19	[80]	SETTABLE 	5 -5 6	; "callback" -
	20	[82]	SETLIST  	4 1 1	; 1
	21	[65]	CALL     	2 3 1
	22	[83]	GETGLOBAL	2 -1	; table
	23	[83]	GETTABLE 	2 2 -2	; "insert"
	24	[83]	MOVE     	3 1
	25	[83]	NEWTABLE 	4 1 0
	26	[83]	NEWTABLE 	5 0 2
	27	[85]	GETUPVAL 	6 0	; _
	28	[85]	LOADK    	7 -6	; "Close"
	29	[85]	CALL     	6 2 2
	30	[85]	SETTABLE 	5 -3 6	; "text" -
	31	[88]	CLOSURE  	6 1	; 0x7fe664409470
	32	[88]	GETUPVAL 	0 1	; UIManager
	33	[88]	MOVE     	0 0
	34	[88]	SETTABLE 	5 -5 6	; "callback" -
	35	[90]	SETLIST  	4 1 1	; 1
	36	[83]	CALL     	2 3 1
	37	[91]	GETGLOBAL	2 -7	; G_reader_settings
	38	[91]	SELF     	2 2 -8	; "readSetting"
	39	[91]	LOADK    	4 -9	; "screensaver_dir"
	40	[91]	CALL     	2 3 2
	41	[92]	EQ       	0 2 -10	; - nil
	42	[92]	JMP      	5	; to 48
	43	[93]	GETUPVAL 	3 6	; DataStorage
	44	[93]	SELF     	3 3 -11	; "getDataDir"
	45	[93]	CALL     	3 2 2
	46	[93]	LOADK    	4 -12	; "/screenshots/"
	47	[93]	CONCAT   	2 3 4
	48	[95]	GETUPVAL 	3 7	; ButtonDialogTitle
	49	[95]	SELF     	3 3 -14	; "new"
	50	[95]	NEWTABLE 	5 0 2
	51	[96]	GETUPVAL 	6 4	; T
	52	[96]	GETUPVAL 	7 0	; _
	53	[96]	LOADK    	8 -16	; "Current screensaver image directory:\n%1"
	54	[96]	CALL     	7 2 2
	55	[96]	GETUPVAL 	8 5	; BD
	56	[96]	GETTABLE 	8 8 -17	; "dirpath"
	57	[96]	MOVE     	9 2
	58	[96]	CALL     	8 2 0
	59	[96]	CALL     	6 0 2
	60	[96]	SETTABLE 	5 -15 6	; "title" -
	61	[97]	SETTABLE 	5 -18 1	; "buttons" -
	62	[95]	CALL     	3 3 2
	63	[98]	SETTABLE 	0 -13 3	; "choose_dialog" -
	64	[99]	GETUPVAL 	3 1	; UIManager
	65	[99]	SELF     	3 3 -19	; "show"
	66	[99]	GETTABLE 	5 0 -13	; "choose_dialog"
	67	[99]	CALL     	3 3 1
	68	[100]	RETURN   	0 1

function <./frontend/ui/screensaver.lua:68,80> (22 instructions, 88 bytes at 0x7fe6644087b0)
0 params, 4 slots, 7 upvalues, 0 locals, 7 constants, 1 function
	1	[69]	GETUPVAL 	0 0	; UIManager
	2	[69]	SELF     	0 0 -1	; "close"
	3	[69]	GETUPVAL 	2 1	; self
	4	[69]	GETTABLE 	2 2 -2	; "choose_dialog"
	5	[69]	CALL     	0 3 1
	6	[70]	GETGLOBAL	0 -3	; require
	7	[70]	LOADK    	1 -4	; "ui/downloadmgr"
	8	[70]	CALL     	0 2 2
	9	[70]	SELF     	0 0 -5	; "new"
	10	[70]	NEWTABLE 	2 0 1
	11	[78]	CLOSURE  	3 0	; 0x7fe664408c00
	12	[78]	GETUPVAL 	0 2	; logger
	13	[78]	GETUPVAL 	0 0	; UIManager
	14	[78]	GETUPVAL 	0 3	; InfoMessage
	15	[78]	GETUPVAL 	0 4	; T
	16	[78]	GETUPVAL 	0 5	; _
	17	[78]	GETUPVAL 	0 6	; BD
	18	[78]	SETTABLE 	2 -6 3	; "onConfirm" -
	19	[70]	CALL     	0 3 2
	20	[79]	SELF     	0 0 -7	; "chooseDir"
	21	[79]	CALL     	0 2 1
	22	[80]	RETURN   	0 1

function <./frontend/ui/screensaver.lua:71,78> (29 instructions, 116 bytes at 0x7fe664408c00)
1 param, 10 slots, 6 upvalues, 1 local, 12 constants, 0 functions
	1	[72]	GETUPVAL 	1 0	; logger
	2	[72]	GETTABLE 	1 1 -1	; "dbg"
	3	[72]	LOADK    	2 -2	; "set screensaver directory to"
	4	[72]	MOVE     	3 0
	5	[72]	CALL     	1 3 1
	6	[73]	GETGLOBAL	1 -3	; G_reader_settings
	7	[73]	SELF     	1 1 -4	; "saveSetting"
	8	[73]	LOADK    	3 -5	; "screensaver_dir"
	9	[73]	MOVE     	4 0
	10	[73]	CALL     	1 4 1
	11	[74]	GETUPVAL 	1 1	; UIManager
	12	[74]	SELF     	1 1 -6	; "show"
	13	[74]	GETUPVAL 	3 2	; InfoMessage
	14	[74]	SELF     	3 3 -7	; "new"
	15	[74]	NEWTABLE 	5 0 2
	16	[75]	GETUPVAL 	6 3	; T
	17	[75]	GETUPVAL 	7 4	; _
	18	[75]	LOADK    	8 -9	; "Screensaver directory set to:\n%1"
	19	[75]	CALL     	7 2 2
	20	[75]	GETUPVAL 	8 5	; BD
	21	[75]	GETTABLE 	8 8 -10	; "dirpath"
	22	[75]	MOVE     	9 0
	23	[75]	CALL     	8 2 0
	24	[75]	CALL     	6 0 2
	25	[75]	SETTABLE 	5 -8 6	; "text" -
	26	[76]	SETTABLE 	5 -11 -12	; "timeout" 3
	27	[74]	CALL     	3 3 0
	28	[74]	CALL     	1 0 1
	29	[78]	RETURN   	0 1

function <./frontend/ui/screensaver.lua:86,88> (6 instructions, 24 bytes at 0x7fe664409470)
0 params, 3 slots, 2 upvalues, 0 locals, 2 constants, 0 functions
	1	[87]	GETUPVAL 	0 0	; UIManager
	2	[87]	SELF     	0 0 -1	; "close"
	3	[87]	GETUPVAL 	2 1	; self
	4	[87]	GETTABLE 	2 2 -2	; "choose_dialog"
	5	[87]	CALL     	0 3 1
	6	[88]	RETURN   	0 1

function <./frontend/ui/screensaver.lua:102,165> (94 instructions, 376 bytes at 0x7fe664408730)
2 params, 10 slots, 9 upvalues, 7 locals, 22 constants, 2 functions
	1	[103]	TEST     	1 0 0
	2	[103]	JMP      	5	; to 8
	3	[103]	GETUPVAL 	2 0	; _
	4	[103]	LOADK    	3 -1	; "Choose document cover"
	5	[103]	CALL     	2 2 2
	6	[103]	TEST     	2 0 1
	7	[103]	JMP      	3	; to 11
	8	[103]	GETUPVAL 	2 0	; _
	9	[103]	LOADK    	3 -2	; "Choose screensaver image"
	10	[103]	CALL     	2 2 2
	11	[104]	NEWTABLE 	3 0 0
	12	[105]	GETGLOBAL	4 -3	; table
	13	[105]	GETTABLE 	4 4 -4	; "insert"
	14	[105]	MOVE     	5 3
	15	[105]	NEWTABLE 	6 1 0
	16	[105]	NEWTABLE 	7 0 2
	17	[107]	SETTABLE 	7 -5 2	; "text" -
	18	[142]	CLOSURE  	8 0	; 0x7fe66440a210
	19	[142]	GETUPVAL 	0 1	; UIManager
	20	[142]	MOVE     	0 0
	21	[142]	MOVE     	0 1
	22	[142]	GETUPVAL 	0 2	; DocumentRegistry
	23	[142]	GETUPVAL 	0 3	; screensaver_provider
	24	[142]	GETUPVAL 	0 4	; InfoMessage
	25	[142]	GETUPVAL 	0 5	; T
	26	[142]	GETUPVAL 	0 0	; _
	27	[142]	GETUPVAL 	0 6	; BD
	28	[142]	SETTABLE 	7 -6 8	; "callback" -
	29	[144]	SETLIST  	6 1 1	; 1
	30	[105]	CALL     	4 3 1
	31	[145]	GETGLOBAL	4 -3	; table
	32	[145]	GETTABLE 	4 4 -4	; "insert"
	33	[145]	MOVE     	5 3
	34	[145]	NEWTABLE 	6 1 0
	35	[145]	NEWTABLE 	7 0 2
	36	[147]	GETUPVAL 	8 0	; _
	37	[147]	LOADK    	9 -7	; "Close"
	38	[147]	CALL     	8 2 2
	39	[147]	SETTABLE 	7 -5 8	; "text" -
	40	[150]	CLOSURE  	8 1	; 0x7fe66440a190
	41	[150]	GETUPVAL 	0 1	; UIManager
	42	[150]	MOVE     	0 0
	43	[150]	SETTABLE 	7 -6 8	; "callback" -
	44	[152]	SETLIST  	6 1 1	; 1
	45	[145]	CALL     	4 3 1
	46	[153]	GETGLOBAL	4 -8	; G_reader_settings
	47	[153]	SELF     	4 4 -9	; "readSetting"
	48	[153]	LOADK    	6 -10	; "screensaver_image"
	49	[153]	CALL     	4 3 2
	50	[154]	GETGLOBAL	5 -8	; G_reader_settings
	51	[154]	SELF     	5 5 -9	; "readSetting"
	52	[154]	LOADK    	7 -11	; "screensaver_document_cover"
	53	[154]	CALL     	5 3 2
	54	[155]	EQ       	0 4 -12	; - nil
	55	[155]	JMP      	5	; to 61
	56	[156]	GETUPVAL 	6 7	; DataStorage
	57	[156]	SELF     	6 6 -13	; "getDataDir"
	58	[156]	CALL     	6 2 2
	59	[156]	LOADK    	7 -14	; "/resources/koreader.png"
	60	[156]	CONCAT   	4 6 7
	61	[158]	TEST     	1 0 0
	62	[158]	JMP      	11	; to 74
	63	[158]	GETUPVAL 	6 5	; T
	64	[158]	GETUPVAL 	7 0	; _
	65	[158]	LOADK    	8 -15	; "Current screensaver document cover:\n%1"
	66	[158]	CALL     	7 2 2
	67	[158]	GETUPVAL 	8 6	; BD
	68	[158]	GETTABLE 	8 8 -16	; "filepath"
	69	[158]	MOVE     	9 5
	70	[158]	CALL     	8 2 0
	71	[158]	CALL     	6 0 2
	72	[159]	TEST     	6 0 1
	73	[159]	JMP      	9	; to 83
	74	[159]	GETUPVAL 	6 5	; T
	75	[159]	GETUPVAL 	7 0	; _
	76	[159]	LOADK    	8 -17	; "Current screensaver image:\n%1"
	77	[159]	CALL     	7 2 2
	78	[159]	GETUPVAL 	8 6	; BD
	79	[159]	GETTABLE 	8 8 -16	; "filepath"
	80	[159]	MOVE     	9 4
	81	[159]	CALL     	8 2 0
	82	[159]	CALL     	6 0 2
	83	[160]	GETUPVAL 	7 8	; ButtonDialogTitle
	84	[160]	SELF     	7 7 -19	; "new"
	85	[160]	NEWTABLE 	9 0 2
	86	[161]	SETTABLE 	9 -20 6	; "title" -
	87	[162]	SETTABLE 	9 -21 3	; "buttons" -
	88	[160]	CALL     	7 3 2
	89	[163]	SETTABLE 	0 -18 7	; "choose_dialog" -
	90	[164]	GETUPVAL 	7 1	; UIManager
	91	[164]	SELF     	7 7 -22	; "show"
	92	[164]	GETTABLE 	9 0 -18	; "choose_dialog"
	93	[164]	CALL     	7 3 1
	94	[165]	RETURN   	0 1

function <./frontend/ui/screensaver.lua:108,142> (39 instructions, 156 bytes at 0x7fe66440a210)
0 params, 6 slots, 9 upvalues, 3 locals, 16 constants, 2 functions
	1	[109]	GETUPVAL 	0 0	; UIManager
	2	[109]	SELF     	0 0 -1	; "close"
	3	[109]	GETUPVAL 	2 1	; self
	4	[109]	GETTABLE 	2 2 -2	; "choose_dialog"
	5	[109]	CALL     	0 3 1
	6	[110]	GETGLOBAL	0 -3	; require
	7	[110]	LOADK    	1 -4	; "util"
	8	[110]	CALL     	0 2 2
	9	[111]	GETGLOBAL	1 -3	; require
	10	[111]	LOADK    	2 -5	; "ui/widget/pathchooser"
	11	[111]	CALL     	1 2 2
	12	[112]	SELF     	2 1 -6	; "new"
	13	[112]	NEWTABLE 	4 0 6
	14	[113]	SETTABLE 	4 -7 -8	; "select_directory" false
	15	[114]	SETTABLE 	4 -9 -10	; "select_file" true
	16	[122]	CLOSURE  	5 0	; 0x7fe66440a330
	17	[122]	MOVE     	0 0
	18	[122]	GETUPVAL 	0 2	; document_cover
	19	[122]	GETUPVAL 	0 3	; DocumentRegistry
	20	[122]	GETUPVAL 	0 4	; screensaver_provider
	21	[122]	SETTABLE 	4 -11 5	; "file_filter" -
	22	[123]	SETTABLE 	4 -12 -10	; "detailed_file_info" true
	23	[124]	GETUPVAL 	5 1	; self
	24	[124]	GETTABLE 	5 5 -14	; "root_path"
	25	[124]	SETTABLE 	4 -13 5	; "path" -
	26	[139]	CLOSURE  	5 1	; 0x7fe66440ac70
	27	[139]	GETUPVAL 	0 2	; document_cover
	28	[139]	GETUPVAL 	0 0	; UIManager
	29	[139]	GETUPVAL 	0 5	; InfoMessage
	30	[139]	GETUPVAL 	0 6	; T
	31	[139]	GETUPVAL 	0 7	; _
	32	[139]	GETUPVAL 	0 8	; BD
	33	[139]	SETTABLE 	4 -15 5	; "onConfirm" -
	34	[112]	CALL     	2 3 2
	35	[141]	GETUPVAL 	3 0	; UIManager
	36	[141]	SELF     	3 3 -16	; "show"
	37	[141]	MOVE     	5 2
	38	[141]	CALL     	3 3 1
	39	[142]	RETURN   	0 1

function <./frontend/ui/screensaver.lua:115,122> (23 instructions, 92 bytes at 0x7fe66440a330)
1 param, 5 slots, 4 upvalues, 2 locals, 2 constants, 0 functions
	1	[116]	GETUPVAL 	1 0	; util
	2	[116]	GETTABLE 	1 1 -1	; "getFileNameSuffix"
	3	[116]	MOVE     	2 0
	4	[116]	CALL     	1 2 2
	5	[117]	GETUPVAL 	2 1	; document_cover
	6	[117]	TEST     	2 0 0
	7	[117]	JMP      	9	; to 17
	8	[117]	GETUPVAL 	2 2	; DocumentRegistry
	9	[117]	SELF     	2 2 -2	; "hasProvider"
	10	[117]	MOVE     	4 0
	11	[117]	CALL     	2 3 2
	12	[117]	TEST     	2 0 0
	13	[117]	JMP      	3	; to 17
	14	[118]	LOADBOOL 	2 1 0
	15	[118]	RETURN   	2 2
	16	[118]	JMP      	6	; to 23
	17	[119]	GETUPVAL 	2 3	; screensaver_provider
	18	[119]	GETTABLE 	2 2 1
	19	[119]	TEST     	2 0 0
	20	[119]	JMP      	2	; to 23
	21	[120]	LOADBOOL 	2 1 0
	22	[120]	RETURN   	2 2
	23	[122]	RETURN   	0 1

function <./frontend/ui/screensaver.lua:125,139> (51 instructions, 204 bytes at 0x7fe66440ac70)
1 param, 10 slots, 6 upvalues, 1 local, 12 constants, 0 functions
	1	[126]	GETUPVAL 	1 0	; document_cover
	2	[126]	TEST     	1 0 0
	3	[126]	JMP      	24	; to 28
	4	[127]	GETGLOBAL	1 -1	; G_reader_settings
	5	[127]	SELF     	1 1 -2	; "saveSetting"
	6	[127]	LOADK    	3 -3	; "screensaver_document_cover"
	7	[127]	MOVE     	4 0
	8	[127]	CALL     	1 4 1
	9	[128]	GETUPVAL 	1 1	; UIManager
	10	[128]	SELF     	1 1 -4	; "show"
	11	[128]	GETUPVAL 	3 2	; InfoMessage
	12	[128]	SELF     	3 3 -5	; "new"
	13	[128]	NEWTABLE 	5 0 2
	14	[129]	GETUPVAL 	6 3	; T
	15	[129]	GETUPVAL 	7 4	; _
	16	[129]	LOADK    	8 -7	; "Screensaver document cover set to:\n%1"
	17	[129]	CALL     	7 2 2
	18	[129]	GETUPVAL 	8 5	; BD
	19	[129]	GETTABLE 	8 8 -8	; "filepath"
	20	[129]	MOVE     	9 0
	21	[129]	CALL     	8 2 0
	22	[129]	CALL     	6 0 2
	23	[129]	SETTABLE 	5 -6 6	; "text" -
	24	[130]	SETTABLE 	5 -9 -10	; "timeout" 3
	25	[128]	CALL     	3 3 0
	26	[128]	CALL     	1 0 1
	27	[131]	JMP      	23	; to 51
	28	[133]	GETGLOBAL	1 -1	; G_reader_settings
	29	[133]	SELF     	1 1 -2	; "saveSetting"
	30	[133]	LOADK    	3 -11	; "screensaver_image"
	31	[133]	MOVE     	4 0
	32	[133]	CALL     	1 4 1
	33	[134]	GETUPVAL 	1 1	; UIManager
	34	[134]	SELF     	1 1 -4	; "show"
	35	[134]	GETUPVAL 	3 2	; InfoMessage
	36	[134]	SELF     	3 3 -5	; "new"
	37	[134]	NEWTABLE 	5 0 2
	38	[135]	GETUPVAL 	6 3	; T
	39	[135]	GETUPVAL 	7 4	; _
	40	[135]	LOADK    	8 -12	; "Screensaver image set to:\n%1"
	41	[135]	CALL     	7 2 2
	42	[135]	GETUPVAL 	8 5	; BD
	43	[135]	GETTABLE 	8 8 -8	; "filepath"
	44	[135]	MOVE     	9 0
	45	[135]	CALL     	8 2 0
	46	[135]	CALL     	6 0 2
	47	[135]	SETTABLE 	5 -6 6	; "text" -
	48	[136]	SETTABLE 	5 -9 -10	; "timeout" 3
	49	[134]	CALL     	3 3 0
	50	[134]	CALL     	1 0 1
	51	[139]	RETURN   	0 1

function <./frontend/ui/screensaver.lua:148,150> (6 instructions, 24 bytes at 0x7fe66440a190)
0 params, 3 slots, 2 upvalues, 0 locals, 2 constants, 0 functions
	1	[149]	GETUPVAL 	0 0	; UIManager
	2	[149]	SELF     	0 0 -1	; "close"
	3	[149]	GETUPVAL 	2 1	; self
	4	[149]	GETTABLE 	2 2 -2	; "choose_dialog"
	5	[149]	CALL     	0 3 1
	6	[150]	RETURN   	0 1

function <./frontend/ui/screensaver.lua:167,169> (6 instructions, 24 bytes at 0x7fe66440a110)
1 param, 4 slots, 0 upvalues, 1 local, 3 constants, 0 functions
	1	[168]	GETGLOBAL	1 -1	; G_reader_settings
	2	[168]	SELF     	1 1 -2	; "isTrue"
	3	[168]	LOADK    	3 -3	; "screensaver_stretch_images"
	4	[168]	TAILCALL 	1 3 0
	5	[168]	RETURN   	1 0
	6	[169]	RETURN   	0 1

function <./frontend/ui/screensaver.lua:171,173> (6 instructions, 24 bytes at 0x7fe66440b630)
1 param, 4 slots, 0 upvalues, 1 local, 3 constants, 0 functions
	1	[172]	GETGLOBAL	1 -1	; G_reader_settings
	2	[172]	SELF     	1 1 -2	; "isTrue"
	3	[172]	LOADK    	3 -3	; "screensaver_white_background"
	4	[172]	TAILCALL 	1 3 0
	5	[172]	RETURN   	1 0
	6	[173]	RETURN   	0 1

function <./frontend/ui/screensaver.lua:175,177> (6 instructions, 24 bytes at 0x7fe66440bd40)
1 param, 4 slots, 0 upvalues, 1 local, 3 constants, 0 functions
	1	[176]	GETGLOBAL	1 -1	; G_reader_settings
	2	[176]	SELF     	1 1 -2	; "isTrue"
	3	[176]	LOADK    	3 -3	; "screensaver_no_background"
	4	[176]	TAILCALL 	1 3 0
	5	[176]	RETURN   	1 0
	6	[177]	RETURN   	0 1

function <./frontend/ui/screensaver.lua:179,187> (24 instructions, 96 bytes at 0x7fe66440c020)
1 param, 7 slots, 1 upvalue, 4 locals, 6 constants, 0 functions
	1	[180]	GETGLOBAL	1 -1	; G_reader_settings
	2	[180]	SELF     	1 1 -2	; "readSetting"
	3	[180]	LOADK    	3 -3	; "lastfile"
	4	[180]	CALL     	1 3 2
	5	[181]	LOADBOOL 	2 0 0
	6	[182]	GETUPVAL 	3 0	; DocSettings
	7	[182]	SELF     	3 3 -4	; "hasSidecarFile"
	8	[182]	MOVE     	5 1
	9	[182]	CALL     	3 3 2
	10	[182]	TEST     	3 0 0
	11	[182]	JMP      	8	; to 20
	12	[183]	GETUPVAL 	3 0	; DocSettings
	13	[183]	SELF     	3 3 -5	; "open"
	14	[183]	MOVE     	5 1
	15	[183]	CALL     	3 3 2
	16	[184]	SELF     	4 3 -2	; "readSetting"
	17	[184]	LOADK    	6 -6	; "exclude_screensaver"
	18	[184]	CALL     	4 3 2
	19	[184]	MOVE     	2 4
	20	[186]	TESTSET  	3 2 1
	21	[186]	JMP      	1	; to 23
	22	[186]	LOADBOOL 	3 0 0
	23	[186]	RETURN   	3 2
	24	[187]	RETURN   	0 1

function <./frontend/ui/screensaver.lua:189,220> (52 instructions, 208 bytes at 0x7fe66440c590)
1 param, 12 slots, 3 upvalues, 3 locals, 22 constants, 2 functions
	1	[190]	GETGLOBAL	1 -1	; require
	2	[190]	LOADK    	2 -2	; "ui/widget/inputdialog"
	3	[190]	CALL     	1 2 2
	4	[191]	GETGLOBAL	2 -3	; G_reader_settings
	5	[191]	SELF     	2 2 -4	; "readSetting"
	6	[191]	LOADK    	4 -5	; "screensaver_message"
	7	[191]	CALL     	2 3 2
	8	[192]	EQ       	0 2 -6	; - nil
	9	[192]	JMP      	1	; to 11
	10	[193]	GETUPVAL 	2 0	; default_screensaver_message
	11	[195]	SELF     	3 1 -8	; "new"
	12	[195]	NEWTABLE 	5 0 4
	13	[196]	SETTABLE 	5 -9 -10	; "title" "Screensaver message"
	14	[197]	GETUPVAL 	6 1	; _
	15	[197]	LOADK    	7 -12	; "Enter the message to be displayed by the screensaver. The following escape sequences can be used:\n  %p percentage read\n  %c current page number\n  %t total number of pages\n  %T title"
	16	[197]	CALL     	6 2 2
	17	[197]	SETTABLE 	5 -11 6	; "description" -
	18	[198]	SETTABLE 	5 -13 2	; "input" -
	19	[199]	NEWTABLE 	6 1 0
	20	[199]	NEWTABLE 	7 2 0
	21	[200]	NEWTABLE 	8 0 2
	22	[202]	GETUPVAL 	9 1	; _
	23	[202]	LOADK    	10 -16	; "Cancel"
	24	[202]	CALL     	9 2 2
	25	[202]	SETTABLE 	8 -15 9	; "text" -
	26	[205]	CLOSURE  	9 0	; 0x7fe664408f70
	27	[205]	GETUPVAL 	0 2	; UIManager
	28	[205]	MOVE     	0 0
	29	[205]	SETTABLE 	8 -17 9	; "callback" -
	30	[206]	NEWTABLE 	9 0 3
	31	[208]	GETUPVAL 	10 1	; _
	32	[208]	LOADK    	11 -18	; "Set message"
	33	[208]	CALL     	10 2 2
	34	[208]	SETTABLE 	9 -15 10	; "text" -
	35	[209]	SETTABLE 	9 -19 -20	; "is_enter_default" true
	36	[213]	CLOSURE  	10 1	; 0x7fe66440c770
	37	[213]	MOVE     	0 0
	38	[213]	GETUPVAL 	0 2	; UIManager
	39	[213]	SETTABLE 	9 -17 10	; "callback" -
	40	[215]	SETLIST  	7 2 1	; 1
	41	[216]	SETLIST  	6 1 1	; 1
	42	[216]	SETTABLE 	5 -14 6	; "buttons" -
	43	[195]	CALL     	3 3 2
	44	[217]	SETTABLE 	0 -7 3	; "input_dialog" -
	45	[218]	GETUPVAL 	3 2	; UIManager
	46	[218]	SELF     	3 3 -21	; "show"
	47	[218]	GETTABLE 	5 0 -7	; "input_dialog"
	48	[218]	CALL     	3 3 1
	49	[219]	GETTABLE 	3 0 -7	; "input_dialog"
	50	[219]	SELF     	3 3 -22	; "onShowKeyboard"
	51	[219]	CALL     	3 2 1
	52	[220]	RETURN   	0 1

function <./frontend/ui/screensaver.lua:203,205> (6 instructions, 24 bytes at 0x7fe664408f70)
0 params, 3 slots, 2 upvalues, 0 locals, 2 constants, 0 functions
	1	[204]	GETUPVAL 	0 0	; UIManager
	2	[204]	SELF     	0 0 -1	; "close"
	3	[204]	GETUPVAL 	2 1	; self
	4	[204]	GETTABLE 	2 2 -2	; "input_dialog"
	5	[204]	CALL     	0 3 1
	6	[205]	RETURN   	0 1

function <./frontend/ui/screensaver.lua:210,213> (14 instructions, 56 bytes at 0x7fe66440c770)
0 params, 5 slots, 2 upvalues, 0 locals, 6 constants, 0 functions
	1	[211]	GETGLOBAL	0 -1	; G_reader_settings
	2	[211]	SELF     	0 0 -2	; "saveSetting"
	3	[211]	LOADK    	2 -3	; "screensaver_message"
	4	[211]	GETUPVAL 	3 0	; self
	5	[211]	GETTABLE 	3 3 -4	; "input_dialog"
	6	[211]	SELF     	3 3 -5	; "getInputText"
	7	[211]	CALL     	3 2 0
	8	[211]	CALL     	0 0 1
	9	[212]	GETUPVAL 	0 1	; UIManager
	10	[212]	SELF     	0 0 -6	; "close"
	11	[212]	GETUPVAL 	2 0	; self
	12	[212]	GETTABLE 	2 2 -4	; "input_dialog"
	13	[212]	CALL     	0 3 1
	14	[213]	RETURN   	0 1

function <./frontend/ui/screensaver.lua:222,432> (442 instructions, 1768 bytes at 0x7fe66440c660)
3 params, 23 slots, 19 upvalues, 27 locals, 83 constants, 0 functions
	1	[225]	GETTABLE 	3 0 -1	; "left_msg"
	2	[225]	TEST     	3 0 0
	3	[225]	JMP      	5	; to 9
	4	[226]	GETUPVAL 	3 0	; UIManager
	5	[226]	SELF     	3 3 -2	; "close"
	6	[226]	GETTABLE 	5 0 -1	; "left_msg"
	7	[226]	CALL     	3 3 1
	8	[227]	SETTABLE 	0 -1 -3	; "left_msg" nil
	9	[229]	LOADBOOL 	3 1 0
	10	[230]	LOADNIL  	4 4
	11	[231]	TEST     	1 0 0
	12	[231]	JMP      	5	; to 18
	13	[231]	MOVE     	5 1
	14	[231]	LOADK    	6 -4	; "_"
	15	[231]	CONCAT   	5 5 6
	16	[231]	TEST     	5 0 1
	17	[231]	JMP      	1	; to 19
	18	[231]	LOADK    	5 -5	; ""
	19	[232]	GETGLOBAL	6 -6	; G_reader_settings
	20	[232]	SELF     	6 6 -7	; "readSetting"
	21	[232]	MOVE     	8 5
	22	[232]	LOADK    	9 -8	; "screensaver_type"
	23	[232]	CONCAT   	8 8 9
	24	[232]	CALL     	6 3 2
	25	[233]	TEST     	5 0 0
	26	[233]	JMP      	9	; to 36
	27	[233]	TEST     	6 0 1
	28	[233]	JMP      	7	; to 36
	29	[236]	GETGLOBAL	7 -6	; G_reader_settings
	30	[236]	SELF     	7 7 -7	; "readSetting"
	31	[236]	LOADK    	9 -8	; "screensaver_type"
	32	[236]	CALL     	7 3 2
	33	[236]	MOVE     	6 7
	34	[237]	LOADK    	5 -5	; ""
	35	[241]	MOVE     	4 2
	36	[243]	EQ       	0 6 -3	; - nil
	37	[243]	JMP      	1	; to 39
	38	[244]	LOADK    	6 -9	; "message"
	39	[246]	EQ       	0 6 -10	; - "disable"
	40	[246]	JMP      	1	; to 42
	41	[247]	RETURN   	0 1
	42	[249]	LOADNIL  	7 7
	43	[250]	GETUPVAL 	8 1	; Blitbuffer
	44	[250]	GETTABLE 	8 8 -11	; "COLOR_BLACK"
	45	[251]	SELF     	9 0 -12	; "whiteBackground"
	46	[251]	CALL     	9 2 2
	47	[251]	TEST     	9 0 0
	48	[251]	JMP      	3	; to 52
	49	[252]	GETUPVAL 	9 1	; Blitbuffer
	50	[252]	GETTABLE 	8 9 -13	; "COLOR_WHITE"
	51	[252]	JMP      	5	; to 57
	52	[253]	SELF     	9 0 -14	; "noBackground"
	53	[253]	CALL     	9 2 2
	54	[253]	TEST     	9 0 0
	55	[253]	JMP      	1	; to 57
	56	[254]	LOADNIL  	8 8
	57	[256]	GETGLOBAL	9 -6	; G_reader_settings
	58	[256]	SELF     	9 9 -7	; "readSetting"
	59	[256]	LOADK    	11 -15	; "lastfile"
	60	[256]	CALL     	9 3 2
	61	[257]	EQ       	0 6 -16	; - "document_cover"
	62	[257]	JMP      	6	; to 69
	63	[259]	GETGLOBAL	10 -6	; G_reader_settings
	64	[259]	SELF     	10 10 -7	; "readSetting"
	65	[259]	LOADK    	12 -17	; "screensaver_document_cover"
	66	[259]	CALL     	10 3 2
	67	[259]	MOVE     	9 10
	68	[260]	LOADK    	6 -18	; "cover"
	69	[262]	EQ       	0 6 -18	; - "cover"
	70	[262]	JMP      	81	; to 152
	71	[263]	EQ       	1 9 -3	; - nil
	72	[263]	JMP      	2	; to 75
	73	[263]	TEST     	9 0 1
	74	[263]	JMP      	5	; to 80
	75	[263]	GETGLOBAL	10 -6	; G_reader_settings
	76	[263]	SELF     	10 10 -7	; "readSetting"
	77	[263]	LOADK    	12 -15	; "lastfile"
	78	[263]	CALL     	10 3 2
	79	[263]	MOVE     	9 10
	80	[264]	LOADBOOL 	10 0 0
	81	[265]	GETUPVAL 	11 2	; DocSettings
	82	[265]	SELF     	11 11 -19	; "hasSidecarFile"
	83	[265]	MOVE     	13 9
	84	[265]	CALL     	11 3 2
	85	[265]	TEST     	11 0 0
	86	[265]	JMP      	8	; to 95
	87	[266]	GETUPVAL 	11 2	; DocSettings
	88	[266]	SELF     	11 11 -20	; "open"
	89	[266]	MOVE     	13 9
	90	[266]	CALL     	11 3 2
	91	[267]	SELF     	12 11 -7	; "readSetting"
	92	[267]	LOADK    	14 -21	; "exclude_screensaver"
	93	[267]	CALL     	12 3 2
	94	[267]	MOVE     	10 12
	95	[269]	EQ       	1 10 -22	; - true
	96	[269]	JMP      	54	; to 151
	97	[270]	TEST     	9 0 0
	98	[270]	JMP      	50	; to 149
	99	[270]	GETUPVAL 	11 3	; lfs
	100	[270]	GETTABLE 	11 11 -23	; "attributes"
	101	[270]	MOVE     	12 9
	102	[270]	LOADK    	13 -24	; "mode"
	103	[270]	CALL     	11 3 2
	104	[270]	EQ       	0 11 -25	; - "file"
	105	[270]	JMP      	43	; to 149
	106	[271]	GETUPVAL 	11 4	; DocumentRegistry
	107	[271]	SELF     	11 11 -26	; "openDocument"
	108	[271]	MOVE     	13 9
	109	[271]	CALL     	11 3 2
	110	[272]	GETTABLE 	12 11 -27	; "loadDocument"
	111	[272]	TEST     	12 0 0
	112	[272]	JMP      	3	; to 116
	113	[273]	SELF     	12 11 -27	; "loadDocument"
	114	[273]	LOADBOOL 	14 0 0
	115	[273]	CALL     	12 3 1
	116	[275]	SELF     	12 11 -28	; "getCoverPageImage"
	117	[275]	CALL     	12 2 2
	118	[276]	SELF     	13 11 -2	; "close"
	119	[276]	CALL     	13 2 1
	120	[277]	EQ       	1 12 -3	; - nil
	121	[277]	JMP      	25	; to 147
	122	[278]	GETUPVAL 	13 5	; ImageWidget
	123	[278]	SELF     	13 13 -29	; "new"
	124	[278]	NEWTABLE 	15 0 5
	125	[279]	SETTABLE 	15 -30 12	; "image" -
	126	[280]	SETTABLE 	15 -31 -22	; "image_disposable" true
	127	[281]	GETUPVAL 	16 6	; Screen
	128	[281]	SELF     	16 16 -33	; "getHeight"
	129	[281]	CALL     	16 2 2
	130	[281]	SETTABLE 	15 -32 16	; "height" -
	131	[282]	GETUPVAL 	16 6	; Screen
	132	[282]	SELF     	16 16 -35	; "getWidth"
	133	[282]	CALL     	16 2 2
	134	[282]	SETTABLE 	15 -34 16	; "width" -
	135	[283]	SELF     	16 0 -37	; "stretchImages"
	136	[283]	CALL     	16 2 2
	137	[283]	TEST     	16 0 1
	138	[283]	JMP      	3	; to 142
	139	[283]	LOADK    	16 -38	; 0
	140	[283]	TEST     	16 0 1
	141	[283]	JMP      	1	; to 143
	142	[283]	LOADNIL  	16 16
	143	[283]	SETTABLE 	15 -36 16	; "scale_factor" -
	144	[278]	CALL     	13 3 2
	145	[284]	MOVE     	7 13
	146	[284]	JMP      	5	; to 152
	147	[286]	LOADK    	6 -39	; "random_image"
	148	[287]	JMP      	3	; to 152
	149	[289]	LOADK    	6 -39	; "random_image"
	150	[290]	JMP      	1	; to 152
	151	[292]	LOADK    	6 -39	; "random_image"
	152	[295]	EQ       	0 6 -40	; - "bookstatus"
	153	[295]	JMP      	46	; to 200
	154	[296]	TEST     	9 0 0
	155	[296]	JMP      	43	; to 199
	156	[296]	GETUPVAL 	10 3	; lfs
	157	[296]	GETTABLE 	10 10 -23	; "attributes"
	158	[296]	MOVE     	11 9
	159	[296]	LOADK    	12 -24	; "mode"
	160	[296]	CALL     	10 3 2
	161	[296]	EQ       	0 10 -25	; - "file"
	162	[296]	JMP      	36	; to 199
	163	[297]	GETUPVAL 	10 4	; DocumentRegistry
	164	[297]	SELF     	10 10 -26	; "openDocument"
	165	[297]	MOVE     	12 9
	166	[297]	CALL     	10 3 2
	167	[298]	GETUPVAL 	11 2	; DocSettings
	168	[298]	SELF     	11 11 -20	; "open"
	169	[298]	MOVE     	13 9
	170	[298]	CALL     	11 3 2
	171	[299]	GETGLOBAL	12 -41	; require
	172	[299]	LOADK    	13 -42	; "apps/reader/readerui"
	173	[299]	CALL     	12 2 2
	174	[299]	SELF     	12 12 -43	; "_getRunningInstance"
	175	[299]	CALL     	12 2 2
	176	[300]	EQ       	1 12 -3	; - nil
	177	[300]	JMP      	17	; to 195
	178	[301]	GETUPVAL 	13 7	; BookStatusWidget
	179	[301]	SELF     	13 13 -29	; "new"
	180	[301]	NEWTABLE 	15 0 6
	181	[302]	SELF     	16 10 -28	; "getCoverPageImage"
	182	[302]	CALL     	16 2 2
	183	[302]	SETTABLE 	15 -44 16	; "thumbnail" -
	184	[303]	SELF     	16 10 -46	; "getProps"
	185	[303]	CALL     	16 2 2
	186	[303]	SETTABLE 	15 -45 16	; "props" -
	187	[304]	SETTABLE 	15 -47 10	; "document" -
	188	[305]	SETTABLE 	15 -48 11	; "settings" -
	189	[306]	GETTABLE 	16 12 -49	; "view"
	190	[306]	SETTABLE 	15 -49 16	; "view" -
	191	[307]	SETTABLE 	15 -50 -22	; "readonly" true
	192	[301]	CALL     	13 3 2
	193	[308]	MOVE     	7 13
	194	[308]	JMP      	1	; to 196
	195	[310]	LOADK    	6 -9	; "message"
	196	[312]	SELF     	13 10 -2	; "close"
	197	[312]	CALL     	13 2 1
	198	[312]	JMP      	1	; to 200
	199	[314]	LOADK    	6 -9	; "message"
	200	[317]	EQ       	0 6 -39	; - "random_image"
	201	[317]	JMP      	54	; to 256
	202	[318]	GETGLOBAL	10 -6	; G_reader_settings
	203	[318]	SELF     	10 10 -7	; "readSetting"
	204	[318]	MOVE     	12 5
	205	[318]	LOADK    	13 -51	; "screensaver_dir"
	206	[318]	CONCAT   	12 12 13
	207	[318]	CALL     	10 3 2
	208	[319]	EQ       	0 10 -3	; - nil
	209	[319]	JMP      	7	; to 217
	210	[319]	EQ       	1 5 -5	; - ""
	211	[319]	JMP      	5	; to 217
	212	[320]	GETGLOBAL	11 -6	; G_reader_settings
	213	[320]	SELF     	11 11 -7	; "readSetting"
	214	[320]	LOADK    	13 -51	; "screensaver_dir"
	215	[320]	CALL     	11 3 2
	216	[320]	MOVE     	10 11
	217	[322]	EQ       	0 10 -3	; - nil
	218	[322]	JMP      	5	; to 224
	219	[323]	GETUPVAL 	11 8	; DataStorage
	220	[323]	SELF     	11 11 -52	; "getDataDir"
	221	[323]	CALL     	11 2 2
	222	[323]	LOADK    	12 -53	; "/screenshots/"
	223	[323]	CONCAT   	10 11 12
	224	[325]	GETUPVAL 	11 9	; getRandomImage
	225	[325]	MOVE     	12 10
	226	[325]	CALL     	11 2 2
	227	[326]	EQ       	0 11 -3	; - nil
	228	[326]	JMP      	2	; to 231
	229	[327]	LOADK    	6 -9	; "message"
	230	[327]	JMP      	25	; to 256
	231	[329]	GETUPVAL 	12 5	; ImageWidget
	232	[329]	SELF     	12 12 -29	; "new"
	233	[329]	NEWTABLE 	14 0 6
	234	[330]	SETTABLE 	14 -25 11	; "file" -
	235	[331]	SETTABLE 	14 -54 -55	; "file_do_cache" false
	236	[332]	SETTABLE 	14 -56 -22	; "alpha" true
	237	[333]	GETUPVAL 	15 6	; Screen
	238	[333]	SELF     	15 15 -33	; "getHeight"
	239	[333]	CALL     	15 2 2
	240	[333]	SETTABLE 	14 -32 15	; "height" -
	241	[334]	GETUPVAL 	15 6	; Screen
	242	[334]	SELF     	15 15 -35	; "getWidth"
	243	[334]	CALL     	15 2 2
	244	[334]	SETTABLE 	14 -34 15	; "width" -
	245	[335]	SELF     	15 0 -37	; "stretchImages"
	246	[335]	CALL     	15 2 2
	247	[335]	TEST     	15 0 1
	248	[335]	JMP      	3	; to 252
	249	[335]	LOADK    	15 -38	; 0
	250	[335]	TEST     	15 0 1
	251	[335]	JMP      	1	; to 253
	252	[335]	LOADNIL  	15 15
	253	[335]	SETTABLE 	14 -36 15	; "scale_factor" -
	254	[329]	CALL     	12 3 2
	255	[336]	MOVE     	7 12
	256	[339]	EQ       	0 6 -57	; - "image_file"
	257	[339]	JMP      	56	; to 314
	258	[340]	GETGLOBAL	10 -6	; G_reader_settings
	259	[340]	SELF     	10 10 -7	; "readSetting"
	260	[340]	MOVE     	12 5
	261	[340]	LOADK    	13 -58	; "screensaver_image"
	262	[340]	CONCAT   	12 12 13
	263	[340]	CALL     	10 3 2
	264	[341]	EQ       	0 10 -3	; - nil
	265	[341]	JMP      	7	; to 273
	266	[341]	EQ       	1 5 -5	; - ""
	267	[341]	JMP      	5	; to 273
	268	[342]	GETGLOBAL	11 -6	; G_reader_settings
	269	[342]	SELF     	11 11 -7	; "readSetting"
	270	[342]	LOADK    	13 -58	; "screensaver_image"
	271	[342]	CALL     	11 3 2
	272	[342]	MOVE     	10 11
	273	[344]	EQ       	0 10 -3	; - nil
	274	[344]	JMP      	5	; to 280
	275	[345]	GETUPVAL 	11 8	; DataStorage
	276	[345]	SELF     	11 11 -52	; "getDataDir"
	277	[345]	CALL     	11 2 2
	278	[345]	LOADK    	12 -59	; "/resources/koreader.png"
	279	[345]	CONCAT   	10 11 12
	280	[347]	GETUPVAL 	11 3	; lfs
	281	[347]	GETTABLE 	11 11 -23	; "attributes"
	282	[347]	MOVE     	12 10
	283	[347]	LOADK    	13 -24	; "mode"
	284	[347]	CALL     	11 3 2
	285	[347]	EQ       	1 11 -25	; - "file"
	286	[347]	JMP      	2	; to 289
	287	[348]	LOADK    	6 -9	; "message"
	288	[348]	JMP      	25	; to 314
	289	[350]	GETUPVAL 	11 5	; ImageWidget
	290	[350]	SELF     	11 11 -29	; "new"
	291	[350]	NEWTABLE 	13 0 6
	292	[351]	SETTABLE 	13 -25 10	; "file" -
	293	[352]	SETTABLE 	13 -54 -55	; "file_do_cache" false
	294	[353]	SETTABLE 	13 -56 -22	; "alpha" true
	295	[354]	GETUPVAL 	14 6	; Screen
	296	[354]	SELF     	14 14 -33	; "getHeight"
	297	[354]	CALL     	14 2 2
	298	[354]	SETTABLE 	13 -32 14	; "height" -
	299	[355]	GETUPVAL 	14 6	; Screen
	300	[355]	SELF     	14 14 -35	; "getWidth"
	301	[355]	CALL     	14 2 2
	302	[355]	SETTABLE 	13 -34 14	; "width" -
	303	[356]	SELF     	14 0 -37	; "stretchImages"
	304	[356]	CALL     	14 2 2
	305	[356]	TEST     	14 0 1
	306	[356]	JMP      	3	; to 310
	307	[356]	LOADK    	14 -38	; 0
	308	[356]	TEST     	14 0 1
	309	[356]	JMP      	1	; to 311
	310	[356]	LOADNIL  	14 14
	311	[356]	SETTABLE 	13 -36 14	; "scale_factor" -
	312	[350]	CALL     	11 3 2
	313	[357]	MOVE     	7 11
	314	[360]	EQ       	0 6 -60	; - "readingprogress"
	315	[360]	JMP      	10	; to 326
	316	[361]	GETUPVAL 	10 10	; Screensaver
	317	[361]	GETTABLE 	10 10 -61	; "getReaderProgress"
	318	[361]	EQ       	1 10 -3	; - nil
	319	[361]	JMP      	5	; to 325
	320	[362]	GETUPVAL 	10 10	; Screensaver
	321	[362]	GETTABLE 	10 10 -61	; "getReaderProgress"
	322	[362]	CALL     	10 1 2
	323	[362]	MOVE     	7 10
	324	[362]	JMP      	1	; to 326
	325	[364]	LOADK    	6 -9	; "message"
	326	[367]	EQ       	0 6 -9	; - "message"
	327	[367]	JMP      	88	; to 416
	328	[368]	GETGLOBAL	10 -6	; G_reader_settings
	329	[368]	SELF     	10 10 -7	; "readSetting"
	330	[368]	MOVE     	12 5
	331	[368]	LOADK    	13 -62	; "screensaver_message"
	332	[368]	CONCAT   	12 12 13
	333	[368]	CALL     	10 3 2
	334	[369]	GETGLOBAL	11 -6	; G_reader_settings
	335	[369]	SELF     	11 11 -7	; "readSetting"
	336	[369]	MOVE     	13 5
	337	[369]	LOADK    	14 -63	; "screensaver_message_position"
	338	[369]	CONCAT   	13 13 14
	339	[369]	CALL     	11 3 2
	340	[370]	SELF     	12 0 -12	; "whiteBackground"
	341	[370]	CALL     	12 2 2
	342	[370]	TEST     	12 0 1
	343	[370]	JMP      	2	; to 346
	344	[371]	LOADNIL  	8 8
	345	[372]	LOADBOOL 	3 0 0
	346	[374]	EQ       	0 10 -3	; - nil
	347	[374]	JMP      	7	; to 355
	348	[374]	EQ       	1 5 -5	; - ""
	349	[374]	JMP      	5	; to 355
	350	[375]	GETGLOBAL	12 -6	; G_reader_settings
	351	[375]	SELF     	12 12 -7	; "readSetting"
	352	[375]	LOADK    	14 -62	; "screensaver_message"
	353	[375]	CALL     	12 3 2
	354	[375]	MOVE     	10 12
	355	[378]	TESTSET  	12 2 1
	356	[378]	JMP      	1	; to 358
	357	[378]	GETUPVAL 	12 11	; default_screensaver_message
	358	[379]	EQ       	0 10 -3	; - nil
	359	[379]	JMP      	2	; to 362
	360	[380]	MOVE     	10 12
	361	[380]	JMP      	5	; to 367
	362	[382]	SELF     	13 0 -64	; "expandSpecial"
	363	[382]	MOVE     	15 10
	364	[382]	MOVE     	16 12
	365	[382]	CALL     	13 4 2
	366	[382]	MOVE     	10 13
	367	[385]	EQ       	1 11 -65	; - "middle"
	368	[385]	JMP      	2	; to 371
	369	[385]	EQ       	0 11 -3	; - nil
	370	[385]	JMP      	8	; to 379
	371	[386]	GETUPVAL 	13 12	; InfoMessage
	372	[386]	SELF     	13 13 -29	; "new"
	373	[386]	NEWTABLE 	15 0 2
	374	[387]	SETTABLE 	15 -66 10	; "text" -
	375	[388]	SETTABLE 	15 -50 -22	; "readonly" true
	376	[386]	CALL     	13 3 2
	377	[389]	MOVE     	7 13
	378	[389]	JMP      	36	; to 415
	379	[391]	GETUPVAL 	13 13	; Font
	380	[391]	SELF     	13 13 -67	; "getFace"
	381	[391]	LOADK    	15 -68	; "infofont"
	382	[391]	CALL     	13 3 2
	383	[392]	LOADNIL  	14 14
	384	[393]	EQ       	0 11 -69	; - "bottom"
	385	[393]	JMP      	2	; to 388
	386	[394]	GETUPVAL 	14 14	; BottomContainer
	387	[394]	JMP      	1	; to 389
	388	[396]	GETUPVAL 	14 15	; TopContainer
	389	[399]	GETUPVAL 	15 6	; Screen
	390	[399]	SELF     	15 15 -35	; "getWidth"
	391	[399]	CALL     	15 2 2
	392	[399]	GETUPVAL 	16 6	; Screen
	393	[399]	SELF     	16 16 -33	; "getHeight"
	394	[399]	CALL     	16 2 2
	395	[400]	SELF     	17 14 -29	; "new"
	396	[400]	NEWTABLE 	19 0 1
	397	[401]	GETUPVAL 	20 16	; Geom
	398	[401]	SELF     	20 20 -29	; "new"
	399	[401]	NEWTABLE 	22 0 2
	400	[402]	SETTABLE 	22 -71 15	; "w" -
	401	[403]	SETTABLE 	22 -72 16	; "h" -
	402	[401]	CALL     	20 3 2
	403	[404]	SETTABLE 	19 -70 20	; "dimen" -
	404	[405]	GETUPVAL 	20 17	; TextBoxWidget
	405	[405]	SELF     	20 20 -29	; "new"
	406	[405]	NEWTABLE 	22 0 4
	407	[406]	SETTABLE 	22 -66 10	; "text" -
	408	[407]	SETTABLE 	22 -73 13	; "face" -
	409	[408]	SETTABLE 	22 -34 15	; "width" -
	410	[409]	SETTABLE 	22 -74 -75	; "alignment" "center"
	411	[405]	CALL     	20 3 0
	412	[411]	SETLIST  	19 0 1	; 1
	413	[400]	CALL     	17 3 2
	414	[411]	MOVE     	7 17
	415	[414]	LOADNIL  	4 4
	416	[417]	TEST     	4 0 0
	417	[417]	JMP      	5	; to 423
	418	[418]	SELF     	10 0 -76	; "addOverlayMessage"
	419	[418]	MOVE     	12 7
	420	[418]	MOVE     	13 4
	421	[418]	CALL     	10 4 2
	422	[418]	MOVE     	7 10
	423	[421]	TEST     	7 0 0
	424	[421]	JMP      	17	; to 442
	425	[422]	GETUPVAL 	10 18	; ScreenSaverWidget
	426	[422]	SELF     	10 10 -29	; "new"
	427	[422]	NEWTABLE 	12 0 3
	428	[423]	SETTABLE 	12 -77 7	; "widget" -
	429	[424]	SETTABLE 	12 -78 8	; "background" -
	430	[425]	SETTABLE 	12 -79 3	; "covers_fullscreen" -
	431	[422]	CALL     	10 3 2
	432	[426]	SETTABLE 	0 -1 10	; "left_msg" -
	433	[427]	GETTABLE 	10 0 -1	; "left_msg"
	434	[427]	SETTABLE 	10 -80 -22	; "modal" true
	435	[429]	GETTABLE 	10 0 -1	; "left_msg"
	436	[429]	SETTABLE 	10 -81 -22	; "dithered" true
	437	[430]	GETUPVAL 	10 0	; UIManager
	438	[430]	SELF     	10 10 -82	; "show"
	439	[430]	GETTABLE 	12 0 -1	; "left_msg"
	440	[430]	LOADK    	13 -83	; "full"
	441	[430]	CALL     	10 4 1
	442	[432]	RETURN   	0 1

function <./frontend/ui/screensaver.lua:434,464> (71 instructions, 284 bytes at 0x7fe664407630)
3 params, 15 slots, 3 upvalues, 11 locals, 26 constants, 0 functions
	1	[441]	MOVE     	3 1
	2	[443]	GETGLOBAL	4 -1	; G_reader_settings
	3	[443]	SELF     	4 4 -2	; "readSetting"
	4	[443]	LOADK    	6 -3	; "lastfile"
	5	[443]	CALL     	4 3 2
	6	[444]	GETGLOBAL	5 -4	; require
	7	[444]	LOADK    	6 -5	; "apps/reader/readerui"
	8	[444]	CALL     	5 2 2
	9	[444]	SELF     	5 5 -6	; "_getRunningInstance"
	10	[444]	CALL     	5 2 2
	11	[445]	TEST     	4 0 0
	12	[445]	JMP      	56	; to 69
	13	[445]	GETUPVAL 	6 0	; lfs
	14	[445]	GETTABLE 	6 6 -7	; "attributes"
	15	[445]	MOVE     	7 4
	16	[445]	LOADK    	8 -8	; "mode"
	17	[445]	CALL     	6 3 2
	18	[445]	EQ       	0 6 -9	; - "file"
	19	[445]	JMP      	49	; to 69
	20	[445]	EQ       	1 5 -10	; - nil
	21	[445]	JMP      	47	; to 69
	22	[446]	GETUPVAL 	6 1	; DocumentRegistry
	23	[446]	SELF     	6 6 -11	; "openDocument"
	24	[446]	MOVE     	8 4
	25	[446]	CALL     	6 3 2
	26	[447]	GETTABLE 	7 5 -12	; "view"
	27	[447]	GETTABLE 	7 7 -13	; "state"
	28	[447]	GETTABLE 	7 7 -14	; "page"
	29	[448]	GETGLOBAL	8 -15	; string
	30	[448]	GETTABLE 	8 8 -16	; "gsub"
	31	[448]	MOVE     	9 3
	32	[448]	LOADK    	10 -17	; "%%c"
	33	[448]	MOVE     	11 7
	34	[448]	CALL     	8 4 2
	35	[448]	MOVE     	3 8
	36	[450]	SELF     	8 6 -18	; "getPageCount"
	37	[450]	CALL     	8 2 2
	38	[451]	GETGLOBAL	9 -15	; string
	39	[451]	GETTABLE 	9 9 -16	; "gsub"
	40	[451]	MOVE     	10 3
	41	[451]	LOADK    	11 -19	; "%%t"
	42	[451]	MOVE     	12 8
	43	[451]	CALL     	9 4 2
	44	[451]	MOVE     	3 9
	45	[453]	GETUPVAL 	9 2	; Math
	46	[453]	GETTABLE 	9 9 -20	; "round"
	47	[453]	MUL      	10 7 -21	; - 100
	48	[453]	DIV      	10 10 8
	49	[453]	CALL     	9 2 2
	50	[454]	GETGLOBAL	10 -15	; string
	51	[454]	GETTABLE 	10 10 -16	; "gsub"
	52	[454]	MOVE     	11 3
	53	[454]	LOADK    	12 -22	; "%%p"
	54	[454]	MOVE     	13 9
	55	[454]	CALL     	10 4 2
	56	[454]	MOVE     	3 10
	57	[456]	SELF     	10 6 -23	; "getProps"
	58	[456]	CALL     	10 2 2
	59	[457]	GETGLOBAL	11 -15	; string
	60	[457]	GETTABLE 	11 11 -16	; "gsub"
	61	[457]	MOVE     	12 3
	62	[457]	LOADK    	13 -24	; "%%T"
	63	[457]	GETTABLE 	14 10 -25	; "title"
	64	[457]	CALL     	11 4 2
	65	[457]	MOVE     	3 11
	66	[458]	SELF     	11 6 -26	; "close"
	67	[458]	CALL     	11 2 1
	68	[458]	JMP      	1	; to 70
	69	[460]	MOVE     	3 2
	70	[463]	RETURN   	3 2
	71	[464]	RETURN   	0 1

function <./frontend/ui/screensaver.lua:466,487> (45 instructions, 180 bytes at 0x7fe664407800)
1 param, 7 slots, 2 upvalues, 3 locals, 13 constants, 1 function
	1	[467]	GETTABLE 	1 0 -1	; "left_msg"
	2	[467]	EQ       	0 1 -2	; - nil
	3	[467]	JMP      	1	; to 5
	4	[467]	RETURN   	0 1
	5	[468]	GETGLOBAL	1 -3	; G_reader_settings
	6	[468]	SELF     	1 1 -4	; "readSetting"
	7	[468]	LOADK    	3 -5	; "screensaver_delay"
	8	[468]	CALL     	1 3 2
	9	[469]	GETGLOBAL	2 -6	; tonumber
	10	[469]	MOVE     	3 1
	11	[469]	CALL     	2 2 2
	12	[470]	TEST     	2 0 0
	13	[470]	JMP      	9	; to 23
	14	[471]	GETUPVAL 	3 0	; UIManager
	15	[471]	SELF     	3 3 -7	; "scheduleIn"
	16	[471]	MOVE     	5 2
	17	[477]	CLOSURE  	6 0	; 0x7fe66440deb0
	18	[477]	GETUPVAL 	0 1	; logger
	19	[477]	MOVE     	0 0
	20	[477]	GETUPVAL 	0 0	; UIManager
	21	[471]	CALL     	3 4 1
	22	[477]	JMP      	22	; to 45
	23	[478]	EQ       	1 1 -8	; - "disable"
	24	[478]	JMP      	2	; to 27
	25	[478]	EQ       	0 1 -2	; - nil
	26	[478]	JMP      	14	; to 41
	27	[479]	GETUPVAL 	3 1	; logger
	28	[479]	GETTABLE 	3 3 -9	; "dbg"
	29	[479]	LOADK    	4 -10	; "close screensaver"
	30	[479]	CALL     	3 2 1
	31	[480]	GETTABLE 	3 0 -1	; "left_msg"
	32	[480]	TEST     	3 0 0
	33	[480]	JMP      	11	; to 45
	34	[481]	GETUPVAL 	3 0	; UIManager
	35	[481]	SELF     	3 3 -11	; "close"
	36	[481]	GETTABLE 	5 0 -1	; "left_msg"
	37	[481]	LOADK    	6 -12	; "full"
	38	[481]	CALL     	3 4 1
	39	[482]	SETTABLE 	0 -1 -2	; "left_msg" nil
	40	[483]	JMP      	4	; to 45
	41	[485]	GETUPVAL 	3 1	; logger
	42	[485]	GETTABLE 	3 3 -9	; "dbg"
	43	[485]	LOADK    	4 -13	; "tap to exit from screensaver"
	44	[485]	CALL     	3 2 1
	45	[487]	RETURN   	0 1

function <./frontend/ui/screensaver.lua:471,477> (17 instructions, 68 bytes at 0x7fe66440deb0)
0 params, 4 slots, 3 upvalues, 0 locals, 6 constants, 0 functions
	1	[472]	GETUPVAL 	0 0	; logger
	2	[472]	GETTABLE 	0 0 -1	; "dbg"
	3	[472]	LOADK    	1 -2	; "close screensaver"
	4	[472]	CALL     	0 2 1
	5	[473]	GETUPVAL 	0 1	; self
	6	[473]	GETTABLE 	0 0 -3	; "left_msg"
	7	[473]	TEST     	0 0 0
	8	[473]	JMP      	8	; to 17
	9	[474]	GETUPVAL 	0 2	; UIManager
	10	[474]	SELF     	0 0 -4	; "close"
	11	[474]	GETUPVAL 	2 1	; self
	12	[474]	GETTABLE 	2 2 -3	; "left_msg"
	13	[474]	LOADK    	3 -5	; "full"
	14	[474]	CALL     	0 4 1
	15	[475]	GETUPVAL 	0 1	; self
	16	[475]	SETTABLE 	0 -3 -6	; "left_msg" nil
	17	[477]	RETURN   	0 1

function <./frontend/ui/screensaver.lua:489,534> (86 instructions, 344 bytes at 0x7fe66440e1b0)
3 params, 18 slots, 4 upvalues, 12 locals, 28 constants, 0 functions
	1	[490]	GETGLOBAL	3 -1	; require
	2	[490]	LOADK    	4 -2	; "ui/widget/container/framecontainer"
	3	[490]	CALL     	3 2 2
	4	[491]	GETGLOBAL	4 -1	; require
	5	[491]	LOADK    	5 -3	; "ui/widget/overlapgroup"
	6	[491]	CALL     	4 2 2
	7	[492]	GETGLOBAL	5 -1	; require
	8	[492]	LOADK    	6 -4	; "ui/widget/container/rightcontainer"
	9	[492]	CALL     	5 2 2
	10	[493]	GETGLOBAL	6 -1	; require
	11	[493]	LOADK    	7 -5	; "ui/size"
	12	[493]	CALL     	6 2 2
	13	[494]	GETGLOBAL	7 -1	; require
	14	[494]	LOADK    	8 -6	; "ui/widget/textwidget"
	15	[494]	CALL     	7 2 2
	16	[496]	GETUPVAL 	8 0	; Font
	17	[496]	SELF     	8 8 -7	; "getFace"
	18	[496]	LOADK    	10 -8	; "infofont"
	19	[496]	CALL     	8 3 2
	20	[497]	GETUPVAL 	9 1	; Screen
	21	[497]	SELF     	9 9 -9	; "getWidth"
	22	[497]	CALL     	9 2 2
	23	[497]	GETUPVAL 	10 1	; Screen
	24	[497]	SELF     	10 10 -10	; "getHeight"
	25	[497]	CALL     	10 2 2
	26	[499]	SELF     	11 7 -11	; "new"
	27	[499]	NEWTABLE 	13 0 2
	28	[500]	SETTABLE 	13 -12 2	; "text" -
	29	[501]	SETTABLE 	13 -13 8	; "face" -
	30	[499]	CALL     	11 3 2
	31	[504]	SELF     	12 11 -9	; "getWidth"
	32	[504]	CALL     	12 2 2
	33	[504]	MUL      	13 9 -14	; - 0.9
	34	[504]	LT       	0 13 12
	35	[504]	JMP      	12	; to 48
	36	[506]	GETUPVAL 	12 2	; TextBoxWidget
	37	[506]	SELF     	12 12 -11	; "new"
	38	[506]	NEWTABLE 	14 0 3
	39	[507]	SETTABLE 	14 -12 2	; "text" -
	40	[508]	SETTABLE 	14 -13 8	; "face" -
	41	[509]	GETGLOBAL	15 -16	; math
	42	[509]	GETTABLE 	15 15 -17	; "floor"
	43	[509]	MUL      	16 9 -14	; - 0.9
	44	[509]	CALL     	15 2 2
	45	[509]	SETTABLE 	14 -15 15	; "width" -
	46	[506]	CALL     	12 3 2
	47	[510]	MOVE     	11 12
	48	[512]	SELF     	12 3 -11	; "new"
	49	[512]	NEWTABLE 	14 1 3
	50	[513]	GETUPVAL 	15 3	; Blitbuffer
	51	[513]	GETTABLE 	15 15 -19	; "COLOR_WHITE"
	52	[513]	SETTABLE 	14 -18 15	; "background" -
	53	[514]	GETTABLE 	15 6 -21	; "border"
	54	[514]	GETTABLE 	15 15 -22	; "default"
	55	[514]	SETTABLE 	14 -20 15	; "bordersize" -
	56	[515]	SETTABLE 	14 -23 -24	; "margin" 0
	57	[517]	MOVE     	15 11
	58	[517]	SETLIST  	14 1 1	; 1
	59	[512]	CALL     	12 3 2
	60	[517]	MOVE     	11 12
	61	[518]	SELF     	12 5 -11	; "new"
	62	[518]	NEWTABLE 	14 1 1
	63	[519]	NEWTABLE 	15 0 2
	64	[520]	SETTABLE 	15 -26 9	; "w" -
	65	[521]	SELF     	16 11 -28	; "getSize"
	66	[521]	CALL     	16 2 2
	67	[521]	GETTABLE 	16 16 -27	; "h"
	68	[521]	SETTABLE 	15 -27 16	; "h" -
	69	[522]	SETTABLE 	14 -25 15	; "dimen" -
	70	[524]	MOVE     	15 11
	71	[524]	SETLIST  	14 1 1	; 1
	72	[518]	CALL     	12 3 2
	73	[524]	MOVE     	11 12
	74	[525]	SELF     	12 4 -11	; "new"
	75	[525]	NEWTABLE 	14 2 1
	76	[526]	NEWTABLE 	15 0 2
	77	[527]	SETTABLE 	15 -27 9	; "h" -
	78	[528]	SETTABLE 	15 -26 10	; "w" -
	79	[529]	SETTABLE 	14 -25 15	; "dimen" -
	80	[530]	MOVE     	15 1
	81	[532]	MOVE     	16 11
	82	[532]	SETLIST  	14 2 1	; 1
	83	[525]	CALL     	12 3 2
	84	[532]	MOVE     	1 12
	85	[533]	RETURN   	1 2
	86	[534]	RETURN   	0 1
