-- BYTECODE -- screenshoter.lua:17-38
0001    GGET     1   0      ; "math"
0002    TGETS    1   1   1  ; "sqrt"
0003    GGET     2   0      ; "math"
0004    TGETS    2   2   2  ; "pow"
0005    UGET     3   0      ; Screen
0006    MOV      4   3
0007    TGETS    3   3   3  ; "getWidth"
0008    CALL     3   2   2
0009    KSHORT   4   2
0010    CALL     2   2   3
0011    GGET     3   0      ; "math"
0012    TGETS    3   3   2  ; "pow"
0013    UGET     4   0      ; Screen
0014    MOV      5   4
0015    TGETS    4   4   4  ; "getHeight"
0016    CALL     4   2   2
0017    KSHORT   5   2
0018    CALL     3   2   3
0019    ADDVV    2   2   3
0020    CALL     1   2   2
0021    TDUP     2  10
0022    TNEW     3   3
0023    UGET     4   1      ; GestureRange
0024    MOV      5   4
0025    TGETS    4   4   6  ; "new"
0026    TDUP     6   7
0027    TNEW     7   3
0028    UGET     8   0      ; Screen
0029    MOV      9   8
0030    TGETS    8   8   8  ; "scaleBySize"
0031    KSHORT  10 200
0032    CALL     8   2   3
0033    SUBVV    8   1   8
0034    TSETB    8   7   1
0035    TSETB    1   7   2
0036    TSETS    7   6   9  ; "scale"
0037    CALL     4   0   3
0038    TSETM    4   0      ; 1
0039    TSETS    3   2  11  ; "TapDiagonal"
0040    TNEW     3   3
0041    UGET     4   1      ; GestureRange
0042    MOV      5   4
0043    TGETS    4   4   6  ; "new"
0044    TDUP     6  12
0045    TNEW     7   3
0046    UGET     8   0      ; Screen
0047    MOV      9   8
0048    TGETS    8   8   8  ; "scaleBySize"
0049    KSHORT  10 200
0050    CALL     8   2   3
0051    SUBVV    8   1   8
0052    TSETB    8   7   1
0053    TSETB    1   7   2
0054    TSETS    7   6   9  ; "scale"
0055    CALL     4   0   3
0056    TSETM    4   0      ; 1
0057    TSETS    3   2  13  ; "SwipeDiagonal"
0058    TSETS    2   0   5  ; "ges_events"
0059    RET0     0   1

-- BYTECODE -- screenshoter.lua:48-51
0001    GGET     0   0      ; "G_reader_settings"
0002    MOV      1   0
0003    TGETS    0   0   1  ; "saveSetting"
0004    KSTR     2   2      ; "screensaver_type"
0005    KSTR     3   3      ; "image_file"
0006    CALL     0   1   4
0007    GGET     0   0      ; "G_reader_settings"
0008    MOV      1   0
0009    TGETS    0   0   1  ; "saveSetting"
0010    KSTR     2   4      ; "screensaver_image"
0011    UGET     3   0      ; screenshot_name
0012    CALL     0   1   4
0013    RET0     0   1

-- BYTECODE -- screenshoter.lua:40-58
0001    GGET     2   0      ; "G_reader_settings"
0002    MOV      3   2
0003    TGETS    2   2   1  ; "readSetting"
0004    KSTR     4   2      ; "screenshot_dir"
0005    CALL     2   2   3
0006    IST          2
0007    JMP      3 => 0014
0008    UGET     2   0      ; DataStorage
0009    MOV      3   2
0010    TGETS    2   2   3  ; "getDataDir"
0011    CALL     2   2   2
0012    KSTR     3   4      ; "/screenshots/"
0013    CAT      2   2   3
0014 => MOV      3   2
0015    TGETS    4   0   6  ; "prefix"
0016    KSTR     5   7      ; "_%Y-%m-%d_%H%M%S.png"
0017    CAT      3   3   5
0018    TSETS    3   0   5  ; "screenshot_fn_fmt"
0019    ISTC     3   1
0020    JMP      3 => 0025
0021    GGET     3   8      ; "os"
0022    TGETS    3   3   9  ; "date"
0023    TGETS    4   0   5  ; "screenshot_fn_fmt"
0024    CALL     3   2   2
0025 => UGET     4   1      ; Screen
0026    MOV      5   4
0027    TGETS    4   4  10  ; "shot"
0028    MOV      6   3
0029    CALL     4   1   3
0030    UGET     4   2      ; ConfirmBox
0031    MOV      5   4
0032    TGETS    4   4  11  ; "new"
0033    TDUP     6  14
0034    UGET     7   3      ; T
0035    UGET     8   4      ; _
0036    KSTR     9  12      ; "Saved screenshot to %1.\nWould you like "~
0037    CALL     8   2   2
0038    UGET     9   5      ; BD
0039    TGETS    9   9  13  ; "filepath"
0040    MOV     10   3
0041    CALL     9   0   2
0042    CALLM    7   2   1
0043    TSETS    7   6  15  ; "text"
0044    UGET     7   4      ; _
0045    KSTR     8  16      ; "Yes"
0046    CALL     7   2   2
0047    TSETS    7   6  17  ; "ok_text"
0048    FNEW     7  18      ; screenshoter.lua:48
0049    TSETS    7   6  19  ; "ok_callback"
0050    UGET     7   4      ; _
0051    KSTR     8  20      ; "No"
0052    CALL     7   2   2
0053    TSETS    7   6  21  ; "cancel_text"
0054    CALL     4   2   3
0055    UGET     5   6      ; UIManager
0056    MOV      6   5
0057    TGETS    5   5  22  ; "show"
0058    MOV      7   4
0059    CALL     5   1   3
0060    UGET     5   6      ; UIManager
0061    MOV      6   5
0062    TGETS    5   5  23  ; "setDirty"
0063    KPRI     7   0
0064    KSTR     8  24      ; "full"
0065    CALL     5   1   4
0066    KPRI     5   2
0067    UCLO     0 => 0068
0068 => RET1     5   2

-- BYTECODE -- screenshoter.lua:68-74
0001    GGET     1   0      ; "G_reader_settings"
0002    MOV      2   1
0003    TGETS    1   1   1  ; "saveSetting"
0004    KSTR     3   2      ; "screenshot_dir"
0005    MOV      4   0
0006    KSTR     5   3      ; "/"
0007    CAT      4   4   5
0008    CALL     1   1   4
0009    UGET     1   0      ; UIManager
0010    MOV      2   1
0011    TGETS    1   1   4  ; "show"
0012    UGET     3   1      ; InfoMessage
0013    MOV      4   3
0014    TGETS    3   3   5  ; "new"
0015    TDUP     5   8
0016    UGET     6   2      ; T
0017    UGET     7   3      ; _
0018    KSTR     8   6      ; "Screenshot directory set to:\n%1"
0019    CALL     7   2   2
0020    UGET     8   4      ; BD
0021    TGETS    8   8   7  ; "dirpath"
0022    MOV      9   0
0023    CALL     8   0   2
0024    CALLM    6   2   1
0025    TSETS    6   5   9  ; "text"
0026    CALL     3   0   3
0027    CALLM    1   1   1
0028    RET0     0   1

-- BYTECODE -- screenshoter.lua:65-76
0001    UGET     0   0      ; UIManager
0002    MOV      1   0
0003    TGETS    0   0   0  ; "close"
0004    UGET     2   1      ; self
0005    TGETS    2   2   1  ; "choose_dialog"
0006    CALL     0   1   3
0007    GGET     0   2      ; "require"
0008    KSTR     1   3      ; "ui/downloadmgr"
0009    CALL     0   2   2
0010    MOV      1   0
0011    TGETS    0   0   4  ; "new"
0012    TDUP     2   6
0013    FNEW     3   5      ; screenshoter.lua:68
0014    TSETS    3   2   7  ; "onConfirm"
0015    CALL     0   2   3
0016    MOV      1   0
0017    TGETS    0   0   8  ; "chooseDir"
0018    CALL     0   1   2
0019    RET0     0   1

-- BYTECODE -- screenshoter.lua:82-84
0001    UGET     0   0      ; UIManager
0002    MOV      1   0
0003    TGETS    0   0   0  ; "close"
0004    UGET     2   1      ; self
0005    TGETS    2   2   1  ; "choose_dialog"
0006    CALL     0   1   3
0007    RET0     0   1

-- BYTECODE -- screenshoter.lua:60-93
0001    TNEW     1   0
0002    GGET     2   0      ; "table"
0003    TGETS    2   2   1  ; "insert"
0004    MOV      3   1
0005    TNEW     4   3
0006    TDUP     5   3
0007    UGET     6   0      ; _
0008    KSTR     7   2      ; "Choose screenshot directory"
0009    CALL     6   2   2
0010    TSETS    6   5   4  ; "text"
0011    FNEW     6   5      ; screenshoter.lua:65
0012    TSETS    6   5   6  ; "callback"
0013    TSETB    5   4   1
0014    CALL     2   1   3
0015    GGET     2   0      ; "table"
0016    TGETS    2   2   1  ; "insert"
0017    MOV      3   1
0018    TNEW     4   3
0019    TDUP     5   8
0020    UGET     6   0      ; _
0021    KSTR     7   7      ; "Close"
0022    CALL     6   2   2
0023    TSETS    6   5   4  ; "text"
0024    FNEW     6   9      ; screenshoter.lua:82
0025    TSETS    6   5   6  ; "callback"
0026    TSETB    5   4   1
0027    CALL     2   1   3
0028    GGET     2  10      ; "G_reader_settings"
0029    MOV      3   2
0030    TGETS    2   2  11  ; "readSetting"
0031    KSTR     4  12      ; "screenshot_dir"
0032    CALL     2   2   3
0033    IST          2
0034    JMP      3 => 0041
0035    UGET     2   5      ; DataStorage
0036    MOV      3   2
0037    TGETS    2   2  13  ; "getDataDir"
0038    CALL     2   2   2
0039    KSTR     3  14      ; "/screenshots/"
0040    CAT      2   2   3
0041 => UGET     3   6      ; ButtonDialogTitle
0042    MOV      4   3
0043    TGETS    3   3  16  ; "new"
0044    TDUP     5  19
0045    UGET     6   3      ; T
0046    UGET     7   0      ; _
0047    KSTR     8  17      ; "Current screenshot directory:\n%1"
0048    CALL     7   2   2
0049    UGET     8   4      ; BD
0050    TGETS    8   8  18  ; "dirpath"
0051    MOV      9   2
0052    CALL     8   0   2
0053    CALLM    6   2   1
0054    TSETS    6   5  20  ; "title"
0055    TSETS    1   5  21  ; "buttons"
0056    CALL     3   2   3
0057    TSETS    3   0  15  ; "choose_dialog"
0058    UGET     3   1      ; UIManager
0059    MOV      4   3
0060    TGETS    3   3  22  ; "show"
0061    TGETS    5   0  15  ; "choose_dialog"
0062    CALL     3   1   3
0063    UCLO     0 => 0064
0064 => RET0     0   1

-- BYTECODE -- screenshoter.lua:95-97
0001    MOV      2   0
0002    TGETS    1   0   0  ; "onScreenshot"
0003    CALLT    1   2

-- BYTECODE -- screenshoter.lua:99-101
0001    MOV      2   0
0002    TGETS    1   0   0  ; "onScreenshot"
0003    CALLT    1   2

-- BYTECODE -- screenshoter.lua:0-104
0001    GGET     0   0      ; "require"
0002    KSTR     1   1      ; "ui/bidi"
0003    CALL     0   2   2
0004    GGET     1   0      ; "require"
0005    KSTR     2   2      ; "ui/widget/buttondialogtitle"
0006    CALL     1   2   2
0007    GGET     2   0      ; "require"
0008    KSTR     3   3      ; "ui/widget/confirmbox"
0009    CALL     2   2   2
0010    GGET     3   0      ; "require"
0011    KSTR     4   4      ; "datastorage"
0012    CALL     3   2   2
0013    GGET     4   0      ; "require"
0014    KSTR     5   5      ; "ui/gesturerange"
0015    CALL     4   2   2
0016    GGET     5   0      ; "require"
0017    KSTR     6   6      ; "ui/widget/infomessage"
0018    CALL     5   2   2
0019    GGET     6   0      ; "require"
0020    KSTR     7   7      ; "ui/widget/container/inputcontainer"
0021    CALL     6   2   2
0022    GGET     7   0      ; "require"
0023    KSTR     8   8      ; "ui/uimanager"
0024    CALL     7   2   2
0025    GGET     8   0      ; "require"
0026    KSTR     9   9      ; "device"
0027    CALL     8   2   2
0028    TGETS    8   8  10  ; "screen"
0029    GGET     9   0      ; "require"
0030    KSTR    10  11      ; "ffi/util"
0031    CALL     9   2   2
0032    TGETS    9   9  12  ; "template"
0033    GGET    10   0      ; "require"
0034    KSTR    11  13      ; "gettext"
0035    CALL    10   2   2
0036    MOV     12   6
0037    TGETS   11   6  14  ; "new"
0038    TDUP    13  15
0039    CALL    11   2   3
0040    FNEW    12  17      ; screenshoter.lua:17
0041    TSETS   12  11  16  ; "init"
0042    FNEW    12  19      ; screenshoter.lua:40
0043    TSETS   12  11  18  ; "onScreenshot"
0044    FNEW    12  21      ; screenshoter.lua:60
0045    TSETS   12  11  20  ; "chooseFolder"
0046    FNEW    12  23      ; screenshoter.lua:95
0047    TSETS   12  11  22  ; "onTapDiagonal"
0048    FNEW    12  25      ; screenshoter.lua:99
0049    TSETS   12  11  24  ; "onSwipeDiagonal"
0050    UCLO     0 => 0051
0051 => RET1    11   2

