
main <./frontend/ui/elements/screen_color_menu_table.lua:0,0> (38 instructions, 152 bytes at 0x7fb779c06900)
0+ params, 8 slots, 0 upvalues, 5 locals, 14 constants, 1 function
	1	[1]	GETGLOBAL	0 -1	; require
	2	[1]	LOADK    	1 -2	; "ui/event"
	3	[1]	CALL     	0 2 2
	4	[2]	GETGLOBAL	1 -1	; require
	5	[2]	LOADK    	2 -3	; "device"
	6	[2]	CALL     	1 2 2
	7	[2]	GETTABLE 	1 1 -4	; "screen"
	8	[3]	GETGLOBAL	2 -1	; require
	9	[3]	LOADK    	3 -5	; "ui/uimanager"
	10	[3]	CALL     	2 2 2
	11	[4]	GETGLOBAL	3 -1	; require
	12	[4]	LOADK    	4 -6	; "document/canvascontext"
	13	[4]	CALL     	3 2 2
	14	[5]	GETGLOBAL	4 -1	; require
	15	[5]	LOADK    	5 -7	; "gettext"
	16	[5]	CALL     	4 2 2
	17	[8]	NEWTABLE 	5 0 4
	18	[9]	MOVE     	6 4
	19	[9]	LOADK    	7 -9	; "Color rendering"
	20	[9]	CALL     	6 2 2
	21	[9]	SETTABLE 	5 -8 6	; "text" -
	22	[10]	SELF     	6 1 -11	; "isColorEnabled"
	23	[10]	CALL     	6 2 2
	24	[10]	TEST     	6 0 1
	25	[10]	JMP      	2	; to 28
	26	[10]	SELF     	6 1 -12	; "isColorScreen"
	27	[10]	CALL     	6 2 2
	28	[10]	SETTABLE 	5 -10 6	; "enabled" -
	29	[11]	GETTABLE 	6 1 -11	; "isColorEnabled"
	30	[11]	SETTABLE 	5 -13 6	; "checked_func" -
	31	[18]	CLOSURE  	6 0	; 0x7fb779c06bf0
	32	[18]	MOVE     	0 1
	33	[18]	MOVE     	0 3
	34	[18]	MOVE     	0 2
	35	[18]	MOVE     	0 0
	36	[18]	SETTABLE 	5 -14 6	; "callback" -
	37	[19]	RETURN   	5 2
	38	[19]	RETURN   	0 1

function <./frontend/ui/elements/screen_color_menu_table.lua:12,18> (21 instructions, 84 bytes at 0x7fb779c06bf0)
0 params, 6 slots, 4 upvalues, 1 local, 8 constants, 0 functions
	1	[13]	GETUPVAL 	0 0	; Screen
	2	[13]	GETTABLE 	0 0 -1	; "isColorEnabled"
	3	[13]	CALL     	0 1 2
	4	[13]	NOT      	0 0
	5	[15]	GETGLOBAL	1 -2	; G_reader_settings
	6	[15]	SELF     	1 1 -3	; "saveSetting"
	7	[15]	LOADK    	3 -4	; "color_rendering"
	8	[15]	MOVE     	4 0
	9	[15]	CALL     	1 4 1
	10	[16]	GETUPVAL 	1 1	; CanvasContext
	11	[16]	SELF     	1 1 -5	; "setColorRenderingEnabled"
	12	[16]	MOVE     	3 0
	13	[16]	CALL     	1 3 1
	14	[17]	GETUPVAL 	1 2	; UIManager
	15	[17]	SELF     	1 1 -6	; "broadcastEvent"
	16	[17]	GETUPVAL 	3 3	; Event
	17	[17]	SELF     	3 3 -7	; "new"
	18	[17]	LOADK    	5 -8	; "ColorRenderingUpdate"
	19	[17]	CALL     	3 3 0
	20	[17]	CALL     	1 0 1
	21	[18]	RETURN   	0 1
