-- BYTECODE -- screenshoter_spec.lua:5-16
0001    GGET     0   0      ; "require"
0002    KSTR     1   1      ; "commonrequire"
0003    CALL     0   1   2
0004    GGET     0   0      ; "require"
0005    KSTR     1   2      ; "document/documentregistry"
0006    CALL     0   2   2
0007    USETV    0   0      ; DocumentRegistry
0008    GGET     0   0      ; "require"
0009    KSTR     1   3      ; "apps/reader/readerui"
0010    CALL     0   2   2
0011    USETV    1   0      ; ReaderUI
0012    GGET     0   0      ; "require"
0013    KSTR     1   4      ; "libs/libkoreader-lfs"
0014    CALL     0   2   2
0015    USETV    2   0      ; lfs
0016    GGET     0   0      ; "require"
0017    KSTR     1   5      ; "ui/uimanager"
0018    CALL     0   2   2
0019    USETV    3   0      ; UIManager
0020    GGET     0   0      ; "require"
0021    KSTR     1   6      ; "ui/event"
0022    CALL     0   2   2
0023    USETV    4   0      ; Event
0024    UGET     0   1      ; ReaderUI
0025    MOV      1   0
0026    TGETS    0   0   7  ; "new"
0027    TDUP     2   9
0028    UGET     3   0      ; DocumentRegistry
0029    MOV      4   3
0030    TGETS    3   3   8  ; "openDocument"
0031    UGET     5   6      ; sample_epub
0032    CALL     3   2   3
0033    TSETS    3   2  10  ; "document"
0034    CALL     0   2   3
0035    USETV    5   0      ; readerui
0036    RET0     0   1

-- BYTECODE -- screenshoter_spec.lua:18-20
0001    UGET     0   0      ; readerui
0002    MOV      1   0
0003    TGETS    0   0   0  ; "handleEvent"
0004    UGET     2   1      ; Event
0005    MOV      3   2
0006    TGETS    2   2   1  ; "new"
0007    KSTR     4   2      ; "ChangeScreenMode"
0008    KSTR     5   3      ; "portrait"
0009    CALL     2   0   4
0010    CALLM    0   1   1
0011    RET0     0   1

-- BYTECODE -- screenshoter_spec.lua:27-27
0001    UGET     0   0      ; UIManager
0002    MOV      1   0
0003    TGETS    0   0   0  ; "close"
0004    UGET     2   1      ; readerui
0005    CALL     0   1   3
0006    RET0     0   1

-- BYTECODE -- screenshoter_spec.lua:22-32
0001    KSTR     0   0      ; "screenshots/reader_screenshot_portrait.p"~
0002    UGET     1   0      ; readerui
0003    MOV      2   1
0004    TGETS    1   1   1  ; "handleEvent"
0005    UGET     3   1      ; Event
0006    MOV      4   3
0007    TGETS    3   3   2  ; "new"
0008    KSTR     5   3      ; "ChangeScreenMode"
0009    KSTR     6   4      ; "portrait"
0010    CALL     3   0   4
0011    CALLM    1   1   1
0012    UGET     1   2      ; UIManager
0013    MOV      2   1
0014    TGETS    1   1   5  ; "quit"
0015    CALL     1   1   2
0016    UGET     1   2      ; UIManager
0017    MOV      2   1
0018    TGETS    1   1   6  ; "show"
0019    UGET     3   0      ; readerui
0020    CALL     1   1   3
0021    UGET     1   2      ; UIManager
0022    MOV      2   1
0023    TGETS    1   1   7  ; "scheduleIn"
0024    KSHORT   3   1
0025    FNEW     4   8      ; screenshoter_spec.lua:27
0026    CALL     1   1   4
0027    UGET     1   2      ; UIManager
0028    MOV      2   1
0029    TGETS    1   1   9  ; "run"
0030    CALL     1   1   2
0031    UGET     1   0      ; readerui
0032    TGETS    1   1  10  ; "screenshot"
0033    MOV      2   1
0034    TGETS    1   1  11  ; "onScreenshot"
0035    MOV      3   0
0036    CALL     1   1   3
0037    GGET     1  12      ; "assert"
0038    TGETS    1   1  13  ; "truthy"
0039    UGET     2   3      ; lfs
0040    TGETS    2   2  14  ; "attributes"
0041    MOV      3   0
0042    KSTR     4  15      ; "mode"
0043    CALL     2   0   3
0044    CALLM    1   1   0
0045    UGET     1   2      ; UIManager
0046    MOV      2   1
0047    TGETS    1   1   5  ; "quit"
0048    CALL     1   1   2
0049    RET0     0   1

-- BYTECODE -- screenshoter_spec.lua:39-39
0001    UGET     0   0      ; UIManager
0002    MOV      1   0
0003    TGETS    0   0   0  ; "close"
0004    UGET     2   1      ; readerui
0005    CALL     0   1   3
0006    RET0     0   1

-- BYTECODE -- screenshoter_spec.lua:34-44
0001    KSTR     0   0      ; "screenshots/reader_screenshot_landscape."~
0002    UGET     1   0      ; readerui
0003    MOV      2   1
0004    TGETS    1   1   1  ; "handleEvent"
0005    UGET     3   1      ; Event
0006    MOV      4   3
0007    TGETS    3   3   2  ; "new"
0008    KSTR     5   3      ; "ChangeScreenMode"
0009    KSTR     6   4      ; "landscape"
0010    CALL     3   0   4
0011    CALLM    1   1   1
0012    UGET     1   2      ; UIManager
0013    MOV      2   1
0014    TGETS    1   1   5  ; "quit"
0015    CALL     1   1   2
0016    UGET     1   2      ; UIManager
0017    MOV      2   1
0018    TGETS    1   1   6  ; "show"
0019    UGET     3   0      ; readerui
0020    CALL     1   1   3
0021    UGET     1   2      ; UIManager
0022    MOV      2   1
0023    TGETS    1   1   7  ; "scheduleIn"
0024    KSHORT   3   2
0025    FNEW     4   8      ; screenshoter_spec.lua:39
0026    CALL     1   1   4
0027    UGET     1   2      ; UIManager
0028    MOV      2   1
0029    TGETS    1   1   9  ; "run"
0030    CALL     1   1   2
0031    UGET     1   0      ; readerui
0032    TGETS    1   1  10  ; "screenshot"
0033    MOV      2   1
0034    TGETS    1   1  11  ; "onScreenshot"
0035    MOV      3   0
0036    CALL     1   1   3
0037    GGET     1  12      ; "assert"
0038    TGETS    1   1  13  ; "truthy"
0039    UGET     2   3      ; lfs
0040    TGETS    2   2  14  ; "attributes"
0041    MOV      3   0
0042    KSTR     4  15      ; "mode"
0043    CALL     2   0   3
0044    CALLM    1   1   0
0045    UGET     1   2      ; UIManager
0046    MOV      2   1
0047    TGETS    1   1   5  ; "quit"
0048    CALL     1   1   2
0049    RET0     0   1

-- BYTECODE -- screenshoter_spec.lua:1-45
0001    KNIL     0   4
0002    KSTR     5   0      ; "spec/front/unit/data/leaves.epub"
0003    KPRI     6   0
0004    GGET     7   1      ; "setup"
0005    FNEW     8   2      ; screenshoter_spec.lua:5
0006    CALL     7   1   2
0007    GGET     7   3      ; "teardown"
0008    FNEW     8   4      ; screenshoter_spec.lua:18
0009    CALL     7   1   2
0010    GGET     7   5      ; "it"
0011    KSTR     8   6      ; "should get screenshot in portrait"
0012    FNEW     9   7      ; screenshoter_spec.lua:22
0013    CALL     7   1   3
0014    GGET     7   5      ; "it"
0015    KSTR     8   8      ; "should get screenshot in landscape"
0016    FNEW     9   9      ; screenshoter_spec.lua:34
0017    CALL     7   1   3
0018    UCLO     0 => 0019
0019 => RET0     0   1

-- BYTECODE -- screenshoter_spec.lua:0-46
0001    GGET     0   0      ; "describe"
0002    KSTR     1   1      ; "ReaderScreenshot module"
0003    FNEW     2   2      ; screenshoter_spec.lua:1
0004    CALL     0   1   3
0005    RET0     0   1

