-- BYTECODE -- screen_toggle_gsensor.lua:6-8
0001    GGET     0   0      ; "G_reader_settings"
0002    MOV      1   0
0003    TGETS    0   0   1  ; "isTrue"
0004    KSTR     2   2      ; "input_ignore_gsensor"
0005    CALLT    0   3

-- BYTECODE -- screen_toggle_gsensor.lua:9-12
0001    GGET     0   0      ; "G_reader_settings"
0002    MOV      1   0
0003    TGETS    0   0   1  ; "flipNilOrFalse"
0004    KSTR     2   2      ; "input_ignore_gsensor"
0005    CALL     0   1   3
0006    UGET     0   0      ; Device
0007    MOV      1   0
0008    TGETS    0   0   3  ; "toggleGSensor"
0009    GGET     2   0      ; "G_reader_settings"
0010    MOV      3   2
0011    TGETS    2   2   4  ; "isTrue"
0012    KSTR     4   2      ; "input_ignore_gsensor"
0013    CALL     2   2   3
0014    NOT      2   2
0015    CALL     0   1   3
0016    RET0     0   1

-- BYTECODE -- screen_toggle_gsensor.lua:0-14
0001    GGET     0   0      ; "require"
0002    KSTR     1   1      ; "device"
0003    CALL     0   2   2
0004    GGET     1   0      ; "require"
0005    KSTR     2   2      ; "gettext"
0006    CALL     1   2   2
0007    TDUP     2   4
0008    MOV      3   1
0009    KSTR     4   3      ; "Ignore accelerometer rotation events"
0010    CALL     3   2   2
0011    TSETS    3   2   5  ; "text"
0012    FNEW     3   6      ; screen_toggle_gsensor.lua:6
0013    TSETS    3   2   7  ; "checked_func"
0014    FNEW     3   8      ; screen_toggle_gsensor.lua:9
0015    TSETS    3   2   9  ; "callback"
0016    UCLO     0 => 0017
0017 => RET1     2   2

