-- BYTECODE -- screensaverwidget.lua:14-31
0001    UGET     1   0      ; Device
0002    MOV      2   1
0003    TGETS    1   1   0  ; "hasKeys"
0004    CALL     1   2   2
0005    ISF          1
0006    JMP      2 => 0013
0007    TDUP     1   4
0008    TDUP     2   3
0009    TDUP     3   2
0010    TSETB    3   2   1
0011    TSETS    2   1   5  ; "Close"
0012    TSETS    1   0   1  ; "key_events"
0013 => UGET     1   0      ; Device
0014    MOV      2   1
0015    TGETS    1   1   6  ; "isTouchDevice"
0016    CALL     1   2   2
0017    ISF          1
0018    JMP      2 => 0045
0019    UGET     1   1      ; Geom
0020    MOV      2   1
0021    TGETS    1   1   7  ; "new"
0022    TDUP     3   8
0023    UGET     4   2      ; Screen
0024    MOV      5   4
0025    TGETS    4   4   9  ; "getWidth"
0026    CALL     4   2   2
0027    TSETS    4   3  10  ; "w"
0028    UGET     4   2      ; Screen
0029    MOV      5   4
0030    TGETS    4   4  11  ; "getHeight"
0031    CALL     4   2   2
0032    TSETS    4   3  12  ; "h"
0033    CALL     1   2   3
0034    TDUP     2  16
0035    TNEW     3   3
0036    UGET     4   3      ; GestureRange
0037    MOV      5   4
0038    TGETS    4   4   7  ; "new"
0039    TDUP     6  14
0040    TSETS    1   6  15  ; "range"
0041    CALL     4   0   3
0042    TSETM    4   0      ; 1
0043    TSETS    3   2  17  ; "Tap"
0044    TSETS    2   0  13  ; "ges_events"
0045 => MOV      2   0
0046    TGETS    1   0  18  ; "update"
0047    CALL     1   1   2
0048    RET0     0   1

-- BYTECODE -- screensaverwidget.lua:54-57
0001    UGET     0   0      ; self
0002    TGETS    0   0   0  ; "main_frame"
0003    TGETS    0   0   1  ; "dimen"
0004    KSTR     1   2      ; "full"
0005    MOV      2   0
0006    RET      1   3

-- BYTECODE -- screensaverwidget.lua:33-58
0001    UGET     1   0      ; Screen
0002    MOV      2   1
0003    TGETS    1   1   1  ; "getHeight"
0004    CALL     1   2   2
0005    TSETS    1   0   0  ; "height"
0006    UGET     1   0      ; Screen
0007    MOV      2   1
0008    TGETS    1   1   3  ; "getWidth"
0009    CALL     1   2   2
0010    TSETS    1   0   2  ; "width"
0011    UGET     1   1      ; Geom
0012    MOV      2   1
0013    TGETS    1   1   5  ; "new"
0014    TDUP     3   6
0015    TGETS    4   0   2  ; "width"
0016    TSETS    4   3   7  ; "w"
0017    TGETS    4   0   0  ; "height"
0018    TSETS    4   3   8  ; "h"
0019    CALL     1   2   3
0020    TSETS    1   0   4  ; "region"
0021    UGET     1   2      ; FrameContainer
0022    MOV      2   1
0023    TGETS    1   1   5  ; "new"
0024    TDUP     3  10
0025    TGETS    4   0  11  ; "background"
0026    TSETS    4   3  11  ; "background"
0027    TGETS    4   0   2  ; "width"
0028    TSETS    4   3   2  ; "width"
0029    TGETS    4   0   0  ; "height"
0030    TSETS    4   3   0  ; "height"
0031    TGETS    4   0  12  ; "widget"
0032    TSETB    4   3   1
0033    CALL     1   2   3
0034    TSETS    1   0   9  ; "main_frame"
0035    KPRI     1   2
0036    TSETS    1   0  13  ; "dithered"
0037    TGETS    1   0   9  ; "main_frame"
0038    TSETB    1   0   1
0039    UGET     1   3      ; UIManager
0040    MOV      2   1
0041    TGETS    1   1  14  ; "setDirty"
0042    MOV      3   0
0043    FNEW     4  15      ; screensaverwidget.lua:54
0044    CALL     1   1   4
0045    UCLO     0 => 0046
0046 => RET0     0   1

-- BYTECODE -- screensaverwidget.lua:61-63
0001    KSTR     0   0      ; "full"
0002    UGET     1   0      ; self
0003    TGETS    1   1   1  ; "main_frame"
0004    TGETS    1   1   2  ; "dimen"
0005    RET      0   3

-- BYTECODE -- screensaverwidget.lua:60-65
0001    UGET     1   0      ; UIManager
0002    MOV      2   1
0003    TGETS    1   1   0  ; "setDirty"
0004    MOV      3   0
0005    FNEW     4   1      ; screensaverwidget.lua:61
0006    CALL     1   1   4
0007    KPRI     1   2
0008    UCLO     0 => 0009
0009 => RET1     1   2

-- BYTECODE -- screensaverwidget.lua:67-72
0001    TGETS    3   2   0  ; "pos"
0002    MOV      4   3
0003    TGETS    3   3   1  ; "intersectWith"
0004    TGETS    5   0   2  ; "main_frame"
0005    TGETS    5   5   3  ; "dimen"
0006    CALL     3   2   3
0007    ISF          3
0008    JMP      4 => 0012
0009    MOV      4   0
0010    TGETS    3   0   4  ; "onClose"
0011    CALL     3   1   2
0012 => KPRI     3   2
0013    RET1     3   2

-- BYTECODE -- screensaverwidget.lua:74-77
0001    UGET     1   0      ; UIManager
0002    MOV      2   1
0003    TGETS    1   1   0  ; "close"
0004    MOV      3   0
0005    KSTR     4   1      ; "full"
0006    CALL     1   1   4
0007    KPRI     1   2
0008    RET1     1   2

-- BYTECODE -- screensaverwidget.lua:79-82
0001    MOV      2   0
0002    TGETS    1   0   0  ; "onClose"
0003    CALL     1   1   2
0004    KPRI     1   2
0005    RET1     1   2

-- BYTECODE -- screensaverwidget.lua:85-87
0001    KSTR     0   0      ; "full"
0002    UGET     1   0      ; self
0003    TGETS    1   1   1  ; "main_frame"
0004    TGETS    1   1   2  ; "dimen"
0005    RET      0   3

-- BYTECODE -- screensaverwidget.lua:84-89
0001    UGET     1   0      ; UIManager
0002    MOV      2   1
0003    TGETS    1   1   0  ; "setDirty"
0004    KPRI     3   0
0005    FNEW     4   1      ; screensaverwidget.lua:85
0006    CALL     1   1   4
0007    KPRI     1   2
0008    UCLO     0 => 0009
0009 => RET1     1   2

-- BYTECODE -- screensaverwidget.lua:0-92
0001    GGET     0   0      ; "require"
0002    KSTR     1   1      ; "device"
0003    CALL     0   2   2
0004    GGET     1   0      ; "require"
0005    KSTR     2   2      ; "ui/geometry"
0006    CALL     1   2   2
0007    GGET     2   0      ; "require"
0008    KSTR     3   3      ; "ui/gesturerange"
0009    CALL     2   2   2
0010    GGET     3   0      ; "require"
0011    KSTR     4   4      ; "ui/widget/container/framecontainer"
0012    CALL     3   2   2
0013    GGET     4   0      ; "require"
0014    KSTR     5   5      ; "ui/widget/container/inputcontainer"
0015    CALL     4   2   2
0016    GGET     5   0      ; "require"
0017    KSTR     6   6      ; "ui/uimanager"
0018    CALL     5   2   2
0019    TGETS    6   0   7  ; "screen"
0020    MOV      8   4
0021    TGETS    7   4   8  ; "new"
0022    TDUP     9   9
0023    CALL     7   2   3
0024    FNEW     8  11      ; screensaverwidget.lua:14
0025    TSETS    8   7  10  ; "init"
0026    FNEW     8  13      ; screensaverwidget.lua:33
0027    TSETS    8   7  12  ; "update"
0028    FNEW     8  15      ; screensaverwidget.lua:60
0029    TSETS    8   7  14  ; "onShow"
0030    FNEW     8  17      ; screensaverwidget.lua:67
0031    TSETS    8   7  16  ; "onTap"
0032    FNEW     8  19      ; screensaverwidget.lua:74
0033    TSETS    8   7  18  ; "onClose"
0034    FNEW     8  21      ; screensaverwidget.lua:79
0035    TSETS    8   7  20  ; "onAnyKeyPressed"
0036    FNEW     8  23      ; screensaverwidget.lua:84
0037    TSETS    8   7  22  ; "onCloseWidget"
0038    UCLO     0 => 0039
0039 => RET1     7   2

