
main <./frontend/ui/widget/screenshoter.lua:0,0> (67 instructions, 268 bytes at 0x7f93d74068d0)
0+ params, 14 slots, 0 upvalues, 12 locals, 22 constants, 5 functions
	1	[1]	GETGLOBAL	0 -1	; require
	2	[1]	LOADK    	1 -2	; "ui/bidi"
	3	[1]	CALL     	0 2 2
	4	[2]	GETGLOBAL	1 -1	; require
	5	[2]	LOADK    	2 -3	; "ui/widget/buttondialogtitle"
	6	[2]	CALL     	1 2 2
	7	[3]	GETGLOBAL	2 -1	; require
	8	[3]	LOADK    	3 -4	; "ui/widget/confirmbox"
	9	[3]	CALL     	2 2 2
	10	[4]	GETGLOBAL	3 -1	; require
	11	[4]	LOADK    	4 -5	; "datastorage"
	12	[4]	CALL     	3 2 2
	13	[5]	GETGLOBAL	4 -1	; require
	14	[5]	LOADK    	5 -6	; "ui/gesturerange"
	15	[5]	CALL     	4 2 2
	16	[6]	GETGLOBAL	5 -1	; require
	17	[6]	LOADK    	6 -7	; "ui/widget/infomessage"
	18	[6]	CALL     	5 2 2
	19	[7]	GETGLOBAL	6 -1	; require
	20	[7]	LOADK    	7 -8	; "ui/widget/container/inputcontainer"
	21	[7]	CALL     	6 2 2
	22	[8]	GETGLOBAL	7 -1	; require
	23	[8]	LOADK    	8 -9	; "ui/uimanager"
	24	[8]	CALL     	7 2 2
	25	[9]	GETGLOBAL	8 -1	; require
	26	[9]	LOADK    	9 -10	; "device"
	27	[9]	CALL     	8 2 2
	28	[9]	GETTABLE 	8 8 -11	; "screen"
	29	[10]	GETGLOBAL	9 -1	; require
	30	[10]	LOADK    	10 -12	; "ffi/util"
	31	[10]	CALL     	9 2 2
	32	[10]	GETTABLE 	9 9 -13	; "template"
	33	[11]	GETGLOBAL	10 -1	; require
	34	[11]	LOADK    	11 -14	; "gettext"
	35	[11]	CALL     	10 2 2
	36	[13]	SELF     	11 6 -15	; "new"
	37	[13]	NEWTABLE 	13 0 1
	38	[14]	SETTABLE 	13 -16 -17	; "prefix" "Screenshot"
	39	[13]	CALL     	11 3 2
	40	[38]	CLOSURE  	12 0	; 0x7f93d74070d0
	41	[38]	MOVE     	0 8
	42	[38]	MOVE     	0 4
	43	[17]	SETTABLE 	11 -18 12	; "init" -
	44	[58]	CLOSURE  	12 1	; 0x7f93d74078e0
	45	[58]	MOVE     	0 3
	46	[58]	MOVE     	0 8
	47	[58]	MOVE     	0 2
	48	[58]	MOVE     	0 9
	49	[58]	MOVE     	0 10
	50	[58]	MOVE     	0 0
	51	[58]	MOVE     	0 7
	52	[40]	SETTABLE 	11 -19 12	; "onScreenshot" -
	53	[93]	CLOSURE  	12 2	; 0x7f93d7408620
	54	[93]	MOVE     	0 10
	55	[93]	MOVE     	0 7
	56	[93]	MOVE     	0 5
	57	[93]	MOVE     	0 9
	58	[93]	MOVE     	0 0
	59	[93]	MOVE     	0 3
	60	[93]	MOVE     	0 1
	61	[60]	SETTABLE 	11 -20 12	; "chooseFolder" -
	62	[97]	CLOSURE  	12 3	; 0x7f93d7408880
	63	[95]	SETTABLE 	11 -21 12	; "onTapDiagonal" -
	64	[101]	CLOSURE  	12 4	; 0x7f93d7409ae0
	65	[99]	SETTABLE 	11 -22 12	; "onSwipeDiagonal" -
	66	[103]	RETURN   	11 2
	67	[103]	RETURN   	0 1

function <./frontend/ui/widget/screenshoter.lua:17,38> (57 instructions, 228 bytes at 0x7f93d74070d0)
1 param, 11 slots, 2 upvalues, 2 locals, 18 constants, 0 functions
	1	[18]	GETGLOBAL	1 -1	; math
	2	[18]	GETTABLE 	1 1 -2	; "sqrt"
	3	[19]	GETGLOBAL	2 -1	; math
	4	[19]	GETTABLE 	2 2 -3	; "pow"
	5	[19]	GETUPVAL 	3 0	; Screen
	6	[19]	SELF     	3 3 -4	; "getWidth"
	7	[19]	CALL     	3 2 2
	8	[19]	LOADK    	4 -5	; 2
	9	[19]	CALL     	2 3 2
	10	[20]	GETGLOBAL	3 -1	; math
	11	[20]	GETTABLE 	3 3 -3	; "pow"
	12	[20]	GETUPVAL 	4 0	; Screen
	13	[20]	SELF     	4 4 -6	; "getHeight"
	14	[20]	CALL     	4 2 2
	15	[20]	LOADK    	5 -5	; 2
	16	[20]	CALL     	3 3 2
	17	[20]	ADD      	2 2 3
	18	[18]	CALL     	1 2 2
	19	[22]	NEWTABLE 	2 0 2
	20	[23]	NEWTABLE 	3 0 0
	21	[24]	GETUPVAL 	4 1	; GestureRange
	22	[24]	SELF     	4 4 -9	; "new"
	23	[24]	NEWTABLE 	6 0 3
	24	[25]	SETTABLE 	6 -10 -11	; "ges" "two_finger_tap"
	25	[26]	NEWTABLE 	7 2 0
	26	[26]	GETUPVAL 	8 0	; Screen
	27	[26]	SELF     	8 8 -13	; "scaleBySize"
	28	[26]	LOADK    	10 -14	; 200
	29	[26]	CALL     	8 3 2
	30	[26]	SUB      	8 1 8
	31	[26]	MOVE     	9 1
	32	[26]	SETLIST  	7 2 1	; 1
	33	[26]	SETTABLE 	6 -12 7	; "scale" -
	34	[27]	SETTABLE 	6 -15 -16	; "rate" 1
	35	[24]	CALL     	4 3 0
	36	[29]	SETLIST  	3 0 1	; 1
	37	[29]	SETTABLE 	2 -8 3	; "TapDiagonal" -
	38	[30]	NEWTABLE 	3 0 0
	39	[31]	GETUPVAL 	4 1	; GestureRange
	40	[31]	SELF     	4 4 -9	; "new"
	41	[31]	NEWTABLE 	6 0 3
	42	[32]	SETTABLE 	6 -10 -18	; "ges" "swipe"
	43	[33]	NEWTABLE 	7 2 0
	44	[33]	GETUPVAL 	8 0	; Screen
	45	[33]	SELF     	8 8 -13	; "scaleBySize"
	46	[33]	LOADK    	10 -14	; 200
	47	[33]	CALL     	8 3 2
	48	[33]	SUB      	8 1 8
	49	[33]	MOVE     	9 1
	50	[33]	SETLIST  	7 2 1	; 1
	51	[33]	SETTABLE 	6 -12 7	; "scale" -
	52	[34]	SETTABLE 	6 -15 -16	; "rate" 1
	53	[31]	CALL     	4 3 0
	54	[36]	SETLIST  	3 0 1	; 1
	55	[36]	SETTABLE 	2 -17 3	; "SwipeDiagonal" -
	56	[37]	SETTABLE 	0 -7 2	; "ges_events" -
	57	[38]	RETURN   	0 1

function <./frontend/ui/widget/screenshoter.lua:40,58> (63 instructions, 252 bytes at 0x7f93d74078e0)
2 params, 11 slots, 7 upvalues, 5 locals, 23 constants, 1 function
	1	[41]	GETGLOBAL	2 -1	; G_reader_settings
	2	[41]	SELF     	2 2 -2	; "readSetting"
	3	[41]	LOADK    	4 -3	; "screenshot_dir"
	4	[41]	CALL     	2 3 2
	5	[41]	TEST     	2 0 1
	6	[41]	JMP      	5	; to 12
	7	[41]	GETUPVAL 	2 0	; DataStorage
	8	[41]	SELF     	2 2 -4	; "getDataDir"
	9	[41]	CALL     	2 2 2
	10	[41]	LOADK    	3 -5	; "/screenshots/"
	11	[41]	CONCAT   	2 2 3
	12	[42]	MOVE     	3 2
	13	[42]	GETTABLE 	4 0 -7	; "prefix"
	14	[42]	LOADK    	5 -8	; "_%Y-%m-%d_%H%M%S.png"
	15	[42]	CONCAT   	3 3 5
	16	[42]	SETTABLE 	0 -6 3	; "screenshot_fn_fmt" -
	17	[43]	TESTSET  	3 1 1
	18	[43]	JMP      	4	; to 23
	19	[43]	GETGLOBAL	3 -9	; os
	20	[43]	GETTABLE 	3 3 -10	; "date"
	21	[43]	GETTABLE 	4 0 -6	; "screenshot_fn_fmt"
	22	[43]	CALL     	3 2 2
	23	[44]	GETUPVAL 	4 1	; Screen
	24	[44]	SELF     	4 4 -11	; "shot"
	25	[44]	MOVE     	6 3
	26	[44]	CALL     	4 3 1
	27	[45]	GETUPVAL 	4 2	; ConfirmBox
	28	[45]	SELF     	4 4 -12	; "new"
	29	[45]	NEWTABLE 	6 0 4
	30	[46]	GETUPVAL 	7 3	; T
	31	[46]	GETUPVAL 	8 4	; _
	32	[46]	LOADK    	9 -14	; "Saved screenshot to %1.\nWould you like to set it as screensaver?"
	33	[46]	CALL     	8 2 2
	34	[46]	GETUPVAL 	9 5	; BD
	35	[46]	GETTABLE 	9 9 -15	; "filepath"
	36	[46]	MOVE     	10 3
	37	[46]	CALL     	9 2 0
	38	[46]	CALL     	7 0 2
	39	[46]	SETTABLE 	6 -13 7	; "text" -
	40	[47]	GETUPVAL 	7 4	; _
	41	[47]	LOADK    	8 -17	; "Yes"
	42	[47]	CALL     	7 2 2
	43	[47]	SETTABLE 	6 -16 7	; "ok_text" -
	44	[51]	CLOSURE  	7 0	; 0x7f93d7408170
	45	[51]	MOVE     	0 3
	46	[51]	SETTABLE 	6 -18 7	; "ok_callback" -
	47	[52]	GETUPVAL 	7 4	; _
	48	[52]	LOADK    	8 -20	; "No"
	49	[52]	CALL     	7 2 2
	50	[52]	SETTABLE 	6 -19 7	; "cancel_text" -
	51	[45]	CALL     	4 3 2
	52	[54]	GETUPVAL 	5 6	; UIManager
	53	[54]	SELF     	5 5 -21	; "show"
	54	[54]	MOVE     	7 4
	55	[54]	CALL     	5 3 1
	56	[56]	GETUPVAL 	5 6	; UIManager
	57	[56]	SELF     	5 5 -22	; "setDirty"
	58	[56]	LOADNIL  	7 7
	59	[56]	LOADK    	8 -23	; "full"
	60	[56]	CALL     	5 4 1
	61	[57]	LOADBOOL 	5 1 0
	62	[57]	RETURN   	5 2
	63	[58]	RETURN   	0 1

function <./frontend/ui/widget/screenshoter.lua:48,51> (11 instructions, 44 bytes at 0x7f93d7408170)
0 params, 4 slots, 1 upvalue, 0 locals, 5 constants, 0 functions
	1	[49]	GETGLOBAL	0 -1	; G_reader_settings
	2	[49]	SELF     	0 0 -2	; "saveSetting"
	3	[49]	LOADK    	2 -3	; "screensaver_type"
	4	[49]	LOADK    	3 -4	; "image_file"
	5	[49]	CALL     	0 4 1
	6	[50]	GETGLOBAL	0 -1	; G_reader_settings
	7	[50]	SELF     	0 0 -2	; "saveSetting"
	8	[50]	LOADK    	2 -5	; "screensaver_image"
	9	[50]	GETUPVAL 	3 0	; screenshot_name
	10	[50]	CALL     	0 4 1
	11	[51]	RETURN   	0 1

function <./frontend/ui/widget/screenshoter.lua:60,93> (67 instructions, 268 bytes at 0x7f93d7408620)
1 param, 10 slots, 7 upvalues, 3 locals, 18 constants, 2 functions
	1	[61]	NEWTABLE 	1 0 0
	2	[62]	GETGLOBAL	2 -1	; table
	3	[62]	GETTABLE 	2 2 -2	; "insert"
	4	[62]	MOVE     	3 1
	5	[62]	NEWTABLE 	4 1 0
	6	[62]	NEWTABLE 	5 0 2
	7	[64]	GETUPVAL 	6 0	; _
	8	[64]	LOADK    	7 -4	; "Choose screenshot directory"
	9	[64]	CALL     	6 2 2
	10	[64]	SETTABLE 	5 -3 6	; "text" -
	11	[76]	CLOSURE  	6 0	; 0x7f93d7408900
	12	[76]	GETUPVAL 	0 1	; UIManager
	13	[76]	MOVE     	0 0
	14	[76]	GETUPVAL 	0 2	; InfoMessage
	15	[76]	GETUPVAL 	0 3	; T
	16	[76]	GETUPVAL 	0 0	; _
	17	[76]	GETUPVAL 	0 4	; BD
	18	[76]	SETTABLE 	5 -5 6	; "callback" -
	19	[78]	SETLIST  	4 1 1	; 1
	20	[62]	CALL     	2 3 1
	21	[79]	GETGLOBAL	2 -1	; table
	22	[79]	GETTABLE 	2 2 -2	; "insert"
	23	[79]	MOVE     	3 1
	24	[79]	NEWTABLE 	4 1 0
	25	[79]	NEWTABLE 	5 0 2
	26	[81]	GETUPVAL 	6 0	; _
	27	[81]	LOADK    	7 -6	; "Close"
	28	[81]	CALL     	6 2 2
	29	[81]	SETTABLE 	5 -3 6	; "text" -
	30	[84]	CLOSURE  	6 1	; 0x7f93d74095f0
	31	[84]	GETUPVAL 	0 1	; UIManager
	32	[84]	MOVE     	0 0
	33	[84]	SETTABLE 	5 -5 6	; "callback" -
	34	[86]	SETLIST  	4 1 1	; 1
	35	[79]	CALL     	2 3 1
	36	[87]	GETGLOBAL	2 -7	; G_reader_settings
	37	[87]	SELF     	2 2 -8	; "readSetting"
	38	[87]	LOADK    	4 -9	; "screenshot_dir"
	39	[87]	CALL     	2 3 2
	40	[87]	TEST     	2 0 1
	41	[87]	JMP      	5	; to 47
	42	[87]	GETUPVAL 	2 5	; DataStorage
	43	[87]	SELF     	2 2 -10	; "getDataDir"
	44	[87]	CALL     	2 2 2
	45	[87]	LOADK    	3 -11	; "/screenshots/"
	46	[87]	CONCAT   	2 2 3
	47	[88]	GETUPVAL 	3 6	; ButtonDialogTitle
	48	[88]	SELF     	3 3 -13	; "new"
	49	[88]	NEWTABLE 	5 0 2
	50	[89]	GETUPVAL 	6 3	; T
	51	[89]	GETUPVAL 	7 0	; _
	52	[89]	LOADK    	8 -15	; "Current screenshot directory:\n%1"
	53	[89]	CALL     	7 2 2
	54	[89]	GETUPVAL 	8 4	; BD
	55	[89]	GETTABLE 	8 8 -16	; "dirpath"
	56	[89]	MOVE     	9 2
	57	[89]	CALL     	8 2 0
	58	[89]	CALL     	6 0 2
	59	[89]	SETTABLE 	5 -14 6	; "title" -
	60	[90]	SETTABLE 	5 -17 1	; "buttons" -
	61	[88]	CALL     	3 3 2
	62	[91]	SETTABLE 	0 -12 3	; "choose_dialog" -
	63	[92]	GETUPVAL 	3 1	; UIManager
	64	[92]	SELF     	3 3 -18	; "show"
	65	[92]	GETTABLE 	5 0 -12	; "choose_dialog"
	66	[92]	CALL     	3 3 1
	67	[93]	RETURN   	0 1

function <./frontend/ui/widget/screenshoter.lua:65,76> (21 instructions, 84 bytes at 0x7f93d7408900)
0 params, 4 slots, 6 upvalues, 0 locals, 7 constants, 1 function
	1	[66]	GETUPVAL 	0 0	; UIManager
	2	[66]	SELF     	0 0 -1	; "close"
	3	[66]	GETUPVAL 	2 1	; self
	4	[66]	GETTABLE 	2 2 -2	; "choose_dialog"
	5	[66]	CALL     	0 3 1
	6	[67]	GETGLOBAL	0 -3	; require
	7	[67]	LOADK    	1 -4	; "ui/downloadmgr"
	8	[67]	CALL     	0 2 2
	9	[67]	SELF     	0 0 -5	; "new"
	10	[67]	NEWTABLE 	2 0 1
	11	[74]	CLOSURE  	3 0	; 0x7f93d7408e20
	12	[74]	GETUPVAL 	0 0	; UIManager
	13	[74]	GETUPVAL 	0 2	; InfoMessage
	14	[74]	GETUPVAL 	0 3	; T
	15	[74]	GETUPVAL 	0 4	; _
	16	[74]	GETUPVAL 	0 5	; BD
	17	[74]	SETTABLE 	2 -6 3	; "onConfirm" -
	18	[67]	CALL     	0 3 2
	19	[75]	SELF     	0 0 -7	; "chooseDir"
	20	[75]	CALL     	0 2 1
	21	[76]	RETURN   	0 1

function <./frontend/ui/widget/screenshoter.lua:68,74> (26 instructions, 104 bytes at 0x7f93d7408e20)
1 param, 10 slots, 5 upvalues, 1 local, 11 constants, 0 functions
	1	[69]	GETGLOBAL	1 -1	; G_reader_settings
	2	[69]	SELF     	1 1 -2	; "saveSetting"
	3	[69]	LOADK    	3 -3	; "screenshot_dir"
	4	[69]	MOVE     	4 0
	5	[69]	LOADK    	5 -4	; "/"
	6	[69]	CONCAT   	4 4 5
	7	[69]	CALL     	1 4 1
	8	[70]	GETUPVAL 	1 0	; UIManager
	9	[70]	SELF     	1 1 -5	; "show"
	10	[70]	GETUPVAL 	3 1	; InfoMessage
	11	[70]	SELF     	3 3 -6	; "new"
	12	[70]	NEWTABLE 	5 0 2
	13	[71]	GETUPVAL 	6 2	; T
	14	[71]	GETUPVAL 	7 3	; _
	15	[71]	LOADK    	8 -8	; "Screenshot directory set to:\n%1"
	16	[71]	CALL     	7 2 2
	17	[71]	GETUPVAL 	8 4	; BD
	18	[71]	GETTABLE 	8 8 -9	; "dirpath"
	19	[71]	MOVE     	9 0
	20	[71]	CALL     	8 2 0
	21	[71]	CALL     	6 0 2
	22	[71]	SETTABLE 	5 -7 6	; "text" -
	23	[72]	SETTABLE 	5 -10 -11	; "timeout" 3
	24	[70]	CALL     	3 3 0
	25	[70]	CALL     	1 0 1
	26	[74]	RETURN   	0 1

function <./frontend/ui/widget/screenshoter.lua:82,84> (6 instructions, 24 bytes at 0x7f93d74095f0)
0 params, 3 slots, 2 upvalues, 0 locals, 2 constants, 0 functions
	1	[83]	GETUPVAL 	0 0	; UIManager
	2	[83]	SELF     	0 0 -1	; "close"
	3	[83]	GETUPVAL 	2 1	; self
	4	[83]	GETTABLE 	2 2 -2	; "choose_dialog"
	5	[83]	CALL     	0 3 1
	6	[84]	RETURN   	0 1

function <./frontend/ui/widget/screenshoter.lua:95,97> (4 instructions, 16 bytes at 0x7f93d7408880)
1 param, 3 slots, 0 upvalues, 1 local, 1 constant, 0 functions
	1	[96]	SELF     	1 0 -1	; "onScreenshot"
	2	[96]	TAILCALL 	1 2 0
	3	[96]	RETURN   	1 0
	4	[97]	RETURN   	0 1

function <./frontend/ui/widget/screenshoter.lua:99,101> (4 instructions, 16 bytes at 0x7f93d7409ae0)
1 param, 3 slots, 0 upvalues, 1 local, 1 constant, 0 functions
	1	[100]	SELF     	1 0 -1	; "onScreenshot"
	2	[100]	TAILCALL 	1 2 0
	3	[100]	RETURN   	1 0
	4	[101]	RETURN   	0 1
