
main <./frontend/ui/elements/screen_android.lua:0,0> (88 instructions, 352 bytes at 0x7f9b5a4068f0)
0+ params, 27 slots, 0 upvalues, 26 locals, 26 constants, 8 functions
	1	[1]	GETGLOBAL	0 -1	; pcall
	2	[1]	GETGLOBAL	1 -2	; require
	3	[1]	LOADK    	2 -3	; "android"
	4	[1]	CALL     	0 3 3
	5	[2]	GETGLOBAL	2 -2	; require
	6	[2]	LOADK    	3 -4	; "device"
	7	[2]	CALL     	2 2 2
	8	[3]	GETGLOBAL	3 -2	; require
	9	[3]	LOADK    	4 -5	; "ui/geometry"
	10	[3]	CALL     	3 2 2
	11	[4]	GETGLOBAL	4 -2	; require
	12	[4]	LOADK    	5 -6	; "ffi"
	13	[4]	CALL     	4 2 2
	14	[5]	GETGLOBAL	5 -2	; require
	15	[5]	LOADK    	6 -7	; "logger"
	16	[5]	CALL     	5 2 2
	17	[6]	GETGLOBAL	6 -2	; require
	18	[6]	LOADK    	7 -8	; "gettext"
	19	[6]	CALL     	6 2 2
	20	[7]	GETTABLE 	7 2 -9	; "input"
	21	[8]	GETTABLE 	8 2 -10	; "screen"
	22	[9]	GETGLOBAL	9 -2	; require
	23	[9]	LOADK    	10 -11	; "ffi/util"
	24	[9]	CALL     	9 2 2
	25	[9]	GETTABLE 	9 9 -12	; "template"
	26	[11]	TEST     	0 0 1
	27	[11]	JMP      	1	; to 29
	28	[11]	RETURN   	0 1
	29	[13]	GETTABLE 	10 4 -13	; "C"
	30	[13]	GETTABLE 	10 10 -14	; "AKEEP_SCREEN_ON_DISABLED"
	31	[14]	GETTABLE 	11 4 -13	; "C"
	32	[14]	GETTABLE 	11 11 -15	; "AKEEP_SCREEN_ON_ENABLED"
	33	[15]	GETTABLE 	12 1 -16	; "needsWakelocks"
	34	[15]	CALL     	12 1 2
	35	[18]	LOADK    	13 -17	; 120000
	36	[19]	LOADK    	14 -18	; 300000
	37	[20]	LOADK    	15 -19	; 600000
	38	[21]	LOADK    	16 -20	; 900000
	39	[22]	LOADK    	17 -21	; 1200000
	40	[23]	LOADK    	18 -22	; 1500000
	41	[24]	LOADK    	19 -23	; 1800000
	42	[33]	CLOSURE  	20 0	; 0x7f9b5a407030
	43	[33]	MOVE     	0 9
	44	[33]	MOVE     	0 6
	45	[42]	CLOSURE  	21 1	; 0x7f9b5a407a70
	46	[42]	MOVE     	0 12
	47	[42]	MOVE     	0 10
	48	[42]	MOVE     	0 11
	49	[42]	MOVE     	0 1
	50	[46]	CLOSURE  	22 2	; 0x7f9b5a407fa0
	51	[46]	MOVE     	0 1
	52	[51]	CLOSURE  	23 3	; 0x7f9b5a408250
	53	[51]	MOVE     	0 1
	54	[64]	CLOSURE  	24 4	; 0x7f9b5a4085f0
	55	[64]	MOVE     	0 6
	56	[64]	MOVE     	0 1
	57	[66]	NEWTABLE 	25 0 0
	58	[81]	CLOSURE  	26 5	; 0x7f9b5a4094c0
	59	[81]	MOVE     	0 2
	60	[81]	MOVE     	0 6
	61	[68]	SETTABLE 	25 -24 26	; "toggleFullscreen" -
	62	[114]	CLOSURE  	26 6	; 0x7f9b5a408470
	63	[114]	MOVE     	0 1
	64	[114]	MOVE     	0 5
	65	[114]	MOVE     	0 8
	66	[114]	MOVE     	0 7
	67	[114]	MOVE     	0 3
	68	[84]	SETTABLE 	25 -25 26	; "toggleFullscreenLegacy" -
	69	[189]	CLOSURE  	26 7	; 0x7f9b5a406d50
	70	[189]	MOVE     	0 6
	71	[189]	MOVE     	0 21
	72	[189]	MOVE     	0 10
	73	[189]	MOVE     	0 22
	74	[189]	MOVE     	0 23
	75	[189]	MOVE     	0 20
	76	[189]	MOVE     	0 13
	77	[189]	MOVE     	0 14
	78	[189]	MOVE     	0 15
	79	[189]	MOVE     	0 16
	80	[189]	MOVE     	0 17
	81	[189]	MOVE     	0 18
	82	[189]	MOVE     	0 19
	83	[189]	MOVE     	0 11
	84	[189]	MOVE     	0 1
	85	[189]	MOVE     	0 24
	86	[117]	SETTABLE 	25 -26 26	; "getTimeoutMenuTable" -
	87	[191]	RETURN   	25 2
	88	[191]	RETURN   	0 1

function <./frontend/ui/elements/screen_android.lua:26,33> (19 instructions, 76 bytes at 0x7f9b5a407030)
1 param, 5 slots, 2 upvalues, 2 locals, 5 constants, 0 functions
	1	[27]	DIV      	1 0 -1	; - 1000
	2	[28]	LE       	0 -2 1	; 120 -
	3	[28]	JMP      	8	; to 12
	4	[29]	GETUPVAL 	2 0	; T
	5	[29]	GETUPVAL 	3 1	; _
	6	[29]	LOADK    	4 -3	; "%1 minutes"
	7	[29]	CALL     	3 2 2
	8	[29]	DIV      	4 1 -4	; - 60
	9	[29]	TAILCALL 	2 3 0
	10	[29]	RETURN   	2 0
	11	[29]	JMP      	7	; to 19
	12	[31]	GETUPVAL 	2 0	; T
	13	[31]	GETUPVAL 	3 1	; _
	14	[31]	LOADK    	4 -5	; "%1 seconds"
	15	[31]	CALL     	3 2 2
	16	[31]	MOVE     	4 1
	17	[31]	TAILCALL 	2 3 0
	18	[31]	RETURN   	2 0
	19	[33]	RETURN   	0 1

function <./frontend/ui/elements/screen_android.lua:35,42> (20 instructions, 80 bytes at 0x7f9b5a407a70)
1 param, 2 slots, 4 upvalues, 1 local, 2 constants, 0 functions
	1	[36]	GETUPVAL 	1 0	; needs_wakelocks
	2	[36]	TEST     	1 0 0
	3	[36]	JMP      	2	; to 6
	4	[36]	LOADBOOL 	1 0 0
	5	[36]	RETURN   	1 2
	6	[37]	GETUPVAL 	1 1	; system
	7	[37]	EQ       	1 0 1
	8	[37]	JMP      	3	; to 12
	9	[37]	GETUPVAL 	1 2	; screenOn
	10	[37]	EQ       	0 0 1
	11	[37]	JMP      	3	; to 15
	12	[38]	LOADBOOL 	1 1 0
	13	[38]	RETURN   	1 2
	14	[38]	JMP      	5	; to 20
	15	[40]	GETUPVAL 	1 3	; android
	16	[40]	GETTABLE 	1 1 -1	; "settings"
	17	[40]	GETTABLE 	1 1 -2	; "canWrite"
	18	[40]	TAILCALL 	1 1 0
	19	[40]	RETURN   	1 0
	20	[42]	RETURN   	0 1

function <./frontend/ui/elements/screen_android.lua:44,46> (10 instructions, 40 bytes at 0x7f9b5a407fa0)
1 param, 2 slots, 1 upvalue, 1 local, 2 constants, 0 functions
	1	[45]	GETUPVAL 	1 0	; android
	2	[45]	GETTABLE 	1 1 -1	; "timeout"
	3	[45]	GETTABLE 	1 1 -2	; "get"
	4	[45]	CALL     	1 1 2
	5	[45]	EQ       	1 0 1
	6	[45]	JMP      	1	; to 8
	7	[45]	LOADBOOL 	1 0 1
	8	[45]	LOADBOOL 	1 1 0
	9	[45]	RETURN   	1 2
	10	[46]	RETURN   	0 1

function <./frontend/ui/elements/screen_android.lua:48,51> (11 instructions, 44 bytes at 0x7f9b5a408250)
1 param, 5 slots, 1 upvalue, 1 local, 5 constants, 0 functions
	1	[49]	GETGLOBAL	1 -1	; G_reader_settings
	2	[49]	SELF     	1 1 -2	; "saveSetting"
	3	[49]	LOADK    	3 -3	; "android_screen_timeout"
	4	[49]	MOVE     	4 0
	5	[49]	CALL     	1 4 1
	6	[50]	GETUPVAL 	1 0	; android
	7	[50]	GETTABLE 	1 1 -4	; "timeout"
	8	[50]	GETTABLE 	1 1 -5	; "set"
	9	[50]	MOVE     	2 0
	10	[50]	CALL     	1 2 1
	11	[51]	RETURN   	0 1

function <./frontend/ui/elements/screen_android.lua:53,64> (24 instructions, 96 bytes at 0x7f9b5a4085f0)
0 params, 9 slots, 2 upvalues, 2 locals, 10 constants, 1 function
	1	[54]	GETGLOBAL	0 -1	; require
	2	[54]	LOADK    	1 -2	; "ui/uimanager"
	3	[54]	CALL     	0 2 2
	4	[55]	GETGLOBAL	1 -1	; require
	5	[55]	LOADK    	2 -3	; "ui/widget/confirmbox"
	6	[55]	CALL     	1 2 2
	7	[56]	SELF     	2 0 -4	; "show"
	8	[56]	SELF     	4 1 -5	; "new"
	9	[56]	NEWTABLE 	6 0 3
	10	[57]	GETUPVAL 	7 0	; _
	11	[57]	LOADK    	8 -7	; "Allow KOReader to modify system settings?\n\nYou will be prompted with a permission management screen. You'll need to give KOReader permission and then restart the program."
	12	[57]	CALL     	7 2 2
	13	[57]	SETTABLE 	6 -6 7	; "text" -
	14	[58]	GETUPVAL 	7 0	; _
	15	[58]	LOADK    	8 -9	; "Allow"
	16	[58]	CALL     	7 2 2
	17	[58]	SETTABLE 	6 -8 7	; "ok_text" -
	18	[62]	CLOSURE  	7 0	; 0x7f9b5a408f00
	19	[62]	MOVE     	0 0
	20	[62]	GETUPVAL 	0 1	; android
	21	[62]	SETTABLE 	6 -10 7	; "ok_callback" -
	22	[56]	CALL     	4 3 0
	23	[56]	CALL     	2 0 1
	24	[64]	RETURN   	0 1

function <./frontend/ui/elements/screen_android.lua:59,62> (11 instructions, 44 bytes at 0x7f9b5a408f00)
0 params, 4 slots, 2 upvalues, 0 locals, 4 constants, 1 function
	1	[60]	GETUPVAL 	0 0	; UIManager
	2	[60]	SELF     	0 0 -1	; "scheduleIn"
	3	[60]	LOADK    	2 -2	; 1
	4	[60]	CLOSURE  	3 0	; 0x7f9b5a409100
	5	[60]	GETUPVAL 	0 0	; UIManager
	6	[60]	CALL     	0 4 1
	7	[61]	GETUPVAL 	0 1	; android
	8	[61]	GETTABLE 	0 0 -3	; "settings"
	9	[61]	GETTABLE 	0 0 -4	; "requestWritePermission"
	10	[61]	CALL     	0 1 1
	11	[62]	RETURN   	0 1

function <./frontend/ui/elements/screen_android.lua:60,60> (4 instructions, 16 bytes at 0x7f9b5a409100)
0 params, 2 slots, 1 upvalue, 0 locals, 1 constant, 0 functions
	1	[60]	GETUPVAL 	0 0	; UIManager
	2	[60]	SELF     	0 0 -1	; "quit"
	3	[60]	CALL     	0 2 1
	4	[60]	RETURN   	0 1

function <./frontend/ui/elements/screen_android.lua:68,81> (30 instructions, 120 bytes at 0x7f9b5a4094c0)
1 param, 11 slots, 2 upvalues, 4 locals, 12 constants, 0 functions
	1	[69]	GETUPVAL 	1 0	; Device
	2	[69]	GETTABLE 	1 1 -1	; "firmware_rev"
	3	[71]	LT       	0 1 -2	; - 19
	4	[71]	JMP      	21	; to 26
	5	[71]	LE       	0 -3 1	; 17 -
	6	[71]	JMP      	19	; to 26
	7	[72]	GETUPVAL 	2 0	; Device
	8	[72]	SELF     	2 2 -4	; "toggleFullscreen"
	9	[72]	CALL     	2 2 1
	10	[73]	GETGLOBAL	2 -5	; require
	11	[73]	LOADK    	3 -6	; "ui/uimanager"
	12	[73]	CALL     	2 2 2
	13	[74]	GETGLOBAL	3 -5	; require
	14	[74]	LOADK    	4 -7	; "ui/widget/infomessage"
	15	[74]	CALL     	3 2 2
	16	[75]	SELF     	4 2 -8	; "show"
	17	[75]	SELF     	6 3 -9	; "new"
	18	[75]	NEWTABLE 	8 0 1
	19	[76]	GETUPVAL 	9 1	; _
	20	[76]	LOADK    	10 -11	; "This will take effect on next restart."
	21	[76]	CALL     	9 2 2
	22	[76]	SETTABLE 	8 -10 9	; "text" -
	23	[75]	CALL     	6 3 0
	24	[75]	CALL     	4 0 1
	25	[77]	JMP      	4	; to 30
	26	[78]	LT       	0 1 -3	; - 17
	27	[78]	JMP      	2	; to 30
	28	[79]	SELF     	2 0 -12	; "toggleFullscreenLegacy"
	29	[79]	CALL     	2 2 1
	30	[81]	RETURN   	0 1

function <./frontend/ui/elements/screen_android.lua:84,114> (94 instructions, 376 bytes at 0x7f9b5a408470)
1 param, 14 slots, 5 upvalues, 7 locals, 21 constants, 0 functions
	1	[86]	GETUPVAL 	1 0	; android
	2	[86]	GETTABLE 	1 1 -1	; "isFullscreen"
	3	[86]	CALL     	1 1 2
	4	[87]	GETUPVAL 	2 0	; android
	5	[87]	GETTABLE 	2 2 -2	; "setFullscreen"
	6	[87]	NOT      	3 1
	7	[87]	CALL     	2 2 1
	8	[88]	GETUPVAL 	2 1	; logger
	9	[88]	GETTABLE 	2 2 -3	; "dbg"
	10	[88]	GETGLOBAL	3 -4	; string
	11	[88]	GETTABLE 	3 3 -5	; "format"
	12	[88]	LOADK    	4 -6	; "requesting fullscreen: %s"
	13	[88]	NOT      	5 1
	14	[88]	CALL     	3 3 0
	15	[88]	CALL     	2 0 1
	16	[90]	GETUPVAL 	2 0	; android
	17	[90]	GETTABLE 	2 2 -7	; "getScreenWidth"
	18	[90]	CALL     	2 1 2
	19	[91]	GETUPVAL 	3 0	; android
	20	[91]	GETTABLE 	3 3 -8	; "getScreenHeight"
	21	[91]	CALL     	3 1 2
	22	[92]	GETUPVAL 	4 0	; android
	23	[92]	GETTABLE 	4 4 -9	; "getStatusBarHeight"
	24	[92]	CALL     	4 1 2
	25	[93]	SUB      	5 3 4
	26	[95]	TEST     	1 0 1
	27	[95]	JMP      	21	; to 49
	28	[95]	GETUPVAL 	6 2	; Screen
	29	[95]	GETTABLE 	6 6 -10	; "viewport"
	30	[95]	TEST     	6 0 0
	31	[95]	JMP      	17	; to 49
	32	[96]	LOADK    	4 -11	; 0
	33	[98]	GETUPVAL 	6 3	; Input
	34	[98]	SELF     	6 6 -12	; "registerEventAdjustHook"
	35	[99]	GETUPVAL 	8 3	; Input
	36	[99]	GETTABLE 	8 8 -13	; "adjustTouchTranslate"
	37	[99]	NEWTABLE 	9 0 2
	38	[100]	GETUPVAL 	10 2	; Screen
	39	[100]	GETTABLE 	10 10 -10	; "viewport"
	40	[100]	GETTABLE 	10 10 -14	; "x"
	41	[100]	ADD      	10 -11 10	; 0 -
	42	[100]	SETTABLE 	9 -14 10	; "x" -
	43	[100]	GETUPVAL 	10 2	; Screen
	44	[100]	GETTABLE 	10 10 -10	; "viewport"
	45	[100]	GETTABLE 	10 10 -15	; "y"
	46	[100]	ADD      	10 -11 10	; 0 -
	47	[100]	SETTABLE 	9 -15 10	; "y" -
	48	[98]	CALL     	6 4 1
	49	[103]	GETUPVAL 	6 4	; Geom
	50	[103]	SELF     	6 6 -16	; "new"
	51	[103]	NEWTABLE 	8 0 4
	52	[103]	SETTABLE 	8 -14 -11	; "x" 0
	53	[103]	SETTABLE 	8 -15 4	; "y" -
	54	[103]	SETTABLE 	8 -17 2	; "w" -
	55	[103]	SETTABLE 	8 -18 5	; "h" -
	56	[103]	CALL     	6 3 2
	57	[104]	GETUPVAL 	7 1	; logger
	58	[104]	GETTABLE 	7 7 -19	; "info"
	59	[104]	GETGLOBAL	8 -4	; string
	60	[104]	GETTABLE 	8 8 -5	; "format"
	61	[104]	LOADK    	9 -20	; "Switching viewport to new geometry [x=%d,y=%d,w=%d,h=%d]"
	62	[105]	LOADK    	10 -11	; 0
	63	[105]	MOVE     	11 4
	64	[105]	MOVE     	12 2
	65	[105]	MOVE     	13 5
	66	[104]	CALL     	8 6 0
	67	[104]	CALL     	7 0 1
	68	[107]	GETUPVAL 	7 2	; Screen
	69	[107]	SELF     	7 7 -21	; "setViewport"
	70	[107]	MOVE     	9 6
	71	[107]	CALL     	7 3 1
	72	[109]	TEST     	1 0 0
	73	[109]	JMP      	20	; to 94
	74	[109]	GETUPVAL 	7 2	; Screen
	75	[109]	GETTABLE 	7 7 -10	; "viewport"
	76	[109]	TEST     	7 0 0
	77	[109]	JMP      	16	; to 94
	78	[110]	GETUPVAL 	7 3	; Input
	79	[110]	SELF     	7 7 -12	; "registerEventAdjustHook"
	80	[111]	GETUPVAL 	9 3	; Input
	81	[111]	GETTABLE 	9 9 -13	; "adjustTouchTranslate"
	82	[111]	NEWTABLE 	10 0 2
	83	[112]	GETUPVAL 	11 2	; Screen
	84	[112]	GETTABLE 	11 11 -10	; "viewport"
	85	[112]	GETTABLE 	11 11 -14	; "x"
	86	[112]	SUB      	11 -11 11	; 0 -
	87	[112]	SETTABLE 	10 -14 11	; "x" -
	88	[112]	GETUPVAL 	11 2	; Screen
	89	[112]	GETTABLE 	11 11 -10	; "viewport"
	90	[112]	GETTABLE 	11 11 -15	; "y"
	91	[112]	SUB      	11 -11 11	; 0 -
	92	[112]	SETTABLE 	10 -15 11	; "y" -
	93	[110]	CALL     	7 4 1
	94	[114]	RETURN   	0 1

function <./frontend/ui/elements/screen_android.lua:117,189> (189 instructions, 756 bytes at 0x7f9b5a406d50)
1 param, 13 slots, 16 upvalues, 2 locals, 16 constants, 30 functions
	1	[118]	NEWTABLE 	1 9 0
	2	[118]	NEWTABLE 	2 0 4
	3	[120]	GETUPVAL 	3 0	; _
	4	[120]	LOADK    	4 -2	; "Use system settings"
	5	[120]	CALL     	3 2 2
	6	[120]	SETTABLE 	2 -1 3	; "text" -
	7	[121]	CLOSURE  	3 0	; 0x7f9b5a409d60
	8	[121]	GETUPVAL 	0 1	; canModifyTimeout
	9	[121]	GETUPVAL 	0 2	; system
	10	[121]	SETTABLE 	2 -3 3	; "enabled_func" -
	11	[122]	CLOSURE  	3 1	; 0x7f9b5a409df0
	12	[122]	GETUPVAL 	0 3	; timeoutEquals
	13	[122]	GETUPVAL 	0 2	; system
	14	[122]	SETTABLE 	2 -4 3	; "checked_func" -
	15	[123]	CLOSURE  	3 2	; 0x7f9b5a40a4f0
	16	[123]	GETUPVAL 	0 4	; saveAndApplyTimeout
	17	[123]	GETUPVAL 	0 2	; system
	18	[123]	SETTABLE 	2 -5 3	; "callback" -
	19	[124]	NEWTABLE 	3 0 4
	20	[126]	GETUPVAL 	4 5	; humanReadableTimeout
	21	[126]	GETUPVAL 	5 6	; timeout_custom1
	22	[126]	CALL     	4 2 2
	23	[126]	SETTABLE 	3 -1 4	; "text" -
	24	[127]	CLOSURE  	4 3	; 0x7f9b5a40a7a0
	25	[127]	GETUPVAL 	0 1	; canModifyTimeout
	26	[127]	GETUPVAL 	0 6	; timeout_custom1
	27	[127]	SETTABLE 	3 -3 4	; "enabled_func" -
	28	[128]	CLOSURE  	4 4	; 0x7f9b5a40a8c0
	29	[128]	GETUPVAL 	0 3	; timeoutEquals
	30	[128]	GETUPVAL 	0 6	; timeout_custom1
	31	[128]	SETTABLE 	3 -4 4	; "checked_func" -
	32	[129]	CLOSURE  	4 5	; 0x7f9b5a40aa60
	33	[129]	GETUPVAL 	0 4	; saveAndApplyTimeout
	34	[129]	GETUPVAL 	0 6	; timeout_custom1
	35	[129]	SETTABLE 	3 -5 4	; "callback" -
	36	[130]	NEWTABLE 	4 0 4
	37	[132]	GETUPVAL 	5 5	; humanReadableTimeout
	38	[132]	GETUPVAL 	6 7	; timeout_custom2
	39	[132]	CALL     	5 2 2
	40	[132]	SETTABLE 	4 -1 5	; "text" -
	41	[133]	CLOSURE  	5 6	; 0x7f9b5a40a720
	42	[133]	GETUPVAL 	0 1	; canModifyTimeout
	43	[133]	GETUPVAL 	0 7	; timeout_custom2
	44	[133]	SETTABLE 	4 -3 5	; "enabled_func" -
	45	[134]	CLOSURE  	5 7	; 0x7f9b5a40aee0
	46	[134]	GETUPVAL 	0 3	; timeoutEquals
	47	[134]	GETUPVAL 	0 7	; timeout_custom2
	48	[134]	SETTABLE 	4 -4 5	; "checked_func" -
	49	[135]	CLOSURE  	5 8	; 0x7f9b5a40b090
	50	[135]	GETUPVAL 	0 4	; saveAndApplyTimeout
	51	[135]	GETUPVAL 	0 7	; timeout_custom2
	52	[135]	SETTABLE 	4 -5 5	; "callback" -
	53	[136]	NEWTABLE 	5 0 4
	54	[138]	GETUPVAL 	6 5	; humanReadableTimeout
	55	[138]	GETUPVAL 	7 8	; timeout_custom3
	56	[138]	CALL     	6 2 2
	57	[138]	SETTABLE 	5 -1 6	; "text" -
	58	[139]	CLOSURE  	6 9	; 0x7f9b5a40b350
	59	[139]	GETUPVAL 	0 1	; canModifyTimeout
	60	[139]	GETUPVAL 	0 8	; timeout_custom3
	61	[139]	SETTABLE 	5 -3 6	; "enabled_func" -
	62	[140]	CLOSURE  	6 10	; 0x7f9b5a40b470
	63	[140]	GETUPVAL 	0 3	; timeoutEquals
	64	[140]	GETUPVAL 	0 8	; timeout_custom3
	65	[140]	SETTABLE 	5 -4 6	; "checked_func" -
	66	[141]	CLOSURE  	6 11	; 0x7f9b5a40ac40
	67	[141]	GETUPVAL 	0 4	; saveAndApplyTimeout
	68	[141]	GETUPVAL 	0 8	; timeout_custom3
	69	[141]	SETTABLE 	5 -5 6	; "callback" -
	70	[142]	NEWTABLE 	6 0 4
	71	[144]	GETUPVAL 	7 5	; humanReadableTimeout
	72	[144]	GETUPVAL 	8 9	; timeout_custom4
	73	[144]	CALL     	7 2 2
	74	[144]	SETTABLE 	6 -1 7	; "text" -
	75	[145]	CLOSURE  	7 12	; 0x7f9b5a40ba10
	76	[145]	GETUPVAL 	0 1	; canModifyTimeout
	77	[145]	GETUPVAL 	0 9	; timeout_custom4
	78	[145]	SETTABLE 	6 -3 7	; "enabled_func" -
	79	[146]	CLOSURE  	7 13	; 0x7f9b5a40bb50
	80	[146]	GETUPVAL 	0 3	; timeoutEquals
	81	[146]	GETUPVAL 	0 9	; timeout_custom4
	82	[146]	SETTABLE 	6 -4 7	; "checked_func" -
	83	[147]	CLOSURE  	7 14	; 0x7f9b5a40bd10
	84	[147]	GETUPVAL 	0 4	; saveAndApplyTimeout
	85	[147]	GETUPVAL 	0 9	; timeout_custom4
	86	[147]	SETTABLE 	6 -5 7	; "callback" -
	87	[148]	NEWTABLE 	7 0 4
	88	[150]	GETUPVAL 	8 5	; humanReadableTimeout
	89	[150]	GETUPVAL 	9 10	; timeout_custom5
	90	[150]	CALL     	8 2 2
	91	[150]	SETTABLE 	7 -1 8	; "text" -
	92	[151]	CLOSURE  	8 15	; 0x7f9b5a40bed0
	93	[151]	GETUPVAL 	0 1	; canModifyTimeout
	94	[151]	GETUPVAL 	0 10	; timeout_custom5
	95	[151]	SETTABLE 	7 -3 8	; "enabled_func" -
	96	[152]	CLOSURE  	8 16	; 0x7f9b5a40c050
	97	[152]	GETUPVAL 	0 3	; timeoutEquals
	98	[152]	GETUPVAL 	0 10	; timeout_custom5
	99	[152]	SETTABLE 	7 -4 8	; "checked_func" -
	100	[153]	CLOSURE  	8 17	; 0x7f9b5a40b250
	101	[153]	GETUPVAL 	0 4	; saveAndApplyTimeout
	102	[153]	GETUPVAL 	0 10	; timeout_custom5
	103	[153]	SETTABLE 	7 -5 8	; "callback" -
	104	[154]	NEWTABLE 	8 0 4
	105	[156]	GETUPVAL 	9 5	; humanReadableTimeout
	106	[156]	GETUPVAL 	10 11	; timeout_custom6
	107	[156]	CALL     	9 2 2
	108	[156]	SETTABLE 	8 -1 9	; "text" -
	109	[157]	CLOSURE  	9 18	; 0x7f9b5a40a150
	110	[157]	GETUPVAL 	0 1	; canModifyTimeout
	111	[157]	GETUPVAL 	0 11	; timeout_custom6
	112	[157]	SETTABLE 	8 -3 9	; "enabled_func" -
	113	[158]	CLOSURE  	9 19	; 0x7f9b5a40a2d0
	114	[158]	GETUPVAL 	0 3	; timeoutEquals
	115	[158]	GETUPVAL 	0 11	; timeout_custom6
	116	[158]	SETTABLE 	8 -4 9	; "checked_func" -
	117	[159]	CLOSURE  	9 20	; 0x7f9b5a40c510
	118	[159]	GETUPVAL 	0 4	; saveAndApplyTimeout
	119	[159]	GETUPVAL 	0 11	; timeout_custom6
	120	[159]	SETTABLE 	8 -5 9	; "callback" -
	121	[160]	NEWTABLE 	9 0 4
	122	[162]	GETUPVAL 	10 5	; humanReadableTimeout
	123	[162]	GETUPVAL 	11 12	; timeout_custom7
	124	[162]	CALL     	10 2 2
	125	[162]	SETTABLE 	9 -1 10	; "text" -
	126	[163]	CLOSURE  	10 21	; 0x7f9b5a40c6d0
	127	[163]	GETUPVAL 	0 1	; canModifyTimeout
	128	[163]	GETUPVAL 	0 12	; timeout_custom7
	129	[163]	SETTABLE 	9 -3 10	; "enabled_func" -
	130	[164]	CLOSURE  	10 22	; 0x7f9b5a40b610
	131	[164]	GETUPVAL 	0 3	; timeoutEquals
	132	[164]	GETUPVAL 	0 12	; timeout_custom7
	133	[164]	SETTABLE 	9 -4 10	; "checked_func" -
	134	[165]	CLOSURE  	10 23	; 0x7f9b5a40b7d0
	135	[165]	GETUPVAL 	0 4	; saveAndApplyTimeout
	136	[165]	GETUPVAL 	0 12	; timeout_custom7
	137	[165]	SETTABLE 	9 -5 10	; "callback" -
	138	[166]	NEWTABLE 	10 0 4
	139	[168]	GETUPVAL 	11 0	; _
	140	[168]	LOADK    	12 -6	; "Keep screen on"
	141	[168]	CALL     	11 2 2
	142	[168]	SETTABLE 	10 -1 11	; "text" -
	143	[169]	CLOSURE  	11 24	; 0x7f9b5a40b990
	144	[169]	GETUPVAL 	0 1	; canModifyTimeout
	145	[169]	GETUPVAL 	0 13	; screenOn
	146	[169]	SETTABLE 	10 -3 11	; "enabled_func" -
	147	[170]	CLOSURE  	11 25	; 0x7f9b5a40c980
	148	[170]	GETUPVAL 	0 3	; timeoutEquals
	149	[170]	GETUPVAL 	0 13	; screenOn
	150	[170]	SETTABLE 	10 -4 11	; "checked_func" -
	151	[171]	CLOSURE  	11 26	; 0x7f9b5a40af60
	152	[171]	GETUPVAL 	0 4	; saveAndApplyTimeout
	153	[171]	GETUPVAL 	0 13	; screenOn
	154	[171]	SETTABLE 	10 -5 11	; "callback" -
	155	[173]	SETLIST  	1 9 1	; 1
	156	[175]	GETUPVAL 	2 14	; android
	157	[175]	GETTABLE 	2 2 -7	; "settings"
	158	[175]	GETTABLE 	2 2 -8	; "canWrite"
	159	[175]	CALL     	2 1 2
	160	[175]	TEST     	2 0 1
	161	[175]	JMP      	20	; to 182
	162	[176]	GETGLOBAL	2 -9	; table
	163	[176]	GETTABLE 	2 2 -10	; "insert"
	164	[176]	MOVE     	3 1
	165	[176]	LOADK    	4 -11	; 1
	166	[176]	NEWTABLE 	5 0 5
	167	[177]	GETUPVAL 	6 0	; _
	168	[177]	LOADK    	7 -12	; "Allow system settings override"
	169	[177]	CALL     	6 2 2
	170	[177]	SETTABLE 	5 -1 6	; "text" -
	171	[178]	CLOSURE  	6 27	; 0x7f9b5a40a470
	172	[178]	GETUPVAL 	0 14	; android
	173	[178]	SETTABLE 	5 -3 6	; "enabled_func" -
	174	[179]	CLOSURE  	6 28	; 0x7f9b5a40a9c0
	175	[179]	GETUPVAL 	0 14	; android
	176	[179]	SETTABLE 	5 -4 6	; "checked_func" -
	177	[180]	CLOSURE  	6 29	; 0x7f9b5a40aba0
	178	[180]	GETUPVAL 	0 15	; requestWriteSettings
	179	[180]	SETTABLE 	5 -5 6	; "callback" -
	180	[181]	SETTABLE 	5 -13 -14	; "separator" true
	181	[176]	CALL     	2 4 1
	182	[185]	NEWTABLE 	2 0 2
	183	[186]	GETUPVAL 	3 0	; _
	184	[186]	LOADK    	4 -15	; "Screen Timeout"
	185	[186]	CALL     	3 2 2
	186	[186]	SETTABLE 	2 -1 3	; "text" -
	187	[187]	SETTABLE 	2 -16 1	; "sub_item_table" -
	188	[188]	RETURN   	2 2
	189	[189]	RETURN   	0 1

function <./frontend/ui/elements/screen_android.lua:121,121> (5 instructions, 20 bytes at 0x7f9b5a409d60)
0 params, 2 slots, 2 upvalues, 0 locals, 0 constants, 0 functions
	1	[121]	GETUPVAL 	0 0	; canModifyTimeout
	2	[121]	GETUPVAL 	1 1	; system
	3	[121]	TAILCALL 	0 2 0
	4	[121]	RETURN   	0 0
	5	[121]	RETURN   	0 1

function <./frontend/ui/elements/screen_android.lua:122,122> (5 instructions, 20 bytes at 0x7f9b5a409df0)
0 params, 2 slots, 2 upvalues, 0 locals, 0 constants, 0 functions
	1	[122]	GETUPVAL 	0 0	; timeoutEquals
	2	[122]	GETUPVAL 	1 1	; system
	3	[122]	TAILCALL 	0 2 0
	4	[122]	RETURN   	0 0
	5	[122]	RETURN   	0 1

function <./frontend/ui/elements/screen_android.lua:123,123> (4 instructions, 16 bytes at 0x7f9b5a40a4f0)
0 params, 2 slots, 2 upvalues, 0 locals, 0 constants, 0 functions
	1	[123]	GETUPVAL 	0 0	; saveAndApplyTimeout
	2	[123]	GETUPVAL 	1 1	; system
	3	[123]	CALL     	0 2 1
	4	[123]	RETURN   	0 1

function <./frontend/ui/elements/screen_android.lua:127,127> (5 instructions, 20 bytes at 0x7f9b5a40a7a0)
0 params, 2 slots, 2 upvalues, 0 locals, 0 constants, 0 functions
	1	[127]	GETUPVAL 	0 0	; canModifyTimeout
	2	[127]	GETUPVAL 	1 1	; timeout_custom1
	3	[127]	TAILCALL 	0 2 0
	4	[127]	RETURN   	0 0
	5	[127]	RETURN   	0 1

function <./frontend/ui/elements/screen_android.lua:128,128> (5 instructions, 20 bytes at 0x7f9b5a40a8c0)
0 params, 2 slots, 2 upvalues, 0 locals, 0 constants, 0 functions
	1	[128]	GETUPVAL 	0 0	; timeoutEquals
	2	[128]	GETUPVAL 	1 1	; timeout_custom1
	3	[128]	TAILCALL 	0 2 0
	4	[128]	RETURN   	0 0
	5	[128]	RETURN   	0 1

function <./frontend/ui/elements/screen_android.lua:129,129> (4 instructions, 16 bytes at 0x7f9b5a40aa60)
0 params, 2 slots, 2 upvalues, 0 locals, 0 constants, 0 functions
	1	[129]	GETUPVAL 	0 0	; saveAndApplyTimeout
	2	[129]	GETUPVAL 	1 1	; timeout_custom1
	3	[129]	CALL     	0 2 1
	4	[129]	RETURN   	0 1

function <./frontend/ui/elements/screen_android.lua:133,133> (5 instructions, 20 bytes at 0x7f9b5a40a720)
0 params, 2 slots, 2 upvalues, 0 locals, 0 constants, 0 functions
	1	[133]	GETUPVAL 	0 0	; canModifyTimeout
	2	[133]	GETUPVAL 	1 1	; timeout_custom2
	3	[133]	TAILCALL 	0 2 0
	4	[133]	RETURN   	0 0
	5	[133]	RETURN   	0 1

function <./frontend/ui/elements/screen_android.lua:134,134> (5 instructions, 20 bytes at 0x7f9b5a40aee0)
0 params, 2 slots, 2 upvalues, 0 locals, 0 constants, 0 functions
	1	[134]	GETUPVAL 	0 0	; timeoutEquals
	2	[134]	GETUPVAL 	1 1	; timeout_custom2
	3	[134]	TAILCALL 	0 2 0
	4	[134]	RETURN   	0 0
	5	[134]	RETURN   	0 1

function <./frontend/ui/elements/screen_android.lua:135,135> (4 instructions, 16 bytes at 0x7f9b5a40b090)
0 params, 2 slots, 2 upvalues, 0 locals, 0 constants, 0 functions
	1	[135]	GETUPVAL 	0 0	; saveAndApplyTimeout
	2	[135]	GETUPVAL 	1 1	; timeout_custom2
	3	[135]	CALL     	0 2 1
	4	[135]	RETURN   	0 1

function <./frontend/ui/elements/screen_android.lua:139,139> (5 instructions, 20 bytes at 0x7f9b5a40b350)
0 params, 2 slots, 2 upvalues, 0 locals, 0 constants, 0 functions
	1	[139]	GETUPVAL 	0 0	; canModifyTimeout
	2	[139]	GETUPVAL 	1 1	; timeout_custom3
	3	[139]	TAILCALL 	0 2 0
	4	[139]	RETURN   	0 0
	5	[139]	RETURN   	0 1

function <./frontend/ui/elements/screen_android.lua:140,140> (5 instructions, 20 bytes at 0x7f9b5a40b470)
0 params, 2 slots, 2 upvalues, 0 locals, 0 constants, 0 functions
	1	[140]	GETUPVAL 	0 0	; timeoutEquals
	2	[140]	GETUPVAL 	1 1	; timeout_custom3
	3	[140]	TAILCALL 	0 2 0
	4	[140]	RETURN   	0 0
	5	[140]	RETURN   	0 1

function <./frontend/ui/elements/screen_android.lua:141,141> (4 instructions, 16 bytes at 0x7f9b5a40ac40)
0 params, 2 slots, 2 upvalues, 0 locals, 0 constants, 0 functions
	1	[141]	GETUPVAL 	0 0	; saveAndApplyTimeout
	2	[141]	GETUPVAL 	1 1	; timeout_custom3
	3	[141]	CALL     	0 2 1
	4	[141]	RETURN   	0 1

function <./frontend/ui/elements/screen_android.lua:145,145> (5 instructions, 20 bytes at 0x7f9b5a40ba10)
0 params, 2 slots, 2 upvalues, 0 locals, 0 constants, 0 functions
	1	[145]	GETUPVAL 	0 0	; canModifyTimeout
	2	[145]	GETUPVAL 	1 1	; timeout_custom4
	3	[145]	TAILCALL 	0 2 0
	4	[145]	RETURN   	0 0
	5	[145]	RETURN   	0 1

function <./frontend/ui/elements/screen_android.lua:146,146> (5 instructions, 20 bytes at 0x7f9b5a40bb50)
0 params, 2 slots, 2 upvalues, 0 locals, 0 constants, 0 functions
	1	[146]	GETUPVAL 	0 0	; timeoutEquals
	2	[146]	GETUPVAL 	1 1	; timeout_custom4
	3	[146]	TAILCALL 	0 2 0
	4	[146]	RETURN   	0 0
	5	[146]	RETURN   	0 1

function <./frontend/ui/elements/screen_android.lua:147,147> (4 instructions, 16 bytes at 0x7f9b5a40bd10)
0 params, 2 slots, 2 upvalues, 0 locals, 0 constants, 0 functions
	1	[147]	GETUPVAL 	0 0	; saveAndApplyTimeout
	2	[147]	GETUPVAL 	1 1	; timeout_custom4
	3	[147]	CALL     	0 2 1
	4	[147]	RETURN   	0 1

function <./frontend/ui/elements/screen_android.lua:151,151> (5 instructions, 20 bytes at 0x7f9b5a40bed0)
0 params, 2 slots, 2 upvalues, 0 locals, 0 constants, 0 functions
	1	[151]	GETUPVAL 	0 0	; canModifyTimeout
	2	[151]	GETUPVAL 	1 1	; timeout_custom5
	3	[151]	TAILCALL 	0 2 0
	4	[151]	RETURN   	0 0
	5	[151]	RETURN   	0 1

function <./frontend/ui/elements/screen_android.lua:152,152> (5 instructions, 20 bytes at 0x7f9b5a40c050)
0 params, 2 slots, 2 upvalues, 0 locals, 0 constants, 0 functions
	1	[152]	GETUPVAL 	0 0	; timeoutEquals
	2	[152]	GETUPVAL 	1 1	; timeout_custom5
	3	[152]	TAILCALL 	0 2 0
	4	[152]	RETURN   	0 0
	5	[152]	RETURN   	0 1

function <./frontend/ui/elements/screen_android.lua:153,153> (4 instructions, 16 bytes at 0x7f9b5a40b250)
0 params, 2 slots, 2 upvalues, 0 locals, 0 constants, 0 functions
	1	[153]	GETUPVAL 	0 0	; saveAndApplyTimeout
	2	[153]	GETUPVAL 	1 1	; timeout_custom5
	3	[153]	CALL     	0 2 1
	4	[153]	RETURN   	0 1

function <./frontend/ui/elements/screen_android.lua:157,157> (5 instructions, 20 bytes at 0x7f9b5a40a150)
0 params, 2 slots, 2 upvalues, 0 locals, 0 constants, 0 functions
	1	[157]	GETUPVAL 	0 0	; canModifyTimeout
	2	[157]	GETUPVAL 	1 1	; timeout_custom6
	3	[157]	TAILCALL 	0 2 0
	4	[157]	RETURN   	0 0
	5	[157]	RETURN   	0 1

function <./frontend/ui/elements/screen_android.lua:158,158> (5 instructions, 20 bytes at 0x7f9b5a40a2d0)
0 params, 2 slots, 2 upvalues, 0 locals, 0 constants, 0 functions
	1	[158]	GETUPVAL 	0 0	; timeoutEquals
	2	[158]	GETUPVAL 	1 1	; timeout_custom6
	3	[158]	TAILCALL 	0 2 0
	4	[158]	RETURN   	0 0
	5	[158]	RETURN   	0 1

function <./frontend/ui/elements/screen_android.lua:159,159> (4 instructions, 16 bytes at 0x7f9b5a40c510)
0 params, 2 slots, 2 upvalues, 0 locals, 0 constants, 0 functions
	1	[159]	GETUPVAL 	0 0	; saveAndApplyTimeout
	2	[159]	GETUPVAL 	1 1	; timeout_custom6
	3	[159]	CALL     	0 2 1
	4	[159]	RETURN   	0 1

function <./frontend/ui/elements/screen_android.lua:163,163> (5 instructions, 20 bytes at 0x7f9b5a40c6d0)
0 params, 2 slots, 2 upvalues, 0 locals, 0 constants, 0 functions
	1	[163]	GETUPVAL 	0 0	; canModifyTimeout
	2	[163]	GETUPVAL 	1 1	; timeout_custom7
	3	[163]	TAILCALL 	0 2 0
	4	[163]	RETURN   	0 0
	5	[163]	RETURN   	0 1

function <./frontend/ui/elements/screen_android.lua:164,164> (5 instructions, 20 bytes at 0x7f9b5a40b610)
0 params, 2 slots, 2 upvalues, 0 locals, 0 constants, 0 functions
	1	[164]	GETUPVAL 	0 0	; timeoutEquals
	2	[164]	GETUPVAL 	1 1	; timeout_custom7
	3	[164]	TAILCALL 	0 2 0
	4	[164]	RETURN   	0 0
	5	[164]	RETURN   	0 1

function <./frontend/ui/elements/screen_android.lua:165,165> (4 instructions, 16 bytes at 0x7f9b5a40b7d0)
0 params, 2 slots, 2 upvalues, 0 locals, 0 constants, 0 functions
	1	[165]	GETUPVAL 	0 0	; saveAndApplyTimeout
	2	[165]	GETUPVAL 	1 1	; timeout_custom7
	3	[165]	CALL     	0 2 1
	4	[165]	RETURN   	0 1

function <./frontend/ui/elements/screen_android.lua:169,169> (5 instructions, 20 bytes at 0x7f9b5a40b990)
0 params, 2 slots, 2 upvalues, 0 locals, 0 constants, 0 functions
	1	[169]	GETUPVAL 	0 0	; canModifyTimeout
	2	[169]	GETUPVAL 	1 1	; screenOn
	3	[169]	TAILCALL 	0 2 0
	4	[169]	RETURN   	0 0
	5	[169]	RETURN   	0 1

function <./frontend/ui/elements/screen_android.lua:170,170> (5 instructions, 20 bytes at 0x7f9b5a40c980)
0 params, 2 slots, 2 upvalues, 0 locals, 0 constants, 0 functions
	1	[170]	GETUPVAL 	0 0	; timeoutEquals
	2	[170]	GETUPVAL 	1 1	; screenOn
	3	[170]	TAILCALL 	0 2 0
	4	[170]	RETURN   	0 0
	5	[170]	RETURN   	0 1

function <./frontend/ui/elements/screen_android.lua:171,171> (4 instructions, 16 bytes at 0x7f9b5a40af60)
0 params, 2 slots, 2 upvalues, 0 locals, 0 constants, 0 functions
	1	[171]	GETUPVAL 	0 0	; saveAndApplyTimeout
	2	[171]	GETUPVAL 	1 1	; screenOn
	3	[171]	CALL     	0 2 1
	4	[171]	RETURN   	0 1

function <./frontend/ui/elements/screen_android.lua:178,178> (7 instructions, 28 bytes at 0x7f9b5a40a470)
0 params, 2 slots, 1 upvalue, 0 locals, 2 constants, 0 functions
	1	[178]	GETUPVAL 	0 0	; android
	2	[178]	GETTABLE 	0 0 -1	; "settings"
	3	[178]	GETTABLE 	0 0 -2	; "canWrite"
	4	[178]	CALL     	0 1 2
	5	[178]	NOT      	0 0
	6	[178]	RETURN   	0 2
	7	[178]	RETURN   	0 1

function <./frontend/ui/elements/screen_android.lua:179,179> (6 instructions, 24 bytes at 0x7f9b5a40a9c0)
0 params, 2 slots, 1 upvalue, 0 locals, 2 constants, 0 functions
	1	[179]	GETUPVAL 	0 0	; android
	2	[179]	GETTABLE 	0 0 -1	; "settings"
	3	[179]	GETTABLE 	0 0 -2	; "canWrite"
	4	[179]	TAILCALL 	0 1 0
	5	[179]	RETURN   	0 0
	6	[179]	RETURN   	0 1

function <./frontend/ui/elements/screen_android.lua:180,180> (3 instructions, 12 bytes at 0x7f9b5a40aba0)
0 params, 2 slots, 1 upvalue, 0 locals, 0 constants, 0 functions
	1	[180]	GETUPVAL 	0 0	; requestWriteSettings
	2	[180]	CALL     	0 1 1
	3	[180]	RETURN   	0 1
