-- BYTECODE -- screen_color_menu_table.lua:12-18
0001    UGET     0   0      ; Screen
0002    TGETS    0   0   0  ; "isColorEnabled"
0003    CALL     0   2   1
0004    NOT      0   0
0005    GGET     1   1      ; "G_reader_settings"
0006    MOV      2   1
0007    TGETS    1   1   2  ; "saveSetting"
0008    KSTR     3   3      ; "color_rendering"
0009    MOV      4   0
0010    CALL     1   1   4
0011    UGET     1   1      ; CanvasContext
0012    MOV      2   1
0013    TGETS    1   1   4  ; "setColorRenderingEnabled"
0014    MOV      3   0
0015    CALL     1   1   3
0016    UGET     1   2      ; UIManager
0017    MOV      2   1
0018    TGETS    1   1   5  ; "broadcastEvent"
0019    UGET     3   3      ; Event
0020    MOV      4   3
0021    TGETS    3   3   6  ; "new"
0022    KSTR     5   7      ; "ColorRenderingUpdate"
0023    CALL     3   0   3
0024    CALLM    1   1   1
0025    RET0     0   1

-- BYTECODE -- screen_color_menu_table.lua:0-20
0001    GGET     0   0      ; "require"
0002    KSTR     1   1      ; "ui/event"
0003    CALL     0   2   2
0004    GGET     1   0      ; "require"
0005    KSTR     2   2      ; "device"
0006    CALL     1   2   2
0007    TGETS    1   1   3  ; "screen"
0008    GGET     2   0      ; "require"
0009    KSTR     3   4      ; "ui/uimanager"
0010    CALL     2   2   2
0011    GGET     3   0      ; "require"
0012    KSTR     4   5      ; "document/canvascontext"
0013    CALL     3   2   2
0014    GGET     4   0      ; "require"
0015    KSTR     5   6      ; "gettext"
0016    CALL     4   2   2
0017    TDUP     5   8
0018    MOV      6   4
0019    KSTR     7   7      ; "Color rendering"
0020    CALL     6   2   2
0021    TSETS    6   5   9  ; "text"
0022    MOV      7   1
0023    TGETS    6   1  10  ; "isColorEnabled"
0024    CALL     6   2   2
0025    IST          6
0026    JMP      7 => 0030
0027    MOV      7   1
0028    TGETS    6   1  11  ; "isColorScreen"
0029    CALL     6   2   2
0030 => TSETS    6   5  12  ; "enabled"
0031    TGETS    6   1  10  ; "isColorEnabled"
0032    TSETS    6   5  13  ; "checked_func"
0033    FNEW     6  14      ; screen_color_menu_table.lua:12
0034    TSETS    6   5  15  ; "callback"
0035    UCLO     0 => 0036
0036 => RET1     5   2

