-- BYTECODE -- scrolltextwidget.lua:87-87
0001    UGET     0   0      ; self
0002    TGETS    0   0   0  ; "dimen"
0003    RET1     0   2

-- BYTECODE -- scrolltextwidget.lua:93-93
0001    UGET     0   0      ; self
0002    TGETS    0   0   0  ; "dimen"
0003    RET1     0   2

-- BYTECODE -- scrolltextwidget.lua:101-101
0001    UGET     0   0      ; self
0002    TGETS    0   0   0  ; "dimen"
0003    RET1     0   2

-- BYTECODE -- scrolltextwidget.lua:107-107
0001    UGET     0   0      ; self
0002    TGETS    0   0   0  ; "dimen"
0003    RET1     0   2

-- BYTECODE -- scrolltextwidget.lua:45-118
0001    UGET     1   0      ; TextBoxWidget
0002    MOV      2   1
0003    TGETS    1   1   1  ; "new"
0004    TDUP     3   3
0005    TGETS    4   0   2  ; "text"
0006    TSETS    4   3   2  ; "text"
0007    TGETS    4   0   4  ; "charlist"
0008    TSETS    4   3   4  ; "charlist"
0009    TGETS    4   0   5  ; "charpos"
0010    TSETS    4   3   5  ; "charpos"
0011    TGETS    4   0   6  ; "top_line_num"
0012    TSETS    4   3   6  ; "top_line_num"
0013    TGETS    4   0   7  ; "dialog"
0014    TSETS    4   3   7  ; "dialog"
0015    TGETS    4   0   8  ; "editable"
0016    TSETS    4   3   8  ; "editable"
0017    TGETS    4   0   9  ; "face"
0018    TSETS    4   3   9  ; "face"
0019    TGETS    4   0  10  ; "image_alt_face"
0020    TSETS    4   3  10  ; "image_alt_face"
0021    TGETS    4   0  11  ; "fgcolor"
0022    TSETS    4   3  11  ; "fgcolor"
0023    TGETS    4   0  12  ; "width"
0024    TGETS    5   0  13  ; "scroll_bar_width"
0025    SUBVV    4   4   5
0026    TGETS    5   0  14  ; "text_scroll_span"
0027    SUBVV    4   4   5
0028    TSETS    4   3  12  ; "width"
0029    TGETS    4   0  15  ; "height"
0030    TSETS    4   3  15  ; "height"
0031    TGETS    4   0  16  ; "images"
0032    TSETS    4   3  16  ; "images"
0033    TGETS    4   0  17  ; "alignment"
0034    TSETS    4   3  17  ; "alignment"
0035    TGETS    4   0  18  ; "justified"
0036    TSETS    4   3  18  ; "justified"
0037    TGETS    4   0  19  ; "lang"
0038    TSETS    4   3  19  ; "lang"
0039    TGETS    4   0  20  ; "para_direction_rtl"
0040    TSETS    4   3  20  ; "para_direction_rtl"
0041    TGETS    4   0  21  ; "auto_para_direction"
0042    TSETS    4   3  21  ; "auto_para_direction"
0043    TGETS    4   0  22  ; "alignment_strict"
0044    TSETS    4   3  22  ; "alignment_strict"
0045    CALL     1   2   3
0046    TSETS    1   0   0  ; "text_widget"
0047    TGETS    1   0   0  ; "text_widget"
0048    MOV      2   1
0049    TGETS    1   1  23  ; "getVisLineCount"
0050    CALL     1   2   2
0051    TGETS    2   0   0  ; "text_widget"
0052    MOV      3   2
0053    TGETS    2   2  24  ; "getAllLineCount"
0054    CALL     2   2   2
0055    UGET     3   1      ; VerticalScrollBar
0056    MOV      4   3
0057    TGETS    3   3   1  ; "new"
0058    TDUP     5  26
0059    ISLT     1   2
0060    JMP      6 => 0063
0061    KPRI     6   1
0062    JMP      7 => 0064
0063 => KPRI     6   2
0064 => TSETS    6   5  27  ; "enable"
0065    DIVVV    6   1   2
0066    TSETS    6   5  28  ; "high"
0067    TGETS    6   0  13  ; "scroll_bar_width"
0068    TSETS    6   5  12  ; "width"
0069    TGETS    6   0   0  ; "text_widget"
0070    MOV      7   6
0071    TGETS    6   6  29  ; "getTextHeight"
0072    CALL     6   2   2
0073    TSETS    6   5  15  ; "height"
0074    CALL     3   2   3
0075    TSETS    3   0  25  ; "v_scroll_bar"
0076    MOV      4   0
0077    TGETS    3   0  30  ; "updateScrollBar"
0078    CALL     3   1   2
0079    UGET     3   2      ; HorizontalGroup
0080    MOV      4   3
0081    TGETS    3   3   1  ; "new"
0082    TDUP     5  31
0083    CALL     3   2   3
0084    GGET     4  32      ; "table"
0085    TGETS    4   4  33  ; "insert"
0086    MOV      5   3
0087    TGETS    6   0   0  ; "text_widget"
0088    CALL     4   1   3
0089    GGET     4  32      ; "table"
0090    TGETS    4   4  33  ; "insert"
0091    MOV      5   3
0092    UGET     6   3      ; HorizontalSpan
0093    MOV      7   6
0094    TGETS    6   6   1  ; "new"
0095    TDUP     8  34
0096    TGETS    9   0  14  ; "text_scroll_span"
0097    TSETS    9   8  12  ; "width"
0098    CALL     6   0   3
0099    CALLM    4   1   1
0100    GGET     4  32      ; "table"
0101    TGETS    4   4  33  ; "insert"
0102    MOV      5   3
0103    TGETS    6   0  25  ; "v_scroll_bar"
0104    CALL     4   1   3
0105    TSETB    3   0   1
0106    UGET     4   4      ; Geom
0107    MOV      5   4
0108    TGETS    4   4   1  ; "new"
0109    TGETB    6   0   1
0110    MOV      7   6
0111    TGETS    6   6  36  ; "getSize"
0112    CALL     6   0   2
0113    CALLM    4   2   1
0114    TSETS    4   0  35  ; "dimen"
0115    UGET     4   5      ; Device
0116    MOV      5   4
0117    TGETS    4   4  37  ; "isTouchDevice"
0118    CALL     4   2   2
0119    ISF          4
0120    JMP      5 => 0168
0121    TDUP     4  42
0122    TNEW     5   3
0123    UGET     6   6      ; GestureRange
0124    MOV      7   6
0125    TGETS    6   6   1  ; "new"
0126    TDUP     8  39
0127    FNEW     9  40      ; scrolltextwidget.lua:87
0128    TSETS    9   8  41  ; "range"
0129    CALL     6   0   3
0130    TSETM    6   0      ; 1
0131    TSETS    5   4  43  ; "ScrollText"
0132    TNEW     5   3
0133    UGET     6   6      ; GestureRange
0134    MOV      7   6
0135    TGETS    6   6   1  ; "new"
0136    TDUP     8  44
0137    FNEW     9  45      ; scrolltextwidget.lua:93
0138    TSETS    9   8  41  ; "range"
0139    CALL     6   0   3
0140    TSETM    6   0      ; 1
0141    TSETS    5   4  46  ; "TapScrollText"
0142    TSETS    4   0  38  ; "ges_events"
0143    TGETS    4   0  47  ; "scroll_by_pan"
0144    ISF          4
0145    JMP      5 => 0168
0146    TGETS    4   0  38  ; "ges_events"
0147    TNEW     5   3
0148    UGET     6   6      ; GestureRange
0149    MOV      7   6
0150    TGETS    6   6   1  ; "new"
0151    TDUP     8  49
0152    FNEW     9  50      ; scrolltextwidget.lua:101
0153    TSETS    9   8  41  ; "range"
0154    CALL     6   0   3
0155    TSETM    6   0      ; 1
0156    TSETS    5   4  48  ; "PanText"
0157    TGETS    4   0  38  ; "ges_events"
0158    TNEW     5   3
0159    UGET     6   6      ; GestureRange
0160    MOV      7   6
0161    TGETS    6   6   1  ; "new"
0162    TDUP     8  52
0163    FNEW     9  53      ; scrolltextwidget.lua:107
0164    TSETS    9   8  41  ; "range"
0165    CALL     6   0   3
0166    TSETM    6   0      ; 1
0167    TSETS    5   4  51  ; "PanReleaseText"
0168 => UGET     4   5      ; Device
0169    MOV      5   4
0170    TGETS    4   4  54  ; "hasKeys"
0171    CALL     4   2   2
0172    ISF          4
0173    JMP      5 => 0192
0174    TDUP     4  59
0175    TDUP     5  58
0176    TNEW     6   3
0177    UGET     7   7      ; Input
0178    TGETS    7   7  56  ; "group"
0179    TGETS    7   7  57  ; "PgFwd"
0180    TSETB    7   6   1
0181    TSETB    6   5   1
0182    TSETS    5   4  60  ; "ScrollDown"
0183    TDUP     5  62
0184    TNEW     6   3
0185    UGET     7   7      ; Input
0186    TGETS    7   7  56  ; "group"
0187    TGETS    7   7  61  ; "PgBack"
0188    TSETB    7   6   1
0189    TSETB    6   5   1
0190    TSETS    5   4  63  ; "ScrollUp"
0191    TSETS    4   0  55  ; "key_events"
0192 => UCLO     0 => 0193
0193 => RET0     0   1

-- BYTECODE -- scrolltextwidget.lua:120-122
0001    TGETS    1   0   0  ; "text_widget"
0002    MOV      2   1
0003    TGETS    1   1   1  ; "unfocus"
0004    CALL     1   1   2
0005    RET0     0   1

-- BYTECODE -- scrolltextwidget.lua:124-126
0001    TGETS    1   0   0  ; "text_widget"
0002    MOV      2   1
0003    TGETS    1   1   1  ; "focus"
0004    CALL     1   1   2
0005    RET0     0   1

-- BYTECODE -- scrolltextwidget.lua:128-130
0001    TGETS    1   0   0  ; "text_widget"
0002    MOV      2   1
0003    TGETS    1   1   1  ; "getTextHeight"
0004    CALLT    1   2

-- BYTECODE -- scrolltextwidget.lua:132-134
0001    TGETS    1   0   0  ; "text_widget"
0002    MOV      2   1
0003    TGETS    1   1   1  ; "getLineHeight"
0004    CALLT    1   2

-- BYTECODE -- scrolltextwidget.lua:136-138
0001    TGETS    1   0   0  ; "text_widget"
0002    MOV      2   1
0003    TGETS    1   1   1  ; "getCharPos"
0004    CALLT    1   2

-- BYTECODE -- scrolltextwidget.lua:150-152
0001    UGET     0   0      ; refreshfunc
0002    UGET     1   1      ; self
0003    TGETS    1   1   0  ; "dimen"
0004    RET      0   3

-- BYTECODE -- scrolltextwidget.lua:140-157
0001    TGETS    2   0   0  ; "text_widget"
0002    MOV      3   2
0003    TGETS    2   2   1  ; "getVisibleHeightRatios"
0004    CALL     2   3   2
0005    TGETS    4   0   2  ; "prev_low"
0006    ISNEV    2   4
0007    JMP      4 => 0011
0008    TGETS    4   0   3  ; "prev_high"
0009    ISEQV    3   4
0010    JMP      4 => 0037
0011 => TSETS    2   0   2  ; "prev_low"
0012    TSETS    3   0   3  ; "prev_high"
0013    TGETS    4   0   4  ; "v_scroll_bar"
0014    MOV      5   4
0015    TGETS    4   4   5  ; "set"
0016    MOV      6   2
0017    MOV      7   3
0018    CALL     4   1   4
0019    KSTR     4   6      ; "ui"
0020    ISF          1
0021    JMP      5 => 0023
0022    KSTR     4   7      ; "partial"
0023 => UGET     5   0      ; UIManager
0024    MOV      6   5
0025    TGETS    5   5   8  ; "setDirty"
0026    TGETS    7   0   9  ; "dialog"
0027    FNEW     8  10      ; scrolltextwidget.lua:150
0028    CALL     5   1   4
0029    TGETS    5   0  11  ; "scroll_callback"
0030    ISF          5
0031    JMP      6 => 0036
0032    TGETS    5   0  11  ; "scroll_callback"
0033    MOV      6   2
0034    MOV      7   3
0035    CALL     5   1   3
0036 => UCLO     4 => 0037
0037 => UCLO     0 => 0038
0038 => RET0     0   1

-- BYTECODE -- scrolltextwidget.lua:159-162
0001    TGETS    2   0   0  ; "text_widget"
0002    MOV      3   2
0003    TGETS    2   2   1  ; "moveCursorToCharPos"
0004    MOV      4   1
0005    CALL     2   1   3
0006    MOV      3   0
0007    TGETS    2   0   2  ; "updateScrollBar"
0008    CALL     2   1   2
0009    RET0     0   1

-- BYTECODE -- scrolltextwidget.lua:164-170
0001    UGET     4   0      ; BD
0002    TGETS    4   4   0  ; "mirroredUILayout"
0003    CALL     4   2   1
0004    ISF          4
0005    JMP      5 => 0010
0006    TGETS    4   0   1  ; "scroll_bar_width"
0007    SUBVV    4   1   4
0008    TGETS    5   0   2  ; "text_scroll_span"
0009    SUBVV    1   4   5
0010 => TGETS    4   0   3  ; "text_widget"
0011    MOV      5   4
0012    TGETS    4   4   4  ; "moveCursorToXY"
0013    MOV      6   1
0014    MOV      7   2
0015    MOV      8   3
0016    CALL     4   1   5
0017    MOV      5   0
0018    TGETS    4   0   5  ; "updateScrollBar"
0019    CALL     4   1   2
0020    RET0     0   1

-- BYTECODE -- scrolltextwidget.lua:172-175
0001    TGETS    1   0   0  ; "text_widget"
0002    MOV      2   1
0003    TGETS    1   1   1  ; "moveCursorLeft"
0004    CALL     1   1   2
0005    MOV      2   0
0006    TGETS    1   0   2  ; "updateScrollBar"
0007    CALL     1   1   2
0008    RET0     0   1

-- BYTECODE -- scrolltextwidget.lua:177-180
0001    TGETS    1   0   0  ; "text_widget"
0002    MOV      2   1
0003    TGETS    1   1   1  ; "moveCursorRight"
0004    CALL     1   1   2
0005    MOV      2   0
0006    TGETS    1   0   2  ; "updateScrollBar"
0007    CALL     1   1   2
0008    RET0     0   1

-- BYTECODE -- scrolltextwidget.lua:182-185
0001    TGETS    1   0   0  ; "text_widget"
0002    MOV      2   1
0003    TGETS    1   1   1  ; "moveCursorUp"
0004    CALL     1   1   2
0005    MOV      2   0
0006    TGETS    1   0   2  ; "updateScrollBar"
0007    CALL     1   1   2
0008    RET0     0   1

-- BYTECODE -- scrolltextwidget.lua:187-190
0001    TGETS    1   0   0  ; "text_widget"
0002    MOV      2   1
0003    TGETS    1   1   1  ; "moveCursorDown"
0004    CALL     1   1   2
0005    MOV      2   0
0006    TGETS    1   0   2  ; "updateScrollBar"
0007    CALL     1   1   2
0008    RET0     0   1

-- BYTECODE -- scrolltextwidget.lua:192-195
0001    TGETS    1   0   0  ; "text_widget"
0002    MOV      2   1
0003    TGETS    1   1   1  ; "scrollDown"
0004    CALL     1   1   2
0005    MOV      2   0
0006    TGETS    1   0   2  ; "updateScrollBar"
0007    KPRI     3   2
0008    CALL     1   1   3
0009    RET0     0   1

-- BYTECODE -- scrolltextwidget.lua:197-200
0001    TGETS    1   0   0  ; "text_widget"
0002    MOV      2   1
0003    TGETS    1   1   1  ; "scrollUp"
0004    CALL     1   1   2
0005    MOV      2   0
0006    TGETS    1   0   2  ; "updateScrollBar"
0007    KPRI     3   2
0008    CALL     1   1   3
0009    RET0     0   1

-- BYTECODE -- scrolltextwidget.lua:202-205
0001    TGETS    1   0   0  ; "text_widget"
0002    MOV      2   1
0003    TGETS    1   1   1  ; "scrollToTop"
0004    CALL     1   1   2
0005    MOV      2   0
0006    TGETS    1   0   2  ; "updateScrollBar"
0007    KPRI     3   2
0008    CALL     1   1   3
0009    RET0     0   1

-- BYTECODE -- scrolltextwidget.lua:207-210
0001    TGETS    1   0   0  ; "text_widget"
0002    MOV      2   1
0003    TGETS    1   1   1  ; "scrollToBottom"
0004    CALL     1   1   2
0005    MOV      2   0
0006    TGETS    1   0   2  ; "updateScrollBar"
0007    KPRI     3   2
0008    CALL     1   1   3
0009    RET0     0   1

-- BYTECODE -- scrolltextwidget.lua:212-220
0001    ISNEN    1   0      ; 0
0002    JMP      2 => 0004
0003    RET0     0   1
0004 => KSHORT   2   0
0005    ISGE     2   1
0006    JMP      2 => 0012
0007    TGETS    2   0   0  ; "text_widget"
0008    MOV      3   2
0009    TGETS    2   2   1  ; "scrollDown"
0010    CALL     2   1   2
0011    JMP      2 => 0016
0012 => TGETS    2   0   0  ; "text_widget"
0013    MOV      3   2
0014    TGETS    2   2   2  ; "scrollUp"
0015    CALL     2   1   2
0016 => MOV      3   0
0017    TGETS    2   0   3  ; "updateScrollBar"
0018    KPRI     4   2
0019    CALL     2   1   3
0020    RET0     0   1

-- BYTECODE -- scrolltextwidget.lua:222-225
0001    TGETS    2   0   0  ; "text_widget"
0002    MOV      3   2
0003    TGETS    2   2   1  ; "scrollToRatio"
0004    MOV      4   1
0005    CALL     2   1   3
0006    MOV      3   0
0007    TGETS    2   0   2  ; "updateScrollBar"
0008    KPRI     4   2
0009    CALL     2   1   3
0010    RET0     0   1

-- BYTECODE -- scrolltextwidget.lua:227-237
0001    TGETS    3   2   0  ; "direction"
0002    ISNES    3   1      ; "north"
0003    JMP      3 => 0011
0004    MOV      4   0
0005    TGETS    3   0   2  ; "scrollText"
0006    KSHORT   5   1
0007    CALL     3   1   3
0008    KPRI     3   2
0009    RET1     3   2
0010    JMP      3 => 0020
0011 => TGETS    3   2   0  ; "direction"
0012    ISNES    3   3      ; "south"
0013    JMP      3 => 0020
0014    MOV      4   0
0015    TGETS    3   0   2  ; "scrollText"
0016    KSHORT   5  -1
0017    CALL     3   1   3
0018    KPRI     3   2
0019    RET1     3   2
0020 => RET0     0   1

-- BYTECODE -- scrolltextwidget.lua:239-258
0001    TGETS    3   0   0  ; "editable"
0002    ISF          3
0003    JMP      4 => 0006
0004    KPRI     3   1
0005    RET1     3   2
0006 => UGET     3   0      ; BD
0007    TGETS    3   3   1  ; "flipIfMirroredUILayout"
0008    TGETS    4   2   2  ; "pos"
0009    TGETS    4   4   3  ; "x"
0010    UGET     5   1      ; Screen
0011    MOV      6   5
0012    TGETS    5   5   4  ; "getWidth"
0013    CALL     5   2   2
0014    DIVVN    5   5   0  ; 2
0015    ISLT     4   5
0016    JMP      4 => 0019
0017    KPRI     4   1
0018    JMP      5 => 0020
0019 => KPRI     4   2
0020 => CALL     3   2   2
0021    ISF          3
0022    JMP      4 => 0035
0023    TGETS    3   0   5  ; "text_widget"
0024    TGETS    3   3   6  ; "virtual_line_num"
0025    KSHORT   4   1
0026    ISGE     4   3
0027    JMP      3 => 0053
0028    MOV      4   0
0029    TGETS    3   0   7  ; "scrollText"
0030    KSHORT   5  -1
0031    CALL     3   1   3
0032    KPRI     3   2
0033    RET1     3   2
0034    JMP      3 => 0053
0035 => TGETS    3   0   5  ; "text_widget"
0036    TGETS    3   3   6  ; "virtual_line_num"
0037    TGETS    4   0   5  ; "text_widget"
0038    MOV      5   4
0039    TGETS    4   4   8  ; "getVisLineCount"
0040    CALL     4   2   2
0041    ADDVV    3   3   4
0042    TGETS    4   0   5  ; "text_widget"
0043    TGETS    4   4   9  ; "vertical_string_list"
0044    LEN      4   4
0045    ISGT     3   4
0046    JMP      3 => 0053
0047    MOV      4   0
0048    TGETS    3   0   7  ; "scrollText"
0049    KSHORT   5   1
0050    CALL     3   1   3
0051    KPRI     3   2
0052    RET1     3   2
0053 => RET0     0   1

-- BYTECODE -- scrolltextwidget.lua:260-263
0001    MOV      2   0
0002    TGETS    1   0   0  ; "scrollText"
0003    KSHORT   3   1
0004    CALL     1   1   3
0005    KPRI     1   2
0006    RET1     1   2

-- BYTECODE -- scrolltextwidget.lua:265-268
0001    MOV      2   0
0002    TGETS    1   0   0  ; "scrollText"
0003    KSHORT   3  -1
0004    CALL     1   1   3
0005    KPRI     1   2
0006    RET1     1   2

-- BYTECODE -- scrolltextwidget.lua:270-275
0001    TGETS    3   2   1  ; "direction"
0002    TSETS    3   0   0  ; "_pan_direction"
0003    TGETS    3   2   3  ; "relative"
0004    TGETS    3   3   4  ; "x"
0005    TSETS    3   0   2  ; "_pan_relative_x"
0006    TGETS    3   2   3  ; "relative"
0007    TGETS    3   3   6  ; "y"
0008    TSETS    3   0   5  ; "_pan_relative_y"
0009    KPRI     3   2
0010    RET1     3   2

-- BYTECODE -- scrolltextwidget.lua:277-290
0001    TGETS    3   0   0  ; "_pan_direction"
0002    ISF          3
0003    JMP      4 => 0038
0004    TGETS    3   0   1  ; "_pan_relative_y"
0005    ISF          3
0006    JMP      4 => 0038
0007    TGETS    3   0   0  ; "_pan_direction"
0008    ISEQS    3   2      ; "north"
0009    JMP      3 => 0013
0010    TGETS    3   0   0  ; "_pan_direction"
0011    ISNES    3   3      ; "south"
0012    JMP      3 => 0030
0013 => UGET     3   0      ; Math
0014    TGETS    3   3   4  ; "round"
0015    TGETS    4   0   1  ; "_pan_relative_y"
0016    MOV      6   0
0017    TGETS    5   0   5  ; "getLineHeight"
0018    CALL     5   2   2
0019    DIVVV    4   4   5
0020    CALL     3   2   2
0021    TGETS    4   0   6  ; "text_widget"
0022    MOV      5   4
0023    TGETS    4   4   7  ; "scrollLines"
0024    UNM      6   3
0025    CALL     4   1   3
0026    MOV      5   0
0027    TGETS    4   0   8  ; "updateScrollBar"
0028    KPRI     6   2
0029    CALL     4   1   3
0030 => KPRI     3   0
0031    TSETS    3   0   0  ; "_pan_direction"
0032    KPRI     3   0
0033    TSETS    3   0   9  ; "_pan_relative_x"
0034    KPRI     3   0
0035    TSETS    3   0   1  ; "_pan_relative_y"
0036    KPRI     3   2
0037    RET1     3   2
0038 => KPRI     3   1
0039    RET1     3   2

-- BYTECODE -- scrolltextwidget.lua:0-293
0001    GGET     0   0      ; "require"
0002    KSTR     1   1      ; "ui/bidi"
0003    CALL     0   2   2
0004    GGET     1   0      ; "require"
0005    KSTR     2   2      ; "ffi/blitbuffer"
0006    CALL     1   2   2
0007    GGET     2   0      ; "require"
0008    KSTR     3   3      ; "device"
0009    CALL     2   2   2
0010    GGET     3   0      ; "require"
0011    KSTR     4   4      ; "ui/geometry"
0012    CALL     3   2   2
0013    GGET     4   0      ; "require"
0014    KSTR     5   5      ; "ui/gesturerange"
0015    CALL     4   2   2
0016    GGET     5   0      ; "require"
0017    KSTR     6   6      ; "ui/widget/horizontalgroup"
0018    CALL     5   2   2
0019    GGET     6   0      ; "require"
0020    KSTR     7   7      ; "ui/widget/horizontalspan"
0021    CALL     6   2   2
0022    GGET     7   0      ; "require"
0023    KSTR     8   8      ; "ui/widget/container/inputcontainer"
0024    CALL     7   2   2
0025    GGET     8   0      ; "require"
0026    KSTR     9   9      ; "optmath"
0027    CALL     8   2   2
0028    GGET     9   0      ; "require"
0029    KSTR    10  10      ; "ui/widget/textboxwidget"
0030    CALL     9   2   2
0031    GGET    10   0      ; "require"
0032    KSTR    11  11      ; "ui/widget/verticalscrollbar"
0033    CALL    10   2   2
0034    GGET    11   0      ; "require"
0035    KSTR    12  12      ; "ui/uimanager"
0036    CALL    11   2   2
0037    TGETS   12   2  13  ; "input"
0038    TGETS   13   2  14  ; "screen"
0039    MOV     15   7
0040    TGETS   14   7  15  ; "new"
0041    TDUP    16  16
0042    TGETS   17   1  17  ; "COLOR_BLACK"
0043    TSETS   17  16  18  ; "fgcolor"
0044    MOV     18  13
0045    TGETS   17  13  19  ; "scaleBySize"
0046    KSHORT  19 400
0047    CALL    17   2   3
0048    TSETS   17  16  20  ; "width"
0049    MOV     18  13
0050    TGETS   17  13  19  ; "scaleBySize"
0051    KSHORT  19  20
0052    CALL    17   2   3
0053    TSETS   17  16  21  ; "height"
0054    MOV     18  13
0055    TGETS   17  13  19  ; "scaleBySize"
0056    KSHORT  19   6
0057    CALL    17   2   3
0058    TSETS   17  16  22  ; "scroll_bar_width"
0059    MOV     18  13
0060    TGETS   17  13  19  ; "scaleBySize"
0061    KSHORT  19  12
0062    CALL    17   2   3
0063    TSETS   17  16  23  ; "text_scroll_span"
0064    CALL    14   2   3
0065    FNEW    15  25      ; scrolltextwidget.lua:45
0066    TSETS   15  14  24  ; "init"
0067    FNEW    15  27      ; scrolltextwidget.lua:120
0068    TSETS   15  14  26  ; "unfocus"
0069    FNEW    15  29      ; scrolltextwidget.lua:124
0070    TSETS   15  14  28  ; "focus"
0071    FNEW    15  31      ; scrolltextwidget.lua:128
0072    TSETS   15  14  30  ; "getTextHeight"
0073    FNEW    15  33      ; scrolltextwidget.lua:132
0074    TSETS   15  14  32  ; "getLineHeight"
0075    FNEW    15  35      ; scrolltextwidget.lua:136
0076    TSETS   15  14  34  ; "getCharPos"
0077    FNEW    15  37      ; scrolltextwidget.lua:140
0078    TSETS   15  14  36  ; "updateScrollBar"
0079    FNEW    15  39      ; scrolltextwidget.lua:159
0080    TSETS   15  14  38  ; "moveCursorToCharPos"
0081    FNEW    15  41      ; scrolltextwidget.lua:164
0082    TSETS   15  14  40  ; "moveCursorToXY"
0083    FNEW    15  43      ; scrolltextwidget.lua:172
0084    TSETS   15  14  42  ; "moveCursorLeft"
0085    FNEW    15  45      ; scrolltextwidget.lua:177
0086    TSETS   15  14  44  ; "moveCursorRight"
0087    FNEW    15  47      ; scrolltextwidget.lua:182
0088    TSETS   15  14  46  ; "moveCursorUp"
0089    FNEW    15  49      ; scrolltextwidget.lua:187
0090    TSETS   15  14  48  ; "moveCursorDown"
0091    FNEW    15  51      ; scrolltextwidget.lua:192
0092    TSETS   15  14  50  ; "scrollDown"
0093    FNEW    15  53      ; scrolltextwidget.lua:197
0094    TSETS   15  14  52  ; "scrollUp"
0095    FNEW    15  55      ; scrolltextwidget.lua:202
0096    TSETS   15  14  54  ; "scrollToTop"
0097    FNEW    15  57      ; scrolltextwidget.lua:207
0098    TSETS   15  14  56  ; "scrollToBottom"
0099    FNEW    15  59      ; scrolltextwidget.lua:212
0100    TSETS   15  14  58  ; "scrollText"
0101    FNEW    15  61      ; scrolltextwidget.lua:222
0102    TSETS   15  14  60  ; "scrollToRatio"
0103    FNEW    15  63      ; scrolltextwidget.lua:227
0104    TSETS   15  14  62  ; "onScrollText"
0105    FNEW    15  65      ; scrolltextwidget.lua:239
0106    TSETS   15  14  64  ; "onTapScrollText"
0107    FNEW    15  67      ; scrolltextwidget.lua:260
0108    TSETS   15  14  66  ; "onScrollDown"
0109    FNEW    15  69      ; scrolltextwidget.lua:265
0110    TSETS   15  14  68  ; "onScrollUp"
0111    FNEW    15  71      ; scrolltextwidget.lua:270
0112    TSETS   15  14  70  ; "onPanText"
0113    FNEW    15  73      ; scrolltextwidget.lua:277
0114    TSETS   15  14  72  ; "onPanReleaseText"
0115    UCLO     0 => 0116
0116 => RET1    14   2

