-- BYTECODE -- scrollhtmlwidget.lua:66-66
0001    UGET     0   0      ; self
0002    TGETS    0   0   0  ; "dimen"
0003    RET1     0   2

-- BYTECODE -- scrollhtmlwidget.lua:72-72
0001    UGET     0   0      ; self
0002    TGETS    0   0   0  ; "dimen"
0003    RET1     0   2

-- BYTECODE -- scrollhtmlwidget.lua:34-84
0001    UGET     1   0      ; HtmlBoxWidget
0002    MOV      2   1
0003    TGETS    1   1   1  ; "new"
0004    TDUP     3   9
0005    UGET     4   1      ; Geom
0006    MOV      5   4
0007    TGETS    4   4   1  ; "new"
0008    TDUP     6   5
0009    TGETS    7   0   2  ; "width"
0010    TGETS    8   0   3  ; "scroll_bar_width"
0011    SUBVV    7   7   8
0012    TGETS    8   0   4  ; "text_scroll_span"
0013    SUBVV    7   7   8
0014    TSETS    7   6   6  ; "w"
0015    TGETS    7   0   7  ; "height"
0016    TSETS    7   6   8  ; "h"
0017    CALL     4   2   3
0018    TSETS    4   3  10  ; "dimen"
0019    TGETS    4   0  11  ; "html_link_tapped_callback"
0020    TSETS    4   3  11  ; "html_link_tapped_callback"
0021    CALL     1   2   3
0022    TSETS    1   0   0  ; "htmlbox_widget"
0023    TGETS    1   0   0  ; "htmlbox_widget"
0024    MOV      2   1
0025    TGETS    1   1  12  ; "setContent"
0026    TGETS    3   0  13  ; "html_body"
0027    TGETS    4   0  14  ; "css"
0028    TGETS    5   0  15  ; "default_font_size"
0029    CALL     1   1   5
0030    UGET     1   2      ; VerticalScrollBar
0031    MOV      2   1
0032    TGETS    1   1   1  ; "new"
0033    TDUP     3  18
0034    TGETS    4   0   0  ; "htmlbox_widget"
0035    TGETS    4   4  17  ; "page_count"
0036    KSHORT   5   1
0037    ISLT     5   4
0038    JMP      4 => 0041
0039    KPRI     4   1
0040    JMP      5 => 0042
0041 => KPRI     4   2
0042 => TSETS    4   3  19  ; "enable"
0043    TGETS    4   0   3  ; "scroll_bar_width"
0044    TSETS    4   3   2  ; "width"
0045    TGETS    4   0   7  ; "height"
0046    TSETS    4   3   7  ; "height"
0047    CALL     1   2   3
0048    TSETS    1   0  16  ; "v_scroll_bar"
0049    TGETS    1   0  16  ; "v_scroll_bar"
0050    MOV      2   1
0051    TGETS    1   1  20  ; "set"
0052    TGETS    3   0   0  ; "htmlbox_widget"
0053    TGETS    3   3  21  ; "page_number"
0054    SUBVN    3   3   0  ; 1
0055    TGETS    4   0   0  ; "htmlbox_widget"
0056    TGETS    4   4  17  ; "page_count"
0057    DIVVV    3   3   4
0058    TGETS    4   0   0  ; "htmlbox_widget"
0059    TGETS    4   4  21  ; "page_number"
0060    TGETS    5   0   0  ; "htmlbox_widget"
0061    TGETS    5   5  17  ; "page_count"
0062    DIVVV    4   4   5
0063    CALL     1   1   4
0064    UGET     1   3      ; HorizontalGroup
0065    MOV      2   1
0066    TGETS    1   1   1  ; "new"
0067    TNEW     3   0
0068    CALL     1   2   3
0069    GGET     2  22      ; "table"
0070    TGETS    2   2  23  ; "insert"
0071    MOV      3   1
0072    TGETS    4   0   0  ; "htmlbox_widget"
0073    CALL     2   1   3
0074    GGET     2  22      ; "table"
0075    TGETS    2   2  23  ; "insert"
0076    MOV      3   1
0077    UGET     4   4      ; HorizontalSpan
0078    MOV      5   4
0079    TGETS    4   4   1  ; "new"
0080    TDUP     6  24
0081    TGETS    7   0   4  ; "text_scroll_span"
0082    TSETS    7   6   2  ; "width"
0083    CALL     4   0   3
0084    CALLM    2   1   1
0085    GGET     2  22      ; "table"
0086    TGETS    2   2  23  ; "insert"
0087    MOV      3   1
0088    TGETS    4   0  16  ; "v_scroll_bar"
0089    CALL     2   1   3
0090    TSETB    1   0   1
0091    UGET     2   1      ; Geom
0092    MOV      3   2
0093    TGETS    2   2   1  ; "new"
0094    TGETB    4   0   1
0095    MOV      5   4
0096    TGETS    4   4  25  ; "getSize"
0097    CALL     4   0   2
0098    CALLM    2   2   1
0099    TSETS    2   0  10  ; "dimen"
0100    UGET     2   5      ; Device
0101    MOV      3   2
0102    TGETS    2   2  26  ; "isTouchDevice"
0103    CALL     2   2   2
0104    ISF          2
0105    JMP      3 => 0128
0106    TDUP     2  31
0107    TNEW     3   3
0108    UGET     4   6      ; GestureRange
0109    MOV      5   4
0110    TGETS    4   4   1  ; "new"
0111    TDUP     6  28
0112    FNEW     7  29      ; scrollhtmlwidget.lua:66
0113    TSETS    7   6  30  ; "range"
0114    CALL     4   0   3
0115    TSETM    4   1      ; 1
0116    TSETS    3   2  32  ; "ScrollText"
0117    TNEW     3   3
0118    UGET     4   6      ; GestureRange
0119    MOV      5   4
0120    TGETS    4   4   1  ; "new"
0121    TDUP     6  33
0122    FNEW     7  34      ; scrollhtmlwidget.lua:72
0123    TSETS    7   6  30  ; "range"
0124    CALL     4   0   3
0125    TSETM    4   1      ; 1
0126    TSETS    3   2  35  ; "TapScrollText"
0127    TSETS    2   0  27  ; "ges_events"
0128 => UGET     2   5      ; Device
0129    MOV      3   2
0130    TGETS    2   2  36  ; "hasKeys"
0131    CALL     2   2   2
0132    ISF          2
0133    JMP      3 => 0152
0134    TDUP     2  41
0135    TDUP     3  40
0136    TNEW     4   3
0137    UGET     5   7      ; Input
0138    TGETS    5   5  38  ; "group"
0139    TGETS    5   5  39  ; "PgFwd"
0140    TSETB    5   4   1
0141    TSETB    4   3   1
0142    TSETS    3   2  42  ; "ScrollDown"
0143    TDUP     3  44
0144    TNEW     4   3
0145    UGET     5   7      ; Input
0146    TGETS    5   5  38  ; "group"
0147    TGETS    5   5  43  ; "PgBack"
0148    TSETB    5   4   1
0149    TSETB    4   3   1
0150    TSETS    3   2  45  ; "ScrollUp"
0151    TSETS    2   0  37  ; "key_events"
0152 => UCLO     0 => 0153
0153 => RET0     0   1

-- BYTECODE -- scrollhtmlwidget.lua:86-88
0001    TGETS    1   0   0  ; "htmlbox_widget"
0002    MOV      2   1
0003    TGETS    1   1   1  ; "getSinglePageHeight"
0004    CALLT    1   2

-- BYTECODE -- scrollhtmlwidget.lua:100-102
0001    KSTR     0   0      ; "partial"
0002    UGET     1   0      ; self
0003    TGETS    1   1   1  ; "dimen"
0004    RET      0   3

-- BYTECODE -- scrollhtmlwidget.lua:90-103
0001    GGET     2   0      ; "math"
0002    TGETS    2   2   1  ; "max"
0003    KSHORT   3   0
0004    GGET     4   0      ; "math"
0005    TGETS    4   4   2  ; "min"
0006    KSHORT   5   1
0007    MOV      6   1
0008    CALL     4   0   3
0009    CALLM    2   2   1
0010    MOV      1   2
0011    UGET     2   0      ; Math
0012    TGETS    2   2   3  ; "round"
0013    TGETS    3   0   4  ; "htmlbox_widget"
0014    TGETS    3   3   5  ; "page_count"
0015    SUBVN    3   3   0  ; 1
0016    MULVV    3   3   1
0017    CALL     2   2   2
0018    ADDNV    2   2   0  ; 1
0019    TGETS    3   0   4  ; "htmlbox_widget"
0020    TGETS    3   3   6  ; "page_number"
0021    ISNEV    2   3
0022    JMP      3 => 0024
0023    UCLO     0 => 0053
0024 => TGETS    3   0   4  ; "htmlbox_widget"
0025    TSETS    2   3   6  ; "page_number"
0026    TGETS    3   0   7  ; "v_scroll_bar"
0027    MOV      4   3
0028    TGETS    3   3   8  ; "set"
0029    SUBVN    5   2   0  ; 1
0030    TGETS    6   0   4  ; "htmlbox_widget"
0031    TGETS    6   6   5  ; "page_count"
0032    DIVVV    5   5   6
0033    TGETS    6   0   4  ; "htmlbox_widget"
0034    TGETS    6   6   5  ; "page_count"
0035    DIVVV    6   2   6
0036    CALL     3   1   4
0037    TGETS    3   0   4  ; "htmlbox_widget"
0038    MOV      4   3
0039    TGETS    3   3   9  ; "freeBb"
0040    CALL     3   1   2
0041    TGETS    3   0   4  ; "htmlbox_widget"
0042    MOV      4   3
0043    TGETS    3   3  10  ; "_render"
0044    CALL     3   1   2
0045    UGET     3   1      ; UIManager
0046    MOV      4   3
0047    TGETS    3   3  11  ; "setDirty"
0048    TGETS    5   0  12  ; "dialog"
0049    FNEW     6  13      ; scrollhtmlwidget.lua:100
0050    CALL     3   1   4
0051    UCLO     0 => 0052
0052 => RET0     0   1
0053 => RET0     0   1

-- BYTECODE -- scrollhtmlwidget.lua:129-131
0001    KSTR     0   0      ; "partial"
0002    UGET     1   0      ; self
0003    TGETS    1   1   1  ; "dimen"
0004    RET      0   3

-- BYTECODE -- scrollhtmlwidget.lua:105-132
0001    ISNEN    1   0      ; 0
0002    JMP      2 => 0004
0003    UCLO     0 => 0065
0004 => KSHORT   2   0
0005    ISGE     2   1
0006    JMP      2 => 0020
0007    TGETS    2   0   0  ; "htmlbox_widget"
0008    TGETS    2   2   1  ; "page_number"
0009    TGETS    3   0   0  ; "htmlbox_widget"
0010    TGETS    3   3   2  ; "page_count"
0011    ISGT     3   2
0012    JMP      2 => 0014
0013    UCLO     0 => 0066
0014 => TGETS    2   0   0  ; "htmlbox_widget"
0015    TGETS    3   0   0  ; "htmlbox_widget"
0016    TGETS    3   3   1  ; "page_number"
0017    ADDVN    3   3   1  ; 1
0018    TSETS    3   2   1  ; "page_number"
0019    JMP      2 => 0034
0020 => KSHORT   2   0
0021    ISGE     1   2
0022    JMP      2 => 0034
0023    TGETS    2   0   0  ; "htmlbox_widget"
0024    TGETS    2   2   1  ; "page_number"
0025    KSHORT   3   1
0026    ISGT     2   3
0027    JMP      2 => 0029
0028    UCLO     0 => 0067
0029 => TGETS    2   0   0  ; "htmlbox_widget"
0030    TGETS    3   0   0  ; "htmlbox_widget"
0031    TGETS    3   3   1  ; "page_number"
0032    SUBVN    3   3   1  ; 1
0033    TSETS    3   2   1  ; "page_number"
0034 => TGETS    2   0   3  ; "v_scroll_bar"
0035    MOV      3   2
0036    TGETS    2   2   4  ; "set"
0037    TGETS    4   0   0  ; "htmlbox_widget"
0038    TGETS    4   4   1  ; "page_number"
0039    SUBVN    4   4   1  ; 1
0040    TGETS    5   0   0  ; "htmlbox_widget"
0041    TGETS    5   5   2  ; "page_count"
0042    DIVVV    4   4   5
0043    TGETS    5   0   0  ; "htmlbox_widget"
0044    TGETS    5   5   1  ; "page_number"
0045    TGETS    6   0   0  ; "htmlbox_widget"
0046    TGETS    6   6   2  ; "page_count"
0047    DIVVV    5   5   6
0048    CALL     2   1   4
0049    TGETS    2   0   0  ; "htmlbox_widget"
0050    MOV      3   2
0051    TGETS    2   2   5  ; "freeBb"
0052    CALL     2   1   2
0053    TGETS    2   0   0  ; "htmlbox_widget"
0054    MOV      3   2
0055    TGETS    2   2   6  ; "_render"
0056    CALL     2   1   2
0057    UGET     2   0      ; UIManager
0058    MOV      3   2
0059    TGETS    2   2   7  ; "setDirty"
0060    TGETS    4   0   8  ; "dialog"
0061    FNEW     5   9      ; scrollhtmlwidget.lua:129
0062    CALL     2   1   4
0063    UCLO     0 => 0064
0064 => RET0     0   1
0065 => RET0     0   1
0066 => RET0     0   1
0067 => RET0     0   1

-- BYTECODE -- scrollhtmlwidget.lua:134-144
0001    TGETS    3   2   0  ; "direction"
0002    ISNES    3   1      ; "north"
0003    JMP      3 => 0011
0004    MOV      4   0
0005    TGETS    3   0   2  ; "scrollText"
0006    KSHORT   5   1
0007    CALL     3   1   3
0008    KPRI     3   2
0009    RET1     3   2
0010    JMP      3 => 0020
0011 => TGETS    3   2   0  ; "direction"
0012    ISNES    3   3      ; "south"
0013    JMP      3 => 0020
0014    MOV      4   0
0015    TGETS    3   0   2  ; "scrollText"
0016    KSHORT   5  -1
0017    CALL     3   1   3
0018    KPRI     3   2
0019    RET1     3   2
0020 => RET0     0   1

-- BYTECODE -- scrollhtmlwidget.lua:146-160
0001    UGET     3   0      ; BD
0002    TGETS    3   3   0  ; "flipIfMirroredUILayout"
0003    TGETS    4   2   1  ; "pos"
0004    TGETS    4   4   2  ; "x"
0005    UGET     5   1      ; Screen
0006    MOV      6   5
0007    TGETS    5   5   3  ; "getWidth"
0008    CALL     5   2   2
0009    DIVVN    5   5   0  ; 2
0010    ISLT     4   5
0011    JMP      4 => 0014
0012    KPRI     4   1
0013    JMP      5 => 0015
0014 => KPRI     4   2
0015 => CALL     3   2   2
0016    ISF          3
0017    JMP      4 => 0030
0018    TGETS    3   0   4  ; "htmlbox_widget"
0019    TGETS    3   3   5  ; "page_number"
0020    KSHORT   4   1
0021    ISGE     4   3
0022    JMP      3 => 0042
0023    MOV      4   0
0024    TGETS    3   0   6  ; "scrollText"
0025    KSHORT   5  -1
0026    CALL     3   1   3
0027    KPRI     3   2
0028    RET1     3   2
0029    JMP      3 => 0042
0030 => TGETS    3   0   4  ; "htmlbox_widget"
0031    TGETS    3   3   5  ; "page_number"
0032    TGETS    4   0   4  ; "htmlbox_widget"
0033    TGETS    4   4   7  ; "page_count"
0034    ISGE     3   4
0035    JMP      3 => 0042
0036    MOV      4   0
0037    TGETS    3   0   6  ; "scrollText"
0038    KSHORT   5   1
0039    CALL     3   1   3
0040    KPRI     3   2
0041    RET1     3   2
0042 => RET0     0   1

-- BYTECODE -- scrollhtmlwidget.lua:162-165
0001    MOV      2   0
0002    TGETS    1   0   0  ; "scrollText"
0003    KSHORT   3   1
0004    CALL     1   1   3
0005    KPRI     1   2
0006    RET1     1   2

-- BYTECODE -- scrollhtmlwidget.lua:167-170
0001    MOV      2   0
0002    TGETS    1   0   0  ; "scrollText"
0003    KSHORT   3  -1
0004    CALL     1   1   3
0005    KPRI     1   2
0006    RET1     1   2

-- BYTECODE -- scrollhtmlwidget.lua:0-173
0001    GGET     0   0      ; "require"
0002    KSTR     1   1      ; "ui/bidi"
0003    CALL     0   2   2
0004    GGET     1   0      ; "require"
0005    KSTR     2   2      ; "device"
0006    CALL     1   2   2
0007    GGET     2   0      ; "require"
0008    KSTR     3   3      ; "ui/widget/htmlboxwidget"
0009    CALL     2   2   2
0010    GGET     3   0      ; "require"
0011    KSTR     4   4      ; "ui/geometry"
0012    CALL     3   2   2
0013    GGET     4   0      ; "require"
0014    KSTR     5   5      ; "ui/gesturerange"
0015    CALL     4   2   2
0016    GGET     5   0      ; "require"
0017    KSTR     6   6      ; "ui/widget/horizontalgroup"
0018    CALL     5   2   2
0019    GGET     6   0      ; "require"
0020    KSTR     7   7      ; "ui/widget/horizontalspan"
0021    CALL     6   2   2
0022    GGET     7   0      ; "require"
0023    KSTR     8   8      ; "ui/widget/container/inputcontainer"
0024    CALL     7   2   2
0025    GGET     8   0      ; "require"
0026    KSTR     9   9      ; "ui/uimanager"
0027    CALL     8   2   2
0028    GGET     9   0      ; "require"
0029    KSTR    10  10      ; "ui/widget/verticalscrollbar"
0030    CALL     9   2   2
0031    GGET    10   0      ; "require"
0032    KSTR    11  11      ; "optmath"
0033    CALL    10   2   2
0034    TGETS   11   1  12  ; "input"
0035    TGETS   12   1  13  ; "screen"
0036    MOV     14   7
0037    TGETS   13   7  14  ; "new"
0038    TDUP    15  15
0039    MOV     17  12
0040    TGETS   16  12  16  ; "scaleBySize"
0041    KSHORT  18  24
0042    CALL    16   2   3
0043    TSETS   16  15  17  ; "default_font_size"
0044    MOV     17  12
0045    TGETS   16  12  16  ; "scaleBySize"
0046    KSHORT  18   6
0047    CALL    16   2   3
0048    TSETS   16  15  18  ; "scroll_bar_width"
0049    MOV     17  12
0050    TGETS   16  12  16  ; "scaleBySize"
0051    KSHORT  18  12
0052    CALL    16   2   3
0053    TSETS   16  15  19  ; "text_scroll_span"
0054    CALL    13   2   3
0055    FNEW    14  21      ; scrollhtmlwidget.lua:34
0056    TSETS   14  13  20  ; "init"
0057    FNEW    14  23      ; scrollhtmlwidget.lua:86
0058    TSETS   14  13  22  ; "getSinglePageHeight"
0059    FNEW    14  25      ; scrollhtmlwidget.lua:90
0060    TSETS   14  13  24  ; "scrollToRatio"
0061    FNEW    14  27      ; scrollhtmlwidget.lua:105
0062    TSETS   14  13  26  ; "scrollText"
0063    FNEW    14  29      ; scrollhtmlwidget.lua:134
0064    TSETS   14  13  28  ; "onScrollText"
0065    FNEW    14  31      ; scrollhtmlwidget.lua:146
0066    TSETS   14  13  30  ; "onTapScrollText"
0067    FNEW    14  33      ; scrollhtmlwidget.lua:162
0068    TSETS   14  13  32  ; "onScrollDown"
0069    FNEW    14  35      ; scrollhtmlwidget.lua:167
0070    TSETS   14  13  34  ; "onScrollUp"
0071    UCLO     0 => 0072
0072 => RET1    13   2

