
main <./frontend/ui/widget/scrollhtmlwidget.lua:0,0> (90 instructions, 360 bytes at 0x7ff802c068f0)
0+ params, 19 slots, 0 upvalues, 14 locals, 41 constants, 8 functions
	1	[5]	GETGLOBAL	0 -1	; require
	2	[5]	LOADK    	1 -2	; "ui/bidi"
	3	[5]	CALL     	0 2 2
	4	[6]	GETGLOBAL	1 -1	; require
	5	[6]	LOADK    	2 -3	; "device"
	6	[6]	CALL     	1 2 2
	7	[7]	GETGLOBAL	2 -1	; require
	8	[7]	LOADK    	3 -4	; "ui/widget/htmlboxwidget"
	9	[7]	CALL     	2 2 2
	10	[8]	GETGLOBAL	3 -1	; require
	11	[8]	LOADK    	4 -5	; "ui/geometry"
	12	[8]	CALL     	3 2 2
	13	[9]	GETGLOBAL	4 -1	; require
	14	[9]	LOADK    	5 -6	; "ui/gesturerange"
	15	[9]	CALL     	4 2 2
	16	[10]	GETGLOBAL	5 -1	; require
	17	[10]	LOADK    	6 -7	; "ui/widget/horizontalgroup"
	18	[10]	CALL     	5 2 2
	19	[11]	GETGLOBAL	6 -1	; require
	20	[11]	LOADK    	7 -8	; "ui/widget/horizontalspan"
	21	[11]	CALL     	6 2 2
	22	[12]	GETGLOBAL	7 -1	; require
	23	[12]	LOADK    	8 -9	; "ui/widget/container/inputcontainer"
	24	[12]	CALL     	7 2 2
	25	[13]	GETGLOBAL	8 -1	; require
	26	[13]	LOADK    	9 -10	; "ui/uimanager"
	27	[13]	CALL     	8 2 2
	28	[14]	GETGLOBAL	9 -1	; require
	29	[14]	LOADK    	10 -11	; "ui/widget/verticalscrollbar"
	30	[14]	CALL     	9 2 2
	31	[15]	GETGLOBAL	10 -1	; require
	32	[15]	LOADK    	11 -12	; "optmath"
	33	[15]	CALL     	10 2 2
	34	[16]	GETTABLE 	11 1 -13	; "input"
	35	[17]	GETTABLE 	12 1 -14	; "screen"
	36	[19]	SELF     	13 7 -15	; "new"
	37	[19]	NEWTABLE 	15 0 12
	38	[20]	SETTABLE 	15 -16 -17	; "html_body" nil
	39	[21]	SETTABLE 	15 -18 -17	; "css" nil
	40	[22]	SELF     	16 12 -20	; "scaleBySize"
	41	[22]	LOADK    	18 -21	; 24
	42	[22]	CALL     	16 3 2
	43	[22]	SETTABLE 	15 -19 16	; "default_font_size" -
	44	[23]	SETTABLE 	15 -22 -17	; "htmlbox_widget" nil
	45	[24]	SETTABLE 	15 -23 -17	; "v_scroll_bar" nil
	46	[25]	SETTABLE 	15 -24 -17	; "dialog" nil
	47	[26]	SETTABLE 	15 -25 -17	; "html_link_tapped_callback" nil
	48	[27]	SETTABLE 	15 -26 -17	; "dimen" nil
	49	[28]	SETTABLE 	15 -27 -28	; "width" 0
	50	[29]	SETTABLE 	15 -29 -28	; "height" 0
	51	[30]	SELF     	16 12 -20	; "scaleBySize"
	52	[30]	LOADK    	18 -31	; 6
	53	[30]	CALL     	16 3 2
	54	[30]	SETTABLE 	15 -30 16	; "scroll_bar_width" -
	55	[31]	SELF     	16 12 -20	; "scaleBySize"
	56	[31]	LOADK    	18 -33	; 12
	57	[31]	CALL     	16 3 2
	58	[31]	SETTABLE 	15 -32 16	; "text_scroll_span" -
	59	[19]	CALL     	13 3 2
	60	[84]	CLOSURE  	14 0	; 0x7ff802c07080
	61	[84]	MOVE     	0 2
	62	[84]	MOVE     	0 3
	63	[84]	MOVE     	0 9
	64	[84]	MOVE     	0 5
	65	[84]	MOVE     	0 6
	66	[84]	MOVE     	0 1
	67	[84]	MOVE     	0 4
	68	[84]	MOVE     	0 11
	69	[34]	SETTABLE 	13 -34 14	; "init" -
	70	[88]	CLOSURE  	14 1	; 0x7ff802c077d0
	71	[86]	SETTABLE 	13 -35 14	; "getSinglePageHeight" -
	72	[103]	CLOSURE  	14 2	; 0x7ff802c06730
	73	[103]	MOVE     	0 10
	74	[103]	MOVE     	0 8
	75	[90]	SETTABLE 	13 -36 14	; "scrollToRatio" -
	76	[132]	CLOSURE  	14 3	; 0x7ff802c067c0
	77	[132]	MOVE     	0 8
	78	[105]	SETTABLE 	13 -37 14	; "scrollText" -
	79	[144]	CLOSURE  	14 4	; 0x7ff802c09030
	80	[134]	SETTABLE 	13 -38 14	; "onScrollText" -
	81	[160]	CLOSURE  	14 5	; 0x7ff802c08bb0
	82	[160]	MOVE     	0 0
	83	[160]	MOVE     	0 12
	84	[146]	SETTABLE 	13 -39 14	; "onTapScrollText" -
	85	[165]	CLOSURE  	14 6	; 0x7ff802c09840
	86	[162]	SETTABLE 	13 -40 14	; "onScrollDown" -
	87	[170]	CLOSURE  	14 7	; 0x7ff802c099c0
	88	[167]	SETTABLE 	13 -41 14	; "onScrollUp" -
	89	[172]	RETURN   	13 2
	90	[172]	RETURN   	0 1

function <./frontend/ui/widget/scrollhtmlwidget.lua:34,84> (143 instructions, 572 bytes at 0x7ff802c07080)
1 param, 9 slots, 8 upvalues, 2 locals, 41 constants, 2 functions
	1	[35]	GETUPVAL 	1 0	; HtmlBoxWidget
	2	[35]	SELF     	1 1 -2	; "new"
	3	[35]	NEWTABLE 	3 0 2
	4	[36]	GETUPVAL 	4 1	; Geom
	5	[36]	SELF     	4 4 -2	; "new"
	6	[36]	NEWTABLE 	6 0 2
	7	[37]	GETTABLE 	7 0 -5	; "width"
	8	[37]	GETTABLE 	8 0 -6	; "scroll_bar_width"
	9	[37]	SUB      	7 7 8
	10	[37]	GETTABLE 	8 0 -7	; "text_scroll_span"
	11	[37]	SUB      	7 7 8
	12	[37]	SETTABLE 	6 -4 7	; "w" -
	13	[38]	GETTABLE 	7 0 -9	; "height"
	14	[38]	SETTABLE 	6 -8 7	; "h" -
	15	[36]	CALL     	4 3 2
	16	[39]	SETTABLE 	3 -3 4	; "dimen" -
	17	[40]	GETTABLE 	4 0 -10	; "html_link_tapped_callback"
	18	[40]	SETTABLE 	3 -10 4	; "html_link_tapped_callback" -
	19	[35]	CALL     	1 3 2
	20	[41]	SETTABLE 	0 -1 1	; "htmlbox_widget" -
	21	[43]	GETTABLE 	1 0 -1	; "htmlbox_widget"
	22	[43]	SELF     	1 1 -11	; "setContent"
	23	[43]	GETTABLE 	3 0 -12	; "html_body"
	24	[43]	GETTABLE 	4 0 -13	; "css"
	25	[43]	GETTABLE 	5 0 -14	; "default_font_size"
	26	[43]	CALL     	1 5 1
	27	[45]	GETUPVAL 	1 2	; VerticalScrollBar
	28	[45]	SELF     	1 1 -2	; "new"
	29	[45]	NEWTABLE 	3 0 3
	30	[46]	GETTABLE 	4 0 -1	; "htmlbox_widget"
	31	[46]	GETTABLE 	4 4 -17	; "page_count"
	32	[46]	LT       	1 -18 4	; 1 -
	33	[46]	JMP      	1	; to 35
	34	[46]	LOADBOOL 	4 0 1
	35	[46]	LOADBOOL 	4 1 0
	36	[46]	SETTABLE 	3 -16 4	; "enable" -
	37	[47]	GETTABLE 	4 0 -6	; "scroll_bar_width"
	38	[47]	SETTABLE 	3 -5 4	; "width" -
	39	[48]	GETTABLE 	4 0 -9	; "height"
	40	[48]	SETTABLE 	3 -9 4	; "height" -
	41	[45]	CALL     	1 3 2
	42	[49]	SETTABLE 	0 -15 1	; "v_scroll_bar" -
	43	[51]	GETTABLE 	1 0 -15	; "v_scroll_bar"
	44	[51]	SELF     	1 1 -19	; "set"
	45	[51]	GETTABLE 	3 0 -1	; "htmlbox_widget"
	46	[51]	GETTABLE 	3 3 -20	; "page_number"
	47	[51]	SUB      	3 3 -18	; - 1
	48	[51]	GETTABLE 	4 0 -1	; "htmlbox_widget"
	49	[51]	GETTABLE 	4 4 -17	; "page_count"
	50	[51]	DIV      	3 3 4
	51	[51]	GETTABLE 	4 0 -1	; "htmlbox_widget"
	52	[51]	GETTABLE 	4 4 -20	; "page_number"
	53	[51]	GETTABLE 	5 0 -1	; "htmlbox_widget"
	54	[51]	GETTABLE 	5 5 -17	; "page_count"
	55	[51]	DIV      	4 4 5
	56	[51]	CALL     	1 4 1
	57	[53]	GETUPVAL 	1 3	; HorizontalGroup
	58	[53]	SELF     	1 1 -2	; "new"
	59	[53]	NEWTABLE 	3 0 0
	60	[53]	CALL     	1 3 2
	61	[54]	GETGLOBAL	2 -21	; table
	62	[54]	GETTABLE 	2 2 -22	; "insert"
	63	[54]	MOVE     	3 1
	64	[54]	GETTABLE 	4 0 -1	; "htmlbox_widget"
	65	[54]	CALL     	2 3 1
	66	[55]	GETGLOBAL	2 -21	; table
	67	[55]	GETTABLE 	2 2 -22	; "insert"
	68	[55]	MOVE     	3 1
	69	[55]	GETUPVAL 	4 4	; HorizontalSpan
	70	[55]	SELF     	4 4 -2	; "new"
	71	[55]	NEWTABLE 	6 0 1
	72	[55]	GETTABLE 	7 0 -7	; "text_scroll_span"
	73	[55]	SETTABLE 	6 -5 7	; "width" -
	74	[55]	CALL     	4 3 0
	75	[55]	CALL     	2 0 1
	76	[56]	GETGLOBAL	2 -21	; table
	77	[56]	GETTABLE 	2 2 -22	; "insert"
	78	[56]	MOVE     	3 1
	79	[56]	GETTABLE 	4 0 -15	; "v_scroll_bar"
	80	[56]	CALL     	2 3 1
	81	[57]	SETTABLE 	0 -18 1	; 1 -
	82	[59]	GETUPVAL 	2 1	; Geom
	83	[59]	SELF     	2 2 -2	; "new"
	84	[59]	GETTABLE 	4 0 -18	; 1
	85	[59]	SELF     	4 4 -23	; "getSize"
	86	[59]	CALL     	4 2 0
	87	[59]	CALL     	2 0 2
	88	[59]	SETTABLE 	0 -3 2	; "dimen" -
	89	[61]	GETUPVAL 	2 5	; Device
	90	[61]	SELF     	2 2 -24	; "isTouchDevice"
	91	[61]	CALL     	2 2 2
	92	[61]	TEST     	2 0 0
	93	[61]	JMP      	24	; to 118
	94	[62]	NEWTABLE 	2 0 2
	95	[63]	NEWTABLE 	3 0 0
	96	[64]	GETUPVAL 	4 6	; GestureRange
	97	[64]	SELF     	4 4 -2	; "new"
	98	[64]	NEWTABLE 	6 0 2
	99	[65]	SETTABLE 	6 -27 -28	; "ges" "swipe"
	100	[66]	CLOSURE  	7 0	; 0x7ff802c078a0
	101	[66]	MOVE     	0 0
	102	[66]	SETTABLE 	6 -29 7	; "range" -
	103	[64]	CALL     	4 3 0
	104	[68]	SETLIST  	3 0 1	; 1
	105	[68]	SETTABLE 	2 -26 3	; "ScrollText" -
	106	[69]	NEWTABLE 	3 0 0
	107	[70]	GETUPVAL 	4 6	; GestureRange
	108	[70]	SELF     	4 4 -2	; "new"
	109	[70]	NEWTABLE 	6 0 2
	110	[71]	SETTABLE 	6 -27 -31	; "ges" "tap"
	111	[72]	CLOSURE  	7 1	; 0x7ff802c07ed0
	112	[72]	MOVE     	0 0
	113	[72]	SETTABLE 	6 -29 7	; "range" -
	114	[70]	CALL     	4 3 0
	115	[74]	SETLIST  	3 0 1	; 1
	116	[74]	SETTABLE 	2 -30 3	; "TapScrollText" -
	117	[75]	SETTABLE 	0 -25 2	; "ges_events" -
	118	[78]	GETUPVAL 	2 5	; Device
	119	[78]	SELF     	2 2 -32	; "hasKeys"
	120	[78]	CALL     	2 2 2
	121	[78]	TEST     	2 0 0
	122	[78]	JMP      	20	; to 143
	123	[79]	NEWTABLE 	2 0 2
	124	[80]	NEWTABLE 	3 1 1
	125	[80]	NEWTABLE 	4 1 0
	126	[80]	GETUPVAL 	5 7	; Input
	127	[80]	GETTABLE 	5 5 -35	; "group"
	128	[80]	GETTABLE 	5 5 -36	; "PgFwd"
	129	[80]	SETLIST  	4 1 1	; 1
	130	[80]	SETTABLE 	3 -37 -38	; "doc" "scroll down"
	131	[80]	SETLIST  	3 1 1	; 1
	132	[80]	SETTABLE 	2 -34 3	; "ScrollDown" -
	133	[81]	NEWTABLE 	3 1 1
	134	[81]	NEWTABLE 	4 1 0
	135	[81]	GETUPVAL 	5 7	; Input
	136	[81]	GETTABLE 	5 5 -35	; "group"
	137	[81]	GETTABLE 	5 5 -40	; "PgBack"
	138	[81]	SETLIST  	4 1 1	; 1
	139	[81]	SETTABLE 	3 -37 -41	; "doc" "scroll up"
	140	[81]	SETLIST  	3 1 1	; 1
	141	[81]	SETTABLE 	2 -39 3	; "ScrollUp" -
	142	[82]	SETTABLE 	0 -33 2	; "key_events" -
	143	[84]	RETURN   	0 1

function <./frontend/ui/widget/scrollhtmlwidget.lua:66,66> (4 instructions, 16 bytes at 0x7ff802c078a0)
0 params, 2 slots, 1 upvalue, 0 locals, 1 constant, 0 functions
	1	[66]	GETUPVAL 	0 0	; self
	2	[66]	GETTABLE 	0 0 -1	; "dimen"
	3	[66]	RETURN   	0 2
	4	[66]	RETURN   	0 1

function <./frontend/ui/widget/scrollhtmlwidget.lua:72,72> (4 instructions, 16 bytes at 0x7ff802c07ed0)
0 params, 2 slots, 1 upvalue, 0 locals, 1 constant, 0 functions
	1	[72]	GETUPVAL 	0 0	; self
	2	[72]	GETTABLE 	0 0 -1	; "dimen"
	3	[72]	RETURN   	0 2
	4	[72]	RETURN   	0 1

function <./frontend/ui/widget/scrollhtmlwidget.lua:86,88> (5 instructions, 20 bytes at 0x7ff802c077d0)
1 param, 3 slots, 0 upvalues, 1 local, 2 constants, 0 functions
	1	[87]	GETTABLE 	1 0 -1	; "htmlbox_widget"
	2	[87]	SELF     	1 1 -2	; "getSinglePageHeight"
	3	[87]	TAILCALL 	1 2 0
	4	[87]	RETURN   	1 0
	5	[88]	RETURN   	0 1

function <./frontend/ui/widget/scrollhtmlwidget.lua:90,103> (48 instructions, 192 bytes at 0x7ff802c06730)
2 params, 7 slots, 2 upvalues, 3 locals, 15 constants, 1 function
	1	[91]	GETGLOBAL	2 -1	; math
	2	[91]	GETTABLE 	2 2 -2	; "max"
	3	[91]	LOADK    	3 -3	; 0
	4	[91]	GETGLOBAL	4 -1	; math
	5	[91]	GETTABLE 	4 4 -4	; "min"
	6	[91]	LOADK    	5 -5	; 1
	7	[91]	MOVE     	6 1
	8	[91]	CALL     	4 3 0
	9	[91]	CALL     	2 0 2
	10	[91]	MOVE     	1 2
	11	[92]	GETUPVAL 	2 0	; Math
	12	[92]	GETTABLE 	2 2 -6	; "round"
	13	[92]	GETTABLE 	3 0 -7	; "htmlbox_widget"
	14	[92]	GETTABLE 	3 3 -8	; "page_count"
	15	[92]	SUB      	3 3 -5	; - 1
	16	[92]	MUL      	3 3 1
	17	[92]	CALL     	2 2 2
	18	[92]	ADD      	2 -5 2	; 1 -
	19	[93]	GETTABLE 	3 0 -7	; "htmlbox_widget"
	20	[93]	GETTABLE 	3 3 -9	; "page_number"
	21	[93]	EQ       	0 2 3
	22	[93]	JMP      	1	; to 24
	23	[94]	RETURN   	0 1
	24	[96]	GETTABLE 	3 0 -7	; "htmlbox_widget"
	25	[96]	SETTABLE 	3 -9 2	; "page_number" -
	26	[97]	GETTABLE 	3 0 -10	; "v_scroll_bar"
	27	[97]	SELF     	3 3 -11	; "set"
	28	[97]	SUB      	5 2 -5	; - 1
	29	[97]	GETTABLE 	6 0 -7	; "htmlbox_widget"
	30	[97]	GETTABLE 	6 6 -8	; "page_count"
	31	[97]	DIV      	5 5 6
	32	[97]	GETTABLE 	6 0 -7	; "htmlbox_widget"
	33	[97]	GETTABLE 	6 6 -8	; "page_count"
	34	[97]	DIV      	6 2 6
	35	[97]	CALL     	3 4 1
	36	[98]	GETTABLE 	3 0 -7	; "htmlbox_widget"
	37	[98]	SELF     	3 3 -12	; "freeBb"
	38	[98]	CALL     	3 2 1
	39	[99]	GETTABLE 	3 0 -7	; "htmlbox_widget"
	40	[99]	SELF     	3 3 -13	; "_render"
	41	[99]	CALL     	3 2 1
	42	[100]	GETUPVAL 	3 1	; UIManager
	43	[100]	SELF     	3 3 -14	; "setDirty"
	44	[100]	GETTABLE 	5 0 -15	; "dialog"
	45	[102]	CLOSURE  	6 0	; 0x7ff802c08490
	46	[102]	MOVE     	0 0
	47	[100]	CALL     	3 4 1
	48	[103]	RETURN   	0 1

function <./frontend/ui/widget/scrollhtmlwidget.lua:100,102> (5 instructions, 20 bytes at 0x7ff802c08490)
0 params, 2 slots, 1 upvalue, 0 locals, 2 constants, 0 functions
	1	[101]	LOADK    	0 -1	; "partial"
	2	[101]	GETUPVAL 	1 0	; self
	3	[101]	GETTABLE 	1 1 -2	; "dimen"
	4	[101]	RETURN   	0 3
	5	[102]	RETURN   	0 1

function <./frontend/ui/widget/scrollhtmlwidget.lua:105,132> (57 instructions, 228 bytes at 0x7ff802c067c0)
2 params, 7 slots, 1 upvalue, 2 locals, 11 constants, 1 function
	1	[106]	EQ       	0 1 -1	; - 0
	2	[106]	JMP      	1	; to 4
	3	[107]	RETURN   	0 1
	4	[110]	LT       	0 -1 1	; 0 -
	5	[110]	JMP      	13	; to 19
	6	[111]	GETTABLE 	2 0 -2	; "htmlbox_widget"
	7	[111]	GETTABLE 	2 2 -3	; "page_number"
	8	[111]	GETTABLE 	3 0 -2	; "htmlbox_widget"
	9	[111]	GETTABLE 	3 3 -4	; "page_count"
	10	[111]	LE       	0 3 2
	11	[111]	JMP      	1	; to 13
	12	[112]	RETURN   	0 1
	13	[115]	GETTABLE 	2 0 -2	; "htmlbox_widget"
	14	[115]	GETTABLE 	3 0 -2	; "htmlbox_widget"
	15	[115]	GETTABLE 	3 3 -3	; "page_number"
	16	[115]	ADD      	3 3 -5	; - 1
	17	[115]	SETTABLE 	2 -3 3	; "page_number" -
	18	[115]	JMP      	12	; to 31
	19	[116]	LT       	0 1 -1	; - 0
	20	[116]	JMP      	10	; to 31
	21	[117]	GETTABLE 	2 0 -2	; "htmlbox_widget"
	22	[117]	GETTABLE 	2 2 -3	; "page_number"
	23	[117]	LE       	0 2 -5	; - 1
	24	[117]	JMP      	1	; to 26
	25	[118]	RETURN   	0 1
	26	[121]	GETTABLE 	2 0 -2	; "htmlbox_widget"
	27	[121]	GETTABLE 	3 0 -2	; "htmlbox_widget"
	28	[121]	GETTABLE 	3 3 -3	; "page_number"
	29	[121]	SUB      	3 3 -5	; - 1
	30	[121]	SETTABLE 	2 -3 3	; "page_number" -
	31	[124]	GETTABLE 	2 0 -6	; "v_scroll_bar"
	32	[124]	SELF     	2 2 -7	; "set"
	33	[124]	GETTABLE 	4 0 -2	; "htmlbox_widget"
	34	[124]	GETTABLE 	4 4 -3	; "page_number"
	35	[124]	SUB      	4 4 -5	; - 1
	36	[124]	GETTABLE 	5 0 -2	; "htmlbox_widget"
	37	[124]	GETTABLE 	5 5 -4	; "page_count"
	38	[124]	DIV      	4 4 5
	39	[124]	GETTABLE 	5 0 -2	; "htmlbox_widget"
	40	[124]	GETTABLE 	5 5 -3	; "page_number"
	41	[124]	GETTABLE 	6 0 -2	; "htmlbox_widget"
	42	[124]	GETTABLE 	6 6 -4	; "page_count"
	43	[124]	DIV      	5 5 6
	44	[124]	CALL     	2 4 1
	45	[126]	GETTABLE 	2 0 -2	; "htmlbox_widget"
	46	[126]	SELF     	2 2 -8	; "freeBb"
	47	[126]	CALL     	2 2 1
	48	[127]	GETTABLE 	2 0 -2	; "htmlbox_widget"
	49	[127]	SELF     	2 2 -9	; "_render"
	50	[127]	CALL     	2 2 1
	51	[129]	GETUPVAL 	2 0	; UIManager
	52	[129]	SELF     	2 2 -10	; "setDirty"
	53	[129]	GETTABLE 	4 0 -11	; "dialog"
	54	[131]	CLOSURE  	5 0	; 0x7ff802c07fd0
	55	[131]	MOVE     	0 0
	56	[129]	CALL     	2 4 1
	57	[132]	RETURN   	0 1

function <./frontend/ui/widget/scrollhtmlwidget.lua:129,131> (5 instructions, 20 bytes at 0x7ff802c07fd0)
0 params, 2 slots, 1 upvalue, 0 locals, 2 constants, 0 functions
	1	[130]	LOADK    	0 -1	; "partial"
	2	[130]	GETUPVAL 	1 0	; self
	3	[130]	GETTABLE 	1 1 -2	; "dimen"
	4	[130]	RETURN   	0 3
	5	[131]	RETURN   	0 1

function <./frontend/ui/widget/scrollhtmlwidget.lua:134,144> (18 instructions, 72 bytes at 0x7ff802c09030)
3 params, 6 slots, 0 upvalues, 3 locals, 6 constants, 0 functions
	1	[135]	GETTABLE 	3 2 -1	; "direction"
	2	[135]	EQ       	0 3 -2	; - "north"
	3	[135]	JMP      	6	; to 10
	4	[136]	SELF     	3 0 -3	; "scrollText"
	5	[136]	LOADK    	5 -4	; 1
	6	[136]	CALL     	3 3 1
	7	[137]	LOADBOOL 	3 1 0
	8	[137]	RETURN   	3 2
	9	[137]	JMP      	8	; to 18
	10	[138]	GETTABLE 	3 2 -1	; "direction"
	11	[138]	EQ       	0 3 -5	; - "south"
	12	[138]	JMP      	5	; to 18
	13	[139]	SELF     	3 0 -3	; "scrollText"
	14	[139]	LOADK    	5 -6	; -1
	15	[139]	CALL     	3 3 1
	16	[140]	LOADBOOL 	3 1 0
	17	[140]	RETURN   	3 2
	18	[144]	RETURN   	0 1

function <./frontend/ui/widget/scrollhtmlwidget.lua:146,160> (37 instructions, 148 bytes at 0x7ff802c08bb0)
3 params, 7 slots, 2 upvalues, 3 locals, 11 constants, 0 functions
	1	[147]	GETUPVAL 	3 0	; BD
	2	[147]	GETTABLE 	3 3 -1	; "flipIfMirroredUILayout"
	3	[147]	GETTABLE 	4 2 -2	; "pos"
	4	[147]	GETTABLE 	4 4 -3	; "x"
	5	[147]	GETUPVAL 	5 1	; Screen
	6	[147]	SELF     	5 5 -4	; "getWidth"
	7	[147]	CALL     	5 2 2
	8	[147]	DIV      	5 5 -5	; - 2
	9	[147]	LT       	1 4 5
	10	[147]	JMP      	1	; to 12
	11	[147]	LOADBOOL 	4 0 1
	12	[147]	LOADBOOL 	4 1 0
	13	[147]	CALL     	3 2 2
	14	[147]	TEST     	3 0 0
	15	[147]	JMP      	10	; to 26
	16	[148]	GETTABLE 	3 0 -6	; "htmlbox_widget"
	17	[148]	GETTABLE 	3 3 -7	; "page_number"
	18	[148]	LT       	0 -8 3	; 1 -
	19	[148]	JMP      	17	; to 37
	20	[149]	SELF     	3 0 -9	; "scrollText"
	21	[149]	LOADK    	5 -10	; -1
	22	[149]	CALL     	3 3 1
	23	[150]	LOADBOOL 	3 1 0
	24	[150]	RETURN   	3 2
	25	[151]	JMP      	11	; to 37
	26	[153]	GETTABLE 	3 0 -6	; "htmlbox_widget"
	27	[153]	GETTABLE 	3 3 -7	; "page_number"
	28	[153]	GETTABLE 	4 0 -6	; "htmlbox_widget"
	29	[153]	GETTABLE 	4 4 -11	; "page_count"
	30	[153]	LT       	0 3 4
	31	[153]	JMP      	5	; to 37
	32	[154]	SELF     	3 0 -9	; "scrollText"
	33	[154]	LOADK    	5 -8	; 1
	34	[154]	CALL     	3 3 1
	35	[155]	LOADBOOL 	3 1 0
	36	[155]	RETURN   	3 2
	37	[160]	RETURN   	0 1

function <./frontend/ui/widget/scrollhtmlwidget.lua:162,165> (6 instructions, 24 bytes at 0x7ff802c09840)
1 param, 4 slots, 0 upvalues, 1 local, 2 constants, 0 functions
	1	[163]	SELF     	1 0 -1	; "scrollText"
	2	[163]	LOADK    	3 -2	; 1
	3	[163]	CALL     	1 3 1
	4	[164]	LOADBOOL 	1 1 0
	5	[164]	RETURN   	1 2
	6	[165]	RETURN   	0 1

function <./frontend/ui/widget/scrollhtmlwidget.lua:167,170> (6 instructions, 24 bytes at 0x7ff802c099c0)
1 param, 4 slots, 0 upvalues, 1 local, 2 constants, 0 functions
	1	[168]	SELF     	1 0 -1	; "scrollText"
	2	[168]	LOADK    	3 -2	; -1
	3	[168]	CALL     	1 3 1
	4	[169]	LOADBOOL 	1 1 0
	5	[169]	RETURN   	1 2
	6	[170]	RETURN   	0 1
