-- BYTECODE -- settings_migration.lua:13-53
0001    GGET     2   0      ; "getmetatable"
0002    MOV      3   1
0003    CALL     2   2   2
0004    TGETS    2   2   1  ; "__index"
0005    KPRI     3   0
0006    UGET     4   0      ; DocSettings
0007    ISNEV    2   4
0008    JMP      4 => 0011
0009    KSTR     3   2      ; "book"
0010    JMP      4 => 0021
0011 => UGET     4   1      ; LuaSettings
0012    ISNEV    2   4
0013    JMP      4 => 0016
0014    KSTR     3   3      ; "global"
0015    JMP      4 => 0021
0016 => UGET     4   2      ; logger
0017    TGETS    4   4   4  ; "warn"
0018    KSTR     5   5      ; "Passed an unsupported object class to Se"~
0019    CALL     4   1   2
0020    RET0     0   1
0021 => MOV      5   1
0022    TGETS    4   1   6  ; "readSetting"
0023    KSTR     6   7      ; "copt_page_margins"
0024    CALL     4   2   3
0025    ISF          4
0026    JMP      5 => 0063
0027    UGET     5   2      ; logger
0028    TGETS    5   5   8  ; "info"
0029    KSTR     6   9      ; "Migrating old"
0030    MOV      7   3
0031    KSTR     8  10      ; "CRe margin settings: L"
0032    TGETB    9   4   1
0033    KSTR    10  11      ; "T"
0034    TGETB   11   4   2
0035    KSTR    12  12      ; "R"
0036    TGETB   13   4   3
0037    KSTR    14  13      ; "B"
0038    TGETB   15   4   4
0039    CALL     5   1  11
0040    MOV      6   1
0041    TGETS    5   1  14  ; "saveSetting"
0042    KSTR     7  15      ; "copt_h_page_margins"
0043    TNEW     8   3
0044    TGETB    9   4   1
0045    TSETB    9   8   1
0046    TGETB    9   4   3
0047    TSETB    9   8   2
0048    CALL     5   1   4
0049    MOV      6   1
0050    TGETS    5   1  14  ; "saveSetting"
0051    KSTR     7  16      ; "copt_t_page_margin"
0052    TGETB    8   4   2
0053    CALL     5   1   4
0054    MOV      6   1
0055    TGETS    5   1  14  ; "saveSetting"
0056    KSTR     7  17      ; "copt_b_page_margin"
0057    TGETB    8   4   4
0058    CALL     5   1   4
0059    MOV      6   1
0060    TGETS    5   1  18  ; "delSetting"
0061    KSTR     7   7      ; "copt_page_margins"
0062    CALL     5   1   3
0063 => MOV      6   1
0064    TGETS    5   1   6  ; "readSetting"
0065    KSTR     7  19      ; "copt_word_spacing"
0066    CALL     5   2   3
0067    IST          5
0068    JMP      5 => 0100
0069    MOV      6   1
0070    TGETS    5   1   6  ; "readSetting"
0071    KSTR     7  20      ; "copt_space_condensing"
0072    CALL     5   2   3
0073    ISF          5
0074    JMP      6 => 0100
0075    MOV      6   1
0076    TGETS    5   1   6  ; "readSetting"
0077    KSTR     7  20      ; "copt_space_condensing"
0078    CALL     5   2   3
0079    UGET     6   2      ; logger
0080    TGETS    6   6   8  ; "info"
0081    KSTR     7   9      ; "Migrating old"
0082    MOV      8   3
0083    KSTR     9  21      ; "CRe space condensing:"
0084    MOV     10   5
0085    CALL     6   1   5
0086    MOV      7   1
0087    TGETS    6   1  14  ; "saveSetting"
0088    KSTR     8  19      ; "copt_word_spacing"
0089    TDUP     9  22
0090    TSETB    5   9   2
0091    CALL     6   1   4
0092    ISNES    3   2      ; "book"
0093    JMP      6 => 0100
0094    MOV      7   1
0095    TGETS    6   1  14  ; "saveSetting"
0096    KSTR     8  23      ; "word_spacing"
0097    TDUP     9  24
0098    TSETB    5   9   2
0099    CALL     6   1   4
0100 => RET0     0   1

-- BYTECODE -- settings_migration.lua:0-56
0001    GGET     0   0      ; "require"
0002    KSTR     1   1      ; "docsettings"
0003    CALL     0   2   2
0004    GGET     1   0      ; "require"
0005    KSTR     2   2      ; "luasettings"
0006    CALL     1   2   2
0007    GGET     2   0      ; "require"
0008    KSTR     3   3      ; "logger"
0009    CALL     2   2   2
0010    TNEW     3   0
0011    FNEW     4   5      ; settings_migration.lua:13
0012    TSETS    4   3   4  ; "migrateSettings"
0013    UCLO     0 => 0014
0014 => RET1     3   2

