-- BYTECODE -- size_spec.lua:3-6
0001    GGET     0   0      ; "require"
0002    KSTR     1   1      ; "commonrequire"
0003    CALL     0   1   2
0004    GGET     0   0      ; "require"
0005    KSTR     1   2      ; "ui/size"
0006    CALL     0   2   2
0007    USETV    0   0      ; Size
0008    RET0     0   1

-- BYTECODE -- size_spec.lua:8-10
0001    GGET     0   0      ; "assert"
0002    TGETS    0   0   1  ; "is_true"
0003    UGET     1   0      ; Size
0004    TGETS    1   1   2  ; "border"
0005    TGETS    1   1   3  ; "window"
0006    KSHORT   2   1
0007    ISLE     2   1
0008    JMP      1 => 0011
0009    KPRI     1   1
0010    JMP      2 => 0012
0011 => KPRI     1   2
0012 => CALL     0   1   2
0013    RET0     0   1

-- BYTECODE -- size_spec.lua:7-11
0001    GGET     0   0      ; "it"
0002    KSTR     1   1      ; "for window border"
0003    FNEW     2   2      ; size_spec.lua:8
0004    CALL     0   1   3
0005    RET0     0   1

-- BYTECODE -- size_spec.lua:12-15
0001    GGET     0   0      ; "assert"
0002    TGETS    0   0   1  ; "is_nil"
0003    UGET     1   0      ; Size
0004    TGETS    1   1   2  ; "supercalifragilisticexpialidocious"
0005    CALL     0   1   2
0006    GGET     0   0      ; "assert"
0007    TGETS    0   0   1  ; "is_nil"
0008    UGET     1   0      ; Size
0009    TGETS    1   1   3  ; "border"
0010    TGETS    1   1   2  ; "supercalifragilisticexpialidocious"
0011    CALL     0   1   2
0012    RET0     0   1

-- BYTECODE -- size_spec.lua:20-22
0001    UGET     0   0      ; Size
0002    TGETS    0   0   0  ; "supercalifragilisticexpialidocious"
0003    RET1     0   2

-- BYTECODE -- size_spec.lua:23-25
0001    UGET     0   0      ; Size
0002    TGETS    0   0   0  ; "border"
0003    TGETS    0   0   1  ; "supercalifragilisticexpialidocious"
0004    RET1     0   2

-- BYTECODE -- size_spec.lua:16-30
0001    GGET     0   0      ; "require"
0002    KSTR     1   1      ; "dbg"
0003    CALL     0   2   2
0004    MOV      2   0
0005    TGETS    1   0   2  ; "turnOn"
0006    CALL     1   1   2
0007    GGET     1   3      ; "package"
0008    TGETS    1   1   4  ; "reload"
0009    KSTR     2   5      ; "ui/size"
0010    CALL     1   2   2
0011    USETV    0   1      ; Size
0012    FNEW     1   6      ; size_spec.lua:20
0013    FNEW     2   7      ; size_spec.lua:23
0014    GGET     3   8      ; "assert"
0015    TGETS    3   3   9  ; "has_error"
0016    MOV      4   1
0017    KSTR     5  10      ; "Size: this property does not exist: Size"~
0018    CALL     3   1   3
0019    GGET     3   8      ; "assert"
0020    TGETS    3   3   9  ; "has_error"
0021    MOV      4   2
0022    KSTR     5  11      ; "Size: this property does not exist: Size"~
0023    CALL     3   1   3
0024    MOV      4   0
0025    TGETS    3   0  12  ; "turnOff"
0026    CALL     3   1   2
0027    RET0     0   1

-- BYTECODE -- size_spec.lua:1-31
0001    KPRI     0   0
0002    GGET     1   0      ; "setup"
0003    FNEW     2   1      ; size_spec.lua:3
0004    CALL     1   1   2
0005    GGET     1   2      ; "describe"
0006    KSTR     2   3      ; "should get size"
0007    FNEW     3   4      ; size_spec.lua:7
0008    CALL     1   1   3
0009    GGET     1   5      ; "it"
0010    KSTR     2   6      ; "should be nil for non-existent property"
0011    FNEW     3   7      ; size_spec.lua:12
0012    CALL     1   1   3
0013    GGET     1   5      ; "it"
0014    KSTR     2   8      ; "should fail for non-existent property wh"~
0015    FNEW     3   9      ; size_spec.lua:16
0016    CALL     1   1   3
0017    UCLO     0 => 0018
0018 => RET0     0   1

-- BYTECODE -- size_spec.lua:0-32
0001    GGET     0   0      ; "describe"
0002    KSTR     1   1      ; "Size module"
0003    FNEW     2   2      ; size_spec.lua:1
0004    CALL     0   1   3
0005    RET0     0   1

