
main <./spec/unit/size_spec.lua:0,0> (5 instructions, 20 bytes at 0x7ff1ff4068c0)
0+ params, 3 slots, 0 upvalues, 0 locals, 2 constants, 1 function
	1	[1]	GETGLOBAL	0 -1	; describe
	2	[1]	LOADK    	1 -2	; "Size module"
	3	[31]	CLOSURE  	2 0	; 0x7ff1ff406b60
	4	[1]	CALL     	0 3 1
	5	[31]	RETURN   	0 1

function <./spec/unit/size_spec.lua:1,31> (20 instructions, 80 bytes at 0x7ff1ff406b60)
0 params, 4 slots, 0 upvalues, 1 local, 6 constants, 4 functions
	1	[3]	GETGLOBAL	1 -1	; setup
	2	[6]	CLOSURE  	2 0	; 0x7ff1ff406d80
	3	[6]	MOVE     	0 0
	4	[3]	CALL     	1 2 1
	5	[7]	GETGLOBAL	1 -2	; describe
	6	[7]	LOADK    	2 -3	; "should get size"
	7	[11]	CLOSURE  	3 1	; 0x7ff1ff406c60
	8	[11]	MOVE     	0 0
	9	[7]	CALL     	1 3 1
	10	[12]	GETGLOBAL	1 -4	; it
	11	[12]	LOADK    	2 -5	; "should be nil for non-existent property"
	12	[15]	CLOSURE  	3 2	; 0x7ff1ff407930
	13	[15]	MOVE     	0 0
	14	[12]	CALL     	1 3 1
	15	[16]	GETGLOBAL	1 -4	; it
	16	[16]	LOADK    	2 -6	; "should fail for non-existent property when debug is activated"
	17	[30]	CLOSURE  	3 3	; 0x7ff1ff407110
	18	[30]	MOVE     	0 0
	19	[16]	CALL     	1 3 1
	20	[31]	RETURN   	0 1

function <./spec/unit/size_spec.lua:3,6> (8 instructions, 32 bytes at 0x7ff1ff406d80)
0 params, 2 slots, 1 upvalue, 0 locals, 3 constants, 0 functions
	1	[4]	GETGLOBAL	0 -1	; require
	2	[4]	LOADK    	1 -2	; "commonrequire"
	3	[4]	CALL     	0 2 1
	4	[5]	GETGLOBAL	0 -1	; require
	5	[5]	LOADK    	1 -3	; "ui/size"
	6	[5]	CALL     	0 2 2
	7	[5]	SETUPVAL 	0 0	; Size
	8	[6]	RETURN   	0 1

function <./spec/unit/size_spec.lua:7,11> (6 instructions, 24 bytes at 0x7ff1ff406c60)
0 params, 3 slots, 1 upvalue, 0 locals, 2 constants, 1 function
	1	[8]	GETGLOBAL	0 -1	; it
	2	[8]	LOADK    	1 -2	; "for window border"
	3	[10]	CLOSURE  	2 0	; 0x7ff1ff4073e0
	4	[10]	GETUPVAL 	0 0	; Size
	5	[8]	CALL     	0 3 1
	6	[11]	RETURN   	0 1

function <./spec/unit/size_spec.lua:8,10> (11 instructions, 44 bytes at 0x7ff1ff4073e0)
0 params, 2 slots, 1 upvalue, 0 locals, 5 constants, 0 functions
	1	[9]	GETGLOBAL	0 -1	; assert
	2	[9]	GETTABLE 	0 0 -2	; "is_true"
	3	[9]	GETUPVAL 	1 0	; Size
	4	[9]	GETTABLE 	1 1 -3	; "border"
	5	[9]	GETTABLE 	1 1 -4	; "window"
	6	[9]	LE       	1 -5 1	; 1 -
	7	[9]	JMP      	1	; to 9
	8	[9]	LOADBOOL 	1 0 1
	9	[9]	LOADBOOL 	1 1 0
	10	[9]	CALL     	0 2 1
	11	[10]	RETURN   	0 1

function <./spec/unit/size_spec.lua:12,15> (12 instructions, 48 bytes at 0x7ff1ff407930)
0 params, 2 slots, 1 upvalue, 0 locals, 4 constants, 0 functions
	1	[13]	GETGLOBAL	0 -1	; assert
	2	[13]	GETTABLE 	0 0 -2	; "is_nil"
	3	[13]	GETUPVAL 	1 0	; Size
	4	[13]	GETTABLE 	1 1 -3	; "supercalifragilisticexpialidocious"
	5	[13]	CALL     	0 2 1
	6	[14]	GETGLOBAL	0 -1	; assert
	7	[14]	GETTABLE 	0 0 -2	; "is_nil"
	8	[14]	GETUPVAL 	1 0	; Size
	9	[14]	GETTABLE 	1 1 -4	; "border"
	10	[14]	GETTABLE 	1 1 -3	; "supercalifragilisticexpialidocious"
	11	[14]	CALL     	0 2 1
	12	[15]	RETURN   	0 1

function <./spec/unit/size_spec.lua:16,30> (27 instructions, 108 bytes at 0x7ff1ff407110)
0 params, 6 slots, 1 upvalue, 3 locals, 11 constants, 2 functions
	1	[17]	GETGLOBAL	0 -1	; require
	2	[17]	LOADK    	1 -2	; "dbg"
	3	[17]	CALL     	0 2 2
	4	[18]	SELF     	1 0 -3	; "turnOn"
	5	[18]	CALL     	1 2 1
	6	[19]	GETGLOBAL	1 -4	; package
	7	[19]	GETTABLE 	1 1 -5	; "reload"
	8	[19]	LOADK    	2 -6	; "ui/size"
	9	[19]	CALL     	1 2 2
	10	[19]	SETUPVAL 	1 0	; Size
	11	[22]	CLOSURE  	1 0	; 0x7ff1ff408000
	12	[22]	GETUPVAL 	0 0	; Size
	13	[25]	CLOSURE  	2 1	; 0x7ff1ff4066f0
	14	[25]	GETUPVAL 	0 0	; Size
	15	[27]	GETGLOBAL	3 -7	; assert
	16	[27]	GETTABLE 	3 3 -8	; "has_error"
	17	[27]	MOVE     	4 1
	18	[27]	LOADK    	5 -9	; "Size: this property does not exist: Size.supercalifragilisticexpialidocious"
	19	[27]	CALL     	3 3 1
	20	[28]	GETGLOBAL	3 -7	; assert
	21	[28]	GETTABLE 	3 3 -8	; "has_error"
	22	[28]	MOVE     	4 2
	23	[28]	LOADK    	5 -10	; "Size: this property does not exist: Size.border.supercalifragilisticexpialidocious"
	24	[28]	CALL     	3 3 1
	25	[29]	SELF     	3 0 -11	; "turnOff"
	26	[29]	CALL     	3 2 1
	27	[30]	RETURN   	0 1

function <./spec/unit/size_spec.lua:20,22> (4 instructions, 16 bytes at 0x7ff1ff408000)
0 params, 2 slots, 1 upvalue, 0 locals, 1 constant, 0 functions
	1	[21]	GETUPVAL 	0 0	; Size
	2	[21]	GETTABLE 	0 0 -1	; "supercalifragilisticexpialidocious"
	3	[21]	RETURN   	0 2
	4	[22]	RETURN   	0 1

function <./spec/unit/size_spec.lua:23,25> (5 instructions, 20 bytes at 0x7ff1ff4066f0)
0 params, 2 slots, 1 upvalue, 0 locals, 2 constants, 0 functions
	1	[24]	GETUPVAL 	0 0	; Size
	2	[24]	GETTABLE 	0 0 -1	; "border"
	3	[24]	GETTABLE 	0 0 -2	; "supercalifragilisticexpialidocious"
	4	[24]	RETURN   	0 2
	5	[25]	RETURN   	0 1
