
main <./frontend/ui/size.lua:0,0> (170 instructions, 680 bytes at 0x7fac4dc068a0)
0+ params, 12 slots, 0 upvalues, 9 locals, 53 constants, 1 function
	1	[28]	GETGLOBAL	0 -1	; require
	2	[28]	LOADK    	1 -2	; "dbg"
	3	[28]	CALL     	0 2 2
	4	[29]	GETGLOBAL	1 -1	; require
	5	[29]	LOADK    	2 -3	; "device"
	6	[29]	CALL     	1 2 2
	7	[29]	GETTABLE 	1 1 -4	; "screen"
	8	[31]	NEWTABLE 	2 0 7
	9	[32]	NEWTABLE 	3 0 5
	10	[33]	SELF     	4 1 -7	; "scaleBySize"
	11	[33]	LOADK    	6 -8	; 1
	12	[33]	CALL     	4 3 2
	13	[33]	SETTABLE 	3 -6 4	; "default" -
	14	[34]	SELF     	4 1 -7	; "scaleBySize"
	15	[34]	LOADK    	6 -10	; 0.5
	16	[34]	CALL     	4 3 2
	17	[34]	SETTABLE 	3 -9 4	; "thin" -
	18	[35]	SELF     	4 1 -7	; "scaleBySize"
	19	[35]	LOADK    	6 -12	; 1.5
	20	[35]	CALL     	4 3 2
	21	[35]	SETTABLE 	3 -11 4	; "button" -
	22	[36]	SELF     	4 1 -7	; "scaleBySize"
	23	[36]	LOADK    	6 -12	; 1.5
	24	[36]	CALL     	4 3 2
	25	[36]	SETTABLE 	3 -13 4	; "window" -
	26	[37]	SELF     	4 1 -7	; "scaleBySize"
	27	[37]	LOADK    	6 -15	; 2
	28	[37]	CALL     	4 3 2
	29	[37]	SETTABLE 	3 -14 4	; "inputtext" -
	30	[38]	SETTABLE 	2 -5 3	; "border" -
	31	[39]	NEWTABLE 	3 0 6
	32	[40]	SELF     	4 1 -7	; "scaleBySize"
	33	[40]	LOADK    	6 -17	; 5
	34	[40]	CALL     	4 3 2
	35	[40]	SETTABLE 	3 -6 4	; "default" -
	36	[41]	SELF     	4 1 -7	; "scaleBySize"
	37	[41]	LOADK    	6 -8	; 1
	38	[41]	CALL     	4 3 2
	39	[41]	SETTABLE 	3 -18 4	; "tiny" -
	40	[42]	SELF     	4 1 -7	; "scaleBySize"
	41	[42]	LOADK    	6 -15	; 2
	42	[42]	CALL     	4 3 2
	43	[42]	SETTABLE 	3 -19 4	; "small" -
	44	[43]	SELF     	4 1 -7	; "scaleBySize"
	45	[43]	LOADK    	6 -15	; 2
	46	[43]	CALL     	4 3 2
	47	[43]	SETTABLE 	3 -20 4	; "title" -
	48	[44]	SELF     	4 1 -7	; "scaleBySize"
	49	[44]	LOADK    	6 -22	; 3
	50	[44]	CALL     	4 3 2
	51	[44]	SETTABLE 	3 -21 4	; "fine_tune" -
	52	[45]	SETTABLE 	3 -11 -23	; "button" 0
	53	[46]	SETTABLE 	2 -16 3	; "margin" -
	54	[47]	NEWTABLE 	3 0 7
	55	[48]	SELF     	4 1 -7	; "scaleBySize"
	56	[48]	LOADK    	6 -17	; 5
	57	[48]	CALL     	4 3 2
	58	[48]	SETTABLE 	3 -6 4	; "default" -
	59	[49]	SELF     	4 1 -7	; "scaleBySize"
	60	[49]	LOADK    	6 -8	; 1
	61	[49]	CALL     	4 3 2
	62	[49]	SETTABLE 	3 -18 4	; "tiny" -
	63	[50]	SELF     	4 1 -7	; "scaleBySize"
	64	[50]	LOADK    	6 -15	; 2
	65	[50]	CALL     	4 3 2
	66	[50]	SETTABLE 	3 -19 4	; "small" -
	67	[51]	SELF     	4 1 -7	; "scaleBySize"
	68	[51]	LOADK    	6 -26	; 10
	69	[51]	CALL     	4 3 2
	70	[51]	SETTABLE 	3 -25 4	; "large" -
	71	[52]	SELF     	4 1 -7	; "scaleBySize"
	72	[52]	LOADK    	6 -15	; 2
	73	[52]	CALL     	4 3 2
	74	[52]	SETTABLE 	3 -11 4	; "button" -
	75	[53]	SELF     	4 1 -7	; "scaleBySize"
	76	[53]	LOADK    	6 -28	; 4
	77	[53]	CALL     	4 3 2
	78	[53]	SETTABLE 	3 -27 4	; "buttontable" -
	79	[54]	SELF     	4 1 -7	; "scaleBySize"
	80	[54]	LOADK    	6 -30	; 15
	81	[54]	CALL     	4 3 2
	82	[54]	SETTABLE 	3 -29 4	; "fullscreen" -
	83	[55]	SETTABLE 	2 -24 3	; "padding" -
	84	[56]	NEWTABLE 	3 0 3
	85	[57]	SELF     	4 1 -7	; "scaleBySize"
	86	[57]	LOADK    	6 -15	; 2
	87	[57]	CALL     	4 3 2
	88	[57]	SETTABLE 	3 -6 4	; "default" -
	89	[58]	SELF     	4 1 -7	; "scaleBySize"
	90	[58]	LOADK    	6 -32	; 7
	91	[58]	CALL     	4 3 2
	92	[58]	SETTABLE 	3 -13 4	; "window" -
	93	[59]	SELF     	4 1 -7	; "scaleBySize"
	94	[59]	LOADK    	6 -30	; 15
	95	[59]	CALL     	4 3 2
	96	[59]	SETTABLE 	3 -11 4	; "button" -
	97	[60]	SETTABLE 	2 -31 3	; "radius" -
	98	[61]	NEWTABLE 	3 0 4
	99	[62]	SELF     	4 1 -7	; "scaleBySize"
	100	[62]	LOADK    	6 -10	; 0.5
	101	[62]	CALL     	4 3 2
	102	[62]	SETTABLE 	3 -9 4	; "thin" -
	103	[63]	SELF     	4 1 -7	; "scaleBySize"
	104	[63]	LOADK    	6 -8	; 1
	105	[63]	CALL     	4 3 2
	106	[63]	SETTABLE 	3 -34 4	; "medium" -
	107	[64]	SELF     	4 1 -7	; "scaleBySize"
	108	[64]	LOADK    	6 -12	; 1.5
	109	[64]	CALL     	4 3 2
	110	[64]	SETTABLE 	3 -35 4	; "thick" -
	111	[65]	SELF     	4 1 -7	; "scaleBySize"
	112	[65]	LOADK    	6 -32	; 7
	113	[65]	CALL     	4 3 2
	114	[65]	SETTABLE 	3 -36 4	; "progress" -
	115	[66]	SETTABLE 	2 -33 3	; "line" -
	116	[67]	NEWTABLE 	3 0 3
	117	[68]	SELF     	4 1 -7	; "scaleBySize"
	118	[68]	LOADK    	6 -39	; 30
	119	[68]	CALL     	4 3 2
	120	[68]	SETTABLE 	3 -38 4	; "height_default" -
	121	[69]	SELF     	4 1 -7	; "scaleBySize"
	122	[69]	LOADK    	6 -41	; 40
	123	[69]	CALL     	4 3 2
	124	[69]	SETTABLE 	3 -40 4	; "height_big" -
	125	[70]	SELF     	4 1 -7	; "scaleBySize"
	126	[70]	LOADK    	6 -43	; 50
	127	[70]	CALL     	4 3 2
	128	[70]	SETTABLE 	3 -42 4	; "height_large" -
	129	[71]	SETTABLE 	2 -37 3	; "item" -
	130	[72]	NEWTABLE 	3 0 4
	131	[73]	SELF     	4 1 -7	; "scaleBySize"
	132	[73]	LOADK    	6 -26	; 10
	133	[73]	CALL     	4 3 2
	134	[73]	SETTABLE 	3 -45 4	; "horizontal_default" -
	135	[74]	SELF     	4 1 -7	; "scaleBySize"
	136	[74]	LOADK    	6 -17	; 5
	137	[74]	CALL     	4 3 2
	138	[74]	SETTABLE 	3 -46 4	; "horizontal_small" -
	139	[75]	SELF     	4 1 -7	; "scaleBySize"
	140	[75]	LOADK    	6 -15	; 2
	141	[75]	CALL     	4 3 2
	142	[75]	SETTABLE 	3 -47 4	; "vertical_default" -
	143	[76]	SELF     	4 1 -7	; "scaleBySize"
	144	[76]	LOADK    	6 -17	; 5
	145	[76]	CALL     	4 3 2
	146	[76]	SETTABLE 	3 -48 4	; "vertical_large" -
	147	[77]	SETTABLE 	2 -44 3	; "span" -
	148	[80]	GETTABLE 	3 0 -49	; "is_on"
	149	[80]	TEST     	3 0 0
	150	[80]	JMP      	18	; to 169
	151	[81]	NEWTABLE 	3 0 1
	152	[92]	CLOSURE  	4 0	; 0x7fac4dc07170
	153	[92]	SETTABLE 	3 -50 4	; "__index" -
	154	[94]	GETGLOBAL	4 -51	; setmetatable
	155	[94]	MOVE     	5 2
	156	[94]	MOVE     	6 3
	157	[94]	CALL     	4 3 1
	158	[95]	GETGLOBAL	4 -52	; pairs
	159	[95]	MOVE     	5 2
	160	[95]	CALL     	4 2 4
	161	[95]	JMP      	5	; to 167
	162	[96]	SETTABLE 	8 -53 7	; "_name" -
	163	[97]	GETGLOBAL	9 -51	; setmetatable
	164	[97]	GETTABLE 	10 2 7
	165	[97]	MOVE     	11 3
	166	[97]	CALL     	9 3 1
	167	[95]	TFORLOOP 	4 2
	168	[97]	JMP      	-7	; to 162
	169	[101]	RETURN   	2 2
	170	[101]	RETURN   	0 1

function <./frontend/ui/size.lua:82,92> (42 instructions, 168 bytes at 0x7fac4dc07170)
2 params, 9 slots, 0 upvalues, 5 locals, 10 constants, 0 functions
	1	[83]	GETGLOBAL	2 -1	; rawget
	2	[83]	MOVE     	3 0
	3	[83]	MOVE     	4 1
	4	[83]	CALL     	2 3 2
	5	[84]	EQ       	0 2 -2	; - nil
	6	[84]	JMP      	1	; to 8
	7	[84]	LOADBOOL 	3 0 1
	8	[84]	LOADBOOL 	3 1 0
	9	[85]	TEST     	3 0 1
	10	[85]	JMP      	27	; to 38
	11	[86]	GETGLOBAL	4 -1	; rawget
	12	[86]	MOVE     	5 0
	13	[86]	LOADK    	6 -3	; "_name"
	14	[86]	CALL     	4 3 2
	15	[86]	TEST     	4 0 0
	16	[86]	JMP      	11	; to 28
	17	[86]	GETGLOBAL	4 -4	; string
	18	[86]	GETTABLE 	4 4 -5	; "format"
	19	[86]	LOADK    	5 -6	; "Size.%s.%s"
	20	[86]	GETGLOBAL	6 -1	; rawget
	21	[86]	MOVE     	7 0
	22	[86]	LOADK    	8 -3	; "_name"
	23	[86]	CALL     	6 3 2
	24	[86]	MOVE     	7 1
	25	[86]	CALL     	4 4 2
	26	[87]	TEST     	4 0 1
	27	[87]	JMP      	5	; to 33
	28	[87]	GETGLOBAL	4 -4	; string
	29	[87]	GETTABLE 	4 4 -5	; "format"
	30	[87]	LOADK    	5 -7	; "Size.%s"
	31	[87]	MOVE     	6 1
	32	[87]	CALL     	4 3 2
	33	[88]	GETGLOBAL	5 -8	; error
	34	[88]	LOADK    	6 -9	; "Size: this property does not exist: "
	35	[88]	MOVE     	7 4
	36	[88]	CONCAT   	6 6 7
	37	[88]	CALL     	5 2 1
	38	[90]	GETGLOBAL	4 -10	; assert
	39	[90]	MOVE     	5 3
	40	[90]	CALL     	4 2 1
	41	[91]	RETURN   	2 2
	42	[92]	RETURN   	0 1
