-- BYTECODE -- skimtowidget.lua:82-82
0001    LEN      2   0
0002    LEN      3   1
0003    ISLT     3   2
0004    JMP      2 => 0007
0005    KPRI     2   1
0006    JMP      3 => 0008
0007 => KPRI     2   2
0008 => RET1     2   2

-- BYTECODE -- skimtowidget.lua:137-139
0001    UGET     0   0      ; self
0002    MOV      1   0
0003    TGETS    0   0   0  ; "goToPage"
0004    UGET     2   0      ; self
0005    TGETS    2   2   1  ; "curr_page"
0006    SUBVN    2   2   0  ; 1
0007    CALL     0   1   3
0008    RET0     0   1

-- BYTECODE -- skimtowidget.lua:149-151
0001    UGET     0   0      ; self
0002    MOV      1   0
0003    TGETS    0   0   0  ; "goToPage"
0004    UGET     2   0      ; self
0005    TGETS    2   2   1  ; "curr_page"
0006    SUBVN    2   2   0  ; 10
0007    CALL     0   1   3
0008    RET0     0   1

-- BYTECODE -- skimtowidget.lua:161-163
0001    UGET     0   0      ; self
0002    MOV      1   0
0003    TGETS    0   0   0  ; "goToPage"
0004    UGET     2   0      ; self
0005    TGETS    2   2   1  ; "curr_page"
0006    ADDVN    2   2   0  ; 1
0007    CALL     0   1   3
0008    RET0     0   1

-- BYTECODE -- skimtowidget.lua:173-175
0001    UGET     0   0      ; self
0002    MOV      1   0
0003    TGETS    0   0   0  ; "goToPage"
0004    UGET     2   0      ; self
0005    TGETS    2   2   1  ; "curr_page"
0006    ADDVN    2   2   0  ; 10
0007    CALL     0   1   3
0008    RET0     0   1

-- BYTECODE -- skimtowidget.lua:186-188
0001    UGET     0   0      ; self
0002    TGETS    0   0   0  ; "callback_switch_to_goto"
0003    CALL     0   1   1
0004    RET0     0   1

-- BYTECODE -- skimtowidget.lua:207-212
0001    UGET     0   0      ; self
0002    MOV      1   0
0003    TGETS    0   0   0  ; "getNextChapter"
0004    UGET     2   0      ; self
0005    TGETS    2   2   1  ; "curr_page"
0006    CALL     0   2   3
0007    ISF          0
0008    JMP      1 => 0021
0009    KSHORT   1   1
0010    ISGT     1   0
0011    JMP      1 => 0021
0012    UGET     1   0      ; self
0013    TGETS    1   1   2  ; "page_count"
0014    ISGT     0   1
0015    JMP      1 => 0021
0016    UGET     1   0      ; self
0017    MOV      2   1
0018    TGETS    1   1   3  ; "goToPage"
0019    MOV      3   0
0020    CALL     1   1   3
0021 => RET0     0   1

-- BYTECODE -- skimtowidget.lua:213-215
0001    UGET     0   0      ; self
0002    MOV      1   0
0003    TGETS    0   0   0  ; "goToPage"
0004    UGET     2   0      ; self
0005    TGETS    2   2   1  ; "page_count"
0006    CALL     0   1   3
0007    RET0     0   1

-- BYTECODE -- skimtowidget.lua:226-231
0001    UGET     0   0      ; self
0002    MOV      1   0
0003    TGETS    0   0   0  ; "getPrevChapter"
0004    UGET     2   0      ; self
0005    TGETS    2   2   1  ; "curr_page"
0006    CALL     0   2   3
0007    ISF          0
0008    JMP      1 => 0021
0009    KSHORT   1   1
0010    ISGT     1   0
0011    JMP      1 => 0021
0012    UGET     1   0      ; self
0013    TGETS    1   1   2  ; "page_count"
0014    ISGT     0   1
0015    JMP      1 => 0021
0016    UGET     1   0      ; self
0017    MOV      2   1
0018    TGETS    1   1   3  ; "goToPage"
0019    MOV      3   0
0020    CALL     1   1   3
0021 => RET0     0   1

-- BYTECODE -- skimtowidget.lua:232-234
0001    UGET     0   0      ; self
0002    MOV      1   0
0003    TGETS    0   0   0  ; "goToPage"
0004    KSHORT   2   1
0005    CALL     0   1   3
0006    RET0     0   1

-- BYTECODE -- skimtowidget.lua:245-247
0001    UGET     0   0      ; self
0002    TGETS    0   0   0  ; "ui"
0003    MOV      1   0
0004    TGETS    0   0   1  ; "handleEvent"
0005    UGET     2   1      ; Event
0006    MOV      3   2
0007    TGETS    2   2   2  ; "new"
0008    KSTR     4   3      ; "GotoNextBookmarkFromPage"
0009    CALL     2   0   3
0010    CALLM    0   1   1
0011    RET0     0   1

-- BYTECODE -- skimtowidget.lua:248-251
0001    UGET     0   0      ; self
0002    TGETS    0   0   0  ; "ui"
0003    TGETS    0   0   1  ; "bookmark"
0004    MOV      1   0
0005    TGETS    0   0   2  ; "getLastBookmarkedPageFromPage"
0006    UGET     2   0      ; self
0007    TGETS    2   2   0  ; "ui"
0008    MOV      3   2
0009    TGETS    2   2   3  ; "getCurrentPage"
0010    CALL     2   0   2
0011    CALLM    0   2   1
0012    UGET     1   0      ; self
0013    MOV      2   1
0014    TGETS    1   1   4  ; "goToBookmark"
0015    MOV      3   0
0016    CALL     1   1   3
0017    RET0     0   1

-- BYTECODE -- skimtowidget.lua:262-264
0001    UGET     0   0      ; self
0002    TGETS    0   0   0  ; "ui"
0003    MOV      1   0
0004    TGETS    0   0   1  ; "handleEvent"
0005    UGET     2   1      ; Event
0006    MOV      3   2
0007    TGETS    2   2   2  ; "new"
0008    KSTR     4   3      ; "GotoPreviousBookmarkFromPage"
0009    CALL     2   0   3
0010    CALLM    0   1   1
0011    RET0     0   1

-- BYTECODE -- skimtowidget.lua:265-268
0001    UGET     0   0      ; self
0002    TGETS    0   0   0  ; "ui"
0003    TGETS    0   0   1  ; "bookmark"
0004    MOV      1   0
0005    TGETS    0   0   2  ; "getFirstBookmarkedPageFromPage"
0006    UGET     2   0      ; self
0007    TGETS    2   2   0  ; "ui"
0008    MOV      3   2
0009    TGETS    2   2   3  ; "getCurrentPage"
0010    CALL     2   0   2
0011    CALLM    0   2   1
0012    UGET     1   0      ; self
0013    MOV      2   1
0014    TGETS    1   1   4  ; "goToBookmark"
0015    MOV      3   0
0016    CALL     1   1   3
0017    RET0     0   1

-- BYTECODE -- skimtowidget.lua:35-334
0001    UGET     1   0      ; Font
0002    MOV      2   1
0003    TGETS    1   1   1  ; "getFace"
0004    KSTR     3   2      ; "ffont"
0005    CALL     1   2   3
0006    TSETS    1   0   0  ; "medium_font_face"
0007    UGET     1   1      ; Screen
0008    MOV      2   1
0009    TGETS    1   1   4  ; "getWidth"
0010    CALL     1   2   2
0011    TSETS    1   0   3  ; "screen_width"
0012    UGET     1   1      ; Screen
0013    MOV      2   1
0014    TGETS    1   1   6  ; "getHeight"
0015    CALL     1   2   2
0016    TSETS    1   0   5  ; "screen_height"
0017    GGET     1   8      ; "math"
0018    TGETS    1   1   9  ; "ceil"
0019    TGETS    2   0   5  ; "screen_height"
0020    MULVN    2   2   0  ; 0.01
0021    CALL     1   2   2
0022    TSETS    1   0   7  ; "span"
0023    TGETS    1   0   3  ; "screen_width"
0024    MULVN    1   1   1  ; 0.95
0025    TSETS    1   0  10  ; "width"
0026    UGET     1   2      ; Size
0027    TGETS    1   1  12  ; "border"
0028    TGETS    1   1  13  ; "button"
0029    TSETS    1   0  11  ; "button_bordersize"
0030    TGETS    1   0  11  ; "button_bordersize"
0031    TSETS    1   0  14  ; "button_margin"
0032    TGETS    1   0   3  ; "screen_width"
0033    MULVN    1   1   2  ; 0.16
0034    TGETS    2   0  14  ; "button_margin"
0035    MULNV    2   2   3  ; 2
0036    SUBVV    1   1   2
0037    TSETS    1   0  15  ; "button_width"
0038    UGET     1   3      ; Device
0039    MOV      2   1
0040    TGETS    1   1  16  ; "hasKeys"
0041    CALL     1   2   2
0042    ISF          1
0043    JMP      2 => 0050
0044    TDUP     1  20
0045    TDUP     2  19
0046    TDUP     3  18
0047    TSETB    3   2   1
0048    TSETS    2   1  21  ; "Close"
0049    TSETS    1   0  17  ; "key_events"
0050 => UGET     1   3      ; Device
0051    MOV      2   1
0052    TGETS    1   1  22  ; "isTouchDevice"
0053    CALL     1   2   2
0054    ISF          1
0055    JMP      2 => 0076
0056    TDUP     1  30
0057    TNEW     2   3
0058    UGET     3   4      ; GestureRange
0059    MOV      4   3
0060    TGETS    3   3  24  ; "new"
0061    TDUP     5  25
0062    UGET     6   5      ; Geom
0063    MOV      7   6
0064    TGETS    6   6  24  ; "new"
0065    TDUP     8  26
0066    TGETS    9   0   3  ; "screen_width"
0067    TSETS    9   8  27  ; "w"
0068    TGETS    9   0   5  ; "screen_height"
0069    TSETS    9   8  28  ; "h"
0070    CALL     6   2   3
0071    TSETS    6   5  29  ; "range"
0072    CALL     3   0   3
0073    TSETM    3   4      ; 1
0074    TSETS    2   1  31  ; "TapProgress"
0075    TSETS    1   0  23  ; "ges_events"
0076 => UGET     1   6      ; _
0077    KSTR     2  32      ; "Skim"
0078    CALL     1   2   2
0079    TGETS    2   0  34  ; "ui"
0080    MOV      3   2
0081    TGETS    2   2  35  ; "getCurrentPage"
0082    CALL     2   2   2
0083    TSETS    2   0  33  ; "curr_page"
0084    TGETS    2   0  37  ; "document"
0085    MOV      3   2
0086    TGETS    2   2  38  ; "getPageCount"
0087    CALL     2   2   2
0088    TSETS    2   0  36  ; "page_count"
0089    GGET     2  39      ; "tostring"
0090    TGETS    3   0  33  ; "curr_page"
0091    CALL     2   2   2
0092    TGETS    3   0  34  ; "ui"
0093    TGETS    3   3  40  ; "pagemap"
0094    ISF          3
0095    JMP      4 => 0110
0096    TGETS    3   0  34  ; "ui"
0097    TGETS    3   3  40  ; "pagemap"
0098    MOV      4   3
0099    TGETS    3   3  41  ; "wantsPageLabels"
0100    CALL     3   2   2
0101    ISF          3
0102    JMP      4 => 0110
0103    TGETS    3   0  34  ; "ui"
0104    TGETS    3   3  40  ; "pagemap"
0105    MOV      4   3
0106    TGETS    3   3  42  ; "getCurrentPageLabel"
0107    KPRI     5   2
0108    CALL     3   2   3
0109    MOV      2   3
0110 => TNEW     3   0
0111    TGETS    4   0  34  ; "ui"
0112    TGETS    4   4  43  ; "toc"
0113    ISF          4
0114    JMP      5 => 0141
0115    TGETS    4   0  34  ; "ui"
0116    TGETS    4   4  43  ; "toc"
0117    MOV      5   4
0118    TGETS    4   4  44  ; "getMaxDepth"
0119    CALL     4   2   2
0120    KSHORT   5   0
0121    UNM      6   4
0122    KSHORT   7  -1
0123    FORI     5 => 0136
0124 => TGETS    9   0  34  ; "ui"
0125    TGETS    9   9  43  ; "toc"
0126    MOV     10   9
0127    TGETS    9   9  45  ; "getTocTicks"
0128    MOV     11   8
0129    CALL     9   2   3
0130    GGET    10  46      ; "table"
0131    TGETS   10  10  47  ; "insert"
0132    MOV     11   3
0133    MOV     12   9
0134    CALL    10   1   3
0135    FORL     5 => 0124
0136 => GGET     5  46      ; "table"
0137    TGETS    5   5  48  ; "sort"
0138    MOV      6   3
0139    FNEW     7  49      ; skimtowidget.lua:82
0140    CALL     5   1   3
0141 => LEN      4   3
0142    KSHORT   5   0
0143    ISGE     5   4
0144    JMP      4 => 0147
0145    TGETB    4   3   1
0146    TSETS    4   0  50  ; "ticks_candidates"
0147 => UGET     4   7      ; FrameContainer
0148    MOV      5   4
0149    TGETS    4   4  24  ; "new"
0150    TDUP     6  53
0151    UGET     7   2      ; Size
0152    TGETS    7   7  51  ; "padding"
0153    TGETS    7   7  52  ; "default"
0154    TSETS    7   6  51  ; "padding"
0155    UGET     7   2      ; Size
0156    TGETS    7   7  54  ; "margin"
0157    TGETS    7   7  55  ; "title"
0158    TSETS    7   6  54  ; "margin"
0159    UGET     7   8      ; TextWidget
0160    MOV      8   7
0161    TGETS    7   7  24  ; "new"
0162    TDUP     9  56
0163    TSETS    1   9  57  ; "text"
0164    TGETS   10   0  58  ; "title_face"
0165    TSETS   10   9  59  ; "face"
0166    TGETS   10   0   3  ; "screen_width"
0167    MULVN   10  10   1  ; 0.95
0168    TSETS   10   9  60  ; "max_width"
0169    CALL     7   0   3
0170    TSETM    7   4      ; 1
0171    CALL     4   2   3
0172    UGET     5   9      ; ProgressWidget
0173    MOV      6   5
0174    TGETS    5   5  24  ; "new"
0175    TDUP     7  62
0176    TGETS    8   0   3  ; "screen_width"
0177    MULVN    8   8   5  ; 0.9
0178    TSETS    8   7  10  ; "width"
0179    UGET     8   2      ; Size
0180    TGETS    8   8  63  ; "item"
0181    TGETS    8   8  64  ; "height_big"
0182    TSETS    8   7  65  ; "height"
0183    TGETS    8   0  33  ; "curr_page"
0184    TGETS    9   0  36  ; "page_count"
0185    DIVVV    8   8   9
0186    TSETS    8   7  66  ; "percentage"
0187    TGETS    8   0  50  ; "ticks_candidates"
0188    TSETS    8   7  67  ; "ticks"
0189    UGET     8   2      ; Size
0190    TGETS    8   8  68  ; "line"
0191    TGETS    8   8  69  ; "medium"
0192    TSETS    8   7  70  ; "tick_width"
0193    TGETS    8   0  36  ; "page_count"
0194    TSETS    8   7  71  ; "last"
0195    CALL     5   2   3
0196    TSETS    5   0  61  ; "progress_bar"
0197    UGET     5   7      ; FrameContainer
0198    MOV      6   5
0199    TGETS    5   5  24  ; "new"
0200    TDUP     7  73
0201    UGET     8   2      ; Size
0202    TGETS    8   8  51  ; "padding"
0203    TGETS    8   8  13  ; "button"
0204    TSETS    8   7  51  ; "padding"
0205    UGET     8   2      ; Size
0206    TGETS    8   8  54  ; "margin"
0207    TGETS    8   8  74  ; "small"
0208    TSETS    8   7  54  ; "margin"
0209    TGETS    8   0  61  ; "progress_bar"
0210    TSETB    8   7   1
0211    CALL     5   2   3
0212    TSETS    5   0  72  ; "skimto_progress"
0213    UGET     5  10      ; LineWidget
0214    MOV      6   5
0215    TGETS    5   5  24  ; "new"
0216    TDUP     7  77
0217    UGET     8   5      ; Geom
0218    MOV      9   8
0219    TGETS    8   8  24  ; "new"
0220    TDUP    10  75
0221    TGETS   11   0  10  ; "width"
0222    TSETS   11  10  27  ; "w"
0223    UGET    11   2      ; Size
0224    TGETS   11  11  68  ; "line"
0225    TGETS   11  11  76  ; "thick"
0226    TSETS   11  10  28  ; "h"
0227    CALL     8   2   3
0228    TSETS    8   7  78  ; "dimen"
0229    CALL     5   2   3
0230    UGET     6  11      ; OverlapGroup
0231    MOV      7   6
0232    TGETS    6   6  24  ; "new"
0233    TDUP     8  81
0234    TDUP     9  79
0235    TGETS   10   0  10  ; "width"
0236    TSETS   10   9  27  ; "w"
0237    MOV     11   4
0238    TGETS   10   4  80  ; "getSize"
0239    CALL    10   2   2
0240    TGETS   10  10  28  ; "h"
0241    TSETS   10   9  28  ; "h"
0242    TSETS    9   8  78  ; "dimen"
0243    TSETB    4   8   1
0244    UGET     9  12      ; CloseButton
0245    MOV     10   9
0246    TGETS    9   9  24  ; "new"
0247    TDUP    11  82
0248    TSETS    0  11  83  ; "window"
0249    UGET    12   2      ; Size
0250    TGETS   12  12  54  ; "margin"
0251    TGETS   12  12  55  ; "title"
0252    TSETS   12  11  84  ; "padding_top"
0253    CALL     9   0   3
0254    TSETM    9   6      ; 2
0255    CALL     6   2   3
0256    UGET     7  13      ; Button
0257    MOV      8   7
0258    TGETS    7   7  24  ; "new"
0259    TDUP     9  85
0260    TGETS   10   0  11  ; "button_bordersize"
0261    TSETS   10   9  86  ; "bordersize"
0262    TGETS   10   0  14  ; "button_margin"
0263    TSETS   10   9  54  ; "margin"
0264    TGETS   10   0  15  ; "button_width"
0265    TSETS   10   9  10  ; "width"
0266    TSETS    0   9  87  ; "show_parent"
0267    FNEW    10  88      ; skimtowidget.lua:137
0268    TSETS   10   9  89  ; "callback"
0269    CALL     7   2   3
0270    UGET     8  13      ; Button
0271    MOV      9   8
0272    TGETS    8   8  24  ; "new"
0273    TDUP    10  90
0274    TGETS   11   0  11  ; "button_bordersize"
0275    TSETS   11  10  86  ; "bordersize"
0276    TGETS   11   0  14  ; "button_margin"
0277    TSETS   11  10  54  ; "margin"
0278    TGETS   11   0  15  ; "button_width"
0279    TSETS   11  10  10  ; "width"
0280    TSETS    0  10  87  ; "show_parent"
0281    FNEW    11  91      ; skimtowidget.lua:149
0282    TSETS   11  10  89  ; "callback"
0283    CALL     8   2   3
0284    UGET     9  13      ; Button
0285    MOV     10   9
0286    TGETS    9   9  24  ; "new"
0287    TDUP    11  92
0288    TGETS   12   0  11  ; "button_bordersize"
0289    TSETS   12  11  86  ; "bordersize"
0290    TGETS   12   0  14  ; "button_margin"
0291    TSETS   12  11  54  ; "margin"
0292    TGETS   12   0  15  ; "button_width"
0293    TSETS   12  11  10  ; "width"
0294    TSETS    0  11  87  ; "show_parent"
0295    FNEW    12  93      ; skimtowidget.lua:161
0296    TSETS   12  11  89  ; "callback"
0297    CALL     9   2   3
0298    UGET    10  13      ; Button
0299    MOV     11  10
0300    TGETS   10  10  24  ; "new"
0301    TDUP    12  94
0302    TGETS   13   0  11  ; "button_bordersize"
0303    TSETS   13  12  86  ; "bordersize"
0304    TGETS   13   0  14  ; "button_margin"
0305    TSETS   13  12  54  ; "margin"
0306    TGETS   13   0  15  ; "button_width"
0307    TSETS   13  12  10  ; "width"
0308    TSETS    0  12  87  ; "show_parent"
0309    FNEW    13  95      ; skimtowidget.lua:173
0310    TSETS   13  12  89  ; "callback"
0311    CALL    10   2   3
0312    UGET    11  13      ; Button
0313    MOV     12  11
0314    TGETS   11  11  24  ; "new"
0315    TDUP    13  97
0316    TSETS    2  13  57  ; "text"
0317    TGETS   14   0  14  ; "button_margin"
0318    TSETS   14  13  54  ; "margin"
0319    TGETS   14   0   3  ; "screen_width"
0320    MULVN   14  14   7  ; 0.2
0321    TGETS   15   0  14  ; "button_margin"
0322    MULNV   15  15   3  ; 2
0323    SUBVV   14  14  15
0324    TSETS   14  13  10  ; "width"
0325    TSETS    0  13  87  ; "show_parent"
0326    FNEW    14  98      ; skimtowidget.lua:186
0327    TSETS   14  13  89  ; "callback"
0328    CALL    11   2   3
0329    TSETS   11   0  96  ; "current_page_text"
0330    KSTR    11  99      ; "▷│"
0331    KSTR    12 100      ; "│◁"
0332    KSTR    13 101      ; "☆▷"
0333    KSTR    14 102      ; "◁☆"
0334    UGET    15  14      ; BD
0335    TGETS   15  15 103  ; "mirroredUILayout"
0336    CALL    15   2   1
0337    ISF         15
0338    JMP     16 => 0345
0339    MOV     15  12
0340    MOV     12  11
0341    MOV     11  15
0342    MOV     15  14
0343    MOV     14  13
0344    MOV     13  15
0345 => UGET    15  13      ; Button
0346    MOV     16  15
0347    TGETS   15  15  24  ; "new"
0348    TDUP    17 104
0349    TSETS   11  17  57  ; "text"
0350    TGETS   18   0  11  ; "button_bordersize"
0351    TSETS   18  17  86  ; "bordersize"
0352    TGETS   18   0  14  ; "button_margin"
0353    TSETS   18  17  54  ; "margin"
0354    TGETS   18   0  15  ; "button_width"
0355    TSETS   18  17  10  ; "width"
0356    TSETS    0  17  87  ; "show_parent"
0357    FNEW    18 105      ; skimtowidget.lua:207
0358    TSETS   18  17  89  ; "callback"
0359    FNEW    18 106      ; skimtowidget.lua:213
0360    TSETS   18  17 107  ; "hold_callback"
0361    CALL    15   2   3
0362    UGET    16  13      ; Button
0363    MOV     17  16
0364    TGETS   16  16  24  ; "new"
0365    TDUP    18 108
0366    TSETS   12  18  57  ; "text"
0367    TGETS   19   0  11  ; "button_bordersize"
0368    TSETS   19  18  86  ; "bordersize"
0369    TGETS   19   0  14  ; "button_margin"
0370    TSETS   19  18  54  ; "margin"
0371    TGETS   19   0  15  ; "button_width"
0372    TSETS   19  18  10  ; "width"
0373    TSETS    0  18  87  ; "show_parent"
0374    FNEW    19 109      ; skimtowidget.lua:226
0375    TSETS   19  18  89  ; "callback"
0376    FNEW    19 110      ; skimtowidget.lua:232
0377    TSETS   19  18 107  ; "hold_callback"
0378    CALL    16   2   3
0379    UGET    17  13      ; Button
0380    MOV     18  17
0381    TGETS   17  17  24  ; "new"
0382    TDUP    19 111
0383    TSETS   13  19  57  ; "text"
0384    TGETS   20   0  11  ; "button_bordersize"
0385    TSETS   20  19  86  ; "bordersize"
0386    TGETS   20   0  14  ; "button_margin"
0387    TSETS   20  19  54  ; "margin"
0388    TGETS   20   0  15  ; "button_width"
0389    TSETS   20  19  10  ; "width"
0390    TSETS    0  19  87  ; "show_parent"
0391    FNEW    20 112      ; skimtowidget.lua:245
0392    TSETS   20  19  89  ; "callback"
0393    FNEW    20 113      ; skimtowidget.lua:248
0394    TSETS   20  19 107  ; "hold_callback"
0395    CALL    17   2   3
0396    UGET    18  13      ; Button
0397    MOV     19  18
0398    TGETS   18  18  24  ; "new"
0399    TDUP    20 114
0400    TSETS   14  20  57  ; "text"
0401    TGETS   21   0  11  ; "button_bordersize"
0402    TSETS   21  20  86  ; "bordersize"
0403    TGETS   21   0  14  ; "button_margin"
0404    TSETS   21  20  54  ; "margin"
0405    TGETS   21   0  15  ; "button_width"
0406    TSETS   21  20  10  ; "width"
0407    TSETS    0  20  87  ; "show_parent"
0408    FNEW    21 115      ; skimtowidget.lua:262
0409    TSETS   21  20  89  ; "callback"
0410    FNEW    21 116      ; skimtowidget.lua:265
0411    TSETS   21  20 107  ; "hold_callback"
0412    CALL    18   2   3
0413    UGET    19  16      ; HorizontalSpan
0414    MOV     20  19
0415    TGETS   19  19  24  ; "new"
0416    TDUP    21 117
0417    TGETS   22   0   3  ; "screen_width"
0418    MULVN   22  22   7  ; 0.2
0419    TSETS   22  21  10  ; "width"
0420    CALL    19   2   3
0421    UGET    20  17      ; HorizontalGroup
0422    MOV     21  20
0423    TGETS   20  20  24  ; "new"
0424    TDUP    22 118
0425    TSETB   16  22   1
0426    TSETB   18  22   2
0427    TSETB   19  22   3
0428    TSETB   17  22   4
0429    TSETB   15  22   5
0430    CALL    20   2   3
0431    UGET    21  18      ; VerticalGroup
0432    MOV     22  21
0433    TGETS   21  21  24  ; "new"
0434    TDUP    23 119
0435    CALL    21   2   3
0436    UGET    22  19      ; VerticalSpan
0437    MOV     23  22
0438    TGETS   22  22  24  ; "new"
0439    TDUP    24 120
0440    GGET    25   8      ; "math"
0441    TGETS   25  25   9  ; "ceil"
0442    TGETS   26   0   5  ; "screen_height"
0443    MULVN   26  26   8  ; 0.015
0444    CALL    25   2   2
0445    TSETS   25  24  10  ; "width"
0446    CALL    22   2   3
0447    GGET    23  46      ; "table"
0448    TGETS   23  23  47  ; "insert"
0449    MOV     24  21
0450    MOV     25  22
0451    CALL    23   1   3
0452    GGET    23  46      ; "table"
0453    TGETS   23  23  47  ; "insert"
0454    MOV     24  21
0455    MOV     25  20
0456    CALL    23   1   3
0457    GGET    23  46      ; "table"
0458    TGETS   23  23  47  ; "insert"
0459    MOV     24  21
0460    MOV     25  22
0461    CALL    23   1   3
0462    UGET    23  17      ; HorizontalGroup
0463    MOV     24  23
0464    TGETS   23  23  24  ; "new"
0465    TDUP    25 121
0466    TSETB    7  25   1
0467    TSETB    8  25   2
0468    TGETS   26   0  96  ; "current_page_text"
0469    TSETB   26  25   3
0470    TSETB   10  25   4
0471    TSETB    9  25   5
0472    CALL    23   2   3
0473    UGET    24  18      ; VerticalGroup
0474    MOV     25  24
0475    TGETS   24  24  24  ; "new"
0476    TDUP    26 122
0477    CALL    24   2   3
0478    UGET    25  19      ; VerticalSpan
0479    MOV     26  25
0480    TGETS   25  25  24  ; "new"
0481    TDUP    27 123
0482    GGET    28   8      ; "math"
0483    TGETS   28  28   9  ; "ceil"
0484    TGETS   29   0   5  ; "screen_height"
0485    MULVN   29  29   8  ; 0.015
0486    CALL    28   2   2
0487    TSETS   28  27  10  ; "width"
0488    CALL    25   2   3
0489    GGET    26  46      ; "table"
0490    TGETS   26  26  47  ; "insert"
0491    MOV     27  24
0492    MOV     28  25
0493    CALL    26   1   3
0494    GGET    26  46      ; "table"
0495    TGETS   26  26  47  ; "insert"
0496    MOV     27  24
0497    MOV     28  23
0498    CALL    26   1   3
0499    GGET    26  46      ; "table"
0500    TGETS   26  26  47  ; "insert"
0501    MOV     27  24
0502    MOV     28  25
0503    CALL    26   1   3
0504    UGET    26   7      ; FrameContainer
0505    MOV     27  26
0506    TGETS   26  26  24  ; "new"
0507    TDUP    28 126
0508    UGET    29   2      ; Size
0509    TGETS   29  29 125  ; "radius"
0510    TGETS   29  29  83  ; "window"
0511    TSETS   29  28 125  ; "radius"
0512    UGET    29   2      ; Size
0513    TGETS   29  29  12  ; "border"
0514    TGETS   29  29  83  ; "window"
0515    TSETS   29  28  86  ; "bordersize"
0516    UGET    29  20      ; Blitbuffer
0517    TGETS   29  29 127  ; "COLOR_WHITE"
0518    TSETS   29  28 128  ; "background"
0519    UGET    29  18      ; VerticalGroup
0520    MOV     30  29
0521    TGETS   29  29  24  ; "new"
0522    TDUP    31 129
0523    TSETB    6  31   1
0524    TSETB    5  31   2
0525    TSETB   21  31   3
0526    UGET    32  21      ; CenterContainer
0527    MOV     33  32
0528    TGETS   32  32  24  ; "new"
0529    TDUP    34 131
0530    UGET    35   5      ; Geom
0531    MOV     36  35
0532    TGETS   35  35  24  ; "new"
0533    TDUP    37 130
0534    MOV     39   5
0535    TGETS   38   5  80  ; "getSize"
0536    CALL    38   2   2
0537    TGETS   38  38  27  ; "w"
0538    TSETS   38  37  27  ; "w"
0539    TGETS   38   0  72  ; "skimto_progress"
0540    MOV     39  38
0541    TGETS   38  38  80  ; "getSize"
0542    CALL    38   2   2
0543    TGETS   38  38  28  ; "h"
0544    TSETS   38  37  28  ; "h"
0545    CALL    35   2   3
0546    TSETS   35  34  78  ; "dimen"
0547    TGETS   35   0  72  ; "skimto_progress"
0548    TSETB   35  34   1
0549    CALL    32   2   3
0550    TSETB   32  31   4
0551    TSETB   24  31   5
0552    CALL    29   0   3
0553    TSETM   29   4      ; 1
0554    CALL    26   2   3
0555    TSETS   26   0 124  ; "skimto_frame"
0556    UGET    26  22      ; WidgetContainer
0557    MOV     27  26
0558    TGETS   26  26  24  ; "new"
0559    TDUP    28 132
0560    UGET    29   5      ; Geom
0561    MOV     30  29
0562    TGETS   29  29  24  ; "new"
0563    TDUP    31 133
0564    TGETS   32   0   3  ; "screen_width"
0565    TSETS   32  31  27  ; "w"
0566    TGETS   32   0   5  ; "screen_height"
0567    TSETS   32  31  28  ; "h"
0568    CALL    29   2   3
0569    TSETS   29  28  78  ; "dimen"
0570    UGET    29  23      ; MovableContainer
0571    MOV     30  29
0572    TGETS   29  29  24  ; "new"
0573    TNEW    31   3
0574    TGETS   32   0 124  ; "skimto_frame"
0575    TSETB   32  31   1
0576    CALL    29   0   3
0577    TSETM   29   4      ; 1
0578    CALL    26   2   3
0579    TSETB   26   0   1
0580    UCLO     0 => 0581
0581 => RET0     0   1

-- BYTECODE -- skimtowidget.lua:336-349
0001    TGETS    1   0   0  ; "curr_page"
0002    KSHORT   2   0
0003    ISGT     1   2
0004    JMP      1 => 0007
0005    KSHORT   1   1
0006    TSETS    1   0   0  ; "curr_page"
0007 => TGETS    1   0   0  ; "curr_page"
0008    TGETS    2   0   1  ; "page_count"
0009    ISGE     2   1
0010    JMP      1 => 0013
0011    TGETS    1   0   1  ; "page_count"
0012    TSETS    1   0   0  ; "curr_page"
0013 => TGETS    1   0   2  ; "progress_bar"
0014    TGETS    2   0   0  ; "curr_page"
0015    TGETS    3   0   1  ; "page_count"
0016    DIVVV    2   2   3
0017    TSETS    2   1   3  ; "percentage"
0018    GGET     1   4      ; "tostring"
0019    TGETS    2   0   0  ; "curr_page"
0020    CALL     1   2   2
0021    TGETS    2   0   5  ; "ui"
0022    TGETS    2   2   6  ; "pagemap"
0023    ISF          2
0024    JMP      3 => 0039
0025    TGETS    2   0   5  ; "ui"
0026    TGETS    2   2   6  ; "pagemap"
0027    MOV      3   2
0028    TGETS    2   2   7  ; "wantsPageLabels"
0029    CALL     2   2   2
0030    ISF          2
0031    JMP      3 => 0039
0032    TGETS    2   0   5  ; "ui"
0033    TGETS    2   2   6  ; "pagemap"
0034    MOV      3   2
0035    TGETS    2   2   8  ; "getCurrentPageLabel"
0036    KPRI     4   2
0037    CALL     2   2   3
0038    MOV      1   2
0039 => TGETS    2   0   9  ; "current_page_text"
0040    MOV      3   2
0041    TGETS    2   2  10  ; "setText"
0042    MOV      4   1
0043    TGETS    5   0   9  ; "current_page_text"
0044    TGETS    5   5  11  ; "width"
0045    CALL     2   1   4
0046    RET0     0   1

-- BYTECODE -- skimtowidget.lua:351-358
0001    TGETS    2   0   0  ; "orig_page_added_to_stack"
0002    ISF          2
0003    JMP      2 => 0006
0004    ISF          1
0005    JMP      2 => 0013
0006 => TGETS    2   0   1  ; "ui"
0007    TGETS    2   2   2  ; "link"
0008    MOV      3   2
0009    TGETS    2   2   3  ; "addCurrentLocationToStack"
0010    CALL     2   1   2
0011    KPRI     2   2
0012    TSETS    2   0   0  ; "orig_page_added_to_stack"
0013 => RET0     0   1

-- BYTECODE -- skimtowidget.lua:360-369
0001    KPRI     2   0
0002    KSHORT   3   1
0003    TGETS    4   0   0  ; "ticks_candidates"
0004    LEN      4   4
0005    KSHORT   5   1
0006    FORI     3 => 0015
0007 => TGETS    7   0   0  ; "ticks_candidates"
0008    TGETV    7   7   6
0009    ISGE     1   7
0010    JMP      7 => 0014
0011    TGETS    7   0   0  ; "ticks_candidates"
0012    TGETV    2   7   6
0013    JMP      3 => 0015
0014 => FORL     3 => 0007
0015 => RET1     2   2

-- BYTECODE -- skimtowidget.lua:371-380
0001    KPRI     2   0
0002    KSHORT   3   1
0003    TGETS    4   0   0  ; "ticks_candidates"
0004    LEN      4   4
0005    KSHORT   5   1
0006    FORI     3 => 0015
0007 => TGETS    7   0   0  ; "ticks_candidates"
0008    TGETV    7   7   6
0009    ISGT     1   7
0010    JMP      7 => 0012
0011    JMP      3 => 0015
0012 => TGETS    7   0   0  ; "ticks_candidates"
0013    TGETV    2   7   6
0014    FORL     3 => 0007
0015 => RET1     2   2

-- BYTECODE -- skimtowidget.lua:383-385
0001    KSTR     0   0      ; "ui"
0002    UGET     1   0      ; self
0003    TGETS    1   1   1  ; "skimto_frame"
0004    TGETS    1   1   2  ; "dimen"
0005    RET      0   3

-- BYTECODE -- skimtowidget.lua:382-387
0001    UGET     1   0      ; UIManager
0002    MOV      2   1
0003    TGETS    1   1   0  ; "setDirty"
0004    KPRI     3   0
0005    FNEW     4   1      ; skimtowidget.lua:383
0006    CALL     1   1   4
0007    KPRI     1   2
0008    UCLO     0 => 0009
0009 => RET1     1   2

-- BYTECODE -- skimtowidget.lua:390-392
0001    KSTR     0   0      ; "ui"
0002    UGET     1   0      ; self
0003    TGETS    1   1   1  ; "skimto_frame"
0004    TGETS    1   1   2  ; "dimen"
0005    RET      0   3

-- BYTECODE -- skimtowidget.lua:389-394
0001    UGET     1   0      ; UIManager
0002    MOV      2   1
0003    TGETS    1   1   0  ; "setDirty"
0004    MOV      3   0
0005    FNEW     4   1      ; skimtowidget.lua:390
0006    CALL     1   1   4
0007    KPRI     1   2
0008    UCLO     0 => 0009
0009 => RET1     1   2

-- BYTECODE -- skimtowidget.lua:396-401
0001    TSETS    1   0   0  ; "curr_page"
0002    MOV      3   0
0003    TGETS    2   0   1  ; "addOriginToLocationStack"
0004    CALL     2   1   2
0005    TGETS    2   0   2  ; "ui"
0006    MOV      3   2
0007    TGETS    2   2   3  ; "handleEvent"
0008    UGET     4   0      ; Event
0009    MOV      5   4
0010    TGETS    4   4   4  ; "new"
0011    KSTR     6   5      ; "GotoPage"
0012    TGETS    7   0   0  ; "curr_page"
0013    CALL     4   0   4
0014    CALLM    2   1   1
0015    MOV      3   0
0016    TGETS    2   0   6  ; "update"
0017    CALL     2   1   2
0018    RET0     0   1

-- BYTECODE -- skimtowidget.lua:403-410
0001    ISF          1
0002    JMP      2 => 0020
0003    MOV      3   0
0004    TGETS    2   0   0  ; "addOriginToLocationStack"
0005    CALL     2   1   2
0006    TGETS    2   0   1  ; "ui"
0007    TGETS    2   2   2  ; "bookmark"
0008    MOV      3   2
0009    TGETS    2   2   3  ; "gotoBookmark"
0010    MOV      4   1
0011    CALL     2   1   3
0012    TGETS    2   0   1  ; "ui"
0013    MOV      3   2
0014    TGETS    2   2   5  ; "getCurrentPage"
0015    CALL     2   2   2
0016    TSETS    2   0   4  ; "curr_page"
0017    MOV      3   0
0018    TGETS    2   0   6  ; "update"
0019    CALL     2   1   2
0020 => RET0     0   1

-- BYTECODE -- skimtowidget.lua:412-415
0001    UGET     1   0      ; UIManager
0002    MOV      2   1
0003    TGETS    1   1   0  ; "close"
0004    MOV      3   0
0005    CALL     1   1   3
0006    KPRI     1   2
0007    RET1     1   2

-- BYTECODE -- skimtowidget.lua:417-434
0001    TGETS    3   2   0  ; "pos"
0002    MOV      4   3
0003    TGETS    3   3   1  ; "intersectWith"
0004    TGETS    5   0   2  ; "progress_bar"
0005    TGETS    5   5   3  ; "dimen"
0006    CALL     3   2   3
0007    ISF          3
0008    JMP      4 => 0041
0009    TGETS    3   0   2  ; "progress_bar"
0010    MOV      4   3
0011    TGETS    3   3   4  ; "getPercentageFromPosition"
0012    TGETS    5   2   0  ; "pos"
0013    CALL     3   2   3
0014    IST          3
0015    JMP      4 => 0018
0016    KPRI     4   2
0017    RET1     4   2
0018 => UGET     4   0      ; Math
0019    TGETS    4   4   5  ; "round"
0020    TGETS    5   0   6  ; "page_count"
0021    MULVV    5   3   5
0022    CALL     4   2   2
0023    MOV      6   0
0024    TGETS    5   0   7  ; "addOriginToLocationStack"
0025    CALL     5   1   2
0026    TGETS    5   0   8  ; "ui"
0027    MOV      6   5
0028    TGETS    5   5   9  ; "handleEvent"
0029    UGET     7   1      ; Event
0030    MOV      8   7
0031    TGETS    7   7  10  ; "new"
0032    KSTR     9  11      ; "GotoPage"
0033    MOV     10   4
0034    CALL     7   0   4
0035    CALLM    5   1   1
0036    TSETS    4   0  12  ; "curr_page"
0037    MOV      6   0
0038    TGETS    5   0  13  ; "update"
0039    CALL     5   1   2
0040    JMP      3 => 0052
0041 => TGETS    3   2   0  ; "pos"
0042    MOV      4   3
0043    TGETS    3   3   1  ; "intersectWith"
0044    TGETS    5   0  14  ; "skimto_frame"
0045    TGETS    5   5   3  ; "dimen"
0046    CALL     3   2   3
0047    IST          3
0048    JMP      3 => 0052
0049    MOV      4   0
0050    TGETS    3   0  15  ; "onClose"
0051    CALL     3   1   2
0052 => KPRI     3   2
0053    RET1     3   2

-- BYTECODE -- skimtowidget.lua:436-439
0001    UGET     1   0      ; UIManager
0002    MOV      2   1
0003    TGETS    1   1   0  ; "close"
0004    MOV      3   0
0005    CALL     1   1   3
0006    KPRI     1   2
0007    RET1     1   2

-- BYTECODE -- skimtowidget.lua:0-442
0001    GGET     0   0      ; "require"
0002    KSTR     1   1      ; "ui/bidi"
0003    CALL     0   2   2
0004    GGET     1   0      ; "require"
0005    KSTR     2   2      ; "ffi/blitbuffer"
0006    CALL     1   2   2
0007    GGET     2   0      ; "require"
0008    KSTR     3   3      ; "ui/widget/button"
0009    CALL     2   2   2
0010    GGET     3   0      ; "require"
0011    KSTR     4   4      ; "ui/widget/container/centercontainer"
0012    CALL     3   2   2
0013    GGET     4   0      ; "require"
0014    KSTR     5   5      ; "ui/widget/closebutton"
0015    CALL     4   2   2
0016    GGET     5   0      ; "require"
0017    KSTR     6   6      ; "device"
0018    CALL     5   2   2
0019    GGET     6   0      ; "require"
0020    KSTR     7   7      ; "ui/event"
0021    CALL     6   2   2
0022    GGET     7   0      ; "require"
0023    KSTR     8   8      ; "ui/font"
0024    CALL     7   2   2
0025    GGET     8   0      ; "require"
0026    KSTR     9   9      ; "ui/widget/container/framecontainer"
0027    CALL     8   2   2
0028    GGET     9   0      ; "require"
0029    KSTR    10  10      ; "ui/geometry"
0030    CALL     9   2   2
0031    GGET    10   0      ; "require"
0032    KSTR    11  11      ; "ui/gesturerange"
0033    CALL    10   2   2
0034    GGET    11   0      ; "require"
0035    KSTR    12  12      ; "ui/widget/horizontalgroup"
0036    CALL    11   2   2
0037    GGET    12   0      ; "require"
0038    KSTR    13  13      ; "ui/widget/horizontalspan"
0039    CALL    12   2   2
0040    GGET    13   0      ; "require"
0041    KSTR    14  14      ; "ui/widget/container/inputcontainer"
0042    CALL    13   2   2
0043    GGET    14   0      ; "require"
0044    KSTR    15  15      ; "ui/widget/linewidget"
0045    CALL    14   2   2
0046    GGET    15   0      ; "require"
0047    KSTR    16  16      ; "optmath"
0048    CALL    15   2   2
0049    GGET    16   0      ; "require"
0050    KSTR    17  17      ; "ui/widget/container/movablecontainer"
0051    CALL    16   2   2
0052    GGET    17   0      ; "require"
0053    KSTR    18  18      ; "ui/widget/overlapgroup"
0054    CALL    17   2   2
0055    GGET    18   0      ; "require"
0056    KSTR    19  19      ; "ui/widget/progresswidget"
0057    CALL    18   2   2
0058    GGET    19   0      ; "require"
0059    KSTR    20  20      ; "ui/size"
0060    CALL    19   2   2
0061    GGET    20   0      ; "require"
0062    KSTR    21  21      ; "ui/widget/textwidget"
0063    CALL    20   2   2
0064    GGET    21   0      ; "require"
0065    KSTR    22  22      ; "ui/uimanager"
0066    CALL    21   2   2
0067    GGET    22   0      ; "require"
0068    KSTR    23  23      ; "ui/widget/verticalgroup"
0069    CALL    22   2   2
0070    GGET    23   0      ; "require"
0071    KSTR    24  24      ; "ui/widget/verticalspan"
0072    CALL    23   2   2
0073    GGET    24   0      ; "require"
0074    KSTR    25  25      ; "ui/widget/container/widgetcontainer"
0075    CALL    24   2   2
0076    GGET    25   0      ; "require"
0077    KSTR    26  26      ; "gettext"
0078    CALL    25   2   2
0079    TGETS   26   5  27  ; "screen"
0080    MOV     28  13
0081    TGETS   27  13  28  ; "new"
0082    TDUP    29  31
0083    MOV     31   7
0084    TGETS   30   7  29  ; "getFace"
0085    KSTR    32  30      ; "x_smalltfont"
0086    CALL    30   2   3
0087    TSETS   30  29  32  ; "title_face"
0088    CALL    27   2   3
0089    FNEW    28  34      ; skimtowidget.lua:35
0090    TSETS   28  27  33  ; "init"
0091    FNEW    28  36      ; skimtowidget.lua:336
0092    TSETS   28  27  35  ; "update"
0093    FNEW    28  38      ; skimtowidget.lua:351
0094    TSETS   28  27  37  ; "addOriginToLocationStack"
0095    FNEW    28  40      ; skimtowidget.lua:360
0096    TSETS   28  27  39  ; "getNextChapter"
0097    FNEW    28  42      ; skimtowidget.lua:371
0098    TSETS   28  27  41  ; "getPrevChapter"
0099    FNEW    28  44      ; skimtowidget.lua:382
0100    TSETS   28  27  43  ; "onCloseWidget"
0101    FNEW    28  46      ; skimtowidget.lua:389
0102    TSETS   28  27  45  ; "onShow"
0103    FNEW    28  48      ; skimtowidget.lua:396
0104    TSETS   28  27  47  ; "goToPage"
0105    FNEW    28  50      ; skimtowidget.lua:403
0106    TSETS   28  27  49  ; "goToBookmark"
0107    FNEW    28  52      ; skimtowidget.lua:412
0108    TSETS   28  27  51  ; "onAnyKeyPressed"
0109    FNEW    28  54      ; skimtowidget.lua:417
0110    TSETS   28  27  53  ; "onTapProgress"
0111    FNEW    28  56      ; skimtowidget.lua:436
0112    TSETS   28  27  55  ; "onClose"
0113    UCLO     0 => 0114
0114 => RET1    27   2

