
main <./frontend/apps/reader/skimtowidget.lua:0,0> (145 instructions, 580 bytes at 0x7fa7b2c068e0)
0+ params, 33 slots, 0 upvalues, 28 locals, 47 constants, 12 functions
	1	[1]	GETGLOBAL	0 -1	; require
	2	[1]	LOADK    	1 -2	; "ui/bidi"
	3	[1]	CALL     	0 2 2
	4	[2]	GETGLOBAL	1 -1	; require
	5	[2]	LOADK    	2 -3	; "ffi/blitbuffer"
	6	[2]	CALL     	1 2 2
	7	[3]	GETGLOBAL	2 -1	; require
	8	[3]	LOADK    	3 -4	; "ui/widget/button"
	9	[3]	CALL     	2 2 2
	10	[4]	GETGLOBAL	3 -1	; require
	11	[4]	LOADK    	4 -5	; "ui/widget/container/centercontainer"
	12	[4]	CALL     	3 2 2
	13	[5]	GETGLOBAL	4 -1	; require
	14	[5]	LOADK    	5 -6	; "ui/widget/closebutton"
	15	[5]	CALL     	4 2 2
	16	[6]	GETGLOBAL	5 -1	; require
	17	[6]	LOADK    	6 -7	; "device"
	18	[6]	CALL     	5 2 2
	19	[7]	GETGLOBAL	6 -1	; require
	20	[7]	LOADK    	7 -8	; "ui/event"
	21	[7]	CALL     	6 2 2
	22	[8]	GETGLOBAL	7 -1	; require
	23	[8]	LOADK    	8 -9	; "ui/font"
	24	[8]	CALL     	7 2 2
	25	[9]	GETGLOBAL	8 -1	; require
	26	[9]	LOADK    	9 -10	; "ui/widget/container/framecontainer"
	27	[9]	CALL     	8 2 2
	28	[10]	GETGLOBAL	9 -1	; require
	29	[10]	LOADK    	10 -11	; "ui/geometry"
	30	[10]	CALL     	9 2 2
	31	[11]	GETGLOBAL	10 -1	; require
	32	[11]	LOADK    	11 -12	; "ui/gesturerange"
	33	[11]	CALL     	10 2 2
	34	[12]	GETGLOBAL	11 -1	; require
	35	[12]	LOADK    	12 -13	; "ui/widget/horizontalgroup"
	36	[12]	CALL     	11 2 2
	37	[13]	GETGLOBAL	12 -1	; require
	38	[13]	LOADK    	13 -14	; "ui/widget/horizontalspan"
	39	[13]	CALL     	12 2 2
	40	[14]	GETGLOBAL	13 -1	; require
	41	[14]	LOADK    	14 -15	; "ui/widget/container/inputcontainer"
	42	[14]	CALL     	13 2 2
	43	[15]	GETGLOBAL	14 -1	; require
	44	[15]	LOADK    	15 -16	; "ui/widget/linewidget"
	45	[15]	CALL     	14 2 2
	46	[16]	GETGLOBAL	15 -1	; require
	47	[16]	LOADK    	16 -17	; "optmath"
	48	[16]	CALL     	15 2 2
	49	[17]	GETGLOBAL	16 -1	; require
	50	[17]	LOADK    	17 -18	; "ui/widget/container/movablecontainer"
	51	[17]	CALL     	16 2 2
	52	[18]	GETGLOBAL	17 -1	; require
	53	[18]	LOADK    	18 -19	; "ui/widget/overlapgroup"
	54	[18]	CALL     	17 2 2
	55	[19]	GETGLOBAL	18 -1	; require
	56	[19]	LOADK    	19 -20	; "ui/widget/progresswidget"
	57	[19]	CALL     	18 2 2
	58	[20]	GETGLOBAL	19 -1	; require
	59	[20]	LOADK    	20 -21	; "ui/size"
	60	[20]	CALL     	19 2 2
	61	[21]	GETGLOBAL	20 -1	; require
	62	[21]	LOADK    	21 -22	; "ui/widget/textwidget"
	63	[21]	CALL     	20 2 2
	64	[22]	GETGLOBAL	21 -1	; require
	65	[22]	LOADK    	22 -23	; "ui/uimanager"
	66	[22]	CALL     	21 2 2
	67	[23]	GETGLOBAL	22 -1	; require
	68	[23]	LOADK    	23 -24	; "ui/widget/verticalgroup"
	69	[23]	CALL     	22 2 2
	70	[24]	GETGLOBAL	23 -1	; require
	71	[24]	LOADK    	24 -25	; "ui/widget/verticalspan"
	72	[24]	CALL     	23 2 2
	73	[25]	GETGLOBAL	24 -1	; require
	74	[25]	LOADK    	25 -26	; "ui/widget/container/widgetcontainer"
	75	[25]	CALL     	24 2 2
	76	[26]	GETGLOBAL	25 -1	; require
	77	[26]	LOADK    	26 -27	; "gettext"
	78	[26]	CALL     	25 2 2
	79	[27]	GETTABLE 	26 5 -28	; "screen"
	80	[29]	SELF     	27 13 -29	; "new"
	81	[29]	NEWTABLE 	29 0 3
	82	[30]	SELF     	30 7 -31	; "getFace"
	83	[30]	LOADK    	32 -32	; "x_smalltfont"
	84	[30]	CALL     	30 3 2
	85	[30]	SETTABLE 	29 -30 30	; "title_face" -
	86	[31]	SETTABLE 	29 -33 -34	; "width" nil
	87	[32]	SETTABLE 	29 -35 -34	; "height" nil
	88	[29]	CALL     	27 3 2
	89	[334]	CLOSURE  	28 0	; 0x7fa7b2c07080
	90	[334]	MOVE     	0 7
	91	[334]	MOVE     	0 26
	92	[334]	MOVE     	0 19
	93	[334]	MOVE     	0 5
	94	[334]	MOVE     	0 10
	95	[334]	MOVE     	0 9
	96	[334]	MOVE     	0 25
	97	[334]	MOVE     	0 8
	98	[334]	MOVE     	0 20
	99	[334]	MOVE     	0 18
	100	[334]	MOVE     	0 14
	101	[334]	MOVE     	0 17
	102	[334]	MOVE     	0 4
	103	[334]	MOVE     	0 2
	104	[334]	MOVE     	0 0
	105	[334]	MOVE     	0 6
	106	[334]	MOVE     	0 12
	107	[334]	MOVE     	0 11
	108	[334]	MOVE     	0 22
	109	[334]	MOVE     	0 23
	110	[334]	MOVE     	0 1
	111	[334]	MOVE     	0 3
	112	[334]	MOVE     	0 24
	113	[334]	MOVE     	0 16
	114	[35]	SETTABLE 	27 -36 28	; "init" -
	115	[349]	CLOSURE  	28 1	; 0x7fa7b2c084f0
	116	[336]	SETTABLE 	27 -37 28	; "update" -
	117	[358]	CLOSURE  	28 2	; 0x7fa7b2c0ba60
	118	[351]	SETTABLE 	27 -38 28	; "addOriginToLocationStack" -
	119	[369]	CLOSURE  	28 3	; 0x7fa7b2c0bfb0
	120	[360]	SETTABLE 	27 -39 28	; "getNextChapter" -
	121	[380]	CLOSURE  	28 4	; 0x7fa7b2c0c430
	122	[371]	SETTABLE 	27 -40 28	; "getPrevChapter" -
	123	[387]	CLOSURE  	28 5	; 0x7fa7b2c0ca60
	124	[387]	MOVE     	0 21
	125	[382]	SETTABLE 	27 -41 28	; "onCloseWidget" -
	126	[394]	CLOSURE  	28 6	; 0x7fa7b2c0c800
	127	[394]	MOVE     	0 21
	128	[389]	SETTABLE 	27 -42 28	; "onShow" -
	129	[401]	CLOSURE  	28 7	; 0x7fa7b2c0d290
	130	[401]	MOVE     	0 6
	131	[396]	SETTABLE 	27 -43 28	; "goToPage" -
	132	[410]	CLOSURE  	28 8	; 0x7fa7b2c0d440
	133	[403]	SETTABLE 	27 -44 28	; "goToBookmark" -
	134	[415]	CLOSURE  	28 9	; 0x7fa7b2c077e0
	135	[415]	MOVE     	0 21
	136	[412]	SETTABLE 	27 -45 28	; "onAnyKeyPressed" -
	137	[434]	CLOSURE  	28 10	; 0x7fa7b2c07870
	138	[434]	MOVE     	0 15
	139	[434]	MOVE     	0 6
	140	[417]	SETTABLE 	27 -46 28	; "onTapProgress" -
	141	[439]	CLOSURE  	28 11	; 0x7fa7b2c0de00
	142	[439]	MOVE     	0 21
	143	[436]	SETTABLE 	27 -47 28	; "onClose" -
	144	[441]	RETURN   	27 2
	145	[441]	RETURN   	0 1

function <./frontend/apps/reader/skimtowidget.lua:35,334> (591 instructions, 2364 bytes at 0x7fa7b2c07080)
1 param, 43 slots, 24 upvalues, 32 locals, 109 constants, 14 functions
	1	[36]	GETUPVAL 	1 0	; Font
	2	[36]	SELF     	1 1 -2	; "getFace"
	3	[36]	LOADK    	3 -3	; "ffont"
	4	[36]	CALL     	1 3 2
	5	[36]	SETTABLE 	0 -1 1	; "medium_font_face" -
	6	[37]	GETUPVAL 	1 1	; Screen
	7	[37]	SELF     	1 1 -5	; "getWidth"
	8	[37]	CALL     	1 2 2
	9	[37]	SETTABLE 	0 -4 1	; "screen_width" -
	10	[38]	GETUPVAL 	1 1	; Screen
	11	[38]	SELF     	1 1 -7	; "getHeight"
	12	[38]	CALL     	1 2 2
	13	[38]	SETTABLE 	0 -6 1	; "screen_height" -
	14	[39]	GETGLOBAL	1 -9	; math
	15	[39]	GETTABLE 	1 1 -10	; "ceil"
	16	[39]	GETTABLE 	2 0 -6	; "screen_height"
	17	[39]	MUL      	2 2 -11	; - 0.01
	18	[39]	CALL     	1 2 2
	19	[39]	SETTABLE 	0 -8 1	; "span" -
	20	[40]	GETTABLE 	1 0 -4	; "screen_width"
	21	[40]	MUL      	1 1 -13	; - 0.95
	22	[40]	SETTABLE 	0 -12 1	; "width" -
	23	[41]	GETUPVAL 	1 2	; Size
	24	[41]	GETTABLE 	1 1 -15	; "border"
	25	[41]	GETTABLE 	1 1 -16	; "button"
	26	[41]	SETTABLE 	0 -14 1	; "button_bordersize" -
	27	[44]	GETTABLE 	1 0 -14	; "button_bordersize"
	28	[44]	SETTABLE 	0 -17 1	; "button_margin" -
	29	[45]	GETTABLE 	1 0 -4	; "screen_width"
	30	[45]	MUL      	1 1 -19	; - 0.16
	31	[45]	GETTABLE 	2 0 -17	; "button_margin"
	32	[45]	MUL      	2 -20 2	; 2 -
	33	[45]	SUB      	1 1 2
	34	[45]	SETTABLE 	0 -18 1	; "button_width" -
	35	[46]	GETUPVAL 	1 3	; Device
	36	[46]	SELF     	1 1 -21	; "hasKeys"
	37	[46]	CALL     	1 2 2
	38	[46]	TEST     	1 0 0
	39	[46]	JMP      	9	; to 49
	40	[47]	NEWTABLE 	1 0 1
	41	[48]	NEWTABLE 	2 1 1
	42	[48]	NEWTABLE 	3 1 0
	43	[48]	LOADK    	4 -24	; "Back"
	44	[48]	SETLIST  	3 1 1	; 1
	45	[48]	SETTABLE 	2 -25 -26	; "doc" "close skimto page"
	46	[48]	SETLIST  	2 1 1	; 1
	47	[48]	SETTABLE 	1 -23 2	; "Close" -
	48	[49]	SETTABLE 	0 -22 1	; "key_events" -
	49	[51]	GETUPVAL 	1 3	; Device
	50	[51]	SELF     	1 1 -27	; "isTouchDevice"
	51	[51]	CALL     	1 2 2
	52	[51]	TEST     	1 0 0
	53	[51]	JMP      	21	; to 75
	54	[52]	NEWTABLE 	1 0 1
	55	[53]	NEWTABLE 	2 0 0
	56	[54]	GETUPVAL 	3 4	; GestureRange
	57	[54]	SELF     	3 3 -30	; "new"
	58	[54]	NEWTABLE 	5 0 2
	59	[55]	SETTABLE 	5 -31 -32	; "ges" "tap"
	60	[56]	GETUPVAL 	6 5	; Geom
	61	[56]	SELF     	6 6 -30	; "new"
	62	[56]	NEWTABLE 	8 0 4
	63	[57]	SETTABLE 	8 -34 -35	; "x" 0
	64	[57]	SETTABLE 	8 -36 -35	; "y" 0
	65	[58]	GETTABLE 	9 0 -4	; "screen_width"
	66	[58]	SETTABLE 	8 -37 9	; "w" -
	67	[59]	GETTABLE 	9 0 -6	; "screen_height"
	68	[59]	SETTABLE 	8 -38 9	; "h" -
	69	[56]	CALL     	6 3 2
	70	[60]	SETTABLE 	5 -33 6	; "range" -
	71	[54]	CALL     	3 3 0
	72	[62]	SETLIST  	2 0 1	; 1
	73	[62]	SETTABLE 	1 -29 2	; "TapProgress" -
	74	[63]	SETTABLE 	0 -28 1	; "ges_events" -
	75	[65]	GETUPVAL 	1 6	; _
	76	[65]	LOADK    	2 -39	; "Skim"
	77	[65]	CALL     	1 2 2
	78	[66]	GETTABLE 	2 0 -41	; "ui"
	79	[66]	SELF     	2 2 -42	; "getCurrentPage"
	80	[66]	CALL     	2 2 2
	81	[66]	SETTABLE 	0 -40 2	; "curr_page" -
	82	[67]	GETTABLE 	2 0 -44	; "document"
	83	[67]	SELF     	2 2 -45	; "getPageCount"
	84	[67]	CALL     	2 2 2
	85	[67]	SETTABLE 	0 -43 2	; "page_count" -
	86	[69]	GETGLOBAL	2 -46	; tostring
	87	[69]	GETTABLE 	3 0 -40	; "curr_page"
	88	[69]	CALL     	2 2 2
	89	[70]	GETTABLE 	3 0 -41	; "ui"
	90	[70]	GETTABLE 	3 3 -47	; "pagemap"
	91	[70]	TEST     	3 0 0
	92	[70]	JMP      	12	; to 105
	93	[70]	GETTABLE 	3 0 -41	; "ui"
	94	[70]	GETTABLE 	3 3 -47	; "pagemap"
	95	[70]	SELF     	3 3 -48	; "wantsPageLabels"
	96	[70]	CALL     	3 2 2
	97	[70]	TEST     	3 0 0
	98	[70]	JMP      	6	; to 105
	99	[71]	GETTABLE 	3 0 -41	; "ui"
	100	[71]	GETTABLE 	3 3 -47	; "pagemap"
	101	[71]	SELF     	3 3 -49	; "getCurrentPageLabel"
	102	[71]	LOADBOOL 	5 1 0
	103	[71]	CALL     	3 3 2
	104	[71]	MOVE     	2 3
	105	[74]	NEWTABLE 	3 0 0
	106	[75]	GETTABLE 	4 0 -41	; "ui"
	107	[75]	GETTABLE 	4 4 -50	; "toc"
	108	[75]	TEST     	4 0 0
	109	[75]	JMP      	24	; to 134
	110	[76]	GETTABLE 	4 0 -41	; "ui"
	111	[76]	GETTABLE 	4 4 -50	; "toc"
	112	[76]	SELF     	4 4 -51	; "getMaxDepth"
	113	[76]	CALL     	4 2 2
	114	[77]	LOADK    	5 -35	; 0
	115	[77]	UNM      	6 4
	116	[77]	LOADK    	7 -52	; -1
	117	[77]	FORPREP  	5 10	; to 128
	118	[78]	GETTABLE 	9 0 -41	; "ui"
	119	[78]	GETTABLE 	9 9 -50	; "toc"
	120	[78]	SELF     	9 9 -53	; "getTocTicks"
	121	[78]	MOVE     	11 8
	122	[78]	CALL     	9 3 2
	123	[79]	GETGLOBAL	10 -54	; table
	124	[79]	GETTABLE 	10 10 -55	; "insert"
	125	[79]	MOVE     	11 3
	126	[79]	MOVE     	12 9
	127	[79]	CALL     	10 3 1
	128	[77]	FORLOOP  	5 -11	; to 118
	129	[82]	GETGLOBAL	5 -54	; table
	130	[82]	GETTABLE 	5 5 -56	; "sort"
	131	[82]	MOVE     	6 3
	132	[82]	CLOSURE  	7 0	; 0x7fa7b2c07e90
	133	[82]	CALL     	5 3 1
	134	[84]	LEN      	4 3
	135	[84]	LT       	0 -35 4	; 0 -
	136	[84]	JMP      	2	; to 139
	137	[85]	GETTABLE 	4 3 -58	; 1
	138	[85]	SETTABLE 	0 -57 4	; "ticks_candidates" -
	139	[88]	GETUPVAL 	4 7	; FrameContainer
	140	[88]	SELF     	4 4 -30	; "new"
	141	[88]	NEWTABLE 	6 0 3
	142	[89]	GETUPVAL 	7 2	; Size
	143	[89]	GETTABLE 	7 7 -59	; "padding"
	144	[89]	GETTABLE 	7 7 -60	; "default"
	145	[89]	SETTABLE 	6 -59 7	; "padding" -
	146	[90]	GETUPVAL 	7 2	; Size
	147	[90]	GETTABLE 	7 7 -61	; "margin"
	148	[90]	GETTABLE 	7 7 -62	; "title"
	149	[90]	SETTABLE 	6 -61 7	; "margin" -
	150	[91]	SETTABLE 	6 -63 -35	; "bordersize" 0
	151	[92]	GETUPVAL 	7 8	; TextWidget
	152	[92]	SELF     	7 7 -30	; "new"
	153	[92]	NEWTABLE 	9 0 4
	154	[93]	SETTABLE 	9 -64 1	; "text" -
	155	[94]	GETTABLE 	10 0 -66	; "title_face"
	156	[94]	SETTABLE 	9 -65 10	; "face" -
	157	[95]	SETTABLE 	9 -67 -68	; "bold" true
	158	[96]	GETTABLE 	10 0 -4	; "screen_width"
	159	[96]	MUL      	10 10 -13	; - 0.95
	160	[96]	SETTABLE 	9 -69 10	; "max_width" -
	161	[92]	CALL     	7 3 0
	162	[98]	SETLIST  	6 0 1	; 1
	163	[88]	CALL     	4 3 2
	164	[100]	GETUPVAL 	5 9	; ProgressWidget
	165	[100]	SELF     	5 5 -30	; "new"
	166	[100]	NEWTABLE 	7 0 6
	167	[101]	GETTABLE 	8 0 -4	; "screen_width"
	168	[101]	MUL      	8 8 -71	; - 0.9
	169	[101]	SETTABLE 	7 -12 8	; "width" -
	170	[102]	GETUPVAL 	8 2	; Size
	171	[102]	GETTABLE 	8 8 -73	; "item"
	172	[102]	GETTABLE 	8 8 -74	; "height_big"
	173	[102]	SETTABLE 	7 -72 8	; "height" -
	174	[103]	GETTABLE 	8 0 -40	; "curr_page"
	175	[103]	GETTABLE 	9 0 -43	; "page_count"
	176	[103]	DIV      	8 8 9
	177	[103]	SETTABLE 	7 -75 8	; "percentage" -
	178	[104]	GETTABLE 	8 0 -57	; "ticks_candidates"
	179	[104]	SETTABLE 	7 -76 8	; "ticks" -
	180	[105]	GETUPVAL 	8 2	; Size
	181	[105]	GETTABLE 	8 8 -78	; "line"
	182	[105]	GETTABLE 	8 8 -79	; "medium"
	183	[105]	SETTABLE 	7 -77 8	; "tick_width" -
	184	[106]	GETTABLE 	8 0 -43	; "page_count"
	185	[106]	SETTABLE 	7 -80 8	; "last" -
	186	[100]	CALL     	5 3 2
	187	[107]	SETTABLE 	0 -70 5	; "progress_bar" -
	188	[108]	GETUPVAL 	5 7	; FrameContainer
	189	[108]	SELF     	5 5 -30	; "new"
	190	[108]	NEWTABLE 	7 1 3
	191	[109]	GETUPVAL 	8 2	; Size
	192	[109]	GETTABLE 	8 8 -59	; "padding"
	193	[109]	GETTABLE 	8 8 -16	; "button"
	194	[109]	SETTABLE 	7 -59 8	; "padding" -
	195	[110]	GETUPVAL 	8 2	; Size
	196	[110]	GETTABLE 	8 8 -61	; "margin"
	197	[110]	GETTABLE 	8 8 -82	; "small"
	198	[110]	SETTABLE 	7 -61 8	; "margin" -
	199	[111]	SETTABLE 	7 -63 -35	; "bordersize" 0
	200	[113]	GETTABLE 	8 0 -70	; "progress_bar"
	201	[113]	SETLIST  	7 1 1	; 1
	202	[108]	CALL     	5 3 2
	203	[113]	SETTABLE 	0 -81 5	; "skimto_progress" -
	204	[115]	GETUPVAL 	5 10	; LineWidget
	205	[115]	SELF     	5 5 -30	; "new"
	206	[115]	NEWTABLE 	7 0 1
	207	[116]	GETUPVAL 	8 5	; Geom
	208	[116]	SELF     	8 8 -30	; "new"
	209	[116]	NEWTABLE 	10 0 2
	210	[117]	GETTABLE 	11 0 -12	; "width"
	211	[117]	SETTABLE 	10 -37 11	; "w" -
	212	[118]	GETUPVAL 	11 2	; Size
	213	[118]	GETTABLE 	11 11 -78	; "line"
	214	[118]	GETTABLE 	11 11 -84	; "thick"
	215	[118]	SETTABLE 	10 -38 11	; "h" -
	216	[116]	CALL     	8 3 2
	217	[119]	SETTABLE 	7 -83 8	; "dimen" -
	218	[115]	CALL     	5 3 2
	219	[121]	GETUPVAL 	6 11	; OverlapGroup
	220	[121]	SELF     	6 6 -30	; "new"
	221	[121]	NEWTABLE 	8 1 1
	222	[122]	NEWTABLE 	9 0 2
	223	[123]	GETTABLE 	10 0 -12	; "width"
	224	[123]	SETTABLE 	9 -37 10	; "w" -
	225	[124]	SELF     	10 4 -85	; "getSize"
	226	[124]	CALL     	10 2 2
	227	[124]	GETTABLE 	10 10 -38	; "h"
	228	[124]	SETTABLE 	9 -38 10	; "h" -
	229	[125]	SETTABLE 	8 -83 9	; "dimen" -
	230	[126]	MOVE     	9 4
	231	[127]	GETUPVAL 	10 12	; CloseButton
	232	[127]	SELF     	10 10 -30	; "new"
	233	[127]	NEWTABLE 	12 0 2
	234	[127]	SETTABLE 	12 -86 0	; "window" -
	235	[127]	GETUPVAL 	13 2	; Size
	236	[127]	GETTABLE 	13 13 -61	; "margin"
	237	[127]	GETTABLE 	13 13 -62	; "title"
	238	[127]	SETTABLE 	12 -87 13	; "padding_top" -
	239	[127]	CALL     	10 3 0
	240	[128]	SETLIST  	8 0 1	; 1
	241	[121]	CALL     	6 3 2
	242	[129]	GETUPVAL 	7 13	; Button
	243	[129]	SELF     	7 7 -30	; "new"
	244	[129]	NEWTABLE 	9 0 8
	245	[130]	SETTABLE 	9 -64 -88	; "text" "-1"
	246	[131]	GETTABLE 	10 0 -14	; "button_bordersize"
	247	[131]	SETTABLE 	9 -63 10	; "bordersize" -
	248	[132]	GETTABLE 	10 0 -17	; "button_margin"
	249	[132]	SETTABLE 	9 -61 10	; "margin" -
	250	[133]	SETTABLE 	9 -89 -35	; "radius" 0
	251	[134]	SETTABLE 	9 -90 -68	; "enabled" true
	252	[135]	GETTABLE 	10 0 -18	; "button_width"
	253	[135]	SETTABLE 	9 -12 10	; "width" -
	254	[136]	SETTABLE 	9 -91 0	; "show_parent" -
	255	[139]	CLOSURE  	10 1	; 0x7fa7b2c08b50
	256	[139]	MOVE     	0 0
	257	[139]	SETTABLE 	9 -92 10	; "callback" -
	258	[129]	CALL     	7 3 2
	259	[141]	GETUPVAL 	8 13	; Button
	260	[141]	SELF     	8 8 -30	; "new"
	261	[141]	NEWTABLE 	10 0 8
	262	[142]	SETTABLE 	10 -64 -93	; "text" "-10"
	263	[143]	GETTABLE 	11 0 -14	; "button_bordersize"
	264	[143]	SETTABLE 	10 -63 11	; "bordersize" -
	265	[144]	GETTABLE 	11 0 -17	; "button_margin"
	266	[144]	SETTABLE 	10 -61 11	; "margin" -
	267	[145]	SETTABLE 	10 -89 -35	; "radius" 0
	268	[146]	SETTABLE 	10 -90 -68	; "enabled" true
	269	[147]	GETTABLE 	11 0 -18	; "button_width"
	270	[147]	SETTABLE 	10 -12 11	; "width" -
	271	[148]	SETTABLE 	10 -91 0	; "show_parent" -
	272	[151]	CLOSURE  	11 2	; 0x7fa7b2c08e60
	273	[151]	MOVE     	0 0
	274	[151]	SETTABLE 	10 -92 11	; "callback" -
	275	[141]	CALL     	8 3 2
	276	[153]	GETUPVAL 	9 13	; Button
	277	[153]	SELF     	9 9 -30	; "new"
	278	[153]	NEWTABLE 	11 0 8
	279	[154]	SETTABLE 	11 -64 -94	; "text" "+1"
	280	[155]	GETTABLE 	12 0 -14	; "button_bordersize"
	281	[155]	SETTABLE 	11 -63 12	; "bordersize" -
	282	[156]	GETTABLE 	12 0 -17	; "button_margin"
	283	[156]	SETTABLE 	11 -61 12	; "margin" -
	284	[157]	SETTABLE 	11 -89 -35	; "radius" 0
	285	[158]	SETTABLE 	11 -90 -68	; "enabled" true
	286	[159]	GETTABLE 	12 0 -18	; "button_width"
	287	[159]	SETTABLE 	11 -12 12	; "width" -
	288	[160]	SETTABLE 	11 -91 0	; "show_parent" -
	289	[163]	CLOSURE  	12 3	; 0x7fa7b2c091a0
	290	[163]	MOVE     	0 0
	291	[163]	SETTABLE 	11 -92 12	; "callback" -
	292	[153]	CALL     	9 3 2
	293	[165]	GETUPVAL 	10 13	; Button
	294	[165]	SELF     	10 10 -30	; "new"
	295	[165]	NEWTABLE 	12 0 8
	296	[166]	SETTABLE 	12 -64 -95	; "text" "+10"
	297	[167]	GETTABLE 	13 0 -14	; "button_bordersize"
	298	[167]	SETTABLE 	12 -63 13	; "bordersize" -
	299	[168]	GETTABLE 	13 0 -17	; "button_margin"
	300	[168]	SETTABLE 	12 -61 13	; "margin" -
	301	[169]	SETTABLE 	12 -89 -35	; "radius" 0
	302	[170]	SETTABLE 	12 -90 -68	; "enabled" true
	303	[171]	GETTABLE 	13 0 -18	; "button_width"
	304	[171]	SETTABLE 	12 -12 13	; "width" -
	305	[172]	SETTABLE 	12 -91 0	; "show_parent" -
	306	[175]	CLOSURE  	13 4	; 0x7fa7b2c086d0
	307	[175]	MOVE     	0 0
	308	[175]	SETTABLE 	12 -92 13	; "callback" -
	309	[165]	CALL     	10 3 2
	310	[177]	GETUPVAL 	11 13	; Button
	311	[177]	SELF     	11 11 -30	; "new"
	312	[177]	NEWTABLE 	13 0 9
	313	[178]	SETTABLE 	13 -64 2	; "text" -
	314	[179]	SETTABLE 	13 -63 -35	; "bordersize" 0
	315	[180]	GETTABLE 	14 0 -17	; "button_margin"
	316	[180]	SETTABLE 	13 -61 14	; "margin" -
	317	[181]	SETTABLE 	13 -89 -35	; "radius" 0
	318	[182]	SETTABLE 	13 -59 -35	; "padding" 0
	319	[183]	SETTABLE 	13 -90 -68	; "enabled" true
	320	[184]	GETTABLE 	14 0 -4	; "screen_width"
	321	[184]	MUL      	14 14 -97	; - 0.2
	322	[184]	GETTABLE 	15 0 -17	; "button_margin"
	323	[184]	MUL      	15 -20 15	; 2 -
	324	[184]	SUB      	14 14 15
	325	[184]	SETTABLE 	13 -12 14	; "width" -
	326	[185]	SETTABLE 	13 -91 0	; "show_parent" -
	327	[188]	CLOSURE  	14 5	; 0x7fa7b2c09640
	328	[188]	MOVE     	0 0
	329	[188]	SETTABLE 	13 -92 14	; "callback" -
	330	[177]	CALL     	11 3 2
	331	[189]	SETTABLE 	0 -96 11	; "current_page_text" -
	332	[191]	LOADK    	11 -98	; "\226\150\183\226\148\130"
	333	[192]	LOADK    	12 -99	; "\226\148\130\226\151\129"
	334	[193]	LOADK    	13 -100	; "\226\152\134\226\150\183"
	335	[194]	LOADK    	14 -101	; "\226\151\129\226\152\134"
	336	[195]	GETUPVAL 	15 14	; BD
	337	[195]	GETTABLE 	15 15 -102	; "mirroredUILayout"
	338	[195]	CALL     	15 1 2
	339	[195]	TEST     	15 0 0
	340	[195]	JMP      	6	; to 347
	341	[196]	MOVE     	15 12
	342	[196]	MOVE     	12 11
	343	[196]	MOVE     	11 15
	344	[197]	MOVE     	15 14
	345	[197]	MOVE     	14 13
	346	[197]	MOVE     	13 15
	347	[199]	GETUPVAL 	15 13	; Button
	348	[199]	SELF     	15 15 -30	; "new"
	349	[199]	NEWTABLE 	17 0 9
	350	[200]	SETTABLE 	17 -64 11	; "text" -
	351	[201]	GETTABLE 	18 0 -14	; "button_bordersize"
	352	[201]	SETTABLE 	17 -63 18	; "bordersize" -
	353	[202]	GETTABLE 	18 0 -17	; "button_margin"
	354	[202]	SETTABLE 	17 -61 18	; "margin" -
	355	[203]	SETTABLE 	17 -89 -35	; "radius" 0
	356	[204]	SETTABLE 	17 -90 -68	; "enabled" true
	357	[205]	GETTABLE 	18 0 -18	; "button_width"
	358	[205]	SETTABLE 	17 -12 18	; "width" -
	359	[206]	SETTABLE 	17 -91 0	; "show_parent" -
	360	[212]	CLOSURE  	18 6	; 0x7fa7b2c09af0
	361	[212]	MOVE     	0 0
	362	[212]	SETTABLE 	17 -92 18	; "callback" -
	363	[215]	CLOSURE  	18 7	; 0x7fa7b2c08d40
	364	[215]	MOVE     	0 0
	365	[215]	SETTABLE 	17 -103 18	; "hold_callback" -
	366	[199]	CALL     	15 3 2
	367	[218]	GETUPVAL 	16 13	; Button
	368	[218]	SELF     	16 16 -30	; "new"
	369	[218]	NEWTABLE 	18 0 9
	370	[219]	SETTABLE 	18 -64 12	; "text" -
	371	[220]	GETTABLE 	19 0 -14	; "button_bordersize"
	372	[220]	SETTABLE 	18 -63 19	; "bordersize" -
	373	[221]	GETTABLE 	19 0 -17	; "button_margin"
	374	[221]	SETTABLE 	18 -61 19	; "margin" -
	375	[222]	SETTABLE 	18 -89 -35	; "radius" 0
	376	[223]	SETTABLE 	18 -90 -68	; "enabled" true
	377	[224]	GETTABLE 	19 0 -18	; "button_width"
	378	[224]	SETTABLE 	18 -12 19	; "width" -
	379	[225]	SETTABLE 	18 -91 0	; "show_parent" -
	380	[231]	CLOSURE  	19 8	; 0x7fa7b2c09780
	381	[231]	MOVE     	0 0
	382	[231]	SETTABLE 	18 -92 19	; "callback" -
	383	[234]	CLOSURE  	19 9	; 0x7fa7b2c0a0e0
	384	[234]	MOVE     	0 0
	385	[234]	SETTABLE 	18 -103 19	; "hold_callback" -
	386	[218]	CALL     	16 3 2
	387	[237]	GETUPVAL 	17 13	; Button
	388	[237]	SELF     	17 17 -30	; "new"
	389	[237]	NEWTABLE 	19 0 9
	390	[238]	SETTABLE 	19 -64 13	; "text" -
	391	[239]	GETTABLE 	20 0 -14	; "button_bordersize"
	392	[239]	SETTABLE 	19 -63 20	; "bordersize" -
	393	[240]	GETTABLE 	20 0 -17	; "button_margin"
	394	[240]	SETTABLE 	19 -61 20	; "margin" -
	395	[241]	SETTABLE 	19 -89 -35	; "radius" 0
	396	[242]	SETTABLE 	19 -90 -68	; "enabled" true
	397	[243]	GETTABLE 	20 0 -18	; "button_width"
	398	[243]	SETTABLE 	19 -12 20	; "width" -
	399	[244]	SETTABLE 	19 -91 0	; "show_parent" -
	400	[247]	CLOSURE  	20 10	; 0x7fa7b2c0a160
	401	[247]	MOVE     	0 0
	402	[247]	GETUPVAL 	0 15	; Event
	403	[247]	SETTABLE 	19 -92 20	; "callback" -
	404	[251]	CLOSURE  	20 11	; 0x7fa7b2c0a7e0
	405	[251]	MOVE     	0 0
	406	[251]	SETTABLE 	19 -103 20	; "hold_callback" -
	407	[237]	CALL     	17 3 2
	408	[254]	GETUPVAL 	18 13	; Button
	409	[254]	SELF     	18 18 -30	; "new"
	410	[254]	NEWTABLE 	20 0 9
	411	[255]	SETTABLE 	20 -64 14	; "text" -
	412	[256]	GETTABLE 	21 0 -14	; "button_bordersize"
	413	[256]	SETTABLE 	20 -63 21	; "bordersize" -
	414	[257]	GETTABLE 	21 0 -17	; "button_margin"
	415	[257]	SETTABLE 	20 -61 21	; "margin" -
	416	[258]	SETTABLE 	20 -89 -35	; "radius" 0
	417	[259]	SETTABLE 	20 -90 -68	; "enabled" true
	418	[260]	GETTABLE 	21 0 -18	; "button_width"
	419	[260]	SETTABLE 	20 -12 21	; "width" -
	420	[261]	SETTABLE 	20 -91 0	; "show_parent" -
	421	[264]	CLOSURE  	21 12	; 0x7fa7b2c0aa40
	422	[264]	MOVE     	0 0
	423	[264]	GETUPVAL 	0 15	; Event
	424	[264]	SETTABLE 	20 -92 21	; "callback" -
	425	[268]	CLOSURE  	21 13	; 0x7fa7b2c0b090
	426	[268]	MOVE     	0 0
	427	[268]	SETTABLE 	20 -103 21	; "hold_callback" -
	428	[254]	CALL     	18 3 2
	429	[271]	GETUPVAL 	19 16	; HorizontalSpan
	430	[271]	SELF     	19 19 -30	; "new"
	431	[271]	NEWTABLE 	21 0 1
	432	[271]	GETTABLE 	22 0 -4	; "screen_width"
	433	[271]	MUL      	22 22 -97	; - 0.2
	434	[271]	SETTABLE 	21 -12 22	; "width" -
	435	[271]	CALL     	19 3 2
	436	[272]	GETUPVAL 	20 17	; HorizontalGroup
	437	[272]	SELF     	20 20 -30	; "new"
	438	[272]	NEWTABLE 	22 5 1
	439	[273]	SETTABLE 	22 -104 -105	; "align" "center"
	440	[274]	MOVE     	23 16
	441	[275]	MOVE     	24 18
	442	[276]	MOVE     	25 19
	443	[277]	MOVE     	26 17
	444	[279]	MOVE     	27 15
	445	[279]	SETLIST  	22 5 1	; 1
	446	[272]	CALL     	20 3 2
	447	[281]	GETUPVAL 	21 18	; VerticalGroup
	448	[281]	SELF     	21 21 -30	; "new"
	449	[281]	NEWTABLE 	23 0 1
	450	[281]	SETTABLE 	23 -104 -105	; "align" "center"
	451	[281]	CALL     	21 3 2
	452	[282]	GETUPVAL 	22 19	; VerticalSpan
	453	[282]	SELF     	22 22 -30	; "new"
	454	[282]	NEWTABLE 	24 0 1
	455	[282]	GETGLOBAL	25 -9	; math
	456	[282]	GETTABLE 	25 25 -10	; "ceil"
	457	[282]	GETTABLE 	26 0 -6	; "screen_height"
	458	[282]	MUL      	26 26 -106	; - 0.015
	459	[282]	CALL     	25 2 2
	460	[282]	SETTABLE 	24 -12 25	; "width" -
	461	[282]	CALL     	22 3 2
	462	[283]	GETGLOBAL	23 -54	; table
	463	[283]	GETTABLE 	23 23 -55	; "insert"
	464	[283]	MOVE     	24 21
	465	[283]	MOVE     	25 22
	466	[283]	CALL     	23 3 1
	467	[284]	GETGLOBAL	23 -54	; table
	468	[284]	GETTABLE 	23 23 -55	; "insert"
	469	[284]	MOVE     	24 21
	470	[284]	MOVE     	25 20
	471	[284]	CALL     	23 3 1
	472	[285]	GETGLOBAL	23 -54	; table
	473	[285]	GETTABLE 	23 23 -55	; "insert"
	474	[285]	MOVE     	24 21
	475	[285]	MOVE     	25 22
	476	[285]	CALL     	23 3 1
	477	[287]	GETUPVAL 	23 17	; HorizontalGroup
	478	[287]	SELF     	23 23 -30	; "new"
	479	[287]	NEWTABLE 	25 5 1
	480	[288]	SETTABLE 	25 -104 -105	; "align" "center"
	481	[289]	MOVE     	26 7
	482	[290]	MOVE     	27 8
	483	[291]	GETTABLE 	28 0 -96	; "current_page_text"
	484	[292]	MOVE     	29 10
	485	[294]	MOVE     	30 9
	486	[294]	SETLIST  	25 5 1	; 1
	487	[287]	CALL     	23 3 2
	488	[295]	GETUPVAL 	24 18	; VerticalGroup
	489	[295]	SELF     	24 24 -30	; "new"
	490	[295]	NEWTABLE 	26 0 1
	491	[295]	SETTABLE 	26 -104 -105	; "align" "center"
	492	[295]	CALL     	24 3 2
	493	[296]	GETUPVAL 	25 19	; VerticalSpan
	494	[296]	SELF     	25 25 -30	; "new"
	495	[296]	NEWTABLE 	27 0 1
	496	[296]	GETGLOBAL	28 -9	; math
	497	[296]	GETTABLE 	28 28 -10	; "ceil"
	498	[296]	GETTABLE 	29 0 -6	; "screen_height"
	499	[296]	MUL      	29 29 -106	; - 0.015
	500	[296]	CALL     	28 2 2
	501	[296]	SETTABLE 	27 -12 28	; "width" -
	502	[296]	CALL     	25 3 2
	503	[297]	GETGLOBAL	26 -54	; table
	504	[297]	GETTABLE 	26 26 -55	; "insert"
	505	[297]	MOVE     	27 24
	506	[297]	MOVE     	28 25
	507	[297]	CALL     	26 3 1
	508	[298]	GETGLOBAL	26 -54	; table
	509	[298]	GETTABLE 	26 26 -55	; "insert"
	510	[298]	MOVE     	27 24
	511	[298]	MOVE     	28 23
	512	[298]	CALL     	26 3 1
	513	[299]	GETGLOBAL	26 -54	; table
	514	[299]	GETTABLE 	26 26 -55	; "insert"
	515	[299]	MOVE     	27 24
	516	[299]	MOVE     	28 25
	517	[299]	CALL     	26 3 1
	518	[301]	GETUPVAL 	26 7	; FrameContainer
	519	[301]	SELF     	26 26 -30	; "new"
	520	[301]	NEWTABLE 	28 0 5
	521	[302]	GETUPVAL 	29 2	; Size
	522	[302]	GETTABLE 	29 29 -89	; "radius"
	523	[302]	GETTABLE 	29 29 -86	; "window"
	524	[302]	SETTABLE 	28 -89 29	; "radius" -
	525	[303]	GETUPVAL 	29 2	; Size
	526	[303]	GETTABLE 	29 29 -15	; "border"
	527	[303]	GETTABLE 	29 29 -86	; "window"
	528	[303]	SETTABLE 	28 -63 29	; "bordersize" -
	529	[304]	SETTABLE 	28 -59 -35	; "padding" 0
	530	[305]	SETTABLE 	28 -61 -35	; "margin" 0
	531	[306]	GETUPVAL 	29 20	; Blitbuffer
	532	[306]	GETTABLE 	29 29 -109	; "COLOR_WHITE"
	533	[306]	SETTABLE 	28 -108 29	; "background" -
	534	[307]	GETUPVAL 	29 18	; VerticalGroup
	535	[307]	SELF     	29 29 -30	; "new"
	536	[307]	NEWTABLE 	31 5 1
	537	[308]	SETTABLE 	31 -104 -105	; "align" "center"
	538	[309]	MOVE     	32 6
	539	[310]	MOVE     	33 5
	540	[311]	MOVE     	34 21
	541	[312]	GETUPVAL 	35 21	; CenterContainer
	542	[312]	SELF     	35 35 -30	; "new"
	543	[312]	NEWTABLE 	37 1 1
	544	[313]	GETUPVAL 	38 5	; Geom
	545	[313]	SELF     	38 38 -30	; "new"
	546	[313]	NEWTABLE 	40 0 2
	547	[314]	SELF     	41 5 -85	; "getSize"
	548	[314]	CALL     	41 2 2
	549	[314]	GETTABLE 	41 41 -37	; "w"
	550	[314]	SETTABLE 	40 -37 41	; "w" -
	551	[315]	GETTABLE 	41 0 -81	; "skimto_progress"
	552	[315]	SELF     	41 41 -85	; "getSize"
	553	[315]	CALL     	41 2 2
	554	[315]	GETTABLE 	41 41 -38	; "h"
	555	[315]	SETTABLE 	40 -38 41	; "h" -
	556	[313]	CALL     	38 3 2
	557	[316]	SETTABLE 	37 -83 38	; "dimen" -
	558	[318]	GETTABLE 	38 0 -81	; "skimto_progress"
	559	[318]	SETLIST  	37 1 1	; 1
	560	[312]	CALL     	35 3 2
	561	[320]	MOVE     	36 24
	562	[320]	SETLIST  	31 5 1	; 1
	563	[307]	CALL     	29 3 0
	564	[321]	SETLIST  	28 0 1	; 1
	565	[301]	CALL     	26 3 2
	566	[321]	SETTABLE 	0 -107 26	; "skimto_frame" -
	567	[322]	GETUPVAL 	26 22	; WidgetContainer
	568	[322]	SELF     	26 26 -30	; "new"
	569	[322]	NEWTABLE 	28 0 2
	570	[323]	SETTABLE 	28 -104 -105	; "align" "center"
	571	[324]	GETUPVAL 	29 5	; Geom
	572	[324]	SELF     	29 29 -30	; "new"
	573	[324]	NEWTABLE 	31 0 4
	574	[325]	SETTABLE 	31 -34 -35	; "x" 0
	575	[325]	SETTABLE 	31 -36 -35	; "y" 0
	576	[326]	GETTABLE 	32 0 -4	; "screen_width"
	577	[326]	SETTABLE 	31 -37 32	; "w" -
	578	[327]	GETTABLE 	32 0 -6	; "screen_height"
	579	[327]	SETTABLE 	31 -38 32	; "h" -
	580	[324]	CALL     	29 3 2
	581	[328]	SETTABLE 	28 -83 29	; "dimen" -
	582	[329]	GETUPVAL 	29 23	; MovableContainer
	583	[329]	SELF     	29 29 -30	; "new"
	584	[329]	NEWTABLE 	31 1 0
	585	[332]	GETTABLE 	32 0 -107	; "skimto_frame"
	586	[332]	SETLIST  	31 1 1	; 1
	587	[329]	CALL     	29 3 0
	588	[333]	SETLIST  	28 0 1	; 1
	589	[322]	CALL     	26 3 2
	590	[333]	SETTABLE 	0 -58 26	; 1 -
	591	[334]	RETURN   	0 1

function <./frontend/apps/reader/skimtowidget.lua:82,82> (8 instructions, 32 bytes at 0x7fa7b2c07e90)
2 params, 4 slots, 0 upvalues, 2 locals, 0 constants, 0 functions
	1	[82]	LEN      	2 0
	2	[82]	LEN      	3 1
	3	[82]	LT       	1 3 2
	4	[82]	JMP      	1	; to 6
	5	[82]	LOADBOOL 	2 0 1
	6	[82]	LOADBOOL 	2 1 0
	7	[82]	RETURN   	2 2
	8	[82]	RETURN   	0 1

function <./frontend/apps/reader/skimtowidget.lua:137,139> (7 instructions, 28 bytes at 0x7fa7b2c08b50)
0 params, 3 slots, 1 upvalue, 0 locals, 3 constants, 0 functions
	1	[138]	GETUPVAL 	0 0	; self
	2	[138]	SELF     	0 0 -1	; "goToPage"
	3	[138]	GETUPVAL 	2 0	; self
	4	[138]	GETTABLE 	2 2 -2	; "curr_page"
	5	[138]	SUB      	2 2 -3	; - 1
	6	[138]	CALL     	0 3 1
	7	[139]	RETURN   	0 1

function <./frontend/apps/reader/skimtowidget.lua:149,151> (7 instructions, 28 bytes at 0x7fa7b2c08e60)
0 params, 3 slots, 1 upvalue, 0 locals, 3 constants, 0 functions
	1	[150]	GETUPVAL 	0 0	; self
	2	[150]	SELF     	0 0 -1	; "goToPage"
	3	[150]	GETUPVAL 	2 0	; self
	4	[150]	GETTABLE 	2 2 -2	; "curr_page"
	5	[150]	SUB      	2 2 -3	; - 10
	6	[150]	CALL     	0 3 1
	7	[151]	RETURN   	0 1

function <./frontend/apps/reader/skimtowidget.lua:161,163> (7 instructions, 28 bytes at 0x7fa7b2c091a0)
0 params, 3 slots, 1 upvalue, 0 locals, 3 constants, 0 functions
	1	[162]	GETUPVAL 	0 0	; self
	2	[162]	SELF     	0 0 -1	; "goToPage"
	3	[162]	GETUPVAL 	2 0	; self
	4	[162]	GETTABLE 	2 2 -2	; "curr_page"
	5	[162]	ADD      	2 2 -3	; - 1
	6	[162]	CALL     	0 3 1
	7	[163]	RETURN   	0 1

function <./frontend/apps/reader/skimtowidget.lua:173,175> (7 instructions, 28 bytes at 0x7fa7b2c086d0)
0 params, 3 slots, 1 upvalue, 0 locals, 3 constants, 0 functions
	1	[174]	GETUPVAL 	0 0	; self
	2	[174]	SELF     	0 0 -1	; "goToPage"
	3	[174]	GETUPVAL 	2 0	; self
	4	[174]	GETTABLE 	2 2 -2	; "curr_page"
	5	[174]	ADD      	2 2 -3	; - 10
	6	[174]	CALL     	0 3 1
	7	[175]	RETURN   	0 1

function <./frontend/apps/reader/skimtowidget.lua:186,188> (4 instructions, 16 bytes at 0x7fa7b2c09640)
0 params, 2 slots, 1 upvalue, 0 locals, 1 constant, 0 functions
	1	[187]	GETUPVAL 	0 0	; self
	2	[187]	GETTABLE 	0 0 -1	; "callback_switch_to_goto"
	3	[187]	CALL     	0 1 1
	4	[188]	RETURN   	0 1

function <./frontend/apps/reader/skimtowidget.lua:207,212> (18 instructions, 72 bytes at 0x7fa7b2c09af0)
0 params, 4 slots, 1 upvalue, 1 local, 5 constants, 0 functions
	1	[208]	GETUPVAL 	0 0	; self
	2	[208]	SELF     	0 0 -1	; "getNextChapter"
	3	[208]	GETUPVAL 	2 0	; self
	4	[208]	GETTABLE 	2 2 -2	; "curr_page"
	5	[208]	CALL     	0 3 2
	6	[209]	TEST     	0 0 0
	7	[209]	JMP      	10	; to 18
	8	[209]	LE       	0 -3 0	; 1 -
	9	[209]	JMP      	8	; to 18
	10	[209]	GETUPVAL 	1 0	; self
	11	[209]	GETTABLE 	1 1 -4	; "page_count"
	12	[209]	LE       	0 0 1
	13	[209]	JMP      	4	; to 18
	14	[210]	GETUPVAL 	1 0	; self
	15	[210]	SELF     	1 1 -5	; "goToPage"
	16	[210]	MOVE     	3 0
	17	[210]	CALL     	1 3 1
	18	[212]	RETURN   	0 1

function <./frontend/apps/reader/skimtowidget.lua:213,215> (6 instructions, 24 bytes at 0x7fa7b2c08d40)
0 params, 3 slots, 1 upvalue, 0 locals, 2 constants, 0 functions
	1	[214]	GETUPVAL 	0 0	; self
	2	[214]	SELF     	0 0 -1	; "goToPage"
	3	[214]	GETUPVAL 	2 0	; self
	4	[214]	GETTABLE 	2 2 -2	; "page_count"
	5	[214]	CALL     	0 3 1
	6	[215]	RETURN   	0 1

function <./frontend/apps/reader/skimtowidget.lua:226,231> (18 instructions, 72 bytes at 0x7fa7b2c09780)
0 params, 4 slots, 1 upvalue, 1 local, 5 constants, 0 functions
	1	[227]	GETUPVAL 	0 0	; self
	2	[227]	SELF     	0 0 -1	; "getPrevChapter"
	3	[227]	GETUPVAL 	2 0	; self
	4	[227]	GETTABLE 	2 2 -2	; "curr_page"
	5	[227]	CALL     	0 3 2
	6	[228]	TEST     	0 0 0
	7	[228]	JMP      	10	; to 18
	8	[228]	LE       	0 -3 0	; 1 -
	9	[228]	JMP      	8	; to 18
	10	[228]	GETUPVAL 	1 0	; self
	11	[228]	GETTABLE 	1 1 -4	; "page_count"
	12	[228]	LE       	0 0 1
	13	[228]	JMP      	4	; to 18
	14	[229]	GETUPVAL 	1 0	; self
	15	[229]	SELF     	1 1 -5	; "goToPage"
	16	[229]	MOVE     	3 0
	17	[229]	CALL     	1 3 1
	18	[231]	RETURN   	0 1

function <./frontend/apps/reader/skimtowidget.lua:232,234> (5 instructions, 20 bytes at 0x7fa7b2c0a0e0)
0 params, 3 slots, 1 upvalue, 0 locals, 2 constants, 0 functions
	1	[233]	GETUPVAL 	0 0	; self
	2	[233]	SELF     	0 0 -1	; "goToPage"
	3	[233]	LOADK    	2 -2	; 1
	4	[233]	CALL     	0 3 1
	5	[234]	RETURN   	0 1

function <./frontend/apps/reader/skimtowidget.lua:245,247> (9 instructions, 36 bytes at 0x7fa7b2c0a160)
0 params, 5 slots, 2 upvalues, 0 locals, 4 constants, 0 functions
	1	[246]	GETUPVAL 	0 0	; self
	2	[246]	GETTABLE 	0 0 -1	; "ui"
	3	[246]	SELF     	0 0 -2	; "handleEvent"
	4	[246]	GETUPVAL 	2 1	; Event
	5	[246]	SELF     	2 2 -3	; "new"
	6	[246]	LOADK    	4 -4	; "GotoNextBookmarkFromPage"
	7	[246]	CALL     	2 3 0
	8	[246]	CALL     	0 0 1
	9	[247]	RETURN   	0 1

function <./frontend/apps/reader/skimtowidget.lua:248,251> (14 instructions, 56 bytes at 0x7fa7b2c0a7e0)
0 params, 4 slots, 1 upvalue, 1 local, 5 constants, 0 functions
	1	[249]	GETUPVAL 	0 0	; self
	2	[249]	GETTABLE 	0 0 -1	; "ui"
	3	[249]	GETTABLE 	0 0 -2	; "bookmark"
	4	[249]	SELF     	0 0 -3	; "getLastBookmarkedPageFromPage"
	5	[249]	GETUPVAL 	2 0	; self
	6	[249]	GETTABLE 	2 2 -1	; "ui"
	7	[249]	SELF     	2 2 -4	; "getCurrentPage"
	8	[249]	CALL     	2 2 0
	9	[249]	CALL     	0 0 2
	10	[250]	GETUPVAL 	1 0	; self
	11	[250]	SELF     	1 1 -5	; "goToBookmark"
	12	[250]	MOVE     	3 0
	13	[250]	CALL     	1 3 1
	14	[251]	RETURN   	0 1

function <./frontend/apps/reader/skimtowidget.lua:262,264> (9 instructions, 36 bytes at 0x7fa7b2c0aa40)
0 params, 5 slots, 2 upvalues, 0 locals, 4 constants, 0 functions
	1	[263]	GETUPVAL 	0 0	; self
	2	[263]	GETTABLE 	0 0 -1	; "ui"
	3	[263]	SELF     	0 0 -2	; "handleEvent"
	4	[263]	GETUPVAL 	2 1	; Event
	5	[263]	SELF     	2 2 -3	; "new"
	6	[263]	LOADK    	4 -4	; "GotoPreviousBookmarkFromPage"
	7	[263]	CALL     	2 3 0
	8	[263]	CALL     	0 0 1
	9	[264]	RETURN   	0 1

function <./frontend/apps/reader/skimtowidget.lua:265,268> (14 instructions, 56 bytes at 0x7fa7b2c0b090)
0 params, 4 slots, 1 upvalue, 1 local, 5 constants, 0 functions
	1	[266]	GETUPVAL 	0 0	; self
	2	[266]	GETTABLE 	0 0 -1	; "ui"
	3	[266]	GETTABLE 	0 0 -2	; "bookmark"
	4	[266]	SELF     	0 0 -3	; "getFirstBookmarkedPageFromPage"
	5	[266]	GETUPVAL 	2 0	; self
	6	[266]	GETTABLE 	2 2 -1	; "ui"
	7	[266]	SELF     	2 2 -4	; "getCurrentPage"
	8	[266]	CALL     	2 2 0
	9	[266]	CALL     	0 0 2
	10	[267]	GETUPVAL 	1 0	; self
	11	[267]	SELF     	1 1 -5	; "goToBookmark"
	12	[267]	MOVE     	3 0
	13	[267]	CALL     	1 3 1
	14	[268]	RETURN   	0 1

function <./frontend/apps/reader/skimtowidget.lua:336,349> (41 instructions, 164 bytes at 0x7fa7b2c084f0)
1 param, 6 slots, 0 upvalues, 2 locals, 14 constants, 0 functions
	1	[337]	GETTABLE 	1 0 -1	; "curr_page"
	2	[337]	LE       	0 1 -2	; - 0
	3	[337]	JMP      	1	; to 5
	4	[338]	SETTABLE 	0 -1 -3	; "curr_page" 1
	5	[340]	GETTABLE 	1 0 -1	; "curr_page"
	6	[340]	GETTABLE 	2 0 -4	; "page_count"
	7	[340]	LT       	0 2 1
	8	[340]	JMP      	2	; to 11
	9	[341]	GETTABLE 	1 0 -4	; "page_count"
	10	[341]	SETTABLE 	0 -1 1	; "curr_page" -
	11	[343]	GETTABLE 	1 0 -5	; "progress_bar"
	12	[343]	GETTABLE 	2 0 -1	; "curr_page"
	13	[343]	GETTABLE 	3 0 -4	; "page_count"
	14	[343]	DIV      	2 2 3
	15	[343]	SETTABLE 	1 -6 2	; "percentage" -
	16	[344]	GETGLOBAL	1 -7	; tostring
	17	[344]	GETTABLE 	2 0 -1	; "curr_page"
	18	[344]	CALL     	1 2 2
	19	[345]	GETTABLE 	2 0 -8	; "ui"
	20	[345]	GETTABLE 	2 2 -9	; "pagemap"
	21	[345]	TEST     	2 0 0
	22	[345]	JMP      	12	; to 35
	23	[345]	GETTABLE 	2 0 -8	; "ui"
	24	[345]	GETTABLE 	2 2 -9	; "pagemap"
	25	[345]	SELF     	2 2 -10	; "wantsPageLabels"
	26	[345]	CALL     	2 2 2
	27	[345]	TEST     	2 0 0
	28	[345]	JMP      	6	; to 35
	29	[346]	GETTABLE 	2 0 -8	; "ui"
	30	[346]	GETTABLE 	2 2 -9	; "pagemap"
	31	[346]	SELF     	2 2 -11	; "getCurrentPageLabel"
	32	[346]	LOADBOOL 	4 1 0
	33	[346]	CALL     	2 3 2
	34	[346]	MOVE     	1 2
	35	[348]	GETTABLE 	2 0 -12	; "current_page_text"
	36	[348]	SELF     	2 2 -13	; "setText"
	37	[348]	MOVE     	4 1
	38	[348]	GETTABLE 	5 0 -12	; "current_page_text"
	39	[348]	GETTABLE 	5 5 -14	; "width"
	40	[348]	CALL     	2 4 1
	41	[349]	RETURN   	0 1

function <./frontend/apps/reader/skimtowidget.lua:351,358> (11 instructions, 44 bytes at 0x7fa7b2c0ba60)
2 params, 4 slots, 0 upvalues, 2 locals, 5 constants, 0 functions
	1	[354]	GETTABLE 	2 0 -1	; "orig_page_added_to_stack"
	2	[354]	TEST     	2 0 0
	3	[354]	JMP      	2	; to 6
	4	[354]	TEST     	1 0 0
	5	[354]	JMP      	5	; to 11
	6	[355]	GETTABLE 	2 0 -2	; "ui"
	7	[355]	GETTABLE 	2 2 -3	; "link"
	8	[355]	SELF     	2 2 -4	; "addCurrentLocationToStack"
	9	[355]	CALL     	2 2 1
	10	[356]	SETTABLE 	0 -1 -5	; "orig_page_added_to_stack" true
	11	[358]	RETURN   	0 1

function <./frontend/apps/reader/skimtowidget.lua:360,369> (15 instructions, 60 bytes at 0x7fa7b2c0bfb0)
2 params, 8 slots, 0 upvalues, 7 locals, 2 constants, 0 functions
	1	[362]	LOADK    	3 -1	; 1
	2	[362]	GETTABLE 	4 0 -2	; "ticks_candidates"
	3	[362]	LEN      	4 4
	4	[362]	LOADK    	5 -1	; 1
	5	[362]	FORPREP  	3 7	; to 13
	6	[363]	GETTABLE 	7 0 -2	; "ticks_candidates"
	7	[363]	GETTABLE 	7 7 6
	8	[363]	LT       	0 1 7
	9	[363]	JMP      	3	; to 13
	10	[364]	GETTABLE 	7 0 -2	; "ticks_candidates"
	11	[364]	GETTABLE 	2 7 6
	12	[365]	JMP      	1	; to 14
	13	[362]	FORLOOP  	3 -8	; to 6
	14	[368]	RETURN   	2 2
	15	[369]	RETURN   	0 1

function <./frontend/apps/reader/skimtowidget.lua:371,380> (15 instructions, 60 bytes at 0x7fa7b2c0c430)
2 params, 8 slots, 0 upvalues, 7 locals, 2 constants, 0 functions
	1	[373]	LOADK    	3 -1	; 1
	2	[373]	GETTABLE 	4 0 -2	; "ticks_candidates"
	3	[373]	LEN      	4 4
	4	[373]	LOADK    	5 -1	; 1
	5	[373]	FORPREP  	3 7	; to 13
	6	[374]	GETTABLE 	7 0 -2	; "ticks_candidates"
	7	[374]	GETTABLE 	7 7 6
	8	[374]	LE       	0 1 7
	9	[374]	JMP      	1	; to 11
	10	[375]	JMP      	3	; to 14
	11	[377]	GETTABLE 	7 0 -2	; "ticks_candidates"
	12	[377]	GETTABLE 	2 7 6
	13	[373]	FORLOOP  	3 -8	; to 6
	14	[379]	RETURN   	2 2
	15	[380]	RETURN   	0 1

function <./frontend/apps/reader/skimtowidget.lua:382,387> (9 instructions, 36 bytes at 0x7fa7b2c0ca60)
1 param, 5 slots, 1 upvalue, 1 local, 1 constant, 1 function
	1	[383]	GETUPVAL 	1 0	; UIManager
	2	[383]	SELF     	1 1 -1	; "setDirty"
	3	[383]	LOADNIL  	3 3
	4	[385]	CLOSURE  	4 0	; 0x7fa7b2c0c740
	5	[385]	MOVE     	0 0
	6	[383]	CALL     	1 4 1
	7	[386]	LOADBOOL 	1 1 0
	8	[386]	RETURN   	1 2
	9	[387]	RETURN   	0 1

function <./frontend/apps/reader/skimtowidget.lua:383,385> (6 instructions, 24 bytes at 0x7fa7b2c0c740)
0 params, 2 slots, 1 upvalue, 0 locals, 3 constants, 0 functions
	1	[384]	LOADK    	0 -1	; "ui"
	2	[384]	GETUPVAL 	1 0	; self
	3	[384]	GETTABLE 	1 1 -2	; "skimto_frame"
	4	[384]	GETTABLE 	1 1 -3	; "dimen"
	5	[384]	RETURN   	0 3
	6	[385]	RETURN   	0 1

function <./frontend/apps/reader/skimtowidget.lua:389,394> (9 instructions, 36 bytes at 0x7fa7b2c0c800)
1 param, 5 slots, 1 upvalue, 1 local, 1 constant, 1 function
	1	[390]	GETUPVAL 	1 0	; UIManager
	2	[390]	SELF     	1 1 -1	; "setDirty"
	3	[390]	MOVE     	3 0
	4	[392]	CLOSURE  	4 0	; 0x7fa7b2c0ceb0
	5	[392]	MOVE     	0 0
	6	[390]	CALL     	1 4 1
	7	[393]	LOADBOOL 	1 1 0
	8	[393]	RETURN   	1 2
	9	[394]	RETURN   	0 1

function <./frontend/apps/reader/skimtowidget.lua:390,392> (6 instructions, 24 bytes at 0x7fa7b2c0ceb0)
0 params, 2 slots, 1 upvalue, 0 locals, 3 constants, 0 functions
	1	[391]	LOADK    	0 -1	; "ui"
	2	[391]	GETUPVAL 	1 0	; self
	3	[391]	GETTABLE 	1 1 -2	; "skimto_frame"
	4	[391]	GETTABLE 	1 1 -3	; "dimen"
	5	[391]	RETURN   	0 3
	6	[392]	RETURN   	0 1

function <./frontend/apps/reader/skimtowidget.lua:396,401> (14 instructions, 56 bytes at 0x7fa7b2c0d290)
2 params, 8 slots, 1 upvalue, 2 locals, 7 constants, 0 functions
	1	[397]	SETTABLE 	0 -1 1	; "curr_page" -
	2	[398]	SELF     	2 0 -2	; "addOriginToLocationStack"
	3	[398]	CALL     	2 2 1
	4	[399]	GETTABLE 	2 0 -3	; "ui"
	5	[399]	SELF     	2 2 -4	; "handleEvent"
	6	[399]	GETUPVAL 	4 0	; Event
	7	[399]	SELF     	4 4 -5	; "new"
	8	[399]	LOADK    	6 -6	; "GotoPage"
	9	[399]	GETTABLE 	7 0 -1	; "curr_page"
	10	[399]	CALL     	4 4 0
	11	[399]	CALL     	2 0 1
	12	[400]	SELF     	2 0 -7	; "update"
	13	[400]	CALL     	2 2 1
	14	[401]	RETURN   	0 1

function <./frontend/apps/reader/skimtowidget.lua:403,410> (16 instructions, 64 bytes at 0x7fa7b2c0d440)
2 params, 5 slots, 0 upvalues, 2 locals, 7 constants, 0 functions
	1	[404]	TEST     	1 0 0
	2	[404]	JMP      	13	; to 16
	3	[405]	SELF     	2 0 -1	; "addOriginToLocationStack"
	4	[405]	CALL     	2 2 1
	5	[406]	GETTABLE 	2 0 -2	; "ui"
	6	[406]	GETTABLE 	2 2 -3	; "bookmark"
	7	[406]	SELF     	2 2 -4	; "gotoBookmark"
	8	[406]	MOVE     	4 1
	9	[406]	CALL     	2 3 1
	10	[407]	GETTABLE 	2 0 -2	; "ui"
	11	[407]	SELF     	2 2 -6	; "getCurrentPage"
	12	[407]	CALL     	2 2 2
	13	[407]	SETTABLE 	0 -5 2	; "curr_page" -
	14	[408]	SELF     	2 0 -7	; "update"
	15	[408]	CALL     	2 2 1
	16	[410]	RETURN   	0 1

function <./frontend/apps/reader/skimtowidget.lua:412,415> (7 instructions, 28 bytes at 0x7fa7b2c077e0)
1 param, 4 slots, 1 upvalue, 1 local, 1 constant, 0 functions
	1	[413]	GETUPVAL 	1 0	; UIManager
	2	[413]	SELF     	1 1 -1	; "close"
	3	[413]	MOVE     	3 0
	4	[413]	CALL     	1 3 1
	5	[414]	LOADBOOL 	1 1 0
	6	[414]	RETURN   	1 2
	7	[415]	RETURN   	0 1

function <./frontend/apps/reader/skimtowidget.lua:417,434> (46 instructions, 184 bytes at 0x7fa7b2c07870)
3 params, 11 slots, 2 upvalues, 5 locals, 16 constants, 0 functions
	1	[418]	GETTABLE 	3 2 -1	; "pos"
	2	[418]	SELF     	3 3 -2	; "intersectWith"
	3	[418]	GETTABLE 	5 0 -3	; "progress_bar"
	4	[418]	GETTABLE 	5 5 -4	; "dimen"
	5	[418]	CALL     	3 3 2
	6	[418]	TEST     	3 0 0
	7	[418]	JMP      	27	; to 35
	8	[419]	GETTABLE 	3 0 -3	; "progress_bar"
	9	[419]	SELF     	3 3 -5	; "getPercentageFromPosition"
	10	[419]	GETTABLE 	5 2 -1	; "pos"
	11	[419]	CALL     	3 3 2
	12	[420]	TEST     	3 0 1
	13	[420]	JMP      	2	; to 16
	14	[421]	LOADBOOL 	4 1 0
	15	[421]	RETURN   	4 2
	16	[423]	GETUPVAL 	4 0	; Math
	17	[423]	GETTABLE 	4 4 -6	; "round"
	18	[423]	GETTABLE 	5 0 -7	; "page_count"
	19	[423]	MUL      	5 3 5
	20	[423]	CALL     	4 2 2
	21	[424]	SELF     	5 0 -8	; "addOriginToLocationStack"
	22	[424]	CALL     	5 2 1
	23	[425]	GETTABLE 	5 0 -9	; "ui"
	24	[425]	SELF     	5 5 -10	; "handleEvent"
	25	[425]	GETUPVAL 	7 1	; Event
	26	[425]	SELF     	7 7 -11	; "new"
	27	[425]	LOADK    	9 -12	; "GotoPage"
	28	[425]	MOVE     	10 4
	29	[425]	CALL     	7 4 0
	30	[425]	CALL     	5 0 1
	31	[426]	SETTABLE 	0 -13 4	; "curr_page" -
	32	[427]	SELF     	5 0 -14	; "update"
	33	[427]	CALL     	5 2 1
	34	[427]	JMP      	9	; to 44
	35	[428]	GETTABLE 	3 2 -1	; "pos"
	36	[428]	SELF     	3 3 -2	; "intersectWith"
	37	[428]	GETTABLE 	5 0 -15	; "skimto_frame"
	38	[428]	GETTABLE 	5 5 -4	; "dimen"
	39	[428]	CALL     	3 3 2
	40	[428]	TEST     	3 0 1
	41	[428]	JMP      	2	; to 44
	42	[430]	SELF     	3 0 -16	; "onClose"
	43	[430]	CALL     	3 2 1
	44	[433]	LOADBOOL 	3 1 0
	45	[433]	RETURN   	3 2
	46	[434]	RETURN   	0 1

function <./frontend/apps/reader/skimtowidget.lua:436,439> (7 instructions, 28 bytes at 0x7fa7b2c0de00)
1 param, 4 slots, 1 upvalue, 1 local, 1 constant, 0 functions
	1	[437]	GETUPVAL 	1 0	; UIManager
	2	[437]	SELF     	1 1 -1	; "close"
	3	[437]	MOVE     	3 0
	4	[437]	CALL     	1 3 1
	5	[438]	LOADBOOL 	1 1 0
	6	[438]	RETURN   	1 2
	7	[439]	RETURN   	0 1
