
main <./plugins/evernote.koplugin/slt2.lua:0,0> (32 instructions, 128 bytes at 0x7f8cc5c068d0)
0+ params, 6 slots, 0 upvalues, 5 locals, 9 constants, 8 functions
	1	[10]	NEWTABLE 	0 0 0
	2	[43]	CLOSURE  	1 0	; 0x7f8cc5c06b30
	3	[43]	MOVE     	0 1
	4	[58]	CLOSURE  	2 1	; 0x7f8cc5c070e0
	5	[58]	MOVE     	0 1
	6	[47]	SETTABLE 	0 -1 2	; "precompile" -
	7	[71]	CLOSURE  	2 2	; 0x7f8cc5c07930
	8	[90]	CLOSURE  	3 3	; 0x7f8cc5c087e0
	9	[90]	MOVE     	0 2
	10	[90]	MOVE     	0 1
	11	[74]	SETTABLE 	0 -2 3	; "get_dependency" -
	12	[132]	CLOSURE  	3 4	; 0x7f8cc5c08e00
	13	[132]	MOVE     	0 0
	14	[93]	SETTABLE 	0 -3 3	; "loadstring" -
	15	[140]	CLOSURE  	3 5	; 0x7f8cc5c077f0
	16	[140]	MOVE     	0 0
	17	[135]	SETTABLE 	0 -4 3	; "loadfile" -
	18	[142]	NEWTABLE 	3 0 1
	19	[142]	GETGLOBAL	4 -6	; _ENV
	20	[142]	SETTABLE 	3 -5 4	; "__index" -
	21	[143]	NEWTABLE 	4 0 1
	22	[143]	GETGLOBAL	5 -7	; _G
	23	[143]	SETTABLE 	4 -5 5	; "__index" -
	24	[160]	CLOSURE  	5 6	; 0x7f8cc5c09900
	25	[160]	MOVE     	0 3
	26	[160]	MOVE     	0 4
	27	[146]	SETTABLE 	0 -8 5	; "render_co" -
	28	[174]	CLOSURE  	5 7	; 0x7f8cc5c07f80
	29	[174]	MOVE     	0 0
	30	[163]	SETTABLE 	0 -9 5	; "render" -
	31	[176]	RETURN   	0 2
	32	[176]	RETURN   	0 1

function <./plugins/evernote.koplugin/slt2.lua:14,43> (110 instructions, 440 bytes at 0x7f8cc5c06b30)
5 params, 21 slots, 1 upvalue, 13 locals, 19 constants, 0 functions
	1	[15]	MOVE     	5 4
	2	[15]	CALL     	5 1 2
	3	[17]	TEST     	1 0 1
	4	[17]	JMP      	1	; to 6
	5	[17]	LOADK    	1 -1	; "#{"
	6	[18]	TEST     	2 0 1
	7	[18]	JMP      	1	; to 9
	8	[18]	LOADK    	2 -2	; "}#"
	9	[19]	MOVE     	6 1
	10	[19]	LOADK    	7 -3	; "include:"
	11	[19]	CONCAT   	6 6 7
	12	[21]	GETGLOBAL	7 -4	; string
	13	[21]	GETTABLE 	7 7 -5	; "find"
	14	[21]	MOVE     	8 0
	15	[21]	MOVE     	9 6
	16	[21]	LOADK    	10 -6	; 1
	17	[21]	LOADBOOL 	11 1 0
	18	[21]	CALL     	7 5 3
	19	[22]	LOADNIL  	9 9
	20	[23]	LOADK    	10 -7	; 0
	21	[25]	EQ       	1 7 -8	; - nil
	22	[25]	JMP      	77	; to 100
	23	[26]	ADD      	11 10 -6	; - 1
	24	[26]	LT       	0 11 7
	25	[26]	JMP      	10	; to 36
	26	[27]	MOVE     	11 3
	27	[27]	MOVE     	12 5
	28	[27]	GETGLOBAL	13 -4	; string
	29	[27]	GETTABLE 	13 13 -9	; "sub"
	30	[27]	MOVE     	14 0
	31	[27]	ADD      	15 10 -6	; - 1
	32	[27]	SUB      	16 7 -6	; - 1
	33	[27]	CALL     	13 4 0
	34	[27]	CALL     	11 0 2
	35	[27]	MOVE     	5 11
	36	[29]	GETGLOBAL	11 -4	; string
	37	[29]	GETTABLE 	11 11 -5	; "find"
	38	[29]	MOVE     	12 0
	39	[29]	MOVE     	13 2
	40	[29]	ADD      	14 8 -6	; - 1
	41	[29]	LOADBOOL 	15 1 0
	42	[29]	CALL     	11 5 3
	43	[29]	MOVE     	10 12
	44	[29]	MOVE     	9 11
	45	[30]	GETGLOBAL	11 -10	; assert
	46	[30]	MOVE     	12 9
	47	[30]	LOADK    	13 -11	; "end tag \""
	48	[30]	MOVE     	14 2
	49	[30]	LOADK    	15 -12	; "\" missing"
	50	[30]	CONCAT   	13 13 15
	51	[30]	CALL     	11 3 1
	52	[32]	GETGLOBAL	11 -10	; assert
	53	[32]	GETGLOBAL	12 -13	; loadstring
	54	[32]	LOADK    	13 -14	; "return "
	55	[32]	GETGLOBAL	14 -4	; string
	56	[32]	GETTABLE 	14 14 -9	; "sub"
	57	[32]	MOVE     	15 0
	58	[32]	ADD      	16 8 -6	; - 1
	59	[32]	SUB      	17 9 -6	; - 1
	60	[32]	CALL     	14 4 2
	61	[32]	CONCAT   	13 13 14
	62	[32]	CALL     	12 2 0
	63	[32]	CALL     	11 0 2
	64	[32]	CALL     	11 1 2
	65	[33]	GETGLOBAL	12 -10	; assert
	66	[33]	MOVE     	13 11
	67	[33]	CALL     	12 2 1
	68	[34]	GETGLOBAL	12 -10	; assert
	69	[34]	GETGLOBAL	13 -15	; io
	70	[34]	GETTABLE 	13 13 -16	; "open"
	71	[34]	MOVE     	14 11
	72	[34]	CALL     	13 2 0
	73	[34]	CALL     	12 0 2
	74	[36]	MOVE     	13 3
	75	[36]	MOVE     	14 5
	76	[36]	GETUPVAL 	15 0	; include_fold
	77	[36]	SELF     	16 12 -17	; "read"
	78	[36]	LOADK    	18 -18	; "*a"
	79	[36]	CALL     	16 3 2
	80	[36]	MOVE     	17 1
	81	[36]	MOVE     	18 2
	82	[36]	MOVE     	19 3
	83	[36]	MOVE     	20 4
	84	[36]	CALL     	15 6 2
	85	[36]	MOVE     	16 11
	86	[36]	CALL     	13 4 2
	87	[36]	MOVE     	5 13
	88	[37]	SELF     	13 12 -19	; "close"
	89	[37]	CALL     	13 2 1
	90	[39]	GETGLOBAL	11 -4	; string
	91	[39]	GETTABLE 	11 11 -5	; "find"
	92	[39]	MOVE     	12 0
	93	[39]	MOVE     	13 6
	94	[39]	ADD      	14 10 -6	; - 1
	95	[39]	LOADBOOL 	15 1 0
	96	[39]	CALL     	11 5 3
	97	[39]	MOVE     	8 12
	98	[39]	MOVE     	7 11
	99	[39]	JMP      	-79	; to 21
	100	[41]	MOVE     	11 3
	101	[41]	MOVE     	12 5
	102	[41]	GETGLOBAL	13 -4	; string
	103	[41]	GETTABLE 	13 13 -9	; "sub"
	104	[41]	MOVE     	14 0
	105	[41]	ADD      	15 10 -6	; - 1
	106	[41]	CALL     	13 3 0
	107	[41]	CALL     	11 0 2
	108	[41]	MOVE     	5 11
	109	[42]	RETURN   	5 2
	110	[43]	RETURN   	0 1

function <./plugins/evernote.koplugin/slt2.lua:47,58> (12 instructions, 48 bytes at 0x7f8cc5c070e0)
3 params, 10 slots, 1 upvalue, 3 locals, 2 constants, 2 functions
	1	[48]	GETGLOBAL	3 -1	; table
	2	[48]	GETTABLE 	3 3 -2	; "concat"
	3	[48]	GETUPVAL 	4 0	; include_fold
	4	[48]	MOVE     	5 0
	5	[48]	MOVE     	6 1
	6	[48]	MOVE     	7 2
	7	[57]	CLOSURE  	8 0	; 0x7f8cc5c06a90
	8	[57]	CLOSURE  	9 1	; 0x7f8cc5c07cc0
	9	[48]	CALL     	4 6 0
	10	[48]	TAILCALL 	3 0 0
	11	[57]	RETURN   	3 0
	12	[58]	RETURN   	0 1

function <./plugins/evernote.koplugin/slt2.lua:48,57> (34 instructions, 136 bytes at 0x7f8cc5c06a90)
2 params, 6 slots, 0 upvalues, 2 locals, 7 constants, 0 functions
	1	[49]	GETGLOBAL	2 -1	; type
	2	[49]	MOVE     	3 1
	3	[49]	CALL     	2 2 2
	4	[49]	EQ       	0 2 -2	; - "string"
	5	[49]	JMP      	6	; to 12
	6	[50]	GETGLOBAL	2 -3	; table
	7	[50]	GETTABLE 	2 2 -4	; "insert"
	8	[50]	MOVE     	3 0
	9	[50]	MOVE     	4 1
	10	[50]	CALL     	2 3 1
	11	[50]	JMP      	21	; to 33
	12	[51]	GETGLOBAL	2 -1	; type
	13	[51]	MOVE     	3 1
	14	[51]	CALL     	2 2 2
	15	[51]	EQ       	0 2 -3	; - "table"
	16	[51]	JMP      	9	; to 26
	17	[52]	GETGLOBAL	2 -3	; table
	18	[52]	GETTABLE 	2 2 -4	; "insert"
	19	[52]	MOVE     	3 0
	20	[52]	GETGLOBAL	4 -3	; table
	21	[52]	GETTABLE 	4 4 -5	; "concat"
	22	[52]	MOVE     	5 1
	23	[52]	CALL     	4 2 0
	24	[52]	CALL     	2 0 1
	25	[52]	JMP      	7	; to 33
	26	[54]	GETGLOBAL	2 -6	; error
	27	[54]	LOADK    	3 -7	; "Unknown type: "
	28	[54]	GETGLOBAL	4 -1	; type
	29	[54]	MOVE     	5 1
	30	[54]	CALL     	4 2 2
	31	[54]	CONCAT   	3 3 4
	32	[54]	CALL     	2 2 1
	33	[56]	RETURN   	0 2
	34	[57]	RETURN   	0 1

function <./plugins/evernote.koplugin/slt2.lua:57,57> (3 instructions, 12 bytes at 0x7f8cc5c07cc0)
0 params, 2 slots, 0 upvalues, 0 locals, 0 constants, 0 functions
	1	[57]	NEWTABLE 	0 0 0
	2	[57]	RETURN   	0 2
	3	[57]	RETURN   	0 1

function <./plugins/evernote.koplugin/slt2.lua:61,71> (19 instructions, 76 bytes at 0x7f8cc5c07930)
1 param, 11 slots, 0 upvalues, 8 locals, 4 constants, 0 functions
	1	[62]	NEWTABLE 	1 0 0
	2	[63]	NEWTABLE 	2 0 0
	3	[64]	GETGLOBAL	3 -1	; ipairs
	4	[64]	MOVE     	4 0
	5	[64]	CALL     	3 2 4
	6	[64]	JMP      	9	; to 16
	7	[65]	GETTABLE 	8 1 7
	8	[65]	TEST     	8 0 1
	9	[65]	JMP      	6	; to 16
	10	[66]	GETGLOBAL	8 -2	; table
	11	[66]	GETTABLE 	8 8 -3	; "insert"
	12	[66]	MOVE     	9 2
	13	[66]	MOVE     	10 7
	14	[66]	CALL     	8 3 1
	15	[67]	SETTABLE 	1 7 -4	; - true
	16	[64]	TFORLOOP 	3 2
	17	[68]	JMP      	-11	; to 7
	18	[70]	RETURN   	2 2
	19	[71]	RETURN   	0 1

function <./plugins/evernote.koplugin/slt2.lua:74,90> (11 instructions, 44 bytes at 0x7f8cc5c087e0)
3 params, 10 slots, 2 upvalues, 3 locals, 0 constants, 2 functions
	1	[75]	GETUPVAL 	3 0	; stable_uniq
	2	[75]	GETUPVAL 	4 1	; include_fold
	3	[75]	MOVE     	5 0
	4	[75]	MOVE     	6 1
	5	[75]	MOVE     	7 2
	6	[89]	CLOSURE  	8 0	; 0x7f8cc5c088e0
	7	[89]	CLOSURE  	9 1	; 0x7f8cc5c067c0
	8	[75]	CALL     	4 6 0
	9	[75]	TAILCALL 	3 0 0
	10	[89]	RETURN   	3 0
	11	[90]	RETURN   	0 1

function <./plugins/evernote.koplugin/slt2.lua:75,89> (40 instructions, 160 bytes at 0x7f8cc5c088e0)
3 params, 11 slots, 0 upvalues, 8 locals, 8 constants, 0 functions
	1	[76]	GETGLOBAL	3 -1	; type
	2	[76]	MOVE     	4 1
	3	[76]	CALL     	3 2 2
	4	[76]	EQ       	0 3 -2	; - "string"
	5	[76]	JMP      	2	; to 8
	6	[77]	RETURN   	0 2
	7	[77]	JMP      	31	; to 39
	8	[78]	GETGLOBAL	3 -1	; type
	9	[78]	MOVE     	4 1
	10	[78]	CALL     	3 2 2
	11	[78]	EQ       	0 3 -3	; - "table"
	12	[78]	JMP      	19	; to 32
	13	[79]	EQ       	1 2 -4	; - nil
	14	[79]	JMP      	5	; to 20
	15	[80]	GETGLOBAL	3 -3	; table
	16	[80]	GETTABLE 	3 3 -5	; "insert"
	17	[80]	MOVE     	4 0
	18	[80]	MOVE     	5 2
	19	[80]	CALL     	3 3 1
	20	[82]	GETGLOBAL	3 -6	; ipairs
	21	[82]	MOVE     	4 1
	22	[82]	CALL     	3 2 4
	23	[82]	JMP      	5	; to 29
	24	[83]	GETGLOBAL	8 -3	; table
	25	[83]	GETTABLE 	8 8 -5	; "insert"
	26	[83]	MOVE     	9 0
	27	[83]	MOVE     	10 7
	28	[83]	CALL     	8 3 1
	29	[82]	TFORLOOP 	3 2
	30	[83]	JMP      	-7	; to 24
	31	[84]	JMP      	7	; to 39
	32	[86]	GETGLOBAL	3 -7	; error
	33	[86]	LOADK    	4 -8	; "Unknown type: "
	34	[86]	GETGLOBAL	5 -1	; type
	35	[86]	MOVE     	6 1
	36	[86]	CALL     	5 2 2
	37	[86]	CONCAT   	4 4 5
	38	[86]	CALL     	3 2 1
	39	[88]	RETURN   	0 2
	40	[89]	RETURN   	0 1

function <./plugins/evernote.koplugin/slt2.lua:89,89> (3 instructions, 12 bytes at 0x7f8cc5c067c0)
0 params, 2 slots, 0 upvalues, 0 locals, 0 constants, 0 functions
	1	[89]	NEWTABLE 	0 0 0
	2	[89]	RETURN   	0 2
	3	[89]	RETURN   	0 1

function <./plugins/evernote.koplugin/slt2.lua:93,132> (155 instructions, 620 bytes at 0x7f8cc5c08e00)
4 params, 21 slots, 1 upvalue, 12 locals, 29 constants, 0 functions
	1	[95]	NEWTABLE 	4 0 0
	2	[97]	TEST     	1 0 1
	3	[97]	JMP      	1	; to 5
	4	[97]	LOADK    	1 -1	; "#{"
	5	[98]	TEST     	2 0 1
	6	[98]	JMP      	1	; to 8
	7	[98]	LOADK    	2 -2	; "}#"
	8	[100]	LOADK    	5 -3	; "coroutine.yield"
	9	[102]	GETUPVAL 	6 0	; slt2
	10	[102]	GETTABLE 	6 6 -4	; "precompile"
	11	[102]	MOVE     	7 0
	12	[102]	MOVE     	8 1
	13	[102]	MOVE     	9 2
	14	[102]	CALL     	6 4 2
	15	[102]	MOVE     	0 6
	16	[104]	GETGLOBAL	6 -5	; string
	17	[104]	GETTABLE 	6 6 -6	; "find"
	18	[104]	MOVE     	7 0
	19	[104]	MOVE     	8 1
	20	[104]	LOADK    	9 -7	; 1
	21	[104]	LOADBOOL 	10 1 0
	22	[104]	CALL     	6 5 3
	23	[105]	LOADNIL  	8 8
	24	[106]	LOADK    	9 -8	; 0
	25	[108]	GETGLOBAL	10 -5	; string
	26	[108]	GETTABLE 	10 10 -9	; "byte"
	27	[108]	LOADK    	11 -10	; "="
	28	[108]	LOADK    	12 -7	; 1
	29	[108]	CALL     	10 3 2
	30	[110]	EQ       	1 6 -11	; - nil
	31	[110]	JMP      	79	; to 111
	32	[111]	ADD      	11 9 -7	; - 1
	33	[111]	LT       	0 11 6
	34	[111]	JMP      	18	; to 53
	35	[112]	GETGLOBAL	11 -12	; table
	36	[112]	GETTABLE 	11 11 -13	; "insert"
	37	[112]	MOVE     	12 4
	38	[112]	MOVE     	13 5
	39	[112]	LOADK    	14 -14	; "("
	40	[112]	GETGLOBAL	15 -5	; string
	41	[112]	GETTABLE 	15 15 -15	; "format"
	42	[112]	LOADK    	16 -16	; "%q"
	43	[112]	GETGLOBAL	17 -5	; string
	44	[112]	GETTABLE 	17 17 -17	; "sub"
	45	[112]	MOVE     	18 0
	46	[112]	ADD      	19 9 -7	; - 1
	47	[112]	SUB      	20 6 -7	; - 1
	48	[112]	CALL     	17 4 0
	49	[112]	CALL     	15 0 2
	50	[112]	LOADK    	16 -18	; ")"
	51	[112]	CONCAT   	13 13 16
	52	[112]	CALL     	11 3 1
	53	[114]	GETGLOBAL	11 -5	; string
	54	[114]	GETTABLE 	11 11 -6	; "find"
	55	[114]	MOVE     	12 0
	56	[114]	MOVE     	13 2
	57	[114]	ADD      	14 7 -7	; - 1
	58	[114]	LOADBOOL 	15 1 0
	59	[114]	CALL     	11 5 3
	60	[114]	MOVE     	9 12
	61	[114]	MOVE     	8 11
	62	[115]	GETGLOBAL	11 -19	; assert
	63	[115]	MOVE     	12 8
	64	[115]	LOADK    	13 -20	; "end_tag \""
	65	[115]	MOVE     	14 2
	66	[115]	LOADK    	15 -21	; "\" missing"
	67	[115]	CONCAT   	13 13 15
	68	[115]	CALL     	11 3 1
	69	[116]	GETGLOBAL	11 -5	; string
	70	[116]	GETTABLE 	11 11 -9	; "byte"
	71	[116]	MOVE     	12 0
	72	[116]	ADD      	13 7 -7	; - 1
	73	[116]	CALL     	11 3 2
	74	[116]	EQ       	0 11 10
	75	[116]	JMP      	15	; to 91
	76	[117]	GETGLOBAL	11 -12	; table
	77	[117]	GETTABLE 	11 11 -13	; "insert"
	78	[117]	MOVE     	12 4
	79	[117]	MOVE     	13 5
	80	[117]	LOADK    	14 -14	; "("
	81	[117]	GETGLOBAL	15 -5	; string
	82	[117]	GETTABLE 	15 15 -17	; "sub"
	83	[117]	MOVE     	16 0
	84	[117]	ADD      	17 7 -22	; - 2
	85	[117]	SUB      	18 8 -7	; - 1
	86	[117]	CALL     	15 4 2
	87	[117]	LOADK    	16 -18	; ")"
	88	[117]	CONCAT   	13 13 16
	89	[117]	CALL     	11 3 1
	90	[117]	JMP      	10	; to 101
	91	[119]	GETGLOBAL	11 -12	; table
	92	[119]	GETTABLE 	11 11 -13	; "insert"
	93	[119]	MOVE     	12 4
	94	[119]	GETGLOBAL	13 -5	; string
	95	[119]	GETTABLE 	13 13 -17	; "sub"
	96	[119]	MOVE     	14 0
	97	[119]	ADD      	15 7 -7	; - 1
	98	[119]	SUB      	16 8 -7	; - 1
	99	[119]	CALL     	13 4 0
	100	[119]	CALL     	11 0 1
	101	[121]	GETGLOBAL	11 -5	; string
	102	[121]	GETTABLE 	11 11 -6	; "find"
	103	[121]	MOVE     	12 0
	104	[121]	MOVE     	13 1
	105	[121]	ADD      	14 9 -7	; - 1
	106	[121]	LOADBOOL 	15 1 0
	107	[121]	CALL     	11 5 3
	108	[121]	MOVE     	7 12
	109	[121]	MOVE     	6 11
	110	[121]	JMP      	-81	; to 30
	111	[123]	GETGLOBAL	11 -12	; table
	112	[123]	GETTABLE 	11 11 -13	; "insert"
	113	[123]	MOVE     	12 4
	114	[123]	MOVE     	13 5
	115	[123]	LOADK    	14 -14	; "("
	116	[123]	GETGLOBAL	15 -5	; string
	117	[123]	GETTABLE 	15 15 -15	; "format"
	118	[123]	LOADK    	16 -16	; "%q"
	119	[123]	GETGLOBAL	17 -5	; string
	120	[123]	GETTABLE 	17 17 -17	; "sub"
	121	[123]	MOVE     	18 0
	122	[123]	ADD      	19 9 -7	; - 1
	123	[123]	CALL     	17 3 0
	124	[123]	CALL     	15 0 2
	125	[123]	LOADK    	16 -18	; ")"
	126	[123]	CONCAT   	13 13 16
	127	[123]	CALL     	11 3 1
	128	[125]	NEWTABLE 	11 0 1
	129	[125]	TESTSET  	12 3 1
	130	[125]	JMP      	1	; to 132
	131	[125]	LOADK    	12 -24	; "=(slt2.loadstring)"
	132	[125]	SETTABLE 	11 -23 12	; "name" -
	133	[126]	GETGLOBAL	12 -25	; setfenv
	134	[126]	EQ       	0 12 -11	; - nil
	135	[126]	JMP      	7	; to 143
	136	[127]	GETGLOBAL	12 -12	; table
	137	[127]	GETTABLE 	12 12 -27	; "concat"
	138	[127]	MOVE     	13 4
	139	[127]	LOADK    	14 -28	; "\n"
	140	[127]	CALL     	12 3 2
	141	[127]	SETTABLE 	11 -26 12	; "code" -
	142	[127]	JMP      	11	; to 154
	143	[129]	GETGLOBAL	12 -19	; assert
	144	[129]	GETGLOBAL	13 -29	; loadstring
	145	[129]	GETGLOBAL	14 -12	; table
	146	[129]	GETTABLE 	14 14 -27	; "concat"
	147	[129]	MOVE     	15 4
	148	[129]	LOADK    	16 -28	; "\n"
	149	[129]	CALL     	14 3 2
	150	[129]	GETTABLE 	15 11 -23	; "name"
	151	[129]	CALL     	13 3 0
	152	[129]	CALL     	12 0 2
	153	[129]	SETTABLE 	11 -26 12	; "code" -
	154	[131]	RETURN   	11 2
	155	[132]	RETURN   	0 1

function <./plugins/evernote.koplugin/slt2.lua:135,140> (20 instructions, 80 bytes at 0x7f8cc5c077f0)
3 params, 10 slots, 1 upvalue, 5 locals, 7 constants, 0 functions
	1	[136]	GETGLOBAL	3 -1	; assert
	2	[136]	GETGLOBAL	4 -2	; io
	3	[136]	GETTABLE 	4 4 -3	; "open"
	4	[136]	MOVE     	5 0
	5	[136]	CALL     	4 2 0
	6	[136]	CALL     	3 0 2
	7	[137]	SELF     	4 3 -4	; "read"
	8	[137]	LOADK    	6 -5	; "*a"
	9	[137]	CALL     	4 3 2
	10	[138]	SELF     	5 3 -6	; "close"
	11	[138]	CALL     	5 2 1
	12	[139]	GETUPVAL 	5 0	; slt2
	13	[139]	GETTABLE 	5 5 -7	; "loadstring"
	14	[139]	MOVE     	6 4
	15	[139]	MOVE     	7 1
	16	[139]	MOVE     	8 2
	17	[139]	MOVE     	9 0
	18	[139]	TAILCALL 	5 5 0
	19	[139]	RETURN   	5 0
	20	[140]	RETURN   	0 1

function <./plugins/evernote.koplugin/slt2.lua:146,160> (36 instructions, 144 bytes at 0x7f8cc5c09900)
2 params, 9 slots, 2 upvalues, 3 locals, 10 constants, 0 functions
	1	[148]	GETGLOBAL	3 -1	; setfenv
	2	[148]	EQ       	0 3 -2	; - nil
	3	[148]	JMP      	18	; to 22
	4	[149]	EQ       	1 1 -2	; - nil
	5	[149]	JMP      	4	; to 10
	6	[150]	GETGLOBAL	3 -3	; setmetatable
	7	[150]	MOVE     	4 1
	8	[150]	GETUPVAL 	5 0	; mt52
	9	[150]	CALL     	3 3 1
	10	[152]	GETGLOBAL	3 -4	; assert
	11	[152]	GETGLOBAL	4 -5	; load
	12	[152]	GETTABLE 	5 0 -6	; "code"
	13	[152]	GETTABLE 	6 0 -7	; "name"
	14	[152]	LOADK    	7 -8	; "t"
	15	[152]	TESTSET  	8 1 1
	16	[152]	JMP      	1	; to 18
	17	[152]	GETGLOBAL	8 -9	; _ENV
	18	[152]	CALL     	4 5 0
	19	[152]	CALL     	3 0 2
	20	[152]	MOVE     	2 3
	21	[152]	JMP      	13	; to 35
	22	[154]	EQ       	1 1 -2	; - nil
	23	[154]	JMP      	4	; to 28
	24	[155]	GETGLOBAL	3 -3	; setmetatable
	25	[155]	MOVE     	4 1
	26	[155]	GETUPVAL 	5 1	; mt51
	27	[155]	CALL     	3 3 1
	28	[157]	GETGLOBAL	3 -1	; setfenv
	29	[157]	GETTABLE 	4 0 -6	; "code"
	30	[157]	TESTSET  	5 1 1
	31	[157]	JMP      	1	; to 33
	32	[157]	GETGLOBAL	5 -10	; _G
	33	[157]	CALL     	3 3 2
	34	[157]	MOVE     	2 3
	35	[159]	RETURN   	2 2
	36	[160]	RETURN   	0 1

function <./plugins/evernote.koplugin/slt2.lua:163,174> (36 instructions, 144 bytes at 0x7f8cc5c07f80)
2 params, 9 slots, 1 upvalue, 6 locals, 10 constants, 0 functions
	1	[164]	NEWTABLE 	2 0 0
	2	[165]	GETGLOBAL	3 -1	; coroutine
	3	[165]	GETTABLE 	3 3 -2	; "create"
	4	[165]	GETUPVAL 	4 0	; slt2
	5	[165]	GETTABLE 	4 4 -3	; "render_co"
	6	[165]	MOVE     	5 0
	7	[165]	MOVE     	6 1
	8	[165]	CALL     	4 3 0
	9	[165]	CALL     	3 0 2
	10	[166]	GETGLOBAL	4 -1	; coroutine
	11	[166]	GETTABLE 	4 4 -4	; "status"
	12	[166]	MOVE     	5 3
	13	[166]	CALL     	4 2 2
	14	[166]	EQ       	1 4 -5	; - "dead"
	15	[166]	JMP      	15	; to 31
	16	[167]	GETGLOBAL	4 -1	; coroutine
	17	[167]	GETTABLE 	4 4 -6	; "resume"
	18	[167]	MOVE     	5 3
	19	[167]	CALL     	4 2 3
	20	[168]	TEST     	4 0 1
	21	[168]	JMP      	3	; to 25
	22	[169]	GETGLOBAL	6 -7	; error
	23	[169]	MOVE     	7 5
	24	[169]	CALL     	6 2 1
	25	[171]	GETGLOBAL	6 -8	; table
	26	[171]	GETTABLE 	6 6 -9	; "insert"
	27	[171]	MOVE     	7 2
	28	[171]	MOVE     	8 5
	29	[171]	CALL     	6 3 1
	30	[171]	JMP      	-21	; to 10
	31	[173]	GETGLOBAL	4 -8	; table
	32	[173]	GETTABLE 	4 4 -10	; "concat"
	33	[173]	MOVE     	5 2
	34	[173]	TAILCALL 	4 2 0
	35	[173]	RETURN   	4 0
	36	[174]	RETURN   	0 1
