-- BYTECODE -- streammessagequeue.lua:15-31
0001    UGET     1   0      ; czmq
0002    TGETS    1   1   1  ; "zctx_new"
0003    CALL     1   2   1
0004    TSETS    1   0   0  ; "context"
0005    UGET     1   0      ; czmq
0006    TGETS    1   1   3  ; "zsocket_new"
0007    TGETS    2   0   0  ; "context"
0008    UGET     3   1      ; C
0009    TGETS    3   3   4  ; "ZMQ_STREAM"
0010    CALL     1   2   3
0011    TSETS    1   0   2  ; "socket"
0012    UGET     1   0      ; czmq
0013    TGETS    1   1   6  ; "zpoller_new"
0014    TGETS    2   0   2  ; "socket"
0015    KPRI     3   0
0016    CALL     1   2   3
0017    TSETS    1   0   5  ; "poller"
0018    GGET     1   7      ; "string"
0019    TGETS    1   1   8  ; "format"
0020    KSTR     2   9      ; "tcp://%s:%d"
0021    TGETS    3   0  10  ; "host"
0022    TGETS    4   0  11  ; "port"
0023    CALL     1   2   4
0024    UGET     2   2      ; logger
0025    TGETS    2   2  12  ; "warn"
0026    KSTR     3  13      ; "connect to endpoint"
0027    MOV      4   1
0028    CALL     2   1   3
0029    UGET     2   0      ; czmq
0030    TGETS    2   2  14  ; "zsocket_connect"
0031    TGETS    3   0   2  ; "socket"
0032    MOV      4   1
0033    CALL     2   2   3
0034    ISEQN    2   0      ; 0
0035    JMP      3 => 0041
0036    GGET     3  15      ; "error"
0037    KSTR     4  16      ; "cannot connect to "
0038    MOV      5   1
0039    CAT      4   4   5
0040    CALL     3   1   2
0041 => UGET     3   3      ; ffi
0042    TGETS    3   3  17  ; "new"
0043    KSTR     4  18      ; "size_t[1]"
0044    KSHORT   5 256
0045    CALL     3   2   3
0046    UGET     4   3      ; ffi
0047    TGETS    4   4  17  ; "new"
0048    KSTR     5  19      ; "uint8_t[?]"
0049    TGETB    6   3   0
0050    CALL     4   2   3
0051    UGET     5   4      ; zmq
0052    TGETS    5   5  20  ; "zmq_getsockopt"
0053    TGETS    6   0   2  ; "socket"
0054    UGET     7   1      ; C
0055    TGETS    7   7  21  ; "ZMQ_IDENTITY"
0056    MOV      8   4
0057    MOV      9   3
0058    CALL     5   1   5
0059    UGET     5   3      ; ffi
0060    TGETS    5   5   7  ; "string"
0061    MOV      6   4
0062    TGETB    7   3   0
0063    CALL     5   2   3
0064    TSETS    5   0  22  ; "id"
0065    UGET     5   2      ; logger
0066    TGETS    5   5  23  ; "dbg"
0067    KSTR     6  22      ; "id"
0068    TGETS    7   0  22  ; "id"
0069    LEN      7   7
0070    TGETS    8   0  22  ; "id"
0071    CALL     5   1   4
0072    RET0     0   1

-- BYTECODE -- streammessagequeue.lua:33-43
0001    TGETS    1   0   0  ; "poller"
0002    ISEQP    1   0
0003    JMP      1 => 0012
0004    UGET     1   0      ; czmq
0005    TGETS    1   1   1  ; "zpoller_destroy"
0006    UGET     2   1      ; ffi
0007    TGETS    2   2   2  ; "new"
0008    KSTR     3   3      ; "zpoller_t *[1]"
0009    TGETS    4   0   0  ; "poller"
0010    CALL     2   0   3
0011    CALLM    1   1   0
0012 => TGETS    1   0   4  ; "socket"
0013    ISEQP    1   0
0014    JMP      1 => 0020
0015    UGET     1   0      ; czmq
0016    TGETS    1   1   5  ; "zsocket_destroy"
0017    TGETS    2   0   6  ; "context"
0018    TGETS    3   0   4  ; "socket"
0019    CALL     1   1   3
0020 => TGETS    1   0   6  ; "context"
0021    ISEQP    1   0
0022    JMP      1 => 0031
0023    UGET     1   0      ; czmq
0024    TGETS    1   1   7  ; "zctx_destroy"
0025    UGET     2   1      ; ffi
0026    TGETS    2   2   2  ; "new"
0027    KSTR     3   8      ; "zctx_t *[1]"
0028    TGETS    4   0   6  ; "context"
0029    CALL     2   0   3
0030    CALLM    1   1   0
0031 => RET0     0   1

-- BYTECODE -- streammessagequeue.lua:45-56
0001    UGET     2   0      ; czmq
0002    TGETS    2   2   0  ; "zframe_size"
0003    MOV      3   1
0004    CALL     2   2   2
0005    KPRI     3   0
0006    KSHORT   4   0
0007    ISGE     4   2
0008    JMP      4 => 0021
0009    UGET     4   0      ; czmq
0010    TGETS    4   4   1  ; "zframe_data"
0011    MOV      5   1
0012    CALL     4   2   2
0013    ISEQP    4   0
0014    JMP      5 => 0021
0015    UGET     5   1      ; ffi
0016    TGETS    5   5   2  ; "string"
0017    MOV      6   4
0018    MOV      7   2
0019    CALL     5   2   3
0020    MOV      3   5
0021 => UGET     4   0      ; czmq
0022    TGETS    4   4   3  ; "zframe_destroy"
0023    UGET     5   1      ; ffi
0024    TGETS    5   5   4  ; "new"
0025    KSTR     6   5      ; "zframe_t *[1]"
0026    MOV      7   1
0027    CALL     5   0   3
0028    CALLM    4   1   0
0029    RET1     3   2

-- BYTECODE -- streammessagequeue.lua:58-80
0001    KSTR     1   0      ; ""
0002    KSHORT   2  10
0003 => UGET     3   0      ; czmq
0004    TGETS    3   3   1  ; "zpoller_wait"
0005    TGETS    4   0   2  ; "poller"
0006    KSHORT   5   0
0007    CALL     3   2   3
0008    ISEQP    3   0
0009    JMP      3 => 0041
0010    KSHORT   3   0
0011    ISGE     3   2
0012    JMP      3 => 0041
0013    LOOP     3 => 0041
0014    UGET     3   0      ; czmq
0015    TGETS    3   3   3  ; "zframe_recv"
0016    TGETS    4   0   4  ; "socket"
0017    CALL     3   2   2
0018    ISEQP    3   0
0019    JMP      4 => 0024
0020    MOV      5   0
0021    TGETS    4   0   5  ; "handleZframe"
0022    MOV      6   3
0023    CALL     4   1   3
0024 => UGET     4   0      ; czmq
0025    TGETS    4   4   3  ; "zframe_recv"
0026    TGETS    5   0   4  ; "socket"
0027    CALL     4   2   2
0028    ISEQP    4   0
0029    JMP      5 => 0039
0030    MOV      5   1
0031    MOV      7   0
0032    TGETS    6   0   5  ; "handleZframe"
0033    MOV      8   4
0034    CALL     6   2   3
0035    IST          6
0036    JMP      7 => 0038
0037    KSTR     6   0      ; ""
0038 => CAT      1   5   6
0039 => SUBVN    2   2   0  ; 1
0040    JMP      3 => 0003
0041 => TGETS    3   0   6  ; "receiveCallback"
0042    ISF          3
0043    JMP      4 => 0049
0044    ISEQS    1   0      ; ""
0045    JMP      3 => 0049
0046    TGETS    3   0   6  ; "receiveCallback"
0047    MOV      4   1
0048    CALL     3   1   2
0049 => RET0     0   1

-- BYTECODE -- streammessagequeue.lua:82-87
0001    UGET     2   0      ; czmq
0002    TGETS    2   2   0  ; "zmsg_new"
0003    CALL     2   2   1
0004    UGET     3   0      ; czmq
0005    TGETS    3   3   1  ; "zmsg_addmem"
0006    MOV      4   2
0007    TGETS    5   0   2  ; "id"
0008    TGETS    6   0   2  ; "id"
0009    LEN      6   6
0010    CALL     3   1   4
0011    UGET     3   0      ; czmq
0012    TGETS    3   3   1  ; "zmsg_addmem"
0013    MOV      4   2
0014    MOV      5   1
0015    LEN      6   1
0016    CALL     3   1   4
0017    UGET     3   0      ; czmq
0018    TGETS    3   3   3  ; "zmsg_send"
0019    UGET     4   1      ; ffi
0020    TGETS    4   4   4  ; "new"
0021    KSTR     5   5      ; "zmsg_t *[1]"
0022    MOV      6   2
0023    CALL     4   2   3
0024    TGETS    5   0   6  ; "socket"
0025    CALL     3   1   3
0026    RET0     0   1

-- BYTECODE -- streammessagequeue.lua:0-90
0001    GGET     0   0      ; "require"
0002    KSTR     1   1      ; "ffi"
0003    CALL     0   2   2
0004    GGET     1   0      ; "require"
0005    KSTR     2   2      ; "logger"
0006    CALL     1   2   2
0007    GGET     2   0      ; "require"
0008    KSTR     3   3      ; "ui/message/messagequeue"
0009    CALL     2   2   2
0010    GGET     3   0      ; "require"
0011    KSTR     4   4      ; "ffi/zeromq_h"
0012    CALL     3   2   2
0013    TGETS    4   0   5  ; "load"
0014    KSTR     5   6      ; "libs/libzmq.so.4"
0015    CALL     4   2   2
0016    TGETS    5   0   5  ; "load"
0017    KSTR     6   7      ; "libs/libczmq.so.1"
0018    CALL     5   2   2
0019    TGETS    6   0   8  ; "C"
0020    MOV      8   2
0021    TGETS    7   2   9  ; "new"
0022    TDUP     9  10
0023    CALL     7   2   3
0024    FNEW     8  12      ; streammessagequeue.lua:15
0025    TSETS    8   7  11  ; "start"
0026    FNEW     8  14      ; streammessagequeue.lua:33
0027    TSETS    8   7  13  ; "stop"
0028    FNEW     8  16      ; streammessagequeue.lua:45
0029    TSETS    8   7  15  ; "handleZframe"
0030    FNEW     8  18      ; streammessagequeue.lua:58
0031    TSETS    8   7  17  ; "waitEvent"
0032    FNEW     8  20      ; streammessagequeue.lua:82
0033    TSETS    8   7  19  ; "send"
0034    UCLO     0 => 0035
0035 => RET1     7   2

