
main <./spec/unit/switch_plugin_spec.lua:0,0> (5 instructions, 20 bytes at 0x7fb9cb4068d0)
0+ params, 3 slots, 0 upvalues, 0 locals, 2 constants, 1 function
	1	[1]	GETGLOBAL	0 -1	; describe
	2	[1]	LOADK    	1 -2	; "SwitchPlugin"
	3	[165]	CLOSURE  	2 0	; 0x7fb9cb406b70
	4	[1]	CALL     	0 3 1
	5	[165]	RETURN   	0 1

function <./spec/unit/switch_plugin_spec.lua:1,165> (48 instructions, 192 bytes at 0x7fb9cb406b70)
0 params, 6 slots, 0 upvalues, 3 locals, 14 constants, 10 functions
	1	[2]	GETGLOBAL	0 -1	; require
	2	[2]	LOADK    	1 -2	; "commonrequire"
	3	[2]	CALL     	0 2 1
	4	[3]	GETGLOBAL	0 -1	; require
	5	[3]	LOADK    	1 -3	; "ui/plugin/switch_plugin"
	6	[3]	CALL     	0 2 2
	7	[19]	CLOSURE  	1 0	; 0x7fb9cb406f00
	8	[19]	MOVE     	0 0
	9	[21]	SELF     	2 0 -4	; "extend"
	10	[21]	CALL     	2 2 2
	11	[33]	CLOSURE  	3 1	; 0x7fb9cb406e40
	12	[33]	MOVE     	0 0
	13	[23]	SETTABLE 	2 -5 3	; "new" -
	14	[37]	CLOSURE  	3 2	; 0x7fb9cb407c30
	15	[35]	SETTABLE 	2 -6 3	; "_start" -
	16	[41]	CLOSURE  	3 3	; 0x7fb9cb407cf0
	17	[39]	SETTABLE 	2 -7 3	; "_stop" -
	18	[43]	GETGLOBAL	3 -8	; it
	19	[43]	LOADK    	4 -9	; "should be able to create a enabled plugin"
	20	[66]	CLOSURE  	5 4	; 0x7fb9cb406dc0
	21	[66]	MOVE     	0 1
	22	[43]	CALL     	3 3 1
	23	[68]	GETGLOBAL	3 -8	; it
	24	[68]	LOADK    	4 -10	; "should be able to create a disabled plugin"
	25	[87]	CLOSURE  	5 5	; 0x7fb9cb408c30
	26	[87]	MOVE     	0 1
	27	[68]	CALL     	3 3 1
	28	[89]	GETGLOBAL	3 -8	; it
	29	[89]	LOADK    	4 -11	; "should be able to create a derived enabled plugin"
	30	[105]	CLOSURE  	5 6	; 0x7fb9cb4087b0
	31	[105]	MOVE     	0 2
	32	[89]	CALL     	3 3 1
	33	[107]	GETGLOBAL	3 -8	; it
	34	[107]	LOADK    	4 -12	; "should be able to create a derived disabled plugin"
	35	[117]	CLOSURE  	5 7	; 0x7fb9cb407db0
	36	[117]	MOVE     	0 2
	37	[107]	CALL     	3 3 1
	38	[119]	GETGLOBAL	3 -8	; it
	39	[119]	LOADK    	4 -13	; "should be able to create an invisible plugin"
	40	[131]	CLOSURE  	5 8	; 0x7fb9cb407380
	41	[131]	MOVE     	0 0
	42	[119]	CALL     	3 3 1
	43	[133]	GETGLOBAL	3 -8	; it
	44	[133]	LOADK    	4 -14	; "should show a correct message box"
	45	[164]	CLOSURE  	5 9	; 0x7fb9cb407e70
	46	[164]	MOVE     	0 2
	47	[133]	CALL     	3 3 1
	48	[165]	RETURN   	0 1

function <./spec/unit/switch_plugin_spec.lua:5,19> (17 instructions, 68 bytes at 0x7fb9cb406f00)
3 params, 7 slots, 1 upvalue, 3 locals, 12 constants, 2 functions
	1	[6]	GETUPVAL 	3 0	; SwitchPlugin
	2	[6]	SELF     	3 3 -1	; "new"
	3	[6]	NEWTABLE 	5 0 7
	4	[7]	SETTABLE 	5 -2 -3	; "name" "test_plugin"
	5	[8]	SETTABLE 	5 -4 -5	; "menu_item" "test_plugin_menu"
	6	[9]	SETTABLE 	5 -6 -7	; "menu_text" "This is a test plugin"
	7	[10]	SETTABLE 	5 -8 -9	; "confirm_message" "This is a test plugin, it's for test purpose only."
	8	[11]	SETTABLE 	5 -10 0	; "default_enable" -
	9	[14]	CLOSURE  	6 0	; 0x7fb9cb407150
	10	[14]	MOVE     	0 1
	11	[14]	SETTABLE 	5 -11 6	; "_start" -
	12	[17]	CLOSURE  	6 1	; 0x7fb9cb407300
	13	[17]	MOVE     	0 2
	14	[17]	SETTABLE 	5 -12 6	; "_stop" -
	15	[6]	TAILCALL 	3 3 0
	16	[18]	RETURN   	3 0
	17	[19]	RETURN   	0 1

function <./spec/unit/switch_plugin_spec.lua:12,14> (3 instructions, 12 bytes at 0x7fb9cb407150)
0 params, 2 slots, 1 upvalue, 0 locals, 0 constants, 0 functions
	1	[13]	GETUPVAL 	0 0	; start
	2	[13]	CALL     	0 1 1
	3	[14]	RETURN   	0 1

function <./spec/unit/switch_plugin_spec.lua:15,17> (3 instructions, 12 bytes at 0x7fb9cb407300)
0 params, 2 slots, 1 upvalue, 0 locals, 0 constants, 0 functions
	1	[16]	GETUPVAL 	0 0	; stop
	2	[16]	CALL     	0 1 1
	3	[17]	RETURN   	0 1

function <./spec/unit/switch_plugin_spec.lua:23,33> (18 instructions, 72 bytes at 0x7fb9cb406e40)
2 params, 5 slots, 1 upvalue, 2 locals, 12 constants, 0 functions
	1	[24]	TEST     	1 0 1
	2	[24]	JMP      	2	; to 5
	3	[24]	NEWTABLE 	2 0 0
	4	[24]	MOVE     	1 2
	5	[25]	SETTABLE 	1 -1 -2	; "name" "test_plugin2"
	6	[26]	SETTABLE 	1 -3 -4	; "menu_item" "test_plugin2_menu"
	7	[27]	SETTABLE 	1 -5 -6	; "menu_text" "This is a test plugin2"
	8	[28]	SETTABLE 	1 -7 -8	; "confirm_message" "This is a test plugin2, it's for test purpose only."
	9	[29]	SETTABLE 	1 -9 -10	; "start_called" 0
	10	[30]	SETTABLE 	1 -11 -10	; "stop_called" 0
	11	[31]	GETUPVAL 	2 0	; SwitchPlugin
	12	[31]	GETTABLE 	2 2 -12	; "new"
	13	[31]	MOVE     	3 0
	14	[31]	MOVE     	4 1
	15	[31]	CALL     	2 3 2
	16	[31]	MOVE     	1 2
	17	[32]	RETURN   	1 2
	18	[33]	RETURN   	0 1

function <./spec/unit/switch_plugin_spec.lua:35,37> (4 instructions, 16 bytes at 0x7fb9cb407c30)
1 param, 2 slots, 0 upvalues, 1 local, 2 constants, 0 functions
	1	[36]	GETTABLE 	1 0 -1	; "start_called"
	2	[36]	ADD      	1 1 -2	; - 1
	3	[36]	SETTABLE 	0 -1 1	; "start_called" -
	4	[37]	RETURN   	0 1

function <./spec/unit/switch_plugin_spec.lua:39,41> (4 instructions, 16 bytes at 0x7fb9cb407cf0)
1 param, 2 slots, 0 upvalues, 1 local, 2 constants, 0 functions
	1	[40]	GETTABLE 	1 0 -1	; "stop_called"
	2	[40]	ADD      	1 1 -2	; - 1
	3	[40]	SETTABLE 	0 -1 1	; "stop_called" -
	4	[41]	RETURN   	0 1

function <./spec/unit/switch_plugin_spec.lua:43,66> (61 instructions, 244 bytes at 0x7fb9cb406dc0)
0 params, 7 slots, 1 upvalue, 4 locals, 11 constants, 2 functions
	1	[44]	LOADK    	0 -1	; 0
	2	[45]	LOADK    	1 -1	; 0
	3	[46]	GETUPVAL 	2 0	; createTestPlugin
	4	[47]	LOADBOOL 	3 1 0
	5	[50]	CLOSURE  	4 0	; 0x7fb9cb408400
	6	[50]	MOVE     	0 0
	7	[53]	CLOSURE  	5 1	; 0x7fb9cb4084f0
	8	[53]	MOVE     	0 1
	9	[46]	CALL     	2 4 2
	10	[54]	GETGLOBAL	3 -2	; assert
	11	[54]	GETTABLE 	3 3 -3	; "are"
	12	[54]	GETTABLE 	3 3 -4	; "equal"
	13	[54]	LOADK    	4 -5	; 1
	14	[54]	MOVE     	5 0
	15	[54]	CALL     	3 3 1
	16	[55]	GETGLOBAL	3 -2	; assert
	17	[55]	GETTABLE 	3 3 -3	; "are"
	18	[55]	GETTABLE 	3 3 -4	; "equal"
	19	[55]	LOADK    	4 -1	; 0
	20	[55]	MOVE     	5 1
	21	[55]	CALL     	3 3 1
	22	[56]	SELF     	3 2 -6	; "flipSetting"
	23	[56]	CALL     	3 2 1
	24	[57]	GETGLOBAL	3 -2	; assert
	25	[57]	GETTABLE 	3 3 -3	; "are"
	26	[57]	GETTABLE 	3 3 -4	; "equal"
	27	[57]	LOADK    	4 -5	; 1
	28	[57]	MOVE     	5 0
	29	[57]	CALL     	3 3 1
	30	[58]	GETGLOBAL	3 -2	; assert
	31	[58]	GETTABLE 	3 3 -3	; "are"
	32	[58]	GETTABLE 	3 3 -4	; "equal"
	33	[58]	LOADK    	4 -5	; 1
	34	[58]	MOVE     	5 1
	35	[58]	CALL     	3 3 1
	36	[59]	SELF     	3 2 -6	; "flipSetting"
	37	[59]	CALL     	3 2 1
	38	[60]	GETGLOBAL	3 -2	; assert
	39	[60]	GETTABLE 	3 3 -3	; "are"
	40	[60]	GETTABLE 	3 3 -4	; "equal"
	41	[60]	LOADK    	4 -7	; 2
	42	[60]	MOVE     	5 0
	43	[60]	CALL     	3 3 1
	44	[61]	GETGLOBAL	3 -2	; assert
	45	[61]	GETTABLE 	3 3 -3	; "are"
	46	[61]	GETTABLE 	3 3 -4	; "equal"
	47	[61]	LOADK    	4 -5	; 1
	48	[61]	MOVE     	5 1
	49	[61]	CALL     	3 3 1
	50	[63]	NEWTABLE 	3 0 0
	51	[64]	SELF     	4 2 -8	; "addToMainMenu"
	52	[64]	MOVE     	6 3
	53	[64]	CALL     	4 3 1
	54	[65]	GETGLOBAL	4 -2	; assert
	55	[65]	GETTABLE 	4 4 -3	; "are"
	56	[65]	GETTABLE 	4 4 -4	; "equal"
	57	[65]	LOADK    	5 -9	; "This is a test plugin"
	58	[65]	GETTABLE 	6 3 -10	; "test_plugin_menu"
	59	[65]	GETTABLE 	6 6 -11	; "text"
	60	[65]	CALL     	4 3 1
	61	[66]	RETURN   	0 1

function <./spec/unit/switch_plugin_spec.lua:48,50> (4 instructions, 16 bytes at 0x7fb9cb408400)
0 params, 2 slots, 1 upvalue, 0 locals, 1 constant, 0 functions
	1	[49]	GETUPVAL 	0 0	; start_called
	2	[49]	ADD      	0 0 -1	; - 1
	3	[49]	SETUPVAL 	0 0	; start_called
	4	[50]	RETURN   	0 1

function <./spec/unit/switch_plugin_spec.lua:51,53> (4 instructions, 16 bytes at 0x7fb9cb4084f0)
0 params, 2 slots, 1 upvalue, 0 locals, 1 constant, 0 functions
	1	[52]	GETUPVAL 	0 0	; stop_called
	2	[52]	ADD      	0 0 -1	; - 1
	3	[52]	SETUPVAL 	0 0	; stop_called
	4	[53]	RETURN   	0 1

function <./spec/unit/switch_plugin_spec.lua:68,87> (50 instructions, 200 bytes at 0x7fb9cb408c30)
0 params, 6 slots, 1 upvalue, 3 locals, 7 constants, 2 functions
	1	[69]	LOADK    	0 -1	; 0
	2	[70]	LOADK    	1 -1	; 0
	3	[71]	GETUPVAL 	2 0	; createTestPlugin
	4	[72]	LOADBOOL 	3 0 0
	5	[75]	CLOSURE  	4 0	; 0x7fb9cb408cf0
	6	[75]	MOVE     	0 0
	7	[78]	CLOSURE  	5 1	; 0x7fb9cb4088b0
	8	[78]	MOVE     	0 1
	9	[71]	CALL     	2 4 2
	10	[79]	GETGLOBAL	3 -2	; assert
	11	[79]	GETTABLE 	3 3 -3	; "are"
	12	[79]	GETTABLE 	3 3 -4	; "equal"
	13	[79]	LOADK    	4 -1	; 0
	14	[79]	MOVE     	5 0
	15	[79]	CALL     	3 3 1
	16	[80]	GETGLOBAL	3 -2	; assert
	17	[80]	GETTABLE 	3 3 -3	; "are"
	18	[80]	GETTABLE 	3 3 -4	; "equal"
	19	[80]	LOADK    	4 -5	; 1
	20	[80]	MOVE     	5 1
	21	[80]	CALL     	3 3 1
	22	[81]	SELF     	3 2 -6	; "flipSetting"
	23	[81]	CALL     	3 2 1
	24	[82]	GETGLOBAL	3 -2	; assert
	25	[82]	GETTABLE 	3 3 -3	; "are"
	26	[82]	GETTABLE 	3 3 -4	; "equal"
	27	[82]	LOADK    	4 -5	; 1
	28	[82]	MOVE     	5 0
	29	[82]	CALL     	3 3 1
	30	[83]	GETGLOBAL	3 -2	; assert
	31	[83]	GETTABLE 	3 3 -3	; "are"
	32	[83]	GETTABLE 	3 3 -4	; "equal"
	33	[83]	LOADK    	4 -5	; 1
	34	[83]	MOVE     	5 1
	35	[83]	CALL     	3 3 1
	36	[84]	SELF     	3 2 -6	; "flipSetting"
	37	[84]	CALL     	3 2 1
	38	[85]	GETGLOBAL	3 -2	; assert
	39	[85]	GETTABLE 	3 3 -3	; "are"
	40	[85]	GETTABLE 	3 3 -4	; "equal"
	41	[85]	LOADK    	4 -5	; 1
	42	[85]	MOVE     	5 0
	43	[85]	CALL     	3 3 1
	44	[86]	GETGLOBAL	3 -2	; assert
	45	[86]	GETTABLE 	3 3 -3	; "are"
	46	[86]	GETTABLE 	3 3 -4	; "equal"
	47	[86]	LOADK    	4 -7	; 2
	48	[86]	MOVE     	5 1
	49	[86]	CALL     	3 3 1
	50	[87]	RETURN   	0 1

function <./spec/unit/switch_plugin_spec.lua:73,75> (4 instructions, 16 bytes at 0x7fb9cb408cf0)
0 params, 2 slots, 1 upvalue, 0 locals, 1 constant, 0 functions
	1	[74]	GETUPVAL 	0 0	; start_called
	2	[74]	ADD      	0 0 -1	; - 1
	3	[74]	SETUPVAL 	0 0	; start_called
	4	[75]	RETURN   	0 1

function <./spec/unit/switch_plugin_spec.lua:76,78> (4 instructions, 16 bytes at 0x7fb9cb4088b0)
0 params, 2 slots, 1 upvalue, 0 locals, 1 constant, 0 functions
	1	[77]	GETUPVAL 	0 0	; stop_called
	2	[77]	ADD      	0 0 -1	; - 1
	3	[77]	SETUPVAL 	0 0	; stop_called
	4	[78]	RETURN   	0 1

function <./spec/unit/switch_plugin_spec.lua:89,105> (57 instructions, 228 bytes at 0x7fb9cb4087b0)
0 params, 5 slots, 1 upvalue, 2 locals, 16 constants, 0 functions
	1	[90]	GETUPVAL 	0 0	; TestPlugin2
	2	[90]	SELF     	0 0 -1	; "new"
	3	[90]	NEWTABLE 	2 0 1
	4	[91]	SETTABLE 	2 -2 -3	; "default_enable" true
	5	[90]	CALL     	0 3 2
	6	[93]	GETGLOBAL	1 -4	; assert
	7	[93]	GETTABLE 	1 1 -5	; "are"
	8	[93]	GETTABLE 	1 1 -6	; "equal"
	9	[93]	LOADK    	2 -7	; 1
	10	[93]	GETTABLE 	3 0 -8	; "start_called"
	11	[93]	CALL     	1 3 1
	12	[94]	GETGLOBAL	1 -4	; assert
	13	[94]	GETTABLE 	1 1 -5	; "are"
	14	[94]	GETTABLE 	1 1 -6	; "equal"
	15	[94]	LOADK    	2 -9	; 0
	16	[94]	GETTABLE 	3 0 -10	; "stop_called"
	17	[94]	CALL     	1 3 1
	18	[95]	SELF     	1 0 -11	; "flipSetting"
	19	[95]	CALL     	1 2 1
	20	[96]	GETGLOBAL	1 -4	; assert
	21	[96]	GETTABLE 	1 1 -5	; "are"
	22	[96]	GETTABLE 	1 1 -6	; "equal"
	23	[96]	LOADK    	2 -7	; 1
	24	[96]	GETTABLE 	3 0 -8	; "start_called"
	25	[96]	CALL     	1 3 1
	26	[97]	GETGLOBAL	1 -4	; assert
	27	[97]	GETTABLE 	1 1 -5	; "are"
	28	[97]	GETTABLE 	1 1 -6	; "equal"
	29	[97]	LOADK    	2 -7	; 1
	30	[97]	GETTABLE 	3 0 -10	; "stop_called"
	31	[97]	CALL     	1 3 1
	32	[98]	SELF     	1 0 -11	; "flipSetting"
	33	[98]	CALL     	1 2 1
	34	[99]	GETGLOBAL	1 -4	; assert
	35	[99]	GETTABLE 	1 1 -5	; "are"
	36	[99]	GETTABLE 	1 1 -6	; "equal"
	37	[99]	LOADK    	2 -12	; 2
	38	[99]	GETTABLE 	3 0 -8	; "start_called"
	39	[99]	CALL     	1 3 1
	40	[100]	GETGLOBAL	1 -4	; assert
	41	[100]	GETTABLE 	1 1 -5	; "are"
	42	[100]	GETTABLE 	1 1 -6	; "equal"
	43	[100]	LOADK    	2 -7	; 1
	44	[100]	GETTABLE 	3 0 -10	; "stop_called"
	45	[100]	CALL     	1 3 1
	46	[102]	NEWTABLE 	1 0 0
	47	[103]	SELF     	2 0 -13	; "addToMainMenu"
	48	[103]	MOVE     	4 1
	49	[103]	CALL     	2 3 1
	50	[104]	GETGLOBAL	2 -4	; assert
	51	[104]	GETTABLE 	2 2 -5	; "are"
	52	[104]	GETTABLE 	2 2 -6	; "equal"
	53	[104]	LOADK    	3 -14	; "This is a test plugin2"
	54	[104]	GETTABLE 	4 1 -15	; "test_plugin2_menu"
	55	[104]	GETTABLE 	4 4 -16	; "text"
	56	[104]	CALL     	2 3 1
	57	[105]	RETURN   	0 1

function <./spec/unit/switch_plugin_spec.lua:107,117> (44 instructions, 176 bytes at 0x7fb9cb407db0)
0 params, 4 slots, 1 upvalue, 1 local, 10 constants, 0 functions
	1	[108]	GETUPVAL 	0 0	; TestPlugin2
	2	[108]	SELF     	0 0 -1	; "new"
	3	[108]	CALL     	0 2 2
	4	[109]	GETGLOBAL	1 -2	; assert
	5	[109]	GETTABLE 	1 1 -3	; "are"
	6	[109]	GETTABLE 	1 1 -4	; "equal"
	7	[109]	LOADK    	2 -5	; 0
	8	[109]	GETTABLE 	3 0 -6	; "start_called"
	9	[109]	CALL     	1 3 1
	10	[110]	GETGLOBAL	1 -2	; assert
	11	[110]	GETTABLE 	1 1 -3	; "are"
	12	[110]	GETTABLE 	1 1 -4	; "equal"
	13	[110]	LOADK    	2 -7	; 1
	14	[110]	GETTABLE 	3 0 -8	; "stop_called"
	15	[110]	CALL     	1 3 1
	16	[111]	SELF     	1 0 -9	; "flipSetting"
	17	[111]	CALL     	1 2 1
	18	[112]	GETGLOBAL	1 -2	; assert
	19	[112]	GETTABLE 	1 1 -3	; "are"
	20	[112]	GETTABLE 	1 1 -4	; "equal"
	21	[112]	LOADK    	2 -7	; 1
	22	[112]	GETTABLE 	3 0 -6	; "start_called"
	23	[112]	CALL     	1 3 1
	24	[113]	GETGLOBAL	1 -2	; assert
	25	[113]	GETTABLE 	1 1 -3	; "are"
	26	[113]	GETTABLE 	1 1 -4	; "equal"
	27	[113]	LOADK    	2 -7	; 1
	28	[113]	GETTABLE 	3 0 -8	; "stop_called"
	29	[113]	CALL     	1 3 1
	30	[114]	SELF     	1 0 -9	; "flipSetting"
	31	[114]	CALL     	1 2 1
	32	[115]	GETGLOBAL	1 -2	; assert
	33	[115]	GETTABLE 	1 1 -3	; "are"
	34	[115]	GETTABLE 	1 1 -4	; "equal"
	35	[115]	LOADK    	2 -7	; 1
	36	[115]	GETTABLE 	3 0 -6	; "start_called"
	37	[115]	CALL     	1 3 1
	38	[116]	GETGLOBAL	1 -2	; assert
	39	[116]	GETTABLE 	1 1 -3	; "are"
	40	[116]	GETTABLE 	1 1 -4	; "equal"
	41	[116]	LOADK    	2 -10	; 2
	42	[116]	GETTABLE 	3 0 -8	; "stop_called"
	43	[116]	CALL     	1 3 1
	44	[117]	RETURN   	0 1

function <./spec/unit/switch_plugin_spec.lua:119,131> (14 instructions, 56 bytes at 0x7fb9cb407380)
0 params, 6 slots, 1 upvalue, 1 local, 7 constants, 1 function
	1	[120]	GETUPVAL 	0 0	; SwitchPlugin
	2	[120]	SELF     	0 0 -1	; "new"
	3	[120]	NEWTABLE 	2 0 2
	4	[121]	SETTABLE 	2 -2 -3	; "name" "test_plugin"
	5	[122]	NEWTABLE 	3 0 1
	6	[123]	NEWTABLE 	4 0 1
	7	[126]	CLOSURE  	5 0	; 0x7fb9cb4090f0
	8	[126]	SETTABLE 	4 -6 5	; "registerToMainMenu" -
	9	[127]	SETTABLE 	3 -5 4	; "menu" -
	10	[128]	SETTABLE 	2 -4 3	; "ui" -
	11	[120]	CALL     	0 3 2
	12	[130]	SELF     	1 0 -7	; "init"
	13	[130]	CALL     	1 2 1
	14	[131]	RETURN   	0 1

function <./spec/unit/switch_plugin_spec.lua:124,126> (6 instructions, 24 bytes at 0x7fb9cb4090f0)
0 params, 3 slots, 0 upvalues, 0 locals, 3 constants, 0 functions
	1	[125]	GETGLOBAL	0 -1	; assert
	2	[125]	GETTABLE 	0 0 -2	; "is_true"
	3	[125]	LOADBOOL 	1 0 0
	4	[125]	LOADK    	2 -3	; "This should not reach."
	5	[125]	CALL     	0 3 1
	6	[126]	RETURN   	0 1

function <./spec/unit/switch_plugin_spec.lua:133,164> (60 instructions, 240 bytes at 0x7fb9cb407e70)
0 params, 6 slots, 1 upvalue, 3 locals, 20 constants, 1 function
	1	[134]	GETGLOBAL	0 -1	; require
	2	[134]	LOADK    	1 -2	; "ui/uimanager"
	3	[134]	CALL     	0 2 2
	4	[136]	LOADNIL  	1 1
	5	[139]	CLOSURE  	2 0	; 0x7fb9cb409fb0
	6	[139]	MOVE     	0 1
	7	[139]	SETTABLE 	0 -3 2	; "show" -
	8	[141]	GETUPVAL 	2 0	; TestPlugin2
	9	[141]	SELF     	2 2 -4	; "new"
	10	[141]	CALL     	2 2 2
	11	[143]	SELF     	3 2 -5	; "_showConfirmBox"
	12	[143]	CALL     	3 2 1
	13	[144]	GETGLOBAL	3 -6	; assert
	14	[144]	GETTABLE 	3 3 -7	; "is_not_nil"
	15	[144]	MOVE     	4 1
	16	[144]	CALL     	3 2 1
	17	[145]	GETGLOBAL	3 -6	; assert
	18	[145]	GETTABLE 	3 3 -8	; "are"
	19	[145]	GETTABLE 	3 3 -9	; "equal"
	20	[146]	LOADK    	4 -10	; "This is a test plugin2, it's for test purpose only.\nDo you want to enable it?"
	21	[147]	GETTABLE 	5 1 -11	; "text"
	22	[145]	CALL     	3 3 1
	23	[148]	GETGLOBAL	3 -6	; assert
	24	[148]	GETTABLE 	3 3 -8	; "are"
	25	[148]	GETTABLE 	3 3 -9	; "equal"
	26	[148]	LOADK    	4 -12	; "Enable"
	27	[148]	GETTABLE 	5 1 -13	; "ok_text"
	28	[148]	CALL     	3 3 1
	29	[149]	GETTABLE 	3 1 -14	; "ok_callback"
	30	[149]	CALL     	3 1 1
	31	[150]	LOADNIL  	1 1
	32	[153]	SELF     	3 2 -5	; "_showConfirmBox"
	33	[153]	CALL     	3 2 1
	34	[154]	GETGLOBAL	3 -6	; assert
	35	[154]	GETTABLE 	3 3 -7	; "is_not_nil"
	36	[154]	MOVE     	4 1
	37	[154]	CALL     	3 2 1
	38	[155]	GETGLOBAL	3 -6	; assert
	39	[155]	GETTABLE 	3 3 -8	; "are"
	40	[155]	GETTABLE 	3 3 -9	; "equal"
	41	[156]	LOADK    	4 -15	; "This is a test plugin2, it's for test purpose only.\nDo you want to disable it?"
	42	[157]	GETTABLE 	5 1 -11	; "text"
	43	[155]	CALL     	3 3 1
	44	[158]	GETGLOBAL	3 -6	; assert
	45	[158]	GETTABLE 	3 3 -8	; "are"
	46	[158]	GETTABLE 	3 3 -9	; "equal"
	47	[158]	LOADK    	4 -16	; "Disable"
	48	[158]	GETTABLE 	5 1 -13	; "ok_text"
	49	[158]	CALL     	3 3 1
	50	[159]	GETTABLE 	3 1 -14	; "ok_callback"
	51	[159]	CALL     	3 1 1
	52	[161]	GETGLOBAL	3 -6	; assert
	53	[161]	GETTABLE 	3 3 -17	; "is_false"
	54	[161]	GETTABLE 	4 2 -18	; "enabled"
	55	[161]	CALL     	3 2 1
	56	[163]	GETGLOBAL	3 -19	; package
	57	[163]	GETTABLE 	3 3 -20	; "unload"
	58	[163]	LOADK    	4 -2	; "ui/uimanager"
	59	[163]	CALL     	3 2 1
	60	[164]	RETURN   	0 1

function <./spec/unit/switch_plugin_spec.lua:137,139> (2 instructions, 8 bytes at 0x7fb9cb409fb0)
2 params, 2 slots, 1 upvalue, 2 locals, 0 constants, 0 functions
	1	[138]	SETUPVAL 	1 0	; confirm_box
	2	[139]	RETURN   	0 1
