-- BYTECODE -- switch_plugin.lua:16-21
0001    IST          1
0002    JMP      2 => 0004
0003    TNEW     1   0
0004 => GGET     2   0      ; "setmetatable"
0005    MOV      3   1
0006    MOV      4   0
0007    CALL     2   1   3
0008    TSETS    0   0   1  ; "__index"
0009    RET1     1   2

-- BYTECODE -- switch_plugin.lua:23-30
0001    MOV      3   0
0002    TGETS    2   0   0  ; "extend"
0003    MOV      4   1
0004    CALL     2   2   3
0005    MOV      1   2
0006    GGET     2   1      ; "assert"
0007    GGET     3   2      ; "type"
0008    TGETS    4   1   3  ; "name"
0009    CALL     3   2   2
0010    ISEQS    3   4      ; "string"
0011    JMP      3 => 0014
0012    KPRI     3   1
0013    JMP      4 => 0015
0014 => KPRI     3   2
0015 => KSTR     4   5      ; "name is required"
0016    CALL     2   1   3
0017    UGET     2   0      ; LuaSettings
0018    MOV      3   2
0019    TGETS    2   2   7  ; "open"
0020    UGET     4   1      ; DataStorage
0021    MOV      5   4
0022    TGETS    4   4   8  ; "getSettingsDir"
0023    CALL     4   2   2
0024    KSTR     5   9      ; "/"
0025    TGETS    6   1   3  ; "name"
0026    KSTR     7  10      ; ".lua"
0027    CAT      4   4   7
0028    CALL     2   2   3
0029    TSETS    2   1   6  ; "settings"
0030    KSHORT   2   0
0031    TSETS    2   1  11  ; "settings_id"
0032    UGET     2   2      ; SwitchPlugin
0033    TGETS    2   2  12  ; "_init"
0034    MOV      3   1
0035    CALL     2   1   2
0036    RET1     1   2

-- BYTECODE -- switch_plugin.lua:32-45
0001    TGETS    1   0   0  ; "default_enable"
0002    ISF          1
0003    JMP      2 => 0011
0004    TGETS    1   0   2  ; "settings"
0005    MOV      2   1
0006    TGETS    1   1   3  ; "nilOrTrue"
0007    KSTR     3   4      ; "enable"
0008    CALL     1   2   3
0009    TSETS    1   0   1  ; "enabled"
0010    JMP      1 => 0018
0011 => TGETS    1   0   2  ; "settings"
0012    MOV      2   1
0013    TGETS    1   1   5  ; "nilOrFalse"
0014    KSTR     3   4      ; "enable"
0015    CALL     1   2   3
0016    NOT      1   1
0017    TSETS    1   0   1  ; "enabled"
0018 => TGETS    1   0   6  ; "settings_id"
0019    ADDVN    1   1   0  ; 1
0020    TSETS    1   0   6  ; "settings_id"
0021    UGET     1   0      ; logger
0022    TGETS    1   1   7  ; "dbg"
0023    KSTR     2   8      ; "SwitchPlugin:_init() self.enabled: "
0024    TGETS    3   0   1  ; "enabled"
0025    KSTR     4   9      ; " with id "
0026    TGETS    5   0   6  ; "settings_id"
0027    CALL     1   1   5
0028    TGETS    1   0   1  ; "enabled"
0029    ISF          1
0030    JMP      2 => 0035
0031    MOV      2   0
0032    TGETS    1   0  10  ; "_start"
0033    CALL     1   1   2
0034    JMP      1 => 0038
0035 => MOV      2   0
0036    TGETS    1   0  11  ; "_stop"
0037    CALL     1   1   2
0038 => RET0     0   1

-- BYTECODE -- switch_plugin.lua:47-54
0001    TGETS    1   0   0  ; "default_enable"
0002    ISF          1
0003    JMP      2 => 0010
0004    TGETS    1   0   1  ; "settings"
0005    MOV      2   1
0006    TGETS    1   1   2  ; "flipNilOrTrue"
0007    KSTR     3   3      ; "enable"
0008    CALL     1   1   3
0009    JMP      1 => 0015
0010 => TGETS    1   0   1  ; "settings"
0011    MOV      2   1
0012    TGETS    1   1   4  ; "flipNilOrFalse"
0013    KSTR     3   3      ; "enable"
0014    CALL     1   1   3
0015 => MOV      2   0
0016    TGETS    1   0   5  ; "_init"
0017    CALL     1   1   2
0018    RET0     0   1

-- BYTECODE -- switch_plugin.lua:56-58
0001    TGETS    1   0   0  ; "settings"
0002    MOV      2   1
0003    TGETS    1   1   1  ; "flush"
0004    CALL     1   1   2
0005    RET0     0   1

-- BYTECODE -- switch_plugin.lua:65-67
0001    UGET     0   0      ; self
0002    MOV      1   0
0003    TGETS    0   0   0  ; "flipSetting"
0004    CALL     0   1   2
0005    RET0     0   1

-- BYTECODE -- switch_plugin.lua:61-69
0001    UGET     1   0      ; UIManager
0002    MOV      2   1
0003    TGETS    1   1   0  ; "show"
0004    UGET     3   1      ; ConfirmBox
0005    MOV      4   3
0006    TGETS    3   3   1  ; "new"
0007    TDUP     5   3
0008    MOV      7   0
0009    TGETS    6   0   2  ; "_confirmMessage"
0010    CALL     6   2   2
0011    TSETS    6   5   4  ; "text"
0012    TGETS    6   0   5  ; "enabled"
0013    ISF          6
0014    JMP      7 => 0020
0015    UGET     6   2      ; _
0016    KSTR     7   6      ; "Disable"
0017    CALL     6   2   2
0018    IST          6
0019    JMP      7 => 0023
0020 => UGET     6   2      ; _
0021    KSTR     7   7      ; "Enable"
0022    CALL     6   2   2
0023 => TSETS    6   5   8  ; "ok_text"
0024    FNEW     6   9      ; switch_plugin.lua:65
0025    TSETS    6   5  10  ; "ok_callback"
0026    CALL     3   0   3
0027    CALLM    1   1   1
0028    UCLO     0 => 0029
0029 => RET0     0   1

-- BYTECODE -- switch_plugin.lua:71-84
0001    KSTR     1   0      ; ""
0002    GGET     2   1      ; "type"
0003    TGETS    3   0   2  ; "confirm_message"
0004    CALL     2   2   2
0005    ISNES    2   3      ; "string"
0006    JMP      2 => 0011
0007    TGETS    2   0   2  ; "confirm_message"
0008    KSTR     3   4      ; "\n"
0009    CAT      1   2   3
0010    JMP      2 => 0020
0011 => GGET     2   1      ; "type"
0012    TGETS    3   0   2  ; "confirm_message"
0013    CALL     2   2   2
0014    ISNES    2   5      ; "function"
0015    JMP      2 => 0020
0016    TGETS    2   0   2  ; "confirm_message"
0017    CALL     2   2   1
0018    KSTR     3   4      ; "\n"
0019    CAT      1   2   3
0020 => TGETS    2   0   6  ; "enabled"
0021    ISF          2
0022    JMP      3 => 0029
0023    MOV      2   1
0024    UGET     3   0      ; _
0025    KSTR     4   7      ; "Do you want to disable it?"
0026    CALL     3   2   2
0027    CAT      1   2   3
0028    JMP      2 => 0034
0029 => MOV      2   1
0030    UGET     3   0      ; _
0031    KSTR     4   8      ; "Do you want to enable it?"
0032    CALL     3   2   2
0033    CAT      1   2   3
0034 => RET1     1   2

-- BYTECODE -- switch_plugin.lua:86-90
0001    GGET     1   0      ; "type"
0002    TGETS    2   0   1  ; "menu_item"
0003    CALL     1   2   2
0004    ISNES    1   2      ; "string"
0005    JMP      1 => 0019
0006    TGETS    1   0   3  ; "ui"
0007    ISEQP    1   0
0008    JMP      1 => 0019
0009    TGETS    1   0   3  ; "ui"
0010    TGETS    1   1   4  ; "menu"
0011    ISEQP    1   0
0012    JMP      1 => 0019
0013    TGETS    1   0   3  ; "ui"
0014    TGETS    1   1   4  ; "menu"
0015    MOV      2   1
0016    TGETS    1   1   5  ; "registerToMainMenu"
0017    MOV      3   0
0018    CALL     1   1   3
0019 => RET0     0   1

-- BYTECODE -- switch_plugin.lua:99-101
0001    UGET     0   0      ; self
0002    MOV      1   0
0003    TGETS    0   0   0  ; "_showConfirmBox"
0004    CALL     0   1   2
0005    RET0     0   1

-- BYTECODE -- switch_plugin.lua:102-102
0001    UGET     0   0      ; self
0002    TGETS    0   0   0  ; "enabled"
0003    RET1     0   2

-- BYTECODE -- switch_plugin.lua:92-104
0001    GGET     2   0      ; "assert"
0002    GGET     3   1      ; "type"
0003    TGETS    4   0   2  ; "menu_item"
0004    CALL     3   2   2
0005    ISEQS    3   3      ; "string"
0006    JMP      3 => 0009
0007    KPRI     3   1
0008    JMP      4 => 0010
0009 => KPRI     3   2
0010 => KSTR     4   4      ; "addToMainMenu should not be called witho"~
0011    CALL     2   1   3
0012    GGET     2   0      ; "assert"
0013    GGET     3   1      ; "type"
0014    TGETS    4   0   5  ; "menu_text"
0015    CALL     3   2   2
0016    ISEQS    3   3      ; "string"
0017    JMP      3 => 0020
0018    KPRI     3   1
0019    JMP      4 => 0021
0020 => KPRI     3   2
0021 => KSTR     4   6      ; "Have you forgotten to set "menu_text""
0022    CALL     2   1   3
0023    TGETS    2   0   2  ; "menu_item"
0024    TDUP     3   7
0025    TGETS    4   0   5  ; "menu_text"
0026    TSETS    4   3   8  ; "text"
0027    FNEW     4   9      ; switch_plugin.lua:99
0028    TSETS    4   3  10  ; "callback"
0029    FNEW     4  11      ; switch_plugin.lua:102
0030    TSETS    4   3  12  ; "checked_func"
0031    TSETV    3   1   2
0032    UCLO     0 => 0033
0033 => RET0     0   1

-- BYTECODE -- switch_plugin.lua:107-107
0001    RET0     0   1

-- BYTECODE -- switch_plugin.lua:109-109
0001    RET0     0   1

-- BYTECODE -- switch_plugin.lua:0-112
0001    GGET     0   0      ; "require"
0002    KSTR     1   1      ; "ui/widget/confirmbox"
0003    CALL     0   2   2
0004    GGET     1   0      ; "require"
0005    KSTR     2   2      ; "datastorage"
0006    CALL     1   2   2
0007    GGET     2   0      ; "require"
0008    KSTR     3   3      ; "luasettings"
0009    CALL     2   2   2
0010    GGET     3   0      ; "require"
0011    KSTR     4   4      ; "ui/uimanager"
0012    CALL     3   2   2
0013    GGET     4   0      ; "require"
0014    KSTR     5   5      ; "ui/widget/container/widgetcontainer"
0015    CALL     4   2   2
0016    GGET     5   0      ; "require"
0017    KSTR     6   6      ; "logger"
0018    CALL     5   2   2
0019    GGET     6   0      ; "require"
0020    KSTR     7   7      ; "gettext"
0021    CALL     6   2   2
0022    MOV      8   4
0023    TGETS    7   4   8  ; "new"
0024    CALL     7   2   2
0025    FNEW     8  10      ; switch_plugin.lua:16
0026    TSETS    8   7   9  ; "extend"
0027    FNEW     8  11      ; switch_plugin.lua:23
0028    TSETS    8   7   8  ; "new"
0029    FNEW     8  13      ; switch_plugin.lua:32
0030    TSETS    8   7  12  ; "_init"
0031    FNEW     8  15      ; switch_plugin.lua:47
0032    TSETS    8   7  14  ; "flipSetting"
0033    FNEW     8  17      ; switch_plugin.lua:56
0034    TSETS    8   7  16  ; "onFlushSettings"
0035    FNEW     8  19      ; switch_plugin.lua:61
0036    TSETS    8   7  18  ; "_showConfirmBox"
0037    FNEW     8  21      ; switch_plugin.lua:71
0038    TSETS    8   7  20  ; "_confirmMessage"
0039    FNEW     8  23      ; switch_plugin.lua:86
0040    TSETS    8   7  22  ; "init"
0041    FNEW     8  25      ; switch_plugin.lua:92
0042    TSETS    8   7  24  ; "addToMainMenu"
0043    FNEW     8  27      ; switch_plugin.lua:107
0044    TSETS    8   7  26  ; "_start"
0045    FNEW     8  29      ; switch_plugin.lua:109
0046    TSETS    8   7  28  ; "_stop"
0047    UCLO     0 => 0048
0048 => RET1     7   2

