
main <./frontend/ui/plugin/switch_plugin.lua:0,0> (55 instructions, 220 bytes at 0x7fd7824068d0)
0+ params, 9 slots, 0 upvalues, 8 locals, 19 constants, 11 functions
	1	[6]	GETGLOBAL	0 -1	; require
	2	[6]	LOADK    	1 -2	; "ui/widget/confirmbox"
	3	[6]	CALL     	0 2 2
	4	[7]	GETGLOBAL	1 -1	; require
	5	[7]	LOADK    	2 -3	; "datastorage"
	6	[7]	CALL     	1 2 2
	7	[8]	GETGLOBAL	2 -1	; require
	8	[8]	LOADK    	3 -4	; "luasettings"
	9	[8]	CALL     	2 2 2
	10	[9]	GETGLOBAL	3 -1	; require
	11	[9]	LOADK    	4 -5	; "ui/uimanager"
	12	[9]	CALL     	3 2 2
	13	[10]	GETGLOBAL	4 -1	; require
	14	[10]	LOADK    	5 -6	; "ui/widget/container/widgetcontainer"
	15	[10]	CALL     	4 2 2
	16	[11]	GETGLOBAL	5 -1	; require
	17	[11]	LOADK    	6 -7	; "logger"
	18	[11]	CALL     	5 2 2
	19	[12]	GETGLOBAL	6 -1	; require
	20	[12]	LOADK    	7 -8	; "gettext"
	21	[12]	CALL     	6 2 2
	22	[14]	SELF     	7 4 -9	; "new"
	23	[14]	CALL     	7 2 2
	24	[21]	CLOSURE  	8 0	; 0x7fd782406c10
	25	[16]	SETTABLE 	7 -10 8	; "extend" -
	26	[30]	CLOSURE  	8 1	; 0x7fd782407360
	27	[30]	MOVE     	0 2
	28	[30]	MOVE     	0 1
	29	[30]	MOVE     	0 7
	30	[23]	SETTABLE 	7 -9 8	; "new" -
	31	[45]	CLOSURE  	8 2	; 0x7fd782407590
	32	[45]	MOVE     	0 5
	33	[32]	SETTABLE 	7 -11 8	; "_init" -
	34	[54]	CLOSURE  	8 3	; 0x7fd782407090
	35	[47]	SETTABLE 	7 -12 8	; "flipSetting" -
	36	[58]	CLOSURE  	8 4	; 0x7fd782407b40
	37	[56]	SETTABLE 	7 -13 8	; "onFlushSettings" -
	38	[69]	CLOSURE  	8 5	; 0x7fd782408000
	39	[69]	MOVE     	0 3
	40	[69]	MOVE     	0 0
	41	[69]	MOVE     	0 6
	42	[61]	SETTABLE 	7 -14 8	; "_showConfirmBox" -
	43	[84]	CLOSURE  	8 6	; 0x7fd7824067b0
	44	[84]	MOVE     	0 6
	45	[71]	SETTABLE 	7 -15 8	; "_confirmMessage" -
	46	[90]	CLOSURE  	8 7	; 0x7fd782408960
	47	[86]	SETTABLE 	7 -16 8	; "init" -
	48	[104]	CLOSURE  	8 8	; 0x7fd782406d90
	49	[92]	SETTABLE 	7 -17 8	; "addToMainMenu" -
	50	[107]	CLOSURE  	8 9	; 0x7fd782409bc0
	51	[107]	SETTABLE 	7 -18 8	; "_start" -
	52	[109]	CLOSURE  	8 10	; 0x7fd782409d30
	53	[109]	SETTABLE 	7 -19 8	; "_stop" -
	54	[111]	RETURN   	7 2
	55	[111]	RETURN   	0 1

function <./frontend/ui/plugin/switch_plugin.lua:16,21> (11 instructions, 44 bytes at 0x7fd782406c10)
2 params, 5 slots, 0 upvalues, 2 locals, 2 constants, 0 functions
	1	[17]	TEST     	1 0 1
	2	[17]	JMP      	2	; to 5
	3	[17]	NEWTABLE 	2 0 0
	4	[17]	MOVE     	1 2
	5	[18]	GETGLOBAL	2 -1	; setmetatable
	6	[18]	MOVE     	3 1
	7	[18]	MOVE     	4 0
	8	[18]	CALL     	2 3 1
	9	[19]	SETTABLE 	0 -2 0	; "__index" -
	10	[20]	RETURN   	1 2
	11	[21]	RETURN   	0 1

function <./frontend/ui/plugin/switch_plugin.lua:23,30> (32 instructions, 128 bytes at 0x7fd782407360)
2 params, 8 slots, 3 upvalues, 2 locals, 14 constants, 0 functions
	1	[24]	SELF     	2 0 -1	; "extend"
	2	[24]	MOVE     	4 1
	3	[24]	CALL     	2 3 2
	4	[24]	MOVE     	1 2
	5	[25]	GETGLOBAL	2 -2	; assert
	6	[25]	GETGLOBAL	3 -3	; type
	7	[25]	GETTABLE 	4 1 -4	; "name"
	8	[25]	CALL     	3 2 2
	9	[25]	EQ       	1 3 -5	; - "string"
	10	[25]	JMP      	1	; to 12
	11	[25]	LOADBOOL 	3 0 1
	12	[25]	LOADBOOL 	3 1 0
	13	[25]	LOADK    	4 -6	; "name is required"
	14	[25]	CALL     	2 3 1
	15	[26]	GETUPVAL 	2 0	; LuaSettings
	16	[26]	SELF     	2 2 -8	; "open"
	17	[26]	GETUPVAL 	4 1	; DataStorage
	18	[26]	SELF     	4 4 -9	; "getSettingsDir"
	19	[26]	CALL     	4 2 2
	20	[26]	LOADK    	5 -10	; "/"
	21	[26]	GETTABLE 	6 1 -4	; "name"
	22	[26]	LOADK    	7 -11	; ".lua"
	23	[26]	CONCAT   	4 4 7
	24	[26]	CALL     	2 3 2
	25	[26]	SETTABLE 	1 -7 2	; "settings" -
	26	[27]	SETTABLE 	1 -12 -13	; "settings_id" 0
	27	[28]	GETUPVAL 	2 2	; SwitchPlugin
	28	[28]	GETTABLE 	2 2 -14	; "_init"
	29	[28]	MOVE     	3 1
	30	[28]	CALL     	2 2 1
	31	[29]	RETURN   	1 2
	32	[30]	RETURN   	0 1

function <./frontend/ui/plugin/switch_plugin.lua:32,45> (34 instructions, 136 bytes at 0x7fd782407590)
1 param, 6 slots, 1 upvalue, 1 local, 13 constants, 0 functions
	1	[33]	GETTABLE 	1 0 -1	; "default_enable"
	2	[33]	TEST     	1 0 0
	3	[33]	JMP      	6	; to 10
	4	[34]	GETTABLE 	1 0 -3	; "settings"
	5	[34]	SELF     	1 1 -4	; "nilOrTrue"
	6	[34]	LOADK    	3 -5	; "enable"
	7	[34]	CALL     	1 3 2
	8	[34]	SETTABLE 	0 -2 1	; "enabled" -
	9	[34]	JMP      	6	; to 16
	10	[36]	GETTABLE 	1 0 -3	; "settings"
	11	[36]	SELF     	1 1 -6	; "nilOrFalse"
	12	[36]	LOADK    	3 -5	; "enable"
	13	[36]	CALL     	1 3 2
	14	[36]	NOT      	1 1
	15	[36]	SETTABLE 	0 -2 1	; "enabled" -
	16	[38]	GETTABLE 	1 0 -7	; "settings_id"
	17	[38]	ADD      	1 1 -8	; - 1
	18	[38]	SETTABLE 	0 -7 1	; "settings_id" -
	19	[39]	GETUPVAL 	1 0	; logger
	20	[39]	GETTABLE 	1 1 -9	; "dbg"
	21	[39]	LOADK    	2 -10	; "SwitchPlugin:_init() self.enabled: "
	22	[39]	GETTABLE 	3 0 -2	; "enabled"
	23	[39]	LOADK    	4 -11	; " with id "
	24	[39]	GETTABLE 	5 0 -7	; "settings_id"
	25	[39]	CALL     	1 5 1
	26	[40]	GETTABLE 	1 0 -2	; "enabled"
	27	[40]	TEST     	1 0 0
	28	[40]	JMP      	3	; to 32
	29	[41]	SELF     	1 0 -12	; "_start"
	30	[41]	CALL     	1 2 1
	31	[41]	JMP      	2	; to 34
	32	[43]	SELF     	1 0 -13	; "_stop"
	33	[43]	CALL     	1 2 1
	34	[45]	RETURN   	0 1

function <./frontend/ui/plugin/switch_plugin.lua:47,54> (15 instructions, 60 bytes at 0x7fd782407090)
1 param, 4 slots, 0 upvalues, 1 local, 6 constants, 0 functions
	1	[48]	GETTABLE 	1 0 -1	; "default_enable"
	2	[48]	TEST     	1 0 0
	3	[48]	JMP      	5	; to 9
	4	[49]	GETTABLE 	1 0 -2	; "settings"
	5	[49]	SELF     	1 1 -3	; "flipNilOrTrue"
	6	[49]	LOADK    	3 -4	; "enable"
	7	[49]	CALL     	1 3 1
	8	[49]	JMP      	4	; to 13
	9	[51]	GETTABLE 	1 0 -2	; "settings"
	10	[51]	SELF     	1 1 -5	; "flipNilOrFalse"
	11	[51]	LOADK    	3 -4	; "enable"
	12	[51]	CALL     	1 3 1
	13	[53]	SELF     	1 0 -6	; "_init"
	14	[53]	CALL     	1 2 1
	15	[54]	RETURN   	0 1

function <./frontend/ui/plugin/switch_plugin.lua:56,58> (4 instructions, 16 bytes at 0x7fd782407b40)
1 param, 3 slots, 0 upvalues, 1 local, 2 constants, 0 functions
	1	[57]	GETTABLE 	1 0 -1	; "settings"
	2	[57]	SELF     	1 1 -2	; "flush"
	3	[57]	CALL     	1 2 1
	4	[58]	RETURN   	0 1

function <./frontend/ui/plugin/switch_plugin.lua:61,69> (26 instructions, 104 bytes at 0x7fd782408000)
1 param, 8 slots, 3 upvalues, 1 local, 9 constants, 1 function
	1	[62]	GETUPVAL 	1 0	; UIManager
	2	[62]	SELF     	1 1 -1	; "show"
	3	[62]	GETUPVAL 	3 1	; ConfirmBox
	4	[62]	SELF     	3 3 -2	; "new"
	5	[62]	NEWTABLE 	5 0 3
	6	[63]	SELF     	6 0 -4	; "_confirmMessage"
	7	[63]	CALL     	6 2 2
	8	[63]	SETTABLE 	5 -3 6	; "text" -
	9	[64]	GETTABLE 	6 0 -6	; "enabled"
	10	[64]	TEST     	6 0 0
	11	[64]	JMP      	5	; to 17
	12	[64]	GETUPVAL 	6 2	; _
	13	[64]	LOADK    	7 -7	; "Disable"
	14	[64]	CALL     	6 2 2
	15	[64]	TEST     	6 0 1
	16	[64]	JMP      	3	; to 20
	17	[64]	GETUPVAL 	6 2	; _
	18	[64]	LOADK    	7 -8	; "Enable"
	19	[64]	CALL     	6 2 2
	20	[64]	SETTABLE 	5 -5 6	; "ok_text" -
	21	[67]	CLOSURE  	6 0	; 0x7fd7824087e0
	22	[67]	MOVE     	0 0
	23	[67]	SETTABLE 	5 -9 6	; "ok_callback" -
	24	[62]	CALL     	3 3 0
	25	[62]	CALL     	1 0 1
	26	[69]	RETURN   	0 1

function <./frontend/ui/plugin/switch_plugin.lua:65,67> (4 instructions, 16 bytes at 0x7fd7824087e0)
0 params, 2 slots, 1 upvalue, 0 locals, 1 constant, 0 functions
	1	[66]	GETUPVAL 	0 0	; self
	2	[66]	SELF     	0 0 -1	; "flipSetting"
	3	[66]	CALL     	0 2 1
	4	[67]	RETURN   	0 1

function <./frontend/ui/plugin/switch_plugin.lua:71,84> (35 instructions, 140 bytes at 0x7fd7824067b0)
1 param, 5 slots, 1 upvalue, 2 locals, 9 constants, 0 functions
	1	[72]	LOADK    	1 -1	; ""
	2	[73]	GETGLOBAL	2 -2	; type
	3	[73]	GETTABLE 	3 0 -3	; "confirm_message"
	4	[73]	CALL     	2 2 2
	5	[73]	EQ       	0 2 -4	; - "string"
	6	[73]	JMP      	4	; to 11
	7	[74]	GETTABLE 	2 0 -3	; "confirm_message"
	8	[74]	LOADK    	3 -5	; "\n"
	9	[74]	CONCAT   	1 2 3
	10	[74]	JMP      	9	; to 20
	11	[75]	GETGLOBAL	2 -2	; type
	12	[75]	GETTABLE 	3 0 -3	; "confirm_message"
	13	[75]	CALL     	2 2 2
	14	[75]	EQ       	0 2 -6	; - "function"
	15	[75]	JMP      	4	; to 20
	16	[76]	GETTABLE 	2 0 -3	; "confirm_message"
	17	[76]	CALL     	2 1 2
	18	[76]	LOADK    	3 -5	; "\n"
	19	[76]	CONCAT   	1 2 3
	20	[78]	GETTABLE 	2 0 -7	; "enabled"
	21	[78]	TEST     	2 0 0
	22	[78]	JMP      	6	; to 29
	23	[79]	MOVE     	2 1
	24	[79]	GETUPVAL 	3 0	; _
	25	[79]	LOADK    	4 -8	; "Do you want to disable it?"
	26	[79]	CALL     	3 2 2
	27	[79]	CONCAT   	1 2 3
	28	[79]	JMP      	5	; to 34
	29	[81]	MOVE     	2 1
	30	[81]	GETUPVAL 	3 0	; _
	31	[81]	LOADK    	4 -9	; "Do you want to enable it?"
	32	[81]	CALL     	3 2 2
	33	[81]	CONCAT   	1 2 3
	34	[83]	RETURN   	1 2
	35	[84]	RETURN   	0 1

function <./frontend/ui/plugin/switch_plugin.lua:86,90> (18 instructions, 72 bytes at 0x7fd782408960)
1 param, 4 slots, 0 upvalues, 1 local, 7 constants, 0 functions
	1	[87]	GETGLOBAL	1 -1	; type
	2	[87]	GETTABLE 	2 0 -2	; "menu_item"
	3	[87]	CALL     	1 2 2
	4	[87]	EQ       	0 1 -3	; - "string"
	5	[87]	JMP      	12	; to 18
	6	[87]	GETTABLE 	1 0 -4	; "ui"
	7	[87]	EQ       	1 1 -5	; - nil
	8	[87]	JMP      	9	; to 18
	9	[87]	GETTABLE 	1 0 -4	; "ui"
	10	[87]	GETTABLE 	1 1 -6	; "menu"
	11	[87]	EQ       	1 1 -5	; - nil
	12	[87]	JMP      	5	; to 18
	13	[88]	GETTABLE 	1 0 -4	; "ui"
	14	[88]	GETTABLE 	1 1 -6	; "menu"
	15	[88]	SELF     	1 1 -7	; "registerToMainMenu"
	16	[88]	MOVE     	3 0
	17	[88]	CALL     	1 3 1
	18	[90]	RETURN   	0 1

function <./frontend/ui/plugin/switch_plugin.lua:92,104> (32 instructions, 128 bytes at 0x7fd782406d90)
2 params, 5 slots, 0 upvalues, 2 locals, 10 constants, 2 functions
	1	[93]	GETGLOBAL	2 -1	; assert
	2	[93]	GETGLOBAL	3 -2	; type
	3	[93]	GETTABLE 	4 0 -3	; "menu_item"
	4	[93]	CALL     	3 2 2
	5	[93]	EQ       	1 3 -4	; - "string"
	6	[93]	JMP      	1	; to 8
	7	[93]	LOADBOOL 	3 0 1
	8	[93]	LOADBOOL 	3 1 0
	9	[94]	LOADK    	4 -5	; "addToMainMenu should not be called without menu_item."
	10	[93]	CALL     	2 3 1
	11	[95]	GETGLOBAL	2 -1	; assert
	12	[95]	GETGLOBAL	3 -2	; type
	13	[95]	GETTABLE 	4 0 -6	; "menu_text"
	14	[95]	CALL     	3 2 2
	15	[95]	EQ       	1 3 -4	; - "string"
	16	[95]	JMP      	1	; to 18
	17	[95]	LOADBOOL 	3 0 1
	18	[95]	LOADBOOL 	3 1 0
	19	[96]	LOADK    	4 -7	; "Have you forgotten to set \"menu_text\""
	20	[95]	CALL     	2 3 1
	21	[97]	GETTABLE 	2 0 -3	; "menu_item"
	22	[97]	NEWTABLE 	3 0 3
	23	[98]	GETTABLE 	4 0 -6	; "menu_text"
	24	[98]	SETTABLE 	3 -8 4	; "text" -
	25	[101]	CLOSURE  	4 0	; 0x7fd782409220
	26	[101]	MOVE     	0 0
	27	[101]	SETTABLE 	3 -9 4	; "callback" -
	28	[102]	CLOSURE  	4 1	; 0x7fd7824099a0
	29	[102]	MOVE     	0 0
	30	[102]	SETTABLE 	3 -10 4	; "checked_func" -
	31	[103]	SETTABLE 	1 2 3
	32	[104]	RETURN   	0 1

function <./frontend/ui/plugin/switch_plugin.lua:99,101> (4 instructions, 16 bytes at 0x7fd782409220)
0 params, 2 slots, 1 upvalue, 0 locals, 1 constant, 0 functions
	1	[100]	GETUPVAL 	0 0	; self
	2	[100]	SELF     	0 0 -1	; "_showConfirmBox"
	3	[100]	CALL     	0 2 1
	4	[101]	RETURN   	0 1

function <./frontend/ui/plugin/switch_plugin.lua:102,102> (4 instructions, 16 bytes at 0x7fd7824099a0)
0 params, 2 slots, 1 upvalue, 0 locals, 1 constant, 0 functions
	1	[102]	GETUPVAL 	0 0	; self
	2	[102]	GETTABLE 	0 0 -1	; "enabled"
	3	[102]	RETURN   	0 2
	4	[102]	RETURN   	0 1

function <./frontend/ui/plugin/switch_plugin.lua:107,107> (1 instruction, 4 bytes at 0x7fd782409bc0)
1 param, 2 slots, 0 upvalues, 1 local, 0 constants, 0 functions
	1	[107]	RETURN   	0 1

function <./frontend/ui/plugin/switch_plugin.lua:109,109> (1 instruction, 4 bytes at 0x7fd782409d30)
1 param, 2 slots, 0 upvalues, 1 local, 0 constants, 0 functions
	1	[109]	RETURN   	0 1
