-- BYTECODE -- switch_plugin_spec.lua:12-14
0001    UGET     0   0      ; start
0002    CALL     0   1   1
0003    RET0     0   1

-- BYTECODE -- switch_plugin_spec.lua:15-17
0001    UGET     0   0      ; stop
0002    CALL     0   1   1
0003    RET0     0   1

-- BYTECODE -- switch_plugin_spec.lua:5-19
0001    UGET     3   0      ; SwitchPlugin
0002    MOV      4   3
0003    TGETS    3   3   0  ; "new"
0004    TDUP     5   1
0005    TSETS    0   5   2  ; "default_enable"
0006    FNEW     6   3      ; switch_plugin_spec.lua:12
0007    TSETS    6   5   4  ; "_start"
0008    FNEW     6   5      ; switch_plugin_spec.lua:15
0009    TSETS    6   5   6  ; "_stop"
0010    UCLO     0 => 0011
0011 => CALLT    3   3

-- BYTECODE -- switch_plugin_spec.lua:23-33
0001    IST          1
0002    JMP      2 => 0004
0003    TNEW     1   0
0004 => KSTR     2   1      ; "test_plugin2"
0005    TSETS    2   1   0  ; "name"
0006    KSTR     2   3      ; "test_plugin2_menu"
0007    TSETS    2   1   2  ; "menu_item"
0008    KSTR     2   5      ; "This is a test plugin2"
0009    TSETS    2   1   4  ; "menu_text"
0010    KSTR     2   7      ; "This is a test plugin2, it's for test pu"~
0011    TSETS    2   1   6  ; "confirm_message"
0012    KSHORT   2   0
0013    TSETS    2   1   8  ; "start_called"
0014    KSHORT   2   0
0015    TSETS    2   1   9  ; "stop_called"
0016    UGET     2   0      ; SwitchPlugin
0017    TGETS    2   2  10  ; "new"
0018    MOV      3   0
0019    MOV      4   1
0020    CALL     2   2   3
0021    MOV      1   2
0022    RET1     1   2

-- BYTECODE -- switch_plugin_spec.lua:35-37
0001    TGETS    1   0   0  ; "start_called"
0002    ADDVN    1   1   0  ; 1
0003    TSETS    1   0   0  ; "start_called"
0004    RET0     0   1

-- BYTECODE -- switch_plugin_spec.lua:39-41
0001    TGETS    1   0   0  ; "stop_called"
0002    ADDVN    1   1   0  ; 1
0003    TSETS    1   0   0  ; "stop_called"
0004    RET0     0   1

-- BYTECODE -- switch_plugin_spec.lua:48-50
0001    UGET     0   0      ; start_called
0002    ADDVN    0   0   0  ; 1
0003    USETV    0   0      ; start_called
0004    RET0     0   1

-- BYTECODE -- switch_plugin_spec.lua:51-53
0001    UGET     0   0      ; stop_called
0002    ADDVN    0   0   0  ; 1
0003    USETV    0   0      ; stop_called
0004    RET0     0   1

-- BYTECODE -- switch_plugin_spec.lua:43-66
0001    KSHORT   0   0
0002    KSHORT   1   0
0003    UGET     2   0      ; createTestPlugin
0004    KPRI     3   2
0005    FNEW     4   0      ; switch_plugin_spec.lua:48
0006    FNEW     5   1      ; switch_plugin_spec.lua:51
0007    CALL     2   2   4
0008    GGET     3   2      ; "assert"
0009    TGETS    3   3   3  ; "are"
0010    TGETS    3   3   4  ; "equal"
0011    KSHORT   4   1
0012    MOV      5   0
0013    CALL     3   1   3
0014    GGET     3   2      ; "assert"
0015    TGETS    3   3   3  ; "are"
0016    TGETS    3   3   4  ; "equal"
0017    KSHORT   4   0
0018    MOV      5   1
0019    CALL     3   1   3
0020    MOV      4   2
0021    TGETS    3   2   5  ; "flipSetting"
0022    CALL     3   1   2
0023    GGET     3   2      ; "assert"
0024    TGETS    3   3   3  ; "are"
0025    TGETS    3   3   4  ; "equal"
0026    KSHORT   4   1
0027    MOV      5   0
0028    CALL     3   1   3
0029    GGET     3   2      ; "assert"
0030    TGETS    3   3   3  ; "are"
0031    TGETS    3   3   4  ; "equal"
0032    KSHORT   4   1
0033    MOV      5   1
0034    CALL     3   1   3
0035    MOV      4   2
0036    TGETS    3   2   5  ; "flipSetting"
0037    CALL     3   1   2
0038    GGET     3   2      ; "assert"
0039    TGETS    3   3   3  ; "are"
0040    TGETS    3   3   4  ; "equal"
0041    KSHORT   4   2
0042    MOV      5   0
0043    CALL     3   1   3
0044    GGET     3   2      ; "assert"
0045    TGETS    3   3   3  ; "are"
0046    TGETS    3   3   4  ; "equal"
0047    KSHORT   4   1
0048    MOV      5   1
0049    CALL     3   1   3
0050    TNEW     3   0
0051    MOV      5   2
0052    TGETS    4   2   6  ; "addToMainMenu"
0053    MOV      6   3
0054    CALL     4   1   3
0055    GGET     4   2      ; "assert"
0056    TGETS    4   4   3  ; "are"
0057    TGETS    4   4   4  ; "equal"
0058    KSTR     5   7      ; "This is a test plugin"
0059    TGETS    6   3   8  ; "test_plugin_menu"
0060    TGETS    6   6   9  ; "text"
0061    CALL     4   1   3
0062    UCLO     0 => 0063
0063 => RET0     0   1

-- BYTECODE -- switch_plugin_spec.lua:73-75
0001    UGET     0   0      ; start_called
0002    ADDVN    0   0   0  ; 1
0003    USETV    0   0      ; start_called
0004    RET0     0   1

-- BYTECODE -- switch_plugin_spec.lua:76-78
0001    UGET     0   0      ; stop_called
0002    ADDVN    0   0   0  ; 1
0003    USETV    0   0      ; stop_called
0004    RET0     0   1

-- BYTECODE -- switch_plugin_spec.lua:68-87
0001    KSHORT   0   0
0002    KSHORT   1   0
0003    UGET     2   0      ; createTestPlugin
0004    KPRI     3   1
0005    FNEW     4   0      ; switch_plugin_spec.lua:73
0006    FNEW     5   1      ; switch_plugin_spec.lua:76
0007    CALL     2   2   4
0008    GGET     3   2      ; "assert"
0009    TGETS    3   3   3  ; "are"
0010    TGETS    3   3   4  ; "equal"
0011    KSHORT   4   0
0012    MOV      5   0
0013    CALL     3   1   3
0014    GGET     3   2      ; "assert"
0015    TGETS    3   3   3  ; "are"
0016    TGETS    3   3   4  ; "equal"
0017    KSHORT   4   1
0018    MOV      5   1
0019    CALL     3   1   3
0020    MOV      4   2
0021    TGETS    3   2   5  ; "flipSetting"
0022    CALL     3   1   2
0023    GGET     3   2      ; "assert"
0024    TGETS    3   3   3  ; "are"
0025    TGETS    3   3   4  ; "equal"
0026    KSHORT   4   1
0027    MOV      5   0
0028    CALL     3   1   3
0029    GGET     3   2      ; "assert"
0030    TGETS    3   3   3  ; "are"
0031    TGETS    3   3   4  ; "equal"
0032    KSHORT   4   1
0033    MOV      5   1
0034    CALL     3   1   3
0035    MOV      4   2
0036    TGETS    3   2   5  ; "flipSetting"
0037    CALL     3   1   2
0038    GGET     3   2      ; "assert"
0039    TGETS    3   3   3  ; "are"
0040    TGETS    3   3   4  ; "equal"
0041    KSHORT   4   1
0042    MOV      5   0
0043    CALL     3   1   3
0044    GGET     3   2      ; "assert"
0045    TGETS    3   3   3  ; "are"
0046    TGETS    3   3   4  ; "equal"
0047    KSHORT   4   2
0048    MOV      5   1
0049    CALL     3   1   3
0050    UCLO     0 => 0051
0051 => RET0     0   1

-- BYTECODE -- switch_plugin_spec.lua:89-105
0001    UGET     0   0      ; TestPlugin2
0002    MOV      1   0
0003    TGETS    0   0   0  ; "new"
0004    TDUP     2   1
0005    CALL     0   2   3
0006    GGET     1   2      ; "assert"
0007    TGETS    1   1   3  ; "are"
0008    TGETS    1   1   4  ; "equal"
0009    KSHORT   2   1
0010    TGETS    3   0   5  ; "start_called"
0011    CALL     1   1   3
0012    GGET     1   2      ; "assert"
0013    TGETS    1   1   3  ; "are"
0014    TGETS    1   1   4  ; "equal"
0015    KSHORT   2   0
0016    TGETS    3   0   6  ; "stop_called"
0017    CALL     1   1   3
0018    MOV      2   0
0019    TGETS    1   0   7  ; "flipSetting"
0020    CALL     1   1   2
0021    GGET     1   2      ; "assert"
0022    TGETS    1   1   3  ; "are"
0023    TGETS    1   1   4  ; "equal"
0024    KSHORT   2   1
0025    TGETS    3   0   5  ; "start_called"
0026    CALL     1   1   3
0027    GGET     1   2      ; "assert"
0028    TGETS    1   1   3  ; "are"
0029    TGETS    1   1   4  ; "equal"
0030    KSHORT   2   1
0031    TGETS    3   0   6  ; "stop_called"
0032    CALL     1   1   3
0033    MOV      2   0
0034    TGETS    1   0   7  ; "flipSetting"
0035    CALL     1   1   2
0036    GGET     1   2      ; "assert"
0037    TGETS    1   1   3  ; "are"
0038    TGETS    1   1   4  ; "equal"
0039    KSHORT   2   2
0040    TGETS    3   0   5  ; "start_called"
0041    CALL     1   1   3
0042    GGET     1   2      ; "assert"
0043    TGETS    1   1   3  ; "are"
0044    TGETS    1   1   4  ; "equal"
0045    KSHORT   2   1
0046    TGETS    3   0   6  ; "stop_called"
0047    CALL     1   1   3
0048    TNEW     1   0
0049    MOV      3   0
0050    TGETS    2   0   8  ; "addToMainMenu"
0051    MOV      4   1
0052    CALL     2   1   3
0053    GGET     2   2      ; "assert"
0054    TGETS    2   2   3  ; "are"
0055    TGETS    2   2   4  ; "equal"
0056    KSTR     3   9      ; "This is a test plugin2"
0057    TGETS    4   1  10  ; "test_plugin2_menu"
0058    TGETS    4   4  11  ; "text"
0059    CALL     2   1   3
0060    RET0     0   1

-- BYTECODE -- switch_plugin_spec.lua:107-117
0001    UGET     0   0      ; TestPlugin2
0002    MOV      1   0
0003    TGETS    0   0   0  ; "new"
0004    CALL     0   2   2
0005    GGET     1   1      ; "assert"
0006    TGETS    1   1   2  ; "are"
0007    TGETS    1   1   3  ; "equal"
0008    KSHORT   2   0
0009    TGETS    3   0   4  ; "start_called"
0010    CALL     1   1   3
0011    GGET     1   1      ; "assert"
0012    TGETS    1   1   2  ; "are"
0013    TGETS    1   1   3  ; "equal"
0014    KSHORT   2   1
0015    TGETS    3   0   5  ; "stop_called"
0016    CALL     1   1   3
0017    MOV      2   0
0018    TGETS    1   0   6  ; "flipSetting"
0019    CALL     1   1   2
0020    GGET     1   1      ; "assert"
0021    TGETS    1   1   2  ; "are"
0022    TGETS    1   1   3  ; "equal"
0023    KSHORT   2   1
0024    TGETS    3   0   4  ; "start_called"
0025    CALL     1   1   3
0026    GGET     1   1      ; "assert"
0027    TGETS    1   1   2  ; "are"
0028    TGETS    1   1   3  ; "equal"
0029    KSHORT   2   1
0030    TGETS    3   0   5  ; "stop_called"
0031    CALL     1   1   3
0032    MOV      2   0
0033    TGETS    1   0   6  ; "flipSetting"
0034    CALL     1   1   2
0035    GGET     1   1      ; "assert"
0036    TGETS    1   1   2  ; "are"
0037    TGETS    1   1   3  ; "equal"
0038    KSHORT   2   1
0039    TGETS    3   0   4  ; "start_called"
0040    CALL     1   1   3
0041    GGET     1   1      ; "assert"
0042    TGETS    1   1   2  ; "are"
0043    TGETS    1   1   3  ; "equal"
0044    KSHORT   2   2
0045    TGETS    3   0   5  ; "stop_called"
0046    CALL     1   1   3
0047    RET0     0   1

-- BYTECODE -- switch_plugin_spec.lua:124-126
0001    GGET     0   0      ; "assert"
0002    TGETS    0   0   1  ; "is_true"
0003    KPRI     1   1
0004    KSTR     2   2      ; "This should not reach."
0005    CALL     0   1   3
0006    RET0     0   1

-- BYTECODE -- switch_plugin_spec.lua:119-131
0001    UGET     0   0      ; SwitchPlugin
0002    MOV      1   0
0003    TGETS    0   0   0  ; "new"
0004    TDUP     2   1
0005    TDUP     3   5
0006    TDUP     4   3
0007    FNEW     5   2      ; switch_plugin_spec.lua:124
0008    TSETS    5   4   4  ; "registerToMainMenu"
0009    TSETS    4   3   6  ; "menu"
0010    TSETS    3   2   7  ; "ui"
0011    CALL     0   2   3
0012    MOV      2   0
0013    TGETS    1   0   8  ; "init"
0014    CALL     1   1   2
0015    RET0     0   1

-- BYTECODE -- switch_plugin_spec.lua:137-139
0001    USETV    0   1      ; confirm_box
0002    RET0     0   1

-- BYTECODE -- switch_plugin_spec.lua:133-164
0001    GGET     0   0      ; "require"
0002    KSTR     1   1      ; "ui/uimanager"
0003    CALL     0   2   2
0004    KPRI     1   0
0005    FNEW     2   3      ; switch_plugin_spec.lua:137
0006    TSETS    2   0   2  ; "show"
0007    UGET     2   0      ; TestPlugin2
0008    MOV      3   2
0009    TGETS    2   2   4  ; "new"
0010    CALL     2   2   2
0011    MOV      4   2
0012    TGETS    3   2   5  ; "_showConfirmBox"
0013    CALL     3   1   2
0014    GGET     3   6      ; "assert"
0015    TGETS    3   3   7  ; "is_not_nil"
0016    MOV      4   1
0017    CALL     3   1   2
0018    GGET     3   6      ; "assert"
0019    TGETS    3   3   8  ; "are"
0020    TGETS    3   3   9  ; "equal"
0021    KSTR     4  10      ; "This is a test plugin2, it's for test pu"~
0022    TGETS    5   1  11  ; "text"
0023    CALL     3   1   3
0024    GGET     3   6      ; "assert"
0025    TGETS    3   3   8  ; "are"
0026    TGETS    3   3   9  ; "equal"
0027    KSTR     4  12      ; "Enable"
0028    TGETS    5   1  13  ; "ok_text"
0029    CALL     3   1   3
0030    TGETS    3   1  14  ; "ok_callback"
0031    CALL     3   1   1
0032    KPRI     1   0
0033    MOV      4   2
0034    TGETS    3   2   5  ; "_showConfirmBox"
0035    CALL     3   1   2
0036    GGET     3   6      ; "assert"
0037    TGETS    3   3   7  ; "is_not_nil"
0038    MOV      4   1
0039    CALL     3   1   2
0040    GGET     3   6      ; "assert"
0041    TGETS    3   3   8  ; "are"
0042    TGETS    3   3   9  ; "equal"
0043    KSTR     4  15      ; "This is a test plugin2, it's for test pu"~
0044    TGETS    5   1  11  ; "text"
0045    CALL     3   1   3
0046    GGET     3   6      ; "assert"
0047    TGETS    3   3   8  ; "are"
0048    TGETS    3   3   9  ; "equal"
0049    KSTR     4  16      ; "Disable"
0050    TGETS    5   1  13  ; "ok_text"
0051    CALL     3   1   3
0052    TGETS    3   1  14  ; "ok_callback"
0053    CALL     3   1   1
0054    GGET     3   6      ; "assert"
0055    TGETS    3   3  17  ; "is_false"
0056    TGETS    4   2  18  ; "enabled"
0057    CALL     3   1   2
0058    GGET     3  19      ; "package"
0059    TGETS    3   3  20  ; "unload"
0060    KSTR     4   1      ; "ui/uimanager"
0061    CALL     3   1   2
0062    UCLO     0 => 0063
0063 => RET0     0   1

-- BYTECODE -- switch_plugin_spec.lua:1-165
0001    GGET     0   0      ; "require"
0002    KSTR     1   1      ; "commonrequire"
0003    CALL     0   1   2
0004    GGET     0   0      ; "require"
0005    KSTR     1   2      ; "ui/plugin/switch_plugin"
0006    CALL     0   2   2
0007    FNEW     1   3      ; switch_plugin_spec.lua:5
0008    MOV      3   0
0009    TGETS    2   0   4  ; "extend"
0010    CALL     2   2   2
0011    FNEW     3   6      ; switch_plugin_spec.lua:23
0012    TSETS    3   2   5  ; "new"
0013    FNEW     3   8      ; switch_plugin_spec.lua:35
0014    TSETS    3   2   7  ; "_start"
0015    FNEW     3  10      ; switch_plugin_spec.lua:39
0016    TSETS    3   2   9  ; "_stop"
0017    GGET     3  11      ; "it"
0018    KSTR     4  12      ; "should be able to create a enabled plugi"~
0019    FNEW     5  13      ; switch_plugin_spec.lua:43
0020    CALL     3   1   3
0021    GGET     3  11      ; "it"
0022    KSTR     4  14      ; "should be able to create a disabled plug"~
0023    FNEW     5  15      ; switch_plugin_spec.lua:68
0024    CALL     3   1   3
0025    GGET     3  11      ; "it"
0026    KSTR     4  16      ; "should be able to create a derived enabl"~
0027    FNEW     5  17      ; switch_plugin_spec.lua:89
0028    CALL     3   1   3
0029    GGET     3  11      ; "it"
0030    KSTR     4  18      ; "should be able to create a derived disab"~
0031    FNEW     5  19      ; switch_plugin_spec.lua:107
0032    CALL     3   1   3
0033    GGET     3  11      ; "it"
0034    KSTR     4  20      ; "should be able to create an invisible pl"~
0035    FNEW     5  21      ; switch_plugin_spec.lua:119
0036    CALL     3   1   3
0037    GGET     3  11      ; "it"
0038    KSTR     4  22      ; "should show a correct message box"
0039    FNEW     5  23      ; switch_plugin_spec.lua:133
0040    CALL     3   1   3
0041    UCLO     0 => 0042
0042 => RET0     0   1

-- BYTECODE -- switch_plugin_spec.lua:0-166
0001    GGET     0   0      ; "describe"
0002    KSTR     1   1      ; "SwitchPlugin"
0003    FNEW     2   2      ; switch_plugin_spec.lua:1
0004    CALL     0   1   3
0005    RET0     0   1

