
main <./frontend/device/sysfs_light.lua:0,0> (54 instructions, 216 bytes at 0x7ff42f4068d0)
0+ params, 8 slots, 0 upvalues, 3 locals, 34 constants, 9 functions
	1	[5]	GETGLOBAL	0 -1	; require
	2	[5]	LOADK    	1 -2	; "logger"
	3	[5]	CALL     	0 2 2
	4	[6]	GETGLOBAL	1 -1	; require
	5	[6]	LOADK    	2 -3	; "dbg"
	6	[6]	CALL     	1 2 2
	7	[8]	NEWTABLE 	2 0 17
	8	[9]	SETTABLE 	2 -4 -5	; "frontlight_white" nil
	9	[10]	SETTABLE 	2 -6 -5	; "frontlight_red" nil
	10	[11]	SETTABLE 	2 -7 -5	; "frontlight_green" nil
	11	[12]	SETTABLE 	2 -8 -5	; "frontlight_mixer" nil
	12	[13]	SETTABLE 	2 -9 -5	; "frontlight_ioctl" nil
	13	[14]	SETTABLE 	2 -10 -5	; "nl_min" nil
	14	[15]	SETTABLE 	2 -11 -5	; "nl_max" nil
	15	[16]	SETTABLE 	2 -12 -5	; "nl_inverted" nil
	16	[17]	SETTABLE 	2 -13 -14	; "current_brightness" 0
	17	[18]	SETTABLE 	2 -15 -14	; "current_warmth" 0
	18	[19]	SETTABLE 	2 -16 -17	; "white_gain" 25
	19	[20]	SETTABLE 	2 -18 -19	; "red_gain" 24
	20	[21]	SETTABLE 	2 -20 -19	; "green_gain" 24
	21	[22]	SETTABLE 	2 -21 -22	; "white_offset" -25
	22	[23]	SETTABLE 	2 -23 -14	; "red_offset" 0
	23	[24]	SETTABLE 	2 -24 -25	; "green_offset" -65
	24	[25]	SETTABLE 	2 -26 -27	; "exponent" 0.25
	25	[34]	CLOSURE  	3 0	; 0x7ff42f406f00
	26	[28]	SETTABLE 	2 -28 3	; "new" -
	27	[38]	CLOSURE  	3 1	; 0x7ff42f406630
	28	[36]	SETTABLE 	2 -29 3	; "setBrightness" -
	29	[40]	SELF     	3 1 -30	; "guard"
	30	[40]	MOVE     	5 2
	31	[40]	LOADK    	6 -29	; "setBrightness"
	32	[44]	CLOSURE  	7 2	; 0x7ff42f4075e0
	33	[40]	CALL     	3 5 1
	34	[48]	CLOSURE  	3 3	; 0x7ff42f406da0
	35	[46]	SETTABLE 	2 -31 3	; "setWarmth" -
	36	[50]	SELF     	3 1 -30	; "guard"
	37	[50]	MOVE     	5 2
	38	[50]	LOADK    	6 -31	; "setWarmth"
	39	[54]	CLOSURE  	7 4	; 0x7ff42f407d10
	40	[50]	CALL     	3 5 1
	41	[116]	CLOSURE  	3 5	; 0x7ff42f408200
	42	[56]	SETTABLE 	2 -32 3	; "setNaturalBrightness" -
	43	[118]	SELF     	3 1 -30	; "guard"
	44	[118]	MOVE     	5 2
	45	[118]	LOADK    	6 -32	; "setNaturalBrightness"
	46	[124]	CLOSURE  	7 6	; 0x7ff42f4067c0
	47	[118]	CALL     	3 5 1
	48	[135]	CLOSURE  	3 7	; 0x7ff42f407700
	49	[126]	SETTABLE 	2 -33 3	; "_set_light_value" -
	50	[150]	CLOSURE  	3 8	; 0x7ff42f408a30
	51	[150]	MOVE     	0 0
	52	[137]	SETTABLE 	2 -34 3	; "_write_value" -
	53	[152]	RETURN   	2 2
	54	[152]	RETURN   	0 1

function <./frontend/device/sysfs_light.lua:28,34> (16 instructions, 64 bytes at 0x7ff42f406f00)
2 params, 5 slots, 0 upvalues, 2 locals, 3 constants, 0 functions
	1	[29]	TEST     	1 0 1
	2	[29]	JMP      	2	; to 5
	3	[29]	NEWTABLE 	2 0 0
	4	[29]	MOVE     	1 2
	5	[30]	GETGLOBAL	2 -1	; setmetatable
	6	[30]	MOVE     	3 1
	7	[30]	MOVE     	4 0
	8	[30]	CALL     	2 3 1
	9	[31]	SETTABLE 	0 -2 0	; "__index" -
	10	[32]	GETTABLE 	2 1 -3	; "init"
	11	[32]	TEST     	2 0 0
	12	[32]	JMP      	2	; to 15
	13	[32]	SELF     	2 1 -3	; "init"
	14	[32]	CALL     	2 2 1
	15	[33]	RETURN   	1 2
	16	[34]	RETURN   	0 1

function <./frontend/device/sysfs_light.lua:36,38> (5 instructions, 20 bytes at 0x7ff42f406630)
2 params, 6 slots, 0 upvalues, 2 locals, 1 constant, 0 functions
	1	[37]	SELF     	2 0 -1	; "setNaturalBrightness"
	2	[37]	MOVE     	4 1
	3	[37]	LOADNIL  	5 5
	4	[37]	CALL     	2 4 1
	5	[38]	RETURN   	0 1

function <./frontend/device/sysfs_light.lua:41,44> (10 instructions, 40 bytes at 0x7ff42f4075e0)
2 params, 5 slots, 0 upvalues, 2 locals, 4 constants, 0 functions
	1	[42]	GETGLOBAL	2 -1	; assert
	2	[42]	LE       	0 -2 1	; 0 -
	3	[42]	JMP      	2	; to 6
	4	[42]	LE       	1 1 -3	; - 100
	5	[42]	JMP      	1	; to 7
	6	[42]	LOADBOOL 	3 0 1
	7	[42]	LOADBOOL 	3 1 0
	8	[43]	LOADK    	4 -4	; "Wrong brightness value given!"
	9	[42]	CALL     	2 3 1
	10	[44]	RETURN   	0 1

function <./frontend/device/sysfs_light.lua:46,48> (5 instructions, 20 bytes at 0x7ff42f406da0)
2 params, 6 slots, 0 upvalues, 2 locals, 1 constant, 0 functions
	1	[47]	SELF     	2 0 -1	; "setNaturalBrightness"
	2	[47]	LOADNIL  	4 4
	3	[47]	MOVE     	5 1
	4	[47]	CALL     	2 4 1
	5	[48]	RETURN   	0 1

function <./frontend/device/sysfs_light.lua:51,54> (10 instructions, 40 bytes at 0x7ff42f407d10)
2 params, 5 slots, 0 upvalues, 2 locals, 4 constants, 0 functions
	1	[52]	GETGLOBAL	2 -1	; assert
	2	[52]	LE       	0 -2 1	; 0 -
	3	[52]	JMP      	2	; to 6
	4	[52]	LE       	1 1 -3	; - 100
	5	[52]	JMP      	1	; to 7
	6	[52]	LOADBOOL 	3 0 1
	7	[52]	LOADBOOL 	3 1 0
	8	[53]	LOADK    	4 -4	; "Wrong warmth value given!"
	9	[52]	CALL     	2 3 1
	10	[54]	RETURN   	0 1

function <./frontend/device/sysfs_light.lua:56,116> (158 instructions, 632 bytes at 0x7ff42f408200)
3 params, 13 slots, 0 upvalues, 8 locals, 27 constants, 0 functions
	1	[57]	LOADBOOL 	3 1 0
	2	[58]	LOADBOOL 	4 1 0
	3	[59]	TEST     	1 0 1
	4	[59]	JMP      	2	; to 7
	5	[60]	LOADBOOL 	3 0 0
	6	[61]	GETTABLE 	1 0 -1	; "current_brightness"
	7	[63]	TEST     	2 0 1
	8	[63]	JMP      	2	; to 11
	9	[64]	LOADBOOL 	4 0 0
	10	[65]	GETTABLE 	2 0 -2	; "current_warmth"
	11	[69]	GETTABLE 	5 0 -3	; "frontlight_mixer"
	12	[69]	TEST     	5 0 0
	13	[69]	JMP      	36	; to 50
	14	[71]	GETGLOBAL	5 -4	; math
	15	[71]	GETTABLE 	5 5 -5	; "floor"
	16	[71]	GETTABLE 	6 0 -6	; "nl_max"
	17	[71]	DIV      	6 2 6
	18	[71]	CALL     	5 2 2
	19	[71]	MOVE     	2 5
	20	[72]	TEST     	3 0 0
	21	[72]	JMP      	12	; to 34
	22	[74]	GETTABLE 	5 0 -7	; "frontlight_ioctl"
	23	[74]	TEST     	5 0 0
	24	[74]	JMP      	5	; to 30
	25	[75]	GETTABLE 	5 0 -7	; "frontlight_ioctl"
	26	[75]	SELF     	5 5 -8	; "setBrightness"
	27	[75]	MOVE     	7 1
	28	[75]	CALL     	5 3 1
	29	[75]	JMP      	4	; to 34
	30	[77]	SELF     	5 0 -9	; "_write_value"
	31	[77]	GETTABLE 	7 0 -10	; "frontlight_white"
	32	[77]	MOVE     	8 1
	33	[77]	CALL     	5 4 1
	34	[81]	TEST     	4 0 0
	35	[81]	JMP      	120	; to 156
	36	[82]	GETTABLE 	5 0 -11	; "nl_inverted"
	37	[82]	TEST     	5 0 0
	38	[82]	JMP      	6	; to 45
	39	[83]	SELF     	5 0 -9	; "_write_value"
	40	[83]	GETTABLE 	7 0 -3	; "frontlight_mixer"
	41	[83]	GETTABLE 	8 0 -6	; "nl_max"
	42	[83]	SUB      	8 8 2
	43	[83]	CALL     	5 4 1
	44	[83]	JMP      	111	; to 156
	45	[85]	SELF     	5 0 -9	; "_write_value"
	46	[85]	GETTABLE 	7 0 -3	; "frontlight_mixer"
	47	[85]	MOVE     	8 2
	48	[85]	CALL     	5 4 1
	49	[87]	JMP      	106	; to 156
	50	[89]	LOADK    	5 -12	; 0
	51	[90]	LOADK    	6 -12	; 0
	52	[91]	LOADK    	7 -12	; 0
	53	[92]	LT       	0 -12 1	; 0 -
	54	[92]	JMP      	20	; to 75
	55	[95]	GETGLOBAL	8 -4	; math
	56	[95]	GETTABLE 	8 8 -13	; "min"
	57	[95]	GETTABLE 	9 0 -14	; "white_gain"
	58	[95]	GETGLOBAL	10 -4	; math
	59	[95]	GETTABLE 	10 10 -15	; "pow"
	60	[95]	MOVE     	11 1
	61	[95]	GETTABLE 	12 0 -16	; "exponent"
	62	[95]	CALL     	10 3 2
	63	[95]	MUL      	9 9 10
	64	[96]	GETGLOBAL	10 -4	; math
	65	[96]	GETTABLE 	10 10 -15	; "pow"
	66	[96]	SUB      	11 -17 2	; 100 -
	67	[96]	GETTABLE 	12 0 -16	; "exponent"
	68	[96]	CALL     	10 3 2
	69	[96]	MUL      	9 9 10
	70	[96]	GETTABLE 	10 0 -18	; "white_offset"
	71	[96]	ADD      	9 9 10
	72	[96]	LOADK    	10 -19	; 255
	73	[95]	CALL     	8 3 2
	74	[96]	MOVE     	7 8
	75	[98]	LT       	0 -12 2	; 0 -
	76	[98]	JMP      	40	; to 117
	77	[99]	GETGLOBAL	8 -4	; math
	78	[99]	GETTABLE 	8 8 -13	; "min"
	79	[99]	GETTABLE 	9 0 -20	; "red_gain"
	80	[99]	GETGLOBAL	10 -4	; math
	81	[99]	GETTABLE 	10 10 -15	; "pow"
	82	[99]	MOVE     	11 1
	83	[99]	GETTABLE 	12 0 -16	; "exponent"
	84	[99]	CALL     	10 3 2
	85	[99]	MUL      	9 9 10
	86	[100]	GETGLOBAL	10 -4	; math
	87	[100]	GETTABLE 	10 10 -15	; "pow"
	88	[100]	MOVE     	11 2
	89	[100]	GETTABLE 	12 0 -16	; "exponent"
	90	[100]	CALL     	10 3 2
	91	[100]	MUL      	9 9 10
	92	[100]	GETTABLE 	10 0 -21	; "red_offset"
	93	[100]	ADD      	9 9 10
	94	[100]	LOADK    	10 -19	; 255
	95	[99]	CALL     	8 3 2
	96	[100]	MOVE     	5 8
	97	[101]	GETGLOBAL	8 -4	; math
	98	[101]	GETTABLE 	8 8 -13	; "min"
	99	[101]	GETTABLE 	9 0 -22	; "green_gain"
	100	[101]	GETGLOBAL	10 -4	; math
	101	[101]	GETTABLE 	10 10 -15	; "pow"
	102	[101]	MOVE     	11 1
	103	[101]	GETTABLE 	12 0 -16	; "exponent"
	104	[101]	CALL     	10 3 2
	105	[101]	MUL      	9 9 10
	106	[102]	GETGLOBAL	10 -4	; math
	107	[102]	GETTABLE 	10 10 -15	; "pow"
	108	[102]	MOVE     	11 2
	109	[102]	GETTABLE 	12 0 -16	; "exponent"
	110	[102]	CALL     	10 3 2
	111	[102]	MUL      	9 9 10
	112	[102]	GETTABLE 	10 0 -23	; "green_offset"
	113	[102]	ADD      	9 9 10
	114	[102]	LOADK    	10 -19	; 255
	115	[101]	CALL     	8 3 2
	116	[102]	MOVE     	6 8
	117	[105]	GETGLOBAL	8 -4	; math
	118	[105]	GETTABLE 	8 8 -24	; "max"
	119	[105]	MOVE     	9 7
	120	[105]	LOADK    	10 -12	; 0
	121	[105]	CALL     	8 3 2
	122	[105]	MOVE     	7 8
	123	[106]	GETGLOBAL	8 -4	; math
	124	[106]	GETTABLE 	8 8 -24	; "max"
	125	[106]	MOVE     	9 5
	126	[106]	LOADK    	10 -12	; 0
	127	[106]	CALL     	8 3 2
	128	[106]	MOVE     	5 8
	129	[107]	GETGLOBAL	8 -4	; math
	130	[107]	GETTABLE 	8 8 -24	; "max"
	131	[107]	MOVE     	9 6
	132	[107]	LOADK    	10 -12	; 0
	133	[107]	CALL     	8 3 2
	134	[107]	MOVE     	6 8
	135	[109]	SELF     	8 0 -25	; "_set_light_value"
	136	[109]	GETTABLE 	10 0 -10	; "frontlight_white"
	137	[109]	GETGLOBAL	11 -4	; math
	138	[109]	GETTABLE 	11 11 -5	; "floor"
	139	[109]	MOVE     	12 7
	140	[109]	CALL     	11 2 0
	141	[109]	CALL     	8 0 1
	142	[110]	SELF     	8 0 -25	; "_set_light_value"
	143	[110]	GETTABLE 	10 0 -26	; "frontlight_green"
	144	[110]	GETGLOBAL	11 -4	; math
	145	[110]	GETTABLE 	11 11 -5	; "floor"
	146	[110]	MOVE     	12 6
	147	[110]	CALL     	11 2 0
	148	[110]	CALL     	8 0 1
	149	[111]	SELF     	8 0 -25	; "_set_light_value"
	150	[111]	GETTABLE 	10 0 -27	; "frontlight_red"
	151	[111]	GETGLOBAL	11 -4	; math
	152	[111]	GETTABLE 	11 11 -5	; "floor"
	153	[111]	MOVE     	12 5
	154	[111]	CALL     	11 2 0
	155	[111]	CALL     	8 0 1
	156	[114]	SETTABLE 	0 -1 1	; "current_brightness" -
	157	[115]	SETTABLE 	0 -2 2	; "current_warmth" -
	158	[116]	RETURN   	0 1

function <./frontend/device/sysfs_light.lua:119,124> (23 instructions, 92 bytes at 0x7ff42f4067c0)
3 params, 6 slots, 0 upvalues, 3 locals, 6 constants, 0 functions
	1	[120]	GETGLOBAL	3 -1	; assert
	2	[120]	EQ       	1 1 -2	; - nil
	3	[120]	JMP      	5	; to 9
	4	[120]	LE       	0 -3 1	; 0 -
	5	[120]	JMP      	2	; to 8
	6	[120]	LE       	1 1 -4	; - 100
	7	[120]	JMP      	1	; to 9
	8	[120]	LOADBOOL 	4 0 1
	9	[120]	LOADBOOL 	4 1 0
	10	[121]	LOADK    	5 -5	; "Wrong brightness value given!"
	11	[120]	CALL     	3 3 1
	12	[122]	GETGLOBAL	3 -1	; assert
	13	[122]	EQ       	1 2 -2	; - nil
	14	[122]	JMP      	5	; to 20
	15	[122]	LE       	0 -3 2	; 0 -
	16	[122]	JMP      	2	; to 19
	17	[122]	LE       	1 2 -4	; - 100
	18	[122]	JMP      	1	; to 20
	19	[122]	LOADBOOL 	4 0 1
	20	[122]	LOADBOOL 	4 1 0
	21	[123]	LOADK    	5 -6	; "Wrong warmth value given!"
	22	[122]	CALL     	3 3 1
	23	[124]	RETURN   	0 1

function <./frontend/device/sysfs_light.lua:126,135> (25 instructions, 100 bytes at 0x7ff42f407700)
3 params, 7 slots, 0 upvalues, 3 locals, 5 constants, 0 functions
	1	[127]	TEST     	1 0 1
	2	[127]	JMP      	1	; to 4
	3	[127]	RETURN   	0 1
	4	[129]	LT       	0 -1 2	; 0 -
	5	[129]	JMP      	7	; to 13
	6	[130]	SELF     	3 0 -2	; "_write_value"
	7	[130]	MOVE     	5 1
	8	[130]	LOADK    	6 -3	; "/bl_power"
	9	[130]	CONCAT   	5 5 6
	10	[130]	LOADK    	6 -4	; 31
	11	[130]	CALL     	3 4 1
	12	[130]	JMP      	6	; to 19
	13	[132]	SELF     	3 0 -2	; "_write_value"
	14	[132]	MOVE     	5 1
	15	[132]	LOADK    	6 -3	; "/bl_power"
	16	[132]	CONCAT   	5 5 6
	17	[132]	LOADK    	6 -1	; 0
	18	[132]	CALL     	3 4 1
	19	[134]	SELF     	3 0 -2	; "_write_value"
	20	[134]	MOVE     	5 1
	21	[134]	LOADK    	6 -5	; "/brightness"
	22	[134]	CONCAT   	5 5 6
	23	[134]	MOVE     	6 2
	24	[134]	CALL     	3 4 1
	25	[135]	RETURN   	0 1

function <./frontend/device/sysfs_light.lua:137,150> (34 instructions, 136 bytes at 0x7ff42f408a30)
3 params, 11 slots, 1 upvalue, 7 locals, 8 constants, 0 functions
	1	[138]	GETGLOBAL	3 -1	; io
	2	[138]	GETTABLE 	3 3 -2	; "open"
	3	[138]	MOVE     	4 1
	4	[138]	LOADK    	5 -3	; "w"
	5	[138]	CALL     	3 3 2
	6	[139]	TEST     	3 0 1
	7	[139]	JMP      	7	; to 15
	8	[140]	GETUPVAL 	4 0	; logger
	9	[140]	GETTABLE 	4 4 -4	; "err"
	10	[140]	LOADK    	5 -5	; "Could not open file: "
	11	[140]	MOVE     	6 1
	12	[140]	CALL     	4 3 1
	13	[141]	LOADBOOL 	4 0 0
	14	[141]	RETURN   	4 2
	15	[143]	SELF     	4 3 -6	; "write"
	16	[143]	MOVE     	6 2
	17	[143]	CALL     	4 3 4
	18	[144]	GETGLOBAL	7 -1	; io
	19	[144]	GETTABLE 	7 7 -7	; "close"
	20	[144]	MOVE     	8 3
	21	[144]	CALL     	7 2 1
	22	[145]	TEST     	4 0 1
	23	[145]	JMP      	8	; to 32
	24	[146]	GETUPVAL 	7 0	; logger
	25	[146]	GETTABLE 	7 7 -4	; "err"
	26	[146]	LOADK    	8 -8	; "Write error: "
	27	[146]	MOVE     	9 5
	28	[146]	MOVE     	10 6
	29	[146]	CALL     	7 4 1
	30	[147]	LOADBOOL 	7 0 0
	31	[147]	RETURN   	7 2
	32	[149]	LOADBOOL 	7 1 0
	33	[149]	RETURN   	7 2
	34	[150]	RETURN   	0 1
