
main <./plugins/statistics.koplugin/tableutil.lua:0,0> (5 instructions, 20 bytes at 0x7f90414068f0)
0+ params, 2 slots, 0 upvalues, 1 local, 1 constant, 1 function
	1	[1]	NEWTABLE 	0 0 0
	2	[26]	CLOSURE  	1 0	; 0x7f9041406ba0
	3	[5]	SETTABLE 	0 -1 1	; "spairs" -
	4	[28]	RETURN   	0 2
	5	[28]	RETURN   	0 1

function <./plugins/statistics.koplugin/tableutil.lua:5,26> (31 instructions, 124 bytes at 0x7f9041406ba0)
2 params, 9 slots, 0 upvalues, 8 locals, 5 constants, 2 functions
	1	[7]	NEWTABLE 	2 0 0
	2	[8]	GETGLOBAL	3 -1	; pairs
	3	[8]	MOVE     	4 0
	4	[8]	CALL     	3 2 4
	5	[8]	JMP      	3	; to 9
	6	[8]	LEN      	7 2
	7	[8]	ADD      	7 7 -2	; - 1
	8	[8]	SETTABLE 	2 7 6
	9	[8]	TFORLOOP 	3 1
	10	[8]	JMP      	-5	; to 6
	11	[12]	TEST     	1 0 0
	12	[12]	JMP      	8	; to 21
	13	[13]	GETGLOBAL	3 -3	; table
	14	[13]	GETTABLE 	3 3 -4	; "sort"
	15	[13]	MOVE     	4 2
	16	[13]	CLOSURE  	5 0	; 0x7f9041406f20
	17	[13]	MOVE     	0 1
	18	[13]	MOVE     	0 0
	19	[13]	CALL     	3 3 1
	20	[13]	JMP      	4	; to 25
	21	[15]	GETGLOBAL	3 -3	; table
	22	[15]	GETTABLE 	3 3 -4	; "sort"
	23	[15]	MOVE     	4 2
	24	[15]	CALL     	3 2 1
	25	[19]	LOADK    	3 -5	; 0
	26	[25]	CLOSURE  	4 1	; 0x7f9041406e30
	27	[25]	MOVE     	0 3
	28	[25]	MOVE     	0 2
	29	[25]	MOVE     	0 0
	30	[25]	RETURN   	4 2
	31	[26]	RETURN   	0 1

function <./plugins/statistics.koplugin/tableutil.lua:13,13> (7 instructions, 28 bytes at 0x7f9041406f20)
2 params, 6 slots, 2 upvalues, 2 locals, 0 constants, 0 functions
	1	[13]	GETUPVAL 	2 0	; order
	2	[13]	GETUPVAL 	3 1	; t
	3	[13]	MOVE     	4 0
	4	[13]	MOVE     	5 1
	5	[13]	TAILCALL 	2 4 0
	6	[13]	RETURN   	2 0
	7	[13]	RETURN   	0 1

function <./plugins/statistics.koplugin/tableutil.lua:20,25> (18 instructions, 72 bytes at 0x7f9041406e30)
0 params, 4 slots, 3 upvalues, 0 locals, 1 constant, 0 functions
	1	[21]	GETUPVAL 	0 0	; i
	2	[21]	ADD      	0 0 -1	; - 1
	3	[21]	SETUPVAL 	0 0	; i
	4	[22]	GETUPVAL 	0 1	; keys
	5	[22]	GETUPVAL 	1 0	; i
	6	[22]	GETTABLE 	0 0 1
	7	[22]	TEST     	0 0 0
	8	[22]	JMP      	9	; to 18
	9	[23]	GETUPVAL 	0 1	; keys
	10	[23]	GETUPVAL 	1 0	; i
	11	[23]	GETTABLE 	0 0 1
	12	[23]	GETUPVAL 	1 2	; t
	13	[23]	GETUPVAL 	2 1	; keys
	14	[23]	GETUPVAL 	3 0	; i
	15	[23]	GETTABLE 	2 2 3
	16	[23]	GETTABLE 	1 1 2
	17	[23]	RETURN   	0 3
	18	[25]	RETURN   	0 1
