
main <./frontend/ui/widget/textwidget.lua:0,0> (108 instructions, 432 bytes at 0x7ff2dbc068d0)
0+ params, 16 slots, 0 upvalues, 11 locals, 56 constants, 14 functions
	1	[15]	GETGLOBAL	0 -1	; require
	2	[15]	LOADK    	1 -2	; "ffi/blitbuffer"
	3	[15]	CALL     	0 2 2
	4	[16]	GETGLOBAL	1 -1	; require
	5	[16]	LOADK    	2 -3	; "ui/font"
	6	[16]	CALL     	1 2 2
	7	[17]	GETGLOBAL	2 -1	; require
	8	[17]	LOADK    	3 -4	; "ui/geometry"
	9	[17]	CALL     	2 2 2
	10	[18]	GETGLOBAL	3 -1	; require
	11	[18]	LOADK    	4 -5	; "optmath"
	12	[18]	CALL     	3 2 2
	13	[19]	GETGLOBAL	4 -1	; require
	14	[19]	LOADK    	5 -6	; "ui/rendertext"
	15	[19]	CALL     	4 2 2
	16	[20]	GETGLOBAL	5 -1	; require
	17	[20]	LOADK    	6 -7	; "ui/size"
	18	[20]	CALL     	5 2 2
	19	[21]	GETGLOBAL	6 -1	; require
	20	[21]	LOADK    	7 -8	; "ui/widget/widget"
	21	[21]	CALL     	6 2 2
	22	[22]	GETGLOBAL	7 -1	; require
	23	[22]	LOADK    	8 -9	; "device"
	24	[22]	CALL     	7 2 2
	25	[22]	GETTABLE 	7 7 -10	; "screen"
	26	[23]	GETGLOBAL	8 -1	; require
	27	[23]	LOADK    	9 -11	; "dbg"
	28	[23]	CALL     	8 2 2
	29	[24]	GETGLOBAL	9 -1	; require
	30	[24]	LOADK    	10 -12	; "util"
	31	[24]	CALL     	9 2 2
	32	[26]	SELF     	10 6 -13	; "new"
	33	[26]	NEWTABLE 	12 0 19
	34	[27]	SETTABLE 	12 -14 -15	; "text" nil
	35	[28]	SETTABLE 	12 -16 -15	; "face" nil
	36	[29]	SETTABLE 	12 -17 -18	; "bold" false
	37	[32]	GETTABLE 	13 0 -20	; "COLOR_BLACK"
	38	[32]	SETTABLE 	12 -19 13	; "fgcolor" -
	39	[33]	GETTABLE 	13 5 -21	; "padding"
	40	[33]	GETTABLE 	13 13 -22	; "small"
	41	[33]	SETTABLE 	12 -21 13	; "padding" -
	42	[35]	SETTABLE 	12 -23 -15	; "max_width" nil
	43	[36]	SETTABLE 	12 -24 -25	; "truncate_with_ellipsis" true
	44	[37]	SETTABLE 	12 -26 -18	; "truncate_left" false
	45	[40]	SETTABLE 	12 -27 -15	; "_updated" nil
	46	[41]	SETTABLE 	12 -28 -15	; "_face_adjusted" nil
	47	[42]	SETTABLE 	12 -29 -15	; "_text_to_draw" nil
	48	[43]	SETTABLE 	12 -30 -31	; "_length" 0
	49	[44]	SETTABLE 	12 -32 -31	; "_height" 0
	50	[45]	SETTABLE 	12 -33 -31	; "_baseline_h" 0
	51	[46]	SETTABLE 	12 -34 -35	; "_maxlength" 1200
	52	[49]	GETGLOBAL	13 -37	; G_reader_settings
	53	[49]	SELF     	13 13 -38	; "nilOrTrue"
	54	[49]	LOADK    	15 -36	; "use_xtext"
	55	[49]	CALL     	13 3 2
	56	[49]	SETTABLE 	12 -36 13	; "use_xtext" -
	57	[50]	SETTABLE 	12 -39 -15	; "lang" nil
	58	[51]	SETTABLE 	12 -40 -15	; "para_direction_rtl" nil
	59	[52]	SETTABLE 	12 -41 -18	; "auto_para_direction" false
	60	[55]	SETTABLE 	12 -42 -15	; "_xtext" nil
	61	[56]	SETTABLE 	12 -43 -15	; "_xshaping" nil
	62	[26]	CALL     	10 3 2
	63	[80]	CLOSURE  	11 0	; 0x7ff2dbc06ff0
	64	[80]	MOVE     	0 1
	65	[62]	SETTABLE 	10 -44 11	; "getFontSizeToFitHeight" -
	66	[168]	CLOSURE  	11 1	; 0x7ff2dbc07070
	67	[168]	MOVE     	0 1
	68	[168]	MOVE     	0 3
	69	[168]	MOVE     	0 4
	70	[168]	MOVE     	0 7
	71	[168]	MOVE     	0 9
	72	[82]	SETTABLE 	10 -45 11	; "updateSize" -
	73	[169]	SELF     	11 8 -46	; "guard"
	74	[169]	MOVE     	13 10
	75	[169]	LOADK    	14 -45	; "updateSize"
	76	[173]	CLOSURE  	15 2	; 0x7ff2dbc07970
	77	[169]	CALL     	11 5 1
	78	[225]	CLOSURE  	11 3	; 0x7ff2dbc07e50
	79	[225]	MOVE     	0 10
	80	[225]	MOVE     	0 4
	81	[175]	SETTABLE 	10 -47 11	; "_measureWithXText" -
	82	[276]	CLOSURE  	11 4	; 0x7ff2dbc08780
	83	[234]	SETTABLE 	10 -48 11	; "getFittedText" -
	84	[284]	CLOSURE  	11 5	; 0x7ff2dbc08cb0
	85	[284]	MOVE     	0 2
	86	[278]	SETTABLE 	10 -49 11	; "getSize" -
	87	[289]	CLOSURE  	11 6	; 0x7ff2dbc09630
	88	[286]	SETTABLE 	10 -50 11	; "getWidth" -
	89	[294]	CLOSURE  	11 7	; 0x7ff2dbc09a20
	90	[291]	SETTABLE 	10 -51 11	; "getBaseline" -
	91	[302]	CLOSURE  	11 8	; 0x7ff2dbc09c90
	92	[296]	SETTABLE 	10 -52 11	; "setText" -
	93	[303]	SELF     	11 8 -46	; "guard"
	94	[303]	MOVE     	13 10
	95	[303]	LOADK    	14 -52	; "setText"
	96	[307]	CLOSURE  	15 9	; 0x7ff2dbc09f80
	97	[303]	CALL     	11 5 1
	98	[315]	CLOSURE  	11 10	; 0x7ff2dbc0a560
	99	[309]	SETTABLE 	10 -53 11	; "setMaxWidth" -
	100	[357]	CLOSURE  	11 11	; 0x7ff2dbc0a690
	101	[357]	MOVE     	0 4
	102	[317]	SETTABLE 	10 -54 11	; "paintTo" -
	103	[364]	CLOSURE  	11 12	; 0x7ff2dbc0af50
	104	[359]	SETTABLE 	10 -55 11	; "free" -
	105	[370]	CLOSURE  	11 13	; 0x7ff2dbc0adf0
	106	[366]	SETTABLE 	10 -56 11	; "onCloseWidget" -
	107	[372]	RETURN   	10 2
	108	[372]	RETURN   	0 1

function <./frontend/ui/widget/textwidget.lua:62,80> (26 instructions, 104 bytes at 0x7ff2dbc06ff0)
4 params, 9 slots, 1 upvalue, 7 locals, 8 constants, 0 functions
	1	[64]	TEST     	3 0 1
	2	[64]	JMP      	1	; to 4
	3	[65]	GETTABLE 	3 0 -1	; "padding"
	4	[69]	MOVE     	4 2
	5	[71]	SUB      	4 4 -2	; - 1
	6	[72]	LE       	0 4 -2	; - 1
	7	[72]	JMP      	1	; to 9
	8	[73]	JMP      	16	; to 25
	9	[75]	GETUPVAL 	5 0	; Font
	10	[75]	SELF     	5 5 -3	; "getFace"
	11	[75]	MOVE     	7 1
	12	[75]	MOVE     	8 4
	13	[75]	CALL     	5 4 2
	14	[76]	GETTABLE 	6 5 -4	; "ftface"
	15	[76]	SELF     	6 6 -5	; "getHeightAndAscender"
	16	[76]	CALL     	6 2 2
	17	[77]	GETGLOBAL	7 -6	; math
	18	[77]	GETTABLE 	7 7 -7	; "ceil"
	19	[77]	MOVE     	8 6
	20	[77]	CALL     	7 2 2
	21	[77]	MUL      	8 -8 3	; 2 -
	22	[77]	ADD      	6 7 8
	23	[78]	LE       	0 6 2
	24	[78]	JMP      	-20	; to 5
	25	[79]	RETURN   	4 2
	26	[80]	RETURN   	0 1

function <./frontend/ui/widget/textwidget.lua:82,168> (152 instructions, 608 bytes at 0x7ff2dbc07070)
1 param, 12 slots, 5 upvalues, 5 locals, 36 constants, 0 functions
	1	[83]	GETTABLE 	1 0 -1	; "_updated"
	2	[83]	TEST     	1 0 0
	3	[83]	JMP      	1	; to 5
	4	[84]	RETURN   	0 1
	5	[86]	SETTABLE 	0 -1 -2	; "_updated" true
	6	[88]	GETTABLE 	1 0 -3	; "_face_adjusted"
	7	[88]	TEST     	1 0 1
	8	[88]	JMP      	8	; to 17
	9	[89]	SETTABLE 	0 -3 -2	; "_face_adjusted" true
	10	[94]	GETUPVAL 	1 0	; Font
	11	[94]	SELF     	1 1 -6	; "getAdjustedFace"
	12	[94]	GETTABLE 	3 0 -4	; "face"
	13	[94]	GETTABLE 	4 0 -5	; "bold"
	14	[94]	CALL     	1 4 3
	15	[94]	SETTABLE 	0 -5 2	; "bold" -
	16	[94]	SETTABLE 	0 -4 1	; "face" -
	17	[104]	GETTABLE 	1 0 -4	; "face"
	18	[104]	GETTABLE 	1 1 -7	; "ftface"
	19	[104]	SELF     	1 1 -8	; "getHeightAndAscender"
	20	[104]	CALL     	1 2 3
	21	[105]	GETGLOBAL	3 -10	; math
	22	[105]	GETTABLE 	3 3 -11	; "ceil"
	23	[105]	MOVE     	4 1
	24	[105]	CALL     	3 2 2
	25	[105]	GETTABLE 	4 0 -12	; "padding"
	26	[105]	MUL      	4 -13 4	; 2 -
	27	[105]	ADD      	3 3 4
	28	[105]	SETTABLE 	0 -9 3	; "_height" -
	29	[106]	GETUPVAL 	3 1	; Math
	30	[106]	GETTABLE 	3 3 -15	; "round"
	31	[106]	MOVE     	4 2
	32	[106]	CALL     	3 2 2
	33	[106]	GETTABLE 	4 0 -12	; "padding"
	34	[106]	ADD      	3 3 4
	35	[106]	SETTABLE 	0 -14 3	; "_baseline_h" -
	36	[110]	GETTABLE 	3 0 -16	; "text"
	37	[110]	TEST     	3 0 0
	38	[110]	JMP      	9	; to 48
	39	[110]	GETGLOBAL	3 -17	; type
	40	[110]	GETTABLE 	4 0 -16	; "text"
	41	[110]	CALL     	3 2 2
	42	[110]	EQ       	1 3 -18	; - "string"
	43	[110]	JMP      	4	; to 48
	44	[111]	GETGLOBAL	3 -19	; tostring
	45	[111]	GETTABLE 	4 0 -16	; "text"
	46	[111]	CALL     	3 2 2
	47	[111]	SETTABLE 	0 -16 3	; "text" -
	48	[113]	SETTABLE 	0 -20 -21	; "_is_empty" false
	49	[114]	GETTABLE 	3 0 -16	; "text"
	50	[114]	TEST     	3 0 0
	51	[114]	JMP      	4	; to 56
	52	[114]	GETTABLE 	3 0 -16	; "text"
	53	[114]	LEN      	3 3
	54	[114]	EQ       	0 3 -22	; - 0
	55	[114]	JMP      	3	; to 59
	56	[115]	SETTABLE 	0 -20 -2	; "_is_empty" true
	57	[116]	SETTABLE 	0 -23 -22	; "_length" 0
	58	[117]	RETURN   	0 1
	59	[121]	GETTABLE 	3 0 -24	; "use_xtext"
	60	[121]	TEST     	3 0 0
	61	[121]	JMP      	3	; to 65
	62	[122]	SELF     	3 0 -25	; "_measureWithXText"
	63	[122]	CALL     	3 2 1
	64	[123]	RETURN   	0 1
	65	[133]	GETTABLE 	3 0 -16	; "text"
	66	[133]	SETTABLE 	0 -26 3	; "_text_to_draw" -
	67	[137]	GETUPVAL 	3 2	; RenderText
	68	[137]	SELF     	3 3 -27	; "sizeUtf8Text"
	69	[137]	LOADK    	5 -22	; 0
	70	[137]	GETUPVAL 	6 3	; Screen
	71	[137]	SELF     	6 6 -28	; "getWidth"
	72	[137]	CALL     	6 2 2
	73	[137]	GETTABLE 	7 0 -4	; "face"
	74	[137]	GETTABLE 	8 0 -26	; "_text_to_draw"
	75	[137]	LOADBOOL 	9 1 0
	76	[137]	GETTABLE 	10 0 -5	; "bold"
	77	[137]	CALL     	3 8 2
	78	[142]	GETGLOBAL	4 -10	; math
	79	[142]	GETTABLE 	4 4 -29	; "floor"
	80	[142]	GETTABLE 	5 3 -30	; "x"
	81	[142]	CALL     	4 2 2
	82	[142]	SETTABLE 	0 -23 4	; "_length" -
	83	[145]	GETTABLE 	4 0 -31	; "max_width"
	84	[145]	TEST     	4 0 0
	85	[145]	JMP      	66	; to 152
	86	[145]	GETTABLE 	4 0 -23	; "_length"
	87	[145]	GETTABLE 	5 0 -31	; "max_width"
	88	[145]	LT       	0 5 4
	89	[145]	JMP      	62	; to 152
	90	[146]	GETTABLE 	4 0 -32	; "truncate_left"
	91	[146]	TEST     	4 0 0
	92	[146]	JMP      	32	; to 125
	93	[153]	GETUPVAL 	4 4	; util
	94	[153]	GETTABLE 	4 4 -33	; "utf8Reverse"
	95	[153]	GETTABLE 	5 0 -26	; "_text_to_draw"
	96	[153]	CALL     	4 2 2
	97	[154]	GETTABLE 	5 0 -34	; "truncate_with_ellipsis"
	98	[154]	TEST     	5 0 0
	99	[154]	JMP      	10	; to 110
	100	[155]	GETUPVAL 	5 2	; RenderText
	101	[155]	SELF     	5 5 -35	; "truncateTextByWidth"
	102	[155]	MOVE     	7 4
	103	[155]	GETTABLE 	8 0 -4	; "face"
	104	[155]	GETTABLE 	9 0 -31	; "max_width"
	105	[155]	LOADBOOL 	10 0 0
	106	[155]	GETTABLE 	11 0 -5	; "bold"
	107	[155]	CALL     	5 7 2
	108	[155]	MOVE     	4 5
	109	[155]	JMP      	9	; to 119
	110	[157]	GETUPVAL 	5 2	; RenderText
	111	[157]	SELF     	5 5 -36	; "getSubTextByWidth"
	112	[157]	MOVE     	7 4
	113	[157]	GETTABLE 	8 0 -4	; "face"
	114	[157]	GETTABLE 	9 0 -31	; "max_width"
	115	[157]	LOADBOOL 	10 0 0
	116	[157]	GETTABLE 	11 0 -5	; "bold"
	117	[157]	CALL     	5 7 2
	118	[157]	MOVE     	4 5
	119	[159]	GETUPVAL 	5 4	; util
	120	[159]	GETTABLE 	5 5 -33	; "utf8Reverse"
	121	[159]	MOVE     	6 4
	122	[159]	CALL     	5 2 2
	123	[159]	SETTABLE 	0 -26 5	; "_text_to_draw" -
	124	[159]	JMP      	12	; to 137
	125	[160]	GETTABLE 	4 0 -34	; "truncate_with_ellipsis"
	126	[160]	TEST     	4 0 0
	127	[160]	JMP      	9	; to 137
	128	[161]	GETUPVAL 	4 2	; RenderText
	129	[161]	SELF     	4 4 -35	; "truncateTextByWidth"
	130	[161]	GETTABLE 	6 0 -26	; "_text_to_draw"
	131	[161]	GETTABLE 	7 0 -4	; "face"
	132	[161]	GETTABLE 	8 0 -31	; "max_width"
	133	[161]	LOADBOOL 	9 1 0
	134	[161]	GETTABLE 	10 0 -5	; "bold"
	135	[161]	CALL     	4 7 2
	136	[161]	SETTABLE 	0 -26 4	; "_text_to_draw" -
	137	[165]	GETUPVAL 	4 2	; RenderText
	138	[165]	SELF     	4 4 -27	; "sizeUtf8Text"
	139	[165]	LOADK    	6 -22	; 0
	140	[165]	GETTABLE 	7 0 -31	; "max_width"
	141	[165]	GETTABLE 	8 0 -4	; "face"
	142	[165]	GETTABLE 	9 0 -26	; "_text_to_draw"
	143	[165]	LOADBOOL 	10 1 0
	144	[165]	GETTABLE 	11 0 -5	; "bold"
	145	[165]	CALL     	4 8 2
	146	[165]	MOVE     	3 4
	147	[166]	GETGLOBAL	4 -10	; math
	148	[166]	GETTABLE 	4 4 -29	; "floor"
	149	[166]	GETTABLE 	5 3 -30	; "x"
	150	[166]	CALL     	4 2 2
	151	[166]	SETTABLE 	0 -23 4	; "_length" -
	152	[168]	RETURN   	0 1

function <./frontend/ui/widget/textwidget.lua:170,173> (11 instructions, 44 bytes at 0x7ff2dbc07970)
1 param, 4 slots, 0 upvalues, 1 local, 5 constants, 0 functions
	1	[171]	GETGLOBAL	1 -1	; assert
	2	[171]	GETGLOBAL	2 -2	; type
	3	[171]	GETTABLE 	3 0 -3	; "text"
	4	[171]	CALL     	2 2 2
	5	[171]	EQ       	1 2 -4	; - "string"
	6	[171]	JMP      	1	; to 8
	7	[171]	LOADBOOL 	2 0 1
	8	[171]	LOADBOOL 	2 1 0
	9	[172]	LOADK    	3 -5	; "Wrong text type (expected string)"
	10	[171]	CALL     	1 3 1
	11	[173]	RETURN   	0 1

function <./frontend/ui/widget/textwidget.lua:175,225> (96 instructions, 384 bytes at 0x7ff2dbc07e50)
1 param, 9 slots, 2 upvalues, 5 locals, 31 constants, 0 functions
	1	[176]	GETTABLE 	1 0 -1	; "_xtext_loaded"
	2	[176]	TEST     	1 0 1
	3	[176]	JMP      	5	; to 9
	4	[177]	GETGLOBAL	1 -2	; require
	5	[177]	LOADK    	2 -3	; "libs/libkoreader-xtext"
	6	[177]	CALL     	1 2 1
	7	[178]	GETUPVAL 	1 0	; TextWidget
	8	[178]	SETTABLE 	1 -1 -4	; "_xtext_loaded" true
	9	[180]	GETGLOBAL	1 -6	; xtext
	10	[180]	GETTABLE 	1 1 -7	; "new"
	11	[180]	GETTABLE 	2 0 -8	; "text"
	12	[180]	GETTABLE 	3 0 -9	; "face"
	13	[180]	GETTABLE 	4 0 -10	; "auto_para_direction"
	14	[181]	GETTABLE 	5 0 -11	; "para_direction_rtl"
	15	[181]	GETTABLE 	6 0 -12	; "lang"
	16	[180]	CALL     	1 6 2
	17	[181]	SETTABLE 	0 -5 1	; "_xtext" -
	18	[182]	GETTABLE 	1 0 -5	; "_xtext"
	19	[182]	SELF     	1 1 -13	; "measure"
	20	[182]	CALL     	1 2 1
	21	[183]	GETTABLE 	1 0 -5	; "_xtext"
	22	[183]	SELF     	1 1 -15	; "getWidth"
	23	[183]	CALL     	1 2 2
	24	[183]	SETTABLE 	0 -14 1	; "_length" -
	25	[184]	SETTABLE 	0 -16 -17	; "_xshaping" nil
	26	[187]	SETTABLE 	0 -18 -19	; "_shape_start" 1
	27	[188]	GETTABLE 	1 0 -5	; "_xtext"
	28	[188]	LEN      	1 1
	29	[188]	SETTABLE 	0 -20 1	; "_shape_end" -
	30	[189]	SETTABLE 	0 -21 -17	; "_shape_idx_to_substitute_with_ellipsis" nil
	31	[192]	GETTABLE 	1 0 -22	; "max_width"
	32	[192]	TEST     	1 0 0
	33	[192]	JMP      	62	; to 96
	34	[192]	GETTABLE 	1 0 -14	; "_length"
	35	[192]	GETTABLE 	2 0 -22	; "max_width"
	36	[192]	LT       	0 2 1
	37	[192]	JMP      	58	; to 96
	38	[193]	LOADK    	1 -19	; 1
	39	[194]	LOADK    	2 -23	; 0
	40	[195]	GETTABLE 	3 0 -24	; "truncate_with_ellipsis"
	41	[195]	TEST     	3 0 0
	42	[195]	JMP      	5	; to 48
	43	[204]	GETUPVAL 	3 1	; RenderText
	44	[204]	SELF     	3 3 -25	; "getEllipsisWidth"
	45	[204]	GETTABLE 	5 0 -9	; "face"
	46	[204]	CALL     	3 3 2
	47	[204]	MOVE     	2 3
	48	[207]	GETTABLE 	3 0 -22	; "max_width"
	49	[207]	SUB      	3 3 2
	50	[208]	GETTABLE 	4 0 -26	; "truncate_left"
	51	[208]	TEST     	4 0 0
	52	[208]	JMP      	5	; to 58
	53	[209]	GETTABLE 	4 0 -5	; "_xtext"
	54	[209]	SELF     	4 4 -27	; "getSegmentFromEnd"
	55	[209]	MOVE     	6 3
	56	[209]	CALL     	4 3 2
	57	[209]	MOVE     	1 4
	58	[211]	GETTABLE 	4 0 -5	; "_xtext"
	59	[211]	SELF     	4 4 -28	; "makeLine"
	60	[211]	MOVE     	6 1
	61	[211]	MOVE     	7 3
	62	[211]	LOADBOOL 	8 1 0
	63	[211]	CALL     	4 5 2
	64	[212]	GETTABLE 	5 4 -29	; "offset"
	65	[212]	SETTABLE 	0 -18 5	; "_shape_start" -
	66	[213]	GETTABLE 	5 4 -30	; "end_offset"
	67	[213]	SETTABLE 	0 -20 5	; "_shape_end" -
	68	[214]	GETTABLE 	5 4 -31	; "width"
	69	[214]	ADD      	5 5 2
	70	[214]	SETTABLE 	0 -14 5	; "_length" -
	71	[215]	GETTABLE 	5 0 -24	; "truncate_with_ellipsis"
	72	[215]	TEST     	5 0 0
	73	[215]	JMP      	22	; to 96
	74	[216]	GETTABLE 	5 0 -26	; "truncate_left"
	75	[216]	TEST     	5 0 0
	76	[216]	JMP      	9	; to 86
	77	[216]	GETTABLE 	5 0 -18	; "_shape_start"
	78	[216]	LT       	0 -19 5	; 1 -
	79	[216]	JMP      	6	; to 86
	80	[217]	GETTABLE 	5 0 -18	; "_shape_start"
	81	[217]	SUB      	5 5 -19	; - 1
	82	[217]	SETTABLE 	0 -18 5	; "_shape_start" -
	83	[218]	GETTABLE 	5 0 -18	; "_shape_start"
	84	[218]	SETTABLE 	0 -21 5	; "_shape_idx_to_substitute_with_ellipsis" -
	85	[218]	JMP      	10	; to 96
	86	[219]	GETTABLE 	5 0 -20	; "_shape_end"
	87	[219]	GETTABLE 	6 0 -5	; "_xtext"
	88	[219]	LEN      	6 6
	89	[219]	LT       	0 5 6
	90	[219]	JMP      	5	; to 96
	91	[220]	GETTABLE 	5 0 -20	; "_shape_end"
	92	[220]	ADD      	5 5 -19	; - 1
	93	[220]	SETTABLE 	0 -20 5	; "_shape_end" -
	94	[221]	GETTABLE 	5 0 -20	; "_shape_end"
	95	[221]	SETTABLE 	0 -21 5	; "_shape_idx_to_substitute_with_ellipsis" -
	96	[225]	RETURN   	0 1

function <./frontend/ui/widget/textwidget.lua:234,276> (80 instructions, 320 bytes at 0x7ff2dbc08780)
1 param, 8 slots, 0 upvalues, 5 locals, 18 constants, 0 functions
	1	[235]	GETTABLE 	1 0 -1	; "max_width"
	2	[235]	TEST     	1 0 1
	3	[235]	JMP      	3	; to 7
	4	[236]	GETTABLE 	1 0 -2	; "text"
	5	[236]	LOADNIL  	2 2
	6	[236]	RETURN   	1 3
	7	[238]	SELF     	1 0 -3	; "updateSize"
	8	[238]	CALL     	1 2 1
	9	[239]	GETTABLE 	1 0 -4	; "_is_empty"
	10	[239]	TEST     	1 0 0
	11	[239]	JMP      	3	; to 15
	12	[240]	LOADK    	1 -5	; ""
	13	[240]	LOADNIL  	2 2
	14	[240]	RETURN   	1 3
	15	[242]	GETTABLE 	1 0 -6	; "use_xtext"
	16	[242]	TEST     	1 0 1
	17	[242]	JMP      	30	; to 48
	18	[243]	GETTABLE 	1 0 -7	; "_text_to_draw"
	19	[243]	GETTABLE 	2 0 -2	; "text"
	20	[243]	EQ       	0 1 2
	21	[243]	JMP      	3	; to 25
	22	[244]	GETTABLE 	1 0 -2	; "text"
	23	[244]	LOADNIL  	2 2
	24	[244]	RETURN   	1 3
	25	[246]	GETTABLE 	1 0 -8	; "truncate_with_ellipsis"
	26	[246]	TEST     	1 0 1
	27	[246]	JMP      	3	; to 31
	28	[247]	GETTABLE 	1 0 -7	; "_text_to_draw"
	29	[247]	LOADBOOL 	2 0 0
	30	[247]	RETURN   	1 3
	31	[250]	GETTABLE 	1 0 -9	; "truncate_left"
	32	[250]	TEST     	1 0 0
	33	[250]	JMP      	7	; to 41
	34	[251]	GETTABLE 	1 0 -7	; "_text_to_draw"
	35	[251]	SELF     	1 1 -10	; "sub"
	36	[251]	LOADK    	3 -11	; 3
	37	[251]	CALL     	1 3 2
	38	[251]	LOADBOOL 	2 1 0
	39	[251]	RETURN   	1 3
	40	[251]	JMP      	7	; to 48
	41	[253]	GETTABLE 	1 0 -7	; "_text_to_draw"
	42	[253]	SELF     	1 1 -10	; "sub"
	43	[253]	LOADK    	3 -12	; 1
	44	[253]	LOADK    	4 -13	; -4
	45	[253]	CALL     	1 4 2
	46	[253]	LOADBOOL 	2 1 0
	47	[253]	RETURN   	1 3
	48	[256]	GETTABLE 	1 0 -14	; "_shape_start"
	49	[256]	EQ       	0 1 -12	; - 1
	50	[256]	JMP      	8	; to 59
	51	[256]	GETTABLE 	1 0 -15	; "_shape_end"
	52	[256]	GETTABLE 	2 0 -2	; "text"
	53	[256]	LEN      	2 2
	54	[256]	EQ       	0 1 2
	55	[256]	JMP      	3	; to 59
	56	[258]	GETTABLE 	1 0 -2	; "text"
	57	[258]	LOADNIL  	2 2
	58	[258]	RETURN   	1 3
	59	[260]	LOADBOOL 	1 0 0
	60	[261]	GETTABLE 	2 0 -14	; "_shape_start"
	61	[261]	GETTABLE 	3 0 -15	; "_shape_end"
	62	[262]	GETTABLE 	4 0 -16	; "_shape_idx_to_substitute_with_ellipsis"
	63	[262]	TEST     	4 0 0
	64	[262]	JMP      	7	; to 72
	65	[263]	LOADBOOL 	1 1 0
	66	[264]	GETTABLE 	4 0 -9	; "truncate_left"
	67	[264]	TEST     	4 0 0
	68	[264]	JMP      	2	; to 71
	69	[265]	ADD      	2 2 -12	; - 1
	70	[265]	JMP      	1	; to 72
	71	[267]	SUB      	3 3 -12	; - 1
	72	[274]	GETTABLE 	4 0 -17	; "_xtext"
	73	[274]	SELF     	4 4 -18	; "getText"
	74	[274]	MOVE     	6 2
	75	[274]	MOVE     	7 3
	76	[274]	CALL     	4 4 2
	77	[275]	MOVE     	5 4
	78	[275]	MOVE     	6 1
	79	[275]	RETURN   	5 3
	80	[276]	RETURN   	0 1

function <./frontend/ui/widget/textwidget.lua:278,284> (12 instructions, 48 bytes at 0x7ff2dbc08cb0)
1 param, 5 slots, 1 upvalue, 1 local, 6 constants, 0 functions
	1	[279]	SELF     	1 0 -1	; "updateSize"
	2	[279]	CALL     	1 2 1
	3	[280]	GETUPVAL 	1 0	; Geom
	4	[280]	SELF     	1 1 -2	; "new"
	5	[280]	NEWTABLE 	3 0 2
	6	[281]	GETTABLE 	4 0 -4	; "_length"
	7	[281]	SETTABLE 	3 -3 4	; "w" -
	8	[282]	GETTABLE 	4 0 -6	; "_height"
	9	[282]	SETTABLE 	3 -5 4	; "h" -
	10	[280]	TAILCALL 	1 3 0
	11	[283]	RETURN   	1 0
	12	[284]	RETURN   	0 1

function <./frontend/ui/widget/textwidget.lua:286,289> (5 instructions, 20 bytes at 0x7ff2dbc09630)
1 param, 3 slots, 0 upvalues, 1 local, 2 constants, 0 functions
	1	[287]	SELF     	1 0 -1	; "updateSize"
	2	[287]	CALL     	1 2 1
	3	[288]	GETTABLE 	1 0 -2	; "_length"
	4	[288]	RETURN   	1 2
	5	[289]	RETURN   	0 1

function <./frontend/ui/widget/textwidget.lua:291,294> (5 instructions, 20 bytes at 0x7ff2dbc09a20)
1 param, 3 slots, 0 upvalues, 1 local, 2 constants, 0 functions
	1	[292]	SELF     	1 0 -1	; "updateSize"
	2	[292]	CALL     	1 2 1
	3	[293]	GETTABLE 	1 0 -2	; "_baseline_h"
	4	[293]	RETURN   	1 2
	5	[294]	RETURN   	0 1

function <./frontend/ui/widget/textwidget.lua:296,302> (8 instructions, 32 bytes at 0x7ff2dbc09c90)
2 params, 4 slots, 0 upvalues, 2 locals, 4 constants, 0 functions
	1	[297]	GETTABLE 	2 0 -1	; "text"
	2	[297]	EQ       	1 1 2
	3	[297]	JMP      	4	; to 8
	4	[298]	SETTABLE 	0 -1 1	; "text" -
	5	[299]	SETTABLE 	0 -2 -3	; "_updated" false
	6	[300]	SELF     	2 0 -4	; "free"
	7	[300]	CALL     	2 2 1
	8	[302]	RETURN   	0 1

function <./frontend/ui/widget/textwidget.lua:304,307> (11 instructions, 44 bytes at 0x7ff2dbc09f80)
2 params, 5 slots, 0 upvalues, 2 locals, 4 constants, 0 functions
	1	[305]	GETGLOBAL	2 -1	; assert
	2	[305]	GETGLOBAL	3 -2	; type
	3	[305]	MOVE     	4 1
	4	[305]	CALL     	3 2 2
	5	[305]	EQ       	1 3 -3	; - "string"
	6	[305]	JMP      	1	; to 8
	7	[305]	LOADBOOL 	3 0 1
	8	[305]	LOADBOOL 	3 1 0
	9	[306]	LOADK    	4 -4	; "Wrong text type (expected string)"
	10	[305]	CALL     	2 3 1
	11	[307]	RETURN   	0 1

function <./frontend/ui/widget/textwidget.lua:309,315> (8 instructions, 32 bytes at 0x7ff2dbc0a560)
2 params, 4 slots, 0 upvalues, 2 locals, 4 constants, 0 functions
	1	[310]	GETTABLE 	2 0 -1	; "max_width"
	2	[310]	EQ       	1 1 2
	3	[310]	JMP      	4	; to 8
	4	[311]	SETTABLE 	0 -1 1	; "max_width" -
	5	[312]	SETTABLE 	0 -2 -3	; "_updated" false
	6	[313]	SELF     	2 0 -4	; "free"
	7	[313]	CALL     	2 2 1
	8	[315]	RETURN   	0 1

function <./frontend/ui/widget/textwidget.lua:317,357> (89 instructions, 356 bytes at 0x7ff2dbc0a690)
4 params, 24 slots, 1 upvalue, 14 locals, 32 constants, 0 functions
	1	[318]	SELF     	4 0 -1	; "updateSize"
	2	[318]	CALL     	4 2 1
	3	[319]	GETTABLE 	4 0 -2	; "_is_empty"
	4	[319]	TEST     	4 0 0
	5	[319]	JMP      	1	; to 7
	6	[320]	RETURN   	0 1
	7	[323]	GETTABLE 	4 0 -3	; "use_xtext"
	8	[323]	TEST     	4 0 1
	9	[323]	JMP      	14	; to 24
	10	[324]	GETUPVAL 	4 0	; RenderText
	11	[324]	SELF     	4 4 -4	; "renderUtf8Text"
	12	[324]	MOVE     	6 1
	13	[324]	MOVE     	7 2
	14	[324]	GETTABLE 	8 0 -5	; "_baseline_h"
	15	[324]	ADD      	8 3 8
	16	[324]	GETTABLE 	9 0 -6	; "face"
	17	[324]	GETTABLE 	10 0 -7	; "_text_to_draw"
	18	[325]	LOADBOOL 	11 1 0
	19	[325]	GETTABLE 	12 0 -8	; "bold"
	20	[325]	GETTABLE 	13 0 -9	; "fgcolor"
	21	[325]	GETTABLE 	14 0 -10	; "_length"
	22	[324]	CALL     	4 11 1
	23	[326]	RETURN   	0 1
	24	[330]	GETTABLE 	4 0 -11	; "_xshaping"
	25	[330]	TEST     	4 0 1
	26	[330]	JMP      	7	; to 34
	27	[331]	GETTABLE 	4 0 -12	; "_xtext"
	28	[331]	SELF     	4 4 -13	; "shapeLine"
	29	[331]	GETTABLE 	6 0 -14	; "_shape_start"
	30	[331]	GETTABLE 	7 0 -15	; "_shape_end"
	31	[332]	GETTABLE 	8 0 -16	; "_shape_idx_to_substitute_with_ellipsis"
	32	[331]	CALL     	4 5 2
	33	[332]	SETTABLE 	0 -11 4	; "_xshaping" -
	34	[336]	SELF     	4 1 -17	; "getWidth"
	35	[336]	CALL     	4 2 2
	36	[336]	SUB      	4 4 2
	37	[337]	GETTABLE 	5 0 -18	; "max_width"
	38	[337]	TEST     	5 0 0
	39	[337]	JMP      	4	; to 44
	40	[337]	GETTABLE 	5 0 -18	; "max_width"
	41	[337]	LT       	0 5 4
	42	[337]	JMP      	1	; to 44
	43	[338]	GETTABLE 	4 0 -18	; "max_width"
	44	[340]	LOADK    	5 -19	; 0
	45	[341]	GETTABLE 	6 0 -5	; "_baseline_h"
	46	[342]	GETGLOBAL	7 -20	; ipairs
	47	[342]	GETTABLE 	8 0 -11	; "_xshaping"
	48	[342]	CALL     	7 2 4
	49	[342]	JMP      	37	; to 87
	50	[343]	LE       	0 4 5
	51	[343]	JMP      	1	; to 53
	52	[344]	JMP      	36	; to 89
	53	[346]	GETTABLE 	12 0 -6	; "face"
	54	[346]	GETTABLE 	12 12 -21	; "getFallbackFont"
	55	[346]	GETTABLE 	13 11 -22	; "font_num"
	56	[346]	CALL     	12 2 2
	57	[347]	GETUPVAL 	13 0	; RenderText
	58	[347]	SELF     	13 13 -23	; "getGlyphByIndex"
	59	[347]	MOVE     	15 12
	60	[347]	GETTABLE 	16 11 -24	; "glyph"
	61	[347]	GETTABLE 	17 0 -8	; "bold"
	62	[347]	CALL     	13 5 2
	63	[348]	SELF     	14 1 -25	; "colorblitFrom"
	64	[349]	GETTABLE 	16 13 -26	; "bb"
	65	[350]	ADD      	17 2 5
	66	[350]	GETTABLE 	18 13 -27	; "l"
	67	[350]	ADD      	17 17 18
	68	[350]	GETTABLE 	18 11 -28	; "x_offset"
	69	[350]	ADD      	17 17 18
	70	[351]	ADD      	18 3 6
	71	[351]	GETTABLE 	19 13 -29	; "t"
	72	[351]	SUB      	18 18 19
	73	[351]	GETTABLE 	19 11 -30	; "y_offset"
	74	[351]	SUB      	18 18 19
	75	[352]	LOADK    	19 -19	; 0
	76	[352]	LOADK    	20 -19	; 0
	77	[353]	GETTABLE 	21 13 -26	; "bb"
	78	[353]	SELF     	21 21 -17	; "getWidth"
	79	[353]	CALL     	21 2 2
	80	[353]	GETTABLE 	22 13 -26	; "bb"
	81	[353]	SELF     	22 22 -31	; "getHeight"
	82	[353]	CALL     	22 2 2
	83	[354]	GETTABLE 	23 0 -9	; "fgcolor"
	84	[348]	CALL     	14 10 1
	85	[355]	GETTABLE 	14 11 -32	; "x_advance"
	86	[355]	ADD      	5 5 14
	87	[342]	TFORLOOP 	7 2
	88	[355]	JMP      	-39	; to 50
	89	[357]	RETURN   	0 1

function <./frontend/ui/widget/textwidget.lua:359,364> (7 instructions, 28 bytes at 0x7ff2dbc0af50)
1 param, 3 slots, 0 upvalues, 1 local, 2 constants, 0 functions
	1	[361]	GETTABLE 	1 0 -1	; "_xtext"
	2	[361]	TEST     	1 0 0
	3	[361]	JMP      	3	; to 7
	4	[362]	GETTABLE 	1 0 -1	; "_xtext"
	5	[362]	SELF     	1 1 -2	; "free"
	6	[362]	CALL     	1 2 1
	7	[364]	RETURN   	0 1

function <./frontend/ui/widget/textwidget.lua:366,370> (3 instructions, 12 bytes at 0x7ff2dbc0adf0)
1 param, 3 slots, 0 upvalues, 1 local, 1 constant, 0 functions
	1	[369]	SELF     	1 0 -1	; "free"
	2	[369]	CALL     	1 2 1
	3	[370]	RETURN   	0 1
