
main <./frontend/ui/widget/textviewer.lua:0,0> (146 instructions, 584 bytes at 0x7fb660c068d0)
0+ params, 29 slots, 0 upvalues, 24 locals, 62 constants, 7 functions
	1	[11]	GETGLOBAL	0 -1	; require
	2	[11]	LOADK    	1 -2	; "ui/bidi"
	3	[11]	CALL     	0 2 2
	4	[12]	GETGLOBAL	1 -1	; require
	5	[12]	LOADK    	2 -3	; "ffi/blitbuffer"
	6	[12]	CALL     	1 2 2
	7	[13]	GETGLOBAL	2 -1	; require
	8	[13]	LOADK    	3 -4	; "ui/widget/buttontable"
	9	[13]	CALL     	2 2 2
	10	[14]	GETGLOBAL	3 -1	; require
	11	[14]	LOADK    	4 -5	; "ui/widget/container/centercontainer"
	12	[14]	CALL     	3 2 2
	13	[15]	GETGLOBAL	4 -1	; require
	14	[15]	LOADK    	5 -6	; "ui/widget/closebutton"
	15	[15]	CALL     	4 2 2
	16	[16]	GETGLOBAL	5 -1	; require
	17	[16]	LOADK    	6 -7	; "device"
	18	[16]	CALL     	5 2 2
	19	[17]	GETGLOBAL	6 -1	; require
	20	[17]	LOADK    	7 -8	; "ui/geometry"
	21	[17]	CALL     	6 2 2
	22	[18]	GETGLOBAL	7 -1	; require
	23	[18]	LOADK    	8 -9	; "ui/font"
	24	[18]	CALL     	7 2 2
	25	[19]	GETGLOBAL	8 -1	; require
	26	[19]	LOADK    	9 -10	; "ui/widget/container/framecontainer"
	27	[19]	CALL     	8 2 2
	28	[20]	GETGLOBAL	9 -1	; require
	29	[20]	LOADK    	10 -11	; "ui/gesturerange"
	30	[20]	CALL     	9 2 2
	31	[21]	GETGLOBAL	10 -1	; require
	32	[21]	LOADK    	11 -12	; "ui/widget/container/inputcontainer"
	33	[21]	CALL     	10 2 2
	34	[22]	GETGLOBAL	11 -1	; require
	35	[22]	LOADK    	12 -13	; "ui/widget/linewidget"
	36	[22]	CALL     	11 2 2
	37	[23]	GETGLOBAL	12 -1	; require
	38	[23]	LOADK    	13 -14	; "ui/widget/container/movablecontainer"
	39	[23]	CALL     	12 2 2
	40	[24]	GETGLOBAL	13 -1	; require
	41	[24]	LOADK    	14 -15	; "ui/widget/overlapgroup"
	42	[24]	CALL     	13 2 2
	43	[25]	GETGLOBAL	14 -1	; require
	44	[25]	LOADK    	15 -16	; "ui/widget/scrolltextwidget"
	45	[25]	CALL     	14 2 2
	46	[26]	GETGLOBAL	15 -1	; require
	47	[26]	LOADK    	16 -17	; "ui/size"
	48	[26]	CALL     	15 2 2
	49	[27]	GETGLOBAL	16 -1	; require
	50	[27]	LOADK    	17 -18	; "ui/widget/textboxwidget"
	51	[27]	CALL     	16 2 2
	52	[28]	GETGLOBAL	17 -1	; require
	53	[28]	LOADK    	18 -19	; "ui/uimanager"
	54	[28]	CALL     	17 2 2
	55	[29]	GETGLOBAL	18 -1	; require
	56	[29]	LOADK    	19 -20	; "ui/widget/verticalgroup"
	57	[29]	CALL     	18 2 2
	58	[30]	GETGLOBAL	19 -1	; require
	59	[30]	LOADK    	20 -21	; "ui/widget/container/widgetcontainer"
	60	[30]	CALL     	19 2 2
	61	[31]	GETGLOBAL	20 -1	; require
	62	[31]	LOADK    	21 -22	; "logger"
	63	[31]	CALL     	20 2 2
	64	[32]	GETGLOBAL	21 -1	; require
	65	[32]	LOADK    	22 -23	; "gettext"
	66	[32]	CALL     	21 2 2
	67	[33]	GETTABLE 	22 5 -24	; "screen"
	68	[35]	SELF     	23 10 -25	; "new"
	69	[35]	NEWTABLE 	25 0 17
	70	[36]	SETTABLE 	25 -26 -27	; "title" nil
	71	[37]	SETTABLE 	25 -28 -27	; "text" nil
	72	[38]	SETTABLE 	25 -29 -27	; "width" nil
	73	[39]	SETTABLE 	25 -30 -27	; "height" nil
	74	[40]	SETTABLE 	25 -31 -27	; "buttons_table" nil
	75	[47]	SETTABLE 	25 -32 -33	; "alignment" "left"
	76	[48]	SETTABLE 	25 -34 -35	; "justified" true
	77	[49]	SETTABLE 	25 -36 -27	; "lang" nil
	78	[50]	SETTABLE 	25 -37 -27	; "para_direction_rtl" nil
	79	[51]	SETTABLE 	25 -38 -35	; "auto_para_direction" true
	80	[52]	SETTABLE 	25 -39 -40	; "alignment_strict" false
	81	[54]	SELF     	26 7 -42	; "getFace"
	82	[54]	LOADK    	28 -43	; "x_smalltfont"
	83	[54]	CALL     	26 3 2
	84	[54]	SETTABLE 	25 -41 26	; "title_face" -
	85	[55]	SELF     	26 7 -42	; "getFace"
	86	[55]	LOADK    	28 -45	; "x_smallinfofont"
	87	[55]	CALL     	26 3 2
	88	[55]	SETTABLE 	25 -44 26	; "text_face" -
	89	[56]	GETTABLE 	26 15 -47	; "padding"
	90	[56]	GETTABLE 	26 26 -48	; "default"
	91	[56]	SETTABLE 	25 -46 26	; "title_padding" -
	92	[57]	GETTABLE 	26 15 -50	; "margin"
	93	[57]	GETTABLE 	26 26 -26	; "title"
	94	[57]	SETTABLE 	25 -49 26	; "title_margin" -
	95	[58]	GETTABLE 	26 15 -47	; "padding"
	96	[58]	GETTABLE 	26 26 -52	; "large"
	97	[58]	SETTABLE 	25 -51 26	; "text_padding" -
	98	[59]	GETTABLE 	26 15 -50	; "margin"
	99	[59]	GETTABLE 	26 26 -54	; "small"
	100	[59]	SETTABLE 	25 -53 26	; "text_margin" -
	101	[60]	GETTABLE 	26 15 -47	; "padding"
	102	[60]	GETTABLE 	26 26 -48	; "default"
	103	[60]	SETTABLE 	25 -55 26	; "button_padding" -
	104	[35]	CALL     	23 3 2
	105	[225]	CLOSURE  	24 0	; 0x7fb660c07070
	106	[225]	MOVE     	0 6
	107	[225]	MOVE     	0 22
	108	[225]	MOVE     	0 5
	109	[225]	MOVE     	0 9
	110	[225]	MOVE     	0 4
	111	[225]	MOVE     	0 15
	112	[225]	MOVE     	0 16
	113	[225]	MOVE     	0 8
	114	[225]	MOVE     	0 13
	115	[225]	MOVE     	0 11
	116	[225]	MOVE     	0 21
	117	[225]	MOVE     	0 17
	118	[225]	MOVE     	0 2
	119	[225]	MOVE     	0 14
	120	[225]	MOVE     	0 1
	121	[225]	MOVE     	0 18
	122	[225]	MOVE     	0 3
	123	[225]	MOVE     	0 12
	124	[225]	MOVE     	0 19
	125	[225]	MOVE     	0 20
	126	[63]	SETTABLE 	23 -56 24	; "init" -
	127	[232]	CLOSURE  	24 1	; 0x7fb660c08c20
	128	[232]	MOVE     	0 17
	129	[227]	SETTABLE 	23 -57 24	; "onCloseWidget" -
	130	[239]	CLOSURE  	24 2	; 0x7fb660c07650
	131	[239]	MOVE     	0 17
	132	[234]	SETTABLE 	23 -58 24	; "onShow" -
	133	[244]	CLOSURE  	24 3	; 0x7fb660c079a0
	134	[244]	MOVE     	0 17
	135	[241]	SETTABLE 	23 -59 24	; "onAnyKeyPressed" -
	136	[251]	CLOSURE  	24 4	; 0x7fb660c09750
	137	[246]	SETTABLE 	23 -60 24	; "onTapClose" -
	138	[256]	CLOSURE  	24 5	; 0x7fb660c09b90
	139	[256]	MOVE     	0 17
	140	[253]	SETTABLE 	23 -61 24	; "onClose" -
	141	[277]	CLOSURE  	24 6	; 0x7fb660c09f60
	142	[277]	MOVE     	0 0
	143	[277]	MOVE     	0 17
	144	[258]	SETTABLE 	23 -62 24	; "onSwipe" -
	145	[279]	RETURN   	23 2
	146	[279]	RETURN   	0 1

function <./frontend/ui/widget/textviewer.lua:63,225> (387 instructions, 1548 bytes at 0x7fb660c07070)
1 param, 26 slots, 20 upvalues, 9 locals, 82 constants, 2 functions
	1	[64]	GETTABLE 	1 0 -1	; "frame"
	2	[64]	TEST     	1 0 0
	3	[64]	JMP      	4	; to 8
	4	[64]	GETTABLE 	1 0 -1	; "frame"
	5	[64]	GETTABLE 	1 1 -2	; "dimen"
	6	[64]	TEST     	1 0 1
	7	[64]	JMP      	4	; to 12
	8	[64]	GETUPVAL 	1 0	; Geom
	9	[64]	SELF     	1 1 -3	; "new"
	10	[64]	NEWTABLE 	3 0 0
	11	[64]	CALL     	1 3 2
	12	[66]	SETTABLE 	0 -4 -5	; "align" "center"
	13	[67]	GETUPVAL 	2 0	; Geom
	14	[67]	SELF     	2 2 -3	; "new"
	15	[67]	NEWTABLE 	4 0 4
	16	[68]	SETTABLE 	4 -7 -8	; "x" 0
	17	[68]	SETTABLE 	4 -9 -8	; "y" 0
	18	[69]	GETUPVAL 	5 1	; Screen
	19	[69]	SELF     	5 5 -11	; "getWidth"
	20	[69]	CALL     	5 2 2
	21	[69]	SETTABLE 	4 -10 5	; "w" -
	22	[70]	GETUPVAL 	5 1	; Screen
	23	[70]	SELF     	5 5 -13	; "getHeight"
	24	[70]	CALL     	5 2 2
	25	[70]	SETTABLE 	4 -12 5	; "h" -
	26	[67]	CALL     	2 3 2
	27	[71]	SETTABLE 	0 -6 2	; "region" -
	28	[72]	GETTABLE 	2 0 -14	; "width"
	29	[72]	TEST     	2 0 1
	30	[72]	JMP      	8	; to 39
	31	[72]	GETUPVAL 	2 1	; Screen
	32	[72]	SELF     	2 2 -11	; "getWidth"
	33	[72]	CALL     	2 2 2
	34	[72]	GETUPVAL 	3 1	; Screen
	35	[72]	SELF     	3 3 -15	; "scaleBySize"
	36	[72]	LOADK    	5 -16	; 30
	37	[72]	CALL     	3 3 2
	38	[72]	SUB      	2 2 3
	39	[72]	SETTABLE 	0 -14 2	; "width" -
	40	[73]	GETTABLE 	2 0 -17	; "height"
	41	[73]	TEST     	2 0 1
	42	[73]	JMP      	8	; to 51
	43	[73]	GETUPVAL 	2 1	; Screen
	44	[73]	SELF     	2 2 -13	; "getHeight"
	45	[73]	CALL     	2 2 2
	46	[73]	GETUPVAL 	3 1	; Screen
	47	[73]	SELF     	3 3 -15	; "scaleBySize"
	48	[73]	LOADK    	5 -16	; 30
	49	[73]	CALL     	3 3 2
	50	[73]	SUB      	2 2 3
	51	[73]	SETTABLE 	0 -17 2	; "height" -
	52	[75]	GETUPVAL 	2 2	; Device
	53	[75]	SELF     	2 2 -18	; "hasKeys"
	54	[75]	CALL     	2 2 2
	55	[75]	TEST     	2 0 0
	56	[75]	JMP      	9	; to 66
	57	[76]	NEWTABLE 	2 0 1
	58	[77]	NEWTABLE 	3 1 1
	59	[77]	NEWTABLE 	4 1 0
	60	[77]	LOADK    	5 -21	; "Back"
	61	[77]	SETLIST  	4 1 1	; 1
	62	[77]	SETTABLE 	3 -22 -23	; "doc" "close text viewer"
	63	[77]	SETLIST  	3 1 1	; 1
	64	[77]	SETTABLE 	2 -20 3	; "Close" -
	65	[78]	SETTABLE 	0 -19 2	; "key_events" -
	66	[81]	GETUPVAL 	2 2	; Device
	67	[81]	SELF     	2 2 -24	; "isTouchDevice"
	68	[81]	CALL     	2 2 2
	69	[81]	TEST     	2 0 0
	70	[81]	JMP      	48	; to 119
	71	[82]	NEWTABLE 	2 0 2
	72	[83]	NEWTABLE 	3 0 0
	73	[84]	GETUPVAL 	4 3	; GestureRange
	74	[84]	SELF     	4 4 -3	; "new"
	75	[84]	NEWTABLE 	6 0 2
	76	[85]	SETTABLE 	6 -27 -28	; "ges" "tap"
	77	[86]	GETUPVAL 	7 0	; Geom
	78	[86]	SELF     	7 7 -3	; "new"
	79	[86]	NEWTABLE 	9 0 4
	80	[87]	SETTABLE 	9 -7 -8	; "x" 0
	81	[87]	SETTABLE 	9 -9 -8	; "y" 0
	82	[88]	GETUPVAL 	10 1	; Screen
	83	[88]	SELF     	10 10 -11	; "getWidth"
	84	[88]	CALL     	10 2 2
	85	[88]	SETTABLE 	9 -10 10	; "w" -
	86	[89]	GETUPVAL 	10 1	; Screen
	87	[89]	SELF     	10 10 -13	; "getHeight"
	88	[89]	CALL     	10 2 2
	89	[89]	SETTABLE 	9 -12 10	; "h" -
	90	[86]	CALL     	7 3 2
	91	[90]	SETTABLE 	6 -29 7	; "range" -
	92	[84]	CALL     	4 3 0
	93	[92]	SETLIST  	3 0 1	; 1
	94	[92]	SETTABLE 	2 -26 3	; "TapClose" -
	95	[93]	NEWTABLE 	3 0 0
	96	[94]	GETUPVAL 	4 3	; GestureRange
	97	[94]	SELF     	4 4 -3	; "new"
	98	[94]	NEWTABLE 	6 0 2
	99	[95]	SETTABLE 	6 -27 -31	; "ges" "swipe"
	100	[96]	GETUPVAL 	7 0	; Geom
	101	[96]	SELF     	7 7 -3	; "new"
	102	[96]	NEWTABLE 	9 0 4
	103	[97]	SETTABLE 	9 -7 -8	; "x" 0
	104	[97]	SETTABLE 	9 -9 -8	; "y" 0
	105	[98]	GETUPVAL 	10 1	; Screen
	106	[98]	SELF     	10 10 -11	; "getWidth"
	107	[98]	CALL     	10 2 2
	108	[98]	SETTABLE 	9 -10 10	; "w" -
	109	[99]	GETUPVAL 	10 1	; Screen
	110	[99]	SELF     	10 10 -13	; "getHeight"
	111	[99]	CALL     	10 2 2
	112	[99]	SETTABLE 	9 -12 10	; "h" -
	113	[96]	CALL     	7 3 2
	114	[100]	SETTABLE 	6 -29 7	; "range" -
	115	[94]	CALL     	4 3 0
	116	[102]	SETLIST  	3 0 1	; 1
	117	[102]	SETTABLE 	2 -30 3	; "Swipe" -
	118	[103]	SETTABLE 	0 -25 2	; "ges_events" -
	119	[106]	GETUPVAL 	2 4	; CloseButton
	120	[106]	SELF     	2 2 -3	; "new"
	121	[106]	NEWTABLE 	4 0 2
	122	[106]	SETTABLE 	4 -32 0	; "window" -
	123	[106]	GETUPVAL 	5 5	; Size
	124	[106]	GETTABLE 	5 5 -34	; "padding"
	125	[106]	GETTABLE 	5 5 -35	; "tiny"
	126	[106]	SETTABLE 	4 -33 5	; "padding_top" -
	127	[106]	CALL     	2 3 2
	128	[107]	GETUPVAL 	3 6	; TextBoxWidget
	129	[107]	SELF     	3 3 -3	; "new"
	130	[107]	NEWTABLE 	5 0 4
	131	[108]	GETTABLE 	6 0 -37	; "title"
	132	[108]	SETTABLE 	5 -36 6	; "text" -
	133	[109]	GETTABLE 	6 0 -39	; "title_face"
	134	[109]	SETTABLE 	5 -38 6	; "face" -
	135	[110]	SETTABLE 	5 -40 -41	; "bold" true
	136	[111]	GETTABLE 	6 0 -14	; "width"
	137	[111]	GETTABLE 	7 0 -42	; "title_padding"
	138	[111]	MUL      	7 -43 7	; 2 -
	139	[111]	SUB      	6 6 7
	140	[111]	GETTABLE 	7 0 -44	; "title_margin"
	141	[111]	MUL      	7 -43 7	; 2 -
	142	[111]	SUB      	6 6 7
	143	[111]	SELF     	7 2 -45	; "getSize"
	144	[111]	CALL     	7 2 2
	145	[111]	GETTABLE 	7 7 -10	; "w"
	146	[111]	SUB      	6 6 7
	147	[111]	SETTABLE 	5 -14 6	; "width" -
	148	[107]	CALL     	3 3 2
	149	[113]	GETUPVAL 	4 7	; FrameContainer
	150	[113]	SELF     	4 4 -3	; "new"
	151	[113]	NEWTABLE 	6 1 5
	152	[114]	GETTABLE 	7 0 -42	; "title_padding"
	153	[114]	SETTABLE 	6 -34 7	; "padding" -
	154	[118]	GETTABLE 	7 0 -42	; "title_padding"
	155	[118]	GETUPVAL 	8 5	; Size
	156	[118]	GETTABLE 	8 8 -34	; "padding"
	157	[118]	GETTABLE 	8 8 -46	; "small"
	158	[118]	ADD      	7 7 8
	159	[118]	SETTABLE 	6 -33 7	; "padding_top" -
	160	[119]	GETTABLE 	7 0 -42	; "title_padding"
	161	[119]	GETUPVAL 	8 5	; Size
	162	[119]	GETTABLE 	8 8 -34	; "padding"
	163	[119]	GETTABLE 	8 8 -46	; "small"
	164	[119]	ADD      	7 7 8
	165	[119]	SETTABLE 	6 -47 7	; "padding_bottom" -
	166	[120]	GETTABLE 	7 0 -44	; "title_margin"
	167	[120]	SETTABLE 	6 -48 7	; "margin" -
	168	[121]	SETTABLE 	6 -49 -8	; "bordersize" 0
	169	[123]	MOVE     	7 3
	170	[123]	SETLIST  	6 1 1	; 1
	171	[113]	CALL     	4 3 2
	172	[124]	GETUPVAL 	5 8	; OverlapGroup
	173	[124]	SELF     	5 5 -3	; "new"
	174	[124]	NEWTABLE 	7 2 1
	175	[125]	NEWTABLE 	8 0 2
	176	[126]	GETTABLE 	9 0 -14	; "width"
	177	[126]	SETTABLE 	8 -10 9	; "w" -
	178	[127]	SELF     	9 4 -45	; "getSize"
	179	[127]	CALL     	9 2 2
	180	[127]	GETTABLE 	9 9 -12	; "h"
	181	[127]	SETTABLE 	8 -12 9	; "h" -
	182	[128]	SETTABLE 	7 -2 8	; "dimen" -
	183	[129]	MOVE     	8 4
	184	[131]	MOVE     	9 2
	185	[131]	SETLIST  	7 2 1	; 1
	186	[124]	CALL     	5 3 2
	187	[131]	MOVE     	4 5
	188	[133]	GETUPVAL 	5 9	; LineWidget
	189	[133]	SELF     	5 5 -3	; "new"
	190	[133]	NEWTABLE 	7 0 1
	191	[134]	GETUPVAL 	8 0	; Geom
	192	[134]	SELF     	8 8 -3	; "new"
	193	[134]	NEWTABLE 	10 0 2
	194	[135]	GETTABLE 	11 0 -14	; "width"
	195	[135]	SETTABLE 	10 -10 11	; "w" -
	196	[136]	GETUPVAL 	11 5	; Size
	197	[136]	GETTABLE 	11 11 -50	; "line"
	198	[136]	GETTABLE 	11 11 -51	; "thick"
	199	[136]	SETTABLE 	10 -12 11	; "h" -
	200	[134]	CALL     	8 3 2
	201	[137]	SETTABLE 	7 -2 8	; "dimen" -
	202	[133]	CALL     	5 3 2
	203	[140]	LOADNIL  	6 6
	204	[141]	GETTABLE 	7 0 -52	; "buttons_table"
	205	[141]	EQ       	0 7 -53	; - nil
	206	[141]	JMP      	15	; to 222
	207	[142]	NEWTABLE 	7 1 0
	208	[142]	NEWTABLE 	8 1 0
	209	[143]	NEWTABLE 	9 0 2
	210	[145]	GETUPVAL 	10 10	; _
	211	[145]	LOADK    	11 -20	; "Close"
	212	[145]	CALL     	10 2 2
	213	[145]	SETTABLE 	9 -36 10	; "text" -
	214	[148]	CLOSURE  	10 0	; 0x7fb660c08330
	215	[148]	GETUPVAL 	0 11	; UIManager
	216	[148]	MOVE     	0 0
	217	[148]	SETTABLE 	9 -54 10	; "callback" -
	218	[150]	SETLIST  	8 1 1	; 1
	219	[151]	SETLIST  	7 1 1	; 1
	220	[151]	MOVE     	6 7
	221	[151]	JMP      	1	; to 223
	222	[153]	GETTABLE 	6 0 -52	; "buttons_table"
	223	[155]	GETUPVAL 	7 12	; ButtonTable
	224	[155]	SELF     	7 7 -3	; "new"
	225	[155]	NEWTABLE 	9 0 6
	226	[156]	GETTABLE 	10 0 -14	; "width"
	227	[156]	GETTABLE 	11 0 -55	; "button_padding"
	228	[156]	MUL      	11 -43 11	; 2 -
	229	[156]	SUB      	10 10 11
	230	[156]	SETTABLE 	9 -14 10	; "width" -
	231	[157]	SETTABLE 	9 -56 -57	; "button_font_face" "cfont"
	232	[158]	SETTABLE 	9 -58 -59	; "button_font_size" 20
	233	[159]	SETTABLE 	9 -60 6	; "buttons" -
	234	[160]	SETTABLE 	9 -61 -41	; "zero_sep" true
	235	[161]	SETTABLE 	9 -62 0	; "show_parent" -
	236	[155]	CALL     	7 3 2
	237	[164]	GETTABLE 	8 0 -17	; "height"
	238	[164]	SELF     	9 4 -45	; "getSize"
	239	[164]	CALL     	9 2 2
	240	[164]	GETTABLE 	9 9 -12	; "h"
	241	[164]	SUB      	8 8 9
	242	[164]	SELF     	9 5 -45	; "getSize"
	243	[164]	CALL     	9 2 2
	244	[164]	GETTABLE 	9 9 -12	; "h"
	245	[164]	SUB      	8 8 9
	246	[164]	SELF     	9 7 -45	; "getSize"
	247	[164]	CALL     	9 2 2
	248	[164]	GETTABLE 	9 9 -12	; "h"
	249	[164]	SUB      	8 8 9
	250	[166]	GETUPVAL 	9 13	; ScrollTextWidget
	251	[166]	SELF     	9 9 -3	; "new"
	252	[166]	NEWTABLE 	11 0 11
	253	[167]	GETTABLE 	12 0 -36	; "text"
	254	[167]	SETTABLE 	11 -36 12	; "text" -
	255	[168]	GETTABLE 	12 0 -64	; "text_face"
	256	[168]	SETTABLE 	11 -38 12	; "face" -
	257	[169]	GETTABLE 	12 0 -14	; "width"
	258	[169]	GETTABLE 	13 0 -65	; "text_padding"
	259	[169]	MUL      	13 -43 13	; 2 -
	260	[169]	SUB      	12 12 13
	261	[169]	GETTABLE 	13 0 -66	; "text_margin"
	262	[169]	MUL      	13 -43 13	; 2 -
	263	[169]	SUB      	12 12 13
	264	[169]	SETTABLE 	11 -14 12	; "width" -
	265	[170]	GETTABLE 	12 0 -65	; "text_padding"
	266	[170]	MUL      	12 -43 12	; 2 -
	267	[170]	SUB      	12 8 12
	268	[170]	GETTABLE 	13 0 -66	; "text_margin"
	269	[170]	MUL      	13 -43 13	; 2 -
	270	[170]	SUB      	12 12 13
	271	[170]	SETTABLE 	11 -17 12	; "height" -
	272	[171]	SETTABLE 	11 -67 0	; "dialog" -
	273	[172]	GETTABLE 	12 0 -68	; "alignment"
	274	[172]	SETTABLE 	11 -68 12	; "alignment" -
	275	[173]	GETTABLE 	12 0 -69	; "justified"
	276	[173]	SETTABLE 	11 -69 12	; "justified" -
	277	[174]	GETTABLE 	12 0 -70	; "lang"
	278	[174]	SETTABLE 	11 -70 12	; "lang" -
	279	[175]	GETTABLE 	12 0 -71	; "para_direction_rtl"
	280	[175]	SETTABLE 	11 -71 12	; "para_direction_rtl" -
	281	[176]	GETTABLE 	12 0 -72	; "auto_para_direction"
	282	[176]	SETTABLE 	11 -72 12	; "auto_para_direction" -
	283	[177]	GETTABLE 	12 0 -73	; "alignment_strict"
	284	[177]	SETTABLE 	11 -73 12	; "alignment_strict" -
	285	[166]	CALL     	9 3 2
	286	[178]	SETTABLE 	0 -63 9	; "scroll_text_w" -
	287	[179]	GETUPVAL 	9 7	; FrameContainer
	288	[179]	SELF     	9 9 -3	; "new"
	289	[179]	NEWTABLE 	11 1 3
	290	[180]	GETTABLE 	12 0 -65	; "text_padding"
	291	[180]	SETTABLE 	11 -34 12	; "padding" -
	292	[181]	GETTABLE 	12 0 -66	; "text_margin"
	293	[181]	SETTABLE 	11 -48 12	; "margin" -
	294	[182]	SETTABLE 	11 -49 -8	; "bordersize" 0
	295	[184]	GETTABLE 	12 0 -63	; "scroll_text_w"
	296	[184]	SETLIST  	11 1 1	; 1
	297	[179]	CALL     	9 3 2
	298	[184]	SETTABLE 	0 -74 9	; "textw" -
	299	[186]	GETUPVAL 	9 7	; FrameContainer
	300	[186]	SELF     	9 9 -3	; "new"
	301	[186]	NEWTABLE 	11 0 4
	302	[187]	GETUPVAL 	12 5	; Size
	303	[187]	GETTABLE 	12 12 -75	; "radius"
	304	[187]	GETTABLE 	12 12 -32	; "window"
	305	[187]	SETTABLE 	11 -75 12	; "radius" -
	306	[188]	SETTABLE 	11 -34 -8	; "padding" 0
	307	[189]	SETTABLE 	11 -48 -8	; "margin" 0
	308	[190]	GETUPVAL 	12 14	; Blitbuffer
	309	[190]	GETTABLE 	12 12 -77	; "COLOR_WHITE"
	310	[190]	SETTABLE 	11 -76 12	; "background" -
	311	[191]	GETUPVAL 	12 15	; VerticalGroup
	312	[191]	SELF     	12 12 -3	; "new"
	313	[191]	NEWTABLE 	14 3 1
	314	[192]	SETTABLE 	14 -4 -78	; "align" "left"
	315	[193]	MOVE     	15 4
	316	[194]	MOVE     	16 5
	317	[195]	GETUPVAL 	17 16	; CenterContainer
	318	[195]	SELF     	17 17 -3	; "new"
	319	[195]	NEWTABLE 	19 1 1
	320	[196]	GETUPVAL 	20 0	; Geom
	321	[196]	SELF     	20 20 -3	; "new"
	322	[196]	NEWTABLE 	22 0 2
	323	[197]	GETTABLE 	23 0 -14	; "width"
	324	[197]	SETTABLE 	22 -10 23	; "w" -
	325	[198]	GETTABLE 	23 0 -74	; "textw"
	326	[198]	SELF     	23 23 -45	; "getSize"
	327	[198]	CALL     	23 2 2
	328	[198]	GETTABLE 	23 23 -12	; "h"
	329	[198]	SETTABLE 	22 -12 23	; "h" -
	330	[196]	CALL     	20 3 2
	331	[199]	SETTABLE 	19 -2 20	; "dimen" -
	332	[201]	GETTABLE 	20 0 -74	; "textw"
	333	[201]	SETLIST  	19 1 1	; 1
	334	[195]	CALL     	17 3 2
	335	[202]	GETUPVAL 	18 16	; CenterContainer
	336	[202]	SELF     	18 18 -3	; "new"
	337	[202]	NEWTABLE 	20 1 1
	338	[203]	GETUPVAL 	21 0	; Geom
	339	[203]	SELF     	21 21 -3	; "new"
	340	[203]	NEWTABLE 	23 0 2
	341	[204]	GETTABLE 	24 0 -14	; "width"
	342	[204]	SETTABLE 	23 -10 24	; "w" -
	343	[205]	SELF     	24 7 -45	; "getSize"
	344	[205]	CALL     	24 2 2
	345	[205]	GETTABLE 	24 24 -12	; "h"
	346	[205]	SETTABLE 	23 -12 24	; "h" -
	347	[203]	CALL     	21 3 2
	348	[206]	SETTABLE 	20 -2 21	; "dimen" -
	349	[208]	MOVE     	21 7
	350	[208]	SETLIST  	20 1 1	; 1
	351	[202]	CALL     	18 3 0
	352	[209]	SETLIST  	14 0 1	; 1
	353	[191]	CALL     	12 3 0
	354	[210]	SETLIST  	11 0 1	; 1
	355	[186]	CALL     	9 3 2
	356	[210]	SETTABLE 	0 -1 9	; "frame" -
	357	[211]	GETUPVAL 	9 17	; MovableContainer
	358	[211]	SELF     	9 9 -3	; "new"
	359	[211]	NEWTABLE 	11 1 1
	360	[212]	NEWTABLE 	12 1 0
	361	[212]	LOADK    	13 -31	; "swipe"
	362	[212]	SETLIST  	12 1 1	; 1
	363	[212]	SETTABLE 	11 -80 12	; "ignore_events" -
	364	[214]	GETTABLE 	12 0 -1	; "frame"
	365	[214]	SETLIST  	11 1 1	; 1
	366	[211]	CALL     	9 3 2
	367	[214]	SETTABLE 	0 -79 9	; "movable" -
	368	[215]	GETUPVAL 	9 18	; WidgetContainer
	369	[215]	SELF     	9 9 -3	; "new"
	370	[215]	NEWTABLE 	11 1 2
	371	[216]	GETTABLE 	12 0 -4	; "align"
	372	[216]	SETTABLE 	11 -4 12	; "align" -
	373	[217]	GETTABLE 	12 0 -6	; "region"
	374	[217]	SETTABLE 	11 -2 12	; "dimen" -
	375	[219]	GETTABLE 	12 0 -79	; "movable"
	376	[219]	SETLIST  	11 1 1	; 1
	377	[215]	CALL     	9 3 2
	378	[219]	SETTABLE 	0 -81 9	; 1 -
	379	[220]	GETUPVAL 	9 11	; UIManager
	380	[220]	SELF     	9 9 -82	; "setDirty"
	381	[220]	MOVE     	11 0
	382	[224]	CLOSURE  	12 1	; 0x7fb660c08280
	383	[224]	MOVE     	0 0
	384	[224]	MOVE     	0 1
	385	[224]	GETUPVAL 	0 19	; logger
	386	[220]	CALL     	9 4 1
	387	[225]	RETURN   	0 1

function <./frontend/ui/widget/textviewer.lua:146,148> (5 instructions, 20 bytes at 0x7fb660c08330)
0 params, 3 slots, 2 upvalues, 0 locals, 1 constant, 0 functions
	1	[147]	GETUPVAL 	0 0	; UIManager
	2	[147]	SELF     	0 0 -1	; "close"
	3	[147]	GETUPVAL 	2 1	; self
	4	[147]	CALL     	0 3 1
	5	[148]	RETURN   	0 1

function <./frontend/ui/widget/textviewer.lua:220,224> (15 instructions, 60 bytes at 0x7fb660c08280)
0 params, 4 slots, 3 upvalues, 1 local, 6 constants, 0 functions
	1	[221]	GETUPVAL 	0 0	; self
	2	[221]	GETTABLE 	0 0 -1	; "frame"
	3	[221]	GETTABLE 	0 0 -2	; "dimen"
	4	[221]	SELF     	0 0 -3	; "combine"
	5	[221]	GETUPVAL 	2 1	; orig_dimen
	6	[221]	CALL     	0 3 2
	7	[222]	GETUPVAL 	1 2	; logger
	8	[222]	GETTABLE 	1 1 -4	; "dbg"
	9	[222]	LOADK    	2 -5	; "update region"
	10	[222]	MOVE     	3 0
	11	[222]	CALL     	1 3 1
	12	[223]	LOADK    	1 -6	; "partial"
	13	[223]	MOVE     	2 0
	14	[223]	RETURN   	1 3
	15	[224]	RETURN   	0 1

function <./frontend/ui/widget/textviewer.lua:227,232> (9 instructions, 36 bytes at 0x7fb660c08c20)
1 param, 5 slots, 1 upvalue, 1 local, 1 constant, 1 function
	1	[228]	GETUPVAL 	1 0	; UIManager
	2	[228]	SELF     	1 1 -1	; "setDirty"
	3	[228]	LOADNIL  	3 3
	4	[230]	CLOSURE  	4 0	; 0x7fb660c09210
	5	[230]	MOVE     	0 0
	6	[228]	CALL     	1 4 1
	7	[231]	LOADBOOL 	1 1 0
	8	[231]	RETURN   	1 2
	9	[232]	RETURN   	0 1

function <./frontend/ui/widget/textviewer.lua:228,230> (6 instructions, 24 bytes at 0x7fb660c09210)
0 params, 2 slots, 1 upvalue, 0 locals, 3 constants, 0 functions
	1	[229]	LOADK    	0 -1	; "partial"
	2	[229]	GETUPVAL 	1 0	; self
	3	[229]	GETTABLE 	1 1 -2	; "frame"
	4	[229]	GETTABLE 	1 1 -3	; "dimen"
	5	[229]	RETURN   	0 3
	6	[230]	RETURN   	0 1

function <./frontend/ui/widget/textviewer.lua:234,239> (9 instructions, 36 bytes at 0x7fb660c07650)
1 param, 5 slots, 1 upvalue, 1 local, 1 constant, 1 function
	1	[235]	GETUPVAL 	1 0	; UIManager
	2	[235]	SELF     	1 1 -1	; "setDirty"
	3	[235]	MOVE     	3 0
	4	[237]	CLOSURE  	4 0	; 0x7fb660c07840
	5	[237]	MOVE     	0 0
	6	[235]	CALL     	1 4 1
	7	[238]	LOADBOOL 	1 1 0
	8	[238]	RETURN   	1 2
	9	[239]	RETURN   	0 1

function <./frontend/ui/widget/textviewer.lua:235,237> (6 instructions, 24 bytes at 0x7fb660c07840)
0 params, 2 slots, 1 upvalue, 0 locals, 3 constants, 0 functions
	1	[236]	LOADK    	0 -1	; "ui"
	2	[236]	GETUPVAL 	1 0	; self
	3	[236]	GETTABLE 	1 1 -2	; "frame"
	4	[236]	GETTABLE 	1 1 -3	; "dimen"
	5	[236]	RETURN   	0 3
	6	[237]	RETURN   	0 1

function <./frontend/ui/widget/textviewer.lua:241,244> (7 instructions, 28 bytes at 0x7fb660c079a0)
1 param, 4 slots, 1 upvalue, 1 local, 1 constant, 0 functions
	1	[242]	GETUPVAL 	1 0	; UIManager
	2	[242]	SELF     	1 1 -1	; "close"
	3	[242]	MOVE     	3 0
	4	[242]	CALL     	1 3 1
	5	[243]	LOADBOOL 	1 1 0
	6	[243]	RETURN   	1 2
	7	[244]	RETURN   	0 1

function <./frontend/ui/widget/textviewer.lua:246,251> (12 instructions, 48 bytes at 0x7fb660c09750)
3 params, 6 slots, 0 upvalues, 3 locals, 5 constants, 0 functions
	1	[247]	GETTABLE 	3 2 -1	; "pos"
	2	[247]	SELF     	3 3 -2	; "notIntersectWith"
	3	[247]	GETTABLE 	5 0 -3	; "frame"
	4	[247]	GETTABLE 	5 5 -4	; "dimen"
	5	[247]	CALL     	3 3 2
	6	[247]	TEST     	3 0 0
	7	[247]	JMP      	2	; to 10
	8	[248]	SELF     	3 0 -5	; "onClose"
	9	[248]	CALL     	3 2 1
	10	[250]	LOADBOOL 	3 1 0
	11	[250]	RETURN   	3 2
	12	[251]	RETURN   	0 1

function <./frontend/ui/widget/textviewer.lua:253,256> (7 instructions, 28 bytes at 0x7fb660c09b90)
1 param, 4 slots, 1 upvalue, 1 local, 1 constant, 0 functions
	1	[254]	GETUPVAL 	1 0	; UIManager
	2	[254]	SELF     	1 1 -1	; "close"
	3	[254]	MOVE     	3 0
	4	[254]	CALL     	1 3 1
	5	[255]	LOADBOOL 	1 1 0
	6	[255]	RETURN   	1 2
	7	[256]	RETURN   	0 1

function <./frontend/ui/widget/textviewer.lua:258,277> (43 instructions, 172 bytes at 0x7fb660c09f60)
3 params, 8 slots, 2 upvalues, 4 locals, 16 constants, 0 functions
	1	[259]	GETTABLE 	3 2 -1	; "pos"
	2	[259]	SELF     	3 3 -2	; "intersectWith"
	3	[259]	GETTABLE 	5 0 -3	; "textw"
	4	[259]	GETTABLE 	5 5 -4	; "dimen"
	5	[259]	CALL     	3 3 2
	6	[259]	TEST     	3 0 0
	7	[259]	JMP      	29	; to 37
	8	[260]	GETUPVAL 	3 0	; BD
	9	[260]	GETTABLE 	3 3 -5	; "flipDirectionIfMirroredUILayout"
	10	[260]	GETTABLE 	4 2 -6	; "direction"
	11	[260]	CALL     	3 2 2
	12	[261]	EQ       	0 3 -7	; - "west"
	13	[261]	JMP      	7	; to 21
	14	[262]	GETTABLE 	4 0 -8	; "scroll_text_w"
	15	[262]	SELF     	4 4 -9	; "scrollText"
	16	[262]	LOADK    	6 -10	; 1
	17	[262]	CALL     	4 3 1
	18	[263]	LOADBOOL 	4 1 0
	19	[263]	RETURN   	4 2
	20	[263]	JMP      	16	; to 37
	21	[264]	EQ       	0 3 -11	; - "east"
	22	[264]	JMP      	7	; to 30
	23	[265]	GETTABLE 	4 0 -8	; "scroll_text_w"
	24	[265]	SELF     	4 4 -9	; "scrollText"
	25	[265]	LOADK    	6 -12	; -1
	26	[265]	CALL     	4 3 1
	27	[266]	LOADBOOL 	4 1 0
	28	[266]	RETURN   	4 2
	29	[266]	JMP      	7	; to 37
	30	[269]	GETUPVAL 	4 1	; UIManager
	31	[269]	SELF     	4 4 -13	; "setDirty"
	32	[269]	LOADNIL  	6 6
	33	[269]	LOADK    	7 -14	; "full"
	34	[269]	CALL     	4 4 1
	35	[272]	LOADBOOL 	4 0 0
	36	[272]	RETURN   	4 2
	37	[276]	GETTABLE 	3 0 -15	; "movable"
	38	[276]	SELF     	3 3 -16	; "onMovableSwipe"
	39	[276]	MOVE     	5 1
	40	[276]	MOVE     	6 2
	41	[276]	TAILCALL 	3 4 0
	42	[276]	RETURN   	3 0
	43	[277]	RETURN   	0 1
