-- BYTECODE -- textboxwidget_spec.lua:3-7
0001    GGET     0   0      ; "require"
0002    KSTR     1   1      ; "commonrequire"
0003    CALL     0   1   2
0004    GGET     0   0      ; "require"
0005    KSTR     1   2      ; "ui/font"
0006    CALL     0   2   2
0007    USETV    0   0      ; Font
0008    GGET     0   0      ; "require"
0009    KSTR     1   3      ; "ui/widget/textboxwidget"
0010    CALL     0   2   2
0011    USETV    1   0      ; TextBoxWidget
0012    RET0     0   1

-- BYTECODE -- textboxwidget_spec.lua:18-20
0001    GGET     1   0      ; "assert"
0002    TGETS    1   1   1  ; "is"
0003    TGETS    1   1   2  ; "same"
0004    MOV      2   0
0005    KSTR     3   3      ; "YOOOOOOOOOOOOOOOO"
0006    CALL     1   1   3
0007    RET0     0   1

-- BYTECODE -- textboxwidget_spec.lua:24-26
0001    GGET     1   0      ; "assert"
0002    TGETS    1   1   1  ; "is"
0003    TGETS    1   1   2  ; "same"
0004    MOV      2   0
0005    KSTR     3   3      ; "Foo"
0006    CALL     1   1   3
0007    RET0     0   1

-- BYTECODE -- textboxwidget_spec.lua:30-32
0001    GGET     1   0      ; "assert"
0002    TGETS    1   1   1  ; "is"
0003    TGETS    1   1   2  ; "same"
0004    MOV      2   0
0005    KSTR     3   3      ; "Bar"
0006    CALL     1   1   3
0007    RET0     0   1

-- BYTECODE -- textboxwidget_spec.lua:35-37
0001    GGET     1   0      ; "assert"
0002    TGETS    1   1   1  ; "is"
0003    TGETS    1   1   2  ; "same"
0004    MOV      2   0
0005    KSTR     3   3      ; "welcomes Bar into"
0006    CALL     1   1   3
0007    RET0     0   1

-- BYTECODE -- textboxwidget_spec.lua:40-42
0001    GGET     1   0      ; "assert"
0002    TGETS    1   1   1  ; "is"
0003    TGETS    1   1   2  ; "same"
0004    MOV      2   0
0005    KSTR     3   3      ; "Bar.\nFoo welcomes Bar into"
0006    CALL     1   1   3
0007    RET0     0   1

-- BYTECODE -- textboxwidget_spec.lua:9-56
0001    UGET     0   0      ; TextBoxWidget
0002    MOV      1   0
0003    TGETS    0   0   0  ; "new"
0004    TDUP     2   2
0005    TDUP     3   1
0006    TSETS    3   2   3  ; "dimen"
0007    UGET     3   1      ; Font
0008    MOV      4   3
0009    TGETS    3   3   4  ; "getFace"
0010    KSTR     5   5      ; "cfont"
0011    KSHORT   6  25
0012    CALL     3   2   4
0013    TSETS    3   2   6  ; "face"
0014    CALL     0   2   3
0015    TDUP     1   7
0016    MOV      3   0
0017    TGETS    2   0   8  ; "onHoldStartText"
0018    KPRI     4   0
0019    TDUP     5   9
0020    TSETS    1   5  10  ; "pos"
0021    CALL     2   1   4
0022    MOV      3   0
0023    TGETS    2   0  11  ; "onHoldReleaseText"
0024    FNEW     4  12      ; textboxwidget_spec.lua:18
0025    TDUP     5  13
0026    TSETS    1   5  10  ; "pos"
0027    CALL     2   1   4
0028    TDUP     1  14
0029    MOV      3   0
0030    TGETS    2   0   8  ; "onHoldStartText"
0031    KPRI     4   0
0032    TDUP     5  15
0033    TSETS    1   5  10  ; "pos"
0034    CALL     2   1   4
0035    MOV      3   0
0036    TGETS    2   0  11  ; "onHoldReleaseText"
0037    FNEW     4  16      ; textboxwidget_spec.lua:24
0038    TDUP     5  17
0039    TSETS    1   5  10  ; "pos"
0040    CALL     2   1   4
0041    TDUP     1  18
0042    MOV      3   0
0043    TGETS    2   0   8  ; "onHoldStartText"
0044    KPRI     4   0
0045    TDUP     5  19
0046    TSETS    1   5  10  ; "pos"
0047    CALL     2   1   4
0048    MOV      3   0
0049    TGETS    2   0  11  ; "onHoldReleaseText"
0050    FNEW     4  20      ; textboxwidget_spec.lua:30
0051    TDUP     5  21
0052    TSETS    1   5  10  ; "pos"
0053    CALL     2   1   4
0054    MOV      3   0
0055    TGETS    2   0   8  ; "onHoldStartText"
0056    KPRI     4   0
0057    TDUP     5  23
0058    TDUP     6  22
0059    TSETS    6   5  10  ; "pos"
0060    CALL     2   1   4
0061    MOV      3   0
0062    TGETS    2   0  11  ; "onHoldReleaseText"
0063    FNEW     4  24      ; textboxwidget_spec.lua:35
0064    TDUP     5  26
0065    TDUP     6  25
0066    TSETS    6   5  10  ; "pos"
0067    CALL     2   1   4
0068    MOV      3   0
0069    TGETS    2   0   8  ; "onHoldStartText"
0070    KPRI     4   0
0071    TDUP     5  28
0072    TDUP     6  27
0073    TSETS    6   5  10  ; "pos"
0074    CALL     2   1   4
0075    MOV      3   0
0076    TGETS    2   0  11  ; "onHoldReleaseText"
0077    FNEW     4  29      ; textboxwidget_spec.lua:40
0078    TDUP     5  31
0079    TDUP     6  30
0080    TSETS    6   5  10  ; "pos"
0081    CALL     2   1   4
0082    RET0     0   1

-- BYTECODE -- textboxwidget_spec.lua:1-57
0001    KNIL     0   1
0002    GGET     2   0      ; "setup"
0003    FNEW     3   1      ; textboxwidget_spec.lua:3
0004    CALL     2   1   2
0005    GGET     2   2      ; "it"
0006    KSTR     3   3      ; "should select the correct word on HoldWo"~
0007    FNEW     4   4      ; textboxwidget_spec.lua:9
0008    CALL     2   1   3
0009    UCLO     0 => 0010
0010 => RET0     0   1

-- BYTECODE -- textboxwidget_spec.lua:0-58
0001    GGET     0   0      ; "describe"
0002    KSTR     1   1      ; "TextBoxWidget module"
0003    FNEW     2   2      ; textboxwidget_spec.lua:1
0004    CALL     0   1   3
0005    RET0     0   1

