
main <./spec/unit/textboxwidget_spec.lua:0,0> (5 instructions, 20 bytes at 0x7ff6664068d0)
0+ params, 3 slots, 0 upvalues, 0 locals, 2 constants, 1 function
	1	[1]	GETGLOBAL	0 -1	; describe
	2	[1]	LOADK    	1 -2	; "TextBoxWidget module"
	3	[57]	CLOSURE  	2 0	; 0x7ff666406b70
	4	[1]	CALL     	0 3 1
	5	[57]	RETURN   	0 1

function <./spec/unit/textboxwidget_spec.lua:1,57> (12 instructions, 48 bytes at 0x7ff666406b70)
0 params, 5 slots, 0 upvalues, 2 locals, 3 constants, 2 functions
	1	[3]	GETGLOBAL	2 -1	; setup
	2	[7]	CLOSURE  	3 0	; 0x7ff666406ef0
	3	[7]	MOVE     	0 1
	4	[7]	MOVE     	0 0
	5	[3]	CALL     	2 2 1
	6	[9]	GETGLOBAL	2 -2	; it
	7	[9]	LOADK    	3 -3	; "should select the correct word on HoldWord event"
	8	[56]	CLOSURE  	4 1	; 0x7ff6664072c0
	9	[56]	MOVE     	0 0
	10	[56]	MOVE     	0 1
	11	[9]	CALL     	2 3 1
	12	[57]	RETURN   	0 1

function <./spec/unit/textboxwidget_spec.lua:3,7> (12 instructions, 48 bytes at 0x7ff666406ef0)
0 params, 2 slots, 2 upvalues, 0 locals, 4 constants, 0 functions
	1	[4]	GETGLOBAL	0 -1	; require
	2	[4]	LOADK    	1 -2	; "commonrequire"
	3	[4]	CALL     	0 2 1
	4	[5]	GETGLOBAL	0 -1	; require
	5	[5]	LOADK    	1 -3	; "ui/font"
	6	[5]	CALL     	0 2 2
	7	[5]	SETUPVAL 	0 0	; Font
	8	[6]	GETGLOBAL	0 -1	; require
	9	[6]	LOADK    	1 -4	; "ui/widget/textboxwidget"
	10	[6]	CALL     	0 2 2
	11	[6]	SETUPVAL 	0 1	; TextBoxWidget
	12	[7]	RETURN   	0 1

function <./spec/unit/textboxwidget_spec.lua:9,56> (89 instructions, 356 bytes at 0x7ff6664072c0)
0 params, 7 slots, 2 upvalues, 2 locals, 21 constants, 5 functions
	1	[10]	GETUPVAL 	0 0	; TextBoxWidget
	2	[10]	SELF     	0 0 -1	; "new"
	3	[10]	NEWTABLE 	2 0 3
	4	[11]	NEWTABLE 	3 0 2
	5	[11]	SETTABLE 	3 -3 -4	; "x" 0
	6	[11]	SETTABLE 	3 -5 -4	; "y" 0
	7	[11]	SETTABLE 	2 -2 3	; "dimen" -
	8	[12]	GETUPVAL 	3 1	; Font
	9	[12]	SELF     	3 3 -7	; "getFace"
	10	[12]	LOADK    	5 -8	; "cfont"
	11	[12]	LOADK    	6 -9	; 25
	12	[12]	CALL     	3 4 2
	13	[12]	SETTABLE 	2 -6 3	; "face" -
	14	[13]	SETTABLE 	2 -10 -11	; "text" "YOOOOOOOOOOOOOOOO\nFoo.\nBar.\nFoo welcomes Bar into the fun."
	15	[10]	CALL     	0 3 2
	16	[16]	NEWTABLE 	1 0 2
	17	[16]	SETTABLE 	1 -3 -12	; "x" 110
	18	[16]	SETTABLE 	1 -5 -13	; "y" 4
	19	[17]	SELF     	2 0 -14	; "onHoldStartText"
	20	[17]	LOADNIL  	4 4
	21	[17]	NEWTABLE 	5 0 1
	22	[17]	SETTABLE 	5 -15 1	; "pos" -
	23	[17]	CALL     	2 4 1
	24	[18]	SELF     	2 0 -16	; "onHoldReleaseText"
	25	[20]	CLOSURE  	4 0	; 0x7ff666406670
	26	[20]	NEWTABLE 	5 0 1
	27	[20]	SETTABLE 	5 -15 1	; "pos" -
	28	[18]	CALL     	2 4 1
	29	[22]	NEWTABLE 	2 0 2
	30	[22]	SETTABLE 	2 -3 -4	; "x" 0
	31	[22]	SETTABLE 	2 -5 -17	; "y" 50
	32	[22]	MOVE     	1 2
	33	[23]	SELF     	2 0 -14	; "onHoldStartText"
	34	[23]	LOADNIL  	4 4
	35	[23]	NEWTABLE 	5 0 1
	36	[23]	SETTABLE 	5 -15 1	; "pos" -
	37	[23]	CALL     	2 4 1
	38	[24]	SELF     	2 0 -16	; "onHoldReleaseText"
	39	[26]	CLOSURE  	4 1	; 0x7ff6664065c0
	40	[26]	NEWTABLE 	5 0 1
	41	[26]	SETTABLE 	5 -15 1	; "pos" -
	42	[24]	CALL     	2 4 1
	43	[28]	NEWTABLE 	2 0 2
	44	[28]	SETTABLE 	2 -3 -18	; "x" 20
	45	[28]	SETTABLE 	2 -5 -19	; "y" 80
	46	[28]	MOVE     	1 2
	47	[29]	SELF     	2 0 -14	; "onHoldStartText"
	48	[29]	LOADNIL  	4 4
	49	[29]	NEWTABLE 	5 0 1
	50	[29]	SETTABLE 	5 -15 1	; "pos" -
	51	[29]	CALL     	2 4 1
	52	[30]	SELF     	2 0 -16	; "onHoldReleaseText"
	53	[32]	CLOSURE  	4 2	; 0x7ff666407d80
	54	[32]	NEWTABLE 	5 0 1
	55	[32]	SETTABLE 	5 -15 1	; "pos" -
	56	[30]	CALL     	2 4 1
	57	[34]	SELF     	2 0 -14	; "onHoldStartText"
	58	[34]	LOADNIL  	4 4
	59	[34]	NEWTABLE 	5 0 1
	60	[34]	NEWTABLE 	6 0 2
	61	[34]	SETTABLE 	6 -3 -17	; "x" 50
	62	[34]	SETTABLE 	6 -5 -20	; "y" 100
	63	[34]	SETTABLE 	5 -15 6	; "pos" -
	64	[34]	CALL     	2 4 1
	65	[35]	SELF     	2 0 -16	; "onHoldReleaseText"
	66	[37]	CLOSURE  	4 3	; 0x7ff666407f70
	67	[37]	NEWTABLE 	5 0 1
	68	[37]	NEWTABLE 	6 0 2
	69	[37]	SETTABLE 	6 -3 -21	; "x" 240
	70	[37]	SETTABLE 	6 -5 -20	; "y" 100
	71	[37]	SETTABLE 	5 -15 6	; "pos" -
	72	[35]	CALL     	2 4 1
	73	[39]	SELF     	2 0 -14	; "onHoldStartText"
	74	[39]	LOADNIL  	4 4
	75	[39]	NEWTABLE 	5 0 1
	76	[39]	NEWTABLE 	6 0 2
	77	[39]	SETTABLE 	6 -3 -18	; "x" 20
	78	[39]	SETTABLE 	6 -5 -19	; "y" 80
	79	[39]	SETTABLE 	5 -15 6	; "pos" -
	80	[39]	CALL     	2 4 1
	81	[40]	SELF     	2 0 -16	; "onHoldReleaseText"
	82	[42]	CLOSURE  	4 4	; 0x7ff6664075a0
	83	[42]	NEWTABLE 	5 0 1
	84	[42]	NEWTABLE 	6 0 2
	85	[42]	SETTABLE 	6 -3 -21	; "x" 240
	86	[42]	SETTABLE 	6 -5 -20	; "y" 100
	87	[42]	SETTABLE 	5 -15 6	; "pos" -
	88	[40]	CALL     	2 4 1
	89	[56]	RETURN   	0 1

function <./spec/unit/textboxwidget_spec.lua:18,20> (7 instructions, 28 bytes at 0x7ff666406670)
1 param, 4 slots, 0 upvalues, 1 local, 4 constants, 0 functions
	1	[19]	GETGLOBAL	1 -1	; assert
	2	[19]	GETTABLE 	1 1 -2	; "is"
	3	[19]	GETTABLE 	1 1 -3	; "same"
	4	[19]	MOVE     	2 0
	5	[19]	LOADK    	3 -4	; "YOOOOOOOOOOOOOOOO"
	6	[19]	CALL     	1 3 1
	7	[20]	RETURN   	0 1

function <./spec/unit/textboxwidget_spec.lua:24,26> (7 instructions, 28 bytes at 0x7ff6664065c0)
1 param, 4 slots, 0 upvalues, 1 local, 4 constants, 0 functions
	1	[25]	GETGLOBAL	1 -1	; assert
	2	[25]	GETTABLE 	1 1 -2	; "is"
	3	[25]	GETTABLE 	1 1 -3	; "same"
	4	[25]	MOVE     	2 0
	5	[25]	LOADK    	3 -4	; "Foo"
	6	[25]	CALL     	1 3 1
	7	[26]	RETURN   	0 1

function <./spec/unit/textboxwidget_spec.lua:30,32> (7 instructions, 28 bytes at 0x7ff666407d80)
1 param, 4 slots, 0 upvalues, 1 local, 4 constants, 0 functions
	1	[31]	GETGLOBAL	1 -1	; assert
	2	[31]	GETTABLE 	1 1 -2	; "is"
	3	[31]	GETTABLE 	1 1 -3	; "same"
	4	[31]	MOVE     	2 0
	5	[31]	LOADK    	3 -4	; "Bar"
	6	[31]	CALL     	1 3 1
	7	[32]	RETURN   	0 1

function <./spec/unit/textboxwidget_spec.lua:35,37> (7 instructions, 28 bytes at 0x7ff666407f70)
1 param, 4 slots, 0 upvalues, 1 local, 4 constants, 0 functions
	1	[36]	GETGLOBAL	1 -1	; assert
	2	[36]	GETTABLE 	1 1 -2	; "is"
	3	[36]	GETTABLE 	1 1 -3	; "same"
	4	[36]	MOVE     	2 0
	5	[36]	LOADK    	3 -4	; "welcomes Bar into"
	6	[36]	CALL     	1 3 1
	7	[37]	RETURN   	0 1

function <./spec/unit/textboxwidget_spec.lua:40,42> (7 instructions, 28 bytes at 0x7ff6664075a0)
1 param, 4 slots, 0 upvalues, 1 local, 4 constants, 0 functions
	1	[41]	GETGLOBAL	1 -1	; assert
	2	[41]	GETTABLE 	1 1 -2	; "is"
	3	[41]	GETTABLE 	1 1 -3	; "same"
	4	[41]	MOVE     	2 0
	5	[41]	LOADK    	3 -4	; "Bar.\nFoo welcomes Bar into"
	6	[41]	CALL     	1 3 1
	7	[42]	RETURN   	0 1
