
main <./spec/unit/timeval_spec.lua:0,0> (5 instructions, 20 bytes at 0x7fbb57c068c0)
0+ params, 3 slots, 0 upvalues, 0 locals, 2 constants, 1 function
	1	[1]	GETGLOBAL	0 -1	; describe
	2	[1]	LOADK    	1 -2	; "TimeVal module"
	3	[73]	CLOSURE  	2 0	; 0x7fbb57c06b60
	4	[1]	CALL     	0 3 1
	5	[73]	RETURN   	0 1

function <./spec/unit/timeval_spec.lua:1,73> (38 instructions, 152 bytes at 0x7fbb57c06b60)
0 params, 6 slots, 0 upvalues, 3 locals, 8 constants, 7 functions
	1	[3]	GETGLOBAL	3 -1	; setup
	2	[8]	CLOSURE  	4 0	; 0x7fbb57c06ea0
	3	[8]	MOVE     	0 0
	4	[8]	MOVE     	0 1
	5	[8]	MOVE     	0 2
	6	[3]	CALL     	3 2 1
	7	[10]	GETGLOBAL	3 -2	; after_each
	8	[16]	CLOSURE  	4 1	; 0x7fbb57c07280
	9	[16]	MOVE     	0 2
	10	[16]	MOVE     	0 1
	11	[10]	CALL     	3 2 1
	12	[18]	GETGLOBAL	3 -3	; it
	13	[18]	LOADK    	4 -4	; "should add"
	14	[25]	CLOSURE  	5 2	; 0x7fbb57c06d60
	15	[25]	MOVE     	0 0
	16	[18]	CALL     	3 3 1
	17	[27]	GETGLOBAL	3 -3	; it
	18	[27]	LOADK    	4 -5	; "should subtract"
	19	[33]	CLOSURE  	5 3	; 0x7fbb57c07c30
	20	[33]	MOVE     	0 0
	21	[27]	CALL     	3 3 1
	22	[35]	GETGLOBAL	3 -3	; it
	23	[35]	LOADK    	4 -6	; "should guard against reverse subtraction logic"
	24	[42]	CLOSURE  	5 4	; 0x7fbb57c07f70
	25	[42]	MOVE     	0 1
	26	[42]	MOVE     	0 0
	27	[35]	CALL     	3 3 1
	28	[44]	GETGLOBAL	3 -3	; it
	29	[44]	LOADK    	4 -7	; "should derive sec and usec from more than 1 sec worth of usec"
	30	[48]	CLOSURE  	5 5	; 0x7fbb57c08530
	31	[48]	MOVE     	0 0
	32	[44]	CALL     	3 3 1
	33	[50]	GETGLOBAL	3 -3	; it
	34	[50]	LOADK    	4 -8	; "should compare"
	35	[72]	CLOSURE  	5 6	; 0x7fbb57c07b30
	36	[72]	MOVE     	0 0
	37	[50]	CALL     	3 3 1
	38	[73]	RETURN   	0 1

function <./spec/unit/timeval_spec.lua:3,8> (15 instructions, 60 bytes at 0x7fbb57c06ea0)
0 params, 2 slots, 3 upvalues, 0 locals, 5 constants, 0 functions
	1	[4]	GETGLOBAL	0 -1	; require
	2	[4]	LOADK    	1 -2	; "commonrequire"
	3	[4]	CALL     	0 2 1
	4	[5]	GETGLOBAL	0 -1	; require
	5	[5]	LOADK    	1 -3	; "ui/timeval"
	6	[5]	CALL     	0 2 2
	7	[5]	SETUPVAL 	0 0	; TimeVal
	8	[6]	GETGLOBAL	0 -1	; require
	9	[6]	LOADK    	1 -4	; "dbg"
	10	[6]	CALL     	0 2 2
	11	[6]	SETUPVAL 	0 1	; dbg
	12	[7]	GETUPVAL 	0 1	; dbg
	13	[7]	GETTABLE 	0 0 -5	; "is_on"
	14	[7]	SETUPVAL 	0 2	; dbg_on
	15	[8]	RETURN   	0 1

function <./spec/unit/timeval_spec.lua:10,16> (11 instructions, 44 bytes at 0x7fbb57c07280)
0 params, 2 slots, 2 upvalues, 0 locals, 2 constants, 0 functions
	1	[11]	GETUPVAL 	0 0	; dbg_on
	2	[11]	TEST     	0 0 0
	3	[11]	JMP      	4	; to 8
	4	[12]	GETUPVAL 	0 1	; dbg
	5	[12]	SELF     	0 0 -1	; "turnOn"
	6	[12]	CALL     	0 2 1
	7	[12]	JMP      	3	; to 11
	8	[14]	GETUPVAL 	0 1	; dbg
	9	[14]	SELF     	0 0 -2	; "turnOff"
	10	[14]	CALL     	0 2 1
	11	[16]	RETURN   	0 1

function <./spec/unit/timeval_spec.lua:18,25> (35 instructions, 140 bytes at 0x7fbb57c06d60)
0 params, 6 slots, 1 upvalue, 3 locals, 14 constants, 0 functions
	1	[19]	GETUPVAL 	0 0	; TimeVal
	2	[19]	SELF     	0 0 -1	; "new"
	3	[19]	NEWTABLE 	2 0 2
	4	[19]	SETTABLE 	2 -2 -3	; "sec" 5
	5	[19]	SETTABLE 	2 -4 -5	; "usec" 5000
	6	[19]	CALL     	0 3 2
	7	[20]	GETUPVAL 	1 0	; TimeVal
	8	[20]	SELF     	1 1 -1	; "new"
	9	[20]	NEWTABLE 	3 0 2
	10	[20]	SETTABLE 	3 -2 -6	; "sec" 10
	11	[20]	SETTABLE 	3 -4 -7	; "usec" 6000
	12	[20]	CALL     	1 3 2
	13	[21]	GETUPVAL 	2 0	; TimeVal
	14	[21]	SELF     	2 2 -1	; "new"
	15	[21]	NEWTABLE 	4 0 2
	16	[21]	SETTABLE 	4 -2 -6	; "sec" 10
	17	[21]	SETTABLE 	4 -4 -8	; "usec" 50000000
	18	[21]	CALL     	2 3 2
	19	[23]	GETGLOBAL	3 -9	; assert
	20	[23]	GETTABLE 	3 3 -10	; "is"
	21	[23]	GETTABLE 	3 3 -11	; "same"
	22	[23]	NEWTABLE 	4 0 2
	23	[23]	SETTABLE 	4 -2 -12	; "sec" 15
	24	[23]	SETTABLE 	4 -4 -13	; "usec" 11000
	25	[23]	ADD      	5 0 1
	26	[23]	CALL     	3 3 1
	27	[24]	GETGLOBAL	3 -9	; assert
	28	[24]	GETTABLE 	3 3 -10	; "is"
	29	[24]	GETTABLE 	3 3 -11	; "same"
	30	[24]	NEWTABLE 	4 0 2
	31	[24]	SETTABLE 	4 -2 -14	; "sec" 65
	32	[24]	SETTABLE 	4 -4 -5	; "usec" 5000
	33	[24]	ADD      	5 0 2
	34	[24]	CALL     	3 3 1
	35	[25]	RETURN   	0 1

function <./spec/unit/timeval_spec.lua:27,33> (29 instructions, 116 bytes at 0x7fbb57c07c30)
0 params, 5 slots, 1 upvalue, 2 locals, 13 constants, 0 functions
	1	[28]	GETUPVAL 	0 0	; TimeVal
	2	[28]	SELF     	0 0 -1	; "new"
	3	[28]	NEWTABLE 	2 0 2
	4	[28]	SETTABLE 	2 -2 -3	; "sec" 5
	5	[28]	SETTABLE 	2 -4 -5	; "usec" 5000
	6	[28]	CALL     	0 3 2
	7	[29]	GETUPVAL 	1 0	; TimeVal
	8	[29]	SELF     	1 1 -1	; "new"
	9	[29]	NEWTABLE 	3 0 2
	10	[29]	SETTABLE 	3 -2 -6	; "sec" 10
	11	[29]	SETTABLE 	3 -4 -7	; "usec" 6000
	12	[29]	CALL     	1 3 2
	13	[31]	GETGLOBAL	2 -8	; assert
	14	[31]	GETTABLE 	2 2 -9	; "is"
	15	[31]	GETTABLE 	2 2 -10	; "same"
	16	[31]	NEWTABLE 	3 0 2
	17	[31]	SETTABLE 	3 -2 -3	; "sec" 5
	18	[31]	SETTABLE 	3 -4 -11	; "usec" 1000
	19	[31]	SUB      	4 1 0
	20	[31]	CALL     	2 3 1
	21	[32]	GETGLOBAL	2 -8	; assert
	22	[32]	GETTABLE 	2 2 -9	; "is"
	23	[32]	GETTABLE 	2 2 -10	; "same"
	24	[32]	NEWTABLE 	3 0 2
	25	[32]	SETTABLE 	3 -2 -12	; "sec" -5
	26	[32]	SETTABLE 	3 -4 -13	; "usec" -1000
	27	[32]	SUB      	4 0 1
	28	[32]	CALL     	2 3 1
	29	[33]	RETURN   	0 1

function <./spec/unit/timeval_spec.lua:35,42> (28 instructions, 112 bytes at 0x7fbb57c07f70)
0 params, 4 slots, 2 upvalues, 2 locals, 13 constants, 1 function
	1	[36]	GETUPVAL 	0 0	; dbg
	2	[36]	SELF     	0 0 -1	; "turnOn"
	3	[36]	CALL     	0 2 1
	4	[37]	GETGLOBAL	0 -2	; package
	5	[37]	GETTABLE 	0 0 -3	; "reload"
	6	[37]	LOADK    	1 -4	; "ui/timeval"
	7	[37]	CALL     	0 2 2
	8	[37]	SETUPVAL 	0 1	; TimeVal
	9	[38]	GETUPVAL 	0 1	; TimeVal
	10	[38]	SELF     	0 0 -5	; "new"
	11	[38]	NEWTABLE 	2 0 2
	12	[38]	SETTABLE 	2 -6 -7	; "sec" 5
	13	[38]	SETTABLE 	2 -8 -9	; "usec" 5000
	14	[38]	CALL     	0 3 2
	15	[39]	GETUPVAL 	1 1	; TimeVal
	16	[39]	SELF     	1 1 -5	; "new"
	17	[39]	NEWTABLE 	3 0 2
	18	[39]	SETTABLE 	3 -6 -10	; "sec" 10
	19	[39]	SETTABLE 	3 -8 -9	; "usec" 5000
	20	[39]	CALL     	1 3 2
	21	[41]	GETGLOBAL	2 -11	; assert
	22	[41]	GETTABLE 	2 2 -12	; "has"
	23	[41]	GETTABLE 	2 2 -13	; "errors"
	24	[41]	CLOSURE  	3 0	; 0x7fbb57c08320
	25	[41]	MOVE     	0 0
	26	[41]	MOVE     	0 1
	27	[41]	CALL     	2 2 1
	28	[42]	RETURN   	0 1

function <./spec/unit/timeval_spec.lua:41,41> (5 instructions, 20 bytes at 0x7fbb57c08320)
0 params, 2 slots, 2 upvalues, 0 locals, 0 constants, 0 functions
	1	[41]	GETUPVAL 	0 0	; timev1
	2	[41]	GETUPVAL 	1 1	; timev2
	3	[41]	SUB      	0 0 1
	4	[41]	RETURN   	0 2
	5	[41]	RETURN   	0 1

function <./spec/unit/timeval_spec.lua:44,48> (15 instructions, 60 bytes at 0x7fbb57c08530)
0 params, 4 slots, 1 upvalue, 1 local, 10 constants, 0 functions
	1	[45]	GETUPVAL 	0 0	; TimeVal
	2	[45]	SELF     	0 0 -1	; "new"
	3	[45]	NEWTABLE 	2 0 2
	4	[45]	SETTABLE 	2 -2 -3	; "sec" 5
	5	[45]	SETTABLE 	2 -4 -5	; "usec" 5000000
	6	[45]	CALL     	0 3 2
	7	[47]	GETGLOBAL	1 -6	; assert
	8	[47]	GETTABLE 	1 1 -7	; "is"
	9	[47]	GETTABLE 	1 1 -8	; "same"
	10	[47]	NEWTABLE 	2 0 2
	11	[47]	SETTABLE 	2 -2 -9	; "sec" 10
	12	[47]	SETTABLE 	2 -4 -10	; "usec" 0
	13	[47]	MOVE     	3 0
	14	[47]	CALL     	1 3 1
	15	[48]	RETURN   	0 1

function <./spec/unit/timeval_spec.lua:50,72> (116 instructions, 464 bytes at 0x7fbb57c07b30)
0 params, 6 slots, 1 upvalue, 4 locals, 10 constants, 0 functions
	1	[51]	GETUPVAL 	0 0	; TimeVal
	2	[51]	SELF     	0 0 -1	; "new"
	3	[51]	NEWTABLE 	2 0 2
	4	[51]	SETTABLE 	2 -2 -3	; "sec" 5
	5	[51]	SETTABLE 	2 -4 -5	; "usec" 5000
	6	[51]	CALL     	0 3 2
	7	[52]	GETUPVAL 	1 0	; TimeVal
	8	[52]	SELF     	1 1 -1	; "new"
	9	[52]	NEWTABLE 	3 0 2
	10	[52]	SETTABLE 	3 -2 -6	; "sec" 10
	11	[52]	SETTABLE 	3 -4 -7	; "usec" 6000
	12	[52]	CALL     	1 3 2
	13	[53]	GETUPVAL 	2 0	; TimeVal
	14	[53]	SELF     	2 2 -1	; "new"
	15	[53]	NEWTABLE 	4 0 2
	16	[53]	SETTABLE 	4 -2 -3	; "sec" 5
	17	[53]	SETTABLE 	4 -4 -5	; "usec" 5000
	18	[53]	CALL     	2 3 2
	19	[54]	GETUPVAL 	3 0	; TimeVal
	20	[54]	SELF     	3 3 -1	; "new"
	21	[54]	NEWTABLE 	5 0 2
	22	[54]	SETTABLE 	5 -2 -3	; "sec" 5
	23	[54]	SETTABLE 	5 -4 -7	; "usec" 6000
	24	[54]	CALL     	3 3 2
	25	[56]	GETGLOBAL	4 -8	; assert
	26	[56]	GETTABLE 	4 4 -9	; "is_true"
	27	[56]	LT       	1 0 1
	28	[56]	JMP      	1	; to 30
	29	[56]	LOADBOOL 	5 0 1
	30	[56]	LOADBOOL 	5 1 0
	31	[56]	CALL     	4 2 1
	32	[57]	GETGLOBAL	4 -8	; assert
	33	[57]	GETTABLE 	4 4 -10	; "is_false"
	34	[57]	LT       	1 1 0
	35	[57]	JMP      	1	; to 37
	36	[57]	LOADBOOL 	5 0 1
	37	[57]	LOADBOOL 	5 1 0
	38	[57]	CALL     	4 2 1
	39	[58]	GETGLOBAL	4 -8	; assert
	40	[58]	GETTABLE 	4 4 -9	; "is_true"
	41	[58]	LE       	1 0 1
	42	[58]	JMP      	1	; to 44
	43	[58]	LOADBOOL 	5 0 1
	44	[58]	LOADBOOL 	5 1 0
	45	[58]	CALL     	4 2 1
	46	[60]	GETGLOBAL	4 -8	; assert
	47	[60]	GETTABLE 	4 4 -9	; "is_true"
	48	[60]	LT       	1 0 3
	49	[60]	JMP      	1	; to 51
	50	[60]	LOADBOOL 	5 0 1
	51	[60]	LOADBOOL 	5 1 0
	52	[60]	CALL     	4 2 1
	53	[61]	GETGLOBAL	4 -8	; assert
	54	[61]	GETTABLE 	4 4 -10	; "is_false"
	55	[61]	LT       	1 3 0
	56	[61]	JMP      	1	; to 58
	57	[61]	LOADBOOL 	5 0 1
	58	[61]	LOADBOOL 	5 1 0
	59	[61]	CALL     	4 2 1
	60	[62]	GETGLOBAL	4 -8	; assert
	61	[62]	GETTABLE 	4 4 -9	; "is_true"
	62	[62]	LE       	1 0 3
	63	[62]	JMP      	1	; to 65
	64	[62]	LOADBOOL 	5 0 1
	65	[62]	LOADBOOL 	5 1 0
	66	[62]	CALL     	4 2 1
	67	[64]	GETGLOBAL	4 -8	; assert
	68	[64]	GETTABLE 	4 4 -9	; "is_true"
	69	[64]	LT       	1 0 1
	70	[64]	JMP      	1	; to 72
	71	[64]	LOADBOOL 	5 0 1
	72	[64]	LOADBOOL 	5 1 0
	73	[64]	CALL     	4 2 1
	74	[65]	GETGLOBAL	4 -8	; assert
	75	[65]	GETTABLE 	4 4 -10	; "is_false"
	76	[65]	LT       	1 1 0
	77	[65]	JMP      	1	; to 79
	78	[65]	LOADBOOL 	5 0 1
	79	[65]	LOADBOOL 	5 1 0
	80	[65]	CALL     	4 2 1
	81	[66]	GETGLOBAL	4 -8	; assert
	82	[66]	GETTABLE 	4 4 -9	; "is_true"
	83	[66]	LE       	1 0 1
	84	[66]	JMP      	1	; to 86
	85	[66]	LOADBOOL 	5 0 1
	86	[66]	LOADBOOL 	5 1 0
	87	[66]	CALL     	4 2 1
	88	[68]	GETGLOBAL	4 -8	; assert
	89	[68]	GETTABLE 	4 4 -9	; "is_true"
	90	[68]	EQ       	1 0 2
	91	[68]	JMP      	1	; to 93
	92	[68]	LOADBOOL 	5 0 1
	93	[68]	LOADBOOL 	5 1 0
	94	[68]	CALL     	4 2 1
	95	[69]	GETGLOBAL	4 -8	; assert
	96	[69]	GETTABLE 	4 4 -10	; "is_false"
	97	[69]	EQ       	1 0 1
	98	[69]	JMP      	1	; to 100
	99	[69]	LOADBOOL 	5 0 1
	100	[69]	LOADBOOL 	5 1 0
	101	[69]	CALL     	4 2 1
	102	[70]	GETGLOBAL	4 -8	; assert
	103	[70]	GETTABLE 	4 4 -9	; "is_true"
	104	[70]	LE       	1 2 0
	105	[70]	JMP      	1	; to 107
	106	[70]	LOADBOOL 	5 0 1
	107	[70]	LOADBOOL 	5 1 0
	108	[70]	CALL     	4 2 1
	109	[71]	GETGLOBAL	4 -8	; assert
	110	[71]	GETTABLE 	4 4 -9	; "is_true"
	111	[71]	LE       	1 0 2
	112	[71]	JMP      	1	; to 114
	113	[71]	LOADBOOL 	5 0 1
	114	[71]	LOADBOOL 	5 1 0
	115	[71]	CALL     	4 2 1
	116	[72]	RETURN   	0 1
