
main <./frontend/ui/timeval.lua:0,0> (34 instructions, 136 bytes at 0x7f84f54068c0)
0+ params, 8 slots, 0 upvalues, 3 locals, 14 constants, 8 functions
	1	[16]	GETGLOBAL	0 -1	; require
	2	[16]	LOADK    	1 -2	; "dbg"
	3	[16]	CALL     	0 2 2
	4	[17]	GETGLOBAL	1 -1	; require
	5	[17]	LOADK    	2 -3	; "ffi/util"
	6	[17]	CALL     	1 2 2
	7	[26]	NEWTABLE 	2 0 2
	8	[27]	SETTABLE 	2 -4 -5	; "sec" 0
	9	[28]	SETTABLE 	2 -6 -5	; "usec" 0
	10	[56]	CLOSURE  	3 0	; 0x7f84f5406bf0
	11	[42]	SETTABLE 	2 -7 3	; "new" -
	12	[72]	CLOSURE  	3 1	; 0x7f84f5407160
	13	[59]	SETTABLE 	2 -8 3	; "__lt" -
	14	[87]	CLOSURE  	3 2	; 0x7f84f5406aa0
	15	[74]	SETTABLE 	2 -9 3	; "__le" -
	16	[95]	CLOSURE  	3 3	; 0x7f84f5407bc0
	17	[89]	SETTABLE 	2 -10 3	; "__eq" -
	18	[112]	CLOSURE  	3 4	; 0x7f84f5408080
	19	[112]	MOVE     	0 2
	20	[97]	SETTABLE 	2 -11 3	; "__sub" -
	21	[114]	SELF     	3 0 -12	; "guard"
	22	[114]	MOVE     	5 2
	23	[114]	LOADK    	6 -11	; "__sub"
	24	[118]	CLOSURE  	7 5	; 0x7f84f5408a60
	25	[114]	CALL     	3 5 1
	26	[139]	CLOSURE  	3 6	; 0x7f84f5406d10
	27	[139]	MOVE     	0 2
	28	[120]	SETTABLE 	2 -13 3	; "__add" -
	29	[156]	CLOSURE  	3 7	; 0x7f84f5406d90
	30	[156]	MOVE     	0 1
	31	[156]	MOVE     	0 2
	32	[153]	SETTABLE 	2 -14 3	; "now" -
	33	[158]	RETURN   	2 2
	34	[158]	RETURN   	0 1

function <./frontend/ui/timeval.lua:42,56> (33 instructions, 132 bytes at 0x7f84f5406bf0)
2 params, 6 slots, 0 upvalues, 3 locals, 9 constants, 0 functions
	1	[43]	TESTSET  	2 1 1
	2	[43]	JMP      	1	; to 4
	3	[43]	NEWTABLE 	2 0 0
	4	[44]	GETTABLE 	3 2 -1	; "sec"
	5	[44]	EQ       	0 3 -2	; - nil
	6	[44]	JMP      	1	; to 8
	7	[45]	SETTABLE 	2 -1 -3	; "sec" 0
	8	[47]	GETTABLE 	3 2 -4	; "usec"
	9	[47]	EQ       	0 3 -2	; - nil
	10	[47]	JMP      	2	; to 13
	11	[48]	SETTABLE 	2 -4 -3	; "usec" 0
	12	[48]	JMP      	14	; to 27
	13	[49]	GETTABLE 	3 2 -4	; "usec"
	14	[49]	LT       	0 -5 3	; 1000000 -
	15	[49]	JMP      	11	; to 27
	16	[50]	GETTABLE 	3 2 -1	; "sec"
	17	[50]	GETGLOBAL	4 -6	; math
	18	[50]	GETTABLE 	4 4 -7	; "floor"
	19	[50]	GETTABLE 	5 2 -4	; "usec"
	20	[50]	DIV      	5 5 -5	; - 1000000
	21	[50]	CALL     	4 2 2
	22	[50]	ADD      	3 3 4
	23	[50]	SETTABLE 	2 -1 3	; "sec" -
	24	[51]	GETTABLE 	3 2 -4	; "usec"
	25	[51]	MOD      	3 3 -5
	26	[51]	SETTABLE 	2 -4 3	; "usec" -
	27	[53]	GETGLOBAL	3 -8	; setmetatable
	28	[53]	MOVE     	4 2
	29	[53]	MOVE     	5 0
	30	[53]	CALL     	3 3 1
	31	[54]	SETTABLE 	0 -9 0	; "__index" -
	32	[55]	RETURN   	2 2
	33	[56]	RETURN   	0 1

function <./frontend/ui/timeval.lua:59,72> (24 instructions, 96 bytes at 0x7f84f5407160)
2 params, 4 slots, 0 upvalues, 2 locals, 2 constants, 0 functions
	1	[60]	GETTABLE 	2 0 -1	; "sec"
	2	[60]	GETTABLE 	3 1 -1	; "sec"
	3	[60]	LT       	0 2 3
	4	[60]	JMP      	3	; to 8
	5	[61]	LOADBOOL 	2 1 0
	6	[61]	RETURN   	2 2
	7	[61]	JMP      	16	; to 24
	8	[62]	GETTABLE 	2 0 -1	; "sec"
	9	[62]	GETTABLE 	3 1 -1	; "sec"
	10	[62]	LT       	0 3 2
	11	[62]	JMP      	3	; to 15
	12	[63]	LOADBOOL 	2 0 0
	13	[63]	RETURN   	2 2
	14	[63]	JMP      	9	; to 24
	15	[66]	GETTABLE 	2 0 -2	; "usec"
	16	[66]	GETTABLE 	3 1 -2	; "usec"
	17	[66]	LT       	0 2 3
	18	[66]	JMP      	3	; to 22
	19	[67]	LOADBOOL 	2 1 0
	20	[67]	RETURN   	2 2
	21	[67]	JMP      	2	; to 24
	22	[69]	LOADBOOL 	2 0 0
	23	[69]	RETURN   	2 2
	24	[72]	RETURN   	0 1

function <./frontend/ui/timeval.lua:74,87> (24 instructions, 96 bytes at 0x7f84f5406aa0)
2 params, 4 slots, 0 upvalues, 2 locals, 2 constants, 0 functions
	1	[75]	GETTABLE 	2 0 -1	; "sec"
	2	[75]	GETTABLE 	3 1 -1	; "sec"
	3	[75]	LT       	0 2 3
	4	[75]	JMP      	3	; to 8
	5	[76]	LOADBOOL 	2 1 0
	6	[76]	RETURN   	2 2
	7	[76]	JMP      	16	; to 24
	8	[77]	GETTABLE 	2 0 -1	; "sec"
	9	[77]	GETTABLE 	3 1 -1	; "sec"
	10	[77]	LT       	0 3 2
	11	[77]	JMP      	3	; to 15
	12	[78]	LOADBOOL 	2 0 0
	13	[78]	RETURN   	2 2
	14	[78]	JMP      	9	; to 24
	15	[81]	GETTABLE 	2 0 -2	; "usec"
	16	[81]	GETTABLE 	3 1 -2	; "usec"
	17	[81]	LT       	0 3 2
	18	[81]	JMP      	3	; to 22
	19	[82]	LOADBOOL 	2 0 0
	20	[82]	RETURN   	2 2
	21	[82]	JMP      	2	; to 24
	22	[84]	LOADBOOL 	2 1 0
	23	[84]	RETURN   	2 2
	24	[87]	RETURN   	0 1

function <./frontend/ui/timeval.lua:89,95> (14 instructions, 56 bytes at 0x7f84f5407bc0)
2 params, 4 slots, 0 upvalues, 2 locals, 2 constants, 0 functions
	1	[90]	GETTABLE 	2 0 -1	; "sec"
	2	[90]	GETTABLE 	3 1 -1	; "sec"
	3	[90]	EQ       	0 2 3
	4	[90]	JMP      	7	; to 12
	5	[90]	GETTABLE 	2 0 -2	; "usec"
	6	[90]	GETTABLE 	3 1 -2	; "usec"
	7	[90]	EQ       	0 2 3
	8	[90]	JMP      	3	; to 12
	9	[91]	LOADBOOL 	2 1 0
	10	[91]	RETURN   	2 2
	11	[91]	JMP      	2	; to 14
	12	[93]	LOADBOOL 	2 0 0
	13	[93]	RETURN   	2 2
	14	[95]	RETURN   	0 1

function <./frontend/ui/timeval.lua:97,112> (39 instructions, 156 bytes at 0x7f84f5408080)
2 params, 5 slots, 1 upvalue, 3 locals, 6 constants, 0 functions
	1	[98]	GETUPVAL 	2 0	; TimeVal
	2	[98]	SELF     	2 2 -1	; "new"
	3	[98]	NEWTABLE 	4 0 0
	4	[98]	CALL     	2 3 2
	5	[100]	GETTABLE 	3 0 -2	; "sec"
	6	[100]	GETTABLE 	4 1 -2	; "sec"
	7	[100]	SUB      	3 3 4
	8	[100]	SETTABLE 	2 -2 3	; "sec" -
	9	[101]	GETTABLE 	3 0 -3	; "usec"
	10	[101]	GETTABLE 	4 1 -3	; "usec"
	11	[101]	SUB      	3 3 4
	12	[101]	SETTABLE 	2 -3 3	; "usec" -
	13	[103]	GETTABLE 	3 2 -2	; "sec"
	14	[103]	LT       	0 3 -4	; - 0
	15	[103]	JMP      	10	; to 26
	16	[103]	GETTABLE 	3 2 -3	; "usec"
	17	[103]	LT       	0 -4 3	; 0 -
	18	[103]	JMP      	7	; to 26
	19	[104]	GETTABLE 	3 2 -2	; "sec"
	20	[104]	ADD      	3 3 -5	; - 1
	21	[104]	SETTABLE 	2 -2 3	; "sec" -
	22	[105]	GETTABLE 	3 2 -3	; "usec"
	23	[105]	SUB      	3 3 -6	; - 1000000
	24	[105]	SETTABLE 	2 -3 3	; "usec" -
	25	[105]	JMP      	12	; to 38
	26	[106]	GETTABLE 	3 2 -2	; "sec"
	27	[106]	LT       	0 -4 3	; 0 -
	28	[106]	JMP      	9	; to 38
	29	[106]	GETTABLE 	3 2 -3	; "usec"
	30	[106]	LT       	0 3 -4	; - 0
	31	[106]	JMP      	6	; to 38
	32	[107]	GETTABLE 	3 2 -2	; "sec"
	33	[107]	SUB      	3 3 -5	; - 1
	34	[107]	SETTABLE 	2 -2 3	; "sec" -
	35	[108]	GETTABLE 	3 2 -3	; "usec"
	36	[108]	ADD      	3 3 -6	; - 1000000
	37	[108]	SETTABLE 	2 -3 3	; "usec" -
	38	[111]	RETURN   	2 2
	39	[112]	RETURN   	0 1

function <./frontend/ui/timeval.lua:115,118> (18 instructions, 72 bytes at 0x7f84f5408a60)
2 params, 5 slots, 0 upvalues, 2 locals, 4 constants, 0 functions
	1	[116]	GETGLOBAL	2 -1	; assert
	2	[116]	GETTABLE 	3 0 -2	; "sec"
	3	[116]	GETTABLE 	4 1 -2	; "sec"
	4	[116]	LT       	1 4 3
	5	[116]	JMP      	9	; to 15
	6	[116]	GETTABLE 	3 0 -2	; "sec"
	7	[116]	GETTABLE 	4 1 -2	; "sec"
	8	[116]	EQ       	0 3 4
	9	[116]	JMP      	4	; to 14
	10	[116]	GETTABLE 	3 0 -3	; "usec"
	11	[116]	GETTABLE 	4 1 -3	; "usec"
	12	[116]	LE       	1 4 3
	13	[116]	JMP      	1	; to 15
	14	[116]	LOADBOOL 	3 0 1
	15	[116]	LOADBOOL 	3 1 0
	16	[117]	LOADK    	4 -4	; "Subtract the first timeval from the latest, not vice versa."
	17	[116]	CALL     	2 3 1
	18	[118]	RETURN   	0 1

function <./frontend/ui/timeval.lua:120,139> (48 instructions, 192 bytes at 0x7f84f5406d10)
2 params, 5 slots, 1 upvalue, 3 locals, 6 constants, 0 functions
	1	[121]	GETUPVAL 	2 0	; TimeVal
	2	[121]	SELF     	2 2 -1	; "new"
	3	[121]	NEWTABLE 	4 0 0
	4	[121]	CALL     	2 3 2
	5	[123]	GETTABLE 	3 0 -2	; "sec"
	6	[123]	GETTABLE 	4 1 -2	; "sec"
	7	[123]	ADD      	3 3 4
	8	[123]	SETTABLE 	2 -2 3	; "sec" -
	9	[124]	GETTABLE 	3 0 -3	; "usec"
	10	[124]	GETTABLE 	4 1 -3	; "usec"
	11	[124]	ADD      	3 3 4
	12	[124]	SETTABLE 	2 -3 3	; "usec" -
	13	[125]	GETTABLE 	3 2 -3	; "usec"
	14	[125]	LT       	0 -4 3	; 1000000 -
	15	[125]	JMP      	6	; to 22
	16	[126]	GETTABLE 	3 2 -3	; "usec"
	17	[126]	SUB      	3 3 -4	; - 1000000
	18	[126]	SETTABLE 	2 -3 3	; "usec" -
	19	[127]	GETTABLE 	3 2 -2	; "sec"
	20	[127]	ADD      	3 3 -5	; - 1
	21	[127]	SETTABLE 	2 -2 3	; "sec" -
	22	[130]	GETTABLE 	3 2 -2	; "sec"
	23	[130]	LT       	0 3 -6	; - 0
	24	[130]	JMP      	10	; to 35
	25	[130]	GETTABLE 	3 2 -3	; "usec"
	26	[130]	LT       	0 -6 3	; 0 -
	27	[130]	JMP      	7	; to 35
	28	[131]	GETTABLE 	3 2 -2	; "sec"
	29	[131]	ADD      	3 3 -5	; - 1
	30	[131]	SETTABLE 	2 -2 3	; "sec" -
	31	[132]	GETTABLE 	3 2 -3	; "usec"
	32	[132]	SUB      	3 3 -4	; - 1000000
	33	[132]	SETTABLE 	2 -3 3	; "usec" -
	34	[132]	JMP      	12	; to 47
	35	[133]	GETTABLE 	3 2 -2	; "sec"
	36	[133]	LT       	0 -6 3	; 0 -
	37	[133]	JMP      	9	; to 47
	38	[133]	GETTABLE 	3 2 -3	; "usec"
	39	[133]	LT       	0 3 -6	; - 0
	40	[133]	JMP      	6	; to 47
	41	[134]	GETTABLE 	3 2 -2	; "sec"
	42	[134]	SUB      	3 3 -5	; - 1
	43	[134]	SETTABLE 	2 -2 3	; "sec" -
	44	[135]	GETTABLE 	3 2 -3	; "usec"
	45	[135]	ADD      	3 3 -4	; - 1000000
	46	[135]	SETTABLE 	2 -3 3	; "usec" -
	47	[138]	RETURN   	2 2
	48	[139]	RETURN   	0 1

function <./frontend/ui/timeval.lua:153,156> (11 instructions, 44 bytes at 0x7f84f5406d90)
1 param, 6 slots, 2 upvalues, 3 locals, 4 constants, 0 functions
	1	[154]	GETUPVAL 	1 0	; util
	2	[154]	GETTABLE 	1 1 -1	; "gettime"
	3	[154]	CALL     	1 1 3
	4	[155]	GETUPVAL 	3 1	; TimeVal
	5	[155]	SELF     	3 3 -2	; "new"
	6	[155]	NEWTABLE 	5 0 2
	7	[155]	SETTABLE 	5 -3 1	; "sec" -
	8	[155]	SETTABLE 	5 -4 2	; "usec" -
	9	[155]	TAILCALL 	3 3 0
	10	[155]	RETURN   	3 0
	11	[156]	RETURN   	0 1
