-- BYTECODE -- timeval.lua:42-56
0001    ISTC     2   1
0002    JMP      2 => 0004
0003    TNEW     2   0
0004 => TGETS    3   2   0  ; "sec"
0005    ISNEP    3   0
0006    JMP      3 => 0009
0007    KSHORT   3   0
0008    TSETS    3   2   0  ; "sec"
0009 => TGETS    3   2   1  ; "usec"
0010    ISNEP    3   0
0011    JMP      3 => 0015
0012    KSHORT   3   0
0013    TSETS    3   2   1  ; "usec"
0014    JMP      3 => 0030
0015 => TGETS    3   2   1  ; "usec"
0016    KNUM     4   0      ; 1000000
0017    ISGE     4   3
0018    JMP      3 => 0030
0019    TGETS    3   2   0  ; "sec"
0020    GGET     4   2      ; "math"
0021    TGETS    4   4   3  ; "floor"
0022    TGETS    5   2   1  ; "usec"
0023    DIVVN    5   5   0  ; 1000000
0024    CALL     4   2   2
0025    ADDVV    3   3   4
0026    TSETS    3   2   0  ; "sec"
0027    TGETS    3   2   1  ; "usec"
0028    MODVN    3   3   0  ; 1000000
0029    TSETS    3   2   1  ; "usec"
0030 => GGET     3   4      ; "setmetatable"
0031    MOV      4   2
0032    MOV      5   0
0033    CALL     3   1   3
0034    TSETS    0   0   5  ; "__index"
0035    RET1     2   2

-- BYTECODE -- timeval.lua:59-72
0001    TGETS    2   0   0  ; "sec"
0002    TGETS    3   1   0  ; "sec"
0003    ISGE     2   3
0004    JMP      2 => 0008
0005    KPRI     2   2
0006    RET1     2   2
0007    JMP      2 => 0024
0008 => TGETS    2   0   0  ; "sec"
0009    TGETS    3   1   0  ; "sec"
0010    ISGE     3   2
0011    JMP      2 => 0015
0012    KPRI     2   1
0013    RET1     2   2
0014    JMP      2 => 0024
0015 => TGETS    2   0   1  ; "usec"
0016    TGETS    3   1   1  ; "usec"
0017    ISGE     2   3
0018    JMP      2 => 0022
0019    KPRI     2   2
0020    RET1     2   2
0021    JMP      2 => 0024
0022 => KPRI     2   1
0023    RET1     2   2
0024 => RET0     0   1

-- BYTECODE -- timeval.lua:74-87
0001    TGETS    2   0   0  ; "sec"
0002    TGETS    3   1   0  ; "sec"
0003    ISGE     2   3
0004    JMP      2 => 0008
0005    KPRI     2   2
0006    RET1     2   2
0007    JMP      2 => 0024
0008 => TGETS    2   0   0  ; "sec"
0009    TGETS    3   1   0  ; "sec"
0010    ISGE     3   2
0011    JMP      2 => 0015
0012    KPRI     2   1
0013    RET1     2   2
0014    JMP      2 => 0024
0015 => TGETS    2   0   1  ; "usec"
0016    TGETS    3   1   1  ; "usec"
0017    ISGE     3   2
0018    JMP      2 => 0022
0019    KPRI     2   1
0020    RET1     2   2
0021    JMP      2 => 0024
0022 => KPRI     2   2
0023    RET1     2   2
0024 => RET0     0   1

-- BYTECODE -- timeval.lua:89-95
0001    TGETS    2   0   0  ; "sec"
0002    TGETS    3   1   0  ; "sec"
0003    ISNEV    2   3
0004    JMP      2 => 0012
0005    TGETS    2   0   1  ; "usec"
0006    TGETS    3   1   1  ; "usec"
0007    ISNEV    2   3
0008    JMP      2 => 0012
0009    KPRI     2   2
0010    RET1     2   2
0011    JMP      2 => 0014
0012 => KPRI     2   1
0013    RET1     2   2
0014 => RET0     0   1

-- BYTECODE -- timeval.lua:97-112
0001    UGET     2   0      ; TimeVal
0002    MOV      3   2
0003    TGETS    2   2   0  ; "new"
0004    TNEW     4   0
0005    CALL     2   2   3
0006    TGETS    3   0   1  ; "sec"
0007    TGETS    4   1   1  ; "sec"
0008    SUBVV    3   3   4
0009    TSETS    3   2   1  ; "sec"
0010    TGETS    3   0   2  ; "usec"
0011    TGETS    4   1   2  ; "usec"
0012    SUBVV    3   3   4
0013    TSETS    3   2   2  ; "usec"
0014    TGETS    3   2   1  ; "sec"
0015    KSHORT   4   0
0016    ISGE     3   4
0017    JMP      3 => 0029
0018    TGETS    3   2   2  ; "usec"
0019    KSHORT   4   0
0020    ISGE     4   3
0021    JMP      3 => 0029
0022    TGETS    3   2   1  ; "sec"
0023    ADDVN    3   3   0  ; 1
0024    TSETS    3   2   1  ; "sec"
0025    TGETS    3   2   2  ; "usec"
0026    SUBVN    3   3   1  ; 1000000
0027    TSETS    3   2   2  ; "usec"
0028    JMP      3 => 0043
0029 => TGETS    3   2   1  ; "sec"
0030    KSHORT   4   0
0031    ISGE     4   3
0032    JMP      3 => 0043
0033    TGETS    3   2   2  ; "usec"
0034    KSHORT   4   0
0035    ISGE     3   4
0036    JMP      3 => 0043
0037    TGETS    3   2   1  ; "sec"
0038    SUBVN    3   3   0  ; 1
0039    TSETS    3   2   1  ; "sec"
0040    TGETS    3   2   2  ; "usec"
0041    ADDVN    3   3   1  ; 1000000
0042    TSETS    3   2   2  ; "usec"
0043 => RET1     2   2

-- BYTECODE -- timeval.lua:115-118
0001    GGET     2   0      ; "assert"
0002    TGETS    3   0   1  ; "sec"
0003    TGETS    4   1   1  ; "sec"
0004    ISLT     4   3
0005    JMP      3 => 0016
0006    TGETS    3   0   1  ; "sec"
0007    TGETS    4   1   1  ; "sec"
0008    ISNEV    3   4
0009    JMP      3 => 0014
0010    TGETS    3   0   2  ; "usec"
0011    TGETS    4   1   2  ; "usec"
0012    ISLE     4   3
0013    JMP      3 => 0016
0014 => KPRI     3   1
0015    JMP      4 => 0017
0016 => KPRI     3   2
0017 => KSTR     4   3      ; "Subtract the first timeval from the late"~
0018    CALL     2   1   3
0019    RET0     0   1

-- BYTECODE -- timeval.lua:120-139
0001    UGET     2   0      ; TimeVal
0002    MOV      3   2
0003    TGETS    2   2   0  ; "new"
0004    TNEW     4   0
0005    CALL     2   2   3
0006    TGETS    3   0   1  ; "sec"
0007    TGETS    4   1   1  ; "sec"
0008    ADDVV    3   3   4
0009    TSETS    3   2   1  ; "sec"
0010    TGETS    3   0   2  ; "usec"
0011    TGETS    4   1   2  ; "usec"
0012    ADDVV    3   3   4
0013    TSETS    3   2   2  ; "usec"
0014    TGETS    3   2   2  ; "usec"
0015    KNUM     4   0      ; 1000000
0016    ISGE     4   3
0017    JMP      3 => 0024
0018    TGETS    3   2   2  ; "usec"
0019    SUBVN    3   3   0  ; 1000000
0020    TSETS    3   2   2  ; "usec"
0021    TGETS    3   2   1  ; "sec"
0022    ADDVN    3   3   1  ; 1
0023    TSETS    3   2   1  ; "sec"
0024 => TGETS    3   2   1  ; "sec"
0025    KSHORT   4   0
0026    ISGE     3   4
0027    JMP      3 => 0039
0028    TGETS    3   2   2  ; "usec"
0029    KSHORT   4   0
0030    ISGE     4   3
0031    JMP      3 => 0039
0032    TGETS    3   2   1  ; "sec"
0033    ADDVN    3   3   1  ; 1
0034    TSETS    3   2   1  ; "sec"
0035    TGETS    3   2   2  ; "usec"
0036    SUBVN    3   3   0  ; 1000000
0037    TSETS    3   2   2  ; "usec"
0038    JMP      3 => 0053
0039 => TGETS    3   2   1  ; "sec"
0040    KSHORT   4   0
0041    ISGE     4   3
0042    JMP      3 => 0053
0043    TGETS    3   2   2  ; "usec"
0044    KSHORT   4   0
0045    ISGE     3   4
0046    JMP      3 => 0053
0047    TGETS    3   2   1  ; "sec"
0048    SUBVN    3   3   1  ; 1
0049    TSETS    3   2   1  ; "sec"
0050    TGETS    3   2   2  ; "usec"
0051    ADDVN    3   3   0  ; 1000000
0052    TSETS    3   2   2  ; "usec"
0053 => RET1     2   2

-- BYTECODE -- timeval.lua:153-156
0001    UGET     1   0      ; util
0002    TGETS    1   1   0  ; "gettime"
0003    CALL     1   3   1
0004    UGET     3   1      ; TimeVal
0005    MOV      4   3
0006    TGETS    3   3   1  ; "new"
0007    TDUP     5   2
0008    TSETS    1   5   3  ; "sec"
0009    TSETS    2   5   4  ; "usec"
0010    CALLT    3   3

-- BYTECODE -- timeval.lua:0-159
0001    GGET     0   0      ; "require"
0002    KSTR     1   1      ; "dbg"
0003    CALL     0   2   2
0004    GGET     1   0      ; "require"
0005    KSTR     2   2      ; "ffi/util"
0006    CALL     1   2   2
0007    TDUP     2   3
0008    FNEW     3   5      ; timeval.lua:42
0009    TSETS    3   2   4  ; "new"
0010    FNEW     3   7      ; timeval.lua:59
0011    TSETS    3   2   6  ; "__lt"
0012    FNEW     3   9      ; timeval.lua:74
0013    TSETS    3   2   8  ; "__le"
0014    FNEW     3  11      ; timeval.lua:89
0015    TSETS    3   2  10  ; "__eq"
0016    FNEW     3  13      ; timeval.lua:97
0017    TSETS    3   2  12  ; "__sub"
0018    MOV      4   0
0019    TGETS    3   0  14  ; "guard"
0020    MOV      5   2
0021    KSTR     6  12      ; "__sub"
0022    FNEW     7  15      ; timeval.lua:115
0023    CALL     3   1   5
0024    FNEW     3  17      ; timeval.lua:120
0025    TSETS    3   2  16  ; "__add"
0026    FNEW     3  19      ; timeval.lua:153
0027    TSETS    3   2  18  ; "now"
0028    UCLO     0 => 0029
0029 => RET1     2   2

