-- BYTECODE -- toggleswitch_spec.lua:3-6
0001    GGET     0   0      ; "require"
0002    KSTR     1   1      ; "commonrequire"
0003    CALL     0   1   2
0004    GGET     0   0      ; "require"
0005    KSTR     1   2      ; "ui/widget/toggleswitch"
0006    CALL     0   2   2
0007    USETV    0   0      ; ToggleSwitch
0008    RET0     0   1

-- BYTECODE -- toggleswitch_spec.lua:10-10
0001    RET0     0   1

-- BYTECODE -- toggleswitch_spec.lua:8-25
0001    TDUP     0   1
0002    FNEW     1   0      ; toggleswitch_spec.lua:10
0003    TSETS    1   0   2  ; "onConfigChoose"
0004    UGET     1   0      ; ToggleSwitch
0005    MOV      2   1
0006    TGETS    1   1   3  ; "new"
0007    TDUP     3   4
0008    TDUP     4   5
0009    TSETS    4   3   6  ; "toggle"
0010    TDUP     4   7
0011    TSETS    4   3   8  ; "values"
0012    TSETS    0   3   9  ; "config"
0013    CALL     1   2   3
0014    MOV      3   1
0015    TGETS    2   1  10  ; "togglePosition"
0016    KSHORT   4   1
0017    KPRI     5   2
0018    CALL     2   1   4
0019    MOV      3   1
0020    TGETS    2   1  11  ; "onTapSelect"
0021    KSHORT   4   3
0022    CALL     2   1   3
0023    RET0     0   1

-- BYTECODE -- toggleswitch_spec.lua:1-26
0001    KPRI     0   0
0002    GGET     1   0      ; "setup"
0003    FNEW     2   1      ; toggleswitch_spec.lua:3
0004    CALL     1   1   2
0005    GGET     1   2      ; "it"
0006    KSTR     2   3      ; "should toggle without args"
0007    FNEW     3   4      ; toggleswitch_spec.lua:8
0008    CALL     1   1   3
0009    UCLO     0 => 0010
0010 => RET0     0   1

-- BYTECODE -- toggleswitch_spec.lua:0-27
0001    GGET     0   0      ; "describe"
0002    KSTR     1   1      ; "ToggleSwitch module"
0003    FNEW     2   2      ; toggleswitch_spec.lua:1
0004    CALL     0   1   3
0005    RET0     0   1

