
main <./frontend/ui/widget/touchmenu.lua:0,0> (249 instructions, 996 bytes at 0x7fb23b4068d0)
0+ params, 39 slots, 0 upvalues, 34 locals, 91 constants, 23 functions
	1	[4]	GETGLOBAL	0 -1	; require
	2	[4]	LOADK    	1 -2	; "ui/bidi"
	3	[4]	CALL     	0 2 2
	4	[5]	GETGLOBAL	1 -1	; require
	5	[5]	LOADK    	2 -3	; "ffi/blitbuffer"
	6	[5]	CALL     	1 2 2
	7	[6]	GETGLOBAL	2 -1	; require
	8	[6]	LOADK    	3 -4	; "ui/widget/button"
	9	[6]	CALL     	2 2 2
	10	[7]	GETGLOBAL	3 -1	; require
	11	[7]	LOADK    	4 -5	; "ui/widget/container/centercontainer"
	12	[7]	CALL     	3 2 2
	13	[8]	GETGLOBAL	4 -1	; require
	14	[8]	LOADK    	5 -6	; "ui/widget/checkmark"
	15	[8]	CALL     	4 2 2
	16	[9]	GETGLOBAL	5 -1	; require
	17	[9]	LOADK    	6 -7	; "device"
	18	[9]	CALL     	5 2 2
	19	[10]	GETGLOBAL	6 -1	; require
	20	[10]	LOADK    	7 -8	; "ui/event"
	21	[10]	CALL     	6 2 2
	22	[11]	GETGLOBAL	7 -1	; require
	23	[11]	LOADK    	8 -9	; "ui/widget/focusmanager"
	24	[11]	CALL     	7 2 2
	25	[12]	GETGLOBAL	8 -1	; require
	26	[12]	LOADK    	9 -10	; "ui/font"
	27	[12]	CALL     	8 2 2
	28	[13]	GETGLOBAL	9 -1	; require
	29	[13]	LOADK    	10 -11	; "ui/widget/container/framecontainer"
	30	[13]	CALL     	9 2 2
	31	[14]	GETGLOBAL	10 -1	; require
	32	[14]	LOADK    	11 -12	; "ui/geometry"
	33	[14]	CALL     	10 2 2
	34	[15]	GETGLOBAL	11 -1	; require
	35	[15]	LOADK    	12 -13	; "ui/gesturerange"
	36	[15]	CALL     	11 2 2
	37	[16]	GETGLOBAL	12 -1	; require
	38	[16]	LOADK    	13 -14	; "ui/widget/horizontalgroup"
	39	[16]	CALL     	12 2 2
	40	[17]	GETGLOBAL	13 -1	; require
	41	[17]	LOADK    	14 -15	; "ui/widget/horizontalspan"
	42	[17]	CALL     	13 2 2
	43	[18]	GETGLOBAL	14 -1	; require
	44	[18]	LOADK    	15 -16	; "ui/widget/iconbutton"
	45	[18]	CALL     	14 2 2
	46	[19]	GETGLOBAL	15 -1	; require
	47	[19]	LOADK    	16 -17	; "ui/widget/infomessage"
	48	[19]	CALL     	15 2 2
	49	[20]	GETGLOBAL	16 -1	; require
	50	[20]	LOADK    	17 -18	; "ui/widget/container/inputcontainer"
	51	[20]	CALL     	16 2 2
	52	[21]	GETGLOBAL	17 -1	; require
	53	[21]	LOADK    	18 -19	; "ui/widget/container/leftcontainer"
	54	[21]	CALL     	17 2 2
	55	[22]	GETGLOBAL	18 -1	; require
	56	[22]	LOADK    	19 -20	; "ui/widget/linewidget"
	57	[22]	CALL     	18 2 2
	58	[23]	GETGLOBAL	19 -1	; require
	59	[23]	LOADK    	20 -21	; "ui/widget/container/rightcontainer"
	60	[23]	CALL     	19 2 2
	61	[24]	GETGLOBAL	20 -1	; require
	62	[24]	LOADK    	21 -22	; "ui/size"
	63	[24]	CALL     	20 2 2
	64	[25]	GETGLOBAL	21 -1	; require
	65	[25]	LOADK    	22 -23	; "ui/widget/textwidget"
	66	[25]	CALL     	21 2 2
	67	[26]	GETGLOBAL	22 -1	; require
	68	[26]	LOADK    	23 -24	; "ui/uimanager"
	69	[26]	CALL     	22 2 2
	70	[27]	GETGLOBAL	23 -1	; require
	71	[27]	LOADK    	24 -25	; "ui/widget/container/underlinecontainer"
	72	[27]	CALL     	23 2 2
	73	[28]	GETGLOBAL	24 -1	; require
	74	[28]	LOADK    	25 -26	; "ui/widget/verticalgroup"
	75	[28]	CALL     	24 2 2
	76	[29]	GETGLOBAL	25 -1	; require
	77	[29]	LOADK    	26 -27	; "ui/widget/verticalspan"
	78	[29]	CALL     	25 2 2
	79	[30]	GETGLOBAL	26 -1	; require
	80	[30]	LOADK    	27 -28	; "ui/widget/menu"
	81	[30]	CALL     	26 2 2
	82	[30]	GETTABLE 	26 26 -29	; "getMenuText"
	83	[31]	GETGLOBAL	27 -1	; require
	84	[31]	LOADK    	28 -30	; "gettext"
	85	[31]	CALL     	27 2 2
	86	[32]	GETGLOBAL	28 -1	; require
	87	[32]	LOADK    	29 -31	; "ffi/util"
	88	[32]	CALL     	28 2 2
	89	[32]	GETTABLE 	28 28 -32	; "template"
	90	[33]	GETTABLE 	29 5 -33	; "input"
	91	[34]	GETTABLE 	30 5 -34	; "screen"
	92	[39]	SELF     	31 16 -35	; "new"
	93	[39]	NEWTABLE 	33 0 6
	94	[40]	SETTABLE 	33 -36 -37	; "menu" nil
	95	[41]	SETTABLE 	33 -38 -39	; "vertical_align" "center"
	96	[42]	SETTABLE 	33 -40 -37	; "item" nil
	97	[43]	SETTABLE 	33 -41 -37	; "dimen" nil
	98	[44]	SELF     	34 8 -43	; "getFace"
	99	[44]	LOADK    	36 -44	; "smallinfofont"
	100	[44]	CALL     	34 3 2
	101	[44]	SETTABLE 	33 -42 34	; "face" -
	102	[45]	SETTABLE 	33 -45 -37	; "show_parent" nil
	103	[39]	CALL     	31 3 2
	104	[119]	CLOSURE  	32 0	; 0x7fb23b407070
	105	[119]	MOVE     	0 11
	106	[119]	MOVE     	0 4
	107	[119]	MOVE     	0 20
	108	[119]	MOVE     	0 26
	109	[119]	MOVE     	0 9
	110	[119]	MOVE     	0 1
	111	[119]	MOVE     	0 12
	112	[119]	MOVE     	0 3
	113	[119]	MOVE     	0 10
	114	[119]	MOVE     	0 21
	115	[119]	MOVE     	0 23
	116	[48]	SETTABLE 	31 -46 32	; "init" -
	117	[124]	CLOSURE  	32 1	; 0x7fb23b408610
	118	[124]	MOVE     	0 1
	119	[121]	SETTABLE 	31 -47 32	; "onFocus" -
	120	[129]	CLOSURE  	32 2	; 0x7fb23b408760
	121	[129]	MOVE     	0 1
	122	[126]	SETTABLE 	31 -48 32	; "onUnfocus" -
	123	[163]	CLOSURE  	32 3	; 0x7fb23b408c10
	124	[163]	MOVE     	0 22
	125	[131]	SETTABLE 	31 -49 32	; "onTapSelect" -
	126	[193]	CLOSURE  	32 4	; 0x7fb23b409bd0
	127	[193]	MOVE     	0 22
	128	[165]	SETTABLE 	31 -50 32	; "onHoldSelect" -
	129	[198]	SELF     	32 16 -35	; "new"
	130	[198]	NEWTABLE 	34 0 4
	131	[199]	SELF     	35 30 -52	; "getWidth"
	132	[199]	CALL     	35 2 2
	133	[199]	SETTABLE 	34 -51 35	; "width" -
	134	[200]	NEWTABLE 	35 0 0
	135	[200]	SETTABLE 	34 -53 35	; "icons" -
	136	[202]	SETTABLE 	34 -45 -37	; "show_parent" nil
	137	[203]	SETTABLE 	34 -36 -37	; "menu" nil
	138	[198]	CALL     	32 3 2
	139	[356]	CLOSURE  	33 5	; 0x7fb23b407450
	140	[356]	MOVE     	0 20
	141	[356]	MOVE     	0 30
	142	[356]	MOVE     	0 12
	143	[356]	MOVE     	0 14
	144	[356]	MOVE     	0 0
	145	[356]	MOVE     	0 18
	146	[356]	MOVE     	0 10
	147	[356]	MOVE     	0 13
	148	[356]	MOVE     	0 9
	149	[356]	MOVE     	0 24
	150	[206]	SETTABLE 	32 -46 33	; "init" -
	151	[365]	CLOSURE  	33 6	; 0x7fb23b408b80
	152	[358]	SETTABLE 	32 -54 33	; "switchToTab" -
	153	[370]	SELF     	33 7 -35	; "new"
	154	[370]	NEWTABLE 	35 0 15
	155	[371]	NEWTABLE 	36 0 0
	156	[371]	SETTABLE 	35 -55 36	; "tab_item_table" -
	157	[373]	SETTABLE 	35 -56 -37	; "item_table_stack" nil
	158	[374]	SETTABLE 	35 -57 -37	; "item_table" nil
	159	[375]	GETTABLE 	36 20 -40	; "item"
	160	[375]	GETTABLE 	36 36 -59	; "height_large"
	161	[375]	SETTABLE 	35 -58 36	; "item_height" -
	162	[376]	GETTABLE 	36 20 -61	; "border"
	163	[376]	GETTABLE 	36 36 -62	; "window"
	164	[376]	SETTABLE 	35 -60 36	; "bordersize" -
	165	[377]	GETTABLE 	36 20 -63	; "padding"
	166	[377]	GETTABLE 	36 36 -64	; "default"
	167	[377]	SETTABLE 	35 -63 36	; "padding" -
	168	[378]	SELF     	36 8 -43	; "getFace"
	169	[378]	LOADK    	38 -66	; "ffont"
	170	[378]	CALL     	36 3 2
	171	[378]	SETTABLE 	35 -65 36	; "fface" -
	172	[379]	SETTABLE 	35 -51 -37	; "width" nil
	173	[380]	SETTABLE 	35 -67 -37	; "height" nil
	174	[381]	SETTABLE 	35 -68 -69	; "page" 1
	175	[382]	SETTABLE 	35 -70 -71	; "max_per_page_default" 10
	176	[384]	SETTABLE 	35 -45 -37	; "show_parent" nil
	177	[385]	SETTABLE 	35 -72 -73	; "cur_tab" -1
	178	[386]	SETTABLE 	35 -74 -37	; "close_callback" nil
	179	[387]	SETTABLE 	35 -75 -76	; "is_fresh" true
	180	[370]	CALL     	33 3 2
	181	[537]	CLOSURE  	34 7	; 0x7fb23b408ef0
	182	[537]	MOVE     	0 10
	183	[537]	MOVE     	0 22
	184	[537]	MOVE     	0 11
	185	[537]	MOVE     	0 30
	186	[537]	MOVE     	0 29
	187	[537]	MOVE     	0 32
	188	[537]	MOVE     	0 24
	189	[537]	MOVE     	0 0
	190	[537]	MOVE     	0 2
	191	[537]	MOVE     	0 21
	192	[537]	MOVE     	0 12
	193	[537]	MOVE     	0 13
	194	[537]	MOVE     	0 20
	195	[537]	MOVE     	0 14
	196	[537]	MOVE     	0 17
	197	[537]	MOVE     	0 3
	198	[537]	MOVE     	0 19
	199	[537]	MOVE     	0 9
	200	[537]	MOVE     	0 1
	201	[537]	MOVE     	0 18
	202	[537]	MOVE     	0 25
	203	[390]	SETTABLE 	33 -46 34	; "init" -
	204	[542]	CLOSURE  	34 8	; 0x7fb23b40b630
	205	[542]	MOVE     	0 22
	206	[539]	SETTABLE 	33 -77 34	; "onCloseWidget" -
	207	[569]	CLOSURE  	34 9	; 0x7fb23b40c9b0
	208	[569]	MOVE     	0 30
	209	[544]	SETTABLE 	33 -78 34	; "_recalculatePageLayout" -
	210	[691]	CLOSURE  	34 10	; 0x7fb23b40cc50
	211	[691]	MOVE     	0 31
	212	[691]	MOVE     	0 10
	213	[691]	MOVE     	0 28
	214	[691]	MOVE     	0 27
	215	[691]	MOVE     	0 5
	216	[691]	MOVE     	0 0
	217	[691]	MOVE     	0 22
	218	[571]	SETTABLE 	33 -79 34	; "updateItems" -
	219	[712]	CLOSURE  	34 11	; 0x7fb23b40c880
	220	[693]	SETTABLE 	33 -80 34	; "switchMenuTab" -
	221	[722]	CLOSURE  	34 12	; 0x7fb23b40d550
	222	[714]	SETTABLE 	33 -81 34	; "backToUpperMenu" -
	223	[726]	CLOSURE  	34 13	; 0x7fb23b40db30
	224	[724]	SETTABLE 	33 -82 34	; "closeMenu" -
	225	[736]	CLOSURE  	34 14	; 0x7fb23b40e160
	226	[728]	SETTABLE 	33 -83 34	; "onNextPage" -
	227	[746]	CLOSURE  	34 15	; 0x7fb23b40e3c0
	228	[738]	SETTABLE 	33 -84 34	; "onPrevPage" -
	229	[757]	CLOSURE  	34 16	; 0x7fb23b40e8c0
	230	[757]	MOVE     	0 0
	231	[748]	SETTABLE 	33 -85 34	; "onSwipe" -
	232	[807]	CLOSURE  	34 17	; 0x7fb23b40c780
	233	[807]	MOVE     	0 22
	234	[759]	SETTABLE 	33 -86 34	; "onMenuSelect" -
	235	[850]	CLOSURE  	34 18	; 0x7fb23b40f460
	236	[850]	MOVE     	0 22
	237	[850]	MOVE     	0 15
	238	[809]	SETTABLE 	33 -87 34	; "onMenuHold" -
	239	[856]	CLOSURE  	34 19	; 0x7fb23b40fed0
	240	[852]	SETTABLE 	33 -88 34	; "onTapCloseAllMenus" -
	241	[860]	CLOSURE  	34 20	; 0x7fb23b410a40
	242	[858]	SETTABLE 	33 -89 34	; "onClose" -
	243	[864]	CLOSURE  	34 21	; 0x7fb23b410f50
	244	[862]	SETTABLE 	33 -90 34	; "onBack" -
	245	[868]	CLOSURE  	34 22	; 0x7fb23b4110f0
	246	[868]	MOVE     	0 6
	247	[866]	SETTABLE 	33 -91 34	; "onPress" -
	248	[870]	RETURN   	33 2
	249	[870]	RETURN   	0 1

function <./frontend/ui/widget/touchmenu.lua:48,119> (139 instructions, 556 bytes at 0x7fb23b407070)
1 param, 22 slots, 11 upvalues, 8 locals, 42 constants, 1 function
	1	[49]	NEWTABLE 	1 0 2
	2	[50]	NEWTABLE 	2 1 1
	3	[51]	GETUPVAL 	3 0	; GestureRange
	4	[51]	SELF     	3 3 -3	; "new"
	5	[51]	NEWTABLE 	5 0 2
	6	[52]	SETTABLE 	5 -4 -5	; "ges" "tap"
	7	[53]	GETTABLE 	6 0 -7	; "dimen"
	8	[53]	SETTABLE 	5 -6 6	; "range" -
	9	[51]	CALL     	3 3 2
	10	[55]	SETTABLE 	2 -8 -9	; "doc" "Select Menu Item"
	11	[56]	SETLIST  	2 1 1	; 1
	12	[56]	SETTABLE 	1 -2 2	; "TapSelect" -
	13	[57]	NEWTABLE 	2 1 1
	14	[58]	GETUPVAL 	3 0	; GestureRange
	15	[58]	SELF     	3 3 -3	; "new"
	16	[58]	NEWTABLE 	5 0 2
	17	[59]	SETTABLE 	5 -4 -11	; "ges" "hold"
	18	[60]	GETTABLE 	6 0 -7	; "dimen"
	19	[60]	SETTABLE 	5 -6 6	; "range" -
	20	[58]	CALL     	3 3 2
	21	[62]	SETTABLE 	2 -8 -12	; "doc" "Hold Menu Item"
	22	[63]	SETLIST  	2 1 1	; 1
	23	[63]	SETTABLE 	1 -10 2	; "HoldSelect" -
	24	[64]	SETTABLE 	0 -1 1	; "ges_events" -
	25	[66]	GETTABLE 	1 0 -13	; "item"
	26	[66]	GETTABLE 	1 1 -14	; "enabled"
	27	[67]	GETTABLE 	2 0 -13	; "item"
	28	[67]	GETTABLE 	2 2 -15	; "enabled_func"
	29	[67]	TEST     	2 0 0
	30	[67]	JMP      	4	; to 35
	31	[68]	GETTABLE 	2 0 -13	; "item"
	32	[68]	GETTABLE 	2 2 -15	; "enabled_func"
	33	[68]	CALL     	2 1 2
	34	[68]	MOVE     	1 2
	35	[70]	LOADBOOL 	2 0 0
	36	[71]	GETTABLE 	3 0 -13	; "item"
	37	[71]	GETTABLE 	3 3 -16	; "checked"
	38	[72]	GETTABLE 	4 0 -13	; "item"
	39	[72]	GETTABLE 	4 4 -17	; "checked_func"
	40	[72]	TEST     	4 0 0
	41	[72]	JMP      	5	; to 47
	42	[73]	LOADBOOL 	2 1 0
	43	[74]	GETTABLE 	4 0 -13	; "item"
	44	[74]	GETTABLE 	4 4 -17	; "checked_func"
	45	[74]	CALL     	4 1 2
	46	[74]	MOVE     	3 4
	47	[76]	GETUPVAL 	4 1	; CheckMark
	48	[76]	SELF     	4 4 -3	; "new"
	49	[76]	NEWTABLE 	6 0 3
	50	[77]	SETTABLE 	6 -18 2	; "checkable" -
	51	[78]	SETTABLE 	6 -16 3	; "checked" -
	52	[79]	SETTABLE 	6 -14 1	; "enabled" -
	53	[76]	CALL     	4 3 2
	54	[82]	GETUPVAL 	5 1	; CheckMark
	55	[82]	SELF     	5 5 -3	; "new"
	56	[82]	NEWTABLE 	7 0 1
	57	[83]	SETTABLE 	7 -16 -19	; "checked" true
	58	[82]	CALL     	5 3 2
	59	[88]	GETTABLE 	6 0 -7	; "dimen"
	60	[88]	GETTABLE 	6 6 -20	; "w"
	61	[88]	GETUPVAL 	7 2	; Size
	62	[88]	GETTABLE 	7 7 -21	; "padding"
	63	[88]	GETTABLE 	7 7 -22	; "default"
	64	[88]	MUL      	7 -23 7	; 2 -
	65	[88]	SUB      	6 6 7
	66	[88]	SELF     	7 5 -24	; "getSize"
	67	[88]	CALL     	7 2 2
	68	[88]	GETTABLE 	7 7 -20	; "w"
	69	[88]	SUB      	6 6 7
	70	[89]	GETUPVAL 	7 3	; getMenuText
	71	[89]	GETTABLE 	8 0 -13	; "item"
	72	[89]	CALL     	7 2 2
	73	[90]	GETUPVAL 	8 4	; FrameContainer
	74	[90]	SELF     	8 8 -3	; "new"
	75	[90]	NEWTABLE 	10 0 3
	76	[91]	GETTABLE 	11 0 -7	; "dimen"
	77	[91]	GETTABLE 	11 11 -20	; "w"
	78	[91]	SETTABLE 	10 -26 11	; "width" -
	79	[92]	SETTABLE 	10 -27 -28	; "bordersize" 0
	80	[93]	GETUPVAL 	11 5	; Blitbuffer
	81	[93]	GETTABLE 	11 11 -30	; "COLOR_BLACK"
	82	[93]	SETTABLE 	10 -29 11	; "color" -
	83	[94]	GETUPVAL 	11 6	; HorizontalGroup
	84	[94]	SELF     	11 11 -3	; "new"
	85	[94]	NEWTABLE 	13 1 1
	86	[95]	SETTABLE 	13 -31 -32	; "align" "center"
	87	[96]	GETUPVAL 	14 7	; CenterContainer
	88	[96]	SELF     	14 14 -3	; "new"
	89	[96]	NEWTABLE 	16 1 1
	90	[97]	GETUPVAL 	17 8	; Geom
	91	[97]	SELF     	17 17 -3	; "new"
	92	[97]	NEWTABLE 	19 0 1
	93	[97]	SELF     	20 5 -24	; "getSize"
	94	[97]	CALL     	20 2 2
	95	[97]	GETTABLE 	20 20 -20	; "w"
	96	[97]	SETTABLE 	19 -20 20	; "w" -
	97	[97]	CALL     	17 3 2
	98	[97]	SETTABLE 	16 -7 17	; "dimen" -
	99	[99]	MOVE     	17 4
	100	[99]	SETLIST  	16 1 1	; 1
	101	[96]	CALL     	14 3 2
	102	[100]	GETUPVAL 	15 9	; TextWidget
	103	[100]	SELF     	15 15 -3	; "new"
	104	[100]	NEWTABLE 	17 0 4
	105	[101]	SETTABLE 	17 -33 7	; "text" -
	106	[102]	SETTABLE 	17 -34 6	; "max_width" -
	107	[103]	EQ       	1 1 -36	; - false
	108	[103]	JMP      	4	; to 113
	109	[103]	GETUPVAL 	18 5	; Blitbuffer
	110	[103]	GETTABLE 	18 18 -30	; "COLOR_BLACK"
	111	[103]	TEST     	18 0 1
	112	[103]	JMP      	2	; to 115
	113	[103]	GETUPVAL 	18 5	; Blitbuffer
	114	[103]	GETTABLE 	18 18 -37	; "COLOR_DARK_GRAY"
	115	[103]	SETTABLE 	17 -35 18	; "fgcolor" -
	116	[104]	GETTABLE 	18 0 -38	; "face"
	117	[104]	SETTABLE 	17 -38 18	; "face" -
	118	[100]	CALL     	15 3 0
	119	[106]	SETLIST  	13 0 1	; 1
	120	[94]	CALL     	11 3 0
	121	[107]	SETLIST  	10 0 1	; 1
	122	[90]	CALL     	8 3 2
	123	[107]	SETTABLE 	0 -25 8	; "item_frame" -
	124	[109]	GETUPVAL 	8 10	; UnderlineContainer
	125	[109]	SELF     	8 8 -3	; "new"
	126	[109]	NEWTABLE 	10 1 2
	127	[110]	SETTABLE 	10 -40 -32	; "vertical_align" "center"
	128	[111]	GETTABLE 	11 0 -7	; "dimen"
	129	[111]	SETTABLE 	10 -7 11	; "dimen" -
	130	[113]	GETTABLE 	11 0 -25	; "item_frame"
	131	[113]	SETLIST  	10 1 1	; 1
	132	[109]	CALL     	8 3 2
	133	[113]	SETTABLE 	0 -39 8	; "_underline_container" -
	134	[115]	GETTABLE 	8 0 -39	; "_underline_container"
	135	[115]	SETTABLE 	0 -41 8	; 1 -
	136	[118]	CLOSURE  	8 0	; 0x7fb23b4082b0
	137	[118]	MOVE     	0 1
	138	[116]	SETTABLE 	0 -42 8	; "isEnabled" -
	139	[119]	RETURN   	0 1

function <./frontend/ui/widget/touchmenu.lua:116,118> (9 instructions, 36 bytes at 0x7fb23b4082b0)
1 param, 2 slots, 1 upvalue, 1 local, 1 constant, 0 functions
	1	[117]	GETUPVAL 	1 0	; item_enabled
	2	[117]	EQ       	1 1 -1	; - false
	3	[117]	JMP      	2	; to 6
	4	[117]	LOADBOOL 	1 1 0
	5	[117]	JMP      	2	; to 8
	6	[117]	LOADBOOL 	1 0 1
	7	[117]	LOADBOOL 	1 1 0
	8	[117]	RETURN   	1 2
	9	[118]	RETURN   	0 1

function <./frontend/ui/widget/touchmenu.lua:121,124> (7 instructions, 28 bytes at 0x7fb23b408610)
1 param, 3 slots, 1 upvalue, 1 local, 3 constants, 0 functions
	1	[122]	GETTABLE 	1 0 -1	; "_underline_container"
	2	[122]	GETUPVAL 	2 0	; Blitbuffer
	3	[122]	GETTABLE 	2 2 -3	; "COLOR_BLACK"
	4	[122]	SETTABLE 	1 -2 2	; "color" -
	5	[123]	LOADBOOL 	1 1 0
	6	[123]	RETURN   	1 2
	7	[124]	RETURN   	0 1

function <./frontend/ui/widget/touchmenu.lua:126,129> (7 instructions, 28 bytes at 0x7fb23b408760)
1 param, 3 slots, 1 upvalue, 1 local, 3 constants, 0 functions
	1	[127]	GETTABLE 	1 0 -1	; "_underline_container"
	2	[127]	GETUPVAL 	2 0	; Blitbuffer
	3	[127]	GETTABLE 	2 2 -3	; "COLOR_WHITE"
	4	[127]	SETTABLE 	1 -2 2	; "color" -
	5	[128]	LOADBOOL 	1 1 0
	6	[128]	RETURN   	1 2
	7	[129]	RETURN   	0 1

function <./frontend/ui/widget/touchmenu.lua:131,163> (51 instructions, 204 bytes at 0x7fb23b408c10)
3 params, 9 slots, 1 upvalue, 4 locals, 19 constants, 2 functions
	1	[132]	GETTABLE 	3 0 -1	; "item"
	2	[132]	GETTABLE 	3 3 -2	; "enabled"
	3	[133]	GETTABLE 	4 0 -1	; "item"
	4	[133]	GETTABLE 	4 4 -3	; "enabled_func"
	5	[133]	TEST     	4 0 0
	6	[133]	JMP      	4	; to 11
	7	[134]	GETTABLE 	4 0 -1	; "item"
	8	[134]	GETTABLE 	4 4 -3	; "enabled_func"
	9	[134]	CALL     	4 1 2
	10	[134]	MOVE     	3 4
	11	[136]	EQ       	0 3 -4	; - false
	12	[136]	JMP      	1	; to 14
	13	[136]	RETURN   	0 1
	14	[138]	GETGLOBAL	4 -5	; G_reader_settings
	15	[138]	SELF     	4 4 -6	; "isFalse"
	16	[138]	LOADK    	6 -7	; "flash_ui"
	17	[138]	CALL     	4 3 2
	18	[138]	TEST     	4 0 0
	19	[138]	JMP      	5	; to 25
	20	[139]	GETTABLE 	4 0 -8	; "menu"
	21	[139]	SELF     	4 4 -9	; "onMenuSelect"
	22	[139]	GETTABLE 	6 0 -1	; "item"
	23	[139]	CALL     	4 3 1
	24	[139]	JMP      	24	; to 49
	25	[141]	GETTABLE 	4 0 -10	; "item_frame"
	26	[141]	SETTABLE 	4 -11 -12	; "invert" true
	27	[142]	GETUPVAL 	4 0	; UIManager
	28	[142]	SELF     	4 4 -13	; "widgetRepaint"
	29	[142]	GETTABLE 	6 0 -14	; 1
	30	[142]	GETTABLE 	7 0 -14	; 1
	31	[142]	GETTABLE 	7 7 -15	; "dimen"
	32	[142]	GETTABLE 	7 7 -16	; "x"
	33	[142]	GETTABLE 	8 0 -14	; 1
	34	[142]	GETTABLE 	8 8 -15	; "dimen"
	35	[142]	GETTABLE 	8 8 -17	; "y"
	36	[142]	CALL     	4 5 1
	37	[143]	GETUPVAL 	4 0	; UIManager
	38	[143]	SELF     	4 4 -18	; "setDirty"
	39	[143]	LOADNIL  	6 6
	40	[145]	CLOSURE  	7 0	; 0x7fb23b409120
	41	[145]	MOVE     	0 0
	42	[143]	CALL     	4 4 1
	43	[147]	GETUPVAL 	4 0	; UIManager
	44	[147]	SELF     	4 4 -19	; "tickAfterNext"
	45	[160]	CLOSURE  	6 1	; 0x7fb23b409210
	46	[160]	MOVE     	0 0
	47	[160]	GETUPVAL 	0 0	; UIManager
	48	[147]	CALL     	4 3 1
	49	[162]	LOADBOOL 	4 1 0
	50	[162]	RETURN   	4 2
	51	[163]	RETURN   	0 1

function <./frontend/ui/widget/touchmenu.lua:143,145> (5 instructions, 20 bytes at 0x7fb23b409120)
0 params, 2 slots, 1 upvalue, 0 locals, 2 constants, 0 functions
	1	[144]	LOADK    	0 -1	; "fast"
	2	[144]	GETUPVAL 	1 0	; self
	3	[144]	GETTABLE 	1 1 -2	; "dimen"
	4	[144]	RETURN   	0 3
	5	[145]	RETURN   	0 1

function <./frontend/ui/widget/touchmenu.lua:147,160> (27 instructions, 108 bytes at 0x7fb23b409210)
0 params, 4 slots, 2 upvalues, 0 locals, 10 constants, 1 function
	1	[148]	GETUPVAL 	0 0	; self
	2	[148]	GETTABLE 	0 0 -1	; "menu"
	3	[148]	SELF     	0 0 -2	; "onMenuSelect"
	4	[148]	GETUPVAL 	2 0	; self
	5	[148]	GETTABLE 	2 2 -3	; "item"
	6	[148]	CALL     	0 3 1
	7	[149]	GETUPVAL 	0 0	; self
	8	[149]	GETTABLE 	0 0 -4	; "item_frame"
	9	[149]	SETTABLE 	0 -5 -6	; "invert" false
	10	[154]	GETUPVAL 	0 0	; self
	11	[154]	GETTABLE 	0 0 -3	; "item"
	12	[154]	GETTABLE 	0 0 -7	; "hold_keep_menu_open"
	13	[154]	TEST     	0 0 1
	14	[154]	JMP      	5	; to 20
	15	[154]	GETUPVAL 	0 0	; self
	16	[154]	GETTABLE 	0 0 -3	; "item"
	17	[154]	GETTABLE 	0 0 -8	; "keep_menu_open"
	18	[154]	TEST     	0 0 0
	19	[154]	JMP      	7	; to 27
	20	[156]	GETUPVAL 	0 1	; UIManager
	21	[156]	SELF     	0 0 -9	; "setDirty"
	22	[156]	GETUPVAL 	2 0	; self
	23	[156]	GETTABLE 	2 2 -10	; "show_parent"
	24	[158]	CLOSURE  	3 0	; 0x7fb23b409960
	25	[158]	GETUPVAL 	0 0	; self
	26	[156]	CALL     	0 4 1
	27	[160]	RETURN   	0 1

function <./frontend/ui/widget/touchmenu.lua:156,158> (5 instructions, 20 bytes at 0x7fb23b409960)
0 params, 2 slots, 1 upvalue, 0 locals, 2 constants, 0 functions
	1	[157]	LOADK    	0 -1	; "ui"
	2	[157]	GETUPVAL 	1 0	; self
	3	[157]	GETTABLE 	1 1 -2	; "dimen"
	4	[157]	RETURN   	0 3
	5	[158]	RETURN   	0 1

function <./frontend/ui/widget/touchmenu.lua:165,193> (57 instructions, 228 bytes at 0x7fb23b409bd0)
3 params, 9 slots, 1 upvalue, 4 locals, 21 constants, 3 functions
	1	[166]	GETTABLE 	3 0 -1	; "item"
	2	[166]	GETTABLE 	3 3 -2	; "enabled"
	3	[167]	GETTABLE 	4 0 -1	; "item"
	4	[167]	GETTABLE 	4 4 -3	; "enabled_func"
	5	[167]	TEST     	4 0 0
	6	[167]	JMP      	4	; to 11
	7	[168]	GETTABLE 	4 0 -1	; "item"
	8	[168]	GETTABLE 	4 4 -3	; "enabled_func"
	9	[168]	CALL     	4 1 2
	10	[168]	MOVE     	3 4
	11	[170]	EQ       	0 3 -4	; - false
	12	[170]	JMP      	1	; to 14
	13	[170]	RETURN   	0 1
	14	[172]	GETGLOBAL	4 -5	; G_reader_settings
	15	[172]	SELF     	4 4 -6	; "isFalse"
	16	[172]	LOADK    	6 -7	; "flash_ui"
	17	[172]	CALL     	4 3 2
	18	[172]	TEST     	4 0 0
	19	[172]	JMP      	5	; to 25
	20	[173]	GETTABLE 	4 0 -8	; "menu"
	21	[173]	SELF     	4 4 -9	; "onMenuHold"
	22	[173]	GETTABLE 	6 0 -1	; "item"
	23	[173]	CALL     	4 3 1
	24	[173]	JMP      	30	; to 55
	25	[175]	GETTABLE 	4 0 -10	; "item_frame"
	26	[175]	SETTABLE 	4 -11 -12	; "invert" true
	27	[176]	GETUPVAL 	4 0	; UIManager
	28	[176]	SELF     	4 4 -13	; "widgetRepaint"
	29	[176]	GETTABLE 	6 0 -14	; 1
	30	[176]	GETTABLE 	7 0 -14	; 1
	31	[176]	GETTABLE 	7 7 -15	; "dimen"
	32	[176]	GETTABLE 	7 7 -16	; "x"
	33	[176]	GETTABLE 	8 0 -14	; 1
	34	[176]	GETTABLE 	8 8 -15	; "dimen"
	35	[176]	GETTABLE 	8 8 -17	; "y"
	36	[176]	CALL     	4 5 1
	37	[177]	GETUPVAL 	4 0	; UIManager
	38	[177]	SELF     	4 4 -18	; "setDirty"
	39	[177]	LOADNIL  	6 6
	40	[179]	CLOSURE  	7 0	; 0x7fb23b40a100
	41	[179]	MOVE     	0 0
	42	[177]	CALL     	4 4 1
	43	[180]	GETUPVAL 	4 0	; UIManager
	44	[180]	SELF     	4 4 -19	; "tickAfterNext"
	45	[182]	CLOSURE  	6 1	; 0x7fb23b40a180
	46	[182]	MOVE     	0 0
	47	[180]	CALL     	4 3 1
	48	[183]	GETUPVAL 	4 0	; UIManager
	49	[183]	SELF     	4 4 -20	; "scheduleIn"
	50	[183]	LOADK    	6 -21	; 0.5
	51	[190]	CLOSURE  	7 2	; 0x7fb23b40a080
	52	[190]	MOVE     	0 0
	53	[190]	GETUPVAL 	0 0	; UIManager
	54	[183]	CALL     	4 4 1
	55	[192]	LOADBOOL 	4 1 0
	56	[192]	RETURN   	4 2
	57	[193]	RETURN   	0 1

function <./frontend/ui/widget/touchmenu.lua:177,179> (5 instructions, 20 bytes at 0x7fb23b40a100)
0 params, 2 slots, 1 upvalue, 0 locals, 2 constants, 0 functions
	1	[178]	LOADK    	0 -1	; "fast"
	2	[178]	GETUPVAL 	1 0	; self
	3	[178]	GETTABLE 	1 1 -2	; "dimen"
	4	[178]	RETURN   	0 3
	5	[179]	RETURN   	0 1

function <./frontend/ui/widget/touchmenu.lua:180,182> (7 instructions, 28 bytes at 0x7fb23b40a180)
0 params, 3 slots, 1 upvalue, 0 locals, 3 constants, 0 functions
	1	[181]	GETUPVAL 	0 0	; self
	2	[181]	GETTABLE 	0 0 -1	; "menu"
	3	[181]	SELF     	0 0 -2	; "onMenuHold"
	4	[181]	GETUPVAL 	2 0	; self
	5	[181]	GETTABLE 	2 2 -3	; "item"
	6	[181]	CALL     	0 3 1
	7	[182]	RETURN   	0 1

function <./frontend/ui/widget/touchmenu.lua:183,190> (11 instructions, 44 bytes at 0x7fb23b40a080)
0 params, 4 slots, 2 upvalues, 0 locals, 5 constants, 1 function
	1	[184]	GETUPVAL 	0 0	; self
	2	[184]	GETTABLE 	0 0 -1	; "item_frame"
	3	[184]	SETTABLE 	0 -2 -3	; "invert" false
	4	[187]	GETUPVAL 	0 1	; UIManager
	5	[187]	SELF     	0 0 -4	; "setDirty"
	6	[187]	GETUPVAL 	2 0	; self
	7	[187]	GETTABLE 	2 2 -5	; "show_parent"
	8	[189]	CLOSURE  	3 0	; 0x7fb23b40ab10
	9	[189]	GETUPVAL 	0 0	; self
	10	[187]	CALL     	0 4 1
	11	[190]	RETURN   	0 1

function <./frontend/ui/widget/touchmenu.lua:187,189> (5 instructions, 20 bytes at 0x7fb23b40ab10)
0 params, 2 slots, 1 upvalue, 0 locals, 2 constants, 0 functions
	1	[188]	LOADK    	0 -1	; "ui"
	2	[188]	GETUPVAL 	1 0	; self
	3	[188]	GETTABLE 	1 1 -2	; "dimen"
	4	[188]	RETURN   	0 3
	5	[189]	RETURN   	0 1

function <./frontend/ui/widget/touchmenu.lua:206,356> (246 instructions, 984 bytes at 0x7fb23b407450)
1 param, 27 slots, 10 upvalues, 21 locals, 49 constants, 1 function
	1	[207]	GETUPVAL 	1 0	; Size
	2	[207]	GETTABLE 	1 1 -1	; "span"
	3	[207]	GETTABLE 	1 1 -2	; "vertical_default"
	4	[208]	GETTABLE 	2 0 -3	; "icons"
	5	[208]	LEN      	2 2
	6	[208]	ADD      	2 2 -4	; - 1
	7	[208]	MUL      	2 1 2
	8	[210]	GETUPVAL 	3 1	; Screen
	9	[210]	SELF     	3 3 -5	; "scaleBySize"
	10	[210]	LOADK    	5 -6	; 40
	11	[210]	CALL     	3 3 2
	12	[211]	MOVE     	4 3
	13	[213]	GETTABLE 	5 0 -3	; "icons"
	14	[213]	LEN      	5 5
	15	[213]	MUL      	5 3 5
	16	[213]	ADD      	5 5 2
	17	[214]	GETTABLE 	6 0 -7	; "width"
	18	[214]	SUB      	6 6 5
	19	[214]	GETTABLE 	7 0 -3	; "icons"
	20	[214]	LEN      	7 7
	21	[214]	MUL      	7 7 -8	; - 2
	22	[214]	DIV      	6 6 7
	23	[215]	GETGLOBAL	7 -9	; math
	24	[215]	GETTABLE 	7 7 -10	; "min"
	25	[215]	MOVE     	8 6
	26	[215]	GETUPVAL 	9 1	; Screen
	27	[215]	SELF     	9 9 -5	; "scaleBySize"
	28	[215]	LOADK    	11 -11	; 16
	29	[215]	CALL     	9 3 0
	30	[215]	CALL     	7 0 2
	31	[216]	GETUPVAL 	8 0	; Size
	32	[216]	GETTABLE 	8 8 -1	; "span"
	33	[216]	GETTABLE 	8 8 -13	; "vertical_large"
	34	[216]	ADD      	8 4 8
	35	[216]	SETTABLE 	0 -12 8	; "height" -
	36	[217]	GETTABLE 	8 0 -14	; "show_parent"
	37	[217]	TEST     	8 0 1
	38	[217]	JMP      	1	; to 40
	39	[217]	MOVE     	8 0
	40	[217]	SETTABLE 	0 -14 8	; "show_parent" -
	41	[218]	GETUPVAL 	8 2	; HorizontalGroup
	42	[218]	SELF     	8 8 -16	; "new"
	43	[218]	NEWTABLE 	10 0 0
	44	[218]	CALL     	8 3 2
	45	[218]	SETTABLE 	0 -15 8	; "bar_icon_group" -
	46	[220]	NEWTABLE 	8 0 0
	47	[220]	SETTABLE 	0 -17 8	; "icon_widgets" -
	48	[222]	NEWTABLE 	8 0 0
	49	[222]	SETTABLE 	0 -18 8	; "icon_seps" -
	50	[225]	UNM      	8 1
	51	[226]	MOVE     	9 8
	52	[230]	GETTABLE 	10 0 -7	; "width"
	53	[230]	SUB      	10 10 5
	54	[230]	MUL      	11 -8 7	; 2 -
	55	[230]	GETTABLE 	12 0 -3	; "icons"
	56	[230]	LEN      	12 12
	57	[230]	MUL      	11 11 12
	58	[230]	SUB      	10 10 11
	59	[230]	ADD      	10 10 1
	60	[232]	GETGLOBAL	11 -19	; ipairs
	61	[232]	GETTABLE 	12 0 -3	; "icons"
	62	[232]	CALL     	11 2 4
	63	[232]	JMP      	155	; to 219
	64	[233]	GETUPVAL 	16 3	; IconButton
	65	[233]	SELF     	16 16 -16	; "new"
	66	[233]	NEWTABLE 	18 0 9
	67	[234]	GETTABLE 	19 0 -14	; "show_parent"
	68	[234]	SETTABLE 	18 -14 19	; "show_parent" -
	69	[235]	SETTABLE 	18 -20 15	; "icon_file" -
	70	[236]	SETTABLE 	18 -7 3	; "width" -
	71	[237]	SETTABLE 	18 -12 4	; "height" -
	72	[238]	SETTABLE 	18 -21 -22	; "scale_for_dpi" false
	73	[239]	SETTABLE 	18 -23 -24	; "callback" nil
	74	[240]	SETTABLE 	18 -25 7	; "padding_left" -
	75	[241]	SETTABLE 	18 -26 7	; "padding_right" -
	76	[242]	GETTABLE 	19 0 -27	; "menu"
	77	[242]	SETTABLE 	18 -27 19	; "menu" -
	78	[233]	CALL     	16 3 2
	79	[245]	GETGLOBAL	17 -28	; table
	80	[245]	GETTABLE 	17 17 -29	; "insert"
	81	[245]	GETTABLE 	18 0 -17	; "icon_widgets"
	82	[245]	MOVE     	19 16
	83	[245]	CALL     	17 3 1
	84	[246]	GETGLOBAL	17 -28	; table
	85	[246]	GETTABLE 	17 17 -29	; "insert"
	86	[246]	GETTABLE 	18 0 -27	; "menu"
	87	[246]	GETTABLE 	18 18 -30	; "layout"
	88	[246]	MOVE     	19 16
	89	[246]	CALL     	17 3 1
	90	[249]	ADD      	17 9 1
	91	[250]	GETTABLE 	18 0 -17	; "icon_widgets"
	92	[250]	GETTABLE 	18 18 14
	93	[250]	SELF     	18 18 -31	; "getSize"
	94	[250]	CALL     	18 2 2
	95	[250]	GETTABLE 	18 18 -32	; "w"
	96	[250]	ADD      	18 17 18
	97	[251]	MOVE     	9 18
	98	[253]	GETUPVAL 	19 4	; BD
	99	[253]	GETTABLE 	19 19 -33	; "mirroredUILayout"
	100	[253]	CALL     	19 1 2
	101	[253]	TEST     	19 0 0
	102	[253]	JMP      	5	; to 108
	103	[254]	GETTABLE 	19 0 -7	; "width"
	104	[254]	SUB      	19 19 18
	105	[254]	GETTABLE 	20 0 -7	; "width"
	106	[254]	SUB      	18 20 17
	107	[254]	MOVE     	17 19
	108	[257]	EQ       	0 14 -4	; - 1
	109	[257]	JMP      	22	; to 132
	110	[258]	GETUPVAL 	19 5	; LineWidget
	111	[258]	SELF     	19 19 -16	; "new"
	112	[258]	NEWTABLE 	21 0 2
	113	[259]	GETUPVAL 	22 6	; Geom
	114	[259]	SELF     	22 22 -16	; "new"
	115	[259]	NEWTABLE 	24 0 2
	116	[260]	GETTABLE 	25 0 -7	; "width"
	117	[260]	SETTABLE 	24 -32 25	; "w" -
	118	[261]	GETUPVAL 	25 0	; Size
	119	[261]	GETTABLE 	25 25 -37	; "line"
	120	[261]	GETTABLE 	25 25 -38	; "thick"
	121	[261]	SETTABLE 	24 -36 25	; "h" -
	122	[259]	CALL     	22 3 2
	123	[262]	SETTABLE 	21 -35 22	; "dimen" -
	124	[263]	NEWTABLE 	22 1 0
	125	[263]	NEWTABLE 	23 0 2
	126	[265]	SETTABLE 	23 -40 17	; "s" -
	127	[265]	SETTABLE 	23 -41 18	; "e" -
	128	[267]	SETLIST  	22 1 1	; 1
	129	[267]	SETTABLE 	21 -39 22	; "empty_segments" -
	130	[258]	CALL     	19 3 2
	131	[268]	SETTABLE 	0 -34 19	; "bar_sep" -
	132	[271]	GETUPVAL 	19 5	; LineWidget
	133	[271]	SELF     	19 19 -16	; "new"
	134	[271]	NEWTABLE 	21 0 2
	135	[272]	EQ       	0 14 -4	; - 1
	136	[272]	JMP      	3	; to 140
	137	[272]	LOADK    	22 -43	; "solid"
	138	[272]	TEST     	22 0 1
	139	[272]	JMP      	1	; to 141
	140	[272]	LOADK    	22 -44	; "none"
	141	[272]	SETTABLE 	21 -42 22	; "style" -
	142	[273]	GETUPVAL 	22 6	; Geom
	143	[273]	SELF     	22 22 -16	; "new"
	144	[273]	NEWTABLE 	24 0 2
	145	[274]	SETTABLE 	24 -32 1	; "w" -
	146	[275]	GETTABLE 	25 0 -12	; "height"
	147	[275]	SETTABLE 	24 -36 25	; "h" -
	148	[273]	CALL     	22 3 2
	149	[276]	SETTABLE 	21 -35 22	; "dimen" -
	150	[271]	CALL     	19 3 2
	151	[279]	GETTABLE 	20 0 -3	; "icons"
	152	[279]	LEN      	20 20
	153	[279]	LT       	0 14 20
	154	[279]	JMP      	5	; to 160
	155	[280]	GETGLOBAL	20 -28	; table
	156	[280]	GETTABLE 	20 20 -29	; "insert"
	157	[280]	GETTABLE 	21 0 -18	; "icon_seps"
	158	[280]	MOVE     	22 19
	159	[280]	CALL     	20 3 1
	160	[321]	CLOSURE  	20 0	; 0x7fb23b408530
	161	[321]	MOVE     	0 0
	162	[321]	MOVE     	0 17
	163	[321]	MOVE     	0 18
	164	[321]	MOVE     	0 14
	165	[321]	MOVE     	0 1
	166	[321]	MOVE     	0 10
	167	[321]	GETUPVAL 	0 4	; BD
	168	[321]	SETTABLE 	16 -23 20	; "callback" -
	169	[323]	GETGLOBAL	20 -28	; table
	170	[323]	GETTABLE 	20 20 -29	; "insert"
	171	[323]	GETTABLE 	21 0 -15	; "bar_icon_group"
	172	[323]	GETTABLE 	22 0 -17	; "icon_widgets"
	173	[323]	GETTABLE 	22 22 14
	174	[323]	CALL     	20 3 1
	175	[324]	GETGLOBAL	20 -28	; table
	176	[324]	GETTABLE 	20 20 -29	; "insert"
	177	[324]	GETTABLE 	21 0 -15	; "bar_icon_group"
	178	[324]	MOVE     	22 19
	179	[324]	CALL     	20 3 1
	180	[327]	GETTABLE 	20 0 -3	; "icons"
	181	[327]	LEN      	20 20
	182	[327]	SUB      	20 20 -4	; - 1
	183	[327]	EQ       	0 14 20
	184	[327]	JMP      	32	; to 217
	185	[328]	GETGLOBAL	20 -28	; table
	186	[328]	GETTABLE 	20 20 -29	; "insert"
	187	[328]	GETTABLE 	21 0 -15	; "bar_icon_group"
	188	[328]	GETUPVAL 	22 7	; HorizontalSpan
	189	[328]	SELF     	22 22 -16	; "new"
	190	[328]	NEWTABLE 	24 0 1
	191	[329]	SETTABLE 	24 -7 10	; "width" -
	192	[328]	CALL     	22 3 0
	193	[328]	CALL     	20 0 1
	194	[332]	GETUPVAL 	20 5	; LineWidget
	195	[332]	SELF     	20 20 -16	; "new"
	196	[332]	NEWTABLE 	22 0 2
	197	[333]	SETTABLE 	22 -42 -44	; "style" "none"
	198	[334]	GETUPVAL 	23 6	; Geom
	199	[334]	SELF     	23 23 -16	; "new"
	200	[334]	NEWTABLE 	25 0 2
	201	[335]	SETTABLE 	25 -32 1	; "w" -
	202	[336]	GETTABLE 	26 0 -12	; "height"
	203	[336]	SETTABLE 	25 -36 26	; "h" -
	204	[334]	CALL     	23 3 2
	205	[337]	SETTABLE 	22 -35 23	; "dimen" -
	206	[332]	CALL     	20 3 2
	207	[339]	GETGLOBAL	21 -28	; table
	208	[339]	GETTABLE 	21 21 -29	; "insert"
	209	[339]	GETTABLE 	22 0 -18	; "icon_seps"
	210	[339]	MOVE     	23 20
	211	[339]	CALL     	21 3 1
	212	[340]	GETGLOBAL	21 -28	; table
	213	[340]	GETTABLE 	21 21 -29	; "insert"
	214	[340]	GETTABLE 	22 0 -15	; "bar_icon_group"
	215	[340]	MOVE     	23 20
	216	[340]	CALL     	21 3 1
	217	[341]	CLOSE    	16
	218	[341]	CLOSE    	14
	219	[232]	TFORLOOP 	11 2
	220	[341]	JMP      	-157	; to 64
	221	[344]	GETUPVAL 	11 8	; FrameContainer
	222	[344]	SELF     	11 11 -16	; "new"
	223	[344]	NEWTABLE 	13 0 2
	224	[345]	SETTABLE 	13 -45 -46	; "bordersize" 0
	225	[346]	SETTABLE 	13 -47 -46	; "padding" 0
	226	[347]	GETUPVAL 	14 9	; VerticalGroup
	227	[347]	SELF     	14 14 -16	; "new"
	228	[347]	NEWTABLE 	16 2 1
	229	[348]	SETTABLE 	16 -48 -49	; "align" "left"
	230	[350]	GETTABLE 	17 0 -15	; "bar_icon_group"
	231	[353]	GETTABLE 	18 0 -34	; "bar_sep"
	232	[353]	SETLIST  	16 2 1	; 1
	233	[347]	CALL     	14 3 0
	234	[354]	SETLIST  	13 0 1	; 1
	235	[344]	CALL     	11 3 2
	236	[354]	SETTABLE 	0 -4 11	; 1 -
	237	[355]	GETUPVAL 	11 6	; Geom
	238	[355]	SELF     	11 11 -16	; "new"
	239	[355]	NEWTABLE 	13 0 2
	240	[355]	GETTABLE 	14 0 -7	; "width"
	241	[355]	SETTABLE 	13 -32 14	; "w" -
	242	[355]	GETTABLE 	14 0 -12	; "height"
	243	[355]	SETTABLE 	13 -36 14	; "h" -
	244	[355]	CALL     	11 3 2
	245	[355]	SETTABLE 	0 -35 11	; "dimen" -
	246	[356]	RETURN   	0 1

function <./frontend/ui/widget/touchmenu.lua:284,321> (91 instructions, 364 bytes at 0x7fb23b408530)
0 params, 12 slots, 7 upvalues, 9 locals, 14 constants, 0 functions
	1	[285]	GETUPVAL 	0 0	; self
	2	[285]	GETTABLE 	0 0 -1	; "bar_sep"
	3	[285]	NEWTABLE 	1 1 0
	4	[285]	NEWTABLE 	2 0 2
	5	[287]	GETUPVAL 	3 1	; _start_seg
	6	[287]	SETTABLE 	2 -3 3	; "s" -
	7	[287]	GETUPVAL 	3 2	; _end_seg
	8	[287]	SETTABLE 	2 -4 3	; "e" -
	9	[289]	SETLIST  	1 1 1	; 1
	10	[289]	SETTABLE 	0 -2 1	; "empty_segments" -
	11	[290]	GETGLOBAL	0 -5	; ipairs
	12	[290]	GETUPVAL 	1 0	; self
	13	[290]	GETTABLE 	1 1 -6	; "icon_seps"
	14	[290]	CALL     	0 2 4
	15	[290]	JMP      	68	; to 84
	16	[291]	LOADNIL  	5 6
	17	[292]	GETUPVAL 	7 3	; k
	18	[292]	GETUPVAL 	8 0	; self
	19	[292]	GETTABLE 	8 8 -7	; "icons"
	20	[292]	LEN      	8 8
	21	[292]	EQ       	0 7 8
	22	[292]	JMP      	7	; to 30
	23	[293]	LOADBOOL 	5 0 0
	24	[294]	GETUPVAL 	7 3	; k
	25	[294]	EQ       	1 3 7
	26	[294]	JMP      	1	; to 28
	27	[294]	LOADBOOL 	6 0 1
	28	[294]	LOADBOOL 	6 1 0
	29	[294]	JMP      	10	; to 40
	30	[296]	GETUPVAL 	7 3	; k
	31	[296]	SUB      	7 7 -8	; - 1
	32	[296]	EQ       	1 3 7
	33	[296]	JMP      	4	; to 38
	34	[296]	GETUPVAL 	7 3	; k
	35	[296]	EQ       	1 3 7
	36	[296]	JMP      	1	; to 38
	37	[296]	LOADBOOL 	5 0 1
	38	[296]	LOADBOOL 	5 1 0
	39	[297]	LOADBOOL 	6 0 0
	40	[302]	TEST     	6 0 0
	41	[302]	JMP      	35	; to 77
	42	[303]	GETUPVAL 	7 4	; icon_sep_width
	43	[303]	GETUPVAL 	8 5	; stretch_width
	44	[303]	ADD      	7 7 8
	45	[303]	GETUPVAL 	8 1	; _start_seg
	46	[303]	ADD      	7 7 8
	47	[304]	GETUPVAL 	8 4	; icon_sep_width
	48	[304]	GETUPVAL 	9 5	; stretch_width
	49	[304]	ADD      	8 8 9
	50	[304]	GETUPVAL 	9 2	; _end_seg
	51	[304]	ADD      	8 8 9
	52	[305]	GETUPVAL 	9 6	; BD
	53	[305]	GETTABLE 	9 9 -9	; "mirroredUILayout"
	54	[305]	CALL     	9 1 2
	55	[305]	TEST     	9 0 0
	56	[305]	JMP      	10	; to 67
	57	[306]	GETUPVAL 	9 1	; _start_seg
	58	[306]	GETUPVAL 	10 4	; icon_sep_width
	59	[306]	SUB      	9 9 10
	60	[306]	GETUPVAL 	10 5	; stretch_width
	61	[306]	SUB      	7 9 10
	62	[307]	GETUPVAL 	9 2	; _end_seg
	63	[307]	GETUPVAL 	10 4	; icon_sep_width
	64	[307]	SUB      	9 9 10
	65	[307]	GETUPVAL 	10 5	; stretch_width
	66	[307]	SUB      	8 9 10
	67	[309]	GETUPVAL 	9 0	; self
	68	[309]	GETTABLE 	9 9 -1	; "bar_sep"
	69	[309]	NEWTABLE 	10 1 0
	70	[309]	NEWTABLE 	11 0 2
	71	[311]	SETTABLE 	11 -3 7	; "s" -
	72	[311]	SETTABLE 	11 -4 8	; "e" -
	73	[313]	SETLIST  	10 1 1	; 1
	74	[313]	SETTABLE 	9 -2 10	; "empty_segments" -
	75	[314]	SETTABLE 	4 -10 -11	; "style" "solid"
	76	[314]	JMP      	7	; to 84
	77	[317]	TEST     	5 0 0
	78	[317]	JMP      	3	; to 82
	79	[317]	LOADK    	7 -11	; "solid"
	80	[317]	TEST     	7 0 1
	81	[317]	JMP      	1	; to 83
	82	[317]	LOADK    	7 -12	; "none"
	83	[317]	SETTABLE 	4 -10 7	; "style" -
	84	[290]	TFORLOOP 	0 2
	85	[318]	JMP      	-70	; to 16
	86	[320]	GETUPVAL 	0 0	; self
	87	[320]	GETTABLE 	0 0 -13	; "menu"
	88	[320]	SELF     	0 0 -14	; "switchMenuTab"
	89	[320]	GETUPVAL 	2 3	; k
	90	[320]	CALL     	0 3 1
	91	[321]	RETURN   	0 1

function <./frontend/ui/widget/touchmenu.lua:358,365> (11 instructions, 44 bytes at 0x7fb23b408b80)
2 params, 3 slots, 0 upvalues, 2 locals, 2 constants, 0 functions
	1	[361]	GETTABLE 	2 0 -1	; "icon_widgets"
	2	[361]	LEN      	2 2
	3	[361]	LT       	0 2 1
	4	[361]	JMP      	2	; to 7
	5	[362]	GETTABLE 	2 0 -1	; "icon_widgets"
	6	[362]	LEN      	1 2
	7	[364]	GETTABLE 	2 0 -1	; "icon_widgets"
	8	[364]	GETTABLE 	2 2 1
	9	[364]	GETTABLE 	2 2 -2	; "callback"
	10	[364]	CALL     	2 1 1
	11	[365]	RETURN   	0 1

function <./frontend/ui/widget/touchmenu.lua:390,537> (370 instructions, 1480 bytes at 0x7fb23b408ef0)
1 param, 19 slots, 21 upvalues, 12 locals, 88 constants, 4 functions
	1	[395]	GETTABLE 	1 0 -1	; "dimen"
	2	[395]	TEST     	1 0 1
	3	[395]	JMP      	5	; to 9
	4	[395]	GETUPVAL 	1 0	; Geom
	5	[395]	SELF     	1 1 -2	; "new"
	6	[395]	NEWTABLE 	3 0 0
	7	[395]	CALL     	1 3 2
	8	[395]	SETTABLE 	0 -1 1	; "dimen" -
	9	[396]	GETTABLE 	1 0 -3	; "show_parent"
	10	[396]	TEST     	1 0 1
	11	[396]	JMP      	1	; to 13
	12	[396]	MOVE     	1 0
	13	[396]	SETTABLE 	0 -3 1	; "show_parent" -
	14	[397]	GETTABLE 	1 0 -4	; "close_callback"
	15	[397]	TEST     	1 0 1
	16	[397]	JMP      	4	; to 21
	17	[400]	CLOSURE  	1 0	; 0x7fb23b40b4b0
	18	[400]	GETUPVAL 	0 1	; UIManager
	19	[400]	MOVE     	0 0
	20	[400]	SETTABLE 	0 -4 1	; "close_callback" -
	21	[403]	NEWTABLE 	1 0 0
	22	[403]	SETTABLE 	0 -5 1	; "layout" -
	23	[405]	GETTABLE 	1 0 -6	; "ges_events"
	24	[405]	NEWTABLE 	2 0 0
	25	[406]	GETUPVAL 	3 2	; GestureRange
	26	[406]	SELF     	3 3 -2	; "new"
	27	[406]	NEWTABLE 	5 0 2
	28	[407]	SETTABLE 	5 -8 -9	; "ges" "tap"
	29	[408]	GETUPVAL 	6 0	; Geom
	30	[408]	SELF     	6 6 -2	; "new"
	31	[408]	NEWTABLE 	8 0 4
	32	[409]	SETTABLE 	8 -11 -12	; "x" 0
	33	[409]	SETTABLE 	8 -13 -12	; "y" 0
	34	[410]	GETUPVAL 	9 3	; Screen
	35	[410]	SELF     	9 9 -15	; "getWidth"
	36	[410]	CALL     	9 2 2
	37	[410]	SETTABLE 	8 -14 9	; "w" -
	38	[411]	GETUPVAL 	9 3	; Screen
	39	[411]	SELF     	9 9 -17	; "getHeight"
	40	[411]	CALL     	9 2 2
	41	[411]	SETTABLE 	8 -16 9	; "h" -
	42	[408]	CALL     	6 3 2
	43	[412]	SETTABLE 	5 -10 6	; "range" -
	44	[406]	CALL     	3 3 0
	45	[414]	SETLIST  	2 0 1	; 1
	46	[414]	SETTABLE 	1 -7 2	; "TapCloseAllMenus" -
	47	[415]	GETTABLE 	1 0 -6	; "ges_events"
	48	[415]	NEWTABLE 	2 0 0
	49	[416]	GETUPVAL 	3 2	; GestureRange
	50	[416]	SELF     	3 3 -2	; "new"
	51	[416]	NEWTABLE 	5 0 2
	52	[417]	SETTABLE 	5 -8 -19	; "ges" "swipe"
	53	[418]	GETTABLE 	6 0 -1	; "dimen"
	54	[418]	SETTABLE 	5 -10 6	; "range" -
	55	[416]	CALL     	3 3 0
	56	[420]	SETLIST  	2 0 1	; 1
	57	[420]	SETTABLE 	1 -18 2	; "Swipe" -
	58	[422]	GETTABLE 	1 0 -20	; "key_events"
	59	[422]	NEWTABLE 	2 1 1
	60	[422]	NEWTABLE 	3 1 0
	61	[422]	LOADK    	4 -21	; "Back"
	62	[422]	SETLIST  	3 1 1	; 1
	63	[422]	SETTABLE 	2 -22 -23	; "doc" "back to upper menu or close touchmenu"
	64	[422]	SETLIST  	2 1 1	; 1
	65	[422]	SETTABLE 	1 -21 2	; "Back" -
	66	[423]	GETTABLE 	1 0 -20	; "key_events"
	67	[423]	NEWTABLE 	2 1 1
	68	[423]	NEWTABLE 	3 1 0
	69	[423]	GETUPVAL 	4 4	; Input
	70	[423]	GETTABLE 	4 4 -25	; "group"
	71	[423]	GETTABLE 	4 4 -26	; "PgFwd"
	72	[423]	SETLIST  	3 1 1	; 1
	73	[423]	SETTABLE 	2 -22 -27	; "doc" "next page"
	74	[423]	SETLIST  	2 1 1	; 1
	75	[423]	SETTABLE 	1 -24 2	; "NextPage" -
	76	[424]	GETTABLE 	1 0 -20	; "key_events"
	77	[424]	NEWTABLE 	2 1 1
	78	[424]	NEWTABLE 	3 1 0
	79	[424]	GETUPVAL 	4 4	; Input
	80	[424]	GETTABLE 	4 4 -25	; "group"
	81	[424]	GETTABLE 	4 4 -29	; "PgBack"
	82	[424]	SETLIST  	3 1 1	; 1
	83	[424]	SETTABLE 	2 -22 -30	; "doc" "previous page"
	84	[424]	SETLIST  	2 1 1	; 1
	85	[424]	SETTABLE 	1 -28 2	; "PrevPage" -
	86	[425]	GETTABLE 	1 0 -20	; "key_events"
	87	[425]	NEWTABLE 	2 1 1
	88	[425]	NEWTABLE 	3 1 0
	89	[425]	LOADK    	4 -31	; "Press"
	90	[425]	SETLIST  	3 1 1	; 1
	91	[425]	SETTABLE 	2 -22 -32	; "doc" "chose selected item"
	92	[425]	SETLIST  	2 1 1	; 1
	93	[425]	SETTABLE 	1 -31 2	; "Press" -
	94	[427]	NEWTABLE 	1 0 0
	95	[428]	GETGLOBAL	2 -33	; ipairs
	96	[428]	GETTABLE 	3 0 -34	; "tab_item_table"
	97	[428]	CALL     	2 2 4
	98	[428]	JMP      	5	; to 104
	99	[429]	GETGLOBAL	7 -35	; table
	100	[429]	GETTABLE 	7 7 -36	; "insert"
	101	[429]	MOVE     	8 1
	102	[429]	GETTABLE 	9 6 -37	; "icon"
	103	[429]	CALL     	7 3 1
	104	[428]	TFORLOOP 	2 2
	105	[429]	JMP      	-7	; to 99
	106	[431]	GETUPVAL 	2 5	; TouchMenuBar
	107	[431]	SELF     	2 2 -2	; "new"
	108	[431]	NEWTABLE 	4 0 4
	109	[432]	GETTABLE 	5 0 -39	; "width"
	110	[432]	SETTABLE 	4 -39 5	; "width" -
	111	[433]	SETTABLE 	4 -40 1	; "icons" -
	112	[434]	GETTABLE 	5 0 -3	; "show_parent"
	113	[434]	SETTABLE 	4 -3 5	; "show_parent" -
	114	[435]	SETTABLE 	4 -41 0	; "menu" -
	115	[431]	CALL     	2 3 2
	116	[436]	SETTABLE 	0 -38 2	; "bar" -
	117	[438]	GETUPVAL 	2 6	; VerticalGroup
	118	[438]	SELF     	2 2 -2	; "new"
	119	[438]	NEWTABLE 	4 0 1
	120	[439]	SETTABLE 	4 -43 -44	; "align" "center"
	121	[438]	CALL     	2 3 2
	122	[440]	SETTABLE 	0 -42 2	; "item_group" -
	123	[442]	LOADK    	2 -45	; "resources/icons/appbar.chevron.left.png"
	124	[443]	LOADK    	3 -46	; "resources/icons/appbar.chevron.right.png"
	125	[444]	GETUPVAL 	4 7	; BD
	126	[444]	GETTABLE 	4 4 -47	; "mirroredUILayout"
	127	[444]	CALL     	4 1 2
	128	[444]	TEST     	4 0 0
	129	[444]	JMP      	3	; to 133
	130	[445]	MOVE     	4 3
	131	[445]	MOVE     	3 2
	132	[445]	MOVE     	2 4
	133	[447]	GETUPVAL 	4 8	; Button
	134	[447]	SELF     	4 4 -2	; "new"
	135	[447]	NEWTABLE 	6 0 4
	136	[448]	SETTABLE 	6 -37 2	; "icon" -
	137	[449]	CLOSURE  	7 1	; 0x7fb23b40bc20
	138	[449]	MOVE     	0 0
	139	[449]	SETTABLE 	6 -49 7	; "callback" -
	140	[450]	SETTABLE 	6 -50 -12	; "bordersize" 0
	141	[451]	GETTABLE 	7 0 -3	; "show_parent"
	142	[451]	SETTABLE 	6 -3 7	; "show_parent" -
	143	[447]	CALL     	4 3 2
	144	[452]	SETTABLE 	0 -48 4	; "page_info_left_chev" -
	145	[453]	GETUPVAL 	4 8	; Button
	146	[453]	SELF     	4 4 -2	; "new"
	147	[453]	NEWTABLE 	6 0 4
	148	[454]	SETTABLE 	6 -37 3	; "icon" -
	149	[455]	CLOSURE  	7 2	; 0x7fb23b40be50
	150	[455]	MOVE     	0 0
	151	[455]	SETTABLE 	6 -49 7	; "callback" -
	152	[456]	SETTABLE 	6 -50 -12	; "bordersize" 0
	153	[457]	GETTABLE 	7 0 -3	; "show_parent"
	154	[457]	SETTABLE 	6 -3 7	; "show_parent" -
	155	[453]	CALL     	4 3 2
	156	[458]	SETTABLE 	0 -51 4	; "page_info_right_chev" -
	157	[459]	GETTABLE 	4 0 -48	; "page_info_left_chev"
	158	[459]	SELF     	4 4 -52	; "hide"
	159	[459]	CALL     	4 2 1
	160	[460]	GETTABLE 	4 0 -51	; "page_info_right_chev"
	161	[460]	SELF     	4 4 -52	; "hide"
	162	[460]	CALL     	4 2 1
	163	[461]	GETUPVAL 	4 9	; TextWidget
	164	[461]	SELF     	4 4 -2	; "new"
	165	[461]	NEWTABLE 	6 0 2
	166	[462]	SETTABLE 	6 -54 -55	; "text" ""
	167	[463]	GETTABLE 	7 0 -57	; "fface"
	168	[463]	SETTABLE 	6 -56 7	; "face" -
	169	[461]	CALL     	4 3 2
	170	[464]	SETTABLE 	0 -53 4	; "page_info_text" -
	171	[465]	GETUPVAL 	4 10	; HorizontalGroup
	172	[465]	SELF     	4 4 -2	; "new"
	173	[465]	NEWTABLE 	6 3 0
	174	[466]	GETTABLE 	7 0 -48	; "page_info_left_chev"
	175	[467]	GETTABLE 	8 0 -53	; "page_info_text"
	176	[469]	GETTABLE 	9 0 -51	; "page_info_right_chev"
	177	[469]	SETLIST  	6 3 1	; 1
	178	[465]	CALL     	4 3 2
	179	[469]	SETTABLE 	0 -58 4	; "page_info" -
	180	[471]	GETUPVAL 	4 9	; TextWidget
	181	[471]	SELF     	4 4 -2	; "new"
	182	[471]	NEWTABLE 	6 0 2
	183	[472]	SETTABLE 	6 -54 -55	; "text" ""
	184	[473]	GETTABLE 	7 0 -57	; "fface"
	185	[473]	SETTABLE 	6 -56 7	; "face" -
	186	[471]	CALL     	4 3 2
	187	[474]	SETTABLE 	0 -59 4	; "time_info" -
	188	[475]	GETUPVAL 	4 10	; HorizontalGroup
	189	[475]	SELF     	4 4 -2	; "new"
	190	[475]	NEWTABLE 	6 1 0
	191	[476]	GETTABLE 	7 0 -59	; "time_info"
	192	[478]	GETUPVAL 	8 11	; HorizontalSpan
	193	[478]	SELF     	8 8 -2	; "new"
	194	[478]	NEWTABLE 	10 0 1
	195	[478]	GETUPVAL 	11 12	; Size
	196	[478]	GETTABLE 	11 11 -61	; "span"
	197	[478]	GETTABLE 	11 11 -62	; "horizontal_default"
	198	[478]	SETTABLE 	10 -39 11	; "width" -
	199	[478]	CALL     	8 3 0
	200	[479]	SETLIST  	6 0 1	; 1
	201	[475]	CALL     	4 3 2
	202	[479]	SETTABLE 	0 -60 4	; "device_info" -
	203	[480]	GETTABLE 	4 0 -39	; "width"
	204	[480]	GETTABLE 	5 0 -63	; "padding"
	205	[480]	MUL      	5 5 -64	; - 2
	206	[480]	SUB      	4 4 5
	207	[481]	GETUPVAL 	5 13	; IconButton
	208	[481]	SELF     	5 5 -2	; "new"
	209	[481]	NEWTABLE 	7 0 5
	210	[482]	SETTABLE 	7 -65 -66	; "icon_file" "resources/icons/appbar.chevron.up.png"
	211	[483]	GETTABLE 	8 0 -3	; "show_parent"
	212	[483]	SETTABLE 	7 -3 8	; "show_parent" -
	213	[484]	MUL      	8 4 -68	; - 0.33
	214	[484]	MUL      	8 8 -69	; - 0.1
	215	[484]	SETTABLE 	7 -67 8	; "padding_left" -
	216	[485]	MUL      	8 4 -68	; - 0.33
	217	[485]	MUL      	8 8 -69	; - 0.1
	218	[485]	SETTABLE 	7 -70 8	; "padding_right" -
	219	[488]	CLOSURE  	8 3	; 0x7fb23b40c1c0
	220	[488]	MOVE     	0 0
	221	[488]	SETTABLE 	7 -49 8	; "callback" -
	222	[481]	CALL     	5 3 2
	223	[490]	SELF     	6 5 -71	; "getSize"
	224	[490]	CALL     	6 2 2
	225	[490]	GETTABLE 	6 6 -16	; "h"
	226	[490]	GETUPVAL 	7 12	; Size
	227	[490]	GETTABLE 	7 7 -72	; "line"
	228	[490]	GETTABLE 	7 7 -73	; "thick"
	229	[490]	ADD      	6 6 7
	230	[491]	GETUPVAL 	7 10	; HorizontalGroup
	231	[491]	SELF     	7 7 -2	; "new"
	232	[491]	NEWTABLE 	9 2 0
	233	[492]	GETUPVAL 	10 14	; LeftContainer
	234	[492]	SELF     	10 10 -2	; "new"
	235	[492]	NEWTABLE 	12 1 1
	236	[493]	GETUPVAL 	13 0	; Geom
	237	[493]	SELF     	13 13 -2	; "new"
	238	[493]	NEWTABLE 	15 0 2
	239	[493]	MUL      	16 4 -68	; - 0.33
	240	[493]	SETTABLE 	15 -14 16	; "w" -
	241	[493]	SETTABLE 	15 -16 6	; "h" -
	242	[493]	CALL     	13 3 2
	243	[493]	SETTABLE 	12 -1 13	; "dimen" -
	244	[495]	MOVE     	13 5
	245	[495]	SETLIST  	12 1 1	; 1
	246	[492]	CALL     	10 3 2
	247	[496]	GETUPVAL 	11 15	; CenterContainer
	248	[496]	SELF     	11 11 -2	; "new"
	249	[496]	NEWTABLE 	13 1 1
	250	[497]	GETUPVAL 	14 0	; Geom
	251	[497]	SELF     	14 14 -2	; "new"
	252	[497]	NEWTABLE 	16 0 2
	253	[497]	MUL      	17 4 -68	; - 0.33
	254	[497]	SETTABLE 	16 -14 17	; "w" -
	255	[497]	SETTABLE 	16 -16 6	; "h" -
	256	[497]	CALL     	14 3 2
	257	[497]	SETTABLE 	13 -1 14	; "dimen" -
	258	[499]	GETTABLE 	14 0 -58	; "page_info"
	259	[499]	SETLIST  	13 1 1	; 1
	260	[496]	CALL     	11 3 2
	261	[500]	GETUPVAL 	12 16	; RightContainer
	262	[500]	SELF     	12 12 -2	; "new"
	263	[500]	NEWTABLE 	14 1 1
	264	[501]	GETUPVAL 	15 0	; Geom
	265	[501]	SELF     	15 15 -2	; "new"
	266	[501]	NEWTABLE 	17 0 2
	267	[501]	MUL      	18 4 -68	; - 0.33
	268	[501]	SETTABLE 	17 -14 18	; "w" -
	269	[501]	SETTABLE 	17 -16 6	; "h" -
	270	[501]	CALL     	15 3 2
	271	[501]	SETTABLE 	14 -1 15	; "dimen" -
	272	[503]	GETTABLE 	15 0 -60	; "device_info"
	273	[503]	SETLIST  	14 1 1	; 1
	274	[500]	CALL     	12 3 0
	275	[504]	SETLIST  	9 0 1	; 1
	276	[491]	CALL     	7 3 2
	277	[504]	SETTABLE 	0 -74 7	; "footer" -
	278	[506]	GETUPVAL 	7 17	; FrameContainer
	279	[506]	SELF     	7 7 -2	; "new"
	280	[506]	NEWTABLE 	9 1 3
	281	[507]	GETTABLE 	10 0 -63	; "padding"
	282	[507]	SETTABLE 	9 -63 10	; "padding" -
	283	[508]	GETTABLE 	10 0 -50	; "bordersize"
	284	[508]	SETTABLE 	9 -50 10	; "bordersize" -
	285	[509]	GETUPVAL 	10 18	; Blitbuffer
	286	[509]	GETTABLE 	10 10 -77	; "COLOR_WHITE"
	287	[509]	SETTABLE 	9 -76 10	; "background" -
	288	[513]	GETTABLE 	10 0 -42	; "item_group"
	289	[513]	SETLIST  	9 1 1	; 1
	290	[506]	CALL     	7 3 2
	291	[513]	SETTABLE 	0 -75 7	; "menu_frame" -
	292	[516]	GETUPVAL 	7 15	; CenterContainer
	293	[516]	SELF     	7 7 -2	; "new"
	294	[516]	NEWTABLE 	9 1 2
	295	[517]	GETUPVAL 	10 3	; Screen
	296	[517]	SELF     	10 10 -71	; "getSize"
	297	[517]	CALL     	10 2 2
	298	[517]	SETTABLE 	9 -1 10	; "dimen" -
	299	[518]	SETTABLE 	9 -79 -80	; "ignore" "height"
	300	[520]	GETTABLE 	10 0 -75	; "menu_frame"
	301	[520]	SETLIST  	9 1 1	; 1
	302	[516]	CALL     	7 3 2
	303	[520]	SETTABLE 	0 -78 7	; 1 -
	304	[522]	GETTABLE 	7 0 -39	; "width"
	305	[522]	GETTABLE 	8 0 -63	; "padding"
	306	[522]	MUL      	8 8 -64	; - 2
	307	[522]	SUB      	7 7 8
	308	[522]	SETTABLE 	0 -81 7	; "item_width" -
	309	[523]	GETUPVAL 	7 10	; HorizontalGroup
	310	[523]	SELF     	7 7 -2	; "new"
	311	[523]	NEWTABLE 	9 2 0
	312	[525]	GETUPVAL 	10 11	; HorizontalSpan
	313	[525]	SELF     	10 10 -2	; "new"
	314	[525]	NEWTABLE 	12 0 1
	315	[525]	GETUPVAL 	13 12	; Size
	316	[525]	GETTABLE 	13 13 -61	; "span"
	317	[525]	GETTABLE 	13 13 -62	; "horizontal_default"
	318	[525]	SETTABLE 	12 -39 13	; "width" -
	319	[525]	CALL     	10 3 2
	320	[526]	GETUPVAL 	11 19	; LineWidget
	321	[526]	SELF     	11 11 -2	; "new"
	322	[526]	NEWTABLE 	13 0 2
	323	[527]	GETUPVAL 	14 18	; Blitbuffer
	324	[527]	GETTABLE 	14 14 -83	; "COLOR_GRAY"
	325	[527]	SETTABLE 	13 -76 14	; "background" -
	326	[528]	GETUPVAL 	14 0	; Geom
	327	[528]	SELF     	14 14 -2	; "new"
	328	[528]	NEWTABLE 	16 0 2
	329	[529]	GETTABLE 	17 0 -81	; "item_width"
	330	[529]	GETUPVAL 	18 12	; Size
	331	[529]	GETTABLE 	18 18 -61	; "span"
	332	[529]	GETTABLE 	18 18 -62	; "horizontal_default"
	333	[529]	MUL      	18 -64 18	; 2 -
	334	[529]	SUB      	17 17 18
	335	[529]	SETTABLE 	16 -14 17	; "w" -
	336	[530]	GETUPVAL 	17 12	; Size
	337	[530]	GETTABLE 	17 17 -72	; "line"
	338	[530]	GETTABLE 	17 17 -84	; "medium"
	339	[530]	SETTABLE 	16 -16 17	; "h" -
	340	[528]	CALL     	14 3 2
	341	[531]	SETTABLE 	13 -1 14	; "dimen" -
	342	[526]	CALL     	11 3 2
	343	[533]	GETUPVAL 	12 11	; HorizontalSpan
	344	[533]	SELF     	12 12 -2	; "new"
	345	[533]	NEWTABLE 	14 0 1
	346	[533]	GETUPVAL 	15 12	; Size
	347	[533]	GETTABLE 	15 15 -61	; "span"
	348	[533]	GETTABLE 	15 15 -62	; "horizontal_default"
	349	[533]	SETTABLE 	14 -39 15	; "width" -
	350	[533]	CALL     	12 3 0
	351	[534]	SETLIST  	9 0 1	; 1
	352	[523]	CALL     	7 3 2
	353	[534]	SETTABLE 	0 -82 7	; "split_line" -
	354	[535]	GETUPVAL 	7 20	; VerticalSpan
	355	[535]	SELF     	7 7 -2	; "new"
	356	[535]	NEWTABLE 	9 0 1
	357	[535]	GETUPVAL 	10 12	; Size
	358	[535]	GETTABLE 	10 10 -61	; "span"
	359	[535]	GETTABLE 	10 10 -86	; "vertical_default"
	360	[535]	SETTABLE 	9 -39 10	; "width" -
	361	[535]	CALL     	7 3 2
	362	[535]	SETTABLE 	0 -85 7	; "footer_top_margin" -
	363	[536]	GETTABLE 	7 0 -38	; "bar"
	364	[536]	SELF     	7 7 -87	; "switchToTab"
	365	[536]	GETTABLE 	9 0 -88	; "last_index"
	366	[536]	TEST     	9 0 1
	367	[536]	JMP      	1	; to 369
	368	[536]	LOADK    	9 -78	; 1
	369	[536]	CALL     	7 3 1
	370	[537]	RETURN   	0 1

function <./frontend/ui/widget/touchmenu.lua:398,400> (6 instructions, 24 bytes at 0x7fb23b40b4b0)
0 params, 3 slots, 2 upvalues, 0 locals, 2 constants, 0 functions
	1	[399]	GETUPVAL 	0 0	; UIManager
	2	[399]	SELF     	0 0 -1	; "close"
	3	[399]	GETUPVAL 	2 1	; self
	4	[399]	GETTABLE 	2 2 -2	; "show_parent"
	5	[399]	CALL     	0 3 1
	6	[400]	RETURN   	0 1

function <./frontend/ui/widget/touchmenu.lua:449,449> (4 instructions, 16 bytes at 0x7fb23b40bc20)
0 params, 2 slots, 1 upvalue, 0 locals, 1 constant, 0 functions
	1	[449]	GETUPVAL 	0 0	; self
	2	[449]	SELF     	0 0 -1	; "onPrevPage"
	3	[449]	CALL     	0 2 1
	4	[449]	RETURN   	0 1

function <./frontend/ui/widget/touchmenu.lua:455,455> (4 instructions, 16 bytes at 0x7fb23b40be50)
0 params, 2 slots, 1 upvalue, 0 locals, 1 constant, 0 functions
	1	[455]	GETUPVAL 	0 0	; self
	2	[455]	SELF     	0 0 -1	; "onNextPage"
	3	[455]	CALL     	0 2 1
	4	[455]	RETURN   	0 1

function <./frontend/ui/widget/touchmenu.lua:486,488> (4 instructions, 16 bytes at 0x7fb23b40c1c0)
0 params, 2 slots, 1 upvalue, 0 locals, 1 constant, 0 functions
	1	[487]	GETUPVAL 	0 0	; self
	2	[487]	SELF     	0 0 -1	; "backToUpperMenu"
	3	[487]	CALL     	0 2 1
	4	[488]	RETURN   	0 1

function <./frontend/ui/widget/touchmenu.lua:539,542> (6 instructions, 24 bytes at 0x7fb23b40b630)
1 param, 5 slots, 1 upvalue, 1 local, 2 constants, 0 functions
	1	[541]	GETUPVAL 	1 0	; UIManager
	2	[541]	SELF     	1 1 -1	; "setDirty"
	3	[541]	LOADNIL  	3 3
	4	[541]	LOADK    	4 -2	; "flashui"
	5	[541]	CALL     	1 4 1
	6	[542]	RETURN   	0 1

function <./frontend/ui/widget/touchmenu.lua:544,569> (63 instructions, 252 bytes at 0x7fb23b40c9b0)
1 param, 9 slots, 1 upvalue, 6 locals, 17 constants, 0 functions
	1	[547]	GETTABLE 	2 0 -1	; "bar"
	2	[547]	SELF     	2 2 -2	; "getSize"
	3	[547]	CALL     	2 2 2
	4	[547]	GETTABLE 	2 2 -3	; "h"
	5	[548]	GETTABLE 	3 0 -4	; "footer"
	6	[548]	SELF     	3 3 -2	; "getSize"
	7	[548]	CALL     	3 2 2
	8	[548]	GETTABLE 	3 3 -3	; "h"
	9	[549]	GETTABLE 	4 0 -5	; "height"
	10	[549]	TEST     	4 0 0
	11	[549]	JMP      	3	; to 15
	12	[550]	GETTABLE 	4 0 -5	; "height"
	13	[550]	SUB      	1 4 2
	14	[550]	JMP      	14	; to 29
	15	[552]	GETTABLE 	4 0 -6	; "item_table"
	16	[552]	LEN      	4 4
	17	[552]	GETTABLE 	5 0 -7	; "item_height"
	18	[552]	MUL      	4 4 5
	19	[552]	ADD      	1 4 3
	20	[554]	GETTABLE 	4 0 -6	; "item_table"
	21	[554]	LEN      	4 4
	22	[554]	SUB      	4 4 -8	; - 1
	23	[554]	ADD      	1 1 4
	24	[555]	GETTABLE 	4 0 -9	; "footer_top_margin"
	25	[555]	SELF     	4 4 -2	; "getSize"
	26	[555]	CALL     	4 2 2
	27	[555]	GETTABLE 	4 4 -3	; "h"
	28	[555]	ADD      	1 1 4
	29	[557]	ADD      	4 1 2
	30	[557]	GETUPVAL 	5 0	; Screen
	31	[557]	SELF     	5 5 -10	; "getHeight"
	32	[557]	CALL     	5 2 2
	33	[557]	LT       	0 5 4
	34	[557]	JMP      	4	; to 39
	35	[558]	GETUPVAL 	4 0	; Screen
	36	[558]	SELF     	4 4 -10	; "getHeight"
	37	[558]	CALL     	4 2 2
	38	[558]	SUB      	1 4 2
	39	[561]	SUB      	4 1 3
	40	[562]	GETGLOBAL	5 -12	; math
	41	[562]	GETTABLE 	5 5 -13	; "floor"
	42	[562]	GETTABLE 	6 0 -7	; "item_height"
	43	[562]	DIV      	6 4 6
	44	[562]	CALL     	5 2 2
	45	[562]	SETTABLE 	0 -11 5	; "perpage" -
	46	[563]	GETTABLE 	5 0 -6	; "item_table"
	47	[563]	GETTABLE 	5 5 -14	; "max_per_page"
	48	[563]	TEST     	5 0 1
	49	[563]	JMP      	1	; to 51
	50	[563]	GETTABLE 	5 0 -15	; "max_per_page_default"
	51	[564]	GETTABLE 	6 0 -11	; "perpage"
	52	[564]	LT       	0 5 6
	53	[564]	JMP      	1	; to 55
	54	[565]	SETTABLE 	0 -11 5	; "perpage" -
	55	[568]	GETGLOBAL	6 -12	; math
	56	[568]	GETTABLE 	6 6 -17	; "ceil"
	57	[568]	GETTABLE 	7 0 -6	; "item_table"
	58	[568]	LEN      	7 7
	59	[568]	GETTABLE 	8 0 -11	; "perpage"
	60	[568]	DIV      	7 7 8
	61	[568]	CALL     	6 2 2
	62	[568]	SETTABLE 	0 -16 6	; "page_num" -
	63	[569]	RETURN   	0 1

function <./frontend/ui/widget/touchmenu.lua:571,691> (310 instructions, 1240 bytes at 0x7fb23b40cc50)
1 param, 15 slots, 7 upvalues, 14 locals, 89 constants, 1 function
	1	[572]	GETTABLE 	1 0 -1	; "dimen"
	2	[572]	TEST     	1 0 0
	3	[572]	JMP      	3	; to 7
	4	[572]	GETTABLE 	1 0 -1	; "dimen"
	5	[572]	SELF     	1 1 -2	; "copy"
	6	[572]	CALL     	1 2 2
	7	[573]	SELF     	2 0 -3	; "_recalculatePageLayout"
	8	[573]	CALL     	2 2 1
	9	[574]	GETTABLE 	2 0 -4	; "item_group"
	10	[574]	SELF     	2 2 -5	; "clear"
	11	[574]	CALL     	2 2 1
	12	[575]	NEWTABLE 	2 0 0
	13	[575]	SETTABLE 	0 -6 2	; "layout" -
	14	[576]	GETGLOBAL	2 -7	; table
	15	[576]	GETTABLE 	2 2 -8	; "insert"
	16	[576]	GETTABLE 	3 0 -4	; "item_group"
	17	[576]	GETTABLE 	4 0 -9	; "bar"
	18	[576]	CALL     	2 3 1
	19	[577]	GETGLOBAL	2 -7	; table
	20	[577]	GETTABLE 	2 2 -8	; "insert"
	21	[577]	GETTABLE 	3 0 -6	; "layout"
	22	[577]	GETTABLE 	4 0 -9	; "bar"
	23	[577]	GETTABLE 	4 4 -10	; "icon_widgets"
	24	[577]	CALL     	2 3 1
	25	[579]	LOADK    	2 -11	; 1
	26	[579]	GETTABLE 	3 0 -12	; "perpage"
	27	[579]	LOADK    	4 -11	; 1
	28	[579]	FORPREP  	2 57	; to 86
	29	[581]	GETTABLE 	6 0 -13	; "page"
	30	[581]	SUB      	6 6 -11	; - 1
	31	[581]	GETTABLE 	7 0 -12	; "perpage"
	32	[581]	MUL      	6 6 7
	33	[581]	ADD      	6 6 5
	34	[582]	GETTABLE 	7 0 -14	; "item_table"
	35	[582]	LEN      	7 7
	36	[582]	LE       	0 6 7
	37	[582]	JMP      	49	; to 87
	38	[583]	GETTABLE 	7 0 -14	; "item_table"
	39	[583]	GETTABLE 	7 7 6
	40	[584]	GETUPVAL 	8 0	; TouchMenuItem
	41	[584]	SELF     	8 8 -15	; "new"
	42	[584]	NEWTABLE 	10 0 4
	43	[585]	SETTABLE 	10 -16 7	; "item" -
	44	[586]	SETTABLE 	10 -17 0	; "menu" -
	45	[587]	GETUPVAL 	11 1	; Geom
	46	[587]	SELF     	11 11 -15	; "new"
	47	[587]	NEWTABLE 	13 0 2
	48	[588]	GETTABLE 	14 0 -19	; "item_width"
	49	[588]	SETTABLE 	13 -18 14	; "w" -
	50	[589]	GETTABLE 	14 0 -21	; "item_height"
	51	[589]	SETTABLE 	13 -20 14	; "h" -
	52	[587]	CALL     	11 3 2
	53	[590]	SETTABLE 	10 -1 11	; "dimen" -
	54	[591]	GETTABLE 	11 0 -22	; "show_parent"
	55	[591]	SETTABLE 	10 -22 11	; "show_parent" -
	56	[584]	CALL     	8 3 2
	57	[593]	GETGLOBAL	9 -7	; table
	58	[593]	GETTABLE 	9 9 -8	; "insert"
	59	[593]	GETTABLE 	10 0 -4	; "item_group"
	60	[593]	MOVE     	11 8
	61	[593]	CALL     	9 3 1
	62	[594]	SELF     	9 8 -23	; "isEnabled"
	63	[594]	CALL     	9 2 2
	64	[594]	TEST     	9 0 0
	65	[594]	JMP      	7	; to 73
	66	[595]	GETGLOBAL	9 -7	; table
	67	[595]	GETTABLE 	9 9 -8	; "insert"
	68	[595]	GETTABLE 	10 0 -6	; "layout"
	69	[595]	NEWTABLE 	11 0 1
	70	[595]	GETTABLE 	12 0 -24	; "cur_tab"
	71	[595]	SETTABLE 	11 12 8
	72	[595]	CALL     	9 3 1
	73	[597]	GETTABLE 	9 7 -25	; "separator"
	74	[597]	TEST     	9 0 0
	75	[597]	JMP      	10	; to 86
	76	[597]	GETTABLE 	9 0 -12	; "perpage"
	77	[597]	EQ       	1 5 9
	78	[597]	JMP      	7	; to 86
	79	[599]	GETGLOBAL	9 -7	; table
	80	[599]	GETTABLE 	9 9 -8	; "insert"
	81	[599]	GETTABLE 	10 0 -4	; "item_group"
	82	[599]	GETTABLE 	11 0 -26	; "split_line"
	83	[599]	CALL     	9 3 1
	84	[600]	JMP      	1	; to 86
	85	[603]	JMP      	1	; to 87
	86	[579]	FORLOOP  	2 -58	; to 29
	87	[607]	GETGLOBAL	2 -7	; table
	88	[607]	GETTABLE 	2 2 -8	; "insert"
	89	[607]	GETTABLE 	3 0 -4	; "item_group"
	90	[607]	GETTABLE 	4 0 -27	; "footer_top_margin"
	91	[607]	CALL     	2 3 1
	92	[608]	GETGLOBAL	2 -7	; table
	93	[608]	GETTABLE 	2 2 -8	; "insert"
	94	[608]	GETTABLE 	3 0 -4	; "item_group"
	95	[608]	GETTABLE 	4 0 -28	; "footer"
	96	[608]	CALL     	2 3 1
	97	[609]	GETTABLE 	2 0 -29	; "page_num"
	98	[609]	LT       	0 -11 2	; 1 -
	99	[609]	JMP      	11	; to 111
	100	[611]	GETTABLE 	2 0 -30	; "page_info_text"
	101	[611]	SELF     	2 2 -31	; "setText"
	102	[611]	GETUPVAL 	4 2	; T
	103	[611]	GETUPVAL 	5 3	; _
	104	[611]	LOADK    	6 -32	; "Page %1 of %2"
	105	[611]	CALL     	5 2 2
	106	[611]	GETTABLE 	6 0 -13	; "page"
	107	[611]	GETTABLE 	7 0 -29	; "page_num"
	108	[611]	CALL     	4 4 0
	109	[611]	CALL     	2 0 1
	110	[611]	JMP      	4	; to 115
	111	[613]	GETTABLE 	2 0 -30	; "page_info_text"
	112	[613]	SELF     	2 2 -31	; "setText"
	113	[613]	LOADK    	4 -33	; ""
	114	[613]	CALL     	2 3 1
	115	[615]	GETTABLE 	2 0 -34	; "page_info_left_chev"
	116	[615]	SELF     	2 2 -35	; "showHide"
	117	[615]	GETTABLE 	4 0 -29	; "page_num"
	118	[615]	LT       	1 -11 4	; 1 -
	119	[615]	JMP      	1	; to 121
	120	[615]	LOADBOOL 	4 0 1
	121	[615]	LOADBOOL 	4 1 0
	122	[615]	CALL     	2 3 1
	123	[616]	GETTABLE 	2 0 -36	; "page_info_right_chev"
	124	[616]	SELF     	2 2 -35	; "showHide"
	125	[616]	GETTABLE 	4 0 -29	; "page_num"
	126	[616]	LT       	1 -11 4	; 1 -
	127	[616]	JMP      	1	; to 129
	128	[616]	LOADBOOL 	4 0 1
	129	[616]	LOADBOOL 	4 1 0
	130	[616]	CALL     	2 3 1
	131	[617]	GETTABLE 	2 0 -34	; "page_info_left_chev"
	132	[617]	SELF     	2 2 -37	; "enableDisable"
	133	[617]	GETTABLE 	4 0 -13	; "page"
	134	[617]	LT       	1 -11 4	; 1 -
	135	[617]	JMP      	1	; to 137
	136	[617]	LOADBOOL 	4 0 1
	137	[617]	LOADBOOL 	4 1 0
	138	[617]	CALL     	2 3 1
	139	[618]	GETTABLE 	2 0 -36	; "page_info_right_chev"
	140	[618]	SELF     	2 2 -37	; "enableDisable"
	141	[618]	GETTABLE 	4 0 -13	; "page"
	142	[618]	GETTABLE 	5 0 -29	; "page_num"
	143	[618]	LT       	1 4 5
	144	[618]	JMP      	1	; to 146
	145	[618]	LOADBOOL 	4 0 1
	146	[618]	LOADBOOL 	4 1 0
	147	[618]	CALL     	2 3 1
	148	[620]	LOADNIL  	2 2
	149	[621]	GETGLOBAL	3 -38	; G_reader_settings
	150	[621]	SELF     	3 3 -39	; "nilOrTrue"
	151	[621]	LOADK    	5 -40	; "twelve_hour_clock"
	152	[621]	CALL     	3 3 2
	153	[621]	TEST     	3 0 0
	154	[621]	JMP      	22	; to 177
	155	[622]	GETGLOBAL	3 -41	; os
	156	[622]	GETTABLE 	3 3 -42	; "date"
	157	[622]	LOADK    	4 -43	; "%p"
	158	[622]	CALL     	3 2 2
	159	[622]	EQ       	0 3 -44	; - "AM"
	160	[622]	JMP      	8	; to 169
	161	[624]	GETGLOBAL	3 -41	; os
	162	[624]	GETTABLE 	3 3 -42	; "date"
	163	[624]	GETUPVAL 	4 3	; _
	164	[624]	LOADK    	5 -45	; "%I:%M AM"
	165	[624]	CALL     	4 2 0
	166	[624]	CALL     	3 0 2
	167	[624]	MOVE     	2 3
	168	[624]	JMP      	15	; to 184
	169	[627]	GETGLOBAL	3 -41	; os
	170	[627]	GETTABLE 	3 3 -42	; "date"
	171	[627]	GETUPVAL 	4 3	; _
	172	[627]	LOADK    	5 -46	; "%I:%M PM"
	173	[627]	CALL     	4 2 0
	174	[627]	CALL     	3 0 2
	175	[627]	MOVE     	2 3
	176	[628]	JMP      	7	; to 184
	177	[631]	GETGLOBAL	3 -41	; os
	178	[631]	GETTABLE 	3 3 -42	; "date"
	179	[631]	GETUPVAL 	4 3	; _
	180	[631]	LOADK    	5 -47	; "%H:%M"
	181	[631]	CALL     	4 2 0
	182	[631]	CALL     	3 0 2
	183	[631]	MOVE     	2 3
	184	[633]	GETUPVAL 	3 4	; Device
	185	[633]	SELF     	3 3 -48	; "getPowerDevice"
	186	[633]	CALL     	3 2 2
	187	[634]	SELF     	4 3 -49	; "getCapacity"
	188	[634]	CALL     	4 2 2
	189	[635]	LOADNIL  	5 5
	190	[636]	SELF     	6 3 -50	; "isCharging"
	191	[636]	CALL     	6 2 2
	192	[636]	TEST     	6 0 0
	193	[636]	JMP      	2	; to 196
	194	[637]	LOADK    	5 -51	; "\238\158\131"
	195	[637]	JMP      	41	; to 237
	196	[639]	LE       	0 -52 4	; 100 -
	197	[639]	JMP      	2	; to 200
	198	[640]	LOADK    	5 -53	; "\238\157\184"
	199	[640]	JMP      	37	; to 237
	200	[641]	LE       	0 -54 4	; 90 -
	201	[641]	JMP      	2	; to 204
	202	[642]	LOADK    	5 -55	; "\238\158\129"
	203	[642]	JMP      	33	; to 237
	204	[643]	LE       	0 -56 4	; 80 -
	205	[643]	JMP      	2	; to 208
	206	[644]	LOADK    	5 -57	; "\238\158\128"
	207	[644]	JMP      	29	; to 237
	208	[645]	LE       	0 -58 4	; 70 -
	209	[645]	JMP      	2	; to 212
	210	[646]	LOADK    	5 -59	; "\238\157\191"
	211	[646]	JMP      	25	; to 237
	212	[647]	LE       	0 -60 4	; 60 -
	213	[647]	JMP      	2	; to 216
	214	[648]	LOADK    	5 -61	; "\238\157\190"
	215	[648]	JMP      	21	; to 237
	216	[649]	LE       	0 -62 4	; 50 -
	217	[649]	JMP      	2	; to 220
	218	[650]	LOADK    	5 -63	; "\238\157\189"
	219	[650]	JMP      	17	; to 237
	220	[651]	LE       	0 -64 4	; 40 -
	221	[651]	JMP      	2	; to 224
	222	[652]	LOADK    	5 -65	; "\238\157\188"
	223	[652]	JMP      	13	; to 237
	224	[653]	LE       	0 -66 4	; 30 -
	225	[653]	JMP      	2	; to 228
	226	[654]	LOADK    	5 -67	; "\238\157\187"
	227	[654]	JMP      	9	; to 237
	228	[655]	LE       	0 -68 4	; 20 -
	229	[655]	JMP      	2	; to 232
	230	[656]	LOADK    	5 -69	; "\238\157\186"
	231	[656]	JMP      	5	; to 237
	232	[657]	LE       	0 -70 4	; 10 -
	233	[657]	JMP      	2	; to 236
	234	[658]	LOADK    	5 -71	; "\238\157\185"
	235	[658]	JMP      	1	; to 237
	236	[660]	LOADK    	5 -72	; "\238\158\130"
	237	[663]	GETUPVAL 	6 4	; Device
	238	[663]	SELF     	6 6 -73	; "isDesktop"
	239	[663]	CALL     	6 2 2
	240	[663]	TEST     	6 0 1
	241	[663]	JMP      	20	; to 262
	242	[664]	GETUPVAL 	6 5	; BD
	243	[664]	GETTABLE 	6 6 -74	; "wrap"
	244	[664]	MOVE     	7 2
	245	[664]	CALL     	6 2 2
	246	[664]	LOADK    	7 -75	; " "
	247	[664]	GETUPVAL 	8 5	; BD
	248	[664]	GETTABLE 	8 8 -74	; "wrap"
	249	[664]	LOADK    	9 -76	; "\226\140\129"
	250	[664]	CALL     	8 2 2
	251	[664]	GETUPVAL 	9 5	; BD
	252	[664]	GETTABLE 	9 9 -74	; "wrap"
	253	[664]	MOVE     	10 5
	254	[664]	CALL     	9 2 2
	255	[664]	GETUPVAL 	10 5	; BD
	256	[664]	GETTABLE 	10 10 -74	; "wrap"
	257	[664]	MOVE     	11 4
	258	[664]	LOADK    	12 -77	; "%"
	259	[664]	CONCAT   	11 11 12
	260	[664]	CALL     	10 2 2
	261	[664]	CONCAT   	2 6 10
	262	[666]	GETTABLE 	6 0 -78	; "time_info"
	263	[666]	SELF     	6 6 -31	; "setText"
	264	[666]	MOVE     	8 2
	265	[666]	CALL     	6 3 1
	266	[669]	GETTABLE 	6 0 -1	; "dimen"
	267	[669]	GETTABLE 	7 0 -79	; "width"
	268	[669]	SETTABLE 	6 -18 7	; "w" -
	269	[670]	GETTABLE 	6 0 -1	; "dimen"
	270	[670]	GETTABLE 	7 0 -4	; "item_group"
	271	[670]	SELF     	7 7 -80	; "getSize"
	272	[670]	CALL     	7 2 2
	273	[670]	GETTABLE 	7 7 -20	; "h"
	274	[670]	GETTABLE 	8 0 -81	; "bordersize"
	275	[670]	MUL      	8 8 -82	; - 2
	276	[670]	ADD      	7 7 8
	277	[670]	GETTABLE 	8 0 -83	; "padding"
	278	[670]	MUL      	8 8 -82	; - 2
	279	[670]	ADD      	7 7 8
	280	[670]	SETTABLE 	6 -20 7	; "h" -
	281	[671]	NEWTABLE 	6 0 2
	282	[671]	GETTABLE 	7 0 -24	; "cur_tab"
	283	[671]	SETTABLE 	6 -85 7	; "x" -
	284	[671]	SETTABLE 	6 -86 -11	; "y" 1
	285	[671]	SETTABLE 	0 -84 6	; "selected" -
	286	[677]	TESTSET  	6 1 0
	287	[677]	JMP      	7	; to 295
	288	[677]	GETTABLE 	6 0 -1	; "dimen"
	289	[677]	GETTABLE 	6 6 -20	; "h"
	290	[677]	GETTABLE 	7 1 -20	; "h"
	291	[677]	LE       	1 7 6
	292	[677]	JMP      	1	; to 294
	293	[677]	LOADBOOL 	6 0 1
	294	[677]	LOADBOOL 	6 1 0
	295	[678]	GETUPVAL 	7 6	; UIManager
	296	[678]	SELF     	7 7 -87	; "setDirty"
	297	[678]	GETTABLE 	9 0 -88	; "is_fresh"
	298	[678]	TEST     	9 0 1
	299	[678]	JMP      	2	; to 302
	300	[678]	TEST     	6 0 0
	301	[678]	JMP      	3	; to 305
	302	[678]	GETTABLE 	9 0 -22	; "show_parent"
	303	[678]	TEST     	9 0 1
	304	[678]	JMP      	1	; to 306
	305	[678]	LOADK    	9 -89	; "all"
	306	[690]	CLOSURE  	10 0	; 0x7fb23b40b960
	307	[690]	MOVE     	0 1
	308	[690]	MOVE     	0 0
	309	[678]	CALL     	7 4 1
	310	[691]	RETURN   	0 1

function <./frontend/ui/widget/touchmenu.lua:678,690> (24 instructions, 96 bytes at 0x7fb23b40b960)
0 params, 4 slots, 2 upvalues, 2 locals, 6 constants, 0 functions
	1	[680]	GETUPVAL 	0 0	; old_dimen
	2	[680]	TEST     	0 0 0
	3	[680]	JMP      	7	; to 11
	4	[680]	GETUPVAL 	0 0	; old_dimen
	5	[680]	SELF     	0 0 -1	; "combine"
	6	[680]	GETUPVAL 	2 1	; self
	7	[680]	GETTABLE 	2 2 -2	; "dimen"
	8	[680]	CALL     	0 3 2
	9	[681]	TEST     	0 0 1
	10	[681]	JMP      	2	; to 13
	11	[681]	GETUPVAL 	0 1	; self
	12	[681]	GETTABLE 	0 0 -2	; "dimen"
	13	[682]	LOADK    	1 -3	; "ui"
	14	[683]	GETUPVAL 	2 1	; self
	15	[683]	GETTABLE 	2 2 -4	; "is_fresh"
	16	[683]	TEST     	2 0 0
	17	[683]	JMP      	3	; to 21
	18	[684]	LOADK    	1 -5	; "flashui"
	19	[687]	GETUPVAL 	2 1	; self
	20	[687]	SETTABLE 	2 -4 -6	; "is_fresh" false
	21	[689]	MOVE     	2 1
	22	[689]	MOVE     	3 0
	23	[689]	RETURN   	2 3
	24	[690]	RETURN   	0 1

function <./frontend/ui/widget/touchmenu.lua:693,712> (33 instructions, 132 bytes at 0x7fb23b40c880)
2 params, 4 slots, 0 upvalues, 2 locals, 12 constants, 0 functions
	1	[694]	GETTABLE 	2 0 -1	; "tab_item_table"
	2	[694]	GETTABLE 	2 2 1
	3	[694]	GETTABLE 	2 2 -2	; "remember"
	4	[694]	EQ       	1 2 -3	; - false
	5	[694]	JMP      	1	; to 7
	6	[695]	SETTABLE 	0 -4 1	; "last_index" -
	7	[697]	GETTABLE 	2 0 -5	; "touch_menu_callback"
	8	[697]	TEST     	2 0 0
	9	[697]	JMP      	2	; to 12
	10	[698]	GETTABLE 	2 0 -5	; "touch_menu_callback"
	11	[698]	CALL     	2 1 1
	12	[700]	GETTABLE 	2 0 -1	; "tab_item_table"
	13	[700]	GETTABLE 	2 2 1
	14	[700]	GETTABLE 	2 2 -6	; "callback"
	15	[700]	TEST     	2 0 0
	16	[700]	JMP      	4	; to 21
	17	[701]	GETTABLE 	2 0 -1	; "tab_item_table"
	18	[701]	GETTABLE 	2 2 1
	19	[701]	GETTABLE 	2 2 -6	; "callback"
	20	[701]	CALL     	2 1 1
	21	[703]	GETTABLE 	2 0 -7	; "cur_tab"
	22	[703]	EQ       	1 2 1
	23	[703]	JMP      	9	; to 33
	24	[705]	SETTABLE 	0 -8 -9	; "page" 1
	25	[707]	NEWTABLE 	2 0 0
	26	[707]	SETTABLE 	0 -10 2	; "item_table_stack" -
	27	[708]	SETTABLE 	0 -7 1	; "cur_tab" -
	28	[709]	GETTABLE 	2 0 -1	; "tab_item_table"
	29	[709]	GETTABLE 	2 2 1
	30	[709]	SETTABLE 	0 -11 2	; "item_table" -
	31	[710]	SELF     	2 0 -12	; "updateItems"
	32	[710]	CALL     	2 2 1
	33	[712]	RETURN   	0 1

function <./frontend/ui/widget/touchmenu.lua:714,722> (16 instructions, 64 bytes at 0x7fb23b40d550)
1 param, 3 slots, 0 upvalues, 1 local, 9 constants, 0 functions
	1	[715]	GETTABLE 	1 0 -1	; "item_table_stack"
	2	[715]	LEN      	1 1
	3	[715]	EQ       	1 1 -2	; - 0
	4	[715]	JMP      	9	; to 14
	5	[716]	GETGLOBAL	1 -4	; table
	6	[716]	GETTABLE 	1 1 -5	; "remove"
	7	[716]	GETTABLE 	2 0 -1	; "item_table_stack"
	8	[716]	CALL     	1 2 2
	9	[716]	SETTABLE 	0 -3 1	; "item_table" -
	10	[717]	SETTABLE 	0 -6 -7	; "page" 1
	11	[718]	SELF     	1 0 -8	; "updateItems"
	12	[718]	CALL     	1 2 1
	13	[718]	JMP      	2	; to 16
	14	[720]	SELF     	1 0 -9	; "closeMenu"
	15	[720]	CALL     	1 2 1
	16	[722]	RETURN   	0 1

function <./frontend/ui/widget/touchmenu.lua:724,726> (3 instructions, 12 bytes at 0x7fb23b40db30)
1 param, 2 slots, 0 upvalues, 1 local, 1 constant, 0 functions
	1	[725]	GETTABLE 	1 0 -1	; "close_callback"
	2	[725]	CALL     	1 1 1
	3	[726]	RETURN   	0 1

function <./frontend/ui/widget/touchmenu.lua:728,736> (18 instructions, 72 bytes at 0x7fb23b40e160)
1 param, 3 slots, 0 upvalues, 1 local, 4 constants, 0 functions
	1	[729]	GETTABLE 	1 0 -1	; "page"
	2	[729]	GETTABLE 	2 0 -2	; "page_num"
	3	[729]	LT       	0 1 2
	4	[729]	JMP      	4	; to 9
	5	[730]	GETTABLE 	1 0 -1	; "page"
	6	[730]	ADD      	1 1 -3	; - 1
	7	[730]	SETTABLE 	0 -1 1	; "page" -
	8	[730]	JMP      	5	; to 14
	9	[731]	GETTABLE 	1 0 -1	; "page"
	10	[731]	GETTABLE 	2 0 -2	; "page_num"
	11	[731]	EQ       	0 1 2
	12	[731]	JMP      	1	; to 14
	13	[732]	SETTABLE 	0 -1 -3	; "page" 1
	14	[734]	SELF     	1 0 -4	; "updateItems"
	15	[734]	CALL     	1 2 1
	16	[735]	LOADBOOL 	1 1 0
	17	[735]	RETURN   	1 2
	18	[736]	RETURN   	0 1

function <./frontend/ui/widget/touchmenu.lua:738,746> (17 instructions, 68 bytes at 0x7fb23b40e3c0)
1 param, 3 slots, 0 upvalues, 1 local, 4 constants, 0 functions
	1	[739]	GETTABLE 	1 0 -1	; "page"
	2	[739]	LT       	0 -2 1	; 1 -
	3	[739]	JMP      	4	; to 8
	4	[740]	GETTABLE 	1 0 -1	; "page"
	5	[740]	SUB      	1 1 -2	; - 1
	6	[740]	SETTABLE 	0 -1 1	; "page" -
	7	[740]	JMP      	5	; to 13
	8	[741]	GETTABLE 	1 0 -1	; "page"
	9	[741]	EQ       	0 1 -2	; - 1
	10	[741]	JMP      	2	; to 13
	11	[742]	GETTABLE 	1 0 -3	; "page_num"
	12	[742]	SETTABLE 	0 -1 1	; "page" -
	13	[744]	SELF     	1 0 -4	; "updateItems"
	14	[744]	CALL     	1 2 1
	15	[745]	LOADBOOL 	1 1 0
	16	[745]	RETURN   	1 2
	17	[746]	RETURN   	0 1

function <./frontend/ui/widget/touchmenu.lua:748,757> (19 instructions, 76 bytes at 0x7fb23b40e8c0)
3 params, 6 slots, 1 upvalue, 4 locals, 8 constants, 0 functions
	1	[749]	GETUPVAL 	3 0	; BD
	2	[749]	GETTABLE 	3 3 -1	; "flipDirectionIfMirroredUILayout"
	3	[749]	GETTABLE 	4 2 -2	; "direction"
	4	[749]	CALL     	3 2 2
	5	[750]	EQ       	0 3 -3	; - "west"
	6	[750]	JMP      	3	; to 10
	7	[751]	SELF     	4 0 -4	; "onNextPage"
	8	[751]	CALL     	4 2 1
	9	[751]	JMP      	9	; to 19
	10	[752]	EQ       	0 3 -5	; - "east"
	11	[752]	JMP      	3	; to 15
	12	[753]	SELF     	4 0 -6	; "onPrevPage"
	13	[753]	CALL     	4 2 1
	14	[753]	JMP      	4	; to 19
	15	[754]	EQ       	0 3 -7	; - "north"
	16	[754]	JMP      	2	; to 19
	17	[755]	SELF     	4 0 -8	; "closeMenu"
	18	[755]	CALL     	4 2 1
	19	[757]	RETURN   	0 1

function <./frontend/ui/widget/touchmenu.lua:759,807> (74 instructions, 296 bytes at 0x7fb23b40c780)
2 params, 8 slots, 1 upvalue, 5 locals, 23 constants, 1 function
	1	[760]	GETTABLE 	2 0 -1	; "touch_menu_callback"
	2	[760]	TEST     	2 0 0
	3	[760]	JMP      	2	; to 6
	4	[761]	GETTABLE 	2 0 -1	; "touch_menu_callback"
	5	[761]	CALL     	2 1 1
	6	[763]	GETTABLE 	2 1 -2	; "tap_input"
	7	[763]	TEST     	2 0 1
	8	[763]	JMP      	5	; to 14
	9	[763]	GETGLOBAL	2 -3	; type
	10	[763]	GETTABLE 	3 1 -4	; "tap_input_func"
	11	[763]	CALL     	2 2 2
	12	[763]	EQ       	0 2 -5	; - "function"
	13	[763]	JMP      	17	; to 31
	14	[764]	GETTABLE 	2 1 -6	; "keep_menu_open"
	15	[764]	TEST     	2 0 1
	16	[764]	JMP      	2	; to 19
	17	[765]	SELF     	2 0 -7	; "closeMenu"
	18	[765]	CALL     	2 2 1
	19	[767]	GETTABLE 	2 1 -2	; "tap_input"
	20	[767]	TEST     	2 0 0
	21	[767]	JMP      	4	; to 26
	22	[768]	SELF     	2 0 -8	; "onInput"
	23	[768]	GETTABLE 	4 1 -2	; "tap_input"
	24	[768]	CALL     	2 3 1
	25	[768]	JMP      	46	; to 72
	26	[770]	SELF     	2 0 -8	; "onInput"
	27	[770]	GETTABLE 	4 1 -4	; "tap_input_func"
	28	[770]	CALL     	4 1 0
	29	[770]	CALL     	2 0 1
	30	[771]	JMP      	41	; to 72
	31	[773]	GETTABLE 	2 1 -9	; "sub_item_table"
	32	[774]	GETTABLE 	3 1 -10	; "sub_item_table_func"
	33	[774]	TEST     	3 0 0
	34	[774]	JMP      	3	; to 38
	35	[775]	GETTABLE 	3 1 -10	; "sub_item_table_func"
	36	[775]	CALL     	3 1 2
	37	[775]	MOVE     	2 3
	38	[777]	EQ       	0 2 -11	; - nil
	39	[777]	JMP      	23	; to 63
	40	[779]	GETTABLE 	3 1 -12	; "callback"
	41	[779]	GETTABLE 	4 1 -13	; "checked"
	42	[779]	TEST     	4 0 1
	43	[779]	JMP      	1	; to 45
	44	[779]	GETTABLE 	4 1 -14	; "checked_func"
	45	[780]	GETTABLE 	5 1 -15	; "callback_func"
	46	[780]	TEST     	5 0 0
	47	[780]	JMP      	3	; to 51
	48	[781]	GETTABLE 	5 1 -15	; "callback_func"
	49	[781]	CALL     	5 1 2
	50	[781]	MOVE     	3 5
	51	[783]	TEST     	3 0 0
	52	[783]	JMP      	8	; to 61
	53	[786]	GETUPVAL 	5 0	; UIManager
	54	[786]	SELF     	5 5 -16	; "tickAfterNext"
	55	[797]	CLOSURE  	7 0	; 0x7fb23b40f390
	56	[797]	MOVE     	0 3
	57	[797]	MOVE     	0 0
	58	[797]	MOVE     	0 4
	59	[797]	MOVE     	0 1
	60	[786]	CALL     	5 3 1
	61	[798]	CLOSE    	3
	62	[798]	JMP      	9	; to 72
	63	[800]	GETGLOBAL	3 -17	; table
	64	[800]	GETTABLE 	3 3 -18	; "insert"
	65	[800]	GETTABLE 	4 0 -19	; "item_table_stack"
	66	[800]	GETTABLE 	5 0 -20	; "item_table"
	67	[800]	CALL     	3 3 1
	68	[801]	SETTABLE 	0 -20 2	; "item_table" -
	69	[802]	SETTABLE 	0 -21 -22	; "page" 1
	70	[803]	SELF     	3 0 -23	; "updateItems"
	71	[803]	CALL     	3 2 1
	72	[806]	LOADBOOL 	2 1 0
	73	[806]	RETURN   	2 2
	74	[807]	RETURN   	0 1

function <./frontend/ui/widget/touchmenu.lua:786,797> (18 instructions, 72 bytes at 0x7fb23b40f390)
0 params, 2 slots, 4 upvalues, 0 locals, 3 constants, 0 functions
	1	[791]	GETUPVAL 	0 0	; callback
	2	[791]	GETUPVAL 	1 1	; self
	3	[791]	CALL     	0 2 1
	4	[792]	GETUPVAL 	0 2	; refresh
	5	[792]	TEST     	0 0 0
	6	[792]	JMP      	4	; to 11
	7	[793]	GETUPVAL 	0 1	; self
	8	[793]	SELF     	0 0 -1	; "updateItems"
	9	[793]	CALL     	0 2 1
	10	[793]	JMP      	7	; to 18
	11	[794]	GETUPVAL 	0 3	; item
	12	[794]	GETTABLE 	0 0 -2	; "keep_menu_open"
	13	[794]	TEST     	0 0 1
	14	[794]	JMP      	3	; to 18
	15	[795]	GETUPVAL 	0 1	; self
	16	[795]	SELF     	0 0 -3	; "closeMenu"
	17	[795]	CALL     	0 2 1
	18	[797]	RETURN   	0 1

function <./frontend/ui/widget/touchmenu.lua:809,850> (84 instructions, 336 bytes at 0x7fb23b40f460)
2 params, 8 slots, 2 upvalues, 4 locals, 17 constants, 1 function
	1	[810]	GETTABLE 	2 0 -1	; "touch_menu_callback"
	2	[810]	TEST     	2 0 0
	3	[810]	JMP      	2	; to 6
	4	[811]	GETTABLE 	2 0 -1	; "touch_menu_callback"
	5	[811]	CALL     	2 1 1
	6	[813]	GETTABLE 	2 1 -2	; "hold_input"
	7	[813]	TEST     	2 0 1
	8	[813]	JMP      	5	; to 14
	9	[813]	GETGLOBAL	2 -3	; type
	10	[813]	GETTABLE 	3 1 -4	; "hold_input_func"
	11	[813]	CALL     	2 2 2
	12	[813]	EQ       	0 2 -5	; - "function"
	13	[813]	JMP      	17	; to 31
	14	[814]	GETTABLE 	2 1 -6	; "hold_keep_menu_open"
	15	[814]	EQ       	0 2 -7	; - false
	16	[814]	JMP      	2	; to 19
	17	[815]	SELF     	2 0 -8	; "closeMenu"
	18	[815]	CALL     	2 2 1
	19	[817]	GETTABLE 	2 1 -2	; "hold_input"
	20	[817]	TEST     	2 0 0
	21	[817]	JMP      	4	; to 26
	22	[818]	SELF     	2 0 -9	; "onInput"
	23	[818]	GETTABLE 	4 1 -2	; "hold_input"
	24	[818]	CALL     	2 3 1
	25	[818]	JMP      	56	; to 82
	26	[820]	SELF     	2 0 -9	; "onInput"
	27	[820]	GETTABLE 	4 1 -4	; "hold_input_func"
	28	[820]	CALL     	4 1 0
	29	[820]	CALL     	2 0 1
	30	[821]	JMP      	51	; to 82
	31	[822]	GETTABLE 	2 1 -10	; "hold_callback"
	32	[822]	TEST     	2 0 1
	33	[822]	JMP      	5	; to 39
	34	[822]	GETGLOBAL	2 -3	; type
	35	[822]	GETTABLE 	3 1 -11	; "hold_callback_func"
	36	[822]	CALL     	2 2 2
	37	[822]	EQ       	0 2 -5	; - "function"
	38	[822]	JMP      	18	; to 57
	39	[823]	GETTABLE 	2 1 -10	; "hold_callback"
	40	[824]	GETTABLE 	3 1 -11	; "hold_callback_func"
	41	[824]	TEST     	3 0 0
	42	[824]	JMP      	3	; to 46
	43	[825]	GETTABLE 	3 1 -11	; "hold_callback_func"
	44	[825]	CALL     	3 1 2
	45	[825]	MOVE     	2 3
	46	[827]	TEST     	2 0 0
	47	[827]	JMP      	7	; to 55
	48	[828]	GETUPVAL 	3 0	; UIManager
	49	[828]	SELF     	3 3 -12	; "tickAfterNext"
	50	[838]	CLOSURE  	5 0	; 0x7fb23b40fe50
	51	[838]	MOVE     	0 1
	52	[838]	MOVE     	0 0
	53	[838]	MOVE     	0 2
	54	[828]	CALL     	3 3 1
	55	[839]	CLOSE    	2
	56	[839]	JMP      	25	; to 82
	57	[840]	GETTABLE 	2 1 -13	; "help_text"
	58	[840]	TEST     	2 0 1
	59	[840]	JMP      	5	; to 65
	60	[840]	GETGLOBAL	2 -3	; type
	61	[840]	GETTABLE 	3 1 -14	; "help_text_func"
	62	[840]	CALL     	2 2 2
	63	[840]	EQ       	0 2 -5	; - "function"
	64	[840]	JMP      	17	; to 82
	65	[841]	GETTABLE 	2 1 -13	; "help_text"
	66	[842]	GETTABLE 	3 1 -14	; "help_text_func"
	67	[842]	TEST     	3 0 0
	68	[842]	JMP      	3	; to 72
	69	[843]	GETTABLE 	3 1 -14	; "help_text_func"
	70	[843]	CALL     	3 1 2
	71	[843]	MOVE     	2 3
	72	[845]	TEST     	2 0 0
	73	[845]	JMP      	8	; to 82
	74	[846]	GETUPVAL 	3 0	; UIManager
	75	[846]	SELF     	3 3 -15	; "show"
	76	[846]	GETUPVAL 	5 1	; InfoMessage
	77	[846]	SELF     	5 5 -16	; "new"
	78	[846]	NEWTABLE 	7 0 1
	79	[846]	SETTABLE 	7 -17 2	; "text" -
	80	[846]	CALL     	5 3 0
	81	[846]	CALL     	3 0 1
	82	[849]	LOADBOOL 	2 1 0
	83	[849]	RETURN   	2 2
	84	[850]	RETURN   	0 1

function <./frontend/ui/widget/touchmenu.lua:828,838> (11 instructions, 44 bytes at 0x7fb23b40fe50)
0 params, 2 slots, 3 upvalues, 0 locals, 3 constants, 0 functions
	1	[832]	GETUPVAL 	0 0	; item
	2	[832]	GETTABLE 	0 0 -1	; "hold_keep_menu_open"
	3	[832]	EQ       	0 0 -2	; - false
	4	[832]	JMP      	3	; to 8
	5	[833]	GETUPVAL 	0 1	; self
	6	[833]	SELF     	0 0 -3	; "closeMenu"
	7	[833]	CALL     	0 2 1
	8	[837]	GETUPVAL 	0 2	; callback
	9	[837]	GETUPVAL 	1 1	; self
	10	[837]	CALL     	0 2 1
	11	[838]	RETURN   	0 1

function <./frontend/ui/widget/touchmenu.lua:852,856> (9 instructions, 36 bytes at 0x7fb23b40fed0)
3 params, 6 slots, 0 upvalues, 3 locals, 4 constants, 0 functions
	1	[853]	GETTABLE 	3 2 -1	; "pos"
	2	[853]	SELF     	3 3 -2	; "notIntersectWith"
	3	[853]	GETTABLE 	5 0 -3	; "dimen"
	4	[853]	CALL     	3 3 2
	5	[853]	TEST     	3 0 0
	6	[853]	JMP      	2	; to 9
	7	[854]	SELF     	3 0 -4	; "closeMenu"
	8	[854]	CALL     	3 2 1
	9	[856]	RETURN   	0 1

function <./frontend/ui/widget/touchmenu.lua:858,860> (3 instructions, 12 bytes at 0x7fb23b410a40)
1 param, 3 slots, 0 upvalues, 1 local, 1 constant, 0 functions
	1	[859]	SELF     	1 0 -1	; "closeMenu"
	2	[859]	CALL     	1 2 1
	3	[860]	RETURN   	0 1

function <./frontend/ui/widget/touchmenu.lua:862,864> (3 instructions, 12 bytes at 0x7fb23b410f50)
1 param, 3 slots, 0 upvalues, 1 local, 1 constant, 0 functions
	1	[863]	SELF     	1 0 -1	; "backToUpperMenu"
	2	[863]	CALL     	1 2 1
	3	[864]	RETURN   	0 1

function <./frontend/ui/widget/touchmenu.lua:866,868> (9 instructions, 36 bytes at 0x7fb23b4110f0)
1 param, 6 slots, 1 upvalue, 1 local, 4 constants, 0 functions
	1	[867]	SELF     	1 0 -1	; "getFocusItem"
	2	[867]	CALL     	1 2 2
	3	[867]	SELF     	1 1 -2	; "handleEvent"
	4	[867]	GETUPVAL 	3 0	; Event
	5	[867]	SELF     	3 3 -3	; "new"
	6	[867]	LOADK    	5 -4	; "TapSelect"
	7	[867]	CALL     	3 3 0
	8	[867]	CALL     	1 0 1
	9	[868]	RETURN   	0 1
