
main <./spec/unit/touch_probe_spec.lua:0,0> (5 instructions, 20 bytes at 0x7fc0514068d0)
0+ params, 3 slots, 0 upvalues, 0 locals, 2 constants, 1 function
	1	[1]	GETGLOBAL	0 -1	; describe
	2	[1]	LOADK    	1 -2	; "touch probe module"
	3	[63]	CLOSURE  	2 0	; 0x7fc051406b70
	4	[1]	CALL     	0 3 1
	5	[63]	RETURN   	0 1

function <./spec/unit/touch_probe_spec.lua:1,63> (10 instructions, 40 bytes at 0x7fc051406b70)
0 params, 5 slots, 0 upvalues, 2 locals, 3 constants, 2 functions
	1	[3]	GETGLOBAL	2 -1	; setup
	2	[5]	CLOSURE  	3 0	; 0x7fc051406ee0
	3	[3]	CALL     	2 2 1
	4	[7]	GETGLOBAL	2 -2	; it
	5	[7]	LOADK    	3 -3	; "should probe properly for kobo touch"
	6	[62]	CLOSURE  	4 1	; 0x7fc0514070e0
	7	[62]	MOVE     	0 0
	8	[62]	MOVE     	0 1
	9	[7]	CALL     	2 3 1
	10	[63]	RETURN   	0 1

function <./spec/unit/touch_probe_spec.lua:3,5> (4 instructions, 16 bytes at 0x7fc051406ee0)
0 params, 2 slots, 0 upvalues, 0 locals, 2 constants, 0 functions
	1	[4]	GETGLOBAL	0 -1	; require
	2	[4]	LOADK    	1 -2	; "commonrequire"
	3	[4]	CALL     	0 2 1
	4	[5]	RETURN   	0 1

function <./spec/unit/touch_probe_spec.lua:7,62> (142 instructions, 568 bytes at 0x7fc0514070e0)
0 params, 10 slots, 2 upvalues, 3 locals, 21 constants, 1 function
	1	[8]	GETGLOBAL	0 -1	; require
	2	[8]	LOADK    	1 -2	; "device"
	3	[8]	CALL     	0 2 2
	4	[9]	GETGLOBAL	1 -1	; require
	5	[9]	LOADK    	2 -3	; "tools/kobo_touch_probe"
	6	[9]	CALL     	1 2 2
	7	[9]	SELF     	1 1 -4	; "new"
	8	[9]	NEWTABLE 	3 0 0
	9	[9]	CALL     	1 3 2
	10	[10]	LOADNIL  	2 2
	11	[13]	CLOSURE  	3 0	; 0x7fc051407410
	12	[13]	MOVE     	0 2
	13	[13]	SETTABLE 	1 -5 3	; "saveSwitchXYSetting" -
	14	[16]	GETTABLE 	3 0 -6	; "screen"
	15	[16]	SELF     	3 3 -7	; "getWidth"
	16	[16]	CALL     	3 2 2
	17	[16]	SUB      	3 3 -8	; - 40
	18	[16]	GETTABLE 	4 0 -6	; "screen"
	19	[16]	SELF     	4 4 -9	; "getHeight"
	20	[16]	CALL     	4 2 2
	21	[16]	SUB      	4 4 -8	; - 40
	22	[16]	SETUPVAL 	4 1	; y
	23	[16]	SETUPVAL 	3 0	; x
	24	[17]	LOADNIL  	2 2
	25	[18]	SELF     	3 1 -10	; "onTapProbe"
	26	[18]	LOADNIL  	5 5
	27	[18]	NEWTABLE 	6 0 1
	28	[19]	NEWTABLE 	7 0 2
	29	[20]	GETUPVAL 	8 1	; y
	30	[20]	SETTABLE 	7 -12 8	; "x" -
	31	[21]	GETTABLE 	8 0 -6	; "screen"
	32	[21]	SELF     	8 8 -7	; "getWidth"
	33	[21]	CALL     	8 2 2
	34	[21]	GETUPVAL 	9 0	; x
	35	[21]	SUB      	8 8 9
	36	[21]	SETTABLE 	7 -13 8	; "y" -
	37	[22]	SETTABLE 	6 -11 7	; "pos" -
	38	[18]	CALL     	3 4 1
	39	[24]	GETGLOBAL	3 -14	; assert
	40	[24]	GETTABLE 	3 3 -15	; "is"
	41	[24]	GETTABLE 	3 3 -16	; "same"
	42	[24]	GETTABLE 	4 1 -17	; "curr_probe_step"
	43	[24]	LOADK    	5 -18	; 1
	44	[24]	CALL     	3 3 1
	45	[25]	GETGLOBAL	3 -14	; assert
	46	[25]	GETTABLE 	3 3 -19	; "truthy"
	47	[25]	MOVE     	4 2
	48	[25]	CALL     	3 2 1
	49	[29]	GETTABLE 	3 0 -6	; "screen"
	50	[29]	SELF     	3 3 -7	; "getWidth"
	51	[29]	CALL     	3 2 2
	52	[29]	SUB      	3 3 -8	; - 40
	53	[29]	GETTABLE 	4 0 -6	; "screen"
	54	[29]	SELF     	4 4 -9	; "getHeight"
	55	[29]	CALL     	4 2 2
	56	[29]	SUB      	4 4 -8	; - 40
	57	[29]	SETUPVAL 	4 1	; y
	58	[29]	SETUPVAL 	3 0	; x
	59	[30]	LOADNIL  	2 2
	60	[31]	SELF     	3 1 -10	; "onTapProbe"
	61	[31]	LOADNIL  	5 5
	62	[31]	NEWTABLE 	6 0 1
	63	[32]	NEWTABLE 	7 0 2
	64	[33]	GETTABLE 	8 0 -6	; "screen"
	65	[33]	SELF     	8 8 -7	; "getWidth"
	66	[33]	CALL     	8 2 2
	67	[33]	GETUPVAL 	9 0	; x
	68	[33]	SUB      	8 8 9
	69	[33]	SETTABLE 	7 -12 8	; "x" -
	70	[34]	GETUPVAL 	8 1	; y
	71	[34]	SETTABLE 	7 -13 8	; "y" -
	72	[35]	SETTABLE 	6 -11 7	; "pos" -
	73	[31]	CALL     	3 4 1
	74	[37]	GETGLOBAL	3 -14	; assert
	75	[37]	GETTABLE 	3 3 -15	; "is"
	76	[37]	GETTABLE 	3 3 -16	; "same"
	77	[37]	GETTABLE 	4 1 -17	; "curr_probe_step"
	78	[37]	LOADK    	5 -18	; 1
	79	[37]	CALL     	3 3 1
	80	[38]	GETGLOBAL	3 -14	; assert
	81	[38]	GETTABLE 	3 3 -20	; "falsy"
	82	[38]	MOVE     	4 2
	83	[38]	CALL     	3 2 1
	84	[42]	GETTABLE 	3 0 -6	; "screen"
	85	[42]	SELF     	3 3 -7	; "getWidth"
	86	[42]	CALL     	3 2 2
	87	[42]	SUB      	3 3 -8	; - 40
	88	[42]	GETTABLE 	4 0 -6	; "screen"
	89	[42]	SELF     	4 4 -9	; "getHeight"
	90	[42]	CALL     	4 2 2
	91	[42]	SUB      	4 4 -8	; - 40
	92	[42]	SETUPVAL 	4 1	; y
	93	[42]	SETUPVAL 	3 0	; x
	94	[43]	LOADNIL  	2 2
	95	[44]	SELF     	3 1 -10	; "onTapProbe"
	96	[44]	LOADNIL  	5 5
	97	[44]	NEWTABLE 	6 0 1
	98	[45]	NEWTABLE 	7 0 2
	99	[46]	GETUPVAL 	8 1	; y
	100	[46]	SETTABLE 	7 -12 8	; "x" -
	101	[47]	GETUPVAL 	8 0	; x
	102	[47]	SETTABLE 	7 -13 8	; "y" -
	103	[48]	SETTABLE 	6 -11 7	; "pos" -
	104	[44]	CALL     	3 4 1
	105	[50]	GETGLOBAL	3 -14	; assert
	106	[50]	GETTABLE 	3 3 -15	; "is"
	107	[50]	GETTABLE 	3 3 -16	; "same"
	108	[50]	GETTABLE 	4 1 -17	; "curr_probe_step"
	109	[50]	LOADK    	5 -21	; 2
	110	[50]	CALL     	3 3 1
	111	[51]	GETGLOBAL	3 -14	; assert
	112	[51]	GETTABLE 	3 3 -20	; "falsy"
	113	[51]	MOVE     	4 2
	114	[51]	CALL     	3 2 1
	115	[53]	GETTABLE 	3 0 -6	; "screen"
	116	[53]	SELF     	3 3 -7	; "getWidth"
	117	[53]	CALL     	3 2 2
	118	[53]	SUB      	3 3 -8	; - 40
	119	[53]	LOADK    	4 -8	; 40
	120	[53]	SETUPVAL 	4 1	; y
	121	[53]	SETUPVAL 	3 0	; x
	122	[54]	SELF     	3 1 -10	; "onTapProbe"
	123	[54]	LOADNIL  	5 5
	124	[54]	NEWTABLE 	6 0 1
	125	[55]	NEWTABLE 	7 0 2
	126	[56]	GETUPVAL 	8 1	; y
	127	[56]	SETTABLE 	7 -12 8	; "x" -
	128	[57]	GETUPVAL 	8 0	; x
	129	[57]	SETTABLE 	7 -13 8	; "y" -
	130	[58]	SETTABLE 	6 -11 7	; "pos" -
	131	[54]	CALL     	3 4 1
	132	[60]	GETGLOBAL	3 -14	; assert
	133	[60]	GETTABLE 	3 3 -15	; "is"
	134	[60]	GETTABLE 	3 3 -16	; "same"
	135	[60]	GETTABLE 	4 1 -17	; "curr_probe_step"
	136	[60]	LOADK    	5 -21	; 2
	137	[60]	CALL     	3 3 1
	138	[61]	GETGLOBAL	3 -14	; assert
	139	[61]	GETTABLE 	3 3 -19	; "truthy"
	140	[61]	MOVE     	4 2
	141	[61]	CALL     	3 2 1
	142	[62]	RETURN   	0 1

function <./spec/unit/touch_probe_spec.lua:11,13> (2 instructions, 8 bytes at 0x7fc051407410)
2 params, 2 slots, 1 upvalue, 2 locals, 0 constants, 0 functions
	1	[12]	SETUPVAL 	1 0	; need_to_switch_xy
	2	[13]	RETURN   	0 1
