
main <./tools/trace_require.lua:0,0> (25 instructions, 100 bytes at 0x7f96a24068c0)
0+ params, 9 slots, 0 upvalues, 8 locals, 9 constants, 1 function
	1	[4]	GETGLOBAL	0 -1	; require
	2	[4]	LOADK    	1 -2	; "math"
	3	[4]	CALL     	0 2 2
	4	[5]	GETGLOBAL	1 -1	; require
	5	[7]	NEWTABLE 	2 0 0
	6	[8]	LOADK    	3 -3	; "*"
	7	[10]	LOADK    	4 -4	; 0.001
	8	[12]	LOADBOOL 	5 0 0
	9	[13]	GETGLOBAL	6 -5	; string
	10	[13]	GETTABLE 	6 6 -6	; "rep"
	11	[13]	LOADK    	7 -7	; " "
	12	[13]	LOADK    	8 -8	; 4
	13	[13]	CALL     	6 3 2
	14	[15]	LOADK    	7 -9	; 0
	15	[47]	CLOSURE  	8 0	; 0x7f96a2406be0
	16	[47]	MOVE     	0 7
	17	[47]	MOVE     	0 2
	18	[47]	MOVE     	0 6
	19	[47]	MOVE     	0 5
	20	[47]	MOVE     	0 1
	21	[47]	MOVE     	0 3
	22	[47]	MOVE     	0 0
	23	[47]	MOVE     	0 4
	24	[16]	SETGLOBAL	8 -1	; require
	25	[47]	RETURN   	0 1

function <./tools/trace_require.lua:16,47> (109 instructions, 436 bytes at 0x7f96a2406be0)
1 param, 15 slots, 8 upvalues, 8 locals, 24 constants, 0 functions
	1	[17]	GETUPVAL 	1 0	; level
	2	[17]	ADD      	1 1 -1	; - 1
	3	[17]	SETUPVAL 	1 0	; level
	4	[18]	GETGLOBAL	1 -2	; os
	5	[18]	GETTABLE 	1 1 -3	; "clock"
	6	[18]	CALL     	1 1 2
	7	[19]	GETGLOBAL	2 -4	; debug
	8	[19]	GETTABLE 	2 2 -5	; "getinfo"
	9	[19]	LOADK    	3 -6	; 2
	10	[19]	CALL     	2 2 2
	11	[21]	GETTABLE 	3 2 -7	; "short_src"
	12	[21]	EQ       	0 3 -8	; - "[C]"
	13	[21]	JMP      	5	; to 19
	14	[22]	GETGLOBAL	3 -4	; debug
	15	[22]	GETTABLE 	3 3 -5	; "getinfo"
	16	[22]	LOADK    	4 -9	; 3
	17	[22]	CALL     	3 2 2
	18	[22]	MOVE     	2 3
	19	[24]	GETUPVAL 	3 1	; loaded_modules
	20	[24]	GETTABLE 	3 3 0
	21	[25]	TEST     	3 0 1
	22	[25]	JMP      	14	; to 37
	23	[26]	GETGLOBAL	4 -10	; print
	24	[26]	GETGLOBAL	5 -11	; string
	25	[26]	GETTABLE 	5 5 -12	; "format"
	26	[26]	LOADK    	6 -13	; "%s%s:%s => %s"
	27	[27]	GETUPVAL 	7 2	; indent
	28	[27]	SELF     	7 7 -14	; "rep"
	29	[27]	GETUPVAL 	9 0	; level
	30	[27]	CALL     	7 3 2
	31	[27]	GETTABLE 	8 2 -7	; "short_src"
	32	[27]	GETTABLE 	9 2 -15	; "currentline"
	33	[27]	MOVE     	10 0
	34	[26]	CALL     	5 6 0
	35	[26]	CALL     	4 0 1
	36	[27]	JMP      	16	; to 53
	37	[28]	GETUPVAL 	4 3	; trace_loaded
	38	[28]	TEST     	4 0 0
	39	[28]	JMP      	13	; to 53
	40	[29]	GETGLOBAL	4 -10	; print
	41	[29]	GETGLOBAL	5 -11	; string
	42	[29]	GETTABLE 	5 5 -12	; "format"
	43	[29]	LOADK    	6 -16	; "%s%s:%s -> %s"
	44	[30]	GETUPVAL 	7 2	; indent
	45	[30]	SELF     	7 7 -14	; "rep"
	46	[30]	GETUPVAL 	9 0	; level
	47	[30]	CALL     	7 3 2
	48	[30]	GETTABLE 	8 2 -7	; "short_src"
	49	[30]	GETTABLE 	9 2 -15	; "currentline"
	50	[30]	MOVE     	10 0
	51	[29]	CALL     	5 6 0
	52	[29]	CALL     	4 0 1
	53	[33]	GETGLOBAL	4 -17	; pcall
	54	[33]	GETUPVAL 	5 4	; _require
	55	[33]	MOVE     	6 0
	56	[33]	CALL     	4 3 3
	57	[34]	TEST     	4 0 1
	58	[34]	JMP      	6	; to 65
	59	[35]	GETUPVAL 	6 0	; level
	60	[35]	SUB      	6 6 -1	; - 1
	61	[35]	SETUPVAL 	6 0	; level
	62	[36]	GETGLOBAL	6 -18	; error
	63	[36]	MOVE     	7 5
	64	[36]	CALL     	6 2 1
	65	[38]	GETGLOBAL	6 -2	; os
	66	[38]	GETTABLE 	6 6 -3	; "clock"
	67	[38]	CALL     	6 1 2
	68	[38]	SUB      	6 6 1
	69	[39]	GETUPVAL 	7 5	; highlight
	70	[39]	SELF     	7 7 -14	; "rep"
	71	[39]	GETUPVAL 	9 6	; math
	72	[39]	GETTABLE 	9 9 -19	; "ceil"
	73	[39]	GETUPVAL 	10 6	; math
	74	[39]	GETTABLE 	10 10 -20	; "log10"
	75	[39]	GETUPVAL 	11 7	; threshold
	76	[39]	DIV      	11 6 11
	77	[39]	CALL     	10 2 0
	78	[39]	CALL     	9 0 0
	79	[39]	CALL     	7 0 2
	80	[39]	TEST     	7 0 1
	81	[39]	JMP      	1	; to 83
	82	[39]	LOADK    	7 -21	; ""
	83	[40]	TEST     	3 0 1
	84	[40]	JMP      	18	; to 103
	85	[41]	GETGLOBAL	8 -10	; print
	86	[41]	GETGLOBAL	9 -11	; string
	87	[41]	GETTABLE 	9 9 -12	; "format"
	88	[41]	LOADK    	10 -22	; "%s%s loading time: %.3f"
	89	[42]	MOVE     	11 7
	90	[42]	GETUPVAL 	12 2	; indent
	91	[42]	SELF     	12 12 -14	; "rep"
	92	[42]	GETUPVAL 	14 0	; level
	93	[42]	CALL     	12 3 2
	94	[42]	SELF     	12 12 -23	; "sub"
	95	[42]	LEN      	14 7
	96	[42]	ADD      	14 14 -1	; - 1
	97	[42]	CALL     	12 3 2
	98	[42]	CONCAT   	11 11 12
	99	[42]	MOVE     	12 0
	100	[42]	MOVE     	13 6
	101	[41]	CALL     	9 5 0
	102	[41]	CALL     	8 0 1
	103	[44]	GETUPVAL 	8 1	; loaded_modules
	104	[44]	SETTABLE 	8 0 -24	; - true
	105	[45]	GETUPVAL 	8 0	; level
	106	[45]	SUB      	8 8 -1	; - 1
	107	[45]	SETUPVAL 	8 0	; level
	108	[46]	RETURN   	5 2
	109	[47]	RETURN   	0 1
