
main <./frontend/ui/translator.lua:0,0> (519 instructions, 2076 bytes at 0x7fb33c4068c0)
0+ params, 18 slots, 0 upvalues, 14 locals, 255 constants, 10 functions
	1	[12]	GETGLOBAL	0 -1	; require
	2	[12]	LOADK    	1 -2	; "ui/widget/infomessage"
	3	[12]	CALL     	0 2 2
	4	[13]	GETGLOBAL	1 -1	; require
	5	[13]	LOADK    	2 -3	; "ui/widget/textviewer"
	6	[13]	CALL     	1 2 2
	7	[14]	GETGLOBAL	2 -1	; require
	8	[14]	LOADK    	3 -4	; "ui/uimanager"
	9	[14]	CALL     	2 2 2
	10	[15]	GETGLOBAL	3 -1	; require
	11	[15]	LOADK    	4 -5	; "json"
	12	[15]	CALL     	3 2 2
	13	[16]	GETGLOBAL	4 -1	; require
	14	[16]	LOADK    	5 -6	; "device"
	15	[16]	CALL     	4 2 2
	16	[16]	GETTABLE 	4 4 -7	; "screen"
	17	[17]	GETGLOBAL	5 -1	; require
	18	[17]	LOADK    	6 -8	; "ffi/util"
	19	[17]	CALL     	5 2 2
	20	[18]	GETGLOBAL	6 -1	; require
	21	[18]	LOADK    	7 -9	; "logger"
	22	[18]	CALL     	6 2 2
	23	[19]	GETGLOBAL	7 -1	; require
	24	[19]	LOADK    	8 -10	; "util"
	25	[19]	CALL     	7 2 2
	26	[20]	GETGLOBAL	8 -1	; require
	27	[20]	LOADK    	9 -8	; "ffi/util"
	28	[20]	CALL     	8 2 2
	29	[20]	GETTABLE 	8 8 -11	; "template"
	30	[21]	GETGLOBAL	9 -1	; require
	31	[21]	LOADK    	10 -12	; "gettext"
	32	[21]	CALL     	9 2 2
	33	[25]	LOADK    	10 -13	; "auto"
	34	[26]	NEWTABLE 	11 0 37
	35	[28]	MOVE     	12 9
	36	[28]	LOADK    	13 -15	; "Afrikaans"
	37	[28]	CALL     	12 2 2
	38	[28]	SETTABLE 	11 -14 12	; "af" -
	39	[29]	MOVE     	12 9
	40	[29]	LOADK    	13 -17	; "Albanian"
	41	[29]	CALL     	12 2 2
	42	[29]	SETTABLE 	11 -16 12	; "sq" -
	43	[30]	MOVE     	12 9
	44	[30]	LOADK    	13 -19	; "Amharic"
	45	[30]	CALL     	12 2 2
	46	[30]	SETTABLE 	11 -18 12	; "am" -
	47	[31]	MOVE     	12 9
	48	[31]	LOADK    	13 -21	; "Arabic"
	49	[31]	CALL     	12 2 2
	50	[31]	SETTABLE 	11 -20 12	; "ar" -
	51	[32]	MOVE     	12 9
	52	[32]	LOADK    	13 -23	; "Armenian"
	53	[32]	CALL     	12 2 2
	54	[32]	SETTABLE 	11 -22 12	; "hy" -
	55	[33]	MOVE     	12 9
	56	[33]	LOADK    	13 -25	; "Azerbaijani"
	57	[33]	CALL     	12 2 2
	58	[33]	SETTABLE 	11 -24 12	; "az" -
	59	[34]	MOVE     	12 9
	60	[34]	LOADK    	13 -27	; "Basque"
	61	[34]	CALL     	12 2 2
	62	[34]	SETTABLE 	11 -26 12	; "eu" -
	63	[35]	MOVE     	12 9
	64	[35]	LOADK    	13 -29	; "Belarusian"
	65	[35]	CALL     	12 2 2
	66	[35]	SETTABLE 	11 -28 12	; "be" -
	67	[36]	MOVE     	12 9
	68	[36]	LOADK    	13 -31	; "Bengali"
	69	[36]	CALL     	12 2 2
	70	[36]	SETTABLE 	11 -30 12	; "bn" -
	71	[37]	MOVE     	12 9
	72	[37]	LOADK    	13 -33	; "Bosnian"
	73	[37]	CALL     	12 2 2
	74	[37]	SETTABLE 	11 -32 12	; "bs" -
	75	[38]	MOVE     	12 9
	76	[38]	LOADK    	13 -35	; "Bulgarian"
	77	[38]	CALL     	12 2 2
	78	[38]	SETTABLE 	11 -34 12	; "bg" -
	79	[39]	MOVE     	12 9
	80	[39]	LOADK    	13 -37	; "Catalan"
	81	[39]	CALL     	12 2 2
	82	[39]	SETTABLE 	11 -36 12	; "ca" -
	83	[40]	MOVE     	12 9
	84	[40]	LOADK    	13 -39	; "Cebuano"
	85	[40]	CALL     	12 2 2
	86	[40]	SETTABLE 	11 -38 12	; "ceb" -
	87	[41]	MOVE     	12 9
	88	[41]	LOADK    	13 -41	; "Chinese (Simplified)"
	89	[41]	CALL     	12 2 2
	90	[41]	SETTABLE 	11 -40 12	; "zh" -
	91	[42]	MOVE     	12 9
	92	[42]	LOADK    	13 -43	; "Chinese (Traditional)"
	93	[42]	CALL     	12 2 2
	94	[42]	SETTABLE 	11 -42 12	; "zh_TW" -
	95	[43]	MOVE     	12 9
	96	[43]	LOADK    	13 -45	; "Corsican"
	97	[43]	CALL     	12 2 2
	98	[43]	SETTABLE 	11 -44 12	; "co" -
	99	[44]	MOVE     	12 9
	100	[44]	LOADK    	13 -47	; "Croatian"
	101	[44]	CALL     	12 2 2
	102	[44]	SETTABLE 	11 -46 12	; "hr" -
	103	[45]	MOVE     	12 9
	104	[45]	LOADK    	13 -49	; "Czech"
	105	[45]	CALL     	12 2 2
	106	[45]	SETTABLE 	11 -48 12	; "cs" -
	107	[46]	MOVE     	12 9
	108	[46]	LOADK    	13 -51	; "Danish"
	109	[46]	CALL     	12 2 2
	110	[46]	SETTABLE 	11 -50 12	; "da" -
	111	[47]	MOVE     	12 9
	112	[47]	LOADK    	13 -53	; "Dutch"
	113	[47]	CALL     	12 2 2
	114	[47]	SETTABLE 	11 -52 12	; "nl" -
	115	[48]	MOVE     	12 9
	116	[48]	LOADK    	13 -55	; "English"
	117	[48]	CALL     	12 2 2
	118	[48]	SETTABLE 	11 -54 12	; "en" -
	119	[49]	MOVE     	12 9
	120	[49]	LOADK    	13 -57	; "Esperanto"
	121	[49]	CALL     	12 2 2
	122	[49]	SETTABLE 	11 -56 12	; "eo" -
	123	[50]	MOVE     	12 9
	124	[50]	LOADK    	13 -59	; "Estonian"
	125	[50]	CALL     	12 2 2
	126	[50]	SETTABLE 	11 -58 12	; "et" -
	127	[51]	MOVE     	12 9
	128	[51]	LOADK    	13 -61	; "Finnish"
	129	[51]	CALL     	12 2 2
	130	[51]	SETTABLE 	11 -60 12	; "fi" -
	131	[52]	MOVE     	12 9
	132	[52]	LOADK    	13 -63	; "French"
	133	[52]	CALL     	12 2 2
	134	[52]	SETTABLE 	11 -62 12	; "fr" -
	135	[53]	MOVE     	12 9
	136	[53]	LOADK    	13 -65	; "Frisian"
	137	[53]	CALL     	12 2 2
	138	[53]	SETTABLE 	11 -64 12	; "fy" -
	139	[54]	MOVE     	12 9
	140	[54]	LOADK    	13 -67	; "Galician"
	141	[54]	CALL     	12 2 2
	142	[54]	SETTABLE 	11 -66 12	; "gl" -
	143	[55]	MOVE     	12 9
	144	[55]	LOADK    	13 -69	; "Georgian"
	145	[55]	CALL     	12 2 2
	146	[55]	SETTABLE 	11 -68 12	; "ka" -
	147	[56]	MOVE     	12 9
	148	[56]	LOADK    	13 -71	; "German"
	149	[56]	CALL     	12 2 2
	150	[56]	SETTABLE 	11 -70 12	; "de" -
	151	[57]	MOVE     	12 9
	152	[57]	LOADK    	13 -73	; "Greek"
	153	[57]	CALL     	12 2 2
	154	[57]	SETTABLE 	11 -72 12	; "el" -
	155	[59]	MOVE     	12 9
	156	[59]	LOADK    	13 -75	; "Gujarati"
	157	[59]	CALL     	12 2 2
	158	[59]	SETTABLE 	11 -74 12	; "gu" -
	159	[60]	MOVE     	12 9
	160	[60]	LOADK    	13 -77	; "Haitian Creole"
	161	[60]	CALL     	12 2 2
	162	[60]	SETTABLE 	11 -76 12	; "ht" -
	163	[61]	MOVE     	12 9
	164	[61]	LOADK    	13 -79	; "Hausa"
	165	[61]	CALL     	12 2 2
	166	[61]	SETTABLE 	11 -78 12	; "ha" -
	167	[62]	MOVE     	12 9
	168	[62]	LOADK    	13 -81	; "Hawaiian"
	169	[62]	CALL     	12 2 2
	170	[62]	SETTABLE 	11 -80 12	; "haw" -
	171	[63]	MOVE     	12 9
	172	[63]	LOADK    	13 -83	; "Hebrew"
	173	[63]	CALL     	12 2 2
	174	[63]	SETTABLE 	11 -82 12	; "he" -
	175	[64]	MOVE     	12 9
	176	[64]	LOADK    	13 -85	; "Hindi"
	177	[64]	CALL     	12 2 2
	178	[64]	SETTABLE 	11 -84 12	; "hi" -
	179	[65]	MOVE     	12 9
	180	[65]	LOADK    	13 -87	; "Hmong"
	181	[65]	CALL     	12 2 2
	182	[65]	SETTABLE 	11 -86 12	; "hmn" -
	183	[66]	MOVE     	12 9
	184	[66]	LOADK    	13 -89	; "Hungarian"
	185	[66]	CALL     	12 2 2
	186	[66]	SETTABLE 	11 -88 12	; "hu" -
	187	[67]	MOVE     	12 9
	188	[67]	LOADK    	13 -91	; "Icelandic"
	189	[67]	CALL     	12 2 2
	190	[67]	SETTABLE 	11 -90 12	; "is" -
	191	[68]	MOVE     	12 9
	192	[68]	LOADK    	13 -93	; "Igbo"
	193	[68]	CALL     	12 2 2
	194	[68]	SETTABLE 	11 -92 12	; "ig" -
	195	[69]	MOVE     	12 9
	196	[69]	LOADK    	13 -95	; "Indonesian"
	197	[69]	CALL     	12 2 2
	198	[69]	SETTABLE 	11 -94 12	; "id" -
	199	[70]	MOVE     	12 9
	200	[70]	LOADK    	13 -97	; "Irish"
	201	[70]	CALL     	12 2 2
	202	[70]	SETTABLE 	11 -96 12	; "ga" -
	203	[71]	MOVE     	12 9
	204	[71]	LOADK    	13 -99	; "Italian"
	205	[71]	CALL     	12 2 2
	206	[71]	SETTABLE 	11 -98 12	; "it" -
	207	[72]	MOVE     	12 9
	208	[72]	LOADK    	13 -101	; "Japanese"
	209	[72]	CALL     	12 2 2
	210	[72]	SETTABLE 	11 -100 12	; "ja" -
	211	[73]	MOVE     	12 9
	212	[73]	LOADK    	13 -103	; "Javanese"
	213	[73]	CALL     	12 2 2
	214	[73]	SETTABLE 	11 -102 12	; "jw" -
	215	[75]	MOVE     	12 9
	216	[75]	LOADK    	13 -105	; "Kannada"
	217	[75]	CALL     	12 2 2
	218	[75]	SETTABLE 	11 -104 12	; "kn" -
	219	[76]	MOVE     	12 9
	220	[76]	LOADK    	13 -107	; "Kazakh"
	221	[76]	CALL     	12 2 2
	222	[76]	SETTABLE 	11 -106 12	; "kk" -
	223	[77]	MOVE     	12 9
	224	[77]	LOADK    	13 -109	; "Khmer"
	225	[77]	CALL     	12 2 2
	226	[77]	SETTABLE 	11 -108 12	; "km" -
	227	[78]	MOVE     	12 9
	228	[78]	LOADK    	13 -111	; "Korean"
	229	[78]	CALL     	12 2 2
	230	[78]	SETTABLE 	11 -110 12	; "ko" -
	231	[79]	MOVE     	12 9
	232	[79]	LOADK    	13 -113	; "Kurdish"
	233	[79]	CALL     	12 2 2
	234	[79]	SETTABLE 	11 -112 12	; "ku" -
	235	[80]	MOVE     	12 9
	236	[80]	LOADK    	13 -115	; "Kyrgyz"
	237	[80]	CALL     	12 2 2
	238	[80]	SETTABLE 	11 -114 12	; "ky" -
	239	[81]	MOVE     	12 9
	240	[81]	LOADK    	13 -117	; "Lao"
	241	[81]	CALL     	12 2 2
	242	[81]	SETTABLE 	11 -116 12	; "lo" -
	243	[82]	MOVE     	12 9
	244	[82]	LOADK    	13 -119	; "Latin"
	245	[82]	CALL     	12 2 2
	246	[82]	SETTABLE 	11 -118 12	; "la" -
	247	[83]	MOVE     	12 9
	248	[83]	LOADK    	13 -121	; "Latvian"
	249	[83]	CALL     	12 2 2
	250	[83]	SETTABLE 	11 -120 12	; "lv" -
	251	[84]	MOVE     	12 9
	252	[84]	LOADK    	13 -123	; "Lithuanian"
	253	[84]	CALL     	12 2 2
	254	[84]	SETTABLE 	11 -122 12	; "lt" -
	255	[85]	MOVE     	12 9
	256	[85]	LOADK    	13 -125	; "Luxembourgish"
	257	[85]	CALL     	12 2 2
	258	[85]	SETTABLE 	11 -124 12	; "lb" -
	259	[86]	MOVE     	12 9
	260	[86]	LOADK    	13 -127	; "Macedonian"
	261	[86]	CALL     	12 2 2
	262	[86]	SETTABLE 	11 -126 12	; "mk" -
	263	[87]	MOVE     	12 9
	264	[87]	LOADK    	13 -129	; "Malagasy"
	265	[87]	CALL     	12 2 2
	266	[87]	SETTABLE 	11 -128 12	; "mg" -
	267	[88]	MOVE     	12 9
	268	[88]	LOADK    	13 -131	; "Malay"
	269	[88]	CALL     	12 2 2
	270	[88]	SETTABLE 	11 -130 12	; "ms" -
	271	[89]	MOVE     	12 9
	272	[89]	LOADK    	13 -133	; "Malayalam"
	273	[89]	CALL     	12 2 2
	274	[89]	SETTABLE 	11 -132 12	; "ml" -
	275	[90]	MOVE     	12 9
	276	[90]	LOADK    	13 -135	; "Maltese"
	277	[90]	CALL     	12 2 2
	278	[90]	SETTABLE 	11 -134 12	; "mt" -
	279	[91]	MOVE     	12 9
	280	[91]	LOADK    	13 -137	; "Maori"
	281	[91]	CALL     	12 2 2
	282	[91]	SETTABLE 	11 -136 12	; "mi" -
	283	[92]	MOVE     	12 9
	284	[92]	LOADK    	13 -139	; "Marathi"
	285	[92]	CALL     	12 2 2
	286	[92]	SETTABLE 	11 -138 12	; "mr" -
	287	[93]	MOVE     	12 9
	288	[93]	LOADK    	13 -141	; "Mongolian"
	289	[93]	CALL     	12 2 2
	290	[93]	SETTABLE 	11 -140 12	; "mn" -
	291	[94]	MOVE     	12 9
	292	[94]	LOADK    	13 -143	; "Myanmar (Burmese)"
	293	[94]	CALL     	12 2 2
	294	[94]	SETTABLE 	11 -142 12	; "my" -
	295	[95]	MOVE     	12 9
	296	[95]	LOADK    	13 -145	; "Nepali"
	297	[95]	CALL     	12 2 2
	298	[95]	SETTABLE 	11 -144 12	; "ne" -
	299	[96]	MOVE     	12 9
	300	[96]	LOADK    	13 -147	; "Norwegian"
	301	[96]	CALL     	12 2 2
	302	[96]	SETTABLE 	11 -146 12	; "no" -
	303	[97]	MOVE     	12 9
	304	[97]	LOADK    	13 -149	; "Nyanja (Chichewa)"
	305	[97]	CALL     	12 2 2
	306	[97]	SETTABLE 	11 -148 12	; "ny" -
	307	[98]	MOVE     	12 9
	308	[98]	LOADK    	13 -151	; "Pashto"
	309	[98]	CALL     	12 2 2
	310	[98]	SETTABLE 	11 -150 12	; "ps" -
	311	[99]	MOVE     	12 9
	312	[99]	LOADK    	13 -153	; "Persian"
	313	[99]	CALL     	12 2 2
	314	[99]	SETTABLE 	11 -152 12	; "fa" -
	315	[100]	MOVE     	12 9
	316	[100]	LOADK    	13 -155	; "Polish"
	317	[100]	CALL     	12 2 2
	318	[100]	SETTABLE 	11 -154 12	; "pl" -
	319	[101]	MOVE     	12 9
	320	[101]	LOADK    	13 -157	; "Portuguese"
	321	[101]	CALL     	12 2 2
	322	[101]	SETTABLE 	11 -156 12	; "pt" -
	323	[102]	MOVE     	12 9
	324	[102]	LOADK    	13 -159	; "Punjabi"
	325	[102]	CALL     	12 2 2
	326	[102]	SETTABLE 	11 -158 12	; "pa" -
	327	[103]	MOVE     	12 9
	328	[103]	LOADK    	13 -161	; "Romanian"
	329	[103]	CALL     	12 2 2
	330	[103]	SETTABLE 	11 -160 12	; "ro" -
	331	[104]	MOVE     	12 9
	332	[104]	LOADK    	13 -163	; "Russian"
	333	[104]	CALL     	12 2 2
	334	[104]	SETTABLE 	11 -162 12	; "ru" -
	335	[105]	MOVE     	12 9
	336	[105]	LOADK    	13 -165	; "Samoan"
	337	[105]	CALL     	12 2 2
	338	[105]	SETTABLE 	11 -164 12	; "sm" -
	339	[106]	MOVE     	12 9
	340	[106]	LOADK    	13 -167	; "Scots Gaelic"
	341	[106]	CALL     	12 2 2
	342	[106]	SETTABLE 	11 -166 12	; "gd" -
	343	[107]	MOVE     	12 9
	344	[107]	LOADK    	13 -169	; "Serbian"
	345	[107]	CALL     	12 2 2
	346	[107]	SETTABLE 	11 -168 12	; "sr" -
	347	[108]	MOVE     	12 9
	348	[108]	LOADK    	13 -171	; "Sesotho"
	349	[108]	CALL     	12 2 2
	350	[108]	SETTABLE 	11 -170 12	; "st" -
	351	[109]	MOVE     	12 9
	352	[109]	LOADK    	13 -173	; "Shona"
	353	[109]	CALL     	12 2 2
	354	[109]	SETTABLE 	11 -172 12	; "sn" -
	355	[110]	MOVE     	12 9
	356	[110]	LOADK    	13 -175	; "Sindhi"
	357	[110]	CALL     	12 2 2
	358	[110]	SETTABLE 	11 -174 12	; "sd" -
	359	[111]	MOVE     	12 9
	360	[111]	LOADK    	13 -177	; "Sinhala (Sinhalese)"
	361	[111]	CALL     	12 2 2
	362	[111]	SETTABLE 	11 -176 12	; "si" -
	363	[112]	MOVE     	12 9
	364	[112]	LOADK    	13 -179	; "Slovak"
	365	[112]	CALL     	12 2 2
	366	[112]	SETTABLE 	11 -178 12	; "sk" -
	367	[113]	MOVE     	12 9
	368	[113]	LOADK    	13 -181	; "Slovenian"
	369	[113]	CALL     	12 2 2
	370	[113]	SETTABLE 	11 -180 12	; "sl" -
	371	[114]	MOVE     	12 9
	372	[114]	LOADK    	13 -183	; "Somali"
	373	[114]	CALL     	12 2 2
	374	[114]	SETTABLE 	11 -182 12	; "so" -
	375	[115]	MOVE     	12 9
	376	[115]	LOADK    	13 -185	; "Spanish"
	377	[115]	CALL     	12 2 2
	378	[115]	SETTABLE 	11 -184 12	; "es" -
	379	[116]	MOVE     	12 9
	380	[116]	LOADK    	13 -187	; "Sundanese"
	381	[116]	CALL     	12 2 2
	382	[116]	SETTABLE 	11 -186 12	; "su" -
	383	[117]	MOVE     	12 9
	384	[117]	LOADK    	13 -189	; "Swahili"
	385	[117]	CALL     	12 2 2
	386	[117]	SETTABLE 	11 -188 12	; "sw" -
	387	[118]	MOVE     	12 9
	388	[118]	LOADK    	13 -191	; "Swedish"
	389	[118]	CALL     	12 2 2
	390	[118]	SETTABLE 	11 -190 12	; "sv" -
	391	[119]	MOVE     	12 9
	392	[119]	LOADK    	13 -193	; "Tagalog (Filipino)"
	393	[119]	CALL     	12 2 2
	394	[119]	SETTABLE 	11 -192 12	; "tl" -
	395	[120]	MOVE     	12 9
	396	[120]	LOADK    	13 -195	; "Tajik"
	397	[120]	CALL     	12 2 2
	398	[120]	SETTABLE 	11 -194 12	; "tg" -
	399	[121]	MOVE     	12 9
	400	[121]	LOADK    	13 -197	; "Tamil"
	401	[121]	CALL     	12 2 2
	402	[121]	SETTABLE 	11 -196 12	; "ta" -
	403	[122]	MOVE     	12 9
	404	[122]	LOADK    	13 -199	; "Telugu"
	405	[122]	CALL     	12 2 2
	406	[122]	SETTABLE 	11 -198 12	; "te" -
	407	[123]	MOVE     	12 9
	408	[123]	LOADK    	13 -201	; "Thai"
	409	[123]	CALL     	12 2 2
	410	[123]	SETTABLE 	11 -200 12	; "th" -
	411	[124]	MOVE     	12 9
	412	[124]	LOADK    	13 -203	; "Turkish"
	413	[124]	CALL     	12 2 2
	414	[124]	SETTABLE 	11 -202 12	; "tr" -
	415	[125]	MOVE     	12 9
	416	[125]	LOADK    	13 -205	; "Ukrainian"
	417	[125]	CALL     	12 2 2
	418	[125]	SETTABLE 	11 -204 12	; "uk" -
	419	[126]	MOVE     	12 9
	420	[126]	LOADK    	13 -207	; "Urdu"
	421	[126]	CALL     	12 2 2
	422	[126]	SETTABLE 	11 -206 12	; "ur" -
	423	[127]	MOVE     	12 9
	424	[127]	LOADK    	13 -209	; "Uzbek"
	425	[127]	CALL     	12 2 2
	426	[127]	SETTABLE 	11 -208 12	; "uz" -
	427	[128]	MOVE     	12 9
	428	[128]	LOADK    	13 -211	; "Vietnamese"
	429	[128]	CALL     	12 2 2
	430	[128]	SETTABLE 	11 -210 12	; "vi" -
	431	[129]	MOVE     	12 9
	432	[129]	LOADK    	13 -213	; "Welsh"
	433	[129]	CALL     	12 2 2
	434	[129]	SETTABLE 	11 -212 12	; "cy" -
	435	[131]	MOVE     	12 9
	436	[131]	LOADK    	13 -215	; "Xhosa"
	437	[131]	CALL     	12 2 2
	438	[131]	SETTABLE 	11 -214 12	; "xh" -
	439	[132]	MOVE     	12 9
	440	[132]	LOADK    	13 -217	; "Yiddish"
	441	[132]	CALL     	12 2 2
	442	[132]	SETTABLE 	11 -216 12	; "yi" -
	443	[133]	MOVE     	12 9
	444	[133]	LOADK    	13 -219	; "Yoruba"
	445	[133]	CALL     	12 2 2
	446	[133]	SETTABLE 	11 -218 12	; "yo" -
	447	[134]	MOVE     	12 9
	448	[134]	LOADK    	13 -221	; "Zulu"
	449	[134]	CALL     	12 2 2
	450	[134]	SETTABLE 	11 -220 12	; "zu" -
	451	[137]	GETTABLE 	12 11 -42	; "zh_TW"
	452	[137]	SETTABLE 	11 -222 12	; "zh-TW" -
	453	[138]	SETTABLE 	11 -42 -223	; "zh_TW" nil
	454	[140]	NEWTABLE 	12 0 0
	455	[141]	SETTABLE 	12 -224 -40	; "zh-CN" "zh"
	456	[142]	SETTABLE 	12 -225 -82	; "iw" "he"
	457	[144]	NEWTABLE 	13 0 4
	458	[145]	NEWTABLE 	14 1 0
	459	[148]	LOADK    	15 -227	; "https://translate.googleapis.com/"
	460	[148]	SETLIST  	14 1 1	; 1
	461	[148]	SETTABLE 	13 -226 14	; "trans_servers" -
	462	[149]	SETTABLE 	13 -228 -229	; "trans_path" "/translate_a/single"
	463	[150]	NEWTABLE 	14 0 10
	464	[151]	SETTABLE 	14 -231 -232	; "client" "gtx"
	465	[152]	SETTABLE 	14 -233 -234	; "ie" "UTF-8"
	466	[153]	SETTABLE 	14 -235 -234	; "oe" "UTF-8"
	467	[154]	SETTABLE 	14 -180 -13	; "sl" "auto"
	468	[155]	SETTABLE 	14 -192 -54	; "tl" "en"
	469	[156]	SETTABLE 	14 -236 -54	; "hl" "en"
	470	[157]	SETTABLE 	14 -237 -238	; "otf" 1
	471	[158]	SETTABLE 	14 -239 -240	; "ssel" 0
	472	[159]	SETTABLE 	14 -241 -240	; "tsel" 0
	473	[161]	NEWTABLE 	15 2 0
	474	[162]	LOADK    	16 -243	; "t"
	475	[173]	LOADK    	17 -244	; "at"
	476	[173]	SETLIST  	15 2 1	; 1
	477	[173]	SETTABLE 	14 -242 15	; "dt" -
	478	[175]	SETTABLE 	13 -230 14	; "trans_params" -
	479	[176]	SETTABLE 	13 -245 -54	; "default_lang" "en"
	480	[181]	CLOSURE  	14 0	; 0x7fb33c408c10
	481	[179]	SETTABLE 	13 -246 14	; "getTransServer" -
	482	[192]	CLOSURE  	14 1	; 0x7fb33c408f30
	483	[192]	MOVE     	0 11
	484	[192]	MOVE     	0 12
	485	[183]	SETTABLE 	13 -247 14	; "getLanguageName" -
	486	[251]	CLOSURE  	14 2	; 0x7fb33c409470
	487	[251]	MOVE     	0 5
	488	[251]	MOVE     	0 11
	489	[251]	MOVE     	0 8
	490	[251]	MOVE     	0 9
	491	[195]	SETTABLE 	13 -248 14	; "genSettingsMenu" -
	492	[259]	CLOSURE  	14 3	; 0x7fb33c40bbd0
	493	[259]	MOVE     	0 10
	494	[253]	SETTABLE 	13 -249 14	; "getSourceLanguage" -
	495	[276]	CLOSURE  	14 4	; 0x7fb33c40c140
	496	[261]	SETTABLE 	13 -250 14	; "getTargetLanguage" -
	497	[351]	CLOSURE  	14 5	; 0x7fb33c40c7a0
	498	[351]	MOVE     	0 6
	499	[351]	MOVE     	0 3
	500	[286]	SETTABLE 	13 -251 14	; "loadPage" -
	501	[382]	CLOSURE  	14 6	; 0x7fb33c40cec0
	502	[382]	MOVE     	0 10
	503	[382]	MOVE     	0 6
	504	[373]	SETTABLE 	13 -252 14	; "detect" -
	505	[408]	CLOSURE  	14 7	; 0x7fb33c40d5d0
	506	[392]	SETTABLE 	13 -253 14	; "translate" -
	507	[429]	CLOSURE  	14 8	; 0x7fb33c40d7d0
	508	[417]	SETTABLE 	13 -254 14	; "showTranslation" -
	509	[505]	CLOSURE  	14 9	; 0x7fb33c40dc50
	510	[505]	MOVE     	0 9
	511	[505]	MOVE     	0 2
	512	[505]	MOVE     	0 0
	513	[505]	MOVE     	0 7
	514	[505]	MOVE     	0 1
	515	[505]	MOVE     	0 8
	516	[505]	MOVE     	0 4
	517	[431]	SETTABLE 	13 -255 14	; "_showTranslation" -
	518	[507]	RETURN   	13 2
	519	[507]	RETURN   	0 1

function <./frontend/ui/translator.lua:179,181> (10 instructions, 40 bytes at 0x7fb33c408c10)
1 param, 4 slots, 0 upvalues, 1 local, 5 constants, 0 functions
	1	[180]	GETGLOBAL	1 -1	; G_reader_settings
	2	[180]	SELF     	1 1 -2	; "readSetting"
	3	[180]	LOADK    	3 -3	; "trans_server"
	4	[180]	CALL     	1 3 2
	5	[180]	TEST     	1 0 1
	6	[180]	JMP      	2	; to 9
	7	[180]	GETTABLE 	1 0 -4	; "trans_servers"
	8	[180]	GETTABLE 	1 1 -5	; 1
	9	[180]	RETURN   	1 2
	10	[181]	RETURN   	0 1

function <./frontend/ui/translator.lua:183,192> (25 instructions, 100 bytes at 0x7fb33c408f30)
3 params, 5 slots, 2 upvalues, 3 locals, 1 constant, 0 functions
	1	[184]	GETUPVAL 	3 0	; SUPPORTED_LANGUAGES
	2	[184]	GETTABLE 	3 3 1
	3	[184]	TEST     	3 0 0
	4	[184]	JMP      	4	; to 9
	5	[185]	GETUPVAL 	3 0	; SUPPORTED_LANGUAGES
	6	[185]	GETTABLE 	3 3 1
	7	[185]	RETURN   	3 2
	8	[185]	JMP      	15	; to 24
	9	[186]	GETUPVAL 	3 1	; ALT_LANGUAGE_CODES
	10	[186]	GETTABLE 	3 3 1
	11	[186]	TEST     	3 0 0
	12	[186]	JMP      	6	; to 19
	13	[187]	GETUPVAL 	3 0	; SUPPORTED_LANGUAGES
	14	[187]	GETUPVAL 	4 1	; ALT_LANGUAGE_CODES
	15	[187]	GETTABLE 	4 4 1
	16	[187]	GETTABLE 	3 3 4
	17	[187]	RETURN   	3 2
	18	[187]	JMP      	5	; to 24
	19	[188]	TEST     	1 0 0
	20	[188]	JMP      	3	; to 24
	21	[189]	SELF     	3 1 -1	; "upper"
	22	[189]	TAILCALL 	3 2 0
	23	[189]	RETURN   	3 0
	24	[191]	RETURN   	2 2
	25	[192]	RETURN   	0 1

function <./frontend/ui/translator.lua:195,251> (50 instructions, 200 bytes at 0x7fb33c409470)
1 param, 11 slots, 4 upvalues, 2 locals, 14 constants, 6 functions
	1	[216]	CLOSURE  	1 0	; 0x7fb33c409910
	2	[216]	GETUPVAL 	0 0	; ffiutil
	3	[216]	GETUPVAL 	0 1	; SUPPORTED_LANGUAGES
	4	[216]	GETUPVAL 	0 2	; T
	5	[217]	NEWTABLE 	2 0 2
	6	[218]	GETUPVAL 	3 3	; _
	7	[218]	LOADK    	4 -2	; "Translation settings"
	8	[218]	CALL     	3 2 2
	9	[218]	SETTABLE 	2 -1 3	; "text" -
	10	[219]	NEWTABLE 	3 3 0
	11	[219]	NEWTABLE 	4 0 3
	12	[221]	GETUPVAL 	5 3	; _
	13	[221]	LOADK    	6 -4	; "Auto-detect source language"
	14	[221]	CALL     	5 2 2
	15	[221]	SETTABLE 	4 -1 5	; "text" -
	16	[224]	CLOSURE  	5 1	; 0x7fb33c40a9b0
	17	[224]	SETTABLE 	4 -5 5	; "checked_func" -
	18	[227]	CLOSURE  	5 2	; 0x7fb33c40b020
	19	[227]	SETTABLE 	4 -6 5	; "callback" -
	20	[228]	NEWTABLE 	5 0 5
	21	[233]	CLOSURE  	6 3	; 0x7fb33c40b1c0
	22	[233]	GETUPVAL 	0 2	; T
	23	[233]	GETUPVAL 	0 3	; _
	24	[233]	MOVE     	0 0
	25	[233]	SETTABLE 	5 -7 6	; "text_func" -
	26	[236]	CLOSURE  	6 4	; 0x7fb33c40b4b0
	27	[236]	SETTABLE 	5 -8 6	; "enabled_func" -
	28	[237]	MOVE     	6 1
	29	[237]	LOADK    	7 -9	; "translator_from_language"
	30	[237]	CALL     	6 2 2
	31	[237]	SETTABLE 	5 -3 6	; "sub_item_table" -
	32	[238]	SETTABLE 	5 -10 -11	; "keep_menu_open" true
	33	[239]	SETTABLE 	5 -12 -11	; "separator" true
	34	[240]	NEWTABLE 	6 0 3
	35	[245]	CLOSURE  	7 5	; 0x7fb33c40afa0
	36	[245]	MOVE     	0 0
	37	[245]	GETUPVAL 	0 2	; T
	38	[245]	GETUPVAL 	0 3	; _
	39	[245]	SETTABLE 	6 -7 7	; "text_func" -
	40	[246]	MOVE     	7 1
	41	[246]	LOADK    	8 -13	; "translator_to_language"
	42	[246]	SELF     	9 0 -14	; "getTargetLanguage"
	43	[246]	CALL     	9 2 0
	44	[246]	CALL     	7 0 2
	45	[246]	SETTABLE 	6 -3 7	; "sub_item_table" -
	46	[247]	SETTABLE 	6 -10 -11	; "keep_menu_open" true
	47	[249]	SETLIST  	3 3 1	; 1
	48	[249]	SETTABLE 	2 -3 3	; "sub_item_table" -
	49	[250]	RETURN   	2 2
	50	[251]	RETURN   	0 1

function <./frontend/ui/translator.lua:196,216> (30 instructions, 120 bytes at 0x7fb33c409910)
2 params, 12 slots, 3 upvalues, 8 locals, 6 constants, 3 functions
	1	[197]	NEWTABLE 	2 0 0
	2	[198]	GETUPVAL 	3 0	; ffiutil
	3	[198]	GETTABLE 	3 3 -1	; "orderedPairs"
	4	[198]	GETUPVAL 	4 1	; SUPPORTED_LANGUAGES
	5	[198]	CALL     	3 2 4
	6	[198]	JMP      	20	; to 27
	7	[199]	GETGLOBAL	8 -2	; table
	8	[199]	GETTABLE 	8 8 -3	; "insert"
	9	[199]	MOVE     	9 2
	10	[199]	NEWTABLE 	10 0 3
	11	[202]	CLOSURE  	11 0	; 0x7fb33c409d60
	12	[202]	GETUPVAL 	0 2	; T
	13	[202]	MOVE     	0 7
	14	[202]	MOVE     	0 6
	15	[202]	SETTABLE 	10 -4 11	; "text_func" -
	16	[209]	CLOSURE  	11 1	; 0x7fb33c409ea0
	17	[209]	MOVE     	0 0
	18	[209]	MOVE     	0 6
	19	[209]	MOVE     	0 1
	20	[209]	SETTABLE 	10 -5 11	; "checked_func" -
	21	[212]	CLOSURE  	11 2	; 0x7fb33c40a2e0
	22	[212]	MOVE     	0 0
	23	[212]	MOVE     	0 6
	24	[212]	SETTABLE 	10 -6 11	; "callback" -
	25	[199]	CALL     	8 3 1
	26	[213]	CLOSE    	6
	27	[198]	TFORLOOP 	3 2
	28	[213]	JMP      	-22	; to 7
	29	[215]	RETURN   	2 2
	30	[216]	RETURN   	0 1

function <./frontend/ui/translator.lua:200,202> (7 instructions, 28 bytes at 0x7fb33c409d60)
0 params, 4 slots, 3 upvalues, 0 locals, 1 constant, 0 functions
	1	[201]	GETUPVAL 	0 0	; T
	2	[201]	LOADK    	1 -1	; "%1 (%2)"
	3	[201]	GETUPVAL 	2 1	; lang_name
	4	[201]	GETUPVAL 	3 2	; lang_key
	5	[201]	TAILCALL 	0 4 0
	6	[201]	RETURN   	0 0
	7	[202]	RETURN   	0 1

function <./frontend/ui/translator.lua:203,209> (25 instructions, 100 bytes at 0x7fb33c409ea0)
0 params, 4 slots, 3 upvalues, 0 locals, 2 constants, 0 functions
	1	[204]	GETGLOBAL	0 -1	; G_reader_settings
	2	[204]	SELF     	0 0 -2	; "readSetting"
	3	[204]	GETUPVAL 	2 0	; setting_name
	4	[204]	CALL     	0 3 2
	5	[204]	TEST     	0 0 0
	6	[204]	JMP      	11	; to 18
	7	[205]	GETUPVAL 	0 1	; lang_key
	8	[205]	GETGLOBAL	1 -1	; G_reader_settings
	9	[205]	SELF     	1 1 -2	; "readSetting"
	10	[205]	GETUPVAL 	3 0	; setting_name
	11	[205]	CALL     	1 3 2
	12	[205]	EQ       	1 0 1
	13	[205]	JMP      	1	; to 15
	14	[205]	LOADBOOL 	0 0 1
	15	[205]	LOADBOOL 	0 1 0
	16	[205]	RETURN   	0 2
	17	[205]	JMP      	7	; to 25
	18	[207]	GETUPVAL 	0 1	; lang_key
	19	[207]	GETUPVAL 	1 2	; default_checked_item
	20	[207]	EQ       	1 0 1
	21	[207]	JMP      	1	; to 23
	22	[207]	LOADBOOL 	0 0 1
	23	[207]	LOADBOOL 	0 1 0
	24	[207]	RETURN   	0 2
	25	[209]	RETURN   	0 1

function <./frontend/ui/translator.lua:210,212> (6 instructions, 24 bytes at 0x7fb33c40a2e0)
0 params, 4 slots, 2 upvalues, 0 locals, 2 constants, 0 functions
	1	[211]	GETGLOBAL	0 -1	; G_reader_settings
	2	[211]	SELF     	0 0 -2	; "saveSetting"
	3	[211]	GETUPVAL 	2 0	; setting_name
	4	[211]	GETUPVAL 	3 1	; lang_key
	5	[211]	CALL     	0 4 1
	6	[212]	RETURN   	0 1

function <./frontend/ui/translator.lua:222,224> (6 instructions, 24 bytes at 0x7fb33c40a9b0)
0 params, 3 slots, 0 upvalues, 0 locals, 3 constants, 0 functions
	1	[223]	GETGLOBAL	0 -1	; G_reader_settings
	2	[223]	SELF     	0 0 -2	; "nilOrTrue"
	3	[223]	LOADK    	2 -3	; "translator_from_auto_detect"
	4	[223]	TAILCALL 	0 3 0
	5	[223]	RETURN   	0 0
	6	[224]	RETURN   	0 1

function <./frontend/ui/translator.lua:225,227> (5 instructions, 20 bytes at 0x7fb33c40b020)
0 params, 3 slots, 0 upvalues, 0 locals, 3 constants, 0 functions
	1	[226]	GETGLOBAL	0 -1	; G_reader_settings
	2	[226]	SELF     	0 0 -2	; "flipNilOrTrue"
	3	[226]	LOADK    	2 -3	; "translator_from_auto_detect"
	4	[226]	CALL     	0 3 1
	5	[227]	RETURN   	0 1

function <./frontend/ui/translator.lua:230,233> (16 instructions, 64 bytes at 0x7fb33c40b1c0)
0 params, 7 slots, 3 upvalues, 1 local, 6 constants, 0 functions
	1	[231]	GETGLOBAL	0 -1	; G_reader_settings
	2	[231]	SELF     	0 0 -2	; "readSetting"
	3	[231]	LOADK    	2 -3	; "translator_from_language"
	4	[231]	CALL     	0 3 2
	5	[232]	GETUPVAL 	1 0	; T
	6	[232]	GETUPVAL 	2 1	; _
	7	[232]	LOADK    	3 -4	; "Translate from: %1"
	8	[232]	CALL     	2 2 2
	9	[232]	GETUPVAL 	3 2	; self
	10	[232]	SELF     	3 3 -5	; "getLanguageName"
	11	[232]	MOVE     	5 0
	12	[232]	LOADK    	6 -6	; ""
	13	[232]	CALL     	3 4 0
	14	[232]	TAILCALL 	1 0 0
	15	[232]	RETURN   	1 0
	16	[233]	RETURN   	0 1

function <./frontend/ui/translator.lua:234,236> (7 instructions, 28 bytes at 0x7fb33c40b4b0)
0 params, 3 slots, 0 upvalues, 0 locals, 3 constants, 0 functions
	1	[235]	GETGLOBAL	0 -1	; G_reader_settings
	2	[235]	SELF     	0 0 -2	; "nilOrTrue"
	3	[235]	LOADK    	2 -3	; "translator_from_auto_detect"
	4	[235]	CALL     	0 3 2
	5	[235]	NOT      	0 0
	6	[235]	RETURN   	0 2
	7	[236]	RETURN   	0 1

function <./frontend/ui/translator.lua:242,245> (15 instructions, 60 bytes at 0x7fb33c40afa0)
0 params, 7 slots, 3 upvalues, 1 local, 4 constants, 0 functions
	1	[243]	GETUPVAL 	0 0	; self
	2	[243]	SELF     	0 0 -1	; "getTargetLanguage"
	3	[243]	CALL     	0 2 2
	4	[244]	GETUPVAL 	1 1	; T
	5	[244]	GETUPVAL 	2 2	; _
	6	[244]	LOADK    	3 -2	; "Translate to: %1"
	7	[244]	CALL     	2 2 2
	8	[244]	GETUPVAL 	3 0	; self
	9	[244]	SELF     	3 3 -3	; "getLanguageName"
	10	[244]	MOVE     	5 0
	11	[244]	LOADK    	6 -4	; ""
	12	[244]	CALL     	3 4 0
	13	[244]	TAILCALL 	1 0 0
	14	[244]	RETURN   	1 0
	15	[245]	RETURN   	0 1

function <./frontend/ui/translator.lua:253,259> (20 instructions, 80 bytes at 0x7fb33c40bbd0)
1 param, 4 slots, 1 upvalue, 1 local, 5 constants, 0 functions
	1	[254]	GETGLOBAL	1 -1	; G_reader_settings
	2	[254]	SELF     	1 1 -2	; "isFalse"
	3	[254]	LOADK    	3 -3	; "translator_from_auto_detect"
	4	[254]	CALL     	1 3 2
	5	[254]	TEST     	1 0 0
	6	[254]	JMP      	11	; to 18
	7	[255]	GETGLOBAL	1 -1	; G_reader_settings
	8	[255]	SELF     	1 1 -4	; "readSetting"
	9	[255]	LOADK    	3 -5	; "translator_from_language"
	10	[255]	CALL     	1 3 2
	11	[255]	TEST     	1 0 0
	12	[255]	JMP      	5	; to 18
	13	[256]	GETGLOBAL	1 -1	; G_reader_settings
	14	[256]	SELF     	1 1 -4	; "readSetting"
	15	[256]	LOADK    	3 -5	; "translator_from_language"
	16	[256]	TAILCALL 	1 3 0
	17	[256]	RETURN   	1 0
	18	[258]	GETUPVAL 	1 0	; AUTODETECT_LANGUAGE
	19	[258]	RETURN   	1 2
	20	[259]	RETURN   	0 1

function <./frontend/ui/translator.lua:261,276> (31 instructions, 124 bytes at 0x7fb33c40c140)
1 param, 5 slots, 0 upvalues, 2 locals, 10 constants, 0 functions
	1	[262]	GETGLOBAL	1 -1	; G_reader_settings
	2	[262]	SELF     	1 1 -2	; "readSetting"
	3	[262]	LOADK    	3 -3	; "translator_to_language"
	4	[262]	CALL     	1 3 2
	5	[263]	TEST     	1 0 1
	6	[263]	JMP      	20	; to 27
	7	[265]	GETGLOBAL	2 -1	; G_reader_settings
	8	[265]	SELF     	2 2 -2	; "readSetting"
	9	[265]	LOADK    	4 -4	; "language"
	10	[265]	CALL     	2 3 2
	11	[265]	MOVE     	1 2
	12	[266]	TEST     	1 0 0
	13	[266]	JMP      	13	; to 27
	14	[266]	EQ       	1 1 -5	; - ""
	15	[266]	JMP      	11	; to 27
	16	[268]	SELF     	2 1 -6	; "match"
	17	[268]	LOADK    	4 -7	; "(.*)-"
	18	[268]	CALL     	2 3 2
	19	[268]	TESTSET  	1 2 1
	20	[268]	JMP      	0	; to 21
	21	[269]	EQ       	0 1 -8	; - "C"
	22	[269]	JMP      	1	; to 24
	23	[270]	LOADK    	1 -9	; "en"
	24	[272]	SELF     	2 1 -10	; "lower"
	25	[272]	CALL     	2 2 2
	26	[272]	MOVE     	1 2
	27	[275]	TESTSET  	2 1 1
	28	[275]	JMP      	1	; to 30
	29	[275]	LOADK    	2 -9	; "en"
	30	[275]	RETURN   	2 2
	31	[276]	RETURN   	0 1

function <./frontend/ui/translator.lua:286,351> (154 instructions, 616 bytes at 0x7fb33c40c7a0)
4 params, 27 slots, 2 upvalues, 31 locals, 53 constants, 0 functions
	1	[287]	GETGLOBAL	4 -1	; require
	2	[287]	LOADK    	5 -2	; "socket"
	3	[287]	CALL     	4 2 2
	4	[288]	GETGLOBAL	5 -1	; require
	5	[288]	LOADK    	6 -3	; "socket.url"
	6	[288]	CALL     	5 2 2
	7	[289]	GETGLOBAL	6 -1	; require
	8	[289]	LOADK    	7 -4	; "socket.http"
	9	[289]	CALL     	6 2 2
	10	[290]	GETGLOBAL	7 -1	; require
	11	[290]	LOADK    	8 -5	; "ssl.https"
	12	[290]	CALL     	7 2 2
	13	[291]	GETGLOBAL	8 -1	; require
	14	[291]	LOADK    	9 -6	; "ltn12"
	15	[291]	CALL     	8 2 2
	16	[293]	NEWTABLE 	9 0 0
	17	[293]	NEWTABLE 	10 0 0
	18	[294]	LOADK    	11 -7	; ""
	19	[295]	GETTABLE 	12 0 -8	; "trans_params"
	20	[295]	SETTABLE 	12 -9 2	; "tl" -
	21	[296]	GETTABLE 	12 0 -8	; "trans_params"
	22	[296]	SETTABLE 	12 -10 3	; "sl" -
	23	[297]	GETGLOBAL	12 -11	; pairs
	24	[297]	GETTABLE 	13 0 -8	; "trans_params"
	25	[297]	CALL     	12 2 4
	26	[297]	JMP      	24	; to 51
	27	[298]	GETGLOBAL	17 -12	; type
	28	[298]	MOVE     	18 16
	29	[298]	CALL     	17 2 2
	30	[298]	EQ       	0 17 -13	; - "table"
	31	[298]	JMP      	13	; to 45
	32	[299]	GETGLOBAL	17 -14	; ipairs
	33	[299]	MOVE     	18 16
	34	[299]	CALL     	17 2 4
	35	[299]	JMP      	6	; to 42
	36	[300]	MOVE     	22 11
	37	[300]	MOVE     	23 15
	38	[300]	LOADK    	24 -15	; "="
	39	[300]	MOVE     	25 21
	40	[300]	LOADK    	26 -16	; "&"
	41	[300]	CONCAT   	11 22 26
	42	[299]	TFORLOOP 	17 2
	43	[300]	JMP      	-8	; to 36
	44	[301]	JMP      	6	; to 51
	45	[303]	MOVE     	17 11
	46	[303]	MOVE     	18 15
	47	[303]	LOADK    	19 -15	; "="
	48	[303]	MOVE     	20 16
	49	[303]	LOADK    	21 -16	; "&"
	50	[303]	CONCAT   	11 17 21
	51	[297]	TFORLOOP 	12 2
	52	[304]	JMP      	-26	; to 27
	53	[306]	GETTABLE 	12 5 -17	; "parse"
	54	[306]	SELF     	13 0 -18	; "getTransServer"
	55	[306]	CALL     	13 2 0
	56	[306]	CALL     	12 0 2
	57	[307]	GETTABLE 	13 0 -20	; "trans_path"
	58	[307]	SETTABLE 	12 -19 13	; "path" -
	59	[308]	MOVE     	13 11
	60	[308]	LOADK    	14 -22	; "q="
	61	[308]	GETTABLE 	15 5 -23	; "escape"
	62	[308]	MOVE     	16 1
	63	[308]	CALL     	15 2 2
	64	[308]	CONCAT   	13 13 15
	65	[308]	SETTABLE 	12 -21 13	; "query" -
	66	[311]	GETTABLE 	13 5 -25	; "build"
	67	[311]	MOVE     	14 12
	68	[311]	CALL     	13 2 2
	69	[311]	SETTABLE 	9 -24 13	; "url" -
	70	[312]	GETUPVAL 	13 0	; logger
	71	[312]	GETTABLE 	13 13 -26	; "dbg"
	72	[312]	LOADK    	14 -27	; "Calling"
	73	[312]	GETTABLE 	15 9 -24	; "url"
	74	[312]	CALL     	13 3 1
	75	[313]	SETTABLE 	9 -28 -29	; "method" "GET"
	76	[314]	GETTABLE 	13 8 -30	; "sink"
	77	[314]	GETTABLE 	13 13 -13	; "table"
	78	[314]	MOVE     	14 10
	79	[314]	CALL     	13 2 2
	80	[314]	SETTABLE 	9 -30 13	; "sink" -
	81	[319]	LOADK    	13 -32	; 10
	82	[319]	SETTABLE 	7 -31 -32	; "TIMEOUT" 10
	83	[319]	SETTABLE 	6 -31 13	; "TIMEOUT" -
	84	[320]	GETTABLE 	13 12 -33	; "scheme"
	85	[320]	EQ       	0 13 -34	; - "http"
	86	[320]	JMP      	3	; to 90
	87	[320]	GETTABLE 	13 6 -35	; "request"
	88	[320]	TEST     	13 0 1
	89	[320]	JMP      	1	; to 91
	90	[320]	GETTABLE 	13 7 -35	; "request"
	91	[322]	GETTABLE 	14 4 -36	; "skip"
	92	[322]	LOADK    	15 -37	; 1
	93	[322]	MOVE     	16 13
	94	[322]	MOVE     	17 9
	95	[322]	CALL     	16 2 0
	96	[322]	CALL     	14 0 4
	97	[325]	EQ       	0 15 -38	; - nil
	98	[325]	JMP      	3	; to 102
	99	[326]	GETGLOBAL	17 -39	; error
	100	[326]	LOADK    	18 -40	; "Network is unreachable"
	101	[326]	CALL     	17 2 1
	102	[329]	EQ       	1 16 -41	; - "HTTP/1.1 200 OK"
	103	[329]	JMP      	6	; to 110
	104	[330]	GETUPVAL 	17 0	; logger
	105	[330]	GETTABLE 	17 17 -42	; "warn"
	106	[330]	LOADK    	18 -43	; "translator HTTP status not okay:"
	107	[330]	MOVE     	19 16
	108	[330]	CALL     	17 3 1
	109	[331]	RETURN   	0 1
	110	[334]	GETGLOBAL	17 -13	; table
	111	[334]	GETTABLE 	17 17 -44	; "concat"
	112	[334]	MOVE     	18 10
	113	[334]	CALL     	17 2 2
	114	[336]	SELF     	18 17 -45	; "sub"
	115	[336]	LOADK    	20 -37	; 1
	116	[336]	LOADK    	21 -37	; 1
	117	[336]	CALL     	18 4 2
	118	[337]	EQ       	1 17 -7	; - ""
	119	[337]	JMP      	29	; to 149
	120	[337]	EQ       	1 18 -46	; - "{"
	121	[337]	JMP      	2	; to 124
	122	[337]	EQ       	0 18 -47	; - "["
	123	[337]	JMP      	25	; to 149
	124	[341]	GETGLOBAL	19 -48	; pcall
	125	[341]	GETUPVAL 	20 1	; JSON
	126	[341]	GETTABLE 	20 20 -49	; "decode"
	127	[341]	MOVE     	21 17
	128	[341]	GETUPVAL 	22 1	; JSON
	129	[341]	GETTABLE 	22 22 -49	; "decode"
	130	[341]	GETTABLE 	22 22 -50	; "simple"
	131	[341]	CALL     	19 4 3
	132	[342]	TEST     	19 0 0
	133	[342]	JMP      	9	; to 143
	134	[342]	TEST     	20 0 0
	135	[342]	JMP      	7	; to 143
	136	[343]	GETUPVAL 	21 0	; logger
	137	[343]	GETTABLE 	21 21 -26	; "dbg"
	138	[343]	LOADK    	22 -51	; "translator json:"
	139	[343]	MOVE     	23 20
	140	[343]	CALL     	21 3 1
	141	[344]	RETURN   	20 2
	142	[344]	JMP      	11	; to 154
	143	[346]	GETUPVAL 	21 0	; logger
	144	[346]	GETTABLE 	21 21 -42	; "warn"
	145	[346]	LOADK    	22 -52	; "translator error:"
	146	[346]	MOVE     	23 20
	147	[346]	CALL     	21 3 1
	148	[347]	JMP      	5	; to 154
	149	[349]	GETUPVAL 	19 0	; logger
	150	[349]	GETTABLE 	19 19 -42	; "warn"
	151	[349]	LOADK    	20 -53	; "not JSON in translator response:"
	152	[349]	MOVE     	21 17
	153	[349]	CALL     	19 3 1
	154	[351]	RETURN   	0 1

function <./frontend/ui/translator.lua:373,382> (21 instructions, 84 bytes at 0x7fb33c40cec0)
2 params, 7 slots, 2 upvalues, 4 locals, 6 constants, 0 functions
	1	[374]	SELF     	2 0 -1	; "loadPage"
	2	[374]	MOVE     	4 1
	3	[374]	LOADK    	5 -2	; "en"
	4	[374]	GETUPVAL 	6 0	; AUTODETECT_LANGUAGE
	5	[374]	CALL     	2 5 2
	6	[375]	TEST     	2 0 0
	7	[375]	JMP      	11	; to 19
	8	[375]	GETTABLE 	3 2 -3	; 3
	9	[375]	TEST     	3 0 0
	10	[375]	JMP      	8	; to 19
	11	[376]	GETTABLE 	3 2 -3	; 3
	12	[377]	GETUPVAL 	4 1	; logger
	13	[377]	GETTABLE 	4 4 -4	; "dbg"
	14	[377]	LOADK    	5 -5	; "detected language:"
	15	[377]	MOVE     	6 3
	16	[377]	CALL     	4 3 1
	17	[378]	RETURN   	3 2
	18	[378]	JMP      	2	; to 21
	19	[380]	GETTABLE 	3 0 -6	; "default_lang"
	20	[380]	RETURN   	3 2
	21	[382]	RETURN   	0 1

function <./frontend/ui/translator.lua:392,408> (46 instructions, 184 bytes at 0x7fb33c40d5d0)
4 params, 14 slots, 0 upvalues, 11 locals, 10 constants, 0 functions
	1	[393]	TEST     	2 0 1
	2	[393]	JMP      	3	; to 6
	3	[394]	SELF     	4 0 -1	; "getTargetLanguage"
	4	[394]	CALL     	4 2 2
	5	[394]	MOVE     	2 4
	6	[396]	TEST     	3 0 1
	7	[396]	JMP      	3	; to 11
	8	[397]	SELF     	4 0 -2	; "getSourceLanguage"
	9	[397]	CALL     	4 2 2
	10	[397]	MOVE     	3 4
	11	[399]	SELF     	4 0 -3	; "loadPage"
	12	[399]	MOVE     	6 1
	13	[399]	MOVE     	7 2
	14	[399]	MOVE     	8 3
	15	[399]	CALL     	4 5 2
	16	[400]	TEST     	4 0 0
	17	[400]	JMP      	26	; to 44
	18	[400]	GETTABLE 	5 4 -4	; 1
	19	[400]	TEST     	5 0 0
	20	[400]	JMP      	23	; to 44
	21	[400]	GETGLOBAL	5 -5	; type
	22	[400]	GETTABLE 	6 4 -4	; 1
	23	[400]	CALL     	5 2 2
	24	[400]	EQ       	0 5 -6	; - "table"
	25	[400]	JMP      	18	; to 44
	26	[401]	NEWTABLE 	5 0 0
	27	[402]	GETGLOBAL	6 -7	; ipairs
	28	[402]	GETTABLE 	7 4 -4	; 1
	29	[402]	CALL     	6 2 4
	30	[402]	JMP      	5	; to 36
	31	[403]	GETGLOBAL	11 -6	; table
	32	[403]	GETTABLE 	11 11 -8	; "insert"
	33	[403]	MOVE     	12 5
	34	[403]	GETTABLE 	13 10 -4	; 1
	35	[403]	CALL     	11 3 1
	36	[402]	TFORLOOP 	6 2
	37	[403]	JMP      	-7	; to 31
	38	[405]	GETGLOBAL	6 -6	; table
	39	[405]	GETTABLE 	6 6 -9	; "concat"
	40	[405]	MOVE     	7 5
	41	[405]	LOADK    	8 -10	; ""
	42	[405]	TAILCALL 	6 3 0
	43	[405]	RETURN   	6 0
	44	[407]	LOADNIL  	5 5
	45	[407]	RETURN   	5 2
	46	[408]	RETURN   	0 1

function <./frontend/ui/translator.lua:417,429> (21 instructions, 84 bytes at 0x7fb33c40d7d0)
4 params, 9 slots, 0 upvalues, 6 locals, 6 constants, 1 function
	1	[418]	GETGLOBAL	4 -1	; require
	2	[418]	LOADK    	5 -2	; "ui/network/manager"
	3	[418]	CALL     	4 2 2
	4	[419]	SELF     	5 4 -3	; "isOnline"
	5	[419]	CALL     	5 2 2
	6	[419]	TEST     	5 0 1
	7	[419]	JMP      	3	; to 11
	8	[420]	SELF     	5 4 -4	; "promptWifiOn"
	9	[420]	CALL     	5 2 1
	10	[421]	RETURN   	0 1
	11	[425]	GETGLOBAL	5 -1	; require
	12	[425]	LOADK    	6 -5	; "ui/trapper"
	13	[425]	CALL     	5 2 2
	14	[426]	SELF     	6 5 -6	; "wrap"
	15	[428]	CLOSURE  	8 0	; 0x7fb33c40dea0
	16	[428]	MOVE     	0 0
	17	[428]	MOVE     	0 1
	18	[428]	MOVE     	0 2
	19	[428]	MOVE     	0 3
	20	[426]	CALL     	6 3 1
	21	[429]	RETURN   	0 1

function <./frontend/ui/translator.lua:426,428> (7 instructions, 28 bytes at 0x7fb33c40dea0)
0 params, 5 slots, 4 upvalues, 0 locals, 1 constant, 0 functions
	1	[427]	GETUPVAL 	0 0	; self
	2	[427]	SELF     	0 0 -1	; "_showTranslation"
	3	[427]	GETUPVAL 	2 1	; text
	4	[427]	GETUPVAL 	3 2	; target_lang
	5	[427]	GETUPVAL 	4 3	; source_lang
	6	[427]	CALL     	0 5 1
	7	[428]	RETURN   	0 1

function <./frontend/ui/translator.lua:431,505> (255 instructions, 1020 bytes at 0x7fb33c40dc50)
4 params, 26 slots, 7 upvalues, 30 locals, 44 constants, 1 function
	1	[432]	TEST     	2 0 1
	2	[432]	JMP      	3	; to 6
	3	[433]	SELF     	4 0 -1	; "getTargetLanguage"
	4	[433]	CALL     	4 2 2
	5	[433]	MOVE     	2 4
	6	[435]	TEST     	3 0 1
	7	[435]	JMP      	3	; to 11
	8	[436]	SELF     	4 0 -2	; "getSourceLanguage"
	9	[436]	CALL     	4 2 2
	10	[436]	MOVE     	3 4
	11	[439]	GETGLOBAL	4 -3	; require
	12	[439]	LOADK    	5 -4	; "ui/trapper"
	13	[439]	CALL     	4 2 2
	14	[440]	SELF     	5 4 -5	; "dismissableRunInSubprocess"
	15	[442]	CLOSURE  	7 0	; 0x7fb33c40e490
	16	[442]	MOVE     	0 0
	17	[442]	MOVE     	0 1
	18	[442]	MOVE     	0 2
	19	[442]	MOVE     	0 3
	20	[442]	GETUPVAL 	8 0	; _
	21	[442]	LOADK    	9 -6	; "Querying translation service\226\128\166"
	22	[442]	CALL     	8 2 0
	23	[440]	CALL     	5 0 3
	24	[443]	TEST     	5 0 1
	25	[443]	JMP      	12	; to 38
	26	[444]	GETUPVAL 	7 1	; UIManager
	27	[444]	SELF     	7 7 -7	; "show"
	28	[444]	GETUPVAL 	9 2	; InfoMessage
	29	[444]	SELF     	9 9 -8	; "new"
	30	[444]	NEWTABLE 	11 0 1
	31	[445]	GETUPVAL 	12 0	; _
	32	[445]	LOADK    	13 -10	; "Translation interrupted."
	33	[445]	CALL     	12 2 2
	34	[445]	SETTABLE 	11 -9 12	; "text" -
	35	[444]	CALL     	9 3 0
	36	[444]	CALL     	7 0 1
	37	[447]	RETURN   	0 1
	38	[449]	TEST     	6 0 0
	39	[449]	JMP      	5	; to 45
	40	[449]	GETGLOBAL	7 -11	; type
	41	[449]	MOVE     	8 6
	42	[449]	CALL     	7 2 2
	43	[449]	EQ       	1 7 -12	; - "table"
	44	[449]	JMP      	12	; to 57
	45	[450]	GETUPVAL 	7 1	; UIManager
	46	[450]	SELF     	7 7 -7	; "show"
	47	[450]	GETUPVAL 	9 2	; InfoMessage
	48	[450]	SELF     	9 9 -8	; "new"
	49	[450]	NEWTABLE 	11 0 1
	50	[451]	GETUPVAL 	12 0	; _
	51	[451]	LOADK    	13 -13	; "Translation failed."
	52	[451]	CALL     	12 2 2
	53	[451]	SETTABLE 	11 -9 12	; "text" -
	54	[450]	CALL     	9 3 0
	55	[450]	CALL     	7 0 1
	56	[453]	RETURN   	0 1
	57	[456]	GETTABLE 	7 6 -14	; 3
	58	[456]	TEST     	7 0 0
	59	[456]	JMP      	1	; to 61
	60	[457]	GETTABLE 	3 6 -14	; 3
	61	[459]	NEWTABLE 	7 0 0
	62	[463]	GETTABLE 	8 6 -15	; 1
	63	[463]	TEST     	8 0 0
	64	[463]	JMP      	67	; to 132
	65	[463]	GETGLOBAL	8 -11	; type
	66	[463]	GETTABLE 	9 6 -15	; 1
	67	[463]	CALL     	8 2 2
	68	[463]	EQ       	0 8 -12	; - "table"
	69	[463]	JMP      	62	; to 132
	70	[463]	GETTABLE 	8 6 -15	; 1
	71	[463]	LEN      	8 8
	72	[463]	LT       	0 -16 8	; 0 -
	73	[463]	JMP      	58	; to 132
	74	[466]	NEWTABLE 	8 0 0
	75	[467]	NEWTABLE 	9 0 0
	76	[468]	GETGLOBAL	10 -17	; ipairs
	77	[468]	GETTABLE 	11 6 -15	; 1
	78	[468]	CALL     	10 2 4
	79	[468]	JMP      	28	; to 108
	80	[469]	GETGLOBAL	15 -11	; type
	81	[469]	GETTABLE 	16 14 -18	; 2
	82	[469]	CALL     	15 2 2
	83	[469]	EQ       	0 15 -19	; - "string"
	84	[469]	JMP      	3	; to 88
	85	[469]	GETTABLE 	15 14 -18	; 2
	86	[469]	TEST     	15 0 1
	87	[469]	JMP      	1	; to 89
	88	[469]	LOADK    	15 -20	; ""
	89	[470]	GETGLOBAL	16 -11	; type
	90	[470]	GETTABLE 	17 14 -15	; 1
	91	[470]	CALL     	16 2 2
	92	[470]	EQ       	0 16 -19	; - "string"
	93	[470]	JMP      	3	; to 97
	94	[470]	GETTABLE 	16 14 -15	; 1
	95	[470]	TEST     	16 0 1
	96	[470]	JMP      	1	; to 98
	97	[470]	LOADK    	16 -20	; ""
	98	[471]	GETGLOBAL	17 -12	; table
	99	[471]	GETTABLE 	17 17 -21	; "insert"
	100	[471]	MOVE     	18 8
	101	[471]	MOVE     	19 15
	102	[471]	CALL     	17 3 1
	103	[472]	GETGLOBAL	17 -12	; table
	104	[472]	GETTABLE 	17 17 -21	; "insert"
	105	[472]	MOVE     	18 9
	106	[472]	MOVE     	19 16
	107	[472]	CALL     	17 3 1
	108	[468]	TFORLOOP 	10 2
	109	[472]	JMP      	-30	; to 80
	110	[474]	GETGLOBAL	10 -12	; table
	111	[474]	GETTABLE 	10 10 -21	; "insert"
	112	[474]	MOVE     	11 7
	113	[474]	LOADK    	12 -22	; "\226\150\163 "
	114	[474]	GETGLOBAL	13 -12	; table
	115	[474]	GETTABLE 	13 13 -23	; "concat"
	116	[474]	MOVE     	14 8
	117	[474]	LOADK    	15 -24	; " "
	118	[474]	CALL     	13 3 2
	119	[474]	CONCAT   	12 12 13
	120	[474]	CALL     	10 3 1
	121	[475]	GETGLOBAL	10 -12	; table
	122	[475]	GETTABLE 	10 10 -21	; "insert"
	123	[475]	MOVE     	11 7
	124	[475]	LOADK    	12 -25	; "\226\151\143 "
	125	[475]	GETGLOBAL	13 -12	; table
	126	[475]	GETTABLE 	13 13 -23	; "concat"
	127	[475]	MOVE     	14 9
	128	[475]	LOADK    	15 -24	; " "
	129	[475]	CALL     	13 3 2
	130	[475]	CONCAT   	12 12 13
	131	[475]	CALL     	10 3 1
	132	[478]	GETTABLE 	8 6 -26	; 6
	133	[478]	TEST     	8 0 0
	134	[478]	JMP      	86	; to 221
	135	[478]	GETGLOBAL	8 -11	; type
	136	[478]	GETTABLE 	9 6 -26	; 6
	137	[478]	CALL     	8 2 2
	138	[478]	EQ       	0 8 -12	; - "table"
	139	[478]	JMP      	81	; to 221
	140	[478]	GETTABLE 	8 6 -26	; 6
	141	[478]	LEN      	8 8
	142	[478]	LT       	0 -16 8	; 0 -
	143	[478]	JMP      	77	; to 221
	144	[480]	GETGLOBAL	8 -12	; table
	145	[480]	GETTABLE 	8 8 -21	; "insert"
	146	[480]	MOVE     	9 7
	147	[480]	LOADK    	10 -27	; "________"
	148	[480]	CALL     	8 3 1
	149	[481]	GETGLOBAL	8 -17	; ipairs
	150	[481]	GETTABLE 	9 6 -26	; 6
	151	[481]	CALL     	8 2 4
	152	[481]	JMP      	66	; to 219
	153	[482]	GETGLOBAL	13 -11	; type
	154	[482]	GETTABLE 	14 12 -14	; 3
	155	[482]	CALL     	13 2 2
	156	[482]	EQ       	0 13 -12	; - "table"
	157	[482]	JMP      	56	; to 214
	158	[483]	GETGLOBAL	13 -11	; type
	159	[483]	GETTABLE 	14 12 -15	; 1
	160	[483]	CALL     	13 2 2
	161	[483]	EQ       	0 13 -19	; - "string"
	162	[483]	JMP      	7	; to 170
	163	[483]	GETTABLE 	13 12 -15	; 1
	164	[483]	SELF     	13 13 -28	; "gsub"
	165	[483]	LOADK    	15 -29	; "\n"
	166	[483]	LOADK    	16 -20	; ""
	167	[483]	CALL     	13 4 2
	168	[483]	TEST     	13 0 1
	169	[483]	JMP      	1	; to 171
	170	[483]	LOADK    	13 -20	; ""
	171	[484]	GETGLOBAL	14 -12	; table
	172	[484]	GETTABLE 	14 14 -21	; "insert"
	173	[484]	MOVE     	15 7
	174	[484]	LOADK    	16 -22	; "\226\150\163 "
	175	[484]	MOVE     	17 13
	176	[484]	CONCAT   	16 16 17
	177	[484]	CALL     	14 3 1
	178	[485]	GETGLOBAL	14 -17	; ipairs
	179	[485]	GETTABLE 	15 12 -14	; 3
	180	[485]	CALL     	14 2 4
	181	[485]	JMP      	30	; to 212
	182	[487]	GETUPVAL 	19 3	; util
	183	[487]	GETTABLE 	19 19 -30	; "unicodeCodepointToUtf8"
	184	[487]	LT       	0 17 -31	; - 10
	185	[487]	JMP      	2	; to 188
	186	[487]	TESTSET  	20 17 1
	187	[487]	JMP      	1	; to 189
	188	[487]	LOADK    	20 -31	; 10
	189	[487]	ADD      	20 -32 20	; 10101 -
	190	[487]	CALL     	19 2 2
	191	[488]	GETGLOBAL	20 -11	; type
	192	[488]	GETTABLE 	21 18 -15	; 1
	193	[488]	CALL     	20 2 2
	194	[488]	EQ       	0 20 -19	; - "string"
	195	[488]	JMP      	7	; to 203
	196	[488]	GETTABLE 	20 18 -15	; 1
	197	[488]	SELF     	20 20 -28	; "gsub"
	198	[488]	LOADK    	22 -29	; "\n"
	199	[488]	LOADK    	23 -20	; ""
	200	[488]	CALL     	20 4 2
	201	[488]	TEST     	20 0 1
	202	[488]	JMP      	1	; to 204
	203	[488]	LOADK    	20 -20	; ""
	204	[489]	GETGLOBAL	21 -12	; table
	205	[489]	GETTABLE 	21 21 -21	; "insert"
	206	[489]	MOVE     	22 7
	207	[489]	MOVE     	23 19
	208	[489]	LOADK    	24 -24	; " "
	209	[489]	MOVE     	25 20
	210	[489]	CONCAT   	23 23 25
	211	[489]	CALL     	21 3 1
	212	[485]	TFORLOOP 	14 2
	213	[489]	JMP      	-32	; to 182
	214	[492]	GETGLOBAL	13 -12	; table
	215	[492]	GETTABLE 	13 13 -21	; "insert"
	216	[492]	MOVE     	14 7
	217	[492]	LOADK    	15 -20	; ""
	218	[492]	CALL     	13 3 1
	219	[481]	TFORLOOP 	8 2
	220	[492]	JMP      	-68	; to 153
	221	[497]	GETUPVAL 	8 1	; UIManager
	222	[497]	SELF     	8 8 -7	; "show"
	223	[497]	GETUPVAL 	10 4	; TextViewer
	224	[497]	SELF     	10 10 -8	; "new"
	225	[497]	NEWTABLE 	12 0 4
	226	[498]	GETUPVAL 	13 5	; T
	227	[498]	GETUPVAL 	14 0	; _
	228	[498]	LOADK    	15 -34	; "Translation from %1"
	229	[498]	CALL     	14 2 2
	230	[498]	SELF     	15 0 -35	; "getLanguageName"
	231	[498]	MOVE     	17 3
	232	[498]	LOADK    	18 -36	; "?"
	233	[498]	CALL     	15 4 0
	234	[498]	CALL     	13 0 2
	235	[498]	SETTABLE 	12 -33 13	; "title" -
	236	[501]	GETGLOBAL	13 -12	; table
	237	[501]	GETTABLE 	13 13 -23	; "concat"
	238	[501]	MOVE     	14 7
	239	[501]	LOADK    	15 -29	; "\n"
	240	[501]	CALL     	13 3 2
	241	[501]	SETTABLE 	12 -9 13	; "text" -
	242	[502]	GETUPVAL 	13 6	; Screen
	243	[502]	SELF     	13 13 -38	; "getHeight"
	244	[502]	CALL     	13 2 2
	245	[502]	MUL      	13 13 -39	; - 4
	246	[502]	DIV      	13 13 -40	; - 5
	247	[502]	SETTABLE 	12 -37 13	; "height" -
	248	[503]	GETGLOBAL	13 -42	; G_reader_settings
	249	[503]	SELF     	13 13 -43	; "nilOrTrue"
	250	[503]	LOADK    	15 -44	; "dict_justify"
	251	[503]	CALL     	13 3 2
	252	[503]	SETTABLE 	12 -41 13	; "justified" -
	253	[497]	CALL     	10 3 0
	254	[497]	CALL     	8 0 1
	255	[505]	RETURN   	0 1

function <./frontend/ui/translator.lua:440,442> (8 instructions, 32 bytes at 0x7fb33c40e490)
0 params, 5 slots, 4 upvalues, 0 locals, 1 constant, 0 functions
	1	[441]	GETUPVAL 	0 0	; self
	2	[441]	SELF     	0 0 -1	; "loadPage"
	3	[441]	GETUPVAL 	2 1	; text
	4	[441]	GETUPVAL 	3 2	; target_lang
	5	[441]	GETUPVAL 	4 3	; source_lang
	6	[441]	TAILCALL 	0 5 0
	7	[441]	RETURN   	0 0
	8	[442]	RETURN   	0 1
