
main <./frontend/ui/widget/trapwidget.lua:0,0> (94 instructions, 376 bytes at 0x7faaa7c068d0)
0+ params, 23 slots, 0 upvalues, 18 locals, 37 constants, 9 functions
	1	[10]	GETGLOBAL	0 -1	; require
	2	[10]	LOADK    	1 -2	; "ffi/blitbuffer"
	3	[10]	CALL     	0 2 2
	4	[11]	GETGLOBAL	1 -1	; require
	5	[11]	LOADK    	2 -3	; "ui/widget/container/bottomcontainer"
	6	[11]	CALL     	1 2 2
	7	[12]	GETGLOBAL	2 -1	; require
	8	[12]	LOADK    	3 -4	; "ui/widget/container/centercontainer"
	9	[12]	CALL     	2 2 2
	10	[13]	GETGLOBAL	3 -1	; require
	11	[13]	LOADK    	4 -5	; "device"
	12	[13]	CALL     	3 2 2
	13	[14]	GETGLOBAL	4 -1	; require
	14	[14]	LOADK    	5 -6	; "ui/event"
	15	[14]	CALL     	4 2 2
	16	[15]	GETGLOBAL	5 -1	; require
	17	[15]	LOADK    	6 -7	; "ui/font"
	18	[15]	CALL     	5 2 2
	19	[16]	GETGLOBAL	6 -1	; require
	20	[16]	LOADK    	7 -8	; "ui/widget/container/framecontainer"
	21	[16]	CALL     	6 2 2
	22	[17]	GETGLOBAL	7 -1	; require
	23	[17]	LOADK    	8 -9	; "ui/geometry"
	24	[17]	CALL     	7 2 2
	25	[18]	GETGLOBAL	8 -1	; require
	26	[18]	LOADK    	9 -10	; "ui/gesturerange"
	27	[18]	CALL     	8 2 2
	28	[19]	GETGLOBAL	9 -1	; require
	29	[19]	LOADK    	10 -11	; "ui/widget/container/inputcontainer"
	30	[19]	CALL     	9 2 2
	31	[20]	GETGLOBAL	10 -1	; require
	32	[20]	LOADK    	11 -12	; "ui/widget/container/leftcontainer"
	33	[20]	CALL     	10 2 2
	34	[21]	GETGLOBAL	11 -1	; require
	35	[21]	LOADK    	12 -13	; "ui/size"
	36	[21]	CALL     	11 2 2
	37	[22]	GETGLOBAL	12 -1	; require
	38	[22]	LOADK    	13 -14	; "ui/widget/textboxwidget"
	39	[22]	CALL     	12 2 2
	40	[23]	GETGLOBAL	13 -1	; require
	41	[23]	LOADK    	14 -15	; "ui/widget/textwidget"
	42	[23]	CALL     	13 2 2
	43	[24]	GETGLOBAL	14 -1	; require
	44	[24]	LOADK    	15 -16	; "ui/uimanager"
	45	[24]	CALL     	14 2 2
	46	[25]	GETTABLE 	15 3 -17	; "input"
	47	[26]	GETTABLE 	16 3 -18	; "screen"
	48	[28]	SELF     	17 9 -19	; "new"
	49	[28]	NEWTABLE 	19 0 5
	50	[29]	SETTABLE 	19 -20 -21	; "modal" true
	51	[30]	CLOSURE  	20 0	; 0x7faaa7c070e0
	52	[30]	SETTABLE 	19 -22 20	; "dismiss_callback" -
	53	[31]	SETTABLE 	19 -23 -24	; "text" nil
	54	[32]	SELF     	20 5 -26	; "getFace"
	55	[32]	LOADK    	22 -27	; "infofont"
	56	[32]	CALL     	20 3 2
	57	[32]	SETTABLE 	19 -25 20	; "face" -
	58	[34]	SETTABLE 	19 -28 -29	; "resend_event" false
	59	[28]	CALL     	17 3 2
	60	[109]	CLOSURE  	18 1	; 0x7faaa7c076b0
	61	[109]	MOVE     	0 7
	62	[109]	MOVE     	0 16
	63	[109]	MOVE     	0 3
	64	[109]	MOVE     	0 15
	65	[109]	MOVE     	0 8
	66	[109]	MOVE     	0 13
	67	[109]	MOVE     	0 12
	68	[109]	MOVE     	0 11
	69	[109]	MOVE     	0 6
	70	[109]	MOVE     	0 0
	71	[109]	MOVE     	0 2
	72	[109]	MOVE     	0 1
	73	[109]	MOVE     	0 10
	74	[37]	SETTABLE 	17 -30 18	; "init" -
	75	[125]	CLOSURE  	18 2	; 0x7faaa7c071c0
	76	[125]	MOVE     	0 14
	77	[125]	MOVE     	0 4
	78	[111]	SETTABLE 	17 -31 18	; "_dismissAndResent" -
	79	[129]	CLOSURE  	18 3	; 0x7faaa7c08aa0
	80	[127]	SETTABLE 	17 -32 18	; "onAnyKeyPressed" -
	81	[133]	CLOSURE  	18 4	; 0x7faaa7c08bb0
	82	[131]	SETTABLE 	17 -33 18	; "onTapDismiss" -
	83	[137]	CLOSURE  	18 5	; 0x7faaa7c073a0
	84	[135]	SETTABLE 	17 -34 18	; "onHoldDismiss" -
	85	[141]	CLOSURE  	18 6	; 0x7faaa7c08f60
	86	[139]	SETTABLE 	17 -35 18	; "onSwipeDismiss" -
	87	[150]	CLOSURE  	18 7	; 0x7faaa7c09240
	88	[150]	MOVE     	0 14
	89	[143]	SETTABLE 	17 -36 18	; "onShow" -
	90	[159]	CLOSURE  	18 8	; 0x7faaa7c095e0
	91	[159]	MOVE     	0 14
	92	[152]	SETTABLE 	17 -37 18	; "onCloseWidget" -
	93	[161]	RETURN   	17 2
	94	[161]	RETURN   	0 1

function <./frontend/ui/widget/trapwidget.lua:30,30> (1 instruction, 4 bytes at 0x7faaa7c070e0)
0 params, 2 slots, 0 upvalues, 0 locals, 0 constants, 0 functions
	1	[30]	RETURN   	0 1

function <./frontend/ui/widget/trapwidget.lua:37,109> (174 instructions, 696 bytes at 0x7faaa7c076b0)
1 param, 18 slots, 13 upvalues, 4 locals, 50 constants, 0 functions
	1	[38]	GETUPVAL 	1 0	; Geom
	2	[38]	SELF     	1 1 -1	; "new"
	3	[38]	NEWTABLE 	3 0 4
	4	[39]	SETTABLE 	3 -2 -3	; "x" 0
	5	[39]	SETTABLE 	3 -4 -3	; "y" 0
	6	[40]	GETUPVAL 	4 1	; Screen
	7	[40]	SELF     	4 4 -6	; "getWidth"
	8	[40]	CALL     	4 2 2
	9	[40]	SETTABLE 	3 -5 4	; "w" -
	10	[41]	GETUPVAL 	4 1	; Screen
	11	[41]	SELF     	4 4 -8	; "getHeight"
	12	[41]	CALL     	4 2 2
	13	[41]	SETTABLE 	3 -7 4	; "h" -
	14	[38]	CALL     	1 3 2
	15	[43]	GETUPVAL 	2 2	; Device
	16	[43]	SELF     	2 2 -9	; "hasKeys"
	17	[43]	CALL     	2 2 2
	18	[43]	TEST     	2 0 0
	19	[43]	JMP      	12	; to 32
	20	[44]	NEWTABLE 	2 0 1
	21	[45]	NEWTABLE 	3 1 2
	22	[45]	NEWTABLE 	4 1 0
	23	[45]	GETUPVAL 	5 3	; Input
	24	[45]	GETTABLE 	5 5 -12	; "group"
	25	[45]	GETTABLE 	5 5 -13	; "Any"
	26	[45]	SETLIST  	4 1 1	; 1
	27	[46]	SETTABLE 	3 -14 -15	; "seqtext" "any key"
	28	[46]	SETTABLE 	3 -16 -17	; "doc" "dismiss"
	29	[46]	SETLIST  	3 1 1	; 1
	30	[46]	SETTABLE 	2 -11 3	; "AnyKeyPressed" -
	31	[47]	SETTABLE 	0 -10 2	; "key_events" -
	32	[49]	GETUPVAL 	2 2	; Device
	33	[49]	SELF     	2 2 -18	; "isTouchDevice"
	34	[49]	CALL     	2 2 2
	35	[49]	TEST     	2 0 0
	36	[49]	JMP      	30	; to 67
	37	[50]	GETTABLE 	2 0 -19	; "ges_events"
	38	[50]	NEWTABLE 	3 0 0
	39	[51]	GETUPVAL 	4 4	; GestureRange
	40	[51]	SELF     	4 4 -1	; "new"
	41	[51]	NEWTABLE 	6 0 2
	42	[51]	SETTABLE 	6 -21 -22	; "ges" "tap"
	43	[51]	SETTABLE 	6 -23 1	; "range" -
	44	[51]	CALL     	4 3 0
	45	[52]	SETLIST  	3 0 1	; 1
	46	[52]	SETTABLE 	2 -20 3	; "TapDismiss" -
	47	[53]	GETTABLE 	2 0 -19	; "ges_events"
	48	[53]	NEWTABLE 	3 0 0
	49	[54]	GETUPVAL 	4 4	; GestureRange
	50	[54]	SELF     	4 4 -1	; "new"
	51	[54]	NEWTABLE 	6 0 2
	52	[54]	SETTABLE 	6 -21 -25	; "ges" "hold"
	53	[54]	SETTABLE 	6 -23 1	; "range" -
	54	[54]	CALL     	4 3 0
	55	[55]	SETLIST  	3 0 1	; 1
	56	[55]	SETTABLE 	2 -24 3	; "HoldDismiss" -
	57	[56]	GETTABLE 	2 0 -19	; "ges_events"
	58	[56]	NEWTABLE 	3 0 0
	59	[57]	GETUPVAL 	4 4	; GestureRange
	60	[57]	SELF     	4 4 -1	; "new"
	61	[57]	NEWTABLE 	6 0 2
	62	[57]	SETTABLE 	6 -21 -27	; "ges" "swipe"
	63	[57]	SETTABLE 	6 -23 1	; "range" -
	64	[57]	CALL     	4 3 0
	65	[58]	SETLIST  	3 0 1	; 1
	66	[58]	SETTABLE 	2 -26 3	; "SwipeDismiss" -
	67	[60]	GETTABLE 	2 0 -28	; "text"
	68	[60]	TEST     	2 0 0
	69	[60]	JMP      	103	; to 173
	70	[61]	GETUPVAL 	2 5	; TextWidget
	71	[61]	SELF     	2 2 -1	; "new"
	72	[61]	NEWTABLE 	4 0 2
	73	[62]	GETTABLE 	5 0 -28	; "text"
	74	[62]	SETTABLE 	4 -28 5	; "text" -
	75	[63]	GETTABLE 	5 0 -29	; "face"
	76	[63]	SETTABLE 	4 -29 5	; "face" -
	77	[61]	CALL     	2 3 2
	78	[67]	SELF     	3 2 -6	; "getWidth"
	79	[67]	CALL     	3 2 2
	80	[67]	GETUPVAL 	4 1	; Screen
	81	[67]	SELF     	4 4 -6	; "getWidth"
	82	[67]	CALL     	4 2 2
	83	[67]	MUL      	4 4 -30	; - 0.9
	84	[67]	LT       	0 4 3
	85	[67]	JMP      	17	; to 103
	86	[69]	GETUPVAL 	3 6	; TextBoxWidget
	87	[69]	SELF     	3 3 -1	; "new"
	88	[69]	NEWTABLE 	5 0 3
	89	[70]	GETTABLE 	6 0 -28	; "text"
	90	[70]	SETTABLE 	5 -28 6	; "text" -
	91	[71]	GETTABLE 	6 0 -29	; "face"
	92	[71]	SETTABLE 	5 -29 6	; "face" -
	93	[72]	GETGLOBAL	6 -32	; math
	94	[72]	GETTABLE 	6 6 -33	; "floor"
	95	[72]	GETUPVAL 	7 1	; Screen
	96	[72]	SELF     	7 7 -6	; "getWidth"
	97	[72]	CALL     	7 2 2
	98	[72]	MUL      	7 7 -30	; - 0.9
	99	[72]	CALL     	6 2 2
	100	[72]	SETTABLE 	5 -31 6	; "width" -
	101	[69]	CALL     	3 3 2
	102	[73]	MOVE     	2 3
	103	[75]	GETUPVAL 	3 7	; Size
	104	[75]	GETTABLE 	3 3 -34	; "border"
	105	[75]	GETTABLE 	3 3 -35	; "default"
	106	[76]	GETUPVAL 	4 8	; FrameContainer
	107	[76]	SELF     	4 4 -1	; "new"
	108	[76]	NEWTABLE 	6 1 6
	109	[77]	GETUPVAL 	7 9	; Blitbuffer
	110	[77]	GETTABLE 	7 7 -38	; "COLOR_WHITE"
	111	[77]	SETTABLE 	6 -37 7	; "background" -
	112	[78]	SETTABLE 	6 -39 3	; "bordersize" -
	113	[79]	SETTABLE 	6 -40 -3	; "margin" 0
	114	[80]	SETTABLE 	6 -41 -3	; "padding" 0
	115	[81]	GETUPVAL 	7 7	; Size
	116	[81]	GETTABLE 	7 7 -41	; "padding"
	117	[81]	GETTABLE 	7 7 -35	; "default"
	118	[81]	SETTABLE 	6 -42 7	; "padding_left" -
	119	[82]	GETUPVAL 	7 7	; Size
	120	[82]	GETTABLE 	7 7 -41	; "padding"
	121	[82]	GETTABLE 	7 7 -35	; "default"
	122	[82]	SETTABLE 	6 -43 7	; "padding_right" -
	123	[84]	MOVE     	7 2
	124	[84]	SETLIST  	6 1 1	; 1
	125	[76]	CALL     	4 3 2
	126	[84]	SETTABLE 	0 -36 4	; "frame" -
	127	[88]	GETUPVAL 	4 10	; CenterContainer
	128	[88]	SELF     	4 4 -1	; "new"
	129	[88]	NEWTABLE 	6 0 1
	130	[89]	SELF     	7 1 -46	; "copy"
	131	[89]	CALL     	7 2 2
	132	[89]	SETTABLE 	6 -45 7	; "dimen" -
	133	[90]	GETUPVAL 	7 11	; BottomContainer
	134	[90]	SELF     	7 7 -1	; "new"
	135	[90]	NEWTABLE 	9 0 1
	136	[91]	GETUPVAL 	10 0	; Geom
	137	[91]	SELF     	10 10 -1	; "new"
	138	[91]	NEWTABLE 	12 0 2
	139	[92]	GETTABLE 	13 1 -5	; "w"
	140	[92]	SETTABLE 	12 -5 13	; "w" -
	141	[93]	GETTABLE 	13 1 -7	; "h"
	142	[93]	MUL      	14 -47 3	; 2 -
	143	[93]	ADD      	13 13 14
	144	[93]	SETTABLE 	12 -7 13	; "h" -
	145	[91]	CALL     	10 3 2
	146	[94]	SETTABLE 	9 -45 10	; "dimen" -
	147	[95]	GETUPVAL 	10 12	; LeftContainer
	148	[95]	SELF     	10 10 -1	; "new"
	149	[95]	NEWTABLE 	12 1 1
	150	[96]	GETUPVAL 	13 0	; Geom
	151	[96]	SELF     	13 13 -1	; "new"
	152	[96]	NEWTABLE 	15 0 2
	153	[97]	GETTABLE 	16 1 -5	; "w"
	154	[97]	MUL      	17 -47 3	; 2 -
	155	[97]	ADD      	16 16 17
	156	[97]	SETTABLE 	15 -5 16	; "w" -
	157	[98]	GETTABLE 	16 0 -36	; "frame"
	158	[98]	SELF     	16 16 -48	; "getSize"
	159	[98]	CALL     	16 2 2
	160	[98]	GETTABLE 	16 16 -7	; "h"
	161	[98]	SETTABLE 	15 -7 16	; "h" -
	162	[96]	CALL     	13 3 2
	163	[99]	SETTABLE 	12 -45 13	; "dimen" -
	164	[101]	GETTABLE 	13 0 -36	; "frame"
	165	[101]	SETLIST  	12 1 1	; 1
	166	[95]	CALL     	10 3 0
	167	[102]	SETLIST  	9 0 1	; 1
	168	[90]	CALL     	7 3 0
	169	[103]	SETLIST  	6 0 1	; 1
	170	[88]	CALL     	4 3 2
	171	[103]	SETTABLE 	0 -44 4	; 1 -
	172	[103]	JMP      	1	; to 174
	173	[107]	SETTABLE 	0 -49 -50	; "invisible" true
	174	[109]	RETURN   	0 1

function <./frontend/ui/widget/trapwidget.lua:111,125> (24 instructions, 96 bytes at 0x7faaa7c071c0)
3 params, 6 slots, 2 upvalues, 3 locals, 4 constants, 1 function
	1	[112]	GETTABLE 	3 0 -1	; "dismiss_callback"
	2	[112]	CALL     	3 1 1
	3	[113]	GETUPVAL 	3 0	; UIManager
	4	[113]	SELF     	3 3 -2	; "close"
	5	[113]	MOVE     	5 0
	6	[113]	CALL     	3 3 1
	7	[114]	GETTABLE 	3 0 -3	; "resend_event"
	8	[114]	TEST     	3 0 0
	9	[114]	JMP      	12	; to 22
	10	[114]	TEST     	1 0 0
	11	[114]	JMP      	10	; to 22
	12	[114]	TEST     	2 0 0
	13	[114]	JMP      	8	; to 22
	14	[122]	GETUPVAL 	3 0	; UIManager
	15	[122]	SELF     	3 3 -4	; "nextTick"
	16	[122]	CLOSURE  	5 0	; 0x7faaa7c07e00
	17	[122]	GETUPVAL 	0 0	; UIManager
	18	[122]	GETUPVAL 	0 1	; Event
	19	[122]	MOVE     	0 1
	20	[122]	MOVE     	0 2
	21	[122]	CALL     	3 3 1
	22	[124]	LOADBOOL 	3 1 0
	23	[124]	RETURN   	3 2
	24	[125]	RETURN   	0 1

function <./frontend/ui/widget/trapwidget.lua:122,122> (9 instructions, 36 bytes at 0x7faaa7c07e00)
0 params, 6 slots, 4 upvalues, 0 locals, 2 constants, 0 functions
	1	[122]	GETUPVAL 	0 0	; UIManager
	2	[122]	SELF     	0 0 -1	; "handleInputEvent"
	3	[122]	GETUPVAL 	2 1	; Event
	4	[122]	SELF     	2 2 -2	; "new"
	5	[122]	GETUPVAL 	4 2	; evtype
	6	[122]	GETUPVAL 	5 3	; ev
	7	[122]	CALL     	2 4 0
	8	[122]	CALL     	0 0 1
	9	[122]	RETURN   	0 1

function <./frontend/ui/widget/trapwidget.lua:127,129> (6 instructions, 24 bytes at 0x7faaa7c08aa0)
3 params, 7 slots, 0 upvalues, 3 locals, 2 constants, 0 functions
	1	[128]	SELF     	3 0 -1	; "_dismissAndResent"
	2	[128]	LOADK    	5 -2	; "KeyPress"
	3	[128]	MOVE     	6 2
	4	[128]	TAILCALL 	3 4 0
	5	[128]	RETURN   	3 0
	6	[129]	RETURN   	0 1

function <./frontend/ui/widget/trapwidget.lua:131,133> (6 instructions, 24 bytes at 0x7faaa7c08bb0)
3 params, 7 slots, 0 upvalues, 3 locals, 2 constants, 0 functions
	1	[132]	SELF     	3 0 -1	; "_dismissAndResent"
	2	[132]	LOADK    	5 -2	; "Gesture"
	3	[132]	MOVE     	6 2
	4	[132]	TAILCALL 	3 4 0
	5	[132]	RETURN   	3 0
	6	[133]	RETURN   	0 1

function <./frontend/ui/widget/trapwidget.lua:135,137> (6 instructions, 24 bytes at 0x7faaa7c073a0)
3 params, 7 slots, 0 upvalues, 3 locals, 2 constants, 0 functions
	1	[136]	SELF     	3 0 -1	; "_dismissAndResent"
	2	[136]	LOADK    	5 -2	; "Gesture"
	3	[136]	MOVE     	6 2
	4	[136]	TAILCALL 	3 4 0
	5	[136]	RETURN   	3 0
	6	[137]	RETURN   	0 1

function <./frontend/ui/widget/trapwidget.lua:139,141> (6 instructions, 24 bytes at 0x7faaa7c08f60)
3 params, 7 slots, 0 upvalues, 3 locals, 2 constants, 0 functions
	1	[140]	SELF     	3 0 -1	; "_dismissAndResent"
	2	[140]	LOADK    	5 -2	; "Gesture"
	3	[140]	MOVE     	6 2
	4	[140]	TAILCALL 	3 4 0
	5	[140]	RETURN   	3 0
	6	[141]	RETURN   	0 1

function <./frontend/ui/widget/trapwidget.lua:143,150> (12 instructions, 48 bytes at 0x7faaa7c09240)
1 param, 5 slots, 1 upvalue, 1 local, 2 constants, 1 function
	1	[144]	GETTABLE 	1 0 -1	; "frame"
	2	[144]	TEST     	1 0 0
	3	[144]	JMP      	6	; to 10
	4	[145]	GETUPVAL 	1 0	; UIManager
	5	[145]	SELF     	1 1 -2	; "setDirty"
	6	[145]	MOVE     	3 0
	7	[147]	CLOSURE  	4 0	; 0x7faaa7c094f0
	8	[147]	MOVE     	0 0
	9	[145]	CALL     	1 4 1
	10	[149]	LOADBOOL 	1 1 0
	11	[149]	RETURN   	1 2
	12	[150]	RETURN   	0 1

function <./frontend/ui/widget/trapwidget.lua:145,147> (6 instructions, 24 bytes at 0x7faaa7c094f0)
0 params, 2 slots, 1 upvalue, 0 locals, 3 constants, 0 functions
	1	[146]	LOADK    	0 -1	; "ui"
	2	[146]	GETUPVAL 	1 0	; self
	3	[146]	GETTABLE 	1 1 -2	; "frame"
	4	[146]	GETTABLE 	1 1 -3	; "dimen"
	5	[146]	RETURN   	0 3
	6	[147]	RETURN   	0 1

function <./frontend/ui/widget/trapwidget.lua:152,159> (12 instructions, 48 bytes at 0x7faaa7c095e0)
1 param, 5 slots, 1 upvalue, 1 local, 2 constants, 1 function
	1	[153]	GETTABLE 	1 0 -1	; "frame"
	2	[153]	TEST     	1 0 0
	3	[153]	JMP      	6	; to 10
	4	[154]	GETUPVAL 	1 0	; UIManager
	5	[154]	SELF     	1 1 -2	; "setDirty"
	6	[154]	LOADNIL  	3 3
	7	[156]	CLOSURE  	4 0	; 0x7faaa7c09c80
	8	[156]	MOVE     	0 0
	9	[154]	CALL     	1 4 1
	10	[158]	LOADBOOL 	1 1 0
	11	[158]	RETURN   	1 2
	12	[159]	RETURN   	0 1

function <./frontend/ui/widget/trapwidget.lua:154,156> (6 instructions, 24 bytes at 0x7faaa7c09c80)
0 params, 2 slots, 1 upvalue, 0 locals, 3 constants, 0 functions
	1	[155]	LOADK    	0 -1	; "ui"
	2	[155]	GETUPVAL 	1 0	; self
	3	[155]	GETTABLE 	1 1 -2	; "frame"
	4	[155]	GETTABLE 	1 1 -3	; "dimen"
	5	[155]	RETURN   	0 3
	6	[156]	RETURN   	0 1
