
main <./frontend/ui/uimanager.lua:0,0> (227 instructions, 908 bytes at 0x7ffe484068c0)
0+ params, 18 slots, 0 upvalues, 16 locals, 95 constants, 46 functions
	1	[5]	GETGLOBAL	0 -1	; require
	2	[5]	LOADK    	1 -2	; "device"
	3	[5]	CALL     	0 2 2
	4	[6]	GETGLOBAL	1 -1	; require
	5	[6]	LOADK    	2 -3	; "ui/event"
	6	[6]	CALL     	1 2 2
	7	[7]	GETGLOBAL	2 -1	; require
	8	[7]	LOADK    	3 -4	; "ui/geometry"
	9	[7]	CALL     	2 2 2
	10	[8]	GETGLOBAL	3 -1	; require
	11	[8]	LOADK    	4 -5	; "dbg"
	12	[8]	CALL     	3 2 2
	13	[9]	GETGLOBAL	4 -1	; require
	14	[9]	LOADK    	5 -6	; "logger"
	15	[9]	CALL     	4 2 2
	16	[10]	GETGLOBAL	5 -1	; require
	17	[10]	LOADK    	6 -7	; "ffi/util"
	18	[10]	CALL     	5 2 2
	19	[11]	GETGLOBAL	6 -1	; require
	20	[11]	LOADK    	7 -8	; "gettext"
	21	[11]	CALL     	6 2 2
	22	[12]	GETTABLE 	7 0 -9	; "input"
	23	[13]	GETTABLE 	8 0 -10	; "screen"
	24	[15]	LOADK    	9 -11	; 1000000
	25	[16]	LOADK    	10 -12	; 6
	26	[19]	NEWTABLE 	11 0 15
	27	[22]	GETGLOBAL	12 -14	; G_reader_settings
	28	[22]	SELF     	12 12 -15	; "readSetting"
	29	[22]	LOADK    	14 -16	; "full_refresh_count"
	30	[22]	CALL     	12 3 2
	31	[22]	TEST     	12 0 1
	32	[22]	JMP      	1	; to 34
	33	[22]	MOVE     	12 10
	34	[22]	SETTABLE 	11 -13 12	; "FULL_REFRESH_COUNT" -
	35	[23]	SETTABLE 	11 -17 -18	; "refresh_count" 0
	36	[26]	SETTABLE 	11 -19 -20	; "ZMQ_TIMEOUT" 50000
	37	[28]	SETTABLE 	11 -21 -22	; "event_handlers" nil
	38	[30]	SETTABLE 	11 -23 -24	; "_running" true
	39	[31]	NEWTABLE 	12 0 0
	40	[31]	SETTABLE 	11 -25 12	; "_window_stack" -
	41	[32]	NEWTABLE 	12 0 0
	42	[32]	SETTABLE 	11 -26 12	; "_task_queue" -
	43	[33]	SETTABLE 	11 -27 -28	; "_task_queue_dirty" false
	44	[34]	NEWTABLE 	12 0 0
	45	[34]	SETTABLE 	11 -29 12	; "_dirty" -
	46	[35]	NEWTABLE 	12 0 0
	47	[35]	SETTABLE 	11 -30 12	; "_zeromqs" -
	48	[36]	NEWTABLE 	12 0 0
	49	[36]	SETTABLE 	11 -31 12	; "_refresh_stack" -
	50	[37]	NEWTABLE 	12 0 0
	51	[37]	SETTABLE 	11 -32 12	; "_refresh_func_stack" -
	52	[38]	SETTABLE 	11 -33 -28	; "_entered_poweroff_stage" false
	53	[39]	SETTABLE 	11 -34 -22	; "_exit_code" nil
	54	[41]	GETGLOBAL	12 -1	; require
	55	[41]	LOADK    	13 -36	; "ui/hook_container"
	56	[41]	CALL     	12 2 2
	57	[41]	SELF     	12 12 -37	; "new"
	58	[41]	CALL     	12 2 2
	59	[41]	SETTABLE 	11 -35 12	; "event_hook" -
	60	[337]	CLOSURE  	12 0	; 0x7ffe48407020
	61	[337]	MOVE     	0 0
	62	[337]	MOVE     	0 8
	63	[337]	MOVE     	0 6
	64	[337]	MOVE     	0 11
	65	[337]	MOVE     	0 1
	66	[44]	SETTABLE 	11 -38 12	; "init" -
	67	[380]	CLOSURE  	12 1	; 0x7ffe486049d0
	68	[380]	MOVE     	0 4
	69	[380]	MOVE     	0 1
	70	[380]	MOVE     	0 7
	71	[352]	SETTABLE 	11 -39 12	; "show" -
	72	[435]	CLOSURE  	12 2	; 0x7ffe48604e00
	73	[435]	MOVE     	0 4
	74	[435]	MOVE     	0 1
	75	[435]	MOVE     	0 7
	76	[392]	SETTABLE 	11 -40 12	; "close" -
	77	[474]	CLOSURE  	12 3	; 0x7ffe48605150
	78	[474]	MOVE     	0 9
	79	[438]	SETTABLE 	11 -41 12	; "schedule" -
	80	[475]	SELF     	12 3 -42	; "guard"
	81	[475]	MOVE     	14 11
	82	[475]	LOADK    	15 -41	; "schedule"
	83	[479]	CLOSURE  	16 4	; 0x7ffe48606170
	84	[475]	CALL     	12 5 1
	85	[493]	CLOSURE  	12 5	; 0x7ffe48606a50
	86	[493]	MOVE     	0 5
	87	[493]	MOVE     	0 9
	88	[482]	SETTABLE 	11 -43 12	; "scheduleIn" -
	89	[494]	SELF     	12 3 -42	; "guard"
	90	[494]	MOVE     	14 11
	91	[494]	LOADK    	15 -43	; "scheduleIn"
	92	[497]	CLOSURE  	16 6	; 0x7ffe486073d0
	93	[494]	CALL     	12 5 1
	94	[501]	CLOSURE  	12 7	; 0x7ffe486071f0
	95	[499]	SETTABLE 	11 -44 12	; "nextTick" -
	96	[506]	CLOSURE  	12 8	; 0x7ffe48607570
	97	[504]	SETTABLE 	11 -45 12	; "tickAfterNext" -
	98	[530]	CLOSURE  	12 9	; 0x7ffe48607c10
	99	[524]	SETTABLE 	11 -46 12	; "unschedule" -
	100	[531]	SELF     	12 3 -42	; "guard"
	101	[531]	MOVE     	14 11
	102	[531]	LOADK    	15 -46	; "unschedule"
	103	[532]	CLOSURE  	16 10	; 0x7ffe48607f10
	104	[531]	CALL     	12 5 1
	105	[647]	CLOSURE  	12 11	; 0x7ffe48608270
	106	[647]	MOVE     	0 4
	107	[647]	MOVE     	0 3
	108	[587]	SETTABLE 	11 -47 12	; "setDirty" -
	109	[648]	SELF     	12 3 -42	; "guard"
	110	[648]	MOVE     	14 11
	111	[648]	LOADK    	15 -47	; "setDirty"
	112	[649]	LOADNIL  	16 16
	113	[661]	CLOSURE  	17 12	; 0x7ffe48608ac0
	114	[661]	MOVE     	0 3
	115	[648]	CALL     	12 6 1
	116	[673]	CLOSURE  	12 13	; 0x7ffe48608dc0
	117	[673]	MOVE     	0 4
	118	[668]	SETTABLE 	11 -48 12	; "clearRenderStack" -
	119	[678]	CLOSURE  	12 14	; 0x7ffe48607af0
	120	[675]	SETTABLE 	11 -49 12	; "insertZMQ" -
	121	[686]	CLOSURE  	12 15	; 0x7ffe48609160
	122	[680]	SETTABLE 	11 -50 12	; "removeZMQ" -
	123	[695]	CLOSURE  	12 16	; 0x7ffe48608310
	124	[695]	MOVE     	0 4
	125	[691]	SETTABLE 	11 -51 12	; "setRefreshRate" -
	126	[700]	CLOSURE  	12 17	; 0x7ffe48607b90
	127	[698]	SETTABLE 	11 -52 12	; "getRefreshRate" -
	128	[705]	CLOSURE  	12 18	; 0x7ffe48608fe0
	129	[703]	SETTABLE 	11 -53 12	; "getTopWidget" -
	130	[728]	CLOSURE  	12 19	; 0x7ffe486045a0
	131	[728]	MOVE     	0 4
	132	[708]	SETTABLE 	11 -54 12	; "quit" -
	133	[768]	CLOSURE  	12 20	; 0x7ffe48604930
	134	[731]	SETTABLE 	11 -55 12	; "sendEvent" -
	135	[786]	CLOSURE  	12 21	; 0x7ffe48604860
	136	[771]	SETTABLE 	11 -56 12	; "broadcastEvent" -
	137	[822]	CLOSURE  	12 22	; 0x7ffe48609d30
	138	[822]	MOVE     	0 5
	139	[822]	MOVE     	0 9
	140	[788]	SETTABLE 	11 -57 12	; "_checkTasks" -
	141	[825]	NEWTABLE 	12 0 6
	142	[825]	SETTABLE 	12 -58 -59	; "fast" 1
	143	[825]	SETTABLE 	12 -60 -61	; "ui" 2
	144	[825]	SETTABLE 	12 -62 -63	; "partial" 3
	145	[825]	SETTABLE 	12 -64 -65	; "flashui" 4
	146	[825]	SETTABLE 	12 -66 -67	; "flashpartial" 5
	147	[825]	SETTABLE 	12 -68 -12	; "full" 6
	148	[829]	NEWTABLE 	13 0 6
	149	[830]	SETTABLE 	13 -58 -69	; "fast" "refreshFast"
	150	[831]	SETTABLE 	13 -60 -70	; "ui" "refreshUI"
	151	[832]	SETTABLE 	13 -62 -71	; "partial" "refreshPartial"
	152	[833]	SETTABLE 	13 -64 -72	; "flashui" "refreshFlashUI"
	153	[834]	SETTABLE 	13 -66 -73	; "flashpartial" "refreshFlashPartial"
	154	[835]	SETTABLE 	13 -68 -74	; "full" "refreshFull"
	155	[850]	CLOSURE  	14 23	; 0x7ffe4860a800
	156	[850]	MOVE     	0 12
	157	[850]	MOVE     	0 4
	158	[864]	CLOSURE  	15 24	; 0x7ffe4860aeb0
	159	[864]	MOVE     	0 4
	160	[963]	CLOSURE  	16 25	; 0x7ffe4860b3c0
	161	[963]	MOVE     	0 4
	162	[963]	MOVE     	0 2
	163	[963]	MOVE     	0 8
	164	[963]	MOVE     	0 14
	165	[963]	MOVE     	0 15
	166	[882]	SETTABLE 	11 -75 16	; "_refresh" -
	167	[1044]	CLOSURE  	16 26	; 0x7ffe4860b9f0
	168	[1044]	MOVE     	0 4
	169	[1044]	MOVE     	0 8
	170	[1044]	MOVE     	0 15
	171	[1044]	MOVE     	0 3
	172	[1044]	MOVE     	0 13
	173	[966]	SETTABLE 	11 -76 16	; "_repaint" -
	174	[1048]	CLOSURE  	16 27	; 0x7ffe4860bf20
	175	[1046]	SETTABLE 	11 -77 16	; "forceRePaint" -
	176	[1058]	CLOSURE  	16 28	; 0x7ffe4860c440
	177	[1058]	MOVE     	0 4
	178	[1058]	MOVE     	0 8
	179	[1053]	SETTABLE 	11 -78 16	; "widgetRepaint" -
	180	[1062]	CLOSURE  	16 29	; 0x7ffe4860c5d0
	181	[1060]	SETTABLE 	11 -79 16	; "setInputTimeout" -
	182	[1066]	CLOSURE  	16 30	; 0x7ffe4860c8f0
	183	[1064]	SETTABLE 	11 -80 16	; "resetInputTimeout" -
	184	[1078]	CLOSURE  	16 31	; 0x7ffe4860ca10
	185	[1068]	SETTABLE 	11 -81 16	; "handleInputEvent" -
	186	[1087]	CLOSURE  	16 32	; 0x7ffe4860d2f0
	187	[1081]	SETTABLE 	11 -82 16	; "processZMQs" -
	188	[1154]	CLOSURE  	16 33	; 0x7ffe486078e0
	189	[1154]	MOVE     	0 4
	190	[1154]	MOVE     	0 9
	191	[1154]	MOVE     	0 7
	192	[1089]	SETTABLE 	11 -83 16	; "handleInput" -
	193	[1160]	CLOSURE  	16 34	; 0x7ffe4860eca0
	194	[1157]	SETTABLE 	11 -84 16	; "onRotation" -
	195	[1169]	CLOSURE  	16 35	; 0x7ffe4860ee10
	196	[1162]	SETTABLE 	11 -85 16	; "initLooper" -
	197	[1189]	CLOSURE  	16 36	; 0x7ffe4860f2a0
	198	[1174]	SETTABLE 	11 -86 16	; "run" -
	199	[1195]	CLOSURE  	16 37	; 0x7ffe4860f6e0
	200	[1192]	SETTABLE 	11 -87 16	; "runForever" -
	201	[1201]	CLOSURE  	16 38	; 0x7ffe4860f7a0
	202	[1201]	MOVE     	0 1
	203	[1198]	SETTABLE 	11 -88 16	; "_beforeSuspend" -
	204	[1206]	CLOSURE  	16 39	; 0x7ffe4860fd80
	205	[1206]	MOVE     	0 1
	206	[1204]	SETTABLE 	11 -89 16	; "_afterResume" -
	207	[1210]	CLOSURE  	16 40	; 0x7ffe4860fe00
	208	[1210]	MOVE     	0 1
	209	[1208]	SETTABLE 	11 -90 16	; "_beforeCharging" -
	210	[1214]	CLOSURE  	16 41	; 0x7ffe48610100
	211	[1214]	MOVE     	0 1
	212	[1212]	SETTABLE 	11 -91 16	; "_afterNotCharging" -
	213	[1224]	CLOSURE  	16 42	; 0x7ffe48610330
	214	[1224]	MOVE     	0 0
	215	[1218]	SETTABLE 	11 -92 16	; "suspend" -
	216	[1233]	CLOSURE  	16 43	; 0x7ffe486106c0
	217	[1233]	MOVE     	0 0
	218	[1227]	SETTABLE 	11 -93 16	; "resume" -
	219	[1237]	CLOSURE  	16 44	; 0x7ffe48610620
	220	[1237]	MOVE     	0 1
	221	[1235]	SETTABLE 	11 -94 16	; "flushSettings" -
	222	[1243]	CLOSURE  	16 45	; 0x7ffe4860c3a0
	223	[1239]	SETTABLE 	11 -95 16	; "restartKOReader" -
	224	[1245]	SELF     	16 11 -38	; "init"
	225	[1245]	CALL     	16 2 1
	226	[1246]	RETURN   	11 2
	227	[1246]	RETURN   	0 1

function <./frontend/ui/uimanager.lua:44,337> (299 instructions, 1196 bytes at 0x7ffe48407020)
1 param, 4 slots, 5 upvalues, 1 local, 32 constants, 48 functions
	1	[45]	NEWTABLE 	1 0 3
	2	[48]	CLOSURE  	2 0	; 0x7ffe484073e0
	3	[48]	MOVE     	0 0
	4	[48]	SETTABLE 	1 -2 2	; "__default__" -
	5	[51]	CLOSURE  	2 1	; 0x7ffe484077a0
	6	[51]	MOVE     	0 0
	7	[51]	SETTABLE 	1 -3 2	; "SaveState" -
	8	[54]	CLOSURE  	2 2	; 0x7ffe48407350
	9	[54]	GETUPVAL 	0 0	; Device
	10	[54]	SETTABLE 	1 -4 2	; "Power" -
	11	[55]	SETTABLE 	0 -1 1	; "event_handlers" -
	12	[68]	CLOSURE  	1 3	; 0x7ffe48407cd0
	13	[68]	MOVE     	0 0
	14	[68]	GETUPVAL 	0 1	; Screen
	15	[68]	GETUPVAL 	0 2	; _
	16	[68]	GETUPVAL 	0 0	; Device
	17	[68]	GETUPVAL 	0 3	; UIManager
	18	[68]	GETUPVAL 	0 4	; Event
	19	[68]	SETTABLE 	0 -5 1	; "poweroff_action" -
	20	[81]	CLOSURE  	1 4	; 0x7ffe484087b0
	21	[81]	MOVE     	0 0
	22	[81]	GETUPVAL 	0 1	; Screen
	23	[81]	GETUPVAL 	0 2	; _
	24	[81]	GETUPVAL 	0 0	; Device
	25	[81]	GETUPVAL 	0 3	; UIManager
	26	[81]	GETUPVAL 	0 4	; Event
	27	[81]	SETTABLE 	0 -6 1	; "reboot_action" -
	28	[82]	GETUPVAL 	1 0	; Device
	29	[82]	SELF     	1 1 -7	; "isPocketBook"
	30	[82]	CALL     	1 2 2
	31	[82]	TEST     	1 0 0
	32	[82]	JMP      	10	; to 43
	33	[83]	GETTABLE 	1 0 -1	; "event_handlers"
	34	[86]	CLOSURE  	2 5	; 0x7ffe484083c0
	35	[86]	MOVE     	0 0
	36	[86]	GETUPVAL 	0 0	; Device
	37	[86]	SETTABLE 	1 -8 2	; "Suspend" -
	38	[87]	GETTABLE 	1 0 -1	; "event_handlers"
	39	[90]	CLOSURE  	2 6	; 0x7ffe48407c50
	40	[90]	GETUPVAL 	0 0	; Device
	41	[90]	MOVE     	0 0
	42	[90]	SETTABLE 	1 -9 2	; "Resume" -
	43	[92]	GETUPVAL 	1 0	; Device
	44	[92]	SELF     	1 1 -10	; "isKobo"
	45	[92]	CALL     	1 2 2
	46	[92]	TEST     	1 0 0
	47	[92]	JMP      	77	; to 125
	48	[96]	GETTABLE 	1 0 -1	; "event_handlers"
	49	[103]	CLOSURE  	2 7	; 0x7ffe48407ac0
	50	[103]	GETUPVAL 	0 0	; Device
	51	[103]	MOVE     	0 0
	52	[103]	SETTABLE 	1 -8 2	; "Suspend" -
	53	[104]	GETTABLE 	1 0 -1	; "event_handlers"
	54	[111]	CLOSURE  	2 8	; 0x7ffe48409850
	55	[111]	GETUPVAL 	0 0	; Device
	56	[111]	MOVE     	0 0
	57	[111]	SETTABLE 	1 -9 2	; "Resume" -
	58	[112]	GETTABLE 	1 0 -1	; "event_handlers"
	59	[116]	CLOSURE  	2 9	; 0x7ffe48409d80
	60	[116]	GETUPVAL 	0 3	; UIManager
	61	[116]	MOVE     	0 0
	62	[116]	SETTABLE 	1 -11 2	; "PowerPress" -
	63	[117]	GETTABLE 	1 0 -1	; "event_handlers"
	64	[127]	CLOSURE  	2 10	; 0x7ffe48409e90
	65	[127]	MOVE     	0 0
	66	[127]	GETUPVAL 	0 3	; UIManager
	67	[127]	GETUPVAL 	0 0	; Device
	68	[127]	SETTABLE 	1 -12 2	; "PowerRelease" -
	69	[129]	GETGLOBAL	1 -13	; G_reader_settings
	70	[129]	SELF     	1 1 -14	; "readSetting"
	71	[129]	LOADK    	3 -15	; "ignore_power_sleepcover"
	72	[129]	CALL     	1 3 2
	73	[129]	TEST     	1 0 0
	74	[129]	JMP      	5	; to 80
	75	[132]	GETTABLE 	1 0 -1	; "event_handlers"
	76	[132]	SETTABLE 	1 -16 -17	; "SleepCoverClosed" nil
	77	[133]	GETTABLE 	1 0 -1	; "event_handlers"
	78	[133]	SETTABLE 	1 -18 -17	; "SleepCoverOpened" nil
	79	[133]	JMP      	25	; to 105
	80	[134]	GETGLOBAL	1 -13	; G_reader_settings
	81	[134]	SELF     	1 1 -14	; "readSetting"
	82	[134]	LOADK    	3 -19	; "ignore_open_sleepcover"
	83	[134]	CALL     	1 3 2
	84	[134]	TEST     	1 0 0
	85	[134]	JMP      	9	; to 95
	86	[137]	GETTABLE 	1 0 -1	; "event_handlers"
	87	[139]	CLOSURE  	2 11	; 0x7ffe484092b0
	88	[139]	MOVE     	0 0
	89	[139]	SETTABLE 	1 -16 2	; "SleepCoverClosed" -
	90	[140]	GETTABLE 	1 0 -1	; "event_handlers"
	91	[142]	CLOSURE  	2 12	; 0x7ffe4840a970
	92	[142]	GETUPVAL 	0 0	; Device
	93	[142]	SETTABLE 	1 -18 2	; "SleepCoverOpened" -
	94	[142]	JMP      	10	; to 105
	95	[144]	GETTABLE 	1 0 -1	; "event_handlers"
	96	[147]	CLOSURE  	2 13	; 0x7ffe48408d50
	97	[147]	GETUPVAL 	0 0	; Device
	98	[147]	MOVE     	0 0
	99	[147]	SETTABLE 	1 -16 2	; "SleepCoverClosed" -
	100	[148]	GETTABLE 	1 0 -1	; "event_handlers"
	101	[151]	CLOSURE  	2 14	; 0x7ffe4840ac10
	102	[151]	GETUPVAL 	0 0	; Device
	103	[151]	MOVE     	0 0
	104	[151]	SETTABLE 	1 -18 2	; "SleepCoverOpened" -
	105	[153]	GETTABLE 	1 0 -1	; "event_handlers"
	106	[155]	CLOSURE  	2 15	; 0x7ffe4840aeb0
	107	[155]	GETUPVAL 	0 0	; Device
	108	[155]	SETTABLE 	1 -20 2	; "Light" -
	109	[156]	GETTABLE 	1 0 -1	; "event_handlers"
	110	[161]	CLOSURE  	2 16	; 0x7ffe4840b3c0
	111	[161]	MOVE     	0 0
	112	[161]	GETUPVAL 	0 0	; Device
	113	[161]	SETTABLE 	1 -21 2	; "Charging" -
	114	[162]	GETTABLE 	1 0 -1	; "event_handlers"
	115	[168]	CLOSURE  	2 17	; 0x7ffe48409a50
	116	[168]	MOVE     	0 0
	117	[168]	GETUPVAL 	0 0	; Device
	118	[168]	SETTABLE 	1 -22 2	; "NotCharging" -
	119	[169]	GETTABLE 	1 0 -1	; "event_handlers"
	120	[177]	CLOSURE  	2 18	; 0x7ffe4840ba80
	121	[177]	GETUPVAL 	0 0	; Device
	122	[177]	MOVE     	0 0
	123	[177]	SETTABLE 	1 -2 2	; "__default__" -
	124	[177]	JMP      	174	; to 299
	125	[178]	GETUPVAL 	1 0	; Device
	126	[178]	SELF     	1 1 -23	; "isKindle"
	127	[178]	CALL     	1 2 2
	128	[178]	TEST     	1 0 0
	129	[178]	JMP      	21	; to 151
	130	[179]	GETTABLE 	1 0 -1	; "event_handlers"
	131	[182]	CLOSURE  	2 19	; 0x7ffe4840bc30
	132	[182]	MOVE     	0 0
	133	[182]	GETUPVAL 	0 0	; Device
	134	[182]	SETTABLE 	1 -24 2	; "IntoSS" -
	135	[183]	GETTABLE 	1 0 -1	; "event_handlers"
	136	[186]	CLOSURE  	2 20	; 0x7ffe4840a550
	137	[186]	GETUPVAL 	0 0	; Device
	138	[186]	MOVE     	0 0
	139	[186]	SETTABLE 	1 -25 2	; "OutOfSS" -
	140	[187]	GETTABLE 	1 0 -1	; "event_handlers"
	141	[190]	CLOSURE  	2 21	; 0x7ffe4840a390
	142	[190]	MOVE     	0 0
	143	[190]	GETUPVAL 	0 0	; Device
	144	[190]	SETTABLE 	1 -21 2	; "Charging" -
	145	[191]	GETTABLE 	1 0 -1	; "event_handlers"
	146	[194]	CLOSURE  	2 22	; 0x7ffe4840c3e0
	147	[194]	GETUPVAL 	0 0	; Device
	148	[194]	MOVE     	0 0
	149	[194]	SETTABLE 	1 -22 2	; "NotCharging" -
	150	[194]	JMP      	148	; to 299
	151	[195]	GETUPVAL 	1 0	; Device
	152	[195]	SELF     	1 1 -26	; "isRemarkable"
	153	[195]	CALL     	1 2 2
	154	[195]	TEST     	1 0 0
	155	[195]	JMP      	27	; to 183
	156	[196]	GETTABLE 	1 0 -1	; "event_handlers"
	157	[198]	CLOSURE  	2 23	; 0x7ffe4840c220
	158	[198]	GETUPVAL 	0 3	; UIManager
	159	[198]	MOVE     	0 0
	160	[198]	SETTABLE 	1 -11 2	; "PowerPress" -
	161	[199]	GETTABLE 	1 0 -1	; "event_handlers"
	162	[209]	CLOSURE  	2 24	; 0x7ffe4840c740
	163	[209]	MOVE     	0 0
	164	[209]	GETUPVAL 	0 3	; UIManager
	165	[209]	GETUPVAL 	0 0	; Device
	166	[209]	SETTABLE 	1 -12 2	; "PowerRelease" -
	167	[210]	GETTABLE 	1 0 -1	; "event_handlers"
	168	[214]	CLOSURE  	2 25	; 0x7ffe4840ce20
	169	[214]	MOVE     	0 0
	170	[214]	GETUPVAL 	0 0	; Device
	171	[214]	SETTABLE 	1 -8 2	; "Suspend" -
	172	[215]	GETTABLE 	1 0 -1	; "event_handlers"
	173	[219]	CLOSURE  	2 26	; 0x7ffe4840d0c0
	174	[219]	GETUPVAL 	0 0	; Device
	175	[219]	MOVE     	0 0
	176	[219]	SETTABLE 	1 -9 2	; "Resume" -
	177	[220]	GETTABLE 	1 0 -1	; "event_handlers"
	178	[225]	CLOSURE  	2 27	; 0x7ffe4840d3b0
	179	[225]	GETUPVAL 	0 0	; Device
	180	[225]	MOVE     	0 0
	181	[225]	SETTABLE 	1 -2 2	; "__default__" -
	182	[225]	JMP      	116	; to 299
	183	[226]	GETUPVAL 	1 0	; Device
	184	[226]	SELF     	1 1 -27	; "isSonyPRSTUX"
	185	[226]	CALL     	1 2 2
	186	[226]	TEST     	1 0 0
	187	[226]	JMP      	44	; to 232
	188	[227]	GETTABLE 	1 0 -1	; "event_handlers"
	189	[229]	CLOSURE  	2 28	; 0x7ffe4840d530
	190	[229]	GETUPVAL 	0 3	; UIManager
	191	[229]	MOVE     	0 0
	192	[229]	SETTABLE 	1 -11 2	; "PowerPress" -
	193	[230]	GETTABLE 	1 0 -1	; "event_handlers"
	194	[240]	CLOSURE  	2 29	; 0x7ffe4840d920
	195	[240]	MOVE     	0 0
	196	[240]	GETUPVAL 	0 3	; UIManager
	197	[240]	GETUPVAL 	0 0	; Device
	198	[240]	SETTABLE 	1 -12 2	; "PowerRelease" -
	199	[241]	GETTABLE 	1 0 -1	; "event_handlers"
	200	[245]	CLOSURE  	2 30	; 0x7ffe4840db00
	201	[245]	MOVE     	0 0
	202	[245]	GETUPVAL 	0 0	; Device
	203	[245]	SETTABLE 	1 -8 2	; "Suspend" -
	204	[246]	GETTABLE 	1 0 -1	; "event_handlers"
	205	[250]	CLOSURE  	2 31	; 0x7ffe4840e250
	206	[250]	GETUPVAL 	0 0	; Device
	207	[250]	MOVE     	0 0
	208	[250]	SETTABLE 	1 -9 2	; "Resume" -
	209	[251]	GETTABLE 	1 0 -1	; "event_handlers"
	210	[253]	CLOSURE  	2 32	; 0x7ffe4840e360
	211	[253]	MOVE     	0 0
	212	[253]	SETTABLE 	1 -21 2	; "Charging" -
	213	[254]	GETTABLE 	1 0 -1	; "event_handlers"
	214	[256]	CLOSURE  	2 33	; 0x7ffe48409d00
	215	[256]	MOVE     	0 0
	216	[256]	SETTABLE 	1 -22 2	; "NotCharging" -
	217	[257]	GETTABLE 	1 0 -1	; "event_handlers"
	218	[264]	CLOSURE  	2 34	; 0x7ffe4840b280
	219	[264]	GETUPVAL 	0 0	; Device
	220	[264]	MOVE     	0 0
	221	[264]	SETTABLE 	1 -28 2	; "UsbPlugIn" -
	222	[265]	GETTABLE 	1 0 -1	; "event_handlers"
	223	[267]	CLOSURE  	2 35	; 0x7ffe4840a490
	224	[267]	GETUPVAL 	0 0	; Device
	225	[267]	SETTABLE 	1 -29 2	; "UsbPlugOut" -
	226	[268]	GETTABLE 	1 0 -1	; "event_handlers"
	227	[273]	CLOSURE  	2 36	; 0x7ffe4840c340
	228	[273]	GETUPVAL 	0 0	; Device
	229	[273]	MOVE     	0 0
	230	[273]	SETTABLE 	1 -2 2	; "__default__" -
	231	[273]	JMP      	67	; to 299
	232	[274]	GETUPVAL 	1 0	; Device
	233	[274]	SELF     	1 1 -30	; "isCervantes"
	234	[274]	CALL     	1 2 2
	235	[274]	TEST     	1 0 0
	236	[274]	JMP      	47	; to 284
	237	[275]	GETTABLE 	1 0 -1	; "event_handlers"
	238	[278]	CLOSURE  	2 37	; 0x7ffe4840d9c0
	239	[278]	MOVE     	0 0
	240	[278]	GETUPVAL 	0 0	; Device
	241	[278]	SETTABLE 	1 -8 2	; "Suspend" -
	242	[279]	GETTABLE 	1 0 -1	; "event_handlers"
	243	[282]	CLOSURE  	2 38	; 0x7ffe4840b930
	244	[282]	GETUPVAL 	0 0	; Device
	245	[282]	MOVE     	0 0
	246	[282]	SETTABLE 	1 -9 2	; "Resume" -
	247	[283]	GETTABLE 	1 0 -1	; "event_handlers"
	248	[285]	CLOSURE  	2 39	; 0x7ffe4840da40
	249	[285]	GETUPVAL 	0 3	; UIManager
	250	[285]	MOVE     	0 0
	251	[285]	SETTABLE 	1 -11 2	; "PowerPress" -
	252	[286]	GETTABLE 	1 0 -1	; "event_handlers"
	253	[296]	CLOSURE  	2 40	; 0x7ffe4840b9b0
	254	[296]	MOVE     	0 0
	255	[296]	GETUPVAL 	0 3	; UIManager
	256	[296]	GETUPVAL 	0 0	; Device
	257	[296]	SETTABLE 	1 -12 2	; "PowerRelease" -
	258	[297]	GETTABLE 	1 0 -1	; "event_handlers"
	259	[302]	CLOSURE  	2 41	; 0x7ffe4840aa50
	260	[302]	MOVE     	0 0
	261	[302]	GETUPVAL 	0 0	; Device
	262	[302]	SETTABLE 	1 -21 2	; "Charging" -
	263	[303]	GETTABLE 	1 0 -1	; "event_handlers"
	264	[308]	CLOSURE  	2 42	; 0x7ffe4840b740
	265	[308]	MOVE     	0 0
	266	[308]	GETUPVAL 	0 0	; Device
	267	[308]	SETTABLE 	1 -22 2	; "NotCharging" -
	268	[309]	GETTABLE 	1 0 -1	; "event_handlers"
	269	[314]	CLOSURE  	2 43	; 0x7ffe4840a070
	270	[314]	MOVE     	0 0
	271	[314]	GETUPVAL 	0 0	; Device
	272	[314]	SETTABLE 	1 -28 2	; "UsbPlugIn" -
	273	[315]	GETTABLE 	1 0 -1	; "event_handlers"
	274	[320]	CLOSURE  	2 44	; 0x7ffe4840a1c0
	275	[320]	MOVE     	0 0
	276	[320]	GETUPVAL 	0 0	; Device
	277	[320]	SETTABLE 	1 -31 2	; "USbPlugOut" -
	278	[321]	GETTABLE 	1 0 -1	; "event_handlers"
	279	[326]	CLOSURE  	2 45	; 0x7ffe4840bf20
	280	[326]	GETUPVAL 	0 0	; Device
	281	[326]	MOVE     	0 0
	282	[326]	SETTABLE 	1 -2 2	; "__default__" -
	283	[326]	JMP      	15	; to 299
	284	[327]	GETUPVAL 	1 0	; Device
	285	[327]	SELF     	1 1 -32	; "isSDL"
	286	[327]	CALL     	1 2 2
	287	[327]	TEST     	1 0 0
	288	[327]	JMP      	10	; to 299
	289	[328]	GETTABLE 	1 0 -1	; "event_handlers"
	290	[331]	CLOSURE  	2 46	; 0x7ffe48408f80
	291	[331]	MOVE     	0 0
	292	[331]	GETUPVAL 	0 0	; Device
	293	[331]	SETTABLE 	1 -8 2	; "Suspend" -
	294	[332]	GETTABLE 	1 0 -1	; "event_handlers"
	295	[335]	CLOSURE  	2 47	; 0x7ffe48604200
	296	[335]	GETUPVAL 	0 0	; Device
	297	[335]	MOVE     	0 0
	298	[335]	SETTABLE 	1 -9 2	; "Resume" -
	299	[337]	RETURN   	0 1

function <./frontend/ui/uimanager.lua:46,48> (5 instructions, 20 bytes at 0x7ffe484073e0)
1 param, 4 slots, 1 upvalue, 1 local, 1 constant, 0 functions
	1	[47]	GETUPVAL 	1 0	; self
	2	[47]	SELF     	1 1 -1	; "sendEvent"
	3	[47]	MOVE     	3 0
	4	[47]	CALL     	1 3 1
	5	[48]	RETURN   	0 1

function <./frontend/ui/uimanager.lua:49,51> (4 instructions, 16 bytes at 0x7ffe484077a0)
0 params, 2 slots, 1 upvalue, 0 locals, 1 constant, 0 functions
	1	[50]	GETUPVAL 	0 0	; self
	2	[50]	SELF     	0 0 -1	; "flushSettings"
	3	[50]	CALL     	0 2 1
	4	[51]	RETURN   	0 1

function <./frontend/ui/uimanager.lua:52,54> (5 instructions, 20 bytes at 0x7ffe48407350)
1 param, 4 slots, 1 upvalue, 1 local, 1 constant, 0 functions
	1	[53]	GETUPVAL 	1 0	; Device
	2	[53]	SELF     	1 1 -1	; "onPowerEvent"
	3	[53]	MOVE     	3 0
	4	[53]	CALL     	1 3 1
	5	[54]	RETURN   	0 1

function <./frontend/ui/uimanager.lua:56,68> (31 instructions, 124 bytes at 0x7ffe48407cd0)
0 params, 5 slots, 6 upvalues, 0 locals, 12 constants, 1 function
	1	[57]	GETUPVAL 	0 0	; self
	2	[57]	SETTABLE 	0 -1 -2	; "_entered_poweroff_stage" true
	3	[58]	GETUPVAL 	0 1	; Screen
	4	[58]	SELF     	0 0 -3	; "setRotationMode"
	5	[58]	LOADK    	2 -4	; 0
	6	[58]	CALL     	0 3 1
	7	[59]	GETGLOBAL	0 -5	; require
	8	[59]	LOADK    	1 -6	; "ui/screensaver"
	9	[59]	CALL     	0 2 2
	10	[59]	SELF     	0 0 -7	; "show"
	11	[59]	LOADK    	2 -8	; "poweroff"
	12	[59]	GETUPVAL 	3 2	; _
	13	[59]	LOADK    	4 -9	; "Powered off"
	14	[59]	CALL     	3 2 0
	15	[59]	CALL     	0 0 1
	16	[60]	GETUPVAL 	0 3	; Device
	17	[60]	SELF     	0 0 -10	; "needsScreenRefreshAfterResume"
	18	[60]	CALL     	0 2 2
	19	[60]	TEST     	0 0 0
	20	[60]	JMP      	3	; to 24
	21	[61]	GETUPVAL 	0 1	; Screen
	22	[61]	SELF     	0 0 -11	; "refreshFull"
	23	[61]	CALL     	0 2 1
	24	[63]	GETUPVAL 	0 4	; UIManager
	25	[63]	SELF     	0 0 -12	; "nextTick"
	26	[67]	CLOSURE  	2 0	; 0x7ffe48407fc0
	27	[67]	GETUPVAL 	0 3	; Device
	28	[67]	GETUPVAL 	0 0	; self
	29	[67]	GETUPVAL 	0 5	; Event
	30	[63]	CALL     	0 3 1
	31	[68]	RETURN   	0 1

function <./frontend/ui/uimanager.lua:63,67> (14 instructions, 56 bytes at 0x7ffe48407fc0)
0 params, 5 slots, 3 upvalues, 0 locals, 5 constants, 0 functions
	1	[64]	GETUPVAL 	0 0	; Device
	2	[64]	SELF     	0 0 -1	; "saveSettings"
	3	[64]	CALL     	0 2 1
	4	[65]	GETUPVAL 	0 1	; self
	5	[65]	SELF     	0 0 -2	; "broadcastEvent"
	6	[65]	GETUPVAL 	2 2	; Event
	7	[65]	SELF     	2 2 -3	; "new"
	8	[65]	LOADK    	4 -4	; "Close"
	9	[65]	CALL     	2 3 0
	10	[65]	CALL     	0 0 1
	11	[66]	GETUPVAL 	0 0	; Device
	12	[66]	SELF     	0 0 -5	; "powerOff"
	13	[66]	CALL     	0 2 1
	14	[67]	RETURN   	0 1

function <./frontend/ui/uimanager.lua:69,81> (31 instructions, 124 bytes at 0x7ffe484087b0)
0 params, 5 slots, 6 upvalues, 0 locals, 12 constants, 1 function
	1	[70]	GETUPVAL 	0 0	; self
	2	[70]	SETTABLE 	0 -1 -2	; "_entered_poweroff_stage" true
	3	[71]	GETUPVAL 	0 1	; Screen
	4	[71]	SELF     	0 0 -3	; "setRotationMode"
	5	[71]	LOADK    	2 -4	; 0
	6	[71]	CALL     	0 3 1
	7	[72]	GETGLOBAL	0 -5	; require
	8	[72]	LOADK    	1 -6	; "ui/screensaver"
	9	[72]	CALL     	0 2 2
	10	[72]	SELF     	0 0 -7	; "show"
	11	[72]	LOADK    	2 -8	; "reboot"
	12	[72]	GETUPVAL 	3 2	; _
	13	[72]	LOADK    	4 -9	; "Rebooting\226\128\166"
	14	[72]	CALL     	3 2 0
	15	[72]	CALL     	0 0 1
	16	[73]	GETUPVAL 	0 3	; Device
	17	[73]	SELF     	0 0 -10	; "needsScreenRefreshAfterResume"
	18	[73]	CALL     	0 2 2
	19	[73]	TEST     	0 0 0
	20	[73]	JMP      	3	; to 24
	21	[74]	GETUPVAL 	0 1	; Screen
	22	[74]	SELF     	0 0 -11	; "refreshFull"
	23	[74]	CALL     	0 2 1
	24	[76]	GETUPVAL 	0 4	; UIManager
	25	[76]	SELF     	0 0 -12	; "nextTick"
	26	[80]	CLOSURE  	2 0	; 0x7ffe484089e0
	27	[80]	GETUPVAL 	0 3	; Device
	28	[80]	GETUPVAL 	0 0	; self
	29	[80]	GETUPVAL 	0 5	; Event
	30	[76]	CALL     	0 3 1
	31	[81]	RETURN   	0 1

function <./frontend/ui/uimanager.lua:76,80> (14 instructions, 56 bytes at 0x7ffe484089e0)
0 params, 5 slots, 3 upvalues, 0 locals, 5 constants, 0 functions
	1	[77]	GETUPVAL 	0 0	; Device
	2	[77]	SELF     	0 0 -1	; "saveSettings"
	3	[77]	CALL     	0 2 1
	4	[78]	GETUPVAL 	0 1	; self
	5	[78]	SELF     	0 0 -2	; "broadcastEvent"
	6	[78]	GETUPVAL 	2 2	; Event
	7	[78]	SELF     	2 2 -3	; "new"
	8	[78]	LOADK    	4 -4	; "Close"
	9	[78]	CALL     	2 3 0
	10	[78]	CALL     	0 0 1
	11	[79]	GETUPVAL 	0 0	; Device
	12	[79]	SELF     	0 0 -5	; "reboot"
	13	[79]	CALL     	0 2 1
	14	[80]	RETURN   	0 1

function <./frontend/ui/uimanager.lua:83,86> (8 instructions, 32 bytes at 0x7ffe484083c0)
0 params, 3 slots, 2 upvalues, 0 locals, 3 constants, 0 functions
	1	[84]	GETUPVAL 	0 0	; self
	2	[84]	SELF     	0 0 -1	; "_beforeSuspend"
	3	[84]	CALL     	0 2 1
	4	[85]	GETUPVAL 	0 1	; Device
	5	[85]	SELF     	0 0 -2	; "onPowerEvent"
	6	[85]	LOADK    	2 -3	; "Power"
	7	[85]	CALL     	0 3 1
	8	[86]	RETURN   	0 1

function <./frontend/ui/uimanager.lua:87,90> (8 instructions, 32 bytes at 0x7ffe48407c50)
0 params, 3 slots, 2 upvalues, 0 locals, 3 constants, 0 functions
	1	[88]	GETUPVAL 	0 0	; Device
	2	[88]	SELF     	0 0 -1	; "onPowerEvent"
	3	[88]	LOADK    	2 -2	; "Power"
	4	[88]	CALL     	0 3 1
	5	[89]	GETUPVAL 	0 1	; self
	6	[89]	SELF     	0 0 -3	; "_afterResume"
	7	[89]	CALL     	0 2 1
	8	[90]	RETURN   	0 1

function <./frontend/ui/uimanager.lua:96,103> (18 instructions, 72 bytes at 0x7ffe48407ac0)
0 params, 3 slots, 2 upvalues, 0 locals, 7 constants, 0 functions
	1	[98]	GETGLOBAL	0 -1	; G_reader_settings
	2	[98]	SELF     	0 0 -2	; "nilOrFalse"
	3	[98]	LOADK    	2 -3	; "input_ignore_gsensor"
	4	[98]	CALL     	0 3 2
	5	[98]	TEST     	0 0 0
	6	[98]	JMP      	4	; to 11
	7	[99]	GETUPVAL 	0 0	; Device
	8	[99]	SELF     	0 0 -4	; "toggleGSensor"
	9	[99]	LOADBOOL 	2 0 0
	10	[99]	CALL     	0 3 1
	11	[101]	GETUPVAL 	0 1	; self
	12	[101]	SELF     	0 0 -5	; "_beforeSuspend"
	13	[101]	CALL     	0 2 1
	14	[102]	GETUPVAL 	0 0	; Device
	15	[102]	SELF     	0 0 -6	; "onPowerEvent"
	16	[102]	LOADK    	2 -7	; "Suspend"
	17	[102]	CALL     	0 3 1
	18	[103]	RETURN   	0 1

function <./frontend/ui/uimanager.lua:104,111> (18 instructions, 72 bytes at 0x7ffe48409850)
0 params, 3 slots, 2 upvalues, 0 locals, 7 constants, 0 functions
	1	[105]	GETUPVAL 	0 0	; Device
	2	[105]	SELF     	0 0 -1	; "onPowerEvent"
	3	[105]	LOADK    	2 -2	; "Resume"
	4	[105]	CALL     	0 3 1
	5	[106]	GETUPVAL 	0 1	; self
	6	[106]	SELF     	0 0 -3	; "_afterResume"
	7	[106]	CALL     	0 2 1
	8	[108]	GETGLOBAL	0 -4	; G_reader_settings
	9	[108]	SELF     	0 0 -5	; "nilOrFalse"
	10	[108]	LOADK    	2 -6	; "input_ignore_gsensor"
	11	[108]	CALL     	0 3 2
	12	[108]	TEST     	0 0 0
	13	[108]	JMP      	4	; to 18
	14	[109]	GETUPVAL 	0 0	; Device
	15	[109]	SELF     	0 0 -7	; "toggleGSensor"
	16	[109]	LOADBOOL 	2 1 0
	17	[109]	CALL     	0 3 1
	18	[111]	RETURN   	0 1

function <./frontend/ui/uimanager.lua:112,116> (7 instructions, 28 bytes at 0x7ffe48409d80)
0 params, 4 slots, 2 upvalues, 0 locals, 3 constants, 0 functions
	1	[115]	GETUPVAL 	0 0	; UIManager
	2	[115]	SELF     	0 0 -1	; "scheduleIn"
	3	[115]	LOADK    	2 -2	; 2
	4	[115]	GETUPVAL 	3 1	; self
	5	[115]	GETTABLE 	3 3 -3	; "poweroff_action"
	6	[115]	CALL     	0 4 1
	7	[116]	RETURN   	0 1

function <./frontend/ui/uimanager.lua:117,127> (21 instructions, 84 bytes at 0x7ffe48409e90)
0 params, 3 slots, 3 upvalues, 0 locals, 6 constants, 0 functions
	1	[118]	GETUPVAL 	0 0	; self
	2	[118]	GETTABLE 	0 0 -1	; "_entered_poweroff_stage"
	3	[118]	TEST     	0 0 1
	4	[118]	JMP      	16	; to 21
	5	[119]	GETUPVAL 	0 1	; UIManager
	6	[119]	SELF     	0 0 -2	; "unschedule"
	7	[119]	GETUPVAL 	2 0	; self
	8	[119]	GETTABLE 	2 2 -3	; "poweroff_action"
	9	[119]	CALL     	0 3 1
	10	[121]	GETUPVAL 	0 2	; Device
	11	[121]	GETTABLE 	0 0 -4	; "screen_saver_mode"
	12	[121]	TEST     	0 0 0
	13	[121]	JMP      	4	; to 18
	14	[122]	GETUPVAL 	0 0	; self
	15	[122]	SELF     	0 0 -5	; "resume"
	16	[122]	CALL     	0 2 1
	17	[122]	JMP      	3	; to 21
	18	[124]	GETUPVAL 	0 0	; self
	19	[124]	SELF     	0 0 -6	; "suspend"
	20	[124]	CALL     	0 2 1
	21	[127]	RETURN   	0 1

function <./frontend/ui/uimanager.lua:137,139> (4 instructions, 16 bytes at 0x7ffe484092b0)
0 params, 2 slots, 1 upvalue, 0 locals, 1 constant, 0 functions
	1	[138]	GETUPVAL 	0 0	; self
	2	[138]	SELF     	0 0 -1	; "suspend"
	3	[138]	CALL     	0 2 1
	4	[139]	RETURN   	0 1

function <./frontend/ui/uimanager.lua:140,142> (3 instructions, 12 bytes at 0x7ffe4840a970)
0 params, 2 slots, 1 upvalue, 0 locals, 2 constants, 0 functions
	1	[141]	GETUPVAL 	0 0	; Device
	2	[141]	SETTABLE 	0 -1 -2	; "is_cover_closed" false
	3	[142]	RETURN   	0 1

function <./frontend/ui/uimanager.lua:144,147> (6 instructions, 24 bytes at 0x7ffe48408d50)
0 params, 2 slots, 2 upvalues, 0 locals, 3 constants, 0 functions
	1	[145]	GETUPVAL 	0 0	; Device
	2	[145]	SETTABLE 	0 -1 -2	; "is_cover_closed" true
	3	[146]	GETUPVAL 	0 1	; self
	4	[146]	SELF     	0 0 -3	; "suspend"
	5	[146]	CALL     	0 2 1
	6	[147]	RETURN   	0 1

function <./frontend/ui/uimanager.lua:148,151> (6 instructions, 24 bytes at 0x7ffe4840ac10)
0 params, 2 slots, 2 upvalues, 0 locals, 3 constants, 0 functions
	1	[149]	GETUPVAL 	0 0	; Device
	2	[149]	SETTABLE 	0 -1 -2	; "is_cover_closed" false
	3	[150]	GETUPVAL 	0 1	; self
	4	[150]	SELF     	0 0 -3	; "resume"
	5	[150]	CALL     	0 2 1
	6	[151]	RETURN   	0 1

function <./frontend/ui/uimanager.lua:153,155> (6 instructions, 24 bytes at 0x7ffe4840aeb0)
0 params, 2 slots, 1 upvalue, 0 locals, 2 constants, 0 functions
	1	[154]	GETUPVAL 	0 0	; Device
	2	[154]	SELF     	0 0 -1	; "getPowerDevice"
	3	[154]	CALL     	0 2 2
	4	[154]	SELF     	0 0 -2	; "toggleFrontlight"
	5	[154]	CALL     	0 2 1
	6	[155]	RETURN   	0 1

function <./frontend/ui/uimanager.lua:156,161> (11 instructions, 44 bytes at 0x7ffe4840b3c0)
0 params, 2 slots, 2 upvalues, 0 locals, 3 constants, 0 functions
	1	[157]	GETUPVAL 	0 0	; self
	2	[157]	SELF     	0 0 -1	; "_beforeCharging"
	3	[157]	CALL     	0 2 1
	4	[158]	GETUPVAL 	0 1	; Device
	5	[158]	GETTABLE 	0 0 -2	; "screen_saver_mode"
	6	[158]	TEST     	0 0 0
	7	[158]	JMP      	3	; to 11
	8	[159]	GETUPVAL 	0 0	; self
	9	[159]	SELF     	0 0 -3	; "suspend"
	10	[159]	CALL     	0 2 1
	11	[161]	RETURN   	0 1

function <./frontend/ui/uimanager.lua:162,168> (11 instructions, 44 bytes at 0x7ffe48409a50)
0 params, 2 slots, 2 upvalues, 0 locals, 3 constants, 0 functions
	1	[164]	GETUPVAL 	0 0	; self
	2	[164]	SELF     	0 0 -1	; "_afterNotCharging"
	3	[164]	CALL     	0 2 1
	4	[165]	GETUPVAL 	0 1	; Device
	5	[165]	GETTABLE 	0 0 -2	; "screen_saver_mode"
	6	[165]	TEST     	0 0 0
	7	[165]	JMP      	3	; to 11
	8	[166]	GETUPVAL 	0 0	; self
	9	[166]	SELF     	0 0 -3	; "suspend"
	10	[166]	CALL     	0 2 1
	11	[168]	RETURN   	0 1

function <./frontend/ui/uimanager.lua:169,177> (9 instructions, 36 bytes at 0x7ffe4840ba80)
1 param, 4 slots, 2 upvalues, 1 local, 2 constants, 0 functions
	1	[174]	GETUPVAL 	1 0	; Device
	2	[174]	GETTABLE 	1 1 -1	; "screen_saver_mode"
	3	[174]	TEST     	1 0 1
	4	[174]	JMP      	4	; to 9
	5	[175]	GETUPVAL 	1 1	; self
	6	[175]	SELF     	1 1 -2	; "sendEvent"
	7	[175]	MOVE     	3 0
	8	[175]	CALL     	1 3 1
	9	[177]	RETURN   	0 1

function <./frontend/ui/uimanager.lua:179,182> (7 instructions, 28 bytes at 0x7ffe4840bc30)
0 params, 2 slots, 2 upvalues, 0 locals, 2 constants, 0 functions
	1	[180]	GETUPVAL 	0 0	; self
	2	[180]	SELF     	0 0 -1	; "_beforeSuspend"
	3	[180]	CALL     	0 2 1
	4	[181]	GETUPVAL 	0 1	; Device
	5	[181]	SELF     	0 0 -2	; "intoScreenSaver"
	6	[181]	CALL     	0 2 1
	7	[182]	RETURN   	0 1

function <./frontend/ui/uimanager.lua:183,186> (7 instructions, 28 bytes at 0x7ffe4840a550)
0 params, 2 slots, 2 upvalues, 0 locals, 2 constants, 0 functions
	1	[184]	GETUPVAL 	0 0	; Device
	2	[184]	SELF     	0 0 -1	; "outofScreenSaver"
	3	[184]	CALL     	0 2 1
	4	[185]	GETUPVAL 	0 1	; self
	5	[185]	SELF     	0 0 -2	; "_afterResume"
	6	[185]	CALL     	0 2 1
	7	[186]	RETURN   	0 1

function <./frontend/ui/uimanager.lua:187,190> (7 instructions, 28 bytes at 0x7ffe4840a390)
0 params, 2 slots, 2 upvalues, 0 locals, 2 constants, 0 functions
	1	[188]	GETUPVAL 	0 0	; self
	2	[188]	SELF     	0 0 -1	; "_beforeCharging"
	3	[188]	CALL     	0 2 1
	4	[189]	GETUPVAL 	0 1	; Device
	5	[189]	SELF     	0 0 -2	; "usbPlugIn"
	6	[189]	CALL     	0 2 1
	7	[190]	RETURN   	0 1

function <./frontend/ui/uimanager.lua:191,194> (7 instructions, 28 bytes at 0x7ffe4840c3e0)
0 params, 2 slots, 2 upvalues, 0 locals, 2 constants, 0 functions
	1	[192]	GETUPVAL 	0 0	; Device
	2	[192]	SELF     	0 0 -1	; "usbPlugOut"
	3	[192]	CALL     	0 2 1
	4	[193]	GETUPVAL 	0 1	; self
	5	[193]	SELF     	0 0 -2	; "_afterNotCharging"
	6	[193]	CALL     	0 2 1
	7	[194]	RETURN   	0 1

function <./frontend/ui/uimanager.lua:196,198> (7 instructions, 28 bytes at 0x7ffe4840c220)
0 params, 4 slots, 2 upvalues, 0 locals, 3 constants, 0 functions
	1	[197]	GETUPVAL 	0 0	; UIManager
	2	[197]	SELF     	0 0 -1	; "scheduleIn"
	3	[197]	LOADK    	2 -2	; 2
	4	[197]	GETUPVAL 	3 1	; self
	5	[197]	GETTABLE 	3 3 -3	; "poweroff_action"
	6	[197]	CALL     	0 4 1
	7	[198]	RETURN   	0 1

function <./frontend/ui/uimanager.lua:199,209> (21 instructions, 84 bytes at 0x7ffe4840c740)
0 params, 3 slots, 3 upvalues, 0 locals, 6 constants, 0 functions
	1	[200]	GETUPVAL 	0 0	; self
	2	[200]	GETTABLE 	0 0 -1	; "_entered_poweroff_stage"
	3	[200]	TEST     	0 0 1
	4	[200]	JMP      	16	; to 21
	5	[201]	GETUPVAL 	0 1	; UIManager
	6	[201]	SELF     	0 0 -2	; "unschedule"
	7	[201]	GETUPVAL 	2 0	; self
	8	[201]	GETTABLE 	2 2 -3	; "poweroff_action"
	9	[201]	CALL     	0 3 1
	10	[203]	GETUPVAL 	0 2	; Device
	11	[203]	GETTABLE 	0 0 -4	; "screen_saver_mode"
	12	[203]	TEST     	0 0 0
	13	[203]	JMP      	4	; to 18
	14	[204]	GETUPVAL 	0 0	; self
	15	[204]	SELF     	0 0 -5	; "resume"
	16	[204]	CALL     	0 2 1
	17	[204]	JMP      	3	; to 21
	18	[206]	GETUPVAL 	0 0	; self
	19	[206]	SELF     	0 0 -6	; "suspend"
	20	[206]	CALL     	0 2 1
	21	[209]	RETURN   	0 1

function <./frontend/ui/uimanager.lua:210,214> (10 instructions, 40 bytes at 0x7ffe4840ce20)
0 params, 2 slots, 2 upvalues, 0 locals, 3 constants, 0 functions
	1	[211]	GETUPVAL 	0 0	; self
	2	[211]	SELF     	0 0 -1	; "_beforeSuspend"
	3	[211]	CALL     	0 2 1
	4	[212]	GETUPVAL 	0 1	; Device
	5	[212]	SELF     	0 0 -2	; "intoScreenSaver"
	6	[212]	CALL     	0 2 1
	7	[213]	GETUPVAL 	0 1	; Device
	8	[213]	SELF     	0 0 -3	; "suspend"
	9	[213]	CALL     	0 2 1
	10	[214]	RETURN   	0 1

function <./frontend/ui/uimanager.lua:215,219> (10 instructions, 40 bytes at 0x7ffe4840d0c0)
0 params, 2 slots, 2 upvalues, 0 locals, 3 constants, 0 functions
	1	[216]	GETUPVAL 	0 0	; Device
	2	[216]	SELF     	0 0 -1	; "resume"
	3	[216]	CALL     	0 2 1
	4	[217]	GETUPVAL 	0 0	; Device
	5	[217]	SELF     	0 0 -2	; "outofScreenSaver"
	6	[217]	CALL     	0 2 1
	7	[218]	GETUPVAL 	0 1	; self
	8	[218]	SELF     	0 0 -3	; "_afterResume"
	9	[218]	CALL     	0 2 1
	10	[219]	RETURN   	0 1

function <./frontend/ui/uimanager.lua:220,225> (9 instructions, 36 bytes at 0x7ffe4840d3b0)
1 param, 4 slots, 2 upvalues, 1 local, 2 constants, 0 functions
	1	[222]	GETUPVAL 	1 0	; Device
	2	[222]	GETTABLE 	1 1 -1	; "screen_saver_mode"
	3	[222]	TEST     	1 0 1
	4	[222]	JMP      	4	; to 9
	5	[223]	GETUPVAL 	1 1	; self
	6	[223]	SELF     	1 1 -2	; "sendEvent"
	7	[223]	MOVE     	3 0
	8	[223]	CALL     	1 3 1
	9	[225]	RETURN   	0 1

function <./frontend/ui/uimanager.lua:227,229> (7 instructions, 28 bytes at 0x7ffe4840d530)
0 params, 4 slots, 2 upvalues, 0 locals, 3 constants, 0 functions
	1	[228]	GETUPVAL 	0 0	; UIManager
	2	[228]	SELF     	0 0 -1	; "scheduleIn"
	3	[228]	LOADK    	2 -2	; 2
	4	[228]	GETUPVAL 	3 1	; self
	5	[228]	GETTABLE 	3 3 -3	; "poweroff_action"
	6	[228]	CALL     	0 4 1
	7	[229]	RETURN   	0 1

function <./frontend/ui/uimanager.lua:230,240> (21 instructions, 84 bytes at 0x7ffe4840d920)
0 params, 3 slots, 3 upvalues, 0 locals, 6 constants, 0 functions
	1	[231]	GETUPVAL 	0 0	; self
	2	[231]	GETTABLE 	0 0 -1	; "_entered_poweroff_stage"
	3	[231]	TEST     	0 0 1
	4	[231]	JMP      	16	; to 21
	5	[232]	GETUPVAL 	0 1	; UIManager
	6	[232]	SELF     	0 0 -2	; "unschedule"
	7	[232]	GETUPVAL 	2 0	; self
	8	[232]	GETTABLE 	2 2 -3	; "poweroff_action"
	9	[232]	CALL     	0 3 1
	10	[234]	GETUPVAL 	0 2	; Device
	11	[234]	GETTABLE 	0 0 -4	; "screen_saver_mode"
	12	[234]	TEST     	0 0 0
	13	[234]	JMP      	4	; to 18
	14	[235]	GETUPVAL 	0 0	; self
	15	[235]	SELF     	0 0 -5	; "resume"
	16	[235]	CALL     	0 2 1
	17	[235]	JMP      	3	; to 21
	18	[237]	GETUPVAL 	0 0	; self
	19	[237]	SELF     	0 0 -6	; "suspend"
	20	[237]	CALL     	0 2 1
	21	[240]	RETURN   	0 1

function <./frontend/ui/uimanager.lua:241,245> (10 instructions, 40 bytes at 0x7ffe4840db00)
0 params, 2 slots, 2 upvalues, 0 locals, 3 constants, 0 functions
	1	[242]	GETUPVAL 	0 0	; self
	2	[242]	SELF     	0 0 -1	; "_beforeSuspend"
	3	[242]	CALL     	0 2 1
	4	[243]	GETUPVAL 	0 1	; Device
	5	[243]	SELF     	0 0 -2	; "intoScreenSaver"
	6	[243]	CALL     	0 2 1
	7	[244]	GETUPVAL 	0 1	; Device
	8	[244]	SELF     	0 0 -3	; "suspend"
	9	[244]	CALL     	0 2 1
	10	[245]	RETURN   	0 1

function <./frontend/ui/uimanager.lua:246,250> (10 instructions, 40 bytes at 0x7ffe4840e250)
0 params, 2 slots, 2 upvalues, 0 locals, 3 constants, 0 functions
	1	[247]	GETUPVAL 	0 0	; Device
	2	[247]	SELF     	0 0 -1	; "resume"
	3	[247]	CALL     	0 2 1
	4	[248]	GETUPVAL 	0 0	; Device
	5	[248]	SELF     	0 0 -2	; "outofScreenSaver"
	6	[248]	CALL     	0 2 1
	7	[249]	GETUPVAL 	0 1	; self
	8	[249]	SELF     	0 0 -3	; "_afterResume"
	9	[249]	CALL     	0 2 1
	10	[250]	RETURN   	0 1

function <./frontend/ui/uimanager.lua:251,253> (4 instructions, 16 bytes at 0x7ffe4840e360)
0 params, 2 slots, 1 upvalue, 0 locals, 1 constant, 0 functions
	1	[252]	GETUPVAL 	0 0	; self
	2	[252]	SELF     	0 0 -1	; "_beforeCharging"
	3	[252]	CALL     	0 2 1
	4	[253]	RETURN   	0 1

function <./frontend/ui/uimanager.lua:254,256> (4 instructions, 16 bytes at 0x7ffe48409d00)
0 params, 2 slots, 1 upvalue, 0 locals, 1 constant, 0 functions
	1	[255]	GETUPVAL 	0 0	; self
	2	[255]	SELF     	0 0 -1	; "_afterNotCharging"
	3	[255]	CALL     	0 2 1
	4	[256]	RETURN   	0 1

function <./frontend/ui/uimanager.lua:257,264> (17 instructions, 68 bytes at 0x7ffe4840b280)
0 params, 2 slots, 2 upvalues, 0 locals, 5 constants, 0 functions
	1	[258]	GETUPVAL 	0 0	; Device
	2	[258]	GETTABLE 	0 0 -1	; "screen_saver_mode"
	3	[258]	TEST     	0 0 0
	4	[258]	JMP      	9	; to 14
	5	[259]	GETUPVAL 	0 0	; Device
	6	[259]	SELF     	0 0 -2	; "resume"
	7	[259]	CALL     	0 2 1
	8	[260]	GETUPVAL 	0 0	; Device
	9	[260]	SELF     	0 0 -3	; "outofScreenSaver"
	10	[260]	CALL     	0 2 1
	11	[261]	GETUPVAL 	0 1	; self
	12	[261]	SELF     	0 0 -4	; "_afterResume"
	13	[261]	CALL     	0 2 1
	14	[263]	GETUPVAL 	0 0	; Device
	15	[263]	SELF     	0 0 -5	; "usbPlugIn"
	16	[263]	CALL     	0 2 1
	17	[264]	RETURN   	0 1

function <./frontend/ui/uimanager.lua:265,267> (4 instructions, 16 bytes at 0x7ffe4840a490)
0 params, 2 slots, 1 upvalue, 0 locals, 1 constant, 0 functions
	1	[266]	GETUPVAL 	0 0	; Device
	2	[266]	SELF     	0 0 -1	; "usbPlugOut"
	3	[266]	CALL     	0 2 1
	4	[267]	RETURN   	0 1

function <./frontend/ui/uimanager.lua:268,273> (9 instructions, 36 bytes at 0x7ffe4840c340)
1 param, 4 slots, 2 upvalues, 1 local, 2 constants, 0 functions
	1	[270]	GETUPVAL 	1 0	; Device
	2	[270]	GETTABLE 	1 1 -1	; "screen_saver_mode"
	3	[270]	TEST     	1 0 1
	4	[270]	JMP      	4	; to 9
	5	[271]	GETUPVAL 	1 1	; self
	6	[271]	SELF     	1 1 -2	; "sendEvent"
	7	[271]	MOVE     	3 0
	8	[271]	CALL     	1 3 1
	9	[273]	RETURN   	0 1

function <./frontend/ui/uimanager.lua:275,278> (8 instructions, 32 bytes at 0x7ffe4840d9c0)
0 params, 3 slots, 2 upvalues, 0 locals, 3 constants, 0 functions
	1	[276]	GETUPVAL 	0 0	; self
	2	[276]	SELF     	0 0 -1	; "_beforeSuspend"
	3	[276]	CALL     	0 2 1
	4	[277]	GETUPVAL 	0 1	; Device
	5	[277]	SELF     	0 0 -2	; "onPowerEvent"
	6	[277]	LOADK    	2 -3	; "Suspend"
	7	[277]	CALL     	0 3 1
	8	[278]	RETURN   	0 1

function <./frontend/ui/uimanager.lua:279,282> (8 instructions, 32 bytes at 0x7ffe4840b930)
0 params, 3 slots, 2 upvalues, 0 locals, 3 constants, 0 functions
	1	[280]	GETUPVAL 	0 0	; Device
	2	[280]	SELF     	0 0 -1	; "onPowerEvent"
	3	[280]	LOADK    	2 -2	; "Resume"
	4	[280]	CALL     	0 3 1
	5	[281]	GETUPVAL 	0 1	; self
	6	[281]	SELF     	0 0 -3	; "_afterResume"
	7	[281]	CALL     	0 2 1
	8	[282]	RETURN   	0 1

function <./frontend/ui/uimanager.lua:283,285> (7 instructions, 28 bytes at 0x7ffe4840da40)
0 params, 4 slots, 2 upvalues, 0 locals, 3 constants, 0 functions
	1	[284]	GETUPVAL 	0 0	; UIManager
	2	[284]	SELF     	0 0 -1	; "scheduleIn"
	3	[284]	LOADK    	2 -2	; 2
	4	[284]	GETUPVAL 	3 1	; self
	5	[284]	GETTABLE 	3 3 -3	; "poweroff_action"
	6	[284]	CALL     	0 4 1
	7	[285]	RETURN   	0 1

function <./frontend/ui/uimanager.lua:286,296> (21 instructions, 84 bytes at 0x7ffe4840b9b0)
0 params, 3 slots, 3 upvalues, 0 locals, 6 constants, 0 functions
	1	[287]	GETUPVAL 	0 0	; self
	2	[287]	GETTABLE 	0 0 -1	; "_entered_poweroff_stage"
	3	[287]	TEST     	0 0 1
	4	[287]	JMP      	16	; to 21
	5	[288]	GETUPVAL 	0 1	; UIManager
	6	[288]	SELF     	0 0 -2	; "unschedule"
	7	[288]	GETUPVAL 	2 0	; self
	8	[288]	GETTABLE 	2 2 -3	; "poweroff_action"
	9	[288]	CALL     	0 3 1
	10	[290]	GETUPVAL 	0 2	; Device
	11	[290]	GETTABLE 	0 0 -4	; "screen_saver_mode"
	12	[290]	TEST     	0 0 0
	13	[290]	JMP      	4	; to 18
	14	[291]	GETUPVAL 	0 0	; self
	15	[291]	SELF     	0 0 -5	; "resume"
	16	[291]	CALL     	0 2 1
	17	[291]	JMP      	3	; to 21
	18	[293]	GETUPVAL 	0 0	; self
	19	[293]	SELF     	0 0 -6	; "suspend"
	20	[293]	CALL     	0 2 1
	21	[296]	RETURN   	0 1

function <./frontend/ui/uimanager.lua:297,302> (11 instructions, 44 bytes at 0x7ffe4840aa50)
0 params, 2 slots, 2 upvalues, 0 locals, 3 constants, 0 functions
	1	[298]	GETUPVAL 	0 0	; self
	2	[298]	SELF     	0 0 -1	; "_beforeCharging"
	3	[298]	CALL     	0 2 1
	4	[299]	GETUPVAL 	0 1	; Device
	5	[299]	GETTABLE 	0 0 -2	; "screen_saver_mode"
	6	[299]	TEST     	0 0 0
	7	[299]	JMP      	3	; to 11
	8	[300]	GETUPVAL 	0 0	; self
	9	[300]	SELF     	0 0 -3	; "suspend"
	10	[300]	CALL     	0 2 1
	11	[302]	RETURN   	0 1

function <./frontend/ui/uimanager.lua:303,308> (11 instructions, 44 bytes at 0x7ffe4840b740)
0 params, 2 slots, 2 upvalues, 0 locals, 3 constants, 0 functions
	1	[304]	GETUPVAL 	0 0	; self
	2	[304]	SELF     	0 0 -1	; "_afterNotCharging"
	3	[304]	CALL     	0 2 1
	4	[305]	GETUPVAL 	0 1	; Device
	5	[305]	GETTABLE 	0 0 -2	; "screen_saver_mode"
	6	[305]	TEST     	0 0 0
	7	[305]	JMP      	3	; to 11
	8	[306]	GETUPVAL 	0 0	; self
	9	[306]	SELF     	0 0 -3	; "suspend"
	10	[306]	CALL     	0 2 1
	11	[308]	RETURN   	0 1

function <./frontend/ui/uimanager.lua:309,314> (11 instructions, 44 bytes at 0x7ffe4840a070)
0 params, 2 slots, 2 upvalues, 0 locals, 3 constants, 0 functions
	1	[310]	GETUPVAL 	0 0	; self
	2	[310]	SELF     	0 0 -1	; "_beforeCharging"
	3	[310]	CALL     	0 2 1
	4	[311]	GETUPVAL 	0 1	; Device
	5	[311]	GETTABLE 	0 0 -2	; "screen_saver_mode"
	6	[311]	TEST     	0 0 0
	7	[311]	JMP      	3	; to 11
	8	[312]	GETUPVAL 	0 0	; self
	9	[312]	SELF     	0 0 -3	; "suspend"
	10	[312]	CALL     	0 2 1
	11	[314]	RETURN   	0 1

function <./frontend/ui/uimanager.lua:315,320> (11 instructions, 44 bytes at 0x7ffe4840a1c0)
0 params, 2 slots, 2 upvalues, 0 locals, 3 constants, 0 functions
	1	[316]	GETUPVAL 	0 0	; self
	2	[316]	SELF     	0 0 -1	; "_afterNotCharging"
	3	[316]	CALL     	0 2 1
	4	[317]	GETUPVAL 	0 1	; Device
	5	[317]	GETTABLE 	0 0 -2	; "screen_saver_mode"
	6	[317]	TEST     	0 0 0
	7	[317]	JMP      	3	; to 11
	8	[318]	GETUPVAL 	0 0	; self
	9	[318]	SELF     	0 0 -3	; "suspend"
	10	[318]	CALL     	0 2 1
	11	[320]	RETURN   	0 1

function <./frontend/ui/uimanager.lua:321,326> (9 instructions, 36 bytes at 0x7ffe4840bf20)
1 param, 4 slots, 2 upvalues, 1 local, 2 constants, 0 functions
	1	[323]	GETUPVAL 	1 0	; Device
	2	[323]	GETTABLE 	1 1 -1	; "screen_saver_mode"
	3	[323]	TEST     	1 0 1
	4	[323]	JMP      	4	; to 9
	5	[324]	GETUPVAL 	1 1	; self
	6	[324]	SELF     	1 1 -2	; "sendEvent"
	7	[324]	MOVE     	3 0
	8	[324]	CALL     	1 3 1
	9	[326]	RETURN   	0 1

function <./frontend/ui/uimanager.lua:328,331> (7 instructions, 28 bytes at 0x7ffe48408f80)
0 params, 2 slots, 2 upvalues, 0 locals, 2 constants, 0 functions
	1	[329]	GETUPVAL 	0 0	; self
	2	[329]	SELF     	0 0 -1	; "_beforeSuspend"
	3	[329]	CALL     	0 2 1
	4	[330]	GETUPVAL 	0 1	; Device
	5	[330]	SELF     	0 0 -2	; "simulateSuspend"
	6	[330]	CALL     	0 2 1
	7	[331]	RETURN   	0 1

function <./frontend/ui/uimanager.lua:332,335> (7 instructions, 28 bytes at 0x7ffe48604200)
0 params, 2 slots, 2 upvalues, 0 locals, 2 constants, 0 functions
	1	[333]	GETUPVAL 	0 0	; Device
	2	[333]	SELF     	0 0 -1	; "simulateResume"
	3	[333]	CALL     	0 2 1
	4	[334]	GETUPVAL 	0 1	; self
	5	[334]	SELF     	0 0 -2	; "_afterResume"
	6	[334]	CALL     	0 2 1
	7	[335]	RETURN   	0 1

function <./frontend/ui/uimanager.lua:352,380> (76 instructions, 304 bytes at 0x7ffe486049d0)
7 params, 17 slots, 3 upvalues, 13 locals, 24 constants, 0 functions
	1	[353]	TEST     	1 0 1
	2	[353]	JMP      	5	; to 8
	3	[354]	GETUPVAL 	7 0	; logger
	4	[354]	GETTABLE 	7 7 -1	; "dbg"
	5	[354]	LOADK    	8 -2	; "widget not exist to be shown"
	6	[354]	CALL     	7 2 1
	7	[355]	RETURN   	0 1
	8	[357]	GETUPVAL 	7 0	; logger
	9	[357]	GETTABLE 	7 7 -1	; "dbg"
	10	[357]	LOADK    	8 -3	; "show widget:"
	11	[357]	GETTABLE 	9 1 -4	; "id"
	12	[357]	TEST     	9 0 1
	13	[357]	JMP      	6	; to 20
	14	[357]	GETTABLE 	9 1 -5	; "name"
	15	[357]	TEST     	9 0 1
	16	[357]	JMP      	3	; to 20
	17	[357]	GETGLOBAL	9 -6	; tostring
	18	[357]	MOVE     	10 1
	19	[357]	CALL     	9 2 2
	20	[357]	CALL     	7 3 1
	21	[359]	SETTABLE 	0 -7 -8	; "_running" true
	22	[360]	NEWTABLE 	7 0 3
	23	[360]	TESTSET  	8 4 1
	24	[360]	JMP      	1	; to 26
	25	[360]	LOADK    	8 -10	; 0
	26	[360]	SETTABLE 	7 -9 8	; "x" -
	27	[360]	TESTSET  	8 5 1
	28	[360]	JMP      	1	; to 30
	29	[360]	LOADK    	8 -10	; 0
	30	[360]	SETTABLE 	7 -11 8	; "y" -
	31	[360]	SETTABLE 	7 -12 1	; "widget" -
	32	[362]	GETTABLE 	8 0 -13	; "_window_stack"
	33	[362]	LEN      	8 8
	34	[362]	LOADK    	9 -10	; 0
	35	[362]	LOADK    	10 -14	; -1
	36	[362]	FORPREP  	8 18	; to 55
	37	[363]	GETTABLE 	12 0 -13	; "_window_stack"
	38	[363]	GETTABLE 	12 12 11
	39	[365]	GETTABLE 	13 1 -15	; "modal"
	40	[365]	TEST     	13 0 1
	41	[365]	JMP      	6	; to 48
	42	[365]	TEST     	12 0 0
	43	[365]	JMP      	4	; to 48
	44	[365]	GETTABLE 	13 12 -12	; "widget"
	45	[365]	GETTABLE 	13 13 -15	; "modal"
	46	[365]	TEST     	13 0 1
	47	[365]	JMP      	7	; to 55
	48	[366]	GETGLOBAL	13 -16	; table
	49	[366]	GETTABLE 	13 13 -17	; "insert"
	50	[366]	GETTABLE 	14 0 -13	; "_window_stack"
	51	[366]	ADD      	15 11 -18	; - 1
	52	[366]	MOVE     	16 7
	53	[366]	CALL     	13 4 1
	54	[367]	JMP      	1	; to 56
	55	[362]	FORLOOP  	8 -19	; to 37
	56	[371]	SELF     	8 0 -19	; "setDirty"
	57	[371]	MOVE     	10 1
	58	[371]	MOVE     	11 2
	59	[371]	MOVE     	12 3
	60	[371]	MOVE     	13 6
	61	[371]	CALL     	8 6 1
	62	[373]	SELF     	8 1 -20	; "handleEvent"
	63	[373]	GETUPVAL 	10 1	; Event
	64	[373]	SELF     	10 10 -21	; "new"
	65	[373]	LOADK    	12 -22	; "Show"
	66	[373]	CALL     	10 3 0
	67	[373]	CALL     	8 0 1
	68	[375]	GETTABLE 	8 1 -23	; "disable_double_tap"
	69	[375]	EQ       	0 8 -24	; - false
	70	[375]	JMP      	3	; to 74
	71	[376]	GETUPVAL 	8 2	; Input
	72	[376]	SETTABLE 	8 -23 -24	; "disable_double_tap" false
	73	[376]	JMP      	2	; to 76
	74	[378]	GETUPVAL 	8 2	; Input
	75	[378]	SETTABLE 	8 -23 -8	; "disable_double_tap" true
	76	[380]	RETURN   	0 1

function <./frontend/ui/uimanager.lua:392,435> (126 instructions, 504 bytes at 0x7ffe48604e00)
5 params, 15 slots, 3 upvalues, 15 locals, 26 constants, 0 functions
	1	[393]	TEST     	1 0 1
	2	[393]	JMP      	5	; to 8
	3	[394]	GETUPVAL 	5 0	; logger
	4	[394]	GETTABLE 	5 5 -1	; "dbg"
	5	[394]	LOADK    	6 -2	; "widget to be closed does not exist"
	6	[394]	CALL     	5 2 1
	7	[395]	RETURN   	0 1
	8	[397]	GETUPVAL 	5 0	; logger
	9	[397]	GETTABLE 	5 5 -1	; "dbg"
	10	[397]	LOADK    	6 -3	; "close widget:"
	11	[397]	GETTABLE 	7 1 -4	; "name"
	12	[397]	TEST     	7 0 1
	13	[397]	JMP      	6	; to 20
	14	[397]	GETTABLE 	7 1 -5	; "id"
	15	[397]	TEST     	7 0 1
	16	[397]	JMP      	3	; to 20
	17	[397]	GETGLOBAL	7 -6	; tostring
	18	[397]	MOVE     	8 1
	19	[397]	CALL     	7 2 2
	20	[397]	CALL     	5 3 1
	21	[398]	LOADBOOL 	5 0 0
	22	[400]	SELF     	6 1 -7	; "handleEvent"
	23	[400]	GETUPVAL 	8 1	; Event
	24	[400]	SELF     	8 8 -8	; "new"
	25	[400]	LOADK    	10 -9	; "FlushSettings"
	26	[400]	CALL     	8 3 0
	27	[400]	CALL     	6 0 1
	28	[402]	SELF     	6 1 -7	; "handleEvent"
	29	[402]	GETUPVAL 	8 1	; Event
	30	[402]	SELF     	8 8 -8	; "new"
	31	[402]	LOADK    	10 -10	; "CloseWidget"
	32	[402]	CALL     	8 3 0
	33	[402]	CALL     	6 0 1
	34	[404]	GETUPVAL 	6 2	; Input
	35	[404]	SETTABLE 	6 -11 -12	; "disable_double_tap" true
	36	[405]	LOADNIL  	6 6
	37	[407]	GETTABLE 	7 0 -13	; "_window_stack"
	38	[407]	LEN      	7 7
	39	[407]	LOADK    	8 -14	; 1
	40	[407]	LOADK    	9 -15	; -1
	41	[407]	FORPREP  	7 58	; to 100
	42	[408]	GETTABLE 	11 0 -13	; "_window_stack"
	43	[408]	GETTABLE 	11 11 10
	44	[408]	GETTABLE 	11 11 -16	; "widget"
	45	[408]	EQ       	0 11 1
	46	[408]	JMP      	12	; to 59
	47	[409]	GETTABLE 	11 0 -17	; "_dirty"
	48	[409]	GETTABLE 	12 0 -13	; "_window_stack"
	49	[409]	GETTABLE 	12 12 10
	50	[409]	GETTABLE 	12 12 -16	; "widget"
	51	[409]	SETTABLE 	11 12 -18	; - nil
	52	[410]	GETGLOBAL	11 -19	; table
	53	[410]	GETTABLE 	11 11 -20	; "remove"
	54	[410]	GETTABLE 	12 0 -13	; "_window_stack"
	55	[410]	MOVE     	13 10
	56	[410]	CALL     	11 3 1
	57	[411]	LOADBOOL 	5 1 0
	58	[411]	JMP      	41	; to 100
	59	[414]	GETTABLE 	11 0 -13	; "_window_stack"
	60	[414]	GETTABLE 	11 11 10
	61	[414]	GETTABLE 	11 11 -16	; "widget"
	62	[414]	GETTABLE 	11 11 -21	; "dithered"
	63	[414]	TEST     	11 0 0
	64	[414]	JMP      	23	; to 88
	65	[415]	LOADBOOL 	4 1 0
	66	[416]	GETUPVAL 	11 0	; logger
	67	[416]	GETTABLE 	11 11 -1	; "dbg"
	68	[416]	LOADK    	12 -22	; "Lower widget"
	69	[416]	GETTABLE 	13 0 -13	; "_window_stack"
	70	[416]	GETTABLE 	13 13 10
	71	[416]	GETTABLE 	13 13 -16	; "widget"
	72	[416]	GETTABLE 	13 13 -4	; "name"
	73	[416]	TEST     	13 0 1
	74	[416]	JMP      	11	; to 86
	75	[416]	GETTABLE 	13 0 -13	; "_window_stack"
	76	[416]	GETTABLE 	13 13 10
	77	[416]	GETTABLE 	13 13 -16	; "widget"
	78	[416]	GETTABLE 	13 13 -5	; "id"
	79	[416]	TEST     	13 0 1
	80	[416]	JMP      	5	; to 86
	81	[416]	GETGLOBAL	13 -6	; tostring
	82	[416]	GETTABLE 	14 0 -13	; "_window_stack"
	83	[416]	GETTABLE 	14 14 10
	84	[416]	GETTABLE 	14 14 -16	; "widget"
	85	[416]	CALL     	13 2 2
	86	[416]	LOADK    	14 -23	; "was dithered, honoring the dithering hint"
	87	[416]	CALL     	11 4 1
	88	[420]	EQ       	0 6 -18	; - nil
	89	[420]	JMP      	10	; to 100
	90	[420]	GETTABLE 	11 0 -13	; "_window_stack"
	91	[420]	GETTABLE 	11 11 10
	92	[420]	GETTABLE 	11 11 -16	; "widget"
	93	[420]	GETTABLE 	11 11 -11	; "disable_double_tap"
	94	[420]	EQ       	1 11 -18	; - nil
	95	[420]	JMP      	4	; to 100
	96	[421]	GETTABLE 	11 0 -13	; "_window_stack"
	97	[421]	GETTABLE 	11 11 10
	98	[421]	GETTABLE 	11 11 -16	; "widget"
	99	[421]	GETTABLE 	6 11 -11	; "disable_double_tap"
	100	[407]	FORLOOP  	7 -59	; to 42
	101	[425]	EQ       	1 6 -18	; - nil
	102	[425]	JMP      	2	; to 105
	103	[426]	GETUPVAL 	7 2	; Input
	104	[426]	SETTABLE 	7 -11 6	; "disable_double_tap" -
	105	[428]	TEST     	5 0 0
	106	[428]	JMP      	19	; to 126
	107	[428]	GETTABLE 	7 1 -24	; "invisible"
	108	[428]	TEST     	7 0 1
	109	[428]	JMP      	16	; to 126
	110	[430]	LOADK    	7 -14	; 1
	111	[430]	GETTABLE 	8 0 -13	; "_window_stack"
	112	[430]	LEN      	8 8
	113	[430]	LOADK    	9 -14	; 1
	114	[430]	FORPREP  	7 5	; to 120
	115	[431]	SELF     	11 0 -25	; "setDirty"
	116	[431]	GETTABLE 	13 0 -13	; "_window_stack"
	117	[431]	GETTABLE 	13 13 10
	118	[431]	GETTABLE 	13 13 -16	; "widget"
	119	[431]	CALL     	11 3 1
	120	[430]	FORLOOP  	7 -6	; to 115
	121	[433]	SELF     	7 0 -26	; "_refresh"
	122	[433]	MOVE     	9 2
	123	[433]	MOVE     	10 3
	124	[433]	MOVE     	11 4
	125	[433]	CALL     	7 5 1
	126	[435]	RETURN   	0 1

function <./frontend/ui/uimanager.lua:438,474> (64 instructions, 256 bytes at 0x7ffe48605150)
3+ params, 13 slots, 1 upvalue, 10 locals, 13 constants, 0 functions
	1	[439]	LOADK    	4 -1	; 1
	2	[439]	LOADK    	5 -1	; 1
	3	[439]	GETTABLE 	6 0 -2	; "_task_queue"
	4	[439]	LEN      	6 6
	5	[440]	EQ       	1 6 -3	; - 0
	6	[440]	JMP      	44	; to 51
	7	[441]	GETTABLE 	7 1 -1	; 1
	8	[441]	GETUPVAL 	8 0	; MILLION
	9	[441]	MUL      	7 7 8
	10	[441]	GETTABLE 	8 1 -4	; 2
	11	[441]	ADD      	7 7 8
	12	[444]	GETGLOBAL	8 -5	; math
	13	[444]	GETTABLE 	8 8 -6	; "floor"
	14	[444]	SUB      	9 6 5
	15	[444]	DIV      	9 9 -4	; - 2
	16	[444]	ADD      	9 5 9
	17	[444]	CALL     	8 2 2
	18	[444]	MOVE     	4 8
	19	[445]	GETTABLE 	8 0 -2	; "_task_queue"
	20	[445]	GETTABLE 	8 8 4
	21	[445]	GETTABLE 	8 8 -7	; "time"
	22	[446]	GETTABLE 	9 8 -1	; 1
	23	[446]	GETUPVAL 	10 0	; MILLION
	24	[446]	MUL      	9 9 10
	25	[446]	GETTABLE 	10 8 -4	; 2
	26	[446]	ADD      	9 9 10
	27	[447]	LT       	0 9 7
	28	[447]	JMP      	12	; to 41
	29	[448]	EQ       	0 5 6
	30	[448]	JMP      	3	; to 34
	31	[449]	ADD      	4 6 -1	; - 1
	32	[450]	JMP      	18	; to 51
	33	[450]	JMP      	15	; to 49
	34	[451]	ADD      	10 5 -1	; - 1
	35	[451]	EQ       	0 10 6
	36	[451]	JMP      	2	; to 39
	37	[452]	MOVE     	5 6
	38	[452]	JMP      	10	; to 49
	39	[454]	MOVE     	5 4
	40	[455]	JMP      	8	; to 49
	41	[456]	LT       	0 7 9
	42	[456]	JMP      	8	; to 51
	43	[457]	MOVE     	6 4
	44	[458]	EQ       	0 5 6
	45	[458]	JMP      	3	; to 49
	46	[459]	JMP      	4	; to 51
	47	[460]	JMP      	1	; to 49
	48	[464]	JMP      	2	; to 51
	49	[466]	LT       	0 6 5
	50	[466]	JMP      	-39	; to 12
	51	[468]	GETGLOBAL	7 -8	; table
	52	[468]	GETTABLE 	7 7 -9	; "insert"
	53	[468]	GETTABLE 	8 0 -2	; "_task_queue"
	54	[468]	MOVE     	9 4
	55	[468]	NEWTABLE 	10 0 3
	56	[469]	SETTABLE 	10 -7 1	; "time" -
	57	[470]	SETTABLE 	10 -10 2	; "action" -
	58	[471]	NEWTABLE 	11 0 0
	59	[471]	VARARG   	12 0
	60	[471]	SETLIST  	11 0 1	; 1
	61	[471]	SETTABLE 	10 -11 11	; "args" -
	62	[468]	CALL     	7 4 1
	63	[473]	SETTABLE 	0 -12 -13	; "_task_queue_dirty" true
	64	[474]	RETURN   	0 1

function <./frontend/ui/uimanager.lua:476,479> (18 instructions, 72 bytes at 0x7ffe48606170)
3 params, 6 slots, 0 upvalues, 3 locals, 6 constants, 0 functions
	1	[477]	GETGLOBAL	3 -1	; assert
	2	[477]	GETTABLE 	4 1 -2	; 1
	3	[477]	LE       	0 -3 4	; 0 -
	4	[477]	JMP      	3	; to 8
	5	[477]	GETTABLE 	4 1 -4	; 2
	6	[477]	LE       	1 -3 4	; 0 -
	7	[477]	JMP      	1	; to 9
	8	[477]	LOADBOOL 	4 0 1
	9	[477]	LOADBOOL 	4 1 0
	10	[477]	LOADK    	5 -5	; "Only positive time allowed"
	11	[477]	CALL     	3 3 1
	12	[478]	GETGLOBAL	3 -1	; assert
	13	[478]	EQ       	0 2 -6	; - nil
	14	[478]	JMP      	1	; to 16
	15	[478]	LOADBOOL 	4 0 1
	16	[478]	LOADBOOL 	4 1 0
	17	[478]	CALL     	3 2 1
	18	[479]	RETURN   	0 1

function <./frontend/ui/uimanager.lua:482,493> (35 instructions, 140 bytes at 0x7ffe48606a50)
3+ params, 12 slots, 2 upvalues, 7 locals, 6 constants, 0 functions
	1	[483]	NEWTABLE 	4 0 0
	2	[483]	GETUPVAL 	5 0	; util
	3	[483]	GETTABLE 	5 5 -1	; "gettime"
	4	[483]	CALL     	5 1 0
	5	[483]	SETLIST  	4 0 1	; 1
	6	[484]	GETGLOBAL	5 -2	; math
	7	[484]	GETTABLE 	5 5 -3	; "floor"
	8	[484]	MOVE     	6 1
	9	[484]	CALL     	5 2 2
	10	[485]	SUB      	6 1 5
	11	[485]	GETUPVAL 	7 1	; MILLION
	12	[485]	MUL      	6 6 7
	13	[486]	GETTABLE 	7 4 -4	; 1
	14	[486]	ADD      	7 7 5
	15	[486]	SETTABLE 	4 -4 7	; 1 -
	16	[487]	GETTABLE 	7 4 -5	; 2
	17	[487]	ADD      	7 7 6
	18	[487]	SETTABLE 	4 -5 7	; 2 -
	19	[488]	GETTABLE 	7 4 -5	; 2
	20	[488]	GETUPVAL 	8 1	; MILLION
	21	[488]	LE       	0 8 7
	22	[488]	JMP      	7	; to 30
	23	[489]	GETTABLE 	7 4 -4	; 1
	24	[489]	ADD      	7 7 -4	; - 1
	25	[489]	SETTABLE 	4 -4 7	; 1 -
	26	[490]	GETTABLE 	7 4 -5	; 2
	27	[490]	GETUPVAL 	8 1	; MILLION
	28	[490]	SUB      	7 7 8
	29	[490]	SETTABLE 	4 -5 7	; 2 -
	30	[492]	SELF     	7 0 -6	; "schedule"
	31	[492]	MOVE     	9 4
	32	[492]	MOVE     	10 2
	33	[492]	VARARG   	11 0
	34	[492]	CALL     	7 0 1
	35	[493]	RETURN   	0 1

function <./frontend/ui/uimanager.lua:495,497> (8 instructions, 32 bytes at 0x7ffe486073d0)
3 params, 6 slots, 0 upvalues, 3 locals, 3 constants, 0 functions
	1	[496]	GETGLOBAL	3 -1	; assert
	2	[496]	LE       	1 -2 1	; 0 -
	3	[496]	JMP      	1	; to 5
	4	[496]	LOADBOOL 	4 0 1
	5	[496]	LOADBOOL 	4 1 0
	6	[496]	LOADK    	5 -3	; "Only positive seconds allowed"
	7	[496]	CALL     	3 3 1
	8	[497]	RETURN   	0 1

function <./frontend/ui/uimanager.lua:499,501> (6 instructions, 24 bytes at 0x7ffe486071f0)
2 params, 6 slots, 0 upvalues, 2 locals, 2 constants, 0 functions
	1	[500]	SELF     	2 0 -1	; "scheduleIn"
	2	[500]	LOADK    	4 -2	; 0
	3	[500]	MOVE     	5 1
	4	[500]	TAILCALL 	2 4 0
	5	[500]	RETURN   	2 0
	6	[501]	RETURN   	0 1

function <./frontend/ui/uimanager.lua:504,506> (7 instructions, 28 bytes at 0x7ffe48607570)
2 params, 5 slots, 0 upvalues, 2 locals, 1 constant, 1 function
	1	[505]	SELF     	2 0 -1	; "nextTick"
	2	[505]	CLOSURE  	4 0	; 0x7ffe48607a20
	3	[505]	MOVE     	0 0
	4	[505]	MOVE     	0 1
	5	[505]	TAILCALL 	2 3 0
	6	[505]	RETURN   	2 0
	7	[506]	RETURN   	0 1

function <./frontend/ui/uimanager.lua:505,505> (5 instructions, 20 bytes at 0x7ffe48607a20)
0 params, 3 slots, 2 upvalues, 0 locals, 1 constant, 0 functions
	1	[505]	GETUPVAL 	0 0	; self
	2	[505]	SELF     	0 0 -1	; "nextTick"
	3	[505]	GETUPVAL 	2 1	; action
	4	[505]	CALL     	0 3 1
	5	[505]	RETURN   	0 1

function <./frontend/ui/uimanager.lua:524,530> (17 instructions, 68 bytes at 0x7ffe48607c10)
2 params, 9 slots, 0 upvalues, 6 locals, 6 constants, 0 functions
	1	[525]	GETTABLE 	2 0 -1	; "_task_queue"
	2	[525]	LEN      	2 2
	3	[525]	LOADK    	3 -2	; 1
	4	[525]	LOADK    	4 -3	; -1
	5	[525]	FORPREP  	2 10	; to 16
	6	[526]	GETTABLE 	6 0 -1	; "_task_queue"
	7	[526]	GETTABLE 	6 6 5
	8	[526]	GETTABLE 	6 6 -4	; "action"
	9	[526]	EQ       	0 6 1
	10	[526]	JMP      	5	; to 16
	11	[527]	GETGLOBAL	6 -5	; table
	12	[527]	GETTABLE 	6 6 -6	; "remove"
	13	[527]	GETTABLE 	7 0 -1	; "_task_queue"
	14	[527]	MOVE     	8 5
	15	[527]	CALL     	6 3 1
	16	[525]	FORLOOP  	2 -11	; to 6
	17	[530]	RETURN   	0 1

function <./frontend/ui/uimanager.lua:532,532> (7 instructions, 28 bytes at 0x7ffe48607f10)
2 params, 4 slots, 0 upvalues, 2 locals, 2 constants, 0 functions
	1	[532]	GETGLOBAL	2 -1	; assert
	2	[532]	EQ       	0 1 -2	; - nil
	3	[532]	JMP      	1	; to 5
	4	[532]	LOADBOOL 	3 0 1
	5	[532]	LOADBOOL 	3 1 0
	6	[532]	CALL     	2 2 1
	7	[532]	RETURN   	0 1

function <./frontend/ui/uimanager.lua:587,647> (179 instructions, 716 bytes at 0x7ffe48608270)
5 params, 16 slots, 2 upvalues, 17 locals, 34 constants, 0 functions
	1	[588]	TEST     	1 0 0
	2	[588]	JMP      	46	; to 49
	3	[589]	EQ       	0 1 -1	; - "all"
	4	[589]	JMP      	23	; to 28
	5	[591]	LOADK    	5 -2	; 1
	6	[591]	GETTABLE 	6 0 -3	; "_window_stack"
	7	[591]	LEN      	6 6
	8	[591]	LOADK    	7 -2	; 1
	9	[591]	FORPREP  	5 16	; to 26
	10	[592]	GETTABLE 	9 0 -4	; "_dirty"
	11	[592]	GETTABLE 	10 0 -3	; "_window_stack"
	12	[592]	GETTABLE 	10 10 8
	13	[592]	GETTABLE 	10 10 -5	; "widget"
	14	[592]	SETTABLE 	9 10 -6	; - true
	15	[594]	GETTABLE 	9 0 -3	; "_window_stack"
	16	[594]	GETTABLE 	9 9 8
	17	[594]	GETTABLE 	9 9 -5	; "widget"
	18	[594]	GETTABLE 	9 9 -7	; "dithered"
	19	[594]	TEST     	9 0 0
	20	[594]	JMP      	5	; to 26
	21	[597]	GETUPVAL 	9 0	; logger
	22	[597]	GETTABLE 	9 9 -8	; "dbg"
	23	[597]	LOADK    	10 -9	; "setDirty on all widgets: found a dithered widget, infecting the refresh queue"
	24	[597]	CALL     	9 2 1
	25	[598]	LOADBOOL 	4 1 0
	26	[591]	FORLOOP  	5 -17	; to 10
	27	[600]	JMP      	40	; to 68
	28	[601]	GETTABLE 	5 1 -10	; "invisible"
	29	[601]	TEST     	5 0 1
	30	[601]	JMP      	37	; to 68
	31	[604]	LOADK    	5 -2	; 1
	32	[604]	GETTABLE 	6 0 -3	; "_window_stack"
	33	[604]	LEN      	6 6
	34	[604]	LOADK    	7 -2	; 1
	35	[604]	FORPREP  	5 7	; to 43
	36	[605]	GETTABLE 	9 0 -3	; "_window_stack"
	37	[605]	GETTABLE 	9 9 8
	38	[605]	GETTABLE 	9 9 -5	; "widget"
	39	[605]	EQ       	0 9 1
	40	[605]	JMP      	2	; to 43
	41	[606]	GETTABLE 	9 0 -4	; "_dirty"
	42	[606]	SETTABLE 	9 1 -6	; - true
	43	[604]	FORLOOP  	5 -8	; to 36
	44	[610]	GETTABLE 	5 1 -7	; "dithered"
	45	[610]	TEST     	5 0 0
	46	[610]	JMP      	21	; to 68
	47	[611]	LOADBOOL 	4 1 0
	48	[613]	JMP      	19	; to 68
	49	[617]	EQ       	0 2 -11	; - "full"
	50	[617]	JMP      	17	; to 68
	51	[618]	LOADK    	5 -2	; 1
	52	[618]	GETTABLE 	6 0 -3	; "_window_stack"
	53	[618]	LEN      	6 6
	54	[618]	LOADK    	7 -2	; 1
	55	[618]	FORPREP  	5 11	; to 67
	56	[620]	GETTABLE 	9 0 -3	; "_window_stack"
	57	[620]	GETTABLE 	9 9 8
	58	[620]	GETTABLE 	9 9 -5	; "widget"
	59	[620]	GETTABLE 	9 9 -7	; "dithered"
	60	[620]	TEST     	9 0 0
	61	[620]	JMP      	5	; to 67
	62	[621]	GETUPVAL 	9 0	; logger
	63	[621]	GETTABLE 	9 9 -8	; "dbg"
	64	[621]	LOADK    	10 -12	; "setDirty full on no specific widget: found a dithered widget, infecting the refresh queue"
	65	[621]	CALL     	9 2 1
	66	[622]	LOADBOOL 	4 1 0
	67	[618]	FORLOOP  	5 -12	; to 56
	68	[628]	GETGLOBAL	5 -13	; type
	69	[628]	MOVE     	6 2
	70	[628]	CALL     	5 2 2
	71	[628]	EQ       	0 5 -14	; - "function"
	72	[628]	JMP      	28	; to 101
	73	[630]	GETGLOBAL	5 -15	; table
	74	[630]	GETTABLE 	5 5 -16	; "insert"
	75	[630]	GETTABLE 	6 0 -17	; "_refresh_func_stack"
	76	[630]	MOVE     	7 2
	77	[630]	CALL     	5 3 1
	78	[631]	GETUPVAL 	5 1	; dbg
	79	[631]	GETTABLE 	5 5 -18	; "is_on"
	80	[631]	TEST     	5 0 0
	81	[631]	JMP      	97	; to 179
	82	[634]	GETUPVAL 	5 0	; logger
	83	[634]	GETTABLE 	5 5 -8	; "dbg"
	84	[634]	LOADK    	6 -19	; "setDirty via a func from widget"
	85	[634]	TEST     	1 0 0
	86	[634]	JMP      	11	; to 98
	87	[634]	GETTABLE 	7 1 -20	; "name"
	88	[634]	TEST     	7 0 1
	89	[634]	JMP      	9	; to 99
	90	[634]	GETTABLE 	7 1 -21	; "id"
	91	[634]	TEST     	7 0 1
	92	[634]	JMP      	6	; to 99
	93	[634]	GETGLOBAL	7 -22	; tostring
	94	[634]	MOVE     	8 1
	95	[634]	CALL     	7 2 2
	96	[634]	TEST     	7 0 1
	97	[634]	JMP      	1	; to 99
	98	[634]	LOADK    	7 -23	; "nil"
	99	[634]	CALL     	5 3 1
	100	[635]	JMP      	78	; to 179
	101	[638]	SELF     	5 0 -24	; "_refresh"
	102	[638]	MOVE     	7 2
	103	[638]	MOVE     	8 3
	104	[638]	MOVE     	9 4
	105	[638]	CALL     	5 5 1
	106	[639]	GETUPVAL 	5 1	; dbg
	107	[639]	GETTABLE 	5 5 -18	; "is_on"
	108	[639]	TEST     	5 0 0
	109	[639]	JMP      	69	; to 179
	110	[640]	TEST     	3 0 0
	111	[640]	JMP      	36	; to 148
	112	[641]	GETUPVAL 	5 0	; logger
	113	[641]	GETTABLE 	5 5 -8	; "dbg"
	114	[641]	LOADK    	6 -25	; "setDirty"
	115	[641]	TEST     	2 0 0
	116	[641]	JMP      	2	; to 119
	117	[641]	TESTSET  	7 2 1
	118	[641]	JMP      	1	; to 120
	119	[641]	LOADK    	7 -23	; "nil"
	120	[641]	LOADK    	8 -26	; "from widget"
	121	[641]	TEST     	1 0 0
	122	[641]	JMP      	11	; to 134
	123	[641]	GETTABLE 	9 1 -20	; "name"
	124	[641]	TEST     	9 0 1
	125	[641]	JMP      	9	; to 135
	126	[641]	GETTABLE 	9 1 -21	; "id"
	127	[641]	TEST     	9 0 1
	128	[641]	JMP      	6	; to 135
	129	[641]	GETGLOBAL	9 -22	; tostring
	130	[641]	MOVE     	10 1
	131	[641]	CALL     	9 2 2
	132	[641]	TEST     	9 0 1
	133	[641]	JMP      	1	; to 135
	134	[641]	LOADK    	9 -23	; "nil"
	135	[641]	LOADK    	10 -27	; "w/ region"
	136	[641]	GETTABLE 	11 3 -28	; "x"
	137	[641]	GETTABLE 	12 3 -29	; "y"
	138	[641]	GETTABLE 	13 3 -30	; "w"
	139	[641]	GETTABLE 	14 3 -31	; "h"
	140	[641]	TEST     	4 0 0
	141	[641]	JMP      	3	; to 145
	142	[641]	LOADK    	15 -32	; "AND w/ HW dithering"
	143	[641]	TEST     	15 0 1
	144	[641]	JMP      	1	; to 146
	145	[641]	LOADK    	15 -33	; ""
	146	[641]	CALL     	5 11 1
	147	[641]	JMP      	31	; to 179
	148	[643]	GETUPVAL 	5 0	; logger
	149	[643]	GETTABLE 	5 5 -8	; "dbg"
	150	[643]	LOADK    	6 -25	; "setDirty"
	151	[643]	TEST     	2 0 0
	152	[643]	JMP      	2	; to 155
	153	[643]	TESTSET  	7 2 1
	154	[643]	JMP      	1	; to 156
	155	[643]	LOADK    	7 -23	; "nil"
	156	[643]	LOADK    	8 -26	; "from widget"
	157	[643]	TEST     	1 0 0
	158	[643]	JMP      	11	; to 170
	159	[643]	GETTABLE 	9 1 -20	; "name"
	160	[643]	TEST     	9 0 1
	161	[643]	JMP      	9	; to 171
	162	[643]	GETTABLE 	9 1 -21	; "id"
	163	[643]	TEST     	9 0 1
	164	[643]	JMP      	6	; to 171
	165	[643]	GETGLOBAL	9 -22	; tostring
	166	[643]	MOVE     	10 1
	167	[643]	CALL     	9 2 2
	168	[643]	TEST     	9 0 1
	169	[643]	JMP      	1	; to 171
	170	[643]	LOADK    	9 -23	; "nil"
	171	[643]	LOADK    	10 -34	; "w/ NO region"
	172	[643]	TEST     	4 0 0
	173	[643]	JMP      	3	; to 177
	174	[643]	LOADK    	11 -32	; "AND w/ HW dithering"
	175	[643]	TEST     	11 0 1
	176	[643]	JMP      	1	; to 178
	177	[643]	LOADK    	11 -33	; ""
	178	[643]	CALL     	5 7 1
	179	[647]	RETURN   	0 1

function <./frontend/ui/uimanager.lua:650,661> (28 instructions, 112 bytes at 0x7ffe48608ac0)
5 params, 11 slots, 1 upvalue, 10 locals, 8 constants, 0 functions
	1	[651]	TEST     	1 0 0
	2	[651]	JMP      	2	; to 5
	3	[651]	EQ       	0 1 -1	; - "all"
	4	[651]	JMP      	1	; to 6
	5	[651]	RETURN   	0 1
	6	[654]	LOADBOOL 	5 0 0
	7	[655]	LOADK    	6 -2	; 1
	8	[655]	GETTABLE 	7 0 -3	; "_window_stack"
	9	[655]	LEN      	7 7
	10	[655]	LOADK    	8 -2	; 1
	11	[655]	FORPREP  	6 6	; to 18
	12	[656]	GETTABLE 	10 0 -3	; "_window_stack"
	13	[656]	GETTABLE 	10 10 9
	14	[656]	GETTABLE 	10 10 -4	; "widget"
	15	[656]	EQ       	0 10 1
	16	[656]	JMP      	1	; to 18
	17	[656]	LOADBOOL 	5 1 0
	18	[655]	FORLOOP  	6 -7	; to 12
	19	[658]	TEST     	5 0 1
	20	[658]	JMP      	7	; to 28
	21	[659]	GETUPVAL 	6 0	; dbg
	22	[659]	SELF     	6 6 -5	; "v"
	23	[659]	LOADK    	8 -6	; "INFO: invalid widget for setDirty()"
	24	[659]	GETGLOBAL	9 -7	; debug
	25	[659]	GETTABLE 	9 9 -8	; "traceback"
	26	[659]	CALL     	9 1 0
	27	[659]	CALL     	6 0 1
	28	[661]	RETURN   	0 1

function <./frontend/ui/uimanager.lua:668,673> (11 instructions, 44 bytes at 0x7ffe48608dc0)
1 param, 3 slots, 1 upvalue, 1 local, 5 constants, 0 functions
	1	[669]	GETUPVAL 	1 0	; logger
	2	[669]	GETTABLE 	1 1 -1	; "dbg"
	3	[669]	LOADK    	2 -2	; "clearRenderStack: Clearing the full render stack!"
	4	[669]	CALL     	1 2 1
	5	[670]	NEWTABLE 	1 0 0
	6	[670]	SETTABLE 	0 -3 1	; "_dirty" -
	7	[671]	NEWTABLE 	1 0 0
	8	[671]	SETTABLE 	0 -4 1	; "_refresh_func_stack" -
	9	[672]	NEWTABLE 	1 0 0
	10	[672]	SETTABLE 	0 -5 1	; "_refresh_stack" -
	11	[673]	RETURN   	0 1

function <./frontend/ui/uimanager.lua:675,678> (7 instructions, 28 bytes at 0x7ffe48607af0)
2 params, 5 slots, 0 upvalues, 2 locals, 3 constants, 0 functions
	1	[676]	GETGLOBAL	2 -1	; table
	2	[676]	GETTABLE 	2 2 -2	; "insert"
	3	[676]	GETTABLE 	3 0 -3	; "_zeromqs"
	4	[676]	MOVE     	4 1
	5	[676]	CALL     	2 3 1
	6	[677]	RETURN   	1 2
	7	[678]	RETURN   	0 1

function <./frontend/ui/uimanager.lua:680,686> (16 instructions, 64 bytes at 0x7ffe48609160)
2 params, 9 slots, 0 upvalues, 6 locals, 5 constants, 0 functions
	1	[681]	GETTABLE 	2 0 -1	; "_zeromqs"
	2	[681]	LEN      	2 2
	3	[681]	LOADK    	3 -2	; 1
	4	[681]	LOADK    	4 -3	; -1
	5	[681]	FORPREP  	2 9	; to 15
	6	[682]	GETTABLE 	6 0 -1	; "_zeromqs"
	7	[682]	GETTABLE 	6 6 5
	8	[682]	EQ       	0 6 1
	9	[682]	JMP      	5	; to 15
	10	[683]	GETGLOBAL	6 -4	; table
	11	[683]	GETTABLE 	6 6 -5	; "remove"
	12	[683]	GETTABLE 	7 0 -1	; "_zeromqs"
	13	[683]	MOVE     	8 5
	14	[683]	CALL     	6 3 1
	15	[681]	FORLOOP  	2 -10	; to 6
	16	[686]	RETURN   	0 1

function <./frontend/ui/uimanager.lua:691,695> (12 instructions, 48 bytes at 0x7ffe48608310)
2 params, 6 slots, 1 upvalue, 2 locals, 6 constants, 0 functions
	1	[692]	GETUPVAL 	2 0	; logger
	2	[692]	GETTABLE 	2 2 -1	; "dbg"
	3	[692]	LOADK    	3 -2	; "set screen full refresh rate"
	4	[692]	MOVE     	4 1
	5	[692]	CALL     	2 3 1
	6	[693]	SETTABLE 	0 -3 1	; "FULL_REFRESH_COUNT" -
	7	[694]	GETGLOBAL	2 -4	; G_reader_settings
	8	[694]	SELF     	2 2 -5	; "saveSetting"
	9	[694]	LOADK    	4 -6	; "full_refresh_count"
	10	[694]	MOVE     	5 1
	11	[694]	CALL     	2 4 1
	12	[695]	RETURN   	0 1

function <./frontend/ui/uimanager.lua:698,700> (3 instructions, 12 bytes at 0x7ffe48607b90)
2 params, 3 slots, 0 upvalues, 2 locals, 1 constant, 0 functions
	1	[699]	GETTABLE 	2 0 -1	; "FULL_REFRESH_COUNT"
	2	[699]	RETURN   	2 2
	3	[700]	RETURN   	0 1

function <./frontend/ui/uimanager.lua:703,705> (14 instructions, 56 bytes at 0x7ffe48608fe0)
1 param, 3 slots, 0 upvalues, 1 local, 3 constants, 0 functions
	1	[704]	GETTABLE 	1 0 -1	; "_window_stack"
	2	[704]	GETTABLE 	2 0 -1	; "_window_stack"
	3	[704]	LEN      	2 2
	4	[704]	GETTABLE 	1 1 2
	5	[704]	TEST     	1 0 1
	6	[704]	JMP      	1	; to 8
	7	[704]	NEWTABLE 	1 0 0
	8	[704]	GETTABLE 	1 1 -2	; "widget"
	9	[704]	TEST     	1 0 1
	10	[704]	JMP      	1	; to 12
	11	[704]	NEWTABLE 	1 0 0
	12	[704]	GETTABLE 	1 1 -3	; "name"
	13	[704]	RETURN   	1 2
	14	[705]	RETURN   	0 1

function <./frontend/ui/uimanager.lua:708,728> (56 instructions, 224 bytes at 0x7ffe486045a0)
1 param, 8 slots, 1 upvalue, 13 locals, 17 constants, 0 functions
	1	[709]	GETTABLE 	1 0 -1	; "_running"
	2	[709]	TEST     	1 0 1
	3	[709]	JMP      	1	; to 5
	4	[709]	RETURN   	0 1
	5	[710]	GETUPVAL 	1 0	; logger
	6	[710]	GETTABLE 	1 1 -2	; "info"
	7	[710]	LOADK    	2 -3	; "quitting uimanager"
	8	[710]	CALL     	1 2 1
	9	[711]	SETTABLE 	0 -4 -5	; "_task_queue_dirty" false
	10	[712]	SETTABLE 	0 -1 -5	; "_running" false
	11	[713]	SETTABLE 	0 -6 -7	; "_run_forever" nil
	12	[714]	GETTABLE 	1 0 -8	; "_window_stack"
	13	[714]	LEN      	1 1
	14	[714]	LOADK    	2 -9	; 1
	15	[714]	LOADK    	3 -10	; -1
	16	[714]	FORPREP  	1 5	; to 22
	17	[715]	GETGLOBAL	5 -11	; table
	18	[715]	GETTABLE 	5 5 -12	; "remove"
	19	[715]	GETTABLE 	6 0 -8	; "_window_stack"
	20	[715]	MOVE     	7 4
	21	[715]	CALL     	5 3 1
	22	[714]	FORLOOP  	1 -6	; to 17
	23	[717]	GETTABLE 	1 0 -13	; "_task_queue"
	24	[717]	LEN      	1 1
	25	[717]	LOADK    	2 -9	; 1
	26	[717]	LOADK    	3 -10	; -1
	27	[717]	FORPREP  	1 5	; to 33
	28	[718]	GETGLOBAL	5 -11	; table
	29	[718]	GETTABLE 	5 5 -12	; "remove"
	30	[718]	GETTABLE 	6 0 -13	; "_task_queue"
	31	[718]	MOVE     	7 4
	32	[718]	CALL     	5 3 1
	33	[717]	FORLOOP  	1 -6	; to 28
	34	[720]	GETTABLE 	1 0 -14	; "_zeromqs"
	35	[720]	LEN      	1 1
	36	[720]	LOADK    	2 -9	; 1
	37	[720]	LOADK    	3 -10	; -1
	38	[720]	FORPREP  	1 9	; to 48
	39	[721]	GETTABLE 	5 0 -14	; "_zeromqs"
	40	[721]	GETTABLE 	5 5 4
	41	[721]	SELF     	5 5 -15	; "stop"
	42	[721]	CALL     	5 2 1
	43	[722]	GETGLOBAL	5 -11	; table
	44	[722]	GETTABLE 	5 5 -12	; "remove"
	45	[722]	GETTABLE 	6 0 -14	; "_zeromqs"
	46	[722]	MOVE     	7 4
	47	[722]	CALL     	5 3 1
	48	[720]	FORLOOP  	1 -10	; to 39
	49	[724]	GETTABLE 	1 0 -16	; "looper"
	50	[724]	TEST     	1 0 0
	51	[724]	JMP      	4	; to 56
	52	[725]	GETTABLE 	1 0 -16	; "looper"
	53	[725]	SELF     	1 1 -17	; "close"
	54	[725]	CALL     	1 2 1
	55	[726]	SETTABLE 	0 -16 -7	; "looper" nil
	56	[728]	RETURN   	0 1

function <./frontend/ui/uimanager.lua:731,768> (78 instructions, 312 bytes at 0x7ffe48604930)
2 params, 17 slots, 0 upvalues, 19 locals, 11 constants, 0 functions
	1	[732]	GETTABLE 	2 0 -1	; "_window_stack"
	2	[732]	LEN      	2 2
	3	[732]	EQ       	0 2 -2	; - 0
	4	[732]	JMP      	1	; to 6
	5	[732]	RETURN   	0 1
	6	[734]	GETTABLE 	2 0 -1	; "_window_stack"
	7	[734]	GETTABLE 	3 0 -1	; "_window_stack"
	8	[734]	LEN      	3 3
	9	[734]	GETTABLE 	2 2 3
	10	[736]	GETTABLE 	3 2 -3	; "widget"
	11	[736]	SELF     	3 3 -4	; "handleEvent"
	12	[736]	MOVE     	5 1
	13	[736]	CALL     	3 3 2
	14	[736]	TEST     	3 0 0
	15	[736]	JMP      	1	; to 17
	16	[737]	RETURN   	0 1
	17	[739]	GETTABLE 	3 2 -3	; "widget"
	18	[739]	GETTABLE 	3 3 -5	; "active_widgets"
	19	[739]	TEST     	3 0 0
	20	[739]	JMP      	13	; to 34
	21	[740]	GETGLOBAL	3 -6	; ipairs
	22	[740]	GETTABLE 	4 2 -3	; "widget"
	23	[740]	GETTABLE 	4 4 -5	; "active_widgets"
	24	[740]	CALL     	3 2 4
	25	[740]	JMP      	6	; to 32
	26	[741]	SELF     	8 7 -4	; "handleEvent"
	27	[741]	MOVE     	10 1
	28	[741]	CALL     	8 3 2
	29	[741]	TEST     	8 0 0
	30	[741]	JMP      	1	; to 32
	31	[741]	RETURN   	0 1
	32	[740]	TFORLOOP 	3 2
	33	[741]	JMP      	-8	; to 26
	34	[747]	NEWTABLE 	3 1 0
	35	[747]	MOVE     	4 2
	36	[747]	SETLIST  	3 1 1	; 1
	37	[748]	GETTABLE 	4 0 -1	; "_window_stack"
	38	[748]	LEN      	4 4
	39	[748]	LOADK    	5 -7	; 1
	40	[748]	LOADK    	6 -8	; -1
	41	[748]	FORPREP  	4 35	; to 77
	42	[749]	GETTABLE 	8 0 -1	; "_window_stack"
	43	[749]	GETTABLE 	8 8 7
	44	[750]	GETTABLE 	9 3 8
	45	[750]	EQ       	0 9 -9	; - nil
	46	[750]	JMP      	30	; to 77
	47	[753]	GETTABLE 	9 8 -3	; "widget"
	48	[753]	GETTABLE 	9 9 -5	; "active_widgets"
	49	[753]	TEST     	9 0 0
	50	[753]	JMP      	14	; to 65
	51	[754]	SETTABLE 	3 8 -10	; - true
	52	[755]	GETGLOBAL	9 -6	; ipairs
	53	[755]	GETTABLE 	10 8 -3	; "widget"
	54	[755]	GETTABLE 	10 10 -5	; "active_widgets"
	55	[755]	CALL     	9 2 4
	56	[755]	JMP      	6	; to 63
	57	[756]	SELF     	14 13 -4	; "handleEvent"
	58	[756]	MOVE     	16 1
	59	[756]	CALL     	14 3 2
	60	[756]	TEST     	14 0 0
	61	[756]	JMP      	1	; to 63
	62	[756]	RETURN   	0 1
	63	[755]	TFORLOOP 	9 2
	64	[756]	JMP      	-8	; to 57
	65	[759]	GETTABLE 	9 8 -3	; "widget"
	66	[759]	GETTABLE 	9 9 -11	; "is_always_active"
	67	[759]	TEST     	9 0 0
	68	[759]	JMP      	8	; to 77
	69	[763]	SETTABLE 	3 8 -10	; - true
	70	[764]	GETTABLE 	9 8 -3	; "widget"
	71	[764]	SELF     	9 9 -4	; "handleEvent"
	72	[764]	MOVE     	11 1
	73	[764]	CALL     	9 3 2
	74	[764]	TEST     	9 0 0
	75	[764]	JMP      	1	; to 77
	76	[764]	RETURN   	0 1
	77	[748]	FORLOOP  	4 -36	; to 42
	78	[768]	RETURN   	0 1

function <./frontend/ui/uimanager.lua:771,786> (26 instructions, 104 bytes at 0x7ffe48604860)
2 params, 7 slots, 0 upvalues, 5 locals, 5 constants, 0 functions
	1	[774]	LOADK    	2 -1	; 1
	2	[775]	GETTABLE 	3 0 -2	; "_window_stack"
	3	[775]	LEN      	3 3
	4	[775]	LE       	0 2 3
	5	[775]	JMP      	20	; to 26
	6	[776]	GETTABLE 	3 0 -2	; "_window_stack"
	7	[776]	GETTABLE 	3 3 2
	8	[776]	GETTABLE 	3 3 -3	; "widget"
	9	[777]	GETTABLE 	4 0 -2	; "_window_stack"
	10	[777]	GETTABLE 	4 4 2
	11	[777]	GETTABLE 	4 4 -3	; "widget"
	12	[777]	SELF     	4 4 -4	; "handleEvent"
	13	[777]	MOVE     	6 1
	14	[777]	CALL     	4 3 1
	15	[778]	GETTABLE 	4 0 -2	; "_window_stack"
	16	[778]	GETTABLE 	4 4 2
	17	[779]	EQ       	0 4 -5	; - nil
	18	[779]	JMP      	2	; to 21
	19	[781]	JMP      	6	; to 26
	20	[781]	JMP      	-19	; to 2
	21	[782]	GETTABLE 	5 4 -3	; "widget"
	22	[782]	EQ       	0 5 3
	23	[782]	JMP      	-22	; to 2
	24	[783]	ADD      	2 2 -1	; - 1
	25	[784]	JMP      	-24	; to 2
	26	[786]	RETURN   	0 1

function <./frontend/ui/uimanager.lua:788,822> (53 instructions, 212 bytes at 0x7ffe48609d30)
1 param, 10 slots, 2 upvalues, 7 locals, 14 constants, 0 functions
	1	[789]	NEWTABLE 	1 0 0
	2	[789]	GETUPVAL 	2 0	; util
	3	[789]	GETTABLE 	2 2 -1	; "gettime"
	4	[789]	CALL     	2 1 0
	5	[789]	SETLIST  	1 0 1	; 1
	6	[790]	GETTABLE 	2 1 -2	; 1
	7	[790]	GETUPVAL 	3 1	; MILLION
	8	[790]	MUL      	2 2 3
	9	[790]	GETTABLE 	3 1 -3	; 2
	10	[790]	ADD      	2 2 3
	11	[791]	LOADNIL  	3 3
	12	[794]	SETTABLE 	0 -4 -5	; "_task_queue_dirty" false
	13	[796]	GETTABLE 	4 0 -6	; "_task_queue"
	14	[796]	LEN      	4 4
	15	[797]	EQ       	0 4 -7	; - 0
	16	[797]	JMP      	1	; to 18
	17	[799]	JMP      	32	; to 50
	18	[801]	GETTABLE 	5 0 -6	; "_task_queue"
	19	[801]	GETTABLE 	5 5 -2	; 1
	20	[802]	LOADK    	6 -7	; 0
	21	[803]	GETTABLE 	7 5 -8	; "time"
	22	[803]	EQ       	1 7 -9	; - nil
	23	[803]	JMP      	7	; to 31
	24	[804]	GETTABLE 	7 5 -8	; "time"
	25	[804]	GETTABLE 	7 7 -2	; 1
	26	[804]	GETUPVAL 	8 1	; MILLION
	27	[804]	MUL      	7 7 8
	28	[804]	GETTABLE 	8 5 -8	; "time"
	29	[804]	GETTABLE 	8 8 -3	; 2
	30	[804]	ADD      	6 7 8
	31	[806]	LE       	0 6 2
	32	[806]	JMP      	14	; to 47
	33	[808]	GETGLOBAL	7 -10	; table
	34	[808]	GETTABLE 	7 7 -11	; "remove"
	35	[808]	GETTABLE 	8 0 -6	; "_task_queue"
	36	[808]	LOADK    	9 -2	; 1
	37	[808]	CALL     	7 3 1
	38	[812]	GETTABLE 	7 5 -12	; "action"
	39	[812]	GETGLOBAL	8 -13	; unpack
	40	[812]	GETTABLE 	9 5 -14	; "args"
	41	[812]	TEST     	9 0 1
	42	[812]	JMP      	1	; to 44
	43	[812]	NEWTABLE 	9 0 0
	44	[812]	CALL     	8 2 0
	45	[812]	CALL     	7 0 1
	46	[812]	JMP      	-34	; to 13
	47	[816]	GETTABLE 	3 5 -8	; "time"
	48	[817]	JMP      	1	; to 50
	49	[818]	JMP      	-37	; to 13
	50	[821]	MOVE     	4 3
	51	[821]	MOVE     	5 1
	52	[821]	RETURN   	4 3
	53	[822]	RETURN   	0 1

function <./frontend/ui/uimanager.lua:843,850> (17 instructions, 68 bytes at 0x7ffe4860a800)
2 params, 7 slots, 2 upvalues, 2 locals, 3 constants, 0 functions
	1	[844]	GETUPVAL 	2 0	; refresh_modes
	2	[844]	GETTABLE 	2 2 0
	3	[844]	GETUPVAL 	3 0	; refresh_modes
	4	[844]	GETTABLE 	3 3 1
	5	[844]	LT       	0 3 2
	6	[844]	JMP      	9	; to 16
	7	[845]	GETUPVAL 	2 1	; logger
	8	[845]	GETTABLE 	2 2 -1	; "dbg"
	9	[845]	LOADK    	3 -2	; "update_mode: Update refresh mode"
	10	[845]	MOVE     	4 1
	11	[845]	LOADK    	5 -3	; "to"
	12	[845]	MOVE     	6 0
	13	[845]	CALL     	2 5 1
	14	[846]	RETURN   	0 2
	15	[846]	JMP      	1	; to 17
	16	[848]	RETURN   	1 2
	17	[850]	RETURN   	0 1

function <./frontend/ui/uimanager.lua:857,864> (15 instructions, 60 bytes at 0x7ffe4860aeb0)
2 params, 7 slots, 1 upvalue, 2 locals, 3 constants, 0 functions
	1	[858]	TEST     	0 0 0
	2	[858]	JMP      	11	; to 14
	3	[858]	TEST     	1 0 1
	4	[858]	JMP      	9	; to 14
	5	[859]	GETUPVAL 	2 0	; logger
	6	[859]	GETTABLE 	2 2 -1	; "dbg"
	7	[859]	LOADK    	3 -2	; "update_dither: Update dither hint"
	8	[859]	MOVE     	4 1
	9	[859]	LOADK    	5 -3	; "to"
	10	[859]	MOVE     	6 0
	11	[859]	CALL     	2 5 1
	12	[860]	RETURN   	0 2
	13	[860]	JMP      	1	; to 15
	14	[862]	RETURN   	1 2
	15	[864]	RETURN   	0 1

function <./frontend/ui/uimanager.lua:882,963> (158 instructions, 632 bytes at 0x7ffe4860b3c0)
4 params, 14 slots, 5 upvalues, 9 locals, 40 constants, 0 functions
	1	[883]	TEST     	1 0 1
	2	[883]	JMP      	5	; to 8
	3	[886]	TEST     	3 0 0
	4	[886]	JMP      	2	; to 7
	5	[887]	LOADK    	1 -1	; "ui"
	6	[887]	JMP      	1	; to 8
	7	[889]	RETURN   	0 1
	8	[892]	TEST     	2 0 1
	9	[892]	JMP      	3	; to 13
	10	[892]	EQ       	0 1 -2	; - "full"
	11	[892]	JMP      	1	; to 13
	12	[893]	SETTABLE 	0 -3 -4	; "refresh_count" 0
	13	[897]	GETGLOBAL	4 -5	; G_reader_settings
	14	[897]	SELF     	4 4 -6	; "isTrue"
	15	[897]	LOADK    	6 -7	; "avoid_flashing_ui"
	16	[897]	CALL     	4 3 2
	17	[897]	TEST     	4 0 0
	18	[897]	JMP      	28	; to 47
	19	[898]	EQ       	0 1 -8	; - "flashui"
	20	[898]	JMP      	7	; to 28
	21	[899]	LOADK    	1 -1	; "ui"
	22	[900]	GETUPVAL 	4 0	; logger
	23	[900]	GETTABLE 	4 4 -9	; "dbg"
	24	[900]	LOADK    	5 -10	; "_refresh: downgraded flashui refresh to"
	25	[900]	MOVE     	6 1
	26	[900]	CALL     	4 3 1
	27	[900]	JMP      	19	; to 47
	28	[901]	EQ       	0 1 -11	; - "flashpartial"
	29	[901]	JMP      	7	; to 37
	30	[902]	LOADK    	1 -12	; "partial"
	31	[903]	GETUPVAL 	4 0	; logger
	32	[903]	GETTABLE 	4 4 -9	; "dbg"
	33	[903]	LOADK    	5 -13	; "_refresh: downgraded flashpartial refresh to"
	34	[903]	MOVE     	6 1
	35	[903]	CALL     	4 3 1
	36	[903]	JMP      	10	; to 47
	37	[904]	EQ       	0 1 -12	; - "partial"
	38	[904]	JMP      	8	; to 47
	39	[904]	TEST     	2 0 0
	40	[904]	JMP      	6	; to 47
	41	[905]	LOADK    	1 -1	; "ui"
	42	[906]	GETUPVAL 	4 0	; logger
	43	[906]	GETTABLE 	4 4 -9	; "dbg"
	44	[906]	LOADK    	5 -14	; "_refresh: downgraded regional partial refresh to"
	45	[906]	MOVE     	6 1
	46	[906]	CALL     	4 3 1
	47	[919]	EQ       	0 1 -12	; - "partial"
	48	[919]	JMP      	24	; to 73
	49	[919]	GETTABLE 	4 0 -15	; "refresh_counted"
	50	[919]	TEST     	4 0 1
	51	[919]	JMP      	21	; to 73
	52	[920]	GETTABLE 	4 0 -3	; "refresh_count"
	53	[920]	ADD      	4 4 -16	; - 1
	54	[920]	GETTABLE 	5 0 -17	; "FULL_REFRESH_COUNT"
	55	[920]	MOD      	4 4 5
	56	[920]	SETTABLE 	0 -3 4	; "refresh_count" -
	57	[921]	GETTABLE 	4 0 -3	; "refresh_count"
	58	[921]	GETTABLE 	5 0 -17	; "FULL_REFRESH_COUNT"
	59	[921]	SUB      	5 5 -16	; - 1
	60	[921]	EQ       	0 4 5
	61	[921]	JMP      	10	; to 72
	62	[923]	TEST     	2 0 0
	63	[923]	JMP      	2	; to 66
	64	[924]	LOADK    	1 -8	; "flashui"
	65	[924]	JMP      	1	; to 67
	66	[926]	LOADK    	1 -2	; "full"
	67	[928]	GETUPVAL 	4 0	; logger
	68	[928]	GETTABLE 	4 4 -9	; "dbg"
	69	[928]	LOADK    	5 -18	; "_refresh: promote refresh to"
	70	[928]	MOVE     	6 1
	71	[928]	CALL     	4 3 1
	72	[930]	SETTABLE 	0 -15 -19	; "refresh_counted" true
	73	[934]	TEST     	2 0 1
	74	[934]	JMP      	13	; to 88
	75	[934]	GETUPVAL 	4 1	; Geom
	76	[934]	SELF     	4 4 -20	; "new"
	77	[934]	NEWTABLE 	6 0 2
	78	[934]	GETUPVAL 	7 2	; Screen
	79	[934]	SELF     	7 7 -22	; "getWidth"
	80	[934]	CALL     	7 2 2
	81	[934]	SETTABLE 	6 -21 7	; "w" -
	82	[934]	GETUPVAL 	7 2	; Screen
	83	[934]	SELF     	7 7 -24	; "getHeight"
	84	[934]	CALL     	7 2 2
	85	[934]	SETTABLE 	6 -23 7	; "h" -
	86	[934]	CALL     	4 3 2
	87	[934]	MOVE     	2 4
	88	[937]	TEST     	3 0 1
	89	[937]	JMP      	1	; to 91
	90	[937]	LOADBOOL 	3 0 0
	91	[944]	LOADK    	4 -16	; 1
	92	[944]	GETTABLE 	5 0 -25	; "_refresh_stack"
	93	[944]	LEN      	5 5
	94	[944]	LOADK    	6 -16	; 1
	95	[944]	FORPREP  	4 37	; to 133
	96	[946]	SELF     	8 2 -26	; "intersectWith"
	97	[946]	GETTABLE 	10 0 -25	; "_refresh_stack"
	98	[946]	GETTABLE 	10 10 7
	99	[946]	GETTABLE 	10 10 -27	; "region"
	100	[946]	CALL     	8 3 2
	101	[946]	TEST     	8 0 0
	102	[946]	JMP      	30	; to 133
	103	[948]	SELF     	8 2 -28	; "combine"
	104	[948]	GETTABLE 	10 0 -25	; "_refresh_stack"
	105	[948]	GETTABLE 	10 10 7
	106	[948]	GETTABLE 	10 10 -27	; "region"
	107	[948]	CALL     	8 3 2
	108	[950]	GETUPVAL 	9 3	; update_mode
	109	[950]	MOVE     	10 1
	110	[950]	GETTABLE 	11 0 -25	; "_refresh_stack"
	111	[950]	GETTABLE 	11 11 7
	112	[950]	GETTABLE 	11 11 -29	; "mode"
	113	[950]	CALL     	9 3 2
	114	[950]	MOVE     	1 9
	115	[952]	GETUPVAL 	9 4	; update_dither
	116	[952]	MOVE     	10 3
	117	[952]	GETTABLE 	11 0 -25	; "_refresh_stack"
	118	[952]	GETTABLE 	11 11 7
	119	[952]	GETTABLE 	11 11 -30	; "dither"
	120	[952]	CALL     	9 3 2
	121	[952]	MOVE     	3 9
	122	[954]	GETGLOBAL	9 -31	; table
	123	[954]	GETTABLE 	9 9 -32	; "remove"
	124	[954]	GETTABLE 	10 0 -25	; "_refresh_stack"
	125	[954]	MOVE     	11 7
	126	[954]	CALL     	9 3 1
	127	[956]	SELF     	9 0 -33	; "_refresh"
	128	[956]	MOVE     	11 1
	129	[956]	MOVE     	12 8
	130	[956]	MOVE     	13 3
	131	[956]	TAILCALL 	9 5 0
	132	[956]	RETURN   	9 0
	133	[944]	FORLOOP  	4 -38	; to 96
	134	[961]	GETUPVAL 	4 0	; logger
	135	[961]	GETTABLE 	4 4 -9	; "dbg"
	136	[961]	LOADK    	5 -34	; "_refresh: Enqueued"
	137	[961]	MOVE     	6 1
	138	[961]	LOADK    	7 -35	; "update for region"
	139	[961]	GETTABLE 	8 2 -36	; "x"
	140	[961]	GETTABLE 	9 2 -37	; "y"
	141	[961]	GETTABLE 	10 2 -21	; "w"
	142	[961]	GETTABLE 	11 2 -23	; "h"
	143	[961]	TEST     	3 0 0
	144	[961]	JMP      	3	; to 148
	145	[961]	LOADK    	12 -38	; "w/ HW dithering"
	146	[961]	TEST     	12 0 1
	147	[961]	JMP      	1	; to 149
	148	[961]	LOADK    	12 -39	; ""
	149	[961]	CALL     	4 9 1
	150	[962]	GETGLOBAL	4 -31	; table
	151	[962]	GETTABLE 	4 4 -40	; "insert"
	152	[962]	GETTABLE 	5 0 -25	; "_refresh_stack"
	153	[962]	NEWTABLE 	6 0 3
	154	[962]	SETTABLE 	6 -29 1	; "mode" -
	155	[962]	SETTABLE 	6 -27 2	; "region" -
	156	[962]	SETTABLE 	6 -30 3	; "dither" -
	157	[962]	CALL     	4 3 1
	158	[963]	RETURN   	0 1

function <./frontend/ui/uimanager.lua:966,1044> (158 instructions, 632 bytes at 0x7ffe4860b9f0)
1 param, 17 slots, 5 upvalues, 26 locals, 38 constants, 0 functions
	1	[969]	LOADBOOL 	1 0 0
	2	[971]	LOADBOOL 	2 0 0
	3	[975]	LOADK    	3 -1	; 1
	4	[976]	GETTABLE 	4 0 -2	; "_window_stack"
	5	[976]	LEN      	4 4
	6	[976]	LOADK    	5 -1	; 1
	7	[976]	LOADK    	6 -3	; -1
	8	[976]	FORPREP  	4 16	; to 25
	9	[977]	GETTABLE 	8 0 -2	; "_window_stack"
	10	[977]	GETTABLE 	8 8 7
	11	[977]	GETTABLE 	8 8 -4	; "widget"
	12	[977]	GETTABLE 	8 8 -5	; "covers_fullscreen"
	13	[977]	TEST     	8 0 0
	14	[977]	JMP      	10	; to 25
	15	[978]	MOVE     	3 7
	16	[979]	LT       	0 -1 7	; 1 -
	17	[979]	JMP      	8	; to 26
	18	[980]	GETUPVAL 	8 0	; logger
	19	[980]	GETTABLE 	8 8 -6	; "dbg"
	20	[980]	LOADK    	9 -7	; "not painting"
	21	[980]	SUB      	10 7 -1	; - 1
	22	[980]	LOADK    	11 -8	; "covered widget(s)"
	23	[980]	CALL     	8 4 1
	24	[982]	JMP      	1	; to 26
	25	[976]	FORLOOP  	4 -17	; to 9
	26	[986]	MOVE     	4 3
	27	[986]	GETTABLE 	5 0 -2	; "_window_stack"
	28	[986]	LEN      	5 5
	29	[986]	LOADK    	6 -1	; 1
	30	[986]	FORPREP  	4 47	; to 78
	31	[987]	GETTABLE 	8 0 -2	; "_window_stack"
	32	[987]	GETTABLE 	8 8 7
	33	[989]	TEST     	1 0 1
	34	[989]	JMP      	5	; to 40
	35	[989]	GETTABLE 	9 0 -9	; "_dirty"
	36	[989]	GETTABLE 	10 8 -4	; "widget"
	37	[989]	GETTABLE 	9 9 10
	38	[989]	TEST     	9 0 0
	39	[989]	JMP      	38	; to 78
	40	[992]	GETUPVAL 	9 0	; logger
	41	[992]	GETTABLE 	9 9 -6	; "dbg"
	42	[992]	LOADK    	10 -10	; "painting widget:"
	43	[992]	GETTABLE 	11 8 -4	; "widget"
	44	[992]	GETTABLE 	11 11 -11	; "name"
	45	[992]	TEST     	11 0 1
	46	[992]	JMP      	7	; to 54
	47	[992]	GETTABLE 	11 8 -4	; "widget"
	48	[992]	GETTABLE 	11 11 -12	; "id"
	49	[992]	TEST     	11 0 1
	50	[992]	JMP      	3	; to 54
	51	[992]	GETGLOBAL	11 -13	; tostring
	52	[992]	MOVE     	12 8
	53	[992]	CALL     	11 2 2
	54	[992]	CALL     	9 3 1
	55	[993]	GETTABLE 	9 8 -4	; "widget"
	56	[993]	SELF     	9 9 -14	; "paintTo"
	57	[993]	GETUPVAL 	11 1	; Screen
	58	[993]	GETTABLE 	11 11 -15	; "bb"
	59	[993]	GETTABLE 	12 8 -16	; "x"
	60	[993]	GETTABLE 	13 8 -17	; "y"
	61	[993]	GETTABLE 	14 0 -9	; "_dirty"
	62	[993]	GETTABLE 	15 8 -4	; "widget"
	63	[993]	GETTABLE 	14 14 15
	64	[993]	CALL     	9 6 1
	65	[996]	GETTABLE 	9 0 -9	; "_dirty"
	66	[996]	GETTABLE 	10 8 -4	; "widget"
	67	[996]	SETTABLE 	9 10 -18	; - nil
	68	[999]	LOADBOOL 	1 1 0
	69	[1002]	GETTABLE 	9 8 -4	; "widget"
	70	[1002]	GETTABLE 	9 9 -19	; "dithered"
	71	[1002]	TEST     	9 0 0
	72	[1002]	JMP      	5	; to 78
	73	[1003]	GETUPVAL 	9 0	; logger
	74	[1003]	GETTABLE 	9 9 -6	; "dbg"
	75	[1003]	LOADK    	10 -20	; "_repaint: it was dithered, infecting the refresh queue"
	76	[1003]	CALL     	9 2 1
	77	[1004]	LOADBOOL 	2 1 0
	78	[986]	FORLOOP  	4 -48	; to 31
	79	[1010]	GETGLOBAL	4 -21	; ipairs
	80	[1010]	GETTABLE 	5 0 -22	; "_refresh_func_stack"
	81	[1010]	CALL     	4 2 4
	82	[1010]	JMP      	14	; to 97
	83	[1011]	MOVE     	9 8
	84	[1011]	CALL     	9 1 4
	85	[1013]	GETUPVAL 	12 2	; update_dither
	86	[1013]	MOVE     	13 11
	87	[1013]	MOVE     	14 2
	88	[1013]	CALL     	12 3 2
	89	[1013]	MOVE     	11 12
	90	[1014]	TEST     	9 0 0
	91	[1014]	JMP      	5	; to 97
	92	[1014]	SELF     	12 0 -23	; "_refresh"
	93	[1014]	MOVE     	14 9
	94	[1014]	MOVE     	15 10
	95	[1014]	MOVE     	16 11
	96	[1014]	CALL     	12 5 1
	97	[1010]	TFORLOOP 	4 2
	98	[1014]	JMP      	-16	; to 83
	99	[1016]	NEWTABLE 	4 0 0
	100	[1016]	SETTABLE 	0 -22 4	; "_refresh_func_stack" -
	101	[1020]	TEST     	1 0 0
	102	[1020]	JMP      	11	; to 114
	103	[1020]	GETTABLE 	4 0 -24	; "_refresh_stack"
	104	[1020]	LEN      	4 4
	105	[1020]	EQ       	0 4 -25	; - 0
	106	[1020]	JMP      	7	; to 114
	107	[1021]	GETUPVAL 	4 0	; logger
	108	[1021]	GETTABLE 	4 4 -6	; "dbg"
	109	[1021]	LOADK    	5 -26	; "no refresh got enqueued. Will do a partial full screen refresh, which might be inefficient"
	110	[1021]	CALL     	4 2 1
	111	[1022]	SELF     	4 0 -23	; "_refresh"
	112	[1022]	LOADK    	6 -27	; "partial"
	113	[1022]	CALL     	4 3 1
	114	[1026]	GETGLOBAL	4 -21	; ipairs
	115	[1026]	GETTABLE 	5 0 -24	; "_refresh_stack"
	116	[1026]	CALL     	4 2 4
	117	[1026]	JMP      	35	; to 153
	118	[1028]	GETUPVAL 	9 2	; update_dither
	119	[1028]	GETTABLE 	10 8 -28	; "dither"
	120	[1028]	MOVE     	11 2
	121	[1028]	CALL     	9 3 2
	122	[1028]	SETTABLE 	8 -28 9	; "dither" -
	123	[1030]	GETUPVAL 	9 1	; Screen
	124	[1030]	GETTABLE 	9 9 -29	; "hw_dithering"
	125	[1030]	TEST     	9 0 1
	126	[1030]	JMP      	1	; to 128
	127	[1031]	SETTABLE 	8 -28 -18	; "dither" nil
	128	[1033]	GETUPVAL 	9 3	; dbg
	129	[1033]	SELF     	9 9 -30	; "v"
	130	[1033]	LOADK    	11 -31	; "triggering refresh"
	131	[1033]	MOVE     	12 8
	132	[1033]	CALL     	9 4 1
	133	[1037]	GETUPVAL 	9 1	; Screen
	134	[1037]	GETUPVAL 	10 4	; refresh_methods
	135	[1037]	GETTABLE 	11 8 -32	; "mode"
	136	[1037]	GETTABLE 	10 10 11
	137	[1037]	GETTABLE 	9 9 10
	138	[1037]	GETUPVAL 	10 1	; Screen
	139	[1038]	GETTABLE 	11 8 -33	; "region"
	140	[1038]	GETTABLE 	11 11 -16	; "x"
	141	[1038]	SUB      	11 11 -1	; - 1
	142	[1038]	GETTABLE 	12 8 -33	; "region"
	143	[1038]	GETTABLE 	12 12 -17	; "y"
	144	[1038]	SUB      	12 12 -1	; - 1
	145	[1039]	GETTABLE 	13 8 -33	; "region"
	146	[1039]	GETTABLE 	13 13 -34	; "w"
	147	[1039]	ADD      	13 13 -35	; - 2
	148	[1039]	GETTABLE 	14 8 -33	; "region"
	149	[1039]	GETTABLE 	14 14 -36	; "h"
	150	[1039]	ADD      	14 14 -35	; - 2
	151	[1040]	GETTABLE 	15 8 -28	; "dither"
	152	[1037]	CALL     	9 7 1
	153	[1026]	TFORLOOP 	4 2
	154	[1040]	JMP      	-37	; to 118
	155	[1042]	NEWTABLE 	4 0 0
	156	[1042]	SETTABLE 	0 -24 4	; "_refresh_stack" -
	157	[1043]	SETTABLE 	0 -37 -38	; "refresh_counted" false
	158	[1044]	RETURN   	0 1

function <./frontend/ui/uimanager.lua:1046,1048> (3 instructions, 12 bytes at 0x7ffe4860bf20)
1 param, 3 slots, 0 upvalues, 1 local, 1 constant, 0 functions
	1	[1047]	SELF     	1 0 -1	; "_repaint"
	2	[1047]	CALL     	1 2 1
	3	[1048]	RETURN   	0 1

function <./frontend/ui/uimanager.lua:1053,1058> (28 instructions, 112 bytes at 0x7ffe4860c440)
4 params, 12 slots, 2 upvalues, 4 locals, 10 constants, 0 functions
	1	[1054]	TEST     	1 0 1
	2	[1054]	JMP      	1	; to 4
	3	[1054]	RETURN   	0 1
	4	[1056]	GETUPVAL 	4 0	; logger
	5	[1056]	GETTABLE 	4 4 -1	; "dbg"
	6	[1056]	LOADK    	5 -2	; "Explicit widgetRepaint:"
	7	[1056]	GETTABLE 	6 1 -3	; "name"
	8	[1056]	TEST     	6 0 1
	9	[1056]	JMP      	6	; to 16
	10	[1056]	GETTABLE 	6 1 -4	; "id"
	11	[1056]	TEST     	6 0 1
	12	[1056]	JMP      	3	; to 16
	13	[1056]	GETGLOBAL	6 -5	; tostring
	14	[1056]	MOVE     	7 1
	15	[1056]	CALL     	6 2 2
	16	[1056]	LOADK    	7 -6	; "@ ("
	17	[1056]	MOVE     	8 2
	18	[1056]	LOADK    	9 -7	; ","
	19	[1056]	MOVE     	10 3
	20	[1056]	LOADK    	11 -8	; ")"
	21	[1056]	CALL     	4 8 1
	22	[1057]	SELF     	4 1 -9	; "paintTo"
	23	[1057]	GETUPVAL 	6 1	; Screen
	24	[1057]	GETTABLE 	6 6 -10	; "bb"
	25	[1057]	MOVE     	7 2
	26	[1057]	MOVE     	8 3
	27	[1057]	CALL     	4 5 1
	28	[1058]	RETURN   	0 1

function <./frontend/ui/uimanager.lua:1060,1062> (5 instructions, 20 bytes at 0x7ffe4860c5d0)
2 params, 3 slots, 0 upvalues, 2 locals, 2 constants, 0 functions
	1	[1061]	TESTSET  	2 1 1
	2	[1061]	JMP      	1	; to 4
	3	[1061]	LOADK    	2 -2	; 200000
	4	[1061]	SETTABLE 	0 -1 2	; "INPUT_TIMEOUT" -
	5	[1062]	RETURN   	0 1

function <./frontend/ui/uimanager.lua:1064,1066> (2 instructions, 8 bytes at 0x7ffe4860c8f0)
1 param, 2 slots, 0 upvalues, 1 local, 2 constants, 0 functions
	1	[1065]	SETTABLE 	0 -1 -2	; "INPUT_TIMEOUT" nil
	2	[1066]	RETURN   	0 1

function <./frontend/ui/uimanager.lua:1068,1078> (21 instructions, 84 bytes at 0x7ffe4860ca10)
2 params, 6 slots, 0 upvalues, 3 locals, 7 constants, 0 functions
	1	[1069]	GETTABLE 	2 1 -1	; "handler"
	2	[1069]	EQ       	1 2 -2	; - "onInputError"
	3	[1069]	JMP      	5	; to 9
	4	[1070]	GETTABLE 	2 0 -3	; "event_hook"
	5	[1070]	SELF     	2 2 -4	; "execute"
	6	[1070]	LOADK    	4 -5	; "InputEvent"
	7	[1070]	MOVE     	5 1
	8	[1070]	CALL     	2 4 1
	9	[1072]	GETTABLE 	2 0 -6	; "event_handlers"
	10	[1072]	GETTABLE 	2 2 1
	11	[1073]	TEST     	2 0 0
	12	[1073]	JMP      	4	; to 17
	13	[1074]	MOVE     	3 2
	14	[1074]	MOVE     	4 1
	15	[1074]	CALL     	3 2 1
	16	[1074]	JMP      	4	; to 21
	17	[1076]	GETTABLE 	3 0 -6	; "event_handlers"
	18	[1076]	GETTABLE 	3 3 -7	; "__default__"
	19	[1076]	MOVE     	4 1
	20	[1076]	CALL     	3 2 1
	21	[1078]	RETURN   	0 1

function <./frontend/ui/uimanager.lua:1081,1087> (16 instructions, 64 bytes at 0x7ffe4860d2f0)
1 param, 13 slots, 0 upvalues, 10 locals, 4 constants, 0 functions
	1	[1082]	GETGLOBAL	1 -1	; ipairs
	2	[1082]	GETTABLE 	2 0 -2	; "_zeromqs"
	3	[1082]	CALL     	1 2 4
	4	[1082]	JMP      	9	; to 14
	5	[1083]	GETTABLE 	6 5 -3	; "waitEvent"
	6	[1083]	MOVE     	7 5
	7	[1083]	LOADNIL  	8 8
	8	[1083]	JMP      	3	; to 12
	9	[1084]	SELF     	10 0 -4	; "handleInputEvent"
	10	[1084]	MOVE     	12 9
	11	[1084]	CALL     	10 3 1
	12	[1083]	TFORLOOP 	6 1
	13	[1084]	JMP      	-5	; to 9
	14	[1082]	TFORLOOP 	1 2
	15	[1085]	JMP      	-11	; to 5
	16	[1087]	RETURN   	0 1

function <./frontend/ui/uimanager.lua:1089,1154> (81 instructions, 324 bytes at 0x7ffe486078e0)
1 param, 9 slots, 3 upvalues, 5 locals, 23 constants, 1 function
	1	[1095]	SELF     	3 0 -1	; "_checkTasks"
	2	[1095]	CALL     	3 2 3
	3	[1095]	MOVE     	2 4
	4	[1095]	MOVE     	1 3
	5	[1103]	GETTABLE 	3 0 -2	; "_window_stack"
	6	[1103]	LEN      	3 3
	7	[1103]	EQ       	0 3 -3	; - 0
	8	[1103]	JMP      	11	; to 20
	9	[1103]	GETTABLE 	3 0 -4	; "_run_forever"
	10	[1103]	TEST     	3 0 1
	11	[1103]	JMP      	8	; to 20
	12	[1104]	GETUPVAL 	3 0	; logger
	13	[1104]	GETTABLE 	3 3 -5	; "info"
	14	[1104]	LOADK    	4 -6	; "no dialog left to show"
	15	[1104]	CALL     	3 2 1
	16	[1105]	SELF     	3 0 -7	; "quit"
	17	[1105]	CALL     	3 2 1
	18	[1106]	LOADNIL  	3 3
	19	[1106]	RETURN   	3 2
	20	[1109]	SELF     	3 0 -8	; "_repaint"
	21	[1109]	CALL     	3 2 1
	22	[1110]	GETTABLE 	3 0 -9	; "_task_queue_dirty"
	23	[1110]	TEST     	3 0 1
	24	[1110]	JMP      	-24	; to 1
	25	[1113]	SELF     	3 0 -10	; "processZMQs"
	26	[1113]	CALL     	3 2 1
	27	[1117]	GETTABLE 	3 0 -11	; "INPUT_TIMEOUT"
	28	[1120]	TEST     	1 0 0
	29	[1120]	JMP      	17	; to 47
	30	[1121]	GETGLOBAL	4 -12	; math
	31	[1121]	GETTABLE 	4 4 -13	; "min"
	32	[1122]	TESTSET  	5 3 1
	33	[1122]	JMP      	2	; to 36
	34	[1122]	GETGLOBAL	5 -12	; math
	35	[1122]	GETTABLE 	5 5 -14	; "huge"
	36	[1123]	GETTABLE 	6 1 -15	; 1
	37	[1123]	GETTABLE 	7 2 -15	; 1
	38	[1123]	SUB      	6 6 7
	39	[1123]	GETUPVAL 	7 1	; MILLION
	40	[1123]	MUL      	6 6 7
	41	[1124]	GETTABLE 	7 1 -16	; 2
	42	[1124]	GETTABLE 	8 2 -16	; 2
	43	[1124]	SUB      	7 7 8
	44	[1124]	ADD      	6 6 7
	45	[1121]	CALL     	4 3 2
	46	[1124]	MOVE     	3 4
	47	[1128]	GETTABLE 	4 0 -17	; "_zeromqs"
	48	[1128]	LEN      	4 4
	49	[1128]	LT       	0 -3 4	; 0 -
	50	[1128]	JMP      	9	; to 60
	51	[1129]	GETGLOBAL	4 -12	; math
	52	[1129]	GETTABLE 	4 4 -13	; "min"
	53	[1129]	TESTSET  	5 3 1
	54	[1129]	JMP      	2	; to 57
	55	[1129]	GETGLOBAL	5 -12	; math
	56	[1129]	GETTABLE 	5 5 -14	; "huge"
	57	[1129]	GETTABLE 	6 0 -18	; "ZMQ_TIMEOUT"
	58	[1129]	CALL     	4 3 2
	59	[1129]	MOVE     	3 4
	60	[1133]	GETUPVAL 	4 2	; Input
	61	[1133]	SELF     	4 4 -19	; "waitEvent"
	62	[1133]	MOVE     	6 3
	63	[1133]	CALL     	4 3 2
	64	[1136]	TEST     	4 0 0
	65	[1136]	JMP      	3	; to 69
	66	[1137]	SELF     	5 0 -20	; "handleInputEvent"
	67	[1137]	MOVE     	7 4
	68	[1137]	CALL     	5 3 1
	69	[1140]	GETTABLE 	5 0 -21	; "looper"
	70	[1140]	TEST     	5 0 0
	71	[1140]	JMP      	9	; to 81
	72	[1141]	GETUPVAL 	5 0	; logger
	73	[1141]	GETTABLE 	5 5 -5	; "info"
	74	[1141]	LOADK    	6 -22	; "handle input in turbo I/O looper"
	75	[1141]	CALL     	5 2 1
	76	[1142]	GETTABLE 	5 0 -21	; "looper"
	77	[1142]	SELF     	5 5 -23	; "add_callback"
	78	[1152]	CLOSURE  	7 0	; 0x7ffe4860de80
	79	[1152]	MOVE     	0 0
	80	[1142]	CALL     	5 3 1
	81	[1154]	RETURN   	0 1

function <./frontend/ui/uimanager.lua:1142,1152> (7 instructions, 28 bytes at 0x7ffe4860de80)
0 params, 3 slots, 1 upvalue, 0 locals, 1 constant, 2 functions
	1	[1145]	GETGLOBAL	0 -1	; xpcall
	2	[1145]	CLOSURE  	1 0	; 0x7ffe4860e360
	3	[1145]	GETUPVAL 	0 0	; self
	4	[1151]	CLOSURE  	2 1	; 0x7ffe4860e570
	5	[1151]	GETUPVAL 	0 0	; self
	6	[1145]	CALL     	0 3 1
	7	[1152]	RETURN   	0 1

function <./frontend/ui/uimanager.lua:1145,1145> (4 instructions, 16 bytes at 0x7ffe4860e360)
0 params, 2 slots, 1 upvalue, 0 locals, 1 constant, 0 functions
	1	[1145]	GETUPVAL 	0 0	; self
	2	[1145]	SELF     	0 0 -1	; "handleInput"
	3	[1145]	CALL     	0 2 1
	4	[1145]	RETURN   	0 1

function <./frontend/ui/uimanager.lua:1145,1151> (29 instructions, 116 bytes at 0x7ffe4860e570)
1 param, 5 slots, 1 upvalue, 1 local, 12 constants, 0 functions
	1	[1146]	GETGLOBAL	1 -1	; io
	2	[1146]	GETTABLE 	1 1 -2	; "stderr"
	3	[1146]	SELF     	1 1 -3	; "write"
	4	[1146]	MOVE     	3 0
	5	[1146]	LOADK    	4 -4	; "\n"
	6	[1146]	CONCAT   	3 3 4
	7	[1146]	CALL     	1 3 1
	8	[1147]	GETGLOBAL	1 -1	; io
	9	[1147]	GETTABLE 	1 1 -2	; "stderr"
	10	[1147]	SELF     	1 1 -3	; "write"
	11	[1147]	GETGLOBAL	3 -5	; debug
	12	[1147]	GETTABLE 	3 3 -6	; "traceback"
	13	[1147]	CALL     	3 1 2
	14	[1147]	LOADK    	4 -4	; "\n"
	15	[1147]	CONCAT   	3 3 4
	16	[1147]	CALL     	1 3 1
	17	[1148]	GETGLOBAL	1 -1	; io
	18	[1148]	GETTABLE 	1 1 -2	; "stderr"
	19	[1148]	SELF     	1 1 -7	; "flush"
	20	[1148]	CALL     	1 2 1
	21	[1149]	GETUPVAL 	1 0	; self
	22	[1149]	GETTABLE 	1 1 -8	; "looper"
	23	[1149]	SELF     	1 1 -9	; "close"
	24	[1149]	CALL     	1 2 1
	25	[1150]	GETGLOBAL	1 -10	; os
	26	[1150]	GETTABLE 	1 1 -11	; "exit"
	27	[1150]	LOADK    	2 -12	; 1
	28	[1150]	CALL     	1 2 1
	29	[1151]	RETURN   	0 1

function <./frontend/ui/uimanager.lua:1157,1160> (7 instructions, 28 bytes at 0x7ffe4860eca0)
1 param, 5 slots, 0 upvalues, 1 local, 4 constants, 0 functions
	1	[1158]	SELF     	1 0 -1	; "setDirty"
	2	[1158]	LOADK    	3 -2	; "all"
	3	[1158]	LOADK    	4 -3	; "full"
	4	[1158]	CALL     	1 4 1
	5	[1159]	SELF     	1 0 -4	; "forceRePaint"
	6	[1159]	CALL     	1 2 1
	7	[1160]	RETURN   	0 1

function <./frontend/ui/uimanager.lua:1162,1169> (18 instructions, 72 bytes at 0x7ffe4860ee10)
1 param, 3 slots, 0 upvalues, 2 locals, 8 constants, 0 functions
	1	[1163]	GETGLOBAL	1 -1	; DUSE_TURBO_LIB
	2	[1163]	TEST     	1 0 0
	3	[1163]	JMP      	14	; to 18
	4	[1163]	GETTABLE 	1 0 -2	; "looper"
	5	[1163]	TEST     	1 0 1
	6	[1163]	JMP      	11	; to 18
	7	[1164]	LOADBOOL 	1 1 0
	8	[1164]	SETGLOBAL	1 -3	; TURBO_SSL
	9	[1165]	LOADBOOL 	1 1 0
	10	[1165]	SETGLOBAL	1 -4	; __TURBO_USE_LUASOCKET__
	11	[1166]	GETGLOBAL	1 -5	; require
	12	[1166]	LOADK    	2 -6	; "turbo"
	13	[1166]	CALL     	1 2 2
	14	[1167]	GETTABLE 	2 1 -7	; "ioloop"
	15	[1167]	GETTABLE 	2 2 -8	; "instance"
	16	[1167]	CALL     	2 1 2
	17	[1167]	SETTABLE 	0 -2 2	; "looper" -
	18	[1169]	RETURN   	0 1

function <./frontend/ui/uimanager.lua:1174,1189> (24 instructions, 96 bytes at 0x7ffe4860f2a0)
1 param, 4 slots, 0 upvalues, 1 local, 8 constants, 1 function
	1	[1175]	SETTABLE 	0 -1 -2	; "_running" true
	2	[1176]	SELF     	1 0 -3	; "initLooper"
	3	[1176]	CALL     	1 2 1
	4	[1179]	GETTABLE 	1 0 -4	; "looper"
	5	[1179]	TEST     	1 0 1
	6	[1179]	JMP      	7	; to 14
	7	[1180]	GETTABLE 	1 0 -1	; "_running"
	8	[1180]	TEST     	1 0 0
	9	[1180]	JMP      	12	; to 22
	10	[1181]	SELF     	1 0 -5	; "handleInput"
	11	[1181]	CALL     	1 2 1
	12	[1181]	JMP      	-6	; to 7
	13	[1182]	JMP      	8	; to 22
	14	[1184]	GETTABLE 	1 0 -4	; "looper"
	15	[1184]	SELF     	1 1 -6	; "add_callback"
	16	[1184]	CLOSURE  	3 0	; 0x7ffe4860f5e0
	17	[1184]	MOVE     	0 0
	18	[1184]	CALL     	1 3 1
	19	[1185]	GETTABLE 	1 0 -4	; "looper"
	20	[1185]	SELF     	1 1 -7	; "start"
	21	[1185]	CALL     	1 2 1
	22	[1188]	GETTABLE 	1 0 -8	; "_exit_code"
	23	[1188]	RETURN   	1 2
	24	[1189]	RETURN   	0 1

function <./frontend/ui/uimanager.lua:1184,1184> (4 instructions, 16 bytes at 0x7ffe4860f5e0)
0 params, 2 slots, 1 upvalue, 0 locals, 1 constant, 0 functions
	1	[1184]	GETUPVAL 	0 0	; self
	2	[1184]	SELF     	0 0 -1	; "handleInput"
	3	[1184]	CALL     	0 2 1
	4	[1184]	RETURN   	0 1

function <./frontend/ui/uimanager.lua:1192,1195> (5 instructions, 20 bytes at 0x7ffe4860f6e0)
1 param, 3 slots, 0 upvalues, 1 local, 3 constants, 0 functions
	1	[1193]	SETTABLE 	0 -1 -2	; "_run_forever" true
	2	[1194]	SELF     	1 0 -3	; "run"
	3	[1194]	TAILCALL 	1 2 0
	4	[1194]	RETURN   	1 0
	5	[1195]	RETURN   	0 1

function <./frontend/ui/uimanager.lua:1198,1201> (9 instructions, 36 bytes at 0x7ffe4860f7a0)
1 param, 6 slots, 1 upvalue, 1 local, 4 constants, 0 functions
	1	[1199]	SELF     	1 0 -1	; "flushSettings"
	2	[1199]	CALL     	1 2 1
	3	[1200]	SELF     	1 0 -2	; "broadcastEvent"
	4	[1200]	GETUPVAL 	3 0	; Event
	5	[1200]	SELF     	3 3 -3	; "new"
	6	[1200]	LOADK    	5 -4	; "Suspend"
	7	[1200]	CALL     	3 3 0
	8	[1200]	CALL     	1 0 1
	9	[1201]	RETURN   	0 1

function <./frontend/ui/uimanager.lua:1204,1206> (7 instructions, 28 bytes at 0x7ffe4860fd80)
1 param, 6 slots, 1 upvalue, 1 local, 3 constants, 0 functions
	1	[1205]	SELF     	1 0 -1	; "broadcastEvent"
	2	[1205]	GETUPVAL 	3 0	; Event
	3	[1205]	SELF     	3 3 -2	; "new"
	4	[1205]	LOADK    	5 -3	; "Resume"
	5	[1205]	CALL     	3 3 0
	6	[1205]	CALL     	1 0 1
	7	[1206]	RETURN   	0 1

function <./frontend/ui/uimanager.lua:1208,1210> (7 instructions, 28 bytes at 0x7ffe4860fe00)
1 param, 6 slots, 1 upvalue, 1 local, 3 constants, 0 functions
	1	[1209]	SELF     	1 0 -1	; "broadcastEvent"
	2	[1209]	GETUPVAL 	3 0	; Event
	3	[1209]	SELF     	3 3 -2	; "new"
	4	[1209]	LOADK    	5 -3	; "Charging"
	5	[1209]	CALL     	3 3 0
	6	[1209]	CALL     	1 0 1
	7	[1210]	RETURN   	0 1

function <./frontend/ui/uimanager.lua:1212,1214> (7 instructions, 28 bytes at 0x7ffe48610100)
1 param, 6 slots, 1 upvalue, 1 local, 3 constants, 0 functions
	1	[1213]	SELF     	1 0 -1	; "broadcastEvent"
	2	[1213]	GETUPVAL 	3 0	; Event
	3	[1213]	SELF     	3 3 -2	; "new"
	4	[1213]	LOADK    	5 -3	; "NotCharging"
	5	[1213]	CALL     	3 3 0
	6	[1213]	CALL     	1 0 1
	7	[1214]	RETURN   	0 1

function <./frontend/ui/uimanager.lua:1218,1224> (39 instructions, 156 bytes at 0x7ffe48610330)
1 param, 3 slots, 1 upvalue, 1 local, 10 constants, 0 functions
	1	[1219]	GETUPVAL 	1 0	; Device
	2	[1219]	SELF     	1 1 -1	; "isCervantes"
	3	[1219]	CALL     	1 2 2
	4	[1219]	TEST     	1 0 1
	5	[1219]	JMP      	20	; to 26
	6	[1219]	GETUPVAL 	1 0	; Device
	7	[1219]	SELF     	1 1 -2	; "isKobo"
	8	[1219]	CALL     	1 2 2
	9	[1219]	TEST     	1 0 1
	10	[1219]	JMP      	15	; to 26
	11	[1219]	GETUPVAL 	1 0	; Device
	12	[1219]	SELF     	1 1 -3	; "isSDL"
	13	[1219]	CALL     	1 2 2
	14	[1219]	TEST     	1 0 1
	15	[1219]	JMP      	10	; to 26
	16	[1219]	GETUPVAL 	1 0	; Device
	17	[1219]	SELF     	1 1 -4	; "isRemarkable"
	18	[1219]	CALL     	1 2 2
	19	[1219]	TEST     	1 0 1
	20	[1219]	JMP      	5	; to 26
	21	[1219]	GETUPVAL 	1 0	; Device
	22	[1219]	SELF     	1 1 -5	; "isSonyPRSTUX"
	23	[1219]	CALL     	1 2 2
	24	[1219]	TEST     	1 0 0
	25	[1219]	JMP      	4	; to 30
	26	[1220]	GETTABLE 	1 0 -6	; "event_handlers"
	27	[1220]	GETTABLE 	1 1 -7	; "Suspend"
	28	[1220]	CALL     	1 1 1
	29	[1220]	JMP      	9	; to 39
	30	[1221]	GETUPVAL 	1 0	; Device
	31	[1221]	SELF     	1 1 -8	; "isKindle"
	32	[1221]	CALL     	1 2 2
	33	[1221]	TEST     	1 0 0
	34	[1221]	JMP      	4	; to 39
	35	[1222]	GETUPVAL 	1 0	; Device
	36	[1222]	GETTABLE 	1 1 -9	; "powerd"
	37	[1222]	SELF     	1 1 -10	; "toggleSuspend"
	38	[1222]	CALL     	1 2 1
	39	[1224]	RETURN   	0 1

function <./frontend/ui/uimanager.lua:1227,1233> (38 instructions, 152 bytes at 0x7ffe486106c0)
1 param, 3 slots, 1 upvalue, 1 local, 9 constants, 0 functions
	1	[1228]	GETUPVAL 	1 0	; Device
	2	[1228]	SELF     	1 1 -1	; "isCervantes"
	3	[1228]	CALL     	1 2 2
	4	[1228]	TEST     	1 0 1
	5	[1228]	JMP      	20	; to 26
	6	[1228]	GETUPVAL 	1 0	; Device
	7	[1228]	SELF     	1 1 -2	; "isKobo"
	8	[1228]	CALL     	1 2 2
	9	[1228]	TEST     	1 0 1
	10	[1228]	JMP      	15	; to 26
	11	[1228]	GETUPVAL 	1 0	; Device
	12	[1228]	SELF     	1 1 -3	; "isSDL"
	13	[1228]	CALL     	1 2 2
	14	[1228]	TEST     	1 0 1
	15	[1228]	JMP      	10	; to 26
	16	[1228]	GETUPVAL 	1 0	; Device
	17	[1228]	SELF     	1 1 -4	; "isRemarkable"
	18	[1228]	CALL     	1 2 2
	19	[1228]	TEST     	1 0 1
	20	[1228]	JMP      	5	; to 26
	21	[1228]	GETUPVAL 	1 0	; Device
	22	[1228]	SELF     	1 1 -5	; "isSonyPRSTUX"
	23	[1228]	CALL     	1 2 2
	24	[1228]	TEST     	1 0 0
	25	[1228]	JMP      	4	; to 30
	26	[1229]	GETTABLE 	1 0 -6	; "event_handlers"
	27	[1229]	GETTABLE 	1 1 -7	; "Resume"
	28	[1229]	CALL     	1 1 1
	29	[1229]	JMP      	8	; to 38
	30	[1230]	GETUPVAL 	1 0	; Device
	31	[1230]	SELF     	1 1 -8	; "isKindle"
	32	[1230]	CALL     	1 2 2
	33	[1230]	TEST     	1 0 0
	34	[1230]	JMP      	3	; to 38
	35	[1231]	GETTABLE 	1 0 -6	; "event_handlers"
	36	[1231]	GETTABLE 	1 1 -9	; "OutOfSS"
	37	[1231]	CALL     	1 1 1
	38	[1233]	RETURN   	0 1

function <./frontend/ui/uimanager.lua:1235,1237> (7 instructions, 28 bytes at 0x7ffe48610620)
1 param, 6 slots, 1 upvalue, 1 local, 3 constants, 0 functions
	1	[1236]	SELF     	1 0 -1	; "broadcastEvent"
	2	[1236]	GETUPVAL 	3 0	; Event
	3	[1236]	SELF     	3 3 -2	; "new"
	4	[1236]	LOADK    	5 -3	; "FlushSettings"
	5	[1236]	CALL     	3 3 0
	6	[1236]	CALL     	1 0 1
	7	[1237]	RETURN   	0 1

function <./frontend/ui/uimanager.lua:1239,1243> (4 instructions, 16 bytes at 0x7ffe4860c3a0)
1 param, 3 slots, 0 upvalues, 1 local, 3 constants, 0 functions
	1	[1240]	SELF     	1 0 -1	; "quit"
	2	[1240]	CALL     	1 2 1
	3	[1242]	SETTABLE 	0 -2 -3	; "_exit_code" 85
	4	[1243]	RETURN   	0 1
