-- BYTECODE -- underlinecontainer.lua:20-26
0001    TGETB    1   0   1
0002    MOV      2   1
0003    TGETS    1   1   0  ; "getSize"
0004    CALL     1   2   2
0005    UGET     2   0      ; Geom
0006    MOV      3   2
0007    TGETS    2   2   1  ; "new"
0008    TDUP     4   3
0009    TGETS    5   1   2  ; "w"
0010    TSETS    5   4   2  ; "w"
0011    TGETS    5   1   4  ; "h"
0012    TGETS    6   0   5  ; "linesize"
0013    ADDVV    5   5   6
0014    TGETS    6   0   6  ; "padding"
0015    MULNV    6   6   0  ; 2
0016    ADDVV    5   5   6
0017    TSETS    5   4   4  ; "h"
0018    CALLT    2   3

-- BYTECODE -- underlinecontainer.lua:28-45
0001    MOV      5   0
0002    TGETS    4   0   0  ; "getSize"
0003    CALL     4   2   2
0004    UGET     5   0      ; Geom
0005    MOV      6   5
0006    TGETS    5   5   2  ; "new"
0007    TDUP     7   3
0008    TSETS    2   7   4  ; "x"
0009    TSETS    3   7   5  ; "y"
0010    TGETS    8   4   6  ; "w"
0011    TSETS    8   7   6  ; "w"
0012    TGETS    8   4   7  ; "h"
0013    TSETS    8   7   7  ; "h"
0014    CALL     5   2   3
0015    TSETS    5   0   1  ; "dimen"
0016    TGETB    5   0   1
0017    MOV      6   5
0018    TGETS    5   5   0  ; "getSize"
0019    CALL     5   2   2
0020    MOV      6   3
0021    TGETS    7   0   8  ; "vertical_align"
0022    ISNES    7   9      ; "center"
0023    JMP      7 => 0033
0024    GGET     7  10      ; "math"
0025    TGETS    7   7  11  ; "floor"
0026    TGETS    8   4   7  ; "h"
0027    TGETS    9   5   7  ; "h"
0028    SUBVV    8   8   9
0029    DIVVN    8   8   0  ; 2
0030    CALL     7   2   2
0031    ADDVV    6   7   3
0032    JMP      7 => 0040
0033 => TGETS    7   0   8  ; "vertical_align"
0034    ISNES    7  12      ; "bottom"
0035    JMP      7 => 0040
0036    TGETS    7   4   7  ; "h"
0037    TGETS    8   5   7  ; "h"
0038    SUBVV    7   7   8
0039    ADDVV    6   7   3
0040 => TGETB    7   0   1
0041    MOV      8   7
0042    TGETS    7   7  13  ; "paintTo"
0043    MOV      9   1
0044    MOV     10   2
0045    MOV     11   6
0046    CALL     7   1   5
0047    MOV      8   1
0048    TGETS    7   1  14  ; "paintRect"
0049    MOV      9   2
0050    TGETS   10   4   7  ; "h"
0051    ADDVV   10   3  10
0052    TGETS   11   0  15  ; "linesize"
0053    SUBVV   10  10  11
0054    TGETS   11   4   6  ; "w"
0055    TGETS   12   0  15  ; "linesize"
0056    TGETS   13   0  16  ; "color"
0057    CALL     7   1   7
0058    RET0     0   1

-- BYTECODE -- underlinecontainer.lua:0-48
0001    GGET     0   0      ; "require"
0002    KSTR     1   1      ; "ffi/blitbuffer"
0003    CALL     0   2   2
0004    GGET     1   0      ; "require"
0005    KSTR     2   2      ; "ui/geometry"
0006    CALL     1   2   2
0007    GGET     2   0      ; "require"
0008    KSTR     3   3      ; "ui/size"
0009    CALL     2   2   2
0010    GGET     3   0      ; "require"
0011    KSTR     4   4      ; "ui/widget/container/widgetcontainer"
0012    CALL     3   2   2
0013    MOV      5   3
0014    TGETS    4   3   5  ; "new"
0015    TDUP     6   8
0016    TGETS    7   2   6  ; "line"
0017    TGETS    7   7   7  ; "thick"
0018    TSETS    7   6   9  ; "linesize"
0019    TGETS    7   2  10  ; "padding"
0020    TGETS    7   7  11  ; "tiny"
0021    TSETS    7   6  10  ; "padding"
0022    TGETS    7   0  12  ; "COLOR_WHITE"
0023    TSETS    7   6  13  ; "color"
0024    CALL     4   2   3
0025    FNEW     5  15      ; underlinecontainer.lua:20
0026    TSETS    5   4  14  ; "getSize"
0027    FNEW     5  17      ; underlinecontainer.lua:28
0028    TSETS    5   4  16  ; "paintTo"
0029    UCLO     0 => 0030
0030 => RET1     4   2

