
main <./frontend/util.lua:0,0> (206 instructions, 824 bytes at 0x7fed58c068a0)
0+ params, 27 slots, 0 upvalues, 17 locals, 81 constants, 48 functions
	1	[5]	GETGLOBAL	0 -1	; require
	2	[5]	LOADK    	1 -2	; "ffi/util"
	3	[5]	CALL     	0 2 2
	4	[6]	GETGLOBAL	1 -1	; require
	5	[6]	LOADK    	2 -3	; "dbg"
	6	[6]	CALL     	1 2 2
	7	[7]	GETGLOBAL	2 -1	; require
	8	[7]	LOADK    	3 -4	; "gettext"
	9	[7]	CALL     	2 2 2
	10	[8]	GETTABLE 	3 0 -5	; "template"
	11	[10]	GETGLOBAL	4 -6	; bit
	12	[10]	GETTABLE 	4 4 -7	; "lshift"
	13	[11]	GETGLOBAL	5 -6	; bit
	14	[11]	GETTABLE 	5 5 -8	; "rshift"
	15	[12]	GETGLOBAL	6 -6	; bit
	16	[12]	GETTABLE 	6 6 -9	; "band"
	17	[13]	GETGLOBAL	7 -6	; bit
	18	[13]	GETTABLE 	7 7 -10	; "bor"
	19	[15]	NEWTABLE 	8 0 0
	20	[25]	CLOSURE  	9 0	; 0x7fed58c06c20
	21	[20]	SETTABLE 	8 -11 9	; "stripPunctuation" -
	22	[73]	CLOSURE  	9 1	; 0x7fed58c07290
	23	[48]	SETTABLE 	8 -12 9	; "gsplit" -
	24	[105]	CLOSURE  	9 2	; 0x7fed58c07a50
	25	[83]	SETTABLE 	8 -13 9	; "secondsToClock" -
	26	[195]	CLOSURE  	9 3	; 0x7fed58c07d90
	27	[195]	MOVE     	0 3
	28	[195]	MOVE     	0 2
	29	[112]	SETTABLE 	8 -14 9	; "secondsToHClock" -
	30	[236]	CLOSURE  	9 4	; 0x7fed58c08190
	31	[236]	MOVE     	0 8
	32	[207]	SETTABLE 	8 -15 9	; "tableEquals" -
	33	[263]	CLOSURE  	9 5	; 0x7fed58c08cd0
	34	[263]	MOVE     	0 8
	35	[245]	SETTABLE 	8 -16 9	; "tableDeepCopy" -
	36	[272]	CLOSURE  	9 6	; 0x7fed58c07090
	37	[268]	SETTABLE 	8 -17 9	; "tableSize" -
	38	[281]	CLOSURE  	9 7	; 0x7fed58c09cb0
	39	[277]	SETTABLE 	8 -18 9	; "arrayAppend" -
	40	[292]	CLOSURE  	9 8	; 0x7fed58c0a1a0
	41	[285]	SETTABLE 	8 -19 9	; "arrayReverse" -
	42	[302]	CLOSURE  	9 9	; 0x7fed58c0a8d0
	43	[298]	SETTABLE 	8 -20 9	; "tableMerge" -
	44	[318]	CLOSURE  	9 10	; 0x7fed58c0a950
	45	[315]	SETTABLE 	8 -21 9	; "lastIndexOf" -
	46	[326]	CLOSURE  	9 11	; 0x7fed58c0af30
	47	[323]	SETTABLE 	8 -22 9	; "utf8Reverse" -
	48	[382]	CLOSURE  	9 12	; 0x7fed58c0b560
	49	[382]	MOVE     	0 0
	50	[382]	MOVE     	0 4
	51	[382]	MOVE     	0 8
	52	[331]	SETTABLE 	8 -23 9	; "splitToChars" -
	53	[389]	CLOSURE  	9 13	; 0x7fed58c0a540
	54	[387]	SETTABLE 	8 -24 9	; "isCJKChar" -
	55	[396]	CLOSURE  	9 14	; 0x7fed58c0ba40
	56	[394]	SETTABLE 	8 -25 9	; "hasCJKChar" -
	57	[415]	CLOSURE  	9 15	; 0x7fed58c0bf80
	58	[415]	MOVE     	0 8
	59	[401]	SETTABLE 	8 -26 9	; "splitToWords" -
	60	[421]	LOADK    	9 -27	; ":;,.!?)]}$%=-+*/|<>\194\187\226\128\157"
	61	[423]	LOADK    	10 -28	; "([{$=-+*/|<>\194\171\226\128\156"
	62	[429]	GETGLOBAL	11 -29	; table
	63	[429]	GETTABLE 	11 11 -30	; "concat"
	64	[429]	NEWTABLE 	12 4 0
	65	[431]	LOADK    	13 -31	; "!%),.:;?]}\194\162\194\176\194\183\226\128\153\"\226\128\160\226\128\161\226\128\186\226\132\131\226\136\182\227\128\129\227\128\130\227\128\131\227\128\134\227\128\149\227\128\151\227\128\158\239\185\154\239\185\156\239\188\129\239\188\130\239\188\133\239\188\135\239\188\137\239\188\140\239\188\142\239\188\154\239\188\155\239\188\159\239\188\129\239\188\189\239\189\157\239\189\158"
	66	[433]	LOADK    	14 -32	; "!),.:;?]}\194\162\194\183\226\128\147\226\128\148\226\128\153\"\226\128\162\227\128\129\227\128\130\227\128\134\227\128\158\227\128\149\227\128\137\227\128\139\227\128\141\239\184\176\239\184\177\239\184\178\239\184\179\239\185\144\239\185\145\239\185\146\239\185\147\239\185\148\239\185\149\239\185\150\239\185\152\239\185\154\239\185\156\239\188\129\239\188\137\239\188\140\239\188\142\239\188\154\239\188\155\239\188\159\239\184\182\239\184\184\239\184\186\239\184\188\239\184\190\239\185\128\239\185\130\239\185\151\239\188\189\239\189\156\239\189\157\239\189\164"
	67	[435]	LOADK    	15 -33	; ")]\239\189\157\227\128\149\227\128\137\227\128\139\227\128\141\227\128\143\227\128\145\227\128\153\227\128\151\227\128\159\226\128\153\"\239\189\160\194\187\227\131\189\227\131\190\227\131\188\227\130\161\227\130\163\227\130\165\227\130\167\227\130\169\227\131\131\227\131\163\227\131\165\227\131\167\227\131\174\227\131\181\227\131\182\227\129\129\227\129\131\227\129\133\227\129\135\227\129\137\227\129\163\227\130\131\227\130\133\227\130\135\227\130\142\227\130\149\227\130\150\227\135\176\227\135\177\227\135\178\227\135\179\227\135\180\227\135\181\227\135\182\227\135\183\227\135\184\227\135\185\227\135\186\227\135\187\227\135\188\227\135\189\227\135\190\227\135\191\227\128\133\227\128\187\226\128\144\227\130\160\226\128\147\227\128\156?!\226\128\188\226\129\135\226\129\136\226\129\137\227\131\187\227\128\129:;,\227\128\130."
	68	[438]	LOADK    	16 -34	; "!%),.:;?]}\194\162\194\176\226\128\153\"\226\128\160\226\128\161\226\132\131\227\128\134\227\128\136\227\128\138\227\128\140\227\128\142\227\128\149\239\188\129\239\188\133\239\188\137\239\188\140\239\188\142\239\188\154\239\188\155\239\188\159\239\188\189\239\189\157"
	69	[438]	SETLIST  	12 4 1	; 1
	70	[429]	CALL     	11 2 2
	71	[440]	GETGLOBAL	12 -29	; table
	72	[440]	GETTABLE 	12 12 -30	; "concat"
	73	[440]	NEWTABLE 	13 4 0
	74	[442]	LOADK    	14 -35	; "$(\194\163\194\165\194\183\226\128\152\"\227\128\136\227\128\138\227\128\140\227\128\142\227\128\144\227\128\148\227\128\150\227\128\157\239\185\153\239\185\155\239\188\132\239\188\136\239\188\142\239\188\187\239\189\155\239\191\161\239\191\165"
	75	[444]	LOADK    	15 -36	; "([{\194\163\194\165\226\128\152\"\226\128\181\227\128\136\227\128\138\227\128\140\227\128\142\227\128\148\227\128\157\239\184\180\239\185\153\239\185\155\239\188\136\239\189\155\239\184\181\239\184\183\239\184\185\239\184\187\239\184\189\239\184\191\239\185\129\239\185\131\239\185\143"
	76	[446]	LOADK    	16 -37	; "([\239\189\155\227\128\148\227\128\136\227\128\138\227\128\140\227\128\142\227\128\144\227\128\152\227\128\150\227\128\157\226\128\152\"\239\189\159\194\171"
	77	[449]	LOADK    	17 -38	; "$([{\194\163\194\165\226\128\152\"\227\128\133\227\128\135\227\128\137\227\128\139\227\128\141\227\128\148\239\188\132\239\188\136\239\188\187\239\189\155\239\189\160\239\191\165\239\191\166#"
	78	[449]	SETLIST  	13 4 1	; 1
	79	[440]	CALL     	12 2 2
	80	[451]	GETGLOBAL	13 -29	; table
	81	[451]	GETTABLE 	13 13 -30	; "concat"
	82	[451]	NEWTABLE 	14 1 0
	83	[454]	LOADK    	15 -39	; "\226\128\148\226\128\166\226\128\165\227\128\179\227\128\180\227\128\181"
	84	[454]	SETLIST  	14 1 1	; 1
	85	[451]	CALL     	13 2 2
	86	[494]	CLOSURE  	14 16	; 0x7fed58c09be0
	87	[494]	MOVE     	0 8
	88	[494]	MOVE     	0 13
	89	[494]	MOVE     	0 11
	90	[494]	MOVE     	0 12
	91	[494]	MOVE     	0 9
	92	[494]	MOVE     	0 10
	93	[462]	SETTABLE 	8 -40 14	; "isSplittable" -
	94	[522]	CLOSURE  	14 17	; 0x7fed58c0a6c0
	95	[501]	SETTABLE 	8 -41 14	; "getFilesystemType" -
	96	[538]	CLOSURE  	14 18	; 0x7fed58c0d110
	97	[527]	SETTABLE 	8 -42 14	; "isEmptyDir" -
	98	[546]	CLOSURE  	14 19	; 0x7fed58c0d8f0
	99	[543]	SETTABLE 	8 -43 14	; "pathExists" -
	100	[564]	CLOSURE  	14 20	; 0x7fed58c0daf0
	101	[564]	MOVE     	0 8
	102	[553]	SETTABLE 	8 -44 14	; "makePath" -
	103	[577]	CLOSURE  	14 21	; 0x7fed58c0e0a0
	104	[586]	CLOSURE  	15 22	; 0x7fed58c0dfc0
	105	[634]	CLOSURE  	16 23	; 0x7fed58c0e8c0
	106	[634]	MOVE     	0 8
	107	[634]	MOVE     	0 14
	108	[634]	MOVE     	0 15
	109	[599]	SETTABLE 	8 -45 16	; "getSafeFilename" -
	110	[645]	CLOSURE  	16 24	; 0x7fed58c0efd0
	111	[641]	SETTABLE 	8 -46 16	; "splitFilePathName" -
	112	[654]	CLOSURE  	16 25	; 0x7fed58c0f410
	113	[650]	SETTABLE 	8 -47 16	; "splitFileNameSuffix" -
	114	[662]	CLOSURE  	16 26	; 0x7fed58c0f510
	115	[662]	MOVE     	0 8
	116	[659]	SETTABLE 	8 -48 16	; "getFileNameSuffix" -
	117	[676]	CLOSURE  	16 27	; 0x7fed58c0f690
	118	[676]	MOVE     	0 8
	119	[668]	SETTABLE 	8 -49 16	; "isAllowedScript" -
	120	[689]	CLOSURE  	16 28	; 0x7fed58c10080
	121	[689]	MOVE     	0 8
	122	[682]	SETTABLE 	8 -50 16	; "getScriptType" -
	123	[715]	CLOSURE  	16 29	; 0x7fed58c103b0
	124	[715]	MOVE     	0 3
	125	[715]	MOVE     	0 2
	126	[695]	SETTABLE 	8 -51 16	; "getFriendlySize" -
	127	[725]	CLOSURE  	16 30	; 0x7fed58c0b4e0
	128	[720]	SETTABLE 	8 -52 16	; "getFormattedSize" -
	129	[757]	CLOSURE  	16 31	; 0x7fed58c10600
	130	[737]	SETTABLE 	8 -53 16	; "fixUtf8" -
	131	[771]	CLOSURE  	16 32	; 0x7fed58c10800
	132	[771]	MOVE     	0 8
	133	[765]	SETTABLE 	8 -54 16	; "splitToArray" -
	134	[807]	CLOSURE  	16 33	; 0x7fed58c0e6c0
	135	[807]	MOVE     	0 7
	136	[807]	MOVE     	0 5
	137	[807]	MOVE     	0 6
	138	[780]	SETTABLE 	8 -55 16	; "unicodeCodepointToUtf8" -
	139	[810]	NEWTABLE 	16 8 0
	140	[810]	NEWTABLE 	17 2 0
	141	[811]	LOADK    	18 -56	; "&lt;"
	142	[811]	LOADK    	19 -57	; "<"
	143	[811]	SETLIST  	17 2 1	; 1
	144	[811]	NEWTABLE 	18 2 0
	145	[812]	LOADK    	19 -58	; "&gt;"
	146	[812]	LOADK    	20 -59	; ">"
	147	[812]	SETLIST  	18 2 1	; 1
	148	[812]	NEWTABLE 	19 2 0
	149	[813]	LOADK    	20 -60	; "&quot;"
	150	[813]	LOADK    	21 -61	; "\""
	151	[813]	SETLIST  	19 2 1	; 1
	152	[813]	NEWTABLE 	20 2 0
	153	[814]	LOADK    	21 -62	; "&apos;"
	154	[814]	LOADK    	22 -63	; "'"
	155	[814]	SETLIST  	20 2 1	; 1
	156	[814]	NEWTABLE 	21 2 0
	157	[815]	LOADK    	22 -64	; "&nbsp;"
	158	[815]	LOADK    	23 -65	; "xC2xA0"
	159	[815]	SETLIST  	21 2 1	; 1
	160	[815]	NEWTABLE 	22 2 0
	161	[816]	LOADK    	23 -66	; "&#(%d+);"
	162	[816]	CLOSURE  	24 34	; 0x7fed58c0caa0
	163	[816]	MOVE     	0 8
	164	[816]	SETLIST  	22 2 1	; 1
	165	[816]	NEWTABLE 	23 2 0
	166	[817]	LOADK    	24 -67	; "&#x(%x+);"
	167	[817]	CLOSURE  	25 35	; 0x7fed58c0a840
	168	[817]	MOVE     	0 8
	169	[817]	SETLIST  	23 2 1	; 1
	170	[817]	NEWTABLE 	24 2 0
	171	[818]	LOADK    	25 -68	; "&amp;"
	172	[818]	LOADK    	26 -69	; "&"
	173	[818]	SETLIST  	24 2 1	; 1
	174	[819]	SETLIST  	16 8 1	; 1
	175	[833]	CLOSURE  	17 36	; 0x7fed58c115b0
	176	[833]	MOVE     	0 16
	177	[828]	SETTABLE 	8 -70 17	; "htmlEntitiesToUtf8" -
	178	[857]	CLOSURE  	17 37	; 0x7fed58c11810
	179	[857]	MOVE     	0 8
	180	[843]	SETTABLE 	8 -71 17	; "htmlToPlainText" -
	181	[895]	CLOSURE  	17 38	; 0x7fed58c11f90
	182	[895]	MOVE     	0 8
	183	[866]	SETTABLE 	8 -72 17	; "htmlToPlainTextIfHtml" -
	184	[909]	CLOSURE  	17 39	; 0x7fed58c11ed0
	185	[900]	SETTABLE 	8 -73 17	; "htmlEscape" -
	186	[921]	CLOSURE  	17 40	; 0x7fed58c127c0
	187	[914]	SETTABLE 	8 -74 17	; "shell_escape" -
	188	[928]	CLOSURE  	17 41	; 0x7fed58c12be0
	189	[925]	SETTABLE 	8 -75 17	; "clearTable" -
	190	[944]	CLOSURE  	17 42	; 0x7fed58c13010
	191	[934]	SETTABLE 	8 -76 17	; "urlEncode" -
	192	[959]	CLOSURE  	17 43	; 0x7fed58c13900
	193	[950]	SETTABLE 	8 -77 17	; "urlDecode" -
	194	[973]	CLOSURE  	17 44	; 0x7fed58c140f0
	195	[964]	SETTABLE 	8 -78 17	; "checkLuaSyntax" -
	196	[995]	CLOSURE  	17 45	; 0x7fed58c14680
	197	[995]	MOVE     	0 1
	198	[995]	MOVE     	0 3
	199	[995]	MOVE     	0 2
	200	[981]	SETTABLE 	8 -79 17	; "unpackArchive" -
	201	[1004]	CLOSURE  	17 46	; 0x7fed58c14ab0
	202	[1002]	SETTABLE 	8 -80 17	; "stringStartsWith" -
	203	[1011]	CLOSURE  	17 47	; 0x7fed58c15490
	204	[1009]	SETTABLE 	8 -81 17	; "stringEndsWith" -
	205	[1013]	RETURN   	8 2
	206	[1013]	RETURN   	0 1

function <./frontend/util.lua:20,25> (17 instructions, 68 bytes at 0x7fed58c06c20)
1 param, 5 slots, 0 upvalues, 1 local, 5 constants, 0 functions
	1	[21]	TEST     	0 0 1
	2	[21]	JMP      	1	; to 4
	3	[21]	RETURN   	0 1
	4	[24]	SELF     	1 0 -1	; "gsub"
	5	[24]	LOADK    	3 -2	; "\226[\128-\131][\128-\191]"
	6	[24]	LOADK    	4 -3	; ""
	7	[24]	CALL     	1 4 2
	8	[24]	SELF     	1 1 -1	; "gsub"
	9	[24]	LOADK    	3 -4	; "^%p+"
	10	[24]	LOADK    	4 -3	; ""
	11	[24]	CALL     	1 4 2
	12	[24]	SELF     	1 1 -1	; "gsub"
	13	[24]	LOADK    	3 -5	; "%p+$"
	14	[24]	LOADK    	4 -3	; ""
	15	[24]	TAILCALL 	1 4 0
	16	[24]	RETURN   	1 0
	17	[25]	RETURN   	0 1

function <./frontend/util.lua:48,73> (28 instructions, 112 bytes at 0x7fed58c07290)
4 params, 7 slots, 0 upvalues, 4 locals, 9 constants, 1 function
	1	[49]	TEST     	1 0 0
	2	[49]	JMP      	5	; to 8
	3	[49]	GETGLOBAL	4 -1	; tostring
	4	[49]	MOVE     	5 1
	5	[49]	CALL     	4 2 2
	6	[49]	TESTSET  	1 4 1
	7	[49]	JMP      	1	; to 9
	8	[49]	LOADK    	1 -2	; "%s+"
	9	[50]	LOADK    	4 -3	; ""
	10	[50]	SELF     	4 4 -4	; "find"
	11	[50]	MOVE     	6 1
	12	[50]	CALL     	4 3 2
	13	[50]	TEST     	4 0 0
	14	[50]	JMP      	4	; to 19
	15	[51]	GETGLOBAL	4 -5	; error
	16	[51]	LOADK    	5 -6	; "pattern matches empty string!"
	17	[51]	LOADK    	6 -7	; 2
	18	[51]	CALL     	4 3 1
	19	[53]	GETGLOBAL	4 -8	; coroutine
	20	[53]	GETTABLE 	4 4 -9	; "wrap"
	21	[72]	CLOSURE  	5 0	; 0x7fed58c075d0
	22	[72]	MOVE     	0 0
	23	[72]	MOVE     	0 1
	24	[72]	MOVE     	0 3
	25	[72]	MOVE     	0 2
	26	[53]	TAILCALL 	4 2 0
	27	[72]	RETURN   	4 0
	28	[73]	RETURN   	0 1

function <./frontend/util.lua:53,72> (55 instructions, 220 bytes at 0x7fed58c075d0)
0 params, 8 slots, 4 upvalues, 3 locals, 5 constants, 0 functions
	1	[54]	LOADK    	0 -1	; 1
	2	[56]	GETUPVAL 	1 0	; str
	3	[56]	SELF     	1 1 -2	; "find"
	4	[56]	GETUPVAL 	3 1	; pattern
	5	[56]	MOVE     	4 0
	6	[56]	CALL     	1 4 3
	7	[57]	TEST     	1 0 0
	8	[57]	JMP      	30	; to 39
	9	[57]	TEST     	2 0 0
	10	[57]	JMP      	28	; to 39
	11	[58]	LT       	1 0 1
	12	[58]	JMP      	5	; to 18
	13	[58]	EQ       	0 0 1
	14	[58]	JMP      	11	; to 26
	15	[58]	GETUPVAL 	3 2	; capture_empty_entity
	16	[58]	TEST     	3 0 0
	17	[58]	JMP      	8	; to 26
	18	[59]	GETGLOBAL	3 -3	; coroutine
	19	[59]	GETTABLE 	3 3 -4	; "yield"
	20	[59]	GETUPVAL 	4 0	; str
	21	[59]	SELF     	4 4 -5	; "sub"
	22	[59]	MOVE     	6 0
	23	[59]	SUB      	7 1 -1	; - 1
	24	[59]	CALL     	4 4 0
	25	[59]	CALL     	3 0 1
	26	[61]	GETUPVAL 	3 3	; capture
	27	[61]	TEST     	3 0 0
	28	[61]	JMP      	8	; to 37
	29	[62]	GETGLOBAL	3 -3	; coroutine
	30	[62]	GETTABLE 	3 3 -4	; "yield"
	31	[62]	GETUPVAL 	4 0	; str
	32	[62]	SELF     	4 4 -5	; "sub"
	33	[62]	MOVE     	6 1
	34	[62]	MOVE     	7 2
	35	[62]	CALL     	4 4 0
	36	[62]	CALL     	3 0 1
	37	[64]	ADD      	0 2 -1	; - 1
	38	[64]	JMP      	12	; to 51
	39	[66]	GETUPVAL 	3 0	; str
	40	[66]	LEN      	3 3
	41	[66]	LE       	0 0 3
	42	[66]	JMP      	12	; to 55
	43	[67]	GETGLOBAL	3 -3	; coroutine
	44	[67]	GETTABLE 	3 3 -4	; "yield"
	45	[67]	GETUPVAL 	4 0	; str
	46	[67]	SELF     	4 4 -5	; "sub"
	47	[67]	MOVE     	6 0
	48	[67]	CALL     	4 3 0
	49	[67]	CALL     	3 0 1
	50	[69]	JMP      	4	; to 55
	51	[71]	GETUPVAL 	3 0	; str
	52	[71]	LEN      	3 3
	53	[71]	LT       	0 3 0
	54	[71]	JMP      	-53	; to 2
	55	[72]	RETURN   	0 1

function <./frontend/util.lua:83,105> (83 instructions, 332 bytes at 0x7fed58c07a50)
2 params, 11 slots, 0 upvalues, 6 locals, 17 constants, 0 functions
	1	[84]	GETGLOBAL	2 -1	; tonumber
	2	[84]	MOVE     	3 0
	3	[84]	CALL     	2 2 2
	4	[84]	MOVE     	0 2
	5	[85]	EQ       	1 0 -2	; - 0
	6	[85]	JMP      	2	; to 9
	7	[85]	EQ       	1 0 0
	8	[85]	JMP      	8	; to 17
	9	[86]	TEST     	1 0 0
	10	[86]	JMP      	3	; to 14
	11	[87]	LOADK    	2 -3	; "00:00"
	12	[87]	RETURN   	2 2
	13	[87]	JMP      	69	; to 83
	14	[89]	LOADK    	2 -4	; "00:00:00"
	15	[89]	RETURN   	2 2
	16	[90]	JMP      	66	; to 83
	17	[92]	TEST     	1 0 0
	18	[92]	JMP      	6	; to 25
	19	[92]	GETGLOBAL	2 -5	; require
	20	[92]	LOADK    	3 -6	; "optmath"
	21	[92]	CALL     	2 2 2
	22	[92]	GETTABLE 	2 2 -7	; "round"
	23	[92]	TEST     	2 0 1
	24	[92]	JMP      	2	; to 27
	25	[92]	GETGLOBAL	2 -8	; math
	26	[92]	GETTABLE 	2 2 -9	; "floor"
	27	[93]	GETGLOBAL	3 -10	; string
	28	[93]	GETTABLE 	3 3 -11	; "format"
	29	[93]	LOADK    	4 -12	; "%02.f"
	30	[93]	GETGLOBAL	5 -8	; math
	31	[93]	GETTABLE 	5 5 -9	; "floor"
	32	[93]	DIV      	6 0 -13	; - 3600
	33	[93]	CALL     	5 2 0
	34	[93]	CALL     	3 0 2
	35	[94]	GETGLOBAL	4 -10	; string
	36	[94]	GETTABLE 	4 4 -11	; "format"
	37	[94]	LOADK    	5 -12	; "%02.f"
	38	[94]	MOVE     	6 2
	39	[94]	DIV      	7 0 -14	; - 60
	40	[94]	MUL      	8 3 -14	; - 60
	41	[94]	SUB      	7 7 8
	42	[94]	CALL     	6 2 0
	43	[94]	CALL     	4 0 2
	44	[95]	EQ       	0 4 -15	; - "60"
	45	[95]	JMP      	12	; to 58
	46	[96]	GETGLOBAL	5 -10	; string
	47	[96]	GETTABLE 	5 5 -11	; "format"
	48	[96]	LOADK    	6 -12	; "%02.f"
	49	[96]	LOADK    	7 -2	; 0
	50	[96]	CALL     	5 3 2
	51	[96]	MOVE     	4 5
	52	[97]	GETGLOBAL	5 -10	; string
	53	[97]	GETTABLE 	5 5 -11	; "format"
	54	[97]	LOADK    	6 -12	; "%02.f"
	55	[97]	ADD      	7 3 -16	; - 1
	56	[97]	CALL     	5 3 2
	57	[97]	MOVE     	3 5
	58	[99]	TEST     	1 0 0
	59	[99]	JMP      	5	; to 65
	60	[100]	MOVE     	5 3
	61	[100]	LOADK    	6 -17	; ":"
	62	[100]	MOVE     	7 4
	63	[100]	CONCAT   	5 5 7
	64	[100]	RETURN   	5 2
	65	[102]	GETGLOBAL	5 -10	; string
	66	[102]	GETTABLE 	5 5 -11	; "format"
	67	[102]	LOADK    	6 -12	; "%02.f"
	68	[102]	GETGLOBAL	7 -8	; math
	69	[102]	GETTABLE 	7 7 -9	; "floor"
	70	[102]	MUL      	8 3 -13	; - 3600
	71	[102]	SUB      	8 0 8
	72	[102]	MUL      	9 4 -14	; - 60
	73	[102]	SUB      	8 8 9
	74	[102]	CALL     	7 2 0
	75	[102]	CALL     	5 0 2
	76	[103]	MOVE     	6 3
	77	[103]	LOADK    	7 -17	; ":"
	78	[103]	MOVE     	8 4
	79	[103]	LOADK    	9 -17	; ":"
	80	[103]	MOVE     	10 5
	81	[103]	CONCAT   	6 6 10
	82	[103]	RETURN   	6 2
	83	[105]	RETURN   	0 1

function <./frontend/util.lua:112,195> (252 instructions, 1008 bytes at 0x7fed58c07d90)
3 params, 12 slots, 2 upvalues, 7 locals, 32 constants, 0 functions
	1	[113]	GETGLOBAL	3 -1	; tonumber
	2	[113]	MOVE     	4 0
	3	[113]	CALL     	3 2 2
	4	[113]	MOVE     	0 3
	5	[114]	EQ       	0 0 -2	; - 0
	6	[114]	JMP      	28	; to 35
	7	[115]	TEST     	1 0 0
	8	[115]	JMP      	13	; to 22
	9	[116]	TEST     	2 0 0
	10	[116]	JMP      	8	; to 19
	11	[117]	GETUPVAL 	3 0	; T
	12	[117]	GETUPVAL 	4 1	; _
	13	[117]	LOADK    	5 -3	; "%1m"
	14	[117]	CALL     	4 2 2
	15	[117]	LOADK    	5 -4	; "0"
	16	[117]	TAILCALL 	3 3 0
	17	[117]	RETURN   	3 0
	18	[117]	JMP      	233	; to 252
	19	[119]	LOADK    	3 -5	; "0'"
	20	[119]	RETURN   	3 2
	21	[120]	JMP      	230	; to 252
	22	[122]	TEST     	2 0 0
	23	[122]	JMP      	8	; to 32
	24	[123]	GETUPVAL 	3 0	; T
	25	[123]	GETUPVAL 	4 1	; _
	26	[123]	LOADK    	5 -6	; "%1s"
	27	[123]	CALL     	4 2 2
	28	[123]	LOADK    	5 -4	; "0"
	29	[123]	TAILCALL 	3 3 0
	30	[123]	RETURN   	3 0
	31	[123]	JMP      	220	; to 252
	32	[125]	LOADK    	3 -7	; "0''"
	33	[125]	RETURN   	3 2
	34	[127]	JMP      	217	; to 252
	35	[128]	LT       	0 0 -8	; - 60
	36	[128]	JMP      	59	; to 96
	37	[129]	TEST     	1 0 0
	38	[129]	JMP      	15	; to 54
	39	[129]	LT       	0 0 -9	; - 30
	40	[129]	JMP      	13	; to 54
	41	[130]	TEST     	2 0 0
	42	[130]	JMP      	8	; to 51
	43	[131]	GETUPVAL 	3 0	; T
	44	[131]	GETUPVAL 	4 1	; _
	45	[131]	LOADK    	5 -3	; "%1m"
	46	[131]	CALL     	4 2 2
	47	[131]	LOADK    	5 -4	; "0"
	48	[131]	TAILCALL 	3 3 0
	49	[131]	RETURN   	3 0
	50	[131]	JMP      	201	; to 252
	51	[133]	LOADK    	3 -5	; "0'"
	52	[133]	RETURN   	3 2
	53	[134]	JMP      	198	; to 252
	54	[135]	TEST     	1 0 0
	55	[135]	JMP      	15	; to 71
	56	[135]	LE       	0 -9 0	; 30 -
	57	[135]	JMP      	13	; to 71
	58	[136]	TEST     	2 0 0
	59	[136]	JMP      	8	; to 68
	60	[137]	GETUPVAL 	3 0	; T
	61	[137]	GETUPVAL 	4 1	; _
	62	[137]	LOADK    	5 -3	; "%1m"
	63	[137]	CALL     	4 2 2
	64	[137]	LOADK    	5 -10	; "1"
	65	[137]	TAILCALL 	3 3 0
	66	[137]	RETURN   	3 0
	67	[137]	JMP      	184	; to 252
	68	[139]	LOADK    	3 -11	; "1'"
	69	[139]	RETURN   	3 2
	70	[140]	JMP      	181	; to 252
	71	[142]	TEST     	2 0 0
	72	[142]	JMP      	13	; to 86
	73	[143]	GETUPVAL 	3 0	; T
	74	[143]	GETUPVAL 	4 1	; _
	75	[143]	LOADK    	5 -12	; "%1m%2s"
	76	[143]	CALL     	4 2 2
	77	[143]	LOADK    	5 -4	; "0"
	78	[143]	GETGLOBAL	6 -13	; string
	79	[143]	GETTABLE 	6 6 -14	; "format"
	80	[143]	LOADK    	7 -15	; "%02.f"
	81	[143]	MOVE     	8 0
	82	[143]	CALL     	6 3 0
	83	[143]	TAILCALL 	3 0 0
	84	[143]	RETURN   	3 0
	85	[143]	JMP      	166	; to 252
	86	[145]	LOADK    	3 -5	; "0'"
	87	[145]	GETGLOBAL	4 -13	; string
	88	[145]	GETTABLE 	4 4 -14	; "format"
	89	[145]	LOADK    	5 -15	; "%02.f"
	90	[145]	MOVE     	6 0
	91	[145]	CALL     	4 3 2
	92	[145]	LOADK    	5 -16	; "''"
	93	[145]	CONCAT   	3 3 5
	94	[145]	RETURN   	3 2
	95	[147]	JMP      	156	; to 252
	96	[149]	TEST     	1 0 0
	97	[149]	JMP      	6	; to 104
	98	[149]	GETGLOBAL	3 -17	; require
	99	[149]	LOADK    	4 -18	; "optmath"
	100	[149]	CALL     	3 2 2
	101	[149]	GETTABLE 	3 3 -19	; "round"
	102	[149]	TEST     	3 0 1
	103	[149]	JMP      	2	; to 106
	104	[149]	GETGLOBAL	3 -20	; math
	105	[149]	GETTABLE 	3 3 -21	; "floor"
	106	[150]	GETGLOBAL	4 -13	; string
	107	[150]	GETTABLE 	4 4 -14	; "format"
	108	[150]	LOADK    	5 -22	; "%.f"
	109	[150]	GETGLOBAL	6 -20	; math
	110	[150]	GETTABLE 	6 6 -21	; "floor"
	111	[150]	DIV      	7 0 -23	; - 3600
	112	[150]	CALL     	6 2 0
	113	[150]	CALL     	4 0 2
	114	[151]	GETGLOBAL	5 -13	; string
	115	[151]	GETTABLE 	5 5 -14	; "format"
	116	[151]	LOADK    	6 -15	; "%02.f"
	117	[151]	MOVE     	7 3
	118	[151]	DIV      	8 0 -8	; - 60
	119	[151]	MUL      	9 4 -8	; - 60
	120	[151]	SUB      	8 8 9
	121	[151]	CALL     	7 2 0
	122	[151]	CALL     	5 0 2
	123	[152]	EQ       	0 5 -24	; - "60"
	124	[152]	JMP      	12	; to 137
	125	[153]	GETGLOBAL	6 -13	; string
	126	[153]	GETTABLE 	6 6 -14	; "format"
	127	[153]	LOADK    	7 -15	; "%02.f"
	128	[153]	LOADK    	8 -2	; 0
	129	[153]	CALL     	6 3 2
	130	[153]	MOVE     	5 6
	131	[154]	GETGLOBAL	6 -13	; string
	132	[154]	GETTABLE 	6 6 -14	; "format"
	133	[154]	LOADK    	7 -22	; "%.f"
	134	[154]	ADD      	8 4 -25	; - 1
	135	[154]	CALL     	6 3 2
	136	[154]	MOVE     	4 6
	137	[156]	TEST     	1 0 0
	138	[156]	JMP      	32	; to 171
	139	[157]	EQ       	0 4 -4	; - "0"
	140	[157]	JMP      	22	; to 163
	141	[158]	GETGLOBAL	6 -13	; string
	142	[158]	GETTABLE 	6 6 -14	; "format"
	143	[158]	LOADK    	7 -22	; "%.f"
	144	[158]	MOVE     	8 3
	145	[158]	DIV      	9 0 -8	; - 60
	146	[158]	CALL     	8 2 0
	147	[158]	CALL     	6 0 2
	148	[158]	MOVE     	5 6
	149	[159]	TEST     	2 0 0
	150	[159]	JMP      	8	; to 159
	151	[160]	GETUPVAL 	6 0	; T
	152	[160]	GETUPVAL 	7 1	; _
	153	[160]	LOADK    	8 -3	; "%1m"
	154	[160]	CALL     	7 2 2
	155	[160]	MOVE     	8 5
	156	[160]	TAILCALL 	6 3 0
	157	[160]	RETURN   	6 0
	158	[160]	JMP      	4	; to 163
	159	[162]	MOVE     	6 5
	160	[162]	LOADK    	7 -26	; "'"
	161	[162]	CONCAT   	6 6 7
	162	[162]	RETURN   	6 2
	163	[166]	GETUPVAL 	6 0	; T
	164	[166]	GETUPVAL 	7 1	; _
	165	[166]	LOADK    	8 -27	; "%1h%2"
	166	[166]	CALL     	7 2 2
	167	[166]	MOVE     	8 4
	168	[166]	MOVE     	9 5
	169	[166]	TAILCALL 	6 4 0
	170	[166]	RETURN   	6 0
	171	[168]	GETGLOBAL	6 -13	; string
	172	[168]	GETTABLE 	6 6 -14	; "format"
	173	[168]	LOADK    	7 -15	; "%02.f"
	174	[168]	GETGLOBAL	8 -20	; math
	175	[168]	GETTABLE 	8 8 -21	; "floor"
	176	[168]	MUL      	9 4 -23	; - 3600
	177	[168]	SUB      	9 0 9
	178	[168]	MUL      	10 5 -8	; - 60
	179	[168]	SUB      	9 9 10
	180	[168]	CALL     	8 2 0
	181	[168]	CALL     	6 0 2
	182	[169]	EQ       	0 4 -4	; - "0"
	183	[169]	JMP      	25	; to 209
	184	[170]	GETGLOBAL	7 -13	; string
	185	[170]	GETTABLE 	7 7 -14	; "format"
	186	[170]	LOADK    	8 -22	; "%.f"
	187	[170]	MOVE     	9 3
	188	[170]	DIV      	10 0 -8	; - 60
	189	[170]	CALL     	9 2 0
	190	[170]	CALL     	7 0 2
	191	[170]	MOVE     	5 7
	192	[171]	TEST     	2 0 0
	193	[171]	JMP      	9	; to 203
	194	[173]	GETUPVAL 	7 0	; T
	195	[173]	GETUPVAL 	8 1	; _
	196	[173]	LOADK    	9 -12	; "%1m%2s"
	197	[173]	CALL     	8 2 2
	198	[173]	MOVE     	9 5
	199	[173]	MOVE     	10 6
	200	[173]	TAILCALL 	7 4 0
	201	[173]	RETURN   	7 0
	202	[173]	JMP      	6	; to 209
	203	[175]	MOVE     	7 5
	204	[175]	LOADK    	8 -26	; "'"
	205	[175]	MOVE     	9 6
	206	[175]	LOADK    	10 -16	; "''"
	207	[175]	CONCAT   	7 7 10
	208	[175]	RETURN   	7 2
	209	[178]	TEST     	2 0 0
	210	[178]	JMP      	21	; to 232
	211	[179]	EQ       	0 6 -28	; - "00"
	212	[179]	JMP      	9	; to 222
	213	[181]	GETUPVAL 	7 0	; T
	214	[181]	GETUPVAL 	8 1	; _
	215	[181]	LOADK    	9 -29	; "%1h%2m"
	216	[181]	CALL     	8 2 2
	217	[181]	MOVE     	9 4
	218	[181]	MOVE     	10 5
	219	[181]	TAILCALL 	7 4 0
	220	[181]	RETURN   	7 0
	221	[181]	JMP      	30	; to 252
	222	[184]	GETUPVAL 	7 0	; T
	223	[184]	GETUPVAL 	8 1	; _
	224	[184]	LOADK    	9 -30	; "%1h%2m%3s"
	225	[184]	CALL     	8 2 2
	226	[184]	MOVE     	9 4
	227	[184]	MOVE     	10 5
	228	[184]	MOVE     	11 6
	229	[184]	TAILCALL 	7 5 0
	230	[184]	RETURN   	7 0
	231	[185]	JMP      	20	; to 252
	232	[188]	EQ       	0 6 -28	; - "00"
	233	[188]	JMP      	9	; to 243
	234	[189]	GETUPVAL 	7 0	; T
	235	[189]	GETUPVAL 	8 1	; _
	236	[189]	LOADK    	9 -31	; "%1h%2'"
	237	[189]	CALL     	8 2 2
	238	[189]	MOVE     	9 4
	239	[189]	MOVE     	10 5
	240	[189]	TAILCALL 	7 4 0
	241	[189]	RETURN   	7 0
	242	[189]	JMP      	9	; to 252
	243	[191]	GETUPVAL 	7 0	; T
	244	[191]	GETUPVAL 	8 1	; _
	245	[191]	LOADK    	9 -32	; "%1h%2'%3''"
	246	[191]	CALL     	8 2 2
	247	[191]	MOVE     	9 4
	248	[191]	MOVE     	10 5
	249	[191]	MOVE     	11 6
	250	[191]	TAILCALL 	7 5 0
	251	[191]	RETURN   	7 0
	252	[195]	RETURN   	0 1

function <./frontend/util.lua:207,236> (68 instructions, 272 bytes at 0x7fed58c08190)
3 params, 16 slots, 1 upvalue, 18 locals, 9 constants, 0 functions
	1	[208]	EQ       	0 0 1
	2	[208]	JMP      	2	; to 5
	3	[208]	LOADBOOL 	3 1 0
	4	[208]	RETURN   	3 2
	5	[209]	GETGLOBAL	3 -1	; type
	6	[209]	MOVE     	4 0
	7	[209]	CALL     	3 2 2
	8	[210]	GETGLOBAL	4 -1	; type
	9	[210]	MOVE     	5 1
	10	[210]	CALL     	4 2 2
	11	[211]	EQ       	1 3 4
	12	[211]	JMP      	2	; to 15
	13	[211]	LOADBOOL 	5 0 0
	14	[211]	RETURN   	5 2
	15	[212]	EQ       	1 3 -2	; - "table"
	16	[212]	JMP      	2	; to 19
	17	[212]	LOADBOOL 	5 0 0
	18	[212]	RETURN   	5 2
	19	[214]	TEST     	2 0 1
	20	[214]	JMP      	13	; to 34
	21	[215]	GETGLOBAL	5 -3	; getmetatable
	22	[215]	MOVE     	6 0
	23	[215]	CALL     	5 2 2
	24	[216]	TEST     	5 0 0
	25	[216]	JMP      	8	; to 34
	26	[216]	GETTABLE 	6 5 -4	; "__eq"
	27	[216]	TEST     	6 0 0
	28	[216]	JMP      	5	; to 34
	29	[218]	EQ       	1 0 1
	30	[218]	JMP      	1	; to 32
	31	[218]	LOADBOOL 	6 0 1
	32	[218]	LOADBOOL 	6 1 0
	33	[218]	RETURN   	6 2
	34	[222]	NEWTABLE 	5 0 0
	35	[224]	GETGLOBAL	6 -5	; pairs
	36	[224]	MOVE     	7 0
	37	[224]	CALL     	6 2 4
	38	[224]	JMP      	14	; to 53
	39	[225]	GETTABLE 	11 1 9
	40	[226]	EQ       	1 11 -6	; - nil
	41	[226]	JMP      	8	; to 50
	42	[226]	GETUPVAL 	12 0	; util
	43	[226]	GETTABLE 	12 12 -7	; "tableEquals"
	44	[226]	MOVE     	13 10
	45	[226]	MOVE     	14 11
	46	[226]	MOVE     	15 2
	47	[226]	CALL     	12 4 2
	48	[226]	EQ       	0 12 -8	; - false
	49	[226]	JMP      	2	; to 52
	50	[227]	LOADBOOL 	12 0 0
	51	[227]	RETURN   	12 2
	52	[229]	SETTABLE 	5 9 -9	; - true
	53	[224]	TFORLOOP 	6 2
	54	[229]	JMP      	-16	; to 39
	55	[232]	GETGLOBAL	6 -5	; pairs
	56	[232]	MOVE     	7 1
	57	[232]	CALL     	6 2 4
	58	[232]	JMP      	5	; to 64
	59	[233]	GETTABLE 	11 5 9
	60	[233]	TEST     	11 0 1
	61	[233]	JMP      	2	; to 64
	62	[233]	LOADBOOL 	11 0 0
	63	[233]	RETURN   	11 2
	64	[232]	TFORLOOP 	6 2
	65	[233]	JMP      	-7	; to 59
	66	[235]	LOADBOOL 	6 1 0
	67	[235]	RETURN   	6 2
	68	[236]	RETURN   	0 1

function <./frontend/util.lua:245,263> (53 instructions, 212 bytes at 0x7fed58c08cd0)
2 params, 12 slots, 1 upvalue, 8 locals, 7 constants, 0 functions
	1	[246]	TEST     	1 0 1
	2	[246]	JMP      	2	; to 5
	3	[246]	NEWTABLE 	2 0 0
	4	[246]	MOVE     	1 2
	5	[247]	EQ       	0 0 -1	; - nil
	6	[247]	JMP      	2	; to 9
	7	[247]	LOADNIL  	2 2
	8	[247]	RETURN   	2 2
	9	[248]	GETTABLE 	2 1 0
	10	[248]	TEST     	2 0 0
	11	[248]	JMP      	2	; to 14
	12	[248]	GETTABLE 	2 1 0
	13	[248]	RETURN   	2 2
	14	[250]	LOADNIL  	2 2
	15	[251]	GETGLOBAL	3 -2	; type
	16	[251]	MOVE     	4 0
	17	[251]	CALL     	3 2 2
	18	[251]	EQ       	0 3 -3	; - "table"
	19	[251]	JMP      	31	; to 51
	20	[252]	NEWTABLE 	3 0 0
	21	[252]	MOVE     	2 3
	22	[253]	SETTABLE 	1 0 2
	23	[255]	GETGLOBAL	3 -4	; next
	24	[255]	MOVE     	4 0
	25	[255]	LOADNIL  	5 5
	26	[255]	JMP      	11	; to 38
	27	[256]	GETUPVAL 	8 0	; util
	28	[256]	GETTABLE 	8 8 -5	; "tableDeepCopy"
	29	[256]	MOVE     	9 6
	30	[256]	MOVE     	10 1
	31	[256]	CALL     	8 3 2
	32	[256]	GETUPVAL 	9 0	; util
	33	[256]	GETTABLE 	9 9 -5	; "tableDeepCopy"
	34	[256]	MOVE     	10 7
	35	[256]	MOVE     	11 1
	36	[256]	CALL     	9 3 2
	37	[256]	SETTABLE 	2 8 9
	38	[255]	TFORLOOP 	3 2
	39	[256]	JMP      	-13	; to 27
	40	[258]	GETGLOBAL	3 -6	; setmetatable
	41	[258]	MOVE     	4 2
	42	[258]	GETUPVAL 	5 0	; util
	43	[258]	GETTABLE 	5 5 -5	; "tableDeepCopy"
	44	[258]	GETGLOBAL	6 -7	; getmetatable
	45	[258]	MOVE     	7 0
	46	[258]	CALL     	6 2 2
	47	[258]	MOVE     	7 1
	48	[258]	CALL     	5 3 0
	49	[258]	CALL     	3 0 1
	50	[258]	JMP      	1	; to 52
	51	[260]	MOVE     	2 0
	52	[262]	RETURN   	2 2
	53	[263]	RETURN   	0 1

function <./frontend/util.lua:268,272> (10 instructions, 40 bytes at 0x7fed58c07090)
1 param, 8 slots, 0 upvalues, 6 locals, 3 constants, 0 functions
	1	[269]	LOADK    	1 -1	; 0
	2	[270]	GETGLOBAL	2 -2	; pairs
	3	[270]	MOVE     	3 0
	4	[270]	CALL     	2 2 4
	5	[270]	JMP      	1	; to 7
	6	[270]	ADD      	1 1 -3	; - 1
	7	[270]	TFORLOOP 	2 1
	8	[270]	JMP      	-3	; to 6
	9	[271]	RETURN   	1 2
	10	[272]	RETURN   	0 1

function <./frontend/util.lua:277,281> (12 instructions, 48 bytes at 0x7fed58c09cb0)
2 params, 10 slots, 0 upvalues, 7 locals, 3 constants, 0 functions
	1	[278]	GETGLOBAL	2 -1	; ipairs
	2	[278]	MOVE     	3 1
	3	[278]	CALL     	2 2 4
	4	[278]	JMP      	5	; to 10
	5	[279]	GETGLOBAL	7 -2	; table
	6	[279]	GETTABLE 	7 7 -3	; "insert"
	7	[279]	MOVE     	8 0
	8	[279]	MOVE     	9 6
	9	[279]	CALL     	7 3 1
	10	[278]	TFORLOOP 	2 2
	11	[279]	JMP      	-7	; to 5
	12	[281]	RETURN   	0 1

function <./frontend/util.lua:285,292> (12 instructions, 48 bytes at 0x7fed58c0a1a0)
1 param, 5 slots, 0 upvalues, 3 locals, 1 constant, 0 functions
	1	[286]	LOADK    	1 -1	; 1
	2	[286]	LEN      	2 0
	3	[287]	LT       	0 1 2
	4	[287]	JMP      	7	; to 12
	5	[288]	GETTABLE 	3 0 2
	6	[288]	GETTABLE 	4 0 1
	7	[288]	SETTABLE 	0 2 4
	8	[288]	SETTABLE 	0 1 3
	9	[289]	ADD      	1 1 -1	; - 1
	10	[290]	SUB      	2 2 -1	; - 1
	11	[290]	JMP      	-9	; to 3
	12	[292]	RETURN   	0 1

function <./frontend/util.lua:298,302> (8 instructions, 32 bytes at 0x7fed58c0a8d0)
2 params, 8 slots, 0 upvalues, 7 locals, 1 constant, 0 functions
	1	[299]	GETGLOBAL	2 -1	; pairs
	2	[299]	MOVE     	3 1
	3	[299]	CALL     	2 2 4
	4	[299]	JMP      	1	; to 6
	5	[300]	SETTABLE 	0 5 6
	6	[299]	TFORLOOP 	2 2
	7	[300]	JMP      	-3	; to 5
	8	[302]	RETURN   	0 1

function <./frontend/util.lua:315,318> (14 instructions, 56 bytes at 0x7fed58c0a950)
2 params, 7 slots, 0 upvalues, 3 locals, 6 constants, 0 functions
	1	[316]	SELF     	2 0 -1	; "match"
	2	[316]	LOADK    	4 -2	; ".*"
	3	[316]	MOVE     	5 1
	4	[316]	LOADK    	6 -3	; "()"
	5	[316]	CONCAT   	4 4 6
	6	[316]	CALL     	2 3 2
	7	[317]	EQ       	0 2 -4	; - nil
	8	[317]	JMP      	3	; to 12
	9	[317]	LOADK    	3 -5	; -1
	10	[317]	RETURN   	3 2
	11	[317]	JMP      	2	; to 14
	12	[317]	SUB      	3 2 -6	; - 1
	13	[317]	RETURN   	3 2
	14	[318]	RETURN   	0 1

function <./frontend/util.lua:323,326> (9 instructions, 36 bytes at 0x7fed58c0af30)
1 param, 5 slots, 0 upvalues, 1 local, 3 constants, 1 function
	1	[324]	SELF     	1 0 -1	; "gsub"
	2	[324]	LOADK    	3 -2	; "[%z\001-\127\194-\244][\128-\191]*"
	3	[324]	CLOSURE  	4 0	; 0x7fed58c0b190
	4	[324]	CALL     	1 4 2
	5	[324]	MOVE     	0 1
	6	[325]	SELF     	1 0 -3	; "reverse"
	7	[325]	TAILCALL 	1 2 0
	8	[325]	RETURN   	1 0
	9	[326]	RETURN   	0 1

function <./frontend/util.lua:324,324> (10 instructions, 40 bytes at 0x7fed58c0b190)
1 param, 3 slots, 0 upvalues, 1 local, 2 constants, 0 functions
	1	[324]	LEN      	1 0
	2	[324]	LT       	0 -1 1	; 1 -
	3	[324]	JMP      	3	; to 7
	4	[324]	SELF     	1 0 -2	; "reverse"
	5	[324]	CALL     	1 2 2
	6	[324]	JMP      	2	; to 9
	7	[324]	LOADBOOL 	1 0 1
	8	[324]	LOADBOOL 	1 1 0
	9	[324]	RETURN   	1 2
	10	[324]	RETURN   	0 1

function <./frontend/util.lua:331,382> (77 instructions, 308 bytes at 0x7fed58c0b560)
1 param, 14 slots, 3 upvalues, 10 locals, 15 constants, 0 functions
	1	[332]	NEWTABLE 	1 0 0
	2	[333]	EQ       	1 0 -1	; - nil
	3	[333]	JMP      	72	; to 76
	4	[334]	LOADK    	2 -2	; 0
	5	[334]	LOADNIL  	3 5
	6	[353]	GETGLOBAL	6 -3	; string
	7	[353]	GETTABLE 	6 6 -4	; "gmatch"
	8	[353]	MOVE     	7 0
	9	[353]	LOADK    	8 -5	; "([%z\001-\127\194-\244][\128-\191]*)"
	10	[353]	CALL     	6 3 4
	11	[353]	JMP      	62	; to 74
	12	[354]	GETUPVAL 	10 0	; BaseUtil
	13	[354]	GETTABLE 	10 10 -6	; "utf8charcode"
	14	[354]	MOVE     	11 9
	15	[354]	CALL     	10 2 2
	16	[354]	MOVE     	3 10
	17	[358]	TEST     	2 0 0
	18	[358]	JMP      	54	; to 73
	19	[359]	TEST     	3 0 0
	20	[359]	JMP      	14	; to 35
	21	[359]	LE       	0 -7 3	; 55296 -
	22	[359]	JMP      	12	; to 35
	23	[359]	LE       	0 3 -8	; - 56319
	24	[359]	JMP      	10	; to 35
	25	[360]	TEST     	4 0 0
	26	[360]	JMP      	5	; to 32
	27	[361]	GETGLOBAL	10 -9	; table
	28	[361]	GETTABLE 	10 10 -10	; "insert"
	29	[361]	MOVE     	11 1
	30	[361]	MOVE     	12 5
	31	[361]	CALL     	10 3 1
	32	[363]	MOVE     	4 3
	33	[364]	MOVE     	5 9
	34	[364]	JMP      	38	; to 73
	35	[365]	TEST     	4 0 0
	36	[365]	JMP      	23	; to 60
	37	[365]	TEST     	3 0 0
	38	[365]	JMP      	21	; to 60
	39	[365]	LE       	0 -11 3	; 56320 -
	40	[365]	JMP      	19	; to 60
	41	[365]	LE       	0 3 -12	; - 57343
	42	[365]	JMP      	17	; to 60
	43	[367]	GETUPVAL 	10 1	; lshift
	44	[367]	SUB      	11 4 -7	; - 55296
	45	[367]	LOADK    	12 -13	; 10
	46	[367]	CALL     	10 3 2
	47	[367]	SUB      	11 3 -11	; - 56320
	48	[367]	ADD      	10 10 11
	49	[367]	ADD      	3 10 -14	; - 65536
	50	[368]	GETGLOBAL	10 -9	; table
	51	[368]	GETTABLE 	10 10 -10	; "insert"
	52	[368]	MOVE     	11 1
	53	[368]	GETUPVAL 	12 2	; util
	54	[368]	GETTABLE 	12 12 -15	; "unicodeCodepointToUtf8"
	55	[368]	MOVE     	13 3
	56	[368]	CALL     	12 2 0
	57	[368]	CALL     	10 0 1
	58	[369]	LOADNIL  	4 4
	59	[369]	JMP      	13	; to 73
	60	[371]	TEST     	4 0 0
	61	[371]	JMP      	5	; to 67
	62	[372]	GETGLOBAL	10 -9	; table
	63	[372]	GETTABLE 	10 10 -10	; "insert"
	64	[372]	MOVE     	11 1
	65	[372]	MOVE     	12 5
	66	[372]	CALL     	10 3 1
	67	[374]	LOADNIL  	4 4
	68	[375]	GETGLOBAL	10 -9	; table
	69	[375]	GETTABLE 	10 10 -10	; "insert"
	70	[375]	MOVE     	11 1
	71	[375]	MOVE     	12 9
	72	[375]	CALL     	10 3 1
	73	[378]	MOVE     	2 3
	74	[353]	TFORLOOP 	6 1
	75	[378]	JMP      	-64	; to 12
	76	[381]	RETURN   	1 2
	77	[382]	RETURN   	0 1

function <./frontend/util.lua:387,389> (11 instructions, 44 bytes at 0x7fed58c0a540)
1 param, 4 slots, 0 upvalues, 1 local, 3 constants, 0 functions
	1	[388]	GETGLOBAL	1 -1	; string
	2	[388]	GETTABLE 	1 1 -2	; "match"
	3	[388]	MOVE     	2 0
	4	[388]	LOADK    	3 -3	; "[\228-\234][\128-\191]."
	5	[388]	CALL     	1 3 2
	6	[388]	EQ       	1 1 0
	7	[388]	JMP      	1	; to 9
	8	[388]	LOADBOOL 	1 0 1
	9	[388]	LOADBOOL 	1 1 0
	10	[388]	RETURN   	1 2
	11	[389]	RETURN   	0 1

function <./frontend/util.lua:394,396> (11 instructions, 44 bytes at 0x7fed58c0ba40)
1 param, 4 slots, 0 upvalues, 1 local, 4 constants, 0 functions
	1	[395]	GETGLOBAL	1 -1	; string
	2	[395]	GETTABLE 	1 1 -2	; "match"
	3	[395]	MOVE     	2 0
	4	[395]	LOADK    	3 -3	; "[\228-\234][\128-\191]."
	5	[395]	CALL     	1 3 2
	6	[395]	EQ       	0 1 -4	; - nil
	7	[395]	JMP      	1	; to 9
	8	[395]	LOADBOOL 	1 0 1
	9	[395]	LOADBOOL 	1 1 0
	10	[395]	RETURN   	1 2
	11	[396]	RETURN   	0 1

function <./frontend/util.lua:401,415> (38 instructions, 152 bytes at 0x7fed58c0bf80)
1 param, 13 slots, 1 upvalue, 10 locals, 6 constants, 0 functions
	1	[402]	NEWTABLE 	1 0 0
	2	[403]	GETUPVAL 	2 0	; util
	3	[403]	GETTABLE 	2 2 -1	; "gsplit"
	4	[403]	MOVE     	3 0
	5	[403]	LOADK    	4 -2	; "[%s%p]+"
	6	[403]	LOADBOOL 	5 1 0
	7	[403]	CALL     	2 4 4
	8	[403]	JMP      	26	; to 35
	9	[405]	GETUPVAL 	6 0	; util
	10	[405]	GETTABLE 	6 6 -3	; "hasCJKChar"
	11	[405]	MOVE     	7 5
	12	[405]	CALL     	6 2 2
	13	[405]	TEST     	6 0 0
	14	[405]	JMP      	15	; to 30
	15	[407]	GETUPVAL 	6 0	; util
	16	[407]	GETTABLE 	6 6 -1	; "gsplit"
	17	[407]	MOVE     	7 5
	18	[407]	LOADK    	8 -4	; "[\228-\234\192-\255][\128-\191]+"
	19	[407]	LOADBOOL 	9 1 0
	20	[407]	CALL     	6 4 4
	21	[407]	JMP      	5	; to 27
	22	[408]	GETGLOBAL	10 -5	; table
	23	[408]	GETTABLE 	10 10 -6	; "insert"
	24	[408]	MOVE     	11 1
	25	[408]	MOVE     	12 9
	26	[408]	CALL     	10 3 1
	27	[407]	TFORLOOP 	6 1
	28	[408]	JMP      	-7	; to 22
	29	[409]	JMP      	5	; to 35
	30	[411]	GETGLOBAL	6 -5	; table
	31	[411]	GETTABLE 	6 6 -6	; "insert"
	32	[411]	MOVE     	7 1
	33	[411]	MOVE     	8 5
	34	[411]	CALL     	6 3 1
	35	[403]	TFORLOOP 	2 1
	36	[412]	JMP      	-28	; to 9
	37	[414]	RETURN   	1 2
	38	[415]	RETURN   	0 1

function <./frontend/util.lua:462,494> (79 instructions, 316 bytes at 0x7fed58c09be0)
3 params, 8 slots, 6 upvalues, 3 locals, 4 constants, 0 functions
	1	[463]	GETUPVAL 	3 0	; util
	2	[463]	GETTABLE 	3 3 -1	; "isCJKChar"
	3	[463]	MOVE     	4 0
	4	[463]	CALL     	3 2 2
	5	[463]	TEST     	3 0 0
	6	[463]	JMP      	40	; to 47
	7	[465]	GETUPVAL 	3 1	; cjk_non_splittable
	8	[465]	SELF     	3 3 -2	; "find"
	9	[465]	MOVE     	5 0
	10	[465]	LOADK    	6 -3	; 1
	11	[465]	LOADBOOL 	7 1 0
	12	[465]	CALL     	3 5 2
	13	[465]	TEST     	3 0 0
	14	[465]	JMP      	3	; to 18
	15	[467]	LOADBOOL 	3 0 0
	16	[467]	RETURN   	3 2
	17	[467]	JMP      	59	; to 77
	18	[468]	TEST     	1 0 0
	19	[468]	JMP      	11	; to 31
	20	[468]	GETUPVAL 	3 2	; cjk_non_splittable_tailers
	21	[468]	SELF     	3 3 -2	; "find"
	22	[468]	MOVE     	5 1
	23	[468]	LOADK    	6 -3	; 1
	24	[468]	LOADBOOL 	7 1 0
	25	[468]	CALL     	3 5 2
	26	[468]	TEST     	3 0 0
	27	[468]	JMP      	3	; to 31
	28	[470]	LOADBOOL 	3 0 0
	29	[470]	RETURN   	3 2
	30	[470]	JMP      	46	; to 77
	31	[471]	TEST     	2 0 0
	32	[471]	JMP      	11	; to 44
	33	[471]	GETUPVAL 	3 3	; cjk_non_splittable_leaders
	34	[471]	SELF     	3 3 -2	; "find"
	35	[471]	MOVE     	5 2
	36	[471]	LOADK    	6 -3	; 1
	37	[471]	LOADBOOL 	7 1 0
	38	[471]	CALL     	3 5 2
	39	[471]	TEST     	3 0 0
	40	[471]	JMP      	3	; to 44
	41	[473]	LOADBOOL 	3 0 0
	42	[473]	RETURN   	3 2
	43	[473]	JMP      	33	; to 77
	44	[476]	LOADBOOL 	3 1 0
	45	[476]	RETURN   	3 2
	46	[477]	JMP      	30	; to 77
	47	[478]	EQ       	0 0 -4	; - " "
	48	[478]	JMP      	28	; to 77
	49	[481]	TEST     	1 0 0
	50	[481]	JMP      	11	; to 62
	51	[481]	GETUPVAL 	3 4	; non_splittable_space_tailers
	52	[481]	SELF     	3 3 -2	; "find"
	53	[481]	MOVE     	5 1
	54	[481]	LOADK    	6 -3	; 1
	55	[481]	LOADBOOL 	7 1 0
	56	[481]	CALL     	3 5 2
	57	[481]	TEST     	3 0 0
	58	[481]	JMP      	3	; to 62
	59	[483]	LOADBOOL 	3 0 0
	60	[483]	RETURN   	3 2
	61	[483]	JMP      	15	; to 77
	62	[484]	TEST     	2 0 0
	63	[484]	JMP      	11	; to 75
	64	[484]	GETUPVAL 	3 5	; non_splittable_space_leaders
	65	[484]	SELF     	3 3 -2	; "find"
	66	[484]	MOVE     	5 2
	67	[484]	LOADK    	6 -3	; 1
	68	[484]	LOADBOOL 	7 1 0
	69	[484]	CALL     	3 5 2
	70	[484]	TEST     	3 0 0
	71	[484]	JMP      	3	; to 75
	72	[486]	LOADBOOL 	3 0 0
	73	[486]	RETURN   	3 2
	74	[486]	JMP      	2	; to 77
	75	[489]	LOADBOOL 	3 1 0
	76	[489]	RETURN   	3 2
	77	[493]	LOADBOOL 	3 0 0
	78	[493]	RETURN   	3 2
	79	[494]	RETURN   	0 1

function <./frontend/util.lua:501,522> (46 instructions, 184 bytes at 0x7fed58c0a6c0)
1 param, 12 slots, 0 upvalues, 9 locals, 16 constants, 0 functions
	1	[502]	GETGLOBAL	1 -1	; io
	2	[502]	GETTABLE 	1 1 -2	; "open"
	3	[502]	LOADK    	2 -3	; "/proc/mounts"
	4	[502]	LOADK    	3 -4	; "r"
	5	[502]	CALL     	1 3 2
	6	[503]	TEST     	1 0 1
	7	[503]	JMP      	2	; to 10
	8	[503]	LOADNIL  	2 2
	9	[503]	RETURN   	2 2
	10	[504]	LOADNIL  	2 2
	11	[506]	LOADNIL  	3 3
	12	[507]	NEWTABLE 	4 0 0
	13	[508]	SELF     	5 1 -5	; "read"
	14	[508]	CALL     	5 2 2
	15	[508]	MOVE     	3 5
	16	[509]	EQ       	0 3 -6	; - nil
	17	[509]	JMP      	1	; to 19
	18	[510]	JMP      	24	; to 43
	19	[512]	SELF     	5 3 -7	; "gmatch"
	20	[512]	LOADK    	7 -8	; "%S+"
	21	[512]	CALL     	5 3 4
	22	[512]	JMP      	5	; to 28
	23	[512]	GETGLOBAL	9 -9	; table
	24	[512]	GETTABLE 	9 9 -10	; "insert"
	25	[512]	MOVE     	10 4
	26	[512]	MOVE     	11 8
	27	[512]	CALL     	9 3 1
	28	[512]	TFORLOOP 	5 1
	29	[512]	JMP      	-7	; to 23
	30	[513]	GETGLOBAL	5 -11	; string
	31	[513]	GETTABLE 	5 5 -12	; "match"
	32	[513]	MOVE     	6 0
	33	[513]	GETTABLE 	7 4 -13	; 2
	34	[513]	CALL     	5 3 2
	35	[513]	TEST     	5 0 0
	36	[513]	JMP      	-26	; to 11
	37	[514]	GETTABLE 	2 4 -14	; 3
	38	[515]	GETTABLE 	5 4 -13	; 2
	39	[515]	EQ       	1 5 -15	; - "/"
	40	[515]	JMP      	-30	; to 11
	41	[516]	JMP      	1	; to 43
	42	[518]	JMP      	-32	; to 11
	43	[520]	SELF     	3 1 -16	; "close"
	44	[520]	CALL     	3 2 1
	45	[521]	RETURN   	2 2
	46	[522]	RETURN   	0 1

function <./frontend/util.lua:527,538> (25 instructions, 100 bytes at 0x7fed58c0d110)
1 param, 11 slots, 0 upvalues, 9 locals, 6 constants, 0 functions
	1	[528]	GETGLOBAL	1 -1	; require
	2	[528]	LOADK    	2 -2	; "libs/libkoreader-lfs"
	3	[528]	CALL     	1 2 2
	4	[530]	GETGLOBAL	2 -3	; pcall
	5	[530]	GETTABLE 	3 1 -4	; "dir"
	6	[530]	MOVE     	4 0
	7	[530]	CALL     	2 3 4
	8	[531]	TEST     	2 0 1
	9	[531]	JMP      	1	; to 11
	10	[531]	RETURN   	0 1
	11	[532]	MOVE     	5 3
	12	[532]	MOVE     	6 4
	13	[532]	LOADNIL  	7 7
	14	[532]	JMP      	6	; to 21
	15	[533]	EQ       	1 8 -5	; - "."
	16	[533]	JMP      	4	; to 21
	17	[533]	EQ       	1 8 -6	; - ".."
	18	[533]	JMP      	2	; to 21
	19	[534]	LOADBOOL 	9 0 0
	20	[534]	RETURN   	9 2
	21	[532]	TFORLOOP 	5 1
	22	[535]	JMP      	-8	; to 15
	23	[537]	LOADBOOL 	5 1 0
	24	[537]	RETURN   	5 2
	25	[538]	RETURN   	0 1

function <./frontend/util.lua:543,546> (13 instructions, 52 bytes at 0x7fed58c0d8f0)
1 param, 5 slots, 0 upvalues, 2 locals, 5 constants, 0 functions
	1	[544]	GETGLOBAL	1 -1	; require
	2	[544]	LOADK    	2 -2	; "libs/libkoreader-lfs"
	3	[544]	CALL     	1 2 2
	4	[545]	GETTABLE 	2 1 -3	; "attributes"
	5	[545]	MOVE     	3 0
	6	[545]	LOADK    	4 -4	; "mode"
	7	[545]	CALL     	2 3 2
	8	[545]	EQ       	0 2 -5	; - nil
	9	[545]	JMP      	1	; to 11
	10	[545]	LOADBOOL 	2 0 1
	11	[545]	LOADBOOL 	2 1 0
	12	[545]	RETURN   	2 2
	13	[546]	RETURN   	0 1

function <./frontend/util.lua:553,564> (37 instructions, 148 bytes at 0x7fed58c0daf0)
1 param, 8 slots, 1 upvalue, 4 locals, 11 constants, 0 functions
	1	[554]	SELF     	1 0 -1	; "gsub"
	2	[554]	LOADK    	3 -2	; "/+$"
	3	[554]	LOADK    	4 -3	; ""
	4	[554]	CALL     	1 4 2
	5	[554]	MOVE     	0 1
	6	[555]	GETUPVAL 	1 0	; util
	7	[555]	GETTABLE 	1 1 -4	; "pathExists"
	8	[555]	MOVE     	2 0
	9	[555]	CALL     	1 2 2
	10	[555]	TEST     	1 0 0
	11	[555]	JMP      	2	; to 14
	12	[555]	LOADBOOL 	1 1 0
	13	[555]	RETURN   	1 2
	14	[557]	GETUPVAL 	1 0	; util
	15	[557]	GETTABLE 	1 1 -5	; "makePath"
	16	[557]	GETUPVAL 	2 0	; util
	17	[557]	GETTABLE 	2 2 -6	; "splitFilePathName"
	18	[557]	MOVE     	3 0
	19	[557]	CALL     	2 2 2
	20	[557]	CALL     	1 2 3
	21	[558]	TEST     	1 0 1
	22	[558]	JMP      	7	; to 30
	23	[559]	LOADNIL  	3 3
	24	[559]	MOVE     	4 2
	25	[559]	LOADK    	5 -7	; " (creating "
	26	[559]	MOVE     	6 0
	27	[559]	LOADK    	7 -8	; ")"
	28	[559]	CONCAT   	4 4 7
	29	[559]	RETURN   	3 3
	30	[562]	GETGLOBAL	3 -9	; require
	31	[562]	LOADK    	4 -10	; "libs/libkoreader-lfs"
	32	[562]	CALL     	3 2 2
	33	[563]	GETTABLE 	4 3 -11	; "mkdir"
	34	[563]	MOVE     	5 0
	35	[563]	TAILCALL 	4 2 0
	36	[563]	RETURN   	4 0
	37	[564]	RETURN   	0 1

function <./frontend/util.lua:573,577> (8 instructions, 32 bytes at 0x7fed58c0e0a0)
1 param, 5 slots, 0 upvalues, 1 local, 3 constants, 0 functions
	1	[574]	TEST     	0 0 0
	2	[574]	JMP      	5	; to 8
	3	[575]	SELF     	1 0 -1	; "gsub"
	4	[575]	LOADK    	3 -2	; "[\\,%/,:,%*,%?,%\",%<,%>,%|]"
	5	[575]	LOADK    	4 -3	; "_"
	6	[575]	TAILCALL 	1 4 0
	7	[575]	RETURN   	1 0
	8	[577]	RETURN   	0 1

function <./frontend/util.lua:582,586> (8 instructions, 32 bytes at 0x7fed58c0dfc0)
1 param, 5 slots, 0 upvalues, 1 local, 3 constants, 0 functions
	1	[583]	TEST     	0 0 0
	2	[583]	JMP      	5	; to 8
	3	[584]	SELF     	1 0 -1	; "gsub"
	4	[584]	LOADK    	3 -2	; "%/"
	5	[584]	LOADK    	4 -3	; "_"
	6	[584]	TAILCALL 	1 4 0
	7	[584]	RETURN   	1 0
	8	[586]	RETURN   	0 1

function <./frontend/util.lua:599,634> (64 instructions, 256 bytes at 0x7fed58c0e8c0)
4 params, 12 slots, 3 upvalues, 9 locals, 13 constants, 0 functions
	1	[600]	GETUPVAL 	4 0	; util
	2	[600]	GETTABLE 	4 4 -1	; "splitFileNameSuffix"
	3	[600]	MOVE     	5 0
	4	[600]	CALL     	4 2 3
	5	[601]	GETUPVAL 	6 1	; replaceAllInvalidChars
	6	[602]	LOADNIL  	7 7
	7	[605]	TEST     	2 0 1
	8	[605]	JMP      	1	; to 10
	9	[605]	LOADK    	2 -2	; 240
	10	[606]	TEST     	3 0 1
	11	[606]	JMP      	1	; to 13
	12	[606]	LOADK    	3 -3	; 10
	13	[608]	TEST     	1 0 0
	14	[608]	JMP      	9	; to 24
	15	[609]	GETUPVAL 	8 0	; util
	16	[609]	GETTABLE 	8 8 -4	; "getFilesystemType"
	17	[609]	MOVE     	9 1
	18	[609]	CALL     	8 2 2
	19	[610]	EQ       	1 8 -5	; - "vfat"
	20	[610]	JMP      	3	; to 24
	21	[610]	EQ       	1 8 -6	; - "fuse.fsp"
	22	[610]	JMP      	1	; to 24
	23	[611]	GETUPVAL 	6 2	; replaceSlashChar
	24	[615]	SELF     	8 5 -7	; "len"
	25	[615]	CALL     	8 2 2
	26	[615]	LT       	0 3 8
	27	[615]	JMP      	2	; to 30
	28	[618]	MOVE     	4 0
	29	[619]	LOADNIL  	5 5
	30	[622]	GETUPVAL 	8 0	; util
	31	[622]	GETTABLE 	8 8 -8	; "htmlToPlainTextIfHtml"
	32	[622]	MOVE     	9 4
	33	[622]	CALL     	8 2 2
	34	[622]	MOVE     	4 8
	35	[623]	SELF     	8 4 -9	; "sub"
	36	[623]	LOADK    	10 -10	; 1
	37	[623]	MOVE     	11 2
	38	[623]	CALL     	8 4 2
	39	[623]	MOVE     	4 8
	40	[625]	GETUPVAL 	8 0	; util
	41	[625]	GETTABLE 	8 8 -11	; "fixUtf8"
	42	[625]	MOVE     	9 4
	43	[625]	LOADK    	10 -12	; ""
	44	[625]	CALL     	8 3 2
	45	[625]	MOVE     	4 8
	46	[627]	TEST     	5 0 0
	47	[627]	JMP      	11	; to 59
	48	[627]	EQ       	1 5 -12	; - ""
	49	[627]	JMP      	9	; to 59
	50	[628]	MOVE     	8 6
	51	[628]	MOVE     	9 4
	52	[628]	CALL     	8 2 2
	53	[628]	LOADK    	9 -13	; "."
	54	[628]	MOVE     	10 6
	55	[628]	MOVE     	11 5
	56	[628]	CALL     	10 2 2
	57	[628]	CONCAT   	7 8 10
	58	[628]	JMP      	4	; to 63
	59	[630]	MOVE     	8 6
	60	[630]	MOVE     	9 4
	61	[630]	CALL     	8 2 2
	62	[630]	MOVE     	7 8
	63	[633]	RETURN   	7 2
	64	[634]	RETURN   	0 1

function <./frontend/util.lua:641,645> (31 instructions, 124 bytes at 0x7fed58c0efd0)
1 param, 6 slots, 0 upvalues, 1 local, 9 constants, 0 functions
	1	[642]	EQ       	1 0 -1	; - nil
	2	[642]	JMP      	2	; to 5
	3	[642]	EQ       	0 0 -2	; - ""
	4	[642]	JMP      	3	; to 8
	5	[642]	LOADK    	1 -2	; ""
	6	[642]	LOADK    	2 -2	; ""
	7	[642]	RETURN   	1 3
	8	[643]	GETGLOBAL	1 -3	; string
	9	[643]	GETTABLE 	1 1 -4	; "find"
	10	[643]	MOVE     	2 0
	11	[643]	LOADK    	3 -5	; "/"
	12	[643]	CALL     	1 3 2
	13	[643]	EQ       	0 1 -1	; - nil
	14	[643]	JMP      	3	; to 18
	15	[643]	LOADK    	1 -2	; ""
	16	[643]	MOVE     	2 0
	17	[643]	RETURN   	1 3
	18	[644]	GETGLOBAL	1 -3	; string
	19	[644]	GETTABLE 	1 1 -6	; "gsub"
	20	[644]	MOVE     	2 0
	21	[644]	LOADK    	3 -7	; "(.*/)(.*)"
	22	[644]	LOADK    	4 -8	; "%1"
	23	[644]	CALL     	1 4 2
	24	[644]	GETGLOBAL	2 -3	; string
	25	[644]	GETTABLE 	2 2 -6	; "gsub"
	26	[644]	MOVE     	3 0
	27	[644]	LOADK    	4 -9	; ".*/"
	28	[644]	LOADK    	5 -2	; ""
	29	[644]	CALL     	2 4 0
	30	[644]	RETURN   	1 0
	31	[645]	RETURN   	0 1

function <./frontend/util.lua:650,654> (31 instructions, 124 bytes at 0x7fed58c0f410)
1 param, 6 slots, 0 upvalues, 1 local, 9 constants, 0 functions
	1	[651]	EQ       	1 0 -1	; - nil
	2	[651]	JMP      	2	; to 5
	3	[651]	EQ       	0 0 -2	; - ""
	4	[651]	JMP      	3	; to 8
	5	[651]	LOADK    	1 -2	; ""
	6	[651]	LOADK    	2 -2	; ""
	7	[651]	RETURN   	1 3
	8	[652]	GETGLOBAL	1 -3	; string
	9	[652]	GETTABLE 	1 1 -4	; "find"
	10	[652]	MOVE     	2 0
	11	[652]	LOADK    	3 -5	; "%."
	12	[652]	CALL     	1 3 2
	13	[652]	EQ       	0 1 -1	; - nil
	14	[652]	JMP      	3	; to 18
	15	[652]	MOVE     	1 0
	16	[652]	LOADK    	2 -2	; ""
	17	[652]	RETURN   	1 3
	18	[653]	GETGLOBAL	1 -3	; string
	19	[653]	GETTABLE 	1 1 -6	; "gsub"
	20	[653]	MOVE     	2 0
	21	[653]	LOADK    	3 -7	; "(.*)%.(.*)"
	22	[653]	LOADK    	4 -8	; "%1"
	23	[653]	CALL     	1 4 2
	24	[653]	GETGLOBAL	2 -3	; string
	25	[653]	GETTABLE 	2 2 -6	; "gsub"
	26	[653]	MOVE     	3 0
	27	[653]	LOADK    	4 -9	; ".*%."
	28	[653]	LOADK    	5 -2	; ""
	29	[653]	CALL     	2 4 0
	30	[653]	RETURN   	1 0
	31	[654]	RETURN   	0 1

function <./frontend/util.lua:659,662> (6 instructions, 24 bytes at 0x7fed58c0f510)
1 param, 3 slots, 1 upvalue, 3 locals, 1 constant, 0 functions
	1	[660]	GETUPVAL 	1 0	; util
	2	[660]	GETTABLE 	1 1 -1	; "splitFileNameSuffix"
	3	[660]	MOVE     	2 0
	4	[660]	CALL     	1 2 3
	5	[661]	RETURN   	2 2
	6	[662]	RETURN   	0 1

function <./frontend/util.lua:668,676> (17 instructions, 68 bytes at 0x7fed58c0f690)
1 param, 4 slots, 1 upvalue, 2 locals, 5 constants, 0 functions
	1	[669]	GETGLOBAL	1 -1	; string
	2	[669]	GETTABLE 	1 1 -2	; "lower"
	3	[669]	GETUPVAL 	2 0	; util
	4	[669]	GETTABLE 	2 2 -3	; "getFileNameSuffix"
	5	[669]	MOVE     	3 0
	6	[669]	CALL     	2 2 0
	7	[669]	CALL     	1 0 2
	8	[670]	EQ       	1 1 -4	; - "sh"
	9	[670]	JMP      	2	; to 12
	10	[671]	EQ       	0 1 -5	; - "py"
	11	[671]	JMP      	3	; to 15
	12	[672]	LOADBOOL 	2 1 0
	13	[672]	RETURN   	2 2
	14	[672]	JMP      	2	; to 17
	15	[674]	LOADBOOL 	2 0 0
	16	[674]	RETURN   	2 2
	17	[676]	RETURN   	0 1

function <./frontend/util.lua:682,689> (17 instructions, 68 bytes at 0x7fed58c10080)
1 param, 4 slots, 1 upvalue, 2 locals, 7 constants, 0 functions
	1	[683]	GETGLOBAL	1 -1	; string
	2	[683]	GETTABLE 	1 1 -2	; "lower"
	3	[683]	GETUPVAL 	2 0	; util
	4	[683]	GETTABLE 	2 2 -3	; "getFileNameSuffix"
	5	[683]	MOVE     	3 0
	6	[683]	CALL     	2 2 0
	7	[683]	CALL     	1 0 2
	8	[684]	EQ       	0 1 -4	; - "sh"
	9	[684]	JMP      	3	; to 13
	10	[685]	LOADK    	2 -5	; "shell"
	11	[685]	RETURN   	2 2
	12	[685]	JMP      	4	; to 17
	13	[686]	EQ       	0 1 -6	; - "py"
	14	[686]	JMP      	2	; to 17
	15	[687]	LOADK    	2 -7	; "python"
	16	[687]	RETURN   	2 2
	17	[689]	RETURN   	0 1

function <./frontend/util.lua:695,715> (79 instructions, 316 bytes at 0x7fed58c103b0)
2 params, 9 slots, 2 upvalues, 4 locals, 16 constants, 0 functions
	1	[696]	TEST     	1 0 0
	2	[696]	JMP      	3	; to 6
	3	[696]	LOADK    	2 -1	; "%6.1f"
	4	[696]	TEST     	2 0 1
	5	[696]	JMP      	1	; to 7
	6	[696]	LOADK    	2 -2	; "%.1f"
	7	[697]	TEST     	1 0 0
	8	[697]	JMP      	3	; to 12
	9	[697]	LOADK    	3 -3	; "%6d"
	10	[697]	TEST     	3 0 1
	11	[697]	JMP      	1	; to 13
	12	[697]	LOADK    	3 -4	; "%d"
	13	[698]	GETGLOBAL	4 -5	; tonumber
	14	[698]	MOVE     	5 0
	15	[698]	CALL     	4 2 2
	16	[698]	MOVE     	0 4
	17	[699]	TEST     	0 0 0
	18	[699]	JMP      	5	; to 24
	19	[699]	GETGLOBAL	4 -6	; type
	20	[699]	MOVE     	5 0
	21	[699]	CALL     	4 2 2
	22	[699]	EQ       	1 4 -7	; - "number"
	23	[699]	JMP      	1	; to 25
	24	[699]	RETURN   	0 1
	25	[700]	LT       	0 -8 0	; 1073741824 -
	26	[700]	JMP      	13	; to 40
	27	[702]	GETUPVAL 	4 0	; T
	28	[702]	GETUPVAL 	5 1	; _
	29	[702]	LOADK    	6 -9	; "%1 GB"
	30	[702]	CALL     	5 2 2
	31	[702]	GETGLOBAL	6 -10	; string
	32	[702]	GETTABLE 	6 6 -11	; "format"
	33	[702]	MOVE     	7 2
	34	[702]	DIV      	8 0 -12	; - 1024
	35	[702]	DIV      	8 8 -12	; - 1024
	36	[702]	DIV      	8 8 -12	; - 1024
	37	[702]	CALL     	6 3 0
	38	[702]	TAILCALL 	4 0 0
	39	[702]	RETURN   	4 0
	40	[704]	LT       	0 -13 0	; 1048576 -
	41	[704]	JMP      	12	; to 54
	42	[706]	GETUPVAL 	4 0	; T
	43	[706]	GETUPVAL 	5 1	; _
	44	[706]	LOADK    	6 -14	; "%1 MB"
	45	[706]	CALL     	5 2 2
	46	[706]	GETGLOBAL	6 -10	; string
	47	[706]	GETTABLE 	6 6 -11	; "format"
	48	[706]	MOVE     	7 2
	49	[706]	DIV      	8 0 -12	; - 1024
	50	[706]	DIV      	8 8 -12	; - 1024
	51	[706]	CALL     	6 3 0
	52	[706]	TAILCALL 	4 0 0
	53	[706]	RETURN   	4 0
	54	[708]	LT       	0 -12 0	; 1024 -
	55	[708]	JMP      	12	; to 68
	56	[710]	GETUPVAL 	4 0	; T
	57	[710]	GETUPVAL 	5 1	; _
	58	[710]	LOADK    	6 -15	; "%1 KB"
	59	[710]	CALL     	5 2 2
	60	[710]	GETGLOBAL	6 -10	; string
	61	[710]	GETTABLE 	6 6 -11	; "format"
	62	[710]	MOVE     	7 2
	63	[710]	DIV      	8 0 -12	; - 1024
	64	[710]	CALL     	6 3 0
	65	[710]	TAILCALL 	4 0 0
	66	[710]	RETURN   	4 0
	67	[710]	JMP      	11	; to 79
	68	[713]	GETUPVAL 	4 0	; T
	69	[713]	GETUPVAL 	5 1	; _
	70	[713]	LOADK    	6 -16	; "%1 B"
	71	[713]	CALL     	5 2 2
	72	[713]	GETGLOBAL	6 -10	; string
	73	[713]	GETTABLE 	6 6 -11	; "format"
	74	[713]	MOVE     	7 3
	75	[713]	MOVE     	8 0
	76	[713]	CALL     	6 3 0
	77	[713]	TAILCALL 	4 0 0
	78	[713]	RETURN   	4 0
	79	[715]	RETURN   	0 1

function <./frontend/util.lua:720,725> (19 instructions, 76 bytes at 0x7fed58c0b4e0)
1 param, 6 slots, 0 upvalues, 2 locals, 7 constants, 0 functions
	1	[721]	GETGLOBAL	1 -1	; tostring
	2	[721]	MOVE     	2 0
	3	[721]	CALL     	1 2 2
	4	[722]	SELF     	2 1 -2	; "reverse"
	5	[722]	CALL     	2 2 2
	6	[722]	SELF     	2 2 -3	; "gsub"
	7	[722]	LOADK    	4 -4	; "(%d%d%d)"
	8	[722]	LOADK    	5 -5	; "%1,"
	9	[722]	CALL     	2 4 2
	10	[722]	MOVE     	1 2
	11	[723]	SELF     	2 1 -2	; "reverse"
	12	[723]	CALL     	2 2 2
	13	[723]	SELF     	2 2 -3	; "gsub"
	14	[723]	LOADK    	4 -6	; "^,"
	15	[723]	LOADK    	5 -7	; ""
	16	[723]	CALL     	2 4 2
	17	[723]	MOVE     	1 2
	18	[724]	RETURN   	1 2
	19	[725]	RETURN   	0 1

function <./frontend/util.lua:737,757> (83 instructions, 332 bytes at 0x7fed58c10600)
2 params, 9 slots, 0 upvalues, 4 locals, 15 constants, 0 functions
	1	[738]	LOADK    	2 -1	; 1
	2	[739]	LEN      	3 0
	3	[740]	LE       	0 2 3
	4	[740]	JMP      	77	; to 82
	5	[741]	SELF     	4 0 -2	; "find"
	6	[741]	LOADK    	6 -3	; "^[%z\001-\127]"
	7	[741]	MOVE     	7 2
	8	[741]	CALL     	4 4 2
	9	[741]	TEST     	4 0 0
	10	[741]	JMP      	2	; to 13
	11	[741]	ADD      	2 2 -1	; - 1
	12	[741]	JMP      	-10	; to 3
	13	[742]	SELF     	4 0 -2	; "find"
	14	[742]	LOADK    	6 -4	; "^[\194-\223][\128-\191]"
	15	[742]	MOVE     	7 2
	16	[742]	CALL     	4 4 2
	17	[742]	TEST     	4 0 0
	18	[742]	JMP      	2	; to 21
	19	[742]	ADD      	2 2 -5	; - 2
	20	[742]	JMP      	-18	; to 3
	21	[743]	SELF     	4 0 -2	; "find"
	22	[743]	LOADK    	6 -6	; "^\224[\160-\191][\128-\191]"
	23	[743]	MOVE     	7 2
	24	[743]	CALL     	4 4 2
	25	[744]	TEST     	4 0 1
	26	[744]	JMP      	18	; to 45
	27	[744]	SELF     	4 0 -2	; "find"
	28	[744]	LOADK    	6 -7	; "^[\225-\236][\128-\191][\128-\191]"
	29	[744]	MOVE     	7 2
	30	[744]	CALL     	4 4 2
	31	[745]	TEST     	4 0 1
	32	[745]	JMP      	12	; to 45
	33	[745]	SELF     	4 0 -2	; "find"
	34	[745]	LOADK    	6 -8	; "^\237[\128-\159][\128-\191]"
	35	[745]	MOVE     	7 2
	36	[745]	CALL     	4 4 2
	37	[746]	TEST     	4 0 1
	38	[746]	JMP      	6	; to 45
	39	[746]	SELF     	4 0 -2	; "find"
	40	[746]	LOADK    	6 -9	; "^[\238-\239][\128-\191][\128-\191]"
	41	[746]	MOVE     	7 2
	42	[746]	CALL     	4 4 2
	43	[746]	TEST     	4 0 0
	44	[746]	JMP      	2	; to 47
	45	[746]	ADD      	2 2 -10	; - 3
	46	[746]	JMP      	-44	; to 3
	47	[747]	SELF     	4 0 -2	; "find"
	48	[747]	LOADK    	6 -11	; "^\240[\144-\191][\128-\191][\128-\191]"
	49	[747]	MOVE     	7 2
	50	[747]	CALL     	4 4 2
	51	[748]	TEST     	4 0 1
	52	[748]	JMP      	12	; to 65
	53	[748]	SELF     	4 0 -2	; "find"
	54	[748]	LOADK    	6 -12	; "^[\241-\243][\128-\191][\128-\191][\128-\191]"
	55	[748]	MOVE     	7 2
	56	[748]	CALL     	4 4 2
	57	[749]	TEST     	4 0 1
	58	[749]	JMP      	6	; to 65
	59	[749]	SELF     	4 0 -2	; "find"
	60	[749]	LOADK    	6 -13	; "^\244[\128-\143][\128-\191][\128-\191]"
	61	[749]	MOVE     	7 2
	62	[749]	CALL     	4 4 2
	63	[749]	TEST     	4 0 0
	64	[749]	JMP      	2	; to 67
	65	[749]	ADD      	2 2 -14	; - 4
	66	[749]	JMP      	-64	; to 3
	67	[751]	SELF     	4 0 -15	; "sub"
	68	[751]	LOADK    	6 -1	; 1
	69	[751]	SUB      	7 2 -1	; - 1
	70	[751]	CALL     	4 4 2
	71	[751]	MOVE     	5 1
	72	[751]	SELF     	6 0 -15	; "sub"
	73	[751]	ADD      	8 2 -1	; - 1
	74	[751]	CALL     	6 3 2
	75	[751]	CONCAT   	0 4 6
	76	[752]	LEN      	4 1
	77	[752]	ADD      	2 2 4
	78	[753]	LEN      	4 1
	79	[753]	ADD      	4 3 4
	80	[753]	SUB      	3 4 -1	; - 1
	81	[754]	JMP      	-79	; to 3
	82	[756]	RETURN   	0 2
	83	[757]	RETURN   	0 1

function <./frontend/util.lua:765,771> (18 instructions, 72 bytes at 0x7fed58c10800)
3 params, 11 slots, 1 upvalue, 8 locals, 3 constants, 0 functions
	1	[766]	NEWTABLE 	3 0 0
	2	[767]	GETUPVAL 	4 0	; util
	3	[767]	GETTABLE 	4 4 -1	; "gsplit"
	4	[767]	MOVE     	5 0
	5	[767]	MOVE     	6 1
	6	[767]	LOADBOOL 	7 0 0
	7	[767]	MOVE     	8 2
	8	[767]	CALL     	4 5 4
	9	[767]	JMP      	5	; to 15
	10	[768]	GETGLOBAL	8 -2	; table
	11	[768]	GETTABLE 	8 8 -3	; "insert"
	12	[768]	MOVE     	9 3
	13	[768]	MOVE     	10 7
	14	[768]	CALL     	8 3 1
	15	[767]	TFORLOOP 	4 1
	16	[768]	JMP      	-7	; to 10
	17	[770]	RETURN   	3 2
	18	[771]	RETURN   	0 1

function <./frontend/util.lua:780,807> (110 instructions, 440 bytes at 0x7fed58c0e6c0)
1 param, 10 slots, 3 upvalues, 1 local, 16 constants, 0 functions
	1	[781]	LT       	0 0 -1	; - 128
	2	[781]	JMP      	6	; to 9
	3	[782]	GETGLOBAL	1 -2	; string
	4	[782]	GETTABLE 	1 1 -3	; "char"
	5	[782]	MOVE     	2 0
	6	[782]	TAILCALL 	1 2 0
	7	[782]	RETURN   	1 0
	8	[782]	JMP      	101	; to 110
	9	[783]	LT       	0 0 -4	; - 2048
	10	[783]	JMP      	19	; to 30
	11	[784]	GETGLOBAL	1 -2	; string
	12	[784]	GETTABLE 	1 1 -3	; "char"
	13	[785]	GETUPVAL 	2 0	; bor
	14	[785]	LOADK    	3 -5	; 192
	15	[785]	GETUPVAL 	4 1	; rshift
	16	[785]	MOVE     	5 0
	17	[785]	LOADK    	6 -6	; 6
	18	[785]	CALL     	4 3 0
	19	[785]	CALL     	2 0 2
	20	[786]	GETUPVAL 	3 0	; bor
	21	[786]	LOADK    	4 -1	; 128
	22	[786]	GETUPVAL 	5 2	; band
	23	[786]	MOVE     	6 0
	24	[786]	LOADK    	7 -7	; 63
	25	[786]	CALL     	5 3 0
	26	[786]	CALL     	3 0 0
	27	[784]	TAILCALL 	1 0 0
	28	[787]	RETURN   	1 0
	29	[787]	JMP      	80	; to 110
	30	[788]	LT       	0 0 -8	; - 65536
	31	[788]	JMP      	35	; to 67
	32	[789]	LE       	0 -9 0	; 55296 -
	33	[789]	JMP      	4	; to 38
	34	[789]	LE       	0 0 -10	; - 57343
	35	[789]	JMP      	2	; to 38
	36	[790]	LOADK    	1 -11	; "\239\191\189"
	37	[790]	RETURN   	1 2
	38	[792]	GETGLOBAL	1 -2	; string
	39	[792]	GETTABLE 	1 1 -3	; "char"
	40	[793]	GETUPVAL 	2 0	; bor
	41	[793]	LOADK    	3 -12	; 224
	42	[793]	GETUPVAL 	4 1	; rshift
	43	[793]	MOVE     	5 0
	44	[793]	LOADK    	6 -13	; 12
	45	[793]	CALL     	4 3 0
	46	[793]	CALL     	2 0 2
	47	[794]	GETUPVAL 	3 0	; bor
	48	[794]	LOADK    	4 -1	; 128
	49	[794]	GETUPVAL 	5 2	; band
	50	[794]	GETUPVAL 	6 1	; rshift
	51	[794]	MOVE     	7 0
	52	[794]	LOADK    	8 -6	; 6
	53	[794]	CALL     	6 3 2
	54	[794]	LOADK    	7 -7	; 63
	55	[794]	CALL     	5 3 0
	56	[794]	CALL     	3 0 2
	57	[795]	GETUPVAL 	4 0	; bor
	58	[795]	LOADK    	5 -1	; 128
	59	[795]	GETUPVAL 	6 2	; band
	60	[795]	MOVE     	7 0
	61	[795]	LOADK    	8 -7	; 63
	62	[795]	CALL     	6 3 0
	63	[795]	CALL     	4 0 0
	64	[792]	TAILCALL 	1 0 0
	65	[796]	RETURN   	1 0
	66	[796]	JMP      	43	; to 110
	67	[797]	LT       	0 0 -14	; - 1114112
	68	[797]	JMP      	39	; to 108
	69	[798]	GETGLOBAL	1 -2	; string
	70	[798]	GETTABLE 	1 1 -3	; "char"
	71	[799]	GETUPVAL 	2 0	; bor
	72	[799]	LOADK    	3 -15	; 240
	73	[799]	GETUPVAL 	4 1	; rshift
	74	[799]	MOVE     	5 0
	75	[799]	LOADK    	6 -16	; 18
	76	[799]	CALL     	4 3 0
	77	[799]	CALL     	2 0 2
	78	[800]	GETUPVAL 	3 0	; bor
	79	[800]	LOADK    	4 -1	; 128
	80	[800]	GETUPVAL 	5 2	; band
	81	[800]	GETUPVAL 	6 1	; rshift
	82	[800]	MOVE     	7 0
	83	[800]	LOADK    	8 -13	; 12
	84	[800]	CALL     	6 3 2
	85	[800]	LOADK    	7 -7	; 63
	86	[800]	CALL     	5 3 0
	87	[800]	CALL     	3 0 2
	88	[801]	GETUPVAL 	4 0	; bor
	89	[801]	LOADK    	5 -1	; 128
	90	[801]	GETUPVAL 	6 2	; band
	91	[801]	GETUPVAL 	7 1	; rshift
	92	[801]	MOVE     	8 0
	93	[801]	LOADK    	9 -6	; 6
	94	[801]	CALL     	7 3 2
	95	[801]	LOADK    	8 -7	; 63
	96	[801]	CALL     	6 3 0
	97	[801]	CALL     	4 0 2
	98	[802]	GETUPVAL 	5 0	; bor
	99	[802]	LOADK    	6 -1	; 128
	100	[802]	GETUPVAL 	7 2	; band
	101	[802]	MOVE     	8 0
	102	[802]	LOADK    	9 -7	; 63
	103	[802]	CALL     	7 3 0
	104	[802]	CALL     	5 0 0
	105	[798]	TAILCALL 	1 0 0
	106	[803]	RETURN   	1 0
	107	[803]	JMP      	2	; to 110
	108	[805]	LOADK    	1 -11	; "\239\191\189"
	109	[805]	RETURN   	1 2
	110	[807]	RETURN   	0 1

function <./frontend/util.lua:816,816> (8 instructions, 32 bytes at 0x7fed58c0caa0)
1 param, 4 slots, 1 upvalue, 1 local, 2 constants, 0 functions
	1	[816]	GETUPVAL 	1 0	; util
	2	[816]	GETTABLE 	1 1 -1	; "unicodeCodepointToUtf8"
	3	[816]	GETGLOBAL	2 -2	; tonumber
	4	[816]	MOVE     	3 0
	5	[816]	CALL     	2 2 0
	6	[816]	TAILCALL 	1 0 0
	7	[816]	RETURN   	1 0
	8	[816]	RETURN   	0 1

function <./frontend/util.lua:817,817> (9 instructions, 36 bytes at 0x7fed58c0a840)
1 param, 5 slots, 1 upvalue, 1 local, 3 constants, 0 functions
	1	[817]	GETUPVAL 	1 0	; util
	2	[817]	GETTABLE 	1 1 -1	; "unicodeCodepointToUtf8"
	3	[817]	GETGLOBAL	2 -2	; tonumber
	4	[817]	MOVE     	3 0
	5	[817]	LOADK    	4 -3	; 16
	6	[817]	CALL     	2 3 0
	7	[817]	TAILCALL 	1 0 0
	8	[817]	RETURN   	1 0
	9	[817]	RETURN   	0 1

function <./frontend/util.lua:828,833> (13 instructions, 52 bytes at 0x7fed58c115b0)
1 param, 10 slots, 1 upvalue, 6 locals, 4 constants, 0 functions
	1	[829]	GETGLOBAL	1 -1	; ipairs
	2	[829]	GETUPVAL 	2 0	; HTML_ENTITIES_TO_UTF8
	3	[829]	CALL     	1 2 4
	4	[829]	JMP      	5	; to 10
	5	[830]	SELF     	6 0 -2	; "gsub"
	6	[830]	GETTABLE 	8 5 -3	; 1
	7	[830]	GETTABLE 	9 5 -4	; 2
	8	[830]	CALL     	6 4 2
	9	[830]	MOVE     	0 6
	10	[829]	TFORLOOP 	1 2
	11	[830]	JMP      	-7	; to 5
	12	[832]	RETURN   	0 2
	13	[833]	RETURN   	0 1

function <./frontend/util.lua:843,857> (42 instructions, 168 bytes at 0x7fed58c11810)
1 param, 5 slots, 1 upvalue, 1 local, 11 constants, 0 functions
	1	[845]	SELF     	1 0 -1	; "gsub"
	2	[845]	LOADK    	3 -2	; "%s*<%s*br%s*/?>%s*"
	3	[845]	LOADK    	4 -3	; "\n"
	4	[845]	CALL     	1 4 2
	5	[845]	MOVE     	0 1
	6	[846]	SELF     	1 0 -1	; "gsub"
	7	[846]	LOADK    	3 -4	; "%s*<%s*p%s*>%s*"
	8	[846]	LOADK    	4 -3	; "\n"
	9	[846]	CALL     	1 4 2
	10	[846]	MOVE     	0 1
	11	[847]	SELF     	1 0 -1	; "gsub"
	12	[847]	LOADK    	3 -5	; "%s*</%s*p%s*>%s*"
	13	[847]	LOADK    	4 -3	; "\n"
	14	[847]	CALL     	1 4 2
	15	[847]	MOVE     	0 1
	16	[848]	SELF     	1 0 -1	; "gsub"
	17	[848]	LOADK    	3 -6	; "%s*<%s*p%s*/>%s*"
	18	[848]	LOADK    	4 -3	; "\n"
	19	[848]	CALL     	1 4 2
	20	[848]	MOVE     	0 1
	21	[850]	SELF     	1 0 -1	; "gsub"
	22	[850]	LOADK    	3 -7	; "<[^>]*>"
	23	[850]	LOADK    	4 -8	; ""
	24	[850]	CALL     	1 4 2
	25	[850]	MOVE     	0 1
	26	[852]	GETUPVAL 	1 0	; util
	27	[852]	GETTABLE 	1 1 -9	; "htmlEntitiesToUtf8"
	28	[852]	MOVE     	2 0
	29	[852]	CALL     	1 2 2
	30	[852]	MOVE     	0 1
	31	[854]	SELF     	1 0 -1	; "gsub"
	32	[854]	LOADK    	3 -10	; "^[\n%s]*"
	33	[854]	LOADK    	4 -8	; ""
	34	[854]	CALL     	1 4 2
	35	[854]	MOVE     	0 1
	36	[855]	SELF     	1 0 -1	; "gsub"
	37	[855]	LOADK    	3 -11	; "[\n%s]*$"
	38	[855]	LOADK    	4 -8	; ""
	39	[855]	CALL     	1 4 2
	40	[855]	MOVE     	0 1
	41	[856]	RETURN   	0 2
	42	[857]	RETURN   	0 1

function <./frontend/util.lua:866,895> (42 instructions, 168 bytes at 0x7fed58c11f90)
1 param, 9 slots, 1 upvalue, 5 locals, 8 constants, 0 functions
	1	[867]	LOADBOOL 	1 0 0
	2	[870]	LOADNIL  	2 3
	3	[871]	SELF     	4 0 -1	; "gsub"
	4	[871]	LOADK    	6 -2	; "<%w+.->"
	5	[871]	LOADK    	7 -3	; ""
	6	[871]	CALL     	4 4 3
	7	[871]	MOVE     	3 5
	8	[871]	MOVE     	2 4
	9	[872]	LT       	0 -4 3	; 0 -
	10	[872]	JMP      	2	; to 13
	11	[873]	LOADBOOL 	1 1 0
	12	[873]	JMP      	15	; to 28
	13	[877]	LOADNIL  	4 4
	14	[878]	SELF     	5 0 -1	; "gsub"
	15	[878]	LOADK    	7 -5	; "&lt;%a+&gt;"
	16	[878]	LOADK    	8 -3	; ""
	17	[878]	CALL     	5 4 3
	18	[878]	MOVE     	4 6
	19	[878]	MOVE     	2 5
	20	[879]	LT       	0 -4 4	; 0 -
	21	[879]	JMP      	6	; to 28
	22	[880]	LOADBOOL 	1 1 0
	23	[882]	GETUPVAL 	5 0	; util
	24	[882]	GETTABLE 	5 5 -6	; "htmlEntitiesToUtf8"
	25	[882]	MOVE     	6 0
	26	[882]	CALL     	5 2 2
	27	[882]	MOVE     	0 5
	28	[886]	TEST     	1 0 0
	29	[886]	JMP      	6	; to 36
	30	[887]	GETUPVAL 	4 0	; util
	31	[887]	GETTABLE 	4 4 -7	; "htmlToPlainText"
	32	[887]	MOVE     	5 0
	33	[887]	CALL     	4 2 2
	34	[887]	MOVE     	0 4
	35	[887]	JMP      	5	; to 41
	36	[892]	SELF     	4 0 -1	; "gsub"
	37	[892]	LOADK    	6 -8	; "]]>%s*$"
	38	[892]	LOADK    	7 -3	; ""
	39	[892]	CALL     	4 4 2
	40	[892]	MOVE     	0 4
	41	[894]	RETURN   	0 2
	42	[895]	RETURN   	0 1

function <./frontend/util.lua:900,909> (12 instructions, 48 bytes at 0x7fed58c11ed0)
1 param, 5 slots, 0 upvalues, 1 local, 14 constants, 0 functions
	1	[901]	SELF     	1 0 -1	; "gsub"
	2	[901]	LOADK    	3 -2	; "[}{\">/<'&]"
	3	[901]	NEWTABLE 	4 0 6
	4	[902]	SETTABLE 	4 -3 -4	; "&" "&amp;"
	5	[903]	SETTABLE 	4 -5 -6	; "<" "&lt;"
	6	[904]	SETTABLE 	4 -7 -8	; ">" "&gt;"
	7	[905]	SETTABLE 	4 -9 -10	; "\"" "&quot;"
	8	[906]	SETTABLE 	4 -11 -12	; "'" "&#39;"
	9	[907]	SETTABLE 	4 -13 -14	; "/" "&#47;"
	10	[901]	TAILCALL 	1 4 0
	11	[908]	RETURN   	1 0
	12	[909]	RETURN   	0 1

function <./frontend/util.lua:914,921> (26 instructions, 104 bytes at 0x7fed58c127c0)
1 param, 12 slots, 0 upvalues, 7 locals, 8 constants, 0 functions
	1	[915]	NEWTABLE 	1 0 0
	2	[916]	GETGLOBAL	2 -1	; ipairs
	3	[916]	MOVE     	3 0
	4	[916]	CALL     	2 2 4
	5	[916]	JMP      	12	; to 18
	6	[917]	LOADK    	7 -2	; "'"
	7	[917]	SELF     	8 6 -3	; "gsub"
	8	[917]	LOADK    	10 -2	; "'"
	9	[917]	LOADK    	11 -4	; "'\\''"
	10	[917]	CALL     	8 4 2
	11	[917]	LOADK    	9 -2	; "'"
	12	[917]	CONCAT   	6 7 9
	13	[918]	GETGLOBAL	7 -5	; table
	14	[918]	GETTABLE 	7 7 -6	; "insert"
	15	[918]	MOVE     	8 1
	16	[918]	MOVE     	9 6
	17	[918]	CALL     	7 3 1
	18	[916]	TFORLOOP 	2 2
	19	[918]	JMP      	-14	; to 6
	20	[920]	GETGLOBAL	2 -5	; table
	21	[920]	GETTABLE 	2 2 -7	; "concat"
	22	[920]	MOVE     	3 1
	23	[920]	LOADK    	4 -8	; " "
	24	[920]	TAILCALL 	2 3 0
	25	[920]	RETURN   	2 0
	26	[921]	RETURN   	0 1

function <./frontend/util.lua:925,928> (8 instructions, 32 bytes at 0x7fed58c12be0)
1 param, 6 slots, 0 upvalues, 6 locals, 3 constants, 0 functions
	1	[926]	LEN      	1 0
	2	[927]	LOADK    	2 -1	; 0
	3	[927]	MOVE     	3 1
	4	[927]	LOADK    	4 -2	; 1
	5	[927]	FORPREP  	2 1	; to 7
	6	[927]	SETTABLE 	0 5 -3	; - nil
	7	[927]	FORLOOP  	2 -2	; to 6
	8	[928]	RETURN   	0 1

function <./frontend/util.lua:934,944> (16 instructions, 64 bytes at 0x7fed58c13010)
1 param, 6 slots, 0 upvalues, 2 locals, 5 constants, 1 function
	1	[937]	CLOSURE  	1 0	; 0x7fed58c13530
	2	[938]	EQ       	0 0 -1	; - nil
	3	[938]	JMP      	1	; to 5
	4	[939]	RETURN   	0 1
	5	[941]	SELF     	2 0 -2	; "gsub"
	6	[941]	LOADK    	4 -3	; "\n"
	7	[941]	LOADK    	5 -4	; "\r\n"
	8	[941]	CALL     	2 4 2
	9	[941]	MOVE     	0 2
	10	[942]	SELF     	2 0 -2	; "gsub"
	11	[942]	LOADK    	4 -5	; "([^%w%-%.%_%~%!%*%'%(%)])"
	12	[942]	MOVE     	5 1
	13	[942]	CALL     	2 4 2
	14	[942]	MOVE     	0 2
	15	[943]	RETURN   	0 2
	16	[944]	RETURN   	0 1

function <./frontend/util.lua:935,937> (10 instructions, 40 bytes at 0x7fed58c13530)
1 param, 5 slots, 0 upvalues, 1 local, 4 constants, 0 functions
	1	[936]	GETGLOBAL	1 -1	; string
	2	[936]	GETTABLE 	1 1 -2	; "format"
	3	[936]	LOADK    	2 -3	; "%%%02X"
	4	[936]	GETGLOBAL	3 -1	; string
	5	[936]	GETTABLE 	3 3 -4	; "byte"
	6	[936]	MOVE     	4 0
	7	[936]	CALL     	3 2 0
	8	[936]	TAILCALL 	1 0 0
	9	[936]	RETURN   	1 0
	10	[937]	RETURN   	0 1

function <./frontend/util.lua:950,959> (11 instructions, 44 bytes at 0x7fed58c13900)
1 param, 6 slots, 0 upvalues, 2 locals, 3 constants, 1 function
	1	[953]	CLOSURE  	1 0	; 0x7fed58c13d70
	2	[954]	EQ       	0 0 -1	; - nil
	3	[954]	JMP      	1	; to 5
	4	[955]	RETURN   	0 1
	5	[957]	SELF     	2 0 -2	; "gsub"
	6	[957]	LOADK    	4 -3	; "%%(%x%x)"
	7	[957]	MOVE     	5 1
	8	[957]	CALL     	2 4 2
	9	[957]	MOVE     	0 2
	10	[958]	RETURN   	0 2
	11	[959]	RETURN   	0 1

function <./frontend/util.lua:951,953> (9 instructions, 36 bytes at 0x7fed58c13d70)
1 param, 5 slots, 0 upvalues, 1 local, 4 constants, 0 functions
	1	[952]	GETGLOBAL	1 -1	; string
	2	[952]	GETTABLE 	1 1 -2	; "char"
	3	[952]	GETGLOBAL	2 -3	; tonumber
	4	[952]	MOVE     	3 0
	5	[952]	LOADK    	4 -4	; 16
	6	[952]	CALL     	2 3 0
	7	[952]	TAILCALL 	1 0 0
	8	[952]	RETURN   	1 0
	9	[953]	RETURN   	0 1

function <./frontend/util.lua:964,973> (14 instructions, 56 bytes at 0x7fed58c140f0)
1 param, 7 slots, 0 upvalues, 3 locals, 4 constants, 0 functions
	1	[965]	GETGLOBAL	1 -1	; loadstring
	2	[965]	MOVE     	2 0
	3	[965]	CALL     	1 2 3
	4	[966]	TEST     	1 0 0
	5	[966]	JMP      	2	; to 8
	6	[967]	LOADNIL  	3 3
	7	[967]	RETURN   	3 2
	8	[971]	SELF     	3 2 -2	; "gsub"
	9	[971]	LOADK    	5 -3	; "%[string \".-%\"]:"
	10	[971]	LOADK    	6 -4	; "Line "
	11	[971]	CALL     	3 4 2
	12	[971]	MOVE     	2 3
	13	[972]	RETURN   	2 2
	14	[973]	RETURN   	0 1

function <./frontend/util.lua:981,995> (69 instructions, 276 bytes at 0x7fed58c14680)
2 params, 10 slots, 3 upvalues, 4 locals, 17 constants, 0 functions
	1	[982]	GETUPVAL 	2 0	; dbg
	2	[982]	GETTABLE 	2 2 -1	; "dassert"
	3	[982]	GETGLOBAL	3 -2	; type
	4	[982]	MOVE     	4 0
	5	[982]	CALL     	3 2 2
	6	[982]	EQ       	1 3 -3	; - "string"
	7	[982]	JMP      	1	; to 9
	8	[982]	LOADBOOL 	3 0 1
	9	[982]	LOADBOOL 	3 1 0
	10	[982]	CALL     	2 2 1
	11	[984]	GETGLOBAL	2 -4	; require
	12	[984]	LOADK    	3 -5	; "ui/bidi"
	13	[984]	CALL     	2 2 2
	14	[985]	LOADNIL  	3 3
	15	[986]	SELF     	4 0 -6	; "match"
	16	[986]	LOADK    	6 -7	; "%.tar%.bz2$"
	17	[986]	CALL     	4 3 2
	18	[986]	TEST     	4 0 1
	19	[986]	JMP      	15	; to 35
	20	[986]	SELF     	4 0 -6	; "match"
	21	[986]	LOADK    	6 -8	; "%.tar%.gz$"
	22	[986]	CALL     	4 3 2
	23	[986]	TEST     	4 0 1
	24	[986]	JMP      	10	; to 35
	25	[986]	SELF     	4 0 -6	; "match"
	26	[986]	LOADK    	6 -9	; "%.tar%.lz$"
	27	[986]	CALL     	4 3 2
	28	[986]	TEST     	4 0 1
	29	[986]	JMP      	5	; to 35
	30	[986]	SELF     	4 0 -6	; "match"
	31	[986]	LOADK    	6 -10	; "%.tgz$"
	32	[986]	CALL     	4 3 2
	33	[986]	TEST     	4 0 0
	34	[986]	JMP      	10	; to 45
	35	[987]	GETGLOBAL	4 -11	; os
	36	[987]	GETTABLE 	4 4 -12	; "execute"
	37	[987]	LOADK    	5 -13	; "./tar xf %q -C %q"
	38	[987]	SELF     	5 5 -14	; "format"
	39	[987]	MOVE     	7 0
	40	[987]	MOVE     	8 1
	41	[987]	CALL     	5 4 0
	42	[987]	CALL     	4 0 2
	43	[987]	MOVE     	3 4
	44	[987]	JMP      	10	; to 55
	45	[989]	LOADBOOL 	4 0 0
	46	[989]	GETUPVAL 	5 1	; T
	47	[989]	GETUPVAL 	6 2	; _
	48	[989]	LOADK    	7 -15	; "Couldn't extract archive:\n\n%1\n\nUnrecognized filename extension."
	49	[989]	CALL     	6 2 2
	50	[989]	GETTABLE 	7 2 -16	; "filepath"
	51	[989]	MOVE     	8 0
	52	[989]	CALL     	7 2 0
	53	[989]	CALL     	5 0 0
	54	[989]	RETURN   	4 0
	55	[991]	TEST     	3 0 1
	56	[991]	JMP      	10	; to 67
	57	[992]	LOADBOOL 	4 0 0
	58	[992]	GETUPVAL 	5 1	; T
	59	[992]	GETUPVAL 	6 2	; _
	60	[992]	LOADK    	7 -17	; "Extracting archive failed:\n\n%1"
	61	[992]	GETTABLE 	8 2 -16	; "filepath"
	62	[992]	MOVE     	9 0
	63	[992]	CALL     	8 2 0
	64	[992]	CALL     	6 0 0
	65	[992]	CALL     	5 0 0
	66	[992]	RETURN   	4 0
	67	[994]	LOADBOOL 	4 1 0
	68	[994]	RETURN   	4 2
	69	[995]	RETURN   	0 1

function <./frontend/util.lua:1002,1004> (10 instructions, 40 bytes at 0x7fed58c14ab0)
2 params, 6 slots, 0 upvalues, 2 locals, 2 constants, 0 functions
	1	[1003]	SELF     	2 0 -1	; "sub"
	2	[1003]	LOADK    	4 -2	; 1
	3	[1003]	LEN      	5 1
	4	[1003]	CALL     	2 4 2
	5	[1003]	EQ       	1 2 1
	6	[1003]	JMP      	1	; to 8
	7	[1003]	LOADBOOL 	2 0 1
	8	[1003]	LOADBOOL 	2 1 0
	9	[1003]	RETURN   	2 2
	10	[1004]	RETURN   	0 1

function <./frontend/util.lua:1009,1011> (12 instructions, 48 bytes at 0x7fed58c15490)
2 params, 5 slots, 0 upvalues, 2 locals, 2 constants, 0 functions
	1	[1010]	EQ       	1 1 -1	; - ""
	2	[1010]	JMP      	7	; to 10
	3	[1010]	SELF     	2 0 -2	; "sub"
	4	[1010]	LEN      	4 1
	5	[1010]	UNM      	4 4
	6	[1010]	CALL     	2 3 2
	7	[1010]	EQ       	1 2 1
	8	[1010]	JMP      	1	; to 10
	9	[1010]	LOADBOOL 	2 0 1
	10	[1010]	LOADBOOL 	2 1 0
	11	[1010]	RETURN   	2 2
	12	[1011]	RETURN   	0 1
