-- BYTECODE -- util.lua:20-25
0001    IST          0
0002    JMP      1 => 0004
0003    RET0     0   1
0004 => MOV      2   0
0005    TGETS    1   0   0  ; "gsub"
0006    KSTR     3   1      ; "â[€-ƒ][€-¿]"
0007    KSTR     4   2      ; ""
0008    CALL     1   2   4
0009    MOV      2   1
0010    TGETS    1   1   0  ; "gsub"
0011    KSTR     3   3      ; "^%p+"
0012    KSTR     4   2      ; ""
0013    CALL     1   2   4
0014    MOV      2   1
0015    TGETS    1   1   0  ; "gsub"
0016    KSTR     3   4      ; "%p+$"
0017    KSTR     4   2      ; ""
0018    CALLT    1   4

-- BYTECODE -- util.lua:53-72
0001    KSHORT   0   1
0002 => LOOP     1 => 0060
0003    UGET     1   0      ; str
0004    MOV      2   1
0005    TGETS    1   1   0  ; "find"
0006    UGET     3   1      ; pattern
0007    MOV      4   0
0008    CALL     1   3   4
0009    ISF          1
0010    JMP      3 => 0043
0011    ISF          2
0012    JMP      3 => 0043
0013    ISLT     0   1
0014    JMP      3 => 0020
0015    ISNEV    0   1
0016    JMP      3 => 0029
0017    UGET     3   2      ; capture_empty_entity
0018    ISF          3
0019    JMP      4 => 0029
0020 => GGET     3   1      ; "coroutine"
0021    TGETS    3   3   2  ; "yield"
0022    UGET     4   0      ; str
0023    MOV      5   4
0024    TGETS    4   4   3  ; "sub"
0025    MOV      6   0
0026    SUBVN    7   1   0  ; 1
0027    CALL     4   0   4
0028    CALLM    3   1   0
0029 => UGET     3   3      ; capture
0030    ISF          3
0031    JMP      4 => 0041
0032    GGET     3   1      ; "coroutine"
0033    TGETS    3   3   2  ; "yield"
0034    UGET     4   0      ; str
0035    MOV      5   4
0036    TGETS    4   4   3  ; "sub"
0037    MOV      6   1
0038    MOV      7   2
0039    CALL     4   0   4
0040    CALLM    3   1   0
0041 => ADDVN    0   2   0  ; 1
0042    JMP      3 => 0056
0043 => UGET     3   0      ; str
0044    LEN      3   3
0045    ISGT     0   3
0046    JMP      3 => 0060
0047    GGET     3   1      ; "coroutine"
0048    TGETS    3   3   2  ; "yield"
0049    UGET     4   0      ; str
0050    MOV      5   4
0051    TGETS    4   4   3  ; "sub"
0052    MOV      6   0
0053    CALL     4   0   3
0054    CALLM    3   1   0
0055    JMP      1 => 0060
0056 => UGET     3   0      ; str
0057    LEN      3   3
0058    ISGE     3   0
0059    JMP      3 => 0002
0060 => RET0     0   1

-- BYTECODE -- util.lua:48-73
0001    ISF          1
0002    JMP      4 => 0008
0003    GGET     4   0      ; "tostring"
0004    MOV      5   1
0005    CALL     4   2   2
0006    ISTC     1   4
0007    JMP      5 => 0009
0008 => KSTR     1   1      ; "%s+"
0009 => KSTR     4   2      ; ""
0010    MOV      5   4
0011    TGETS    4   4   3  ; "find"
0012    MOV      6   1
0013    CALL     4   2   3
0014    ISF          4
0015    JMP      5 => 0020
0016    GGET     4   4      ; "error"
0017    KSTR     5   5      ; "pattern matches empty string!"
0018    KSHORT   6   2
0019    CALL     4   1   3
0020 => GGET     4   6      ; "coroutine"
0021    TGETS    4   4   7  ; "wrap"
0022    FNEW     5   8      ; util.lua:53
0023    UCLO     0 => 0024
0024 => CALLT    4   2

-- BYTECODE -- util.lua:83-105
0001    GGET     2   0      ; "tonumber"
0002    MOV      3   0
0003    CALL     2   2   2
0004    MOV      0   2
0005    ISEQN    0   0      ; 0
0006    JMP      2 => 0009
0007    ISEQV    0   0
0008    JMP      2 => 0017
0009 => ISF          1
0010    JMP      2 => 0014
0011    KSTR     2   1      ; "00:00"
0012    RET1     2   2
0013    JMP      2 => 0083
0014 => KSTR     2   2      ; "00:00:00"
0015    RET1     2   2
0016    JMP      2 => 0083
0017 => ISF          1
0018    JMP      2 => 0025
0019    GGET     2   3      ; "require"
0020    KSTR     3   4      ; "optmath"
0021    CALL     2   2   2
0022    TGETS    2   2   5  ; "round"
0023    IST          2
0024    JMP      3 => 0027
0025 => GGET     2   6      ; "math"
0026    TGETS    2   2   7  ; "floor"
0027 => GGET     3   8      ; "string"
0028    TGETS    3   3   9  ; "format"
0029    KSTR     4  10      ; "%02.f"
0030    GGET     5   6      ; "math"
0031    TGETS    5   5   7  ; "floor"
0032    DIVVN    6   0   1  ; 3600
0033    CALL     5   0   2
0034    CALLM    3   2   1
0035    GGET     4   8      ; "string"
0036    TGETS    4   4   9  ; "format"
0037    KSTR     5  10      ; "%02.f"
0038    MOV      6   2
0039    DIVVN    7   0   2  ; 60
0040    MULVN    8   3   2  ; 60
0041    SUBVV    7   7   8
0042    CALL     6   0   2
0043    CALLM    4   2   1
0044    ISNES    4  11      ; "60"
0045    JMP      5 => 0058
0046    GGET     5   8      ; "string"
0047    TGETS    5   5   9  ; "format"
0048    KSTR     6  10      ; "%02.f"
0049    KSHORT   7   0
0050    CALL     5   2   3
0051    MOV      4   5
0052    GGET     5   8      ; "string"
0053    TGETS    5   5   9  ; "format"
0054    KSTR     6  10      ; "%02.f"
0055    ADDVN    7   3   3  ; 1
0056    CALL     5   2   3
0057    MOV      3   5
0058 => ISF          1
0059    JMP      5 => 0065
0060    MOV      5   3
0061    KSTR     6  12      ; ":"
0062    MOV      7   4
0063    CAT      5   5   7
0064    RET1     5   2
0065 => GGET     5   8      ; "string"
0066    TGETS    5   5   9  ; "format"
0067    KSTR     6  10      ; "%02.f"
0068    GGET     7   6      ; "math"
0069    TGETS    7   7   7  ; "floor"
0070    MULVN    8   3   1  ; 3600
0071    SUBVV    8   0   8
0072    MULVN    9   4   2  ; 60
0073    SUBVV    8   8   9
0074    CALL     7   0   2
0075    CALLM    5   2   1
0076    MOV      6   3
0077    KSTR     7  12      ; ":"
0078    MOV      8   4
0079    KSTR     9  12      ; ":"
0080    MOV     10   5
0081    CAT      6   6  10
0082    RET1     6   2
0083 => RET0     0   1

-- BYTECODE -- util.lua:112-195
0001    GGET     3   0      ; "tonumber"
0002    MOV      4   0
0003    CALL     3   2   2
0004    MOV      0   3
0005    ISNEN    0   0      ; 0
0006    JMP      3 => 0033
0007    ISF          1
0008    JMP      3 => 0021
0009    ISF          2
0010    JMP      3 => 0018
0011    UGET     3   0      ; T
0012    UGET     4   1      ; _
0013    KSTR     5   1      ; "%1m"
0014    CALL     4   2   2
0015    KSTR     5   2      ; "0"
0016    CALLT    3   3
0017    JMP      3 => 0243
0018 => KSTR     3   3      ; "0'"
0019    RET1     3   2
0020    JMP      3 => 0243
0021 => ISF          2
0022    JMP      3 => 0030
0023    UGET     3   0      ; T
0024    UGET     4   1      ; _
0025    KSTR     5   4      ; "%1s"
0026    CALL     4   2   2
0027    KSTR     5   2      ; "0"
0028    CALLT    3   3
0029    JMP      3 => 0243
0030 => KSTR     3   5      ; "0''"
0031    RET1     3   2
0032    JMP      3 => 0243
0033 => KSHORT   3  60
0034    ISGE     0   3
0035    JMP      3 => 0094
0036    ISF          1
0037    JMP      3 => 0053
0038    KSHORT   3  30
0039    ISGE     0   3
0040    JMP      3 => 0053
0041    ISF          2
0042    JMP      3 => 0050
0043    UGET     3   0      ; T
0044    UGET     4   1      ; _
0045    KSTR     5   1      ; "%1m"
0046    CALL     4   2   2
0047    KSTR     5   2      ; "0"
0048    CALLT    3   3
0049    JMP      3 => 0243
0050 => KSTR     3   3      ; "0'"
0051    RET1     3   2
0052    JMP      3 => 0243
0053 => ISF          1
0054    JMP      3 => 0070
0055    KSHORT   3  30
0056    ISGT     3   0
0057    JMP      3 => 0070
0058    ISF          2
0059    JMP      3 => 0067
0060    UGET     3   0      ; T
0061    UGET     4   1      ; _
0062    KSTR     5   1      ; "%1m"
0063    CALL     4   2   2
0064    KSTR     5   6      ; "1"
0065    CALLT    3   3
0066    JMP      3 => 0243
0067 => KSTR     3   7      ; "1'"
0068    RET1     3   2
0069    JMP      3 => 0243
0070 => ISF          2
0071    JMP      3 => 0084
0072    UGET     3   0      ; T
0073    UGET     4   1      ; _
0074    KSTR     5   8      ; "%1m%2s"
0075    CALL     4   2   2
0076    KSTR     5   2      ; "0"
0077    GGET     6   9      ; "string"
0078    TGETS    6   6  10  ; "format"
0079    KSTR     7  11      ; "%02.f"
0080    MOV      8   0
0081    CALL     6   0   3
0082    CALLMT   3   2
0083    JMP      3 => 0243
0084 => KSTR     3   3      ; "0'"
0085    GGET     4   9      ; "string"
0086    TGETS    4   4  10  ; "format"
0087    KSTR     5  11      ; "%02.f"
0088    MOV      6   0
0089    CALL     4   2   3
0090    KSTR     5  12      ; "''"
0091    CAT      3   3   5
0092    RET1     3   2
0093    JMP      3 => 0243
0094 => ISF          1
0095    JMP      3 => 0102
0096    GGET     3  13      ; "require"
0097    KSTR     4  14      ; "optmath"
0098    CALL     3   2   2
0099    TGETS    3   3  15  ; "round"
0100    IST          3
0101    JMP      4 => 0104
0102 => GGET     3  16      ; "math"
0103    TGETS    3   3  17  ; "floor"
0104 => GGET     4   9      ; "string"
0105    TGETS    4   4  10  ; "format"
0106    KSTR     5  18      ; "%.f"
0107    GGET     6  16      ; "math"
0108    TGETS    6   6  17  ; "floor"
0109    DIVVN    7   0   1  ; 3600
0110    CALL     6   0   2
0111    CALLM    4   2   1
0112    GGET     5   9      ; "string"
0113    TGETS    5   5  10  ; "format"
0114    KSTR     6  11      ; "%02.f"
0115    MOV      7   3
0116    DIVVN    8   0   2  ; 60
0117    MULVN    9   4   2  ; 60
0118    SUBVV    8   8   9
0119    CALL     7   0   2
0120    CALLM    5   2   1
0121    ISNES    5  19      ; "60"
0122    JMP      6 => 0135
0123    GGET     6   9      ; "string"
0124    TGETS    6   6  10  ; "format"
0125    KSTR     7  11      ; "%02.f"
0126    KSHORT   8   0
0127    CALL     6   2   3
0128    MOV      5   6
0129    GGET     6   9      ; "string"
0130    TGETS    6   6  10  ; "format"
0131    KSTR     7  18      ; "%.f"
0132    ADDVN    8   4   3  ; 1
0133    CALL     6   2   3
0134    MOV      4   6
0135 => ISF          1
0136    JMP      6 => 0167
0137    ISNES    4   2      ; "0"
0138    JMP      6 => 0160
0139    GGET     6   9      ; "string"
0140    TGETS    6   6  10  ; "format"
0141    KSTR     7  18      ; "%.f"
0142    MOV      8   3
0143    DIVVN    9   0   2  ; 60
0144    CALL     8   0   2
0145    CALLM    6   2   1
0146    MOV      5   6
0147    ISF          2
0148    JMP      6 => 0156
0149    UGET     6   0      ; T
0150    UGET     7   1      ; _
0151    KSTR     8   1      ; "%1m"
0152    CALL     7   2   2
0153    MOV      8   5
0154    CALLT    6   3
0155    JMP      6 => 0160
0156 => MOV      6   5
0157    KSTR     7  20      ; "'"
0158    CAT      6   6   7
0159    RET1     6   2
0160 => UGET     6   0      ; T
0161    UGET     7   1      ; _
0162    KSTR     8  21      ; "%1h%2"
0163    CALL     7   2   2
0164    MOV      8   4
0165    MOV      9   5
0166    CALLT    6   4
0167 => GGET     6   9      ; "string"
0168    TGETS    6   6  10  ; "format"
0169    KSTR     7  11      ; "%02.f"
0170    GGET     8  16      ; "math"
0171    TGETS    8   8  17  ; "floor"
0172    MULVN    9   4   1  ; 3600
0173    SUBVV    9   0   9
0174    MULVN   10   5   2  ; 60
0175    SUBVV    9   9  10
0176    CALL     8   0   2
0177    CALLM    6   2   1
0178    ISNES    4   2      ; "0"
0179    JMP      7 => 0204
0180    GGET     7   9      ; "string"
0181    TGETS    7   7  10  ; "format"
0182    KSTR     8  18      ; "%.f"
0183    MOV      9   3
0184    DIVVN   10   0   2  ; 60
0185    CALL     9   0   2
0186    CALLM    7   2   1
0187    MOV      5   7
0188    ISF          2
0189    JMP      7 => 0198
0190    UGET     7   0      ; T
0191    UGET     8   1      ; _
0192    KSTR     9   8      ; "%1m%2s"
0193    CALL     8   2   2
0194    MOV      9   5
0195    MOV     10   6
0196    CALLT    7   4
0197    JMP      7 => 0204
0198 => MOV      7   5
0199    KSTR     8  20      ; "'"
0200    MOV      9   6
0201    KSTR    10  12      ; "''"
0202    CAT      7   7  10
0203    RET1     7   2
0204 => ISF          2
0205    JMP      7 => 0225
0206    ISNES    6  22      ; "00"
0207    JMP      7 => 0216
0208    UGET     7   0      ; T
0209    UGET     8   1      ; _
0210    KSTR     9  23      ; "%1h%2m"
0211    CALL     8   2   2
0212    MOV      9   4
0213    MOV     10   5
0214    CALLT    7   4
0215    JMP      7 => 0243
0216 => UGET     7   0      ; T
0217    UGET     8   1      ; _
0218    KSTR     9  24      ; "%1h%2m%3s"
0219    CALL     8   2   2
0220    MOV      9   4
0221    MOV     10   5
0222    MOV     11   6
0223    CALLT    7   5
0224    JMP      7 => 0243
0225 => ISNES    6  22      ; "00"
0226    JMP      7 => 0235
0227    UGET     7   0      ; T
0228    UGET     8   1      ; _
0229    KSTR     9  25      ; "%1h%2'"
0230    CALL     8   2   2
0231    MOV      9   4
0232    MOV     10   5
0233    CALLT    7   4
0234    JMP      7 => 0243
0235 => UGET     7   0      ; T
0236    UGET     8   1      ; _
0237    KSTR     9  26      ; "%1h%2'%3''"
0238    CALL     8   2   2
0239    MOV      9   4
0240    MOV     10   5
0241    MOV     11   6
0242    CALLT    7   5
0243 => RET0     0   1

-- BYTECODE -- util.lua:207-236
0001    ISNEV    0   1
0002    JMP      3 => 0005
0003    KPRI     3   2
0004    RET1     3   2
0005 => GGET     3   0      ; "type"
0006    MOV      4   0
0007    CALL     3   2   2
0008    GGET     4   0      ; "type"
0009    MOV      5   1
0010    CALL     4   2   2
0011    ISEQV    3   4
0012    JMP      5 => 0015
0013    KPRI     5   1
0014    RET1     5   2
0015 => ISEQS    3   1      ; "table"
0016    JMP      5 => 0019
0017    KPRI     5   1
0018    RET1     5   2
0019 => IST          2
0020    JMP      5 => 0035
0021    GGET     5   2      ; "getmetatable"
0022    MOV      6   0
0023    CALL     5   2   2
0024    ISF          5
0025    JMP      6 => 0035
0026    TGETS    6   5   3  ; "__eq"
0027    ISF          6
0028    JMP      7 => 0035
0029    ISEQV    0   1
0030    JMP      6 => 0033
0031    KPRI     6   1
0032    JMP      7 => 0034
0033 => KPRI     6   2
0034 => RET1     6   2
0035 => TNEW     5   0
0036    GGET     6   4      ; "pairs"
0037    MOV      7   0
0038    CALL     6   4   2
0039    ISNEXT   9 => 0055
0040 => TGETV   11   1   9
0041    ISEQP   11   0
0042    JMP     12 => 0051
0043    UGET    12   0      ; util
0044    TGETS   12  12   5  ; "tableEquals"
0045    MOV     13  10
0046    MOV     14  11
0047    MOV     15   2
0048    CALL    12   2   4
0049    ISNEP   12   1
0050    JMP     12 => 0053
0051 => KPRI    12   1
0052    RET1    12   2
0053 => KPRI    12   2
0054    TSETV   12   5   9
0055 => ITERN    9   3   3
0056    ITERL    9 => 0040
0057    GGET     6   4      ; "pairs"
0058    MOV      7   1
0059    CALL     6   4   2
0060    ISNEXT   9 => 0066
0061 => TGETV   11   5   9
0062    IST         11
0063    JMP     11 => 0066
0064    KPRI    11   1
0065    RET1    11   2
0066 => ITERN    9   3   3
0067    ITERL    9 => 0061
0068    KPRI     6   2
0069    RET1     6   2

-- BYTECODE -- util.lua:245-263
0001    IST          1
0002    JMP      2 => 0004
0003    TNEW     1   0
0004 => ISNEP    0   0
0005    JMP      2 => 0008
0006    KPRI     2   0
0007    RET1     2   2
0008 => TGETV    2   1   0
0009    ISF          2
0010    JMP      3 => 0013
0011    TGETV    2   1   0
0012    RET1     2   2
0013 => KPRI     2   0
0014    GGET     3   0      ; "type"
0015    MOV      4   0
0016    CALL     3   2   2
0017    ISNES    3   1      ; "table"
0018    JMP      3 => 0049
0019    TNEW     2   0
0020    TSETV    2   1   0
0021    GGET     3   2      ; "next"
0022    MOV      4   0
0023    KPRI     5   0
0024    ISNEXT   6 => 0036
0025 => UGET     8   0      ; util
0026    TGETS    8   8   3  ; "tableDeepCopy"
0027    MOV      9   6
0028    MOV     10   1
0029    CALL     8   2   3
0030    UGET     9   0      ; util
0031    TGETS    9   9   3  ; "tableDeepCopy"
0032    MOV     10   7
0033    MOV     11   1
0034    CALL     9   2   3
0035    TSETV    9   2   8
0036 => ITERN    6   3   3
0037    ITERL    6 => 0025
0038    GGET     3   4      ; "setmetatable"
0039    MOV      4   2
0040    UGET     5   0      ; util
0041    TGETS    5   5   3  ; "tableDeepCopy"
0042    GGET     6   5      ; "getmetatable"
0043    MOV      7   0
0044    CALL     6   2   2
0045    MOV      7   1
0046    CALL     5   0   3
0047    CALLM    3   1   1
0048    JMP      3 => 0050
0049 => MOV      2   0
0050 => RET1     2   2

-- BYTECODE -- util.lua:268-272
0001    KSHORT   1   0
0002    GGET     2   0      ; "pairs"
0003    MOV      3   0
0004    CALL     2   4   2
0005    ISNEXT   5 => 0007
0006 => ADDVN    1   1   0  ; 1
0007 => ITERN    5   2   3
0008    ITERL    5 => 0006
0009    RET1     1   2

-- BYTECODE -- util.lua:277-281
0001    GGET     2   0      ; "ipairs"
0002    MOV      3   1
0003    CALL     2   4   2
0004    JMP      5 => 0010
0005 => GGET     7   1      ; "table"
0006    TGETS    7   7   2  ; "insert"
0007    MOV      8   0
0008    MOV      9   6
0009    CALL     7   1   3
0010 => ITERC    5   3   3
0011    ITERL    5 => 0005
0012    RET0     0   1

-- BYTECODE -- util.lua:285-292
0001    KSHORT   1   1
0002    LEN      2   0
0003 => ISGE     1   2
0004    JMP      3 => 0013
0005    LOOP     3 => 0013
0006    TGETV    3   0   2
0007    TGETV    4   0   1
0008    TSETV    4   0   2
0009    TSETV    3   0   1
0010    ADDVN    1   1   0  ; 1
0011    SUBVN    2   2   0  ; 1
0012    JMP      3 => 0003
0013 => RET0     0   1

-- BYTECODE -- util.lua:298-302
0001    GGET     2   0      ; "pairs"
0002    MOV      3   1
0003    CALL     2   4   2
0004    ISNEXT   5 => 0006
0005 => TSETV    6   0   5
0006 => ITERN    5   3   3
0007    ITERL    5 => 0005
0008    RET0     0   1

-- BYTECODE -- util.lua:315-318
0001    MOV      3   0
0002    TGETS    2   0   0  ; "match"
0003    KSTR     4   1      ; ".*"
0004    MOV      5   1
0005    KSTR     6   2      ; "()"
0006    CAT      4   4   6
0007    CALL     2   2   3
0008    ISNEP    2   0
0009    JMP      3 => 0013
0010    KSHORT   3  -1
0011    RET1     3   2
0012    JMP      3 => 0015
0013 => SUBVN    3   2   0  ; 1
0014    RET1     3   2
0015 => RET0     0   1

-- BYTECODE -- util.lua:324-324
0001    LEN      1   0
0002    KSHORT   2   1
0003    ISGE     2   1
0004    JMP      1 => 0009
0005    MOV      2   0
0006    TGETS    1   0   0  ; "reverse"
0007    CALL     1   2   2
0008    JMP      2 => 0012
0009 => KPRI     1   1
0010    JMP      2 => 0012
0011    KPRI     1   2
0012 => RET1     1   2

-- BYTECODE -- util.lua:323-326
0001    MOV      2   0
0002    TGETS    1   0   0  ; "gsub"
0003    KSTR     3   1      ; "[%z\001-\127Â-ô][€-¿]*"
0004    FNEW     4   2      ; util.lua:324
0005    CALL     1   2   4
0006    MOV      0   1
0007    MOV      2   0
0008    TGETS    1   0   3  ; "reverse"
0009    UCLO     0 => 0010
0010 => CALLT    1   2

-- BYTECODE -- util.lua:331-382
0001    TNEW     1   0
0002    ISEQP    0   0
0003    JMP      2 => 0080
0004    KSHORT   2   0
0005    KNIL     3   5
0006    GGET     6   0      ; "string"
0007    TGETS    6   6   1  ; "gmatch"
0008    MOV      7   0
0009    KSTR     8   2      ; "([%z\001-\127Â-ô][€-¿]*)"
0010    CALL     6   4   3
0011    JMP      9 => 0078
0012 => UGET    10   0      ; BaseUtil
0013    TGETS   10  10   3  ; "utf8charcode"
0014    MOV     11   9
0015    CALL    10   2   2
0016    MOV      3  10
0017    ISF          2
0018    JMP     10 => 0077
0019    ISF          3
0020    JMP     10 => 0037
0021    KNUM    10   0      ; 55296
0022    ISGT    10   3
0023    JMP     10 => 0037
0024    KNUM    10   1      ; 56319
0025    ISGT     3  10
0026    JMP     10 => 0037
0027    ISF          4
0028    JMP     10 => 0034
0029    GGET    10   4      ; "table"
0030    TGETS   10  10   5  ; "insert"
0031    MOV     11   1
0032    MOV     12   5
0033    CALL    10   1   3
0034 => MOV      4   3
0035    MOV      5   9
0036    JMP     10 => 0077
0037 => ISF          4
0038    JMP     10 => 0064
0039    ISF          3
0040    JMP     10 => 0064
0041    KNUM    10   2      ; 56320
0042    ISGT    10   3
0043    JMP     10 => 0064
0044    KNUM    10   3      ; 57343
0045    ISGT     3  10
0046    JMP     10 => 0064
0047    UGET    10   1      ; lshift
0048    SUBVN   11   4   0  ; 55296
0049    KSHORT  12  10
0050    CALL    10   2   3
0051    SUBVN   11   3   2  ; 56320
0052    ADDVV   10  10  11
0053    ADDVN    3  10   4  ; 65536
0054    GGET    10   4      ; "table"
0055    TGETS   10  10   5  ; "insert"
0056    MOV     11   1
0057    UGET    12   2      ; util
0058    TGETS   12  12   6  ; "unicodeCodepointToUtf8"
0059    MOV     13   3
0060    CALL    12   0   2
0061    CALLM   10   1   1
0062    KPRI     4   0
0063    JMP     10 => 0077
0064 => ISF          4
0065    JMP     10 => 0071
0066    GGET    10   4      ; "table"
0067    TGETS   10  10   5  ; "insert"
0068    MOV     11   1
0069    MOV     12   5
0070    CALL    10   1   3
0071 => KPRI     4   0
0072    GGET    10   4      ; "table"
0073    TGETS   10  10   5  ; "insert"
0074    MOV     11   1
0075    MOV     12   9
0076    CALL    10   1   3
0077 => MOV      2   3
0078 => ITERC    9   2   3
0079    ITERL    9 => 0012
0080 => RET1     1   2

-- BYTECODE -- util.lua:387-389
0001    GGET     1   0      ; "string"
0002    TGETS    1   1   1  ; "match"
0003    MOV      2   0
0004    KSTR     3   2      ; "[ä-ê][€-¿]."
0005    CALL     1   2   3
0006    ISEQV    1   0
0007    JMP      1 => 0010
0008    KPRI     1   1
0009    JMP      2 => 0011
0010 => KPRI     1   2
0011 => RET1     1   2

-- BYTECODE -- util.lua:394-396
0001    GGET     1   0      ; "string"
0002    TGETS    1   1   1  ; "match"
0003    MOV      2   0
0004    KSTR     3   2      ; "[ä-ê][€-¿]."
0005    CALL     1   2   3
0006    ISNEP    1   0
0007    JMP      1 => 0010
0008    KPRI     1   1
0009    JMP      2 => 0011
0010 => KPRI     1   2
0011 => RET1     1   2

-- BYTECODE -- util.lua:401-415
0001    TNEW     1   0
0002    UGET     2   0      ; util
0003    TGETS    2   2   0  ; "gsplit"
0004    MOV      3   0
0005    KSTR     4   1      ; "[%s%p]+"
0006    KPRI     5   2
0007    CALL     2   4   4
0008    JMP      5 => 0035
0009 => UGET     6   0      ; util
0010    TGETS    6   6   2  ; "hasCJKChar"
0011    MOV      7   5
0012    CALL     6   2   2
0013    ISF          6
0014    JMP      7 => 0030
0015    UGET     6   0      ; util
0016    TGETS    6   6   0  ; "gsplit"
0017    MOV      7   5
0018    KSTR     8   3      ; "[ä-êÀ-ÿ][€-¿]+"
0019    KPRI     9   2
0020    CALL     6   4   4
0021    JMP      9 => 0027
0022 => GGET    10   4      ; "table"
0023    TGETS   10  10   5  ; "insert"
0024    MOV     11   1
0025    MOV     12   9
0026    CALL    10   1   3
0027 => ITERC    9   2   3
0028    ITERL    9 => 0022
0029    JMP      6 => 0035
0030 => GGET     6   4      ; "table"
0031    TGETS    6   6   5  ; "insert"
0032    MOV      7   1
0033    MOV      8   5
0034    CALL     6   1   3
0035 => ITERC    5   2   3
0036    ITERL    5 => 0009
0037    RET1     1   2

-- BYTECODE -- util.lua:462-494
0001    UGET     3   0      ; util
0002    TGETS    3   3   0  ; "isCJKChar"
0003    MOV      4   0
0004    CALL     3   2   2
0005    ISF          3
0006    JMP      4 => 0050
0007    UGET     3   1      ; cjk_non_splittable
0008    MOV      4   3
0009    TGETS    3   3   1  ; "find"
0010    MOV      5   0
0011    KSHORT   6   1
0012    KPRI     7   2
0013    CALL     3   2   5
0014    ISF          3
0015    JMP      4 => 0019
0016    KPRI     3   1
0017    RET1     3   2
0018    JMP      3 => 0082
0019 => ISF          1
0020    JMP      3 => 0033
0021    UGET     3   2      ; cjk_non_splittable_tailers
0022    MOV      4   3
0023    TGETS    3   3   1  ; "find"
0024    MOV      5   1
0025    KSHORT   6   1
0026    KPRI     7   2
0027    CALL     3   2   5
0028    ISF          3
0029    JMP      4 => 0033
0030    KPRI     3   1
0031    RET1     3   2
0032    JMP      3 => 0082
0033 => ISF          2
0034    JMP      3 => 0047
0035    UGET     3   3      ; cjk_non_splittable_leaders
0036    MOV      4   3
0037    TGETS    3   3   1  ; "find"
0038    MOV      5   2
0039    KSHORT   6   1
0040    KPRI     7   2
0041    CALL     3   2   5
0042    ISF          3
0043    JMP      4 => 0047
0044    KPRI     3   1
0045    RET1     3   2
0046    JMP      3 => 0082
0047 => KPRI     3   2
0048    RET1     3   2
0049    JMP      3 => 0082
0050 => ISNES    0   2      ; " "
0051    JMP      3 => 0082
0052    ISF          1
0053    JMP      3 => 0066
0054    UGET     3   4      ; non_splittable_space_tailers
0055    MOV      4   3
0056    TGETS    3   3   1  ; "find"
0057    MOV      5   1
0058    KSHORT   6   1
0059    KPRI     7   2
0060    CALL     3   2   5
0061    ISF          3
0062    JMP      4 => 0066
0063    KPRI     3   1
0064    RET1     3   2
0065    JMP      3 => 0082
0066 => ISF          2
0067    JMP      3 => 0080
0068    UGET     3   5      ; non_splittable_space_leaders
0069    MOV      4   3
0070    TGETS    3   3   1  ; "find"
0071    MOV      5   2
0072    KSHORT   6   1
0073    KPRI     7   2
0074    CALL     3   2   5
0075    ISF          3
0076    JMP      4 => 0080
0077    KPRI     3   1
0078    RET1     3   2
0079    JMP      3 => 0082
0080 => KPRI     3   2
0081    RET1     3   2
0082 => KPRI     3   1
0083    RET1     3   2

-- BYTECODE -- util.lua:501-522
0001    GGET     1   0      ; "io"
0002    TGETS    1   1   1  ; "open"
0003    KSTR     2   2      ; "/proc/mounts"
0004    KSTR     3   3      ; "r"
0005    CALL     1   2   3
0006    IST          1
0007    JMP      2 => 0010
0008    KPRI     2   0
0009    RET1     2   2
0010 => KPRI     2   0
0011 => LOOP     3 => 0046
0012    KPRI     3   0
0013    TNEW     4   0
0014    MOV      6   1
0015    TGETS    5   1   4  ; "read"
0016    CALL     5   2   2
0017    MOV      3   5
0018    ISNEP    3   0
0019    JMP      5 => 0021
0020    JMP      3 => 0046
0021 => MOV      6   3
0022    TGETS    5   3   5  ; "gmatch"
0023    KSTR     7   6      ; "%S+"
0024    CALL     5   4   3
0025    JMP      8 => 0031
0026 => GGET     9   7      ; "table"
0027    TGETS    9   9   8  ; "insert"
0028    MOV     10   4
0029    MOV     11   8
0030    CALL     9   1   3
0031 => ITERC    8   2   3
0032    ITERL    8 => 0026
0033    GGET     5   9      ; "string"
0034    TGETS    5   5  10  ; "match"
0035    MOV      6   0
0036    TGETB    7   4   2
0037    CALL     5   2   3
0038    ISF          5
0039    JMP      6 => 0011
0040    TGETB    2   4   3
0041    TGETB    5   4   2
0042    ISEQS    5  11      ; "/"
0043    JMP      5 => 0011
0044    JMP      3 => 0046
0045    JMP      3 => 0011
0046 => MOV      4   1
0047    TGETS    3   1  12  ; "close"
0048    CALL     3   1   2
0049    RET1     2   2

-- BYTECODE -- util.lua:527-538
0001    GGET     1   0      ; "require"
0002    KSTR     2   1      ; "libs/libkoreader-lfs"
0003    CALL     1   2   2
0004    GGET     2   2      ; "pcall"
0005    TGETS    3   1   3  ; "dir"
0006    MOV      4   0
0007    CALL     2   4   3
0008    IST          2
0009    JMP      5 => 0011
0010    RET0     0   1
0011 => MOV      5   3
0012    MOV      6   4
0013    KPRI     7   0
0014    JMP      8 => 0021
0015 => ISEQS    8   4      ; "."
0016    JMP      9 => 0021
0017    ISEQS    8   5      ; ".."
0018    JMP      9 => 0021
0019    KPRI     9   1
0020    RET1     9   2
0021 => ITERC    8   2   3
0022    ITERL    8 => 0015
0023    KPRI     5   2
0024    RET1     5   2

-- BYTECODE -- util.lua:543-546
0001    GGET     1   0      ; "require"
0002    KSTR     2   1      ; "libs/libkoreader-lfs"
0003    CALL     1   2   2
0004    TGETS    2   1   2  ; "attributes"
0005    MOV      3   0
0006    KSTR     4   3      ; "mode"
0007    CALL     2   2   3
0008    ISNEP    2   0
0009    JMP      2 => 0012
0010    KPRI     2   1
0011    JMP      3 => 0013
0012 => KPRI     2   2
0013 => RET1     2   2

-- BYTECODE -- util.lua:553-564
0001    MOV      2   0
0002    TGETS    1   0   0  ; "gsub"
0003    KSTR     3   1      ; "/+$"
0004    KSTR     4   2      ; ""
0005    CALL     1   2   4
0006    MOV      0   1
0007    UGET     1   0      ; util
0008    TGETS    1   1   3  ; "pathExists"
0009    MOV      2   0
0010    CALL     1   2   2
0011    ISF          1
0012    JMP      2 => 0015
0013    KPRI     1   2
0014    RET1     1   2
0015 => UGET     1   0      ; util
0016    TGETS    1   1   4  ; "makePath"
0017    UGET     2   0      ; util
0018    TGETS    2   2   5  ; "splitFilePathName"
0019    MOV      3   0
0020    CALL     2   2   2
0021    CALL     1   3   2
0022    IST          1
0023    JMP      3 => 0031
0024    KPRI     3   0
0025    MOV      4   2
0026    KSTR     5   6      ; " (creating "
0027    MOV      6   0
0028    KSTR     7   7      ; ")"
0029    CAT      4   4   7
0030    RET      3   3
0031 => GGET     3   8      ; "require"
0032    KSTR     4   9      ; "libs/libkoreader-lfs"
0033    CALL     3   2   2
0034    TGETS    4   3  10  ; "mkdir"
0035    MOV      5   0
0036    CALLT    4   2

-- BYTECODE -- util.lua:573-577
0001    ISF          0
0002    JMP      1 => 0008
0003    MOV      2   0
0004    TGETS    1   0   0  ; "gsub"
0005    KSTR     3   1      ; "[\,%/,:,%*,%?,%",%<,%>,%|]"
0006    KSTR     4   2      ; "_"
0007    CALLT    1   4
0008 => RET0     0   1

-- BYTECODE -- util.lua:582-586
0001    ISF          0
0002    JMP      1 => 0008
0003    MOV      2   0
0004    TGETS    1   0   0  ; "gsub"
0005    KSTR     3   1      ; "%/"
0006    KSTR     4   2      ; "_"
0007    CALLT    1   4
0008 => RET0     0   1

-- BYTECODE -- util.lua:599-634
0001    UGET     4   0      ; util
0002    TGETS    4   4   0  ; "splitFileNameSuffix"
0003    MOV      5   0
0004    CALL     4   3   2
0005    UGET     6   1      ; replaceAllInvalidChars
0006    KPRI     7   0
0007    IST          2
0008    JMP      8 => 0010
0009    KSHORT   2 240
0010 => IST          3
0011    JMP      8 => 0013
0012    KSHORT   3  10
0013 => ISF          1
0014    JMP      8 => 0024
0015    UGET     8   0      ; util
0016    TGETS    8   8   1  ; "getFilesystemType"
0017    MOV      9   1
0018    CALL     8   2   2
0019    ISEQS    8   2      ; "vfat"
0020    JMP      9 => 0024
0021    ISEQS    8   3      ; "fuse.fsp"
0022    JMP      9 => 0024
0023    UGET     6   2      ; replaceSlashChar
0024 => MOV      9   5
0025    TGETS    8   5   4  ; "len"
0026    CALL     8   2   2
0027    ISGE     3   8
0028    JMP      8 => 0031
0029    MOV      4   0
0030    KPRI     5   0
0031 => UGET     8   0      ; util
0032    TGETS    8   8   5  ; "htmlToPlainTextIfHtml"
0033    MOV      9   4
0034    CALL     8   2   2
0035    MOV      4   8
0036    MOV      9   4
0037    TGETS    8   4   6  ; "sub"
0038    KSHORT  10   1
0039    MOV     11   2
0040    CALL     8   2   4
0041    MOV      4   8
0042    UGET     8   0      ; util
0043    TGETS    8   8   7  ; "fixUtf8"
0044    MOV      9   4
0045    KSTR    10   8      ; ""
0046    CALL     8   2   3
0047    MOV      4   8
0048    ISF          5
0049    JMP      8 => 0061
0050    ISEQS    5   8      ; ""
0051    JMP      8 => 0061
0052    MOV      8   6
0053    MOV      9   4
0054    CALL     8   2   2
0055    KSTR     9   9      ; "."
0056    MOV     10   6
0057    MOV     11   5
0058    CALL    10   2   2
0059    CAT      7   8  10
0060    JMP      8 => 0065
0061 => MOV      8   6
0062    MOV      9   4
0063    CALL     8   2   2
0064    MOV      7   8
0065 => RET1     7   2

-- BYTECODE -- util.lua:641-645
0001    ISEQP    0   0
0002    JMP      1 => 0005
0003    ISNES    0   0      ; ""
0004    JMP      1 => 0008
0005 => KSTR     1   0      ; ""
0006    KSTR     2   0      ; ""
0007    RET      1   3
0008 => GGET     1   1      ; "string"
0009    TGETS    1   1   2  ; "find"
0010    MOV      2   0
0011    KSTR     3   3      ; "/"
0012    CALL     1   2   3
0013    ISNEP    1   0
0014    JMP      1 => 0018
0015    KSTR     1   0      ; ""
0016    MOV      2   0
0017    RET      1   3
0018 => GGET     1   1      ; "string"
0019    TGETS    1   1   4  ; "gsub"
0020    MOV      2   0
0021    KSTR     3   5      ; "(.*/)(.*)"
0022    KSTR     4   6      ; "%1"
0023    CALL     1   2   4
0024    GGET     2   1      ; "string"
0025    TGETS    2   2   4  ; "gsub"
0026    MOV      3   0
0027    KSTR     4   7      ; ".*/"
0028    KSTR     5   0      ; ""
0029    CALL     2   0   4
0030    RETM     1   1

-- BYTECODE -- util.lua:650-654
0001    ISEQP    0   0
0002    JMP      1 => 0005
0003    ISNES    0   0      ; ""
0004    JMP      1 => 0008
0005 => KSTR     1   0      ; ""
0006    KSTR     2   0      ; ""
0007    RET      1   3
0008 => GGET     1   1      ; "string"
0009    TGETS    1   1   2  ; "find"
0010    MOV      2   0
0011    KSTR     3   3      ; "%."
0012    CALL     1   2   3
0013    ISNEP    1   0
0014    JMP      1 => 0018
0015    MOV      1   0
0016    KSTR     2   0      ; ""
0017    RET      1   3
0018 => GGET     1   1      ; "string"
0019    TGETS    1   1   4  ; "gsub"
0020    MOV      2   0
0021    KSTR     3   5      ; "(.*)%.(.*)"
0022    KSTR     4   6      ; "%1"
0023    CALL     1   2   4
0024    GGET     2   1      ; "string"
0025    TGETS    2   2   4  ; "gsub"
0026    MOV      3   0
0027    KSTR     4   7      ; ".*%."
0028    KSTR     5   0      ; ""
0029    CALL     2   0   4
0030    RETM     1   1

-- BYTECODE -- util.lua:659-662
0001    UGET     1   0      ; util
0002    TGETS    1   1   0  ; "splitFileNameSuffix"
0003    MOV      2   0
0004    CALL     1   3   2
0005    RET1     2   2

-- BYTECODE -- util.lua:668-676
0001    GGET     1   0      ; "string"
0002    TGETS    1   1   1  ; "lower"
0003    UGET     2   0      ; util
0004    TGETS    2   2   2  ; "getFileNameSuffix"
0005    MOV      3   0
0006    CALL     2   0   2
0007    CALLM    1   2   0
0008    ISEQS    1   3      ; "sh"
0009    JMP      2 => 0012
0010    ISNES    1   4      ; "py"
0011    JMP      2 => 0015
0012 => KPRI     2   2
0013    RET1     2   2
0014    JMP      2 => 0017
0015 => KPRI     2   1
0016    RET1     2   2
0017 => RET0     0   1

-- BYTECODE -- util.lua:682-689
0001    GGET     1   0      ; "string"
0002    TGETS    1   1   1  ; "lower"
0003    UGET     2   0      ; util
0004    TGETS    2   2   2  ; "getFileNameSuffix"
0005    MOV      3   0
0006    CALL     2   0   2
0007    CALLM    1   2   0
0008    ISNES    1   3      ; "sh"
0009    JMP      2 => 0013
0010    KSTR     2   4      ; "shell"
0011    RET1     2   2
0012    JMP      2 => 0017
0013 => ISNES    1   5      ; "py"
0014    JMP      2 => 0017
0015    KSTR     2   6      ; "python"
0016    RET1     2   2
0017 => RET0     0   1

-- BYTECODE -- util.lua:695-715
0001    ISF          1
0002    JMP      2 => 0005
0003    KSTR     2   0      ; "%6.1f"
0004    JMP      3 => 0006
0005 => KSTR     2   1      ; "%.1f"
0006 => ISF          1
0007    JMP      3 => 0010
0008    KSTR     3   2      ; "%6d"
0009    JMP      4 => 0011
0010 => KSTR     3   3      ; "%d"
0011 => GGET     4   4      ; "tonumber"
0012    MOV      5   0
0013    CALL     4   2   2
0014    MOV      0   4
0015    ISF          0
0016    JMP      4 => 0022
0017    GGET     4   5      ; "type"
0018    MOV      5   0
0019    CALL     4   2   2
0020    ISEQS    4   6      ; "number"
0021    JMP      4 => 0023
0022 => RET0     0   1
0023 => KNUM     4   0      ; 1073741824
0024    ISGE     4   0
0025    JMP      4 => 0038
0026    UGET     4   0      ; T
0027    UGET     5   1      ; _
0028    KSTR     6   7      ; "%1 GB"
0029    CALL     5   2   2
0030    GGET     6   8      ; "string"
0031    TGETS    6   6   9  ; "format"
0032    MOV      7   2
0033    DIVVN    8   0   1  ; 1024
0034    DIVVN    8   8   1  ; 1024
0035    DIVVN    8   8   1  ; 1024
0036    CALL     6   0   3
0037    CALLMT   4   1
0038 => KNUM     4   2      ; 1048576
0039    ISGE     4   0
0040    JMP      4 => 0052
0041    UGET     4   0      ; T
0042    UGET     5   1      ; _
0043    KSTR     6  10      ; "%1 MB"
0044    CALL     5   2   2
0045    GGET     6   8      ; "string"
0046    TGETS    6   6   9  ; "format"
0047    MOV      7   2
0048    DIVVN    8   0   1  ; 1024
0049    DIVVN    8   8   1  ; 1024
0050    CALL     6   0   3
0051    CALLMT   4   1
0052 => KSHORT   4 1024
0053    ISGE     4   0
0054    JMP      4 => 0066
0055    UGET     4   0      ; T
0056    UGET     5   1      ; _
0057    KSTR     6  11      ; "%1 KB"
0058    CALL     5   2   2
0059    GGET     6   8      ; "string"
0060    TGETS    6   6   9  ; "format"
0061    MOV      7   2
0062    DIVVN    8   0   1  ; 1024
0063    CALL     6   0   3
0064    CALLMT   4   1
0065    JMP      4 => 0076
0066 => UGET     4   0      ; T
0067    UGET     5   1      ; _
0068    KSTR     6  12      ; "%1 B"
0069    CALL     5   2   2
0070    GGET     6   8      ; "string"
0071    TGETS    6   6   9  ; "format"
0072    MOV      7   3
0073    MOV      8   0
0074    CALL     6   0   3
0075    CALLMT   4   1
0076 => RET0     0   1

-- BYTECODE -- util.lua:720-725
0001    GGET     1   0      ; "tostring"
0002    MOV      2   0
0003    CALL     1   2   2
0004    MOV      3   1
0005    TGETS    2   1   1  ; "reverse"
0006    CALL     2   2   2
0007    MOV      3   2
0008    TGETS    2   2   2  ; "gsub"
0009    KSTR     4   3      ; "(%d%d%d)"
0010    KSTR     5   4      ; "%1,"
0011    CALL     2   2   4
0012    MOV      1   2
0013    MOV      3   1
0014    TGETS    2   1   1  ; "reverse"
0015    CALL     2   2   2
0016    MOV      3   2
0017    TGETS    2   2   2  ; "gsub"
0018    KSTR     4   5      ; "^,"
0019    KSTR     5   6      ; ""
0020    CALL     2   2   4
0021    MOV      1   2
0022    RET1     1   2

-- BYTECODE -- util.lua:737-757
0001    KSHORT   2   1
0002    LEN      3   0
0003 => ISGT     2   3
0004    JMP      4 => 0094
0005    LOOP     4 => 0094
0006    MOV      5   0
0007    TGETS    4   0   0  ; "find"
0008    KSTR     6   1      ; "^[%z\001-\127]"
0009    MOV      7   2
0010    CALL     4   2   4
0011    ISF          4
0012    JMP      5 => 0015
0013    ADDVN    2   2   0  ; 1
0014    JMP      4 => 0003
0015 => MOV      5   0
0016    TGETS    4   0   0  ; "find"
0017    KSTR     6   2      ; "^[Â-ß][€-¿]"
0018    MOV      7   2
0019    CALL     4   2   4
0020    ISF          4
0021    JMP      5 => 0024
0022    ADDVN    2   2   1  ; 2
0023    JMP      4 => 0003
0024 => MOV      5   0
0025    TGETS    4   0   0  ; "find"
0026    KSTR     6   3      ; "^à[ -¿][€-¿]"
0027    MOV      7   2
0028    CALL     4   2   4
0029    IST          4
0030    JMP      5 => 0052
0031    MOV      5   0
0032    TGETS    4   0   0  ; "find"
0033    KSTR     6   4      ; "^[á-ì][€-¿][€-¿]"
0034    MOV      7   2
0035    CALL     4   2   4
0036    IST          4
0037    JMP      5 => 0052
0038    MOV      5   0
0039    TGETS    4   0   0  ; "find"
0040    KSTR     6   5      ; "^í[€-Ÿ][€-¿]"
0041    MOV      7   2
0042    CALL     4   2   4
0043    IST          4
0044    JMP      5 => 0052
0045    MOV      5   0
0046    TGETS    4   0   0  ; "find"
0047    KSTR     6   6      ; "^[î-ï][€-¿][€-¿]"
0048    MOV      7   2
0049    CALL     4   2   4
0050    ISF          4
0051    JMP      5 => 0054
0052 => ADDVN    2   2   2  ; 3
0053    JMP      4 => 0003
0054 => MOV      5   0
0055    TGETS    4   0   0  ; "find"
0056    KSTR     6   7      ; "^ð[-¿][€-¿][€-¿]"
0057    MOV      7   2
0058    CALL     4   2   4
0059    IST          4
0060    JMP      5 => 0075
0061    MOV      5   0
0062    TGETS    4   0   0  ; "find"
0063    KSTR     6   8      ; "^[ñ-ó][€-¿][€-¿][€-¿]"
0064    MOV      7   2
0065    CALL     4   2   4
0066    IST          4
0067    JMP      5 => 0075
0068    MOV      5   0
0069    TGETS    4   0   0  ; "find"
0070    KSTR     6   9      ; "^ô[€-][€-¿][€-¿]"
0071    MOV      7   2
0072    CALL     4   2   4
0073    ISF          4
0074    JMP      5 => 0077
0075 => ADDVN    2   2   3  ; 4
0076    JMP      4 => 0003
0077 => MOV      5   0
0078    TGETS    4   0  10  ; "sub"
0079    KSHORT   6   1
0080    SUBVN    7   2   0  ; 1
0081    CALL     4   2   4
0082    MOV      5   1
0083    MOV      7   0
0084    TGETS    6   0  10  ; "sub"
0085    ADDVN    8   2   0  ; 1
0086    CALL     6   2   3
0087    CAT      0   4   6
0088    LEN      4   1
0089    ADDVV    2   2   4
0090    LEN      4   1
0091    ADDVV    4   3   4
0092    SUBVN    3   4   0  ; 1
0093    JMP      4 => 0003
0094 => RET1     0   2

-- BYTECODE -- util.lua:765-771
0001    TNEW     3   0
0002    UGET     4   0      ; util
0003    TGETS    4   4   0  ; "gsplit"
0004    MOV      5   0
0005    MOV      6   1
0006    KPRI     7   1
0007    MOV      8   2
0008    CALL     4   4   5
0009    JMP      7 => 0015
0010 => GGET     8   1      ; "table"
0011    TGETS    8   8   2  ; "insert"
0012    MOV      9   3
0013    MOV     10   7
0014    CALL     8   1   3
0015 => ITERC    7   2   3
0016    ITERL    7 => 0010
0017    RET1     3   2

-- BYTECODE -- util.lua:780-807
0001    KSHORT   1 128
0002    ISGE     0   1
0003    JMP      1 => 0009
0004    GGET     1   0      ; "string"
0005    TGETS    1   1   1  ; "char"
0006    MOV      2   0
0007    CALLT    1   2
0008    JMP      1 => 0112
0009 => KSHORT   1 2048
0010    ISGE     0   1
0011    JMP      1 => 0030
0012    GGET     1   0      ; "string"
0013    TGETS    1   1   1  ; "char"
0014    UGET     2   0      ; bor
0015    KSHORT   3 192
0016    UGET     4   1      ; rshift
0017    MOV      5   0
0018    KSHORT   6   6
0019    CALL     4   0   3
0020    CALLM    2   2   1
0021    UGET     3   0      ; bor
0022    KSHORT   4 128
0023    UGET     5   2      ; band
0024    MOV      6   0
0025    KSHORT   7  63
0026    CALL     5   0   3
0027    CALLM    3   0   1
0028    CALLMT   1   1
0029    JMP      1 => 0112
0030 => KNUM     1   0      ; 65536
0031    ISGE     0   1
0032    JMP      1 => 0069
0033    KNUM     1   1      ; 55296
0034    ISGT     1   0
0035    JMP      1 => 0041
0036    KNUM     1   2      ; 57343
0037    ISGT     0   1
0038    JMP      1 => 0041
0039    KSTR     1   2      ; "ï¿½"
0040    RET1     1   2
0041 => GGET     1   0      ; "string"
0042    TGETS    1   1   1  ; "char"
0043    UGET     2   0      ; bor
0044    KSHORT   3 224
0045    UGET     4   1      ; rshift
0046    MOV      5   0
0047    KSHORT   6  12
0048    CALL     4   0   3
0049    CALLM    2   2   1
0050    UGET     3   0      ; bor
0051    KSHORT   4 128
0052    UGET     5   2      ; band
0053    UGET     6   1      ; rshift
0054    MOV      7   0
0055    KSHORT   8   6
0056    CALL     6   2   3
0057    KSHORT   7  63
0058    CALL     5   0   3
0059    CALLM    3   2   1
0060    UGET     4   0      ; bor
0061    KSHORT   5 128
0062    UGET     6   2      ; band
0063    MOV      7   0
0064    KSHORT   8  63
0065    CALL     6   0   3
0066    CALLM    4   0   1
0067    CALLMT   1   2
0068    JMP      1 => 0112
0069 => KNUM     1   3      ; 1114112
0070    ISGE     0   1
0071    JMP      1 => 0110
0072    GGET     1   0      ; "string"
0073    TGETS    1   1   1  ; "char"
0074    UGET     2   0      ; bor
0075    KSHORT   3 240
0076    UGET     4   1      ; rshift
0077    MOV      5   0
0078    KSHORT   6  18
0079    CALL     4   0   3
0080    CALLM    2   2   1
0081    UGET     3   0      ; bor
0082    KSHORT   4 128
0083    UGET     5   2      ; band
0084    UGET     6   1      ; rshift
0085    MOV      7   0
0086    KSHORT   8  12
0087    CALL     6   2   3
0088    KSHORT   7  63
0089    CALL     5   0   3
0090    CALLM    3   2   1
0091    UGET     4   0      ; bor
0092    KSHORT   5 128
0093    UGET     6   2      ; band
0094    UGET     7   1      ; rshift
0095    MOV      8   0
0096    KSHORT   9   6
0097    CALL     7   2   3
0098    KSHORT   8  63
0099    CALL     6   0   3
0100    CALLM    4   2   1
0101    UGET     5   0      ; bor
0102    KSHORT   6 128
0103    UGET     7   2      ; band
0104    MOV      8   0
0105    KSHORT   9  63
0106    CALL     7   0   3
0107    CALLM    5   0   1
0108    CALLMT   1   3
0109    JMP      1 => 0112
0110 => KSTR     1   2      ; "ï¿½"
0111    RET1     1   2
0112 => RET0     0   1

-- BYTECODE -- util.lua:816-816
0001    UGET     1   0      ; util
0002    TGETS    1   1   0  ; "unicodeCodepointToUtf8"
0003    GGET     2   1      ; "tonumber"
0004    MOV      3   0
0005    CALL     2   0   2
0006    CALLMT   1   0

-- BYTECODE -- util.lua:817-817
0001    UGET     1   0      ; util
0002    TGETS    1   1   0  ; "unicodeCodepointToUtf8"
0003    GGET     2   1      ; "tonumber"
0004    MOV      3   0
0005    KSHORT   4  16
0006    CALL     2   0   3
0007    CALLMT   1   0

-- BYTECODE -- util.lua:828-833
0001    GGET     1   0      ; "ipairs"
0002    UGET     2   0      ; HTML_ENTITIES_TO_UTF8
0003    CALL     1   4   2
0004    JMP      4 => 0011
0005 => MOV      7   0
0006    TGETS    6   0   1  ; "gsub"
0007    TGETB    8   5   1
0008    TGETB    9   5   2
0009    CALL     6   2   4
0010    MOV      0   6
0011 => ITERC    4   3   3
0012    ITERL    4 => 0005
0013    RET1     0   2

-- BYTECODE -- util.lua:843-857
0001    MOV      2   0
0002    TGETS    1   0   0  ; "gsub"
0003    KSTR     3   1      ; "%s*<%s*br%s*/?>%s*"
0004    KSTR     4   2      ; "\n"
0005    CALL     1   2   4
0006    MOV      0   1
0007    MOV      2   0
0008    TGETS    1   0   0  ; "gsub"
0009    KSTR     3   3      ; "%s*<%s*p%s*>%s*"
0010    KSTR     4   2      ; "\n"
0011    CALL     1   2   4
0012    MOV      0   1
0013    MOV      2   0
0014    TGETS    1   0   0  ; "gsub"
0015    KSTR     3   4      ; "%s*</%s*p%s*>%s*"
0016    KSTR     4   2      ; "\n"
0017    CALL     1   2   4
0018    MOV      0   1
0019    MOV      2   0
0020    TGETS    1   0   0  ; "gsub"
0021    KSTR     3   5      ; "%s*<%s*p%s*/>%s*"
0022    KSTR     4   2      ; "\n"
0023    CALL     1   2   4
0024    MOV      0   1
0025    MOV      2   0
0026    TGETS    1   0   0  ; "gsub"
0027    KSTR     3   6      ; "<[^>]*>"
0028    KSTR     4   7      ; ""
0029    CALL     1   2   4
0030    MOV      0   1
0031    UGET     1   0      ; util
0032    TGETS    1   1   8  ; "htmlEntitiesToUtf8"
0033    MOV      2   0
0034    CALL     1   2   2
0035    MOV      0   1
0036    MOV      2   0
0037    TGETS    1   0   0  ; "gsub"
0038    KSTR     3   9      ; "^[\n%s]*"
0039    KSTR     4   7      ; ""
0040    CALL     1   2   4
0041    MOV      0   1
0042    MOV      2   0
0043    TGETS    1   0   0  ; "gsub"
0044    KSTR     3  10      ; "[\n%s]*$"
0045    KSTR     4   7      ; ""
0046    CALL     1   2   4
0047    MOV      0   1
0048    RET1     0   2

-- BYTECODE -- util.lua:866-895
0001    KPRI     1   1
0002    KNIL     2   3
0003    MOV      5   0
0004    TGETS    4   0   0  ; "gsub"
0005    KSTR     6   1      ; "<%w+.->"
0006    KSTR     7   2      ; ""
0007    CALL     4   3   4
0008    MOV      3   5
0009    MOV      2   4
0010    KSHORT   4   0
0011    ISGE     4   3
0012    JMP      4 => 0015
0013    KPRI     1   2
0014    JMP      4 => 0032
0015 => KPRI     4   0
0016    MOV      6   0
0017    TGETS    5   0   0  ; "gsub"
0018    KSTR     7   3      ; "&lt;%a+&gt;"
0019    KSTR     8   2      ; ""
0020    CALL     5   3   4
0021    MOV      4   6
0022    MOV      2   5
0023    KSHORT   5   0
0024    ISGE     5   4
0025    JMP      5 => 0032
0026    KPRI     1   2
0027    UGET     5   0      ; util
0028    TGETS    5   5   4  ; "htmlEntitiesToUtf8"
0029    MOV      6   0
0030    CALL     5   2   2
0031    MOV      0   5
0032 => ISF          1
0033    JMP      4 => 0040
0034    UGET     4   0      ; util
0035    TGETS    4   4   5  ; "htmlToPlainText"
0036    MOV      5   0
0037    CALL     4   2   2
0038    MOV      0   4
0039    JMP      4 => 0046
0040 => MOV      5   0
0041    TGETS    4   0   0  ; "gsub"
0042    KSTR     6   6      ; "]]>%s*$"
0043    KSTR     7   2      ; ""
0044    CALL     4   2   4
0045    MOV      0   4
0046 => RET1     0   2

-- BYTECODE -- util.lua:900-909
0001    MOV      2   0
0002    TGETS    1   0   0  ; "gsub"
0003    KSTR     3   1      ; "[}{">/<'&]"
0004    TDUP     4   2
0005    CALLT    1   4

-- BYTECODE -- util.lua:914-921
0001    TNEW     1   0
0002    GGET     2   0      ; "ipairs"
0003    MOV      3   0
0004    CALL     2   4   2
0005    JMP      5 => 0019
0006 => KSTR     7   1      ; "'"
0007    MOV      9   6
0008    TGETS    8   6   2  ; "gsub"
0009    KSTR    10   1      ; "'"
0010    KSTR    11   3      ; "'\''"
0011    CALL     8   2   4
0012    KSTR     9   1      ; "'"
0013    CAT      6   7   9
0014    GGET     7   4      ; "table"
0015    TGETS    7   7   5  ; "insert"
0016    MOV      8   1
0017    MOV      9   6
0018    CALL     7   1   3
0019 => ITERC    5   3   3
0020    ITERL    5 => 0006
0021    GGET     2   4      ; "table"
0022    TGETS    2   2   6  ; "concat"
0023    MOV      3   1
0024    KSTR     4   7      ; " "
0025    CALLT    2   3

-- BYTECODE -- util.lua:925-928
0001    LEN      1   0
0002    KSHORT   2   0
0003    MOV      3   1
0004    KSHORT   4   1
0005    FORI     2 => 0009
0006 => KPRI     6   0
0007    TSETV    6   0   5
0008    FORL     2 => 0006
0009 => RET0     0   1

-- BYTECODE -- util.lua:935-937
0001    GGET     1   0      ; "string"
0002    TGETS    1   1   1  ; "format"
0003    KSTR     2   2      ; "%%%02X"
0004    GGET     3   0      ; "string"
0005    TGETS    3   3   3  ; "byte"
0006    MOV      4   0
0007    CALL     3   0   2
0008    CALLMT   1   1

-- BYTECODE -- util.lua:934-944
0001    FNEW     1   0      ; util.lua:935
0002    ISNEP    0   0
0003    JMP      2 => 0006
0004    UCLO     0 => 0005
0005 => RET0     0   1
0006 => MOV      3   0
0007    TGETS    2   0   1  ; "gsub"
0008    KSTR     4   2      ; "\n"
0009    KSTR     5   3      ; "\r\n"
0010    CALL     2   2   4
0011    MOV      0   2
0012    MOV      3   0
0013    TGETS    2   0   1  ; "gsub"
0014    KSTR     4   4      ; "([^%w%-%.%_%~%!%*%'%(%)])"
0015    MOV      5   1
0016    CALL     2   2   4
0017    MOV      0   2
0018    UCLO     0 => 0019
0019 => RET1     0   2

-- BYTECODE -- util.lua:951-953
0001    GGET     1   0      ; "string"
0002    TGETS    1   1   1  ; "char"
0003    GGET     2   2      ; "tonumber"
0004    MOV      3   0
0005    KSHORT   4  16
0006    CALL     2   0   3
0007    CALLMT   1   0

-- BYTECODE -- util.lua:950-959
0001    FNEW     1   0      ; util.lua:951
0002    ISNEP    0   0
0003    JMP      2 => 0006
0004    UCLO     0 => 0005
0005 => RET0     0   1
0006 => MOV      3   0
0007    TGETS    2   0   1  ; "gsub"
0008    KSTR     4   2      ; "%%(%x%x)"
0009    MOV      5   1
0010    CALL     2   2   4
0011    MOV      0   2
0012    UCLO     0 => 0013
0013 => RET1     0   2

-- BYTECODE -- util.lua:964-973
0001    GGET     1   0      ; "loadstring"
0002    MOV      2   0
0003    CALL     1   3   2
0004    ISF          1
0005    JMP      3 => 0008
0006    KPRI     3   0
0007    RET1     3   2
0008 => MOV      4   2
0009    TGETS    3   2   1  ; "gsub"
0010    KSTR     5   2      ; "%[string ".-%"]:"
0011    KSTR     6   3      ; "Line "
0012    CALL     3   2   4
0013    MOV      2   3
0014    RET1     2   2

-- BYTECODE -- util.lua:981-995
0001    UGET     2   0      ; dbg
0002    TGETS    2   2   0  ; "dassert"
0003    GGET     3   1      ; "type"
0004    MOV      4   0
0005    CALL     3   2   2
0006    ISEQS    3   2      ; "string"
0007    JMP      3 => 0010
0008    KPRI     3   1
0009    JMP      4 => 0011
0010 => KPRI     3   2
0011 => CALL     2   1   2
0012    GGET     2   3      ; "require"
0013    KSTR     3   4      ; "ui/bidi"
0014    CALL     2   2   2
0015    KPRI     3   0
0016    MOV      5   0
0017    TGETS    4   0   5  ; "match"
0018    KSTR     6   6      ; "%.tar%.bz2$"
0019    CALL     4   2   3
0020    IST          4
0021    JMP      5 => 0040
0022    MOV      5   0
0023    TGETS    4   0   5  ; "match"
0024    KSTR     6   7      ; "%.tar%.gz$"
0025    CALL     4   2   3
0026    IST          4
0027    JMP      5 => 0040
0028    MOV      5   0
0029    TGETS    4   0   5  ; "match"
0030    KSTR     6   8      ; "%.tar%.lz$"
0031    CALL     4   2   3
0032    IST          4
0033    JMP      5 => 0040
0034    MOV      5   0
0035    TGETS    4   0   5  ; "match"
0036    KSTR     6   9      ; "%.tgz$"
0037    CALL     4   2   3
0038    ISF          4
0039    JMP      5 => 0051
0040 => GGET     4  10      ; "os"
0041    TGETS    4   4  11  ; "execute"
0042    KSTR     5  12      ; "./tar xf %q -C %q"
0043    MOV      6   5
0044    TGETS    5   5  13  ; "format"
0045    MOV      7   0
0046    MOV      8   1
0047    CALL     5   0   4
0048    CALLM    4   2   0
0049    MOV      3   4
0050    JMP      4 => 0061
0051 => KPRI     4   1
0052    UGET     5   1      ; T
0053    UGET     6   2      ; _
0054    KSTR     7  14      ; "Couldn't extract archive:\n\n%1\n\nUnrec"~
0055    CALL     6   2   2
0056    TGETS    7   2  15  ; "filepath"
0057    MOV      8   0
0058    CALL     7   0   2
0059    CALLM    5   0   1
0060    RETM     4   1
0061 => IST          3
0062    JMP      4 => 0073
0063    KPRI     4   1
0064    UGET     5   1      ; T
0065    UGET     6   2      ; _
0066    KSTR     7  16      ; "Extracting archive failed:\n\n%1"
0067    TGETS    8   2  15  ; "filepath"
0068    MOV      9   0
0069    CALL     8   0   2
0070    CALLM    6   0   1
0071    CALLM    5   0   0
0072    RETM     4   1
0073 => KPRI     4   2
0074    RET1     4   2

-- BYTECODE -- util.lua:1002-1004
0001    MOV      3   0
0002    TGETS    2   0   0  ; "sub"
0003    KSHORT   4   1
0004    LEN      5   1
0005    CALL     2   2   4
0006    ISEQV    2   1
0007    JMP      2 => 0010
0008    KPRI     2   1
0009    JMP      3 => 0011
0010 => KPRI     2   2
0011 => RET1     2   2

-- BYTECODE -- util.lua:1009-1011
0001    ISEQS    1   0      ; ""
0002    JMP      2 => 0012
0003    MOV      3   0
0004    TGETS    2   0   1  ; "sub"
0005    LEN      4   1
0006    UNM      4   4
0007    CALL     2   2   3
0008    ISEQV    2   1
0009    JMP      2 => 0012
0010    KPRI     2   1
0011    JMP      3 => 0013
0012 => KPRI     2   2
0013 => RET1     2   2

-- BYTECODE -- util.lua:0-1014
0001    GGET     0   0      ; "require"
0002    KSTR     1   1      ; "ffi/util"
0003    CALL     0   2   2
0004    GGET     1   0      ; "require"
0005    KSTR     2   2      ; "dbg"
0006    CALL     1   2   2
0007    GGET     2   0      ; "require"
0008    KSTR     3   3      ; "gettext"
0009    CALL     2   2   2
0010    TGETS    3   0   4  ; "template"
0011    GGET     4   5      ; "bit"
0012    TGETS    4   4   6  ; "lshift"
0013    GGET     5   5      ; "bit"
0014    TGETS    5   5   7  ; "rshift"
0015    GGET     6   5      ; "bit"
0016    TGETS    6   6   8  ; "band"
0017    GGET     7   5      ; "bit"
0018    TGETS    7   7   9  ; "bor"
0019    TNEW     8   0
0020    FNEW     9  11      ; util.lua:20
0021    TSETS    9   8  10  ; "stripPunctuation"
0022    FNEW     9  13      ; util.lua:48
0023    TSETS    9   8  12  ; "gsplit"
0024    FNEW     9  15      ; util.lua:83
0025    TSETS    9   8  14  ; "secondsToClock"
0026    FNEW     9  17      ; util.lua:112
0027    TSETS    9   8  16  ; "secondsToHClock"
0028    FNEW     9  19      ; util.lua:207
0029    TSETS    9   8  18  ; "tableEquals"
0030    FNEW     9  21      ; util.lua:245
0031    TSETS    9   8  20  ; "tableDeepCopy"
0032    FNEW     9  23      ; util.lua:268
0033    TSETS    9   8  22  ; "tableSize"
0034    FNEW     9  25      ; util.lua:277
0035    TSETS    9   8  24  ; "arrayAppend"
0036    FNEW     9  27      ; util.lua:285
0037    TSETS    9   8  26  ; "arrayReverse"
0038    FNEW     9  29      ; util.lua:298
0039    TSETS    9   8  28  ; "tableMerge"
0040    FNEW     9  31      ; util.lua:315
0041    TSETS    9   8  30  ; "lastIndexOf"
0042    FNEW     9  33      ; util.lua:323
0043    TSETS    9   8  32  ; "utf8Reverse"
0044    FNEW     9  35      ; util.lua:331
0045    TSETS    9   8  34  ; "splitToChars"
0046    FNEW     9  37      ; util.lua:387
0047    TSETS    9   8  36  ; "isCJKChar"
0048    FNEW     9  39      ; util.lua:394
0049    TSETS    9   8  38  ; "hasCJKChar"
0050    FNEW     9  41      ; util.lua:401
0051    TSETS    9   8  40  ; "splitToWords"
0052    KSTR     9  42      ; ":;,.!?)]}$%=-+*/|<>Â»â€"
0053    KSTR    10  43      ; "([{$=-+*/|<>Â«â€œ"
0054    GGET    11  44      ; "table"
0055    TGETS   11  11  45  ; "concat"
0056    TDUP    12  46
0057    CALL    11   2   2
0058    GGET    12  44      ; "table"
0059    TGETS   12  12  45  ; "concat"
0060    TDUP    13  47
0061    CALL    12   2   2
0062    GGET    13  44      ; "table"
0063    TGETS   13  13  45  ; "concat"
0064    TDUP    14  48
0065    CALL    13   2   2
0066    FNEW    14  50      ; util.lua:462
0067    TSETS   14   8  49  ; "isSplittable"
0068    FNEW    14  52      ; util.lua:501
0069    TSETS   14   8  51  ; "getFilesystemType"
0070    FNEW    14  54      ; util.lua:527
0071    TSETS   14   8  53  ; "isEmptyDir"
0072    FNEW    14  56      ; util.lua:543
0073    TSETS   14   8  55  ; "pathExists"
0074    FNEW    14  58      ; util.lua:553
0075    TSETS   14   8  57  ; "makePath"
0076    FNEW    14  59      ; util.lua:573
0077    FNEW    15  60      ; util.lua:582
0078    FNEW    16  62      ; util.lua:599
0079    TSETS   16   8  61  ; "getSafeFilename"
0080    FNEW    16  64      ; util.lua:641
0081    TSETS   16   8  63  ; "splitFilePathName"
0082    FNEW    16  66      ; util.lua:650
0083    TSETS   16   8  65  ; "splitFileNameSuffix"
0084    FNEW    16  68      ; util.lua:659
0085    TSETS   16   8  67  ; "getFileNameSuffix"
0086    FNEW    16  70      ; util.lua:668
0087    TSETS   16   8  69  ; "isAllowedScript"
0088    FNEW    16  72      ; util.lua:682
0089    TSETS   16   8  71  ; "getScriptType"
0090    FNEW    16  74      ; util.lua:695
0091    TSETS   16   8  73  ; "getFriendlySize"
0092    FNEW    16  76      ; util.lua:720
0093    TSETS   16   8  75  ; "getFormattedSize"
0094    FNEW    16  78      ; util.lua:737
0095    TSETS   16   8  77  ; "fixUtf8"
0096    FNEW    16  80      ; util.lua:765
0097    TSETS   16   8  79  ; "splitToArray"
0098    FNEW    16  82      ; util.lua:780
0099    TSETS   16   8  81  ; "unicodeCodepointToUtf8"
0100    TNEW    16   9
0101    TDUP    17  83
0102    TSETB   17  16   1
0103    TDUP    17  84
0104    TSETB   17  16   2
0105    TDUP    17  85
0106    TSETB   17  16   3
0107    TDUP    17  86
0108    TSETB   17  16   4
0109    TDUP    17  87
0110    TSETB   17  16   5
0111    TDUP    17  88
0112    FNEW    18  89      ; util.lua:816
0113    TSETB   18  17   2
0114    TSETB   17  16   6
0115    TDUP    17  90
0116    FNEW    18  91      ; util.lua:817
0117    TSETB   18  17   2
0118    TSETB   17  16   7
0119    TDUP    17  92
0120    TSETB   17  16   8
0121    FNEW    17  94      ; util.lua:828
0122    TSETS   17   8  93  ; "htmlEntitiesToUtf8"
0123    FNEW    17  96      ; util.lua:843
0124    TSETS   17   8  95  ; "htmlToPlainText"
0125    FNEW    17  98      ; util.lua:866
0126    TSETS   17   8  97  ; "htmlToPlainTextIfHtml"
0127    FNEW    17 100      ; util.lua:900
0128    TSETS   17   8  99  ; "htmlEscape"
0129    FNEW    17 102      ; util.lua:914
0130    TSETS   17   8 101  ; "shell_escape"
0131    FNEW    17 104      ; util.lua:925
0132    TSETS   17   8 103  ; "clearTable"
0133    FNEW    17 106      ; util.lua:934
0134    TSETS   17   8 105  ; "urlEncode"
0135    FNEW    17 108      ; util.lua:950
0136    TSETS   17   8 107  ; "urlDecode"
0137    FNEW    17 110      ; util.lua:964
0138    TSETS   17   8 109  ; "checkLuaSyntax"
0139    FNEW    17 112      ; util.lua:981
0140    TSETS   17   8 111  ; "unpackArchive"
0141    FNEW    17 114      ; util.lua:1002
0142    TSETS   17   8 113  ; "stringStartsWith"
0143    FNEW    17 116      ; util.lua:1009
0144    TSETS   17   8 115  ; "stringEndsWith"
0145    UCLO     0 => 0146
0146 => RET1     8   2

