-- BYTECODE -- version.lua:9-22
0001    TGETS    1   0   0  ; "rev"
0002    IST          1
0003    JMP      1 => 0023
0004    GGET     1   1      ; "io"
0005    TGETS    1   1   2  ; "open"
0006    KSTR     2   3      ; "git-rev"
0007    KSTR     3   4      ; "r"
0008    CALL     1   2   3
0009    ISF          1
0010    JMP      2 => 0018
0011    MOV      3   1
0012    TGETS    2   1   5  ; "read"
0013    CALL     2   2   2
0014    TSETS    2   0   0  ; "rev"
0015    MOV      3   1
0016    TGETS    2   1   6  ; "close"
0017    CALL     2   1   2
0018 => TGETS    2   0   0  ; "rev"
0019    ISNES    2   7      ; "fatal: No names found, cannot describe a"~
0020    JMP      2 => 0023
0021    KPRI     2   0
0022    TSETS    2   0   0  ; "rev"
0023 => TGETS    1   0   0  ; "rev"
0024    RET1     1   2

-- BYTECODE -- version.lua:28-40
0001    IST          1
0002    JMP      2 => 0004
0003    RET0     0   1
0004 => MOV      3   1
0005    TGETS    2   1   0  ; "match"
0006    KSTR     4   1      ; "v(%d%d%d%d)%.(%d%d)%.?(%d?%d?)-?(%d*)"
0007    CALL     2   5   3
0008    GGET     6   2      ; "tonumber"
0009    MOV      7   2
0010    CALL     6   2   2
0011    MOV      2   6
0012    GGET     6   2      ; "tonumber"
0013    MOV      7   3
0014    CALL     6   2   2
0015    MOV      3   6
0016    GGET     6   2      ; "tonumber"
0017    MOV      7   4
0018    CALL     6   2   2
0019    MOV      4   6
0020    GGET     6   2      ; "tonumber"
0021    MOV      7   5
0022    CALL     6   2   2
0023    MOV      5   6
0024    MOV      7   1
0025    TGETS    6   1   0  ; "match"
0026    KSTR     8   3      ; "-%d*-g(%x*)[%d_%-]*"
0027    CALL     6   2   3
0028    ISTC     7   2
0029    JMP      7 => 0031
0030    KSHORT   7   0
0031 => MULVN    7   7   0  ; 100
0032    ISTC     8   3
0033    JMP      8 => 0035
0034    KSHORT   8   0
0035 => ADDVV    7   7   8
0036    MULVN    7   7   1  ; 1000000
0037    ISTC     8   4
0038    JMP      8 => 0040
0039    KSHORT   8   0
0040 => MULVN    8   8   2  ; 10000
0041    ADDVV    7   7   8
0042    ISTC     8   5
0043    JMP      8 => 0045
0044    KSHORT   8   0
0045 => ADDVV    7   7   8
0046    MOV      8   6
0047    RET      7   3

-- BYTECODE -- version.lua:46-51
0001    TGETS    1   0   0  ; "version"
0002    ISF          1
0003    JMP      1 => 0007
0004    TGETS    1   0   1  ; "commit"
0005    IST          1
0006    JMP      1 => 0015
0007 => MOV      2   0
0008    TGETS    1   0   2  ; "getNormalizedVersion"
0009    MOV      4   0
0010    TGETS    3   0   3  ; "getCurrentRevision"
0011    CALL     3   0   2
0012    CALLM    1   3   1
0013    TSETS    2   0   1  ; "commit"
0014    TSETS    1   0   0  ; "version"
0015 => TGETS    1   0   0  ; "version"
0016    TGETS    2   0   1  ; "commit"
0017    RET      1   3

-- BYTECODE -- version.lua:0-54
0001    TNEW     0   0
0002    FNEW     1   1      ; version.lua:9
0003    TSETS    1   0   0  ; "getCurrentRevision"
0004    FNEW     1   3      ; version.lua:28
0005    TSETS    1   0   2  ; "getNormalizedVersion"
0006    FNEW     1   5      ; version.lua:46
0007    TSETS    1   0   4  ; "getNormalizedCurrentVersion"
0008    UCLO     0 => 0009
0009 => RET1     0   2

