
main <./spec/unit/version_spec.lua:0,0> (5 instructions, 20 bytes at 0x7fa9af4068c0)
0+ params, 3 slots, 0 upvalues, 0 locals, 2 constants, 1 function
	1	[1]	GETGLOBAL	0 -1	; describe
	2	[1]	LOADK    	1 -2	; "Version module"
	3	[68]	CLOSURE  	2 0	; 0x7fa9af406b60
	4	[1]	CALL     	0 3 1
	5	[68]	RETURN   	0 1

function <./spec/unit/version_spec.lua:1,68> (20 instructions, 80 bytes at 0x7fa9af406b60)
0 params, 4 slots, 0 upvalues, 1 local, 6 constants, 4 functions
	1	[3]	GETGLOBAL	1 -1	; setup
	2	[6]	CLOSURE  	2 0	; 0x7fa9af406d80
	3	[6]	MOVE     	0 0
	4	[3]	CALL     	1 2 1
	5	[7]	GETGLOBAL	1 -2	; it
	6	[7]	LOADK    	2 -3	; "should get current revision"
	7	[15]	CLOSURE  	3 1	; 0x7fa9af406c60
	8	[15]	MOVE     	0 0
	9	[7]	CALL     	1 3 1
	10	[16]	GETGLOBAL	1 -4	; describe
	11	[16]	LOADK    	2 -5	; "normalized"
	12	[60]	CLOSURE  	3 2	; 0x7fa9af4075e0
	13	[60]	MOVE     	0 0
	14	[16]	CALL     	1 3 1
	15	[61]	GETGLOBAL	1 -2	; it
	16	[61]	LOADK    	2 -6	; "should fail gracefully"
	17	[67]	CLOSURE  	3 3	; 0x7fa9af409b00
	18	[67]	MOVE     	0 0
	19	[61]	CALL     	1 3 1
	20	[68]	RETURN   	0 1

function <./spec/unit/version_spec.lua:3,6> (8 instructions, 32 bytes at 0x7fa9af406d80)
0 params, 2 slots, 1 upvalue, 0 locals, 3 constants, 0 functions
	1	[4]	GETGLOBAL	0 -1	; require
	2	[4]	LOADK    	1 -2	; "commonrequire"
	3	[4]	CALL     	0 2 1
	4	[5]	GETGLOBAL	0 -1	; require
	5	[5]	LOADK    	1 -3	; "version"
	6	[5]	CALL     	0 2 2
	7	[5]	SETUPVAL 	0 0	; Version
	8	[6]	RETURN   	0 1

function <./spec/unit/version_spec.lua:7,15> (36 instructions, 144 bytes at 0x7fa9af406c60)
0 params, 9 slots, 1 upvalue, 6 locals, 10 constants, 0 functions
	1	[8]	GETUPVAL 	0 0	; Version
	2	[8]	SELF     	0 0 -1	; "getCurrentRevision"
	3	[8]	CALL     	0 2 2
	4	[9]	SELF     	1 0 -2	; "match"
	5	[9]	LOADK    	3 -3	; "v(%d%d%d%d)%.(%d%d)%.?(%d?)-?(%d*)"
	6	[9]	CALL     	1 3 5
	7	[10]	SELF     	5 0 -2	; "match"
	8	[10]	LOADK    	7 -4	; "-%d*-g(%x*)[%d_%-]*"
	9	[10]	CALL     	5 3 2
	10	[11]	GETGLOBAL	6 -5	; assert
	11	[11]	GETTABLE 	6 6 -6	; "is_truthy"
	12	[11]	MOVE     	7 1
	13	[11]	CALL     	6 2 1
	14	[12]	GETGLOBAL	6 -5	; assert
	15	[12]	GETTABLE 	6 6 -6	; "is_truthy"
	16	[12]	MOVE     	7 2
	17	[12]	CALL     	6 2 1
	18	[13]	GETGLOBAL	6 -5	; assert
	19	[13]	GETTABLE 	6 6 -7	; "is_true"
	20	[13]	SELF     	7 1 -9	; "len"
	21	[13]	CALL     	7 2 2
	22	[13]	EQ       	1 -8 7	; 4 -
	23	[13]	JMP      	1	; to 25
	24	[13]	LOADBOOL 	7 0 1
	25	[13]	LOADBOOL 	7 1 0
	26	[13]	CALL     	6 2 1
	27	[14]	GETGLOBAL	6 -5	; assert
	28	[14]	GETTABLE 	6 6 -7	; "is_true"
	29	[14]	SELF     	7 2 -9	; "len"
	30	[14]	CALL     	7 2 2
	31	[14]	EQ       	1 -10 7	; 2 -
	32	[14]	JMP      	1	; to 34
	33	[14]	LOADBOOL 	7 0 1
	34	[14]	LOADBOOL 	7 1 0
	35	[14]	CALL     	6 2 1
	36	[15]	RETURN   	0 1

function <./spec/unit/version_spec.lua:16,60> (31 instructions, 124 bytes at 0x7fa9af4075e0)
0 params, 3 slots, 1 upvalue, 0 locals, 7 constants, 6 functions
	1	[17]	GETGLOBAL	0 -1	; it
	2	[17]	LOADK    	1 -2	; "should get current version"
	3	[19]	CLOSURE  	2 0	; 0x7fa9af4077d0
	4	[19]	GETUPVAL 	0 0	; Version
	5	[17]	CALL     	0 3 1
	6	[20]	GETGLOBAL	0 -1	; it
	7	[20]	LOADK    	1 -3	; "should get version"
	8	[27]	CLOSURE  	2 1	; 0x7fa9af407d20
	9	[27]	GETUPVAL 	0 0	; Version
	10	[20]	CALL     	0 3 1
	11	[28]	GETGLOBAL	0 -1	; it
	12	[28]	LOADK    	1 -4	; "should get version with four number revision"
	13	[35]	CLOSURE  	2 2	; 0x7fa9af4085f0
	14	[35]	GETUPVAL 	0 0	; Version
	15	[28]	CALL     	0 3 1
	16	[36]	GETGLOBAL	0 -1	; it
	17	[36]	LOADK    	1 -5	; "should get stable version"
	18	[43]	CLOSURE  	2 3	; 0x7fa9af408d60
	19	[43]	GETUPVAL 	0 0	; Version
	20	[36]	CALL     	0 3 1
	21	[44]	GETGLOBAL	0 -1	; it
	22	[44]	LOADK    	1 -6	; "should get stable point release version"
	23	[51]	CLOSURE  	2 4	; 0x7fa9af409290
	24	[51]	GETUPVAL 	0 0	; Version
	25	[44]	CALL     	0 3 1
	26	[52]	GETGLOBAL	0 -1	; it
	27	[52]	LOADK    	1 -7	; "should get point release nightly version"
	28	[59]	CLOSURE  	2 5	; 0x7fa9af409810
	29	[59]	GETUPVAL 	0 0	; Version
	30	[52]	CALL     	0 3 1
	31	[60]	RETURN   	0 1

function <./spec/unit/version_spec.lua:17,19> (15 instructions, 60 bytes at 0x7fa9af4077d0)
0 params, 4 slots, 1 upvalue, 0 locals, 6 constants, 0 functions
	1	[18]	GETGLOBAL	0 -1	; assert
	2	[18]	GETTABLE 	0 0 -2	; "is_true"
	3	[18]	GETGLOBAL	1 -4	; tostring
	4	[18]	GETUPVAL 	2 0	; Version
	5	[18]	SELF     	2 2 -5	; "getNormalizedCurrentVersion"
	6	[18]	CALL     	2 2 0
	7	[18]	CALL     	1 0 2
	8	[18]	SELF     	1 1 -6	; "len"
	9	[18]	CALL     	1 2 2
	10	[18]	EQ       	1 -3 1	; 12 -
	11	[18]	JMP      	1	; to 13
	12	[18]	LOADBOOL 	1 0 1
	13	[18]	LOADBOOL 	1 1 0
	14	[18]	CALL     	0 2 1
	15	[19]	RETURN   	0 1

function <./spec/unit/version_spec.lua:20,27> (20 instructions, 80 bytes at 0x7fa9af407d20)
0 params, 8 slots, 1 upvalue, 5 locals, 7 constants, 0 functions
	1	[21]	LOADK    	0 -1	; "v2015.11-982-g704d4238"
	2	[22]	GETUPVAL 	1 0	; Version
	3	[22]	SELF     	1 1 -2	; "getNormalizedVersion"
	4	[22]	MOVE     	3 0
	5	[22]	CALL     	1 3 3
	6	[23]	LOADK    	3 -3	; 201511000982
	7	[24]	LOADK    	4 -4	; "704d4238"
	8	[25]	GETGLOBAL	5 -5	; assert
	9	[25]	GETTABLE 	5 5 -6	; "are"
	10	[25]	GETTABLE 	5 5 -7	; "same"
	11	[25]	MOVE     	6 3
	12	[25]	MOVE     	7 1
	13	[25]	CALL     	5 3 1
	14	[26]	GETGLOBAL	5 -5	; assert
	15	[26]	GETTABLE 	5 5 -6	; "are"
	16	[26]	GETTABLE 	5 5 -7	; "same"
	17	[26]	MOVE     	6 4
	18	[26]	MOVE     	7 2
	19	[26]	CALL     	5 3 1
	20	[27]	RETURN   	0 1

function <./spec/unit/version_spec.lua:28,35> (20 instructions, 80 bytes at 0x7fa9af4085f0)
0 params, 8 slots, 1 upvalue, 5 locals, 7 constants, 0 functions
	1	[29]	LOADK    	0 -1	; "v2015.11-1755-gecd7b5b_2018-07-02"
	2	[30]	GETUPVAL 	1 0	; Version
	3	[30]	SELF     	1 1 -2	; "getNormalizedVersion"
	4	[30]	MOVE     	3 0
	5	[30]	CALL     	1 3 3
	6	[31]	LOADK    	3 -3	; 201511001755
	7	[32]	LOADK    	4 -4	; "ecd7b5b"
	8	[33]	GETGLOBAL	5 -5	; assert
	9	[33]	GETTABLE 	5 5 -6	; "are"
	10	[33]	GETTABLE 	5 5 -7	; "same"
	11	[33]	MOVE     	6 3
	12	[33]	MOVE     	7 1
	13	[33]	CALL     	5 3 1
	14	[34]	GETGLOBAL	5 -5	; assert
	15	[34]	GETTABLE 	5 5 -6	; "are"
	16	[34]	GETTABLE 	5 5 -7	; "same"
	17	[34]	MOVE     	6 4
	18	[34]	MOVE     	7 2
	19	[34]	CALL     	5 3 1
	20	[35]	RETURN   	0 1

function <./spec/unit/version_spec.lua:36,43> (20 instructions, 80 bytes at 0x7fa9af408d60)
0 params, 8 slots, 1 upvalue, 5 locals, 6 constants, 0 functions
	1	[37]	LOADK    	0 -1	; "v2018.11"
	2	[38]	GETUPVAL 	1 0	; Version
	3	[38]	SELF     	1 1 -2	; "getNormalizedVersion"
	4	[38]	MOVE     	3 0
	5	[38]	CALL     	1 3 3
	6	[39]	LOADK    	3 -3	; 201811000000
	7	[40]	LOADNIL  	4 4
	8	[41]	GETGLOBAL	5 -4	; assert
	9	[41]	GETTABLE 	5 5 -5	; "are"
	10	[41]	GETTABLE 	5 5 -6	; "same"
	11	[41]	MOVE     	6 3
	12	[41]	MOVE     	7 1
	13	[41]	CALL     	5 3 1
	14	[42]	GETGLOBAL	5 -4	; assert
	15	[42]	GETTABLE 	5 5 -5	; "are"
	16	[42]	GETTABLE 	5 5 -6	; "same"
	17	[42]	MOVE     	6 4
	18	[42]	MOVE     	7 2
	19	[42]	CALL     	5 3 1
	20	[43]	RETURN   	0 1

function <./spec/unit/version_spec.lua:44,51> (20 instructions, 80 bytes at 0x7fa9af409290)
0 params, 8 slots, 1 upvalue, 5 locals, 6 constants, 0 functions
	1	[45]	LOADK    	0 -1	; "v2018.11.1"
	2	[46]	GETUPVAL 	1 0	; Version
	3	[46]	SELF     	1 1 -2	; "getNormalizedVersion"
	4	[46]	MOVE     	3 0
	5	[46]	CALL     	1 3 3
	6	[47]	LOADK    	3 -3	; 201811010000
	7	[48]	LOADNIL  	4 4
	8	[49]	GETGLOBAL	5 -4	; assert
	9	[49]	GETTABLE 	5 5 -5	; "are"
	10	[49]	GETTABLE 	5 5 -6	; "same"
	11	[49]	MOVE     	6 3
	12	[49]	MOVE     	7 1
	13	[49]	CALL     	5 3 1
	14	[50]	GETGLOBAL	5 -4	; assert
	15	[50]	GETTABLE 	5 5 -5	; "are"
	16	[50]	GETTABLE 	5 5 -6	; "same"
	17	[50]	MOVE     	6 4
	18	[50]	MOVE     	7 2
	19	[50]	CALL     	5 3 1
	20	[51]	RETURN   	0 1

function <./spec/unit/version_spec.lua:52,59> (20 instructions, 80 bytes at 0x7fa9af409810)
0 params, 8 slots, 1 upvalue, 5 locals, 7 constants, 0 functions
	1	[53]	LOADK    	0 -1	; "v2018.11.1-1755-gecd7b5b_2018-07-02"
	2	[54]	GETUPVAL 	1 0	; Version
	3	[54]	SELF     	1 1 -2	; "getNormalizedVersion"
	4	[54]	MOVE     	3 0
	5	[54]	CALL     	1 3 3
	6	[55]	LOADK    	3 -3	; 201811011755
	7	[56]	LOADK    	4 -4	; "ecd7b5b"
	8	[57]	GETGLOBAL	5 -5	; assert
	9	[57]	GETTABLE 	5 5 -6	; "are"
	10	[57]	GETTABLE 	5 5 -7	; "same"
	11	[57]	MOVE     	6 3
	12	[57]	MOVE     	7 1
	13	[57]	CALL     	5 3 1
	14	[58]	GETGLOBAL	5 -5	; assert
	15	[58]	GETTABLE 	5 5 -6	; "are"
	16	[58]	GETTABLE 	5 5 -7	; "same"
	17	[58]	MOVE     	6 4
	18	[58]	MOVE     	7 2
	19	[58]	CALL     	5 3 1
	20	[59]	RETURN   	0 1

function <./spec/unit/version_spec.lua:61,67> (17 instructions, 68 bytes at 0x7fa9af409b00)
0 params, 7 slots, 1 upvalue, 4 locals, 4 constants, 0 functions
	1	[62]	GETUPVAL 	0 0	; Version
	2	[62]	SELF     	0 0 -1	; "getNormalizedVersion"
	3	[62]	CALL     	0 2 3
	4	[63]	LOADNIL  	2 3
	5	[65]	GETGLOBAL	4 -2	; assert
	6	[65]	GETTABLE 	4 4 -3	; "are"
	7	[65]	GETTABLE 	4 4 -4	; "same"
	8	[65]	MOVE     	5 2
	9	[65]	MOVE     	6 0
	10	[65]	CALL     	4 3 1
	11	[66]	GETGLOBAL	4 -2	; assert
	12	[66]	GETTABLE 	4 4 -3	; "are"
	13	[66]	GETTABLE 	4 4 -4	; "same"
	14	[66]	MOVE     	5 3
	15	[66]	MOVE     	6 1
	16	[66]	CALL     	4 3 1
	17	[67]	RETURN   	0 1
