
main <./frontend/ui/widget/virtualkeyboard.lua:0,0> (306 instructions, 1224 bytes at 0x7fd558c068f0)
0+ params, 33 slots, 0 upvalues, 28 locals, 131 constants, 35 functions
	1	[1]	GETGLOBAL	0 -1	; require
	2	[1]	LOADK    	1 -2	; "ffi/blitbuffer"
	3	[1]	CALL     	0 2 2
	4	[2]	GETGLOBAL	1 -1	; require
	5	[2]	LOADK    	2 -3	; "ui/widget/container/bottomcontainer"
	6	[2]	CALL     	1 2 2
	7	[3]	GETGLOBAL	2 -1	; require
	8	[3]	LOADK    	3 -4	; "ui/widget/container/centercontainer"
	9	[3]	CALL     	2 2 2
	10	[4]	GETGLOBAL	3 -1	; require
	11	[4]	LOADK    	4 -5	; "device"
	12	[4]	CALL     	3 2 2
	13	[5]	GETGLOBAL	4 -1	; require
	14	[5]	LOADK    	5 -6	; "ui/event"
	15	[5]	CALL     	4 2 2
	16	[6]	GETGLOBAL	5 -1	; require
	17	[6]	LOADK    	6 -7	; "ui/widget/focusmanager"
	18	[6]	CALL     	5 2 2
	19	[7]	GETGLOBAL	6 -1	; require
	20	[7]	LOADK    	7 -8	; "ui/font"
	21	[7]	CALL     	6 2 2
	22	[8]	GETGLOBAL	7 -1	; require
	23	[8]	LOADK    	8 -9	; "ui/widget/container/framecontainer"
	24	[8]	CALL     	7 2 2
	25	[9]	GETGLOBAL	8 -1	; require
	26	[9]	LOADK    	9 -10	; "ui/geometry"
	27	[9]	CALL     	8 2 2
	28	[10]	GETGLOBAL	9 -1	; require
	29	[10]	LOADK    	10 -11	; "ui/gesturerange"
	30	[10]	CALL     	9 2 2
	31	[11]	GETGLOBAL	10 -1	; require
	32	[11]	LOADK    	11 -12	; "ui/widget/horizontalgroup"
	33	[11]	CALL     	10 2 2
	34	[12]	GETGLOBAL	11 -1	; require
	35	[12]	LOADK    	12 -13	; "ui/widget/horizontalspan"
	36	[12]	CALL     	11 2 2
	37	[13]	GETGLOBAL	12 -1	; require
	38	[13]	LOADK    	13 -14	; "ui/widget/imagewidget"
	39	[13]	CALL     	12 2 2
	40	[14]	GETGLOBAL	13 -1	; require
	41	[14]	LOADK    	14 -15	; "ui/widget/container/inputcontainer"
	42	[14]	CALL     	13 2 2
	43	[15]	GETGLOBAL	14 -1	; require
	44	[15]	LOADK    	15 -16	; "ui/widget/keyboardlayoutdialog"
	45	[15]	CALL     	14 2 2
	46	[16]	GETGLOBAL	15 -1	; require
	47	[16]	LOADK    	16 -17	; "ui/size"
	48	[16]	CALL     	15 2 2
	49	[17]	GETGLOBAL	16 -1	; require
	50	[17]	LOADK    	17 -18	; "ui/widget/textwidget"
	51	[17]	CALL     	16 2 2
	52	[18]	GETGLOBAL	17 -1	; require
	53	[18]	LOADK    	18 -19	; "ui/uimanager"
	54	[18]	CALL     	17 2 2
	55	[19]	GETGLOBAL	18 -1	; require
	56	[19]	LOADK    	19 -20	; "ui/widget/verticalgroup"
	57	[19]	CALL     	18 2 2
	58	[20]	GETGLOBAL	19 -1	; require
	59	[20]	LOADK    	20 -21	; "ui/widget/verticalspan"
	60	[20]	CALL     	19 2 2
	61	[21]	GETGLOBAL	20 -1	; require
	62	[21]	LOADK    	21 -22	; "ui/widget/container/widgetcontainer"
	63	[21]	CALL     	20 2 2
	64	[22]	GETGLOBAL	21 -1	; require
	65	[22]	LOADK    	22 -23	; "logger"
	66	[22]	CALL     	21 2 2
	67	[23]	GETGLOBAL	22 -1	; require
	68	[23]	LOADK    	23 -24	; "ffi/util"
	69	[23]	CALL     	22 2 2
	70	[23]	GETTABLE 	22 22 -25	; "orderedPairs"
	71	[24]	GETGLOBAL	23 -1	; require
	72	[24]	LOADK    	24 -26	; "util"
	73	[24]	CALL     	23 2 2
	74	[25]	GETTABLE 	24 3 -27	; "screen"
	75	[27]	LOADNIL  	25 25
	76	[29]	SELF     	26 13 -28	; "new"
	77	[29]	NEWTABLE 	28 0 14
	78	[30]	SETTABLE 	28 -29 -30	; "key" nil
	79	[31]	SETTABLE 	28 -31 -30	; "icon" nil
	80	[32]	SETTABLE 	28 -32 -30	; "label" nil
	81	[33]	SETTABLE 	28 -33 -30	; "bold" nil
	82	[35]	SETTABLE 	28 -34 -30	; "keyboard" nil
	83	[36]	SETTABLE 	28 -35 -30	; "callback" nil
	84	[38]	SETTABLE 	28 -36 -30	; "skiptap" nil
	85	[39]	SETTABLE 	28 -37 -30	; "skiphold" nil
	86	[41]	SETTABLE 	28 -38 -30	; "width" nil
	87	[42]	GETGLOBAL	29 -40	; math
	88	[42]	GETTABLE 	29 29 -41	; "max"
	89	[42]	SELF     	30 24 -42	; "getWidth"
	90	[42]	CALL     	30 2 2
	91	[42]	SELF     	31 24 -43	; "getHeight"
	92	[42]	CALL     	31 2 0
	93	[42]	CALL     	29 0 2
	94	[42]	MUL      	29 29 -44	; - 0.33
	95	[42]	SETTABLE 	28 -39 29	; "height" -
	96	[43]	GETTABLE 	29 15 -46	; "border"
	97	[43]	GETTABLE 	29 29 -47	; "thin"
	98	[43]	SETTABLE 	28 -45 29	; "bordersize" -
	99	[44]	GETTABLE 	29 15 -46	; "border"
	100	[44]	GETTABLE 	29 29 -49	; "default"
	101	[44]	MUL      	29 29 -50	; - 5
	102	[44]	SETTABLE 	28 -48 29	; "focused_bordersize" -
	103	[45]	SETTABLE 	28 -51 -52	; "radius" 0
	104	[46]	SELF     	29 6 -54	; "getFace"
	105	[46]	LOADK    	31 -55	; "infont"
	106	[46]	CALL     	29 3 2
	107	[46]	SETTABLE 	28 -53 29	; "face" -
	108	[29]	CALL     	26 3 2
	109	[219]	CLOSURE  	27 0	; 0x7fd558c070b0
	110	[219]	MOVE     	0 22
	111	[219]	MOVE     	0 23
	112	[219]	MOVE     	0 25
	113	[219]	MOVE     	0 14
	114	[219]	MOVE     	0 17
	115	[219]	MOVE     	0 12
	116	[219]	MOVE     	0 16
	117	[219]	MOVE     	0 7
	118	[219]	MOVE     	0 0
	119	[219]	MOVE     	0 2
	120	[219]	MOVE     	0 8
	121	[219]	MOVE     	0 3
	122	[219]	MOVE     	0 9
	123	[49]	SETTABLE 	26 -56 27	; "init" -
	124	[253]	CLOSURE  	27 1	; 0x7fd558c09a50
	125	[253]	MOVE     	0 14
	126	[253]	MOVE     	0 17
	127	[253]	MOVE     	0 22
	128	[221]	SETTABLE 	26 -57 27	; "genkeyboardLayoutKeyChars" -
	129	[274]	CLOSURE  	27 2	; 0x7fd558c0a2d0
	130	[274]	MOVE     	0 17
	131	[274]	MOVE     	0 21
	132	[255]	SETTABLE 	26 -58 27	; "update_keyboard" -
	133	[278]	CLOSURE  	27 3	; 0x7fd558c0ba60
	134	[276]	SETTABLE 	26 -59 27	; "onFocus" -
	135	[282]	CLOSURE  	27 4	; 0x7fd558c07880
	136	[280]	SETTABLE 	26 -60 27	; "onUnfocus" -
	137	[301]	CLOSURE  	27 5	; 0x7fd558c07950
	138	[301]	MOVE     	0 3
	139	[301]	MOVE     	0 17
	140	[284]	SETTABLE 	26 -61 27	; "onTapSelect" -
	141	[321]	CLOSURE  	27 6	; 0x7fd558c0c7f0
	142	[321]	MOVE     	0 3
	143	[321]	MOVE     	0 17
	144	[303]	SETTABLE 	26 -62 27	; "onHoldSelect" -
	145	[338]	CLOSURE  	27 7	; 0x7fd558c0cc20
	146	[338]	MOVE     	0 3
	147	[338]	MOVE     	0 17
	148	[323]	SETTABLE 	26 -63 27	; "onSwipeKey" -
	149	[352]	CLOSURE  	27 8	; 0x7fd558c0d4f0
	150	[352]	MOVE     	0 3
	151	[340]	SETTABLE 	26 -64 27	; "onHoldReleaseKey" -
	152	[366]	CLOSURE  	27 9	; 0x7fd558c0d990
	153	[366]	MOVE     	0 3
	154	[354]	SETTABLE 	26 -65 27	; "onPanReleaseKey" -
	155	[375]	CLOSURE  	27 10	; 0x7fd558c0de40
	156	[368]	SETTABLE 	26 -66 27	; "invert" -
	157	[377]	SELF     	27 5 -28	; "new"
	158	[377]	NEWTABLE 	29 0 4
	159	[378]	SETTABLE 	29 -67 -68	; "modal" true
	160	[379]	SETTABLE 	29 -69 -68	; "disable_double_tap" true
	161	[380]	SETTABLE 	29 -70 -30	; "inputbox" nil
	162	[381]	NEWTABLE 	30 0 0
	163	[381]	SETTABLE 	29 -71 30	; "layout" -
	164	[377]	CALL     	27 3 2
	165	[382]	MOVE     	25 27
	166	[390]	CLOSURE  	27 11	; 0x7fd558c0e2f0
	167	[390]	MOVE     	0 17
	168	[384]	SETTABLE 	25 -72 27	; "onTapClose" -
	169	[395]	CLOSURE  	27 12	; 0x7fd558c0e4f0
	170	[395]	MOVE     	0 17
	171	[392]	SETTABLE 	25 -73 27	; "onClose" -
	172	[402]	CLOSURE  	27 13	; 0x7fd558c0e5b0
	173	[402]	MOVE     	0 17
	174	[397]	SETTABLE 	25 -74 27	; "onCloseWidget" -
	175	[407]	CLOSURE  	27 14	; 0x7fd558c0f090
	176	[407]	MOVE     	0 4
	177	[404]	SETTABLE 	25 -75 27	; "onPressKey" -
	178	[635]	CLOSURE  	27 15	; 0x7fd558c0f3a0
	179	[635]	MOVE     	0 23
	180	[635]	MOVE     	0 11
	181	[635]	MOVE     	0 19
	182	[635]	MOVE     	0 18
	183	[635]	MOVE     	0 10
	184	[635]	MOVE     	0 26
	185	[635]	MOVE     	0 17
	186	[635]	MOVE     	0 0
	187	[635]	MOVE     	0 7
	188	[635]	MOVE     	0 15
	189	[635]	MOVE     	0 2
	190	[635]	MOVE     	0 8
	191	[635]	MOVE     	0 9
	192	[635]	MOVE     	0 3
	193	[635]	MOVE     	0 20
	194	[635]	MOVE     	0 24
	195	[409]	SETTABLE 	25 -56 27	; "init" -
	196	[637]	SELF     	27 5 -28	; "new"
	197	[637]	NEWTABLE 	29 0 18
	198	[638]	SETTABLE 	29 -67 -68	; "modal" true
	199	[639]	SETTABLE 	29 -69 -68	; "disable_double_tap" true
	200	[640]	SETTABLE 	29 -70 -30	; "inputbox" nil
	201	[641]	NEWTABLE 	30 0 0
	202	[641]	SETTABLE 	29 -76 30	; "KEYS" -
	203	[642]	NEWTABLE 	30 0 0
	204	[642]	SETTABLE 	29 -77 30	; "shiftmode_keys" -
	205	[643]	NEWTABLE 	30 0 0
	206	[643]	SETTABLE 	29 -78 30	; "symbolmode_keys" -
	207	[644]	NEWTABLE 	30 0 0
	208	[644]	SETTABLE 	29 -79 30	; "utf8mode_keys" -
	209	[645]	NEWTABLE 	30 0 0
	210	[645]	SETTABLE 	29 -80 30	; "umlautmode_keys" -
	211	[646]	SETTABLE 	29 -81 -82	; "keyboard_layer" 2
	212	[647]	SETTABLE 	29 -83 -84	; "shiftmode" false
	213	[648]	SETTABLE 	29 -85 -84	; "symbolmode" false
	214	[649]	SETTABLE 	29 -86 -84	; "umlautmode" false
	215	[650]	NEWTABLE 	30 0 0
	216	[650]	SETTABLE 	29 -71 30	; "layout" -
	217	[652]	SELF     	30 24 -87	; "scaleBySize"
	218	[652]	LOADK    	32 -88	; 600
	219	[652]	CALL     	30 3 2
	220	[652]	SETTABLE 	29 -38 30	; "width" -
	221	[653]	SETTABLE 	29 -39 -30	; "height" nil
	222	[654]	GETTABLE 	30 15 -46	; "border"
	223	[654]	GETTABLE 	30 30 -49	; "default"
	224	[654]	SETTABLE 	29 -45 30	; "bordersize" -
	225	[655]	GETTABLE 	30 15 -89	; "padding"
	226	[655]	GETTABLE 	30 30 -90	; "small"
	227	[655]	SETTABLE 	29 -89 30	; "padding" -
	228	[656]	GETTABLE 	30 15 -89	; "padding"
	229	[656]	GETTABLE 	30 30 -49	; "default"
	230	[656]	SETTABLE 	29 -91 30	; "key_padding" -
	231	[658]	NEWTABLE 	30 0 12
	232	[659]	SETTABLE 	30 -93 -94	; "ar_AA" "ar_AA_keyboard"
	233	[660]	SETTABLE 	30 -95 -96	; "el" "el_keyboard"
	234	[661]	SETTABLE 	30 -97 -98	; "en" "en_keyboard"
	235	[662]	SETTABLE 	30 -99 -100	; "es" "es_keyboard"
	236	[663]	SETTABLE 	30 -101 -102	; "fr" "fr_keyboard"
	237	[664]	SETTABLE 	30 -103 -104	; "he" "he_keyboard"
	238	[665]	SETTABLE 	30 -105 -106	; "ja" "ja_keyboard"
	239	[666]	SETTABLE 	30 -107 -108	; "pt_BR" "pt_keyboard"
	240	[667]	SETTABLE 	30 -109 -110	; "ro" "ro_keyboard"
	241	[668]	SETTABLE 	30 -111 -112	; "ko_KR" "ko_KR_keyboard"
	242	[669]	SETTABLE 	30 -113 -114	; "ru" "ru_keyboard"
	243	[670]	SETTABLE 	30 -115 -116	; "tr" "tr_keyboard"
	244	[671]	SETTABLE 	29 -92 30	; "lang_to_keyboard_layout" -
	245	[637]	CALL     	27 3 2
	246	[700]	CLOSURE  	28 16	; 0x7fd558c0f110
	247	[700]	MOVE     	0 24
	248	[700]	MOVE     	0 3
	249	[674]	SETTABLE 	27 -56 28	; "init" -
	250	[704]	CLOSURE  	28 17	; 0x7fd558c0dbd0
	251	[702]	SETTABLE 	27 -117 28	; "getKeyboardLayout" -
	252	[719]	CLOSURE  	28 18	; 0x7fd558c0c280
	253	[706]	SETTABLE 	27 -118 28	; "setKeyboardLayout" -
	254	[724]	CLOSURE  	28 19	; 0x7fd558c10790
	255	[724]	MOVE     	0 17
	256	[721]	SETTABLE 	27 -73 28	; "onClose" -
	257	[729]	CLOSURE  	28 20	; 0x7fd558c0e910
	258	[729]	MOVE     	0 4
	259	[726]	SETTABLE 	27 -75 28	; "onPressKey" -
	260	[743]	CLOSURE  	28 21	; 0x7fd558c10c90
	261	[743]	MOVE     	0 17
	262	[731]	SETTABLE 	27 -119 28	; "_refresh" -
	263	[748]	CLOSURE  	28 22	; 0x7fd558c11790
	264	[745]	SETTABLE 	27 -120 28	; "onShow" -
	265	[753]	CLOSURE  	28 23	; 0x7fd558c11820
	266	[750]	SETTABLE 	27 -74 28	; "onCloseWidget" -
	267	[776]	CLOSURE  	28 24	; 0x7fd558c11a90
	268	[755]	SETTABLE 	27 -121 28	; "initLayer" -
	269	[851]	CLOSURE  	28 25	; 0x7fd558c12170
	270	[851]	MOVE     	0 11
	271	[851]	MOVE     	0 19
	272	[851]	MOVE     	0 18
	273	[851]	MOVE     	0 10
	274	[851]	MOVE     	0 26
	275	[851]	MOVE     	0 7
	276	[851]	MOVE     	0 15
	277	[851]	MOVE     	0 0
	278	[851]	MOVE     	0 2
	279	[851]	MOVE     	0 8
	280	[851]	MOVE     	0 1
	281	[851]	MOVE     	0 24
	282	[778]	SETTABLE 	27 -122 28	; "addKeys" -
	283	[863]	CLOSURE  	28 26	; 0x7fd558c12ca0
	284	[853]	SETTABLE 	27 -123 28	; "setLayer" -
	285	[868]	CLOSURE  	28 27	; 0x7fd558c131e0
	286	[868]	MOVE     	0 21
	287	[865]	SETTABLE 	27 -124 28	; "addChar" -
	288	[873]	CLOSURE  	28 28	; 0x7fd558c12f60
	289	[873]	MOVE     	0 21
	290	[870]	SETTABLE 	27 -125 28	; "delChar" -
	291	[878]	CLOSURE  	28 29	; 0x7fd558c13020
	292	[878]	MOVE     	0 21
	293	[875]	SETTABLE 	27 -126 28	; "delToStartOfLine" -
	294	[882]	CLOSURE  	28 30	; 0x7fd558c13c20
	295	[880]	SETTABLE 	27 -127 28	; "leftChar" -
	296	[886]	CLOSURE  	28 31	; 0x7fd558c14100
	297	[884]	SETTABLE 	27 -128 28	; "rightChar" -
	298	[890]	CLOSURE  	28 32	; 0x7fd558c14190
	299	[888]	SETTABLE 	27 -129 28	; "upLine" -
	300	[894]	CLOSURE  	28 33	; 0x7fd558c14230
	301	[892]	SETTABLE 	27 -130 28	; "downLine" -
	302	[899]	CLOSURE  	28 34	; 0x7fd558c14450
	303	[899]	MOVE     	0 21
	304	[896]	SETTABLE 	27 -131 28	; "clear" -
	305	[901]	RETURN   	27 2
	306	[901]	RETURN   	0 1

function <./frontend/ui/widget/virtualkeyboard.lua:49,219> (281 instructions, 1124 bytes at 0x7fd558c070b0)
1 param, 13 slots, 13 upvalues, 3 locals, 66 constants, 15 functions
	1	[50]	GETTABLE 	1 0 -1	; "keyboard"
	2	[50]	GETTABLE 	1 1 -2	; "symbolmode_keys"
	3	[50]	GETTABLE 	2 0 -3	; "label"
	4	[50]	GETTABLE 	1 1 2
	5	[50]	EQ       	1 1 -4	; - nil
	6	[50]	JMP      	5	; to 12
	7	[51]	CLOSURE  	1 0	; 0x7fd558c07c70
	8	[51]	MOVE     	0 0
	9	[51]	SETTABLE 	0 -5 1	; "callback" -
	10	[52]	SETTABLE 	0 -6 -7	; "skiptap" true
	11	[52]	JMP      	95	; to 107
	12	[53]	GETTABLE 	1 0 -1	; "keyboard"
	13	[53]	GETTABLE 	1 1 -8	; "shiftmode_keys"
	14	[53]	GETTABLE 	2 0 -3	; "label"
	15	[53]	GETTABLE 	1 1 2
	16	[53]	EQ       	1 1 -4	; - nil
	17	[53]	JMP      	5	; to 23
	18	[54]	CLOSURE  	1 1	; 0x7fd558c083a0
	19	[54]	MOVE     	0 0
	20	[54]	SETTABLE 	0 -5 1	; "callback" -
	21	[55]	SETTABLE 	0 -6 -7	; "skiptap" true
	22	[55]	JMP      	84	; to 107
	23	[56]	GETTABLE 	1 0 -1	; "keyboard"
	24	[56]	GETTABLE 	1 1 -9	; "utf8mode_keys"
	25	[56]	GETTABLE 	2 0 -3	; "label"
	26	[56]	GETTABLE 	1 1 2
	27	[56]	EQ       	1 1 -4	; - nil
	28	[56]	JMP      	19	; to 48
	29	[57]	SELF     	1 0 -11	; "genkeyboardLayoutKeyChars"
	30	[57]	CALL     	1 2 2
	31	[57]	SETTABLE 	0 -10 1	; "key_chars" -
	32	[83]	CLOSURE  	1 2	; 0x7fd558c07d20
	33	[83]	GETUPVAL 	0 0	; orderedPairs
	34	[83]	MOVE     	0 0
	35	[83]	SETTABLE 	0 -5 1	; "callback" -
	36	[95]	CLOSURE  	1 3	; 0x7fd558c08120
	37	[95]	GETUPVAL 	0 1	; util
	38	[95]	MOVE     	0 0
	39	[95]	GETUPVAL 	0 2	; VirtualKeyPopup
	40	[95]	GETUPVAL 	0 3	; KeyboardLayoutDialog
	41	[95]	GETUPVAL 	0 4	; UIManager
	42	[95]	SETTABLE 	0 -12 1	; "hold_callback" -
	43	[101]	CLOSURE  	1 4	; 0x7fd558c08790
	44	[101]	MOVE     	0 0
	45	[101]	SETTABLE 	0 -13 1	; "swipe_callback" -
	46	[102]	SETTABLE 	0 -6 -7	; "skiptap" true
	47	[102]	JMP      	59	; to 107
	48	[103]	GETTABLE 	1 0 -1	; "keyboard"
	49	[103]	GETTABLE 	1 1 -14	; "umlautmode_keys"
	50	[103]	GETTABLE 	2 0 -3	; "label"
	51	[103]	GETTABLE 	1 1 2
	52	[103]	EQ       	1 1 -4	; - nil
	53	[103]	JMP      	5	; to 59
	54	[104]	CLOSURE  	1 5	; 0x7fd558c09380
	55	[104]	MOVE     	0 0
	56	[104]	SETTABLE 	0 -5 1	; "callback" -
	57	[105]	SETTABLE 	0 -6 -7	; "skiptap" true
	58	[105]	JMP      	48	; to 107
	59	[106]	GETTABLE 	1 0 -3	; "label"
	60	[106]	EQ       	0 1 -15	; - "\238\157\173"
	61	[106]	JMP      	7	; to 69
	62	[107]	CLOSURE  	1 6	; 0x7fd558c09780
	63	[107]	MOVE     	0 0
	64	[107]	SETTABLE 	0 -5 1	; "callback" -
	65	[111]	CLOSURE  	1 7	; 0x7fd558c09af0
	66	[111]	MOVE     	0 0
	67	[111]	SETTABLE 	0 -12 1	; "hold_callback" -
	68	[111]	JMP      	38	; to 107
	69	[113]	GETTABLE 	1 0 -3	; "label"
	70	[113]	EQ       	0 1 -16	; - "\226\134\144"
	71	[113]	JMP      	4	; to 76
	72	[114]	CLOSURE  	1 8	; 0x7fd558c09c90
	73	[114]	MOVE     	0 0
	74	[114]	SETTABLE 	0 -5 1	; "callback" -
	75	[114]	JMP      	31	; to 107
	76	[115]	GETTABLE 	1 0 -3	; "label"
	77	[115]	EQ       	0 1 -17	; - "\226\134\146"
	78	[115]	JMP      	4	; to 83
	79	[116]	CLOSURE  	1 9	; 0x7fd558c08690
	80	[116]	MOVE     	0 0
	81	[116]	SETTABLE 	0 -5 1	; "callback" -
	82	[116]	JMP      	24	; to 107
	83	[117]	GETTABLE 	1 0 -3	; "label"
	84	[117]	EQ       	0 1 -18	; - "\226\134\145"
	85	[117]	JMP      	4	; to 90
	86	[118]	CLOSURE  	1 10	; 0x7fd558c0a5b0
	87	[118]	MOVE     	0 0
	88	[118]	SETTABLE 	0 -5 1	; "callback" -
	89	[118]	JMP      	17	; to 107
	90	[119]	GETTABLE 	1 0 -3	; "label"
	91	[119]	EQ       	0 1 -19	; - "\226\134\147"
	92	[119]	JMP      	4	; to 97
	93	[120]	CLOSURE  	1 11	; 0x7fd558c0a880
	94	[120]	MOVE     	0 0
	95	[120]	SETTABLE 	0 -5 1	; "callback" -
	96	[120]	JMP      	10	; to 107
	97	[122]	CLOSURE  	1 12	; 0x7fd558c0ab10
	98	[122]	MOVE     	0 0
	99	[122]	SETTABLE 	0 -5 1	; "callback" -
	100	[129]	CLOSURE  	1 13	; 0x7fd558c0adf0
	101	[129]	MOVE     	0 0
	102	[129]	GETUPVAL 	0 2	; VirtualKeyPopup
	103	[129]	SETTABLE 	0 -12 1	; "hold_callback" -
	104	[139]	CLOSURE  	1 14	; 0x7fd558c0b0d0
	105	[139]	MOVE     	0 0
	106	[139]	SETTABLE 	0 -13 1	; "swipe_callback" -
	107	[142]	LOADNIL  	1 1
	108	[143]	GETTABLE 	2 0 -20	; "icon"
	109	[143]	TEST     	2 0 0
	110	[143]	JMP      	21	; to 132
	111	[146]	GETGLOBAL	2 -21	; math
	112	[146]	GETTABLE 	2 2 -22	; "ceil"
	113	[146]	GETTABLE 	3 0 -23	; "face"
	114	[146]	GETTABLE 	3 3 -24	; "size"
	115	[146]	MUL      	3 3 -25	; - 1.5
	116	[146]	CALL     	2 2 2
	117	[147]	GETUPVAL 	3 5	; ImageWidget
	118	[147]	SELF     	3 3 -26	; "new"
	119	[147]	NEWTABLE 	5 0 4
	120	[148]	GETTABLE 	6 0 -20	; "icon"
	121	[148]	SETTABLE 	5 -27 6	; "file" -
	122	[149]	SETTABLE 	5 -28 -29	; "scale_factor" 0
	123	[150]	SETTABLE 	5 -30 2	; "height" -
	124	[151]	GETTABLE 	6 0 -31	; "width"
	125	[151]	GETTABLE 	7 0 -32	; "bordersize"
	126	[151]	MUL      	7 -33 7	; 2 -
	127	[151]	SUB      	6 6 7
	128	[151]	SETTABLE 	5 -31 6	; "width" -
	129	[147]	CALL     	3 3 2
	130	[152]	MOVE     	1 3
	131	[152]	JMP      	14	; to 146
	132	[154]	GETUPVAL 	2 6	; TextWidget
	133	[154]	SELF     	2 2 -26	; "new"
	134	[154]	NEWTABLE 	4 0 3
	135	[155]	GETTABLE 	5 0 -3	; "label"
	136	[155]	SETTABLE 	4 -34 5	; "text" -
	137	[156]	GETTABLE 	5 0 -23	; "face"
	138	[156]	SETTABLE 	4 -23 5	; "face" -
	139	[157]	GETTABLE 	5 0 -35	; "bold"
	140	[157]	TEST     	5 0 1
	141	[157]	JMP      	1	; to 143
	142	[157]	LOADBOOL 	5 0 0
	143	[157]	SETTABLE 	4 -35 5	; "bold" -
	144	[154]	CALL     	2 3 2
	145	[158]	MOVE     	1 2
	146	[160]	GETUPVAL 	2 7	; FrameContainer
	147	[160]	SELF     	2 2 -26	; "new"
	148	[160]	NEWTABLE 	4 0 6
	149	[161]	SETTABLE 	4 -37 -29	; "margin" 0
	150	[162]	GETTABLE 	5 0 -32	; "bordersize"
	151	[162]	SETTABLE 	4 -32 5	; "bordersize" -
	152	[163]	GETUPVAL 	5 8	; Blitbuffer
	153	[163]	GETTABLE 	5 5 -39	; "COLOR_WHITE"
	154	[163]	SETTABLE 	4 -38 5	; "background" -
	155	[164]	SETTABLE 	4 -40 -29	; "radius" 0
	156	[165]	SETTABLE 	4 -41 -29	; "padding" 0
	157	[166]	SETTABLE 	4 -42 -43	; "allow_mirroring" false
	158	[167]	GETUPVAL 	5 9	; CenterContainer
	159	[167]	SELF     	5 5 -26	; "new"
	160	[167]	NEWTABLE 	7 1 1
	161	[168]	GETUPVAL 	8 10	; Geom
	162	[168]	SELF     	8 8 -26	; "new"
	163	[168]	NEWTABLE 	10 0 2
	164	[169]	GETTABLE 	11 0 -31	; "width"
	165	[169]	GETTABLE 	12 0 -32	; "bordersize"
	166	[169]	MUL      	12 -33 12	; 2 -
	167	[169]	SUB      	11 11 12
	168	[169]	SETTABLE 	10 -45 11	; "w" -
	169	[170]	GETTABLE 	11 0 -30	; "height"
	170	[170]	GETTABLE 	12 0 -32	; "bordersize"
	171	[170]	MUL      	12 -33 12	; 2 -
	172	[170]	SUB      	11 11 12
	173	[170]	SETTABLE 	10 -46 11	; "h" -
	174	[168]	CALL     	8 3 2
	175	[171]	SETTABLE 	7 -44 8	; "dimen" -
	176	[173]	MOVE     	8 1
	177	[173]	SETLIST  	7 1 1	; 1
	178	[167]	CALL     	5 3 0
	179	[174]	SETLIST  	4 0 1	; 1
	180	[160]	CALL     	2 3 2
	181	[174]	SETTABLE 	0 -36 2	; 1 -
	182	[175]	GETUPVAL 	2 10	; Geom
	183	[175]	SELF     	2 2 -26	; "new"
	184	[175]	NEWTABLE 	4 0 2
	185	[176]	GETTABLE 	5 0 -31	; "width"
	186	[176]	SETTABLE 	4 -45 5	; "w" -
	187	[177]	GETTABLE 	5 0 -30	; "height"
	188	[177]	SETTABLE 	4 -46 5	; "h" -
	189	[175]	CALL     	2 3 2
	190	[178]	SETTABLE 	0 -44 2	; "dimen" -
	191	[180]	GETUPVAL 	2 11	; Device
	192	[180]	SELF     	2 2 -47	; "isTouchDevice"
	193	[180]	CALL     	2 2 2
	194	[180]	TEST     	2 0 0
	195	[180]	JMP      	52	; to 248
	196	[181]	NEWTABLE 	2 0 5
	197	[182]	NEWTABLE 	3 0 0
	198	[183]	GETUPVAL 	4 12	; GestureRange
	199	[183]	SELF     	4 4 -26	; "new"
	200	[183]	NEWTABLE 	6 0 2
	201	[184]	SETTABLE 	6 -50 -51	; "ges" "tap"
	202	[185]	GETTABLE 	7 0 -44	; "dimen"
	203	[185]	SETTABLE 	6 -52 7	; "range" -
	204	[183]	CALL     	4 3 0
	205	[187]	SETLIST  	3 0 1	; 1
	206	[187]	SETTABLE 	2 -49 3	; "TapSelect" -
	207	[188]	NEWTABLE 	3 0 0
	208	[189]	GETUPVAL 	4 12	; GestureRange
	209	[189]	SELF     	4 4 -26	; "new"
	210	[189]	NEWTABLE 	6 0 2
	211	[190]	SETTABLE 	6 -50 -54	; "ges" "hold"
	212	[191]	GETTABLE 	7 0 -44	; "dimen"
	213	[191]	SETTABLE 	6 -52 7	; "range" -
	214	[189]	CALL     	4 3 0
	215	[193]	SETLIST  	3 0 1	; 1
	216	[193]	SETTABLE 	2 -53 3	; "HoldSelect" -
	217	[194]	NEWTABLE 	3 0 0
	218	[195]	GETUPVAL 	4 12	; GestureRange
	219	[195]	SELF     	4 4 -26	; "new"
	220	[195]	NEWTABLE 	6 0 2
	221	[196]	SETTABLE 	6 -50 -56	; "ges" "hold_release"
	222	[197]	GETTABLE 	7 0 -44	; "dimen"
	223	[197]	SETTABLE 	6 -52 7	; "range" -
	224	[195]	CALL     	4 3 0
	225	[199]	SETLIST  	3 0 1	; 1
	226	[199]	SETTABLE 	2 -55 3	; "HoldReleaseKey" -
	227	[200]	NEWTABLE 	3 0 0
	228	[201]	GETUPVAL 	4 12	; GestureRange
	229	[201]	SELF     	4 4 -26	; "new"
	230	[201]	NEWTABLE 	6 0 2
	231	[202]	SETTABLE 	6 -50 -58	; "ges" "pan_release"
	232	[203]	GETTABLE 	7 0 -44	; "dimen"
	233	[203]	SETTABLE 	6 -52 7	; "range" -
	234	[201]	CALL     	4 3 0
	235	[205]	SETLIST  	3 0 1	; 1
	236	[205]	SETTABLE 	2 -57 3	; "PanReleaseKey" -
	237	[206]	NEWTABLE 	3 0 0
	238	[207]	GETUPVAL 	4 12	; GestureRange
	239	[207]	SELF     	4 4 -26	; "new"
	240	[207]	NEWTABLE 	6 0 2
	241	[208]	SETTABLE 	6 -50 -60	; "ges" "swipe"
	242	[209]	GETTABLE 	7 0 -44	; "dimen"
	243	[209]	SETTABLE 	6 -52 7	; "range" -
	244	[207]	CALL     	4 3 0
	245	[211]	SETLIST  	3 0 1	; 1
	246	[211]	SETTABLE 	2 -59 3	; "SwipeKey" -
	247	[212]	SETTABLE 	0 -48 2	; "ges_events" -
	248	[214]	GETTABLE 	2 0 -1	; "keyboard"
	249	[214]	GETTABLE 	2 2 -8	; "shiftmode_keys"
	250	[214]	GETTABLE 	3 0 -3	; "label"
	251	[214]	GETTABLE 	2 2 3
	252	[214]	EQ       	1 2 -4	; - nil
	253	[214]	JMP      	4	; to 258
	254	[214]	GETTABLE 	2 0 -1	; "keyboard"
	255	[214]	GETTABLE 	2 2 -61	; "shiftmode"
	256	[214]	TEST     	2 0 1
	257	[214]	JMP      	10	; to 268
	258	[215]	GETTABLE 	2 0 -1	; "keyboard"
	259	[215]	GETTABLE 	2 2 -14	; "umlautmode_keys"
	260	[215]	GETTABLE 	3 0 -3	; "label"
	261	[215]	GETTABLE 	2 2 3
	262	[215]	EQ       	1 2 -4	; - nil
	263	[215]	JMP      	8	; to 272
	264	[215]	GETTABLE 	2 0 -1	; "keyboard"
	265	[215]	GETTABLE 	2 2 -62	; "umlautmode"
	266	[215]	TEST     	2 0 0
	267	[215]	JMP      	4	; to 272
	268	[216]	GETTABLE 	2 0 -36	; 1
	269	[216]	GETUPVAL 	3 8	; Blitbuffer
	270	[216]	GETTABLE 	3 3 -63	; "COLOR_LIGHT_GRAY"
	271	[216]	SETTABLE 	2 -38 3	; "background" -
	272	[218]	GETGLOBAL	2 -65	; G_reader_settings
	273	[218]	SELF     	2 2 -66	; "readSetting"
	274	[218]	LOADK    	4 -64	; "flash_keyboard"
	275	[218]	CALL     	2 3 2
	276	[218]	EQ       	0 2 -43	; - false
	277	[218]	JMP      	1	; to 279
	278	[218]	LOADBOOL 	2 0 1
	279	[218]	LOADBOOL 	2 1 0
	280	[218]	SETTABLE 	0 -64 2	; "flash_keyboard" -
	281	[219]	RETURN   	0 1

function <./frontend/ui/widget/virtualkeyboard.lua:51,51> (6 instructions, 24 bytes at 0x7fd558c07c70)
0 params, 3 slots, 1 upvalue, 0 locals, 3 constants, 0 functions
	1	[51]	GETUPVAL 	0 0	; self
	2	[51]	GETTABLE 	0 0 -1	; "keyboard"
	3	[51]	SELF     	0 0 -2	; "setLayer"
	4	[51]	LOADK    	2 -3	; "Sym"
	5	[51]	CALL     	0 3 1
	6	[51]	RETURN   	0 1

function <./frontend/ui/widget/virtualkeyboard.lua:54,54> (6 instructions, 24 bytes at 0x7fd558c083a0)
0 params, 3 slots, 1 upvalue, 0 locals, 3 constants, 0 functions
	1	[54]	GETUPVAL 	0 0	; self
	2	[54]	GETTABLE 	0 0 -1	; "keyboard"
	3	[54]	SELF     	0 0 -2	; "setLayer"
	4	[54]	LOADK    	2 -3	; "Shift"
	5	[54]	CALL     	0 3 1
	6	[54]	RETURN   	0 1

function <./frontend/ui/widget/virtualkeyboard.lua:58,83> (50 instructions, 200 bytes at 0x7fd558c07d20)
0 params, 10 slots, 2 upvalues, 14 locals, 7 constants, 0 functions
	1	[59]	GETGLOBAL	0 -1	; G_reader_settings
	2	[59]	SELF     	0 0 -2	; "readSetting"
	3	[59]	LOADK    	2 -3	; "keyboard_layout"
	4	[59]	CALL     	0 3 2
	5	[60]	GETGLOBAL	1 -1	; G_reader_settings
	6	[60]	SELF     	1 1 -2	; "readSetting"
	7	[60]	LOADK    	3 -4	; "keyboard_layouts"
	8	[60]	CALL     	1 3 2
	9	[60]	TEST     	1 0 1
	10	[60]	JMP      	1	; to 12
	11	[60]	NEWTABLE 	1 0 0
	12	[61]	LOADBOOL 	2 0 0
	13	[62]	LOADNIL  	3 3
	14	[63]	GETUPVAL 	4 0	; orderedPairs
	15	[63]	MOVE     	5 1
	16	[63]	CALL     	4 2 4
	17	[63]	JMP      	9	; to 27
	18	[64]	TEST     	2 0 0
	19	[64]	JMP      	4	; to 24
	20	[64]	EQ       	0 8 -5	; - true
	21	[64]	JMP      	2	; to 24
	22	[65]	MOVE     	3 7
	23	[66]	JMP      	5	; to 29
	24	[68]	EQ       	0 7 0
	25	[68]	JMP      	1	; to 27
	26	[69]	LOADBOOL 	2 1 0
	27	[63]	TFORLOOP 	4 2
	28	[70]	JMP      	-11	; to 18
	29	[72]	TEST     	3 0 1
	30	[72]	JMP      	12	; to 43
	31	[73]	GETUPVAL 	4 0	; orderedPairs
	32	[73]	MOVE     	5 1
	33	[73]	CALL     	4 2 4
	34	[73]	JMP      	6	; to 41
	35	[74]	TEST     	2 0 0
	36	[74]	JMP      	4	; to 41
	37	[74]	EQ       	0 8 -5	; - true
	38	[74]	JMP      	2	; to 41
	39	[75]	MOVE     	3 7
	40	[76]	JMP      	2	; to 43
	41	[73]	TFORLOOP 	4 2
	42	[77]	JMP      	-8	; to 35
	43	[80]	TEST     	3 0 0
	44	[80]	JMP      	5	; to 50
	45	[81]	GETUPVAL 	4 1	; self
	46	[81]	GETTABLE 	4 4 -6	; "keyboard"
	47	[81]	SELF     	4 4 -7	; "setKeyboardLayout"
	48	[81]	MOVE     	6 3
	49	[81]	CALL     	4 3 1
	50	[83]	RETURN   	0 1

function <./frontend/ui/widget/virtualkeyboard.lua:84,95> (30 instructions, 120 bytes at 0x7fd558c08120)
0 params, 5 slots, 5 upvalues, 0 locals, 9 constants, 0 functions
	1	[85]	GETUPVAL 	0 0	; util
	2	[85]	GETTABLE 	0 0 -1	; "tableSize"
	3	[85]	GETUPVAL 	1 1	; self
	4	[85]	GETTABLE 	1 1 -2	; "key_chars"
	5	[85]	CALL     	0 2 2
	6	[85]	LT       	0 -3 0	; 3 -
	7	[85]	JMP      	9	; to 17
	8	[86]	GETUPVAL 	0 1	; self
	9	[86]	GETUPVAL 	1 2	; VirtualKeyPopup
	10	[86]	SELF     	1 1 -5	; "new"
	11	[86]	NEWTABLE 	3 0 1
	12	[87]	GETUPVAL 	4 1	; self
	13	[87]	SETTABLE 	3 -6 4	; "parent_key" -
	14	[86]	CALL     	1 3 2
	15	[88]	SETTABLE 	0 -4 1	; "popup" -
	16	[88]	JMP      	13	; to 30
	17	[90]	GETUPVAL 	0 1	; self
	18	[90]	GETUPVAL 	1 3	; KeyboardLayoutDialog
	19	[90]	SELF     	1 1 -5	; "new"
	20	[90]	NEWTABLE 	3 0 1
	21	[91]	GETUPVAL 	4 1	; self
	22	[91]	SETTABLE 	3 -8 4	; "parent" -
	23	[90]	CALL     	1 3 2
	24	[92]	SETTABLE 	0 -7 1	; "keyboard_layout_dialog" -
	25	[93]	GETUPVAL 	0 4	; UIManager
	26	[93]	SELF     	0 0 -9	; "show"
	27	[93]	GETUPVAL 	2 1	; self
	28	[93]	GETTABLE 	2 2 -7	; "keyboard_layout_dialog"
	29	[93]	CALL     	0 3 1
	30	[95]	RETURN   	0 1

function <./frontend/ui/widget/virtualkeyboard.lua:96,101> (11 instructions, 44 bytes at 0x7fd558c08790)
1 param, 4 slots, 1 upvalue, 2 locals, 3 constants, 0 functions
	1	[97]	GETUPVAL 	1 0	; self
	2	[97]	GETTABLE 	1 1 -1	; "key_chars"
	3	[97]	GETTABLE 	2 0 -2	; "direction"
	4	[97]	LOADK    	3 -3	; "_func"
	5	[97]	CONCAT   	2 2 3
	6	[97]	GETTABLE 	1 1 2
	7	[98]	TEST     	1 0 0
	8	[98]	JMP      	2	; to 11
	9	[99]	MOVE     	2 1
	10	[99]	CALL     	2 1 1
	11	[101]	RETURN   	0 1

function <./frontend/ui/widget/virtualkeyboard.lua:104,104> (6 instructions, 24 bytes at 0x7fd558c09380)
0 params, 3 slots, 1 upvalue, 0 locals, 3 constants, 0 functions
	1	[104]	GETUPVAL 	0 0	; self
	2	[104]	GETTABLE 	0 0 -1	; "keyboard"
	3	[104]	SELF     	0 0 -2	; "setLayer"
	4	[104]	LOADK    	2 -3	; "\195\132\195\169\195\159"
	5	[104]	CALL     	0 3 1
	6	[104]	RETURN   	0 1

function <./frontend/ui/widget/virtualkeyboard.lua:107,107> (5 instructions, 20 bytes at 0x7fd558c09780)
0 params, 2 slots, 1 upvalue, 0 locals, 2 constants, 0 functions
	1	[107]	GETUPVAL 	0 0	; self
	2	[107]	GETTABLE 	0 0 -1	; "keyboard"
	3	[107]	SELF     	0 0 -2	; "delChar"
	4	[107]	CALL     	0 2 1
	5	[107]	RETURN   	0 1

function <./frontend/ui/widget/virtualkeyboard.lua:108,111> (7 instructions, 28 bytes at 0x7fd558c09af0)
0 params, 2 slots, 1 upvalue, 0 locals, 4 constants, 0 functions
	1	[109]	GETUPVAL 	0 0	; self
	2	[109]	SETTABLE 	0 -1 -2	; "ignore_key_release" true
	3	[110]	GETUPVAL 	0 0	; self
	4	[110]	GETTABLE 	0 0 -3	; "keyboard"
	5	[110]	SELF     	0 0 -4	; "delToStartOfLine"
	6	[110]	CALL     	0 2 1
	7	[111]	RETURN   	0 1

function <./frontend/ui/widget/virtualkeyboard.lua:114,114> (5 instructions, 20 bytes at 0x7fd558c09c90)
0 params, 2 slots, 1 upvalue, 0 locals, 2 constants, 0 functions
	1	[114]	GETUPVAL 	0 0	; self
	2	[114]	GETTABLE 	0 0 -1	; "keyboard"
	3	[114]	SELF     	0 0 -2	; "leftChar"
	4	[114]	CALL     	0 2 1
	5	[114]	RETURN   	0 1

function <./frontend/ui/widget/virtualkeyboard.lua:116,116> (5 instructions, 20 bytes at 0x7fd558c08690)
0 params, 2 slots, 1 upvalue, 0 locals, 2 constants, 0 functions
	1	[116]	GETUPVAL 	0 0	; self
	2	[116]	GETTABLE 	0 0 -1	; "keyboard"
	3	[116]	SELF     	0 0 -2	; "rightChar"
	4	[116]	CALL     	0 2 1
	5	[116]	RETURN   	0 1

function <./frontend/ui/widget/virtualkeyboard.lua:118,118> (5 instructions, 20 bytes at 0x7fd558c0a5b0)
0 params, 2 slots, 1 upvalue, 0 locals, 2 constants, 0 functions
	1	[118]	GETUPVAL 	0 0	; self
	2	[118]	GETTABLE 	0 0 -1	; "keyboard"
	3	[118]	SELF     	0 0 -2	; "upLine"
	4	[118]	CALL     	0 2 1
	5	[118]	RETURN   	0 1

function <./frontend/ui/widget/virtualkeyboard.lua:120,120> (5 instructions, 20 bytes at 0x7fd558c0a880)
0 params, 2 slots, 1 upvalue, 0 locals, 2 constants, 0 functions
	1	[120]	GETUPVAL 	0 0	; self
	2	[120]	GETTABLE 	0 0 -1	; "keyboard"
	3	[120]	SELF     	0 0 -2	; "downLine"
	4	[120]	CALL     	0 2 1
	5	[120]	RETURN   	0 1

function <./frontend/ui/widget/virtualkeyboard.lua:122,122> (7 instructions, 28 bytes at 0x7fd558c0ab10)
0 params, 3 slots, 1 upvalue, 0 locals, 3 constants, 0 functions
	1	[122]	GETUPVAL 	0 0	; self
	2	[122]	GETTABLE 	0 0 -1	; "keyboard"
	3	[122]	SELF     	0 0 -2	; "addChar"
	4	[122]	GETUPVAL 	2 0	; self
	5	[122]	GETTABLE 	2 2 -3	; "key"
	6	[122]	CALL     	0 3 1
	7	[122]	RETURN   	0 1

function <./frontend/ui/widget/virtualkeyboard.lua:123,129> (12 instructions, 48 bytes at 0x7fd558c0adf0)
0 params, 4 slots, 2 upvalues, 0 locals, 3 constants, 0 functions
	1	[124]	GETUPVAL 	0 0	; self
	2	[124]	GETTABLE 	0 0 -1	; "key_chars"
	3	[124]	TEST     	0 0 1
	4	[124]	JMP      	1	; to 6
	5	[124]	RETURN   	0 1
	6	[126]	GETUPVAL 	0 1	; VirtualKeyPopup
	7	[126]	SELF     	0 0 -2	; "new"
	8	[126]	NEWTABLE 	2 0 1
	9	[127]	GETUPVAL 	3 0	; self
	10	[127]	SETTABLE 	2 -3 3	; "parent_key" -
	11	[126]	CALL     	0 3 1
	12	[129]	RETURN   	0 1

function <./frontend/ui/widget/virtualkeyboard.lua:130,139> (25 instructions, 100 bytes at 0x7fd558c0b0d0)
1 param, 6 slots, 1 upvalue, 3 locals, 5 constants, 0 functions
	1	[131]	GETUPVAL 	1 0	; self
	2	[131]	GETTABLE 	1 1 -1	; "key_chars"
	3	[131]	GETTABLE 	2 0 -2	; "direction"
	4	[131]	GETTABLE 	1 1 2
	5	[132]	GETUPVAL 	2 0	; self
	6	[132]	GETTABLE 	2 2 -1	; "key_chars"
	7	[132]	GETTABLE 	3 0 -2	; "direction"
	8	[132]	LOADK    	4 -3	; "_func"
	9	[132]	CONCAT   	3 3 4
	10	[132]	GETTABLE 	2 2 3
	11	[134]	TEST     	2 0 1
	12	[134]	JMP      	8	; to 21
	13	[134]	TEST     	1 0 0
	14	[134]	JMP      	6	; to 21
	15	[135]	GETUPVAL 	3 0	; self
	16	[135]	GETTABLE 	3 3 -4	; "keyboard"
	17	[135]	SELF     	3 3 -5	; "addChar"
	18	[135]	MOVE     	5 1
	19	[135]	CALL     	3 3 1
	20	[135]	JMP      	4	; to 25
	21	[136]	TEST     	2 0 0
	22	[136]	JMP      	2	; to 25
	23	[137]	MOVE     	3 2
	24	[137]	CALL     	3 1 1
	25	[139]	RETURN   	0 1

function <./frontend/ui/widget/virtualkeyboard.lua:221,253> (58 instructions, 232 bytes at 0x7fd558c09a50)
1 param, 15 slots, 3 upvalues, 10 locals, 18 constants, 2 functions
	1	[222]	NEWTABLE 	1 4 0
	2	[223]	LOADK    	2 -1	; "northeast"
	3	[224]	LOADK    	3 -2	; "north"
	4	[225]	LOADK    	4 -3	; "northwest"
	5	[227]	LOADK    	5 -4	; "west"
	6	[227]	SETLIST  	1 4 1	; 1
	7	[228]	GETGLOBAL	2 -5	; G_reader_settings
	8	[228]	SELF     	2 2 -6	; "readSetting"
	9	[228]	LOADK    	4 -7	; "keyboard_layouts"
	10	[228]	CALL     	2 3 2
	11	[228]	TEST     	2 0 1
	12	[228]	JMP      	1	; to 14
	13	[228]	NEWTABLE 	2 0 0
	14	[229]	NEWTABLE 	3 1 2
	15	[229]	NEWTABLE 	4 0 1
	16	[230]	SETTABLE 	4 -8 -9	; "label" "\240\159\140\144"
	17	[232]	NEWTABLE 	5 0 1
	18	[232]	SETTABLE 	5 -8 -9	; "label" "\240\159\140\144"
	19	[232]	SETTABLE 	3 -10 5	; "east" -
	20	[238]	CLOSURE  	5 0	; 0x7fd558c09d10
	21	[238]	MOVE     	0 0
	22	[238]	GETUPVAL 	0 0	; KeyboardLayoutDialog
	23	[238]	GETUPVAL 	0 1	; UIManager
	24	[238]	SETTABLE 	3 -11 5	; "east_func" -
	25	[239]	SETLIST  	3 1 1	; 1
	26	[240]	LOADK    	4 -12	; 1
	27	[241]	GETUPVAL 	5 2	; orderedPairs
	28	[241]	MOVE     	6 2
	29	[241]	CALL     	5 2 4
	30	[241]	JMP      	24	; to 55
	31	[242]	EQ       	0 9 -13	; - true
	32	[242]	JMP      	21	; to 54
	33	[243]	GETTABLE 	10 1 4
	34	[243]	GETGLOBAL	11 -14	; string
	35	[243]	GETTABLE 	11 11 -15	; "sub"
	36	[243]	MOVE     	12 8
	37	[243]	LOADK    	13 -12	; 1
	38	[243]	LOADK    	14 -16	; 2
	39	[243]	CALL     	11 4 2
	40	[243]	SETTABLE 	3 10 11
	41	[244]	GETTABLE 	10 1 4
	42	[244]	LOADK    	11 -17	; "_func"
	43	[244]	CONCAT   	10 10 11
	44	[247]	CLOSURE  	11 1	; 0x7fd558c08260
	45	[247]	GETUPVAL 	0 1	; UIManager
	46	[247]	MOVE     	0 0
	47	[247]	MOVE     	0 8
	48	[247]	SETTABLE 	3 10 11
	49	[248]	LE       	0 -18 4	; 4 -
	50	[248]	JMP      	2	; to 53
	51	[248]	CLOSE    	5
	52	[248]	JMP      	4	; to 57
	53	[249]	ADD      	4 4 -12	; - 1
	54	[250]	CLOSE    	8
	55	[241]	TFORLOOP 	5 2
	56	[250]	JMP      	-26	; to 31
	57	[252]	RETURN   	3 2
	58	[253]	RETURN   	0 1

function <./frontend/ui/widget/virtualkeyboard.lua:233,238> (14 instructions, 56 bytes at 0x7fd558c09d10)
0 params, 5 slots, 3 upvalues, 0 locals, 4 constants, 0 functions
	1	[234]	GETUPVAL 	0 0	; self
	2	[234]	GETUPVAL 	1 1	; KeyboardLayoutDialog
	3	[234]	SELF     	1 1 -2	; "new"
	4	[234]	NEWTABLE 	3 0 1
	5	[235]	GETUPVAL 	4 0	; self
	6	[235]	SETTABLE 	3 -3 4	; "parent" -
	7	[234]	CALL     	1 3 2
	8	[236]	SETTABLE 	0 -1 1	; "keyboard_layout_dialog" -
	9	[237]	GETUPVAL 	0 2	; UIManager
	10	[237]	SELF     	0 0 -4	; "show"
	11	[237]	GETUPVAL 	2 0	; self
	12	[237]	GETTABLE 	2 2 -1	; "keyboard_layout_dialog"
	13	[237]	CALL     	0 3 1
	14	[238]	RETURN   	0 1

function <./frontend/ui/widget/virtualkeyboard.lua:244,247> (12 instructions, 48 bytes at 0x7fd558c08260)
0 params, 3 slots, 3 upvalues, 0 locals, 3 constants, 1 function
	1	[245]	GETUPVAL 	0 0	; UIManager
	2	[245]	SELF     	0 0 -1	; "tickAfterNext"
	3	[245]	CLOSURE  	2 0	; 0x7fd558c09910
	4	[245]	GETUPVAL 	0 0	; UIManager
	5	[245]	GETUPVAL 	0 1	; self
	6	[245]	CALL     	0 3 1
	7	[246]	GETUPVAL 	0 1	; self
	8	[246]	GETTABLE 	0 0 -2	; "keyboard"
	9	[246]	SELF     	0 0 -3	; "setKeyboardLayout"
	10	[246]	GETUPVAL 	2 2	; k
	11	[246]	CALL     	0 3 1
	12	[247]	RETURN   	0 1

function <./frontend/ui/widget/virtualkeyboard.lua:245,245> (6 instructions, 24 bytes at 0x7fd558c09910)
0 params, 3 slots, 2 upvalues, 0 locals, 2 constants, 0 functions
	1	[245]	GETUPVAL 	0 0	; UIManager
	2	[245]	SELF     	0 0 -1	; "close"
	3	[245]	GETUPVAL 	2 1	; self
	4	[245]	GETTABLE 	2 2 -2	; "popup"
	5	[245]	CALL     	0 3 1
	6	[245]	RETURN   	0 1

function <./frontend/ui/widget/virtualkeyboard.lua:255,274> (33 instructions, 132 bytes at 0x7fd558c0a2d0)
3 params, 9 slots, 2 upvalues, 4 locals, 9 constants, 2 functions
	1	[258]	TEST     	1 0 0
	2	[258]	JMP      	7	; to 10
	3	[259]	GETUPVAL 	3 0	; UIManager
	4	[259]	SELF     	3 3 -1	; "setDirty"
	5	[259]	GETTABLE 	5 0 -2	; "keyboard"
	6	[261]	CLOSURE  	6 0	; 0x7fd558c09630
	7	[261]	MOVE     	0 0
	8	[259]	CALL     	3 4 1
	9	[261]	JMP      	23	; to 33
	10	[263]	LOADK    	3 -3	; "ui"
	11	[264]	TEST     	2 0 0
	12	[264]	JMP      	1	; to 14
	13	[265]	LOADK    	3 -4	; "fast"
	14	[268]	GETUPVAL 	4 0	; UIManager
	15	[268]	SELF     	4 4 -5	; "widgetRepaint"
	16	[268]	GETTABLE 	6 0 -6	; 1
	17	[268]	GETTABLE 	7 0 -6	; 1
	18	[268]	GETTABLE 	7 7 -7	; "dimen"
	19	[268]	GETTABLE 	7 7 -8	; "x"
	20	[268]	GETTABLE 	8 0 -6	; 1
	21	[268]	GETTABLE 	8 8 -7	; "dimen"
	22	[268]	GETTABLE 	8 8 -9	; "y"
	23	[268]	CALL     	4 5 1
	24	[269]	GETUPVAL 	4 0	; UIManager
	25	[269]	SELF     	4 4 -1	; "setDirty"
	26	[269]	LOADNIL  	6 6
	27	[272]	CLOSURE  	7 1	; 0x7fd558c0bae0
	28	[272]	GETUPVAL 	0 1	; logger
	29	[272]	MOVE     	0 0
	30	[272]	MOVE     	0 3
	31	[269]	CALL     	4 4 1
	32	[272]	CLOSE    	3
	33	[274]	RETURN   	0 1

function <./frontend/ui/widget/virtualkeyboard.lua:259,261> (8 instructions, 32 bytes at 0x7fd558c09630)
0 params, 2 slots, 1 upvalue, 0 locals, 4 constants, 0 functions
	1	[260]	LOADK    	0 -1	; "flashui"
	2	[260]	GETUPVAL 	1 0	; self
	3	[260]	GETTABLE 	1 1 -2	; "keyboard"
	4	[260]	GETTABLE 	1 1 -3	; 1
	5	[260]	GETTABLE 	1 1 -3	; 1
	6	[260]	GETTABLE 	1 1 -4	; "dimen"
	7	[260]	RETURN   	0 3
	8	[261]	RETURN   	0 1

function <./frontend/ui/widget/virtualkeyboard.lua:269,272> (13 instructions, 52 bytes at 0x7fd558c0bae0)
0 params, 3 slots, 3 upvalues, 0 locals, 4 constants, 0 functions
	1	[270]	GETUPVAL 	0 0	; logger
	2	[270]	GETTABLE 	0 0 -1	; "dbg"
	3	[270]	LOADK    	1 -2	; "update key region"
	4	[270]	GETUPVAL 	2 1	; self
	5	[270]	GETTABLE 	2 2 -3	; 1
	6	[270]	GETTABLE 	2 2 -4	; "dimen"
	7	[270]	CALL     	0 3 1
	8	[271]	GETUPVAL 	0 2	; refresh_type
	9	[271]	GETUPVAL 	1 1	; self
	10	[271]	GETTABLE 	1 1 -3	; 1
	11	[271]	GETTABLE 	1 1 -4	; "dimen"
	12	[271]	RETURN   	0 3
	13	[272]	RETURN   	0 1

function <./frontend/ui/widget/virtualkeyboard.lua:276,278> (4 instructions, 16 bytes at 0x7fd558c0ba60)
1 param, 3 slots, 0 upvalues, 1 local, 3 constants, 0 functions
	1	[277]	GETTABLE 	1 0 -1	; 1
	2	[277]	GETTABLE 	2 0 -3	; "focused_bordersize"
	3	[277]	SETTABLE 	1 -2 2	; "inner_bordersize" -
	4	[278]	RETURN   	0 1

function <./frontend/ui/widget/virtualkeyboard.lua:280,282> (3 instructions, 12 bytes at 0x7fd558c07880)
1 param, 2 slots, 0 upvalues, 1 local, 3 constants, 0 functions
	1	[281]	GETTABLE 	1 0 -1	; 1
	2	[281]	SETTABLE 	1 -2 -3	; "inner_bordersize" 0
	3	[282]	RETURN   	0 1

function <./frontend/ui/widget/virtualkeyboard.lua:284,301> (40 instructions, 160 bytes at 0x7fd558c07950)
2 params, 6 slots, 2 upvalues, 2 locals, 13 constants, 1 function
	1	[285]	GETUPVAL 	2 0	; Device
	2	[285]	SELF     	2 2 -1	; "performHapticFeedback"
	3	[285]	LOADK    	4 -2	; "KEYBOARD_TAP"
	4	[285]	CALL     	2 3 1
	5	[287]	GETTABLE 	2 0 -3	; "keyboard"
	6	[287]	SETTABLE 	2 -4 -5	; "ignore_first_hold_release" false
	7	[288]	GETTABLE 	2 0 -6	; "flash_keyboard"
	8	[288]	TEST     	2 0 0
	9	[288]	JMP      	23	; to 33
	10	[288]	TEST     	1 0 1
	11	[288]	JMP      	21	; to 33
	12	[288]	GETTABLE 	2 0 -7	; "skiptap"
	13	[288]	TEST     	2 0 1
	14	[288]	JMP      	18	; to 33
	15	[289]	GETTABLE 	2 0 -8	; 1
	16	[289]	GETTABLE 	3 0 -10	; "focused_bordersize"
	17	[289]	SETTABLE 	2 -9 3	; "inner_bordersize" -
	18	[290]	SELF     	2 0 -11	; "update_keyboard"
	19	[290]	LOADBOOL 	4 0 0
	20	[290]	LOADBOOL 	5 1 0
	21	[290]	CALL     	2 4 1
	22	[291]	GETTABLE 	2 0 -12	; "callback"
	23	[291]	TEST     	2 0 0
	24	[291]	JMP      	2	; to 27
	25	[292]	GETTABLE 	2 0 -12	; "callback"
	26	[292]	CALL     	2 1 1
	27	[294]	GETUPVAL 	2 1	; UIManager
	28	[294]	SELF     	2 2 -13	; "tickAfterNext"
	29	[294]	CLOSURE  	4 0	; 0x7fd558c0c870
	30	[294]	MOVE     	0 0
	31	[294]	CALL     	2 3 1
	32	[294]	JMP      	5	; to 38
	33	[296]	GETTABLE 	2 0 -12	; "callback"
	34	[296]	TEST     	2 0 0
	35	[296]	JMP      	2	; to 38
	36	[297]	GETTABLE 	2 0 -12	; "callback"
	37	[297]	CALL     	2 1 1
	38	[300]	LOADBOOL 	2 1 0
	39	[300]	RETURN   	2 2
	40	[301]	RETURN   	0 1

function <./frontend/ui/widget/virtualkeyboard.lua:294,294> (5 instructions, 20 bytes at 0x7fd558c0c870)
0 params, 3 slots, 1 upvalue, 0 locals, 1 constant, 0 functions
	1	[294]	GETUPVAL 	0 0	; self
	2	[294]	SELF     	0 0 -1	; "invert"
	3	[294]	LOADBOOL 	2 0 0
	4	[294]	CALL     	0 3 1
	5	[294]	RETURN   	0 1

function <./frontend/ui/widget/virtualkeyboard.lua:303,321> (39 instructions, 156 bytes at 0x7fd558c0c7f0)
1 param, 5 slots, 2 upvalues, 1 local, 11 constants, 1 function
	1	[304]	GETUPVAL 	1 0	; Device
	2	[304]	SELF     	1 1 -1	; "performHapticFeedback"
	3	[304]	LOADK    	3 -2	; "LONG_PRESS"
	4	[304]	CALL     	1 3 1
	5	[305]	GETTABLE 	1 0 -3	; "flash_keyboard"
	6	[305]	TEST     	1 0 0
	7	[305]	JMP      	24	; to 32
	8	[305]	GETTABLE 	1 0 -4	; "skiphold"
	9	[305]	TEST     	1 0 1
	10	[305]	JMP      	21	; to 32
	11	[306]	GETTABLE 	1 0 -5	; 1
	12	[306]	GETTABLE 	2 0 -7	; "focused_bordersize"
	13	[306]	SETTABLE 	1 -6 2	; "inner_bordersize" -
	14	[307]	SELF     	1 0 -8	; "update_keyboard"
	15	[307]	LOADBOOL 	3 0 0
	16	[307]	LOADBOOL 	4 1 0
	17	[307]	CALL     	1 4 1
	18	[309]	GETTABLE 	1 0 -9	; "hold_callback"
	19	[309]	TEST     	1 0 0
	20	[309]	JMP      	5	; to 26
	21	[310]	GETTABLE 	1 0 -5	; 1
	22	[310]	SETTABLE 	1 -6 -10	; "inner_bordersize" 0
	23	[311]	GETTABLE 	1 0 -9	; "hold_callback"
	24	[311]	CALL     	1 1 1
	25	[311]	JMP      	11	; to 37
	26	[313]	GETUPVAL 	1 1	; UIManager
	27	[313]	SELF     	1 1 -11	; "tickAfterNext"
	28	[313]	CLOSURE  	3 0	; 0x7fd558c0ccf0
	29	[313]	MOVE     	0 0
	30	[313]	CALL     	1 3 1
	31	[314]	JMP      	5	; to 37
	32	[316]	GETTABLE 	1 0 -9	; "hold_callback"
	33	[316]	TEST     	1 0 0
	34	[316]	JMP      	2	; to 37
	35	[317]	GETTABLE 	1 0 -9	; "hold_callback"
	36	[317]	CALL     	1 1 1
	37	[320]	LOADBOOL 	1 1 0
	38	[320]	RETURN   	1 2
	39	[321]	RETURN   	0 1

function <./frontend/ui/widget/virtualkeyboard.lua:313,313> (6 instructions, 24 bytes at 0x7fd558c0ccf0)
0 params, 4 slots, 1 upvalue, 0 locals, 1 constant, 0 functions
	1	[313]	GETUPVAL 	0 0	; self
	2	[313]	SELF     	0 0 -1	; "invert"
	3	[313]	LOADBOOL 	2 0 0
	4	[313]	LOADBOOL 	3 1 0
	5	[313]	CALL     	0 4 1
	6	[313]	RETURN   	0 1

function <./frontend/ui/widget/virtualkeyboard.lua:323,338> (38 instructions, 152 bytes at 0x7fd558c0cc20)
3 params, 7 slots, 2 upvalues, 3 locals, 10 constants, 1 function
	1	[324]	GETUPVAL 	3 0	; Device
	2	[324]	SELF     	3 3 -1	; "performHapticFeedback"
	3	[324]	LOADK    	5 -2	; "KEYBOARD_TAP"
	4	[324]	CALL     	3 3 1
	5	[325]	GETTABLE 	3 0 -3	; "flash_keyboard"
	6	[325]	TEST     	3 0 0
	7	[325]	JMP      	22	; to 30
	8	[325]	GETTABLE 	3 0 -4	; "skipswipe"
	9	[325]	TEST     	3 0 1
	10	[325]	JMP      	19	; to 30
	11	[326]	GETTABLE 	3 0 -5	; 1
	12	[326]	GETTABLE 	4 0 -7	; "focused_bordersize"
	13	[326]	SETTABLE 	3 -6 4	; "inner_bordersize" -
	14	[327]	SELF     	3 0 -8	; "update_keyboard"
	15	[327]	LOADBOOL 	5 0 0
	16	[327]	LOADBOOL 	6 1 0
	17	[327]	CALL     	3 4 1
	18	[328]	GETTABLE 	3 0 -9	; "swipe_callback"
	19	[328]	TEST     	3 0 0
	20	[328]	JMP      	3	; to 24
	21	[329]	GETTABLE 	3 0 -9	; "swipe_callback"
	22	[329]	MOVE     	4 2
	23	[329]	CALL     	3 2 1
	24	[331]	GETUPVAL 	3 1	; UIManager
	25	[331]	SELF     	3 3 -10	; "tickAfterNext"
	26	[331]	CLOSURE  	5 0	; 0x7fd558c0d3f0
	27	[331]	MOVE     	0 0
	28	[331]	CALL     	3 3 1
	29	[331]	JMP      	6	; to 36
	30	[333]	GETTABLE 	3 0 -9	; "swipe_callback"
	31	[333]	TEST     	3 0 0
	32	[333]	JMP      	3	; to 36
	33	[334]	GETTABLE 	3 0 -9	; "swipe_callback"
	34	[334]	MOVE     	4 2
	35	[334]	CALL     	3 2 1
	36	[337]	LOADBOOL 	3 1 0
	37	[337]	RETURN   	3 2
	38	[338]	RETURN   	0 1

function <./frontend/ui/widget/virtualkeyboard.lua:331,331> (6 instructions, 24 bytes at 0x7fd558c0d3f0)
0 params, 4 slots, 1 upvalue, 0 locals, 1 constant, 0 functions
	1	[331]	GETUPVAL 	0 0	; self
	2	[331]	SELF     	0 0 -1	; "invert"
	3	[331]	LOADBOOL 	2 0 0
	4	[331]	LOADBOOL 	3 0 0
	5	[331]	CALL     	0 4 1
	6	[331]	RETURN   	0 1

function <./frontend/ui/widget/virtualkeyboard.lua:340,352> (23 instructions, 92 bytes at 0x7fd558c0d4f0)
1 param, 4 slots, 1 upvalue, 1 local, 8 constants, 0 functions
	1	[341]	GETTABLE 	1 0 -1	; "ignore_key_release"
	2	[341]	TEST     	1 0 0
	3	[341]	JMP      	3	; to 7
	4	[342]	SETTABLE 	0 -1 -2	; "ignore_key_release" nil
	5	[343]	LOADBOOL 	1 1 0
	6	[343]	RETURN   	1 2
	7	[345]	GETUPVAL 	1 0	; Device
	8	[345]	SELF     	1 1 -3	; "performHapticFeedback"
	9	[345]	LOADK    	3 -4	; "LONG_PRESS"
	10	[345]	CALL     	1 3 1
	11	[346]	GETTABLE 	1 0 -5	; "keyboard"
	12	[346]	GETTABLE 	1 1 -6	; "ignore_first_hold_release"
	13	[346]	TEST     	1 0 0
	14	[346]	JMP      	4	; to 19
	15	[347]	GETTABLE 	1 0 -5	; "keyboard"
	16	[347]	SETTABLE 	1 -6 -7	; "ignore_first_hold_release" false
	17	[348]	LOADBOOL 	1 1 0
	18	[348]	RETURN   	1 2
	19	[350]	SELF     	1 0 -8	; "onTapSelect"
	20	[350]	CALL     	1 2 1
	21	[351]	LOADBOOL 	1 1 0
	22	[351]	RETURN   	1 2
	23	[352]	RETURN   	0 1

function <./frontend/ui/widget/virtualkeyboard.lua:354,366> (23 instructions, 92 bytes at 0x7fd558c0d990)
1 param, 4 slots, 1 upvalue, 1 local, 8 constants, 0 functions
	1	[355]	GETTABLE 	1 0 -1	; "ignore_key_release"
	2	[355]	TEST     	1 0 0
	3	[355]	JMP      	3	; to 7
	4	[356]	SETTABLE 	0 -1 -2	; "ignore_key_release" nil
	5	[357]	LOADBOOL 	1 1 0
	6	[357]	RETURN   	1 2
	7	[359]	GETUPVAL 	1 0	; Device
	8	[359]	SELF     	1 1 -3	; "performHapticFeedback"
	9	[359]	LOADK    	3 -4	; "LONG_PRESS"
	10	[359]	CALL     	1 3 1
	11	[360]	GETTABLE 	1 0 -5	; "keyboard"
	12	[360]	GETTABLE 	1 1 -6	; "ignore_first_hold_release"
	13	[360]	TEST     	1 0 0
	14	[360]	JMP      	4	; to 19
	15	[361]	GETTABLE 	1 0 -5	; "keyboard"
	16	[361]	SETTABLE 	1 -6 -7	; "ignore_first_hold_release" false
	17	[362]	LOADBOOL 	1 1 0
	18	[362]	RETURN   	1 2
	19	[364]	SELF     	1 0 -8	; "onTapSelect"
	20	[364]	CALL     	1 2 1
	21	[365]	LOADBOOL 	1 1 0
	22	[365]	RETURN   	1 2
	23	[366]	RETURN   	0 1

function <./frontend/ui/widget/virtualkeyboard.lua:368,375> (13 instructions, 52 bytes at 0x7fd558c0de40)
3 params, 7 slots, 0 upvalues, 3 locals, 5 constants, 0 functions
	1	[369]	TEST     	1 0 0
	2	[369]	JMP      	4	; to 7
	3	[370]	GETTABLE 	3 0 -1	; 1
	4	[370]	GETTABLE 	4 0 -3	; "focused_bordersize"
	5	[370]	SETTABLE 	3 -2 4	; "inner_bordersize" -
	6	[370]	JMP      	2	; to 9
	7	[372]	GETTABLE 	3 0 -1	; 1
	8	[372]	SETTABLE 	3 -2 -4	; "inner_bordersize" 0
	9	[374]	SELF     	3 0 -5	; "update_keyboard"
	10	[374]	MOVE     	5 2
	11	[374]	LOADBOOL 	6 0 0
	12	[374]	CALL     	3 4 1
	13	[375]	RETURN   	0 1

function <./frontend/ui/widget/virtualkeyboard.lua:384,390> (17 instructions, 68 bytes at 0x7fd558c0e2f0)
3 params, 6 slots, 1 upvalue, 3 locals, 5 constants, 0 functions
	1	[385]	GETTABLE 	3 2 -1	; "pos"
	2	[385]	SELF     	3 3 -2	; "notIntersectWith"
	3	[385]	GETTABLE 	5 0 -3	; 1
	4	[385]	GETTABLE 	5 5 -3	; 1
	5	[385]	GETTABLE 	5 5 -4	; "dimen"
	6	[385]	CALL     	3 3 2
	7	[385]	TEST     	3 0 0
	8	[385]	JMP      	6	; to 15
	9	[386]	GETUPVAL 	3 0	; UIManager
	10	[386]	SELF     	3 3 -5	; "close"
	11	[386]	MOVE     	5 0
	12	[386]	CALL     	3 3 1
	13	[387]	LOADBOOL 	3 1 0
	14	[387]	RETURN   	3 2
	15	[389]	LOADBOOL 	3 0 0
	16	[389]	RETURN   	3 2
	17	[390]	RETURN   	0 1

function <./frontend/ui/widget/virtualkeyboard.lua:392,395> (7 instructions, 28 bytes at 0x7fd558c0e4f0)
1 param, 4 slots, 1 upvalue, 1 local, 1 constant, 0 functions
	1	[393]	GETUPVAL 	1 0	; UIManager
	2	[393]	SELF     	1 1 -1	; "close"
	3	[393]	MOVE     	3 0
	4	[393]	CALL     	1 3 1
	5	[394]	LOADBOOL 	1 1 0
	6	[394]	RETURN   	1 2
	7	[395]	RETURN   	0 1

function <./frontend/ui/widget/virtualkeyboard.lua:397,402> (9 instructions, 36 bytes at 0x7fd558c0e5b0)
1 param, 5 slots, 1 upvalue, 1 local, 2 constants, 1 function
	1	[398]	SELF     	1 0 -1	; "free"
	2	[398]	CALL     	1 2 1
	3	[399]	GETUPVAL 	1 0	; UIManager
	4	[399]	SELF     	1 1 -2	; "setDirty"
	5	[399]	LOADNIL  	3 3
	6	[401]	CLOSURE  	4 0	; 0x7fd558c0ed30
	7	[401]	MOVE     	0 0
	8	[399]	CALL     	1 4 1
	9	[402]	RETURN   	0 1

function <./frontend/ui/widget/virtualkeyboard.lua:399,401> (7 instructions, 28 bytes at 0x7fd558c0ed30)
0 params, 2 slots, 1 upvalue, 0 locals, 3 constants, 0 functions
	1	[400]	LOADK    	0 -1	; "ui"
	2	[400]	GETUPVAL 	1 0	; self
	3	[400]	GETTABLE 	1 1 -2	; 1
	4	[400]	GETTABLE 	1 1 -2	; 1
	5	[400]	GETTABLE 	1 1 -3	; "dimen"
	6	[400]	RETURN   	0 3
	7	[401]	RETURN   	0 1

function <./frontend/ui/widget/virtualkeyboard.lua:404,407> (11 instructions, 44 bytes at 0x7fd558c0f090)
1 param, 6 slots, 1 upvalue, 1 local, 4 constants, 0 functions
	1	[405]	SELF     	1 0 -1	; "getFocusItem"
	2	[405]	CALL     	1 2 2
	3	[405]	SELF     	1 1 -2	; "handleEvent"
	4	[405]	GETUPVAL 	3 0	; Event
	5	[405]	SELF     	3 3 -3	; "new"
	6	[405]	LOADK    	5 -4	; "TapSelect"
	7	[405]	CALL     	3 3 0
	8	[405]	CALL     	1 0 1
	9	[406]	LOADBOOL 	1 1 0
	10	[406]	RETURN   	1 2
	11	[407]	RETURN   	0 1

function <./frontend/ui/widget/virtualkeyboard.lua:409,635> (429 instructions, 1716 bytes at 0x7fd558c0f3a0)
1 param, 29 slots, 16 upvalues, 22 locals, 74 constants, 2 functions
	1	[410]	GETTABLE 	1 0 -1	; "parent_key"
	2	[411]	GETTABLE 	2 1 -2	; "key_chars"
	3	[412]	GETTABLE 	3 2 -3	; 1
	4	[413]	GETTABLE 	4 1 -4	; "callback"
	5	[415]	NEWTABLE 	5 0 4
	6	[416]	NEWTABLE 	6 6 0
	7	[417]	GETTABLE 	7 2 -6	; 2
	8	[418]	GETTABLE 	8 2 -7	; 3
	9	[419]	GETTABLE 	9 2 -8	; 4
	10	[421]	GETTABLE 	10 2 -9	; 5
	11	[422]	GETTABLE 	11 2 -10	; 6
	12	[424]	GETTABLE 	12 2 -11	; 7
	13	[424]	SETLIST  	6 6 1	; 1
	14	[424]	SETTABLE 	5 -5 6	; "extra_key_chars" -
	15	[425]	NEWTABLE 	6 6 0
	16	[426]	GETTABLE 	7 2 -13	; "northwest"
	17	[427]	GETTABLE 	8 2 -14	; "north"
	18	[428]	GETTABLE 	9 2 -15	; "northeast"
	19	[429]	GETTABLE 	10 2 -16	; "northwest_func"
	20	[430]	GETTABLE 	11 2 -17	; "north_func"
	21	[432]	GETTABLE 	12 2 -18	; "northeast_func"
	22	[432]	SETLIST  	6 6 1	; 1
	23	[432]	SETTABLE 	5 -12 6	; "top_key_chars" -
	24	[433]	NEWTABLE 	6 6 0
	25	[434]	GETTABLE 	7 2 -20	; "west"
	26	[435]	MOVE     	8 3
	27	[436]	GETTABLE 	9 2 -21	; "east"
	28	[437]	GETTABLE 	10 2 -22	; "west_func"
	29	[438]	MOVE     	11 4
	30	[440]	GETTABLE 	12 2 -23	; "east_func"
	31	[440]	SETLIST  	6 6 1	; 1
	32	[440]	SETTABLE 	5 -19 6	; "middle_key_chars" -
	33	[441]	NEWTABLE 	6 6 0
	34	[442]	GETTABLE 	7 2 -25	; "southwest"
	35	[443]	GETTABLE 	8 2 -26	; "south"
	36	[444]	GETTABLE 	9 2 -27	; "southeast"
	37	[445]	GETTABLE 	10 2 -28	; "southwest_func"
	38	[446]	GETTABLE 	11 2 -29	; "south_func"
	39	[448]	GETTABLE 	12 2 -30	; "southeast_func"
	40	[448]	SETLIST  	6 6 1	; 1
	41	[448]	SETTABLE 	5 -24 6	; "bottom_key_chars" -
	42	[450]	GETUPVAL 	6 0	; util
	43	[450]	GETTABLE 	6 6 -31	; "tableSize"
	44	[450]	GETTABLE 	7 5 -5	; "extra_key_chars"
	45	[450]	CALL     	6 2 2
	46	[450]	EQ       	0 6 -32	; - 0
	47	[450]	JMP      	1	; to 49
	48	[450]	SETTABLE 	5 -5 -33	; "extra_key_chars" nil
	49	[451]	GETUPVAL 	6 0	; util
	50	[451]	GETTABLE 	6 6 -31	; "tableSize"
	51	[451]	GETTABLE 	7 5 -12	; "top_key_chars"
	52	[451]	CALL     	6 2 2
	53	[451]	EQ       	0 6 -32	; - 0
	54	[451]	JMP      	1	; to 56
	55	[451]	SETTABLE 	5 -12 -33	; "top_key_chars" nil
	56	[453]	GETUPVAL 	6 0	; util
	57	[453]	GETTABLE 	6 6 -31	; "tableSize"
	58	[453]	GETTABLE 	7 5 -24	; "bottom_key_chars"
	59	[453]	CALL     	6 2 2
	60	[453]	EQ       	0 6 -32	; - 0
	61	[453]	JMP      	1	; to 63
	62	[453]	SETTABLE 	5 -24 -33	; "bottom_key_chars" nil
	63	[456]	NEWTABLE 	6 0 0
	64	[457]	NEWTABLE 	7 2 0
	65	[458]	GETUPVAL 	8 1	; HorizontalSpan
	66	[458]	SELF     	8 8 -34	; "new"
	67	[458]	NEWTABLE 	10 0 1
	68	[458]	SETTABLE 	10 -35 -32	; "width" 0
	69	[458]	CALL     	8 3 2
	70	[459]	GETUPVAL 	9 1	; HorizontalSpan
	71	[459]	SELF     	9 9 -34	; "new"
	72	[459]	NEWTABLE 	11 0 1
	73	[459]	GETTABLE 	12 1 -35	; "width"
	74	[459]	SETTABLE 	11 -35 12	; "width" -
	75	[459]	CALL     	9 3 2
	76	[460]	GETUPVAL 	10 1	; HorizontalSpan
	77	[460]	SELF     	10 10 -34	; "new"
	78	[460]	NEWTABLE 	12 0 1
	79	[460]	SETTABLE 	12 -35 -32	; "width" 0
	80	[460]	CALL     	10 3 0
	81	[461]	SETLIST  	7 0 1	; 1
	82	[462]	NEWTABLE 	8 2 0
	83	[463]	GETUPVAL 	9 1	; HorizontalSpan
	84	[463]	SELF     	9 9 -34	; "new"
	85	[463]	NEWTABLE 	11 0 1
	86	[463]	SETTABLE 	11 -35 -32	; "width" 0
	87	[463]	CALL     	9 3 2
	88	[464]	GETUPVAL 	10 1	; HorizontalSpan
	89	[464]	SELF     	10 10 -34	; "new"
	90	[464]	NEWTABLE 	12 0 1
	91	[464]	GETTABLE 	13 1 -36	; "keyboard"
	92	[464]	GETTABLE 	13 13 -37	; "key_padding"
	93	[464]	SETTABLE 	12 -35 13	; "width" -
	94	[464]	CALL     	10 3 2
	95	[465]	GETUPVAL 	11 1	; HorizontalSpan
	96	[465]	SELF     	11 11 -34	; "new"
	97	[465]	NEWTABLE 	13 0 1
	98	[465]	SETTABLE 	13 -35 -32	; "width" 0
	99	[465]	CALL     	11 3 0
	100	[466]	SETLIST  	8 0 1	; 1
	101	[467]	GETUPVAL 	9 2	; VerticalSpan
	102	[467]	SELF     	9 9 -34	; "new"
	103	[467]	NEWTABLE 	11 0 1
	104	[467]	GETTABLE 	12 1 -36	; "keyboard"
	105	[467]	GETTABLE 	12 12 -37	; "key_padding"
	106	[467]	SETTABLE 	11 -35 12	; "width" -
	107	[467]	CALL     	9 3 2
	108	[469]	GETUPVAL 	10 3	; VerticalGroup
	109	[469]	SELF     	10 10 -34	; "new"
	110	[469]	NEWTABLE 	12 0 1
	111	[469]	SETTABLE 	12 -38 -39	; "allow_mirroring" false
	112	[469]	CALL     	10 3 2
	113	[470]	GETUPVAL 	11 4	; HorizontalGroup
	114	[470]	SELF     	11 11 -34	; "new"
	115	[470]	NEWTABLE 	13 0 1
	116	[470]	SETTABLE 	13 -38 -39	; "allow_mirroring" false
	117	[470]	CALL     	11 3 2
	118	[471]	GETUPVAL 	12 4	; HorizontalGroup
	119	[471]	SELF     	12 12 -34	; "new"
	120	[471]	NEWTABLE 	14 0 1
	121	[471]	SETTABLE 	14 -38 -39	; "allow_mirroring" false
	122	[471]	CALL     	12 3 2
	123	[472]	GETUPVAL 	13 4	; HorizontalGroup
	124	[472]	SELF     	13 13 -34	; "new"
	125	[472]	NEWTABLE 	15 0 1
	126	[472]	SETTABLE 	15 -38 -39	; "allow_mirroring" false
	127	[472]	CALL     	13 3 2
	128	[473]	GETUPVAL 	14 4	; HorizontalGroup
	129	[473]	SELF     	14 14 -34	; "new"
	130	[473]	NEWTABLE 	16 0 1
	131	[473]	SETTABLE 	16 -38 -39	; "allow_mirroring" false
	132	[473]	CALL     	14 3 2
	133	[540]	CLOSURE  	15 0	; 0x7fd558c10040
	134	[540]	MOVE     	0 6
	135	[540]	MOVE     	0 7
	136	[540]	MOVE     	0 8
	137	[540]	GETUPVAL 	0 5	; VirtualKey
	138	[540]	MOVE     	0 1
	139	[540]	MOVE     	0 2
	140	[540]	GETUPVAL 	0 6	; UIManager
	141	[540]	MOVE     	0 0
	142	[540]	MOVE     	0 3
	143	[540]	GETUPVAL 	0 7	; Blitbuffer
	144	[540]	MOVE     	0 10
	145	[541]	GETTABLE 	16 5 -5	; "extra_key_chars"
	146	[541]	TEST     	16 0 0
	147	[541]	JMP      	9	; to 157
	148	[542]	MOVE     	16 15
	149	[542]	GETTABLE 	17 5 -5	; "extra_key_chars"
	150	[542]	MOVE     	18 11
	151	[542]	CALL     	16 3 1
	152	[543]	GETGLOBAL	16 -40	; table
	153	[543]	GETTABLE 	16 16 -41	; "insert"
	154	[543]	MOVE     	17 10
	155	[543]	MOVE     	18 9
	156	[543]	CALL     	16 3 1
	157	[545]	GETTABLE 	16 5 -12	; "top_key_chars"
	158	[545]	TEST     	16 0 0
	159	[545]	JMP      	9	; to 169
	160	[546]	MOVE     	16 15
	161	[546]	GETTABLE 	17 5 -12	; "top_key_chars"
	162	[546]	MOVE     	18 12
	163	[546]	CALL     	16 3 1
	164	[547]	GETGLOBAL	16 -40	; table
	165	[547]	GETTABLE 	16 16 -41	; "insert"
	166	[547]	MOVE     	17 10
	167	[547]	MOVE     	18 9
	168	[547]	CALL     	16 3 1
	169	[550]	MOVE     	16 15
	170	[550]	GETTABLE 	17 5 -19	; "middle_key_chars"
	171	[550]	MOVE     	18 13
	172	[550]	CALL     	16 3 1
	173	[551]	GETTABLE 	16 5 -24	; "bottom_key_chars"
	174	[551]	TEST     	16 0 0
	175	[551]	JMP      	9	; to 185
	176	[552]	GETGLOBAL	16 -40	; table
	177	[552]	GETTABLE 	16 16 -41	; "insert"
	178	[552]	MOVE     	17 10
	179	[552]	MOVE     	18 9
	180	[552]	CALL     	16 3 1
	181	[553]	MOVE     	16 15
	182	[553]	GETTABLE 	17 5 -24	; "bottom_key_chars"
	183	[553]	MOVE     	18 14
	184	[553]	CALL     	16 3 1
	185	[556]	GETTABLE 	16 6 -7	; 3
	186	[556]	TEST     	16 0 1
	187	[556]	JMP      	2	; to 190
	188	[557]	GETTABLE 	16 8 -6	; 2
	189	[557]	SETTABLE 	16 -35 -32	; "width" 0
	190	[560]	GETUPVAL 	16 0	; util
	191	[560]	GETTABLE 	16 16 -31	; "tableSize"
	192	[560]	MOVE     	17 5
	193	[560]	CALL     	16 2 2
	194	[561]	GETUPVAL 	17 0	; util
	195	[561]	GETTABLE 	17 17 -31	; "tableSize"
	196	[561]	MOVE     	18 6
	197	[561]	CALL     	17 2 2
	198	[563]	GETUPVAL 	18 8	; FrameContainer
	199	[563]	SELF     	18 18 -34	; "new"
	200	[563]	NEWTABLE 	20 0 6
	201	[564]	SETTABLE 	20 -42 -32	; "margin" 0
	202	[565]	GETUPVAL 	21 9	; Size
	203	[565]	GETTABLE 	21 21 -44	; "border"
	204	[565]	GETTABLE 	21 21 -45	; "default"
	205	[565]	SETTABLE 	20 -43 21	; "bordersize" -
	206	[566]	GETUPVAL 	21 7	; Blitbuffer
	207	[566]	GETTABLE 	21 21 -47	; "COLOR_WHITE"
	208	[566]	SETTABLE 	20 -46 21	; "background" -
	209	[567]	SETTABLE 	20 -48 -32	; "radius" 0
	210	[568]	GETTABLE 	21 1 -36	; "keyboard"
	211	[568]	GETTABLE 	21 21 -49	; "padding"
	212	[568]	SETTABLE 	20 -49 21	; "padding" -
	213	[569]	SETTABLE 	20 -38 -39	; "allow_mirroring" false
	214	[570]	GETUPVAL 	21 10	; CenterContainer
	215	[570]	SELF     	21 21 -34	; "new"
	216	[570]	NEWTABLE 	23 1 1
	217	[571]	GETUPVAL 	24 11	; Geom
	218	[571]	SELF     	24 24 -34	; "new"
	219	[571]	NEWTABLE 	26 0 2
	220	[572]	GETTABLE 	27 1 -35	; "width"
	221	[572]	MUL      	27 27 17
	222	[572]	GETUPVAL 	28 9	; Size
	223	[572]	GETTABLE 	28 28 -44	; "border"
	224	[572]	GETTABLE 	28 28 -45	; "default"
	225	[572]	MUL      	28 -6 28	; 2 -
	226	[572]	ADD      	27 27 28
	227	[572]	GETTABLE 	28 1 -36	; "keyboard"
	228	[572]	GETTABLE 	28 28 -37	; "key_padding"
	229	[572]	MUL      	28 17 28
	230	[572]	ADD      	27 27 28
	231	[572]	SETTABLE 	26 -51 27	; "w" -
	232	[573]	GETTABLE 	27 1 -53	; "height"
	233	[573]	MUL      	27 27 16
	234	[573]	GETUPVAL 	28 9	; Size
	235	[573]	GETTABLE 	28 28 -44	; "border"
	236	[573]	GETTABLE 	28 28 -45	; "default"
	237	[573]	MUL      	28 -6 28	; 2 -
	238	[573]	ADD      	27 27 28
	239	[573]	GETTABLE 	28 1 -36	; "keyboard"
	240	[573]	GETTABLE 	28 28 -37	; "key_padding"
	241	[573]	MUL      	28 16 28
	242	[573]	ADD      	27 27 28
	243	[573]	SETTABLE 	26 -52 27	; "h" -
	244	[571]	CALL     	24 3 2
	245	[574]	SETTABLE 	23 -50 24	; "dimen" -
	246	[576]	MOVE     	24 10
	247	[576]	SETLIST  	23 1 1	; 1
	248	[570]	CALL     	21 3 0
	249	[577]	SETLIST  	20 0 1	; 1
	250	[563]	CALL     	18 3 2
	251	[578]	SELF     	19 18 -54	; "getSize"
	252	[578]	CALL     	19 2 2
	253	[578]	SETTABLE 	18 -50 19	; "dimen" -
	254	[580]	NEWTABLE 	19 0 1
	255	[581]	NEWTABLE 	20 0 0
	256	[582]	GETUPVAL 	21 12	; GestureRange
	257	[582]	SELF     	21 21 -34	; "new"
	258	[582]	NEWTABLE 	23 0 1
	259	[583]	SETTABLE 	23 -57 -58	; "ges" "tap"
	260	[582]	CALL     	21 3 0
	261	[585]	SETLIST  	20 0 1	; 1
	262	[585]	SETTABLE 	19 -56 20	; "TapClose" -
	263	[586]	SETTABLE 	0 -55 19	; "ges_events" -
	264	[588]	GETUPVAL 	19 13	; Device
	265	[588]	SELF     	19 19 -59	; "hasDPad"
	266	[588]	CALL     	19 2 2
	267	[588]	TEST     	19 0 0
	268	[588]	JMP      	8	; to 277
	269	[589]	GETTABLE 	19 0 -60	; "key_events"
	270	[589]	NEWTABLE 	20 1 1
	271	[589]	NEWTABLE 	21 1 0
	272	[589]	LOADK    	22 -62	; "Press"
	273	[589]	SETLIST  	21 1 1	; 1
	274	[589]	SETTABLE 	20 -63 -64	; "doc" "select key"
	275	[589]	SETLIST  	20 1 1	; 1
	276	[589]	SETTABLE 	19 -61 20	; "PressKey" -
	277	[591]	GETUPVAL 	19 13	; Device
	278	[591]	SELF     	19 19 -65	; "hasKeys"
	279	[591]	CALL     	19 2 2
	280	[591]	TEST     	19 0 0
	281	[591]	JMP      	8	; to 290
	282	[592]	GETTABLE 	19 0 -60	; "key_events"
	283	[592]	NEWTABLE 	20 1 1
	284	[592]	NEWTABLE 	21 1 0
	285	[592]	LOADK    	22 -67	; "Back"
	286	[592]	SETLIST  	21 1 1	; 1
	287	[592]	SETTABLE 	20 -63 -68	; "doc" "close keyboard"
	288	[592]	SETLIST  	20 1 1	; 1
	289	[592]	SETTABLE 	19 -66 20	; "Close" -
	290	[595]	GETTABLE 	19 1 -36	; "keyboard"
	291	[595]	GETTABLE 	19 19 -49	; "padding"
	292	[595]	MUL      	19 -6 19	; 2 -
	293	[595]	GETTABLE 	20 1 -36	; "keyboard"
	294	[595]	GETTABLE 	20 20 -43	; "bordersize"
	295	[595]	MUL      	20 -6 20	; 2 -
	296	[595]	ADD      	19 19 20
	297	[596]	GETTABLE 	20 6 -3	; 1
	298	[596]	TEST     	20 0 0
	299	[596]	JMP      	9	; to 309
	300	[597]	GETTABLE 	20 1 -35	; "width"
	301	[597]	ADD      	20 19 20
	302	[597]	GETTABLE 	21 1 -36	; "keyboard"
	303	[597]	GETTABLE 	21 21 -49	; "padding"
	304	[597]	ADD      	20 20 21
	305	[597]	GETTABLE 	21 1 -36	; "keyboard"
	306	[597]	GETTABLE 	21 21 -43	; "bordersize"
	307	[597]	MUL      	21 -6 21	; 2 -
	308	[597]	ADD      	19 20 21
	309	[600]	GETTABLE 	20 1 -36	; "keyboard"
	310	[600]	GETTABLE 	20 20 -49	; "padding"
	311	[600]	GETTABLE 	21 1 -36	; "keyboard"
	312	[600]	GETTABLE 	21 21 -49	; "padding"
	313	[600]	ADD      	20 20 21
	314	[600]	GETTABLE 	21 1 -36	; "keyboard"
	315	[600]	GETTABLE 	21 21 -43	; "bordersize"
	316	[600]	MUL      	21 -6 21	; 2 -
	317	[600]	ADD      	20 20 21
	318	[601]	GETTABLE 	21 5 -5	; "extra_key_chars"
	319	[601]	TEST     	21 0 0
	320	[601]	JMP      	9	; to 330
	321	[602]	GETTABLE 	21 1 -53	; "height"
	322	[602]	ADD      	21 20 21
	323	[602]	GETTABLE 	22 1 -36	; "keyboard"
	324	[602]	GETTABLE 	22 22 -49	; "padding"
	325	[602]	ADD      	21 21 22
	326	[602]	GETTABLE 	22 1 -36	; "keyboard"
	327	[602]	GETTABLE 	22 22 -43	; "bordersize"
	328	[602]	MUL      	22 -6 22	; 2 -
	329	[602]	ADD      	20 21 22
	330	[604]	GETTABLE 	21 5 -12	; "top_key_chars"
	331	[604]	TEST     	21 0 0
	332	[604]	JMP      	9	; to 342
	333	[605]	GETTABLE 	21 1 -53	; "height"
	334	[605]	ADD      	21 20 21
	335	[605]	GETTABLE 	22 1 -36	; "keyboard"
	336	[605]	GETTABLE 	22 22 -49	; "padding"
	337	[605]	ADD      	21 21 22
	338	[605]	GETTABLE 	22 1 -36	; "keyboard"
	339	[605]	GETTABLE 	22 22 -43	; "bordersize"
	340	[605]	MUL      	22 -6 22	; 2 -
	341	[605]	ADD      	20 21 22
	342	[608]	GETUPVAL 	21 14	; WidgetContainer
	343	[608]	SELF     	21 21 -34	; "new"
	344	[608]	NEWTABLE 	23 1 1
	345	[609]	NEWTABLE 	24 0 4
	346	[610]	GETTABLE 	25 1 -50	; "dimen"
	347	[610]	GETTABLE 	25 25 -69	; "x"
	348	[610]	SUB      	25 25 19
	349	[610]	SETTABLE 	24 -69 25	; "x" -
	350	[611]	GETTABLE 	25 1 -50	; "dimen"
	351	[611]	GETTABLE 	25 25 -70	; "y"
	352	[611]	SUB      	25 25 20
	353	[611]	SETTABLE 	24 -70 25	; "y" -
	354	[612]	GETUPVAL 	25 15	; Screen
	355	[612]	SELF     	25 25 -54	; "getSize"
	356	[612]	CALL     	25 2 2
	357	[612]	GETTABLE 	25 25 -52	; "h"
	358	[612]	SETTABLE 	24 -52 25	; "h" -
	359	[613]	GETUPVAL 	25 15	; Screen
	360	[613]	SELF     	25 25 -54	; "getSize"
	361	[613]	CALL     	25 2 2
	362	[613]	GETTABLE 	25 25 -51	; "w"
	363	[613]	SETTABLE 	24 -51 25	; "w" -
	364	[614]	SETTABLE 	23 -50 24	; "dimen" -
	365	[616]	MOVE     	24 18
	366	[616]	SETLIST  	23 1 1	; 1
	367	[608]	CALL     	21 3 2
	368	[617]	GETTABLE 	22 21 -50	; "dimen"
	369	[617]	GETTABLE 	22 22 -69	; "x"
	370	[617]	LT       	0 22 -32	; - 0
	371	[617]	JMP      	3	; to 375
	372	[618]	GETTABLE 	22 21 -50	; "dimen"
	373	[618]	SETTABLE 	22 -69 -32	; "x" 0
	374	[618]	JMP      	18	; to 393
	375	[619]	GETTABLE 	22 21 -50	; "dimen"
	376	[619]	GETTABLE 	22 22 -69	; "x"
	377	[619]	GETTABLE 	23 18 -50	; "dimen"
	378	[619]	GETTABLE 	23 23 -51	; "w"
	379	[619]	ADD      	22 22 23
	380	[619]	GETUPVAL 	23 15	; Screen
	381	[619]	SELF     	23 23 -71	; "getWidth"
	382	[619]	CALL     	23 2 2
	383	[619]	LT       	0 23 22
	384	[619]	JMP      	8	; to 393
	385	[620]	GETTABLE 	22 21 -50	; "dimen"
	386	[620]	GETUPVAL 	23 15	; Screen
	387	[620]	SELF     	23 23 -71	; "getWidth"
	388	[620]	CALL     	23 2 2
	389	[620]	GETTABLE 	24 18 -50	; "dimen"
	390	[620]	GETTABLE 	24 24 -51	; "w"
	391	[620]	SUB      	23 23 24
	392	[620]	SETTABLE 	22 -69 23	; "x" -
	393	[622]	GETTABLE 	22 21 -50	; "dimen"
	394	[622]	GETTABLE 	22 22 -70	; "y"
	395	[622]	LT       	0 22 -32	; - 0
	396	[622]	JMP      	3	; to 400
	397	[623]	GETTABLE 	22 21 -50	; "dimen"
	398	[623]	SETTABLE 	22 -70 -32	; "y" 0
	399	[623]	JMP      	18	; to 418
	400	[624]	GETTABLE 	22 21 -50	; "dimen"
	401	[624]	GETTABLE 	22 22 -70	; "y"
	402	[624]	GETTABLE 	23 18 -50	; "dimen"
	403	[624]	GETTABLE 	23 23 -52	; "h"
	404	[624]	ADD      	22 22 23
	405	[624]	GETUPVAL 	23 15	; Screen
	406	[624]	SELF     	23 23 -72	; "getHeight"
	407	[624]	CALL     	23 2 2
	408	[624]	LT       	0 23 22
	409	[624]	JMP      	8	; to 418
	410	[625]	GETTABLE 	22 21 -50	; "dimen"
	411	[625]	GETUPVAL 	23 15	; Screen
	412	[625]	SELF     	23 23 -72	; "getHeight"
	413	[625]	CALL     	23 2 2
	414	[625]	GETTABLE 	24 18 -50	; "dimen"
	415	[625]	GETTABLE 	24 24 -52	; "h"
	416	[625]	SUB      	23 23 24
	417	[625]	SETTABLE 	22 -70 23	; "y" -
	418	[628]	SETTABLE 	0 -3 21	; 1 -
	419	[630]	GETUPVAL 	22 6	; UIManager
	420	[630]	SELF     	22 22 -73	; "show"
	421	[630]	MOVE     	24 0
	422	[630]	CALL     	22 3 1
	423	[632]	GETUPVAL 	22 6	; UIManager
	424	[632]	SELF     	22 22 -74	; "setDirty"
	425	[632]	MOVE     	24 0
	426	[634]	CLOSURE  	25 1	; 0x7fd558c0fdb0
	427	[634]	MOVE     	0 18
	428	[632]	CALL     	22 4 1
	429	[635]	RETURN   	0 1

function <./frontend/ui/widget/virtualkeyboard.lua:475,540> (147 instructions, 588 bytes at 0x7fd558c10040)
2 params, 17 slots, 11 upvalues, 14 locals, 27 constants, 2 functions
	1	[476]	NEWTABLE 	2 0 0
	2	[478]	LOADK    	3 -1	; 1
	3	[478]	LOADK    	4 -2	; 3
	4	[478]	LOADK    	5 -1	; 1
	5	[478]	FORPREP  	3 129	; to 135
	6	[479]	GETTABLE 	7 0 6
	7	[480]	ADD      	8 6 -2	; - 3
	8	[480]	GETTABLE 	8 0 8
	9	[482]	TEST     	7 0 0
	10	[482]	JMP      	112	; to 123
	11	[483]	GETUPVAL 	9 0	; columns
	12	[483]	SETTABLE 	9 6 -3	; - true
	13	[484]	GETUPVAL 	9 1	; blank
	14	[484]	GETTABLE 	9 9 6
	15	[484]	GETUPVAL 	10 1	; blank
	16	[484]	GETTABLE 	10 10 -5	; 2
	17	[484]	GETTABLE 	10 10 -4	; "width"
	18	[484]	SETTABLE 	9 -4 10	; "width" -
	19	[485]	EQ       	0 6 -1	; - 1
	20	[485]	JMP      	6	; to 27
	21	[486]	GETUPVAL 	9 2	; h_key_padding
	22	[486]	GETTABLE 	9 9 6
	23	[486]	GETUPVAL 	10 2	; h_key_padding
	24	[486]	GETTABLE 	10 10 -5	; 2
	25	[486]	GETTABLE 	10 10 -4	; "width"
	26	[486]	SETTABLE 	9 -4 10	; "width" -
	27	[489]	GETGLOBAL	9 -6	; type
	28	[489]	MOVE     	10 7
	29	[489]	CALL     	9 2 2
	30	[489]	EQ       	0 9 -7	; - "table"
	31	[489]	JMP      	3	; to 35
	32	[489]	GETTABLE 	9 7 -8	; "key"
	33	[489]	TEST     	9 0 1
	34	[489]	JMP      	1	; to 36
	35	[489]	MOVE     	9 7
	36	[490]	GETGLOBAL	10 -6	; type
	37	[490]	MOVE     	11 7
	38	[490]	CALL     	10 2 2
	39	[490]	EQ       	0 10 -7	; - "table"
	40	[490]	JMP      	3	; to 44
	41	[490]	GETTABLE 	10 7 -9	; "label"
	42	[490]	TEST     	10 0 1
	43	[490]	JMP      	1	; to 45
	44	[490]	MOVE     	10 9
	45	[491]	GETGLOBAL	11 -6	; type
	46	[491]	MOVE     	12 7
	47	[491]	CALL     	11 2 2
	48	[491]	EQ       	0 11 -7	; - "table"
	49	[491]	JMP      	2	; to 52
	50	[491]	GETTABLE 	11 7 -10	; "icon"
	51	[491]	JMP      	2	; to 54
	52	[491]	LOADBOOL 	11 0 1
	53	[491]	LOADBOOL 	11 1 0
	54	[492]	GETGLOBAL	12 -6	; type
	55	[492]	MOVE     	13 7
	56	[492]	CALL     	12 2 2
	57	[492]	EQ       	0 12 -7	; - "table"
	58	[492]	JMP      	2	; to 61
	59	[492]	GETTABLE 	12 7 -11	; "bold"
	60	[492]	JMP      	2	; to 63
	61	[492]	LOADBOOL 	12 0 1
	62	[492]	LOADBOOL 	12 1 0
	63	[493]	GETUPVAL 	13 3	; VirtualKey
	64	[493]	SELF     	13 13 -12	; "new"
	65	[493]	NEWTABLE 	15 0 8
	66	[494]	SETTABLE 	15 -8 9	; "key" -
	67	[495]	SETTABLE 	15 -9 10	; "label" -
	68	[496]	SETTABLE 	15 -10 11	; "icon" -
	69	[497]	SETTABLE 	15 -11 12	; "bold" -
	70	[498]	GETUPVAL 	16 4	; parent_key
	71	[498]	GETTABLE 	16 16 -13	; "keyboard"
	72	[498]	SETTABLE 	15 -13 16	; "keyboard" -
	73	[499]	GETUPVAL 	16 5	; key_chars
	74	[499]	SETTABLE 	15 -14 16	; "key_chars" -
	75	[500]	GETUPVAL 	16 4	; parent_key
	76	[500]	GETTABLE 	16 16 -4	; "width"
	77	[500]	SETTABLE 	15 -4 16	; "width" -
	78	[501]	GETUPVAL 	16 4	; parent_key
	79	[501]	GETTABLE 	16 16 -15	; "height"
	80	[501]	SETTABLE 	15 -15 16	; "height" -
	81	[493]	CALL     	13 3 2
	82	[504]	TEST     	8 0 0
	83	[504]	JMP      	1	; to 85
	84	[505]	SETTABLE 	13 -16 8	; "callback" -
	85	[508]	SETTABLE 	13 -17 -18	; "hold_callback" nil
	86	[514]	CLOSURE  	14 0	; 0x7fd558c10180
	87	[514]	MOVE     	0 13
	88	[514]	GETUPVAL 	0 6	; UIManager
	89	[514]	GETUPVAL 	0 7	; self
	90	[514]	SETTABLE 	13 -19 14	; "onHoldReleaseKey" -
	91	[515]	GETTABLE 	14 13 -19	; "onHoldReleaseKey"
	92	[515]	SETTABLE 	13 -20 14	; "onPanReleaseKey" -
	93	[517]	GETUPVAL 	14 8	; key_char_orig
	94	[517]	EQ       	0 7 14
	95	[517]	JMP      	15	; to 111
	96	[518]	GETTABLE 	14 13 -1	; 1
	97	[518]	GETUPVAL 	15 9	; Blitbuffer
	98	[518]	GETTABLE 	15 15 -22	; "COLOR_LIGHT_GRAY"
	99	[518]	SETTABLE 	14 -21 15	; "background" -
	100	[524]	CLOSURE  	14 1	; 0x7fd558c0c980
	101	[524]	MOVE     	0 13
	102	[524]	SETTABLE 	13 -23 14	; "_keyOrigHoldPanHandler" -
	103	[525]	GETTABLE 	14 13 -19	; "onHoldReleaseKey"
	104	[525]	SETTABLE 	13 -24 14	; "_onHoldReleaseKey" -
	105	[526]	GETTABLE 	14 13 -23	; "_keyOrigHoldPanHandler"
	106	[526]	SETTABLE 	13 -19 14	; "onHoldReleaseKey" -
	107	[527]	GETTABLE 	14 13 -20	; "onPanReleaseKey"
	108	[527]	SETTABLE 	13 -25 14	; "_onPanReleaseKey" -
	109	[528]	GETTABLE 	14 13 -23	; "_keyOrigHoldPanHandler"
	110	[528]	SETTABLE 	13 -20 14	; "onPanReleaseKey" -
	111	[531]	GETGLOBAL	14 -7	; table
	112	[531]	GETTABLE 	14 14 -26	; "insert"
	113	[531]	MOVE     	15 1
	114	[531]	MOVE     	16 13
	115	[531]	CALL     	14 3 1
	116	[532]	GETGLOBAL	14 -7	; table
	117	[532]	GETTABLE 	14 14 -26	; "insert"
	118	[532]	MOVE     	15 2
	119	[532]	MOVE     	16 13
	120	[532]	CALL     	14 3 1
	121	[532]	CLOSE    	9
	122	[532]	JMP      	6	; to 129
	123	[534]	GETGLOBAL	9 -7	; table
	124	[534]	GETTABLE 	9 9 -26	; "insert"
	125	[534]	MOVE     	10 1
	126	[534]	GETUPVAL 	11 1	; blank
	127	[534]	GETTABLE 	11 11 6
	128	[534]	CALL     	9 3 1
	129	[536]	GETGLOBAL	9 -7	; table
	130	[536]	GETTABLE 	9 9 -26	; "insert"
	131	[536]	MOVE     	10 1
	132	[536]	GETUPVAL 	11 2	; h_key_padding
	133	[536]	GETTABLE 	11 11 6
	134	[536]	CALL     	9 3 1
	135	[478]	FORLOOP  	3 -130	; to 6
	136	[538]	GETGLOBAL	3 -7	; table
	137	[538]	GETTABLE 	3 3 -26	; "insert"
	138	[538]	GETUPVAL 	4 10	; vertical_group
	139	[538]	MOVE     	5 1
	140	[538]	CALL     	3 3 1
	141	[539]	GETGLOBAL	3 -7	; table
	142	[539]	GETTABLE 	3 3 -26	; "insert"
	143	[539]	GETUPVAL 	4 7	; self
	144	[539]	GETTABLE 	4 4 -27	; "layout"
	145	[539]	MOVE     	5 2
	146	[539]	CALL     	3 3 1
	147	[540]	RETURN   	0 1

function <./frontend/ui/widget/virtualkeyboard.lua:510,514> (11 instructions, 44 bytes at 0x7fd558c10180)
0 params, 3 slots, 3 upvalues, 0 locals, 2 constants, 0 functions
	1	[511]	GETUPVAL 	0 0	; virtual_key
	2	[511]	SELF     	0 0 -1	; "onTapSelect"
	3	[511]	LOADBOOL 	2 1 0
	4	[511]	CALL     	0 3 1
	5	[512]	GETUPVAL 	0 1	; UIManager
	6	[512]	SELF     	0 0 -2	; "close"
	7	[512]	GETUPVAL 	2 2	; self
	8	[512]	CALL     	0 3 1
	9	[513]	LOADBOOL 	0 1 0
	10	[513]	RETURN   	0 2
	11	[514]	RETURN   	0 1

function <./frontend/ui/widget/virtualkeyboard.lua:521,524> (9 instructions, 36 bytes at 0x7fd558c0c980)
0 params, 2 slots, 1 upvalue, 0 locals, 4 constants, 0 functions
	1	[522]	GETUPVAL 	0 0	; virtual_key
	2	[522]	GETUPVAL 	1 0	; virtual_key
	3	[522]	GETTABLE 	1 1 -2	; "_onHoldReleaseKey"
	4	[522]	SETTABLE 	0 -1 1	; "onHoldReleaseKey" -
	5	[523]	GETUPVAL 	0 0	; virtual_key
	6	[523]	GETUPVAL 	1 0	; virtual_key
	7	[523]	GETTABLE 	1 1 -4	; "_onPanReleaseKey"
	8	[523]	SETTABLE 	0 -3 1	; "onPanReleaseKey" -
	9	[524]	RETURN   	0 1

function <./frontend/ui/widget/virtualkeyboard.lua:632,634> (5 instructions, 20 bytes at 0x7fd558c0fdb0)
0 params, 2 slots, 1 upvalue, 0 locals, 2 constants, 0 functions
	1	[633]	LOADK    	0 -1	; "ui"
	2	[633]	GETUPVAL 	1 0	; keyboard_frame
	3	[633]	GETTABLE 	1 1 -2	; "dimen"
	4	[633]	RETURN   	0 3
	5	[634]	RETURN   	0 1

function <./frontend/ui/widget/virtualkeyboard.lua:674,700> (80 instructions, 320 bytes at 0x7fd558c0f110)
1 param, 8 slots, 2 upvalues, 4 locals, 32 constants, 0 functions
	1	[675]	GETTABLE 	1 0 -1	; "uwrap_func"
	2	[675]	TEST     	1 0 0
	3	[675]	JMP      	3	; to 7
	4	[676]	GETTABLE 	1 0 -1	; "uwrap_func"
	5	[676]	CALL     	1 1 1
	6	[677]	SETTABLE 	0 -1 -2	; "uwrap_func" nil
	7	[679]	SELF     	1 0 -3	; "getKeyboardLayout"
	8	[679]	CALL     	1 2 2
	9	[680]	GETTABLE 	2 0 -4	; "lang_to_keyboard_layout"
	10	[680]	GETTABLE 	2 2 1
	11	[680]	TEST     	2 0 1
	12	[680]	JMP      	2	; to 15
	13	[680]	GETTABLE 	2 0 -4	; "lang_to_keyboard_layout"
	14	[680]	GETTABLE 	2 2 -5	; "en"
	15	[681]	GETGLOBAL	3 -6	; require
	16	[681]	LOADK    	4 -7	; "ui/data/keyboardlayouts/"
	17	[681]	MOVE     	5 2
	18	[681]	CONCAT   	4 4 5
	19	[681]	CALL     	3 2 2
	20	[682]	GETTABLE 	4 3 -9	; "keys"
	21	[682]	SETTABLE 	0 -8 4	; "KEYS" -
	22	[683]	GETTABLE 	4 3 -10	; "shiftmode_keys"
	23	[683]	SETTABLE 	0 -10 4	; "shiftmode_keys" -
	24	[684]	GETTABLE 	4 3 -11	; "symbolmode_keys"
	25	[684]	SETTABLE 	0 -11 4	; "symbolmode_keys" -
	26	[685]	GETTABLE 	4 3 -12	; "utf8mode_keys"
	27	[685]	SETTABLE 	0 -12 4	; "utf8mode_keys" -
	28	[686]	GETTABLE 	4 3 -13	; "umlautmode_keys"
	29	[686]	SETTABLE 	0 -13 4	; "umlautmode_keys" -
	30	[687]	GETUPVAL 	4 0	; Screen
	31	[687]	SELF     	4 4 -15	; "scaleBySize"
	32	[687]	GETTABLE 	6 0 -8	; "KEYS"
	33	[687]	LEN      	6 6
	34	[687]	MUL      	6 -16 6	; 64 -
	35	[687]	CALL     	4 3 2
	36	[687]	SETTABLE 	0 -14 4	; "height" -
	37	[688]	GETTABLE 	4 3 -17	; "min_layer"
	38	[688]	SETTABLE 	0 -17 4	; "min_layer" -
	39	[689]	GETTABLE 	4 3 -18	; "max_layer"
	40	[689]	SETTABLE 	0 -18 4	; "max_layer" -
	41	[690]	SELF     	4 0 -19	; "initLayer"
	42	[690]	GETTABLE 	6 0 -20	; "keyboard_layer"
	43	[690]	CALL     	4 3 1
	44	[691]	GETUPVAL 	4 1	; Device
	45	[691]	SELF     	4 4 -21	; "hasDPad"
	46	[691]	CALL     	4 2 2
	47	[691]	TEST     	4 0 0
	48	[691]	JMP      	8	; to 57
	49	[692]	GETTABLE 	4 0 -22	; "key_events"
	50	[692]	NEWTABLE 	5 1 1
	51	[692]	NEWTABLE 	6 1 0
	52	[692]	LOADK    	7 -24	; "Press"
	53	[692]	SETLIST  	6 1 1	; 1
	54	[692]	SETTABLE 	5 -25 -26	; "doc" "select key"
	55	[692]	SETLIST  	5 1 1	; 1
	56	[692]	SETTABLE 	4 -23 5	; "PressKey" -
	57	[694]	GETUPVAL 	4 1	; Device
	58	[694]	SELF     	4 4 -27	; "hasKeys"
	59	[694]	CALL     	4 2 2
	60	[694]	TEST     	4 0 0
	61	[694]	JMP      	8	; to 70
	62	[695]	GETTABLE 	4 0 -22	; "key_events"
	63	[695]	NEWTABLE 	5 1 1
	64	[695]	NEWTABLE 	6 1 0
	65	[695]	LOADK    	7 -29	; "Back"
	66	[695]	SETLIST  	6 1 1	; 1
	67	[695]	SETTABLE 	5 -25 -30	; "doc" "close keyboard"
	68	[695]	SETLIST  	5 1 1	; 1
	69	[695]	SETTABLE 	4 -28 5	; "Close" -
	70	[697]	GETTABLE 	4 3 -31	; "wrapInputBox"
	71	[697]	TEST     	4 0 0
	72	[697]	JMP      	7	; to 80
	73	[698]	GETTABLE 	4 3 -31	; "wrapInputBox"
	74	[698]	GETTABLE 	5 0 -32	; "inputbox"
	75	[698]	CALL     	4 2 2
	76	[698]	TEST     	4 0 1
	77	[698]	JMP      	1	; to 79
	78	[698]	GETTABLE 	4 0 -1	; "uwrap_func"
	79	[698]	SETTABLE 	0 -1 4	; "uwrap_func" -
	80	[700]	RETURN   	0 1

function <./frontend/ui/widget/virtualkeyboard.lua:702,704> (12 instructions, 48 bytes at 0x7fd558c0dbd0)
1 param, 4 slots, 0 upvalues, 1 local, 4 constants, 0 functions
	1	[703]	GETGLOBAL	1 -1	; G_reader_settings
	2	[703]	SELF     	1 1 -2	; "readSetting"
	3	[703]	LOADK    	3 -3	; "keyboard_layout"
	4	[703]	CALL     	1 3 2
	5	[703]	TEST     	1 0 1
	6	[703]	JMP      	4	; to 11
	7	[703]	GETGLOBAL	1 -1	; G_reader_settings
	8	[703]	SELF     	1 1 -2	; "readSetting"
	9	[703]	LOADK    	3 -4	; "language"
	10	[703]	CALL     	1 3 2
	11	[703]	RETURN   	1 2
	12	[704]	RETURN   	0 1

function <./frontend/ui/widget/virtualkeyboard.lua:706,719> (43 instructions, 172 bytes at 0x7fd558c0c280)
2 params, 7 slots, 0 upvalues, 3 locals, 10 constants, 0 functions
	1	[707]	GETTABLE 	2 0 -1	; "dimen"
	2	[707]	TEST     	2 0 0
	3	[707]	JMP      	2	; to 6
	4	[707]	GETTABLE 	2 0 -1	; "dimen"
	5	[707]	GETTABLE 	2 2 -2	; "h"
	6	[708]	GETGLOBAL	3 -3	; G_reader_settings
	7	[708]	SELF     	3 3 -4	; "saveSetting"
	8	[708]	LOADK    	5 -5	; "keyboard_layout"
	9	[708]	MOVE     	6 1
	10	[708]	CALL     	3 4 1
	11	[709]	SELF     	3 0 -6	; "init"
	12	[709]	CALL     	3 2 1
	13	[710]	TEST     	2 0 0
	14	[710]	JMP      	25	; to 40
	15	[710]	GETTABLE 	3 0 -1	; "dimen"
	16	[710]	GETTABLE 	3 3 -2	; "h"
	17	[710]	EQ       	1 3 2
	18	[710]	JMP      	21	; to 40
	19	[711]	SELF     	3 0 -7	; "_refresh"
	20	[711]	LOADBOOL 	5 1 0
	21	[711]	LOADBOOL 	6 1 0
	22	[711]	CALL     	3 4 1
	23	[713]	GETTABLE 	3 0 -8	; "inputbox"
	24	[713]	TEST     	3 0 0
	25	[713]	JMP      	17	; to 43
	26	[713]	GETTABLE 	3 0 -8	; "inputbox"
	27	[713]	GETTABLE 	3 3 -9	; "parent"
	28	[713]	TEST     	3 0 0
	29	[713]	JMP      	13	; to 43
	30	[713]	GETTABLE 	3 0 -8	; "inputbox"
	31	[713]	GETTABLE 	3 3 -9	; "parent"
	32	[713]	GETTABLE 	3 3 -10	; "onKeyboardHeightChanged"
	33	[713]	TEST     	3 0 0
	34	[713]	JMP      	8	; to 43
	35	[714]	GETTABLE 	3 0 -8	; "inputbox"
	36	[714]	GETTABLE 	3 3 -9	; "parent"
	37	[714]	SELF     	3 3 -10	; "onKeyboardHeightChanged"
	38	[714]	CALL     	3 2 1
	39	[715]	JMP      	3	; to 43
	40	[717]	SELF     	3 0 -7	; "_refresh"
	41	[717]	LOADBOOL 	5 1 0
	42	[717]	CALL     	3 3 1
	43	[719]	RETURN   	0 1

function <./frontend/ui/widget/virtualkeyboard.lua:721,724> (7 instructions, 28 bytes at 0x7fd558c10790)
1 param, 4 slots, 1 upvalue, 1 local, 1 constant, 0 functions
	1	[722]	GETUPVAL 	1 0	; UIManager
	2	[722]	SELF     	1 1 -1	; "close"
	3	[722]	MOVE     	3 0
	4	[722]	CALL     	1 3 1
	5	[723]	LOADBOOL 	1 1 0
	6	[723]	RETURN   	1 2
	7	[724]	RETURN   	0 1

function <./frontend/ui/widget/virtualkeyboard.lua:726,729> (11 instructions, 44 bytes at 0x7fd558c0e910)
1 param, 6 slots, 1 upvalue, 1 local, 4 constants, 0 functions
	1	[727]	SELF     	1 0 -1	; "getFocusItem"
	2	[727]	CALL     	1 2 2
	3	[727]	SELF     	1 1 -2	; "handleEvent"
	4	[727]	GETUPVAL 	3 0	; Event
	5	[727]	SELF     	3 3 -3	; "new"
	6	[727]	LOADK    	5 -4	; "TapSelect"
	7	[727]	CALL     	3 3 0
	8	[727]	CALL     	1 0 1
	9	[728]	LOADBOOL 	1 1 0
	10	[728]	RETURN   	1 2
	11	[729]	RETURN   	0 1

function <./frontend/ui/widget/virtualkeyboard.lua:731,743> (20 instructions, 80 bytes at 0x7fd558c10c90)
3 params, 8 slots, 1 upvalue, 4 locals, 4 constants, 1 function
	1	[732]	LOADK    	3 -1	; "ui"
	2	[733]	TEST     	1 0 0
	3	[733]	JMP      	1	; to 5
	4	[734]	LOADK    	3 -2	; "flashui"
	5	[736]	TEST     	2 0 0
	6	[736]	JMP      	6	; to 13
	7	[737]	GETUPVAL 	4 0	; UIManager
	8	[737]	SELF     	4 4 -3	; "setDirty"
	9	[737]	LOADK    	6 -4	; "all"
	10	[737]	MOVE     	7 3
	11	[737]	CALL     	4 4 1
	12	[738]	RETURN   	0 1
	13	[740]	GETUPVAL 	4 0	; UIManager
	14	[740]	SELF     	4 4 -3	; "setDirty"
	15	[740]	MOVE     	6 0
	16	[742]	CLOSURE  	7 0	; 0x7fd558c11130
	17	[742]	MOVE     	0 3
	18	[742]	MOVE     	0 0
	19	[740]	CALL     	4 4 1
	20	[743]	RETURN   	0 1

function <./frontend/ui/widget/virtualkeyboard.lua:740,742> (7 instructions, 28 bytes at 0x7fd558c11130)
0 params, 2 slots, 2 upvalues, 0 locals, 2 constants, 0 functions
	1	[741]	GETUPVAL 	0 0	; refresh_type
	2	[741]	GETUPVAL 	1 1	; self
	3	[741]	GETTABLE 	1 1 -1	; 1
	4	[741]	GETTABLE 	1 1 -1	; 1
	5	[741]	GETTABLE 	1 1 -2	; "dimen"
	6	[741]	RETURN   	0 3
	7	[742]	RETURN   	0 1

function <./frontend/ui/widget/virtualkeyboard.lua:745,748> (6 instructions, 24 bytes at 0x7fd558c11790)
1 param, 4 slots, 0 upvalues, 1 local, 1 constant, 0 functions
	1	[746]	SELF     	1 0 -1	; "_refresh"
	2	[746]	LOADBOOL 	3 1 0
	3	[746]	CALL     	1 3 1
	4	[747]	LOADBOOL 	1 1 0
	5	[747]	RETURN   	1 2
	6	[748]	RETURN   	0 1

function <./frontend/ui/widget/virtualkeyboard.lua:750,753> (6 instructions, 24 bytes at 0x7fd558c11820)
1 param, 4 slots, 0 upvalues, 1 local, 1 constant, 0 functions
	1	[751]	SELF     	1 0 -1	; "_refresh"
	2	[751]	LOADBOOL 	3 0 0
	3	[751]	CALL     	1 3 1
	4	[752]	LOADBOOL 	1 1 0
	5	[752]	RETURN   	1 2
	6	[753]	RETURN   	0 1

function <./frontend/ui/widget/virtualkeyboard.lua:755,776> (67 instructions, 268 bytes at 0x7fd558c11a90)
2 params, 7 slots, 0 upvalues, 3 locals, 20 constants, 1 function
	1	[761]	CLOSURE  	2 0	; 0x7fd558c11f10
	2	[763]	TEST     	1 0 0
	3	[763]	JMP      	55	; to 59
	4	[765]	GETGLOBAL	3 -1	; math
	5	[765]	GETTABLE 	3 3 -2	; "max"
	6	[765]	MOVE     	4 1
	7	[765]	GETTABLE 	5 0 -3	; "min_layer"
	8	[765]	CALL     	3 3 2
	9	[765]	MOVE     	1 3
	10	[766]	GETGLOBAL	3 -1	; math
	11	[766]	GETTABLE 	3 3 -4	; "min"
	12	[766]	MOVE     	4 1
	13	[766]	GETTABLE 	5 0 -5	; "max_layer"
	14	[766]	CALL     	3 3 2
	15	[766]	MOVE     	1 3
	16	[767]	SETTABLE 	0 -6 1	; "keyboard_layer" -
	17	[769]	EQ       	1 1 -8	; - 1
	18	[769]	JMP      	11	; to 30
	19	[769]	EQ       	1 1 -9	; - 3
	20	[769]	JMP      	9	; to 30
	21	[769]	EQ       	1 1 -10	; - 5
	22	[769]	JMP      	7	; to 30
	23	[769]	EQ       	1 1 -11	; - 7
	24	[769]	JMP      	5	; to 30
	25	[769]	EQ       	1 1 -12	; - 9
	26	[769]	JMP      	3	; to 30
	27	[769]	EQ       	1 1 -13	; - 11
	28	[769]	JMP      	1	; to 30
	29	[769]	LOADBOOL 	3 0 1
	30	[769]	LOADBOOL 	3 1 0
	31	[769]	SETTABLE 	0 -7 3	; "shiftmode" -
	32	[770]	EQ       	1 1 -9	; - 3
	33	[770]	JMP      	11	; to 45
	34	[770]	EQ       	1 1 -15	; - 4
	35	[770]	JMP      	9	; to 45
	36	[770]	EQ       	1 1 -11	; - 7
	37	[770]	JMP      	7	; to 45
	38	[770]	EQ       	1 1 -16	; - 8
	39	[770]	JMP      	5	; to 45
	40	[770]	EQ       	1 1 -13	; - 11
	41	[770]	JMP      	3	; to 45
	42	[770]	EQ       	1 1 -17	; - 12
	43	[770]	JMP      	1	; to 45
	44	[770]	LOADBOOL 	3 0 1
	45	[770]	LOADBOOL 	3 1 0
	46	[770]	SETTABLE 	0 -14 3	; "symbolmode" -
	47	[771]	EQ       	1 1 -10	; - 5
	48	[771]	JMP      	7	; to 56
	49	[771]	EQ       	1 1 -19	; - 6
	50	[771]	JMP      	5	; to 56
	51	[771]	EQ       	1 1 -11	; - 7
	52	[771]	JMP      	3	; to 56
	53	[771]	EQ       	1 1 -16	; - 8
	54	[771]	JMP      	1	; to 56
	55	[771]	LOADBOOL 	3 0 1
	56	[771]	LOADBOOL 	3 1 0
	57	[771]	SETTABLE 	0 -18 3	; "umlautmode" -
	58	[771]	JMP      	6	; to 65
	59	[773]	MOVE     	3 2
	60	[773]	GETTABLE 	4 0 -7	; "shiftmode"
	61	[773]	GETTABLE 	5 0 -14	; "symbolmode"
	62	[773]	GETTABLE 	6 0 -18	; "umlautmode"
	63	[773]	CALL     	3 4 2
	64	[773]	SETTABLE 	0 -6 3	; "keyboard_layer" -
	65	[775]	SELF     	3 0 -20	; "addKeys"
	66	[775]	CALL     	3 2 1
	67	[776]	RETURN   	0 1

function <./frontend/ui/widget/virtualkeyboard.lua:756,761> (17 instructions, 68 bytes at 0x7fd558c11f10)
3 params, 7 slots, 0 upvalues, 4 locals, 2 constants, 1 function
	1	[759]	CLOSURE  	3 0	; 0x7fd558c11d50
	2	[760]	MOVE     	4 3
	3	[760]	MOVE     	5 0
	4	[760]	CALL     	4 2 2
	5	[760]	SUB      	4 -1 4	; 2 -
	6	[760]	MOVE     	5 3
	7	[760]	MOVE     	6 1
	8	[760]	CALL     	5 2 2
	9	[760]	MUL      	5 -1 5	; 2 -
	10	[760]	ADD      	4 4 5
	11	[760]	MOVE     	5 3
	12	[760]	MOVE     	6 2
	13	[760]	CALL     	5 2 2
	14	[760]	MUL      	5 -2 5	; 4 -
	15	[760]	ADD      	4 4 5
	16	[760]	RETURN   	4 2
	17	[761]	RETURN   	0 1

function <./frontend/ui/widget/virtualkeyboard.lua:757,759> (8 instructions, 32 bytes at 0x7fd558c11d50)
1 param, 2 slots, 0 upvalues, 1 local, 2 constants, 0 functions
	1	[758]	TEST     	0 0 0
	2	[758]	JMP      	3	; to 6
	3	[758]	LOADK    	1 -1	; 1
	4	[758]	TEST     	1 0 1
	5	[758]	JMP      	1	; to 7
	6	[758]	LOADK    	1 -2	; 0
	7	[758]	RETURN   	1 2
	8	[759]	RETURN   	0 1

function <./frontend/ui/widget/virtualkeyboard.lua:778,851> (242 instructions, 968 bytes at 0x7fd558c12170)
1 param, 26 slots, 12 upvalues, 24 locals, 38 constants, 0 functions
	1	[779]	SELF     	1 0 -1	; "free"
	2	[779]	CALL     	1 2 1
	3	[780]	NEWTABLE 	1 0 0
	4	[780]	SETTABLE 	0 -2 1	; "layout" -
	5	[781]	GETGLOBAL	1 -3	; math
	6	[781]	GETTABLE 	1 1 -4	; "floor"
	7	[781]	GETTABLE 	2 0 -5	; "width"
	8	[781]	GETTABLE 	3 0 -6	; "KEYS"
	9	[781]	GETTABLE 	3 3 -7	; 1
	10	[781]	LEN      	3 3
	11	[781]	ADD      	3 3 -7	; - 1
	12	[781]	GETTABLE 	4 0 -8	; "key_padding"
	13	[781]	MUL      	3 3 4
	14	[781]	SUB      	2 2 3
	15	[781]	GETTABLE 	3 0 -9	; "padding"
	16	[781]	MUL      	3 -10 3	; 2 -
	17	[781]	SUB      	2 2 3
	18	[781]	GETTABLE 	3 0 -6	; "KEYS"
	19	[781]	GETTABLE 	3 3 -7	; 1
	20	[781]	LEN      	3 3
	21	[781]	DIV      	2 2 3
	22	[781]	CALL     	1 2 2
	23	[782]	GETGLOBAL	2 -3	; math
	24	[782]	GETTABLE 	2 2 -4	; "floor"
	25	[782]	GETTABLE 	3 0 -11	; "height"
	26	[782]	GETTABLE 	4 0 -6	; "KEYS"
	27	[782]	LEN      	4 4
	28	[782]	ADD      	4 4 -7	; - 1
	29	[782]	GETTABLE 	5 0 -8	; "key_padding"
	30	[782]	MUL      	4 4 5
	31	[782]	SUB      	3 3 4
	32	[782]	GETTABLE 	4 0 -9	; "padding"
	33	[782]	MUL      	4 -10 4	; 2 -
	34	[782]	SUB      	3 3 4
	35	[782]	GETTABLE 	4 0 -6	; "KEYS"
	36	[782]	LEN      	4 4
	37	[782]	DIV      	3 3 4
	38	[782]	CALL     	2 2 2
	39	[783]	GETUPVAL 	3 0	; HorizontalSpan
	40	[783]	SELF     	3 3 -12	; "new"
	41	[783]	NEWTABLE 	5 0 1
	42	[783]	GETTABLE 	6 0 -8	; "key_padding"
	43	[783]	SETTABLE 	5 -5 6	; "width" -
	44	[783]	CALL     	3 3 2
	45	[784]	GETUPVAL 	4 1	; VerticalSpan
	46	[784]	SELF     	4 4 -12	; "new"
	47	[784]	NEWTABLE 	6 0 1
	48	[784]	GETTABLE 	7 0 -8	; "key_padding"
	49	[784]	SETTABLE 	6 -5 7	; "width" -
	50	[784]	CALL     	4 3 2
	51	[785]	GETUPVAL 	5 2	; VerticalGroup
	52	[785]	SELF     	5 5 -12	; "new"
	53	[785]	NEWTABLE 	7 0 1
	54	[785]	SETTABLE 	7 -13 -14	; "allow_mirroring" false
	55	[785]	CALL     	5 3 2
	56	[786]	LOADK    	6 -7	; 1
	57	[786]	GETTABLE 	7 0 -6	; "KEYS"
	58	[786]	LEN      	7 7
	59	[786]	LOADK    	8 -7	; 1
	60	[786]	FORPREP  	6 118	; to 179
	61	[787]	GETUPVAL 	10 3	; HorizontalGroup
	62	[787]	SELF     	10 10 -12	; "new"
	63	[787]	NEWTABLE 	12 0 1
	64	[787]	SETTABLE 	12 -13 -14	; "allow_mirroring" false
	65	[787]	CALL     	10 3 2
	66	[788]	NEWTABLE 	11 0 0
	67	[789]	LOADK    	12 -7	; 1
	68	[789]	GETTABLE 	13 0 -6	; "KEYS"
	69	[789]	GETTABLE 	13 13 9
	70	[789]	LEN      	13 13
	71	[789]	LOADK    	14 -7	; 1
	72	[789]	FORPREP  	12 86	; to 159
	73	[790]	LOADNIL  	16 16
	74	[791]	GETTABLE 	17 0 -6	; "KEYS"
	75	[791]	GETTABLE 	17 17 9
	76	[791]	GETTABLE 	17 17 15
	77	[791]	GETTABLE 	18 0 -15	; "keyboard_layer"
	78	[791]	GETTABLE 	17 17 18
	79	[792]	LOADNIL  	18 18
	80	[793]	GETGLOBAL	19 -16	; type
	81	[793]	MOVE     	20 17
	82	[793]	CALL     	19 2 2
	83	[793]	EQ       	0 19 -17	; - "table"
	84	[793]	JMP      	3	; to 88
	85	[794]	GETTABLE 	16 17 -7	; 1
	86	[795]	GETTABLE 	18 17 -18	; "label"
	87	[795]	JMP      	2	; to 90
	88	[797]	MOVE     	16 17
	89	[798]	LOADNIL  	17 17
	90	[800]	GETTABLE 	19 0 -6	; "KEYS"
	91	[800]	GETTABLE 	19 19 9
	92	[800]	GETTABLE 	19 19 15
	93	[800]	GETTABLE 	19 19 -5	; "width"
	94	[800]	TEST     	19 0 1
	95	[800]	JMP      	1	; to 97
	96	[800]	LOADK    	19 -7	; 1
	97	[801]	GETGLOBAL	20 -3	; math
	98	[801]	GETTABLE 	20 20 -4	; "floor"
	99	[801]	GETTABLE 	21 0 -8	; "key_padding"
	100	[801]	ADD      	21 1 21
	101	[801]	MUL      	21 21 19
	102	[801]	CALL     	20 2 2
	103	[802]	GETTABLE 	21 0 -8	; "key_padding"
	104	[802]	SUB      	20 20 21
	105	[803]	MOVE     	21 2
	106	[804]	TEST     	18 0 1
	107	[804]	JMP      	7	; to 115
	108	[804]	GETTABLE 	22 0 -6	; "KEYS"
	109	[804]	GETTABLE 	22 22 9
	110	[804]	GETTABLE 	22 22 15
	111	[804]	GETTABLE 	22 22 -18	; "label"
	112	[804]	TESTSET  	18 22 1
	113	[804]	JMP      	1	; to 115
	114	[804]	MOVE     	18 16
	115	[805]	GETUPVAL 	22 4	; VirtualKey
	116	[805]	SELF     	22 22 -12	; "new"
	117	[805]	NEWTABLE 	24 0 8
	118	[806]	SETTABLE 	24 -19 16	; "key" -
	119	[807]	SETTABLE 	24 -20 17	; "key_chars" -
	120	[808]	GETTABLE 	25 0 -6	; "KEYS"
	121	[808]	GETTABLE 	25 25 9
	122	[808]	GETTABLE 	25 25 15
	123	[808]	GETTABLE 	25 25 -21	; "icon"
	124	[808]	SETTABLE 	24 -21 25	; "icon" -
	125	[809]	SETTABLE 	24 -18 18	; "label" -
	126	[810]	GETTABLE 	25 0 -6	; "KEYS"
	127	[810]	GETTABLE 	25 25 9
	128	[810]	GETTABLE 	25 25 15
	129	[810]	GETTABLE 	25 25 -22	; "bold"
	130	[810]	SETTABLE 	24 -22 25	; "bold" -
	131	[811]	SETTABLE 	24 -23 0	; "keyboard" -
	132	[812]	SETTABLE 	24 -5 20	; "width" -
	133	[813]	SETTABLE 	24 -11 21	; "height" -
	134	[805]	CALL     	22 3 2
	135	[815]	GETTABLE 	23 22 -20	; "key_chars"
	136	[815]	TEST     	23 0 1
	137	[815]	JMP      	1	; to 139
	138	[816]	SETTABLE 	22 -24 -25	; "swipe_callback" nil
	139	[818]	GETGLOBAL	23 -17	; table
	140	[818]	GETTABLE 	23 23 -26	; "insert"
	141	[818]	MOVE     	24 10
	142	[818]	MOVE     	25 22
	143	[818]	CALL     	23 3 1
	144	[819]	GETGLOBAL	23 -17	; table
	145	[819]	GETTABLE 	23 23 -26	; "insert"
	146	[819]	MOVE     	24 11
	147	[819]	MOVE     	25 22
	148	[819]	CALL     	23 3 1
	149	[820]	GETTABLE 	23 0 -6	; "KEYS"
	150	[820]	GETTABLE 	23 23 9
	151	[820]	LEN      	23 23
	152	[820]	EQ       	1 15 23
	153	[820]	JMP      	5	; to 159
	154	[821]	GETGLOBAL	23 -17	; table
	155	[821]	GETTABLE 	23 23 -26	; "insert"
	156	[821]	MOVE     	24 10
	157	[821]	MOVE     	25 3
	158	[821]	CALL     	23 3 1
	159	[789]	FORLOOP  	12 -87	; to 73
	160	[824]	GETGLOBAL	12 -17	; table
	161	[824]	GETTABLE 	12 12 -26	; "insert"
	162	[824]	MOVE     	13 5
	163	[824]	MOVE     	14 10
	164	[824]	CALL     	12 3 1
	165	[825]	GETGLOBAL	12 -17	; table
	166	[825]	GETTABLE 	12 12 -26	; "insert"
	167	[825]	GETTABLE 	13 0 -2	; "layout"
	168	[825]	MOVE     	14 11
	169	[825]	CALL     	12 3 1
	170	[826]	GETTABLE 	12 0 -6	; "KEYS"
	171	[826]	LEN      	12 12
	172	[826]	EQ       	1 9 12
	173	[826]	JMP      	5	; to 179
	174	[827]	GETGLOBAL	12 -17	; table
	175	[827]	GETTABLE 	12 12 -26	; "insert"
	176	[827]	MOVE     	13 5
	177	[827]	MOVE     	14 4
	178	[827]	CALL     	12 3 1
	179	[786]	FORLOOP  	6 -119	; to 61
	180	[831]	GETUPVAL 	6 5	; FrameContainer
	181	[831]	SELF     	6 6 -12	; "new"
	182	[831]	NEWTABLE 	8 0 6
	183	[832]	SETTABLE 	8 -27 -28	; "margin" 0
	184	[833]	GETUPVAL 	9 6	; Size
	185	[833]	GETTABLE 	9 9 -30	; "border"
	186	[833]	GETTABLE 	9 9 -31	; "default"
	187	[833]	SETTABLE 	8 -29 9	; "bordersize" -
	188	[834]	GETUPVAL 	9 7	; Blitbuffer
	189	[834]	GETTABLE 	9 9 -33	; "COLOR_WHITE"
	190	[834]	SETTABLE 	8 -32 9	; "background" -
	191	[835]	SETTABLE 	8 -34 -28	; "radius" 0
	192	[836]	GETTABLE 	9 0 -9	; "padding"
	193	[836]	SETTABLE 	8 -9 9	; "padding" -
	194	[837]	SETTABLE 	8 -13 -14	; "allow_mirroring" false
	195	[838]	GETUPVAL 	9 8	; CenterContainer
	196	[838]	SELF     	9 9 -12	; "new"
	197	[838]	NEWTABLE 	11 1 1
	198	[839]	GETUPVAL 	12 9	; Geom
	199	[839]	SELF     	12 12 -12	; "new"
	200	[839]	NEWTABLE 	14 0 2
	201	[840]	GETTABLE 	15 0 -5	; "width"
	202	[840]	GETUPVAL 	16 6	; Size
	203	[840]	GETTABLE 	16 16 -30	; "border"
	204	[840]	GETTABLE 	16 16 -31	; "default"
	205	[840]	MUL      	16 -10 16	; 2 -
	206	[840]	SUB      	15 15 16
	207	[840]	GETTABLE 	16 0 -9	; "padding"
	208	[840]	MUL      	16 -10 16	; 2 -
	209	[840]	SUB      	15 15 16
	210	[840]	SETTABLE 	14 -36 15	; "w" -
	211	[841]	GETTABLE 	15 0 -11	; "height"
	212	[841]	GETUPVAL 	16 6	; Size
	213	[841]	GETTABLE 	16 16 -30	; "border"
	214	[841]	GETTABLE 	16 16 -31	; "default"
	215	[841]	MUL      	16 -10 16	; 2 -
	216	[841]	SUB      	15 15 16
	217	[841]	GETTABLE 	16 0 -9	; "padding"
	218	[841]	MUL      	16 -10 16	; 2 -
	219	[841]	SUB      	15 15 16
	220	[841]	SETTABLE 	14 -37 15	; "h" -
	221	[839]	CALL     	12 3 2
	222	[842]	SETTABLE 	11 -35 12	; "dimen" -
	223	[844]	MOVE     	12 5
	224	[844]	SETLIST  	11 1 1	; 1
	225	[838]	CALL     	9 3 0
	226	[845]	SETLIST  	8 0 1	; 1
	227	[831]	CALL     	6 3 2
	228	[846]	GETUPVAL 	7 10	; BottomContainer
	229	[846]	SELF     	7 7 -12	; "new"
	230	[846]	NEWTABLE 	9 1 1
	231	[847]	GETUPVAL 	10 11	; Screen
	232	[847]	SELF     	10 10 -38	; "getSize"
	233	[847]	CALL     	10 2 2
	234	[847]	SETTABLE 	9 -35 10	; "dimen" -
	235	[849]	MOVE     	10 6
	236	[849]	SETLIST  	9 1 1	; 1
	237	[846]	CALL     	7 3 2
	238	[849]	SETTABLE 	0 -7 7	; 1 -
	239	[850]	SELF     	7 6 -38	; "getSize"
	240	[850]	CALL     	7 2 2
	241	[850]	SETTABLE 	0 -35 7	; "dimen" -
	242	[851]	RETURN   	0 1

function <./frontend/ui/widget/virtualkeyboard.lua:853,863> (25 instructions, 100 bytes at 0x7fd558c12ca0)
2 params, 5 slots, 0 upvalues, 2 locals, 9 constants, 0 functions
	1	[854]	EQ       	0 1 -1	; - "Shift"
	2	[854]	JMP      	4	; to 7
	3	[855]	GETTABLE 	2 0 -2	; "shiftmode"
	4	[855]	NOT      	2 2
	5	[855]	SETTABLE 	0 -2 2	; "shiftmode" -
	6	[855]	JMP      	13	; to 20
	7	[856]	EQ       	1 1 -3	; - "Sym"
	8	[856]	JMP      	2	; to 11
	9	[856]	EQ       	0 1 -4	; - "ABC"
	10	[856]	JMP      	4	; to 15
	11	[857]	GETTABLE 	2 0 -5	; "symbolmode"
	12	[857]	NOT      	2 2
	13	[857]	SETTABLE 	0 -5 2	; "symbolmode" -
	14	[857]	JMP      	5	; to 20
	15	[858]	EQ       	0 1 -6	; - "\195\132\195\169\195\159"
	16	[858]	JMP      	3	; to 20
	17	[859]	GETTABLE 	2 0 -7	; "umlautmode"
	18	[859]	NOT      	2 2
	19	[859]	SETTABLE 	0 -7 2	; "umlautmode" -
	20	[861]	SELF     	2 0 -8	; "initLayer"
	21	[861]	CALL     	2 2 1
	22	[862]	SELF     	2 0 -9	; "_refresh"
	23	[862]	LOADBOOL 	4 1 0
	24	[862]	CALL     	2 3 1
	25	[863]	RETURN   	0 1

function <./frontend/ui/widget/virtualkeyboard.lua:865,868> (10 instructions, 40 bytes at 0x7fd558c131e0)
2 params, 5 slots, 1 upvalue, 2 locals, 4 constants, 0 functions
	1	[866]	GETUPVAL 	2 0	; logger
	2	[866]	GETTABLE 	2 2 -1	; "dbg"
	3	[866]	LOADK    	3 -2	; "add char"
	4	[866]	MOVE     	4 1
	5	[866]	CALL     	2 3 1
	6	[867]	GETTABLE 	2 0 -3	; "inputbox"
	7	[867]	SELF     	2 2 -4	; "addChars"
	8	[867]	MOVE     	4 1
	9	[867]	CALL     	2 3 1
	10	[868]	RETURN   	0 1

function <./frontend/ui/widget/virtualkeyboard.lua:870,873> (8 instructions, 32 bytes at 0x7fd558c12f60)
1 param, 3 slots, 1 upvalue, 1 local, 4 constants, 0 functions
	1	[871]	GETUPVAL 	1 0	; logger
	2	[871]	GETTABLE 	1 1 -1	; "dbg"
	3	[871]	LOADK    	2 -2	; "delete char"
	4	[871]	CALL     	1 2 1
	5	[872]	GETTABLE 	1 0 -3	; "inputbox"
	6	[872]	SELF     	1 1 -4	; "delChar"
	7	[872]	CALL     	1 2 1
	8	[873]	RETURN   	0 1

function <./frontend/ui/widget/virtualkeyboard.lua:875,878> (8 instructions, 32 bytes at 0x7fd558c13020)
1 param, 3 slots, 1 upvalue, 1 local, 4 constants, 0 functions
	1	[876]	GETUPVAL 	1 0	; logger
	2	[876]	GETTABLE 	1 1 -1	; "dbg"
	3	[876]	LOADK    	2 -2	; "delete to start of line"
	4	[876]	CALL     	1 2 1
	5	[877]	GETTABLE 	1 0 -3	; "inputbox"
	6	[877]	SELF     	1 1 -4	; "delToStartOfLine"
	7	[877]	CALL     	1 2 1
	8	[878]	RETURN   	0 1

function <./frontend/ui/widget/virtualkeyboard.lua:880,882> (4 instructions, 16 bytes at 0x7fd558c13c20)
1 param, 3 slots, 0 upvalues, 1 local, 2 constants, 0 functions
	1	[881]	GETTABLE 	1 0 -1	; "inputbox"
	2	[881]	SELF     	1 1 -2	; "leftChar"
	3	[881]	CALL     	1 2 1
	4	[882]	RETURN   	0 1

function <./frontend/ui/widget/virtualkeyboard.lua:884,886> (4 instructions, 16 bytes at 0x7fd558c14100)
1 param, 3 slots, 0 upvalues, 1 local, 2 constants, 0 functions
	1	[885]	GETTABLE 	1 0 -1	; "inputbox"
	2	[885]	SELF     	1 1 -2	; "rightChar"
	3	[885]	CALL     	1 2 1
	4	[886]	RETURN   	0 1

function <./frontend/ui/widget/virtualkeyboard.lua:888,890> (4 instructions, 16 bytes at 0x7fd558c14190)
1 param, 3 slots, 0 upvalues, 1 local, 2 constants, 0 functions
	1	[889]	GETTABLE 	1 0 -1	; "inputbox"
	2	[889]	SELF     	1 1 -2	; "upLine"
	3	[889]	CALL     	1 2 1
	4	[890]	RETURN   	0 1

function <./frontend/ui/widget/virtualkeyboard.lua:892,894> (4 instructions, 16 bytes at 0x7fd558c14230)
1 param, 3 slots, 0 upvalues, 1 local, 2 constants, 0 functions
	1	[893]	GETTABLE 	1 0 -1	; "inputbox"
	2	[893]	SELF     	1 1 -2	; "downLine"
	3	[893]	CALL     	1 2 1
	4	[894]	RETURN   	0 1

function <./frontend/ui/widget/virtualkeyboard.lua:896,899> (8 instructions, 32 bytes at 0x7fd558c14450)
1 param, 3 slots, 1 upvalue, 1 local, 4 constants, 0 functions
	1	[897]	GETUPVAL 	1 0	; logger
	2	[897]	GETTABLE 	1 1 -1	; "dbg"
	3	[897]	LOADK    	2 -2	; "clear input"
	4	[897]	CALL     	1 2 1
	5	[898]	GETTABLE 	1 0 -3	; "inputbox"
	6	[898]	SELF     	1 1 -4	; "clear"
	7	[898]	CALL     	1 2 1
	8	[899]	RETURN   	0 1
