-- BYTECODE -- wbuilder.lua:53-66
0001    GGET     2   0      ; "math"
0002    TGETS    2   2   1  ; "floor"
0003    MOV      4   1
0004    TGETS    3   1   2  ; "getWidth"
0005    CALL     3   2   2
0006    DIVVN    3   3   0  ; 50
0007    CALL     2   2   2
0008    GSET     2   3      ; "v_line"
0009    GGET     2   0      ; "math"
0010    TGETS    2   2   1  ; "floor"
0011    MOV      4   1
0012    TGETS    3   1   4  ; "getHeight"
0013    CALL     3   2   2
0014    DIVVN    3   3   0  ; 50
0015    CALL     2   2   2
0016    GSET     2   5      ; "h_line"
0017    KSHORT   2   1
0018    GGET     3   5      ; "h_line"
0019    KSHORT   4   1
0020    FORI     2 => 0053
0021 => MULVN    6   5   0  ; 50
0022    GSET     6   6      ; "y_num"
0023    UGET     6   0      ; RenderText
0024    MOV      7   6
0025    TGETS    6   6   7  ; "renderUtf8Text"
0026    MOV      8   1
0027    KSHORT   9   0
0028    GGET    10   6      ; "y_num"
0029    ADDVN   10  10   1  ; 10
0030    UGET    11   1      ; Font
0031    MOV     12  11
0032    TGETS   11  11   8  ; "getFace"
0033    KSTR    13   9      ; "ffont"
0034    KSHORT  14  12
0035    CALL    11   2   4
0036    GGET    12   6      ; "y_num"
0037    KPRI    13   2
0038    CALL     6   1   8
0039    MOV      7   1
0040    TGETS    6   1  10  ; "paintRect"
0041    KSHORT   8   0
0042    GGET     9   6      ; "y_num"
0043    MOV     11   1
0044    TGETS   10   1   2  ; "getWidth"
0045    CALL    10   2   2
0046    KSHORT  11   1
0047    UGET    12   2      ; Blitbuffer
0048    TGETS   12  12  11  ; "gray"
0049    KNUM    13   2      ; 0.7
0050    CALL    12   0   2
0051    CALLM    6   1   5
0052    FORL     2 => 0021
0053 => KSHORT   2   1
0054    GGET     3   3      ; "v_line"
0055    KSHORT   4   1
0056    FORI     2 => 0088
0057 => MULVN    6   5   0  ; 50
0058    GSET     6  12      ; "x_num"
0059    UGET     6   0      ; RenderText
0060    MOV      7   6
0061    TGETS    6   6   7  ; "renderUtf8Text"
0062    MOV      8   1
0063    GGET     9  12      ; "x_num"
0064    KSHORT  10  10
0065    UGET    11   1      ; Font
0066    MOV     12  11
0067    TGETS   11  11   8  ; "getFace"
0068    KSTR    13   9      ; "ffont"
0069    KSHORT  14  12
0070    CALL    11   2   4
0071    GGET    12  12      ; "x_num"
0072    KPRI    13   2
0073    CALL     6   1   8
0074    MOV      7   1
0075    TGETS    6   1  10  ; "paintRect"
0076    GGET     8  12      ; "x_num"
0077    KSHORT   9   0
0078    KSHORT  10   1
0079    MOV     12   1
0080    TGETS   11   1   4  ; "getHeight"
0081    CALL    11   2   2
0082    UGET    12   2      ; Blitbuffer
0083    TGETS   12  12  11  ; "gray"
0084    KNUM    13   2      ; 0.7
0085    CALL    12   0   2
0086    CALLM    6   1   5
0087    FORL     2 => 0057
0088 => RET0     0   1

-- BYTECODE -- wbuilder.lua:68-122
0001    GGET     2   0      ; "math"
0002    TGETS    2   2   1  ; "floor"
0003    MOV      4   1
0004    TGETS    3   1   2  ; "getWidth"
0005    CALL     3   2   2
0006    DIVVN    3   3   0  ; 50
0007    CALL     2   2   2
0008    GSET     2   3      ; "v_line"
0009    GGET     2   0      ; "math"
0010    TGETS    2   2   1  ; "floor"
0011    MOV      4   1
0012    TGETS    3   1   4  ; "getHeight"
0013    CALL     3   2   2
0014    DIVVN    3   3   0  ; 50
0015    CALL     2   2   2
0016    GSET     2   5      ; "h_line"
0017    MOV      3   1
0018    TGETS    2   1   6  ; "paintRect"
0019    KSHORT   4   0
0020    KSHORT   5   0
0021    MOV      7   1
0022    TGETS    6   1   2  ; "getWidth"
0023    CALL     6   2   2
0024    MOV      8   1
0025    TGETS    7   1   4  ; "getHeight"
0026    CALL     7   2   2
0027    UGET     8   0      ; Blitbuffer
0028    TGETS    8   8   7  ; "COLOR_WHITE"
0029    CALL     2   1   7
0030    KSHORT   2   1
0031    GGET     3   5      ; "h_line"
0032    KSHORT   4   1
0033    FORI     2 => 0053
0034 => MULVN    6   5   0  ; 50
0035    GSET     6   8      ; "y_num"
0036    UGET     6   1      ; RenderText
0037    MOV      7   6
0038    TGETS    6   6   9  ; "renderUtf8Text"
0039    MOV      8   1
0040    KSHORT   9  40
0041    GGET    10   8      ; "y_num"
0042    ADDVN   10  10   1  ; 10
0043    UGET    11   2      ; Font
0044    MOV     12  11
0045    TGETS   11  11  10  ; "getFace"
0046    KSTR    13  11      ; "ffont"
0047    KSHORT  14  12
0048    CALL    11   2   4
0049    GGET    12   8      ; "y_num"
0050    KPRI    13   2
0051    CALL     6   1   8
0052    FORL     2 => 0034
0053 => KSHORT   2   1
0054    GGET     3   3      ; "v_line"
0055    KSHORT   4   1
0056    FORI     2 => 0075
0057 => MULVN    6   5   0  ; 50
0058    GSET     6  12      ; "x_num"
0059    UGET     6   1      ; RenderText
0060    MOV      7   6
0061    TGETS    6   6   9  ; "renderUtf8Text"
0062    MOV      8   1
0063    GGET     9  12      ; "x_num"
0064    KSHORT  10  40
0065    UGET    11   2      ; Font
0066    MOV     12  11
0067    TGETS   11  11  10  ; "getFace"
0068    KSTR    13  11      ; "ffont"
0069    KSHORT  14  12
0070    CALL    11   2   4
0071    GGET    12  12      ; "x_num"
0072    KPRI    13   2
0073    CALL     6   1   8
0074    FORL     2 => 0057
0075 => KSHORT   2   4
0076    MOV      4   1
0077    TGETS    3   1   2  ; "getWidth"
0078    CALL     3   2   2
0079    SUBVN    3   3   2  ; 4
0080    KSHORT   4   3
0081    MOV      6   1
0082    TGETS    5   1   4  ; "getHeight"
0083    CALL     5   2   2
0084    SUBVN    5   5   3  ; 3
0085    SUBVN    5   5   4  ; 12
0086    UGET     6   1      ; RenderText
0087    MOV      7   6
0088    TGETS    6   6   9  ; "renderUtf8Text"
0089    MOV      8   1
0090    KSHORT   9 150
0091    KSHORT  10 100
0092    UGET    11   2      ; Font
0093    MOV     12  11
0094    TGETS   11  11  10  ; "getFace"
0095    KSTR    13  11      ; "ffont"
0096    KSHORT  14  22
0097    CALL    11   2   4
0098    KSTR    12  13      ; "x_min = "
0099    MOV     13   2
0100    CAT     12  12  13
0101    KPRI    13   2
0102    CALL     6   1   8
0103    UGET     6   1      ; RenderText
0104    MOV      7   6
0105    TGETS    6   6   9  ; "renderUtf8Text"
0106    MOV      8   1
0107    KSHORT   9 500
0108    KSHORT  10 100
0109    UGET    11   2      ; Font
0110    MOV     12  11
0111    TGETS   11  11  10  ; "getFace"
0112    KSTR    13  11      ; "ffont"
0113    KSHORT  14  22
0114    CALL    11   2   4
0115    KSTR    12  14      ; "x_max = "
0116    MOV     13   3
0117    CAT     12  12  13
0118    KPRI    13   2
0119    CALL     6   1   8
0120    UGET     6   1      ; RenderText
0121    MOV      7   6
0122    TGETS    6   6   9  ; "renderUtf8Text"
0123    MOV      8   1
0124    KSHORT   9 100
0125    KSHORT  10 150
0126    UGET    11   2      ; Font
0127    MOV     12  11
0128    TGETS   11  11  10  ; "getFace"
0129    KSTR    13  11      ; "ffont"
0130    KSHORT  14  22
0131    CALL    11   2   4
0132    KSTR    12  15      ; "y_min = "
0133    MOV     13   4
0134    CAT     12  12  13
0135    KPRI    13   2
0136    CALL     6   1   8
0137    UGET     6   1      ; RenderText
0138    MOV      7   6
0139    TGETS    6   6   9  ; "renderUtf8Text"
0140    MOV      8   1
0141    KSHORT   9 100
0142    KSHORT  10 300
0143    UGET    11   2      ; Font
0144    MOV     12  11
0145    TGETS   11  11  10  ; "getFace"
0146    KSTR    13  11      ; "ffont"
0147    KSHORT  14  22
0148    CALL    11   2   4
0149    KSTR    12  16      ; "y_max = "
0150    MOV     13   5
0151    CAT     12  12  13
0152    KPRI    13   2
0153    CALL     6   1   8
0154    UGET     6   1      ; RenderText
0155    MOV      7   6
0156    TGETS    6   6   9  ; "renderUtf8Text"
0157    MOV      8   1
0158    KSHORT   9 100
0159    KSHORT  10 500
0160    UGET    11   2      ; Font
0161    MOV     12  11
0162    TGETS   11  11  10  ; "getFace"
0163    KSTR    13  11      ; "ffont"
0164    KSHORT  14  26
0165    CALL    11   2   4
0166    KSTR    12  17      ; "Visible screen size :  "
0167    SUBVV   13   3   2
0168    KSTR    14  18      ; "x"
0169    SUBVV   15   5   4
0170    CAT     12  12  15
0171    KPRI    13   2
0172    CALL     6   1   8
0173    MOV      7   1
0174    TGETS    6   1   6  ; "paintRect"
0175    MOV      8   2
0176    MOV      9   4
0177    MOV     10   3
0178    KSHORT  11   1
0179    UGET    12   0      ; Blitbuffer
0180    TGETS   12  12  19  ; "gray"
0181    KNUM    13   5      ; 0.7
0182    CALL    12   0   2
0183    CALLM    6   1   5
0184    MOV      7   1
0185    TGETS    6   1   6  ; "paintRect"
0186    MOV      8   2
0187    ADDVN    9   4   3  ; 3
0188    MOV     10   3
0189    KSHORT  11   1
0190    UGET    12   0      ; Blitbuffer
0191    TGETS   12  12  19  ; "gray"
0192    KNUM    13   5      ; 0.7
0193    CALL    12   0   2
0194    CALLM    6   1   5
0195    MOV      7   1
0196    TGETS    6   1   6  ; "paintRect"
0197    MOV      8   2
0198    ADDVN    9   4   6  ; 6
0199    MOV     10   3
0200    KSHORT  11   1
0201    UGET    12   0      ; Blitbuffer
0202    TGETS   12  12  19  ; "gray"
0203    KNUM    13   5      ; 0.7
0204    CALL    12   0   2
0205    CALLM    6   1   5
0206    MOV      7   1
0207    TGETS    6   1   6  ; "paintRect"
0208    MOV      8   2
0209    MOV      9   5
0210    MOV     10   3
0211    KSHORT  11   1
0212    UGET    12   0      ; Blitbuffer
0213    TGETS   12  12  19  ; "gray"
0214    KNUM    13   5      ; 0.7
0215    CALL    12   0   2
0216    CALLM    6   1   5
0217    MOV      7   1
0218    TGETS    6   1   6  ; "paintRect"
0219    MOV      8   2
0220    SUBVN    9   5   3  ; 3
0221    MOV     10   3
0222    KSHORT  11   1
0223    UGET    12   0      ; Blitbuffer
0224    TGETS   12  12  19  ; "gray"
0225    KNUM    13   5      ; 0.7
0226    CALL    12   0   2
0227    CALLM    6   1   5
0228    MOV      7   1
0229    TGETS    6   1   6  ; "paintRect"
0230    MOV      8   2
0231    SUBVN    9   5   6  ; 6
0232    MOV     10   3
0233    KSHORT  11   1
0234    UGET    12   0      ; Blitbuffer
0235    TGETS   12  12  19  ; "gray"
0236    KNUM    13   5      ; 0.7
0237    CALL    12   0   2
0238    CALLM    6   1   5
0239    MOV      7   1
0240    TGETS    6   1   6  ; "paintRect"
0241    MOV      8   2
0242    MOV      9   4
0243    KSHORT  10   1
0244    MOV     11   5
0245    UGET    12   0      ; Blitbuffer
0246    TGETS   12  12  19  ; "gray"
0247    KNUM    13   5      ; 0.7
0248    CALL    12   0   2
0249    CALLM    6   1   5
0250    MOV      7   1
0251    TGETS    6   1   6  ; "paintRect"
0252    ADDVN    8   2   3  ; 3
0253    MOV      9   4
0254    KSHORT  10   1
0255    MOV     11   5
0256    UGET    12   0      ; Blitbuffer
0257    TGETS   12  12  19  ; "gray"
0258    KNUM    13   5      ; 0.7
0259    CALL    12   0   2
0260    CALLM    6   1   5
0261    MOV      7   1
0262    TGETS    6   1   6  ; "paintRect"
0263    ADDVN    8   2   6  ; 6
0264    MOV      9   4
0265    KSHORT  10   1
0266    MOV     11   5
0267    UGET    12   0      ; Blitbuffer
0268    TGETS   12  12  19  ; "gray"
0269    KNUM    13   5      ; 0.7
0270    CALL    12   0   2
0271    CALLM    6   1   5
0272    MOV      7   1
0273    TGETS    6   1   6  ; "paintRect"
0274    MOV      8   3
0275    MOV      9   4
0276    KSHORT  10   1
0277    MOV     11   5
0278    UGET    12   0      ; Blitbuffer
0279    TGETS   12  12  19  ; "gray"
0280    KNUM    13   5      ; 0.7
0281    CALL    12   0   2
0282    CALLM    6   1   5
0283    MOV      7   1
0284    TGETS    6   1   6  ; "paintRect"
0285    SUBVN    8   3   3  ; 3
0286    MOV      9   4
0287    KSHORT  10   1
0288    MOV     11   5
0289    UGET    12   0      ; Blitbuffer
0290    TGETS   12  12  19  ; "gray"
0291    KNUM    13   5      ; 0.7
0292    CALL    12   0   2
0293    CALLM    6   1   5
0294    MOV      7   1
0295    TGETS    6   1   6  ; "paintRect"
0296    SUBVN    8   3   6  ; 6
0297    MOV      9   4
0298    KSHORT  10   1
0299    MOV     11   5
0300    UGET    12   0      ; Blitbuffer
0301    TGETS   12  12  19  ; "gray"
0302    KNUM    13   5      ; 0.7
0303    CALL    12   0   2
0304    CALLM    6   1   5
0305    MOV      7   1
0306    TGETS    6   1   6  ; "paintRect"
0307    KSHORT   8 100
0308    KSHORT   9 600
0309    KSHORT  10   1
0310    KSHORT  11 250
0311    UGET    12   0      ; Blitbuffer
0312    TGETS   12  12  19  ; "gray"
0313    KNUM    13   5      ; 0.7
0314    CALL    12   0   2
0315    CALLM    6   1   5
0316    MOV      7   1
0317    TGETS    6   1   6  ; "paintRect"
0318    KSHORT   8 700
0319    KSHORT   9 600
0320    KSHORT  10   1
0321    KSHORT  11 250
0322    UGET    12   0      ; Blitbuffer
0323    TGETS   12  12  19  ; "gray"
0324    KNUM    13   5      ; 0.7
0325    CALL    12   0   2
0326    CALLM    6   1   5
0327    UGET     6   1      ; RenderText
0328    MOV      7   6
0329    TGETS    6   6   9  ; "renderUtf8Text"
0330    MOV      8   1
0331    KSHORT   9 150
0332    KSHORT  10 670
0333    UGET    11   2      ; Font
0334    MOV     12  11
0335    TGETS   11  11  10  ; "getFace"
0336    KSTR    13  11      ; "ffont"
0337    KSHORT  14  26
0338    CALL    11   2   4
0339    KSTR    12  20      ; "Measure inches per 600 pixels"
0340    KPRI    13   2
0341    CALL     6   1   8
0342    UGET     6   1      ; RenderText
0343    MOV      7   6
0344    TGETS    6   6   9  ; "renderUtf8Text"
0345    MOV      8   1
0346    KSHORT   9 150
0347    KSHORT  10 770
0348    UGET    11   2      ; Font
0349    MOV     12  11
0350    TGETS   11  11  10  ; "getFace"
0351    KSTR    13  11      ; "ffont"
0352    KSHORT  14  22
0353    CALL    11   2   4
0354    KSTR    12  21      ; "Kobo Aura: 600 pixels/ 2.82 " = "
0355    KNUM    13   7      ; 212.76595744681
0356    KSTR    14  22      ; " dpi"
0357    CAT     12  12  14
0358    KPRI    13   2
0359    CALL     6   1   8
0360    RET0     0   1

-- BYTECODE -- wbuilder.lua:148-153
0001    UGET     1   0      ; UIManager
0002    MOV      2   1
0003    TGETS    1   1   0  ; "show"
0004    UGET     3   1      ; InfoMessage
0005    MOV      4   3
0006    TGETS    3   3   1  ; "new"
0007    TDUP     5   2
0008    CALL     3   0   3
0009    CALLM    1   1   1
0010    RET0     0   1

-- BYTECODE -- wbuilder.lua:155-159
0001    UGET     1   0      ; UIManager
0002    MOV      2   1
0003    TGETS    1   1   0  ; "show"
0004    UGET     3   1      ; ConfirmBox
0005    MOV      4   3
0006    TGETS    3   3   1  ; "new"
0007    TDUP     5   2
0008    CALL     3   0   3
0009    CALLM    1   1   1
0010    RET0     0   1

-- BYTECODE -- wbuilder.lua:161-163
0001    UGET     1   0      ; UIManager
0002    MOV      2   1
0003    TGETS    1   1   0  ; "quit"
0004    CALL     1   1   2
0005    RET0     0   1

-- BYTECODE -- wbuilder.lua:165-167
0001    UGET     1   0      ; UIManager
0002    MOV      2   1
0003    TGETS    1   1   0  ; "quit"
0004    CALL     1   1   2
0005    RET0     0   1

-- BYTECODE -- wbuilder.lua:188-188
0001    UGET     0   0      ; self
0002    MOV      1   0
0003    TGETS    0   0   0  ; "schedFunc"
0004    CALL     0   1   2
0005    RET0     0   1

-- BYTECODE -- wbuilder.lua:183-189
0001    TGETB    1   0   1
0002    TGETB    1   1   1
0003    MOV      2   1
0004    TGETS    1   1   0  ; "free"
0005    CALL     1   1   2
0006    TGETB    1   0   1
0007    MOV      3   0
0008    TGETS    2   0   1  ; "getTextWidget"
0009    CALL     2   2   2
0010    TSETB    2   1   1
0011    UGET     1   0      ; UIManager
0012    MOV      2   1
0013    TGETS    1   1   2  ; "setDirty"
0014    MOV      3   0
0015    CALL     1   1   3
0016    UGET     1   0      ; UIManager
0017    MOV      2   1
0018    TGETS    1   1   3  ; "scheduleIn"
0019    KSHORT   3   1
0020    FNEW     4   4      ; wbuilder.lua:188
0021    CALL     1   1   4
0022    UCLO     0 => 0023
0023 => RET0     0   1

-- BYTECODE -- wbuilder.lua:191-194
0001    TGETB    1   0   1
0002    MOV      3   0
0003    TGETS    2   0   0  ; "getTextWidget"
0004    CALL     2   2   2
0005    TSETB    2   1   1
0006    MOV      2   0
0007    TGETS    1   0   1  ; "schedFunc"
0008    CALL     1   1   2
0009    RET0     0   1

-- BYTECODE -- wbuilder.lua:196-204
0001    UGET     1   0      ; CenterContainer
0002    MOV      2   1
0003    TGETS    1   1   0  ; "new"
0004    TDUP     3   2
0005    TDUP     4   1
0006    TSETS    4   3   3  ; "dimen"
0007    UGET     4   1      ; TextWidget
0008    MOV      5   4
0009    TGETS    4   4   0  ; "new"
0010    TDUP     6   7
0011    GGET     7   4      ; "os"
0012    TGETS    7   7   5  ; "date"
0013    KSTR     8   6      ; "%H:%M:%S"
0014    CALL     7   2   2
0015    TSETS    7   6   8  ; "text"
0016    UGET     7   2      ; Font
0017    MOV      8   7
0018    TGETS    7   7   9  ; "getFace"
0019    KSTR     9  10      ; "cfont"
0020    KSHORT  10  12
0021    CALL     7   2   4
0022    TSETS    7   6  11  ; "face"
0023    CALL     4   0   3
0024    TSETM    4   0      ; 1
0025    CALLT    1   3

-- BYTECODE -- wbuilder.lua:214-218
0001    UGET     0   0      ; UIManager
0002    MOV      1   0
0003    TGETS    0   0   0  ; "show"
0004    UGET     2   1      ; InfoMessage
0005    MOV      3   2
0006    TGETS    2   2   1  ; "new"
0007    TDUP     4   2
0008    CALL     2   0   3
0009    CALLM    0   1   1
0010    RET0     0   1

-- BYTECODE -- wbuilder.lua:277-277
0001    RET0     0   1

-- BYTECODE -- wbuilder.lua:281-281
0001    RET0     0   1

-- BYTECODE -- wbuilder.lua:285-285
0001    RET0     0   1

-- BYTECODE -- wbuilder.lua:289-289
0001    RET0     0   1

-- BYTECODE -- wbuilder.lua:293-293
0001    RET0     0   1

-- BYTECODE -- wbuilder.lua:297-297
0001    RET0     0   1

-- BYTECODE -- wbuilder.lua:301-301
0001    RET0     0   1

-- BYTECODE -- wbuilder.lua:305-305
0001    RET0     0   1

-- BYTECODE -- wbuilder.lua:309-309
0001    RET0     0   1

-- BYTECODE -- wbuilder.lua:316-316
0001    RET0     0   1

-- BYTECODE -- wbuilder.lua:320-320
0001    RET0     0   1

-- BYTECODE -- wbuilder.lua:325-325
0001    UGET     0   0      ; DEBUG
0002    KSTR     1   0      ; "hello world!"
0003    CALL     0   1   2
0004    RET0     0   1

-- BYTECODE -- wbuilder.lua:335-335
0001    GGET     0   0      ; "print"
0002    KSTR     1   1      ; "Entered"
0003    CALL     0   1   2
0004    RET0     0   1

-- BYTECODE -- wbuilder.lua:346-378
0001    GGET     0   0      ; "require"
0002    KSTR     1   1      ; "ui/widget/keyvaluepage"
0003    CALL     0   2   2
0004    MOV      2   0
0005    TGETS    1   0   2  ; "new"
0006    TDUP     3   3
0007    TDUP     4  17
0008    TDUP     5   4
0009    TSETB    5   4   1
0010    TDUP     5   5
0011    TSETB    5   4   2
0012    TDUP     5   6
0013    TSETB    5   4   3
0014    TDUP     5   7
0015    TSETB    5   4   4
0016    TDUP     5   8
0017    TSETB    5   4   5
0018    TDUP     5   9
0019    TSETB    5   4   6
0020    TDUP     5  10
0021    TSETB    5   4   7
0022    TDUP     5  11
0023    TSETB    5   4   8
0024    TDUP     5  12
0025    TSETB    5   4   9
0026    TDUP     5  13
0027    TSETB    5   4  10
0028    TDUP     5  14
0029    TSETB    5   4  11
0030    TDUP     5  15
0031    TSETB    5   4  12
0032    TDUP     5  16
0033    TSETB    5   4  13
0034    TDUP     5  18
0035    TSETB    5   4  15
0036    TDUP     5  19
0037    TSETB    5   4  16
0038    TDUP     5  20
0039    TSETB    5   4  17
0040    TDUP     5  21
0041    TSETB    5   4  18
0042    TDUP     5  22
0043    TSETB    5   4  19
0044    TDUP     5  23
0045    TSETB    5   4  20
0046    TDUP     5  24
0047    TSETB    5   4  21
0048    TDUP     5  25
0049    TSETB    5   4  22
0050    TDUP     5  26
0051    TSETB    5   4  23
0052    TDUP     5  27
0053    TSETB    5   4  24
0054    TSETS    4   3  28  ; "kv_pairs"
0055    CALL     1   2   3
0056    UGET     2   0      ; UIManager
0057    MOV      3   2
0058    TGETS    2   2  29  ; "show"
0059    MOV      4   1
0060    CALL     2   1   3
0061    RET0     0   1

-- BYTECODE -- wbuilder.lua:380-396
0001    UGET     0   0      ; DocumentRegistry
0002    MOV      1   0
0003    TGETS    0   0   0  ; "openDocument"
0004    KSTR     2   1      ; "spec/front/unit/data/2col.pdf"
0005    CALL     0   2   3
0006    GSET     0   2      ; "doc"
0007    UGET     0   1      ; ReaderUI
0008    MOV      1   0
0009    TGETS    0   0   3  ; "new"
0010    TDUP     2   4
0011    GGET     3   5      ; "readerwindow"
0012    TSETS    3   2   6  ; "dialog"
0013    UGET     3   2      ; Geom
0014    MOV      4   3
0015    TGETS    3   3   3  ; "new"
0016    TDUP     5   8
0017    UGET     6   3      ; Screen
0018    MOV      7   6
0019    TGETS    6   6   7  ; "getWidth"
0020    CALL     6   2   2
0021    SUBVN    6   6   0  ; 100
0022    TSETS    6   5   9  ; "w"
0023    UGET     6   3      ; Screen
0024    MOV      7   6
0025    TGETS    6   6  10  ; "getHeight"
0026    CALL     6   2   2
0027    SUBVN    6   6   0  ; 100
0028    TSETS    6   5  11  ; "h"
0029    CALL     3   2   3
0030    TSETS    3   2  12  ; "dimen"
0031    GGET     3   2      ; "doc"
0032    TSETS    3   2  13  ; "document"
0033    CALL     0   2   3
0034    GSET     0  14      ; "reader"
0035    GGET     0  15      ; "require"
0036    KSTR     1  16      ; "ui/widget/bookstatuswidget"
0037    CALL     0   2   2
0038    MOV      1   0
0039    TGETS    0   0   3  ; "new"
0040    TDUP     2  18
0041    GGET     3   2      ; "doc"
0042    MOV      4   3
0043    TGETS    3   3  17  ; "getCoverPageImage"
0044    CALL     3   2   2
0045    TSETS    3   2  19  ; "thumbnail"
0046    GGET     3   2      ; "doc"
0047    MOV      4   3
0048    TGETS    3   3  20  ; "getProps"
0049    CALL     3   2   2
0050    TSETS    3   2  21  ; "props"
0051    GGET     3   2      ; "doc"
0052    TSETS    3   2  13  ; "document"
0053    GGET     3  14      ; "reader"
0054    TGETS    3   3  22  ; "view"
0055    TSETS    3   2  22  ; "view"
0056    CALL     0   2   3
0057    UGET     1   4      ; UIManager
0058    MOV      2   1
0059    TGETS    1   1  23  ; "show"
0060    MOV      3   0
0061    CALL     1   1   3
0062    RET0     0   1

-- BYTECODE -- wbuilder.lua:398-401
0001    GGET     0   0      ; "require"
0002    KSTR     1   1      ; "tools/kobo_touch_probe"
0003    CALL     0   2   2
0004    UGET     1   0      ; UIManager
0005    MOV      2   1
0006    TGETS    1   1   2  ; "show"
0007    MOV      4   0
0008    TGETS    3   0   3  ; "new"
0009    TNEW     5   0
0010    CALL     3   0   3
0011    CALLM    1   1   1
0012    RET0     0   1

-- BYTECODE -- wbuilder.lua:403-443
0001    TNEW     0   5
0002    TDUP     1   0
0003    TSETB    1   0   1
0004    TDUP     1   1
0005    TSETB    1   0   2
0006    TDUP     1   2
0007    TSETB    1   0   3
0008    TDUP     1   3
0009    TSETB    1   0   4
0010    KSHORT   1   1
0011    KSHORT   2  10
0012    KSHORT   3   1
0013    FORI     1 => 0032
0014 => GGET     5   4      ; "table"
0015    TGETS    5   5   5  ; "insert"
0016    MOV      6   0
0017    TDUP     7   8
0018    KSTR     8   6      ; "918-"
0019    GGET     9   7      ; "tostring"
0020    MOV     10   4
0021    CALL     9   2   2
0022    CAT      8   8   9
0023    TSETS    8   7   9  ; "ssid"
0024    MULVN    8   4   0  ; 2
0025    SUBNV    8   8   1  ; -58
0026    TSETS    8   7  10  ; "signal_level"
0027    MULVN    8   4   0  ; 2
0028    SUBNV    8   8   2  ; 84
0029    TSETS    8   7  11  ; "signal_quality"
0030    CALL     5   1   3
0031    FORL     1 => 0014
0032 => GGET     1  12      ; "require"
0033    KSTR     2  13      ; "ui/widget/networksetting"
0034    CALL     1   2   2
0035    MOV      2   1
0036    TGETS    1   1  14  ; "new"
0037    TDUP     3  15
0038    TSETS    0   3  16  ; "network_list"
0039    CALL     1   2   3
0040    UGET     2   0      ; UIManager
0041    MOV      3   2
0042    TGETS    2   2  17  ; "show"
0043    MOV      4   1
0044    CALL     2   1   3
0045    RET0     0   1

-- BYTECODE -- wbuilder.lua:0-465
0001    GGET     0   0      ; "require"
0002    KSTR     1   1      ; "defaults"
0003    CALL     0   1   2
0004    GGET     0   2      ; "print"
0005    GGET     1   3      ; "package"
0006    TGETS    1   1   4  ; "path"
0007    CALL     0   1   2
0008    GGET     0   3      ; "package"
0009    KSTR     1   5      ; "common/?.lua;rocks/share/lua/5.1/?.lua;f"~
0010    GGET     2   3      ; "package"
0011    TGETS    2   2   4  ; "path"
0012    CAT      1   1   2
0013    TSETS    1   0   4  ; "path"
0014    GGET     0   3      ; "package"
0015    KSTR     1   7      ; "common/?.so;common/?.dll;/usr/lib/lua/?."~
0016    GGET     2   3      ; "package"
0017    TGETS    2   2   6  ; "cpath"
0018    CAT      1   1   2
0019    TSETS    1   0   6  ; "cpath"
0020    GGET     0   0      ; "require"
0021    KSTR     1   8      ; "datastorage"
0022    CALL     0   2   2
0023    GGET     1   0      ; "require"
0024    KSTR     2   9      ; "gettext"
0025    CALL     1   2   2
0026    GGET     2   0      ; "require"
0027    KSTR     3  10      ; "luasettings"
0028    CALL     2   2   2
0029    MOV      3   2
0030    TGETS    2   2  11  ; "open"
0031    MOV      5   0
0032    TGETS    4   0  12  ; "getDataDir"
0033    CALL     4   2   2
0034    KSTR     5  13      ; "/settings.reader.lua"
0035    CAT      4   4   5
0036    CALL     2   2   3
0037    GSET     2  14      ; "G_reader_settings"
0038    GGET     2  14      ; "G_reader_settings"
0039    MOV      3   2
0040    TGETS    2   2  15  ; "readSetting"
0041    KSTR     4  16      ; "language"
0042    CALL     2   2   3
0043    ISF          2
0044    JMP      3 => 0048
0045    TGETS    3   1  17  ; "changeLang"
0046    MOV      4   2
0047    CALL     3   1   2
0048 => GGET     3   0      ; "require"
0049    KSTR     4  18      ; "device"
0050    CALL     3   2   2
0051    GGET     4   0      ; "require"
0052    KSTR     5  19      ; "document/canvascontext"
0053    CALL     4   2   2
0054    MOV      6   4
0055    TGETS    5   4  20  ; "init"
0056    MOV      7   3
0057    CALL     5   1   3
0058    GGET     5   0      ; "require"
0059    KSTR     6  21      ; "ui/uimanager"
0060    CALL     5   2   2
0061    GGET     6   0      ; "require"
0062    KSTR     7  22      ; "ui/rendertext"
0063    CALL     6   2   2
0064    GGET     7   0      ; "require"
0065    KSTR     8  23      ; "ui/font"
0066    CALL     7   2   2
0067    GGET     8   0      ; "require"
0068    KSTR     9  24      ; "ui/geometry"
0069    CALL     8   2   2
0070    GGET     9   0      ; "require"
0071    KSTR    10  25      ; "ui/widget/menu"
0072    CALL     9   2   2
0073    GGET    10   0      ; "require"
0074    KSTR    11  26      ; "ui/widget/widget"
0075    CALL    10   2   2
0076    GGET    11   0      ; "require"
0077    KSTR    12  27      ; "ui/widget/textwidget"
0078    CALL    11   2   2
0079    GGET    12   0      ; "require"
0080    KSTR    13  28      ; "ui/widget/infomessage"
0081    CALL    12   2   2
0082    GGET    13   0      ; "require"
0083    KSTR    14  29      ; "ui/widget/container/inputcontainer"
0084    CALL    13   2   2
0085    GGET    14   0      ; "require"
0086    KSTR    15  30      ; "ui/widget/container/centercontainer"
0087    CALL    14   2   2
0088    GGET    15   0      ; "require"
0089    KSTR    16  31      ; "ui/widget/container/framecontainer"
0090    CALL    15   2   2
0091    GGET    16   0      ; "require"
0092    KSTR    17  32      ; "ui/widget/container/alphacontainer"
0093    CALL    16   2   2
0094    GGET    17   0      ; "require"
0095    KSTR    18  33      ; "ui/widget/confirmbox"
0096    CALL    17   2   2
0097    GGET    18   0      ; "require"
0098    KSTR    19  34      ; "ui/widget/touchmenu"
0099    CALL    18   2   2
0100    GGET    19   0      ; "require"
0101    KSTR    20  35      ; "document/documentregistry"
0102    CALL    19   2   2
0103    GGET    20   0      ; "require"
0104    KSTR    21  36      ; "apps/reader/readerui"
0105    CALL    20   2   2
0106    GGET    21   0      ; "require"
0107    KSTR    22  37      ; "dbg"
0108    CALL    21   2   2
0109    GGET    22   0      ; "require"
0110    KSTR    23  18      ; "device"
0111    CALL    22   2   2
0112    TGETS   22  22  38  ; "screen"
0113    GGET    23   0      ; "require"
0114    KSTR    24  39      ; "ffi/blitbuffer"
0115    CALL    23   2   2
0116    GGET    24   0      ; "require"
0117    KSTR    25  40      ; "ui/widget/inputtext"
0118    CALL    24   2   2
0119    MOV     26  21
0120    TGETS   25  21  41  ; "turnOn"
0121    CALL    25   1   2
0122    MOV     26  10
0123    TGETS   25  10  42  ; "new"
0124    TNEW    27   0
0125    CALL    25   2   3
0126    GSET    25  43      ; "TestGrid"
0127    MOV     26  10
0128    TGETS   25  10  42  ; "new"
0129    TNEW    27   0
0130    CALL    25   2   3
0131    GSET    25  44      ; "TestVisible"
0132    GGET    25  43      ; "TestGrid"
0133    FNEW    26  46      ; wbuilder.lua:53
0134    TSETS   26  25  45  ; "paintTo"
0135    GGET    25  44      ; "TestVisible"
0136    FNEW    26  47      ; wbuilder.lua:68
0137    TSETS   26  25  45  ; "paintTo"
0138    MOV     26  13
0139    TGETS   25  13  42  ; "new"
0140    TDUP    27  48
0141    TDUP    28  50
0142    TNEW    29   3
0143    TDUP    30  49
0144    TSETB   30  29   1
0145    TSETS   29  28  51  ; "OpenDialog"
0146    TNEW    29   3
0147    TDUP    30  52
0148    TSETB   30  29   1
0149    TSETS   29  28  53  ; "OpenConfirmBox"
0150    TNEW    29   3
0151    TNEW    30   3
0152    TDUP    31  54
0153    TSETB   31  30   1
0154    TSETB   30  29   1
0155    TSETS   29  28  55  ; "QuitApplication"
0156    TSETS   28  27  56  ; "key_events"
0157    MOV     29  15
0158    TGETS   28  15  42  ; "new"
0159    TDUP    30  58
0160    TGETS   31  23  57  ; "COLOR_DARK_GRAY"
0161    TSETS   31  30  59  ; "background"
0162    MOV     32  22
0163    TGETS   31  22  60  ; "getSize"
0164    CALL    31   2   2
0165    TSETS   31  30  61  ; "dimen"
0166    MOV     32  10
0167    TGETS   31  10  42  ; "new"
0168    TDUP    33  67
0169    TDUP    34  63
0170    MOV     36  22
0171    TGETS   35  22  62  ; "getWidth"
0172    CALL    35   2   2
0173    TSETS   35  34  64  ; "w"
0174    MOV     36  22
0175    TGETS   35  22  65  ; "getHeight"
0176    CALL    35   2   2
0177    TSETS   35  34  66  ; "h"
0178    TSETS   34  33  61  ; "dimen"
0179    CALL    31   0   3
0180    TSETM   31   0      ; 1
0181    CALL    28   0   3
0182    TSETM   28   0      ; 1
0183    CALL    25   2   3
0184    GSET    25  68      ; "Background"
0185    GGET    25  68      ; "Background"
0186    FNEW    26  70      ; wbuilder.lua:148
0187    TSETS   26  25  69  ; "onOpenDialog"
0188    GGET    25  68      ; "Background"
0189    FNEW    26  72      ; wbuilder.lua:155
0190    TSETS   26  25  71  ; "onOpenConfirmBox"
0191    GGET    25  68      ; "Background"
0192    FNEW    26  74      ; wbuilder.lua:161
0193    TSETS   26  25  73  ; "onInputError"
0194    GGET    25  68      ; "Background"
0195    FNEW    26  76      ; wbuilder.lua:165
0196    TSETS   26  25  75  ; "onQuitApplication"
0197    MOV     26  16
0198    TGETS   25  16  42  ; "new"
0199    TDUP    27  77
0200    MOV     29  15
0201    TGETS   28  15  42  ; "new"
0202    TDUP    30  79
0203    TGETS   31  23  78  ; "COLOR_WHITE"
0204    TSETS   31  30  59  ; "background"
0205    MOV     32  22
0206    TGETS   31  22  80  ; "scaleBySize"
0207    KSHORT  33   1
0208    CALL    31   2   3
0209    TSETS   31  30  81  ; "bordersize"
0210    MOV     32  22
0211    TGETS   31  22  80  ; "scaleBySize"
0212    KSHORT  33   1
0213    CALL    31   2   3
0214    TSETS   31  30  82  ; "padding"
0215    CALL    28   0   3
0216    TSETM   28   0      ; 1
0217    CALL    25   2   3
0218    GSET    25  83      ; "Clock"
0219    GGET    25  83      ; "Clock"
0220    FNEW    26  85      ; wbuilder.lua:183
0221    TSETS   26  25  84  ; "schedFunc"
0222    GGET    25  83      ; "Clock"
0223    FNEW    26  87      ; wbuilder.lua:191
0224    TSETS   26  25  86  ; "onShow"
0225    GGET    25  83      ; "Clock"
0226    FNEW    26  89      ; wbuilder.lua:196
0227    TSETS   26  25  88  ; "getTextWidget"
0228    MOV     26  17
0229    TGETS   25  17  42  ; "new"
0230    TDUP    27  90
0231    MOV     29  22
0232    TGETS   28  22  80  ; "scaleBySize"
0233    KSHORT  30 300
0234    CALL    28   2   3
0235    TSETS   28  27  91  ; "width"
0236    FNEW    28  92      ; wbuilder.lua:214
0237    TSETS   28  27  93  ; "cancel_callback"
0238    CALL    25   2   3
0239    GSET    25  94      ; "Quiz"
0240    TNEW    25  19
0241    TDUP    26  95
0242    TSETB   26  25   1
0243    TDUP    26  96
0244    TSETB   26  25   2
0245    TDUP    26  97
0246    TSETB   26  25   3
0247    TDUP    26  98
0248    TSETB   26  25   4
0249    TDUP    26  99
0250    TSETB   26  25   5
0251    TDUP    26 100
0252    TSETB   26  25   6
0253    TDUP    26 101
0254    TSETB   26  25   7
0255    TDUP    26 102
0256    TSETB   26  25   8
0257    TDUP    26 103
0258    TSETB   26  25   9
0259    TDUP    26 104
0260    TSETB   26  25  10
0261    TDUP    26 105
0262    TSETB   26  25  11
0263    TDUP    26 106
0264    TSETB   26  25  12
0265    TDUP    26 107
0266    TSETB   26  25  13
0267    TDUP    26 108
0268    TSETB   26  25  14
0269    TDUP    26 109
0270    TSETB   26  25  15
0271    TDUP    26 110
0272    TSETB   26  25  16
0273    TDUP    26 111
0274    TSETB   26  25  17
0275    TDUP    26 112
0276    TSETB   26  25  18
0277    GSET    25 113      ; "menu_items"
0278    MOV     26   9
0279    TGETS   25   9  42  ; "new"
0280    TDUP    27 114
0281    GGET    28 113      ; "menu_items"
0282    TSETS   28  27 115  ; "item_table"
0283    MOV     29  22
0284    TGETS   28  22  80  ; "scaleBySize"
0285    KSHORT  30 500
0286    CALL    28   2   3
0287    TSETS   28  27  91  ; "width"
0288    MOV     29  22
0289    TGETS   28  22  80  ; "scaleBySize"
0290    KSHORT  30 600
0291    CALL    28   2   3
0292    TSETS   28  27 116  ; "height"
0293    CALL    25   2   3
0294    GSET    25 117      ; "M"
0295    MOV     26  14
0296    TGETS   25  14  42  ; "new"
0297    TDUP    27 118
0298    MOV     29  22
0299    TGETS   28  22  60  ; "getSize"
0300    CALL    28   2   2
0301    TSETS   28  27  61  ; "dimen"
0302    MOV     29  15
0303    TGETS   28  15  42  ; "new"
0304    TDUP    30 120
0305    TGETS   31  23 119  ; "COLOR_BLACK"
0306    TSETS   31  30  59  ; "background"
0307    CALL    28   0   3
0308    TSETM   28   0      ; 1
0309    CALL    25   2   3
0310    GSET    25 121      ; "readerwindow"
0311    MOV     26  20
0312    TGETS   25  20  42  ; "new"
0313    TDUP    27 122
0314    GGET    28 121      ; "readerwindow"
0315    TSETS   28  27 123  ; "dialog"
0316    MOV     29   8
0317    TGETS   28   8  42  ; "new"
0318    TDUP    30 124
0319    MOV     32  22
0320    TGETS   31  22  62  ; "getWidth"
0321    CALL    31   2   2
0322    SUBVN   31  31   1  ; 100
0323    TSETS   31  30  64  ; "w"
0324    MOV     32  22
0325    TGETS   31  22  65  ; "getHeight"
0326    CALL    31   2   2
0327    SUBVN   31  31   1  ; 100
0328    TSETS   31  30  66  ; "h"
0329    CALL    28   2   3
0330    TSETS   28  27  61  ; "dimen"
0331    MOV     29  19
0332    TGETS   28  19 125  ; "openDocument"
0333    KSTR    30 126      ; "spec/front/unit/data/2col.pdf"
0334    CALL    28   2   3
0335    TSETS   28  27 127  ; "document"
0336    CALL    25   2   3
0337    GSET    25 128      ; "reader"
0338    GGET    25 121      ; "readerwindow"
0339    TGETB   25  25   1
0340    GGET    26 128      ; "reader"
0341    TSETB   26  25   1
0342    MOV     26  18
0343    TGETS   25  18  42  ; "new"
0344    TDUP    27 129
0345    MOV     29  22
0346    TGETS   28  22  62  ; "getWidth"
0347    CALL    28   2   2
0348    TSETS   28  27  91  ; "width"
0349    TNEW    28   4
0350    TDUP    29 130
0351    TDUP    30 131
0352    FNEW    31 132      ; wbuilder.lua:277
0353    TSETS   31  30 133  ; "callback"
0354    TSETB   30  29   1
0355    TDUP    30 134
0356    FNEW    31 135      ; wbuilder.lua:281
0357    TSETS   31  30 133  ; "callback"
0358    TSETB   30  29   2
0359    TDUP    30 136
0360    FNEW    31 137      ; wbuilder.lua:285
0361    TSETS   31  30 133  ; "callback"
0362    TSETB   30  29   3
0363    TDUP    30 138
0364    FNEW    31 139      ; wbuilder.lua:289
0365    TSETS   31  30 133  ; "callback"
0366    TSETB   30  29   4
0367    TDUP    30 140
0368    FNEW    31 141      ; wbuilder.lua:293
0369    TSETS   31  30 133  ; "callback"
0370    TSETB   30  29   5
0371    TDUP    30 142
0372    FNEW    31 143      ; wbuilder.lua:297
0373    TSETS   31  30 133  ; "callback"
0374    TSETB   30  29   6
0375    TDUP    30 144
0376    FNEW    31 145      ; wbuilder.lua:301
0377    TSETS   31  30 133  ; "callback"
0378    TSETB   30  29   7
0379    TDUP    30 146
0380    FNEW    31 147      ; wbuilder.lua:305
0381    TSETS   31  30 133  ; "callback"
0382    TSETB   30  29   8
0383    TDUP    30 148
0384    FNEW    31 149      ; wbuilder.lua:309
0385    TSETS   31  30 133  ; "callback"
0386    TSETB   30  29   9
0387    TSETB   29  28   1
0388    TDUP    29 150
0389    TDUP    30 151
0390    FNEW    31 152      ; wbuilder.lua:316
0391    TSETS   31  30 133  ; "callback"
0392    TSETB   30  29   1
0393    TDUP    30 153
0394    FNEW    31 154      ; wbuilder.lua:320
0395    TSETS   31  30 133  ; "callback"
0396    TSETB   30  29   2
0397    TSETB   29  28   2
0398    TDUP    29 155
0399    FNEW    30 156      ; wbuilder.lua:325
0400    TSETS   30  29 133  ; "callback"
0401    TSETB   29  28   3
0402    TSETS   28  27 157  ; "tab_item_table"
0403    CALL    25   2   3
0404    GSET    25 158      ; "touch_menu"
0405    MOV     26  24
0406    TGETS   25  24  42  ; "new"
0407    TDUP    27 159
0408    MOV     29  22
0409    TGETS   28  22  80  ; "scaleBySize"
0410    KSHORT  30 400
0411    CALL    28   2   3
0412    TSETS   28  27  91  ; "width"
0413    FNEW    28 160      ; wbuilder.lua:335
0414    TSETS   28  27 161  ; "enter_callback"
0415    TDUP    28 162
0416    TSETS   28  27 163  ; "parent"
0417    CALL    25   2   3
0418    FNEW    26 164      ; wbuilder.lua:346
0419    GSET    26 165      ; "testKeyValuePage"
0420    FNEW    26 166      ; wbuilder.lua:380
0421    GSET    26 167      ; "testBookStatus"
0422    FNEW    26 168      ; wbuilder.lua:398
0423    GSET    26 169      ; "testTouchProbe"
0424    FNEW    26 170      ; wbuilder.lua:403
0425    GSET    26 171      ; "testNetworkSetting"
0426    MOV     27   5
0427    TGETS   26   5 172  ; "show"
0428    GGET    28  44      ; "TestVisible"
0429    CALL    26   1   3
0430    MOV     27   5
0431    TGETS   26   5 172  ; "show"
0432    GGET    28  83      ; "Clock"
0433    MOV     29  28
0434    TGETS   28  28  42  ; "new"
0435    CALL    28   0   2
0436    CALLM   26   1   1
0437    GGET    26 171      ; "testNetworkSetting"
0438    CALL    26   1   1
0439    MOV     27   5
0440    TGETS   26   5 173  ; "run"
0441    CALL    26   1   2
0442    UCLO     0 => 0443
0443 => RET0     0   1

