
main <./tools/wbuilder.lua:0,0> (454 instructions, 1816 bytes at 0x7ffab7505050)
0+ params, 44 slots, 0 upvalues, 26 locals, 148 constants, 27 functions
	1	[4]	GETGLOBAL	0 -1	; require
	2	[4]	LOADK    	1 -2	; "defaults"
	3	[4]	CALL     	0 2 1
	4	[5]	GETGLOBAL	0 -3	; print
	5	[5]	GETGLOBAL	1 -4	; package
	6	[5]	GETTABLE 	1 1 -5	; "path"
	7	[5]	CALL     	0 2 1
	8	[6]	GETGLOBAL	0 -4	; package
	9	[6]	LOADK    	1 -6	; "common/?.lua;rocks/share/lua/5.1/?.lua;frontend/?.lua;"
	10	[6]	GETGLOBAL	2 -4	; package
	11	[6]	GETTABLE 	2 2 -5	; "path"
	12	[6]	CONCAT   	1 1 2
	13	[6]	SETTABLE 	0 -5 1	; "path" -
	14	[7]	GETGLOBAL	0 -4	; package
	15	[7]	LOADK    	1 -8	; "common/?.so;common/?.dll;/usr/lib/lua/?.so;rocks/lib/lua/5.1/?.so;"
	16	[7]	GETGLOBAL	2 -4	; package
	17	[7]	GETTABLE 	2 2 -7	; "cpath"
	18	[7]	CONCAT   	1 1 2
	19	[7]	SETTABLE 	0 -7 1	; "cpath" -
	20	[9]	GETGLOBAL	0 -1	; require
	21	[9]	LOADK    	1 -9	; "datastorage"
	22	[9]	CALL     	0 2 2
	23	[10]	GETGLOBAL	1 -1	; require
	24	[10]	LOADK    	2 -10	; "gettext"
	25	[10]	CALL     	1 2 2
	26	[15]	GETGLOBAL	2 -1	; require
	27	[15]	LOADK    	3 -12	; "luasettings"
	28	[15]	CALL     	2 2 2
	29	[15]	SELF     	2 2 -13	; "open"
	30	[16]	SELF     	4 0 -14	; "getDataDir"
	31	[16]	CALL     	4 2 2
	32	[16]	LOADK    	5 -15	; "/settings.reader.lua"
	33	[16]	CONCAT   	4 4 5
	34	[15]	CALL     	2 3 2
	35	[16]	SETGLOBAL	2 -11	; G_reader_settings
	36	[17]	GETGLOBAL	2 -11	; G_reader_settings
	37	[17]	SELF     	2 2 -16	; "readSetting"
	38	[17]	LOADK    	4 -17	; "language"
	39	[17]	CALL     	2 3 2
	40	[18]	TEST     	2 0 0
	41	[18]	JMP      	3	; to 45
	42	[19]	GETTABLE 	3 1 -18	; "changeLang"
	43	[19]	MOVE     	4 2
	44	[19]	CALL     	3 2 1
	45	[21]	GETGLOBAL	3 -1	; require
	46	[21]	LOADK    	4 -19	; "device"
	47	[21]	CALL     	3 2 2
	48	[22]	GETGLOBAL	4 -1	; require
	49	[22]	LOADK    	5 -20	; "document/canvascontext"
	50	[22]	CALL     	4 2 2
	51	[23]	SELF     	5 4 -21	; "init"
	52	[23]	MOVE     	7 3
	53	[23]	CALL     	5 3 1
	54	[24]	GETGLOBAL	5 -1	; require
	55	[24]	LOADK    	6 -22	; "ui/uimanager"
	56	[24]	CALL     	5 2 2
	57	[25]	GETGLOBAL	6 -1	; require
	58	[25]	LOADK    	7 -23	; "ui/rendertext"
	59	[25]	CALL     	6 2 2
	60	[26]	GETGLOBAL	7 -1	; require
	61	[26]	LOADK    	8 -24	; "ui/font"
	62	[26]	CALL     	7 2 2
	63	[27]	GETGLOBAL	8 -1	; require
	64	[27]	LOADK    	9 -25	; "ui/geometry"
	65	[27]	CALL     	8 2 2
	66	[28]	GETGLOBAL	9 -1	; require
	67	[28]	LOADK    	10 -26	; "ui/widget/menu"
	68	[28]	CALL     	9 2 2
	69	[29]	GETGLOBAL	10 -1	; require
	70	[29]	LOADK    	11 -27	; "ui/widget/widget"
	71	[29]	CALL     	10 2 2
	72	[30]	GETGLOBAL	11 -1	; require
	73	[30]	LOADK    	12 -28	; "ui/widget/textwidget"
	74	[30]	CALL     	11 2 2
	75	[31]	GETGLOBAL	12 -1	; require
	76	[31]	LOADK    	13 -29	; "ui/widget/infomessage"
	77	[31]	CALL     	12 2 2
	78	[32]	GETGLOBAL	13 -1	; require
	79	[32]	LOADK    	14 -30	; "ui/widget/container/inputcontainer"
	80	[32]	CALL     	13 2 2
	81	[33]	GETGLOBAL	14 -1	; require
	82	[33]	LOADK    	15 -31	; "ui/widget/container/centercontainer"
	83	[33]	CALL     	14 2 2
	84	[34]	GETGLOBAL	15 -1	; require
	85	[34]	LOADK    	16 -32	; "ui/widget/container/framecontainer"
	86	[34]	CALL     	15 2 2
	87	[35]	GETGLOBAL	16 -1	; require
	88	[35]	LOADK    	17 -33	; "ui/widget/container/alphacontainer"
	89	[35]	CALL     	16 2 2
	90	[36]	GETGLOBAL	17 -1	; require
	91	[36]	LOADK    	18 -34	; "ui/widget/confirmbox"
	92	[36]	CALL     	17 2 2
	93	[37]	GETGLOBAL	18 -1	; require
	94	[37]	LOADK    	19 -35	; "ui/widget/touchmenu"
	95	[37]	CALL     	18 2 2
	96	[38]	GETGLOBAL	19 -1	; require
	97	[38]	LOADK    	20 -36	; "document/documentregistry"
	98	[38]	CALL     	19 2 2
	99	[39]	GETGLOBAL	20 -1	; require
	100	[39]	LOADK    	21 -37	; "apps/reader/readerui"
	101	[39]	CALL     	20 2 2
	102	[40]	GETGLOBAL	21 -1	; require
	103	[40]	LOADK    	22 -38	; "dbg"
	104	[40]	CALL     	21 2 2
	105	[41]	GETGLOBAL	22 -1	; require
	106	[41]	LOADK    	23 -19	; "device"
	107	[41]	CALL     	22 2 2
	108	[41]	GETTABLE 	22 22 -39	; "screen"
	109	[42]	GETGLOBAL	23 -1	; require
	110	[42]	LOADK    	24 -40	; "ffi/blitbuffer"
	111	[42]	CALL     	23 2 2
	112	[43]	GETGLOBAL	24 -1	; require
	113	[43]	LOADK    	25 -41	; "ui/widget/inputtext"
	114	[43]	CALL     	24 2 2
	115	[45]	SELF     	25 21 -42	; "turnOn"
	116	[45]	CALL     	25 2 1
	117	[50]	SELF     	25 10 -44	; "new"
	118	[50]	NEWTABLE 	27 0 0
	119	[50]	CALL     	25 3 2
	120	[50]	SETGLOBAL	25 -43	; TestGrid
	121	[51]	SELF     	25 10 -44	; "new"
	122	[51]	NEWTABLE 	27 0 0
	123	[51]	CALL     	25 3 2
	124	[51]	SETGLOBAL	25 -45	; TestVisible
	125	[53]	GETGLOBAL	25 -43	; TestGrid
	126	[66]	CLOSURE  	26 0	; 0x7ffab7505330
	127	[66]	MOVE     	0 6
	128	[66]	MOVE     	0 7
	129	[66]	MOVE     	0 23
	130	[53]	SETTABLE 	25 -46 26	; "paintTo" -
	131	[68]	GETGLOBAL	25 -45	; TestVisible
	132	[122]	CLOSURE  	26 1	; 0x7ffab7506980
	133	[122]	MOVE     	0 23
	134	[122]	MOVE     	0 6
	135	[122]	MOVE     	0 7
	136	[68]	SETTABLE 	25 -46 26	; "paintTo" -
	137	[127]	SELF     	25 13 -44	; "new"
	138	[127]	NEWTABLE 	27 0 2
	139	[128]	SETTABLE 	27 -48 -49	; "is_always_active" true
	140	[129]	NEWTABLE 	28 0 3
	141	[130]	NEWTABLE 	29 1 0
	142	[130]	NEWTABLE 	30 1 0
	143	[130]	LOADK    	31 -52	; "Press"
	144	[130]	SETLIST  	30 1 1	; 1
	145	[130]	SETLIST  	29 1 1	; 1
	146	[130]	SETTABLE 	28 -51 29	; "OpenDialog" -
	147	[131]	NEWTABLE 	29 1 0
	148	[131]	NEWTABLE 	30 1 0
	149	[131]	LOADK    	31 -54	; "Del"
	150	[131]	SETLIST  	30 1 1	; 1
	151	[131]	SETLIST  	29 1 1	; 1
	152	[131]	SETTABLE 	28 -53 29	; "OpenConfirmBox" -
	153	[132]	NEWTABLE 	29 1 0
	154	[132]	NEWTABLE 	30 1 0
	155	[132]	NEWTABLE 	31 2 0
	156	[132]	LOADK    	32 -56	; "Home"
	157	[132]	LOADK    	33 -57	; "Back"
	158	[132]	SETLIST  	31 2 1	; 1
	159	[132]	SETLIST  	30 1 1	; 1
	160	[132]	SETLIST  	29 1 1	; 1
	161	[132]	SETTABLE 	28 -55 29	; "QuitApplication" -
	162	[133]	SETTABLE 	27 -50 28	; "key_events" -
	163	[135]	SELF     	28 15 -44	; "new"
	164	[135]	NEWTABLE 	30 0 3
	165	[136]	GETTABLE 	31 23 -59	; "COLOR_DARK_GRAY"
	166	[136]	SETTABLE 	30 -58 31	; "background" -
	167	[137]	SETTABLE 	30 -60 -61	; "bordersize" 0
	168	[138]	SELF     	31 22 -63	; "getSize"
	169	[138]	CALL     	31 2 2
	170	[138]	SETTABLE 	30 -62 31	; "dimen" -
	171	[139]	SELF     	31 10 -44	; "new"
	172	[139]	NEWTABLE 	33 0 1
	173	[140]	NEWTABLE 	34 0 2
	174	[141]	SELF     	35 22 -65	; "getWidth"
	175	[141]	CALL     	35 2 2
	176	[141]	SETTABLE 	34 -64 35	; "w" -
	177	[142]	SELF     	35 22 -67	; "getHeight"
	178	[142]	CALL     	35 2 2
	179	[142]	SETTABLE 	34 -66 35	; "h" -
	180	[143]	SETTABLE 	33 -62 34	; "dimen" -
	181	[139]	CALL     	31 3 0
	182	[145]	SETLIST  	30 0 1	; 1
	183	[135]	CALL     	28 3 0
	184	[146]	SETLIST  	27 0 1	; 1
	185	[127]	CALL     	25 3 2
	186	[146]	SETGLOBAL	25 -47	; Background
	187	[148]	GETGLOBAL	25 -47	; Background
	188	[153]	CLOSURE  	26 2	; 0x7ffab7505d20
	189	[153]	MOVE     	0 5
	190	[153]	MOVE     	0 12
	191	[148]	SETTABLE 	25 -68 26	; "onOpenDialog" -
	192	[155]	GETGLOBAL	25 -47	; Background
	193	[159]	CLOSURE  	26 3	; 0x7ffab7507460
	194	[159]	MOVE     	0 5
	195	[159]	MOVE     	0 17
	196	[155]	SETTABLE 	25 -69 26	; "onOpenConfirmBox" -
	197	[161]	GETGLOBAL	25 -47	; Background
	198	[163]	CLOSURE  	26 4	; 0x7ffab75077c0
	199	[163]	MOVE     	0 5
	200	[161]	SETTABLE 	25 -70 26	; "onInputError" -
	201	[165]	GETGLOBAL	25 -47	; Background
	202	[167]	CLOSURE  	26 5	; 0x7ffab7507be0
	203	[167]	MOVE     	0 5
	204	[165]	SETTABLE 	25 -71 26	; "onQuitApplication" -
	205	[172]	SELF     	25 16 -44	; "new"
	206	[172]	NEWTABLE 	27 0 1
	207	[173]	SETTABLE 	27 -73 -74	; "alpha" 0.7
	208	[175]	SELF     	28 15 -44	; "new"
	209	[175]	NEWTABLE 	30 0 4
	210	[176]	GETTABLE 	31 23 -75	; "COLOR_WHITE"
	211	[176]	SETTABLE 	30 -58 31	; "background" -
	212	[177]	SELF     	31 22 -76	; "scaleBySize"
	213	[177]	LOADK    	33 -77	; 1
	214	[177]	CALL     	31 3 2
	215	[177]	SETTABLE 	30 -60 31	; "bordersize" -
	216	[178]	SETTABLE 	30 -78 -61	; "margin" 0
	217	[179]	SELF     	31 22 -76	; "scaleBySize"
	218	[179]	LOADK    	33 -77	; 1
	219	[179]	CALL     	31 3 2
	220	[179]	SETTABLE 	30 -79 31	; "padding" -
	221	[175]	CALL     	28 3 0
	222	[181]	SETLIST  	27 0 1	; 1
	223	[172]	CALL     	25 3 2
	224	[181]	SETGLOBAL	25 -72	; Clock
	225	[183]	GETGLOBAL	25 -72	; Clock
	226	[189]	CLOSURE  	26 6	; 0x7ffab75080b0
	227	[189]	MOVE     	0 5
	228	[183]	SETTABLE 	25 -80 26	; "schedFunc" -
	229	[191]	GETGLOBAL	25 -72	; Clock
	230	[194]	CLOSURE  	26 7	; 0x7ffab75086c0
	231	[191]	SETTABLE 	25 -81 26	; "onShow" -
	232	[196]	GETGLOBAL	25 -72	; Clock
	233	[204]	CLOSURE  	26 8	; 0x7ffab75089e0
	234	[204]	MOVE     	0 14
	235	[204]	MOVE     	0 11
	236	[204]	MOVE     	0 7
	237	[196]	SETTABLE 	25 -82 26	; "getTextWidget" -
	238	[209]	SELF     	25 17 -44	; "new"
	239	[209]	NEWTABLE 	27 0 5
	240	[210]	SETTABLE 	27 -84 -85	; "text" "Tell me the truth, isn't it COOL?!"
	241	[211]	SELF     	28 22 -76	; "scaleBySize"
	242	[211]	LOADK    	30 -87	; 300
	243	[211]	CALL     	28 3 2
	244	[211]	SETTABLE 	27 -86 28	; "width" -
	245	[212]	SETTABLE 	27 -88 -89	; "ok_text" "Yes, of course."
	246	[213]	SETTABLE 	27 -90 -91	; "cancel_text" "No, it's ugly."
	247	[218]	CLOSURE  	28 9	; 0x7ffab7508e00
	248	[218]	MOVE     	0 5
	249	[218]	MOVE     	0 12
	250	[218]	SETTABLE 	27 -92 28	; "cancel_callback" -
	251	[209]	CALL     	25 3 2
	252	[219]	SETGLOBAL	25 -83	; Quiz
	253	[224]	NEWTABLE 	25 17 0
	254	[224]	NEWTABLE 	26 0 1
	255	[225]	SETTABLE 	26 -84 -94	; "text" "item1"
	256	[225]	NEWTABLE 	27 0 1
	257	[226]	SETTABLE 	27 -84 -95	; "text" "item2"
	258	[226]	NEWTABLE 	28 0 1
	259	[227]	SETTABLE 	28 -84 -96	; "text" "This is a very very log item whose length should exceed the width of the menu."
	260	[227]	NEWTABLE 	29 0 1
	261	[228]	SETTABLE 	29 -84 -97	; "text" "item3"
	262	[228]	NEWTABLE 	30 0 1
	263	[229]	SETTABLE 	30 -84 -98	; "text" "item4"
	264	[229]	NEWTABLE 	31 0 1
	265	[230]	SETTABLE 	31 -84 -99	; "text" "item5"
	266	[230]	NEWTABLE 	32 0 1
	267	[231]	SETTABLE 	32 -84 -100	; "text" "item6"
	268	[231]	NEWTABLE 	33 0 1
	269	[232]	SETTABLE 	33 -84 -101	; "text" "item7"
	270	[232]	NEWTABLE 	34 0 1
	271	[233]	SETTABLE 	34 -84 -102	; "text" "item8"
	272	[233]	NEWTABLE 	35 0 1
	273	[234]	SETTABLE 	35 -84 -103	; "text" "item9"
	274	[234]	NEWTABLE 	36 0 1
	275	[235]	SETTABLE 	36 -84 -104	; "text" "item10"
	276	[235]	NEWTABLE 	37 0 1
	277	[236]	SETTABLE 	37 -84 -105	; "text" "item11"
	278	[236]	NEWTABLE 	38 0 1
	279	[237]	SETTABLE 	38 -84 -106	; "text" "item12"
	280	[237]	NEWTABLE 	39 0 1
	281	[238]	SETTABLE 	39 -84 -107	; "text" "item13"
	282	[238]	NEWTABLE 	40 0 1
	283	[239]	SETTABLE 	40 -84 -108	; "text" "item14"
	284	[239]	NEWTABLE 	41 0 1
	285	[240]	SETTABLE 	41 -84 -109	; "text" "item15"
	286	[240]	NEWTABLE 	42 0 1
	287	[241]	SETTABLE 	42 -84 -110	; "text" "item16"
	288	[241]	NEWTABLE 	43 0 1
	289	[242]	SETTABLE 	43 -84 -111	; "text" "item17"
	290	[243]	SETLIST  	25 18 1	; 1
	291	[243]	SETGLOBAL	25 -93	; menu_items
	292	[244]	SELF     	25 9 -44	; "new"
	293	[244]	NEWTABLE 	27 0 4
	294	[245]	SETTABLE 	27 -113 -114	; "title" "Test Menu"
	295	[246]	GETGLOBAL	28 -93	; menu_items
	296	[246]	SETTABLE 	27 -115 28	; "item_table" -
	297	[247]	SELF     	28 22 -76	; "scaleBySize"
	298	[247]	LOADK    	30 -116	; 500
	299	[247]	CALL     	28 3 2
	300	[247]	SETTABLE 	27 -86 28	; "width" -
	301	[248]	SELF     	28 22 -76	; "scaleBySize"
	302	[248]	LOADK    	30 -118	; 600
	303	[248]	CALL     	28 3 2
	304	[248]	SETTABLE 	27 -117 28	; "height" -
	305	[244]	CALL     	25 3 2
	306	[249]	SETGLOBAL	25 -112	; M
	307	[254]	SELF     	25 14 -44	; "new"
	308	[254]	NEWTABLE 	27 0 1
	309	[255]	SELF     	28 22 -63	; "getSize"
	310	[255]	CALL     	28 2 2
	311	[255]	SETTABLE 	27 -62 28	; "dimen" -
	312	[256]	SELF     	28 15 -44	; "new"
	313	[256]	NEWTABLE 	30 0 1
	314	[257]	GETTABLE 	31 23 -120	; "COLOR_BLACK"
	315	[257]	SETTABLE 	30 -58 31	; "background" -
	316	[256]	CALL     	28 3 0
	317	[259]	SETLIST  	27 0 1	; 1
	318	[254]	CALL     	25 3 2
	319	[259]	SETGLOBAL	25 -119	; readerwindow
	320	[260]	SELF     	25 20 -44	; "new"
	321	[260]	NEWTABLE 	27 0 3
	322	[261]	GETGLOBAL	28 -119	; readerwindow
	323	[261]	SETTABLE 	27 -122 28	; "dialog" -
	324	[262]	SELF     	28 8 -44	; "new"
	325	[262]	NEWTABLE 	30 0 2
	326	[262]	SELF     	31 22 -65	; "getWidth"
	327	[262]	CALL     	31 2 2
	328	[262]	SUB      	31 31 -123	; - 100
	329	[262]	SETTABLE 	30 -64 31	; "w" -
	330	[262]	SELF     	31 22 -67	; "getHeight"
	331	[262]	CALL     	31 2 2
	332	[262]	SUB      	31 31 -123	; - 100
	333	[262]	SETTABLE 	30 -66 31	; "h" -
	334	[262]	CALL     	28 3 2
	335	[262]	SETTABLE 	27 -62 28	; "dimen" -
	336	[263]	SELF     	28 19 -125	; "openDocument"
	337	[263]	LOADK    	30 -126	; "spec/front/unit/data/2col.pdf"
	338	[263]	CALL     	28 3 2
	339	[263]	SETTABLE 	27 -124 28	; "document" -
	340	[260]	CALL     	25 3 2
	341	[265]	SETGLOBAL	25 -121	; reader
	342	[266]	GETGLOBAL	25 -119	; readerwindow
	343	[266]	GETTABLE 	25 25 -77	; 1
	344	[266]	GETGLOBAL	26 -121	; reader
	345	[266]	SETTABLE 	25 -77 26	; 1 -
	346	[269]	SELF     	25 18 -44	; "new"
	347	[269]	NEWTABLE 	27 0 3
	348	[270]	SETTABLE 	27 -113 -128	; "title" "Document menu"
	349	[271]	SELF     	28 22 -65	; "getWidth"
	350	[271]	CALL     	28 2 2
	351	[271]	SETTABLE 	27 -86 28	; "width" -
	352	[272]	NEWTABLE 	28 3 0
	353	[272]	NEWTABLE 	29 9 1
	354	[274]	SETTABLE 	29 -130 -131	; "icon" "resources/icons/appbar.pokeball.png"
	355	[274]	NEWTABLE 	30 0 2
	356	[276]	SETTABLE 	30 -84 -94	; "text" "item1"
	357	[277]	CLOSURE  	31 10	; 0x7ffab7508390
	358	[277]	SETTABLE 	30 -132 31	; "callback" -
	359	[278]	NEWTABLE 	31 0 2
	360	[280]	SETTABLE 	31 -84 -95	; "text" "item2"
	361	[281]	CLOSURE  	32 11	; 0x7ffab75088d0
	362	[281]	SETTABLE 	31 -132 32	; "callback" -
	363	[282]	NEWTABLE 	32 0 2
	364	[284]	SETTABLE 	32 -84 -97	; "text" "item3"
	365	[285]	CLOSURE  	33 12	; 0x7ffab7507f60
	366	[285]	SETTABLE 	32 -132 33	; "callback" -
	367	[286]	NEWTABLE 	33 0 2
	368	[288]	SETTABLE 	33 -84 -98	; "text" "item4"
	369	[289]	CLOSURE  	34 13	; 0x7ffab7509040
	370	[289]	SETTABLE 	33 -132 34	; "callback" -
	371	[290]	NEWTABLE 	34 0 2
	372	[292]	SETTABLE 	34 -84 -99	; "text" "item5"
	373	[293]	CLOSURE  	35 14	; 0x7ffab75090f0
	374	[293]	SETTABLE 	34 -132 35	; "callback" -
	375	[294]	NEWTABLE 	35 0 2
	376	[296]	SETTABLE 	35 -84 -100	; "text" "item6"
	377	[297]	CLOSURE  	36 15	; 0x7ffab7507540
	378	[297]	SETTABLE 	35 -132 36	; "callback" -
	379	[298]	NEWTABLE 	36 0 2
	380	[300]	SETTABLE 	36 -84 -101	; "text" "item7"
	381	[301]	CLOSURE  	37 16	; 0x7ffab7507630
	382	[301]	SETTABLE 	36 -132 37	; "callback" -
	383	[302]	NEWTABLE 	37 0 2
	384	[304]	SETTABLE 	37 -84 -102	; "text" "item8"
	385	[305]	CLOSURE  	38 17	; 0x7ffab7508cf0
	386	[305]	SETTABLE 	37 -132 38	; "callback" -
	387	[306]	NEWTABLE 	38 0 2
	388	[308]	SETTABLE 	38 -84 -103	; "text" "item9"
	389	[309]	CLOSURE  	39 18	; 0x7ffab7507a90
	390	[309]	SETTABLE 	38 -132 39	; "callback" -
	391	[311]	SETLIST  	29 9 1	; 1
	392	[311]	NEWTABLE 	30 2 1
	393	[313]	SETTABLE 	30 -130 -133	; "icon" "resources/icons/appbar.page.corner.bookmark.png"
	394	[313]	NEWTABLE 	31 0 2
	395	[315]	SETTABLE 	31 -84 -104	; "text" "item10"
	396	[316]	CLOSURE  	32 19	; 0x7ffab7509250
	397	[316]	SETTABLE 	31 -132 32	; "callback" -
	398	[317]	NEWTABLE 	32 0 2
	399	[319]	SETTABLE 	32 -84 -105	; "text" "item11"
	400	[320]	CLOSURE  	33 20	; 0x7ffab7509340
	401	[320]	SETTABLE 	32 -132 33	; "callback" -
	402	[322]	SETLIST  	30 2 1	; 1
	403	[322]	NEWTABLE 	31 0 2
	404	[324]	SETTABLE 	31 -130 -134	; "icon" "resources/icons/appbar.home.png"
	405	[325]	CLOSURE  	32 21	; 0x7ffab7509470
	406	[325]	MOVE     	0 21
	407	[325]	SETTABLE 	31 -132 32	; "callback" -
	408	[327]	SETLIST  	28 3 1	; 1
	409	[327]	SETTABLE 	27 -129 28	; "tab_item_table" -
	410	[269]	CALL     	25 3 2
	411	[328]	SETGLOBAL	25 -127	; touch_menu
	412	[333]	SELF     	25 24 -44	; "new"
	413	[333]	NEWTABLE 	27 0 5
	414	[334]	SELF     	28 22 -76	; "scaleBySize"
	415	[334]	LOADK    	30 -135	; 400
	416	[334]	CALL     	28 3 2
	417	[334]	SETTABLE 	27 -86 28	; "width" -
	418	[335]	CLOSURE  	28 22	; 0x7ffab75096d0
	419	[335]	SETTABLE 	27 -136 28	; "enter_callback" -
	420	[336]	SETTABLE 	27 -137 -138	; "scroll" false
	421	[337]	SETTABLE 	27 -139 -140	; "input_type" "number"
	422	[338]	NEWTABLE 	28 0 1
	423	[339]	SETTABLE 	28 -142 -138	; "onSwitchFocus" false
	424	[340]	SETTABLE 	27 -141 28	; "parent" -
	425	[333]	CALL     	25 3 2
	426	[378]	CLOSURE  	26 23	; 0x7ffab7509970
	427	[378]	MOVE     	0 5
	428	[346]	SETGLOBAL	26 -143	; testKeyValuePage
	429	[396]	CLOSURE  	26 24	; 0x7ffab7509cb0
	430	[396]	MOVE     	0 19
	431	[396]	MOVE     	0 20
	432	[396]	MOVE     	0 8
	433	[396]	MOVE     	0 22
	434	[396]	MOVE     	0 5
	435	[380]	SETGLOBAL	26 -144	; testBookStatus
	436	[401]	CLOSURE  	26 25	; 0x7ffab750a780
	437	[401]	MOVE     	0 5
	438	[398]	SETGLOBAL	26 -145	; testTouchProbe
	439	[443]	CLOSURE  	26 26	; 0x7ffab750adb0
	440	[443]	MOVE     	0 5
	441	[403]	SETGLOBAL	26 -146	; testNetworkSetting
	442	[451]	SELF     	26 5 -147	; "show"
	443	[451]	GETGLOBAL	28 -45	; TestVisible
	444	[451]	CALL     	26 3 1
	445	[452]	SELF     	26 5 -147	; "show"
	446	[452]	GETGLOBAL	28 -72	; Clock
	447	[452]	SELF     	28 28 -44	; "new"
	448	[452]	CALL     	28 2 0
	449	[452]	CALL     	26 0 1
	450	[463]	GETGLOBAL	26 -146	; testNetworkSetting
	451	[463]	CALL     	26 1 1
	452	[464]	SELF     	26 5 -148	; "run"
	453	[464]	CALL     	26 2 1
	454	[464]	RETURN   	0 1

function <./tools/wbuilder.lua:53,66> (78 instructions, 312 bytes at 0x7ffab7505330)
2 params, 15 slots, 3 upvalues, 10 locals, 19 constants, 0 functions
	1	[54]	GETGLOBAL	2 -2	; math
	2	[54]	GETTABLE 	2 2 -3	; "floor"
	3	[54]	SELF     	3 1 -4	; "getWidth"
	4	[54]	CALL     	3 2 2
	5	[54]	DIV      	3 3 -5	; - 50
	6	[54]	CALL     	2 2 2
	7	[54]	SETGLOBAL	2 -1	; v_line
	8	[55]	GETGLOBAL	2 -2	; math
	9	[55]	GETTABLE 	2 2 -3	; "floor"
	10	[55]	SELF     	3 1 -7	; "getHeight"
	11	[55]	CALL     	3 2 2
	12	[55]	DIV      	3 3 -5	; - 50
	13	[55]	CALL     	2 2 2
	14	[55]	SETGLOBAL	2 -6	; h_line
	15	[56]	LOADK    	2 -8	; 1
	16	[56]	GETGLOBAL	3 -6	; h_line
	17	[56]	LOADK    	4 -8	; 1
	18	[56]	FORPREP  	2 27	; to 46
	19	[57]	MUL      	6 5 -5	; - 50
	20	[57]	SETGLOBAL	6 -9	; y_num
	21	[58]	GETUPVAL 	6 0	; RenderText
	22	[58]	SELF     	6 6 -10	; "renderUtf8Text"
	23	[58]	MOVE     	8 1
	24	[58]	LOADK    	9 -11	; 0
	25	[58]	GETGLOBAL	10 -9	; y_num
	26	[58]	ADD      	10 10 -12	; - 10
	27	[58]	GETUPVAL 	11 1	; Font
	28	[58]	SELF     	11 11 -13	; "getFace"
	29	[58]	LOADK    	13 -14	; "ffont"
	30	[58]	LOADK    	14 -15	; 12
	31	[58]	CALL     	11 4 2
	32	[58]	GETGLOBAL	12 -9	; y_num
	33	[58]	LOADBOOL 	13 1 0
	34	[58]	CALL     	6 8 1
	35	[59]	SELF     	6 1 -16	; "paintRect"
	36	[59]	LOADK    	8 -11	; 0
	37	[59]	GETGLOBAL	9 -9	; y_num
	38	[59]	SELF     	10 1 -4	; "getWidth"
	39	[59]	CALL     	10 2 2
	40	[59]	LOADK    	11 -8	; 1
	41	[59]	GETUPVAL 	12 2	; Blitbuffer
	42	[59]	GETTABLE 	12 12 -17	; "gray"
	43	[59]	LOADK    	13 -18	; 0.7
	44	[59]	CALL     	12 2 0
	45	[59]	CALL     	6 0 1
	46	[56]	FORLOOP  	2 -28	; to 19
	47	[61]	LOADK    	2 -8	; 1
	48	[61]	GETGLOBAL	3 -1	; v_line
	49	[61]	LOADK    	4 -8	; 1
	50	[61]	FORPREP  	2 26	; to 77
	51	[62]	MUL      	6 5 -5	; - 50
	52	[62]	SETGLOBAL	6 -19	; x_num
	53	[63]	GETUPVAL 	6 0	; RenderText
	54	[63]	SELF     	6 6 -10	; "renderUtf8Text"
	55	[63]	MOVE     	8 1
	56	[63]	GETGLOBAL	9 -19	; x_num
	57	[63]	LOADK    	10 -12	; 10
	58	[63]	GETUPVAL 	11 1	; Font
	59	[63]	SELF     	11 11 -13	; "getFace"
	60	[63]	LOADK    	13 -14	; "ffont"
	61	[63]	LOADK    	14 -15	; 12
	62	[63]	CALL     	11 4 2
	63	[63]	GETGLOBAL	12 -19	; x_num
	64	[63]	LOADBOOL 	13 1 0
	65	[63]	CALL     	6 8 1
	66	[64]	SELF     	6 1 -16	; "paintRect"
	67	[64]	GETGLOBAL	8 -19	; x_num
	68	[64]	LOADK    	9 -11	; 0
	69	[64]	LOADK    	10 -8	; 1
	70	[64]	SELF     	11 1 -7	; "getHeight"
	71	[64]	CALL     	11 2 2
	72	[64]	GETUPVAL 	12 2	; Blitbuffer
	73	[64]	GETTABLE 	12 12 -17	; "gray"
	74	[64]	LOADK    	13 -18	; 0.7
	75	[64]	CALL     	12 2 0
	76	[64]	CALL     	6 0 1
	77	[61]	FORLOOP  	2 -27	; to 51
	78	[66]	RETURN   	0 1

function <./tools/wbuilder.lua:68,122> (321 instructions, 1284 bytes at 0x7ffab7506980)
2 params, 16 slots, 3 upvalues, 14 locals, 45 constants, 0 functions
	1	[70]	GETGLOBAL	2 -2	; math
	2	[70]	GETTABLE 	2 2 -3	; "floor"
	3	[70]	SELF     	3 1 -4	; "getWidth"
	4	[70]	CALL     	3 2 2
	5	[70]	DIV      	3 3 -5	; - 50
	6	[70]	CALL     	2 2 2
	7	[70]	SETGLOBAL	2 -1	; v_line
	8	[71]	GETGLOBAL	2 -2	; math
	9	[71]	GETTABLE 	2 2 -3	; "floor"
	10	[71]	SELF     	3 1 -7	; "getHeight"
	11	[71]	CALL     	3 2 2
	12	[71]	DIV      	3 3 -5	; - 50
	13	[71]	CALL     	2 2 2
	14	[71]	SETGLOBAL	2 -6	; h_line
	15	[73]	SELF     	2 1 -8	; "paintRect"
	16	[73]	LOADK    	4 -9	; 0
	17	[73]	LOADK    	5 -9	; 0
	18	[73]	SELF     	6 1 -4	; "getWidth"
	19	[73]	CALL     	6 2 2
	20	[73]	SELF     	7 1 -7	; "getHeight"
	21	[73]	CALL     	7 2 2
	22	[73]	GETUPVAL 	8 0	; Blitbuffer
	23	[73]	GETTABLE 	8 8 -10	; "COLOR_WHITE"
	24	[73]	CALL     	2 7 1
	25	[75]	LOADK    	2 -11	; 1
	26	[75]	GETGLOBAL	3 -6	; h_line
	27	[75]	LOADK    	4 -11	; 1
	28	[75]	FORPREP  	2 16	; to 45
	29	[76]	MUL      	6 5 -5	; - 50
	30	[76]	SETGLOBAL	6 -12	; y_num
	31	[77]	GETUPVAL 	6 1	; RenderText
	32	[77]	SELF     	6 6 -13	; "renderUtf8Text"
	33	[77]	MOVE     	8 1
	34	[77]	LOADK    	9 -14	; 40
	35	[77]	GETGLOBAL	10 -12	; y_num
	36	[77]	ADD      	10 10 -15	; - 10
	37	[77]	GETUPVAL 	11 2	; Font
	38	[77]	SELF     	11 11 -16	; "getFace"
	39	[77]	LOADK    	13 -17	; "ffont"
	40	[77]	LOADK    	14 -18	; 12
	41	[77]	CALL     	11 4 2
	42	[77]	GETGLOBAL	12 -12	; y_num
	43	[77]	LOADBOOL 	13 1 0
	44	[77]	CALL     	6 8 1
	45	[75]	FORLOOP  	2 -17	; to 29
	46	[79]	LOADK    	2 -11	; 1
	47	[79]	GETGLOBAL	3 -1	; v_line
	48	[79]	LOADK    	4 -11	; 1
	49	[79]	FORPREP  	2 15	; to 65
	50	[80]	MUL      	6 5 -5	; - 50
	51	[80]	SETGLOBAL	6 -19	; x_num
	52	[81]	GETUPVAL 	6 1	; RenderText
	53	[81]	SELF     	6 6 -13	; "renderUtf8Text"
	54	[81]	MOVE     	8 1
	55	[81]	GETGLOBAL	9 -19	; x_num
	56	[81]	LOADK    	10 -14	; 40
	57	[81]	GETUPVAL 	11 2	; Font
	58	[81]	SELF     	11 11 -16	; "getFace"
	59	[81]	LOADK    	13 -17	; "ffont"
	60	[81]	LOADK    	14 -18	; 12
	61	[81]	CALL     	11 4 2
	62	[81]	GETGLOBAL	12 -19	; x_num
	63	[81]	LOADBOOL 	13 1 0
	64	[81]	CALL     	6 8 1
	65	[79]	FORLOOP  	2 -16	; to 50
	66	[85]	LOADK    	2 -20	; 4
	67	[86]	SELF     	3 1 -4	; "getWidth"
	68	[86]	CALL     	3 2 2
	69	[86]	SUB      	3 3 -20	; - 4
	70	[87]	LOADK    	4 -21	; 3
	71	[88]	SELF     	5 1 -7	; "getHeight"
	72	[88]	CALL     	5 2 2
	73	[88]	SUB      	5 5 -21	; - 3
	74	[88]	SUB      	5 5 -18	; - 12
	75	[91]	GETUPVAL 	6 1	; RenderText
	76	[91]	SELF     	6 6 -13	; "renderUtf8Text"
	77	[91]	MOVE     	8 1
	78	[91]	LOADK    	9 -22	; 150
	79	[91]	LOADK    	10 -23	; 100
	80	[91]	GETUPVAL 	11 2	; Font
	81	[91]	SELF     	11 11 -16	; "getFace"
	82	[91]	LOADK    	13 -17	; "ffont"
	83	[91]	LOADK    	14 -24	; 22
	84	[91]	CALL     	11 4 2
	85	[91]	LOADK    	12 -25	; "x_min = "
	86	[91]	MOVE     	13 2
	87	[91]	CONCAT   	12 12 13
	88	[91]	LOADBOOL 	13 1 0
	89	[91]	CALL     	6 8 1
	90	[92]	GETUPVAL 	6 1	; RenderText
	91	[92]	SELF     	6 6 -13	; "renderUtf8Text"
	92	[92]	MOVE     	8 1
	93	[92]	LOADK    	9 -26	; 500
	94	[92]	LOADK    	10 -23	; 100
	95	[92]	GETUPVAL 	11 2	; Font
	96	[92]	SELF     	11 11 -16	; "getFace"
	97	[92]	LOADK    	13 -17	; "ffont"
	98	[92]	LOADK    	14 -24	; 22
	99	[92]	CALL     	11 4 2
	100	[92]	LOADK    	12 -27	; "x_max = "
	101	[92]	MOVE     	13 3
	102	[92]	CONCAT   	12 12 13
	103	[92]	LOADBOOL 	13 1 0
	104	[92]	CALL     	6 8 1
	105	[93]	GETUPVAL 	6 1	; RenderText
	106	[93]	SELF     	6 6 -13	; "renderUtf8Text"
	107	[93]	MOVE     	8 1
	108	[93]	LOADK    	9 -23	; 100
	109	[93]	LOADK    	10 -22	; 150
	110	[93]	GETUPVAL 	11 2	; Font
	111	[93]	SELF     	11 11 -16	; "getFace"
	112	[93]	LOADK    	13 -17	; "ffont"
	113	[93]	LOADK    	14 -24	; 22
	114	[93]	CALL     	11 4 2
	115	[93]	LOADK    	12 -28	; "y_min = "
	116	[93]	MOVE     	13 4
	117	[93]	CONCAT   	12 12 13
	118	[93]	LOADBOOL 	13 1 0
	119	[93]	CALL     	6 8 1
	120	[94]	GETUPVAL 	6 1	; RenderText
	121	[94]	SELF     	6 6 -13	; "renderUtf8Text"
	122	[94]	MOVE     	8 1
	123	[94]	LOADK    	9 -23	; 100
	124	[94]	LOADK    	10 -29	; 300
	125	[94]	GETUPVAL 	11 2	; Font
	126	[94]	SELF     	11 11 -16	; "getFace"
	127	[94]	LOADK    	13 -17	; "ffont"
	128	[94]	LOADK    	14 -24	; 22
	129	[94]	CALL     	11 4 2
	130	[94]	LOADK    	12 -30	; "y_max = "
	131	[94]	MOVE     	13 5
	132	[94]	CONCAT   	12 12 13
	133	[94]	LOADBOOL 	13 1 0
	134	[94]	CALL     	6 8 1
	135	[95]	GETUPVAL 	6 1	; RenderText
	136	[95]	SELF     	6 6 -13	; "renderUtf8Text"
	137	[95]	MOVE     	8 1
	138	[95]	LOADK    	9 -23	; 100
	139	[95]	LOADK    	10 -26	; 500
	140	[95]	GETUPVAL 	11 2	; Font
	141	[95]	SELF     	11 11 -16	; "getFace"
	142	[95]	LOADK    	13 -17	; "ffont"
	143	[95]	LOADK    	14 -31	; 26
	144	[95]	CALL     	11 4 2
	145	[95]	LOADK    	12 -32	; "Visible screen size :  "
	146	[95]	SUB      	13 3 2
	147	[95]	LOADK    	14 -33	; "x"
	148	[95]	SUB      	15 5 4
	149	[95]	CONCAT   	12 12 15
	150	[95]	LOADBOOL 	13 1 0
	151	[95]	CALL     	6 8 1
	152	[98]	SELF     	6 1 -8	; "paintRect"
	153	[98]	MOVE     	8 2
	154	[98]	MOVE     	9 4
	155	[98]	MOVE     	10 3
	156	[98]	LOADK    	11 -11	; 1
	157	[98]	GETUPVAL 	12 0	; Blitbuffer
	158	[98]	GETTABLE 	12 12 -34	; "gray"
	159	[98]	LOADK    	13 -35	; 0.7
	160	[98]	CALL     	12 2 0
	161	[98]	CALL     	6 0 1
	162	[99]	SELF     	6 1 -8	; "paintRect"
	163	[99]	MOVE     	8 2
	164	[99]	ADD      	9 4 -21	; - 3
	165	[99]	MOVE     	10 3
	166	[99]	LOADK    	11 -11	; 1
	167	[99]	GETUPVAL 	12 0	; Blitbuffer
	168	[99]	GETTABLE 	12 12 -34	; "gray"
	169	[99]	LOADK    	13 -35	; 0.7
	170	[99]	CALL     	12 2 0
	171	[99]	CALL     	6 0 1
	172	[100]	SELF     	6 1 -8	; "paintRect"
	173	[100]	MOVE     	8 2
	174	[100]	ADD      	9 4 -36	; - 6
	175	[100]	MOVE     	10 3
	176	[100]	LOADK    	11 -11	; 1
	177	[100]	GETUPVAL 	12 0	; Blitbuffer
	178	[100]	GETTABLE 	12 12 -34	; "gray"
	179	[100]	LOADK    	13 -35	; 0.7
	180	[100]	CALL     	12 2 0
	181	[100]	CALL     	6 0 1
	182	[103]	SELF     	6 1 -8	; "paintRect"
	183	[103]	MOVE     	8 2
	184	[103]	MOVE     	9 5
	185	[103]	MOVE     	10 3
	186	[103]	LOADK    	11 -11	; 1
	187	[103]	GETUPVAL 	12 0	; Blitbuffer
	188	[103]	GETTABLE 	12 12 -34	; "gray"
	189	[103]	LOADK    	13 -35	; 0.7
	190	[103]	CALL     	12 2 0
	191	[103]	CALL     	6 0 1
	192	[104]	SELF     	6 1 -8	; "paintRect"
	193	[104]	MOVE     	8 2
	194	[104]	SUB      	9 5 -21	; - 3
	195	[104]	MOVE     	10 3
	196	[104]	LOADK    	11 -11	; 1
	197	[104]	GETUPVAL 	12 0	; Blitbuffer
	198	[104]	GETTABLE 	12 12 -34	; "gray"
	199	[104]	LOADK    	13 -35	; 0.7
	200	[104]	CALL     	12 2 0
	201	[104]	CALL     	6 0 1
	202	[105]	SELF     	6 1 -8	; "paintRect"
	203	[105]	MOVE     	8 2
	204	[105]	SUB      	9 5 -36	; - 6
	205	[105]	MOVE     	10 3
	206	[105]	LOADK    	11 -11	; 1
	207	[105]	GETUPVAL 	12 0	; Blitbuffer
	208	[105]	GETTABLE 	12 12 -34	; "gray"
	209	[105]	LOADK    	13 -35	; 0.7
	210	[105]	CALL     	12 2 0
	211	[105]	CALL     	6 0 1
	212	[108]	SELF     	6 1 -8	; "paintRect"
	213	[108]	MOVE     	8 2
	214	[108]	MOVE     	9 4
	215	[108]	LOADK    	10 -11	; 1
	216	[108]	MOVE     	11 5
	217	[108]	GETUPVAL 	12 0	; Blitbuffer
	218	[108]	GETTABLE 	12 12 -34	; "gray"
	219	[108]	LOADK    	13 -35	; 0.7
	220	[108]	CALL     	12 2 0
	221	[108]	CALL     	6 0 1
	222	[109]	SELF     	6 1 -8	; "paintRect"
	223	[109]	ADD      	8 2 -21	; - 3
	224	[109]	MOVE     	9 4
	225	[109]	LOADK    	10 -11	; 1
	226	[109]	MOVE     	11 5
	227	[109]	GETUPVAL 	12 0	; Blitbuffer
	228	[109]	GETTABLE 	12 12 -34	; "gray"
	229	[109]	LOADK    	13 -35	; 0.7
	230	[109]	CALL     	12 2 0
	231	[109]	CALL     	6 0 1
	232	[110]	SELF     	6 1 -8	; "paintRect"
	233	[110]	ADD      	8 2 -36	; - 6
	234	[110]	MOVE     	9 4
	235	[110]	LOADK    	10 -11	; 1
	236	[110]	MOVE     	11 5
	237	[110]	GETUPVAL 	12 0	; Blitbuffer
	238	[110]	GETTABLE 	12 12 -34	; "gray"
	239	[110]	LOADK    	13 -35	; 0.7
	240	[110]	CALL     	12 2 0
	241	[110]	CALL     	6 0 1
	242	[113]	SELF     	6 1 -8	; "paintRect"
	243	[113]	MOVE     	8 3
	244	[113]	MOVE     	9 4
	245	[113]	LOADK    	10 -11	; 1
	246	[113]	MOVE     	11 5
	247	[113]	GETUPVAL 	12 0	; Blitbuffer
	248	[113]	GETTABLE 	12 12 -34	; "gray"
	249	[113]	LOADK    	13 -35	; 0.7
	250	[113]	CALL     	12 2 0
	251	[113]	CALL     	6 0 1
	252	[114]	SELF     	6 1 -8	; "paintRect"
	253	[114]	SUB      	8 3 -21	; - 3
	254	[114]	MOVE     	9 4
	255	[114]	LOADK    	10 -11	; 1
	256	[114]	MOVE     	11 5
	257	[114]	GETUPVAL 	12 0	; Blitbuffer
	258	[114]	GETTABLE 	12 12 -34	; "gray"
	259	[114]	LOADK    	13 -35	; 0.7
	260	[114]	CALL     	12 2 0
	261	[114]	CALL     	6 0 1
	262	[115]	SELF     	6 1 -8	; "paintRect"
	263	[115]	SUB      	8 3 -36	; - 6
	264	[115]	MOVE     	9 4
	265	[115]	LOADK    	10 -11	; 1
	266	[115]	MOVE     	11 5
	267	[115]	GETUPVAL 	12 0	; Blitbuffer
	268	[115]	GETTABLE 	12 12 -34	; "gray"
	269	[115]	LOADK    	13 -35	; 0.7
	270	[115]	CALL     	12 2 0
	271	[115]	CALL     	6 0 1
	272	[118]	SELF     	6 1 -8	; "paintRect"
	273	[118]	LOADK    	8 -23	; 100
	274	[118]	LOADK    	9 -37	; 600
	275	[118]	LOADK    	10 -11	; 1
	276	[118]	LOADK    	11 -38	; 250
	277	[118]	GETUPVAL 	12 0	; Blitbuffer
	278	[118]	GETTABLE 	12 12 -34	; "gray"
	279	[118]	LOADK    	13 -35	; 0.7
	280	[118]	CALL     	12 2 0
	281	[118]	CALL     	6 0 1
	282	[119]	SELF     	6 1 -8	; "paintRect"
	283	[119]	LOADK    	8 -39	; 700
	284	[119]	LOADK    	9 -37	; 600
	285	[119]	LOADK    	10 -11	; 1
	286	[119]	LOADK    	11 -38	; 250
	287	[119]	GETUPVAL 	12 0	; Blitbuffer
	288	[119]	GETTABLE 	12 12 -34	; "gray"
	289	[119]	LOADK    	13 -35	; 0.7
	290	[119]	CALL     	12 2 0
	291	[119]	CALL     	6 0 1
	292	[120]	GETUPVAL 	6 1	; RenderText
	293	[120]	SELF     	6 6 -13	; "renderUtf8Text"
	294	[120]	MOVE     	8 1
	295	[120]	LOADK    	9 -22	; 150
	296	[120]	LOADK    	10 -40	; 670
	297	[120]	GETUPVAL 	11 2	; Font
	298	[120]	SELF     	11 11 -16	; "getFace"
	299	[120]	LOADK    	13 -17	; "ffont"
	300	[120]	LOADK    	14 -31	; 26
	301	[120]	CALL     	11 4 2
	302	[120]	LOADK    	12 -41	; "Measure inches per 600 pixels"
	303	[120]	LOADBOOL 	13 1 0
	304	[120]	CALL     	6 8 1
	305	[121]	GETUPVAL 	6 1	; RenderText
	306	[121]	SELF     	6 6 -13	; "renderUtf8Text"
	307	[121]	MOVE     	8 1
	308	[121]	LOADK    	9 -22	; 150
	309	[121]	LOADK    	10 -42	; 770
	310	[121]	GETUPVAL 	11 2	; Font
	311	[121]	SELF     	11 11 -16	; "getFace"
	312	[121]	LOADK    	13 -17	; "ffont"
	313	[121]	LOADK    	14 -24	; 22
	314	[121]	CALL     	11 4 2
	315	[121]	LOADK    	12 -43	; "Kobo Aura: 600 pixels/ 2.82 \" = "
	316	[121]	LOADK    	13 -44	; 212.76595744681
	317	[121]	LOADK    	14 -45	; " dpi"
	318	[121]	CONCAT   	12 12 14
	319	[121]	LOADBOOL 	13 1 0
	320	[121]	CALL     	6 8 1
	321	[122]	RETURN   	0 1

function <./tools/wbuilder.lua:148,153> (10 instructions, 40 bytes at 0x7ffab7505d20)
1 param, 6 slots, 2 upvalues, 1 local, 6 constants, 0 functions
	1	[149]	GETUPVAL 	1 0	; UIManager
	2	[149]	SELF     	1 1 -1	; "show"
	3	[149]	GETUPVAL 	3 1	; InfoMessage
	4	[149]	SELF     	3 3 -2	; "new"
	5	[149]	NEWTABLE 	5 0 2
	6	[150]	SETTABLE 	5 -3 -4	; "text" "Example message."
	7	[151]	SETTABLE 	5 -5 -6	; "timeout" 10
	8	[149]	CALL     	3 3 0
	9	[149]	CALL     	1 0 1
	10	[153]	RETURN   	0 1

function <./tools/wbuilder.lua:155,159> (9 instructions, 36 bytes at 0x7ffab7507460)
1 param, 6 slots, 2 upvalues, 1 local, 4 constants, 0 functions
	1	[156]	GETUPVAL 	1 0	; UIManager
	2	[156]	SELF     	1 1 -1	; "show"
	3	[156]	GETUPVAL 	3 1	; ConfirmBox
	4	[156]	SELF     	3 3 -2	; "new"
	5	[156]	NEWTABLE 	5 0 1
	6	[157]	SETTABLE 	5 -3 -4	; "text" "Please confirm delete"
	7	[156]	CALL     	3 3 0
	8	[156]	CALL     	1 0 1
	9	[159]	RETURN   	0 1

function <./tools/wbuilder.lua:161,163> (4 instructions, 16 bytes at 0x7ffab75077c0)
1 param, 3 slots, 1 upvalue, 1 local, 1 constant, 0 functions
	1	[162]	GETUPVAL 	1 0	; UIManager
	2	[162]	SELF     	1 1 -1	; "quit"
	3	[162]	CALL     	1 2 1
	4	[163]	RETURN   	0 1

function <./tools/wbuilder.lua:165,167> (4 instructions, 16 bytes at 0x7ffab7507be0)
1 param, 3 slots, 1 upvalue, 1 local, 1 constant, 0 functions
	1	[166]	GETUPVAL 	1 0	; UIManager
	2	[166]	SELF     	1 1 -1	; "quit"
	3	[166]	CALL     	1 2 1
	4	[167]	RETURN   	0 1

function <./tools/wbuilder.lua:183,189> (19 instructions, 76 bytes at 0x7ffab75080b0)
1 param, 5 slots, 1 upvalue, 1 local, 5 constants, 1 function
	1	[184]	GETTABLE 	1 0 -1	; 1
	2	[184]	GETTABLE 	1 1 -1	; 1
	3	[184]	SELF     	1 1 -2	; "free"
	4	[184]	CALL     	1 2 1
	5	[185]	GETTABLE 	1 0 -1	; 1
	6	[185]	SELF     	2 0 -3	; "getTextWidget"
	7	[185]	CALL     	2 2 2
	8	[185]	SETTABLE 	1 -1 2	; 1 -
	9	[186]	GETUPVAL 	1 0	; UIManager
	10	[186]	SELF     	1 1 -4	; "setDirty"
	11	[186]	MOVE     	3 0
	12	[186]	CALL     	1 3 1
	13	[188]	GETUPVAL 	1 0	; UIManager
	14	[188]	SELF     	1 1 -5	; "scheduleIn"
	15	[188]	LOADK    	3 -1	; 1
	16	[188]	CLOSURE  	4 0	; 0x7ffab7508460
	17	[188]	MOVE     	0 0
	18	[188]	CALL     	1 4 1
	19	[189]	RETURN   	0 1

function <./tools/wbuilder.lua:188,188> (4 instructions, 16 bytes at 0x7ffab7508460)
0 params, 2 slots, 1 upvalue, 0 locals, 1 constant, 0 functions
	1	[188]	GETUPVAL 	0 0	; self
	2	[188]	SELF     	0 0 -1	; "schedFunc"
	3	[188]	CALL     	0 2 1
	4	[188]	RETURN   	0 1

function <./tools/wbuilder.lua:191,194> (7 instructions, 28 bytes at 0x7ffab75086c0)
1 param, 4 slots, 0 upvalues, 1 local, 3 constants, 0 functions
	1	[192]	GETTABLE 	1 0 -1	; 1
	2	[192]	SELF     	2 0 -2	; "getTextWidget"
	3	[192]	CALL     	2 2 2
	4	[192]	SETTABLE 	1 -1 2	; 1 -
	5	[193]	SELF     	1 0 -3	; "schedFunc"
	6	[193]	CALL     	1 2 1
	7	[194]	RETURN   	0 1

function <./tools/wbuilder.lua:196,204> (26 instructions, 104 bytes at 0x7ffab75089e0)
1 param, 11 slots, 3 upvalues, 1 local, 14 constants, 0 functions
	1	[197]	GETUPVAL 	1 0	; CenterContainer
	2	[197]	SELF     	1 1 -1	; "new"
	3	[197]	NEWTABLE 	3 0 1
	4	[198]	NEWTABLE 	4 0 2
	5	[198]	SETTABLE 	4 -3 -4	; "w" 300
	6	[198]	SETTABLE 	4 -5 -6	; "h" 25
	7	[198]	SETTABLE 	3 -2 4	; "dimen" -
	8	[199]	GETUPVAL 	4 1	; TextWidget
	9	[199]	SELF     	4 4 -1	; "new"
	10	[199]	NEWTABLE 	6 0 2
	11	[200]	GETGLOBAL	7 -8	; os
	12	[200]	GETTABLE 	7 7 -9	; "date"
	13	[200]	LOADK    	8 -10	; "%H:%M:%S"
	14	[200]	CALL     	7 2 2
	15	[200]	SETTABLE 	6 -7 7	; "text" -
	16	[201]	GETUPVAL 	7 2	; Font
	17	[201]	SELF     	7 7 -12	; "getFace"
	18	[201]	LOADK    	9 -13	; "cfont"
	19	[201]	LOADK    	10 -14	; 12
	20	[201]	CALL     	7 4 2
	21	[201]	SETTABLE 	6 -11 7	; "face" -
	22	[199]	CALL     	4 3 0
	23	[203]	SETLIST  	3 0 1	; 1
	24	[197]	TAILCALL 	1 3 0
	25	[203]	RETURN   	1 0
	26	[204]	RETURN   	0 1

function <./tools/wbuilder.lua:214,218> (9 instructions, 36 bytes at 0x7ffab7508e00)
0 params, 5 slots, 2 upvalues, 0 locals, 4 constants, 0 functions
	1	[215]	GETUPVAL 	0 0	; UIManager
	2	[215]	SELF     	0 0 -1	; "show"
	3	[215]	GETUPVAL 	2 1	; InfoMessage
	4	[215]	SELF     	2 2 -2	; "new"
	5	[215]	NEWTABLE 	4 0 1
	6	[216]	SETTABLE 	4 -3 -4	; "text" "You liar!"
	7	[215]	CALL     	2 3 0
	8	[215]	CALL     	0 0 1
	9	[218]	RETURN   	0 1

function <./tools/wbuilder.lua:277,277> (1 instruction, 4 bytes at 0x7ffab7508390)
0 params, 2 slots, 0 upvalues, 0 locals, 0 constants, 0 functions
	1	[277]	RETURN   	0 1

function <./tools/wbuilder.lua:281,281> (1 instruction, 4 bytes at 0x7ffab75088d0)
0 params, 2 slots, 0 upvalues, 0 locals, 0 constants, 0 functions
	1	[281]	RETURN   	0 1

function <./tools/wbuilder.lua:285,285> (1 instruction, 4 bytes at 0x7ffab7507f60)
0 params, 2 slots, 0 upvalues, 0 locals, 0 constants, 0 functions
	1	[285]	RETURN   	0 1

function <./tools/wbuilder.lua:289,289> (1 instruction, 4 bytes at 0x7ffab7509040)
0 params, 2 slots, 0 upvalues, 0 locals, 0 constants, 0 functions
	1	[289]	RETURN   	0 1

function <./tools/wbuilder.lua:293,293> (1 instruction, 4 bytes at 0x7ffab75090f0)
0 params, 2 slots, 0 upvalues, 0 locals, 0 constants, 0 functions
	1	[293]	RETURN   	0 1

function <./tools/wbuilder.lua:297,297> (1 instruction, 4 bytes at 0x7ffab7507540)
0 params, 2 slots, 0 upvalues, 0 locals, 0 constants, 0 functions
	1	[297]	RETURN   	0 1

function <./tools/wbuilder.lua:301,301> (1 instruction, 4 bytes at 0x7ffab7507630)
0 params, 2 slots, 0 upvalues, 0 locals, 0 constants, 0 functions
	1	[301]	RETURN   	0 1

function <./tools/wbuilder.lua:305,305> (1 instruction, 4 bytes at 0x7ffab7508cf0)
0 params, 2 slots, 0 upvalues, 0 locals, 0 constants, 0 functions
	1	[305]	RETURN   	0 1

function <./tools/wbuilder.lua:309,309> (1 instruction, 4 bytes at 0x7ffab7507a90)
0 params, 2 slots, 0 upvalues, 0 locals, 0 constants, 0 functions
	1	[309]	RETURN   	0 1

function <./tools/wbuilder.lua:316,316> (1 instruction, 4 bytes at 0x7ffab7509250)
0 params, 2 slots, 0 upvalues, 0 locals, 0 constants, 0 functions
	1	[316]	RETURN   	0 1

function <./tools/wbuilder.lua:320,320> (1 instruction, 4 bytes at 0x7ffab7509340)
0 params, 2 slots, 0 upvalues, 0 locals, 0 constants, 0 functions
	1	[320]	RETURN   	0 1

function <./tools/wbuilder.lua:325,325> (4 instructions, 16 bytes at 0x7ffab7509470)
0 params, 2 slots, 1 upvalue, 0 locals, 1 constant, 0 functions
	1	[325]	GETUPVAL 	0 0	; DEBUG
	2	[325]	LOADK    	1 -1	; "hello world!"
	3	[325]	CALL     	0 2 1
	4	[325]	RETURN   	0 1

function <./tools/wbuilder.lua:335,335> (4 instructions, 16 bytes at 0x7ffab75096d0)
0 params, 2 slots, 0 upvalues, 0 locals, 2 constants, 0 functions
	1	[335]	GETGLOBAL	0 -1	; print
	2	[335]	LOADK    	1 -2	; "Entered"
	3	[335]	CALL     	0 2 1
	4	[335]	RETURN   	0 1

function <./tools/wbuilder.lua:346,378> (108 instructions, 432 bytes at 0x7ffab7509970)
0 params, 31 slots, 1 upvalue, 2 locals, 33 constants, 0 functions
	1	[347]	GETGLOBAL	0 -1	; require
	2	[347]	LOADK    	1 -2	; "ui/widget/keyvaluepage"
	3	[347]	CALL     	0 2 2
	4	[348]	SELF     	1 0 -3	; "new"
	5	[348]	NEWTABLE 	3 0 2
	6	[349]	SETTABLE 	3 -4 -5	; "title" "Statistics This is a very very log item whose length should exceed the width of the men"
	7	[350]	NEWTABLE 	4 20 0
	8	[350]	NEWTABLE 	5 2 0
	9	[351]	LOADK    	6 -7	; "1 Current period"
	10	[351]	LOADK    	7 -8	; "00:00:00"
	11	[351]	SETLIST  	5 2 1	; 1
	12	[351]	NEWTABLE 	6 2 0
	13	[352]	LOADK    	7 -9	; "This is a very very log item whose length should exceed the width of the menu."
	14	[352]	LOADK    	8 -10	; "value"
	15	[352]	SETLIST  	6 2 1	; 1
	16	[352]	NEWTABLE 	7 2 0
	17	[353]	LOADK    	8 -11	; "2 Time to read"
	18	[353]	LOADK    	9 -12	; "00:00:00 00:00:00 00:00:00 00:00:00"
	19	[353]	SETLIST  	7 2 1	; 1
	20	[353]	NEWTABLE 	8 2 0
	21	[354]	LOADK    	9 -11	; "2 Time to read"
	22	[354]	LOADK    	10 -8	; "00:00:00"
	23	[354]	SETLIST  	8 2 1	; 1
	24	[354]	NEWTABLE 	9 2 0
	25	[355]	LOADK    	10 -13	; "3 Time to read"
	26	[355]	LOADK    	11 -8	; "00:00:00"
	27	[355]	SETLIST  	9 2 1	; 1
	28	[355]	NEWTABLE 	10 2 0
	29	[356]	LOADK    	11 -14	; "4 Time to read"
	30	[356]	LOADK    	12 -8	; "00:00:00"
	31	[356]	SETLIST  	10 2 1	; 1
	32	[356]	NEWTABLE 	11 2 0
	33	[357]	LOADK    	12 -15	; "5 Time to read"
	34	[357]	LOADK    	13 -8	; "00:00:00"
	35	[357]	SETLIST  	11 2 1	; 1
	36	[357]	NEWTABLE 	12 2 0
	37	[358]	LOADK    	13 -16	; "6 Time to read"
	38	[358]	LOADK    	14 -8	; "00:00:00"
	39	[358]	SETLIST  	12 2 1	; 1
	40	[358]	NEWTABLE 	13 2 0
	41	[359]	LOADK    	14 -17	; "7 Time to read"
	42	[359]	LOADK    	15 -8	; "00:00:00"
	43	[359]	SETLIST  	13 2 1	; 1
	44	[359]	NEWTABLE 	14 2 0
	45	[360]	LOADK    	15 -18	; "8 Time to read"
	46	[360]	LOADK    	16 -8	; "00:00:00"
	47	[360]	SETLIST  	14 2 1	; 1
	48	[360]	NEWTABLE 	15 2 0
	49	[361]	LOADK    	16 -19	; "9 Time to read"
	50	[361]	LOADK    	17 -8	; "00:00:00"
	51	[361]	SETLIST  	15 2 1	; 1
	52	[361]	NEWTABLE 	16 2 0
	53	[362]	LOADK    	17 -20	; "10 Time to read"
	54	[362]	LOADK    	18 -8	; "00:00:00"
	55	[362]	SETLIST  	16 2 1	; 1
	56	[362]	NEWTABLE 	17 2 0
	57	[363]	LOADK    	18 -21	; "11 Time to read"
	58	[363]	LOADK    	19 -8	; "00:00:00"
	59	[363]	SETLIST  	17 2 1	; 1
	60	[364]	LOADK    	18 -22	; "----------------------------"
	61	[364]	NEWTABLE 	19 2 0
	62	[365]	LOADK    	20 -23	; "12 Time to read"
	63	[365]	LOADK    	21 -8	; "00:00:00"
	64	[365]	SETLIST  	19 2 1	; 1
	65	[365]	NEWTABLE 	20 2 0
	66	[366]	LOADK    	21 -24	; "13 Time to read"
	67	[366]	LOADK    	22 -8	; "00:00:00"
	68	[366]	SETLIST  	20 2 1	; 1
	69	[366]	NEWTABLE 	21 2 0
	70	[367]	LOADK    	22 -25	; "14 Time to read"
	71	[367]	LOADK    	23 -8	; "00:00:00"
	72	[367]	SETLIST  	21 2 1	; 1
	73	[367]	NEWTABLE 	22 2 0
	74	[368]	LOADK    	23 -26	; "15 Time to read"
	75	[368]	LOADK    	24 -8	; "00:00:00"
	76	[368]	SETLIST  	22 2 1	; 1
	77	[368]	NEWTABLE 	23 2 0
	78	[369]	LOADK    	24 -27	; "16 Time to read"
	79	[369]	LOADK    	25 -8	; "00:00:00"
	80	[369]	SETLIST  	23 2 1	; 1
	81	[369]	NEWTABLE 	24 2 0
	82	[370]	LOADK    	25 -28	; "17 Time to read"
	83	[370]	LOADK    	26 -8	; "00:00:00"
	84	[370]	SETLIST  	24 2 1	; 1
	85	[370]	NEWTABLE 	25 2 0
	86	[371]	LOADK    	26 -29	; "18 Time to read"
	87	[371]	LOADK    	27 -8	; "00:00:00"
	88	[371]	SETLIST  	25 2 1	; 1
	89	[371]	NEWTABLE 	26 2 0
	90	[372]	LOADK    	27 -30	; "19 Time to read"
	91	[372]	LOADK    	28 -8	; "00:00:00"
	92	[372]	SETLIST  	26 2 1	; 1
	93	[372]	NEWTABLE 	27 2 0
	94	[373]	LOADK    	28 -31	; "20 Time to read"
	95	[373]	LOADK    	29 -8	; "00:00:00"
	96	[373]	SETLIST  	27 2 1	; 1
	97	[373]	NEWTABLE 	28 2 0
	98	[374]	LOADK    	29 -32	; "21 Time to read"
	99	[374]	LOADK    	30 -8	; "00:00:00"
	100	[374]	SETLIST  	28 2 1	; 1
	101	[375]	SETLIST  	4 24 1	; 1
	102	[375]	SETTABLE 	3 -6 4	; "kv_pairs" -
	103	[348]	CALL     	1 3 2
	104	[377]	GETUPVAL 	2 0	; UIManager
	105	[377]	SELF     	2 2 -33	; "show"
	106	[377]	MOVE     	4 1
	107	[377]	CALL     	2 3 1
	108	[378]	RETURN   	0 1

function <./tools/wbuilder.lua:380,396> (53 instructions, 212 bytes at 0x7ffab7509cb0)
0 params, 8 slots, 5 upvalues, 1 local, 22 constants, 0 functions
	1	[382]	GETUPVAL 	0 0	; DocumentRegistry
	2	[382]	SELF     	0 0 -2	; "openDocument"
	3	[382]	LOADK    	2 -3	; "spec/front/unit/data/2col.pdf"
	4	[382]	CALL     	0 3 2
	5	[382]	SETGLOBAL	0 -1	; doc
	6	[383]	GETUPVAL 	0 1	; ReaderUI
	7	[383]	SELF     	0 0 -5	; "new"
	8	[383]	NEWTABLE 	2 0 3
	9	[384]	GETGLOBAL	3 -7	; readerwindow
	10	[384]	SETTABLE 	2 -6 3	; "dialog" -
	11	[385]	GETUPVAL 	3 2	; Geom
	12	[385]	SELF     	3 3 -5	; "new"
	13	[385]	NEWTABLE 	5 0 2
	14	[385]	GETUPVAL 	6 3	; Screen
	15	[385]	SELF     	6 6 -10	; "getWidth"
	16	[385]	CALL     	6 2 2
	17	[385]	SUB      	6 6 -11	; - 100
	18	[385]	SETTABLE 	5 -9 6	; "w" -
	19	[385]	GETUPVAL 	6 3	; Screen
	20	[385]	SELF     	6 6 -13	; "getHeight"
	21	[385]	CALL     	6 2 2
	22	[385]	SUB      	6 6 -11	; - 100
	23	[385]	SETTABLE 	5 -12 6	; "h" -
	24	[385]	CALL     	3 3 2
	25	[385]	SETTABLE 	2 -8 3	; "dimen" -
	26	[386]	GETGLOBAL	3 -1	; doc
	27	[386]	SETTABLE 	2 -14 3	; "document" -
	28	[383]	CALL     	0 3 2
	29	[387]	SETGLOBAL	0 -4	; reader
	30	[389]	GETGLOBAL	0 -15	; require
	31	[389]	LOADK    	1 -16	; "ui/widget/bookstatuswidget"
	32	[389]	CALL     	0 2 2
	33	[389]	SELF     	0 0 -5	; "new"
	34	[389]	NEWTABLE 	2 0 4
	35	[390]	GETGLOBAL	3 -1	; doc
	36	[390]	SELF     	3 3 -18	; "getCoverPageImage"
	37	[390]	CALL     	3 2 2
	38	[390]	SETTABLE 	2 -17 3	; "thumbnail" -
	39	[391]	GETGLOBAL	3 -1	; doc
	40	[391]	SELF     	3 3 -20	; "getProps"
	41	[391]	CALL     	3 2 2
	42	[391]	SETTABLE 	2 -19 3	; "props" -
	43	[392]	GETGLOBAL	3 -1	; doc
	44	[392]	SETTABLE 	2 -14 3	; "document" -
	45	[393]	GETGLOBAL	3 -4	; reader
	46	[393]	GETTABLE 	3 3 -21	; "view"
	47	[393]	SETTABLE 	2 -21 3	; "view" -
	48	[389]	CALL     	0 3 2
	49	[395]	GETUPVAL 	1 4	; UIManager
	50	[395]	SELF     	1 1 -22	; "show"
	51	[395]	MOVE     	3 0
	52	[395]	CALL     	1 3 1
	53	[396]	RETURN   	0 1

function <./tools/wbuilder.lua:398,401> (10 instructions, 40 bytes at 0x7ffab750a780)
0 params, 6 slots, 1 upvalue, 1 local, 4 constants, 0 functions
	1	[399]	GETGLOBAL	0 -1	; require
	2	[399]	LOADK    	1 -2	; "tools/kobo_touch_probe"
	3	[399]	CALL     	0 2 2
	4	[400]	GETUPVAL 	1 0	; UIManager
	5	[400]	SELF     	1 1 -3	; "show"
	6	[400]	SELF     	3 0 -4	; "new"
	7	[400]	NEWTABLE 	5 0 0
	8	[400]	CALL     	3 3 0
	9	[400]	CALL     	1 0 1
	10	[401]	RETURN   	0 1

function <./tools/wbuilder.lua:403,443> (58 instructions, 232 bytes at 0x7ffab750adb0)
0 params, 11 slots, 1 upvalue, 6 locals, 30 constants, 0 functions
	1	[404]	NEWTABLE 	0 4 0
	2	[404]	NEWTABLE 	1 0 4
	3	[406]	SETTABLE 	1 -1 -2	; "ssid" "CMU-SECURE"
	4	[407]	SETTABLE 	1 -3 -4	; "signal_level" -58
	5	[408]	SETTABLE 	1 -5 -6	; "flags" "[WPA2-PSK-CCMP][ESS]"
	6	[409]	SETTABLE 	1 -7 -8	; "signal_quality" 84
	7	[410]	NEWTABLE 	2 0 5
	8	[412]	SETTABLE 	2 -1 -9	; "ssid" "CMU-SECURE 2"
	9	[413]	SETTABLE 	2 -3 -10	; "signal_level" -258
	10	[414]	SETTABLE 	2 -7 -11	; "signal_quality" 44
	11	[415]	SETTABLE 	2 -5 -6	; "flags" "[WPA2-PSK-CCMP][ESS]"
	12	[416]	SETTABLE 	2 -12 -13	; "password" "okgo"
	13	[417]	NEWTABLE 	3 0 4
	14	[419]	SETTABLE 	3 -1 -14	; "ssid" "218"
	15	[420]	SETTABLE 	3 -3 -15	; "signal_level" 58
	16	[421]	SETTABLE 	3 -7 -16	; "signal_quality" 100
	17	[422]	SETTABLE 	3 -5 -17	; "flags" "[WEP][ESS]"
	18	[423]	NEWTABLE 	4 0 4
	19	[425]	SETTABLE 	4 -1 -18	; "ssid" "318"
	20	[426]	SETTABLE 	4 -3 -16	; "signal_level" 100
	21	[427]	SETTABLE 	4 -7 -16	; "signal_quality" 100
	22	[428]	SETTABLE 	4 -5 -6	; "flags" "[WPA2-PSK-CCMP][ESS]"
	23	[430]	SETLIST  	0 4 1	; 1
	24	[432]	LOADK    	1 -19	; 1
	25	[432]	LOADK    	2 -20	; 10
	26	[432]	LOADK    	3 -19	; 1
	27	[432]	FORPREP  	1 18	; to 46
	28	[433]	GETGLOBAL	5 -21	; table
	29	[433]	GETTABLE 	5 5 -22	; "insert"
	30	[433]	MOVE     	6 0
	31	[433]	NEWTABLE 	7 0 4
	32	[434]	LOADK    	8 -23	; "918-"
	33	[434]	GETGLOBAL	9 -24	; tostring
	34	[434]	MOVE     	10 4
	35	[434]	CALL     	9 2 2
	36	[434]	CONCAT   	8 8 9
	37	[434]	SETTABLE 	7 -1 8	; "ssid" -
	38	[435]	MUL      	8 4 -25	; - 2
	39	[435]	SUB      	8 -4 8	; -58 -
	40	[435]	SETTABLE 	7 -3 8	; "signal_level" -
	41	[436]	MUL      	8 4 -25	; - 2
	42	[436]	SUB      	8 -8 8	; 84 -
	43	[436]	SETTABLE 	7 -7 8	; "signal_quality" -
	44	[437]	SETTABLE 	7 -5 -6	; "flags" "[WPA2-PSK-CCMP][ESS]"
	45	[433]	CALL     	5 3 1
	46	[432]	FORLOOP  	1 -19	; to 28
	47	[441]	GETGLOBAL	1 -26	; require
	48	[441]	LOADK    	2 -27	; "ui/widget/networksetting"
	49	[441]	CALL     	1 2 2
	50	[441]	SELF     	1 1 -28	; "new"
	51	[441]	NEWTABLE 	3 0 1
	52	[441]	SETTABLE 	3 -29 0	; "network_list" -
	53	[441]	CALL     	1 3 2
	54	[442]	GETUPVAL 	2 0	; UIManager
	55	[442]	SELF     	2 2 -30	; "show"
	56	[442]	MOVE     	4 1
	57	[442]	CALL     	2 3 1
	58	[443]	RETURN   	0 1
