
main <./frontend/apps/cloudstorage/webdavapi.lua:0,0> (55 instructions, 220 bytes at 0x7fca80005770)
0+ params, 12 slots, 0 upvalues, 11 locals, 15 constants, 4 functions
	1	[1]	GETGLOBAL	0 -1	; require
	2	[1]	LOADK    	1 -2	; "document/documentregistry"
	3	[1]	CALL     	0 2 2
	4	[2]	GETGLOBAL	1 -1	; require
	5	[2]	LOADK    	2 -3	; "ffi/util"
	6	[2]	CALL     	1 2 2
	7	[3]	GETGLOBAL	2 -1	; require
	8	[3]	LOADK    	3 -4	; "socket.http"
	9	[3]	CALL     	2 2 2
	10	[4]	GETGLOBAL	3 -1	; require
	11	[4]	LOADK    	4 -5	; "ssl.https"
	12	[4]	CALL     	3 2 2
	13	[5]	GETGLOBAL	4 -1	; require
	14	[5]	LOADK    	5 -6	; "ltn12"
	15	[5]	CALL     	4 2 2
	16	[6]	GETGLOBAL	5 -1	; require
	17	[6]	LOADK    	6 -7	; "mime"
	18	[6]	CALL     	5 2 2
	19	[7]	GETGLOBAL	6 -1	; require
	20	[7]	LOADK    	7 -8	; "socket"
	21	[7]	CALL     	6 2 2
	22	[8]	GETGLOBAL	7 -1	; require
	23	[8]	LOADK    	8 -9	; "socket.url"
	24	[8]	CALL     	7 2 2
	25	[9]	GETGLOBAL	8 -1	; require
	26	[9]	LOADK    	9 -10	; "util"
	27	[9]	CALL     	8 2 2
	28	[10]	GETGLOBAL	9 -1	; require
	29	[10]	LOADK    	10 -11	; "gettext"
	30	[10]	CALL     	9 2 2
	31	[12]	NEWTABLE 	10 0 0
	32	[41]	CLOSURE  	11 0	; 0x7fca80005b30
	33	[15]	SETTABLE 	10 -12 11	; "isCurrentDirectory" -
	34	[53]	CLOSURE  	11 1	; 0x7fca80005f00
	35	[44]	SETTABLE 	10 -13 11	; "urlEncode" -
	36	[148]	CLOSURE  	11 2	; 0x7fca80006dd0
	37	[148]	MOVE     	0 7
	38	[148]	MOVE     	0 5
	39	[148]	MOVE     	0 4
	40	[148]	MOVE     	0 2
	41	[148]	MOVE     	0 3
	42	[148]	MOVE     	0 6
	43	[148]	MOVE     	0 8
	44	[148]	MOVE     	0 1
	45	[148]	MOVE     	0 0
	46	[55]	SETTABLE 	10 -14 11	; "listFolder" -
	47	[164]	CLOSURE  	11 3	; 0x7fca80007d50
	48	[164]	MOVE     	0 7
	49	[164]	MOVE     	0 5
	50	[164]	MOVE     	0 2
	51	[164]	MOVE     	0 3
	52	[164]	MOVE     	0 4
	53	[150]	SETTABLE 	10 -15 11	; "downloadFile" -
	54	[166]	RETURN   	10 2
	55	[166]	RETURN   	0 1

function <./frontend/apps/cloudstorage/webdavapi.lua:15,41> (54 instructions, 216 bytes at 0x7fca80005b30)
4 params, 13 slots, 0 upvalues, 10 locals, 9 constants, 0 functions
	1	[19]	GETGLOBAL	7 -1	; string
	2	[19]	GETTABLE 	7 7 -2	; "find"
	3	[19]	MOVE     	8 2
	4	[19]	LOADK    	9 -3	; "/"
	5	[19]	LOADK    	10 -4	; 9
	6	[19]	CALL     	7 4 2
	7	[20]	TEST     	7 0 1
	8	[20]	JMP      	2	; to 11
	9	[21]	LOADK    	6 -3	; "/"
	10	[21]	JMP      	6	; to 17
	11	[23]	GETGLOBAL	8 -1	; string
	12	[23]	GETTABLE 	8 8 -5	; "sub"
	13	[23]	MOVE     	9 2
	14	[23]	MOVE     	10 7
	15	[23]	CALL     	8 3 2
	16	[23]	MOVE     	6 8
	17	[25]	LOADNIL  	8 8
	18	[26]	GETGLOBAL	9 -1	; string
	19	[26]	GETTABLE 	9 9 -5	; "sub"
	20	[26]	MOVE     	10 1
	21	[26]	LOADK    	11 -6	; -1
	22	[26]	CALL     	9 3 2
	23	[26]	EQ       	0 9 -3	; - "/"
	24	[26]	JMP      	8	; to 33
	25	[27]	GETGLOBAL	9 -1	; string
	26	[27]	GETTABLE 	9 9 -5	; "sub"
	27	[27]	MOVE     	10 1
	28	[27]	LOADK    	11 -7	; 1
	29	[27]	LOADK    	12 -8	; -2
	30	[27]	CALL     	9 4 2
	31	[27]	MOVE     	8 9
	32	[27]	JMP      	1	; to 34
	33	[29]	MOVE     	8 1
	34	[32]	EQ       	0 8 6
	35	[32]	JMP      	2	; to 38
	36	[33]	LOADBOOL 	4 1 0
	37	[33]	JMP      	12	; to 50
	38	[35]	GETGLOBAL	9 -1	; string
	39	[35]	GETTABLE 	9 9 -5	; "sub"
	40	[35]	MOVE     	10 8
	41	[35]	GETGLOBAL	11 -1	; string
	42	[35]	GETTABLE 	11 11 -9	; "len"
	43	[35]	MOVE     	12 6
	44	[35]	CALL     	11 2 2
	45	[35]	ADD      	11 11 -7	; - 1
	46	[35]	CALL     	9 3 2
	47	[36]	EQ       	0 9 3
	48	[36]	JMP      	1	; to 50
	49	[37]	LOADBOOL 	5 1 0
	50	[40]	TESTSET  	9 4 1
	51	[40]	JMP      	1	; to 53
	52	[40]	MOVE     	9 5
	53	[40]	RETURN   	9 2
	54	[41]	RETURN   	0 1

function <./frontend/apps/cloudstorage/webdavapi.lua:44,53> (11 instructions, 44 bytes at 0x7fca80005f00)
2 params, 7 slots, 0 upvalues, 3 locals, 3 constants, 1 function
	1	[47]	CLOSURE  	2 0	; 0x7fca800068e0
	2	[48]	EQ       	0 1 -1	; - nil
	3	[48]	JMP      	1	; to 5
	4	[49]	RETURN   	0 1
	5	[51]	SELF     	3 1 -2	; "gsub"
	6	[51]	LOADK    	5 -3	; "([^%w%/%-%.%_%~%!%*%'%(%)])"
	7	[51]	MOVE     	6 2
	8	[51]	CALL     	3 4 2
	9	[51]	MOVE     	1 3
	10	[52]	RETURN   	1 2
	11	[53]	RETURN   	0 1

function <./frontend/apps/cloudstorage/webdavapi.lua:45,47> (10 instructions, 40 bytes at 0x7fca800068e0)
1 param, 5 slots, 0 upvalues, 1 local, 4 constants, 0 functions
	1	[46]	GETGLOBAL	1 -1	; string
	2	[46]	GETTABLE 	1 1 -2	; "format"
	3	[46]	LOADK    	2 -3	; "%%%02X"
	4	[46]	GETGLOBAL	3 -1	; string
	5	[46]	GETTABLE 	3 3 -4	; "byte"
	6	[46]	MOVE     	4 0
	7	[46]	CALL     	3 2 0
	8	[46]	TAILCALL 	1 0 0
	9	[46]	RETURN   	1 0
	10	[47]	RETURN   	0 1

function <./frontend/apps/cloudstorage/webdavapi.lua:55,148> (241 instructions, 964 bytes at 0x7fca80006dd0)
5 params, 33 slots, 9 upvalues, 33 locals, 57 constants, 2 functions
	1	[56]	SELF     	5 0 -1	; "urlEncode"
	2	[56]	MOVE     	7 4
	3	[56]	CALL     	5 3 2
	4	[57]	NEWTABLE 	6 0 0
	5	[58]	NEWTABLE 	7 0 0
	6	[60]	LOADBOOL 	8 0 0
	7	[61]	LOADBOOL 	9 0 0
	8	[62]	GETGLOBAL	10 -2	; string
	9	[62]	GETTABLE 	10 10 -3	; "sub"
	10	[62]	MOVE     	11 1
	11	[62]	LOADK    	12 -4	; -1
	12	[62]	CALL     	10 3 2
	13	[62]	EQ       	1 10 -5	; - "/"
	14	[62]	JMP      	1	; to 16
	15	[62]	LOADBOOL 	8 1 0
	16	[63]	EQ       	1 5 -6	; - nil
	17	[63]	JMP      	2	; to 20
	18	[63]	EQ       	0 5 -5	; - "/"
	19	[63]	JMP      	2	; to 22
	20	[64]	LOADK    	5 -7	; ""
	21	[64]	JMP      	17	; to 39
	22	[65]	GETGLOBAL	10 -2	; string
	23	[65]	GETTABLE 	10 10 -3	; "sub"
	24	[65]	MOVE     	11 5
	25	[65]	LOADK    	12 -8	; 1
	26	[65]	LOADK    	13 -9	; 2
	27	[65]	CALL     	10 4 2
	28	[65]	EQ       	0 10 -5	; - "/"
	29	[65]	JMP      	9	; to 39
	30	[66]	TEST     	8 0 0
	31	[66]	JMP      	6	; to 38
	32	[68]	GETGLOBAL	10 -2	; string
	33	[68]	GETTABLE 	10 10 -3	; "sub"
	34	[68]	MOVE     	11 5
	35	[68]	LOADK    	12 -8	; 1
	36	[68]	CALL     	10 3 2
	37	[68]	MOVE     	5 10
	38	[70]	LOADBOOL 	9 1 0
	39	[72]	TEST     	8 0 1
	40	[72]	JMP      	5	; to 46
	41	[72]	TEST     	9 0 1
	42	[72]	JMP      	3	; to 46
	43	[73]	MOVE     	10 1
	44	[73]	LOADK    	11 -5	; "/"
	45	[73]	CONCAT   	1 10 11
	46	[75]	MOVE     	10 1
	47	[75]	MOVE     	11 5
	48	[75]	CONCAT   	10 10 11
	49	[77]	NEWTABLE 	11 0 0
	50	[77]	NEWTABLE 	12 0 0
	51	[78]	GETUPVAL 	13 0	; url
	52	[78]	GETTABLE 	13 13 -10	; "parse"
	53	[78]	MOVE     	14 10
	54	[78]	CALL     	13 2 2
	55	[79]	LOADK    	14 -11	; "<?xml version=\"1.0\"?><a:propfind xmlns:a=\"DAV:\"><a:prop><a:resourcetype/></a:prop></a:propfind>"
	56	[80]	GETGLOBAL	15 -2	; string
	57	[80]	GETTABLE 	15 15 -12	; "format"
	58	[80]	LOADK    	16 -13	; "%s:%s"
	59	[80]	MOVE     	17 2
	60	[80]	MOVE     	18 3
	61	[80]	CALL     	15 4 2
	62	[81]	NEWTABLE 	16 0 4
	63	[81]	LOADK    	17 -15	; "Basic "
	64	[81]	GETUPVAL 	18 1	; mime
	65	[81]	GETTABLE 	18 18 -16	; "b64"
	66	[81]	MOVE     	19 15
	67	[81]	CALL     	18 2 2
	68	[81]	CONCAT   	17 17 18
	69	[81]	SETTABLE 	16 -14 17	; "Authorization" -
	70	[82]	SETTABLE 	16 -17 -18	; "Content-Type" "application/xml"
	71	[83]	SETTABLE 	16 -19 -20	; "Depth" "1"
	72	[84]	LEN      	17 14
	73	[84]	SETTABLE 	16 -21 17	; "Content-Length" -
	74	[85]	SETTABLE 	11 -22 10	; "url" -
	75	[86]	SETTABLE 	11 -23 -24	; "method" "PROPFIND"
	76	[87]	SETTABLE 	11 -25 16	; "headers" -
	77	[88]	GETUPVAL 	17 2	; ltn12
	78	[88]	GETTABLE 	17 17 -26	; "source"
	79	[88]	GETTABLE 	17 17 -2	; "string"
	80	[88]	MOVE     	18 14
	81	[88]	CALL     	17 2 2
	82	[88]	SETTABLE 	11 -26 17	; "source" -
	83	[89]	GETUPVAL 	17 2	; ltn12
	84	[89]	GETTABLE 	17 17 -27	; "sink"
	85	[89]	GETTABLE 	17 17 -28	; "table"
	86	[89]	MOVE     	18 12
	87	[89]	CALL     	17 2 2
	88	[89]	SETTABLE 	11 -27 17	; "sink" -
	89	[90]	GETUPVAL 	17 3	; http
	90	[90]	SETTABLE 	17 -29 -30	; "TIMEOUT" 5
	91	[91]	GETUPVAL 	17 4	; https
	92	[91]	SETTABLE 	17 -29 -30	; "TIMEOUT" 5
	93	[92]	GETTABLE 	17 13 -31	; "scheme"
	94	[92]	EQ       	0 17 -32	; - "http"
	95	[92]	JMP      	4	; to 100
	96	[92]	GETUPVAL 	17 3	; http
	97	[92]	GETTABLE 	17 17 -33	; "request"
	98	[92]	TEST     	17 0 1
	99	[92]	JMP      	2	; to 102
	100	[92]	GETUPVAL 	17 4	; https
	101	[92]	GETTABLE 	17 17 -33	; "request"
	102	[93]	GETUPVAL 	18 5	; socket
	103	[93]	GETTABLE 	18 18 -34	; "skip"
	104	[93]	LOADK    	19 -8	; 1
	105	[93]	MOVE     	20 17
	106	[93]	MOVE     	21 11
	107	[93]	CALL     	20 2 0
	108	[93]	CALL     	18 0 2
	109	[94]	EQ       	0 18 -6	; - nil
	110	[94]	JMP      	2	; to 113
	111	[95]	LOADNIL  	19 19
	112	[95]	RETURN   	19 2
	113	[98]	GETGLOBAL	19 -28	; table
	114	[98]	GETTABLE 	19 19 -35	; "concat"
	115	[98]	MOVE     	20 12
	116	[98]	CALL     	19 2 2
	117	[99]	EQ       	1 19 -7	; - ""
	118	[99]	JMP      	92	; to 211
	119	[101]	SELF     	20 19 -36	; "gmatch"
	120	[101]	LOADK    	22 -37	; "<d:response>(.-)</d:response>"
	121	[101]	CALL     	20 3 4
	122	[101]	JMP      	85	; to 208
	123	[104]	SELF     	24 23 -38	; "match"
	124	[104]	LOADK    	26 -39	; "<d:href>(.*)</d:href>"
	125	[104]	CALL     	24 3 2
	126	[105]	GETGLOBAL	25 -2	; string
	127	[105]	GETTABLE 	25 25 -3	; "sub"
	128	[105]	MOVE     	26 24
	129	[105]	LOADK    	27 -4	; -1
	130	[105]	CALL     	25 3 2
	131	[105]	EQ       	0 25 -5	; - "/"
	132	[105]	JMP      	7	; to 140
	133	[106]	GETGLOBAL	25 -2	; string
	134	[106]	GETTABLE 	25 25 -3	; "sub"
	135	[106]	MOVE     	26 24
	136	[106]	LOADK    	27 -8	; 1
	137	[106]	LOADK    	28 -40	; -2
	138	[106]	CALL     	25 4 2
	139	[106]	MOVE     	24 25
	140	[108]	SELF     	25 0 -41	; "isCurrentDirectory"
	141	[108]	MOVE     	27 24
	142	[108]	MOVE     	28 1
	143	[108]	MOVE     	29 5
	144	[108]	CALL     	25 5 2
	145	[109]	GETUPVAL 	26 6	; util
	146	[109]	GETTABLE 	26 26 -42	; "urlDecode"
	147	[109]	GETUPVAL 	27 7	; FFIUtil
	148	[109]	GETTABLE 	27 27 -43	; "basename"
	149	[109]	MOVE     	28 24
	150	[109]	CALL     	27 2 0
	151	[109]	CALL     	26 0 2
	152	[110]	MOVE     	27 5
	153	[110]	LOADK    	28 -5	; "/"
	154	[110]	MOVE     	29 26
	155	[110]	CONCAT   	27 27 29
	156	[111]	SELF     	28 23 -44	; "find"
	157	[111]	LOADK    	30 -45	; "<d:collection/>"
	158	[111]	CALL     	28 3 2
	159	[111]	TEST     	28 0 0
	160	[111]	JMP      	18	; to 179
	161	[112]	MOVE     	28 26
	162	[112]	LOADK    	29 -5	; "/"
	163	[112]	CONCAT   	26 28 29
	164	[113]	TEST     	25 0 1
	165	[113]	JMP      	42	; to 208
	166	[114]	GETGLOBAL	28 -28	; table
	167	[114]	GETTABLE 	28 28 -46	; "insert"
	168	[114]	MOVE     	29 6
	169	[114]	NEWTABLE 	30 0 3
	170	[115]	SETTABLE 	30 -47 26	; "text" -
	171	[116]	GETUPVAL 	31 6	; util
	172	[116]	GETTABLE 	31 31 -42	; "urlDecode"
	173	[116]	MOVE     	32 27
	174	[116]	CALL     	31 2 2
	175	[116]	SETTABLE 	30 -22 31	; "url" -
	176	[117]	SETTABLE 	30 -48 -49	; "type" "folder"
	177	[114]	CALL     	28 3 1
	178	[119]	JMP      	29	; to 208
	179	[120]	SELF     	28 23 -44	; "find"
	180	[120]	LOADK    	30 -50	; "<d:resourcetype/>"
	181	[120]	CALL     	28 3 2
	182	[120]	TEST     	28 0 0
	183	[120]	JMP      	24	; to 208
	184	[120]	GETUPVAL 	28 8	; DocumentRegistry
	185	[120]	SELF     	28 28 -51	; "hasProvider"
	186	[120]	MOVE     	30 26
	187	[120]	CALL     	28 3 2
	188	[121]	TEST     	28 0 1
	189	[121]	JMP      	6	; to 196
	190	[121]	GETGLOBAL	28 -52	; G_reader_settings
	191	[121]	SELF     	28 28 -53	; "isTrue"
	192	[121]	LOADK    	30 -54	; "show_unsupported"
	193	[121]	CALL     	28 3 2
	194	[121]	TEST     	28 0 0
	195	[121]	JMP      	12	; to 208
	196	[122]	GETGLOBAL	28 -28	; table
	197	[122]	GETTABLE 	28 28 -46	; "insert"
	198	[122]	MOVE     	29 7
	199	[122]	NEWTABLE 	30 0 3
	200	[123]	SETTABLE 	30 -47 26	; "text" -
	201	[124]	GETUPVAL 	31 6	; util
	202	[124]	GETTABLE 	31 31 -42	; "urlDecode"
	203	[124]	MOVE     	32 27
	204	[124]	CALL     	31 2 2
	205	[124]	SETTABLE 	30 -22 31	; "url" -
	206	[125]	SETTABLE 	30 -48 -55	; "type" "file"
	207	[122]	CALL     	28 3 1
	208	[101]	TFORLOOP 	20 1
	209	[127]	JMP      	-87	; to 123
	210	[128]	JMP      	2	; to 213
	211	[130]	LOADNIL  	20 20
	212	[130]	RETURN   	20 2
	213	[134]	GETGLOBAL	20 -28	; table
	214	[134]	GETTABLE 	20 20 -56	; "sort"
	215	[134]	MOVE     	21 6
	216	[136]	CLOSURE  	22 0	; 0x7fca80006c70
	217	[134]	CALL     	20 3 1
	218	[137]	GETGLOBAL	20 -28	; table
	219	[137]	GETTABLE 	20 20 -56	; "sort"
	220	[137]	MOVE     	21 7
	221	[139]	CLOSURE  	22 1	; 0x7fca800077e0
	222	[137]	CALL     	20 3 1
	223	[140]	GETGLOBAL	20 -57	; ipairs
	224	[140]	MOVE     	21 7
	225	[140]	CALL     	20 2 4
	226	[140]	JMP      	11	; to 238
	227	[141]	GETGLOBAL	25 -28	; table
	228	[141]	GETTABLE 	25 25 -46	; "insert"
	229	[141]	MOVE     	26 6
	230	[141]	NEWTABLE 	27 0 3
	231	[142]	GETTABLE 	28 24 -47	; "text"
	232	[142]	SETTABLE 	27 -47 28	; "text" -
	233	[143]	GETTABLE 	28 24 -22	; "url"
	234	[143]	SETTABLE 	27 -22 28	; "url" -
	235	[144]	GETTABLE 	28 24 -48	; "type"
	236	[144]	SETTABLE 	27 -48 28	; "type" -
	237	[141]	CALL     	25 3 1
	238	[140]	TFORLOOP 	20 2
	239	[145]	JMP      	-13	; to 227
	240	[147]	RETURN   	6 2
	241	[148]	RETURN   	0 1

function <./frontend/apps/cloudstorage/webdavapi.lua:134,136> (8 instructions, 32 bytes at 0x7fca80006c70)
2 params, 4 slots, 0 upvalues, 2 locals, 1 constant, 0 functions
	1	[135]	GETTABLE 	2 0 -1	; "text"
	2	[135]	GETTABLE 	3 1 -1	; "text"
	3	[135]	LT       	1 2 3
	4	[135]	JMP      	1	; to 6
	5	[135]	LOADBOOL 	2 0 1
	6	[135]	LOADBOOL 	2 1 0
	7	[135]	RETURN   	2 2
	8	[136]	RETURN   	0 1

function <./frontend/apps/cloudstorage/webdavapi.lua:137,139> (8 instructions, 32 bytes at 0x7fca800077e0)
2 params, 4 slots, 0 upvalues, 2 locals, 1 constant, 0 functions
	1	[138]	GETTABLE 	2 0 -1	; "text"
	2	[138]	GETTABLE 	3 1 -1	; "text"
	3	[138]	LT       	1 2 3
	4	[138]	JMP      	1	; to 6
	5	[138]	LOADBOOL 	2 0 1
	6	[138]	LOADBOOL 	2 1 0
	7	[138]	RETURN   	2 2
	8	[139]	RETURN   	0 1

function <./frontend/apps/cloudstorage/webdavapi.lua:150,164> (49 instructions, 196 bytes at 0x7fca80007d50)
5 params, 15 slots, 5 upvalues, 12 locals, 21 constants, 0 functions
	1	[151]	GETUPVAL 	5 0	; url
	2	[151]	GETTABLE 	5 5 -1	; "parse"
	3	[151]	MOVE     	6 1
	4	[151]	CALL     	5 2 2
	5	[152]	GETGLOBAL	6 -2	; string
	6	[152]	GETTABLE 	6 6 -3	; "format"
	7	[152]	LOADK    	7 -4	; "%s:%s"
	8	[152]	MOVE     	8 2
	9	[152]	MOVE     	9 3
	10	[152]	CALL     	6 4 2
	11	[153]	NEWTABLE 	7 0 1
	12	[153]	LOADK    	8 -6	; "Basic "
	13	[153]	GETUPVAL 	9 1	; mime
	14	[153]	GETTABLE 	9 9 -7	; "b64"
	15	[153]	MOVE     	10 6
	16	[153]	CALL     	9 2 2
	17	[153]	CONCAT   	8 8 9
	18	[153]	SETTABLE 	7 -5 8	; "Authorization" -
	19	[154]	GETUPVAL 	8 2	; http
	20	[154]	SETTABLE 	8 -8 -9	; "TIMEOUT" 5
	21	[155]	GETUPVAL 	8 3	; https
	22	[155]	SETTABLE 	8 -8 -9	; "TIMEOUT" 5
	23	[156]	GETTABLE 	8 5 -10	; "scheme"
	24	[156]	EQ       	0 8 -11	; - "http"
	25	[156]	JMP      	4	; to 30
	26	[156]	GETUPVAL 	8 2	; http
	27	[156]	GETTABLE 	8 8 -12	; "request"
	28	[156]	TEST     	8 0 1
	29	[156]	JMP      	2	; to 32
	30	[156]	GETUPVAL 	8 3	; https
	31	[156]	GETTABLE 	8 8 -12	; "request"
	32	[157]	MOVE     	9 8
	33	[157]	NEWTABLE 	10 0 4
	34	[158]	SETTABLE 	10 -13 1	; "url" -
	35	[159]	SETTABLE 	10 -14 -15	; "method" "GET"
	36	[160]	SETTABLE 	10 -16 7	; "headers" -
	37	[161]	GETUPVAL 	11 4	; ltn12
	38	[161]	GETTABLE 	11 11 -17	; "sink"
	39	[161]	GETTABLE 	11 11 -18	; "file"
	40	[161]	GETGLOBAL	12 -19	; io
	41	[161]	GETTABLE 	12 12 -20	; "open"
	42	[161]	MOVE     	13 4
	43	[161]	LOADK    	14 -21	; "w"
	44	[161]	CALL     	12 3 0
	45	[161]	CALL     	11 0 2
	46	[161]	SETTABLE 	10 -17 11	; "sink" -
	47	[157]	CALL     	9 2 4
	48	[163]	RETURN   	10 2
	49	[164]	RETURN   	0 1
