
main <./spec/unit/widget_menu_spec.lua:0,0> (5 instructions, 20 bytes at 0x7fdce1c068d0)
0+ params, 3 slots, 0 upvalues, 0 locals, 2 constants, 1 function
	1	[1]	GETGLOBAL	0 -1	; describe
	2	[1]	LOADK    	1 -2	; "Menu widget"
	3	[37]	CLOSURE  	2 0	; 0x7fdce1c06b70
	4	[1]	CALL     	0 3 1
	5	[37]	RETURN   	0 1

function <./spec/unit/widget_menu_spec.lua:1,37> (10 instructions, 40 bytes at 0x7fdce1c06b70)
0 params, 4 slots, 0 upvalues, 1 local, 3 constants, 2 functions
	1	[3]	GETGLOBAL	1 -1	; setup
	2	[6]	CLOSURE  	2 0	; 0x7fdce1c06d90
	3	[6]	MOVE     	0 0
	4	[3]	CALL     	1 2 1
	5	[8]	GETGLOBAL	1 -2	; it
	6	[8]	LOADK    	2 -3	; "should convert item table from touch menu properly"
	7	[36]	CLOSURE  	3 1	; 0x7fdce1c07270
	8	[36]	MOVE     	0 0
	9	[8]	CALL     	1 3 1
	10	[37]	RETURN   	0 1

function <./spec/unit/widget_menu_spec.lua:3,6> (8 instructions, 32 bytes at 0x7fdce1c06d90)
0 params, 2 slots, 1 upvalue, 0 locals, 3 constants, 0 functions
	1	[4]	GETGLOBAL	0 -1	; require
	2	[4]	LOADK    	1 -2	; "commonrequire"
	3	[4]	CALL     	0 2 1
	4	[5]	GETGLOBAL	0 -1	; require
	5	[5]	LOADK    	1 -3	; "ui/widget/menu"
	6	[5]	CALL     	0 2 2
	7	[5]	SETUPVAL 	0 0	; Menu
	8	[6]	RETURN   	0 1

function <./spec/unit/widget_menu_spec.lua:8,36> (43 instructions, 172 bytes at 0x7fdce1c07270)
0 params, 10 slots, 1 upvalue, 3 locals, 14 constants, 2 functions
	1	[9]	CLOSURE  	0 0	; 0x7fdce1c07450
	2	[10]	CLOSURE  	1 1	; 0x7fdce1c07530
	3	[11]	GETUPVAL 	2 0	; Menu
	4	[11]	GETTABLE 	2 2 -1	; "itemTableFromTouchMenu"
	5	[11]	NEWTABLE 	3 0 2
	6	[12]	NEWTABLE 	4 2 1
	7	[13]	SETTABLE 	4 -3 -4	; "icon" "foo/bar.png"
	8	[13]	NEWTABLE 	5 0 2
	9	[14]	SETTABLE 	5 -5 -6	; "text" "foo"
	10	[14]	SETTABLE 	5 -7 0	; "callback" -
	11	[14]	NEWTABLE 	6 0 2
	12	[15]	SETTABLE 	6 -5 -8	; "text" "bar"
	13	[15]	SETTABLE 	6 -7 1	; "callback" -
	14	[16]	SETLIST  	4 2 1	; 1
	15	[16]	SETTABLE 	3 -2 4	; "navi" -
	16	[17]	NEWTABLE 	4 0 2
	17	[18]	SETTABLE 	4 -3 -10	; "icon" "foo/bar2.png"
	18	[19]	SETTABLE 	4 -7 1	; "callback" -
	19	[20]	SETTABLE 	3 -9 4	; "exit" -
	20	[11]	CALL     	2 2 2
	21	[22]	GETGLOBAL	3 -11	; assert
	22	[22]	GETTABLE 	3 3 -12	; "are"
	23	[22]	GETTABLE 	3 3 -13	; "same"
	24	[22]	MOVE     	4 2
	25	[22]	NEWTABLE 	5 2 0
	26	[22]	NEWTABLE 	6 0 2
	27	[24]	SETTABLE 	6 -5 -2	; "text" "navi"
	28	[25]	NEWTABLE 	7 2 1
	29	[26]	SETTABLE 	7 -3 -4	; "icon" "foo/bar.png"
	30	[26]	NEWTABLE 	8 0 2
	31	[27]	SETTABLE 	8 -5 -6	; "text" "foo"
	32	[27]	SETTABLE 	8 -7 0	; "callback" -
	33	[27]	NEWTABLE 	9 0 2
	34	[28]	SETTABLE 	9 -5 -8	; "text" "bar"
	35	[28]	SETTABLE 	9 -7 1	; "callback" -
	36	[29]	SETLIST  	7 2 1	; 1
	37	[29]	SETTABLE 	6 -14 7	; "sub_item_table" -
	38	[30]	NEWTABLE 	7 0 2
	39	[32]	SETTABLE 	7 -5 -9	; "text" "exit"
	40	[33]	SETTABLE 	7 -7 1	; "callback" -
	41	[35]	SETLIST  	5 2 1	; 1
	42	[22]	CALL     	3 3 1
	43	[36]	RETURN   	0 1

function <./spec/unit/widget_menu_spec.lua:9,9> (1 instruction, 4 bytes at 0x7fdce1c07450)
0 params, 2 slots, 0 upvalues, 0 locals, 0 constants, 0 functions
	1	[9]	RETURN   	0 1

function <./spec/unit/widget_menu_spec.lua:10,10> (1 instruction, 4 bytes at 0x7fdce1c07530)
0 params, 2 slots, 0 upvalues, 0 locals, 0 constants, 0 functions
	1	[10]	RETURN   	0 1
