
main <./spec/unit/widget_progresswidget_spec.lua:0,0> (5 instructions, 20 bytes at 0x7fd5114068f0)
0+ params, 3 slots, 0 upvalues, 0 locals, 2 constants, 1 function
	1	[1]	GETGLOBAL	0 -1	; describe
	2	[1]	LOADK    	1 -2	; "ProgressWidget widget"
	3	[18]	CLOSURE  	2 0	; 0x7fd511406b90
	4	[1]	CALL     	0 3 1
	5	[18]	RETURN   	0 1

function <./spec/unit/widget_progresswidget_spec.lua:1,18> (12 instructions, 48 bytes at 0x7fd511406b90)
0 params, 5 slots, 0 upvalues, 2 locals, 3 constants, 2 functions
	1	[3]	GETGLOBAL	2 -1	; setup
	2	[7]	CLOSURE  	3 0	; 0x7fd511406f10
	3	[7]	MOVE     	0 0
	4	[7]	MOVE     	0 1
	5	[3]	CALL     	2 2 1
	6	[9]	GETGLOBAL	2 -2	; it
	7	[9]	LOADK    	3 -3	; "should not crash with nil self.last"
	8	[17]	CLOSURE  	4 1	; 0x7fd511407350
	9	[17]	MOVE     	0 0
	10	[17]	MOVE     	0 1
	11	[9]	CALL     	2 3 1
	12	[18]	RETURN   	0 1

function <./spec/unit/widget_progresswidget_spec.lua:3,7> (13 instructions, 52 bytes at 0x7fd511406f10)
0 params, 2 slots, 2 upvalues, 0 locals, 5 constants, 0 functions
	1	[4]	GETGLOBAL	0 -1	; require
	2	[4]	LOADK    	1 -2	; "commonrequire"
	3	[4]	CALL     	0 2 1
	4	[5]	GETGLOBAL	0 -1	; require
	5	[5]	LOADK    	1 -3	; "ui/widget/progresswidget"
	6	[5]	CALL     	0 2 2
	7	[5]	SETUPVAL 	0 0	; ProgressWidget
	8	[6]	GETGLOBAL	0 -1	; require
	9	[6]	LOADK    	1 -4	; "device"
	10	[6]	CALL     	0 2 2
	11	[6]	GETTABLE 	0 0 -5	; "screen"
	12	[6]	SETUPVAL 	0 1	; Screen
	13	[7]	RETURN   	0 1

function <./spec/unit/widget_progresswidget_spec.lua:9,17> (26 instructions, 104 bytes at 0x7fd511407350)
0 params, 6 slots, 2 upvalues, 1 local, 13 constants, 0 functions
	1	[10]	GETUPVAL 	0 0	; ProgressWidget
	2	[10]	SELF     	0 0 -1	; "new"
	3	[10]	NEWTABLE 	2 0 4
	4	[11]	GETUPVAL 	3 1	; Screen
	5	[11]	SELF     	3 3 -3	; "scaleBySize"
	6	[11]	LOADK    	5 -4	; 100
	7	[11]	CALL     	3 3 2
	8	[11]	SETTABLE 	2 -2 3	; "width" -
	9	[12]	GETUPVAL 	3 1	; Screen
	10	[12]	SELF     	3 3 -3	; "scaleBySize"
	11	[12]	LOADK    	5 -6	; 50
	12	[12]	CALL     	3 3 2
	13	[12]	SETTABLE 	2 -5 3	; "height" -
	14	[13]	SETTABLE 	2 -7 -8	; "percentage" 0.05
	15	[14]	NEWTABLE 	3 1 0
	16	[14]	LOADK    	4 -10	; 1
	17	[14]	SETLIST  	3 1 1	; 1
	18	[14]	SETTABLE 	2 -9 3	; "ticks" -
	19	[10]	CALL     	0 3 2
	20	[16]	SELF     	1 0 -11	; "paintTo"
	21	[16]	GETUPVAL 	3 1	; Screen
	22	[16]	GETTABLE 	3 3 -12	; "bb"
	23	[16]	LOADK    	4 -13	; 0
	24	[16]	LOADK    	5 -13	; 0
	25	[16]	CALL     	1 5 1
	26	[17]	RETURN   	0 1
