-- BYTECODE -- widget_menu_spec.lua:3-6
0001    GGET     0   0      ; "require"
0002    KSTR     1   1      ; "commonrequire"
0003    CALL     0   1   2
0004    GGET     0   0      ; "require"
0005    KSTR     1   2      ; "ui/widget/menu"
0006    CALL     0   2   2
0007    USETV    0   0      ; Menu
0008    RET0     0   1

-- BYTECODE -- widget_menu_spec.lua:9-9
0001    RET0     0   1

-- BYTECODE -- widget_menu_spec.lua:10-10
0001    RET0     0   1

-- BYTECODE -- widget_menu_spec.lua:8-36
0001    FNEW     0   0      ; widget_menu_spec.lua:9
0002    FNEW     1   1      ; widget_menu_spec.lua:10
0003    UGET     2   0      ; Menu
0004    TGETS    2   2   2  ; "itemTableFromTouchMenu"
0005    TDUP     3   7
0006    TDUP     4   3
0007    TDUP     5   4
0008    TSETS    0   5   5  ; "callback"
0009    TSETB    5   4   1
0010    TDUP     5   6
0011    TSETS    1   5   5  ; "callback"
0012    TSETB    5   4   2
0013    TSETS    4   3   8  ; "navi"
0014    TDUP     4   9
0015    TSETS    1   4   5  ; "callback"
0016    TSETS    4   3  10  ; "exit"
0017    CALL     2   2   2
0018    GGET     3  11      ; "assert"
0019    TGETS    3   3  12  ; "are"
0020    TGETS    3   3  13  ; "same"
0021    MOV      4   2
0022    TNEW     5   3
0023    TDUP     6  14
0024    TDUP     7  15
0025    TDUP     8  16
0026    TSETS    0   8   5  ; "callback"
0027    TSETB    8   7   1
0028    TDUP     8  17
0029    TSETS    1   8   5  ; "callback"
0030    TSETB    8   7   2
0031    TSETS    7   6  18  ; "sub_item_table"
0032    TSETB    6   5   1
0033    TDUP     6  19
0034    TSETS    1   6   5  ; "callback"
0035    TSETB    6   5   2
0036    CALL     3   1   3
0037    RET0     0   1

-- BYTECODE -- widget_menu_spec.lua:1-37
0001    KPRI     0   0
0002    GGET     1   0      ; "setup"
0003    FNEW     2   1      ; widget_menu_spec.lua:3
0004    CALL     1   1   2
0005    GGET     1   2      ; "it"
0006    KSTR     2   3      ; "should convert item table from touch men"~
0007    FNEW     3   4      ; widget_menu_spec.lua:8
0008    CALL     1   1   3
0009    UCLO     0 => 0010
0010 => RET0     0   1

-- BYTECODE -- widget_menu_spec.lua:0-38
0001    GGET     0   0      ; "describe"
0002    KSTR     1   1      ; "Menu widget"
0003    FNEW     2   2      ; widget_menu_spec.lua:1
0004    CALL     0   1   3
0005    RET0     0   1

