
main <./frontend/ui/widget/container/widgetcontainer.lua:0,0> (39 instructions, 156 bytes at 0x7fd980406900)
0+ params, 6 slots, 0 upvalues, 4 locals, 15 constants, 7 functions
	1	[16]	GETGLOBAL	0 -1	; require
	2	[16]	LOADK    	1 -2	; "ui/geometry"
	3	[16]	CALL     	0 2 2
	4	[17]	GETGLOBAL	1 -1	; require
	5	[17]	LOADK    	2 -3	; "ui/widget/widget"
	6	[17]	CALL     	1 2 2
	7	[18]	GETGLOBAL	2 -1	; require
	8	[18]	LOADK    	3 -4	; "device"
	9	[18]	CALL     	2 2 2
	10	[20]	GETTABLE 	3 2 -5	; "should_restrict_JIT"
	11	[20]	TEST     	3 0 0
	12	[20]	JMP      	7	; to 20
	13	[21]	GETGLOBAL	3 -1	; require
	14	[21]	LOADK    	4 -6	; "jit"
	15	[21]	CALL     	3 2 2
	16	[21]	GETTABLE 	3 3 -7	; "off"
	17	[21]	LOADBOOL 	4 1 0
	18	[21]	LOADBOOL 	5 1 0
	19	[21]	CALL     	3 3 1
	20	[24]	SELF     	3 1 -8	; "new"
	21	[24]	CALL     	3 2 2
	22	[39]	CLOSURE  	4 0	; 0x7fd980406d60
	23	[26]	SETTABLE 	3 -9 4	; "init" -
	24	[51]	CLOSURE  	4 1	; 0x7fd9804071b0
	25	[51]	MOVE     	0 0
	26	[41]	SETTABLE 	3 -10 4	; "getSize" -
	27	[58]	CLOSURE  	4 2	; 0x7fd980407770
	28	[56]	SETTABLE 	3 -11 4	; "clear" -
	29	[83]	CLOSURE  	4 3	; 0x7fd9804077f0
	30	[60]	SETTABLE 	3 -12 4	; "paintTo" -
	31	[94]	CLOSURE  	4 4	; 0x7fd980407d70
	32	[85]	SETTABLE 	3 -13 4	; "propagateEvent" -
	33	[112]	CLOSURE  	4 5	; 0x7fd980408590
	34	[112]	MOVE     	0 1
	35	[105]	SETTABLE 	3 -14 4	; "handleEvent" -
	36	[118]	CLOSURE  	4 6	; 0x7fd980407030
	37	[114]	SETTABLE 	3 -15 4	; "free" -
	38	[120]	RETURN   	3 2
	39	[120]	RETURN   	0 1

function <./frontend/ui/widget/container/widgetcontainer.lua:26,39> (30 instructions, 120 bytes at 0x7fd980406d60)
1 param, 4 slots, 0 upvalues, 1 local, 6 constants, 0 functions
	1	[27]	GETTABLE 	1 0 -1	; "dimen"
	2	[27]	TEST     	1 0 0
	3	[27]	JMP      	26	; to 30
	4	[28]	GETTABLE 	1 0 -2	; "initDimen"
	5	[28]	TEST     	1 0 0
	6	[28]	JMP      	3	; to 10
	7	[29]	SELF     	1 0 -2	; "initDimen"
	8	[29]	CALL     	1 2 1
	9	[29]	JMP      	20	; to 30
	10	[31]	GETTABLE 	1 0 -1	; "dimen"
	11	[31]	GETTABLE 	1 1 -3	; "w"
	12	[31]	TEST     	1 0 1
	13	[31]	JMP      	6	; to 20
	14	[32]	GETTABLE 	1 0 -1	; "dimen"
	15	[32]	GETTABLE 	2 0 -4	; 1
	16	[32]	SELF     	2 2 -5	; "getSize"
	17	[32]	CALL     	2 2 2
	18	[32]	GETTABLE 	2 2 -3	; "w"
	19	[32]	SETTABLE 	1 -3 2	; "w" -
	20	[34]	GETTABLE 	1 0 -1	; "dimen"
	21	[34]	GETTABLE 	1 1 -6	; "h"
	22	[34]	TEST     	1 0 1
	23	[34]	JMP      	6	; to 30
	24	[35]	GETTABLE 	1 0 -1	; "dimen"
	25	[35]	GETTABLE 	2 0 -4	; 1
	26	[35]	SELF     	2 2 -5	; "getSize"
	27	[35]	CALL     	2 2 2
	28	[35]	GETTABLE 	2 2 -6	; "h"
	29	[35]	SETTABLE 	1 -6 2	; "h" -
	30	[39]	RETURN   	0 1

function <./frontend/ui/widget/container/widgetcontainer.lua:41,51> (22 instructions, 88 bytes at 0x7fd9804071b0)
1 param, 4 slots, 1 upvalue, 1 local, 7 constants, 0 functions
	1	[42]	GETTABLE 	1 0 -1	; "dimen"
	2	[42]	TEST     	1 0 0
	3	[42]	JMP      	3	; to 7
	4	[44]	GETTABLE 	1 0 -1	; "dimen"
	5	[44]	RETURN   	1 2
	6	[44]	JMP      	15	; to 22
	7	[45]	GETTABLE 	1 0 -2	; 1
	8	[45]	TEST     	1 0 0
	9	[45]	JMP      	5	; to 15
	10	[47]	GETTABLE 	1 0 -2	; 1
	11	[47]	SELF     	1 1 -3	; "getSize"
	12	[47]	TAILCALL 	1 2 0
	13	[47]	RETURN   	1 0
	14	[47]	JMP      	7	; to 22
	15	[49]	GETUPVAL 	1 0	; Geom
	16	[49]	SELF     	1 1 -4	; "new"
	17	[49]	NEWTABLE 	3 0 2
	18	[49]	SETTABLE 	3 -5 -6	; "w" 0
	19	[49]	SETTABLE 	3 -7 -6	; "h" 0
	20	[49]	TAILCALL 	1 3 0
	21	[49]	RETURN   	1 0
	22	[51]	RETURN   	0 1

function <./frontend/ui/widget/container/widgetcontainer.lua:56,58> (8 instructions, 32 bytes at 0x7fd980407770)
1 param, 3 slots, 0 upvalues, 1 local, 2 constants, 0 functions
	1	[57]	GETGLOBAL	1 -1	; table
	2	[57]	GETTABLE 	1 1 -2	; "remove"
	3	[57]	MOVE     	2 0
	4	[57]	CALL     	1 2 2
	5	[57]	TEST     	1 0 0
	6	[57]	JMP      	1	; to 8
	7	[57]	JMP      	-7	; to 1
	8	[58]	RETURN   	0 1

function <./frontend/ui/widget/container/widgetcontainer.lua:60,83> (98 instructions, 392 bytes at 0x7fd9804077f0)
4 params, 12 slots, 0 upvalues, 7 locals, 16 constants, 0 functions
	1	[62]	GETTABLE 	4 0 -1	; 1
	2	[62]	TEST     	4 0 0
	3	[62]	JMP      	94	; to 98
	4	[63]	GETTABLE 	4 0 -2	; "dimen"
	5	[63]	GETTABLE 	4 4 -3	; "x"
	6	[63]	TEST     	4 0 1
	7	[63]	JMP      	1	; to 9
	8	[63]	LOADK    	4 -4	; 0
	9	[63]	ADD      	2 2 4
	10	[64]	GETTABLE 	4 0 -2	; "dimen"
	11	[64]	GETTABLE 	4 4 -5	; "y"
	12	[64]	TEST     	4 0 1
	13	[64]	JMP      	1	; to 15
	14	[64]	LOADK    	4 -4	; 0
	15	[64]	ADD      	3 3 4
	16	[65]	GETTABLE 	4 0 -6	; "align"
	17	[65]	EQ       	0 4 -7	; - "top"
	18	[65]	JMP      	18	; to 37
	19	[66]	GETTABLE 	4 0 -1	; 1
	20	[66]	SELF     	4 4 -8	; "getSize"
	21	[66]	CALL     	4 2 2
	22	[67]	GETTABLE 	5 0 -1	; 1
	23	[67]	SELF     	5 5 -9	; "paintTo"
	24	[67]	MOVE     	7 1
	25	[68]	GETGLOBAL	8 -10	; math
	26	[68]	GETTABLE 	8 8 -11	; "floor"
	27	[68]	GETTABLE 	9 0 -2	; "dimen"
	28	[68]	GETTABLE 	9 9 -12	; "w"
	29	[68]	GETTABLE 	10 4 -12	; "w"
	30	[68]	SUB      	9 9 10
	31	[68]	DIV      	9 9 -13	; - 2
	32	[68]	CALL     	8 2 2
	33	[68]	ADD      	8 2 8
	34	[68]	MOVE     	9 3
	35	[67]	CALL     	5 5 1
	36	[68]	JMP      	61	; to 98
	37	[69]	GETTABLE 	4 0 -6	; "align"
	38	[69]	EQ       	0 4 -14	; - "bottom"
	39	[69]	JMP      	22	; to 62
	40	[70]	GETTABLE 	4 0 -1	; 1
	41	[70]	SELF     	4 4 -8	; "getSize"
	42	[70]	CALL     	4 2 2
	43	[71]	GETTABLE 	5 0 -1	; 1
	44	[71]	SELF     	5 5 -9	; "paintTo"
	45	[71]	MOVE     	7 1
	46	[72]	GETGLOBAL	8 -10	; math
	47	[72]	GETTABLE 	8 8 -11	; "floor"
	48	[72]	GETTABLE 	9 0 -2	; "dimen"
	49	[72]	GETTABLE 	9 9 -12	; "w"
	50	[72]	GETTABLE 	10 4 -12	; "w"
	51	[72]	SUB      	9 9 10
	52	[72]	DIV      	9 9 -13	; - 2
	53	[72]	CALL     	8 2 2
	54	[72]	ADD      	8 2 8
	55	[73]	GETTABLE 	9 0 -2	; "dimen"
	56	[73]	GETTABLE 	9 9 -15	; "h"
	57	[73]	GETTABLE 	10 4 -15	; "h"
	58	[73]	SUB      	9 9 10
	59	[73]	ADD      	9 3 9
	60	[71]	CALL     	5 5 1
	61	[73]	JMP      	36	; to 98
	62	[74]	GETTABLE 	4 0 -6	; "align"
	63	[74]	EQ       	0 4 -16	; - "center"
	64	[74]	JMP      	26	; to 91
	65	[75]	GETTABLE 	4 0 -1	; 1
	66	[75]	SELF     	4 4 -8	; "getSize"
	67	[75]	CALL     	4 2 2
	68	[76]	GETTABLE 	5 0 -1	; 1
	69	[76]	SELF     	5 5 -9	; "paintTo"
	70	[76]	MOVE     	7 1
	71	[77]	GETGLOBAL	8 -10	; math
	72	[77]	GETTABLE 	8 8 -11	; "floor"
	73	[77]	GETTABLE 	9 0 -2	; "dimen"
	74	[77]	GETTABLE 	9 9 -12	; "w"
	75	[77]	GETTABLE 	10 4 -12	; "w"
	76	[77]	SUB      	9 9 10
	77	[77]	DIV      	9 9 -13	; - 2
	78	[77]	CALL     	8 2 2
	79	[77]	ADD      	8 2 8
	80	[78]	GETGLOBAL	9 -10	; math
	81	[78]	GETTABLE 	9 9 -11	; "floor"
	82	[78]	GETTABLE 	10 0 -2	; "dimen"
	83	[78]	GETTABLE 	10 10 -15	; "h"
	84	[78]	GETTABLE 	11 4 -15	; "h"
	85	[78]	SUB      	10 10 11
	86	[78]	DIV      	10 10 -13	; - 2
	87	[78]	CALL     	9 2 2
	88	[78]	ADD      	9 3 9
	89	[76]	CALL     	5 5 1
	90	[78]	JMP      	7	; to 98
	91	[80]	GETTABLE 	4 0 -1	; 1
	92	[80]	SELF     	4 4 -9	; "paintTo"
	93	[80]	MOVE     	6 1
	94	[80]	MOVE     	7 2
	95	[80]	MOVE     	8 3
	96	[80]	TAILCALL 	4 5 0
	97	[80]	RETURN   	4 0
	98	[83]	RETURN   	0 1

function <./frontend/ui/widget/container/widgetcontainer.lua:85,94> (16 instructions, 64 bytes at 0x7fd980407d70)
2 params, 10 slots, 0 upvalues, 7 locals, 2 constants, 0 functions
	1	[87]	GETGLOBAL	2 -1	; ipairs
	2	[87]	MOVE     	3 0
	3	[87]	CALL     	2 2 4
	4	[87]	JMP      	7	; to 12
	5	[88]	SELF     	7 6 -2	; "handleEvent"
	6	[88]	MOVE     	9 1
	7	[88]	CALL     	7 3 2
	8	[88]	TEST     	7 0 0
	9	[88]	JMP      	2	; to 12
	10	[90]	LOADBOOL 	7 1 0
	11	[90]	RETURN   	7 2
	12	[87]	TFORLOOP 	2 2
	13	[91]	JMP      	-9	; to 5
	14	[93]	LOADBOOL 	2 0 0
	15	[93]	RETURN   	2 2
	16	[94]	RETURN   	0 1

function <./frontend/ui/widget/container/widgetcontainer.lua:105,112> (15 instructions, 60 bytes at 0x7fd980408590)
2 params, 5 slots, 1 upvalue, 2 locals, 2 constants, 0 functions
	1	[106]	SELF     	2 0 -1	; "propagateEvent"
	2	[106]	MOVE     	4 1
	3	[106]	CALL     	2 3 2
	4	[106]	TEST     	2 0 1
	5	[106]	JMP      	7	; to 13
	6	[108]	GETUPVAL 	2 0	; Widget
	7	[108]	GETTABLE 	2 2 -2	; "handleEvent"
	8	[108]	MOVE     	3 0
	9	[108]	MOVE     	4 1
	10	[108]	TAILCALL 	2 3 0
	11	[108]	RETURN   	2 0
	12	[108]	JMP      	2	; to 15
	13	[110]	LOADBOOL 	2 1 0
	14	[110]	RETURN   	2 2
	15	[112]	RETURN   	0 1

function <./frontend/ui/widget/container/widgetcontainer.lua:114,118> (12 instructions, 48 bytes at 0x7fd980407030)
1 param, 8 slots, 0 upvalues, 6 locals, 2 constants, 0 functions
	1	[115]	GETGLOBAL	1 -1	; ipairs
	2	[115]	MOVE     	2 0
	3	[115]	CALL     	1 2 4
	4	[115]	JMP      	5	; to 10
	5	[116]	GETTABLE 	6 5 -2	; "free"
	6	[116]	TEST     	6 0 0
	7	[116]	JMP      	2	; to 10
	8	[116]	SELF     	6 5 -2	; "free"
	9	[116]	CALL     	6 2 1
	10	[115]	TFORLOOP 	1 2
	11	[116]	JMP      	-7	; to 5
	12	[118]	RETURN   	0 1
