-- BYTECODE -- widget_progresswidget_spec.lua:3-7
0001    GGET     0   0      ; "require"
0002    KSTR     1   1      ; "commonrequire"
0003    CALL     0   1   2
0004    GGET     0   0      ; "require"
0005    KSTR     1   2      ; "ui/widget/progresswidget"
0006    CALL     0   2   2
0007    USETV    0   0      ; ProgressWidget
0008    GGET     0   0      ; "require"
0009    KSTR     1   3      ; "device"
0010    CALL     0   2   2
0011    TGETS    0   0   4  ; "screen"
0012    USETV    1   0      ; Screen
0013    RET0     0   1

-- BYTECODE -- widget_progresswidget_spec.lua:9-17
0001    UGET     0   0      ; ProgressWidget
0002    MOV      1   0
0003    TGETS    0   0   0  ; "new"
0004    TDUP     2   2
0005    UGET     3   1      ; Screen
0006    MOV      4   3
0007    TGETS    3   3   1  ; "scaleBySize"
0008    KSHORT   5 100
0009    CALL     3   2   3
0010    TSETS    3   2   3  ; "width"
0011    UGET     3   1      ; Screen
0012    MOV      4   3
0013    TGETS    3   3   1  ; "scaleBySize"
0014    KSHORT   5  50
0015    CALL     3   2   3
0016    TSETS    3   2   4  ; "height"
0017    TDUP     3   5
0018    TSETS    3   2   6  ; "ticks"
0019    CALL     0   2   3
0020    MOV      2   0
0021    TGETS    1   0   7  ; "paintTo"
0022    UGET     3   1      ; Screen
0023    TGETS    3   3   8  ; "bb"
0024    KSHORT   4   0
0025    KSHORT   5   0
0026    CALL     1   1   5
0027    RET0     0   1

-- BYTECODE -- widget_progresswidget_spec.lua:1-18
0001    KNIL     0   1
0002    GGET     2   0      ; "setup"
0003    FNEW     3   1      ; widget_progresswidget_spec.lua:3
0004    CALL     2   1   2
0005    GGET     2   2      ; "it"
0006    KSTR     3   3      ; "should not crash with nil self.last"
0007    FNEW     4   4      ; widget_progresswidget_spec.lua:9
0008    CALL     2   1   3
0009    UCLO     0 => 0010
0010 => RET0     0   1

-- BYTECODE -- widget_progresswidget_spec.lua:0-19
0001    GGET     0   0      ; "describe"
0002    KSTR     1   1      ; "ProgressWidget widget"
0003    FNEW     2   2      ; widget_progresswidget_spec.lua:1
0004    CALL     0   1   3
0005    RET0     0   1

