
main <./frontend/ui/widget/widget.lua:0,0> (15 instructions, 60 bytes at 0x7fb985c068c0)
0+ params, 3 slots, 0 upvalues, 2 locals, 6 constants, 4 functions
	1	[13]	GETGLOBAL	0 -1	; require
	2	[13]	LOADK    	1 -2	; "ui/widget/eventlistener"
	3	[13]	CALL     	0 2 2
	4	[17]	SELF     	1 0 -3	; "new"
	5	[17]	CALL     	1 2 2
	6	[32]	CLOSURE  	2 0	; 0x7fb985c06ab0
	7	[27]	SETTABLE 	1 -4 2	; "extend" -
	8	[50]	CLOSURE  	2 1	; 0x7fb985c06ef0
	9	[41]	SETTABLE 	1 -3 2	; "new" -
	10	[62]	CLOSURE  	2 2	; 0x7fb985c074d0
	11	[60]	SETTABLE 	1 -5 2	; "getSize" -
	12	[73]	CLOSURE  	2 3	; 0x7fb985c06bd0
	13	[72]	SETTABLE 	1 -6 2	; "paintTo" -
	14	[75]	RETURN   	1 2
	15	[75]	RETURN   	0 1

function <./frontend/ui/widget/widget.lua:27,32> (10 instructions, 40 bytes at 0x7fb985c06ab0)
2 params, 6 slots, 0 upvalues, 3 locals, 2 constants, 0 functions
	1	[28]	TESTSET  	2 1 1
	2	[28]	JMP      	1	; to 4
	3	[28]	NEWTABLE 	2 0 0
	4	[29]	GETGLOBAL	3 -1	; setmetatable
	5	[29]	MOVE     	4 2
	6	[29]	MOVE     	5 0
	7	[29]	CALL     	3 3 1
	8	[30]	SETTABLE 	0 -2 0	; "__index" -
	9	[31]	RETURN   	2 2
	10	[32]	RETURN   	0 1

function <./frontend/ui/widget/widget.lua:41,50> (16 instructions, 64 bytes at 0x7fb985c06ef0)
2 params, 5 slots, 0 upvalues, 2 locals, 3 constants, 0 functions
	1	[42]	SELF     	2 0 -1	; "extend"
	2	[42]	MOVE     	4 1
	3	[42]	CALL     	2 3 2
	4	[42]	MOVE     	1 2
	5	[47]	GETTABLE 	2 1 -2	; "_init"
	6	[47]	TEST     	2 0 0
	7	[47]	JMP      	2	; to 10
	8	[47]	SELF     	2 1 -2	; "_init"
	9	[47]	CALL     	2 2 1
	10	[48]	GETTABLE 	2 1 -3	; "init"
	11	[48]	TEST     	2 0 0
	12	[48]	JMP      	2	; to 15
	13	[48]	SELF     	2 1 -3	; "init"
	14	[48]	CALL     	2 2 1
	15	[49]	RETURN   	1 2
	16	[50]	RETURN   	0 1

function <./frontend/ui/widget/widget.lua:60,62> (3 instructions, 12 bytes at 0x7fb985c074d0)
1 param, 2 slots, 0 upvalues, 1 local, 1 constant, 0 functions
	1	[61]	GETTABLE 	1 0 -1	; "dimen"
	2	[61]	RETURN   	1 2
	3	[62]	RETURN   	0 1

function <./frontend/ui/widget/widget.lua:72,73> (1 instruction, 4 bytes at 0x7fb985c06bd0)
4 params, 4 slots, 0 upvalues, 4 locals, 0 constants, 0 functions
	1	[73]	RETURN   	0 1
