-- BYTECODE -- widget.lua:27-32
0001    ISTC     2   1
0002    JMP      2 => 0004
0003    TNEW     2   0
0004 => GGET     3   0      ; "setmetatable"
0005    MOV      4   2
0006    MOV      5   0
0007    CALL     3   1   3
0008    TSETS    0   0   1  ; "__index"
0009    RET1     2   2

-- BYTECODE -- widget.lua:41-50
0001    MOV      3   0
0002    TGETS    2   0   0  ; "extend"
0003    MOV      4   1
0004    CALL     2   2   3
0005    MOV      1   2
0006    TGETS    2   1   1  ; "_init"
0007    ISF          2
0008    JMP      3 => 0012
0009    MOV      3   1
0010    TGETS    2   1   1  ; "_init"
0011    CALL     2   1   2
0012 => TGETS    2   1   2  ; "init"
0013    ISF          2
0014    JMP      3 => 0018
0015    MOV      3   1
0016    TGETS    2   1   2  ; "init"
0017    CALL     2   1   2
0018 => RET1     1   2

-- BYTECODE -- widget.lua:60-62
0001    TGETS    1   0   0  ; "dimen"
0002    RET1     1   2

-- BYTECODE -- widget.lua:72-73
0001    RET0     0   1

-- BYTECODE -- widget.lua:0-76
0001    GGET     0   0      ; "require"
0002    KSTR     1   1      ; "ui/widget/eventlistener"
0003    CALL     0   2   2
0004    MOV      2   0
0005    TGETS    1   0   2  ; "new"
0006    CALL     1   2   2
0007    FNEW     2   4      ; widget.lua:27
0008    TSETS    2   1   3  ; "extend"
0009    FNEW     2   5      ; widget.lua:41
0010    TSETS    2   1   2  ; "new"
0011    FNEW     2   7      ; widget.lua:60
0012    TSETS    2   1   6  ; "getSize"
0013    FNEW     2   9      ; widget.lua:72
0014    TSETS    2   1   8  ; "paintTo"
0015    UCLO     0 => 0016
0016 => RET1     1   2

