-- BYTECODE -- widgetcontainer.lua:26-39
0001    TGETS    1   0   0  ; "dimen"
0002    ISF          1
0003    JMP      2 => 0033
0004    TGETS    1   0   1  ; "initDimen"
0005    ISF          1
0006    JMP      2 => 0011
0007    MOV      2   0
0008    TGETS    1   0   1  ; "initDimen"
0009    CALL     1   1   2
0010    JMP      1 => 0033
0011 => TGETS    1   0   0  ; "dimen"
0012    TGETS    1   1   2  ; "w"
0013    IST          1
0014    JMP      1 => 0022
0015    TGETS    1   0   0  ; "dimen"
0016    TGETB    2   0   1
0017    MOV      3   2
0018    TGETS    2   2   3  ; "getSize"
0019    CALL     2   2   2
0020    TGETS    2   2   2  ; "w"
0021    TSETS    2   1   2  ; "w"
0022 => TGETS    1   0   0  ; "dimen"
0023    TGETS    1   1   4  ; "h"
0024    IST          1
0025    JMP      1 => 0033
0026    TGETS    1   0   0  ; "dimen"
0027    TGETB    2   0   1
0028    MOV      3   2
0029    TGETS    2   2   3  ; "getSize"
0030    CALL     2   2   2
0031    TGETS    2   2   4  ; "h"
0032    TSETS    2   1   4  ; "h"
0033 => RET0     0   1

-- BYTECODE -- widgetcontainer.lua:41-51
0001    TGETS    1   0   0  ; "dimen"
0002    ISF          1
0003    JMP      2 => 0007
0004    TGETS    1   0   0  ; "dimen"
0005    RET1     1   2
0006    JMP      1 => 0020
0007 => TGETB    1   0   1
0008    ISF          1
0009    JMP      2 => 0015
0010    TGETB    1   0   1
0011    MOV      2   1
0012    TGETS    1   1   1  ; "getSize"
0013    CALLT    1   2
0014    JMP      1 => 0020
0015 => UGET     1   0      ; Geom
0016    MOV      2   1
0017    TGETS    1   1   2  ; "new"
0018    TDUP     3   3
0019    CALLT    1   3
0020 => RET0     0   1

-- BYTECODE -- widgetcontainer.lua:56-58
0001 => GGET     1   0      ; "table"
0002    TGETS    1   1   1  ; "remove"
0003    MOV      2   0
0004    CALL     1   2   2
0005    ISF          1
0006    JMP      2 => 0009
0007    LOOP     1 => 0009
0008    JMP      1 => 0001
0009 => RET0     0   1

-- BYTECODE -- widgetcontainer.lua:60-83
0001    TGETB    4   0   1
0002    ISF          4
0003    JMP      5 => 0104
0004    TGETS    4   0   0  ; "dimen"
0005    TGETS    4   4   1  ; "x"
0006    IST          4
0007    JMP      5 => 0009
0008    KSHORT   4   0
0009 => ADDVV    2   2   4
0010    TGETS    4   0   0  ; "dimen"
0011    TGETS    4   4   2  ; "y"
0012    IST          4
0013    JMP      5 => 0015
0014    KSHORT   4   0
0015 => ADDVV    3   3   4
0016    TGETS    4   0   3  ; "align"
0017    ISNES    4   4      ; "top"
0018    JMP      4 => 0039
0019    TGETB    4   0   1
0020    MOV      5   4
0021    TGETS    4   4   5  ; "getSize"
0022    CALL     4   2   2
0023    TGETB    5   0   1
0024    MOV      6   5
0025    TGETS    5   5   6  ; "paintTo"
0026    MOV      7   1
0027    GGET     8   7      ; "math"
0028    TGETS    8   8   8  ; "floor"
0029    TGETS    9   0   0  ; "dimen"
0030    TGETS    9   9   9  ; "w"
0031    TGETS   10   4   9  ; "w"
0032    SUBVV    9   9  10
0033    DIVVN    9   9   0  ; 2
0034    CALL     8   2   2
0035    ADDVV    8   2   8
0036    MOV      9   3
0037    CALL     5   1   5
0038    JMP      4 => 0104
0039 => TGETS    4   0   3  ; "align"
0040    ISNES    4  10      ; "bottom"
0041    JMP      4 => 0066
0042    TGETB    4   0   1
0043    MOV      5   4
0044    TGETS    4   4   5  ; "getSize"
0045    CALL     4   2   2
0046    TGETB    5   0   1
0047    MOV      6   5
0048    TGETS    5   5   6  ; "paintTo"
0049    MOV      7   1
0050    GGET     8   7      ; "math"
0051    TGETS    8   8   8  ; "floor"
0052    TGETS    9   0   0  ; "dimen"
0053    TGETS    9   9   9  ; "w"
0054    TGETS   10   4   9  ; "w"
0055    SUBVV    9   9  10
0056    DIVVN    9   9   0  ; 2
0057    CALL     8   2   2
0058    ADDVV    8   2   8
0059    TGETS    9   0   0  ; "dimen"
0060    TGETS    9   9  11  ; "h"
0061    TGETS   10   4  11  ; "h"
0062    SUBVV    9   9  10
0063    ADDVV    9   3   9
0064    CALL     5   1   5
0065    JMP      4 => 0104
0066 => TGETS    4   0   3  ; "align"
0067    ISNES    4  12      ; "center"
0068    JMP      4 => 0097
0069    TGETB    4   0   1
0070    MOV      5   4
0071    TGETS    4   4   5  ; "getSize"
0072    CALL     4   2   2
0073    TGETB    5   0   1
0074    MOV      6   5
0075    TGETS    5   5   6  ; "paintTo"
0076    MOV      7   1
0077    GGET     8   7      ; "math"
0078    TGETS    8   8   8  ; "floor"
0079    TGETS    9   0   0  ; "dimen"
0080    TGETS    9   9   9  ; "w"
0081    TGETS   10   4   9  ; "w"
0082    SUBVV    9   9  10
0083    DIVVN    9   9   0  ; 2
0084    CALL     8   2   2
0085    ADDVV    8   2   8
0086    GGET     9   7      ; "math"
0087    TGETS    9   9   8  ; "floor"
0088    TGETS   10   0   0  ; "dimen"
0089    TGETS   10  10  11  ; "h"
0090    TGETS   11   4  11  ; "h"
0091    SUBVV   10  10  11
0092    DIVVN   10  10   0  ; 2
0093    CALL     9   2   2
0094    ADDVV    9   3   9
0095    CALL     5   1   5
0096    JMP      4 => 0104
0097 => TGETB    4   0   1
0098    MOV      5   4
0099    TGETS    4   4   6  ; "paintTo"
0100    MOV      6   1
0101    MOV      7   2
0102    MOV      8   3
0103    CALLT    4   5
0104 => RET0     0   1

-- BYTECODE -- widgetcontainer.lua:85-94
0001    GGET     2   0      ; "ipairs"
0002    MOV      3   0
0003    CALL     2   4   2
0004    JMP      5 => 0013
0005 => MOV      8   6
0006    TGETS    7   6   1  ; "handleEvent"
0007    MOV      9   1
0008    CALL     7   2   3
0009    ISF          7
0010    JMP      8 => 0013
0011    KPRI     7   2
0012    RET1     7   2
0013 => ITERC    5   3   3
0014    ITERL    5 => 0005
0015    KPRI     2   1
0016    RET1     2   2

-- BYTECODE -- widgetcontainer.lua:105-112
0001    MOV      3   0
0002    TGETS    2   0   0  ; "propagateEvent"
0003    MOV      4   1
0004    CALL     2   2   3
0005    IST          2
0006    JMP      2 => 0013
0007    UGET     2   0      ; Widget
0008    TGETS    2   2   1  ; "handleEvent"
0009    MOV      3   0
0010    MOV      4   1
0011    CALLT    2   3
0012    JMP      2 => 0015
0013 => KPRI     2   2
0014    RET1     2   2
0015 => RET0     0   1

-- BYTECODE -- widgetcontainer.lua:114-118
0001    GGET     1   0      ; "ipairs"
0002    MOV      2   0
0003    CALL     1   4   2
0004    JMP      4 => 0011
0005 => TGETS    6   5   1  ; "free"
0006    ISF          6
0007    JMP      7 => 0011
0008    MOV      7   5
0009    TGETS    6   5   1  ; "free"
0010    CALL     6   1   2
0011 => ITERC    4   3   3
0012    ITERL    4 => 0005
0013    RET0     0   1

-- BYTECODE -- widgetcontainer.lua:0-121
0001    GGET     0   0      ; "require"
0002    KSTR     1   1      ; "ui/geometry"
0003    CALL     0   2   2
0004    GGET     1   0      ; "require"
0005    KSTR     2   2      ; "ui/widget/widget"
0006    CALL     1   2   2
0007    GGET     2   0      ; "require"
0008    KSTR     3   3      ; "device"
0009    CALL     2   2   2
0010    TGETS    3   2   4  ; "should_restrict_JIT"
0011    ISF          3
0012    JMP      4 => 0020
0013    GGET     3   0      ; "require"
0014    KSTR     4   5      ; "jit"
0015    CALL     3   2   2
0016    TGETS    3   3   6  ; "off"
0017    KPRI     4   2
0018    KPRI     5   2
0019    CALL     3   1   3
0020 => MOV      4   1
0021    TGETS    3   1   7  ; "new"
0022    CALL     3   2   2
0023    FNEW     4   9      ; widgetcontainer.lua:26
0024    TSETS    4   3   8  ; "init"
0025    FNEW     4  11      ; widgetcontainer.lua:41
0026    TSETS    4   3  10  ; "getSize"
0027    FNEW     4  13      ; widgetcontainer.lua:56
0028    TSETS    4   3  12  ; "clear"
0029    FNEW     4  15      ; widgetcontainer.lua:60
0030    TSETS    4   3  14  ; "paintTo"
0031    FNEW     4  17      ; widgetcontainer.lua:85
0032    TSETS    4   3  16  ; "propagateEvent"
0033    FNEW     4  19      ; widgetcontainer.lua:105
0034    TSETS    4   3  18  ; "handleEvent"
0035    FNEW     4  21      ; widgetcontainer.lua:114
0036    TSETS    4   3  20  ; "free"
0037    UCLO     0 => 0038
0038 => RET1     3   2

