
main <./spec/unit/wikipedia_spec.lua:0,0> (5 instructions, 20 bytes at 0x7ff05fc068c0)
0+ params, 3 slots, 0 upvalues, 0 locals, 2 constants, 1 function
	1	[1]	GETGLOBAL	0 -1	; describe
	2	[1]	LOADK    	1 -2	; "Wikipedia module"
	3	[14]	CLOSURE  	2 0	; 0x7ff05fc06b60
	4	[1]	CALL     	0 3 1
	5	[14]	RETURN   	0 1

function <./spec/unit/wikipedia_spec.lua:1,14> (10 instructions, 40 bytes at 0x7ff05fc06b60)
0 params, 4 slots, 0 upvalues, 1 local, 3 constants, 2 functions
	1	[3]	GETGLOBAL	1 -1	; setup
	2	[6]	CLOSURE  	2 0	; 0x7ff05fc06d90
	3	[6]	MOVE     	0 0
	4	[3]	CALL     	1 2 1
	5	[8]	GETGLOBAL	1 -2	; it
	6	[8]	LOADK    	2 -3	; "should return Wikipedia server"
	7	[13]	CLOSURE  	3 1	; 0x7ff05fc06c70
	8	[13]	MOVE     	0 0
	9	[8]	CALL     	1 3 1
	10	[14]	RETURN   	0 1

function <./spec/unit/wikipedia_spec.lua:3,6> (8 instructions, 32 bytes at 0x7ff05fc06d90)
0 params, 2 slots, 1 upvalue, 0 locals, 3 constants, 0 functions
	1	[4]	GETGLOBAL	0 -1	; require
	2	[4]	LOADK    	1 -2	; "commonrequire"
	3	[4]	CALL     	0 2 1
	4	[5]	GETGLOBAL	0 -1	; require
	5	[5]	LOADK    	1 -3	; "ui/wikipedia"
	6	[5]	CALL     	0 2 2
	7	[5]	SETUPVAL 	0 0	; Wikipedia
	8	[6]	RETURN   	0 1

function <./spec/unit/wikipedia_spec.lua:8,13> (20 instructions, 80 bytes at 0x7ff05fc06c70)
0 params, 7 slots, 1 upvalue, 2 locals, 7 constants, 0 functions
	1	[9]	LOADK    	0 -1	; "https://en.wikipedia.org"
	2	[10]	LOADK    	1 -2	; "https://nl.wikipedia.org"
	3	[11]	GETGLOBAL	2 -3	; assert
	4	[11]	GETTABLE 	2 2 -4	; "is"
	5	[11]	GETTABLE 	2 2 -5	; "same"
	6	[11]	MOVE     	3 0
	7	[11]	GETUPVAL 	4 0	; Wikipedia
	8	[11]	SELF     	4 4 -6	; "getWikiServer"
	9	[11]	CALL     	4 2 0
	10	[11]	CALL     	2 0 1
	11	[12]	GETGLOBAL	2 -3	; assert
	12	[12]	GETTABLE 	2 2 -4	; "is"
	13	[12]	GETTABLE 	2 2 -5	; "same"
	14	[12]	MOVE     	3 1
	15	[12]	GETUPVAL 	4 0	; Wikipedia
	16	[12]	SELF     	4 4 -6	; "getWikiServer"
	17	[12]	LOADK    	6 -7	; "nl"
	18	[12]	CALL     	4 3 0
	19	[12]	CALL     	2 0 1
	20	[13]	RETURN   	0 1
