-- BYTECODE -- zyremessagequeue.lua:12-23
0001    UGET     1   0      ; zyre
0002    TGETS    1   1   1  ; "zyre_new"
0003    CALL     1   2   1
0004    TSETS    1   0   0  ; "node"
0005    UGET     1   1      ; czmq
0006    TGETS    1   1   3  ; "zpoller_new"
0007    UGET     2   0      ; zyre
0008    TGETS    2   2   4  ; "zyre_socket"
0009    TGETS    3   0   0  ; "node"
0010    CALL     2   2   2
0011    KPRI     3   0
0012    CALL     1   2   3
0013    TSETS    1   0   2  ; "poller"
0014    GGET     1   5      ; "pairs"
0015    TGETS    2   0   6  ; "header"
0016    CALL     1   4   2
0017    ISNEXT   4 => 0024
0018 => UGET     6   0      ; zyre
0019    TGETS    6   6   7  ; "zyre_set_header"
0020    TGETS    7   0   0  ; "node"
0021    MOV      8   4
0022    MOV      9   5
0023    CALL     6   1   4
0024 => ITERN    4   3   3
0025    ITERL    4 => 0018
0026    UGET     1   0      ; zyre
0027    TGETS    1   1   8  ; "zyre_set_interface"
0028    TGETS    2   0   0  ; "node"
0029    KSTR     3   9      ; "wlan0"
0030    CALL     1   1   3
0031    UGET     1   0      ; zyre
0032    TGETS    1   1  10  ; "zyre_start"
0033    TGETS    2   0   0  ; "node"
0034    CALL     1   1   2
0035    UGET     1   0      ; zyre
0036    TGETS    1   1  11  ; "zyre_join"
0037    TGETS    2   0   0  ; "node"
0038    KSTR     3  12      ; "GLOBAL"
0039    CALL     1   1   3
0040    RET0     0   1

-- BYTECODE -- zyremessagequeue.lua:25-33
0001    TGETS    1   0   0  ; "node"
0002    ISEQP    1   0
0003    JMP      1 => 0016
0004    UGET     1   0      ; zyre
0005    TGETS    1   1   1  ; "zyre_stop"
0006    TGETS    2   0   0  ; "node"
0007    CALL     1   1   2
0008    UGET     1   0      ; zyre
0009    TGETS    1   1   2  ; "zyre_destroy"
0010    UGET     2   1      ; ffi
0011    TGETS    2   2   3  ; "new"
0012    KSTR     3   4      ; "zyre_t *[1]"
0013    TGETS    4   0   0  ; "node"
0014    CALL     2   0   3
0015    CALLM    1   1   0
0016 => TGETS    1   0   5  ; "poller"
0017    ISEQP    1   0
0018    JMP      1 => 0027
0019    UGET     1   2      ; czmq
0020    TGETS    1   1   6  ; "zpoller_destroy"
0021    UGET     2   1      ; ffi
0022    TGETS    2   2   3  ; "new"
0023    KSTR     3   7      ; "zpoller_t *[1]"
0024    TGETS    4   0   5  ; "poller"
0025    CALL     2   0   3
0026    CALLM    1   1   0
0027 => RET0     0   1

-- BYTECODE -- zyremessagequeue.lua:35-43
0001    UGET     1   0      ; czmq
0002    TGETS    1   1   0  ; "zpoller_wait"
0003    TGETS    2   0   1  ; "poller"
0004    KSHORT   3   0
0005    CALL     1   2   3
0006    ISEQP    1   0
0007    JMP      1 => 0019
0008    UGET     1   1      ; zyre
0009    TGETS    1   1   2  ; "zyre_recv"
0010    TGETS    2   0   3  ; "node"
0011    CALL     1   2   2
0012    ISEQP    1   0
0013    JMP      2 => 0019
0014    GGET     2   4      ; "table"
0015    TGETS    2   2   5  ; "insert"
0016    TGETS    3   0   6  ; "messages"
0017    MOV      4   1
0018    CALL     2   1   3
0019 => MOV      2   0
0020    TGETS    1   0   7  ; "handleZMsgs"
0021    TGETS    3   0   6  ; "messages"
0022    CALLT    1   3

-- BYTECODE -- zyremessagequeue.lua:0-46
0001    GGET     0   0      ; "require"
0002    KSTR     1   1      ; "ffi"
0003    CALL     0   2   2
0004    GGET     1   0      ; "require"
0005    KSTR     2   2      ; "ui/message/messagequeue"
0006    CALL     1   2   2
0007    GGET     2   0      ; "require"
0008    KSTR     3   3      ; "ffi/zeromq_h"
0009    CALL     2   2   2
0010    TGETS    3   0   4  ; "load"
0011    KSTR     4   5      ; "libs/libczmq.so.1"
0012    CALL     3   2   2
0013    TGETS    4   0   4  ; "load"
0014    KSTR     5   6      ; "libs/libzyre.so.1"
0015    CALL     4   2   2
0016    MOV      6   1
0017    TGETS    5   1   7  ; "new"
0018    TDUP     7   8
0019    TNEW     8   0
0020    TSETS    8   7   9  ; "header"
0021    CALL     5   2   3
0022    FNEW     6  11      ; zyremessagequeue.lua:12
0023    TSETS    6   5  10  ; "start"
0024    FNEW     6  13      ; zyremessagequeue.lua:25
0025    TSETS    6   5  12  ; "stop"
0026    FNEW     6  15      ; zyremessagequeue.lua:35
0027    TSETS    6   5  14  ; "waitEvent"
0028    UCLO     0 => 0029
0029 => RET1     5   2

